{
  "type": "Feature",
  "properties": {
    "addr:full":"16413 N Glade Rd Mesa WA 99343",
    "addr:housenumber":"16413",
    "addr:postcode":"99343",
    "addr:street":"N Glade Rd",
    "iso:country":"US",
    "sg:address":"16413 N Glade Rd",
    "sg:city":"Mesa",
    "sg:classifiers":[
        {
            "category":"Building & Trades",
            "subcategory":"Cleaning & Sanitation",
            "type":"Services"
        }
    ],
    "sg:phone":"+1 509 266 4278",
    "sg:postcode":"99343",
    "sg:province":"WA",
    "sg:tags":[
        "maintenance"
    ],
    "wof:name":"Susan C Bailie",
    "wof:placetype":"venue"
},
  "geometry": {"coordinates":[-119.13215099999999,46.488669],"type":"Point"}
}