{
  "type": "Feature",
  "properties": {
    "addr:full":"15 S 3rd Ave Walla Walla WA 99362",
    "addr:housenumber":"15",
    "addr:postcode":"99362",
    "addr:street":"S 3Rd Ave",
    "iso:country":"US",
    "sg:address":"15 S 3rd Ave",
    "sg:city":"Walla Walla",
    "sg:classifiers":[
        {
            "category":"Local Transit",
            "type":"Transportation"
        }
    ],
    "sg:phone":"+1 509 527 3744",
    "sg:postcode":"99362",
    "sg:province":"WA",
    "sg:tags":[
        "ambulance"
    ],
    "wof:name":"Walla Walla Ambulance",
    "wof:placetype":"venue"
},
  "geometry": {"coordinates":[-118.340532,46.066112],"type":"Point"}
}