{
  "type": "Feature",
  "properties": {
    "addr:full":"3000 Landerholm Cir SE Bellevue WA 98007",
    "addr:housenumber":"3000",
    "addr:postcode":"98007",
    "addr:street":"Landerholm Cir Se",
    "iso:country":"US",
    "sg:address":"3000 Landerholm Cir SE",
    "sg:city":"Bellevue",
    "sg:classifiers":[
        {
            "category":"Education",
            "subcategory":"College",
            "type":"Public Place"
        }
    ],
    "sg:phone":"+1 425 564 5073",
    "sg:postcode":"98007",
    "sg:province":"WA",
    "wof:name":"Bcc Tech Services",
    "wof:placetype":"venue"
},
  "geometry": {"coordinates":[-122.143084,47.585376],"type":"Point"}
}