{
  "type": "Feature",
  "properties": {
    "addr:full":"3898 Old Monitor Rd Cashmere WA 98815",
    "addr:housenumber":"3898",
    "addr:postcode":"98815",
    "addr:street":"Old Monitor Rd",
    "iso:country":"US",
    "sg:address":"3898 Old Monitor Rd",
    "sg:city":"Cashmere",
    "sg:classifiers":[
        {
            "category":"Bakery",
            "type":"Food & Drink"
        }
    ],
    "sg:phone":"+1 509 782 4360",
    "sg:postcode":"98815",
    "sg:province":"WA",
    "wof:name":"Anjou Bakery",
    "wof:placetype":"venue"
},
  "geometry": {"coordinates":[-120.420998,47.4888],"type":"Point"}
}