{
  "type": "Feature",
  "properties": {
    "addr:full":"7191 E Stanley Ln Port Orchard WA 98366",
    "addr:housenumber":"7191",
    "addr:postcode":"98366",
    "addr:street":"E Stanley Ln",
    "iso:country":"US",
    "sg:address":"7191 E Stanley Ln",
    "sg:city":"Port Orchard",
    "sg:classifiers":[
        {
            "category":"Real Estate",
            "subcategory":"Real Estate Agent",
            "type":"Services"
        }
    ],
    "sg:phone":"+1 360 871 2019",
    "sg:postcode":"98366",
    "sg:province":"WA",
    "wof:name":"Nartea Rentals",
    "wof:placetype":"venue"
},
  "geometry": {"coordinates":[-122.557293,47.550325],"type":"Point"}
}