{
  "type": "Feature",
  "properties": {
    "addr:full":"6430 Tacoma Mall Blvd Tacoma WA 98409",
    "addr:housenumber":"6430",
    "addr:postcode":"98409",
    "addr:street":"Tacoma Mall Blvd",
    "iso:country":"US",
    "sg:address":"6430 Tacoma Mall Blvd",
    "sg:city":"Tacoma",
    "sg:classifiers":[
        {
            "category":"Education",
            "subcategory":"School",
            "type":"Public Place"
        }
    ],
    "sg:phone":"+1 253 471 0900",
    "sg:postcode":"98409",
    "sg:province":"WA",
    "wof:name":"Aster Technology Institute LLC",
    "wof:placetype":"venue"
},
  "geometry": {"coordinates":[-122.463092,47.197687],"type":"Point"}
}