{
  "type": "Feature",
  "properties": {
    "addr:full":"29501 R SW Mattawa WA 99349",
    "addr:housenumber":"29501",
    "addr:postcode":"99349",
    "addr:street":"R Sw",
    "iso:country":"US",
    "sg:address":"29501 R SW",
    "sg:city":"Mattawa",
    "sg:classifiers":[
        {
            "category":"Farming",
            "subcategory":"Orchard",
            "type":"Manufacturing & Wholesale Goods"
        }
    ],
    "sg:phone":"+1 509 932 4862",
    "sg:postcode":"99349",
    "sg:province":"WA",
    "sg:tags":[
        "fruit",
        "tree"
    ],
    "wof:name":"David Paul Allen",
    "wof:placetype":"venue"
},
  "geometry": {"coordinates":[-119.87424799999999,46.661664],"type":"Point"}
}