{
  "type": "Feature",
  "properties": {
    "iso:country":"US",
    "sg:address":"8425 NE 14th Ln",
    "sg:city":"Vancouver",
    "sg:classifiers":[
        {
            "category":"Building & Trades",
            "subcategory":"Cleaning & Sanitation",
            "type":"Services"
        }
    ],
    "sg:phone":"+1 360 882 0160",
    "sg:postcode":"98664",
    "sg:province":"WA",
    "sg:tags":[
        "maintenance"
    ],
    "wof:name":"Ilia D Bojilov",
    "wof:placetype":"venue"
},
  "geometry": {"coordinates":[-122.586913,45.632502],"type":"Point"}
}