{
  "type": "Feature",
  "properties": {
    "iso:country":"US",
    "sg:address":"2500 Cadet Way",
    "sg:city":"Everett",
    "sg:classifiers":[
        {
            "category":"Education",
            "subcategory":"School",
            "type":"Public Place"
        }
    ],
    "sg:phone":"+1 425 338 5130",
    "sg:postcode":"98208",
    "sg:province":"WA",
    "wof:name":"Jefferson Elementary School",
    "wof:placetype":"venue"
},
  "geometry": {"coordinates":[-122.197892,47.917647],"type":"Point"}
}