{
  "type": "Feature",
  "properties": {
    "addr:full":"196 E Sussex Ave Tenino WA 98589",
    "addr:housenumber":"196",
    "addr:postcode":"98589",
    "addr:street":"E Sussex Ave",
    "iso:country":"US",
    "sg:address":"196 E Sussex Ave",
    "sg:city":"Tenino",
    "sg:classifiers":[
        {
            "category":"Shopping",
            "subcategory":"Pharmacy",
            "type":"Retail Goods"
        }
    ],
    "sg:phone":"+1 360 264 2575",
    "sg:postcode":"98589",
    "sg:province":"WA",
    "wof:name":"Hedden's Pharmacy",
    "wof:placetype":"venue"
},
  "geometry": {"coordinates":[-122.850623,46.857793],"type":"Point"}
}