{
  "type": "Feature",
  "properties": {
    "addr:full":"16728 Promise Ln SW Rochester WA 98579",
    "addr:housenumber":"16728",
    "addr:postcode":"98579",
    "addr:street":"Promise Ln Sw",
    "iso:country":"US",
    "sg:address":"16728 Promise Ln SW",
    "sg:city":"Rochester",
    "sg:classifiers":[
        {
            "category":"Building & Trades",
            "subcategory":"Plumbing",
            "type":"Services"
        }
    ],
    "sg:phone":"+1 360 273 6826",
    "sg:postcode":"98579",
    "sg:province":"WA",
    "sg:tags":[
        "home",
        "installer",
        "tank",
        "septic",
        "repair"
    ],
    "wof:name":"Bollinger Kelly",
    "wof:placetype":"venue"
},
  "geometry": {"coordinates":[-123.041844,46.838179],"type":"Point"}
}