{
  "type": "Feature",
  "properties": {
    "addr:full":"2849 Fir St Longview WA 98632",
    "addr:housenumber":"2849",
    "addr:postcode":"98632",
    "addr:street":"Fir St",
    "iso:country":"US",
    "sg:address":"2849 Fir St",
    "sg:city":"Longview",
    "sg:classifiers":[
        {
            "category":"Professional",
            "subcategory":"Business Services",
            "type":"Services"
        }
    ],
    "sg:phone":"+1 360 423 7768",
    "sg:postcode":"98632",
    "sg:province":"WA",
    "wof:name":"Calhoun Diving",
    "wof:placetype":"venue"
},
  "geometry": {"coordinates":[-122.96126,46.134612],"type":"Point"}
}