{
  "type": "Feature",
  "properties": {
    "addr:full":"3115 N Ferdinand St Tacoma WA 98407",
    "addr:housenumber":"3115",
    "addr:postcode":"98407",
    "addr:street":"N Ferdinand St",
    "iso:country":"US",
    "sg:address":"3115 N Ferdinand St",
    "sg:city":"Tacoma",
    "sg:classifiers":[
        {
            "category":"Retail",
            "subcategory":"Portrait Studio",
            "type":"Services"
        }
    ],
    "sg:phone":"+1 253 759 7477",
    "sg:postcode":"98407",
    "sg:province":"WA",
    "sg:tags":[
        "photo"
    ],
    "wof:name":"Deanna Kilga",
    "wof:placetype":"venue"
},
  "geometry": {"coordinates":[-122.502441,47.277652],"type":"Point"}
}