{
  "type": "Feature",
  "properties": {
    "addr:full":"310 Cascade Pl Burlington WA 98233",
    "addr:housenumber":"310",
    "addr:postcode":"98233",
    "addr:street":"Cascade Pl",
    "iso:country":"US",
    "sg:address":"310 Cascade Pl",
    "sg:city":"Burlington",
    "sg:classifiers":[
        {
            "category":"Real Estate",
            "subcategory":"Real Estate Operator",
            "type":"Services"
        }
    ],
    "sg:phone":"+1 360 757 1048",
    "sg:postcode":"98233",
    "sg:province":"WA",
    "sg:tags":[
        "apartment"
    ],
    "wof:name":"Cascade Meadows Apartments",
    "wof:placetype":"venue"
},
  "geometry": {"coordinates":[-122.33463999999999,48.459967],"type":"Point"}
}