{
  "type": "Feature",
  "properties": {
    "iso:country":"US",
    "sg:address":"6402 S 196th St",
    "sg:city":"Kent",
    "sg:classifiers":[
        {
            "category":"Professional",
            "subcategory":"Advertising",
            "type":"Services"
        }
    ],
    "sg:phone":"+1 253 872 7211",
    "sg:postcode":"98032",
    "sg:province":"WA",
    "sg:tags":[
        "mail",
        "direct"
    ],
    "wof:name":"Kc Mailing Services Inc",
    "wof:placetype":"venue"
},
  "geometry": {"coordinates":[-122.256293,47.426811],"type":"Point"}
}