{
  "type": "Feature",
  "properties": {
    "addr:full":"2779 Strawberry Point Rd Oak Harbor WA 98277",
    "addr:housenumber":"2779",
    "addr:postcode":"98277",
    "addr:street":"Strawberry Point Rd",
    "iso:country":"US",
    "sg:address":"2779 Strawberry Point Rd",
    "sg:city":"Oak Harbor",
    "sg:classifiers":[
        {
            "category":"Retail",
            "subcategory":"Auto Repair",
            "type":"Services"
        }
    ],
    "sg:phone":"+1 360 675 6250",
    "sg:postcode":"98277",
    "sg:province":"WA",
    "sg:tags":[
        "general"
    ],
    "wof:name":"Tonys Repair Service",
    "wof:placetype":"venue"
},
  "geometry": {"coordinates":[-122.51454099999999,48.315051],"type":"Point"}
}