{
  "type": "Feature",
  "properties": {
    "addr:full":"215 Melody Ln Wenatchee WA 98801",
    "addr:housenumber":"215",
    "addr:postcode":"98801",
    "addr:street":"Melody Ln",
    "iso:country":"US",
    "sg:address":"215 Melody Ln",
    "sg:city":"Wenatchee",
    "sg:classifiers":[
        {
            "category":"Professional",
            "type":"Services"
        }
    ],
    "sg:phone":"+1 509 663 1487",
    "sg:postcode":"98801",
    "sg:province":"WA",
    "sg:tags":[
        "establishment"
    ],
    "wof:name":"DNA",
    "wof:placetype":"venue"
},
  "geometry": {"coordinates":[-120.338719,47.469493],"type":"Point"}
}