{
  "type": "Feature",
  "properties": {
    "addr:full":"4326 Bridgeport Way W Tacoma WA 98466",
    "addr:housenumber":"4326",
    "addr:postcode":"98466",
    "addr:street":"Bridgeport Way W",
    "iso:country":"US",
    "sg:address":"4326 Bridgeport Way W",
    "sg:city":"Tacoma",
    "sg:classifiers":[
        {
            "category":"Restaurant",
            "type":"Food & Drink"
        },
        {
            "category":"Ice Cream",
            "type":"Food & Drink"
        }
    ],
    "sg:menulink":"http://www.allmenus.com/wa/tacoma/242902-baskin-robbins/menu/",
    "sg:phone":"+1 253 565 6078",
    "sg:postcode":"98466",
    "sg:province":"WA",
    "sg:tags":[
        "american",
        "ice",
        "cream"
    ],
    "wof:name":"Baskin-Robbins",
    "wof:placetype":"venue"
},
  "geometry": {"coordinates":[-122.537173,47.217544],"type":"Point"}
}