{
  "type": "Feature",
  "properties": {
    "addr:full":"1350 Cole St Enumclaw WA 98022",
    "addr:housenumber":"1350",
    "addr:postcode":"98022",
    "addr:street":"Cole St",
    "iso:country":"US",
    "sg:address":"1350 Cole St",
    "sg:city":"Enumclaw",
    "sg:classifiers":[
        {
            "category":"Social Services",
            "type":"Services"
        }
    ],
    "sg:phone":"+1 360 825 4741",
    "sg:postcode":"98022",
    "sg:province":"WA",
    "sg:tags":[
        "executive"
    ],
    "wof:name":"Enumclaw City",
    "wof:placetype":"venue"
},
  "geometry": {"coordinates":[-121.99191399999999,47.201227],"type":"Point"}
}