{
  "type": "Feature",
  "properties": {
    "addr:full":"13354 SE 232nd Pl Kent WA 98042",
    "addr:postcode":"13354;98042",
    "addr:street":"Se 232Nd Pl",
    "iso:country":"US",
    "sg:address":"13354 SE 232nd Pl",
    "sg:city":"Kent",
    "sg:classifiers":[
        {
            "category":"Wholesale",
            "subcategory":"Machinery & Supplies",
            "type":"Manufacturing & Wholesale Goods"
        }
    ],
    "sg:phone":"+1 253 639 0821",
    "sg:postcode":"98042",
    "sg:province":"WA",
    "sg:tags":[
        "equipment",
        "establishment"
    ],
    "wof:name":"Alpha Omega Vending",
    "wof:placetype":"venue"
},
  "geometry": {"coordinates":[-122.162052,47.393863],"type":"Point"}
}