{
  "type": "Feature",
  "properties": {
    "addr:full":"25914 NE 32nd St Redmond WA 98053",
    "addr:housenumber":"25914",
    "addr:postcode":"98053",
    "addr:street":"Ne 32Nd St",
    "iso:country":"US",
    "sg:address":"25914 NE 32nd St",
    "sg:city":"Redmond",
    "sg:classifiers":[
        {
            "category":"Professional",
            "subcategory":"Computer Services",
            "type":"Services"
        }
    ],
    "sg:phone":"+1 425 868 6945",
    "sg:postcode":"98053",
    "sg:province":"WA",
    "sg:tags":[
        "programing",
        "custom"
    ],
    "wof:name":"Tony Yip",
    "wof:placetype":"venue"
},
  "geometry": {"coordinates":[-121.993562,47.637005],"type":"Point"}
}