{
  "type": "Feature",
  "properties": {
    "addr:full":"14920 NE 95th St Redmond WA 98052",
    "addr:housenumber":"14920",
    "addr:postcode":"98052",
    "addr:street":"Ne 95Th St",
    "iso:country":"US",
    "sg:address":"14920 NE 95th St",
    "sg:city":"Redmond",
    "sg:classifiers":[
        {
            "category":"Wholesale",
            "subcategory":"Toys & Hobbies",
            "type":"Manufacturing & Wholesale Goods"
        }
    ],
    "sg:phone":"+1 425 885 1551",
    "sg:postcode":"98052",
    "sg:province":"WA",
    "sg:tags":[
        "wholesaler"
    ],
    "wof:name":"Hardwood Flooring Distributors",
    "wof:placetype":"venue"
},
  "geometry": {"coordinates":[-122.140343,47.685953],"type":"Point"}
}