{
  "type": "Feature",
  "properties": {
    "addr:full":"612 E 2nd Ave Odessa WA 99159",
    "addr:housenumber":"612",
    "addr:postcode":"99159",
    "addr:street":"E 2Nd Ave",
    "iso:country":"US",
    "sg:address":"612 E 2nd Ave",
    "sg:city":"Odessa",
    "sg:phone":"+1 509 982 2267",
    "sg:postcode":"99159",
    "sg:province":"WA",
    "sg:tags":[
        "farm",
        "wheat",
        "beef",
        "feedlot",
        "cattle"
    ],
    "wof:name":"Triple S Ranch Inc",
    "wof:placetype":"venue"
},
  "geometry": {"coordinates":[-118.67885800000001,47.331841],"type":"Point"}
}