{
  "type": "Feature",
  "properties": {
    "addr:full":"124 243rd Pl SE Sammamish WA 98074",
    "addr:housenumber":"124",
    "addr:postcode":"98074",
    "addr:street":"243Rd Pl Se",
    "iso:country":"US",
    "sg:address":"124 243rd Pl SE",
    "sg:city":"Sammamish",
    "sg:classifiers":[
        {
            "category":"Building & Trades",
            "subcategory":"Locksmith",
            "type":"Services"
        }
    ],
    "sg:phone":"+1 425 818 2842",
    "sg:postcode":"98074",
    "sg:province":"WA",
    "sg:tags":[
        "key"
    ],
    "wof:name":"1 Hour All Day Emergency Locksmith In Sammamish",
    "wof:placetype":"venue"
},
  "geometry": {"coordinates":[-122.014622,47.608679],"type":"Point"}
}