{
  "type": "Feature",
  "properties": {
    "addr:full":"202 Plum Tree Ln Sequim WA 98382",
    "addr:housenumber":"202",
    "addr:postcode":"98382",
    "addr:street":"Plum Tree Ln",
    "iso:country":"US",
    "sg:address":"202 Plum Tree Ln",
    "sg:city":"Sequim",
    "sg:classifiers":[
        {
            "category":"Building & Trades",
            "subcategory":"Construction",
            "type":"Services"
        }
    ],
    "sg:phone":"+1 360 683 7000",
    "sg:postcode":"98382",
    "sg:province":"WA",
    "sg:tags":[
        "real",
        "speculative",
        "commercial",
        "property",
        "builder",
        "developer"
    ],
    "wof:name":"S B Enterprises",
    "wof:placetype":"venue"
},
  "geometry": {"coordinates":[-123.110642,48.10048],"type":"Point"}
}