{
  "type": "Feature",
  "properties": {
    "iso:country":"US",
    "sg:address":"12617 231st Ave E",
    "sg:city":"Buckley",
    "sg:classifiers":[
        {
            "category":"Building & Trades",
            "subcategory":"Construction",
            "type":"Services"
        }
    ],
    "sg:phone":"+1 360 897 9288",
    "sg:postcode":"98321",
    "sg:province":"WA",
    "sg:tags":[
        "contractor"
    ],
    "wof:name":"Pearls MBL Wldg & Fabrication",
    "wof:placetype":"venue"
},
  "geometry": {"coordinates":[-122.121662,47.140988],"type":"Point"}
}