{
  "type": "Feature",
  "properties": {
    "addr:full":"10515 36th Street Ct NW Gig Harbor WA 98335",
    "addr:housenumber":"10515",
    "addr:postcode":"98335",
    "addr:street":"36Th Street",
    "iso:country":"US",
    "sg:address":"10515 36th Street Ct NW",
    "sg:city":"Gig Harbor",
    "sg:classifiers":[
        {
            "category":"Shopping",
            "subcategory":"Hobbies, Toys, & Games",
            "type":"Retail Goods"
        }
    ],
    "sg:phone":"+1 253 265 6577",
    "sg:postcode":"98335",
    "sg:province":"WA",
    "wof:name":"Crafts4u",
    "wof:placetype":"venue"
},
  "geometry": {"coordinates":[-122.679278,47.290709],"type":"Point"}
}