{
  "type": "Feature",
  "properties": {
    "addr:full":"4135 Providence Hts Lp Issaquah WA 98029",
    "addr:housenumber":"4135",
    "addr:postcode":"98029",
    "addr:street":"Providence Hts Lp",
    "iso:country":"US",
    "sg:address":"4135 Providence Hts Lp",
    "sg:city":"Issaquah",
    "sg:classifiers":[
        {
            "category":"Real Estate",
            "subcategory":"Developer",
            "type":"Services"
        }
    ],
    "sg:phone":"+1 425 392 1922",
    "sg:postcode":"98029",
    "sg:province":"WA",
    "sg:tags":[
        "development"
    ],
    "wof:name":"Daewoo America Development",
    "wof:placetype":"venue"
},
  "geometry": {"coordinates":[-122.040138,47.572535],"type":"Point"}
}