{
  "type": "Feature",
  "properties": {
    "addr:full":"500 Sagebrush Rd Ellensburg WA 98926",
    "addr:housenumber":"500",
    "addr:postcode":"98926",
    "addr:street":"Sagebrush Rd",
    "iso:country":"US",
    "sg:address":"500 Sagebrush Rd",
    "sg:city":"Ellensburg",
    "sg:classifiers":[
        {
            "category":"Freight",
            "type":"Transportation"
        }
    ],
    "sg:phone":"+1 509 964 2337",
    "sg:postcode":"98926",
    "sg:province":"WA",
    "sg:tags":[
        "operator",
        "local",
        "trucking"
    ],
    "wof:name":"Cameron Trucking",
    "wof:placetype":"venue"
},
  "geometry": {"coordinates":[-120.681527,47.122515],"type":"Point"}
}