{
  "type": "Feature",
  "properties": {
    "addr:full":"1416 Columbia St Pomeroy WA 99347",
    "addr:housenumber":"1416",
    "addr:postcode":"99347",
    "addr:street":"Columbia St",
    "iso:country":"US",
    "sg:address":"1416 Columbia St",
    "sg:city":"Pomeroy",
    "sg:classifiers":[
        {
            "category":"Retail",
            "subcategory":"Auto Repair",
            "type":"Services"
        }
    ],
    "sg:phone":"+1 509 843 3828",
    "sg:postcode":"99347",
    "sg:province":"WA",
    "sg:tags":[
        "glass",
        "windshield",
        "replacement"
    ],
    "wof:name":"Glass Pro",
    "wof:placetype":"venue"
},
  "geometry": {"coordinates":[-117.59129299999999,46.473028],"type":"Point"}
}