{
  "type": "Feature",
  "properties": {
    "addr:full":"1113 Swan Ave Yakima WA 98902",
    "addr:housenumber":"1113",
    "addr:postcode":"98902",
    "addr:street":"Swan Ave",
    "iso:country":"US",
    "sg:address":"1113 Swan Ave",
    "sg:city":"Yakima",
    "sg:classifiers":[
        {
            "category":"Social Services",
            "subcategory":"Child Care",
            "type":"Services"
        }
    ],
    "sg:phone":"+1 509 452 5583",
    "sg:postcode":"98902",
    "sg:province":"WA",
    "sg:tags":[
        "day"
    ],
    "wof:name":"El Payasito Day Care",
    "wof:placetype":"venue"
},
  "geometry": {"coordinates":[-120.522476,46.609584],"type":"Point"}
}