{
  "type": "Feature",
  "properties": {
    "addr:full":"4332 S 41st St Tacoma WA 98409",
    "addr:housenumber":"4332",
    "addr:postcode":"98409",
    "addr:street":"S 41St St",
    "iso:country":"US",
    "sg:address":"4332 S 41st St",
    "sg:city":"Tacoma",
    "sg:classifiers":[
        {
            "category":"Real Estate",
            "subcategory":"Real Estate Operator",
            "type":"Services"
        }
    ],
    "sg:phone":"+1 253 474 4930",
    "sg:postcode":"98409",
    "sg:province":"WA",
    "sg:tags":[
        "building",
        "apartment"
    ],
    "wof:name":"Forest Hill Village Apartments",
    "wof:placetype":"venue"
},
  "geometry": {"coordinates":[-122.493522,47.220074],"type":"Point"}
}