{
  "type": "Feature",
  "properties": {
    "addr:full":"19975 Karla Ct Mount Vernon WA 98274",
    "addr:postcode":"19975;98274",
    "addr:street":"Karla Ct",
    "iso:country":"US",
    "sg:address":"19975 Karla Ct",
    "sg:city":"Mount Vernon",
    "sg:classifiers":[
        {
            "category":"Wholesale",
            "subcategory":"Seafood",
            "type":"Manufacturing & Wholesale Goods"
        }
    ],
    "sg:phone":"+1 360 445 6909",
    "sg:postcode":"98274",
    "sg:province":"WA",
    "sg:tags":[
        "commercial",
        "fishing"
    ],
    "wof:name":"Normar Inc",
    "wof:placetype":"venue"
},
  "geometry": {"coordinates":[-122.314052,48.337572],"type":"Point"}
}