{
  "type": "Feature",
  "properties": {
    "addr:full":"301 NE 51st St Seattle WA 98105",
    "addr:housenumber":"301",
    "addr:postcode":"98105",
    "addr:street":"Ne 51St St",
    "iso:country":"US",
    "sg:address":"301 NE 51st St",
    "sg:city":"Seattle",
    "sg:classifiers":[
        {
            "category":"Building & Trades",
            "subcategory":"Locksmith",
            "type":"Services"
        }
    ],
    "sg:phone":"+1 206 408 8224",
    "sg:postcode":"98105",
    "sg:province":"WA",
    "sg:tags":[
        "key"
    ],
    "wof:name":"Lock To Pop 24 Hr Locksmith",
    "wof:placetype":"venue"
},
  "geometry": {"coordinates":[-122.324212,47.665584],"type":"Point"}
}