{
  "type": "Feature",
  "properties": {
    "addr:full":"20271 13th Ave S Seattle WA 98198",
    "addr:housenumber":"20271",
    "addr:postcode":"98198",
    "addr:street":"13Th Ave S",
    "iso:country":"US",
    "sg:address":"20271 13th Ave S",
    "sg:city":"Seattle",
    "sg:classifiers":[
        {
            "category":"Building & Trades",
            "subcategory":"Landscaping Services",
            "type":"Services"
        }
    ],
    "sg:phone":"+1 206 323 9282",
    "sg:postcode":"98198",
    "sg:province":"WA",
    "sg:tags":[
        "landscape"
    ],
    "wof:name":"Down and Dirty Landscaping",
    "wof:placetype":"venue"
},
  "geometry": {"coordinates":[-122.316818,47.421001],"type":"Point"}
}