{
  "type": "Feature",
  "properties": {
    "addr:full":"26416 187th Ave SE Kent WA 98042",
    "addr:housenumber":"26416",
    "addr:postcode":"98042",
    "addr:street":"187Th Ave Se",
    "iso:country":"US",
    "sg:address":"26416 187th Ave SE",
    "sg:city":"Kent",
    "sg:classifiers":[
        {
            "category":"Sports & Exercise",
            "subcategory":"Gym",
            "type":"Entertainment"
        }
    ],
    "sg:phone":"+1 253 630 4355",
    "sg:postcode":"98042",
    "sg:province":"WA",
    "sg:tags":[
        "fitness",
        "physical",
        "facility"
    ],
    "wof:name":"Unico Fitness",
    "wof:placetype":"venue"
},
  "geometry": {"coordinates":[-122.093703,47.36501],"type":"Point"}
}