{
  "type": "Feature",
  "properties": {
    "addr:full":"812 E Main Ave Puyallup WA 98372",
    "addr:housenumber":"812",
    "addr:postcode":"98372",
    "addr:street":"E Main Ave",
    "iso:country":"US",
    "sg:address":"812 E Main Ave",
    "sg:city":"Puyallup",
    "sg:classifiers":[
        {
            "category":"Banks & Credit Unions",
            "subcategory":"Bank",
            "type":"Services"
        }
    ],
    "sg:phone":"+1 253 848 5494",
    "sg:postcode":"98372",
    "sg:province":"WA",
    "sg:tags":[
        "national",
        "commercial"
    ],
    "sg:website":"www.charterfunding.com",
    "wof:name":"Charter Bank Funding",
    "wof:placetype":"venue"
},
  "geometry": {"coordinates":[-122.28309900000001,47.191907],"type":"Point"}
}