{
  "type": "Feature",
  "properties": {
    "addr:full":"1016 S 10th St Tacoma WA 98405",
    "addr:housenumber":"1016",
    "addr:postcode":"98405",
    "addr:street":"S 10Th St",
    "iso:country":"US",
    "sg:address":"1016 S 10th St",
    "sg:city":"Tacoma",
    "sg:classifiers":[
        {
            "category":"Organizations",
            "subcategory":"Religious Organization",
            "type":"Services"
        }
    ],
    "sg:phone":"+1 253 272 3250",
    "sg:postcode":"98405",
    "sg:province":"WA",
    "sg:tags":[
        "church"
    ],
    "wof:name":"Hilltop Christian Ctr",
    "wof:placetype":"venue"
},
  "geometry": {"coordinates":[-122.451784,47.252981],"type":"Point"}
}