{
  "type": "Feature",
  "properties": {
    "addr:full":"205 E 11th St Vancouver WA 98660",
    "addr:housenumber":"205",
    "addr:postcode":"98660",
    "addr:street":"E 11Th St",
    "iso:country":"US",
    "sg:address":"205 E 11th St",
    "sg:city":"Vancouver",
    "sg:classifiers":[
        {
            "category":"Real Estate",
            "subcategory":"Real Estate Agent",
            "type":"Services"
        }
    ],
    "sg:phone":"+1 360 943 4663",
    "sg:postcode":"98660",
    "sg:province":"WA",
    "sg:tags":[
        "management"
    ],
    "wof:name":"Quantum Residential Inc",
    "wof:placetype":"venue"
},
  "geometry": {"coordinates":[-122.669442,45.62944],"type":"Point"}
}