{
  "type": "Feature",
  "properties": {
    "addr:full":"19333 International Blvd Seatac WA 98188",
    "addr:housenumber":"19333",
    "addr:postcode":"98188",
    "addr:street":"International Blvd",
    "iso:country":"US",
    "sg:address":"19333 International Blvd",
    "sg:city":"Seatac",
    "sg:classifiers":[
        {
            "category":"Building & Trades",
            "subcategory":"Construction",
            "type":"Services"
        }
    ],
    "sg:phone":"+1 206 870 8692",
    "sg:postcode":"98188",
    "sg:province":"WA",
    "sg:tags":[
        "project"
    ],
    "wof:name":"Condor Developments",
    "wof:placetype":"venue"
},
  "geometry": {"coordinates":[-122.29562199999999,47.428786],"type":"Point"}
}