{
  "type": "Feature",
  "properties": {
    "iso:country":"US",
    "sg:address":"3517 Sapp Rd SW",
    "sg:city":"Olympia",
    "sg:classifiers":[
        {
            "category":"Building & Trades",
            "subcategory":"Plumbing",
            "type":"Services"
        }
    ],
    "sg:phone":"+1 360 754 9670",
    "sg:postcode":"98512",
    "sg:province":"WA",
    "sg:tags":[
        "plumbing",
        "contractor"
    ],
    "wof:name":"Springer Plumbing LLC",
    "wof:placetype":"venue"
},
  "geometry": {"coordinates":[-122.953779,47.008819],"type":"Point"}
}