{
  "type": "Feature",
  "properties": {
    "addr:full":"401 S Henderson St Seattle WA 98108",
    "addr:housenumber":"401",
    "addr:postcode":"98108",
    "addr:street":"S Henderson St",
    "iso:country":"US",
    "sg:address":"401 S Henderson St",
    "sg:city":"Seattle",
    "sg:classifiers":[
        {
            "category":"Building & Trades",
            "subcategory":"Cleaning & Sanitation",
            "type":"Services"
        }
    ],
    "sg:phone":"+1 206 226 3016",
    "sg:postcode":"98108",
    "sg:province":"WA",
    "sg:tags":[
        "maintenance"
    ],
    "wof:name":"Alh Cleaning Service",
    "wof:placetype":"venue"
},
  "geometry": {"coordinates":[-122.32825699999999,47.523078],"type":"Point"}
}