{
  "type": "Feature",
  "properties": {
    "addr:full":"12217 NE Hwy 99 Vancouver WA 98686",
    "addr:housenumber":"12217",
    "addr:postcode":"98686",
    "addr:street":"Ne Hwy 99",
    "iso:country":"US",
    "sg:address":"12217 NE Hwy 99",
    "sg:city":"Vancouver",
    "sg:classifiers":[
        {
            "category":"Social Services",
            "subcategory":"Child Care",
            "type":"Services"
        }
    ],
    "sg:phone":"+1 360 573 9541",
    "sg:postcode":"98686",
    "sg:province":"WA",
    "wof:name":"Salmon Creek Christian Day Cr",
    "wof:placetype":"venue"
},
  "geometry": {"coordinates":[-122.64987600000001,45.710864],"type":"Point"}
}