{
  "type": "Feature",
  "properties": {
    "addr:full":"1711 Fern St Walla Walla WA 99362",
    "addr:housenumber":"1711",
    "addr:postcode":"99362",
    "addr:street":"Fern St",
    "iso:country":"US",
    "sg:address":"1711 Fern St",
    "sg:city":"Walla Walla",
    "sg:classifiers":[
        {
            "category":"Building & Trades",
            "subcategory":"Cleaning & Sanitation",
            "type":"Services"
        }
    ],
    "sg:phone":"+1 509 525 2385",
    "sg:postcode":"99362",
    "sg:province":"WA",
    "sg:tags":[
        "janitor"
    ],
    "wof:name":"Diversified Maintenance System",
    "wof:placetype":"venue"
},
  "geometry": {"coordinates":[-118.314716,46.052952],"type":"Point"}
}