{
  "type": "Feature",
  "properties": {
    "addr:full":"5820 188th St SW Lynnwood WA 98037",
    "addr:housenumber":"5820",
    "addr:postcode":"98037",
    "addr:street":"188Th St Sw",
    "iso:country":"US",
    "sg:address":"5820 188th St SW",
    "sg:city":"Lynnwood",
    "sg:classifiers":[
        {
            "category":"Manufacturing",
            "subcategory":"Metals",
            "type":"Manufacturing & Wholesale Goods"
        }
    ],
    "sg:phone":"+1 425 778 4123",
    "sg:postcode":"98037",
    "sg:province":"WA",
    "sg:tags":[
        "fabricator",
        "sheet"
    ],
    "sg:website":"www.lafargeinc.com",
    "wof:name":"LA Farge & Egge",
    "wof:placetype":"venue"
},
  "geometry": {"coordinates":[-122.31014500000001,47.828303],"type":"Point"}
}