{
  "type": "Feature",
  "properties": {
    "addr:full":"1120 Andover Park E Tukwila WA 98188",
    "addr:housenumber":"1120",
    "addr:postcode":"98188",
    "addr:street":"Andover Park E",
    "iso:country":"US",
    "sg:address":"1120 Andover Park E",
    "sg:city":"Tukwila",
    "sg:classifiers":[
        {
            "category":"Wholesale",
            "subcategory":"Home Furnishings",
            "type":"Manufacturing & Wholesale Goods"
        }
    ],
    "sg:phone":"+1 206 577 7718",
    "sg:postcode":"98188",
    "sg:province":"WA",
    "sg:tags":[
        "tube",
        "fitting"
    ],
    "sg:website":"http://www.pacificpowertech.com",
    "wof:name":"Pacific PowerTech, LLC",
    "wof:placetype":"venue"
},
  "geometry": {"coordinates":[-122.25101600000001,47.444874],"type":"Point"}
}