{
  "type": "Feature",
  "properties": {
    "addr:full":"901 24th St Anacortes WA 98221",
    "addr:housenumber":"901",
    "addr:postcode":"98221",
    "addr:street":"24Th St",
    "iso:country":"US",
    "sg:address":"901 24th St",
    "sg:city":"Anacortes",
    "sg:classifiers":[
        {
            "category":"Insurance",
            "subcategory":"Insurance Agent",
            "type":"Services"
        }
    ],
    "sg:phone":"+1 360 293 2135",
    "sg:postcode":"98221",
    "sg:province":"WA",
    "sg:website":"www.risnet.com",
    "wof:name":"RIS Insurance Svc",
    "wof:placetype":"venue"
},
  "geometry": {"coordinates":[-122.61272700000001,48.502883],"type":"Point"}
}