{
  "type": "Feature",
  "properties": {
    "addr:full":"12004 NW 36th Ave Vancouver WA 98685",
    "addr:housenumber":"12004",
    "addr:postcode":"98685",
    "addr:street":"Nw 36Th Ave",
    "iso:country":"US",
    "sg:address":"12004 NW 36th Ave",
    "sg:city":"Vancouver",
    "sg:classifiers":[
        {
            "category":"Manufacturing",
            "subcategory":"Tools & Machinery",
            "type":"Manufacturing & Wholesale Goods"
        }
    ],
    "sg:phone":"+1 360 573 5592",
    "sg:postcode":"98685",
    "sg:province":"WA",
    "sg:tags":[
        "industrial",
        "mfg"
    ],
    "wof:name":"Portable Fab & Machine",
    "wof:placetype":"venue"
},
  "geometry": {"coordinates":[-122.708232,45.708426],"type":"Point"}
}