{
  "type": "Feature",
  "properties": {
    "iso:country":"US",
    "sg:address":"1005 Fir St",
    "sg:city":"Longview",
    "sg:classifiers":[
        {
            "category":"Health Services",
            "subcategory":"Doctor",
            "type":"Services"
        }
    ],
    "sg:phone":"+1 360 414 7700",
    "sg:postcode":"98632",
    "sg:province":"WA",
    "sg:tags":[
        "medical"
    ],
    "wof:name":"Melody R Stupey MD",
    "wof:placetype":"venue"
},
  "geometry": {"coordinates":[-122.93331499999999,46.13125],"type":"Point"}
}