{
  "type": "Feature",
  "properties": {
    "addr:full":"151 S Lander St Ste B Seattle WA 98134",
    "addr:housenumber":"151",
    "addr:postcode":"98134",
    "addr:street":"S Lander St Ste B",
    "iso:country":"US",
    "sg:address":"151 S Lander St Ste B",
    "sg:city":"Seattle",
    "sg:classifiers":[
        {
            "category":"Health Services",
            "subcategory":"Doctor",
            "type":"Services"
        }
    ],
    "sg:phone":"+1 206 287 1577",
    "sg:postcode":"98134",
    "sg:province":"WA",
    "sg:tags":[
        "physician",
        "surgeon"
    ],
    "sg:website":"http://www.healthsouth.com",
    "wof:name":"Healthsouth",
    "wof:placetype":"venue"
},
  "geometry": {"coordinates":[-122.333252,47.579811],"type":"Point"}
}