{
  "type": "Feature",
  "properties": {
    "addr:full":"11306 Steele St S Lakewood WA 98499",
    "addr:housenumber":"11306",
    "addr:postcode":"98499",
    "addr:street":"Steele St S",
    "iso:country":"US",
    "sg:address":"11306 Steele St S",
    "sg:city":"Lakewood",
    "sg:classifiers":[
        {
            "category":"Retail",
            "subcategory":"Auto Repair",
            "type":"Services"
        }
    ],
    "sg:phone":"+1 253 537 2787",
    "sg:postcode":"98499",
    "sg:province":"WA",
    "sg:tags":[
        "body",
        "automobile",
        "painting"
    ],
    "wof:name":"Euro Collison",
    "wof:placetype":"venue"
},
  "geometry": {"coordinates":[-122.46803300000001,47.154023],"type":"Point"}
}