{
  "type": "Feature",
  "properties": {
    "addr:full":"793 Mountain View Ave Buckley WA 98321",
    "addr:housenumber":"793",
    "addr:postcode":"98321",
    "addr:street":"Mountain View Ave",
    "iso:country":"US",
    "sg:address":"793 Mountain View Ave",
    "sg:city":"Buckley",
    "sg:classifiers":[
        {
            "category":"Food & Beverages",
            "subcategory":"Groceries & Convenience Stores",
            "type":"Retail Goods"
        }
    ],
    "sg:phone":"+1 360 829 2409",
    "sg:postcode":"98321",
    "sg:province":"WA",
    "wof:name":"Allzees Market Place",
    "wof:placetype":"venue"
},
  "geometry": {"coordinates":[-122.03010500000001,47.155015],"type":"Point"}
}