{
  "type": "Feature",
  "properties": {
    "iso:country":"US",
    "sg:address":"5705 Airport Way S",
    "sg:city":"Seattle",
    "sg:classifiers":[
        {
            "category":"Wholesale",
            "subcategory":"Hardware",
            "type":"Manufacturing & Wholesale Goods"
        }
    ],
    "sg:phone":"+1 206 762 8408",
    "sg:postcode":"98108",
    "sg:province":"WA",
    "sg:tags":[
        "fastener"
    ],
    "wof:name":"Cheler Corp",
    "wof:placetype":"venue"
},
  "geometry": {"coordinates":[-122.31849,47.550736],"type":"Point"}
}