{
  "type": "Feature",
  "properties": {
    "addr:full":"627 SW 144th Pl Burien WA 98166",
    "addr:housenumber":"627",
    "addr:postcode":"98166",
    "addr:street":"Sw 144Th Pl",
    "iso:country":"US",
    "sg:address":"627 SW 144th Pl",
    "sg:city":"Burien",
    "sg:classifiers":[
        {
            "category":"Professional",
            "subcategory":"Business Services",
            "type":"Services"
        }
    ],
    "sg:phone":"+1 206 938 3343",
    "sg:postcode":"98166",
    "sg:province":"WA",
    "sg:tags":[
        "interior",
        "consultant",
        "design",
        "decorator"
    ],
    "wof:name":"Catherine J Du Bose Designs",
    "wof:placetype":"venue"
},
  "geometry": {"coordinates":[-122.34437699999999,47.473599],"type":"Point"}
}