{
  "type": "Feature",
  "properties": {
    "addr:full":"1257 SW 301st St Federal Way WA 98023",
    "addr:housenumber":"1257",
    "addr:postcode":"98023",
    "addr:street":"Sw 301St St",
    "iso:country":"US",
    "sg:address":"1257 SW 301st St",
    "sg:city":"Federal Way",
    "sg:classifiers":[
        {
            "category":"Autos & Motor Vehicles",
            "subcategory":"Automobile Sales",
            "type":"Retail Goods"
        }
    ],
    "sg:phone":"+1 253 946 9247",
    "sg:postcode":"98023",
    "sg:province":"WA",
    "sg:tags":[
        "used"
    ],
    "wof:name":"Dreamchaser Autos",
    "wof:placetype":"venue"
},
  "geometry": {"coordinates":[-122.355532,47.331934],"type":"Point"}
}