{
  "type": "Feature",
  "properties": {
    "addr:full":"17015 129th Ave SE Renton WA 98058",
    "addr:housenumber":"17015",
    "addr:postcode":"98058",
    "addr:street":"129Th Ave Se",
    "iso:country":"US",
    "sg:address":"17015 129th Ave SE",
    "sg:city":"Renton",
    "sg:classifiers":[
        {
            "category":"Building & Trades",
            "subcategory":"Cleaning & Sanitation",
            "type":"Services"
        }
    ],
    "sg:phone":"+1 206 229 9990",
    "sg:postcode":"98058",
    "sg:province":"WA",
    "sg:tags":[
        "maintenance"
    ],
    "wof:name":"Julias Cleaning Services",
    "wof:placetype":"venue"
},
  "geometry": {"coordinates":[-122.168745,47.448861],"type":"Point"}
}