{
  "type": "Feature",
  "properties": {
    "addr:full":"3521 S Woodward Rd Spokane WA 99206",
    "addr:housenumber":"3521",
    "addr:postcode":"99206",
    "addr:street":"S Woodward Rd",
    "iso:country":"US",
    "sg:address":"3521 S Woodward Rd",
    "sg:city":"Spokane",
    "sg:classifiers":[
        {
            "category":"Recreation",
            "type":"Entertainment"
        }
    ],
    "sg:phone":"+1 509 922 4259",
    "sg:postcode":"99206",
    "sg:province":"WA",
    "sg:tags":[
        "club",
        "membership"
    ],
    "wof:name":"Felts Field Flyers Club LLC",
    "wof:placetype":"venue"
},
  "geometry": {"coordinates":[-117.25189,47.623961],"type":"Point"}
}