{
  "type": "Feature",
  "properties": {
    "addr:full":"15 S Grady Way Suite 534 Renton WA 98057",
    "addr:housenumber":"15",
    "addr:postcode":"98057",
    "addr:street":"S Grady Way Suite 534",
    "iso:country":"US",
    "sg:address":"15 S Grady Way Suite 534",
    "sg:city":"Renton",
    "sg:classifiers":[
        {
            "category":"Banks & Credit Unions",
            "subcategory":"Investment Brokerage",
            "type":"Services"
        },
        {
            "category":"Banks & Credit Unions",
            "subcategory":"Bank",
            "type":"Services"
        },
        {
            "category":"Banks & Credit Unions",
            "subcategory":"Financial Services",
            "type":"Services"
        }
    ],
    "sg:phone":"+1 425 227 3294",
    "sg:postcode":"98057",
    "sg:province":"WA",
    "sg:tags":[
        "mutual",
        "retirement",
        "broker",
        "fund",
        "planning",
        "security",
        "bond",
        "stock"
    ],
    "sg:website":"http://www.edwardjones.com/en_US/fa/index.html&CIRN=307399",
    "wof:name":"Edward Jones - Financial Advisor: EUGENE HECHEL II",
    "wof:placetype":"venue"
},
  "geometry": {"coordinates":[-122.215141,47.471191],"type":"Point"}
}