{
  "type": "Feature",
  "properties": {
    "addr:full":"401 Alexander Ave E Tacoma WA 98424",
    "addr:housenumber":"401",
    "addr:postcode":"98424",
    "addr:street":"Alexander Ave E",
    "iso:country":"US",
    "sg:address":"401 Alexander Ave E",
    "sg:city":"Tacoma",
    "sg:classifiers":[
        {
            "category":"Government",
            "subcategory":"Office",
            "type":"Public Place"
        }
    ],
    "sg:phone":"+1 253 474 8297",
    "sg:postcode":"98424",
    "sg:province":"WA",
    "sg:tags":[
        "federal",
        "security"
    ],
    "wof:name":"US Army Reserve Ctr",
    "wof:placetype":"venue"
},
  "geometry": {"coordinates":[-122.372981,47.251532],"type":"Point"}
}