{
  "type": "Feature",
  "properties": {
    "addr:full":"3640 128th Ave SE Bellevue WA 98006",
    "addr:housenumber":"3640",
    "addr:postcode":"98006",
    "addr:street":"128Th Ave Se",
    "iso:country":"US",
    "sg:address":"3640 128th Ave SE",
    "sg:city":"Bellevue",
    "sg:classifiers":[
        {
            "category":"Food & Beverages",
            "subcategory":"Dairy",
            "type":"Retail Goods"
        }
    ],
    "sg:phone":"+1 425 644 9509",
    "sg:postcode":"98006",
    "sg:province":"WA",
    "sg:tags":[
        "yogurt"
    ],
    "wof:name":"Euphoria Yogurt",
    "wof:placetype":"venue"
},
  "geometry": {"coordinates":[-122.168949,47.579195],"type":"Point"}
}