{
  "type": "Feature",
  "properties": {
    "addr:full":"580 Long Ln Yakima WA 98908",
    "addr:housenumber":"580",
    "addr:postcode":"98908",
    "addr:street":"Long Ln",
    "iso:country":"US",
    "sg:address":"580 Long Ln",
    "sg:city":"Yakima",
    "sg:classifiers":[
        {
            "category":"Manufacturing",
            "subcategory":"Watercraft",
            "type":"Manufacturing & Wholesale Goods"
        }
    ],
    "sg:phone":"+1 509 966 5375",
    "sg:postcode":"98908",
    "sg:province":"WA",
    "sg:tags":[
        "boat"
    ],
    "wof:name":"Columbia Jet Boats",
    "wof:placetype":"venue"
},
  "geometry": {"coordinates":[-120.615629,46.650897],"type":"Point"}
}