{
  "type": "Feature",
  "properties": {
    "addr:full":"11860 1st Ave S Seattle WA 98168",
    "addr:housenumber":"11860",
    "addr:postcode":"98168",
    "addr:street":"1St Ave S",
    "iso:country":"US",
    "sg:address":"11860 1st Ave S",
    "sg:city":"Seattle",
    "sg:classifiers":[
        {
            "category":"Arts & Performance",
            "subcategory":"Arts Center",
            "type":"Entertainment"
        },
        {
            "category":"Education",
            "subcategory":"School",
            "type":"Public Place"
        }
    ],
    "sg:phone":"+1 206 505 9097",
    "sg:postcode":"98168",
    "sg:province":"WA",
    "wof:name":"Conga Drum Intensive",
    "wof:placetype":"venue"
},
  "geometry": {"coordinates":[-122.33345,47.495995],"type":"Point"}
}