{
  "type": "Feature",
  "properties": {
    "addr:full":"9221 NE 128th Ln Kirkland WA 98034",
    "addr:housenumber":"9221",
    "addr:postcode":"98034",
    "addr:street":"Ne 128Th Ln",
    "iso:country":"US",
    "sg:address":"9221 NE 128th Ln",
    "sg:city":"Kirkland",
    "sg:classifiers":[
        {
            "category":"Manufacturing",
            "subcategory":"Jewelry",
            "type":"Manufacturing & Wholesale Goods"
        }
    ],
    "sg:phone":"+1 425 820 7564",
    "sg:postcode":"98034",
    "sg:province":"WA",
    "sg:tags":[
        "manufacturer",
        "costume",
        "jewelers-wholesale",
        "mfg"
    ],
    "wof:name":"Patti Beth De Fazio",
    "wof:placetype":"venue"
},
  "geometry": {"coordinates":[-122.21704099999999,47.715328],"type":"Point"}
}