{
  "type": "Feature",
  "properties": {
    "addr:full":"3900 Starboard Ln SE Port Orchard WA 98366",
    "addr:housenumber":"3900",
    "addr:postcode":"98366",
    "addr:street":"Starboard Ln Se",
    "iso:country":"US",
    "sg:address":"3900 Starboard Ln SE",
    "sg:city":"Port Orchard",
    "sg:classifiers":[
        {
            "category":"Real Estate",
            "subcategory":"Real Estate Operator",
            "type":"Services"
        }
    ],
    "sg:phone":"+1 360 895 0120",
    "sg:postcode":"98366",
    "sg:province":"WA",
    "sg:tags":[
        "building",
        "apartment"
    ],
    "wof:name":"Pointe West Apartments",
    "wof:placetype":"venue"
},
  "geometry": {"coordinates":[-122.61082,47.512733],"type":"Point"}
}