{
  "type": "Feature",
  "properties": {
    "iso:country":"US",
    "sg:address":"55 Main St",
    "sg:city":"Pacific Beach",
    "sg:classifiers":[
        {
            "category":"Shopping",
            "subcategory":"Hobbies, Toys, & Games",
            "type":"Retail Goods"
        }
    ],
    "sg:phone":"+1 360 276 8377",
    "sg:postcode":"98571",
    "sg:province":"WA",
    "sg:tags":[
        "kite"
    ],
    "wof:name":"Hi-Flyers Kites & Things",
    "wof:placetype":"venue"
},
  "geometry": {"coordinates":[-124.202991,47.20874],"type":"Point"}
}