{
  "type": "Feature",
  "properties": {
    "addr:full":"2571 Dewey Rd Lamont WA 99017",
    "addr:housenumber":"2571",
    "addr:postcode":"99017",
    "addr:street":"Dewey Rd",
    "iso:country":"US",
    "sg:address":"2571 Dewey Rd",
    "sg:city":"Lamont",
    "sg:classifiers":[
        {
            "category":"Farming",
            "subcategory":"Farm",
            "type":"Manufacturing & Wholesale Goods"
        }
    ],
    "sg:phone":"+1 509 257 2523",
    "sg:postcode":"99017",
    "sg:province":"WA",
    "wof:name":"Melville Dean",
    "wof:placetype":"venue"
},
  "geometry": {"coordinates":[-117.872241,47.216709],"type":"Point"}
}