{
  "type": "Feature",
  "properties": {
    "addr:full":"35 Highway 20 Tonasket WA 98855",
    "addr:housenumber":"35",
    "addr:postcode":"98855",
    "addr:street":"Highway 20",
    "iso:country":"US",
    "sg:address":"35 Highway 20",
    "sg:city":"Tonasket",
    "sg:classifiers":[
        {
            "category":"Education",
            "subcategory":"School",
            "type":"Public Place"
        }
    ],
    "sg:phone":"+1 509 486 1428",
    "sg:postcode":"98855",
    "sg:province":"WA",
    "sg:tags":[
        "elementary"
    ],
    "wof:name":"Tonasket Alternative School",
    "wof:placetype":"venue"
},
  "geometry": {"coordinates":[-119.43767,48.701427],"type":"Point"}
}