{
  "type": "Feature",
  "properties": {
    "addr:full":"300 NE Silver Pine Dr Bremerton WA 98311",
    "addr:housenumber":"300",
    "addr:postcode":"98311",
    "addr:street":"Ne Silver Pine Dr",
    "iso:country":"US",
    "sg:address":"300 NE Silver Pine Dr",
    "sg:city":"Bremerton",
    "sg:classifiers":[
        {
            "category":"Professional",
            "type":"Services"
        }
    ],
    "sg:phone":"+1 360 620 0404",
    "sg:postcode":"98311",
    "sg:province":"WA",
    "wof:name":"Ginas Sari Sari",
    "wof:placetype":"venue"
},
  "geometry": {"coordinates":[-122.644248,47.638197],"type":"Point"}
}