{
  "type": "Feature",
  "properties": {
    "addr:full":"13530 184th Ave NE Woodinville WA 98072",
    "addr:housenumber":"13530",
    "addr:postcode":"98072",
    "addr:street":"184Th Ave Ne",
    "iso:country":"US",
    "sg:address":"13530 184th Ave NE",
    "sg:city":"Woodinville",
    "sg:classifiers":[
        {
            "category":"Professional",
            "subcategory":"Management & Consulting",
            "type":"Services"
        }
    ],
    "sg:phone":"+1 425 883 6390",
    "sg:postcode":"98072",
    "sg:province":"WA",
    "wof:name":"Jlm Assoc",
    "wof:placetype":"venue"
},
  "geometry": {"coordinates":[-122.09410200000001,47.721505],"type":"Point"}
}