{
  "type": "Feature",
  "properties": {
    "addr:full":"9 W Pine Ct Longview WA 98632",
    "addr:housenumber":"9",
    "addr:postcode":"98632",
    "addr:street":"W Pine Ct",
    "iso:country":"US",
    "sg:address":"9 W Pine Ct",
    "sg:city":"Longview",
    "sg:classifiers":[
        {
            "category":"Travel",
            "subcategory":"Campground",
            "type":"Entertainment"
        }
    ],
    "sg:phone":"+1 360 636 1549",
    "sg:postcode":"98632",
    "sg:province":"WA",
    "sg:tags":[
        "camp"
    ],
    "wof:name":"Robert Owen Blackman III",
    "wof:placetype":"venue"
},
  "geometry": {"coordinates":[-122.98496799999999,46.170123],"type":"Point"}
}