{
  "type": "Feature",
  "properties": {
    "addr:full":"202434 E Game Farm Rd Kennewick WA 99337",
    "addr:housenumber":"202434",
    "addr:postcode":"99337",
    "addr:street":"E Game Farm Rd",
    "iso:country":"US",
    "sg:address":"202434 E Game Farm Rd",
    "sg:city":"Kennewick",
    "sg:phone":"+1 509 582 5621",
    "sg:postcode":"99337",
    "sg:province":"WA",
    "sg:tags":[
        "beef",
        "farm",
        "crop",
        "field",
        "cattle",
        "feedlot"
    ],
    "wof:name":"Mel Wood",
    "wof:placetype":"venue"
},
  "geometry": {"coordinates":[-119.07537600000001,46.154259],"type":"Point"}
}