{
  "type": "Feature",
  "properties": {
    "addr:full":"7215 192nd Ave E Sumner WA 98391",
    "addr:housenumber":"7215",
    "addr:postcode":"98391",
    "addr:street":"192Nd Ave E",
    "iso:country":"US",
    "sg:address":"7215 192nd Ave E",
    "sg:city":"Sumner",
    "sg:classifiers":[
        {
            "category":"Professional",
            "subcategory":"Engineering",
            "type":"Services"
        }
    ],
    "sg:phone":"+1 206 510 0528",
    "sg:postcode":"98391",
    "sg:province":"WA",
    "wof:name":"Northwest Landworks",
    "wof:placetype":"venue"
},
  "geometry": {"coordinates":[-122.173793,47.189958],"type":"Point"}
}