{
  "type": "Feature",
  "properties": {
    "addr:full":"509 E Yelm Ave Yelm WA 98597",
    "addr:housenumber":"509",
    "addr:postcode":"98597",
    "addr:street":"E Yelm Ave",
    "iso:country":"US",
    "sg:address":"509 E Yelm Ave",
    "sg:city":"Yelm",
    "sg:classifiers":[
        {
            "category":"Autos & Motor Vehicles",
            "subcategory":"Auto Supplies",
            "type":"Retail Goods"
        }
    ],
    "sg:phone":"+1 360 458 5100",
    "sg:postcode":"98597",
    "sg:province":"WA",
    "sg:tags":[
        "automobile",
        "parts"
    ],
    "wof:name":"NAPA Auto Parts",
    "wof:placetype":"venue"
},
  "geometry": {"coordinates":[-122.601373,46.938702],"type":"Point"}
}