{
  "type": "Feature",
  "properties": {
    "addr:full":"8416 NE 121st Pl Kirkland WA 98034",
    "addr:housenumber":"8416",
    "addr:postcode":"98034",
    "addr:street":"Ne 121St Pl",
    "iso:country":"US",
    "sg:address":"8416 NE 121st Pl",
    "sg:city":"Kirkland",
    "sg:classifiers":[
        {
            "category":"Professional",
            "subcategory":"Management & Consulting",
            "type":"Services"
        }
    ],
    "sg:phone":"+1 206 369 0990",
    "sg:postcode":"98034",
    "sg:province":"WA",
    "wof:name":"Management Concepts Inc",
    "wof:placetype":"venue"
},
  "geometry": {"coordinates":[-122.22878900000001,47.709458],"type":"Point"}
}