{
  "type": "Feature",
  "properties": {
    "addr:full":"3702 S Fife St Ste. B Tacoma WA 98409",
    "addr:housenumber":"3702",
    "addr:postcode":"98409",
    "addr:street":"S Fife St Ste. B",
    "iso:country":"US",
    "sg:address":"3702 S Fife St Ste. B",
    "sg:city":"Tacoma",
    "sg:classifiers":[
        {
            "category":"Utilities",
            "subcategory":"Mobile Phone",
            "type":"Services"
        },
        {
            "category":"Shopping",
            "subcategory":"Mobile Phones",
            "type":"Retail Goods"
        }
    ],
    "sg:phone":"+1 253 476 2100",
    "sg:postcode":"98409",
    "sg:province":"WA",
    "sg:tags":[
        "supply",
        "communication",
        "telephone",
        "wireless",
        "equipment",
        "cellular"
    ],
    "sg:website":"http://www.sprint.com",
    "wof:name":"Sprint Store",
    "wof:placetype":"venue"
},
  "geometry": {"coordinates":[-122.471338,47.223194],"type":"Point"}
}