{
  "type": "Feature",
  "properties": {
    "addr:full":"10059 8th Ave SW Seattle WA 98146",
    "addr:housenumber":"10059",
    "addr:postcode":"98146",
    "addr:street":"8Th Ave Sw",
    "iso:country":"US",
    "sg:address":"10059 8th Ave SW",
    "sg:city":"Seattle",
    "sg:classifiers":[
        {
            "category":"Utilities",
            "subcategory":"Water",
            "type":"Services"
        }
    ],
    "sg:phone":"+1 206 762 3540",
    "sg:postcode":"98146",
    "sg:province":"WA",
    "sg:tags":[
        "company-utility",
        "system",
        "supply"
    ],
    "wof:name":"King County Water Dept",
    "wof:placetype":"venue"
},
  "geometry": {"coordinates":[-122.34508599999999,47.512731],"type":"Point"}
}