{
  "type": "Feature",
  "properties": {
    "addr:full":"7781 Rathbone Rd Ferndale WA 98248",
    "addr:housenumber":"7781",
    "addr:postcode":"98248",
    "addr:street":"Rathbone Rd",
    "iso:country":"US",
    "sg:address":"7781 Rathbone Rd",
    "sg:city":"Ferndale",
    "sg:classifiers":[
        {
            "category":"Building & Trades",
            "subcategory":"Electrical",
            "type":"Services"
        }
    ],
    "sg:phone":"+1 360 354 4811",
    "sg:postcode":"98248",
    "sg:province":"WA",
    "sg:tags":[
        "electric",
        "contractor"
    ],
    "wof:name":"Lightening Electric Co",
    "wof:placetype":"venue"
},
  "geometry": {"coordinates":[-122.53004900000001,48.926631],"type":"Point"}
}