{
  "type": "Feature",
  "properties": {
    "addr:full":"1314 Union Ave NE Renton WA 98059",
    "addr:housenumber":"1314",
    "addr:postcode":"98059",
    "addr:street":"Union Ave Ne",
    "iso:country":"US",
    "sg:address":"1314 Union Ave NE",
    "sg:city":"Renton",
    "sg:classifiers":[
        {
            "category":"Government",
            "subcategory":"Department Of Motor Vehicles",
            "type":"Public Place"
        }
    ],
    "sg:phone":"+1 425 277 7230",
    "sg:postcode":"98059",
    "sg:province":"WA",
    "wof:name":"Washington State Department of Licensing",
    "wof:placetype":"venue"
},
  "geometry": {"coordinates":[-122.164687,47.50398],"type":"Point"}
}