{
  "type": "Feature",
  "properties": {
    "addr:full":"5026 196th St SW Lynnwood WA 98036",
    "addr:housenumber":"5026",
    "addr:postcode":"98036",
    "addr:street":"196Th St Sw",
    "iso:country":"US",
    "sg:address":"5026 196th St SW",
    "sg:city":"Lynnwood",
    "sg:classifiers":[
        {
            "category":"Shopping",
            "subcategory":"Florist",
            "type":"Retail Goods"
        },
        {
            "category":"Home & Garden",
            "subcategory":"Garden Supply",
            "type":"Retail Goods"
        }
    ],
    "sg:phone":"+1 425 775 3550",
    "sg:postcode":"98036",
    "sg:province":"WA",
    "sg:tags":[
        "me"
    ],
    "wof:name":"Wight's Home & Garden",
    "wof:placetype":"venue"
},
  "geometry": {"coordinates":[-122.300814,47.821025],"type":"Point"}
}