{
  "type": "Feature",
  "properties": {
    "addr:full":"480 Williams Blvd Richland WA 99354",
    "addr:housenumber":"480",
    "addr:postcode":"99354",
    "addr:street":"Williams Blvd",
    "iso:country":"US",
    "sg:address":"480 Williams Blvd",
    "sg:city":"Richland",
    "sg:classifiers":[
        {
            "category":"Shopping",
            "type":"Retail Goods"
        }
    ],
    "sg:phone":"+1 509 943 5424",
    "sg:postcode":"99354",
    "sg:province":"WA",
    "sg:tags":[
        "merchandise"
    ],
    "wof:name":"Columbia Home Medical",
    "wof:placetype":"venue"
},
  "geometry": {"coordinates":[-119.277934,46.285716],"type":"Point"}
}