{
  "type": "Feature",
  "properties": {
    "addr:full":"1708 54th St Washougal WA 98671",
    "addr:housenumber":"1708",
    "addr:postcode":"98671",
    "addr:street":"54Th St",
    "iso:country":"US",
    "sg:address":"1708 54th St",
    "sg:city":"Washougal",
    "sg:classifiers":[
        {
            "category":"Organizations",
            "subcategory":"Community Association",
            "type":"Services"
        }
    ],
    "sg:phone":"+1 360 835 1777",
    "sg:postcode":"98671",
    "sg:province":"WA",
    "wof:name":"Traffic Boosters",
    "wof:placetype":"venue"
},
  "geometry": {"coordinates":[-122.311263,45.588929],"type":"Point"}
}