{
  "type": "Feature",
  "properties": {
    "addr:full":"1010 N Yakima Ave Tacoma WA 98403",
    "addr:housenumber":"1010",
    "addr:postcode":"98403",
    "addr:street":"N Yakima Ave",
    "iso:country":"US",
    "sg:address":"1010 N Yakima Ave",
    "sg:city":"Tacoma",
    "sg:classifiers":[
        {
            "category":"Shopping",
            "subcategory":"Used Merchandise",
            "type":"Retail Goods"
        }
    ],
    "sg:phone":"+1 253 627 3375",
    "sg:postcode":"98403",
    "sg:province":"WA",
    "wof:name":"CAM & Daves Antiques",
    "wof:placetype":"venue"
},
  "geometry": {"coordinates":[-122.463494,47.267147],"type":"Point"}
}