{
  "type": "Feature",
  "properties": {
    "addr:full":"2196 38th Ave Longview WA 98632",
    "addr:housenumber":"2196",
    "addr:postcode":"98632",
    "addr:street":"38Th Ave",
    "iso:country":"US",
    "sg:address":"2196 38th Ave",
    "sg:city":"Longview",
    "sg:classifiers":[
        {
            "category":"Restaurant",
            "type":"Food & Drink"
        }
    ],
    "sg:menulink":"http://www.allmenus.com/wa/longview-kelso/212710-mcdonalds/menu/",
    "sg:phone":"+1 360 578 2499",
    "sg:postcode":"98632",
    "sg:province":"WA",
    "sg:tags":[
        "burger",
        "american"
    ],
    "wof:name":"McDonald's",
    "wof:placetype":"venue"
},
  "geometry": {"coordinates":[-122.98339799999999,46.155372],"type":"Point"}
}