{
  "type": "Feature",
  "properties": {
    "addr:full":"1102 Broadway Seattle WA 98122",
    "addr:housenumber":"1102",
    "addr:postcode":"98122",
    "addr:street":"Broadway",
    "iso:country":"US",
    "sg:address":"1102 Broadway",
    "sg:city":"Seattle",
    "sg:classifiers":[
        {
            "category":"Professional",
            "subcategory":"Lawyer & Legal Services",
            "type":"Services"
        }
    ],
    "sg:phone":"+1 425 251 5938",
    "sg:postcode":"98122",
    "sg:province":"WA",
    "wof:name":"Dolman Brian L Atty",
    "wof:placetype":"venue"
},
  "geometry": {"coordinates":[-122.320527,47.611472],"type":"Point"}
}