{
  "type": "Feature",
  "properties": {
    "iso:country":"US",
    "sg:address":"711 148th St NE",
    "sg:city":"Arlington",
    "sg:classifiers":[
        {
            "category":"Professional",
            "subcategory":"Management & Consulting",
            "type":"Services"
        }
    ],
    "sg:phone":"+1 360 652 2134",
    "sg:postcode":"98223",
    "sg:province":"WA",
    "wof:name":"Phifer Consulting Group I",
    "wof:placetype":"venue"
},
  "geometry": {"coordinates":[-122.221097,48.130252],"type":"Point"}
}