{
  "type": "Feature",
  "properties": {
    "addr:full":"17008 Larch Way Lynnwood WA 98037",
    "addr:housenumber":"17008",
    "addr:postcode":"98037",
    "addr:street":"Larch Way",
    "iso:country":"US",
    "sg:address":"17008 Larch Way",
    "sg:city":"Lynnwood",
    "sg:classifiers":[
        {
            "category":"Home & Garden",
            "subcategory":"Building Materials",
            "type":"Retail Goods"
        }
    ],
    "sg:phone":"+1 425 742 4522",
    "sg:postcode":"98037",
    "sg:province":"WA",
    "wof:name":"Sherman & Jennings Glass",
    "wof:placetype":"venue"
},
  "geometry": {"coordinates":[-122.24667700000001,47.843434],"type":"Point"}
}