{
  "type": "Feature",
  "properties": {
    "addr:full":"2101 Deer Harbor Rd Eastsound WA 98245",
    "addr:housenumber":"2101",
    "addr:postcode":"98245",
    "addr:street":"Deer Harbor Rd",
    "iso:country":"US",
    "sg:address":"2101 Deer Harbor Rd",
    "sg:city":"Eastsound",
    "sg:classifiers":[
        {
            "category":"Travel",
            "subcategory":"Hotels & Motels",
            "type":"Entertainment"
        }
    ],
    "sg:phone":"+1 360 376 4114",
    "sg:postcode":"98245",
    "sg:province":"WA",
    "sg:tags":[
        "operation"
    ],
    "wof:name":"Cabins On Point",
    "wof:placetype":"venue"
},
  "geometry": {"coordinates":[-122.977186,48.639221],"type":"Point"}
}