{
  "type": "Feature",
  "properties": {
    "addr:full":"13107 Orchard Ave Yakima WA 98908",
    "addr:housenumber":"13107",
    "addr:postcode":"98908",
    "addr:street":"Orchard Ave",
    "iso:country":"US",
    "sg:address":"13107 Orchard Ave",
    "sg:city":"Yakima",
    "sg:classifiers":[
        {
            "category":"Farming",
            "subcategory":"Livestock Farm",
            "type":"Manufacturing & Wholesale Goods"
        }
    ],
    "sg:phone":"+1 509 966 1767",
    "sg:postcode":"98908",
    "sg:province":"WA",
    "sg:tags":[
        "ranch"
    ],
    "wof:name":"Richard Floren",
    "wof:placetype":"venue"
},
  "geometry": {"coordinates":[-120.683116,46.595104],"type":"Point"}
}