{
  "type": "Feature",
  "properties": {
    "addr:full":"527 NE 131st Pl Seattle WA 98125",
    "addr:housenumber":"527",
    "addr:postcode":"98125",
    "addr:street":"Ne 131St Pl",
    "iso:country":"US",
    "sg:address":"527 NE 131st Pl",
    "sg:city":"Seattle",
    "sg:classifiers":[
        {
            "category":"Shopping",
            "subcategory":"Bicycles & Sporting Goods",
            "type":"Retail Goods"
        }
    ],
    "sg:phone":"+1 206 364 4553",
    "sg:postcode":"98125",
    "sg:province":"WA",
    "wof:name":"Sports Plus",
    "wof:placetype":"venue"
},
  "geometry": {"coordinates":[-122.322317,47.723769],"type":"Point"}
}