{
  "type": "Feature",
  "properties": {
    "addr:full":"10115 Greenwood Ave N #233 Seattle WA 98133",
    "addr:housenumber":"10115",
    "addr:postcode":"98133",
    "addr:street":"Greenwood Ave N # 233",
    "iso:country":"US",
    "sg:address":"10115 Greenwood Ave N #233",
    "sg:city":"Seattle",
    "sg:classifiers":[
        {
            "category":"Building & Trades",
            "subcategory":"Electrical",
            "type":"Services"
        }
    ],
    "sg:phone":"+1 206 434 6915",
    "sg:postcode":"98133",
    "sg:province":"WA",
    "sg:tags":[
        "electrician"
    ],
    "sg:website":"exactelectricllc.com",
    "wof:name":"Exact Electric, LLC",
    "wof:placetype":"venue"
},
  "geometry": {"coordinates":[-122.355424,47.702253],"type":"Point"}
}