{
  "type": "Feature",
  "properties": {
    "addr:full":"5005 SW 318th St Federal Way WA 98023",
    "addr:housenumber":"5005",
    "addr:postcode":"98023",
    "addr:street":"Sw 318Th St",
    "iso:country":"US",
    "sg:address":"5005 SW 318th St",
    "sg:city":"Federal Way",
    "sg:classifiers":[
        {
            "category":"Social Services",
            "subcategory":"Child Care",
            "type":"Services"
        }
    ],
    "sg:phone":"+1 253 874 5292",
    "sg:postcode":"98023",
    "sg:province":"WA",
    "sg:tags":[
        "day"
    ],
    "wof:name":"Rainbow Connection Child Care",
    "wof:placetype":"venue"
},
  "geometry": {"coordinates":[-122.39811,47.317071],"type":"Point"}
}