{
  "type": "Feature",
  "properties": {
    "addr:full":"1110 Marine Dr NE Marysville WA 98271",
    "addr:housenumber":"1110",
    "addr:postcode":"98271",
    "addr:street":"Marine Dr Ne",
    "iso:country":"US",
    "sg:address":"1110 Marine Dr NE",
    "sg:city":"Marysville",
    "sg:classifiers":[
        {
            "category":"Building & Trades",
            "subcategory":"Construction",
            "type":"Services"
        }
    ],
    "sg:phone":"+1 425 303 3479",
    "sg:postcode":"98271",
    "sg:province":"WA",
    "sg:tags":[
        "nonresidential"
    ],
    "wof:name":"Dome Construction Co",
    "wof:placetype":"venue"
},
  "geometry": {"coordinates":[-122.21243699999999,48.050416],"type":"Point"}
}