{
  "type": "Feature",
  "properties": {
    "addr:full":"2547 Perkins Ln W Seattle WA 98199",
    "addr:housenumber":"2547",
    "addr:postcode":"98199",
    "addr:street":"Perkins Ln W",
    "iso:country":"US",
    "sg:address":"2547 Perkins Ln W",
    "sg:city":"Seattle",
    "sg:classifiers":[
        {
            "category":"Professional",
            "subcategory":"Engineering",
            "type":"Services"
        }
    ],
    "sg:phone":"+1 206 618 8632",
    "sg:postcode":"98199",
    "sg:province":"WA",
    "sg:tags":[
        "architect",
        "naval"
    ],
    "wof:name":"Headway Marine",
    "wof:placetype":"venue"
},
  "geometry": {"coordinates":[-122.40526699999999,47.635141],"type":"Point"}
}