{
  "type": "Feature",
  "properties": {
    "addr:full":"5456 Beach Dr SW Seattle WA 98136",
    "addr:housenumber":"5456",
    "addr:postcode":"98136",
    "addr:street":"Beach Dr Sw",
    "iso:country":"US",
    "sg:address":"5456 Beach Dr SW",
    "sg:city":"Seattle",
    "sg:classifiers":[
        {
            "category":"Professional",
            "type":"Services"
        }
    ],
    "sg:phone":"+1 206 856 6802",
    "sg:postcode":"98136",
    "sg:province":"WA",
    "wof:name":"Damn Thirsty",
    "wof:placetype":"venue"
},
  "geometry": {"coordinates":[-122.398319,47.54594],"type":"Point"}
}