{
  "type": "Feature",
  "properties": {
    "addr:full":"8811 S Tacoma Way # 105 Lakewood WA 98499",
    "addr:housenumber":"8811",
    "addr:postcode":"98499",
    "addr:street":"S Tacoma Way # 105",
    "iso:country":"US",
    "sg:address":"8811 S Tacoma Way # 105",
    "sg:city":"Lakewood",
    "sg:classifiers":[
        {
            "category":"Professional",
            "subcategory":"Lawyer & Legal Services",
            "type":"Services"
        }
    ],
    "sg:phone":"+1 253 589 8779",
    "sg:postcode":"98499",
    "sg:province":"WA",
    "sg:tags":[
        "attorney",
        "practice",
        "plan"
    ],
    "wof:name":"Kim Naomi & Co",
    "wof:placetype":"venue"
},
  "geometry": {"coordinates":[-122.48380899999999,47.177127],"type":"Point"}
}