{
  "type": "Feature",
  "properties": {
    "addr:full":"12926 Mukilteo Speedway Ste 3 Lynnwood WA 98087",
    "addr:housenumber":"12926",
    "addr:postcode":"98087",
    "addr:street":"Mukilteo Speedway Ste 3",
    "iso:country":"US",
    "sg:address":"12926 Mukilteo Speedway Ste 3",
    "sg:city":"Lynnwood",
    "sg:phone":"+1 425 423 8569",
    "sg:postcode":"98087",
    "sg:province":"WA",
    "wof:name":"Chiangmai Thai Restaurant",
    "wof:placetype":"venue"
},
  "geometry": {"coordinates":[-122.27870299999999,47.880627],"type":"Point"}
}