{
  "type": "Feature",
  "properties": {
    "addr:full":"24112 77th Ave E Graham WA 98338",
    "addr:housenumber":"24112",
    "addr:postcode":"98338",
    "addr:street":"77Th Ave E",
    "iso:country":"US",
    "sg:address":"24112 77th Ave E",
    "sg:city":"Graham",
    "sg:classifiers":[
        {
            "category":"Wholesale",
            "subcategory":"Vending Machines",
            "type":"Manufacturing & Wholesale Goods"
        }
    ],
    "sg:phone":"+1 253 847 1728",
    "sg:postcode":"98338",
    "sg:province":"WA",
    "sg:tags":[
        "operator"
    ],
    "wof:name":"Nical Vending",
    "wof:placetype":"venue"
},
  "geometry": {"coordinates":[-122.32876899999999,47.03751],"type":"Point"}
}