{
  "type": "Feature",
  "properties": {
    "addr:full":"1206 E Main Ave Puyallup WA 98372",
    "addr:housenumber":"1206",
    "addr:postcode":"98372",
    "addr:street":"E Main Ave",
    "iso:country":"US",
    "sg:address":"1206 E Main Ave",
    "sg:city":"Puyallup",
    "sg:classifiers":[
        {
            "category":"Shopping",
            "subcategory":"Crafts & Fabrics",
            "type":"Retail Goods"
        }
    ],
    "sg:phone":"+1 253 845 1532",
    "sg:postcode":"98372",
    "sg:province":"WA",
    "sg:tags":[
        "material",
        "quilting",
        "supply"
    ],
    "sg:website":"www.quiltbarn.com",
    "wof:name":"Quilt Barn",
    "wof:placetype":"venue"
},
  "geometry": {"coordinates":[-122.27411499999999,47.191835],"type":"Point"}
}