{
  "type": "Feature",
  "properties": {
    "addr:full":"64 Main St Cathlamet WA 98612",
    "addr:housenumber":"64",
    "addr:postcode":"98612",
    "addr:street":"Main St",
    "iso:country":"US",
    "sg:address":"64 Main St",
    "sg:city":"Cathlamet",
    "sg:classifiers":[
        {
            "category":"Government",
            "subcategory":"Court House",
            "type":"Public Place"
        }
    ],
    "sg:phone":"+1 360 795 3558",
    "sg:postcode":"98612",
    "sg:province":"WA",
    "sg:tags":[
        "county"
    ],
    "wof:name":"Wahkiakum Superior Court Clerk",
    "wof:placetype":"venue"
},
  "geometry": {"coordinates":[-123.384394,46.202844],"type":"Point"}
}