{
  "type": "Feature",
  "properties": {
    "addr:full":"16915 NE 98th Ct Redmond WA 98052",
    "addr:housenumber":"16915",
    "addr:postcode":"98052",
    "addr:street":"Ne 98Th Ct",
    "iso:country":"US",
    "sg:address":"16915 NE 98th Ct",
    "sg:city":"Redmond",
    "sg:classifiers":[
        {
            "category":"Professional",
            "subcategory":"Accounting & Tax Preparation",
            "type":"Services"
        }
    ],
    "sg:phone":"+1 425 883 2141",
    "sg:postcode":"98052",
    "sg:province":"WA",
    "wof:name":"Charlene Irwin",
    "wof:placetype":"venue"
},
  "geometry": {"coordinates":[-122.1123,47.687765],"type":"Point"}
}