{
  "type": "Feature",
  "properties": {
    "addr:full":"410 5th Ave SW Olympia WA 98501",
    "addr:housenumber":"410",
    "addr:postcode":"98501",
    "addr:street":"5Th Ave Sw",
    "iso:country":"US",
    "sg:address":"410 5th Ave SW",
    "sg:city":"Olympia",
    "sg:classifiers":[
        {
            "category":"Government",
            "subcategory":"Office",
            "type":"Public Place"
        }
    ],
    "sg:phone":"+1 360 753 1500",
    "sg:postcode":"98501",
    "sg:province":"WA",
    "sg:tags":[
        "state"
    ],
    "wof:name":"Office Administrative Svc",
    "wof:placetype":"venue"
},
  "geometry": {"coordinates":[-122.906539,47.043808],"type":"Point"}
}