{
  "type": "Feature",
  "properties": {
    "addr:full":"5007 Pacific Hwy E Fife WA 98424",
    "addr:housenumber":"5007",
    "addr:postcode":"98424",
    "addr:street":"Pacific Hwy E",
    "iso:country":"US",
    "sg:address":"5007 Pacific Hwy E",
    "sg:city":"Fife",
    "sg:classifiers":[
        {
            "category":"Wholesale",
            "subcategory":"Electrical",
            "type":"Manufacturing & Wholesale Goods"
        }
    ],
    "sg:phone":"+1 253 922 3300",
    "sg:postcode":"98424",
    "sg:province":"WA",
    "sg:tags":[
        "fire",
        "alarm",
        "system"
    ],
    "wof:name":"Emerald Security Svc",
    "wof:placetype":"venue"
},
  "geometry": {"coordinates":[-122.35974400000001,47.243143],"type":"Point"}
}