{
  "type": "Feature",
  "properties": {
    "addr:full":"23311 54th St E Buckley WA 98321",
    "addr:housenumber":"23311",
    "addr:postcode":"98321",
    "addr:street":"54Th St",
    "iso:country":"US",
    "sg:address":"23311 54th St E",
    "sg:city":"Buckley",
    "sg:classifiers":[
        {
            "category":"Airport",
            "type":"Transportation"
        }
    ],
    "sg:phone":"+1 253 862 6293",
    "sg:postcode":"98321",
    "sg:province":"WA",
    "wof:name":"Accipiter Corp",
    "wof:placetype":"venue"
},
  "geometry": {"coordinates":[-122.118673,47.208317],"type":"Point"}
}