{
  "type": "Feature",
  "properties": {
    "iso:country":"US",
    "sg:address":"2700 NE Andresen Rd",
    "sg:city":"Vancouver",
    "sg:classifiers":[
        {
            "category":"Banks & Credit Unions",
            "subcategory":"Investment Brokerage",
            "type":"Services"
        }
    ],
    "sg:phone":"+1 360 597 0043",
    "sg:postcode":"98661",
    "sg:province":"WA",
    "sg:tags":[
        "consultant",
        "planning",
        "financial"
    ],
    "wof:name":"Gallegos Luhn & Assoc Inc",
    "wof:placetype":"venue"
},
  "geometry": {"coordinates":[-122.60089000000001,45.642399],"type":"Point"}
}