{
  "type": "Feature",
  "properties": {
    "iso:country":"US",
    "sg:address":"8698 Rd K NW",
    "sg:city":"Quincy",
    "sg:classifiers":[
        {
            "category":"Restaurant",
            "type":"Food & Drink"
        }
    ],
    "sg:phone":"+1 509 787 3857",
    "sg:postcode":"98848",
    "sg:province":"WA",
    "sg:tags":[
        "eating"
    ],
    "wof:name":"Stockyard Cafe",
    "wof:placetype":"venue"
},
  "geometry": {"coordinates":[-119.72517499999999,47.209892],"type":"Point"}
}