{
  "type": "Feature",
  "properties": {
    "addr:full":"747 Douglas Falls Rd Colville WA 99114",
    "addr:housenumber":"747",
    "addr:postcode":"99114",
    "addr:street":"Douglas Falls Rd",
    "iso:country":"US",
    "sg:address":"747 Douglas Falls Rd",
    "sg:city":"Colville",
    "sg:classifiers":[
        {
            "category":"Health Services",
            "subcategory":"Clinic",
            "type":"Services"
        }
    ],
    "sg:phone":"+1 509 684 6988",
    "sg:postcode":"99114",
    "sg:province":"WA",
    "wof:name":"Olson Linda Rn Nurse Delegate",
    "wof:placetype":"venue"
},
  "geometry": {"coordinates":[-117.91793699999999,48.629325],"type":"Point"}
}