{
  "type": "Feature",
  "properties": {
    "iso:country":"US",
    "sg:address":"61 NE Mountain Lake Dr",
    "sg:city":"Belfair",
    "sg:classifiers":[
        {
            "category":"Professional",
            "subcategory":"Management & Consulting",
            "type":"Services"
        }
    ],
    "sg:phone":"+1 360 275 5774",
    "sg:postcode":"98528",
    "sg:province":"WA",
    "sg:tags":[
        "business"
    ],
    "wof:name":"Livewire Technical Consulting",
    "wof:placetype":"venue"
},
  "geometry": {"coordinates":[-122.82646099999999,47.520252],"type":"Point"}
}