{
  "type": "Feature",
  "properties": {
    "addr:full":"7811 Pioneer Way Gig Harbor WA 98335",
    "addr:housenumber":"7811",
    "addr:postcode":"98335",
    "addr:street":"Pioneer Way",
    "iso:country":"US",
    "sg:address":"7811 Pioneer Way",
    "sg:city":"Gig Harbor",
    "sg:classifiers":[
        {
            "category":"Shopping",
            "subcategory":"Jewelry",
            "type":"Retail Goods"
        }
    ],
    "sg:phone":"+1 253 853 4579",
    "sg:postcode":"98335",
    "sg:province":"WA",
    "wof:name":"Reverence Designs",
    "wof:placetype":"venue"
},
  "geometry": {"coordinates":[-122.580878,47.329228],"type":"Point"}
}