{
  "type": "Feature",
  "properties": {
    "addr:full":"3424 S 288th St Auburn WA 98001",
    "addr:housenumber":"3424",
    "addr:postcode":"98001",
    "addr:street":"S 288Th St",
    "iso:country":"US",
    "sg:address":"3424 S 288th St",
    "sg:city":"Auburn",
    "sg:classifiers":[
        {
            "category":"Retail",
            "subcategory":"Repair Shop",
            "type":"Services"
        }
    ],
    "sg:phone":"+1 253 946 8700",
    "sg:postcode":"98001",
    "sg:province":"WA",
    "wof:name":"Georgettes Collectibles",
    "wof:placetype":"venue"
},
  "geometry": {"coordinates":[-122.28666200000001,47.343414],"type":"Point"}
}