{
  "type": "Feature",
  "properties": {
    "addr:full":"14803 SE Newport Way Bellevue WA 98006",
    "addr:postcode":"14803;98006",
    "addr:street":"Se Newport Way",
    "iso:country":"US",
    "sg:address":"14803 SE Newport Way",
    "sg:city":"Bellevue",
    "sg:classifiers":[
        {
            "category":"Retail",
            "subcategory":"Portrait Studio",
            "type":"Services"
        }
    ],
    "sg:phone":"+1 425 641 0565",
    "sg:postcode":"98006",
    "sg:province":"WA",
    "sg:tags":[
        "photo"
    ],
    "wof:name":"Lifetime Photography",
    "wof:placetype":"venue"
},
  "geometry": {"coordinates":[-122.144311,47.5702],"type":"Point"}
}