{
  "type": "Feature",
  "properties": {
    "addr:full":"841 Central Ave N Kent WA 98032",
    "addr:housenumber":"841",
    "addr:postcode":"98032",
    "addr:street":"Central Ave N",
    "iso:country":"US",
    "sg:address":"841 Central Ave N",
    "sg:city":"Kent",
    "sg:classifiers":[
        {
            "category":"Manufacturing",
            "subcategory":"Printing",
            "type":"Manufacturing & Wholesale Goods"
        }
    ],
    "sg:phone":"+1 253 852 6020",
    "sg:postcode":"98032",
    "sg:province":"WA",
    "sg:tags":[
        "photocopying",
        "commercial"
    ],
    "wof:name":"Minuteman Press-Kent",
    "wof:placetype":"venue"
},
  "geometry": {"coordinates":[-122.231167,47.387966],"type":"Point"}
}