{
  "type": "Feature",
  "properties": {
    "addr:full":"403 Jackrabbit Ln Oak Harbor WA 98277",
    "addr:housenumber":"403",
    "addr:postcode":"98277",
    "addr:street":"Jackrabbit Ln",
    "iso:country":"US",
    "sg:address":"403 Jackrabbit Ln",
    "sg:city":"Oak Harbor",
    "sg:classifiers":[
        {
            "category":"Professional",
            "subcategory":"Secretarial Services",
            "type":"Services"
        }
    ],
    "sg:phone":"+1 360 675 0825",
    "sg:postcode":"98277",
    "sg:province":"WA",
    "sg:tags":[
        "reporting"
    ],
    "wof:name":"C & M Secretarial",
    "wof:placetype":"venue"
},
  "geometry": {"coordinates":[-122.59177,48.364935],"type":"Point"}
}