{
  "type": "Feature",
  "properties": {
    "addr:full":"150 9th St Clarkston WA 99403",
    "addr:housenumber":"150",
    "addr:postcode":"99403",
    "addr:street":"9Th St",
    "iso:country":"US",
    "sg:address":"150 9th St",
    "sg:city":"Clarkston",
    "sg:classifiers":[
        {
            "category":"Wholesale",
            "subcategory":"Groceries",
            "type":"Manufacturing & Wholesale Goods"
        }
    ],
    "sg:phone":"+1 509 758 4069",
    "sg:postcode":"99403",
    "sg:province":"WA",
    "sg:tags":[
        "food",
        "snack"
    ],
    "wof:name":"Frito-Lay",
    "wof:placetype":"venue"
},
  "geometry": {"coordinates":[-117.049583,46.424863],"type":"Point"}
}