{
  "type": "Feature",
  "properties": {
    "addr:full":"21109 Pioneer Way Edmonds WA 98026",
    "addr:housenumber":"21109",
    "addr:postcode":"98026",
    "addr:street":"Pioneer Way",
    "iso:country":"US",
    "sg:address":"21109 Pioneer Way",
    "sg:city":"Edmonds",
    "sg:classifiers":[
        {
            "category":"Professional",
            "subcategory":"Management & Consulting",
            "type":"Services"
        }
    ],
    "sg:phone":"+1 425 776 7824",
    "sg:postcode":"98026",
    "sg:province":"WA",
    "sg:tags":[
        "business"
    ],
    "wof:name":"Vaudrin Assoc",
    "wof:placetype":"venue"
},
  "geometry": {"coordinates":[-122.352456,47.806708],"type":"Point"}
}