{
  "type": "Feature",
  "properties": {
    "addr:full":"18024 49th Pl W Lynnwood WA 98037",
    "addr:housenumber":"18024",
    "addr:postcode":"98037",
    "addr:street":"49Th Pl W",
    "iso:country":"US",
    "sg:address":"18024 49th Pl W",
    "sg:city":"Lynnwood",
    "sg:classifiers":[
        {
            "category":"Manufacturing",
            "subcategory":"Wood Products",
            "type":"Manufacturing & Wholesale Goods"
        }
    ],
    "sg:phone":"+1 425 210 0532",
    "sg:postcode":"98037",
    "sg:province":"WA",
    "sg:tags":[
        "house",
        "construction",
        "mfg"
    ],
    "wof:name":"Classichome Remodel & Repair",
    "wof:placetype":"venue"
},
  "geometry": {"coordinates":[-122.300256,47.829794],"type":"Point"}
}