{
  "type": "Feature",
  "properties": {
    "addr:full":"7716 W Dradie St Pasco WA 99301",
    "addr:housenumber":"7716",
    "addr:postcode":"99301",
    "addr:street":"W Dradie St",
    "iso:country":"US",
    "sg:address":"7716 W Dradie St",
    "sg:city":"Pasco",
    "sg:classifiers":[
        {
            "category":"Building & Trades",
            "subcategory":"Electrical",
            "type":"Services"
        }
    ],
    "sg:phone":"+1 509 547 6588",
    "sg:postcode":"99301",
    "sg:province":"WA",
    "sg:tags":[
        "electrical",
        "contractor"
    ],
    "wof:name":"Cree Electric Inc",
    "wof:placetype":"venue"
},
  "geometry": {"coordinates":[-119.194581,46.254321],"type":"Point"}
}