{
  "type": "Feature",
  "properties": {
    "iso:country":"US",
    "sg:address":"204 US Hwy 12",
    "sg:city":"Chehalis",
    "sg:classifiers":[
        {
            "category":"Shopping",
            "subcategory":"Bicycles & Sporting Goods",
            "type":"Retail Goods"
        }
    ],
    "sg:phone":"+1 360 262 0810",
    "sg:postcode":"98532",
    "sg:province":"WA",
    "sg:tags":[
        "equipment",
        "archery",
        "supply"
    ],
    "wof:name":"Archery House",
    "wof:placetype":"venue"
},
  "geometry": {"coordinates":[-122.861053,46.545728],"type":"Point"}
}