{
  "type": "Feature",
  "properties": {
    "addr:full":"240 Bald Rd Touchet WA 99360",
    "addr:housenumber":"240",
    "addr:postcode":"99360",
    "addr:street":"Bald Rd",
    "iso:country":"US",
    "sg:address":"240 Bald Rd",
    "sg:city":"Touchet",
    "sg:classifiers":[
        {
            "category":"Farming",
            "subcategory":"Farm",
            "type":"Manufacturing & Wholesale Goods"
        }
    ],
    "sg:phone":"+1 509 394 2625",
    "sg:postcode":"99360",
    "sg:province":"WA",
    "wof:name":"Saranto Farms Inc",
    "wof:placetype":"venue"
},
  "geometry": {"coordinates":[-118.690788,46.024726],"type":"Point"}
}