{
  "type": "Feature",
  "properties": {
    "addr:full":"8003 Seaview Ave NW Seattle WA 98117",
    "addr:housenumber":"8003",
    "addr:postcode":"98117",
    "addr:street":"Seaview Ave Nw",
    "iso:country":"US",
    "sg:address":"8003 Seaview Ave NW",
    "sg:city":"Seattle",
    "sg:classifiers":[
        {
            "category":"Fast Food",
            "type":"Food & Drink"
        },
        {
            "category":"Restaurant",
            "type":"Food & Drink"
        },
        {
            "category":"Ice Cream",
            "type":"Food & Drink"
        }
    ],
    "sg:phone":"+1 206 782 6598",
    "sg:postcode":"98117",
    "sg:province":"WA",
    "sg:tags":[
        "frozen",
        "traditional",
        "american",
        "yogurt",
        "burger"
    ],
    "wof:name":"Little Coney",
    "wof:placetype":"venue"
},
  "geometry": {"coordinates":[-122.40272899999999,47.686476],"type":"Point"}
}