{
  "type": "Feature",
  "properties": {
    "addr:full":"8528 E Side Dr NE Tacoma WA 98422",
    "addr:housenumber":"8528",
    "addr:postcode":"98422",
    "addr:street":"E Side Dr Ne",
    "iso:country":"US",
    "sg:address":"8528 E Side Dr NE",
    "sg:city":"Tacoma",
    "sg:classifiers":[
        {
            "category":"Travel",
            "subcategory":"Travel Agent",
            "type":"Entertainment"
        }
    ],
    "sg:phone":"+1 253 838 6652",
    "sg:postcode":"98422",
    "sg:province":"WA",
    "sg:tags":[
        "agency"
    ],
    "wof:name":"Golf Holidays",
    "wof:placetype":"venue"
},
  "geometry": {"coordinates":[-122.42348699999999,47.316986],"type":"Point"}
}