{
  "type": "Feature",
  "properties": {
    "iso:country":"US",
    "sg:address":"13623 184th Ave NE",
    "sg:city":"Woodinville",
    "sg:classifiers":[
        {
            "category":"Professional",
            "subcategory":"Management & Consulting",
            "type":"Services"
        }
    ],
    "sg:phone":"+1 425 861 8866",
    "sg:postcode":"98072",
    "sg:province":"WA",
    "sg:tags":[
        "business"
    ],
    "wof:name":"Traffic Count Consultants Inc",
    "wof:placetype":"venue"
},
  "geometry": {"coordinates":[-122.094093,47.722132],"type":"Point"}
}