{
  "type": "Feature",
  "properties": {
    "addr:full":"2233 California Ave SW Seattle WA 98116",
    "addr:housenumber":"2233",
    "addr:postcode":"98116",
    "addr:street":"California Ave Sw",
    "iso:country":"US",
    "sg:address":"2233 California Ave SW",
    "sg:city":"Seattle",
    "sg:classifiers":[
        {
            "category":"Retail",
            "subcategory":"Storage",
            "type":"Services"
        }
    ],
    "sg:phone":"+1 800 206 6983",
    "sg:postcode":"98116",
    "sg:province":"WA",
    "sg:tags":[
        "household",
        "commercial"
    ],
    "sg:website":"http://gotshed.com",
    "wof:name":"Portable Storage Of America",
    "wof:placetype":"venue"
},
  "geometry": {"coordinates":[-122.38644600000001,47.583687],"type":"Point"}
}