{
  "type": "Feature",
  "properties": {
    "addr:full":"295 NE Gilman Blvd Issaquah WA 98027",
    "addr:housenumber":"295",
    "addr:postcode":"98027",
    "addr:street":"Ne Gilman Blvd",
    "iso:country":"US",
    "sg:address":"295 NE Gilman Blvd",
    "sg:city":"Issaquah",
    "sg:classifiers":[
        {
            "category":"Professional",
            "subcategory":"Management & Consulting",
            "type":"Services"
        }
    ],
    "sg:phone":"+1 425 395 0010",
    "sg:postcode":"98027",
    "sg:province":"WA",
    "sg:tags":[
        "environmental"
    ],
    "wof:name":"Epi",
    "wof:placetype":"venue"
},
  "geometry": {"coordinates":[-122.031132,47.53429],"type":"Point"}
}