{
  "type": "Feature",
  "properties": {
    "addr:full":"3709 Forest Beach Dr NW Gig Harbor WA 98335",
    "addr:housenumber":"3709",
    "addr:postcode":"98335",
    "addr:street":"Forest Beach Dr Nw",
    "iso:country":"US",
    "sg:address":"3709 Forest Beach Dr NW",
    "sg:city":"Gig Harbor",
    "sg:classifiers":[
        {
            "category":"Professional",
            "subcategory":"Computer Services",
            "type":"Services"
        }
    ],
    "sg:phone":"+1 253 265 1444",
    "sg:postcode":"98335",
    "sg:province":"WA",
    "sg:tags":[
        "website",
        "design"
    ],
    "wof:name":"Intershock Design Studio",
    "wof:placetype":"venue"
},
  "geometry": {"coordinates":[-122.688849,47.29389],"type":"Point"}
}