{
  "type": "Feature",
  "properties": {
    "addr:full":"6011 152nd Ave SE Bellevue WA 98006",
    "addr:housenumber":"6011",
    "addr:postcode":"98006",
    "addr:street":"152Nd Ave Se",
    "iso:country":"US",
    "sg:address":"6011 152nd Ave SE",
    "sg:city":"Bellevue",
    "sg:classifiers":[
        {
            "category":"Professional",
            "subcategory":"Business Services",
            "type":"Services"
        }
    ],
    "sg:phone":"+1 425 644 7728",
    "sg:postcode":"98006",
    "sg:province":"WA",
    "sg:tags":[
        "organizing",
        "services-household"
    ],
    "wof:name":"Itech Management",
    "wof:placetype":"venue"
},
  "geometry": {"coordinates":[-122.137719,47.548823],"type":"Point"}
}