{
  "type": "Feature",
  "properties": {
    "addr:full":"1123 California Ave SW Seattle WA 98116",
    "addr:housenumber":"1123",
    "addr:postcode":"98116",
    "addr:street":"California Ave Sw",
    "iso:country":"US",
    "sg:address":"1123 California Ave SW",
    "sg:city":"Seattle",
    "sg:classifiers":[
        {
            "category":"Professional",
            "subcategory":"Management & Consulting",
            "type":"Services"
        }
    ],
    "sg:phone":"+1 206 937 3096",
    "sg:postcode":"98116",
    "sg:province":"WA",
    "sg:tags":[
        "engineering",
        "business"
    ],
    "wof:name":"Michael J Reberg",
    "wof:placetype":"venue"
},
  "geometry": {"coordinates":[-122.38676100000001,47.593136],"type":"Point"}
}