{
  "type": "Feature",
  "properties": {
    "addr:full":"32410 NE 202nd St Duvall WA 98019",
    "addr:housenumber":"32410",
    "addr:postcode":"98019",
    "addr:street":"Ne 202Nd St",
    "iso:country":"US",
    "sg:address":"32410 NE 202nd St",
    "sg:city":"Duvall",
    "sg:classifiers":[
        {
            "category":"Arena",
            "subcategory":"Sports Club",
            "type":"Entertainment"
        }
    ],
    "sg:phone":"+1 425 788 3002",
    "sg:postcode":"98019",
    "sg:province":"WA",
    "wof:name":"Valley Umpires Association",
    "wof:placetype":"venue"
},
  "geometry": {"coordinates":[-121.904428,47.773357],"type":"Point"}
}