{
  "type": "Feature",
  "properties": {
    "addr:full":"545 E Wellesley Ave Spokane WA 99207",
    "addr:housenumber":"545",
    "addr:postcode":"99207",
    "addr:street":"E Wellesley Ave",
    "iso:country":"US",
    "sg:address":"545 E Wellesley Ave",
    "sg:city":"Spokane",
    "sg:classifiers":[
        {
            "category":"Organizations",
            "subcategory":"Religious Organization",
            "type":"Services"
        }
    ],
    "sg:phone":"+1 509 489 8073",
    "sg:postcode":"99207",
    "sg:province":"WA",
    "sg:tags":[
        "church"
    ],
    "sg:website":"www.zionchristiancenter.org",
    "wof:name":"Zion Christian Ctr",
    "wof:placetype":"venue"
},
  "geometry": {"coordinates":[-117.40152,47.700743],"type":"Point"}
}