{
  "type": "Feature",
  "properties": {
    "addr:full":"2263 W Mockingbird Ln Othello WA 99344",
    "addr:housenumber":"2263",
    "addr:postcode":"99344",
    "addr:street":"W Mockingbird Ln Othello",
    "iso:country":"US",
    "sg:address":"2263 W Mockingbird Ln",
    "sg:city":"Othello",
    "sg:classifiers":[
        {
            "category":"Real Estate",
            "subcategory":"Real Estate Agent",
            "type":"Services"
        }
    ],
    "sg:phone":"+1 509 488 9940",
    "sg:postcode":"99344",
    "sg:province":"WA",
    "wof:name":"Para Ranch Lands Inc",
    "wof:placetype":"venue"
},
  "geometry": {"coordinates":[-119.210463,46.796311],"type":"Point"}
}