{
  "type": "Feature",
  "properties": {
    "addr:full":"408 T St SE Olympia WA 98501",
    "addr:housenumber":"408",
    "addr:postcode":"98501",
    "addr:street":"T St Se",
    "iso:country":"US",
    "sg:address":"408 T St SE",
    "sg:city":"Olympia",
    "sg:classifiers":[
        {
            "category":"Manufacturing",
            "subcategory":"Tools & Machinery",
            "type":"Manufacturing & Wholesale Goods"
        }
    ],
    "sg:phone":"+1 360 943 0405",
    "sg:postcode":"98501",
    "sg:province":"WA",
    "sg:tags":[
        "pattern",
        "industrial",
        "mfg"
    ],
    "wof:name":"Sandi Gray Custom Pattern",
    "wof:placetype":"venue"
},
  "geometry": {"coordinates":[-122.899489,46.996311],"type":"Point"}
}