{
  "type": "Feature",
  "properties": {
    "iso:country":"US",
    "sg:address":"10610 SE Kent Kangley Rd",
    "sg:city":"Kent",
    "sg:classifiers":[
        {
            "category":"Home & Garden",
            "subcategory":"Hardware",
            "type":"Retail Goods"
        }
    ],
    "sg:phone":"+1 425 271 0594",
    "sg:postcode":"98030",
    "sg:province":"WA",
    "wof:name":"Rainier Properties",
    "wof:placetype":"venue"
},
  "geometry": {"coordinates":[-122.198915,47.37154],"type":"Point"}
}