{
  "type": "Feature",
  "properties": {
    "addr:full":"1616 S 325th St Federal Way WA 98003",
    "addr:housenumber":"1616",
    "addr:postcode":"98003",
    "addr:street":"S 325Th St",
    "iso:country":"US",
    "sg:address":"1616 S 325th St",
    "sg:city":"Federal Way",
    "sg:classifiers":[
        {
            "category":"Restaurant",
            "type":"Food & Drink"
        }
    ],
    "sg:phone":"+1 253 927 4045",
    "sg:postcode":"98003",
    "sg:province":"WA",
    "sg:tags":[
        "lounge"
    ],
    "wof:name":"Diamond Jim's",
    "wof:placetype":"venue"
},
  "geometry": {"coordinates":[-122.312096,47.310685],"type":"Point"}
}