{
  "type": "Feature",
  "properties": {
    "addr:full":"3011 177th Ave NE Redmond WA 98052",
    "addr:housenumber":"3011",
    "addr:postcode":"98052",
    "addr:street":"177Th Ave Ne",
    "iso:country":"US",
    "sg:address":"3011 177th Ave NE",
    "sg:city":"Redmond",
    "sg:classifiers":[
        {
            "category":"Shopping",
            "subcategory":"Crafts & Fabrics",
            "type":"Retail Goods"
        },
        {
            "category":"Wholesale",
            "subcategory":"Books, Periodicals, & Newspapers",
            "type":"Manufacturing & Wholesale Goods"
        }
    ],
    "sg:phone":"+1 425 881 2846",
    "sg:postcode":"98052",
    "sg:province":"WA",
    "sg:tags":[
        "canvas",
        "manufacturer",
        "canvas-wholesale"
    ],
    "sg:website":"http://www.carrsails.com",
    "wof:name":"Rod Carr Sailmaker",
    "wof:placetype":"venue"
},
  "geometry": {"coordinates":[-122.10362600000001,47.637189],"type":"Point"}
}