{
  "type": "Feature",
  "properties": {
    "addr:full":"13621 NE 136th Pl Kirkland WA 98034",
    "addr:housenumber":"13621",
    "addr:postcode":"98034",
    "addr:street":"Ne 136Th Pl",
    "iso:country":"US",
    "sg:address":"13621 NE 136th Pl",
    "sg:city":"Kirkland",
    "sg:classifiers":[
        {
            "category":"Professional",
            "subcategory":"Computer Services",
            "type":"Services"
        }
    ],
    "sg:phone":"+1 425 823 1632",
    "sg:postcode":"98034",
    "sg:province":"WA",
    "sg:tags":[
        "programing",
        "custom"
    ],
    "wof:name":"Meta Play Inc",
    "wof:placetype":"venue"
},
  "geometry": {"coordinates":[-122.15730000000001,47.722417],"type":"Point"}
}