{
  "type": "Feature",
  "properties": {
    "addr:full":"17008 SE 14th Ln Bellevue WA 98008",
    "addr:postcode":"17008;98008",
    "addr:street":"Se 14Th Ln",
    "iso:country":"US",
    "sg:address":"17008 SE 14th Ln",
    "sg:city":"Bellevue",
    "sg:classifiers":[
        {
            "category":"Professional",
            "subcategory":"Business Services",
            "type":"Services"
        }
    ],
    "sg:phone":"+1 425 641 8502",
    "sg:postcode":"98008",
    "sg:province":"WA",
    "sg:tags":[
        "holding"
    ],
    "wof:name":"A Development Stage Company",
    "wof:placetype":"venue"
},
  "geometry": {"coordinates":[-122.111811,47.596815],"type":"Point"}
}