{
  "type": "Feature",
  "properties": {
    "addr:full":"5610 75th St W Tacoma WA 98499",
    "addr:housenumber":"5610",
    "addr:postcode":"98499",
    "addr:street":"75Th St W",
    "iso:country":"US",
    "sg:address":"5610 75th St W",
    "sg:city":"Tacoma",
    "sg:classifiers":[
        {
            "category":"Insurance",
            "subcategory":"Insurance Agent",
            "type":"Services"
        }
    ],
    "sg:phone":"+1 253 473 3930",
    "sg:postcode":"98499",
    "sg:province":"WA",
    "wof:name":"Wyman & Assoc Inc",
    "wof:placetype":"venue"
},
  "geometry": {"coordinates":[-122.51128300000001,47.189296],"type":"Point"}
}