{
  "type": "Feature",
  "properties": {
    "addr:full":"3820 Bridgeport Way W University Place WA 98466",
    "addr:housenumber":"3820",
    "addr:postcode":"98466",
    "addr:street":"Bridgeport Way W;Place",
    "iso:country":"US",
    "sg:address":"3820 Bridgeport Way W",
    "sg:city":"University Place",
    "sg:classifiers":[
        {
            "category":"Restaurant",
            "type":"Food & Drink"
        }
    ],
    "sg:phone":"+1 253 565 2265",
    "sg:postcode":"98466",
    "sg:province":"WA",
    "wof:name":"El Toro",
    "wof:placetype":"venue"
},
  "geometry": {"coordinates":[-122.53715699999999,47.223147],"type":"Point"}
}