{
  "type": "Feature",
  "properties": {
    "addr:full":"3423 Rosedale St NW Gig Harbor WA 98335",
    "addr:housenumber":"3423",
    "addr:postcode":"98335",
    "addr:street":"Rosedale St Nw",
    "iso:country":"US",
    "sg:address":"3423 Rosedale St NW",
    "sg:city":"Gig Harbor",
    "sg:classifiers":[
        {
            "category":"Personal",
            "type":"Services"
        }
    ],
    "sg:phone":"+1 253 858 7602",
    "sg:postcode":"98335",
    "sg:province":"WA",
    "wof:name":"Vh Therapeutic Massage",
    "wof:placetype":"venue"
},
  "geometry": {"coordinates":[-122.58357100000001,47.330783],"type":"Point"}
}