{
  "type": "Feature",
  "properties": {
    "addr:full":"172 Lighthouse Ln Friday Harbor WA 98250",
    "addr:housenumber":"172",
    "addr:postcode":"98250",
    "addr:street":"Lighthouse Ln",
    "iso:country":"US",
    "sg:address":"172 Lighthouse Ln",
    "sg:city":"Friday Harbor",
    "sg:classifiers":[
        {
            "category":"Professional",
            "subcategory":"Management & Consulting",
            "type":"Services"
        }
    ],
    "sg:phone":"+1 360 378 3123",
    "sg:postcode":"98250",
    "sg:province":"WA",
    "sg:tags":[
        "marketing",
        "consultant"
    ],
    "sg:website":"www.networkdirectinc.com",
    "wof:name":"Network Direct Inc",
    "wof:placetype":"venue"
},
  "geometry": {"coordinates":[-122.96561199999999,48.454121],"type":"Point"}
}