{
  "type": "Feature",
  "properties": {
    "iso:country":"US",
    "sg:address":"200 1st Ave W",
    "sg:city":"Seattle",
    "sg:classifiers":[
        {
            "category":"Real Estate",
            "subcategory":"Real Estate Agent",
            "type":"Services"
        },
        {
            "category":"Professional",
            "subcategory":"Management & Consulting",
            "type":"Services"
        }
    ],
    "sg:phone":"+1 206 505 7900",
    "sg:postcode":"98119",
    "sg:province":"WA",
    "sg:tags":[
        "desk",
        "space"
    ],
    "wof:name":"First West Suites",
    "wof:placetype":"venue"
},
  "geometry": {"coordinates":[-122.358046,47.620945],"type":"Point"}
}