{
  "type": "Feature",
  "properties": {
    "addr:full":"712 Harrison Ave Centralia WA 98531",
    "addr:housenumber":"712",
    "addr:postcode":"98531",
    "addr:street":"Harrison Ave",
    "iso:country":"US",
    "sg:address":"712 Harrison Ave",
    "sg:city":"Centralia",
    "sg:classifiers":[
        {
            "category":"Restaurant",
            "type":"Food & Drink"
        }
    ],
    "sg:phone":"+1 360 330 1661",
    "sg:postcode":"98531",
    "sg:province":"WA",
    "wof:name":"Lunch Box",
    "wof:placetype":"venue"
},
  "geometry": {"coordinates":[-122.97292299999999,46.724892],"type":"Point"}
}