{
  "type": "Feature",
  "properties": {
    "addr:full":"362 Ten Mile Rd Lynden WA 98264",
    "addr:housenumber":"362",
    "addr:postcode":"98264",
    "addr:street":"Ten Mile Rd",
    "iso:country":"US",
    "sg:address":"362 Ten Mile Rd",
    "sg:city":"Lynden",
    "sg:classifiers":[
        {
            "category":"Farming",
            "subcategory":"Dairy Farm",
            "type":"Manufacturing & Wholesale Goods"
        }
    ],
    "sg:phone":"+1 360 398 1374",
    "sg:postcode":"98264",
    "sg:province":"WA",
    "sg:tags":[
        "mfg"
    ],
    "wof:name":"Parker Manufacturing",
    "wof:placetype":"venue"
},
  "geometry": {"coordinates":[-122.481962,48.869733],"type":"Point"}
}