{
  "type": "Feature",
  "properties": {
    "addr:full":"4502 S Steele St Tacoma WA 98409",
    "addr:housenumber":"4502",
    "addr:postcode":"98409",
    "addr:street":"S Steele St",
    "iso:country":"US",
    "sg:address":"4502 S Steele St",
    "sg:city":"Tacoma",
    "sg:classifiers":[
        {
            "category":"Manufacturing",
            "subcategory":"Food",
            "type":"Manufacturing & Wholesale Goods"
        },
        {
            "category":"Bakery",
            "type":"Food & Drink"
        }
    ],
    "sg:menulink":"http://www.allmenus.com/wa/tacoma/235788-pretzel-time/menu/",
    "sg:phone":"+1 253 475 9533",
    "sg:postcode":"98409",
    "sg:province":"WA",
    "sg:tags":[
        "new",
        "american",
        "bakery",
        "pastry"
    ],
    "wof:name":"Pretzel Time",
    "wof:placetype":"venue"
},
  "geometry": {"coordinates":[-122.467608,47.217853],"type":"Point"}
}