{
  "type": "Feature",
  "properties": {
    "addr:full":"7407 NE Vancouver Plaza Dr Vancouver WA 98662",
    "addr:housenumber":"7407",
    "addr:postcode":"98662",
    "addr:street":"Ne Vancouver Plaza Dr",
    "iso:country":"US",
    "sg:address":"7407 NE Vancouver Plaza Dr",
    "sg:city":"Vancouver",
    "sg:classifiers":[
        {
            "category":"Autos & Motor Vehicles",
            "subcategory":"Automobile Sales",
            "type":"Retail Goods"
        }
    ],
    "sg:phone":"+1 360 314 0532",
    "sg:postcode":"98662",
    "sg:province":"WA",
    "sg:tags":[
        "new",
        "truck",
        "car"
    ],
    "sg:website":"http://www.ford.com/footer/dealer-directory?Criteria=/WA/Vancouver",
    "wof:name":"Hannah Motor Co",
    "wof:placetype":"venue"
},
  "geometry": {"coordinates":[-122.597526,45.648961],"type":"Point"}
}