{
  "type": "Feature",
  "properties": {
    "iso:country":"US",
    "sg:address":"3416 NE 86th Ave",
    "sg:city":"Vancouver",
    "sg:classifiers":[
        {
            "category":"Professional",
            "subcategory":"Accounting & Tax Preparation",
            "type":"Services"
        }
    ],
    "sg:phone":"+1 360 891 4764",
    "sg:postcode":"98662",
    "sg:province":"WA",
    "wof:name":"Martin H Oreschnigg CPA",
    "wof:placetype":"venue"
},
  "geometry": {"coordinates":[-122.58551900000001,45.647862],"type":"Point"}
}