{
  "type": "Feature",
  "properties": {
    "addr:full":"428 E 3rd Ave Spokane WA 99202",
    "addr:housenumber":"428",
    "addr:postcode":"99202",
    "addr:street":"E 3Rd Ave",
    "iso:country":"US",
    "sg:address":"428 E 3rd Ave",
    "sg:city":"Spokane",
    "sg:classifiers":[
        {
            "category":"Banks & Credit Unions",
            "subcategory":"Bank",
            "type":"Services"
        }
    ],
    "sg:phone":"+1 509 838 6157",
    "sg:postcode":"99202",
    "sg:province":"WA",
    "sg:website":"http://www.primesourcecu.org",
    "wof:name":"Primesource Credit Union",
    "wof:placetype":"venue"
},
  "geometry": {"coordinates":[-117.404156,47.653552],"type":"Point"}
}