{
  "type": "Feature",
  "properties": {
    "addr:full":"4739 Rainier Avenue S Seattle WA 98118",
    "addr:housenumber":"4739",
    "addr:postcode":"98118",
    "addr:street":"Rainier Avenue S",
    "iso:country":"US",
    "sg:address":"4739 Rainier Avenue S",
    "sg:city":"Seattle",
    "sg:classifiers":[
        {
            "category":"Health Services",
            "subcategory":"Doctor",
            "type":"Services"
        }
    ],
    "sg:phone":"+1 206 725 0119",
    "sg:postcode":"98118",
    "sg:province":"WA",
    "wof:name":"Mylieu Tuan",
    "wof:placetype":"venue"
},
  "geometry": {"coordinates":[-122.286661,47.560527],"type":"Point"}
}