{
  "type": "Feature",
  "properties": {
    "addr:full":"3016 E Bay Dr NW Gig Harbor WA 98335",
    "addr:housenumber":"3016",
    "addr:postcode":"98335",
    "addr:street":"E Bay Dr Nw",
    "iso:country":"US",
    "sg:address":"3016 E Bay Dr NW",
    "sg:city":"Gig Harbor",
    "sg:classifiers":[
        {
            "category":"Manufacturing",
            "subcategory":"Printing",
            "type":"Manufacturing & Wholesale Goods"
        }
    ],
    "sg:phone":"+1 253 858 7286",
    "sg:postcode":"98335",
    "sg:province":"WA",
    "sg:tags":[
        "book"
    ],
    "wof:name":"Washington Primedia Inc",
    "wof:placetype":"venue"
},
  "geometry": {"coordinates":[-122.59893,47.285813],"type":"Point"}
}