{
  "type": "Feature",
  "properties": {
    "addr:full":"6900 Sexton Dr NW Olympia WA 98502",
    "addr:housenumber":"6900",
    "addr:postcode":"olympia wa 98502",
    "addr:street":"Sexton Dr Nw",
    "iso:country":"US",
    "sg:address":"6900 Sexton Dr NW",
    "sg:city":"Olympia",
    "sg:classifiers":[
        {
            "category":"Home & Garden",
            "subcategory":"Furniture",
            "type":"Retail Goods"
        }
    ],
    "sg:phone":"+1 360 866 7906",
    "sg:postcode":"98502",
    "sg:province":"WA",
    "sg:tags":[
        "cabinet"
    ],
    "wof:name":"Jim's Fine Woodworks",
    "wof:placetype":"venue"
},
  "geometry": {"coordinates":[-123.02367099999999,47.083351],"type":"Point"}
}