{
  "type": "Feature",
  "properties": {
    "addr:full":"20871 Redmond Fall City Rd NE Redmond WA 98053",
    "addr:housenumber":"20871",
    "addr:postcode":"98053",
    "addr:street":"Redmond Fall City Rd Ne",
    "iso:country":"US",
    "sg:address":"20871 Redmond Fall City Rd NE",
    "sg:city":"Redmond",
    "sg:classifiers":[
        {
            "category":"Home & Garden",
            "subcategory":"Garden Supply",
            "type":"Retail Goods"
        }
    ],
    "sg:phone":"+1 425 868 5757",
    "sg:postcode":"98053",
    "sg:province":"WA",
    "sg:tags":[
        "nurseryman"
    ],
    "wof:name":"Gray Barn Garden Ctr",
    "wof:placetype":"venue"
},
  "geometry": {"coordinates":[-122.060694,47.655954],"type":"Point"}
}