{
  "type": "Feature",
  "properties": {
    "addr:full":"15004 N Edencrest Dr Spokane WA 99208",
    "addr:housenumber":"15004",
    "addr:postcode":"99208",
    "addr:street":"N Edencrest Dr",
    "iso:country":"US",
    "sg:address":"15004 N Edencrest Dr",
    "sg:city":"Spokane",
    "sg:classifiers":[
        {
            "category":"Retail",
            "subcategory":"Auto Rental",
            "type":"Services"
        }
    ],
    "sg:phone":"+1 509 483 2912",
    "sg:postcode":"99208",
    "sg:province":"WA",
    "sg:tags":[
        "truck",
        "leasing"
    ],
    "wof:name":"Oasis Leasing",
    "wof:placetype":"venue"
},
  "geometry": {"coordinates":[-117.40176099999999,47.795003],"type":"Point"}
}