{
  "type": "Feature",
  "properties": {
    "iso:country":"US",
    "sg:address":"3611 I St NE",
    "sg:city":"Auburn",
    "sg:classifiers":[
        {
            "category":"Retail",
            "subcategory":"Portrait Studio",
            "type":"Services"
        }
    ],
    "sg:phone":"+1 253 833 0901",
    "sg:postcode":"98031",
    "sg:province":"WA",
    "sg:tags":[
        "photographer"
    ],
    "sg:website":"www.doveportraits.com",
    "wof:name":"Dove Portraits",
    "wof:placetype":"venue"
},
  "geometry": {"coordinates":[-122.219325,47.340196],"type":"Point"}
}