{
  "type": "Feature",
  "properties": {
    "iso:country":"US",
    "sg:address":"6100 238th St SE",
    "sg:city":"Woodinville",
    "sg:classifiers":[
        {
            "category":"Building & Trades",
            "subcategory":"Equipment Rental",
            "type":"Services"
        }
    ],
    "sg:phone":"+1 425 487 6503",
    "sg:postcode":"98072",
    "sg:province":"WA",
    "wof:name":"Baker Tanks",
    "wof:placetype":"venue"
},
  "geometry": {"coordinates":[-122.151686,47.781852],"type":"Point"}
}