{
  "type": "Feature",
  "properties": {
    "addr:full":"293 Logan Hill Rd Chehalis WA 98532",
    "addr:housenumber":"293",
    "addr:postcode":"98532",
    "addr:street":"Logan Hill Rd",
    "iso:country":"US",
    "sg:address":"293 Logan Hill Rd",
    "sg:city":"Chehalis",
    "sg:classifiers":[
        {
            "category":"Building & Trades",
            "subcategory":"Construction",
            "type":"Services"
        }
    ],
    "sg:phone":"+1 360 748 9219",
    "sg:postcode":"98532",
    "sg:province":"WA",
    "sg:tags":[
        "contractor"
    ],
    "wof:name":"Classic Gutter Service",
    "wof:placetype":"venue"
},
  "geometry": {"coordinates":[-122.875742,46.630262],"type":"Point"}
}