{
  "type": "Feature",
  "properties": {
    "addr:full":"613 E Pike Street Seattle WA 98122",
    "addr:housenumber":"613",
    "addr:postcode":"98122",
    "addr:street":"E Pike Street",
    "iso:country":"US",
    "sg:address":"613 E Pike Street",
    "sg:city":"Seattle",
    "sg:classifiers":[
        {
            "category":"Building & Trades",
            "subcategory":"Construction",
            "type":"Services"
        }
    ],
    "sg:phone":"+1 206 320 1048",
    "sg:postcode":"98122",
    "sg:province":"WA",
    "sg:tags":[
        "contractor"
    ],
    "sg:website":"www.caledoniabay.com",
    "wof:name":"Caledonia Bay Builders",
    "wof:placetype":"venue"
},
  "geometry": {"coordinates":[-122.32391699999999,47.614202],"type":"Point"}
}