{
  "type": "Feature",
  "properties": {
    "addr:full":"16618 N Bluebell Ct Nine Mile Falls WA 99026",
    "addr:housenumber":"16618",
    "addr:postcode":"99026",
    "addr:street":"N Bluebell Ct",
    "iso:country":"US",
    "sg:address":"16618 N Bluebell Ct",
    "sg:city":"Nine Mile Falls",
    "sg:classifiers":[
        {
            "category":"Manufacturing",
            "subcategory":"Metals",
            "type":"Manufacturing & Wholesale Goods"
        }
    ],
    "sg:phone":"+1 509 466 9438",
    "sg:postcode":"99026",
    "sg:province":"WA",
    "sg:tags":[
        "tool",
        "mfg"
    ],
    "wof:name":"Snap-On Tools",
    "wof:placetype":"venue"
},
  "geometry": {"coordinates":[-117.59772,47.810604],"type":"Point"}
}