{
  "type": "Feature",
  "properties": {
    "addr:full":"2000 Nile Rd Naches WA 98937",
    "addr:housenumber":"2000",
    "addr:postcode":"98937",
    "addr:street":"Nile Rd",
    "iso:country":"US",
    "sg:address":"2000 Nile Rd",
    "sg:city":"Naches",
    "sg:classifiers":[
        {
            "category":"Building & Trades",
            "subcategory":"Construction",
            "type":"Services"
        }
    ],
    "sg:phone":"+1 509 658 2279",
    "sg:postcode":"98937",
    "sg:province":"WA",
    "sg:tags":[
        "new",
        "home"
    ],
    "wof:name":"George Cameron",
    "wof:placetype":"venue"
},
  "geometry": {"coordinates":[-120.940151,46.821816],"type":"Point"}
}