{
  "type": "Feature",
  "properties": {
    "addr:full":"515 Madison St Seattle WA 98104",
    "addr:housenumber":"515",
    "addr:postcode":"98104",
    "addr:street":"Madison St",
    "iso:country":"US",
    "sg:address":"515 Madison St",
    "sg:city":"Seattle",
    "sg:phone":"+1 206 583 0300",
    "sg:postcode":"98104",
    "sg:province":"WA",
    "sg:website":"http://www.pregorestaurant.com",
    "wof:name":"Maxwell's Restaurant",
    "wof:placetype":"venue"
},
  "geometry": {"coordinates":[-122.331553,47.606668],"type":"Point"}
}