{
  "type": "Feature",
  "properties": {
    "addr:full":"859 Monse River Rd Brewster WA 98812",
    "addr:housenumber":"859",
    "addr:postcode":"98812",
    "addr:street":"Monse River Rd",
    "iso:country":"US",
    "sg:address":"859 Monse River Rd",
    "sg:city":"Brewster",
    "sg:classifiers":[
        {
            "category":"Farming",
            "subcategory":"Orchard",
            "type":"Manufacturing & Wholesale Goods"
        }
    ],
    "sg:phone":"+1 509 689 2156",
    "sg:postcode":"98812",
    "sg:province":"WA",
    "sg:tags":[
        "fruit",
        "tree"
    ],
    "wof:name":"Roger W Robinson",
    "wof:placetype":"venue"
},
  "geometry": {"coordinates":[-119.716956,48.204903],"type":"Point"}
}