{
  "type": "Feature",
  "properties": {
    "iso:country":"US",
    "sg:address":"520 Simpson Ave",
    "sg:city":"Hoquiam",
    "sg:classifiers":[
        {
            "category":"Shopping",
            "subcategory":"Florist",
            "type":"Retail Goods"
        }
    ],
    "sg:phone":"+1 360 533 1933",
    "sg:postcode":"98550",
    "sg:province":"WA",
    "wof:name":"Flower Shoppe",
    "wof:placetype":"venue"
},
  "geometry": {"coordinates":[-123.887326,46.979266],"type":"Point"}
}