{
  "type": "Feature",
  "properties": {
    "addr:full":"1455 S Puget Dr Renton WA 98055",
    "addr:housenumber":"1455",
    "addr:postcode":"98055",
    "addr:street":"S Puget Dr",
    "iso:country":"US",
    "sg:address":"1455 S Puget Dr",
    "sg:city":"Renton",
    "sg:classifiers":[
        {
            "category":"Building & Trades",
            "subcategory":"Construction",
            "type":"Services"
        }
    ],
    "sg:phone":"+1 425 228 2010",
    "sg:postcode":"98055",
    "sg:province":"WA",
    "sg:tags":[
        "contractor"
    ],
    "wof:name":"Integrity Tile & Marble",
    "wof:placetype":"venue"
},
  "geometry": {"coordinates":[-122.19112,47.463781],"type":"Point"}
}