{
  "type": "Feature",
  "properties": {
    "addr:full":"606 E Woodin Ave Chelan WA 98816",
    "addr:housenumber":"606",
    "addr:postcode":"98816",
    "addr:street":"E Woodin Ave",
    "iso:country":"US",
    "sg:address":"606 E Woodin Ave",
    "sg:city":"Chelan",
    "sg:classifiers":[
        {
            "category":"Utilities",
            "subcategory":"Cable",
            "type":"Services"
        }
    ],
    "sg:phone":"+1 509 682 2057",
    "sg:postcode":"98816",
    "sg:province":"WA",
    "sg:tags":[
        "satellite",
        "carrier"
    ],
    "wof:name":"Satellite Services",
    "wof:placetype":"venue"
},
  "geometry": {"coordinates":[-120.008706,47.839624],"type":"Point"}
}