{
  "type": "Feature",
  "properties": {
    "addr:full":"23601 Hwy 99 Edmonds WA 98026",
    "addr:housenumber":"23601",
    "addr:postcode":"98026",
    "addr:street":"Hwy 99",
    "iso:country":"US",
    "sg:address":"23601 Hwy 99",
    "sg:city":"Edmonds",
    "sg:classifiers":[
        {
            "category":"Home & Garden",
            "subcategory":"Building Materials",
            "type":"Retail Goods"
        }
    ],
    "sg:phone":"+1 425 771 0101",
    "sg:postcode":"98026",
    "sg:province":"WA",
    "sg:tags":[
        "windows",
        "door",
        "cabinet"
    ],
    "wof:name":"Cabinet Door & Window Store",
    "wof:placetype":"venue"
},
  "geometry": {"coordinates":[-122.343563,47.783242],"type":"Point"}
}