{
  "type": "Feature",
  "properties": {
    "addr:full":"3041 NE 143rd St Apt 21 Seattle WA 98125",
    "addr:housenumber":"3041;21",
    "addr:postcode":"98125",
    "addr:street":"Ne 143Rd St Apt",
    "iso:country":"US",
    "sg:address":"3041 NE 143rd St Apt 21",
    "sg:city":"Seattle",
    "sg:classifiers":[
        {
            "category":"Community Center",
            "subcategory":"Senior",
            "type":"Public Place"
        },
        {
            "category":"Health Services",
            "subcategory":"Nursing And Care Facility",
            "type":"Services"
        },
        {
            "category":"Health Services",
            "subcategory":"Health Practitioner",
            "type":"Services"
        },
        {
            "category":"Social Services",
            "subcategory":"Adult Care",
            "type":"Services"
        }
    ],
    "sg:phone":"+1 206 363 4599",
    "sg:postcode":"98125",
    "sg:province":"WA",
    "sg:tags":[
        "living",
        "people",
        "home",
        "assisted",
        "citizen",
        "elder",
        "homes-elderly",
        "counseling",
        "eldercare-home"
    ],
    "sg:website":"http://www.homewatchcaregivers.com",
    "wof:name":"Homewatch Caregivers",
    "wof:placetype":"venue"
},
  "geometry": {"coordinates":[-122.295447,47.731956],"type":"Point"}
}