{
  "type": "Feature",
  "properties": {
    "addr:full":"16620 11th Avenue Kp N Lakebay WA 98349",
    "addr:housenumber":"16620",
    "addr:postcode":"98349",
    "addr:street":"11Th Avenue Kp N Lakebay",
    "iso:country":"US",
    "sg:address":"16620 11th Avenue Kp N",
    "sg:city":"Lakebay",
    "sg:classifiers":[
        {
            "category":"Manufacturing",
            "subcategory":"Signs",
            "type":"Manufacturing & Wholesale Goods"
        }
    ],
    "sg:phone":"+1 253 884 5533",
    "sg:postcode":"98349",
    "sg:province":"WA",
    "sg:tags":[
        "specialty",
        "mfg"
    ],
    "wof:name":"Ruby Neon",
    "wof:placetype":"venue"
},
  "geometry": {"coordinates":[-122.76055599999999,47.278752],"type":"Point"}
}