{
  "type": "Feature",
  "properties": {
    "addr:full":"5408 Meridian Ave N Seattle WA 98103",
    "addr:housenumber":"5408",
    "addr:postcode":"98103",
    "addr:street":"Meridian Ave N",
    "iso:country":"US",
    "sg:address":"5408 Meridian Ave N",
    "sg:city":"Seattle",
    "sg:classifiers":[
        {
            "category":"Real Estate",
            "subcategory":"Real Estate Services",
            "type":"Services"
        }
    ],
    "sg:phone":"+1 206 462 2722",
    "sg:postcode":"98103",
    "sg:province":"WA",
    "sg:website":"www.forbesappraisal.com/",
    "wof:name":"Forbes Appraisal Group",
    "wof:placetype":"venue"
},
  "geometry": {"coordinates":[-122.33335099999999,47.668214],"type":"Point"}
}