{
  "type": "Feature",
  "properties": {
    "addr:full":"29148 Outlook Ln Sedro Woolley WA 98284",
    "addr:housenumber":"29148",
    "addr:postcode":"98284",
    "addr:street":"Outlook Ln",
    "iso:country":"US",
    "sg:address":"29148 Outlook Ln",
    "sg:city":"Sedro Woolley",
    "sg:classifiers":[
        {
            "category":"Professional",
            "subcategory":"Computer Services",
            "type":"Services"
        }
    ],
    "sg:phone":"+1 360 404 5600",
    "sg:postcode":"98284",
    "sg:province":"WA",
    "sg:tags":[
        "consulting",
        "software"
    ],
    "wof:name":"Web/Ekg Inc",
    "wof:placetype":"venue"
},
  "geometry": {"coordinates":[-122.113969,48.5296],"type":"Point"}
}