{
  "type": "Feature",
  "properties": {
    "addr:full":"Seattle Tower 1220 3rd Ave Seattle WA 98101",
    "addr:housenumber":"1220",
    "addr:postcode":"98101",
    "addr:street":"3Rd Ave",
    "iso:country":"US",
    "sg:address":"Seattle Tower 1220 3rd Ave",
    "sg:city":"Seattle",
    "sg:classifiers":[
        {
            "category":"Arts & Performance",
            "subcategory":"Art Gallery",
            "type":"Entertainment"
        }
    ],
    "sg:phone":"+1 206 343 1101",
    "sg:postcode":"98101",
    "sg:province":"WA",
    "sg:website":"www.seattleartmuseum.org/visit/v...",
    "wof:name":"SAM Gallery",
    "wof:placetype":"venue"
},
  "geometry": {"coordinates":[-122.335505,47.607213],"type":"Point"}
}