{
  "type": "Feature",
  "properties": {
    "addr:full":"1127 Summerfield Dr SE Olympia WA 98513",
    "addr:housenumber":"1127",
    "addr:postcode":"98513",
    "addr:street":"Summerfield Dr Se",
    "iso:country":"US",
    "sg:address":"1127 Summerfield Dr SE",
    "sg:city":"Olympia",
    "sg:classifiers":[
        {
            "category":"Building & Trades",
            "subcategory":"Construction",
            "type":"Services"
        }
    ],
    "sg:phone":"+1 360 455 0092",
    "sg:postcode":"98513",
    "sg:province":"WA",
    "sg:tags":[
        "manufacture",
        "housing"
    ],
    "wof:name":"Raymonds Mobile Home Setup",
    "wof:placetype":"venue"
},
  "geometry": {"coordinates":[-122.734075,47.046429],"type":"Point"}
}