{
  "type": "Feature",
  "properties": {
    "addr:full":"13375 48th Ave S Seattle WA 98168",
    "addr:housenumber":"13375",
    "addr:postcode":"98168",
    "addr:street":"48Th Ave S",
    "iso:country":"US",
    "sg:address":"13375 48th Ave S",
    "sg:city":"Seattle",
    "sg:classifiers":[
        {
            "category":"Manufacturing",
            "subcategory":"Tools & Machinery",
            "type":"Manufacturing & Wholesale Goods"
        }
    ],
    "sg:phone":"+1 206 242 0598",
    "sg:postcode":"98168",
    "sg:province":"WA",
    "sg:tags":[
        "machine",
        "mfg",
        "accessory"
    ],
    "wof:name":"Schweiger Industries",
    "wof:placetype":"venue"
},
  "geometry": {"coordinates":[-122.273276,47.483085],"type":"Point"}
}