{
  "type": "Feature",
  "properties": {
    "addr:full":"7936 Union Mills Rd SE Lacey WA 98503",
    "addr:housenumber":"7936",
    "addr:postcode":"98503",
    "addr:street":"Union Mills Rd Se",
    "iso:country":"US",
    "sg:address":"7936 Union Mills Rd SE",
    "sg:city":"Lacey",
    "sg:classifiers":[
        {
            "category":"Wholesale",
            "subcategory":"Vending Machines",
            "type":"Manufacturing & Wholesale Goods"
        }
    ],
    "sg:phone":"+1 360 491 3339",
    "sg:postcode":"98503",
    "sg:province":"WA",
    "sg:tags":[
        "operator"
    ],
    "wof:name":"US Vending",
    "wof:placetype":"venue"
},
  "geometry": {"coordinates":[-122.771767,47.031438],"type":"Point"}
}