{
  "type": "Feature",
  "properties": {
    "iso:country":"US",
    "sg:address":"1014 Brentwood Pl",
    "sg:city":"Tacoma",
    "sg:classifiers":[
        {
            "category":"Professional",
            "type":"Services"
        }
    ],
    "sg:phone":"+1 253 564 5229",
    "sg:postcode":"98466",
    "sg:province":"WA",
    "wof:name":"High Flying Art",
    "wof:placetype":"venue"
},
  "geometry": {"coordinates":[-122.517523,47.233037],"type":"Point"}
}