{
  "type": "Feature",
  "properties": {
    "addr:full":"8556 Greenwood Ave N Seattle WA 98103",
    "addr:housenumber":"8556",
    "addr:postcode":"98103",
    "addr:street":"Greenwood Ave N",
    "iso:country":"US",
    "sg:address":"8556 Greenwood Ave N",
    "sg:city":"Seattle",
    "sg:classifiers":[
        {
            "category":"Bars & Pubs",
            "subcategory":"Dive Bar",
            "type":"Food & Drink"
        }
    ],
    "sg:phone":"+1 206 789 9691",
    "sg:postcode":"98103",
    "sg:province":"WA",
    "wof:name":"Crosswalk",
    "wof:placetype":"venue"
},
  "geometry": {"coordinates":[-122.355003,47.6912],"type":"Point"}
}