{
  "type": "Feature",
  "properties": {
    "addr:full":"14906 SE 138th Pl Renton WA 98059",
    "addr:housenumber":"14906",
    "addr:postcode":"98059",
    "addr:street":"Se 138Th Pl",
    "iso:country":"US",
    "sg:address":"14906 SE 138th Pl",
    "sg:city":"Renton",
    "sg:classifiers":[
        {
            "category":"Home & Garden",
            "subcategory":"Carpets & Floor Coverings",
            "type":"Retail Goods"
        }
    ],
    "sg:phone":"+1 425 277 8386",
    "sg:postcode":"98059",
    "sg:province":"WA",
    "wof:name":"Accent Tile & Floor Cover Inc",
    "wof:placetype":"venue"
},
  "geometry": {"coordinates":[-122.14126,47.478952],"type":"Point"}
}