{
  "type": "Feature",
  "properties": {
    "addr:full":"1702 Pike St NW Auburn WA 98001",
    "addr:housenumber":"1702",
    "addr:postcode":"98001",
    "addr:street":"Pike St Nw",
    "iso:country":"US",
    "sg:address":"1702 Pike St NW",
    "sg:city":"Auburn",
    "sg:classifiers":[
        {
            "category":"Professional",
            "subcategory":"Business Services",
            "type":"Services"
        },
        {
            "category":"Shopping",
            "subcategory":"Computers & Home Electronics",
            "type":"Retail Goods"
        }
    ],
    "sg:phone":"+1 253 833 1888",
    "sg:postcode":"98001",
    "sg:province":"WA",
    "sg:tags":[
        "used",
        "merchandise"
    ],
    "wof:name":"Computer Marketing Investments",
    "wof:placetype":"venue"
},
  "geometry": {"coordinates":[-122.251971,47.324655],"type":"Point"}
}