{
  "type": "Feature",
  "properties": {
    "addr:full":"8319 238th St SW Edmonds WA 98026",
    "addr:housenumber":"8319",
    "addr:postcode":"98026",
    "addr:street":"238Th St Sw",
    "iso:country":"US",
    "sg:address":"8319 238th St SW",
    "sg:city":"Edmonds",
    "sg:classifiers":[
        {
            "category":"Building & Trades",
            "subcategory":"Construction",
            "type":"Services"
        }
    ],
    "sg:phone":"+1 425 771 6150",
    "sg:postcode":"98026",
    "sg:province":"WA",
    "sg:tags":[
        "contractor"
    ],
    "wof:name":"Stella Tile Co",
    "wof:placetype":"venue"
},
  "geometry": {"coordinates":[-122.345072,47.783323],"type":"Point"}
}