{
  "type": "Feature",
  "properties": {
    "addr:full":"416 Mount Vernon Terminal RR Mt Vernon WA 98273",
    "addr:housenumber":"416",
    "addr:postcode":"98273",
    "addr:street":"Mount;Vernon",
    "iso:country":"US",
    "sg:address":"416 Mount Vernon Terminal RR",
    "sg:city":"Mt Vernon",
    "sg:classifiers":[
        {
            "category":"Real Estate",
            "subcategory":"Architect",
            "type":"Services"
        }
    ],
    "sg:phone":"+1 360 336 5235",
    "sg:postcode":"98273",
    "sg:province":"WA",
    "wof:name":"Harold A Page Architect",
    "wof:placetype":"venue"
},
  "geometry": {"coordinates":[-122.33840600000001,48.420211],"type":"Point"}
}