{
  "type": "Feature",
  "properties": {
    "iso:country":"US",
    "sg:address":"355 Malaga Alcoa Hwy",
    "sg:city":"Wenatchee",
    "sg:classifiers":[
        {
            "category":"Home & Garden",
            "subcategory":"Building Materials",
            "type":"Retail Goods"
        }
    ],
    "sg:phone":"+1 509 662 1877",
    "sg:postcode":"98801",
    "sg:province":"WA",
    "sg:tags":[
        "truss"
    ],
    "wof:name":"Noble Truss & Lumber Inc",
    "wof:placetype":"venue"
},
  "geometry": {"coordinates":[-120.275453,47.385559],"type":"Point"}
}