{
  "type": "Feature",
  "properties": {
    "addr:full":"104 Davenhill Ln Sequim WA 98382",
    "addr:housenumber":"104",
    "addr:postcode":"98382",
    "addr:street":"Davenhill Ln",
    "iso:country":"US",
    "sg:address":"104 Davenhill Ln",
    "sg:city":"Sequim",
    "sg:classifiers":[
        {
            "category":"Building & Trades",
            "subcategory":"Construction",
            "type":"Services"
        }
    ],
    "sg:phone":"+1 360 582 0440",
    "sg:postcode":"98382",
    "sg:province":"WA",
    "sg:tags":[
        "contractor"
    ],
    "wof:name":"Wipe Out",
    "wof:placetype":"venue"
},
  "geometry": {"coordinates":[-123.204341,48.090889],"type":"Point"}
}