{
  "type": "Feature",
  "properties": {
    "addr:full":"11711 101st Ave E Puyallup WA 98373",
    "addr:housenumber":"11711",
    "addr:postcode":"98373",
    "addr:street":"101St Ave E",
    "iso:country":"US",
    "sg:address":"11711 101st Ave E",
    "sg:city":"Puyallup",
    "sg:classifiers":[
        {
            "category":"Professional",
            "subcategory":"Lawyer & Legal Services",
            "type":"Services"
        }
    ],
    "sg:phone":"+1 253 864 7800",
    "sg:postcode":"98373",
    "sg:province":"WA",
    "sg:tags":[
        "plan"
    ],
    "wof:name":"Thomas A Baldwin",
    "wof:placetype":"venue"
},
  "geometry": {"coordinates":[-122.294284,47.150133],"type":"Point"}
}