{
  "type": "Feature",
  "properties": {
    "addr:full":"1309 4th Avenue Seattle WA 98101",
    "addr:housenumber":"1309",
    "addr:postcode":"98101",
    "addr:street":"4Th Avenue",
    "iso:country":"US",
    "sg:address":"1309 4th Avenue",
    "sg:city":"Seattle",
    "sg:classifiers":[
        {
            "category":"Banks & Credit Unions",
            "subcategory":"Bank",
            "type":"Services"
        },
        {
            "category":"Banks & Credit Unions",
            "subcategory":"Financial Services",
            "type":"Services"
        }
    ],
    "sg:phone":"+1 206 358 1279",
    "sg:postcode":"98101",
    "sg:province":"WA",
    "sg:tags":[
        "broker",
        "mortgage"
    ],
    "sg:website":"www.bankofamerica.com",
    "wof:name":"Bank of America",
    "wof:placetype":"venue"
},
  "geometry": {"coordinates":[-122.33498299999999,47.608286],"type":"Point"}
}