{
  "type": "Feature",
  "properties": {
    "addr:full":"13926 SE 92nd St Renton WA 98059",
    "addr:housenumber":"13926",
    "addr:postcode":"98059",
    "addr:street":"Se 92Nd St",
    "iso:country":"US",
    "sg:address":"13926 SE 92nd St",
    "sg:city":"Renton",
    "sg:classifiers":[
        {
            "category":"Professional",
            "subcategory":"Business Services",
            "type":"Services"
        }
    ],
    "sg:phone":"+1 425 430 7900",
    "sg:postcode":"98059",
    "sg:province":"WA",
    "wof:name":"Raining Virtue Solutions Inc",
    "wof:placetype":"venue"
},
  "geometry": {"coordinates":[-122.154803,47.519502],"type":"Point"}
}