{
  "type": "Feature",
  "properties": {
    "addr:full":"7627 Westside Hwy Castle Rock WA 98611",
    "addr:housenumber":"7627",
    "addr:postcode":"98611",
    "addr:street":"Westside Hwy",
    "iso:country":"US",
    "sg:address":"7627 Westside Hwy",
    "sg:city":"Castle Rock",
    "sg:classifiers":[
        {
            "category":"Manufacturing",
            "subcategory":"Leather Goods",
            "type":"Manufacturing & Wholesale Goods"
        }
    ],
    "sg:phone":"+1 360 274 9975",
    "sg:postcode":"98611",
    "sg:province":"WA",
    "sg:tags":[
        "mfg"
    ],
    "wof:name":"Sirius Leather",
    "wof:placetype":"venue"
},
  "geometry": {"coordinates":[-122.93652,46.355093],"type":"Point"}
}