{
  "type": "Feature",
  "properties": {
    "addr:full":"312 Blackledge Rd Carson WA 98610",
    "addr:housenumber":"312",
    "addr:postcode":"98610",
    "addr:street":"Blackledge Rd",
    "iso:country":"US",
    "sg:address":"312 Blackledge Rd",
    "sg:city":"Carson",
    "sg:classifiers":[
        {
            "category":"Professional",
            "subcategory":"Management & Consulting",
            "type":"Services"
        }
    ],
    "sg:phone":"+1 509 427 8438",
    "sg:postcode":"98610",
    "sg:province":"WA",
    "sg:tags":[
        "agricultural",
        "consultant"
    ],
    "wof:name":"Earthkeep Inc",
    "wof:placetype":"venue"
},
  "geometry": {"coordinates":[-121.910909,45.782702],"type":"Point"}
}