{
  "type": "Feature",
  "properties": {
    "addr:full":"113 W Locust St Waterville WA 98858",
    "addr:housenumber":"113",
    "addr:postcode":"98858",
    "addr:street":"W Locust St",
    "iso:country":"US",
    "sg:address":"113 W Locust St",
    "sg:city":"Waterville",
    "sg:classifiers":[
        {
            "category":"Shopping",
            "subcategory":"Used Merchandise",
            "type":"Retail Goods"
        }
    ],
    "sg:phone":"+1 509 745 8800",
    "sg:postcode":"98858",
    "sg:province":"WA",
    "sg:tags":[
        "shop",
        "thrift"
    ],
    "wof:name":"Douglas County Thrift Store",
    "wof:placetype":"venue"
},
  "geometry": {"coordinates":[-120.071646,47.647446],"type":"Point"}
}