{
  "type": "Feature",
  "properties": {
    "addr:full":"5633 W Bedford Ave Spokane WA 99208",
    "addr:housenumber":"5633",
    "addr:postcode":"99208",
    "addr:street":"W Bedford Ave",
    "iso:country":"US",
    "sg:address":"5633 W Bedford Ave",
    "sg:city":"Spokane",
    "sg:classifiers":[
        {
            "category":"Wholesale",
            "subcategory":"Hardware",
            "type":"Manufacturing & Wholesale Goods"
        }
    ],
    "sg:phone":"+1 509 464 3673",
    "sg:postcode":"99208",
    "sg:province":"WA",
    "sg:tags":[
        "control",
        "mfg",
        "air",
        "representative",
        "pollution"
    ],
    "wof:name":"Airstream Equipment Supply",
    "wof:placetype":"venue"
},
  "geometry": {"coordinates":[-117.49445900000001,47.754684],"type":"Point"}
}