{
  "type": "Feature",
  "properties": {
    "addr:full":"91 Corey St Brinnon WA 98320",
    "addr:housenumber":"91",
    "addr:postcode":"98320",
    "addr:street":"Corey St",
    "iso:country":"US",
    "sg:address":"91 Corey St",
    "sg:city":"Brinnon",
    "sg:classifiers":[
        {
            "category":"Food & Beverages",
            "subcategory":"Liquor & Beverages",
            "type":"Retail Goods"
        }
    ],
    "sg:phone":"+1 360 796 4613",
    "sg:postcode":"98320",
    "sg:province":"WA",
    "wof:name":"Cottage By The Bay",
    "wof:placetype":"venue"
},
  "geometry": {"coordinates":[-122.90218900000001,47.692817],"type":"Point"}
}