{
  "type": "Feature",
  "properties": {
    "addr:full":"3820 NE 155th Pl Seattle WA 98155",
    "addr:housenumber":"3820",
    "addr:postcode":"98155",
    "addr:street":"Ne 155Th Pl",
    "iso:country":"US",
    "sg:address":"3820 NE 155th Pl",
    "sg:city":"Seattle",
    "sg:classifiers":[
        {
            "category":"Retail",
            "subcategory":"Auto Repair",
            "type":"Services"
        }
    ],
    "sg:phone":"+1 206 365 1175",
    "sg:postcode":"98155",
    "sg:province":"WA",
    "sg:tags":[
        "glass",
        "replacement"
    ],
    "wof:name":"May Valley Auto Glass",
    "wof:placetype":"venue"
},
  "geometry": {"coordinates":[-122.286449,47.741696],"type":"Point"}
}