{
  "type": "Feature",
  "properties": {
    "addr:full":"27732 NE 29th Ct Redmond WA 98053",
    "addr:housenumber":"27732",
    "addr:postcode":"98053",
    "addr:street":"Ne 29Th Ct",
    "iso:country":"US",
    "sg:address":"27732 NE 29th Ct",
    "sg:city":"Redmond",
    "sg:classifiers":[
        {
            "category":"Retail",
            "subcategory":"Auto Rental",
            "type":"Services"
        }
    ],
    "sg:phone":"+1 425 880 4205",
    "sg:postcode":"98053",
    "sg:province":"WA",
    "sg:tags":[
        "property"
    ],
    "wof:name":"Centurion Properties",
    "wof:placetype":"venue"
},
  "geometry": {"coordinates":[-121.968254,47.63446],"type":"Point"}
}