{
  "type": "Feature",
  "properties": {
    "addr:full":"4708 76th St NE Marysville WA 98270",
    "addr:housenumber":"4708",
    "addr:postcode":"98270",
    "addr:street":"76Th St Ne",
    "iso:country":"US",
    "sg:address":"4708 76th St NE",
    "sg:city":"Marysville",
    "sg:classifiers":[
        {
            "category":"Building & Trades",
            "subcategory":"Construction",
            "type":"Services"
        }
    ],
    "sg:phone":"+1 360 653 2110",
    "sg:postcode":"98270",
    "sg:province":"WA",
    "sg:tags":[
        "heavy"
    ],
    "wof:name":"Sygs Timber Cutting",
    "wof:placetype":"venue"
},
  "geometry": {"coordinates":[-122.16628799999999,48.064721],"type":"Point"}
}