{
  "type": "Feature",
  "properties": {
    "addr:full":"17640 NE 122nd Ave Battle Ground WA 98604",
    "addr:housenumber":"17640",
    "addr:postcode":"98604",
    "addr:street":"Ne 122Nd Ave",
    "iso:country":"US",
    "sg:address":"17640 NE 122nd Ave",
    "sg:city":"Battle Ground",
    "sg:classifiers":[
        {
            "category":"Real Estate",
            "subcategory":"Developer",
            "type":"Services"
        }
    ],
    "sg:phone":"+1 360 687 2052",
    "sg:postcode":"98604",
    "sg:province":"WA",
    "sg:tags":[
        "development"
    ],
    "wof:name":"Lear Virginia Gail & Joseph",
    "wof:placetype":"venue"
},
  "geometry": {"coordinates":[-122.54741799999999,45.74836],"type":"Point"}
}