{
  "type": "Feature",
  "properties": {
    "addr:full":"900 Lenora St Ste W100 Seattle WA 98121",
    "addr:housenumber":"900",
    "addr:postcode":"98121",
    "addr:street":"Lenora St;W100",
    "iso:country":"US",
    "sg:address":"900 Lenora St Ste W100",
    "sg:city":"Seattle",
    "sg:classifiers":[
        {
            "category":"Shopping",
            "subcategory":"Jewelry",
            "type":"Retail Goods"
        },
        {
            "category":"Shopping",
            "subcategory":"Bridal",
            "type":"Retail Goods"
        }
    ],
    "sg:phone":"+1 206 625 0105",
    "sg:postcode":"98121",
    "sg:province":"WA",
    "sg:website":"www.seattlediamonds.com",
    "wof:name":"Gemological Trading Corporation",
    "wof:placetype":"venue"
},
  "geometry": {"coordinates":[-122.347488,47.611508],"type":"Point"}
}