{
  "type": "Feature",
  "properties": {
    "addr:full":"9011 14th Ave S Seattle WA 98108",
    "addr:housenumber":"9011",
    "addr:postcode":"98108",
    "addr:street":"14Th Ave S",
    "iso:country":"US",
    "sg:address":"9011 14th Ave S",
    "sg:city":"Seattle",
    "sg:classifiers":[
        {
            "category":"Professional",
            "subcategory":"Business Services",
            "type":"Services"
        }
    ],
    "sg:phone":"+1 206 524 6269",
    "sg:postcode":"98108",
    "sg:province":"WA",
    "sg:tags":[
        "translator",
        "interpreter"
    ],
    "wof:name":"Interpreters International",
    "wof:placetype":"venue"
},
  "geometry": {"coordinates":[-122.31505799999999,47.522284],"type":"Point"}
}