{
  "type": "Feature",
  "properties": {
    "addr:full":"141 Orchard Rite Rd Yakima WA 98908",
    "addr:housenumber":"141",
    "addr:postcode":"98908",
    "addr:street":"Orchard Rite Rd",
    "iso:country":"US",
    "sg:address":"141 Orchard Rite Rd",
    "sg:city":"Yakima",
    "sg:classifiers":[
        {
            "category":"Freight",
            "type":"Transportation"
        }
    ],
    "sg:phone":"+1 509 965 4374",
    "sg:postcode":"98908",
    "sg:province":"WA",
    "sg:tags":[
        "operator",
        "local",
        "trucking"
    ],
    "wof:name":"Mt Adams Trucking",
    "wof:placetype":"venue"
},
  "geometry": {"coordinates":[-120.632971,46.671492],"type":"Point"}
}