{
  "type": "Feature",
  "properties": {
    "addr:full":"2027 15th Ave S Seattle WA 98144",
    "addr:housenumber":"2027",
    "addr:postcode":"98144",
    "addr:street":"15Th Ave S",
    "iso:country":"US",
    "sg:address":"2027 15th Ave S",
    "sg:city":"Seattle",
    "sg:classifiers":[
        {
            "category":"Wholesale",
            "subcategory":"Durable Goods & Equipment",
            "type":"Manufacturing & Wholesale Goods"
        }
    ],
    "sg:phone":"+1 206 726 7629",
    "sg:postcode":"98144",
    "sg:province":"WA",
    "wof:name":"Crystal Star International",
    "wof:placetype":"venue"
},
  "geometry": {"coordinates":[-122.31345399999999,47.584805],"type":"Point"}
}