{
  "type": "Feature",
  "properties": {
    "addr:full":"15 Hope Ln Eastsound WA 98245",
    "addr:housenumber":"15",
    "addr:postcode":"98245",
    "addr:street":"Hope Ln",
    "iso:country":"US",
    "sg:address":"15 Hope Ln",
    "sg:city":"Eastsound",
    "sg:classifiers":[
        {
            "category":"Building & Trades",
            "subcategory":"Plumbing",
            "type":"Services"
        }
    ],
    "sg:phone":"+1 360 385 1076",
    "sg:postcode":"98245",
    "sg:province":"WA",
    "sg:tags":[
        "tank",
        "septic"
    ],
    "wof:name":"Jerry Lindsey Excavating",
    "wof:placetype":"venue"
},
  "geometry": {"coordinates":[-122.91547799999999,48.702184],"type":"Point"}
}