{
  "type": "Feature",
  "properties": {
    "addr:full":"2171 Erlands Point Rd NW Bremerton WA 98312",
    "addr:housenumber":"2171",
    "addr:postcode":"98312",
    "addr:street":"Erlands Point Rd Nw",
    "iso:country":"US",
    "sg:address":"2171 Erlands Point Rd NW",
    "sg:city":"Bremerton",
    "sg:classifiers":[
        {
            "category":"Bars & Pubs",
            "type":"Food & Drink"
        }
    ],
    "sg:phone":"+1 360 479 9077",
    "sg:postcode":"98312",
    "sg:province":"WA",
    "sg:tags":[
        "drinking"
    ],
    "wof:name":"19th Hole Tavern",
    "wof:placetype":"venue"
},
  "geometry": {"coordinates":[-122.70616800000001,47.596313],"type":"Point"}
}