{
  "type": "Feature",
  "properties": {
    "addr:full":"706 Grade St Kelso WA 98626",
    "addr:housenumber":"706",
    "addr:postcode":"98626",
    "addr:street":"Grade St",
    "iso:country":"US",
    "sg:address":"706 Grade St",
    "sg:city":"Kelso",
    "sg:classifiers":[
        {
            "category":"Home & Garden",
            "subcategory":"Building Materials",
            "type":"Retail Goods"
        }
    ],
    "sg:phone":"+1 360 423 2154",
    "sg:postcode":"98626",
    "sg:province":"WA",
    "sg:tags":[
        "glass",
        "window",
        "plate"
    ],
    "wof:name":"Palmer's Glass Co",
    "wof:placetype":"venue"
},
  "geometry": {"coordinates":[-122.906809,46.141684],"type":"Point"}
}