{
  "type": "Feature",
  "properties": {
    "addr:full":"7608 Aurora Ave N Seattle WA 98103",
    "addr:housenumber":"7608",
    "addr:postcode":"98103",
    "addr:street":"Aurora Ave N",
    "iso:country":"US",
    "sg:address":"7608 Aurora Ave N",
    "sg:city":"Seattle",
    "sg:classifiers":[
        {
            "category":"Place Of Worship",
            "type":"Public Place"
        }
    ],
    "sg:phone":"+1 206 525 1840",
    "sg:postcode":"98103",
    "sg:province":"WA",
    "sg:tags":[
        "church"
    ],
    "wof:name":"I Am Reading Room",
    "wof:placetype":"venue"
},
  "geometry": {"coordinates":[-122.3445,47.684118],"type":"Point"}
}