{
  "type": "Feature",
  "properties": {
    "iso:country":"US",
    "sg:address":"17849 Garden Way NE",
    "sg:city":"Woodinville",
    "sg:classifiers":[
        {
            "category":"Home & Garden",
            "subcategory":"Home Furnishings",
            "type":"Retail Goods"
        }
    ],
    "sg:phone":"+1 425 486 9921",
    "sg:postcode":"98072",
    "sg:province":"WA",
    "wof:name":"Linens n Things",
    "wof:placetype":"venue"
},
  "geometry": {"coordinates":[-122.154409,47.757373],"type":"Point"}
}