{
  "type": "Feature",
  "properties": {
    "addr:full":"12924 Old Snohomish Monroe Rd Snohomish WA 98290",
    "addr:housenumber":"12924",
    "addr:postcode":"98290",
    "addr:street":"Old Snohomish Monroe Rd",
    "iso:country":"US",
    "sg:address":"12924 Old Snohomish Monroe Rd",
    "sg:city":"Snohomish",
    "sg:classifiers":[
        {
            "category":"Building & Trades",
            "subcategory":"Plumbing",
            "type":"Services"
        }
    ],
    "sg:phone":"+1 360 568 9653",
    "sg:postcode":"98290",
    "sg:province":"WA",
    "sg:tags":[
        "plumbing",
        "contractor"
    ],
    "wof:name":"Wolfe Plumbing Inc",
    "wof:placetype":"venue"
},
  "geometry": {"coordinates":[-122.054711,47.881855],"type":"Point"}
}