{
  "type": "Feature",
  "properties": {
    "addr:full":"3007 Hunts Point Cir Bellevue WA 98004",
    "addr:housenumber":"3007",
    "addr:postcode":"98004",
    "addr:street":"Hunts Point Cir",
    "iso:country":"US",
    "sg:address":"3007 Hunts Point Cir",
    "sg:city":"Bellevue",
    "sg:classifiers":[
        {
            "category":"Professional",
            "subcategory":"Lawyer & Legal Services",
            "type":"Services"
        }
    ],
    "sg:phone":"+1 425 688 8845",
    "sg:postcode":"98004",
    "sg:province":"WA",
    "wof:name":"Evergreen Estate Services",
    "wof:placetype":"venue"
},
  "geometry": {"coordinates":[-122.22972900000001,47.636806],"type":"Point"}
}