{
  "type": "Feature",
  "properties": {
    "addr:full":"711 Haggen Dr Burlington WA 98233",
    "addr:housenumber":"711",
    "addr:postcode":"98233",
    "addr:street":"Haggen Dr",
    "iso:country":"US",
    "sg:address":"711 Haggen Dr",
    "sg:city":"Burlington",
    "sg:classifiers":[
        {
            "category":"Bakery",
            "type":"Food & Drink"
        }
    ],
    "sg:menulink":"http://www.allmenus.com/wa/burlington/121435-krispy-kreme/menu/",
    "sg:phone":"+1 360 707 2000",
    "sg:postcode":"98233",
    "sg:province":"WA",
    "sg:tags":[
        "american",
        "pastry"
    ],
    "wof:name":"Krispy Kreme",
    "wof:placetype":"venue"
},
  "geometry": {"coordinates":[-122.33615500000001,48.469858],"type":"Point"}
}