{
  "type": "Feature",
  "properties": {
    "addr:full":"2731 S Judkins St Seattle WA 98144",
    "addr:housenumber":"2731",
    "addr:postcode":"98144",
    "addr:street":"S Judkins St",
    "iso:country":"US",
    "sg:address":"2731 S Judkins St",
    "sg:city":"Seattle",
    "sg:classifiers":[
        {
            "category":"Building & Trades",
            "subcategory":"Construction",
            "type":"Services"
        }
    ],
    "sg:phone":"+1 206 325 3208",
    "sg:postcode":"98144",
    "sg:province":"WA",
    "sg:tags":[
        "plastering",
        "drywall",
        "contractor"
    ],
    "wof:name":"John Callen Drywall Work",
    "wof:placetype":"venue"
},
  "geometry": {"coordinates":[-122.297152,47.592016],"type":"Point"}
}