{
  "type": "Feature",
  "properties": {
    "addr:full":"10510 NE 135th Ln Kirkland WA 98034",
    "addr:housenumber":"10510",
    "addr:postcode":"98034",
    "addr:street":"Ne 135Th Ln",
    "iso:country":"US",
    "sg:address":"10510 NE 135th Ln",
    "sg:city":"Kirkland",
    "sg:classifiers":[
        {
            "category":"Professional",
            "subcategory":"Management & Consulting",
            "type":"Services"
        }
    ],
    "sg:phone":"+1 425 820 1485",
    "sg:postcode":"98034",
    "sg:province":"WA",
    "wof:name":"James Management Inc",
    "wof:placetype":"venue"
},
  "geometry": {"coordinates":[-122.201587,47.721175],"type":"Point"}
}