{
  "type": "Feature",
  "properties": {
    "addr:full":"1400 S Main St Ste 109 Seattle WA 98144",
    "addr:housenumber":"1400",
    "addr:postcode":"98144",
    "addr:street":"S Main St Ste 109",
    "iso:country":"US",
    "sg:address":"1400 S Main St Ste 109",
    "sg:city":"Seattle",
    "sg:classifiers":[
        {
            "category":"Real Estate",
            "subcategory":"Real Estate Services",
            "type":"Services"
        },
        {
            "category":"Real Estate",
            "subcategory":"Real Estate Operator",
            "type":"Services"
        }
    ],
    "sg:phone":"+1 206 325 9810",
    "sg:postcode":"98144",
    "sg:province":"WA",
    "sg:tags":[
        "apartment",
        "vacancy",
        "listing",
        "rental",
        "finder"
    ],
    "wof:name":"Wisteria View Manor",
    "wof:placetype":"venue"
},
  "geometry": {"coordinates":[-122.314003,47.599998],"type":"Point"}
}