{
  "type": "Feature",
  "properties": {
    "addr:full":"19330 SE 270th Pl Kent WA 98042",
    "addr:postcode":"19330;98042",
    "addr:street":"Se 270Th Pl",
    "iso:country":"US",
    "sg:address":"19330 SE 270th Pl",
    "sg:city":"Kent",
    "sg:classifiers":[
        {
            "category":"Social Services",
            "subcategory":"Child Care",
            "type":"Services"
        }
    ],
    "sg:phone":"+1 253 639 9157",
    "sg:postcode":"98042",
    "sg:province":"WA",
    "sg:tags":[
        "day"
    ],
    "wof:name":"Loris Little Ones",
    "wof:placetype":"venue"
},
  "geometry": {"coordinates":[-122.08447,47.359131],"type":"Point"}
}