{
  "type": "Feature",
  "properties": {
    "addr:full":"3450 W Blaine St Seattle WA 98199",
    "addr:housenumber":"3450",
    "addr:postcode":"98199",
    "addr:street":"W Blaine St",
    "iso:country":"US",
    "sg:address":"3450 W Blaine St",
    "sg:city":"Seattle",
    "sg:classifiers":[
        {
            "category":"Professional",
            "subcategory":"Engineering",
            "type":"Services"
        }
    ],
    "sg:phone":"+1 206 213 0182",
    "sg:postcode":"98199",
    "sg:province":"WA",
    "wof:name":"Diagnostic Imagining Cons",
    "wof:placetype":"venue"
},
  "geometry": {"coordinates":[-122.39994299999999,47.635904],"type":"Point"}
}