{
  "type": "Feature",
  "properties": {
    "addr:full":"118 Schoonover Rd Mossyrock WA 98564",
    "addr:housenumber":"118",
    "addr:postcode":"98564",
    "addr:street":"Schoonover Rd",
    "iso:country":"US",
    "sg:address":"118 Schoonover Rd",
    "sg:city":"Mossyrock",
    "sg:classifiers":[
        {
            "category":"Recreation",
            "type":"Entertainment"
        }
    ],
    "sg:phone":"+1 253 983 3482",
    "sg:postcode":"98564",
    "sg:province":"WA",
    "wof:name":"Berrys Trdtnal Taekwon Do Krte",
    "wof:placetype":"venue"
},
  "geometry": {"coordinates":[-122.45032500000001,46.516259],"type":"Point"}
}