{
  "type": "Feature",
  "properties": {
    "addr:full":"1115 W Clark St Pasco WA 99301",
    "addr:housenumber":"1115",
    "addr:postcode":"99301",
    "addr:street":"W Clark St",
    "iso:country":"US",
    "sg:address":"1115 W Clark St",
    "sg:city":"Pasco",
    "sg:classifiers":[
        {
            "category":"Banks & Credit Unions",
            "subcategory":"Bank",
            "type":"Services"
        }
    ],
    "sg:phone":"+1 509 547 3357",
    "sg:postcode":"99301",
    "sg:province":"WA",
    "sg:website":"www.bankofthewest.com",
    "wof:name":"Bank of the West",
    "wof:placetype":"venue"
},
  "geometry": {"coordinates":[-119.10321,46.229173],"type":"Point"}
}