{
  "type": "Feature",
  "properties": {
    "iso:country":"US",
    "sg:address":"6628 212th St SW",
    "sg:city":"Lynnwood",
    "sg:classifiers":[
        {
            "category":"Insurance",
            "subcategory":"Insurance Agent",
            "type":"Services"
        }
    ],
    "sg:phone":"+1 425 774 1215",
    "sg:postcode":"98036",
    "sg:province":"WA",
    "sg:tags":[
        "home"
    ],
    "wof:name":"Mobile Home Owners",
    "wof:placetype":"venue"
},
  "geometry": {"coordinates":[-122.32287700000001,47.806703],"type":"Point"}
}