{
  "type": "Feature",
  "properties": {
    "addr:full":"2941 S 38th St Ste D Tacoma WA 98409",
    "addr:housenumber":"2941",
    "addr:postcode":"98409",
    "addr:street":"S 38Th St Ste D",
    "iso:country":"US",
    "sg:address":"2941 S 38th St Ste D",
    "sg:city":"Tacoma",
    "sg:classifiers":[
        {
            "category":"Shopping",
            "subcategory":"Clothing, Apparel, & Fashions",
            "type":"Retail Goods"
        }
    ],
    "sg:phone":"+1 253 476 0012",
    "sg:postcode":"98409",
    "sg:province":"WA",
    "sg:tags":[
        "apparel",
        "women's"
    ],
    "sg:website":"http://Avenue.com",
    "wof:name":"Avenue",
    "wof:placetype":"venue"
},
  "geometry": {"coordinates":[-122.474992,47.222432],"type":"Point"}
}