{
  "type": "Feature",
  "properties": {
    "addr:full":"3795 Sunnyslope Rd SW Port Orchard WA 98367",
    "addr:housenumber":"3795",
    "addr:postcode":"98367",
    "addr:street":"Sunnyslope Rd Sw Port Orchard",
    "iso:country":"US",
    "sg:address":"3795 Sunnyslope Rd SW",
    "sg:city":"Port Orchard",
    "sg:classifiers":[
        {
            "category":"Social Services",
            "subcategory":"Child Care",
            "type":"Services"
        }
    ],
    "sg:phone":"+1 360 674 2848",
    "sg:postcode":"98367",
    "sg:province":"WA",
    "sg:tags":[
        "day"
    ],
    "wof:name":"Beverly Winsett",
    "wof:placetype":"venue"
},
  "geometry": {"coordinates":[-122.734021,47.514872],"type":"Point"}
}