{
  "type": "Feature",
  "properties": {
    "addr:full":"226 Cramer Ln Eastsound WA 98245",
    "addr:housenumber":"226",
    "addr:postcode":"98245",
    "addr:street":"Cramer Ln",
    "iso:country":"US",
    "sg:address":"226 Cramer Ln",
    "sg:city":"Eastsound",
    "sg:classifiers":[
        {
            "category":"Building & Trades",
            "subcategory":"Landscaping Services",
            "type":"Services"
        }
    ],
    "sg:phone":"+1 360 376 6522",
    "sg:postcode":"98245",
    "sg:province":"WA",
    "wof:name":"Lutz Tree Service",
    "wof:placetype":"venue"
},
  "geometry": {"coordinates":[-122.95392200000001,48.686175],"type":"Point"}
}