{
  "type": "Feature",
  "properties": {
    "addr:full":"400 W Holly St Bellingham WA 98225",
    "addr:housenumber":"400",
    "addr:postcode":"98225",
    "addr:street":"W Holly St",
    "iso:country":"US",
    "sg:address":"400 W Holly St",
    "sg:city":"Bellingham",
    "sg:classifiers":[
        {
            "category":"Restaurant",
            "type":"Food & Drink"
        }
    ],
    "sg:phone":"+1 360 734 5555",
    "sg:postcode":"98225",
    "sg:province":"WA",
    "sg:tags":[
        "eating"
    ],
    "wof:name":"Boss Tweed Restaurant",
    "wof:placetype":"venue"
},
  "geometry": {"coordinates":[-122.48333100000001,48.752461],"type":"Point"}
}