{
  "type": "Feature",
  "properties": {
    "addr:full":"2000 Franklin St Bellingham WA 98225",
    "addr:housenumber":"2000",
    "addr:postcode":"98225",
    "addr:street":"Franklin St",
    "iso:country":"US",
    "sg:address":"2000 Franklin St",
    "sg:city":"Bellingham",
    "sg:classifiers":[
        {
            "category":"Retail",
            "subcategory":"Auto Repair",
            "type":"Services"
        }
    ],
    "sg:phone":"+1 360 733 1130",
    "sg:postcode":"98225",
    "sg:province":"WA",
    "sg:tags":[
        "automotive",
        "w",
        "general"
    ],
    "wof:name":"Whatcom Equipment Repair",
    "wof:placetype":"venue"
},
  "geometry": {"coordinates":[-122.470727,48.757763],"type":"Point"}
}