{
  "type": "Feature",
  "properties": {
    "addr:full":"2 S Horton St Seattle WA 98134",
    "addr:housenumber":"2",
    "addr:postcode":"98134",
    "addr:street":"S Horton St",
    "iso:country":"US",
    "sg:address":"2 S Horton St",
    "sg:city":"Seattle",
    "sg:classifiers":[
        {
            "category":"Wholesale",
            "subcategory":"Groceries",
            "type":"Manufacturing & Wholesale Goods"
        }
    ],
    "sg:phone":"+1 206 382 1453",
    "sg:postcode":"98134",
    "sg:province":"WA",
    "sg:tags":[
        "broker",
        "sugar"
    ],
    "sg:website":"http://www.cargillsalt.com",
    "wof:name":"Cargill",
    "wof:placetype":"venue"
},
  "geometry": {"coordinates":[-122.33921100000001,47.574371],"type":"Point"}
}