{
  "type": "Feature",
  "properties": {
    "addr:full":"6335 Portal Way Ferndale WA 98248",
    "addr:housenumber":"6335",
    "addr:postcode":"98248",
    "addr:street":"Portal Way",
    "iso:country":"US",
    "sg:address":"6335 Portal Way",
    "sg:city":"Ferndale",
    "sg:classifiers":[
        {
            "category":"Travel",
            "subcategory":"Campground",
            "type":"Entertainment"
        }
    ],
    "sg:phone":"+1 360 384 2622",
    "sg:postcode":"98248",
    "sg:province":"WA",
    "sg:tags":[
        "recreational",
        "park",
        "vehicle"
    ],
    "wof:name":"Cedars Rv Resort",
    "wof:placetype":"venue"
},
  "geometry": {"coordinates":[-122.584298,48.874772],"type":"Point"}
}