{
  "type": "Feature",
  "properties": {
    "addr:full":"3011 78th Ave SE Mercer Island WA 98040",
    "addr:housenumber":"3011",
    "addr:postcode":"98040",
    "addr:street":"78Th Ave Se",
    "iso:country":"US",
    "sg:address":"3011 78th Ave SE",
    "sg:city":"Mercer Island",
    "sg:classifiers":[
        {
            "category":"Sports & Exercise",
            "subcategory":"Gym",
            "type":"Entertainment"
        }
    ],
    "sg:phone":"+1 206 275 1313",
    "sg:postcode":"98040",
    "sg:province":"WA",
    "sg:tags":[
        "trainer"
    ],
    "sg:website":"www.ftmercerisland.com",
    "wof:name":"Fitness Together",
    "wof:placetype":"venue"
},
  "geometry": {"coordinates":[-122.23371,47.583602],"type":"Point"}
}