{
  "type": "Feature",
  "properties": {
    "addr:full":"208 S. Jackson Street Seattle WA 98104",
    "addr:housenumber":"208",
    "addr:postcode":"98104",
    "addr:street":"S. Jackson Street",
    "iso:country":"US",
    "sg:address":"208 S. Jackson Street",
    "sg:city":"Seattle",
    "sg:classifiers":[
        {
            "category":"Personal",
            "subcategory":"Beauty Salon",
            "type":"Services"
        },
        {
            "category":"Shopping",
            "type":"Retail Goods"
        }
    ],
    "sg:phone":"+1 206 246 3488",
    "sg:postcode":"98104",
    "sg:province":"WA",
    "sg:tags":[
        "spa"
    ],
    "sg:website":"www.sweetpetula.com",
    "wof:name":"Sweet Petula",
    "wof:placetype":"venue"
},
  "geometry": {"coordinates":[-122.33147,47.59921],"type":"Point"}
}