{
  "type": "Feature",
  "properties": {
    "addr:full":"3020 S Clinton Rd Spokane Valley WA 99216",
    "addr:housenumber":"3020",
    "addr:postcode":"99216",
    "addr:street":"S Clinton Rd",
    "iso:country":"US",
    "sg:address":"3020 S Clinton Rd",
    "sg:city":"Spokane Valley",
    "sg:classifiers":[
        {
            "category":"Real Estate",
            "subcategory":"Real Estate Operator",
            "type":"Services"
        }
    ],
    "sg:phone":"+1 509 928 5050",
    "sg:postcode":"99216",
    "sg:province":"WA",
    "sg:tags":[
        "building",
        "apartment"
    ],
    "wof:name":"Amberwood Club Apartments",
    "wof:placetype":"venue"
},
  "geometry": {"coordinates":[-117.22769099999999,47.629001],"type":"Point"}
}