{
  "type": "Feature",
  "properties": {
    "addr:full":"1622 SW 98th St Seattle WA 98106",
    "addr:housenumber":"1622",
    "addr:postcode":"98106",
    "addr:street":"Sw 98Th St",
    "iso:country":"US",
    "sg:address":"1622 SW 98th St",
    "sg:city":"Seattle",
    "sg:classifiers":[
        {
            "category":"Autos & Motor Vehicles",
            "subcategory":"Automobile Sales",
            "type":"Retail Goods"
        }
    ],
    "sg:phone":"+1 206 762 7321",
    "sg:postcode":"98106",
    "sg:province":"WA",
    "sg:tags":[
        "automotive"
    ],
    "wof:name":"New SW Auto Repair",
    "wof:placetype":"venue"
},
  "geometry": {"coordinates":[-122.355446,47.515533],"type":"Point"}
}