{
  "type": "Feature",
  "properties": {
    "addr:full":"1002 E Seneca St Seattle WA 98122",
    "addr:housenumber":"1002",
    "addr:postcode":"98122",
    "addr:street":"E Seneca St",
    "iso:country":"US",
    "sg:address":"1002 E Seneca St",
    "sg:city":"Seattle",
    "sg:classifiers":[
        {
            "category":"Food & Beverages",
            "subcategory":"Groceries & Convenience Stores",
            "type":"Retail Goods"
        }
    ],
    "sg:phone":"+1 206 861 1543",
    "sg:postcode":"98122",
    "sg:province":"WA",
    "sg:tags":[
        "product"
    ],
    "wof:name":"Food Services",
    "wof:placetype":"venue"
},
  "geometry": {"coordinates":[-122.318347,47.612255],"type":"Point"}
}