{
  "type": "Feature",
  "properties": {
    "addr:full":"4918 Rainier Ave S Seattle WA 98118",
    "addr:housenumber":"4918",
    "addr:postcode":"98118",
    "addr:street":"Rainier Ave S",
    "iso:country":"US",
    "sg:address":"4918 Rainier Ave S",
    "sg:city":"Seattle",
    "sg:classifiers":[
        {
            "category":"Restaurant",
            "type":"Food & Drink"
        }
    ],
    "sg:phone":"+1 206 721 3501",
    "sg:postcode":"98118",
    "sg:province":"WA",
    "sg:tags":[
        "italian",
        "pizza"
    ],
    "sg:website":"www.tuttabella.com",
    "wof:name":"Tutta Bella Neapolitan Pizzeria",
    "wof:placetype":"venue"
},
  "geometry": {"coordinates":[-122.28443300000001,47.557202],"type":"Point"}
}