{
  "type": "Feature",
  "properties": {
    "addr:full":"864 S Cambridge Street Seattle WA 98108",
    "addr:housenumber":"864",
    "addr:postcode":"98108",
    "addr:street":"S Cambridge Street",
    "iso:country":"US",
    "sg:address":"864 S Cambridge Street",
    "sg:city":"Seattle",
    "sg:classifiers":[
        {
            "category":"Shopping",
            "subcategory":"Antiques",
            "type":"Retail Goods"
        }
    ],
    "sg:phone":"+1 206 767 0940",
    "sg:postcode":"98108",
    "sg:province":"WA",
    "wof:name":"Smith Trading Company",
    "wof:placetype":"venue"
},
  "geometry": {"coordinates":[-122.323151,47.518708],"type":"Point"}
}