{
  "type": "Feature",
  "properties": {
    "addr:full":"17118 NE 43rd Ter Redmond WA 98052",
    "addr:housenumber":"17118",
    "addr:postcode":"98052",
    "addr:street":"Ne 43Rd Ter",
    "iso:country":"US",
    "sg:address":"17118 NE 43rd Ter",
    "sg:city":"Redmond",
    "sg:classifiers":[
        {
            "category":"Shopping",
            "subcategory":"Hobbies, Toys, & Games",
            "type":"Retail Goods"
        }
    ],
    "sg:phone":"+1 425 558 0220",
    "sg:postcode":"98052",
    "sg:province":"WA",
    "wof:name":"Fairie Land Creations",
    "wof:placetype":"venue"
},
  "geometry": {"coordinates":[-122.111863,47.649096],"type":"Point"}
}