{
  "type": "Feature",
  "properties": {
    "addr:full":"14719 NE 177th St Woodinville WA 98072",
    "addr:housenumber":"14719",
    "addr:postcode":"98072",
    "addr:street":"Ne 177Th St",
    "iso:country":"US",
    "sg:address":"14719 NE 177th St",
    "sg:city":"Woodinville",
    "sg:classifiers":[
        {
            "category":"Retail",
            "subcategory":"Portrait Studio",
            "type":"Services"
        }
    ],
    "sg:phone":"+1 425 489 0895",
    "sg:postcode":"98072",
    "sg:province":"WA",
    "sg:tags":[
        "photo"
    ],
    "wof:name":"Carey Photography",
    "wof:placetype":"venue"
},
  "geometry": {"coordinates":[-122.14373000000001,47.755808],"type":"Point"}
}