{
  "type": "Feature",
  "properties": {
    "addr:full":"5 S Wenatchee Ave Wenatchee WA 98801",
    "addr:housenumber":"5",
    "addr:postcode":"98801",
    "addr:street":"S Wenatchee Ave",
    "iso:country":"US",
    "sg:address":"5 S Wenatchee Ave",
    "sg:city":"Wenatchee",
    "sg:classifiers":[
        {
            "category":"Personal",
            "subcategory":"Beauty Salon",
            "type":"Services"
        }
    ],
    "sg:phone":"+1 509 667 2577",
    "sg:postcode":"98801",
    "sg:province":"WA",
    "wof:name":"Colors",
    "wof:placetype":"venue"
},
  "geometry": {"coordinates":[-120.31040299999999,47.423503],"type":"Point"}
}