{
  "type": "Feature",
  "properties": {
    "addr:full":"11311 Bridgeport Way SW Ste 303 Lakewood WA 98499",
    "addr:housenumber":"11311",
    "addr:postcode":"98499",
    "addr:street":"Bridgeport Way Sw Ste 303",
    "iso:country":"US",
    "sg:address":"11311 Bridgeport Way SW Ste 303",
    "sg:city":"Lakewood",
    "sg:classifiers":[
        {
            "category":"Health Services",
            "subcategory":"Doctor",
            "type":"Services"
        }
    ],
    "sg:phone":"+1 253 588 8000",
    "sg:postcode":"98499",
    "sg:province":"WA",
    "sg:tags":[
        "surgeon",
        "oral"
    ],
    "wof:name":"Lee Walter DDS",
    "wof:placetype":"venue"
},
  "geometry": {"coordinates":[-122.503998,47.154701],"type":"Point"}
}