{
  "type": "Feature",
  "properties": {
    "iso:country":"US",
    "sg:address":"2507 Summitview Ave",
    "sg:city":"Yakima",
    "sg:classifiers":[
        {
            "category":"Manufacturing",
            "subcategory":"Jewelry",
            "type":"Manufacturing & Wholesale Goods"
        }
    ],
    "sg:phone":"+1 509 457 5390",
    "sg:postcode":"98902",
    "sg:province":"WA",
    "wof:name":"Made For Fun",
    "wof:placetype":"venue"
},
  "geometry": {"coordinates":[-120.543499,46.599958],"type":"Point"}
}