{
  "type": "Feature",
  "properties": {
    "addr:full":"2427 W Sims Way Port Townsend WA 98368",
    "addr:housenumber":"2427",
    "addr:postcode":"98368",
    "addr:street":"W Sims Way",
    "iso:country":"US",
    "sg:address":"2427 W Sims Way",
    "sg:city":"Port Townsend",
    "sg:classifiers":[
        {
            "category":"Shopping",
            "subcategory":"Discount & Variety Stores",
            "type":"Retail Goods"
        }
    ],
    "sg:phone":"+1 360 385 6812",
    "sg:postcode":"98368",
    "sg:province":"WA",
    "wof:name":"Swains Dollar Store & Less",
    "wof:placetype":"venue"
},
  "geometry": {"coordinates":[-122.803765,48.102614],"type":"Point"}
}