{
  "type": "Feature",
  "properties": {
    "addr:full":"6700 NE 162nd Ave Vancouver WA 98682",
    "addr:housenumber":"6700",
    "addr:postcode":"98682",
    "addr:street":"Ne 162Nd Ave",
    "iso:country":"US",
    "sg:address":"6700 NE 162nd Ave",
    "sg:city":"Vancouver",
    "sg:classifiers":[
        {
            "category":"Restaurant",
            "type":"Food & Drink"
        }
    ],
    "sg:menulink":"http://www.allmenus.com/wa/orchards/217225-burgerville/menu/",
    "sg:phone":"+1 360 567 1550",
    "sg:postcode":"98682",
    "sg:province":"WA",
    "sg:tags":[
        "burger",
        "american"
    ],
    "wof:name":"Burgerville",
    "wof:placetype":"venue"
},
  "geometry": {"coordinates":[-122.507282,45.67112],"type":"Point"}
}