{
  "type": "Feature",
  "properties": {
    "addr:full":"1015 4th Ave N Seattle WA 98109",
    "addr:housenumber":"1015",
    "addr:postcode":"98109",
    "addr:street":"4Th Ave N",
    "iso:country":"US",
    "sg:address":"1015 4th Ave N",
    "sg:city":"Seattle",
    "sg:classifiers":[
        {
            "category":"Banks & Credit Unions",
            "subcategory":"Financial Services",
            "type":"Services"
        }
    ],
    "sg:phone":"+1 206 285 3932",
    "sg:postcode":"98109",
    "sg:province":"WA",
    "sg:tags":[
        "holding"
    ],
    "wof:name":"Mtb Assoc",
    "wof:placetype":"venue"
},
  "geometry": {"coordinates":[-122.348918,47.628223],"type":"Point"}
}