{
  "type": "Feature",
  "properties": {
    "addr:full":"405 S Broadway Ave Othello WA 99344",
    "addr:housenumber":"405",
    "addr:postcode":"99344",
    "addr:street":"S Broadway Ave Othello",
    "iso:country":"US",
    "sg:address":"405 S Broadway Ave",
    "sg:city":"Othello",
    "sg:classifiers":[
        {
            "category":"Home & Garden",
            "subcategory":"Furniture",
            "type":"Retail Goods"
        }
    ],
    "sg:phone":"+1 509 488 3198",
    "sg:postcode":"99344",
    "sg:province":"WA",
    "sg:tags":[
        "store"
    ],
    "wof:name":"Leroy Nelson",
    "wof:placetype":"venue"
},
  "geometry": {"coordinates":[-119.175529,46.82963],"type":"Point"}
}