{
  "type": "Feature",
  "properties": {
    "addr:full":"1430 NE Upper Dr Pullman WA 99163",
    "addr:housenumber":"1430",
    "addr:postcode":"99163",
    "addr:street":"Ne Upper Dr",
    "iso:country":"US",
    "sg:address":"1430 NE Upper Dr",
    "sg:city":"Pullman",
    "sg:classifiers":[
        {
            "category":"Professional",
            "subcategory":"Business Services",
            "type":"Services"
        }
    ],
    "sg:phone":"+1 509 332 7324",
    "sg:postcode":"99163",
    "sg:province":"WA",
    "wof:name":"Suarez Language Services",
    "wof:placetype":"venue"
},
  "geometry": {"coordinates":[-117.161272,46.737568],"type":"Point"}
}