{
  "type": "Feature",
  "properties": {
    "iso:country":"US",
    "sg:address":"2726 N Proctor St",
    "sg:city":"Tacoma",
    "sg:classifiers":[
        {
            "category":"Retail",
            "subcategory":"Repair Shop",
            "type":"Services"
        }
    ],
    "sg:phone":"+1 253 756 5000",
    "sg:postcode":"98407",
    "sg:province":"WA",
    "sg:tags":[
        "lock",
        "locksmith"
    ],
    "wof:name":"Corcorans Lock & Safe",
    "wof:placetype":"venue"
},
  "geometry": {"coordinates":[-122.48894199999999,47.272729],"type":"Point"}
}