{
  "type": "Feature",
  "properties": {
    "addr:full":"3824 Williamson Way Bellingham WA 98226",
    "addr:housenumber":"3824",
    "addr:postcode":"98226",
    "addr:street":"Williamson Way",
    "iso:country":"US",
    "sg:address":"3824 Williamson Way",
    "sg:city":"Bellingham",
    "sg:classifiers":[
        {
            "category":"Real Estate",
            "subcategory":"Real Estate Agent",
            "type":"Services"
        }
    ],
    "sg:phone":"+1 360 752 1800",
    "sg:postcode":"98226",
    "sg:province":"WA",
    "sg:tags":[
        "developer"
    ],
    "wof:name":"Wise Enterprises LLC",
    "wof:placetype":"venue"
},
  "geometry": {"coordinates":[-122.532025,48.781578],"type":"Point"}
}