{
  "type": "Feature",
  "properties": {
    "iso:country":"US",
    "sg:address":"1420 King St",
    "sg:city":"Bellingham",
    "sg:classifiers":[
        {
            "category":"Health Services",
            "subcategory":"Doctor",
            "type":"Services"
        }
    ],
    "sg:phone":"+1 360 671 4552",
    "sg:postcode":"98229",
    "sg:province":"WA",
    "wof:name":"Bellinghams Mildscom Dntl Care",
    "wof:placetype":"venue"
},
  "geometry": {"coordinates":[-122.46370899999999,48.747663],"type":"Point"}
}