{
  "type": "Feature",
  "properties": {
    "addr:full":"6400 Capitol Blvd SE Olympia WA 98501",
    "addr:housenumber":"6400",
    "addr:postcode":"98501",
    "addr:street":"Capitol Blvd Se",
    "iso:country":"US",
    "sg:address":"6400 Capitol Blvd SE",
    "sg:city":"Olympia",
    "sg:classifiers":[
        {
            "category":"Restaurant",
            "type":"Food & Drink"
        }
    ],
    "sg:menulink":"http://www.allmenus.com/wa/olympia/45416-eagans-drive-in--espresso/menu/",
    "sg:phone":"+1 360 357 9349",
    "sg:postcode":"98501",
    "sg:province":"WA",
    "sg:tags":[
        "burger",
        "american"
    ],
    "wof:name":"Eagan's Drive-In & Espresso",
    "wof:placetype":"venue"
},
  "geometry": {"coordinates":[-122.90665300000001,46.990676],"type":"Point"}
}