{
  "type": "Feature",
  "properties": {
    "addr:full":"12505 131st Ct NE Kirkland WA 98034",
    "addr:housenumber":"12505",
    "addr:postcode":"98034",
    "addr:street":"131St Ct Ne",
    "iso:country":"US",
    "sg:address":"12505 131st Ct NE",
    "sg:city":"Kirkland",
    "sg:classifiers":[
        {
            "category":"Communications",
            "type":"Services"
        }
    ],
    "sg:phone":"+1 425 732 6100",
    "sg:postcode":"98034",
    "sg:province":"WA",
    "wof:name":"Peak Communication Systems",
    "wof:placetype":"venue"
},
  "geometry": {"coordinates":[-122.166145,47.712765],"type":"Point"}
}