{
  "type": "Feature",
  "properties": {
    "addr:full":"16820 SE McGillivray Blvd Ste A Vancouver WA 98683",
    "addr:postcode":"16820;98683",
    "addr:street":"Se Mcgillivray Blvd Ste A",
    "iso:country":"US",
    "sg:address":"16820 SE McGillivray Blvd Ste A",
    "sg:city":"Vancouver",
    "sg:classifiers":[
        {
            "category":"Retail",
            "subcategory":"Veterinary Services",
            "type":"Services"
        }
    ],
    "sg:phone":"+1 360 892 2122",
    "sg:postcode":"98683",
    "sg:province":"WA",
    "sg:tags":[
        "veterinarian"
    ],
    "sg:website":"www.cascadeparkanimalhospital.com",
    "wof:name":"Cascade Park Animal Hospital",
    "wof:placetype":"venue"
},
  "geometry": {"coordinates":[-122.49924300000001,45.606288],"type":"Point"}
}