{
  "type": "Feature",
  "properties": {
    "addr:full":"2323 32nd Ave S Seattle WA 98144",
    "addr:housenumber":"2323",
    "addr:postcode":"98144",
    "addr:street":"32Nd Ave S",
    "iso:country":"US",
    "sg:address":"2323 32nd Ave S",
    "sg:city":"Seattle",
    "sg:classifiers":[
        {
            "category":"Food & Beverages",
            "subcategory":"Farmers Market",
            "type":"Retail Goods"
        }
    ],
    "sg:phone":"+1 206 763 1060",
    "sg:postcode":"98144",
    "sg:province":"WA",
    "sg:tags":[
        "vegetable",
        "fruit",
        "shipper",
        "grower"
    ],
    "wof:name":"City Fruit",
    "wof:placetype":"venue"
},
  "geometry": {"coordinates":[-122.291929,47.582163],"type":"Point"}
}