{
  "type": "Feature",
  "properties": {
    "addr:full":"1724 W Mallon Ave Spokane WA 99201",
    "addr:housenumber":"1724",
    "addr:postcode":"99201",
    "addr:street":"W Mallon Ave",
    "iso:country":"US",
    "sg:address":"1724 W Mallon Ave",
    "sg:city":"Spokane",
    "sg:classifiers":[
        {
            "category":"Social Services",
            "subcategory":"Adult Care",
            "type":"Services"
        }
    ],
    "sg:phone":"+1 509 327 5945",
    "sg:postcode":"99201",
    "sg:province":"WA",
    "sg:tags":[
        "residential"
    ],
    "wof:name":"Mallon Place",
    "wof:placetype":"venue"
},
  "geometry": {"coordinates":[-117.438112,47.665315],"type":"Point"}
}