{
  "type": "Feature",
  "properties": {
    "addr:full":"1310 177th Pl Long Beach WA 98631",
    "addr:housenumber":"1310",
    "addr:postcode":"98631",
    "addr:street":"177Th Pl",
    "iso:country":"US",
    "sg:address":"1310 177th Pl",
    "sg:city":"Long Beach",
    "sg:classifiers":[
        {
            "category":"Building & Trades",
            "subcategory":"Pest Control",
            "type":"Services"
        }
    ],
    "sg:phone":"+1 360 642 2133",
    "sg:postcode":"98631",
    "sg:province":"WA",
    "wof:name":"A & A Pest Control Inc",
    "wof:placetype":"venue"
},
  "geometry": {"coordinates":[-124.051574,46.430748],"type":"Point"}
}