{
  "type": "Feature",
  "properties": {
    "addr:full":"436 Index Ave Index WA 98256",
    "addr:housenumber":"436",
    "addr:postcode":"98256",
    "addr:street":"Index Ave",
    "iso:country":"US",
    "sg:address":"436 Index Ave",
    "sg:city":"Index",
    "sg:classifiers":[
        {
            "category":"Education",
            "subcategory":"School",
            "type":"Public Place"
        }
    ],
    "sg:phone":"+1 360 793 1330",
    "sg:postcode":"98256",
    "sg:province":"WA",
    "wof:name":"Index Elementary School",
    "wof:placetype":"venue"
},
  "geometry": {"coordinates":[-121.55671100000001,47.820386],"type":"Point"}
}