{
  "type": "Feature",
  "properties": {
    "addr:full":"5322 S Assembly Rd Spokane WA 99224",
    "addr:housenumber":"5322",
    "addr:postcode":"99224",
    "addr:street":"S Assembly Rd",
    "iso:country":"US",
    "sg:address":"5322 S Assembly Rd",
    "sg:city":"Spokane",
    "sg:classifiers":[
        {
            "category":"Recreation",
            "type":"Entertainment"
        }
    ],
    "sg:phone":"+1 509 924 4264",
    "sg:postcode":"99224",
    "sg:province":"WA",
    "wof:name":"Stables Blue Diamond",
    "wof:placetype":"venue"
},
  "geometry": {"coordinates":[-117.475582,47.600003],"type":"Point"}
}