{
  "type": "Feature",
  "properties": {
    "addr:full":"528 213th St SW Bothell WA 98021",
    "addr:housenumber":"528",
    "addr:postcode":"98021",
    "addr:street":"213Th St Sw",
    "iso:country":"US",
    "sg:address":"528 213th St SW",
    "sg:city":"Bothell",
    "sg:classifiers":[
        {
            "category":"Building & Trades",
            "subcategory":"Construction",
            "type":"Services"
        }
    ],
    "sg:phone":"+1 425 672 7219",
    "sg:postcode":"98021",
    "sg:province":"WA",
    "sg:tags":[
        "contractor"
    ],
    "wof:name":"Ricks Tile & Marble",
    "wof:placetype":"venue"
},
  "geometry": {"coordinates":[-122.23923600000001,47.804864],"type":"Point"}
}