{
  "type": "Feature",
  "properties": {
    "addr:full":"2731 Wetmore Ave Ste 410 Everett WA 98201",
    "addr:housenumber":"2731",
    "addr:postcode":"98201",
    "addr:street":"Wetmore Ave Ste 410",
    "iso:country":"US",
    "sg:address":"2731 Wetmore Ave Ste 410",
    "sg:city":"Everett",
    "sg:classifiers":[
        {
            "category":"Professional",
            "subcategory":"Lawyer & Legal Services",
            "type":"Services"
        }
    ],
    "sg:phone":"+1 425 252 8515",
    "sg:postcode":"98201",
    "sg:province":"WA",
    "sg:tags":[
        "clinic"
    ],
    "sg:website":"http://www.nwjustice.org",
    "wof:name":"Northwest Justice Project",
    "wof:placetype":"venue"
},
  "geometry": {"coordinates":[-122.20717500000001,47.981555],"type":"Point"}
}