{
  "type": "Feature",
  "properties": {
    "addr:full":"5812 S Adams St Tacoma WA 98409",
    "addr:housenumber":"5812",
    "addr:postcode":"98409",
    "addr:street":"S Adams St",
    "iso:country":"US",
    "sg:address":"5812 S Adams St",
    "sg:city":"Tacoma",
    "sg:classifiers":[
        {
            "category":"Building & Trades",
            "subcategory":"Construction",
            "type":"Services"
        }
    ],
    "sg:phone":"+1 253 475 4711",
    "sg:postcode":"98409",
    "sg:province":"WA",
    "sg:tags":[
        "concrete",
        "contractor"
    ],
    "wof:name":"South Tacoma Concrete",
    "wof:placetype":"venue"
},
  "geometry": {"coordinates":[-122.48665699999999,47.203591],"type":"Point"}
}