{
  "type": "Feature",
  "properties": {
    "addr:full":"1078 Tamarack Ln Port Angeles WA 98362",
    "addr:housenumber":"1078",
    "addr:postcode":"98362",
    "addr:street":"Tamarack Ln",
    "iso:country":"US",
    "sg:address":"1078 Tamarack Ln",
    "sg:city":"Port Angeles",
    "sg:classifiers":[
        {
            "category":"Professional",
            "subcategory":"Business Services",
            "type":"Services"
        }
    ],
    "sg:phone":"+1 360 452 1746",
    "sg:postcode":"98362",
    "sg:province":"WA",
    "wof:name":"Unique Treasures Inc",
    "wof:placetype":"venue"
},
  "geometry": {"coordinates":[-123.42144,48.08303],"type":"Point"}
}