{
  "type": "Feature",
  "properties": {
    "addr:full":"2202 Glenwood Hwy Goldendale WA 98620",
    "addr:housenumber":"2202",
    "addr:postcode":"98620",
    "addr:street":"Glenwood Hwy",
    "iso:country":"US",
    "sg:address":"2202 Glenwood Hwy",
    "sg:city":"Goldendale",
    "sg:classifiers":[
        {
            "category":"Farming",
            "subcategory":"Livestock Farm",
            "type":"Manufacturing & Wholesale Goods"
        }
    ],
    "sg:phone":"+1 509 773 6067",
    "sg:postcode":"98620",
    "sg:province":"WA",
    "sg:tags":[
        "feedlot",
        "field",
        "crop",
        "beef",
        "cattle"
    ],
    "wof:name":"Larry Williams",
    "wof:placetype":"venue"
},
  "geometry": {"coordinates":[-121.02499899999999,45.892447],"type":"Point"}
}