{
  "type": "Feature",
  "properties": {
    "addr:full":"3312 NE 55th St Seattle WA 98105",
    "addr:housenumber":"3312",
    "addr:postcode":"98105",
    "addr:street":"Ne 55Th St",
    "iso:country":"US",
    "sg:address":"3312 NE 55th St",
    "sg:city":"Seattle",
    "sg:classifiers":[
        {
            "category":"Shopping",
            "subcategory":"Jewelry",
            "type":"Retail Goods"
        }
    ],
    "sg:phone":"+1 206 408 1815",
    "sg:postcode":"98105",
    "sg:province":"WA",
    "wof:name":"United Gold",
    "wof:placetype":"venue"
},
  "geometry": {"coordinates":[-122.292486,47.66853],"type":"Point"}
}