{
  "type": "Feature",
  "properties": {
    "addr:full":"514 Smith St Port Orchard WA 98366",
    "addr:housenumber":"514",
    "addr:postcode":"98366",
    "addr:street":"Smith St",
    "iso:country":"US",
    "sg:address":"514 Smith St",
    "sg:city":"Port Orchard",
    "sg:classifiers":[
        {
            "category":"Building & Trades",
            "subcategory":"Construction",
            "type":"Services"
        }
    ],
    "sg:phone":"+1 360 895 1795",
    "sg:postcode":"98366",
    "sg:province":"WA",
    "sg:tags":[
        "contracting",
        "general"
    ],
    "wof:name":"Signature Kitchen & Interiors",
    "wof:placetype":"venue"
},
  "geometry": {"coordinates":[-122.639562,47.535347],"type":"Point"}
}