{
  "type": "Feature",
  "properties": {
    "addr:full":"8828 Stone Ave N Seattle WA 98103",
    "addr:housenumber":"8828",
    "addr:postcode":"98103",
    "addr:street":"Stone Ave N",
    "iso:country":"US",
    "sg:address":"8828 Stone Ave N",
    "sg:city":"Seattle",
    "sg:classifiers":[
        {
            "category":"Building & Trades",
            "subcategory":"Locksmith",
            "type":"Services"
        }
    ],
    "sg:phone":"+1 206 357 5214",
    "sg:postcode":"98103",
    "sg:province":"WA",
    "sg:tags":[
        "key"
    ],
    "wof:name":"All State Locksmith",
    "wof:placetype":"venue"
},
  "geometry": {"coordinates":[-122.34112399999999,47.693763],"type":"Point"}
}