{
  "type": "Feature",
  "properties": {
    "addr:full":"1007 Hewitt Ave Everett WA 98201",
    "addr:housenumber":"1007",
    "addr:postcode":"98201",
    "addr:street":"Hewitt Ave",
    "iso:country":"US",
    "sg:address":"1007 Hewitt Ave",
    "sg:city":"Everett",
    "sg:classifiers":[
        {
            "category":"Wholesale",
            "subcategory":"Durable Goods & Equipment",
            "type":"Manufacturing & Wholesale Goods"
        }
    ],
    "sg:phone":"+1 425 259 4888",
    "sg:postcode":"98201",
    "sg:province":"WA",
    "sg:tags":[
        "pull",
        "tab"
    ],
    "wof:name":"Viking Distributors Inc",
    "wof:placetype":"venue"
},
  "geometry": {"coordinates":[-122.21578100000001,47.979443],"type":"Point"}
}