{
  "type": "Feature",
  "properties": {
    "addr:full":"13623 88th Pl NE Kirkland WA 98034",
    "addr:housenumber":"13623",
    "addr:postcode":"98034",
    "addr:street":"88Th Pl Ne",
    "iso:country":"US",
    "sg:address":"13623 88th Pl NE",
    "sg:city":"Kirkland",
    "sg:classifiers":[
        {
            "category":"Manufacturing",
            "subcategory":"Glass & Minerals",
            "type":"Manufacturing & Wholesale Goods"
        }
    ],
    "sg:phone":"+1 425 820 5330",
    "sg:postcode":"98034",
    "sg:province":"WA",
    "sg:tags":[
        "product",
        "mfg"
    ],
    "wof:name":"First Choice Mirror & Glass",
    "wof:placetype":"venue"
},
  "geometry": {"coordinates":[-122.223613,47.72255],"type":"Point"}
}