{
  "type": "Feature",
  "properties": {
    "addr:full":"41020 State Rte 20 Oak Harbor WA 98277",
    "addr:housenumber":"41020",
    "addr:postcode":"98277",
    "addr:street":"State Rte 20",
    "iso:country":"US",
    "sg:address":"41020 State Rte 20",
    "sg:city":"Oak Harbor",
    "sg:classifiers":[
        {
            "category":"Restaurant",
            "type":"Food & Drink"
        }
    ],
    "sg:phone":"+1 360 679 3194",
    "sg:postcode":"98277",
    "sg:province":"WA",
    "sg:tags":[
        "eating"
    ],
    "wof:name":"Island Grill",
    "wof:placetype":"venue"
},
  "geometry": {"coordinates":[-122.645861,48.396974],"type":"Point"}
}