{
  "type": "Feature",
  "properties": {
    "iso:country":"US",
    "sg:address":"30 B St NE",
    "sg:city":"Auburn",
    "sg:classifiers":[
        {
            "category":"Manufacturing",
            "subcategory":"Apparel",
            "type":"Manufacturing & Wholesale Goods"
        }
    ],
    "sg:phone":"+1 253 804 9193",
    "sg:postcode":"98002",
    "sg:province":"WA",
    "sg:tags":[
        "embroidery"
    ],
    "wof:name":"Embroidery Designs Unlimited",
    "wof:placetype":"venue"
},
  "geometry": {"coordinates":[-122.22676300000001,47.30805],"type":"Point"}
}