{
  "type": "Feature",
  "properties": {
    "addr:full":"740 126th Ave NE Bellevue WA 98005",
    "addr:housenumber":"740",
    "addr:postcode":"98005",
    "addr:street":"126Th Ave Ne",
    "iso:country":"US",
    "sg:address":"740 126th Ave NE",
    "sg:city":"Bellevue",
    "sg:classifiers":[
        {
            "category":"Communications",
            "subcategory":"Film & Video Production",
            "type":"Services"
        }
    ],
    "sg:phone":"+1 425 590 4173",
    "sg:postcode":"98005",
    "sg:province":"WA",
    "sg:tags":[
        "motion"
    ],
    "wof:name":"Gramham Albertini",
    "wof:placetype":"venue"
},
  "geometry": {"coordinates":[-122.172239,47.617199],"type":"Point"}
}