{
  "type": "Feature",
  "properties": {
    "addr:full":"1934 E Isaacs Ave Walla Walla WA 99362",
    "addr:housenumber":"1934",
    "addr:postcode":"99362",
    "addr:street":"E Isaacs Ave",
    "iso:country":"US",
    "sg:address":"1934 E Isaacs Ave",
    "sg:city":"Walla Walla",
    "sg:classifiers":[
        {
            "category":"Shopping",
            "type":"Retail Goods"
        }
    ],
    "sg:phone":"+1 509 529 5677",
    "sg:postcode":"99362",
    "sg:province":"WA",
    "sg:tags":[
        "merchandise"
    ],
    "wof:name":"UPS Store",
    "wof:placetype":"venue"
},
  "geometry": {"coordinates":[-118.307491,46.075007],"type":"Point"}
}