{
  "type": "Feature",
  "properties": {
    "addr:full":"1214 S 6th St Yakima WA 98901",
    "addr:housenumber":"1214",
    "addr:postcode":"98901",
    "addr:street":"S 6Th St",
    "iso:country":"US",
    "sg:address":"1214 S 6th St",
    "sg:city":"Yakima",
    "sg:classifiers":[
        {
            "category":"Professional",
            "type":"Services"
        }
    ],
    "sg:phone":"+1 509 469 7860",
    "sg:postcode":"98901",
    "sg:province":"WA",
    "wof:name":"Centro Botanero El Parian",
    "wof:placetype":"venue"
},
  "geometry": {"coordinates":[-120.494552,46.58723],"type":"Point"}
}