{
  "type": "Feature",
  "properties": {
    "addr:full":"13521 N Mill Rd Spokane WA 99208",
    "addr:housenumber":"13521",
    "addr:postcode":"99208",
    "addr:street":"N Mill Rd",
    "iso:country":"US",
    "sg:address":"13521 N Mill Rd",
    "sg:city":"Spokane",
    "sg:classifiers":[
        {
            "category":"Education",
            "subcategory":"Preschool",
            "type":"Public Place"
        },
        {
            "category":"Education",
            "subcategory":"School",
            "type":"Public Place"
        }
    ],
    "sg:phone":"+1 509 467 6014",
    "sg:postcode":"99208",
    "sg:province":"WA",
    "sg:tags":[
        "kindergarten",
        "interest",
        "religious",
        "k-",
        "private"
    ],
    "wof:name":"Christian Northview School",
    "wof:placetype":"venue"
},
  "geometry": {"coordinates":[-117.411672,47.780268],"type":"Point"}
}