{
  "type": "Feature",
  "properties": {
    "addr:full":"24610 53rd Ave Ct E Graham WA 98338",
    "addr:housenumber":"24610",
    "addr:postcode":"98338",
    "addr:street":"53Rd Ave Ct E",
    "iso:country":"US",
    "sg:address":"24610 53rd Ave Ct E",
    "sg:city":"Graham",
    "sg:classifiers":[
        {
            "category":"Building & Trades",
            "subcategory":"Construction",
            "type":"Services"
        }
    ],
    "sg:phone":"+1 253 846 7609",
    "sg:postcode":"98338",
    "sg:province":"WA",
    "sg:tags":[
        "carpentry",
        "contractor"
    ],
    "wof:name":"Hastings Enterprises NW LLC",
    "wof:placetype":"venue"
},
  "geometry": {"coordinates":[-122.358524,47.032473],"type":"Point"}
}