{
  "type": "Feature",
  "properties": {
    "addr:full":"1001 E 8th Ave Ellensburg WA 98926",
    "addr:housenumber":"1001",
    "addr:postcode":"98926",
    "addr:street":"E 8Th Ave",
    "iso:country":"US",
    "sg:address":"1001 E 8th Ave",
    "sg:city":"Ellensburg",
    "sg:classifiers":[
        {
            "category":"Food & Beverages",
            "subcategory":"Groceries & Convenience Stores",
            "type":"Retail Goods"
        }
    ],
    "sg:phone":"+1 509 925 1605",
    "sg:postcode":"98926",
    "sg:province":"WA",
    "wof:name":"7-Eleven",
    "wof:placetype":"venue"
},
  "geometry": {"coordinates":[-120.53351000000001,46.999978],"type":"Point"}
}