{
  "type": "Feature",
  "properties": {
    "iso:country":"US",
    "sg:address":"212 NE 164th Ave",
    "sg:city":"Vancouver",
    "sg:classifiers":[
        {
            "category":"Personal",
            "type":"Services"
        }
    ],
    "sg:phone":"+1 360 896 5291",
    "sg:postcode":"98684",
    "sg:province":"WA",
    "wof:name":"California Tan Two",
    "wof:placetype":"venue"
},
  "geometry": {"coordinates":[-122.504268,45.621362],"type":"Point"}
}