{
  "type": "Feature",
  "properties": {
    "addr:full":"Greenwood Ave N and N 85th Seattle WA 98115",
    "addr:postcode":"98115",
    "addr:street":"Greenwood Ave N And N",
    "iso:country":"US",
    "sg:address":"Greenwood Ave N and N 85th",
    "sg:city":"Seattle",
    "sg:classifiers":[
        {
            "category":"Restaurant",
            "type":"Food & Drink"
        }
    ],
    "sg:postcode":"98115",
    "sg:province":"WA",
    "wof:name":"The Sweet Life Organic Gelato",
    "wof:placetype":"venue"
},
  "geometry": {"coordinates":[-122.355306,47.690585],"type":"Point"}
}