{
  "type": "Feature",
  "properties": {
    "iso:country":"US",
    "sg:address":"8628 173rd Ave NE",
    "sg:city":"Redmond",
    "sg:classifiers":[
        {
            "category":"Wholesale",
            "subcategory":"Furniture",
            "type":"Manufacturing & Wholesale Goods"
        }
    ],
    "sg:phone":"+1 425 861 5799",
    "sg:postcode":"98052",
    "sg:province":"WA",
    "wof:name":"China Best A Trading Co",
    "wof:placetype":"venue"
},
  "geometry": {"coordinates":[-122.105835,47.680779],"type":"Point"}
}