{
  "type": "Feature",
  "properties": {
    "addr:full":"709 Alexander Ave E Tacoma WA 98424",
    "addr:housenumber":"709",
    "addr:postcode":"98424",
    "addr:street":"Alexander Ave E",
    "iso:country":"US",
    "sg:address":"709 Alexander Ave E",
    "sg:city":"Tacoma",
    "sg:classifiers":[
        {
            "category":"Professional",
            "subcategory":"Management & Consulting",
            "type":"Services"
        }
    ],
    "sg:phone":"+1 253 274 9760",
    "sg:postcode":"98424",
    "sg:province":"WA",
    "sg:tags":[
        "support",
        "facility"
    ],
    "wof:name":"Glenn Springs Holdings Inc",
    "wof:placetype":"venue"
},
  "geometry": {"coordinates":[-122.372922,47.248692],"type":"Point"}
}