{
  "type": "Feature",
  "properties": {
    "addr:full":"3011 S 15th St Ridgefield WA 98642",
    "addr:housenumber":"3011",
    "addr:postcode":"98642",
    "addr:street":"S 15Th St",
    "iso:country":"US",
    "sg:address":"3011 S 15th St",
    "sg:city":"Ridgefield",
    "sg:classifiers":[
        {
            "category":"Building & Trades",
            "subcategory":"Construction",
            "type":"Services"
        }
    ],
    "sg:phone":"+1 360 887 4284",
    "sg:postcode":"98642",
    "sg:province":"WA",
    "sg:tags":[
        "house"
    ],
    "wof:name":"Oberreuter Construction",
    "wof:placetype":"venue"
},
  "geometry": {"coordinates":[-122.720658,45.804671],"type":"Point"}
}