{
  "type": "Feature",
  "properties": {
    "addr:full":"970 S College Ave College Place WA 99324",
    "addr:housenumber":"970",
    "addr:postcode":"99324",
    "addr:street":"S College Ave",
    "iso:country":"US",
    "sg:address":"970 S College Ave",
    "sg:city":"College Place",
    "sg:classifiers":[
        {
            "category":"Education",
            "subcategory":"School",
            "type":"Public Place"
        }
    ],
    "sg:phone":"+1 509 525 0125",
    "sg:postcode":"99324",
    "sg:province":"WA",
    "wof:name":"Country Garden School",
    "wof:placetype":"venue"
},
  "geometry": {"coordinates":[-118.388627,46.040484],"type":"Point"}
}