{
  "type": "Feature",
  "properties": {
    "addr:full":"803 Lenora St Seattle WA 98121",
    "addr:housenumber":"803",
    "addr:postcode":"98121",
    "addr:street":"Lenora St",
    "iso:country":"US",
    "sg:address":"803 Lenora St",
    "sg:city":"Seattle",
    "sg:classifiers":[
        {
            "category":"Autos & Motor Vehicles",
            "subcategory":"Fuel & Gas Station",
            "type":"Retail Goods"
        },
        {
            "category":"Autos & Motor Vehicles",
            "subcategory":"Auto Supplies",
            "type":"Retail Goods"
        },
        {
            "category":"Retail",
            "subcategory":"Auto Repair",
            "type":"Services"
        },
        {
            "category":"Autos & Motor Vehicles",
            "subcategory":"Recreational Vehicle Sales",
            "type":"Retail Goods"
        }
    ],
    "sg:phone":"+1 206 801 0943",
    "sg:postcode":"98121",
    "sg:province":"WA",
    "sg:tags":[
        "engine",
        "radiator",
        "exchange",
        "transmission",
        "automobile",
        "equipment-service",
        "diagnostic",
        "brake",
        "automotive",
        "rebuilding",
        "tune",
        "engines-rebuild"
    ],
    "sg:website":"http://seattle.citysearch.com/profile/external/10797029/seattle_wa/the_import_doctors.html?publisher=yellowpages&reference_id=1&placement=ypwebsitemip",
    "wof:name":"The Import Doctors",
    "wof:placetype":"venue"
},
  "geometry": {"coordinates":[-122.337873,47.616503],"type":"Point"}
}