{
  "type": "Feature",
  "properties": {
    "addr:full":"1561 Whitmore Way Buckley WA 98321",
    "addr:housenumber":"1561",
    "addr:postcode":"98321",
    "addr:street":"Whitmore Way",
    "iso:country":"US",
    "sg:address":"1561 Whitmore Way",
    "sg:city":"Buckley",
    "sg:classifiers":[
        {
            "category":"Building & Trades",
            "subcategory":"Electrical",
            "type":"Services"
        }
    ],
    "sg:phone":"+1 360 829 2145",
    "sg:postcode":"98321",
    "sg:province":"WA",
    "sg:tags":[
        "electrical",
        "contractor"
    ],
    "wof:name":"Walthers Electric",
    "wof:placetype":"venue"
},
  "geometry": {"coordinates":[-122.014127,47.166059],"type":"Point"}
}