{
  "type": "Feature",
  "properties": {
    "iso:country":"US",
    "sg:address":"10121 N Nevada St",
    "sg:city":"Spokane",
    "sg:classifiers":[
        {
            "category":"Health Services",
            "subcategory":"Doctor",
            "type":"Services"
        }
    ],
    "sg:phone":"+1 509 466 6614",
    "sg:postcode":"99218",
    "sg:province":"WA",
    "sg:tags":[
        "dental"
    ],
    "wof:name":"Tracy Von R DDS",
    "wof:placetype":"venue"
},
  "geometry": {"coordinates":[-117.395358,47.748224],"type":"Point"}
}