{
  "type": "Feature",
  "properties": {
    "addr:full":"1637 Vantage Hwy Ellensburg WA 98926",
    "addr:housenumber":"1637",
    "addr:postcode":"98926",
    "addr:street":"Vantage Hwy",
    "iso:country":"US",
    "sg:address":"1637 Vantage Hwy",
    "sg:city":"Ellensburg",
    "sg:classifiers":[
        {
            "category":"Professional",
            "subcategory":"Lawyer & Legal Services",
            "type":"Services"
        }
    ],
    "sg:phone":"+1 509 933 7210",
    "sg:postcode":"98926",
    "sg:province":"WA",
    "wof:name":"Law Office of C K Heaverlo",
    "wof:placetype":"venue"
},
  "geometry": {"coordinates":[-120.522357,47.000521],"type":"Point"}
}