{
  "type": "Feature",
  "properties": {
    "addr:full":"2123 N 40th St Seattle WA 98103",
    "addr:housenumber":"2123",
    "addr:postcode":"98103",
    "addr:street":"N 40Th St",
    "iso:country":"US",
    "sg:address":"2123 N 40th St",
    "sg:city":"Seattle",
    "sg:classifiers":[
        {
            "category":"Shopping",
            "subcategory":"Comic Books",
            "type":"Retail Goods"
        }
    ],
    "sg:phone":"+1 206 547 3559",
    "sg:postcode":"98103",
    "sg:province":"WA",
    "wof:name":"Roadrunner Copy House",
    "wof:placetype":"venue"
},
  "geometry": {"coordinates":[-122.33360500000001,47.655604],"type":"Point"}
}