{
  "type": "Feature",
  "properties": {
    "addr:full":"4410 106th St SW Mukilteo WA 98275",
    "addr:housenumber":"4410",
    "addr:postcode":"98275",
    "addr:street":"106Th St Sw",
    "iso:country":"US",
    "sg:address":"4410 106th St SW",
    "sg:city":"Mukilteo",
    "sg:classifiers":[
        {
            "category":"Health Services",
            "subcategory":"Doctor",
            "type":"Services"
        }
    ],
    "sg:phone":"+1 425 259 0966",
    "sg:postcode":"98275",
    "sg:province":"WA",
    "sg:tags":[
        "physician",
        "surgeon"
    ],
    "wof:name":"The Everett Clinic",
    "wof:placetype":"venue"
},
  "geometry": {"coordinates":[-122.293075,47.902267],"type":"Point"}
}