{
  "type": "Feature",
  "properties": {
    "addr:full":"4200 SW Admiral Way Seattle WA 98116",
    "addr:housenumber":"4200",
    "addr:postcode":"98116",
    "addr:street":"Sw Admiral Way",
    "iso:country":"US",
    "sg:address":"4200 SW Admiral Way",
    "sg:city":"Seattle",
    "sg:classifiers":[
        {
            "category":"Retail",
            "subcategory":"Repair Shop",
            "type":"Services"
        }
    ],
    "sg:phone":"+1 206 932 6966",
    "sg:postcode":"98116",
    "sg:province":"WA",
    "sg:tags":[
        "plumbing",
        "drain",
        "cleaning",
        "sewer"
    ],
    "wof:name":"Bob's Plumbing & Sewer Svc",
    "wof:placetype":"venue"
},
  "geometry": {"coordinates":[-122.386548,47.581194],"type":"Point"}
}