{
  "type": "Feature",
  "properties": {
    "addr:full":"108 N Liberty St Port Angeles WA 98362",
    "addr:housenumber":"108",
    "addr:postcode":"98362",
    "addr:street":"N Liberty St",
    "iso:country":"US",
    "sg:address":"108 N Liberty St",
    "sg:city":"Port Angeles",
    "sg:classifiers":[
        {
            "category":"Professional",
            "subcategory":"Employment Agencies",
            "type":"Services"
        }
    ],
    "sg:phone":"+1 360 452 8961",
    "sg:postcode":"98362",
    "sg:province":"WA",
    "wof:name":"Priority Nursing",
    "wof:placetype":"venue"
},
  "geometry": {"coordinates":[-123.41139800000001,48.110363],"type":"Point"}
}