{
  "type": "Feature",
  "properties": {
    "addr:full":"654 E Division St Forks WA 98331",
    "addr:housenumber":"654",
    "addr:postcode":"98331",
    "addr:street":"E Division St",
    "iso:country":"US",
    "sg:address":"654 E Division St",
    "sg:city":"Forks",
    "sg:classifiers":[
        {
            "category":"Travel",
            "subcategory":"Hotels & Motels",
            "type":"Entertainment"
        },
        {
            "category":"Travel",
            "subcategory":"Bed & Breakfast",
            "type":"Entertainment"
        }
    ],
    "sg:phone":"+1 360 374 6806",
    "sg:postcode":"98331",
    "sg:province":"WA",
    "sg:tags":[
        "inn",
        "lodging"
    ],
    "sg:website":"http://www.millertreeinn.com",
    "wof:name":"Miller Tree Inn",
    "wof:placetype":"venue"
},
  "geometry": {"coordinates":[-124.377785,47.950378],"type":"Point"}
}