{
  "type": "Feature",
  "properties": {
    "addr:full":"16557 21st Ave NE Seattle WA 98155",
    "addr:housenumber":"16557",
    "addr:postcode":"98155",
    "addr:street":"21St Ave Ne",
    "iso:country":"US",
    "sg:address":"16557 21st Ave NE",
    "sg:city":"Seattle",
    "sg:classifiers":[
        {
            "category":"Wholesale",
            "subcategory":"Hardware",
            "type":"Manufacturing & Wholesale Goods"
        }
    ],
    "sg:phone":"+1 206 365 4956",
    "sg:postcode":"98155",
    "sg:province":"WA",
    "sg:tags":[
        "refrigeration"
    ],
    "wof:name":"Vaca Refrigeration",
    "wof:placetype":"venue"
},
  "geometry": {"coordinates":[-122.306861,47.749814],"type":"Point"}
}