{
  "type": "Feature",
  "properties": {
    "addr:full":"911 Boetzke Ave Manson WA 98831",
    "addr:housenumber":"911",
    "addr:postcode":"98831",
    "addr:street":"Boetzke Ave",
    "iso:country":"US",
    "sg:address":"911 Boetzke Ave",
    "sg:city":"Manson",
    "sg:classifiers":[
        {
            "category":"Building & Trades",
            "subcategory":"Construction",
            "type":"Services"
        }
    ],
    "sg:phone":"+1 509 687 3229",
    "sg:postcode":"98831",
    "sg:province":"WA",
    "sg:tags":[
        "house"
    ],
    "wof:name":"Smith Construction",
    "wof:placetype":"venue"
},
  "geometry": {"coordinates":[-120.17142800000001,47.888618],"type":"Point"}
}