{
  "type": "Feature",
  "properties": {
    "addr:full":"554 S 5th St Selah WA 98942",
    "addr:housenumber":"554",
    "addr:postcode":"98942",
    "addr:street":"S 5Th St",
    "iso:country":"US",
    "sg:address":"554 S 5th St",
    "sg:city":"Selah",
    "sg:classifiers":[
        {
            "category":"Real Estate",
            "subcategory":"Real Estate Operator",
            "type":"Services"
        }
    ],
    "sg:phone":"+1 509 697 9830",
    "sg:postcode":"98942",
    "sg:province":"WA",
    "sg:tags":[
        "building",
        "apartment"
    ],
    "wof:name":"Selah Park & Park Village Apts",
    "wof:placetype":"venue"
},
  "geometry": {"coordinates":[-120.535786,46.645687],"type":"Point"}
}