{
  "type": "Feature",
  "properties": {
    "addr:full":"23513 75th Ave W Edmonds WA 98026",
    "addr:housenumber":"23513",
    "addr:postcode":"98026",
    "addr:street":"75Th Ave W",
    "iso:country":"US",
    "sg:address":"23513 75th Ave W",
    "sg:city":"Edmonds",
    "sg:classifiers":[
        {
            "category":"Retail",
            "subcategory":"Repair Shop",
            "type":"Services"
        }
    ],
    "sg:phone":"+1 425 712 0329",
    "sg:postcode":"98026",
    "sg:province":"WA",
    "wof:name":"Sallys Cleaning",
    "wof:placetype":"venue"
},
  "geometry": {"coordinates":[-122.334194,47.788361],"type":"Point"}
}