{
  "type": "Feature",
  "properties": {
    "addr:full":"1025 S King St Seattle WA 98104",
    "addr:housenumber":"1025",
    "addr:postcode":"98104",
    "addr:street":"S King St",
    "iso:country":"US",
    "sg:address":"1025 S King St",
    "sg:city":"Seattle",
    "sg:classifiers":[
        {
            "category":"Retail",
            "subcategory":"Event Space",
            "type":"Services"
        }
    ],
    "sg:phone":"+1 206 860 8522",
    "sg:postcode":"98104",
    "sg:province":"WA",
    "sg:tags":[
        "venue"
    ],
    "sg:website":"www.asianresourcecenter.org",
    "wof:name":"Asian Resource Center",
    "wof:placetype":"venue"
},
  "geometry": {"coordinates":[-122.318398,47.597922],"type":"Point"}
}