{
  "type": "Feature",
  "properties": {
    "addr:full":"1102 23rd Ave Seattle WA 98122",
    "addr:housenumber":"1102",
    "addr:postcode":"98122",
    "addr:street":"23Rd Ave",
    "iso:country":"US",
    "sg:address":"1102 23rd Ave",
    "sg:city":"Seattle",
    "sg:classifiers":[
        {
            "category":"Shopping",
            "subcategory":"Department Store",
            "type":"Retail Goods"
        }
    ],
    "sg:phone":"+1 206 323 3283",
    "sg:postcode":"98122",
    "sg:province":"WA",
    "sg:tags":[
        "shop"
    ],
    "wof:name":"99 Cents Plus",
    "wof:placetype":"venue"
},
  "geometry": {"coordinates":[-122.302637,47.612929],"type":"Point"}
}