{
  "type": "Feature",
  "properties": {
    "addr:full":"219 Rodeo Trl Okanogan WA 98840",
    "addr:housenumber":"219",
    "addr:postcode":"98840",
    "addr:street":"Rodeo Trl",
    "iso:country":"US",
    "sg:address":"219 Rodeo Trl",
    "sg:city":"Okanogan",
    "sg:classifiers":[
        {
            "category":"Home & Garden",
            "subcategory":"Garden Supply",
            "type":"Retail Goods"
        }
    ],
    "sg:phone":"+1 509 422 1044",
    "sg:postcode":"98840",
    "sg:province":"WA",
    "sg:tags":[
        "bark"
    ],
    "wof:name":"Country Rock & Bark",
    "wof:placetype":"venue"
},
  "geometry": {"coordinates":[-119.54285299999999,48.380738],"type":"Point"}
}