{
  "type": "Feature",
  "properties": {
    "addr:full":"2104 10th Ave W Seattle WA 98119",
    "addr:housenumber":"2104",
    "addr:postcode":"98119",
    "addr:street":"10Th Ave W",
    "iso:country":"US",
    "sg:address":"2104 10th Ave W",
    "sg:city":"Seattle",
    "sg:classifiers":[
        {
            "category":"Recreation",
            "type":"Entertainment"
        }
    ],
    "sg:phone":"+1 206 283 0575",
    "sg:postcode":"98119",
    "sg:province":"WA",
    "wof:name":"Get Your Bearings Inline Skate",
    "wof:placetype":"venue"
},
  "geometry": {"coordinates":[-122.37022899999999,47.63957],"type":"Point"}
}