{
  "type": "Feature",
  "properties": {
    "addr:full":"601 108th Ave NE, Ste 1800 Bellevue WA 98004",
    "addr:housenumber":"601",
    "addr:postcode":"98004",
    "addr:street":"108Th Ave Ne Ste 1800",
    "iso:country":"US",
    "sg:address":"601 108th Ave NE, Ste 1800",
    "sg:city":"Bellevue",
    "sg:classifiers":[
        {
            "category":"Banks & Credit Unions",
            "subcategory":"Investment Brokerage",
            "type":"Services"
        },
        {
            "category":"Banks & Credit Unions",
            "subcategory":"Financial Services",
            "type":"Services"
        }
    ],
    "sg:phone":"+1 425 372 4800",
    "sg:postcode":"98004",
    "sg:province":"WA",
    "sg:tags":[
        "investing",
        "advising"
    ],
    "sg:website":"www.ameripriseadvisors.com",
    "wof:name":"Ameriprise Financial Advisors",
    "wof:placetype":"venue"
},
  "geometry": {"coordinates":[-122.196878,47.615846],"type":"Point"}
}