{
  "type": "Feature",
  "properties": {
    "iso:country":"US",
    "sg:address":"15104 Hwy 99",
    "sg:city":"Lynnwood",
    "sg:classifiers":[
        {
            "category":"Retail",
            "subcategory":"Auto Repair",
            "type":"Services"
        }
    ],
    "sg:phone":"+1 425 743 0220",
    "sg:postcode":"98087",
    "sg:province":"WA",
    "sg:tags":[
        "repairing",
        "automobile",
        "radiator"
    ],
    "wof:name":"Guaranteed Radiator Inc",
    "wof:placetype":"venue"
},
  "geometry": {"coordinates":[-122.284811,47.861334],"type":"Point"}
}