{
  "type": "Feature",
  "properties": {
    "addr:full":"12636 100th Ln NE Kirkland WA 98034",
    "addr:housenumber":"12636",
    "addr:postcode":"98034",
    "addr:street":"100Th Ln Ne",
    "iso:country":"US",
    "sg:address":"12636 100th Ln NE",
    "sg:city":"Kirkland",
    "sg:classifiers":[
        {
            "category":"Retail",
            "subcategory":"Car Wash",
            "type":"Services"
        }
    ],
    "sg:phone":"+1 425 241 2934",
    "sg:postcode":"98034",
    "sg:province":"WA",
    "sg:tags":[
        "carwash"
    ],
    "wof:name":"Eddies Mobile Auto Detailing",
    "wof:placetype":"venue"
},
  "geometry": {"coordinates":[-122.20702300000001,47.713688],"type":"Point"}
}