{
  "type": "Feature",
  "properties": {
    "addr:full":"285 Spring St Friday Harbor WA 98250",
    "addr:housenumber":"285",
    "addr:postcode":"98250",
    "addr:street":"Spring St",
    "iso:country":"US",
    "sg:address":"285 Spring St",
    "sg:city":"Friday Harbor",
    "sg:classifiers":[
        {
            "category":"Shopping",
            "subcategory":"Clothing, Apparel, & Fashions",
            "type":"Retail Goods"
        }
    ],
    "sg:phone":"+1 360 378 6454",
    "sg:postcode":"98250",
    "sg:province":"WA",
    "wof:name":"Dominique's",
    "wof:placetype":"venue"
},
  "geometry": {"coordinates":[-123.01747899999999,48.533661],"type":"Point"}
}