{
  "type": "Feature",
  "properties": {
    "iso:country":"US",
    "sg:address":"6 S 2nd St",
    "sg:city":"Yakima",
    "sg:classifiers":[
        {
            "category":"Professional",
            "subcategory":"Detective & Security Services",
            "type":"Services"
        }
    ],
    "sg:phone":"+1 509 452 7700",
    "sg:postcode":"98901",
    "sg:province":"WA",
    "sg:tags":[
        "car",
        "investigator"
    ],
    "wof:name":"Action Investigators LLC",
    "wof:placetype":"venue"
},
  "geometry": {"coordinates":[-120.50408,46.601341],"type":"Point"}
}