{
  "type": "Feature",
  "properties": {
    "addr:full":"8028 Corliss Ave N Seattle WA 98103",
    "addr:housenumber":"8028",
    "addr:postcode":"98103",
    "addr:street":"Corliss Ave N",
    "iso:country":"US",
    "sg:address":"8028 Corliss Ave N",
    "sg:city":"Seattle",
    "sg:classifiers":[
        {
            "category":"Health Services",
            "subcategory":"Doctor",
            "type":"Services"
        }
    ],
    "sg:phone":"+1 206 527 0343",
    "sg:postcode":"98103",
    "sg:province":"WA",
    "wof:name":"Daniel D Bekker DDS Inc",
    "wof:placetype":"venue"
},
  "geometry": {"coordinates":[-122.33096399999999,47.688398],"type":"Point"}
}