{
  "type": "Feature",
  "properties": {
    "addr:full":"25 N Wenatchee Ave Wenatchee WA 98801",
    "addr:housenumber":"25",
    "addr:postcode":"98801",
    "addr:street":"N Wenatchee Ave",
    "iso:country":"US",
    "sg:address":"25 N Wenatchee Ave",
    "sg:city":"Wenatchee",
    "sg:classifiers":[
        {
            "category":"Social Services",
            "type":"Services"
        }
    ],
    "sg:phone":"+1 509 670 2663",
    "sg:postcode":"98801",
    "sg:province":"WA",
    "sg:tags":[
        "counselor",
        "marriage",
        "family"
    ],
    "wof:name":"Mark M Weick",
    "wof:placetype":"venue"
},
  "geometry": {"coordinates":[-120.311629,47.425023],"type":"Point"}
}