{
  "type": "Feature",
  "properties": {
    "addr:full":"367 Old Dominion Rd Colville WA 99114",
    "addr:housenumber":"367",
    "addr:postcode":"99114",
    "addr:street":"Old Dominion Rd",
    "iso:country":"US",
    "sg:address":"367 Old Dominion Rd",
    "sg:city":"Colville",
    "sg:classifiers":[
        {
            "category":"Manufacturing",
            "subcategory":"Watercraft",
            "type":"Manufacturing & Wholesale Goods"
        }
    ],
    "sg:phone":"+1 509 684 8348",
    "sg:postcode":"99114",
    "sg:province":"WA",
    "sg:tags":[
        "boat"
    ],
    "sg:website":"www.raiderboats.com",
    "wof:name":"Raider Welded Aluminum Boat Co",
    "wof:placetype":"venue"
},
  "geometry": {"coordinates":[-117.843355,48.54572],"type":"Point"}
}