{
  "type": "Feature",
  "properties": {
    "addr:full":"1615 Emerald St Milton WA 98354",
    "addr:housenumber":"1615",
    "addr:postcode":"98354",
    "addr:street":"Emerald St",
    "iso:country":"US",
    "sg:address":"1615 Emerald St",
    "sg:city":"Milton",
    "sg:classifiers":[
        {
            "category":"Museum",
            "subcategory":"Botanical Garden",
            "type":"Entertainment"
        }
    ],
    "sg:phone":"+1 253 926 6818",
    "sg:postcode":"98354",
    "sg:province":"WA",
    "wof:name":"Indoor Oceans",
    "wof:placetype":"venue"
},
  "geometry": {"coordinates":[-122.31172599999999,47.253694],"type":"Point"}
}