{
  "type": "Feature",
  "properties": {
    "addr:full":"11545 SW 212th Pl Vashon WA 98070",
    "addr:housenumber":"11545",
    "addr:postcode":"98070",
    "addr:street":"Sw 212Th Pl",
    "iso:country":"US",
    "sg:address":"11545 SW 212th Pl",
    "sg:city":"Vashon",
    "sg:classifiers":[
        {
            "category":"Wholesale",
            "subcategory":"Machinery & Supplies",
            "type":"Manufacturing & Wholesale Goods"
        }
    ],
    "sg:phone":"+1 206 463 4455",
    "sg:postcode":"98070",
    "sg:province":"WA",
    "sg:tags":[
        "equipment",
        "industrial"
    ],
    "wof:name":"D J & K Construction Inc",
    "wof:placetype":"venue"
},
  "geometry": {"coordinates":[-122.48119,47.415008],"type":"Point"}
}