{
  "type": "Feature",
  "properties": {
    "addr:full":"8816 NE 163rd St Kenmore WA 98028",
    "addr:housenumber":"8816",
    "addr:postcode":"98028",
    "addr:street":"Ne 163Rd St",
    "iso:country":"US",
    "sg:address":"8816 NE 163rd St",
    "sg:city":"Kenmore",
    "sg:classifiers":[
        {
            "category":"Professional",
            "subcategory":"Management & Consulting",
            "type":"Services"
        }
    ],
    "sg:phone":"+1 425 486 7519",
    "sg:postcode":"98028",
    "sg:province":"WA",
    "wof:name":"Managed Retail",
    "wof:placetype":"venue"
},
  "geometry": {"coordinates":[-122.223395,47.746795],"type":"Point"}
}