{
  "type": "Feature",
  "properties": {
    "addr:full":"216 Auburn Way S Auburn WA 98002",
    "addr:housenumber":"216",
    "addr:postcode":"98002",
    "addr:street":"Auburn Way S",
    "iso:country":"US",
    "sg:address":"216 Auburn Way S",
    "sg:city":"Auburn",
    "sg:classifiers":[
        {
            "category":"Professional",
            "subcategory":"Management & Consulting",
            "type":"Services"
        }
    ],
    "sg:phone":"+1 253 939 3389",
    "sg:postcode":"98002",
    "sg:province":"WA",
    "sg:tags":[
        "business",
        "association"
    ],
    "wof:name":"Auburn Good Ol Days Inc",
    "wof:placetype":"venue"
},
  "geometry": {"coordinates":[-122.225616,47.304283],"type":"Point"}
}