{
  "type": "Feature",
  "properties": {
    "addr:full":"1051 Puget Dr E Port Orchard WA 98366",
    "addr:housenumber":"1051",
    "addr:postcode":"98366",
    "addr:street":"Puget Dr E",
    "iso:country":"US",
    "sg:address":"1051 Puget Dr E",
    "sg:city":"Port Orchard",
    "sg:classifiers":[
        {
            "category":"Professional",
            "subcategory":"Computer Services",
            "type":"Services"
        }
    ],
    "sg:phone":"+1 206 255 3214",
    "sg:postcode":"98366",
    "sg:province":"WA",
    "sg:tags":[
        "information",
        "consulting",
        "technology"
    ],
    "wof:name":"Banks Consulting Northwest Inc",
    "wof:placetype":"venue"
},
  "geometry": {"coordinates":[-122.546965,47.542285],"type":"Point"}
}