{
  "type": "Feature",
  "properties": {
    "addr:full":"2905 13th St SE Puyallup WA 98374",
    "addr:housenumber":"2905",
    "addr:postcode":"98374",
    "addr:street":"13Th St Se",
    "iso:country":"US",
    "sg:address":"2905 13th St SE",
    "sg:city":"Puyallup",
    "sg:classifiers":[
        {
            "category":"Professional",
            "subcategory":"Business Services",
            "type":"Services"
        }
    ],
    "sg:phone":"+1 253 840 2177",
    "sg:postcode":"98374",
    "sg:province":"WA",
    "wof:name":"Xander Enterprises LLC",
    "wof:placetype":"venue"
},
  "geometry": {"coordinates":[-122.277913,47.164859],"type":"Point"}
}