{
  "type": "Feature",
  "properties": {
    "addr:full":"9023 State Ave Marysville WA 98270",
    "addr:housenumber":"9023",
    "addr:postcode":"98270",
    "addr:street":"State Ave",
    "iso:country":"US",
    "sg:address":"9023 State Ave",
    "sg:city":"Marysville",
    "sg:classifiers":[
        {
            "category":"Retail",
            "subcategory":"Photofinishing",
            "type":"Services"
        }
    ],
    "sg:phone":"+1 360 659 4933",
    "sg:postcode":"98270",
    "sg:province":"WA",
    "sg:tags":[
        "laboratory",
        "supply"
    ],
    "wof:name":"Clear Image One Hour Photo",
    "wof:placetype":"venue"
},
  "geometry": {"coordinates":[-122.175691,48.0772],"type":"Point"}
}