{
  "type": "Feature",
  "properties": {
    "iso:country":"US",
    "sg:address":"17997 Martin Rd NW",
    "sg:city":"Quincy",
    "sg:classifiers":[
        {
            "category":"Farming",
            "subcategory":"Farm",
            "type":"Manufacturing & Wholesale Goods"
        }
    ],
    "sg:phone":"+1 509 787 1209",
    "sg:postcode":"98848",
    "sg:province":"WA",
    "sg:tags":[
        "crop",
        "general"
    ],
    "wof:name":"Ker & Ruppert",
    "wof:placetype":"venue"
},
  "geometry": {"coordinates":[-119.872203,47.262151],"type":"Point"}
}