{
  "type": "Feature",
  "properties": {
    "addr:full":"13917 E Sprague Ave Spokane Valley WA 99216",
    "addr:housenumber":"13917",
    "addr:postcode":"99216",
    "addr:street":"E Sprague Ave",
    "iso:country":"US",
    "sg:address":"13917 E Sprague Ave",
    "sg:city":"Spokane Valley",
    "sg:classifiers":[
        {
            "category":"Home & Garden",
            "subcategory":"Furniture",
            "type":"Retail Goods"
        }
    ],
    "sg:phone":"+1 509 926 0464",
    "sg:postcode":"99216",
    "sg:province":"WA",
    "wof:name":"Complete Suite Furniture Inc",
    "wof:placetype":"venue"
},
  "geometry": {"coordinates":[-117.216222,47.65714],"type":"Point"}
}