{
  "type": "Feature",
  "properties": {
    "addr:full":"519 Galloway St Steilacoom WA 98388",
    "addr:housenumber":"519",
    "addr:postcode":"98388",
    "addr:street":"Galloway St",
    "iso:country":"US",
    "sg:address":"519 Galloway St",
    "sg:city":"Steilacoom",
    "sg:classifiers":[
        {
            "category":"Wholesale",
            "subcategory":"Vending Machines",
            "type":"Manufacturing & Wholesale Goods"
        }
    ],
    "sg:phone":"+1 253 381 7525",
    "sg:postcode":"98388",
    "sg:province":"WA",
    "sg:tags":[
        "operator"
    ],
    "wof:name":"Sugar Foot Vending",
    "wof:placetype":"venue"
},
  "geometry": {"coordinates":[-122.588876,47.171701],"type":"Point"}
}