{
  "type": "Feature",
  "properties": {
    "addr:full":"14235 156th Ave SE Renton WA 98059",
    "addr:housenumber":"14235",
    "addr:postcode":"98059",
    "addr:street":"156Th Ave Se",
    "iso:country":"US",
    "sg:address":"14235 156th Ave SE",
    "sg:city":"Renton",
    "sg:classifiers":[
        {
            "category":"Professional",
            "subcategory":"Business Services",
            "type":"Services"
        }
    ],
    "sg:phone":"+1 425 228 1183",
    "sg:postcode":"98059",
    "sg:province":"WA",
    "wof:name":"Candle Crazed",
    "wof:placetype":"venue"
},
  "geometry": {"coordinates":[-122.132344,47.474998],"type":"Point"}
}