{
  "type": "Feature",
  "properties": {
    "addr:full":"18411 Highway 99 Lynnwood WA 98037",
    "addr:housenumber":"18411",
    "addr:postcode":"98037",
    "addr:street":"Highway 99",
    "iso:country":"US",
    "sg:address":"18411 Highway 99",
    "sg:city":"Lynnwood",
    "sg:classifiers":[
        {
            "category":"Restaurant",
            "type":"Food & Drink"
        }
    ],
    "sg:menulink":"http://www.allmenus.com/wa/edmonds/45660-maddox/menu/",
    "sg:phone":"+1 425 778 2223",
    "sg:postcode":"98037",
    "sg:province":"WA",
    "sg:tags":[
        "american"
    ],
    "wof:name":"Maddox",
    "wof:placetype":"venue"
},
  "geometry": {"coordinates":[-122.305578,47.832184],"type":"Point"}
}