{
  "type": "Feature",
  "properties": {
    "addr:full":"Seatac Airport Terminal 'N' Seattle WA 98127",
    "addr:postcode":"98127",
    "iso:country":"US",
    "sg:address":"Seatac Airport Terminal 'N'",
    "sg:city":"Seattle",
    "sg:classifiers":[
        {
            "category":"Restaurant",
            "type":"Food & Drink"
        },
        {
            "category":"Bars & Pubs",
            "subcategory":"Nightclub",
            "type":"Food & Drink"
        }
    ],
    "sg:postcode":"98127",
    "sg:province":"WA",
    "sg:tags":[
        "nightlife"
    ],
    "sg:website":"www.portseattle.org/about/maps/n...",
    "wof:name":"The Edge Sports Bar",
    "wof:placetype":"venue"
},
  "geometry": {"coordinates":[-122.28839499999999,47.514063],"type":"Point"}
}