{
  "type": "Feature",
  "properties": {
    "addr:full":"8513 NE Hazel Dell Ave Suite 101 Vancouver WA 98665",
    "addr:housenumber":"8513",
    "addr:postcode":"98665",
    "addr:street":"Ne Hazel Dell Ave Suite 101",
    "iso:country":"US",
    "sg:address":"8513 NE Hazel Dell Ave Suite 101",
    "sg:city":"Vancouver",
    "sg:classifiers":[
        {
            "category":"Real Estate",
            "subcategory":"Real Estate Services",
            "type":"Services"
        },
        {
            "category":"Real Estate",
            "subcategory":"Real Estate Agent",
            "type":"Services"
        }
    ],
    "sg:phone":"+1 360 574 7647",
    "sg:postcode":"98665",
    "sg:province":"WA",
    "sg:tags":[
        "management"
    ],
    "sg:website":"http://www.rosspacific.com",
    "wof:name":"Ross Pacific Management",
    "wof:placetype":"venue"
},
  "geometry": {"coordinates":[-122.669411,45.683979],"type":"Point"}
}