{
  "type": "Feature",
  "properties": {
    "addr:full":"12615 NE 32nd St Bellevue WA 98005",
    "addr:housenumber":"12615",
    "addr:postcode":"98005",
    "addr:street":"Ne 32Nd St",
    "iso:country":"US",
    "sg:address":"12615 NE 32nd St",
    "sg:city":"Bellevue",
    "sg:classifiers":[
        {
            "category":"Education",
            "subcategory":"Special Training",
            "type":"Public Place"
        }
    ],
    "sg:phone":"+1 425 881 7287",
    "sg:postcode":"98005",
    "sg:province":"WA",
    "wof:name":"Toastmasters International",
    "wof:placetype":"venue"
},
  "geometry": {"coordinates":[-122.172132,47.638682],"type":"Point"}
}