{
  "type": "Feature",
  "properties": {
    "addr:full":"1113 6th St Bremerton WA 98337",
    "addr:housenumber":"1113",
    "addr:postcode":"98337",
    "addr:street":"6Th St",
    "iso:country":"US",
    "sg:address":"1113 6th St",
    "sg:city":"Bremerton",
    "sg:classifiers":[
        {
            "category":"Insurance",
            "subcategory":"Insurance Agent",
            "type":"Services"
        }
    ],
    "sg:phone":"+1 360 377 3992",
    "sg:postcode":"98337",
    "sg:province":"WA",
    "sg:tags":[
        "agency"
    ],
    "wof:name":"State Farm Insurance",
    "wof:placetype":"venue"
},
  "geometry": {"coordinates":[-122.635474,47.567272],"type":"Point"}
}