{
  "type": "Feature",
  "properties": {
    "addr:full":"33 E Graves Rd Spokane WA 99218",
    "addr:housenumber":"33",
    "addr:postcode":"99218",
    "addr:street":"E Graves Rd",
    "iso:country":"US",
    "sg:address":"33 E Graves Rd",
    "sg:city":"Spokane",
    "sg:classifiers":[
        {
            "category":"Real Estate",
            "subcategory":"Real Estate Operator",
            "type":"Services"
        }
    ],
    "sg:phone":"+1 509 467 6865",
    "sg:postcode":"99218",
    "sg:province":"WA",
    "sg:tags":[
        "building",
        "apartment"
    ],
    "wof:name":"Pine Villa",
    "wof:placetype":"venue"
},
  "geometry": {"coordinates":[-117.408828,47.748038],"type":"Point"}
}