{
  "type": "Feature",
  "properties": {
    "addr:full":"12061 Seabeck Hwy NW Seabeck WA 98380",
    "addr:housenumber":"12061",
    "addr:postcode":"98380",
    "addr:street":"Seabeck Hwy Nw",
    "iso:country":"US",
    "sg:address":"12061 Seabeck Hwy NW",
    "sg:city":"Seabeck",
    "sg:classifiers":[
        {
            "category":"Manufacturing",
            "subcategory":"Apparel",
            "type":"Manufacturing & Wholesale Goods"
        }
    ],
    "sg:phone":"+1 360 830 9072",
    "sg:postcode":"98380",
    "sg:province":"WA",
    "wof:name":"Sisters Attic",
    "wof:placetype":"venue"
},
  "geometry": {"coordinates":[-122.799565,47.652636],"type":"Point"}
}