{
  "type": "Feature",
  "properties": {
    "iso:country":"US",
    "sg:address":"2030 Beans Bight Rd NE",
    "sg:city":"Bainbridge Island",
    "sg:classifiers":[
        {
            "category":"Professional",
            "subcategory":"Business Services",
            "type":"Services"
        }
    ],
    "sg:phone":"+1 206 780 9418",
    "sg:postcode":"98110",
    "sg:province":"WA",
    "sg:tags":[
        "interior",
        "antique",
        "designer",
        "appraiser"
    ],
    "wof:name":"Bowden Wm D F A S I D Ltd",
    "wof:placetype":"venue"
},
  "geometry": {"coordinates":[-122.493517,47.58122],"type":"Point"}
}