{
  "type": "Feature",
  "properties": {
    "addr:full":"18916 NE 103rd St Redmond WA 98052",
    "addr:housenumber":"18916",
    "addr:postcode":"98052",
    "addr:street":"Ne 103Rd St",
    "iso:country":"US",
    "sg:address":"18916 NE 103rd St",
    "sg:city":"Redmond",
    "sg:classifiers":[
        {
            "category":"Building & Trades",
            "subcategory":"Construction",
            "type":"Services"
        }
    ],
    "sg:phone":"+1 425 644 4474",
    "sg:postcode":"98052",
    "sg:province":"WA",
    "sg:tags":[
        "roofing",
        "contractor"
    ],
    "sg:website":"www.redmondroofing.com",
    "wof:name":"A Redmond Roofing",
    "wof:placetype":"venue"
},
  "geometry": {"coordinates":[-122.088831,47.691816],"type":"Point"}
}