{
  "type": "Feature",
  "properties": {
    "addr:full":"2922 S Manito Blvd Spokane WA 99203",
    "addr:housenumber":"2922",
    "addr:postcode":"99203",
    "addr:street":"S Manito Blvd",
    "iso:country":"US",
    "sg:address":"2922 S Manito Blvd",
    "sg:city":"Spokane",
    "sg:classifiers":[
        {
            "category":"Recreation",
            "type":"Entertainment"
        }
    ],
    "sg:phone":"+1 509 924 3079",
    "sg:postcode":"99203",
    "sg:province":"WA",
    "sg:tags":[
        "water",
        "slide",
        "park"
    ],
    "wof:name":"Splash-Down Concession Inc",
    "wof:placetype":"venue"
},
  "geometry": {"coordinates":[-117.40782299999999,47.626559],"type":"Point"}
}