{
  "type": "Feature",
  "properties": {
    "addr:full":"3705 S 162nd St Seatac WA 98188",
    "addr:housenumber":"3705",
    "addr:postcode":"98188",
    "addr:street":"S 162Nd St",
    "iso:country":"US",
    "sg:address":"3705 S 162nd St",
    "sg:city":"Seatac",
    "sg:classifiers":[
        {
            "category":"Building & Trades",
            "subcategory":"Landscaping Services",
            "type":"Services"
        }
    ],
    "sg:phone":"+1 206 248 0560",
    "sg:postcode":"98188",
    "sg:province":"WA",
    "sg:tags":[
        "tree"
    ],
    "wof:name":"Clay Heatley",
    "wof:placetype":"venue"
},
  "geometry": {"coordinates":[-122.28668500000001,47.457972],"type":"Point"}
}