{
  "type": "Feature",
  "properties": {
    "addr:full":"2430 96th St S Tacoma WA 98444",
    "addr:housenumber":"2430",
    "addr:postcode":"98444",
    "addr:street":"96Th St S",
    "iso:country":"US",
    "sg:address":"2430 96th St S",
    "sg:city":"Tacoma",
    "sg:classifiers":[
        {
            "category":"Education",
            "subcategory":"Special Training",
            "type":"Public Place"
        }
    ],
    "sg:phone":"+1 253 983 7060",
    "sg:postcode":"98444",
    "sg:province":"WA",
    "sg:tags":[
        "educational"
    ],
    "wof:name":"Parents For Better Education",
    "wof:placetype":"venue"
},
  "geometry": {"coordinates":[-122.46606800000001,47.170181],"type":"Point"}
}