{
  "type": "Feature",
  "properties": {
    "addr:full":"4123 128th St E Tacoma WA 98446",
    "addr:housenumber":"4123",
    "addr:postcode":"98446",
    "addr:street":"128Th St",
    "iso:country":"US",
    "sg:address":"4123 128th St E",
    "sg:city":"Tacoma",
    "sg:classifiers":[
        {
            "category":"Professional",
            "subcategory":"Art Services",
            "type":"Services"
        }
    ],
    "sg:phone":"+1 253 538 9393",
    "sg:postcode":"98446",
    "sg:province":"WA",
    "sg:tags":[
        "artist"
    ],
    "wof:name":"Anderson Illustration",
    "wof:placetype":"venue"
},
  "geometry": {"coordinates":[-122.374319,47.140294],"type":"Point"}
}