{
  "type": "Feature",
  "properties": {
    "addr:full":"714 Highland Dr Port Ludlow WA 98365",
    "addr:housenumber":"714",
    "addr:postcode":"98365",
    "addr:street":"Highland Dr",
    "iso:country":"US",
    "sg:address":"714 Highland Dr",
    "sg:city":"Port Ludlow",
    "sg:classifiers":[
        {
            "category":"Shopping",
            "subcategory":"Gifts & Souvenirs",
            "type":"Retail Goods"
        }
    ],
    "sg:phone":"+1 360 437 9230",
    "sg:postcode":"98365",
    "sg:province":"WA",
    "wof:name":"Nichols",
    "wof:placetype":"venue"
},
  "geometry": {"coordinates":[-122.692752,47.906204],"type":"Point"}
}