{
  "type": "Feature",
  "properties": {
    "addr:full":"313 Alderwood St Coupeville WA 98239",
    "addr:housenumber":"313",
    "addr:postcode":"98239",
    "addr:street":"Alderwood St",
    "iso:country":"US",
    "sg:address":"313 Alderwood St",
    "sg:city":"Coupeville",
    "sg:classifiers":[
        {
            "category":"Museum",
            "type":"Entertainment"
        }
    ],
    "sg:phone":"+1 360 678 3430",
    "sg:postcode":"98239",
    "sg:province":"WA",
    "sg:tags":[
        "gallery"
    ],
    "wof:name":"B J Studio",
    "wof:placetype":"venue"
},
  "geometry": {"coordinates":[-122.599079,48.140333],"type":"Point"}
}