{
  "type": "Feature",
  "properties": {
    "addr:full":"1818 Westlake Ave N, #114 Seattle WA 98109",
    "addr:housenumber":"1818",
    "addr:postcode":"98109",
    "addr:street":"Westlake Ave N # 114",
    "iso:country":"US",
    "sg:address":"1818 Westlake Ave N, #114",
    "sg:city":"Seattle",
    "sg:classifiers":[
        {
            "category":"Health Services",
            "subcategory":"Clinic",
            "type":"Services"
        },
        {
            "category":"Professional",
            "subcategory":"Employment Agencies",
            "type":"Services"
        }
    ],
    "sg:phone":"+1 206 859 5509",
    "sg:postcode":"98109",
    "sg:province":"WA",
    "sg:tags":[
        "medical"
    ],
    "sg:website":"www.dentalconnections.com",
    "wof:name":"Dental Connections, Inc",
    "wof:placetype":"venue"
},
  "geometry": {"coordinates":[-122.340486,47.63598],"type":"Point"}
}