{
  "type": "Feature",
  "properties": {
    "addr:full":"1069 Timber Ln Freeland WA 98249",
    "addr:housenumber":"1069",
    "addr:postcode":"98249",
    "addr:street":"Timber Ln",
    "iso:country":"US",
    "sg:address":"1069 Timber Ln",
    "sg:city":"Freeland",
    "sg:classifiers":[
        {
            "category":"Personal",
            "subcategory":"Beauty Salon",
            "type":"Services"
        }
    ],
    "sg:phone":"+1 360 331 7030",
    "sg:postcode":"98249",
    "sg:province":"WA",
    "sg:tags":[
        "shop"
    ],
    "wof:name":"Beverly's Mutiny Bay Salon",
    "wof:placetype":"venue"
},
  "geometry": {"coordinates":[-122.55792099999999,48.011303],"type":"Point"}
}