{
  "type": "Feature",
  "properties": {
    "addr:full":"8900 NE St Johns Rd Vancouver WA 98665",
    "addr:housenumber":"8900",
    "addr:postcode":"98665",
    "addr:street":"Ne St Johns Rd",
    "iso:country":"US",
    "sg:address":"8900 NE St Johns Rd",
    "sg:city":"Vancouver",
    "sg:classifiers":[
        {
            "category":"Autos & Motor Vehicles",
            "subcategory":"Automobile Sales",
            "type":"Retail Goods"
        }
    ],
    "sg:phone":"+1 360 574 9179",
    "sg:postcode":"98665",
    "sg:province":"WA",
    "sg:tags":[
        "used"
    ],
    "wof:name":"Ehlke Auto Sales & Service",
    "wof:placetype":"venue"
},
  "geometry": {"coordinates":[-122.620492,45.689613],"type":"Point"}
}