{
  "type": "Feature",
  "properties": {
    "addr:full":"6819 114th St E Puyallup WA 98373",
    "addr:housenumber":"6819",
    "addr:postcode":"98373",
    "addr:street":"114Th St E",
    "iso:country":"US",
    "sg:address":"6819 114th St E",
    "sg:city":"Puyallup",
    "sg:classifiers":[
        {
            "category":"Home & Garden",
            "subcategory":"Carpets & Floor Coverings",
            "type":"Retail Goods"
        }
    ],
    "sg:phone":"+1 253 445 1206",
    "sg:postcode":"98373",
    "sg:province":"WA",
    "sg:tags":[
        "sales",
        "facility"
    ],
    "wof:name":"Kevco Carpets Etc",
    "wof:placetype":"venue"
},
  "geometry": {"coordinates":[-122.337103,47.152984],"type":"Point"}
}