{
  "type": "Feature",
  "properties": {
    "iso:country":"US",
    "sg:address":"3305 SW Seola Ln",
    "sg:city":"Seattle",
    "sg:classifiers":[
        {
            "category":"Professional",
            "subcategory":"Management & Consulting",
            "type":"Services"
        }
    ],
    "sg:phone":"+1 206 849 3818",
    "sg:postcode":"98146",
    "sg:province":"WA",
    "wof:name":"B & M Construction Services",
    "wof:placetype":"venue"
},
  "geometry": {"coordinates":[-122.37457499999999,47.496218],"type":"Point"}
}