{
  "type": "Feature",
  "properties": {
    "addr:full":"1011 SW Klickitat Way Seattle WA 98134",
    "addr:housenumber":"1011",
    "addr:postcode":"98134",
    "addr:street":"Sw Klickitat Way",
    "iso:country":"US",
    "sg:address":"1011 SW Klickitat Way",
    "sg:city":"Seattle",
    "sg:classifiers":[
        {
            "category":"Cinema",
            "subcategory":"Movie Rental",
            "type":"Entertainment"
        }
    ],
    "sg:phone":"+1 206 748 0800",
    "sg:postcode":"98134",
    "sg:province":"WA",
    "sg:tags":[
        "leasing",
        "video",
        "disc",
        "tape"
    ],
    "wof:name":"Blockbuster Video Rentals",
    "wof:placetype":"venue"
},
  "geometry": {"coordinates":[-122.350182,47.570745],"type":"Point"}
}