{
  "type": "Feature",
  "properties": {
    "addr:full":"1724 E 44th St Tacoma WA 98404",
    "addr:housenumber":"1724",
    "addr:postcode":"98404",
    "addr:street":"E 44Th St",
    "iso:country":"US",
    "sg:address":"1724 E 44th St",
    "sg:city":"Tacoma",
    "sg:classifiers":[
        {
            "category":"Social Services",
            "type":"Services"
        }
    ],
    "sg:phone":"+1 253 473 5666",
    "sg:postcode":"98404",
    "sg:province":"WA",
    "sg:tags":[
        "organization",
        "welfare"
    ],
    "wof:name":"Indochinese Cultural & Svc Ctr",
    "wof:placetype":"venue"
},
  "geometry": {"coordinates":[-122.40418,47.217067],"type":"Point"}
}