{
  "type": "Feature",
  "properties": {
    "addr:full":"17461 147th St SE Monroe WA 98272",
    "addr:housenumber":"17461",
    "addr:postcode":"98272",
    "addr:street":"147Th St Se",
    "iso:country":"US",
    "sg:address":"17461 147th St SE",
    "sg:city":"Monroe",
    "sg:classifiers":[
        {
            "category":"Wholesale",
            "subcategory":"Auto Parts",
            "type":"Manufacturing & Wholesale Goods"
        }
    ],
    "sg:phone":"+1 425 481 6780",
    "sg:postcode":"98272",
    "sg:province":"WA",
    "sg:tags":[
        "automobile",
        "rebuilt"
    ],
    "sg:website":"www.wildwestmustang.com",
    "wof:name":"Wild West Mustang Ranch",
    "wof:placetype":"venue"
},
  "geometry": {"coordinates":[-121.997122,47.864656],"type":"Point"}
}