{
  "type": "Feature",
  "properties": {
    "addr:full":"2424 Viewcrest Ave Everett WA 98203",
    "addr:housenumber":"2424",
    "addr:postcode":"98203",
    "addr:street":"Viewcrest Ave",
    "iso:country":"US",
    "sg:address":"2424 Viewcrest Ave",
    "sg:city":"Everett",
    "sg:classifiers":[
        {
            "category":"Health Services",
            "subcategory":"Clinic",
            "type":"Services"
        }
    ],
    "sg:phone":"+1 425 355 7748",
    "sg:postcode":"98203",
    "sg:province":"WA",
    "wof:name":"Anita Janice Welch",
    "wof:placetype":"venue"
},
  "geometry": {"coordinates":[-122.26488999999999,47.949892],"type":"Point"}
}