{
  "type": "Feature",
  "properties": {
    "addr:full":"5642 47th Ave SW Seattle WA 98136",
    "addr:housenumber":"5642",
    "addr:postcode":"98136",
    "addr:street":"47Th Ave Sw",
    "iso:country":"US",
    "sg:address":"5642 47th Ave SW",
    "sg:city":"Seattle",
    "sg:classifiers":[
        {
            "category":"Home & Garden",
            "subcategory":"Home Furnishings",
            "type":"Retail Goods"
        }
    ],
    "sg:phone":"+1 206 923 2054",
    "sg:postcode":"98136",
    "sg:province":"WA",
    "wof:name":"Sunday Specialties",
    "wof:placetype":"venue"
},
  "geometry": {"coordinates":[-122.392352,47.550623],"type":"Point"}
}