{
  "type": "Feature",
  "properties": {
    "addr:full":"7944 12th Ave SW Seattle WA 98106",
    "addr:housenumber":"7944",
    "addr:postcode":"98106",
    "addr:street":"12Th Ave Sw",
    "iso:country":"US",
    "sg:address":"7944 12th Ave SW",
    "sg:city":"Seattle",
    "sg:classifiers":[
        {
            "category":"Personal",
            "type":"Services"
        }
    ],
    "sg:phone":"+1 206 768 2818",
    "sg:postcode":"98106",
    "sg:province":"WA",
    "wof:name":"International Occasions",
    "wof:placetype":"venue"
},
  "geometry": {"coordinates":[-122.35051900000001,47.530541],"type":"Point"}
}