{
  "type": "Feature",
  "properties": {
    "addr:full":"17505 110th Ave SE Yelm WA 98597",
    "addr:housenumber":"17505",
    "addr:postcode":"98597",
    "addr:street":"110Th Ave Se",
    "iso:country":"US",
    "sg:address":"17505 110th Ave SE",
    "sg:city":"Yelm",
    "sg:classifiers":[
        {
            "category":"Wholesale",
            "subcategory":"Scrap",
            "type":"Manufacturing & Wholesale Goods"
        }
    ],
    "sg:phone":"+1 360 458 7938",
    "sg:postcode":"98597",
    "sg:province":"WA",
    "sg:tags":[
        "material"
    ],
    "wof:name":"B n H Auto Wrecking",
    "wof:placetype":"venue"
},
  "geometry": {"coordinates":[-122.56384,46.927101],"type":"Point"}
}