{
  "type": "Feature",
  "properties": {
    "addr:full":"8651 Zircon Dr SW Lakewood WA 98498",
    "addr:housenumber":"8651",
    "addr:postcode":"98498",
    "addr:street":"Zircon Dr Sw",
    "iso:country":"US",
    "sg:address":"8651 Zircon Dr SW",
    "sg:city":"Lakewood",
    "sg:classifiers":[
        {
            "category":"Recreation",
            "type":"Entertainment"
        }
    ],
    "sg:phone":"+1 253 582 5691",
    "sg:postcode":"98498",
    "sg:province":"WA",
    "wof:name":"Rizmoe Golf Works",
    "wof:placetype":"venue"
},
  "geometry": {"coordinates":[-122.55203400000001,47.191796],"type":"Point"}
}