{
  "type": "Feature",
  "properties": {
    "addr:full":"2720 3rd Ave, Ste 5 Seattle WA 98121",
    "addr:housenumber":"2720",
    "addr:postcode":"98121",
    "addr:street":"3Rd Ave Ste 5",
    "iso:country":"US",
    "sg:address":"2720 3rd Ave, Ste 5",
    "sg:city":"Seattle",
    "sg:classifiers":[
        {
            "category":"Coffee & Tea",
            "type":"Food & Drink"
        }
    ],
    "sg:phone":"+1 206 397 3875",
    "sg:postcode":"98121",
    "sg:province":"WA",
    "sg:website":"thegreenleafcafe.com",
    "wof:name":"The Green Leaf Cafe",
    "wof:placetype":"venue"
},
  "geometry": {"coordinates":[-122.349126,47.617276],"type":"Point"}
}