{
  "type": "Feature",
  "properties": {
    "addr:full":"407 Smith St Seattle WA 98109",
    "addr:housenumber":"407",
    "addr:postcode":"98109",
    "addr:street":"Smith St",
    "iso:country":"US",
    "sg:address":"407 Smith St",
    "sg:city":"Seattle",
    "sg:classifiers":[
        {
            "category":"Professional",
            "subcategory":"Lawyer & Legal Services",
            "type":"Services"
        }
    ],
    "sg:phone":"+1 206 283 6497",
    "sg:postcode":"98109",
    "sg:province":"WA",
    "wof:name":"Mary G Henderson",
    "wof:placetype":"venue"
},
  "geometry": {"coordinates":[-122.347572,47.641418],"type":"Point"}
}