{
  "type": "Feature",
  "properties": {
    "addr:full":"2223 Queen Anne Ave N Seattle WA 98109",
    "addr:housenumber":"2223",
    "addr:postcode":"98109",
    "addr:street":"Queen Anne Ave N",
    "iso:country":"US",
    "sg:address":"2223 Queen Anne Ave N",
    "sg:city":"Seattle",
    "sg:classifiers":[
        {
            "category":"Health Services",
            "subcategory":"Dentist",
            "type":"Services"
        }
    ],
    "sg:phone":"+1 206 432 9954",
    "sg:postcode":"98109",
    "sg:province":"WA",
    "sg:tags":[
        "orthodontist"
    ],
    "sg:website":"www.smilesbysmita.com/",
    "wof:name":"Smiles By Smita",
    "wof:placetype":"venue"
},
  "geometry": {"coordinates":[-122.35731199999999,47.639174],"type":"Point"}
}