{
  "type": "Feature",
  "properties": {
    "addr:full":"11012 Canyon Rd E Puyallup WA 98373",
    "addr:housenumber":"11012",
    "addr:postcode":"98373",
    "addr:street":"Canyon Rd E",
    "iso:country":"US",
    "sg:address":"11012 Canyon Rd E",
    "sg:city":"Puyallup",
    "sg:classifiers":[
        {
            "category":"Shopping",
            "subcategory":"Tobacco",
            "type":"Retail Goods"
        }
    ],
    "sg:phone":"+1 253 531 8899",
    "sg:postcode":"98373",
    "sg:province":"WA",
    "sg:tags":[
        "cigarette",
        "cigar",
        "dealer"
    ],
    "wof:name":"Cigarland Canyon Road",
    "wof:placetype":"venue"
},
  "geometry": {"coordinates":[-122.357269,47.15547],"type":"Point"}
}