{
  "type": "Feature",
  "properties": {
    "addr:full":"2025 Fairview Ave E Seattle WA 98102",
    "addr:housenumber":"2025",
    "addr:postcode":"98102",
    "addr:street":"Fairview Ave E",
    "iso:country":"US",
    "sg:address":"2025 Fairview Ave E",
    "sg:city":"Seattle",
    "sg:classifiers":[
        {
            "category":"Building & Trades",
            "subcategory":"Construction",
            "type":"Services"
        }
    ],
    "sg:phone":"+1 206 323 3489",
    "sg:postcode":"98102",
    "sg:province":"WA",
    "sg:tags":[
        "residential"
    ],
    "wof:name":"Sj McFarland Inc",
    "wof:placetype":"venue"
},
  "geometry": {"coordinates":[-122.327175,47.635443],"type":"Point"}
}