{
  "type": "Feature",
  "properties": {
    "iso:country":"US",
    "sg:address":"705 State Rte 4",
    "sg:city":"Naselle",
    "sg:classifiers":[
        {
            "category":"Home & Garden",
            "subcategory":"Garden Supply",
            "type":"Retail Goods"
        }
    ],
    "sg:phone":"+1 360 484 7166",
    "sg:postcode":"98638",
    "sg:province":"WA",
    "wof:name":"Kelly Creek Nursery",
    "wof:placetype":"venue"
},
  "geometry": {"coordinates":[-123.824642,46.387599],"type":"Point"}
}