{
  "type": "Feature",
  "properties": {
    "addr:full":"715 E Sprague Ave Spokane WA 99202",
    "addr:housenumber":"715",
    "addr:postcode":"99202",
    "addr:street":"E Sprague Ave",
    "iso:country":"US",
    "sg:address":"715 E Sprague Ave",
    "sg:city":"Spokane",
    "sg:classifiers":[
        {
            "category":"Social Services",
            "type":"Services"
        }
    ],
    "sg:phone":"+1 509 217 2708",
    "sg:postcode":"99202",
    "sg:province":"WA",
    "sg:tags":[
        "counselor",
        "marriage",
        "family"
    ],
    "wof:name":"Advantage Counseling & Rehab",
    "wof:placetype":"venue"
},
  "geometry": {"coordinates":[-117.399236,47.657259],"type":"Point"}
}