{
  "type": "Feature",
  "properties": {
    "addr:full":"144 River Rd Lynden WA 98264",
    "addr:housenumber":"144",
    "addr:postcode":"98264",
    "addr:street":"River Rd",
    "iso:country":"US",
    "sg:address":"144 River Rd",
    "sg:city":"Lynden",
    "sg:classifiers":[
        {
            "category":"Home & Garden",
            "subcategory":"Building Materials",
            "type":"Retail Goods"
        }
    ],
    "sg:phone":"+1 360 312 3502",
    "sg:postcode":"98264",
    "sg:province":"WA",
    "sg:tags":[
        "concrete",
        "contractor"
    ],
    "sg:website":"http://www.ferndalereadymix.net",
    "wof:name":"Ferndale Ready Mix & Gravel Inc",
    "wof:placetype":"venue"
},
  "geometry": {"coordinates":[-122.485832,48.920673],"type":"Point"}
}