{
  "type": "Feature",
  "properties": {
    "addr:full":"1204 Thurston Ct NW Yelm WA 98597",
    "addr:housenumber":"1204",
    "addr:postcode":"98597",
    "addr:street":"Thurston Ct Nw",
    "iso:country":"US",
    "sg:address":"1204 Thurston Ct NW",
    "sg:city":"Yelm",
    "sg:classifiers":[
        {
            "category":"Professional",
            "type":"Services"
        }
    ],
    "sg:phone":"+1 360 458 3235",
    "sg:postcode":"98597",
    "sg:province":"WA",
    "wof:name":"Services In Platinum Plus",
    "wof:placetype":"venue"
},
  "geometry": {"coordinates":[-122.602585,46.953867],"type":"Point"}
}