{
  "type": "Feature",
  "properties": {
    "addr:full":"601 S 291st St Federal Way WA 98003",
    "addr:housenumber":"601",
    "addr:postcode":"98003",
    "addr:street":"S 291St St",
    "iso:country":"US",
    "sg:address":"601 S 291st St",
    "sg:city":"Federal Way",
    "sg:classifiers":[
        {
            "category":"Travel",
            "subcategory":"Travel Agent",
            "type":"Entertainment"
        }
    ],
    "sg:phone":"+1 253 839 0665",
    "sg:postcode":"98003",
    "sg:province":"WA",
    "sg:tags":[
        "agency"
    ],
    "wof:name":"Ft Travel Inc",
    "wof:placetype":"venue"
},
  "geometry": {"coordinates":[-122.32459,47.340821],"type":"Point"}
}