{
  "type": "Feature",
  "properties": {
    "addr:full":"1233 232nd Pl SW Bothell WA 98021",
    "addr:housenumber":"1233",
    "addr:postcode":"98021",
    "addr:street":"232Nd Pl Sw",
    "iso:country":"US",
    "sg:address":"1233 232nd Pl SW",
    "sg:city":"Bothell",
    "sg:classifiers":[
        {
            "category":"Education",
            "subcategory":"School",
            "type":"Public Place"
        }
    ],
    "sg:phone":"+1 425 485 0655",
    "sg:postcode":"98021",
    "sg:province":"WA",
    "wof:name":"Inglemoor Jnior High Chrladers",
    "wof:placetype":"venue"
},
  "geometry": {"coordinates":[-122.249559,47.787661],"type":"Point"}
}