{
  "type": "Feature",
  "properties": {
    "addr:full":"19132 34th Dr SE Bothell WA 98012",
    "addr:housenumber":"19132",
    "addr:postcode":"98012",
    "addr:street":"34Th Dr Se",
    "iso:country":"US",
    "sg:address":"19132 34th Dr SE",
    "sg:city":"Bothell",
    "sg:classifiers":[
        {
            "category":"Restaurant",
            "type":"Food & Drink"
        }
    ],
    "sg:phone":"+1 425 481 0818",
    "sg:postcode":"98012",
    "sg:province":"WA",
    "sg:tags":[
        "eating"
    ],
    "wof:name":"Mels Diner",
    "wof:placetype":"venue"
},
  "geometry": {"coordinates":[-122.187158,47.823262],"type":"Point"}
}