{
  "type": "Feature",
  "properties": {
    "addr:full":"4820 N 22nd St Tacoma WA 98406",
    "addr:housenumber":"4820",
    "addr:postcode":"98406",
    "addr:street":"N 22Nd St",
    "iso:country":"US",
    "sg:address":"4820 N 22nd St",
    "sg:city":"Tacoma",
    "sg:classifiers":[
        {
            "category":"Building & Trades",
            "subcategory":"Landscaping Services",
            "type":"Services"
        }
    ],
    "sg:phone":"+1 253 565 0792",
    "sg:postcode":"98406",
    "sg:province":"WA",
    "wof:name":"George P Franko Jr",
    "wof:placetype":"venue"
},
  "geometry": {"coordinates":[-122.502095,47.268182],"type":"Point"}
}