{
  "type": "Feature",
  "properties": {
    "iso:country":"US",
    "sg:address":"3350 Cherrywood Ave",
    "sg:city":"Bellingham",
    "sg:classifiers":[
        {
            "category":"Retail",
            "subcategory":"Portrait Studio",
            "type":"Services"
        }
    ],
    "sg:phone":"+1 360 738 6838",
    "sg:postcode":"98225",
    "sg:province":"WA",
    "sg:tags":[
        "photo"
    ],
    "wof:name":"As Mel Sees It",
    "wof:placetype":"venue"
},
  "geometry": {"coordinates":[-122.522385,48.78052],"type":"Point"}
}