{
  "type": "Feature",
  "properties": {
    "addr:full":"12427 Greenwood Ave N Seattle WA 98133",
    "addr:housenumber":"12427",
    "addr:postcode":"98133",
    "addr:street":"Greenwood Ave N",
    "iso:country":"US",
    "sg:address":"12427 Greenwood Ave N",
    "sg:city":"Seattle",
    "sg:classifiers":[
        {
            "category":"Restaurant",
            "type":"Food & Drink"
        }
    ],
    "sg:phone":"+1 206 368 9810",
    "sg:postcode":"98133",
    "sg:province":"WA",
    "wof:name":"Brother John's Pizzeria",
    "wof:placetype":"venue"
},
  "geometry": {"coordinates":[-122.355614,47.719382],"type":"Point"}
}