{
  "type": "Feature",
  "properties": {
    "addr:full":"4426 Burke Ave N Seattle WA 98103",
    "addr:housenumber":"4426",
    "addr:postcode":"98103",
    "addr:street":"Burke Ave N",
    "iso:country":"US",
    "sg:address":"4426 Burke Ave N",
    "sg:city":"Seattle",
    "sg:classifiers":[
        {
            "category":"Professional",
            "subcategory":"Management & Consulting",
            "type":"Services"
        }
    ],
    "sg:phone":"+1 206 548 0152",
    "sg:postcode":"98103",
    "sg:province":"WA",
    "sg:tags":[
        "business"
    ],
    "wof:name":"Population Connection WA",
    "wof:placetype":"venue"
},
  "geometry": {"coordinates":[-122.334908,47.661096],"type":"Point"}
}