{
  "type": "Feature",
  "properties": {
    "addr:full":"3233 Northwest Ave Bellingham WA 98225",
    "addr:housenumber":"3233",
    "addr:postcode":"98225",
    "addr:street":"Northwest Ave",
    "iso:country":"US",
    "sg:address":"3233 Northwest Ave",
    "sg:city":"Bellingham",
    "sg:classifiers":[
        {
            "category":"Banks & Credit Unions",
            "subcategory":"Bank",
            "type":"Services"
        }
    ],
    "sg:phone":"+1 360 734 2043",
    "sg:postcode":"98225",
    "sg:province":"WA",
    "wof:name":"Industrial Credit Union",
    "wof:placetype":"venue"
},
  "geometry": {"coordinates":[-122.497012,48.775121],"type":"Point"}
}