{
  "type": "Feature",
  "properties": {
    "addr:full":"50 Olympian Ct Port Angeles WA 98362",
    "addr:housenumber":"50",
    "addr:postcode":"98362",
    "addr:street":"Olympian Ct",
    "iso:country":"US",
    "sg:address":"50 Olympian Ct",
    "sg:city":"Port Angeles",
    "sg:classifiers":[
        {
            "category":"Building & Trades",
            "subcategory":"Plumbing",
            "type":"Services"
        }
    ],
    "sg:phone":"+1 360 452 8500",
    "sg:postcode":"98362",
    "sg:province":"WA",
    "sg:tags":[
        "tank",
        "septic"
    ],
    "wof:name":"JOHN Scott Fleming Engineering",
    "wof:placetype":"venue"
},
  "geometry": {"coordinates":[-123.301248,48.100136],"type":"Point"}
}