{
  "type": "Feature",
  "properties": {
    "addr:full":"2725 Oakes Ave Everett WA 98201",
    "addr:housenumber":"2725",
    "addr:postcode":"98201",
    "addr:street":"Oakes Ave",
    "iso:country":"US",
    "sg:address":"2725 Oakes Ave",
    "sg:city":"Everett",
    "sg:classifiers":[
        {
            "category":"Organizations",
            "subcategory":"Membership Organization",
            "type":"Services"
        }
    ],
    "sg:phone":"+1 425 252 0291",
    "sg:postcode":"98201",
    "sg:province":"WA",
    "wof:name":"Sons of Norway",
    "wof:placetype":"venue"
},
  "geometry": {"coordinates":[-122.204291,47.980906],"type":"Point"}
}