{
  "type": "Feature",
  "properties": {
    "addr:full":"7701 Bridgeport Way W Lakewood WA 98499",
    "addr:housenumber":"7701",
    "addr:postcode":"98499",
    "addr:street":"Bridgeport Way W",
    "iso:country":"US",
    "sg:address":"7701 Bridgeport Way W",
    "sg:city":"Lakewood",
    "sg:classifiers":[
        {
            "category":"Freight",
            "type":"Transportation"
        }
    ],
    "sg:phone":"+1 253 474 2011",
    "sg:postcode":"98499",
    "sg:province":"WA",
    "sg:tags":[
        "truck",
        "general"
    ],
    "wof:name":"Pace Bridgeport Mini Storage",
    "wof:placetype":"venue"
},
  "geometry": {"coordinates":[-122.518348,47.188379],"type":"Point"}
}