{
  "type": "Feature",
  "properties": {
    "addr:full":"141 E Laurel Rd Bellingham WA 98226",
    "addr:housenumber":"141",
    "addr:postcode":"98226",
    "addr:street":"E Laurel Rd",
    "iso:country":"US",
    "sg:address":"141 E Laurel Rd",
    "sg:city":"Bellingham",
    "sg:classifiers":[
        {
            "category":"Building & Trades",
            "subcategory":"Construction",
            "type":"Services"
        }
    ],
    "sg:phone":"+1 360 756 9477",
    "sg:postcode":"98226",
    "sg:province":"WA",
    "sg:tags":[
        "contractor"
    ],
    "wof:name":"Holz Contractors",
    "wof:placetype":"venue"
},
  "geometry": {"coordinates":[-122.484859,48.855064],"type":"Point"}
}