{
  "type": "Feature",
  "properties": {
    "addr:full":"6913 62nd Dr NE Marysville WA 98270",
    "addr:housenumber":"6913",
    "addr:postcode":"98270",
    "addr:street":"62Nd Dr Ne",
    "iso:country":"US",
    "sg:address":"6913 62nd Dr NE",
    "sg:city":"Marysville",
    "sg:classifiers":[
        {
            "category":"Home & Garden",
            "subcategory":"Building Materials",
            "type":"Retail Goods"
        }
    ],
    "sg:phone":"+1 360 651 7830",
    "sg:postcode":"98270",
    "sg:province":"WA",
    "sg:tags":[
        "door"
    ],
    "wof:name":"Allphase Garage Door Repair",
    "wof:placetype":"venue"
},
  "geometry": {"coordinates":[-122.146807,48.058301],"type":"Point"}
}