{
  "type": "Feature",
  "properties": {
    "addr:full":"4510 SW Heinze Way Seattle WA 98136",
    "addr:housenumber":"4510",
    "addr:postcode":"98136",
    "addr:street":"Sw Heinze Way",
    "iso:country":"US",
    "sg:address":"4510 SW Heinze Way",
    "sg:city":"Seattle",
    "sg:classifiers":[
        {
            "category":"Professional",
            "subcategory":"Business Services",
            "type":"Services"
        }
    ],
    "sg:phone":"+1 206 935 8574",
    "sg:postcode":"98136",
    "sg:province":"WA",
    "wof:name":"Post Alley Productions In",
    "wof:placetype":"venue"
},
  "geometry": {"coordinates":[-122.390648,47.556495],"type":"Point"}
}