{
  "type": "Feature",
  "properties": {
    "addr:full":"4232 196th St SW Lynnwood WA 98036",
    "addr:housenumber":"4232",
    "addr:postcode":"98036",
    "addr:street":"196Th St Sw",
    "iso:country":"US",
    "sg:address":"4232 196th St SW",
    "sg:city":"Lynnwood",
    "sg:classifiers":[
        {
            "category":"Shopping",
            "subcategory":"Computers & Home Electronics",
            "type":"Retail Goods"
        }
    ],
    "sg:phone":"+1 425 778 6495",
    "sg:postcode":"98036",
    "sg:province":"WA",
    "sg:tags":[
        "equipment",
        "dealer"
    ],
    "wof:name":"P C Club Computers",
    "wof:placetype":"venue"
},
  "geometry": {"coordinates":[-122.28779,47.820883],"type":"Point"}
}