{
  "type": "Feature",
  "properties": {
    "addr:full":"2855 152nd Ave NE Redmond WA 98052",
    "addr:housenumber":"2855",
    "addr:postcode":"98052",
    "addr:street":"152Nd Ave Ne",
    "iso:country":"US",
    "sg:address":"2855 152nd Ave NE",
    "sg:city":"Redmond",
    "sg:classifiers":[
        {
            "category":"Shopping",
            "subcategory":"Catalog Store",
            "type":"Retail Goods"
        }
    ],
    "sg:phone":"+1 425 644 9263",
    "sg:postcode":"98052",
    "sg:province":"WA",
    "sg:tags":[
        "mail",
        "house"
    ],
    "wof:name":"Hard To Find Books LLC",
    "wof:placetype":"venue"
},
  "geometry": {"coordinates":[-122.13775200000001,47.635697],"type":"Point"}
}