{
  "type": "Feature",
  "properties": {
    "addr:full":"1215 S 7th St Mount Vernon WA 98273",
    "addr:housenumber":"1215",
    "addr:postcode":"98273",
    "addr:street":"S 7Th St",
    "iso:country":"US",
    "sg:address":"1215 S 7th St",
    "sg:city":"Mount Vernon",
    "sg:classifiers":[
        {
            "category":"Freight",
            "type":"Transportation"
        }
    ],
    "sg:phone":"+1 360 419 0119",
    "sg:postcode":"98273",
    "sg:province":"WA",
    "wof:name":"Police Transport",
    "wof:placetype":"venue"
},
  "geometry": {"coordinates":[-122.332087,48.413713],"type":"Point"}
}