{
  "type": "Feature",
  "properties": {
    "addr:full":"6075 Coles Rd Langley WA 98260",
    "addr:housenumber":"6075",
    "addr:postcode":"98260",
    "addr:street":"Coles Rd",
    "iso:country":"US",
    "sg:address":"6075 Coles Rd",
    "sg:city":"Langley",
    "sg:classifiers":[
        {
            "category":"Building & Trades",
            "subcategory":"Landscaping Services",
            "type":"Services"
        }
    ],
    "sg:phone":"+1 360 321 6505",
    "sg:postcode":"98260",
    "sg:province":"WA",
    "sg:tags":[
        "lawn",
        "maintenance"
    ],
    "wof:name":"Growing Concern",
    "wof:placetype":"venue"
},
  "geometry": {"coordinates":[-122.428349,47.990752],"type":"Point"}
}