{
  "type": "Feature",
  "properties": {
    "addr:full":"803 S McKinney Rd Othello WA 99344",
    "addr:housenumber":"803",
    "addr:postcode":"99344",
    "addr:street":"S Mckinney Rd",
    "iso:country":"US",
    "sg:address":"803 S McKinney Rd",
    "sg:city":"Othello",
    "sg:classifiers":[
        {
            "category":"Banks & Credit Unions",
            "subcategory":"Financial Services",
            "type":"Services"
        }
    ],
    "sg:phone":"+1 509 488 3765",
    "sg:postcode":"99344",
    "sg:province":"WA",
    "sg:tags":[
        "trust",
        "management"
    ],
    "wof:name":"Antelope Trust & Ballar",
    "wof:placetype":"venue"
},
  "geometry": {"coordinates":[-119.22878,46.79624],"type":"Point"}
}