{
  "type": "Feature",
  "properties": {
    "addr:full":"18100 19th Dr SE Bothell WA 98012",
    "addr:housenumber":"18100",
    "addr:postcode":"98012",
    "addr:street":"19Th Dr Se",
    "iso:country":"US",
    "sg:address":"18100 19th Dr SE",
    "sg:city":"Bothell",
    "sg:classifiers":[
        {
            "category":"Professional",
            "subcategory":"Computer Services",
            "type":"Services"
        }
    ],
    "sg:phone":"+1 425 487 1291",
    "sg:postcode":"98012",
    "sg:province":"WA",
    "sg:tags":[
        "datum"
    ],
    "wof:name":"Deaners Web Consultant S",
    "wof:placetype":"venue"
},
  "geometry": {"coordinates":[-122.206594,47.83412],"type":"Point"}
}