{
  "type": "Feature",
  "properties": {
    "addr:full":"513 N Front St Yakima WA 98901",
    "addr:housenumber":"513",
    "addr:postcode":"98901",
    "addr:street":"N Front St",
    "iso:country":"US",
    "sg:address":"513 N Front St",
    "sg:city":"Yakima",
    "sg:classifiers":[
        {
            "category":"Professional",
            "subcategory":"Management & Consulting",
            "type":"Services"
        }
    ],
    "sg:phone":"+1 509 248 4156",
    "sg:postcode":"98901",
    "sg:province":"WA",
    "sg:tags":[
        "consultant",
        "business"
    ],
    "wof:name":"Durant Development Svc Inc",
    "wof:placetype":"venue"
},
  "geometry": {"coordinates":[-120.511084,46.60928],"type":"Point"}
}