{
  "type": "Feature",
  "properties": {
    "addr:full":"715 9th Ave Ste 400 Seattle WA 98104",
    "addr:housenumber":"715",
    "addr:postcode":"98104",
    "addr:street":"9Th Ave Ste 400",
    "iso:country":"US",
    "sg:address":"715 9th Ave Ste 400",
    "sg:city":"Seattle",
    "sg:classifiers":[
        {
            "category":"Social Services",
            "subcategory":"Retirement Home",
            "type":"Services"
        }
    ],
    "sg:phone":"+1 206 826 2111",
    "sg:postcode":"98104",
    "sg:province":"WA",
    "sg:website":"www.prcn.net",
    "wof:name":"Presbyterian Retirement Communities Northwest",
    "wof:placetype":"venue"
},
  "geometry": {"coordinates":[-122.325513,47.606369],"type":"Point"}
}