{
  "type": "Feature",
  "properties": {
    "addr:full":"200 1st Ave W Ste 401 Seattle WA 98119",
    "addr:housenumber":"200",
    "addr:postcode":"98119",
    "addr:street":"1St Ave W Ste 401",
    "iso:country":"US",
    "sg:address":"200 1st Ave W Ste 401",
    "sg:city":"Seattle",
    "sg:classifiers":[
        {
            "category":"Professional",
            "subcategory":"Accounting & Tax Preparation",
            "type":"Services"
        }
    ],
    "sg:phone":"+1 206 284 9900",
    "sg:postcode":"98119",
    "sg:province":"WA",
    "sg:tags":[
        "accountant"
    ],
    "wof:name":"Nelson Watson & Erickson",
    "wof:placetype":"venue"
},
  "geometry": {"coordinates":[-122.364998,47.6353],"type":"Point"}
}