{
  "type": "Feature",
  "properties": {
    "addr:full":"812 S Dishman Rd Spokane Valley WA 99206",
    "addr:housenumber":"812",
    "addr:postcode":"99206",
    "addr:street":"S Dishman Rd",
    "iso:country":"US",
    "sg:address":"812 S Dishman Rd",
    "sg:city":"Spokane Valley",
    "sg:classifiers":[
        {
            "category":"Home & Garden",
            "subcategory":"Garden Supply",
            "type":"Retail Goods"
        }
    ],
    "sg:phone":"+1 509 924 0024",
    "sg:postcode":"99206",
    "sg:province":"WA",
    "sg:tags":[
        "bark"
    ],
    "wof:name":"Valley Landscape Materials",
    "wof:placetype":"venue"
},
  "geometry": {"coordinates":[-117.278238,47.648817],"type":"Point"}
}