{
  "type": "Feature",
  "properties": {
    "addr:full":"5128 55th Ave S Seattle WA 98118",
    "addr:housenumber":"5128",
    "addr:postcode":"98118",
    "addr:street":"55Th Ave S",
    "iso:country":"US",
    "sg:address":"5128 55th Ave S",
    "sg:city":"Seattle",
    "sg:classifiers":[
        {
            "category":"Real Estate",
            "subcategory":"Real Estate Agent",
            "type":"Services"
        }
    ],
    "sg:phone":"+1 206 723 6484",
    "sg:postcode":"98118",
    "sg:province":"WA",
    "sg:tags":[
        "organization",
        "membership"
    ],
    "wof:name":"Mar Family LLC",
    "wof:placetype":"venue"
},
  "geometry": {"coordinates":[-122.264567,47.555178],"type":"Point"}
}