{
  "type": "Feature",
  "properties": {
    "iso:country":"US",
    "sg:address":"11020 280th St E",
    "sg:city":"Graham",
    "sg:classifiers":[
        {
            "category":"Building & Trades",
            "subcategory":"Construction",
            "type":"Services"
        }
    ],
    "sg:phone":"+1 253 847 9320",
    "sg:postcode":"98338",
    "sg:province":"WA",
    "sg:tags":[
        "painting",
        "contractor"
    ],
    "wof:name":"General Coatings",
    "wof:placetype":"venue"
},
  "geometry": {"coordinates":[-122.28302600000001,47.001924],"type":"Point"}
}