{
  "type": "Feature",
  "properties": {
    "iso:country":"US",
    "sg:address":"611 E Gordon Ave",
    "sg:city":"Spokane",
    "sg:classifiers":[
        {
            "category":"Education",
            "subcategory":"Special Training",
            "type":"Public Place"
        }
    ],
    "sg:phone":"+1 509 489 2978",
    "sg:postcode":"99207",
    "sg:province":"WA",
    "wof:name":"Kathy Riopelles Piano Lesson",
    "wof:placetype":"venue"
},
  "geometry": {"coordinates":[-117.39795599999999,47.690874],"type":"Point"}
}