{
  "type": "Feature",
  "properties": {
    "addr:full":"10501 NE Hwy 99 Vancouver WA 98686",
    "addr:housenumber":"10501",
    "addr:postcode":"98686",
    "addr:street":"Ne Hwy 99",
    "iso:country":"US",
    "sg:address":"10501 NE Hwy 99",
    "sg:city":"Vancouver",
    "sg:classifiers":[
        {
            "category":"Food & Beverages",
            "subcategory":"Groceries & Convenience Stores",
            "type":"Retail Goods"
        }
    ],
    "sg:phone":"+1 360 573 7527",
    "sg:postcode":"98686",
    "sg:province":"WA",
    "sg:tags":[
        "grocer"
    ],
    "wof:name":"Corner Market",
    "wof:placetype":"venue"
},
  "geometry": {"coordinates":[-122.65399499999999,45.697514],"type":"Point"}
}