{
  "type": "Feature",
  "properties": {
    "addr:full":"1521 Cole St Enumclaw WA 98022",
    "addr:housenumber":"1521",
    "addr:postcode":"98022",
    "addr:street":"Cole St",
    "iso:country":"US",
    "sg:address":"1521 Cole St",
    "sg:city":"Enumclaw",
    "sg:classifiers":[
        {
            "category":"Restaurant",
            "type":"Food & Drink"
        }
    ],
    "sg:phone":"+1 360 825 3451",
    "sg:postcode":"98022",
    "sg:province":"WA",
    "wof:name":"The Kitchen Of Enumclaw",
    "wof:placetype":"venue"
},
  "geometry": {"coordinates":[-121.99022100000001,47.203113],"type":"Point"}
}