{
  "type": "Feature",
  "properties": {
    "addr:full":"4307 236th St SW Mountlake Terrace WA 98043",
    "addr:housenumber":"4307",
    "addr:postcode":"98043",
    "addr:street":"236Th St Sw",
    "iso:country":"US",
    "sg:address":"4307 236th St SW",
    "sg:city":"Mountlake Terrace",
    "sg:classifiers":[
        {
            "category":"Professional",
            "subcategory":"Computer Services",
            "type":"Services"
        }
    ],
    "sg:phone":"+1 509 663 2535",
    "sg:postcode":"98043",
    "sg:province":"WA",
    "sg:tags":[
        "related"
    ],
    "wof:name":"Aidan M Garverr",
    "wof:placetype":"venue"
},
  "geometry": {"coordinates":[-122.28989199999999,47.785024],"type":"Point"}
}