{
  "type": "Feature",
  "properties": {
    "addr:full":"304 N 2nd St Yakima WA 98901",
    "addr:housenumber":"304",
    "addr:postcode":"98901",
    "addr:street":"N 2Nd St",
    "iso:country":"US",
    "sg:address":"304 N 2nd St",
    "sg:city":"Yakima",
    "sg:classifiers":[
        {
            "category":"Organizations",
            "subcategory":"Non-profit Organization",
            "type":"Services"
        },
        {
            "category":"Organizations",
            "subcategory":"Community Association",
            "type":"Services"
        }
    ],
    "sg:phone":"+1 509 453 3921",
    "sg:postcode":"98901",
    "sg:province":"WA",
    "sg:tags":[
        "real estate"
    ],
    "wof:name":"Women's Century Club",
    "wof:placetype":"venue"
},
  "geometry": {"coordinates":[-120.50709000000001,46.607518],"type":"Point"}
}