{
  "type": "Feature",
  "properties": {
    "addr:full":"7551 15th Ave NW Seattle WA 98117",
    "addr:housenumber":"7551",
    "addr:postcode":"98117",
    "addr:street":"15Th Ave Nw",
    "iso:country":"US",
    "sg:address":"7551 15th Ave NW",
    "sg:city":"Seattle",
    "sg:classifiers":[
        {
            "category":"Shopping",
            "subcategory":"Used Merchandise",
            "type":"Retail Goods"
        }
    ],
    "sg:phone":"+1 206 782 1173",
    "sg:postcode":"98117",
    "sg:province":"WA",
    "sg:tags":[
        "vintage",
        "consignment"
    ],
    "sg:website":"www.facebook.com/pages/Seattle-W...",
    "wof:name":"Los Rubbish",
    "wof:placetype":"venue"
},
  "geometry": {"coordinates":[-122.377139,47.684806],"type":"Point"}
}