{
  "type": "Feature",
  "properties": {
    "iso:country":"US",
    "sg:address":"14700 E Indiana Ave",
    "sg:city":"Spokane Valley",
    "sg:classifiers":[
        {
            "category":"Professional",
            "type":"Services"
        }
    ],
    "sg:phone":"+1 509 228 9664",
    "sg:postcode":"99216",
    "sg:province":"WA",
    "sg:tags":[
        "establishment"
    ],
    "wof:name":"Cavalcade",
    "wof:placetype":"venue"
},
  "geometry": {"coordinates":[-117.204581,47.675322],"type":"Point"}
}