{
  "type": "Feature",
  "properties": {
    "iso:country":"US",
    "sg:address":"6316 NE 196th St",
    "sg:city":"Kenmore",
    "sg:classifiers":[
        {
            "category":"Professional",
            "subcategory":"Management & Consulting",
            "type":"Services"
        }
    ],
    "sg:phone":"+1 425 481 7199",
    "sg:postcode":"98028",
    "sg:province":"WA",
    "sg:tags":[
        "business"
    ],
    "wof:name":"Enalliance",
    "wof:placetype":"venue"
},
  "geometry": {"coordinates":[-122.25582900000001,47.770827],"type":"Point"}
}