{
  "type": "Feature",
  "properties": {
    "addr:full":"2100 Rangeview Rd Othello WA 99344",
    "addr:housenumber":"2100",
    "addr:postcode":"99344",
    "addr:street":"Rangeview Rd",
    "iso:country":"US",
    "sg:address":"2100 Rangeview Rd",
    "sg:city":"Othello",
    "sg:classifiers":[
        {
            "category":"Professional",
            "type":"Services"
        }
    ],
    "sg:phone":"+1 509 488 1006",
    "sg:postcode":"99344",
    "sg:province":"WA",
    "wof:name":"Washington Fruit & Produc",
    "wof:placetype":"venue"
},
  "geometry": {"coordinates":[-119.191011,46.719642],"type":"Point"}
}