{
  "type": "Feature",
  "properties": {
    "iso:country":"US",
    "sg:address":"1905 D St",
    "sg:city":"Bellingham",
    "sg:classifiers":[
        {
            "category":"Personal",
            "subcategory":"Beauty Salon",
            "type":"Services"
        }
    ],
    "sg:phone":"+1 360 714 8964",
    "sg:postcode":"98225",
    "sg:province":"WA",
    "sg:tags":[
        "shop"
    ],
    "wof:name":"Equilibrium Skin Care Clinic",
    "wof:placetype":"venue"
},
  "geometry": {"coordinates":[-122.481306,48.757282],"type":"Point"}
}