{
  "type": "Feature",
  "properties": {
    "addr:full":"1502 22nd St NW Auburn WA 98001",
    "addr:housenumber":"1502",
    "addr:postcode":"98001",
    "addr:street":"22Nd St Nw",
    "iso:country":"US",
    "sg:address":"1502 22nd St NW",
    "sg:city":"Auburn",
    "sg:classifiers":[
        {
            "category":"Manufacturing",
            "subcategory":"Metals",
            "type":"Manufacturing & Wholesale Goods"
        }
    ],
    "sg:phone":"+1 253 833 4342",
    "sg:postcode":"98001",
    "sg:province":"WA",
    "sg:tags":[
        "dry wall",
        "contractor"
    ],
    "sg:website":"www.sprayrig.com",
    "wof:name":"American Spray Technologies",
    "wof:placetype":"venue"
},
  "geometry": {"coordinates":[-122.251204,47.327191],"type":"Point"}
}