{
  "type": "Feature",
  "properties": {
    "addr:full":"8512 122nd Ave NE Kirkland WA 98033",
    "addr:housenumber":"8512",
    "addr:postcode":"98033",
    "addr:street":"122Nd Ave Ne",
    "iso:country":"US",
    "sg:address":"8512 122nd Ave NE",
    "sg:city":"Kirkland",
    "sg:classifiers":[
        {
            "category":"Professional",
            "subcategory":"Lawyer & Legal Services",
            "type":"Services"
        }
    ],
    "sg:phone":"+1 425 739 4502",
    "sg:postcode":"98033",
    "sg:province":"WA",
    "sg:tags":[
        "notary"
    ],
    "wof:name":"Mail-Max",
    "wof:placetype":"venue"
},
  "geometry": {"coordinates":[-122.178279,47.680042],"type":"Point"}
}