{
  "type": "Feature",
  "properties": {
    "addr:full":"304 Wells Ave S Renton WA 98057",
    "addr:housenumber":"304",
    "addr:postcode":"98057",
    "addr:street":"Wells Ave S Renton",
    "iso:country":"US",
    "sg:address":"304 Wells Ave S",
    "sg:city":"Renton",
    "sg:classifiers":[
        {
            "category":"Professional",
            "type":"Services"
        },
        {
            "category":"Restaurant",
            "type":"Food & Drink"
        },
        {
            "category":"Fast Food",
            "type":"Food & Drink"
        }
    ],
    "sg:phone":"+1 425 255 4820",
    "sg:postcode":"98057",
    "sg:province":"WA",
    "sg:tags":[
        "house",
        "soul",
        "take",
        "caterer",
        "barbecue",
        "steak",
        "barbeque"
    ],
    "sg:website":"www.cedarriversmokehouse.com",
    "wof:name":"Cedar River Smoke House",
    "wof:placetype":"venue"
},
  "geometry": {"coordinates":[-122.205412,47.479552],"type":"Point"}
}