{
  "type": "Feature",
  "properties": {
    "addr:full":"616 SW 152nd St Ste B Burien WA 98166",
    "addr:housenumber":"616",
    "addr:postcode":"98166",
    "addr:street":"Sw 152Nd St Ste B",
    "iso:country":"US",
    "sg:address":"616 SW 152nd St Ste B",
    "sg:city":"Burien",
    "sg:classifiers":[
        {
            "category":"Organizations",
            "subcategory":"Membership Organization",
            "type":"Services"
        }
    ],
    "sg:phone":"+1 206 241 1843",
    "sg:postcode":"98166",
    "sg:province":"WA",
    "sg:tags":[
        "military",
        "veteran"
    ],
    "wof:name":"Paralyzed Veterans Of America",
    "wof:placetype":"venue"
},
  "geometry": {"coordinates":[-122.342281,47.466804],"type":"Point"}
}