{
  "type": "Feature",
  "properties": {
    "addr:full":"3011 N Monroe St Spokane WA 99205",
    "addr:housenumber":"3011",
    "addr:postcode":"99205",
    "addr:street":"N Monroe St",
    "iso:country":"US",
    "sg:address":"3011 N Monroe St",
    "sg:city":"Spokane",
    "sg:classifiers":[
        {
            "category":"Retail",
            "subcategory":"Auto Repair",
            "type":"Services"
        }
    ],
    "sg:phone":"+1 509 324 8863",
    "sg:postcode":"99205",
    "sg:province":"WA",
    "sg:tags":[
        "repairing",
        "automobile"
    ],
    "wof:name":"Tune Tech",
    "wof:placetype":"venue"
},
  "geometry": {"coordinates":[-117.426706,47.685144],"type":"Point"}
}