{
  "type": "Feature",
  "properties": {
    "addr:full":"600 Saint Joseph Pl Wenatchee WA 98801",
    "addr:housenumber":"600",
    "addr:postcode":"98801",
    "addr:street":"Saint Joseph Pl",
    "iso:country":"US",
    "sg:address":"600 Saint Joseph Pl",
    "sg:city":"Wenatchee",
    "sg:classifiers":[
        {
            "category":"Education",
            "subcategory":"School",
            "type":"Public Place"
        }
    ],
    "sg:phone":"+1 509 663 2644",
    "sg:postcode":"98801",
    "sg:province":"WA",
    "wof:name":"St Joseph's School",
    "wof:placetype":"venue"
},
  "geometry": {"coordinates":[-120.332553,47.415914],"type":"Point"}
}