{
  "type": "Feature",
  "properties": {
    "addr:full":"720 W Lewis St Pasco WA 99301",
    "addr:housenumber":"720",
    "addr:postcode":"99301",
    "addr:street":"W Lewis St",
    "iso:country":"US",
    "sg:address":"720 W Lewis St",
    "sg:city":"Pasco",
    "sg:classifiers":[
        {
            "category":"Taxi",
            "type":"Transportation"
        }
    ],
    "sg:phone":"+1 509 547 7877",
    "sg:postcode":"99301",
    "sg:province":"WA",
    "sg:tags":[
        "taxicab"
    ],
    "wof:name":"Taxi 1",
    "wof:placetype":"venue"
},
  "geometry": {"coordinates":[-119.100171,46.228607],"type":"Point"}
}