{
  "type": "Feature",
  "properties": {
    "addr:full":"3121 E Madison St Seattle WA 98112",
    "addr:housenumber":"3121",
    "addr:postcode":"98112",
    "addr:street":"E Madison St",
    "iso:country":"US",
    "sg:address":"3121 E Madison St",
    "sg:city":"Seattle",
    "sg:classifiers":[
        {
            "category":"Professional",
            "type":"Services"
        }
    ],
    "sg:phone":"+1 206 328 6411",
    "sg:postcode":"98112",
    "sg:province":"WA",
    "wof:name":"Mead West Vaco Fsc",
    "wof:placetype":"venue"
},
  "geometry": {"coordinates":[-122.292202,47.626015],"type":"Point"}
}