{
  "type": "Feature",
  "properties": {
    "iso:country":"US",
    "sg:address":"202 S Sams St",
    "sg:city":"Monroe",
    "sg:classifiers":[
        {
            "category":"Organizations",
            "subcategory":"Non-profit Organization",
            "type":"Services"
        }
    ],
    "sg:phone":"+1 360 794 1022",
    "sg:postcode":"98272",
    "sg:province":"WA",
    "wof:name":"Next Step A Skyvalley Resource",
    "wof:placetype":"venue"
},
  "geometry": {"coordinates":[-121.97529299999999,47.853491],"type":"Point"}
}