{
  "type": "Feature",
  "properties": {
    "addr:full":"2802 S Kent Des Moines Rd Seattle WA 98198",
    "addr:housenumber":"2802",
    "addr:postcode":"98198",
    "addr:street":"S Kent Des Moines Rd",
    "iso:country":"US",
    "sg:address":"2802 S Kent Des Moines Rd",
    "sg:city":"Seattle",
    "sg:classifiers":[
        {
            "category":"Retail",
            "subcategory":"Auto Repair",
            "type":"Services"
        }
    ],
    "sg:phone":"+1 206 878 0228",
    "sg:postcode":"98198",
    "sg:province":"WA",
    "sg:tags":[
        "automotive",
        "general"
    ],
    "wof:name":"Quality Auto Electric Inc",
    "wof:placetype":"venue"
},
  "geometry": {"coordinates":[-122.295767,47.394623],"type":"Point"}
}