{
  "type": "Feature",
  "properties": {
    "addr:full":"31840 Pacific Hwy S Federal Way WA 98003",
    "addr:housenumber":"31840",
    "addr:postcode":"98003",
    "addr:street":"Pacific Hwy S Federal Way",
    "iso:country":"US",
    "sg:address":"31840 Pacific Hwy S",
    "sg:city":"Federal Way",
    "sg:classifiers":[
        {
            "category":"Personal",
            "subcategory":"Beauty Salon",
            "type":"Services"
        }
    ],
    "sg:phone":"+1 253 946 8359",
    "sg:postcode":"98003",
    "sg:province":"WA",
    "sg:tags":[
        "shop"
    ],
    "wof:name":"Standing On Top",
    "wof:placetype":"venue"
},
  "geometry": {"coordinates":[-122.313304,47.317996],"type":"Point"}
}