{
  "type": "Feature",
  "properties": {
    "addr:full":"6082 22nd Ave NE Moses Lake WA 98837",
    "addr:housenumber":"6082",
    "addr:postcode":"98837",
    "addr:street":"22Nd Ave Ne",
    "iso:country":"US",
    "sg:address":"6082 22nd Ave NE",
    "sg:city":"Moses Lake",
    "sg:classifiers":[
        {
            "category":"Professional",
            "subcategory":"Business Services",
            "type":"Services"
        }
    ],
    "sg:phone":"+1 509 765 7297",
    "sg:postcode":"98837",
    "sg:province":"WA",
    "sg:tags":[
        "water",
        "treatment"
    ],
    "wof:name":"Cascade Quality Water",
    "wof:placetype":"venue"
},
  "geometry": {"coordinates":[-119.317921,47.174796],"type":"Point"}
}