{
  "type": "Feature",
  "properties": {
    "addr:full":"2506 Jackson Ave Everett WA 98203",
    "addr:housenumber":"2506",
    "addr:postcode":"98203",
    "addr:street":"Jackson Ave",
    "iso:country":"US",
    "sg:address":"2506 Jackson Ave",
    "sg:city":"Everett",
    "sg:classifiers":[
        {
            "category":"Social Services",
            "subcategory":"Child Care",
            "type":"Services"
        }
    ],
    "sg:phone":"+1 425 355 7169",
    "sg:postcode":"98203",
    "sg:province":"WA",
    "sg:tags":[
        "day"
    ],
    "wof:name":"Bons Day Care",
    "wof:placetype":"venue"
},
  "geometry": {"coordinates":[-122.196873,47.93293],"type":"Point"}
}