{
  "type": "Feature",
  "properties": {
    "addr:full":"1712 S 6th Ave Tacoma WA 98405",
    "addr:housenumber":"1712",
    "addr:postcode":"98405",
    "addr:street":"S 6Th Ave",
    "iso:country":"US",
    "sg:address":"1712 S 6th Ave",
    "sg:city":"Tacoma",
    "sg:classifiers":[
        {
            "category":"Social Services",
            "type":"Services"
        }
    ],
    "sg:phone":"+1 253 835 3023",
    "sg:postcode":"98405",
    "sg:province":"WA",
    "sg:tags":[
        "probation"
    ],
    "wof:name":"Maximus Inc",
    "wof:placetype":"venue"
},
  "geometry": {"coordinates":[-122.46287100000001,47.256026],"type":"Point"}
}