{
  "type": "Feature",
  "properties": {
    "addr:full":"1530 Black Lake Blvd SW Olympia WA 98502",
    "addr:housenumber":"1530",
    "addr:postcode":"98502",
    "addr:street":"Black Lake Blvd Sw",
    "iso:country":"US",
    "sg:address":"1530 Black Lake Blvd SW",
    "sg:city":"Olympia",
    "sg:classifiers":[
        {
            "category":"Wholesale",
            "subcategory":"Sporting Goods",
            "type":"Manufacturing & Wholesale Goods"
        }
    ],
    "sg:phone":"+1 360 754 1834",
    "sg:postcode":"98502",
    "sg:province":"WA",
    "sg:tags":[
        "boat",
        "accessory"
    ],
    "wof:name":"Ritz Camera",
    "wof:placetype":"venue"
},
  "geometry": {"coordinates":[-122.939898,47.033156],"type":"Point"}
}