{
  "type": "Feature",
  "properties": {
    "addr:full":"2614 Rucker Ave Everett WA 98201",
    "addr:housenumber":"2614",
    "addr:postcode":"98201",
    "addr:street":"Rucker Ave",
    "iso:country":"US",
    "sg:address":"2614 Rucker Ave",
    "sg:city":"Everett",
    "sg:classifiers":[
        {
            "category":"Real Estate",
            "subcategory":"Real Estate Services",
            "type":"Services"
        },
        {
            "category":"Real Estate",
            "subcategory":"Real Estate Operator",
            "type":"Services"
        }
    ],
    "sg:phone":"+1 425 304 0700",
    "sg:postcode":"98201",
    "sg:province":"WA",
    "sg:tags":[
        "vacancy",
        "apartment",
        "rental",
        "finder",
        "listing"
    ],
    "wof:name":"Rucker Court Apartments",
    "wof:placetype":"venue"
},
  "geometry": {"coordinates":[-122.211367,47.983099],"type":"Point"}
}