{
  "type": "Feature",
  "properties": {
    "addr:full":"211 S Main St Colville WA 99114",
    "addr:housenumber":"211",
    "addr:postcode":"99114",
    "addr:street":"S Main St",
    "iso:country":"US",
    "sg:address":"211 S Main St",
    "sg:city":"Colville",
    "sg:classifiers":[
        {
            "category":"Banks & Credit Unions",
            "subcategory":"Bank",
            "type":"Services"
        }
    ],
    "sg:phone":"+1 509 684 4591",
    "sg:postcode":"99114",
    "sg:province":"WA",
    "wof:name":"Key Bank",
    "wof:placetype":"venue"
},
  "geometry": {"coordinates":[-117.905688,48.543263],"type":"Point"}
}