{
  "type": "Feature",
  "properties": {
    "addr:full":"38109 83rd Ave E Eatonville WA 98328",
    "addr:housenumber":"38109",
    "addr:postcode":"98328",
    "addr:street":"83Rd Ave E",
    "iso:country":"US",
    "sg:address":"38109 83rd Ave E",
    "sg:city":"Eatonville",
    "sg:classifiers":[
        {
            "category":"Building & Trades",
            "subcategory":"Construction",
            "type":"Services"
        }
    ],
    "sg:phone":"+1 360 832 8200",
    "sg:postcode":"98328",
    "sg:province":"WA",
    "sg:tags":[
        "general",
        "contractor"
    ],
    "wof:name":"Maida's Custom Stairs",
    "wof:placetype":"venue"
},
  "geometry": {"coordinates":[-122.3202,46.909978],"type":"Point"}
}