{
  "type": "Feature",
  "properties": {
    "iso:country":"US",
    "sg:address":"840 E Allen Rd",
    "sg:city":"Sunnyside",
    "sg:classifiers":[
        {
            "category":"Farming",
            "subcategory":"Livestock Farm",
            "type":"Manufacturing & Wholesale Goods"
        }
    ],
    "sg:phone":"+1 509 837 7650",
    "sg:postcode":"98944",
    "sg:province":"WA",
    "sg:tags":[
        "beef",
        "marketing",
        "corn",
        "crop",
        "cattle",
        "prep",
        "feedlot"
    ],
    "wof:name":"J & L Rollinger Farms",
    "wof:placetype":"venue"
},
  "geometry": {"coordinates":[-119.96277499999999,46.30952],"type":"Point"}
}