{
  "type": "Feature",
  "properties": {
    "addr:full":"1111 Northcliff Rd Shelton WA 98584",
    "addr:housenumber":"1111",
    "addr:postcode":"98584",
    "addr:street":"Northcliff Rd",
    "iso:country":"US",
    "sg:address":"1111 Northcliff Rd",
    "sg:city":"Shelton",
    "sg:classifiers":[
        {
            "category":"Banks & Credit Unions",
            "subcategory":"Investment Brokerage",
            "type":"Services"
        }
    ],
    "sg:phone":"+1 360 427 5814",
    "sg:postcode":"98584",
    "sg:province":"WA",
    "sg:tags":[
        "advisory"
    ],
    "wof:name":"Dh Roberts Investments",
    "wof:placetype":"venue"
},
  "geometry": {"coordinates":[-123.103167,47.220248],"type":"Point"}
}