{
  "type": "Feature",
  "properties": {
    "addr:full":"321 9th St Leavenworth WA 98826",
    "addr:housenumber":"321",
    "addr:postcode":"98826",
    "addr:street":"9Th St",
    "iso:country":"US",
    "sg:address":"321 9th St",
    "sg:city":"Leavenworth",
    "sg:classifiers":[
        {
            "category":"Home & Garden",
            "subcategory":"Home Furnishings",
            "type":"Retail Goods"
        }
    ],
    "sg:phone":"+1 509 548 8005",
    "sg:postcode":"98826",
    "sg:province":"WA",
    "sg:tags":[
        "curtain",
        "made",
        "drapery"
    ],
    "wof:name":"A Shady Lady & Co",
    "wof:placetype":"venue"
},
  "geometry": {"coordinates":[-120.66017100000001,47.594936],"type":"Point"}
}