{
  "type": "Feature",
  "properties": {
    "addr:full":"1904 3rd Avenue Seattle WA 98101",
    "addr:housenumber":"1904",
    "addr:postcode":"98101",
    "addr:street":"3Rd Avenue",
    "iso:country":"US",
    "sg:address":"1904 3rd Avenue",
    "sg:city":"Seattle",
    "sg:classifiers":[
        {
            "category":"Professional",
            "subcategory":"Lawyer & Legal Services",
            "type":"Services"
        }
    ],
    "sg:phone":"+1 206 223 1543",
    "sg:postcode":"98101",
    "sg:province":"WA",
    "sg:tags":[
        "divorce",
        "law",
        "family"
    ],
    "wof:name":"Rimson Lorraine",
    "wof:placetype":"venue"
},
  "geometry": {"coordinates":[-122.339647,47.61172],"type":"Point"}
}