{
  "type": "Feature",
  "properties": {
    "addr:full":"4967 Waschke Rd Bellingham WA 98226",
    "addr:housenumber":"4967",
    "addr:postcode":"98226",
    "addr:street":"Waschke Rd",
    "iso:country":"US",
    "sg:address":"4967 Waschke Rd",
    "sg:city":"Bellingham",
    "sg:classifiers":[
        {
            "category":"Food & Beverages",
            "subcategory":"Meat & Fish",
            "type":"Retail Goods"
        }
    ],
    "sg:phone":"+1 360 384 0436",
    "sg:postcode":"98226",
    "sg:province":"WA",
    "wof:name":"Mark Pennylegion",
    "wof:placetype":"venue"
},
  "geometry": {"coordinates":[-122.530007,48.8202],"type":"Point"}
}