{
  "type": "Feature",
  "properties": {
    "addr:full":"8630 NE 24th St Bellevue WA 98004",
    "addr:housenumber":"8630",
    "addr:postcode":"98004",
    "addr:street":"Ne 24Th St",
    "iso:country":"US",
    "sg:address":"8630 NE 24th St",
    "sg:city":"Bellevue",
    "sg:classifiers":[
        {
            "category":"Professional",
            "subcategory":"Art Services",
            "type":"Services"
        }
    ],
    "sg:phone":"+1 425 456 0051",
    "sg:postcode":"98004",
    "sg:province":"WA",
    "sg:tags":[
        "commercial",
        "graphic",
        "design",
        "package"
    ],
    "wof:name":"S & S Design Group",
    "wof:placetype":"venue"
},
  "geometry": {"coordinates":[-122.22369399999999,47.631935],"type":"Point"}
}