{
  "type": "Feature",
  "properties": {
    "addr:full":"1365 NE Hahobas Way Tahuya WA 98588",
    "addr:housenumber":"1365",
    "addr:postcode":"98588",
    "addr:street":"Ne Hahobas Way",
    "iso:country":"US",
    "sg:address":"1365 NE Hahobas Way",
    "sg:city":"Tahuya",
    "sg:classifiers":[
        {
            "category":"Travel",
            "subcategory":"Campground",
            "type":"Entertainment"
        }
    ],
    "sg:phone":"+1 360 372 2701",
    "sg:postcode":"98588",
    "sg:province":"WA",
    "sg:tags":[
        "camp"
    ],
    "wof:name":"Hohobas Bsa Camp",
    "wof:placetype":"venue"
},
  "geometry": {"coordinates":[-123.067583,47.427914],"type":"Point"}
}