{
  "type": "Feature",
  "properties": {
    "addr:full":"221 18th Avenue S Ofc Seattle WA 98144",
    "addr:housenumber":"221",
    "addr:postcode":"98144",
    "addr:street":"18Th Avenue S",
    "iso:country":"US",
    "sg:address":"221 18th Avenue S Ofc",
    "sg:city":"Seattle",
    "sg:classifiers":[
        {
            "category":"Real Estate",
            "subcategory":"Real Estate Operator",
            "type":"Services"
        }
    ],
    "sg:phone":"+1 206 322 4550",
    "sg:postcode":"98144",
    "sg:province":"WA",
    "sg:tags":[
        "apartment"
    ],
    "wof:name":"Kawabe Memorial House",
    "wof:placetype":"venue"
},
  "geometry": {"coordinates":[-122.308892,47.600595],"type":"Point"}
}