{
  "type": "Feature",
  "properties": {
    "addr:full":"9860 40th Ave S Seattle WA 98118",
    "addr:housenumber":"9860",
    "addr:postcode":"98118",
    "addr:street":"40Th Ave S",
    "iso:country":"US",
    "sg:address":"9860 40th Ave S",
    "sg:city":"Seattle",
    "sg:classifiers":[
        {
            "category":"Manufacturing",
            "subcategory":"Paper Products",
            "type":"Manufacturing & Wholesale Goods"
        }
    ],
    "sg:phone":"+1 206 723 5880",
    "sg:postcode":"98118",
    "sg:province":"WA",
    "sg:tags":[
        "box",
        "pr",
        "folding",
        "mfg",
        "paperboard",
        "commercial",
        "lithographic"
    ],
    "wof:name":"Stoneway Carton Company Inc",
    "wof:placetype":"venue"
},
  "geometry": {"coordinates":[-122.284238,47.512647],"type":"Point"}
}