{
  "type": "Feature",
  "properties": {
    "addr:full":"15100 SE 38th St Bellevue WA 98006",
    "addr:postcode":"15100;98006",
    "addr:street":"Se 38Th St",
    "iso:country":"US",
    "sg:address":"15100 SE 38th St",
    "sg:city":"Bellevue",
    "sg:classifiers":[
        {
            "category":"Shopping",
            "subcategory":"Florist",
            "type":"Retail Goods"
        }
    ],
    "sg:phone":"+1 425 747 3585",
    "sg:postcode":"98006",
    "sg:province":"WA",
    "wof:name":"Delaurenti's Florist & Gifts",
    "wof:placetype":"venue"
},
  "geometry": {"coordinates":[-122.139,47.576],"type":"Point"}
}