{
  "type": "Feature",
  "properties": {
    "addr:full":"10824 SE 200th St Kent WA 98031",
    "addr:housenumber":"10824",
    "addr:postcode":"98031",
    "addr:street":"Se 200Th St",
    "iso:country":"US",
    "sg:address":"10824 SE 200th St",
    "sg:city":"Kent",
    "sg:classifiers":[
        {
            "category":"Building & Trades",
            "subcategory":"Construction",
            "type":"Services"
        }
    ],
    "sg:phone":"+1 253 813 0260",
    "sg:postcode":"98031",
    "sg:province":"WA",
    "sg:tags":[
        "house"
    ],
    "wof:name":"Z Man Construction",
    "wof:placetype":"venue"
},
  "geometry": {"coordinates":[-122.19516900000001,47.423162],"type":"Point"}
}