{
  "type": "Feature",
  "properties": {
    "addr:full":"12303 NE 130th Ln # 350 Kirkland WA 98034",
    "addr:housenumber":"12303",
    "addr:postcode":"98034",
    "addr:street":"Ne 130Th Ln # 350",
    "iso:country":"US",
    "sg:address":"12303 NE 130th Ln # 350",
    "sg:city":"Kirkland",
    "sg:classifiers":[
        {
            "category":"Health Services",
            "subcategory":"Doctor",
            "type":"Services"
        }
    ],
    "sg:phone":"+1 425 899 4400",
    "sg:postcode":"98034",
    "sg:province":"WA",
    "sg:tags":[
        "physician",
        "reconstructive",
        "surgeons",
        "cosmetic",
        "plastic",
        "manipulative",
        "osteopathic",
        "treatment",
        "surgery",
        "surgeon"
    ],
    "sg:website":"http://www.remingtonplasticsurgery.com",
    "wof:name":"Bradley L. Remington, MD",
    "wof:placetype":"venue"
},
  "geometry": {"coordinates":[-122.177059,47.716721],"type":"Point"}
}