{
  "type": "Feature",
  "properties": {
    "addr:full":"1 Bellis Fair Pkwy Ste 326 Bellingham WA 98226",
    "addr:housenumber":"1",
    "addr:postcode":"98226",
    "addr:street":"Bellis Fair Pkwy Ste 326",
    "iso:country":"US",
    "sg:address":"1 Bellis Fair Pkwy Ste 326",
    "sg:city":"Bellingham",
    "sg:classifiers":[
        {
            "category":"Shopping",
            "subcategory":"Clothing, Apparel, & Fashions",
            "type":"Retail Goods"
        },
        {
            "category":"Shopping",
            "subcategory":"Baby Store",
            "type":"Retail Goods"
        }
    ],
    "sg:phone":"+1 360 647 9398",
    "sg:postcode":"98226",
    "sg:province":"WA",
    "sg:tags":[
        "infant",
        "children's",
        "wear",
        "girls'",
        "clothing",
        "boys'"
    ],
    "sg:website":"http://www.gymboree.com",
    "wof:name":"Gymboree",
    "wof:placetype":"venue"
},
  "geometry": {"coordinates":[-122.486183,48.784382],"type":"Point"}
}