{
  "type": "Feature",
  "properties": {
    "addr:full":"600 1st Ave Seattle WA 98104",
    "addr:housenumber":"600",
    "addr:postcode":"98104",
    "addr:street":"1St Ave",
    "iso:country":"US",
    "sg:address":"600 1st Ave",
    "sg:city":"Seattle",
    "sg:classifiers":[
        {
            "category":"Professional",
            "type":"Services"
        }
    ],
    "sg:phone":"+1 206 583 5900",
    "sg:postcode":"98104",
    "sg:province":"WA",
    "sg:tags":[
        "arts",
        "artist"
    ],
    "wof:name":"Atlas Robin Fine Art Consltng",
    "wof:placetype":"venue"
},
  "geometry": {"coordinates":[-122.334283,47.602554],"type":"Point"}
}