{
  "type": "Feature",
  "properties": {
    "addr:full":"2914 McDougall Ave Everett WA 98201",
    "addr:housenumber":"2914",
    "addr:postcode":"98201",
    "addr:street":"Mcdougall Ave",
    "iso:country":"US",
    "sg:address":"2914 McDougall Ave",
    "sg:city":"Everett",
    "sg:classifiers":[
        {
            "category":"Wholesale",
            "subcategory":"Machinery & Supplies",
            "type":"Manufacturing & Wholesale Goods"
        }
    ],
    "sg:phone":"+1 425 252 2105",
    "sg:postcode":"98201",
    "sg:province":"WA",
    "sg:tags":[
        "janitor"
    ],
    "sg:website":"www.westfacsup.com",
    "wof:name":"Western Facilities Supply",
    "wof:placetype":"venue"
},
  "geometry": {"coordinates":[-122.20017799999999,47.97805],"type":"Point"}
}