{
  "type": "Feature",
  "properties": {
    "addr:full":"11801 NE 212th Ave Brush Prairie WA 98606",
    "addr:housenumber":"11801",
    "addr:postcode":"98606",
    "addr:street":"Ne 212Th Ave",
    "iso:country":"US",
    "sg:address":"11801 NE 212th Ave",
    "sg:city":"Brush Prairie",
    "sg:classifiers":[
        {
            "category":"Wholesale",
            "subcategory":"Home Furnishings",
            "type":"Manufacturing & Wholesale Goods"
        }
    ],
    "sg:phone":"+1 360 604 1945",
    "sg:postcode":"98606",
    "sg:province":"WA",
    "wof:name":"Bamboo Man",
    "wof:placetype":"venue"
},
  "geometry": {"coordinates":[-122.455382,45.706228],"type":"Point"}
}