{
  "type": "Feature",
  "properties": {
    "addr:full":"8416 NE Beck Rd Bainbridge Island WA 98110",
    "addr:housenumber":"8416",
    "addr:postcode":"98110",
    "addr:street":"Ne Beck Rd",
    "iso:country":"US",
    "sg:address":"8416 NE Beck Rd",
    "sg:city":"Bainbridge Island",
    "sg:classifiers":[
        {
            "category":"Shopping",
            "type":"Retail Goods"
        }
    ],
    "sg:phone":"+1 206 842 9080",
    "sg:postcode":"98110",
    "sg:province":"WA",
    "sg:tags":[
        "merchandise"
    ],
    "wof:name":"Voice Gallery The",
    "wof:placetype":"venue"
},
  "geometry": {"coordinates":[-122.536241,47.599651],"type":"Point"}
}