{
  "type": "Feature",
  "properties": {
    "addr:full":"324 Capitol Way N Olympia WA 98501",
    "addr:housenumber":"324",
    "addr:postcode":"98501",
    "addr:street":"Capitol Way N",
    "iso:country":"US",
    "sg:address":"324 Capitol Way N",
    "sg:city":"Olympia",
    "sg:classifiers":[
        {
            "category":"Food & Beverages",
            "subcategory":"Candy",
            "type":"Retail Goods"
        },
        {
            "category":"Manufacturing",
            "subcategory":"Food",
            "type":"Manufacturing & Wholesale Goods"
        }
    ],
    "sg:phone":"+1 360 236 1620",
    "sg:postcode":"98501",
    "sg:province":"WA",
    "sg:tags":[
        "confectionery-wholesale",
        "confectionery",
        "manufacturer"
    ],
    "sg:website":"http://www.sweetfactory.com",
    "wof:name":"Sweet Factory",
    "wof:placetype":"venue"
},
  "geometry": {"coordinates":[-122.90198700000001,47.046834],"type":"Point"}
}