{
  "type": "Feature",
  "properties": {
    "addr:full":"11708 NE 269th St Battle Ground WA 98604",
    "addr:housenumber":"11708",
    "addr:postcode":"98604",
    "addr:street":"Ne 269Th St",
    "iso:country":"US",
    "sg:address":"11708 NE 269th St",
    "sg:city":"Battle Ground",
    "sg:classifiers":[
        {
            "category":"Building & Trades",
            "subcategory":"Construction",
            "type":"Services"
        }
    ],
    "sg:phone":"+1 360 687 1264",
    "sg:postcode":"98604",
    "sg:province":"WA",
    "sg:tags":[
        "heavy",
        "excavation",
        "landscape",
        "contractor"
    ],
    "wof:name":"M & R Land Clearing",
    "wof:placetype":"venue"
},
  "geometry": {"coordinates":[-122.553684,45.816935],"type":"Point"}
}