{
  "type": "Feature",
  "properties": {
    "addr:full":"1125 N 152 St Shoreline WA 98133",
    "addr:housenumber":"1125",
    "addr:postcode":"98133",
    "addr:street":"N 152 St",
    "iso:country":"US",
    "sg:address":"1125 N 152 St",
    "sg:city":"Shoreline",
    "sg:classifiers":[
        {
            "category":"Restaurant",
            "type":"Food & Drink"
        },
        {
            "category":"Food & Beverages",
            "subcategory":"Ethnic Foods",
            "type":"Retail Goods"
        }
    ],
    "sg:phone":"+1 206 364 1044",
    "sg:postcode":"98133",
    "sg:province":"WA",
    "sg:tags":[
        "greek",
        "mediterranean"
    ],
    "wof:name":"Gyro House & Resturant",
    "wof:placetype":"venue"
},
  "geometry": {"coordinates":[-122.343902,47.738904],"type":"Point"}
}