{
  "type": "Feature",
  "properties": {
    "addr:full":"1812 98th Ave NE Bellevue WA 98004",
    "addr:housenumber":"1812",
    "addr:postcode":"98004",
    "addr:street":"98Th Ave Ne",
    "iso:country":"US",
    "sg:address":"1812 98th Ave NE",
    "sg:city":"Bellevue",
    "sg:classifiers":[
        {
            "category":"Health Services",
            "subcategory":"Doctor",
            "type":"Services"
        }
    ],
    "sg:phone":"+1 425 637 5543",
    "sg:postcode":"98004",
    "sg:province":"WA",
    "sg:tags":[
        "physician",
        "surgeon"
    ],
    "wof:name":"Dr Scott Smith",
    "wof:placetype":"venue"
},
  "geometry": {"coordinates":[-122.209709,47.627324],"type":"Point"}
}