{
  "type": "Feature",
  "properties": {
    "addr:full":"7700 NE 72nd Ave Apt G106 Vancouver WA 98661",
    "addr:housenumber":"7700",
    "addr:postcode":"98661",
    "addr:street":"Ne 72Nd Ave Apt G106",
    "iso:country":"US",
    "sg:address":"7700 NE 72nd Ave Apt G106",
    "sg:city":"Vancouver",
    "sg:classifiers":[
        {
            "category":"Real Estate",
            "subcategory":"Real Estate Operator",
            "type":"Services"
        }
    ],
    "sg:phone":"+1 360 253 2700",
    "sg:postcode":"98661",
    "sg:province":"WA",
    "sg:tags":[
        "apartment"
    ],
    "wof:name":"Golfside Village Apartments",
    "wof:placetype":"venue"
},
  "geometry": {"coordinates":[-122.62400100000001,45.641998],"type":"Point"}
}