{
  "type": "Feature",
  "properties": {
    "addr:full":"304 Center Ave Northport WA 99157",
    "addr:housenumber":"304",
    "addr:postcode":"99157",
    "addr:street":"Center Ave",
    "iso:country":"US",
    "sg:address":"304 Center Ave",
    "sg:city":"Northport",
    "sg:classifiers":[
        {
            "category":"Bars & Pubs",
            "type":"Food & Drink"
        },
        {
            "category":"Restaurant",
            "type":"Food & Drink"
        }
    ],
    "sg:phone":"+1 509 732 6638",
    "sg:postcode":"99157",
    "sg:province":"WA",
    "sg:tags":[
        "tavern"
    ],
    "sg:website":"http://www.whitebirdapps.com",
    "wof:name":"White Bird Tavern",
    "wof:placetype":"venue"
},
  "geometry": {"coordinates":[-117.78094900000001,48.916379],"type":"Point"}
}