{
  "type": "Feature",
  "properties": {
    "addr:full":"8195 166th Ave NE Redmond WA 98052",
    "addr:housenumber":"8195",
    "addr:postcode":"98052",
    "addr:street":"166Th Ave Ne",
    "iso:country":"US",
    "sg:address":"8195 166th Ave NE",
    "sg:city":"Redmond",
    "sg:classifiers":[
        {
            "category":"Professional",
            "subcategory":"Management & Consulting",
            "type":"Services"
        }
    ],
    "sg:phone":"+1 425 497 9003",
    "sg:postcode":"98052",
    "sg:province":"WA",
    "sg:tags":[
        "telecommunication"
    ],
    "wof:name":"Trinity 3",
    "wof:placetype":"venue"
},
  "geometry": {"coordinates":[-122.119253,47.675492],"type":"Point"}
}