{
  "type": "Feature",
  "properties": {
    "addr:full":"9191 Icicle Rd Leavenworth WA 98826",
    "addr:housenumber":"9191",
    "addr:postcode":"98826",
    "addr:street":"Icicle Rd",
    "iso:country":"US",
    "sg:address":"9191 Icicle Rd",
    "sg:city":"Leavenworth",
    "sg:classifiers":[
        {
            "category":"Manufacturing",
            "subcategory":"Lumber",
            "type":"Manufacturing & Wholesale Goods"
        }
    ],
    "sg:phone":"+1 509 548 5850",
    "sg:postcode":"98826",
    "sg:province":"WA",
    "sg:tags":[
        "forestry"
    ],
    "wof:name":"Rick Norman",
    "wof:placetype":"venue"
},
  "geometry": {"coordinates":[-120.674274,47.58435],"type":"Point"}
}