{
  "type": "Feature",
  "properties": {
    "addr:full":"316 W Boone Ave Spokane WA 99201",
    "addr:housenumber":"316",
    "addr:postcode":"99201",
    "addr:street":"W Boone Ave",
    "iso:country":"US",
    "sg:address":"316 W Boone Ave",
    "sg:city":"Spokane",
    "sg:classifiers":[
        {
            "category":"Professional",
            "subcategory":"Management & Consulting",
            "type":"Services"
        }
    ],
    "sg:phone":"+1 509 624 7655",
    "sg:postcode":"99201",
    "sg:province":"WA",
    "sg:tags":[
        "counselor",
        "relation",
        "public",
        "relations"
    ],
    "wof:name":"Gallatin Group Inc",
    "wof:placetype":"venue"
},
  "geometry": {"coordinates":[-117.417159,47.668166],"type":"Point"}
}