{
  "type": "Feature",
  "properties": {
    "addr:full":"5612 W Clearwater Ave Kennewick WA 99336",
    "addr:housenumber":"5612",
    "addr:postcode":"99336",
    "addr:street":"W Clearwater Ave",
    "iso:country":"US",
    "sg:address":"5612 W Clearwater Ave",
    "sg:city":"Kennewick",
    "sg:classifiers":[
        {
            "category":"Insurance",
            "subcategory":"Hazard Insurance",
            "type":"Services"
        }
    ],
    "sg:phone":"+1 509 735 0316",
    "sg:postcode":"99336",
    "sg:province":"WA",
    "sg:website":"http://statefarm.mqgroup.com/url.asp?usr=472304",
    "wof:name":"State Farm Insurance Agent-Hollis Zschokke",
    "wof:placetype":"venue"
},
  "geometry": {"coordinates":[-119.196192,46.21244],"type":"Point"}
}