{
  "type": "Feature",
  "properties": {
    "addr:full":"510 Bell St Edmonds WA 98020",
    "addr:housenumber":"510",
    "addr:postcode":"98020",
    "addr:street":"Bell",
    "iso:country":"US",
    "sg:address":"510 Bell St",
    "sg:city":"Edmonds",
    "sg:classifiers":[
        {
            "category":"Professional",
            "subcategory":"Lawyer & Legal Services",
            "type":"Services"
        }
    ],
    "sg:phone":"+1 425 778 8555",
    "sg:postcode":"98020",
    "sg:province":"WA",
    "sg:tags":[
        "attorney"
    ],
    "wof:name":"Thomas F Mc Donough",
    "wof:placetype":"venue"
},
  "geometry": {"coordinates":[-122.376147,47.811331],"type":"Point"}
}