{
  "type": "Feature",
  "properties": {
    "addr:full":"908 N Lake Rd Spokane WA 99212",
    "addr:housenumber":"908",
    "addr:postcode":"99212",
    "addr:street":"N Lake Rd",
    "iso:country":"US",
    "sg:address":"908 N Lake Rd",
    "sg:city":"Spokane",
    "sg:classifiers":[
        {
            "category":"Retail",
            "subcategory":"Auto Repair",
            "type":"Services"
        }
    ],
    "sg:phone":"+1 509 534 0456",
    "sg:postcode":"99212",
    "sg:province":"WA",
    "sg:tags":[
        "bumper",
        "exchange"
    ],
    "wof:name":"All American Bumper & Plating",
    "wof:placetype":"venue"
},
  "geometry": {"coordinates":[-117.321788,47.664831],"type":"Point"}
}