{
  "type": "Feature",
  "properties": {
    "addr:full":"12574 SE 52nd St Bellevue WA 98006",
    "addr:postcode":"12574;98006",
    "addr:street":"Se 52Nd St",
    "iso:country":"US",
    "sg:address":"12574 SE 52nd St",
    "sg:city":"Bellevue",
    "sg:classifiers":[
        {
            "category":"Professional",
            "subcategory":"Business Services",
            "type":"Services"
        }
    ],
    "sg:phone":"+1 425 643 4859",
    "sg:postcode":"98006",
    "sg:province":"WA",
    "wof:name":"Deborah Ennis Duitch Bus Svc",
    "wof:placetype":"venue"
},
  "geometry": {"coordinates":[-122.171237,47.555181],"type":"Point"}
}