{
  "type": "Feature",
  "properties": {
    "addr:full":"22911 NE 4th St Sammamish WA 98074",
    "addr:housenumber":"22911",
    "addr:postcode":"98074",
    "addr:street":"Ne 4Th St",
    "iso:country":"US",
    "sg:address":"22911 NE 4th St",
    "sg:city":"Sammamish",
    "sg:classifiers":[
        {
            "category":"Restaurant",
            "type":"Food & Drink"
        }
    ],
    "sg:menulink":"http://www.allmenus.com/wa/issaquah-plateau/181416-kfc---kentucky-fried-chicken/menu/",
    "sg:phone":"+1 425 837 8900",
    "sg:postcode":"98074",
    "sg:province":"WA",
    "sg:tags":[
        "american",
        "chicken"
    ],
    "wof:name":"KFC - Kentucky Fried Chicken",
    "wof:placetype":"venue"
},
  "geometry": {"coordinates":[-122.033903,47.612833],"type":"Point"}
}