{
  "type": "Feature",
  "properties": {
    "addr:full":"13719 Densmore Ave N Seattle WA 98133",
    "addr:housenumber":"13719",
    "addr:postcode":"98133",
    "addr:street":"Densmore Ave N",
    "iso:country":"US",
    "sg:address":"13719 Densmore Ave N",
    "sg:city":"Seattle",
    "sg:classifiers":[
        {
            "category":"Autos & Motor Vehicles",
            "subcategory":"Motorcycle Sales",
            "type":"Retail Goods"
        }
    ],
    "sg:phone":"+1 206 818 5014",
    "sg:postcode":"98133",
    "sg:province":"WA",
    "wof:name":"Dragonfly Cycle Concepts",
    "wof:placetype":"venue"
},
  "geometry": {"coordinates":[-122.338284,47.728983],"type":"Point"}
}