{
  "type": "Feature",
  "properties": {
    "addr:full":"14105 Purdy Dr NW Gig Harbor WA 98332",
    "addr:housenumber":"14105",
    "addr:postcode":"98332",
    "addr:street":"Purdy Dr Nw",
    "iso:country":"US",
    "sg:address":"14105 Purdy Dr NW",
    "sg:city":"Gig Harbor",
    "sg:classifiers":[
        {
            "category":"Education",
            "subcategory":"School",
            "type":"Public Place"
        }
    ],
    "sg:phone":"+1 253 857 3530",
    "sg:postcode":"98332",
    "sg:province":"WA",
    "sg:tags":[
        "high"
    ],
    "sg:website":"www.peninsula.wednet.edu",
    "wof:name":"Peninsula High School",
    "wof:placetype":"venue"
},
  "geometry": {"coordinates":[-122.62598699999999,47.386627],"type":"Point"}
}