{
  "type": "Feature",
  "properties": {
    "addr:full":"421 N Mission St Wenatchee WA 98801",
    "addr:housenumber":"421",
    "addr:postcode":"98801",
    "addr:street":"N Mission St",
    "iso:country":"US",
    "sg:address":"421 N Mission St",
    "sg:city":"Wenatchee",
    "sg:classifiers":[
        {
            "category":"Retail",
            "subcategory":"Car Wash",
            "type":"Services"
        }
    ],
    "sg:phone":"+1 509 664 5167",
    "sg:postcode":"98801",
    "sg:province":"WA",
    "sg:tags":[
        "carwash"
    ],
    "wof:name":"Detail Man",
    "wof:placetype":"venue"
},
  "geometry": {"coordinates":[-120.31704999999999,47.429553],"type":"Point"}
}