{
  "type": "Feature",
  "properties": {
    "addr:full":"1309 Washington St Vancouver WA 98660",
    "addr:housenumber":"1309",
    "addr:postcode":"98660",
    "addr:street":"Washington St",
    "iso:country":"US",
    "sg:address":"1309 Washington St",
    "sg:city":"Vancouver",
    "sg:classifiers":[
        {
            "category":"Professional",
            "subcategory":"Advertising",
            "type":"Services"
        }
    ],
    "sg:phone":"+1 360 993 0725",
    "sg:postcode":"98660",
    "sg:province":"WA",
    "sg:tags":[
        "distribution"
    ],
    "wof:name":"Global Corp",
    "wof:placetype":"venue"
},
  "geometry": {"coordinates":[-122.672574,45.631784],"type":"Point"}
}