{
  "type": "Feature",
  "properties": {
    "addr:full":"515 Chenault Ave Hoquiam WA 98550",
    "addr:housenumber":"515",
    "addr:postcode":"98550",
    "addr:street":"Chenault Ave",
    "iso:country":"US",
    "sg:address":"515 Chenault Ave",
    "sg:city":"Hoquiam",
    "sg:classifiers":[
        {
            "category":"Travel",
            "subcategory":"Hotels & Motels",
            "type":"Entertainment"
        }
    ],
    "sg:phone":"+1 360 533 2005",
    "sg:postcode":"98550",
    "sg:province":"WA",
    "sg:tags":[
        "gallery",
        "breakfast",
        "operation",
        "bed",
        "accommodation"
    ],
    "wof:name":"Hoquiam's Castle",
    "wof:placetype":"venue"
},
  "geometry": {"coordinates":[-123.891632,46.983763],"type":"Point"}
}