{
  "type": "Feature",
  "properties": {
    "addr:full":"3624 Courtland Pl S Seattle WA 98144",
    "addr:housenumber":"3624",
    "addr:postcode":"98144",
    "addr:street":"Courtland Pl S",
    "iso:country":"US",
    "sg:address":"3624 Courtland Pl S",
    "sg:city":"Seattle",
    "sg:classifiers":[
        {
            "category":"Place Of Worship",
            "type":"Public Place"
        }
    ],
    "sg:phone":"+1 206 723 9333",
    "sg:postcode":"98144",
    "sg:province":"WA",
    "sg:tags":[
        "church"
    ],
    "wof:name":"Chu Yard Service",
    "wof:placetype":"venue"
},
  "geometry": {"coordinates":[-122.28722,47.571124],"type":"Point"}
}