{
  "type": "Feature",
  "properties": {
    "addr:full":"11421 164th St E Puyallup WA 98374",
    "addr:housenumber":"11421",
    "addr:postcode":"98374",
    "addr:street":"164Th St E",
    "iso:country":"US",
    "sg:address":"11421 164th St E",
    "sg:city":"Puyallup",
    "sg:classifiers":[
        {
            "category":"Building & Trades",
            "subcategory":"Construction",
            "type":"Services"
        }
    ],
    "sg:phone":"+1 253 845 4555",
    "sg:postcode":"98374",
    "sg:province":"WA",
    "sg:tags":[
        "concrete",
        "restoration",
        "cleaning",
        "repair"
    ],
    "wof:name":"National Grouting Systems",
    "wof:placetype":"venue"
},
  "geometry": {"coordinates":[-122.27500999999999,47.107452],"type":"Point"}
}