{
  "type": "Feature",
  "properties": {
    "addr:full":"5546 21st Ave S Seattle WA 98108",
    "addr:housenumber":"5546",
    "addr:postcode":"98108",
    "addr:street":"21St Ave S",
    "iso:country":"US",
    "sg:address":"5546 21st Ave S",
    "sg:city":"Seattle",
    "sg:classifiers":[
        {
            "category":"Shopping",
            "subcategory":"Crafts & Fabrics",
            "type":"Retail Goods"
        }
    ],
    "sg:phone":"+1 206 767 6451",
    "sg:postcode":"98108",
    "sg:province":"WA",
    "sg:tags":[
        "sewing"
    ],
    "wof:name":"Khamphong Khammixay",
    "wof:placetype":"venue"
},
  "geometry": {"coordinates":[-122.30617700000001,47.551479],"type":"Point"}
}