{
  "type": "Feature",
  "properties": {
    "addr:full":"3001 Bridgeport Way W University Place WA 98466",
    "addr:housenumber":"3001",
    "addr:postcode":"98466",
    "addr:street":"Bridgeport Way W;Place",
    "iso:country":"US",
    "sg:address":"3001 Bridgeport Way W",
    "sg:city":"University Place",
    "sg:classifiers":[
        {
            "category":"Professional",
            "subcategory":"Management & Consulting",
            "type":"Services"
        }
    ],
    "sg:phone":"+1 253 566 0995",
    "sg:postcode":"98466",
    "sg:province":"WA",
    "sg:tags":[
        "consultant"
    ],
    "wof:name":"Washington Environmental",
    "wof:placetype":"venue"
},
  "geometry": {"coordinates":[-122.537042,47.232624],"type":"Point"}
}