{
  "type": "Feature",
  "properties": {
    "addr:full":"6416 204th St SW Lynnwood WA 98036",
    "addr:housenumber":"6416",
    "addr:postcode":"98036",
    "addr:street":"204Th St Sw",
    "iso:country":"US",
    "sg:address":"6416 204th St SW",
    "sg:city":"Lynnwood",
    "sg:classifiers":[
        {
            "category":"Wholesale",
            "subcategory":"Groceries",
            "type":"Manufacturing & Wholesale Goods"
        }
    ],
    "sg:phone":"+1 425 774 9164",
    "sg:postcode":"98036",
    "sg:province":"WA",
    "sg:tags":[
        "p",
        "mfg"
    ],
    "wof:name":"Olson Baking Company The",
    "wof:placetype":"venue"
},
  "geometry": {"coordinates":[-122.32048500000001,47.81394],"type":"Point"}
}