{
  "type": "Feature",
  "properties": {
    "addr:full":"825 E Shorecrest Dr Oak Harbor WA 98277",
    "addr:housenumber":"825",
    "addr:postcode":"98277",
    "addr:street":"E Shorecrest Dr",
    "iso:country":"US",
    "sg:address":"825 E Shorecrest Dr",
    "sg:city":"Oak Harbor",
    "sg:classifiers":[
        {
            "category":"Wholesale",
            "subcategory":"Electrical",
            "type":"Manufacturing & Wholesale Goods"
        }
    ],
    "sg:phone":"+1 360 675 8992",
    "sg:postcode":"98277",
    "sg:province":"WA",
    "sg:tags":[
        "sound",
        "electronic",
        "video",
        "equipment"
    ],
    "wof:name":"Walters Jim Co",
    "wof:placetype":"venue"
},
  "geometry": {"coordinates":[-122.570227,48.348953],"type":"Point"}
}