{
  "type": "Feature",
  "properties": {
    "addr:full":"902 S Howard St Walla Walla WA 99362",
    "addr:housenumber":"902",
    "addr:postcode":"99362",
    "addr:street":"S Howard St",
    "iso:country":"US",
    "sg:address":"902 S Howard St",
    "sg:city":"Walla Walla",
    "sg:classifiers":[
        {
            "category":"Organizations",
            "subcategory":"Religious Organization",
            "type":"Services"
        }
    ],
    "sg:phone":"+1 509 529 5400",
    "sg:postcode":"99362",
    "sg:province":"WA",
    "wof:name":"Walla Walla Alliance Church",
    "wof:placetype":"venue"
},
  "geometry": {"coordinates":[-118.32522,46.060251],"type":"Point"}
}