{
  "type": "Feature",
  "properties": {
    "addr:full":"13031 8th Ave W Everett WA 98204",
    "addr:housenumber":"13031",
    "addr:postcode":"98204",
    "addr:street":"8Th Ave W",
    "iso:country":"US",
    "sg:address":"13031 8th Ave W",
    "sg:city":"Everett",
    "sg:classifiers":[
        {
            "category":"Real Estate",
            "subcategory":"Real Estate Operator",
            "type":"Services"
        }
    ],
    "sg:phone":"+1 425 347 0900",
    "sg:postcode":"98204",
    "sg:province":"WA",
    "sg:tags":[
        "building",
        "apartment"
    ],
    "wof:name":"Comble Hill Apartments",
    "wof:placetype":"venue"
},
  "geometry": {"coordinates":[-122.2441,47.879587],"type":"Point"}
}