{
  "type": "Feature",
  "properties": {
    "addr:full":"1005 N Fairgrounds Rd Goldendale WA 98620",
    "addr:housenumber":"1005",
    "addr:postcode":"98620",
    "addr:street":"N Fairgrounds Rd",
    "iso:country":"US",
    "sg:address":"1005 N Fairgrounds Rd",
    "sg:city":"Goldendale",
    "sg:classifiers":[
        {
            "category":"Airline",
            "type":"Transportation"
        }
    ],
    "sg:phone":"+1 509 773 9926",
    "sg:postcode":"98620",
    "sg:province":"WA",
    "sg:tags":[
        "airport"
    ],
    "wof:name":"Goldendale Airport",
    "wof:placetype":"venue"
},
  "geometry": {"coordinates":[-120.83860799999999,45.832543],"type":"Point"}
}