{
  "type": "Feature",
  "properties": {
    "addr:full":"7521 Bridgeport Way W Lakewood WA 98499",
    "addr:housenumber":"7521",
    "addr:postcode":"98499",
    "addr:street":"Bridgeport Way W",
    "iso:country":"US",
    "sg:address":"7521 Bridgeport Way W",
    "sg:city":"Lakewood",
    "sg:classifiers":[
        {
            "category":"Retail",
            "subcategory":"Auto Repair",
            "type":"Services"
        }
    ],
    "sg:phone":"+1 253 588 2700",
    "sg:postcode":"98499",
    "sg:province":"WA",
    "sg:tags":[
        "automotive",
        "glass",
        "replacement"
    ],
    "wof:name":"Lakewood City Glass",
    "wof:placetype":"venue"
},
  "geometry": {"coordinates":[-122.51830699999999,47.186625],"type":"Point"}
}