{
  "type": "Feature",
  "properties": {
    "addr:full":"400 Pine St Ste 042 Seattle WA 98101",
    "addr:housenumber":"400",
    "addr:postcode":"98101",
    "addr:street":"Pine St Ste 042",
    "iso:country":"US",
    "sg:address":"400 Pine St Ste 042",
    "sg:city":"Seattle",
    "sg:classifiers":[
        {
            "category":"Coffee & Tea",
            "type":"Food & Drink"
        }
    ],
    "sg:phone":"+1 206 652 0801",
    "sg:postcode":"98101",
    "sg:province":"WA",
    "sg:website":"www.starbucks.com",
    "wof:name":"Starbucks",
    "wof:placetype":"venue"
},
  "geometry": {"coordinates":[-122.337594,47.612376],"type":"Point"}
}