{
  "type": "Feature",
  "properties": {
    "addr:full":"6775 Guide Meridian Rd Lynden WA 98264",
    "addr:housenumber":"6775",
    "addr:postcode":"98264",
    "addr:street":"Guide Meridian Rd",
    "iso:country":"US",
    "sg:address":"6775 Guide Meridian Rd",
    "sg:city":"Lynden",
    "sg:classifiers":[
        {
            "category":"Wholesale",
            "subcategory":"Machinery & Supplies",
            "type":"Manufacturing & Wholesale Goods"
        }
    ],
    "sg:phone":"+1 360 398 7064",
    "sg:postcode":"98264",
    "sg:province":"WA",
    "sg:tags":[
        "contractor"
    ],
    "wof:name":"Midway Equipment Sales Inc",
    "wof:placetype":"venue"
},
  "geometry": {"coordinates":[-122.48574499999999,48.888896],"type":"Point"}
}