{
  "type": "Feature",
  "properties": {
    "addr:full":"755 Winslow Way E Ste 202 Bainbridge Island WA 98110",
    "addr:housenumber":"755",
    "addr:postcode":"98110",
    "addr:street":"Winslow Way E Ste 202",
    "iso:country":"US",
    "sg:address":"755 Winslow Way E Ste 202",
    "sg:city":"Bainbridge Island",
    "sg:classifiers":[
        {
            "category":"Real Estate",
            "subcategory":"Architect",
            "type":"Services"
        }
    ],
    "sg:phone":"+1 206 842 4993",
    "sg:postcode":"98110",
    "sg:province":"WA",
    "wof:name":"Briant & Associates Architects",
    "wof:placetype":"venue"
},
  "geometry": {"coordinates":[-122.511002,47.624901],"type":"Point"}
}