{
  "type": "Feature",
  "properties": {
    "addr:full":"2590 Ridgeview Dr Oak Harbor WA 98277",
    "addr:housenumber":"2590",
    "addr:postcode":"98277",
    "addr:street":"Ridgeview Dr",
    "iso:country":"US",
    "sg:address":"2590 Ridgeview Dr",
    "sg:city":"Oak Harbor",
    "sg:classifiers":[
        {
            "category":"Building & Trades",
            "subcategory":"Electrical",
            "type":"Services"
        }
    ],
    "sg:phone":"+1 360 675 8888",
    "sg:postcode":"98277",
    "sg:province":"WA",
    "sg:tags":[
        "electric",
        "contractor"
    ],
    "wof:name":"Skagit Island Electric Co",
    "wof:placetype":"venue"
},
  "geometry": {"coordinates":[-122.683617,48.302239],"type":"Point"}
}