{
  "type": "Feature",
  "properties": {
    "addr:full":"116 N Machias Rd Snohomish WA 98290",
    "addr:housenumber":"116",
    "addr:postcode":"98290",
    "addr:street":"N Machias Rd",
    "iso:country":"US",
    "sg:address":"116 N Machias Rd",
    "sg:city":"Snohomish",
    "sg:classifiers":[
        {
            "category":"Building & Trades",
            "subcategory":"Construction",
            "type":"Services"
        }
    ],
    "sg:phone":"+1 425 397 8631",
    "sg:postcode":"98290",
    "sg:province":"WA",
    "sg:tags":[
        "installation",
        "antenna",
        "contractor"
    ],
    "wof:name":"Antenna & Tower Resources",
    "wof:placetype":"venue"
},
  "geometry": {"coordinates":[-122.038842,48.000119],"type":"Point"}
}