{
  "type": "Feature",
  "properties": {
    "addr:full":"111 Queen Anne Ave N # 510 Seattle WA 98109",
    "addr:housenumber":"111",
    "addr:postcode":"98109",
    "addr:street":"Queen Anne Ave N # 510",
    "iso:country":"US",
    "sg:address":"111 Queen Anne Ave N # 510",
    "sg:city":"Seattle",
    "sg:classifiers":[
        {
            "category":"Real Estate",
            "subcategory":"Real Estate Services",
            "type":"Services"
        },
        {
            "category":"Real Estate",
            "subcategory":"Real Estate Agent",
            "type":"Services"
        }
    ],
    "sg:phone":"+1 206 285 1881",
    "sg:postcode":"98109",
    "sg:province":"WA",
    "sg:tags":[
        "buyer",
        "broker"
    ],
    "wof:name":"Williams Marketing, Inc.",
    "wof:placetype":"venue"
},
  "geometry": {"coordinates":[-122.356758,47.61872],"type":"Point"}
}