{
  "type": "Feature",
  "properties": {
    "addr:full":"7915 Greenwood Ave N Seattle WA 98103",
    "addr:housenumber":"7915",
    "addr:postcode":"98103",
    "addr:street":"Greenwood Ave N",
    "iso:country":"US",
    "sg:address":"7915 Greenwood Ave N",
    "sg:city":"Seattle",
    "sg:classifiers":[
        {
            "category":"Health Services",
            "subcategory":"Health Practitioner",
            "type":"Services"
        }
    ],
    "sg:phone":"+1 206 784 9977",
    "sg:postcode":"98103",
    "sg:province":"WA",
    "wof:name":"Jungian Psychotherapist Assoc",
    "wof:placetype":"venue"
},
  "geometry": {"coordinates":[-122.35537600000001,47.686836],"type":"Point"}
}