{
  "type": "Feature",
  "properties": {
    "addr:full":"12838 NE 94th St Kirkland WA 98033",
    "addr:housenumber":"12838",
    "addr:postcode":"98033",
    "addr:street":"Ne 94Th St",
    "iso:country":"US",
    "sg:address":"12838 NE 94th St",
    "sg:city":"Kirkland",
    "sg:classifiers":[
        {
            "category":"Personal",
            "type":"Services"
        }
    ],
    "sg:phone":"+1 425 828 4000",
    "sg:postcode":"98033",
    "sg:province":"WA",
    "wof:name":"Puget Sound Digital",
    "wof:placetype":"venue"
},
  "geometry": {"coordinates":[-122.168211,47.685305],"type":"Point"}
}