{
  "type": "Feature",
  "properties": {
    "iso:country":"US",
    "sg:address":"9321 Bayshore Dr NW",
    "sg:city":"Silverdale",
    "sg:classifiers":[
        {
            "category":"Real Estate",
            "subcategory":"Real Estate Services",
            "type":"Services"
        }
    ],
    "sg:phone":"+1 360 698 5020",
    "sg:postcode":"98383",
    "sg:province":"WA",
    "sg:tags":[
        "company",
        "title"
    ],
    "wof:name":"Kitsap County Title Agency",
    "wof:placetype":"venue"
},
  "geometry": {"coordinates":[-122.693455,47.648645],"type":"Point"}
}