{
  "type": "Feature",
  "properties": {
    "addr:full":"3510 Elm Rd Pasco WA 99301",
    "addr:housenumber":"3510",
    "addr:postcode":"99301",
    "addr:street":"Elm Rd",
    "iso:country":"US",
    "sg:address":"3510 Elm Rd",
    "sg:city":"Pasco",
    "sg:classifiers":[
        {
            "category":"Fast Food",
            "type":"Food & Drink"
        },
        {
            "category":"Restaurant",
            "type":"Food & Drink"
        }
    ],
    "sg:phone":"+1 509 266 4683",
    "sg:postcode":"99301",
    "sg:province":"WA",
    "sg:tags":[
        "take"
    ],
    "wof:name":"Ron's Original Kettle Korn",
    "wof:placetype":"venue"
},
  "geometry": {"coordinates":[-119.185875,46.430675],"type":"Point"}
}