{
  "type": "Feature",
  "properties": {
    "iso:country":"US",
    "sg:address":"16042 47th Ave S",
    "sg:city":"Seattle",
    "sg:classifiers":[
        {
            "category":"Retail",
            "subcategory":"Auto Repair",
            "type":"Services"
        }
    ],
    "sg:phone":"+1 206 988 0115",
    "sg:postcode":"98188",
    "sg:province":"WA",
    "sg:tags":[
        "automotive"
    ],
    "wof:name":"Tow Express Inc",
    "wof:placetype":"venue"
},
  "geometry": {"coordinates":[-122.274321,47.458273],"type":"Point"}
}