{
  "type": "Feature",
  "properties": {
    "addr:full":"2101 9th Ave Seattle WA 98121",
    "addr:housenumber":"2101",
    "addr:postcode":"98121",
    "addr:street":"9Th Ave",
    "iso:country":"US",
    "sg:address":"2101 9th Ave",
    "sg:city":"Seattle",
    "sg:classifiers":[
        {
            "category":"Home & Garden",
            "subcategory":"Building Materials",
            "type":"Retail Goods"
        }
    ],
    "sg:phone":"+1 206 343 9308",
    "sg:postcode":"98121",
    "sg:province":"WA",
    "sg:tags":[
        "equipment",
        "fixture",
        "lighting"
    ],
    "wof:name":"Resolute",
    "wof:placetype":"venue"
},
  "geometry": {"coordinates":[-122.33699799999999,47.617199],"type":"Point"}
}