{
  "type": "Feature",
  "properties": {
    "addr:full":"16419 261st Ave SE Issaquah WA 98027",
    "addr:housenumber":"16419",
    "addr:postcode":"98027",
    "addr:street":"261St Ave Se",
    "iso:country":"US",
    "sg:address":"16419 261st Ave SE",
    "sg:city":"Issaquah",
    "sg:phone":"+1 206 462 4519",
    "sg:postcode":"98027",
    "sg:province":"WA",
    "sg:website":"http://www.dawsonplumbing.com",
    "wof:name":"Dawson Plumbing Showroom",
    "wof:placetype":"venue"
},
  "geometry": {"coordinates":[-121.99241600000001,47.453509],"type":"Point"}
}