{
  "type": "Feature",
  "properties": {
    "iso:country":"US",
    "sg:address":"500 Metcalf St",
    "sg:city":"Sedro Woolley",
    "sg:classifiers":[
        {
            "category":"Home & Garden",
            "subcategory":"Furniture",
            "type":"Retail Goods"
        }
    ],
    "sg:phone":"+1 360 855 3376",
    "sg:postcode":"98284",
    "sg:province":"WA",
    "sg:tags":[
        "builder",
        "custom"
    ],
    "wof:name":"Norden Morrin",
    "wof:placetype":"venue"
},
  "geometry": {"coordinates":[-122.23857099999999,48.507495],"type":"Point"}
}