{
  "type": "Feature",
  "properties": {
    "iso:country":"US",
    "sg:address":"1836 Westlake Ave N",
    "sg:city":"Seattle",
    "sg:classifiers":[
        {
            "category":"Utilities",
            "subcategory":"Mobile Phone",
            "type":"Services"
        }
    ],
    "sg:phone":"+1 206 284 6260",
    "sg:postcode":"98109",
    "sg:province":"WA",
    "sg:tags":[
        "communication",
        "radiotelephone"
    ],
    "wof:name":"M V S U S A Inc",
    "wof:placetype":"venue"
},
  "geometry": {"coordinates":[-122.340344,47.634684],"type":"Point"}
}