{
  "type": "Feature",
  "properties": {
    "addr:full":"2151 S L St Tacoma WA 98405",
    "addr:housenumber":"2151",
    "addr:postcode":"98405",
    "addr:street":"S L St",
    "iso:country":"US",
    "sg:address":"2151 S L St",
    "sg:city":"Tacoma",
    "sg:classifiers":[
        {
            "category":"Professional",
            "type":"Services"
        }
    ],
    "sg:phone":"+1 253 272 0660",
    "sg:postcode":"98405",
    "sg:province":"WA",
    "wof:name":"Central Tacomacuts",
    "wof:placetype":"venue"
},
  "geometry": {"coordinates":[-122.450346,47.240026],"type":"Point"}
}