{
  "type": "Feature",
  "properties": {
    "addr:full":"3138 Overhulse Rd NW Olympia WA 98502",
    "addr:housenumber":"3138",
    "addr:postcode":"olympia wa 98502",
    "addr:street":"Overhulse Rd Nw",
    "iso:country":"US",
    "sg:address":"3138 Overhulse Rd NW",
    "sg:city":"Olympia",
    "sg:classifiers":[
        {
            "category":"Professional",
            "type":"Services"
        }
    ],
    "sg:phone":"+1 360 866 7332",
    "sg:postcode":"98502",
    "sg:province":"WA",
    "wof:name":"Water Dragon Adventures",
    "wof:placetype":"venue"
},
  "geometry": {"coordinates":[-122.970446,47.077538],"type":"Point"}
}