{
  "type": "Feature",
  "properties": {
    "addr:full":"205 N 22nd Ave Yakima WA 98902",
    "addr:housenumber":"205",
    "addr:postcode":"98902",
    "addr:street":"N 22Nd Ave",
    "iso:country":"US",
    "sg:address":"205 N 22nd Ave",
    "sg:city":"Yakima",
    "sg:classifiers":[
        {
            "category":"Manufacturing",
            "subcategory":"Retail Goods",
            "type":"Manufacturing & Wholesale Goods"
        }
    ],
    "sg:phone":"+1 509 248 8340",
    "sg:postcode":"98902",
    "sg:province":"WA",
    "sg:tags":[
        "product",
        "mfg"
    ],
    "wof:name":"Ginnys",
    "wof:placetype":"venue"
},
  "geometry": {"coordinates":[-120.538112,46.602456],"type":"Point"}
}