{
  "type": "Feature",
  "properties": {
    "addr:full":"2322 Tacoma Rd E Puyallup WA 98371",
    "addr:housenumber":"2322",
    "addr:postcode":"98371",
    "addr:street":"Tacoma Rd E",
    "iso:country":"US",
    "sg:address":"2322 Tacoma Rd E",
    "sg:city":"Puyallup",
    "sg:classifiers":[
        {
            "category":"Building & Trades",
            "subcategory":"Landscaping Services",
            "type":"Services"
        }
    ],
    "sg:phone":"+1 253 845 8080",
    "sg:postcode":"98371",
    "sg:province":"WA",
    "wof:name":"G&G Cleaning & Lawn Care Servi",
    "wof:placetype":"venue"
},
  "geometry": {"coordinates":[-122.326564,47.195652],"type":"Point"}
}