{
  "type": "Feature",
  "properties": {
    "iso:country":"US",
    "sg:address":"8201 E Sprague Ave",
    "sg:city":"Spokane Valley",
    "sg:classifiers":[
        {
            "category":"Autos & Motor Vehicles",
            "subcategory":"Automobile Sales",
            "type":"Retail Goods"
        }
    ],
    "sg:phone":"+1 509 927 7000",
    "sg:postcode":"99212",
    "sg:province":"WA",
    "sg:tags":[
        "car",
        "dealer"
    ],
    "sg:website":"www.hondaofspokane.com",
    "wof:name":"Honda Of Spokane",
    "wof:placetype":"venue"
},
  "geometry": {"coordinates":[-117.292119,47.656924],"type":"Point"}
}