{
  "type": "Feature",
  "properties": {
    "addr:full":"11805 NE 99th St Vancouver WA 98682",
    "addr:housenumber":"11805",
    "addr:postcode":"98682",
    "addr:street":"Ne 99Th St",
    "iso:country":"US",
    "sg:address":"11805 NE 99th St",
    "sg:city":"Vancouver",
    "sg:classifiers":[
        {
            "category":"Professional",
            "subcategory":"Detective & Security Services",
            "type":"Services"
        }
    ],
    "sg:phone":"+1 360 253 4151",
    "sg:postcode":"98682",
    "sg:province":"WA",
    "sg:tags":[
        "investigator"
    ],
    "sg:website":"www.marosi.com",
    "wof:name":"BRI Group/Marosi Group",
    "wof:placetype":"venue"
},
  "geometry": {"coordinates":[-122.552516,45.693352],"type":"Point"}
}