{
  "type": "Feature",
  "properties": {
    "addr:full":"11614 Ambaum Boulevard SW Burien WA 98146",
    "addr:housenumber":"11614",
    "addr:postcode":"98146",
    "addr:street":"Ambaum Boulevard Sw",
    "iso:country":"US",
    "sg:address":"11614 Ambaum Boulevard SW",
    "sg:city":"Burien",
    "sg:classifiers":[
        {
            "category":"Professional",
            "type":"Services"
        },
        {
            "category":"Restaurant",
            "type":"Food & Drink"
        }
    ],
    "sg:phone":"+1 206 444 5141",
    "sg:postcode":"98146",
    "sg:province":"WA",
    "sg:tags":[
        "barbeque",
        "caterer"
    ],
    "sg:website":"www.berrysbbq.com",
    "wof:name":"Berry's Bbq",
    "wof:placetype":"venue"
},
  "geometry": {"coordinates":[-122.354885,47.498953],"type":"Point"}
}