{
  "type": "Feature",
  "properties": {
    "addr:full":"4924 W Staley Rd Deer Park WA 99006",
    "addr:housenumber":"4924",
    "addr:postcode":"99006",
    "addr:street":"W Staley Rd",
    "iso:country":"US",
    "sg:address":"4924 W Staley Rd",
    "sg:city":"Deer Park",
    "sg:classifiers":[
        {
            "category":"Wholesale",
            "subcategory":"Scrap",
            "type":"Manufacturing & Wholesale Goods"
        }
    ],
    "sg:phone":"+1 509 276 8490",
    "sg:postcode":"99006",
    "sg:province":"WA",
    "sg:tags":[
        "material"
    ],
    "wof:name":"R&J Technical Services",
    "wof:placetype":"venue"
},
  "geometry": {"coordinates":[-117.48555,47.903475],"type":"Point"}
}