{
  "type": "Feature",
  "properties": {
    "addr:full":"990 E Washington St Sequim WA 98382",
    "addr:housenumber":"990",
    "addr:postcode":"98382",
    "addr:street":"E Washington St",
    "iso:country":"US",
    "sg:address":"990 E Washington St",
    "sg:city":"Sequim",
    "sg:classifiers":[
        {
            "category":"Wholesale",
            "subcategory":"Home Furnishings",
            "type":"Manufacturing & Wholesale Goods"
        }
    ],
    "sg:phone":"+1 360 681 4925",
    "sg:postcode":"98382",
    "sg:province":"WA",
    "sg:tags":[
        "closet",
        "accessory"
    ],
    "wof:name":"Stick Stash Stow Inc",
    "wof:placetype":"venue"
},
  "geometry": {"coordinates":[-123.086299,48.076118],"type":"Point"}
}