{
  "type": "Feature",
  "properties": {
    "addr:full":"7213 265th St NW Stanwood WA 98292",
    "addr:housenumber":"7213",
    "addr:postcode":"98292",
    "addr:street":"265Th St Nw",
    "iso:country":"US",
    "sg:address":"7213 265th St NW",
    "sg:city":"Stanwood",
    "sg:classifiers":[
        {
            "category":"Sports & Exercise",
            "subcategory":"Gym",
            "type":"Entertainment"
        }
    ],
    "sg:phone":"+1 360 629 5433",
    "sg:postcode":"98292",
    "sg:province":"WA",
    "sg:tags":[
        "club",
        "health",
        "studio",
        "gymnasium"
    ],
    "wof:name":"Sports Club",
    "wof:placetype":"venue"
},
  "geometry": {"coordinates":[-122.33177000000001,48.23715],"type":"Point"}
}