{
  "type": "Feature",
  "properties": {
    "addr:full":"4330 Samish Way Bellingham WA 98229",
    "addr:postcode":"4330;98229",
    "addr:street":"Samish Way",
    "iso:country":"US",
    "sg:address":"4330 Samish Way",
    "sg:city":"Bellingham",
    "sg:classifiers":[
        {
            "category":"Professional",
            "type":"Services"
        }
    ],
    "sg:phone":"+1 360 733 1620",
    "sg:postcode":"98229",
    "sg:province":"WA",
    "wof:name":"Peter M Arm",
    "wof:placetype":"venue"
},
  "geometry": {"coordinates":[-122.459419,48.707074],"type":"Point"}
}