{
  "type": "Feature",
  "properties": {
    "addr:full":"4619 14th Avenue SW Seattle WA 98106",
    "addr:housenumber":"4619",
    "addr:postcode":"98106",
    "addr:street":"14Th Avenue Sw",
    "iso:country":"US",
    "sg:address":"4619 14th Avenue SW",
    "sg:city":"Seattle",
    "sg:classifiers":[
        {
            "category":"Sports & Exercise",
            "subcategory":"Ice Rink",
            "type":"Entertainment"
        }
    ],
    "sg:phone":"+1 206 932 6414",
    "sg:postcode":"98106",
    "sg:province":"WA",
    "sg:tags":[
        "skating"
    ],
    "sg:website":"www.grindline.com",
    "wof:name":"Grindline",
    "wof:placetype":"venue"
},
  "geometry": {"coordinates":[-122.35367599999999,47.561573],"type":"Point"}
}