{
  "type": "Feature",
  "properties": {
    "addr:full":"1 Bellis Fair Pkwy Bellingham WA 98226",
    "addr:housenumber":"1",
    "addr:postcode":"98226",
    "addr:street":"Bellis Fair Pkwy",
    "iso:country":"US",
    "sg:address":"1 Bellis Fair Pkwy",
    "sg:city":"Bellingham",
    "sg:classifiers":[
        {
            "category":"Bakery",
            "type":"Food & Drink"
        }
    ],
    "sg:menulink":"http://www.allmenus.com/wa/bellingham/220328-auntie-annes-pretzels/menu/",
    "sg:phone":"+1 360 714 8258",
    "sg:postcode":"98226",
    "sg:province":"WA",
    "sg:tags":[
        "american",
        "pastry"
    ],
    "wof:name":"Auntie Anne's Pretzels",
    "wof:placetype":"venue"
},
  "geometry": {"coordinates":[-122.48625,48.784344],"type":"Point"}
}