{
  "type": "Feature",
  "properties": {
    "addr:full":"525 E 8th St Port Angeles WA 98362",
    "addr:housenumber":"525",
    "addr:postcode":"98362",
    "addr:street":"E 8Th St",
    "iso:country":"US",
    "sg:address":"525 E 8th St",
    "sg:city":"Port Angeles",
    "sg:classifiers":[
        {
            "category":"Personal",
            "subcategory":"Beauty Salon",
            "type":"Services"
        }
    ],
    "sg:phone":"+1 360 417 0800",
    "sg:postcode":"98362",
    "sg:province":"WA",
    "sg:tags":[
        "shop"
    ],
    "wof:name":"Sassy Cat Salon Inc",
    "wof:placetype":"venue"
},
  "geometry": {"coordinates":[-123.431236,48.109835],"type":"Point"}
}