{
  "type": "Feature",
  "properties": {
    "addr:full":"18289 Olympic Ave S Seattle WA 98188",
    "addr:housenumber":"18289",
    "addr:postcode":"98188",
    "addr:street":"Olympic Ave S",
    "iso:country":"US",
    "sg:address":"18289 Olympic Ave S",
    "sg:city":"Seattle",
    "sg:classifiers":[
        {
            "category":"Wholesale",
            "subcategory":"Groceries",
            "type":"Manufacturing & Wholesale Goods"
        }
    ],
    "sg:phone":"+1 425 656 7863",
    "sg:postcode":"98188",
    "sg:province":"WA",
    "sg:tags":[
        "distributor",
        "energy",
        "drink"
    ],
    "wof:name":"3d Distribution LLC",
    "wof:placetype":"venue"
},
  "geometry": {"coordinates":[-122.25175400000001,47.436885],"type":"Point"}
}