{
  "type": "Feature",
  "properties": {
    "addr:full":"815 Plymouth St SW Olympia WA 98502",
    "addr:housenumber":"815",
    "addr:postcode":"98502",
    "addr:street":"Plymouth St Sw",
    "iso:country":"US",
    "sg:address":"815 Plymouth St SW",
    "sg:city":"Olympia",
    "sg:classifiers":[
        {
            "category":"Professional",
            "subcategory":"Computer Services",
            "type":"Services"
        }
    ],
    "sg:phone":"+1 360 357 6291",
    "sg:postcode":"98502",
    "sg:province":"WA",
    "sg:tags":[
        "related"
    ],
    "wof:name":"Turningmoon",
    "wof:placetype":"venue"
},
  "geometry": {"coordinates":[-122.91950300000001,47.040691],"type":"Point"}
}