{
  "type": "Feature",
  "properties": {
    "addr:full":"2521 River Rd Yakima WA 98902",
    "addr:housenumber":"2521",
    "addr:postcode":"98902",
    "addr:street":"River Rd",
    "iso:country":"US",
    "sg:address":"2521 River Rd",
    "sg:city":"Yakima",
    "sg:classifiers":[
        {
            "category":"Wholesale",
            "subcategory":"Machinery & Supplies",
            "type":"Manufacturing & Wholesale Goods"
        }
    ],
    "sg:phone":"+1 509 453 8271",
    "sg:postcode":"98902",
    "sg:province":"WA",
    "sg:tags":[
        "farm",
        "equipment"
    ],
    "wof:name":"Rankin Equipment Co",
    "wof:placetype":"venue"
},
  "geometry": {"coordinates":[-120.543237,46.618055],"type":"Point"}
}