{
  "type": "Feature",
  "properties": {
    "addr:full":"9809 38th Ave NE Seattle WA 98115",
    "addr:housenumber":"9809",
    "addr:postcode":"98115",
    "addr:street":"38Th Ave Ne",
    "iso:country":"US",
    "sg:address":"9809 38th Ave NE",
    "sg:city":"Seattle",
    "sg:classifiers":[
        {
            "category":"Professional",
            "subcategory":"Business Services",
            "type":"Services"
        }
    ],
    "sg:phone":"+1 206 525 5090",
    "sg:postcode":"98115",
    "sg:province":"WA",
    "wof:name":"Seattle Product Design",
    "wof:placetype":"venue"
},
  "geometry": {"coordinates":[-122.288115,47.701055],"type":"Point"}
}