{
  "type": "Feature",
  "properties": {
    "addr:full":"1224 N Clinton St Walla Walla WA 99362",
    "addr:housenumber":"1224",
    "addr:postcode":"99362",
    "addr:street":"N Clinton St",
    "iso:country":"US",
    "sg:address":"1224 N Clinton St",
    "sg:city":"Walla Walla",
    "sg:classifiers":[
        {
            "category":"Social Services",
            "type":"Services"
        }
    ],
    "sg:phone":"+1 509 522 2797",
    "sg:postcode":"99362",
    "sg:province":"WA",
    "wof:name":"Ralston Family Homes",
    "wof:placetype":"venue"
},
  "geometry": {"coordinates":[-118.32537000000001,46.079377],"type":"Point"}
}