{
  "type": "Feature",
  "properties": {
    "addr:full":"3507 S Caballo Rd Kennewick WA 99338",
    "addr:housenumber":"3507",
    "addr:postcode":"99338",
    "addr:street":"S Caballo Rd",
    "iso:country":"US",
    "sg:address":"3507 S Caballo Rd",
    "sg:city":"Kennewick",
    "sg:classifiers":[
        {
            "category":"Building & Trades",
            "subcategory":"Electrical",
            "type":"Services"
        }
    ],
    "sg:phone":"+1 509 627 2581",
    "sg:postcode":"99338",
    "sg:province":"WA",
    "sg:tags":[
        "electrical",
        "contractor"
    ],
    "wof:name":"Nipper Electric",
    "wof:placetype":"venue"
},
  "geometry": {"coordinates":[-119.292828,46.206076],"type":"Point"}
}