{
  "type": "Feature",
  "properties": {
    "addr:full":"2100 Hillyard Dr Clarkston WA 99403",
    "addr:postcode":"2100;99403",
    "addr:street":"Hillyard Dr",
    "iso:country":"US",
    "sg:address":"2100 Hillyard Dr",
    "sg:city":"Clarkston",
    "sg:classifiers":[
        {
            "category":"Freight",
            "type":"Transportation"
        }
    ],
    "sg:phone":"+1 509 979 0795",
    "sg:postcode":"99403",
    "sg:province":"WA",
    "sg:tags":[
        "delivery",
        "package"
    ],
    "wof:name":"Pacific Northwest Express Inc",
    "wof:placetype":"venue"
},
  "geometry": {"coordinates":[-117.05359,46.39029],"type":"Point"}
}