{
  "type": "Feature",
  "properties": {
    "iso:country":"US",
    "sg:address":"9060 Wyvern Dr SE",
    "sg:city":"Port Orchard",
    "sg:classifiers":[
        {
            "category":"Manufacturing",
            "subcategory":"Retail Goods",
            "type":"Manufacturing & Wholesale Goods"
        }
    ],
    "sg:phone":"+1 253 857 6215",
    "sg:postcode":"98367",
    "sg:province":"WA",
    "sg:tags":[
        "product",
        "mfg"
    ],
    "wof:name":"Alm Industries",
    "wof:placetype":"venue"
},
  "geometry": {"coordinates":[-122.580251,47.467929],"type":"Point"}
}