{
  "type": "Feature",
  "properties": {
    "addr:full":"325 112th St SW Everett WA 98204",
    "addr:housenumber":"325",
    "addr:postcode":"98204",
    "addr:street":"112Th St Sw",
    "iso:country":"US",
    "sg:address":"325 112th St SW",
    "sg:city":"Everett",
    "sg:classifiers":[
        {
            "category":"Food & Beverages",
            "subcategory":"Groceries & Convenience Stores",
            "type":"Retail Goods"
        }
    ],
    "sg:phone":"+1 425 353 5637",
    "sg:postcode":"98204",
    "sg:province":"WA",
    "wof:name":"Jackpot Food Mart",
    "wof:placetype":"venue"
},
  "geometry": {"coordinates":[-122.2379,47.896468],"type":"Point"}
}