{
  "type": "Feature",
  "properties": {
    "addr:full":"1325 4th Ave Lbby Seattle WA 98101",
    "addr:housenumber":"1325",
    "addr:postcode":"98101",
    "addr:street":"4Th Ave",
    "iso:country":"US",
    "sg:address":"1325 4th Ave Lbby",
    "sg:city":"Seattle",
    "sg:classifiers":[
        {
            "category":"Professional",
            "subcategory":"Lawyer & Legal Services",
            "type":"Services"
        }
    ],
    "sg:phone":"+1 206 467 6477",
    "sg:postcode":"98101",
    "sg:province":"WA",
    "wof:name":"Gordon Charles C Atty",
    "wof:placetype":"venue"
},
  "geometry": {"coordinates":[-122.334999,47.608601],"type":"Point"}
}