{
  "type": "Feature",
  "properties": {
    "addr:full":"1110 Hewitt Ave Everett WA 98201",
    "addr:housenumber":"1110",
    "addr:postcode":"98201",
    "addr:street":"Hewitt Ave",
    "iso:country":"US",
    "sg:address":"1110 Hewitt Ave",
    "sg:city":"Everett",
    "sg:classifiers":[
        {
            "category":"Professional",
            "subcategory":"Employment Agencies",
            "type":"Services"
        }
    ],
    "sg:phone":"+1 425 259 8193",
    "sg:postcode":"98201",
    "sg:province":"WA",
    "sg:tags":[
        "contractor"
    ],
    "wof:name":"Stevedoring Services-America",
    "wof:placetype":"venue"
},
  "geometry": {"coordinates":[-122.214415,47.979279],"type":"Point"}
}