{
  "type": "Feature",
  "properties": {
    "addr:full":"1300 SE 181st Ave Vancouver WA 98683",
    "addr:housenumber":"1300",
    "addr:postcode":"98683",
    "addr:street":"Se 181St Ave",
    "iso:country":"US",
    "sg:address":"1300 SE 181st Ave",
    "sg:city":"Vancouver",
    "sg:classifiers":[
        {
            "category":"Professional",
            "subcategory":"Business Services",
            "type":"Services"
        }
    ],
    "sg:phone":"+1 360 891 2903",
    "sg:postcode":"98683",
    "sg:province":"WA",
    "wof:name":"21 Wayz Productions LLC",
    "wof:placetype":"venue"
},
  "geometry": {"coordinates":[-122.487257,45.611673],"type":"Point"}
}