{
  "type": "Feature",
  "properties": {
    "iso:country":"US",
    "sg:address":"4916 Center St",
    "sg:city":"Tacoma",
    "sg:classifiers":[
        {
            "category":"Social Services",
            "type":"Services"
        }
    ],
    "sg:phone":"+1 253 460 6711",
    "sg:postcode":"98409",
    "sg:province":"WA",
    "sg:tags":[
        "organization",
        "welfare"
    ],
    "wof:name":"Toy Rescue Mission",
    "wof:placetype":"venue"
},
  "geometry": {"coordinates":[-122.505042,47.234339],"type":"Point"}
}