{
  "type": "Feature",
  "properties": {
    "iso:country":"US",
    "sg:address":"324 19th Ave",
    "sg:city":"Kirkland",
    "sg:classifiers":[
        {
            "category":"Professional",
            "subcategory":"Business Services",
            "type":"Services"
        }
    ],
    "sg:phone":"+1 425 828 8559",
    "sg:postcode":"98033",
    "sg:province":"WA",
    "wof:name":"Deborah Eliasen Design",
    "wof:placetype":"venue"
},
  "geometry": {"coordinates":[-122.20380900000001,47.691533],"type":"Point"}
}