{
  "type": "Feature",
  "properties": {
    "addr:full":"16623 Columbia Ave SW Vashon WA 98070",
    "addr:housenumber":"16623",
    "addr:postcode":"98070",
    "addr:street":"Columbia Ave Sw",
    "iso:country":"US",
    "sg:address":"16623 Columbia Ave SW",
    "sg:city":"Vashon",
    "sg:classifiers":[
        {
            "category":"Manufacturing",
            "subcategory":"Lumber",
            "type":"Manufacturing & Wholesale Goods"
        }
    ],
    "sg:phone":"+1 206 463 3014",
    "sg:postcode":"98070",
    "sg:province":"WA",
    "sg:tags":[
        "mill"
    ],
    "wof:name":"Blakes Sawmilling & Service",
    "wof:placetype":"venue"
},
  "geometry": {"coordinates":[-122.495222,47.456831],"type":"Point"}
}