{
  "type": "Feature",
  "properties": {
    "addr:full":"9368 NE Eglon Rd Kingston WA 98346",
    "addr:housenumber":"9368",
    "addr:postcode":"98346",
    "addr:street":"Ne Eglon Rd",
    "iso:country":"US",
    "sg:address":"9368 NE Eglon Rd",
    "sg:city":"Kingston",
    "sg:classifiers":[
        {
            "category":"Manufacturing",
            "subcategory":"Metals",
            "type":"Manufacturing & Wholesale Goods"
        }
    ],
    "sg:phone":"+1 360 638 0101",
    "sg:postcode":"98346",
    "sg:province":"WA",
    "sg:tags":[
        "metalwork",
        "architectural",
        "mfg"
    ],
    "wof:name":"Scorpion Iron Works",
    "wof:placetype":"venue"
},
  "geometry": {"coordinates":[-122.52432899999999,47.871135],"type":"Point"}
}