{
  "type": "Feature",
  "properties": {
    "iso:country":"US",
    "sg:address":"1101 NE Boat St",
    "sg:city":"Seattle",
    "sg:classifiers":[
        {
            "category":"Recreation",
            "subcategory":"Marina",
            "type":"Entertainment"
        }
    ],
    "sg:phone":"+1 206 381 9357",
    "sg:postcode":"98105",
    "sg:province":"WA",
    "sg:tags":[
        "operation"
    ],
    "wof:name":"Boat Street Marina",
    "wof:placetype":"venue"
},
  "geometry": {"coordinates":[-122.314536,47.651807],"type":"Point"}
}