{
  "type": "Feature",
  "properties": {
    "addr:full":"1001 W Howe St Seattle WA 98119",
    "addr:housenumber":"1001",
    "addr:postcode":"98119",
    "addr:street":"W Howe St",
    "iso:country":"US",
    "sg:address":"1001 W Howe St",
    "sg:city":"Seattle",
    "sg:classifiers":[
        {
            "category":"Sports & Exercise",
            "subcategory":"Gym",
            "type":"Entertainment"
        }
    ],
    "sg:phone":"+1 206 282 2504",
    "sg:postcode":"98119",
    "sg:province":"WA",
    "sg:tags":[
        "equipment",
        "pilate",
        "instruction"
    ],
    "sg:website":"www.youngpilates.com",
    "wof:name":"Young Pilates And Fitness",
    "wof:placetype":"venue"
},
  "geometry": {"coordinates":[-122.370637,47.635736],"type":"Point"}
}