{
  "type": "Feature",
  "properties": {
    "addr:full":"102 S 26th St Tacoma WA 98402",
    "addr:housenumber":"102",
    "addr:postcode":"98402",
    "addr:street":"S 26Th St",
    "iso:country":"US",
    "sg:address":"102 S 26th St",
    "sg:city":"Tacoma",
    "sg:classifiers":[
        {
            "category":"Real Estate",
            "subcategory":"Architect",
            "type":"Services"
        }
    ],
    "sg:phone":"+1 253 284 3101",
    "sg:postcode":"98402",
    "sg:province":"WA",
    "sg:tags":[
        "home",
        "planning",
        "design"
    ],
    "wof:name":"Northwest Architectural",
    "wof:placetype":"venue"
},
  "geometry": {"coordinates":[-122.43510000000001,47.237918],"type":"Point"}
}