{
  "type": "Feature",
  "properties": {
    "addr:full":"1212 Jefferson St SE Olympia WA 98501",
    "addr:housenumber":"1212",
    "addr:postcode":"98501",
    "addr:street":"Jefferson St Se",
    "iso:country":"US",
    "sg:address":"1212 Jefferson St SE",
    "sg:city":"Olympia",
    "sg:classifiers":[
        {
            "category":"Professional",
            "subcategory":"Lawyer & Legal Services",
            "type":"Services"
        }
    ],
    "sg:phone":"+1 360 357 6799",
    "sg:postcode":"98501",
    "sg:province":"WA",
    "wof:name":"Jamie M Moore Attorney",
    "wof:placetype":"venue"
},
  "geometry": {"coordinates":[-122.895839,47.037227],"type":"Point"}
}