{
  "type": "Feature",
  "properties": {
    "addr:full":"260 Pillsbury Rd Mesa WA 99343",
    "addr:housenumber":"260",
    "addr:postcode":"99343",
    "addr:street":"Pillsbury Rd",
    "iso:country":"US",
    "sg:address":"260 Pillsbury Rd",
    "sg:city":"Mesa",
    "sg:classifiers":[
        {
            "category":"Wholesale",
            "subcategory":"Farm Supplies",
            "type":"Manufacturing & Wholesale Goods"
        }
    ],
    "sg:phone":"+1 509 269 9218",
    "sg:postcode":"99343",
    "sg:province":"WA",
    "wof:name":"Washington Producers Inc",
    "wof:placetype":"venue"
},
  "geometry": {"coordinates":[-119.13884400000001,46.591642],"type":"Point"}
}