{
  "type": "Feature",
  "properties": {
    "addr:full":"817 N Trafton St Tacoma WA 98403",
    "addr:housenumber":"817",
    "addr:postcode":"98403",
    "addr:street":"N Trafton St",
    "iso:country":"US",
    "sg:address":"817 N Trafton St",
    "sg:city":"Tacoma",
    "sg:classifiers":[
        {
            "category":"Organizations",
            "subcategory":"Religious Organization",
            "type":"Services"
        }
    ],
    "sg:phone":"+1 253 272 8632",
    "sg:postcode":"98403",
    "sg:province":"WA",
    "wof:name":"Gods Little Chapel",
    "wof:placetype":"venue"
},
  "geometry": {"coordinates":[-122.46688,47.257863],"type":"Point"}
}