{
  "type": "Feature",
  "properties": {
    "addr:full":"15621 3rd Ave SE Bothell WA 98012",
    "addr:housenumber":"15621",
    "addr:postcode":"98012",
    "addr:street":"3Rd Ave Se",
    "iso:country":"US",
    "sg:address":"15621 3rd Ave SE",
    "sg:city":"Bothell",
    "sg:classifiers":[
        {
            "category":"Building & Trades",
            "subcategory":"Construction",
            "type":"Services"
        }
    ],
    "sg:phone":"+1 425 743 9679",
    "sg:postcode":"98012",
    "sg:province":"WA",
    "sg:tags":[
        "contractor"
    ],
    "wof:name":"Himple Drywall",
    "wof:placetype":"venue"
},
  "geometry": {"coordinates":[-122.227788,47.854681],"type":"Point"}
}