{
  "type": "Feature",
  "properties": {
    "addr:full":"1515 116th Ave NE Ste 101 Bellevue WA 98004",
    "addr:housenumber":"1515",
    "addr:postcode":"98004",
    "addr:street":"116Th Ave Ne Ste 101",
    "iso:country":"US",
    "sg:address":"1515 116th Ave NE Ste 101",
    "sg:city":"Bellevue",
    "sg:classifiers":[
        {
            "category":"Health Services",
            "subcategory":"Doctor",
            "type":"Services"
        }
    ],
    "sg:phone":"+1 425 455 8888",
    "sg:postcode":"98004",
    "sg:province":"WA",
    "wof:name":"Kim Young Min",
    "wof:placetype":"venue"
},
  "geometry": {"coordinates":[-122.18589799999999,47.624749],"type":"Point"}
}