{
  "type": "Feature",
  "properties": {
    "addr:full":"200 N Chelan Ave Wenatchee WA 98801",
    "addr:housenumber":"200",
    "addr:postcode":"98801",
    "addr:street":"N Chelan Ave",
    "iso:country":"US",
    "sg:address":"200 N Chelan Ave",
    "sg:city":"Wenatchee",
    "sg:classifiers":[
        {
            "category":"Government",
            "subcategory":"Office",
            "type":"Public Place"
        }
    ],
    "sg:phone":"+1 509 667 6200",
    "sg:postcode":"98801",
    "sg:province":"WA",
    "sg:tags":[
        "county",
        "resource"
    ],
    "wof:name":"Chelan County Child Support",
    "wof:placetype":"venue"
},
  "geometry": {"coordinates":[-120.315943,47.426254],"type":"Point"}
}