{
  "type": "Feature",
  "properties": {
    "addr:full":"7216 Aurora Ave N Seattle WA 98103",
    "addr:housenumber":"7216",
    "addr:postcode":"98103",
    "addr:street":"Aurora Ave N",
    "iso:country":"US",
    "sg:address":"7216 Aurora Ave N",
    "sg:city":"Seattle",
    "sg:classifiers":[
        {
            "category":"Personal",
            "subcategory":"Beauty Salon",
            "type":"Services"
        }
    ],
    "sg:phone":"+1 206 364 5500",
    "sg:postcode":"98103",
    "sg:province":"WA",
    "sg:tags":[
        "hair"
    ],
    "sg:website":"www.salonlotusstyle.com",
    "wof:name":"Salon Lotus",
    "wof:placetype":"venue"
},
  "geometry": {"coordinates":[-122.34439999999999,47.681452],"type":"Point"}
}