{
  "type": "Feature",
  "properties": {
    "iso:country":"US",
    "sg:address":"20211 S St",
    "sg:city":"Ocean Park",
    "sg:classifiers":[
        {
            "category":"Shopping",
            "subcategory":"Jewelry",
            "type":"Retail Goods"
        }
    ],
    "sg:phone":"+1 360 665 6391",
    "sg:postcode":"98640",
    "sg:province":"WA",
    "wof:name":"Charmee Dingles",
    "wof:placetype":"venue"
},
  "geometry": {"coordinates":[-124.04759799999999,46.44808],"type":"Point"}
}