{
  "type": "Feature",
  "properties": {
    "addr:full":"502 S 2nd St Yakima WA 98901",
    "addr:housenumber":"502",
    "addr:postcode":"98901",
    "addr:street":"S 2Nd St",
    "iso:country":"US",
    "sg:address":"502 S 2nd St",
    "sg:city":"Yakima",
    "sg:classifiers":[
        {
            "category":"Building & Trades",
            "subcategory":"Construction",
            "type":"Services"
        }
    ],
    "sg:phone":"+1 509 945 0249",
    "sg:postcode":"98901",
    "sg:province":"WA",
    "sg:tags":[
        "general",
        "contractor"
    ],
    "wof:name":"Sal Marquez Construction",
    "wof:placetype":"venue"
},
  "geometry": {"coordinates":[-120.501024,46.595063],"type":"Point"}
}