{
  "type": "Feature",
  "properties": {
    "addr:full":"981 E Birch Ave Colville WA 99114",
    "addr:housenumber":"981",
    "addr:postcode":"99114",
    "addr:street":"E Birch Ave",
    "iso:country":"US",
    "sg:address":"981 E Birch Ave",
    "sg:city":"Colville",
    "sg:classifiers":[
        {
            "category":"Professional",
            "subcategory":"Accounting & Tax Preparation",
            "type":"Services"
        }
    ],
    "sg:phone":"+1 509 684 4647",
    "sg:postcode":"99114",
    "sg:province":"WA",
    "sg:tags":[
        "accountant"
    ],
    "wof:name":"Jack Droter Tax & Accounting",
    "wof:placetype":"venue"
},
  "geometry": {"coordinates":[-117.891547,48.542397],"type":"Point"}
}