{
  "type": "Feature",
  "properties": {
    "addr:full":"5141 Capitol Blvd S Olympia WA 98501",
    "addr:housenumber":"5141",
    "addr:postcode":"98501",
    "addr:street":"Capitol Blvd S",
    "iso:country":"US",
    "sg:address":"5141 Capitol Blvd S",
    "sg:city":"Olympia",
    "sg:classifiers":[
        {
            "category":"Retail",
            "subcategory":"Laundry & Dry Cleaning",
            "type":"Services"
        }
    ],
    "sg:phone":"+1 360 943 5819",
    "sg:postcode":"98501",
    "sg:province":"WA",
    "sg:tags":[
        "cleaners"
    ],
    "wof:name":"Southgate Clrs SLF-Srvice Ldry",
    "wof:placetype":"venue"
},
  "geometry": {"coordinates":[-122.908869,46.999978],"type":"Point"}
}