{
  "type": "Feature",
  "properties": {
    "addr:full":"1377 W State Road 4 Skamokawa WA 98647",
    "addr:housenumber":"1377",
    "addr:postcode":"98647",
    "addr:street":"W State Road 4",
    "iso:country":"US",
    "sg:address":"1377 W State Road 4",
    "sg:city":"Skamokawa",
    "sg:phone":"+1 360 795 3655",
    "sg:postcode":"98647",
    "sg:province":"WA",
    "wof:name":"Duck Inn",
    "wof:placetype":"venue"
},
  "geometry": {"coordinates":[-123.458038,46.271622],"type":"Point"}
}