{
  "type": "Feature",
  "properties": {
    "addr:full":"225 W Indiana Ave Spokane WA 99205",
    "addr:housenumber":"225",
    "addr:postcode":"ave;99205",
    "addr:street":"W Indiana",
    "iso:country":"US",
    "sg:address":"225 W Indiana Ave",
    "sg:city":"Spokane",
    "sg:classifiers":[
        {
            "category":"Manufacturing",
            "subcategory":"Apparel",
            "type":"Manufacturing & Wholesale Goods"
        }
    ],
    "sg:phone":"+1 509 326 7094",
    "sg:postcode":"99205",
    "sg:province":"WA",
    "sg:tags":[
        "draperies",
        "mfg",
        "commercial",
        "custom",
        "window",
        "treatment",
        "curtain",
        "drapery"
    ],
    "wof:name":"Drapery Mart",
    "wof:placetype":"venue"
},
  "geometry": {"coordinates":[-117.414694,47.674958],"type":"Point"}
}