{
  "type": "Feature",
  "properties": {
    "addr:full":"5308 276th Street Ct E Spanaway WA 98387",
    "addr:housenumber":"5308",
    "addr:postcode":"98387",
    "addr:street":"276Th Street Ct E",
    "iso:country":"US",
    "sg:address":"5308 276th Street Ct E",
    "sg:city":"Spanaway",
    "sg:classifiers":[
        {
            "category":"Building & Trades",
            "subcategory":"Plumbing",
            "type":"Services"
        }
    ],
    "sg:phone":"+1 253 875 7779",
    "sg:postcode":"98387",
    "sg:province":"WA",
    "sg:tags":[
        "plumber",
        "industrial",
        "contractors-commercial"
    ],
    "wof:name":"Able Plumbing Plus",
    "wof:placetype":"venue"
},
  "geometry": {"coordinates":[-122.360529,47.005063],"type":"Point"}
}