{
  "type": "Feature",
  "properties": {
    "addr:full":"20288 E Hickox Rd Mount Vernon WA 98274",
    "addr:housenumber":"20288",
    "addr:postcode":"98274",
    "addr:street":"E Hickox Rd",
    "iso:country":"US",
    "sg:address":"20288 E Hickox Rd",
    "sg:city":"Mount Vernon",
    "sg:classifiers":[
        {
            "category":"Professional",
            "subcategory":"Management & Consulting",
            "type":"Services"
        }
    ],
    "sg:phone":"+1 360 424 7332",
    "sg:postcode":"98274",
    "sg:province":"WA",
    "wof:name":"Nicholas P Governale",
    "wof:placetype":"venue"
},
  "geometry": {"coordinates":[-122.30695799999999,48.384699],"type":"Point"}
}