{
  "type": "Feature",
  "properties": {
    "addr:full":"3242 Capitol Blvd S Tumwater WA 98501",
    "addr:housenumber":"3242",
    "addr:postcode":"98501",
    "addr:street":"Capitol Blvd S Tumwater",
    "iso:country":"US",
    "sg:address":"3242 Capitol Blvd S",
    "sg:city":"Tumwater",
    "sg:classifiers":[
        {
            "category":"Building & Trades",
            "subcategory":"Construction",
            "type":"Services"
        }
    ],
    "sg:phone":"+1 360 352 7483",
    "sg:postcode":"98501",
    "sg:province":"WA",
    "sg:tags":[
        "general",
        "contractor"
    ],
    "sg:website":"www.thewaterco.net",
    "wof:name":"Harrington Construction & Dev",
    "wof:placetype":"venue"
},
  "geometry": {"coordinates":[-122.898635,47.019379],"type":"Point"}
}