{
  "type": "Feature",
  "properties": {
    "addr:full":"507 N Maple Hill Rd Kelso WA 98626",
    "addr:housenumber":"507",
    "addr:postcode":"98626",
    "addr:street":"N Maple Hill Rd",
    "iso:country":"US",
    "sg:address":"507 N Maple Hill Rd",
    "sg:city":"Kelso",
    "sg:classifiers":[
        {
            "category":"Shopping",
            "subcategory":"Discount & Variety Stores",
            "type":"Retail Goods"
        }
    ],
    "sg:phone":"+1 360 636 0545",
    "sg:postcode":"98626",
    "sg:province":"WA",
    "sg:tags":[
        "merchandise",
        "general"
    ],
    "wof:name":"D and D Sales",
    "wof:placetype":"venue"
},
  "geometry": {"coordinates":[-122.84703,46.099013],"type":"Point"}
}