{
  "type": "Feature",
  "properties": {
    "addr:full":"308 S 210th St Seattle WA 98198",
    "addr:housenumber":"308",
    "addr:postcode":"98198",
    "addr:street":"S 210Th St",
    "iso:country":"US",
    "sg:address":"308 S 210th St",
    "sg:city":"Seattle",
    "sg:classifiers":[
        {
            "category":"Real Estate",
            "subcategory":"Real Estate Agent",
            "type":"Services"
        }
    ],
    "sg:phone":"+1 206 878 9694",
    "sg:postcode":"98198",
    "sg:province":"WA",
    "wof:name":"Pacific Rim Investments",
    "wof:placetype":"venue"
},
  "geometry": {"coordinates":[-122.330783,47.413596],"type":"Point"}
}