{
  "type": "Feature",
  "properties": {
    "addr:full":"1303 Marine Dr Bellingham WA 98225",
    "addr:housenumber":"1303",
    "addr:postcode":"98225",
    "addr:street":"Marine Dr",
    "iso:country":"US",
    "sg:address":"1303 Marine Dr",
    "sg:city":"Bellingham",
    "sg:classifiers":[
        {
            "category":"Professional",
            "subcategory":"Secretarial Services",
            "type":"Services"
        }
    ],
    "sg:phone":"+1 360 715 1302",
    "sg:postcode":"98225",
    "sg:province":"WA",
    "sg:tags":[
        "reporting"
    ],
    "wof:name":"Binggeli Medical Transcription",
    "wof:placetype":"venue"
},
  "geometry": {"coordinates":[-122.55305799999999,48.783214],"type":"Point"}
}