{
  "type": "Feature",
  "properties": {
    "addr:full":"3614 Cedarville Rd Bellingham WA 98226",
    "addr:housenumber":"3614",
    "addr:postcode":"98226",
    "addr:street":"Cedarville Rd",
    "iso:country":"US",
    "sg:address":"3614 Cedarville Rd",
    "sg:city":"Bellingham",
    "sg:classifiers":[
        {
            "category":"Shopping",
            "subcategory":"Gifts & Souvenirs",
            "type":"Retail Goods"
        }
    ],
    "sg:phone":"+1 360 318 8680",
    "sg:postcode":"98226",
    "sg:province":"WA",
    "sg:tags":[
        "shop"
    ],
    "wof:name":"Harvest House",
    "wof:placetype":"venue"
},
  "geometry": {"coordinates":[-122.294346,48.838995],"type":"Point"}
}