{
  "type": "Feature",
  "properties": {
    "addr:full":"14220 Juanita Drive NE Bothell WA 98011",
    "addr:housenumber":"14220",
    "addr:postcode":"98011",
    "addr:street":"Juanita Drive Ne",
    "iso:country":"US",
    "sg:address":"14220 Juanita Drive NE",
    "sg:city":"Bothell",
    "sg:classifiers":[
        {
            "category":"Real Estate",
            "subcategory":"Real Estate Operator",
            "type":"Services"
        }
    ],
    "sg:phone":"+1 866 406 4043",
    "sg:postcode":"98011",
    "sg:province":"WA",
    "sg:tags":[
        "apartment"
    ],
    "sg:website":"www.essexapartmenthomes.com/",
    "wof:name":"Inglenook Court Apartments",
    "wof:placetype":"venue"
},
  "geometry": {"coordinates":[-122.24464,47.729848],"type":"Point"}
}