{
  "type": "Feature",
  "properties": {
    "addr:full":"710 S Cedar St Port Angeles WA 98362",
    "addr:housenumber":"710",
    "addr:postcode":"98362",
    "addr:street":"S Cedar St",
    "iso:country":"US",
    "sg:address":"710 S Cedar St",
    "sg:city":"Port Angeles",
    "sg:classifiers":[
        {
            "category":"Health Services",
            "subcategory":"Doctor",
            "type":"Services"
        }
    ],
    "sg:phone":"+1 360 417 3739",
    "sg:postcode":"98362",
    "sg:province":"WA",
    "sg:tags":[
        "dental"
    ],
    "wof:name":"Medley Deanetta",
    "wof:placetype":"venue"
},
  "geometry": {"coordinates":[-123.44835399999999,48.117829],"type":"Point"}
}