{
  "type": "Feature",
  "properties": {
    "addr:full":"11606 SE 47th St Bellevue WA 98006",
    "addr:housenumber":"11606",
    "addr:postcode":"98006",
    "addr:street":"Se 47Th St",
    "iso:country":"US",
    "sg:address":"11606 SE 47th St",
    "sg:city":"Bellevue",
    "sg:classifiers":[
        {
            "category":"Building & Trades",
            "subcategory":"Locksmith",
            "type":"Services"
        }
    ],
    "sg:phone":"+1 425 749 3387",
    "sg:postcode":"98006",
    "sg:province":"WA",
    "sg:tags":[
        "key"
    ],
    "wof:name":"Any Time 24 Locksmith",
    "wof:placetype":"venue"
},
  "geometry": {"coordinates":[-122.185103,47.563147],"type":"Point"}
}