{
  "type": "Feature",
  "properties": {
    "addr:full":"1260 116th Ave NE Bellevue WA 98004",
    "addr:housenumber":"1260",
    "addr:postcode":"98004",
    "addr:street":"116Th Ave Ne",
    "iso:country":"US",
    "sg:address":"1260 116th Ave NE",
    "sg:city":"Bellevue",
    "sg:phone":"+1 425 453 4598",
    "sg:postcode":"98004",
    "sg:province":"WA",
    "wof:name":"Craig Hertz BC, HIS, IHS",
    "wof:placetype":"venue"
},
  "geometry": {"coordinates":[-122.185675,47.621592],"type":"Point"}
}