{
  "type": "Feature",
  "properties": {
    "addr:full":"11620 NE 149th St Kirkland WA 98034",
    "addr:housenumber":"11620",
    "addr:postcode":"98034",
    "addr:street":"Ne 149Th St",
    "iso:country":"US",
    "sg:address":"11620 NE 149th St",
    "sg:city":"Kirkland",
    "sg:classifiers":[
        {
            "category":"Retail",
            "subcategory":"Portrait Studio",
            "type":"Services"
        }
    ],
    "sg:phone":"+1 425 486 8150",
    "sg:postcode":"98034",
    "sg:province":"WA",
    "sg:tags":[
        "photo"
    ],
    "wof:name":"Donald Marshall Photography",
    "wof:placetype":"venue"
},
  "geometry": {"coordinates":[-122.184877,47.736323],"type":"Point"}
}