{
  "type": "Feature",
  "properties": {
    "addr:full":"6863 Eagle Harbor Dr NE Bainbridge Island WA 98110",
    "addr:housenumber":"6863",
    "addr:postcode":"98110",
    "addr:street":"Eagle Harbor Dr Ne",
    "iso:country":"US",
    "sg:address":"6863 Eagle Harbor Dr NE",
    "sg:city":"Bainbridge Island",
    "sg:classifiers":[
        {
            "category":"Social Services",
            "type":"Services"
        }
    ],
    "sg:phone":"+1 206 780 2322",
    "sg:postcode":"98110",
    "sg:province":"WA",
    "wof:name":"About Getting Better",
    "wof:placetype":"venue"
},
  "geometry": {"coordinates":[-122.536637,47.621833],"type":"Point"}
}