{
  "type": "Feature",
  "properties": {
    "addr:full":"5043 19th Ave NE Seattle WA 98105",
    "addr:housenumber":"5043",
    "addr:postcode":"98105",
    "addr:street":"19Th Ave Ne",
    "iso:country":"US",
    "sg:address":"5043 19th Ave NE",
    "sg:city":"Seattle",
    "sg:classifiers":[
        {
            "category":"Professional",
            "subcategory":"Computer Services",
            "type":"Services"
        }
    ],
    "sg:phone":"+1 206 522 2172",
    "sg:postcode":"98105",
    "sg:province":"WA",
    "sg:tags":[
        "consultant",
        "designer"
    ],
    "wof:name":"Allenlea Consulting Group Inc",
    "wof:placetype":"venue"
},
  "geometry": {"coordinates":[-122.307247,47.666068],"type":"Point"}
}