{
  "type": "Feature",
  "properties": {
    "addr:full":"3046 Beacon Ave S Seattle WA 98144",
    "addr:housenumber":"3046",
    "addr:postcode":"98144",
    "addr:street":"Beacon Ave S",
    "iso:country":"US",
    "sg:address":"3046 Beacon Ave S",
    "sg:city":"Seattle",
    "sg:classifiers":[
        {
            "category":"Professional",
            "subcategory":"Business Services",
            "type":"Services"
        }
    ],
    "sg:phone":"+1 206 290 3369",
    "sg:postcode":"98144",
    "sg:province":"WA",
    "wof:name":"Static Factory Media LLC",
    "wof:placetype":"venue"
},
  "geometry": {"coordinates":[-122.309335,47.575992],"type":"Point"}
}