{
  "type": "Feature",
  "properties": {
    "addr:full":"122 S Highland Dr Kennewick WA 99337",
    "addr:housenumber":"122",
    "addr:postcode":"99337",
    "addr:street":"S Highland Dr",
    "iso:country":"US",
    "sg:address":"122 S Highland Dr",
    "sg:city":"Kennewick",
    "sg:classifiers":[
        {
            "category":"Building & Trades",
            "subcategory":"Construction",
            "type":"Services"
        }
    ],
    "sg:phone":"+1 509 582 2461",
    "sg:postcode":"99337",
    "sg:province":"WA",
    "sg:tags":[
        "excavating",
        "contractor"
    ],
    "wof:name":"Loftus Inc",
    "wof:placetype":"venue"
},
  "geometry": {"coordinates":[-119.12363000000001,46.172453],"type":"Point"}
}