{
  "type": "Feature",
  "properties": {
    "addr:full":"3480 Martin Way E Olympia WA 98506",
    "addr:housenumber":"3480",
    "addr:postcode":"98506",
    "addr:street":"Martin Way E",
    "iso:country":"US",
    "sg:address":"3480 Martin Way E",
    "sg:city":"Olympia",
    "sg:classifiers":[
        {
            "category":"Wholesale",
            "subcategory":"Auto Parts",
            "type":"Manufacturing & Wholesale Goods"
        }
    ],
    "sg:phone":"+1 360 438 2747",
    "sg:postcode":"98506",
    "sg:province":"WA",
    "sg:tags":[
        "equipment",
        "electrical"
    ],
    "wof:name":"Interstate Battery System",
    "wof:placetype":"venue"
},
  "geometry": {"coordinates":[-122.84536799999999,47.047237],"type":"Point"}
}