{
  "type": "Feature",
  "properties": {
    "addr:full":"5001 NE 50th St Seattle WA 98105",
    "addr:housenumber":"5001",
    "addr:postcode":"98105",
    "addr:street":"Ne 50Th St",
    "iso:country":"US",
    "sg:address":"5001 NE 50th St",
    "sg:city":"Seattle",
    "sg:classifiers":[
        {
            "category":"Education",
            "subcategory":"Special Training",
            "type":"Public Place"
        },
        {
            "category":"Social Services",
            "subcategory":"Child Care",
            "type":"Services"
        },
        {
            "category":"Education",
            "subcategory":"Preschool",
            "type":"Public Place"
        },
        {
            "category":"Education",
            "subcategory":"School",
            "type":"Public Place"
        }
    ],
    "sg:phone":"+1 206 524 8885",
    "sg:postcode":"98105",
    "sg:province":"WA",
    "sg:tags":[
        "kindergarten",
        "educational",
        "k-",
        "high",
        "middle",
        "nursery",
        "private",
        "elementary",
        "day"
    ],
    "sg:website":"http://www.thevilla.org",
    "wof:name":"Villa Academy",
    "wof:placetype":"venue"
},
  "geometry": {"coordinates":[-122.274002,47.665001],"type":"Point"}
}