{
  "type": "Feature",
  "properties": {
    "addr:full":"4020 E Madison St Seattle WA 98112",
    "addr:housenumber":"4020",
    "addr:postcode":"98112",
    "addr:street":"E Madison St",
    "iso:country":"US",
    "sg:address":"4020 E Madison St",
    "sg:city":"Seattle",
    "sg:classifiers":[
        {
            "category":"Professional",
            "type":"Services"
        }
    ],
    "sg:phone":"+1 206 323 8540",
    "sg:postcode":"98112",
    "sg:province":"WA",
    "wof:name":"John M McClelland Sr",
    "wof:placetype":"venue"
},
  "geometry": {"coordinates":[-122.27964299999999,47.634766],"type":"Point"}
}