{
  "type": "Feature",
  "properties": {
    "addr:full":"821 Water St Port Townsend WA 98368",
    "addr:housenumber":"821",
    "addr:postcode":"98368",
    "addr:street":"Water St",
    "iso:country":"US",
    "sg:address":"821 Water St",
    "sg:city":"Port Townsend",
    "sg:classifiers":[
        {
            "category":"Shopping",
            "subcategory":"Gifts & Souvenirs",
            "type":"Retail Goods"
        }
    ],
    "sg:phone":"+1 360 385 5565",
    "sg:postcode":"98368",
    "sg:province":"WA",
    "wof:name":"Maestrale",
    "wof:placetype":"venue"
},
  "geometry": {"coordinates":[-122.755601,48.114695],"type":"Point"}
}