{
  "type": "Feature",
  "properties": {
    "addr:full":"1018 Market St Kirkland WA 98033",
    "addr:housenumber":"1018",
    "addr:postcode":"98033",
    "addr:street":"Market St",
    "iso:country":"US",
    "sg:address":"1018 Market St",
    "sg:city":"Kirkland",
    "sg:classifiers":[
        {
            "category":"Building & Trades",
            "subcategory":"Construction",
            "type":"Services"
        }
    ],
    "sg:phone":"+1 866 432 5129",
    "sg:postcode":"98033",
    "sg:province":"WA",
    "sg:tags":[
        "painter"
    ],
    "sg:website":"www.painter-kirkland-wa.info/",
    "wof:name":"Kds Painting",
    "wof:placetype":"venue"
},
  "geometry": {"coordinates":[-122.20934,47.683486],"type":"Point"}
}