{
  "type": "Feature",
  "properties": {
    "iso:country":"US",
    "sg:address":"4091 State Hwy 3",
    "sg:city":"Bremerton",
    "sg:classifiers":[
        {
            "category":"Retail",
            "subcategory":"Veterinary Services",
            "type":"Services"
        }
    ],
    "sg:phone":"+1 360 377 3801",
    "sg:postcode":"98312",
    "sg:province":"WA",
    "wof:name":"James Little Dvm",
    "wof:placetype":"venue"
},
  "geometry": {"coordinates":[-122.70365,47.599619],"type":"Point"}
}