{
  "type": "Feature",
  "properties": {
    "addr:full":"13240 Northup Way NE Bellevue WA 98005",
    "addr:housenumber":"13240",
    "addr:postcode":"98005",
    "addr:street":"Northup Way Ne",
    "iso:country":"US",
    "sg:address":"13240 Northup Way NE",
    "sg:city":"Bellevue",
    "sg:classifiers":[
        {
            "category":"Personal",
            "type":"Services"
        }
    ],
    "sg:phone":"+1 425 641 9471",
    "sg:postcode":"98005",
    "sg:province":"WA",
    "sg:tags":[
        "therapist",
        "massage"
    ],
    "wof:name":"Eastside Massage Clinic",
    "wof:placetype":"venue"
},
  "geometry": {"coordinates":[-122.157698,47.628066],"type":"Point"}
}