{
  "type": "Feature",
  "properties": {
    "iso:country":"US",
    "sg:address":"8502 Valley Green Dr SE",
    "sg:city":"Olympia",
    "sg:classifiers":[
        {
            "category":"Building & Trades",
            "subcategory":"Electrical",
            "type":"Services"
        }
    ],
    "sg:phone":"+1 360 491 0626",
    "sg:postcode":"98513",
    "sg:province":"WA",
    "sg:tags":[
        "electrical",
        "electric",
        "contractor"
    ],
    "wof:name":"Huttmann Electric Inc",
    "wof:placetype":"venue"
},
  "geometry": {"coordinates":[-122.72909,46.960349],"type":"Point"}
}