{
  "type": "Feature",
  "properties": {
    "addr:full":"12320 Mukilteo Speedway Mukilteo WA 98275",
    "addr:housenumber":"12320",
    "addr:postcode":"98275",
    "addr:street":"Mukilteo Speedway",
    "iso:country":"US",
    "sg:address":"12320 Mukilteo Speedway",
    "sg:city":"Mukilteo",
    "sg:classifiers":[
        {
            "category":"Freight",
            "type":"Transportation"
        }
    ],
    "sg:phone":"+1 425 745 5760",
    "sg:postcode":"98275",
    "sg:province":"WA",
    "sg:tags":[
        "general"
    ],
    "wof:name":"Pack Rat Mini Storage",
    "wof:placetype":"venue"
},
  "geometry": {"coordinates":[-122.28236800000001,47.885936],"type":"Point"}
}