{
  "type": "Feature",
  "properties": {
    "addr:full":"2815 Nichols Blvd Longview WA 98632",
    "addr:housenumber":"2815",
    "addr:postcode":"98632",
    "addr:street":"Nichols Blvd",
    "iso:country":"US",
    "sg:address":"2815 Nichols Blvd",
    "sg:city":"Longview",
    "sg:classifiers":[
        {
            "category":"Food & Beverages",
            "subcategory":"Groceries & Convenience Stores",
            "type":"Retail Goods"
        }
    ],
    "sg:phone":"+1 360 425 0260",
    "sg:postcode":"98632",
    "sg:province":"WA",
    "wof:name":"Hemlock Store",
    "wof:placetype":"venue"
},
  "geometry": {"coordinates":[-122.95358899999999,46.137814],"type":"Point"}
}