{
  "type": "Feature",
  "properties": {
    "addr:full":"3434 1st Ave S Seattle WA 98134",
    "addr:housenumber":"3434",
    "addr:postcode":"98134",
    "addr:street":"1St Ave S",
    "iso:country":"US",
    "sg:address":"3434 1st Ave S",
    "sg:city":"Seattle",
    "sg:classifiers":[
        {
            "category":"Wholesale",
            "subcategory":"Electrical",
            "type":"Manufacturing & Wholesale Goods"
        }
    ],
    "sg:phone":"+1 206 622 5087",
    "sg:postcode":"98134",
    "sg:province":"WA",
    "sg:tags":[
        "fire",
        "equipment",
        "protection"
    ],
    "wof:name":"Fire Protection Supply Co",
    "wof:placetype":"venue"
},
  "geometry": {"coordinates":[-122.334125,47.572081],"type":"Point"}
}