{
  "type": "Feature",
  "properties": {
    "addr:full":"6016 Phinney Ave N Seattle WA 98103",
    "addr:housenumber":"6016",
    "addr:postcode":"98103",
    "addr:street":"Phinney Ave N",
    "iso:country":"US",
    "sg:address":"6016 Phinney Ave N",
    "sg:city":"Seattle",
    "sg:classifiers":[
        {
            "category":"Shopping",
            "subcategory":"Used Merchandise",
            "type":"Retail Goods"
        }
    ],
    "sg:phone":"+1 206 789 2805",
    "sg:postcode":"98103",
    "sg:province":"WA",
    "sg:tags":[
        "antique"
    ],
    "wof:name":"Daily Planet the",
    "wof:placetype":"venue"
},
  "geometry": {"coordinates":[-122.353996,47.672901],"type":"Point"}
}