{
  "type": "Feature",
  "properties": {
    "addr:full":"20731 Chautauqua Beach Rd SW Vashon WA 98070",
    "addr:postcode":"20731;98070",
    "addr:street":"Beach Rd Sw",
    "iso:country":"US",
    "sg:address":"20731 Chautauqua Beach Rd SW",
    "sg:city":"Vashon",
    "sg:classifiers":[
        {
            "category":"Retail",
            "subcategory":"Repair Shop",
            "type":"Services"
        }
    ],
    "sg:phone":"+1 206 463 2207",
    "sg:postcode":"98070",
    "sg:province":"WA",
    "sg:tags":[
        "upholsterer"
    ],
    "wof:name":"Phoenix Upholstery",
    "wof:placetype":"venue"
},
  "geometry": {"coordinates":[-122.44015,47.417902],"type":"Point"}
}