{
  "type": "Feature",
  "properties": {
    "iso:country":"US",
    "sg:address":"1 E Main St",
    "sg:city":"Walla Walla",
    "sg:classifiers":[
        {
            "category":"Professional",
            "subcategory":"Advertising",
            "type":"Services"
        }
    ],
    "sg:phone":"+1 509 522 1383",
    "sg:postcode":"99362",
    "sg:province":"WA",
    "wof:name":"KWHT",
    "wof:placetype":"venue"
},
  "geometry": {"coordinates":[-118.338094,46.067215],"type":"Point"}
}