{
  "type": "Feature",
  "properties": {
    "addr:full":"18634 72nd Ave S Kent WA 98032",
    "addr:housenumber":"18634",
    "addr:postcode":"98032",
    "addr:street":"72Nd Ave S",
    "iso:country":"US",
    "sg:address":"18634 72nd Ave S",
    "sg:city":"Kent",
    "sg:classifiers":[
        {
            "category":"Freight",
            "type":"Transportation"
        }
    ],
    "sg:phone":"+1 425 656 4423",
    "sg:postcode":"98032",
    "sg:province":"WA",
    "sg:tags":[
        "warehouse"
    ],
    "wof:name":"Meadow Burke Products",
    "wof:placetype":"venue"
},
  "geometry": {"coordinates":[-122.243785,47.435683],"type":"Point"}
}