{
  "type": "Feature",
  "properties": {
    "addr:full":"4752 89th Ave SE Mercer Island WA 98040",
    "addr:housenumber":"4752",
    "addr:postcode":"98040",
    "addr:street":"89Th Ave Se",
    "iso:country":"US",
    "sg:address":"4752 89th Ave SE",
    "sg:city":"Mercer Island",
    "sg:classifiers":[
        {
            "category":"Shopping",
            "subcategory":"Crafts & Fabrics",
            "type":"Retail Goods"
        }
    ],
    "sg:phone":"+1 206 232 2854",
    "sg:postcode":"98040",
    "sg:province":"WA",
    "sg:tags":[
        "trade",
        "sewing",
        "contractor"
    ],
    "wof:name":"Linda Tuells Sewing",
    "wof:placetype":"venue"
},
  "geometry": {"coordinates":[-122.220176,47.560756],"type":"Point"}
}