{
  "type": "Feature",
  "properties": {
    "addr:full":"843 E Lake Samish Dr Bellingham WA 98229",
    "addr:housenumber":"843",
    "addr:postcode":"98229",
    "addr:street":"E Lake Samish Dr",
    "iso:country":"US",
    "sg:address":"843 E Lake Samish Dr",
    "sg:city":"Bellingham",
    "sg:classifiers":[
        {
            "category":"Manufacturing",
            "subcategory":"Lumber",
            "type":"Manufacturing & Wholesale Goods"
        }
    ],
    "sg:phone":"+1 360 733 6413",
    "sg:postcode":"98229",
    "sg:province":"WA",
    "sg:tags":[
        "operation",
        "timber",
        "tract"
    ],
    "wof:name":"Wefers Forest Ltd Partnership",
    "wof:placetype":"venue"
},
  "geometry": {"coordinates":[-122.393748,48.674381],"type":"Point"}
}