{
  "type": "Feature",
  "properties": {
    "iso:country":"US",
    "sg:address":"443 N Bend Blvd N",
    "sg:city":"North Bend",
    "sg:classifiers":[
        {
            "category":"Building & Trades",
            "subcategory":"Plumbing",
            "type":"Services"
        }
    ],
    "sg:phone":"+1 425 831 5802",
    "sg:postcode":"98045",
    "sg:province":"WA",
    "sg:tags":[
        "contractor"
    ],
    "wof:name":"Chris Hunt Plumbing",
    "wof:placetype":"venue"
},
  "geometry": {"coordinates":[-121.789371,47.499793],"type":"Point"}
}