{
  "type": "Feature",
  "properties": {
    "addr:full":"631 5th St Mukilteo WA 98275",
    "addr:housenumber":"631",
    "addr:postcode":"98275",
    "addr:street":"5Th St",
    "iso:country":"US",
    "sg:address":"631 5th St",
    "sg:city":"Mukilteo",
    "sg:classifiers":[
        {
            "category":"Real Estate",
            "subcategory":"Real Estate Agent",
            "type":"Services"
        }
    ],
    "sg:phone":"+1 425 353 7770",
    "sg:postcode":"98275",
    "sg:province":"WA",
    "wof:name":"Re/Max",
    "wof:placetype":"venue"
},
  "geometry": {"coordinates":[-122.303444,47.944684],"type":"Point"}
}