{
  "type": "Feature",
  "properties": {
    "addr:full":"17511 68th Ave NE Kenmore WA 98028",
    "addr:housenumber":"17511",
    "addr:postcode":"98028",
    "addr:street":"68Th Ave Ne",
    "iso:country":"US",
    "sg:address":"17511 68th Ave NE",
    "sg:city":"Kenmore",
    "sg:classifiers":[
        {
            "category":"Shopping",
            "subcategory":"Computers & Home Electronics",
            "type":"Retail Goods"
        }
    ],
    "sg:phone":"+1 425 486 0244",
    "sg:postcode":"98028",
    "sg:province":"WA",
    "sg:tags":[
        "car",
        "stereo",
        "radio",
        "install"
    ],
    "wof:name":"Audio Lab",
    "wof:placetype":"venue"
},
  "geometry": {"coordinates":[-122.24984600000001,47.75784],"type":"Point"}
}