{
  "type": "Feature",
  "properties": {
    "addr:full":"519 King St Wenatchee WA 98801",
    "addr:housenumber":"519",
    "addr:postcode":"98801",
    "addr:street":"King St",
    "iso:country":"US",
    "sg:address":"519 King St",
    "sg:city":"Wenatchee",
    "sg:classifiers":[
        {
            "category":"Health Services",
            "subcategory":"Health Practitioner",
            "type":"Services"
        },
        {
            "category":"Health Services",
            "subcategory":"Doctor",
            "type":"Services"
        }
    ],
    "sg:phone":"+1 509 662 6771",
    "sg:postcode":"98801",
    "sg:province":"WA",
    "sg:tags":[
        "physician",
        "medical"
    ],
    "wof:name":"Glenn R Hoey ND",
    "wof:placetype":"venue"
},
  "geometry": {"coordinates":[-120.319576,47.420158],"type":"Point"}
}