{
  "type": "Feature",
  "properties": {
    "addr:full":"1201 Iler Ln Yakima WA 98901",
    "addr:housenumber":"1201",
    "addr:postcode":"98901",
    "addr:street":"Iler Ln",
    "iso:country":"US",
    "sg:address":"1201 Iler Ln",
    "sg:city":"Yakima",
    "sg:classifiers":[
        {
            "category":"Utilities",
            "subcategory":"Fuel Oil & Lpg",
            "type":"Services"
        }
    ],
    "sg:phone":"+1 509 457 7247",
    "sg:postcode":"98901",
    "sg:province":"WA",
    "sg:tags":[
        "dealer"
    ],
    "wof:name":"Kens Wood Yard & Service",
    "wof:placetype":"venue"
},
  "geometry": {"coordinates":[-120.487808,46.579639],"type":"Point"}
}