{
  "type": "Feature",
  "properties": {
    "addr:full":"3201 1st Ave S Seattle WA 98134",
    "addr:housenumber":"3201",
    "addr:postcode":"98134",
    "addr:street":"1St Ave S",
    "iso:country":"US",
    "sg:address":"3201 1st Ave S",
    "sg:city":"Seattle",
    "sg:classifiers":[
        {
            "category":"Real Estate",
            "subcategory":"Architect",
            "type":"Services"
        }
    ],
    "sg:phone":"+1 206 623 8733",
    "sg:postcode":"98134",
    "sg:province":"WA",
    "wof:name":"Thienes Williams Architects Pllc",
    "wof:placetype":"venue"
},
  "geometry": {"coordinates":[-122.334,47.5756],"type":"Point"}
}