{
  "type": "Feature",
  "properties": {
    "addr:full":"1203 E Mission Ave Spokane WA 99202",
    "addr:housenumber":"1203",
    "addr:postcode":"99202",
    "addr:street":"E Mission Ave",
    "iso:country":"US",
    "sg:address":"1203 E Mission Ave",
    "sg:city":"Spokane",
    "sg:classifiers":[
        {
            "category":"Communications",
            "subcategory":"Television Station",
            "type":"Services"
        }
    ],
    "sg:phone":"+1 509 489 5697",
    "sg:postcode":"99202",
    "sg:province":"WA",
    "wof:name":"Mark A Querio",
    "wof:placetype":"venue"
},
  "geometry": {"coordinates":[-117.39039099999999,47.671746],"type":"Point"}
}