{
  "type": "Feature",
  "properties": {
    "addr:full":"610 W Riverside Ave Spokane WA 99201",
    "addr:housenumber":"610",
    "addr:postcode":"99201",
    "addr:street":"W Riverside Ave",
    "iso:country":"US",
    "sg:address":"610 W Riverside Ave",
    "sg:city":"Spokane",
    "sg:classifiers":[
        {
            "category":"Professional",
            "type":"Services"
        }
    ],
    "sg:phone":"+1 509 624 6086",
    "sg:postcode":"99201",
    "sg:province":"WA",
    "wof:name":"Shadrall Assoc",
    "wof:placetype":"venue"
},
  "geometry": {"coordinates":[-117.42201300000001,47.658009],"type":"Point"}
}