{
  "type": "Feature",
  "properties": {
    "addr:full":"5269 16th Ave NE Seattle WA 98105",
    "addr:housenumber":"5269",
    "addr:postcode":"98105",
    "addr:street":"16Th Ave Ne",
    "iso:country":"US",
    "sg:address":"5269 16th Ave NE",
    "sg:city":"Seattle",
    "sg:classifiers":[
        {
            "category":"Professional",
            "type":"Services"
        }
    ],
    "sg:phone":"+1 206 524 1331",
    "sg:postcode":"98105",
    "sg:province":"WA",
    "sg:tags":[
        "motion",
        "technician",
        "picture"
    ],
    "wof:name":"Mydoc Productions",
    "wof:placetype":"venue"
},
  "geometry": {"coordinates":[-122.31074700000001,47.667867],"type":"Point"}
}