{
  "type": "Feature",
  "properties": {
    "addr:full":"10026 Tilley Rd S Olympia WA 98512",
    "addr:housenumber":"10026",
    "addr:postcode":"98512",
    "addr:street":"Tilley Rd",
    "iso:country":"US",
    "sg:address":"10026 Tilley Rd S",
    "sg:city":"Olympia",
    "sg:classifiers":[
        {
            "category":"Organizations",
            "subcategory":"Religious Organization",
            "type":"Services"
        }
    ],
    "sg:phone":"+1 360 943 5516",
    "sg:postcode":"98512",
    "sg:province":"WA",
    "wof:name":"Church of Cgod Cleveland Tenn",
    "wof:placetype":"venue"
},
  "geometry": {"coordinates":[-122.907798,46.942784],"type":"Point"}
}