{
  "type": "Feature",
  "properties": {
    "addr:full":"2229 5th St SW Puyallup WA 98371",
    "addr:housenumber":"2229",
    "addr:postcode":"98371",
    "addr:street":"5Th St Sw",
    "iso:country":"US",
    "sg:address":"2229 5th St SW",
    "sg:city":"Puyallup",
    "sg:classifiers":[
        {
            "category":"Home & Garden",
            "subcategory":"Garden Supply",
            "type":"Retail Goods"
        }
    ],
    "sg:phone":"+1 253 848 0754",
    "sg:postcode":"98371",
    "sg:province":"WA",
    "wof:name":"Garden Shop",
    "wof:placetype":"venue"
},
  "geometry": {"coordinates":[-122.298745,47.171093],"type":"Point"}
}