{
  "type": "Feature",
  "properties": {
    "addr:full":"329 W 14th St Port Angeles WA 98362",
    "addr:housenumber":"329",
    "addr:postcode":"98362",
    "addr:street":"W 14Th St",
    "iso:country":"US",
    "sg:address":"329 W 14th St",
    "sg:city":"Port Angeles",
    "sg:classifiers":[
        {
            "category":"Home & Garden",
            "subcategory":"Home Furnishings",
            "type":"Retail Goods"
        }
    ],
    "sg:phone":"+1 360 457 9776",
    "sg:postcode":"98362",
    "sg:province":"WA",
    "wof:name":"Draperies Northwest",
    "wof:placetype":"venue"
},
  "geometry": {"coordinates":[-123.44877200000001,48.109839],"type":"Point"}
}