{
  "type": "Feature",
  "properties": {
    "addr:full":"2030 Sleepy Hollow Hts Wenatchee WA 98801",
    "addr:housenumber":"2030",
    "addr:postcode":"98801",
    "addr:street":"Sleepy Hollow",
    "iso:country":"US",
    "sg:address":"2030 Sleepy Hollow Hts",
    "sg:city":"Wenatchee",
    "sg:classifiers":[
        {
            "category":"Building & Trades",
            "subcategory":"Construction",
            "type":"Services"
        }
    ],
    "sg:phone":"+1 509 665 9197",
    "sg:postcode":"98801",
    "sg:province":"WA",
    "sg:tags":[
        "contractor"
    ],
    "wof:name":"Phenix Construction",
    "wof:placetype":"venue"
},
  "geometry": {"coordinates":[-120.385648,47.474669],"type":"Point"}
}