{
  "type": "Feature",
  "properties": {
    "addr:full":"155 Spring St Friday Harbor WA 98250",
    "addr:housenumber":"155",
    "addr:postcode":"98250",
    "addr:street":"Spring St",
    "iso:country":"US",
    "sg:address":"155 Spring St",
    "sg:city":"Friday Harbor",
    "sg:classifiers":[
        {
            "category":"Shopping",
            "subcategory":"Clothing, Apparel, & Fashions",
            "type":"Retail Goods"
        }
    ],
    "sg:phone":"+1 360 378 2299",
    "sg:postcode":"98250",
    "sg:province":"WA",
    "sg:tags":[
        "sportswear"
    ],
    "wof:name":"Toggery",
    "wof:placetype":"venue"
},
  "geometry": {"coordinates":[-123.016379,48.534412],"type":"Point"}
}