{
  "type": "Feature",
  "properties": {
    "addr:full":"15018 Starr Rd SE Olalla WA 98359",
    "addr:housenumber":"15018",
    "addr:postcode":"98359",
    "addr:street":"Starr Rd Se Olalla",
    "iso:country":"US",
    "sg:address":"15018 Starr Rd SE",
    "sg:city":"Olalla",
    "sg:classifiers":[
        {
            "category":"Health Services",
            "subcategory":"Clinic",
            "type":"Services"
        }
    ],
    "sg:phone":"+1 253 857 2723",
    "sg:postcode":"98359",
    "sg:province":"WA",
    "wof:name":"Abbott House",
    "wof:placetype":"venue"
},
  "geometry": {"coordinates":[-122.54667600000001,47.413368],"type":"Point"}
}