{
  "type": "Feature",
  "properties": {
    "addr:full":"108 Sequoia Rd Longview WA 98632",
    "addr:housenumber":"108",
    "addr:postcode":"98632",
    "addr:street":"Sequoia Rd",
    "iso:country":"US",
    "sg:address":"108 Sequoia Rd",
    "sg:city":"Longview",
    "sg:classifiers":[
        {
            "category":"Shopping",
            "subcategory":"Florist",
            "type":"Retail Goods"
        }
    ],
    "sg:phone":"+1 360 501 6092",
    "sg:postcode":"98632",
    "sg:province":"WA",
    "sg:tags":[
        "supply"
    ],
    "wof:name":"Evergreen Terrace Gardens",
    "wof:placetype":"venue"
},
  "geometry": {"coordinates":[-123.001532,46.180554],"type":"Point"}
}