{
  "type": "Feature",
  "properties": {
    "addr:full":"8536 Greenwood Ave N Seattle WA 98103",
    "addr:housenumber":"8536",
    "addr:postcode":"98103",
    "addr:street":"Greenwood Ave N",
    "iso:country":"US",
    "sg:address":"8536 Greenwood Ave N",
    "sg:city":"Seattle",
    "sg:classifiers":[
        {
            "category":"Arts & Performance",
            "subcategory":"Art Gallery",
            "type":"Entertainment"
        },
        {
            "category":"Shopping",
            "subcategory":"Books",
            "type":"Retail Goods"
        }
    ],
    "sg:phone":"+1 206 784 4660",
    "sg:postcode":"98103",
    "sg:province":"WA",
    "sg:tags":[
        "dealers-used",
        "bookstore",
        "rare",
        "store"
    ],
    "sg:website":"www.balderdashbooksandart.com",
    "wof:name":"Balderdash Books And Art",
    "wof:placetype":"venue"
},
  "geometry": {"coordinates":[-122.355284,47.690924],"type":"Point"}
}