{
  "type": "Feature",
  "properties": {
    "addr:full":"17725 NE 65th St Redmond WA 98052",
    "addr:housenumber":"17725",
    "addr:postcode":"98052",
    "addr:street":"Ne 65Th St",
    "iso:country":"US",
    "sg:address":"17725 NE 65th St",
    "sg:city":"Redmond",
    "sg:classifiers":[
        {
            "category":"Professional",
            "subcategory":"Business Services",
            "type":"Services"
        },
        {
            "category":"Home & Garden",
            "subcategory":"Carpets & Floor Coverings",
            "type":"Retail Goods"
        }
    ],
    "sg:phone":"+1 425 558 9427",
    "sg:postcode":"98052",
    "sg:province":"WA",
    "sg:tags":[
        "building",
        "residential",
        "commercial",
        "rug",
        "remodeling",
        "dealer"
    ],
    "wof:name":"Equity Interiors",
    "wof:placetype":"venue"
},
  "geometry": {"coordinates":[-122.10248900000001,47.663911],"type":"Point"}
}