{
  "type": "Feature",
  "properties": {
    "addr:full":"201 SW Lake Roesiger Rd Snohomish WA 98290",
    "addr:housenumber":"201",
    "addr:postcode":"98290",
    "addr:street":"Sw Lake Roesiger Rd",
    "iso:country":"US",
    "sg:address":"201 SW Lake Roesiger Rd",
    "sg:city":"Snohomish",
    "sg:classifiers":[
        {
            "category":"Health Services",
            "subcategory":"Doctor",
            "type":"Services"
        }
    ],
    "sg:phone":"+1 425 334 6889",
    "sg:postcode":"98290",
    "sg:province":"WA",
    "sg:tags":[
        "medical"
    ],
    "wof:name":"Cascade Vly Anesthesiologist",
    "wof:placetype":"venue"
},
  "geometry": {"coordinates":[-121.917998,47.995596],"type":"Point"}
}