{
  "type": "Feature",
  "properties": {
    "addr:full":"10806 NE Crest Ave Vancouver WA 98685",
    "addr:housenumber":"10806",
    "addr:postcode":"98685",
    "addr:street":"Ne Crest Ave",
    "iso:country":"US",
    "sg:address":"10806 NE Crest Ave",
    "sg:city":"Vancouver",
    "sg:classifiers":[
        {
            "category":"Professional",
            "subcategory":"Advertising",
            "type":"Services"
        }
    ],
    "sg:phone":"+1 360 574 7673",
    "sg:postcode":"98685",
    "sg:province":"WA",
    "sg:tags":[
        "agency"
    ],
    "wof:name":"Heaton Advertising Inc",
    "wof:placetype":"venue"
},
  "geometry": {"coordinates":[-122.66491600000001,45.699688],"type":"Point"}
}