{
  "type": "Feature",
  "properties": {
    "addr:full":"6146 Portal Way Ferndale WA 98248",
    "addr:housenumber":"6146",
    "addr:postcode":"98248",
    "addr:street":"Portal Way",
    "iso:country":"US",
    "sg:address":"6146 Portal Way",
    "sg:city":"Ferndale",
    "sg:classifiers":[
        {
            "category":"Building & Trades",
            "subcategory":"Construction",
            "type":"Services"
        },
        {
            "category":"Manufacturing",
            "subcategory":"Building Materials",
            "type":"Manufacturing & Wholesale Goods"
        },
        {
            "category":"Utilities",
            "type":"Services"
        }
    ],
    "sg:phone":"+1 360 746 2370",
    "sg:postcode":"98248",
    "sg:province":"WA",
    "sg:tags":[
        "repair",
        "sheet",
        "specialty",
        "work",
        "metal",
        "system",
        "cooling",
        "heating",
        "geothermal",
        "mechanical",
        "ventilating",
        "contractor",
        "air conditioning"
    ],
    "sg:website":"http://www.smithmechanical.wholehome.com",
    "wof:name":"Smith Mechanical Inc",
    "wof:placetype":"venue"
},
  "geometry": {"coordinates":[-122.58464600000001,48.863619],"type":"Point"}
}