{
  "type": "Feature",
  "properties": {
    "addr:full":"16030 Bothell Everett Hwy Bothell WA 98012",
    "addr:housenumber":"16030",
    "addr:postcode":"98012",
    "addr:street":"Bothell Everett Hwy",
    "iso:country":"US",
    "sg:address":"16030 Bothell Everett Hwy",
    "sg:city":"Bothell",
    "sg:classifiers":[
        {
            "category":"Health Services",
            "subcategory":"Doctor",
            "type":"Services"
        }
    ],
    "sg:phone":"+1 425 481 4101",
    "sg:postcode":"98012",
    "sg:province":"WA",
    "sg:tags":[
        "medical"
    ],
    "wof:name":"Ray Cardwell MD",
    "wof:placetype":"venue"
},
  "geometry": {"coordinates":[-122.218321,47.852777],"type":"Point"}
}