{
  "type": "Feature",
  "properties": {
    "addr:full":"4161 Lopez Sound Rd Lopez WA 98261",
    "addr:housenumber":"4161",
    "addr:postcode":"98261",
    "addr:street":"Lopez Sound Rd Lopez",
    "iso:country":"US",
    "sg:address":"4161 Lopez Sound Rd",
    "sg:city":"Lopez",
    "sg:classifiers":[
        {
            "category":"Manufacturing",
            "subcategory":"Printing",
            "type":"Manufacturing & Wholesale Goods"
        }
    ],
    "sg:phone":"+1 360 468 3250",
    "sg:postcode":"98261",
    "sg:province":"WA",
    "sg:tags":[
        "book"
    ],
    "wof:name":"Water Marked Press",
    "wof:placetype":"venue"
},
  "geometry": {"coordinates":[-122.876887,48.47395],"type":"Point"}
}