{
  "type": "Feature",
  "properties": {
    "iso:country":"US",
    "sg:address":"11450 Roseberg Ave S",
    "sg:city":"Seattle",
    "sg:classifiers":[
        {
            "category":"Restaurant",
            "type":"Food & Drink"
        }
    ],
    "sg:phone":"+1 206 246 5026",
    "sg:postcode":"98168",
    "sg:province":"WA",
    "sg:tags":[
        "caterer"
    ],
    "wof:name":"Feeding Frenzy",
    "wof:placetype":"venue"
},
  "geometry": {"coordinates":[-122.302094,47.501903],"type":"Point"}
}