{
  "type": "Feature",
  "properties": {
    "addr:full":"7945 14th Ave SW Seattle WA 98106",
    "addr:housenumber":"7945",
    "addr:postcode":"98106",
    "addr:street":"14Th Ave Sw",
    "iso:country":"US",
    "sg:address":"7945 14th Ave SW",
    "sg:city":"Seattle",
    "sg:classifiers":[
        {
            "category":"Building & Trades",
            "subcategory":"Landscaping Services",
            "type":"Services"
        }
    ],
    "sg:phone":"+1 206 387 6100",
    "sg:postcode":"98106",
    "sg:province":"WA",
    "sg:tags":[
        "landscape"
    ],
    "wof:name":"Surinder Verraich",
    "wof:placetype":"venue"
},
  "geometry": {"coordinates":[-122.35285399999999,47.530723],"type":"Point"}
}