{
  "type": "Feature",
  "properties": {
    "iso:country":"US",
    "sg:address":"5335 90th Ave SE",
    "sg:city":"Mercer Island",
    "sg:classifiers":[
        {
            "category":"Banks & Credit Unions",
            "subcategory":"Financial Services",
            "type":"Services"
        }
    ],
    "sg:phone":"+1 206 275 1171",
    "sg:postcode":"98040",
    "sg:province":"WA",
    "sg:tags":[
        "investor"
    ],
    "wof:name":"M K Pacific",
    "wof:placetype":"venue"
},
  "geometry": {"coordinates":[-122.22067800000001,47.555297],"type":"Point"}
}