{
  "type": "Feature",
  "properties": {
    "addr:full":"3323 33rd Avenue SW Seattle WA 98126",
    "addr:housenumber":"3323",
    "addr:postcode":"98126",
    "addr:street":"33Rd Avenue Sw",
    "iso:country":"US",
    "sg:address":"3323 33rd Avenue SW",
    "sg:city":"Seattle",
    "sg:classifiers":[
        {
            "category":"Building & Trades",
            "subcategory":"Cleaning & Sanitation",
            "type":"Services"
        }
    ],
    "sg:phone":"+1 206 575 4402",
    "sg:postcode":"98126",
    "sg:province":"WA",
    "wof:name":"Balmore Janitorial Service & Supplies",
    "wof:placetype":"venue"
},
  "geometry": {"coordinates":[-122.374061,47.573225],"type":"Point"}
}