{
  "type": "Feature",
  "properties": {
    "addr:full":"905 W 11th St Port Angeles WA 98363",
    "addr:housenumber":"905",
    "addr:postcode":"98363",
    "addr:street":"W 11Th St",
    "iso:country":"US",
    "sg:address":"905 W 11th St",
    "sg:city":"Port Angeles",
    "sg:classifiers":[
        {
            "category":"Professional",
            "subcategory":"Accounting & Tax Preparation",
            "type":"Services"
        }
    ],
    "sg:phone":"+1 360 452 4751",
    "sg:postcode":"98363",
    "sg:province":"WA",
    "sg:tags":[
        "bookkeeping",
        "general"
    ],
    "wof:name":"Central Bookkeeping Svc",
    "wof:placetype":"venue"
},
  "geometry": {"coordinates":[-123.459292,48.117712],"type":"Point"}
}