{
  "type": "Feature",
  "properties": {
    "addr:full":"516 S Shore Rd Quinault WA 98575",
    "addr:housenumber":"516",
    "addr:postcode":"98575",
    "addr:street":"S Shore Rd",
    "iso:country":"US",
    "sg:address":"516 S Shore Rd",
    "sg:city":"Quinault",
    "sg:classifiers":[
        {
            "category":"Travel",
            "subcategory":"Hotels & Motels",
            "type":"Entertainment"
        }
    ],
    "sg:phone":"+1 360 288 2535",
    "sg:postcode":"98575",
    "sg:province":"WA",
    "sg:tags":[
        "resort"
    ],
    "sg:website":"www.rfrv.com",
    "wof:name":"Rain Forest Resort Village",
    "wof:placetype":"venue"
},
  "geometry": {"coordinates":[-123.831547,47.475069],"type":"Point"}
}