{
  "type": "Feature",
  "properties": {
    "addr:full":"8411 E Rich Ave Spokane WA 99212",
    "addr:housenumber":"8411",
    "addr:postcode":"99212",
    "addr:street":"E Rich Ave",
    "iso:country":"US",
    "sg:address":"8411 E Rich Ave",
    "sg:city":"Spokane",
    "sg:classifiers":[
        {
            "category":"Shopping",
            "subcategory":"Clothing, Apparel, & Fashions",
            "type":"Retail Goods"
        }
    ],
    "sg:phone":"+1 509 928 4272",
    "sg:postcode":"99212",
    "sg:province":"WA",
    "wof:name":"A Thread Runs Through It",
    "wof:placetype":"venue"
},
  "geometry": {"coordinates":[-117.29067000000001,47.696586],"type":"Point"}
}