{
  "type": "Feature",
  "properties": {
    "addr:full":"311 Railroad Ave S Kent WA 98032",
    "addr:housenumber":"311",
    "addr:postcode":"98032",
    "addr:street":"Railroad Ave S",
    "iso:country":"US",
    "sg:address":"311 Railroad Ave S",
    "sg:city":"Kent",
    "sg:classifiers":[
        {
            "category":"Manufacturing",
            "subcategory":"Aerospace",
            "type":"Manufacturing & Wholesale Goods"
        },
        {
            "category":"Manufacturing",
            "subcategory":"Tools & Machinery",
            "type":"Manufacturing & Wholesale Goods"
        }
    ],
    "sg:phone":"+1 253 852 6869",
    "sg:postcode":"98032",
    "sg:province":"WA",
    "sg:tags":[
        "machine",
        "shop",
        "aircraft",
        "mfg"
    ],
    "sg:website":"www.cncdiversified.com",
    "wof:name":"C N C Diversified Mfg Inc",
    "wof:placetype":"venue"
},
  "geometry": {"coordinates":[-122.232415,47.378749],"type":"Point"}
}