{
  "type": "Feature",
  "properties": {
    "addr:full":"Westin Hotel 600 Bellevue Way NE Bellevue WA 98004",
    "addr:housenumber":"600",
    "addr:postcode":"98004",
    "addr:street":"Bellevue Way Ne",
    "iso:country":"US",
    "sg:address":"Westin Hotel 600 Bellevue Way NE",
    "sg:city":"Bellevue",
    "sg:classifiers":[
        {
            "category":"Bars & Pubs",
            "subcategory":"Wine Bar",
            "type":"Food & Drink"
        }
    ],
    "sg:phone":"+1 425 638 1000",
    "sg:postcode":"98004",
    "sg:province":"WA",
    "wof:name":"Cypress Lounge and Wine Bar",
    "wof:placetype":"venue"
},
  "geometry": {"coordinates":[-122.201588,47.615611],"type":"Point"}
}