{
  "type": "Feature",
  "properties": {
    "addr:full":"205 7th Ave NW Puyallup WA 98371",
    "addr:housenumber":"205",
    "addr:postcode":"98371",
    "addr:street":"7Th Ave Nw",
    "iso:country":"US",
    "sg:address":"205 7th Ave NW",
    "sg:city":"Puyallup",
    "sg:classifiers":[
        {
            "category":"Health Services",
            "subcategory":"Clinic",
            "type":"Services"
        }
    ],
    "sg:phone":"+1 253 841 1010",
    "sg:postcode":"98371",
    "sg:province":"WA",
    "wof:name":"Labor of Love Doula Services",
    "wof:placetype":"venue"
},
  "geometry": {"coordinates":[-122.296914,47.197133],"type":"Point"}
}