{
  "type": "Feature",
  "properties": {
    "addr:full":"21540 30th Dr SE Ste 230 Bothell WA 98021",
    "addr:housenumber":"21540",
    "addr:postcode":"98021",
    "addr:street":"30Th Dr Se Ste 230",
    "iso:country":"US",
    "sg:address":"21540 30th Dr SE Ste 230",
    "sg:city":"Bothell",
    "sg:classifiers":[
        {
            "category":"Professional",
            "subcategory":"Computer Services",
            "type":"Services"
        }
    ],
    "sg:phone":"+1 425 939 3100",
    "sg:postcode":"98021",
    "sg:province":"WA",
    "sg:tags":[
        "cd-rom"
    ],
    "wof:name":"Dexterra Inc",
    "wof:placetype":"venue"
},
  "geometry": {"coordinates":[-122.196324,47.802219],"type":"Point"}
}