{
  "type": "Feature",
  "properties": {
    "addr:full":"3844 1st Ave S Bldg A Seattle WA 98134",
    "addr:housenumber":"3844",
    "addr:postcode":"98134",
    "addr:street":"1St Ave S Bldg A",
    "iso:country":"US",
    "sg:address":"3844 1st Ave S Bldg A",
    "sg:city":"Seattle",
    "sg:classifiers":[
        {
            "category":"Professional",
            "subcategory":"Engineering",
            "type":"Services"
        },
        {
            "category":"Retail",
            "subcategory":"Repair Shop",
            "type":"Services"
        },
        {
            "category":"Restaurant",
            "type":"Food & Drink"
        },
        {
            "category":"Wholesale",
            "subcategory":"Machinery & Supplies",
            "type":"Manufacturing & Wholesale Goods"
        }
    ],
    "sg:phone":"+1 206 621 0194",
    "sg:postcode":"98134",
    "sg:province":"WA",
    "sg:tags":[
        "industrial",
        "equipment",
        "supplies-refrigeration",
        "equipment-commercial",
        "refrigeration",
        "freezers-repair",
        "refrigerator",
        "engineer"
    ],
    "sg:website":"http://www.eastonrefrigeration.net",
    "wof:name":"Easton Refrigeration",
    "wof:placetype":"venue"
},
  "geometry": {"coordinates":[-122.334183,47.569052],"type":"Point"}
}