{
  "type": "Feature",
  "properties": {
    "addr:full":"12829 62nd Ave E Puyallup WA 98373",
    "addr:housenumber":"12829",
    "addr:postcode":"98373",
    "addr:street":"62Nd Ave E",
    "iso:country":"US",
    "sg:address":"12829 62nd Ave E",
    "sg:city":"Puyallup",
    "sg:classifiers":[
        {
            "category":"Food & Beverages",
            "subcategory":"Bakery",
            "type":"Retail Goods"
        }
    ],
    "sg:phone":"+1 253 531 1994",
    "sg:postcode":"98373",
    "sg:province":"WA",
    "wof:name":"Rwk Enterprises",
    "wof:placetype":"venue"
},
  "geometry": {"coordinates":[-122.346647,47.136831],"type":"Point"}
}