{
  "type": "Feature",
  "properties": {
    "addr:full":"330 Prospect St Leavenworth WA 98826",
    "addr:housenumber":"330",
    "addr:postcode":"98826",
    "addr:street":"Prospect St",
    "iso:country":"US",
    "sg:address":"330 Prospect St",
    "sg:city":"Leavenworth",
    "sg:classifiers":[
        {
            "category":"Real Estate",
            "subcategory":"Real Estate Operator",
            "type":"Services"
        }
    ],
    "sg:phone":"+1 509 548 6262",
    "sg:postcode":"98826",
    "sg:province":"WA",
    "sg:tags":[
        "building",
        "apartment"
    ],
    "wof:name":"Bavarian Village Apartments",
    "wof:placetype":"venue"
},
  "geometry": {"coordinates":[-120.675928,47.593674],"type":"Point"}
}