{
  "type": "Feature",
  "properties": {
    "addr:full":"1104 Main St Vancouver WA 98660",
    "addr:housenumber":"1104",
    "addr:postcode":"98660",
    "addr:street":"Main St",
    "iso:country":"US",
    "sg:address":"1104 Main St",
    "sg:city":"Vancouver",
    "sg:classifiers":[
        {
            "category":"Professional",
            "type":"Services"
        }
    ],
    "sg:phone":"+1 360 694 4646",
    "sg:postcode":"98660",
    "sg:province":"WA",
    "sg:tags":[
        "establishment"
    ],
    "wof:name":"Onsite Solution LLC",
    "wof:placetype":"venue"
},
  "geometry": {"coordinates":[-122.67166899999999,45.630266],"type":"Point"}
}