{
  "type": "Feature",
  "properties": {
    "addr:full":"16207 52nd Ave W Edmonds WA 98026",
    "addr:housenumber":"16207",
    "addr:postcode":"98026",
    "addr:street":"52Nd Ave W",
    "iso:country":"US",
    "sg:address":"16207 52nd Ave W",
    "sg:city":"Edmonds",
    "sg:classifiers":[
        {
            "category":"Manufacturing",
            "subcategory":"Tools & Machinery",
            "type":"Manufacturing & Wholesale Goods"
        }
    ],
    "sg:phone":"+1 425 743 0629",
    "sg:postcode":"98026",
    "sg:province":"WA",
    "sg:tags":[
        "surgical",
        "mfg"
    ],
    "wof:name":"Emer North West",
    "wof:placetype":"venue"
},
  "geometry": {"coordinates":[-122.303589,47.850287],"type":"Point"}
}