{
  "type": "Feature",
  "properties": {
    "addr:full":"13821 28th Dr SE Bothell WA 98012",
    "addr:housenumber":"13821",
    "addr:postcode":"98012",
    "addr:street":"28Th Dr Se",
    "iso:country":"US",
    "sg:address":"13821 28th Dr SE",
    "sg:city":"Bothell",
    "sg:classifiers":[
        {
            "category":"Building & Trades",
            "subcategory":"Cleaning & Sanitation",
            "type":"Services"
        }
    ],
    "sg:phone":"+1 425 357 1904",
    "sg:postcode":"98012",
    "sg:province":"WA",
    "sg:tags":[
        "maintenance"
    ],
    "wof:name":"Elite House Cleaning",
    "wof:placetype":"venue"
},
  "geometry": {"coordinates":[-122.192435,47.871361],"type":"Point"}
}