{
  "type": "Feature",
  "properties": {
    "addr:full":"5505 University Way NE Seattle WA 98105",
    "addr:housenumber":"5505",
    "addr:postcode":"98105",
    "addr:street":"University Way Ne",
    "iso:country":"US",
    "sg:address":"5505 University Way NE",
    "sg:city":"Seattle",
    "sg:classifiers":[
        {
            "category":"Personal",
            "subcategory":"Massage",
            "type":"Services"
        }
    ],
    "sg:phone":"+1 206 816 0583",
    "sg:postcode":"98105",
    "sg:province":"WA",
    "sg:website":"www.puressencetherapies.com",
    "wof:name":"Puressence Therapies",
    "wof:placetype":"venue"
},
  "geometry": {"coordinates":[-122.31337000000001,47.668756],"type":"Point"}
}