{
  "type": "Feature",
  "properties": {
    "iso:country":"US",
    "sg:address":"220 W 1st St",
    "sg:city":"Aberdeen",
    "sg:classifiers":[
        {
            "category":"Banks & Credit Unions",
            "subcategory":"Investment Brokerage",
            "type":"Services"
        }
    ],
    "sg:phone":"+1 360 537 9200",
    "sg:postcode":"98520",
    "sg:province":"WA",
    "sg:tags":[
        "security"
    ],
    "wof:name":"Wedbush Morgan Securities Inc",
    "wof:placetype":"venue"
},
  "geometry": {"coordinates":[-123.821161,46.975156],"type":"Point"}
}