{
  "type": "Feature",
  "properties": {
    "addr:full":"2535 Beacon Ave S Seattle WA 98144",
    "addr:housenumber":"2535",
    "addr:postcode":"98144",
    "addr:street":"Beacon Ave S",
    "iso:country":"US",
    "sg:address":"2535 Beacon Ave S",
    "sg:city":"Seattle",
    "sg:classifiers":[
        {
            "category":"Health Services",
            "subcategory":"Doctor",
            "type":"Services"
        }
    ],
    "sg:phone":"+1 206 325 6036",
    "sg:postcode":"98144",
    "sg:province":"WA",
    "wof:name":"Sy Jesus MD",
    "wof:placetype":"venue"
},
  "geometry": {"coordinates":[-122.31300400000001,47.5807],"type":"Point"}
}