{
  "type": "Feature",
  "properties": {
    "addr:full":"2410 NW 125th St Vancouver WA 98685",
    "addr:housenumber":"2410",
    "addr:postcode":"98685",
    "addr:street":"Nw 125Th St",
    "iso:country":"US",
    "sg:address":"2410 NW 125th St",
    "sg:city":"Vancouver",
    "sg:classifiers":[
        {
            "category":"Shopping",
            "subcategory":"Gifts & Souvenirs",
            "type":"Retail Goods"
        }
    ],
    "sg:phone":"+1 360 258 1738",
    "sg:postcode":"98685",
    "sg:province":"WA",
    "wof:name":"Scott W Evenson",
    "wof:placetype":"venue"
},
  "geometry": {"coordinates":[-122.697817,45.711403],"type":"Point"}
}