{
  "type": "Feature",
  "properties": {
    "addr:full":"3710 Grandview St Gig Harbor WA 98335",
    "addr:housenumber":"3710",
    "addr:postcode":"98335",
    "addr:street":"Grandview St",
    "iso:country":"US",
    "sg:address":"3710 Grandview St",
    "sg:city":"Gig Harbor",
    "sg:classifiers":[
        {
            "category":"Building & Trades",
            "subcategory":"Construction",
            "type":"Services"
        }
    ],
    "sg:phone":"+1 253 851 3329",
    "sg:postcode":"98335",
    "sg:province":"WA",
    "sg:tags":[
        "general",
        "contractor"
    ],
    "wof:name":"Hunter Construction",
    "wof:placetype":"venue"
},
  "geometry": {"coordinates":[-122.58946400000001,47.323315],"type":"Point"}
}