{
  "type": "Feature",
  "properties": {
    "iso:country":"US",
    "sg:address":"1542 Madrona Dr",
    "sg:city":"Seattle",
    "sg:classifiers":[
        {
            "category":"Health Services",
            "subcategory":"Clinic",
            "type":"Services"
        }
    ],
    "sg:phone":"+1 206 850 5952",
    "sg:postcode":"98122",
    "sg:province":"WA",
    "wof:name":"Executive Focus On Health",
    "wof:placetype":"venue"
},
  "geometry": {"coordinates":[-122.283528,47.614638],"type":"Point"}
}