{
  "type": "Feature",
  "properties": {
    "addr:full":"2548 29th Ave W Seattle WA 98199",
    "addr:housenumber":"2548",
    "addr:postcode":"98199",
    "addr:street":"29Th Ave W",
    "iso:country":"US",
    "sg:address":"2548 29th Ave W",
    "sg:city":"Seattle",
    "sg:classifiers":[
        {
            "category":"Wholesale",
            "subcategory":"Seafood",
            "type":"Manufacturing & Wholesale Goods"
        }
    ],
    "sg:phone":"+1 206 283 2406",
    "sg:postcode":"98199",
    "sg:province":"WA",
    "wof:name":"Quality Certif Seafood of Wash",
    "wof:placetype":"venue"
},
  "geometry": {"coordinates":[-122.394102,47.642195],"type":"Point"}
}