{
  "type": "Feature",
  "properties": {
    "addr:full":"15650 SE 296th St Kent WA 98042",
    "addr:postcode":"15650;98042",
    "addr:street":"Se 296Th St",
    "iso:country":"US",
    "sg:address":"15650 SE 296th St",
    "sg:city":"Kent",
    "sg:classifiers":[
        {
            "category":"Professional",
            "subcategory":"Accounting & Tax Preparation",
            "type":"Services"
        }
    ],
    "sg:phone":"+1 253 630 1273",
    "sg:postcode":"98042",
    "sg:province":"WA",
    "wof:name":"Hopper W R & Assoc Inc",
    "wof:placetype":"venue"
},
  "geometry": {"coordinates":[-122.130475,47.336687],"type":"Point"}
}