{
  "type": "Feature",
  "properties": {
    "addr:full":"17555 15th Ave NE Shoreline WA 98155",
    "addr:housenumber":"17555",
    "addr:postcode":"98155",
    "addr:street":"15Th Ave Ne",
    "iso:country":"US",
    "sg:address":"17555 15th Ave NE",
    "sg:city":"Shoreline",
    "sg:classifiers":[
        {
            "category":"Professional",
            "subcategory":"Detective & Security Services",
            "type":"Services"
        }
    ],
    "sg:phone":"+1 206 525 6900",
    "sg:postcode":"98155",
    "sg:province":"WA",
    "sg:tags":[
        "burglar",
        "equipment",
        "fire",
        "consultant",
        "alarm",
        "system",
        "installs",
        "lease"
    ],
    "wof:name":"Puget Sound Guard Assurance Inc",
    "wof:placetype":"venue"
},
  "geometry": {"coordinates":[-122.313455,47.756227],"type":"Point"}
}