{
  "type": "Feature",
  "properties": {
    "addr:full":"15422 NE 28th Ave Vancouver WA 98686",
    "addr:housenumber":"15422",
    "addr:postcode":"98686",
    "addr:street":"Ne 28Th Ave",
    "iso:country":"US",
    "sg:address":"15422 NE 28th Ave",
    "sg:city":"Vancouver",
    "sg:classifiers":[
        {
            "category":"Professional",
            "type":"Services"
        }
    ],
    "sg:phone":"+1 360 910 0144",
    "sg:postcode":"98686",
    "sg:province":"WA",
    "wof:name":"Arv Slumwear",
    "wof:placetype":"venue"
},
  "geometry": {"coordinates":[-122.642261,45.734782],"type":"Point"}
}