{
  "type": "Feature",
  "properties": {
    "addr:full":"7728 47th Ave NE Marysville WA 98270",
    "addr:housenumber":"7728",
    "addr:postcode":"98270",
    "addr:street":"47Th Ave Ne",
    "iso:country":"US",
    "sg:address":"7728 47th Ave NE",
    "sg:city":"Marysville",
    "sg:classifiers":[
        {
            "category":"Home & Garden",
            "subcategory":"Furniture",
            "type":"Retail Goods"
        }
    ],
    "sg:phone":"+1 360 659 7500",
    "sg:postcode":"98270",
    "sg:province":"WA",
    "wof:name":"Chets Cabinets",
    "wof:placetype":"venue"
},
  "geometry": {"coordinates":[-122.16775800000001,48.068252],"type":"Point"}
}