{
  "type": "Feature",
  "properties": {
    "addr:full":"430 E 25th St Tacoma WA 98421",
    "addr:housenumber":"430",
    "addr:postcode":"98421",
    "addr:street":"E 25Th St",
    "iso:country":"US",
    "sg:address":"430 E 25th St",
    "sg:city":"Tacoma",
    "sg:classifiers":[
        {
            "category":"Shopping",
            "subcategory":"Department Store",
            "type":"Retail Goods"
        }
    ],
    "sg:phone":"+1 253 305 0678",
    "sg:postcode":"98421",
    "sg:province":"WA",
    "wof:name":"Freighthouse Square",
    "wof:placetype":"venue"
},
  "geometry": {"coordinates":[-122.428045,47.239696],"type":"Point"}
}