{
  "type": "Feature",
  "properties": {
    "addr:full":"3207 Walnut Ave SW Seattle WA 98116",
    "addr:housenumber":"3207",
    "addr:postcode":"98116",
    "addr:street":"Walnut Ave Sw",
    "iso:country":"US",
    "sg:address":"3207 Walnut Ave SW",
    "sg:city":"Seattle",
    "sg:classifiers":[
        {
            "category":"Shopping",
            "type":"Retail Goods"
        }
    ],
    "sg:phone":"+1 206 262 1059",
    "sg:postcode":"98116",
    "sg:province":"WA",
    "sg:tags":[
        "merchandise"
    ],
    "wof:name":"Dog Scooter",
    "wof:placetype":"venue"
},
  "geometry": {"coordinates":[-122.383655,47.573233],"type":"Point"}
}