{
  "type": "Feature",
  "properties": {
    "addr:full":"12712 E Skyview Ave Spokane WA 99216",
    "addr:housenumber":"12712",
    "addr:postcode":"99216",
    "addr:street":"E Skyview Ave",
    "iso:country":"US",
    "sg:address":"12712 E Skyview Ave",
    "sg:city":"Spokane",
    "sg:classifiers":[
        {
            "category":"Shopping",
            "subcategory":"Computers & Home Electronics",
            "type":"Retail Goods"
        }
    ],
    "sg:phone":"+1 509 928 1227",
    "sg:postcode":"99216",
    "sg:province":"WA",
    "wof:name":"Computers Plus",
    "wof:placetype":"venue"
},
  "geometry": {"coordinates":[-117.234056,47.630721],"type":"Point"}
}