{
  "type": "Feature",
  "properties": {
    "iso:country":"US",
    "sg:address":"3522 6th St SE",
    "sg:city":"Olympia",
    "sg:classifiers":[
        {
            "category":"Building & Trades",
            "subcategory":"Construction",
            "type":"Services"
        }
    ],
    "sg:phone":"+1 360 943 1161",
    "sg:postcode":"98501",
    "sg:province":"WA",
    "sg:tags":[
        "general",
        "contractor"
    ],
    "wof:name":"Orland's Remodeling",
    "wof:placetype":"venue"
},
  "geometry": {"coordinates":[-122.846608,47.040347],"type":"Point"}
}