{
  "type": "Feature",
  "properties": {
    "addr:full":"6200 Fair Oaks Rd SE Olympia WA 98513",
    "addr:housenumber":"6200",
    "addr:postcode":"olympia;98513",
    "addr:street":"Fair Oaks Rd Se",
    "iso:country":"US",
    "sg:address":"6200 Fair Oaks Rd SE",
    "sg:city":"Olympia",
    "sg:classifiers":[
        {
            "category":"Professional",
            "subcategory":"Business Services",
            "type":"Services"
        }
    ],
    "sg:phone":"+1 360 455 1606",
    "sg:postcode":"98513",
    "sg:province":"WA",
    "wof:name":"Mickelson Enterprises",
    "wof:placetype":"venue"
},
  "geometry": {"coordinates":[-122.77757099999999,46.988186],"type":"Point"}
}