{
  "type": "Feature",
  "properties": {
    "addr:full":"25308 168th Pl SE Kent WA 98042",
    "addr:housenumber":"25308",
    "addr:postcode":"98042",
    "addr:street":"168Th Pl Se",
    "iso:country":"US",
    "sg:address":"25308 168th Pl SE",
    "sg:city":"Kent",
    "sg:classifiers":[
        {
            "category":"Professional",
            "type":"Services"
        }
    ],
    "sg:phone":"+1 253 639 9289",
    "sg:postcode":"98042",
    "sg:province":"WA",
    "wof:name":"D & D Creations",
    "wof:placetype":"venue"
},
  "geometry": {"coordinates":[-122.11707,47.374705],"type":"Point"}
}