{
  "type": "Feature",
  "properties": {
    "addr:full":"4309 E Valley Hwy E Sumner WA 98390",
    "addr:housenumber":"4309",
    "addr:postcode":"98390",
    "addr:street":"E Valley Hwy E",
    "iso:country":"US",
    "sg:address":"4309 E Valley Hwy E",
    "sg:city":"Sumner",
    "sg:classifiers":[
        {
            "category":"Autos & Motor Vehicles",
            "subcategory":"Recreational Vehicle Sales",
            "type":"Retail Goods"
        }
    ],
    "sg:phone":"+1 253 863 5644",
    "sg:postcode":"98390",
    "sg:province":"WA",
    "sg:tags":[
        "travel",
        "parts",
        "trailer"
    ],
    "wof:name":"Sumner Rv Center",
    "wof:placetype":"venue"
},
  "geometry": {"coordinates":[-122.22732600000001,47.22354],"type":"Point"}
}