{
  "type": "Feature",
  "properties": {
    "iso:country":"US",
    "sg:address":"91 Pine St",
    "sg:city":"Okanogan",
    "sg:classifiers":[
        {
            "category":"Home & Garden",
            "subcategory":"Home Furnishings",
            "type":"Retail Goods"
        }
    ],
    "sg:phone":"+1 509 422 2703",
    "sg:postcode":"98840",
    "sg:province":"WA",
    "wof:name":"House Of Shades",
    "wof:placetype":"venue"
},
  "geometry": {"coordinates":[-119.57907,48.363004],"type":"Point"}
}