{
  "type": "Feature",
  "properties": {
    "addr:full":"3018 80th Street Ct S Tacoma WA 98499",
    "addr:housenumber":"3018",
    "addr:postcode":"98499",
    "addr:street":"80Th Street Ct S",
    "iso:country":"US",
    "sg:address":"3018 80th Street Ct S",
    "sg:city":"Tacoma",
    "sg:classifiers":[
        {
            "category":"Building & Trades",
            "subcategory":"Cleaning & Sanitation",
            "type":"Services"
        }
    ],
    "sg:phone":"+1 253 677 0213",
    "sg:postcode":"98499",
    "sg:province":"WA",
    "sg:tags":[
        "house"
    ],
    "wof:name":"Clean As A Whistle Cleaning",
    "wof:placetype":"venue"
},
  "geometry": {"coordinates":[-122.47474,47.184461],"type":"Point"}
}