{
  "type": "Feature",
  "properties": {
    "addr:full":"5608 6th Ave S Seattle WA 98108",
    "addr:housenumber":"5608",
    "addr:postcode":"98108",
    "addr:street":"6Th Ave S",
    "iso:country":"US",
    "sg:address":"5608 6th Ave S",
    "sg:city":"Seattle",
    "sg:classifiers":[
        {
            "category":"Wholesale",
            "subcategory":"Furniture",
            "type":"Manufacturing & Wholesale Goods"
        }
    ],
    "sg:phone":"+1 206 762 9266",
    "sg:postcode":"98108",
    "sg:province":"WA",
    "wof:name":"Cornerstone Corp Intl",
    "wof:placetype":"venue"
},
  "geometry": {"coordinates":[-122.32679,47.551922],"type":"Point"}
}