{
  "type": "Feature",
  "properties": {
    "addr:full":"1300 E Sunset Dr Bellingham WA 98226",
    "addr:housenumber":"1300",
    "addr:postcode":"98226",
    "addr:street":"E Sunset Dr",
    "iso:country":"US",
    "sg:address":"1300 E Sunset Dr",
    "sg:city":"Bellingham",
    "sg:classifiers":[
        {
            "category":"Autos & Motor Vehicles",
            "subcategory":"Fuel & Gas Station",
            "type":"Retail Goods"
        }
    ],
    "sg:phone":"+1 360 738 7240",
    "sg:postcode":"98226",
    "sg:province":"WA",
    "sg:tags":[
        "station",
        "gasoline"
    ],
    "wof:name":"Sunset Food Mart",
    "wof:placetype":"venue"
},
  "geometry": {"coordinates":[-122.45554,48.773982],"type":"Point"}
}