{
  "type": "Feature",
  "properties": {
    "addr:full":"13206 Bothell Everett Hwy Bothell WA 98012",
    "addr:housenumber":"13206",
    "addr:postcode":"98012",
    "addr:street":"Bothell Everett Hwy",
    "iso:country":"US",
    "sg:address":"13206 Bothell Everett Hwy",
    "sg:city":"Bothell",
    "sg:classifiers":[
        {
            "category":"Restaurant",
            "type":"Food & Drink"
        }
    ],
    "sg:menulink":"http://www.allmenus.com/wa/everett/62900-sushi-zen/menu/",
    "sg:phone":"+1 425 357 1611",
    "sg:postcode":"98012",
    "sg:province":"WA",
    "sg:tags":[
        "japanese",
        "asian"
    ],
    "wof:name":"Sushi Zen",
    "wof:placetype":"venue"
},
  "geometry": {"coordinates":[-122.211035,47.877198],"type":"Point"}
}