{
  "type": "Feature",
  "properties": {
    "addr:full":"3220 S 296th Pl Auburn WA 98001",
    "addr:housenumber":"3220",
    "addr:postcode":"98001",
    "addr:street":"S 296Th Pl",
    "iso:country":"US",
    "sg:address":"3220 S 296th Pl",
    "sg:city":"Auburn",
    "sg:classifiers":[
        {
            "category":"Professional",
            "type":"Services"
        }
    ],
    "sg:phone":"+1 253 839 3627",
    "sg:postcode":"98001",
    "sg:province":"WA",
    "wof:name":"Donald J Valdez",
    "wof:placetype":"venue"
},
  "geometry": {"coordinates":[-122.290645,47.336459],"type":"Point"}
}