{
  "type": "Feature",
  "properties": {
    "addr:full":"13842 SE 161st Pl Renton WA 98058",
    "addr:postcode":"13842;98058",
    "addr:street":"Se 161St Pl",
    "iso:country":"US",
    "sg:address":"13842 SE 161st Pl",
    "sg:city":"Renton",
    "sg:classifiers":[
        {
            "category":"Professional",
            "subcategory":"Employment Agencies",
            "type":"Services"
        }
    ],
    "sg:phone":"+1 425 226 7954",
    "sg:postcode":"98058",
    "sg:province":"WA",
    "sg:tags":[
        "help",
        "supply"
    ],
    "wof:name":"Manpower",
    "wof:placetype":"venue"
},
  "geometry": {"coordinates":[-122.15554899999999,47.45746],"type":"Point"}
}