{
  "type": "Feature",
  "properties": {
    "addr:full":"1212 D St Bellingham WA 98225",
    "addr:housenumber":"1212",
    "addr:postcode":"98225",
    "addr:street":"D St",
    "iso:country":"US",
    "sg:address":"1212 D St",
    "sg:city":"Bellingham",
    "sg:classifiers":[
        {
            "category":"Freight",
            "type":"Transportation"
        }
    ],
    "sg:phone":"+1 360 733 0100",
    "sg:postcode":"98225",
    "sg:province":"WA",
    "sg:tags":[
        "commercial",
        "storage"
    ],
    "wof:name":"Northwest Recycling Inc",
    "wof:placetype":"venue"
},
  "geometry": {"coordinates":[-122.486001,48.754131],"type":"Point"}
}