{
  "type": "Feature",
  "properties": {
    "addr:full":"2128 N Pines Rd Spokane Valley WA 99206",
    "addr:housenumber":"2128",
    "addr:postcode":"99206",
    "addr:street":"N Pines Rd",
    "iso:country":"US",
    "sg:address":"2128 N Pines Rd",
    "sg:city":"Spokane Valley",
    "sg:classifiers":[
        {
            "category":"Wholesale",
            "subcategory":"Electrical",
            "type":"Manufacturing & Wholesale Goods"
        }
    ],
    "sg:phone":"+1 509 228 9934",
    "sg:postcode":"99206",
    "sg:province":"WA",
    "sg:tags":[
        "electronic",
        "telecommunication"
    ],
    "wof:name":"Valere Power",
    "wof:placetype":"venue"
},
  "geometry": {"coordinates":[-117.239541,47.677199],"type":"Point"}
}