{
  "type": "Feature",
  "properties": {
    "addr:full":"12005 S Spotted Rd Cheney WA 99004",
    "addr:housenumber":"12005",
    "addr:postcode":"99004",
    "addr:street":"S Spotted Rd",
    "iso:country":"US",
    "sg:address":"12005 S Spotted Rd",
    "sg:city":"Cheney",
    "sg:classifiers":[
        {
            "category":"Personal",
            "type":"Services"
        }
    ],
    "sg:phone":"+1 509 455 6857",
    "sg:postcode":"99004",
    "sg:province":"WA",
    "wof:name":"Making Lemonade Designs",
    "wof:placetype":"venue"
},
  "geometry": {"coordinates":[-117.518367,47.544074],"type":"Point"}
}