{
  "type": "Feature",
  "properties": {
    "addr:full":"9021 Ridgeview Cir W University Place WA 98466",
    "addr:housenumber":"9021",
    "addr:postcode":"98466",
    "addr:street":"Ridgeview Cir W;Place",
    "iso:country":"US",
    "sg:address":"9021 Ridgeview Cir W",
    "sg:city":"University Place",
    "sg:classifiers":[
        {
            "category":"Professional",
            "subcategory":"Management & Consulting",
            "type":"Services"
        }
    ],
    "sg:phone":"+1 253 460 8397",
    "sg:postcode":"98466",
    "sg:province":"WA",
    "sg:tags":[
        "consultant",
        "business"
    ],
    "wof:name":"Hays Granvil CFP",
    "wof:placetype":"venue"
},
  "geometry": {"coordinates":[-122.558725,47.21514],"type":"Point"}
}