{
  "type": "Feature",
  "properties": {
    "addr:full":"520 Pike St Ste 1520 Seattle WA 98101",
    "addr:housenumber":"520",
    "addr:postcode":"98101",
    "addr:street":"Pike St Ste 1520",
    "iso:country":"US",
    "sg:address":"520 Pike St Ste 1520",
    "sg:city":"Seattle",
    "sg:classifiers":[
        {
            "category":"Professional",
            "subcategory":"Lawyer & Legal Services",
            "type":"Services"
        }
    ],
    "sg:phone":"+1 206 622 6562",
    "sg:postcode":"98101",
    "sg:province":"WA",
    "sg:tags":[
        "attorney",
        "practice"
    ],
    "wof:name":"Sara S Kim",
    "wof:placetype":"venue"
},
  "geometry": {"coordinates":[-122.33540499999999,47.610771],"type":"Point"}
}