{
  "type": "Feature",
  "properties": {
    "addr:full":"212 N Chelan Ave Wenatchee WA 98801",
    "addr:housenumber":"212",
    "addr:postcode":"98801",
    "addr:street":"N Chelan Ave",
    "iso:country":"US",
    "sg:address":"212 N Chelan Ave",
    "sg:city":"Wenatchee",
    "sg:classifiers":[
        {
            "category":"Professional",
            "subcategory":"Lawyer & Legal Services",
            "type":"Services"
        }
    ],
    "sg:phone":"+1 509 663 1879",
    "sg:postcode":"98801",
    "sg:province":"WA",
    "sg:tags":[
        "attorney",
        "law",
        "family",
        "duo",
        "elder",
        "criminal",
        "dwi"
    ],
    "sg:website":"http://www.bellwenatchee.com",
    "wof:name":"Bell Law Firm",
    "wof:placetype":"venue"
},
  "geometry": {"coordinates":[-120.316093,47.426476],"type":"Point"}
}