{
  "type": "Feature",
  "properties": {
    "addr:full":"11301 5th Avenue NE Seattle WA 98125",
    "addr:housenumber":"11301",
    "addr:postcode":"98125",
    "addr:street":"5Th Avenue Ne",
    "iso:country":"US",
    "sg:address":"11301 5th Avenue NE",
    "sg:city":"Seattle",
    "sg:classifiers":[
        {
            "category":"Health Services",
            "subcategory":"Health Practitioner",
            "type":"Services"
        }
    ],
    "sg:phone":"+1 206 361 0108",
    "sg:postcode":"98125",
    "sg:province":"WA",
    "sg:tags":[
        "acupuncture",
        "medicine",
        "alternative"
    ],
    "wof:name":"International Clinic For Acupuncture and Holistic Medicine",
    "wof:placetype":"venue"
},
  "geometry": {"coordinates":[-122.32332599999999,47.710839],"type":"Point"}
}