{
  "type": "Feature",
  "properties": {
    "addr:full":"1325 4th Ave Ste 210 Seattle WA 98101",
    "addr:housenumber":"1325",
    "addr:postcode":"98101",
    "addr:street":"4Th Ave Ste 210",
    "iso:country":"US",
    "sg:address":"1325 4th Ave Ste 210",
    "sg:city":"Seattle",
    "sg:phone":"+1 206 682 8676",
    "sg:postcode":"98101",
    "sg:province":"WA",
    "sg:website":"http://www.seattledentalassociates.com",
    "wof:name":"Barnes, Dexter E, Dds - Seattle Dental Assoc",
    "wof:placetype":"venue"
},
  "geometry": {"coordinates":[-122.335097,47.608444],"type":"Point"}
}