{
  "type": "Feature",
  "properties": {
    "addr:full":"15050 Van Ave SE Monroe WA 98272",
    "addr:housenumber":"15050",
    "addr:postcode":"98272",
    "addr:street":"Van Ave Se",
    "iso:country":"US",
    "sg:address":"15050 Van Ave SE",
    "sg:city":"Monroe",
    "sg:classifiers":[
        {
            "category":"Building & Trades",
            "subcategory":"Construction",
            "type":"Services"
        }
    ],
    "sg:phone":"+1 360 794 9493",
    "sg:postcode":"98272",
    "sg:province":"WA",
    "sg:tags":[
        "contractor"
    ],
    "wof:name":"Parker Michael John",
    "wof:placetype":"venue"
},
  "geometry": {"coordinates":[-122.00601899999999,47.860523],"type":"Point"}
}