{
  "type": "Feature",
  "properties": {
    "addr:full":"3056 Alki Ave SW Seattle WA 98116",
    "addr:housenumber":"3056",
    "addr:postcode":"98116",
    "addr:street":"Alki Ave Sw",
    "iso:country":"US",
    "sg:address":"3056 Alki Ave SW",
    "sg:city":"Seattle",
    "sg:classifiers":[
        {
            "category":"Professional",
            "subcategory":"Business Services",
            "type":"Services"
        }
    ],
    "sg:phone":"+1 206 937 4825",
    "sg:postcode":"98116",
    "sg:province":"WA",
    "wof:name":"Habitat Design",
    "wof:placetype":"venue"
},
  "geometry": {"coordinates":[-122.41835399999999,47.576938],"type":"Point"}
}