{
  "type": "Feature",
  "properties": {
    "addr:full":"1414 Griffin Ave Enumclaw WA 98022",
    "addr:housenumber":"1414",
    "addr:postcode":"98022",
    "addr:street":"Griffin Ave",
    "iso:country":"US",
    "sg:address":"1414 Griffin Ave",
    "sg:city":"Enumclaw",
    "sg:classifiers":[
        {
            "category":"Education",
            "subcategory":"College",
            "type":"Public Place"
        }
    ],
    "sg:phone":"+1 253 288 3400",
    "sg:postcode":"98022",
    "sg:province":"WA",
    "sg:tags":[
        "academic",
        "school"
    ],
    "wof:name":"Green River Community College",
    "wof:placetype":"venue"
},
  "geometry": {"coordinates":[-121.99169000000001,47.204445],"type":"Point"}
}