{
  "type": "Feature",
  "properties": {
    "iso:country":"US",
    "sg:address":"3607 W Nob Hill Blvd",
    "sg:city":"Yakima",
    "sg:classifiers":[
        {
            "category":"Restaurant",
            "type":"Food & Drink"
        }
    ],
    "sg:phone":"+1 509 453 8646",
    "sg:postcode":"98902",
    "sg:province":"WA",
    "sg:tags":[
        "eating"
    ],
    "wof:name":"El Porton Express",
    "wof:placetype":"venue"
},
  "geometry": {"coordinates":[-120.55726900000001,46.585516],"type":"Point"}
}