{
  "type": "Feature",
  "properties": {
    "addr:full":"120 N 79th Street Seattle WA 98103",
    "addr:housenumber":"120",
    "addr:postcode":"98103",
    "addr:street":"N 79Th Street",
    "iso:country":"US",
    "sg:address":"120 N 79th Street",
    "sg:city":"Seattle",
    "sg:classifiers":[
        {
            "category":"Education",
            "subcategory":"School",
            "type":"Public Place"
        }
    ],
    "sg:phone":"+1 206 783 0337",
    "sg:postcode":"98103",
    "sg:province":"WA",
    "sg:tags":[
        "high",
        "middle",
        "elementary"
    ],
    "wof:name":"St John Catholic Church",
    "wof:placetype":"venue"
},
  "geometry": {"coordinates":[-122.35740699999999,47.686076],"type":"Point"}
}