{
  "type": "Feature",
  "properties": {
    "addr:full":"1208 S I St Tacoma WA 98405",
    "addr:housenumber":"1208",
    "addr:postcode":"98405",
    "addr:street":"S I St",
    "iso:country":"US",
    "sg:address":"1208 S I St",
    "sg:city":"Tacoma",
    "sg:classifiers":[
        {
            "category":"Social Services",
            "subcategory":"Child Care",
            "type":"Services"
        }
    ],
    "sg:phone":"+1 253 274 1100",
    "sg:postcode":"98405",
    "sg:province":"WA",
    "sg:tags":[
        "day"
    ],
    "wof:name":"Lily Of The Valley Childcare",
    "wof:placetype":"venue"
},
  "geometry": {"coordinates":[-122.44847799999999,47.250316],"type":"Point"}
}