{
  "type": "Feature",
  "properties": {
    "addr:full":"812 39th Ave SW Puyallup WA 98373",
    "addr:housenumber":"812",
    "addr:postcode":"98373",
    "addr:street":"39Th Ave Sw",
    "iso:country":"US",
    "sg:address":"812 39th Ave SW",
    "sg:city":"Puyallup",
    "sg:classifiers":[
        {
            "category":"Education",
            "subcategory":"Special Training",
            "type":"Public Place"
        }
    ],
    "sg:phone":"+1 253 840 8450",
    "sg:postcode":"98373",
    "sg:province":"WA",
    "sg:tags":[
        "center"
    ],
    "wof:name":"Community Education",
    "wof:placetype":"venue"
},
  "geometry": {"coordinates":[-122.302324,47.154762],"type":"Point"}
}