{
  "type": "Feature",
  "properties": {
    "addr:full":"8185 Stein Rd Custer WA 98240",
    "addr:housenumber":"8185",
    "addr:postcode":"98240",
    "addr:street":"Stein Rd",
    "iso:country":"US",
    "sg:address":"8185 Stein Rd",
    "sg:city":"Custer",
    "sg:classifiers":[
        {
            "category":"Retail",
            "subcategory":"Animal Services",
            "type":"Services"
        }
    ],
    "sg:phone":"+1 360 366 4709",
    "sg:postcode":"98240",
    "sg:province":"WA",
    "wof:name":"Custer Kennels",
    "wof:placetype":"venue"
},
  "geometry": {"coordinates":[-122.627258,48.935809],"type":"Point"}
}