{
  "type": "Feature",
  "properties": {
    "addr:full":"2018 E Mission Ave Spokane WA 99202",
    "addr:housenumber":"2018",
    "addr:postcode":"99202",
    "addr:street":"E Mission Ave",
    "iso:country":"US",
    "sg:address":"2018 E Mission Ave",
    "sg:city":"Spokane",
    "sg:classifiers":[
        {
            "category":"Professional",
            "subcategory":"Management & Consulting",
            "type":"Services"
        }
    ],
    "sg:phone":"+1 509 532 1259",
    "sg:postcode":"99202",
    "sg:province":"WA",
    "sg:tags":[
        "business"
    ],
    "wof:name":"Pharmaceutical Validation Svc",
    "wof:placetype":"venue"
},
  "geometry": {"coordinates":[-117.379673,47.671844],"type":"Point"}
}