{
  "type": "Feature",
  "properties": {
    "addr:full":"7107 Greenwood Ave N Ste C Seattle WA 98103",
    "addr:housenumber":"7107",
    "addr:postcode":"98103",
    "addr:street":"Greenwood Ave N Ste C",
    "iso:country":"US",
    "sg:address":"7107 Greenwood Ave N Ste C",
    "sg:city":"Seattle",
    "sg:classifiers":[
        {
            "category":"Personal",
            "subcategory":"Hair Removal",
            "type":"Services"
        },
        {
            "category":"Personal",
            "subcategory":"Skin Care",
            "type":"Services"
        }
    ],
    "sg:phone":"+1 206 380 6754",
    "sg:postcode":"98103",
    "sg:province":"WA",
    "sg:website":"www.babyfacespa.com",
    "wof:name":"Babyface Skincare and Body Sugaring",
    "wof:placetype":"venue"
},
  "geometry": {"coordinates":[-122.355418,47.680643],"type":"Point"}
}