{
  "type": "Feature",
  "properties": {
    "addr:full":"200 SW Mountain View St Pullman WA 99163",
    "addr:housenumber":"200",
    "addr:postcode":"99163",
    "addr:street":"Sw Mountain View St",
    "iso:country":"US",
    "sg:address":"200 SW Mountain View St",
    "sg:city":"Pullman",
    "sg:classifiers":[
        {
            "category":"Government",
            "subcategory":"Office",
            "type":"Public Place"
        }
    ],
    "sg:phone":"+1 509 332 2012",
    "sg:postcode":"99163",
    "sg:province":"WA",
    "sg:tags":[
        "housing",
        "program"
    ],
    "wof:name":"Washington Beta Building",
    "wof:placetype":"venue"
},
  "geometry": {"coordinates":[-117.187112,46.72434],"type":"Point"}
}