{
  "type": "Feature",
  "properties": {
    "iso:country":"US",
    "sg:address":"19214 140th Ave SE",
    "sg:city":"Renton",
    "sg:classifiers":[
        {
            "category":"Manufacturing",
            "subcategory":"Tools & Machinery",
            "type":"Manufacturing & Wholesale Goods"
        }
    ],
    "sg:phone":"+1 253 630 3126",
    "sg:postcode":"98058",
    "sg:province":"WA",
    "sg:tags":[
        "model",
        "maker"
    ],
    "wof:name":"Accurate Models",
    "wof:placetype":"venue"
},
  "geometry": {"coordinates":[-122.15448000000001,47.42835],"type":"Point"}
}