{
  "type": "Feature",
  "properties": {
    "addr:full":"17048 155th St SE Monroe WA 98272",
    "addr:housenumber":"17048",
    "addr:postcode":"98272",
    "addr:street":"155Th St Se",
    "iso:country":"US",
    "sg:address":"17048 155th St SE",
    "sg:city":"Monroe",
    "sg:classifiers":[
        {
            "category":"Professional",
            "subcategory":"Computer Services",
            "type":"Services"
        }
    ],
    "sg:phone":"+1 360 805 8300",
    "sg:postcode":"98272",
    "sg:province":"WA",
    "sg:tags":[
        "related"
    ],
    "wof:name":"System Integration Partners",
    "wof:placetype":"venue"
},
  "geometry": {"coordinates":[-122.002325,47.856338],"type":"Point"}
}