{
  "type": "Feature",
  "properties": {
    "addr:full":"31 Bay View St Sequim WA 98382",
    "addr:housenumber":"31",
    "addr:postcode":"98382",
    "addr:street":"Bay View St",
    "iso:country":"US",
    "sg:address":"31 Bay View St",
    "sg:city":"Sequim",
    "sg:classifiers":[
        {
            "category":"Professional",
            "type":"Services"
        }
    ],
    "sg:phone":"+1 360 582 0707",
    "sg:postcode":"98382",
    "sg:province":"WA",
    "sg:tags":[
        "establishment"
    ],
    "wof:name":"Diamond Power",
    "wof:placetype":"venue"
},
  "geometry": {"coordinates":[-123.178353,48.14334],"type":"Point"}
}