{
  "type": "Feature",
  "properties": {
    "addr:full":"31711 SE 17th St Washougal WA 98671",
    "addr:postcode":"31711;98671",
    "addr:street":"Se 17Th St",
    "iso:country":"US",
    "sg:address":"31711 SE 17th St",
    "sg:city":"Washougal",
    "sg:classifiers":[
        {
            "category":"Manufacturing",
            "subcategory":"Paper Products",
            "type":"Manufacturing & Wholesale Goods"
        }
    ],
    "sg:phone":"+1 360 335 0600",
    "sg:postcode":"98671",
    "sg:province":"WA",
    "sg:tags":[
        "machine",
        "cutting",
        "drilling"
    ],
    "wof:name":"Jim Ochs & Assoc Inc",
    "wof:placetype":"venue"
},
  "geometry": {"coordinates":[-122.348546,45.60962],"type":"Point"}
}