{
  "type": "Feature",
  "properties": {
    "addr:full":"640 228th Ave NE Sammamish WA 98074",
    "addr:housenumber":"640",
    "addr:postcode":"98074",
    "addr:street":"228Th Ave Ne",
    "iso:country":"US",
    "sg:address":"640 228th Ave NE",
    "sg:city":"Sammamish",
    "sg:classifiers":[
        {
            "category":"Banks & Credit Unions",
            "subcategory":"Bank",
            "type":"Services"
        }
    ],
    "sg:phone":"+1 425 450 5775",
    "sg:postcode":"98074",
    "sg:province":"WA",
    "sg:tags":[
        "national",
        "commercial"
    ],
    "wof:name":"US Bancorp",
    "wof:placetype":"venue"
},
  "geometry": {"coordinates":[-122.035389,47.613834],"type":"Point"}
}