{
  "type": "Feature",
  "properties": {
    "addr:full":"817 E Market St Aberdeen WA 98520",
    "addr:housenumber":"817",
    "addr:postcode":"98520",
    "addr:street":"E Market St",
    "iso:country":"US",
    "sg:address":"817 E Market St",
    "sg:city":"Aberdeen",
    "sg:classifiers":[
        {
            "category":"Retail",
            "subcategory":"Auto Repair",
            "type":"Services"
        }
    ],
    "sg:phone":"+1 360 538 9999",
    "sg:postcode":"98520",
    "sg:province":"WA",
    "sg:tags":[
        "repairing",
        "automobile"
    ],
    "wof:name":"Pro Quality Disc Break Muffler",
    "wof:placetype":"venue"
},
  "geometry": {"coordinates":[-123.80968,46.979849],"type":"Point"}
}