{
  "type": "Feature",
  "properties": {
    "addr:full":"22640 Russell Rd Kent WA 98032",
    "addr:housenumber":"22640",
    "addr:postcode":"98032",
    "addr:street":"Russell Rd",
    "iso:country":"US",
    "sg:address":"22640 Russell Rd",
    "sg:city":"Kent",
    "sg:classifiers":[
        {
            "category":"Wholesale",
            "subcategory":"Hardware",
            "type":"Manufacturing & Wholesale Goods"
        }
    ],
    "sg:phone":"+1 253 859 2133",
    "sg:postcode":"98032",
    "sg:province":"WA",
    "sg:tags":[
        "steel",
        "stainless",
        "fastener",
        "corporation"
    ],
    "wof:name":"Star Stainless Screw Co",
    "wof:placetype":"venue"
},
  "geometry": {"coordinates":[-122.27461700000001,47.399937],"type":"Point"}
}