{
  "type": "Feature",
  "properties": {
    "addr:full":"2005 Cottage Rd E Sumner WA 98390",
    "addr:housenumber":"2005",
    "addr:postcode":"98390",
    "addr:street":"Cottage Rd E",
    "iso:country":"US",
    "sg:address":"2005 Cottage Rd E",
    "sg:city":"Sumner",
    "sg:classifiers":[
        {
            "category":"Freight",
            "type":"Transportation"
        }
    ],
    "sg:phone":"+1 360 662 0222",
    "sg:postcode":"98390",
    "sg:province":"WA",
    "wof:name":"Arrow Transportation",
    "wof:placetype":"venue"
},
  "geometry": {"coordinates":[-122.22258100000001,47.238539],"type":"Point"}
}