{
  "type": "Feature",
  "properties": {
    "addr:full":"3535 Factoria Blvd SE Ste 200 Bellevue WA 98006",
    "addr:housenumber":"3535",
    "addr:postcode":"98006",
    "addr:street":"Factoria Blvd Se Ste 200",
    "iso:country":"US",
    "sg:address":"3535 Factoria Blvd SE Ste 200",
    "sg:city":"Bellevue",
    "sg:classifiers":[
        {
            "category":"Professional",
            "subcategory":"Lawyer & Legal Services",
            "type":"Services"
        }
    ],
    "sg:phone":"+1 425 586 1900",
    "sg:postcode":"98006",
    "sg:province":"WA",
    "wof:name":"Routh Crabtree Fennell Cpc",
    "wof:placetype":"venue"
},
  "geometry": {"coordinates":[-122.168999,47.579899],"type":"Point"}
}