{
  "type": "Feature",
  "properties": {
    "addr:full":"8625 5th Ave NE Seattle WA 98115",
    "addr:housenumber":"8625",
    "addr:postcode":"98115",
    "addr:street":"5Th Ave Ne",
    "iso:country":"US",
    "sg:address":"8625 5th Ave NE",
    "sg:city":"Seattle",
    "sg:classifiers":[
        {
            "category":"Building & Trades",
            "subcategory":"Plumbing",
            "type":"Services"
        }
    ],
    "sg:phone":"+1 206 524 9965",
    "sg:postcode":"98115",
    "sg:province":"WA",
    "sg:tags":[
        "water",
        "gas",
        "furnace",
        "fireplace",
        "installation"
    ],
    "wof:name":"Rays Heating & Cooling",
    "wof:placetype":"venue"
},
  "geometry": {"coordinates":[-122.323081,47.690541],"type":"Point"}
}