{
  "type": "Feature",
  "properties": {
    "addr:full":"23320 57th Ave SE Woodinville WA 98072",
    "addr:housenumber":"23320",
    "addr:postcode":"98072",
    "addr:street":"57Th Ave Se",
    "iso:country":"US",
    "sg:address":"23320 57th Ave SE",
    "sg:city":"Woodinville",
    "sg:classifiers":[
        {
            "category":"Retail",
            "subcategory":"Auto Repair",
            "type":"Services"
        }
    ],
    "sg:phone":"+1 425 483 1290",
    "sg:postcode":"98072",
    "sg:province":"WA",
    "sg:tags":[
        "general"
    ],
    "wof:name":"High Tech Imports",
    "wof:placetype":"venue"
},
  "geometry": {"coordinates":[-122.15685000000001,47.786822],"type":"Point"}
}