{
  "type": "Feature",
  "properties": {
    "addr:full":"3216 E Portland Ave Tacoma WA 98404",
    "addr:housenumber":"3216",
    "addr:postcode":"98404",
    "addr:street":"E Portland Ave",
    "iso:country":"US",
    "sg:address":"3216 E Portland Ave",
    "sg:city":"Tacoma",
    "sg:classifiers":[
        {
            "category":"Home & Garden",
            "subcategory":"Hardware",
            "type":"Retail Goods"
        }
    ],
    "sg:phone":"+1 253 779 4160",
    "sg:postcode":"98404",
    "sg:province":"WA",
    "sg:tags":[
        "water",
        "equipment",
        "filtration",
        "purification"
    ],
    "wof:name":"Tmg Services, Inc.",
    "wof:placetype":"venue"
},
  "geometry": {"coordinates":[-122.40948400000001,47.234589],"type":"Point"}
}