{
  "type": "Feature",
  "properties": {
    "addr:full":"18505 51st Ave SE Bothell WA 98012",
    "addr:housenumber":"18505",
    "addr:postcode":"98012",
    "addr:street":"51St Ave Se",
    "iso:country":"US",
    "sg:address":"18505 51st Ave SE",
    "sg:city":"Bothell",
    "sg:classifiers":[
        {
            "category":"Building & Trades",
            "subcategory":"Landscaping Services",
            "type":"Services"
        }
    ],
    "sg:phone":"+1 425 402 6781",
    "sg:postcode":"98012",
    "sg:province":"WA",
    "sg:tags":[
        "construction",
        "landscape",
        "deck"
    ],
    "wof:name":"Design Scapes",
    "wof:placetype":"venue"
},
  "geometry": {"coordinates":[-122.164154,47.828837],"type":"Point"}
}