{
  "type": "Feature",
  "properties": {
    "addr:full":"901 E 7th Ave Ellensburg WA 98926",
    "addr:housenumber":"901",
    "addr:postcode":"98926",
    "addr:street":"E 7Th Ave",
    "iso:country":"US",
    "sg:address":"901 E 7th Ave",
    "sg:city":"Ellensburg",
    "sg:classifiers":[
        {
            "category":"Government",
            "subcategory":"Office",
            "type":"Public Place"
        }
    ],
    "sg:phone":"+1 509 925 2933",
    "sg:postcode":"98926",
    "sg:province":"WA",
    "sg:tags":[
        "national",
        "security"
    ],
    "wof:name":"Army National Guard",
    "wof:placetype":"venue"
},
  "geometry": {"coordinates":[-120.535383,46.998865],"type":"Point"}
}