{
  "type": "Feature",
  "properties": {
    "addr:full":"2975 Manson Blvd Manson WA 98831",
    "addr:housenumber":"2975",
    "addr:postcode":"98831",
    "addr:street":"Manson Blvd",
    "iso:country":"US",
    "sg:address":"2975 Manson Blvd",
    "sg:city":"Manson",
    "sg:classifiers":[
        {
            "category":"Building & Trades",
            "subcategory":"Construction",
            "type":"Services"
        }
    ],
    "sg:phone":"+1 509 687 3928",
    "sg:postcode":"98831",
    "sg:province":"WA",
    "sg:tags":[
        "general",
        "contractor"
    ],
    "sg:website":"www.chelanvalleybuilders.com",
    "wof:name":"Chelan Valley Builders Inc",
    "wof:placetype":"venue"
},
  "geometry": {"coordinates":[-120.18809,47.907743],"type":"Point"}
}