{
  "type": "Feature",
  "properties": {
    "addr:full":"305 Davie Rd Grandview WA 98930",
    "addr:housenumber":"305",
    "addr:postcode":"98930",
    "addr:street":"Davie Rd",
    "iso:country":"US",
    "sg:address":"305 Davie Rd",
    "sg:city":"Grandview",
    "sg:classifiers":[
        {
            "category":"Building & Trades",
            "subcategory":"Construction",
            "type":"Services"
        }
    ],
    "sg:phone":"+1 509 882 5177",
    "sg:postcode":"98930",
    "sg:province":"WA",
    "sg:tags":[
        "house"
    ],
    "wof:name":"Rodriguez & Sons Construc",
    "wof:placetype":"venue"
},
  "geometry": {"coordinates":[-119.912125,46.260821],"type":"Point"}
}