{
  "type": "Feature",
  "properties": {
    "addr:full":"2522 N Proctor St Tacoma WA 98406",
    "addr:housenumber":"2522",
    "addr:postcode":"98406",
    "addr:street":"N Proctor St",
    "iso:country":"US",
    "sg:address":"2522 N Proctor St",
    "sg:city":"Tacoma",
    "sg:classifiers":[
        {
            "category":"Professional",
            "subcategory":"Business Services",
            "type":"Services"
        }
    ],
    "sg:phone":"+1 253 756 6650",
    "sg:postcode":"98406",
    "sg:province":"WA",
    "sg:tags":[
        "mail",
        "shipping"
    ],
    "sg:website":"http://www.upsstore.com",
    "wof:name":"The UPS Store",
    "wof:placetype":"venue"
},
  "geometry": {"coordinates":[-122.488865,47.270339],"type":"Point"}
}