{
  "type": "Feature",
  "properties": {
    "addr:full":"2442 NW Market St Seattle WA 98107",
    "addr:housenumber":"2442",
    "addr:postcode":"98107",
    "addr:street":"Nw Market St",
    "iso:country":"US",
    "sg:address":"2442 NW Market St",
    "sg:city":"Seattle",
    "sg:classifiers":[
        {
            "category":"Building & Trades",
            "subcategory":"Locksmith",
            "type":"Services"
        }
    ],
    "sg:phone":"+1 206 552 7470",
    "sg:postcode":"98107",
    "sg:province":"WA",
    "sg:tags":[
        "key"
    ],
    "wof:name":"Locksmith",
    "wof:placetype":"venue"
},
  "geometry": {"coordinates":[-122.388137,47.668823],"type":"Point"}
}