{
  "type": "Feature",
  "properties": {
    "addr:full":"421 23rd Avenue S Seattle WA 98144",
    "addr:housenumber":"421",
    "addr:postcode":"98144",
    "addr:street":"23Rd Avenue S",
    "iso:country":"US",
    "sg:address":"421 23rd Avenue S",
    "sg:city":"Seattle",
    "sg:classifiers":[
        {
            "category":"Real Estate",
            "subcategory":"Real Estate Operator",
            "type":"Services"
        }
    ],
    "sg:phone":"+1 206 320 0333",
    "sg:postcode":"98144",
    "sg:province":"WA",
    "sg:tags":[
        "apartment"
    ],
    "wof:name":"Lorig Management Plaza",
    "wof:placetype":"venue"
},
  "geometry": {"coordinates":[-122.302046,47.598857],"type":"Point"}
}