{
  "type": "Feature",
  "properties": {
    "addr:full":"7438 SE 27th St Mercer Island WA 98040",
    "addr:housenumber":"7438",
    "addr:postcode":"98040",
    "addr:street":"Se 27Th St",
    "iso:country":"US",
    "sg:address":"7438 SE 27th St",
    "sg:city":"Mercer Island",
    "sg:classifiers":[
        {
            "category":"Building & Trades",
            "subcategory":"Construction",
            "type":"Services"
        }
    ],
    "sg:phone":"+1 206 230 8500",
    "sg:postcode":"98040",
    "sg:province":"WA",
    "sg:tags":[
        "contractor",
        "commercial",
        "tenant",
        "improvement"
    ],
    "sg:website":"www.expressconstruction.net",
    "wof:name":"Express Construction Co Inc",
    "wof:placetype":"venue"
},
  "geometry": {"coordinates":[-122.236406,47.586811],"type":"Point"}
}