{
  "type": "Feature",
  "properties": {
    "addr:full":"21120 77th Ave S Kent WA 98032",
    "addr:housenumber":"21120",
    "addr:postcode":"98032",
    "addr:street":"77Th Ave S",
    "iso:country":"US",
    "sg:address":"21120 77th Ave S",
    "sg:city":"Kent",
    "sg:classifiers":[
        {
            "category":"Wholesale",
            "subcategory":"Hardware",
            "type":"Manufacturing & Wholesale Goods"
        }
    ],
    "sg:phone":"+1 253 872 4597",
    "sg:postcode":"98032",
    "sg:province":"WA",
    "sg:tags":[
        "fastener"
    ],
    "wof:name":"Fastenal",
    "wof:placetype":"venue"
},
  "geometry": {"coordinates":[-122.23750200000001,47.415],"type":"Point"}
}