{
  "type": "Feature",
  "properties": {
    "addr:full":"1611 116th Ave NE Bellevue WA 98004",
    "addr:housenumber":"1611",
    "addr:postcode":"98004",
    "addr:street":"116Th Ave Ne",
    "iso:country":"US",
    "sg:address":"1611 116th Ave NE",
    "sg:city":"Bellevue",
    "sg:classifiers":[
        {
            "category":"Professional",
            "subcategory":"Lawyer & Legal Services",
            "type":"Services"
        }
    ],
    "sg:phone":"+1 425 462 6132",
    "sg:postcode":"98004",
    "sg:province":"WA",
    "wof:name":"Rehberg & Albertson Law Offs",
    "wof:placetype":"venue"
},
  "geometry": {"coordinates":[-122.185742,47.624581],"type":"Point"}
}