{
  "type": "Feature",
  "properties": {
    "iso:country":"US",
    "sg:address":"12414 SE 173rd Pl",
    "sg:city":"Renton",
    "sg:classifiers":[
        {
            "category":"Professional",
            "subcategory":"Business Services",
            "type":"Services"
        }
    ],
    "sg:phone":"+1 425 226 6767",
    "sg:postcode":"98058",
    "sg:province":"WA",
    "wof:name":"William Reed",
    "wof:placetype":"venue"
},
  "geometry": {"coordinates":[-122.175505,47.447293],"type":"Point"}
}