{
  "type": "Feature",
  "properties": {
    "addr:full":"1502 River Rd Puyallup WA 98371",
    "addr:housenumber":"1502",
    "addr:postcode":"98371",
    "addr:street":"River Rd",
    "iso:country":"US",
    "sg:address":"1502 River Rd",
    "sg:city":"Puyallup",
    "sg:classifiers":[
        {
            "category":"Autos & Motor Vehicles",
            "subcategory":"Automobile Sales",
            "type":"Retail Goods"
        }
    ],
    "sg:phone":"+1 253 435 9101",
    "sg:postcode":"98371",
    "sg:province":"WA",
    "sg:tags":[
        "car",
        "dealer"
    ],
    "wof:name":"Puyallup Motorsport",
    "wof:placetype":"venue"
},
  "geometry": {"coordinates":[-122.31901999999999,47.20603],"type":"Point"}
}