{
  "type": "Feature",
  "properties": {
    "addr:full":"239 NE Midway Blvd Oak Harbor WA 98277",
    "addr:housenumber":"239",
    "addr:postcode":"98277",
    "addr:street":"Ne Midway Blvd",
    "iso:country":"US",
    "sg:address":"239 NE Midway Blvd",
    "sg:city":"Oak Harbor",
    "sg:classifiers":[
        {
            "category":"Building & Trades",
            "subcategory":"Equipment Rental",
            "type":"Services"
        }
    ],
    "sg:phone":"+1 360 679 7927",
    "sg:postcode":"98277",
    "sg:province":"WA",
    "sg:tags":[
        "medical",
        "supply"
    ],
    "wof:name":"Whidbey Patient Aids Inc",
    "wof:placetype":"venue"
},
  "geometry": {"coordinates":[-122.643327,48.300315],"type":"Point"}
}