{
  "type": "Feature",
  "properties": {
    "iso:country":"US",
    "sg:address":"1600 S Roosevelt Ave",
    "sg:city":"Goldendale",
    "sg:classifiers":[
        {
            "category":"Manufacturing",
            "subcategory":"Retail Goods",
            "type":"Manufacturing & Wholesale Goods"
        }
    ],
    "sg:phone":"+1 509 773 6730",
    "sg:postcode":"98620",
    "sg:province":"WA",
    "sg:tags":[
        "product",
        "mfg"
    ],
    "wof:name":"Aladdin Mfg",
    "wof:placetype":"venue"
},
  "geometry": {"coordinates":[-120.812321,45.809333],"type":"Point"}
}