{
  "type": "Feature",
  "properties": {
    "addr:full":"2112 Sumner Ave Aberdeen WA 98520",
    "addr:housenumber":"2112",
    "addr:postcode":"98520",
    "addr:street":"Sumner Ave",
    "iso:country":"US",
    "sg:address":"2112 Sumner Ave",
    "sg:city":"Aberdeen",
    "sg:classifiers":[
        {
            "category":"Food & Beverages",
            "subcategory":"Groceries & Convenience Stores",
            "type":"Retail Goods"
        }
    ],
    "sg:phone":"+1 360 532 9336",
    "sg:postcode":"98520",
    "sg:province":"WA",
    "wof:name":"Parks Mini-Market",
    "wof:placetype":"venue"
},
  "geometry": {"coordinates":[-123.84180499999999,46.97604],"type":"Point"}
}