{
  "type": "Feature",
  "properties": {
    "addr:full":"1702 104th Pl SW Everett WA 98204",
    "addr:housenumber":"1702",
    "addr:postcode":"98204",
    "addr:street":"104Th Pl Sw",
    "iso:country":"US",
    "sg:address":"1702 104th Pl SW",
    "sg:city":"Everett",
    "sg:classifiers":[
        {
            "category":"Real Estate",
            "subcategory":"Real Estate Services",
            "type":"Services"
        },
        {
            "category":"Real Estate",
            "subcategory":"Real Estate Agent",
            "type":"Services"
        }
    ],
    "sg:phone":"+1 425 923 7757",
    "sg:postcode":"98204",
    "sg:province":"WA",
    "sg:tags":[
        "buyer",
        "broker"
    ],
    "wof:name":"Real Estate Guide",
    "wof:placetype":"venue"
},
  "geometry": {"coordinates":[-122.257186,47.904909],"type":"Point"}
}