{
  "type": "Feature",
  "properties": {
    "addr:full":"10206 52nd St SE Snohomish WA 98290",
    "addr:housenumber":"10206",
    "addr:postcode":"98290",
    "addr:street":"52Nd St Se",
    "iso:country":"US",
    "sg:address":"10206 52nd St SE",
    "sg:city":"Snohomish",
    "sg:classifiers":[
        {
            "category":"Building & Trades",
            "subcategory":"Electrical",
            "type":"Services"
        }
    ],
    "sg:phone":"+1 360 568 0881",
    "sg:postcode":"98290",
    "sg:province":"WA",
    "sg:tags":[
        "electric",
        "contractor"
    ],
    "wof:name":"Northland Electric Inc",
    "wof:placetype":"venue"
},
  "geometry": {"coordinates":[-122.09684300000001,47.949149],"type":"Point"}
}