{
  "type": "Feature",
  "properties": {
    "addr:full":"1023 S 2nd St Mount Vernon WA 98273",
    "addr:housenumber":"1023",
    "addr:postcode":"98273",
    "addr:street":"S 2Nd St",
    "iso:country":"US",
    "sg:address":"1023 S 2nd St",
    "sg:city":"Mount Vernon",
    "sg:classifiers":[
        {
            "category":"Food & Beverages",
            "subcategory":"Groceries & Convenience Stores",
            "type":"Retail Goods"
        }
    ],
    "sg:phone":"+1 360 336 5755",
    "sg:postcode":"98273",
    "sg:province":"WA",
    "sg:tags":[
        "grocer",
        "restaurant"
    ],
    "wof:name":"World Market Meats",
    "wof:placetype":"venue"
},
  "geometry": {"coordinates":[-122.337997,48.415401],"type":"Point"}
}