{
  "type": "Feature",
  "properties": {
    "addr:full":"118 W 3rd St Wapato WA 98951",
    "addr:housenumber":"118",
    "addr:postcode":"98951",
    "addr:street":"W 3Rd St",
    "iso:country":"US",
    "sg:address":"118 W 3rd St",
    "sg:city":"Wapato",
    "sg:classifiers":[
        {
            "category":"Retail",
            "subcategory":"Auto Repair",
            "type":"Services"
        }
    ],
    "sg:phone":"+1 509 877 6380",
    "sg:postcode":"98951",
    "sg:province":"WA",
    "sg:tags":[
        "body",
        "automobile",
        "painting"
    ],
    "wof:name":"Bennett's Collision Ctr",
    "wof:placetype":"venue"
},
  "geometry": {"coordinates":[-120.42104500000001,46.446089],"type":"Point"}
}