{
  "type": "Feature",
  "properties": {
    "iso:country":"US",
    "sg:address":"815 E Main St",
    "sg:city":"Auburn",
    "sg:classifiers":[
        {
            "category":"Personal",
            "type":"Services"
        }
    ],
    "sg:phone":"+1 253 880 3054",
    "sg:postcode":"98002",
    "sg:province":"WA",
    "wof:name":"Joyce A Weber Lmp",
    "wof:placetype":"venue"
},
  "geometry": {"coordinates":[-122.218613,47.307884],"type":"Point"}
}