{
  "type": "Feature",
  "properties": {
    "addr:full":"2201 Simpson Ave Aberdeen WA 98520",
    "addr:housenumber":"2201",
    "addr:postcode":"98520",
    "addr:street":"Simpson Ave",
    "iso:country":"US",
    "sg:address":"2201 Simpson Ave",
    "sg:city":"Aberdeen",
    "sg:classifiers":[
        {
            "category":"Organizations",
            "subcategory":"Religious Organization",
            "type":"Services"
        }
    ],
    "sg:phone":"+1 360 533 5049",
    "sg:postcode":"98520",
    "sg:province":"WA",
    "sg:tags":[
        "church"
    ],
    "wof:name":"First Church Of Christ Science",
    "wof:placetype":"venue"
},
  "geometry": {"coordinates":[-123.84443899999999,46.97511],"type":"Point"}
}