{
  "type": "Feature",
  "properties": {
    "addr:full":"1920 SW 324th St Federal Way WA 98023",
    "addr:housenumber":"1920",
    "addr:postcode":"98023",
    "addr:street":"Sw 324Th St",
    "iso:country":"US",
    "sg:address":"1920 SW 324th St",
    "sg:city":"Federal Way",
    "sg:classifiers":[
        {
            "category":"Professional",
            "subcategory":"Accounting & Tax Preparation",
            "type":"Services"
        }
    ],
    "sg:phone":"+1 253 874 0619",
    "sg:postcode":"98023",
    "sg:province":"WA",
    "wof:name":"Best Ever Bookkeeping Service",
    "wof:placetype":"venue"
},
  "geometry": {"coordinates":[-122.359504,47.310884],"type":"Point"}
}