{
  "type": "Feature",
  "properties": {
    "addr:full":"4502 6th St SE Puyallup WA 98374",
    "addr:housenumber":"4502",
    "addr:postcode":"98374",
    "addr:street":"6Th St Se",
    "iso:country":"US",
    "sg:address":"4502 6th St SE",
    "sg:city":"Puyallup",
    "sg:classifiers":[
        {
            "category":"Health Services",
            "subcategory":"Nursing And Care Facility",
            "type":"Services"
        }
    ],
    "sg:phone":"+1 253 848 4430",
    "sg:postcode":"98374",
    "sg:province":"WA",
    "sg:tags":[
        "home",
        "retirement",
        "community"
    ],
    "wof:name":"Willow Gardens Retirement Ctr",
    "wof:placetype":"venue"
},
  "geometry": {"coordinates":[-122.28468100000001,47.149328],"type":"Point"}
}