{
  "type": "Feature",
  "properties": {
    "addr:full":"204 S Oregon Ave Pasco WA 99301",
    "addr:housenumber":"204",
    "addr:postcode":"99301",
    "addr:street":"S Oregon Ave",
    "iso:country":"US",
    "sg:address":"204 S Oregon Ave",
    "sg:city":"Pasco",
    "sg:classifiers":[
        {
            "category":"Retail",
            "subcategory":"Auto Repair",
            "type":"Services"
        }
    ],
    "sg:phone":"+1 509 547 6824",
    "sg:postcode":"99301",
    "sg:province":"WA",
    "sg:tags":[
        "repairing",
        "automobile",
        "radiator"
    ],
    "sg:website":"www.americanradiator.com",
    "wof:name":"American Radiator Inc",
    "wof:placetype":"venue"
},
  "geometry": {"coordinates":[-119.07910200000001,46.231433],"type":"Point"}
}