{
  "type": "Feature",
  "properties": {
    "addr:full":"2825 NW 72nd St Seattle WA 98117",
    "addr:housenumber":"2825",
    "addr:postcode":"98117",
    "addr:street":"Nw 72Nd St",
    "iso:country":"US",
    "sg:address":"2825 NW 72nd St",
    "sg:city":"Seattle",
    "sg:classifiers":[
        {
            "category":"Building & Trades",
            "subcategory":"Construction",
            "type":"Services"
        }
    ],
    "sg:phone":"+1 206 982 9253",
    "sg:postcode":"98117",
    "sg:province":"WA",
    "sg:tags":[
        "floor",
        "laying",
        "contractor"
    ],
    "wof:name":"Lons Hardwood Flooring",
    "wof:placetype":"venue"
},
  "geometry": {"coordinates":[-122.39548499999999,47.680874],"type":"Point"}
}