{
  "type": "Feature",
  "properties": {
    "addr:full":"2801 Hewitt Ave Everett WA 98201",
    "addr:housenumber":"2801",
    "addr:postcode":"98201",
    "addr:street":"Hewitt Ave",
    "iso:country":"US",
    "sg:address":"2801 Hewitt Ave",
    "sg:city":"Everett",
    "sg:classifiers":[
        {
            "category":"Shopping",
            "type":"Retail Goods"
        }
    ],
    "sg:phone":"+1 425 485 6403",
    "sg:postcode":"98201",
    "sg:province":"WA",
    "sg:tags":[
        "merchandise"
    ],
    "wof:name":"Wells Hearing Aid Center",
    "wof:placetype":"venue"
},
  "geometry": {"coordinates":[-122.192402,47.979088],"type":"Point"}
}