{
  "type": "Feature",
  "properties": {
    "addr:full":"2104 Harrison Ave NW Olympia WA 98502",
    "addr:housenumber":"2104",
    "addr:postcode":"olympia wa 98502",
    "addr:street":"Harrison Ave Nw",
    "iso:country":"US",
    "sg:address":"2104 Harrison Ave NW",
    "sg:city":"Olympia",
    "sg:classifiers":[
        {
            "category":"Shopping",
            "subcategory":"Department Store",
            "type":"Retail Goods"
        },
        {
            "category":"Shopping",
            "type":"Retail Goods"
        },
        {
            "category":"Shopping",
            "subcategory":"Discount & Variety Stores",
            "type":"Retail Goods"
        }
    ],
    "sg:phone":"+1 360 534 0210",
    "sg:postcode":"98502",
    "sg:province":"WA",
    "sg:tags":[
        "merchandise"
    ],
    "sg:website":"http://www.dollartree.com/",
    "wof:name":"Dollar Tree",
    "wof:placetype":"venue"
},
  "geometry": {"coordinates":[-122.926962,47.046055],"type":"Point"}
}