{
  "type": "Feature",
  "properties": {
    "addr:full":"8232 Hansen Rd NE Bainbridge Isle WA 98110",
    "addr:housenumber":"8232",
    "addr:postcode":"98110",
    "addr:street":"Hansen Rd Ne;Isle",
    "iso:country":"US",
    "sg:address":"8232 Hansen Rd NE",
    "sg:city":"Bainbridge Isle",
    "sg:classifiers":[
        {
            "category":"Professional",
            "subcategory":"Management & Consulting",
            "type":"Services"
        }
    ],
    "sg:phone":"+1 206 855 0830",
    "sg:postcode":"98110",
    "sg:province":"WA",
    "sg:tags":[
        "consultant",
        "business"
    ],
    "wof:name":"Campbell Consulting",
    "wof:placetype":"venue"
},
  "geometry": {"coordinates":[-122.574518,47.634451],"type":"Point"}
}