{
  "type": "Feature",
  "properties": {
    "addr:full":"4815 N Driscoll Blvd Spokane WA 99205",
    "addr:housenumber":"4815",
    "addr:postcode":"99205",
    "addr:street":"N Driscoll Blvd",
    "iso:country":"US",
    "sg:address":"4815 N Driscoll Blvd",
    "sg:city":"Spokane",
    "sg:classifiers":[
        {
            "category":"Organizations",
            "subcategory":"Religious Organization",
            "type":"Services"
        }
    ],
    "sg:phone":"+1 509 328 3394",
    "sg:postcode":"99205",
    "sg:province":"WA",
    "wof:name":"Driscoll Blvd Baptst Church",
    "wof:placetype":"venue"
},
  "geometry": {"coordinates":[-117.46288800000001,47.702337],"type":"Point"}
}