{
  "type": "Feature",
  "properties": {
    "addr:full":"802 117th St S Tacoma WA 98444",
    "addr:housenumber":"802",
    "addr:postcode":"98444",
    "addr:street":"117Th St S",
    "iso:country":"US",
    "sg:address":"802 117th St S",
    "sg:city":"Tacoma",
    "sg:classifiers":[
        {
            "category":"Professional",
            "subcategory":"Computer Services",
            "type":"Services"
        }
    ],
    "sg:phone":"+1 253 538 9990",
    "sg:postcode":"98444",
    "sg:province":"WA",
    "sg:tags":[
        "processing",
        "datum"
    ],
    "wof:name":"Enabling Health Data",
    "wof:placetype":"venue"
},
  "geometry": {"coordinates":[-122.44399900000001,47.150423],"type":"Point"}
}