{
  "type": "Feature",
  "properties": {
    "addr:full":"167 Calder Rd Elma WA 98541",
    "addr:housenumber":"167",
    "addr:postcode":"98541",
    "addr:street":"Calder Rd",
    "iso:country":"US",
    "sg:address":"167 Calder Rd",
    "sg:city":"Elma",
    "sg:classifiers":[
        {
            "category":"Food & Beverages",
            "subcategory":"Specialty",
            "type":"Retail Goods"
        }
    ],
    "sg:phone":"+1 360 482 6264",
    "sg:postcode":"98541",
    "sg:province":"WA",
    "wof:name":"Spices & Such",
    "wof:placetype":"venue"
},
  "geometry": {"coordinates":[-123.43570800000001,47.013379],"type":"Point"}
}