{
  "type": "Feature",
  "properties": {
    "addr:full":"13510 NE 84th St Vancouver WA 98682",
    "addr:housenumber":"13510",
    "addr:postcode":"98682",
    "addr:street":"Ne 84Th St",
    "iso:country":"US",
    "sg:address":"13510 NE 84th St",
    "sg:city":"Vancouver",
    "sg:classifiers":[
        {
            "category":"Health Services",
            "subcategory":"Doctor",
            "type":"Services"
        }
    ],
    "sg:phone":"+1 360 696 0000",
    "sg:postcode":"98682",
    "sg:province":"WA",
    "sg:tags":[
        "dentist"
    ],
    "wof:name":"Comfort Dental",
    "wof:placetype":"venue"
},
  "geometry": {"coordinates":[-122.53287899999999,45.684268],"type":"Point"}
}