{
  "type": "Feature",
  "properties": {
    "addr:full":"5524 62nd St NW Gig Harbor WA 98335",
    "addr:housenumber":"5524",
    "addr:postcode":"98335",
    "addr:street":"62Nd St Nw",
    "iso:country":"US",
    "sg:address":"5524 62nd St NW",
    "sg:city":"Gig Harbor",
    "sg:classifiers":[
        {
            "category":"Shopping",
            "subcategory":"Computers & Home Electronics",
            "type":"Retail Goods"
        }
    ],
    "sg:phone":"+1 253 851 5727",
    "sg:postcode":"98335",
    "sg:province":"WA",
    "wof:name":"Whitewinter Computer Network",
    "wof:placetype":"venue"
},
  "geometry": {"coordinates":[-122.612241,47.313419],"type":"Point"}
}