{
  "type": "Feature",
  "properties": {
    "addr:full":"18013 121st Ave E Puyallup WA 98374",
    "addr:housenumber":"18013",
    "addr:postcode":"98374",
    "addr:street":"121St Ave E",
    "iso:country":"US",
    "sg:address":"18013 121st Ave E",
    "sg:city":"Puyallup",
    "sg:classifiers":[
        {
            "category":"Building & Trades",
            "subcategory":"Construction",
            "type":"Services"
        }
    ],
    "sg:phone":"+1 253 589 3855",
    "sg:postcode":"98374",
    "sg:province":"WA",
    "sg:tags":[
        "restoration",
        "cleaning",
        "patio",
        "deck"
    ],
    "wof:name":"Pressure Washing Systems",
    "wof:placetype":"venue"
},
  "geometry": {"coordinates":[-122.267681,47.092815],"type":"Point"}
}