{
  "type": "Feature",
  "properties": {
    "addr:full":"2641 120th Ave NE Bellevue WA 98005",
    "addr:housenumber":"2641",
    "addr:postcode":"98005",
    "addr:street":"120Th Ave Ne",
    "iso:country":"US",
    "sg:address":"2641 120th Ave NE",
    "sg:city":"Bellevue",
    "sg:classifiers":[
        {
            "category":"Education",
            "subcategory":"Special Training",
            "type":"Public Place"
        }
    ],
    "sg:phone":"+1 425 562 9190",
    "sg:postcode":"98005",
    "sg:province":"WA",
    "wof:name":"Greg Lyons Trumpet Studio",
    "wof:placetype":"venue"
},
  "geometry": {"coordinates":[-122.179636,47.632719],"type":"Point"}
}