{
  "type": "Feature",
  "properties": {
    "addr:full":"619 125th Ave NE Lake Stevens WA 98258",
    "addr:housenumber":"619",
    "addr:postcode":"98258",
    "addr:street":"125Th Ave Ne",
    "iso:country":"US",
    "sg:address":"619 125th Ave NE",
    "sg:city":"Lake Stevens",
    "sg:classifiers":[
        {
            "category":"Retail",
            "subcategory":"Repair Shop",
            "type":"Services"
        }
    ],
    "sg:phone":"+1 425 335 5750",
    "sg:postcode":"98258",
    "sg:province":"WA",
    "wof:name":"N Quick Clean",
    "wof:placetype":"venue"
},
  "geometry": {"coordinates":[-122.062709,48.003444],"type":"Point"}
}