{
  "type": "Feature",
  "properties": {
    "addr:full":"1508 Riverside Dr Mount Vernon WA 98273",
    "addr:housenumber":"1508",
    "addr:postcode":"98273",
    "addr:street":"Riverside Dr",
    "iso:country":"US",
    "sg:address":"1508 Riverside Dr",
    "sg:city":"Mount Vernon",
    "sg:classifiers":[
        {
            "category":"Banks & Credit Unions",
            "subcategory":"Bank",
            "type":"Services"
        }
    ],
    "sg:phone":"+1 360 424 1086",
    "sg:postcode":"98273",
    "sg:province":"WA",
    "sg:tags":[
        "national",
        "commercial"
    ],
    "wof:name":"US Bank",
    "wof:placetype":"venue"
},
  "geometry": {"coordinates":[-122.335111,48.434257],"type":"Point"}
}