{
  "type": "Feature",
  "properties": {
    "addr:full":"706 S 1st St Mt Vernon WA 98273",
    "addr:housenumber":"706",
    "addr:postcode":"98273",
    "addr:street":"S 1St St",
    "iso:country":"US",
    "sg:address":"706 S 1st St",
    "sg:city":"Mt Vernon",
    "sg:classifiers":[
        {
            "category":"Professional",
            "subcategory":"Business Services",
            "type":"Services"
        },
        {
            "category":"Home & Garden",
            "subcategory":"Furniture",
            "type":"Retail Goods"
        }
    ],
    "sg:phone":"+1 360 336 1010",
    "sg:postcode":"98273",
    "sg:province":"WA",
    "sg:tags":[
        "interior",
        "consultant",
        "design",
        "decorator"
    ],
    "wof:name":"Style",
    "wof:placetype":"venue"
},
  "geometry": {"coordinates":[-122.338454,48.418113],"type":"Point"}
}