{
  "type": "Feature",
  "properties": {
    "addr:full":"7225 Pacific Ave SE Lacey WA 98503",
    "addr:housenumber":"7225",
    "addr:postcode":"98503",
    "addr:street":"Pacific Ave Se",
    "iso:country":"US",
    "sg:address":"7225 Pacific Ave SE",
    "sg:city":"Lacey",
    "sg:classifiers":[
        {
            "category":"Building & Trades",
            "subcategory":"Cleaning & Sanitation",
            "type":"Services"
        }
    ],
    "sg:phone":"+1 360 491 2900",
    "sg:postcode":"98503",
    "sg:province":"WA",
    "sg:tags":[
        "supply",
        "septic",
        "tanks-treatment"
    ],
    "wof:name":"A Plus Septic Service",
    "wof:placetype":"venue"
},
  "geometry": {"coordinates":[-122.784784,47.041891],"type":"Point"}
}