{
  "type": "Feature",
  "properties": {
    "addr:full":"109 Front Ave SW Castle Rock WA 98611",
    "addr:housenumber":"109",
    "addr:postcode":"98611",
    "addr:street":"Front Ave Sw",
    "iso:country":"US",
    "sg:address":"109 Front Ave SW",
    "sg:city":"Castle Rock",
    "sg:classifiers":[
        {
            "category":"Organizations",
            "subcategory":"Professional Association",
            "type":"Services"
        }
    ],
    "sg:phone":"+1 360 274 6260",
    "sg:postcode":"98611",
    "sg:province":"WA",
    "wof:name":"Castle Rock Education Assn",
    "wof:placetype":"venue"
},
  "geometry": {"coordinates":[-122.907911,46.274784],"type":"Point"}
}