{
  "type": "Feature",
  "properties": {
    "addr:full":"812 SE 136th Ave Vancouver WA 98683",
    "addr:housenumber":"812",
    "addr:postcode":"98683",
    "addr:street":"Se 136Th Ave",
    "iso:country":"US",
    "sg:address":"812 SE 136th Ave",
    "sg:city":"Vancouver",
    "sg:classifiers":[
        {
            "category":"Manufacturing",
            "subcategory":"Tools & Machinery",
            "type":"Manufacturing & Wholesale Goods"
        }
    ],
    "sg:phone":"+1 360 891 6044",
    "sg:postcode":"98683",
    "sg:province":"WA",
    "sg:tags":[
        "product",
        "health",
        "related",
        "mfg"
    ],
    "wof:name":"Artec Inc",
    "wof:placetype":"venue"
},
  "geometry": {"coordinates":[-122.532578,45.612604],"type":"Point"}
}