{
  "type": "Feature",
  "properties": {
    "addr:full":"11 Front St St John WA 99171",
    "addr:housenumber":"11",
    "addr:postcode":"99171",
    "addr:street":"Front St St",
    "iso:country":"US",
    "sg:address":"11 Front St",
    "sg:city":"St John",
    "sg:classifiers":[
        {
            "category":"Utilities",
            "subcategory":"Telephone",
            "type":"Services"
        }
    ],
    "sg:phone":"+1 509 648 3322",
    "sg:postcode":"99171",
    "sg:province":"WA",
    "sg:tags":[
        "company"
    ],
    "wof:name":"St John Telephone Co",
    "wof:placetype":"venue"
},
  "geometry": {"coordinates":[-117.582117,47.091765],"type":"Point"}
}