{
  "type": "Feature",
  "properties": {
    "addr:full":"4601 S 134th Pl Seattle WA 98168",
    "addr:housenumber":"4601",
    "addr:postcode":"98168",
    "addr:street":"S 134Th Pl",
    "iso:country":"US",
    "sg:address":"4601 S 134th Pl",
    "sg:city":"Seattle",
    "sg:classifiers":[
        {
            "category":"Building & Trades",
            "subcategory":"Construction",
            "type":"Services"
        }
    ],
    "sg:phone":"+1 253 838 1131",
    "sg:postcode":"98168",
    "sg:province":"WA",
    "sg:tags":[
        "air",
        "heating",
        "conditioning/hvac"
    ],
    "wof:name":"Brennan Heating & Air Conditioning",
    "wof:placetype":"venue"
},
  "geometry": {"coordinates":[-122.275391,47.483657],"type":"Point"}
}