{
  "type": "Feature",
  "properties": {
    "addr:full":"1231 Blaine St Port Townsend WA 98368",
    "addr:housenumber":"1231",
    "addr:postcode":"98368",
    "addr:street":"Blaine St",
    "iso:country":"US",
    "sg:address":"1231 Blaine St",
    "sg:city":"Port Townsend",
    "sg:classifiers":[
        {
            "category":"Professional",
            "type":"Services"
        }
    ],
    "sg:phone":"+1 360 379 6443",
    "sg:postcode":"98368",
    "sg:province":"WA",
    "wof:name":"H and N Payson",
    "wof:placetype":"venue"
},
  "geometry": {"coordinates":[-122.764177,48.118546],"type":"Point"}
}