{
  "type": "Feature",
  "properties": {
    "addr:full":"12819 SE 38th St Bellevue WA 98108",
    "addr:postcode":"12819;98108",
    "addr:street":"Se 38Th St",
    "iso:country":"US",
    "sg:address":"12819 SE 38th St",
    "sg:city":"Bellevue",
    "sg:classifiers":[
        {
            "category":"Personal",
            "type":"Services"
        }
    ],
    "sg:phone":"+1 206 276 4599",
    "sg:postcode":"98108",
    "sg:province":"WA",
    "sg:tags":[
        "mover"
    ],
    "sg:website":"www.expressmoversinc.com",
    "wof:name":"Express Movers, Inc",
    "wof:placetype":"venue"
},
  "geometry": {"coordinates":[-122.168999,47.575901],"type":"Point"}
}