{
  "type": "Feature",
  "properties": {
    "addr:full":"600 SW Kenyon St Apt T201 Seattle WA 98106",
    "addr:housenumber":"600",
    "addr:postcode":"98106",
    "addr:street":"Sw Kenyon St Apt T201",
    "iso:country":"US",
    "sg:address":"600 SW Kenyon St Apt T201",
    "sg:city":"Seattle",
    "sg:classifiers":[
        {
            "category":"Professional",
            "type":"Services"
        }
    ],
    "sg:phone":"+1 206 767 9200",
    "sg:postcode":"98106",
    "sg:province":"WA",
    "sg:tags":[
        "shows",
        "exposition",
        "fair",
        "trade"
    ],
    "sg:website":"http://www.seattletrendshow.com",
    "wof:name":"Seattle Trens Show",
    "wof:placetype":"venue"
},
  "geometry": {"coordinates":[-122.34301600000001,47.531971],"type":"Point"}
}