{
  "type": "Feature",
  "properties": {
    "addr:full":"21905 Beachside Dr SE Yelm WA 98597",
    "addr:postcode":"21905;98597",
    "addr:street":"Beachside Dr Se",
    "iso:country":"US",
    "sg:address":"21905 Beachside Dr SE",
    "sg:city":"Yelm",
    "sg:classifiers":[
        {
            "category":"Real Estate",
            "subcategory":"Architect",
            "type":"Services"
        }
    ],
    "sg:phone":"+1 360 894 7311",
    "sg:postcode":"98597",
    "sg:province":"WA",
    "wof:name":"K Walter Johnson Aia",
    "wof:placetype":"venue"
},
  "geometry": {"coordinates":[-122.479764,46.823225],"type":"Point"}
}