{
  "type": "Feature",
  "properties": {
    "iso:country":"US",
    "sg:address":"10423 Main St",
    "sg:city":"Bellevue",
    "sg:classifiers":[
        {
            "category":"Professional",
            "subcategory":"Engineering",
            "type":"Services"
        }
    ],
    "sg:phone":"+1 425 455 9640",
    "sg:postcode":"98004",
    "sg:province":"WA",
    "wof:name":"Robert S Betts Inc",
    "wof:placetype":"venue"
},
  "geometry": {"coordinates":[-122.200367,47.610063],"type":"Point"}
}