{
  "type": "Feature",
  "properties": {
    "addr:full":"172 23rd Ave Seattle WA 98122",
    "addr:housenumber":"172",
    "addr:postcode":"98122",
    "addr:street":"23Rd Ave",
    "iso:country":"US",
    "sg:address":"172 23rd Ave",
    "sg:city":"Seattle",
    "sg:classifiers":[
        {
            "category":"Organizations",
            "subcategory":"Religious Organization",
            "type":"Services"
        }
    ],
    "sg:phone":"+1 206 325 9344",
    "sg:postcode":"98122",
    "sg:province":"WA",
    "sg:tags":[
        "church"
    ],
    "wof:name":"Curry Temple C M E Church",
    "wof:placetype":"venue"
},
  "geometry": {"coordinates":[-122.30235999999999,47.60312],"type":"Point"}
}