{
  "type": "Feature",
  "properties": {
    "addr:full":"1901 S 1st St Yakima WA 98903",
    "addr:housenumber":"1901",
    "addr:postcode":"98903",
    "addr:street":"S 1St St",
    "iso:country":"US",
    "sg:address":"1901 S 1st St",
    "sg:city":"Yakima",
    "sg:classifiers":[
        {
            "category":"Shopping",
            "subcategory":"Used Merchandise",
            "type":"Retail Goods"
        }
    ],
    "sg:phone":"+1 509 248 3650",
    "sg:postcode":"98903",
    "sg:province":"WA",
    "wof:name":"Silver Appliances",
    "wof:placetype":"venue"
},
  "geometry": {"coordinates":[-120.488862,46.573068],"type":"Point"}
}