{
  "type": "Feature",
  "properties": {
    "iso:country":"US",
    "sg:address":"3818 N Nevada St",
    "sg:city":"Spokane",
    "sg:classifiers":[
        {
            "category":"Shopping",
            "subcategory":"Computers & Home Electronics",
            "type":"Retail Goods"
        }
    ],
    "sg:phone":"+1 509 487 5824",
    "sg:postcode":"99207",
    "sg:province":"WA",
    "sg:tags":[
        "equipment",
        "dealer"
    ],
    "wof:name":"Direct Connection",
    "wof:placetype":"venue"
},
  "geometry": {"coordinates":[-117.39506,47.69256],"type":"Point"}
}