{
  "type": "Feature",
  "properties": {
    "iso:country":"US",
    "sg:address":"3414 132nd St SE",
    "sg:city":"Bothell",
    "sg:classifiers":[
        {
            "category":"Retail",
            "subcategory":"Laundry & Dry Cleaning",
            "type":"Services"
        }
    ],
    "sg:phone":"+1 425 316 1979",
    "sg:postcode":"98012",
    "sg:province":"WA",
    "sg:tags":[
        "drycleaning",
        "plant",
        "cleaners"
    ],
    "wof:name":"Cleanist",
    "wof:placetype":"venue"
},
  "geometry": {"coordinates":[-122.19068799999999,47.877921],"type":"Point"}
}