{
  "type": "Feature",
  "properties": {
    "addr:full":"1098 Cedar Ave Marysville WA 98270",
    "addr:housenumber":"1098",
    "addr:postcode":"98270",
    "addr:street":"Cedar Ave",
    "iso:country":"US",
    "sg:address":"1098 Cedar Ave",
    "sg:city":"Marysville",
    "sg:classifiers":[
        {
            "category":"Coffee & Tea",
            "type":"Food & Drink"
        },
        {
            "category":"Restaurant",
            "type":"Food & Drink"
        }
    ],
    "sg:phone":"+1 360 653 9018",
    "sg:postcode":"98270",
    "sg:province":"WA",
    "sg:tags":[
        "shop",
        "espresso"
    ],
    "wof:name":"La Te Da Espresso Company",
    "wof:placetype":"venue"
},
  "geometry": {"coordinates":[-122.180397,48.057645],"type":"Point"}
}