{
  "type": "Feature",
  "properties": {
    "addr:full":"31 NW Crosby Ave Oak Harbor WA 98277",
    "addr:housenumber":"31",
    "addr:postcode":"98277",
    "addr:street":"Nw Crosby Ave",
    "iso:country":"US",
    "sg:address":"31 NW Crosby Ave",
    "sg:city":"Oak Harbor",
    "sg:classifiers":[
        {
            "category":"Real Estate",
            "subcategory":"Real Estate Operator",
            "type":"Services"
        }
    ],
    "sg:phone":"+1 360 679 6671",
    "sg:postcode":"98277",
    "sg:province":"WA",
    "wof:name":"Harbor Heights Apartments",
    "wof:placetype":"venue"
},
  "geometry": {"coordinates":[-122.658012,48.307628],"type":"Point"}
}