{
  "type": "Feature",
  "properties": {
    "addr:full":"9812 Crescent Valley Dr NW Gig Harbor WA 98332",
    "addr:housenumber":"9812",
    "addr:postcode":"98332",
    "addr:street":"Crescent Valley Dr Nw",
    "iso:country":"US",
    "sg:address":"9812 Crescent Valley Dr NW",
    "sg:city":"Gig Harbor",
    "sg:classifiers":[
        {
            "category":"Farming",
            "subcategory":"Livestock Farm",
            "type":"Manufacturing & Wholesale Goods"
        }
    ],
    "sg:phone":"+1 253 858 2694",
    "sg:postcode":"98332",
    "sg:province":"WA",
    "sg:tags":[
        "beef",
        "feedlot",
        "cattle"
    ],
    "wof:name":"Paul Alvestad",
    "wof:placetype":"venue"
},
  "geometry": {"coordinates":[-122.578593,47.347849],"type":"Point"}
}