{
  "type": "Feature",
  "properties": {
    "addr:full":"1801 E Marion St. Seattle WA 98122",
    "addr:housenumber":"1801",
    "addr:postcode":"98122",
    "addr:street":"E Marion St.",
    "iso:country":"US",
    "sg:address":"1801 E Marion St.",
    "sg:city":"Seattle",
    "sg:classifiers":[
        {
            "category":"Professional",
            "type":"Services"
        }
    ],
    "sg:phone":"+1 206 523 2560",
    "sg:postcode":"98122",
    "sg:province":"WA",
    "sg:tags":[
        "caterer"
    ],
    "sg:website":"www.thewedgecatering.com",
    "wof:name":"The Wedge Catering",
    "wof:placetype":"venue"
},
  "geometry": {"coordinates":[-122.308795,47.61036],"type":"Point"}
}