{
  "type": "Feature",
  "properties": {
    "addr:full":"2102 15th Ave Milton WA 98354",
    "addr:housenumber":"2102",
    "addr:postcode":"98354",
    "addr:street":"15Th Ave",
    "iso:country":"US",
    "sg:address":"2102 15th Ave",
    "sg:city":"Milton",
    "sg:classifiers":[
        {
            "category":"Real Estate",
            "subcategory":"Real Estate Agent",
            "type":"Services"
        }
    ],
    "sg:phone":"+1 253 926 9229",
    "sg:postcode":"98354",
    "sg:province":"WA",
    "sg:tags":[
        "inspection"
    ],
    "wof:name":"Blue Mountain Svc",
    "wof:placetype":"venue"
},
  "geometry": {"coordinates":[-122.31509200000001,47.242281],"type":"Point"}
}