{
  "type": "Feature",
  "properties": {
    "addr:full":"1209 S Bailey Street Seattle WA 98108",
    "addr:housenumber":"1209",
    "addr:postcode":"98108",
    "addr:street":"S Bailey Street",
    "iso:country":"US",
    "sg:address":"1209 S Bailey Street",
    "sg:city":"Seattle",
    "sg:classifiers":[
        {
            "category":"Retail",
            "subcategory":"Auto Repair",
            "type":"Services"
        }
    ],
    "sg:phone":"+1 206 767 4929",
    "sg:postcode":"98108",
    "sg:province":"WA",
    "sg:tags":[
        "body",
        "shop"
    ],
    "wof:name":"Carstar Hammer Auto Rebuild",
    "wof:placetype":"venue"
},
  "geometry": {"coordinates":[-122.31701099999999,47.54759],"type":"Point"}
}