{
  "type": "Feature",
  "properties": {
    "addr:full":"1101 Airport Way S Seattle WA 98134",
    "addr:housenumber":"1101",
    "addr:postcode":"98134",
    "addr:street":"Airport Way S",
    "iso:country":"US",
    "sg:address":"1101 Airport Way S",
    "sg:city":"Seattle",
    "sg:classifiers":[
        {
            "category":"Professional",
            "subcategory":"Business Services",
            "type":"Services"
        }
    ],
    "sg:phone":"+1 206 264 1815",
    "sg:postcode":"98134",
    "sg:province":"WA",
    "wof:name":"Artist Industrial Revolution",
    "wof:placetype":"venue"
},
  "geometry": {"coordinates":[-122.32486400000001,47.593876],"type":"Point"}
}