{
  "type": "Feature",
  "properties": {
    "addr:full":"9817 NE 54th St Vancouver WA 98662",
    "addr:housenumber":"9817",
    "addr:postcode":"98662",
    "addr:street":"Ne 54Th St",
    "iso:country":"US",
    "sg:address":"9817 NE 54th St",
    "sg:city":"Vancouver",
    "sg:classifiers":[
        {
            "category":"Organizations",
            "subcategory":"Professional Association",
            "type":"Services"
        }
    ],
    "sg:phone":"+1 360 254 0109",
    "sg:postcode":"98662",
    "sg:province":"WA",
    "sg:tags":[
        "research"
    ],
    "wof:name":"Nwppa",
    "wof:placetype":"venue"
},
  "geometry": {"coordinates":[-122.57213,45.661439],"type":"Point"}
}