{
  "type": "Feature",
  "properties": {
    "addr:full":"9923 E Trent Ave Spokane Valley WA 99206",
    "addr:housenumber":"9923",
    "addr:postcode":"99206",
    "addr:street":"E Trent Ave",
    "iso:country":"US",
    "sg:address":"9923 E Trent Ave",
    "sg:city":"Spokane Valley",
    "sg:classifiers":[
        {
            "category":"Building & Trades",
            "subcategory":"Landscaping Services",
            "type":"Services"
        }
    ],
    "sg:phone":"+1 509 922 4305",
    "sg:postcode":"99206",
    "sg:province":"WA",
    "sg:tags":[
        "tree"
    ],
    "sg:website":"www.ever-greentree.com",
    "wof:name":"Ever-Green Tree Experts",
    "wof:placetype":"venue"
},
  "geometry": {"coordinates":[-117.267717,47.684134],"type":"Point"}
}