{
  "type": "Feature",
  "properties": {
    "addr:full":"4607 W Wellesley Ave Spokane WA 99205",
    "addr:housenumber":"4607",
    "addr:postcode":"99205",
    "addr:street":"W Wellesley Ave",
    "iso:country":"US",
    "sg:address":"4607 W Wellesley Ave",
    "sg:city":"Spokane",
    "sg:classifiers":[
        {
            "category":"Professional",
            "type":"Services"
        }
    ],
    "sg:phone":"+1 509 328 3773",
    "sg:postcode":"99205",
    "sg:province":"WA",
    "wof:name":"Nelson Ilean",
    "wof:placetype":"venue"
},
  "geometry": {"coordinates":[-117.47895800000001,47.700757],"type":"Point"}
}