{
  "type": "Feature",
  "properties": {
    "addr:full":"19525 81st Pl W Edmonds WA 98026",
    "addr:housenumber":"19525",
    "addr:postcode":"98026",
    "addr:street":"81St Pl W",
    "iso:country":"US",
    "sg:address":"19525 81st Pl W",
    "sg:city":"Edmonds",
    "sg:classifiers":[
        {
            "category":"Retail",
            "subcategory":"Repair Shop",
            "type":"Services"
        }
    ],
    "sg:phone":"+1 425 775 4796",
    "sg:postcode":"98026",
    "sg:province":"WA",
    "wof:name":"Repair Only",
    "wof:placetype":"venue"
},
  "geometry": {"coordinates":[-122.343309,47.823267],"type":"Point"}
}