{
  "type": "Feature",
  "properties": {
    "addr:full":"16606 68th Ave E Puyallup WA 98375",
    "addr:housenumber":"16606",
    "addr:postcode":"98375",
    "addr:street":"68Th Ave E",
    "iso:country":"US",
    "sg:address":"16606 68th Ave E",
    "sg:city":"Puyallup",
    "sg:classifiers":[
        {
            "category":"Retail",
            "subcategory":"Auto Rental",
            "type":"Services"
        }
    ],
    "sg:phone":"+1 253 536 9146",
    "sg:postcode":"98375",
    "sg:province":"WA",
    "sg:tags":[
        "truck"
    ],
    "wof:name":"Hutch Enterprise",
    "wof:placetype":"venue"
},
  "geometry": {"coordinates":[-122.33878799999999,47.105571],"type":"Point"}
}