{
  "type": "Feature",
  "properties": {
    "addr:full":"2020 63rd Ave E Tacoma WA 98424",
    "addr:housenumber":"2020",
    "addr:postcode":"98424",
    "addr:street":"63Rd Ave E",
    "iso:country":"US",
    "sg:address":"2020 63rd Ave E",
    "sg:city":"Tacoma",
    "sg:classifiers":[
        {
            "category":"Social Services",
            "type":"Services"
        }
    ],
    "sg:phone":"+1 253 476 0395",
    "sg:postcode":"98424",
    "sg:province":"WA",
    "wof:name":"Stillwater Counseling P S",
    "wof:placetype":"venue"
},
  "geometry": {"coordinates":[-122.345764,47.237504],"type":"Point"}
}