{
  "type": "Feature",
  "properties": {
    "addr:full":"1402 S Kahuna Dr Spokane WA 99212",
    "addr:housenumber":"1402",
    "addr:postcode":"99212",
    "addr:street":"S Kahuna Dr",
    "iso:country":"US",
    "sg:address":"1402 S Kahuna Dr",
    "sg:city":"Spokane",
    "sg:classifiers":[
        {
            "category":"Professional",
            "subcategory":"Advertising",
            "type":"Services"
        }
    ],
    "sg:phone":"+1 509 534 6020",
    "sg:postcode":"99212",
    "sg:province":"WA",
    "sg:tags":[
        "mail",
        "direct"
    ],
    "wof:name":"1st Generation Radio Archives",
    "wof:placetype":"venue"
},
  "geometry": {"coordinates":[-117.335363,47.644052],"type":"Point"}
}