{
  "type": "Feature",
  "properties": {
    "iso:country":"US",
    "sg:address":"6708 13th Ave SW",
    "sg:city":"Seattle",
    "sg:classifiers":[
        {
            "category":"Manufacturing",
            "subcategory":"Printing",
            "type":"Manufacturing & Wholesale Goods"
        }
    ],
    "sg:phone":"+1 206 767 6084",
    "sg:postcode":"98106",
    "sg:province":"WA",
    "sg:tags":[
        "printer"
    ],
    "wof:name":"Alliant Printing Svc",
    "wof:placetype":"venue"
},
  "geometry": {"coordinates":[-122.35146,47.53917],"type":"Point"}
}