{
  "type": "Feature",
  "properties": {
    "addr:full":"17803 130th St SE Snohomish WA 98290",
    "addr:housenumber":"17803",
    "addr:postcode":"98290",
    "addr:street":"130Th St Se",
    "iso:country":"US",
    "sg:address":"17803 130th St SE",
    "sg:city":"Snohomish",
    "sg:classifiers":[
        {
            "category":"Building & Trades",
            "subcategory":"Landscaping Services",
            "type":"Services"
        }
    ],
    "sg:phone":"+1 360 794 8830",
    "sg:postcode":"98290",
    "sg:province":"WA",
    "sg:tags":[
        "tree"
    ],
    "wof:name":"Mike's Tree Care Inc",
    "wof:placetype":"venue"
},
  "geometry": {"coordinates":[-121.991249,47.879634],"type":"Point"}
}