{
  "type": "Feature",
  "properties": {
    "addr:full":"12874 Interurban Ave S Seattle WA 98168",
    "addr:housenumber":"12874",
    "addr:postcode":"98168",
    "addr:street":"Interurban Ave S",
    "iso:country":"US",
    "sg:address":"12874 Interurban Ave S",
    "sg:city":"Seattle",
    "sg:classifiers":[
        {
            "category":"Manufacturing",
            "subcategory":"Tools & Machinery",
            "type":"Manufacturing & Wholesale Goods"
        }
    ],
    "sg:phone":"+1 206 431 0404",
    "sg:postcode":"98168",
    "sg:province":"WA",
    "sg:tags":[
        "computer",
        "maintenance",
        "sales",
        "related",
        "mfg"
    ],
    "wof:name":"H N Bull Information Systems",
    "wof:placetype":"venue"
},
  "geometry": {"coordinates":[-122.276528,47.487001],"type":"Point"}
}