{
  "type": "Feature",
  "properties": {
    "iso:country":"US",
    "sg:address":"231 Elton Rd",
    "sg:city":"Yakima",
    "sg:classifiers":[
        {
            "category":"Home & Garden",
            "subcategory":"Mobile Homes",
            "type":"Retail Goods"
        }
    ],
    "sg:phone":"+1 509 453 8338",
    "sg:postcode":"98901",
    "sg:province":"WA",
    "wof:name":"Home Heaven LLC",
    "wof:placetype":"venue"
},
  "geometry": {"coordinates":[-120.49712,46.64978],"type":"Point"}
}