{
  "type": "Feature",
  "properties": {
    "addr:full":"122 E Montgomery Ave Spokane WA 99207",
    "addr:housenumber":"122",
    "addr:postcode":"99207",
    "addr:street":"E Montgomery Ave",
    "iso:country":"US",
    "sg:address":"122 E Montgomery Ave",
    "sg:city":"Spokane",
    "sg:classifiers":[
        {
            "category":"Manufacturing",
            "subcategory":"Electronics",
            "type":"Manufacturing & Wholesale Goods"
        }
    ],
    "sg:phone":"+1 509 327 7784",
    "sg:postcode":"99207",
    "sg:province":"WA",
    "sg:tags":[
        "sound",
        "equipment",
        "system"
    ],
    "sg:website":"www.natlmusic.com",
    "wof:name":"Womach Recording Studios",
    "wof:placetype":"venue"
},
  "geometry": {"coordinates":[-117.40831,47.67821],"type":"Point"}
}