{
  "type": "Feature",
  "properties": {
    "addr:full":"1909 S Charles St Seattle WA 98144",
    "addr:housenumber":"1909",
    "addr:postcode":"98144",
    "addr:street":"S Charles St",
    "iso:country":"US",
    "sg:address":"1909 S Charles St",
    "sg:city":"Seattle",
    "sg:classifiers":[
        {
            "category":"Professional",
            "subcategory":"Business Services",
            "type":"Services"
        }
    ],
    "sg:phone":"+1 206 329 9812",
    "sg:postcode":"98144",
    "sg:province":"WA",
    "wof:name":"Binh T Nguyen Enterprises",
    "wof:placetype":"venue"
},
  "geometry": {"coordinates":[-122.307678,47.59444],"type":"Point"}
}