{
  "type": "Feature",
  "properties": {
    "addr:full":"4837 NE 85th St Seattle WA 98115",
    "addr:housenumber":"4837",
    "addr:postcode":"98115",
    "addr:street":"Ne 85Th St",
    "iso:country":"US",
    "sg:address":"4837 NE 85th St",
    "sg:city":"Seattle",
    "sg:classifiers":[
        {
            "category":"Banks & Credit Unions",
            "subcategory":"Investment Brokerage",
            "type":"Services"
        },
        {
            "category":"Insurance",
            "subcategory":"Hazard Insurance",
            "type":"Services"
        }
    ],
    "sg:phone":"+1 206 524 9888",
    "sg:postcode":"98115",
    "sg:province":"WA",
    "sg:tags":[
        "commercial",
        "agent",
        "business",
        "resume"
    ],
    "sg:website":"http://www.suesadowinsurance.com",
    "wof:name":"Shadow Insurance Agency",
    "wof:placetype":"venue"
},
  "geometry": {"coordinates":[-122.276892,47.690591],"type":"Point"}
}