{
  "type": "Feature",
  "properties": {
    "addr:full":"190 Russet Ave Lynden WA 98264",
    "addr:housenumber":"190",
    "addr:postcode":"98264",
    "addr:street":"Russet Ave",
    "iso:country":"US",
    "sg:address":"190 Russet Ave",
    "sg:city":"Lynden",
    "sg:classifiers":[
        {
            "category":"Personal",
            "subcategory":"Beauty Salon",
            "type":"Services"
        }
    ],
    "sg:phone":"+1 360 398 1159",
    "sg:postcode":"98264",
    "sg:province":"WA",
    "wof:name":"No Limits Salon",
    "wof:placetype":"venue"
},
  "geometry": {"coordinates":[-122.48873,48.884504],"type":"Point"}
}