{
  "type": "Feature",
  "properties": {
    "addr:full":"5602 E Desmet Ave Spokane Valley WA 99212",
    "addr:housenumber":"5602",
    "addr:postcode":"99212",
    "addr:street":"E Desmet Ave",
    "iso:country":"US",
    "sg:address":"5602 E Desmet Ave",
    "sg:city":"Spokane Valley",
    "sg:classifiers":[
        {
            "category":"Building & Trades",
            "subcategory":"Landscaping Services",
            "type":"Services"
        }
    ],
    "sg:phone":"+1 509 536 2885",
    "sg:postcode":"99212",
    "sg:province":"WA",
    "sg:tags":[
        "landscape",
        "contractor"
    ],
    "wof:name":"Greenleaf Landscaping Inc",
    "wof:placetype":"venue"
},
  "geometry": {"coordinates":[-117.329172,47.666977],"type":"Point"}
}