{
  "type": "Feature",
  "properties": {
    "iso:country":"US",
    "sg:address":"1619 Index Ct SE",
    "sg:city":"Renton",
    "sg:classifiers":[
        {
            "category":"Building & Trades",
            "subcategory":"Landscaping Services",
            "type":"Services"
        }
    ],
    "sg:phone":"+1 425 228 5735",
    "sg:postcode":"98058",
    "sg:province":"WA",
    "sg:tags":[
        "landscape"
    ],
    "wof:name":"Alfredo H Tiquia",
    "wof:placetype":"venue"
},
  "geometry": {"coordinates":[-122.181027,47.46615],"type":"Point"}
}