{
  "type": "Feature",
  "properties": {
    "addr:full":"4950 Tolt Ave Carnation WA 98014",
    "addr:housenumber":"4950",
    "addr:postcode":"98014",
    "addr:street":"Tolt Ave",
    "iso:country":"US",
    "sg:address":"4950 Tolt Ave",
    "sg:city":"Carnation",
    "sg:classifiers":[
        {
            "category":"Education",
            "subcategory":"School",
            "type":"Public Place"
        }
    ],
    "sg:phone":"+1 425 844 4553",
    "sg:postcode":"98014",
    "sg:province":"WA",
    "sg:tags":[
        "elementary"
    ],
    "sg:website":"http://www.ce.riverview.wednet.edu",
    "wof:name":"Carnation Elementary School",
    "wof:placetype":"venue"
},
  "geometry": {"coordinates":[-121.911919,47.651428],"type":"Point"}
}