{
  "type": "Feature",
  "properties": {
    "addr:full":"880 Cyprus Ct NW Issaquah WA 98027",
    "addr:housenumber":"880",
    "addr:postcode":"98027",
    "addr:street":"Cyprus Ct Nw",
    "iso:country":"US",
    "sg:address":"880 Cyprus Ct NW",
    "sg:city":"Issaquah",
    "sg:phone":"+1 425 829 0572",
    "sg:postcode":"98027",
    "sg:province":"WA",
    "wof:name":"Enterprises In Prime Time",
    "wof:placetype":"venue"
},
  "geometry": {"coordinates":[-122.049513,47.534727],"type":"Point"}
}