{
  "type": "Feature",
  "properties": {
    "addr:full":"2001 152nd Ave NE Redmond WA 98052",
    "addr:housenumber":"2001",
    "addr:postcode":"98052",
    "addr:street":"152Nd Ave Ne",
    "iso:country":"US",
    "sg:address":"2001 152nd Ave NE",
    "sg:city":"Redmond",
    "sg:classifiers":[
        {
            "category":"Health Services",
            "subcategory":"Doctor",
            "type":"Services"
        },
        {
            "category":"Health Services",
            "subcategory":"Clinic",
            "type":"Services"
        },
        {
            "category":"Health Services",
            "subcategory":"Podiatrist",
            "type":"Services"
        }
    ],
    "sg:phone":"+1 425 440 3908",
    "sg:postcode":"98052",
    "sg:province":"WA",
    "sg:tags":[
        "physician",
        "medical",
        "surgeons",
        "surgeon"
    ],
    "sg:website":"http://seattle.citysearch.com/profile/external/618286360/redmond_wa/advanced_foot_ankle_podiatry.html?publisher=yellowpages&reference_id=15&placement=ypwebsitemip",
    "wof:name":"Advanced Foot & Ankle Podiatry",
    "wof:placetype":"venue"
},
  "geometry": {"coordinates":[-122.137749,47.628391],"type":"Point"}
}