{
  "type": "Feature",
  "properties": {
    "addr:full":"307 J St SE Auburn WA 98002",
    "addr:housenumber":"307",
    "addr:postcode":"98002",
    "addr:street":"J St Se",
    "iso:country":"US",
    "sg:address":"307 J St SE",
    "sg:city":"Auburn",
    "sg:classifiers":[
        {
            "category":"Retail",
            "subcategory":"Laundry & Dry Cleaning",
            "type":"Services"
        }
    ],
    "sg:phone":"+1 253 804 5673",
    "sg:postcode":"98002",
    "sg:province":"WA",
    "wof:name":"Will-Clean",
    "wof:placetype":"venue"
},
  "geometry": {"coordinates":[-122.21758800000001,47.305302],"type":"Point"}
}