{
  "type": "Feature",
  "properties": {
    "addr:full":"500 Wellsian Way Richland WA 99352",
    "addr:housenumber":"500",
    "addr:postcode":"99352",
    "addr:street":"Wellsian Way",
    "iso:country":"US",
    "sg:address":"500 Wellsian Way",
    "sg:city":"Richland",
    "sg:classifiers":[
        {
            "category":"Autos & Motor Vehicles",
            "subcategory":"Automobile Sales",
            "type":"Retail Goods"
        }
    ],
    "sg:phone":"+1 509 943 6003",
    "sg:postcode":"99352",
    "sg:province":"WA",
    "sg:tags":[
        "used"
    ],
    "wof:name":"Budget Auto Sales",
    "wof:placetype":"venue"
},
  "geometry": {"coordinates":[-119.28489,46.273058],"type":"Point"}
}