{
  "type": "Feature",
  "properties": {
    "addr:full":"605 E Holland Ave Ste 200 Spokane WA 99218",
    "addr:housenumber":"605",
    "addr:postcode":"99218",
    "addr:street":"E Holland Ave Ste 200",
    "iso:country":"US",
    "sg:address":"605 E Holland Ave Ste 200",
    "sg:city":"Spokane",
    "sg:classifiers":[
        {
            "category":"Health Services",
            "subcategory":"Chiropractor",
            "type":"Services"
        }
    ],
    "sg:phone":"+1 509 465 8400",
    "sg:postcode":"99218",
    "sg:province":"WA",
    "sg:tags":[
        "chiropractic"
    ],
    "wof:name":"Brian Mather P C",
    "wof:placetype":"venue"
},
  "geometry": {"coordinates":[-117.400734,47.74395],"type":"Point"}
}