{
  "type": "Feature",
  "properties": {
    "addr:full":"2757 Belvidere Ave SW Seattle WA 98126",
    "addr:housenumber":"2757",
    "addr:postcode":"98126",
    "addr:street":"Belvidere Ave Sw",
    "iso:country":"US",
    "sg:address":"2757 Belvidere Ave SW",
    "sg:city":"Seattle",
    "sg:classifiers":[
        {
            "category":"Professional",
            "subcategory":"Computer Services",
            "type":"Services"
        }
    ],
    "sg:phone":"+1 206 972 6787",
    "sg:postcode":"98126",
    "sg:province":"WA",
    "sg:tags":[
        "programing",
        "custom"
    ],
    "wof:name":"Clear Mobility",
    "wof:placetype":"venue"
},
  "geometry": {"coordinates":[-122.379261,47.577782],"type":"Point"}
}