{
  "type": "Feature",
  "properties": {
    "iso:country":"US",
    "sg:address":"7675 Perimeter Rd S",
    "sg:city":"Seattle",
    "sg:classifiers":[
        {
            "category":"Airport",
            "type":"Transportation"
        }
    ],
    "sg:phone":"+1 206 762 2205",
    "sg:postcode":"98108",
    "sg:province":"WA",
    "sg:tags":[
        "support",
        "airline"
    ],
    "wof:name":"Aviation Methods Inc",
    "wof:placetype":"venue"
},
  "geometry": {"coordinates":[-122.300414,47.535275],"type":"Point"}
}