{
  "type": "Feature",
  "properties": {
    "addr:full":"1020 Central Ave S Kent WA 98032",
    "addr:housenumber":"1020",
    "addr:postcode":"98032",
    "addr:street":"Central Ave S",
    "iso:country":"US",
    "sg:address":"1020 Central Ave S",
    "sg:city":"Kent",
    "sg:classifiers":[
        {
            "category":"Autos & Motor Vehicles",
            "subcategory":"Auto Supplies",
            "type":"Retail Goods"
        },
        {
            "category":"Retail",
            "subcategory":"Car Wash",
            "type":"Services"
        },
        {
            "category":"Retail",
            "subcategory":"Auto Repair",
            "type":"Services"
        }
    ],
    "sg:phone":"+1 253 520 7777",
    "sg:postcode":"98032",
    "sg:province":"WA",
    "sg:tags":[
        "body",
        "automobile",
        "detailing",
        "part",
        "painting",
        "repairing"
    ],
    "sg:website":"http://Kent.maaco.com",
    "wof:name":"Maaco - Kent",
    "wof:placetype":"venue"
},
  "geometry": {"coordinates":[-122.230024,47.370733],"type":"Point"}
}