{
  "type": "Feature",
  "properties": {
    "addr:full":"1308 Ironwood St Oroville WA 98844",
    "addr:housenumber":"1308",
    "addr:postcode":"98844",
    "addr:street":"Ironwood St",
    "iso:country":"US",
    "sg:address":"1308 Ironwood St",
    "sg:city":"Oroville",
    "sg:classifiers":[
        {
            "category":"Government",
            "subcategory":"Office",
            "type":"Public Place"
        }
    ],
    "sg:phone":"+1 509 476 2926",
    "sg:postcode":"98844",
    "sg:province":"WA",
    "sg:tags":[
        "city"
    ],
    "wof:name":"Oroville City Hall",
    "wof:placetype":"venue"
},
  "geometry": {"coordinates":[-119.43662399999999,48.939654],"type":"Point"}
}