{
  "type": "Feature",
  "properties": {
    "addr:full":"1410 19th Ave NW Issaquah WA 98027",
    "addr:housenumber":"1410",
    "addr:postcode":"98027",
    "addr:street":"19Th Ave Nw",
    "iso:country":"US",
    "sg:address":"1410 19th Ave NW",
    "sg:city":"Issaquah",
    "sg:classifiers":[
        {
            "category":"Wholesale",
            "subcategory":"Machinery & Supplies",
            "type":"Manufacturing & Wholesale Goods"
        }
    ],
    "sg:phone":"+1 425 392 8737",
    "sg:postcode":"98027",
    "sg:province":"WA",
    "sg:tags":[
        "fastener",
        "threaded"
    ],
    "wof:name":"Fastenal Company",
    "wof:placetype":"venue"
},
  "geometry": {"coordinates":[-122.06641999999999,47.545687],"type":"Point"}
}