{
  "type": "Feature",
  "properties": {
    "addr:full":"1314 Lakeside Ave S Seattle WA 98144",
    "addr:housenumber":"1314",
    "addr:postcode":"98144",
    "addr:street":"Lakeside Ave S",
    "iso:country":"US",
    "sg:address":"1314 Lakeside Ave S",
    "sg:city":"Seattle",
    "sg:classifiers":[
        {
            "category":"Professional",
            "subcategory":"Management & Consulting",
            "type":"Services"
        }
    ],
    "sg:phone":"+1 206 322 5522",
    "sg:postcode":"98144",
    "sg:province":"WA",
    "sg:tags":[
        "business"
    ],
    "wof:name":"RCA Consulting Services",
    "wof:placetype":"venue"
},
  "geometry": {"coordinates":[-122.28706099999999,47.591561],"type":"Point"}
}