{
  "type": "Feature",
  "properties": {
    "addr:full":"5808 Summitview Ave Yakima WA 98908",
    "addr:housenumber":"5808",
    "addr:postcode":"98908",
    "addr:street":"Summitview Ave",
    "iso:country":"US",
    "sg:address":"5808 Summitview Ave",
    "sg:city":"Yakima",
    "sg:classifiers":[
        {
            "category":"Communications",
            "subcategory":"Film & Video Production",
            "type":"Services"
        }
    ],
    "sg:phone":"+1 509 966 0644",
    "sg:postcode":"98908",
    "sg:province":"WA",
    "sg:tags":[
        "taping"
    ],
    "wof:name":"Absolute Magic Video Prdctns",
    "wof:placetype":"venue"
},
  "geometry": {"coordinates":[-120.58606,46.599954],"type":"Point"}
}