{
  "type": "Feature",
  "properties": {
    "addr:full":"14535 NE 91st St Redmond WA 98052",
    "addr:housenumber":"14535",
    "addr:postcode":"98052",
    "addr:street":"Ne 91St St",
    "iso:country":"US",
    "sg:address":"14535 NE 91st St",
    "sg:city":"Redmond",
    "sg:classifiers":[
        {
            "category":"Building & Trades",
            "subcategory":"Construction",
            "type":"Services"
        }
    ],
    "sg:phone":"+1 425 885 4110",
    "sg:postcode":"98052",
    "sg:province":"WA",
    "sg:tags":[
        "painting",
        "drywall",
        "contractor"
    ],
    "wof:name":"Vanderlip & Company Inc",
    "wof:placetype":"venue"
},
  "geometry": {"coordinates":[-122.144105,47.683132],"type":"Point"}
}