{
  "type": "Feature",
  "properties": {
    "iso:country":"US",
    "sg:address":"14667 126th Ave NE",
    "sg:city":"Woodinville",
    "sg:classifiers":[
        {
            "category":"Professional",
            "subcategory":"Engineering",
            "type":"Services"
        }
    ],
    "sg:phone":"+1 425 488 2621",
    "sg:postcode":"98072",
    "sg:province":"WA",
    "wof:name":"Edr",
    "wof:placetype":"venue"
},
  "geometry": {"coordinates":[-122.17251899999999,47.734796],"type":"Point"}
}