{
  "type": "Feature",
  "properties": {
    "addr:full":"17740 Southcenter Pkwy Seattle WA 98188",
    "addr:housenumber":"17740",
    "addr:postcode":"98188",
    "addr:street":"Southcenter Pkwy",
    "iso:country":"US",
    "sg:address":"17740 Southcenter Pkwy",
    "sg:city":"Seattle",
    "sg:classifiers":[
        {
            "category":"Home & Garden",
            "subcategory":"Furniture",
            "type":"Retail Goods"
        }
    ],
    "sg:phone":"+1 206 575 1984",
    "sg:postcode":"98188",
    "sg:province":"WA",
    "wof:name":"Krauses Custom Crafted Furn",
    "wof:placetype":"venue"
},
  "geometry": {"coordinates":[-122.26221200000001,47.447227],"type":"Point"}
}