{
  "type": "Feature",
  "properties": {
    "addr:full":"2955 224th Pl SE Sammamish WA 98075",
    "addr:housenumber":"2955",
    "addr:postcode":"98075",
    "addr:street":"224Th Pl Se",
    "iso:country":"US",
    "sg:address":"2955 224th Pl SE",
    "sg:city":"Sammamish",
    "sg:classifiers":[
        {
            "category":"Social Services",
            "type":"Services"
        }
    ],
    "sg:phone":"+1 425 392 3364",
    "sg:postcode":"98075",
    "sg:province":"WA",
    "sg:tags":[
        "counseling"
    ],
    "wof:name":"Personal Best Counseling",
    "wof:placetype":"venue"
},
  "geometry": {"coordinates":[-122.03995399999999,47.583021],"type":"Point"}
}