{
  "type": "Feature",
  "properties": {
    "addr:full":"1317 Hewitt Ave Everett WA 98201",
    "addr:housenumber":"1317",
    "addr:postcode":"98201",
    "addr:street":"Hewitt Ave",
    "iso:country":"US",
    "sg:address":"1317 Hewitt Ave",
    "sg:city":"Everett",
    "sg:classifiers":[
        {
            "category":"Shopping",
            "subcategory":"Florist",
            "type":"Retail Goods"
        }
    ],
    "sg:phone":"+1 425 252 0984",
    "sg:postcode":"98201",
    "sg:province":"WA",
    "wof:name":"Flower Studio",
    "wof:placetype":"venue"
},
  "geometry": {"coordinates":[-122.211624,47.979387],"type":"Point"}
}