{
  "type": "Feature",
  "properties": {
    "addr:full":"171 Lupine Dr Sequim WA 98382",
    "addr:housenumber":"171",
    "addr:postcode":"98382",
    "addr:street":"Lupine Dr",
    "iso:country":"US",
    "sg:address":"171 Lupine Dr",
    "sg:city":"Sequim",
    "sg:classifiers":[
        {
            "category":"Recreation",
            "type":"Entertainment"
        }
    ],
    "sg:phone":"+1 360 582 0220",
    "sg:postcode":"98382",
    "sg:province":"WA",
    "sg:tags":[
        "air",
        "show"
    ],
    "wof:name":"Russian War Birds Air Shows",
    "wof:placetype":"venue"
},
  "geometry": {"coordinates":[-122.923529,48.093451],"type":"Point"}
}