{
  "type": "Feature",
  "properties": {
    "addr:full":"200 SE Front St Winlock WA 98596",
    "addr:housenumber":"200",
    "addr:postcode":"98596",
    "addr:street":"Se Front St",
    "iso:country":"US",
    "sg:address":"200 SE Front St",
    "sg:city":"Winlock",
    "sg:classifiers":[
        {
            "category":"Building & Trades",
            "subcategory":"Construction",
            "type":"Services"
        }
    ],
    "sg:phone":"+1 360 785 3282",
    "sg:postcode":"98596",
    "sg:province":"WA",
    "sg:tags":[
        "tile-contractors"
    ],
    "wof:name":"Totten Tileworks",
    "wof:placetype":"venue"
},
  "geometry": {"coordinates":[-122.93754,46.490978],"type":"Point"}
}