{
  "type": "Feature",
  "properties": {
    "addr:full":"419 Covington Ct Snohomish WA 98290",
    "addr:housenumber":"419",
    "addr:postcode":"98290",
    "addr:street":"Covington Ct",
    "iso:country":"US",
    "sg:address":"419 Covington Ct",
    "sg:city":"Snohomish",
    "sg:classifiers":[
        {
            "category":"Manufacturing",
            "subcategory":"Food",
            "type":"Manufacturing & Wholesale Goods"
        }
    ],
    "sg:phone":"+1 360 563 5419",
    "sg:postcode":"98290",
    "sg:province":"WA",
    "sg:tags":[
        "mfg"
    ],
    "wof:name":"Viva Diva Designs",
    "wof:placetype":"venue"
},
  "geometry": {"coordinates":[-122.110174,47.917695],"type":"Point"}
}