{
  "type": "Feature",
  "properties": {
    "addr:full":"3224 4th Ave S Seattle WA 98134",
    "addr:housenumber":"3224",
    "addr:postcode":"98134",
    "addr:street":"4Th Ave S",
    "iso:country":"US",
    "sg:address":"3224 4th Ave S",
    "sg:city":"Seattle",
    "sg:classifiers":[
        {
            "category":"Government",
            "subcategory":"Fire Station",
            "type":"Public Place"
        }
    ],
    "sg:phone":"+1 206 386 1400",
    "sg:postcode":"98134",
    "sg:province":"WA",
    "sg:tags":[
        "protection"
    ],
    "wof:name":"Fire Station 14",
    "wof:placetype":"venue"
},
  "geometry": {"coordinates":[-122.328986,47.574661],"type":"Point"}
}