{
  "type": "Feature",
  "properties": {
    "addr:full":"4518 S 124th St Seattle WA 98178",
    "addr:housenumber":"4518",
    "addr:postcode":"98178",
    "addr:street":"S 124Th St",
    "iso:country":"US",
    "sg:address":"4518 S 124th St",
    "sg:city":"Seattle",
    "sg:classifiers":[
        {
            "category":"Building & Trades",
            "subcategory":"Cleaning & Sanitation",
            "type":"Services"
        }
    ],
    "sg:phone":"+1 206 762 7332",
    "sg:postcode":"98178",
    "sg:province":"WA",
    "sg:tags":[
        "maintenance",
        "cleaners-interior"
    ],
    "wof:name":"Tamara's House Cleaning",
    "wof:placetype":"venue"
},
  "geometry": {"coordinates":[-122.276791,47.492327],"type":"Point"}
}