{
  "type": "Feature",
  "properties": {
    "addr:full":"655 Clark Rd Bellingham WA 98225",
    "addr:housenumber":"655",
    "addr:postcode":"98225",
    "addr:street":"Clark Rd",
    "iso:country":"US",
    "sg:address":"655 Clark Rd",
    "sg:city":"Bellingham",
    "sg:classifiers":[
        {
            "category":"Education",
            "subcategory":"Special Training",
            "type":"Public Place"
        }
    ],
    "sg:phone":"+1 360 650 3573",
    "sg:postcode":"98225",
    "sg:province":"WA",
    "wof:name":"Sue David",
    "wof:placetype":"venue"
},
  "geometry": {"coordinates":[-122.507578,48.703546],"type":"Point"}
}