{
  "type": "Feature",
  "properties": {
    "addr:full":"2900 Eastlake Ave E Seattle WA 98102",
    "addr:housenumber":"2900",
    "addr:postcode":"98102",
    "addr:street":"Eastlake Ave E",
    "iso:country":"US",
    "sg:address":"2900 Eastlake Ave E",
    "sg:city":"Seattle",
    "sg:classifiers":[
        {
            "category":"Organizations",
            "subcategory":"Non-profit Organization",
            "type":"Services"
        }
    ],
    "sg:phone":"+1 206 726 8580",
    "sg:postcode":"98102",
    "sg:province":"WA",
    "sg:tags":[
        "social"
    ],
    "wof:name":"Washington Alliance Tech Wkr",
    "wof:placetype":"venue"
},
  "geometry": {"coordinates":[-122.32392400000001,47.647687],"type":"Point"}
}