{
  "type": "Feature",
  "properties": {
    "addr:full":"2820 Oakes Ave Everett WA 98201",
    "addr:postcode":"2820;98201",
    "addr:street":"Oakes Ave",
    "iso:country":"US",
    "sg:address":"2820 Oakes Ave",
    "sg:city":"Everett",
    "sg:classifiers":[
        {
            "category":"Recreation",
            "type":"Entertainment"
        }
    ],
    "sg:phone":"+1 425 252 5336",
    "sg:postcode":"98201",
    "sg:province":"WA",
    "sg:tags":[
        "bingo",
        "game",
        "association",
        "civic"
    ],
    "wof:name":"North Everett Lions Club Bingo",
    "wof:placetype":"venue"
},
  "geometry": {"coordinates":[-122.204466,47.98012],"type":"Point"}
}