{
  "type": "Feature",
  "properties": {
    "addr:full":"5701 Rainier Ave S Seattle WA 98118",
    "addr:housenumber":"5701",
    "addr:postcode":"98118",
    "addr:street":"Rainier Ave S",
    "iso:country":"US",
    "sg:address":"5701 Rainier Ave S",
    "sg:city":"Seattle",
    "sg:classifiers":[
        {
            "category":"Shopping",
            "subcategory":"Clothing, Apparel, & Fashions",
            "type":"Retail Goods"
        }
    ],
    "sg:phone":"+1 206 723 6340",
    "sg:postcode":"98118",
    "sg:province":"WA",
    "sg:tags":[
        "apparel",
        "women's"
    ],
    "wof:name":"Ba Baa Bala",
    "wof:placetype":"venue"
},
  "geometry": {"coordinates":[-122.27767900000001,47.551182],"type":"Point"}
}