{
  "type": "Feature",
  "properties": {
    "addr:full":"11906 58th Pl SE Snohomish WA 98290",
    "addr:housenumber":"11906",
    "addr:postcode":"98290",
    "addr:street":"58Th Pl Se",
    "iso:country":"US",
    "sg:address":"11906 58th Pl SE",
    "sg:city":"Snohomish",
    "sg:classifiers":[
        {
            "category":"Building & Trades",
            "subcategory":"Landscaping Services",
            "type":"Services"
        }
    ],
    "sg:phone":"+1 425 931 1275",
    "sg:postcode":"98290",
    "sg:province":"WA",
    "sg:tags":[
        "landscape"
    ],
    "wof:name":"Profinish Landscaping",
    "wof:placetype":"venue"
},
  "geometry": {"coordinates":[-122.06914,47.94331],"type":"Point"}
}