{
  "type": "Feature",
  "properties": {
    "iso:country":"US",
    "sg:address":"689 Dry Gulch Rd",
    "sg:city":"Colville",
    "sg:classifiers":[
        {
            "category":"Manufacturing",
            "subcategory":"Apparel",
            "type":"Manufacturing & Wholesale Goods"
        }
    ],
    "sg:phone":"+1 509 684 0751",
    "sg:postcode":"99114",
    "sg:province":"WA",
    "wof:name":"Fast Frames",
    "wof:placetype":"venue"
},
  "geometry": {"coordinates":[-117.83002500000001,48.606587],"type":"Point"}
}