{
  "type": "Feature",
  "properties": {
    "addr:full":"3728 N 28th St Tacoma WA 98407",
    "addr:housenumber":"3728",
    "addr:postcode":"98407",
    "addr:street":"N 28Th St",
    "iso:country":"US",
    "sg:address":"3728 N 28th St",
    "sg:city":"Tacoma",
    "sg:classifiers":[
        {
            "category":"Health Services",
            "subcategory":"Doctor",
            "type":"Services"
        }
    ],
    "sg:phone":"+1 253 752 8378",
    "sg:postcode":"98407",
    "sg:province":"WA",
    "wof:name":"Gary A Murphy DDS",
    "wof:placetype":"venue"
},
  "geometry": {"coordinates":[-122.488851,47.272918],"type":"Point"}
}