{
  "type": "Feature",
  "properties": {
    "addr:full":"423 Stewart St Seattle WA 98101",
    "addr:housenumber":"423",
    "addr:postcode":"98101",
    "addr:street":"Stewart St",
    "iso:country":"US",
    "sg:address":"423 Stewart St",
    "sg:city":"Seattle",
    "sg:classifiers":[
        {
            "category":"Bars & Pubs",
            "type":"Food & Drink"
        }
    ],
    "sg:phone":"+1 206 441 3303",
    "sg:postcode":"98101",
    "sg:province":"WA",
    "sg:tags":[
        "drinking"
    ],
    "wof:name":"Metropolitan Improvement Distr",
    "wof:placetype":"venue"
},
  "geometry": {"coordinates":[-122.337924,47.612776],"type":"Point"}
}