{
  "type": "Feature",
  "properties": {
    "addr:full":"11730 118th Ave NE Ste 20 Kirkland WA 98034",
    "addr:housenumber":"11730",
    "addr:postcode":"98034",
    "addr:street":"118Th Ave Ne Ste 20",
    "iso:country":"US",
    "sg:address":"11730 118th Ave NE Ste 20",
    "sg:city":"Kirkland",
    "sg:classifiers":[
        {
            "category":"Professional",
            "subcategory":"Engineering",
            "type":"Services"
        },
        {
            "category":"Wholesale",
            "subcategory":"Electrical",
            "type":"Manufacturing & Wholesale Goods"
        }
    ],
    "sg:phone":"+1 425 825 8448",
    "sg:postcode":"98034",
    "sg:province":"WA",
    "sg:tags":[
        "system",
        "systems-wholesale",
        "equipment",
        "air conditioning",
        "manufacturer"
    ],
    "sg:website":"http://www.hadco-supply.com",
    "wof:name":"Hadco Supply",
    "wof:placetype":"venue"
},
  "geometry": {"coordinates":[-122.182591,47.70566],"type":"Point"}
}