{
  "type": "Feature",
  "properties": {
    "addr:full":"1356 Cole St Enumclaw WA 98022",
    "addr:housenumber":"1356",
    "addr:postcode":"98022",
    "addr:street":"Cole St",
    "iso:country":"US",
    "sg:address":"1356 Cole St",
    "sg:city":"Enumclaw",
    "sg:classifiers":[
        {
            "category":"Social Services",
            "type":"Services"
        }
    ],
    "sg:phone":"+1 360 825 4586",
    "sg:postcode":"98022",
    "sg:province":"WA",
    "sg:tags":[
        "executive"
    ],
    "wof:name":"Auburn Youth Center",
    "wof:placetype":"venue"
},
  "geometry": {"coordinates":[-121.991941,47.201187],"type":"Point"}
}