{
  "type": "Feature",
  "properties": {
    "addr:full":"3434 S 144th St Apt 138 Tukwila WA 98168",
    "addr:housenumber":"3434;138",
    "addr:postcode":"98168",
    "addr:street":"S 144Th St Apt",
    "iso:country":"US",
    "sg:address":"3434 S 144th St Apt 138",
    "sg:city":"Tukwila",
    "sg:classifiers":[
        {
            "category":"Building & Trades",
            "subcategory":"Cleaning & Sanitation",
            "type":"Services"
        }
    ],
    "sg:phone":"+1 206 248 7396",
    "sg:postcode":"98168",
    "sg:province":"WA",
    "sg:tags":[
        "janitorial"
    ],
    "wof:name":"Open Works By Mladen",
    "wof:placetype":"venue"
},
  "geometry": {"coordinates":[-122.288602,47.474265],"type":"Point"}
}