{
  "type": "Feature",
  "properties": {
    "addr:full":"8305 N Valerie St Spokane WA 99208",
    "addr:housenumber":"8305",
    "addr:postcode":"99208",
    "addr:street":"N Valerie St",
    "iso:country":"US",
    "sg:address":"8305 N Valerie St",
    "sg:city":"Spokane",
    "sg:classifiers":[
        {
            "category":"Professional",
            "type":"Services"
        }
    ],
    "sg:phone":"+1 509 465 4997",
    "sg:postcode":"99208",
    "sg:province":"WA",
    "wof:name":"Ducks Unlimited Inc",
    "wof:placetype":"venue"
},
  "geometry": {"coordinates":[-117.48805299999999,47.737114],"type":"Point"}
}