{
  "type": "Feature",
  "properties": {
    "addr:full":"13725 32nd Ave NE Seattle WA 98125",
    "addr:housenumber":"13725",
    "addr:postcode":"98125",
    "addr:street":"32Nd Ave Ne",
    "iso:country":"US",
    "sg:address":"13725 32nd Ave NE",
    "sg:city":"Seattle",
    "sg:classifiers":[
        {
            "category":"Real Estate",
            "subcategory":"Real Estate Services",
            "type":"Services"
        },
        {
            "category":"Real Estate",
            "subcategory":"Real Estate Operator",
            "type":"Services"
        }
    ],
    "sg:phone":"+1 206 365 1893",
    "sg:postcode":"98125",
    "sg:province":"WA",
    "sg:tags":[
        "vacancy",
        "apartment",
        "rental",
        "finder",
        "listing"
    ],
    "wof:name":"Clock Tower Apartments",
    "wof:placetype":"venue"
},
  "geometry": {"coordinates":[-122.29474399999999,47.728974],"type":"Point"}
}