{
  "type": "Feature",
  "properties": {
    "addr:full":"730 E Main St Othello WA 99344",
    "addr:housenumber":"730",
    "addr:postcode":"99344",
    "addr:street":"E Main St",
    "iso:country":"US",
    "sg:address":"730 E Main St",
    "sg:city":"Othello",
    "sg:classifiers":[
        {
            "category":"Home & Garden",
            "subcategory":"Household Appliances",
            "type":"Retail Goods"
        }
    ],
    "sg:phone":"+1 509 488 7025",
    "sg:postcode":"99344",
    "sg:province":"WA",
    "wof:name":"Sears Authorized Retail Dealer",
    "wof:placetype":"venue"
},
  "geometry": {"coordinates":[-119.164496,46.826122],"type":"Point"}
}