{
  "type": "Feature",
  "properties": {
    "addr:full":"25515 NE 46th Ave Ridgefield WA 98642",
    "addr:housenumber":"25515",
    "addr:postcode":"98642",
    "addr:street":"Ne 46Th Ave",
    "iso:country":"US",
    "sg:address":"25515 NE 46th Ave",
    "sg:city":"Ridgefield",
    "sg:classifiers":[
        {
            "category":"Recreation",
            "type":"Entertainment"
        }
    ],
    "sg:phone":"+1 360 887 4066",
    "sg:postcode":"98642",
    "sg:province":"WA",
    "sg:tags":[
        "martial",
        "arts",
        "instruction"
    ],
    "wof:name":"Ridgefield Tae KWON Do",
    "wof:placetype":"venue"
},
  "geometry": {"coordinates":[-122.624217,45.808634],"type":"Point"}
}