{
  "type": "Feature",
  "properties": {
    "addr:full":"1350 Bay St Port Orchard WA 98366",
    "addr:housenumber":"1350",
    "addr:postcode":"98366",
    "addr:street":"Bay St",
    "iso:country":"US",
    "sg:address":"1350 Bay St",
    "sg:city":"Port Orchard",
    "sg:classifiers":[
        {
            "category":"Retail",
            "subcategory":"Auto Repair",
            "type":"Services"
        }
    ],
    "sg:phone":"+1 360 874 9101",
    "sg:postcode":"98366",
    "sg:province":"WA",
    "sg:tags":[
        "automotive"
    ],
    "wof:name":"Midas Muffler",
    "wof:placetype":"venue"
},
  "geometry": {"coordinates":[-122.626391,47.542239],"type":"Point"}
}