{
  "type": "Feature",
  "properties": {
    "addr:full":"Northwest Rooms at Seattle Center 305 Harrison Street Seattle WA 98109",
    "addr:housenumber":"305",
    "addr:postcode":"98109",
    "addr:street":"Harrison Street",
    "iso:country":"US",
    "sg:address":"Northwest Rooms at Seattle Center 305 Harrison Street",
    "sg:city":"Seattle",
    "sg:classifiers":[
        {
            "category":"Coffee & Tea",
            "type":"Food & Drink"
        },
        {
            "category":"Restaurant",
            "type":"Food & Drink"
        }
    ],
    "sg:postcode":"98109",
    "sg:province":"WA",
    "sg:tags":[
        "flavor",
        "local"
    ],
    "sg:website":"www.nwteafestival.com",
    "wof:name":"Northwest Tea Festival",
    "wof:placetype":"venue"
},
  "geometry": {"coordinates":[-122.349227,47.621814],"type":"Point"}
}