{
  "type": "Feature",
  "properties": {
    "addr:full":"9013 Key Peninsula Hwy N Lakebay WA 98349",
    "addr:housenumber":"9013",
    "addr:postcode":"98349",
    "addr:street":"Key Peninsula Hwy N Lakebay",
    "iso:country":"US",
    "sg:address":"9013 Key Peninsula Hwy N",
    "sg:city":"Lakebay",
    "sg:classifiers":[
        {
            "category":"Professional",
            "subcategory":"Computer Services",
            "type":"Services"
        }
    ],
    "sg:phone":"+1 253 884 5150",
    "sg:postcode":"98349",
    "sg:province":"WA",
    "sg:tags":[
        "repair"
    ],
    "wof:name":"K C Computer Repair",
    "wof:placetype":"venue"
},
  "geometry": {"coordinates":[-122.745583,47.340026],"type":"Point"}
}