{
  "type": "Feature",
  "properties": {
    "addr:full":"12914 SE 95th Way Newcastle WA 98056",
    "addr:postcode":"12914;98056",
    "addr:street":"Se 95Th Way",
    "iso:country":"US",
    "sg:address":"12914 SE 95th Way",
    "sg:city":"Newcastle",
    "sg:classifiers":[
        {
            "category":"Building & Trades",
            "subcategory":"Construction",
            "type":"Services"
        }
    ],
    "sg:phone":"+1 425 271 4464",
    "sg:postcode":"98056",
    "sg:province":"WA",
    "sg:tags":[
        "contractor",
        "mason"
    ],
    "wof:name":"Buckley Masonry Randy",
    "wof:placetype":"venue"
},
  "geometry": {"coordinates":[-122.168282,47.518058],"type":"Point"}
}