{
  "type": "Feature",
  "properties": {
    "addr:full":"3320 Gravelly Beach Loop NW Olympia WA 98502",
    "addr:housenumber":"3320",
    "addr:postcode":"olympia wa 98502",
    "addr:street":"Gravelly Beach Loop Nw",
    "iso:country":"US",
    "sg:address":"3320 Gravelly Beach Loop NW",
    "sg:city":"Olympia",
    "sg:classifiers":[
        {
            "category":"Farming",
            "subcategory":"Fish & Marine Products",
            "type":"Manufacturing & Wholesale Goods"
        }
    ],
    "sg:phone":"+1 360 866 8989",
    "sg:postcode":"98502",
    "sg:province":"WA",
    "sg:tags":[
        "shellfish",
        "fishing"
    ],
    "wof:name":"Gravelly Beach Shellfish Inc",
    "wof:placetype":"venue"
},
  "geometry": {"coordinates":[-122.961445,47.105578],"type":"Point"}
}