{
  "type": "Feature",
  "properties": {
    "iso:country":"US",
    "sg:address":"4900 9th Ave NW",
    "sg:city":"Seattle",
    "sg:classifiers":[
        {
            "category":"Recreation",
            "subcategory":"Marina",
            "type":"Entertainment"
        }
    ],
    "sg:phone":"+1 206 789 3798",
    "sg:postcode":"98107",
    "sg:province":"WA",
    "sg:tags":[
        "repairing",
        "boat"
    ],
    "wof:name":"Dawn Enterprises",
    "wof:placetype":"venue"
},
  "geometry": {"coordinates":[-122.368611,47.665037],"type":"Point"}
}