{
  "type": "Feature",
  "properties": {
    "addr:full":"12694 Ranger Rd Leavenworth WA 98826",
    "addr:housenumber":"12694",
    "addr:postcode":"98826",
    "addr:street":"Ranger Rd",
    "iso:country":"US",
    "sg:address":"12694 Ranger Rd",
    "sg:city":"Leavenworth",
    "sg:classifiers":[
        {
            "category":"Building & Trades",
            "subcategory":"Construction",
            "type":"Services"
        }
    ],
    "sg:phone":"+1 509 548 1212",
    "sg:postcode":"98826",
    "sg:province":"WA",
    "sg:tags":[
        "house",
        "general",
        "contractor"
    ],
    "wof:name":"Bloom Construction Services",
    "wof:placetype":"venue"
},
  "geometry": {"coordinates":[-120.678122,47.602604],"type":"Point"}
}