{
  "type": "Feature",
  "properties": {
    "iso:country":"US",
    "sg:address":"2399 Mount Baker Hwy",
    "sg:city":"Bellingham",
    "sg:classifiers":[
        {
            "category":"Manufacturing",
            "subcategory":"Tools & Machinery",
            "type":"Manufacturing & Wholesale Goods"
        }
    ],
    "sg:phone":"+1 360 733 2509",
    "sg:postcode":"98226",
    "sg:province":"WA",
    "sg:tags":[
        "machine",
        "shop"
    ],
    "wof:name":"Circle F Enterprises Inc",
    "wof:placetype":"venue"
},
  "geometry": {"coordinates":[-122.361003,48.803739],"type":"Point"}
}