{
  "type": "Feature",
  "properties": {
    "addr:full":"1205 E Pike St Seattle WA 98122",
    "addr:housenumber":"1205",
    "addr:postcode":"98122",
    "addr:street":"E Pike St",
    "iso:country":"US",
    "sg:address":"1205 E Pike St",
    "sg:city":"Seattle",
    "sg:classifiers":[
        {
            "category":"Shopping",
            "subcategory":"Clothing, Apparel, & Fashions",
            "type":"Retail Goods"
        }
    ],
    "sg:phone":"+1 206 329 6339",
    "sg:postcode":"98122",
    "sg:province":"WA",
    "sg:tags":[
        "uniform"
    ],
    "wof:name":"Bristol Bay Clothing Co",
    "wof:placetype":"venue"
},
  "geometry": {"coordinates":[-122.315566,47.614036],"type":"Point"}
}