{
  "type": "Feature",
  "properties": {
    "addr:full":"8201 164th Ave NE Suite 305 Redmond WA 98052",
    "addr:housenumber":"8201",
    "addr:postcode":"98052",
    "addr:street":"164Th Ave Ne Suite 305",
    "iso:country":"US",
    "sg:address":"8201 164th Ave NE Suite 305",
    "sg:city":"Redmond",
    "sg:classifiers":[
        {
            "category":"Professional",
            "subcategory":"Computer Services",
            "type":"Services"
        }
    ],
    "sg:phone":"+1 425 881 9475",
    "sg:postcode":"98052",
    "sg:province":"WA",
    "sg:tags":[
        "ecards",
        "scrapbooking"
    ],
    "sg:website":"http://smilebox.com",
    "wof:name":"Smilebox ",
    "wof:placetype":"venue"
},
  "geometry": {"coordinates":[-122.121689,47.676087],"type":"Point"}
}