{
  "type": "Feature",
  "properties": {
    "addr:full":"18850 8th Ave S Seattle WA 98148",
    "addr:housenumber":"18850",
    "addr:postcode":"98148",
    "addr:street":"8Th Ave S",
    "iso:country":"US",
    "sg:address":"18850 8th Ave S",
    "sg:city":"Seattle",
    "sg:classifiers":[
        {
            "category":"Freight",
            "type":"Transportation"
        }
    ],
    "sg:phone":"+1 206 835 7193",
    "sg:postcode":"98148",
    "sg:province":"WA",
    "sg:tags":[
        "forwarding",
        "air"
    ],
    "wof:name":"A E I",
    "wof:placetype":"venue"
},
  "geometry": {"coordinates":[-122.324744,47.433015],"type":"Point"}
}