{
  "type": "Feature",
  "properties": {
    "addr:full":"7109 S Brookshire Ct Spokane WA 99223",
    "addr:housenumber":"7109",
    "addr:postcode":"99223",
    "addr:street":"S Brookshire Ct",
    "iso:country":"US",
    "sg:address":"7109 S Brookshire Ct",
    "sg:city":"Spokane",
    "sg:classifiers":[
        {
            "category":"Shopping",
            "subcategory":"Gifts & Souvenirs",
            "type":"Retail Goods"
        }
    ],
    "sg:phone":"+1 509 448 9205",
    "sg:postcode":"99223",
    "sg:province":"WA",
    "wof:name":"Sugar Creations",
    "wof:placetype":"venue"
},
  "geometry": {"coordinates":[-117.39820899999999,47.589515],"type":"Point"}
}