{
  "type": "Feature",
  "properties": {
    "addr:full":"1000 Thomas St Seattle WA 98109",
    "addr:housenumber":"1000",
    "addr:postcode":"98109",
    "addr:street":"Thomas St",
    "iso:country":"US",
    "sg:address":"1000 Thomas St",
    "sg:city":"Seattle",
    "sg:classifiers":[
        {
            "category":"Professional",
            "subcategory":"Research",
            "type":"Services"
        }
    ],
    "sg:phone":"+1 206 728 4900",
    "sg:postcode":"98109",
    "sg:province":"WA",
    "sg:tags":[
        "commercial",
        "physical"
    ],
    "wof:name":"Genetic Systems Corp",
    "wof:placetype":"venue"
},
  "geometry": {"coordinates":[-122.335859,47.620861],"type":"Point"}
}