{
  "type": "Feature",
  "properties": {
    "addr:full":"3449 Redwood Ave Bellingham WA 98225",
    "addr:housenumber":"3449",
    "addr:postcode":"98225",
    "addr:street":"Redwood Ave",
    "iso:country":"US",
    "sg:address":"3449 Redwood Ave",
    "sg:city":"Bellingham",
    "sg:classifiers":[
        {
            "category":"Manufacturing",
            "subcategory":"Chemicals & Compounds",
            "type":"Manufacturing & Wholesale Goods"
        }
    ],
    "sg:phone":"+1 360 676 1315",
    "sg:postcode":"98225",
    "sg:province":"WA",
    "sg:tags":[
        "preparation",
        "toilet",
        "mfg"
    ],
    "wof:name":"Bella Berry Lips",
    "wof:placetype":"venue"
},
  "geometry": {"coordinates":[-122.523236,48.77838],"type":"Point"}
}