{
  "type": "Feature",
  "properties": {
    "addr:full":"9205 220th St SW Edmonds WA 98020",
    "addr:housenumber":"9205",
    "addr:postcode":"98020",
    "addr:street":"220Th St Sw",
    "iso:country":"US",
    "sg:address":"9205 220th St SW",
    "sg:city":"Edmonds",
    "sg:classifiers":[
        {
            "category":"Home & Garden",
            "subcategory":"Home Furnishings",
            "type":"Retail Goods"
        }
    ],
    "sg:phone":"+1 425 778 2566",
    "sg:postcode":"98020",
    "sg:province":"WA",
    "wof:name":"Dorothys Draperies",
    "wof:placetype":"venue"
},
  "geometry": {"coordinates":[-122.357466,47.799663],"type":"Point"}
}