{
  "type": "Feature",
  "properties": {
    "addr:full":"230 W 5th St Port Angeles WA 98362",
    "addr:housenumber":"230",
    "addr:postcode":"98362",
    "addr:street":"W 5Th St",
    "iso:country":"US",
    "sg:address":"230 W 5th St",
    "sg:city":"Port Angeles",
    "sg:classifiers":[
        {
            "category":"Professional",
            "subcategory":"Management & Consulting",
            "type":"Services"
        }
    ],
    "sg:phone":"+1 360 457 6362",
    "sg:postcode":"98362",
    "sg:province":"WA",
    "sg:tags":[
        "business"
    ],
    "wof:name":"Safety & Violence Education",
    "wof:placetype":"venue"
},
  "geometry": {"coordinates":[-123.44013200000001,48.116849],"type":"Point"}
}