{
  "type": "Feature",
  "properties": {
    "addr:full":"4202 Corliss Ave N Seattle WA 98103",
    "addr:housenumber":"4202",
    "addr:postcode":"98103",
    "addr:street":"Corliss Ave N",
    "iso:country":"US",
    "sg:address":"4202 Corliss Ave N",
    "sg:city":"Seattle",
    "sg:classifiers":[
        {
            "category":"Home & Garden",
            "subcategory":"Building Materials",
            "type":"Retail Goods"
        },
        {
            "category":"Building & Trades",
            "subcategory":"Construction",
            "type":"Services"
        }
    ],
    "sg:phone":"+1 206 783 5675",
    "sg:postcode":"98103",
    "sg:province":"WA",
    "sg:tags":[
        "concrete",
        "staining",
        "contractor"
    ],
    "wof:name":"Bower Construction",
    "wof:placetype":"venue"
},
  "geometry": {"coordinates":[-122.33139,47.657982],"type":"Point"}
}