{
  "type": "Feature",
  "properties": {
    "addr:full":"21244 116th Ave SE Kent WA 98031",
    "addr:housenumber":"21244",
    "addr:postcode":"98031",
    "addr:street":"116Th Ave Se",
    "iso:country":"US",
    "sg:address":"21244 116th Ave SE",
    "sg:city":"Kent",
    "sg:classifiers":[
        {
            "category":"Professional",
            "subcategory":"Management & Consulting",
            "type":"Services"
        }
    ],
    "sg:phone":"+1 253 852 3081",
    "sg:postcode":"98031",
    "sg:province":"WA",
    "sg:tags":[
        "public",
        "relations"
    ],
    "wof:name":"Pristine Promotions",
    "wof:placetype":"venue"
},
  "geometry": {"coordinates":[-122.186689,47.411836],"type":"Point"}
}