{
  "type": "Feature",
  "properties": {
    "addr:full":"5300 34th Ave NW Seattle WA 98107",
    "addr:housenumber":"5300",
    "addr:postcode":"98107",
    "addr:street":"34Th Ave Nw",
    "iso:country":"US",
    "sg:address":"5300 34th Ave NW",
    "sg:city":"Seattle",
    "sg:classifiers":[
        {
            "category":"Retail",
            "subcategory":"Event Space",
            "type":"Services"
        }
    ],
    "sg:phone":"+1 206 524 4918",
    "sg:postcode":"98107",
    "sg:province":"WA",
    "sg:tags":[
        "venue"
    ],
    "sg:website":"www.thecanalseattle.com/",
    "wof:name":"The Canal",
    "wof:placetype":"venue"
},
  "geometry": {"coordinates":[-122.401179,47.667766],"type":"Point"}
}