{
  "type": "Feature",
  "properties": {
    "addr:full":"229 S 1st St Shelton WA 98584",
    "addr:housenumber":"229",
    "addr:postcode":"98584",
    "addr:street":"S 1St St",
    "iso:country":"US",
    "sg:address":"229 S 1st St",
    "sg:city":"Shelton",
    "sg:classifiers":[
        {
            "category":"Professional",
            "subcategory":"Business Services",
            "type":"Services"
        }
    ],
    "sg:phone":"+1 360 427 1277",
    "sg:postcode":"98584",
    "sg:province":"WA",
    "wof:name":"Rejos",
    "wof:placetype":"venue"
},
  "geometry": {"coordinates":[-123.10038,47.211788],"type":"Point"}
}