{
  "type": "Feature",
  "properties": {
    "addr:full":"2501 6th Ave Tacoma WA 98406",
    "addr:housenumber":"2501",
    "addr:postcode":"98406",
    "addr:street":"6Th Ave",
    "iso:country":"US",
    "sg:address":"2501 6th Ave",
    "sg:city":"Tacoma",
    "sg:classifiers":[
        {
            "category":"Professional",
            "subcategory":"Computer Services",
            "type":"Services"
        }
    ],
    "sg:phone":"+1 253 272 3001",
    "sg:postcode":"98406",
    "sg:province":"WA",
    "sg:tags":[
        "internet"
    ],
    "wof:name":"Blue Box Group LLC",
    "wof:placetype":"venue"
},
  "geometry": {"coordinates":[-122.47023,47.255441],"type":"Point"}
}