{
  "type": "Feature",
  "properties": {
    "addr:full":"18133 52nd Ave W Lynnwood WA 98037",
    "addr:housenumber":"18133",
    "addr:postcode":"98037",
    "addr:street":"52Nd Ave W",
    "iso:country":"US",
    "sg:address":"18133 52nd Ave W",
    "sg:city":"Lynnwood",
    "sg:classifiers":[
        {
            "category":"Social Services",
            "subcategory":"Child Care",
            "type":"Services"
        }
    ],
    "sg:phone":"+1 425 744 1212",
    "sg:postcode":"98037",
    "sg:province":"WA",
    "sg:tags":[
        "day"
    ],
    "wof:name":"Another Best Child Care",
    "wof:placetype":"venue"
},
  "geometry": {"coordinates":[-122.303507,47.834322],"type":"Point"}
}