{
  "type": "Feature",
  "properties": {
    "addr:full":"7833 12th Ave NE Seattle WA 98115",
    "addr:housenumber":"7833",
    "addr:postcode":"98115",
    "addr:street":"12Th Ave Ne",
    "iso:country":"US",
    "sg:address":"7833 12th Ave NE",
    "sg:city":"Seattle",
    "sg:classifiers":[
        {
            "category":"Shopping",
            "subcategory":"Used Merchandise",
            "type":"Retail Goods"
        }
    ],
    "sg:phone":"+1 206 527 7965",
    "sg:postcode":"98115",
    "sg:province":"WA",
    "wof:name":"Recycled Relics",
    "wof:placetype":"venue"
},
  "geometry": {"coordinates":[-122.315028,47.686486],"type":"Point"}
}