{
  "type": "Feature",
  "properties": {
    "addr:full":"16301 NE 8th St Bellevue WA 98008",
    "addr:housenumber":"16301",
    "addr:postcode":"98008",
    "addr:street":"Ne 8Th St",
    "iso:country":"US",
    "sg:address":"16301 NE 8th St",
    "sg:city":"Bellevue",
    "sg:classifiers":[
        {
            "category":"Professional",
            "subcategory":"Computer Services",
            "type":"Services"
        }
    ],
    "sg:phone":"+1 425 641 5858",
    "sg:postcode":"98008",
    "sg:province":"WA",
    "sg:tags":[
        "prepackaged",
        "software"
    ],
    "wof:name":"Client Compass Software",
    "wof:placetype":"venue"
},
  "geometry": {"coordinates":[-122.124521,47.616896],"type":"Point"}
}