{
  "type": "Feature",
  "properties": {
    "addr:full":"14125 SE 11th St Vancouver WA 98683",
    "addr:postcode":"14125;98683",
    "addr:street":"Se 11Th St",
    "iso:country":"US",
    "sg:address":"14125 SE 11th St",
    "sg:city":"Vancouver",
    "sg:classifiers":[
        {
            "category":"Building & Trades",
            "subcategory":"Plumbing",
            "type":"Services"
        }
    ],
    "sg:phone":"+1 360 254 2735",
    "sg:postcode":"98683",
    "sg:province":"WA",
    "sg:tags":[
        "contractor"
    ],
    "wof:name":"Thompson Construction",
    "wof:placetype":"venue"
},
  "geometry": {"coordinates":[-122.527371,45.612744],"type":"Point"}
}