{
  "type": "Feature",
  "properties": {
    "addr:full":"8626 Stevenson Rd Anacortes WA 98221",
    "addr:housenumber":"8626",
    "addr:postcode":"98221",
    "addr:street":"Stevenson Rd",
    "iso:country":"US",
    "sg:address":"8626 Stevenson Rd",
    "sg:city":"Anacortes",
    "sg:classifiers":[
        {
            "category":"Autos & Motor Vehicles",
            "subcategory":"Boat Sales",
            "type":"Retail Goods"
        },
        {
            "category":"Manufacturing",
            "subcategory":"Watercraft",
            "type":"Manufacturing & Wholesale Goods"
        }
    ],
    "sg:phone":"+1 360 293 7766",
    "sg:postcode":"98221",
    "sg:province":"WA",
    "sg:tags":[
        "distributor",
        "repair",
        "builder",
        "maintenance",
        "manufacturer"
    ],
    "wof:name":"The Marine Team Inc",
    "wof:placetype":"venue"
},
  "geometry": {"coordinates":[-122.55394800000001,48.458439],"type":"Point"}
}