{
  "type": "Feature",
  "properties": {
    "addr:full":"2910 E Spring St Seattle WA 98122",
    "addr:housenumber":"2910",
    "addr:postcode":"98122",
    "addr:street":"E Spring St",
    "iso:country":"US",
    "sg:address":"2910 E Spring St",
    "sg:city":"Seattle",
    "sg:classifiers":[
        {
            "category":"Professional",
            "subcategory":"Business Services",
            "type":"Services"
        }
    ],
    "sg:phone":"+1 206 331 1830",
    "sg:postcode":"98122",
    "sg:province":"WA",
    "wof:name":"Youth Educatn & Spt Foundation",
    "wof:placetype":"venue"
},
  "geometry": {"coordinates":[-122.29384899999999,47.61174],"type":"Point"}
}