{
  "type": "Feature",
  "properties": {
    "addr:full":"4201 Bridgeport Way W University Place WA 98466",
    "addr:housenumber":"4201",
    "addr:postcode":"98466",
    "addr:street":"Bridgeport Way W;Place",
    "iso:country":"US",
    "sg:address":"4201 Bridgeport Way W",
    "sg:city":"University Place",
    "sg:classifiers":[
        {
            "category":"Banks & Credit Unions",
            "subcategory":"Investment Brokerage",
            "type":"Services"
        }
    ],
    "sg:phone":"+1 253 564 2104",
    "sg:postcode":"98466",
    "sg:province":"WA",
    "sg:tags":[
        "advisory",
        "financial"
    ],
    "wof:name":"University Place Development",
    "wof:placetype":"venue"
},
  "geometry": {"coordinates":[-122.537116,47.219494],"type":"Point"}
}