{
  "type": "Feature",
  "properties": {
    "addr:full":"803 S 310th Pl Federal Way WA 98003",
    "addr:housenumber":"803",
    "addr:postcode":"98003",
    "addr:street":"S 310Th Pl",
    "iso:country":"US",
    "sg:address":"803 S 310th Pl",
    "sg:city":"Federal Way",
    "sg:classifiers":[
        {
            "category":"Building & Trades",
            "subcategory":"Construction",
            "type":"Services"
        }
    ],
    "sg:phone":"+1 253 347 0827",
    "sg:postcode":"98003",
    "sg:province":"WA",
    "sg:tags":[
        "house"
    ],
    "wof:name":"New World Construction",
    "wof:placetype":"venue"
},
  "geometry": {"coordinates":[-122.323533,47.323776],"type":"Point"}
}