{
  "type": "Feature",
  "properties": {
    "addr:full":"3528 13th Ave SW Olympia WA 98512",
    "addr:housenumber":"3528",
    "addr:postcode":"98512",
    "addr:street":"13Th Ave Sw",
    "iso:country":"US",
    "sg:address":"3528 13th Ave SW",
    "sg:city":"Olympia",
    "sg:classifiers":[
        {
            "category":"Health Services",
            "subcategory":"Chiropractor",
            "type":"Services"
        }
    ],
    "sg:phone":"+1 360 570 9580",
    "sg:postcode":"98512",
    "sg:province":"WA",
    "sg:tags":[
        "chiropractic"
    ],
    "wof:name":"Tumwater Chiropractic Center, Pllc",
    "wof:placetype":"venue"
},
  "geometry": {"coordinates":[-122.95867200000001,47.034649],"type":"Point"}
}