{
  "type": "Feature",
  "properties": {
    "iso:country":"US",
    "sg:address":"1001 NW 167th St",
    "sg:city":"Seattle",
    "sg:classifiers":[
        {
            "category":"Real Estate",
            "subcategory":"Real Estate Operator",
            "type":"Services"
        }
    ],
    "sg:phone":"+1 206 546 5272",
    "sg:postcode":"98177",
    "sg:province":"WA",
    "sg:tags":[
        "building",
        "commercial"
    ],
    "wof:name":"Commercial Group",
    "wof:placetype":"venue"
},
  "geometry": {"coordinates":[-122.37650499999999,47.750766],"type":"Point"}
}