{
  "type": "Feature",
  "properties": {
    "addr:full":"21 Airport Rd Brewster WA 98855",
    "addr:housenumber":"21",
    "addr:postcode":"98855",
    "addr:street":"Airport Rd",
    "iso:country":"US",
    "sg:address":"21 Airport Rd",
    "sg:city":"Brewster",
    "sg:classifiers":[
        {
            "category":"Farming",
            "subcategory":"Farm & Veterinary Services",
            "type":"Manufacturing & Wholesale Goods"
        }
    ],
    "sg:phone":"+1 509 689 2712",
    "sg:postcode":"98855",
    "sg:province":"WA",
    "sg:tags":[
        "school",
        "crop",
        "vocational"
    ],
    "wof:name":"Golden Wings Aviation",
    "wof:placetype":"venue"
},
  "geometry": {"coordinates":[-119.443586,48.71757],"type":"Point"}
}