{
  "type": "Feature",
  "properties": {
    "iso:country":"US",
    "sg:address":"3016 N Narrows Dr",
    "sg:city":"Tacoma",
    "sg:classifiers":[
        {
            "category":"Organizations",
            "subcategory":"Community Association",
            "type":"Services"
        }
    ],
    "sg:phone":"+1 253 759 8754",
    "sg:postcode":"98407",
    "sg:province":"WA",
    "sg:tags":[
        "condominium"
    ],
    "wof:name":"Gold Apartments",
    "wof:placetype":"venue"
},
  "geometry": {"coordinates":[-122.52394099999999,47.274469],"type":"Point"}
}