{
  "type": "Feature",
  "properties": {
    "addr:full":"303 O St NE Auburn WA 98002",
    "addr:housenumber":"303",
    "addr:postcode":"98002",
    "addr:street":"O St Ne",
    "iso:country":"US",
    "sg:address":"303 O St NE",
    "sg:city":"Auburn",
    "sg:classifiers":[
        {
            "category":"Health Services",
            "subcategory":"Health Practitioner",
            "type":"Services"
        }
    ],
    "sg:phone":"+1 253 939 8796",
    "sg:postcode":"98002",
    "sg:province":"WA",
    "sg:tags":[
        "establishment"
    ],
    "wof:name":"Arnp",
    "wof:placetype":"venue"
},
  "geometry": {"coordinates":[-122.210842,47.310833],"type":"Point"}
}