{
  "type": "Feature",
  "properties": {
    "addr:full":"8022 47th Ave NE Marysville WA 98270",
    "addr:housenumber":"8022",
    "addr:postcode":"98270",
    "addr:street":"47Th Ave Ne",
    "iso:country":"US",
    "sg:address":"8022 47th Ave NE",
    "sg:city":"Marysville",
    "sg:classifiers":[
        {
            "category":"Manufacturing",
            "subcategory":"Metals",
            "type":"Manufacturing & Wholesale Goods"
        }
    ],
    "sg:phone":"+1 360 657 4682",
    "sg:postcode":"98270",
    "sg:province":"WA",
    "sg:tags":[
        "mfg"
    ],
    "wof:name":"Eylander Pressure Washing",
    "wof:placetype":"venue"
},
  "geometry": {"coordinates":[-122.167776,48.069602],"type":"Point"}
}