{
  "type": "Feature",
  "properties": {
    "addr:full":"706 Taylor Ave N Seattle WA 98109",
    "addr:housenumber":"706",
    "addr:postcode":"98109",
    "addr:street":"Taylor Ave N",
    "iso:country":"US",
    "sg:address":"706 Taylor Ave N",
    "sg:city":"Seattle",
    "sg:classifiers":[
        {
            "category":"Coffee & Tea",
            "type":"Food & Drink"
        },
        {
            "category":"Restaurant",
            "type":"Food & Drink"
        }
    ],
    "sg:phone":"+1 206 284 1015",
    "sg:postcode":"98109",
    "sg:province":"WA",
    "sg:tags":[
        "creperies"
    ],
    "sg:website":"www.citizencoffee.com",
    "wof:name":"Citizen",
    "wof:placetype":"venue"
},
  "geometry": {"coordinates":[-122.345879,47.625754],"type":"Point"}
}