{
  "type": "Feature",
  "properties": {
    "addr:full":"1167 Mercer St Seattle WA 98109",
    "addr:housenumber":"1167",
    "addr:postcode":"98109",
    "addr:street":"Mercer St",
    "iso:country":"US",
    "sg:address":"1167 Mercer St",
    "sg:city":"Seattle",
    "sg:classifiers":[
        {
            "category":"Retail",
            "subcategory":"Laundry & Dry Cleaning",
            "type":"Services"
        },
        {
            "category":"Building & Trades",
            "subcategory":"Construction",
            "type":"Services"
        }
    ],
    "sg:phone":"+1 800 928 3732",
    "sg:postcode":"98109",
    "sg:province":"WA",
    "sg:tags":[
        "home",
        "house",
        "carpet",
        "rug",
        "cleaner"
    ],
    "sg:website":"www.1800waterdamage.com",
    "wof:name":"Cure Water Damage",
    "wof:placetype":"venue"
},
  "geometry": {"coordinates":[-122.333371,47.624048],"type":"Point"}
}