{
  "type": "Feature",
  "properties": {
    "addr:full":"6707 135th Ave SE Snohomish WA 98290",
    "addr:housenumber":"6707",
    "addr:postcode":"98290",
    "addr:street":"135Th Ave Se",
    "iso:country":"US",
    "sg:address":"6707 135th Ave SE",
    "sg:city":"Snohomish",
    "sg:classifiers":[
        {
            "category":"Retail",
            "subcategory":"Repair Shop",
            "type":"Services"
        }
    ],
    "sg:phone":"+1 360 568 3409",
    "sg:postcode":"98290",
    "sg:province":"WA",
    "sg:tags":[
        "armature",
        "rewinding"
    ],
    "wof:name":"A1 Electric Motor Co",
    "wof:placetype":"venue"
},
  "geometry": {"coordinates":[-122.050212,47.93595],"type":"Point"}
}