{
  "type": "Feature",
  "properties": {
    "addr:full":"1820 E Pine St Seattle WA 98122",
    "addr:housenumber":"1820",
    "addr:postcode":"98122",
    "addr:street":"E Pine St",
    "iso:country":"US",
    "sg:address":"1820 E Pine St",
    "sg:city":"Seattle",
    "sg:classifiers":[
        {
            "category":"Education",
            "subcategory":"Preschool",
            "type":"Public Place"
        }
    ],
    "sg:phone":"+1 206 568 3030",
    "sg:postcode":"98122",
    "sg:province":"WA",
    "sg:tags":[
        "kindergarten"
    ],
    "wof:name":"Black Star Line",
    "wof:placetype":"venue"
},
  "geometry": {"coordinates":[-122.308547,47.615261],"type":"Point"}
}