{
  "type": "Feature",
  "properties": {
    "addr:full":"1516 5th St Bremerton WA 98337",
    "addr:housenumber":"1516",
    "addr:postcode":"98337",
    "addr:street":"5Th St",
    "iso:country":"US",
    "sg:address":"1516 5th St",
    "sg:city":"Bremerton",
    "sg:classifiers":[
        {
            "category":"Social Services",
            "subcategory":"Child Care",
            "type":"Services"
        }
    ],
    "sg:phone":"+1 360 405 0204",
    "sg:postcode":"98337",
    "sg:province":"WA",
    "wof:name":"Star Of The Sea Extended Care",
    "wof:placetype":"venue"
},
  "geometry": {"coordinates":[-122.640835,47.566675],"type":"Point"}
}