{
  "type": "Feature",
  "properties": {
    "addr:full":"273 Otto St Port Townsend WA 98368",
    "addr:housenumber":"273",
    "addr:postcode":"98368",
    "addr:street":"Otto St",
    "iso:country":"US",
    "sg:address":"273 Otto St",
    "sg:city":"Port Townsend",
    "sg:classifiers":[
        {
            "category":"Manufacturing",
            "subcategory":"Retail Goods",
            "type":"Manufacturing & Wholesale Goods"
        }
    ],
    "sg:phone":"+1 360 385 4142",
    "sg:postcode":"98368",
    "sg:province":"WA",
    "sg:tags":[
        "candle"
    ],
    "sg:website":"www.coyote-found-candles.com",
    "wof:name":"Coyote Found Candles",
    "wof:placetype":"venue"
},
  "geometry": {"coordinates":[-122.814795,48.084178],"type":"Point"}
}