{
  "type": "Feature",
  "properties": {
    "addr:full":"Puget Sound Plaza 1325 Fourth Ave, Suite 1500 Seattle WA 98101",
    "addr:housenumber":"1325",
    "addr:postcode":"98101",
    "addr:street":"Fourth Ave Suite 1500",
    "iso:country":"US",
    "sg:address":"Puget Sound Plaza 1325 Fourth Ave, Suite 1500",
    "sg:city":"Seattle",
    "sg:classifiers":[
        {
            "category":"Professional",
            "subcategory":"Lawyer & Legal Services",
            "type":"Services"
        }
    ],
    "sg:phone":"+1 206 459 6392",
    "sg:postcode":"98101",
    "sg:province":"WA",
    "sg:tags":[
        "litigation"
    ],
    "sg:website":"www.davidodefense.com",
    "wof:name":"David O Defense PLLC",
    "wof:placetype":"venue"
},
  "geometry": {"coordinates":[-122.33556900000001,47.608999],"type":"Point"}
}