{
  "type": "Feature",
  "properties": {
    "addr:full":"23 S Spokane St Walla Walla WA 99362",
    "addr:housenumber":"23",
    "addr:postcode":"99362",
    "addr:street":"S Spokane St",
    "iso:country":"US",
    "sg:address":"23 S Spokane St",
    "sg:city":"Walla Walla",
    "sg:classifiers":[
        {
            "category":"Food & Beverages",
            "subcategory":"Bakery",
            "type":"Retail Goods"
        }
    ],
    "sg:phone":"+1 509 522 4826",
    "sg:postcode":"99362",
    "sg:province":"WA",
    "sg:tags":[
        "cafe"
    ],
    "wof:name":"Chocolate Expectations",
    "wof:placetype":"venue"
},
  "geometry": {"coordinates":[-118.335891,46.068547],"type":"Point"}
}