{
  "type": "Feature",
  "properties": {
    "iso:country":"US",
    "sg:address":"1204 E Denny Way",
    "sg:city":"Seattle",
    "sg:classifiers":[
        {
            "category":"Professional",
            "subcategory":"Management & Consulting",
            "type":"Services"
        }
    ],
    "sg:phone":"+1 206 383 0796",
    "sg:postcode":"98122",
    "sg:province":"WA",
    "sg:tags":[
        "business"
    ],
    "wof:name":"Art Consultant Dramaturg",
    "wof:placetype":"venue"
},
  "geometry": {"coordinates":[-122.31564299999999,47.618851],"type":"Point"}
}