{
  "type": "Feature",
  "properties": {
    "addr:full":"620 Naches Ave SW Renton WA 98057",
    "addr:housenumber":"620",
    "addr:postcode":"98057",
    "addr:street":"Naches Ave Sw",
    "iso:country":"US",
    "sg:address":"620 Naches Ave SW",
    "sg:city":"Renton",
    "sg:classifiers":[
        {
            "category":"Shopping",
            "subcategory":"Mobile Phones",
            "type":"Retail Goods"
        }
    ],
    "sg:phone":"+1 425 203 3900",
    "sg:postcode":"98057",
    "sg:province":"WA",
    "wof:name":"X10 Wireless Technology Inc",
    "wof:placetype":"venue"
},
  "geometry": {"coordinates":[-122.233819,47.474237],"type":"Point"}
}