{
  "type": "Feature",
  "properties": {
    "addr:full":"16101 60th Ave W Edmonds WA 98026",
    "addr:housenumber":"16101",
    "addr:postcode":"98026",
    "addr:street":"60Th Ave W",
    "iso:country":"US",
    "sg:address":"16101 60th Ave W",
    "sg:city":"Edmonds",
    "sg:classifiers":[
        {
            "category":"Retail",
            "subcategory":"Animal Services",
            "type":"Services"
        }
    ],
    "sg:phone":"+1 425 745 1034",
    "sg:postcode":"98026",
    "sg:province":"WA",
    "wof:name":"Creevelea Kennel Inc",
    "wof:placetype":"venue"
},
  "geometry": {"coordinates":[-122.31433800000001,47.854051],"type":"Point"}
}