{
  "type": "Feature",
  "properties": {
    "addr:full":"22909 56th Ave W Mountlake Ter WA 98043",
    "addr:housenumber":"22909",
    "addr:postcode":"98043",
    "addr:street":"56Th Ave W Mountlake Ter",
    "iso:country":"US",
    "sg:address":"22909 56th Ave W",
    "sg:city":"Mountlake Ter",
    "sg:classifiers":[
        {
            "category":"Organizations",
            "subcategory":"Community Association",
            "type":"Services"
        }
    ],
    "sg:phone":"+1 425 776 5490",
    "sg:postcode":"98043",
    "sg:province":"WA",
    "sg:tags":[
        "military"
    ],
    "wof:name":"American Legion",
    "wof:placetype":"venue"
},
  "geometry": {"coordinates":[-122.308423,47.791229],"type":"Point"}
}