{
  "type": "Feature",
  "properties": {
    "addr:full":"4645 189th Pl SE Issaquah WA 98027",
    "addr:housenumber":"4645",
    "addr:postcode":"98027",
    "addr:street":"189Th Pl Se",
    "iso:country":"US",
    "sg:address":"4645 189th Pl SE",
    "sg:city":"Issaquah",
    "sg:classifiers":[
        {
            "category":"Building & Trades",
            "subcategory":"Electrical",
            "type":"Services"
        }
    ],
    "sg:phone":"+1 206 240 1711",
    "sg:postcode":"98027",
    "sg:province":"WA",
    "sg:tags":[
        "electrical",
        "contractor"
    ],
    "wof:name":"Light Speed Electric",
    "wof:placetype":"venue"
},
  "geometry": {"coordinates":[-122.087625,47.562343],"type":"Point"}
}