{
  "type": "Feature",
  "properties": {
    "addr:full":"10024 NE 146th Ave Vancouver WA 98682",
    "addr:housenumber":"10024",
    "addr:postcode":"98682",
    "addr:street":"Ne 146Th Ave",
    "iso:country":"US",
    "sg:address":"10024 NE 146th Ave",
    "sg:city":"Vancouver",
    "sg:classifiers":[
        {
            "category":"Building & Trades",
            "subcategory":"Cleaning & Sanitation",
            "type":"Services"
        }
    ],
    "sg:phone":"+1 360 944 6540",
    "sg:postcode":"98682",
    "sg:province":"WA",
    "sg:tags":[
        "maintenance"
    ],
    "wof:name":"Gushtyuk Cleaning Services",
    "wof:placetype":"venue"
},
  "geometry": {"coordinates":[-122.522727,45.695142],"type":"Point"}
}