{
  "type": "Feature",
  "properties": {
    "addr:full":"5008 NE 111th Cir Vancouver WA 98686",
    "addr:housenumber":"5008",
    "addr:postcode":"98686",
    "addr:street":"Ne 111Th Cir",
    "iso:country":"US",
    "sg:address":"5008 NE 111th Cir",
    "sg:city":"Vancouver",
    "sg:classifiers":[
        {
            "category":"Real Estate",
            "subcategory":"Real Estate Agent",
            "type":"Services"
        }
    ],
    "sg:phone":"+1 360 636 2261",
    "sg:postcode":"98686",
    "sg:province":"WA",
    "sg:tags":[
        "inspection"
    ],
    "wof:name":"All-American Home Inspections",
    "wof:placetype":"venue"
},
  "geometry": {"coordinates":[-122.619777,45.701936],"type":"Point"}
}