{
  "type": "Feature",
  "properties": {
    "addr:full":"15300 NE 2nd St Vancouver WA 98684",
    "addr:housenumber":"15300",
    "addr:postcode":"98684",
    "addr:street":"Ne 2Nd St",
    "iso:country":"US",
    "sg:address":"15300 NE 2nd St",
    "sg:city":"Vancouver",
    "sg:classifiers":[
        {
            "category":"Wholesale",
            "subcategory":"Machinery & Supplies",
            "type":"Manufacturing & Wholesale Goods"
        }
    ],
    "sg:phone":"+1 360 892 6005",
    "sg:postcode":"98684",
    "sg:province":"WA",
    "sg:tags":[
        "industrial",
        "equipment",
        "used",
        "machinery-new",
        "supplies-wholesale"
    ],
    "wof:name":"Equipment Resources Nw",
    "wof:placetype":"venue"
},
  "geometry": {"coordinates":[-122.515984,45.62225],"type":"Point"}
}