{
  "type": "Feature",
  "properties": {
    "addr:full":"16735 SE 272nd St Covington WA 98042",
    "addr:postcode":"16735;98042",
    "addr:street":"Se 272Nd St",
    "iso:country":"US",
    "sg:address":"16735 SE 272nd St",
    "sg:city":"Covington",
    "sg:classifiers":[
        {
            "category":"Shopping",
            "subcategory":"Jewelry",
            "type":"Retail Goods"
        }
    ],
    "sg:phone":"+1 253 639 7415",
    "sg:postcode":"98042",
    "sg:province":"WA",
    "sg:tags":[
        "jeweler"
    ],
    "sg:website":"www.fredmeyer.com",
    "wof:name":"Fred Meyer Jewelers",
    "wof:placetype":"venue"
},
  "geometry": {"coordinates":[-122.117335,47.358077],"type":"Point"}
}