{
  "type": "Feature",
  "properties": {
    "addr:full":"1001 Taylor Ave N Seattle WA 98109",
    "addr:housenumber":"1001",
    "addr:postcode":"98109",
    "addr:street":"Taylor Ave N",
    "iso:country":"US",
    "sg:address":"1001 Taylor Ave N",
    "sg:city":"Seattle",
    "sg:classifiers":[
        {
            "category":"Health Services",
            "subcategory":"Health Practitioner",
            "type":"Services"
        }
    ],
    "sg:phone":"+1 206 281 8596",
    "sg:postcode":"98109",
    "sg:province":"WA",
    "wof:name":"Sharon D King",
    "wof:placetype":"venue"
},
  "geometry": {"coordinates":[-122.346234,47.628904],"type":"Point"}
}