{
  "type": "Feature",
  "properties": {
    "addr:full":"14015 River Bend Rd Mount Vernon WA 98273",
    "addr:housenumber":"14015",
    "addr:postcode":"98273",
    "addr:street":"River Bend Rd",
    "iso:country":"US",
    "sg:address":"14015 River Bend Rd",
    "sg:city":"Mount Vernon",
    "sg:classifiers":[
        {
            "category":"Home & Garden",
            "subcategory":"Garden Supply",
            "type":"Retail Goods"
        }
    ],
    "sg:phone":"+1 360 424 0132",
    "sg:postcode":"98273",
    "sg:province":"WA",
    "sg:tags":[
        "nursery",
        "gardening"
    ],
    "wof:name":"Wells Nursery Llc",
    "wof:placetype":"venue"
},
  "geometry": {"coordinates":[-122.34177200000001,48.430225],"type":"Point"}
}