{
  "type": "Feature",
  "properties": {
    "addr:full":"981 Powell Ave SW Ste 100 Renton WA 98057",
    "addr:housenumber":"981",
    "addr:postcode":"98057",
    "addr:street":"Powell Ave Sw Ste 100",
    "iso:country":"US",
    "sg:address":"981 Powell Ave SW Ste 100",
    "sg:city":"Renton",
    "sg:classifiers":[
        {
            "category":"Banks & Credit Unions",
            "subcategory":"Investment Brokerage",
            "type":"Services"
        },
        {
            "category":"Banks & Credit Unions",
            "subcategory":"Financial Services",
            "type":"Services"
        }
    ],
    "sg:phone":"+1 425 793 5593",
    "sg:postcode":"98057",
    "sg:province":"WA",
    "sg:tags":[
        "advisory",
        "planner"
    ],
    "sg:website":"http://www.ameriprise.com",
    "wof:name":"Ameriprise Financial",
    "wof:placetype":"venue"
},
  "geometry": {"coordinates":[-122.230913,47.469197],"type":"Point"}
}