{
  "type": "Feature",
  "properties": {
    "addr:full":"100 S Blake Ave Sequim WA 98382",
    "addr:housenumber":"100",
    "addr:postcode":"98382",
    "addr:street":"S Blake Ave",
    "iso:country":"US",
    "sg:address":"100 S Blake Ave",
    "sg:city":"Sequim",
    "sg:classifiers":[
        {
            "category":"Place Of Worship",
            "subcategory":"Church",
            "type":"Public Place"
        },
        {
            "category":"Place Of Worship",
            "type":"Public Place"
        },
        {
            "category":"Organizations",
            "subcategory":"Religious Organization",
            "type":"Services"
        }
    ],
    "sg:phone":"+1 360 683 5367",
    "sg:postcode":"98382",
    "sg:province":"WA",
    "sg:tags":[
        "churches-methodist"
    ],
    "sg:website":"http://www.sequimtumc.org",
    "wof:name":"Trinity United Methodist Church",
    "wof:placetype":"venue"
},
  "geometry": {"coordinates":[-123.08609,48.078781],"type":"Point"}
}