{
  "type": "Feature",
  "properties": {
    "addr:full":"3172 NE Sunset Blvd Renton WA 98056",
    "addr:housenumber":"3172",
    "addr:postcode":"98056",
    "addr:street":"Ne Sunset Blvd",
    "iso:country":"US",
    "sg:address":"3172 NE Sunset Blvd",
    "sg:city":"Renton",
    "sg:classifiers":[
        {
            "category":"Donuts",
            "subcategory":"None",
            "type":"Food & Drink"
        }
    ],
    "sg:phone":"+1 425 271 2399",
    "sg:postcode":"98056",
    "sg:province":"WA",
    "sg:tags":[
        "shop"
    ],
    "wof:name":"Chuck S Donut 2",
    "wof:placetype":"venue"
},
  "geometry": {"coordinates":[-122.17661699999999,47.503949],"type":"Point"}
}