{
  "type": "Feature",
  "properties": {
    "iso:country":"US",
    "sg:address":"2936 E Olympic Ave",
    "sg:city":"Spokane",
    "sg:classifiers":[
        {
            "category":"Organizations",
            "subcategory":"Religious Organization",
            "type":"Services"
        }
    ],
    "sg:phone":"+1 509 487 9624",
    "sg:postcode":"99217",
    "sg:province":"WA",
    "sg:tags":[
        "church"
    ],
    "wof:name":"Church Of The Resurrection",
    "wof:placetype":"venue"
},
  "geometry": {"coordinates":[-117.366849,47.703259],"type":"Point"}
}