{
  "type": "Feature",
  "properties": {
    "addr:full":"701 Madison Ave Yakima WA 98902",
    "addr:housenumber":"701",
    "addr:postcode":"98902",
    "addr:street":"Madison Ave",
    "iso:country":"US",
    "sg:address":"701 Madison Ave",
    "sg:city":"Yakima",
    "sg:classifiers":[
        {
            "category":"Manufacturing",
            "subcategory":"Building Materials",
            "type":"Manufacturing & Wholesale Goods"
        }
    ],
    "sg:phone":"+1 509 248 0472",
    "sg:postcode":"98902",
    "sg:province":"WA",
    "sg:tags":[
        "mfg",
        "wood",
        "kitchen",
        "cabinet"
    ],
    "wof:name":"Yakima Valley Cabinets Inc",
    "wof:placetype":"venue"
},
  "geometry": {"coordinates":[-120.527517,46.616165],"type":"Point"}
}