{
  "type": "Feature",
  "properties": {
    "addr:full":"1507 30th Ave S Seattle WA 98144",
    "addr:housenumber":"1507",
    "addr:postcode":"98144",
    "addr:street":"30Th Ave S",
    "iso:country":"US",
    "sg:address":"1507 30th Ave S",
    "sg:city":"Seattle",
    "sg:classifiers":[
        {
            "category":"Shopping",
            "type":"Retail Goods"
        }
    ],
    "sg:phone":"+1 206 860 1867",
    "sg:postcode":"98144",
    "sg:province":"WA",
    "sg:tags":[
        "merchandise"
    ],
    "wof:name":"Helen M Lessick",
    "wof:placetype":"venue"
},
  "geometry": {"coordinates":[-122.293668,47.588034],"type":"Point"}
}