{
  "type": "Feature",
  "properties": {
    "addr:full":"323 Wine Country Rd Prosser WA 99350",
    "addr:housenumber":"323",
    "addr:postcode":"99350",
    "addr:street":"Wine Country Rd",
    "iso:country":"US",
    "sg:address":"323 Wine Country Rd",
    "sg:city":"Prosser",
    "sg:classifiers":[
        {
            "category":"Building & Trades",
            "subcategory":"Construction",
            "type":"Services"
        }
    ],
    "sg:phone":"+1 509 786 4382",
    "sg:postcode":"99350",
    "sg:province":"WA",
    "sg:tags":[
        "carpentry",
        "contractor"
    ],
    "wof:name":"Woodshop Inc",
    "wof:placetype":"venue"
},
  "geometry": {"coordinates":[-119.783052,46.213909],"type":"Point"}
}