{
  "type": "Feature",
  "properties": {
    "iso:country":"US",
    "sg:address":"159 S Worthen St",
    "sg:city":"Wenatchee",
    "sg:classifiers":[
        {
            "category":"Professional",
            "subcategory":"Accounting & Tax Preparation",
            "type":"Services"
        }
    ],
    "sg:phone":"+1 509 662 9691",
    "sg:postcode":"98801",
    "sg:province":"WA",
    "sg:tags":[
        "accountant"
    ],
    "wof:name":"Linder & Goetz",
    "wof:placetype":"venue"
},
  "geometry": {"coordinates":[-120.30505700000001,47.42196],"type":"Point"}
}