{
  "type": "Feature",
  "properties": {
    "addr:full":"1778 N Goerig St Woodland WA 98674",
    "addr:housenumber":"1778",
    "addr:postcode":"98674",
    "addr:street":"N Goerig St",
    "iso:country":"US",
    "sg:address":"1778 N Goerig St",
    "sg:city":"Woodland",
    "sg:classifiers":[
        {
            "category":"Restaurant",
            "type":"Food & Drink"
        }
    ],
    "sg:phone":"+1 360 225 0255",
    "sg:postcode":"98674",
    "sg:province":"WA",
    "sg:tags":[
        "eating"
    ],
    "wof:name":"Baskin Works Etc",
    "wof:placetype":"venue"
},
  "geometry": {"coordinates":[-122.742149,45.915721],"type":"Point"}
}