{
  "type": "Feature",
  "properties": {
    "addr:full":"3608 22nd St SE Puyallup WA 98374",
    "addr:housenumber":"3608",
    "addr:postcode":"98374",
    "addr:street":"22Nd St Se",
    "iso:country":"US",
    "sg:address":"3608 22nd St SE",
    "sg:city":"Puyallup",
    "sg:classifiers":[
        {
            "category":"Autos & Motor Vehicles",
            "subcategory":"Automobile Sales",
            "type":"Retail Goods"
        }
    ],
    "sg:phone":"+1 253 848 9330",
    "sg:postcode":"98374",
    "sg:province":"WA",
    "sg:tags":[
        "new",
        "car"
    ],
    "wof:name":"Ray Harley Inc",
    "wof:placetype":"venue"
},
  "geometry": {"coordinates":[-122.26569000000001,47.157666],"type":"Point"}
}