{
  "type": "Feature",
  "properties": {
    "addr:full":"13511 SE 3rd Way Vancouver WA 98684",
    "addr:housenumber":"13511",
    "addr:postcode":"98684",
    "addr:street":"Se 3Rd Way",
    "iso:country":"US",
    "sg:address":"13511 SE 3rd Way",
    "sg:city":"Vancouver",
    "sg:classifiers":[
        {
            "category":"Retail",
            "subcategory":"Portrait Studio",
            "type":"Services"
        },
        {
            "category":"Shopping",
            "subcategory":"Pharmacy",
            "type":"Retail Goods"
        }
    ],
    "sg:phone":"+1 360 885 0839",
    "sg:postcode":"98684",
    "sg:province":"WA",
    "sg:tags":[
        "photography",
        "drugstore",
        "store"
    ],
    "wof:name":"Rite Aid",
    "wof:placetype":"venue"
},
  "geometry": {"coordinates":[-122.530998,45.618301],"type":"Point"}
}