{
  "type": "Feature",
  "properties": {
    "addr:full":"1633 S 246th Pl Seattle WA 98198",
    "addr:housenumber":"1633",
    "addr:postcode":"98198",
    "addr:street":"S 246Th Pl",
    "iso:country":"US",
    "sg:address":"1633 S 246th Pl",
    "sg:city":"Seattle",
    "sg:classifiers":[
        {
            "category":"Building & Trades",
            "subcategory":"Construction",
            "type":"Services"
        }
    ],
    "sg:phone":"+1 206 878 0517",
    "sg:postcode":"98198",
    "sg:province":"WA",
    "sg:tags":[
        "house"
    ],
    "wof:name":"Worrel Construction",
    "wof:placetype":"venue"
},
  "geometry": {"coordinates":[-122.308278,47.380816],"type":"Point"}
}