{
  "type": "Feature",
  "properties": {
    "addr:full":"1705 SE 164th Ave Vancouver WA 98683",
    "addr:housenumber":"1705",
    "addr:postcode":"98683",
    "addr:street":"Se 164Th Ave",
    "iso:country":"US",
    "sg:address":"1705 SE 164th Ave",
    "sg:city":"Vancouver",
    "sg:classifiers":[
        {
            "category":"Restaurant",
            "type":"Food & Drink"
        }
    ],
    "sg:phone":"+1 360 883 0222",
    "sg:postcode":"98683",
    "sg:province":"WA",
    "sg:tags":[
        "german",
        "eating"
    ],
    "sg:website":"www.gustavs.net",
    "wof:name":"Gustav's Pub & Grill",
    "wof:placetype":"venue"
},
  "geometry": {"coordinates":[-122.503426,45.607941],"type":"Point"}
}