{
  "type": "Feature",
  "properties": {
    "addr:full":"2808 Sunset Blvd NE Renton WA 98056",
    "addr:housenumber":"2808",
    "addr:postcode":"98056",
    "addr:street":"Sunset Blvd Ne",
    "iso:country":"US",
    "sg:address":"2808 Sunset Blvd NE",
    "sg:city":"Renton",
    "sg:classifiers":[
        {
            "category":"Restaurant",
            "type":"Food & Drink"
        }
    ],
    "sg:phone":"+1 425 793 6278",
    "sg:postcode":"98056",
    "sg:province":"WA",
    "sg:tags":[
        "thai"
    ],
    "wof:name":"Thai On Hilands",
    "wof:placetype":"venue"
},
  "geometry": {"coordinates":[-122.180504,47.500112],"type":"Point"}
}