{
  "type": "Feature",
  "properties": {
    "addr:full":"620 W Division St Mount Vernon WA 98273",
    "addr:housenumber":"620",
    "addr:postcode":"98273",
    "addr:street":"W Division St",
    "iso:country":"US",
    "sg:address":"620 W Division St",
    "sg:city":"Mount Vernon",
    "sg:classifiers":[
        {
            "category":"Wholesale",
            "subcategory":"Electrical",
            "type":"Manufacturing & Wholesale Goods"
        }
    ],
    "sg:phone":"+1 360 336 3073",
    "sg:postcode":"98273",
    "sg:province":"WA",
    "sg:tags":[
        "parts",
        "electronic"
    ],
    "wof:name":"Electronic Supply Center",
    "wof:placetype":"venue"
},
  "geometry": {"coordinates":[-122.34326900000001,48.421615],"type":"Point"}
}