{
  "type": "Feature",
  "properties": {
    "addr:full":"7702 Phillips Rd SW Lakewood WA 98498",
    "addr:housenumber":"7702",
    "addr:postcode":"98498",
    "addr:street":"Phillips Rd Sw",
    "iso:country":"US",
    "sg:address":"7702 Phillips Rd SW",
    "sg:city":"Lakewood",
    "sg:classifiers":[
        {
            "category":"Education",
            "subcategory":"School",
            "type":"Public Place"
        }
    ],
    "sg:phone":"+1 253 583 5400",
    "sg:postcode":"98498",
    "sg:province":"WA",
    "sg:tags":[
        "high"
    ],
    "wof:name":"Schools Pub Elem High Schools Clover Park Schl di",
    "wof:placetype":"venue"
},
  "geometry": {"coordinates":[-122.539148,47.187293],"type":"Point"}
}