{
  "type": "Feature",
  "properties": {
    "addr:full":"2021 NW Sierra Ln Camas WA 98607",
    "addr:housenumber":"2021",
    "addr:postcode":"98607",
    "addr:street":"Nw Sierra Ln",
    "iso:country":"US",
    "sg:address":"2021 NW Sierra Ln",
    "sg:city":"Camas",
    "sg:classifiers":[
        {
            "category":"Wholesale",
            "subcategory":"Toys & Hobbies",
            "type":"Manufacturing & Wholesale Goods"
        }
    ],
    "sg:phone":"+1 360 834 5444",
    "sg:postcode":"98607",
    "sg:province":"WA",
    "wof:name":"Keepsakes By Penny Holdal",
    "wof:placetype":"venue"
},
  "geometry": {"coordinates":[-122.43383900000001,45.581701],"type":"Point"}
}