{
  "type": "Feature",
  "properties": {
    "addr:full":"1822 E Mead Ave Union Gap WA 98903",
    "addr:housenumber":"1822",
    "addr:postcode":"98903",
    "addr:street":"E Mead Ave",
    "iso:country":"US",
    "sg:address":"1822 E Mead Ave",
    "sg:city":"Union Gap",
    "sg:classifiers":[
        {
            "category":"Home & Garden",
            "subcategory":"Building Materials",
            "type":"Retail Goods"
        }
    ],
    "sg:phone":"+1 509 575 1600",
    "sg:postcode":"98903",
    "sg:province":"WA",
    "sg:tags":[
        "lumber"
    ],
    "sg:website":"www.lumbermens.net",
    "wof:name":"Lumbermen's Building Ctr",
    "wof:placetype":"venue"
},
  "geometry": {"coordinates":[-120.476197,46.577581],"type":"Point"}
}