{
  "type": "Feature",
  "properties": {
    "addr:full":"2602 NW 63rd St Seattle WA 98107",
    "addr:housenumber":"2602",
    "addr:postcode":"98107",
    "addr:street":"Nw 63Rd St",
    "iso:country":"US",
    "sg:address":"2602 NW 63rd St",
    "sg:city":"Seattle",
    "sg:classifiers":[
        {
            "category":"Building & Trades",
            "subcategory":"Cleaning & Sanitation",
            "type":"Services"
        }
    ],
    "sg:phone":"+1 206 783 3036",
    "sg:postcode":"98107",
    "sg:province":"WA",
    "sg:tags":[
        "window"
    ],
    "wof:name":"Byron's Window Cleaning",
    "wof:placetype":"venue"
},
  "geometry": {"coordinates":[-122.392968,47.674559],"type":"Point"}
}