{
  "type": "Feature",
  "properties": {
    "addr:full":"221 Blankenship Rd Mossyrock WA 98564",
    "addr:housenumber":"221",
    "addr:postcode":"98564",
    "addr:street":"Blankenship Rd",
    "iso:country":"US",
    "sg:address":"221 Blankenship Rd",
    "sg:city":"Mossyrock",
    "sg:classifiers":[
        {
            "category":"Real Estate",
            "subcategory":"Real Estate Operator",
            "type":"Services"
        }
    ],
    "sg:phone":"+1 360 983 3516",
    "sg:postcode":"98564",
    "sg:province":"WA",
    "sg:tags":[
        "manager",
        "property",
        "company"
    ],
    "wof:name":"Nettie Downing Inc",
    "wof:placetype":"venue"
},
  "geometry": {"coordinates":[-122.47088100000001,46.516454],"type":"Point"}
}