{
  "type": "Feature",
  "properties": {
    "addr:full":"11818 SE Mill Plain Blvd Ste 209 Vancouver WA 98684",
    "addr:housenumber":"11818",
    "addr:postcode":"98684",
    "addr:street":"Se Mill Plain Blvd Ste 209",
    "iso:country":"US",
    "sg:address":"11818 SE Mill Plain Blvd Ste 209",
    "sg:city":"Vancouver",
    "sg:classifiers":[
        {
            "category":"Education",
            "subcategory":"Special Training",
            "type":"Public Place"
        },
        {
            "category":"Education",
            "subcategory":"School",
            "type":"Public Place"
        }
    ],
    "sg:phone":"+1 360 892 8486",
    "sg:postcode":"98684",
    "sg:province":"WA",
    "sg:tags":[
        "high",
        "middle",
        "tutoring",
        "elementary"
    ],
    "wof:name":"Sylvan Learning Center",
    "wof:placetype":"venue"
},
  "geometry": {"coordinates":[-122.550003,45.620602],"type":"Point"}
}