{
  "type": "Feature",
  "properties": {
    "addr:full":"1451 Grant St Bellingham WA 98225",
    "addr:housenumber":"1451",
    "addr:postcode":"98225",
    "addr:street":"Grant St",
    "iso:country":"US",
    "sg:address":"1451 Grant St",
    "sg:city":"Bellingham",
    "sg:classifiers":[
        {
            "category":"Professional",
            "type":"Services"
        }
    ],
    "sg:phone":"+1 360 714 9409",
    "sg:postcode":"98225",
    "sg:province":"WA",
    "sg:tags":[
        "consulting",
        "business"
    ],
    "wof:name":"Stratum Group",
    "wof:placetype":"venue"
},
  "geometry": {"coordinates":[-122.46913499999999,48.74789],"type":"Point"}
}