{
  "type": "Feature",
  "properties": {
    "addr:full":"4400 88th Ave SE Mercer Island WA 98040",
    "addr:housenumber":"4400",
    "addr:postcode":"98040",
    "addr:street":"88Th Ave Se",
    "iso:country":"US",
    "sg:address":"4400 88th Ave SE",
    "sg:city":"Mercer Island",
    "sg:classifiers":[
        {
            "category":"Education",
            "subcategory":"Library",
            "type":"Public Place"
        }
    ],
    "sg:phone":"+1 206 236 3537",
    "sg:postcode":"98040",
    "sg:province":"WA",
    "wof:name":"Mercer Island City of",
    "wof:placetype":"venue"
},
  "geometry": {"coordinates":[-122.22199999999999,47.566898],"type":"Point"}
}