{
  "type": "Feature",
  "properties": {
    "addr:full":"35810 NE 112th St Carnation WA 98014",
    "addr:housenumber":"35810",
    "addr:postcode":"98014",
    "addr:street":"Ne 112Th St",
    "iso:country":"US",
    "sg:address":"35810 NE 112th St",
    "sg:city":"Carnation",
    "sg:classifiers":[
        {
            "category":"Freight",
            "type":"Transportation"
        }
    ],
    "sg:phone":"+1 206 947 3867",
    "sg:postcode":"98014",
    "sg:province":"WA",
    "sg:tags":[
        "operator",
        "local",
        "trucking"
    ],
    "wof:name":"Donmans Trucking Inc",
    "wof:placetype":"venue"
},
  "geometry": {"coordinates":[-121.862606,47.697777],"type":"Point"}
}