{
  "type": "Feature",
  "properties": {
    "addr:full":"1509 California St Everett WA 98201",
    "addr:housenumber":"1509",
    "addr:postcode":"98201",
    "addr:street":"California St",
    "iso:country":"US",
    "sg:address":"1509 California St",
    "sg:city":"Everett",
    "sg:classifiers":[
        {
            "category":"Education",
            "subcategory":"School",
            "type":"Public Place"
        }
    ],
    "sg:phone":"+1 425 339 1909",
    "sg:postcode":"98201",
    "sg:province":"WA",
    "wof:name":"Northwest Regional Learning",
    "wof:placetype":"venue"
},
  "geometry": {"coordinates":[-122.208685,47.980708],"type":"Point"}
}