{
  "type": "Feature",
  "properties": {
    "addr:full":"2880 Lee Rd Ste C Prosser WA 99350",
    "addr:housenumber":"2880",
    "addr:postcode":"99350",
    "addr:street":"Lee Rd Ste C",
    "iso:country":"US",
    "sg:address":"2880 Lee Rd Ste C",
    "sg:city":"Prosser",
    "sg:classifiers":[
        {
            "category":"Professional",
            "subcategory":"Business Services",
            "type":"Services"
        }
    ],
    "sg:phone":"+1 509 786 3497",
    "sg:postcode":"99350",
    "sg:province":"WA",
    "sg:tags":[
        "consultant",
        "coach"
    ],
    "wof:name":"J & A Wine Consultants",
    "wof:placetype":"venue"
},
  "geometry": {"coordinates":[-119.729332,46.2183],"type":"Point"}
}