{
  "type": "Feature",
  "properties": {
    "addr:full":"10740 Meridian Ave N # 205 Seattle WA 98133",
    "addr:housenumber":"10740",
    "addr:postcode":"98133",
    "addr:street":"Meridian Ave N # 205",
    "iso:country":"US",
    "sg:address":"10740 Meridian Ave N # 205",
    "sg:city":"Seattle",
    "sg:classifiers":[
        {
            "category":"Professional",
            "subcategory":"Management & Consulting",
            "type":"Services"
        },
        {
            "category":"Banks & Credit Unions",
            "subcategory":"Financial Services",
            "type":"Services"
        }
    ],
    "sg:phone":"+1 206 292 2146",
    "sg:postcode":"98133",
    "sg:province":"WA",
    "sg:tags":[
        "consultant",
        "financing",
        "planning"
    ],
    "wof:name":"Haase, Penelope Certified Financial Planning",
    "wof:placetype":"venue"
},
  "geometry": {"coordinates":[-122.333994,47.707579],"type":"Point"}
}