{
  "type": "Feature",
  "properties": {
    "addr:full":"151 Melody Ln Naches WA 98937",
    "addr:housenumber":"151",
    "addr:postcode":"98937",
    "addr:street":"Melody Ln",
    "iso:country":"US",
    "sg:address":"151 Melody Ln",
    "sg:city":"Naches",
    "sg:classifiers":[
        {
            "category":"Real Estate",
            "subcategory":"Real Estate Operator",
            "type":"Services"
        }
    ],
    "sg:phone":"+1 509 653 2160",
    "sg:postcode":"98937",
    "sg:province":"WA",
    "sg:tags":[
        "dwelling"
    ],
    "wof:name":"Theodore D & Melody J Ken",
    "wof:placetype":"venue"
},
  "geometry": {"coordinates":[-120.700834,46.727628],"type":"Point"}
}