{
  "type": "Feature",
  "properties": {
    "addr:full":"555 Franklin Ct Sunnyside WA 98944",
    "addr:housenumber":"555",
    "addr:postcode":"98944",
    "addr:street":"Franklin Ct",
    "iso:country":"US",
    "sg:address":"555 Franklin Ct",
    "sg:city":"Sunnyside",
    "sg:classifiers":[
        {
            "category":"Organizations",
            "subcategory":"Religious Organization",
            "type":"Services"
        }
    ],
    "sg:phone":"+1 509 837 5371",
    "sg:postcode":"98944",
    "sg:province":"WA",
    "sg:tags":[
        "church"
    ],
    "sg:website":"www.sunnysidecrc.com",
    "wof:name":"Christian Reformed Church",
    "wof:placetype":"venue"
},
  "geometry": {"coordinates":[-120.000044,46.322561],"type":"Point"}
}