{
  "type": "Feature",
  "properties": {
    "iso:country":"US",
    "sg:address":"14109 E Sprague Ave",
    "sg:city":"Spokane Valley",
    "sg:classifiers":[
        {
            "category":"Education",
            "subcategory":"Special Training",
            "type":"Public Place"
        }
    ],
    "sg:phone":"+1 509 893 4913",
    "sg:postcode":"99216",
    "sg:province":"WA",
    "sg:tags":[
        "aid",
        "instruction",
        "first"
    ],
    "wof:name":"First Line First Aid Inc",
    "wof:placetype":"venue"
},
  "geometry": {"coordinates":[-117.21505999999999,47.657141],"type":"Point"}
}