{
  "type": "Feature",
  "properties": {
    "addr:full":"1546 Thompson Dr Stanwood WA 98282",
    "addr:housenumber":"1546",
    "addr:postcode":"98282",
    "addr:street":"Thompson Dr",
    "iso:country":"US",
    "sg:address":"1546 Thompson Dr",
    "sg:city":"Stanwood",
    "sg:classifiers":[
        {
            "category":"Autos & Motor Vehicles",
            "subcategory":"Auto Supplies",
            "type":"Retail Goods"
        }
    ],
    "sg:phone":"+1 360 387 1330",
    "sg:postcode":"98282",
    "sg:province":"WA",
    "wof:name":"Ball & Chain Racing",
    "wof:placetype":"venue"
},
  "geometry": {"coordinates":[-122.46917999999999,48.154318],"type":"Point"}
}