{
  "type": "Feature",
  "properties": {
    "addr:full":"302 S 10th Ave Kelso WA 98626",
    "addr:housenumber":"302",
    "addr:postcode":"98626",
    "addr:street":"S 10Th Ave",
    "iso:country":"US",
    "sg:address":"302 S 10th Ave",
    "sg:city":"Kelso",
    "sg:classifiers":[
        {
            "category":"Retail",
            "subcategory":"Animal Services",
            "type":"Services"
        }
    ],
    "sg:phone":"+1 360 636 0498",
    "sg:postcode":"98626",
    "sg:province":"WA",
    "wof:name":"Groomingdales",
    "wof:placetype":"venue"
},
  "geometry": {"coordinates":[-122.90342699999999,46.141278],"type":"Point"}
}