{
  "type": "Feature",
  "properties": {
    "addr:full":"1175 Hudson St Longview WA 98632",
    "addr:housenumber":"1175",
    "addr:postcode":"98632",
    "addr:street":"Hudson St",
    "iso:country":"US",
    "sg:address":"1175 Hudson St",
    "sg:city":"Longview",
    "sg:classifiers":[
        {
            "category":"Home & Garden",
            "subcategory":"Furniture",
            "type":"Retail Goods"
        }
    ],
    "sg:phone":"+1 360 425 7434",
    "sg:postcode":"98632",
    "sg:province":"WA",
    "sg:tags":[
        "cabinet"
    ],
    "wof:name":"Cabinet Guyz",
    "wof:placetype":"venue"
},
  "geometry": {"coordinates":[-122.932378,46.136515],"type":"Point"}
}