{
  "type": "Feature",
  "properties": {
    "addr:full":"1504 O Ave Anacortes WA 98221",
    "addr:housenumber":"1504",
    "addr:postcode":"98221",
    "addr:street":"O Ave",
    "iso:country":"US",
    "sg:address":"1504 O Ave",
    "sg:city":"Anacortes",
    "sg:classifiers":[
        {
            "category":"Personal",
            "subcategory":"Beauty Salon",
            "type":"Services"
        }
    ],
    "sg:phone":"+1 360 293 4542",
    "sg:postcode":"98221",
    "sg:province":"WA",
    "wof:name":"Cameo Hair Care",
    "wof:placetype":"venue"
},
  "geometry": {"coordinates":[-122.61411200000001,48.510171],"type":"Point"}
}