{
  "type": "Feature",
  "properties": {
    "addr:full":"2544 Mount Baker Hwy Bellingham WA 98226",
    "addr:housenumber":"2544",
    "addr:postcode":"98226",
    "addr:street":"Mount Baker Hwy",
    "iso:country":"US",
    "sg:address":"2544 Mount Baker Hwy",
    "sg:city":"Bellingham",
    "sg:classifiers":[
        {
            "category":"Utilities",
            "subcategory":"Cable",
            "type":"Services"
        }
    ],
    "sg:phone":"+1 360 734 7930",
    "sg:postcode":"98226",
    "sg:province":"WA",
    "sg:tags":[
        "television"
    ],
    "wof:name":"Fiber Connections Corp",
    "wof:placetype":"venue"
},
  "geometry": {"coordinates":[-122.35463,48.803788],"type":"Point"}
}