{
  "type": "Feature",
  "properties": {
    "addr:full":"328 Garden Ave N Renton WA 98057",
    "addr:housenumber":"328",
    "addr:postcode":"98057",
    "addr:street":"Garden Ave N",
    "iso:country":"US",
    "sg:address":"328 Garden Ave N",
    "sg:city":"Renton",
    "sg:classifiers":[
        {
            "category":"Shopping",
            "subcategory":"Crafts & Fabrics",
            "type":"Retail Goods"
        },
        {
            "category":"Wholesale",
            "subcategory":"Home Furnishings",
            "type":"Manufacturing & Wholesale Goods"
        }
    ],
    "sg:phone":"+1 425 228 5396",
    "sg:postcode":"98057",
    "sg:province":"WA",
    "sg:tags":[
        "draperies",
        "curtain",
        "shades-wholesale",
        "drapery",
        "manufacturer"
    ],
    "wof:name":"Poquettes Quality Fabric",
    "wof:placetype":"venue"
},
  "geometry": {"coordinates":[-122.20041399999999,47.487183],"type":"Point"}
}