{
  "type": "Feature",
  "properties": {
    "iso:country":"US",
    "sg:address":"3704 E Alderman Ln",
    "sg:city":"Spokane",
    "sg:classifiers":[
        {
            "category":"Professional",
            "subcategory":"Accounting & Tax Preparation",
            "type":"Services"
        }
    ],
    "sg:phone":"+1 509 448 7121",
    "sg:postcode":"99223",
    "sg:province":"WA",
    "wof:name":"Stat Attack",
    "wof:placetype":"venue"
},
  "geometry": {"coordinates":[-117.35557799999999,47.620376],"type":"Point"}
}