{
  "type": "Feature",
  "properties": {
    "iso:country":"US",
    "sg:address":"1419 1st Ave",
    "sg:city":"Seattle",
    "sg:classifiers":[
        {
            "category":"Home & Garden",
            "subcategory":"Furniture",
            "type":"Retail Goods"
        }
    ],
    "sg:phone":"+1 206 622 0974",
    "sg:postcode":"98101",
    "sg:province":"WA",
    "sg:tags":[
        "bedding"
    ],
    "wof:name":"Feathered Friends",
    "wof:placetype":"venue"
},
  "geometry": {"coordinates":[-122.339966,47.608597],"type":"Point"}
}