{
  "type": "Feature",
  "properties": {
    "addr:full":"8100 E Mill Plain Blvd Vancouver WA 98664",
    "addr:housenumber":"8100",
    "addr:postcode":"98664",
    "addr:street":"E Mill Plain Blvd",
    "iso:country":"US",
    "sg:address":"8100 E Mill Plain Blvd",
    "sg:city":"Vancouver",
    "sg:classifiers":[
        {
            "category":"Education",
            "subcategory":"School",
            "type":"Public Place"
        }
    ],
    "sg:phone":"+1 360 735 7915",
    "sg:postcode":"98664",
    "sg:province":"WA",
    "wof:name":"Vancouver Christian High Schl",
    "wof:placetype":"venue"
},
  "geometry": {"coordinates":[-122.59118700000001,45.624532],"type":"Point"}
}