{
  "type": "Feature",
  "properties": {
    "addr:full":"5825 221st Pl SE Issaquah WA 98027",
    "addr:housenumber":"5825",
    "addr:postcode":"98027",
    "addr:street":"221St Pl Se",
    "iso:country":"US",
    "sg:address":"5825 221st Pl SE",
    "sg:city":"Issaquah",
    "sg:classifiers":[
        {
            "category":"Health Services",
            "subcategory":"Health Practitioner",
            "type":"Services"
        }
    ],
    "sg:phone":"+1 425 391 7777",
    "sg:postcode":"98027",
    "sg:province":"WA",
    "wof:name":"Alpine Acupuncture",
    "wof:placetype":"venue"
},
  "geometry": {"coordinates":[-122.04386,47.548441],"type":"Point"}
}