{
  "type": "Feature",
  "properties": {
    "addr:full":"140 Gangle Rd Wapato WA 98951",
    "addr:housenumber":"140",
    "addr:postcode":"98951",
    "addr:street":"Gangle Rd",
    "iso:country":"US",
    "sg:address":"140 Gangle Rd",
    "sg:city":"Wapato",
    "sg:classifiers":[
        {
            "category":"Farming",
            "subcategory":"Orchard",
            "type":"Manufacturing & Wholesale Goods"
        }
    ],
    "sg:phone":"+1 509 877 6610",
    "sg:postcode":"98951",
    "sg:province":"WA",
    "sg:tags":[
        "fruit",
        "tree"
    ],
    "wof:name":"Gaylord Enbom Orchardist",
    "wof:placetype":"venue"
},
  "geometry": {"coordinates":[-120.450979,46.514431],"type":"Point"}
}