{
  "type": "Feature",
  "properties": {
    "addr:full":"16202 SE 137th Pl Renton WA 98059",
    "addr:housenumber":"16202",
    "addr:postcode":"98059",
    "addr:street":"Se 137Th Pl",
    "iso:country":"US",
    "sg:address":"16202 SE 137th Pl",
    "sg:city":"Renton",
    "sg:classifiers":[
        {
            "category":"Shopping",
            "subcategory":"Gifts & Souvenirs",
            "type":"Retail Goods"
        }
    ],
    "sg:phone":"+1 425 271 2577",
    "sg:postcode":"98059",
    "sg:province":"WA",
    "wof:name":"J&B Sports Cards",
    "wof:placetype":"venue"
},
  "geometry": {"coordinates":[-122.122354,47.479648],"type":"Point"}
}