{
  "type": "Feature",
  "properties": {
    "addr:full":"4316 106th Pl NE Kirkland WA 98033",
    "addr:housenumber":"4316",
    "addr:postcode":"98033",
    "addr:street":"106Th Pl Ne",
    "iso:country":"US",
    "sg:address":"4316 106th Pl NE",
    "sg:city":"Kirkland",
    "sg:classifiers":[
        {
            "category":"Real Estate",
            "subcategory":"Architect",
            "type":"Services"
        }
    ],
    "sg:phone":"+1 425 822 5015",
    "sg:postcode":"98033",
    "sg:province":"WA",
    "wof:name":"Steinmann John C Archt",
    "wof:placetype":"venue"
},
  "geometry": {"coordinates":[-122.197998,47.648499],"type":"Point"}
}