{
  "type": "Feature",
  "properties": {
    "addr:full":"10849 Auburn Ave S Seattle WA 98178",
    "addr:housenumber":"10849",
    "addr:postcode":"98178",
    "addr:street":"Auburn Ave S",
    "iso:country":"US",
    "sg:address":"10849 Auburn Ave S",
    "sg:city":"Seattle",
    "sg:classifiers":[
        {
            "category":"Professional",
            "subcategory":"Secretarial Services",
            "type":"Services"
        }
    ],
    "sg:phone":"+1 206 772 4302",
    "sg:postcode":"98178",
    "sg:province":"WA",
    "sg:tags":[
        "reporting"
    ],
    "wof:name":"Ascent Publications",
    "wof:placetype":"venue"
},
  "geometry": {"coordinates":[-122.24073,47.505229],"type":"Point"}
}