{
  "type": "Feature",
  "properties": {
    "addr:full":"1200 12th Ave S Seattle WA 98144",
    "addr:housenumber":"1200",
    "addr:postcode":"98144",
    "addr:street":"12Th Ave S",
    "iso:country":"US",
    "sg:address":"1200 12th Ave S",
    "sg:city":"Seattle",
    "sg:classifiers":[
        {
            "category":"Health Services",
            "subcategory":"Doctor",
            "type":"Services"
        },
        {
            "category":"Health Services",
            "subcategory":"Hospital",
            "type":"Services"
        }
    ],
    "sg:phone":"+1 206 326 2400",
    "sg:postcode":"98144",
    "sg:province":"WA",
    "sg:tags":[
        "physician",
        "surgeon",
        "sleep",
        "treatment",
        "disorders-information"
    ],
    "wof:name":"Karen Wang Md",
    "wof:placetype":"venue"
},
  "geometry": {"coordinates":[-122.317251,47.593793],"type":"Point"}
}