{
  "type": "Feature",
  "properties": {
    "addr:full":"585 Pleasant Valley Rd Mineral WA 98355",
    "addr:housenumber":"585",
    "addr:postcode":"98355",
    "addr:street":"Pleasant Valley Rd",
    "iso:country":"US",
    "sg:address":"585 Pleasant Valley Rd",
    "sg:city":"Mineral",
    "sg:classifiers":[
        {
            "category":"Professional",
            "subcategory":"Business Services",
            "type":"Services"
        }
    ],
    "sg:phone":"+1 360 492 5044",
    "sg:postcode":"98355",
    "sg:province":"WA",
    "sg:tags":[
        "consultant",
        "coach"
    ],
    "wof:name":"Pioneer Spirit Enterprises Inc",
    "wof:placetype":"venue"
},
  "geometry": {"coordinates":[-122.24313600000001,46.75329],"type":"Point"}
}