{
  "type": "Feature",
  "properties": {
    "addr:full":"Sunset Corporate Campus I 13810 SE Eastgate Way, Suite 320 Bellevue WA 98005",
    "addr:postcode":"13810;98005",
    "addr:street":"Se Eastgate Way Suite 320",
    "iso:country":"US",
    "sg:address":"Sunset Corporate Campus I 13810 SE Eastgate Way, Suite 320",
    "sg:city":"Bellevue",
    "sg:classifiers":[
        {
            "category":"Professional",
            "subcategory":"Computer Services",
            "type":"Services"
        }
    ],
    "sg:phone":"+1 425 205 9444",
    "sg:postcode":"98005",
    "sg:province":"WA",
    "sg:tags":[
        "visual-search",
        "facial-recognition",
        "video-copyright",
        "enterprise-search"
    ],
    "sg:website":"http://www.eyealike.com",
    "wof:name":"Eyealike",
    "wof:placetype":"venue"
},
  "geometry": {"coordinates":[-122.16876600000001,47.581013],"type":"Point"}
}