{
  "type": "Feature",
  "properties": {
    "iso:country":"US",
    "sg:address":"315 162nd Pl NE",
    "sg:city":"Bellevue",
    "sg:classifiers":[
        {
            "category":"Professional",
            "subcategory":"Accounting & Tax Preparation",
            "type":"Services"
        }
    ],
    "sg:phone":"+1 425 747 7486",
    "sg:postcode":"98008",
    "sg:province":"WA",
    "wof:name":"Dln Bookkeeping Service",
    "wof:placetype":"venue"
},
  "geometry": {"coordinates":[-122.12424300000001,47.612832],"type":"Point"}
}