{
  "type": "Feature",
  "properties": {
    "addr:full":"1501 10th Ave E Seattle WA 98102",
    "addr:housenumber":"1501",
    "addr:postcode":"98102",
    "addr:street":"10Th Ave E",
    "iso:country":"US",
    "sg:address":"1501 10th Ave E",
    "sg:city":"Seattle",
    "sg:classifiers":[
        {
            "category":"Education",
            "subcategory":"Vocational School",
            "type":"Public Place"
        }
    ],
    "sg:phone":"+1 206 526 2787",
    "sg:postcode":"98102",
    "sg:province":"WA",
    "wof:name":"Ask For Josie",
    "wof:placetype":"venue"
},
  "geometry": {"coordinates":[-122.32012,47.632685],"type":"Point"}
}