{
  "type": "Feature",
  "properties": {
    "addr:full":"9122 Evergreen Way Everett WA 98204",
    "addr:housenumber":"9122",
    "addr:postcode":"98204",
    "addr:street":"Evergreen Way",
    "iso:country":"US",
    "sg:address":"9122 Evergreen Way",
    "sg:city":"Everett",
    "sg:classifiers":[
        {
            "category":"Food & Beverages",
            "subcategory":"Specialty",
            "type":"Retail Goods"
        }
    ],
    "sg:phone":"+1 425 353 2665",
    "sg:postcode":"98204",
    "sg:province":"WA",
    "wof:name":"Stars & Stripes Espresso",
    "wof:placetype":"venue"
},
  "geometry": {"coordinates":[-122.23421999999999,47.915823],"type":"Point"}
}