{
  "type": "Feature",
  "properties": {
    "addr:full":"6625 S Puget Sound Ave Tacoma WA 98409",
    "addr:housenumber":"6625",
    "addr:postcode":"98409",
    "addr:street":"S Puget Sound Ave",
    "iso:country":"US",
    "sg:address":"6625 S Puget Sound Ave",
    "sg:city":"Tacoma",
    "sg:classifiers":[
        {
            "category":"Wholesale",
            "subcategory":"Toys & Hobbies",
            "type":"Manufacturing & Wholesale Goods"
        }
    ],
    "sg:phone":"+1 253 503 6198",
    "sg:postcode":"98409",
    "sg:province":"WA",
    "wof:name":"Chronopoly",
    "wof:placetype":"venue"
},
  "geometry": {"coordinates":[-122.482304,47.195842],"type":"Point"}
}