{
  "type": "Feature",
  "properties": {
    "addr:full":"831 12th Ave Longview WA 98632",
    "addr:housenumber":"831",
    "addr:postcode":"98632",
    "addr:street":"12Th Ave",
    "iso:country":"US",
    "sg:address":"831 12th Ave",
    "sg:city":"Longview",
    "sg:classifiers":[
        {
            "category":"Health Services",
            "subcategory":"Health Practitioner",
            "type":"Services"
        }
    ],
    "sg:phone":"+1 360 425 9475",
    "sg:postcode":"98632",
    "sg:province":"WA",
    "wof:name":"Healing Hands Massage",
    "wof:placetype":"venue"
},
  "geometry": {"coordinates":[-122.936094,46.129443],"type":"Point"}
}