{
  "type": "Feature",
  "properties": {
    "iso:country":"US",
    "sg:address":"916 28th St",
    "sg:city":"Anacortes",
    "sg:classifiers":[
        {
            "category":"Building & Trades",
            "subcategory":"Construction",
            "type":"Services"
        }
    ],
    "sg:phone":"+1 360 299 8979",
    "sg:postcode":"98221",
    "sg:province":"WA",
    "sg:tags":[
        "porch",
        "enclosure",
        "patio",
        "deck"
    ],
    "wof:name":"Back Porch",
    "wof:placetype":"venue"
},
  "geometry": {"coordinates":[-122.611328,48.49972],"type":"Point"}
}