{
  "type": "Feature",
  "properties": {
    "addr:full":"315 3rd Ave S Kirkland WA 98033",
    "addr:housenumber":"315",
    "addr:postcode":"98033",
    "addr:street":"3Rd Ave S",
    "iso:country":"US",
    "sg:address":"315 3rd Ave S",
    "sg:city":"Kirkland",
    "sg:classifiers":[
        {
            "category":"Education",
            "subcategory":"Preschool",
            "type":"Public Place"
        },
        {
            "category":"Education",
            "subcategory":"School",
            "type":"Public Place"
        }
    ],
    "sg:phone":"+1 425 889 4444",
    "sg:postcode":"98033",
    "sg:province":"WA",
    "sg:tags":[
        "elementary"
    ],
    "wof:name":"Northlake Preschool",
    "wof:placetype":"venue"
},
  "geometry": {"coordinates":[-122.20187799999999,47.673129],"type":"Point"}
}