{
  "type": "Feature",
  "properties": {
    "addr:full":"2328 77th Ave NE Everett WA 98205",
    "addr:housenumber":"2328",
    "addr:postcode":"98205",
    "addr:street":"77Th Ave Ne",
    "iso:country":"US",
    "sg:address":"2328 77th Ave NE",
    "sg:city":"Everett",
    "sg:classifiers":[
        {
            "category":"Insurance",
            "subcategory":"Insurance Agent",
            "type":"Services"
        }
    ],
    "sg:phone":"+1 425 377 9165",
    "sg:postcode":"98205",
    "sg:province":"WA",
    "wof:name":"Iw Medical Claims Systems",
    "wof:placetype":"venue"
},
  "geometry": {"coordinates":[-122.127162,48.020414],"type":"Point"}
}