{
  "type": "Feature",
  "properties": {
    "addr:full":"1235 Cornwall Ave Bellingham WA 98225",
    "addr:housenumber":"1235",
    "addr:postcode":"98225",
    "addr:street":"Cornwall Ave",
    "iso:country":"US",
    "sg:address":"1235 Cornwall Ave",
    "sg:city":"Bellingham",
    "sg:classifiers":[
        {
            "category":"Home & Garden",
            "subcategory":"Furniture",
            "type":"Retail Goods"
        }
    ],
    "sg:phone":"+1 360 676 1161",
    "sg:postcode":"98225",
    "sg:province":"WA",
    "wof:name":"Greenhouse",
    "wof:placetype":"venue"
},
  "geometry": {"coordinates":[-122.479563,48.749451],"type":"Point"}
}