{
  "type": "Feature",
  "properties": {
    "addr:full":"4772 Mt Adams View Dr West Richland WA 99353",
    "addr:housenumber":"4772",
    "addr:postcode":"99353",
    "addr:street":"Mt Adams View Dr West",
    "iso:country":"US",
    "sg:address":"4772 Mt Adams View Dr",
    "sg:city":"West Richland",
    "sg:classifiers":[
        {
            "category":"Building & Trades",
            "subcategory":"Construction",
            "type":"Services"
        }
    ],
    "sg:phone":"+1 509 967 2664",
    "sg:postcode":"99353",
    "sg:province":"WA",
    "sg:tags":[
        "restoration",
        "cleaning",
        "patio",
        "deck"
    ],
    "wof:name":"Nu-Shine Mobile Pressure Wash",
    "wof:placetype":"venue"
},
  "geometry": {"coordinates":[-119.350904,46.277041],"type":"Point"}
}