{
  "type": "Feature",
  "properties": {
    "addr:full":"3073 N Oak Harbor Rd Oak Harbor WA 98277",
    "addr:housenumber":"3073",
    "addr:postcode":"98277",
    "addr:street":"N Oak Harbor Rd",
    "iso:country":"US",
    "sg:address":"3073 N Oak Harbor Rd",
    "sg:city":"Oak Harbor",
    "sg:classifiers":[
        {
            "category":"Retail",
            "subcategory":"Repair Shop",
            "type":"Services"
        }
    ],
    "sg:phone":"+1 360 675 7748",
    "sg:postcode":"98277",
    "sg:province":"WA",
    "sg:tags":[
        "auto",
        "general"
    ],
    "wof:name":"K&D Engine Service",
    "wof:placetype":"venue"
},
  "geometry": {"coordinates":[-122.655582,48.32121],"type":"Point"}
}