{
  "type": "Feature",
  "properties": {
    "addr:full":"7803 SE 27th St Ste D160 Mercer Island WA 98040",
    "addr:housenumber":"7803",
    "addr:postcode":"98040",
    "addr:street":"Se 27Th St;D160",
    "iso:country":"US",
    "sg:address":"7803 SE 27th St Ste D160",
    "sg:city":"Mercer Island",
    "sg:classifiers":[
        {
            "category":"Health Services",
            "subcategory":"Dentist",
            "type":"Services"
        }
    ],
    "sg:phone":"+1 206 230 4123",
    "sg:postcode":"98040",
    "sg:province":"WA",
    "wof:name":"Bova Dawn DMD Pllc",
    "wof:placetype":"venue"
},
  "geometry": {"coordinates":[-122.233554,47.586572],"type":"Point"}
}