{
  "type": "Feature",
  "properties": {
    "addr:full":"1333 Washington St Vancouver WA 98660",
    "addr:housenumber":"1333",
    "addr:postcode":"98660",
    "addr:street":"Washington St",
    "iso:country":"US",
    "sg:address":"1333 Washington St",
    "sg:city":"Vancouver",
    "sg:classifiers":[
        {
            "category":"Travel",
            "subcategory":"Travel Agent",
            "type":"Entertainment"
        }
    ],
    "sg:phone":"+1 503 295 0515",
    "sg:postcode":"98660",
    "sg:province":"WA",
    "sg:tags":[
        "passenger",
        "transportation",
        "arrangement"
    ],
    "wof:name":"Interocean Steamship Corp",
    "wof:placetype":"venue"
},
  "geometry": {"coordinates":[-122.67257600000001,45.631587],"type":"Point"}
}