{
  "type": "Feature",
  "properties": {
    "iso:country":"US",
    "sg:address":"17100 NE 31st Pl",
    "sg:city":"Bellevue",
    "sg:classifiers":[
        {
            "category":"Professional",
            "subcategory":"Business Services",
            "type":"Services"
        }
    ],
    "sg:phone":"+1 425 869 8209",
    "sg:postcode":"98008",
    "sg:province":"WA",
    "wof:name":"R M Translations Inc",
    "wof:placetype":"venue"
},
  "geometry": {"coordinates":[-122.111537,47.638078],"type":"Point"}
}