{
  "type": "Feature",
  "properties": {
    "addr:full":"706 13th St NE East Wenatchee WA 98802",
    "addr:housenumber":"706",
    "addr:postcode":"98802",
    "addr:street":"13Th St Ne",
    "iso:country":"US",
    "sg:address":"706 13th St NE",
    "sg:city":"East Wenatchee",
    "sg:classifiers":[
        {
            "category":"Professional",
            "subcategory":"Accounting & Tax Preparation",
            "type":"Services"
        }
    ],
    "sg:phone":"+1 509 884 8357",
    "sg:postcode":"98802",
    "sg:province":"WA",
    "sg:tags":[
        "accountant"
    ],
    "wof:name":"W Alfred",
    "wof:placetype":"venue"
},
  "geometry": {"coordinates":[-120.277809,47.424377],"type":"Point"}
}