{
  "type": "Feature",
  "properties": {
    "addr:full":"827 Hazel Ave N Kent WA 98031",
    "addr:housenumber":"827",
    "addr:postcode":"98031",
    "addr:street":"Hazel Ave N",
    "iso:country":"US",
    "sg:address":"827 Hazel Ave N",
    "sg:city":"Kent",
    "sg:classifiers":[
        {
            "category":"Shopping",
            "subcategory":"Clothing, Apparel, & Fashions",
            "type":"Retail Goods"
        }
    ],
    "sg:phone":"+1 206 349 9113",
    "sg:postcode":"98031",
    "sg:province":"WA",
    "sg:tags":[
        "family"
    ],
    "wof:name":"Minority",
    "wof:placetype":"venue"
},
  "geometry": {"coordinates":[-122.222835,47.389831],"type":"Point"}
}