{
  "type": "Feature",
  "properties": {
    "addr:full":"11605 243rd Avenue Ct E Buckley WA 98321",
    "addr:housenumber":"11605",
    "addr:postcode":"98321",
    "addr:street":"243Rd Avenue Ct E",
    "iso:country":"US",
    "sg:address":"11605 243rd Avenue Ct E",
    "sg:city":"Buckley",
    "sg:classifiers":[
        {
            "category":"Professional",
            "subcategory":"Business Services",
            "type":"Services"
        }
    ],
    "sg:phone":"+1 360 897 8933",
    "sg:postcode":"98321",
    "sg:province":"WA",
    "sg:tags":[
        "consultant",
        "coach"
    ],
    "wof:name":"Northwest Development Enterprises",
    "wof:placetype":"venue"
},
  "geometry": {"coordinates":[-122.104896,47.151604],"type":"Point"}
}