{
  "type": "Feature",
  "properties": {
    "addr:full":"11314 4th Ave W Everett WA 98204",
    "addr:housenumber":"11314",
    "addr:postcode":"98204",
    "addr:street":"4Th Ave W",
    "iso:country":"US",
    "sg:address":"11314 4th Ave W",
    "sg:city":"Everett",
    "sg:classifiers":[
        {
            "category":"Professional",
            "subcategory":"Management & Consulting",
            "type":"Services"
        }
    ],
    "sg:phone":"+1 425 423 9624",
    "sg:postcode":"98204",
    "sg:province":"WA",
    "sg:tags":[
        "fuel"
    ],
    "wof:name":"Metco Management Group",
    "wof:placetype":"venue"
},
  "geometry": {"coordinates":[-122.238986,47.895688],"type":"Point"}
}