{
  "type": "Feature",
  "properties": {
    "addr:full":"515 W Francis Ave Ste 1 Spokane WA 99205",
    "addr:housenumber":"515",
    "addr:postcode":"99205",
    "addr:street":"W Francis Ave Ste 1",
    "iso:country":"US",
    "sg:address":"515 W Francis Ave Ste 1",
    "sg:city":"Spokane",
    "sg:classifiers":[
        {
            "category":"Health Services",
            "subcategory":"Chiropractor",
            "type":"Services"
        }
    ],
    "sg:phone":"+1 509 327 8005",
    "sg:postcode":"99205",
    "sg:province":"WA",
    "sg:tags":[
        "chiropractic"
    ],
    "wof:name":"Wellness Clinic",
    "wof:placetype":"venue"
},
  "geometry": {"coordinates":[-117.419489,47.71508],"type":"Point"}
}