{
  "type": "Feature",
  "properties": {
    "addr:full":"123 S Tower Ave Centralia WA 98531",
    "addr:housenumber":"123",
    "addr:postcode":"98531",
    "addr:street":"S Tower Ave",
    "iso:country":"US",
    "sg:address":"123 S Tower Ave",
    "sg:city":"Centralia",
    "sg:classifiers":[
        {
            "category":"Communications",
            "subcategory":"Film & Video Production",
            "type":"Services"
        }
    ],
    "sg:phone":"+1 360 736 0909",
    "sg:postcode":"98531",
    "sg:province":"WA",
    "sg:tags":[
        "motion"
    ],
    "wof:name":"Figaro Productions",
    "wof:placetype":"venue"
},
  "geometry": {"coordinates":[-122.954454,46.716042],"type":"Point"}
}