{
  "type": "Feature",
  "properties": {
    "addr:full":"505 114th Ave E Puyallup WA 98372",
    "addr:housenumber":"505",
    "addr:postcode":"98372",
    "addr:street":"114Th Ave E",
    "iso:country":"US",
    "sg:address":"505 114th Ave E",
    "sg:city":"Puyallup",
    "sg:classifiers":[
        {
            "category":"Retail",
            "subcategory":"Repair Shop",
            "type":"Services"
        }
    ],
    "sg:phone":"+1 253 925 0613",
    "sg:postcode":"98372",
    "sg:province":"WA",
    "wof:name":"Leslie Alvin Prock",
    "wof:placetype":"venue"
},
  "geometry": {"coordinates":[-122.277041,47.2529],"type":"Point"}
}