{
  "type": "Feature",
  "properties": {
    "addr:full":"8649 39th Avenue S Seattle WA 98118",
    "addr:housenumber":"8649",
    "addr:postcode":"98118",
    "addr:street":"39Th Avenue S",
    "iso:country":"US",
    "sg:address":"8649 39th Avenue S",
    "sg:city":"Seattle",
    "sg:classifiers":[
        {
            "category":"Building & Trades",
            "subcategory":"Locksmith",
            "type":"Services"
        }
    ],
    "sg:phone":"+1 206 319 4047",
    "sg:postcode":"98118",
    "sg:province":"WA",
    "sg:tags":[
        "key"
    ],
    "wof:name":"Any Place Locksmith On 39th Av",
    "wof:placetype":"venue"
},
  "geometry": {"coordinates":[-122.283592,47.524924],"type":"Point"}
}