{
  "type": "Feature",
  "properties": {
    "addr:full":"7228 89th Ave SE Snohomish WA 98290",
    "addr:housenumber":"7228",
    "addr:postcode":"98290",
    "addr:street":"89Th Ave Se",
    "iso:country":"US",
    "sg:address":"7228 89th Ave SE",
    "sg:city":"Snohomish",
    "sg:classifiers":[
        {
            "category":"Shopping",
            "subcategory":"Shoes",
            "type":"Retail Goods"
        }
    ],
    "sg:phone":"+1 360 568 6559",
    "sg:postcode":"98290",
    "sg:province":"WA",
    "wof:name":"KS Enterprises",
    "wof:placetype":"venue"
},
  "geometry": {"coordinates":[-122.112033,47.930869],"type":"Point"}
}