{
  "type": "Feature",
  "properties": {
    "addr:full":"3232 165th Ave SE Bellevue WA 98008",
    "addr:housenumber":"3232",
    "addr:postcode":"98008",
    "addr:street":"165Th Ave Se",
    "iso:country":"US",
    "sg:address":"3232 165th Ave SE",
    "sg:city":"Bellevue",
    "sg:classifiers":[
        {
            "category":"Social Services",
            "subcategory":"Child Care",
            "type":"Services"
        }
    ],
    "sg:phone":"+1 425 747 6556",
    "sg:postcode":"98008",
    "sg:province":"WA",
    "sg:tags":[
        "day"
    ],
    "wof:name":"Loving Arms Daycare",
    "wof:placetype":"venue"
},
  "geometry": {"coordinates":[-122.119185,47.580782],"type":"Point"}
}