{
  "type": "Feature",
  "properties": {
    "addr:full":"208 W Market St Aberdeen WA 98520",
    "addr:housenumber":"208",
    "addr:postcode":"98520",
    "addr:street":"W Market St",
    "iso:country":"US",
    "sg:address":"208 W Market St",
    "sg:city":"Aberdeen",
    "sg:classifiers":[
        {
            "category":"Shopping",
            "subcategory":"Bicycles & Sporting Goods",
            "type":"Retail Goods"
        }
    ],
    "sg:phone":"+1 360 532 4890",
    "sg:postcode":"98520",
    "sg:province":"WA",
    "wof:name":"Failor's Sporting Goods",
    "wof:placetype":"venue"
},
  "geometry": {"coordinates":[-123.82016,46.974431],"type":"Point"}
}