{
  "type": "Feature",
  "properties": {
    "iso:country":"US",
    "sg:address":"12017 SW Cove Rd",
    "sg:city":"Vashon",
    "sg:classifiers":[
        {
            "category":"Professional",
            "subcategory":"Advertising",
            "type":"Services"
        }
    ],
    "sg:phone":"+1 206 463 1204",
    "sg:postcode":"98070",
    "sg:province":"WA",
    "wof:name":"Fox Tales Studio",
    "wof:placetype":"venue"
},
  "geometry": {"coordinates":[-122.488613,47.454512],"type":"Point"}
}