{
  "type": "Feature",
  "properties": {
    "iso:country":"US",
    "sg:address":"1825 4th St",
    "sg:city":"Marysville",
    "sg:classifiers":[
        {
            "category":"Building & Trades",
            "subcategory":"Construction",
            "type":"Services"
        }
    ],
    "sg:phone":"+1 360 657 7246",
    "sg:postcode":"98270",
    "sg:province":"WA",
    "sg:tags":[
        "hanging",
        "contractor"
    ],
    "wof:name":"A Plus Quality",
    "wof:placetype":"venue"
},
  "geometry": {"coordinates":[-122.170056,48.051899],"type":"Point"}
}