{
  "type": "Feature",
  "properties": {
    "addr:full":"281 Moonridge Rd Woodland WA 98674",
    "addr:housenumber":"281",
    "addr:postcode":"98674",
    "addr:street":"Moonridge Rd",
    "iso:country":"US",
    "sg:address":"281 Moonridge Rd",
    "sg:city":"Woodland",
    "sg:classifiers":[
        {
            "category":"Wholesale",
            "subcategory":"Stationery",
            "type":"Manufacturing & Wholesale Goods"
        }
    ],
    "sg:phone":"+1 360 225 8811",
    "sg:postcode":"98674",
    "sg:province":"WA",
    "sg:tags":[
        "supply"
    ],
    "wof:name":"Marilyn R Rohm",
    "wof:placetype":"venue"
},
  "geometry": {"coordinates":[-122.752022,45.936462],"type":"Point"}
}