{
  "type": "Feature",
  "properties": {
    "addr:full":"455 Mount Olympus Dr SW Issaquah WA 98027",
    "addr:housenumber":"455",
    "addr:postcode":"98027",
    "addr:street":"Mount Olympus Dr Sw",
    "iso:country":"US",
    "sg:address":"455 Mount Olympus Dr SW",
    "sg:city":"Issaquah",
    "sg:classifiers":[
        {
            "category":"Manufacturing",
            "subcategory":"Apparel",
            "type":"Manufacturing & Wholesale Goods"
        }
    ],
    "sg:phone":"+1 425 392 3611",
    "sg:postcode":"98027",
    "sg:province":"WA",
    "sg:tags":[
        "mfg"
    ],
    "wof:name":"Remar Enterprises",
    "wof:placetype":"venue"
},
  "geometry": {"coordinates":[-122.054548,47.524542],"type":"Point"}
}