{
  "type": "Feature",
  "properties": {
    "addr:full":"13519 E Sprague Ave Spokane Valley WA 99216",
    "addr:housenumber":"13519",
    "addr:postcode":"99216",
    "addr:street":"E Sprague Ave",
    "iso:country":"US",
    "sg:address":"13519 E Sprague Ave",
    "sg:city":"Spokane Valley",
    "sg:classifiers":[
        {
            "category":"Building & Trades",
            "subcategory":"Electrical",
            "type":"Services"
        }
    ],
    "sg:phone":"+1 509 922 8150",
    "sg:postcode":"99216",
    "sg:province":"WA",
    "sg:tags":[
        "electrical",
        "electric",
        "contractor"
    ],
    "wof:name":"S & G Electric Inc",
    "wof:placetype":"venue"
},
  "geometry": {"coordinates":[-117.22157900000001,47.657136],"type":"Point"}
}