{
  "type": "Feature",
  "properties": {
    "addr:full":"218 Polk St Port Townsend WA 98368",
    "addr:housenumber":"218",
    "addr:postcode":"98368",
    "addr:street":"Polk St",
    "iso:country":"US",
    "sg:address":"218 Polk St",
    "sg:city":"Port Townsend",
    "sg:classifiers":[
        {
            "category":"Professional",
            "type":"Services"
        }
    ],
    "sg:phone":"+1 360 379 0366",
    "sg:postcode":"98368",
    "sg:province":"WA",
    "sg:tags":[
        "establishment"
    ],
    "wof:name":"Pacific & Arctic Inc",
    "wof:placetype":"venue"
},
  "geometry": {"coordinates":[-122.75895300000001,48.113971],"type":"Point"}
}