{
  "type": "Feature",
  "properties": {
    "addr:full":"1333 N Northlake Way Seattle WA 98103",
    "addr:housenumber":"1333",
    "addr:postcode":"98103",
    "addr:street":"N Northlake Way",
    "iso:country":"US",
    "sg:address":"1333 N Northlake Way",
    "sg:city":"Seattle",
    "sg:classifiers":[
        {
            "category":"Real Estate",
            "subcategory":"Architect",
            "type":"Services"
        }
    ],
    "sg:phone":"+1 206 548 1315",
    "sg:postcode":"98103",
    "sg:province":"WA",
    "sg:website":"www.edwardcarrarchitect.com",
    "wof:name":"Carr Edward Architect",
    "wof:placetype":"venue"
},
  "geometry": {"coordinates":[-122.34226,47.648014],"type":"Point"}
}