{
  "type": "Feature",
  "properties": {
    "addr:full":"961 Gromore Rd Yakima WA 98908",
    "addr:housenumber":"961",
    "addr:postcode":"98908",
    "addr:street":"Gromore Rd",
    "iso:country":"US",
    "sg:address":"961 Gromore Rd",
    "sg:city":"Yakima",
    "sg:classifiers":[
        {
            "category":"Building & Trades",
            "subcategory":"Construction",
            "type":"Services"
        }
    ],
    "sg:phone":"+1 509 966 6224",
    "sg:postcode":"98908",
    "sg:province":"WA",
    "sg:tags":[
        "concrete",
        "contractor"
    ],
    "wof:name":"Goodwins Concrete Construction",
    "wof:placetype":"venue"
},
  "geometry": {"coordinates":[-120.698798,46.584462],"type":"Point"}
}