{
  "type": "Feature",
  "properties": {
    "addr:full":"2600 Ohio St Silverdale WA 98315",
    "addr:housenumber":"2600",
    "addr:postcode":"98315",
    "addr:street":"Ohio St",
    "iso:country":"US",
    "sg:address":"2600 Ohio St",
    "sg:city":"Silverdale",
    "sg:classifiers":[
        {
            "category":"Building & Trades",
            "subcategory":"Construction",
            "type":"Services"
        }
    ],
    "sg:phone":"+1 360 535 5625",
    "sg:postcode":"98315",
    "sg:province":"WA",
    "sg:tags":[
        "industrial",
        "contractors-commercial",
        "contractor"
    ],
    "wof:name":"C.F. Jordan",
    "wof:placetype":"venue"
},
  "geometry": {"coordinates":[-122.711747,47.68955],"type":"Point"}
}