{
  "type": "Feature",
  "properties": {
    "addr:full":"2005 W Main St Battle Ground WA 98604",
    "addr:housenumber":"2005",
    "addr:postcode":"98604",
    "addr:street":"W Main St",
    "iso:country":"US",
    "sg:address":"2005 W Main St",
    "sg:city":"Battle Ground",
    "sg:classifiers":[
        {
            "category":"Health Services",
            "subcategory":"Health Practitioner",
            "type":"Services"
        }
    ],
    "sg:phone":"+1 360 604 1600",
    "sg:postcode":"98604",
    "sg:province":"WA",
    "sg:tags":[
        "physician",
        "assistant"
    ],
    "wof:name":"Ron Holmes",
    "wof:placetype":"venue"
},
  "geometry": {"coordinates":[-122.558387,45.780506],"type":"Point"}
}