{
  "type": "Feature",
  "properties": {
    "addr:full":"906 SE Everett Mall Way Everett WA 98208",
    "addr:housenumber":"906",
    "addr:postcode":"98208",
    "addr:street":"Se Everett Mall Way",
    "iso:country":"US",
    "sg:address":"906 SE Everett Mall Way",
    "sg:city":"Everett",
    "sg:classifiers":[
        {
            "category":"Utilities",
            "subcategory":"Telephone",
            "type":"Services"
        }
    ],
    "sg:phone":"+1 425 348 1980",
    "sg:postcode":"98208",
    "sg:province":"WA",
    "sg:tags":[
        "telecommunication"
    ],
    "sg:website":"www.verizon.com",
    "wof:name":"Verizon Communications",
    "wof:placetype":"venue"
},
  "geometry": {"coordinates":[-122.220125,47.910196],"type":"Point"}
}