{
  "type": "Feature",
  "properties": {
    "addr:full":"733 Salnave Rd Cheney WA 99004",
    "addr:housenumber":"733",
    "addr:postcode":"99004",
    "addr:street":"Salnave Rd",
    "iso:country":"US",
    "sg:address":"733 Salnave Rd",
    "sg:city":"Cheney",
    "sg:classifiers":[
        {
            "category":"Wholesale",
            "subcategory":"Machinery & Supplies",
            "type":"Manufacturing & Wholesale Goods"
        }
    ],
    "sg:phone":"+1 509 235 8010",
    "sg:postcode":"99004",
    "sg:province":"WA",
    "sg:tags":[
        "equipment",
        "establishment"
    ],
    "wof:name":"Tom A Oswald",
    "wof:placetype":"venue"
},
  "geometry": {"coordinates":[-117.59134,47.481601],"type":"Point"}
}