{
  "type": "Feature",
  "properties": {
    "addr:full":"836 Sunset Ridge Dr Washougal WA 98671",
    "addr:housenumber":"836",
    "addr:postcode":"98671",
    "addr:street":"Sunset Ridge Dr",
    "iso:country":"US",
    "sg:address":"836 Sunset Ridge Dr",
    "sg:city":"Washougal",
    "sg:classifiers":[
        {
            "category":"Real Estate",
            "subcategory":"Real Estate Agent",
            "type":"Services"
        }
    ],
    "sg:phone":"+1 360 835 8116",
    "sg:postcode":"98671",
    "sg:province":"WA",
    "wof:name":"Pacific Lifestyle Homes",
    "wof:placetype":"venue"
},
  "geometry": {"coordinates":[-122.31335199999999,45.582067],"type":"Point"}
}