{
  "type": "Feature",
  "properties": {
    "addr:full":"252 2nd Ave SW Ephrata WA 98823",
    "addr:housenumber":"252",
    "addr:postcode":"98823",
    "addr:street":"2Nd Ave Sw",
    "iso:country":"US",
    "sg:address":"252 2nd Ave SW",
    "sg:city":"Ephrata",
    "sg:classifiers":[
        {
            "category":"Farming",
            "subcategory":"Farm",
            "type":"Manufacturing & Wholesale Goods"
        }
    ],
    "sg:phone":"+1 509 754 0954",
    "sg:postcode":"98823",
    "sg:province":"WA",
    "sg:tags":[
        "crop",
        "general"
    ],
    "wof:name":"Ernest Oscar Farmer",
    "wof:placetype":"venue"
},
  "geometry": {"coordinates":[-119.55408799999999,47.318884],"type":"Point"}
}