{
  "type": "Feature",
  "properties": {
    "addr:full":"5380 SE Harbor Rd Freeland WA 98249",
    "addr:housenumber":"5380",
    "addr:postcode":"98249",
    "addr:street":"Se Harbor Rd",
    "iso:country":"US",
    "sg:address":"5380 SE Harbor Rd",
    "sg:city":"Freeland",
    "sg:classifiers":[
        {
            "category":"Health Services",
            "subcategory":"Optometrist",
            "type":"Services"
        }
    ],
    "sg:phone":"+1 360 331 4520",
    "sg:postcode":"98249",
    "sg:province":"WA",
    "wof:name":"James L Cox Od",
    "wof:placetype":"venue"
},
  "geometry": {"coordinates":[-122.522942,48.015737],"type":"Point"}
}