{
  "type": "Feature",
  "properties": {
    "addr:full":"1325 4th Ave Ste 1500 Seattle WA 98101",
    "addr:housenumber":"1325",
    "addr:postcode":"98101",
    "addr:street":"4Th Ave Ste 1500",
    "iso:country":"US",
    "sg:address":"1325 4th Ave Ste 1500",
    "sg:city":"Seattle",
    "sg:classifiers":[
        {
            "category":"Professional",
            "subcategory":"Lawyer & Legal Services",
            "type":"Services"
        }
    ],
    "sg:phone":"+1 206 583 0050",
    "sg:postcode":"98101",
    "sg:province":"WA",
    "sg:tags":[
        "attorney",
        "dwi",
        "duo"
    ],
    "sg:website":"http://www.duiandinjuryattorneys.com/testimonials/",
    "wof:name":"Law Offices of Alfoster Garrett Jr P.S.",
    "wof:placetype":"venue"
},
  "geometry": {"coordinates":[-122.335097,47.608444],"type":"Point"}
}