{
  "type": "Feature",
  "properties": {
    "addr:full":"16511 SE 46th St Issaquah WA 98027",
    "addr:postcode":"16511;98027",
    "addr:street":"Se 46Th St",
    "iso:country":"US",
    "sg:address":"16511 SE 46th St",
    "sg:city":"Issaquah",
    "sg:classifiers":[
        {
            "category":"Communications",
            "subcategory":"Film & Video Production",
            "type":"Services"
        }
    ],
    "sg:phone":"+1 425 373 1891",
    "sg:postcode":"98027",
    "sg:province":"WA",
    "sg:tags":[
        "tv",
        "radio",
        "services-commercial",
        "companies-film"
    ],
    "wof:name":"Buckles Production Inc",
    "wof:placetype":"venue"
},
  "geometry": {"coordinates":[-122.120288,47.563125],"type":"Point"}
}