{
  "type": "Feature",
  "properties": {
    "addr:full":"4706 Northport-Waneta Rd Colville WA 99114",
    "addr:housenumber":"4706",
    "addr:postcode":"99114",
    "addr:street":"Northport-Waneta Rd",
    "iso:country":"US",
    "sg:address":"4706 Northport-Waneta Rd",
    "sg:city":"Colville",
    "sg:classifiers":[
        {
            "category":"Travel",
            "subcategory":"Campground",
            "type":"Entertainment"
        }
    ],
    "sg:phone":"+1 509 732 4367",
    "sg:postcode":"99114",
    "sg:province":"WA",
    "wof:name":"Upper Columbia Rv Park",
    "wof:placetype":"venue"
},
  "geometry": {"coordinates":[-117.711299,48.942164],"type":"Point"}
}