{
  "type": "Feature",
  "properties": {
    "addr:full":"452 Sand Rd Pullman WA 99163",
    "addr:housenumber":"452",
    "addr:postcode":"99163",
    "addr:street":"Sand Rd",
    "iso:country":"US",
    "sg:address":"452 Sand Rd",
    "sg:city":"Pullman",
    "sg:phone":"+1 509 332 3695",
    "sg:postcode":"99163",
    "sg:province":"WA",
    "sg:tags":[
        "product",
        "petroleum"
    ],
    "wof:name":"Palouse Petro Products",
    "wof:placetype":"venue"
},
  "geometry": {"coordinates":[-117.15093299999999,46.691472],"type":"Point"}
}