{
  "type": "Feature",
  "properties": {
    "iso:country":"US",
    "sg:address":"7419 NE 145th St",
    "sg:city":"Bothell",
    "sg:classifiers":[
        {
            "category":"Building & Trades",
            "subcategory":"Landscaping Services",
            "type":"Services"
        }
    ],
    "sg:phone":"+1 425 823 8606",
    "sg:postcode":"98011",
    "sg:province":"WA",
    "wof:name":"GPM Construction",
    "wof:placetype":"venue"
},
  "geometry": {"coordinates":[-122.242575,47.732158],"type":"Point"}
}