{
  "type": "Feature",
  "properties": {
    "addr:full":"12505 E Houk Ave Spokane Valley WA 99216",
    "addr:housenumber":"12505",
    "addr:postcode":"99216",
    "addr:street":"E Houk Ave",
    "iso:country":"US",
    "sg:address":"12505 E Houk Ave",
    "sg:city":"Spokane Valley",
    "sg:classifiers":[
        {
            "category":"Shopping",
            "type":"Retail Goods"
        }
    ],
    "sg:phone":"+1 509 926 7900",
    "sg:postcode":"99216",
    "sg:province":"WA",
    "sg:tags":[
        "candle"
    ],
    "wof:name":"Spokandle",
    "wof:placetype":"venue"
},
  "geometry": {"coordinates":[-117.236671,47.64126],"type":"Point"}
}