{
  "type": "Feature",
  "properties": {
    "addr:full":"310 Front St Lynden WA 98264",
    "addr:housenumber":"310",
    "addr:postcode":"98264",
    "addr:street":"Front St",
    "iso:country":"US",
    "sg:address":"310 Front St",
    "sg:city":"Lynden",
    "sg:classifiers":[
        {
            "category":"Retail",
            "subcategory":"Portrait Studio",
            "type":"Services"
        }
    ],
    "sg:phone":"+1 360 354 1565",
    "sg:postcode":"98264",
    "sg:province":"WA",
    "sg:tags":[
        "photographer"
    ],
    "wof:name":"Samuel Lee Photography Studio",
    "wof:placetype":"venue"
},
  "geometry": {"coordinates":[-122.45081,48.943503],"type":"Point"}
}