{
  "type": "Feature",
  "properties": {
    "addr:full":"1538 NW 50th St Seattle WA 98107",
    "addr:housenumber":"1538",
    "addr:postcode":"98107",
    "addr:street":"Nw 50Th St",
    "iso:country":"US",
    "sg:address":"1538 NW 50th St",
    "sg:city":"Seattle",
    "sg:classifiers":[
        {
            "category":"Wholesale",
            "subcategory":"Machinery & Supplies",
            "type":"Manufacturing & Wholesale Goods"
        }
    ],
    "sg:phone":"+1 206 784 0148",
    "sg:postcode":"98107",
    "sg:province":"WA",
    "sg:tags":[
        "engine",
        "repair",
        "diesel",
        "generator",
        "marine"
    ],
    "wof:name":"Klassen Engines Company Inc",
    "wof:placetype":"venue"
},
  "geometry": {"coordinates":[-122.378653,47.665126],"type":"Point"}
}