{
  "type": "Feature",
  "properties": {
    "addr:full":"3481 Selah Loop Rd Selah WA 98942",
    "addr:housenumber":"3481",
    "addr:postcode":"98942",
    "addr:street":"Selah Loop Rd",
    "iso:country":"US",
    "sg:address":"3481 Selah Loop Rd",
    "sg:city":"Selah",
    "sg:classifiers":[
        {
            "category":"Shopping",
            "subcategory":"Crafts & Fabrics",
            "type":"Retail Goods"
        }
    ],
    "sg:phone":"+1 509 697 3259",
    "sg:postcode":"98942",
    "sg:province":"WA",
    "sg:tags":[
        "supplies-wholesale",
        "manufacturer",
        "art",
        "supply"
    ],
    "wof:name":"Sharon's Calligraphy Etc",
    "wof:placetype":"venue"
},
  "geometry": {"coordinates":[-120.551149,46.690938],"type":"Point"}
}