{
  "type": "Feature",
  "properties": {
    "addr:full":"13518 48th Pl W Edmonds WA 98026",
    "addr:housenumber":"13518",
    "addr:postcode":"98026",
    "addr:street":"48Th Pl W",
    "iso:country":"US",
    "sg:address":"13518 48th Pl W",
    "sg:city":"Edmonds",
    "sg:classifiers":[
        {
            "category":"Education",
            "subcategory":"Special Training",
            "type":"Public Place"
        }
    ],
    "sg:phone":"+1 425 743 5246",
    "sg:postcode":"98026",
    "sg:province":"WA",
    "wof:name":"Sharons Music Connection",
    "wof:placetype":"venue"
},
  "geometry": {"coordinates":[-122.299055,47.875676],"type":"Point"}
}