{
  "type": "Feature",
  "properties": {
    "addr:full":"1013 S 50th Ave Yakima WA 98908",
    "addr:housenumber":"1013",
    "addr:postcode":"98908",
    "addr:street":"S 50Th Ave",
    "iso:country":"US",
    "sg:address":"1013 S 50th Ave",
    "sg:city":"Yakima",
    "sg:classifiers":[
        {
            "category":"Organizations",
            "subcategory":"Community Association",
            "type":"Services"
        }
    ],
    "sg:phone":"+1 509 966 1214",
    "sg:postcode":"98908",
    "sg:province":"WA",
    "wof:name":"Sons of Italy In America",
    "wof:placetype":"venue"
},
  "geometry": {"coordinates":[-120.574308,46.585736],"type":"Point"}
}