{
  "type": "Feature",
  "properties": {
    "addr:full":"302 S Mission St Wenatchee WA 98801",
    "addr:housenumber":"302",
    "addr:postcode":"98801",
    "addr:street":"S;St",
    "iso:country":"US",
    "sg:address":"302 S Mission St",
    "sg:city":"Wenatchee",
    "sg:classifiers":[
        {
            "category":"Professional",
            "type":"Services"
        },
        {
            "category":"Restaurant",
            "type":"Food & Drink"
        },
        {
            "category":"Retail",
            "subcategory":"Event Space",
            "type":"Services"
        },
        {
            "category":"Fast Food",
            "type":"Food & Drink"
        }
    ],
    "sg:phone":"+1 509 663 1013",
    "sg:postcode":"98801",
    "sg:province":"WA",
    "sg:tags":[
        "facility",
        "banquet",
        "take",
        "reception",
        "caterer",
        "hall"
    ],
    "wof:name":"Wild Huckleberry",
    "wof:placetype":"venue"
},
  "geometry": {"coordinates":[-120.30952000000001,47.420367],"type":"Point"}
}