{
  "type": "Feature",
  "properties": {
    "addr:full":"1101 Fidalgo St Sedro Woolley WA 98284",
    "addr:housenumber":"1101",
    "addr:postcode":"98284",
    "addr:street":"Fidalgo St",
    "iso:country":"US",
    "sg:address":"1101 Fidalgo St",
    "sg:city":"Sedro Woolley",
    "sg:classifiers":[
        {
            "category":"Organizations",
            "subcategory":"Religious Organization",
            "type":"Services"
        }
    ],
    "sg:phone":"+1 360 855 2326",
    "sg:postcode":"98284",
    "sg:province":"WA",
    "wof:name":"Jesus Padilla Curiel",
    "wof:placetype":"venue"
},
  "geometry": {"coordinates":[-122.221627,48.497833],"type":"Point"}
}