{
  "type": "Feature",
  "properties": {
    "addr:full":"7600 5th Ave S Seattle WA 98108",
    "addr:housenumber":"7600",
    "addr:postcode":"98108",
    "addr:street":"5Th Ave S",
    "iso:country":"US",
    "sg:address":"7600 5th Ave S",
    "sg:city":"Seattle",
    "sg:classifiers":[
        {
            "category":"Manufacturing",
            "subcategory":"Printing",
            "type":"Manufacturing & Wholesale Goods"
        }
    ],
    "sg:phone":"+1 206 768 7052",
    "sg:postcode":"98108",
    "sg:province":"WA",
    "sg:tags":[
        "lithographic",
        "commercial"
    ],
    "wof:name":"Printmasters Plus",
    "wof:placetype":"venue"
},
  "geometry": {"coordinates":[-122.32813400000001,47.53413],"type":"Point"}
}