{
  "type": "Feature",
  "properties": {
    "addr:full":"651 S Rivard Rd Moxee WA 98936",
    "addr:housenumber":"651",
    "addr:postcode":"98936",
    "addr:street":"S Rivard Rd",
    "iso:country":"US",
    "sg:address":"651 S Rivard Rd",
    "sg:city":"Moxee",
    "sg:classifiers":[
        {
            "category":"Building & Trades",
            "subcategory":"Construction",
            "type":"Services"
        }
    ],
    "sg:phone":"+1 509 248 1685",
    "sg:postcode":"98936",
    "sg:province":"WA",
    "sg:tags":[
        "house"
    ],
    "wof:name":"Drainage Improvement District",
    "wof:placetype":"venue"
},
  "geometry": {"coordinates":[-120.385459,46.548065],"type":"Point"}
}