{
  "type": "Feature",
  "properties": {
    "addr:full":"1423 W Garland Ave Spokane WA 99205",
    "addr:housenumber":"1423",
    "addr:postcode":"99205",
    "addr:street":"W Garland Ave",
    "iso:country":"US",
    "sg:address":"1423 W Garland Ave",
    "sg:city":"Spokane",
    "sg:classifiers":[
        {
            "category":"Insurance",
            "subcategory":"Insurance Agent",
            "type":"Services"
        },
        {
            "category":"Insurance",
            "subcategory":"Hazard Insurance",
            "type":"Services"
        }
    ],
    "sg:phone":"+1 509 326 7060",
    "sg:postcode":"99205",
    "sg:province":"WA",
    "sg:tags":[
        "auto"
    ],
    "sg:website":"http://www.farwestinsurance.com",
    "wof:name":"Farwest Insurance",
    "wof:placetype":"venue"
},
  "geometry": {"coordinates":[-117.43265599999999,47.693501],"type":"Point"}
}