{
  "type": "Feature",
  "properties": {
    "addr:full":"5716 149th Ave SE Bellevue WA 98006",
    "addr:housenumber":"5716",
    "addr:postcode":"98006",
    "addr:street":"149Th Ave Se",
    "iso:country":"US",
    "sg:address":"5716 149th Ave SE",
    "sg:city":"Bellevue",
    "sg:classifiers":[
        {
            "category":"Home & Garden",
            "subcategory":"Household Appliances",
            "type":"Retail Goods"
        },
        {
            "category":"Building & Trades",
            "subcategory":"Construction",
            "type":"Services"
        },
        {
            "category":"Building & Trades",
            "subcategory":"Electrical",
            "type":"Services"
        }
    ],
    "sg:phone":"+1 425 643 0368",
    "sg:postcode":"98006",
    "sg:province":"WA",
    "sg:tags":[
        "major",
        "system",
        "appliances-small",
        "specialty",
        "furnaces-heating",
        "heating",
        "contractor",
        "air conditioning"
    ],
    "sg:website":"http://www.alphaheatandac.com",
    "wof:name":"Alpha Heating & Air Conditioning",
    "wof:placetype":"venue"
},
  "geometry": {"coordinates":[-122.139759,47.551391],"type":"Point"}
}