{
  "type": "Feature",
  "properties": {
    "addr:full":"2100 James St Bellingham WA 98225",
    "addr:housenumber":"2100",
    "addr:postcode":"98225",
    "addr:street":"James St",
    "iso:country":"US",
    "sg:address":"2100 James St",
    "sg:city":"Bellingham",
    "sg:classifiers":[
        {
            "category":"Home & Garden",
            "subcategory":"Hardware",
            "type":"Retail Goods"
        }
    ],
    "sg:phone":"+1 360 733 4256",
    "sg:postcode":"98225",
    "sg:province":"WA",
    "sg:tags":[
        "equipment",
        "parts",
        "sales",
        "power"
    ],
    "wof:name":"General Chain Saw Supply Inc",
    "wof:placetype":"venue"
},
  "geometry": {"coordinates":[-122.464918,48.759077],"type":"Point"}
}