{
  "type": "Feature",
  "properties": {
    "addr:full":"457 E 18th St Tacoma WA 98421",
    "addr:housenumber":"457",
    "addr:postcode":"98421",
    "addr:street":"E 18Th St",
    "iso:country":"US",
    "sg:address":"457 E 18th St",
    "sg:city":"Tacoma",
    "sg:classifiers":[
        {
            "category":"Freight",
            "type":"Transportation"
        }
    ],
    "sg:phone":"+1 253 383 1009",
    "sg:postcode":"98421",
    "sg:province":"WA",
    "sg:tags":[
        "dry",
        "distance",
        "storage",
        "hauling",
        "long",
        "trucking",
        "bulk",
        "without"
    ],
    "sg:website":"www.qualitytransport.com",
    "wof:name":"Truck Rail Handling Inc",
    "wof:placetype":"venue"
},
  "geometry": {"coordinates":[-122.42384300000001,47.246748],"type":"Point"}
}