{
  "type": "Feature",
  "properties": {
    "addr:full":"8733 21st Ave NW Seattle WA 98117",
    "addr:housenumber":"8733",
    "addr:postcode":"98117",
    "addr:street":"21St Ave Nw",
    "iso:country":"US",
    "sg:address":"8733 21st Ave NW",
    "sg:city":"Seattle",
    "sg:classifiers":[
        {
            "category":"Shopping",
            "subcategory":"Bicycles & Sporting Goods",
            "type":"Retail Goods"
        }
    ],
    "sg:phone":"+1 206 297 9436",
    "sg:postcode":"98117",
    "sg:province":"WA",
    "sg:tags":[
        "netting"
    ],
    "wof:name":"Fishnet Northwest Inc",
    "wof:placetype":"venue"
},
  "geometry": {"coordinates":[-122.382976,47.693452],"type":"Point"}
}