{
  "type": "Feature",
  "properties": {
    "addr:full":"5517 16th Ave NE Seattle WA 98105",
    "addr:housenumber":"5517",
    "addr:postcode":"98105",
    "addr:street":"16Th Ave Ne",
    "iso:country":"US",
    "sg:address":"5517 16th Ave NE",
    "sg:city":"Seattle",
    "sg:classifiers":[
        {
            "category":"Building & Trades",
            "subcategory":"Landscaping Services",
            "type":"Services"
        }
    ],
    "sg:phone":"+1 206 525 4002",
    "sg:postcode":"98105",
    "sg:province":"WA",
    "sg:tags":[
        "landscape"
    ],
    "wof:name":"Design Collaboration",
    "wof:placetype":"venue"
},
  "geometry": {"coordinates":[-122.310827,47.669295],"type":"Point"}
}