{
  "type": "Feature",
  "properties": {
    "addr:full":"1515 145 se Bellevue WA 98007",
    "addr:housenumber":"1515",
    "addr:postcode":"98007",
    "addr:street":"145 Se",
    "iso:country":"US",
    "sg:address":"1515 145 se",
    "sg:city":"Bellevue",
    "sg:classifiers":[
        {
            "category":"Building & Trades",
            "subcategory":"Landscaping Services",
            "type":"Services"
        }
    ],
    "sg:phone":"+1 425 443 4852",
    "sg:postcode":"98007",
    "sg:province":"WA",
    "sg:tags":[
        "lawn"
    ],
    "sg:website":"http://bellevuegardendesign.info",
    "wof:name":"Bellevue Lawn And Garden Design",
    "wof:placetype":"venue"
},
  "geometry": {"coordinates":[-122.150722,47.59731],"type":"Point"}
}