{
  "type": "Feature",
  "properties": {
    "addr:full":"6205 15th Ave NW Seattle WA 98107",
    "addr:housenumber":"6205",
    "addr:postcode":"98107",
    "addr:street":"15Th Ave Nw",
    "iso:country":"US",
    "sg:address":"6205 15th Ave NW",
    "sg:city":"Seattle",
    "sg:classifiers":[
        {
            "category":"Retail",
            "subcategory":"Laundry & Dry Cleaning",
            "type":"Services"
        }
    ],
    "sg:phone":"+1 206 781 1249",
    "sg:postcode":"98107",
    "sg:province":"WA",
    "sg:tags":[
        "sewing",
        "alteration"
    ],
    "wof:name":"Finer Alterations",
    "wof:placetype":"venue"
},
  "geometry": {"coordinates":[-122.37599899999999,47.674198],"type":"Point"}
}