{
  "type": "Feature",
  "properties": {
    "addr:full":"1005 Spring St Seattle WA 98104",
    "addr:housenumber":"1005",
    "addr:postcode":"98104",
    "addr:street":"Spring St",
    "iso:country":"US",
    "sg:address":"1005 Spring St",
    "sg:city":"Seattle",
    "sg:classifiers":[
        {
            "category":"Travel",
            "subcategory":"Hotels & Motels",
            "type":"Entertainment"
        }
    ],
    "sg:phone":"+1 206 624 0787",
    "sg:postcode":"98104",
    "sg:province":"WA",
    "sg:website":"www.baronesshotel.com",
    "wof:name":"The Baroness Hotel",
    "wof:placetype":"venue"
},
  "geometry": {"coordinates":[-122.326807,47.609607],"type":"Point"}
}