{
  "type": "Feature",
  "properties": {
    "addr:full":"412 11th Ave Seattle WA 98122",
    "addr:housenumber":"412",
    "addr:postcode":"98122",
    "addr:street":"11Th Ave",
    "iso:country":"US",
    "sg:address":"412 11th Ave",
    "sg:city":"Seattle",
    "sg:classifiers":[
        {
            "category":"Building & Trades",
            "subcategory":"Locksmith",
            "type":"Services"
        }
    ],
    "sg:phone":"+1 206 701 6601",
    "sg:postcode":"98122",
    "sg:province":"WA",
    "sg:tags":[
        "key"
    ],
    "wof:name":"Locksmith Always",
    "wof:placetype":"venue"
},
  "geometry": {"coordinates":[-122.317888,47.605372],"type":"Point"}
}