{
  "type": "Feature",
  "properties": {
    "addr:full":"4580 Klahanie Dr SE Issaquah WA 98029",
    "addr:postcode":"4580;98029",
    "addr:street":"Klahanie Dr Se",
    "iso:country":"US",
    "sg:address":"4580 Klahanie Dr SE",
    "sg:city":"Issaquah",
    "sg:classifiers":[
        {
            "category":"Insurance",
            "subcategory":"Insurance Agent",
            "type":"Services"
        }
    ],
    "sg:phone":"+1 425 391 4245",
    "sg:postcode":"98029",
    "sg:province":"WA",
    "wof:name":"Franklin Life Insurance Co",
    "wof:placetype":"venue"
},
  "geometry": {"coordinates":[-122.004234,47.564266],"type":"Point"}
}