{
  "type": "Feature",
  "properties": {
    "addr:full":"101 Glover St Twisp WA 98856",
    "addr:housenumber":"101",
    "addr:postcode":"98856",
    "addr:street":"Glover St",
    "iso:country":"US",
    "sg:address":"101 Glover St",
    "sg:city":"Twisp",
    "sg:classifiers":[
        {
            "category":"Professional",
            "subcategory":"Advertising",
            "type":"Services"
        },
        {
            "category":"Communications",
            "subcategory":"Newspaper",
            "type":"Services"
        },
        {
            "category":"Wholesale",
            "subcategory":"Books, Periodicals, & Newspapers",
            "type":"Manufacturing & Wholesale Goods"
        }
    ],
    "sg:phone":"+1 509 997 7011",
    "sg:postcode":"98856",
    "sg:province":"WA",
    "sg:tags":[
        "print",
        "news",
        "dealers-wholesale"
    ],
    "sg:website":"http://www.methowvalleynews.com",
    "wof:name":"Methow Valley Publishing",
    "wof:placetype":"venue"
},
  "geometry": {"coordinates":[-120.12130000000001,48.362629],"type":"Point"}
}