{
  "type": "Feature",
  "properties": {
    "addr:full":"1253 SW Othello St Seattle WA 98106",
    "addr:housenumber":"1253",
    "addr:postcode":"98106",
    "addr:street":"Sw Othello St",
    "iso:country":"US",
    "sg:address":"1253 SW Othello St",
    "sg:city":"Seattle",
    "sg:classifiers":[
        {
            "category":"Professional",
            "subcategory":"Lawyer & Legal Services",
            "type":"Services"
        }
    ],
    "sg:phone":"+1 253 476 6608",
    "sg:postcode":"98106",
    "sg:province":"WA",
    "wof:name":"3r Enviromental Services",
    "wof:placetype":"venue"
},
  "geometry": {"coordinates":[-122.35460500000001,47.537228],"type":"Point"}
}