{
  "type": "Feature",
  "properties": {
    "addr:full":"724 S 4th St Dayton WA 99328",
    "addr:housenumber":"724",
    "addr:postcode":"99328",
    "addr:street":"S 4Th St",
    "iso:country":"US",
    "sg:address":"724 S 4th St",
    "sg:city":"Dayton",
    "sg:classifiers":[
        {
            "category":"Food & Beverages",
            "subcategory":"Groceries & Convenience Stores",
            "type":"Retail Goods"
        }
    ],
    "sg:phone":"+1 509 382 2231",
    "sg:postcode":"99328",
    "sg:province":"WA",
    "sg:tags":[
        "grocer"
    ],
    "wof:name":"Steve's Cash Grocery",
    "wof:placetype":"venue"
},
  "geometry": {"coordinates":[-117.97082,46.31622],"type":"Point"}
}