{
  "type": "Feature",
  "properties": {
    "addr:full":"2501 Commercial Ave Anacortes WA 98221",
    "addr:housenumber":"2501",
    "addr:postcode":"98221",
    "addr:street":"Commercial Ave",
    "iso:country":"US",
    "sg:address":"2501 Commercial Ave",
    "sg:city":"Anacortes",
    "sg:classifiers":[
        {
            "category":"Restaurant",
            "type":"Food & Drink"
        }
    ],
    "sg:phone":"+1 360 293 9595",
    "sg:postcode":"98221",
    "sg:province":"WA",
    "wof:name":"Hong Kong Gardens",
    "wof:placetype":"venue"
},
  "geometry": {"coordinates":[-122.612742,48.502064],"type":"Point"}
}