{
  "type": "Feature",
  "properties": {
    "addr:full":"1726 271st Pl Ocean Park WA 98640",
    "addr:housenumber":"1726",
    "addr:postcode":"98640",
    "addr:street":"271St Pl;Park",
    "iso:country":"US",
    "sg:address":"1726 271st Pl",
    "sg:city":"Ocean Park",
    "sg:classifiers":[
        {
            "category":"Building & Trades",
            "subcategory":"Construction",
            "type":"Services"
        }
    ],
    "sg:phone":"+1 360 665 3555",
    "sg:postcode":"98640",
    "sg:province":"WA",
    "sg:tags":[
        "general",
        "contractor"
    ],
    "wof:name":"William J Tweed",
    "wof:placetype":"venue"
},
  "geometry": {"coordinates":[-124.048599,46.498583],"type":"Point"}
}