{
  "type": "Feature",
  "properties": {
    "addr:full":"9065 Martin Luther King Jr Way S Seattle WA 98118",
    "addr:housenumber":"9065",
    "addr:postcode":"98118",
    "addr:street":"Martin Luther King Jr Way S",
    "iso:country":"US",
    "sg:address":"9065 Martin Luther King Jr Way S",
    "sg:city":"Seattle",
    "sg:classifiers":[
        {
            "category":"Place Of Worship",
            "subcategory":"Church",
            "type":"Public Place"
        },
        {
            "category":"Place Of Worship",
            "type":"Public Place"
        }
    ],
    "sg:phone":"+1 206 723 6211",
    "sg:postcode":"98118",
    "sg:province":"WA",
    "sg:tags":[
        "churches-baptist-general",
        "churches-baptist"
    ],
    "wof:name":"Cornerstone Filipino-American Baptist Church Inc",
    "wof:placetype":"venue"
},
  "geometry": {"coordinates":[-122.279545,47.522439],"type":"Point"}
}