{
  "type": "Feature",
  "properties": {
    "addr:full":"1226 N Hamilton St Spokane WA 99202",
    "addr:housenumber":"1226",
    "addr:postcode":"99202",
    "addr:street":"N Hamilton St",
    "iso:country":"US",
    "sg:address":"1226 N Hamilton St",
    "sg:city":"Spokane",
    "sg:classifiers":[
        {
            "category":"Bars & Pubs",
            "type":"Food & Drink"
        }
    ],
    "sg:phone":"+1 509 487 6546",
    "sg:postcode":"99202",
    "sg:province":"WA",
    "sg:tags":[
        "drinking"
    ],
    "wof:name":"Jack & Dan's Tavern",
    "wof:placetype":"venue"
},
  "geometry": {"coordinates":[-117.396463,47.668682],"type":"Point"}
}