{
  "type": "Feature",
  "properties": {
    "addr:full":"2624 34th Ave W Seattle WA 98199",
    "addr:housenumber":"2624",
    "addr:postcode":"98199",
    "addr:street":"34Th Ave W",
    "iso:country":"US",
    "sg:address":"2624 34th Ave W",
    "sg:city":"Seattle",
    "sg:classifiers":[
        {
            "category":"Professional",
            "subcategory":"Business Services",
            "type":"Services"
        }
    ],
    "sg:phone":"+1 206 284 6192",
    "sg:postcode":"98199",
    "sg:province":"WA",
    "wof:name":"Murbros LLC",
    "wof:placetype":"venue"
},
  "geometry": {"coordinates":[-122.400899,47.64217],"type":"Point"}
}