{
  "type": "Feature",
  "properties": {
    "addr:full":"3410 214th Pl SE Sammamish WA 98075",
    "addr:housenumber":"3410",
    "addr:postcode":"98075",
    "addr:street":"214Th Pl Se",
    "iso:country":"US",
    "sg:address":"3410 214th Pl SE",
    "sg:city":"Sammamish",
    "sg:classifiers":[
        {
            "category":"Building & Trades",
            "subcategory":"Cleaning & Sanitation",
            "type":"Services"
        }
    ],
    "sg:phone":"+1 425 427 6746",
    "sg:postcode":"98075",
    "sg:province":"WA",
    "sg:tags":[
        "property",
        "maintenance"
    ],
    "wof:name":"Dmh Services Inc",
    "wof:placetype":"venue"
},
  "geometry": {"coordinates":[-122.053391,47.578698],"type":"Point"}
}