{
  "type": "Feature",
  "properties": {
    "addr:full":"210 128th St SE Everett WA 98208",
    "addr:housenumber":"210",
    "addr:postcode":"98208",
    "addr:street":"128Th St Se",
    "iso:country":"US",
    "sg:address":"210 128th St SE",
    "sg:city":"Everett",
    "sg:classifiers":[
        {
            "category":"Health Services",
            "subcategory":"Doctor",
            "type":"Services"
        }
    ],
    "sg:phone":"+1 425 337 5100",
    "sg:postcode":"98208",
    "sg:province":"WA",
    "sg:tags":[
        "physician"
    ],
    "wof:name":"North Creek Medicine",
    "wof:placetype":"venue"
},
  "geometry": {"coordinates":[-122.22934600000001,47.881889],"type":"Point"}
}