{
  "type": "Feature",
  "properties": {
    "addr:full":"2138 93rd Ave SE Olympia WA 98501",
    "addr:housenumber":"2138",
    "addr:postcode":"98501",
    "addr:street":"93Rd Ave Se",
    "iso:country":"US",
    "sg:address":"2138 93rd Ave SE",
    "sg:city":"Olympia",
    "sg:classifiers":[
        {
            "category":"Home & Garden",
            "subcategory":"Building Materials",
            "type":"Retail Goods"
        }
    ],
    "sg:phone":"+1 360 352 8524",
    "sg:postcode":"98501",
    "sg:province":"WA",
    "sg:tags":[
        "lumber"
    ],
    "wof:name":"Pfaff Lumber Co",
    "wof:placetype":"venue"
},
  "geometry": {"coordinates":[-122.86635800000001,46.952881],"type":"Point"}
}