{
  "type": "Feature",
  "properties": {
    "addr:full":"3024 Steilacoom Blvd Steilacoom WA 98388",
    "addr:housenumber":"3024",
    "addr:postcode":"98388",
    "addr:street":"Steilacoom Blvd",
    "iso:country":"US",
    "sg:address":"3024 Steilacoom Blvd",
    "sg:city":"Steilacoom",
    "sg:classifiers":[
        {
            "category":"Real Estate",
            "subcategory":"Real Estate Operator",
            "type":"Services"
        }
    ],
    "sg:phone":"+1 253 582 3022",
    "sg:postcode":"98388",
    "sg:province":"WA",
    "sg:tags":[
        "building",
        "apartment"
    ],
    "wof:name":"Westwood Apartments",
    "wof:placetype":"venue"
},
  "geometry": {"coordinates":[-122.577003,47.1768],"type":"Point"}
}