{
  "type": "Feature",
  "properties": {
    "addr:full":"614 E Main St Battle Ground WA 98604",
    "addr:housenumber":"614",
    "addr:postcode":"98604",
    "addr:street":"E Main St",
    "iso:country":"US",
    "sg:address":"614 E Main St",
    "sg:city":"Battle Ground",
    "sg:classifiers":[
        {
            "category":"Professional",
            "subcategory":"Art Services",
            "type":"Services"
        }
    ],
    "sg:phone":"+1 360 687 9458",
    "sg:postcode":"98604",
    "sg:province":"WA",
    "sg:tags":[
        "graphic",
        "designer"
    ],
    "wof:name":"T K Graphics",
    "wof:placetype":"venue"
},
  "geometry": {"coordinates":[-122.53091999999999,45.781017],"type":"Point"}
}