{
  "type": "Feature",
  "properties": {
    "addr:full":"7304 W Old Inland Empire Hwy Benton City WA 99320",
    "addr:housenumber":"7304",
    "addr:postcode":"99320",
    "addr:street":"W Old;Empire Hwy",
    "iso:country":"US",
    "sg:address":"7304 W Old Inland Empire Hwy",
    "sg:city":"Benton City",
    "sg:classifiers":[
        {
            "category":"Arts & Performance",
            "subcategory":"Theater",
            "type":"Entertainment"
        }
    ],
    "sg:phone":"+1 509 588 5368",
    "sg:postcode":"99320",
    "sg:province":"WA",
    "sg:tags":[
        "entertainer",
        "group",
        "business"
    ],
    "wof:name":"Two of Clubs",
    "wof:placetype":"venue"
},
  "geometry": {"coordinates":[-119.505576,46.272063],"type":"Point"}
}