{
  "type": "Feature",
  "properties": {
    "addr:full":"1113 Caveness Dr Centralia WA 98531",
    "addr:housenumber":"1113",
    "addr:postcode":"98531",
    "addr:street":"Caveness Dr",
    "iso:country":"US",
    "sg:address":"1113 Caveness Dr",
    "sg:city":"Centralia",
    "sg:classifiers":[
        {
            "category":"Real Estate",
            "subcategory":"Developer",
            "type":"Services"
        },
        {
            "category":"Real Estate",
            "subcategory":"Real Estate Agent",
            "type":"Services"
        }
    ],
    "sg:phone":"+1 360 736 9140",
    "sg:postcode":"98531",
    "sg:province":"WA",
    "sg:tags":[
        "management",
        "cemetery"
    ],
    "wof:name":"Mountain View Cemetery Inc",
    "wof:placetype":"venue"
},
  "geometry": {"coordinates":[-122.982511,46.728019],"type":"Point"}
}