{
  "type": "Feature",
  "properties": {
    "addr:full":"2233 S 320th St Federal Way WA 98003",
    "addr:housenumber":"2233",
    "addr:postcode":"98003",
    "addr:street":"S 320Th St",
    "iso:country":"US",
    "sg:address":"2233 S 320th St",
    "sg:city":"Federal Way",
    "sg:classifiers":[
        {
            "category":"Restaurant",
            "type":"Food & Drink"
        }
    ],
    "sg:menulink":"http://www.allmenus.com/wa/auburn/9027-red-robin/menu/",
    "sg:phone":"+1 253 946 8646",
    "sg:postcode":"98003",
    "sg:province":"WA",
    "sg:tags":[
        "american"
    ],
    "wof:name":"Red Robin",
    "wof:placetype":"venue"
},
  "geometry": {"coordinates":[-122.305695,47.315167],"type":"Point"}
}