{
  "type": "Feature",
  "properties": {
    "addr:full":"17224 SE 272nd St Kent WA 98042",
    "addr:postcode":"17224;98042",
    "addr:street":"Se 272Nd St",
    "iso:country":"US",
    "sg:address":"17224 SE 272nd St",
    "sg:city":"Kent",
    "sg:classifiers":[
        {
            "category":"Health Services",
            "subcategory":"Health Practitioner",
            "type":"Services"
        }
    ],
    "sg:phone":"+1 253 630 5808",
    "sg:postcode":"98042",
    "sg:province":"WA",
    "wof:name":"Outpatient Physical Theraphy",
    "wof:placetype":"venue"
},
  "geometry": {"coordinates":[-122.111091,47.35825],"type":"Point"}
}