{
  "type": "Feature",
  "properties": {
    "addr:full":"4900 9th Ave NW Seattle WA 98107",
    "addr:housenumber":"4900",
    "addr:postcode":"98107",
    "addr:street":"9Th Ave Nw",
    "iso:country":"US",
    "sg:address":"4900 9th Ave NW",
    "sg:city":"Seattle",
    "sg:classifiers":[
        {
            "category":"Professional",
            "subcategory":"Accounting & Tax Preparation",
            "type":"Services"
        }
    ],
    "sg:phone":"+1 206 781 0470",
    "sg:postcode":"98107",
    "sg:province":"WA",
    "sg:tags":[
        "accountant"
    ],
    "wof:name":"Jerri Harden CPA",
    "wof:placetype":"venue"
},
  "geometry": {"coordinates":[-122.368611,47.665037],"type":"Point"}
}