{
  "type": "Feature",
  "properties": {
    "iso:country":"US",
    "sg:address":"23419 107th Ave SW",
    "sg:city":"Vashon",
    "sg:classifiers":[
        {
            "category":"Building & Trades",
            "subcategory":"Construction",
            "type":"Services"
        }
    ],
    "sg:phone":"+1 206 463 4363",
    "sg:postcode":"98070",
    "sg:province":"WA",
    "sg:tags":[
        "excavation",
        "contractor"
    ],
    "wof:name":"Earthscapes",
    "wof:placetype":"venue"
},
  "geometry": {"coordinates":[-122.471284,47.394223],"type":"Point"}
}