{
  "type": "Feature",
  "properties": {
    "addr:full":"516 Broad Street Seattle WA 98109",
    "addr:housenumber":"516",
    "addr:postcode":"98109",
    "addr:street":"Broad Street",
    "iso:country":"US",
    "sg:address":"516 Broad Street",
    "sg:city":"Seattle",
    "sg:classifiers":[
        {
            "category":"Building & Trades",
            "subcategory":"Locksmith",
            "type":"Services"
        }
    ],
    "sg:phone":"+1 206 319 4114",
    "sg:postcode":"98109",
    "sg:province":"WA",
    "sg:tags":[
        "key"
    ],
    "wof:name":"1 Hour 7 Day Emergency Locksmith On Broad",
    "wof:placetype":"venue"
},
  "geometry": {"coordinates":[-122.34698899999999,47.621117],"type":"Point"}
}