{
  "type": "Feature",
  "properties": {
    "addr:full":"7808 NE 94th Ave Vancouver WA 98662",
    "addr:housenumber":"7808",
    "addr:postcode":"98662",
    "addr:street":"Ne 94Th Ave",
    "iso:country":"US",
    "sg:address":"7808 NE 94th Ave",
    "sg:city":"Vancouver",
    "sg:classifiers":[
        {
            "category":"Place Of Worship",
            "subcategory":"Church",
            "type":"Public Place"
        },
        {
            "category":"Place Of Worship",
            "type":"Public Place"
        }
    ],
    "sg:phone":"+1 360 254 5198",
    "sg:postcode":"98662",
    "sg:province":"WA",
    "sg:tags":[
        "churches-interdenominational",
        "churches-various",
        "denomination"
    ],
    "wof:name":"Lighthouse Christian Church Inc",
    "wof:placetype":"venue"
},
  "geometry": {"coordinates":[-122.576071,45.678862],"type":"Point"}
}