{
  "type": "Feature",
  "properties": {
    "addr:full":"2610 W Kennewick Ave Kennewick WA 99336",
    "addr:housenumber":"2610",
    "addr:postcode":"99336",
    "addr:street":"W Kennewick Ave",
    "iso:country":"US",
    "sg:address":"2610 W Kennewick Ave",
    "sg:city":"Kennewick",
    "sg:classifiers":[
        {
            "category":"Autos & Motor Vehicles",
            "subcategory":"Fuel & Gas Station",
            "type":"Retail Goods"
        }
    ],
    "sg:phone":"+1 509 783 7518",
    "sg:postcode":"99336",
    "sg:province":"WA",
    "sg:tags":[
        "oil"
    ],
    "wof:name":"Kennewick Avenue Chevron",
    "wof:placetype":"venue"
},
  "geometry": {"coordinates":[-119.15774999999999,46.209465],"type":"Point"}
}