{
  "type": "Feature",
  "properties": {
    "addr:full":"1120 39th Ave E Seattle WA 98112",
    "addr:housenumber":"1120",
    "addr:postcode":"98112",
    "addr:street":"39Th Ave E",
    "iso:country":"US",
    "sg:address":"1120 39th Ave E",
    "sg:city":"Seattle",
    "sg:classifiers":[
        {
            "category":"Real Estate",
            "subcategory":"Real Estate Services",
            "type":"Services"
        },
        {
            "category":"Real Estate",
            "subcategory":"Real Estate Agent",
            "type":"Services"
        }
    ],
    "sg:phone":"+1 206 325 6304",
    "sg:postcode":"98112",
    "sg:province":"WA",
    "sg:tags":[
        "buyer",
        "broker"
    ],
    "wof:name":"Rooks, Janet Real Estate",
    "wof:placetype":"venue"
},
  "geometry": {"coordinates":[-122.28275600000001,47.628804],"type":"Point"}
}