{
  "type": "Feature",
  "properties": {
    "addr:full":"4717 80th St E Tacoma WA 98443",
    "addr:housenumber":"4717",
    "addr:postcode":"98443",
    "addr:street":"80Th St",
    "iso:country":"US",
    "sg:address":"4717 80th St E",
    "sg:city":"Tacoma",
    "sg:classifiers":[
        {
            "category":"Wholesale",
            "subcategory":"Stationery",
            "type":"Manufacturing & Wholesale Goods"
        }
    ],
    "sg:phone":"+1 253 531 4711",
    "sg:postcode":"98443",
    "sg:province":"WA",
    "sg:tags":[
        "paper",
        "stationery-wholesale",
        "manufacturer",
        "supply"
    ],
    "wof:name":"Heaven Sent Distributing",
    "wof:placetype":"venue"
},
  "geometry": {"coordinates":[-122.36644800000001,47.184479],"type":"Point"}
}