{
  "type": "Feature",
  "properties": {
    "iso:country":"US",
    "sg:address":"32429 NE 24th St",
    "sg:city":"Carnation",
    "sg:classifiers":[
        {
            "category":"Building & Trades",
            "subcategory":"Construction",
            "type":"Services"
        }
    ],
    "sg:phone":"+1 425 333 4125",
    "sg:postcode":"98014",
    "sg:province":"WA",
    "sg:tags":[
        "carpentry",
        "landscape",
        "contractor"
    ],
    "wof:name":"Gardens of Eden",
    "wof:placetype":"venue"
},
  "geometry": {"coordinates":[-121.90178899999999,47.629753],"type":"Point"}
}