{
  "type": "Feature",
  "properties": {
    "addr:full":"645 4th St Ste 204 Bremerton WA 98337",
    "addr:housenumber":"645",
    "addr:postcode":"98337",
    "addr:street":"4Th St Ste 204",
    "iso:country":"US",
    "sg:address":"645 4th St Ste 204",
    "sg:city":"Bremerton",
    "sg:classifiers":[
        {
            "category":"Building & Trades",
            "subcategory":"Equipment Rental",
            "type":"Services"
        }
    ],
    "sg:phone":"+1 360 479 1683",
    "sg:postcode":"98337",
    "sg:province":"WA",
    "sg:tags":[
        "yard",
        "leasing",
        "store"
    ],
    "wof:name":"Puget Rental Owners Association",
    "wof:placetype":"venue"
},
  "geometry": {"coordinates":[-122.629349,47.565769],"type":"Point"}
}