{
  "type": "Feature",
  "properties": {
    "addr:full":"336 NW 40th St Seattle WA 98107",
    "addr:housenumber":"336",
    "addr:postcode":"98107",
    "addr:street":"Nw 40Th St",
    "iso:country":"US",
    "sg:address":"336 NW 40th St",
    "sg:city":"Seattle",
    "sg:classifiers":[
        {
            "category":"Coffee & Tea",
            "type":"Food & Drink"
        },
        {
            "category":"Food & Beverages",
            "subcategory":"Bakery",
            "type":"Retail Goods"
        }
    ],
    "sg:phone":"+1 206 789 5900",
    "sg:postcode":"98107",
    "sg:province":"WA",
    "sg:tags":[
        "sandwich"
    ],
    "wof:name":"Short Stop Coffee",
    "wof:placetype":"venue"
},
  "geometry": {"coordinates":[-122.36288999999999,47.65608],"type":"Point"}
}