{
  "type": "Feature",
  "properties": {
    "addr:full":"2200 E 1st St Vancouver WA 98661",
    "addr:housenumber":"2200",
    "addr:postcode":"98661",
    "addr:street":"E 1St St",
    "iso:country":"US",
    "sg:address":"2200 E 1st St",
    "sg:city":"Vancouver",
    "sg:classifiers":[
        {
            "category":"Personal",
            "type":"Services"
        }
    ],
    "sg:phone":"+1 360 696 0441",
    "sg:postcode":"98661",
    "sg:province":"WA",
    "sg:tags":[
        "towing"
    ],
    "wof:name":"Vancouver Towing",
    "wof:placetype":"venue"
},
  "geometry": {"coordinates":[-122.649002,45.6208],"type":"Point"}
}