{
  "type": "Feature",
  "properties": {
    "addr:full":"35100 Enchanted Pkwy S Federal Way WA 98003",
    "addr:postcode":"35100;98003",
    "addr:street":"Enchanted Pkwy S Federal Way",
    "iso:country":"US",
    "sg:address":"35100 Enchanted Pkwy S",
    "sg:city":"Federal Way",
    "sg:classifiers":[
        {
            "category":"Health Services",
            "subcategory":"Optometrist",
            "type":"Services"
        }
    ],
    "sg:phone":"+1 253 661 6950",
    "sg:postcode":"98003",
    "sg:province":"WA",
    "wof:name":"Rhee Walter Costco Opt Dept",
    "wof:placetype":"venue"
},
  "geometry": {"coordinates":[-122.31346600000001,47.287611],"type":"Point"}
}