{
  "type": "Feature",
  "properties": {
    "iso:country":"US",
    "sg:address":"3301 X St",
    "sg:city":"Vancouver",
    "sg:classifiers":[
        {
            "category":"Professional",
            "type":"Services"
        }
    ],
    "sg:phone":"+1 360 695 5185",
    "sg:postcode":"98663",
    "sg:province":"WA",
    "wof:name":"Oogles N Googles",
    "wof:placetype":"venue"
},
  "geometry": {"coordinates":[-122.646058,45.646439],"type":"Point"}
}