{
  "type": "Feature",
  "properties": {
    "addr:full":"5213 Pacific Hwy E Tacoma WA 98424",
    "addr:housenumber":"5213",
    "addr:postcode":"98424",
    "addr:street":"Pacific Hwy E",
    "iso:country":"US",
    "sg:address":"5213 Pacific Hwy E",
    "sg:city":"Tacoma",
    "sg:classifiers":[
        {
            "category":"Organizations",
            "subcategory":"Non-profit Organization",
            "type":"Services"
        }
    ],
    "sg:phone":"+1 253 926 1208",
    "sg:postcode":"98424",
    "sg:province":"WA",
    "sg:tags":[
        "social"
    ],
    "wof:name":"Ladies Aux V F W Dept Wshingto",
    "wof:placetype":"venue"
},
  "geometry": {"coordinates":[-122.35735200000001,47.243135],"type":"Point"}
}