{
  "type": "Feature",
  "properties": {
    "addr:full":"30 E Hemlock St Othello WA 99344",
    "addr:housenumber":"30",
    "addr:postcode":"99344",
    "addr:street":"E Hemlock St",
    "iso:country":"US",
    "sg:address":"30 E Hemlock St",
    "sg:city":"Othello",
    "sg:classifiers":[
        {
            "category":"Building & Trades",
            "subcategory":"Electrical",
            "type":"Services"
        }
    ],
    "sg:phone":"+1 509 488 2822",
    "sg:postcode":"99344",
    "sg:province":"WA",
    "sg:tags":[
        "electric",
        "industrial",
        "contractors-commercial",
        "contractor"
    ],
    "wof:name":"Farmers Electric Ii",
    "wof:placetype":"venue"
},
  "geometry": {"coordinates":[-119.175149,46.825111],"type":"Point"}
}