{
  "type": "Feature",
  "properties": {
    "addr:full":"4761 Fort Rd Toppenish WA 98948",
    "addr:housenumber":"4761",
    "addr:postcode":"98948",
    "addr:street":"Fort Rd",
    "iso:country":"US",
    "sg:address":"4761 Fort Rd",
    "sg:city":"Toppenish",
    "sg:classifiers":[
        {
            "category":"Farming",
            "subcategory":"Farm",
            "type":"Manufacturing & Wholesale Goods"
        }
    ],
    "sg:phone":"+1 509 452 3494",
    "sg:postcode":"98948",
    "sg:province":"WA",
    "wof:name":"Roy Farms Inc",
    "wof:placetype":"venue"
},
  "geometry": {"coordinates":[-120.432845,46.375653],"type":"Point"}
}