{
  "type": "Feature",
  "properties": {
    "addr:full":"11601 10th Ave W Everett WA 98204",
    "addr:housenumber":"11601",
    "addr:postcode":"98204",
    "addr:street":"10Th Ave W",
    "iso:country":"US",
    "sg:address":"11601 10th Ave W",
    "sg:city":"Everett",
    "sg:classifiers":[
        {
            "category":"Retail",
            "subcategory":"Auto Rental",
            "type":"Services"
        }
    ],
    "sg:phone":"+1 425 438 2847",
    "sg:postcode":"98204",
    "sg:province":"WA",
    "sg:tags":[
        "passenger",
        "car"
    ],
    "wof:name":"Fast Avis",
    "wof:placetype":"venue"
},
  "geometry": {"coordinates":[-122.24660299999999,47.89201],"type":"Point"}
}