{
  "type": "Feature",
  "properties": {
    "addr:full":"7321 Martin Way E Olympia WA 98516",
    "addr:housenumber":"7321",
    "addr:postcode":"98516",
    "addr:street":"Martin Way E",
    "iso:country":"US",
    "sg:address":"7321 Martin Way E",
    "sg:city":"Olympia",
    "sg:classifiers":[
        {
            "category":"Restaurant",
            "type":"Food & Drink"
        }
    ],
    "sg:phone":"+1 360 923 2323",
    "sg:postcode":"98516",
    "sg:province":"WA",
    "sg:tags":[
        "eating"
    ],
    "wof:name":"Emperor's Palace",
    "wof:placetype":"venue"
},
  "geometry": {"coordinates":[-122.78026800000001,47.053543],"type":"Point"}
}