{
  "type": "Feature",
  "properties": {
    "addr:full":"15183 Baker Heights Rd Mount Vernon WA 98273",
    "addr:housenumber":"15183",
    "addr:postcode":"98273",
    "addr:street":"Baker Heights Rd",
    "iso:country":"US",
    "sg:address":"15183 Baker Heights Rd",
    "sg:city":"Mount Vernon",
    "sg:classifiers":[
        {
            "category":"Shopping",
            "subcategory":"Department Store",
            "type":"Retail Goods"
        }
    ],
    "sg:phone":"+1 360 428 2036",
    "sg:postcode":"98273",
    "sg:province":"WA",
    "wof:name":"Timeless Treasures",
    "wof:placetype":"venue"
},
  "geometry": {"coordinates":[-122.247531,48.425516],"type":"Point"}
}