{
  "type": "Feature",
  "properties": {
    "addr:full":"525 E Wild Rose Rd Colbert WA 99005",
    "addr:housenumber":"525",
    "addr:postcode":"99005",
    "addr:street":"E Wild Rose Rd Colbert",
    "iso:country":"US",
    "sg:address":"525 E Wild Rose Rd",
    "sg:city":"Colbert",
    "sg:classifiers":[
        {
            "category":"Professional",
            "type":"Services"
        }
    ],
    "sg:phone":"+1 509 276 7679",
    "sg:postcode":"99005",
    "sg:province":"WA",
    "wof:name":"D&L Services",
    "wof:placetype":"venue"
},
  "geometry": {"coordinates":[-117.40963499999999,47.874926],"type":"Point"}
}