{
  "type": "Feature",
  "properties": {
    "addr:full":"45 E 3rd Ave Toppenish WA 98948",
    "addr:housenumber":"45",
    "addr:postcode":"98948",
    "addr:street":"E 3Rd Ave",
    "iso:country":"US",
    "sg:address":"45 E 3rd Ave",
    "sg:city":"Toppenish",
    "sg:classifiers":[
        {
            "category":"Manufacturing",
            "subcategory":"Metals",
            "type":"Manufacturing & Wholesale Goods"
        }
    ],
    "sg:phone":"+1 509 865 4125",
    "sg:postcode":"98948",
    "sg:province":"WA",
    "sg:tags":[
        "can"
    ],
    "wof:name":"Silgan Containers Corp",
    "wof:placetype":"venue"
},
  "geometry": {"coordinates":[-120.30759500000001,46.372634],"type":"Point"}
}