{
  "type": "Feature",
  "properties": {
    "iso:country":"US",
    "sg:address":"15411 Orweiler Ln NW",
    "sg:city":"Poulsbo",
    "sg:classifiers":[
        {
            "category":"Wholesale",
            "subcategory":"Machinery & Supplies",
            "type":"Manufacturing & Wholesale Goods"
        }
    ],
    "sg:phone":"+1 360 697 6882",
    "sg:postcode":"98370",
    "sg:province":"WA",
    "sg:tags":[
        "crane",
        "derrick"
    ],
    "wof:name":"Crane Equipment Northwest",
    "wof:placetype":"venue"
},
  "geometry": {"coordinates":[-122.686879,47.708035],"type":"Point"}
}