{
  "type": "Feature",
  "properties": {
    "addr:full":"430 116th Avenue Northeast Bellevue WA 98004",
    "addr:housenumber":"430",
    "addr:postcode":"98004",
    "addr:street":"116Th Avenue Northeast",
    "iso:country":"US",
    "sg:address":"430 116th Avenue Northeast",
    "sg:city":"Bellevue",
    "sg:classifiers":[
        {
            "category":"Autos & Motor Vehicles",
            "subcategory":"Automobile Sales",
            "type":"Retail Goods"
        }
    ],
    "sg:phone":"+1 866 509 1340",
    "sg:postcode":"98004",
    "sg:province":"WA",
    "sg:tags":[
        "car"
    ],
    "sg:website":"www.cadillacinbellevue.com",
    "wof:name":"Chevrolet Cadillac Hummer of Bellevue",
    "wof:placetype":"venue"
},
  "geometry": {"coordinates":[-122.185569,47.613255],"type":"Point"}
}