{
  "type": "Feature",
  "properties": {
    "addr:full":"818 Industry Dr Seattle WA 98188",
    "addr:housenumber":"818",
    "addr:postcode":"98188",
    "addr:street":"Industry Dr",
    "iso:country":"US",
    "sg:address":"818 Industry Dr",
    "sg:city":"Seattle",
    "sg:classifiers":[
        {
            "category":"Building & Trades",
            "subcategory":"Construction",
            "type":"Services"
        }
    ],
    "sg:phone":"+1 206 394 9600",
    "sg:postcode":"98188",
    "sg:province":"WA",
    "sg:tags":[
        "contractor"
    ],
    "wof:name":"Builders Warehouse",
    "wof:placetype":"venue"
},
  "geometry": {"coordinates":[-122.24838800000001,47.451692],"type":"Point"}
}