{
  "type": "Feature",
  "properties": {
    "addr:full":"190 NW Beaver Ridge Poulsbo WA 98370",
    "addr:housenumber":"190",
    "addr:postcode":"98370",
    "addr:street":"Nw Beaver Ridge",
    "iso:country":"US",
    "sg:address":"190 NW Beaver Ridge",
    "sg:city":"Poulsbo",
    "sg:classifiers":[
        {
            "category":"Building & Trades",
            "subcategory":"Equipment Rental",
            "type":"Services"
        }
    ],
    "sg:phone":"+1 360 779 6723",
    "sg:postcode":"98370",
    "sg:province":"WA",
    "sg:tags":[
        "crane"
    ],
    "wof:name":"A Millican Crane Svc Inc",
    "wof:placetype":"venue"
},
  "geometry": {"coordinates":[-122.64698,47.78392],"type":"Point"}
}