{
  "type": "Feature",
  "properties": {
    "addr:full":"16727 Alderwood Mall Pkwy Lynnwood WA 98037",
    "addr:housenumber":"16727",
    "addr:postcode":"98037",
    "addr:street":"Alderwood Mall Pkwy",
    "iso:country":"US",
    "sg:address":"16727 Alderwood Mall Pkwy",
    "sg:city":"Lynnwood",
    "sg:classifiers":[
        {
            "category":"Social Services",
            "subcategory":"Child Care",
            "type":"Services"
        }
    ],
    "sg:phone":"+1 425 743 0907",
    "sg:postcode":"98037",
    "sg:province":"WA",
    "sg:tags":[
        "day"
    ],
    "wof:name":"Early Learning & Dev Ctr",
    "wof:placetype":"venue"
},
  "geometry": {"coordinates":[-122.271051,47.846787],"type":"Point"}
}