{
  "type": "Feature",
  "properties": {
    "addr:full":"115 Nix Ln Centralia WA 98531",
    "addr:housenumber":"115",
    "addr:postcode":"98531",
    "addr:street":"Nix Ln",
    "iso:country":"US",
    "sg:address":"115 Nix Ln",
    "sg:city":"Centralia",
    "sg:classifiers":[
        {
            "category":"Real Estate",
            "subcategory":"Developer",
            "type":"Services"
        }
    ],
    "sg:phone":"+1 360 807 0907",
    "sg:postcode":"98531",
    "sg:province":"WA",
    "sg:tags":[
        "mobile",
        "home"
    ],
    "wof:name":"Cherry Blossom Estates",
    "wof:placetype":"venue"
},
  "geometry": {"coordinates":[-122.930604,46.697056],"type":"Point"}
}