{
  "type": "Feature",
  "properties": {
    "addr:full":"1150 NW Bryant St Pullman WA 99163",
    "addr:housenumber":"1150",
    "addr:postcode":"99163",
    "addr:street":"Nw Bryant St",
    "iso:country":"US",
    "sg:address":"1150 NW Bryant St",
    "sg:city":"Pullman",
    "sg:classifiers":[
        {
            "category":"Education",
            "subcategory":"School",
            "type":"Public Place"
        }
    ],
    "sg:phone":"+1 509 332 2617",
    "sg:postcode":"99163",
    "sg:province":"WA",
    "wof:name":"Jefferson Elementary School",
    "wof:placetype":"venue"
},
  "geometry": {"coordinates":[-117.18134999999999,46.739029],"type":"Point"}
}