{
  "type": "Feature",
  "properties": {
    "addr:full":"1089 Lake Washington Blvd N Renton WA 98056",
    "addr:housenumber":"1089",
    "addr:postcode":"98056",
    "addr:street":"Lake Washington Blvd N",
    "iso:country":"US",
    "sg:address":"1089 Lake Washington Blvd N",
    "sg:city":"Renton",
    "sg:classifiers":[
        {
            "category":"Health Services",
            "subcategory":"Dentist",
            "type":"Services"
        }
    ],
    "sg:phone":"+1 206 579 5163",
    "sg:postcode":"98056",
    "sg:province":"WA",
    "wof:name":"Andrea M Pearson Dds P",
    "wof:placetype":"venue"
},
  "geometry": {"coordinates":[-122.201114,47.501306],"type":"Point"}
}