{
  "type": "Feature",
  "properties": {
    "addr:full":"10901 9th Dr SE Everett WA 98208",
    "addr:housenumber":"10901",
    "addr:postcode":"98208",
    "addr:street":"9Th Dr Se",
    "iso:country":"US",
    "sg:address":"10901 9th Dr SE",
    "sg:city":"Everett",
    "sg:classifiers":[
        {
            "category":"Retail",
            "subcategory":"Laundry & Dry Cleaning",
            "type":"Services"
        }
    ],
    "sg:phone":"+1 425 239 9388",
    "sg:postcode":"98208",
    "sg:province":"WA",
    "wof:name":"Top Carpet Cleaning",
    "wof:placetype":"venue"
},
  "geometry": {"coordinates":[-122.22005799999999,47.898127],"type":"Point"}
}