{
  "type": "Feature",
  "properties": {
    "addr:full":"805 S Auburn St Kennewick WA 99336",
    "addr:housenumber":"805",
    "addr:postcode":"99336",
    "addr:street":"S Auburn St",
    "iso:country":"US",
    "sg:address":"805 S Auburn St",
    "sg:city":"Kennewick",
    "sg:classifiers":[
        {
            "category":"Organizations",
            "subcategory":"Non-profit Organization",
            "type":"Services"
        }
    ],
    "sg:phone":"+1 509 582 9001",
    "sg:postcode":"99336",
    "sg:province":"WA",
    "sg:tags":[
        "social"
    ],
    "wof:name":"American Heart Association",
    "wof:placetype":"venue"
},
  "geometry": {"coordinates":[-119.118477,46.19844],"type":"Point"}
}