{
  "type": "Feature",
  "properties": {
    "addr:full":"1500 S Canyon Rd Ellensburg WA 98926",
    "addr:housenumber":"1500",
    "addr:postcode":"98926",
    "addr:street":"S Canyon Rd",
    "iso:country":"US",
    "sg:address":"1500 S Canyon Rd",
    "sg:city":"Ellensburg",
    "sg:classifiers":[
        {
            "category":"Travel",
            "subcategory":"Hotels & Motels",
            "type":"Entertainment"
        },
        {
            "category":"Restaurant",
            "type":"Food & Drink"
        }
    ],
    "sg:phone":"+1 509 962 6888",
    "sg:postcode":"98926",
    "sg:province":"WA",
    "sg:tags":[
        "lodging"
    ],
    "sg:website":"http://www.super8.com",
    "wof:name":"Super 8 Motel",
    "wof:placetype":"venue"
},
  "geometry": {"coordinates":[-120.54356,46.977966],"type":"Point"}
}