{
  "type": "Feature",
  "properties": {
    "addr:full":"585 Rainier Ave S Renton WA 98057",
    "addr:housenumber":"585",
    "addr:postcode":"98057",
    "addr:street":"Rainier Ave S Renton",
    "iso:country":"US",
    "sg:address":"585 Rainier Ave S",
    "sg:city":"Renton",
    "sg:phone":"+1 425 430 1000",
    "sg:postcode":"98057",
    "sg:province":"WA",
    "wof:name":"Lithia Chrysler Jeep Dodge",
    "wof:placetype":"venue"
},
  "geometry": {"coordinates":[-122.214828,47.47506],"type":"Point"}
}