{
  "type": "Feature",
  "properties": {
    "addr:full":"101 Yesler Way Seattle WA 98104",
    "addr:housenumber":"101",
    "addr:postcode":"98104",
    "addr:street":"Yesler Way",
    "iso:country":"US",
    "sg:address":"101 Yesler Way",
    "sg:city":"Seattle",
    "sg:classifiers":[
        {
            "category":"Social Services",
            "type":"Services"
        }
    ],
    "sg:phone":"+1 206 340 1124",
    "sg:postcode":"98104",
    "sg:province":"WA",
    "wof:name":"Care Planning Associates",
    "wof:placetype":"venue"
},
  "geometry": {"coordinates":[-122.333901,47.60172],"type":"Point"}
}