{
  "type": "Feature",
  "properties": {
    "addr:full":"3033 Alki Ave SW Seattle WA 98116",
    "addr:housenumber":"3033",
    "addr:postcode":"98116",
    "addr:street":"Alki Ave Sw",
    "iso:country":"US",
    "sg:address":"3033 Alki Ave SW",
    "sg:city":"Seattle",
    "sg:classifiers":[
        {
            "category":"Building & Trades",
            "subcategory":"Construction",
            "type":"Services"
        }
    ],
    "sg:phone":"+1 206 484 7143",
    "sg:postcode":"98116",
    "sg:province":"WA",
    "sg:tags":[
        "house"
    ],
    "wof:name":"S&C Development LLC",
    "wof:placetype":"venue"
},
  "geometry": {"coordinates":[-122.415734,47.57777],"type":"Point"}
}