{
  "type": "Feature",
  "properties": {
    "addr:full":"202 NW 42nd St Seattle WA 98107",
    "addr:housenumber":"202",
    "addr:postcode":"98107",
    "addr:street":"Nw 42Nd St",
    "iso:country":"US",
    "sg:address":"202 NW 42nd St",
    "sg:city":"Seattle",
    "sg:classifiers":[
        {
            "category":"Professional",
            "subcategory":"Computer Services",
            "type":"Services"
        }
    ],
    "sg:phone":"+1 206 910 4903",
    "sg:postcode":"98107",
    "sg:province":"WA",
    "sg:tags":[
        "prepackaged",
        "software"
    ],
    "wof:name":"Espresso Software Dev LLC",
    "wof:placetype":"venue"
},
  "geometry": {"coordinates":[-122.359566,47.657843],"type":"Point"}
}