{
  "type": "Feature",
  "properties": {
    "addr:full":"901 Fairview Ave N Ste A120 Seattle WA 98109",
    "addr:housenumber":"901",
    "addr:postcode":"98109",
    "addr:street":"Fairview Ave N Ste A120",
    "iso:country":"US",
    "sg:address":"901 Fairview Ave N Ste A120",
    "sg:city":"Seattle",
    "sg:classifiers":[
        {
            "category":"Personal",
            "subcategory":"Beauty Salon",
            "type":"Services"
        }
    ],
    "sg:phone":"+1 206 838 8632",
    "sg:postcode":"98109",
    "sg:province":"WA",
    "sg:tags":[
        "hair"
    ],
    "sg:website":"www.salonvoda.com/",
    "wof:name":"Salon Voda",
    "wof:placetype":"venue"
},
  "geometry": {"coordinates":[-122.333546,47.627797],"type":"Point"}
}