{
  "type": "Feature",
  "properties": {
    "addr:full":"1400 E Kincaid St Mount Vernon WA 98274",
    "addr:housenumber":"1400",
    "addr:postcode":"98274",
    "addr:street":"E Kincaid St",
    "iso:country":"US",
    "sg:address":"1400 E Kincaid St",
    "sg:city":"Mount Vernon",
    "sg:classifiers":[
        {
            "category":"Health Services",
            "subcategory":"Doctor",
            "type":"Services"
        },
        {
            "category":"Personal",
            "subcategory":"Adult",
            "type":"Services"
        }
    ],
    "sg:phone":"+1 360 428 2575",
    "sg:postcode":"98274",
    "sg:province":"WA",
    "sg:tags":[
        "obstetrician",
        "midwife",
        "gynecologist"
    ],
    "wof:name":"Hinderstein William N MD",
    "wof:placetype":"venue"
},
  "geometry": {"coordinates":[-122.32399700000001,48.417301],"type":"Point"}
}