{
  "type": "Feature",
  "properties": {
    "addr:full":"3124 Forest Ln Langley WA 98260",
    "addr:housenumber":"3124",
    "addr:postcode":"98260",
    "addr:street":"Forest Ln",
    "iso:country":"US",
    "sg:address":"3124 Forest Ln",
    "sg:city":"Langley",
    "sg:classifiers":[
        {
            "category":"Professional",
            "subcategory":"Management & Consulting",
            "type":"Services"
        }
    ],
    "sg:phone":"+1 360 321 3010",
    "sg:postcode":"98260",
    "sg:province":"WA",
    "sg:tags":[
        "fuel"
    ],
    "wof:name":"Falken Financial Svc",
    "wof:placetype":"venue"
},
  "geometry": {"coordinates":[-122.447846,48.012553],"type":"Point"}
}