{
  "type": "Feature",
  "properties": {
    "addr:full":"1800 SE 202nd Ave Camas WA 98607",
    "addr:housenumber":"1800",
    "addr:postcode":"98607",
    "addr:street":"Se 202Nd Ave",
    "iso:country":"US",
    "sg:address":"1800 SE 202nd Ave",
    "sg:city":"Camas",
    "sg:classifiers":[
        {
            "category":"Professional",
            "subcategory":"Business Services",
            "type":"Services"
        }
    ],
    "sg:phone":"+1 360 834 3043",
    "sg:postcode":"98607",
    "sg:province":"WA",
    "wof:name":"Marlenes Floral Designs",
    "wof:placetype":"venue"
},
  "geometry": {"coordinates":[-122.465626,45.606987],"type":"Point"}
}