{
  "type": "Feature",
  "properties": {
    "addr:full":"3405 W Nob Hill Blvd Yakima WA 98902",
    "addr:housenumber":"3405",
    "addr:postcode":"98902",
    "addr:street":"W Nob Hill Blvd",
    "iso:country":"US",
    "sg:address":"3405 W Nob Hill Blvd",
    "sg:city":"Yakima",
    "sg:classifiers":[
        {
            "category":"Retail",
            "subcategory":"Laundry & Dry Cleaning",
            "type":"Services"
        }
    ],
    "sg:phone":"+1 509 248 7414",
    "sg:postcode":"98902",
    "sg:province":"WA",
    "sg:tags":[
        "cleaners",
        "rug",
        "carpet"
    ],
    "wof:name":"Chem Dry Of Yakima",
    "wof:placetype":"venue"
},
  "geometry": {"coordinates":[-120.556194,46.585521],"type":"Point"}
}