{
  "type": "Feature",
  "properties": {
    "addr:full":"207 Clark Ave Lacrosse WA 99143",
    "addr:housenumber":"207",
    "addr:postcode":"99143",
    "addr:street":"Clark Ave",
    "iso:country":"US",
    "sg:address":"207 Clark Ave",
    "sg:city":"Lacrosse",
    "sg:classifiers":[
        {
            "category":"Personal",
            "subcategory":"Beauty Salon",
            "type":"Services"
        }
    ],
    "sg:phone":"+1 509 549 3890",
    "sg:postcode":"99143",
    "sg:province":"WA",
    "wof:name":"Jeannine's",
    "wof:placetype":"venue"
},
  "geometry": {"coordinates":[-117.879594,46.818448],"type":"Point"}
}