{
  "type": "Feature",
  "properties": {
    "addr:full":"420 W Main St Walla Walla WA 99362",
    "addr:housenumber":"420",
    "addr:postcode":"99362",
    "addr:street":"W Main St",
    "iso:country":"US",
    "sg:address":"420 W Main St",
    "sg:city":"Walla Walla",
    "sg:classifiers":[
        {
            "category":"Wholesale",
            "subcategory":"Machinery & Supplies",
            "type":"Manufacturing & Wholesale Goods"
        }
    ],
    "sg:phone":"+1 509 522 2012",
    "sg:postcode":"99362",
    "sg:province":"WA",
    "sg:tags":[
        "equipment",
        "welding"
    ],
    "wof:name":"Norco Inc",
    "wof:placetype":"venue"
},
  "geometry": {"coordinates":[-118.344701,46.064479],"type":"Point"}
}