{
  "type": "Feature",
  "properties": {
    "iso:country":"US",
    "sg:address":"21019 77th Ave S",
    "sg:city":"Kent",
    "sg:classifiers":[
        {
            "category":"Wholesale",
            "subcategory":"Chemicals & Plastics",
            "type":"Manufacturing & Wholesale Goods"
        }
    ],
    "sg:phone":"+1 206 872 2525",
    "sg:postcode":"98032",
    "sg:province":"WA",
    "sg:tags":[
        "building",
        "maintenance"
    ],
    "wof:name":"Zep Manufacturing Company",
    "wof:placetype":"venue"
},
  "geometry": {"coordinates":[-122.237352,47.414028],"type":"Point"}
}