{
  "type": "Feature",
  "properties": {
    "addr:full":"2576 Douglas Rd Ferndale WA 98248",
    "addr:housenumber":"2576",
    "addr:postcode":"98248",
    "addr:street":"Douglas Rd",
    "iso:country":"US",
    "sg:address":"2576 Douglas Rd",
    "sg:city":"Ferndale",
    "sg:classifiers":[
        {
            "category":"Shopping",
            "subcategory":"Pharmacy",
            "type":"Retail Goods"
        }
    ],
    "sg:phone":"+1 360 384 0155",
    "sg:postcode":"98248",
    "sg:province":"WA",
    "wof:name":"Pharmacy Consultant Service",
    "wof:placetype":"venue"
},
  "geometry": {"coordinates":[-122.623316,48.841164],"type":"Point"}
}