{
  "type": "Feature",
  "properties": {
    "addr:full":"402 15th Ave SE Ste 101 Puyallup WA 98372",
    "addr:housenumber":"402",
    "addr:postcode":"98372",
    "addr:street":"15Th Ave Se Ste 101",
    "iso:country":"US",
    "sg:address":"402 15th Ave SE Ste 101",
    "sg:city":"Puyallup",
    "sg:classifiers":[
        {
            "category":"Health Services",
            "subcategory":"Hospital",
            "type":"Services"
        }
    ],
    "sg:phone":"+1 253 697 5090",
    "sg:postcode":"98372",
    "sg:province":"WA",
    "wof:name":"Good Samaritan Foundation",
    "wof:placetype":"venue"
},
  "geometry": {"coordinates":[-122.289404,47.177391],"type":"Point"}
}