{
  "type": "Feature",
  "properties": {
    "iso:country":"US",
    "sg:address":"420 7th St",
    "sg:city":"Hoquiam",
    "sg:classifiers":[
        {
            "category":"Education",
            "subcategory":"Library",
            "type":"Public Place"
        }
    ],
    "sg:phone":"+1 360 532 1710",
    "sg:postcode":"98550",
    "sg:province":"WA",
    "wof:name":"Hoquiam Timberland Library",
    "wof:placetype":"venue"
},
  "geometry": {"coordinates":[-123.886208,46.977367],"type":"Point"}
}