{
  "type": "Feature",
  "properties": {
    "addr:full":"8518 122nd Ave NE Kirkland WA 98033",
    "addr:housenumber":"8518",
    "addr:postcode":"98033",
    "addr:street":"122Nd Ave Ne",
    "iso:country":"US",
    "sg:address":"8518 122nd Ave NE",
    "sg:city":"Kirkland",
    "sg:classifiers":[
        {
            "category":"Personal",
            "subcategory":"Beauty Salon",
            "type":"Services"
        }
    ],
    "sg:phone":"+1 425 822 8585",
    "sg:postcode":"98033",
    "sg:province":"WA",
    "sg:tags":[
        "spa"
    ],
    "wof:name":"85 Street Salon",
    "wof:placetype":"venue"
},
  "geometry": {"coordinates":[-122.17744999999999,47.679771],"type":"Point"}
}