{
  "type": "Feature",
  "properties": {
    "addr:full":"170 B and O Rd Okanogan WA 98840",
    "addr:housenumber":"170",
    "addr:postcode":"98840",
    "addr:street":"B And O Rd",
    "iso:country":"US",
    "sg:address":"170 B and O Rd",
    "sg:city":"Okanogan",
    "sg:classifiers":[
        {
            "category":"Farming",
            "subcategory":"Orchard",
            "type":"Manufacturing & Wholesale Goods"
        }
    ],
    "sg:phone":"+1 509 422 6144",
    "sg:postcode":"98840",
    "sg:province":"WA",
    "sg:tags":[
        "fruit",
        "tree"
    ],
    "wof:name":"Mike Hinger Orchard",
    "wof:placetype":"venue"
},
  "geometry": {"coordinates":[-119.701072,48.29976],"type":"Point"}
}