{
  "type": "Feature",
  "properties": {
    "iso:country":"US",
    "sg:address":"408 Metcalf St",
    "sg:city":"Sedro Woolley",
    "sg:classifiers":[
        {
            "category":"Professional",
            "type":"Services"
        }
    ],
    "sg:phone":"+1 360 855 1417",
    "sg:postcode":"98284",
    "sg:province":"WA",
    "sg:tags":[
        "establishment"
    ],
    "wof:name":"Klippers",
    "wof:placetype":"venue"
},
  "geometry": {"coordinates":[-122.238642,48.508418],"type":"Point"}
}