{
  "type": "Feature",
  "properties": {
    "addr:full":"11225 1st Avenue S Seattle WA 98168",
    "addr:housenumber":"11225",
    "addr:postcode":"98168",
    "addr:street":"1St Avenue S",
    "iso:country":"US",
    "sg:address":"11225 1st Avenue S",
    "sg:city":"Seattle",
    "sg:classifiers":[
        {
            "category":"Food & Beverages",
            "subcategory":"Meat & Fish",
            "type":"Retail Goods"
        },
        {
            "category":"Food & Beverages",
            "subcategory":"Groceries & Convenience Stores",
            "type":"Retail Goods"
        }
    ],
    "sg:phone":"+1 206 248 1916",
    "sg:postcode":"98168",
    "sg:province":"WA",
    "sg:tags":[
        "shop"
    ],
    "sg:website":"www.bernieandboys.com",
    "wof:name":"Bernie and Boys",
    "wof:placetype":"venue"
},
  "geometry": {"coordinates":[-122.333513,47.501963],"type":"Point"}
}