{
  "type": "Feature",
  "properties": {
    "addr:full":"12604 NE 172nd Ave Brush Prairie WA 98606",
    "addr:housenumber":"12604",
    "addr:postcode":"98606",
    "addr:street":"Ne 172Nd Ave",
    "iso:country":"US",
    "sg:address":"12604 NE 172nd Ave",
    "sg:city":"Brush Prairie",
    "sg:classifiers":[
        {
            "category":"Building & Trades",
            "subcategory":"Construction",
            "type":"Services"
        }
    ],
    "sg:phone":"+1 360 882 0929",
    "sg:postcode":"98606",
    "sg:province":"WA",
    "sg:tags":[
        "demolition",
        "contractor"
    ],
    "wof:name":"Able Contractors Inc",
    "wof:placetype":"venue"
},
  "geometry": {"coordinates":[-122.495897,45.710545],"type":"Point"}
}