{
  "type": "Feature",
  "properties": {
    "addr:full":"315 Howe St Seattle WA 98109",
    "addr:housenumber":"315",
    "addr:postcode":"98109",
    "addr:street":"Howe St",
    "iso:country":"US",
    "sg:address":"315 Howe St",
    "sg:city":"Seattle",
    "sg:classifiers":[
        {
            "category":"Building & Trades",
            "subcategory":"Landscaping Services",
            "type":"Services"
        }
    ],
    "sg:phone":"+1 206 443 8856",
    "sg:postcode":"98109",
    "sg:province":"WA",
    "sg:website":"www.virginiahanddesign.com/",
    "wof:name":"Virginia Hand Design",
    "wof:placetype":"venue"
},
  "geometry": {"coordinates":[-122.35128,47.63549],"type":"Point"}
}