{
  "type": "Feature",
  "properties": {
    "addr:full":"7605 Henderson Blvd SE Olympia WA 98501",
    "addr:housenumber":"7605",
    "addr:postcode":"98501",
    "addr:street":"Henderson Blvd Se",
    "iso:country":"US",
    "sg:address":"7605 Henderson Blvd SE",
    "sg:city":"Olympia",
    "sg:classifiers":[
        {
            "category":"Retail",
            "subcategory":"Car Wash",
            "type":"Services"
        }
    ],
    "sg:phone":"+1 360 352 7707",
    "sg:postcode":"98501",
    "sg:province":"WA",
    "sg:tags":[
        "shop",
        "c",
        "auto",
        "detail",
        "wax",
        "interior"
    ],
    "wof:name":"Tumwater Auto Detailing",
    "wof:placetype":"venue"
},
  "geometry": {"coordinates":[-122.89141100000001,46.978053],"type":"Point"}
}