{
  "type": "Feature",
  "properties": {
    "addr:full":"1616 S Atlantic St Seattle WA 98144",
    "addr:housenumber":"1616",
    "addr:postcode":"98144",
    "addr:street":"S Atlantic St",
    "iso:country":"US",
    "sg:address":"1616 S Atlantic St",
    "sg:city":"Seattle",
    "sg:classifiers":[
        {
            "category":"Manufacturing",
            "subcategory":"Glass & Minerals",
            "type":"Manufacturing & Wholesale Goods"
        }
    ],
    "sg:phone":"+1 206 860 5157",
    "sg:postcode":"98144",
    "sg:province":"WA",
    "sg:tags":[
        "mfg"
    ],
    "wof:name":"Roco Glass Studio",
    "wof:placetype":"venue"
},
  "geometry": {"coordinates":[-122.31070099999999,47.590056],"type":"Point"}
}