{
  "type": "Feature",
  "properties": {
    "iso:country":"US",
    "sg:address":"2916 NE 55th St",
    "sg:city":"Seattle",
    "sg:classifiers":[
        {
            "category":"Health Services",
            "subcategory":"Health Practitioner",
            "type":"Services"
        }
    ],
    "sg:phone":"+1 206 523 2547",
    "sg:postcode":"98105",
    "sg:province":"WA",
    "wof:name":"Muscular Pain Center",
    "wof:placetype":"venue"
},
  "geometry": {"coordinates":[-122.295767,47.668592],"type":"Point"}
}