{
  "type": "Feature",
  "properties": {
    "addr:full":"2713 SE Talton Ave Vancouver WA 98683",
    "addr:housenumber":"2713",
    "addr:postcode":"98683",
    "addr:street":"Se Talton Ave",
    "iso:country":"US",
    "sg:address":"2713 SE Talton Ave",
    "sg:city":"Vancouver",
    "sg:classifiers":[
        {
            "category":"Insurance",
            "subcategory":"Insurance Agent",
            "type":"Services"
        }
    ],
    "sg:phone":"+1 360 449 3872",
    "sg:postcode":"98683",
    "sg:province":"WA",
    "wof:name":"Mega Life & Health Ins Co",
    "wof:placetype":"venue"
},
  "geometry": {"coordinates":[-122.532417,45.601118],"type":"Point"}
}