{
  "type": "Feature",
  "properties": {
    "addr:full":"4327 Fremont Ave N Seattle WA 98103",
    "addr:housenumber":"4327",
    "addr:postcode":"98103",
    "addr:street":"Fremont Ave N",
    "iso:country":"US",
    "sg:address":"4327 Fremont Ave N",
    "sg:city":"Seattle",
    "sg:classifiers":[
        {
            "category":"Retail",
            "subcategory":"Auto Repair",
            "type":"Services"
        }
    ],
    "sg:phone":"+1 206 545 3736",
    "sg:postcode":"98103",
    "sg:province":"WA",
    "sg:tags":[
        "detailing"
    ],
    "sg:website":"www.fremontautodetail.com/",
    "wof:name":"Fremont Auto Detail",
    "wof:placetype":"venue"
},
  "geometry": {"coordinates":[-122.35012,47.659822],"type":"Point"}
}