{
  "type": "Feature",
  "properties": {
    "addr:full":"14019 NE Woodinville Duvall Rd Woodinville WA 98072",
    "addr:housenumber":"14019",
    "addr:postcode":"98072",
    "addr:street":"Ne Woodinville Duvall Rd",
    "iso:country":"US",
    "sg:address":"14019 NE Woodinville Duvall Rd",
    "sg:city":"Woodinville",
    "sg:classifiers":[
        {
            "category":"Food & Beverages",
            "subcategory":"Groceries & Convenience Stores",
            "type":"Retail Goods"
        }
    ],
    "sg:phone":"+1 425 483 9353",
    "sg:postcode":"98072",
    "sg:province":"WA",
    "sg:tags":[
        "grocer"
    ],
    "sg:website":"www.albertson.com",
    "wof:name":"Albertsons",
    "wof:placetype":"venue"
},
  "geometry": {"coordinates":[-122.151349,47.754402],"type":"Point"}
}