{
  "type": "Feature",
  "properties": {
    "addr:full":"3604 This-A-Way Rd NW Bremerton WA 98312",
    "addr:housenumber":"3604",
    "addr:postcode":"98312",
    "addr:street":"This-A-Way Rd Nw",
    "iso:country":"US",
    "sg:address":"3604 This-A-Way Rd NW",
    "sg:city":"Bremerton",
    "sg:classifiers":[
        {
            "category":"Professional",
            "subcategory":"Management & Consulting",
            "type":"Services"
        }
    ],
    "sg:phone":"+1 360 830 5708",
    "sg:postcode":"98312",
    "sg:province":"WA",
    "sg:tags":[
        "business"
    ],
    "wof:name":"John Fullerton Small Busi",
    "wof:placetype":"venue"
},
  "geometry": {"coordinates":[-122.825968,47.594495],"type":"Point"}
}