{
  "type": "Feature",
  "properties": {
    "addr:full":"4911 28th Ave S Seattle WA 98108",
    "addr:housenumber":"4911",
    "addr:postcode":"98108",
    "addr:street":"28Th Ave S",
    "iso:country":"US",
    "sg:address":"4911 28th Ave S",
    "sg:city":"Seattle",
    "sg:classifiers":[
        {
            "category":"Professional",
            "subcategory":"Computer Services",
            "type":"Services"
        }
    ],
    "sg:phone":"+1 206 721 8293",
    "sg:postcode":"98108",
    "sg:province":"WA",
    "sg:tags":[
        "datum"
    ],
    "wof:name":"Aster Production",
    "wof:placetype":"venue"
},
  "geometry": {"coordinates":[-122.296914,47.557371],"type":"Point"}
}