{
  "type": "Feature",
  "properties": {
    "addr:full":"3306 Mount Baker Hwy Bellingham WA 98226",
    "addr:housenumber":"3306",
    "addr:postcode":"98226",
    "addr:street":"Mount Baker Hwy",
    "iso:country":"US",
    "sg:address":"3306 Mount Baker Hwy",
    "sg:city":"Bellingham",
    "sg:classifiers":[
        {
            "category":"Utilities",
            "subcategory":"Telephone",
            "type":"Services"
        }
    ],
    "sg:phone":"+1 360 592 2031",
    "sg:postcode":"98226",
    "sg:province":"WA",
    "sg:tags":[
        "web",
        "hosting"
    ],
    "wof:name":"Ikeloa",
    "wof:placetype":"venue"
},
  "geometry": {"coordinates":[-122.315337,48.824384],"type":"Point"}
}