{
  "type": "Feature",
  "properties": {
    "addr:full":"3246 56th Ave SW Seattle WA 98116",
    "addr:housenumber":"3246",
    "addr:postcode":"98116",
    "addr:street":"56Th Ave Sw",
    "iso:country":"US",
    "sg:address":"3246 56th Ave SW",
    "sg:city":"Seattle",
    "sg:classifiers":[
        {
            "category":"Banks & Credit Unions",
            "subcategory":"Financial Services",
            "type":"Services"
        }
    ],
    "sg:phone":"+1 206 932 7750",
    "sg:postcode":"98116",
    "sg:province":"WA",
    "sg:tags":[
        "investor"
    ],
    "wof:name":"1998 Miller Family Investments",
    "wof:placetype":"venue"
},
  "geometry": {"coordinates":[-122.403459,47.575137],"type":"Point"}
}