{
  "type": "Feature",
  "properties": {
    "addr:full":"16802 Pacific Ave S Spanaway WA 98387",
    "addr:housenumber":"16802",
    "addr:postcode":"98387",
    "addr:street":"Pacific Ave S Spanaway",
    "iso:country":"US",
    "sg:address":"16802 Pacific Ave S",
    "sg:city":"Spanaway",
    "sg:classifiers":[
        {
            "category":"Shopping",
            "subcategory":"Florist",
            "type":"Retail Goods"
        }
    ],
    "sg:phone":"+1 253 539 7822",
    "sg:postcode":"98387",
    "sg:province":"WA",
    "wof:name":"Laura's Roses & Tea Time",
    "wof:placetype":"venue"
},
  "geometry": {"coordinates":[-122.43492000000001,47.103496],"type":"Point"}
}