{
  "type": "Feature",
  "properties": {
    "addr:full":"2413 Kennewick Pl NE Renton WA 98056",
    "addr:housenumber":"2413",
    "addr:postcode":"98056",
    "addr:street":"Kennewick Pl Ne",
    "iso:country":"US",
    "sg:address":"2413 Kennewick Pl NE",
    "sg:city":"Renton",
    "sg:classifiers":[
        {
            "category":"Professional",
            "type":"Services"
        }
    ],
    "sg:phone":"+1 425 271 1844",
    "sg:postcode":"98056",
    "sg:province":"WA",
    "sg:tags":[
        "relocation"
    ],
    "wof:name":"V Dinkins",
    "wof:placetype":"venue"
},
  "geometry": {"coordinates":[-122.193765,47.514007],"type":"Point"}
}