{
  "type": "Feature",
  "properties": {
    "addr:full":"3400 Stone Way N Seattle WA 98103",
    "addr:housenumber":"3400",
    "addr:postcode":"98103",
    "addr:street":"Stone Way N",
    "iso:country":"US",
    "sg:address":"3400 Stone Way N",
    "sg:city":"Seattle",
    "sg:classifiers":[
        {
            "category":"Wholesale",
            "subcategory":"Machinery & Supplies",
            "type":"Manufacturing & Wholesale Goods"
        }
    ],
    "sg:phone":"+1 206 632 3025",
    "sg:postcode":"98103",
    "sg:province":"WA",
    "sg:tags":[
        "marine",
        "retail",
        "electronic"
    ],
    "wof:name":"Offshore Store The",
    "wof:placetype":"venue"
},
  "geometry": {"coordinates":[-122.34273399999999,47.649418],"type":"Point"}
}