{
  "type": "Feature",
  "properties": {
    "addr:full":"18008 59th Ave NE Arlington WA 98223",
    "addr:housenumber":"18008",
    "addr:postcode":"98223",
    "addr:street":"59Th Ave Ne",
    "iso:country":"US",
    "sg:address":"18008 59th Ave NE",
    "sg:city":"Arlington",
    "sg:classifiers":[
        {
            "category":"Museum",
            "type":"Entertainment"
        }
    ],
    "sg:phone":"+1 360 403 9352",
    "sg:postcode":"98223",
    "sg:province":"WA",
    "wof:name":"Air Station Aviation History",
    "wof:placetype":"venue"
},
  "geometry": {"coordinates":[-122.15113599999999,48.159765],"type":"Point"}
}