{
  "type": "Feature",
  "properties": {
    "addr:full":"4700 228th St SW Mountlake Ter WA 98043",
    "addr:housenumber":"4700",
    "addr:postcode":"98043",
    "addr:street":"228Th St Sw Mountlake Ter",
    "iso:country":"US",
    "sg:address":"4700 228th St SW",
    "sg:city":"Mountlake Ter",
    "sg:classifiers":[
        {
            "category":"Organizations",
            "subcategory":"Religious Organization",
            "type":"Services"
        }
    ],
    "sg:phone":"+1 425 672 4407",
    "sg:postcode":"98043",
    "sg:province":"WA",
    "sg:tags":[
        "church"
    ],
    "sg:website":"www.terraceview.org",
    "wof:name":"Terrace View Presbyterian Chr",
    "wof:placetype":"venue"
},
  "geometry": {"coordinates":[-122.296397,47.79186],"type":"Point"}
}