{
  "type": "Feature",
  "properties": {
    "iso:country":"US",
    "sg:address":"3003 S Huson St",
    "sg:city":"Tacoma",
    "sg:classifiers":[
        {
            "category":"Shopping",
            "subcategory":"Bicycles & Sporting Goods",
            "type":"Retail Goods"
        }
    ],
    "sg:phone":"+1 253 564 0166",
    "sg:postcode":"98409",
    "sg:province":"WA",
    "wof:name":"Dead Red Sports",
    "wof:placetype":"venue"
},
  "geometry": {"coordinates":[-122.50372,47.23225],"type":"Point"}
}