{
  "type": "Feature",
  "properties": {
    "addr:full":"8001 Jenkins Rd Sprague WA 99032",
    "addr:housenumber":"8001",
    "addr:postcode":"99032",
    "addr:street":"Jenkins Rd",
    "iso:country":"US",
    "sg:address":"8001 Jenkins Rd",
    "sg:city":"Sprague",
    "sg:phone":"+1 509 253 4455",
    "sg:postcode":"99032",
    "sg:province":"WA",
    "sg:tags":[
        "farm",
        "grain",
        "cash"
    ],
    "wof:name":"Dale Gordon Countryman",
    "wof:placetype":"venue"
},
  "geometry": {"coordinates":[-118.185158,47.377282],"type":"Point"}
}