{
  "type": "Feature",
  "properties": {
    "addr:full":"11001 Lewis River Rd Ariel WA 98603",
    "addr:housenumber":"11001",
    "addr:postcode":"98603",
    "addr:street":"Lewis River Rd",
    "iso:country":"US",
    "sg:address":"11001 Lewis River Rd",
    "sg:city":"Ariel",
    "sg:classifiers":[
        {
            "category":"Farming",
            "subcategory":"Aquatic Farm",
            "type":"Manufacturing & Wholesale Goods"
        }
    ],
    "sg:phone":"+1 360 231 4210",
    "sg:postcode":"98603",
    "sg:province":"WA",
    "sg:tags":[
        "hatchery",
        "fish"
    ],
    "wof:name":"Speelyai Hatchery",
    "wof:placetype":"venue"
},
  "geometry": {"coordinates":[-122.409611,45.995279],"type":"Point"}
}