{
  "type": "Feature",
  "properties": {
    "addr:full":"511 Front St Lynden WA 98264",
    "addr:housenumber":"511",
    "addr:postcode":"98264",
    "addr:street":"Front St",
    "iso:country":"US",
    "sg:address":"511 Front St",
    "sg:city":"Lynden",
    "sg:classifiers":[
        {
            "category":"Shopping",
            "subcategory":"Gifts & Souvenirs",
            "type":"Retail Goods"
        }
    ],
    "sg:phone":"+1 360 354 7959",
    "sg:postcode":"98264",
    "sg:province":"WA",
    "sg:tags":[
        "shop"
    ],
    "wof:name":"Primrose Lane",
    "wof:placetype":"venue"
},
  "geometry": {"coordinates":[-122.45312,48.942661],"type":"Point"}
}