{
  "type": "Feature",
  "properties": {
    "addr:full":"25172 SE 158th St Issaquah WA 98027",
    "addr:postcode":"25172;98027",
    "addr:street":"Se 158Th St",
    "iso:country":"US",
    "sg:address":"25172 SE 158th St",
    "sg:city":"Issaquah",
    "sg:classifiers":[
        {
            "category":"Professional",
            "subcategory":"Computer Services",
            "type":"Services"
        }
    ],
    "sg:phone":"+1 425 222 3527",
    "sg:postcode":"98027",
    "sg:province":"WA",
    "sg:tags":[
        "datum"
    ],
    "wof:name":"All Traffic Data Services Inc",
    "wof:placetype":"venue"
},
  "geometry": {"coordinates":[-122.00563699999999,47.461295],"type":"Point"}
}