{
  "type": "Feature",
  "properties": {
    "addr:full":"5101 101st St SW Lakewood WA 98499",
    "addr:housenumber":"5101",
    "addr:postcode":"98499",
    "addr:street":"101St St Sw",
    "iso:country":"US",
    "sg:address":"5101 101st St SW",
    "sg:city":"Lakewood",
    "sg:classifiers":[
        {
            "category":"Building & Trades",
            "subcategory":"Construction",
            "type":"Services"
        }
    ],
    "sg:phone":"+1 253 581 6535",
    "sg:postcode":"98499",
    "sg:province":"WA",
    "sg:tags":[
        "home",
        "builder"
    ],
    "wof:name":"Puget Sound Homes",
    "wof:placetype":"venue"
},
  "geometry": {"coordinates":[-122.50496200000001,47.166222],"type":"Point"}
}