{
  "type": "Feature",
  "properties": {
    "iso:country":"US",
    "sg:address":"1511 Central Ave S",
    "sg:city":"Kent",
    "sg:classifiers":[
        {
            "category":"Real Estate",
            "subcategory":"Real Estate Agent",
            "type":"Services"
        }
    ],
    "sg:phone":"+1 253 852 5327",
    "sg:postcode":"98032",
    "sg:province":"WA",
    "wof:name":"Real Estate Company LLC Scott",
    "wof:placetype":"venue"
},
  "geometry": {"coordinates":[-122.23033,47.372189],"type":"Point"}
}