{
  "type": "Feature",
  "properties": {
    "addr:full":"218 SW 327th Pl Federal Way WA 98023",
    "addr:housenumber":"218",
    "addr:postcode":"98023",
    "addr:street":"Sw 327Th Pl",
    "iso:country":"US",
    "sg:address":"218 SW 327th Pl",
    "sg:city":"Federal Way",
    "sg:classifiers":[
        {
            "category":"Wholesale",
            "subcategory":"Auto Parts",
            "type":"Manufacturing & Wholesale Goods"
        }
    ],
    "sg:phone":"+1 253 925 5619",
    "sg:postcode":"98023",
    "sg:province":"WA",
    "sg:tags":[
        "representative"
    ],
    "wof:name":"Simex Enterprises",
    "wof:placetype":"venue"
},
  "geometry": {"coordinates":[-122.33790399999999,47.308865],"type":"Point"}
}