{
  "type": "Feature",
  "properties": {
    "addr:full":"312 S Columbia Center Blvd Kennewick WA 99336",
    "addr:housenumber":"312",
    "addr:postcode":"99336",
    "addr:street":"S Columbia Center Blvd",
    "iso:country":"US",
    "sg:address":"312 S Columbia Center Blvd",
    "sg:city":"Kennewick",
    "sg:classifiers":[
        {
            "category":"Professional",
            "subcategory":"Management & Consulting",
            "type":"Services"
        }
    ],
    "sg:phone":"+1 509 783 2007",
    "sg:postcode":"99336",
    "sg:province":"WA",
    "wof:name":"Jeff Short Inc",
    "wof:placetype":"venue"
},
  "geometry": {"coordinates":[-119.222544,46.206388],"type":"Point"}
}