{
  "type": "Feature",
  "properties": {
    "addr:full":"1029 E Wishkah St Aberdeen WA 98520",
    "addr:housenumber":"1029",
    "addr:postcode":"98520",
    "addr:street":"E Wishkah St",
    "iso:country":"US",
    "sg:address":"1029 E Wishkah St",
    "sg:city":"Aberdeen",
    "sg:classifiers":[
        {
            "category":"Utilities",
            "subcategory":"Mobile Phone",
            "type":"Services"
        }
    ],
    "sg:phone":"+1 360 533 3940",
    "sg:postcode":"98520",
    "sg:province":"WA",
    "sg:tags":[
        "telephone",
        "cellular"
    ],
    "wof:name":"Cingular Wireless",
    "wof:placetype":"venue"
},
  "geometry": {"coordinates":[-123.80559599999999,46.977206],"type":"Point"}
}