{
  "type": "Feature",
  "properties": {
    "addr:full":"503 S 3rd Ave Sequim WA 98382",
    "addr:housenumber":"503",
    "addr:postcode":"98382",
    "addr:street":"S 3Rd Ave",
    "iso:country":"US",
    "sg:address":"503 S 3rd Ave",
    "sg:city":"Sequim",
    "sg:classifiers":[
        {
            "category":"Building & Trades",
            "subcategory":"Electrical",
            "type":"Services"
        }
    ],
    "sg:phone":"+1 360 683 6819",
    "sg:postcode":"98382",
    "sg:province":"WA",
    "sg:tags":[
        "consultant",
        "designer",
        "lighting",
        "electric",
        "contractor"
    ],
    "wof:name":"Kirsch Electric Inc",
    "wof:placetype":"venue"
},
  "geometry": {"coordinates":[-123.10775,48.076068],"type":"Point"}
}