{
  "type": "Feature",
  "properties": {
    "addr:full":"4170 Pacific Ave SE Lacey WA 98503",
    "addr:housenumber":"4170",
    "addr:postcode":"98503",
    "addr:street":"Pacific Ave Se",
    "iso:country":"US",
    "sg:address":"4170 Pacific Ave SE",
    "sg:city":"Lacey",
    "sg:classifiers":[
        {
            "category":"Retail",
            "subcategory":"Laundry & Dry Cleaning",
            "type":"Services"
        }
    ],
    "sg:phone":"+1 360 491 3730",
    "sg:postcode":"98503",
    "sg:province":"WA",
    "wof:name":"Howardss Cleaners",
    "wof:placetype":"venue"
},
  "geometry": {"coordinates":[-122.83301899999999,47.039285],"type":"Point"}
}