{
  "type": "Feature",
  "properties": {
    "addr:full":"1305 Bonneville Ave Snohomish WA 98290",
    "addr:housenumber":"1305",
    "addr:postcode":"98290",
    "addr:street":"Bonneville Ave",
    "iso:country":"US",
    "sg:address":"1305 Bonneville Ave",
    "sg:city":"Snohomish",
    "sg:classifiers":[
        {
            "category":"Manufacturing",
            "subcategory":"Tools & Machinery",
            "type":"Manufacturing & Wholesale Goods"
        }
    ],
    "sg:phone":"+1 360 563 0233",
    "sg:postcode":"98290",
    "sg:province":"WA",
    "sg:tags":[
        "packer",
        "equipment",
        "fish"
    ],
    "wof:name":"Pisces Industries LTD",
    "wof:placetype":"venue"
},
  "geometry": {"coordinates":[-122.101186,47.927425],"type":"Point"}
}