{
  "type": "Feature",
  "properties": {
    "addr:full":"712 228th Ave NE Sammamish WA 98074",
    "addr:housenumber":"712",
    "addr:postcode":"98074",
    "addr:street":"228Th Ave Ne",
    "iso:country":"US",
    "sg:address":"712 228th Ave NE",
    "sg:city":"Sammamish",
    "sg:classifiers":[
        {
            "category":"Personal",
            "subcategory":"Nail Salon",
            "type":"Services"
        }
    ],
    "sg:phone":"+1 425 898 7461",
    "sg:postcode":"98074",
    "sg:province":"WA",
    "wof:name":"Sammamish Nails",
    "wof:placetype":"venue"
},
  "geometry": {"coordinates":[-122.0355,47.615571],"type":"Point"}
}