{
  "type": "Feature",
  "properties": {
    "addr:full":"9725 Lowell Larimer Rd Everett WA 98208",
    "addr:housenumber":"9725",
    "addr:postcode":"98208",
    "addr:street":"Larimer Rd",
    "iso:country":"US",
    "sg:address":"9725 Lowell Larimer Rd",
    "sg:city":"Everett",
    "sg:classifiers":[
        {
            "category":"Farming",
            "subcategory":"Dairy Farm",
            "type":"Manufacturing & Wholesale Goods"
        }
    ],
    "sg:phone":"+1 425 337 5772",
    "sg:postcode":"98208",
    "sg:province":"WA",
    "wof:name":"Sunacres Holsteins",
    "wof:placetype":"venue"
},
  "geometry": {"coordinates":[-122.175112,47.909858],"type":"Point"}
}