{
  "type": "Feature",
  "properties": {
    "addr:full":"13549 23rd Ave NE Seattle WA 98125",
    "addr:housenumber":"13549",
    "addr:postcode":"98125",
    "addr:street":"23Rd Ave Ne",
    "iso:country":"US",
    "sg:address":"13549 23rd Ave NE",
    "sg:city":"Seattle",
    "sg:classifiers":[
        {
            "category":"Professional",
            "type":"Services"
        }
    ],
    "sg:phone":"+1 206 440 1563",
    "sg:postcode":"98125",
    "sg:province":"WA",
    "wof:name":"Portico Studios",
    "wof:placetype":"venue"
},
  "geometry": {"coordinates":[-122.304608,47.727915],"type":"Point"}
}