{
  "type": "Feature",
  "properties": {
    "addr:full":"6719 E Tilstra Rd Benton City WA 99320",
    "addr:housenumber":"6719",
    "addr:postcode":"99320",
    "addr:street":"E Tilstra Rd",
    "iso:country":"US",
    "sg:address":"6719 E Tilstra Rd",
    "sg:city":"Benton City",
    "sg:classifiers":[
        {
            "category":"Food & Beverages",
            "subcategory":"Fruits & Vegetables",
            "type":"Retail Goods"
        }
    ],
    "sg:phone":"+1 509 588 3610",
    "sg:postcode":"99320",
    "sg:province":"WA",
    "wof:name":"Lone Sage Produce",
    "wof:placetype":"venue"
},
  "geometry": {"coordinates":[-119.485803,46.304312],"type":"Point"}
}