{
  "type": "Feature",
  "properties": {
    "addr:full":"124 S 2nd St Yakima WA 98901",
    "addr:housenumber":"124",
    "addr:postcode":"98901",
    "addr:street":"S 2Nd St",
    "iso:country":"US",
    "sg:address":"124 S 2nd St",
    "sg:city":"Yakima",
    "sg:classifiers":[
        {
            "category":"Government",
            "subcategory":"Office",
            "type":"Public Place"
        }
    ],
    "sg:phone":"+1 509 575 6092",
    "sg:postcode":"98901",
    "sg:province":"WA",
    "sg:tags":[
        "village"
    ],
    "wof:name":"Yakima Cable Communications",
    "wof:placetype":"venue"
},
  "geometry": {"coordinates":[-120.503587,46.600335],"type":"Point"}
}