{
  "type": "Feature",
  "properties": {
    "iso:country":"US",
    "sg:address":"7501 Icicle Rd",
    "sg:city":"Leavenworth",
    "sg:classifiers":[
        {
            "category":"Government",
            "subcategory":"Office",
            "type":"Public Place"
        }
    ],
    "sg:phone":"+1 509 548 7573",
    "sg:postcode":"98826",
    "sg:province":"WA",
    "sg:tags":[
        "conservation"
    ],
    "wof:name":"Mid-Columbia River Fishery Res",
    "wof:placetype":"venue"
},
  "geometry": {"coordinates":[-120.680143,47.555257],"type":"Point"}
}