{
  "type": "Feature",
  "properties": {
    "addr:full":"11631 59th Ave SE Snohomish WA 98296",
    "addr:housenumber":"11631",
    "addr:postcode":"98296",
    "addr:street":"59Th Ave Se",
    "iso:country":"US",
    "sg:address":"11631 59th Ave SE",
    "sg:city":"Snohomish",
    "sg:classifiers":[
        {
            "category":"Building & Trades",
            "subcategory":"Construction",
            "type":"Services"
        },
        {
            "category":"Manufacturing",
            "subcategory":"Building Materials",
            "type":"Manufacturing & Wholesale Goods"
        },
        {
            "category":"Home & Garden",
            "subcategory":"Carpets & Floor Coverings",
            "type":"Retail Goods"
        }
    ],
    "sg:phone":"+1 206 607 0489",
    "sg:postcode":"98296",
    "sg:province":"WA",
    "sg:tags":[
        "materials-wholesale",
        "manufacturer",
        "tile-contractors"
    ],
    "wof:name":"Northwest Tile and Hardwood Floors",
    "wof:placetype":"venue"
},
  "geometry": {"coordinates":[-122.154464,47.891313],"type":"Point"}
}