{
  "type": "Feature",
  "properties": {
    "iso:country":"US",
    "sg:address":"100 W Wine Country Rd",
    "sg:city":"Grandview",
    "sg:classifiers":[
        {
            "category":"Autos & Motor Vehicles",
            "subcategory":"Fuel & Gas Station",
            "type":"Retail Goods"
        },
        {
            "category":"Retail",
            "subcategory":"Auto Repair",
            "type":"Services"
        }
    ],
    "sg:phone":"+1 509 882 4446",
    "sg:postcode":"98930",
    "sg:province":"WA",
    "sg:tags":[
        "oil",
        "general"
    ],
    "wof:name":"Debock's Auto Repair",
    "wof:placetype":"venue"
},
  "geometry": {"coordinates":[-119.90343300000001,46.256071],"type":"Point"}
}