{
  "type": "Feature",
  "properties": {
    "addr:full":"551 S Forks Ave Forks WA 98331",
    "addr:housenumber":"551",
    "addr:postcode":"98331",
    "addr:street":"S Forks Ave",
    "iso:country":"US",
    "sg:address":"551 S Forks Ave",
    "sg:city":"Forks",
    "sg:classifiers":[
        {
            "category":"Farming",
            "subcategory":"Livestock Farm",
            "type":"Manufacturing & Wholesale Goods"
        },
        {
            "category":"Government",
            "subcategory":"Office",
            "type":"Public Place"
        }
    ],
    "sg:phone":"+1 360 374 7566",
    "sg:postcode":"98331",
    "sg:province":"WA",
    "sg:tags":[
        "government-united",
        "state",
        "livestock-commission"
    ],
    "wof:name":"United States Dept Of Agriculture",
    "wof:placetype":"venue"
},
  "geometry": {"coordinates":[-124.385496,47.945292],"type":"Point"}
}