{
  "type": "Feature",
  "properties": {
    "addr:full":"601 1st Ave S Okanogan WA 98840",
    "addr:housenumber":"601",
    "addr:postcode":"98840",
    "addr:street":"1St Ave S Okanogan",
    "iso:country":"US",
    "sg:address":"601 1st Ave S",
    "sg:city":"Okanogan",
    "sg:classifiers":[
        {
            "category":"Recreation",
            "type":"Entertainment"
        }
    ],
    "sg:phone":"+1 509 422 5711",
    "sg:postcode":"98840",
    "sg:province":"WA",
    "sg:tags":[
        "pool",
        "swimming"
    ],
    "wof:name":"City Swimming Pool",
    "wof:placetype":"venue"
},
  "geometry": {"coordinates":[-119.58323300000001,48.360603],"type":"Point"}
}