{
  "type": "Feature",
  "properties": {
    "addr:full":"3410 Stone Way North Seattle WA 98103",
    "addr:housenumber":"3410",
    "addr:postcode":"98103",
    "addr:street":"Stone Way North",
    "iso:country":"US",
    "sg:address":"3410 Stone Way North",
    "sg:city":"Seattle",
    "sg:classifiers":[
        {
            "category":"Sports & Exercise",
            "subcategory":"Gym",
            "type":"Entertainment"
        }
    ],
    "sg:phone":"+1 425 749 9161",
    "sg:postcode":"98103",
    "sg:province":"WA",
    "sg:tags":[
        "trainer"
    ],
    "sg:website":"www.palumboperformance.com",
    "wof:name":"Palumbo Performance",
    "wof:placetype":"venue"
},
  "geometry": {"coordinates":[-122.34210299999999,47.649026],"type":"Point"}
}