{
  "type": "Feature",
  "properties": {
    "addr:full":"708 Lebo Blvd Bremerton WA 98310",
    "addr:housenumber":"708",
    "addr:postcode":"98310",
    "addr:street":"Lebo Blvd",
    "iso:country":"US",
    "sg:address":"708 Lebo Blvd",
    "sg:city":"Bremerton",
    "sg:classifiers":[
        {
            "category":"Wholesale",
            "subcategory":"Chemicals & Plastics",
            "type":"Manufacturing & Wholesale Goods"
        }
    ],
    "sg:phone":"+1 360 792 9414",
    "sg:postcode":"98310",
    "sg:province":"WA",
    "sg:tags":[
        "oxygen"
    ],
    "wof:name":"Lincare",
    "wof:placetype":"venue"
},
  "geometry": {"coordinates":[-122.627045,47.581634],"type":"Point"}
}