{
  "type": "Feature",
  "properties": {
    "addr:full":"2433 George Washington Way Richland WA 99354",
    "addr:housenumber":"2433",
    "addr:postcode":"99354",
    "addr:street":"George Washington Way",
    "iso:country":"US",
    "sg:address":"2433 George Washington Way",
    "sg:city":"Richland",
    "sg:classifiers":[
        {
            "category":"Real Estate",
            "subcategory":"Real Estate Operator",
            "type":"Services"
        }
    ],
    "sg:phone":"+1 509 375 0608",
    "sg:postcode":"99354",
    "sg:province":"WA",
    "sg:tags":[
        "building",
        "apartment"
    ],
    "wof:name":"Robert Young Assoc Richland Wa",
    "wof:placetype":"venue"
},
  "geometry": {"coordinates":[-119.27299499999999,46.319307],"type":"Point"}
}