{
  "type": "Feature",
  "properties": {
    "addr:full":"960 E Main St Ste B Auburn WA 98002",
    "addr:housenumber":"960",
    "addr:postcode":"98002",
    "addr:street":"E Main St Ste B",
    "iso:country":"US",
    "sg:address":"960 E Main St Ste B",
    "sg:city":"Auburn",
    "sg:classifiers":[
        {
            "category":"Organizations",
            "subcategory":"Labor Organization",
            "type":"Services"
        }
    ],
    "sg:phone":"+1 253 351 0511",
    "sg:postcode":"98002",
    "sg:province":"WA",
    "sg:website":"http://www.uswa.org",
    "wof:name":"Uswa",
    "wof:placetype":"venue"
},
  "geometry": {"coordinates":[-122.216663,47.307906],"type":"Point"}
}