{
  "type": "Feature",
  "properties": {
    "addr:full":"12130 N Mill Rd Spokane WA 99208",
    "addr:housenumber":"12130",
    "addr:postcode":"99208",
    "addr:street":"N Mill Rd",
    "iso:country":"US",
    "sg:address":"12130 N Mill Rd",
    "sg:city":"Spokane",
    "sg:classifiers":[
        {
            "category":"Professional",
            "subcategory":"Computer Services",
            "type":"Services"
        }
    ],
    "sg:phone":"+1 509 468 0618",
    "sg:postcode":"99208",
    "sg:province":"WA",
    "sg:tags":[
        "internet"
    ],
    "sg:website":"www.thriva.com",
    "wof:name":"Thriva",
    "wof:placetype":"venue"
},
  "geometry": {"coordinates":[-117.422698,47.768214],"type":"Point"}
}