{
  "type": "Feature",
  "properties": {
    "addr:full":"1656 N Bend Blvd N North Bend WA 98045",
    "addr:housenumber":"1656",
    "addr:postcode":"98045",
    "addr:street":"N Bend Blvd N",
    "iso:country":"US",
    "sg:address":"1656 N Bend Blvd N",
    "sg:city":"North Bend",
    "sg:phone":"+1 425 888 5195",
    "sg:postcode":"98045",
    "sg:province":"WA",
    "sg:tags":[
        "gas"
    ],
    "wof:name":"Bowman Propane Co",
    "wof:placetype":"venue"
},
  "geometry": {"coordinates":[-121.80218000000001,47.507956],"type":"Point"}
}