{
  "type": "Feature",
  "properties": {
    "addr:full":"8100 C. Freedom Ln Olympia WA 98516",
    "addr:housenumber":"8100 c.",
    "addr:postcode":"98516",
    "addr:street":"Freedom Ln",
    "iso:country":"US",
    "sg:address":"8100 C. Freedom Ln",
    "sg:city":"Olympia",
    "sg:classifiers":[
        {
            "category":"Restaurant",
            "type":"Food & Drink"
        }
    ],
    "sg:menulink":"http://www.allmenus.com/wa/olympia/222794-cb--potts/menu/",
    "sg:postcode":"98516",
    "sg:province":"WA",
    "sg:tags":[
        "american"
    ],
    "wof:name":"C.B. & Potts",
    "wof:placetype":"venue"
},
  "geometry": {"coordinates":[-122.768978,47.061632],"type":"Point"}
}