{
  "type": "Feature",
  "properties": {
    "addr:full":"102 E Francis Ave Spokane WA 99208",
    "addr:housenumber":"102",
    "addr:postcode":"99208",
    "addr:street":"E Francis Ave",
    "iso:country":"US",
    "sg:address":"102 E Francis Ave",
    "sg:city":"Spokane",
    "sg:classifiers":[
        {
            "category":"Shopping",
            "type":"Retail Goods"
        },
        {
            "category":"Food & Beverages",
            "subcategory":"Groceries & Convenience Stores",
            "type":"Retail Goods"
        }
    ],
    "sg:phone":"+1 509 483 3033",
    "sg:postcode":"99208",
    "sg:province":"WA",
    "sg:tags":[
        "merchandise"
    ],
    "wof:name":"De Leon Foods Inc",
    "wof:placetype":"venue"
},
  "geometry": {"coordinates":[-117.408512,47.715092],"type":"Point"}
}