{
  "type": "Feature",
  "properties": {
    "addr:full":"14227 NE Woodinville Duvall Rd Woodinville WA 98072",
    "addr:housenumber":"14227",
    "addr:postcode":"98072",
    "addr:street":"Ne Woodinville Duvall Rd",
    "iso:country":"US",
    "sg:address":"14227 NE Woodinville Duvall Rd",
    "sg:city":"Woodinville",
    "sg:classifiers":[
        {
            "category":"Insurance",
            "subcategory":"Insurance Agent",
            "type":"Services"
        }
    ],
    "sg:phone":"+1 425 483 4583",
    "sg:postcode":"98072",
    "sg:province":"WA",
    "wof:name":"Insurance Services",
    "wof:placetype":"venue"
},
  "geometry": {"coordinates":[-122.149012,47.755872],"type":"Point"}
}