{
  "type": "Feature",
  "properties": {
    "addr:full":"20242 Grand Mound Way SW Centralia WA 98531",
    "addr:housenumber":"20242",
    "addr:postcode":"98531",
    "addr:street":"Grand Mound Way Sw",
    "iso:country":"US",
    "sg:address":"20242 Grand Mound Way SW",
    "sg:city":"Centralia",
    "sg:classifiers":[
        {
            "category":"Food & Beverages",
            "subcategory":"Meat & Fish",
            "type":"Retail Goods"
        }
    ],
    "sg:phone":"+1 360 736 5257",
    "sg:postcode":"98531",
    "sg:province":"WA",
    "sg:tags":[
        "cutting"
    ],
    "wof:name":"Beef Shop",
    "wof:placetype":"venue"
},
  "geometry": {"coordinates":[-123.02812400000001,46.794627],"type":"Point"}
}