{
  "type": "Feature",
  "properties": {
    "addr:full":"1833 W Court St Pasco WA 99301",
    "addr:housenumber":"1833",
    "addr:postcode":"99301",
    "addr:street":"W Court St",
    "iso:country":"US",
    "sg:address":"1833 W Court St",
    "sg:city":"Pasco",
    "sg:classifiers":[
        {
            "category":"Restaurant",
            "type":"Food & Drink"
        }
    ],
    "sg:postcode":"99301",
    "sg:province":"WA",
    "sg:tags":[
        "seafood"
    ],
    "wof:name":"Gracie's Seafood",
    "wof:placetype":"venue"
},
  "geometry": {"coordinates":[-119.114259,46.24151],"type":"Point"}
}