{
  "type": "Feature",
  "properties": {
    "addr:full":"2008 Bellevue Sq Bellevue WA 98004",
    "addr:housenumber":"2008",
    "addr:postcode":"98004",
    "addr:street":"Bellevue Sq",
    "iso:country":"US",
    "sg:address":"2008 Bellevue Sq",
    "sg:city":"Bellevue",
    "sg:classifiers":[
        {
            "category":"Shopping",
            "subcategory":"Clothing, Apparel, & Fashions",
            "type":"Retail Goods"
        }
    ],
    "sg:phone":"+1 425 646 6441",
    "sg:postcode":"98004",
    "sg:province":"WA",
    "sg:tags":[
        "accessory",
        "clothing",
        "women's"
    ],
    "wof:name":"Eileen Fisher Store",
    "wof:placetype":"venue"
},
  "geometry": {"coordinates":[-122.20526700000001,47.617209],"type":"Point"}
}