{
  "type": "Feature",
  "properties": {
    "addr:full":"5429 Scherrer Rd Granite Falls WA 98252",
    "addr:housenumber":"5429",
    "addr:postcode":"98252",
    "addr:street":"Scherrer Rd",
    "iso:country":"US",
    "sg:address":"5429 Scherrer Rd",
    "sg:city":"Granite Falls",
    "sg:classifiers":[
        {
            "category":"Manufacturing",
            "subcategory":"Lumber",
            "type":"Manufacturing & Wholesale Goods"
        }
    ],
    "sg:phone":"+1 360 691 2528",
    "sg:postcode":"98252",
    "sg:province":"WA",
    "sg:tags":[
        "company",
        "logging"
    ],
    "wof:name":"Northern Land Management",
    "wof:placetype":"venue"
},
  "geometry": {"coordinates":[-121.947964,48.048443],"type":"Point"}
}