{
  "type": "Feature",
  "properties": {
    "addr:full":"4602 Sunset Blvd NE Renton WA 98059",
    "addr:housenumber":"4602",
    "addr:postcode":"98059",
    "addr:street":"Sunset Blvd Ne",
    "iso:country":"US",
    "sg:address":"4602 Sunset Blvd NE",
    "sg:city":"Renton",
    "sg:classifiers":[
        {
            "category":"Restaurant",
            "type":"Food & Drink"
        }
    ],
    "sg:phone":"+1 425 277 8606",
    "sg:postcode":"98059",
    "sg:province":"WA",
    "sg:tags":[
        "shop",
        "coffee"
    ],
    "wof:name":"Java Monkie Espresso",
    "wof:placetype":"venue"
},
  "geometry": {"coordinates":[-122.15742400000001,47.505514],"type":"Point"}
}