{
  "type": "Feature",
  "properties": {
    "iso:country":"US",
    "sg:address":"33749 9th Ave S",
    "sg:city":"Federal Way",
    "sg:classifiers":[
        {
            "category":"Professional",
            "subcategory":"Lawyer & Legal Services",
            "type":"Services"
        }
    ],
    "sg:phone":"+1 253 661 1456",
    "sg:postcode":"98003",
    "sg:province":"WA",
    "sg:tags":[
        "attorney"
    ],
    "wof:name":"H J Law",
    "wof:placetype":"venue"
},
  "geometry": {"coordinates":[-122.321901,47.295147],"type":"Point"}
}