{
  "type": "Feature",
  "properties": {
    "addr:full":"602 S 1st St Yakima WA 98901",
    "addr:housenumber":"602",
    "addr:postcode":"98901",
    "addr:street":"S 1St St",
    "iso:country":"US",
    "sg:address":"602 S 1st St",
    "sg:city":"Yakima",
    "sg:classifiers":[
        {
            "category":"Autos & Motor Vehicles",
            "subcategory":"Automobile Sales",
            "type":"Retail Goods"
        }
    ],
    "sg:phone":"+1 509 469 0255",
    "sg:postcode":"98901",
    "sg:province":"WA",
    "sg:tags":[
        "car",
        "dealer"
    ],
    "wof:name":"First Class Auto Sales",
    "wof:placetype":"venue"
},
  "geometry": {"coordinates":[-120.501949,46.593449],"type":"Point"}
}