{
  "type": "Feature",
  "properties": {
    "addr:full":"6020 Rainier Ave S Seattle WA 98118",
    "addr:housenumber":"6020",
    "addr:postcode":"98118",
    "addr:street":"Rainier Ave S",
    "iso:country":"US",
    "sg:address":"6020 Rainier Ave S",
    "sg:city":"Seattle",
    "sg:classifiers":[
        {
            "category":"Organizations",
            "subcategory":"Religious Organization",
            "type":"Services"
        }
    ],
    "sg:phone":"+1 206 723 0346",
    "sg:postcode":"98118",
    "sg:province":"WA",
    "wof:name":"Church of Christ-Iglesia Ni Cristo",
    "wof:placetype":"venue"
},
  "geometry": {"coordinates":[-122.277,47.5485],"type":"Point"}
}