{
  "type": "Feature",
  "properties": {
    "addr:full":"18124 Woodbine Dr Arlington WA 98223",
    "addr:housenumber":"18124",
    "addr:postcode":"98223",
    "addr:street":"Woodbine Dr",
    "iso:country":"US",
    "sg:address":"18124 Woodbine Dr",
    "sg:city":"Arlington",
    "sg:classifiers":[
        {
            "category":"Real Estate",
            "subcategory":"Real Estate Agent",
            "type":"Services"
        }
    ],
    "sg:phone":"+1 425 232 7107",
    "sg:postcode":"98223",
    "sg:province":"WA",
    "wof:name":"Richardson Realty",
    "wof:placetype":"venue"
},
  "geometry": {"coordinates":[-122.13512299999999,48.160361],"type":"Point"}
}