{
  "type": "Feature",
  "properties": {
    "addr:full":"418 US Hwy 12 Chehalis WA 98532",
    "addr:housenumber":"418",
    "addr:postcode":"98532",
    "addr:street":"Us Hwy 12",
    "iso:country":"US",
    "sg:address":"418 US Hwy 12",
    "sg:city":"Chehalis",
    "sg:classifiers":[
        {
            "category":"Professional",
            "type":"Services"
        }
    ],
    "sg:phone":"+1 360 262 9059",
    "sg:postcode":"98532",
    "sg:province":"WA",
    "wof:name":"Triple J Services Inc",
    "wof:placetype":"venue"
},
  "geometry": {"coordinates":[-122.83929500000001,46.544251],"type":"Point"}
}