{
  "type": "Feature",
  "properties": {
    "addr:full":"10036 16th Ave SW Seattle WA 98146",
    "addr:housenumber":"10036",
    "addr:postcode":"98146",
    "addr:street":"16Th Ave Sw",
    "iso:country":"US",
    "sg:address":"10036 16th Ave SW",
    "sg:city":"Seattle",
    "sg:classifiers":[
        {
            "category":"Professional",
            "type":"Services"
        }
    ],
    "sg:phone":"+1 206 762 7077",
    "sg:postcode":"98146",
    "sg:province":"WA",
    "wof:name":"Spot Named Dog Inc",
    "wof:placetype":"venue"
},
  "geometry": {"coordinates":[-122.355037,47.5122],"type":"Point"}
}