{
  "type": "Feature",
  "properties": {
    "addr:full":"20307 Mountain Hwy E Spanaway WA 98387",
    "addr:housenumber":"20307",
    "addr:postcode":"98387",
    "addr:street":"Mountain Hwy E",
    "iso:country":"US",
    "sg:address":"20307 Mountain Hwy E",
    "sg:city":"Spanaway",
    "sg:classifiers":[
        {
            "category":"Utilities",
            "subcategory":"Mobile Phone",
            "type":"Services"
        }
    ],
    "sg:phone":"+1 253 847 0673",
    "sg:postcode":"98387",
    "sg:province":"WA",
    "sg:tags":[
        "telephone",
        "cellular"
    ],
    "wof:name":"Wireless Retail Inc",
    "wof:placetype":"venue"
},
  "geometry": {"coordinates":[-122.419623,47.072581],"type":"Point"}
}