{
  "type": "Feature",
  "properties": {
    "iso:country":"US",
    "sg:address":"13109 SE 24th Cir",
    "sg:city":"Vancouver",
    "sg:classifiers":[
        {
            "category":"Building & Trades",
            "subcategory":"Construction",
            "type":"Services"
        }
    ],
    "sg:phone":"+1 360 892 6578",
    "sg:postcode":"98683",
    "sg:province":"WA",
    "sg:tags":[
        "excavation",
        "logging",
        "contractor"
    ],
    "wof:name":"M & B Excavating Inc",
    "wof:placetype":"venue"
},
  "geometry": {"coordinates":[-122.53818699999999,45.603274],"type":"Point"}
}