{
  "type": "Feature",
  "properties": {
    "addr:full":"300 SE 120th Ave Ste 900 Vancouver WA 98683",
    "addr:housenumber":"300",
    "addr:postcode":"98683",
    "addr:street":"Se 120Th Ave Ste 900",
    "iso:country":"US",
    "sg:address":"300 SE 120th Ave Ste 900",
    "sg:city":"Vancouver",
    "sg:classifiers":[
        {
            "category":"Health Services",
            "subcategory":"Doctor",
            "type":"Services"
        },
        {
            "category":"Health Services",
            "subcategory":"Dentist",
            "type":"Services"
        }
    ],
    "sg:phone":"+1 360 256 7220",
    "sg:postcode":"98683",
    "sg:province":"WA",
    "sg:tags":[
        "surgeon",
        "oral",
        "orthodontist"
    ],
    "sg:website":"www.brownorthodontics.com",
    "wof:name":"Brown Constance M DDS",
    "wof:placetype":"venue"
},
  "geometry": {"coordinates":[-122.549803,45.619503],"type":"Point"}
}