{
  "type": "Feature",
  "properties": {
    "addr:full":"3100 Kitsap Way Bremerton WA 98312",
    "addr:postcode":"3100;98312",
    "addr:street":"Kitsap Way",
    "iso:country":"US",
    "sg:address":"3100 Kitsap Way",
    "sg:city":"Bremerton",
    "sg:classifiers":[
        {
            "category":"Building & Trades",
            "subcategory":"Equipment Rental",
            "type":"Services"
        },
        {
            "category":"Cinema",
            "subcategory":"Movie Rental",
            "type":"Entertainment"
        }
    ],
    "sg:phone":"+1 360 373 0472",
    "sg:postcode":"98312",
    "sg:province":"WA",
    "sg:tags":[
        "video",
        "disc",
        "leasing",
        "tape"
    ],
    "wof:name":"Total Video 1",
    "wof:placetype":"venue"
},
  "geometry": {"coordinates":[-122.65879700000001,47.571782],"type":"Point"}
}