{
  "type": "Feature",
  "properties": {
    "addr:full":"850 SE Klemgard St Pullman WA 99163",
    "addr:postcode":"850;99163",
    "addr:street":"Se Klemgard St",
    "iso:country":"US",
    "sg:address":"850 SE Klemgard St",
    "sg:city":"Pullman",
    "sg:classifiers":[
        {
            "category":"Education",
            "subcategory":"School",
            "type":"Public Place"
        }
    ],
    "sg:phone":"+1 509 334 5641",
    "sg:postcode":"99163",
    "sg:province":"WA",
    "sg:tags":[
        "elementary"
    ],
    "sg:website":"http://www.psd267.wednet.edu",
    "wof:name":"Franklin Elementary School",
    "wof:placetype":"venue"
},
  "geometry": {"coordinates":[-117.16936,46.716558],"type":"Point"}
}