{
  "type": "Feature",
  "properties": {
    "addr:full":"8630 NE Juanita Dr Kirkland WA 98034",
    "addr:housenumber":"8630",
    "addr:postcode":"98034",
    "addr:street":"Ne Juanita Dr",
    "iso:country":"US",
    "sg:address":"8630 NE Juanita Dr",
    "sg:city":"Kirkland",
    "sg:classifiers":[
        {
            "category":"Retail",
            "subcategory":"Repair Shop",
            "type":"Services"
        }
    ],
    "sg:phone":"+1 425 242 0595",
    "sg:postcode":"98034",
    "sg:province":"WA",
    "sg:tags":[
        "television",
        "radio-service"
    ],
    "sg:website":"http://www.domilogic.com",
    "wof:name":"Domilogic Design",
    "wof:placetype":"venue"
},
  "geometry": {"coordinates":[-122.226286,47.702389],"type":"Point"}
}