{
  "type": "Feature",
  "properties": {
    "addr:full":"200 E 3rd Ave Ellensburg WA 98926",
    "addr:housenumber":"200",
    "addr:postcode":"98926",
    "addr:street":"E 3Rd Ave",
    "iso:country":"US",
    "sg:address":"200 E 3rd Ave",
    "sg:city":"Ellensburg",
    "sg:classifiers":[
        {
            "category":"Professional",
            "subcategory":"Lawyer & Legal Services",
            "type":"Services"
        }
    ],
    "sg:phone":"+1 509 925 3191",
    "sg:postcode":"98926",
    "sg:province":"WA",
    "sg:tags":[
        "attorney"
    ],
    "wof:name":"Cone Gilreath Ellis & Cole",
    "wof:placetype":"venue"
},
  "geometry": {"coordinates":[-120.54582600000001,46.994488],"type":"Point"}
}