{
  "type": "Feature",
  "properties": {
    "addr:full":"7418 NE Hazel Dell Ave # 32 Vancouver WA 98665",
    "addr:housenumber":"7418",
    "addr:postcode":"98665",
    "addr:street":"Ne Hazel Dell Ave # 32",
    "iso:country":"US",
    "sg:address":"7418 NE Hazel Dell Ave # 32",
    "sg:city":"Vancouver",
    "sg:classifiers":[
        {
            "category":"Building & Trades",
            "subcategory":"Construction",
            "type":"Services"
        }
    ],
    "sg:phone":"+1 360 735 7754",
    "sg:postcode":"98665",
    "sg:province":"WA",
    "sg:tags":[
        "wallcoverings-installation",
        "wallpaper",
        "painting",
        "contractor"
    ],
    "wof:name":"Wauls Painting Apt 31",
    "wof:placetype":"venue"
},
  "geometry": {"coordinates":[-122.668651,45.676357],"type":"Point"}
}