{
  "type": "Feature",
  "properties": {
    "addr:full":"3242 Fort Rd Toppenish WA 98948",
    "addr:housenumber":"3242",
    "addr:postcode":"98948",
    "addr:street":"Fort Rd",
    "iso:country":"US",
    "sg:address":"3242 Fort Rd",
    "sg:city":"Toppenish",
    "sg:classifiers":[
        {
            "category":"Social Services",
            "subcategory":"Child Care",
            "type":"Services"
        }
    ],
    "sg:phone":"+1 509 865 7903",
    "sg:postcode":"98948",
    "sg:province":"WA",
    "sg:tags":[
        "day"
    ],
    "wof:name":"The Enterprise For Progress In",
    "wof:placetype":"venue"
},
  "geometry": {"coordinates":[-120.416393,46.375431],"type":"Point"}
}