{
  "type": "Feature",
  "properties": {
    "addr:full":"10027 NE 112th St Kirkland WA 98033",
    "addr:housenumber":"10027",
    "addr:postcode":"98033",
    "addr:street":"Ne 112Th St",
    "iso:country":"US",
    "sg:address":"10027 NE 112th St",
    "sg:city":"Kirkland",
    "sg:classifiers":[
        {
            "category":"Wholesale",
            "subcategory":"Groceries",
            "type":"Manufacturing & Wholesale Goods"
        }
    ],
    "sg:phone":"+1 843 247 2304",
    "sg:postcode":"98033",
    "sg:province":"WA",
    "sg:tags":[
        "seafood",
        "retail",
        "meat"
    ],
    "wof:name":"Land and Seafoods Inc",
    "wof:placetype":"venue"
},
  "geometry": {"coordinates":[-122.20764699999999,47.700346],"type":"Point"}
}