{
  "type": "Feature",
  "properties": {
    "addr:full":"2001 6th Avenue Seattle WA 98121",
    "addr:housenumber":"2001",
    "addr:postcode":"98121",
    "addr:street":"6Th Avenue",
    "iso:country":"US",
    "sg:address":"2001 6th Avenue",
    "sg:city":"Seattle",
    "sg:classifiers":[
        {
            "category":"Utilities",
            "type":"Services"
        }
    ],
    "sg:phone":"+1 206 441 3456",
    "sg:postcode":"98121",
    "sg:province":"WA",
    "sg:tags":[
        "provider",
        "internet"
    ],
    "wof:name":"Zipcon",
    "wof:placetype":"venue"
},
  "geometry": {"coordinates":[-122.338385,47.614382],"type":"Point"}
}