{
  "type": "Feature",
  "properties": {
    "addr:full":"17950 50th Ave S Seatac WA 98188",
    "addr:housenumber":"17950",
    "addr:postcode":"98188",
    "addr:street":"50Th Ave S Seatac",
    "iso:country":"US",
    "sg:address":"17950 50th Ave S",
    "sg:city":"Seatac",
    "sg:classifiers":[
        {
            "category":"Professional",
            "subcategory":"Management & Consulting",
            "type":"Services"
        }
    ],
    "sg:phone":"+1 206 244 9158",
    "sg:postcode":"98188",
    "sg:province":"WA",
    "sg:tags":[
        "marketing",
        "program"
    ],
    "wof:name":"A & I Marketing",
    "wof:placetype":"venue"
},
  "geometry": {"coordinates":[-122.27185,47.442145],"type":"Point"}
}