{
  "type": "Feature",
  "properties": {
    "iso:country":"US",
    "sg:address":"612 101st Pl SE",
    "sg:city":"Everett",
    "sg:classifiers":[
        {
            "category":"Professional",
            "subcategory":"Business Services",
            "type":"Services"
        }
    ],
    "sg:phone":"+1 425 347 5616",
    "sg:postcode":"98208",
    "sg:province":"WA",
    "wof:name":"Michael & Company",
    "wof:placetype":"venue"
},
  "geometry": {"coordinates":[-122.223366,47.906055],"type":"Point"}
}