{
  "type": "Feature",
  "properties": {
    "addr:full":"33101 NE Mystic Dr Yacolt WA 98675",
    "addr:housenumber":"33101",
    "addr:postcode":"98675",
    "addr:street":"Ne Mystic Dr",
    "iso:country":"US",
    "sg:address":"33101 NE Mystic Dr",
    "sg:city":"Yacolt",
    "sg:classifiers":[
        {
            "category":"Retail",
            "subcategory":"Animal Services",
            "type":"Services"
        }
    ],
    "sg:phone":"+1 360 686 3623",
    "sg:postcode":"98675",
    "sg:province":"WA",
    "sg:tags":[
        "breeder",
        "dog"
    ],
    "wof:name":"Von Stevenhaus German Import",
    "wof:placetype":"venue"
},
  "geometry": {"coordinates":[-122.427374,45.863397],"type":"Point"}
}