{
  "type": "Feature",
  "properties": {
    "addr:full":"140 6th Ave SE Issaquah WA 98027",
    "addr:housenumber":"140",
    "addr:postcode":"98027",
    "addr:street":"6Th Ave Se",
    "iso:country":"US",
    "sg:address":"140 6th Ave SE",
    "sg:city":"Issaquah",
    "sg:classifiers":[
        {
            "category":"Travel",
            "subcategory":"Hotels & Motels",
            "type":"Entertainment"
        }
    ],
    "sg:phone":"+1 425 391 4828",
    "sg:postcode":"98027",
    "sg:province":"WA",
    "sg:tags":[
        "breakfast",
        "accommodation",
        "bed"
    ],
    "wof:name":"Issaquah Bed & Breakfast",
    "wof:placetype":"venue"
},
  "geometry": {"coordinates":[-122.026326,47.528999],"type":"Point"}
}