{
  "type": "Feature",
  "properties": {
    "addr:full":"505 N Argonne Rd Spokane Valley WA 99212",
    "addr:housenumber":"505",
    "addr:postcode":"99212",
    "addr:street":"N Argonne Rd",
    "iso:country":"US",
    "sg:address":"505 N Argonne Rd",
    "sg:city":"Spokane Valley",
    "sg:classifiers":[
        {
            "category":"Professional",
            "subcategory":"Lawyer & Legal Services",
            "type":"Services"
        }
    ],
    "sg:phone":"+1 509 444 2600",
    "sg:postcode":"99212",
    "sg:province":"WA",
    "sg:tags":[
        "attorney"
    ],
    "wof:name":"Brent Sorenson & Assoc",
    "wof:placetype":"venue"
},
  "geometry": {"coordinates":[-117.282915,47.661354],"type":"Point"}
}