{
  "type": "Feature",
  "properties": {
    "addr:full":"1445 R St NW Auburn WA 98001",
    "addr:housenumber":"1445",
    "addr:postcode":"98001",
    "addr:street":"R St Nw",
    "iso:country":"US",
    "sg:address":"1445 R St NW",
    "sg:city":"Auburn",
    "sg:classifiers":[
        {
            "category":"Manufacturing",
            "subcategory":"Tools & Machinery",
            "type":"Manufacturing & Wholesale Goods"
        }
    ],
    "sg:phone":"+1 253 351 6010",
    "sg:postcode":"98001",
    "sg:province":"WA",
    "sg:tags":[
        "pumps-wholesale",
        "power",
        "mfg",
        "fluid",
        "repair",
        "manufacturer"
    ],
    "wof:name":"Service Hydraulics, Inc.",
    "wof:placetype":"venue"
},
  "geometry": {"coordinates":[-122.2539,47.321027],"type":"Point"}
}