{
  "type": "Feature",
  "properties": {
    "addr:full":"1122 E Pike St Seattle WA 98122",
    "addr:housenumber":"1122",
    "addr:postcode":"98122",
    "addr:street":"E Pike St",
    "iso:country":"US",
    "sg:address":"1122 E Pike St",
    "sg:city":"Seattle",
    "sg:classifiers":[
        {
            "category":"Health Services",
            "subcategory":"Clinic",
            "type":"Services"
        },
        {
            "category":"Social Services",
            "subcategory":"Job Training",
            "type":"Services"
        }
    ],
    "sg:phone":"+1 206 323 0330",
    "sg:postcode":"98122",
    "sg:province":"WA",
    "sg:tags":[
        "career",
        "counseling",
        "mental"
    ],
    "sg:website":"www.SexAddictionSeattle.com",
    "wof:name":"Allmon, Douglas J., PhD",
    "wof:placetype":"venue"
},
  "geometry": {"coordinates":[-122.317246,47.614276],"type":"Point"}
}