{
  "type": "Feature",
  "properties": {
    "addr:full":"600 County Shop Ln Burlington WA 98233",
    "addr:housenumber":"600",
    "addr:postcode":"98233",
    "addr:street":"County Shop Ln",
    "iso:country":"US",
    "sg:address":"600 County Shop Ln",
    "sg:city":"Burlington",
    "sg:classifiers":[
        {
            "category":"Local Transit",
            "type":"Transportation"
        }
    ],
    "sg:phone":"+1 360 757 4433",
    "sg:postcode":"98233",
    "sg:province":"WA",
    "sg:tags":[
        "public"
    ],
    "wof:name":"Skagit Transit",
    "wof:placetype":"venue"
},
  "geometry": {"coordinates":[-122.30300099999999,48.488899],"type":"Point"}
}