{
  "type": "Feature",
  "properties": {
    "addr:full":"2208 NW Market St Seattle WA 98107",
    "addr:housenumber":"2208",
    "addr:postcode":"98107",
    "addr:street":"Nw Market St",
    "iso:country":"US",
    "sg:address":"2208 NW Market St",
    "sg:city":"Seattle",
    "sg:classifiers":[
        {
            "category":"Personal",
            "type":"Services"
        },
        {
            "category":"Sports & Exercise",
            "subcategory":"Gym",
            "type":"Entertainment"
        },
        {
            "category":"Arena",
            "subcategory":"Sports Club",
            "type":"Entertainment"
        }
    ],
    "sg:phone":"+1 206 706 4882",
    "sg:postcode":"98107",
    "sg:province":"WA",
    "sg:tags":[
        "trainer",
        "consultant",
        "physical",
        "health",
        "fitness"
    ],
    "sg:website":"www.ballardhealthclub.com/",
    "wof:name":"Ballard Health Club",
    "wof:placetype":"venue"
},
  "geometry": {"coordinates":[-122.385002,47.668701],"type":"Point"}
}