{
  "type": "Feature",
  "properties": {
    "addr:full":"10015 28th Avenue SW Seattle WA 98146",
    "addr:housenumber":"10015",
    "addr:postcode":"98146",
    "addr:street":"28Th Avenue Sw",
    "iso:country":"US",
    "sg:address":"10015 28th Avenue SW",
    "sg:city":"Seattle",
    "sg:classifiers":[
        {
            "category":"Education",
            "subcategory":"Preschool",
            "type":"Public Place"
        },
        {
            "category":"Education",
            "subcategory":"School",
            "type":"Public Place"
        }
    ],
    "sg:phone":"+1 206 932 2511",
    "sg:postcode":"98146",
    "sg:province":"WA",
    "sg:tags":[
        "high",
        "middle",
        "elementary"
    ],
    "sg:website":"www.westsideschool.org",
    "wof:name":"Westside School",
    "wof:placetype":"venue"
},
  "geometry": {"coordinates":[-122.35847,47.512757],"type":"Point"}
}