{
  "type": "Feature",
  "properties": {
    "addr:full":"600 Front St S Issaquah WA 98027",
    "addr:housenumber":"600",
    "addr:postcode":"98027",
    "addr:street":"Front St S Issaquah",
    "iso:country":"US",
    "sg:address":"600 Front St S",
    "sg:city":"Issaquah",
    "sg:classifiers":[
        {
            "category":"Real Estate",
            "subcategory":"Real Estate Operator",
            "type":"Services"
        }
    ],
    "sg:phone":"+1 425 391 3545",
    "sg:postcode":"98027",
    "sg:province":"WA",
    "sg:tags":[
        "building",
        "apartment"
    ],
    "wof:name":"Windsong APT Community",
    "wof:placetype":"venue"
},
  "geometry": {"coordinates":[-122.034944,47.523012],"type":"Point"}
}