{
  "type": "Feature",
  "properties": {
    "addr:full":"6208 118th St E Puyallup WA 98373",
    "addr:housenumber":"6208",
    "addr:postcode":"98373",
    "addr:street":"118Th St E",
    "iso:country":"US",
    "sg:address":"6208 118th St E",
    "sg:city":"Puyallup",
    "sg:classifiers":[
        {
            "category":"Shopping",
            "type":"Retail Goods"
        }
    ],
    "sg:phone":"+1 253 255 4420",
    "sg:postcode":"98373",
    "sg:province":"WA",
    "sg:tags":[
        "merchandise"
    ],
    "wof:name":"Daddy OS",
    "wof:placetype":"venue"
},
  "geometry": {"coordinates":[-122.34493399999999,47.149031],"type":"Point"}
}