{
  "type": "Feature",
  "properties": {
    "addr:full":"1111 Franklin St Port Townsend WA 98368",
    "addr:housenumber":"1111",
    "addr:postcode":"98368",
    "addr:street":"Franklin St",
    "iso:country":"US",
    "sg:address":"1111 Franklin St",
    "sg:city":"Port Townsend",
    "sg:classifiers":[
        {
            "category":"Organizations",
            "subcategory":"Non-profit Organization",
            "type":"Services"
        }
    ],
    "sg:phone":"+1 360 379 3246",
    "sg:postcode":"98368",
    "sg:province":"WA",
    "sg:tags":[
        "social"
    ],
    "wof:name":"ECHHO",
    "wof:placetype":"venue"
},
  "geometry": {"coordinates":[-122.760481,48.115501],"type":"Point"}
}