{
  "type": "Feature",
  "properties": {
    "addr:full":"8016 NE 14th St Vancouver WA 98664",
    "addr:housenumber":"8016",
    "addr:postcode":"98664",
    "addr:street":"Ne 14Th St",
    "iso:country":"US",
    "sg:address":"8016 NE 14th St",
    "sg:city":"Vancouver",
    "sg:classifiers":[
        {
            "category":"Retail",
            "subcategory":"Repair Shop",
            "type":"Services"
        }
    ],
    "sg:phone":"+1 360 693 8240",
    "sg:postcode":"98664",
    "sg:province":"WA",
    "wof:name":"Dons Small Engine Repair",
    "wof:placetype":"venue"
},
  "geometry": {"coordinates":[-122.589468,45.63197],"type":"Point"}
}