{
  "type": "Feature",
  "properties": {
    "addr:full":"8613 Roosevelt Way NE Seattle WA 98115",
    "addr:housenumber":"8613",
    "addr:postcode":"98115",
    "addr:street":"Roosevelt Way Ne",
    "iso:country":"US",
    "sg:address":"8613 Roosevelt Way NE",
    "sg:city":"Seattle",
    "sg:classifiers":[
        {
            "category":"Building & Trades",
            "subcategory":"Cleaning & Sanitation",
            "type":"Services"
        },
        {
            "category":"Personal",
            "type":"Services"
        }
    ],
    "sg:phone":"+1 206 527 2984",
    "sg:postcode":"98115",
    "sg:province":"WA",
    "sg:tags":[
        "maids'",
        "house",
        "contractor",
        "window",
        "butlers'",
        "home"
    ],
    "sg:website":"www.merrymaids.com/",
    "wof:name":"Merry Maids",
    "wof:placetype":"venue"
},
  "geometry": {"coordinates":[-122.318001,47.6917],"type":"Point"}
}