{
  "type": "Feature",
  "properties": {
    "addr:full":"703 S Wenatchee Ave Wenatchee WA 98801",
    "addr:housenumber":"703",
    "addr:postcode":"98801",
    "addr:street":"S Wenatchee Ave",
    "iso:country":"US",
    "sg:address":"703 S Wenatchee Ave",
    "sg:city":"Wenatchee",
    "sg:classifiers":[
        {
            "category":"Wholesale",
            "subcategory":"Non-durable Goods",
            "type":"Manufacturing & Wholesale Goods"
        }
    ],
    "sg:phone":"+1 509 664 8943",
    "sg:postcode":"98801",
    "sg:province":"WA",
    "sg:tags":[
        "canvas"
    ],
    "wof:name":"A Custom Canvas Shop",
    "wof:placetype":"venue"
},
  "geometry": {"coordinates":[-120.302684,47.413995],"type":"Point"}
}