{
  "type": "Feature",
  "properties": {
    "addr:full":"3802 Broadway Everett WA 98201",
    "addr:housenumber":"3802",
    "addr:postcode":"98201",
    "addr:street":"Broadway",
    "iso:country":"US",
    "sg:address":"3802 Broadway",
    "sg:city":"Everett",
    "sg:classifiers":[
        {
            "category":"Recreation",
            "type":"Entertainment"
        }
    ],
    "sg:phone":"+1 425 258 3673",
    "sg:postcode":"98201",
    "sg:province":"WA",
    "sg:tags":[
        "club",
        "baseball"
    ],
    "sg:website":"www.aquasox.com",
    "wof:name":"Everett Aquasox Baseball",
    "wof:placetype":"venue"
},
  "geometry": {"coordinates":[-122.201106,47.966164],"type":"Point"}
}