{
  "type": "Feature",
  "properties": {
    "addr:full":"9165 151st Ave NE Redmond WA 98052",
    "addr:housenumber":"9165",
    "addr:postcode":"98052",
    "addr:street":"151St Ave Ne",
    "iso:country":"US",
    "sg:address":"9165 151st Ave NE",
    "sg:city":"Redmond",
    "sg:classifiers":[
        {
            "category":"Manufacturing",
            "subcategory":"Metals",
            "type":"Manufacturing & Wholesale Goods"
        }
    ],
    "sg:phone":"+1 425 881 7300",
    "sg:postcode":"98052",
    "sg:province":"WA",
    "sg:tags":[
        "finisher",
        "medical",
        "equipment",
        "electrical",
        "painting",
        "display"
    ],
    "wof:name":"Finishing Unlimited Inc",
    "wof:placetype":"venue"
},
  "geometry": {"coordinates":[-122.139403,47.682573],"type":"Point"}
}