{
  "type": "Feature",
  "properties": {
    "addr:full":"2803 S Inland Empire Way Spokane WA 99224",
    "addr:housenumber":"2803",
    "addr:postcode":"99224",
    "addr:street":"S Inland Empire Way",
    "iso:country":"US",
    "sg:address":"2803 S Inland Empire Way",
    "sg:city":"Spokane",
    "sg:classifiers":[
        {
            "category":"Personal",
            "type":"Services"
        },
        {
            "category":"Professional",
            "subcategory":"Art Services",
            "type":"Services"
        }
    ],
    "sg:phone":"+1 509 456 8724",
    "sg:postcode":"99224",
    "sg:province":"WA",
    "sg:tags":[
        "photography",
        "videography",
        "wedding"
    ],
    "wof:name":"Mckinnon Professional",
    "wof:placetype":"venue"
},
  "geometry": {"coordinates":[-117.440776,47.62864],"type":"Point"}
}