{
  "type": "Feature",
  "properties": {
    "addr:full":"12204 N Division St Spokane WA 99218",
    "addr:housenumber":"12204",
    "addr:postcode":"99218",
    "addr:street":"N Division St",
    "iso:country":"US",
    "sg:address":"12204 N Division St",
    "sg:city":"Spokane",
    "sg:classifiers":[
        {
            "category":"Personal",
            "subcategory":"Beauty Salon",
            "type":"Services"
        }
    ],
    "sg:phone":"+1 509 467 3158",
    "sg:postcode":"99218",
    "sg:province":"WA",
    "wof:name":"Fantastic Sam's",
    "wof:placetype":"venue"
},
  "geometry": {"coordinates":[-117.406176,47.764121],"type":"Point"}
}