{
  "type": "Feature",
  "properties": {
    "addr:full":"206 W Cedar St Sequim WA 98382",
    "addr:housenumber":"206",
    "addr:postcode":"98382",
    "addr:street":"W Cedar St",
    "iso:country":"US",
    "sg:address":"206 W Cedar St",
    "sg:city":"Sequim",
    "sg:classifiers":[
        {
            "category":"Professional",
            "subcategory":"Lawyer & Legal Services",
            "type":"Services"
        }
    ],
    "sg:phone":"+1 360 683 7705",
    "sg:postcode":"98382",
    "sg:province":"WA",
    "sg:tags":[
        "attorney"
    ],
    "wof:name":"Johnson Rutz & Tassie",
    "wof:placetype":"venue"
},
  "geometry": {"coordinates":[-123.105114,48.080645],"type":"Point"}
}