{
  "type": "Feature",
  "properties": {
    "addr:full":"261293 Hwy 101 Sequim WA 98382",
    "addr:housenumber":"261293",
    "addr:postcode":"98382",
    "addr:street":"Hwy 101",
    "iso:country":"US",
    "sg:address":"261293 Hwy 101",
    "sg:city":"Sequim",
    "sg:classifiers":[
        {
            "category":"Autos & Motor Vehicles",
            "subcategory":"Automobile Sales",
            "type":"Retail Goods"
        }
    ],
    "sg:phone":"+1 360 683 1719",
    "sg:postcode":"98382",
    "sg:province":"WA",
    "sg:tags":[
        "used"
    ],
    "wof:name":"Courtesy Automax",
    "wof:placetype":"venue"
},
  "geometry": {"coordinates":[-123.172556,48.079526],"type":"Point"}
}