{
  "type": "Feature",
  "properties": {
    "addr:full":"10718 SW Sylvan Beach Rd Vashon WA 98070",
    "addr:housenumber":"10718",
    "addr:postcode":"98070",
    "addr:street":"Sw Sylvan Beach Rd",
    "iso:country":"US",
    "sg:address":"10718 SW Sylvan Beach Rd",
    "sg:city":"Vashon",
    "sg:classifiers":[
        {
            "category":"Wholesale",
            "subcategory":"Machinery & Supplies",
            "type":"Manufacturing & Wholesale Goods"
        }
    ],
    "sg:phone":"+1 206 567 5690",
    "sg:postcode":"98070",
    "sg:province":"WA",
    "sg:tags":[
        "industrial",
        "equipment",
        "used",
        "machinery-new",
        "supplies-wholesale"
    ],
    "wof:name":"Raymondstone Inc.",
    "wof:placetype":"venue"
},
  "geometry": {"coordinates":[-122.47022800000001,47.494811],"type":"Point"}
}