{
  "type": "Feature",
  "properties": {
    "addr:full":"16812 Colony Rd Bow WA 98232",
    "addr:housenumber":"16812",
    "addr:postcode":"98232",
    "addr:street":"Colony Rd",
    "iso:country":"US",
    "sg:address":"16812 Colony Rd",
    "sg:city":"Bow",
    "sg:classifiers":[
        {
            "category":"Building & Trades",
            "subcategory":"Landscaping Services",
            "type":"Services"
        }
    ],
    "sg:phone":"+1 360 708 1360",
    "sg:postcode":"98232",
    "sg:province":"WA",
    "wof:name":"Northwest Lawn Care",
    "wof:placetype":"venue"
},
  "geometry": {"coordinates":[-122.37996699999999,48.573288],"type":"Point"}
}