{
  "type": "Feature",
  "properties": {
    "addr:full":"1611 SE Commerce Ave Battle Ground WA 98604",
    "addr:housenumber":"1611",
    "addr:postcode":"98604",
    "addr:street":"Se Commerce Ave",
    "iso:country":"US",
    "sg:address":"1611 SE Commerce Ave",
    "sg:city":"Battle Ground",
    "sg:classifiers":[
        {
            "category":"Home & Garden",
            "subcategory":"Building Materials",
            "type":"Retail Goods"
        }
    ],
    "sg:phone":"+1 360 816 7763",
    "sg:postcode":"98604",
    "sg:province":"WA",
    "wof:name":"Western Glass Corp",
    "wof:placetype":"venue"
},
  "geometry": {"coordinates":[-122.52154899999999,45.768659],"type":"Point"}
}