{
  "type": "Feature",
  "properties": {
    "addr:full":"330 NW 77th St Seattle WA 98117",
    "addr:housenumber":"330",
    "addr:postcode":"98117",
    "addr:street":"Nw 77Th St",
    "iso:country":"US",
    "sg:address":"330 NW 77th St",
    "sg:city":"Seattle",
    "sg:classifiers":[
        {
            "category":"Manufacturing",
            "subcategory":"Textiles",
            "type":"Manufacturing & Wholesale Goods"
        }
    ],
    "sg:phone":"+1 206 784 3011",
    "sg:postcode":"98117",
    "sg:province":"WA",
    "wof:name":"Bellflower Textiles",
    "wof:placetype":"venue"
},
  "geometry": {"coordinates":[-122.361451,47.684738],"type":"Point"}
}