{
  "type": "Feature",
  "properties": {
    "addr:full":"17601 Vashon Hwy SW Vashon WA 98070",
    "addr:housenumber":"17601",
    "addr:postcode":"98070",
    "addr:street":"Vashon Hwy Sw",
    "iso:country":"US",
    "sg:address":"17601 Vashon Hwy SW",
    "sg:city":"Vashon",
    "sg:classifiers":[
        {
            "category":"Restaurant",
            "type":"Food & Drink"
        }
    ],
    "sg:phone":"+1 206 463 1800",
    "sg:postcode":"98070",
    "sg:province":"WA",
    "sg:website":"http://www.thsrestaurant.com",
    "wof:name":"The Hardware Store Restaurant",
    "wof:placetype":"venue"
},
  "geometry": {"coordinates":[-122.460503,47.447411],"type":"Point"}
}