{
  "type": "Feature",
  "properties": {
    "addr:full":"1278 Chestnut St Clarkston WA 99403",
    "addr:housenumber":"1278",
    "addr:postcode":"99403",
    "addr:street":"Chestnut St",
    "iso:country":"US",
    "sg:address":"1278 Chestnut St",
    "sg:city":"Clarkston",
    "sg:classifiers":[
        {
            "category":"Social Services",
            "subcategory":"Child Care",
            "type":"Services"
        }
    ],
    "sg:phone":"+1 509 758 3442",
    "sg:postcode":"99403",
    "sg:province":"WA",
    "sg:tags":[
        "day"
    ],
    "wof:name":"Lewis-Clark Erly Chldhd Progra",
    "wof:placetype":"venue"
},
  "geometry": {"coordinates":[-117.058072,46.410944],"type":"Point"}
}