{
  "type": "Feature",
  "properties": {
    "addr:full":"1221 2nd Ave Ste 320 Seattle WA 98101",
    "addr:housenumber":"1221",
    "addr:postcode":"98101",
    "addr:street":"2Nd Ave Ste 320",
    "iso:country":"US",
    "sg:address":"1221 2nd Ave Ste 320",
    "sg:city":"Seattle",
    "sg:classifiers":[
        {
            "category":"Banks & Credit Unions",
            "subcategory":"Investment Brokerage",
            "type":"Services"
        }
    ],
    "sg:phone":"+1 206 838 4880",
    "sg:postcode":"98101",
    "sg:province":"WA",
    "sg:tags":[
        "investing"
    ],
    "sg:website":"www.pioneersquareadvisors.com",
    "wof:name":"Pioneer Square Advisors Llc",
    "wof:placetype":"venue"
},
  "geometry": {"coordinates":[-122.33671699999999,47.606673],"type":"Point"}
}