{
  "type": "Feature",
  "properties": {
    "addr:full":"2109 W 7th St Port Angeles WA 98363",
    "addr:housenumber":"2109",
    "addr:postcode":"98363",
    "addr:street":"W 7Th St",
    "iso:country":"US",
    "sg:address":"2109 W 7th St",
    "sg:city":"Port Angeles",
    "sg:classifiers":[
        {
            "category":"Social Services",
            "type":"Services"
        }
    ],
    "sg:phone":"+1 360 457 6281",
    "sg:postcode":"98363",
    "sg:province":"WA",
    "wof:name":"Litton Family Services",
    "wof:placetype":"venue"
},
  "geometry": {"coordinates":[-123.47883,48.130543],"type":"Point"}
}