{
  "type": "Feature",
  "properties": {
    "addr:full":"706 George Washington Way Richland WA 99352",
    "addr:housenumber":"706",
    "addr:postcode":"99352",
    "addr:street":"George Washington Way",
    "iso:country":"US",
    "sg:address":"706 George Washington Way",
    "sg:city":"Richland",
    "sg:classifiers":[
        {
            "category":"Health Services",
            "subcategory":"Optometrist",
            "type":"Services"
        }
    ],
    "sg:phone":"+1 509 943 3171",
    "sg:postcode":"99352",
    "sg:province":"WA",
    "wof:name":"Heaston & Thompson Vision Clnc",
    "wof:placetype":"venue"
},
  "geometry": {"coordinates":[-119.27363800000001,46.276523],"type":"Point"}
}