{
  "type": "Feature",
  "properties": {
    "addr:full":"702 N Karl Johan Ave Tacoma WA 98406",
    "addr:housenumber":"702",
    "addr:postcode":"98406",
    "addr:street":"N Karl Johan Ave",
    "iso:country":"US",
    "sg:address":"702 N Karl Johan Ave",
    "sg:city":"Tacoma",
    "sg:classifiers":[
        {
            "category":"Professional",
            "type":"Services"
        }
    ],
    "sg:phone":"+1 253 752 0149",
    "sg:postcode":"98406",
    "sg:province":"WA",
    "sg:tags":[
        "consulting",
        "chemist"
    ],
    "wof:name":"Northwest Marine Chemist Inc",
    "wof:placetype":"venue"
},
  "geometry": {"coordinates":[-122.540451,47.254402],"type":"Point"}
}