{
  "type": "Feature",
  "properties": {
    "addr:full":"2332 165th Pl SE Bothell WA 98012",
    "addr:housenumber":"2332",
    "addr:postcode":"98012",
    "addr:street":"165Th Pl Se",
    "iso:country":"US",
    "sg:address":"2332 165th Pl SE",
    "sg:city":"Bothell",
    "sg:classifiers":[
        {
            "category":"Professional",
            "type":"Services"
        }
    ],
    "sg:phone":"+1 425 482 2382",
    "sg:postcode":"98012",
    "sg:province":"WA",
    "wof:name":"Chaparral Labs Inc",
    "wof:placetype":"venue"
},
  "geometry": {"coordinates":[-122.199285,47.848325],"type":"Point"}
}