{
  "type": "Feature",
  "properties": {
    "addr:full":"11413 NE 76th St Vancouver WA 98662",
    "addr:housenumber":"11413",
    "addr:postcode":"98662",
    "addr:street":"Ne 76Th St",
    "iso:country":"US",
    "sg:address":"11413 NE 76th St",
    "sg:city":"Vancouver",
    "sg:classifiers":[
        {
            "category":"Home & Garden",
            "subcategory":"Building Materials",
            "type":"Retail Goods"
        }
    ],
    "sg:phone":"+1 360 260 2120",
    "sg:postcode":"98662",
    "sg:province":"WA",
    "wof:name":"Lowes",
    "wof:placetype":"venue"
},
  "geometry": {"coordinates":[-122.55577599999999,45.677721],"type":"Point"}
}