{
  "type": "Feature",
  "properties": {
    "addr:full":"4424 Chennault Beach Rd Mukilteo WA 98275",
    "addr:housenumber":"4424",
    "addr:postcode":"98275",
    "addr:street":"Chennault Beach Rd",
    "iso:country":"US",
    "sg:address":"4424 Chennault Beach Rd",
    "sg:city":"Mukilteo",
    "sg:classifiers":[
        {
            "category":"Recreation",
            "type":"Entertainment"
        },
        {
            "category":"Wholesale",
            "subcategory":"Non-durable Goods",
            "type":"Manufacturing & Wholesale Goods"
        }
    ],
    "sg:phone":"+1 425 315 8815",
    "sg:postcode":"98275",
    "sg:province":"WA",
    "sg:tags":[
        "bingo",
        "game"
    ],
    "sg:website":"www.wowdistributing.com",
    "wof:name":"Wow Distributing Inc",
    "wof:placetype":"venue"
},
  "geometry": {"coordinates":[-122.29488499999999,47.896403],"type":"Point"}
}