{
  "type": "Feature",
  "properties": {
    "addr:full":"800 5th Ave Seattle WA 98104",
    "addr:housenumber":"800",
    "addr:postcode":"98104",
    "addr:street":"5Th Ave",
    "iso:country":"US",
    "sg:address":"800 5th Ave",
    "sg:city":"Seattle",
    "sg:classifiers":[
        {
            "category":"Personal",
            "subcategory":"Beauty Salon",
            "type":"Services"
        }
    ],
    "sg:phone":"+1 206 652 9920",
    "sg:postcode":"98104",
    "sg:province":"WA",
    "sg:tags":[
        "hair"
    ],
    "wof:name":"Seattle Hair Works",
    "wof:placetype":"venue"
},
  "geometry": {"coordinates":[-122.33056000000001,47.605169],"type":"Point"}
}