{
  "type": "Feature",
  "properties": {
    "addr:full":"111 N 13th St Selah WA 98942",
    "addr:housenumber":"111",
    "addr:postcode":"98942",
    "addr:street":"N 13Th St",
    "iso:country":"US",
    "sg:address":"111 N 13th St",
    "sg:city":"Selah",
    "sg:classifiers":[
        {
            "category":"Professional",
            "subcategory":"Testing Lab",
            "type":"Services"
        }
    ],
    "sg:phone":"+1 509 698 5676",
    "sg:postcode":"98942",
    "sg:province":"WA",
    "sg:tags":[
        "device",
        "flow",
        "back"
    ],
    "wof:name":"Trout's Quality Water Svc",
    "wof:placetype":"venue"
},
  "geometry": {"coordinates":[-120.546722,46.655996],"type":"Point"}
}