{
  "type": "Feature",
  "properties": {
    "addr:full":"602 Valley St Seattle WA 98109",
    "addr:housenumber":"602",
    "addr:postcode":"98109",
    "addr:street":"Valley St",
    "iso:country":"US",
    "sg:address":"602 Valley St",
    "sg:city":"Seattle",
    "sg:classifiers":[
        {
            "category":"Social Services",
            "subcategory":"Child Care",
            "type":"Services"
        }
    ],
    "sg:phone":"+1 206 282 9265",
    "sg:postcode":"98109",
    "sg:province":"WA",
    "wof:name":"City Foursquare Child Dev Ctr",
    "wof:placetype":"venue"
},
  "geometry": {"coordinates":[-122.34370199999999,47.626341],"type":"Point"}
}