{
  "type": "Feature",
  "properties": {
    "addr:full":"17621 Elhi Rim Rd E Sumner WA 98391",
    "addr:housenumber":"17621",
    "addr:postcode":"98391",
    "addr:street":"Elhi Rim Rd E",
    "iso:country":"US",
    "sg:address":"17621 Elhi Rim Rd E",
    "sg:city":"Sumner",
    "sg:classifiers":[
        {
            "category":"Banks & Credit Unions",
            "subcategory":"Financial Services",
            "type":"Services"
        }
    ],
    "sg:phone":"+1 253 863 3169",
    "sg:postcode":"98391",
    "sg:province":"WA",
    "sg:tags":[
        "investor"
    ],
    "wof:name":"TW Investors",
    "wof:placetype":"venue"
},
  "geometry": {"coordinates":[-122.18907,47.178384],"type":"Point"}
}