{
  "type": "Feature",
  "properties": {
    "addr:full":"114 W Main St Monroe WA 98272",
    "addr:housenumber":"114",
    "addr:postcode":"98272",
    "addr:street":"W Main St",
    "iso:country":"US",
    "sg:address":"114 W Main St",
    "sg:city":"Monroe",
    "sg:classifiers":[
        {
            "category":"Health Services",
            "subcategory":"Doctor",
            "type":"Services"
        }
    ],
    "sg:phone":"+1 360 794 8580",
    "sg:postcode":"98272",
    "sg:province":"WA",
    "sg:tags":[
        "house",
        "construction"
    ],
    "wof:name":"Phil M Aronson DDS",
    "wof:placetype":"venue"
},
  "geometry": {"coordinates":[-121.970934,47.855621],"type":"Point"}
}