{
  "type": "Feature",
  "properties": {
    "addr:full":"15169 Summers Dr Mount Vernon WA 98273",
    "addr:housenumber":"15169",
    "addr:postcode":"98273",
    "addr:street":"Summers Dr",
    "iso:country":"US",
    "sg:address":"15169 Summers Dr",
    "sg:city":"Mount Vernon",
    "sg:classifiers":[
        {
            "category":"Building & Trades",
            "subcategory":"Construction",
            "type":"Services"
        }
    ],
    "sg:phone":"+1 360 466 4550",
    "sg:postcode":"98273",
    "sg:province":"WA",
    "sg:tags":[
        "house"
    ],
    "wof:name":"Carlson Construction Inc",
    "wof:placetype":"venue"
},
  "geometry": {"coordinates":[-122.41796100000001,48.36601],"type":"Point"}
}