{
  "type": "Feature",
  "properties": {
    "addr:full":"6024 79th St E Puyallup WA 98371",
    "addr:housenumber":"6024",
    "addr:postcode":"98371",
    "addr:street":"79Th St E",
    "iso:country":"US",
    "sg:address":"6024 79th St E",
    "sg:city":"Puyallup",
    "sg:classifiers":[
        {
            "category":"Real Estate",
            "subcategory":"Real Estate Operator",
            "type":"Services"
        }
    ],
    "sg:phone":"+1 253 845 5525",
    "sg:postcode":"98371",
    "sg:province":"WA",
    "sg:tags":[
        "mobile",
        "home",
        "site"
    ],
    "wof:name":"Crestview Mobile Manor",
    "wof:placetype":"venue"
},
  "geometry": {"coordinates":[-122.34863199999999,47.185264],"type":"Point"}
}