{
  "type": "Feature",
  "properties": {
    "addr:full":"3824 Bridgeport Way W University Place WA 98466",
    "addr:housenumber":"3824",
    "addr:postcode":"98466",
    "addr:street":"Bridgeport Way W;Place",
    "iso:country":"US",
    "sg:address":"3824 Bridgeport Way W",
    "sg:city":"University Place",
    "sg:classifiers":[
        {
            "category":"Shopping",
            "subcategory":"Gifts & Souvenirs",
            "type":"Retail Goods"
        }
    ],
    "sg:phone":"+1 253 565 5121",
    "sg:postcode":"98466",
    "sg:province":"WA",
    "sg:tags":[
        "shop"
    ],
    "wof:name":"Mc Bride's Hallmark",
    "wof:placetype":"venue"
},
  "geometry": {"coordinates":[-122.53715699999999,47.223196],"type":"Point"}
}