{
  "type": "Feature",
  "properties": {
    "addr:full":"22503 4th Ave SE Bothell WA 98021",
    "addr:housenumber":"22503",
    "addr:postcode":"98021",
    "addr:street":"4Th Ave Se",
    "iso:country":"US",
    "sg:address":"22503 4th Ave SE",
    "sg:city":"Bothell",
    "sg:classifiers":[
        {
            "category":"Manufacturing",
            "subcategory":"Retail Goods",
            "type":"Manufacturing & Wholesale Goods"
        }
    ],
    "sg:phone":"+1 425 892 0419",
    "sg:postcode":"98021",
    "sg:province":"WA",
    "sg:tags":[
        "product",
        "mfg"
    ],
    "wof:name":"Misty Valley Designs",
    "wof:placetype":"venue"
},
  "geometry": {"coordinates":[-122.22623900000001,47.791974],"type":"Point"}
}