{
  "type": "Feature",
  "properties": {
    "iso:country":"US",
    "sg:address":"4001 Capitol Mall Dr SW",
    "sg:city":"Olympia",
    "sg:classifiers":[
        {
            "category":"Health Services",
            "subcategory":"Nursing And Care Facility",
            "type":"Services"
        }
    ],
    "sg:phone":"+1 360 754 9792",
    "sg:postcode":"98502",
    "sg:province":"WA",
    "sg:tags":[
        "home",
        "skilled",
        "convalescent"
    ],
    "sg:website":"www.extendicare.com",
    "wof:name":"Puget Sound Health Care Center",
    "wof:placetype":"venue"
},
  "geometry": {"coordinates":[-122.95273,47.041727],"type":"Point"}
}