{
  "type": "Feature",
  "properties": {
    "addr:full":"619 Broadway E Seattle WA 98102",
    "addr:housenumber":"619",
    "addr:postcode":"98102",
    "addr:street":"Broadway",
    "iso:country":"US",
    "sg:address":"619 Broadway E",
    "sg:city":"Seattle",
    "sg:classifiers":[
        {
            "category":"Personal",
            "subcategory":"Massage",
            "type":"Services"
        }
    ],
    "sg:phone":"+1 206 568 3771",
    "sg:postcode":"98102",
    "sg:province":"WA",
    "sg:website":"www.dreamscapemassage.com",
    "wof:name":"Dreamscape Massage",
    "wof:placetype":"venue"
},
  "geometry": {"coordinates":[-122.32128400000001,47.625112],"type":"Point"}
}