{
  "type": "Feature",
  "properties": {
    "addr:full":"14460 SE 224th St Kent WA 98042",
    "addr:postcode":"14460;98042",
    "addr:street":"Se 224Th St",
    "iso:country":"US",
    "sg:address":"14460 SE 224th St",
    "sg:city":"Kent",
    "sg:classifiers":[
        {
            "category":"Building & Trades",
            "subcategory":"Construction",
            "type":"Services"
        }
    ],
    "sg:phone":"+1 253 639 2088",
    "sg:postcode":"98042",
    "sg:province":"WA",
    "sg:tags":[
        "wallpaper"
    ],
    "wof:name":"A-1 Pro Wallpapering By Janet",
    "wof:placetype":"venue"
},
  "geometry": {"coordinates":[-122.146826,47.401041],"type":"Point"}
}