{
  "type": "Feature",
  "properties": {
    "addr:full":"6602 NE St Johns Rd Vancouver WA 98661",
    "addr:housenumber":"6602",
    "addr:postcode":"98661",
    "addr:street":"Ne St Johns Rd",
    "iso:country":"US",
    "sg:address":"6602 NE St Johns Rd",
    "sg:city":"Vancouver",
    "sg:classifiers":[
        {
            "category":"Retail",
            "subcategory":"Auto Repair",
            "type":"Services"
        }
    ],
    "sg:phone":"+1 360 695 6144",
    "sg:postcode":"98661",
    "sg:province":"WA",
    "sg:tags":[
        "repairing",
        "automobile"
    ],
    "wof:name":"Integrity Automotive",
    "wof:placetype":"venue"
},
  "geometry": {"coordinates":[-122.636625,45.670229],"type":"Point"}
}