{
  "type": "Feature",
  "properties": {
    "addr:full":"5221 Ballard Ave NW Seattle WA 98107",
    "addr:housenumber":"5221",
    "addr:postcode":"98107",
    "addr:street":"Ballard Ave Nw",
    "iso:country":"US",
    "sg:address":"5221 Ballard Ave NW",
    "sg:city":"Seattle",
    "sg:classifiers":[
        {
            "category":"Parking",
            "type":"Transportation"
        }
    ],
    "sg:phone":"+1 206 783 4144",
    "sg:postcode":"98107",
    "sg:province":"WA",
    "sg:tags":[
        "automobile",
        "management"
    ],
    "wof:name":"Republic Parking",
    "wof:placetype":"venue"
},
  "geometry": {"coordinates":[-122.383099,47.666166],"type":"Point"}
}