{
  "type": "Feature",
  "properties": {
    "addr:full":"18154 W Stackpole Rd Mount Vernon WA 98273",
    "addr:housenumber":"18154",
    "addr:postcode":"98273",
    "addr:street":"W Stackpole Rd",
    "iso:country":"US",
    "sg:address":"18154 W Stackpole Rd",
    "sg:city":"Mount Vernon",
    "sg:phone":"+1 360 424 5850",
    "sg:postcode":"98273",
    "sg:province":"WA",
    "sg:tags":[
        "vegetable",
        "farm"
    ],
    "wof:name":"Smith & Burkland Farms Inc",
    "wof:placetype":"venue"
},
  "geometry": {"coordinates":[-122.35426699999999,48.370273],"type":"Point"}
}