{
  "type": "Feature",
  "properties": {
    "addr:full":"125 Van Scoyoc Ave SW Orting WA 98360",
    "addr:housenumber":"125",
    "addr:postcode":"98360",
    "addr:street":"Van Scoyoc Ave Sw",
    "iso:country":"US",
    "sg:address":"125 Van Scoyoc Ave SW",
    "sg:city":"Orting",
    "sg:classifiers":[
        {
            "category":"Shopping",
            "subcategory":"Crafts & Fabrics",
            "type":"Retail Goods"
        }
    ],
    "sg:phone":"+1 360 893 0202",
    "sg:postcode":"98360",
    "sg:province":"WA",
    "sg:tags":[
        "material",
        "quilting",
        "supply"
    ],
    "wof:name":"Wild Rose",
    "wof:placetype":"venue"
},
  "geometry": {"coordinates":[-122.20383200000001,47.096728],"type":"Point"}
}