{
  "type": "Feature",
  "properties": {
    "addr:full":"3971 Dixie Ln Malaga WA 98828",
    "addr:housenumber":"3971",
    "addr:postcode":"98828",
    "addr:street":"Dixie Ln",
    "iso:country":"US",
    "sg:address":"3971 Dixie Ln",
    "sg:city":"Malaga",
    "sg:classifiers":[
        {
            "category":"Social Services",
            "subcategory":"Child Care",
            "type":"Services"
        }
    ],
    "sg:phone":"+1 509 665 8800",
    "sg:postcode":"98828",
    "sg:province":"WA",
    "sg:tags":[
        "day"
    ],
    "wof:name":"Super Kids Childcare Preschool",
    "wof:placetype":"venue"
},
  "geometry": {"coordinates":[-120.198747,47.366019],"type":"Point"}
}