{
  "type": "Feature",
  "properties": {
    "addr:full":"307 Bell St Edmonds WA 98020",
    "addr:housenumber":"307",
    "addr:postcode":"98020",
    "addr:street":"Bell",
    "iso:country":"US",
    "sg:address":"307 Bell St",
    "sg:city":"Edmonds",
    "sg:classifiers":[
        {
            "category":"Health Services",
            "subcategory":"Health Practitioner",
            "type":"Services"
        }
    ],
    "sg:phone":"+1 206 412 8812",
    "sg:postcode":"98020",
    "sg:province":"WA",
    "wof:name":"Vital Capacity",
    "wof:placetype":"venue"
},
  "geometry": {"coordinates":[-122.377681,47.812099],"type":"Point"}
}