{
  "type": "Feature",
  "properties": {
    "addr:full":"170 Coulson Rd Chehalis WA 98532",
    "addr:housenumber":"170",
    "addr:postcode":"98532",
    "addr:street":"Coulson Rd",
    "iso:country":"US",
    "sg:address":"170 Coulson Rd",
    "sg:city":"Chehalis",
    "sg:classifiers":[
        {
            "category":"Real Estate",
            "subcategory":"Architect",
            "type":"Services"
        }
    ],
    "sg:phone":"+1 360 266 0781",
    "sg:postcode":"98532",
    "sg:province":"WA",
    "sg:tags":[
        "architectural"
    ],
    "wof:name":"A Plus Designs",
    "wof:placetype":"venue"
},
  "geometry": {"coordinates":[-122.85576500000001,46.574291],"type":"Point"}
}