{
  "type": "Feature",
  "properties": {
    "addr:full":"1418 6th St Sedro Woolley WA 98284",
    "addr:housenumber":"1418",
    "addr:postcode":"98284",
    "addr:street":"6Th St",
    "iso:country":"US",
    "sg:address":"1418 6th St",
    "sg:city":"Sedro Woolley",
    "sg:classifiers":[
        {
            "category":"Manufacturing",
            "subcategory":"Lumber",
            "type":"Manufacturing & Wholesale Goods"
        }
    ],
    "sg:phone":"+1 360 855 0389",
    "sg:postcode":"98284",
    "sg:province":"WA",
    "sg:tags":[
        "construction",
        "logging",
        "road"
    ],
    "wof:name":"Select Logging & Road Building",
    "wof:placetype":"venue"
},
  "geometry": {"coordinates":[-122.231787,48.498694],"type":"Point"}
}