{
  "type": "Feature",
  "properties": {
    "addr:full":"11844 SE 157th Pl Renton WA 98058",
    "addr:housenumber":"11844",
    "addr:postcode":"98058",
    "addr:street":"Se 157Th Pl",
    "iso:country":"US",
    "sg:address":"11844 SE 157th Pl",
    "sg:city":"Renton",
    "sg:classifiers":[
        {
            "category":"Banks & Credit Unions",
            "subcategory":"Bureau De Change",
            "type":"Services"
        }
    ],
    "sg:phone":"+1 425 235 3197",
    "sg:postcode":"98058",
    "sg:province":"WA",
    "sg:tags":[
        "factor"
    ],
    "wof:name":"Kl Note Funding",
    "wof:placetype":"venue"
},
  "geometry": {"coordinates":[-122.181234,47.462312],"type":"Point"}
}