{
  "type": "Feature",
  "properties": {
    "addr:full":"1270 80th Pl NE Medina WA 98039",
    "addr:housenumber":"1270",
    "addr:postcode":"98039",
    "addr:street":"80Th Pl Ne Medina",
    "iso:country":"US",
    "sg:address":"1270 80th Pl NE",
    "sg:city":"Medina",
    "sg:classifiers":[
        {
            "category":"Building & Trades",
            "subcategory":"Construction",
            "type":"Services"
        }
    ],
    "sg:phone":"+1 425 454 1793",
    "sg:postcode":"98039",
    "sg:province":"WA",
    "sg:tags":[
        "house"
    ],
    "wof:name":"Potuzak Construction Inc",
    "wof:placetype":"venue"
},
  "geometry": {"coordinates":[-122.233234,47.62127],"type":"Point"}
}