{
  "type": "Feature",
  "properties": {
    "addr:full":"8312 39th Ave S Seattle WA 98118",
    "addr:housenumber":"8312",
    "addr:postcode":"98118",
    "addr:street":"39Th Ave S",
    "iso:country":"US",
    "sg:address":"8312 39th Ave S",
    "sg:city":"Seattle",
    "sg:classifiers":[
        {
            "category":"Wholesale",
            "subcategory":"Durable Goods & Equipment",
            "type":"Manufacturing & Wholesale Goods"
        }
    ],
    "sg:phone":"+1 206 240 7415",
    "sg:postcode":"98118",
    "sg:province":"WA",
    "wof:name":"Kashmir Best Collection",
    "wof:placetype":"venue"
},
  "geometry": {"coordinates":[-122.283621,47.528701],"type":"Point"}
}