{
  "type": "Feature",
  "properties": {
    "addr:full":"1906 B St Washougal WA 98671",
    "addr:housenumber":"1906",
    "addr:postcode":"98671",
    "addr:street":"B St",
    "iso:country":"US",
    "sg:address":"1906 B St",
    "sg:city":"Washougal",
    "sg:classifiers":[
        {
            "category":"Personal",
            "type":"Services"
        }
    ],
    "sg:phone":"+1 360 335 1416",
    "sg:postcode":"98671",
    "sg:province":"WA",
    "wof:name":"Rikky Joes Tattoo",
    "wof:placetype":"venue"
},
  "geometry": {"coordinates":[-122.351744,45.578431],"type":"Point"}
}