{
  "type": "Feature",
  "properties": {
    "addr:full":"468 228th Ave NE Sammamish WA 98074",
    "addr:housenumber":"468",
    "addr:postcode":"98074",
    "addr:street":"228Th Ave Ne",
    "iso:country":"US",
    "sg:address":"468 228th Ave NE",
    "sg:city":"Sammamish",
    "sg:classifiers":[
        {
            "category":"Professional",
            "subcategory":"Accounting & Tax Preparation",
            "type":"Services"
        },
        {
            "category":"Banks & Credit Unions",
            "subcategory":"Financial Services",
            "type":"Services"
        }
    ],
    "sg:phone":"+1 425 868 3489",
    "sg:postcode":"98074",
    "sg:province":"WA",
    "sg:tags":[
        "return",
        "preparation-business",
        "taxes-consultants",
        "loan",
        "reporting",
        "representative",
        "alternative",
        "bookkeeping"
    ],
    "sg:website":"http://www.hrblock.com",
    "wof:name":"H&R Block",
    "wof:placetype":"venue"
},
  "geometry": {"coordinates":[-122.03549599999999,47.613441],"type":"Point"}
}