{
  "type": "Feature",
  "properties": {
    "addr:full":"1415 5th Ave Ste 5 Seattle WA 98101",
    "addr:housenumber":"1415",
    "addr:postcode":"98101",
    "addr:street":"5Th Ave Ste 5",
    "iso:country":"US",
    "sg:address":"1415 5th Ave Ste 5",
    "sg:city":"Seattle",
    "sg:classifiers":[
        {
            "category":"Restaurant",
            "type":"Food & Drink"
        }
    ],
    "sg:phone":"+1 206 971 8010",
    "sg:postcode":"98101",
    "sg:province":"WA",
    "sg:tags":[
        "lunch",
        "seafood",
        "brunch",
        "american",
        "breakfast"
    ],
    "wof:name":"Terrace Garden Restaurant",
    "wof:placetype":"venue"
},
  "geometry": {"coordinates":[-122.334808,47.609806],"type":"Point"}
}