{
  "type": "Feature",
  "properties": {
    "addr:full":"1510 S Liberty Dr Liberty Lake WA 99019",
    "addr:housenumber":"1510",
    "addr:postcode":"99019",
    "addr:street":"S Liberty Dr",
    "iso:country":"US",
    "sg:address":"1510 S Liberty Dr",
    "sg:city":"Liberty Lake",
    "sg:classifiers":[
        {
            "category":"Building & Trades",
            "subcategory":"Construction",
            "type":"Services"
        }
    ],
    "sg:phone":"+1 509 255 6548",
    "sg:postcode":"99019",
    "sg:province":"WA",
    "sg:tags":[
        "house"
    ],
    "wof:name":"Handyman",
    "wof:placetype":"venue"
},
  "geometry": {"coordinates":[-117.09153000000001,47.642685],"type":"Point"}
}