{
  "type": "Feature",
  "properties": {
    "addr:full":"207 1st Ave S Seattle WA 98127",
    "addr:housenumber":"207",
    "addr:postcode":"98127",
    "addr:street":"1St Ave S",
    "iso:country":"US",
    "sg:address":"207 1st Ave S",
    "sg:city":"Seattle",
    "sg:classifiers":[
        {
            "category":"Bars & Pubs",
            "type":"Food & Drink"
        },
        {
            "category":"Arts & Performance",
            "subcategory":"Music",
            "type":"Entertainment"
        },
        {
            "category":"Restaurant",
            "type":"Food & Drink"
        }
    ],
    "sg:phone":"+1 206 622 0209",
    "sg:postcode":"98127",
    "sg:province":"WA",
    "sg:tags":[
        "venue"
    ],
    "sg:website":"www.centralsaloon.com",
    "wof:name":"The Central Saloon",
    "wof:placetype":"venue"
},
  "geometry": {"coordinates":[-122.33425800000001,47.600817],"type":"Point"}
}