{
  "type": "Feature",
  "properties": {
    "addr:full":"5928 E Trent Ave Spokane Valley WA 99212",
    "addr:housenumber":"5928",
    "addr:postcode":"99212",
    "addr:street":"E Trent Ave",
    "iso:country":"US",
    "sg:address":"5928 E Trent Ave",
    "sg:city":"Spokane Valley",
    "sg:classifiers":[
        {
            "category":"Manufacturing",
            "subcategory":"Glass & Minerals",
            "type":"Manufacturing & Wholesale Goods"
        }
    ],
    "sg:phone":"+1 509 535 7136",
    "sg:postcode":"99212",
    "sg:province":"WA",
    "wof:name":"Glass Gods",
    "wof:placetype":"venue"
},
  "geometry": {"coordinates":[-117.32287700000001,47.675304],"type":"Point"}
}