{
  "type": "Feature",
  "properties": {
    "addr:full":"1829 Mariner Cir NE Tacoma WA 98422",
    "addr:housenumber":"1829",
    "addr:postcode":"98422",
    "addr:street":"Mariner Cir Ne",
    "iso:country":"US",
    "sg:address":"1829 Mariner Cir NE",
    "sg:city":"Tacoma",
    "sg:classifiers":[
        {
            "category":"Wholesale",
            "subcategory":"Drugs",
            "type":"Manufacturing & Wholesale Goods"
        }
    ],
    "sg:phone":"+1 253 952 2905",
    "sg:postcode":"98422",
    "sg:province":"WA",
    "sg:tags":[
        "pharmaceutical",
        "product"
    ],
    "wof:name":"Forest Pharmaceuticals Inc",
    "wof:placetype":"venue"
},
  "geometry": {"coordinates":[-122.37229600000001,47.272826],"type":"Point"}
}