{
  "type": "Feature",
  "properties": {
    "addr:full":"6906 Postma Rd Yakima WA 98901",
    "addr:housenumber":"6906",
    "addr:postcode":"98901",
    "addr:street":"Postma Rd",
    "iso:country":"US",
    "sg:address":"6906 Postma Rd",
    "sg:city":"Yakima",
    "sg:classifiers":[
        {
            "category":"Building & Trades",
            "subcategory":"Construction",
            "type":"Services"
        }
    ],
    "sg:phone":"+1 509 249 1023",
    "sg:postcode":"98901",
    "sg:province":"WA",
    "sg:tags":[
        "general",
        "contractor"
    ],
    "wof:name":"Vance Construction LLC",
    "wof:placetype":"venue"
},
  "geometry": {"coordinates":[-120.40443399999999,46.562139],"type":"Point"}
}