{
  "type": "Feature",
  "properties": {
    "addr:full":"400 E Evergreen Blvd Vancouver WA 98660",
    "addr:housenumber":"400",
    "addr:postcode":"98660",
    "addr:street":"E Evergreen Blvd",
    "iso:country":"US",
    "sg:address":"400 E Evergreen Blvd",
    "sg:city":"Vancouver",
    "sg:classifiers":[
        {
            "category":"Professional",
            "type":"Services"
        }
    ],
    "sg:phone":"+1 360 906 0016",
    "sg:postcode":"98660",
    "sg:province":"WA",
    "sg:tags":[
        "establishment"
    ],
    "wof:name":"Firstcorp",
    "wof:placetype":"venue"
},
  "geometry": {"coordinates":[-122.668164,45.628808],"type":"Point"}
}