{
  "type": "Feature",
  "properties": {
    "addr:full":"8227 44th Ave W Mukilteo WA 98275",
    "addr:housenumber":"8227",
    "addr:postcode":"98275",
    "addr:street":"44Th Ave W",
    "iso:country":"US",
    "sg:address":"8227 44th Ave W",
    "sg:city":"Mukilteo",
    "sg:classifiers":[
        {
            "category":"Professional",
            "subcategory":"Management & Consulting",
            "type":"Services"
        },
        {
            "category":"Wholesale",
            "subcategory":"Durable Goods & Equipment",
            "type":"Manufacturing & Wholesale Goods"
        }
    ],
    "sg:phone":"+1 425 438 1146",
    "sg:postcode":"98275",
    "sg:province":"WA",
    "sg:tags":[
        "mfg",
        "representative",
        "manufacturer"
    ],
    "sg:website":"www.wamfg.org",
    "wof:name":"Washington Manufacturing Svcs",
    "wof:placetype":"venue"
},
  "geometry": {"coordinates":[-122.293161,47.924848],"type":"Point"}
}