{
  "type": "Feature",
  "properties": {
    "addr:full":"2919 W Dravus St Seattle WA 98199",
    "addr:housenumber":"2919",
    "addr:postcode":"98199",
    "addr:street":"W Dravus St",
    "iso:country":"US",
    "sg:address":"2919 W Dravus St",
    "sg:city":"Seattle",
    "sg:classifiers":[
        {
            "category":"Building & Trades",
            "subcategory":"Construction",
            "type":"Services"
        }
    ],
    "sg:phone":"+1 206 793 1717",
    "sg:postcode":"98199",
    "sg:province":"WA",
    "sg:tags":[
        "equipment",
        "supply",
        "drywall",
        "contractor"
    ],
    "wof:name":"Seattle Drywall",
    "wof:placetype":"venue"
},
  "geometry": {"coordinates":[-122.394436,47.648631],"type":"Point"}
}