{
  "type": "Feature",
  "properties": {
    "addr:full":"6830 NE Bothell Way Kenmore WA 98155",
    "addr:housenumber":"6830",
    "addr:postcode":"98155",
    "addr:street":"Ne Bothell Way",
    "iso:country":"US",
    "sg:address":"6830 NE Bothell Way",
    "sg:city":"Kenmore",
    "sg:classifiers":[
        {
            "category":"Wholesale",
            "subcategory":"Non-durable Goods",
            "type":"Manufacturing & Wholesale Goods"
        }
    ],
    "sg:phone":"+1 425 489 8282",
    "sg:postcode":"98155",
    "sg:province":"WA",
    "wof:name":"Central Trading Agency",
    "wof:placetype":"venue"
},
  "geometry": {"coordinates":[-122.26452999999999,47.75816],"type":"Point"}
}