{
  "type": "Feature",
  "properties": {
    "addr:full":"328 Bellevue Ave E Apt 2 Seattle WA 98102",
    "addr:housenumber":"328;2",
    "addr:postcode":"98102",
    "addr:street":"Bellevue Ave E Apt",
    "iso:country":"US",
    "sg:address":"328 Bellevue Ave E Apt 2",
    "sg:city":"Seattle",
    "sg:classifiers":[
        {
            "category":"Retail",
            "subcategory":"Photofinishing",
            "type":"Services"
        },
        {
            "category":"Professional",
            "subcategory":"Art Services",
            "type":"Services"
        },
        {
            "category":"Professional",
            "subcategory":"Printing & Photocopies",
            "type":"Services"
        }
    ],
    "sg:phone":"+1 425 802 4572",
    "sg:postcode":"98102",
    "sg:province":"WA",
    "sg:tags":[
        "photographers-portrait",
        "videography",
        "photo",
        "photography",
        "retouching",
        "restoration",
        "photographers-commercial"
    ],
    "sg:website":"http://www.jeanrenophotography.com/",
    "wof:name":"Wedding Photography by Jean Reno Photography",
    "wof:placetype":"venue"
},
  "geometry": {"coordinates":[-122.32655800000001,47.62115],"type":"Point"}
}