{
  "type": "Feature",
  "properties": {
    "addr:full":"1720 Ellis St Bellingham WA 98225",
    "addr:housenumber":"1720",
    "addr:postcode":"98225",
    "addr:street":"Ellis St",
    "iso:country":"US",
    "sg:address":"1720 Ellis St",
    "sg:city":"Bellingham",
    "sg:classifiers":[
        {
            "category":"Social Services",
            "type":"Services"
        }
    ],
    "sg:phone":"+1 360 647 6100",
    "sg:postcode":"98225",
    "sg:province":"WA",
    "sg:tags":[
        "heal",
        "child",
        "day",
        "care"
    ],
    "wof:name":"Bellinghm Chld & Fmly Svcs",
    "wof:placetype":"venue"
},
  "geometry": {"coordinates":[-122.472077,48.753467],"type":"Point"}
}