{
  "type": "Feature",
  "properties": {
    "addr:full":"177 107th Ave NE Bellevue WA 98004",
    "addr:housenumber":"177",
    "addr:postcode":"98004",
    "addr:street":"107Th Ave Ne",
    "iso:country":"US",
    "sg:address":"177 107th Ave NE",
    "sg:city":"Bellevue",
    "sg:classifiers":[
        {
            "category":"Organizations",
            "subcategory":"Professional Association",
            "type":"Services"
        }
    ],
    "sg:phone":"+1 425 462 0026",
    "sg:postcode":"98004",
    "sg:province":"WA",
    "sg:tags":[
        "business"
    ],
    "wof:name":"Bellevue Pacific Tower",
    "wof:placetype":"venue"
},
  "geometry": {"coordinates":[-122.197523,47.610322],"type":"Point"}
}