{
  "type": "Feature",
  "properties": {
    "addr:full":"1309 Alpine View Dr Mount Vernon WA 98274",
    "addr:housenumber":"1309",
    "addr:postcode":"98274",
    "addr:street":"Alpine View Dr",
    "iso:country":"US",
    "sg:address":"1309 Alpine View Dr",
    "sg:city":"Mount Vernon",
    "sg:classifiers":[
        {
            "category":"Building & Trades",
            "subcategory":"Landscaping Services",
            "type":"Services"
        }
    ],
    "sg:phone":"+1 360 424 8133",
    "sg:postcode":"98274",
    "sg:province":"WA",
    "wof:name":"Soft Touch Plant Artistry",
    "wof:placetype":"venue"
},
  "geometry": {"coordinates":[-122.283542,48.409732],"type":"Point"}
}