{
  "type": "Feature",
  "properties": {
    "addr:full":"334 Capitol Way N Olympia WA 98501",
    "addr:housenumber":"334",
    "addr:postcode":"98501",
    "addr:street":"Capitol Way N",
    "iso:country":"US",
    "sg:address":"334 Capitol Way N",
    "sg:city":"Olympia",
    "sg:classifiers":[
        {
            "category":"Personal",
            "subcategory":"Beauty Salon",
            "type":"Services"
        }
    ],
    "sg:phone":"+1 360 956 9097",
    "sg:postcode":"98501",
    "sg:province":"WA",
    "sg:tags":[
        "shop"
    ],
    "wof:name":"Beauty Nail",
    "wof:placetype":"venue"
},
  "geometry": {"coordinates":[-122.901946,47.047149],"type":"Point"}
}