{
  "type": "Feature",
  "properties": {
    "addr:full":"109 W Goodlander Rd Selah WA 98942",
    "addr:housenumber":"109",
    "addr:postcode":"98942",
    "addr:street":"W Goodlander Rd",
    "iso:country":"US",
    "sg:address":"109 W Goodlander Rd",
    "sg:city":"Selah",
    "sg:classifiers":[
        {
            "category":"Building & Trades",
            "subcategory":"Cleaning & Sanitation",
            "type":"Services"
        }
    ],
    "sg:phone":"+1 509 952 1480",
    "sg:postcode":"98942",
    "sg:province":"WA",
    "sg:tags":[
        "construction",
        "up",
        "clean"
    ],
    "wof:name":"Jensens Detailing",
    "wof:placetype":"venue"
},
  "geometry": {"coordinates":[-120.532239,46.665081],"type":"Point"}
}