{
  "type": "Feature",
  "properties": {
    "addr:full":"2622 E Bay Dr NW Gig Harbor WA 98335",
    "addr:housenumber":"2622",
    "addr:postcode":"98335",
    "addr:street":"E Bay Dr Nw",
    "iso:country":"US",
    "sg:address":"2622 E Bay Dr NW",
    "sg:city":"Gig Harbor",
    "sg:classifiers":[
        {
            "category":"Building & Trades",
            "subcategory":"Cleaning & Sanitation",
            "type":"Services"
        }
    ],
    "sg:phone":"+1 253 851 3174",
    "sg:postcode":"98335",
    "sg:province":"WA",
    "sg:tags":[
        "maintenance"
    ],
    "wof:name":"A Clean Sweep",
    "wof:placetype":"venue"
},
  "geometry": {"coordinates":[-122.592181,47.284182],"type":"Point"}
}