{
  "type": "Feature",
  "properties": {
    "addr:full":"316 Main St Edmonds WA 98020",
    "addr:housenumber":"316",
    "addr:postcode":"98020",
    "addr:street":"Main St",
    "iso:country":"US",
    "sg:address":"316 Main St",
    "sg:city":"Edmonds",
    "sg:classifiers":[
        {
            "category":"Restaurant",
            "type":"Food & Drink"
        },
        {
            "category":"Wholesale",
            "subcategory":"Groceries",
            "type":"Manufacturing & Wholesale Goods"
        }
    ],
    "sg:menulink":"http://www.allmenus.com/wa/edmonds/58922-chanterelle/menu/",
    "sg:phone":"+1 425 774 0650",
    "sg:postcode":"98020",
    "sg:province":"WA",
    "sg:tags":[
        "american"
    ],
    "wof:name":"Chanterelle",
    "wof:placetype":"venue"
},
  "geometry": {"coordinates":[-122.379389,47.81133],"type":"Point"}
}