{
  "type": "Feature",
  "properties": {
    "addr:full":"19103 194th Ave NE Woodinville WA 98077",
    "addr:housenumber":"19103",
    "addr:postcode":"98077",
    "addr:street":"194Th Ave Ne",
    "iso:country":"US",
    "sg:address":"19103 194th Ave NE",
    "sg:city":"Woodinville",
    "sg:classifiers":[
        {
            "category":"Professional",
            "subcategory":"Management & Consulting",
            "type":"Services"
        }
    ],
    "sg:phone":"+1 425 883 8007",
    "sg:postcode":"98077",
    "sg:province":"WA",
    "sg:tags":[
        "business"
    ],
    "wof:name":"Cadre",
    "wof:placetype":"venue"
},
  "geometry": {"coordinates":[-122.07899,47.767423],"type":"Point"}
}