{
  "type": "Feature",
  "properties": {
    "addr:full":"1440 Harvey Rd Auburn WA 98002",
    "addr:housenumber":"1440",
    "addr:postcode":"98002",
    "addr:street":"Harvey Rd",
    "iso:country":"US",
    "sg:address":"1440 Harvey Rd",
    "sg:city":"Auburn",
    "sg:classifiers":[
        {
            "category":"Autos & Motor Vehicles",
            "subcategory":"Automobile Sales",
            "type":"Retail Goods"
        }
    ],
    "sg:phone":"+1 253 351 9222",
    "sg:postcode":"98002",
    "sg:province":"WA",
    "sg:tags":[
        "car",
        "dealer"
    ],
    "wof:name":"Hiatt Of Auburn",
    "wof:placetype":"venue"
},
  "geometry": {"coordinates":[-122.220811,47.320802],"type":"Point"}
}