{
  "type": "Feature",
  "properties": {
    "addr:full":"9704 N Division St Spokane WA 99218",
    "addr:housenumber":"9704",
    "addr:postcode":"99218",
    "addr:street":"N Division St",
    "iso:country":"US",
    "sg:address":"9704 N Division St",
    "sg:city":"Spokane",
    "sg:classifiers":[
        {
            "category":"Place Of Worship",
            "subcategory":"Church",
            "type":"Public Place"
        },
        {
            "category":"Place Of Worship",
            "type":"Public Place"
        }
    ],
    "sg:phone":"+1 509 467 5256",
    "sg:postcode":"99218",
    "sg:province":"WA",
    "sg:tags":[
        "lutheran",
        "america",
        "churches-lutheran",
        "churches-lutheran-evangelical"
    ],
    "sg:website":"http://www.stluke-lutheranchurch.org",
    "wof:name":"St Luke Lutheran Church",
    "wof:placetype":"venue"
},
  "geometry": {"coordinates":[-117.41143,47.745824],"type":"Point"}
}