{
  "type": "Feature",
  "properties": {
    "addr:full":"1818 Grove St NE Marysville WA 98270",
    "addr:housenumber":"1818",
    "addr:postcode":"98270",
    "addr:street":"Grove St Ne",
    "iso:country":"US",
    "sg:address":"1818 Grove St NE",
    "sg:city":"Marysville",
    "sg:classifiers":[
        {
            "category":"Organizations",
            "subcategory":"Non-profit Organization",
            "type":"Services"
        }
    ],
    "sg:phone":"+1 360 653 1899",
    "sg:postcode":"98270",
    "sg:province":"WA",
    "sg:tags":[
        "human"
    ],
    "wof:name":"Steps Inc",
    "wof:placetype":"venue"
},
  "geometry": {"coordinates":[-122.169873,48.051746],"type":"Point"}
}