{
  "type": "Feature",
  "properties": {
    "addr:full":"4019 Smith Ave Everett WA 98201",
    "addr:housenumber":"4019",
    "addr:postcode":"98201",
    "addr:street":"Smith Ave",
    "iso:country":"US",
    "sg:address":"4019 Smith Ave",
    "sg:city":"Everett",
    "sg:classifiers":[
        {
            "category":"Wholesale",
            "subcategory":"Auto Parts",
            "type":"Manufacturing & Wholesale Goods"
        }
    ],
    "sg:phone":"+1 425 252 6288",
    "sg:postcode":"98201",
    "sg:province":"WA",
    "sg:tags":[
        "automobile",
        "rebuilt",
        "used"
    ],
    "sg:website":"www.aallforeignautowrecking.com",
    "wof:name":"A All Foreign Auto Wrecking",
    "wof:placetype":"venue"
},
  "geometry": {"coordinates":[-122.196606,47.964037],"type":"Point"}
}