{
  "type": "Feature",
  "properties": {
    "addr:full":"121 Lakeside Ave Seattle WA 98122",
    "addr:housenumber":"121",
    "addr:postcode":"98122",
    "addr:street":"Lakeside Ave",
    "iso:country":"US",
    "sg:address":"121 Lakeside Ave",
    "sg:city":"Seattle",
    "sg:classifiers":[
        {
            "category":"Professional",
            "subcategory":"Lawyer & Legal Services",
            "type":"Services"
        }
    ],
    "sg:phone":"+1 206 324 4842",
    "sg:postcode":"98122",
    "sg:province":"WA",
    "wof:name":"Marshall Bradley Rev Atty",
    "wof:placetype":"venue"
},
  "geometry": {"coordinates":[-122.285004,47.601799],"type":"Point"}
}