{
  "type": "Feature",
  "properties": {
    "addr:full":"2502 N 50th St Seattle WA 98103",
    "addr:housenumber":"2502",
    "addr:postcode":"98103",
    "addr:street":"N 50Th St",
    "iso:country":"US",
    "sg:address":"2502 N 50th St",
    "sg:city":"Seattle",
    "sg:classifiers":[
        {
            "category":"Professional",
            "subcategory":"Computer Services",
            "type":"Services"
        }
    ],
    "sg:phone":"+1 206 375 0127",
    "sg:postcode":"98103",
    "sg:province":"WA",
    "sg:tags":[
        "datum"
    ],
    "wof:name":"SMH Designs",
    "wof:placetype":"venue"
},
  "geometry": {"coordinates":[-122.328456,47.665078],"type":"Point"}
}