{
  "type": "Feature",
  "properties": {
    "addr:full":"18560 1st Ave NE Shoreline WA 98155",
    "addr:housenumber":"18560",
    "addr:postcode":"98155",
    "addr:street":"1St Ave Ne",
    "iso:country":"US",
    "sg:address":"18560 1st Ave NE",
    "sg:city":"Shoreline",
    "sg:classifiers":[
        {
            "category":"Personal",
            "type":"Services"
        },
        {
            "category":"Sports & Exercise",
            "subcategory":"Gym",
            "type":"Entertainment"
        }
    ],
    "sg:phone":"+1 206 792 7852",
    "sg:postcode":"98155",
    "sg:province":"WA",
    "sg:tags":[
        "trainer",
        "consultant",
        "program",
        "fitness",
        "physical"
    ],
    "sg:website":"http://seattle.citysearch.com/profile/external/604013602/shoreline_wa/jazzercise_shoreline_center_spartan_gym_building.html?publisher=yellowpages&reference_id=1&placement=ypwebsitemip",
    "wof:name":"Jazzercise Shoreline Center - Spartan Gym Building",
    "wof:placetype":"venue"
},
  "geometry": {"coordinates":[-122.329627,47.763767],"type":"Point"}
}