{
  "type": "Feature",
  "properties": {
    "addr:full":"820 Grandview Ave Sunnyside WA 98944",
    "addr:housenumber":"820",
    "addr:postcode":"98944",
    "addr:street":"Grandview Ave",
    "iso:country":"US",
    "sg:address":"820 Grandview Ave",
    "sg:city":"Sunnyside",
    "sg:classifiers":[
        {
            "category":"Shopping",
            "type":"Retail Goods"
        }
    ],
    "sg:phone":"+1 509 837 3765",
    "sg:postcode":"98944",
    "sg:province":"WA",
    "sg:tags":[
        "wedding",
        "supply"
    ],
    "wof:name":"Creations By Carol",
    "wof:placetype":"venue"
},
  "geometry": {"coordinates":[-120.034344,46.318742],"type":"Point"}
}