{
  "type": "Feature",
  "properties": {
    "addr:full":"2613 Conger Ave NW Olympia WA 98502",
    "addr:postcode":"2613;olympia wa 98502",
    "addr:street":"Conger Ave Nw",
    "iso:country":"US",
    "sg:address":"2613 Conger Ave NW",
    "sg:city":"Olympia",
    "sg:classifiers":[
        {
            "category":"Social Services",
            "subcategory":"Child Care",
            "type":"Services"
        }
    ],
    "sg:phone":"+1 360 570 0226",
    "sg:postcode":"98502",
    "sg:province":"WA",
    "sg:tags":[
        "day"
    ],
    "wof:name":"Tadpoles Childcare",
    "wof:placetype":"venue"
},
  "geometry": {"coordinates":[-122.94112699999999,47.051436],"type":"Point"}
}