{
  "type": "Feature",
  "properties": {
    "addr:full":"4401 37th Ave SE Lacey WA 98503",
    "addr:housenumber":"4401",
    "addr:postcode":"98503",
    "addr:street":"37Th Ave Se",
    "iso:country":"US",
    "sg:address":"4401 37th Ave SE",
    "sg:city":"Lacey",
    "sg:classifiers":[
        {
            "category":"Building & Trades",
            "subcategory":"Cleaning & Sanitation",
            "type":"Services"
        }
    ],
    "sg:phone":"+1 360 412 4069",
    "sg:postcode":"98503",
    "sg:province":"WA",
    "sg:tags":[
        "maintenance"
    ],
    "wof:name":"Double E Cleaning Services",
    "wof:placetype":"venue"
},
  "geometry": {"coordinates":[-122.825406,47.014329],"type":"Point"}
}