{
  "type": "Feature",
  "properties": {
    "addr:full":"150 N Clark St Republic WA 99166",
    "addr:housenumber":"150",
    "addr:postcode":"99166",
    "addr:street":"N Clark St",
    "iso:country":"US",
    "sg:address":"150 N Clark St",
    "sg:city":"Republic",
    "sg:classifiers":[
        {
            "category":"Travel",
            "subcategory":"Hotels & Motels",
            "type":"Entertainment"
        }
    ],
    "sg:phone":"+1 509 775 3555",
    "sg:postcode":"99166",
    "sg:province":"WA",
    "wof:name":"Klondike Motel",
    "wof:placetype":"venue"
},
  "geometry": {"coordinates":[-118.73827900000001,48.64923],"type":"Point"}
}