{
  "type": "Feature",
  "properties": {
    "addr:full":"1329 N State St Bellingham WA 98225",
    "addr:housenumber":"1329",
    "addr:postcode":"98225",
    "addr:street":"N State St",
    "iso:country":"US",
    "sg:address":"1329 N State St",
    "sg:city":"Bellingham",
    "sg:classifiers":[
        {
            "category":"Government",
            "subcategory":"Office",
            "type":"Public Place"
        }
    ],
    "sg:phone":"+1 360 676 1211",
    "sg:postcode":"98225",
    "sg:province":"WA",
    "sg:tags":[
        "county"
    ],
    "wof:name":"Friends Of Whatcom County",
    "wof:placetype":"venue"
},
  "geometry": {"coordinates":[-122.475931,48.749182],"type":"Point"}
}