{
  "type": "Feature",
  "properties": {
    "iso:country":"US",
    "sg:address":"1624 E Liberty Ave",
    "sg:city":"Spokane",
    "sg:classifiers":[
        {
            "category":"Social Services",
            "type":"Services"
        }
    ],
    "sg:phone":"+1 509 483 9255",
    "sg:postcode":"99207",
    "sg:province":"WA",
    "wof:name":"Lisas Daycare",
    "wof:placetype":"venue"
},
  "geometry": {"coordinates":[-117.385535,47.687546],"type":"Point"}
}