{
  "type": "Feature",
  "properties": {
    "addr:full":"10611 Canyon Rd E Puyallup WA 98373",
    "addr:housenumber":"10611",
    "addr:postcode":"98373",
    "addr:street":"Canyon Rd E",
    "iso:country":"US",
    "sg:address":"10611 Canyon Rd E",
    "sg:city":"Puyallup",
    "sg:classifiers":[
        {
            "category":"Building & Trades",
            "subcategory":"Construction",
            "type":"Services"
        },
        {
            "category":"Utilities",
            "type":"Services"
        }
    ],
    "sg:phone":"+1 253 535 5153",
    "sg:postcode":"98373",
    "sg:province":"WA",
    "sg:tags":[
        "sanitary",
        "marking",
        "maintenance",
        "parking"
    ],
    "wof:name":"Road Runner Striping",
    "wof:placetype":"venue"
},
  "geometry": {"coordinates":[-122.35715999999999,47.158837],"type":"Point"}
}