{
  "type": "Feature",
  "properties": {
    "addr:full":"3735 Waller Rd E Tacoma WA 98443",
    "addr:housenumber":"3735",
    "addr:postcode":"98443",
    "addr:street":"Waller Rd E",
    "iso:country":"US",
    "sg:address":"3735 Waller Rd E",
    "sg:city":"Tacoma",
    "sg:classifiers":[
        {
            "category":"Place Of Worship",
            "subcategory":"Church",
            "type":"Public Place"
        },
        {
            "category":"Place Of Worship",
            "type":"Public Place"
        },
        {
            "category":"Organizations",
            "subcategory":"Religious Organization",
            "type":"Services"
        }
    ],
    "sg:phone":"+1 253 922 5359",
    "sg:postcode":"98443",
    "sg:province":"WA",
    "sg:tags":[
        "churches-interdenominational",
        "churches-various",
        "denomination"
    ],
    "wof:name":"Valley View Christn Fellowship",
    "wof:placetype":"venue"
},
  "geometry": {"coordinates":[-122.387602,47.223562],"type":"Point"}
}