{
  "type": "Feature",
  "properties": {
    "addr:full":"3720 Harborview Dr Gig Harbor WA 98332",
    "addr:housenumber":"3720",
    "addr:postcode":"98332",
    "addr:street":"Harborview Dr",
    "iso:country":"US",
    "sg:address":"3720 Harborview Dr",
    "sg:city":"Gig Harbor",
    "sg:classifiers":[
        {
            "category":"Home & Garden",
            "subcategory":"Building Materials",
            "type":"Retail Goods"
        }
    ],
    "sg:phone":"+1 253 851 8496",
    "sg:postcode":"98332",
    "sg:province":"WA",
    "sg:tags":[
        "glass",
        "window",
        "plate"
    ],
    "wof:name":"Speedy Glass",
    "wof:placetype":"venue"
},
  "geometry": {"coordinates":[-122.587225,47.333559],"type":"Point"}
}