{
  "type": "Feature",
  "properties": {
    "iso:country":"US",
    "sg:address":"2809 S Skipworth Rd",
    "sg:city":"Spokane",
    "sg:classifiers":[
        {
            "category":"Banks & Credit Unions",
            "subcategory":"Financial Services",
            "type":"Services"
        }
    ],
    "sg:phone":"+1 509 926 7372",
    "sg:postcode":"99206",
    "sg:province":"WA",
    "sg:tags":[
        "trust",
        "management"
    ],
    "wof:name":"B Luella Trust",
    "wof:placetype":"venue"
},
  "geometry": {"coordinates":[-117.253248,47.630726],"type":"Point"}
}