{
  "type": "Feature",
  "properties": {
    "addr:full":"2602 Hoyt Ave Everett WA 98201",
    "addr:housenumber":"2602",
    "addr:postcode":"98201",
    "addr:street":"Hoyt Ave",
    "iso:country":"US",
    "sg:address":"2602 Hoyt Ave",
    "sg:city":"Everett",
    "sg:classifiers":[
        {
            "category":"Place Of Worship",
            "subcategory":"Church",
            "type":"Public Place"
        },
        {
            "category":"Place Of Worship",
            "type":"Public Place"
        },
        {
            "category":"Education",
            "subcategory":"School",
            "type":"Public Place"
        }
    ],
    "sg:phone":"+1 425 259 3730",
    "sg:postcode":"98201",
    "sg:province":"WA",
    "sg:tags":[
        "churches-pentecostal",
        "churches-pentecostal-independent",
        "private",
        "k-"
    ],
    "wof:name":"Living Faith Tabernacle",
    "wof:placetype":"venue"
},
  "geometry": {"coordinates":[-122.209953,47.983235],"type":"Point"}
}