{
  "type": "Feature",
  "properties": {
    "addr:full":"4421 Marionberry Ct Bellingham WA 98229",
    "addr:housenumber":"4421",
    "addr:postcode":"98229",
    "addr:street":"Marionberry Ct",
    "iso:country":"US",
    "sg:address":"4421 Marionberry Ct",
    "sg:city":"Bellingham",
    "sg:classifiers":[
        {
            "category":"Real Estate",
            "subcategory":"Real Estate Services",
            "type":"Services"
        },
        {
            "category":"Real Estate",
            "subcategory":"Real Estate Agent",
            "type":"Services"
        }
    ],
    "sg:phone":"+1 360 647 1820",
    "sg:postcode":"98229",
    "sg:province":"WA",
    "sg:tags":[
        "buyer",
        "broker"
    ],
    "wof:name":"Buyertours Realty",
    "wof:placetype":"venue"
},
  "geometry": {"coordinates":[-122.45926900000001,48.737582],"type":"Point"}
}