{
  "type": "Feature",
  "properties": {
    "addr:full":"24008 Snohomish Woodinville Rd Woodinville WA 98072",
    "addr:postcode":"24008;98072",
    "addr:street":"Woodinville Rd",
    "iso:country":"US",
    "sg:address":"24008 Snohomish Woodinville Rd",
    "sg:city":"Woodinville",
    "sg:phone":"+1 425 806 7700",
    "sg:postcode":"98072",
    "sg:province":"WA",
    "sg:website":"http://www.costco.com",
    "wof:name":"Costco",
    "wof:placetype":"venue"
},
  "geometry": {"coordinates":[-122.146485,47.779411],"type":"Point"}
}