{
  "type": "Feature",
  "properties": {
    "addr:full":"12001 Pacific Ave S Tacoma WA 98444",
    "addr:housenumber":"12001",
    "addr:postcode":"98444",
    "addr:street":"Pacific Ave S",
    "iso:country":"US",
    "sg:address":"12001 Pacific Ave S",
    "sg:city":"Tacoma",
    "sg:classifiers":[
        {
            "category":"Government",
            "subcategory":"Office",
            "type":"Public Place"
        }
    ],
    "sg:phone":"+1 253 536 6165",
    "sg:postcode":"98444",
    "sg:province":"WA",
    "sg:tags":[
        "state",
        "program"
    ],
    "wof:name":"Vocational Rehabilitation Div",
    "wof:placetype":"venue"
},
  "geometry": {"coordinates":[-122.43431200000001,47.148911],"type":"Point"}
}