{
  "type": "Feature",
  "properties": {
    "addr:full":"5042 Roosevelt Way NE Seattle WA 98105",
    "addr:housenumber":"5042",
    "addr:postcode":"98105",
    "addr:street":"Roosevelt Way Ne",
    "iso:country":"US",
    "sg:address":"5042 Roosevelt Way NE",
    "sg:city":"Seattle",
    "sg:classifiers":[
        {
            "category":"Restaurant",
            "type":"Food & Drink"
        }
    ],
    "sg:menulink":"http://www.allmenus.com/wa/seattle/17785-wing-zone/menu/",
    "sg:phone":"+1 206 523 5252",
    "sg:postcode":"98105",
    "sg:province":"WA",
    "sg:tags":[
        "american",
        "wing"
    ],
    "wof:name":"Wing Zone",
    "wof:placetype":"venue"
},
  "geometry": {"coordinates":[-122.31740600000001,47.665311],"type":"Point"}
}