{
  "type": "Feature",
  "properties": {
    "addr:full":"4710 NW Lincoln Ave Vancouver WA 98663",
    "addr:housenumber":"4710",
    "addr:postcode":"98663",
    "addr:street":"Nw Lincoln Ave",
    "iso:country":"US",
    "sg:address":"4710 NW Lincoln Ave",
    "sg:city":"Vancouver",
    "sg:classifiers":[
        {
            "category":"Building & Trades",
            "subcategory":"Construction",
            "type":"Services"
        }
    ],
    "sg:phone":"+1 360 993 2502",
    "sg:postcode":"98663",
    "sg:province":"WA",
    "sg:tags":[
        "contractor"
    ],
    "wof:name":"Pacific Gutter Cleaning",
    "wof:placetype":"venue"
},
  "geometry": {"coordinates":[-122.682547,45.656216],"type":"Point"}
}