{
  "type": "Feature",
  "properties": {
    "addr:full":"21427 SE 33rd Pl Sammamish WA 98075",
    "addr:housenumber":"21427",
    "addr:postcode":"98075",
    "addr:street":"Se 33Rd Pl",
    "iso:country":"US",
    "sg:address":"21427 SE 33rd Pl",
    "sg:city":"Sammamish",
    "sg:classifiers":[
        {
            "category":"Real Estate",
            "subcategory":"Real Estate Services",
            "type":"Services"
        },
        {
            "category":"Real Estate",
            "subcategory":"Real Estate Agent",
            "type":"Services"
        }
    ],
    "sg:phone":"+1 425 557 7641",
    "sg:postcode":"98075",
    "sg:province":"WA",
    "sg:tags":[
        "buyer",
        "broker"
    ],
    "wof:name":"Mary Buckmaster Realtor",
    "wof:placetype":"venue"
},
  "geometry": {"coordinates":[-122.05364899999999,47.579343],"type":"Point"}
}