{
  "type": "Feature",
  "properties": {
    "iso:country":"US",
    "sg:address":"520 S 1st St",
    "sg:city":"Mount Vernon",
    "sg:classifiers":[
        {
            "category":"Farming",
            "subcategory":"Orchard",
            "type":"Manufacturing & Wholesale Goods"
        }
    ],
    "sg:phone":"+1 360 336 9933",
    "sg:postcode":"98273",
    "sg:province":"WA",
    "sg:tags":[
        "citrus",
        "fruit"
    ],
    "wof:name":"Dole Food",
    "wof:placetype":"venue"
},
  "geometry": {"coordinates":[-122.33781399999999,48.419274],"type":"Point"}
}