{
  "type": "Feature",
  "properties": {
    "addr:full":"4243 NW Golf Club Hill Rd Bremerton WA 98312",
    "addr:housenumber":"4243",
    "addr:postcode":"98312",
    "addr:street":"Nw Golf Club Hill Rd",
    "iso:country":"US",
    "sg:address":"4243 NW Golf Club Hill Rd",
    "sg:city":"Bremerton",
    "sg:classifiers":[
        {
            "category":"Professional",
            "subcategory":"Business Services",
            "type":"Services"
        }
    ],
    "sg:phone":"+1 360 373 7919",
    "sg:postcode":"98312",
    "sg:province":"WA",
    "wof:name":"Outlook Inc",
    "wof:placetype":"venue"
},
  "geometry": {"coordinates":[-122.702631,47.591298],"type":"Point"}
}