{
  "type": "Feature",
  "properties": {
    "addr:full":"5351 NE 2nd St Renton WA 98059",
    "addr:housenumber":"5351",
    "addr:postcode":"98059",
    "addr:street":"Ne 2Nd St",
    "iso:country":"US",
    "sg:address":"5351 NE 2nd St",
    "sg:city":"Renton",
    "sg:classifiers":[
        {
            "category":"Building & Trades",
            "subcategory":"Construction",
            "type":"Services"
        }
    ],
    "sg:phone":"+1 425 235 8680",
    "sg:postcode":"98059",
    "sg:province":"WA",
    "sg:tags":[
        "painter"
    ],
    "wof:name":"Horizon Painting Services",
    "wof:placetype":"venue"
},
  "geometry": {"coordinates":[-122.14693200000001,47.484814],"type":"Point"}
}