{
  "type": "Feature",
  "properties": {
    "addr:full":"1102 S Anderson St Tacoma WA 98405",
    "addr:housenumber":"1102",
    "addr:postcode":"98405",
    "addr:street":"S Anderson St",
    "iso:country":"US",
    "sg:address":"1102 S Anderson St",
    "sg:city":"Tacoma",
    "sg:classifiers":[
        {
            "category":"Professional",
            "subcategory":"Business Services",
            "type":"Services"
        }
    ],
    "sg:phone":"+1 253 272 7607",
    "sg:postcode":"98405",
    "sg:province":"WA",
    "wof:name":"Ms JS Environmental Svc",
    "wof:placetype":"venue"
},
  "geometry": {"coordinates":[-122.47273800000001,47.250517],"type":"Point"}
}