{
  "type": "Feature",
  "properties": {
    "iso:country":"US",
    "sg:address":"9409 NE Hwy 99",
    "sg:city":"Vancouver",
    "sg:classifiers":[
        {
            "category":"Insurance",
            "subcategory":"Insurance Agent",
            "type":"Services"
        }
    ],
    "sg:phone":"+1 360 566 0491",
    "sg:postcode":"98665",
    "sg:province":"WA",
    "wof:name":"Eric Payne Agency",
    "wof:placetype":"venue"
},
  "geometry": {"coordinates":[-122.660087,45.686442],"type":"Point"}
}