{
  "type": "Feature",
  "properties": {
    "addr:full":"2547 Bodie Mountain Rd Colville WA 99114",
    "addr:housenumber":"2547",
    "addr:postcode":"99114",
    "addr:street":"Bodie Mountain Rd",
    "iso:country":"US",
    "sg:address":"2547 Bodie Mountain Rd",
    "sg:city":"Colville",
    "sg:classifiers":[
        {
            "category":"Manufacturing",
            "subcategory":"Glass & Minerals",
            "type":"Manufacturing & Wholesale Goods"
        }
    ],
    "sg:phone":"+1 509 732 4868",
    "sg:postcode":"99114",
    "sg:province":"WA",
    "sg:tags":[
        "product",
        "mfg"
    ],
    "wof:name":"Mariannes Metier",
    "wof:placetype":"venue"
},
  "geometry": {"coordinates":[-117.79983,48.848764],"type":"Point"}
}