{
  "type": "Feature",
  "properties": {
    "addr:full":"2232 103rd St SE Everett WA 98208",
    "addr:housenumber":"2232",
    "addr:postcode":"98208",
    "addr:street":"103Rd St Se",
    "iso:country":"US",
    "sg:address":"2232 103rd St SE",
    "sg:city":"Everett",
    "sg:classifiers":[
        {
            "category":"Farming",
            "subcategory":"Nursery",
            "type":"Manufacturing & Wholesale Goods"
        }
    ],
    "sg:phone":"+1 425 337 2136",
    "sg:postcode":"98208",
    "sg:province":"WA",
    "sg:tags":[
        "ornamental"
    ],
    "wof:name":"Yundi",
    "wof:placetype":"venue"
},
  "geometry": {"coordinates":[-122.202172,47.904956],"type":"Point"}
}