{
  "type": "Feature",
  "properties": {
    "addr:full":"14710 E 36th Ave Veradale WA 99037",
    "addr:housenumber":"14710",
    "addr:postcode":"99037",
    "addr:street":"E 36Th Ave",
    "iso:country":"US",
    "sg:address":"14710 E 36th Ave",
    "sg:city":"Veradale",
    "sg:classifiers":[
        {
            "category":"Professional",
            "type":"Services"
        }
    ],
    "sg:phone":"+1 509 924 7861",
    "sg:postcode":"99037",
    "sg:province":"WA",
    "wof:name":"Willtroxel",
    "wof:placetype":"venue"
},
  "geometry": {"coordinates":[-117.20213099999999,47.624136],"type":"Point"}
}