{
  "type": "Feature",
  "properties": {
    "addr:full":"20591 Little Valley Rd NE Poulsbo WA 98370",
    "addr:housenumber":"20591",
    "addr:postcode":"98370",
    "addr:street":"Little Valley Rd Ne",
    "iso:country":"US",
    "sg:address":"20591 Little Valley Rd NE",
    "sg:city":"Poulsbo",
    "sg:classifiers":[
        {
            "category":"Building & Trades",
            "subcategory":"Landscaping Services",
            "type":"Services"
        }
    ],
    "sg:phone":"+1 360 779 7408",
    "sg:postcode":"98370",
    "sg:province":"WA",
    "sg:tags":[
        "lawn",
        "maintenance"
    ],
    "wof:name":"Genes Garden",
    "wof:placetype":"venue"
},
  "geometry": {"coordinates":[-122.638779,47.747782],"type":"Point"}
}