{
  "type": "Feature",
  "properties": {
    "addr:full":"1041 Andover Park E Seattle WA 98188",
    "addr:housenumber":"1041",
    "addr:postcode":"98188",
    "addr:street":"Andover Park E",
    "iso:country":"US",
    "sg:address":"1041 Andover Park E",
    "sg:city":"Seattle",
    "sg:classifiers":[
        {
            "category":"Manufacturing",
            "subcategory":"Furniture",
            "type":"Manufacturing & Wholesale Goods"
        }
    ],
    "sg:phone":"+1 206 575 3858",
    "sg:postcode":"98188",
    "sg:province":"WA",
    "sg:tags":[
        "mfg",
        "mattress"
    ],
    "wof:name":"Case-Littel Furniture Co",
    "wof:placetype":"venue"
},
  "geometry": {"coordinates":[-122.250896,47.447334],"type":"Point"}
}