{
  "type": "Feature",
  "properties": {
    "addr:full":"15600 NE 8th St Ste O-09 Bellevue WA 98008",
    "addr:housenumber":"15600",
    "addr:postcode":"98008",
    "addr:street":"Ne 8Th St Ste O-09",
    "iso:country":"US",
    "sg:address":"15600 NE 8th St Ste O-09",
    "sg:city":"Bellevue",
    "sg:classifiers":[
        {
            "category":"Restaurant",
            "type":"Food & Drink"
        }
    ],
    "sg:phone":"+1 425 641 9999",
    "sg:postcode":"98008",
    "sg:province":"WA",
    "sg:tags":[
        "indian"
    ],
    "sg:website":"www.ohindiarestaurant.com",
    "wof:name":"Oh! India",
    "wof:placetype":"venue"
},
  "geometry": {"coordinates":[-122.13169000000001,47.62147],"type":"Point"}
}