{
  "type": "Feature",
  "properties": {
    "addr:full":"12706 N Market St Mead WA 99021",
    "addr:housenumber":"12706",
    "addr:postcode":"99021",
    "addr:street":"N Market St Mead",
    "iso:country":"US",
    "sg:address":"12706 N Market St",
    "sg:city":"Mead",
    "sg:classifiers":[
        {
            "category":"Food & Beverages",
            "subcategory":"Specialty",
            "type":"Retail Goods"
        }
    ],
    "sg:phone":"+1 509 465 8004",
    "sg:postcode":"99021",
    "sg:province":"WA",
    "sg:tags":[
        "bars",
        "espresso"
    ],
    "wof:name":"Northside Expresso",
    "wof:placetype":"venue"
},
  "geometry": {"coordinates":[-117.353084,47.774722],"type":"Point"}
}