{
  "type": "Feature",
  "properties": {
    "addr:full":"2930 Ford St Washougal WA 98671",
    "addr:housenumber":"2930",
    "addr:postcode":"98671",
    "addr:street":"Ford St",
    "iso:country":"US",
    "sg:address":"2930 Ford St",
    "sg:city":"Washougal",
    "sg:classifiers":[
        {
            "category":"Manufacturing",
            "subcategory":"Glass & Minerals",
            "type":"Manufacturing & Wholesale Goods"
        }
    ],
    "sg:phone":"+1 360 835 2171",
    "sg:postcode":"98671",
    "sg:province":"WA",
    "sg:tags":[
        "fabricator",
        "fiber"
    ],
    "sg:website":"www.ccifrp.com",
    "wof:name":"Corrosion Controllers Inc",
    "wof:placetype":"venue"
},
  "geometry": {"coordinates":[-122.3391,45.57251],"type":"Point"}
}