{
  "type": "Feature",
  "properties": {
    "addr:full":"1400 164th St SW Lynnwood WA 98087",
    "addr:housenumber":"1400",
    "addr:postcode":"98087",
    "addr:street":"164Th St Sw",
    "iso:country":"US",
    "sg:address":"1400 164th St SW",
    "sg:city":"Lynnwood",
    "sg:classifiers":[
        {
            "category":"Shopping",
            "subcategory":"Bicycles & Sporting Goods",
            "type":"Retail Goods"
        }
    ],
    "sg:phone":"+1 425 741 9559",
    "sg:postcode":"98087",
    "sg:province":"WA",
    "sg:tags":[
        "gun",
        "gunsmith"
    ],
    "wof:name":"Blowguns Northwest Inc",
    "wof:placetype":"venue"
},
  "geometry": {"coordinates":[-122.25329600000001,47.84974],"type":"Point"}
}