{
  "type": "Feature",
  "properties": {
    "addr:full":"18560 1st Ave NE Seattle WA 98155",
    "addr:housenumber":"18560",
    "addr:postcode":"98155",
    "addr:street":"1St Ave Ne",
    "iso:country":"US",
    "sg:address":"18560 1st Ave NE",
    "sg:city":"Seattle",
    "sg:classifiers":[
        {
            "category":"Arts & Performance",
            "subcategory":"Theater",
            "type":"Entertainment"
        }
    ],
    "sg:phone":"+1 206 363 2809",
    "sg:postcode":"98155",
    "sg:province":"WA",
    "sg:tags":[
        "theatrical",
        "producer"
    ],
    "wof:name":"Civic Light Opera",
    "wof:placetype":"venue"
},
  "geometry": {"coordinates":[-122.32958600000001,47.764317],"type":"Point"}
}