{
  "type": "Feature",
  "properties": {
    "addr:full":"4017 13th Ave W Seattle WA 98119",
    "addr:housenumber":"4017",
    "addr:postcode":"98119",
    "addr:street":"13Th Ave W",
    "iso:country":"US",
    "sg:address":"4017 13th Ave W",
    "sg:city":"Seattle",
    "sg:classifiers":[
        {
            "category":"Professional",
            "subcategory":"Management & Consulting",
            "type":"Services"
        }
    ],
    "sg:phone":"+1 206 284 0475",
    "sg:postcode":"98119",
    "sg:province":"WA",
    "sg:tags":[
        "consultant",
        "business"
    ],
    "wof:name":"Aasgard Summit Mgmt Svc Inc",
    "wof:placetype":"venue"
},
  "geometry": {"coordinates":[-122.37363499999999,47.655957],"type":"Point"}
}