{
  "type": "Feature",
  "properties": {
    "addr:full":"14028 3rd Ave NW Seattle WA 98177",
    "addr:housenumber":"14028",
    "addr:postcode":"98177",
    "addr:street":"3Rd Ave Nw",
    "iso:country":"US",
    "sg:address":"14028 3rd Ave NW",
    "sg:city":"Seattle",
    "sg:classifiers":[
        {
            "category":"Recreation",
            "type":"Entertainment"
        }
    ],
    "sg:phone":"+1 206 412 2745",
    "sg:postcode":"98177",
    "sg:province":"WA",
    "wof:name":"Carrie A Voltz Lmp",
    "wof:placetype":"venue"
},
  "geometry": {"coordinates":[-122.360859,47.732156],"type":"Point"}
}