{
  "type": "Feature",
  "properties": {
    "addr:full":"2339 Lewis River Rd Woodland WA 98674",
    "addr:housenumber":"2339",
    "addr:postcode":"98674",
    "addr:street":"Lewis River Rd",
    "iso:country":"US",
    "sg:address":"2339 Lewis River Rd",
    "sg:city":"Woodland",
    "sg:classifiers":[
        {
            "category":"Travel",
            "subcategory":"Hotels & Motels",
            "type":"Entertainment"
        }
    ],
    "sg:phone":"+1 360 225 8630",
    "sg:postcode":"98674",
    "sg:province":"WA",
    "sg:tags":[
        "breakfast",
        "accommodation",
        "bed"
    ],
    "wof:name":"Lewis River Bed & Breakfast",
    "wof:placetype":"venue"
},
  "geometry": {"coordinates":[-122.721785,45.929858],"type":"Point"}
}