{
  "type": "Feature",
  "properties": {
    "addr:full":"22 W Carmichael Dr Kennewick WA 99336",
    "addr:housenumber":"22",
    "addr:postcode":"99336",
    "addr:street":"W Carmichael Dr",
    "iso:country":"US",
    "sg:address":"22 W Carmichael Dr",
    "sg:city":"Kennewick",
    "sg:classifiers":[
        {
            "category":"Retail",
            "subcategory":"Laundry & Dry Cleaning",
            "type":"Services"
        }
    ],
    "sg:phone":"+1 509 582 2058",
    "sg:postcode":"99336",
    "sg:province":"WA",
    "sg:tags":[
        "cleaners"
    ],
    "wof:name":"Carmichael Dry Cleaners",
    "wof:placetype":"venue"
},
  "geometry": {"coordinates":[-119.12883100000001,46.208555],"type":"Point"}
}