{
  "type": "Feature",
  "properties": {
    "addr:full":"3417 Crestline Pl Bellingham WA 98226",
    "addr:housenumber":"3417",
    "addr:postcode":"98226",
    "addr:street":"Crestline Pl",
    "iso:country":"US",
    "sg:address":"3417 Crestline Pl",
    "sg:city":"Bellingham",
    "sg:classifiers":[
        {
            "category":"Professional",
            "type":"Services"
        }
    ],
    "sg:phone":"+1 360 527 8580",
    "sg:postcode":"98226",
    "sg:province":"WA",
    "wof:name":"American Post Pounder",
    "wof:placetype":"venue"
},
  "geometry": {"coordinates":[-122.427667,48.763851],"type":"Point"}
}