{
  "type": "Feature",
  "properties": {
    "addr:full":"27149 185th Ave SE Covington WA 98042",
    "addr:housenumber":"27149",
    "addr:postcode":"98042",
    "addr:street":"185Th Ave Se",
    "iso:country":"US",
    "sg:address":"27149 185th Ave SE",
    "sg:city":"Covington",
    "sg:classifiers":[
        {
            "category":"Personal",
            "subcategory":"Beauty Salon",
            "type":"Services"
        },
        {
            "category":"Personal",
            "subcategory":"Nail Salon",
            "type":"Services"
        }
    ],
    "sg:phone":"+1 253 638 2008",
    "sg:postcode":"98042",
    "sg:province":"WA",
    "wof:name":"Four Seasons Nail And Spa",
    "wof:placetype":"venue"
},
  "geometry": {"coordinates":[-122.095877,47.348833],"type":"Point"}
}