{
  "type": "Feature",
  "properties": {
    "addr:full":"4312 Kitsap Way Bremerton WA 98312",
    "addr:housenumber":"4312",
    "addr:postcode":"98312",
    "addr:street":"Kitsap Way",
    "iso:country":"US",
    "sg:address":"4312 Kitsap Way",
    "sg:city":"Bremerton",
    "sg:classifiers":[
        {
            "category":"Government",
            "subcategory":"Office",
            "type":"Public Place"
        }
    ],
    "sg:phone":"+1 360 377 9499",
    "sg:postcode":"98312",
    "sg:province":"WA",
    "sg:tags":[
        "business",
        "general",
        "program",
        "economic",
        "assoc",
        "administrative"
    ],
    "wof:name":"Kitsap Rgnal Ecnmic Dev Cuncil",
    "wof:placetype":"venue"
},
  "geometry": {"coordinates":[-122.67230600000001,47.568323],"type":"Point"}
}