{
  "type": "Feature",
  "properties": {
    "addr:full":"4815 W Clearwater Ave Kennewick WA 99336",
    "addr:housenumber":"4815",
    "addr:postcode":"99336",
    "addr:street":"W Clearwater Ave",
    "iso:country":"US",
    "sg:address":"4815 W Clearwater Ave",
    "sg:city":"Kennewick",
    "sg:classifiers":[
        {
            "category":"Retail",
            "subcategory":"Repair Shop",
            "type":"Services"
        }
    ],
    "sg:phone":"+1 509 735 1734",
    "sg:postcode":"99336",
    "sg:province":"WA",
    "wof:name":"Julie Lee Ohran",
    "wof:placetype":"venue"
},
  "geometry": {"coordinates":[-119.186864,46.212329],"type":"Point"}
}