{
  "type": "Feature",
  "properties": {
    "iso:country":"US",
    "sg:address":"1901 S Union Ave",
    "sg:city":"Tacoma",
    "sg:classifiers":[
        {
            "category":"Professional",
            "type":"Services"
        }
    ],
    "sg:phone":"+1 253 274 8653",
    "sg:postcode":"98405",
    "sg:province":"WA",
    "sg:tags":[
        "establishment"
    ],
    "wof:name":"Exigere Corp",
    "wof:placetype":"venue"
},
  "geometry": {"coordinates":[-122.48194599999999,47.239125],"type":"Point"}
}