{
  "type": "Feature",
  "properties": {
    "addr:full":"1631 W Rose St Walla Walla WA 99362",
    "addr:housenumber":"1631",
    "addr:postcode":"99362",
    "addr:street":"W Rose St",
    "iso:country":"US",
    "sg:address":"1631 W Rose St",
    "sg:city":"Walla Walla",
    "sg:classifiers":[
        {
            "category":"Shopping",
            "subcategory":"Shoes",
            "type":"Retail Goods"
        }
    ],
    "sg:phone":"+1 509 525 0161",
    "sg:postcode":"99362",
    "sg:province":"WA",
    "wof:name":"Foot Locker",
    "wof:placetype":"venue"
},
  "geometry": {"coordinates":[-118.369563,46.057623],"type":"Point"}
}