{
  "type": "Feature",
  "properties": {
    "addr:full":"19613 81st Ave S Kent WA 98032",
    "addr:housenumber":"19613",
    "addr:postcode":"98032",
    "addr:street":"81St Ave S",
    "iso:country":"US",
    "sg:address":"19613 81st Ave S",
    "sg:city":"Kent",
    "sg:classifiers":[
        {
            "category":"Insurance",
            "subcategory":"Insurance Agent",
            "type":"Services"
        }
    ],
    "sg:phone":"+1 206 850 8585",
    "sg:postcode":"98032",
    "sg:province":"WA",
    "wof:name":"Save Max Insurance Servic",
    "wof:placetype":"venue"
},
  "geometry": {"coordinates":[-122.231295,47.425754],"type":"Point"}
}