{
  "type": "Feature",
  "properties": {
    "addr:full":"2431 70th Ave SE Mercer Island WA 98040",
    "addr:housenumber":"2431",
    "addr:postcode":"98040",
    "addr:street":"70Th Ave Se",
    "iso:country":"US",
    "sg:address":"2431 70th Ave SE",
    "sg:city":"Mercer Island",
    "sg:classifiers":[
        {
            "category":"Insurance",
            "subcategory":"Insurance Agent",
            "type":"Services"
        }
    ],
    "sg:phone":"+1 206 232 3333",
    "sg:postcode":"98040",
    "sg:province":"WA",
    "sg:website":"www.ebinw.com",
    "wof:name":"Employee Benefits Inc",
    "wof:placetype":"venue"
},
  "geometry": {"coordinates":[-122.24518,47.58843],"type":"Point"}
}