{
  "type": "Feature",
  "properties": {
    "addr:full":"26059 Hoehn Rd Sedro Woolley WA 98284",
    "addr:postcode":"26059;98284",
    "addr:street":"Hoehn Rd",
    "iso:country":"US",
    "sg:address":"26059 Hoehn Rd",
    "sg:city":"Sedro Woolley",
    "sg:classifiers":[
        {
            "category":"Wholesale",
            "subcategory":"Construction Materials",
            "type":"Manufacturing & Wholesale Goods"
        },
        {
            "category":"Shopping",
            "subcategory":"Computers & Home Electronics",
            "type":"Retail Goods"
        }
    ],
    "sg:phone":"+1 360 856 4151",
    "sg:postcode":"98284",
    "sg:province":"WA",
    "sg:tags":[
        "merchandise",
        "fence"
    ],
    "wof:name":"Invisible Fencing",
    "wof:placetype":"venue"
},
  "geometry": {"coordinates":[-122.17533,48.505963],"type":"Point"}
}