{
  "type": "Feature",
  "properties": {
    "addr:full":"1001 Madison Ave Yakima WA 98902",
    "addr:housenumber":"1001",
    "addr:postcode":"98902",
    "addr:street":"Madison Ave",
    "iso:country":"US",
    "sg:address":"1001 Madison Ave",
    "sg:city":"Yakima",
    "sg:classifiers":[
        {
            "category":"Retail",
            "subcategory":"Auto Repair",
            "type":"Services"
        }
    ],
    "sg:phone":"+1 509 248 4277",
    "sg:postcode":"98902",
    "sg:province":"WA",
    "sg:tags":[
        "truck"
    ],
    "wof:name":"All Better Truck Repair",
    "wof:placetype":"venue"
},
  "geometry": {"coordinates":[-120.52143599999999,46.616235],"type":"Point"}
}