{
  "type": "Feature",
  "properties": {
    "addr:full":"811 1st Ave Ste 100 Seattle WA 98104",
    "addr:housenumber":"811",
    "addr:postcode":"98104",
    "addr:street":"1St Ave Ste 100",
    "iso:country":"US",
    "sg:address":"811 1st Ave Ste 100",
    "sg:city":"Seattle",
    "sg:classifiers":[
        {
            "category":"Professional",
            "subcategory":"Lawyer & Legal Services",
            "type":"Services"
        }
    ],
    "sg:phone":"+1 206 623 5133",
    "sg:postcode":"98104",
    "sg:province":"WA",
    "sg:tags":[
        "divorce",
        "law",
        "family"
    ],
    "sg:website":"www.danceycassady.com",
    "wof:name":"Dancey & Cassady Llp",
    "wof:placetype":"venue"
},
  "geometry": {"coordinates":[-122.33533300000001,47.603577],"type":"Point"}
}