{
  "type": "Feature",
  "properties": {
    "addr:full":"21717 NE Dole Valley Rd Yacolt WA 98675",
    "addr:housenumber":"21717",
    "addr:postcode":"98675",
    "addr:street":"Ne Dole Valley Rd",
    "iso:country":"US",
    "sg:address":"21717 NE Dole Valley Rd",
    "sg:city":"Yacolt",
    "sg:classifiers":[
        {
            "category":"Building & Trades",
            "subcategory":"Construction",
            "type":"Services"
        }
    ],
    "sg:phone":"+1 360 686 3005",
    "sg:postcode":"98675",
    "sg:province":"WA",
    "sg:tags":[
        "residential"
    ],
    "wof:name":"You & I Construction Inc",
    "wof:placetype":"venue"
},
  "geometry": {"coordinates":[-122.337693,45.778425],"type":"Point"}
}