{
  "type": "Feature",
  "properties": {
    "addr:full":"2308 117th Ave NE Lake Stevens WA 98258",
    "addr:housenumber":"2308",
    "addr:postcode":"98258",
    "addr:street":"117Th Ave Ne",
    "iso:country":"US",
    "sg:address":"2308 117th Ave NE",
    "sg:city":"Lake Stevens",
    "sg:classifiers":[
        {
            "category":"Building & Trades",
            "subcategory":"Cleaning & Sanitation",
            "type":"Services"
        }
    ],
    "sg:phone":"+1 425 334 6466",
    "sg:postcode":"98258",
    "sg:province":"WA",
    "sg:tags":[
        "maintenance"
    ],
    "wof:name":"Sandi Clark",
    "wof:placetype":"venue"
},
  "geometry": {"coordinates":[-122.07252800000001,48.020746],"type":"Point"}
}