{
  "type": "Feature",
  "properties": {
    "addr:full":"1202 S 38th St Tacoma WA 98418",
    "addr:housenumber":"1202",
    "addr:postcode":"98418",
    "addr:street":"S 38Th St",
    "iso:country":"US",
    "sg:address":"1202 S 38th St",
    "sg:city":"Tacoma",
    "sg:classifiers":[
        {
            "category":"Food & Beverages",
            "subcategory":"Specialty",
            "type":"Retail Goods"
        }
    ],
    "sg:phone":"+1 253 471 0646",
    "sg:postcode":"98418",
    "sg:province":"WA",
    "sg:tags":[
        "bars",
        "espresso"
    ],
    "wof:name":"Jim's Daily Grind",
    "wof:placetype":"venue"
},
  "geometry": {"coordinates":[-122.450717,47.223058],"type":"Point"}
}