{
  "type": "Feature",
  "properties": {
    "addr:full":"1619 Harbor Ave SW Seattle WA 98126",
    "addr:housenumber":"1619",
    "addr:postcode":"98126",
    "addr:street":"Harbor Ave Sw",
    "iso:country":"US",
    "sg:address":"1619 Harbor Ave SW",
    "sg:city":"Seattle",
    "sg:classifiers":[
        {
            "category":"Coffee & Tea",
            "type":"Food & Drink"
        },
        {
            "category":"Food & Beverages",
            "subcategory":"Bakery",
            "type":"Retail Goods"
        }
    ],
    "sg:phone":"+1 206 938 0153",
    "sg:postcode":"98126",
    "sg:province":"WA",
    "sg:tags":[
        "sandwich"
    ],
    "sg:website":"www.bubblesonalki.net/bubbles/in...",
    "wof:name":"Bubbles on Alki",
    "wof:placetype":"venue"
},
  "geometry": {"coordinates":[-122.381354,47.589147],"type":"Point"}
}