{
  "type": "Feature",
  "properties": {
    "addr:full":"2115 112th St E Tacoma WA 98445",
    "addr:housenumber":"2115",
    "addr:postcode":"98445",
    "addr:street":"112Th St",
    "iso:country":"US",
    "sg:address":"2115 112th St E",
    "sg:city":"Tacoma",
    "sg:classifiers":[
        {
            "category":"Autos & Motor Vehicles",
            "subcategory":"Automobile Sales",
            "type":"Retail Goods"
        }
    ],
    "sg:phone":"+1 253 531 2047",
    "sg:postcode":"98445",
    "sg:province":"WA",
    "sg:tags":[
        "new",
        "car"
    ],
    "wof:name":"R D & K Enterprises",
    "wof:placetype":"venue"
},
  "geometry": {"coordinates":[-122.401366,47.154977],"type":"Point"}
}