{
  "type": "Feature",
  "properties": {
    "addr:full":"1371 Moore Rd Stanwood WA 98282",
    "addr:housenumber":"1371",
    "addr:postcode":"98282",
    "addr:street":"Moore Rd",
    "iso:country":"US",
    "sg:address":"1371 Moore Rd",
    "sg:city":"Stanwood",
    "sg:classifiers":[
        {
            "category":"Retail",
            "subcategory":"Auto Repair",
            "type":"Services"
        }
    ],
    "sg:phone":"+1 360 629 4125",
    "sg:postcode":"98282",
    "sg:province":"WA",
    "sg:tags":[
        "general"
    ],
    "wof:name":"Daniel Rogers Auto Repair",
    "wof:placetype":"venue"
},
  "geometry": {"coordinates":[-122.438911,48.256527],"type":"Point"}
}