{
  "type": "Feature",
  "properties": {
    "addr:full":"1118 Supermall Way Auburn WA 98001",
    "addr:housenumber":"1118",
    "addr:postcode":"98001",
    "addr:street":"Supermall Way",
    "iso:country":"US",
    "sg:address":"1118 Supermall Way",
    "sg:city":"Auburn",
    "sg:classifiers":[
        {
            "category":"Shopping",
            "subcategory":"Hobbies, Toys, & Games",
            "type":"Retail Goods"
        }
    ],
    "sg:phone":"+1 253 833 2993",
    "sg:postcode":"98001",
    "sg:province":"WA",
    "sg:tags":[
        "supply"
    ],
    "wof:name":"EB Games",
    "wof:placetype":"venue"
},
  "geometry": {"coordinates":[-122.24144099999999,47.29972],"type":"Point"}
}