{
  "type": "Feature",
  "properties": {
    "addr:full":"2208 G St Bellingham WA 98225",
    "addr:housenumber":"2208",
    "addr:postcode":"98225",
    "addr:street":"G St",
    "iso:country":"US",
    "sg:address":"2208 G St",
    "sg:city":"Bellingham",
    "sg:classifiers":[
        {
            "category":"Building & Trades",
            "subcategory":"Cleaning & Sanitation",
            "type":"Services"
        }
    ],
    "sg:phone":"+1 360 676 9061",
    "sg:postcode":"98225",
    "sg:province":"WA",
    "sg:tags":[
        "janitorial"
    ],
    "wof:name":"Northwest Protetive Coating",
    "wof:placetype":"venue"
},
  "geometry": {"coordinates":[-122.48018399999999,48.761065],"type":"Point"}
}