{
  "type": "Feature",
  "properties": {
    "addr:full":"653 NE Northlake Way Seattle WA 98105",
    "addr:housenumber":"653",
    "addr:postcode":"98105",
    "addr:street":"Ne Northlake Way",
    "iso:country":"US",
    "sg:address":"653 NE Northlake Way",
    "sg:city":"Seattle",
    "sg:classifiers":[
        {
            "category":"Freight",
            "type":"Transportation"
        }
    ],
    "sg:phone":"+1 206 783 0792",
    "sg:postcode":"98105",
    "sg:province":"WA",
    "wof:name":"Dahl Tug & Barge Inc",
    "wof:placetype":"venue"
},
  "geometry": {"coordinates":[-122.32206100000001,47.654427],"type":"Point"}
}