{
  "type": "Feature",
  "properties": {
    "addr:full":"9523 314th Ave SE Issaquah WA 98027",
    "addr:housenumber":"9523",
    "addr:postcode":"98027",
    "addr:street":"314Th Ave Se",
    "iso:country":"US",
    "sg:address":"9523 314th Ave SE",
    "sg:city":"Issaquah",
    "sg:classifiers":[
        {
            "category":"Building & Trades",
            "subcategory":"Construction",
            "type":"Services"
        }
    ],
    "sg:phone":"+1 425 260 0214",
    "sg:postcode":"98027",
    "sg:province":"WA",
    "sg:tags":[
        "house"
    ],
    "wof:name":"Webb Construction",
    "wof:placetype":"venue"
},
  "geometry": {"coordinates":[-121.91911399999999,47.512632],"type":"Point"}
}