{
  "type": "Feature",
  "properties": {
    "addr:full":"3720 31st Ave NW Gig Harbor WA 98335",
    "addr:housenumber":"3720",
    "addr:postcode":"98335",
    "addr:street":"31St Ave Nw",
    "iso:country":"US",
    "sg:address":"3720 31st Ave NW",
    "sg:city":"Gig Harbor",
    "sg:classifiers":[
        {
            "category":"Banks & Credit Unions",
            "subcategory":"Bank",
            "type":"Services"
        }
    ],
    "sg:phone":"+1 253 858 2407",
    "sg:postcode":"98335",
    "sg:province":"WA",
    "sg:tags":[
        "other",
        "plan",
        "card"
    ],
    "wof:name":"Michael Davis American Express",
    "wof:placetype":"venue"
},
  "geometry": {"coordinates":[-122.580032,47.293185],"type":"Point"}
}