{
  "type": "Feature",
  "properties": {
    "addr:full":"1930 Rudkin Rd Union Gap WA 98903",
    "addr:housenumber":"1930",
    "addr:postcode":"98903",
    "addr:street":"Rudkin Rd",
    "iso:country":"US",
    "sg:address":"1930 Rudkin Rd",
    "sg:city":"Union Gap",
    "sg:classifiers":[
        {
            "category":"Wholesale",
            "subcategory":"Machinery & Supplies",
            "type":"Manufacturing & Wholesale Goods"
        }
    ],
    "sg:phone":"+1 509 248 0580",
    "sg:postcode":"98903",
    "sg:province":"WA",
    "sg:tags":[
        "equipment",
        "hydraulic"
    ],
    "wof:name":"Spencer Industries Inc",
    "wof:placetype":"venue"
},
  "geometry": {"coordinates":[-120.472416,46.57739],"type":"Point"}
}