{
  "type": "Feature",
  "properties": {
    "addr:full":"1627 Tower Rd Castle Rock WA 98611",
    "addr:housenumber":"1627",
    "addr:postcode":"98611",
    "addr:street":"Tower Rd",
    "iso:country":"US",
    "sg:address":"1627 Tower Rd",
    "sg:city":"Castle Rock",
    "sg:classifiers":[
        {
            "category":"Manufacturing",
            "subcategory":"Lumber",
            "type":"Manufacturing & Wholesale Goods"
        }
    ],
    "sg:phone":"+1 360 274 4556",
    "sg:postcode":"98611",
    "sg:province":"WA",
    "sg:tags":[
        "logging",
        "contractor"
    ],
    "wof:name":"Gould & Sons Logging",
    "wof:placetype":"venue"
},
  "geometry": {"coordinates":[-122.844471,46.329665],"type":"Point"}
}