{
  "type": "Feature",
  "properties": {
    "addr:full":"824 Village Way Monroe WA 98272",
    "addr:housenumber":"824",
    "addr:postcode":"98272",
    "addr:street":"Village Way",
    "iso:country":"US",
    "sg:address":"824 Village Way",
    "sg:city":"Monroe",
    "sg:classifiers":[
        {
            "category":"Organizations",
            "subcategory":"Non-profit Organization",
            "type":"Services"
        }
    ],
    "sg:phone":"+1 360 794 6359",
    "sg:postcode":"98272",
    "sg:province":"WA",
    "wof:name":"East County Senior Ctr",
    "wof:placetype":"venue"
},
  "geometry": {"coordinates":[-121.983378,47.849069],"type":"Point"}
}