{
  "type": "Feature",
  "properties": {
    "addr:full":"6109 176th St SW Lynnwood WA 98037",
    "addr:housenumber":"6109",
    "addr:postcode":"98037",
    "addr:street":"176Th St Sw",
    "iso:country":"US",
    "sg:address":"6109 176th St SW",
    "sg:city":"Lynnwood",
    "sg:classifiers":[
        {
            "category":"Social Services",
            "type":"Services"
        }
    ],
    "sg:phone":"+1 425 745 0935",
    "sg:postcode":"98037",
    "sg:province":"WA",
    "wof:name":"Tamara I Piwen",
    "wof:placetype":"venue"
},
  "geometry": {"coordinates":[-122.315371,47.839218],"type":"Point"}
}