{
  "type": "Feature",
  "properties": {
    "addr:full":"10620 NE 8th St Ste 100 Bellevue WA 98004",
    "addr:housenumber":"10620",
    "addr:postcode":"98004",
    "addr:street":"Ne 8Th St Ste 100",
    "iso:country":"US",
    "sg:address":"10620 NE 8th St Ste 100",
    "sg:city":"Bellevue",
    "sg:classifiers":[
        {
            "category":"Home & Garden",
            "subcategory":"Furniture",
            "type":"Retail Goods"
        }
    ],
    "sg:phone":"+1 425 454 8686",
    "sg:postcode":"98004",
    "sg:province":"WA",
    "sg:tags":[
        "store"
    ],
    "wof:name":"Estate Interiors",
    "wof:placetype":"venue"
},
  "geometry": {"coordinates":[-122.198272,47.617792],"type":"Point"}
}