{
  "type": "Feature",
  "properties": {
    "addr:full":"1728 McRae Rd NW Arlington WA 98223",
    "addr:housenumber":"1728",
    "addr:postcode":"98223",
    "addr:street":"Mcrae Rd Nw",
    "iso:country":"US",
    "sg:address":"1728 McRae Rd NW",
    "sg:city":"Arlington",
    "sg:classifiers":[
        {
            "category":"Building & Trades",
            "subcategory":"Cleaning & Sanitation",
            "type":"Services"
        }
    ],
    "sg:phone":"+1 360 201 1947",
    "sg:postcode":"98223",
    "sg:province":"WA",
    "sg:tags":[
        "maintenance"
    ],
    "wof:name":"Personal Touch Maintenace",
    "wof:placetype":"venue"
},
  "geometry": {"coordinates":[-122.25617800000001,48.143313],"type":"Point"}
}