{
  "type": "Feature",
  "properties": {
    "addr:full":"12443 Bel Red Rd Bellevue WA 98005",
    "addr:housenumber":"12443",
    "addr:postcode":"98005",
    "addr:street":"Bel Red Rd",
    "iso:country":"US",
    "sg:address":"12443 Bel Red Rd",
    "sg:city":"Bellevue",
    "sg:classifiers":[
        {
            "category":"Banks & Credit Unions",
            "subcategory":"Bank",
            "type":"Services"
        }
    ],
    "sg:phone":"+1 425 454 1042",
    "sg:postcode":"98005",
    "sg:province":"WA",
    "sg:tags":[
        "loan",
        "real estate"
    ],
    "sg:website":"www.firstnlc.com",
    "wof:name":"First NLC Financial Svc",
    "wof:placetype":"venue"
},
  "geometry": {"coordinates":[-122.16757800000001,47.621309],"type":"Point"}
}