{
  "type": "Feature",
  "properties": {
    "addr:full":"6010 Mount Tacoma Dr SW Lakewood WA 98499",
    "addr:housenumber":"6010",
    "addr:postcode":"98499",
    "addr:street":"Mount Tacoma Dr Sw",
    "iso:country":"US",
    "sg:address":"6010 Mount Tacoma Dr SW",
    "sg:city":"Lakewood",
    "sg:classifiers":[
        {
            "category":"Arena",
            "subcategory":"Sports Club",
            "type":"Entertainment"
        }
    ],
    "sg:phone":"+1 253 582 7200",
    "sg:postcode":"98499",
    "sg:province":"WA",
    "sg:tags":[
        "martial art"
    ],
    "sg:website":"www.theshadowwarriors.com",
    "wof:name":"Tacoma Shadow Warriors",
    "wof:placetype":"venue"
},
  "geometry": {"coordinates":[-122.516445,47.170142],"type":"Point"}
}