{
  "type": "Feature",
  "properties": {
    "addr:full":"5785 Everson Goshen Rd Bellingham WA 98226",
    "addr:housenumber":"5785",
    "addr:postcode":"98226",
    "addr:street":"Everson Goshen Rd",
    "iso:country":"US",
    "sg:address":"5785 Everson Goshen Rd",
    "sg:city":"Bellingham",
    "sg:classifiers":[
        {
            "category":"Wholesale",
            "subcategory":"Toys & Hobbies",
            "type":"Manufacturing & Wholesale Goods"
        }
    ],
    "sg:phone":"+1 360 966 3019",
    "sg:postcode":"98226",
    "sg:province":"WA",
    "sg:tags":[
        "wholesaler"
    ],
    "wof:name":"Payn Run Inc",
    "wof:placetype":"venue"
},
  "geometry": {"coordinates":[-122.376454,48.841985],"type":"Point"}
}