{
  "type": "Feature",
  "properties": {
    "addr:full":"808 W Main Ave Spokane WA 99201",
    "addr:housenumber":"808",
    "addr:postcode":"99201",
    "addr:street":"W Main Ave",
    "iso:country":"US",
    "sg:address":"808 W Main Ave",
    "sg:city":"Spokane",
    "sg:classifiers":[
        {
            "category":"Ice Cream",
            "type":"Food & Drink"
        }
    ],
    "sg:menulink":"http://www.allmenus.com/wa/spokane/217468-ben--jerrys/menu/",
    "sg:postcode":"99201",
    "sg:province":"WA",
    "sg:tags":[
        "american"
    ],
    "wof:name":"Ben & Jerry's",
    "wof:placetype":"venue"
},
  "geometry": {"coordinates":[-117.42394,47.659428],"type":"Point"}
}