{
  "type": "Feature",
  "properties": {
    "addr:full":"18411 57th Ave NE Kenmore WA 98028",
    "addr:housenumber":"18411",
    "addr:postcode":"98028",
    "addr:street":"57Th Ave Ne",
    "iso:country":"US",
    "sg:address":"18411 57th Ave NE",
    "sg:city":"Kenmore",
    "sg:classifiers":[
        {
            "category":"Shopping",
            "subcategory":"Florist",
            "type":"Retail Goods"
        }
    ],
    "sg:phone":"+1 425 486 4644",
    "sg:postcode":"98028",
    "sg:province":"WA",
    "wof:name":"La Maison Des Fleurs",
    "wof:placetype":"venue"
},
  "geometry": {"coordinates":[-122.268635,47.762531],"type":"Point"}
}