{
  "type": "Feature",
  "properties": {
    "addr:full":"21217 23rd Street Ct E Sumner WA 98391",
    "addr:housenumber":"21217",
    "addr:postcode":"98391",
    "addr:street":"23Rd Street Ct E",
    "iso:country":"US",
    "sg:address":"21217 23rd Street Ct E",
    "sg:city":"Sumner",
    "sg:classifiers":[
        {
            "category":"Professional",
            "type":"Services"
        }
    ],
    "sg:phone":"+1 253 299 6419",
    "sg:postcode":"98391",
    "sg:province":"WA",
    "wof:name":"Affordable Mobile Service",
    "wof:placetype":"venue"
},
  "geometry": {"coordinates":[-122.14434900000001,47.236142],"type":"Point"}
}