{
  "type": "Feature",
  "properties": {
    "addr:full":"838 S Trafton St Tacoma WA 98405",
    "addr:housenumber":"838",
    "addr:postcode":"98405",
    "addr:street":"S Trafton St",
    "iso:country":"US",
    "sg:address":"838 S Trafton St",
    "sg:city":"Tacoma",
    "sg:classifiers":[
        {
            "category":"Shopping",
            "subcategory":"Clothing, Apparel, & Fashions",
            "type":"Retail Goods"
        }
    ],
    "sg:phone":"+1 253 572 8549",
    "sg:postcode":"98405",
    "sg:province":"WA",
    "wof:name":"Parnell Products",
    "wof:placetype":"venue"
},
  "geometry": {"coordinates":[-122.467044,47.252234],"type":"Point"}
}