{
  "type": "Feature",
  "properties": {
    "addr:full":"1011 8th St Anacortes WA 98221",
    "addr:housenumber":"1011",
    "addr:postcode":"98221",
    "addr:street":"8Th St",
    "iso:country":"US",
    "sg:address":"1011 8th St",
    "sg:city":"Anacortes",
    "sg:classifiers":[
        {
            "category":"Professional",
            "subcategory":"Lawyer & Legal Services",
            "type":"Services"
        }
    ],
    "sg:phone":"+1 360 293 5094",
    "sg:postcode":"98221",
    "sg:province":"WA",
    "sg:tags":[
        "attorney"
    ],
    "wof:name":"Stephen C Schutt",
    "wof:placetype":"venue"
},
  "geometry": {"coordinates":[-122.614003,48.515788],"type":"Point"}
}