{
  "type": "Feature",
  "properties": {
    "iso:country":"US",
    "sg:address":"2624 Rd N NE",
    "sg:city":"Moses Lake",
    "sg:classifiers":[
        {
            "category":"Wholesale",
            "subcategory":"Farm Supplies",
            "type":"Manufacturing & Wholesale Goods"
        }
    ],
    "sg:phone":"+1 509 766 7772",
    "sg:postcode":"98837",
    "sg:province":"WA",
    "sg:tags":[
        "fertilizer"
    ],
    "wof:name":"Tri-River Chemical Company",
    "wof:placetype":"venue"
},
  "geometry": {"coordinates":[-119.193371,47.128456],"type":"Point"}
}