{
  "type": "Feature",
  "properties": {
    "addr:full":"1224 57th Dr SE Auburn WA 98092",
    "addr:housenumber":"1224",
    "addr:postcode":"98092",
    "addr:street":"57Th Dr Se",
    "iso:country":"US",
    "sg:address":"1224 57th Dr SE",
    "sg:city":"Auburn",
    "sg:classifiers":[
        {
            "category":"Professional",
            "subcategory":"Business Services",
            "type":"Services"
        }
    ],
    "sg:phone":"+1 253 939 9422",
    "sg:postcode":"98092",
    "sg:province":"WA",
    "sg:tags":[
        "event"
    ],
    "wof:name":"Creative Celebrations",
    "wof:placetype":"venue"
},
  "geometry": {"coordinates":[-122.215158,47.25902],"type":"Point"}
}