{
  "type": "Feature",
  "properties": {
    "addr:full":"2631 175th Ave NE Redmond WA 98052",
    "addr:housenumber":"2631",
    "addr:postcode":"98052",
    "addr:street":"175Th Ave Ne",
    "iso:country":"US",
    "sg:address":"2631 175th Ave NE",
    "sg:city":"Redmond",
    "sg:classifiers":[
        {
            "category":"Building & Trades",
            "subcategory":"Construction",
            "type":"Services"
        },
        {
            "category":"Manufacturing",
            "subcategory":"Building Materials",
            "type":"Manufacturing & Wholesale Goods"
        }
    ],
    "sg:phone":"+1 425 869 0845",
    "sg:postcode":"98052",
    "sg:province":"WA",
    "sg:tags":[
        "roofing",
        "sheet",
        "work",
        "metal",
        "contractor",
        "siding"
    ],
    "sg:website":"http://www.edcaroofing.com",
    "wof:name":"Edca Roofing Inc",
    "wof:placetype":"venue"
},
  "geometry": {"coordinates":[-122.10627100000001,47.633305],"type":"Point"}
}