{
  "type": "Feature",
  "properties": {
    "iso:country":"US",
    "sg:address":"845 King Rd",
    "sg:city":"Winlock",
    "sg:classifiers":[
        {
            "category":"Building & Trades",
            "subcategory":"Construction",
            "type":"Services"
        }
    ],
    "sg:phone":"+1 360 785 0815",
    "sg:postcode":"98596",
    "sg:province":"WA",
    "sg:tags":[
        "general",
        "contractor"
    ],
    "wof:name":"T Enterprises",
    "wof:placetype":"venue"
},
  "geometry": {"coordinates":[-122.958316,46.496185],"type":"Point"}
}