{
  "type": "Feature",
  "properties": {
    "addr:full":"404 E Harrison St Seattle WA 98102",
    "addr:housenumber":"404",
    "addr:postcode":"98102",
    "addr:street":"E Harrison St",
    "iso:country":"US",
    "sg:address":"404 E Harrison St",
    "sg:city":"Seattle",
    "sg:classifiers":[
        {
            "category":"Shopping",
            "subcategory":"Discount & Variety Stores",
            "type":"Retail Goods"
        }
    ],
    "sg:phone":"+1 206 328 7925",
    "sg:postcode":"98102",
    "sg:province":"WA",
    "wof:name":"Ddq S Collectibles",
    "wof:placetype":"venue"
},
  "geometry": {"coordinates":[-122.325343,47.622059],"type":"Point"}
}