{
  "type": "Feature",
  "properties": {
    "addr:full":"514 S 3rd St Yakima WA 98901",
    "addr:housenumber":"514",
    "addr:postcode":"98901",
    "addr:street":"S 3Rd St",
    "iso:country":"US",
    "sg:address":"514 S 3rd St",
    "sg:city":"Yakima",
    "sg:classifiers":[
        {
            "category":"Professional",
            "type":"Services"
        }
    ],
    "sg:phone":"+1 509 457 1149",
    "sg:postcode":"98901",
    "sg:province":"WA",
    "wof:name":"Ramirez Motors",
    "wof:placetype":"venue"
},
  "geometry": {"coordinates":[-120.499571,46.595553],"type":"Point"}
}