{
  "type": "Feature",
  "properties": {
    "addr:full":"26223 164th Ave SE Kent WA 98042",
    "addr:housenumber":"26223",
    "addr:postcode":"98042",
    "addr:street":"164Th Ave Se",
    "iso:country":"US",
    "sg:address":"26223 164th Ave SE",
    "sg:city":"Kent",
    "sg:classifiers":[
        {
            "category":"Organizations",
            "subcategory":"Religious Organization",
            "type":"Services"
        }
    ],
    "sg:phone":"+1 253 631 8853",
    "sg:postcode":"98042",
    "sg:province":"WA",
    "wof:name":"Kentwood Family Church",
    "wof:placetype":"venue"
},
  "geometry": {"coordinates":[-122.12307199999999,47.366745],"type":"Point"}
}