{
  "type": "Feature",
  "properties": {
    "addr:full":"6421 Latona Ave NE Seattle WA 98115",
    "addr:housenumber":"6421",
    "addr:postcode":"98115",
    "addr:street":"Latona Ave Ne",
    "iso:country":"US",
    "sg:address":"6421 Latona Ave NE",
    "sg:city":"Seattle",
    "sg:phone":"+1 206 526 1188",
    "sg:postcode":"98115",
    "sg:province":"WA",
    "sg:website":"http://monasseattle.com",
    "wof:name":"MoNA's",
    "wof:placetype":"venue"
},
  "geometry": {"coordinates":[-122.325433,47.675286],"type":"Point"}
}