{
  "type": "Feature",
  "properties": {
    "addr:full":"3591 Tjossem Rd Ellensburg WA 98926",
    "addr:housenumber":"3591",
    "addr:postcode":"98926",
    "addr:street":"Tjossem Rd",
    "iso:country":"US",
    "sg:address":"3591 Tjossem Rd",
    "sg:city":"Ellensburg",
    "sg:classifiers":[
        {
            "category":"Farming",
            "subcategory":"Livestock Farm",
            "type":"Manufacturing & Wholesale Goods"
        }
    ],
    "sg:phone":"+1 509 925 6357",
    "sg:postcode":"98926",
    "sg:province":"WA",
    "sg:tags":[
        "ranch"
    ],
    "wof:name":"Karen Sue Poulsen",
    "wof:placetype":"venue"
},
  "geometry": {"coordinates":[-120.488107,46.963081],"type":"Point"}
}