{
  "type": "Feature",
  "properties": {
    "iso:country":"US",
    "sg:address":"2709 Marine Dr",
    "sg:city":"Bremerton",
    "sg:classifiers":[
        {
            "category":"Professional",
            "subcategory":"Business Services",
            "type":"Services"
        }
    ],
    "sg:phone":"+1 360 782 2469",
    "sg:postcode":"98312",
    "sg:province":"WA",
    "wof:name":"Sound Voices",
    "wof:placetype":"venue"
},
  "geometry": {"coordinates":[-122.675956,47.587449],"type":"Point"}
}