{
  "type": "Feature",
  "properties": {
    "addr:full":"21400 Pacific Hwy S Seattle WA 98198",
    "addr:housenumber":"21400",
    "addr:postcode":"98198",
    "addr:street":"Pacific Hwy S",
    "iso:country":"US",
    "sg:address":"21400 Pacific Hwy S",
    "sg:city":"Seattle",
    "sg:classifiers":[
        {
            "category":"Freight",
            "type":"Transportation"
        }
    ],
    "sg:phone":"+1 206 870 1997",
    "sg:postcode":"98198",
    "sg:province":"WA",
    "sg:tags":[
        "arrangement"
    ],
    "wof:name":"Hecny Transportation Inc",
    "wof:placetype":"venue"
},
  "geometry": {"coordinates":[-122.29798099999999,47.410069],"type":"Point"}
}