{
  "type": "Feature",
  "properties": {
    "addr:full":"30986 E Lake Morton Dr SE Kent WA 98042",
    "addr:housenumber":"30986",
    "addr:postcode":"98042",
    "addr:street":"E Lake Morton Dr Se",
    "iso:country":"US",
    "sg:address":"30986 E Lake Morton Dr SE",
    "sg:city":"Kent",
    "sg:classifiers":[
        {
            "category":"Building & Trades",
            "subcategory":"Construction",
            "type":"Services"
        }
    ],
    "sg:phone":"+1 253 638 3113",
    "sg:postcode":"98042",
    "sg:province":"WA",
    "sg:tags":[
        "system",
        "specialty",
        "heating",
        "contractor",
        "air conditioning"
    ],
    "wof:name":"Jim Just Plumbing Heating Inc",
    "wof:placetype":"venue"
},
  "geometry": {"coordinates":[-122.083217,47.327318],"type":"Point"}
}