{
  "type": "Feature",
  "properties": {
    "addr:full":"5243 S Delphi Rd Langley WA 98260",
    "addr:housenumber":"5243",
    "addr:postcode":"98260",
    "addr:street":"S Delphi Rd",
    "iso:country":"US",
    "sg:address":"5243 S Delphi Rd",
    "sg:city":"Langley",
    "sg:classifiers":[
        {
            "category":"Retail",
            "subcategory":"Repair Shop",
            "type":"Services"
        }
    ],
    "sg:phone":"+1 360 321 1252",
    "sg:postcode":"98260",
    "sg:province":"WA",
    "sg:tags":[
        "electrical"
    ],
    "wof:name":"Bobs Appliance Service Center",
    "wof:placetype":"venue"
},
  "geometry": {"coordinates":[-122.456306,48.019501],"type":"Point"}
}