{
  "type": "Feature",
  "properties": {
    "addr:full":"2055 S Belair Dr Moses Lake WA 98837",
    "addr:housenumber":"2055",
    "addr:postcode":"98837",
    "addr:street":"S Belair Dr",
    "iso:country":"US",
    "sg:address":"2055 S Belair Dr",
    "sg:city":"Moses Lake",
    "sg:classifiers":[
        {
            "category":"Professional",
            "subcategory":"Management & Consulting",
            "type":"Services"
        }
    ],
    "sg:phone":"+1 509 765 3929",
    "sg:postcode":"98837",
    "sg:province":"WA",
    "sg:tags":[
        "public",
        "relations"
    ],
    "wof:name":"Kdh Enterprise",
    "wof:placetype":"venue"
},
  "geometry": {"coordinates":[-119.280226,47.106821],"type":"Point"}
}