{
  "type": "Feature",
  "properties": {
    "addr:full":"3517 Talbot Rd S Renton WA 98055",
    "addr:housenumber":"3517",
    "addr:postcode":"98055",
    "addr:street":"Talbot Rd S",
    "iso:country":"US",
    "sg:address":"3517 Talbot Rd S",
    "sg:city":"Renton",
    "sg:classifiers":[
        {
            "category":"Professional",
            "subcategory":"Detective & Security Services",
            "type":"Services"
        }
    ],
    "sg:phone":"+1 425 226 4155",
    "sg:postcode":"98055",
    "sg:province":"WA",
    "sg:tags":[
        "firm",
        "private"
    ],
    "wof:name":"Libra Security & Protection",
    "wof:placetype":"venue"
},
  "geometry": {"coordinates":[-122.210948,47.447759],"type":"Point"}
}