{
  "type": "Feature",
  "properties": {
    "addr:full":"2922 62nd Ave NE Tacoma WA 98422",
    "addr:housenumber":"2922",
    "addr:postcode":"98422",
    "addr:street":"62Nd Ave Ne",
    "iso:country":"US",
    "sg:address":"2922 62nd Ave NE",
    "sg:city":"Tacoma",
    "sg:classifiers":[
        {
            "category":"Manufacturing",
            "subcategory":"Retail Goods",
            "type":"Manufacturing & Wholesale Goods"
        }
    ],
    "sg:phone":"+1 253 927 4763",
    "sg:postcode":"98422",
    "sg:province":"WA",
    "sg:tags":[
        "product",
        "mfg"
    ],
    "wof:name":"Hug",
    "wof:placetype":"venue"
},
  "geometry": {"coordinates":[-122.36484299999999,47.283579],"type":"Point"}
}