{
  "type": "Feature",
  "properties": {
    "addr:full":"2514 Magnolia Blvd W Seattle WA 98199",
    "addr:housenumber":"2514",
    "addr:postcode":"98199",
    "addr:street":"Magnolia Blvd W",
    "iso:country":"US",
    "sg:address":"2514 Magnolia Blvd W",
    "sg:city":"Seattle",
    "sg:classifiers":[
        {
            "category":"Shopping",
            "type":"Retail Goods"
        }
    ],
    "sg:phone":"+1 206 283 7408",
    "sg:postcode":"98199",
    "sg:province":"WA",
    "sg:tags":[
        "merchandise",
        "lead",
        "mfg"
    ],
    "wof:name":"Designs By Cecily Mitchell",
    "wof:placetype":"venue"
},
  "geometry": {"coordinates":[-122.413408,47.641618],"type":"Point"}
}