{
  "type": "Feature",
  "properties": {
    "addr:full":"9310 4th Ave S Seattle WA 98108",
    "addr:housenumber":"9310",
    "addr:postcode":"98108",
    "addr:street":"4Th Ave S",
    "iso:country":"US",
    "sg:address":"9310 4th Ave S",
    "sg:city":"Seattle",
    "sg:classifiers":[
        {
            "category":"Shopping",
            "subcategory":"Stationery & Office Supplies",
            "type":"Retail Goods"
        },
        {
            "category":"Shopping",
            "subcategory":"Discount & Variety Stores",
            "type":"Retail Goods"
        }
    ],
    "sg:phone":"+1 206 545 1850",
    "sg:postcode":"98108",
    "sg:province":"WA",
    "sg:tags":[
        "wholesale",
        "envelope"
    ],
    "sg:website":"www.rgroup.com",
    "wof:name":"The Revere Group",
    "wof:placetype":"venue"
},
  "geometry": {"coordinates":[-122.329559,47.520802],"type":"Point"}
}