{
  "type": "Feature",
  "properties": {
    "addr:full":"1109 Dyer Rd Sultan WA 98294",
    "addr:housenumber":"1109",
    "addr:postcode":"98294",
    "addr:street":"Dyer Rd",
    "iso:country":"US",
    "sg:address":"1109 Dyer Rd",
    "sg:city":"Sultan",
    "sg:classifiers":[
        {
            "category":"Social Services",
            "subcategory":"Child Care",
            "type":"Services"
        }
    ],
    "sg:phone":"+1 360 793 2911",
    "sg:postcode":"98294",
    "sg:province":"WA",
    "sg:tags":[
        "day"
    ],
    "wof:name":"Precious Treasures",
    "wof:placetype":"venue"
},
  "geometry": {"coordinates":[-121.802632,47.860565],"type":"Point"}
}