{
  "type": "Feature",
  "properties": {
    "addr:full":"2201 Ahtanum Rd Yakima WA 98903",
    "addr:housenumber":"2201",
    "addr:postcode":"98903",
    "addr:street":"Ahtanum Rd",
    "iso:country":"US",
    "sg:address":"2201 Ahtanum Rd",
    "sg:city":"Yakima",
    "sg:classifiers":[
        {
            "category":"Wholesale",
            "subcategory":"Machinery & Supplies",
            "type":"Manufacturing & Wholesale Goods"
        }
    ],
    "sg:phone":"+1 509 249 8200",
    "sg:postcode":"98903",
    "sg:province":"WA",
    "sg:tags":[
        "equipment",
        "industrial"
    ],
    "wof:name":"F E I Inc",
    "wof:placetype":"venue"
},
  "geometry": {"coordinates":[-120.542753,46.55796],"type":"Point"}
}