{
  "type": "Feature",
  "properties": {
    "addr:full":"2222 2nd Ave Seattle WA 98121",
    "addr:housenumber":"2222",
    "addr:postcode":"98121",
    "addr:street":"2Nd Ave",
    "iso:country":"US",
    "sg:address":"2222 2nd Ave",
    "sg:city":"Seattle",
    "sg:classifiers":[
        {
            "category":"Bars & Pubs",
            "subcategory":"Lounge",
            "type":"Food & Drink"
        },
        {
            "category":"Restaurant",
            "type":"Food & Drink"
        }
    ],
    "sg:phone":"+1 206 441 4449",
    "sg:postcode":"98121",
    "sg:province":"WA",
    "sg:tags":[
        "thai"
    ],
    "sg:website":"www.buddhabelltown.com",
    "wof:name":"Buddha Belltown",
    "wof:placetype":"venue"
},
  "geometry": {"coordinates":[-122.34501299999999,47.613817],"type":"Point"}
}