{
  "type": "Feature",
  "properties": {
    "addr:full":"807 W Ave Anacortes WA 98221",
    "addr:housenumber":"807",
    "addr:postcode":"98221",
    "addr:street":"W Ave",
    "iso:country":"US",
    "sg:address":"807 W Ave",
    "sg:city":"Anacortes",
    "sg:classifiers":[
        {
            "category":"Professional",
            "subcategory":"Business Services",
            "type":"Services"
        }
    ],
    "sg:phone":"+1 360 588 8995",
    "sg:postcode":"98221",
    "sg:province":"WA",
    "sg:tags":[
        "appraiser"
    ],
    "wof:name":"Appraisalink For Art & Antique",
    "wof:placetype":"venue"
},
  "geometry": {"coordinates":[-122.598939,48.513535],"type":"Point"}
}