{
  "type": "Feature",
  "properties": {
    "addr:full":"3724 Wollochet Dr NW Gig Harbor WA 98335",
    "addr:housenumber":"3724",
    "addr:postcode":"98335",
    "addr:street":"Wollochet Dr Nw",
    "iso:country":"US",
    "sg:address":"3724 Wollochet Dr NW",
    "sg:city":"Gig Harbor",
    "sg:classifiers":[
        {
            "category":"Building & Trades",
            "subcategory":"Construction",
            "type":"Services"
        }
    ],
    "sg:phone":"+1 253 265 2235",
    "sg:postcode":"98335",
    "sg:province":"WA",
    "sg:tags":[
        "excavating",
        "contractor"
    ],
    "wof:name":"Graham G R & Sons Co Inc",
    "wof:placetype":"venue"
},
  "geometry": {"coordinates":[-122.614422,47.289611],"type":"Point"}
}