{
  "type": "Feature",
  "properties": {
    "iso:country":"US",
    "sg:address":"3214 S Division St",
    "sg:city":"Spokane",
    "sg:classifiers":[
        {
            "category":"Retail",
            "subcategory":"Laundry & Dry Cleaning",
            "type":"Services"
        }
    ],
    "sg:phone":"+1 509 747 2522",
    "sg:postcode":"99203",
    "sg:province":"WA",
    "sg:tags":[
        "cleaners",
        "rug",
        "carpet"
    ],
    "wof:name":"Jet-Hot Professional Carpet",
    "wof:placetype":"venue"
},
  "geometry": {"coordinates":[-117.411423,47.624657],"type":"Point"}
}