{
  "type": "Feature",
  "properties": {
    "addr:full":"215 E Naches Ave Selah WA 98942",
    "addr:housenumber":"215",
    "addr:postcode":"98942",
    "addr:street":"E Naches Ave",
    "iso:country":"US",
    "sg:address":"215 E Naches Ave",
    "sg:city":"Selah",
    "sg:classifiers":[
        {
            "category":"Retail",
            "subcategory":"Repair Shop",
            "type":"Services"
        }
    ],
    "sg:phone":"+1 509 697 8557",
    "sg:postcode":"98942",
    "sg:province":"WA",
    "sg:tags":[
        "air",
        "heating",
        "conditioning"
    ],
    "wof:name":"Advantage Heating & Air Cond",
    "wof:placetype":"venue"
},
  "geometry": {"coordinates":[-120.525947,46.654135],"type":"Point"}
}