{
  "type": "Feature",
  "properties": {
    "addr:full":"1224 Harris Ave Bellingham WA 98225",
    "addr:housenumber":"1224",
    "addr:postcode":"98225",
    "addr:street":"Harris Ave",
    "iso:country":"US",
    "sg:address":"1224 Harris Ave",
    "sg:city":"Bellingham",
    "sg:classifiers":[
        {
            "category":"Coffee & Tea",
            "type":"Food & Drink"
        },
        {
            "category":"Restaurant",
            "type":"Food & Drink"
        }
    ],
    "sg:phone":"+1 360 676 9995",
    "sg:postcode":"98225",
    "sg:province":"WA",
    "sg:tags":[
        "thai",
        "espresso",
        "asian",
        "pan"
    ],
    "wof:name":"On Rice Thai Bistro",
    "wof:placetype":"venue"
},
  "geometry": {"coordinates":[-122.501929,48.720153],"type":"Point"}
}