{
  "type": "Feature",
  "properties": {
    "addr:full":"4846 Johnson Point Rd NE Olympia WA 98516",
    "addr:housenumber":"4846",
    "addr:postcode":"98516",
    "addr:street":"Johnson Point Rd Ne",
    "iso:country":"US",
    "sg:address":"4846 Johnson Point Rd NE",
    "sg:city":"Olympia",
    "sg:classifiers":[
        {
            "category":"Restaurant",
            "type":"Food & Drink"
        }
    ],
    "sg:phone":"+1 360 413 7146",
    "sg:postcode":"98516",
    "sg:province":"WA",
    "sg:tags":[
        "eating"
    ],
    "wof:name":"Mexican Stuff LLC",
    "wof:placetype":"venue"
},
  "geometry": {"coordinates":[-122.818089,47.102609],"type":"Point"}
}