{
  "type": "Feature",
  "properties": {
    "addr:full":"19022 NE 165th Pl Woodinville WA 98072",
    "addr:housenumber":"19022",
    "addr:postcode":"98072",
    "addr:street":"Ne 165Th Pl",
    "iso:country":"US",
    "sg:address":"19022 NE 165th Pl",
    "sg:city":"Woodinville",
    "sg:classifiers":[
        {
            "category":"Manufacturing",
            "subcategory":"Building Materials",
            "type":"Manufacturing & Wholesale Goods"
        }
    ],
    "sg:phone":"+1 425 788 3261",
    "sg:postcode":"98072",
    "sg:province":"WA",
    "sg:tags":[
        "mfg"
    ],
    "wof:name":"Amanco Woodworks",
    "wof:placetype":"venue"
},
  "geometry": {"coordinates":[-122.083466,47.748129],"type":"Point"}
}