{
  "type": "Feature",
  "properties": {
    "addr:full":"31806 54th Ave SW Federal Way WA 98023",
    "addr:housenumber":"31806",
    "addr:postcode":"98023",
    "addr:street":"54Th Ave Sw Federal Way",
    "iso:country":"US",
    "sg:address":"31806 54th Ave SW",
    "sg:city":"Federal Way",
    "sg:classifiers":[
        {
            "category":"Personal",
            "subcategory":"Beauty Salon",
            "type":"Services"
        }
    ],
    "sg:phone":"+1 253 874 6314",
    "sg:postcode":"98023",
    "sg:province":"WA",
    "sg:tags":[
        "shop"
    ],
    "wof:name":"Dixie's Hair Design",
    "wof:placetype":"venue"
},
  "geometry": {"coordinates":[-122.40176700000001,47.316659],"type":"Point"}
}