{
  "type": "Feature",
  "properties": {
    "addr:full":"9590 Radcliff Ave NE Bremerton WA 98311",
    "addr:housenumber":"9590",
    "addr:postcode":"98311",
    "addr:street":"Radcliff Ave Ne",
    "iso:country":"US",
    "sg:address":"9590 Radcliff Ave NE",
    "sg:city":"Bremerton",
    "sg:phone":"+1 360 692 6549",
    "sg:postcode":"98311",
    "sg:province":"WA",
    "sg:website":"http://www.peninsulabible.org",
    "wof:name":"Peninsula Bible Fellowship",
    "wof:placetype":"venue"
},
  "geometry": {"coordinates":[-122.639551,47.650403],"type":"Point"}
}