{
  "type": "Feature",
  "properties": {
    "addr:full":"3400 180th Pl SW Lynnwood WA 98037",
    "addr:housenumber":"3400",
    "addr:postcode":"98037",
    "addr:street":"180Th Pl Sw",
    "iso:country":"US",
    "sg:address":"3400 180th Pl SW",
    "sg:city":"Lynnwood",
    "sg:classifiers":[
        {
            "category":"Insurance",
            "subcategory":"Insurance Agent",
            "type":"Services"
        }
    ],
    "sg:phone":"+1 425 771 4435",
    "sg:postcode":"98037",
    "sg:province":"WA",
    "wof:name":"Insurance Processing Svc",
    "wof:placetype":"venue"
},
  "geometry": {"coordinates":[-122.279967,47.835],"type":"Point"}
}