{
  "type": "Feature",
  "properties": {
    "addr:full":"4551 W Gibson Dahl Rd Deer Park WA 99006",
    "addr:housenumber":"4551",
    "addr:postcode":"99006",
    "addr:street":"W Gibson Dahl Rd",
    "iso:country":"US",
    "sg:address":"4551 W Gibson Dahl Rd",
    "sg:city":"Deer Park",
    "sg:phone":"+1 509 276 6820",
    "sg:postcode":"99006",
    "sg:province":"WA",
    "sg:tags":[
        "farm",
        "field",
        "grain",
        "cash",
        "crop"
    ],
    "wof:name":"Tom Taylor",
    "wof:placetype":"venue"
},
  "geometry": {"coordinates":[-117.48431100000001,47.960208],"type":"Point"}
}