{
  "type": "Feature",
  "properties": {
    "addr:full":"225 108th Ave NE Bellevue WA 98004",
    "addr:housenumber":"225",
    "addr:postcode":"98004",
    "addr:street":"108Th Ave Ne",
    "iso:country":"US",
    "sg:address":"225 108th Ave NE",
    "sg:city":"Bellevue",
    "sg:classifiers":[
        {
            "category":"Professional",
            "subcategory":"Management & Consulting",
            "type":"Services"
        }
    ],
    "sg:phone":"+1 425 638 4800",
    "sg:postcode":"98004",
    "sg:province":"WA",
    "sg:tags":[
        "public",
        "relations"
    ],
    "wof:name":"Prcom",
    "wof:placetype":"venue"
},
  "geometry": {"coordinates":[-122.19629999999999,47.612312],"type":"Point"}
}