{
  "type": "Feature",
  "properties": {
    "addr:full":"74 Hurricane Vw Port Angeles WA 98362",
    "addr:housenumber":"74",
    "addr:postcode":"98362",
    "addr:street":"Hurricane Vw",
    "iso:country":"US",
    "sg:address":"74 Hurricane Vw",
    "sg:city":"Port Angeles",
    "sg:classifiers":[
        {
            "category":"Building & Trades",
            "subcategory":"Construction",
            "type":"Services"
        }
    ],
    "sg:phone":"+1 360 452 3155",
    "sg:postcode":"98362",
    "sg:province":"WA",
    "sg:tags":[
        "general",
        "contractor"
    ],
    "wof:name":"Can Do Constr & Home Mntnc",
    "wof:placetype":"venue"
},
  "geometry": {"coordinates":[-123.3156,48.063482],"type":"Point"}
}