{
  "type": "Feature",
  "properties": {
    "addr:full":"1040 Stevenson Ave Enumclaw WA 98022",
    "addr:housenumber":"1040",
    "addr:postcode":"98022",
    "addr:street":"Stevenson Ave",
    "iso:country":"US",
    "sg:address":"1040 Stevenson Ave",
    "sg:city":"Enumclaw",
    "sg:classifiers":[
        {
            "category":"Restaurant",
            "type":"Food & Drink"
        }
    ],
    "sg:menulink":"http://www.allmenus.com/wa/enumclaw-plateau/139104-quiznos-sub/menu/",
    "sg:phone":"+1 425 258 9496",
    "sg:postcode":"98022",
    "sg:province":"WA",
    "sg:tags":[
        "wrap",
        "american",
        "sandwich"
    ],
    "wof:name":"Quiznos Sub",
    "wof:placetype":"venue"
},
  "geometry": {"coordinates":[-121.989662,47.201432],"type":"Point"}
}