{
  "type": "Feature",
  "properties": {
    "addr:full":"1258 12th Ave Longview WA 98632",
    "addr:housenumber":"1258",
    "addr:postcode":"98632",
    "addr:street":"12Th Ave",
    "iso:country":"US",
    "sg:address":"1258 12th Ave",
    "sg:city":"Longview",
    "sg:phone":"+1 360 577 0530",
    "sg:postcode":"98632",
    "sg:province":"WA",
    "sg:tags":[
        "agricultural",
        "product"
    ],
    "wof:name":"Full Spectrum Agricultural",
    "wof:placetype":"venue"
},
  "geometry": {"coordinates":[-122.93333800000001,46.135817],"type":"Point"}
}