{
  "type": "Feature",
  "properties": {
    "addr:full":"4716 86th Ave NW Gig Harbor WA 98335",
    "addr:housenumber":"4716",
    "addr:postcode":"98335",
    "addr:street":"86Th Ave Nw",
    "iso:country":"US",
    "sg:address":"4716 86th Ave NW",
    "sg:city":"Gig Harbor",
    "sg:classifiers":[
        {
            "category":"Retail",
            "subcategory":"Photofinishing",
            "type":"Services"
        }
    ],
    "sg:phone":"+1 253 265 2526",
    "sg:postcode":"98335",
    "sg:province":"WA",
    "sg:tags":[
        "laboratory"
    ],
    "wof:name":"Barry Berenson Photo",
    "wof:placetype":"venue"
},
  "geometry": {"coordinates":[-122.653334,47.303469],"type":"Point"}
}