{
  "type": "Feature",
  "properties": {
    "addr:full":"900 Lenora St Ste 120 Seattle WA 98121",
    "addr:housenumber":"900",
    "addr:postcode":"98121",
    "addr:street":"Lenora St Ste 120",
    "iso:country":"US",
    "sg:address":"900 Lenora St Ste 120",
    "sg:city":"Seattle",
    "sg:classifiers":[
        {
            "category":"Bakery",
            "type":"Food & Drink"
        }
    ],
    "sg:phone":"+1 206 332 9663",
    "sg:postcode":"98121",
    "sg:province":"WA",
    "wof:name":"Scraps Dog Bakery",
    "wof:placetype":"venue"
},
  "geometry": {"coordinates":[-122.33702099999999,47.617149],"type":"Point"}
}