{
  "type": "Feature",
  "properties": {
    "addr:full":"113 W Main St Centralia WA 98531",
    "addr:housenumber":"113",
    "addr:postcode":"98531",
    "addr:street":"W Main St",
    "iso:country":"US",
    "sg:address":"113 W Main St",
    "sg:city":"Centralia",
    "sg:classifiers":[
        {
            "category":"Shopping",
            "subcategory":"Bicycles & Sporting Goods",
            "type":"Retail Goods"
        }
    ],
    "sg:phone":"+1 360 736 9994",
    "sg:postcode":"98531",
    "sg:province":"WA",
    "wof:name":"Willie's Sport Shop",
    "wof:placetype":"venue"
},
  "geometry": {"coordinates":[-122.955395,46.716521],"type":"Point"}
}