{
  "type": "Feature",
  "properties": {
    "addr:full":"304 N 6th St Cheney WA 99004",
    "addr:housenumber":"304",
    "addr:postcode":"99004",
    "addr:street":"N 6Th St",
    "iso:country":"US",
    "sg:address":"304 N 6th St",
    "sg:city":"Cheney",
    "sg:classifiers":[
        {
            "category":"Professional",
            "type":"Services"
        }
    ],
    "sg:phone":"+1 509 220 1111",
    "sg:postcode":"99004",
    "sg:province":"WA",
    "wof:name":"First Impressions",
    "wof:placetype":"venue"
},
  "geometry": {"coordinates":[-117.575407,47.496253],"type":"Point"}
}