{
  "type": "Feature",
  "properties": {
    "addr:full":"612 S Alaska St Seattle WA 98108",
    "addr:housenumber":"612",
    "addr:postcode":"98108",
    "addr:street":"S Alaska St",
    "iso:country":"US",
    "sg:address":"612 S Alaska St",
    "sg:city":"Seattle",
    "sg:classifiers":[
        {
            "category":"Food & Beverages",
            "subcategory":"Farmers Market",
            "type":"Retail Goods"
        },
        {
            "category":"Wholesale",
            "subcategory":"Fruits & Vegetables",
            "type":"Manufacturing & Wholesale Goods"
        }
    ],
    "sg:phone":"+1 206 624 9754",
    "sg:postcode":"98108",
    "sg:province":"WA",
    "sg:tags":[
        "veggie"
    ],
    "wof:name":"Franks Quality Produce",
    "wof:placetype":"venue"
},
  "geometry": {"coordinates":[-122.32643,47.561327],"type":"Point"}
}