{
  "type": "Feature",
  "properties": {
    "addr:full":"2727 Douglas St Longview WA 98632",
    "addr:housenumber":"2727",
    "addr:postcode":"98632",
    "addr:street":"Douglas St",
    "iso:country":"US",
    "sg:address":"2727 Douglas St",
    "sg:city":"Longview",
    "sg:classifiers":[
        {
            "category":"Autos & Motor Vehicles",
            "subcategory":"Automobile Sales",
            "type":"Retail Goods"
        }
    ],
    "sg:phone":"+1 360 423 1843",
    "sg:postcode":"98632",
    "sg:province":"WA",
    "wof:name":"Bowers Auto Sales",
    "wof:placetype":"venue"
},
  "geometry": {"coordinates":[-122.957131,46.132658],"type":"Point"}
}