{
  "type": "Feature",
  "properties": {
    "addr:full":"18816 NE 80th St Redmond WA 98052",
    "addr:housenumber":"18816",
    "addr:postcode":"98052",
    "addr:street":"Ne 80Th St",
    "iso:country":"US",
    "sg:address":"18816 NE 80th St",
    "sg:city":"Redmond",
    "sg:classifiers":[
        {
            "category":"Wholesale",
            "subcategory":"Construction Materials",
            "type":"Manufacturing & Wholesale Goods"
        }
    ],
    "sg:phone":"+1 425 868 7334",
    "sg:postcode":"98052",
    "sg:province":"WA",
    "sg:website":"www.cadman.com",
    "wof:name":"Cadman Inc",
    "wof:placetype":"venue"
},
  "geometry": {"coordinates":[-122.08441999999999,47.675492],"type":"Point"}
}