{
  "type": "Feature",
  "properties": {
    "addr:full":"5115 Perry Dr SE Auburn WA 98092",
    "addr:housenumber":"5115",
    "addr:postcode":"98092",
    "addr:street":"Perry Dr Se",
    "iso:country":"US",
    "sg:address":"5115 Perry Dr SE",
    "sg:city":"Auburn",
    "sg:classifiers":[
        {
            "category":"Professional",
            "subcategory":"Business Services",
            "type":"Services"
        }
    ],
    "sg:phone":"+1 253 735 5960",
    "sg:postcode":"98092",
    "sg:province":"WA",
    "wof:name":"Kareys Kreative Interior",
    "wof:placetype":"venue"
},
  "geometry": {"coordinates":[-122.21032099999999,47.262033],"type":"Point"}
}