{
  "type": "Feature",
  "properties": {
    "addr:full":"211 Pioneer Ave E Montesano WA 98563",
    "addr:housenumber":"211",
    "addr:postcode":"98563",
    "addr:street":"Pioneer Ave E Montesano",
    "iso:country":"US",
    "sg:address":"211 Pioneer Ave E",
    "sg:city":"Montesano",
    "sg:classifiers":[
        {
            "category":"Building & Trades",
            "subcategory":"Equipment Rental",
            "type":"Services"
        }
    ],
    "sg:phone":"+1 360 249 3420",
    "sg:postcode":"98563",
    "sg:province":"WA",
    "wof:name":"Party Pizzazz",
    "wof:placetype":"venue"
},
  "geometry": {"coordinates":[-123.599487,46.979431],"type":"Point"}
}