{
  "type": "Feature",
  "properties": {
    "addr:full":"316 SW 16th St Renton WA 98057",
    "addr:housenumber":"316",
    "addr:postcode":"98057",
    "addr:street":"Sw 16Th St",
    "iso:country":"US",
    "sg:address":"316 SW 16th St",
    "sg:city":"Renton",
    "sg:classifiers":[
        {
            "category":"Autos & Motor Vehicles",
            "subcategory":"Auto Supplies",
            "type":"Retail Goods"
        },
        {
            "category":"Retail",
            "subcategory":"Auto Repair",
            "type":"Services"
        }
    ],
    "sg:phone":"+1 425 228 0505",
    "sg:postcode":"98057",
    "sg:province":"WA",
    "sg:tags":[
        "recap",
        "retread",
        "tire"
    ],
    "wof:name":"Phelps Tire Company",
    "wof:placetype":"venue"
},
  "geometry": {"coordinates":[-122.221811,47.466105],"type":"Point"}
}