{
  "type": "Feature",
  "properties": {
    "iso:country":"US",
    "sg:address":"4202 SW Roxbury St",
    "sg:city":"Seattle",
    "sg:classifiers":[
        {
            "category":"Professional",
            "subcategory":"Computer Services",
            "type":"Services"
        }
    ],
    "sg:phone":"+1 206 932 6499",
    "sg:postcode":"98136",
    "sg:province":"WA",
    "sg:tags":[
        "related"
    ],
    "wof:name":"Levine Consulting",
    "wof:placetype":"venue"
},
  "geometry": {"coordinates":[-122.384978,47.517525],"type":"Point"}
}