{
  "type": "Feature",
  "properties": {
    "addr:full":"1520 Parker Way Ste B Mount Vernon WA 98273",
    "addr:housenumber":"1520",
    "addr:postcode":"98273",
    "addr:street":"Parker Way Ste B",
    "iso:country":"US",
    "sg:address":"1520 Parker Way Ste B",
    "sg:city":"Mount Vernon",
    "sg:classifiers":[
        {
            "category":"Health Services",
            "subcategory":"Doctor",
            "type":"Services"
        },
        {
            "category":"Health Services",
            "subcategory":"Clinic",
            "type":"Services"
        }
    ],
    "sg:phone":"+1 360 424 6240",
    "sg:postcode":"98273",
    "sg:province":"WA",
    "sg:tags":[
        "counseling",
        "mental"
    ],
    "wof:name":"Hofman Kees C PHD",
    "wof:placetype":"venue"
},
  "geometry": {"coordinates":[-122.32199900000001,48.434601],"type":"Point"}
}