{
  "type": "Feature",
  "properties": {
    "addr:full":"2077 Bellevue Sq Bellevue WA 98004",
    "addr:housenumber":"2077",
    "addr:postcode":"98004",
    "addr:street":"Bellevue Sq",
    "iso:country":"US",
    "sg:address":"2077 Bellevue Sq",
    "sg:city":"Bellevue",
    "sg:classifiers":[
        {
            "category":"Sports & Exercise",
            "subcategory":"Bicycle Rental",
            "type":"Entertainment"
        }
    ],
    "sg:phone":"+1 425 455 3484",
    "sg:postcode":"98004",
    "sg:province":"WA",
    "sg:tags":[
        "wear"
    ],
    "sg:website":"mariners.com",
    "wof:name":"Seattle Mariners Team Store",
    "wof:placetype":"venue"
},
  "geometry": {"coordinates":[-122.201668,47.629462],"type":"Point"}
}