{
  "type": "Feature",
  "properties": {
    "addr:full":"3029 E Boone Ave Spokane WA 99202",
    "addr:housenumber":"3029",
    "addr:postcode":"99202",
    "addr:street":"E Boone Ave",
    "iso:country":"US",
    "sg:address":"3029 E Boone Ave",
    "sg:city":"Spokane",
    "sg:classifiers":[
        {
            "category":"Professional",
            "subcategory":"Art Services",
            "type":"Services"
        }
    ],
    "sg:phone":"+1 509 315 8204",
    "sg:postcode":"99202",
    "sg:province":"WA",
    "sg:tags":[
        "designer",
        "display",
        "producer"
    ],
    "wof:name":"Designers Viewpoint",
    "wof:placetype":"venue"
},
  "geometry": {"coordinates":[-117.36631199999999,47.669189],"type":"Point"}
}