{
  "type": "Feature",
  "properties": {
    "addr:full":"505 Chelan Pl NE Renton WA 98059",
    "addr:housenumber":"505",
    "addr:postcode":"98059",
    "addr:street":"Chelan Pl Ne",
    "iso:country":"US",
    "sg:address":"505 Chelan Pl NE",
    "sg:city":"Renton",
    "sg:classifiers":[
        {
            "category":"Home & Garden",
            "subcategory":"Household Appliances",
            "type":"Retail Goods"
        }
    ],
    "sg:phone":"+1 425 226 7194",
    "sg:postcode":"98059",
    "sg:province":"WA",
    "wof:name":"GE Appliances Sales",
    "wof:placetype":"venue"
},
  "geometry": {"coordinates":[-122.157051,47.490661],"type":"Point"}
}