{
  "type": "Feature",
  "properties": {
    "addr:full":"6610 Fremont Ave N Seattle WA 98103",
    "addr:housenumber":"6610",
    "addr:postcode":"98103",
    "addr:street":"Fremont Ave N",
    "iso:country":"US",
    "sg:address":"6610 Fremont Ave N",
    "sg:city":"Seattle",
    "sg:classifiers":[
        {
            "category":"Professional",
            "subcategory":"Management & Consulting",
            "type":"Services"
        }
    ],
    "sg:phone":"+1 206 226 0888",
    "sg:postcode":"98103",
    "sg:province":"WA",
    "sg:tags":[
        "development",
        "leadership"
    ],
    "wof:name":"Teams & Leaders  Inc",
    "wof:placetype":"venue"
},
  "geometry": {"coordinates":[-122.349886,47.677705],"type":"Point"}
}