{
  "type": "Feature",
  "properties": {
    "addr:full":"18904 Hwy 99 Lynnwood WA 98036",
    "addr:housenumber":"18904",
    "addr:postcode":"98036",
    "addr:street":"Hwy 99",
    "iso:country":"US",
    "sg:address":"18904 Hwy 99",
    "sg:city":"Lynnwood",
    "sg:classifiers":[
        {
            "category":"Insurance",
            "subcategory":"Insurance Agent",
            "type":"Services"
        }
    ],
    "sg:phone":"+1 425 776 0133",
    "sg:postcode":"98036",
    "sg:province":"WA",
    "wof:name":"State Farm Insurance",
    "wof:placetype":"venue"
},
  "geometry": {"coordinates":[-122.30973899999999,47.827672],"type":"Point"}
}