{
  "type": "Feature",
  "properties": {
    "iso:country":"US",
    "sg:address":"143 Park Ln",
    "sg:city":"Kirkland",
    "sg:classifiers":[
        {
            "category":"Health Services",
            "subcategory":"Doctor",
            "type":"Services"
        }
    ],
    "sg:phone":"+1 425 820 9691",
    "sg:postcode":"98033",
    "sg:province":"WA",
    "sg:tags":[
        "medical"
    ],
    "wof:name":"Ray Donna Lynne LMP",
    "wof:placetype":"venue"
},
  "geometry": {"coordinates":[-122.205021,47.676248],"type":"Point"}
}