{
  "type": "Feature",
  "properties": {
    "addr:full":"27402 72nd Ave S Kent WA 98032",
    "addr:housenumber":"27402",
    "addr:postcode":"98032",
    "addr:street":"72Nd Ave S",
    "iso:country":"US",
    "sg:address":"27402 72nd Ave S",
    "sg:city":"Kent",
    "sg:classifiers":[
        {
            "category":"Manufacturing",
            "subcategory":"Metals",
            "type":"Manufacturing & Wholesale Goods"
        }
    ],
    "sg:phone":"+1 253 395 0795",
    "sg:postcode":"98032",
    "sg:province":"WA",
    "sg:tags":[
        "can",
        "mfg"
    ],
    "sg:website":"www.ball.com",
    "wof:name":"Ball Metal Beverage Cont Corp",
    "wof:placetype":"venue"
},
  "geometry": {"coordinates":[-122.24323800000001,47.354344],"type":"Point"}
}