{
  "type": "Feature",
  "properties": {
    "addr:full":"5170 N Wahluke Rd Mesa WA 99343",
    "addr:housenumber":"5170",
    "addr:postcode":"99343",
    "addr:street":"N Wahluke Rd",
    "iso:country":"US",
    "sg:address":"5170 N Wahluke Rd",
    "sg:city":"Mesa",
    "sg:classifiers":[
        {
            "category":"Farming",
            "subcategory":"Orchard",
            "type":"Manufacturing & Wholesale Goods"
        }
    ],
    "sg:phone":"+1 509 269 4786",
    "sg:postcode":"99343",
    "sg:province":"WA",
    "sg:tags":[
        "apple"
    ],
    "wof:name":"Rowley & Hawkins Fruit Farms",
    "wof:placetype":"venue"
},
  "geometry": {"coordinates":[-119.21866,46.628622],"type":"Point"}
}