{
  "type": "Feature",
  "properties": {
    "addr:full":"4628 Village Ct NE Seattle WA 98105",
    "addr:housenumber":"4628",
    "addr:postcode":"98105",
    "addr:street":"Village Ct Ne",
    "iso:country":"US",
    "sg:address":"4628 Village Ct NE",
    "sg:city":"Seattle",
    "sg:classifiers":[
        {
            "category":"Shopping",
            "subcategory":"Jewelry",
            "type":"Retail Goods"
        }
    ],
    "sg:phone":"+1 206 523 7545",
    "sg:postcode":"98105",
    "sg:province":"WA",
    "sg:website":"www.somethingsilver.com/",
    "wof:name":"Something Silver",
    "wof:placetype":"venue"
},
  "geometry": {"coordinates":[-122.299165,47.663276],"type":"Point"}
}