{
  "type": "Feature",
  "properties": {
    "addr:full":"925 Heather Cir Mount Vernon WA 98273",
    "addr:housenumber":"925",
    "addr:postcode":"98273",
    "addr:street":"Heather Cir",
    "iso:country":"US",
    "sg:address":"925 Heather Cir",
    "sg:city":"Mount Vernon",
    "sg:classifiers":[
        {
            "category":"Social Services",
            "subcategory":"Adult Care",
            "type":"Services"
        }
    ],
    "sg:phone":"+1 360 336 5863",
    "sg:postcode":"98273",
    "sg:province":"WA",
    "sg:tags":[
        "residential"
    ],
    "wof:name":"Heather Vlg Chrstn Rtrment Com",
    "wof:placetype":"venue"
},
  "geometry": {"coordinates":[-122.346102,48.408138],"type":"Point"}
}