{
  "type": "Feature",
  "properties": {
    "addr:full":"949 S Montesano St Westport WA 98595",
    "addr:housenumber":"949",
    "addr:postcode":"98595",
    "addr:street":"S Montesano St",
    "iso:country":"US",
    "sg:address":"949 S Montesano St",
    "sg:city":"Westport",
    "sg:classifiers":[
        {
            "category":"Travel",
            "subcategory":"Hotels & Motels",
            "type":"Entertainment"
        }
    ],
    "sg:phone":"+1 360 268 9149",
    "sg:postcode":"98595",
    "sg:province":"WA",
    "sg:tags":[
        "operation"
    ],
    "wof:name":"Surf Spray Motel & Rv Park",
    "wof:placetype":"venue"
},
  "geometry": {"coordinates":[-124.104195,46.878887],"type":"Point"}
}