{
  "type": "Feature",
  "properties": {
    "addr:full":"18050 32nd Ave S Seatac WA 98188",
    "addr:housenumber":"18050",
    "addr:postcode":"98188",
    "addr:street":"32Nd Ave S Seatac",
    "iso:country":"US",
    "sg:address":"18050 32nd Ave S",
    "sg:city":"Seatac",
    "sg:classifiers":[
        {
            "category":"Real Estate",
            "subcategory":"Developer",
            "type":"Services"
        },
        {
            "category":"Real Estate",
            "subcategory":"Real Estate Operator",
            "type":"Services"
        }
    ],
    "sg:phone":"+1 206 244 4755",
    "sg:postcode":"98188",
    "sg:province":"WA",
    "sg:tags":[
        "mobile",
        "home",
        "site"
    ],
    "wof:name":"Bow Lake Inc",
    "wof:placetype":"venue"
},
  "geometry": {"coordinates":[-122.291662,47.440973],"type":"Point"}
}