{
  "type": "Feature",
  "properties": {
    "addr:full":"1215 Bay St Port Orchard WA 98366",
    "addr:housenumber":"1215",
    "addr:postcode":"98366",
    "addr:street":"Bay St",
    "iso:country":"US",
    "sg:address":"1215 Bay St",
    "sg:city":"Port Orchard",
    "sg:classifiers":[
        {
            "category":"Retail",
            "subcategory":"Auto Rental",
            "type":"Services"
        }
    ],
    "sg:phone":"+1 360 876 3799",
    "sg:postcode":"98366",
    "sg:province":"WA",
    "sg:tags":[
        "passenger",
        "car"
    ],
    "wof:name":"Enterprise Rent-A-Car Company",
    "wof:placetype":"venue"
},
  "geometry": {"coordinates":[-122.62860000000001,47.542807],"type":"Point"}
}