{
  "type": "Feature",
  "properties": {
    "addr:full":"830 SE Sunnymead Way Pullman WA 99163",
    "addr:housenumber":"830",
    "addr:postcode":"99163",
    "addr:street":"Se Sunnymead Way",
    "iso:country":"US",
    "sg:address":"830 SE Sunnymead Way",
    "sg:city":"Pullman",
    "sg:phone":"+1 509 334 6376",
    "sg:postcode":"99163",
    "sg:province":"WA",
    "sg:tags":[
        "farm",
        "grain",
        "wheat",
        "cash"
    ],
    "wof:name":"Knapp Farm",
    "wof:placetype":"venue"
},
  "geometry": {"coordinates":[-117.17008800000001,46.721987],"type":"Point"}
}