{
  "type": "Feature",
  "properties": {
    "addr:full":"1970 Kok Rd Lynden WA 98264",
    "addr:housenumber":"1970",
    "addr:postcode":"98264",
    "addr:street":"Kok Rd",
    "iso:country":"US",
    "sg:address":"1970 Kok Rd",
    "sg:city":"Lynden",
    "sg:classifiers":[
        {
            "category":"Autos & Motor Vehicles",
            "subcategory":"Auto Supplies",
            "type":"Retail Goods"
        },
        {
            "category":"Wholesale",
            "subcategory":"Electrical",
            "type":"Manufacturing & Wholesale Goods"
        }
    ],
    "sg:phone":"+1 360 318 8224",
    "sg:postcode":"98264",
    "sg:province":"WA",
    "sg:tags":[
        "battery",
        "automobile",
        "part",
        "accessory"
    ],
    "sg:website":"http://www.oreillyautoparts.com",
    "wof:name":"O'Reilly Auto Parts",
    "wof:placetype":"venue"
},
  "geometry": {"coordinates":[-122.48403399999999,48.935192],"type":"Point"}
}