{
  "type": "Feature",
  "properties": {
    "addr:full":"14211 W Lake Kathleen Dr SE Renton WA 98059",
    "addr:housenumber":"14211",
    "addr:postcode":"98059",
    "addr:street":"W Lake Kathleen Dr Se",
    "iso:country":"US",
    "sg:address":"14211 W Lake Kathleen Dr SE",
    "sg:city":"Renton",
    "sg:classifiers":[
        {
            "category":"Building & Trades",
            "subcategory":"Construction",
            "type":"Services"
        }
    ],
    "sg:phone":"+1 425 277 3292",
    "sg:postcode":"98059",
    "sg:province":"WA",
    "sg:tags":[
        "contractor"
    ],
    "wof:name":"Ralston Homes",
    "wof:placetype":"venue"
},
  "geometry": {"coordinates":[-122.09107,47.47575],"type":"Point"}
}