{
  "type": "Feature",
  "properties": {
    "addr:full":"12221 120th Ave NE Kirkland WA 98034",
    "addr:housenumber":"12221",
    "addr:postcode":"98034",
    "addr:street":"120Th Ave Ne",
    "iso:country":"US",
    "sg:address":"12221 120th Ave NE",
    "sg:city":"Kirkland",
    "sg:classifiers":[
        {
            "category":"Shopping",
            "subcategory":"Jewelry",
            "type":"Retail Goods"
        }
    ],
    "sg:phone":"+1 425 820 5048",
    "sg:postcode":"98034",
    "sg:province":"WA",
    "wof:name":"Le Goldsmith Service",
    "wof:placetype":"venue"
},
  "geometry": {"coordinates":[-122.184819,47.709734],"type":"Point"}
}