{
  "type": "Feature",
  "properties": {
    "addr:full":"1750 Smith Island Ln Oak Harbor WA 98277",
    "addr:housenumber":"1750",
    "addr:postcode":"98277",
    "addr:street":"Smith Island Ln",
    "iso:country":"US",
    "sg:address":"1750 Smith Island Ln",
    "sg:city":"Oak Harbor",
    "sg:classifiers":[
        {
            "category":"Retail",
            "subcategory":"Animal Services",
            "type":"Services"
        }
    ],
    "sg:phone":"+1 360 675 4308",
    "sg:postcode":"98277",
    "sg:province":"WA",
    "wof:name":"Di-TI Dals",
    "wof:placetype":"venue"
},
  "geometry": {"coordinates":[-122.710964,48.305182],"type":"Point"}
}