{
  "type": "Feature",
  "properties": {
    "addr:full":"17715 S Spada Rd Snohomish WA 98290",
    "addr:housenumber":"17715",
    "addr:postcode":"98290",
    "addr:street":"S Spada Rd",
    "iso:country":"US",
    "sg:address":"17715 S Spada Rd",
    "sg:city":"Snohomish",
    "sg:classifiers":[
        {
            "category":"Building & Trades",
            "subcategory":"Construction",
            "type":"Services"
        }
    ],
    "sg:phone":"+1 360 568 4149",
    "sg:postcode":"98290",
    "sg:province":"WA",
    "sg:tags":[
        "excavation",
        "contractor"
    ],
    "wof:name":"Davison Timber Cutting",
    "wof:placetype":"venue"
},
  "geometry": {"coordinates":[-121.994613,47.91353],"type":"Point"}
}