{
  "type": "Feature",
  "properties": {
    "iso:country":"US",
    "sg:address":"8655 154th Ave NE",
    "sg:city":"Redmond",
    "sg:classifiers":[
        {
            "category":"Professional",
            "type":"Services"
        }
    ],
    "sg:phone":"+1 425 882 7800",
    "sg:postcode":"98052",
    "sg:province":"WA",
    "wof:name":"Projectworks",
    "wof:placetype":"venue"
},
  "geometry": {"coordinates":[-122.13475,47.679718],"type":"Point"}
}