{
  "type": "Feature",
  "properties": {
    "addr:full":"8407 Carl Rd Everson WA 98247",
    "addr:housenumber":"8407",
    "addr:postcode":"98247",
    "addr:street":"Carl Rd",
    "iso:country":"US",
    "sg:address":"8407 Carl Rd",
    "sg:city":"Everson",
    "sg:classifiers":[
        {
            "category":"Professional",
            "subcategory":"Art Services",
            "type":"Services"
        }
    ],
    "sg:phone":"+1 360 966 2936",
    "sg:postcode":"98247",
    "sg:province":"WA",
    "sg:tags":[
        "photography",
        "commercial"
    ],
    "wof:name":"Picture Perfect Productions",
    "wof:placetype":"venue"
},
  "geometry": {"coordinates":[-122.271038,48.945038],"type":"Point"}
}