{
  "type": "Feature",
  "properties": {
    "addr:full":"1508 S 1st St Yakima WA 98901",
    "addr:housenumber":"1508",
    "addr:postcode":"98901",
    "addr:street":"S 1St St",
    "iso:country":"US",
    "sg:address":"1508 S 1st St",
    "sg:city":"Yakima",
    "sg:classifiers":[
        {
            "category":"Building & Trades",
            "subcategory":"Equipment Rental",
            "type":"Services"
        }
    ],
    "sg:phone":"+1 509 575 6432",
    "sg:postcode":"98901",
    "sg:province":"WA",
    "sg:tags":[
        "yard"
    ],
    "wof:name":"E Z Rent All",
    "wof:placetype":"venue"
},
  "geometry": {"coordinates":[-120.496354,46.584875],"type":"Point"}
}