{
  "type": "Feature",
  "properties": {
    "addr:full":"2900 NE Blakeley St Seattle WA 98105",
    "addr:housenumber":"2900",
    "addr:postcode":"98105",
    "addr:street":"Ne Blakeley St",
    "iso:country":"US",
    "sg:address":"2900 NE Blakeley St",
    "sg:city":"Seattle",
    "sg:classifiers":[
        {
            "category":"Education",
            "subcategory":"Vocational School",
            "type":"Public Place"
        }
    ],
    "sg:phone":"+1 206 528 8192",
    "sg:postcode":"98105",
    "sg:province":"WA",
    "sg:tags":[
        "cooking"
    ],
    "sg:website":"www.cooksworld.net",
    "wof:name":"Cook's World",
    "wof:placetype":"venue"
},
  "geometry": {"coordinates":[-122.296997,47.665901],"type":"Point"}
}