{
  "type": "Feature",
  "properties": {
    "addr:full":"1818 41st St Anacortes WA 98221",
    "addr:housenumber":"1818",
    "addr:postcode":"98221",
    "addr:street":"41St St",
    "iso:country":"US",
    "sg:address":"1818 41st St",
    "sg:city":"Anacortes",
    "sg:classifiers":[
        {
            "category":"Social Services",
            "subcategory":"Adult Care",
            "type":"Services"
        }
    ],
    "sg:phone":"+1 360 293 6183",
    "sg:postcode":"98221",
    "sg:province":"WA",
    "sg:tags":[
        "slitting",
        "cutting"
    ],
    "wof:name":"Anacortes Metalworks",
    "wof:placetype":"venue"
},
  "geometry": {"coordinates":[-122.626476,48.487985],"type":"Point"}
}