{
  "type": "Feature",
  "properties": {
    "addr:full":"22303 Marine View Dr S Des Moines WA 98198",
    "addr:housenumber":"22303",
    "addr:postcode":"98198",
    "addr:street":"Marine View Dr S",
    "iso:country":"US",
    "sg:address":"22303 Marine View Dr S",
    "sg:city":"Des Moines",
    "sg:classifiers":[
        {
            "category":"Retail",
            "subcategory":"Repair Shop",
            "type":"Services"
        }
    ],
    "sg:phone":"+1 206 824 7617",
    "sg:postcode":"98198",
    "sg:province":"WA",
    "sg:tags":[
        "engine",
        "outboard",
        "marine",
        "motor"
    ],
    "wof:name":"Force Marine Engine Service",
    "wof:placetype":"venue"
},
  "geometry": {"coordinates":[-122.324563,47.400481],"type":"Point"}
}