{
  "type": "Feature",
  "properties": {
    "addr:full":"5807 Titleist Ln SE Olympia WA 98513",
    "addr:housenumber":"5807",
    "addr:postcode":"98513",
    "addr:street":"Titleist Ln Se",
    "iso:country":"US",
    "sg:address":"5807 Titleist Ln SE",
    "sg:city":"Olympia",
    "sg:classifiers":[
        {
            "category":"Education",
            "subcategory":"Special Training",
            "type":"Public Place"
        }
    ],
    "sg:phone":"+1 360 456 3874",
    "sg:postcode":"98513",
    "sg:province":"WA",
    "wof:name":"Professional Educational Svcs",
    "wof:placetype":"venue"
},
  "geometry": {"coordinates":[-122.80821899999999,46.995003],"type":"Point"}
}