{
  "type": "Feature",
  "properties": {
    "addr:full":"424 89th Ave SW Olympia WA 98512",
    "addr:housenumber":"424",
    "addr:postcode":"98512",
    "addr:street":"89Th Ave Sw",
    "iso:country":"US",
    "sg:address":"424 89th Ave SW",
    "sg:city":"Olympia",
    "sg:classifiers":[
        {
            "category":"Building & Trades",
            "subcategory":"Construction",
            "type":"Services"
        }
    ],
    "sg:phone":"+1 360 754 3704",
    "sg:postcode":"98512",
    "sg:province":"WA",
    "sg:tags":[
        "system",
        "contractor",
        "air conditioning"
    ],
    "wof:name":"Soltman",
    "wof:placetype":"venue"
},
  "geometry": {"coordinates":[-122.911191,46.958835],"type":"Point"}
}