{
  "type": "Feature",
  "properties": {
    "addr:full":"5944 Capitol Forest Dr SW Olympia WA 98512",
    "addr:housenumber":"5944",
    "addr:postcode":"98512",
    "addr:street":"Capitol Forest Dr Sw",
    "iso:country":"US",
    "sg:address":"5944 Capitol Forest Dr SW",
    "sg:city":"Olympia",
    "sg:classifiers":[
        {
            "category":"Professional",
            "subcategory":"Computer Services",
            "type":"Services"
        }
    ],
    "sg:phone":"+1 360 956 1992",
    "sg:postcode":"98512",
    "sg:province":"WA",
    "sg:tags":[
        "related"
    ],
    "wof:name":"Bayside Options & Techniq",
    "wof:placetype":"venue"
},
  "geometry": {"coordinates":[-123.002251,46.995914],"type":"Point"}
}