{
  "type": "Feature",
  "properties": {
    "addr:full":"445 Christensen Rd Othello WA 99344",
    "addr:housenumber":"445",
    "addr:postcode":"99344",
    "addr:street":"Christensen Rd",
    "iso:country":"US",
    "sg:address":"445 Christensen Rd",
    "sg:city":"Othello",
    "sg:classifiers":[
        {
            "category":"Building & Trades",
            "subcategory":"Construction",
            "type":"Services"
        }
    ],
    "sg:phone":"+1 509 346 2791",
    "sg:postcode":"99344",
    "sg:province":"WA",
    "sg:tags":[
        "handyman"
    ],
    "wof:name":"Mendoza Auto Repair",
    "wof:placetype":"venue"
},
  "geometry": {"coordinates":[-119.486008,46.917081],"type":"Point"}
}