{
  "type": "Feature",
  "properties": {
    "addr:full":"1808 140th Ave SE Bellevue WA 98005",
    "addr:housenumber":"1808",
    "addr:postcode":"98005",
    "addr:street":"140Th Ave Se",
    "iso:country":"US",
    "sg:address":"1808 140th Ave SE",
    "sg:city":"Bellevue",
    "sg:classifiers":[
        {
            "category":"Manufacturing",
            "subcategory":"Printing",
            "type":"Manufacturing & Wholesale Goods"
        }
    ],
    "sg:phone":"+1 425 378 8065",
    "sg:postcode":"98005",
    "sg:province":"WA",
    "sg:tags":[
        "commercial"
    ],
    "wof:name":"AGA Sports",
    "wof:placetype":"venue"
},
  "geometry": {"coordinates":[-122.153373,47.592666],"type":"Point"}
}