{
  "type": "Feature",
  "properties": {
    "iso:country":"US",
    "sg:address":"1120 Connors Rd",
    "sg:city":"Snohomish",
    "sg:classifiers":[
        {
            "category":"Freight",
            "type":"Transportation"
        }
    ],
    "sg:phone":"+1 425 280 5675",
    "sg:postcode":"98290",
    "sg:province":"WA",
    "wof:name":"Dragon K Stables",
    "wof:placetype":"venue"
},
  "geometry": {"coordinates":[-121.98846399999999,47.985518],"type":"Point"}
}