{
  "type": "Feature",
  "properties": {
    "addr:full":"14563 Dogwood Ln Mount Vernon WA 98273",
    "addr:housenumber":"14563",
    "addr:postcode":"98273",
    "addr:street":"Dogwood Ln",
    "iso:country":"US",
    "sg:address":"14563 Dogwood Ln",
    "sg:city":"Mount Vernon",
    "sg:classifiers":[
        {
            "category":"Farming",
            "subcategory":"Fish & Marine Products",
            "type":"Manufacturing & Wholesale Goods"
        }
    ],
    "sg:phone":"+1 360 424 6238",
    "sg:postcode":"98273",
    "sg:province":"WA",
    "sg:tags":[
        "fishing"
    ],
    "wof:name":"Blackwater Inc",
    "wof:placetype":"venue"
},
  "geometry": {"coordinates":[-122.385533,48.434077],"type":"Point"}
}