{
  "type": "Feature",
  "properties": {
    "addr:full":"2927 95th Dr SE Everett WA 98205",
    "addr:housenumber":"2927",
    "addr:postcode":"98205",
    "addr:street":"95Th Dr Se",
    "iso:country":"US",
    "sg:address":"2927 95th Dr SE",
    "sg:city":"Everett",
    "sg:classifiers":[
        {
            "category":"Professional",
            "subcategory":"Business Services",
            "type":"Services"
        }
    ],
    "sg:phone":"+1 425 334 9472",
    "sg:postcode":"98205",
    "sg:province":"WA",
    "wof:name":"Alan Carey Construction",
    "wof:placetype":"venue"
},
  "geometry": {"coordinates":[-122.103278,47.969441],"type":"Point"}
}