{
  "type": "Feature",
  "properties": {
    "addr:full":"1307 College St SE Lacey WA 98503",
    "addr:housenumber":"1307",
    "addr:postcode":"98503",
    "addr:street":"College St Se",
    "iso:country":"US",
    "sg:address":"1307 College St SE",
    "sg:city":"Lacey",
    "sg:classifiers":[
        {
            "category":"Social Services",
            "type":"Services"
        }
    ],
    "sg:phone":"+1 360 459 0384",
    "sg:postcode":"98503",
    "sg:province":"WA",
    "sg:tags":[
        "counselor",
        "marriage",
        "family"
    ],
    "wof:name":"Pacific Counseling & Life Ctr",
    "wof:placetype":"venue"
},
  "geometry": {"coordinates":[-122.823341,47.035097],"type":"Point"}
}