{
  "type": "Feature",
  "properties": {
    "addr:full":"11110 22nd St SE Everett WA 98205",
    "addr:housenumber":"11110",
    "addr:postcode":"98205",
    "addr:street":"22Nd St Se",
    "iso:country":"US",
    "sg:address":"11110 22nd St SE",
    "sg:city":"Everett",
    "sg:classifiers":[
        {
            "category":"Building & Trades",
            "subcategory":"Electrical",
            "type":"Services"
        }
    ],
    "sg:phone":"+1 425 334 9792",
    "sg:postcode":"98205",
    "sg:province":"WA",
    "sg:tags":[
        "electrical",
        "contractor"
    ],
    "wof:name":"Hansen Electric",
    "wof:placetype":"venue"
},
  "geometry": {"coordinates":[-122.081796,47.975976],"type":"Point"}
}