{
  "type": "Feature",
  "properties": {
    "addr:full":"312 E 1st St Sprague WA 99032",
    "addr:housenumber":"312",
    "addr:postcode":"99032",
    "addr:street":"E 1St St",
    "iso:country":"US",
    "sg:address":"312 E 1st St",
    "sg:city":"Sprague",
    "sg:classifiers":[
        {
            "category":"Travel",
            "subcategory":"Hotels & Motels",
            "type":"Entertainment"
        }
    ],
    "sg:phone":"+1 509 257 2583",
    "sg:postcode":"99032",
    "sg:province":"WA",
    "wof:name":"Foxs Services",
    "wof:placetype":"venue"
},
  "geometry": {"coordinates":[-117.978444,47.30003],"type":"Point"}
}