{
  "type": "Feature",
  "properties": {
    "addr:full":"601 S King St Seattle WA 98104",
    "addr:housenumber":"601",
    "addr:postcode":"98104",
    "addr:street":"S King St",
    "iso:country":"US",
    "sg:address":"601 S King St",
    "sg:city":"Seattle",
    "sg:classifiers":[
        {
            "category":"Bars & Pubs",
            "subcategory":"Lounge",
            "type":"Food & Drink"
        }
    ],
    "sg:phone":"+1 206 264 1779",
    "sg:postcode":"98104",
    "sg:province":"WA",
    "sg:tags":[
        "karaoke"
    ],
    "wof:name":"Venus Karaoke",
    "wof:placetype":"venue"
},
  "geometry": {"coordinates":[-122.325996,47.598301],"type":"Point"}
}