{
  "type": "Feature",
  "properties": {
    "addr:full":"21511 E State Rte 3 Belfair WA 98528",
    "addr:housenumber":"21511",
    "addr:postcode":"98528",
    "addr:street":"E State Rte 3",
    "iso:country":"US",
    "sg:address":"21511 E State Rte 3",
    "sg:city":"Belfair",
    "sg:classifiers":[
        {
            "category":"Organizations",
            "subcategory":"Membership Organization",
            "type":"Services"
        }
    ],
    "sg:phone":"+1 360 275 8021",
    "sg:postcode":"98528",
    "sg:province":"WA",
    "wof:name":"Celebrate Life Pregnancy Crss",
    "wof:placetype":"venue"
},
  "geometry": {"coordinates":[-122.84729299999999,47.422031],"type":"Point"}
}