{
  "type": "Feature",
  "properties": {
    "addr:full":"1118 2nd St Wenatchee WA 98801",
    "addr:housenumber":"1118",
    "addr:postcode":"98801",
    "addr:street":"2Nd St",
    "iso:country":"US",
    "sg:address":"1118 2nd St",
    "sg:city":"Wenatchee",
    "sg:classifiers":[
        {
            "category":"Building & Trades",
            "subcategory":"Plumbing",
            "type":"Services"
        }
    ],
    "sg:phone":"+1 509 663 3602",
    "sg:postcode":"98801",
    "sg:province":"WA",
    "sg:tags":[
        "contractor",
        "mechanical"
    ],
    "wof:name":"Bruggman Mechanical Inc",
    "wof:placetype":"venue"
},
  "geometry": {"coordinates":[-120.329179,47.426878],"type":"Point"}
}