{
  "type": "Feature",
  "properties": {
    "addr:full":"1627 W Broadway Ave Moses Lake WA 98837",
    "addr:housenumber":"1627",
    "addr:postcode":"98837",
    "addr:street":"W Broadway Ave",
    "iso:country":"US",
    "sg:address":"1627 W Broadway Ave",
    "sg:city":"Moses Lake",
    "sg:classifiers":[
        {
            "category":"Professional",
            "type":"Services"
        }
    ],
    "sg:phone":"+1 509 765 2505",
    "sg:postcode":"98837",
    "sg:province":"WA",
    "sg:website":"www.golinex.com",
    "wof:name":"Line-X Of Moses Lake",
    "wof:placetype":"venue"
},
  "geometry": {"coordinates":[-119.296511,47.115711],"type":"Point"}
}