{
  "type": "Feature",
  "properties": {
    "addr:full":"11 NE Main St Wilbur WA 99185",
    "addr:housenumber":"11",
    "addr:postcode":"99185",
    "addr:street":"Ne Main St",
    "iso:country":"US",
    "sg:address":"11 NE Main St",
    "sg:city":"Wilbur",
    "sg:classifiers":[
        {
            "category":"Home & Garden",
            "subcategory":"Household Appliances",
            "type":"Retail Goods"
        },
        {
            "category":"Home & Garden",
            "subcategory":"Furniture",
            "type":"Retail Goods"
        }
    ],
    "sg:phone":"+1 509 647 2341",
    "sg:postcode":"99185",
    "sg:province":"WA",
    "sg:tags":[
        "major",
        "store",
        "appliances-small"
    ],
    "wof:name":"Warrington's Home Furnishings",
    "wof:placetype":"venue"
},
  "geometry": {"coordinates":[-118.704607,47.758412],"type":"Point"}
}