{
  "type": "Feature",
  "properties": {
    "addr:full":"25802 Pacific Hwy S Kent WA 98032",
    "addr:housenumber":"25802",
    "addr:postcode":"98032",
    "addr:street":"Pacific Hwy S",
    "iso:country":"US",
    "sg:address":"25802 Pacific Hwy S",
    "sg:city":"Kent",
    "sg:classifiers":[
        {
            "category":"Autos & Motor Vehicles",
            "subcategory":"Boat Sales",
            "type":"Retail Goods"
        },
        {
            "category":"Manufacturing",
            "subcategory":"Watercraft",
            "type":"Manufacturing & Wholesale Goods"
        }
    ],
    "sg:phone":"+1 253 839 5213",
    "sg:postcode":"98032",
    "sg:province":"WA",
    "sg:tags":[
        "distributor",
        "builder",
        "manufacturer"
    ],
    "wof:name":"Fluid Motion",
    "wof:placetype":"venue"
},
  "geometry": {"coordinates":[-122.303004,47.370163],"type":"Point"}
}