{
  "type": "Feature",
  "properties": {
    "addr:full":"924 S 16th Ave Yakima WA 98902",
    "addr:housenumber":"924",
    "addr:postcode":"98902",
    "addr:street":"S 16Th Ave",
    "iso:country":"US",
    "sg:address":"924 S 16th Ave",
    "sg:city":"Yakima",
    "sg:classifiers":[
        {
            "category":"Organizations",
            "subcategory":"Membership Organization",
            "type":"Services"
        }
    ],
    "sg:phone":"+1 509 248 7814",
    "sg:postcode":"98902",
    "sg:province":"WA",
    "wof:name":"National Chrysanthemum Society",
    "wof:placetype":"venue"
},
  "geometry": {"coordinates":[-120.530418,46.588128],"type":"Point"}
}