{
  "type": "Feature",
  "properties": {
    "addr:full":"4514 SW Trenton Street Seattle WA 98136",
    "addr:housenumber":"4514",
    "addr:postcode":"98136",
    "addr:street":"Sw Trenton Street",
    "iso:country":"US",
    "sg:address":"4514 SW Trenton Street",
    "sg:city":"Seattle",
    "sg:classifiers":[
        {
            "category":"Shopping",
            "subcategory":"Bicycles & Sporting Goods",
            "type":"Retail Goods"
        }
    ],
    "sg:phone":"+1 206 933 8987",
    "sg:postcode":"98136",
    "sg:province":"WA",
    "wof:name":"All Sports Cages and Netting",
    "wof:placetype":"venue"
},
  "geometry": {"coordinates":[-122.39140399999999,47.52496],"type":"Point"}
}