{
  "type": "Feature",
  "properties": {
    "iso:country":"US",
    "sg:address":"9700 Ravenna Ave NE",
    "sg:city":"Seattle",
    "sg:classifiers":[
        {
            "category":"Shopping",
            "subcategory":"Computers & Home Electronics",
            "type":"Retail Goods"
        }
    ],
    "sg:phone":"+1 206 933 0444",
    "sg:postcode":"98115",
    "sg:province":"WA",
    "sg:tags":[
        "software"
    ],
    "sg:website":"www.databasetech.com",
    "wof:name":"Database Solutions",
    "wof:placetype":"venue"
},
  "geometry": {"coordinates":[-122.30132,47.700255],"type":"Point"}
}