{
  "type": "Feature",
  "properties": {
    "addr:full":"31623 3rd Pl SW Federal Way WA 98023",
    "addr:housenumber":"31623",
    "addr:postcode":"98023",
    "addr:street":"3Rd Pl Sw Federal Way",
    "iso:country":"US",
    "sg:address":"31623 3rd Pl SW",
    "sg:city":"Federal Way",
    "sg:classifiers":[
        {
            "category":"Professional",
            "type":"Services"
        }
    ],
    "sg:phone":"+1 253 468 5992",
    "sg:postcode":"98023",
    "sg:province":"WA",
    "wof:name":"Welcome To My World",
    "wof:placetype":"venue"
},
  "geometry": {"coordinates":[-122.33852,47.317949],"type":"Point"}
}