{
  "type": "Feature",
  "properties": {
    "addr:full":"512 NE High St Goldendale WA 98620",
    "addr:housenumber":"512",
    "addr:postcode":"98620",
    "addr:street":"Ne High St",
    "iso:country":"US",
    "sg:address":"512 NE High St",
    "sg:city":"Goldendale",
    "sg:classifiers":[
        {
            "category":"Freight",
            "type":"Transportation"
        }
    ],
    "sg:phone":"+1 509 773 4788",
    "sg:postcode":"98620",
    "sg:province":"WA",
    "sg:tags":[
        "operator",
        "trucking"
    ],
    "wof:name":"Einar H Zetter",
    "wof:placetype":"venue"
},
  "geometry": {"coordinates":[-120.813748,45.828049],"type":"Point"}
}