{
  "type": "Feature",
  "properties": {
    "addr:full":"100 Brumfield Ave Montesano WA 98563",
    "addr:housenumber":"100",
    "addr:postcode":"98563",
    "addr:street":"Brumfield Ave Montesano",
    "iso:country":"US",
    "sg:address":"100 Brumfield Ave",
    "sg:city":"Montesano",
    "sg:classifiers":[
        {
            "category":"Insurance",
            "subcategory":"Hazard Insurance",
            "type":"Services"
        },
        {
            "category":"Insurance",
            "subcategory":"Insurance Agent",
            "type":"Services"
        },
        {
            "category":"Retail",
            "subcategory":"Repair Shop",
            "type":"Services"
        },
        {
            "category":"Professional",
            "subcategory":"Detective & Security Services",
            "type":"Services"
        }
    ],
    "sg:phone":"+1 360 249 2526",
    "sg:postcode":"98563",
    "sg:province":"WA",
    "sg:tags":[
        "business",
        "tracing",
        "commercial",
        "surety",
        "skip",
        "fidelity",
        "bail",
        "bond"
    ],
    "wof:name":"Northwest Surety",
    "wof:placetype":"venue"
},
  "geometry": {"coordinates":[-123.60086800000001,46.976891],"type":"Point"}
}