{
  "type": "Feature",
  "properties": {
    "addr:full":"1881 Wynooche Valley Rd Montesano WA 98563",
    "addr:housenumber":"1881",
    "addr:postcode":"98563",
    "addr:street":"Wynooche Valley Rd",
    "iso:country":"US",
    "sg:address":"1881 Wynooche Valley Rd",
    "sg:city":"Montesano",
    "sg:classifiers":[
        {
            "category":"Manufacturing",
            "subcategory":"Rubber & Plastics",
            "type":"Manufacturing & Wholesale Goods"
        }
    ],
    "sg:phone":"+1 360 249 3126",
    "sg:postcode":"98563",
    "sg:province":"WA",
    "sg:tags":[
        "product",
        "mfg"
    ],
    "wof:name":"Mickey Tozier",
    "wof:placetype":"venue"
},
  "geometry": {"coordinates":[-123.659993,47.111225],"type":"Point"}
}