{
  "type": "Feature",
  "properties": {
    "addr:full":"123 E Cota St Shelton WA 98584",
    "addr:housenumber":"123",
    "addr:postcode":"98584",
    "addr:street":"E Cota St",
    "iso:country":"US",
    "sg:address":"123 E Cota St",
    "sg:city":"Shelton",
    "sg:classifiers":[
        {
            "category":"Food & Beverages",
            "subcategory":"Liquor & Beverages",
            "type":"Retail Goods"
        }
    ],
    "sg:phone":"+1 360 427 2168",
    "sg:postcode":"98584",
    "sg:province":"WA",
    "sg:tags":[
        "alcoholic"
    ],
    "wof:name":"Washington State Liquor Store",
    "wof:placetype":"venue"
},
  "geometry": {"coordinates":[-123.100009,47.211939],"type":"Point"}
}