{
  "type": "Feature",
  "properties": {
    "addr:full":"11309 E Empire Ave Spokane WA 99206",
    "addr:housenumber":"11309",
    "addr:postcode":"99206",
    "addr:street":"E Empire Ave",
    "iso:country":"US",
    "sg:address":"11309 E Empire Ave",
    "sg:city":"Spokane",
    "sg:classifiers":[
        {
            "category":"Professional",
            "subcategory":"Management & Consulting",
            "type":"Services"
        }
    ],
    "sg:phone":"+1 509 927 8724",
    "sg:postcode":"99206",
    "sg:province":"WA",
    "sg:tags":[
        "retail",
        "direct",
        "sales"
    ],
    "wof:name":"Partylite Consultant",
    "wof:placetype":"venue"
},
  "geometry": {"coordinates":[-117.25591799999999,47.688374],"type":"Point"}
}