{
  "type": "Feature",
  "properties": {
    "addr:full":"8802 180th St SE Snohomish WA 98296",
    "addr:housenumber":"8802",
    "addr:postcode":"98296",
    "addr:street":"180Th St Se",
    "iso:country":"US",
    "sg:address":"8802 180th St SE",
    "sg:city":"Snohomish",
    "sg:classifiers":[
        {
            "category":"Utilities",
            "subcategory":"Water",
            "type":"Services"
        }
    ],
    "sg:phone":"+1 425 485 8461",
    "sg:postcode":"98296",
    "sg:province":"WA",
    "sg:tags":[
        "supply"
    ],
    "wof:name":"Cross Valley Water District",
    "wof:placetype":"venue"
},
  "geometry": {"coordinates":[-122.112842,47.833774],"type":"Point"}
}