{
  "type": "Feature",
  "properties": {
    "addr:full":"1517 4th St Bellingham WA 98225",
    "addr:housenumber":"1517",
    "addr:postcode":"98225",
    "addr:street":"4Th St",
    "iso:country":"US",
    "sg:address":"1517 4th St",
    "sg:city":"Bellingham",
    "sg:classifiers":[
        {
            "category":"Recreation",
            "subcategory":"Marina",
            "type":"Entertainment"
        }
    ],
    "sg:phone":"+1 360 671 3434",
    "sg:postcode":"98225",
    "sg:province":"WA",
    "sg:tags":[
        "operation"
    ],
    "wof:name":"Macconnell Marine",
    "wof:placetype":"venue"
},
  "geometry": {"coordinates":[-122.51146300000001,48.717847],"type":"Point"}
}