{
  "type": "Feature",
  "properties": {
    "iso:country":"US",
    "sg:address":"309 N 3rd St",
    "sg:city":"Yakima",
    "sg:classifiers":[
        {
            "category":"Professional",
            "subcategory":"Business Services",
            "type":"Services"
        }
    ],
    "sg:phone":"+1 509 573 6281",
    "sg:postcode":"98901",
    "sg:province":"WA",
    "sg:tags":[
        "food",
        "broker"
    ],
    "wof:name":"MTM National Inc",
    "wof:placetype":"venue"
},
  "geometry": {"coordinates":[-120.505415,46.607865],"type":"Point"}
}