{
  "type": "Feature",
  "properties": {
    "addr:full":"1616 N 2nd Ave Kelso WA 98626",
    "addr:housenumber":"1616",
    "addr:postcode":"98626",
    "addr:street":"N 2Nd Ave",
    "iso:country":"US",
    "sg:address":"1616 N 2nd Ave",
    "sg:city":"Kelso",
    "sg:classifiers":[
        {
            "category":"Shopping",
            "subcategory":"Clothing, Apparel, & Fashions",
            "type":"Retail Goods"
        }
    ],
    "sg:phone":"+1 360 423 8872",
    "sg:postcode":"98626",
    "sg:province":"WA",
    "wof:name":"Stars Wedding Shop",
    "wof:placetype":"venue"
},
  "geometry": {"coordinates":[-122.910597,46.159492],"type":"Point"}
}