{
  "type": "Feature",
  "properties": {
    "addr:full":"18715 80th St E Sumner WA 98391",
    "addr:housenumber":"18715",
    "addr:postcode":"98391",
    "addr:street":"80Th St E",
    "iso:country":"US",
    "sg:address":"18715 80th St E",
    "sg:city":"Sumner",
    "sg:classifiers":[
        {
            "category":"Education",
            "subcategory":"School",
            "type":"Public Place"
        }
    ],
    "sg:phone":"+1 253 891 4450",
    "sg:postcode":"98391",
    "sg:province":"WA",
    "wof:name":"Bonnie Lake Elementary School",
    "wof:placetype":"venue"
},
  "geometry": {"coordinates":[-122.178586,47.185413],"type":"Point"}
}