{
  "type": "Feature",
  "properties": {
    "addr:full":"16629 NE 122nd St Redmond WA 98052",
    "addr:housenumber":"16629",
    "addr:postcode":"98052",
    "addr:street":"Ne 122Nd St",
    "iso:country":"US",
    "sg:address":"16629 NE 122nd St",
    "sg:city":"Redmond",
    "sg:classifiers":[
        {
            "category":"Shopping",
            "subcategory":"Clothing, Apparel, & Fashions",
            "type":"Retail Goods"
        }
    ],
    "sg:phone":"+1 425 883 7453",
    "sg:postcode":"98052",
    "sg:province":"WA",
    "sg:tags":[
        "sporting",
        "sport",
        "order",
        "special"
    ],
    "wof:name":"Eastside Sporting Goods Co",
    "wof:placetype":"venue"
},
  "geometry": {"coordinates":[-122.119679,47.709155],"type":"Point"}
}