{
  "type": "Feature",
  "properties": {
    "addr:full":"11970 SW Misty Ln Port Orchard WA 98367",
    "addr:housenumber":"11970",
    "addr:postcode":"98367",
    "addr:street":"Sw Misty Ln",
    "iso:country":"US",
    "sg:address":"11970 SW Misty Ln",
    "sg:city":"Port Orchard",
    "sg:classifiers":[
        {
            "category":"Building & Trades",
            "subcategory":"Construction",
            "type":"Services"
        }
    ],
    "sg:phone":"+1 360 895 6062",
    "sg:postcode":"98367",
    "sg:province":"WA",
    "sg:tags":[
        "excavation",
        "contractor"
    ],
    "wof:name":"Down To Earth",
    "wof:placetype":"venue"
},
  "geometry": {"coordinates":[-122.691524,47.449043],"type":"Point"}
}