{
  "type": "Feature",
  "properties": {
    "addr:full":"211 SE Kamilche Shores Rd Shelton WA 98584",
    "addr:housenumber":"211",
    "addr:postcode":"98584",
    "addr:street":"Se Kamilche Shores Rd",
    "iso:country":"US",
    "sg:address":"211 SE Kamilche Shores Rd",
    "sg:city":"Shelton",
    "sg:classifiers":[
        {
            "category":"Shopping",
            "subcategory":"Used Merchandise",
            "type":"Retail Goods"
        }
    ],
    "sg:phone":"+1 360 426 5377",
    "sg:postcode":"98584",
    "sg:province":"WA",
    "wof:name":"Homeport Antiques",
    "wof:placetype":"venue"
},
  "geometry": {"coordinates":[-123.01914600000001,47.146113],"type":"Point"}
}