{
  "type": "Feature",
  "properties": {
    "addr:full":"1800 112th Ave NE # 150W Bellevue WA 98004",
    "addr:housenumber":"1800",
    "addr:postcode":"98004",
    "addr:street":"112Th Ave Ne # 150W",
    "iso:country":"US",
    "sg:address":"1800 112th Ave NE # 150W",
    "sg:city":"Bellevue",
    "sg:classifiers":[
        {
            "category":"Health Services",
            "subcategory":"Clinic",
            "type":"Services"
        },
        {
            "category":"Education",
            "subcategory":"School",
            "type":"Public Place"
        }
    ],
    "sg:phone":"+1 425 646 7279",
    "sg:postcode":"98004",
    "sg:province":"WA",
    "sg:tags":[
        "counseling",
        "mental"
    ],
    "sg:website":"www.abhc.com",
    "wof:name":"Associated Behavioral Health Care Inc",
    "wof:placetype":"venue"
},
  "geometry": {"coordinates":[-122.190048,47.627223],"type":"Point"}
}