{
  "type": "Feature",
  "properties": {
    "iso:country":"US",
    "sg:address":"4424 154th Pl SW",
    "sg:city":"Lynnwood",
    "sg:classifiers":[
        {
            "category":"Professional",
            "subcategory":"Computer Services",
            "type":"Services"
        }
    ],
    "sg:phone":"+1 425 787 0193",
    "sg:postcode":"98087",
    "sg:province":"WA",
    "sg:tags":[
        "internet"
    ],
    "wof:name":"Ldowens Computing/Network Svc",
    "wof:placetype":"venue"
},
  "geometry": {"coordinates":[-122.29411399999999,47.858578],"type":"Point"}
}