{
  "type": "Feature",
  "properties": {
    "addr:full":"4717 N Jefferson St Spokane WA 99205",
    "addr:housenumber":"4717",
    "addr:postcode":"99205",
    "addr:street":"N Jefferson St",
    "iso:country":"US",
    "sg:address":"4717 N Jefferson St",
    "sg:city":"Spokane",
    "sg:classifiers":[
        {
            "category":"Social Services",
            "subcategory":"Child Care",
            "type":"Services"
        }
    ],
    "sg:phone":"+1 509 326 2196",
    "sg:postcode":"99205",
    "sg:province":"WA",
    "sg:tags":[
        "day"
    ],
    "wof:name":"Crystals Childcare",
    "wof:placetype":"venue"
},
  "geometry": {"coordinates":[-117.428556,47.702419],"type":"Point"}
}