{
  "type": "Feature",
  "properties": {
    "addr:full":"4104 E 21st Ave Spokane WA 99223",
    "addr:housenumber":"4104",
    "addr:postcode":"99223",
    "addr:street":"E 21St Ave",
    "iso:country":"US",
    "sg:address":"4104 E 21st Ave",
    "sg:city":"Spokane",
    "sg:classifiers":[
        {
            "category":"Building & Trades",
            "subcategory":"Construction",
            "type":"Services"
        }
    ],
    "sg:phone":"+1 509 994 7300",
    "sg:postcode":"99223",
    "sg:province":"WA",
    "sg:tags":[
        "concrete",
        "contractor"
    ],
    "wof:name":"Barnes Carpet",
    "wof:placetype":"venue"
},
  "geometry": {"coordinates":[-117.350908,47.63539],"type":"Point"}
}