{
  "type": "Feature",
  "properties": {
    "addr:full":"81 Vine St Seattle WA 98121",
    "addr:housenumber":"81",
    "addr:postcode":"98121",
    "addr:street":"Vine St",
    "iso:country":"US",
    "sg:address":"81 Vine St",
    "sg:city":"Seattle",
    "sg:classifiers":[
        {
            "category":"Real Estate",
            "subcategory":"Architect",
            "type":"Services"
        }
    ],
    "sg:phone":"+1 206 622 9112",
    "sg:postcode":"98121",
    "sg:province":"WA",
    "sg:tags":[
        "designer"
    ],
    "wof:name":"Zena Design Group",
    "wof:placetype":"venue"
},
  "geometry": {"coordinates":[-122.349858,47.614932],"type":"Point"}
}