{
  "type": "Feature",
  "properties": {
    "addr:full":"10839 24th Ave S Seattle WA 98168",
    "addr:housenumber":"10839",
    "addr:postcode":"98168",
    "addr:street":"24Th Ave S",
    "iso:country":"US",
    "sg:address":"10839 24th Ave S",
    "sg:city":"Seattle",
    "sg:classifiers":[
        {
            "category":"Museum",
            "type":"Entertainment"
        }
    ],
    "sg:phone":"+1 206 244 6745",
    "sg:postcode":"98168",
    "sg:province":"WA",
    "sg:tags":[
        "commercial",
        "design",
        "gallery"
    ],
    "wof:name":"Open Mondays",
    "wof:placetype":"venue"
},
  "geometry": {"coordinates":[-122.302173,47.504912],"type":"Point"}
}