{
  "type": "Feature",
  "properties": {
    "iso:country":"US",
    "sg:address":"1704 Joans Ln",
    "sg:city":"Lummi Island",
    "sg:classifiers":[
        {
            "category":"Freight",
            "type":"Transportation"
        }
    ],
    "sg:phone":"+1 360 758 7470",
    "sg:postcode":"98262",
    "sg:province":"WA",
    "sg:tags":[
        "fixed",
        "motor",
        "facility"
    ],
    "wof:name":"C&S Home Inspections Inc",
    "wof:placetype":"venue"
},
  "geometry": {"coordinates":[-122.685658,48.706435],"type":"Point"}
}