{
  "type": "Feature",
  "properties": {
    "addr:full":"526 Yale Ave N Seattle WA 98109",
    "addr:housenumber":"526",
    "addr:postcode":"98109",
    "addr:street":"Yale Ave N",
    "iso:country":"US",
    "sg:address":"526 Yale Ave N",
    "sg:city":"Seattle",
    "sg:classifiers":[
        {
            "category":"Communications",
            "type":"Services"
        }
    ],
    "sg:phone":"+1 206 256 0420",
    "sg:postcode":"98109",
    "sg:province":"WA",
    "wof:name":"E In Communications Studio 700",
    "wof:placetype":"venue"
},
  "geometry": {"coordinates":[-122.330423,47.623439],"type":"Point"}
}