{
  "type": "Feature",
  "properties": {
    "addr:full":"15759 NE 15th St Bellevue WA 98008",
    "addr:housenumber":"15759",
    "addr:postcode":"98008",
    "addr:street":"Ne 15Th St",
    "iso:country":"US",
    "sg:address":"15759 NE 15th St",
    "sg:city":"Bellevue",
    "sg:classifiers":[
        {
            "category":"Building & Trades",
            "subcategory":"Locksmith",
            "type":"Services"
        }
    ],
    "sg:phone":"+1 425 484 1039",
    "sg:postcode":"98008",
    "sg:province":"WA",
    "sg:tags":[
        "key"
    ],
    "wof:name":"A Master Locksmith 24 7",
    "wof:placetype":"venue"
},
  "geometry": {"coordinates":[-122.129903,47.623113],"type":"Point"}
}