{
  "type": "Feature",
  "properties": {
    "addr:full":"2725 38th Ave SW Seattle WA 98126",
    "addr:housenumber":"2725",
    "addr:postcode":"98126",
    "addr:street":"38Th Ave Sw",
    "iso:country":"US",
    "sg:address":"2725 38th Ave SW",
    "sg:city":"Seattle",
    "sg:classifiers":[
        {
            "category":"Wholesale",
            "subcategory":"Chemicals & Plastics",
            "type":"Manufacturing & Wholesale Goods"
        }
    ],
    "sg:phone":"+1 206 932 7216",
    "sg:postcode":"98126",
    "sg:province":"WA",
    "wof:name":"Christine A Evens",
    "wof:placetype":"venue"
},
  "geometry": {"coordinates":[-122.380342,47.577587],"type":"Point"}
}