{
  "type": "Feature",
  "properties": {
    "iso:country":"US",
    "sg:address":"1550 Hoover Ave SE",
    "sg:city":"Port Orchard",
    "sg:classifiers":[
        {
            "category":"Organizations",
            "subcategory":"Religious Organization",
            "type":"Services"
        }
    ],
    "sg:phone":"+1 360 895 4168",
    "sg:postcode":"98366",
    "sg:province":"WA",
    "sg:tags":[
        "church"
    ],
    "wof:name":"Church Of Jesus Christ Of Lds",
    "wof:placetype":"venue"
},
  "geometry": {"coordinates":[-122.626841,47.52593],"type":"Point"}
}