{
  "type": "Feature",
  "properties": {
    "addr:full":"5333 1st Ave S Seattle WA 98108",
    "addr:housenumber":"5333",
    "addr:postcode":"98108",
    "addr:street":"1St Ave S",
    "iso:country":"US",
    "sg:address":"5333 1st Ave S",
    "sg:city":"Seattle",
    "sg:classifiers":[
        {
            "category":"Professional",
            "subcategory":"Printing & Photocopies",
            "type":"Services"
        }
    ],
    "sg:phone":"+1 206 768 8664",
    "sg:postcode":"98108",
    "sg:province":"WA",
    "sg:tags":[
        "duplicating",
        "copying"
    ],
    "wof:name":"Digital Copier Technology Inc",
    "wof:placetype":"venue"
},
  "geometry": {"coordinates":[-122.334292,47.554412],"type":"Point"}
}