{
  "type": "Feature",
  "properties": {
    "addr:full":"6812 S 220th St Kent WA 98032",
    "addr:housenumber":"6812",
    "addr:postcode":"98032",
    "addr:street":"S 220Th St",
    "iso:country":"US",
    "sg:address":"6812 S 220th St",
    "sg:city":"Kent",
    "sg:classifiers":[
        {
            "category":"Manufacturing",
            "subcategory":"Metals",
            "type":"Manufacturing & Wholesale Goods"
        }
    ],
    "sg:phone":"+1 253 872 8080",
    "sg:postcode":"98032",
    "sg:province":"WA",
    "sg:tags":[
        "fluid",
        "power",
        "mfg"
    ],
    "wof:name":"Parker Store",
    "wof:placetype":"venue"
},
  "geometry": {"coordinates":[-122.248504,47.405038],"type":"Point"}
}