{
  "type": "Feature",
  "properties": {
    "addr:full":"8605 N Division St Spokane WA 99208",
    "addr:housenumber":"8605",
    "addr:postcode":"99208",
    "addr:street":"N Division St",
    "iso:country":"US",
    "sg:address":"8605 N Division St",
    "sg:city":"Spokane",
    "sg:classifiers":[
        {
            "category":"Professional",
            "subcategory":"Accounting & Tax Preparation",
            "type":"Services"
        }
    ],
    "sg:phone":"+1 509 467 5992",
    "sg:postcode":"99208",
    "sg:province":"WA",
    "sg:tags":[
        "return",
        "filing"
    ],
    "wof:name":"Tax It EZ",
    "wof:placetype":"venue"
},
  "geometry": {"coordinates":[-117.41148099999999,47.735881],"type":"Point"}
}