{
  "type": "Feature",
  "properties": {
    "addr:full":"333 Arthur Ln Monroe WA 98272",
    "addr:housenumber":"333",
    "addr:postcode":"98272",
    "addr:street":"Arthur Ln",
    "iso:country":"US",
    "sg:address":"333 Arthur Ln",
    "sg:city":"Monroe",
    "sg:classifiers":[
        {
            "category":"Home & Garden",
            "subcategory":"Furniture",
            "type":"Retail Goods"
        }
    ],
    "sg:phone":"+1 360 794 7845",
    "sg:postcode":"98272",
    "sg:province":"WA",
    "sg:tags":[
        "store"
    ],
    "wof:name":"Arthur Lane Furniture Refinish",
    "wof:placetype":"venue"
},
  "geometry": {"coordinates":[-121.97429700000001,47.85723],"type":"Point"}
}