{
  "type": "Feature",
  "properties": {
    "addr:full":"33506 10th Pl S Federal Way WA 98003",
    "addr:housenumber":"33506",
    "addr:postcode":"98003",
    "addr:street":"10Th Pl S Federal Way",
    "iso:country":"US",
    "sg:address":"33506 10th Pl S",
    "sg:city":"Federal Way",
    "sg:classifiers":[
        {
            "category":"Government",
            "subcategory":"Court House",
            "type":"Public Place"
        }
    ],
    "sg:phone":"+1 206 296 7784",
    "sg:postcode":"98003",
    "sg:province":"WA",
    "sg:tags":[
        "state",
        "system"
    ],
    "wof:name":"King Cnty Dst Crt Federal Way",
    "wof:placetype":"venue"
},
  "geometry": {"coordinates":[-122.320476,47.301825],"type":"Point"}
}