{
  "type": "Feature",
  "properties": {
    "addr:full":"24503 197th Ave SE Maple Valley WA 98038",
    "addr:housenumber":"24503",
    "addr:postcode":"98038",
    "addr:street":"197Th Ave Se;Valley",
    "iso:country":"US",
    "sg:address":"24503 197th Ave SE",
    "sg:city":"Maple Valley",
    "sg:classifiers":[
        {
            "category":"Building & Trades",
            "subcategory":"Construction",
            "type":"Services"
        }
    ],
    "sg:phone":"+1 425 432 4929",
    "sg:postcode":"98038",
    "sg:province":"WA",
    "sg:tags":[
        "industrial",
        "commercial",
        "contractor"
    ],
    "wof:name":"D Wolf Construction Inc",
    "wof:placetype":"venue"
},
  "geometry": {"coordinates":[-122.079117,47.384525],"type":"Point"}
}