{
  "type": "Feature",
  "properties": {
    "addr:full":"25413 SE Mirrormont Dr Issaquah WA 98027",
    "addr:postcode":"25413;98027",
    "addr:street":"Se Mirrormont Dr",
    "iso:country":"US",
    "sg:address":"25413 SE Mirrormont Dr",
    "sg:city":"Issaquah",
    "sg:classifiers":[
        {
            "category":"Building & Trades",
            "subcategory":"Construction",
            "type":"Services"
        }
    ],
    "sg:phone":"+1 425 392 6564",
    "sg:postcode":"98027",
    "sg:province":"WA",
    "sg:tags":[
        "house"
    ],
    "wof:name":"Classic Design & Renovations L",
    "wof:placetype":"venue"
},
  "geometry": {"coordinates":[-122.002938,47.463371],"type":"Point"}
}