{
  "type": "Feature",
  "properties": {
    "addr:full":"7225 S Oakes St Tacoma WA 98409",
    "addr:housenumber":"7225",
    "addr:postcode":"98409",
    "addr:street":"S Oakes St",
    "iso:country":"US",
    "sg:address":"7225 S Oakes St",
    "sg:city":"Tacoma",
    "sg:classifiers":[
        {
            "category":"Building & Trades",
            "subcategory":"Construction",
            "type":"Services"
        }
    ],
    "sg:phone":"+1 253 539 8655",
    "sg:postcode":"98409",
    "sg:province":"WA",
    "sg:tags":[
        "contractor"
    ],
    "wof:name":"King Spider Siding",
    "wof:placetype":"venue"
},
  "geometry": {"coordinates":[-122.47239,47.190369],"type":"Point"}
}