{
  "type": "Feature",
  "properties": {
    "addr:full":"18022 N Judy Dr Colbert WA 99005",
    "addr:housenumber":"18022",
    "addr:postcode":"99005",
    "addr:street":"N Judy Dr Colbert",
    "iso:country":"US",
    "sg:address":"18022 N Judy Dr",
    "sg:city":"Colbert",
    "sg:classifiers":[
        {
            "category":"Manufacturing",
            "subcategory":"Building Materials",
            "type":"Manufacturing & Wholesale Goods"
        }
    ],
    "sg:phone":"+1 509 466 0651",
    "sg:postcode":"99005",
    "sg:province":"WA",
    "sg:tags":[
        "mfg"
    ],
    "wof:name":"Knapps Custom Woodworking",
    "wof:placetype":"venue"
},
  "geometry": {"coordinates":[-117.367332,47.822152],"type":"Point"}
}