{
  "type": "Feature",
  "properties": {
    "addr:full":"2110 116th AVE NE Ste C Bellevue WA 98004",
    "addr:housenumber":"2110",
    "addr:postcode":"98004",
    "addr:street":"116Th Ave Ne Ste C",
    "iso:country":"US",
    "sg:address":"2110 116th AVE NE Ste C",
    "sg:city":"Bellevue",
    "sg:classifiers":[
        {
            "category":"Health Services",
            "subcategory":"Chiropractor",
            "type":"Services"
        }
    ],
    "sg:phone":"+1 425 646 7475",
    "sg:postcode":"98004",
    "sg:province":"WA",
    "wof:name":"Diane M Hughes DC",
    "wof:placetype":"venue"
},
  "geometry": {"coordinates":[-122.18476,47.629852],"type":"Point"}
}