{
  "type": "Feature",
  "properties": {
    "addr:full":"6023 189th Pl SW Lynnwood WA 98036",
    "addr:housenumber":"6023",
    "addr:postcode":"98036",
    "addr:street":"189Th Pl Sw",
    "iso:country":"US",
    "sg:address":"6023 189th Pl SW",
    "sg:city":"Lynnwood",
    "sg:classifiers":[
        {
            "category":"Insurance",
            "subcategory":"Insurance Agent",
            "type":"Services"
        }
    ],
    "sg:phone":"+1 425 776 8017",
    "sg:postcode":"98036",
    "sg:province":"WA",
    "wof:name":"Miller & Miller",
    "wof:placetype":"venue"
},
  "geometry": {"coordinates":[-122.316074,47.827636],"type":"Point"}
}