{
  "type": "Feature",
  "properties": {
    "addr:full":"316 N 11th St Tacoma WA 98403",
    "addr:housenumber":"316",
    "addr:postcode":"98403",
    "addr:street":"N 11Th St",
    "iso:country":"US",
    "sg:address":"316 N 11th St",
    "sg:city":"Tacoma",
    "sg:classifiers":[
        {
            "category":"Professional",
            "subcategory":"Lawyer & Legal Services",
            "type":"Services"
        }
    ],
    "sg:phone":"+1 253 272 3683",
    "sg:postcode":"98403",
    "sg:province":"WA",
    "wof:name":"Leonard J Heritage Attorn",
    "wof:placetype":"venue"
},
  "geometry": {"coordinates":[-122.461202,47.271136],"type":"Point"}
}