{
  "type": "Feature",
  "properties": {
    "addr:full":"442 Bond Rd Cusick WA 99119",
    "addr:housenumber":"442",
    "addr:postcode":"99119",
    "addr:street":"Bond Rd",
    "iso:country":"US",
    "sg:address":"442 Bond Rd",
    "sg:city":"Cusick",
    "sg:classifiers":[
        {
            "category":"Professional",
            "subcategory":"Art Services",
            "type":"Services"
        }
    ],
    "sg:phone":"+1 509 671 0811",
    "sg:postcode":"99119",
    "sg:province":"WA",
    "sg:tags":[
        "commercial",
        "design"
    ],
    "wof:name":"Absolute Design",
    "wof:placetype":"venue"
},
  "geometry": {"coordinates":[-117.351523,48.338083],"type":"Point"}
}