{
  "type": "Feature",
  "properties": {
    "addr:full":"547 Meadows Dr S Richland WA 99352",
    "addr:housenumber":"547",
    "addr:postcode":"99352",
    "addr:street":"Meadows Dr S",
    "iso:country":"US",
    "sg:address":"547 Meadows Dr S",
    "sg:city":"Richland",
    "sg:classifiers":[
        {
            "category":"Professional",
            "subcategory":"Management & Consulting",
            "type":"Services"
        }
    ],
    "sg:phone":"+1 509 627 0621",
    "sg:postcode":"99352",
    "sg:province":"WA",
    "sg:tags":[
        "business"
    ],
    "wof:name":"H & A Industries",
    "wof:placetype":"venue"
},
  "geometry": {"coordinates":[-119.252582,46.219363],"type":"Point"}
}