{
  "type": "Feature",
  "properties": {
    "addr:full":"32925 18th Ave SW Federal Way WA 98023",
    "addr:housenumber":"32925",
    "addr:postcode":"98023",
    "addr:street":"18Th Ave Sw Federal Way",
    "iso:country":"US",
    "sg:address":"32925 18th Ave SW",
    "sg:city":"Federal Way",
    "sg:classifiers":[
        {
            "category":"Retail",
            "subcategory":"Animal Services",
            "type":"Services"
        }
    ],
    "sg:phone":"+1 253 874 4676",
    "sg:postcode":"98023",
    "sg:province":"WA",
    "wof:name":"Doggie Inn",
    "wof:placetype":"venue"
},
  "geometry": {"coordinates":[-122.35810600000001,47.305382],"type":"Point"}
}