{
  "type": "Feature",
  "properties": {
    "addr:full":"1017 168th Ave SE Bellevue WA 98008",
    "addr:housenumber":"1017",
    "addr:postcode":"98008",
    "addr:street":"168Th Ave Se",
    "iso:country":"US",
    "sg:address":"1017 168th Ave SE",
    "sg:city":"Bellevue",
    "sg:classifiers":[
        {
            "category":"Travel",
            "subcategory":"Travel Agent",
            "type":"Entertainment"
        }
    ],
    "sg:phone":"+1 425 746 3414",
    "sg:postcode":"98008",
    "sg:province":"WA",
    "sg:tags":[
        "cruise"
    ],
    "wof:name":"Cebu Cruises For Non-Smokers",
    "wof:placetype":"venue"
},
  "geometry": {"coordinates":[-122.11696000000001,47.600894],"type":"Point"}
}