{
  "type": "Feature",
  "properties": {
    "addr:full":"406 W 1st St Warden WA 98857",
    "addr:housenumber":"406",
    "addr:postcode":"98857",
    "addr:street":"W 1St St",
    "iso:country":"US",
    "sg:address":"406 W 1st St",
    "sg:city":"Warden",
    "sg:classifiers":[
        {
            "category":"Professional",
            "subcategory":"Advertising",
            "type":"Services"
        }
    ],
    "sg:phone":"+1 509 349 0313",
    "sg:postcode":"98857",
    "sg:province":"WA",
    "sg:tags":[
        "mail",
        "direct"
    ],
    "wof:name":"Val-Pak Advertising",
    "wof:placetype":"venue"
},
  "geometry": {"coordinates":[-119.036025,46.969669],"type":"Point"}
}