{
  "type": "Feature",
  "properties": {
    "addr:full":"9448 Hart Rd SE Olympia WA 98501",
    "addr:housenumber":"9448",
    "addr:postcode":"olympia;98501",
    "addr:street":"Hart Rd Se",
    "iso:country":"US",
    "sg:address":"9448 Hart Rd SE",
    "sg:city":"Olympia",
    "sg:classifiers":[
        {
            "category":"Professional",
            "type":"Services"
        }
    ],
    "sg:phone":"+1 360 943 5863",
    "sg:postcode":"98501",
    "sg:province":"WA",
    "wof:name":"Debra Healy",
    "wof:placetype":"venue"
},
  "geometry": {"coordinates":[-122.897127,46.950324],"type":"Point"}
}