{
  "type": "Feature",
  "properties": {
    "addr:full":"1370 Woodcock Rd Sequim WA 98382",
    "addr:housenumber":"1370",
    "addr:postcode":"98382",
    "addr:street":"Woodcock Rd",
    "iso:country":"US",
    "sg:address":"1370 Woodcock Rd",
    "sg:city":"Sequim",
    "sg:classifiers":[
        {
            "category":"Building & Trades",
            "subcategory":"Plumbing",
            "type":"Services"
        },
        {
            "category":"Home & Garden",
            "subcategory":"Building Materials",
            "type":"Retail Goods"
        },
        {
            "category":"Manufacturing",
            "subcategory":"Building Materials",
            "type":"Manufacturing & Wholesale Goods"
        }
    ],
    "sg:phone":"+1 360 683 4714",
    "sg:postcode":"98382",
    "sg:province":"WA",
    "sg:tags":[
        "product",
        "tank",
        "septic",
        "system",
        "concrete",
        "shape",
        "block"
    ],
    "wof:name":"Peninsula Tanks Inc",
    "wof:placetype":"venue"
},
  "geometry": {"coordinates":[-123.186001,48.116112],"type":"Point"}
}