{
  "type": "Feature",
  "properties": {
    "addr:full":"723 S Myrtle St Seattle WA 98108",
    "addr:housenumber":"723",
    "addr:postcode":"98108",
    "addr:street":"S Myrtle St",
    "iso:country":"US",
    "sg:address":"723 S Myrtle St",
    "sg:city":"Seattle",
    "sg:classifiers":[
        {
            "category":"Manufacturing",
            "subcategory":"Tools & Machinery",
            "type":"Manufacturing & Wholesale Goods"
        }
    ],
    "sg:phone":"+1 206 762 4777",
    "sg:postcode":"98108",
    "sg:province":"WA",
    "sg:tags":[
        "machine",
        "shop"
    ],
    "wof:name":"D & D Repair",
    "wof:placetype":"venue"
},
  "geometry": {"coordinates":[-122.32298400000001,47.539326],"type":"Point"}
}