{
  "type": "Feature",
  "properties": {
    "addr:full":"8903 NE Koura Rd Bainbridge Isle WA 98110",
    "addr:housenumber":"8903",
    "addr:postcode":"98110",
    "addr:street":"Ne Koura Rd;Isle",
    "iso:country":"US",
    "sg:address":"8903 NE Koura Rd",
    "sg:city":"Bainbridge Isle",
    "sg:classifiers":[
        {
            "category":"Social Services",
            "subcategory":"Child Care",
            "type":"Services"
        }
    ],
    "sg:phone":"+1 206 780 1928",
    "sg:postcode":"98110",
    "sg:province":"WA",
    "sg:website":"www.hazelcreekmontessori.com",
    "wof:name":"Hazel Creek Montessori",
    "wof:placetype":"venue"
},
  "geometry": {"coordinates":[-122.529027,47.66478],"type":"Point"}
}