{
  "type": "Feature",
  "properties": {
    "iso:country":"US",
    "sg:address":"11504 21st Pl NE",
    "sg:city":"Lake Stevens",
    "sg:classifiers":[
        {
            "category":"Social Services",
            "subcategory":"Child Care",
            "type":"Services"
        }
    ],
    "sg:phone":"+1 425 334 3289",
    "sg:postcode":"98258",
    "sg:province":"WA",
    "sg:tags":[
        "day"
    ],
    "wof:name":"Hill Cottage Child Care",
    "wof:placetype":"venue"
},
  "geometry": {"coordinates":[-122.075551,48.017071],"type":"Point"}
}