{
  "type": "Feature",
  "properties": {
    "addr:full":"9121 50th Ave S Seattle WA 98118",
    "addr:housenumber":"9121",
    "addr:postcode":"98118",
    "addr:street":"50Th Ave S",
    "iso:country":"US",
    "sg:address":"9121 50th Ave S",
    "sg:city":"Seattle",
    "sg:classifiers":[
        {
            "category":"Building & Trades",
            "subcategory":"Construction",
            "type":"Services"
        }
    ],
    "sg:phone":"+1 206 356 2035",
    "sg:postcode":"98118",
    "sg:province":"WA",
    "sg:tags":[
        "painter"
    ],
    "wof:name":"De LA Fuente Painting",
    "wof:placetype":"venue"
},
  "geometry": {"coordinates":[-122.27144199999999,47.521442],"type":"Point"}
}