{
  "type": "Feature",
  "properties": {
    "addr:full":"2 Roy St Seattle WA 98119",
    "addr:housenumber":"2",
    "addr:postcode":"98119",
    "addr:street":"Roy St",
    "iso:country":"US",
    "sg:address":"2 Roy St",
    "sg:city":"Seattle",
    "sg:classifiers":[
        {
            "category":"Park",
            "type":"Public Place"
        }
    ],
    "sg:postcode":"98119",
    "sg:province":"WA",
    "wof:name":"Counterbalance Park",
    "wof:placetype":"venue"
},
  "geometry": {"coordinates":[-122.35671600000001,47.62548],"type":"Point"}
}