{
  "type": "Feature",
  "properties": {
    "addr:full":"3303 Monte Villa Pkwy # 250 Bothell WA 98021",
    "addr:housenumber":"3303",
    "addr:postcode":"98021",
    "addr:street":"Monte Villa Pkwy # 250",
    "iso:country":"US",
    "sg:address":"3303 Monte Villa Pkwy # 250",
    "sg:city":"Bothell",
    "sg:classifiers":[
        {
            "category":"Wholesale",
            "subcategory":"Medical Equipment & Supplies",
            "type":"Manufacturing & Wholesale Goods"
        }
    ],
    "sg:phone":"+1 425 402 2000",
    "sg:postcode":"98021",
    "sg:province":"WA",
    "sg:tags":[
        "instrument",
        "surgical"
    ],
    "wof:name":"Quinton Cardiology Systems, Inc.",
    "wof:placetype":"venue"
},
  "geometry": {"coordinates":[-122.189526,47.778042],"type":"Point"}
}