{
  "type": "Feature",
  "properties": {
    "addr:full":"2135 112th Ave NE Suite 240 Bellevue WA 98004",
    "addr:housenumber":"2135",
    "addr:postcode":"98004",
    "addr:street":"112Th Ave Ne Suite 240",
    "iso:country":"US",
    "sg:address":"2135 112th Ave NE Suite 240",
    "sg:city":"Bellevue",
    "sg:classifiers":[
        {
            "category":"Professional",
            "subcategory":"Lawyer & Legal Services",
            "type":"Services"
        }
    ],
    "sg:phone":"+1 425 451 8668",
    "sg:postcode":"98004",
    "sg:province":"WA",
    "sg:tags":[
        "attorney",
        "business",
        "corporation",
        "partnership",
        "real estate",
        "law"
    ],
    "sg:website":"http://www.abolofialaw.com",
    "wof:name":"Abolofia Gary",
    "wof:placetype":"venue"
},
  "geometry": {"coordinates":[-122.190956,47.628277],"type":"Point"}
}