{
  "type": "Feature",
  "properties": {
    "addr:full":"222 State Rte 505 Winlock WA 98596",
    "addr:housenumber":"222",
    "addr:postcode":"98596",
    "addr:street":"State Rte 505",
    "iso:country":"US",
    "sg:address":"222 State Rte 505",
    "sg:city":"Winlock",
    "sg:classifiers":[
        {
            "category":"Home & Garden",
            "subcategory":"Building Materials",
            "type":"Retail Goods"
        }
    ],
    "sg:phone":"+1 360 785 4714",
    "sg:postcode":"98596",
    "sg:province":"WA",
    "sg:tags":[
        "windows",
        "door",
        "storm"
    ],
    "sg:website":"www.mihomeproducts.com",
    "wof:name":"M I Home Products Inc",
    "wof:placetype":"venue"
},
  "geometry": {"coordinates":[-122.924587,46.489435],"type":"Point"}
}