{
  "type": "Feature",
  "properties": {
    "addr:full":"4014 148th Ave NE Redmond WA 98052",
    "addr:housenumber":"4014",
    "addr:postcode":"98052",
    "addr:street":"148Th Ave Ne",
    "iso:country":"US",
    "sg:address":"4014 148th Ave NE",
    "sg:city":"Redmond",
    "sg:classifiers":[
        {
            "category":"Professional",
            "subcategory":"Employment Agencies",
            "type":"Services"
        }
    ],
    "sg:phone":"+1 425 861 9460",
    "sg:postcode":"98052",
    "sg:province":"WA",
    "sg:website":"www.xtremeconsulting.com",
    "wof:name":"Xtreme Consulting Group",
    "wof:placetype":"venue"
},
  "geometry": {"coordinates":[-122.143028,47.646009],"type":"Point"}
}