{
  "type": "Feature",
  "properties": {
    "addr:full":"21702 84th Ave S Kent WA 98032",
    "addr:housenumber":"21702",
    "addr:postcode":"98032",
    "addr:street":"84Th Ave S",
    "iso:country":"US",
    "sg:address":"21702 84th Ave S",
    "sg:city":"Kent",
    "sg:classifiers":[
        {
            "category":"Manufacturing",
            "subcategory":"Tools & Machinery",
            "type":"Manufacturing & Wholesale Goods"
        }
    ],
    "sg:phone":"+1 253 872 4779",
    "sg:postcode":"98032",
    "sg:province":"WA",
    "sg:tags":[
        "machine",
        "shop",
        "job"
    ],
    "wof:name":"Tcm",
    "wof:placetype":"venue"
},
  "geometry": {"coordinates":[-122.227926,47.406513],"type":"Point"}
}