{
  "type": "Feature",
  "properties": {
    "addr:full":"6115 E Trent Ave Spokane WA 99212",
    "addr:housenumber":"6115",
    "addr:postcode":"99212",
    "addr:street":"E Trent Ave",
    "iso:country":"US",
    "sg:address":"6115 E Trent Ave",
    "sg:city":"Spokane",
    "sg:classifiers":[
        {
            "category":"Restaurant",
            "type":"Food & Drink"
        }
    ],
    "sg:phone":"+1 509 534 3113",
    "sg:postcode":"99212",
    "sg:province":"WA",
    "sg:tags":[
        "eating"
    ],
    "wof:name":"Mikes Burger Royal",
    "wof:placetype":"venue"
},
  "geometry": {"coordinates":[-117.32011300000001,47.675264],"type":"Point"}
}