{
  "type": "Feature",
  "properties": {
    "addr:full":"211 E Hatton Rd Tieton WA 98947",
    "addr:housenumber":"211",
    "addr:postcode":"98947",
    "addr:street":"E Hatton Rd",
    "iso:country":"US",
    "sg:address":"211 E Hatton Rd",
    "sg:city":"Tieton",
    "sg:classifiers":[
        {
            "category":"Farming",
            "subcategory":"Orchard",
            "type":"Manufacturing & Wholesale Goods"
        }
    ],
    "sg:phone":"+1 509 673 2259",
    "sg:postcode":"98947",
    "sg:province":"WA",
    "sg:tags":[
        "fruit",
        "tree"
    ],
    "wof:name":"Clarks Orchard",
    "wof:placetype":"venue"
},
  "geometry": {"coordinates":[-120.734612,46.694358],"type":"Point"}
}