{
  "type": "Feature",
  "properties": {
    "addr:full":"3201 S Grand Blvd Spokane WA 99203",
    "addr:housenumber":"3201",
    "addr:postcode":"99203",
    "addr:street":"S Grand Blvd",
    "iso:country":"US",
    "sg:address":"3201 S Grand Blvd",
    "sg:city":"Spokane",
    "sg:classifiers":[
        {
            "category":"Health Services",
            "subcategory":"Doctor",
            "type":"Services"
        }
    ],
    "sg:phone":"+1 509 747 5184",
    "sg:postcode":"99203",
    "sg:province":"WA",
    "wof:name":"Stephen Mills DDS",
    "wof:placetype":"venue"
},
  "geometry": {"coordinates":[-117.401743,47.624591],"type":"Point"}
}