{
  "type": "Feature",
  "properties": {
    "addr:full":"3925 274th Ave SE Issaquah WA 98029",
    "addr:housenumber":"3925",
    "addr:postcode":"98029",
    "addr:street":"274Th Ave Se",
    "iso:country":"US",
    "sg:address":"3925 274th Ave SE",
    "sg:city":"Issaquah",
    "sg:classifiers":[
        {
            "category":"Shopping",
            "subcategory":"Computers & Home Electronics",
            "type":"Retail Goods"
        }
    ],
    "sg:phone":"+1 425 391 5000",
    "sg:postcode":"98029",
    "sg:province":"WA",
    "sg:tags":[
        "equipment",
        "dealer"
    ],
    "sg:website":"www.basker.com",
    "wof:name":"Basker Computer Group",
    "wof:placetype":"venue"
},
  "geometry": {"coordinates":[-121.973702,47.572545],"type":"Point"}
}