{
  "type": "Feature",
  "properties": {
    "addr:full":"500 Union St Ste 450 Seattle WA 98101",
    "addr:housenumber":"500",
    "addr:postcode":"98101",
    "addr:street":"Union St Ste 450",
    "iso:country":"US",
    "sg:address":"500 Union St Ste 450",
    "sg:city":"Seattle",
    "sg:classifiers":[
        {
            "category":"Professional",
            "subcategory":"Engineering",
            "type":"Services"
        },
        {
            "category":"Professional",
            "subcategory":"Business Services",
            "type":"Services"
        },
        {
            "category":"Real Estate",
            "subcategory":"Architect",
            "type":"Services"
        }
    ],
    "sg:phone":"+1 206 324 6462",
    "sg:postcode":"98101",
    "sg:province":"WA",
    "sg:tags":[
        "architects'",
        "development",
        "product",
        "designers-industrial",
        "marketing",
        "specification",
        "commercial",
        "consulting",
        "builders'",
        "construction",
        "design",
        "architectural",
        "engineer"
    ],
    "sg:website":"http://www.endelman.com",
    "wof:name":"Endelman Assoc Pllc Accssblity",
    "wof:placetype":"venue"
},
  "geometry": {"coordinates":[-122.334671,47.609661],"type":"Point"}
}