{
  "type": "Feature",
  "properties": {
    "addr:full":"3836 46th Ave NE Seattle WA 98105",
    "addr:housenumber":"3836",
    "addr:postcode":"98105",
    "addr:street":"46Th Ave Ne",
    "iso:country":"US",
    "sg:address":"3836 46th Ave NE",
    "sg:city":"Seattle",
    "sg:classifiers":[
        {
            "category":"Professional",
            "subcategory":"Art Services",
            "type":"Services"
        }
    ],
    "sg:phone":"+1 206 517 8005",
    "sg:postcode":"98105",
    "sg:province":"WA",
    "sg:tags":[
        "business"
    ],
    "wof:name":"Apogee Graphics Inc",
    "wof:placetype":"venue"
},
  "geometry": {"coordinates":[-122.278704,47.657268],"type":"Point"}
}