{
  "type": "Feature",
  "properties": {
    "addr:full":"19357 Kanako Ln Mount Vernon WA 98274",
    "addr:postcode":"19357;98274",
    "addr:street":"Kanako Ln",
    "iso:country":"US",
    "sg:address":"19357 Kanako Ln",
    "sg:city":"Mount Vernon",
    "sg:classifiers":[
        {
            "category":"Farming",
            "subcategory":"Dairy Farm",
            "type":"Manufacturing & Wholesale Goods"
        }
    ],
    "sg:phone":"+1 360 428 1990",
    "sg:postcode":"98274",
    "sg:province":"WA",
    "sg:tags":[
        "retail",
        "direct",
        "sales"
    ],
    "wof:name":"King Corn",
    "wof:placetype":"venue"
},
  "geometry": {"coordinates":[-122.309157,48.366359],"type":"Point"}
}