{
  "type": "Feature",
  "properties": {
    "addr:full":"3191 Sagehill Rd Mesa WA 99343",
    "addr:housenumber":"3191",
    "addr:postcode":"99343",
    "addr:street":"Sagehill Rd",
    "iso:country":"US",
    "sg:address":"3191 Sagehill Rd",
    "sg:city":"Mesa",
    "sg:classifiers":[
        {
            "category":"Retail",
            "subcategory":"Repair Shop",
            "type":"Services"
        }
    ],
    "sg:phone":"+1 509 269 4191",
    "sg:postcode":"99343",
    "sg:province":"WA",
    "wof:name":"Lewis Wildlife Art",
    "wof:placetype":"venue"
},
  "geometry": {"coordinates":[-119.176421,46.635627],"type":"Point"}
}