{
  "type": "Feature",
  "properties": {
    "addr:full":"16132 SE 42nd Pl Bellevue WA 98006",
    "addr:postcode":"16132;98006",
    "addr:street":"Se 42Nd Pl",
    "iso:country":"US",
    "sg:address":"16132 SE 42nd Pl",
    "sg:city":"Bellevue",
    "sg:classifiers":[
        {
            "category":"Professional",
            "subcategory":"Management & Consulting",
            "type":"Services"
        }
    ],
    "sg:phone":"+1 425 746 0050",
    "sg:postcode":"98006",
    "sg:province":"WA",
    "sg:tags":[
        "information",
        "pivotal",
        "consultant"
    ],
    "wof:name":"Pivotalinfo LLC",
    "wof:placetype":"venue"
},
  "geometry": {"coordinates":[-122.122989,47.570465],"type":"Point"}
}