{
  "type": "Feature",
  "properties": {
    "addr:full":"1401 S Howe Rd Spokane WA 99212",
    "addr:housenumber":"1401",
    "addr:postcode":"99212",
    "addr:street":"S Howe Rd",
    "iso:country":"US",
    "sg:address":"1401 S Howe Rd",
    "sg:city":"Spokane",
    "sg:classifiers":[
        {
            "category":"Shopping",
            "subcategory":"Gifts & Souvenirs",
            "type":"Retail Goods"
        }
    ],
    "sg:phone":"+1 509 535 0321",
    "sg:postcode":"99212",
    "sg:province":"WA",
    "wof:name":"Expressions In Giving",
    "wof:placetype":"venue"
},
  "geometry": {"coordinates":[-117.32822299999999,47.643475],"type":"Point"}
}