{
  "type": "Feature",
  "properties": {
    "addr:full":"2625 Colby Ave Everett WA 98201",
    "addr:housenumber":"2625",
    "addr:postcode":"98201",
    "addr:street":"Colby Ave",
    "iso:country":"US",
    "sg:address":"2625 Colby Ave",
    "sg:city":"Everett",
    "sg:classifiers":[
        {
            "category":"Freight",
            "type":"Transportation"
        }
    ],
    "sg:phone":"+1 425 339 6269",
    "sg:postcode":"98201",
    "sg:province":"WA",
    "sg:tags":[
        "shipping",
        "agent"
    ],
    "wof:name":"Everett Pack-Man",
    "wof:placetype":"venue"
},
  "geometry": {"coordinates":[-122.208472,47.982289],"type":"Point"}
}