{
  "type": "Feature",
  "properties": {
    "addr:full":"8211 112th St SW Lakewood WA 98498",
    "addr:housenumber":"8211",
    "addr:postcode":"98498",
    "addr:street":"112Th St Sw",
    "iso:country":"US",
    "sg:address":"8211 112th St SW",
    "sg:city":"Lakewood",
    "sg:classifiers":[
        {
            "category":"Social Services",
            "subcategory":"Child Care",
            "type":"Services"
        }
    ],
    "sg:phone":"+1 253 588 7813",
    "sg:postcode":"98498",
    "sg:province":"WA",
    "sg:tags":[
        "day"
    ],
    "wof:name":"Christ Lutheran Latchkey Center",
    "wof:placetype":"venue"
},
  "geometry": {"coordinates":[-122.546997,47.155701],"type":"Point"}
}