{
  "type": "Feature",
  "properties": {
    "addr:full":"1087 Cedar Ave Marysville WA 98270",
    "addr:housenumber":"1087",
    "addr:postcode":"98270",
    "addr:street":"Cedar Ave",
    "iso:country":"US",
    "sg:address":"1087 Cedar Ave",
    "sg:city":"Marysville",
    "sg:classifiers":[
        {
            "category":"Professional",
            "type":"Services"
        },
        {
            "category":"Personal",
            "type":"Services"
        }
    ],
    "sg:phone":"+1 425 258 1994",
    "sg:postcode":"98270",
    "sg:province":"WA",
    "sg:tags":[
        "mover",
        "material",
        "moving",
        "services-labor"
    ],
    "wof:name":"Barnoli Moving",
    "wof:placetype":"venue"
},
  "geometry": {"coordinates":[-122.180397,48.057589],"type":"Point"}
}