{
  "type": "Feature",
  "properties": {
    "addr:full":"17420 NE Delfel Rd Ridgefield WA 98642",
    "addr:housenumber":"17420",
    "addr:postcode":"98642",
    "addr:street":"Ne Delfel Rd",
    "iso:country":"US",
    "sg:address":"17420 NE Delfel Rd",
    "sg:city":"Ridgefield",
    "sg:classifiers":[
        {
            "category":"Building & Trades",
            "subcategory":"Construction",
            "type":"Services"
        }
    ],
    "sg:phone":"+1 360 573 2171",
    "sg:postcode":"98642",
    "sg:province":"WA",
    "sg:tags":[
        "designer",
        "dealer",
        "pool",
        "swimming"
    ],
    "wof:name":"Reconditioned Spas Unlimited",
    "wof:placetype":"venue"
},
  "geometry": {"coordinates":[-122.66419999999999,45.750285],"type":"Point"}
}