{
  "type": "Feature",
  "properties": {
    "addr:full":"8048 E Mill Plain Blvd Vancouver WA 98664",
    "addr:housenumber":"8048",
    "addr:postcode":"98664",
    "addr:street":"E Mill Plain Blvd",
    "iso:country":"US",
    "sg:address":"8048 E Mill Plain Blvd",
    "sg:city":"Vancouver",
    "sg:classifiers":[
        {
            "category":"Banks & Credit Unions",
            "subcategory":"Bank",
            "type":"Services"
        }
    ],
    "sg:phone":"+1 360 737 7670",
    "sg:postcode":"98664",
    "sg:province":"WA",
    "sg:tags":[
        "personal",
        "institution"
    ],
    "wof:name":"Advance America",
    "wof:placetype":"venue"
},
  "geometry": {"coordinates":[-122.590363,45.624437],"type":"Point"}
}