{
  "type": "Feature",
  "properties": {
    "addr:full":"7728 NE Hazel Dell Ave Vancouver WA 98665",
    "addr:housenumber":"7728",
    "addr:postcode":"98665",
    "addr:street":"Ne Hazel Dell Ave",
    "iso:country":"US",
    "sg:address":"7728 NE Hazel Dell Ave",
    "sg:city":"Vancouver",
    "sg:classifiers":[
        {
            "category":"Organizations",
            "subcategory":"Labor Organization",
            "type":"Services"
        }
    ],
    "sg:phone":"+1 360 696 9859",
    "sg:postcode":"98665",
    "sg:province":"WA",
    "wof:name":"United Paperworkers Intl Un",
    "wof:placetype":"venue"
},
  "geometry": {"coordinates":[-122.66893399999999,45.677898],"type":"Point"}
}