{
  "type": "Feature",
  "properties": {
    "addr:full":"11602 SE 225th St Kent WA 98031",
    "addr:postcode":"11602;98031",
    "addr:street":"Se 225Th St",
    "iso:country":"US",
    "sg:address":"11602 SE 225th St",
    "sg:city":"Kent",
    "sg:classifiers":[
        {
            "category":"Professional",
            "type":"Services"
        }
    ],
    "sg:phone":"+1 253 630 6520",
    "sg:postcode":"98031",
    "sg:province":"WA",
    "wof:name":"Stephan T Smith",
    "wof:placetype":"venue"
},
  "geometry": {"coordinates":[-122.186061,47.400976],"type":"Point"}
}