{
  "type": "Feature",
  "properties": {
    "addr:full":"5212 37th Ave SW Seattle WA 98126",
    "addr:housenumber":"5212",
    "addr:postcode":"98126",
    "addr:street":"37Th Ave Sw",
    "iso:country":"US",
    "sg:address":"5212 37th Ave SW",
    "sg:city":"Seattle",
    "sg:classifiers":[
        {
            "category":"Building & Trades",
            "subcategory":"Landscaping Services",
            "type":"Services"
        }
    ],
    "sg:phone":"+1 206 923 3507",
    "sg:postcode":"98126",
    "sg:province":"WA",
    "sg:tags":[
        "landscape"
    ],
    "wof:name":"Terraforma Design Group",
    "wof:placetype":"venue"
},
  "geometry": {"coordinates":[-122.378872,47.554379],"type":"Point"}
}