{
  "type": "Feature",
  "properties": {
    "addr:full":"17280 Hallman Rd NW Poulsbo WA 98370",
    "addr:housenumber":"17280",
    "addr:postcode":"98370",
    "addr:street":"Hallman Rd Nw",
    "iso:country":"US",
    "sg:address":"17280 Hallman Rd NW",
    "sg:city":"Poulsbo",
    "sg:classifiers":[
        {
            "category":"Building & Trades",
            "subcategory":"Plumbing",
            "type":"Services"
        }
    ],
    "sg:phone":"+1 360 779 5233",
    "sg:postcode":"98370",
    "sg:province":"WA",
    "sg:tags":[
        "septic"
    ],
    "wof:name":"Indigo Design Inc",
    "wof:placetype":"venue"
},
  "geometry": {"coordinates":[-122.66014,47.716534],"type":"Point"}
}