{
  "type": "Feature",
  "properties": {
    "addr:full":"4928 W Mason Rd Deer Park WA 99006",
    "addr:housenumber":"4928",
    "addr:postcode":"99006",
    "addr:street":"W Mason Rd",
    "iso:country":"US",
    "sg:address":"4928 W Mason Rd",
    "sg:city":"Deer Park",
    "sg:classifiers":[
        {
            "category":"Building & Trades",
            "subcategory":"Electrical",
            "type":"Services"
        }
    ],
    "sg:phone":"+1 509 276 8246",
    "sg:postcode":"99006",
    "sg:province":"WA",
    "sg:tags":[
        "electrical",
        "contractor"
    ],
    "wof:name":"Kajun Electric",
    "wof:placetype":"venue"
},
  "geometry": {"coordinates":[-117.500874,48.003963],"type":"Point"}
}