{
  "type": "Feature",
  "properties": {
    "addr:full":"4516 S Regal St Spokane WA 99223",
    "addr:housenumber":"4516",
    "addr:postcode":"99223",
    "addr:street":"S Regal St",
    "iso:country":"US",
    "sg:address":"4516 S Regal St",
    "sg:city":"Spokane",
    "sg:classifiers":[
        {
            "category":"Restaurant",
            "type":"Food & Drink"
        }
    ],
    "sg:phone":"+1 509 443 6304",
    "sg:postcode":"99223",
    "sg:province":"WA",
    "wof:name":"Ferrante's Cafe & Shop",
    "wof:placetype":"venue"
},
  "geometry": {"coordinates":[-117.368246,47.611518],"type":"Point"}
}