{
  "type": "Feature",
  "properties": {
    "addr:full":"72 S Washington St Seattle WA 98104",
    "addr:housenumber":"72",
    "addr:postcode":"98104",
    "addr:street":"S Washington St",
    "iso:country":"US",
    "sg:address":"72 S Washington St",
    "sg:city":"Seattle",
    "sg:classifiers":[
        {
            "category":"Building & Trades",
            "subcategory":"Locksmith",
            "type":"Services"
        }
    ],
    "sg:phone":"+1 206 774 2893",
    "sg:postcode":"98104",
    "sg:province":"WA",
    "sg:tags":[
        "key"
    ],
    "wof:name":"24 Hour A Day Locksmith On Washington",
    "wof:placetype":"venue"
},
  "geometry": {"coordinates":[-122.334596,47.601013],"type":"Point"}
}