{
  "type": "Feature",
  "properties": {
    "addr:full":"37231 1st Ave SW Federal Way WA 98023",
    "addr:housenumber":"37231",
    "addr:postcode":"98023",
    "addr:street":"1St Ave Sw Federal Way",
    "iso:country":"US",
    "sg:address":"37231 1st Ave SW",
    "sg:city":"Federal Way",
    "sg:classifiers":[
        {
            "category":"Building & Trades",
            "subcategory":"Construction",
            "type":"Services"
        }
    ],
    "sg:phone":"+1 253 835 4535",
    "sg:postcode":"98023",
    "sg:province":"WA",
    "sg:tags":[
        "house"
    ],
    "wof:name":"Anatoliy Construction",
    "wof:placetype":"venue"
},
  "geometry": {"coordinates":[-122.336253,47.266694],"type":"Point"}
}