{
  "type": "Feature",
  "properties": {
    "addr:full":"1408 W Yakima Ave Yakima WA 98902",
    "addr:housenumber":"1408",
    "addr:postcode":"98902",
    "addr:street":"W Yakima Ave",
    "iso:country":"US",
    "sg:address":"1408 W Yakima Ave",
    "sg:city":"Yakima",
    "sg:classifiers":[
        {
            "category":"Organizations",
            "subcategory":"Non-profit Organization",
            "type":"Services"
        }
    ],
    "sg:phone":"+1 509 248 1800",
    "sg:postcode":"98902",
    "sg:province":"WA",
    "sg:tags":[
        "information",
        "alcoholism",
        "treatment"
    ],
    "wof:name":"Riel House",
    "wof:placetype":"venue"
},
  "geometry": {"coordinates":[-120.527501,46.597147],"type":"Point"}
}