{
  "type": "Feature",
  "properties": {
    "addr:full":"12818 Ambaum Blvd SW Burien WA 98146",
    "addr:housenumber":"12818",
    "addr:postcode":"98146",
    "addr:street":"Ambaum Blvd Sw",
    "iso:country":"US",
    "sg:address":"12818 Ambaum Blvd SW",
    "sg:city":"Burien",
    "sg:classifiers":[
        {
            "category":"Cinema",
            "subcategory":"Movie Rental",
            "type":"Entertainment"
        }
    ],
    "sg:phone":"+1 206 431 1020",
    "sg:postcode":"98146",
    "sg:province":"WA",
    "sg:tags":[
        "tape",
        "game",
        "video"
    ],
    "wof:name":"King Video",
    "wof:placetype":"venue"
},
  "geometry": {"coordinates":[-122.350033,47.487911],"type":"Point"}
}