{
  "type": "Feature",
  "properties": {
    "addr:full":"2310 Main St Vancouver WA 98660",
    "addr:housenumber":"2310",
    "addr:postcode":"98660",
    "addr:street":"Main St",
    "iso:country":"US",
    "sg:address":"2310 Main St",
    "sg:city":"Vancouver",
    "sg:classifiers":[
        {
            "category":"Shopping",
            "subcategory":"Bicycles & Sporting Goods",
            "type":"Retail Goods"
        }
    ],
    "sg:phone":"+1 360 906 0209",
    "sg:postcode":"98660",
    "sg:province":"WA",
    "sg:tags":[
        "repair"
    ],
    "wof:name":"Mike's Bikes",
    "wof:placetype":"venue"
},
  "geometry": {"coordinates":[-122.671499,45.638675],"type":"Point"}
}