{
  "type": "Feature",
  "properties": {
    "addr:full":"1429 1st St SE East Wenatchee WA 98802",
    "addr:housenumber":"1429",
    "addr:postcode":"98802",
    "addr:street":"1St St Se",
    "iso:country":"US",
    "sg:address":"1429 1st St SE",
    "sg:city":"East Wenatchee",
    "sg:classifiers":[
        {
            "category":"Education",
            "subcategory":"School",
            "type":"Public Place"
        }
    ],
    "sg:phone":"+1 509 662 5001",
    "sg:postcode":"98802",
    "sg:province":"WA",
    "wof:name":"Wenatchee Christian Academy",
    "wof:placetype":"venue"
},
  "geometry": {"coordinates":[-120.26510399999999,47.40411],"type":"Point"}
}