{
  "type": "Feature",
  "properties": {
    "addr:full":"12884 Silverdale Way NW Silverdale WA 98383",
    "addr:housenumber":"12884",
    "addr:postcode":"98383",
    "addr:street":"Silverdale Way Nw",
    "iso:country":"US",
    "sg:address":"12884 Silverdale Way NW",
    "sg:city":"Silverdale",
    "sg:classifiers":[
        {
            "category":"Arts & Performance",
            "subcategory":"Theater",
            "type":"Entertainment"
        }
    ],
    "sg:phone":"+1 360 692 1008",
    "sg:postcode":"98383",
    "sg:province":"WA",
    "sg:tags":[
        "clown"
    ],
    "wof:name":"Clown Capers",
    "wof:placetype":"venue"
},
  "geometry": {"coordinates":[-122.674723,47.678729],"type":"Point"}
}