{
  "type": "Feature",
  "properties": {
    "addr:full":"1016 1st Ave S Seattle WA 98134",
    "addr:housenumber":"1016",
    "addr:postcode":"98134",
    "addr:street":"1St Ave S",
    "iso:country":"US",
    "sg:address":"1016 1st Ave S",
    "sg:city":"Seattle",
    "sg:classifiers":[
        {
            "category":"Wholesale",
            "subcategory":"Medical Equipment & Supplies",
            "type":"Manufacturing & Wholesale Goods"
        }
    ],
    "sg:phone":"+1 206 622 6939",
    "sg:postcode":"98134",
    "sg:province":"WA",
    "sg:tags":[
        "optical"
    ],
    "wof:name":"Flipper Enterprises",
    "wof:placetype":"venue"
},
  "geometry": {"coordinates":[-122.33412,47.593625],"type":"Point"}
}