{
  "type": "Feature",
  "properties": {
    "addr:full":"116 N 1st St Sunnyside WA 98944",
    "addr:housenumber":"116",
    "addr:postcode":"98944",
    "addr:street":"N 1St St",
    "iso:country":"US",
    "sg:address":"116 N 1st St",
    "sg:city":"Sunnyside",
    "sg:phone":"+1 509 837 8280",
    "sg:postcode":"98944",
    "sg:province":"WA",
    "sg:tags":[
        "scale"
    ],
    "wof:name":"Bee-Jay Scales Inc",
    "wof:placetype":"venue"
},
  "geometry": {"coordinates":[-120.019949,46.330867],"type":"Point"}
}