{
  "type": "Feature",
  "properties": {
    "addr:full":"949 Wildwood Rd Curtis WA 98538",
    "addr:housenumber":"949",
    "addr:postcode":"98538",
    "addr:street":"Wildwood Rd",
    "iso:country":"US",
    "sg:address":"949 Wildwood Rd",
    "sg:city":"Curtis",
    "sg:classifiers":[
        {
            "category":"Professional",
            "subcategory":"Business Services",
            "type":"Services"
        }
    ],
    "sg:phone":"+1 360 245 3400",
    "sg:postcode":"98538",
    "sg:province":"WA",
    "wof:name":"Norseman Owners Fv Watso",
    "wof:placetype":"venue"
},
  "geometry": {"coordinates":[-123.083732,46.446489],"type":"Point"}
}