{
  "type": "Feature",
  "properties": {
    "addr:full":"4630 16th St E Fife WA 98424",
    "addr:housenumber":"4630",
    "addr:postcode":"98424",
    "addr:street":"16Th St E",
    "iso:country":"US",
    "sg:address":"4630 16th St E",
    "sg:city":"Fife",
    "sg:classifiers":[
        {
            "category":"Organizations",
            "subcategory":"Non-profit Organization",
            "type":"Services"
        }
    ],
    "sg:phone":"+1 253 922 5650",
    "sg:postcode":"98424",
    "sg:province":"WA",
    "sg:website":"www.veteransworkshop.org",
    "wof:name":"Veterans Independent Ents",
    "wof:placetype":"venue"
},
  "geometry": {"coordinates":[-122.3669,47.242586],"type":"Point"}
}