{
  "type": "Feature",
  "properties": {
    "addr:full":"19613 81st Ave S Kent WA 98032",
    "addr:housenumber":"19613",
    "addr:postcode":"98032",
    "addr:street":"81St Ave S",
    "iso:country":"US",
    "sg:address":"19613 81st Ave S",
    "sg:city":"Kent",
    "sg:classifiers":[
        {
            "category":"Wholesale",
            "subcategory":"Machinery & Supplies",
            "type":"Manufacturing & Wholesale Goods"
        }
    ],
    "sg:phone":"+1 253 872 7689",
    "sg:postcode":"98032",
    "sg:province":"WA",
    "sg:tags":[
        "equipment",
        "aircraft",
        "transportation",
        "mfg"
    ],
    "wof:name":"Behrco Tool & Machine",
    "wof:placetype":"venue"
},
  "geometry": {"coordinates":[-122.231295,47.425754],"type":"Point"}
}