{
  "type": "Feature",
  "properties": {
    "iso:country":"US",
    "sg:address":"703 N Homestead Dr",
    "sg:city":"Liberty Lake",
    "sg:classifiers":[
        {
            "category":"Professional",
            "type":"Services"
        }
    ],
    "sg:phone":"+1 509 255 9979",
    "sg:postcode":"99019",
    "sg:province":"WA",
    "wof:name":"Neverstop Computing Inc",
    "wof:placetype":"venue"
},
  "geometry": {"coordinates":[-117.09628600000001,47.662033],"type":"Point"}
}