{
  "type": "Feature",
  "properties": {
    "addr:full":"217 8th St Leavenworth WA 98826",
    "addr:housenumber":"217",
    "addr:postcode":"98826",
    "addr:street":"8Th St",
    "iso:country":"US",
    "sg:address":"217 8th St",
    "sg:city":"Leavenworth",
    "sg:classifiers":[
        {
            "category":"Restaurant",
            "type":"Food & Drink"
        }
    ],
    "sg:phone":"+1 509 548 5226",
    "sg:postcode":"98826",
    "sg:province":"WA",
    "sg:tags":[
        "eating"
    ],
    "wof:name":"Scandia Restaurant",
    "wof:placetype":"venue"
},
  "geometry": {"coordinates":[-120.66229,47.594878],"type":"Point"}
}