{
  "type": "Feature",
  "properties": {
    "addr:full":"11416 Rainier Ave Seattle WA 98178",
    "addr:housenumber":"11416",
    "addr:postcode":"98178",
    "addr:street":"Rainier Ave",
    "iso:country":"US",
    "sg:address":"11416 Rainier Ave",
    "sg:city":"Seattle",
    "sg:classifiers":[
        {
            "category":"Education",
            "subcategory":"School",
            "type":"Public Place"
        }
    ],
    "sg:phone":"+1 206 772 5300",
    "sg:postcode":"98178",
    "sg:province":"WA",
    "wof:name":"Intermed",
    "wof:placetype":"venue"
},
  "geometry": {"coordinates":[-122.22174699999999,47.501102],"type":"Point"}
}