{
  "type": "Feature",
  "properties": {
    "iso:country":"US",
    "sg:address":"1112 16th St NE",
    "sg:city":"Auburn",
    "sg:classifiers":[
        {
            "category":"Shopping",
            "subcategory":"Clothing, Apparel, & Fashions",
            "type":"Retail Goods"
        }
    ],
    "sg:phone":"+1 253 833 8743",
    "sg:postcode":"98002",
    "sg:province":"WA",
    "wof:name":"Abrahams Property Service",
    "wof:placetype":"venue"
},
  "geometry": {"coordinates":[-122.21585899999999,47.322181],"type":"Point"}
}