{
  "type": "Feature",
  "properties": {
    "addr:full":"8009 26th Ave NW Seattle WA 98117",
    "addr:housenumber":"8009",
    "addr:postcode":"98117",
    "addr:street":"26Th Ave Nw",
    "iso:country":"US",
    "sg:address":"8009 26th Ave NW",
    "sg:city":"Seattle",
    "sg:classifiers":[
        {
            "category":"Professional",
            "subcategory":"Art Services",
            "type":"Services"
        }
    ],
    "sg:phone":"+1 206 781 5237",
    "sg:postcode":"98117",
    "sg:province":"WA",
    "sg:tags":[
        "commercial",
        "design"
    ],
    "wof:name":"C M Squared",
    "wof:placetype":"venue"
},
  "geometry": {"coordinates":[-122.38986800000001,47.688941],"type":"Point"}
}