{
  "type": "Feature",
  "properties": {
    "addr:full":"12204 8th Dr SE Everett WA 98208",
    "addr:housenumber":"12204",
    "addr:postcode":"98208",
    "addr:street":"8Th Dr Se",
    "iso:country":"US",
    "sg:address":"12204 8th Dr SE",
    "sg:city":"Everett",
    "sg:classifiers":[
        {
            "category":"Building & Trades",
            "subcategory":"Construction",
            "type":"Services"
        }
    ],
    "sg:phone":"+1 425 787 2635",
    "sg:postcode":"98208",
    "sg:province":"WA",
    "sg:tags":[
        "painter"
    ],
    "wof:name":"Steve VB Painting",
    "wof:placetype":"venue"
},
  "geometry": {"coordinates":[-122.221008,47.884247],"type":"Point"}
}