{
  "type": "Feature",
  "properties": {
    "addr:full":"1720 NE 64th Ave Vancouver WA 98661",
    "addr:housenumber":"1720",
    "addr:postcode":"98661",
    "addr:street":"Ne 64Th Ave",
    "iso:country":"US",
    "sg:address":"1720 NE 64th Ave",
    "sg:city":"Vancouver",
    "sg:classifiers":[
        {
            "category":"Home & Garden",
            "subcategory":"Household Appliances",
            "type":"Retail Goods"
        },
        {
            "category":"Building & Trades",
            "subcategory":"Construction",
            "type":"Services"
        }
    ],
    "sg:phone":"+1 360 693 1757",
    "sg:postcode":"98661",
    "sg:province":"WA",
    "sg:tags":[
        "repair",
        "air",
        "heating",
        "conditioning/hvac",
        "contractor"
    ],
    "sg:website":"www.advancedairsystems.net",
    "wof:name":"Advanced Air Systems Inc.",
    "wof:placetype":"venue"
},
  "geometry": {"coordinates":[-122.606576,45.657581],"type":"Point"}
}