{
  "type": "Feature",
  "properties": {
    "addr:full":"205 S Adams St Ritzville WA 99169",
    "addr:housenumber":"205",
    "addr:postcode":"99169",
    "addr:street":"S Adams St",
    "iso:country":"US",
    "sg:address":"205 S Adams St",
    "sg:city":"Ritzville",
    "sg:classifiers":[
        {
            "category":"Retail",
            "subcategory":"Portrait Studio",
            "type":"Services"
        }
    ],
    "sg:phone":"+1 509 659 1509",
    "sg:postcode":"99169",
    "sg:province":"WA",
    "sg:tags":[
        "photo"
    ],
    "wof:name":"C Meye Photos",
    "wof:placetype":"venue"
},
  "geometry": {"coordinates":[-118.378449,47.124527],"type":"Point"}
}