{
  "type": "Feature",
  "properties": {
    "iso:country":"US",
    "sg:address":"1400 112th Ave SE",
    "sg:city":"Bellevue",
    "sg:classifiers":[
        {
            "category":"Real Estate",
            "subcategory":"Real Estate Agent",
            "type":"Services"
        }
    ],
    "sg:phone":"+1 425 454 3627",
    "sg:postcode":"98004",
    "sg:province":"WA",
    "wof:name":"Westmark Properties Inc",
    "wof:placetype":"venue"
},
  "geometry": {"coordinates":[-122.19070000000001,47.599843],"type":"Point"}
}