{
  "type": "Feature",
  "properties": {
    "addr:full":"6002 32nd Ave NW Seattle WA 98107",
    "addr:housenumber":"6002",
    "addr:postcode":"98107",
    "addr:street":"32Nd Ave Nw",
    "iso:country":"US",
    "sg:address":"6002 32nd Ave NW",
    "sg:city":"Seattle",
    "sg:classifiers":[
        {
            "category":"Personal",
            "type":"Services"
        }
    ],
    "sg:phone":"+1 206 610 3271",
    "sg:postcode":"98107",
    "sg:province":"WA",
    "wof:name":"Its Your Body",
    "wof:placetype":"venue"
},
  "geometry": {"coordinates":[-122.398285,47.672499],"type":"Point"}
}