{
  "type": "Feature",
  "properties": {
    "addr:full":"1620 S 341st Pl Federal Way WA 98003",
    "addr:housenumber":"1620",
    "addr:postcode":"98003",
    "addr:street":"S 341St Pl",
    "iso:country":"US",
    "sg:address":"1620 S 341st Pl",
    "sg:city":"Federal Way",
    "sg:classifiers":[
        {
            "category":"Wholesale",
            "subcategory":"Auto Parts",
            "type":"Manufacturing & Wholesale Goods"
        }
    ],
    "sg:phone":"+1 253 874 8290",
    "sg:postcode":"98003",
    "sg:province":"WA",
    "sg:tags":[
        "used",
        "supply"
    ],
    "wof:name":"Ovals Motorsport Inc",
    "wof:placetype":"venue"
},
  "geometry": {"coordinates":[-122.310687,47.295778],"type":"Point"}
}