{
  "type": "Feature",
  "properties": {
    "addr:full":"33019 37th Ave NE Arlington WA 98223",
    "addr:housenumber":"33019",
    "addr:postcode":"98223",
    "addr:street":"37Th Ave Ne",
    "iso:country":"US",
    "sg:address":"33019 37th Ave NE",
    "sg:city":"Arlington",
    "sg:classifiers":[
        {
            "category":"Professional",
            "subcategory":"Management & Consulting",
            "type":"Services"
        }
    ],
    "sg:phone":"+1 360 474 1664",
    "sg:postcode":"98223",
    "sg:province":"WA",
    "wof:name":"Rino International",
    "wof:placetype":"venue"
},
  "geometry": {"coordinates":[-122.17975800000001,48.295234],"type":"Point"}
}