{
  "type": "Feature",
  "properties": {
    "addr:full":"22301 E Calumet Rd Rockford WA 99030",
    "addr:housenumber":"22301",
    "addr:postcode":"99030",
    "addr:street":"E Calumet Rd",
    "iso:country":"US",
    "sg:address":"22301 E Calumet Rd",
    "sg:city":"Rockford",
    "sg:phone":"+1 509 291 5875",
    "sg:postcode":"99030",
    "sg:province":"WA",
    "sg:tags":[
        "wheat",
        "farm",
        "cash",
        "crop",
        "field",
        "grain"
    ],
    "wof:name":"Rodney Jacot",
    "wof:placetype":"venue"
},
  "geometry": {"coordinates":[-117.10522400000001,47.419907],"type":"Point"}
}