{
  "type": "Feature",
  "properties": {
    "addr:full":"11516 E Sprague Ave Spokane Valley WA 99206",
    "addr:housenumber":"11516",
    "addr:postcode":"99206",
    "addr:street":"E Sprague Ave",
    "iso:country":"US",
    "sg:address":"11516 E Sprague Ave",
    "sg:city":"Spokane Valley",
    "sg:classifiers":[
        {
            "category":"Restaurant",
            "type":"Food & Drink"
        }
    ],
    "sg:phone":"+1 509 928 8893",
    "sg:postcode":"99206",
    "sg:province":"WA",
    "sg:tags":[
        "eating"
    ],
    "wof:name":"Teriyaki House",
    "wof:placetype":"venue"
},
  "geometry": {"coordinates":[-117.246708,47.656982],"type":"Point"}
}