{
  "type": "Feature",
  "properties": {
    "iso:country":"US",
    "sg:address":"601 108th Ave NE",
    "sg:city":"Bellevue",
    "sg:classifiers":[
        {
            "category":"Manufacturing",
            "subcategory":"Electronics",
            "type":"Manufacturing & Wholesale Goods"
        }
    ],
    "sg:phone":"+1 425 943 6140",
    "sg:postcode":"98004",
    "sg:province":"WA",
    "sg:tags":[
        "communication",
        "satellite"
    ],
    "wof:name":"Sars",
    "wof:placetype":"venue"
},
  "geometry": {"coordinates":[-122.196335,47.617405],"type":"Point"}
}