{
  "type": "Feature",
  "properties": {
    "addr:full":"51 Bedrock Rd Beaver WA 98305",
    "addr:housenumber":"51",
    "addr:postcode":"98305",
    "addr:street":"Bedrock Rd",
    "iso:country":"US",
    "sg:address":"51 Bedrock Rd",
    "sg:city":"Beaver",
    "sg:classifiers":[
        {
            "category":"Government",
            "subcategory":"Office",
            "type":"Public Place"
        }
    ],
    "sg:phone":"+1 360 374 5513",
    "sg:postcode":"98305",
    "sg:province":"WA",
    "wof:name":"Clallam County Road Dist",
    "wof:placetype":"venue"
},
  "geometry": {"coordinates":[-124.377754,48.041574],"type":"Point"}
}