{
  "type": "Feature",
  "properties": {
    "addr:full":"3211 Beacon Ave S Seattle WA 98144",
    "addr:housenumber":"3211",
    "addr:postcode":"98144",
    "addr:street":"Beacon Ave S",
    "iso:country":"US",
    "sg:address":"3211 Beacon Ave S",
    "sg:city":"Seattle",
    "sg:classifiers":[
        {
            "category":"Building & Trades",
            "subcategory":"Locksmith",
            "type":"Services"
        }
    ],
    "sg:phone":"+1 425 207 3332",
    "sg:postcode":"98144",
    "sg:province":"WA",
    "sg:tags":[
        "key"
    ],
    "wof:name":"A One Locksmith Service",
    "wof:placetype":"venue"
},
  "geometry": {"coordinates":[-122.309228,47.574463],"type":"Point"}
}