{
  "type": "Feature",
  "properties": {
    "addr:full":"5270 University Way NE Seattle WA 98105",
    "addr:housenumber":"5270",
    "addr:postcode":"98105",
    "addr:street":"University Way Ne",
    "iso:country":"US",
    "sg:address":"5270 University Way NE",
    "sg:city":"Seattle",
    "sg:classifiers":[
        {
            "category":"Autos & Motor Vehicles",
            "subcategory":"Auto Supplies",
            "type":"Retail Goods"
        }
    ],
    "sg:phone":"+1 206 898 2959",
    "sg:postcode":"98105",
    "sg:province":"WA",
    "wof:name":"Twincam Motoring",
    "wof:placetype":"venue"
},
  "geometry": {"coordinates":[-122.31295,47.668026],"type":"Point"}
}