{
  "type": "Feature",
  "properties": {
    "addr:full":"65 Shumway Rd Omak WA 98841",
    "addr:housenumber":"65",
    "addr:postcode":"98841",
    "addr:street":"Shumway Rd",
    "iso:country":"US",
    "sg:address":"65 Shumway Rd",
    "sg:city":"Omak",
    "sg:classifiers":[
        {
            "category":"Retail",
            "subcategory":"Car Wash",
            "type":"Services"
        }
    ],
    "sg:phone":"+1 509 826 4623",
    "sg:postcode":"98841",
    "sg:province":"WA",
    "sg:tags":[
        "carwash"
    ],
    "wof:name":"TLC Auto Detailing",
    "wof:placetype":"venue"
},
  "geometry": {"coordinates":[-119.522103,48.424133],"type":"Point"}
}