{
  "type": "Feature",
  "properties": {
    "addr:full":"13826 Glenwood Rd SW Port Orchard WA 98367",
    "addr:housenumber":"13826",
    "addr:postcode":"98367",
    "addr:street":"Glenwood Rd Sw Port Orchard",
    "iso:country":"US",
    "sg:address":"13826 Glenwood Rd SW",
    "sg:city":"Port Orchard",
    "sg:classifiers":[
        {
            "category":"Freight",
            "type":"Transportation"
        }
    ],
    "sg:phone":"+1 360 876 2671",
    "sg:postcode":"98367",
    "sg:province":"WA",
    "sg:tags":[
        "operator",
        "local",
        "trucking"
    ],
    "wof:name":"Martin Antone Morin III",
    "wof:placetype":"venue"
},
  "geometry": {"coordinates":[-122.690146,47.422748],"type":"Point"}
}