{
  "type": "Feature",
  "properties": {
    "addr:full":"1027 Aladdin Rd Colville WA 99114",
    "addr:housenumber":"1027",
    "addr:postcode":"99114",
    "addr:street":"Aladdin Rd",
    "iso:country":"US",
    "sg:address":"1027 Aladdin Rd",
    "sg:city":"Colville",
    "sg:classifiers":[
        {
            "category":"Retail",
            "subcategory":"Auto Repair",
            "type":"Services"
        }
    ],
    "sg:phone":"+1 509 684 5309",
    "sg:postcode":"99114",
    "sg:province":"WA",
    "sg:tags":[
        "body",
        "automobile",
        "painting",
        "repairing"
    ],
    "wof:name":"Entwistle Automotive",
    "wof:placetype":"venue"
},
  "geometry": {"coordinates":[-117.65942800000001,48.7675],"type":"Point"}
}