{
  "type": "Feature",
  "properties": {
    "addr:full":"120 S 5th Ave Pasco WA 99301",
    "addr:housenumber":"120",
    "addr:postcode":"99301",
    "addr:street":"S 5Th Ave",
    "iso:country":"US",
    "sg:address":"120 S 5th Ave",
    "sg:city":"Pasco",
    "sg:classifiers":[
        {
            "category":"Travel",
            "subcategory":"Travel Agent",
            "type":"Entertainment"
        }
    ],
    "sg:phone":"+1 509 544 9205",
    "sg:postcode":"99301",
    "sg:province":"WA",
    "sg:tags":[
        "agency",
        "bureau"
    ],
    "wof:name":"Resplusnet LLC",
    "wof:placetype":"venue"
},
  "geometry": {"coordinates":[-119.093681,46.229258],"type":"Point"}
}