{
  "type": "Feature",
  "properties": {
    "addr:full":"9999 Holman Rd NW Seattle WA 98117",
    "addr:housenumber":"9999",
    "addr:postcode":"98117",
    "addr:street":"Holman Rd Nw",
    "iso:country":"US",
    "sg:address":"9999 Holman Rd NW",
    "sg:city":"Seattle",
    "sg:classifiers":[
        {
            "category":"Coffee & Tea",
            "type":"Food & Drink"
        }
    ],
    "sg:phone":"+1 206 783 8104",
    "sg:postcode":"98117",
    "sg:province":"WA",
    "wof:name":"Starbucks",
    "wof:placetype":"venue"
},
  "geometry": {"coordinates":[-122.363693,47.701923],"type":"Point"}
}