{
  "type": "Feature",
  "properties": {
    "addr:full":"10105 N Larchwood St Spokane WA 99208",
    "addr:housenumber":"10105",
    "addr:postcode":"99208",
    "addr:street":"N Larchwood St",
    "iso:country":"US",
    "sg:address":"10105 N Larchwood St",
    "sg:city":"Spokane",
    "sg:classifiers":[
        {
            "category":"Manufacturing",
            "subcategory":"Toys & Sporting Goods",
            "type":"Manufacturing & Wholesale Goods"
        }
    ],
    "sg:phone":"+1 509 467 8633",
    "sg:postcode":"99208",
    "sg:province":"WA",
    "sg:tags":[
        "mfg"
    ],
    "wof:name":"Snowflakes & Halos & More",
    "wof:placetype":"venue"
},
  "geometry": {"coordinates":[-117.48214400000001,47.75001],"type":"Point"}
}