{
  "type": "Feature",
  "properties": {
    "addr:full":"524 W Whidbey Ave Oak Harbor WA 98277",
    "addr:housenumber":"524",
    "addr:postcode":"98277",
    "addr:street":"W Whidbey Ave",
    "iso:country":"US",
    "sg:address":"524 W Whidbey Ave",
    "sg:city":"Oak Harbor",
    "sg:classifiers":[
        {
            "category":"Retail",
            "subcategory":"Portrait Studio",
            "type":"Services"
        }
    ],
    "sg:phone":"+1 360 279 2692",
    "sg:postcode":"98277",
    "sg:province":"WA",
    "sg:tags":[
        "photo"
    ],
    "wof:name":"Wilson Photograpy",
    "wof:placetype":"venue"
},
  "geometry": {"coordinates":[-122.664282,48.298609],"type":"Point"}
}