{
  "type": "Feature",
  "properties": {
    "addr:full":"7615 NE 154th Ave Vancouver WA 98682",
    "addr:housenumber":"7615",
    "addr:postcode":"98682",
    "addr:street":"Ne 154Th Ave",
    "iso:country":"US",
    "sg:address":"7615 NE 154th Ave",
    "sg:city":"Vancouver",
    "sg:classifiers":[
        {
            "category":"Building & Trades",
            "subcategory":"Cleaning & Sanitation",
            "type":"Services"
        }
    ],
    "sg:phone":"+1 360 891 0855",
    "sg:postcode":"98682",
    "sg:province":"WA",
    "sg:tags":[
        "maintenance"
    ],
    "wof:name":"Quality Cleaning",
    "wof:placetype":"venue"
},
  "geometry": {"coordinates":[-122.51359600000001,45.677213],"type":"Point"}
}