{
  "type": "Feature",
  "properties": {
    "addr:full":"1127 Pine St Seattle WA 98101",
    "addr:housenumber":"1127",
    "addr:postcode":"98101",
    "addr:street":"Pine St",
    "iso:country":"US",
    "sg:address":"1127 Pine St",
    "sg:city":"Seattle",
    "sg:classifiers":[
        {
            "category":"Travel",
            "subcategory":"Travel Agent",
            "type":"Entertainment"
        }
    ],
    "sg:phone":"+1 206 628 8687",
    "sg:postcode":"98101",
    "sg:province":"WA",
    "sg:tags":[
        "agency"
    ],
    "wof:name":"Escape Tours",
    "wof:placetype":"venue"
},
  "geometry": {"coordinates":[-122.329367,47.614535],"type":"Point"}
}