{
  "type": "Feature",
  "properties": {
    "addr:full":"23309 Wax Orchard Rd SW Vashon WA 98070",
    "addr:housenumber":"23309",
    "addr:postcode":"98070",
    "addr:street":"Wax Orchard Rd Sw",
    "iso:country":"US",
    "sg:address":"23309 Wax Orchard Rd SW",
    "sg:city":"Vashon",
    "sg:classifiers":[
        {
            "category":"Retail",
            "subcategory":"Animal Services",
            "type":"Services"
        }
    ],
    "sg:phone":"+1 206 463 2607",
    "sg:postcode":"98070",
    "sg:province":"WA",
    "wof:name":"Lazy R Ranch",
    "wof:placetype":"venue"
},
  "geometry": {"coordinates":[-122.503208,47.403665],"type":"Point"}
}