{
  "type": "Feature",
  "properties": {
    "addr:full":"4044 Auburn Way N Auburn WA 98002",
    "addr:housenumber":"4044",
    "addr:postcode":"98002",
    "addr:street":"Auburn Way N",
    "iso:country":"US",
    "sg:address":"4044 Auburn Way N",
    "sg:city":"Auburn",
    "sg:classifiers":[
        {
            "category":"Retail",
            "subcategory":"Auto Repair",
            "type":"Services"
        }
    ],
    "sg:phone":"+1 253 850 1570",
    "sg:postcode":"98002",
    "sg:province":"WA",
    "sg:tags":[
        "automotive",
        "general",
        "sup"
    ],
    "wof:name":"Ewing Engine Service",
    "wof:placetype":"venue"
},
  "geometry": {"coordinates":[-122.222229,47.343598],"type":"Point"}
}