{
  "type": "Feature",
  "properties": {
    "addr:full":"17124 Redmond Way Redmond WA 98052",
    "addr:housenumber":"17124",
    "addr:postcode":"98052",
    "addr:street":"Redmond Way",
    "iso:country":"US",
    "sg:address":"17124 Redmond Way",
    "sg:city":"Redmond",
    "sg:classifiers":[
        {
            "category":"Shopping",
            "type":"Retail Goods"
        }
    ],
    "sg:phone":"+1 425 881 6539",
    "sg:postcode":"98052",
    "sg:province":"WA",
    "sg:tags":[
        "merchandise"
    ],
    "wof:name":"Petco 239",
    "wof:placetype":"venue"
},
  "geometry": {"coordinates":[-122.112245,47.671215],"type":"Point"}
}