{
  "type": "Feature",
  "properties": {
    "addr:full":"201 N 3rd Ave Pasco WA 99301",
    "addr:housenumber":"201",
    "addr:postcode":"99301",
    "addr:street":"N 3Rd Ave",
    "iso:country":"US",
    "sg:address":"201 N 3rd Ave",
    "sg:city":"Pasco",
    "sg:classifiers":[
        {
            "category":"Food & Beverages",
            "subcategory":"Meat & Fish",
            "type":"Retail Goods"
        }
    ],
    "sg:phone":"+1 509 543 4125",
    "sg:postcode":"99301",
    "sg:province":"WA",
    "sg:tags":[
        "shop"
    ],
    "wof:name":"Sammy's Meat Market",
    "wof:placetype":"venue"
},
  "geometry": {"coordinates":[-119.091003,46.232201],"type":"Point"}
}