{
  "type": "Feature",
  "properties": {
    "addr:full":"2127 N Monroe St Spokane WA 99205",
    "addr:housenumber":"2127",
    "addr:postcode":"99205",
    "addr:street":"N Monroe St",
    "iso:country":"US",
    "sg:address":"2127 N Monroe St",
    "sg:city":"Spokane",
    "sg:classifiers":[
        {
            "category":"Real Estate",
            "subcategory":"Real Estate Agent",
            "type":"Services"
        }
    ],
    "sg:phone":"+1 509 325 2127",
    "sg:postcode":"99205",
    "sg:province":"WA",
    "sg:tags":[
        "management"
    ],
    "sg:website":"www.spokane4rent.com",
    "wof:name":"Watson Management Co",
    "wof:placetype":"venue"
},
  "geometry": {"coordinates":[-117.426744,47.676951],"type":"Point"}
}