{
  "type": "Feature",
  "properties": {
    "addr:full":"2141 E 3rd Ave Port Angeles WA 98362",
    "addr:housenumber":"2141",
    "addr:postcode":"98362",
    "addr:street":"E 3Rd Ave",
    "iso:country":"US",
    "sg:address":"2141 E 3rd Ave",
    "sg:city":"Port Angeles",
    "sg:classifiers":[
        {
            "category":"Taxi",
            "type":"Transportation"
        }
    ],
    "sg:phone":"+1 360 452 2223",
    "sg:postcode":"98362",
    "sg:province":"WA",
    "sg:tags":[
        "taxicab"
    ],
    "wof:name":"Blue Top Cabs",
    "wof:placetype":"venue"
},
  "geometry": {"coordinates":[-123.396021,48.112964],"type":"Point"}
}