{
  "type": "Feature",
  "properties": {
    "addr:full":"2302 E Trent Ave Spokane WA 99202",
    "addr:housenumber":"2302",
    "addr:postcode":"99202",
    "addr:street":"E Trent Ave",
    "iso:country":"US",
    "sg:address":"2302 E Trent Ave",
    "sg:city":"Spokane",
    "sg:classifiers":[
        {
            "category":"Retail",
            "subcategory":"Auto Repair",
            "type":"Services"
        }
    ],
    "sg:phone":"+1 509 535 3589",
    "sg:postcode":"99202",
    "sg:province":"WA",
    "sg:tags":[
        "body"
    ],
    "wof:name":"Triple Plate Chrome Bmper Repr",
    "wof:placetype":"venue"
},
  "geometry": {"coordinates":[-117.373437,47.662701],"type":"Point"}
}