{
  "type": "Feature",
  "properties": {
    "iso:country":"US",
    "sg:address":"3574 Waitts Lake Rd",
    "sg:city":"Valley",
    "sg:classifiers":[
        {
            "category":"Building & Trades",
            "subcategory":"Landscaping Services",
            "type":"Services"
        }
    ],
    "sg:phone":"+1 509 937 2701",
    "sg:postcode":"99181",
    "sg:province":"WA",
    "sg:tags":[
        "tree"
    ],
    "wof:name":"Brooks Tree Svc Inc",
    "wof:placetype":"venue"
},
  "geometry": {"coordinates":[-117.77161,48.182876],"type":"Point"}
}