{
  "type": "Feature",
  "properties": {
    "addr:full":"16827 Bothell Way NE Seattle WA 98155",
    "addr:housenumber":"16827",
    "addr:postcode":"98155",
    "addr:street":"Bothell Way Ne",
    "iso:country":"US",
    "sg:address":"16827 Bothell Way NE",
    "sg:city":"Seattle",
    "sg:classifiers":[
        {
            "category":"Retail",
            "subcategory":"Car Wash",
            "type":"Services"
        }
    ],
    "sg:phone":"+1 206 362 9440",
    "sg:postcode":"98155",
    "sg:province":"WA",
    "sg:tags":[
        "carwash",
        "station",
        "gasoline"
    ],
    "wof:name":"Texaco",
    "wof:placetype":"venue"
},
  "geometry": {"coordinates":[-122.281127,47.75162],"type":"Point"}
}