{
  "type": "Feature",
  "properties": {
    "addr:full":"2376 Main St Ferndale WA 98248",
    "addr:housenumber":"2376",
    "addr:postcode":"98248",
    "addr:street":"Main St",
    "iso:country":"US",
    "sg:address":"2376 Main St",
    "sg:city":"Ferndale",
    "sg:classifiers":[
        {
            "category":"Health Services",
            "subcategory":"Hospital",
            "type":"Services"
        }
    ],
    "sg:phone":"+1 360 384 2427",
    "sg:postcode":"98248",
    "sg:province":"WA",
    "sg:tags":[
        "general"
    ],
    "wof:name":"Saint Joseph Hospital",
    "wof:placetype":"venue"
},
  "geometry": {"coordinates":[-122.603621,48.848346],"type":"Point"}
}