{
  "type": "Feature",
  "properties": {
    "addr:full":"1377 King Rd Winlock WA 98596",
    "addr:housenumber":"1377",
    "addr:postcode":"98596",
    "addr:street":"King Rd",
    "iso:country":"US",
    "sg:address":"1377 King Rd",
    "sg:city":"Winlock",
    "sg:classifiers":[
        {
            "category":"Health Services",
            "subcategory":"Dentist",
            "type":"Services"
        }
    ],
    "sg:phone":"+1 360 785 4449",
    "sg:postcode":"98596",
    "sg:province":"WA",
    "wof:name":"Wesley R Anderson",
    "wof:placetype":"venue"
},
  "geometry": {"coordinates":[-122.996039,46.513734],"type":"Point"}
}