{
  "type": "Feature",
  "properties": {
    "iso:country":"US",
    "sg:address":"670 NW Gilman Blvd",
    "sg:city":"Issaquah",
    "sg:classifiers":[
        {
            "category":"Health Services",
            "subcategory":"Doctor",
            "type":"Services"
        }
    ],
    "sg:phone":"+1 425 557 9663",
    "sg:postcode":"98027",
    "sg:province":"WA",
    "wof:name":"Pacific Dental Care",
    "wof:placetype":"venue"
},
  "geometry": {"coordinates":[-122.04764900000001,47.543427],"type":"Point"}
}