{
  "type": "Feature",
  "properties": {
    "addr:full":"2012 Broadway St Vancouver WA 98663",
    "addr:housenumber":"2012",
    "addr:postcode":"98663",
    "addr:street":"Broadway St",
    "iso:country":"US",
    "sg:address":"2012 Broadway St",
    "sg:city":"Vancouver",
    "sg:classifiers":[
        {
            "category":"Health Services",
            "subcategory":"Health Practitioner",
            "type":"Services"
        }
    ],
    "sg:phone":"+1 360 737 8150",
    "sg:postcode":"98663",
    "sg:province":"WA",
    "wof:name":"Barbara Ketcham Psyd Clinical",
    "wof:placetype":"venue"
},
  "geometry": {"coordinates":[-122.670441,45.637616],"type":"Point"}
}