{
  "type": "Feature",
  "properties": {
    "addr:full":"23718 Pacific Hwy S Kent WA 98032",
    "addr:housenumber":"23718",
    "addr:postcode":"98032",
    "addr:street":"Pacific Hwy S",
    "iso:country":"US",
    "sg:address":"23718 Pacific Hwy S",
    "sg:city":"Kent",
    "sg:classifiers":[
        {
            "category":"Autos & Motor Vehicles",
            "subcategory":"Automobile Sales",
            "type":"Retail Goods"
        }
    ],
    "sg:phone":"+1 206 824 6888",
    "sg:postcode":"98032",
    "sg:province":"WA",
    "sg:tags":[
        "car",
        "dealer"
    ],
    "wof:name":"Babylon Auto Sales Inc",
    "wof:placetype":"venue"
},
  "geometry": {"coordinates":[-122.296053,47.38793],"type":"Point"}
}