{
  "type": "Feature",
  "properties": {
    "addr:full":"2451 E Delmar Dr Seattle WA 98127",
    "addr:housenumber":"2451",
    "addr:postcode":"98127",
    "addr:street":"E Delmar Dr",
    "iso:country":"US",
    "sg:address":"2451 E Delmar Dr",
    "sg:city":"Seattle",
    "sg:classifiers":[
        {
            "category":"Park",
            "type":"Public Place"
        }
    ],
    "sg:postcode":"98127",
    "sg:province":"WA",
    "sg:website":"www.seattle.gov/parks/park_detai...",
    "wof:name":"Interlaken Park",
    "wof:placetype":"venue"
},
  "geometry": {"coordinates":[-122.317165,47.642095],"type":"Point"}
}