{
  "type": "Feature",
  "properties": {
    "addr:full":"10801 Myers Way S Seattle WA 98168",
    "addr:housenumber":"10801",
    "addr:postcode":"98168",
    "addr:street":"Myers Way S",
    "iso:country":"US",
    "sg:address":"10801 Myers Way S",
    "sg:city":"Seattle",
    "sg:classifiers":[
        {
            "category":"Coffee & Tea",
            "type":"Food & Drink"
        },
        {
            "category":"Restaurant",
            "type":"Food & Drink"
        }
    ],
    "sg:phone":"+1 206 241 0233",
    "sg:postcode":"98168",
    "sg:province":"WA",
    "sg:tags":[
        "shop",
        "espresso"
    ],
    "wof:name":"First Choice Espresso",
    "wof:placetype":"venue"
},
  "geometry": {"coordinates":[-122.33150500000001,47.506605],"type":"Point"}
}