{
  "type": "Feature",
  "properties": {
    "iso:country":"US",
    "sg:address":"9019 228th St SW",
    "sg:city":"Edmonds",
    "sg:classifiers":[
        {
            "category":"Building & Trades",
            "subcategory":"Construction",
            "type":"Services"
        }
    ],
    "sg:phone":"+1 425 771 6029",
    "sg:postcode":"98026",
    "sg:province":"WA",
    "sg:tags":[
        "house"
    ],
    "wof:name":"Home Renovations Inc",
    "wof:placetype":"venue"
},
  "geometry": {"coordinates":[-122.355992,47.792408],"type":"Point"}
}