{
  "type": "Feature",
  "properties": {
    "iso:country":"US",
    "sg:address":"218 E Main St",
    "sg:city":"Fairfield",
    "sg:classifiers":[
        {
            "category":"Government",
            "subcategory":"Office",
            "type":"Public Place"
        }
    ],
    "sg:phone":"+1 509 283 2414",
    "sg:postcode":"99012",
    "sg:province":"WA",
    "sg:tags":[
        "city"
    ],
    "wof:name":"Fairfield City Hall",
    "wof:placetype":"venue"
},
  "geometry": {"coordinates":[-117.17138,47.385157],"type":"Point"}
}