{
  "type": "Feature",
  "properties": {
    "addr:full":"405 S Peabody St Port Angeles WA 98362",
    "addr:housenumber":"405",
    "addr:postcode":"98362",
    "addr:street":"S Peabody St",
    "iso:country":"US",
    "sg:address":"405 S Peabody St",
    "sg:city":"Port Angeles",
    "sg:classifiers":[
        {
            "category":"Building & Trades",
            "subcategory":"Construction",
            "type":"Services"
        }
    ],
    "sg:phone":"+1 360 417 0132",
    "sg:postcode":"98362",
    "sg:province":"WA",
    "sg:tags":[
        "housing",
        "contractor"
    ],
    "wof:name":"German Martin Construction LLC",
    "wof:placetype":"venue"
},
  "geometry": {"coordinates":[-123.43037200000001,48.114111],"type":"Point"}
}