{
  "type": "Feature",
  "properties": {
    "addr:full":"1815 Williams Ave Sumner WA 98390",
    "addr:housenumber":"1815",
    "addr:postcode":"98390",
    "addr:street":"Williams Ave",
    "iso:country":"US",
    "sg:address":"1815 Williams Ave",
    "sg:city":"Sumner",
    "sg:classifiers":[
        {
            "category":"Wholesale",
            "subcategory":"Metals & Minerals",
            "type":"Manufacturing & Wholesale Goods"
        }
    ],
    "sg:phone":"+1 253 833 4044",
    "sg:postcode":"98390",
    "sg:province":"WA",
    "sg:tags":[
        "distribution",
        "center"
    ],
    "wof:name":"Bright Horizon Metals Inc",
    "wof:placetype":"venue"
},
  "geometry": {"coordinates":[-122.234663,47.211144],"type":"Point"}
}