{
  "type": "Feature",
  "properties": {
    "addr:full":"6901 Central Park Dr Aberdeen WA 98520",
    "addr:housenumber":"6901",
    "addr:postcode":"98520",
    "addr:street":"Central Park Dr",
    "iso:country":"US",
    "sg:address":"6901 Central Park Dr",
    "sg:city":"Aberdeen",
    "sg:classifiers":[
        {
            "category":"Professional",
            "subcategory":"Business Services",
            "type":"Services"
        }
    ],
    "sg:phone":"+1 360 538 1386",
    "sg:postcode":"98520",
    "sg:province":"WA",
    "wof:name":"Jeff Miller Enterprises",
    "wof:placetype":"venue"
},
  "geometry": {"coordinates":[-123.69137000000001,46.963132],"type":"Point"}
}