{
  "type": "Feature",
  "properties": {
    "addr:full":"7777 Perimeter Rd S Seattle WA 98108",
    "addr:housenumber":"7777",
    "addr:postcode":"98108",
    "addr:street":"Perimeter Rd S",
    "iso:country":"US",
    "sg:address":"7777 Perimeter Rd S",
    "sg:city":"Seattle",
    "sg:classifiers":[
        {
            "category":"Professional",
            "subcategory":"Engineering",
            "type":"Services"
        }
    ],
    "sg:phone":"+1 206 762 6190",
    "sg:postcode":"98108",
    "sg:province":"WA",
    "wof:name":"Jetlease Partners",
    "wof:placetype":"venue"
},
  "geometry": {"coordinates":[-122.30107599999999,47.536125],"type":"Point"}
}