{
  "type": "Feature",
  "properties": {
    "addr:full":"15414 82nd Ave NW Gig Harbor WA 98329",
    "addr:housenumber":"15414",
    "addr:postcode":"98329",
    "addr:street":"82Nd Ave Nw",
    "iso:country":"US",
    "sg:address":"15414 82nd Ave NW",
    "sg:city":"Gig Harbor",
    "sg:classifiers":[
        {
            "category":"Personal",
            "subcategory":"Massage",
            "type":"Services"
        }
    ],
    "sg:phone":"+1 253 853 7585",
    "sg:postcode":"98329",
    "sg:province":"WA",
    "wof:name":"Helens Therapeutic Touch",
    "wof:placetype":"venue"
},
  "geometry": {"coordinates":[-122.647841,47.397879],"type":"Point"}
}