{
  "type": "Feature",
  "properties": {
    "addr:full":"11755 Corliss Ave N Seattle WA 98133",
    "addr:housenumber":"11755",
    "addr:postcode":"98133",
    "addr:street":"Corliss Ave N",
    "iso:country":"US",
    "sg:address":"11755 Corliss Ave N",
    "sg:city":"Seattle",
    "sg:classifiers":[
        {
            "category":"Professional",
            "subcategory":"Art Services",
            "type":"Services"
        }
    ],
    "sg:phone":"+1 206 367 5893",
    "sg:postcode":"98133",
    "sg:province":"WA",
    "sg:tags":[
        "commercial",
        "design"
    ],
    "wof:name":"Design One Limited",
    "wof:placetype":"venue"
},
  "geometry": {"coordinates":[-122.331534,47.715861],"type":"Point"}
}