{
  "type": "Feature",
  "properties": {
    "addr:full":"1 E 1st Ave Kennewick WA 99336",
    "addr:housenumber":"1",
    "addr:postcode":"99336",
    "addr:street":"E 1St Ave",
    "iso:country":"US",
    "sg:address":"1 E 1st Ave",
    "sg:city":"Kennewick",
    "sg:classifiers":[
        {
            "category":"Autos & Motor Vehicles",
            "subcategory":"Automobile Sales",
            "type":"Retail Goods"
        }
    ],
    "sg:phone":"+1 509 582 9872",
    "sg:postcode":"99336",
    "sg:province":"WA",
    "sg:tags":[
        "car",
        "used",
        "dealer"
    ],
    "wof:name":"Parkade Auto Center",
    "wof:placetype":"venue"
},
  "geometry": {"coordinates":[-119.115381,46.207554],"type":"Point"}
}