{
  "type": "Feature",
  "properties": {
    "addr:full":"4205 Riverhill Dr Pasco WA 99301",
    "addr:housenumber":"4205",
    "addr:postcode":"99301",
    "addr:street":"Riverhill Dr",
    "iso:country":"US",
    "sg:address":"4205 Riverhill Dr",
    "sg:city":"Pasco",
    "sg:classifiers":[
        {
            "category":"Personal",
            "subcategory":"Beauty Salon",
            "type":"Services"
        }
    ],
    "sg:phone":"+1 509 547 6046",
    "sg:postcode":"99301",
    "sg:province":"WA",
    "sg:tags":[
        "shop"
    ],
    "wof:name":"Cute-Icles",
    "wof:placetype":"venue"
},
  "geometry": {"coordinates":[-119.14510799999999,46.261833],"type":"Point"}
}