{
  "type": "Feature",
  "properties": {
    "addr:full":"25539 Omans Rd N Davenport WA 99122",
    "addr:postcode":"25539;99122",
    "addr:street":"Omans Rd N",
    "iso:country":"US",
    "sg:address":"25539 Omans Rd N",
    "sg:city":"Davenport",
    "sg:classifiers":[
        {
            "category":"Retail",
            "subcategory":"Portrait Studio",
            "type":"Services"
        }
    ],
    "sg:phone":"+1 509 725 3842",
    "sg:postcode":"99122",
    "sg:province":"WA",
    "sg:tags":[
        "photo",
        "photography",
        "commercial"
    ],
    "wof:name":"Magical Moments Photography",
    "wof:placetype":"venue"
},
  "geometry": {"coordinates":[-118.098232,47.628854],"type":"Point"}
}