{
  "type": "Feature",
  "properties": {
    "addr:full":"18823 Hwy 99 Lynnwood WA 98036",
    "addr:housenumber":"18823",
    "addr:postcode":"98036",
    "addr:street":"Hwy 99",
    "iso:country":"US",
    "sg:address":"18823 Hwy 99",
    "sg:city":"Lynnwood",
    "sg:classifiers":[
        {
            "category":"Retail",
            "subcategory":"Car Wash",
            "type":"Services"
        }
    ],
    "sg:phone":"+1 425 745 5881",
    "sg:postcode":"98036",
    "sg:province":"WA",
    "sg:tags":[
        "polishing",
        "washing"
    ],
    "wof:name":"Warren & Son's Auto Detail",
    "wof:placetype":"venue"
},
  "geometry": {"coordinates":[-122.310059,47.826969],"type":"Point"}
}