{
  "type": "Feature",
  "properties": {
    "addr:full":"23806 NE 34th St Camas WA 98607",
    "addr:housenumber":"23806",
    "addr:postcode":"98607",
    "addr:street":"Ne 34Th St",
    "iso:country":"US",
    "sg:address":"23806 NE 34th St",
    "sg:city":"Camas",
    "sg:classifiers":[
        {
            "category":"Building & Trades",
            "subcategory":"Construction",
            "type":"Services"
        }
    ],
    "sg:phone":"+1 360 834 0605",
    "sg:postcode":"98607",
    "sg:province":"WA",
    "sg:tags":[
        "contractor"
    ],
    "sg:website":"www.mrtwest.com",
    "wof:name":"Metal Roof Technologies Inc",
    "wof:placetype":"venue"
},
  "geometry": {"coordinates":[-122.42795700000001,45.646949],"type":"Point"}
}