{
  "type": "Feature",
  "properties": {
    "addr:full":"18870 Yakima Valley Hwy Granger WA 98932",
    "addr:postcode":"18870;98932",
    "addr:street":"Valley Hwy",
    "iso:country":"US",
    "sg:address":"18870 Yakima Valley Hwy",
    "sg:city":"Granger",
    "sg:classifiers":[
        {
            "category":"Autos & Motor Vehicles",
            "subcategory":"Automobile Sales",
            "type":"Retail Goods"
        }
    ],
    "sg:phone":"+1 509 854 1055",
    "sg:postcode":"98932",
    "sg:province":"WA",
    "sg:tags":[
        "car",
        "dealer"
    ],
    "wof:name":"Mendoza's Auto Sales",
    "wof:placetype":"venue"
},
  "geometry": {"coordinates":[-120.188281,46.354333],"type":"Point"}
}