{
  "type": "Feature",
  "properties": {
    "addr:full":"2611 N Market St Spokane WA 99207",
    "addr:housenumber":"2611",
    "addr:postcode":"99207",
    "addr:street":"N Market St",
    "iso:country":"US",
    "sg:address":"2611 N Market St",
    "sg:city":"Spokane",
    "sg:classifiers":[
        {
            "category":"Retail",
            "subcategory":"Photofinishing",
            "type":"Services"
        }
    ],
    "sg:phone":"+1 509 487 2167",
    "sg:postcode":"99207",
    "sg:province":"WA",
    "sg:tags":[
        "laboratory"
    ],
    "wof:name":"Digital Showcase Express Photo",
    "wof:placetype":"venue"
},
  "geometry": {"coordinates":[-117.36517499999999,47.682012],"type":"Point"}
}