{
  "type": "Feature",
  "properties": {
    "addr:full":"1516 2nd Ave Seattle WA 98101",
    "addr:housenumber":"1516",
    "addr:postcode":"98101",
    "addr:street":"2Nd Ave",
    "iso:country":"US",
    "sg:address":"1516 2nd Ave",
    "sg:city":"Seattle",
    "sg:classifiers":[
        {
            "category":"Real Estate",
            "subcategory":"Real Estate Agent",
            "type":"Services"
        }
    ],
    "sg:phone":"+1 206 382 9181",
    "sg:postcode":"98101",
    "sg:province":"WA",
    "wof:name":"Imperial Real Estate Corp",
    "wof:placetype":"venue"
},
  "geometry": {"coordinates":[-122.33965000000001,47.610154],"type":"Point"}
}