{
  "type": "Feature",
  "properties": {
    "addr:full":"18200 Segale Park Dr B Seattle WA 98188",
    "addr:postcode":"18200;98188",
    "addr:street":"Segale Park Dr B",
    "iso:country":"US",
    "sg:address":"18200 Segale Park Dr B",
    "sg:city":"Seattle",
    "sg:classifiers":[
        {
            "category":"Professional",
            "subcategory":"Business Services",
            "type":"Services"
        }
    ],
    "sg:phone":"+1 206 575 3591",
    "sg:postcode":"98188",
    "sg:province":"WA",
    "wof:name":"Rainier Sewing Inc",
    "wof:placetype":"venue"
},
  "geometry": {"coordinates":[-122.257582,47.438617],"type":"Point"}
}