{
  "type": "Feature",
  "properties": {
    "addr:full":"3474 Alm Rd Everson WA 98247",
    "addr:postcode":"3474;98247",
    "addr:street":"Alm Rd",
    "iso:country":"US",
    "sg:address":"3474 Alm Rd",
    "sg:city":"Everson",
    "sg:classifiers":[
        {
            "category":"Shopping",
            "subcategory":"Bicycles & Sporting Goods",
            "type":"Retail Goods"
        }
    ],
    "sg:phone":"+1 360 966 4893",
    "sg:postcode":"98247",
    "sg:province":"WA",
    "wof:name":"Out & About Products Inc",
    "wof:placetype":"venue"
},
  "geometry": {"coordinates":[-122.30007000000001,48.942044],"type":"Point"}
}