{
  "type": "Feature",
  "properties": {
    "addr:full":"1022 Sylvan Way Bremerton WA 98310",
    "addr:housenumber":"1022",
    "addr:postcode":"98310",
    "addr:street":"Sylvan Way",
    "iso:country":"US",
    "sg:address":"1022 Sylvan Way",
    "sg:city":"Bremerton",
    "sg:classifiers":[
        {
            "category":"Personal",
            "type":"Services"
        }
    ],
    "sg:phone":"+1 360 377 0725",
    "sg:postcode":"98310",
    "sg:province":"WA",
    "sg:tags":[
        "therapist",
        "massage"
    ],
    "wof:name":"Mountain View Massage",
    "wof:placetype":"venue"
},
  "geometry": {"coordinates":[-122.62951700000001,47.595732],"type":"Point"}
}