{
  "type": "Feature",
  "properties": {
    "addr:full":"7626 S 113th St Seattle WA 98178",
    "addr:housenumber":"7626",
    "addr:postcode":"98178",
    "addr:street":"S 113Th St",
    "iso:country":"US",
    "sg:address":"7626 S 113th St",
    "sg:city":"Seattle",
    "sg:classifiers":[
        {
            "category":"Restaurant",
            "type":"Food & Drink"
        }
    ],
    "sg:phone":"+1 206 772 1216",
    "sg:postcode":"98178",
    "sg:province":"WA",
    "sg:tags":[
        "eating"
    ],
    "wof:name":"Genesristorantecom",
    "wof:placetype":"venue"
},
  "geometry": {"coordinates":[-122.235716,47.502147],"type":"Point"}
}