{
  "type": "Feature",
  "properties": {
    "addr:full":"800 Bellevue Way NE Suite 400 Bellevue WA 98004",
    "addr:housenumber":"800",
    "addr:postcode":"98004",
    "addr:street":"Bellevue Way Ne Suite 400",
    "iso:country":"US",
    "sg:address":"800 Bellevue Way NE Suite 400",
    "sg:city":"Bellevue",
    "sg:classifiers":[
        {
            "category":"Professional",
            "subcategory":"Research",
            "type":"Services"
        }
    ],
    "sg:phone":"+1 866 359 7541",
    "sg:postcode":"98004",
    "sg:province":"WA",
    "sg:website":"http://www.tapimmune.com/",
    "wof:name":"TapImmune",
    "wof:placetype":"venue"
},
  "geometry": {"coordinates":[-122.200642,47.601545],"type":"Point"}
}