{
  "type": "Feature",
  "properties": {
    "addr:full":"9315 Gravelly Lake Dr SW Lakewood WA 98499",
    "addr:housenumber":"9315",
    "addr:postcode":"98499",
    "addr:street":"Gravelly Lake Dr Sw",
    "iso:country":"US",
    "sg:address":"9315 Gravelly Lake Dr SW",
    "sg:city":"Lakewood",
    "sg:classifiers":[
        {
            "category":"Health Services",
            "subcategory":"Doctor",
            "type":"Services"
        }
    ],
    "sg:phone":"+1 800 408 4444",
    "sg:postcode":"98499",
    "sg:province":"WA",
    "sg:website":"www.avalonclinic.com",
    "wof:name":"Avalon Clinic For Cosmetic Surgery",
    "wof:placetype":"venue"
},
  "geometry": {"coordinates":[-122.518744,47.171336],"type":"Point"}
}