{
  "type": "Feature",
  "properties": {
    "addr:full":"604 W Elm St Walla Walla WA 99362",
    "addr:housenumber":"604",
    "addr:postcode":"99362",
    "addr:street":"W Elm St",
    "iso:country":"US",
    "sg:address":"604 W Elm St",
    "sg:city":"Walla Walla",
    "sg:classifiers":[
        {
            "category":"Bars & Pubs",
            "type":"Food & Drink"
        }
    ],
    "sg:phone":"+1 509 525 9944",
    "sg:postcode":"99362",
    "sg:province":"WA",
    "wof:name":"Border Tavern",
    "wof:placetype":"venue"
},
  "geometry": {"coordinates":[-118.35046699999999,46.070588],"type":"Point"}
}