{
  "type": "Feature",
  "properties": {
    "iso:country":"US",
    "sg:address":"1221 29th St NW",
    "sg:city":"Auburn",
    "sg:classifiers":[
        {
            "category":"Wholesale",
            "subcategory":"Metals & Minerals",
            "type":"Manufacturing & Wholesale Goods"
        }
    ],
    "sg:phone":"+1 253 939 4747",
    "sg:postcode":"98001",
    "sg:province":"WA",
    "sg:tags":[
        "metalwork",
        "center",
        "architectural",
        "mfg"
    ],
    "wof:name":"McNichols Company",
    "wof:placetype":"venue"
},
  "geometry": {"coordinates":[-122.248783,47.333409],"type":"Point"}
}