{
  "type": "Feature",
  "properties": {
    "addr:full":"16114 SE 24th St Bellevue WA 98008",
    "addr:postcode":"16114;98008",
    "addr:street":"Se 24Th St",
    "iso:country":"US",
    "sg:address":"16114 SE 24th St",
    "sg:city":"Bellevue",
    "sg:classifiers":[
        {
            "category":"Real Estate",
            "subcategory":"Architect",
            "type":"Services"
        }
    ],
    "sg:phone":"+1 425 643 8418",
    "sg:postcode":"98008",
    "sg:province":"WA",
    "wof:name":"Mrewyn Haneberg",
    "wof:placetype":"venue"
},
  "geometry": {"coordinates":[-122.123901,47.589066],"type":"Point"}
}