{
  "type": "Feature",
  "properties": {
    "addr:full":"125 Central Ave N Kent WA 98032",
    "addr:housenumber":"125",
    "addr:postcode":"98032",
    "addr:street":"Central Ave N",
    "iso:country":"US",
    "sg:address":"125 Central Ave N",
    "sg:city":"Kent",
    "sg:classifiers":[
        {
            "category":"Shopping",
            "type":"Retail Goods"
        }
    ],
    "sg:phone":"+1 253 850 7296",
    "sg:postcode":"98032",
    "sg:province":"WA",
    "sg:tags":[
        "merchandise"
    ],
    "wof:name":"Pawnpros Superstores",
    "wof:placetype":"venue"
},
  "geometry": {"coordinates":[-122.23107899999999,47.382041],"type":"Point"}
}