{
  "type": "Feature",
  "properties": {
    "addr:full":"714 Willow Ct S Bellingham WA 98225",
    "addr:housenumber":"714",
    "addr:postcode":"98225",
    "addr:street":"Willow Ct;Bellingham",
    "iso:country":"US",
    "sg:address":"714 Willow Ct S",
    "sg:city":"Bellingham",
    "sg:classifiers":[
        {
            "category":"Building & Trades",
            "subcategory":"Plumbing",
            "type":"Services"
        }
    ],
    "sg:phone":"+1 360 676 4747",
    "sg:postcode":"98225",
    "sg:province":"WA",
    "sg:tags":[
        "contractor"
    ],
    "wof:name":"Merit Plumbing Contractors",
    "wof:placetype":"venue"
},
  "geometry": {"coordinates":[-122.500467,48.709345],"type":"Point"}
}