{
  "type": "Feature",
  "properties": {
    "addr:full":"9935 8th Ave SW Seattle WA 98106",
    "addr:housenumber":"9935",
    "addr:postcode":"98106",
    "addr:street":"8Th Ave Sw",
    "iso:country":"US",
    "sg:address":"9935 8th Ave SW",
    "sg:city":"Seattle",
    "sg:classifiers":[
        {
            "category":"Real Estate",
            "subcategory":"Real Estate Operator",
            "type":"Services"
        }
    ],
    "sg:phone":"+1 206 529 3233",
    "sg:postcode":"98106",
    "sg:province":"WA",
    "sg:tags":[
        "apartment"
    ],
    "wof:name":"Nia Apartments",
    "wof:placetype":"venue"
},
  "geometry": {"coordinates":[-122.34540200000001,47.514306],"type":"Point"}
}