{
  "type": "Feature",
  "properties": {
    "iso:country":"US",
    "sg:address":"18781 Angeline Ave NE",
    "sg:city":"Suquamish",
    "sg:classifiers":[
        {
            "category":"Professional",
            "subcategory":"Computer Services",
            "type":"Services"
        }
    ],
    "sg:phone":"+1 360 697 1857",
    "sg:postcode":"98392",
    "sg:province":"WA",
    "sg:tags":[
        "home",
        "consulting",
        "page",
        "dev",
        "internet"
    ],
    "wof:name":"Telenet Consulting",
    "wof:placetype":"venue"
},
  "geometry": {"coordinates":[-122.55072800000001,47.731846],"type":"Point"}
}