{
  "type": "Feature",
  "properties": {
    "addr:full":"409 1st Ave S Seattle WA 98104",
    "addr:housenumber":"409",
    "addr:postcode":"98104",
    "addr:street":"1St Ave S",
    "iso:country":"US",
    "sg:address":"409 1st Ave S",
    "sg:city":"Seattle",
    "sg:classifiers":[
        {
            "category":"Shopping",
            "type":"Retail Goods"
        }
    ],
    "sg:phone":"+1 206 625 0347",
    "sg:postcode":"98104",
    "sg:province":"WA",
    "sg:tags":[
        "art",
        "gallery",
        "dealer"
    ],
    "sg:website":"www.animationusa.com",
    "wof:name":"Animation USA",
    "wof:placetype":"venue"
},
  "geometry": {"coordinates":[-122.33426799999999,47.598365],"type":"Point"}
}