{
  "type": "Feature",
  "properties": {
    "addr:full":"10821 8th Ave SW Seattle WA 98146",
    "addr:housenumber":"10821",
    "addr:postcode":"98146",
    "addr:street":"8Th Ave Sw",
    "iso:country":"US",
    "sg:address":"10821 8th Ave SW",
    "sg:city":"Seattle",
    "sg:classifiers":[
        {
            "category":"Health Services",
            "subcategory":"Clinic",
            "type":"Services"
        }
    ],
    "sg:phone":"+1 206 296 4822",
    "sg:postcode":"98146",
    "sg:province":"WA",
    "wof:name":"W I C Program",
    "wof:placetype":"venue"
},
  "geometry": {"coordinates":[-122.344004,47.50493],"type":"Point"}
}