{
  "type": "Feature",
  "properties": {
    "addr:full":"1700 7th Avenue Suite 1900 Seattle WA 98101",
    "addr:housenumber":"1700",
    "addr:postcode":"98101",
    "addr:street":"7Th Avenue Suite 1900",
    "iso:country":"US",
    "sg:address":"1700 7th Avenue Suite 1900",
    "sg:city":"Seattle",
    "sg:classifiers":[
        {
            "category":"Professional",
            "subcategory":"Lawyer & Legal Services",
            "type":"Services"
        }
    ],
    "sg:phone":"+1 206 622 5511",
    "sg:postcode":"98101",
    "sg:province":"WA",
    "sg:website":"www.bbllaw.com",
    "wof:name":"Dettmer Teri M Atty",
    "wof:placetype":"venue"
},
  "geometry": {"coordinates":[-122.334694,47.613145],"type":"Point"}
}