{
  "type": "Feature",
  "properties": {
    "addr:full":"4180 Old Lewis River Rd Woodland WA 98674",
    "addr:housenumber":"4180",
    "addr:postcode":"98674",
    "addr:street":"Old Lewis River Rd",
    "iso:country":"US",
    "sg:address":"4180 Old Lewis River Rd",
    "sg:city":"Woodland",
    "sg:classifiers":[
        {
            "category":"Mining & Drilling",
            "type":"Manufacturing & Wholesale Goods"
        }
    ],
    "sg:phone":"+1 360 225 8084",
    "sg:postcode":"98674",
    "sg:province":"WA",
    "sg:tags":[
        "well"
    ],
    "wof:name":"Don Swett Drilling Inc",
    "wof:placetype":"venue"
},
  "geometry": {"coordinates":[-122.62563900000001,45.94047],"type":"Point"}
}