{
  "type": "Feature",
  "properties": {
    "addr:full":"1025 E Lakeshore Dr Medical Lake WA 99022",
    "addr:housenumber":"1025",
    "addr:postcode":"99022",
    "addr:street":"E Lakeshore",
    "iso:country":"US",
    "sg:address":"1025 E Lakeshore Dr",
    "sg:city":"Medical Lake",
    "sg:classifiers":[
        {
            "category":"Restaurant",
            "type":"Food & Drink"
        }
    ],
    "sg:phone":"+1 509 299 5201",
    "sg:postcode":"99022",
    "sg:province":"WA",
    "sg:tags":[
        "eating"
    ],
    "wof:name":"J CS Java Blenz",
    "wof:placetype":"venue"
},
  "geometry": {"coordinates":[-117.67044199999999,47.56703],"type":"Point"}
}