{
  "type": "Feature",
  "properties": {
    "addr:full":"7417 NE 170th St Kenmore WA 98028",
    "addr:housenumber":"7417",
    "addr:postcode":"98028",
    "addr:street":"Ne 170Th St",
    "iso:country":"US",
    "sg:address":"7417 NE 170th St",
    "sg:city":"Kenmore",
    "sg:classifiers":[
        {
            "category":"Building & Trades",
            "subcategory":"Construction",
            "type":"Services"
        }
    ],
    "sg:phone":"+1 206 601 8984",
    "sg:postcode":"98028",
    "sg:province":"WA",
    "sg:tags":[
        "floor",
        "laying",
        "contractor"
    ],
    "wof:name":"Michael Kerr Company Inc",
    "wof:placetype":"venue"
},
  "geometry": {"coordinates":[-122.242923,47.751514],"type":"Point"}
}