{
  "type": "Feature",
  "properties": {
    "addr:full":"455 Wapato Lake Rd Manson WA 98831",
    "addr:housenumber":"455",
    "addr:postcode":"98831",
    "addr:street":"Wapato Lake Rd",
    "iso:country":"US",
    "sg:address":"455 Wapato Lake Rd",
    "sg:city":"Manson",
    "sg:classifiers":[
        {
            "category":"Sports & Exercise",
            "subcategory":"Golf",
            "type":"Entertainment"
        }
    ],
    "sg:phone":"+1 509 687 6338",
    "sg:postcode":"98831",
    "sg:province":"WA",
    "sg:tags":[
        "course"
    ],
    "wof:name":"Ma 8 Golf",
    "wof:placetype":"venue"
},
  "geometry": {"coordinates":[-120.129642,47.881183],"type":"Point"}
}