{
  "type": "Feature",
  "properties": {
    "addr:full":"1717 NE 97th St Vancouver WA 98665",
    "addr:housenumber":"1717",
    "addr:postcode":"98665",
    "addr:street":"Ne 97Th St",
    "iso:country":"US",
    "sg:address":"1717 NE 97th St",
    "sg:city":"Vancouver",
    "sg:classifiers":[
        {
            "category":"Wholesale",
            "subcategory":"Electrical",
            "type":"Manufacturing & Wholesale Goods"
        }
    ],
    "sg:phone":"+1 360 574 8868",
    "sg:postcode":"98665",
    "sg:province":"WA",
    "sg:tags":[
        "lighting",
        "fixtures-wholesale",
        "fixture",
        "manufacturer"
    ],
    "wof:name":"Buccaneer Enterprises",
    "wof:placetype":"venue"
},
  "geometry": {"coordinates":[-122.65482900000001,45.691613],"type":"Point"}
}