{
  "type": "Feature",
  "properties": {
    "addr:full":"1333 S Shelton St Seattle WA 98108",
    "addr:housenumber":"1333",
    "addr:postcode":"98108",
    "addr:street":"S Shelton St",
    "iso:country":"US",
    "sg:address":"1333 S Shelton St",
    "sg:city":"Seattle",
    "sg:classifiers":[
        {
            "category":"Building & Trades",
            "subcategory":"Locksmith",
            "type":"Services"
        }
    ],
    "sg:phone":"+1 206 774 9777",
    "sg:postcode":"98108",
    "sg:province":"WA",
    "sg:tags":[
        "key"
    ],
    "wof:name":"1 24 Hour Emergency Locksmith On Shelton",
    "wof:placetype":"venue"
},
  "geometry": {"coordinates":[-122.31524400000001,47.557765],"type":"Point"}
}