{
  "type": "Feature",
  "properties": {
    "addr:full":"16011 194th Ave SE Renton WA 98058",
    "addr:housenumber":"16011",
    "addr:postcode":"98058",
    "addr:street":"194Th Ave Se",
    "iso:country":"US",
    "sg:address":"16011 194th Ave SE",
    "sg:city":"Renton",
    "sg:classifiers":[
        {
            "category":"Banks & Credit Unions",
            "subcategory":"Bank",
            "type":"Services"
        }
    ],
    "sg:phone":"+1 425 226 9521",
    "sg:postcode":"98058",
    "sg:province":"WA",
    "sg:tags":[
        "other",
        "plan",
        "card"
    ],
    "sg:website":"www.bancardusa.net",
    "wof:name":"Bancard USA",
    "wof:placetype":"venue"
},
  "geometry": {"coordinates":[-122.081664,47.458161],"type":"Point"}
}