{
  "type": "Feature",
  "properties": {
    "iso:country":"US",
    "sg:address":"12719 NW 25th Ave",
    "sg:city":"Vancouver",
    "sg:classifiers":[
        {
            "category":"Insurance",
            "subcategory":"Insurance Agent",
            "type":"Services"
        }
    ],
    "sg:phone":"+1 360 573 6166",
    "sg:postcode":"98685",
    "sg:province":"WA",
    "wof:name":"Leitner Agency",
    "wof:placetype":"venue"
},
  "geometry": {"coordinates":[-122.69708900000001,45.714208],"type":"Point"}
}