{
  "type": "Feature",
  "properties": {
    "addr:full":"2306 118th Pl SE Everett WA 98208",
    "addr:housenumber":"2306",
    "addr:postcode":"98208",
    "addr:street":"118Th Pl Se",
    "iso:country":"US",
    "sg:address":"2306 118th Pl SE",
    "sg:city":"Everett",
    "sg:classifiers":[
        {
            "category":"Shopping",
            "type":"Retail Goods"
        }
    ],
    "sg:phone":"+1 425 357 1942",
    "sg:postcode":"98208",
    "sg:province":"WA",
    "sg:tags":[
        "comparison",
        "mystery"
    ],
    "wof:name":"Eclipse Intl",
    "wof:placetype":"venue"
},
  "geometry": {"coordinates":[-122.20031299999999,47.89119],"type":"Point"}
}