{
  "type": "Feature",
  "properties": {
    "addr:full":"2100 Electric Ave Bellingham WA 98229",
    "addr:housenumber":"2100",
    "addr:postcode":"98229",
    "addr:street":"Electric Ave",
    "iso:country":"US",
    "sg:address":"2100 Electric Ave",
    "sg:city":"Bellingham",
    "sg:classifiers":[
        {
            "category":"Real Estate",
            "subcategory":"Real Estate Operator",
            "type":"Services"
        }
    ],
    "sg:phone":"+1 360 734 5546",
    "sg:postcode":"98229",
    "sg:province":"WA",
    "sg:tags":[
        "building",
        "apartment"
    ],
    "wof:name":"Boyer Ave Co",
    "wof:placetype":"venue"
},
  "geometry": {"coordinates":[-122.421395,48.75741],"type":"Point"}
}