{
  "type": "Feature",
  "properties": {
    "addr:full":"405 SE Everett Mall Way Everett WA 98208",
    "addr:housenumber":"405",
    "addr:postcode":"98208",
    "addr:street":"Se Everett Mall Way",
    "iso:country":"US",
    "sg:address":"405 SE Everett Mall Way",
    "sg:city":"Everett",
    "sg:classifiers":[
        {
            "category":"Shopping",
            "subcategory":"Department Store",
            "type":"Retail Goods"
        }
    ],
    "sg:phone":"+1 425 353 3167",
    "sg:postcode":"98208",
    "sg:province":"WA",
    "wof:name":"Target",
    "wof:placetype":"venue"
},
  "geometry": {"coordinates":[-122.224532,47.909308],"type":"Point"}
}