{
  "type": "Feature",
  "properties": {
    "addr:full":"1120 W Yelm Ave Yelm WA 98597",
    "addr:housenumber":"1120",
    "addr:postcode":"98597",
    "addr:street":"W Yelm Ave",
    "iso:country":"US",
    "sg:address":"1120 W Yelm Ave",
    "sg:city":"Yelm",
    "sg:classifiers":[
        {
            "category":"Retail",
            "subcategory":"Veterinary Services",
            "type":"Services"
        }
    ],
    "sg:phone":"+1 360 458 7707",
    "sg:postcode":"98597",
    "sg:province":"WA",
    "wof:name":"Henricksen Don Dvm",
    "wof:placetype":"venue"
},
  "geometry": {"coordinates":[-122.61930700000001,46.948956],"type":"Point"}
}