{
  "type": "Feature",
  "properties": {
    "iso:country":"US",
    "sg:address":"392 Golf Course Rd",
    "sg:city":"Tekoa",
    "sg:classifiers":[
        {
            "category":"Farming",
            "subcategory":"Farm",
            "type":"Manufacturing & Wholesale Goods"
        }
    ],
    "sg:phone":"+1 509 284 2018",
    "sg:postcode":"99033",
    "sg:province":"WA",
    "sg:tags":[
        "crop",
        "general"
    ],
    "wof:name":"Hay Farms Joint Venture",
    "wof:placetype":"venue"
},
  "geometry": {"coordinates":[-117.05873,47.21797],"type":"Point"}
}