{
  "type": "Feature",
  "properties": {
    "addr:full":"115 Cherry St Seattle WA 98104",
    "addr:housenumber":"115",
    "addr:postcode":"98104",
    "addr:street":"Cherry St",
    "iso:country":"US",
    "sg:address":"115 Cherry St",
    "sg:city":"Seattle",
    "sg:classifiers":[
        {
            "category":"Wholesale",
            "subcategory":"Non-durable Goods",
            "type":"Manufacturing & Wholesale Goods"
        },
        {
            "category":"Personal",
            "subcategory":"Barber",
            "type":"Services"
        }
    ],
    "sg:phone":"+1 206 621 7533",
    "sg:postcode":"98104",
    "sg:province":"WA",
    "sg:tags":[
        "beauty",
        "supply",
        "equipment",
        "salons-equipment",
        "supplies-wholesale",
        "manufacturer"
    ],
    "wof:name":"Paula Tyo",
    "wof:placetype":"venue"
},
  "geometry": {"coordinates":[-122.334142,47.60262],"type":"Point"}
}