{
  "type": "Feature",
  "properties": {
    "addr:full":"2216 Parrott Way Kelso WA 98626",
    "addr:housenumber":"2216",
    "addr:postcode":"98626",
    "addr:street":"Parrott Way",
    "iso:country":"US",
    "sg:address":"2216 Parrott Way",
    "sg:city":"Kelso",
    "sg:classifiers":[
        {
            "category":"Government",
            "subcategory":"Office",
            "type":"Public Place"
        }
    ],
    "sg:phone":"+1 360 577 3115",
    "sg:postcode":"98626",
    "sg:province":"WA",
    "sg:tags":[
        "automotive",
        "general"
    ],
    "wof:name":"Cowlitz County Motor Pool Grge",
    "wof:placetype":"venue"
},
  "geometry": {"coordinates":[-122.89223699999999,46.11717],"type":"Point"}
}