{
  "type": "Feature",
  "properties": {
    "addr:full":"608 S 8th Ave Yakima WA 98902",
    "addr:housenumber":"608",
    "addr:postcode":"98902",
    "addr:street":"S 8Th Ave",
    "iso:country":"US",
    "sg:address":"608 S 8th Ave",
    "sg:city":"Yakima",
    "sg:classifiers":[
        {
            "category":"Shopping",
            "subcategory":"Hobbies, Toys, & Games",
            "type":"Retail Goods"
        }
    ],
    "sg:phone":"+1 509 457 2062",
    "sg:postcode":"98902",
    "sg:province":"WA",
    "wof:name":"Three Bros",
    "wof:placetype":"venue"
},
  "geometry": {"coordinates":[-120.516957,46.591275],"type":"Point"}
}