{
  "type": "Feature",
  "properties": {
    "addr:full":"4720 84th Ave SE Mercer Island WA 98040",
    "addr:housenumber":"4720",
    "addr:postcode":"98040",
    "addr:street":"84Th Ave Se",
    "iso:country":"US",
    "sg:address":"4720 84th Ave SE",
    "sg:city":"Mercer Island",
    "sg:classifiers":[
        {
            "category":"Retail",
            "subcategory":"Portrait Studio",
            "type":"Services"
        }
    ],
    "sg:phone":"+1 206 232 4256",
    "sg:postcode":"98040",
    "sg:province":"WA",
    "sg:tags":[
        "photo"
    ],
    "wof:name":"Starr Photography",
    "wof:placetype":"venue"
},
  "geometry": {"coordinates":[-122.226888,47.561057],"type":"Point"}
}