{
  "type": "Feature",
  "properties": {
    "addr:full":"1740 S 84th St Tacoma WA 98444",
    "addr:housenumber":"1740",
    "addr:postcode":"98444",
    "addr:street":"S 84Th St",
    "iso:country":"US",
    "sg:address":"1740 S 84th St",
    "sg:city":"Tacoma",
    "sg:classifiers":[
        {
            "category":"Social Services",
            "subcategory":"Child Care",
            "type":"Services"
        },
        {
            "category":"Education",
            "subcategory":"Preschool",
            "type":"Public Place"
        },
        {
            "category":"Education",
            "subcategory":"School",
            "type":"Public Place"
        }
    ],
    "sg:phone":"+1 253 537 6870",
    "sg:postcode":"98444",
    "sg:province":"WA",
    "sg:tags":[
        "high",
        "middle",
        "day",
        "elementary"
    ],
    "wof:name":"Puget Sound Christian School",
    "wof:placetype":"venue"
},
  "geometry": {"coordinates":[-122.459999,47.181198],"type":"Point"}
}