{
  "type": "Feature",
  "properties": {
    "addr:full":"13810 Jefferson St Everett WA 98221",
    "addr:housenumber":"13810",
    "addr:postcode":"98221",
    "addr:street":"Jefferson St",
    "iso:country":"US",
    "sg:address":"13810 Jefferson St",
    "sg:city":"Everett",
    "sg:classifiers":[
        {
            "category":"Social Services",
            "type":"Services"
        }
    ],
    "sg:phone":"+1 206 769 2216",
    "sg:postcode":"98221",
    "sg:province":"WA",
    "wof:name":"Watt Khemararam Snohomish",
    "wof:placetype":"venue"
},
  "geometry": {"coordinates":[-122.604888,48.428129],"type":"Point"}
}