{
  "type": "Feature",
  "properties": {
    "addr:full":"777 108th Ave NE Bellevue WA 98004",
    "addr:housenumber":"777",
    "addr:postcode":"98004",
    "addr:street":"108Th Ave Ne",
    "iso:country":"US",
    "sg:address":"777 108th Ave NE",
    "sg:city":"Bellevue",
    "sg:classifiers":[
        {
            "category":"Professional",
            "type":"Services"
        }
    ],
    "sg:phone":"+1 425 450 4257",
    "sg:postcode":"98004",
    "sg:province":"WA",
    "wof:name":"16116 140th Place Ne LLC",
    "wof:placetype":"venue"
},
  "geometry": {"coordinates":[-122.196387,47.615708],"type":"Point"}
}