{
  "type": "Feature",
  "properties": {
    "addr:full":"212 W Winesap St Tonasket WA 98855",
    "addr:housenumber":"212",
    "addr:postcode":"98855",
    "addr:street":"W Winesap St",
    "iso:country":"US",
    "sg:address":"212 W Winesap St",
    "sg:city":"Tonasket",
    "sg:classifiers":[
        {
            "category":"Freight",
            "type":"Transportation"
        }
    ],
    "sg:phone":"+1 509 486 2201",
    "sg:postcode":"98855",
    "sg:province":"WA",
    "sg:tags":[
        "trucking"
    ],
    "wof:name":"David Hannah Transport Inc",
    "wof:placetype":"venue"
},
  "geometry": {"coordinates":[-119.437816,48.711594],"type":"Point"}
}