{
  "type": "Feature",
  "properties": {
    "addr:full":"15220 SE 272nd St Ste G Kent WA 98042",
    "addr:postcode":"15220;98042",
    "addr:street":"Se 272Nd St Ste G",
    "iso:country":"US",
    "sg:address":"15220 SE 272nd St Ste G",
    "sg:city":"Kent",
    "sg:classifiers":[
        {
            "category":"Personal",
            "subcategory":"Beauty Salon",
            "type":"Services"
        },
        {
            "category":"Personal",
            "subcategory":"Hair Removal",
            "type":"Services"
        }
    ],
    "sg:phone":"+1 253 236 0530",
    "sg:postcode":"98042",
    "sg:province":"WA",
    "sg:website":"http://seattle.citysearch.com/profile/external/653715660/kent_wa/elle_a_clinical_day_spa.html?publisher=yellowpages&reference_id=15&placement=ypwebsitemip",
    "wof:name":"Elle- A Clinical Day Spa",
    "wof:placetype":"venue"
},
  "geometry": {"coordinates":[-122.138311,47.358001],"type":"Point"}
}