{
  "type": "Feature",
  "properties": {
    "addr:full":"4343 Roosevelt Way NE Seattle WA 98105",
    "addr:housenumber":"4343",
    "addr:postcode":"98105",
    "addr:street":"Roosevelt Way Ne",
    "iso:country":"US",
    "sg:address":"4343 Roosevelt Way NE",
    "sg:city":"Seattle",
    "sg:classifiers":[
        {
            "category":"Real Estate",
            "subcategory":"Real Estate Agent",
            "type":"Services"
        }
    ],
    "sg:phone":"+1 206 547 9669",
    "sg:postcode":"98105",
    "sg:province":"WA",
    "wof:name":"Johnson Afg Real Estate",
    "wof:placetype":"venue"
},
  "geometry": {"coordinates":[-122.317824,47.659505],"type":"Point"}
}