{
  "type": "Feature",
  "properties": {
    "addr:full":"1729 12th Ave Seattle WA 98122",
    "addr:housenumber":"1729",
    "addr:postcode":"98122",
    "addr:street":"12Th Ave",
    "iso:country":"US",
    "sg:address":"1729 12th Ave",
    "sg:city":"Seattle",
    "sg:classifiers":[
        {
            "category":"Real Estate",
            "subcategory":"Real Estate Operator",
            "type":"Services"
        }
    ],
    "sg:phone":"+1 206 328 2380",
    "sg:postcode":"98122",
    "sg:province":"WA",
    "sg:tags":[
        "apartment"
    ],
    "wof:name":"Roosevelt Apt",
    "wof:placetype":"venue"
},
  "geometry": {"coordinates":[-122.317001,47.616798],"type":"Point"}
}