{
  "type": "Feature",
  "properties": {
    "addr:full":"3113 199th Ave SE Sammamish WA 98075",
    "addr:housenumber":"3113",
    "addr:postcode":"98075",
    "addr:street":"199Th Ave Se",
    "iso:country":"US",
    "sg:address":"3113 199th Ave SE",
    "sg:city":"Sammamish",
    "sg:classifiers":[
        {
            "category":"Professional",
            "subcategory":"Management & Consulting",
            "type":"Services"
        }
    ],
    "sg:phone":"+1 425 557 5495",
    "sg:postcode":"98075",
    "sg:province":"WA",
    "wof:name":"Creative Impact Group",
    "wof:placetype":"venue"
},
  "geometry": {"coordinates":[-122.074286,47.582592],"type":"Point"}
}