{
  "type": "Feature",
  "properties": {
    "addr:full":"20412 NE 35th St Sammamish WA 98074",
    "addr:housenumber":"20412",
    "addr:postcode":"98074",
    "addr:street":"Ne 35Th St",
    "iso:country":"US",
    "sg:address":"20412 NE 35th St",
    "sg:city":"Sammamish",
    "sg:classifiers":[
        {
            "category":"Personal",
            "subcategory":"Barber",
            "type":"Services"
        }
    ],
    "sg:phone":"+1 425 868 4408",
    "sg:postcode":"98074",
    "sg:province":"WA",
    "sg:tags":[
        "shop"
    ],
    "wof:name":"Nancy C Barber Rn",
    "wof:placetype":"venue"
},
  "geometry": {"coordinates":[-122.066885,47.641709],"type":"Point"}
}