{
  "type": "Feature",
  "properties": {
    "iso:country":"US",
    "sg:address":"881 Harrison Ave",
    "sg:city":"Blaine",
    "sg:classifiers":[
        {
            "category":"Social Services",
            "subcategory":"Child Care",
            "type":"Services"
        }
    ],
    "sg:phone":"+1 360 332 4029",
    "sg:postcode":"98230",
    "sg:province":"WA",
    "sg:tags":[
        "day"
    ],
    "wof:name":"Lindas Little Ones",
    "wof:placetype":"venue"
},
  "geometry": {"coordinates":[-122.746459,48.99211],"type":"Point"}
}