{
  "type": "Feature",
  "properties": {
    "addr:full":"1823 24th Ave E Seattle WA 98112",
    "addr:housenumber":"1823",
    "addr:postcode":"98112",
    "addr:street":"24Th Ave E",
    "iso:country":"US",
    "sg:address":"1823 24th Ave E",
    "sg:city":"Seattle",
    "sg:classifiers":[
        {
            "category":"Real Estate",
            "subcategory":"Real Estate Operator",
            "type":"Services"
        }
    ],
    "sg:phone":"+1 206 726 5266",
    "sg:postcode":"98112",
    "sg:province":"WA",
    "sg:tags":[
        "building",
        "nonresidential"
    ],
    "wof:name":"Praestant Property LLC",
    "wof:placetype":"venue"
},
  "geometry": {"coordinates":[-122.30161200000001,47.636655],"type":"Point"}
}