{
  "type": "Feature",
  "properties": {
    "addr:full":"2607 W Blaine St Seattle WA 98199",
    "addr:housenumber":"2607",
    "addr:postcode":"98199",
    "addr:street":"W Blaine St",
    "iso:country":"US",
    "sg:address":"2607 W Blaine St",
    "sg:city":"Seattle",
    "sg:classifiers":[
        {
            "category":"Home & Garden",
            "subcategory":"Building Materials",
            "type":"Retail Goods"
        }
    ],
    "sg:phone":"+1 206 285 5775",
    "sg:postcode":"98199",
    "sg:province":"WA",
    "wof:name":"Steven C Weiss",
    "wof:placetype":"venue"
},
  "geometry": {"coordinates":[-122.391324,47.63502],"type":"Point"}
}