{
  "type": "Feature",
  "properties": {
    "iso:country":"US",
    "sg:address":"4722 NE 26th Ave",
    "sg:city":"Vancouver",
    "sg:classifiers":[
        {
            "category":"Health Services",
            "subcategory":"Nursing And Care Facility",
            "type":"Services"
        }
    ],
    "sg:phone":"+1 360 993 7734",
    "sg:postcode":"98663",
    "sg:province":"WA",
    "wof:name":"Lovely Adult Family Home",
    "wof:placetype":"venue"
},
  "geometry": {"coordinates":[-122.644355,45.656611],"type":"Point"}
}