{
  "type": "Feature",
  "properties": {
    "addr:full":"6659 Kimball Dr Gig Harbor WA 98335",
    "addr:housenumber":"6659",
    "addr:postcode":"98335",
    "addr:street":"Kimball Dr",
    "iso:country":"US",
    "sg:address":"6659 Kimball Dr",
    "sg:city":"Gig Harbor",
    "sg:classifiers":[
        {
            "category":"Professional",
            "subcategory":"Management & Consulting",
            "type":"Services"
        }
    ],
    "sg:phone":"+1 253 851 8561",
    "sg:postcode":"98335",
    "sg:province":"WA",
    "sg:tags":[
        "marketing"
    ],
    "wof:name":"Marketing Support Srvcs Agency",
    "wof:placetype":"venue"
},
  "geometry": {"coordinates":[-122.586313,47.317682],"type":"Point"}
}