{
  "type": "Feature",
  "properties": {
    "addr:full":"1 16th St NE Auburn WA 98002",
    "addr:housenumber":"1",
    "addr:postcode":"98002",
    "addr:street":"16Th St Ne",
    "iso:country":"US",
    "sg:address":"1 16th St NE",
    "sg:city":"Auburn",
    "sg:classifiers":[
        {
            "category":"Travel",
            "subcategory":"Hotels & Motels",
            "type":"Entertainment"
        }
    ],
    "sg:phone":"+1 253 333 8888",
    "sg:postcode":"98002",
    "sg:province":"WA",
    "wof:name":"Pacific Nw Hospitality Develop",
    "wof:placetype":"venue"
},
  "geometry": {"coordinates":[-122.230812,47.323109],"type":"Point"}
}