{
  "type": "Feature",
  "properties": {
    "iso:country":"US",
    "sg:address":"161 Weatherstone Rd",
    "sg:city":"Omak",
    "sg:classifiers":[
        {
            "category":"Shopping",
            "subcategory":"Discount & Variety Stores",
            "type":"Retail Goods"
        }
    ],
    "sg:phone":"+1 509 422 4474",
    "sg:postcode":"98841",
    "sg:province":"WA",
    "sg:tags":[
        "merchandise",
        "general"
    ],
    "wof:name":"Sheris Treasures",
    "wof:placetype":"venue"
},
  "geometry": {"coordinates":[-119.560136,48.428219],"type":"Point"}
}