{
  "type": "Feature",
  "properties": {
    "iso:country":"US",
    "sg:address":"424 N Fruitland St",
    "sg:city":"Kennewick",
    "sg:classifiers":[
        {
            "category":"Building & Trades",
            "subcategory":"Construction",
            "type":"Services"
        }
    ],
    "sg:phone":"+1 509 582 2597",
    "sg:postcode":"99336",
    "sg:province":"WA",
    "sg:tags":[
        "contractor"
    ],
    "wof:name":"All West Floor Covering",
    "wof:placetype":"venue"
},
  "geometry": {"coordinates":[-119.126116,46.214038],"type":"Point"}
}