{
  "type": "Feature",
  "properties": {
    "iso:country":"US",
    "sg:address":"4000 Aurora Ave N",
    "sg:city":"Seattle",
    "sg:classifiers":[
        {
            "category":"Social Services",
            "type":"Services"
        }
    ],
    "sg:phone":"+1 206 841 5305",
    "sg:postcode":"98103",
    "sg:province":"WA",
    "wof:name":"Mutual Interest",
    "wof:placetype":"venue"
},
  "geometry": {"coordinates":[-122.34724900000001,47.656605],"type":"Point"}
}