{
  "type": "Feature",
  "properties": {
    "addr:full":"2507 N 45th St Seattle WA 98103",
    "addr:housenumber":"2507",
    "addr:postcode":"98103",
    "addr:street":"N 45Th St",
    "iso:country":"US",
    "sg:address":"2507 N 45th St",
    "sg:city":"Seattle",
    "sg:classifiers":[
        {
            "category":"Health Services",
            "subcategory":"Dentist",
            "type":"Services"
        }
    ],
    "sg:phone":"+1 206 633 4035",
    "sg:postcode":"98103",
    "sg:province":"WA",
    "sg:website":"www.drtulaykent.com",
    "wof:name":"Tulay Kent, DDS",
    "wof:placetype":"venue"
},
  "geometry": {"coordinates":[-122.328931,47.661372],"type":"Point"}
}