{
  "type": "Feature",
  "properties": {
    "addr:full":"900 E Pine St Seattle WA 98122",
    "addr:housenumber":"900",
    "addr:postcode":"98122",
    "addr:street":"E Pine St",
    "iso:country":"US",
    "sg:address":"900 E Pine St",
    "sg:city":"Seattle",
    "sg:classifiers":[
        {
            "category":"Museum",
            "type":"Entertainment"
        }
    ],
    "sg:phone":"+1 206 328 9686",
    "sg:postcode":"98122",
    "sg:province":"WA",
    "wof:name":"Seattle Asian Art Museum",
    "wof:placetype":"venue"
},
  "geometry": {"coordinates":[-122.320801,47.615238],"type":"Point"}
}