{
  "type": "Feature",
  "properties": {
    "addr:full":"1414 E Pierce St Union Gap WA 98903",
    "addr:housenumber":"1414",
    "addr:postcode":"98903",
    "addr:street":"E Pierce St",
    "iso:country":"US",
    "sg:address":"1414 E Pierce St",
    "sg:city":"Union Gap",
    "sg:classifiers":[
        {
            "category":"Freight",
            "type":"Transportation"
        }
    ],
    "sg:phone":"+1 509 248 2928",
    "sg:postcode":"98903",
    "sg:province":"WA",
    "sg:tags":[
        "heavy",
        "duty",
        "distance",
        "hauling",
        "long",
        "trucking"
    ],
    "wof:name":"Carrell Crane & Heavy Hauling",
    "wof:placetype":"venue"
},
  "geometry": {"coordinates":[-120.480458,46.574007],"type":"Point"}
}