{
  "type": "Feature",
  "properties": {
    "iso:country":"US",
    "sg:address":"27602 N Monroe Rd",
    "sg:city":"Deer Park",
    "sg:classifiers":[
        {
            "category":"Farming",
            "subcategory":"Farm",
            "type":"Manufacturing & Wholesale Goods"
        }
    ],
    "sg:phone":"+1 509 276 9444",
    "sg:postcode":"99006",
    "sg:province":"WA",
    "sg:tags":[
        "crop",
        "general"
    ],
    "wof:name":"Spur of Moment Farms LLC",
    "wof:placetype":"venue"
},
  "geometry": {"coordinates":[-117.498017,47.906654],"type":"Point"}
}