{
  "type": "Feature",
  "properties": {
    "addr:full":"7011 280th St NW Stanwood WA 98292",
    "addr:housenumber":"7011",
    "addr:postcode":"98292",
    "addr:street":"280Th St Nw",
    "iso:country":"US",
    "sg:address":"7011 280th St NW",
    "sg:city":"Stanwood",
    "sg:classifiers":[
        {
            "category":"Building & Trades",
            "subcategory":"Construction",
            "type":"Services"
        }
    ],
    "sg:phone":"+1 360 629 4686",
    "sg:postcode":"98292",
    "sg:province":"WA",
    "sg:tags":[
        "home",
        "general",
        "contractor"
    ],
    "wof:name":"Gene Eidsness Construction",
    "wof:placetype":"venue"
},
  "geometry": {"coordinates":[-122.330195,48.250246],"type":"Point"}
}