{
  "type": "Feature",
  "properties": {
    "addr:full":"24121 Locust Way Bothell WA 98021",
    "addr:housenumber":"24121",
    "addr:postcode":"98021",
    "addr:street":"Locust Way",
    "iso:country":"US",
    "sg:address":"24121 Locust Way",
    "sg:city":"Bothell",
    "sg:classifiers":[
        {
            "category":"Professional",
            "subcategory":"Business Services",
            "type":"Services"
        }
    ],
    "sg:phone":"+1 425 806 0063",
    "sg:postcode":"98021",
    "sg:province":"WA",
    "sg:tags":[
        "consultant",
        "coach"
    ],
    "wof:name":"Townsend Consulting",
    "wof:placetype":"venue"
},
  "geometry": {"coordinates":[-122.257975,47.779418],"type":"Point"}
}