{
  "type": "Feature",
  "properties": {
    "addr:full":"21820 9th Ave SE Bothell WA 98021",
    "addr:housenumber":"21820",
    "addr:postcode":"98021",
    "addr:street":"9Th Ave Se",
    "iso:country":"US",
    "sg:address":"21820 9th Ave SE",
    "sg:city":"Bothell",
    "sg:classifiers":[
        {
            "category":"Professional",
            "type":"Services"
        }
    ],
    "sg:phone":"+1 425 486 9509",
    "sg:postcode":"98021",
    "sg:province":"WA",
    "wof:name":"Val Flake Kowallis",
    "wof:placetype":"venue"
},
  "geometry": {"coordinates":[-122.22085199999999,47.79849],"type":"Point"}
}