{
  "type": "Feature",
  "properties": {
    "addr:full":"1551 NW 54th St Ste 101 Seattle WA 98107",
    "addr:housenumber":"1551",
    "addr:postcode":"98107",
    "addr:street":"Nw 54Th St Ste 101",
    "iso:country":"US",
    "sg:address":"1551 NW 54th St Ste 101",
    "sg:city":"Seattle",
    "sg:classifiers":[
        {
            "category":"Health Services",
            "subcategory":"Clinic",
            "type":"Services"
        },
        {
            "category":"Personal",
            "subcategory":"Hair Removal",
            "type":"Services"
        },
        {
            "category":"Personal",
            "subcategory":"Skin Care",
            "type":"Services"
        }
    ],
    "sg:phone":"+1 206 525 0903",
    "sg:postcode":"98107",
    "sg:province":"WA",
    "sg:tags":[
        "spa",
        "medical",
        "laser"
    ],
    "sg:website":"www.skinmdseattle.com/",
    "wof:name":"SkinMD",
    "wof:placetype":"venue"
},
  "geometry": {"coordinates":[-122.378201,47.667686],"type":"Point"}
}