{
  "type": "Feature",
  "properties": {
    "addr:full":"226 Main Ave E Soap Lake WA 98851",
    "addr:housenumber":"226",
    "addr:postcode":"98851",
    "addr:street":"Main Ave E Soap",
    "iso:country":"US",
    "sg:address":"226 Main Ave E",
    "sg:city":"Soap Lake",
    "sg:classifiers":[
        {
            "category":"Travel",
            "subcategory":"Hotels & Motels",
            "type":"Entertainment"
        }
    ],
    "sg:phone":"+1 509 246 1132",
    "sg:postcode":"98851",
    "sg:province":"WA",
    "sg:website":"www.innsoaplake.com",
    "wof:name":"Inn At Soap Lake",
    "wof:placetype":"venue"
},
  "geometry": {"coordinates":[-119.486878,47.389433],"type":"Point"}
}