{
  "type": "Feature",
  "properties": {
    "addr:full":"1104 1st St Steilacoom WA 98388",
    "addr:housenumber":"1104",
    "addr:postcode":"98388",
    "addr:street":"1St St",
    "iso:country":"US",
    "sg:address":"1104 1st St",
    "sg:city":"Steilacoom",
    "sg:classifiers":[
        {
            "category":"Professional",
            "subcategory":"Business Services",
            "type":"Services"
        }
    ],
    "sg:phone":"+1 253 582 4988",
    "sg:postcode":"98388",
    "sg:province":"WA",
    "sg:tags":[
        "consultant",
        "coach"
    ],
    "wof:name":"Kelly Enterprises",
    "wof:placetype":"venue"
},
  "geometry": {"coordinates":[-122.61200100000001,47.162049],"type":"Point"}
}