{
  "type": "Feature",
  "properties": {
    "addr:full":"501 Annahat Rd Toppenish WA 98948",
    "addr:housenumber":"501",
    "addr:postcode":"98948",
    "addr:street":"Annahat Rd",
    "iso:country":"US",
    "sg:address":"501 Annahat Rd",
    "sg:city":"Toppenish",
    "sg:classifiers":[
        {
            "category":"Government",
            "subcategory":"Office",
            "type":"Public Place"
        }
    ],
    "sg:phone":"+1 509 865 4089",
    "sg:postcode":"98948",
    "sg:province":"WA",
    "sg:tags":[
        "village"
    ],
    "wof:name":"Toppenish Sewage Treatment",
    "wof:placetype":"venue"
},
  "geometry": {"coordinates":[-120.282899,46.367707],"type":"Point"}
}