{
  "type": "Feature",
  "properties": {
    "addr:full":"32136 118th Ave SE Auburn WA 98092",
    "addr:housenumber":"32136",
    "addr:postcode":"98092",
    "addr:street":"118Th Ave Se",
    "iso:country":"US",
    "sg:address":"32136 118th Ave SE",
    "sg:city":"Auburn",
    "sg:classifiers":[
        {
            "category":"Professional",
            "subcategory":"Business Services",
            "type":"Services"
        }
    ],
    "sg:phone":"+1 253 939 7333",
    "sg:postcode":"98092",
    "sg:province":"WA",
    "wof:name":"Qb Enterprises",
    "wof:placetype":"venue"
},
  "geometry": {"coordinates":[-122.184405,47.313752],"type":"Point"}
}