{
  "type": "Feature",
  "properties": {
    "addr:full":"2926 Yelm Hwy SE Olympia WA 98501",
    "addr:housenumber":"2926",
    "addr:postcode":"98501",
    "addr:street":"Yelm Hwy Se",
    "iso:country":"US",
    "sg:address":"2926 Yelm Hwy SE",
    "sg:city":"Olympia",
    "sg:classifiers":[
        {
            "category":"Manufacturing",
            "subcategory":"Motor Vehicles & Parts",
            "type":"Manufacturing & Wholesale Goods"
        }
    ],
    "sg:phone":"+1 360 491 6197",
    "sg:postcode":"98501",
    "sg:province":"WA",
    "sg:tags":[
        "m",
        "architectural",
        "mfg"
    ],
    "wof:name":"Setina Manufacturing",
    "wof:placetype":"venue"
},
  "geometry": {"coordinates":[-122.857035,47.001175],"type":"Point"}
}