{
  "type": "Feature",
  "properties": {
    "addr:full":"1932 1st Ave Seattle WA 98101",
    "addr:housenumber":"1932",
    "addr:postcode":"98101",
    "addr:street":"1St Ave",
    "iso:country":"US",
    "sg:address":"1932 1st Ave",
    "sg:city":"Seattle",
    "sg:classifiers":[
        {
            "category":"Building & Trades",
            "subcategory":"Landscaping Services",
            "type":"Services"
        }
    ],
    "sg:phone":"+1 206 443 1174",
    "sg:postcode":"98101",
    "sg:province":"WA",
    "sg:tags":[
        "designer",
        "landscape"
    ],
    "wof:name":"Gail Staeger Assoc",
    "wof:placetype":"venue"
},
  "geometry": {"coordinates":[-122.342277,47.61087],"type":"Point"}
}