{
  "type": "Feature",
  "properties": {
    "addr:full":"822 N 1st St Yakima WA 98901",
    "addr:housenumber":"822",
    "addr:postcode":"98901",
    "addr:street":"N 1St St",
    "iso:country":"US",
    "sg:address":"822 N 1st St",
    "sg:city":"Yakima",
    "sg:classifiers":[
        {
            "category":"Restaurant",
            "type":"Food & Drink"
        }
    ],
    "sg:phone":"+1 509 453 7500",
    "sg:postcode":"98901",
    "sg:province":"WA",
    "sg:tags":[
        "asian",
        "pan",
        "japanese"
    ],
    "wof:name":"New York Teriyaki",
    "wof:placetype":"venue"
},
  "geometry": {"coordinates":[-120.51109599999999,46.612518],"type":"Point"}
}