{
  "type": "Feature",
  "properties": {
    "addr:full":"505 S Race St Port Angeles WA 98362",
    "addr:housenumber":"505",
    "addr:postcode":"98362",
    "addr:street":"S Race St",
    "iso:country":"US",
    "sg:address":"505 S Race St",
    "sg:city":"Port Angeles",
    "sg:classifiers":[
        {
            "category":"Organizations",
            "subcategory":"Religious Organization",
            "type":"Services"
        }
    ],
    "sg:phone":"+1 360 452 7078",
    "sg:postcode":"98362",
    "sg:province":"WA",
    "wof:name":"First Church Of God",
    "wof:placetype":"venue"
},
  "geometry": {"coordinates":[-123.4221,48.1094],"type":"Point"}
}