{
  "type": "Feature",
  "properties": {
    "addr:full":"10626 10th Ave Ct S Tacoma WA 98444",
    "addr:housenumber":"10626",
    "addr:postcode":"98444",
    "addr:street":"10Th Ave Ct S",
    "iso:country":"US",
    "sg:address":"10626 10th Ave Ct S",
    "sg:city":"Tacoma",
    "sg:classifiers":[
        {
            "category":"Retail",
            "subcategory":"Laundry & Dry Cleaning",
            "type":"Services"
        }
    ],
    "sg:phone":"+1 253 536 6552",
    "sg:postcode":"98444",
    "sg:province":"WA",
    "sg:tags":[
        "cleaners",
        "rug",
        "carpet"
    ],
    "wof:name":"D & F Dry Cleaning",
    "wof:placetype":"venue"
},
  "geometry": {"coordinates":[-122.44820799999999,47.16433],"type":"Point"}
}