{
  "type": "Feature",
  "properties": {
    "addr:full":"15408 NE 29th Ave Vancouver WA 98686",
    "addr:housenumber":"15408",
    "addr:postcode":"98686",
    "addr:street":"Ne 29Th Ave",
    "iso:country":"US",
    "sg:address":"15408 NE 29th Ave",
    "sg:city":"Vancouver",
    "sg:classifiers":[
        {
            "category":"Manufacturing",
            "subcategory":"Printing",
            "type":"Manufacturing & Wholesale Goods"
        }
    ],
    "sg:phone":"+1 360 576 1523",
    "sg:postcode":"98686",
    "sg:province":"WA",
    "sg:tags":[
        "screen",
        "commercial"
    ],
    "wof:name":"Shiloh Designs",
    "wof:placetype":"venue"
},
  "geometry": {"coordinates":[-122.641087,45.733819],"type":"Point"}
}