{
  "type": "Feature",
  "properties": {
    "addr:full":"27327 SE 22nd Way Sammamish WA 98075",
    "addr:postcode":"27327;98075",
    "addr:street":"Se 22Nd Way",
    "iso:country":"US",
    "sg:address":"27327 SE 22nd Way",
    "sg:city":"Sammamish",
    "sg:classifiers":[
        {
            "category":"Shopping",
            "subcategory":"Hobbies, Toys, & Games",
            "type":"Retail Goods"
        }
    ],
    "sg:phone":"+1 425 391 2571",
    "sg:postcode":"98075",
    "sg:province":"WA",
    "wof:name":"Suzanne Ruth Grabner",
    "wof:placetype":"venue"
},
  "geometry": {"coordinates":[-121.97505200000001,47.588649],"type":"Point"}
}