{
  "type": "Feature",
  "properties": {
    "addr:full":"3722 N Flora Rd Spokane Valley WA 99216",
    "addr:housenumber":"3722",
    "addr:postcode":"99216",
    "addr:street":"N Flora Rd",
    "iso:country":"US",
    "sg:address":"3722 N Flora Rd",
    "sg:city":"Spokane Valley",
    "sg:classifiers":[
        {
            "category":"Building & Trades",
            "subcategory":"Construction",
            "type":"Services"
        }
    ],
    "sg:phone":"+1 509 922 6674",
    "sg:postcode":"99216",
    "sg:province":"WA",
    "sg:tags":[
        "general",
        "contractor"
    ],
    "wof:name":"Red Diamond Construction Inc",
    "wof:placetype":"venue"
},
  "geometry": {"coordinates":[-117.175237,47.692701],"type":"Point"}
}