{
  "type": "Feature",
  "properties": {
    "addr:full":"13905 E 41st Ct Veradale WA 99037",
    "addr:housenumber":"13905",
    "addr:postcode":"99037",
    "addr:street":"E 41St Ct",
    "iso:country":"US",
    "sg:address":"13905 E 41st Ct",
    "sg:city":"Veradale",
    "sg:classifiers":[
        {
            "category":"Retail",
            "subcategory":"Repair Shop",
            "type":"Services"
        }
    ],
    "sg:phone":"+1 509 280 0733",
    "sg:postcode":"99037",
    "sg:province":"WA",
    "sg:tags":[
        "related"
    ],
    "wof:name":"Lyle Olson Irrigation",
    "wof:placetype":"venue"
},
  "geometry": {"coordinates":[-117.216399,47.61813],"type":"Point"}
}