{
  "type": "Feature",
  "properties": {
    "addr:full":"201 160th St S Spanaway WA 98387",
    "addr:housenumber":"201",
    "addr:postcode":"98387",
    "addr:street":"160Th St S",
    "iso:country":"US",
    "sg:address":"201 160th St S",
    "sg:city":"Spanaway",
    "sg:classifiers":[
        {
            "category":"Banks & Credit Unions",
            "subcategory":"Bank",
            "type":"Services"
        }
    ],
    "sg:phone":"+1 253 531 5277",
    "sg:postcode":"98387",
    "sg:province":"WA",
    "sg:tags":[
        "mortgage"
    ],
    "wof:name":"All Fund Mortgage",
    "wof:placetype":"venue"
},
  "geometry": {"coordinates":[-122.437535,47.11181],"type":"Point"}
}