{
  "type": "Feature",
  "properties": {
    "addr:full":"5613 Emerald St SE Lacey WA 98513",
    "addr:housenumber":"5613",
    "addr:postcode":"98513",
    "addr:street":"Emerald St Se",
    "iso:country":"US",
    "sg:address":"5613 Emerald St SE",
    "sg:city":"Lacey",
    "sg:classifiers":[
        {
            "category":"Building & Trades",
            "subcategory":"Cleaning & Sanitation",
            "type":"Services"
        }
    ],
    "sg:phone":"+1 360 459 4802",
    "sg:postcode":"98513",
    "sg:province":"WA",
    "sg:tags":[
        "janitor"
    ],
    "wof:name":"G B Svc",
    "wof:placetype":"venue"
},
  "geometry": {"coordinates":[-122.803667,46.998125],"type":"Point"}
}