{
  "type": "Feature",
  "properties": {
    "addr:full":"2219 E 4th Ave Port Angeles WA 98362",
    "addr:housenumber":"2219",
    "addr:postcode":"98362",
    "addr:street":"E 4Th Ave",
    "iso:country":"US",
    "sg:address":"2219 E 4th Ave",
    "sg:city":"Port Angeles",
    "sg:classifiers":[
        {
            "category":"Farming",
            "subcategory":"Livestock Farm",
            "type":"Manufacturing & Wholesale Goods"
        }
    ],
    "sg:phone":"+1 360 457 1637",
    "sg:postcode":"98362",
    "sg:province":"WA",
    "sg:tags":[
        "bearing",
        "fur",
        "animal"
    ],
    "wof:name":"P C S Pets",
    "wof:placetype":"venue"
},
  "geometry": {"coordinates":[-123.394992,48.111885],"type":"Point"}
}