{
  "type": "Feature",
  "properties": {
    "addr:full":"8525 S 121st St Seattle WA 98178",
    "addr:housenumber":"8525",
    "addr:postcode":"98178",
    "addr:street":"S 121St St",
    "iso:country":"US",
    "sg:address":"8525 S 121st St",
    "sg:city":"Seattle",
    "sg:classifiers":[
        {
            "category":"Retail",
            "subcategory":"Repair Shop",
            "type":"Services"
        }
    ],
    "sg:phone":"+1 206 235 1788",
    "sg:postcode":"98178",
    "sg:province":"WA",
    "sg:tags":[
        "refrigeration"
    ],
    "wof:name":"Tins Refrigeration Repair",
    "wof:placetype":"venue"
},
  "geometry": {"coordinates":[-122.223271,47.494541],"type":"Point"}
}