{
  "type": "Feature",
  "properties": {
    "addr:full":"11114 SE 219th Pl Kent WA 98031",
    "addr:postcode":"11114;98031",
    "addr:street":"Se 219Th Pl",
    "iso:country":"US",
    "sg:address":"11114 SE 219th Pl",
    "sg:city":"Kent",
    "sg:classifiers":[
        {
            "category":"Food & Beverages",
            "subcategory":"Groceries & Convenience Stores",
            "type":"Retail Goods"
        }
    ],
    "sg:phone":"+1 253 852 4966",
    "sg:postcode":"98031",
    "sg:province":"WA",
    "wof:name":"Benson Mart",
    "wof:placetype":"venue"
},
  "geometry": {"coordinates":[-122.19282699999999,47.405434],"type":"Point"}
}