{
  "type": "Feature",
  "properties": {
    "addr:full":"2192 Green Mountain Rd Kalama WA 98625",
    "addr:housenumber":"2192",
    "addr:postcode":"98625",
    "addr:street":"Green Mountain Rd",
    "iso:country":"US",
    "sg:address":"2192 Green Mountain Rd",
    "sg:city":"Kalama",
    "sg:classifiers":[
        {
            "category":"Building & Trades",
            "subcategory":"Electrical",
            "type":"Services"
        }
    ],
    "sg:phone":"+1 360 673 2101",
    "sg:postcode":"98625",
    "sg:province":"WA",
    "sg:tags":[
        "electrical",
        "contractor"
    ],
    "wof:name":"Safety Factors Inc",
    "wof:placetype":"venue"
},
  "geometry": {"coordinates":[-122.79528999999999,45.983281],"type":"Point"}
}