{
  "type": "Feature",
  "properties": {
    "addr:full":"3814 Snyder Ln Gig Harbor WA 98335",
    "addr:housenumber":"3814",
    "addr:postcode":"98335",
    "addr:street":"Snyder Ln",
    "iso:country":"US",
    "sg:address":"3814 Snyder Ln",
    "sg:city":"Gig Harbor",
    "sg:classifiers":[
        {
            "category":"Retail",
            "subcategory":"Auto Rental",
            "type":"Services"
        }
    ],
    "sg:phone":"+1 253 858 9644",
    "sg:postcode":"98335",
    "sg:province":"WA",
    "sg:tags":[
        "passenger",
        "leasing",
        "car"
    ],
    "wof:name":"Sound Motion Inc",
    "wof:placetype":"venue"
},
  "geometry": {"coordinates":[-122.590557,47.326955],"type":"Point"}
}