{
  "type": "Feature",
  "properties": {
    "addr:full":"12045 Lakeside Pl NE Seattle WA 98125",
    "addr:housenumber":"12045",
    "addr:postcode":"98125",
    "addr:street":"Lakeside Pl Ne",
    "iso:country":"US",
    "sg:address":"12045 Lakeside Pl NE",
    "sg:city":"Seattle",
    "sg:classifiers":[
        {
            "category":"Manufacturing",
            "subcategory":"Buildings",
            "type":"Manufacturing & Wholesale Goods"
        },
        {
            "category":"Building & Trades",
            "subcategory":"Construction",
            "type":"Services"
        }
    ],
    "sg:phone":"+1 206 306 9080",
    "sg:postcode":"98125",
    "sg:province":"WA",
    "sg:tags":[
        "industrial",
        "system",
        "specialty",
        "builder",
        "heating",
        "contractor",
        "contractors-commercial",
        "home",
        "air conditioning"
    ],
    "wof:name":"Pulcon Inc",
    "wof:placetype":"venue"
},
  "geometry": {"coordinates":[-122.279853,47.717226],"type":"Point"}
}