{
  "type": "Feature",
  "properties": {
    "iso:country":"US",
    "sg:address":"29393 State Rte 410",
    "sg:city":"Buckley",
    "sg:classifiers":[
        {
            "category":"Shopping",
            "subcategory":"Discount & Variety Stores",
            "type":"Retail Goods"
        }
    ],
    "sg:phone":"+1 360 829 5222",
    "sg:postcode":"98321",
    "sg:province":"WA",
    "wof:name":"Multi A Dollar Store",
    "wof:placetype":"venue"
},
  "geometry": {"coordinates":[-122.039845,47.158304],"type":"Point"}
}