{
  "type": "Feature",
  "properties": {
    "addr:full":"1180 Shearwater Ln NW Seabeck WA 98380",
    "addr:housenumber":"1180",
    "addr:postcode":"98380",
    "addr:street":"Shearwater Ln Nw",
    "iso:country":"US",
    "sg:address":"1180 Shearwater Ln NW",
    "sg:city":"Seabeck",
    "sg:classifiers":[
        {
            "category":"Building & Trades",
            "subcategory":"Cleaning & Sanitation",
            "type":"Services"
        }
    ],
    "sg:phone":"+1 360 830 4671",
    "sg:postcode":"98380",
    "sg:province":"WA",
    "sg:tags":[
        "maintenance",
        "cleaners-interior"
    ],
    "wof:name":"Bobs Maintenance & Repair",
    "wof:placetype":"venue"
},
  "geometry": {"coordinates":[-122.854394,47.575251],"type":"Point"}
}