{
  "type": "Feature",
  "properties": {
    "addr:full":"905 E Pike St Seattle WA 98122",
    "addr:housenumber":"905",
    "addr:postcode":"98122",
    "addr:street":"E Pike St",
    "iso:country":"US",
    "sg:address":"905 E Pike St",
    "sg:city":"Seattle",
    "sg:classifiers":[
        {
            "category":"Shopping",
            "subcategory":"Clothing, Apparel, & Fashions",
            "type":"Retail Goods"
        }
    ],
    "sg:phone":"+1 206 324 4092",
    "sg:postcode":"98122",
    "sg:province":"WA",
    "sg:tags":[
        "men's",
        "clothing",
        "accessory",
        "women's"
    ],
    "sg:website":"www.ineedretailtherapy.com/",
    "wof:name":"Retail Therapy",
    "wof:placetype":"venue"
},
  "geometry": {"coordinates":[-122.320999,47.614201],"type":"Point"}
}