{
  "type": "Feature",
  "properties": {
    "iso:country":"US",
    "sg:address":"1306 S Vancouver St",
    "sg:city":"Kennewick",
    "sg:classifiers":[
        {
            "category":"Professional",
            "subcategory":"Management & Consulting",
            "type":"Services"
        }
    ],
    "sg:phone":"+1 509 582 9303",
    "sg:postcode":"99337",
    "sg:province":"WA",
    "sg:tags":[
        "consultant"
    ],
    "wof:name":"Paul Parish Limited",
    "wof:placetype":"venue"
},
  "geometry": {"coordinates":[-119.14841,46.198599],"type":"Point"}
}