{
  "type": "Feature",
  "properties": {
    "addr:full":"7455 N Sutherlin St Spokane WA 99208",
    "addr:housenumber":"7455",
    "addr:postcode":"99208",
    "addr:street":"N Sutherlin St",
    "iso:country":"US",
    "sg:address":"7455 N Sutherlin St",
    "sg:city":"Spokane",
    "sg:classifiers":[
        {
            "category":"Real Estate",
            "subcategory":"Real Estate Agent",
            "type":"Services"
        }
    ],
    "sg:phone":"+1 509 325 2377",
    "sg:postcode":"99208",
    "sg:province":"WA",
    "sg:tags":[
        "operator",
        "broker"
    ],
    "wof:name":"N N Builders & Natioal Ln Jwly",
    "wof:placetype":"venue"
},
  "geometry": {"coordinates":[-117.478089,47.725979],"type":"Point"}
}