{
  "type": "Feature",
  "properties": {
    "addr:full":"12356 Northup Way Ste 100 Bellevue WA 98005",
    "addr:housenumber":"12356",
    "addr:postcode":"98005",
    "addr:street":"Northup Way Ste 100",
    "iso:country":"US",
    "sg:address":"12356 Northup Way Ste 100",
    "sg:city":"Bellevue",
    "sg:classifiers":[
        {
            "category":"Professional",
            "subcategory":"Lawyer & Legal Services",
            "type":"Services"
        }
    ],
    "sg:phone":"+1 425 450 9401",
    "sg:postcode":"98005",
    "sg:province":"WA",
    "wof:name":"Anderson Gordon B Jr",
    "wof:placetype":"venue"
},
  "geometry": {"coordinates":[-122.17600299999999,47.629601],"type":"Point"}
}