{
  "type": "Feature",
  "properties": {
    "addr:full":"14140 NE 200th St Woodinville WA 98072",
    "addr:housenumber":"14140",
    "addr:postcode":"98072",
    "addr:street":"Ne 200Th St",
    "iso:country":"US",
    "sg:address":"14140 NE 200th St",
    "sg:city":"Woodinville",
    "sg:classifiers":[
        {
            "category":"Manufacturing",
            "subcategory":"Tools & Machinery",
            "type":"Manufacturing & Wholesale Goods"
        }
    ],
    "sg:phone":"+1 425 398 8282",
    "sg:postcode":"98072",
    "sg:province":"WA",
    "sg:tags":[
        "peripheral",
        "computer"
    ],
    "sg:website":"www.ioline.com",
    "wof:name":"Ioline Corp",
    "wof:placetype":"venue"
},
  "geometry": {"coordinates":[-122.150693,47.772546],"type":"Point"}
}