{
  "type": "Feature",
  "properties": {
    "addr:full":"3510 Fremont Ave N Seattle WA 98103",
    "addr:housenumber":"3510",
    "addr:postcode":"98103",
    "addr:street":"Fremont Ave N",
    "iso:country":"US",
    "sg:address":"3510 Fremont Ave N",
    "sg:city":"Seattle",
    "sg:classifiers":[
        {
            "category":"Restaurant",
            "type":"Food & Drink"
        }
    ],
    "sg:phone":"+1 206 923 2740",
    "sg:postcode":"98103",
    "sg:province":"WA",
    "sg:tags":[
        "eating"
    ],
    "wof:name":"Mtbb Inc",
    "wof:placetype":"venue"
},
  "geometry": {"coordinates":[-122.34985500000001,47.651268],"type":"Point"}
}