{
  "type": "Feature",
  "properties": {
    "addr:full":"5101 55th Ave S Seattle WA 98118",
    "addr:housenumber":"5101",
    "addr:postcode":"98118",
    "addr:street":"55Th Ave S",
    "iso:country":"US",
    "sg:address":"5101 55th Ave S",
    "sg:city":"Seattle",
    "sg:classifiers":[
        {
            "category":"Building & Trades",
            "subcategory":"Locksmith",
            "type":"Services"
        }
    ],
    "sg:phone":"+1 206 607 0624",
    "sg:postcode":"98118",
    "sg:province":"WA",
    "sg:tags":[
        "key"
    ],
    "wof:name":"24 Hr Emerg A Locksmith",
    "wof:placetype":"venue"
},
  "geometry": {"coordinates":[-122.26486800000001,47.555444],"type":"Point"}
}