{
  "type": "Feature",
  "properties": {
    "addr:full":"8509 Fauntlee Crst SW Seattle WA 98136",
    "addr:housenumber":"8509",
    "addr:postcode":"98136",
    "addr:street":"Fauntlee Crst Sw",
    "iso:country":"US",
    "sg:address":"8509 Fauntlee Crst SW",
    "sg:city":"Seattle",
    "sg:classifiers":[
        {
            "category":"Professional",
            "subcategory":"Business Services",
            "type":"Services"
        }
    ],
    "sg:phone":"+1 206 938 3440",
    "sg:postcode":"98136",
    "sg:province":"WA",
    "wof:name":"Whole Solution LLC",
    "wof:placetype":"venue"
},
  "geometry": {"coordinates":[-122.38683899999999,47.526067],"type":"Point"}
}