{
  "type": "Feature",
  "properties": {
    "addr:full":"701 5th Avenue Seattle WA 98104",
    "addr:housenumber":"701",
    "addr:postcode":"98104",
    "addr:street":"5Th Avenue",
    "iso:country":"US",
    "sg:address":"701 5th Avenue",
    "sg:city":"Seattle",
    "sg:classifiers":[
        {
            "category":"Building & Trades",
            "subcategory":"Construction",
            "type":"Services"
        }
    ],
    "sg:phone":"+1 206 337 2360",
    "sg:postcode":"98104",
    "sg:province":"WA",
    "sg:tags":[
        "conditioning/hvac",
        "installation",
        "heating",
        "solar",
        "air"
    ],
    "sg:website":"www.complete-hvac.com",
    "wof:name":"Complete Furnace Repair and Heat Pump Installation",
    "wof:placetype":"venue"
},
  "geometry": {"coordinates":[-122.33077900000001,47.604828],"type":"Point"}
}