{
  "type": "Feature",
  "properties": {
    "addr:full":"1299 156th Ave NE Ste 135 Bellevue WA 98007",
    "addr:housenumber":"1299",
    "addr:postcode":"98007",
    "addr:street":"156Th Ave Ne Ste 135",
    "iso:country":"US",
    "sg:address":"1299 156th Ave NE Ste 135",
    "sg:city":"Bellevue",
    "sg:classifiers":[
        {
            "category":"Restaurant",
            "type":"Food & Drink"
        }
    ],
    "sg:phone":"+1 425 644 8888",
    "sg:postcode":"98007",
    "sg:province":"WA",
    "sg:tags":[
        "chinese"
    ],
    "sg:website":"www.spicedonline.com/",
    "wof:name":"Spiced",
    "wof:placetype":"venue"
},
  "geometry": {"coordinates":[-122.132435,47.621438],"type":"Point"}
}