{
  "type": "Feature",
  "properties": {
    "addr:full":"7904 NW Fruit Valley Rd Vancouver WA 98665",
    "addr:housenumber":"7904",
    "addr:postcode":"98665",
    "addr:street":"Nw Fruit Valley Rd",
    "iso:country":"US",
    "sg:address":"7904 NW Fruit Valley Rd",
    "sg:city":"Vancouver",
    "sg:classifiers":[
        {
            "category":"Professional",
            "type":"Services"
        }
    ],
    "sg:phone":"+1 360 566 0424",
    "sg:postcode":"98665",
    "sg:province":"WA",
    "wof:name":"Lasting Mem Evnt & Wedd",
    "wof:placetype":"venue"
},
  "geometry": {"coordinates":[-122.693398,45.680695],"type":"Point"}
}