{
  "type": "Feature",
  "properties": {
    "iso:country":"US",
    "sg:address":"928 N 4th Ave",
    "sg:city":"Walla Walla",
    "sg:classifiers":[
        {
            "category":"Wholesale",
            "subcategory":"Auto Parts",
            "type":"Manufacturing & Wholesale Goods"
        }
    ],
    "sg:phone":"+1 509 522 4766",
    "sg:postcode":"99362",
    "sg:province":"WA",
    "sg:tags":[
        "used"
    ],
    "wof:name":"All American Auto Glass",
    "wof:placetype":"venue"
},
  "geometry": {"coordinates":[-118.345913,46.075256],"type":"Point"}
}