{
  "type": "Feature",
  "properties": {
    "iso:country":"US",
    "sg:address":"1622 S Mildred St",
    "sg:city":"Tacoma",
    "sg:classifiers":[
        {
            "category":"Health Services",
            "subcategory":"Doctor",
            "type":"Services"
        }
    ],
    "sg:phone":"+1 253 460 3431",
    "sg:postcode":"98465",
    "sg:province":"WA",
    "sg:tags":[
        "dentist"
    ],
    "wof:name":"James Center Dental Excellence",
    "wof:placetype":"venue"
},
  "geometry": {"coordinates":[-122.52642400000001,47.246031],"type":"Point"}
}