{
  "type": "Feature",
  "properties": {
    "addr:full":"15027 Bel Red Rd Bellevue WA 98007",
    "addr:housenumber":"15027",
    "addr:postcode":"98007",
    "addr:street":"Bel Red Rd",
    "iso:country":"US",
    "sg:address":"15027 Bel Red Rd",
    "sg:city":"Bellevue",
    "sg:classifiers":[
        {
            "category":"Education",
            "subcategory":"School",
            "type":"Public Place"
        }
    ],
    "sg:phone":"+1 425 456 6400",
    "sg:postcode":"98007",
    "sg:province":"WA",
    "sg:website":"www.bsd405.org",
    "wof:name":"Bellevue Public Schools District 405",
    "wof:placetype":"venue"
},
  "geometry": {"coordinates":[-122.139791,47.627112],"type":"Point"}
}