{
  "type": "Feature",
  "properties": {
    "addr:full":"2525 212th Ave SE Sammamish WA 98075",
    "addr:housenumber":"2525",
    "addr:postcode":"98075",
    "addr:street":"212Th Ave Se",
    "iso:country":"US",
    "sg:address":"2525 212th Ave SE",
    "sg:city":"Sammamish",
    "sg:classifiers":[
        {
            "category":"Manufacturing",
            "subcategory":"Glass & Minerals",
            "type":"Manufacturing & Wholesale Goods"
        }
    ],
    "sg:phone":"+1 425 392 8288",
    "sg:postcode":"98075",
    "sg:province":"WA",
    "sg:tags":[
        "cut",
        "mfg"
    ],
    "wof:name":"Kd Slate",
    "wof:placetype":"venue"
},
  "geometry": {"coordinates":[-122.056792,47.585503],"type":"Point"}
}