{
  "type": "Feature",
  "properties": {
    "addr:full":"861 Industry Dr Seattle WA 98188",
    "addr:housenumber":"861",
    "addr:postcode":"98188",
    "addr:street":"Industry Dr",
    "iso:country":"US",
    "sg:address":"861 Industry Dr",
    "sg:city":"Seattle",
    "sg:classifiers":[
        {
            "category":"Building & Trades",
            "subcategory":"Electrical",
            "type":"Services"
        },
        {
            "category":"Wholesale",
            "subcategory":"Electrical",
            "type":"Manufacturing & Wholesale Goods"
        }
    ],
    "sg:phone":"+1 206 575 1962",
    "sg:postcode":"98188",
    "sg:province":"WA",
    "sg:tags":[
        "burglar",
        "alarm",
        "monitoring",
        "system",
        "contractor"
    ],
    "wof:name":"Froula Alarm Systems Inc",
    "wof:placetype":"venue"
},
  "geometry": {"coordinates":[-122.248544,47.450979],"type":"Point"}
}