{
  "type": "Feature",
  "properties": {
    "addr:full":"16022 17th Avenue Ct E Tacoma WA 98445",
    "addr:housenumber":"16022",
    "addr:postcode":"98445",
    "addr:street":"17Th Avenue Ct E",
    "iso:country":"US",
    "sg:address":"16022 17th Avenue Ct E",
    "sg:city":"Tacoma",
    "sg:classifiers":[
        {
            "category":"Professional",
            "subcategory":"Secretarial Services",
            "type":"Services"
        }
    ],
    "sg:phone":"+1 253 536 5824",
    "sg:postcode":"98445",
    "sg:province":"WA",
    "sg:tags":[
        "reporting"
    ],
    "wof:name":"Excel Court Reporting",
    "wof:placetype":"venue"
},
  "geometry": {"coordinates":[-122.40668700000001,47.111158],"type":"Point"}
}