{
  "type": "Feature",
  "properties": {
    "addr:full":"2501 N 45th Street Seattle WA 98103",
    "addr:housenumber":"2501",
    "addr:postcode":"98103",
    "addr:street":"N 45Th Street",
    "iso:country":"US",
    "sg:address":"2501 N 45th Street",
    "sg:city":"Seattle",
    "sg:classifiers":[
        {
            "category":"Health Services",
            "subcategory":"Optometrist",
            "type":"Services"
        }
    ],
    "sg:phone":"+1 206 526 5222",
    "sg:postcode":"98103",
    "sg:province":"WA",
    "wof:name":"Ono Curtis A OD",
    "wof:placetype":"venue"
},
  "geometry": {"coordinates":[-122.328733,47.66148],"type":"Point"}
}