{
  "type": "Feature",
  "properties": {
    "addr:full":"12805 NE 76th St Vancouver WA 98682",
    "addr:housenumber":"12805",
    "addr:postcode":"98682",
    "addr:street":"Ne 76Th St",
    "iso:country":"US",
    "sg:address":"12805 NE 76th St",
    "sg:city":"Vancouver",
    "sg:classifiers":[
        {
            "category":"Manufacturing",
            "subcategory":"Tools & Machinery",
            "type":"Manufacturing & Wholesale Goods"
        }
    ],
    "sg:phone":"+1 360 256 5113",
    "sg:postcode":"98682",
    "sg:province":"WA",
    "sg:tags":[
        "machine",
        "shop",
        "industrial",
        "mfg"
    ],
    "wof:name":"Gary's Machine",
    "wof:placetype":"venue"
},
  "geometry": {"coordinates":[-122.540774,45.677417],"type":"Point"}
}