{
  "type": "Feature",
  "properties": {
    "addr:full":"38306 State Rte 20 Concrete WA 98237",
    "addr:housenumber":"38306",
    "addr:postcode":"98237",
    "addr:street":"State Rte 20",
    "iso:country":"US",
    "sg:address":"38306 State Rte 20",
    "sg:city":"Concrete",
    "sg:classifiers":[
        {
            "category":"Retail",
            "subcategory":"Repair Shop",
            "type":"Services"
        }
    ],
    "sg:phone":"+1 360 826 3411",
    "sg:postcode":"98237",
    "sg:province":"WA",
    "wof:name":"JFK Upholstery",
    "wof:placetype":"venue"
},
  "geometry": {"coordinates":[-121.909138,48.528918],"type":"Point"}
}