{
  "type": "Feature",
  "properties": {
    "addr:full":"1601 5th Avenue Suite 2200 Seattle WA 98101",
    "addr:housenumber":"1601",
    "addr:postcode":"98101",
    "addr:street":"5Th Avenue Suite 2200",
    "iso:country":"US",
    "sg:address":"1601 5th Avenue Suite 2200",
    "sg:city":"Seattle",
    "sg:classifiers":[
        {
            "category":"Professional",
            "subcategory":"Lawyer & Legal Services",
            "type":"Services"
        }
    ],
    "sg:phone":"+1 206 622 3280",
    "sg:postcode":"98101",
    "sg:province":"WA",
    "wof:name":"McNamara Jeffrey C Atty",
    "wof:placetype":"venue"
},
  "geometry": {"coordinates":[-122.33649200000001,47.611745],"type":"Point"}
}