{
  "type": "Feature",
  "properties": {
    "addr:full":"3045 S 150th St Seattle WA 98188",
    "addr:housenumber":"3045",
    "addr:postcode":"98188",
    "addr:street":"S 150Th St",
    "iso:country":"US",
    "sg:address":"3045 S 150th St",
    "sg:city":"Seattle",
    "sg:classifiers":[
        {
            "category":"Building & Trades",
            "subcategory":"Construction",
            "type":"Services"
        }
    ],
    "sg:phone":"+1 206 243 3117",
    "sg:postcode":"98188",
    "sg:province":"WA",
    "sg:tags":[
        "house"
    ],
    "wof:name":"Rodriguez Construction",
    "wof:placetype":"venue"
},
  "geometry": {"coordinates":[-122.29328700000001,47.468744],"type":"Point"}
}