{
  "type": "Feature",
  "properties": {
    "iso:country":"US",
    "sg:address":"610 Bender Ln",
    "sg:city":"Montesano",
    "sg:classifiers":[
        {
            "category":"Manufacturing",
            "subcategory":"Apparel",
            "type":"Manufacturing & Wholesale Goods"
        }
    ],
    "sg:phone":"+1 360 249 4647",
    "sg:postcode":"98563",
    "sg:province":"WA",
    "sg:tags":[
        "textile",
        "product",
        "fabricated",
        "mfg"
    ],
    "wof:name":"Double D Truck Accessory",
    "wof:placetype":"venue"
},
  "geometry": {"coordinates":[-123.58142700000001,46.98654],"type":"Point"}
}