{
  "type": "Feature",
  "properties": {
    "iso:country":"US",
    "sg:address":"4025 Delridge Way SW",
    "sg:city":"Seattle",
    "sg:classifiers":[
        {
            "category":"Food & Beverages",
            "subcategory":"Groceries & Convenience Stores",
            "type":"Retail Goods"
        }
    ],
    "sg:phone":"+1 206 923 0740",
    "sg:postcode":"98106",
    "sg:province":"WA",
    "wof:name":"Metropolitan Market/Queen Anne",
    "wof:placetype":"venue"
},
  "geometry": {"coordinates":[-122.363367,47.567974],"type":"Point"}
}