{
  "type": "Feature",
  "properties": {
    "addr:full":"105 S Meridian Puyallup WA 98371",
    "addr:housenumber":"105",
    "addr:postcode":"98371",
    "addr:street":"S Meridian",
    "iso:country":"US",
    "sg:address":"105 S Meridian",
    "sg:city":"Puyallup",
    "sg:classifiers":[
        {
            "category":"Restaurant",
            "type":"Food & Drink"
        }
    ],
    "sg:phone":"+1 253 840 6252",
    "sg:postcode":"98371",
    "sg:province":"WA",
    "wof:name":"Bubble Island",
    "wof:placetype":"venue"
},
  "geometry": {"coordinates":[-122.293634,47.191012],"type":"Point"}
}