{
  "type": "Feature",
  "properties": {
    "addr:full":"6333 1st Ave S Seattle WA 98108",
    "addr:housenumber":"6333",
    "addr:postcode":"98108",
    "addr:street":"1St Ave S",
    "iso:country":"US",
    "sg:address":"6333 1st Ave S",
    "sg:city":"Seattle",
    "sg:classifiers":[
        {
            "category":"Shopping",
            "subcategory":"Clothing, Apparel, & Fashions",
            "type":"Retail Goods"
        }
    ],
    "sg:phone":"+1 206 447 9860",
    "sg:postcode":"98108",
    "sg:province":"WA",
    "sg:tags":[
        "girls'",
        "clothing"
    ],
    "sg:website":"http://www.design500.com",
    "wof:name":"Design 500",
    "wof:placetype":"venue"
},
  "geometry": {"coordinates":[-122.33426799999999,47.54567],"type":"Point"}
}