{
  "type": "Feature",
  "properties": {
    "addr:full":"336 State Rte 115 Ocean Shores WA 98550",
    "addr:housenumber":"336",
    "addr:postcode":"98550",
    "addr:street":"State Rte 115",
    "iso:country":"US",
    "sg:address":"336 State Rte 115",
    "sg:city":"Ocean Shores",
    "sg:classifiers":[
        {
            "category":"Education",
            "subcategory":"School",
            "type":"Public Place"
        }
    ],
    "sg:phone":"+1 360 289 3888",
    "sg:postcode":"98550",
    "sg:province":"WA",
    "wof:name":"North Beach Sr High School",
    "wof:placetype":"venue"
},
  "geometry": {"coordinates":[-124.16134599999999,47.017354],"type":"Point"}
}