{
  "type": "Feature",
  "properties": {
    "addr:full":"451 3rd Ave NW Ephrata WA 98823",
    "addr:housenumber":"451",
    "addr:postcode":"98823",
    "addr:street":"3Rd Ave Nw",
    "iso:country":"US",
    "sg:address":"451 3rd Ave NW",
    "sg:city":"Ephrata",
    "sg:classifiers":[
        {
            "category":"Education",
            "subcategory":"School",
            "type":"Public Place"
        }
    ],
    "sg:phone":"+1 509 754 4676",
    "sg:postcode":"98823",
    "sg:province":"WA",
    "sg:tags":[
        "elementary"
    ],
    "wof:name":"Grant Elementary School",
    "wof:placetype":"venue"
},
  "geometry": {"coordinates":[-119.55288299999999,47.324745],"type":"Point"}
}