{
  "type": "Feature",
  "properties": {
    "addr:full":"14050 Juanita Dr NE Ste B Bothell WA 98011",
    "addr:housenumber":"14050",
    "addr:postcode":"98011",
    "addr:street":"Juanita Dr Ne Ste B",
    "iso:country":"US",
    "sg:address":"14050 Juanita Dr NE Ste B",
    "sg:city":"Bothell",
    "sg:classifiers":[
        {
            "category":"Health Services",
            "subcategory":"Health Practitioner",
            "type":"Services"
        }
    ],
    "sg:phone":"+1 425 821 3775",
    "sg:postcode":"98011",
    "sg:province":"WA",
    "sg:tags":[
        "therapy",
        "physical"
    ],
    "sg:website":"www.inglewoodphysicaltherapy.com",
    "wof:name":"Inglewood Physical Therapy",
    "wof:placetype":"venue"
},
  "geometry": {"coordinates":[-122.24400300000001,47.726398],"type":"Point"}
}