{
  "type": "Feature",
  "properties": {
    "addr:full":"18104 SE 254th St Kent WA 98042",
    "addr:postcode":"18104;98042",
    "addr:street":"Se 254Th St",
    "iso:country":"US",
    "sg:address":"18104 SE 254th St",
    "sg:city":"Kent",
    "sg:classifiers":[
        {
            "category":"Building & Trades",
            "subcategory":"Construction",
            "type":"Services"
        }
    ],
    "sg:phone":"+1 253 631 6984",
    "sg:postcode":"98042",
    "sg:province":"WA",
    "sg:tags":[
        "excavation",
        "contractor"
    ],
    "wof:name":"D&G Excavating Inc",
    "wof:placetype":"venue"
},
  "geometry": {"coordinates":[-122.10027700000001,47.374948],"type":"Point"}
}