{
  "type": "Feature",
  "properties": {
    "addr:full":"294 Pacific Hwy Bellingham WA 98229",
    "addr:housenumber":"294",
    "addr:postcode":"98229",
    "addr:street":"Pacific Hwy",
    "iso:country":"US",
    "sg:address":"294 Pacific Hwy",
    "sg:city":"Bellingham",
    "sg:classifiers":[
        {
            "category":"Retail",
            "subcategory":"Auto Repair",
            "type":"Services"
        }
    ],
    "sg:phone":"+1 360 733 3857",
    "sg:postcode":"98229",
    "sg:province":"WA",
    "sg:tags":[
        "glass",
        "replacement"
    ],
    "wof:name":"Big V and V",
    "wof:placetype":"venue"
},
  "geometry": {"coordinates":[-122.363589,48.651714],"type":"Point"}
}