{
  "type": "Feature",
  "properties": {
    "addr:full":"438 Beacon Hill Dr Longview WA 98632",
    "addr:housenumber":"438",
    "addr:postcode":"98632",
    "addr:street":"Beacon Hill Dr",
    "iso:country":"US",
    "sg:address":"438 Beacon Hill Dr",
    "sg:city":"Longview",
    "sg:classifiers":[
        {
            "category":"Home & Garden",
            "subcategory":"Home Furnishings",
            "type":"Retail Goods"
        }
    ],
    "sg:phone":"+1 360 423 0129",
    "sg:postcode":"98632",
    "sg:province":"WA",
    "sg:tags":[
        "curtain",
        "made",
        "drapery"
    ],
    "wof:name":"A Plus Window Decor",
    "wof:placetype":"venue"
},
  "geometry": {"coordinates":[-122.93370899999999,46.178257],"type":"Point"}
}