{
  "type": "Feature",
  "properties": {
    "iso:country":"US",
    "sg:address":"1335 NE Terre View Dr",
    "sg:city":"Pullman",
    "sg:classifiers":[
        {
            "category":"Manufacturing",
            "subcategory":"Tools & Machinery",
            "type":"Manufacturing & Wholesale Goods"
        }
    ],
    "sg:phone":"+1 509 335 4047",
    "sg:postcode":"99163",
    "sg:province":"WA",
    "sg:tags":[
        "equipment",
        "veterinarian"
    ],
    "sg:website":"www.abtechnology.com",
    "wof:name":"A B Technology Inc",
    "wof:placetype":"venue"
},
  "geometry": {"coordinates":[-117.16927,46.748003],"type":"Point"}
}