{
  "type": "Feature",
  "properties": {
    "iso:country":"US",
    "sg:address":"900 Olympic Hwy S",
    "sg:city":"Shelton",
    "sg:classifiers":[
        {
            "category":"Autos & Motor Vehicles",
            "subcategory":"Motorcycle Sales",
            "type":"Retail Goods"
        }
    ],
    "sg:phone":"+1 360 427 3478",
    "sg:postcode":"98584",
    "sg:province":"WA",
    "sg:tags":[
        "scooter"
    ],
    "wof:name":"Dirt Cheap Cycle",
    "wof:placetype":"venue"
},
  "geometry": {"coordinates":[-123.10083,47.206471],"type":"Point"}
}