{
  "type": "Feature",
  "properties": {
    "addr:full":"401 W Maple St Mccleary WA 98557",
    "addr:housenumber":"401",
    "addr:postcode":"98557",
    "addr:street":"W Maple St",
    "iso:country":"US",
    "sg:address":"401 W Maple St",
    "sg:city":"Mccleary",
    "sg:classifiers":[
        {
            "category":"Health Services",
            "subcategory":"Nursing And Care Facility",
            "type":"Services"
        }
    ],
    "sg:phone":"+1 360 495 3555",
    "sg:postcode":"98557",
    "sg:province":"WA",
    "sg:tags":[
        "home",
        "convalescent"
    ],
    "sg:website":"www.beehiveretirement.com",
    "wof:name":"Beehive Retirement Ctr",
    "wof:placetype":"venue"
},
  "geometry": {"coordinates":[-123.270448,47.054539],"type":"Point"}
}