{
  "type": "Feature",
  "properties": {
    "addr:full":"1560 N 115th St Seattle WA 98133",
    "addr:housenumber":"1560",
    "addr:postcode":"98133",
    "addr:street":"N 115Th St",
    "iso:country":"US",
    "sg:address":"1560 N 115th St",
    "sg:city":"Seattle",
    "sg:classifiers":[
        {
            "category":"Health Services",
            "subcategory":"Doctor",
            "type":"Services"
        }
    ],
    "sg:phone":"+1 206 365 8252",
    "sg:postcode":"98133",
    "sg:province":"WA",
    "sg:website":"www.pscc.cc",
    "wof:name":"Lane Robert F MD",
    "wof:placetype":"venue"
},
  "geometry": {"coordinates":[-122.339996,47.712299],"type":"Point"}
}