{
  "type": "Feature",
  "properties": {
    "addr:full":"101 E Troxell Rd Oak Harbor WA 98277",
    "addr:housenumber":"101",
    "addr:postcode":"98277",
    "addr:street":"E Troxell Rd",
    "iso:country":"US",
    "sg:address":"101 E Troxell Rd",
    "sg:city":"Oak Harbor",
    "sg:classifiers":[
        {
            "category":"Farming",
            "subcategory":"Nursery",
            "type":"Manufacturing & Wholesale Goods"
        }
    ],
    "sg:phone":"+1 360 675 9472",
    "sg:postcode":"98277",
    "sg:province":"WA",
    "sg:tags":[
        "ornamental"
    ],
    "wof:name":"Christlin Forest",
    "wof:placetype":"venue"
},
  "geometry": {"coordinates":[-122.615004,48.376357],"type":"Point"}
}