{
  "type": "Feature",
  "properties": {
    "addr:full":"3121 Meridian Ave E Puyallup WA 98371",
    "addr:housenumber":"3121",
    "addr:postcode":"98371",
    "addr:street":"Meridian Ave E",
    "iso:country":"US",
    "sg:address":"3121 Meridian Ave E",
    "sg:city":"Puyallup",
    "sg:classifiers":[
        {
            "category":"Retail",
            "subcategory":"Auto Repair",
            "type":"Services"
        }
    ],
    "sg:phone":"+1 253 839 1096",
    "sg:postcode":"98371",
    "sg:province":"WA",
    "sg:tags":[
        "general"
    ],
    "wof:name":"C M Auto Repair",
    "wof:placetype":"venue"
},
  "geometry": {"coordinates":[-122.293898,47.229161],"type":"Point"}
}