{
  "type": "Feature",
  "properties": {
    "addr:full":"410 S Garden St Bellingham WA 98225",
    "addr:housenumber":"410",
    "addr:postcode":"98225",
    "addr:street":"S Garden St",
    "iso:country":"US",
    "sg:address":"410 S Garden St",
    "sg:city":"Bellingham",
    "sg:classifiers":[
        {
            "category":"Shopping",
            "subcategory":"Clothing, Apparel, & Fashions",
            "type":"Retail Goods"
        }
    ],
    "sg:phone":"+1 360 733 2276",
    "sg:postcode":"98225",
    "sg:province":"WA",
    "wof:name":"L H Clothing Co",
    "wof:placetype":"venue"
},
  "geometry": {"coordinates":[-122.49724999999999,48.731814],"type":"Point"}
}