{
  "type": "Feature",
  "properties": {
    "addr:full":"540 Cowin Ln Wapato WA 98951",
    "addr:housenumber":"540",
    "addr:postcode":"98951",
    "addr:street":"Cowin Ln",
    "iso:country":"US",
    "sg:address":"540 Cowin Ln",
    "sg:city":"Wapato",
    "sg:classifiers":[
        {
            "category":"Farming",
            "subcategory":"Orchard",
            "type":"Manufacturing & Wholesale Goods"
        }
    ],
    "sg:phone":"+1 509 877 5788",
    "sg:postcode":"98951",
    "sg:province":"WA",
    "sg:tags":[
        "packing",
        "fruit",
        "apple"
    ],
    "wof:name":"Cowin & Sons LLC",
    "wof:placetype":"venue"
},
  "geometry": {"coordinates":[-120.511651,46.470171],"type":"Point"}
}