{
  "type": "Feature",
  "properties": {
    "addr:full":"2006 Lotze Creek Rd Colville WA 99114",
    "addr:housenumber":"2006",
    "addr:postcode":"99114",
    "addr:street":"Lotze Creek Rd",
    "iso:country":"US",
    "sg:address":"2006 Lotze Creek Rd",
    "sg:city":"Colville",
    "sg:classifiers":[
        {
            "category":"Education",
            "subcategory":"School",
            "type":"Public Place"
        }
    ],
    "sg:phone":"+1 509 732 4240",
    "sg:postcode":"99114",
    "sg:province":"WA",
    "sg:tags":[
        "educational",
        "administrative"
    ],
    "wof:name":"Onion Creek School District 30",
    "wof:placetype":"venue"
},
  "geometry": {"coordinates":[-117.807226,48.781289],"type":"Point"}
}