{
  "type": "Feature",
  "properties": {
    "iso:country":"US",
    "sg:address":"134 Deer Run",
    "sg:city":"Port Angeles",
    "sg:classifiers":[
        {
            "category":"Retail",
            "subcategory":"Auto Repair",
            "type":"Services"
        }
    ],
    "sg:phone":"+1 360 457 3762",
    "sg:postcode":"98362",
    "sg:province":"WA",
    "sg:tags":[
        "general"
    ],
    "wof:name":"Deer Park Auto Repair",
    "wof:placetype":"venue"
},
  "geometry": {"coordinates":[-123.34505299999999,48.081235],"type":"Point"}
}