{
  "type": "Feature",
  "properties": {
    "addr:full":"259 SW 297th St Federal Way WA 98023",
    "addr:housenumber":"259",
    "addr:postcode":"98023",
    "addr:street":"Sw 297Th St",
    "iso:country":"US",
    "sg:address":"259 SW 297th St",
    "sg:city":"Federal Way",
    "sg:classifiers":[
        {
            "category":"Organizations",
            "subcategory":"Non-profit Organization",
            "type":"Services"
        }
    ],
    "sg:phone":"+1 253 839 9576",
    "sg:postcode":"98023",
    "sg:province":"WA",
    "sg:tags":[
        "fund",
        "piano",
        "voice",
        "teacher",
        "raising"
    ],
    "wof:name":"Sunshine Generation",
    "wof:placetype":"venue"
},
  "geometry": {"coordinates":[-122.338657,47.336168],"type":"Point"}
}