{
  "type": "Feature",
  "properties": {
    "addr:full":"4101 Northshore Blvd NE Tacoma WA 98422",
    "addr:housenumber":"4101",
    "addr:postcode":"98422",
    "addr:street":"Northshore Blvd Ne",
    "iso:country":"US",
    "sg:address":"4101 Northshore Blvd NE",
    "sg:city":"Tacoma",
    "sg:classifiers":[
        {
            "category":"Recreation",
            "type":"Entertainment"
        }
    ],
    "sg:phone":"+1 253 838 3660",
    "sg:postcode":"98422",
    "sg:province":"WA",
    "sg:tags":[
        "golf",
        "club",
        "course",
        "membership",
        "eating",
        "sport",
        "public"
    ],
    "sg:website":"www.northshoregc.com",
    "wof:name":"North Shore Golf Course",
    "wof:placetype":"venue"
},
  "geometry": {"coordinates":[-122.395105,47.294465],"type":"Point"}
}