{
  "type": "Feature",
  "properties": {
    "addr:full":"125 S Kentucky Ave East Wenatchee WA 98802",
    "addr:housenumber":"125",
    "addr:postcode":"98802",
    "addr:street":"S Kentucky Ave",
    "iso:country":"US",
    "sg:address":"125 S Kentucky Ave",
    "sg:city":"East Wenatchee",
    "sg:classifiers":[
        {
            "category":"Organizations",
            "subcategory":"Religious Organization",
            "type":"Services"
        }
    ],
    "sg:phone":"+1 509 884 7748",
    "sg:postcode":"98802",
    "sg:province":"WA",
    "sg:tags":[
        "church"
    ],
    "wof:name":"Grant Missionary Baptist",
    "wof:placetype":"venue"
},
  "geometry": {"coordinates":[-120.260412,47.402631],"type":"Point"}
}