{
  "type": "Feature",
  "properties": {
    "iso:country":"US",
    "sg:address":"18 E A St",
    "sg:city":"Yakima",
    "sg:classifiers":[
        {
            "category":"Insurance",
            "subcategory":"Hazard Insurance",
            "type":"Services"
        },
        {
            "category":"Professional",
            "subcategory":"Business Services",
            "type":"Services"
        }
    ],
    "sg:phone":"+1 509 457 7296",
    "sg:postcode":"98901",
    "sg:province":"WA",
    "sg:tags":[
        "bond"
    ],
    "wof:name":"Egley's Bail Bonds",
    "wof:placetype":"venue"
},
  "geometry": {"coordinates":[-120.50686399999999,46.603354],"type":"Point"}
}