{
  "type": "Feature",
  "properties": {
    "addr:full":"1818 2nd St Cheney WA 99004",
    "addr:housenumber":"1818",
    "addr:postcode":"99004",
    "addr:street":"2Nd St",
    "iso:country":"US",
    "sg:address":"1818 2nd St",
    "sg:city":"Cheney",
    "sg:classifiers":[
        {
            "category":"Restaurant",
            "type":"Food & Drink"
        }
    ],
    "sg:phone":"+1 509 235 2951",
    "sg:postcode":"99004",
    "sg:province":"WA",
    "sg:tags":[
        "eating"
    ],
    "sg:website":"http://www.subway.com",
    "wof:name":"Subway",
    "wof:placetype":"venue"
},
  "geometry": {"coordinates":[-117.565119,47.497113],"type":"Point"}
}