{
  "type": "Feature",
  "properties": {
    "addr:full":"1706 Bellevue Ave Seattle WA 98122",
    "addr:housenumber":"1706",
    "addr:postcode":"98122",
    "addr:street":"Bellevue Ave",
    "iso:country":"US",
    "sg:address":"1706 Bellevue Ave",
    "sg:city":"Seattle",
    "sg:classifiers":[
        {
            "category":"Personal",
            "subcategory":"Hair Removal",
            "type":"Services"
        },
        {
            "category":"Personal",
            "subcategory":"Day Spa",
            "type":"Services"
        }
    ],
    "sg:phone":"+1 206 322 6939",
    "sg:postcode":"98122",
    "sg:province":"WA",
    "sg:website":"www.highmaintenanceskin.com/",
    "wof:name":"High Maintenance Skin Care Studio",
    "wof:placetype":"venue"
},
  "geometry": {"coordinates":[-122.327003,47.616501],"type":"Point"}
}