{
  "type": "Feature",
  "properties": {
    "addr:full":"6428 NE 187th St Kenmore WA 98028",
    "addr:housenumber":"6428",
    "addr:postcode":"98028",
    "addr:street":"Ne 187Th St",
    "iso:country":"US",
    "sg:address":"6428 NE 187th St",
    "sg:city":"Kenmore",
    "sg:classifiers":[
        {
            "category":"Shopping",
            "type":"Retail Goods"
        }
    ],
    "sg:phone":"+1 425 830 2392",
    "sg:postcode":"98028",
    "sg:province":"WA",
    "sg:tags":[
        "training",
        "material",
        "computer",
        "for"
    ],
    "wof:name":"E-Learning Associates",
    "wof:placetype":"venue"
},
  "geometry": {"coordinates":[-122.256159,47.764464],"type":"Point"}
}