{
  "type": "Feature",
  "properties": {
    "addr:full":"18324 Cook Rd SE Unit 1 Yelm WA 98597",
    "addr:housenumber":"18324;1",
    "addr:postcode":"98597",
    "addr:street":"Cook Rd Se Unit",
    "iso:country":"US",
    "sg:address":"18324 Cook Rd SE Unit 1",
    "sg:city":"Yelm",
    "sg:classifiers":[
        {
            "category":"Professional",
            "subcategory":"Management & Consulting",
            "type":"Services"
        },
        {
            "category":"Professional",
            "subcategory":"Advertising",
            "type":"Services"
        }
    ],
    "sg:phone":"+1 360 458 0654",
    "sg:postcode":"98597",
    "sg:province":"WA",
    "sg:tags":[
        "marketing",
        "program",
        "consultant"
    ],
    "wof:name":"True Green Marketing",
    "wof:placetype":"venue"
},
  "geometry": {"coordinates":[-122.55191000000001,46.92355],"type":"Point"}
}