{
  "type": "Feature",
  "properties": {
    "addr:full":"2124 W Wild Rose Rd Colbert WA 99005",
    "addr:housenumber":"2124",
    "addr:postcode":"99005",
    "addr:street":"W Wild Rose Rd Colbert",
    "iso:country":"US",
    "sg:address":"2124 W Wild Rose Rd",
    "sg:city":"Colbert",
    "sg:classifiers":[
        {
            "category":"Autos & Motor Vehicles",
            "subcategory":"Boat Sales",
            "type":"Retail Goods"
        }
    ],
    "sg:phone":"+1 509 276 8972",
    "sg:postcode":"99005",
    "sg:province":"WA",
    "wof:name":"Alaska Sea Kayak Adventures",
    "wof:placetype":"venue"
},
  "geometry": {"coordinates":[-117.442256,47.874714],"type":"Point"}
}