{
  "type": "Feature",
  "properties": {
    "iso:country":"US",
    "sg:address":"27621 221st Ave SE",
    "sg:city":"Maple Valley",
    "sg:classifiers":[
        {
            "category":"Food & Beverages",
            "subcategory":"Groceries & Convenience Stores",
            "type":"Retail Goods"
        }
    ],
    "sg:phone":"+1 425 413 4715",
    "sg:postcode":"98038",
    "sg:province":"WA",
    "wof:name":"Am/PM Mini Market",
    "wof:placetype":"venue"
},
  "geometry": {"coordinates":[-122.046599,47.353622],"type":"Point"}
}