{
  "type": "Feature",
  "properties": {
    "iso:country":"US",
    "sg:address":"196 Tromp Rd",
    "sg:city":"Lynden",
    "sg:classifiers":[
        {
            "category":"Freight",
            "type":"Transportation"
        }
    ],
    "sg:phone":"+1 360 354 6731",
    "sg:postcode":"98264",
    "sg:province":"WA",
    "sg:tags":[
        "operator",
        "trucking"
    ],
    "wof:name":"C&L Enterprises",
    "wof:placetype":"venue"
},
  "geometry": {"coordinates":[-122.49046800000001,48.938829],"type":"Point"}
}