{
  "type": "Feature",
  "properties": {
    "addr:full":"2328 Gibson Rd Everett WA 98204",
    "addr:housenumber":"2328",
    "addr:postcode":"98204",
    "addr:street":"Gibson Rd",
    "iso:country":"US",
    "sg:address":"2328 Gibson Rd",
    "sg:city":"Everett",
    "sg:classifiers":[
        {
            "category":"Autos & Motor Vehicles",
            "subcategory":"Automobile Sales",
            "type":"Retail Goods"
        }
    ],
    "sg:phone":"+1 425 355 1767",
    "sg:postcode":"98204",
    "sg:province":"WA",
    "sg:tags":[
        "used"
    ],
    "wof:name":"Gibson Auto Sales Inc",
    "wof:placetype":"venue"
},
  "geometry": {"coordinates":[-122.26694999999999,47.884545],"type":"Point"}
}