{
  "type": "Feature",
  "properties": {
    "addr:full":"1308 NE 89th Pl Vancouver WA 98664",
    "addr:housenumber":"1308",
    "addr:postcode":"98664",
    "addr:street":"Ne 89Th Pl",
    "iso:country":"US",
    "sg:address":"1308 NE 89th Pl",
    "sg:city":"Vancouver",
    "sg:classifiers":[
        {
            "category":"Banks & Credit Unions",
            "subcategory":"Financial Services",
            "type":"Services"
        }
    ],
    "sg:phone":"+1 360 891 5784",
    "sg:postcode":"98664",
    "sg:province":"WA",
    "sg:tags":[
        "investor"
    ],
    "wof:name":"Mvb Investments LLC",
    "wof:placetype":"venue"
},
  "geometry": {"coordinates":[-122.582031,45.63211],"type":"Point"}
}