{
  "type": "Feature",
  "properties": {
    "iso:country":"US",
    "sg:address":"1820 5th Ave",
    "sg:city":"Clarkston",
    "sg:classifiers":[
        {
            "category":"Personal",
            "type":"Services"
        }
    ],
    "sg:phone":"+1 509 758 7477",
    "sg:postcode":"99403",
    "sg:province":"WA",
    "wof:name":"Brooks Lahti",
    "wof:placetype":"venue"
},
  "geometry": {"coordinates":[-117.07328200000001,46.389274],"type":"Point"}
}