{
  "type": "Feature",
  "properties": {
    "addr:full":"5195 Rd 9 NW Ephrata WA 98823",
    "addr:housenumber":"5195",
    "addr:postcode":"98823",
    "addr:street":"Rd 9 Nw",
    "iso:country":"US",
    "sg:address":"5195 Rd 9 NW",
    "sg:city":"Ephrata",
    "sg:classifiers":[
        {
            "category":"Farming",
            "subcategory":"Farm",
            "type":"Manufacturing & Wholesale Goods"
        }
    ],
    "sg:phone":"+1 509 787 4281",
    "sg:postcode":"98823",
    "sg:province":"WA",
    "sg:tags":[
        "crop",
        "general"
    ],
    "wof:name":"Sylvia & Harvey R Heer",
    "wof:placetype":"venue"
},
  "geometry": {"coordinates":[-119.59961300000001,47.220982],"type":"Point"}
}