{
  "type": "Feature",
  "properties": {
    "iso:country":"US",
    "sg:address":"127 E Euclid Ave",
    "sg:city":"Spokane",
    "sg:classifiers":[
        {
            "category":"Health Services",
            "subcategory":"Health Practitioner",
            "type":"Services"
        }
    ],
    "sg:phone":"+1 509 326 4366",
    "sg:postcode":"99207",
    "sg:province":"WA",
    "sg:tags":[
        "midwife"
    ],
    "wof:name":"Spokane Midwives",
    "wof:placetype":"venue"
},
  "geometry": {"coordinates":[-117.407656,47.686302],"type":"Point"}
}