{
  "type": "Feature",
  "properties": {
    "addr:full":"5121 Dekker Rd Outlook WA 98938",
    "addr:housenumber":"5121",
    "addr:postcode":"98938",
    "addr:street":"Dekker Rd",
    "iso:country":"US",
    "sg:address":"5121 Dekker Rd",
    "sg:city":"Outlook",
    "sg:classifiers":[
        {
            "category":"Farming",
            "subcategory":"Dairy Farm",
            "type":"Manufacturing & Wholesale Goods"
        }
    ],
    "sg:phone":"+1 509 837 7783",
    "sg:postcode":"98938",
    "sg:province":"WA",
    "wof:name":"George Deruyter Dairy",
    "wof:placetype":"venue"
},
  "geometry": {"coordinates":[-120.125309,46.408115],"type":"Point"}
}