{
  "type": "Feature",
  "properties": {
    "iso:country":"US",
    "sg:address":"10005 Bristol Ave SW",
    "sg:city":"Lakewood",
    "sg:classifiers":[
        {
            "category":"Restaurant",
            "type":"Food & Drink"
        }
    ],
    "sg:phone":"+1 253 588 4621",
    "sg:postcode":"98499",
    "sg:province":"WA",
    "sg:tags":[
        "eating",
        "coin",
        "laundry"
    ],
    "wof:name":"Tijuana Taco",
    "wof:placetype":"venue"
},
  "geometry": {"coordinates":[-122.51779500000001,47.16667],"type":"Point"}
}