{
  "type": "Feature",
  "properties": {
    "addr:full":"1055 NW Maple St Issaquah WA 98027",
    "addr:housenumber":"1055",
    "addr:postcode":"98027",
    "addr:street":"Nw Maple St",
    "iso:country":"US",
    "sg:address":"1055 NW Maple St",
    "sg:city":"Issaquah",
    "sg:classifiers":[
        {
            "category":"Banks & Credit Unions",
            "subcategory":"Bank",
            "type":"Services"
        }
    ],
    "sg:phone":"+1 425 557 9111",
    "sg:postcode":"98027",
    "sg:province":"WA",
    "sg:tags":[
        "loan",
        "broker"
    ],
    "wof:name":"Residence Mortgage Corporation",
    "wof:placetype":"venue"
},
  "geometry": {"coordinates":[-122.054199,47.542895],"type":"Point"}
}