{
  "type": "Feature",
  "properties": {
    "addr:full":"703 US Hwy 2 Leavenworth WA 98826",
    "addr:housenumber":"703",
    "addr:postcode":"98826",
    "addr:street":"Us Hwy 2",
    "iso:country":"US",
    "sg:address":"703 US Hwy 2",
    "sg:city":"Leavenworth",
    "sg:classifiers":[
        {
            "category":"Travel",
            "subcategory":"Hotels & Motels",
            "type":"Entertainment"
        }
    ],
    "sg:phone":"+1 509 548 2327",
    "sg:postcode":"98826",
    "sg:province":"WA",
    "sg:tags":[
        "management"
    ],
    "wof:name":"Innsbrucker Building",
    "wof:placetype":"venue"
},
  "geometry": {"coordinates":[-120.663624,47.59499],"type":"Point"}
}