{
  "type": "Feature",
  "properties": {
    "addr:full":"64 W Nob Hill Blvd Yakima WA 98902",
    "addr:housenumber":"64",
    "addr:postcode":"98902",
    "addr:street":"W Nob Hill Blvd",
    "iso:country":"US",
    "sg:address":"64 W Nob Hill Blvd",
    "sg:city":"Yakima",
    "sg:classifiers":[
        {
            "category":"Restaurant",
            "type":"Food & Drink"
        }
    ],
    "sg:menulink":"http://www.allmenus.com/wa/yakima/78101-papa-murphys/menu/",
    "sg:phone":"+1 509 248 2922",
    "sg:postcode":"98902",
    "sg:province":"WA",
    "sg:tags":[
        "american",
        "pizza"
    ],
    "wof:name":"Papa Murphy's",
    "wof:placetype":"venue"
},
  "geometry": {"coordinates":[-120.505683,46.585235],"type":"Point"}
}