{
  "type": "Feature",
  "properties": {
    "addr:full":"100 Oak Flats Ln Naches WA 98937",
    "addr:housenumber":"100",
    "addr:postcode":"98937",
    "addr:street":"Oak Flats Ln",
    "iso:country":"US",
    "sg:address":"100 Oak Flats Ln",
    "sg:city":"Naches",
    "sg:classifiers":[
        {
            "category":"Building & Trades",
            "subcategory":"Construction",
            "type":"Services"
        }
    ],
    "sg:phone":"+1 509 952 9426",
    "sg:postcode":"98937",
    "sg:province":"WA",
    "sg:tags":[
        "fence",
        "contractor"
    ],
    "wof:name":"Bull Pen Fence Co",
    "wof:placetype":"venue"
},
  "geometry": {"coordinates":[-120.79641100000001,46.747089],"type":"Point"}
}