{
  "type": "Feature",
  "properties": {
    "addr:full":"705 N 57th St Yakima WA 98901",
    "addr:housenumber":"705",
    "addr:postcode":"98901",
    "addr:street":"N 57Th St",
    "iso:country":"US",
    "sg:address":"705 N 57th St",
    "sg:city":"Yakima",
    "sg:classifiers":[
        {
            "category":"Home & Garden",
            "subcategory":"Carpets & Floor Coverings",
            "type":"Retail Goods"
        }
    ],
    "sg:phone":"+1 509 452 2398",
    "sg:postcode":"98901",
    "sg:province":"WA",
    "sg:tags":[
        "rug"
    ],
    "wof:name":"Kel Co Carpets",
    "wof:placetype":"venue"
},
  "geometry": {"coordinates":[-120.42549099999999,46.612282],"type":"Point"}
}