{
  "type": "Feature",
  "properties": {
    "addr:full":"306 24th St Hoquiam WA 98550",
    "addr:housenumber":"306",
    "addr:postcode":"98550",
    "addr:street":"24Th St",
    "iso:country":"US",
    "sg:address":"306 24th St",
    "sg:city":"Hoquiam",
    "sg:classifiers":[
        {
            "category":"Retail",
            "subcategory":"Repair Shop",
            "type":"Services"
        }
    ],
    "sg:phone":"+1 360 538 1301",
    "sg:postcode":"98550",
    "sg:province":"WA",
    "sg:tags":[
        "machine",
        "sewing"
    ],
    "wof:name":"Peggy Sue's Sew & Vac",
    "wof:placetype":"venue"
},
  "geometry": {"coordinates":[-123.869733,46.976105],"type":"Point"}
}