{
  "type": "Feature",
  "properties": {
    "addr:full":"13214 E Indiana Ave Spokane Valley WA 99216",
    "addr:housenumber":"13214",
    "addr:postcode":"99216",
    "addr:street":"E Indiana Ave",
    "iso:country":"US",
    "sg:address":"13214 E Indiana Ave",
    "sg:city":"Spokane Valley",
    "sg:classifiers":[
        {
            "category":"Recreation",
            "type":"Entertainment"
        }
    ],
    "sg:phone":"+1 509 922 2003",
    "sg:postcode":"99216",
    "sg:province":"WA",
    "sg:tags":[
        "balloon"
    ],
    "wof:name":"All American Advertising",
    "wof:placetype":"venue"
},
  "geometry": {"coordinates":[-117.227099,47.675303],"type":"Point"}
}