{
  "type": "Feature",
  "properties": {
    "addr:full":"3812 51st Ave SW Seattle WA 98116",
    "addr:housenumber":"3812",
    "addr:postcode":"98116",
    "addr:street":"51St Ave Sw",
    "iso:country":"US",
    "sg:address":"3812 51st Ave SW",
    "sg:city":"Seattle",
    "sg:classifiers":[
        {
            "category":"Professional",
            "subcategory":"Management & Consulting",
            "type":"Services"
        }
    ],
    "sg:phone":"+1 206 933 9659",
    "sg:postcode":"98116",
    "sg:province":"WA",
    "sg:tags":[
        "business"
    ],
    "wof:name":"Jmh Consulting",
    "wof:placetype":"venue"
},
  "geometry": {"coordinates":[-122.39738699999999,47.568613],"type":"Point"}
}