{
  "type": "Feature",
  "properties": {
    "addr:full":"7600 Fort Rd Wapato WA 98951",
    "addr:housenumber":"7600",
    "addr:postcode":"98951",
    "addr:street":"Fort Rd",
    "iso:country":"US",
    "sg:address":"7600 Fort Rd",
    "sg:city":"Wapato",
    "sg:classifiers":[
        {
            "category":"Farming",
            "subcategory":"Orchard",
            "type":"Manufacturing & Wholesale Goods"
        }
    ],
    "sg:phone":"+1 509 848 2515",
    "sg:postcode":"98951",
    "sg:province":"WA",
    "sg:tags":[
        "fruit",
        "tree"
    ],
    "wof:name":"R & R Farms",
    "wof:placetype":"venue"
},
  "geometry": {"coordinates":[-120.48749100000001,46.375346],"type":"Point"}
}