{
  "type": "Feature",
  "properties": {
    "addr:full":"9440 45th Ave SW Seattle WA 98136",
    "addr:housenumber":"9440",
    "addr:postcode":"98136",
    "addr:street":"45Th Ave Sw",
    "iso:country":"US",
    "sg:address":"9440 45th Ave SW",
    "sg:city":"Seattle",
    "sg:classifiers":[
        {
            "category":"Organizations",
            "subcategory":"Professional Association",
            "type":"Services"
        }
    ],
    "sg:phone":"+1 206 935 4167",
    "sg:postcode":"98136",
    "sg:province":"WA",
    "sg:tags":[
        "business"
    ],
    "wof:name":"B S B Utilities Inc",
    "wof:placetype":"venue"
},
  "geometry": {"coordinates":[-122.39109500000001,47.517649],"type":"Point"}
}