{
  "type": "Feature",
  "properties": {
    "addr:full":"2317 256th St NW Stanwood WA 98292",
    "addr:housenumber":"2317",
    "addr:postcode":"98292",
    "addr:street":"256Th St Nw",
    "iso:country":"US",
    "sg:address":"2317 256th St NW",
    "sg:city":"Stanwood",
    "sg:classifiers":[
        {
            "category":"Insurance",
            "subcategory":"Insurance Agent",
            "type":"Services"
        }
    ],
    "sg:phone":"+1 360 629 0275",
    "sg:postcode":"98292",
    "sg:province":"WA",
    "wof:name":"Sunday Lake Community CLU",
    "wof:placetype":"venue"
},
  "geometry": {"coordinates":[-122.264394,48.228534],"type":"Point"}
}