{
  "type": "Feature",
  "properties": {
    "iso:country":"US",
    "sg:address":"602 NW 353rd St",
    "sg:city":"La Center",
    "sg:classifiers":[
        {
            "category":"Real Estate",
            "subcategory":"Developer",
            "type":"Services"
        }
    ],
    "sg:phone":"+1 360 263 1590",
    "sg:postcode":"98629",
    "sg:province":"WA",
    "wof:name":"Green Mountain LLC",
    "wof:placetype":"venue"
},
  "geometry": {"coordinates":[-122.67690899999999,45.876452],"type":"Point"}
}