{
  "type": "Feature",
  "properties": {
    "addr:full":"156 Ceres Hill Rd Chehalis WA 98532",
    "addr:housenumber":"156",
    "addr:postcode":"98532",
    "addr:street":"Ceres Hill Rd",
    "iso:country":"US",
    "sg:address":"156 Ceres Hill Rd",
    "sg:city":"Chehalis",
    "sg:classifiers":[
        {
            "category":"Manufacturing",
            "subcategory":"Lumber",
            "type":"Manufacturing & Wholesale Goods"
        }
    ],
    "sg:phone":"+1 360 245 3334",
    "sg:postcode":"98532",
    "sg:province":"WA",
    "sg:tags":[
        "logging",
        "contractor"
    ],
    "wof:name":"Ter & Bear Trucking & Logging",
    "wof:placetype":"venue"
},
  "geometry": {"coordinates":[-123.138154,46.601887],"type":"Point"}
}