{
  "type": "Feature",
  "properties": {
    "addr:full":"12032 20th Ave NE Seattle WA 98125",
    "addr:housenumber":"12032",
    "addr:postcode":"98125",
    "addr:street":"20Th Ave Ne",
    "iso:country":"US",
    "sg:address":"12032 20th Ave NE",
    "sg:city":"Seattle",
    "sg:classifiers":[
        {
            "category":"Building & Trades",
            "subcategory":"Construction",
            "type":"Services"
        }
    ],
    "sg:phone":"+1 206 363 5800",
    "sg:postcode":"98125",
    "sg:province":"WA",
    "sg:tags":[
        "residential"
    ],
    "wof:name":"Yourhome Construction & Design",
    "wof:placetype":"venue"
},
  "geometry": {"coordinates":[-122.307149,47.717358],"type":"Point"}
}