{
  "type": "Feature",
  "properties": {
    "addr:full":"14385 104th Ave NE Bothell WA 98011",
    "addr:housenumber":"14385",
    "addr:postcode":"98011",
    "addr:street":"104Th Ave Ne",
    "iso:country":"US",
    "sg:address":"14385 104th Ave NE",
    "sg:city":"Bothell",
    "sg:classifiers":[
        {
            "category":"Building & Trades",
            "subcategory":"Landscaping Services",
            "type":"Services"
        }
    ],
    "sg:phone":"+1 425 823 2958",
    "sg:postcode":"98011",
    "sg:province":"WA",
    "sg:tags":[
        "tree",
        "garden",
        "maintenance"
    ],
    "wof:name":"Hauser Ldscpg & Ground Maint",
    "wof:placetype":"venue"
},
  "geometry": {"coordinates":[-122.202054,47.732885],"type":"Point"}
}