{
  "type": "Feature",
  "properties": {
    "addr:full":"5413 NE 200th Pl Seattle WA 98155",
    "addr:housenumber":"5413",
    "addr:postcode":"98155",
    "addr:street":"Ne 200Th Pl",
    "iso:country":"US",
    "sg:address":"5413 NE 200th Pl",
    "sg:city":"Seattle",
    "sg:classifiers":[
        {
            "category":"Professional",
            "subcategory":"Management & Consulting",
            "type":"Services"
        }
    ],
    "sg:phone":"+1 206 306 9715",
    "sg:postcode":"98155",
    "sg:province":"WA",
    "sg:tags":[
        "business"
    ],
    "wof:name":"Oceanic Life Coaching",
    "wof:placetype":"venue"
},
  "geometry": {"coordinates":[-122.271979,47.774037],"type":"Point"}
}