{
  "type": "Feature",
  "properties": {
    "addr:full":"5506 320th Avenue Northeast Carnation WA 98014",
    "addr:housenumber":"5506",
    "addr:postcode":"98014",
    "addr:street":"320Th Avenue Northeast",
    "iso:country":"US",
    "sg:address":"5506 320th Avenue Northeast",
    "sg:city":"Carnation",
    "sg:classifiers":[
        {
            "category":"Building & Trades",
            "subcategory":"Construction",
            "type":"Services"
        }
    ],
    "sg:phone":"+1 425 939 0449",
    "sg:postcode":"98014",
    "sg:province":"WA",
    "sg:tags":[
        "contractor"
    ],
    "sg:website":"www.garagetechinc.com",
    "wof:name":"Garage Tech Inc.",
    "wof:placetype":"venue"
},
  "geometry": {"coordinates":[-121.911722,47.65531],"type":"Point"}
}