{
  "type": "Feature",
  "properties": {
    "addr:full":"340 Krough Rd Prosser WA 99350",
    "addr:housenumber":"340",
    "addr:postcode":"99350",
    "addr:street":"Krough Rd",
    "iso:country":"US",
    "sg:address":"340 Krough Rd",
    "sg:city":"Prosser",
    "sg:classifiers":[
        {
            "category":"Farming",
            "subcategory":"Livestock Farm",
            "type":"Manufacturing & Wholesale Goods"
        }
    ],
    "sg:phone":"+1 509 882 5356",
    "sg:postcode":"99350",
    "sg:province":"WA",
    "sg:tags":[
        "beef",
        "feedlot",
        "cattle"
    ],
    "wof:name":"Hinds Cattle Co",
    "wof:placetype":"venue"
},
  "geometry": {"coordinates":[-119.87706,46.210107],"type":"Point"}
}