{
  "type": "Feature",
  "properties": {
    "addr:full":"12486 Rd E SW Royal City WA 99357",
    "addr:housenumber":"12486",
    "addr:postcode":"99357",
    "addr:street":"Rd E Sw",
    "iso:country":"US",
    "sg:address":"12486 Rd E SW",
    "sg:city":"Royal City",
    "sg:classifiers":[
        {
            "category":"Farming",
            "subcategory":"Farm",
            "type":"Manufacturing & Wholesale Goods"
        }
    ],
    "sg:phone":"+1 509 346 2303",
    "sg:postcode":"99357",
    "sg:province":"WA",
    "wof:name":"Heritage Farms",
    "wof:placetype":"venue"
},
  "geometry": {"coordinates":[-119.60216,46.906413],"type":"Point"}
}