{
  "type": "Feature",
  "properties": {
    "addr:full":"15878 Peterson Rd Burlington WA 98233",
    "addr:housenumber":"15878",
    "addr:postcode":"98233",
    "addr:street":"Peterson Rd",
    "iso:country":"US",
    "sg:address":"15878 Peterson Rd",
    "sg:city":"Burlington",
    "sg:classifiers":[
        {
            "category":"Wholesale",
            "subcategory":"Scrap",
            "type":"Manufacturing & Wholesale Goods"
        }
    ],
    "sg:phone":"+1 360 757 4068",
    "sg:postcode":"98233",
    "sg:province":"WA",
    "sg:tags":[
        "recycling",
        "center"
    ],
    "wof:name":"Waste Management",
    "wof:placetype":"venue"
},
  "geometry": {"coordinates":[-122.402342,48.472159],"type":"Point"}
}