{
  "type": "Feature",
  "properties": {
    "addr:full":"106 S 4th St E Chewelah WA 99109",
    "addr:housenumber":"106",
    "addr:postcode":"99109",
    "addr:street":"S 4Th St E",
    "iso:country":"US",
    "sg:address":"106 S 4th St E",
    "sg:city":"Chewelah",
    "sg:classifiers":[
        {
            "category":"Professional",
            "type":"Services"
        }
    ],
    "sg:phone":"+1 509 935 0755",
    "sg:postcode":"99109",
    "sg:province":"WA",
    "sg:tags":[
        "establishment"
    ],
    "wof:name":"Knack For Markets",
    "wof:placetype":"venue"
},
  "geometry": {"coordinates":[-117.712574,48.275945],"type":"Point"}
}