{
  "type": "Feature",
  "properties": {
    "addr:full":"2208 Enchanted Forest Rd Eastsound WA 98245",
    "addr:housenumber":"2208",
    "addr:postcode":"98245",
    "addr:street":"Enchanted Forest Rd",
    "iso:country":"US",
    "sg:address":"2208 Enchanted Forest Rd",
    "sg:city":"Eastsound",
    "sg:classifiers":[
        {
            "category":"Insurance",
            "subcategory":"Hazard Insurance",
            "type":"Services"
        }
    ],
    "sg:phone":"+1 360 376 6123",
    "sg:postcode":"98245",
    "sg:province":"WA",
    "wof:name":"Robert David Mc Eldowney",
    "wof:placetype":"venue"
},
  "geometry": {"coordinates":[-122.943881,48.68636],"type":"Point"}
}