{
  "type": "Feature",
  "properties": {
    "addr:full":"11 S 2nd Ave Walla Walla WA 99362",
    "addr:housenumber":"11",
    "addr:postcode":"99362",
    "addr:street":"S 2Nd Ave",
    "iso:country":"US",
    "sg:address":"11 S 2nd Ave",
    "sg:city":"Walla Walla",
    "sg:classifiers":[
        {
            "category":"Banks & Credit Unions",
            "subcategory":"Bank",
            "type":"Services"
        }
    ],
    "sg:phone":"+1 509 526 8702",
    "sg:postcode":"99362",
    "sg:province":"WA",
    "wof:name":"Banner Bank",
    "wof:placetype":"venue"
},
  "geometry": {"coordinates":[-118.339253,46.066665],"type":"Point"}
}