{
  "type": "Feature",
  "properties": {
    "addr:full":"6221 Tacoma Mall Blvd Tacoma WA 98409",
    "addr:housenumber":"6221",
    "addr:postcode":"98409",
    "addr:street":"Tacoma Mall Blvd",
    "iso:country":"US",
    "sg:address":"6221 Tacoma Mall Blvd",
    "sg:city":"Tacoma",
    "sg:classifiers":[
        {
            "category":"Insurance",
            "subcategory":"Insurance Agent",
            "type":"Services"
        }
    ],
    "sg:phone":"+1 253 473 4000",
    "sg:postcode":"98409",
    "sg:province":"WA",
    "sg:website":"www.farmers.com",
    "wof:name":"Farmers Insurance Group",
    "wof:placetype":"venue"
},
  "geometry": {"coordinates":[-122.46290399999999,47.200847],"type":"Point"}
}