{
  "type": "Feature",
  "properties": {
    "addr:full":"15709 14th Pl SW Burien WA 98166",
    "addr:housenumber":"15709",
    "addr:postcode":"98166",
    "addr:street":"14Th Pl Sw",
    "iso:country":"US",
    "sg:address":"15709 14th Pl SW",
    "sg:city":"Burien",
    "sg:classifiers":[
        {
            "category":"Professional",
            "subcategory":"Business Services",
            "type":"Services"
        }
    ],
    "sg:phone":"+1 206 246 5678",
    "sg:postcode":"98166",
    "sg:province":"WA",
    "sg:tags":[
        "consultant",
        "coach"
    ],
    "wof:name":"Dana Siverts Consulting",
    "wof:placetype":"venue"
},
  "geometry": {"coordinates":[-122.35370399999999,47.462039],"type":"Point"}
}