{
  "type": "Feature",
  "properties": {
    "addr:full":"630 N Chelan Ave Wenatchee WA 98801",
    "addr:housenumber":"630",
    "addr:postcode":"98801",
    "addr:street":"N Chelan Ave",
    "iso:country":"US",
    "sg:address":"630 N Chelan Ave",
    "sg:city":"Wenatchee",
    "sg:classifiers":[
        {
            "category":"Health Services",
            "subcategory":"Optometrist",
            "type":"Services"
        }
    ],
    "sg:phone":"+1 509 662 3937",
    "sg:postcode":"98801",
    "sg:province":"WA",
    "wof:name":"Milton P Herman OD",
    "wof:placetype":"venue"
},
  "geometry": {"coordinates":[-120.319835,47.431169],"type":"Point"}
}