{
  "type": "Feature",
  "properties": {
    "addr:full":"45 Broadway St Cathlamet WA 98612",
    "addr:housenumber":"45",
    "addr:postcode":"98612",
    "addr:street":"Broadway St",
    "iso:country":"US",
    "sg:address":"45 Broadway St",
    "sg:city":"Cathlamet",
    "sg:classifiers":[
        {
            "category":"Retail",
            "subcategory":"Funeral Services",
            "type":"Services"
        }
    ],
    "sg:phone":"+1 360 795 3591",
    "sg:postcode":"98612",
    "sg:province":"WA",
    "sg:tags":[
        "director"
    ],
    "wof:name":"Dowling Funeral Home",
    "wof:placetype":"venue"
},
  "geometry": {"coordinates":[-123.384885,46.201564],"type":"Point"}
}