{
  "type": "Feature",
  "properties": {
    "addr:full":"616 NW 80th St Seattle WA 98117",
    "addr:housenumber":"616",
    "addr:postcode":"98117",
    "addr:street":"Nw 80Th St",
    "iso:country":"US",
    "sg:address":"616 NW 80th St",
    "sg:city":"Seattle",
    "sg:classifiers":[
        {
            "category":"Building & Trades",
            "subcategory":"Construction",
            "type":"Services"
        }
    ],
    "sg:phone":"+1 206 781 8743",
    "sg:postcode":"98117",
    "sg:province":"WA",
    "sg:tags":[
        "general",
        "contractor"
    ],
    "wof:name":"ARB Construction Co",
    "wof:placetype":"venue"
},
  "geometry": {"coordinates":[-122.365882,47.687011],"type":"Point"}
}