{
  "type": "Feature",
  "properties": {
    "addr:full":"1102 Brandt Rd Vancouver WA 98661",
    "addr:housenumber":"1102",
    "addr:postcode":"98661",
    "addr:street":"Brandt Rd",
    "iso:country":"US",
    "sg:address":"1102 Brandt Rd",
    "sg:city":"Vancouver",
    "sg:classifiers":[
        {
            "category":"Building & Trades",
            "subcategory":"Cleaning & Sanitation",
            "type":"Services"
        }
    ],
    "sg:phone":"+1 360 695 5360",
    "sg:postcode":"98661",
    "sg:province":"WA",
    "sg:tags":[
        "janitorial"
    ],
    "wof:name":"ServiceMaster",
    "wof:placetype":"venue"
},
  "geometry": {"coordinates":[-122.629209,45.630046],"type":"Point"}
}