{
  "type": "Feature",
  "properties": {
    "addr:full":"2125 Park Ave Snohomish WA 98290",
    "addr:housenumber":"2125",
    "addr:postcode":"98290",
    "addr:street":"Park Ave",
    "iso:country":"US",
    "sg:address":"2125 Park Ave",
    "sg:city":"Snohomish",
    "sg:classifiers":[
        {
            "category":"Home & Garden",
            "subcategory":"Garden Supply",
            "type":"Retail Goods"
        }
    ],
    "sg:phone":"+1 360 568 4028",
    "sg:postcode":"98290",
    "sg:province":"WA",
    "sg:tags":[
        "operation",
        "tract",
        "timber"
    ],
    "wof:name":"Park Avenue Firs",
    "wof:placetype":"venue"
},
  "geometry": {"coordinates":[-122.087717,47.937386],"type":"Point"}
}