{
  "type": "Feature",
  "properties": {
    "addr:full":"1318 Lakeview Blvd E Seattle WA 98102",
    "addr:housenumber":"1318",
    "addr:postcode":"98102",
    "addr:street":"Lakeview Blvd E",
    "iso:country":"US",
    "sg:address":"1318 Lakeview Blvd E",
    "sg:city":"Seattle",
    "sg:classifiers":[
        {
            "category":"Building & Trades",
            "subcategory":"Construction",
            "type":"Services"
        }
    ],
    "sg:phone":"+1 206 329 1591",
    "sg:postcode":"98102",
    "sg:province":"WA",
    "sg:tags":[
        "contractor"
    ],
    "wof:name":"Aarmstrong Roofing",
    "wof:placetype":"venue"
},
  "geometry": {"coordinates":[-122.323573,47.6322],"type":"Point"}
}