{
  "type": "Feature",
  "properties": {
    "addr:full":"1960 148th Ave NE Redmond WA 98052",
    "addr:housenumber":"1960",
    "addr:postcode":"98052",
    "addr:street":"148Th Ave Ne",
    "iso:country":"US",
    "sg:address":"1960 148th Ave NE",
    "sg:city":"Redmond",
    "sg:classifiers":[
        {
            "category":"Fast Food",
            "type":"Food & Drink"
        },
        {
            "category":"Restaurant",
            "type":"Food & Drink"
        }
    ],
    "sg:phone":"+1 425 644 8902",
    "sg:postcode":"98052",
    "sg:province":"WA",
    "sg:tags":[
        "mexican"
    ],
    "sg:website":"http://www.tacobell.com",
    "wof:name":"Taco Bell",
    "wof:placetype":"venue"
},
  "geometry": {"coordinates":[-122.14286800000001,47.642641],"type":"Point"}
}