{
  "type": "Feature",
  "properties": {
    "iso:country":"US",
    "sg:address":"1039 E Juniper St",
    "sg:city":"Othello",
    "sg:classifiers":[
        {
            "category":"Professional",
            "subcategory":"Engineering",
            "type":"Services"
        }
    ],
    "sg:phone":"+1 509 488 9059",
    "sg:postcode":"99344",
    "sg:province":"WA",
    "sg:tags":[
        "engineer"
    ],
    "wof:name":"Lonergan Engineering",
    "wof:placetype":"venue"
},
  "geometry": {"coordinates":[-119.160005,46.822213],"type":"Point"}
}