{
  "type": "Feature",
  "properties": {
    "addr:full":"2317 Rolling Hills Dr Clarkston WA 99403",
    "addr:housenumber":"2317",
    "addr:postcode":"99403",
    "addr:street":"Rolling Hills Dr",
    "iso:country":"US",
    "sg:address":"2317 Rolling Hills Dr",
    "sg:city":"Clarkston",
    "sg:classifiers":[
        {
            "category":"Building & Trades",
            "subcategory":"Landscaping Services",
            "type":"Services"
        }
    ],
    "sg:phone":"+1 509 758 8457",
    "sg:postcode":"99403",
    "sg:province":"WA",
    "sg:tags":[
        "tree"
    ],
    "wof:name":"Tom Roberts Tree Farm",
    "wof:placetype":"venue"
},
  "geometry": {"coordinates":[-117.090648,46.40749],"type":"Point"}
}