{
  "type": "Feature",
  "properties": {
    "addr:full":"12707 120th Ave NE Kirkland WA 98034",
    "addr:housenumber":"12707",
    "addr:postcode":"98034",
    "addr:street":"120Th Ave Ne",
    "iso:country":"US",
    "sg:address":"12707 120th Ave NE",
    "sg:city":"Kirkland",
    "sg:classifiers":[
        {
            "category":"Recreation",
            "type":"Entertainment"
        }
    ],
    "sg:phone":"+1 425 820 2110",
    "sg:postcode":"98034",
    "sg:province":"WA",
    "sg:tags":[
        "instruction",
        "physical",
        "fitness"
    ],
    "wof:name":"Washington Spt Mdcine Inst LLC",
    "wof:placetype":"venue"
},
  "geometry": {"coordinates":[-122.1808,47.713436],"type":"Point"}
}