{
  "type": "Feature",
  "properties": {
    "addr:full":"2885 Elmont Ave Enumclaw WA 98022",
    "addr:housenumber":"2885",
    "addr:postcode":"98022",
    "addr:street":"Elmont Ave",
    "iso:country":"US",
    "sg:address":"2885 Elmont Ave",
    "sg:city":"Enumclaw",
    "sg:classifiers":[
        {
            "category":"Health Services",
            "subcategory":"Nursing And Care Facility",
            "type":"Services"
        }
    ],
    "sg:phone":"+1 360 825 4514",
    "sg:postcode":"98022",
    "sg:province":"WA",
    "sg:tags":[
        "skilled"
    ],
    "wof:name":"Cascade Caregivers Adult Care",
    "wof:placetype":"venue"
},
  "geometry": {"coordinates":[-122.00743799999999,47.203018],"type":"Point"}
}