{
  "type": "Feature",
  "properties": {
    "addr:full":"9342 NE 76th St Vancouver WA 98662",
    "addr:housenumber":"9342",
    "addr:postcode":"98662",
    "addr:street":"Ne 76Th St",
    "iso:country":"US",
    "sg:address":"9342 NE 76th St",
    "sg:city":"Vancouver",
    "sg:classifiers":[
        {
            "category":"Personal",
            "subcategory":"Beauty Salon",
            "type":"Services"
        }
    ],
    "sg:phone":"+1 360 260 2995",
    "sg:postcode":"98662",
    "sg:province":"WA",
    "sg:tags":[
        "shop"
    ],
    "wof:name":"Sjogrens Beauty & Hlth Clinic",
    "wof:placetype":"venue"
},
  "geometry": {"coordinates":[-122.58050299999999,45.677788],"type":"Point"}
}