{
  "type": "Feature",
  "properties": {
    "addr:full":"210 W 2nd St Grandview WA 98930",
    "addr:housenumber":"210",
    "addr:postcode":"98930",
    "addr:street":"W 2Nd St",
    "iso:country":"US",
    "sg:address":"210 W 2nd St",
    "sg:city":"Grandview",
    "sg:classifiers":[
        {
            "category":"Food & Beverages",
            "subcategory":"Bakery",
            "type":"Retail Goods"
        }
    ],
    "sg:phone":"+1 509 882 4000",
    "sg:postcode":"98930",
    "sg:province":"WA",
    "sg:tags":[
        "baker"
    ],
    "wof:name":"LA Super Bakery",
    "wof:placetype":"venue"
},
  "geometry": {"coordinates":[-119.904779,46.254724],"type":"Point"}
}