{
  "type": "Feature",
  "properties": {
    "addr:full":"1364 Abbott Rd Lynden WA 98264",
    "addr:housenumber":"1364",
    "addr:postcode":"98264",
    "addr:street":"Abbott Rd",
    "iso:country":"US",
    "sg:address":"1364 Abbott Rd",
    "sg:city":"Lynden",
    "sg:classifiers":[
        {
            "category":"Farming",
            "subcategory":"Dairy Farm",
            "type":"Manufacturing & Wholesale Goods"
        }
    ],
    "sg:phone":"+1 360 354 3107",
    "sg:postcode":"98264",
    "sg:province":"WA",
    "wof:name":"Eagle Mill Farm",
    "wof:placetype":"venue"
},
  "geometry": {"coordinates":[-122.41513,48.927739],"type":"Point"}
}