{
  "type": "Feature",
  "properties": {
    "addr:full":"18528 SE 58th St Issaquah WA 98027",
    "addr:postcode":"18528;98027",
    "addr:street":"Se 58Th St",
    "iso:country":"US",
    "sg:address":"18528 SE 58th St",
    "sg:city":"Issaquah",
    "sg:classifiers":[
        {
            "category":"Organizations",
            "subcategory":"Religious Organization",
            "type":"Services"
        }
    ],
    "sg:phone":"+1 425 641 1527",
    "sg:postcode":"98027",
    "sg:province":"WA",
    "wof:name":"Woman Spirit Center",
    "wof:placetype":"venue"
},
  "geometry": {"coordinates":[-122.09375,47.550355],"type":"Point"}
}