{
  "type": "Feature",
  "properties": {
    "addr:full":"12024 9th Ct SW Seattle WA 98146",
    "addr:housenumber":"12024",
    "addr:postcode":"98146",
    "addr:street":"9Th Ct Sw",
    "iso:country":"US",
    "sg:address":"12024 9th Ct SW",
    "sg:city":"Seattle",
    "sg:classifiers":[
        {
            "category":"Professional",
            "subcategory":"Business Services",
            "type":"Services"
        }
    ],
    "sg:phone":"+1 206 241 1960",
    "sg:postcode":"98146",
    "sg:province":"WA",
    "wof:name":"Super Paint Enterprise Inc",
    "wof:placetype":"venue"
},
  "geometry": {"coordinates":[-122.34666900000001,47.495221],"type":"Point"}
}