{
  "type": "Feature",
  "properties": {
    "addr:full":"2920 SW 337th St Federal Way WA 98023",
    "addr:housenumber":"2920",
    "addr:postcode":"98023",
    "addr:street":"Sw 337Th St",
    "iso:country":"US",
    "sg:address":"2920 SW 337th St",
    "sg:city":"Federal Way",
    "sg:classifiers":[
        {
            "category":"Wholesale",
            "subcategory":"Non-durable Goods",
            "type":"Manufacturing & Wholesale Goods"
        }
    ],
    "sg:phone":"+1 253 838 5114",
    "sg:postcode":"98023",
    "sg:province":"WA",
    "sg:tags":[
        "advertising"
    ],
    "wof:name":"Earline Legge Advertising",
    "wof:placetype":"venue"
},
  "geometry": {"coordinates":[-122.372423,47.301466],"type":"Point"}
}