{
  "type": "Feature",
  "properties": {
    "addr:full":"6437 S 144th St Tukwila WA 98168",
    "addr:housenumber":"6437",
    "addr:postcode":"98168",
    "addr:street":"S 144Th St",
    "iso:country":"US",
    "sg:address":"6437 S 144th St",
    "sg:city":"Tukwila",
    "sg:classifiers":[
        {
            "category":"Building & Trades",
            "subcategory":"Landscaping Services",
            "type":"Services"
        }
    ],
    "sg:phone":"+1 206 420 3184",
    "sg:postcode":"98168",
    "sg:province":"WA",
    "sg:tags":[
        "environmental",
        "remediation",
        "services-site"
    ],
    "wof:name":"Bravo Environmental",
    "wof:placetype":"venue"
},
  "geometry": {"coordinates":[-122.253683,47.473567],"type":"Point"}
}