{
  "type": "Feature",
  "properties": {
    "addr:full":"6546 36th Ave SW Seattle WA 98126",
    "addr:housenumber":"6546",
    "addr:postcode":"98126",
    "addr:street":"36Th Ave Sw",
    "iso:country":"US",
    "sg:address":"6546 36th Ave SW",
    "sg:city":"Seattle",
    "sg:classifiers":[
        {
            "category":"Building & Trades",
            "subcategory":"Construction",
            "type":"Services"
        }
    ],
    "sg:phone":"+1 206 937 9574",
    "sg:postcode":"98126",
    "sg:province":"WA",
    "sg:tags":[
        "house"
    ],
    "wof:name":"A&M Remodeling Inc",
    "wof:placetype":"venue"
},
  "geometry": {"coordinates":[-122.377753,47.543304],"type":"Point"}
}