{
  "type": "Feature",
  "properties": {
    "addr:full":"1225 Union Ave NE Renton WA 98059",
    "addr:housenumber":"1225",
    "addr:postcode":"98059",
    "addr:street":"Union Ave Ne",
    "iso:country":"US",
    "sg:address":"1225 Union Ave NE",
    "sg:city":"Renton",
    "sg:classifiers":[
        {
            "category":"Real Estate",
            "subcategory":"Real Estate Agent",
            "type":"Services"
        }
    ],
    "sg:phone":"+1 425 226 6363",
    "sg:postcode":"98059",
    "sg:province":"WA",
    "wof:name":"Dalpay & Assoc",
    "wof:placetype":"venue"
},
  "geometry": {"coordinates":[-122.164765,47.50365],"type":"Point"}
}