{
  "type": "Feature",
  "properties": {
    "addr:full":"934 S Burlington Blvd Burlington WA 98233",
    "addr:housenumber":"934",
    "addr:postcode":"98233",
    "addr:street":"S Burlington Blvd",
    "iso:country":"US",
    "sg:address":"934 S Burlington Blvd",
    "sg:city":"Burlington",
    "sg:classifiers":[
        {
            "category":"Professional",
            "subcategory":"Advertising",
            "type":"Services"
        }
    ],
    "sg:phone":"+1 360 757 3281",
    "sg:postcode":"98233",
    "sg:province":"WA",
    "sg:tags":[
        "printing",
        "mailing",
        "shipping"
    ],
    "sg:website":"www.postnet.com",
    "wof:name":"Postnet Postal & Business Services",
    "wof:placetype":"venue"
},
  "geometry": {"coordinates":[-122.335999,48.466999],"type":"Point"}
}