{
  "type": "Feature",
  "properties": {
    "addr:full":"4602 NE 40th Ave Vancouver WA 98661",
    "addr:housenumber":"4602",
    "addr:postcode":"98661",
    "addr:street":"Ne 40Th Ave",
    "iso:country":"US",
    "sg:address":"4602 NE 40th Ave",
    "sg:city":"Vancouver",
    "sg:classifiers":[
        {
            "category":"Building & Trades",
            "subcategory":"Construction",
            "type":"Services"
        }
    ],
    "sg:phone":"+1 360 606 1479",
    "sg:postcode":"98661",
    "sg:province":"WA",
    "sg:tags":[
        "house"
    ],
    "wof:name":"Igor G Construction Inc",
    "wof:placetype":"venue"
},
  "geometry": {"coordinates":[-122.630301,45.65354],"type":"Point"}
}