{
  "type": "Feature",
  "properties": {
    "addr:full":"600 108th Ave NE Ste 750 Bellevue WA 98004",
    "addr:housenumber":"600",
    "addr:postcode":"98004",
    "addr:street":"108Th Ave Ne Ste 750",
    "iso:country":"US",
    "sg:address":"600 108th Ave NE Ste 750",
    "sg:city":"Bellevue",
    "sg:classifiers":[
        {
            "category":"Professional",
            "subcategory":"Employment Agencies",
            "type":"Services"
        }
    ],
    "sg:phone":"+1 425 635 0700",
    "sg:postcode":"98004",
    "sg:province":"WA",
    "wof:name":"Ajilon Staffing",
    "wof:placetype":"venue"
},
  "geometry": {"coordinates":[-122.196067,47.615605],"type":"Point"}
}