{
  "type": "Feature",
  "properties": {
    "addr:full":"3121 10th Ave NE Olympia WA 98506",
    "addr:housenumber":"3121",
    "addr:postcode":"98506",
    "addr:street":"10Th Ave Ne",
    "iso:country":"US",
    "sg:address":"3121 10th Ave NE",
    "sg:city":"Olympia",
    "sg:classifiers":[
        {
            "category":"Manufacturing",
            "subcategory":"Lumber",
            "type":"Manufacturing & Wholesale Goods"
        }
    ],
    "sg:phone":"+1 360 786 1666",
    "sg:postcode":"98506",
    "sg:province":"WA",
    "sg:tags":[
        "operation",
        "timber",
        "tract"
    ],
    "wof:name":"Willard Dalebout",
    "wof:placetype":"venue"
},
  "geometry": {"coordinates":[-122.858808,47.052818],"type":"Point"}
}