{
  "type": "Feature",
  "properties": {
    "addr:full":"1228 Harrison Ave Centralia WA 98531",
    "addr:housenumber":"1228",
    "addr:postcode":"98531",
    "addr:street":"Harrison Ave",
    "iso:country":"US",
    "sg:address":"1228 Harrison Ave",
    "sg:city":"Centralia",
    "sg:classifiers":[
        {
            "category":"Real Estate",
            "subcategory":"Real Estate Operator",
            "type":"Services"
        }
    ],
    "sg:phone":"+1 360 736 6497",
    "sg:postcode":"98531",
    "sg:province":"WA",
    "sg:tags":[
        "mobile",
        "home",
        "site"
    ],
    "wof:name":"Mount View Trailer Park",
    "wof:placetype":"venue"
},
  "geometry": {"coordinates":[-122.984436,46.730526],"type":"Point"}
}