{
  "type": "Feature",
  "properties": {
    "addr:full":"1565 SE Woodridge Dr Port Orchard WA 98366",
    "addr:housenumber":"1565",
    "addr:postcode":"98366",
    "addr:street":"Se Woodridge Dr",
    "iso:country":"US",
    "sg:address":"1565 SE Woodridge Dr",
    "sg:city":"Port Orchard",
    "sg:classifiers":[
        {
            "category":"Health Services",
            "subcategory":"Doctor",
            "type":"Services"
        }
    ],
    "sg:phone":"+1 360 876 2010",
    "sg:postcode":"98366",
    "sg:province":"WA",
    "sg:tags":[
        "dentist"
    ],
    "wof:name":"Naumann Orthodontics",
    "wof:placetype":"venue"
},
  "geometry": {"coordinates":[-122.581767,47.534923],"type":"Point"}
}