{
  "type": "Feature",
  "properties": {
    "addr:full":"11825 93rd Ave E Puyallup WA 98373",
    "addr:housenumber":"11825",
    "addr:postcode":"98373",
    "addr:street":"93Rd Ave E",
    "iso:country":"US",
    "sg:address":"11825 93rd Ave E",
    "sg:city":"Puyallup",
    "sg:classifiers":[
        {
            "category":"Building & Trades",
            "subcategory":"Landscaping Services",
            "type":"Services"
        }
    ],
    "sg:phone":"+1 253 845 9123",
    "sg:postcode":"98373",
    "sg:province":"WA",
    "wof:name":"Gs Lawn Service",
    "wof:placetype":"venue"
},
  "geometry": {"coordinates":[-122.304939,47.150642],"type":"Point"}
}