{
  "type": "Feature",
  "properties": {
    "addr:full":"13540 39th Ave NE Seattle WA 98125",
    "addr:housenumber":"13540",
    "addr:postcode":"98125",
    "addr:street":"39Th Ave Ne",
    "iso:country":"US",
    "sg:address":"13540 39th Ave NE",
    "sg:city":"Seattle",
    "sg:classifiers":[
        {
            "category":"Real Estate",
            "subcategory":"Real Estate Operator",
            "type":"Services"
        }
    ],
    "sg:phone":"+1 206 365 1640",
    "sg:postcode":"98125",
    "sg:province":"WA",
    "sg:tags":[
        "building",
        "nonresidential"
    ],
    "wof:name":"Patten Corporation",
    "wof:placetype":"venue"
},
  "geometry": {"coordinates":[-122.286832,47.727905],"type":"Point"}
}