{
  "type": "Feature",
  "properties": {
    "addr:full":"355 118th Ave SE Bellevue WA 98005",
    "addr:housenumber":"355",
    "addr:postcode":"98005",
    "addr:street":"118Th Ave Se",
    "iso:country":"US",
    "sg:address":"355 118th Ave SE",
    "sg:city":"Bellevue",
    "sg:classifiers":[
        {
            "category":"Professional",
            "subcategory":"Engineering",
            "type":"Services"
        }
    ],
    "sg:phone":"+1 425 454 3555",
    "sg:postcode":"98005",
    "sg:province":"WA",
    "sg:tags":[
        "engineer"
    ],
    "wof:name":"Casne Engineering Inc",
    "wof:placetype":"venue"
},
  "geometry": {"coordinates":[-122.182841,47.605879],"type":"Point"}
}