{
  "type": "Feature",
  "properties": {
    "addr:full":"2302 E Q St Tacoma WA 98421",
    "addr:housenumber":"2302",
    "addr:postcode":"98421",
    "addr:street":"E Q St",
    "iso:country":"US",
    "sg:address":"2302 E Q St",
    "sg:city":"Tacoma",
    "sg:classifiers":[
        {
            "category":"Building & Trades",
            "subcategory":"Equipment Rental",
            "type":"Services"
        }
    ],
    "sg:phone":"+1 253 383 1515",
    "sg:postcode":"98421",
    "sg:province":"WA",
    "sg:tags":[
        "contractor"
    ],
    "sg:website":"www.rentalservice.com",
    "wof:name":"Rental Service Corp",
    "wof:placetype":"venue"
},
  "geometry": {"coordinates":[-122.40935500000001,47.241899],"type":"Point"}
}