{
  "type": "Feature",
  "properties": {
    "addr:full":"8419 S 116th St Seattle WA 98178",
    "addr:housenumber":"8419",
    "addr:postcode":"98178",
    "addr:street":"S 116Th St",
    "iso:country":"US",
    "sg:address":"8419 S 116th St",
    "sg:city":"Seattle",
    "sg:classifiers":[
        {
            "category":"Home & Garden",
            "subcategory":"Building Materials",
            "type":"Retail Goods"
        },
        {
            "category":"Building & Trades",
            "subcategory":"Construction",
            "type":"Services"
        },
        {
            "category":"Manufacturing",
            "subcategory":"Building Materials",
            "type":"Manufacturing & Wholesale Goods"
        }
    ],
    "sg:phone":"+1 206 772 0199",
    "sg:postcode":"98178",
    "sg:province":"WA",
    "sg:tags":[
        "doors-wholesale",
        "installation",
        "windows-repair",
        "accessory",
        "window",
        "doors",
        "frames",
        "replacement",
        "manufacturer"
    ],
    "wof:name":"R H D Window & Door Sales & Distribution",
    "wof:placetype":"venue"
},
  "geometry": {"coordinates":[-122.22717799999999,47.498976],"type":"Point"}
}