{
  "type": "Feature",
  "properties": {
    "addr:full":"175443 Highway 101 Forks WA 98331",
    "addr:housenumber":"175443",
    "addr:postcode":"98331",
    "addr:street":"Highway 101",
    "iso:country":"US",
    "sg:address":"175443 Highway 101",
    "sg:city":"Forks",
    "sg:classifiers":[
        {
            "category":"Recreation",
            "subcategory":"Campground",
            "type":"Entertainment"
        },
        {
            "category":"Travel",
            "subcategory":"Resort",
            "type":"Entertainment"
        },
        {
            "category":"Recreation",
            "type":"Entertainment"
        }
    ],
    "sg:phone":"+1 360 374 5566",
    "sg:postcode":"98331",
    "sg:province":"WA",
    "sg:tags":[
        "recreational",
        "park",
        "camps-recreational",
        "vehicle"
    ],
    "wof:name":"Hoh River Resort",
    "wof:placetype":"venue"
},
  "geometry": {"coordinates":[-124.356041,47.891793],"type":"Point"}
}