{
  "type": "Feature",
  "properties": {
    "addr:full":"121 S Arthur St Spokane WA 99202",
    "addr:housenumber":"121",
    "addr:postcode":"99202",
    "addr:street":"S Arthur St",
    "iso:country":"US",
    "sg:address":"121 S Arthur St",
    "sg:city":"Spokane",
    "sg:classifiers":[
        {
            "category":"Health Services",
            "subcategory":"Nursing And Care Facility",
            "type":"Services"
        },
        {
            "category":"Health Services",
            "subcategory":"Health Practitioner",
            "type":"Services"
        },
        {
            "category":"Health Services",
            "subcategory":"Hospice",
            "type":"Services"
        }
    ],
    "sg:phone":"+1 509 456 0438",
    "sg:postcode":"99202",
    "sg:province":"WA",
    "sg:tags":[
        "home",
        "physician",
        "nurse",
        "eldercare-home",
        "assistant"
    ],
    "sg:website":"http://www.hospiceofspokane.org",
    "wof:name":"Hospice Of Spokane",
    "wof:placetype":"venue"
},
  "geometry": {"coordinates":[-117.39529899999999,47.655589],"type":"Point"}
}