{
  "type": "Feature",
  "properties": {
    "addr:full":"10338 Aurora Ave N Seattle WA 98133",
    "addr:housenumber":"10338",
    "addr:postcode":"98133",
    "addr:street":"Aurora Ave N",
    "iso:country":"US",
    "sg:address":"10338 Aurora Ave N",
    "sg:city":"Seattle",
    "sg:classifiers":[
        {
            "category":"Professional",
            "subcategory":"Management & Consulting",
            "type":"Services"
        }
    ],
    "sg:phone":"+1 206 523 1227",
    "sg:postcode":"98133",
    "sg:province":"WA",
    "sg:tags":[
        "bookstore",
        "selling",
        "direct"
    ],
    "wof:name":"Liberty Book Co",
    "wof:placetype":"venue"
},
  "geometry": {"coordinates":[-122.345001,47.703499],"type":"Point"}
}