{
  "type": "Feature",
  "properties": {
    "addr:full":"268 15th St Pomeroy WA 99347",
    "addr:housenumber":"268",
    "addr:postcode":"99347",
    "addr:street":"15Th St",
    "iso:country":"US",
    "sg:address":"268 15th St",
    "sg:city":"Pomeroy",
    "sg:classifiers":[
        {
            "category":"Professional",
            "subcategory":"Detective & Security Services",
            "type":"Services"
        }
    ],
    "sg:phone":"+1 509 843 1232",
    "sg:postcode":"99347",
    "sg:province":"WA",
    "sg:tags":[
        "information",
        "bureau"
    ],
    "wof:name":"Steve A Herres",
    "wof:placetype":"venue"
},
  "geometry": {"coordinates":[-117.59010000000001,46.471822],"type":"Point"}
}