{
  "type": "Feature",
  "properties": {
    "addr:full":"4985 Rd 13.6 SW Royal City WA 99357",
    "addr:postcode":"4985;99357",
    "addr:street":"Rd;Sw",
    "iso:country":"US",
    "sg:address":"4985 Rd 13.6 SW",
    "sg:city":"Royal City",
    "sg:classifiers":[
        {
            "category":"Wholesale",
            "subcategory":"Farm Supplies",
            "type":"Manufacturing & Wholesale Goods"
        }
    ],
    "sg:phone":"+1 509 346 2223",
    "sg:postcode":"99357",
    "sg:province":"WA",
    "sg:tags":[
        "fertilizer"
    ],
    "wof:name":"Simplot Grower Solutions",
    "wof:placetype":"venue"
},
  "geometry": {"coordinates":[-119.598552,46.886416],"type":"Point"}
}