{
  "type": "Feature",
  "properties": {
    "addr:full":"25401 SE 192nd St Maple Valley WA 98038",
    "addr:postcode":"25401;98038",
    "addr:street":"Se 192Nd St",
    "iso:country":"US",
    "sg:address":"25401 SE 192nd St",
    "sg:city":"Maple Valley",
    "sg:classifiers":[
        {
            "category":"Farming",
            "subcategory":"Nursery",
            "type":"Manufacturing & Wholesale Goods"
        }
    ],
    "sg:phone":"+1 425 432 9113",
    "sg:postcode":"98038",
    "sg:province":"WA",
    "sg:tags":[
        "ornamental",
        "supply"
    ],
    "wof:name":"Classic Care Nursery Inc",
    "wof:placetype":"venue"
},
  "geometry": {"coordinates":[-122.002943,47.429377],"type":"Point"}
}