{
  "type": "Feature",
  "properties": {
    "addr:full":"9835 Case Rd SW Olympia WA 98512",
    "addr:housenumber":"9835",
    "addr:postcode":"98512",
    "addr:street":"Case Rd Sw",
    "iso:country":"US",
    "sg:address":"9835 Case Rd SW",
    "sg:city":"Olympia",
    "sg:classifiers":[
        {
            "category":"Freight",
            "type":"Transportation"
        }
    ],
    "sg:phone":"+1 360 943 9456",
    "sg:postcode":"98512",
    "sg:province":"WA",
    "sg:tags":[
        "operator",
        "local",
        "trucking"
    ],
    "wof:name":"Rl Haynie Trucking Inc",
    "wof:placetype":"venue"
},
  "geometry": {"coordinates":[-122.92037999999999,46.946858],"type":"Point"}
}