{
  "type": "Feature",
  "properties": {
    "addr:full":"699 Morton Rd Morton WA 98356",
    "addr:housenumber":"699",
    "addr:postcode":"98356",
    "addr:street":"Morton Rd",
    "iso:country":"US",
    "sg:address":"699 Morton Rd",
    "sg:city":"Morton",
    "sg:classifiers":[
        {
            "category":"Utilities",
            "subcategory":"Fuel Oil & Lpg",
            "type":"Services"
        }
    ],
    "sg:phone":"+1 360 496 6330",
    "sg:postcode":"98356",
    "sg:province":"WA",
    "sg:tags":[
        "liquefied",
        "gas",
        "petroleum"
    ],
    "wof:name":"Evergreen Propane",
    "wof:placetype":"venue"
},
  "geometry": {"coordinates":[-122.247469,46.582989],"type":"Point"}
}