{
  "type": "Feature",
  "properties": {
    "addr:full":"14019 NE 8th St Bellevue WA 98007",
    "addr:housenumber":"14019",
    "addr:postcode":"98007",
    "addr:street":"Ne 8Th St",
    "iso:country":"US",
    "sg:address":"14019 NE 8th St",
    "sg:city":"Bellevue",
    "sg:classifiers":[
        {
            "category":"Building & Trades",
            "subcategory":"Construction",
            "type":"Services"
        }
    ],
    "sg:phone":"+1 425 747 7035",
    "sg:postcode":"98007",
    "sg:province":"WA",
    "sg:tags":[
        "contractor"
    ],
    "wof:name":"Lifetime Roofing Technologies",
    "wof:placetype":"venue"
},
  "geometry": {"coordinates":[-122.15222799999999,47.617064],"type":"Point"}
}