{
  "type": "Feature",
  "properties": {
    "addr:full":"2313 129th Ave SE Bellevue WA 98005",
    "addr:housenumber":"2313",
    "addr:postcode":"98005",
    "addr:street":"129Th Ave Se",
    "iso:country":"US",
    "sg:address":"2313 129th Ave SE",
    "sg:city":"Bellevue",
    "sg:classifiers":[
        {
            "category":"Professional",
            "type":"Services"
        }
    ],
    "sg:phone":"+1 425 641 8173",
    "sg:postcode":"98005",
    "sg:province":"WA",
    "wof:name":"Tiger Forest Products",
    "wof:placetype":"venue"
},
  "geometry": {"coordinates":[-122.168189,47.587893],"type":"Point"}
}