{
  "type": "Feature",
  "properties": {
    "iso:country":"US",
    "sg:address":"1102 St Paul Ave",
    "sg:city":"Tacoma",
    "sg:classifiers":[
        {
            "category":"Manufacturing",
            "subcategory":"Lumber",
            "type":"Manufacturing & Wholesale Goods"
        }
    ],
    "sg:phone":"+1 253 627 8848",
    "sg:postcode":"98421",
    "sg:province":"WA",
    "sg:tags":[
        "wood",
        "mill",
        "industrial",
        "mfg"
    ],
    "sg:website":"www.lindalcedarhomes.com",
    "wof:name":"Western Dry Kilns Inc",
    "wof:placetype":"venue"
},
  "geometry": {"coordinates":[-122.427291,47.254191],"type":"Point"}
}