{
  "type": "Feature",
  "properties": {
    "addr:full":"752 SE Ridgeview St Pullman WA 99163",
    "addr:housenumber":"752",
    "addr:postcode":"99163",
    "addr:street":"Se Ridgeview St",
    "iso:country":"US",
    "sg:address":"752 SE Ridgeview St",
    "sg:city":"Pullman",
    "sg:classifiers":[
        {
            "category":"Health Services",
            "subcategory":"Health Practitioner",
            "type":"Services"
        }
    ],
    "sg:phone":"+1 509 335 5089",
    "sg:postcode":"99163",
    "sg:province":"WA",
    "wof:name":"Franks Audiology",
    "wof:placetype":"venue"
},
  "geometry": {"coordinates":[-117.172085,46.724727],"type":"Point"}
}