{
  "type": "Feature",
  "properties": {
    "addr:full":"4821 S Kent Des Moines Rd Kent WA 98032",
    "addr:housenumber":"4821",
    "addr:postcode":"98032",
    "addr:street":"S Kent Des Moines Rd",
    "iso:country":"US",
    "sg:address":"4821 S Kent Des Moines Rd",
    "sg:city":"Kent",
    "sg:classifiers":[
        {
            "category":"Retail",
            "subcategory":"Repair Shop",
            "type":"Services"
        }
    ],
    "sg:phone":"+1 253 854 6066",
    "sg:postcode":"98032",
    "sg:province":"WA",
    "sg:tags":[
        "electrical"
    ],
    "wof:name":"Appliance Pro",
    "wof:placetype":"venue"
},
  "geometry": {"coordinates":[-122.269616,47.376307],"type":"Point"}
}