{
  "type": "Feature",
  "properties": {
    "addr:full":"15214 42nd Ave E Tacoma WA 98446",
    "addr:housenumber":"15214",
    "addr:postcode":"98446",
    "addr:street":"42Nd Ave E",
    "iso:country":"US",
    "sg:address":"15214 42nd Ave E",
    "sg:city":"Tacoma",
    "sg:classifiers":[
        {
            "category":"Arena",
            "subcategory":"Sports Club",
            "type":"Entertainment"
        }
    ],
    "sg:phone":"+1 253 539 5835",
    "sg:postcode":"98446",
    "sg:province":"WA",
    "sg:tags":[
        "soccer"
    ],
    "wof:name":"Nortac Soccer Club",
    "wof:placetype":"venue"
},
  "geometry": {"coordinates":[-122.3725,47.117531],"type":"Point"}
}