{
  "type": "Feature",
  "properties": {
    "addr:full":"5810 S Gove St Tacoma WA 98409",
    "addr:housenumber":"5810",
    "addr:postcode":"98409",
    "addr:street":"S Gove St",
    "iso:country":"US",
    "sg:address":"5810 S Gove St",
    "sg:city":"Tacoma",
    "sg:classifiers":[
        {
            "category":"Social Services",
            "subcategory":"Child Care",
            "type":"Services"
        }
    ],
    "sg:phone":"+1 253 475 6370",
    "sg:postcode":"98409",
    "sg:province":"WA",
    "sg:tags":[
        "day"
    ],
    "wof:name":"All Gods Children",
    "wof:placetype":"venue"
},
  "geometry": {"coordinates":[-122.499624,47.204489],"type":"Point"}
}