{
  "type": "Feature",
  "properties": {
    "addr:full":"154 Brock St Walla Walla WA 99362",
    "addr:housenumber":"154",
    "addr:postcode":"99362",
    "addr:street":"Brock St",
    "iso:country":"US",
    "sg:address":"154 Brock St",
    "sg:city":"Walla Walla",
    "sg:classifiers":[
        {
            "category":"Building & Trades",
            "subcategory":"Construction",
            "type":"Services"
        }
    ],
    "sg:phone":"+1 509 529 6967",
    "sg:postcode":"99362",
    "sg:province":"WA",
    "sg:tags":[
        "house"
    ],
    "wof:name":"SRN Construction",
    "wof:placetype":"venue"
},
  "geometry": {"coordinates":[-118.302858,46.069908],"type":"Point"}
}