{
  "type": "Feature",
  "properties": {
    "addr:full":"2203 Grandview Dr W Tacoma WA 98466",
    "addr:housenumber":"2203",
    "addr:postcode":"98466",
    "addr:street":"Grandview Dr W",
    "iso:country":"US",
    "sg:address":"2203 Grandview Dr W",
    "sg:city":"Tacoma",
    "sg:classifiers":[
        {
            "category":"Professional",
            "subcategory":"Business Services",
            "type":"Services"
        }
    ],
    "sg:phone":"+1 253 566 6877",
    "sg:postcode":"98466",
    "sg:province":"WA",
    "wof:name":"Techno Primitive Designs",
    "wof:placetype":"venue"
},
  "geometry": {"coordinates":[-122.550265,47.239924],"type":"Point"}
}