{
  "type": "Feature",
  "properties": {
    "addr:full":"1826 N Woodruff Rd Spokane WA 99206",
    "addr:housenumber":"1826",
    "addr:postcode":"99206",
    "addr:street":"N Woodruff Rd",
    "iso:country":"US",
    "sg:address":"1826 N Woodruff Rd",
    "sg:city":"Spokane",
    "sg:classifiers":[
        {
            "category":"Building & Trades",
            "subcategory":"Plumbing",
            "type":"Services"
        }
    ],
    "sg:phone":"+1 509 924 3946",
    "sg:postcode":"99206",
    "sg:province":"WA",
    "sg:tags":[
        "contractor"
    ],
    "wof:name":"Allphase Mechanical",
    "wof:placetype":"venue"
},
  "geometry": {"coordinates":[-117.271952,47.673852],"type":"Point"}
}