{
  "type": "Feature",
  "properties": {
    "addr:full":"1300 N Miller St Wenatchee WA 98801",
    "addr:housenumber":"1300",
    "addr:postcode":"98801",
    "addr:street":"N Miller St",
    "iso:country":"US",
    "sg:address":"1300 N Miller St",
    "sg:city":"Wenatchee",
    "sg:classifiers":[
        {
            "category":"Shopping",
            "subcategory":"Clothing, Apparel, & Fashions",
            "type":"Retail Goods"
        }
    ],
    "sg:phone":"+1 509 662 0874",
    "sg:postcode":"98801",
    "sg:province":"WA",
    "wof:name":"Maurices",
    "wof:placetype":"venue"
},
  "geometry": {"coordinates":[-120.32482299999999,47.440632],"type":"Point"}
}