{
  "type": "Feature",
  "properties": {
    "addr:full":"1801 S 84th St Apt L Tacoma WA 98444",
    "addr:housenumber":"1801",
    "addr:postcode":"98444",
    "addr:street":"S 84Th St Apt L",
    "iso:country":"US",
    "sg:address":"1801 S 84th St Apt L",
    "sg:city":"Tacoma",
    "sg:classifiers":[
        {
            "category":"Real Estate",
            "subcategory":"Real Estate Operator",
            "type":"Services"
        }
    ],
    "sg:phone":"+1 253 539 9259",
    "sg:postcode":"98444",
    "sg:province":"WA",
    "sg:tags":[
        "apartment"
    ],
    "wof:name":"Pacific Point",
    "wof:placetype":"venue"
},
  "geometry": {"coordinates":[-122.462464,47.181177],"type":"Point"}
}