{
  "type": "Feature",
  "properties": {
    "addr:full":"867 S College Ave College Place WA 99324",
    "addr:housenumber":"867",
    "addr:postcode":"99324",
    "addr:street":"S College Ave",
    "iso:country":"US",
    "sg:address":"867 S College Ave",
    "sg:city":"College Place",
    "sg:classifiers":[
        {
            "category":"Wholesale",
            "subcategory":"Construction Materials",
            "type":"Manufacturing & Wholesale Goods"
        }
    ],
    "sg:phone":"+1 509 529 9113",
    "sg:postcode":"99324",
    "sg:province":"WA",
    "wof:name":"Ronald L Jolliffe",
    "wof:placetype":"venue"
},
  "geometry": {"coordinates":[-118.38847199999999,46.041461],"type":"Point"}
}