{
  "type": "Feature",
  "properties": {
    "addr:full":"11010 61st Ave E Puyallup WA 98373",
    "addr:housenumber":"11010",
    "addr:postcode":"98373",
    "addr:street":"61St Ave E",
    "iso:country":"US",
    "sg:address":"11010 61st Ave E",
    "sg:city":"Puyallup",
    "sg:classifiers":[
        {
            "category":"Building & Trades",
            "subcategory":"Construction",
            "type":"Services"
        }
    ],
    "sg:phone":"+1 253 446 9777",
    "sg:postcode":"98373",
    "sg:province":"WA",
    "sg:tags":[
        "carpentry",
        "contractor"
    ],
    "wof:name":"Jacobs Windows",
    "wof:placetype":"venue"
},
  "geometry": {"coordinates":[-122.347544,47.155978],"type":"Point"}
}