{
  "type": "Feature",
  "properties": {
    "addr:full":"12645 Stone Way N Seattle WA 98133",
    "addr:housenumber":"12645",
    "addr:postcode":"98133",
    "addr:street":"Stone Way N",
    "iso:country":"US",
    "sg:address":"12645 Stone Way N",
    "sg:city":"Seattle",
    "sg:classifiers":[
        {
            "category":"Communications",
            "subcategory":"Television Station",
            "type":"Services"
        }
    ],
    "sg:postcode":"98133",
    "sg:province":"WA",
    "sg:tags":[
        "provider"
    ],
    "sg:website":"www.comcast.com",
    "wof:name":"Comcast Cable Store",
    "wof:placetype":"venue"
},
  "geometry": {"coordinates":[-122.343079,47.721822],"type":"Point"}
}