{
  "type": "Feature",
  "properties": {
    "addr:full":"2900 1st Ave S Seattle WA 98134",
    "addr:housenumber":"2900",
    "addr:postcode":"98134",
    "addr:street":"1St Ave S",
    "iso:country":"US",
    "sg:address":"2900 1st Ave S",
    "sg:city":"Seattle",
    "sg:classifiers":[
        {
            "category":"Wholesale",
            "subcategory":"Non-durable Goods",
            "type":"Manufacturing & Wholesale Goods"
        }
    ],
    "sg:phone":"+1 206 624 2494",
    "sg:postcode":"98134",
    "sg:province":"WA",
    "sg:tags":[
        "aluminum",
        "product",
        "paper",
        "foil",
        "ribbon"
    ],
    "wof:name":"Katz Paper Foil & Cordage",
    "wof:placetype":"venue"
},
  "geometry": {"coordinates":[-122.334205,47.575573],"type":"Point"}
}