{
  "type": "Feature",
  "properties": {
    "addr:full":"133 State St Sedro Woolley WA 98284",
    "addr:housenumber":"133",
    "addr:postcode":"98284",
    "addr:street":"State St",
    "iso:country":"US",
    "sg:address":"133 State St",
    "sg:city":"Sedro Woolley",
    "sg:classifiers":[
        {
            "category":"Shopping",
            "subcategory":"Used Merchandise",
            "type":"Retail Goods"
        }
    ],
    "sg:phone":"+1 360 855 3367",
    "sg:postcode":"98284",
    "sg:province":"WA",
    "wof:name":"Past Times",
    "wof:placetype":"venue"
},
  "geometry": {"coordinates":[-122.239057,48.503249],"type":"Point"}
}