{
  "type": "Feature",
  "properties": {
    "addr:full":"3643 169th Ave NE Bellevue WA 98008",
    "addr:housenumber":"3643",
    "addr:postcode":"98008",
    "addr:street":"169Th Ave Ne",
    "iso:country":"US",
    "sg:address":"3643 169th Ave NE",
    "sg:city":"Bellevue",
    "sg:classifiers":[
        {
            "category":"Banks & Credit Unions",
            "subcategory":"Bank",
            "type":"Services"
        }
    ],
    "sg:phone":"+1 425 869 8708",
    "sg:postcode":"98008",
    "sg:province":"WA",
    "sg:tags":[
        "mortgage"
    ],
    "wof:name":"Bfc Funding",
    "wof:placetype":"venue"
},
  "geometry": {"coordinates":[-122.11438699999999,47.642569],"type":"Point"}
}