{
  "type": "Feature",
  "properties": {
    "addr:full":"616 Broadway E Seattle WA 98102",
    "addr:housenumber":"616",
    "addr:postcode":"98102",
    "addr:street":"Broadway",
    "iso:country":"US",
    "sg:address":"616 Broadway E",
    "sg:city":"Seattle",
    "sg:classifiers":[
        {
            "category":"Restaurant",
            "type":"Food & Drink"
        }
    ],
    "sg:phone":"+1 206 324 0892",
    "sg:postcode":"98102",
    "sg:province":"WA",
    "sg:tags":[
        "eating"
    ],
    "wof:name":"Siam On Broadway",
    "wof:placetype":"venue"
},
  "geometry": {"coordinates":[-122.32086,47.624922],"type":"Point"}
}