{
  "type": "Feature",
  "properties": {
    "addr:full":"2001 6th Ave Ste 1701 Seattle WA 98121",
    "addr:housenumber":"2001",
    "addr:postcode":"98121",
    "addr:street":"6Th Ave Ste 1701",
    "iso:country":"US",
    "sg:address":"2001 6th Ave Ste 1701",
    "sg:city":"Seattle",
    "sg:classifiers":[
        {
            "category":"Wholesale",
            "subcategory":"Non-durable Goods",
            "type":"Manufacturing & Wholesale Goods"
        }
    ],
    "sg:phone":"+1 206 441 4600",
    "sg:postcode":"98121",
    "sg:province":"WA",
    "sg:tags":[
        "merchandise-wholesale"
    ],
    "wof:name":"Dalian - 2005 Seattle",
    "wof:placetype":"venue"
},
  "geometry": {"coordinates":[-122.338318,47.614391],"type":"Point"}
}