{
  "type": "Feature",
  "properties": {
    "addr:full":"416 SW State St Pullman WA 99163",
    "addr:housenumber":"416",
    "addr:postcode":"99163",
    "addr:street":"Sw State St",
    "iso:country":"US",
    "sg:address":"416 SW State St",
    "sg:city":"Pullman",
    "sg:classifiers":[
        {
            "category":"Structure",
            "subcategory":"Office Building",
            "type":"Public Place"
        }
    ],
    "sg:phone":"+1 509 432 1729",
    "sg:postcode":"99163",
    "sg:province":"WA",
    "sg:tags":[
        "park"
    ],
    "wof:name":"Rjh Properties",
    "wof:placetype":"venue"
},
  "geometry": {"coordinates":[-117.18603899999999,46.727032],"type":"Point"}
}