{
  "type": "Feature",
  "properties": {
    "addr:full":"88 Front St S Issaquah WA 98027",
    "addr:housenumber":"88",
    "addr:postcode":"98027",
    "addr:street":"Front St S Issaquah",
    "iso:country":"US",
    "sg:address":"88 Front St S",
    "sg:city":"Issaquah",
    "sg:classifiers":[
        {
            "category":"Shopping",
            "subcategory":"Books",
            "type":"Retail Goods"
        }
    ],
    "sg:phone":"+1 425 391 0686",
    "sg:postcode":"98027",
    "sg:province":"WA",
    "wof:name":"Couth Buzzard Books",
    "wof:placetype":"venue"
},
  "geometry": {"coordinates":[-122.036473,47.530037],"type":"Point"}
}