{
  "type": "Feature",
  "properties": {
    "addr:full":"2444 Paradise Dr Longview WA 98632",
    "addr:housenumber":"2444",
    "addr:postcode":"98632",
    "addr:street":"Paradise Dr",
    "iso:country":"US",
    "sg:address":"2444 Paradise Dr",
    "sg:city":"Longview",
    "sg:classifiers":[
        {
            "category":"Shopping",
            "subcategory":"Florist",
            "type":"Retail Goods"
        }
    ],
    "sg:phone":"+1 360 636 1755",
    "sg:postcode":"98632",
    "sg:province":"WA",
    "wof:name":"Creative Flowers",
    "wof:placetype":"venue"
},
  "geometry": {"coordinates":[-122.919675,46.154898],"type":"Point"}
}