{
  "type": "Feature",
  "properties": {
    "addr:full":"14741 Aurora Ave N Ste 102 Shoreline WA 98133",
    "addr:housenumber":"14741",
    "addr:postcode":"98133",
    "addr:street":"Aurora Ave N Ste 102",
    "iso:country":"US",
    "sg:address":"14741 Aurora Ave N Ste 102",
    "sg:city":"Shoreline",
    "sg:classifiers":[
        {
            "category":"Education",
            "subcategory":"Special Training",
            "type":"Public Place"
        },
        {
            "category":"Communications",
            "type":"Services"
        }
    ],
    "sg:phone":"+1 206 365 0024",
    "sg:postcode":"98133",
    "sg:province":"WA",
    "sg:tags":[
        "translator",
        "interpreter",
        "school",
        "language"
    ],
    "wof:name":"Globalwebtrans",
    "wof:placetype":"venue"
},
  "geometry": {"coordinates":[-122.34516600000001,47.735765],"type":"Point"}
}