{
  "type": "Feature",
  "properties": {
    "addr:full":"10725 SE 237th St Kent WA 98031",
    "addr:housenumber":"10725",
    "addr:postcode":"98031",
    "addr:street":"Se 237Th St",
    "iso:country":"US",
    "sg:address":"10725 SE 237th St",
    "sg:city":"Kent",
    "sg:classifiers":[
        {
            "category":"Professional",
            "subcategory":"Business Services",
            "type":"Services"
        }
    ],
    "sg:phone":"+1 253 850 2384",
    "sg:postcode":"98031",
    "sg:province":"WA",
    "wof:name":"Dlo Enterprises",
    "wof:placetype":"venue"
},
  "geometry": {"coordinates":[-122.198739,47.389516],"type":"Point"}
}