{
  "type": "Feature",
  "properties": {
    "addr:full":"549 156th Avenue SE Bellevue WA 98007",
    "addr:housenumber":"549",
    "addr:postcode":"98007",
    "addr:street":"156Th Avenue Se",
    "iso:country":"US",
    "sg:address":"549 156th Avenue SE",
    "sg:city":"Bellevue",
    "sg:classifiers":[
        {
            "category":"Restaurant",
            "type":"Food & Drink"
        }
    ],
    "sg:phone":"+1 425 213 5392",
    "sg:postcode":"98007",
    "sg:province":"WA",
    "sg:tags":[
        "taiwanese"
    ],
    "wof:name":"Henry's Taiwan",
    "wof:placetype":"venue"
},
  "geometry": {"coordinates":[-122.13154900000001,47.604635],"type":"Point"}
}