{
  "type": "Feature",
  "properties": {
    "addr:full":"13617 9th Avenue Ct NW Gig Harbor WA 98332",
    "addr:housenumber":"13617",
    "addr:postcode":"98332",
    "addr:street":"9Th Avenue Ct Nw",
    "iso:country":"US",
    "sg:address":"13617 9th Avenue Ct NW",
    "sg:city":"Gig Harbor",
    "sg:classifiers":[
        {
            "category":"Building & Trades",
            "subcategory":"Construction",
            "type":"Services"
        }
    ],
    "sg:phone":"+1 253 851 7124",
    "sg:postcode":"98332",
    "sg:province":"WA",
    "sg:tags":[
        "house"
    ],
    "wof:name":"Rogers Homes",
    "wof:placetype":"venue"
},
  "geometry": {"coordinates":[-122.550802,47.383325],"type":"Point"}
}