{
  "type": "Feature",
  "properties": {
    "addr:full":"921 Black Lake Blvd SW Olympia WA 98502",
    "addr:housenumber":"921",
    "addr:postcode":"98502",
    "addr:street":"Black Lake Blvd Sw",
    "iso:country":"US",
    "sg:address":"921 Black Lake Blvd SW",
    "sg:city":"Olympia",
    "sg:classifiers":[
        {
            "category":"Autos & Motor Vehicles",
            "subcategory":"Fuel & Gas Station",
            "type":"Retail Goods"
        }
    ],
    "sg:phone":"+1 360 357 6916",
    "sg:postcode":"98502",
    "sg:province":"WA",
    "sg:tags":[
        "station",
        "gasoline"
    ],
    "wof:name":"Shell",
    "wof:placetype":"venue"
},
  "geometry": {"coordinates":[-122.93452600000001,47.03771],"type":"Point"}
}