{
  "type": "Feature",
  "properties": {
    "addr:full":"14434 Ambaum Boulevard SW Suite 5 Burien WA 98166",
    "addr:housenumber":"14434",
    "addr:postcode":"98166",
    "addr:street":"Ambaum Boulevard Sw Suite 5",
    "iso:country":"US",
    "sg:address":"14434 Ambaum Boulevard SW Suite 5",
    "sg:city":"Burien",
    "sg:classifiers":[
        {
            "category":"Health Services",
            "subcategory":"Doctor",
            "type":"Services"
        },
        {
            "category":"Health Services",
            "subcategory":"Hospital",
            "type":"Services"
        }
    ],
    "sg:phone":"+1 206 244 6625",
    "sg:postcode":"98166",
    "sg:province":"WA",
    "wof:name":"Burien Family Medicine",
    "wof:placetype":"venue"
},
  "geometry": {"coordinates":[-122.34735999999999,47.473728],"type":"Point"}
}