{
  "type": "Feature",
  "properties": {
    "addr:full":"3702 Auburn Way S Ofc Auburn WA 98092",
    "addr:housenumber":"3702",
    "addr:postcode":"98092",
    "addr:street":"Auburn Way S",
    "iso:country":"US",
    "sg:address":"3702 Auburn Way S Ofc",
    "sg:city":"Auburn",
    "sg:classifiers":[
        {
            "category":"Real Estate",
            "subcategory":"Real Estate Services",
            "type":"Services"
        },
        {
            "category":"Real Estate",
            "subcategory":"Real Estate Operator",
            "type":"Services"
        }
    ],
    "sg:phone":"+1 253 939 8836",
    "sg:postcode":"98092",
    "sg:province":"WA",
    "sg:tags":[
        "vacancy",
        "apartment",
        "rental",
        "finder",
        "listing"
    ],
    "sg:website":"http://www.buccaneeraptsga.com",
    "wof:name":"Clearwater Ridge Apts",
    "wof:placetype":"venue"
},
  "geometry": {"coordinates":[-122.177522,47.287962],"type":"Point"}
}