{
  "type": "Feature",
  "properties": {
    "addr:full":"1121 S 299th Pl Federal Way WA 98003",
    "addr:housenumber":"1121",
    "addr:postcode":"98003",
    "addr:street":"S 299Th Pl",
    "iso:country":"US",
    "sg:address":"1121 S 299th Pl",
    "sg:city":"Federal Way",
    "sg:classifiers":[
        {
            "category":"Professional",
            "subcategory":"Management & Consulting",
            "type":"Services"
        }
    ],
    "sg:phone":"+1 253 839 1977",
    "sg:postcode":"98003",
    "sg:province":"WA",
    "sg:tags":[
        "business"
    ],
    "wof:name":"Russell Consulting",
    "wof:placetype":"venue"
},
  "geometry": {"coordinates":[-122.316255,47.336586],"type":"Point"}
}