{
  "type": "Feature",
  "properties": {
    "addr:full":"1228 S 3rd St Mount Vernon WA 98273",
    "addr:housenumber":"1228",
    "addr:postcode":"98273",
    "addr:street":"S 3Rd St",
    "iso:country":"US",
    "sg:address":"1228 S 3rd St",
    "sg:city":"Mount Vernon",
    "sg:classifiers":[
        {
            "category":"Utilities",
            "subcategory":"Telephone",
            "type":"Services"
        }
    ],
    "sg:phone":"+1 360 336 1623",
    "sg:postcode":"98273",
    "sg:province":"WA",
    "sg:tags":[
        "communications"
    ],
    "wof:name":"Summit Systems",
    "wof:placetype":"venue"
},
  "geometry": {"coordinates":[-122.336602,48.413647],"type":"Point"}
}