{
  "type": "Feature",
  "properties": {
    "addr:full":"121 Oneida Rd Naselle WA 98638",
    "addr:housenumber":"121",
    "addr:postcode":"98638",
    "addr:street":"Oneida Rd",
    "iso:country":"US",
    "sg:address":"121 Oneida Rd",
    "sg:city":"Naselle",
    "sg:classifiers":[
        {
            "category":"Shopping",
            "subcategory":"Bicycles & Sporting Goods",
            "type":"Retail Goods"
        }
    ],
    "sg:phone":"+1 360 465 2582",
    "sg:postcode":"98638",
    "sg:province":"WA",
    "wof:name":"Eva Bait & Tackle",
    "wof:placetype":"venue"
},
  "geometry": {"coordinates":[-123.71840899999999,46.303168],"type":"Point"}
}