{
  "type": "Feature",
  "properties": {
    "addr:full":"218 Main St Ste 612 Kirkland WA 98033",
    "addr:housenumber":"218",
    "addr:postcode":"98033",
    "addr:street":"Main St Ste 612",
    "iso:country":"US",
    "sg:address":"218 Main St Ste 612",
    "sg:city":"Kirkland",
    "sg:classifiers":[
        {
            "category":"Building & Trades",
            "subcategory":"Plumbing",
            "type":"Services"
        }
    ],
    "sg:phone":"+1 425 250 8771",
    "sg:postcode":"98033",
    "sg:province":"WA",
    "sg:website":"www.pride-plumbing-plumbers.com/...",
    "wof:name":"Pride Plumbing",
    "wof:placetype":"venue"
},
  "geometry": {"coordinates":[-122.204763,47.67666],"type":"Point"}
}