{
  "type": "Feature",
  "properties": {
    "addr:full":"5412 Myrtle Ave Freeland WA 98249",
    "addr:housenumber":"5412",
    "addr:postcode":"98249",
    "addr:street":"Myrtle Ave",
    "iso:country":"US",
    "sg:address":"5412 Myrtle Ave",
    "sg:city":"Freeland",
    "sg:classifiers":[
        {
            "category":"Building & Trades",
            "subcategory":"Landscaping Services",
            "type":"Services"
        }
    ],
    "sg:phone":"+1 360 331 2691",
    "sg:postcode":"98249",
    "sg:province":"WA",
    "wof:name":"Lawn Ranger of South Whid",
    "wof:placetype":"venue"
},
  "geometry": {"coordinates":[-122.531346,48.014561],"type":"Point"}
}