{
  "type": "Feature",
  "properties": {
    "addr:full":"15407 Westminster Wy N Ste 5-D Shoreline WA 98133",
    "addr:housenumber":"15407",
    "addr:postcode":"98133",
    "addr:street":"Westminster Wy N Ste 5-D",
    "iso:country":"US",
    "sg:address":"15407 Westminster Wy N Ste 5-D",
    "sg:city":"Shoreline",
    "sg:classifiers":[
        {
            "category":"Personal",
            "subcategory":"Beauty Salon",
            "type":"Services"
        }
    ],
    "sg:phone":"+1 206 417 4797",
    "sg:postcode":"98133",
    "sg:province":"WA",
    "sg:tags":[
        "hair"
    ],
    "wof:name":"T & D Hair Design",
    "wof:placetype":"venue"
},
  "geometry": {"coordinates":[-122.34856600000001,47.741066],"type":"Point"}
}