{
  "type": "Feature",
  "properties": {
    "addr:full":"5605 Capitol Blvd S Olympia WA 98501",
    "addr:housenumber":"5605",
    "addr:postcode":"98501",
    "addr:street":"Capitol Blvd S",
    "iso:country":"US",
    "sg:address":"5605 Capitol Blvd S",
    "sg:city":"Olympia",
    "sg:classifiers":[
        {
            "category":"Retail",
            "subcategory":"Auto Repair",
            "type":"Services"
        }
    ],
    "sg:phone":"+1 360 352 5822",
    "sg:postcode":"98501",
    "sg:province":"WA",
    "sg:tags":[
        "general"
    ],
    "wof:name":"Taylor and Sons",
    "wof:placetype":"venue"
},
  "geometry": {"coordinates":[-122.907765,46.99758],"type":"Point"}
}