{
  "type": "Feature",
  "properties": {
    "addr:full":"690 Larson St Friday Harbor WA 98250",
    "addr:housenumber":"690",
    "addr:postcode":"98250",
    "addr:street":"Larson St",
    "iso:country":"US",
    "sg:address":"690 Larson St",
    "sg:city":"Friday Harbor",
    "sg:classifiers":[
        {
            "category":"Professional",
            "subcategory":"Business Services",
            "type":"Services"
        }
    ],
    "sg:phone":"+1 360 378 3345",
    "sg:postcode":"98250",
    "sg:province":"WA",
    "sg:tags":[
        "process",
        "server"
    ],
    "wof:name":"Paper Chase",
    "wof:placetype":"venue"
},
  "geometry": {"coordinates":[-123.024297,48.53993],"type":"Point"}
}