{
  "type": "Feature",
  "properties": {
    "addr:full":"11913 64th Pl S Seattle WA 98178",
    "addr:housenumber":"11913",
    "addr:postcode":"98178",
    "addr:street":"64Th Pl S",
    "iso:country":"US",
    "sg:address":"11913 64th Pl S",
    "sg:city":"Seattle",
    "sg:classifiers":[
        {
            "category":"Social Services",
            "type":"Services"
        }
    ],
    "sg:phone":"+1 206 772 5095",
    "sg:postcode":"98178",
    "sg:province":"WA",
    "wof:name":"Ej Enterprises",
    "wof:placetype":"venue"
},
  "geometry": {"coordinates":[-122.253168,47.49574],"type":"Point"}
}