{
  "type": "Feature",
  "properties": {
    "iso:country":"US",
    "sg:address":"12729 NE 20th St",
    "sg:city":"Bellevue",
    "sg:classifiers":[
        {
            "category":"Professional",
            "subcategory":"Advertising",
            "type":"Services"
        }
    ],
    "sg:phone":"+1 425 453 1630",
    "sg:postcode":"98005",
    "sg:province":"WA",
    "sg:tags":[
        "mail"
    ],
    "wof:name":"Computer Assisted Messages",
    "wof:placetype":"venue"
},
  "geometry": {"coordinates":[-122.168217,47.628083],"type":"Point"}
}