{
  "type": "Feature",
  "properties": {
    "addr:full":"4017 E Lyons Ave Spokane WA 99217",
    "addr:housenumber":"4017",
    "addr:postcode":"99217",
    "addr:street":"E Lyons Ave",
    "iso:country":"US",
    "sg:address":"4017 E Lyons Ave",
    "sg:city":"Spokane",
    "sg:classifiers":[
        {
            "category":"Shopping",
            "subcategory":"Used Merchandise",
            "type":"Retail Goods"
        }
    ],
    "sg:phone":"+1 509 467 9520",
    "sg:postcode":"99217",
    "sg:province":"WA",
    "wof:name":"Mikes Antq Stove Rebuilding",
    "wof:placetype":"venue"
},
  "geometry": {"coordinates":[-117.351426,47.718505],"type":"Point"}
}