{
  "type": "Feature",
  "properties": {
    "addr:full":"3312 Rosedale Street NW Suite 103 Gig Harbor WA 98335",
    "addr:housenumber":"3312",
    "addr:postcode":"98335",
    "addr:street":"Rosedale Street Nw Suite 103",
    "iso:country":"US",
    "sg:address":"3312 Rosedale Street NW Suite 103",
    "sg:city":"Gig Harbor",
    "sg:classifiers":[
        {
            "category":"Professional",
            "subcategory":"Computer Services",
            "type":"Services"
        }
    ],
    "sg:phone":"+1 253 857 8683",
    "sg:postcode":"98335",
    "sg:province":"WA",
    "sg:tags":[
        "politics",
        "social-networking",
        "web-2-0",
        "news",
        "knolwdge",
        "civics",
        "causes",
        "organizations",
        "politicians"
    ],
    "sg:website":"http://www.voteiq.com",
    "wof:name":"Vote iQ",
    "wof:placetype":"venue"
},
  "geometry": {"coordinates":[-122.583704,47.330634],"type":"Point"}
}