{
  "type": "Feature",
  "properties": {
    "addr:full":"4215 SE Mile Hill Dr Port Orchard WA 98366",
    "addr:housenumber":"4215",
    "addr:postcode":"98366",
    "addr:street":"Se Mile Hill Dr",
    "iso:country":"US",
    "sg:address":"4215 SE Mile Hill Dr",
    "sg:city":"Port Orchard",
    "sg:classifiers":[
        {
            "category":"Restaurant",
            "type":"Food & Drink"
        }
    ],
    "sg:phone":"+1 360 871 6363",
    "sg:postcode":"98366",
    "sg:province":"WA",
    "sg:tags":[
        "eating"
    ],
    "wof:name":"Clubhouse Grill & Cocktail Bar",
    "wof:placetype":"venue"
},
  "geometry": {"coordinates":[-122.594042,47.533937],"type":"Point"}
}