{
  "type": "Feature",
  "properties": {
    "addr:full":"656 SE Bayshore Dr Oak Harbor WA 98277",
    "addr:housenumber":"656",
    "addr:postcode":"98277",
    "addr:street":"Se Bayshore Dr",
    "iso:country":"US",
    "sg:address":"656 SE Bayshore Dr",
    "sg:city":"Oak Harbor",
    "sg:classifiers":[
        {
            "category":"Government",
            "subcategory":"Office",
            "type":"Public Place"
        }
    ],
    "sg:phone":"+1 360 679 4220",
    "sg:postcode":"98277",
    "sg:province":"WA",
    "sg:tags":[
        "state",
        "program"
    ],
    "wof:name":"Drivers License Examining",
    "wof:placetype":"venue"
},
  "geometry": {"coordinates":[-122.648383,48.287601],"type":"Point"}
}