{
  "type": "Feature",
  "properties": {
    "iso:country":"US",
    "sg:address":"201 18th Ave",
    "sg:city":"Lewiston",
    "sg:classifiers":[
        {
            "category":"Building & Trades",
            "subcategory":"Construction",
            "type":"Services"
        }
    ],
    "sg:phone":"+1 208 798 8958",
    "sg:postcode":"83501",
    "sg:province":"ID",
    "sg:tags":[
        "roofing",
        "contractor"
    ],
    "wof:name":"All Weather Roofing",
    "wof:placetype":"venue"
},
  "geometry": {"coordinates":[-117.02982299999999,46.402966],"type":"Point"}
}