{
  "type": "Feature",
  "properties": {
    "addr:full":"720 E University Way Ellensburg WA 98926",
    "addr:housenumber":"720",
    "addr:postcode":"98926",
    "addr:street":"E University Way",
    "iso:country":"US",
    "sg:address":"720 E University Way",
    "sg:city":"Ellensburg",
    "sg:classifiers":[
        {
            "category":"Professional",
            "subcategory":"Computer Services",
            "type":"Services"
        }
    ],
    "sg:phone":"+1 509 933 2929",
    "sg:postcode":"98926",
    "sg:province":"WA",
    "sg:tags":[
        "repair"
    ],
    "wof:name":"Complete Computer Svc",
    "wof:placetype":"venue"
},
  "geometry": {"coordinates":[-120.53723599999999,46.999505],"type":"Point"}
}