{
  "type": "Feature",
  "properties": {
    "addr:full":"327 W 8th Ave Spokane WA 99204",
    "addr:housenumber":"327",
    "addr:postcode":"99204",
    "addr:street":"W 8Th Ave",
    "iso:country":"US",
    "sg:address":"327 W 8th Ave",
    "sg:city":"Spokane",
    "sg:classifiers":[
        {
            "category":"Professional",
            "subcategory":"Management & Consulting",
            "type":"Services"
        }
    ],
    "sg:phone":"+1 509 624 5325",
    "sg:postcode":"99204",
    "sg:province":"WA",
    "sg:tags":[
        "construction"
    ],
    "wof:name":"Earl Nelson Corp",
    "wof:placetype":"venue"
},
  "geometry": {"coordinates":[-117.417708,47.649059],"type":"Point"}
}