{
  "type": "Feature",
  "properties": {
    "addr:full":"13102 Ash Way Everett WA 98204",
    "addr:housenumber":"13102",
    "addr:postcode":"98204",
    "addr:street":"Ash Way",
    "iso:country":"US",
    "sg:address":"13102 Ash Way",
    "sg:city":"Everett",
    "sg:classifiers":[
        {
            "category":"Retail",
            "subcategory":"Laundry & Dry Cleaning",
            "type":"Services"
        }
    ],
    "sg:phone":"+1 425 347 0623",
    "sg:postcode":"98204",
    "sg:province":"WA",
    "sg:tags":[
        "cleaner",
        "carpet"
    ],
    "wof:name":"Enviro Tech",
    "wof:placetype":"venue"
},
  "geometry": {"coordinates":[-122.24997500000001,47.87843],"type":"Point"}
}