{
  "type": "Feature",
  "properties": {
    "addr:full":"516 W 4th Ave Toppenish WA 98948",
    "addr:housenumber":"516",
    "addr:postcode":"98948",
    "addr:street":"W 4Th Ave",
    "iso:country":"US",
    "sg:address":"516 W 4th Ave",
    "sg:city":"Toppenish",
    "sg:classifiers":[
        {
            "category":"Health Services",
            "subcategory":"Doctor",
            "type":"Services"
        }
    ],
    "sg:phone":"+1 509 865 3551",
    "sg:postcode":"98948",
    "sg:province":"WA",
    "sg:tags":[
        "physician",
        "surgeon"
    ],
    "wof:name":"Lower Valley Surgical Group",
    "wof:placetype":"venue"
},
  "geometry": {"coordinates":[-120.318376,46.37128],"type":"Point"}
}