{
  "type": "Feature",
  "properties": {
    "addr:full":"508 N 4th Ave Pasco WA 99301",
    "addr:housenumber":"508",
    "addr:postcode":"99301",
    "addr:street":"N 4Th Ave",
    "iso:country":"US",
    "sg:address":"508 N 4th Ave",
    "sg:city":"Pasco",
    "sg:classifiers":[
        {
            "category":"Food & Beverages",
            "subcategory":"Groceries & Convenience Stores",
            "type":"Retail Goods"
        }
    ],
    "sg:phone":"+1 509 547 2491",
    "sg:postcode":"99301",
    "sg:province":"WA",
    "wof:name":"Family Mart",
    "wof:placetype":"venue"
},
  "geometry": {"coordinates":[-119.094345,46.234465],"type":"Point"}
}