{
  "type": "Feature",
  "properties": {
    "addr:full":"17650 140th Ave SE Renton WA 98058",
    "addr:housenumber":"17650",
    "addr:postcode":"98058",
    "addr:street":"140Th Ave Se",
    "iso:country":"US",
    "sg:address":"17650 140th Ave SE",
    "sg:city":"Renton",
    "sg:classifiers":[
        {
            "category":"Personal",
            "subcategory":"Beauty Salon",
            "type":"Services"
        }
    ],
    "sg:phone":"+1 425 277 3531",
    "sg:postcode":"98058",
    "sg:province":"WA",
    "sg:tags":[
        "unisex",
        "hair"
    ],
    "wof:name":"Great Clips",
    "wof:placetype":"venue"
},
  "geometry": {"coordinates":[-122.154101,47.445375],"type":"Point"}
}