{
  "type": "Feature",
  "properties": {
    "addr:full":"1850 E Isaacs Ave Walla Walla WA 99362",
    "addr:housenumber":"1850",
    "addr:postcode":"99362",
    "addr:street":"E Isaacs Ave",
    "iso:country":"US",
    "sg:address":"1850 E Isaacs Ave",
    "sg:city":"Walla Walla",
    "sg:classifiers":[
        {
            "category":"Restaurant",
            "type":"Food & Drink"
        }
    ],
    "sg:phone":"+1 509 522 8229",
    "sg:postcode":"99362",
    "sg:province":"WA",
    "sg:tags":[
        "eating"
    ],
    "wof:name":"TCBY",
    "wof:placetype":"venue"
},
  "geometry": {"coordinates":[-118.308616,46.074957],"type":"Point"}
}