{
  "type": "Feature",
  "properties": {
    "addr:full":"520 Russet Rd Walla Walla WA 99362",
    "addr:housenumber":"520",
    "addr:postcode":"99362",
    "addr:street":"Russet Rd",
    "iso:country":"US",
    "sg:address":"520 Russet Rd",
    "sg:city":"Walla Walla",
    "sg:classifiers":[
        {
            "category":"Building & Trades",
            "subcategory":"Plumbing",
            "type":"Services"
        }
    ],
    "sg:phone":"+1 509 529 2088",
    "sg:postcode":"99362",
    "sg:province":"WA",
    "sg:tags":[
        "contractor",
        "mfg"
    ],
    "wof:name":"Harolds Furnace Cleaning",
    "wof:placetype":"venue"
},
  "geometry": {"coordinates":[-118.414393,46.05212],"type":"Point"}
}