{
  "type": "Feature",
  "properties": {
    "addr:full":"4 Copple Rd Omak WA 98841",
    "addr:housenumber":"4",
    "addr:postcode":"98841",
    "addr:street":"Copple Rd",
    "iso:country":"US",
    "sg:address":"4 Copple Rd",
    "sg:city":"Omak",
    "sg:classifiers":[
        {
            "category":"Building & Trades",
            "subcategory":"Construction",
            "type":"Services"
        }
    ],
    "sg:phone":"+1 509 826 5533",
    "sg:postcode":"98841",
    "sg:province":"WA",
    "sg:tags":[
        "concrete",
        "contractor"
    ],
    "wof:name":"Wells Affordable Concrete",
    "wof:placetype":"venue"
},
  "geometry": {"coordinates":[-119.511409,48.42741],"type":"Point"}
}