{
  "type": "Feature",
  "properties": {
    "addr:full":"119 E Jonathan Rd Bothell WA 98012",
    "addr:housenumber":"119",
    "addr:postcode":"98012",
    "addr:street":"E Jonathan Rd",
    "iso:country":"US",
    "sg:address":"119 E Jonathan Rd",
    "sg:city":"Bothell",
    "sg:classifiers":[
        {
            "category":"Building & Trades",
            "subcategory":"Pest Control",
            "type":"Services"
        }
    ],
    "sg:phone":"+1 425 775 7106",
    "sg:postcode":"98012",
    "sg:province":"WA",
    "sg:tags":[
        "disinfecting"
    ],
    "wof:name":"Guardian Pest Control",
    "wof:placetype":"venue"
},
  "geometry": {"coordinates":[-122.23203599999999,47.827348],"type":"Point"}
}