{
  "type": "Feature",
  "properties": {
    "addr:full":"605 Horizon View Pl NW Bainbridge Isle WA 98110",
    "addr:housenumber":"605",
    "addr:postcode":"98110",
    "addr:street":"Horizon View Pl Nw;Isle",
    "iso:country":"US",
    "sg:address":"605 Horizon View Pl NW",
    "sg:city":"Bainbridge Isle",
    "sg:classifiers":[
        {
            "category":"Building & Trades",
            "subcategory":"Landscaping Services",
            "type":"Services"
        }
    ],
    "sg:phone":"+1 206 842 0642",
    "sg:postcode":"98110",
    "sg:province":"WA",
    "sg:tags":[
        "landscape",
        "contractor"
    ],
    "wof:name":"Landmark Tractor Svc Inc",
    "wof:placetype":"venue"
},
  "geometry": {"coordinates":[-122.527648,47.634407],"type":"Point"}
}