{
  "type": "Feature",
  "properties": {
    "addr:full":"7727 30th St W Tacoma WA 98466",
    "addr:housenumber":"7727",
    "addr:postcode":"98466",
    "addr:street":"30Th St W",
    "iso:country":"US",
    "sg:address":"7727 30th St W",
    "sg:city":"Tacoma",
    "sg:classifiers":[
        {
            "category":"Manufacturing",
            "subcategory":"Wood Products",
            "type":"Manufacturing & Wholesale Goods"
        },
        {
            "category":"Building & Trades",
            "subcategory":"Construction",
            "type":"Services"
        }
    ],
    "sg:phone":"+1 253 564 6447",
    "sg:postcode":"98466",
    "sg:province":"WA",
    "sg:tags":[
        "marble",
        "reconstituted",
        "terrazzo",
        "mfg"
    ],
    "wof:name":"Puget Sound Marble",
    "wof:placetype":"venue"
},
  "geometry": {"coordinates":[-122.541774,47.232638],"type":"Point"}
}