{
  "type": "Feature",
  "properties": {
    "addr:full":"304 S Water St Ellensburg WA 98926",
    "addr:housenumber":"304",
    "addr:postcode":"98926",
    "addr:street":"S Water St",
    "iso:country":"US",
    "sg:address":"304 S Water St",
    "sg:city":"Ellensburg",
    "sg:classifiers":[
        {
            "category":"Shopping",
            "subcategory":"Computers & Home Electronics",
            "type":"Retail Goods"
        }
    ],
    "sg:phone":"+1 509 933 4486",
    "sg:postcode":"98926",
    "sg:province":"WA",
    "wof:name":"Jamin Electronics",
    "wof:placetype":"venue"
},
  "geometry": {"coordinates":[-120.549622,46.990191],"type":"Point"}
}