{
  "type": "Feature",
  "properties": {
    "addr:full":"17204 E Sprague Ave Spokane Valley WA 99016",
    "addr:housenumber":"17204",
    "addr:postcode":"99016",
    "addr:street":"E Sprague Ave",
    "iso:country":"US",
    "sg:address":"17204 E Sprague Ave",
    "sg:city":"Spokane Valley",
    "sg:classifiers":[
        {
            "category":"Building & Trades",
            "subcategory":"Landscaping Services",
            "type":"Services"
        }
    ],
    "sg:phone":"+1 509 922 1787",
    "sg:postcode":"99016",
    "sg:province":"WA",
    "sg:tags":[
        "lawn",
        "maintenance",
        "grounds"
    ],
    "wof:name":"Dach's Professional Lawn",
    "wof:placetype":"venue"
},
  "geometry": {"coordinates":[-117.17165300000001,47.656851],"type":"Point"}
}