{
  "type": "Feature",
  "properties": {
    "addr:full":"6914 Merkel Way NE Olympia WA 98516",
    "addr:housenumber":"6914",
    "addr:postcode":"98516",
    "addr:street":"Merkel Way Ne",
    "iso:country":"US",
    "sg:address":"6914 Merkel Way NE",
    "sg:city":"Olympia",
    "sg:classifiers":[
        {
            "category":"Farming",
            "subcategory":"Livestock Farm",
            "type":"Manufacturing & Wholesale Goods"
        }
    ],
    "sg:phone":"+1 360 456 3367",
    "sg:postcode":"98516",
    "sg:province":"WA",
    "sg:tags":[
        "specialty",
        "animal"
    ],
    "wof:name":"Paws-Attraction",
    "wof:placetype":"venue"
},
  "geometry": {"coordinates":[-122.78870000000001,47.054638],"type":"Point"}
}