{
  "type": "Feature",
  "properties": {
    "addr:full":"16110 8th Ave SW Ste A3 Burien WA 98166",
    "addr:housenumber":"16110",
    "addr:postcode":"98166",
    "addr:street":"8Th Ave Sw Ste A3",
    "iso:country":"US",
    "sg:address":"16110 8th Ave SW Ste A3",
    "sg:city":"Burien",
    "sg:classifiers":[
        {
            "category":"Health Services",
            "subcategory":"Doctor",
            "type":"Services"
        }
    ],
    "sg:phone":"+1 206 244 2422",
    "sg:postcode":"98166",
    "sg:province":"WA",
    "sg:tags":[
        "physician",
        "family",
        "practice",
        "surgeons",
        "medicine",
        "surgeon"
    ],
    "wof:name":"Edward W Hartzler Md Inc",
    "wof:placetype":"venue"
},
  "geometry": {"coordinates":[-122.34462000000001,47.458136],"type":"Point"}
}