{
  "type": "Feature",
  "properties": {
    "addr:full":"6812 129th Pl SE Bellevue WA 98006",
    "addr:housenumber":"6812",
    "addr:postcode":"98006",
    "addr:street":"129Th Pl Se",
    "iso:country":"US",
    "sg:address":"6812 129th Pl SE",
    "sg:city":"Bellevue",
    "sg:classifiers":[
        {
            "category":"Professional",
            "type":"Services"
        }
    ],
    "sg:phone":"+1 425 746 4219",
    "sg:postcode":"98006",
    "sg:province":"WA",
    "wof:name":"John H Eyler",
    "wof:placetype":"venue"
},
  "geometry": {"coordinates":[-122.167843,47.541668],"type":"Point"}
}