{
  "type": "Feature",
  "properties": {
    "addr:full":"4604 80th St SW Mukilteo WA 98275",
    "addr:housenumber":"4604",
    "addr:postcode":"98275",
    "addr:street":"80Th St Sw",
    "iso:country":"US",
    "sg:address":"4604 80th St SW",
    "sg:city":"Mukilteo",
    "sg:classifiers":[
        {
            "category":"Professional",
            "subcategory":"Business Services",
            "type":"Services"
        }
    ],
    "sg:phone":"+1 425 347 2708",
    "sg:postcode":"98275",
    "sg:province":"WA",
    "wof:name":"Absolute Home Inspection",
    "wof:placetype":"venue"
},
  "geometry": {"coordinates":[-122.29631500000001,47.925606],"type":"Point"}
}