{
  "type": "Feature",
  "properties": {
    "addr:full":"16311 177th Ave SE Monroe WA 98272",
    "addr:housenumber":"16311",
    "addr:postcode":"98272",
    "addr:street":"177Th Ave Se",
    "iso:country":"US",
    "sg:address":"16311 177th Ave SE",
    "sg:city":"Monroe",
    "sg:classifiers":[
        {
            "category":"Recreation",
            "subcategory":"Campground",
            "type":"Entertainment"
        }
    ],
    "sg:phone":"+1 360 794 5525",
    "sg:postcode":"98272",
    "sg:province":"WA",
    "sg:tags":[
        "recreational",
        "park",
        "vehicle"
    ],
    "wof:name":"Park Place In Monroe",
    "wof:placetype":"venue"
},
  "geometry": {"coordinates":[-121.993118,47.849029],"type":"Point"}
}