{
  "type": "Feature",
  "properties": {
    "addr:full":"1605 SE Everett Mall Way Everett WA 98208",
    "addr:housenumber":"1605",
    "addr:postcode":"98208",
    "addr:street":"Se Everett Mall Way",
    "iso:country":"US",
    "sg:address":"1605 SE Everett Mall Way",
    "sg:city":"Everett",
    "sg:classifiers":[
        {
            "category":"Shopping",
            "subcategory":"Pharmacy",
            "type":"Retail Goods"
        },
        {
            "category":"Food & Beverages",
            "subcategory":"Groceries & Convenience Stores",
            "type":"Retail Goods"
        }
    ],
    "sg:phone":"+1 425 789 2731",
    "sg:postcode":"98208",
    "sg:province":"WA",
    "wof:name":"Haggen Food & Pharmacy",
    "wof:placetype":"venue"
},
  "geometry": {"coordinates":[-122.212532,47.913078],"type":"Point"}
}