{
  "type": "Feature",
  "properties": {
    "addr:full":"15506 91st Pl NE Bothell WA 98011",
    "addr:housenumber":"15506",
    "addr:postcode":"98011",
    "addr:street":"91St Pl Ne",
    "iso:country":"US",
    "sg:address":"15506 91st Pl NE",
    "sg:city":"Bothell",
    "sg:classifiers":[
        {
            "category":"Wholesale",
            "subcategory":"Non-durable Goods",
            "type":"Manufacturing & Wholesale Goods"
        }
    ],
    "sg:phone":"+1 425 487 6681",
    "sg:postcode":"98011",
    "sg:province":"WA",
    "wof:name":"Margaret Down",
    "wof:placetype":"venue"
},
  "geometry": {"coordinates":[-122.218805,47.741476],"type":"Point"}
}