{
  "type": "Feature",
  "properties": {
    "addr:full":"13213 NE Kerr Rd Vancouver WA 98682",
    "addr:housenumber":"13213",
    "addr:postcode":"98682",
    "addr:street":"Ne Kerr Rd",
    "iso:country":"US",
    "sg:address":"13213 NE Kerr Rd",
    "sg:city":"Vancouver",
    "sg:classifiers":[
        {
            "category":"Building & Trades",
            "subcategory":"Plumbing",
            "type":"Services"
        }
    ],
    "sg:phone":"+1 360 944 7611",
    "sg:postcode":"98682",
    "sg:province":"WA",
    "sg:tags":[
        "conditioning",
        "air",
        "system",
        "contractor"
    ],
    "sg:website":"www.allseasonsheatingandcooling.com",
    "wof:name":"All Seasons Heating & Cooling",
    "wof:placetype":"venue"
},
  "geometry": {"coordinates":[-122.537914,45.672394],"type":"Point"}
}