{
  "type": "Feature",
  "properties": {
    "addr:full":"16309 NE 39th St Vancouver WA 98682",
    "addr:housenumber":"16309",
    "addr:postcode":"98682",
    "addr:street":"Ne 39Th St",
    "iso:country":"US",
    "sg:address":"16309 NE 39th St",
    "sg:city":"Vancouver",
    "sg:classifiers":[
        {
            "category":"Professional",
            "type":"Services"
        }
    ],
    "sg:phone":"+1 360 254 4110",
    "sg:postcode":"98682",
    "sg:province":"WA",
    "wof:name":"Patricia Graber",
    "wof:placetype":"venue"
},
  "geometry": {"coordinates":[-122.503929,45.650235],"type":"Point"}
}