{
  "type": "Feature",
  "properties": {
    "addr:full":"2045 Mildred St W Tacoma WA 98466",
    "addr:housenumber":"2045",
    "addr:postcode":"98466",
    "addr:street":"Mildred St W",
    "iso:country":"US",
    "sg:address":"2045 Mildred St W",
    "sg:city":"Tacoma",
    "sg:classifiers":[
        {
            "category":"Cafe",
            "type":"Food & Drink"
        },
        {
            "category":"Restaurant",
            "type":"Food & Drink"
        }
    ],
    "sg:menulink":"http://www.allmenus.com/wa/tacoma/46643-indochine-cafe/menu/",
    "sg:phone":"+1 253 564 9409",
    "sg:postcode":"98466",
    "sg:province":"WA",
    "sg:tags":[
        "asian",
        "chinese"
    ],
    "wof:name":"Indochine Cafe",
    "wof:placetype":"venue"
},
  "geometry": {"coordinates":[-122.526355,47.241728],"type":"Point"}
}