{
  "type": "Feature",
  "properties": {
    "addr:full":"4117 124th Ave SE Apt 402 Bellevue WA 98006",
    "addr:housenumber":"4117;402",
    "addr:postcode":"98006",
    "addr:street":"124Th Ave Se Apt",
    "iso:country":"US",
    "sg:address":"4117 124th Ave SE Apt 402",
    "sg:city":"Bellevue",
    "sg:classifiers":[
        {
            "category":"Real Estate",
            "subcategory":"Real Estate Operator",
            "type":"Services"
        }
    ],
    "sg:phone":"+1 425 747 4055",
    "sg:postcode":"98006",
    "sg:province":"WA",
    "sg:tags":[
        "apartment"
    ],
    "wof:name":"Tenzen",
    "wof:placetype":"venue"
},
  "geometry": {"coordinates":[-122.17446099999999,47.571842],"type":"Point"}
}