{
  "type": "Feature",
  "properties": {
    "addr:full":"15812 116th Ave NE Bothell WA 98011",
    "addr:housenumber":"15812",
    "addr:postcode":"98011",
    "addr:street":"116Th Ave Ne",
    "iso:country":"US",
    "sg:address":"15812 116th Ave NE",
    "sg:city":"Bothell",
    "sg:classifiers":[
        {
            "category":"Retail",
            "subcategory":"Auto Repair",
            "type":"Services"
        }
    ],
    "sg:phone":"+1 425 481 1101",
    "sg:postcode":"98011",
    "sg:province":"WA",
    "wof:name":"Eric's Auto Repair",
    "wof:placetype":"venue"
},
  "geometry": {"coordinates":[-122.18489700000001,47.742753],"type":"Point"}
}