{
  "type": "Feature",
  "properties": {
    "addr:full":"4105 NE 4th St Renton WA 98059",
    "addr:housenumber":"4105",
    "addr:postcode":"98059",
    "addr:street":"Ne 4Th St",
    "iso:country":"US",
    "sg:address":"4105 NE 4th St",
    "sg:city":"Renton",
    "sg:classifiers":[
        {
            "category":"Autos & Motor Vehicles",
            "subcategory":"Fuel & Gas Station",
            "type":"Retail Goods"
        }
    ],
    "sg:phone":"+1 425 271 1305",
    "sg:postcode":"98059",
    "sg:province":"WA",
    "sg:tags":[
        "oil"
    ],
    "wof:name":"Dan's 76 Highland Svc",
    "wof:placetype":"venue"
},
  "geometry": {"coordinates":[-122.159001,47.488452],"type":"Point"}
}