{
  "type": "Feature",
  "properties": {
    "addr:full":"20902 NE Lucia Falls Rd Yacolt WA 98675",
    "addr:housenumber":"20902",
    "addr:postcode":"98675",
    "addr:street":"Ne Lucia Falls Rd",
    "iso:country":"US",
    "sg:address":"20902 NE Lucia Falls Rd",
    "sg:city":"Yacolt",
    "sg:classifiers":[
        {
            "category":"Professional",
            "subcategory":"Management & Consulting",
            "type":"Services"
        }
    ],
    "sg:phone":"+1 360 686 3518",
    "sg:postcode":"98675",
    "sg:province":"WA",
    "wof:name":"Lucia Valley Enterprises",
    "wof:placetype":"venue"
},
  "geometry": {"coordinates":[-122.458252,45.840457],"type":"Point"}
}