{
  "type": "Feature",
  "properties": {
    "addr:full":"3852 S 66th St Tacoma WA 98409",
    "addr:housenumber":"3852",
    "addr:postcode":"98409",
    "addr:street":"S 66Th St",
    "iso:country":"US",
    "sg:address":"3852 S 66th St",
    "sg:city":"Tacoma",
    "sg:classifiers":[
        {
            "category":"Building & Trades",
            "subcategory":"Cleaning & Sanitation",
            "type":"Services"
        }
    ],
    "sg:phone":"+1 253 531 2144",
    "sg:postcode":"98409",
    "sg:province":"WA",
    "sg:tags":[
        "control",
        "hazardous",
        "material",
        "removal"
    ],
    "sg:website":"http://www.saybr.com",
    "wof:name":"Saybr Contractors Inc",
    "wof:placetype":"venue"
},
  "geometry": {"coordinates":[-122.488513,47.197392],"type":"Point"}
}