{
  "type": "Feature",
  "properties": {
    "addr:full":"12020 E Meridian Ave Puyallup WA 98373",
    "addr:housenumber":"12020",
    "addr:postcode":"98373",
    "addr:street":"E Meridian Ave",
    "iso:country":"US",
    "sg:address":"12020 E Meridian Ave",
    "sg:city":"Puyallup",
    "sg:classifiers":[
        {
            "category":"Government",
            "subcategory":"Office",
            "type":"Public Place"
        }
    ],
    "sg:phone":"+1 253 841 4433",
    "sg:postcode":"98373",
    "sg:province":"WA",
    "sg:tags":[
        "armed",
        "force",
        "recruiting"
    ],
    "wof:name":"US Air Force Recruiting",
    "wof:placetype":"venue"
},
  "geometry": {"coordinates":[-122.293025,47.14729],"type":"Point"}
}