{
  "type": "Feature",
  "properties": {
    "addr:full":"550 SE High St Pullman WA 99163",
    "addr:housenumber":"550",
    "addr:postcode":"99163",
    "addr:street":"Se High St",
    "iso:country":"US",
    "sg:address":"550 SE High St",
    "sg:city":"Pullman",
    "sg:classifiers":[
        {
            "category":"Professional",
            "subcategory":"Computer Services",
            "type":"Services"
        }
    ],
    "sg:phone":"+1 509 334 1722",
    "sg:postcode":"99163",
    "sg:province":"WA",
    "sg:tags":[
        "related"
    ],
    "wof:name":"James Hill Consulting Service",
    "wof:placetype":"venue"
},
  "geometry": {"coordinates":[-117.18191299999999,46.72582],"type":"Point"}
}