{
  "type": "Feature",
  "properties": {
    "addr:full":"298 S Main St Colville WA 99114",
    "addr:housenumber":"298",
    "addr:postcode":"99114",
    "addr:street":"S Main St",
    "iso:country":"US",
    "sg:address":"298 S Main St",
    "sg:city":"Colville",
    "sg:classifiers":[
        {
            "category":"Real Estate",
            "subcategory":"Real Estate Agent",
            "type":"Services"
        }
    ],
    "sg:phone":"+1 509 684 2237",
    "sg:postcode":"99114",
    "sg:province":"WA",
    "wof:name":"Tri County Escrow Company",
    "wof:placetype":"venue"
},
  "geometry": {"coordinates":[-117.905744,48.54227],"type":"Point"}
}