{
  "type": "Feature",
  "properties": {
    "addr:full":"6417 Roosevelt Way NE Seattle WA 98115",
    "addr:housenumber":"6417",
    "addr:postcode":"98115",
    "addr:street":"Roosevelt Way Ne",
    "iso:country":"US",
    "sg:address":"6417 Roosevelt Way NE",
    "sg:city":"Seattle",
    "sg:classifiers":[
        {
            "category":"Cinema",
            "subcategory":"Movie Rental",
            "type":"Entertainment"
        }
    ],
    "sg:phone":"+1 206 522 6952",
    "sg:postcode":"98115",
    "sg:province":"WA",
    "sg:tags":[
        "leasing",
        "video",
        "disc",
        "tape"
    ],
    "wof:name":"Crazy Mike's Video",
    "wof:placetype":"venue"
},
  "geometry": {"coordinates":[-122.31744,47.675688],"type":"Point"}
}