{
  "type": "Feature",
  "properties": {
    "addr:full":"1140 15th Ave Longview WA 98632",
    "addr:housenumber":"1140",
    "addr:postcode":"98632",
    "addr:street":"15Th Ave",
    "iso:country":"US",
    "sg:address":"1140 15th Ave",
    "sg:city":"Longview",
    "sg:classifiers":[
        {
            "category":"Restaurant",
            "type":"Food & Drink"
        }
    ],
    "sg:phone":"+1 360 414 5913",
    "sg:postcode":"98632",
    "sg:province":"WA",
    "wof:name":"La Cabana",
    "wof:placetype":"venue"
},
  "geometry": {"coordinates":[-122.93809400000001,46.134914],"type":"Point"}
}