{
  "type": "Feature",
  "properties": {
    "addr:full":"615 Sycamore St Clarkston WA 99403",
    "addr:housenumber":"615",
    "addr:postcode":"99403",
    "addr:street":"Sycamore St",
    "iso:country":"US",
    "sg:address":"615 Sycamore St",
    "sg:city":"Clarkston",
    "sg:classifiers":[
        {
            "category":"Retail",
            "subcategory":"Repair Shop",
            "type":"Services"
        }
    ],
    "sg:phone":"+1 509 758 5037",
    "sg:postcode":"99403",
    "sg:province":"WA",
    "sg:tags":[
        "electrical"
    ],
    "wof:name":"Teeds Appliance Service",
    "wof:placetype":"venue"
},
  "geometry": {"coordinates":[-117.046733,46.412624],"type":"Point"}
}