{
  "type": "Feature",
  "properties": {
    "addr:full":"31511 64th Ave NW Stanwood WA 98292",
    "addr:housenumber":"31511",
    "addr:postcode":"98292",
    "addr:street":"64Th Ave Nw",
    "iso:country":"US",
    "sg:address":"31511 64th Ave NW",
    "sg:city":"Stanwood",
    "sg:classifiers":[
        {
            "category":"Retail",
            "subcategory":"Repair Shop",
            "type":"Services"
        }
    ],
    "sg:phone":"+1 360 629 6163",
    "sg:postcode":"98292",
    "sg:province":"WA",
    "wof:name":"Friendly Foam Shop",
    "wof:placetype":"venue"
},
  "geometry": {"coordinates":[-122.32034,48.282523],"type":"Point"}
}