{
  "type": "Feature",
  "properties": {
    "addr:full":"22 Kenny Dr Yakima WA 98902",
    "addr:housenumber":"22",
    "addr:postcode":"98902",
    "addr:street":"Kenny Dr",
    "iso:country":"US",
    "sg:address":"22 Kenny Dr",
    "sg:city":"Yakima",
    "sg:classifiers":[
        {
            "category":"Building & Trades",
            "subcategory":"Landscaping Services",
            "type":"Services"
        }
    ],
    "sg:phone":"+1 509 966 7073",
    "sg:postcode":"98902",
    "sg:province":"WA",
    "wof:name":"Mos Mowing Service of Yakima",
    "wof:placetype":"venue"
},
  "geometry": {"coordinates":[-120.55985099999999,46.598771],"type":"Point"}
}