{
  "type": "Feature",
  "properties": {
    "iso:country":"US",
    "sg:address":"9930 Edmonds Way",
    "sg:city":"Edmonds",
    "sg:classifiers":[
        {
            "category":"Autos & Motor Vehicles",
            "subcategory":"Fuel & Gas Station",
            "type":"Retail Goods"
        }
    ],
    "sg:phone":"+1 425 778 2700",
    "sg:postcode":"98020",
    "sg:province":"WA",
    "sg:tags":[
        "oil"
    ],
    "wof:name":"Westgate Chevron",
    "wof:placetype":"venue"
},
  "geometry": {"coordinates":[-122.36465200000001,47.790506],"type":"Point"}
}