{
  "type": "Feature",
  "properties": {
    "addr:full":"2111 Division St Camas WA 98607",
    "addr:housenumber":"2111",
    "addr:postcode":"98607",
    "addr:street":"Division St",
    "iso:country":"US",
    "sg:address":"2111 Division St",
    "sg:city":"Camas",
    "sg:classifiers":[
        {
            "category":"Shopping",
            "subcategory":"Books",
            "type":"Retail Goods"
        }
    ],
    "sg:phone":"+1 360 834 4116",
    "sg:postcode":"98607",
    "sg:province":"WA",
    "sg:tags":[
        "organization",
        "religious"
    ],
    "wof:name":"Church of Living Waters",
    "wof:placetype":"venue"
},
  "geometry": {"coordinates":[-122.41003000000001,45.594932],"type":"Point"}
}