{
  "type": "Feature",
  "properties": {
    "addr:full":"4316 136th Pl SE Bellevue WA 98006",
    "addr:housenumber":"4316",
    "addr:postcode":"98006",
    "addr:street":"136Th Pl Se",
    "iso:country":"US",
    "sg:address":"4316 136th Pl SE",
    "sg:city":"Bellevue",
    "sg:classifiers":[
        {
            "category":"Shopping",
            "subcategory":"Catalog Store",
            "type":"Retail Goods"
        }
    ],
    "sg:phone":"+1 941 920 3961",
    "sg:postcode":"98006",
    "sg:province":"WA",
    "sg:tags":[
        "general"
    ],
    "wof:name":"CC Jarrett Inc",
    "wof:placetype":"venue"
},
  "geometry": {"coordinates":[-122.158119,47.568856],"type":"Point"}
}