{
  "type": "Feature",
  "properties": {
    "iso:country":"US",
    "sg:address":"2322 11th St",
    "sg:city":"Anacortes",
    "sg:classifiers":[
        {
            "category":"Wholesale",
            "subcategory":"Seafood",
            "type":"Manufacturing & Wholesale Goods"
        }
    ],
    "sg:phone":"+1 360 293 9448",
    "sg:postcode":"98221",
    "sg:province":"WA",
    "wof:name":"Pan Fish USA",
    "wof:placetype":"venue"
},
  "geometry": {"coordinates":[-122.634118,48.513641],"type":"Point"}
}