{
  "type": "Feature",
  "properties": {
    "addr:full":"505 N 73rd St Seattle WA 98103",
    "addr:housenumber":"505",
    "addr:postcode":"98103",
    "addr:street":"N 73Rd St",
    "iso:country":"US",
    "sg:address":"505 N 73rd St",
    "sg:city":"Seattle",
    "sg:classifiers":[
        {
            "category":"Shopping",
            "subcategory":"Pets & Pet Supplies",
            "type":"Retail Goods"
        },
        {
            "category":"Retail",
            "subcategory":"Animal Services",
            "type":"Services"
        }
    ],
    "sg:phone":"+1 206 784 8237",
    "sg:postcode":"98103",
    "sg:province":"WA",
    "sg:tags":[
        "grooming",
        "cat",
        "specialty",
        "dog"
    ],
    "wof:name":"Behavioral Resources For Cats",
    "wof:placetype":"venue"
},
  "geometry": {"coordinates":[-122.352293,47.681583],"type":"Point"}
}