{
  "type": "Feature",
  "properties": {
    "addr:full":"21409 72nd Ave S Kent WA 98032",
    "addr:housenumber":"21409",
    "addr:postcode":"98032",
    "addr:street":"72Nd Ave S",
    "iso:country":"US",
    "sg:address":"21409 72nd Ave S",
    "sg:city":"Kent",
    "sg:classifiers":[
        {
            "category":"Manufacturing",
            "subcategory":"Tools & Machinery",
            "type":"Manufacturing & Wholesale Goods"
        }
    ],
    "sg:phone":"+1 253 872 2300",
    "sg:postcode":"98032",
    "sg:province":"WA",
    "sg:tags":[
        "machine",
        "jet",
        "mfg",
        "accessory",
        "water",
        "cutting"
    ],
    "wof:name":"Omax Corporation",
    "wof:placetype":"venue"
},
  "geometry": {"coordinates":[-122.244148,47.410239],"type":"Point"}
}