{
  "type": "Feature",
  "properties": {
    "iso:country":"US",
    "sg:address":"2503 Elm Dr",
    "sg:city":"Lynnwood",
    "sg:classifiers":[
        {
            "category":"Professional",
            "subcategory":"Business Services",
            "type":"Services"
        }
    ],
    "sg:phone":"+1 425 712 1072",
    "sg:postcode":"98036",
    "sg:province":"WA",
    "wof:name":"Cain Marketing Group",
    "wof:placetype":"venue"
},
  "geometry": {"coordinates":[-122.265553,47.804825],"type":"Point"}
}