{
  "type": "Feature",
  "properties": {
    "iso:country":"US",
    "sg:address":"21710 W Valeri Ln",
    "sg:city":"Spokane",
    "sg:classifiers":[
        {
            "category":"Home & Garden",
            "subcategory":"Carpets & Floor Coverings",
            "type":"Retail Goods"
        }
    ],
    "sg:phone":"+1 509 796 3861",
    "sg:postcode":"99224",
    "sg:province":"WA",
    "sg:tags":[
        "installation",
        "sales"
    ],
    "wof:name":"Davis Adams Floor Covering",
    "wof:placetype":"venue"
},
  "geometry": {"coordinates":[-117.707774,47.755886],"type":"Point"}
}