{
  "type": "Feature",
  "properties": {
    "addr:full":"9520 NE 8th St Vancouver WA 98664",
    "addr:housenumber":"9520",
    "addr:postcode":"98664",
    "addr:street":"Ne 8Th St",
    "iso:country":"US",
    "sg:address":"9520 NE 8th St",
    "sg:city":"Vancouver",
    "sg:classifiers":[
        {
            "category":"Building & Trades",
            "subcategory":"Plumbing",
            "type":"Services"
        }
    ],
    "sg:phone":"+1 360 944 2035",
    "sg:postcode":"98664",
    "sg:province":"WA",
    "sg:tags":[
        "contractor"
    ],
    "wof:name":"Sure Flow Plumbing",
    "wof:placetype":"venue"
},
  "geometry": {"coordinates":[-122.575672,45.62705],"type":"Point"}
}