{
  "type": "Feature",
  "properties": {
    "addr:full":"307 Asotin Ave Toppenish WA 98948",
    "addr:housenumber":"307",
    "addr:postcode":"98948",
    "addr:street":"Asotin Ave",
    "iso:country":"US",
    "sg:address":"307 Asotin Ave",
    "sg:city":"Toppenish",
    "sg:classifiers":[
        {
            "category":"Wholesale",
            "subcategory":"Durable Goods & Equipment",
            "type":"Manufacturing & Wholesale Goods"
        }
    ],
    "sg:phone":"+1 509 865 2293",
    "sg:postcode":"98948",
    "sg:province":"WA",
    "sg:tags":[
        "importer"
    ],
    "wof:name":"Formas Importantes",
    "wof:placetype":"venue"
},
  "geometry": {"coordinates":[-120.31087599999999,46.379096],"type":"Point"}
}