{
  "type": "Feature",
  "properties": {
    "addr:full":"1907 Everett Ave Everett WA 98201",
    "addr:housenumber":"1907",
    "addr:postcode":"98201",
    "addr:street":"Everett Ave",
    "iso:country":"US",
    "sg:address":"1907 Everett Ave",
    "sg:city":"Everett",
    "sg:classifiers":[
        {
            "category":"Professional",
            "subcategory":"Lawyer & Legal Services",
            "type":"Services"
        }
    ],
    "sg:phone":"+1 425 259 5511",
    "sg:postcode":"98201",
    "sg:province":"WA",
    "sg:tags":[
        "attorney",
        "criminal",
        "personal",
        "damage",
        "accident",
        "real estate",
        "injury",
        "property",
        "law"
    ],
    "sg:website":"http://www.frankwillson.com",
    "wof:name":"Willson Frank R Attorney At Law",
    "wof:placetype":"venue"
},
  "geometry": {"coordinates":[-122.204252,47.981918],"type":"Point"}
}