{
  "type": "Feature",
  "properties": {
    "addr:full":"11347 17th Ave NE Seattle WA 98125",
    "addr:housenumber":"11347",
    "addr:postcode":"98125",
    "addr:street":"17Th Ave Ne",
    "iso:country":"US",
    "sg:address":"11347 17th Ave NE",
    "sg:city":"Seattle",
    "sg:classifiers":[
        {
            "category":"Manufacturing",
            "subcategory":"Rubber & Plastics",
            "type":"Manufacturing & Wholesale Goods"
        }
    ],
    "sg:phone":"+1 206 362 3289",
    "sg:postcode":"98125",
    "sg:province":"WA",
    "sg:tags":[
        "product",
        "fabricated",
        "mfg"
    ],
    "wof:name":"Austad Art",
    "wof:placetype":"venue"
},
  "geometry": {"coordinates":[-122.310076,47.711724],"type":"Point"}
}