{
  "type": "Feature",
  "properties": {
    "addr:full":"18200 Alderwood Mall Pkwy Lynnwood WA 98037",
    "addr:housenumber":"18200",
    "addr:postcode":"98037",
    "addr:street":"Alderwood Mall Pkwy",
    "iso:country":"US",
    "sg:address":"18200 Alderwood Mall Pkwy",
    "sg:city":"Lynnwood",
    "sg:classifiers":[
        {
            "category":"Travel",
            "subcategory":"Hotels & Motels",
            "type":"Entertainment"
        }
    ],
    "sg:phone":"+1 425 771 1100",
    "sg:postcode":"98037",
    "sg:province":"WA",
    "sg:tags":[
        "operation",
        "eating"
    ],
    "wof:name":"Residence Inn Lynnwood",
    "wof:placetype":"venue"
},
  "geometry": {"coordinates":[-122.268919,47.833639],"type":"Point"}
}