{
  "type": "Feature",
  "properties": {
    "addr:full":"5820 Lakewood Towne Center Blvd SW Lakewood WA 98499",
    "addr:housenumber":"5820",
    "addr:postcode":"98499",
    "addr:street":"Lakewood Towne Center Blvd Sw",
    "iso:country":"US",
    "sg:address":"5820 Lakewood Towne Center Blvd SW",
    "sg:city":"Lakewood",
    "sg:classifiers":[
        {
            "category":"Shopping",
            "subcategory":"Department Store",
            "type":"Retail Goods"
        },
        {
            "category":"Shopping",
            "subcategory":"Clothing, Apparel, & Fashions",
            "type":"Retail Goods"
        },
        {
            "category":"Shopping",
            "subcategory":"Discount & Variety Stores",
            "type":"Retail Goods"
        }
    ],
    "sg:phone":"+1 253 583 8488",
    "sg:postcode":"98499",
    "sg:province":"WA",
    "sg:tags":[
        "clothing"
    ],
    "sg:website":"http://www.rossstores.com",
    "wof:name":"Ross Dress For Less",
    "wof:placetype":"venue"
},
  "geometry": {"coordinates":[-122.514017,47.164673],"type":"Point"}
}