{
  "type": "Feature",
  "properties": {
    "addr:full":"22928 210th Ave SE Maple Valley WA 98038",
    "addr:housenumber":"22928",
    "addr:postcode":"98038",
    "addr:street":"210Th Ave Se;Valley",
    "iso:country":"US",
    "sg:address":"22928 210th Ave SE",
    "sg:city":"Maple Valley",
    "sg:classifiers":[
        {
            "category":"Building & Trades",
            "subcategory":"Construction",
            "type":"Services"
        }
    ],
    "sg:phone":"+1 425 432 5596",
    "sg:postcode":"98038",
    "sg:province":"WA",
    "sg:tags":[
        "house"
    ],
    "wof:name":"Morris Construction",
    "wof:placetype":"venue"
},
  "geometry": {"coordinates":[-122.06127499999999,47.395738],"type":"Point"}
}