{
  "type": "Feature",
  "properties": {
    "addr:full":"220 Makela Ct Kelso WA 98626",
    "addr:housenumber":"220",
    "addr:postcode":"98626",
    "addr:street":"Makela Ct",
    "iso:country":"US",
    "sg:address":"220 Makela Ct",
    "sg:city":"Kelso",
    "sg:classifiers":[
        {
            "category":"Professional",
            "subcategory":"Business Services",
            "type":"Services"
        }
    ],
    "sg:phone":"+1 360 636 3202",
    "sg:postcode":"98626",
    "sg:province":"WA",
    "sg:tags":[
        "water",
        "treatment"
    ],
    "wof:name":"Pacific Water Systems Inc",
    "wof:placetype":"venue"
},
  "geometry": {"coordinates":[-122.76553699999999,46.124628],"type":"Point"}
}