{
  "type": "Feature",
  "properties": {
    "addr:full":"1220 E. Columbia ST Suite 302 Seattle WA 98122",
    "addr:housenumber":"1220",
    "addr:postcode":"98122",
    "addr:street":"E. Columbia St Suite 302",
    "iso:country":"US",
    "sg:address":"1220 E. Columbia ST Suite 302",
    "sg:city":"Seattle",
    "sg:classifiers":[
        {
            "category":"Building & Trades",
            "subcategory":"Construction",
            "type":"Services"
        },
        {
            "category":"Real Estate",
            "subcategory":"Architect",
            "type":"Services"
        }
    ],
    "sg:phone":"+1 206 706 2565",
    "sg:postcode":"98122",
    "sg:province":"WA",
    "sg:tags":[
        "interior",
        "design",
        "contractor"
    ],
    "sg:website":"www.dandastudio.com",
    "wof:name":"D+A Studio",
    "wof:placetype":"venue"
},
  "geometry": {"coordinates":[-122.315842,47.609476],"type":"Point"}
}