{
  "type": "Feature",
  "properties": {
    "addr:full":"1840 Iron St Bellingham WA 98225",
    "addr:housenumber":"1840",
    "addr:postcode":"98225",
    "addr:street":"Iron St",
    "iso:country":"US",
    "sg:address":"1840 Iron St",
    "sg:city":"Bellingham",
    "sg:classifiers":[
        {
            "category":"Health Services",
            "subcategory":"Clinic",
            "type":"Services"
        }
    ],
    "sg:phone":"+1 360 647 6700",
    "sg:postcode":"98225",
    "sg:province":"WA",
    "sg:tags":[
        "examination",
        "insurance"
    ],
    "wof:name":"Independent Paramedical",
    "wof:placetype":"venue"
},
  "geometry": {"coordinates":[-122.466263,48.752262],"type":"Point"}
}