{
  "type": "Feature",
  "properties": {
    "addr:full":"200 S Dayton St Kennewick WA 99336",
    "addr:housenumber":"200",
    "addr:postcode":"99336",
    "addr:street":"S Dayton St",
    "iso:country":"US",
    "sg:address":"200 S Dayton St",
    "sg:city":"Kennewick",
    "sg:classifiers":[
        {
            "category":"Education",
            "subcategory":"School",
            "type":"Public Place"
        }
    ],
    "sg:phone":"+1 509 585 3156",
    "sg:postcode":"99336",
    "sg:province":"WA",
    "sg:tags":[
        "center",
        "discovery"
    ],
    "wof:name":"Keewaydin Discovery Center",
    "wof:placetype":"venue"
},
  "geometry": {"coordinates":[-119.12298800000001,46.205812],"type":"Point"}
}