{
  "type": "Feature",
  "properties": {
    "addr:full":"27057 Frodesen Cir NE Kingston WA 98346",
    "addr:postcode":"27057;98346",
    "addr:street":"Frodesen Cir Ne",
    "iso:country":"US",
    "sg:address":"27057 Frodesen Cir NE",
    "sg:city":"Kingston",
    "sg:classifiers":[
        {
            "category":"Building & Trades",
            "subcategory":"Construction",
            "type":"Services"
        }
    ],
    "sg:phone":"+1 360 297 2436",
    "sg:postcode":"98346",
    "sg:province":"WA",
    "sg:tags":[
        "contractor"
    ],
    "wof:name":"Michael Bateman Bldg Constr",
    "wof:placetype":"venue"
},
  "geometry": {"coordinates":[-122.57185,47.806483],"type":"Point"}
}