{
  "type": "Feature",
  "properties": {
    "addr:full":"322 N Spokane Falls Ct Spokane WA 99201",
    "addr:housenumber":"322",
    "addr:postcode":"99201",
    "addr:street":"N Spokane Falls Ct",
    "iso:country":"US",
    "sg:address":"322 N Spokane Falls Ct",
    "sg:city":"Spokane",
    "sg:classifiers":[
        {
            "category":"Professional",
            "type":"Services"
        }
    ],
    "sg:phone":"+1 509 835 4205",
    "sg:postcode":"99201",
    "sg:province":"WA",
    "sg:tags":[
        "establishment"
    ],
    "wof:name":"Cariblner International",
    "wof:placetype":"venue"
},
  "geometry": {"coordinates":[-117.41457200000001,47.660592],"type":"Point"}
}