{
  "type": "Feature",
  "properties": {
    "addr:full":"110 Curtiss St Port Hadlock WA 98339",
    "addr:housenumber":"110",
    "addr:postcode":"98339",
    "addr:street":"Curtiss St",
    "iso:country":"US",
    "sg:address":"110 Curtiss St",
    "sg:city":"Port Hadlock",
    "sg:classifiers":[
        {
            "category":"Manufacturing",
            "subcategory":"Printing",
            "type":"Manufacturing & Wholesale Goods"
        }
    ],
    "sg:phone":"+1 360 379 8800",
    "sg:postcode":"98339",
    "sg:province":"WA",
    "sg:tags":[
        "publisher",
        "guide"
    ],
    "sg:website":"www.youra.com",
    "wof:name":"Dan Youra Studios",
    "wof:placetype":"venue"
},
  "geometry": {"coordinates":[-122.755182,48.033385],"type":"Point"}
}