{
  "type": "Feature",
  "properties": {
    "addr:full":"116 SW 153rd St Burien WA 98166",
    "addr:housenumber":"116",
    "addr:postcode":"98166",
    "addr:street":"Sw 153Rd St",
    "iso:country":"US",
    "sg:address":"116 SW 153rd St",
    "sg:city":"Burien",
    "sg:classifiers":[
        {
            "category":"Travel",
            "subcategory":"Travel Agent",
            "type":"Entertainment"
        }
    ],
    "sg:phone":"+1 206 439 6809",
    "sg:postcode":"98166",
    "sg:province":"WA",
    "sg:tags":[
        "consultant",
        "transportation"
    ],
    "wof:name":"Mexico Express",
    "wof:placetype":"venue"
},
  "geometry": {"coordinates":[-122.33465099999999,47.465989],"type":"Point"}
}