{
  "type": "Feature",
  "properties": {
    "addr:full":"1402 E Main Ave Puyallup WA 98372",
    "addr:housenumber":"1402",
    "addr:postcode":"98372",
    "addr:street":"E Main Ave",
    "iso:country":"US",
    "sg:address":"1402 E Main Ave",
    "sg:city":"Puyallup",
    "sg:classifiers":[
        {
            "category":"Restaurant",
            "type":"Food & Drink"
        }
    ],
    "sg:phone":"+1 253 848 4571",
    "sg:postcode":"98372",
    "sg:province":"WA",
    "sg:tags":[
        "eating"
    ],
    "wof:name":"Harvester",
    "wof:placetype":"venue"
},
  "geometry": {"coordinates":[-122.273743,47.191913],"type":"Point"}
}