{
  "type": "Feature",
  "properties": {
    "iso:country":"US",
    "sg:address":"248 Columbia St SW",
    "sg:city":"Ocean Shores",
    "sg:classifiers":[
        {
            "category":"Home & Garden",
            "subcategory":"Furniture",
            "type":"Retail Goods"
        }
    ],
    "sg:phone":"+1 360 289 4903",
    "sg:postcode":"98569",
    "sg:province":"WA",
    "sg:tags":[
        "cabinet"
    ],
    "wof:name":"Coastal Cabinet Door",
    "wof:placetype":"venue"
},
  "geometry": {"coordinates":[-124.140075,46.952189],"type":"Point"}
}