{
  "type": "Feature",
  "properties": {
    "addr:full":"21010 66th Ave W Lynnwood WA 98036",
    "addr:housenumber":"21010",
    "addr:postcode":"98036",
    "addr:street":"66Th Ave W",
    "iso:country":"US",
    "sg:address":"21010 66th Ave W",
    "sg:city":"Lynnwood",
    "sg:classifiers":[
        {
            "category":"Retail",
            "subcategory":"Auto Repair",
            "type":"Services"
        }
    ],
    "sg:phone":"+1 425 329 6484",
    "sg:postcode":"98036",
    "sg:province":"WA",
    "sg:website":"http://www.bretsindependent.com",
    "wof:name":"Bret's Independent, LLC",
    "wof:placetype":"venue"
},
  "geometry": {"coordinates":[-122.32195,47.808488],"type":"Point"}
}