{
  "type": "Feature",
  "properties": {
    "addr:full":"809 Legion Way SE Olympia WA 98501",
    "addr:housenumber":"809",
    "addr:postcode":"98501",
    "addr:street":"Legion Way Se",
    "iso:country":"US",
    "sg:address":"809 Legion Way SE",
    "sg:city":"Olympia",
    "sg:classifiers":[
        {
            "category":"Professional",
            "type":"Services"
        }
    ],
    "sg:phone":"+1 360 705 7605",
    "sg:postcode":"98501",
    "sg:province":"WA",
    "wof:name":"Wsdot",
    "wof:placetype":"venue"
},
  "geometry": {"coordinates":[-122.891181,47.043818],"type":"Point"}
}