{
  "type": "Feature",
  "properties": {
    "addr:full":"2520 Beacon Ave S Seattle WA 98144",
    "addr:housenumber":"2520",
    "addr:postcode":"98144",
    "addr:street":"Beacon Ave S",
    "iso:country":"US",
    "sg:address":"2520 Beacon Ave S",
    "sg:city":"Seattle",
    "sg:classifiers":[
        {
            "category":"Shopping",
            "subcategory":"Clothing, Apparel, & Fashions",
            "type":"Retail Goods"
        },
        {
            "category":"Personal",
            "type":"Services"
        }
    ],
    "sg:phone":"+1 206 328 2013",
    "sg:postcode":"98144",
    "sg:province":"WA",
    "sg:tags":[
        "tailoring",
        "tailor",
        "alteration",
        "wedding"
    ],
    "wof:name":"Tran's Tailoring",
    "wof:placetype":"venue"
},
  "geometry": {"coordinates":[-122.313197,47.58037],"type":"Point"}
}