{
  "type": "Feature",
  "properties": {
    "addr:full":"1211 Harrison Ave Centralia WA 98531",
    "addr:housenumber":"1211",
    "addr:postcode":"98531",
    "addr:street":"Harrison Ave",
    "iso:country":"US",
    "sg:address":"1211 Harrison Ave",
    "sg:city":"Centralia",
    "sg:classifiers":[
        {
            "category":"Autos & Motor Vehicles",
            "subcategory":"Auto Supplies",
            "type":"Retail Goods"
        }
    ],
    "sg:phone":"+1 360 736 6603",
    "sg:postcode":"98531",
    "sg:province":"WA",
    "sg:tags":[
        "tire"
    ],
    "wof:name":"Les Schwab Tire Center",
    "wof:placetype":"venue"
},
  "geometry": {"coordinates":[-122.985113,46.730841],"type":"Point"}
}