{
  "type": "Feature",
  "properties": {
    "iso:country":"US",
    "sg:address":"2660 S Cornett Dr",
    "sg:city":"Ridgefield",
    "sg:classifiers":[
        {
            "category":"Insurance",
            "subcategory":"Health Insurance",
            "type":"Services"
        }
    ],
    "sg:phone":"+1 360 887 0824",
    "sg:postcode":"98642",
    "sg:province":"WA",
    "sg:tags":[
        "plan"
    ],
    "wof:name":"Susan K Stenehjem",
    "wof:placetype":"venue"
},
  "geometry": {"coordinates":[-122.720448,45.798729],"type":"Point"}
}