{
  "type": "Feature",
  "properties": {
    "addr:full":"1000 17th Ave Longview WA 98632",
    "addr:housenumber":"1000",
    "addr:postcode":"98632",
    "addr:street":"17Th Ave",
    "iso:country":"US",
    "sg:address":"1000 17th Ave",
    "sg:city":"Longview",
    "sg:classifiers":[
        {
            "category":"Health Services",
            "subcategory":"Nursing And Care Facility",
            "type":"Services"
        }
    ],
    "sg:phone":"+1 360 423 3441",
    "sg:postcode":"98632",
    "sg:province":"WA",
    "sg:tags":[
        "home",
        "retirement",
        "community"
    ],
    "wof:name":"Fir At 17th Senior Apartments",
    "wof:placetype":"venue"
},
  "geometry": {"coordinates":[-122.940979,46.134709],"type":"Point"}
}