{
  "type": "Feature",
  "properties": {
    "addr:full":"42110 NW 34th Ave Woodland WA 98674",
    "addr:housenumber":"42110",
    "addr:postcode":"98674",
    "addr:street":"Nw 34Th Ave",
    "iso:country":"US",
    "sg:address":"42110 NW 34th Ave",
    "sg:city":"Woodland",
    "sg:classifiers":[
        {
            "category":"Building & Trades",
            "subcategory":"Construction",
            "type":"Services"
        }
    ],
    "sg:phone":"+1 360 225 8086",
    "sg:postcode":"98674",
    "sg:province":"WA",
    "sg:tags":[
        "foundation",
        "contractor"
    ],
    "wof:name":"Marshall R Adams Inc",
    "wof:placetype":"venue"
},
  "geometry": {"coordinates":[-122.70616,45.926639],"type":"Point"}
}