{
  "type": "Feature",
  "properties": {
    "addr:full":"256421 Hwy 101 Port Angeles WA 98362",
    "addr:housenumber":"256421",
    "addr:postcode":"98362",
    "addr:street":"Hwy 101",
    "iso:country":"US",
    "sg:address":"256421 Hwy 101",
    "sg:city":"Port Angeles",
    "sg:classifiers":[
        {
            "category":"Food & Beverages",
            "subcategory":"Groceries & Convenience Stores",
            "type":"Retail Goods"
        }
    ],
    "sg:phone":"+1 360 457 6044",
    "sg:postcode":"98362",
    "sg:province":"WA",
    "sg:tags":[
        "station",
        "gasoline"
    ],
    "wof:name":"R Corner Grocery",
    "wof:placetype":"venue"
},
  "geometry": {"coordinates":[-123.27486399999999,48.093716],"type":"Point"}
}