{
  "type": "Feature",
  "properties": {
    "addr:full":"25814 Sandridge Rd Nahcotta WA 98640",
    "addr:postcode":"25814;98640",
    "addr:street":"Sandridge Rd",
    "iso:country":"US",
    "sg:address":"25814 Sandridge Rd",
    "sg:city":"Nahcotta",
    "sg:classifiers":[
        {
            "category":"Travel",
            "subcategory":"Hotels & Motels",
            "type":"Entertainment"
        }
    ],
    "sg:phone":"+1 360 665 4690",
    "sg:postcode":"98640",
    "sg:province":"WA",
    "sg:tags":[
        "breakfast",
        "accommodation",
        "bed"
    ],
    "wof:name":"Moby Dick Hotel",
    "wof:placetype":"venue"
},
  "geometry": {"coordinates":[-124.03391000000001,46.488614],"type":"Point"}
}