{
  "type": "Feature",
  "properties": {
    "addr:full":"1832 21st Ave SE Olympia WA 98501",
    "addr:housenumber":"1832",
    "addr:postcode":"98501",
    "addr:street":"21St Ave Se",
    "iso:country":"US",
    "sg:address":"1832 21st Ave SE",
    "sg:city":"Olympia",
    "sg:classifiers":[
        {
            "category":"Home & Garden",
            "subcategory":"Building Materials",
            "type":"Retail Goods"
        }
    ],
    "sg:phone":"+1 360 357 7415",
    "sg:postcode":"98501",
    "sg:province":"WA",
    "sg:tags":[
        "hardwood"
    ],
    "wof:name":"Evergreen Cstm Hardwood Floors",
    "wof:placetype":"venue"
},
  "geometry": {"coordinates":[-122.87690600000001,47.030234],"type":"Point"}
}