{
  "type": "Feature",
  "properties": {
    "addr:full":"3621 S 378th St Auburn WA 98001",
    "addr:housenumber":"3621",
    "addr:postcode":"98001",
    "addr:street":"S 378Th St",
    "iso:country":"US",
    "sg:address":"3621 S 378th St",
    "sg:city":"Auburn",
    "sg:classifiers":[
        {
            "category":"Shopping",
            "subcategory":"Pets & Pet Supplies",
            "type":"Retail Goods"
        }
    ],
    "sg:phone":"+1 253 838 8229",
    "sg:postcode":"98001",
    "sg:province":"WA",
    "sg:tags":[
        "furnishing",
        "dog",
        "store",
        "cat"
    ],
    "wof:name":"Pet Paparazzi",
    "wof:placetype":"venue"
},
  "geometry": {"coordinates":[-122.288657,47.264062],"type":"Point"}
}