{
  "type": "Feature",
  "properties": {
    "addr:full":"720 3rd St S Kirkland WA 98033",
    "addr:housenumber":"720",
    "addr:postcode":"98033",
    "addr:street":"3Rd St S",
    "iso:country":"US",
    "sg:address":"720 3rd St S",
    "sg:city":"Kirkland",
    "sg:classifiers":[
        {
            "category":"Professional",
            "subcategory":"Management & Consulting",
            "type":"Services"
        }
    ],
    "sg:phone":"+1 425 828 6948",
    "sg:postcode":"98033",
    "sg:province":"WA",
    "sg:tags":[
        "business"
    ],
    "wof:name":"Cascade Lnear Intgrted Crcuits",
    "wof:placetype":"venue"
},
  "geometry": {"coordinates":[-122.203275,47.669159],"type":"Point"}
}