{
  "type": "Feature",
  "properties": {
    "addr:full":"5678 Orchard Dr Ferndale WA 98248",
    "addr:housenumber":"5678",
    "addr:postcode":"98248",
    "addr:street":"Orchard Dr",
    "iso:country":"US",
    "sg:address":"5678 Orchard Dr",
    "sg:city":"Ferndale",
    "sg:classifiers":[
        {
            "category":"Home & Garden",
            "subcategory":"Home Furnishings",
            "type":"Retail Goods"
        }
    ],
    "sg:phone":"+1 360 685 0020",
    "sg:postcode":"98248",
    "sg:province":"WA",
    "wof:name":"Orchard Body Creations",
    "wof:placetype":"venue"
},
  "geometry": {"coordinates":[-122.55196599999999,48.846081],"type":"Point"}
}