{
  "type": "Feature",
  "properties": {
    "addr:full":"16121 Tiger Mountain Rd SE Issaquah WA 98027",
    "addr:housenumber":"16121",
    "addr:postcode":"98027",
    "addr:street":"Tiger Mountain Rd Se",
    "iso:country":"US",
    "sg:address":"16121 Tiger Mountain Rd SE",
    "sg:city":"Issaquah",
    "sg:classifiers":[
        {
            "category":"Professional",
            "subcategory":"Computer Services",
            "type":"Services"
        }
    ],
    "sg:phone":"+1 206 954 9542",
    "sg:postcode":"98027",
    "sg:province":"WA",
    "sg:tags":[
        "programing",
        "custom"
    ],
    "wof:name":"Datacatch Corp",
    "wof:placetype":"venue"
},
  "geometry": {"coordinates":[-121.97881,47.456872],"type":"Point"}
}