{
  "type": "Feature",
  "properties": {
    "addr:full":"6204 State Hwy 3 Bremerton WA 98312",
    "addr:housenumber":"6204",
    "addr:postcode":"98312",
    "addr:street":"State Hwy 3",
    "iso:country":"US",
    "sg:address":"6204 State Hwy 3",
    "sg:city":"Bremerton",
    "sg:classifiers":[
        {
            "category":"Wholesale",
            "subcategory":"Metals & Minerals",
            "type":"Manufacturing & Wholesale Goods"
        }
    ],
    "sg:phone":"+1 360 373 2529",
    "sg:postcode":"98312",
    "sg:province":"WA",
    "sg:tags":[
        "steel",
        "warehouse"
    ],
    "wof:name":"Pacific Welding Supplies Inc",
    "wof:placetype":"venue"
},
  "geometry": {"coordinates":[-122.70986600000001,47.632355],"type":"Point"}
}