{
  "type": "Feature",
  "properties": {
    "addr:full":"9926 79th Dr NE Marysville WA 98270",
    "addr:housenumber":"9926",
    "addr:postcode":"98270",
    "addr:street":"79Th Dr Ne",
    "iso:country":"US",
    "sg:address":"9926 79th Dr NE",
    "sg:city":"Marysville",
    "sg:classifiers":[
        {
            "category":"Building & Trades",
            "subcategory":"Construction",
            "type":"Services"
        }
    ],
    "sg:phone":"+1 360 659 3169",
    "sg:postcode":"98270",
    "sg:province":"WA",
    "sg:tags":[
        "house"
    ],
    "wof:name":"Vlc Construction Inc",
    "wof:placetype":"venue"
},
  "geometry": {"coordinates":[-122.12304,48.083473],"type":"Point"}
}