{
  "type": "Feature",
  "properties": {
    "addr:full":"301 E McLoughlin Blvd Vancouver WA 98663",
    "addr:housenumber":"301",
    "addr:postcode":"98663",
    "addr:street":"E Mcloughlin Blvd",
    "iso:country":"US",
    "sg:address":"301 E McLoughlin Blvd",
    "sg:city":"Vancouver",
    "sg:classifiers":[
        {
            "category":"Education",
            "subcategory":"School",
            "type":"Public Place"
        }
    ],
    "sg:phone":"+1 360 256 9681",
    "sg:postcode":"98663",
    "sg:province":"WA",
    "wof:name":"Washington School Of Insurance",
    "wof:placetype":"venue"
},
  "geometry": {"coordinates":[-122.668228,45.634872],"type":"Point"}
}