{
  "type": "Feature",
  "properties": {
    "addr:full":"1106 Harding St Richland WA 99352",
    "addr:housenumber":"1106",
    "addr:postcode":"99352",
    "addr:street":"Harding St",
    "iso:country":"US",
    "sg:address":"1106 Harding St",
    "sg:city":"Richland",
    "sg:classifiers":[
        {
            "category":"Manufacturing",
            "subcategory":"Apparel",
            "type":"Manufacturing & Wholesale Goods"
        }
    ],
    "sg:phone":"+1 509 946 6125",
    "sg:postcode":"99352",
    "sg:province":"WA",
    "sg:tags":[
        "sewing",
        "contractor"
    ],
    "sg:website":"www.uslinen.com",
    "wof:name":"Us Linen & Uniform",
    "wof:placetype":"venue"
},
  "geometry": {"coordinates":[-119.279291,46.273897],"type":"Point"}
}