{
  "type": "Feature",
  "properties": {
    "addr:full":"23401 104th Ave SE Kent WA 98031",
    "addr:housenumber":"23401",
    "addr:postcode":"98031",
    "addr:street":"104Th Ave Se",
    "iso:country":"US",
    "sg:address":"23401 104th Ave SE",
    "sg:city":"Kent",
    "sg:classifiers":[
        {
            "category":"Professional",
            "type":"Services"
        }
    ],
    "sg:phone":"+1 253 850 9517",
    "sg:postcode":"98031",
    "sg:province":"WA",
    "wof:name":"New Chance",
    "wof:placetype":"venue"
},
  "geometry": {"coordinates":[-122.202321,47.392019],"type":"Point"}
}