{
  "type": "Feature",
  "properties": {
    "addr:full":"2751 46th Ave SW Seattle WA 98116",
    "addr:housenumber":"2751",
    "addr:postcode":"98116",
    "addr:street":"46Th Ave Sw",
    "iso:country":"US",
    "sg:address":"2751 46th Ave SW",
    "sg:city":"Seattle",
    "sg:classifiers":[
        {
            "category":"Professional",
            "subcategory":"Lawyer & Legal Services",
            "type":"Services"
        }
    ],
    "sg:phone":"+1 206 935 4479",
    "sg:postcode":"98116",
    "sg:province":"WA",
    "sg:tags":[
        "attorney"
    ],
    "wof:name":"Geoffrey D Patterson Law Ofc",
    "wof:placetype":"venue"
},
  "geometry": {"coordinates":[-122.39082000000001,47.577811],"type":"Point"}
}