{
  "type": "Feature",
  "properties": {
    "addr:full":"741 15th Way SW Edmonds WA 98020",
    "addr:housenumber":"741",
    "addr:postcode":"98020",
    "addr:street":"15Th Way Sw",
    "iso:country":"US",
    "sg:address":"741 15th Way SW",
    "sg:city":"Edmonds",
    "sg:classifiers":[
        {
            "category":"Wholesale",
            "subcategory":"Machinery & Supplies",
            "type":"Manufacturing & Wholesale Goods"
        },
        {
            "category":"Wholesale",
            "subcategory":"Durable Goods & Equipment",
            "type":"Manufacturing & Wholesale Goods"
        }
    ],
    "sg:phone":"+1 425 712 9703",
    "sg:postcode":"98020",
    "sg:province":"WA",
    "sg:tags":[
        "composite",
        "product",
        "exporter"
    ],
    "wof:name":"Techtrade International",
    "wof:placetype":"venue"
},
  "geometry": {"coordinates":[-122.370271,47.793228],"type":"Point"}
}