{
  "type": "Feature",
  "properties": {
    "addr:full":"2409 Cleveland Ave Everett WA 98201",
    "addr:housenumber":"2409",
    "addr:postcode":"98201",
    "addr:street":"Cleveland Ave",
    "iso:country":"US",
    "sg:address":"2409 Cleveland Ave",
    "sg:city":"Everett",
    "sg:classifiers":[
        {
            "category":"Freight",
            "type":"Transportation"
        }
    ],
    "sg:phone":"+1 425 259 4308",
    "sg:postcode":"98201",
    "sg:province":"WA",
    "sg:tags":[
        "operator",
        "local",
        "trucking"
    ],
    "wof:name":"B M Lawn & Hauling",
    "wof:placetype":"venue"
},
  "geometry": {"coordinates":[-122.18063600000001,47.984372],"type":"Point"}
}