{
  "type": "Feature",
  "properties": {
    "addr:full":"1314 NW 359th St La Center WA 98629",
    "addr:housenumber":"1314",
    "addr:postcode":"98629",
    "addr:street":"Nw 359Th St",
    "iso:country":"US",
    "sg:address":"1314 NW 359th St",
    "sg:city":"La Center",
    "sg:classifiers":[
        {
            "category":"Shopping",
            "subcategory":"Florist",
            "type":"Retail Goods"
        }
    ],
    "sg:phone":"+1 360 263 2507",
    "sg:postcode":"98629",
    "sg:province":"WA",
    "wof:name":"Annes Flowers",
    "wof:placetype":"venue"
},
  "geometry": {"coordinates":[-122.68415299999999,45.880758],"type":"Point"}
}