{
  "type": "Feature",
  "properties": {
    "addr:full":"14050 184th Ave NE Woodinville WA 98072",
    "addr:housenumber":"14050",
    "addr:postcode":"98072",
    "addr:street":"184Th Ave Ne",
    "iso:country":"US",
    "sg:address":"14050 184th Ave NE",
    "sg:city":"Woodinville",
    "sg:classifiers":[
        {
            "category":"Retail",
            "subcategory":"Animal Services",
            "type":"Services"
        }
    ],
    "sg:phone":"+1 425 885 4267",
    "sg:postcode":"98072",
    "sg:province":"WA",
    "wof:name":"View Ridge Farms Inc",
    "wof:placetype":"venue"
},
  "geometry": {"coordinates":[-122.093791,47.727219],"type":"Point"}
}