{
  "type": "Feature",
  "properties": {
    "addr:full":"198 Lost Valley Rd Curtis WA 98538",
    "addr:housenumber":"198",
    "addr:postcode":"98538",
    "addr:street":"Lost Valley Rd",
    "iso:country":"US",
    "sg:address":"198 Lost Valley Rd",
    "sg:city":"Curtis",
    "sg:classifiers":[
        {
            "category":"Farming",
            "subcategory":"Livestock Farm",
            "type":"Manufacturing & Wholesale Goods"
        }
    ],
    "sg:phone":"+1 360 245 3315",
    "sg:postcode":"98538",
    "sg:province":"WA",
    "sg:tags":[
        "feedlot",
        "field",
        "crop",
        "beef",
        "cattle"
    ],
    "wof:name":"E Born",
    "wof:placetype":"venue"
},
  "geometry": {"coordinates":[-123.144465,46.546338],"type":"Point"}
}