{
  "type": "Feature",
  "properties": {
    "addr:full":"60 Woodland Rd Goldendale WA 98620",
    "addr:housenumber":"60",
    "addr:postcode":"98620",
    "addr:street":"Woodland Rd",
    "iso:country":"US",
    "sg:address":"60 Woodland Rd",
    "sg:city":"Goldendale",
    "sg:classifiers":[
        {
            "category":"Manufacturing",
            "subcategory":"Lumber",
            "type":"Manufacturing & Wholesale Goods"
        }
    ],
    "sg:phone":"+1 509 773 5788",
    "sg:postcode":"98620",
    "sg:province":"WA",
    "sg:tags":[
        "logging"
    ],
    "wof:name":"Lsc Logging Inc",
    "wof:placetype":"venue"
},
  "geometry": {"coordinates":[-120.75960000000001,45.861618],"type":"Point"}
}