{
  "type": "Feature",
  "properties": {
    "addr:full":"1260 Dayton Rd Pasco WA 99301",
    "addr:housenumber":"1260",
    "addr:postcode":"99301",
    "addr:street":"Dayton Rd",
    "iso:country":"US",
    "sg:address":"1260 Dayton Rd",
    "sg:city":"Pasco",
    "sg:phone":"+1 509 547 2747",
    "sg:postcode":"99301",
    "sg:province":"WA",
    "sg:tags":[
        "farm",
        "field",
        "corn",
        "wheat",
        "crop"
    ],
    "wof:name":"Ernest E Pett",
    "wof:placetype":"venue"
},
  "geometry": {"coordinates":[-119.156223,46.37668],"type":"Point"}
}