{
  "type": "Feature",
  "properties": {
    "addr:full":"401 S Ruby St Ellensburg WA 98926",
    "addr:housenumber":"401",
    "addr:postcode":"98926",
    "addr:street":"S Ruby St",
    "iso:country":"US",
    "sg:address":"401 S Ruby St",
    "sg:city":"Ellensburg",
    "sg:classifiers":[
        {
            "category":"Organizations",
            "subcategory":"Religious Organization",
            "type":"Services"
        }
    ],
    "sg:phone":"+1 509 933 2199",
    "sg:postcode":"98926",
    "sg:province":"WA",
    "sg:tags":[
        "church"
    ],
    "wof:name":"Faith Baptist Church",
    "wof:placetype":"venue"
},
  "geometry": {"coordinates":[-120.544206,46.989316],"type":"Point"}
}