{
  "type": "Feature",
  "properties": {
    "addr:full":"1622 S Howard St Walla Walla WA 99362",
    "addr:housenumber":"1622",
    "addr:postcode":"99362",
    "addr:street":"S Howard St",
    "iso:country":"US",
    "sg:address":"1622 S Howard St",
    "sg:city":"Walla Walla",
    "sg:classifiers":[
        {
            "category":"Organizations",
            "subcategory":"Religious Organization",
            "type":"Services"
        }
    ],
    "sg:phone":"+1 509 529 2012",
    "sg:postcode":"99362",
    "sg:province":"WA",
    "sg:tags":[
        "church"
    ],
    "wof:name":"First Church-Christ-Scientist",
    "wof:placetype":"venue"
},
  "geometry": {"coordinates":[-118.325264,46.053979],"type":"Point"}
}