{
  "type": "Feature",
  "properties": {
    "addr:full":"5024 Lacey Blvd SE Lacey WA 98503",
    "addr:housenumber":"5024",
    "addr:postcode":"98503",
    "addr:street":"Lacey Blvd Se",
    "iso:country":"US",
    "sg:address":"5024 Lacey Blvd SE",
    "sg:city":"Lacey",
    "sg:classifiers":[
        {
            "category":"Health Services",
            "subcategory":"Doctor",
            "type":"Services"
        }
    ],
    "sg:phone":"+1 360 459 4420",
    "sg:postcode":"98503",
    "sg:province":"WA",
    "sg:tags":[
        "dentist"
    ],
    "wof:name":"Philip B Cramer DDS",
    "wof:placetype":"venue"
},
  "geometry": {"coordinates":[-122.817001,47.034825],"type":"Point"}
}