{
  "type": "Feature",
  "properties": {
    "addr:full":"22757 72nd Ave S Kent WA 98032",
    "addr:housenumber":"22757",
    "addr:postcode":"98032",
    "addr:street":"72Nd Ave S",
    "iso:country":"US",
    "sg:address":"22757 72nd Ave S",
    "sg:city":"Kent",
    "sg:classifiers":[
        {
            "category":"Wholesale",
            "subcategory":"Machinery & Supplies",
            "type":"Manufacturing & Wholesale Goods"
        }
    ],
    "sg:phone":"+1 253 395 9297",
    "sg:postcode":"98032",
    "sg:province":"WA",
    "sg:tags":[
        "industrial"
    ],
    "wof:name":"Fastenal Company",
    "wof:placetype":"venue"
},
  "geometry": {"coordinates":[-122.24573599999999,47.398329],"type":"Point"}
}