{
  "type": "Feature",
  "properties": {
    "addr:full":"5528 E Cataldo Ave Spokane Valley WA 99212",
    "addr:housenumber":"5528",
    "addr:postcode":"99212",
    "addr:street":"E Cataldo Ave",
    "iso:country":"US",
    "sg:address":"5528 E Cataldo Ave",
    "sg:city":"Spokane Valley",
    "sg:classifiers":[
        {
            "category":"Manufacturing",
            "subcategory":"Metals",
            "type":"Manufacturing & Wholesale Goods"
        }
    ],
    "sg:phone":"+1 509 532 1997",
    "sg:postcode":"99212",
    "sg:province":"WA",
    "sg:tags":[
        "coating"
    ],
    "wof:name":"Quarra Coatings",
    "wof:placetype":"venue"
},
  "geometry": {"coordinates":[-117.328332,47.666065],"type":"Point"}
}