{
  "type": "Feature",
  "properties": {
    "addr:full":"4250 Shoreclub Dr Mercer Island WA 98040",
    "addr:housenumber":"4250",
    "addr:postcode":"98040",
    "addr:street":"Shoreclub Dr",
    "iso:country":"US",
    "sg:address":"4250 Shoreclub Dr",
    "sg:city":"Mercer Island",
    "sg:classifiers":[
        {
            "category":"Arts & Performance",
            "subcategory":"Theater",
            "type":"Entertainment"
        }
    ],
    "sg:phone":"+1 206 232 7352",
    "sg:postcode":"98040",
    "sg:province":"WA",
    "sg:tags":[
        "group"
    ],
    "wof:name":"Performance An Larkpoint Music",
    "wof:placetype":"venue"
},
  "geometry": {"coordinates":[-122.21070400000001,47.57087],"type":"Point"}
}