{
  "type": "Feature",
  "properties": {
    "addr:full":"516 W Margaret St Pasco WA 99301",
    "addr:housenumber":"516",
    "addr:postcode":"99301",
    "addr:street":"W Margaret St",
    "iso:country":"US",
    "sg:address":"516 W Margaret St",
    "sg:city":"Pasco",
    "sg:classifiers":[
        {
            "category":"Health Services",
            "subcategory":"Doctor",
            "type":"Services"
        }
    ],
    "sg:phone":"+1 509 547 9611",
    "sg:postcode":"99301",
    "sg:province":"WA",
    "sg:tags":[
        "physician",
        "surgeon"
    ],
    "wof:name":"Cleve Henriques MD",
    "wof:placetype":"venue"
},
  "geometry": {"coordinates":[-119.09679800000001,46.236527],"type":"Point"}
}