{
  "type": "Feature",
  "properties": {
    "addr:full":"7234 NE Bothell Way Kenmore WA 98028",
    "addr:housenumber":"7234",
    "addr:postcode":"98028",
    "addr:street":"Ne Bothell Way",
    "iso:country":"US",
    "sg:address":"7234 NE Bothell Way",
    "sg:city":"Kenmore",
    "sg:classifiers":[
        {
            "category":"Restaurant",
            "type":"Food & Drink"
        }
    ],
    "sg:menulink":"http://www.allmenus.com/wa/east-seattle/213036-mcdonalds/menu/",
    "sg:phone":"+1 425 485 5535",
    "sg:postcode":"98028",
    "sg:province":"WA",
    "sg:tags":[
        "burger",
        "american"
    ],
    "wof:name":"McDonald's",
    "wof:placetype":"venue"
},
  "geometry": {"coordinates":[-122.244472,47.757543],"type":"Point"}
}