{
  "type": "Feature",
  "properties": {
    "addr:full":"12506 130th Ln NE Kirkland WA 98034",
    "addr:housenumber":"12506",
    "addr:postcode":"98034",
    "addr:street":"130Th Ln Ne",
    "iso:country":"US",
    "sg:address":"12506 130th Ln NE",
    "sg:city":"Kirkland",
    "sg:classifiers":[
        {
            "category":"Wholesale",
            "subcategory":"Electrical",
            "type":"Manufacturing & Wholesale Goods"
        }
    ],
    "sg:phone":"+1 425 821 5454",
    "sg:postcode":"98034",
    "sg:province":"WA",
    "sg:tags":[
        "electronic"
    ],
    "wof:name":"Master Distributors",
    "wof:placetype":"venue"
},
  "geometry": {"coordinates":[-122.167328,47.713643],"type":"Point"}
}