{
  "type": "Feature",
  "properties": {
    "addr:full":"5302 E Greenbluff Rd Colbert WA 99005",
    "addr:housenumber":"5302",
    "addr:postcode":"99005",
    "addr:street":"E Greenbluff Rd Colbert",
    "iso:country":"US",
    "sg:address":"5302 E Greenbluff Rd",
    "sg:city":"Colbert",
    "sg:classifiers":[
        {
            "category":"Building & Trades",
            "subcategory":"Construction",
            "type":"Services"
        }
    ],
    "sg:phone":"+1 509 238 6049",
    "sg:postcode":"99005",
    "sg:province":"WA",
    "sg:tags":[
        "residential"
    ],
    "wof:name":"Kop Construction",
    "wof:placetype":"venue"
},
  "geometry": {"coordinates":[-117.33449299999999,47.809033],"type":"Point"}
}