{
  "type": "Feature",
  "properties": {
    "iso:country":"US",
    "sg:address":"165 Conconully St",
    "sg:city":"Okanogan",
    "sg:classifiers":[
        {
            "category":"Farming",
            "subcategory":"Livestock Farm",
            "type":"Manufacturing & Wholesale Goods"
        }
    ],
    "sg:phone":"+1 509 826 6822",
    "sg:postcode":"98840",
    "sg:province":"WA",
    "sg:tags":[
        "animal",
        "general"
    ],
    "wof:name":"Tl Ranch LLC",
    "wof:placetype":"venue"
},
  "geometry": {"coordinates":[-119.584793,48.359951],"type":"Point"}
}