{
  "type": "Feature",
  "properties": {
    "addr:full":"3253 E 1st Ave Spokane WA 99202",
    "addr:housenumber":"3253",
    "addr:postcode":"99202",
    "addr:street":"E 1St Ave",
    "iso:country":"US",
    "sg:address":"3253 E 1st Ave",
    "sg:city":"Spokane",
    "sg:classifiers":[
        {
            "category":"Retail",
            "subcategory":"Auto Repair",
            "type":"Services"
        }
    ],
    "sg:phone":"+1 509 535 8008",
    "sg:postcode":"99202",
    "sg:province":"WA",
    "sg:tags":[
        "repairing",
        "automobile"
    ],
    "wof:name":"Liberty Tire & Auto Svc Inc",
    "wof:placetype":"venue"
},
  "geometry": {"coordinates":[-117.36274400000001,47.656365],"type":"Point"}
}