{
  "type": "Feature",
  "properties": {
    "addr:full":"2778 Farm To Market Loop Rd Chewelah WA 99109",
    "addr:housenumber":"2778",
    "addr:postcode":"99109",
    "addr:street":"Farm To Market Loop Rd",
    "iso:country":"US",
    "sg:address":"2778 Farm To Market Loop Rd",
    "sg:city":"Chewelah",
    "sg:classifiers":[
        {
            "category":"Professional",
            "type":"Services"
        }
    ],
    "sg:phone":"+1 509 935 4664",
    "sg:postcode":"99109",
    "sg:province":"WA",
    "wof:name":"Hafer Homestead Inc",
    "wof:placetype":"venue"
},
  "geometry": {"coordinates":[-117.752205,48.219746],"type":"Point"}
}