{
  "type": "Feature",
  "properties": {
    "addr:full":"6809 Sonia St Tacoma WA 98404",
    "addr:housenumber":"6809",
    "addr:postcode":"98404",
    "addr:street":"Sonia St",
    "iso:country":"US",
    "sg:address":"6809 Sonia St",
    "sg:city":"Tacoma",
    "sg:classifiers":[
        {
            "category":"Professional",
            "subcategory":"Computer Services",
            "type":"Services"
        }
    ],
    "sg:phone":"+1 253 468 2044",
    "sg:postcode":"98404",
    "sg:province":"WA",
    "wof:name":"Computechlabscom",
    "wof:placetype":"venue"
},
  "geometry": {"coordinates":[-122.40397900000001,47.195862],"type":"Point"}
}