{
  "type": "Feature",
  "properties": {
    "addr:full":"119 1st Ave South Suite 100 Seattle WA 98104",
    "addr:housenumber":"119",
    "addr:postcode":"98104",
    "addr:street":"1St Ave South Suite 100",
    "iso:country":"US",
    "sg:address":"119 1st Ave South Suite 100",
    "sg:city":"Seattle",
    "sg:classifiers":[
        {
            "category":"Professional",
            "subcategory":"Computer Services",
            "type":"Services"
        }
    ],
    "sg:postcode":"98104",
    "sg:province":"WA",
    "sg:website":"http://www.opscode.com",
    "wof:name":"Opscode",
    "wof:placetype":"venue"
},
  "geometry": {"coordinates":[-122.33425800000001,47.601035],"type":"Point"}
}