{
  "type": "Feature",
  "properties": {
    "addr:full":"13116 39th Ave SE Everett WA 98208",
    "addr:housenumber":"13116",
    "addr:postcode":"98208",
    "addr:street":"39Th Ave Se",
    "iso:country":"US",
    "sg:address":"13116 39th Ave SE",
    "sg:city":"Everett",
    "sg:classifiers":[
        {
            "category":"Deli",
            "type":"Food & Drink"
        }
    ],
    "sg:menulink":"http://www.allmenus.com/wa/everett/126866-blimpie-subs--sandwiches/menu/",
    "sg:phone":"+1 425 385 8544",
    "sg:postcode":"98208",
    "sg:province":"WA",
    "sg:tags":[
        "wrap",
        "american",
        "sandwich"
    ],
    "wof:name":"Blimpie Subs & Sandwiches",
    "wof:placetype":"venue"
},
  "geometry": {"coordinates":[-122.180063,47.878466],"type":"Point"}
}