{
  "type": "Feature",
  "properties": {
    "addr:full":"709 Seahorse Ave NE Ocean Shores WA 98569",
    "addr:housenumber":"709",
    "addr:postcode":"98569",
    "addr:street":"Seahorse Ave Ne",
    "iso:country":"US",
    "sg:address":"709 Seahorse Ave NE",
    "sg:city":"Ocean Shores",
    "sg:classifiers":[
        {
            "category":"Building & Trades",
            "subcategory":"Construction",
            "type":"Services"
        }
    ],
    "sg:phone":"+1 360 289 0248",
    "sg:postcode":"98569",
    "sg:province":"WA",
    "sg:tags":[
        "excavation",
        "excavating",
        "contractor"
    ],
    "wof:name":"D & S Excavating",
    "wof:placetype":"venue"
},
  "geometry": {"coordinates":[-124.159903,47.011239],"type":"Point"}
}