{
  "type": "Feature",
  "properties": {
    "addr:full":"27090 US Hwy 12 Naches WA 98937",
    "addr:postcode":"27090;98937",
    "addr:street":"Us Hwy 12",
    "iso:country":"US",
    "sg:address":"27090 US Hwy 12",
    "sg:city":"Naches",
    "sg:classifiers":[
        {
            "category":"Travel",
            "subcategory":"Hotels & Motels",
            "type":"Entertainment"
        }
    ],
    "sg:phone":"+1 509 672 2211",
    "sg:postcode":"98937",
    "sg:province":"WA",
    "sg:tags":[
        "shop",
        "gift"
    ],
    "wof:name":"Trout Lodge",
    "wof:placetype":"venue"
},
  "geometry": {"coordinates":[-120.986463,46.670407],"type":"Point"}
}