{
  "type": "Feature",
  "properties": {
    "addr:full":"801 N 7th Pl Ridgefield WA 98642",
    "addr:housenumber":"801",
    "addr:postcode":"98642",
    "addr:street":"N 7Th Pl",
    "iso:country":"US",
    "sg:address":"801 N 7th Pl",
    "sg:city":"Ridgefield",
    "sg:classifiers":[
        {
            "category":"Food & Beverages",
            "subcategory":"Groceries & Convenience Stores",
            "type":"Retail Goods"
        }
    ],
    "sg:phone":"+1 360 887 8311",
    "sg:postcode":"98642",
    "sg:province":"WA",
    "sg:tags":[
        "product"
    ],
    "wof:name":"ACH Food Co Inc",
    "wof:placetype":"venue"
},
  "geometry": {"coordinates":[-122.740561,45.822164],"type":"Point"}
}