{
  "type": "Feature",
  "properties": {
    "addr:full":"6435 E Hilldale Rd Port Orchard WA 98366",
    "addr:housenumber":"6435",
    "addr:postcode":"98366",
    "addr:street":"E Hilldale Rd",
    "iso:country":"US",
    "sg:address":"6435 E Hilldale Rd",
    "sg:city":"Port Orchard",
    "sg:classifiers":[
        {
            "category":"Building & Trades",
            "subcategory":"Electrical",
            "type":"Services"
        }
    ],
    "sg:phone":"+1 360 871 2181",
    "sg:postcode":"98366",
    "sg:province":"WA",
    "sg:tags":[
        "electrical",
        "contractor"
    ],
    "wof:name":"Mho Right Electric",
    "wof:placetype":"venue"
},
  "geometry": {"coordinates":[-122.56276099999999,47.577286],"type":"Point"}
}