{
  "type": "Feature",
  "properties": {
    "addr:full":"1st Ave NE Medical Bldg Seattle WA 98115",
    "addr:postcode":"98115",
    "addr:street":"1St Ave Ne",
    "iso:country":"US",
    "sg:address":"1st Ave NE Medical Bldg",
    "sg:city":"Seattle",
    "sg:classifiers":[
        {
            "category":"Social Services",
            "type":"Services"
        }
    ],
    "sg:phone":"+1 206 622 6962",
    "sg:postcode":"98115",
    "sg:province":"WA",
    "sg:tags":[
        "worker"
    ],
    "wof:name":"Mary Jane Golden Msw",
    "wof:placetype":"venue"
},
  "geometry": {"coordinates":[-122.328205,47.672581],"type":"Point"}
}