{
  "type": "Feature",
  "properties": {
    "addr:full":"824 W Casino Rd Ofc Everett WA 98204",
    "addr:housenumber":"824",
    "addr:postcode":"98204",
    "addr:street":"W Casino Rd",
    "iso:country":"US",
    "sg:address":"824 W Casino Rd Ofc",
    "sg:city":"Everett",
    "sg:classifiers":[
        {
            "category":"Real Estate",
            "subcategory":"Real Estate Services",
            "type":"Services"
        },
        {
            "category":"Real Estate",
            "subcategory":"Real Estate Operator",
            "type":"Services"
        }
    ],
    "sg:phone":"+1 425 347 1136",
    "sg:postcode":"98204",
    "sg:province":"WA",
    "sg:tags":[
        "vacancy",
        "apartment",
        "rental",
        "finder",
        "listing"
    ],
    "wof:name":"Casino Lane Apts",
    "wof:placetype":"venue"
},
  "geometry": {"coordinates":[-122.24497700000001,47.921817],"type":"Point"}
}