{
  "type": "Feature",
  "properties": {
    "addr:full":"1228 S Grand Blvd Spokane WA 99202",
    "addr:housenumber":"1228",
    "addr:postcode":"99202",
    "addr:street":"S Grand Blvd",
    "iso:country":"US",
    "sg:address":"1228 S Grand Blvd",
    "sg:city":"Spokane",
    "sg:classifiers":[
        {
            "category":"Restaurant",
            "type":"Food & Drink"
        }
    ],
    "sg:phone":"+1 509 455 7545",
    "sg:postcode":"99202",
    "sg:province":"WA",
    "wof:name":"Paprika",
    "wof:placetype":"venue"
},
  "geometry": {"coordinates":[-117.410461,47.644479],"type":"Point"}
}