{
  "type": "Feature",
  "properties": {
    "addr:full":"21111 75th St E Sumner WA 98391",
    "addr:housenumber":"21111",
    "addr:postcode":"98391",
    "addr:street":"75Th St E",
    "iso:country":"US",
    "sg:address":"21111 75th St E",
    "sg:city":"Sumner",
    "sg:classifiers":[
        {
            "category":"Shopping",
            "type":"Retail Goods"
        }
    ],
    "sg:phone":"+1 253 468 7527",
    "sg:postcode":"98391",
    "sg:province":"WA",
    "sg:tags":[
        "merchandise"
    ],
    "wof:name":"Bonneylake Frame",
    "wof:placetype":"venue"
},
  "geometry": {"coordinates":[-122.14573799999999,47.189105],"type":"Point"}
}