{
  "type": "Feature",
  "properties": {
    "addr:full":"15012 E Meridian Ave Puyallup WA 98375",
    "addr:housenumber":"15012",
    "addr:postcode":"98375",
    "addr:street":"E Meridian Ave",
    "iso:country":"US",
    "sg:address":"15012 E Meridian Ave",
    "sg:city":"Puyallup",
    "sg:classifiers":[
        {
            "category":"Banks & Credit Unions",
            "subcategory":"Bank",
            "type":"Services"
        }
    ],
    "sg:phone":"+1 253 770 2634",
    "sg:postcode":"98375",
    "sg:province":"WA",
    "sg:tags":[
        "loan",
        "real estate"
    ],
    "wof:name":"Creative Options Financial Inc",
    "wof:placetype":"venue"
},
  "geometry": {"coordinates":[-122.293255,47.120854],"type":"Point"}
}