{
  "type": "Feature",
  "properties": {
    "iso:country":"US",
    "sg:address":"1624 Tacoma Ave S",
    "sg:city":"Tacoma",
    "sg:classifiers":[
        {
            "category":"Food & Beverages",
            "subcategory":"Specialty",
            "type":"Retail Goods"
        }
    ],
    "sg:phone":"+1 253 396 1142",
    "sg:postcode":"98402",
    "sg:province":"WA",
    "sg:tags":[
        "health",
        "diet"
    ],
    "wof:name":"Low Carb Corner",
    "wof:placetype":"venue"
},
  "geometry": {"coordinates":[-122.443145,47.246829],"type":"Point"}
}