{
  "type": "Feature",
  "properties": {
    "addr:full":"13787 NE 65th St Redmond WA 98052",
    "addr:housenumber":"13787",
    "addr:postcode":"98052",
    "addr:street":"Ne 65Th St",
    "iso:country":"US",
    "sg:address":"13787 NE 65th St",
    "sg:city":"Redmond",
    "sg:classifiers":[
        {
            "category":"Professional",
            "subcategory":"Management & Consulting",
            "type":"Services"
        }
    ],
    "sg:phone":"+1 425 761 6311",
    "sg:postcode":"98052",
    "sg:province":"WA",
    "wof:name":"Debelle International",
    "wof:placetype":"venue"
},
  "geometry": {"coordinates":[-122.15765,47.665067],"type":"Point"}
}