{
  "type": "Feature",
  "properties": {
    "addr:full":"2240 S 111th Pl Seattle WA 98168",
    "addr:housenumber":"2240",
    "addr:postcode":"98168",
    "addr:street":"S 111Th Pl",
    "iso:country":"US",
    "sg:address":"2240 S 111th Pl",
    "sg:city":"Seattle",
    "sg:classifiers":[
        {
            "category":"Professional",
            "subcategory":"Accounting & Tax Preparation",
            "type":"Services"
        },
        {
            "category":"Professional",
            "subcategory":"Business Services",
            "type":"Services"
        }
    ],
    "sg:phone":"+1 206 244 1040",
    "sg:postcode":"98168",
    "sg:province":"WA",
    "sg:tags":[
        "consultant",
        "coach",
        "bookkeeping"
    ],
    "wof:name":"Wright's Business Service, Inc",
    "wof:placetype":"venue"
},
  "geometry": {"coordinates":[-122.30453799999999,47.503575],"type":"Point"}
}