{
  "type": "Feature",
  "properties": {
    "addr:full":"1318 E Boston St Seattle WA 98102",
    "addr:housenumber":"1318",
    "addr:postcode":"98102",
    "addr:street":"E Boston St",
    "iso:country":"US",
    "sg:address":"1318 E Boston St",
    "sg:city":"Seattle",
    "sg:classifiers":[
        {
            "category":"Farming",
            "subcategory":"Farm & Veterinary Services",
            "type":"Manufacturing & Wholesale Goods"
        }
    ],
    "sg:phone":"+1 206 322 3431",
    "sg:postcode":"98102",
    "sg:province":"WA",
    "sg:tags":[
        "for",
        "soil",
        "site",
        "sampling",
        "construction",
        "drilling",
        "test"
    ],
    "wof:name":"Associated Drilling Inc",
    "wof:placetype":"venue"
},
  "geometry": {"coordinates":[-122.315468,47.638336],"type":"Point"}
}