{
  "type": "Feature",
  "properties": {
    "addr:full":"5102 80th Ave W Tacoma WA 98467",
    "addr:housenumber":"5102",
    "addr:postcode":"98467",
    "addr:street":"80Th Ave W",
    "iso:country":"US",
    "sg:address":"5102 80th Ave W",
    "sg:city":"Tacoma",
    "sg:classifiers":[
        {
            "category":"Personal",
            "subcategory":"Beauty Salon",
            "type":"Services"
        }
    ],
    "sg:phone":"+1 253 565 3054",
    "sg:postcode":"98467",
    "sg:province":"WA",
    "sg:tags":[
        "shop"
    ],
    "wof:name":"Sallys Shoppe",
    "wof:placetype":"venue"
},
  "geometry": {"coordinates":[-122.543987,47.210815],"type":"Point"}
}