{
  "type": "Feature",
  "properties": {
    "addr:full":"7406 Latona Ave NE Seattle WA 98115",
    "addr:housenumber":"7406",
    "addr:postcode":"98115",
    "addr:street":"Latona Ave Ne",
    "iso:country":"US",
    "sg:address":"7406 Latona Ave NE",
    "sg:city":"Seattle",
    "sg:classifiers":[
        {
            "category":"Building & Trades",
            "subcategory":"Locksmith",
            "type":"Services"
        }
    ],
    "sg:phone":"+1 206 701 6773",
    "sg:postcode":"98115",
    "sg:province":"WA",
    "sg:tags":[
        "key"
    ],
    "wof:name":"Locksmith 0 & 0 24 Hour",
    "wof:placetype":"venue"
},
  "geometry": {"coordinates":[-122.326493,47.682195],"type":"Point"}
}