{
  "type": "Feature",
  "properties": {
    "iso:country":"US",
    "sg:address":"360 NW Dogwood St",
    "sg:city":"Issaquah",
    "sg:classifiers":[
        {
            "category":"Professional",
            "subcategory":"Business Services",
            "type":"Services"
        }
    ],
    "sg:phone":"+1 253 538 7293",
    "sg:postcode":"98027",
    "sg:province":"WA",
    "wof:name":"JW Drafting Services",
    "wof:placetype":"venue"
},
  "geometry": {"coordinates":[-122.041849,47.533914],"type":"Point"}
}