{
  "type": "Feature",
  "properties": {
    "addr:full":"40 Jessica Rd Pasco WA 99301",
    "addr:housenumber":"40",
    "addr:postcode":"99301",
    "addr:street":"Jessica Rd",
    "iso:country":"US",
    "sg:address":"40 Jessica Rd",
    "sg:city":"Pasco",
    "sg:classifiers":[
        {
            "category":"Farming",
            "subcategory":"Farm",
            "type":"Manufacturing & Wholesale Goods"
        }
    ],
    "sg:phone":"+1 509 544 0915",
    "sg:postcode":"99301",
    "sg:province":"WA",
    "sg:tags":[
        "crop",
        "general"
    ],
    "wof:name":"Felix Farms",
    "wof:placetype":"venue"
},
  "geometry": {"coordinates":[-118.890877,46.264282],"type":"Point"}
}