{
  "type": "Feature",
  "properties": {
    "addr:full":"54 Fairbairn Rd Montesano WA 98563",
    "addr:housenumber":"54",
    "addr:postcode":"98563",
    "addr:street":"Fairbairn Rd",
    "iso:country":"US",
    "sg:address":"54 Fairbairn Rd",
    "sg:city":"Montesano",
    "sg:classifiers":[
        {
            "category":"Insurance",
            "subcategory":"Hazard Insurance",
            "type":"Services"
        }
    ],
    "sg:phone":"+1 360 249 5393",
    "sg:postcode":"98563",
    "sg:province":"WA",
    "sg:tags":[
        "commercial",
        "business"
    ],
    "wof:name":"Broten Insurance Services",
    "wof:placetype":"venue"
},
  "geometry": {"coordinates":[-123.532973,46.995667],"type":"Point"}
}