{
  "type": "Feature",
  "properties": {
    "addr:full":"1232 Llandwood Ave Richland WA 99352",
    "addr:housenumber":"1232",
    "addr:postcode":"99352",
    "addr:street":"Llandwood Ave",
    "iso:country":"US",
    "sg:address":"1232 Llandwood Ave",
    "sg:city":"Richland",
    "sg:classifiers":[
        {
            "category":"Professional",
            "subcategory":"Art Services",
            "type":"Services"
        }
    ],
    "sg:phone":"+1 509 627 0557",
    "sg:postcode":"99352",
    "sg:province":"WA",
    "sg:tags":[
        "commercial",
        "design"
    ],
    "wof:name":"Keystone Graphics",
    "wof:placetype":"venue"
},
  "geometry": {"coordinates":[-119.270039,46.240919],"type":"Point"}
}