{
  "type": "Feature",
  "properties": {
    "addr:full":"613 Brook Ct Lynden WA 98264",
    "addr:housenumber":"613",
    "addr:postcode":"98264",
    "addr:street":"Brook Ct",
    "iso:country":"US",
    "sg:address":"613 Brook Ct",
    "sg:city":"Lynden",
    "sg:classifiers":[
        {
            "category":"Building & Trades",
            "subcategory":"Construction",
            "type":"Services"
        }
    ],
    "sg:phone":"+1 360 354 5664",
    "sg:postcode":"98264",
    "sg:province":"WA",
    "sg:tags":[
        "contractor"
    ],
    "wof:name":"Kooi Veryl Roofing",
    "wof:placetype":"venue"
},
  "geometry": {"coordinates":[-122.436322,48.956701],"type":"Point"}
}