{
  "type": "Feature",
  "properties": {
    "addr:full":"511 S Weller Street Seattle WA 98104",
    "addr:housenumber":"511",
    "addr:postcode":"98104",
    "addr:street":"S Weller Street",
    "iso:country":"US",
    "sg:address":"511 S Weller Street",
    "sg:city":"Seattle",
    "sg:classifiers":[
        {
            "category":"Restaurant",
            "type":"Food & Drink"
        }
    ],
    "sg:phone":"+1 206 624 9156",
    "sg:postcode":"98104",
    "sg:province":"WA",
    "sg:tags":[
        "hawaiian"
    ],
    "wof:name":"Aloha Plates",
    "wof:placetype":"venue"
},
  "geometry": {"coordinates":[-122.327051,47.597643],"type":"Point"}
}