{
  "type": "Feature",
  "properties": {
    "addr:full":"7871 Chico Way NW Bremerton WA 98312",
    "addr:housenumber":"7871",
    "addr:postcode":"98312",
    "addr:street":"Chico Way Nw",
    "iso:country":"US",
    "sg:address":"7871 Chico Way NW",
    "sg:city":"Bremerton",
    "sg:classifiers":[
        {
            "category":"Manufacturing",
            "subcategory":"Textiles",
            "type":"Manufacturing & Wholesale Goods"
        }
    ],
    "sg:phone":"+1 360 692 7995",
    "sg:postcode":"98312",
    "sg:province":"WA",
    "sg:tags":[
        "textiles-manufacturers"
    ],
    "wof:name":"Wool Works",
    "wof:placetype":"venue"
},
  "geometry": {"coordinates":[-122.703873,47.633539],"type":"Point"}
}