{
  "type": "Feature",
  "properties": {
    "addr:full":"3813 80th St E Tacoma WA 98443",
    "addr:housenumber":"3813",
    "addr:postcode":"98443",
    "addr:street":"80Th St",
    "iso:country":"US",
    "sg:address":"3813 80th St E",
    "sg:city":"Tacoma",
    "sg:classifiers":[
        {
            "category":"Wholesale",
            "subcategory":"Groceries",
            "type":"Manufacturing & Wholesale Goods"
        }
    ],
    "sg:phone":"+1 253 539 1686",
    "sg:postcode":"98443",
    "sg:province":"WA",
    "sg:tags":[
        "frozen",
        "food"
    ],
    "wof:name":"Washington Farms Inc",
    "wof:placetype":"venue"
},
  "geometry": {"coordinates":[-122.37450800000001,47.184522],"type":"Point"}
}