{
  "type": "Feature",
  "properties": {
    "addr:full":"9209 NE 142nd Way Bothell WA 98011",
    "addr:housenumber":"9209",
    "addr:postcode":"98011",
    "addr:street":"Ne 142Nd Way",
    "iso:country":"US",
    "sg:address":"9209 NE 142nd Way",
    "sg:city":"Bothell",
    "sg:classifiers":[
        {
            "category":"Insurance",
            "subcategory":"Health Insurance",
            "type":"Services"
        }
    ],
    "sg:phone":"+1 425 821 0951",
    "sg:postcode":"98011",
    "sg:province":"WA",
    "sg:tags":[
        "market"
    ],
    "wof:name":"Melki Elias & Beverly",
    "wof:placetype":"venue"
},
  "geometry": {"coordinates":[-122.218002,47.729599],"type":"Point"}
}