{
  "type": "Feature",
  "properties": {
    "addr:full":"210 W Highland Ave Chelan WA 98816",
    "addr:housenumber":"210",
    "addr:postcode":"98816",
    "addr:street":"W Highland Ave",
    "iso:country":"US",
    "sg:address":"210 W Highland Ave",
    "sg:city":"Chelan",
    "sg:classifiers":[
        {
            "category":"Building & Trades",
            "subcategory":"Construction",
            "type":"Services"
        }
    ],
    "sg:phone":"+1 509 670 6903",
    "sg:postcode":"98816",
    "sg:province":"WA",
    "sg:tags":[
        "house",
        "architectural"
    ],
    "wof:name":"Anderson Homes & Design",
    "wof:placetype":"venue"
},
  "geometry": {"coordinates":[-120.021849,47.845765],"type":"Point"}
}