{
  "type": "Feature",
  "properties": {
    "addr:full":"4107 Chestnut Dr W Tacoma WA 98466",
    "addr:housenumber":"4107",
    "addr:postcode":"98466",
    "addr:street":"Chestnut Dr W",
    "iso:country":"US",
    "sg:address":"4107 Chestnut Dr W",
    "sg:city":"Tacoma",
    "sg:classifiers":[
        {
            "category":"Professional",
            "subcategory":"Computer Services",
            "type":"Services"
        }
    ],
    "sg:phone":"+1 253 565 4237",
    "sg:postcode":"98466",
    "sg:province":"WA",
    "sg:tags":[
        "custom",
        "programing",
        "graphics"
    ],
    "wof:name":"Hudak Graphics",
    "wof:placetype":"venue"
},
  "geometry": {"coordinates":[-122.55547300000001,47.219222],"type":"Point"}
}