{
  "type": "Feature",
  "properties": {
    "addr:full":"56 Whalers St Aberdeen WA 98520",
    "addr:housenumber":"56",
    "addr:postcode":"98520",
    "addr:street":"Whalers St",
    "iso:country":"US",
    "sg:address":"56 Whalers St",
    "sg:city":"Aberdeen",
    "sg:classifiers":[
        {
            "category":"Food & Beverages",
            "subcategory":"Meat & Fish",
            "type":"Retail Goods"
        }
    ],
    "sg:phone":"+1 360 648 2335",
    "sg:postcode":"98520",
    "sg:province":"WA",
    "sg:tags":[
        "seafood"
    ],
    "wof:name":"Elk River Shellfish",
    "wof:placetype":"venue"
},
  "geometry": {"coordinates":[-124.060254,46.863464],"type":"Point"}
}