{
  "type": "Feature",
  "properties": {
    "addr:full":"4271 April Dr Wenatchee WA 98801",
    "addr:housenumber":"4271",
    "addr:postcode":"98801",
    "addr:street":"April Dr",
    "iso:country":"US",
    "sg:address":"4271 April Dr",
    "sg:city":"Wenatchee",
    "sg:classifiers":[
        {
            "category":"Building & Trades",
            "subcategory":"Construction",
            "type":"Services"
        }
    ],
    "sg:phone":"+1 509 682 4842",
    "sg:postcode":"98801",
    "sg:province":"WA",
    "sg:tags":[
        "designer",
        "dealer",
        "pool",
        "swimming"
    ],
    "wof:name":"Patio Pools Of Chelan",
    "wof:placetype":"venue"
},
  "geometry": {"coordinates":[-120.36417899999999,47.49709],"type":"Point"}
}