{
  "type": "Feature",
  "properties": {
    "addr:full":"935 88th Ave NE Medina WA 98039",
    "addr:housenumber":"935",
    "addr:postcode":"98039",
    "addr:street":"88Th Ave Ne Medina",
    "iso:country":"US",
    "sg:address":"935 88th Ave NE",
    "sg:city":"Medina",
    "sg:classifiers":[
        {
            "category":"Manufacturing",
            "subcategory":"Food",
            "type":"Manufacturing & Wholesale Goods"
        }
    ],
    "sg:phone":"+1 425 454 2912",
    "sg:postcode":"98039",
    "sg:province":"WA",
    "sg:tags":[
        "meat",
        "mfg",
        "packer",
        "industry",
        "supply",
        "preparation",
        "equipment",
        "machinery"
    ],
    "sg:website":"http://www.claudon.com",
    "wof:name":"Claudon Inc",
    "wof:placetype":"venue"
},
  "geometry": {"coordinates":[-122.22324999999999,47.617974],"type":"Point"}
}