{
  "type": "Feature",
  "properties": {
    "addr:full":"1020 112th St SW Everett WA 98204",
    "addr:housenumber":"1020",
    "addr:postcode":"98204",
    "addr:street":"112Th St Sw",
    "iso:country":"US",
    "sg:address":"1020 112th St SW",
    "sg:city":"Everett",
    "sg:classifiers":[
        {
            "category":"Real Estate",
            "subcategory":"Real Estate Operator",
            "type":"Services"
        }
    ],
    "sg:phone":"+1 425 355 6775",
    "sg:postcode":"98204",
    "sg:province":"WA",
    "sg:tags":[
        "building",
        "apartment"
    ],
    "wof:name":"North Meadows",
    "wof:placetype":"venue"
},
  "geometry": {"coordinates":[-122.247449,47.896374],"type":"Point"}
}