{
  "type": "Feature",
  "properties": {
    "addr:full":"15633 Lange Rd Mount Vernon WA 98273",
    "addr:postcode":"15633;98273",
    "addr:street":"Lange Rd",
    "iso:country":"US",
    "sg:address":"15633 Lange Rd",
    "sg:city":"Mount Vernon",
    "sg:classifiers":[
        {
            "category":"Retail",
            "subcategory":"Repair Shop",
            "type":"Services"
        }
    ],
    "sg:phone":"+1 360 422 8530",
    "sg:postcode":"98273",
    "sg:province":"WA",
    "sg:tags":[
        "refrigeration"
    ],
    "wof:name":"Snowline Refridgeration",
    "wof:placetype":"venue"
},
  "geometry": {"coordinates":[-122.21213899999999,48.418454],"type":"Point"}
}