{
  "type": "Feature",
  "properties": {
    "addr:full":"121 S Main St Colfax WA 99111",
    "addr:housenumber":"121",
    "addr:postcode":"99111",
    "addr:street":"S Main St",
    "iso:country":"US",
    "sg:address":"121 S Main St",
    "sg:city":"Colfax",
    "sg:classifiers":[
        {
            "category":"Shopping",
            "subcategory":"Used Merchandise",
            "type":"Retail Goods"
        }
    ],
    "sg:phone":"+1 509 397 2522",
    "sg:postcode":"99111",
    "sg:province":"WA",
    "sg:tags":[
        "antique"
    ],
    "wof:name":"Whitman Mall",
    "wof:placetype":"venue"
},
  "geometry": {"coordinates":[-117.364614,46.880683],"type":"Point"}
}