{
  "type": "Feature",
  "properties": {
    "addr:full":"9437 10th Ave SW Seattle WA 98106",
    "addr:housenumber":"9437",
    "addr:postcode":"98106",
    "addr:street":"10Th Ave Sw",
    "iso:country":"US",
    "sg:address":"9437 10th Ave SW",
    "sg:city":"Seattle",
    "sg:classifiers":[
        {
            "category":"Social Services",
            "subcategory":"Job Training",
            "type":"Services"
        }
    ],
    "sg:phone":"+1 206 768 0199",
    "sg:postcode":"98106",
    "sg:province":"WA",
    "sg:tags":[
        "consultant"
    ],
    "sg:website":"http://www.imaging-resources.com",
    "wof:name":"Imaging Resources, Inc.",
    "wof:placetype":"venue"
},
  "geometry": {"coordinates":[-122.348004,47.518304],"type":"Point"}
}