{
  "type": "Feature",
  "properties": {
    "addr:full":"1500 19th Ave NW Issaquah WA 98027",
    "addr:housenumber":"1500",
    "addr:postcode":"98027",
    "addr:street":"19Th Ave Nw",
    "iso:country":"US",
    "sg:address":"1500 19th Ave NW",
    "sg:city":"Issaquah",
    "sg:classifiers":[
        {
            "category":"Retail",
            "subcategory":"Auto Repair",
            "type":"Services"
        }
    ],
    "sg:phone":"+1 425 392 1268",
    "sg:postcode":"98027",
    "sg:province":"WA",
    "sg:tags":[
        "truck"
    ],
    "wof:name":"Bakamus Truck Repair",
    "wof:placetype":"venue"
},
  "geometry": {"coordinates":[-122.067488,47.547389],"type":"Point"}
}