{
  "type": "Feature",
  "properties": {
    "addr:full":"920 N 34th St Seattle WA 98103",
    "addr:housenumber":"920",
    "addr:postcode":"98103",
    "addr:street":"N 34Th St",
    "iso:country":"US",
    "sg:address":"920 N 34th St",
    "sg:city":"Seattle",
    "sg:classifiers":[
        {
            "category":"Real Estate",
            "subcategory":"Real Estate Operator",
            "type":"Services"
        }
    ],
    "sg:phone":"+1 206 632 0301",
    "sg:postcode":"98103",
    "sg:province":"WA",
    "sg:tags":[
        "apartment"
    ],
    "sg:website":"www.weidner.com",
    "wof:name":"St. James Tower Apartments",
    "wof:placetype":"venue"
},
  "geometry": {"coordinates":[-122.346183,47.649146],"type":"Point"}
}