{
  "type": "Feature",
  "properties": {
    "addr:full":"455 St Helens Ave Tacoma WA 98402",
    "addr:housenumber":"455",
    "addr:postcode":"98402",
    "addr:street":"St Helens Ave",
    "iso:country":"US",
    "sg:address":"455 St Helens Ave",
    "sg:city":"Tacoma",
    "sg:classifiers":[
        {
            "category":"Autos & Motor Vehicles",
            "subcategory":"Automobile Sales",
            "type":"Retail Goods"
        }
    ],
    "sg:phone":"+1 253 627 1052",
    "sg:postcode":"98402",
    "sg:province":"WA",
    "sg:tags":[
        "used"
    ],
    "wof:name":"Sharp & Sons",
    "wof:placetype":"venue"
},
  "geometry": {"coordinates":[-122.44348100000001,47.259153],"type":"Point"}
}