{
  "type": "Feature",
  "properties": {
    "iso:country":"US",
    "sg:address":"11695 Duncan Rd",
    "sg:city":"Leavenworth",
    "sg:classifiers":[
        {
            "category":"Building & Trades",
            "subcategory":"Construction",
            "type":"Services"
        }
    ],
    "sg:phone":"+1 509 548 5605",
    "sg:postcode":"98826",
    "sg:province":"WA",
    "sg:tags":[
        "general",
        "contractor"
    ],
    "wof:name":"Duncan Construction",
    "wof:placetype":"venue"
},
  "geometry": {"coordinates":[-120.64750100000001,47.595321],"type":"Point"}
}