{
  "type": "Feature",
  "properties": {
    "addr:full":"12740 Bel-Red Rd Bellevue WA 98005",
    "addr:postcode":"12740;98005",
    "addr:street":"Bel-Red Rd",
    "iso:country":"US",
    "sg:address":"12740 Bel-Red Rd",
    "sg:city":"Bellevue",
    "sg:classifiers":[
        {
            "category":"Bars & Pubs",
            "subcategory":"Lounge",
            "type":"Food & Drink"
        },
        {
            "category":"Bars & Pubs",
            "subcategory":"Hookah Bar",
            "type":"Food & Drink"
        }
    ],
    "sg:postcode":"98005",
    "sg:province":"WA",
    "sg:website":"www.theclubstatic.com/",
    "wof:name":"Shisha Lounge",
    "wof:placetype":"venue"
},
  "geometry": {"coordinates":[-122.16972800000001,47.621001],"type":"Point"}
}