{
  "type": "Feature",
  "properties": {
    "addr:full":"45 Robbins Rd Nordland WA 98358",
    "addr:housenumber":"45",
    "addr:postcode":"98358",
    "addr:street":"Robbins Rd",
    "iso:country":"US",
    "sg:address":"45 Robbins Rd",
    "sg:city":"Nordland",
    "sg:classifiers":[
        {
            "category":"Manufacturing",
            "subcategory":"Watercraft",
            "type":"Manufacturing & Wholesale Goods"
        }
    ],
    "sg:phone":"+1 360 821 9301",
    "sg:postcode":"98358",
    "sg:province":"WA",
    "wof:name":"Cape Flattery",
    "wof:placetype":"venue"
},
  "geometry": {"coordinates":[-122.69713900000001,48.017461],"type":"Point"}
}