{
  "type": "Feature",
  "properties": {
    "addr:full":"3533 172nd St NE Arlington WA 98223",
    "addr:housenumber":"3533",
    "addr:postcode":"98223",
    "addr:street":"172Nd St Ne",
    "iso:country":"US",
    "sg:address":"3533 172nd St NE",
    "sg:city":"Arlington",
    "sg:classifiers":[
        {
            "category":"Health Services",
            "subcategory":"Doctor",
            "type":"Services"
        }
    ],
    "sg:phone":"+1 360 658 3000",
    "sg:postcode":"98223",
    "sg:province":"WA",
    "wof:name":"Otto J Hanssen DDS",
    "wof:placetype":"venue"
},
  "geometry": {"coordinates":[-122.177932,48.152505],"type":"Point"}
}