{
  "type": "Feature",
  "properties": {
    "addr:full":"7114 Greenwood Ave N Seattle WA 98103",
    "addr:housenumber":"7114",
    "addr:postcode":"98103",
    "addr:street":"Greenwood Ave N",
    "iso:country":"US",
    "sg:address":"7114 Greenwood Ave N",
    "sg:city":"Seattle",
    "sg:classifiers":[
        {
            "category":"Retail",
            "subcategory":"Laundry & Dry Cleaning",
            "type":"Services"
        }
    ],
    "sg:phone":"+1 206 782 9002",
    "sg:postcode":"98103",
    "sg:province":"WA",
    "sg:website":"www.bakkersfinedrycleaning.com",
    "wof:name":"Bakker's Fine Drycleaning",
    "wof:placetype":"venue"
},
  "geometry": {"coordinates":[-122.355307,47.68045],"type":"Point"}
}