{
  "type": "Feature",
  "properties": {
    "addr:full":"1919 E 5th St Vancouver WA 98661",
    "addr:housenumber":"1919",
    "addr:postcode":"98661",
    "addr:street":"E 5Th St",
    "iso:country":"US",
    "sg:address":"1919 E 5th St",
    "sg:city":"Vancouver",
    "sg:classifiers":[
        {
            "category":"Organizations",
            "subcategory":"Membership Organization",
            "type":"Services"
        }
    ],
    "sg:phone":"+1 360 213 0917",
    "sg:postcode":"98661",
    "sg:province":"WA",
    "sg:tags":[
        "military",
        "veteran"
    ],
    "wof:name":"Legion Industries",
    "wof:placetype":"venue"
},
  "geometry": {"coordinates":[-122.65221200000001,45.624466],"type":"Point"}
}