{
  "type": "Feature",
  "properties": {
    "addr:full":"6309 Evergreen Way Ste 6309 Everett WA 98203",
    "addr:housenumber":"6309",
    "addr:postcode":"98203",
    "addr:street":"Evergreen Way Ste 6309",
    "iso:country":"US",
    "sg:address":"6309 Evergreen Way Ste 6309",
    "sg:city":"Everett",
    "sg:phone":"+1 425 353 3224",
    "sg:postcode":"98203",
    "sg:province":"WA",
    "sg:website":"http://www.myvietnam.com",
    "wof:name":"My Vietnam",
    "wof:placetype":"venue"
},
  "geometry": {"coordinates":[-122.217776,47.941037],"type":"Point"}
}