{
  "type": "Feature",
  "properties": {
    "iso:country":"US",
    "sg:address":"12147 Clubhouse Ln",
    "sg:city":"Mukilteo",
    "sg:classifiers":[
        {
            "category":"Professional",
            "type":"Services"
        }
    ],
    "sg:phone":"+1 425 743 1767",
    "sg:postcode":"98275",
    "sg:province":"WA",
    "wof:name":"Plenius International",
    "wof:placetype":"venue"
},
  "geometry": {"coordinates":[-122.317982,47.885346],"type":"Point"}
}