{
  "type": "Feature",
  "properties": {
    "addr:full":"707 E Holly St Bellingham WA 98225",
    "addr:housenumber":"707",
    "addr:postcode":"98225",
    "addr:street":"E Holly St",
    "iso:country":"US",
    "sg:address":"707 E Holly St",
    "sg:city":"Bellingham",
    "sg:classifiers":[
        {
            "category":"Health Services",
            "subcategory":"Optometrist",
            "type":"Services"
        },
        {
            "category":"Shopping",
            "subcategory":"Optical Goods",
            "type":"Retail Goods"
        },
        {
            "category":"Personal",
            "subcategory":"Shoe Repair & Shine",
            "type":"Services"
        }
    ],
    "sg:phone":"+1 360 746 2545",
    "sg:postcode":"98225",
    "sg:province":"WA",
    "sg:tags":[
        "lens",
        "eyeglass",
        "contact",
        "sunglass"
    ],
    "sg:website":"http://www.VisionSource-Bellingham.com",
    "wof:name":"Bellingham Vision Source",
    "wof:placetype":"venue"
},
  "geometry": {"coordinates":[-122.472927,48.745695],"type":"Point"}
}