{
  "type": "Feature",
  "properties": {
    "addr:full":"10655 NE 4th St Ste 300 Bellevue WA 98004",
    "addr:housenumber":"10655",
    "addr:postcode":"98004",
    "addr:street":"Ne 4Th St Ste 300",
    "iso:country":"US",
    "sg:address":"10655 NE 4th St Ste 300",
    "sg:city":"Bellevue",
    "sg:classifiers":[
        {
            "category":"Real Estate",
            "subcategory":"Real Estate Services",
            "type":"Services"
        },
        {
            "category":"Real Estate",
            "subcategory":"Real Estate Agent",
            "type":"Services"
        }
    ],
    "sg:phone":"+1 425 455 0500",
    "sg:postcode":"98004",
    "sg:province":"WA",
    "sg:tags":[
        "buyer",
        "management",
        "broker"
    ],
    "wof:name":"J S H Properties, Inc",
    "wof:placetype":"venue"
},
  "geometry": {"coordinates":[-122.197534,47.613879],"type":"Point"}
}