{
  "type": "Feature",
  "properties": {
    "addr:full":"41 34th St Washougal WA 98671",
    "addr:housenumber":"41",
    "addr:postcode":"98671",
    "addr:street":"34Th St",
    "iso:country":"US",
    "sg:address":"41 34th St",
    "sg:city":"Washougal",
    "sg:classifiers":[
        {
            "category":"Building & Trades",
            "subcategory":"Construction",
            "type":"Services"
        }
    ],
    "sg:phone":"+1 360 835 5146",
    "sg:postcode":"98671",
    "sg:province":"WA",
    "sg:tags":[
        "house"
    ],
    "wof:name":"Gary L Anderson Remodeling",
    "wof:placetype":"venue"
},
  "geometry": {"coordinates":[-122.332838,45.575683],"type":"Point"}
}