{
  "type": "Feature",
  "properties": {
    "addr:full":"4207 E Main Ave Spokane WA 99202",
    "addr:housenumber":"4207",
    "addr:postcode":"99202",
    "addr:street":"E Main Ave",
    "iso:country":"US",
    "sg:address":"4207 E Main Ave",
    "sg:city":"Spokane",
    "sg:classifiers":[
        {
            "category":"Government",
            "subcategory":"Office",
            "type":"Public Place"
        }
    ],
    "sg:phone":"+1 509 353 2504",
    "sg:postcode":"99202",
    "sg:province":"WA",
    "sg:tags":[
        "government-united",
        "state"
    ],
    "wof:name":"United States Government General Services Admi",
    "wof:placetype":"venue"
},
  "geometry": {"coordinates":[-117.348378,47.659091],"type":"Point"}
}