{
  "type": "Feature",
  "properties": {
    "addr:full":"1015 Vandercook Way Longview WA 98632",
    "addr:housenumber":"1015",
    "addr:postcode":"98632",
    "addr:street":"Vandercook Way",
    "iso:country":"US",
    "sg:address":"1015 Vandercook Way",
    "sg:city":"Longview",
    "sg:classifiers":[
        {
            "category":"Building & Trades",
            "subcategory":"Construction",
            "type":"Services"
        },
        {
            "category":"Home & Garden",
            "subcategory":"Carpets & Floor Coverings",
            "type":"Retail Goods"
        }
    ],
    "sg:phone":"+1 800 394 3064",
    "sg:postcode":"98632",
    "sg:province":"WA",
    "sg:tags":[
        "material",
        "tile-contractors",
        "rug",
        "flooring",
        "contractor"
    ],
    "sg:website":"http://www.filitrac.com/Click.aspx?tid=BDEDC5D5EF8BAE3541B5938870DA3DDECE60F60FEE115906&FiliAff=15016&sid=99202&utm_source=YellowPages&utm_medium=ppc&utm_campaign=national&utm_term=98632",
    "wof:name":"Columbia River Carpet One Floor & Home",
    "wof:placetype":"venue"
},
  "geometry": {"coordinates":[-122.92841799999999,46.142726],"type":"Point"}
}