{
  "type": "Feature",
  "properties": {
    "addr:full":"300 NE Northgate Way Seattle WA 98125",
    "addr:housenumber":"300",
    "addr:postcode":"98125",
    "addr:street":"Ne Northgate Way",
    "iso:country":"US",
    "sg:address":"300 NE Northgate Way",
    "sg:city":"Seattle",
    "sg:classifiers":[
        {
            "category":"Restaurant",
            "type":"Food & Drink"
        }
    ],
    "sg:menulink":"http://www.allmenus.com/wa/seattle/139183-quiznos-sub/menu/",
    "sg:phone":"+1 206 306 8811",
    "sg:postcode":"98125",
    "sg:province":"WA",
    "sg:tags":[
        "wrap",
        "american",
        "sandwich"
    ],
    "wof:name":"Quiznos Sub",
    "wof:placetype":"venue"
},
  "geometry": {"coordinates":[-122.325954,47.708664],"type":"Point"}
}