{
  "type": "Feature",
  "properties": {
    "addr:full":"2801 E 35th Ave Spokane WA 99223",
    "addr:housenumber":"2801",
    "addr:postcode":"99223",
    "addr:street":"E 35Th Ave",
    "iso:country":"US",
    "sg:address":"2801 E 35th Ave",
    "sg:city":"Spokane",
    "sg:classifiers":[
        {
            "category":"Professional",
            "type":"Services"
        }
    ],
    "sg:phone":"+1 509 534 3500",
    "sg:postcode":"99223",
    "sg:province":"WA",
    "wof:name":"Forge Lord",
    "wof:placetype":"venue"
},
  "geometry": {"coordinates":[-117.369621,47.622823],"type":"Point"}
}