{
  "type": "Feature",
  "properties": {
    "addr:full":"32917 174th Pl SE Auburn WA 98092",
    "addr:housenumber":"32917",
    "addr:postcode":"98092",
    "addr:street":"174Th Pl Se",
    "iso:country":"US",
    "sg:address":"32917 174th Pl SE",
    "sg:city":"Auburn",
    "sg:classifiers":[
        {
            "category":"Building & Trades",
            "subcategory":"Construction",
            "type":"Services"
        }
    ],
    "sg:phone":"+1 253 939 7761",
    "sg:postcode":"98092",
    "sg:province":"WA",
    "sg:tags":[
        "house"
    ],
    "wof:name":"Berkshire Construction Inc",
    "wof:placetype":"venue"
},
  "geometry": {"coordinates":[-122.109572,47.306622],"type":"Point"}
}