{
  "type": "Feature",
  "properties": {
    "addr:full":"3310 E Lake Sammamish Pkwy SE Sammamish WA 98075",
    "addr:housenumber":"3310",
    "addr:postcode":"98075",
    "addr:street":"E Lake Sammamish Pkwy Se",
    "iso:country":"US",
    "sg:address":"3310 E Lake Sammamish Pkwy SE",
    "sg:city":"Sammamish",
    "sg:classifiers":[
        {
            "category":"Health Services",
            "subcategory":"Optometrist",
            "type":"Services"
        }
    ],
    "sg:phone":"+1 425 391 1116",
    "sg:postcode":"98075",
    "sg:province":"WA",
    "wof:name":"Chin Brent Tod",
    "wof:placetype":"venue"
},
  "geometry": {"coordinates":[-122.075197,47.579817],"type":"Point"}
}