{
  "type": "Feature",
  "properties": {
    "addr:full":"1424 156th Ave NE Bellevue WA 98007",
    "addr:housenumber":"1424",
    "addr:postcode":"98007",
    "addr:street":"156Th Ave Ne",
    "iso:country":"US",
    "sg:address":"1424 156th Ave NE",
    "sg:city":"Bellevue",
    "sg:classifiers":[
        {
            "category":"Restaurant",
            "type":"Food & Drink"
        }
    ],
    "sg:phone":"+1 425 562 4800",
    "sg:postcode":"98007",
    "sg:province":"WA",
    "sg:tags":[
        "indian",
        "mediterranean",
        "halal"
    ],
    "sg:website":"www.mygyro.net",
    "wof:name":"International Food Corner",
    "wof:placetype":"venue"
},
  "geometry": {"coordinates":[-122.13243799999999,47.623021],"type":"Point"}
}