{
  "type": "Feature",
  "properties": {
    "addr:full":"621 5th Ave N Ste B Seattle WA 98109",
    "addr:housenumber":"621",
    "addr:postcode":"98109",
    "addr:street":"5Th Ave N Ste B",
    "iso:country":"US",
    "sg:address":"621 5th Ave N Ste B",
    "sg:city":"Seattle",
    "sg:classifiers":[
        {
            "category":"Wholesale",
            "subcategory":"Non-durable Goods",
            "type":"Manufacturing & Wholesale Goods"
        },
        {
            "category":"Manufacturing",
            "subcategory":"Textiles",
            "type":"Manufacturing & Wholesale Goods"
        }
    ],
    "sg:phone":"+1 206 283 6991",
    "sg:postcode":"98109",
    "sg:province":"WA",
    "sg:tags":[
        "dry",
        "goods-wholesale",
        "textiles-manufacturers"
    ],
    "wof:name":"Schoeller Textil Usa",
    "wof:placetype":"venue"
},
  "geometry": {"coordinates":[-122.34754,47.624738],"type":"Point"}
}