{
  "type": "Feature",
  "properties": {
    "addr:full":"329255 US Hwy 2 Newport WA 99156",
    "addr:housenumber":"329255",
    "addr:postcode":"99156",
    "addr:street":"Us Hwy 2",
    "iso:country":"US",
    "sg:address":"329255 US Hwy 2",
    "sg:city":"Newport",
    "sg:classifiers":[
        {
            "category":"Wholesale",
            "subcategory":"Auto Parts",
            "type":"Manufacturing & Wholesale Goods"
        }
    ],
    "sg:phone":"+1 509 447 4444",
    "sg:postcode":"99156",
    "sg:province":"WA",
    "sg:tags":[
        "automobile",
        "rebuilt"
    ],
    "wof:name":"Shag Nasty's Auto & Truck Recy",
    "wof:placetype":"venue"
},
  "geometry": {"coordinates":[-117.110027,48.152181],"type":"Point"}
}