{
  "type": "Feature",
  "properties": {
    "addr:full":"1400 E Kincaid St Mount Vernon WA 98274",
    "addr:housenumber":"1400",
    "addr:postcode":"98274",
    "addr:street":"E Kincaid St",
    "iso:country":"US",
    "sg:address":"1400 E Kincaid St",
    "sg:city":"Mount Vernon",
    "sg:classifiers":[
        {
            "category":"Shopping",
            "subcategory":"Pharmacy",
            "type":"Retail Goods"
        }
    ],
    "sg:phone":"+1 360 428 6465",
    "sg:postcode":"98274",
    "sg:province":"WA",
    "sg:tags":[
        "drugstore"
    ],
    "wof:name":"Skagit Valley Medical Center Pharmacy",
    "wof:placetype":"venue"
},
  "geometry": {"coordinates":[-122.323905,48.416975],"type":"Point"}
}