{
  "type": "Feature",
  "properties": {
    "addr:full":"520 112th St SW Everett WA 98204",
    "addr:housenumber":"520",
    "addr:postcode":"98204",
    "addr:street":"112Th St Sw",
    "iso:country":"US",
    "sg:address":"520 112th St SW",
    "sg:city":"Everett",
    "sg:classifiers":[
        {
            "category":"Health Services",
            "subcategory":"Nursing And Care Facility",
            "type":"Services"
        }
    ],
    "sg:phone":"+1 425 438 9080",
    "sg:postcode":"98204",
    "sg:province":"WA",
    "sg:tags":[
        "intermediate"
    ],
    "wof:name":"Garden Court Retirement Cmnty",
    "wof:placetype":"venue"
},
  "geometry": {"coordinates":[-122.240478,47.896388],"type":"Point"}
}