{
  "type": "Feature",
  "properties": {
    "iso:country":"US",
    "sg:address":"14119 77th Ave E",
    "sg:city":"Puyallup",
    "sg:classifiers":[
        {
            "category":"Building & Trades",
            "subcategory":"Construction",
            "type":"Services"
        }
    ],
    "sg:phone":"+1 253 472 9460",
    "sg:postcode":"98373",
    "sg:province":"WA",
    "sg:tags":[
        "house"
    ],
    "wof:name":"Advance Custom Gutters",
    "wof:placetype":"venue"
},
  "geometry": {"coordinates":[-122.32700199999999,47.126629],"type":"Point"}
}