{
  "type": "Feature",
  "properties": {
    "addr:full":"15643 Sunny Cove Dr SE Olalla WA 98359",
    "addr:housenumber":"15643",
    "addr:postcode":"98359",
    "addr:street":"Sunny Cove Dr Se",
    "iso:country":"US",
    "sg:address":"15643 Sunny Cove Dr SE",
    "sg:city":"Olalla",
    "sg:classifiers":[
        {
            "category":"Banks & Credit Unions",
            "subcategory":"Financial Services",
            "type":"Services"
        }
    ],
    "sg:phone":"+1 253 857 2521",
    "sg:postcode":"98359",
    "sg:province":"WA",
    "sg:tags":[
        "investor"
    ],
    "wof:name":"Stevio Investments Inc",
    "wof:placetype":"venue"
},
  "geometry": {"coordinates":[-122.55443200000001,47.407109],"type":"Point"}
}