{
  "type": "Feature",
  "properties": {
    "addr:full":"2006 S 320th St Federal Way WA 98003",
    "addr:housenumber":"2006",
    "addr:postcode":"98003",
    "addr:street":"S 320Th St",
    "iso:country":"US",
    "sg:address":"2006 S 320th St",
    "sg:city":"Federal Way",
    "sg:classifiers":[
        {
            "category":"Restaurant",
            "type":"Food & Drink"
        }
    ],
    "sg:menulink":"http://www.allmenus.com/wa/auburn/46442-red-lobster/menu/",
    "sg:phone":"+1 253 941 6162",
    "sg:postcode":"98003",
    "sg:province":"WA",
    "sg:tags":[
        "seafood",
        "american"
    ],
    "wof:name":"Red Lobster",
    "wof:placetype":"venue"
},
  "geometry": {"coordinates":[-122.305998,47.315167],"type":"Point"}
}