{
  "type": "Feature",
  "properties": {
    "addr:full":"1801 NW Market St Ste 405 Seattle WA 98107",
    "addr:housenumber":"1801",
    "addr:postcode":"98107",
    "addr:street":"Nw Market St Ste 405",
    "iso:country":"US",
    "sg:address":"1801 NW Market St Ste 405",
    "sg:city":"Seattle",
    "sg:classifiers":[
        {
            "category":"Health Services",
            "subcategory":"Doctor",
            "type":"Services"
        }
    ],
    "sg:phone":"+1 206 781 6060",
    "sg:postcode":"98107",
    "sg:province":"WA",
    "wof:name":"Tina H. Finesmith, M.D.",
    "wof:placetype":"venue"
},
  "geometry": {"coordinates":[-122.380392,47.668342],"type":"Point"}
}