{
  "type": "Feature",
  "properties": {
    "iso:country":"US",
    "sg:address":"1948 SE Lund Ave",
    "sg:city":"Port Orchard",
    "sg:classifiers":[
        {
            "category":"Banks & Credit Unions",
            "subcategory":"Bank",
            "type":"Services"
        }
    ],
    "sg:phone":"+1 360 876 6646",
    "sg:postcode":"98366",
    "sg:province":"WA",
    "sg:tags":[
        "escrow"
    ],
    "sg:website":"www.landamerica.com",
    "wof:name":"Land America Transnation Title",
    "wof:placetype":"venue"
},
  "geometry": {"coordinates":[-122.626048,47.519445],"type":"Point"}
}