{
  "type": "Feature",
  "properties": {
    "addr:full":"74 S Jackson St Seattle WA 98104",
    "addr:housenumber":"74",
    "addr:postcode":"98104",
    "addr:street":"S Jackson St",
    "iso:country":"US",
    "sg:address":"74 S Jackson St",
    "sg:city":"Seattle",
    "sg:classifiers":[
        {
            "category":"Parking",
            "type":"Transportation"
        }
    ],
    "sg:phone":"+1 206 623 2064",
    "sg:postcode":"98104",
    "sg:province":"WA",
    "wof:name":"Imperial Parking Pioneer Sq Garage",
    "wof:placetype":"venue"
},
  "geometry": {"coordinates":[-122.334,47.599201],"type":"Point"}
}