{
  "type": "Feature",
  "properties": {
    "addr:full":"3435 Martin Way E Olympia WA 98506",
    "addr:housenumber":"3435",
    "addr:postcode":"98506",
    "addr:street":"Martin Way E",
    "iso:country":"US",
    "sg:address":"3435 Martin Way E",
    "sg:city":"Olympia",
    "sg:classifiers":[
        {
            "category":"Professional",
            "type":"Services"
        }
    ],
    "sg:phone":"+1 360 493 0400",
    "sg:postcode":"98506",
    "sg:province":"WA",
    "wof:name":"Sound Support Inc",
    "wof:placetype":"venue"
},
  "geometry": {"coordinates":[-122.844814,47.047138],"type":"Point"}
}