{
  "type": "Feature",
  "properties": {
    "addr:full":"929 Olympic Ave Edmonds WA 98020",
    "addr:housenumber":"929",
    "addr:postcode":"98020",
    "addr:street":"Olympic Ave",
    "iso:country":"US",
    "sg:address":"929 Olympic Ave",
    "sg:city":"Edmonds",
    "sg:classifiers":[
        {
            "category":"Personal",
            "subcategory":"Beauty Salon",
            "type":"Services"
        }
    ],
    "sg:phone":"+1 425 672 1719",
    "sg:postcode":"98020",
    "sg:province":"WA",
    "wof:name":"Salon Nouveau",
    "wof:placetype":"venue"
},
  "geometry": {"coordinates":[-122.36286200000001,47.81813],"type":"Point"}
}