{
  "type": "Feature",
  "properties": {
    "addr:full":"5615 W Umatilla Ave Kennewick WA 99336",
    "addr:housenumber":"5615",
    "addr:postcode":"99336",
    "addr:street":"W Umatilla Ave",
    "iso:country":"US",
    "sg:address":"5615 W Umatilla Ave",
    "sg:city":"Kennewick",
    "sg:classifiers":[
        {
            "category":"Health Services",
            "subcategory":"Nursing And Care Facility",
            "type":"Services"
        }
    ],
    "sg:phone":"+1 509 783 1628",
    "sg:postcode":"99336",
    "sg:province":"WA",
    "sg:tags":[
        "intermediate"
    ],
    "wof:name":"Royal Columbian Retirement Inn",
    "wof:placetype":"venue"
},
  "geometry": {"coordinates":[-119.20220500000001,46.226842],"type":"Point"}
}