{
  "type": "Feature",
  "properties": {
    "addr:full":"17314 140th Ave SE Renton WA 98058",
    "addr:housenumber":"17314",
    "addr:postcode":"98058",
    "addr:street":"140Th Ave Se",
    "iso:country":"US",
    "sg:address":"17314 140th Ave SE",
    "sg:city":"Renton",
    "sg:classifiers":[
        {
            "category":"Banks & Credit Unions",
            "subcategory":"Bank",
            "type":"Services"
        }
    ],
    "sg:phone":"+1 425 255 6960",
    "sg:postcode":"98058",
    "sg:province":"WA",
    "sg:tags":[
        "federal",
        "savings"
    ],
    "wof:name":"Washington Mutual Bank",
    "wof:placetype":"venue"
},
  "geometry": {"coordinates":[-122.15400200000001,47.448883],"type":"Point"}
}