{
  "type": "Feature",
  "properties": {
    "addr:full":"319 S Wapato Ave Wapato WA 98951",
    "addr:housenumber":"319",
    "addr:postcode":"98951",
    "addr:street":"S Wapato Ave",
    "iso:country":"US",
    "sg:address":"319 S Wapato Ave",
    "sg:city":"Wapato",
    "sg:classifiers":[
        {
            "category":"Shopping",
            "subcategory":"Used Merchandise",
            "type":"Retail Goods"
        }
    ],
    "sg:phone":"+1 509 952 3564",
    "sg:postcode":"98951",
    "sg:province":"WA",
    "wof:name":"Samora Music & 2nd Hand",
    "wof:placetype":"venue"
},
  "geometry": {"coordinates":[-120.419794,46.445838],"type":"Point"}
}