{
  "type": "Feature",
  "properties": {
    "addr:full":"14 E Casino Rd Everett WA 98208",
    "addr:housenumber":"14",
    "addr:postcode":"98208",
    "addr:street":"E Casino Rd",
    "iso:country":"US",
    "sg:address":"14 E Casino Rd",
    "sg:city":"Everett",
    "sg:classifiers":[
        {
            "category":"Social Services",
            "type":"Services"
        }
    ],
    "sg:phone":"+1 425 670 7285",
    "sg:postcode":"98208",
    "sg:province":"WA",
    "sg:tags":[
        "family",
        "offer",
        "child",
        "free",
        "to",
        "low",
        "income",
        "clothing"
    ],
    "wof:name":"Childrens Village The",
    "wof:placetype":"venue"
},
  "geometry": {"coordinates":[-122.23291,47.921826],"type":"Point"}
}