{
  "type": "Feature",
  "properties": {
    "addr:full":"18784 Ridgefield Rd NW Seattle WA 98177",
    "addr:housenumber":"18784",
    "addr:postcode":"98177",
    "addr:street":"Ridgefield Rd Nw",
    "iso:country":"US",
    "sg:address":"18784 Ridgefield Rd NW",
    "sg:city":"Seattle",
    "sg:classifiers":[
        {
            "category":"Organizations",
            "subcategory":"Non-profit Organization",
            "type":"Services"
        }
    ],
    "sg:phone":"+1 206 546 2172",
    "sg:postcode":"98177",
    "sg:province":"WA",
    "sg:tags":[
        "social"
    ],
    "wof:name":"Innis Arden Activity Commity",
    "wof:placetype":"venue"
},
  "geometry": {"coordinates":[-122.36965600000001,47.764209],"type":"Point"}
}