{
  "type": "Feature",
  "properties": {
    "addr:full":"9594 1st Ave NE Seattle WA 98115",
    "addr:housenumber":"9594",
    "addr:postcode":"98115",
    "addr:street":"1St Ave Ne",
    "iso:country":"US",
    "sg:address":"9594 1st Ave NE",
    "sg:city":"Seattle",
    "sg:classifiers":[
        {
            "category":"Food & Beverages",
            "subcategory":"Specialty",
            "type":"Retail Goods"
        }
    ],
    "sg:phone":"+1 206 362 6414",
    "sg:postcode":"98115",
    "sg:province":"WA",
    "wof:name":"Natural Nutrition Company",
    "wof:placetype":"venue"
},
  "geometry": {"coordinates":[-122.328389,47.699527],"type":"Point"}
}