{
  "type": "Feature",
  "properties": {
    "iso:country":"US",
    "sg:address":"2601 Valencia St",
    "sg:city":"Bellingham",
    "sg:classifiers":[
        {
            "category":"Manufacturing",
            "subcategory":"Metals",
            "type":"Manufacturing & Wholesale Goods"
        }
    ],
    "sg:phone":"+1 360 671 7739",
    "sg:postcode":"98226",
    "sg:province":"WA",
    "sg:tags":[
        "steel",
        "product",
        "mfg"
    ],
    "wof:name":"AAA Weldor",
    "wof:placetype":"venue"
},
  "geometry": {"coordinates":[-122.446696,48.76557],"type":"Point"}
}