{
  "type": "Feature",
  "properties": {
    "iso:country":"US",
    "sg:address":"26903 Sandridge Rd",
    "sg:city":"Ocean Park",
    "sg:classifiers":[
        {
            "category":"Professional",
            "subcategory":"Accounting & Tax Preparation",
            "type":"Services"
        }
    ],
    "sg:phone":"+1 360 665 5397",
    "sg:postcode":"98640",
    "sg:province":"WA",
    "sg:tags":[
        "bookkeeping",
        "general"
    ],
    "wof:name":"Willapa Bookeeping & Bus Svc",
    "wof:placetype":"venue"
},
  "geometry": {"coordinates":[-124.03365700000001,46.496828],"type":"Point"}
}