{
  "type": "Feature",
  "properties": {
    "iso:country":"US",
    "sg:address":"13326 W Sunset Hwy",
    "sg:city":"Airway Heights",
    "sg:classifiers":[
        {
            "category":"Health Services",
            "subcategory":"Doctor",
            "type":"Services"
        }
    ],
    "sg:phone":"+1 509 244 3655",
    "sg:postcode":"99001",
    "sg:province":"WA",
    "sg:tags":[
        "dentist"
    ],
    "wof:name":"Airway Heights Dental Ctr",
    "wof:placetype":"venue"
},
  "geometry": {"coordinates":[-117.593154,47.642908],"type":"Point"}
}