{
  "type": "Feature",
  "properties": {
    "addr:full":"1600 Cooper Point Rd SW Olympia WA 98502",
    "addr:housenumber":"1600",
    "addr:postcode":"98502",
    "addr:street":"Cooper Point Rd Sw",
    "iso:country":"US",
    "sg:address":"1600 Cooper Point Rd SW",
    "sg:city":"Olympia",
    "sg:classifiers":[
        {
            "category":"Restaurant",
            "type":"Food & Drink"
        }
    ],
    "sg:menulink":"http://www.allmenus.com/wa/olympia/49791-pho-hoa/menu/",
    "sg:phone":"+1 260 754 1601",
    "sg:postcode":"98502",
    "sg:province":"WA",
    "sg:tags":[
        "thai",
        "asian",
        "vietnamese"
    ],
    "wof:name":"Pho Hoa",
    "wof:placetype":"venue"
},
  "geometry": {"coordinates":[-122.94123999999999,47.059537],"type":"Point"}
}