{
  "type": "Feature",
  "properties": {
    "addr:full":"908 S Garry Rd Liberty Lake WA 99019",
    "addr:housenumber":"908",
    "addr:postcode":"99019",
    "addr:street":"S Garry Rd",
    "iso:country":"US",
    "sg:address":"908 S Garry Rd",
    "sg:city":"Liberty Lake",
    "sg:classifiers":[
        {
            "category":"Retail",
            "subcategory":"Auto Repair",
            "type":"Services"
        }
    ],
    "sg:phone":"+1 509 218 4978",
    "sg:postcode":"99019",
    "sg:province":"WA",
    "sg:tags":[
        "glass",
        "replacement"
    ],
    "wof:name":"Liberty Lake Auto Glass",
    "wof:placetype":"venue"
},
  "geometry": {"coordinates":[-117.094675,47.646271],"type":"Point"}
}