{
  "type": "Feature",
  "properties": {
    "addr:full":"1114 Broadway Tacoma WA 98402",
    "addr:housenumber":"1114",
    "addr:postcode":"98402",
    "addr:street":"Broadway",
    "iso:country":"US",
    "sg:address":"1114 Broadway",
    "sg:city":"Tacoma",
    "sg:classifiers":[
        {
            "category":"Restaurant",
            "type":"Food & Drink"
        }
    ],
    "sg:menulink":"http://www.allmenus.com/wa/tacoma/45402-varsity-grill/menu/",
    "sg:phone":"+1 253 627 1229",
    "sg:postcode":"98402",
    "sg:province":"WA",
    "sg:tags":[
        "american"
    ],
    "wof:name":"Varsity Grill",
    "wof:placetype":"venue"
},
  "geometry": {"coordinates":[-122.44439800000001,47.262182],"type":"Point"}
}