{
  "type": "Feature",
  "properties": {
    "addr:full":"4120 6th Ave NE Olympia WA 98516",
    "addr:housenumber":"4120",
    "addr:postcode":"98516",
    "addr:street":"6Th Ave Ne",
    "iso:country":"US",
    "sg:address":"4120 6th Ave NE",
    "sg:city":"Olympia",
    "sg:classifiers":[
        {
            "category":"Retail",
            "subcategory":"Auto Rental",
            "type":"Services"
        }
    ],
    "sg:phone":"+1 360 456 1554",
    "sg:postcode":"98516",
    "sg:province":"WA",
    "sg:tags":[
        "truck"
    ],
    "wof:name":"Olympia Truck Leasing",
    "wof:placetype":"venue"
},
  "geometry": {"coordinates":[-122.82850999999999,47.05421],"type":"Point"}
}