{
  "type": "Feature",
  "properties": {
    "addr:full":"515 Maynard Ave S Seattle WA 98104",
    "addr:housenumber":"515",
    "addr:postcode":"98104",
    "addr:street":"Maynard Ave S",
    "iso:country":"US",
    "sg:address":"515 Maynard Ave S",
    "sg:city":"Seattle",
    "sg:classifiers":[
        {
            "category":"Restaurant",
            "type":"Food & Drink"
        }
    ],
    "sg:phone":"+1 206 622 0288",
    "sg:postcode":"98104",
    "sg:province":"WA",
    "sg:tags":[
        "fusion",
        "asian",
        "chinese"
    ],
    "wof:name":"Purple Dot Cafe",
    "wof:placetype":"venue"
},
  "geometry": {"coordinates":[-122.325084,47.598243],"type":"Point"}
}