{
  "type": "Feature",
  "properties": {
    "addr:full":"3922 Mission Creek Rd Cashmere WA 98815",
    "addr:housenumber":"3922",
    "addr:postcode":"98815",
    "addr:street":"Mission Creek Rd",
    "iso:country":"US",
    "sg:address":"3922 Mission Creek Rd",
    "sg:city":"Cashmere",
    "sg:classifiers":[
        {
            "category":"Farming",
            "subcategory":"Farm & Veterinary Services",
            "type":"Manufacturing & Wholesale Goods"
        }
    ],
    "sg:phone":"+1 509 782 5635",
    "sg:postcode":"98815",
    "sg:province":"WA",
    "sg:tags":[
        "management"
    ],
    "wof:name":"Kenneth M Ahrens",
    "wof:placetype":"venue"
},
  "geometry": {"coordinates":[-120.482484,47.487573],"type":"Point"}
}