{
  "type": "Feature",
  "properties": {
    "addr:full":"6111 90th Ave SE Mercer Island WA 98040",
    "addr:housenumber":"6111",
    "addr:postcode":"98040",
    "addr:street":"90Th Ave Se",
    "iso:country":"US",
    "sg:address":"6111 90th Ave SE",
    "sg:city":"Mercer Island",
    "sg:classifiers":[
        {
            "category":"Building & Trades",
            "subcategory":"Construction",
            "type":"Services"
        }
    ],
    "sg:phone":"+1 206 232 3377",
    "sg:postcode":"98040",
    "sg:province":"WA",
    "sg:tags":[
        "house",
        "nonresidential"
    ],
    "wof:name":"Hammond Construction Inc",
    "wof:placetype":"venue"
},
  "geometry": {"coordinates":[-122.21811700000001,47.546294],"type":"Point"}
}