{
  "type": "Feature",
  "properties": {
    "addr:full":"16190 SE Eastgate Way Bellevue WA 98008",
    "addr:postcode":"16190;98008",
    "addr:street":"Se Eastgate Way",
    "iso:country":"US",
    "sg:address":"16190 SE Eastgate Way",
    "sg:city":"Bellevue",
    "sg:classifiers":[
        {
            "category":"Professional",
            "subcategory":"Computer Services",
            "type":"Services"
        }
    ],
    "sg:phone":"+1 425 653 2132",
    "sg:postcode":"98008",
    "sg:province":"WA",
    "sg:tags":[
        "related"
    ],
    "wof:name":"Cowabunga Consulting",
    "wof:placetype":"venue"
},
  "geometry": {"coordinates":[-122.12818799999999,47.578306],"type":"Point"}
}