{
  "type": "Feature",
  "properties": {
    "addr:full":"4080 Factoria Mall Blvd S Bellevue WA 98004",
    "addr:housenumber":"4080",
    "addr:postcode":"98004",
    "addr:street":"Factoria Mall Blvd S Bellevue",
    "iso:country":"US",
    "sg:address":"4080 Factoria Mall Blvd S",
    "sg:city":"Bellevue",
    "sg:classifiers":[
        {
            "category":"Shopping",
            "subcategory":"Pets & Pet Supplies",
            "type":"Retail Goods"
        }
    ],
    "sg:phone":"+1 425 641 5203",
    "sg:postcode":"98004",
    "sg:province":"WA",
    "sg:tags":[
        "store"
    ],
    "sg:website":"www.petco.com",
    "wof:name":"Petco",
    "wof:placetype":"venue"
},
  "geometry": {"coordinates":[-122.206001,47.613899],"type":"Point"}
}