{
  "type": "Feature",
  "properties": {
    "addr:full":"6795 Chico Way NW Bremerton WA 98312",
    "addr:housenumber":"6795",
    "addr:postcode":"98312",
    "addr:street":"Chico Way Nw",
    "iso:country":"US",
    "sg:address":"6795 Chico Way NW",
    "sg:city":"Bremerton",
    "sg:classifiers":[
        {
            "category":"Professional",
            "type":"Services"
        }
    ],
    "sg:phone":"+1 360 876 5169",
    "sg:postcode":"98312",
    "sg:province":"WA",
    "wof:name":"Donna Wright",
    "wof:placetype":"venue"
},
  "geometry": {"coordinates":[-122.70806,47.624929],"type":"Point"}
}