{
  "type": "Feature",
  "properties": {
    "addr:full":"11202 78th Ave E Puyallup WA 98373",
    "addr:housenumber":"11202",
    "addr:postcode":"98373",
    "addr:street":"78Th Ave E",
    "iso:country":"US",
    "sg:address":"11202 78th Ave E",
    "sg:city":"Puyallup",
    "sg:classifiers":[
        {
            "category":"Building & Trades",
            "subcategory":"Construction",
            "type":"Services"
        }
    ],
    "sg:phone":"+1 253 864 8995",
    "sg:postcode":"98373",
    "sg:province":"WA",
    "sg:tags":[
        "fire",
        "house",
        "restoration",
        "damage"
    ],
    "wof:name":"Sterling Group Inc",
    "wof:placetype":"venue"
},
  "geometry": {"coordinates":[-122.325531,47.153949],"type":"Point"}
}