{
  "type": "Feature",
  "properties": {
    "addr:full":"1516 NW 189th St Ridgefield WA 98642",
    "addr:housenumber":"1516",
    "addr:postcode":"98642",
    "addr:street":"Nw 189Th St",
    "iso:country":"US",
    "sg:address":"1516 NW 189th St",
    "sg:city":"Ridgefield",
    "sg:classifiers":[
        {
            "category":"Organizations",
            "subcategory":"Community Association",
            "type":"Services"
        }
    ],
    "sg:phone":"+1 360 887 4222",
    "sg:postcode":"98642",
    "sg:province":"WA",
    "sg:tags":[
        "club"
    ],
    "wof:name":"Ridgefield Little League",
    "wof:placetype":"venue"
},
  "geometry": {"coordinates":[-122.687517,45.757784],"type":"Point"}
}