{
  "type": "Feature",
  "properties": {
    "addr:full":"2226 Elliott Ave Seattle WA 98121",
    "addr:housenumber":"2226",
    "addr:postcode":"98121",
    "addr:street":"Elliott Ave",
    "iso:country":"US",
    "sg:address":"2226 Elliott Ave",
    "sg:city":"Seattle",
    "sg:classifiers":[
        {
            "category":"Manufacturing",
            "subcategory":"Tools & Machinery",
            "type":"Manufacturing & Wholesale Goods"
        }
    ],
    "sg:phone":"+1 206 728 4073",
    "sg:postcode":"98121",
    "sg:province":"WA",
    "sg:tags":[
        "lab",
        "mfg"
    ],
    "wof:name":"Quintiles Pacific",
    "wof:placetype":"venue"
},
  "geometry": {"coordinates":[-122.34648900000001,47.611719],"type":"Point"}
}