{
  "type": "Feature",
  "properties": {
    "addr:full":"6012 Westside Hwy Castle Rock WA 98611",
    "addr:housenumber":"6012",
    "addr:postcode":"98611",
    "addr:street":"Westside Hwy",
    "iso:country":"US",
    "sg:address":"6012 Westside Hwy",
    "sg:city":"Castle Rock",
    "sg:classifiers":[
        {
            "category":"Building & Trades",
            "subcategory":"Construction",
            "type":"Services"
        }
    ],
    "sg:phone":"+1 360 274 7695",
    "sg:postcode":"98611",
    "sg:province":"WA",
    "sg:tags":[
        "excavation",
        "contractor"
    ],
    "wof:name":"Opsahl Craig Rock & Cnstr",
    "wof:placetype":"venue"
},
  "geometry": {"coordinates":[-122.927654,46.306208],"type":"Point"}
}