{
  "type": "Feature",
  "properties": {
    "addr:full":"3121 E Madison Street Seattle WA 98112",
    "addr:housenumber":"3121",
    "addr:postcode":"98112",
    "addr:street":"E Madison Street",
    "iso:country":"US",
    "sg:address":"3121 E Madison Street",
    "sg:city":"Seattle",
    "sg:classifiers":[
        {
            "category":"Retail",
            "subcategory":"Laundry & Dry Cleaning",
            "type":"Services"
        }
    ],
    "sg:phone":"+1 206 328 3599",
    "sg:postcode":"98112",
    "sg:province":"WA",
    "wof:name":"Ultra Cleaners (U C)",
    "wof:placetype":"venue"
},
  "geometry": {"coordinates":[-122.292096,47.626245],"type":"Point"}
}