{
  "type": "Feature",
  "properties": {
    "addr:full":"5522 N Wall St Spokane WA 99205",
    "addr:housenumber":"5522",
    "addr:postcode":"99205",
    "addr:street":"N Wall St",
    "iso:country":"US",
    "sg:address":"5522 N Wall St",
    "sg:city":"Spokane",
    "sg:classifiers":[
        {
            "category":"Health Services",
            "subcategory":"Optometrist",
            "type":"Services"
        }
    ],
    "sg:phone":"+1 509 489 2020",
    "sg:postcode":"99205",
    "sg:province":"WA",
    "wof:name":"Duane L Zink Od",
    "wof:placetype":"venue"
},
  "geometry": {"coordinates":[-117.421908,47.708672],"type":"Point"}
}