{
  "type": "Feature",
  "properties": {
    "addr:full":"1041 W Smith Rd Bellingham WA 98226",
    "addr:housenumber":"1041",
    "addr:postcode":"98226",
    "addr:street":"W Smith Rd",
    "iso:country":"US",
    "sg:address":"1041 W Smith Rd",
    "sg:city":"Bellingham",
    "sg:classifiers":[
        {
            "category":"Professional",
            "subcategory":"Employment Agencies",
            "type":"Services"
        }
    ],
    "sg:phone":"+1 360 384 6344",
    "sg:postcode":"98226",
    "sg:province":"WA",
    "wof:name":"Whatcom County Search & Rescue",
    "wof:placetype":"venue"
},
  "geometry": {"coordinates":[-122.53849099999999,48.833291],"type":"Point"}
}