{
  "type": "Feature",
  "properties": {
    "iso:country":"US",
    "sg:address":"9206 NE 180th St",
    "sg:city":"Bothell",
    "sg:classifiers":[
        {
            "category":"Real Estate",
            "subcategory":"Real Estate Agent",
            "type":"Services"
        }
    ],
    "sg:phone":"+1 425 485 2124",
    "sg:postcode":"98011",
    "sg:province":"WA",
    "wof:name":"Shearwater Development LLC",
    "wof:placetype":"venue"
},
  "geometry": {"coordinates":[-122.21617500000001,47.758531],"type":"Point"}
}