{
  "type": "Feature",
  "properties": {
    "addr:full":"620 Cedar St Pe Ell WA 98522",
    "addr:housenumber":"620",
    "addr:postcode":"98522",
    "addr:street":"Cedar St",
    "iso:country":"US",
    "sg:address":"620 Cedar St",
    "sg:city":"Pe Ell",
    "sg:classifiers":[
        {
            "category":"Organizations",
            "subcategory":"Religious Organization",
            "type":"Services"
        }
    ],
    "sg:phone":"+1 360 291 3082",
    "sg:postcode":"98522",
    "sg:province":"WA",
    "sg:tags":[
        "clergy"
    ],
    "wof:name":"United Methodist Parsonage",
    "wof:placetype":"venue"
},
  "geometry": {"coordinates":[-123.29421600000001,46.574304],"type":"Point"}
}