{
  "type": "Feature",
  "properties": {
    "addr:full":"10516 Danico Ln SE Olympia WA 98513",
    "addr:housenumber":"10516",
    "addr:postcode":"98513",
    "addr:street":"Danico Ln Se",
    "iso:country":"US",
    "sg:address":"10516 Danico Ln SE",
    "sg:city":"Olympia",
    "sg:classifiers":[
        {
            "category":"Communications",
            "type":"Services"
        }
    ],
    "sg:phone":"+1 360 491 7164",
    "sg:postcode":"98513",
    "sg:province":"WA",
    "sg:tags":[
        "consultant",
        "telecommunication"
    ],
    "wof:name":"Manicke Project Services",
    "wof:placetype":"venue"
},
  "geometry": {"coordinates":[-122.714673,46.994143],"type":"Point"}
}