{
  "type": "Feature",
  "properties": {
    "addr:full":"7 E St SE Quincy WA 98848",
    "addr:housenumber":"7",
    "addr:postcode":"98848",
    "addr:street":"E St Se",
    "iso:country":"US",
    "sg:address":"7 E St SE",
    "sg:city":"Quincy",
    "sg:classifiers":[
        {
            "category":"Personal",
            "subcategory":"Beauty Salon",
            "type":"Services"
        }
    ],
    "sg:phone":"+1 509 787 7209",
    "sg:postcode":"98848",
    "sg:province":"WA",
    "sg:tags":[
        "shop"
    ],
    "wof:name":"Courtyard Salon & Barber",
    "wof:placetype":"venue"
},
  "geometry": {"coordinates":[-119.853281,47.234023],"type":"Point"}
}