{
  "type": "Feature",
  "properties": {
    "addr:full":"17425 NE Union Hill Rd Redmond WA 98052",
    "addr:housenumber":"17425",
    "addr:postcode":"98052",
    "addr:street":"Ne Union Hill Rd",
    "iso:country":"US",
    "sg:address":"17425 NE Union Hill Rd",
    "sg:city":"Redmond",
    "sg:classifiers":[
        {
            "category":"Banks & Credit Unions",
            "subcategory":"Financial Services",
            "type":"Services"
        }
    ],
    "sg:phone":"+1 425 869 6160",
    "sg:postcode":"98052",
    "sg:province":"WA",
    "sg:tags":[
        "card-merchant"
    ],
    "sg:website":"http://www.americanexpress.com",
    "wof:name":"American Express",
    "wof:placetype":"venue"
},
  "geometry": {"coordinates":[-122.107574,47.674805],"type":"Point"}
}