{
  "type": "Feature",
  "properties": {
    "addr:full":"3216 NE 45th Pl Ste 213 Seattle WA 98105",
    "addr:housenumber":"3216",
    "addr:postcode":"98105",
    "addr:street":"Ne 45Th Pl Ste 213",
    "iso:country":"US",
    "sg:address":"3216 NE 45th Pl Ste 213",
    "sg:city":"Seattle",
    "sg:classifiers":[
        {
            "category":"Health Services",
            "subcategory":"Doctor",
            "type":"Services"
        },
        {
            "category":"Health Services",
            "subcategory":"Dentist",
            "type":"Services"
        }
    ],
    "sg:phone":"+1 206 701 6545",
    "sg:postcode":"98105",
    "sg:province":"WA",
    "sg:tags":[
        "physician",
        "product",
        "dentists-cosmetic",
        "denture",
        "dentists-prosthodontists",
        "teeth",
        "surgeons",
        "dentists-periodontists",
        "dentists-endodontists",
        "dentists-pediatric",
        "dentistry",
        "whitening",
        "surgery",
        "oral",
        "dentists-orthodontists"
    ],
    "sg:website":"http://seattle.citysearch.com/profile/external/46298188/seattle_wa/union_bay_dental_care_dr_brady_l_frank_dds.html?publisher=yellowpages&reference_id=1&placement=ypwebsitemip",
    "wof:name":"Union Bay Dental Care - Dr. Brady L. Frank DDS",
    "wof:placetype":"venue"
},
  "geometry": {"coordinates":[-122.292627,47.661331],"type":"Point"}
}