{
  "type": "Feature",
  "properties": {
    "addr:full":"20611 Bothell Everett Hwy Bothell WA 98012",
    "addr:housenumber":"20611",
    "addr:postcode":"98012",
    "addr:street":"Bothell Everett Hwy",
    "iso:country":"US",
    "sg:address":"20611 Bothell Everett Hwy",
    "sg:city":"Bothell",
    "sg:classifiers":[
        {
            "category":"Banks & Credit Unions",
            "subcategory":"Bank",
            "type":"Services"
        }
    ],
    "sg:phone":"+1 425 379 9797",
    "sg:postcode":"98012",
    "sg:province":"WA",
    "sg:tags":[
        "loan",
        "real estate"
    ],
    "wof:name":"Financial Edge Mortgage",
    "wof:placetype":"venue"
},
  "geometry": {"coordinates":[-122.207532,47.810794],"type":"Point"}
}