{
  "type": "Feature",
  "properties": {
    "addr:full":"308 NW 189th St Shoreline WA 98177",
    "addr:housenumber":"308",
    "addr:postcode":"98177",
    "addr:street":"Nw 189Th St",
    "iso:country":"US",
    "sg:address":"308 NW 189th St",
    "sg:city":"Shoreline",
    "sg:classifiers":[
        {
            "category":"Shopping",
            "subcategory":"Crafts & Fabrics",
            "type":"Retail Goods"
        }
    ],
    "sg:phone":"+1 206 542 8811",
    "sg:postcode":"98177",
    "sg:province":"WA",
    "sg:tags":[
        "shop"
    ],
    "wof:name":"Sew What",
    "wof:placetype":"venue"
},
  "geometry": {"coordinates":[-122.361395,47.766529],"type":"Point"}
}