{
  "type": "Feature",
  "properties": {
    "addr:full":"14320 NE 21st St Ste 15 Bellevue WA 98007",
    "addr:housenumber":"14320",
    "addr:postcode":"98007",
    "addr:street":"Ne 21St St Ste 15",
    "iso:country":"US",
    "sg:address":"14320 NE 21st St Ste 15",
    "sg:city":"Bellevue",
    "sg:classifiers":[
        {
            "category":"Autos & Motor Vehicles",
            "subcategory":"Boat Sales",
            "type":"Retail Goods"
        }
    ],
    "sg:phone":"+1 425 957 3575",
    "sg:postcode":"98007",
    "sg:province":"WA",
    "sg:tags":[
        "distributor",
        "manufacturer"
    ],
    "sg:website":"http://www.snapdragondesign.com",
    "wof:name":"Snap Dragon Design Inc",
    "wof:placetype":"venue"
},
  "geometry": {"coordinates":[-122.14885099999999,47.628662],"type":"Point"}
}