{
  "type": "Feature",
  "properties": {
    "addr:full":"3037 Wilderness Loop SE Olympia WA 98501",
    "addr:housenumber":"3037",
    "addr:postcode":"98501",
    "addr:street":"Wilderness Loop Se",
    "iso:country":"US",
    "sg:address":"3037 Wilderness Loop SE",
    "sg:city":"Olympia",
    "sg:classifiers":[
        {
            "category":"Personal",
            "type":"Services"
        },
        {
            "category":"Professional",
            "subcategory":"Art Services",
            "type":"Services"
        }
    ],
    "sg:phone":"+1 360 352 0326",
    "sg:postcode":"98501",
    "sg:province":"WA",
    "sg:tags":[
        "photography",
        "videography",
        "wedding"
    ],
    "wof:name":"Photos By Amy",
    "wof:placetype":"venue"
},
  "geometry": {"coordinates":[-122.85624799999999,47.006237],"type":"Point"}
}