{
  "type": "Feature",
  "properties": {
    "addr:full":"1511 Summitview Ave Yakima WA 98902",
    "addr:housenumber":"1511",
    "addr:postcode":"98902",
    "addr:street":"Summitview Ave",
    "iso:country":"US",
    "sg:address":"1511 Summitview Ave",
    "sg:city":"Yakima",
    "sg:classifiers":[
        {
            "category":"Shopping",
            "subcategory":"Shoes",
            "type":"Retail Goods"
        }
    ],
    "sg:phone":"+1 509 453 4209",
    "sg:postcode":"98902",
    "sg:province":"WA",
    "wof:name":"Casa De Mode",
    "wof:placetype":"venue"
},
  "geometry": {"coordinates":[-120.53026800000001,46.599865],"type":"Point"}
}