{
  "type": "Feature",
  "properties": {
    "addr:full":"21901 W Hwy 124 Burbank WA 99323",
    "addr:housenumber":"21901",
    "addr:postcode":"99323",
    "addr:street":"W Hwy 124",
    "iso:country":"US",
    "sg:address":"21901 W Hwy 124",
    "sg:city":"Burbank",
    "sg:classifiers":[
        {
            "category":"Farming",
            "subcategory":"Farm",
            "type":"Manufacturing & Wholesale Goods"
        }
    ],
    "sg:phone":"+1 509 544 0753",
    "sg:postcode":"99323",
    "sg:province":"WA",
    "wof:name":"Hatch Farms Inc",
    "wof:placetype":"venue"
},
  "geometry": {"coordinates":[-118.89883399999999,46.215102],"type":"Point"}
}