{
  "type": "Feature",
  "properties": {
    "addr:full":"2908 228th Ave SE Ste C Sammamish WA 98075",
    "addr:housenumber":"2908",
    "addr:postcode":"98075",
    "addr:street":"228Th Ave Se Ste C",
    "iso:country":"US",
    "sg:address":"2908 228th Ave SE Ste C",
    "sg:city":"Sammamish",
    "sg:classifiers":[
        {
            "category":"Health Services",
            "subcategory":"Chiropractor",
            "type":"Services"
        }
    ],
    "sg:phone":"+1 425 391 4095",
    "sg:postcode":"98075",
    "sg:province":"WA",
    "sg:tags":[
        "chiropractic"
    ],
    "sg:website":"http://www.pinelakechiropractic.com",
    "wof:name":"Bahm, David E Inc Ps",
    "wof:placetype":"venue"
},
  "geometry": {"coordinates":[-122.03552500000001,47.584003],"type":"Point"}
}