{
  "type": "Feature",
  "properties": {
    "addr:full":"4750 N Division St Spokane WA 99207",
    "addr:housenumber":"4750",
    "addr:postcode":"99207",
    "addr:street":"N Division St",
    "iso:country":"US",
    "sg:address":"4750 N Division St",
    "sg:city":"Spokane",
    "sg:classifiers":[
        {
            "category":"Home & Garden",
            "subcategory":"Home Furnishings",
            "type":"Retail Goods"
        }
    ],
    "sg:phone":"+1 509 484 8373",
    "sg:postcode":"99207",
    "sg:province":"WA",
    "sg:tags":[
        "housewares"
    ],
    "wof:name":"Housewares Unlimited",
    "wof:placetype":"venue"
},
  "geometry": {"coordinates":[-117.41114,47.702045],"type":"Point"}
}