{
  "type": "Feature",
  "properties": {
    "addr:full":"109 Tillie Rd Onalaska WA 98570",
    "addr:housenumber":"109",
    "addr:postcode":"98570",
    "addr:street":"Tillie Rd",
    "iso:country":"US",
    "sg:address":"109 Tillie Rd",
    "sg:city":"Onalaska",
    "sg:classifiers":[
        {
            "category":"Retail",
            "subcategory":"Auto Rental",
            "type":"Services"
        }
    ],
    "sg:phone":"+1 360 269 4600",
    "sg:postcode":"98570",
    "sg:province":"WA",
    "sg:tags":[
        "truck"
    ],
    "wof:name":"Tma Rentals LLC",
    "wof:placetype":"venue"
},
  "geometry": {"coordinates":[-122.615425,46.593651],"type":"Point"}
}