{
  "type": "Feature",
  "properties": {
    "addr:full":"18420 36th Ave W Lynnwood WA 98037",
    "addr:housenumber":"18420",
    "addr:postcode":"98037",
    "addr:street":"36Th Ave W",
    "iso:country":"US",
    "sg:address":"18420 36th Ave W",
    "sg:city":"Lynnwood",
    "sg:classifiers":[
        {
            "category":"Social Services",
            "subcategory":"Adult Care",
            "type":"Services"
        },
        {
            "category":"Real Estate",
            "subcategory":"Real Estate Operator",
            "type":"Services"
        }
    ],
    "sg:phone":"+1 425 672 6749",
    "sg:postcode":"98037",
    "sg:province":"WA",
    "sg:tags":[
        "residential",
        "apartment"
    ],
    "wof:name":"Alderwood Court Apartments",
    "wof:placetype":"venue"
},
  "geometry": {"coordinates":[-122.28184,47.831503],"type":"Point"}
}