{
  "type": "Feature",
  "properties": {
    "addr:full":"10852 Forest Ln NE Bainbridge Isle WA 98110",
    "addr:housenumber":"10852",
    "addr:postcode":"98110",
    "addr:street":"Forest Ln Ne;Isle",
    "iso:country":"US",
    "sg:address":"10852 Forest Ln NE",
    "sg:city":"Bainbridge Isle",
    "sg:classifiers":[
        {
            "category":"Building & Trades",
            "subcategory":"Electrical",
            "type":"Services"
        }
    ],
    "sg:phone":"+1 206 842 2473",
    "sg:postcode":"98110",
    "sg:province":"WA",
    "sg:tags":[
        "electric",
        "contractor"
    ],
    "wof:name":"C W Electric Co",
    "wof:placetype":"venue"
},
  "geometry": {"coordinates":[-122.539889,47.662323],"type":"Point"}
}