{
  "type": "Feature",
  "properties": {
    "addr:full":"20418 Revilo Dr Burlington WA 98233",
    "addr:postcode":"20418;98233",
    "addr:street":"Revilo Dr",
    "iso:country":"US",
    "sg:address":"20418 Revilo Dr",
    "sg:city":"Burlington",
    "sg:classifiers":[
        {
            "category":"Building & Trades",
            "subcategory":"Plumbing",
            "type":"Services"
        }
    ],
    "sg:phone":"+1 360 755 1555",
    "sg:postcode":"98233",
    "sg:province":"WA",
    "sg:tags":[
        "air",
        "heating",
        "refrigeration",
        "conditioning",
        "contractor"
    ],
    "wof:name":"D K Systems Inc",
    "wof:placetype":"venue"
},
  "geometry": {"coordinates":[-122.305227,48.486832],"type":"Point"}
}