{
  "type": "Feature",
  "properties": {
    "addr:full":"38818 302nd Ave SE Enumclaw WA 98022",
    "addr:housenumber":"38818",
    "addr:postcode":"98022",
    "addr:street":"302Nd Ave Se",
    "iso:country":"US",
    "sg:address":"38818 302nd Ave SE",
    "sg:city":"Enumclaw",
    "sg:classifiers":[
        {
            "category":"Personal",
            "subcategory":"Beauty Salon",
            "type":"Services"
        }
    ],
    "sg:phone":"+1 360 825 1914",
    "sg:postcode":"98022",
    "sg:province":"WA",
    "sg:tags":[
        "hair",
        "stylist"
    ],
    "wof:name":"A Day At The Spa Inc",
    "wof:placetype":"venue"
},
  "geometry": {"coordinates":[-121.93897699999999,47.252163],"type":"Point"}
}