{
  "type": "Feature",
  "properties": {
    "addr:full":"2209 304th St S Roy WA 98580",
    "addr:housenumber":"2209",
    "addr:postcode":"98580",
    "addr:street":"304Th St S",
    "iso:country":"US",
    "sg:address":"2209 304th St S",
    "sg:city":"Roy",
    "sg:classifiers":[
        {
            "category":"Retail",
            "subcategory":"Animal Services",
            "type":"Services"
        }
    ],
    "sg:phone":"+1 253 843 1800",
    "sg:postcode":"98580",
    "sg:province":"WA",
    "wof:name":"Penny Creek Farms",
    "wof:placetype":"venue"
},
  "geometry": {"coordinates":[-122.461535,46.981243],"type":"Point"}
}