{
  "type": "Feature",
  "properties": {
    "addr:full":"1818 W Francis Ave Spokane WA 99205",
    "addr:housenumber":"1818",
    "addr:postcode":"99205",
    "addr:street":"W Francis Ave",
    "iso:country":"US",
    "sg:address":"1818 W Francis Ave",
    "sg:city":"Spokane",
    "sg:classifiers":[
        {
            "category":"Building & Trades",
            "subcategory":"Construction",
            "type":"Services"
        }
    ],
    "sg:phone":"+1 509 326 3931",
    "sg:postcode":"99205",
    "sg:province":"WA",
    "sg:tags":[
        "house"
    ],
    "wof:name":"R V Craig Construction",
    "wof:placetype":"venue"
},
  "geometry": {"coordinates":[-117.438812,47.715519],"type":"Point"}
}