{
  "type": "Feature",
  "properties": {
    "iso:country":"US",
    "sg:address":"520 N Rock St",
    "sg:city":"Centralia",
    "sg:classifiers":[
        {
            "category":"Education",
            "subcategory":"Vocational School",
            "type":"Public Place"
        }
    ],
    "sg:phone":"+1 360 736 0259",
    "sg:postcode":"98531",
    "sg:province":"WA",
    "sg:tags":[
        "processing",
        "datum"
    ],
    "wof:name":"Computer Distress Control",
    "wof:placetype":"venue"
},
  "geometry": {"coordinates":[-122.957077,46.721007],"type":"Point"}
}