{
  "type": "Feature",
  "properties": {
    "addr:full":"183 Peele Rd Port Angeles WA 98363",
    "addr:housenumber":"183",
    "addr:postcode":"98363",
    "addr:street":"Peele Rd",
    "iso:country":"US",
    "sg:address":"183 Peele Rd",
    "sg:city":"Port Angeles",
    "sg:classifiers":[
        {
            "category":"Museum",
            "type":"Entertainment"
        }
    ],
    "sg:phone":"+1 360 457 9290",
    "sg:postcode":"98363",
    "sg:province":"WA",
    "sg:tags":[
        "organization",
        "arts",
        "information"
    ],
    "wof:name":"Arts Northwest",
    "wof:placetype":"venue"
},
  "geometry": {"coordinates":[-123.468329,48.087188],"type":"Point"}
}