{
  "type": "Feature",
  "properties": {
    "addr:full":"470 Spring St Friday Harbor WA 98250",
    "addr:housenumber":"470",
    "addr:postcode":"98250",
    "addr:street":"Spring St",
    "iso:country":"US",
    "sg:address":"470 Spring St",
    "sg:city":"Friday Harbor",
    "sg:classifiers":[
        {
            "category":"Recreation",
            "type":"Entertainment"
        }
    ],
    "sg:phone":"+1 360 378 6131",
    "sg:postcode":"98250",
    "sg:province":"WA",
    "sg:tags":[
        "boating",
        "instruction"
    ],
    "sg:website":"www.mahina.com",
    "wof:name":"Mahina Expeditions",
    "wof:placetype":"venue"
},
  "geometry": {"coordinates":[-123.01961300000001,48.532529],"type":"Point"}
}