{
  "type": "Feature",
  "properties": {
    "iso:country":"US",
    "sg:address":"6306 NW Bernie Dr",
    "sg:city":"Vancouver",
    "sg:classifiers":[
        {
            "category":"Professional",
            "subcategory":"Management & Consulting",
            "type":"Services"
        }
    ],
    "sg:phone":"+1 360 993 2610",
    "sg:postcode":"98663",
    "sg:province":"WA",
    "sg:tags":[
        "business"
    ],
    "wof:name":"Power System Consulting Servic",
    "wof:placetype":"venue"
},
  "geometry": {"coordinates":[-122.681727,45.668365],"type":"Point"}
}