{
  "type": "Feature",
  "properties": {
    "addr:full":"Hyatt Regency Bellevue 900 Bellevue Way NE Bellevue WA 98004",
    "addr:housenumber":"900",
    "addr:postcode":"98004",
    "addr:street":"Bellevue Way Ne",
    "iso:country":"US",
    "sg:address":"Hyatt Regency Bellevue 900 Bellevue Way NE",
    "sg:city":"Bellevue",
    "sg:classifiers":[
        {
            "category":"Education",
            "subcategory":"Special Training",
            "type":"Public Place"
        }
    ],
    "sg:phone":"+1 800 576 4628",
    "sg:postcode":"98004",
    "sg:province":"WA",
    "sg:tags":[
        "tutoring"
    ],
    "sg:website":"www.manhattangmat.com/gmat-prep-...",
    "wof:name":"Manhattan GMAT Prep LLC",
    "wof:placetype":"venue"
},
  "geometry": {"coordinates":[-122.20169,47.617984],"type":"Point"}
}