{
  "type": "Feature",
  "properties": {
    "addr:full":"1926 Pike Pl Seattle WA 98101",
    "addr:housenumber":"1926",
    "addr:postcode":"98101",
    "addr:street":"Pike Pl",
    "iso:country":"US",
    "sg:address":"1926 Pike Pl",
    "sg:city":"Seattle",
    "sg:classifiers":[
        {
            "category":"Deli",
            "type":"Food & Drink"
        },
        {
            "category":"Food & Beverages",
            "subcategory":"Specialty",
            "type":"Retail Goods"
        },
        {
            "category":"Food & Beverages",
            "subcategory":"Groceries & Convenience Stores",
            "type":"Retail Goods"
        }
    ],
    "sg:phone":"+1 206 443 1926",
    "sg:postcode":"98101",
    "sg:province":"WA",
    "wof:name":"Pike Place Grocery & Deli",
    "wof:placetype":"venue"
},
  "geometry": {"coordinates":[-122.342935,47.610205],"type":"Point"}
}