{
  "type": "Feature",
  "properties": {
    "addr:full":"800 E Union St Seattle WA 98122",
    "addr:housenumber":"800",
    "addr:postcode":"98122",
    "addr:street":"E Union St",
    "iso:country":"US",
    "sg:address":"800 E Union St",
    "sg:city":"Seattle",
    "sg:classifiers":[
        {
            "category":"Restaurant",
            "type":"Food & Drink"
        }
    ],
    "sg:phone":"+1 206 625 0102",
    "sg:postcode":"98122",
    "sg:province":"WA",
    "sg:tags":[
        "pizza"
    ],
    "wof:name":"Unconventional Pizza",
    "wof:placetype":"venue"
},
  "geometry": {"coordinates":[-122.32199900000001,47.6129],"type":"Point"}
}