{
  "type": "Feature",
  "properties": {
    "addr:full":"5011 S Thorp Hwy Ellensburg WA 98926",
    "addr:housenumber":"5011",
    "addr:postcode":"98926",
    "addr:street":"S Thorp Hwy",
    "iso:country":"US",
    "sg:address":"5011 S Thorp Hwy",
    "sg:city":"Ellensburg",
    "sg:classifiers":[
        {
            "category":"Farming",
            "subcategory":"Farm",
            "type":"Manufacturing & Wholesale Goods"
        }
    ],
    "sg:phone":"+1 509 962 6401",
    "sg:postcode":"98926",
    "sg:province":"WA",
    "sg:tags":[
        "crop",
        "general"
    ],
    "wof:name":"Grousemont Farm",
    "wof:placetype":"venue"
},
  "geometry": {"coordinates":[-120.642999,47.027328],"type":"Point"}
}