{
  "type": "Feature",
  "properties": {
    "addr:full":"2604 Nome St Bellingham WA 98225",
    "addr:housenumber":"2604",
    "addr:postcode":"98225",
    "addr:street":"Nome St",
    "iso:country":"US",
    "sg:address":"2604 Nome St",
    "sg:city":"Bellingham",
    "sg:classifiers":[
        {
            "category":"Manufacturing",
            "subcategory":"Retail Goods",
            "type":"Manufacturing & Wholesale Goods"
        }
    ],
    "sg:phone":"+1 360 714 1722",
    "sg:postcode":"98225",
    "sg:province":"WA",
    "sg:tags":[
        "product",
        "mfg"
    ],
    "wof:name":"Patricia Jean Gatley",
    "wof:placetype":"venue"
},
  "geometry": {"coordinates":[-122.50789899999999,48.765632],"type":"Point"}
}