{
  "type": "Feature",
  "properties": {
    "iso:country":"US",
    "sg:address":"8080 Harborview Rd",
    "sg:city":"Blaine",
    "sg:classifiers":[
        {
            "category":"Travel",
            "subcategory":"Campground",
            "type":"Entertainment"
        }
    ],
    "sg:phone":"+1 360 371 7922",
    "sg:postcode":"98230",
    "sg:province":"WA",
    "sg:tags":[
        "park",
        "trailer"
    ],
    "wof:name":"Birch Bay Resort Park Ltd",
    "wof:placetype":"venue"
},
  "geometry": {"coordinates":[-122.74824599999999,48.934237],"type":"Point"}
}