{
  "type": "Feature",
  "properties": {
    "addr:full":"287 Monahan Rd Castle Rock WA 98611",
    "addr:housenumber":"287",
    "addr:postcode":"98611",
    "addr:street":"Monahan Rd",
    "iso:country":"US",
    "sg:address":"287 Monahan Rd",
    "sg:city":"Castle Rock",
    "sg:classifiers":[
        {
            "category":"Professional",
            "subcategory":"Employment Agencies",
            "type":"Services"
        }
    ],
    "sg:phone":"+1 360 274 4727",
    "sg:postcode":"98611",
    "sg:province":"WA",
    "sg:tags":[
        "logging",
        "help",
        "supply"
    ],
    "wof:name":"Richard Alan Phipps",
    "wof:placetype":"venue"
},
  "geometry": {"coordinates":[-122.980873,46.265127],"type":"Point"}
}