{
  "type": "Feature",
  "properties": {
    "addr:full":"233 N Chelan Ave Wenatchee WA 98801",
    "addr:housenumber":"233",
    "addr:postcode":"98801",
    "addr:street":"N Chelan Ave",
    "iso:country":"US",
    "sg:address":"233 N Chelan Ave",
    "sg:city":"Wenatchee",
    "sg:classifiers":[
        {
            "category":"Professional",
            "type":"Services"
        }
    ],
    "sg:phone":"+1 509 664 3605",
    "sg:postcode":"98801",
    "sg:province":"WA",
    "sg:tags":[
        "establishment"
    ],
    "wof:name":"Workforce Development Council",
    "wof:placetype":"venue"
},
  "geometry": {"coordinates":[-120.31629700000001,47.426863],"type":"Point"}
}