{
  "type": "Feature",
  "properties": {
    "addr:full":"7216 Oat Coles Rd Everson WA 98247",
    "addr:housenumber":"7216",
    "addr:postcode":"98247",
    "addr:street":"Oat Coles Rd",
    "iso:country":"US",
    "sg:address":"7216 Oat Coles Rd",
    "sg:city":"Everson",
    "sg:classifiers":[
        {
            "category":"Building & Trades",
            "subcategory":"Landscaping Services",
            "type":"Services"
        }
    ],
    "sg:phone":"+1 360 739 7740",
    "sg:postcode":"98247",
    "sg:province":"WA",
    "sg:tags":[
        "landscape"
    ],
    "wof:name":"Mount Baker Landscaping",
    "wof:placetype":"venue"
},
  "geometry": {"coordinates":[-122.30393599999999,48.898339],"type":"Point"}
}