{
  "type": "Feature",
  "properties": {
    "addr:full":"20012 166th Ave NE Woodinville WA 98072",
    "addr:housenumber":"20012",
    "addr:postcode":"98072",
    "addr:street":"166Th Ave Ne",
    "iso:country":"US",
    "sg:address":"20012 166th Ave NE",
    "sg:city":"Woodinville",
    "sg:classifiers":[
        {
            "category":"Building & Trades",
            "subcategory":"Construction",
            "type":"Services"
        }
    ],
    "sg:phone":"+1 425 424 1242",
    "sg:postcode":"98072",
    "sg:province":"WA",
    "sg:tags":[
        "general",
        "contractor"
    ],
    "wof:name":"Beta Builders",
    "wof:placetype":"venue"
},
  "geometry": {"coordinates":[-122.11826600000001,47.771779],"type":"Point"}
}