{
  "type": "Feature",
  "properties": {
    "iso:country":"US",
    "sg:address":"10125 SE 200th St",
    "sg:city":"Kent",
    "sg:classifiers":[
        {
            "category":"Banks & Credit Unions",
            "subcategory":"Bank",
            "type":"Services"
        }
    ],
    "sg:phone":"+1 253 813 5899",
    "sg:postcode":"98031",
    "sg:province":"WA",
    "sg:tags":[
        "mortgage"
    ],
    "wof:name":"Kiel Mortgage Inc",
    "wof:placetype":"venue"
},
  "geometry": {"coordinates":[-122.204791,47.423054],"type":"Point"}
}