{
  "type": "Feature",
  "properties": {
    "addr:full":"4703 N Maple St Spokane WA 99205",
    "addr:housenumber":"4703",
    "addr:postcode":"99205",
    "addr:street":"N Maple St",
    "iso:country":"US",
    "sg:address":"4703 N Maple St",
    "sg:city":"Spokane",
    "sg:classifiers":[
        {
            "category":"Professional",
            "subcategory":"Accounting & Tax Preparation",
            "type":"Services"
        }
    ],
    "sg:phone":"+1 509 325 3205",
    "sg:postcode":"99205",
    "sg:province":"WA",
    "sg:tags":[
        "transmission",
        "return"
    ],
    "wof:name":"H & R Block Tax Svc",
    "wof:placetype":"venue"
},
  "geometry": {"coordinates":[-117.435151,47.702555],"type":"Point"}
}