{
  "type": "Feature",
  "properties": {
    "addr:full":"5707 S Augusta St Seattle WA 98178",
    "addr:housenumber":"5707",
    "addr:postcode":"98178",
    "addr:street":"S Augusta St",
    "iso:country":"US",
    "sg:address":"5707 S Augusta St",
    "sg:city":"Seattle",
    "sg:classifiers":[
        {
            "category":"Health Services",
            "subcategory":"Clinic",
            "type":"Services"
        }
    ],
    "sg:phone":"+1 206 722 5100",
    "sg:postcode":"98178",
    "sg:province":"WA",
    "sg:tags":[
        "home",
        "care"
    ],
    "wof:name":"Premier Home Care Agency",
    "wof:placetype":"venue"
},
  "geometry": {"coordinates":[-122.259573,47.500078],"type":"Point"}
}