{
  "type": "Feature",
  "properties": {
    "addr:full":"851 Stevenson Ave Enumclaw WA 98022",
    "addr:housenumber":"851",
    "addr:postcode":"98022",
    "addr:street":"Stevenson Ave",
    "iso:country":"US",
    "sg:address":"851 Stevenson Ave",
    "sg:city":"Enumclaw",
    "sg:classifiers":[
        {
            "category":"Personal",
            "subcategory":"Beauty Salon",
            "type":"Services"
        }
    ],
    "sg:phone":"+1 360 802 6483",
    "sg:postcode":"98022",
    "sg:province":"WA",
    "sg:tags":[
        "shop"
    ],
    "wof:name":"Serendipity Hair Designs",
    "wof:placetype":"venue"
},
  "geometry": {"coordinates":[-121.98785100000001,47.200732],"type":"Point"}
}