{
  "type": "Feature",
  "properties": {
    "addr:full":"5958 Mountain View Ln Freeland WA 98249",
    "addr:housenumber":"5958",
    "addr:postcode":"98249",
    "addr:street":"Mountain View Ln",
    "iso:country":"US",
    "sg:address":"5958 Mountain View Ln",
    "sg:city":"Freeland",
    "sg:classifiers":[
        {
            "category":"Personal",
            "subcategory":"Beauty Salon",
            "type":"Services"
        }
    ],
    "sg:phone":"+1 360 331 5381",
    "sg:postcode":"98249",
    "sg:province":"WA",
    "sg:tags":[
        "shop"
    ],
    "wof:name":"Color Box Salon",
    "wof:placetype":"venue"
},
  "geometry": {"coordinates":[-122.534937,47.995131],"type":"Point"}
}