{
  "type": "Feature",
  "properties": {
    "addr:full":"100 Elliott Ave W Seattle WA 98119",
    "addr:housenumber":"100",
    "addr:postcode":"98119",
    "addr:street":"Elliott Ave W",
    "iso:country":"US",
    "sg:address":"100 Elliott Ave W",
    "sg:city":"Seattle",
    "sg:classifiers":[
        {
            "category":"Manufacturing",
            "subcategory":"Printing",
            "type":"Manufacturing & Wholesale Goods"
        }
    ],
    "sg:phone":"+1 206 285 0146",
    "sg:postcode":"98119",
    "sg:province":"WA",
    "sg:tags":[
        "commercial"
    ],
    "wof:name":"Ligature",
    "wof:placetype":"venue"
},
  "geometry": {"coordinates":[-122.35941,47.619313],"type":"Point"}
}