{
  "type": "Feature",
  "properties": {
    "addr:full":"10566 Raintree Pl SE Port Orchard WA 98367",
    "addr:housenumber":"10566",
    "addr:postcode":"98367",
    "addr:street":"Raintree Pl Se",
    "iso:country":"US",
    "sg:address":"10566 Raintree Pl SE",
    "sg:city":"Port Orchard",
    "sg:classifiers":[
        {
            "category":"Wholesale",
            "subcategory":"Construction Materials",
            "type":"Manufacturing & Wholesale Goods"
        }
    ],
    "sg:phone":"+1 360 876 8428",
    "sg:postcode":"98367",
    "sg:province":"WA",
    "sg:tags":[
        "retail",
        "cabinet"
    ],
    "wof:name":"Rusticana Cabinets",
    "wof:placetype":"venue"
},
  "geometry": {"coordinates":[-122.612686,47.451105],"type":"Point"}
}