{
  "type": "Feature",
  "properties": {
    "addr:full":"10261 16th Avenue SW Seattle WA 98146",
    "addr:housenumber":"10261",
    "addr:postcode":"98146",
    "addr:street":"16Th Avenue Sw",
    "iso:country":"US",
    "sg:address":"10261 16th Avenue SW",
    "sg:city":"Seattle",
    "sg:classifiers":[
        {
            "category":"Personal",
            "subcategory":"Tattoo Parlor",
            "type":"Services"
        }
    ],
    "sg:phone":"+1 206 763 4051",
    "sg:postcode":"98146",
    "sg:province":"WA",
    "wof:name":"Primary Colors Tattoo & Body Piercing",
    "wof:placetype":"venue"
},
  "geometry": {"coordinates":[-122.354946,47.511114],"type":"Point"}
}