{
  "type": "Feature",
  "properties": {
    "addr:full":"1501 Parker Way Mount Vernon WA 98273",
    "addr:housenumber":"1501",
    "addr:postcode":"98273",
    "addr:street":"Parker Way",
    "iso:country":"US",
    "sg:address":"1501 Parker Way",
    "sg:city":"Mount Vernon",
    "sg:classifiers":[
        {
            "category":"Personal",
            "subcategory":"Beauty Salon",
            "type":"Services"
        }
    ],
    "sg:phone":"+1 360 428 5994",
    "sg:postcode":"98273",
    "sg:province":"WA",
    "sg:tags":[
        "shop"
    ],
    "wof:name":"A Gentle Touch Styling Salon",
    "wof:placetype":"venue"
},
  "geometry": {"coordinates":[-122.321619,48.434802],"type":"Point"}
}