{
  "type": "Feature",
  "properties": {
    "addr:full":"1800 Front St Lynden WA 98264",
    "addr:housenumber":"1800",
    "addr:postcode":"98264",
    "addr:street":"Front St",
    "iso:country":"US",
    "sg:address":"1800 Front St",
    "sg:city":"Lynden",
    "sg:classifiers":[
        {
            "category":"Banks & Credit Unions",
            "subcategory":"Bank",
            "type":"Services"
        }
    ],
    "sg:phone":"+1 360 318 8780",
    "sg:postcode":"98264",
    "sg:province":"WA",
    "sg:tags":[
        "saving",
        "commercial"
    ],
    "sg:website":"http://www.banknorthwest.com",
    "wof:name":"Bank Northwest Inc",
    "wof:placetype":"venue"
},
  "geometry": {"coordinates":[-122.47532699999999,48.939255],"type":"Point"}
}