{
  "type": "Feature",
  "properties": {
    "addr:full":"4710 Center Ln NE Lacey WA 98516",
    "addr:housenumber":"4710",
    "addr:postcode":"98516",
    "addr:street":"Center Ln Ne",
    "iso:country":"US",
    "sg:address":"4710 Center Ln NE",
    "sg:city":"Lacey",
    "sg:classifiers":[
        {
            "category":"Education",
            "subcategory":"School",
            "type":"Public Place"
        }
    ],
    "sg:phone":"+1 360 491 2966",
    "sg:postcode":"98516",
    "sg:province":"WA",
    "sg:website":"www.nchs-olympia.org",
    "wof:name":"Northwest Christian High Schl",
    "wof:placetype":"venue"
},
  "geometry": {"coordinates":[-122.74565800000001,47.100491],"type":"Point"}
}