{
  "type": "Feature",
  "properties": {
    "addr:full":"32714 Webster Rd E Eatonville WA 98328",
    "addr:housenumber":"32714",
    "addr:postcode":"98328",
    "addr:street":"Webster Rd E",
    "iso:country":"US",
    "sg:address":"32714 Webster Rd E",
    "sg:city":"Eatonville",
    "sg:classifiers":[
        {
            "category":"Shopping",
            "subcategory":"Hobbies, Toys, & Games",
            "type":"Retail Goods"
        }
    ],
    "sg:phone":"+1 360 847 3344",
    "sg:postcode":"98328",
    "sg:province":"WA",
    "wof:name":"Simply Relative",
    "wof:placetype":"venue"
},
  "geometry": {"coordinates":[-122.30452200000001,46.959141],"type":"Point"}
}