{
  "type": "Feature",
  "properties": {
    "addr:full":"5300 Roosevelt Way NE Seattle WA 98105",
    "addr:housenumber":"5300",
    "addr:postcode":"98105",
    "addr:street":"Roosevelt Way Ne",
    "iso:country":"US",
    "sg:address":"5300 Roosevelt Way NE",
    "sg:city":"Seattle",
    "sg:classifiers":[
        {
            "category":"Bars & Pubs",
            "subcategory":"Sports Bar",
            "type":"Food & Drink"
        },
        {
            "category":"Restaurant",
            "type":"Food & Drink"
        }
    ],
    "sg:phone":"+1 206 525 1300",
    "sg:postcode":"98105",
    "sg:province":"WA",
    "sg:tags":[
        "polish"
    ],
    "sg:website":"www.dantesseattle.net",
    "wof:name":"Dante's",
    "wof:placetype":"venue"
},
  "geometry": {"coordinates":[-122.317001,47.667198],"type":"Point"}
}