{
  "type": "Feature",
  "properties": {
    "addr:full":"311 80th Pl SW Everett WA 98203",
    "addr:housenumber":"311",
    "addr:postcode":"98203",
    "addr:street":"80Th Pl Sw",
    "iso:country":"US",
    "sg:address":"311 80th Pl SW",
    "sg:city":"Everett",
    "sg:classifiers":[
        {
            "category":"Wholesale",
            "subcategory":"Seafood",
            "type":"Manufacturing & Wholesale Goods"
        }
    ],
    "sg:phone":"+1 425 513 9808",
    "sg:postcode":"98203",
    "sg:province":"WA",
    "wof:name":"Ocean King Seafood",
    "wof:placetype":"venue"
},
  "geometry": {"coordinates":[-122.23692699999999,47.925132],"type":"Point"}
}