{
  "type": "Feature",
  "properties": {
    "iso:country":"US",
    "sg:address":"703 W 7th Ave",
    "sg:city":"Spokane",
    "sg:classifiers":[
        {
            "category":"Health Services",
            "subcategory":"Clinic",
            "type":"Services"
        }
    ],
    "sg:phone":"+1 509 838 5427",
    "sg:postcode":"99204",
    "sg:province":"WA",
    "sg:tags":[
        "hypnotherapy"
    ],
    "sg:website":"www.introspect2000.com",
    "wof:name":"Introspect",
    "wof:placetype":"venue"
},
  "geometry": {"coordinates":[-117.423782,47.649275],"type":"Point"}
}