{
  "type": "Feature",
  "properties": {
    "addr:full":"112 Avenue D Snohomish WA 98290",
    "addr:housenumber":"112",
    "addr:postcode":"98290",
    "addr:street":"Avenue D",
    "iso:country":"US",
    "sg:address":"112 Avenue D",
    "sg:city":"Snohomish",
    "sg:classifiers":[
        {
            "category":"Professional",
            "subcategory":"Art Services",
            "type":"Services"
        },
        {
            "category":"Home & Garden",
            "subcategory":"Carpets & Floor Coverings",
            "type":"Retail Goods"
        }
    ],
    "sg:phone":"+1 360 568 2116",
    "sg:postcode":"98290",
    "sg:province":"WA",
    "sg:tags":[
        "interior",
        "designer",
        "rug",
        "decorator"
    ],
    "sg:website":"http://www.smithinteriors.net",
    "wof:name":"Smith Interiors",
    "wof:placetype":"venue"
},
  "geometry": {"coordinates":[-122.09859899999999,47.911637],"type":"Point"}
}