{
  "type": "Feature",
  "properties": {
    "addr:full":"422 N I St Apt 15 Tacoma WA 98403",
    "addr:housenumber":"422;15",
    "addr:postcode":"98403",
    "addr:street":"N I St Apt",
    "iso:country":"US",
    "sg:address":"422 N I St Apt 15",
    "sg:city":"Tacoma",
    "sg:classifiers":[
        {
            "category":"Building & Trades",
            "subcategory":"Landscaping Services",
            "type":"Services"
        }
    ],
    "sg:phone":"+1 253 709 3230",
    "sg:postcode":"98403",
    "sg:province":"WA",
    "sg:tags":[
        "lawn"
    ],
    "wof:name":"Green Summit Landscape",
    "wof:placetype":"venue"
},
  "geometry": {"coordinates":[-122.454871,47.263297],"type":"Point"}
}