{
  "type": "Feature",
  "properties": {
    "addr:full":"4833 Lone Bear Ln SW Port Orchard WA 98367",
    "addr:housenumber":"4833",
    "addr:postcode":"98367",
    "addr:street":"Lone Bear Ln Sw Port Orchard",
    "iso:country":"US",
    "sg:address":"4833 Lone Bear Ln SW",
    "sg:city":"Port Orchard",
    "sg:classifiers":[
        {
            "category":"Building & Trades",
            "subcategory":"Construction",
            "type":"Services"
        }
    ],
    "sg:phone":"+1 360 782 1610",
    "sg:postcode":"98367",
    "sg:province":"WA",
    "sg:tags":[
        "hanging",
        "contractor"
    ],
    "wof:name":"Stewarts P G Painting & RPS",
    "wof:placetype":"venue"
},
  "geometry": {"coordinates":[-122.713216,47.518199],"type":"Point"}
}