{
  "type": "Feature",
  "properties": {
    "addr:full":"1608 W Boone Ave Spokane WA 99201",
    "addr:housenumber":"1608",
    "addr:postcode":"99201",
    "addr:street":"W Boone Ave",
    "iso:country":"US",
    "sg:address":"1608 W Boone Ave",
    "sg:city":"Spokane",
    "sg:classifiers":[
        {
            "category":"Social Services",
            "type":"Services"
        }
    ],
    "sg:phone":"+1 509 363 5000",
    "sg:postcode":"99201",
    "sg:province":"WA",
    "wof:name":"Child Support",
    "wof:placetype":"venue"
},
  "geometry": {"coordinates":[-117.436903,47.668087],"type":"Point"}
}