{
  "type": "Feature",
  "properties": {
    "iso:country":"US",
    "sg:address":"2415 Evergreen Park Dr SW",
    "sg:city":"Olympia",
    "sg:classifiers":[
        {
            "category":"Professional",
            "subcategory":"Lawyer & Legal Services",
            "type":"Services"
        }
    ],
    "sg:phone":"+1 360 754 0197",
    "sg:postcode":"98502",
    "sg:province":"WA",
    "sg:tags":[
        "attorney"
    ],
    "wof:name":"Donna Lynn Holt",
    "wof:placetype":"venue"
},
  "geometry": {"coordinates":[-122.915319,47.027611],"type":"Point"}
}