{
  "type": "Feature",
  "properties": {
    "addr:full":"2914 6th Ave Tacoma WA 98406",
    "addr:housenumber":"2914",
    "addr:postcode":"98406",
    "addr:street":"6Th Ave",
    "iso:country":"US",
    "sg:address":"2914 6th Ave",
    "sg:city":"Tacoma",
    "sg:classifiers":[
        {
            "category":"Shopping",
            "subcategory":"Department Store",
            "type":"Retail Goods"
        }
    ],
    "sg:phone":"+1 253 572 2774",
    "sg:postcode":"98406",
    "sg:province":"WA",
    "sg:tags":[
        "variety"
    ],
    "sg:website":"http://www.liquidationoutlet.com",
    "wof:name":"Dollar Store",
    "wof:placetype":"venue"
},
  "geometry": {"coordinates":[-122.47389099999999,47.255334],"type":"Point"}
}