{
  "type": "Feature",
  "properties": {
    "addr:full":"15127 Main St E Sumner WA 98390",
    "addr:housenumber":"15127",
    "addr:postcode":"98390",
    "addr:street":"Main St E",
    "iso:country":"US",
    "sg:address":"15127 Main St E",
    "sg:city":"Sumner",
    "sg:classifiers":[
        {
            "category":"Fast Food",
            "type":"Food & Drink"
        },
        {
            "category":"Restaurant",
            "type":"Food & Drink"
        }
    ],
    "sg:phone":"+1 253 891 0209",
    "sg:postcode":"98390",
    "sg:province":"WA",
    "sg:tags":[
        "mexican",
        "take"
    ],
    "sg:website":"http://www.tacodelmar.com/",
    "wof:name":"Taco del Mar",
    "wof:placetype":"venue"
},
  "geometry": {"coordinates":[-122.227737,47.20266],"type":"Point"}
}