{
  "type": "Feature",
  "properties": {
    "addr:full":"3512 E 62nd Ave Spokane WA 99223",
    "addr:housenumber":"3512",
    "addr:postcode":"99223",
    "addr:street":"E 62Nd Ave",
    "iso:country":"US",
    "sg:address":"3512 E 62nd Ave",
    "sg:city":"Spokane",
    "sg:classifiers":[
        {
            "category":"Professional",
            "subcategory":"Lawyer & Legal Services",
            "type":"Services"
        }
    ],
    "sg:phone":"+1 509 448 5762",
    "sg:postcode":"99223",
    "sg:province":"WA",
    "wof:name":"Medical Legal Consulting",
    "wof:placetype":"venue"
},
  "geometry": {"coordinates":[-117.361062,47.598113],"type":"Point"}
}