{
  "type": "Feature",
  "properties": {
    "addr:full":"11045 NE 8th St Bellevue WA 98004",
    "addr:housenumber":"11045",
    "addr:postcode":"98004",
    "addr:street":"Ne 8Th St",
    "iso:country":"US",
    "sg:address":"11045 NE 8th St",
    "sg:city":"Bellevue",
    "sg:classifiers":[
        {
            "category":"Professional",
            "subcategory":"Business Services",
            "type":"Services"
        }
    ],
    "sg:phone":"+1 425 454 4900",
    "sg:postcode":"98004",
    "sg:province":"WA",
    "sg:tags":[
        "auctioneer"
    ],
    "wof:name":"Bidadoo Auctions",
    "wof:placetype":"venue"
},
  "geometry": {"coordinates":[-122.191107,47.617274],"type":"Point"}
}