{
  "type": "Feature",
  "properties": {
    "addr:full":"139 W 30th St Vancouver WA 98660",
    "addr:housenumber":"139",
    "addr:postcode":"98660",
    "addr:street":"W 30Th St",
    "iso:country":"US",
    "sg:address":"139 W 30th St",
    "sg:city":"Vancouver",
    "sg:classifiers":[
        {
            "category":"Banks & Credit Unions",
            "subcategory":"Bank",
            "type":"Services"
        }
    ],
    "sg:phone":"+1 360 921 4876",
    "sg:postcode":"98660",
    "sg:province":"WA",
    "sg:tags":[
        "mortgage"
    ],
    "wof:name":"Pierce Mortgage LLC",
    "wof:placetype":"venue"
},
  "geometry": {"coordinates":[-122.671682,45.643124],"type":"Point"}
}