{
  "type": "Feature",
  "properties": {
    "iso:country":"US",
    "sg:address":"2755 SE Salmonberry Rd",
    "sg:city":"Port Orchard",
    "sg:classifiers":[
        {
            "category":"Retail",
            "subcategory":"Portrait Studio",
            "type":"Services"
        }
    ],
    "sg:phone":"+1 360 876 1108",
    "sg:postcode":"98366",
    "sg:province":"WA",
    "sg:tags":[
        "photographer"
    ],
    "wof:name":"Isabella's Image Wedding Phtgr",
    "wof:placetype":"venue"
},
  "geometry": {"coordinates":[-122.61539,47.512177],"type":"Point"}
}