{
  "type": "Feature",
  "properties": {
    "addr:full":"13712 51st Dr SE Everett WA 98208",
    "addr:housenumber":"13712",
    "addr:postcode":"98208",
    "addr:street":"51St Dr Se",
    "iso:country":"US",
    "sg:address":"13712 51st Dr SE",
    "sg:city":"Everett",
    "sg:classifiers":[
        {
            "category":"Building & Trades",
            "subcategory":"Construction",
            "type":"Services"
        }
    ],
    "sg:phone":"+1 425 337 5698",
    "sg:postcode":"98208",
    "sg:province":"WA",
    "sg:tags":[
        "house"
    ],
    "wof:name":"David J Miller Construction",
    "wof:placetype":"venue"
},
  "geometry": {"coordinates":[-122.16295700000001,47.872589],"type":"Point"}
}