{
  "type": "Feature",
  "properties": {
    "addr:full":"8 Fairgrounds Rd Pomeroy WA 99347",
    "addr:housenumber":"8",
    "addr:postcode":"99347",
    "addr:street":"Fairgrounds Rd",
    "iso:country":"US",
    "sg:address":"8 Fairgrounds Rd",
    "sg:city":"Pomeroy",
    "sg:classifiers":[
        {
            "category":"Professional",
            "type":"Services"
        }
    ],
    "sg:phone":"+1 509 843 1535",
    "sg:postcode":"99347",
    "sg:province":"WA",
    "sg:tags":[
        "arranged",
        "outfitted",
        "expedition"
    ],
    "sg:website":"http://www.westernlifeoutfitters.com",
    "wof:name":"Western Life Outfitters",
    "wof:placetype":"venue"
},
  "geometry": {"coordinates":[-117.55414,46.471517],"type":"Point"}
}