{
  "type": "Feature",
  "properties": {
    "addr:full":"4209 Wheaton Way Bremerton WA 98310",
    "addr:housenumber":"4209",
    "addr:postcode":"98310",
    "addr:street":"Wheaton Way",
    "iso:country":"US",
    "sg:address":"4209 Wheaton Way",
    "sg:city":"Bremerton",
    "sg:classifiers":[
        {
            "category":"Shopping",
            "type":"Retail Goods"
        }
    ],
    "sg:phone":"+1 360 377 9112",
    "sg:postcode":"98310",
    "sg:province":"WA",
    "sg:tags":[
        "pet",
        "supply"
    ],
    "wof:name":"PETCO",
    "wof:placetype":"venue"
},
  "geometry": {"coordinates":[-122.628918,47.606834],"type":"Point"}
}