{
  "type": "Feature",
  "properties": {
    "addr:full":"15 Windmill Mountain Rd Oroville WA 98844",
    "addr:housenumber":"15",
    "addr:postcode":"98844",
    "addr:street":"Windmill Mountain Rd",
    "iso:country":"US",
    "sg:address":"15 Windmill Mountain Rd",
    "sg:city":"Oroville",
    "sg:classifiers":[
        {
            "category":"Professional",
            "type":"Services"
        }
    ],
    "sg:phone":"+1 509 476 2598",
    "sg:postcode":"98844",
    "sg:province":"WA",
    "wof:name":"Merrill Corp",
    "wof:placetype":"venue"
},
  "geometry": {"coordinates":[-119.513812,48.862473],"type":"Point"}
}