{
  "type": "Feature",
  "properties": {
    "addr:full":"3212 S 272nd St Kent WA 98032",
    "addr:housenumber":"3212",
    "addr:postcode":"98032",
    "addr:street":"S 272Nd St",
    "iso:country":"US",
    "sg:address":"3212 S 272nd St",
    "sg:city":"Kent",
    "sg:classifiers":[
        {
            "category":"Organizations",
            "subcategory":"Religious Organization",
            "type":"Services"
        }
    ],
    "sg:phone":"+1 253 520 0084",
    "sg:postcode":"98032",
    "sg:province":"WA",
    "sg:tags":[
        "church"
    ],
    "wof:name":"Iglesia Cuadrangular Rey De",
    "wof:placetype":"venue"
},
  "geometry": {"coordinates":[-122.291544,47.357861],"type":"Point"}
}