{
  "type": "Feature",
  "properties": {
    "addr:full":"1521 1st Ave Seattle WA 98101",
    "addr:housenumber":"1521",
    "addr:postcode":"98101",
    "addr:street":"1St Ave",
    "iso:country":"US",
    "sg:address":"1521 1st Ave",
    "sg:city":"Seattle",
    "sg:classifiers":[
        {
            "category":"Shopping",
            "subcategory":"Jewelry",
            "type":"Retail Goods"
        }
    ],
    "sg:phone":"+1 206 340 0702",
    "sg:postcode":"98101",
    "sg:province":"WA",
    "wof:name":"Mile Six Unique Jewelry",
    "wof:placetype":"venue"
},
  "geometry": {"coordinates":[-122.340858,47.609586],"type":"Point"}
}