{
  "type": "Feature",
  "properties": {
    "addr:full":"2819 S 208th St Seatac WA 98198",
    "addr:housenumber":"2819",
    "addr:postcode":"98198",
    "addr:street":"S 208Th St",
    "iso:country":"US",
    "sg:address":"2819 S 208th St",
    "sg:city":"Seatac",
    "sg:classifiers":[
        {
            "category":"Organizations",
            "subcategory":"Religious Organization",
            "type":"Services"
        }
    ],
    "sg:phone":"+1 206 870 8766",
    "sg:postcode":"98198",
    "sg:province":"WA",
    "sg:tags":[
        "church"
    ],
    "wof:name":"Iflesia El Abrigo Del Altisimo",
    "wof:placetype":"venue"
},
  "geometry": {"coordinates":[-122.29659700000001,47.415395],"type":"Point"}
}