{
  "type": "Feature",
  "properties": {
    "addr:full":"600 Ericksen Avenue NE Bainbridge Island WA 98110",
    "addr:housenumber":"600",
    "addr:postcode":"98110",
    "addr:street":"Ericksen Avenue Ne",
    "iso:country":"US",
    "sg:address":"600 Ericksen Avenue NE",
    "sg:city":"Bainbridge Island",
    "sg:classifiers":[
        {
            "category":"Professional",
            "subcategory":"Computer Services",
            "type":"Services"
        }
    ],
    "sg:phone":"+1 206 780 0503",
    "sg:postcode":"98110",
    "sg:province":"WA",
    "sg:tags":[
        "repair"
    ],
    "wof:name":"Mercury Online Solutions",
    "wof:placetype":"venue"
},
  "geometry": {"coordinates":[-122.51698,47.629476],"type":"Point"}
}