{
  "type": "Feature",
  "properties": {
    "addr:full":"120 2nd St NE Puyallup WA 98372",
    "addr:housenumber":"120",
    "addr:postcode":"98372",
    "addr:street":"2Nd St Ne",
    "iso:country":"US",
    "sg:address":"120 2nd St NE",
    "sg:city":"Puyallup",
    "sg:classifiers":[
        {
            "category":"Organizations",
            "subcategory":"Community Association",
            "type":"Services"
        }
    ],
    "sg:phone":"+1 253 841 6362",
    "sg:postcode":"98372",
    "sg:province":"WA",
    "sg:tags":[
        "fraternal"
    ],
    "wof:name":"Veterans Of Foreign Wars",
    "wof:placetype":"venue"
},
  "geometry": {"coordinates":[-122.291759,47.192034],"type":"Point"}
}