{
  "type": "Feature",
  "properties": {
    "addr:full":"801 E 1st St Cle Elum WA 98922",
    "addr:housenumber":"801",
    "addr:postcode":"98922",
    "addr:street":"E 1St St",
    "iso:country":"US",
    "sg:address":"801 E 1st St",
    "sg:city":"Cle Elum",
    "sg:classifiers":[
        {
            "category":"Professional",
            "type":"Services"
        }
    ],
    "sg:phone":"+1 509 674 2249",
    "sg:postcode":"98922",
    "sg:province":"WA",
    "wof:name":"Whoos On 1st",
    "wof:placetype":"venue"
},
  "geometry": {"coordinates":[-120.9222,47.192942],"type":"Point"}
}