{
  "type": "Feature",
  "properties": {
    "iso:country":"US",
    "sg:address":"10140 US Hwy 12",
    "sg:city":"Rochester",
    "sg:classifiers":[
        {
            "category":"Farming",
            "subcategory":"Farm & Veterinary Services",
            "type":"Manufacturing & Wholesale Goods"
        }
    ],
    "sg:phone":"+1 360 273 9175",
    "sg:postcode":"98579",
    "sg:province":"WA",
    "sg:tags":[
        "control",
        "weed"
    ],
    "wof:name":"Rochester Weed & Seed",
    "wof:placetype":"venue"
},
  "geometry": {"coordinates":[-123.096805,46.82189],"type":"Point"}
}