{
  "type": "Feature",
  "properties": {
    "addr:full":"6331 W Powerhouse Rd Yakima WA 98908",
    "addr:housenumber":"6331",
    "addr:postcode":"98908",
    "addr:street":"W Powerhouse Rd",
    "iso:country":"US",
    "sg:address":"6331 W Powerhouse Rd",
    "sg:city":"Yakima",
    "sg:classifiers":[
        {
            "category":"Wholesale",
            "subcategory":"Scrap",
            "type":"Manufacturing & Wholesale Goods"
        }
    ],
    "sg:phone":"+1 509 965 8680",
    "sg:postcode":"98908",
    "sg:province":"WA",
    "sg:tags":[
        "auto",
        "material",
        "parts",
        "used"
    ],
    "wof:name":"Poor Boys Auto Wrecking",
    "wof:placetype":"venue"
},
  "geometry": {"coordinates":[-120.59372999999999,46.637108],"type":"Point"}
}