{
  "type": "Feature",
  "properties": {
    "addr:full":"2700 NE Andresen Rd Vancouver WA 98661",
    "addr:housenumber":"2700",
    "addr:postcode":"98661",
    "addr:street":"Ne Andresen Rd",
    "iso:country":"US",
    "sg:address":"2700 NE Andresen Rd",
    "sg:city":"Vancouver",
    "sg:classifiers":[
        {
            "category":"Organizations",
            "subcategory":"Religious Organization",
            "type":"Services"
        }
    ],
    "sg:phone":"+1 360 944 3681",
    "sg:postcode":"98661",
    "sg:province":"WA",
    "wof:name":"King's Church",
    "wof:placetype":"venue"
},
  "geometry": {"coordinates":[-122.60094599999999,45.642514],"type":"Point"}
}