{
  "type": "Feature",
  "properties": {
    "addr:full":"5927 Merlot Ln SE Lacey WA 98513",
    "addr:housenumber":"5927",
    "addr:postcode":"98513",
    "addr:street":"Merlot Ln Se",
    "iso:country":"US",
    "sg:address":"5927 Merlot Ln SE",
    "sg:city":"Lacey",
    "sg:classifiers":[
        {
            "category":"Professional",
            "subcategory":"Advertising",
            "type":"Services"
        }
    ],
    "sg:phone":"+1 360 455 7335",
    "sg:postcode":"98513",
    "sg:province":"WA",
    "sg:tags":[
        "agency",
        "specialty"
    ],
    "wof:name":"B Bowman",
    "wof:placetype":"venue"
},
  "geometry": {"coordinates":[-122.83274,46.994732],"type":"Point"}
}