{
  "type": "Feature",
  "properties": {
    "iso:country":"US",
    "sg:address":"600 University St",
    "sg:city":"Seattle",
    "sg:classifiers":[
        {
            "category":"Banks & Credit Unions",
            "subcategory":"Financial Services",
            "type":"Services"
        }
    ],
    "sg:phone":"+1 206 624 6166",
    "sg:postcode":"98101",
    "sg:province":"WA",
    "sg:tags":[
        "investor"
    ],
    "wof:name":"Kavilco Incorporated",
    "wof:placetype":"venue"
},
  "geometry": {"coordinates":[-122.33154500000001,47.609589],"type":"Point"}
}