{
  "type": "Feature",
  "properties": {
    "addr:full":"1901 Taylor Way Tacoma WA 98421",
    "addr:housenumber":"1901",
    "addr:postcode":"98421",
    "addr:street":"Taylor Way",
    "iso:country":"US",
    "sg:address":"1901 Taylor Way",
    "sg:city":"Tacoma",
    "sg:classifiers":[
        {
            "category":"Manufacturing",
            "subcategory":"Building Materials",
            "type":"Manufacturing & Wholesale Goods"
        }
    ],
    "sg:phone":"+1 253 627 1191",
    "sg:postcode":"98421",
    "sg:province":"WA",
    "wof:name":"Buffelen Woodworking Co",
    "wof:placetype":"venue"
},
  "geometry": {"coordinates":[-122.391268,47.274053],"type":"Point"}
}