{
  "type": "Feature",
  "properties": {
    "addr:full":"19919 NE 107th Ave Battle Ground WA 98604",
    "addr:housenumber":"19919",
    "addr:postcode":"98604",
    "addr:street":"Ne 107Th Ave",
    "iso:country":"US",
    "sg:address":"19919 NE 107th Ave",
    "sg:city":"Battle Ground",
    "sg:classifiers":[
        {
            "category":"Organizations",
            "subcategory":"Religious Organization",
            "type":"Services"
        }
    ],
    "sg:phone":"+1 360 687 1354",
    "sg:postcode":"98604",
    "sg:province":"WA",
    "sg:tags":[
        "church"
    ],
    "wof:name":"North Country Church",
    "wof:placetype":"venue"
},
  "geometry": {"coordinates":[-122.563169,45.767199],"type":"Point"}
}