{
  "type": "Feature",
  "properties": {
    "addr:full":"2421 Black Rd Oakesdale WA 99158",
    "addr:housenumber":"2421",
    "addr:postcode":"99158",
    "addr:street":"Black Rd",
    "iso:country":"US",
    "sg:address":"2421 Black Rd",
    "sg:city":"Oakesdale",
    "sg:phone":"+1 509 285 4440",
    "sg:postcode":"99158",
    "sg:province":"WA",
    "sg:tags":[
        "farm",
        "wheat"
    ],
    "wof:name":"Bruce Mills",
    "wof:placetype":"venue"
},
  "geometry": {"coordinates":[-117.210852,47.104937],"type":"Point"}
}