{
  "type": "Feature",
  "properties": {
    "addr:full":"8322 Shoemaker Rd Marysville WA 98271",
    "addr:housenumber":"8322",
    "addr:postcode":"98271",
    "addr:street":"Shoemaker Rd",
    "iso:country":"US",
    "sg:address":"8322 Shoemaker Rd",
    "sg:city":"Marysville",
    "sg:classifiers":[
        {
            "category":"Wholesale",
            "subcategory":"Vending Machines",
            "type":"Manufacturing & Wholesale Goods"
        }
    ],
    "sg:phone":"+1 360 653 2301",
    "sg:postcode":"98271",
    "sg:province":"WA",
    "sg:tags":[
        "operator"
    ],
    "wof:name":"Evergreen Vending",
    "wof:placetype":"venue"
},
  "geometry": {"coordinates":[-122.297753,48.071237],"type":"Point"}
}