{
  "type": "Feature",
  "properties": {
    "addr:full":"262 Lotzgesell Rd Sequim WA 98382",
    "addr:housenumber":"262",
    "addr:postcode":"98382",
    "addr:street":"Lotzgesell Rd",
    "iso:country":"US",
    "sg:address":"262 Lotzgesell Rd",
    "sg:city":"Sequim",
    "sg:classifiers":[
        {
            "category":"Personal",
            "type":"Services"
        },
        {
            "category":"Retail",
            "subcategory":"Portrait Studio",
            "type":"Services"
        },
        {
            "category":"Professional",
            "subcategory":"Art Services",
            "type":"Services"
        },
        {
            "category":"Professional",
            "subcategory":"Printing & Photocopies",
            "type":"Services"
        }
    ],
    "sg:phone":"+1 360 681 0902",
    "sg:postcode":"98382",
    "sg:province":"WA",
    "sg:tags":[
        "photographers-portrait",
        "videography",
        "darkroom",
        "rental",
        "photography",
        "wedding",
        "photographers-commercial",
        "photographic"
    ],
    "sg:website":"http://www.collinsphoto.com",
    "wof:name":"Collins Photography",
    "wof:placetype":"venue"
},
  "geometry": {"coordinates":[-123.192481,48.130571],"type":"Point"}
}