{
  "type": "Feature",
  "properties": {
    "addr:full":"1201 N Forest St Bellingham WA 98225",
    "addr:housenumber":"1201",
    "addr:postcode":"98225",
    "addr:street":"N Forest St",
    "iso:country":"US",
    "sg:address":"1201 N Forest St",
    "sg:city":"Bellingham",
    "sg:classifiers":[
        {
            "category":"Utilities",
            "subcategory":"Telephone",
            "type":"Services"
        }
    ],
    "sg:phone":"+1 360 676 4411",
    "sg:postcode":"98225",
    "sg:province":"WA",
    "sg:tags":[
        "communications"
    ],
    "wof:name":"Qwest",
    "wof:placetype":"venue"
},
  "geometry": {"coordinates":[-122.476052,48.74773],"type":"Point"}
}