{
  "type": "Feature",
  "properties": {
    "iso:country":"US",
    "sg:address":"4818 N Lacey St",
    "sg:city":"Spokane",
    "sg:classifiers":[
        {
            "category":"Shopping",
            "subcategory":"Hobbies, Toys, & Games",
            "type":"Retail Goods"
        }
    ],
    "sg:phone":"+1 509 484 4317",
    "sg:postcode":"99217",
    "sg:province":"WA",
    "wof:name":"Paula K Jones",
    "wof:placetype":"venue"
},
  "geometry": {"coordinates":[-117.370743,47.701262],"type":"Point"}
}