{
  "type": "Feature",
  "properties": {
    "addr:full":"1521 15th St SW Auburn WA 98001",
    "addr:housenumber":"1521",
    "addr:postcode":"98001",
    "addr:street":"15Th St Sw",
    "iso:country":"US",
    "sg:address":"1521 15th St SW",
    "sg:city":"Auburn",
    "sg:classifiers":[
        {
            "category":"Retail",
            "subcategory":"Repair Shop",
            "type":"Services"
        }
    ],
    "sg:phone":"+1 253 833 9004",
    "sg:postcode":"98001",
    "sg:province":"WA",
    "wof:name":"Rosemount Inc",
    "wof:placetype":"venue"
},
  "geometry": {"coordinates":[-122.253528,47.295875],"type":"Point"}
}