{
  "type": "Feature",
  "properties": {
    "addr:full":"6763 80th Ave SE Mercer Island WA 98040",
    "addr:housenumber":"6763",
    "addr:postcode":"98040",
    "addr:street":"80Th Ave Se",
    "iso:country":"US",
    "sg:address":"6763 80th Ave SE",
    "sg:city":"Mercer Island",
    "sg:classifiers":[
        {
            "category":"Shopping",
            "subcategory":"Gifts & Souvenirs",
            "type":"Retail Goods"
        }
    ],
    "sg:phone":"+1 206 232 4774",
    "sg:postcode":"98040",
    "sg:province":"WA",
    "wof:name":"Pattis Gifts",
    "wof:placetype":"venue"
},
  "geometry": {"coordinates":[-122.23248700000001,47.541543],"type":"Point"}
}