{
  "type": "Feature",
  "properties": {
    "addr:full":"135 NE 146th Ct Seattle WA 98155",
    "addr:housenumber":"135",
    "addr:postcode":"98155",
    "addr:street":"Ne 146Th Ct",
    "iso:country":"US",
    "sg:address":"135 NE 146th Ct",
    "sg:city":"Seattle",
    "sg:classifiers":[
        {
            "category":"Sports & Exercise",
            "subcategory":"Gym",
            "type":"Entertainment"
        }
    ],
    "sg:phone":"+1 206 246 5913",
    "sg:postcode":"98155",
    "sg:province":"WA",
    "sg:tags":[
        "fitness",
        "physical",
        "facility"
    ],
    "wof:name":"Living Well Lady Fitness Cente",
    "wof:placetype":"venue"
},
  "geometry": {"coordinates":[-122.328137,47.734919],"type":"Point"}
}