{
  "type": "Feature",
  "properties": {
    "addr:full":"18404 NE 139th St Woodinville WA 98072",
    "addr:housenumber":"18404",
    "addr:postcode":"98072",
    "addr:street":"Ne 139Th St",
    "iso:country":"US",
    "sg:address":"18404 NE 139th St",
    "sg:city":"Woodinville",
    "sg:classifiers":[
        {
            "category":"Professional",
            "subcategory":"Management & Consulting",
            "type":"Services"
        }
    ],
    "sg:phone":"+1 425 941 0355",
    "sg:postcode":"98072",
    "sg:province":"WA",
    "sg:tags":[
        "business"
    ],
    "wof:name":"Confiance Consulting LLC",
    "wof:placetype":"venue"
},
  "geometry": {"coordinates":[-122.09339300000001,47.724344],"type":"Point"}
}