{
  "type": "Feature",
  "properties": {
    "addr:full":"930 State St Sedro Woolley WA 98284",
    "addr:housenumber":"930",
    "addr:postcode":"98284",
    "addr:street":"State St",
    "iso:country":"US",
    "sg:address":"930 State St",
    "sg:city":"Sedro Woolley",
    "sg:classifiers":[
        {
            "category":"Retail",
            "subcategory":"Portrait Studio",
            "type":"Services"
        }
    ],
    "sg:phone":"+1 360 855 9199",
    "sg:postcode":"98284",
    "sg:province":"WA",
    "sg:tags":[
        "photographer"
    ],
    "wof:name":"Jen Brown Portrait Studio",
    "wof:placetype":"venue"
},
  "geometry": {"coordinates":[-122.223589,48.503264],"type":"Point"}
}