{
  "type": "Feature",
  "properties": {
    "addr:full":"4447 California Ave SW Seattle WA 98116",
    "addr:housenumber":"4447",
    "addr:postcode":"98116",
    "addr:street":"California Ave Sw",
    "iso:country":"US",
    "sg:address":"4447 California Ave SW",
    "sg:city":"Seattle",
    "sg:classifiers":[
        {
            "category":"Personal",
            "type":"Services"
        }
    ],
    "sg:phone":"+1 206 937 3877",
    "sg:postcode":"98116",
    "sg:province":"WA",
    "wof:name":"Sun Room",
    "wof:placetype":"venue"
},
  "geometry": {"coordinates":[-122.38685099999999,47.563755],"type":"Point"}
}