{
  "type": "Feature",
  "properties": {
    "addr:full":"20531 25th Ave W Lynnwood WA 98036",
    "addr:housenumber":"20531",
    "addr:postcode":"98036",
    "addr:street":"25Th Ave W",
    "iso:country":"US",
    "sg:address":"20531 25th Ave W",
    "sg:city":"Lynnwood",
    "sg:classifiers":[
        {
            "category":"Professional",
            "subcategory":"Management & Consulting",
            "type":"Services"
        }
    ],
    "sg:phone":"+1 425 775 2084",
    "sg:postcode":"98036",
    "sg:province":"WA",
    "sg:tags":[
        "business"
    ],
    "wof:name":"Thomas Wynne Consulting",
    "wof:placetype":"venue"
},
  "geometry": {"coordinates":[-122.267663,47.810438],"type":"Point"}
}