{
  "type": "Feature",
  "properties": {
    "addr:full":"10231 Wilkeson St S Tacoma WA 98444",
    "addr:housenumber":"10231",
    "addr:postcode":"98444",
    "addr:street":"Wilkeson St S",
    "iso:country":"US",
    "sg:address":"10231 Wilkeson St S",
    "sg:city":"Tacoma",
    "sg:classifiers":[
        {
            "category":"Building & Trades",
            "subcategory":"Construction",
            "type":"Services"
        }
    ],
    "sg:phone":"+1 253 537 0378",
    "sg:postcode":"98444",
    "sg:province":"WA",
    "sg:tags":[
        "contractor"
    ],
    "wof:name":"Lee Samuelson Contractor",
    "wof:placetype":"venue"
},
  "geometry": {"coordinates":[-122.459337,47.16341],"type":"Point"}
}