{
  "type": "Feature",
  "properties": {
    "addr:full":"1002 S Emerald Rd Sunnyside WA 98944",
    "addr:housenumber":"1002",
    "addr:postcode":"98944",
    "addr:street":"S Emerald Rd",
    "iso:country":"US",
    "sg:address":"1002 S Emerald Rd",
    "sg:city":"Sunnyside",
    "sg:phone":"+1 509 837 5921",
    "sg:postcode":"98944",
    "sg:province":"WA",
    "sg:tags":[
        "farm",
        "field",
        "corn",
        "crop"
    ],
    "wof:name":"Walter Johnson",
    "wof:placetype":"venue"
},
  "geometry": {"coordinates":[-120.083332,46.287901],"type":"Point"}
}