{
  "type": "Feature",
  "properties": {
    "addr:full":"13306 Occidental Ave Yakima WA 98903",
    "addr:housenumber":"13306",
    "addr:postcode":"98903",
    "addr:street":"Occidental Ave",
    "iso:country":"US",
    "sg:address":"13306 Occidental Ave",
    "sg:city":"Yakima",
    "sg:classifiers":[
        {
            "category":"Farming",
            "subcategory":"Orchard",
            "type":"Manufacturing & Wholesale Goods"
        }
    ],
    "sg:phone":"+1 509 965 1740",
    "sg:postcode":"98903",
    "sg:province":"WA",
    "sg:tags":[
        "fruit",
        "tree"
    ],
    "wof:name":"Brewer Orchards",
    "wof:placetype":"venue"
},
  "geometry": {"coordinates":[-120.68673,46.563764],"type":"Point"}
}