{
  "type": "Feature",
  "properties": {
    "addr:full":"1214 S Tranquility Pr SE Kennewick WA 99338",
    "addr:housenumber":"1214",
    "addr:postcode":"99338",
    "addr:street":"S Tranquility;Se",
    "iso:country":"US",
    "sg:address":"1214 S Tranquility Pr SE",
    "sg:city":"Kennewick",
    "sg:classifiers":[
        {
            "category":"Building & Trades",
            "subcategory":"Construction",
            "type":"Services"
        }
    ],
    "sg:phone":"+1 509 627 0188",
    "sg:postcode":"99338",
    "sg:province":"WA",
    "sg:tags":[
        "house"
    ],
    "wof:name":"Bruce M Pratt",
    "wof:placetype":"venue"
},
  "geometry": {"coordinates":[-119.25736999999999,46.198532],"type":"Point"}
}