{
  "type": "Feature",
  "properties": {
    "addr:full":"231 Rockwood Rd Newport WA 99156",
    "addr:housenumber":"231",
    "addr:postcode":"99156",
    "addr:street":"Rockwood Rd",
    "iso:country":"US",
    "sg:address":"231 Rockwood Rd",
    "sg:city":"Newport",
    "sg:classifiers":[
        {
            "category":"Building & Trades",
            "subcategory":"Landscaping Services",
            "type":"Services"
        }
    ],
    "sg:phone":"+1 509 447 3989",
    "sg:postcode":"99156",
    "sg:province":"WA",
    "sg:tags":[
        "tree"
    ],
    "wof:name":"Paul Bunyan Tree Svc",
    "wof:placetype":"venue"
},
  "geometry": {"coordinates":[-117.196493,48.134233],"type":"Point"}
}