{
  "type": "Feature",
  "properties": {
    "addr:full":"14816 SE 63rd St Bellevue WA 98006",
    "addr:postcode":"14816;98006",
    "addr:street":"Se 63Rd St",
    "iso:country":"US",
    "sg:address":"14816 SE 63rd St",
    "sg:city":"Bellevue",
    "sg:classifiers":[
        {
            "category":"Shopping",
            "subcategory":"Catalog Store",
            "type":"Retail Goods"
        }
    ],
    "sg:phone":"+1 425 643 1141",
    "sg:postcode":"98006",
    "sg:province":"WA",
    "sg:tags":[
        "mail",
        "house"
    ],
    "wof:name":"Treasure House Jewelry",
    "wof:placetype":"venue"
},
  "geometry": {"coordinates":[-122.142976,47.546585],"type":"Point"}
}