{
  "type": "Feature",
  "properties": {
    "addr:full":"3805 108th Ave NE Ste 210 Bellevue WA 98004",
    "addr:housenumber":"3805",
    "addr:postcode":"98004",
    "addr:street":"108Th Ave Ne Ste 210",
    "iso:country":"US",
    "sg:address":"3805 108th Ave NE Ste 210",
    "sg:city":"Bellevue",
    "sg:classifiers":[
        {
            "category":"Building & Trades",
            "subcategory":"Construction",
            "type":"Services"
        }
    ],
    "sg:phone":"+1 425 828 6636",
    "sg:postcode":"98004",
    "sg:province":"WA",
    "sg:tags":[
        "air",
        "heating",
        "conditioning/hvac"
    ],
    "wof:name":"Norby Company",
    "wof:placetype":"venue"
},
  "geometry": {"coordinates":[-122.194,47.644199],"type":"Point"}
}