{
  "type": "Feature",
  "properties": {
    "addr:full":"6801 S Lawrence St Tacoma WA 98409",
    "addr:housenumber":"6801",
    "addr:postcode":"98409",
    "addr:street":"S Lawrence St",
    "iso:country":"US",
    "sg:address":"6801 S Lawrence St",
    "sg:city":"Tacoma",
    "sg:classifiers":[
        {
            "category":"Building & Trades",
            "subcategory":"Construction",
            "type":"Services"
        }
    ],
    "sg:phone":"+1 253 474 5330",
    "sg:postcode":"98409",
    "sg:province":"WA",
    "sg:tags":[
        "contractor"
    ],
    "wof:name":"Johnsons Quality Tile",
    "wof:placetype":"venue"
},
  "geometry": {"coordinates":[-122.47980699999999,47.193829],"type":"Point"}
}