{
  "type": "Feature",
  "properties": {
    "iso:country":"US",
    "sg:address":"23806 97th Ave SW",
    "sg:city":"Vashon",
    "sg:classifiers":[
        {
            "category":"Professional",
            "subcategory":"Art Services",
            "type":"Services"
        }
    ],
    "sg:phone":"+1 206 463 2400",
    "sg:postcode":"98070",
    "sg:province":"WA",
    "sg:tags":[
        "photography"
    ],
    "wof:name":"Peninsula Photos",
    "wof:placetype":"venue"
},
  "geometry": {"coordinates":[-122.45780600000001,47.390874],"type":"Point"}
}