{
  "type": "Feature",
  "properties": {
    "addr:full":"1301 Ferry Rd Lopez Island WA 98261",
    "addr:housenumber":"1301",
    "addr:postcode":"98261",
    "addr:street":"Ferry Rd Lopez Island",
    "iso:country":"US",
    "sg:address":"1301 Ferry Rd",
    "sg:city":"Lopez Island",
    "sg:classifiers":[
        {
            "category":"Home & Garden",
            "subcategory":"Household Appliances",
            "type":"Retail Goods"
        }
    ],
    "sg:phone":"+1 360 468 2587",
    "sg:postcode":"98261",
    "sg:province":"WA",
    "sg:tags":[
        "pump"
    ],
    "wof:name":"A & A Well Drilling",
    "wof:placetype":"venue"
},
  "geometry": {"coordinates":[-122.89380199999999,48.545117],"type":"Point"}
}