{
  "type": "Feature",
  "properties": {
    "addr:full":"719 Front St Leavenworth WA 98826",
    "addr:housenumber":"719",
    "addr:postcode":"98826",
    "addr:street":"Front St",
    "iso:country":"US",
    "sg:address":"719 Front St",
    "sg:city":"Leavenworth",
    "sg:classifiers":[
        {
            "category":"Shopping",
            "subcategory":"Hobbies, Toys, & Games",
            "type":"Retail Goods"
        }
    ],
    "sg:phone":"+1 509 548 4442",
    "sg:postcode":"98826",
    "sg:province":"WA",
    "wof:name":"Wood Shop",
    "wof:placetype":"venue"
},
  "geometry": {"coordinates":[-120.66300699999999,47.594648],"type":"Point"}
}