{
  "type": "Feature",
  "properties": {
    "addr:full":"13 Chapparral Rd Trout Lake WA 98650",
    "addr:housenumber":"13",
    "addr:postcode":"98650",
    "addr:street":"Chapparral Rd",
    "iso:country":"US",
    "sg:address":"13 Chapparral Rd",
    "sg:city":"Trout Lake",
    "sg:classifiers":[
        {
            "category":"Freight",
            "type":"Transportation"
        }
    ],
    "sg:phone":"+1 509 395 2363",
    "sg:postcode":"98650",
    "sg:province":"WA",
    "sg:tags":[
        "trucking",
        "child",
        "operator",
        "local",
        "day",
        "care"
    ],
    "wof:name":"Van Laar Enterprises Inc",
    "wof:placetype":"venue"
},
  "geometry": {"coordinates":[-121.50395,45.977007],"type":"Point"}
}