{
  "type": "Feature",
  "properties": {
    "addr:full":"1321 24th Ave Longview WA 98632",
    "addr:housenumber":"1321",
    "addr:postcode":"98632",
    "addr:street":"24Th Ave",
    "iso:country":"US",
    "sg:address":"1321 24th Ave",
    "sg:city":"Longview",
    "sg:classifiers":[
        {
            "category":"Farming",
            "subcategory":"Fish & Marine Products",
            "type":"Manufacturing & Wholesale Goods"
        }
    ],
    "sg:phone":"+1 360 425 5095",
    "sg:postcode":"98632",
    "sg:province":"WA",
    "sg:tags":[
        "fishing"
    ],
    "wof:name":"Thomas F Stecker",
    "wof:placetype":"venue"
},
  "geometry": {"coordinates":[-122.94877200000001,46.140305],"type":"Point"}
}