{
  "type": "Feature",
  "properties": {
    "addr:full":"7816 NE 8th St Medina WA 98039",
    "addr:housenumber":"7816",
    "addr:postcode":"98039",
    "addr:street":"Ne 8Th St",
    "iso:country":"US",
    "sg:address":"7816 NE 8th St",
    "sg:city":"Medina",
    "sg:classifiers":[
        {
            "category":"Professional",
            "subcategory":"Lawyer & Legal Services",
            "type":"Services"
        }
    ],
    "sg:phone":"+1 425 453 2804",
    "sg:postcode":"98039",
    "sg:province":"WA",
    "wof:name":"Runyan Michael H Atty",
    "wof:placetype":"venue"
},
  "geometry": {"coordinates":[-122.235001,47.617401],"type":"Point"}
}