{
  "type": "Feature",
  "properties": {
    "addr:full":"1308 N 30th St Renton WA 98056",
    "addr:housenumber":"1308",
    "addr:postcode":"98056",
    "addr:street":"N 30Th St",
    "iso:country":"US",
    "sg:address":"1308 N 30th St",
    "sg:city":"Renton",
    "sg:classifiers":[
        {
            "category":"Food & Beverages",
            "subcategory":"Groceries & Convenience Stores",
            "type":"Retail Goods"
        }
    ],
    "sg:phone":"+1 425 228 5969",
    "sg:postcode":"98056",
    "sg:province":"WA",
    "wof:name":"Seven-Eleven Food Stores",
    "wof:placetype":"venue"
},
  "geometry": {"coordinates":[-122.200996,47.518299],"type":"Point"}
}