{
  "type": "Feature",
  "properties": {
    "iso:country":"US",
    "sg:address":"2001 Lind Ave SW",
    "sg:city":"Renton",
    "sg:classifiers":[
        {
            "category":"Real Estate",
            "subcategory":"Real Estate Services",
            "type":"Services"
        }
    ],
    "sg:phone":"+1 425 873 1342",
    "sg:postcode":"98057",
    "sg:province":"WA",
    "sg:tags":[
        "finding",
        "searching"
    ],
    "sg:website":"www.classmates.com",
    "wof:name":"Classmates Online Inc",
    "wof:placetype":"venue"
},
  "geometry": {"coordinates":[-122.22346400000001,47.461868],"type":"Point"}
}