{
  "type": "Feature",
  "properties": {
    "addr:full":"401 E Mountain View Ave Ellensburg WA 98926",
    "addr:housenumber":"401",
    "addr:postcode":"98926",
    "addr:street":"E Mountain View Ave",
    "iso:country":"US",
    "sg:address":"401 E Mountain View Ave",
    "sg:city":"Ellensburg",
    "sg:classifiers":[
        {
            "category":"Government",
            "subcategory":"Office",
            "type":"Public Place"
        }
    ],
    "sg:phone":"+1 509 925 8584",
    "sg:postcode":"98926",
    "sg:province":"WA",
    "sg:tags":[
        "federal"
    ],
    "wof:name":"US Soil Survey",
    "wof:placetype":"venue"
},
  "geometry": {"coordinates":[-120.543144,46.984638],"type":"Point"}
}