{
  "type": "Feature",
  "properties": {
    "iso:country":"US",
    "sg:address":"25805 33rd Ave S",
    "sg:city":"Kent",
    "sg:classifiers":[
        {
            "category":"Building & Trades",
            "subcategory":"Construction",
            "type":"Services"
        }
    ],
    "sg:phone":"+1 206 501 5668",
    "sg:postcode":"98032",
    "sg:province":"WA",
    "sg:tags":[
        "contractor"
    ],
    "wof:name":"All City Drywall & Restoration",
    "wof:placetype":"venue"
},
  "geometry": {"coordinates":[-122.290172,47.371453],"type":"Point"}
}