{
  "type": "Feature",
  "properties": {
    "addr:full":"17322 Vashon Hwy SW Vashon WA 98070",
    "addr:housenumber":"17322",
    "addr:postcode":"98070",
    "addr:street":"Vashon Hwy Sw",
    "iso:country":"US",
    "sg:address":"17322 Vashon Hwy SW",
    "sg:city":"Vashon",
    "sg:classifiers":[
        {
            "category":"Restaurant",
            "type":"Food & Drink"
        }
    ],
    "sg:phone":"+1 206 463 6813",
    "sg:postcode":"98070",
    "sg:province":"WA",
    "sg:tags":[
        "eating"
    ],
    "wof:name":"Rock Island Pub Pizza",
    "wof:placetype":"venue"
},
  "geometry": {"coordinates":[-122.460385,47.450001],"type":"Point"}
}