{
  "type": "Feature",
  "properties": {
    "addr:full":"4198 Westside Hwy Castle Rock WA 98611",
    "addr:housenumber":"4198",
    "addr:postcode":"98611",
    "addr:street":"Westside Hwy",
    "iso:country":"US",
    "sg:address":"4198 Westside Hwy",
    "sg:city":"Castle Rock",
    "sg:classifiers":[
        {
            "category":"Insurance",
            "subcategory":"Hazard Insurance",
            "type":"Services"
        }
    ],
    "sg:phone":"+1 360 274 9000",
    "sg:postcode":"98611",
    "sg:province":"WA",
    "sg:tags":[
        "carrier",
        "surety"
    ],
    "wof:name":"Prime Financial Services",
    "wof:placetype":"venue"
},
  "geometry": {"coordinates":[-122.906757,46.258466],"type":"Point"}
}