{
  "type": "Feature",
  "properties": {
    "addr:full":"1411 4th Ave Seattle WA 98101",
    "addr:housenumber":"1411",
    "addr:postcode":"98101",
    "addr:street":"4Th Ave",
    "iso:country":"US",
    "sg:address":"1411 4th Ave",
    "sg:city":"Seattle",
    "sg:classifiers":[
        {
            "category":"Professional",
            "subcategory":"Lawyer & Legal Services",
            "type":"Services"
        }
    ],
    "sg:phone":"+1 206 398 1142",
    "sg:postcode":"98101",
    "sg:province":"WA",
    "wof:name":"Fisher Daniel R Atty",
    "wof:placetype":"venue"
},
  "geometry": {"coordinates":[-122.333,47.610401],"type":"Point"}
}