{
  "type": "Feature",
  "properties": {
    "addr:full":"11202 Bridgeport Way SW Lakewood WA 98499",
    "addr:housenumber":"11202",
    "addr:postcode":"98499",
    "addr:street":"Bridgeport Way Sw",
    "iso:country":"US",
    "sg:address":"11202 Bridgeport Way SW",
    "sg:city":"Lakewood",
    "sg:classifiers":[
        {
            "category":"Deli",
            "type":"Food & Drink"
        }
    ],
    "sg:phone":"+1 253 589 1211",
    "sg:postcode":"98499",
    "sg:province":"WA",
    "wof:name":"Hoagie's Sub Deli",
    "wof:placetype":"venue"
},
  "geometry": {"coordinates":[-122.504997,47.155701],"type":"Point"}
}