{
  "type": "Feature",
  "properties": {
    "addr:full":"9011 S 19th St Tacoma WA 98466",
    "addr:housenumber":"9011",
    "addr:postcode":"98466",
    "addr:street":"S 19Th St",
    "iso:country":"US",
    "sg:address":"9011 S 19th St",
    "sg:city":"Tacoma",
    "sg:classifiers":[
        {
            "category":"Autos & Motor Vehicles",
            "subcategory":"Automobile Sales",
            "type":"Retail Goods"
        },
        {
            "category":"Autos & Motor Vehicles",
            "subcategory":"Boat Sales",
            "type":"Retail Goods"
        },
        {
            "category":"Retail",
            "subcategory":"Auto Repair",
            "type":"Services"
        },
        {
            "category":"Marine",
            "type":"Transportation"
        },
        {
            "category":"Wholesale",
            "subcategory":"Auto Parts",
            "type":"Manufacturing & Wholesale Goods"
        }
    ],
    "sg:phone":"+1 253 777 3924",
    "sg:postcode":"98466",
    "sg:province":"WA",
    "sg:tags":[
        "used",
        "supply",
        "car",
        "outboard",
        "equipment",
        "maintenance",
        "consultant",
        "distributor",
        "new",
        "motors-repairing",
        "supplies-wholesale"
    ],
    "sg:website":"http://national.citysearch.com/profile/external/37041735/tacoma_wa/day_island_boatworks.html?publisher=yellowpages&reference_id=15&placement=ypwebsitemip",
    "wof:name":"Day Island Boatworks",
    "wof:placetype":"venue"
},
  "geometry": {"coordinates":[-122.556702,47.242691],"type":"Point"}
}