{
  "type": "Feature",
  "properties": {
    "addr:full":"1401 Marvin Rd NE Ste 107 Lacey WA 98516",
    "addr:housenumber":"1401",
    "addr:postcode":"98516",
    "addr:street":"Marvin Rd Ne Ste 107",
    "iso:country":"US",
    "sg:address":"1401 Marvin Rd NE Ste 107",
    "sg:city":"Lacey",
    "sg:classifiers":[
        {
            "category":"Health Services",
            "subcategory":"Chiropractor",
            "type":"Services"
        }
    ],
    "sg:phone":"+1 360 459 5990",
    "sg:postcode":"98516",
    "sg:province":"WA",
    "sg:tags":[
        "chiropractic"
    ],
    "wof:name":"Hawks Prairie Chiropractic",
    "wof:placetype":"venue"
},
  "geometry": {"coordinates":[-122.764689,47.060208],"type":"Point"}
}