{
  "type": "Feature",
  "properties": {
    "addr:full":"216 SW 156th St Seattle WA 98166",
    "addr:housenumber":"216",
    "addr:postcode":"98166",
    "addr:street":"Sw 156Th St",
    "iso:country":"US",
    "sg:address":"216 SW 156th St",
    "sg:city":"Seattle",
    "sg:classifiers":[
        {
            "category":"Health Services",
            "subcategory":"Doctor",
            "type":"Services"
        }
    ],
    "sg:phone":"+1 206 246 0831",
    "sg:postcode":"98166",
    "sg:province":"WA",
    "wof:name":"Fred R Thomas DMD",
    "wof:placetype":"venue"
},
  "geometry": {"coordinates":[-122.33754,47.463355],"type":"Point"}
}