{
  "type": "Feature",
  "properties": {
    "addr:full":"116 W Main St Monroe WA 98272",
    "addr:housenumber":"116",
    "addr:postcode":"98272",
    "addr:street":"W Main St",
    "iso:country":"US",
    "sg:address":"116 W Main St",
    "sg:city":"Monroe",
    "sg:classifiers":[
        {
            "category":"Restaurant",
            "type":"Food & Drink"
        }
    ],
    "sg:phone":"+1 360 805 5660",
    "sg:postcode":"98272",
    "sg:province":"WA",
    "sg:tags":[
        "mexican"
    ],
    "wof:name":"El Tapatio Family Mexican",
    "wof:placetype":"venue"
},
  "geometry": {"coordinates":[-121.971011,47.855698],"type":"Point"}
}