{
  "type": "Feature",
  "properties": {
    "addr:full":"17 Basin St NW Ephrata WA 98823",
    "addr:housenumber":"17",
    "addr:postcode":"98823",
    "addr:street":"Basin St Nw",
    "iso:country":"US",
    "sg:address":"17 Basin St NW",
    "sg:city":"Ephrata",
    "sg:classifiers":[
        {
            "category":"Personal",
            "type":"Services"
        }
    ],
    "sg:phone":"+1 509 754 3411",
    "sg:postcode":"98823",
    "sg:province":"WA",
    "sg:tags":[
        "wear",
        "formal"
    ],
    "wof:name":"Geesey's Formal Wear",
    "wof:placetype":"venue"
},
  "geometry": {"coordinates":[-119.551486,47.320959],"type":"Point"}
}