{
  "type": "Feature",
  "properties": {
    "addr:full":"6232 186th St SW Lynnwood WA 98037",
    "addr:housenumber":"6232",
    "addr:postcode":"98037",
    "addr:street":"186Th St Sw",
    "iso:country":"US",
    "sg:address":"6232 186th St SW",
    "sg:city":"Lynnwood",
    "sg:classifiers":[
        {
            "category":"Professional",
            "subcategory":"Business Services",
            "type":"Services"
        }
    ],
    "sg:phone":"+1 425 776 1578",
    "sg:postcode":"98037",
    "sg:province":"WA",
    "wof:name":"M&H Enterprises",
    "wof:placetype":"venue"
},
  "geometry": {"coordinates":[-122.318189,47.830183],"type":"Point"}
}