{
  "type": "Feature",
  "properties": {
    "addr:full":"5923 Braywood Ln SE Olympia WA 98513",
    "addr:housenumber":"5923",
    "addr:postcode":"98513",
    "addr:street":"Braywood Ln Se",
    "iso:country":"US",
    "sg:address":"5923 Braywood Ln SE",
    "sg:city":"Olympia",
    "sg:classifiers":[
        {
            "category":"Local Transit",
            "type":"Transportation"
        }
    ],
    "sg:phone":"+1 360 456 8054",
    "sg:postcode":"98513",
    "sg:province":"WA",
    "sg:tags":[
        "limousine"
    ],
    "wof:name":"Olympic Limousine",
    "wof:placetype":"venue"
},
  "geometry": {"coordinates":[-122.703841,46.995782],"type":"Point"}
}