{
  "type": "Feature",
  "properties": {
    "addr:full":"412 McGraw St Seattle WA 98109",
    "addr:housenumber":"412",
    "addr:postcode":"98109",
    "addr:street":"Mcgraw St",
    "iso:country":"US",
    "sg:address":"412 McGraw St",
    "sg:city":"Seattle",
    "sg:classifiers":[
        {
            "category":"Education",
            "subcategory":"Special Training",
            "type":"Public Place"
        }
    ],
    "sg:phone":"+1 206 283 5368",
    "sg:postcode":"98109",
    "sg:province":"WA",
    "sg:tags":[
        "tutoring"
    ],
    "wof:name":"Hilltop Tutoring",
    "wof:placetype":"venue"
},
  "geometry": {"coordinates":[-122.348949,47.640209],"type":"Point"}
}