{
  "type": "Feature",
  "properties": {
    "iso:country":"US",
    "sg:address":"631 Birch St",
    "sg:city":"Edmonds",
    "sg:classifiers":[
        {
            "category":"Real Estate",
            "subcategory":"Real Estate Agent",
            "type":"Services"
        }
    ],
    "sg:phone":"+1 425 640 2700",
    "sg:postcode":"98020",
    "sg:province":"WA",
    "wof:name":"Re/Max",
    "wof:placetype":"venue"
},
  "geometry": {"coordinates":[-122.37297100000001,47.797508],"type":"Point"}
}