{
  "type": "Feature",
  "properties": {
    "addr:full":"1423 Railroad Ave Bellingham WA 98225",
    "addr:housenumber":"1423",
    "addr:postcode":"98225",
    "addr:street":"Railroad",
    "iso:country":"US",
    "sg:address":"1423 Railroad Ave",
    "sg:city":"Bellingham",
    "sg:classifiers":[
        {
            "category":"Shopping",
            "subcategory":"Computers & Home Electronics",
            "type":"Retail Goods"
        }
    ],
    "sg:phone":"+1 360 671 4906",
    "sg:postcode":"98225",
    "sg:province":"WA",
    "wof:name":"3-D Computer Corp",
    "wof:placetype":"venue"
},
  "geometry": {"coordinates":[-122.475381,48.750939],"type":"Point"}
}