{
  "type": "Feature",
  "properties": {
    "addr:full":"406 S 2nd St Mt Vernon WA 98273",
    "addr:housenumber":"406",
    "addr:postcode":"98273",
    "addr:street":"S 2Nd St",
    "iso:country":"US",
    "sg:address":"406 S 2nd St",
    "sg:city":"Mt Vernon",
    "sg:classifiers":[
        {
            "category":"Social Services",
            "type":"Services"
        }
    ],
    "sg:phone":"+1 360 419 7066",
    "sg:postcode":"98273",
    "sg:province":"WA",
    "sg:tags":[
        "organization",
        "welfare"
    ],
    "wof:name":"Service Alternatives",
    "wof:placetype":"venue"
},
  "geometry": {"coordinates":[-122.33640200000001,48.419778],"type":"Point"}
}