{
  "type": "Feature",
  "properties": {
    "addr:full":"912 Alaskan Way Seattle WA 98104",
    "addr:housenumber":"912",
    "addr:postcode":"98104",
    "addr:street":"Alaskan Way",
    "iso:country":"US",
    "sg:address":"912 Alaskan Way",
    "sg:city":"Seattle",
    "sg:classifiers":[
        {
            "category":"Education",
            "subcategory":"Dance Studio",
            "type":"Public Place"
        },
        {
            "category":"Shopping",
            "subcategory":"Shoes",
            "type":"Retail Goods"
        }
    ],
    "sg:phone":"+1 206 624 0960",
    "sg:postcode":"98104",
    "sg:province":"WA",
    "sg:tags":[
        "store"
    ],
    "sg:website":"www.salsapromotions.com/",
    "wof:name":"Experience Dance Shoes",
    "wof:placetype":"venue"
},
  "geometry": {"coordinates":[-122.33754999999999,47.6033],"type":"Point"}
}