{
  "type": "Feature",
  "properties": {
    "iso:country":"US",
    "sg:address":"15582 McLean Rd",
    "sg:city":"Mount Vernon",
    "sg:classifiers":[
        {
            "category":"Farming",
            "subcategory":"Farm",
            "type":"Manufacturing & Wholesale Goods"
        }
    ],
    "sg:phone":"+1 360 424 8237",
    "sg:postcode":"98273",
    "sg:province":"WA",
    "sg:tags":[
        "crop",
        "general"
    ],
    "wof:name":"Todd Gordon Farms",
    "wof:placetype":"venue"
},
  "geometry": {"coordinates":[-122.412487,48.420834],"type":"Point"}
}