{
  "type": "Feature",
  "properties": {
    "iso:country":"US",
    "sg:address":"1931 13th St",
    "sg:city":"Port Townsend",
    "sg:classifiers":[
        {
            "category":"Restaurant",
            "type":"Food & Drink"
        }
    ],
    "sg:phone":"+1 360 385 1708",
    "sg:postcode":"98368",
    "sg:province":"WA",
    "sg:tags":[
        "eating"
    ],
    "wof:name":"Dogs A Foot",
    "wof:placetype":"venue"
},
  "geometry": {"coordinates":[-122.79826799999999,48.109205],"type":"Point"}
}