{
  "type": "Feature",
  "properties": {
    "addr:full":"9701 W Champion Ln Cheney WA 99004",
    "addr:housenumber":"9701",
    "addr:postcode":"99004",
    "addr:street":"W Champion Ln",
    "iso:country":"US",
    "sg:address":"9701 W Champion Ln",
    "sg:city":"Cheney",
    "sg:classifiers":[
        {
            "category":"Building & Trades",
            "subcategory":"Construction",
            "type":"Services"
        }
    ],
    "sg:phone":"+1 509 235 4000",
    "sg:postcode":"99004",
    "sg:province":"WA",
    "sg:tags":[
        "contractor"
    ],
    "wof:name":"Castle Construction & Material",
    "wof:placetype":"venue"
},
  "geometry": {"coordinates":[-117.548334,47.576003],"type":"Point"}
}