{
  "type": "Feature",
  "properties": {
    "addr:full":"1504 S 80th Ave Yakima WA 98908",
    "addr:housenumber":"1504",
    "addr:postcode":"98908",
    "addr:street":"S 80Th Ave",
    "iso:country":"US",
    "sg:address":"1504 S 80th Ave",
    "sg:city":"Yakima",
    "sg:classifiers":[
        {
            "category":"Building & Trades",
            "subcategory":"Electrical",
            "type":"Services"
        },
        {
            "category":"Retail",
            "subcategory":"Auto Repair",
            "type":"Services"
        }
    ],
    "sg:phone":"+1 509 966 8552",
    "sg:postcode":"98908",
    "sg:province":"WA",
    "sg:tags":[
        "automobile",
        "electrician",
        "electric"
    ],
    "sg:website":"http://www.comwrx.com",
    "wof:name":"Pro-Techs Automotive",
    "wof:placetype":"venue"
},
  "geometry": {"coordinates":[-120.614829,46.577872],"type":"Point"}
}