{
  "type": "Feature",
  "properties": {
    "addr:full":"13622 NE 20th St Ste A-2 Bellevue WA 98005",
    "addr:housenumber":"13622",
    "addr:postcode":"98005",
    "addr:street":"Ne 20Th St Ste A-2",
    "iso:country":"US",
    "sg:address":"13622 NE 20th St Ste A-2",
    "sg:city":"Bellevue",
    "sg:classifiers":[
        {
            "category":"Professional",
            "subcategory":"Art Services",
            "type":"Services"
        },
        {
            "category":"Professional",
            "subcategory":"Printing & Photocopies",
            "type":"Services"
        }
    ],
    "sg:phone":"+1 425 882 0509",
    "sg:postcode":"98005",
    "sg:province":"WA",
    "sg:tags":[
        "graphic",
        "design"
    ],
    "sg:website":"www.olyrepro.com",
    "wof:name":"Olympic Reprographics",
    "wof:placetype":"venue"
},
  "geometry": {"coordinates":[-122.157882,47.628733],"type":"Point"}
}