{
  "type": "Feature",
  "properties": {
    "addr:full":"1336 S Pioneer Way Moses Lake WA 98837",
    "addr:housenumber":"1336",
    "addr:postcode":"98837",
    "addr:street":"S Pioneer Way",
    "iso:country":"US",
    "sg:address":"1336 S Pioneer Way",
    "sg:city":"Moses Lake",
    "sg:classifiers":[
        {
            "category":"Social Services",
            "type":"Services"
        }
    ],
    "sg:phone":"+1 509 766 2568",
    "sg:postcode":"98837",
    "sg:province":"WA",
    "sg:tags":[
        "senior",
        "citizen"
    ],
    "sg:website":"www.aaccw.org",
    "wof:name":"Central WA Aging & Adult Care",
    "wof:placetype":"venue"
},
  "geometry": {"coordinates":[-119.263454,47.115768],"type":"Point"}
}