{
  "type": "Feature",
  "properties": {
    "addr:full":"16809 Jordan Rd Arlington WA 98223",
    "addr:housenumber":"16809",
    "addr:postcode":"98223",
    "addr:street":"Jordan Rd",
    "iso:country":"US",
    "sg:address":"16809 Jordan Rd",
    "sg:city":"Arlington",
    "sg:classifiers":[
        {
            "category":"Building & Trades",
            "subcategory":"Landscaping Services",
            "type":"Services"
        }
    ],
    "sg:phone":"+1 360 435 9870",
    "sg:postcode":"98223",
    "sg:province":"WA",
    "sg:tags":[
        "landscape"
    ],
    "wof:name":"Misty Meadow Nursery",
    "wof:placetype":"venue"
},
  "geometry": {"coordinates":[-122.044145,48.148958],"type":"Point"}
}