{
  "type": "Feature",
  "properties": {
    "addr:full":"10713 E 32nd Ave Spokane WA 99206",
    "addr:housenumber":"10713",
    "addr:postcode":"99206",
    "addr:street":"E 32Nd Ave",
    "iso:country":"US",
    "sg:address":"10713 E 32nd Ave",
    "sg:city":"Spokane",
    "sg:classifiers":[
        {
            "category":"Freight",
            "type":"Transportation"
        }
    ],
    "sg:phone":"+1 509 926 4679",
    "sg:postcode":"99206",
    "sg:province":"WA",
    "sg:tags":[
        "operator",
        "local",
        "trucking"
    ],
    "wof:name":"Doug Delivers",
    "wof:placetype":"venue"
},
  "geometry": {"coordinates":[-117.258776,47.628009],"type":"Point"}
}