{
  "type": "Feature",
  "properties": {
    "addr:full":"3968 Bancroft Rd Bellingham WA 98225",
    "addr:housenumber":"3968",
    "addr:postcode":"98225",
    "addr:street":"Bancroft Rd",
    "iso:country":"US",
    "sg:address":"3968 Bancroft Rd",
    "sg:city":"Bellingham",
    "sg:classifiers":[
        {
            "category":"Coffee & Tea",
            "type":"Food & Drink"
        },
        {
            "category":"Restaurant",
            "type":"Food & Drink"
        }
    ],
    "sg:phone":"+1 360 671 7015",
    "sg:postcode":"98225",
    "sg:province":"WA",
    "sg:tags":[
        "espresso"
    ],
    "wof:name":"Java Town Espresso",
    "wof:placetype":"venue"
},
  "geometry": {"coordinates":[-122.556173,48.786287],"type":"Point"}
}