{
  "type": "Feature",
  "properties": {
    "addr:full":"6718 172nd Pl SW Edmonds WA 98026",
    "addr:housenumber":"6718",
    "addr:postcode":"98026",
    "addr:street":"172Nd Pl Sw",
    "iso:country":"US",
    "sg:address":"6718 172nd Pl SW",
    "sg:city":"Edmonds",
    "sg:classifiers":[
        {
            "category":"Retail",
            "subcategory":"Portrait Studio",
            "type":"Services"
        }
    ],
    "sg:phone":"+1 425 742 3026",
    "sg:postcode":"98026",
    "sg:province":"WA",
    "sg:tags":[
        "photo"
    ],
    "wof:name":"Steve Lew Photography",
    "wof:placetype":"venue"
},
  "geometry": {"coordinates":[-122.323267,47.842527],"type":"Point"}
}