{
  "type": "Feature",
  "properties": {
    "addr:full":"951 Water St Port Townsend WA 98368",
    "addr:housenumber":"951",
    "addr:postcode":"98368",
    "addr:street":"Water St",
    "iso:country":"US",
    "sg:address":"951 Water St",
    "sg:city":"Port Townsend",
    "sg:classifiers":[
        {
            "category":"Restaurant",
            "type":"Food & Drink"
        }
    ],
    "sg:phone":"+1 360 385 6629",
    "sg:postcode":"98368",
    "sg:province":"WA",
    "sg:tags":[
        "eating",
        "pizza"
    ],
    "wof:name":"Waterfront Pizza Inc",
    "wof:placetype":"venue"
},
  "geometry": {"coordinates":[-122.756828,48.114136],"type":"Point"}
}