{
  "type": "Feature",
  "properties": {
    "addr:full":"16714 122nd Pl NE Bothell WA 98011",
    "addr:housenumber":"16714",
    "addr:postcode":"98011",
    "addr:street":"122Nd Pl Ne",
    "iso:country":"US",
    "sg:address":"16714 122nd Pl NE",
    "sg:city":"Bothell",
    "sg:classifiers":[
        {
            "category":"Health Services",
            "subcategory":"Clinic",
            "type":"Services"
        }
    ],
    "sg:phone":"+1 425 444 6081",
    "sg:postcode":"98011",
    "sg:province":"WA",
    "sg:tags":[
        "home",
        "care"
    ],
    "wof:name":"Cherry Hill Afh",
    "wof:placetype":"venue"
},
  "geometry": {"coordinates":[-122.1781,47.749559],"type":"Point"}
}