{
  "type": "Feature",
  "properties": {
    "addr:full":"14237 Des Moines Memorial Burien WA 98168",
    "addr:housenumber":"14237",
    "addr:postcode":"98168",
    "addr:street":"Des Moines",
    "iso:country":"US",
    "sg:address":"14237 Des Moines Memorial",
    "sg:city":"Burien",
    "sg:classifiers":[
        {
            "category":"Education",
            "subcategory":"School",
            "type":"Public Place"
        }
    ],
    "sg:phone":"+1 206 246 8433",
    "sg:postcode":"98168",
    "sg:province":"WA",
    "sg:tags":[
        "high",
        "middle",
        "elementary"
    ],
    "wof:name":"Burien Adventist School",
    "wof:placetype":"venue"
},
  "geometry": {"coordinates":[-122.314998,47.475582],"type":"Point"}
}