{
  "type": "Feature",
  "properties": {
    "addr:full":"3242 NW 20th Cir Camas WA 98607",
    "addr:housenumber":"3242",
    "addr:postcode":"98607",
    "addr:street":"Nw 20Th Cir",
    "iso:country":"US",
    "sg:address":"3242 NW 20th Cir",
    "sg:city":"Camas",
    "sg:classifiers":[
        {
            "category":"Professional",
            "subcategory":"Computer Services",
            "type":"Services"
        }
    ],
    "sg:phone":"+1 360 834 2458",
    "sg:postcode":"98607",
    "sg:province":"WA",
    "sg:tags":[
        "development",
        "system"
    ],
    "wof:name":"Synchrony Inc",
    "wof:placetype":"venue"
},
  "geometry": {"coordinates":[-122.442583,45.593671],"type":"Point"}
}