{
  "type": "Feature",
  "properties": {
    "addr:full":"17803 196th Ave SE Renton WA 98058",
    "addr:housenumber":"17803",
    "addr:postcode":"98058",
    "addr:street":"196Th Ave Se",
    "iso:country":"US",
    "sg:address":"17803 196th Ave SE",
    "sg:city":"Renton",
    "sg:classifiers":[
        {
            "category":"Building & Trades",
            "subcategory":"Construction",
            "type":"Services"
        }
    ],
    "sg:phone":"+1 425 432 6964",
    "sg:postcode":"98058",
    "sg:province":"WA",
    "sg:tags":[
        "house"
    ],
    "wof:name":"Keiths Preferred Remodeling",
    "wof:placetype":"venue"
},
  "geometry": {"coordinates":[-122.07985499999999,47.439839],"type":"Point"}
}