{
  "type": "Feature",
  "properties": {
    "addr:full":"613 S Washington St Suite 102 Spokane WA 99204",
    "addr:housenumber":"613",
    "addr:postcode":"99204",
    "addr:street":"S Washington St Suite 102",
    "iso:country":"US",
    "sg:address":"613 S Washington St Suite 102",
    "sg:city":"Spokane",
    "sg:classifiers":[
        {
            "category":"Professional",
            "subcategory":"Lawyer & Legal Services",
            "type":"Services"
        }
    ],
    "sg:phone":"+1 509 326 5160",
    "sg:postcode":"99204",
    "sg:province":"WA",
    "sg:tags":[
        "attorney",
        "law",
        "bankruptcy"
    ],
    "sg:website":"http://www.jasoncouey.com",
    "wof:name":"Couey Jason B Attorney At Law",
    "wof:placetype":"venue"
},
  "geometry": {"coordinates":[-117.417959,47.649933],"type":"Point"}
}