{
  "type": "Feature",
  "properties": {
    "addr:full":"11328 NE 51st Cir Ofc Vancouver WA 98682",
    "addr:housenumber":"11328",
    "addr:postcode":"98682",
    "addr:street":"Ne 51St Cir",
    "iso:country":"US",
    "sg:address":"11328 NE 51st Cir Ofc",
    "sg:city":"Vancouver",
    "sg:classifiers":[
        {
            "category":"Real Estate",
            "subcategory":"Real Estate Operator",
            "type":"Services"
        }
    ],
    "sg:phone":"+1 360 604 5259",
    "sg:postcode":"98682",
    "sg:province":"WA",
    "sg:tags":[
        "apartment"
    ],
    "wof:name":"Springbrook Village Apartments",
    "wof:placetype":"venue"
},
  "geometry": {"coordinates":[-122.556,45.659],"type":"Point"}
}