{
  "type": "Feature",
  "properties": {
    "addr:full":"1424 4th Ave Seattle WA 98101",
    "addr:housenumber":"1424",
    "addr:postcode":"98101",
    "addr:street":"4Th Ave",
    "iso:country":"US",
    "sg:address":"1424 4th Ave",
    "sg:city":"Seattle",
    "sg:classifiers":[
        {
            "category":"Wholesale",
            "subcategory":"Jewelry",
            "type":"Manufacturing & Wholesale Goods"
        },
        {
            "category":"Mining & Drilling",
            "type":"Manufacturing & Wholesale Goods"
        }
    ],
    "sg:phone":"+1 206 903 0533",
    "sg:postcode":"98101",
    "sg:province":"WA",
    "sg:tags":[
        "diamonds-wholesale",
        "diamonds-industrial"
    ],
    "wof:name":"Vala U.S.A. Ltd",
    "wof:placetype":"venue"
},
  "geometry": {"coordinates":[-122.33600300000001,47.609435],"type":"Point"}
}