{
  "type": "Feature",
  "properties": {
    "addr:full":"1214 Centralia Ave Centralia WA 98531",
    "addr:housenumber":"1214",
    "addr:postcode":"98531",
    "addr:street":"Centralia Ave",
    "iso:country":"US",
    "sg:address":"1214 Centralia Ave",
    "sg:city":"Centralia",
    "sg:classifiers":[
        {
            "category":"Building & Trades",
            "subcategory":"Construction",
            "type":"Services"
        }
    ],
    "sg:phone":"+1 360 736 7377",
    "sg:postcode":"98531",
    "sg:province":"WA",
    "sg:tags":[
        "roofing",
        "contractor"
    ],
    "wof:name":"ARC",
    "wof:placetype":"venue"
},
  "geometry": {"coordinates":[-122.952624,46.70212],"type":"Point"}
}