{
  "type": "Feature",
  "properties": {
    "addr:full":"1606 Simpson Ave Aberdeen WA 98520",
    "addr:housenumber":"1606",
    "addr:postcode":"98520",
    "addr:street":"Simpson Ave",
    "iso:country":"US",
    "sg:address":"1606 Simpson Ave",
    "sg:city":"Aberdeen",
    "sg:classifiers":[
        {
            "category":"Health Services",
            "subcategory":"Doctor",
            "type":"Services"
        }
    ],
    "sg:phone":"+1 360 533 4442",
    "sg:postcode":"98520",
    "sg:province":"WA",
    "sg:tags":[
        "physician",
        "surgeon",
        "medical"
    ],
    "wof:name":"Harbor Medical Assoc",
    "wof:placetype":"venue"
},
  "geometry": {"coordinates":[-123.83620000000001,46.975167],"type":"Point"}
}