{
  "type": "Feature",
  "properties": {
    "addr:full":"6920 Pioneer Hwy Stanwood WA 98292",
    "addr:housenumber":"6920",
    "addr:postcode":"98292",
    "addr:street":"Pioneer Hwy",
    "iso:country":"US",
    "sg:address":"6920 Pioneer Hwy",
    "sg:city":"Stanwood",
    "sg:classifiers":[
        {
            "category":"Professional",
            "subcategory":"Lawyer & Legal Services",
            "type":"Services"
        }
    ],
    "sg:phone":"+1 360 629 3684",
    "sg:postcode":"98292",
    "sg:province":"WA",
    "sg:tags":[
        "health"
    ],
    "wof:name":"Raneri Jlia C Lcensed Attorney",
    "wof:placetype":"venue"
},
  "geometry": {"coordinates":[-122.32729999999999,48.231884],"type":"Point"}
}