{
  "type": "Feature",
  "properties": {
    "addr:full":"4624 Rd Q SW Quincy WA 98848",
    "addr:postcode":"4624;98848",
    "addr:street":"Rd Q Sw",
    "iso:country":"US",
    "sg:address":"4624 Rd Q SW",
    "sg:city":"Quincy",
    "sg:phone":"+1 509 785 2835",
    "sg:postcode":"98848",
    "sg:province":"WA",
    "sg:tags":[
        "farm",
        "field",
        "crop"
    ],
    "wof:name":"Bunch Acres",
    "wof:placetype":"venue"
},
  "geometry": {"coordinates":[-119.85578,47.020646],"type":"Point"}
}