{
  "type": "Feature",
  "properties": {
    "iso:country":"US",
    "sg:address":"5206 1st Ave NW",
    "sg:city":"Seattle",
    "sg:classifiers":[
        {
            "category":"Retail",
            "subcategory":"Portrait Studio",
            "type":"Services"
        }
    ],
    "sg:phone":"+1 206 784 9320",
    "sg:postcode":"98107",
    "sg:province":"WA",
    "sg:tags":[
        "photo"
    ],
    "wof:name":"Don Zemke Photography",
    "wof:placetype":"venue"
},
  "geometry": {"coordinates":[-122.357305,47.667231],"type":"Point"}
}