{
  "type": "Feature",
  "properties": {
    "addr:full":"8510 SE 79th Pl Mercer Island WA 98040",
    "addr:housenumber":"8510",
    "addr:postcode":"98040",
    "addr:street":"Se 79Th Pl",
    "iso:country":"US",
    "sg:address":"8510 SE 79th Pl",
    "sg:city":"Mercer Island",
    "sg:classifiers":[
        {
            "category":"Banks & Credit Unions",
            "subcategory":"Bank",
            "type":"Services"
        }
    ],
    "sg:phone":"+1 206 232 3597",
    "sg:postcode":"98040",
    "sg:province":"WA",
    "sg:tags":[
        "federal",
        "savings",
        "institution"
    ],
    "wof:name":"Talmans Training",
    "wof:placetype":"venue"
},
  "geometry": {"coordinates":[-122.225154,47.532345],"type":"Point"}
}