{
  "type": "Feature",
  "properties": {
    "addr:full":"126 NW Canal Street suite 220 Seattle WA 98107",
    "addr:housenumber":"126",
    "addr:postcode":"98107",
    "addr:street":"Nw Canal Street Suite 220",
    "iso:country":"US",
    "sg:address":"126 NW Canal Street suite 220",
    "sg:city":"Seattle",
    "sg:classifiers":[
        {
            "category":"Personal",
            "subcategory":"Massage",
            "type":"Services"
        },
        {
            "category":"Health Services",
            "subcategory":"Health Practitioner",
            "type":"Services"
        }
    ],
    "sg:phone":"+1 206 547 1104",
    "sg:postcode":"98107",
    "sg:province":"WA",
    "sg:tags":[
        "acupuncture"
    ],
    "sg:website":"www.chopstixacupuncture.com",
    "wof:name":"Chopstix-Acupuncture Christian Hunt",
    "wof:placetype":"venue"
},
  "geometry": {"coordinates":[-122.35909100000001,47.652637],"type":"Point"}
}