{
  "type": "Feature",
  "properties": {
    "addr:full":"515 W Sprague Ave Spokane WA 99201",
    "addr:housenumber":"515",
    "addr:postcode":"99201",
    "addr:street":"W Sprague Ave",
    "iso:country":"US",
    "sg:address":"515 W Sprague Ave",
    "sg:city":"Spokane",
    "sg:classifiers":[
        {
            "category":"Restaurant",
            "type":"Food & Drink"
        }
    ],
    "sg:phone":"+1 509 838 6308",
    "sg:postcode":"99201",
    "sg:province":"WA",
    "sg:tags":[
        "eating"
    ],
    "wof:name":"Cavanaugh Hospitaitly",
    "wof:placetype":"venue"
},
  "geometry": {"coordinates":[-117.420923,47.657134],"type":"Point"}
}