{
  "type": "Feature",
  "properties": {
    "addr:full":"1240 Commerce Ave Longview WA 98632",
    "addr:housenumber":"1240",
    "addr:postcode":"98632",
    "addr:street":"Commerce Ave",
    "iso:country":"US",
    "sg:address":"1240 Commerce Ave",
    "sg:city":"Longview",
    "sg:classifiers":[
        {
            "category":"Professional",
            "type":"Services"
        }
    ],
    "sg:phone":"+1 360 261 6291",
    "sg:postcode":"98632",
    "sg:province":"WA",
    "wof:name":"Sabotage",
    "wof:placetype":"venue"
},
  "geometry": {"coordinates":[-122.93455,46.136358],"type":"Point"}
}