{
  "type": "Feature",
  "properties": {
    "addr:full":"2044 6th Ave Tacoma WA 98403",
    "addr:housenumber":"2044",
    "addr:postcode":"98403",
    "addr:street":"6Th Ave",
    "iso:country":"US",
    "sg:address":"2044 6th Ave",
    "sg:city":"Tacoma",
    "sg:classifiers":[
        {
            "category":"Wholesale",
            "subcategory":"Machinery & Supplies",
            "type":"Manufacturing & Wholesale Goods"
        }
    ],
    "sg:phone":"+1 253 272 4550",
    "sg:postcode":"98403",
    "sg:province":"WA",
    "sg:tags":[
        "pipe",
        "sales"
    ],
    "wof:name":"Genco Sales",
    "wof:placetype":"venue"
},
  "geometry": {"coordinates":[-122.465451,47.255381],"type":"Point"}
}