{
  "type": "Feature",
  "properties": {
    "addr:full":"475 E 19th St Tacoma WA 98421",
    "addr:housenumber":"475",
    "addr:postcode":"98421",
    "addr:street":"E 19Th St",
    "iso:country":"US",
    "sg:address":"475 E 19th St",
    "sg:city":"Tacoma",
    "sg:classifiers":[
        {
            "category":"Food & Beverages",
            "subcategory":"Groceries & Convenience Stores",
            "type":"Retail Goods"
        }
    ],
    "sg:phone":"+1 253 404 4166",
    "sg:postcode":"98421",
    "sg:province":"WA",
    "sg:tags":[
        "grocer"
    ],
    "sg:website":"www.supervalu.com",
    "wof:name":"Supervalu",
    "wof:placetype":"venue"
},
  "geometry": {"coordinates":[-122.42525999999999,47.246091],"type":"Point"}
}