{
  "type": "Feature",
  "properties": {
    "addr:full":"431 Ave H Snohomish WA 98290",
    "addr:housenumber":"431",
    "addr:postcode":"98290",
    "addr:street":"Ave H",
    "iso:country":"US",
    "sg:address":"431 Ave H",
    "sg:city":"Snohomish",
    "sg:classifiers":[
        {
            "category":"Professional",
            "type":"Services"
        }
    ],
    "sg:phone":"+1 360 568 6676",
    "sg:postcode":"98290",
    "sg:province":"WA",
    "wof:name":"Vicki Lynn Shearer",
    "wof:placetype":"venue"
},
  "geometry": {"coordinates":[-122.103661,47.917256],"type":"Point"}
}