{
  "type": "Feature",
  "properties": {
    "addr:full":"48 Crumbacher Rd Tonasket WA 98855",
    "addr:housenumber":"48",
    "addr:postcode":"98855",
    "addr:street":"Crumbacher Rd",
    "iso:country":"US",
    "sg:address":"48 Crumbacher Rd",
    "sg:city":"Tonasket",
    "sg:classifiers":[
        {
            "category":"Retail",
            "subcategory":"Auto Repair",
            "type":"Services"
        }
    ],
    "sg:phone":"+1 509 422 2702",
    "sg:postcode":"98855",
    "sg:province":"WA",
    "sg:tags":[
        "lube",
        "oil"
    ],
    "wof:name":"Rustys Mobile Lube and Oil",
    "wof:placetype":"venue"
},
  "geometry": {"coordinates":[-119.514089,48.588862],"type":"Point"}
}