{
  "type": "Feature",
  "properties": {
    "addr:full":"10500 NE 8th St Suite B1 #731 Bellevue WA 98004",
    "addr:housenumber":"10500",
    "addr:postcode":"98004",
    "addr:street":"Ne 8Th St Suite B1 # 731",
    "iso:country":"US",
    "sg:address":"10500 NE 8th St Suite B1 #731",
    "sg:city":"Bellevue",
    "sg:classifiers":[
        {
            "category":"Building & Trades",
            "subcategory":"Construction",
            "type":"Services"
        }
    ],
    "sg:phone":"+1 425 250 8720",
    "sg:postcode":"98004",
    "sg:province":"WA",
    "sg:tags":[
        "contractor"
    ],
    "sg:website":"www.ieola.com/home/siding/wa/bel...",
    "wof:name":"Emerald State Siding",
    "wof:placetype":"venue"
},
  "geometry": {"coordinates":[-122.20052,47.617842],"type":"Point"}
}