{
  "type": "Feature",
  "properties": {
    "addr:full":"4170 148th Ave NE Redmond WA 98052",
    "addr:housenumber":"4170",
    "addr:postcode":"98052",
    "addr:street":"148Th Ave Ne",
    "iso:country":"US",
    "sg:address":"4170 148th Ave NE",
    "sg:city":"Redmond",
    "sg:classifiers":[
        {
            "category":"Wholesale",
            "subcategory":"Machinery & Supplies",
            "type":"Manufacturing & Wholesale Goods"
        }
    ],
    "sg:phone":"+1 425 881 1200",
    "sg:postcode":"98052",
    "sg:province":"WA",
    "sg:tags":[
        "equipment",
        "industrial"
    ],
    "wof:name":"Production Machine Tools Inc",
    "wof:placetype":"venue"
},
  "geometry": {"coordinates":[-122.142984,47.645981],"type":"Point"}
}