{
  "type": "Feature",
  "properties": {
    "addr:full":"28335 NE 138th Pl Duvall WA 98019",
    "addr:housenumber":"28335",
    "addr:postcode":"98019",
    "addr:street":"Ne 138Th Pl",
    "iso:country":"US",
    "sg:address":"28335 NE 138th Pl",
    "sg:city":"Duvall",
    "sg:classifiers":[
        {
            "category":"Professional",
            "subcategory":"Computer Services",
            "type":"Services"
        }
    ],
    "sg:phone":"+1 425 844 8252",
    "sg:postcode":"98019",
    "sg:province":"WA",
    "sg:tags":[
        "related"
    ],
    "wof:name":"Wyndham Development",
    "wof:placetype":"venue"
},
  "geometry": {"coordinates":[-121.960037,47.723453],"type":"Point"}
}