{
  "type": "Feature",
  "properties": {
    "addr:full":"4464 Fremont Ave N Seattle WA 98103",
    "addr:housenumber":"4464",
    "addr:postcode":"98103",
    "addr:street":"Fremont Ave N",
    "iso:country":"US",
    "sg:address":"4464 Fremont Ave N",
    "sg:city":"Seattle",
    "sg:classifiers":[
        {
            "category":"Health Services",
            "subcategory":"Doctor",
            "type":"Services"
        }
    ],
    "sg:phone":"+1 206 267 7300",
    "sg:postcode":"98103",
    "sg:province":"WA",
    "sg:tags":[
        "dentist"
    ],
    "wof:name":"Fremont Family Dentistry Pllc",
    "wof:placetype":"venue"
},
  "geometry": {"coordinates":[-122.349965,47.66121],"type":"Point"}
}