{
  "type": "Feature",
  "properties": {
    "addr:full":"4646 144th Pl SE Bellevue WA 98006",
    "addr:housenumber":"4646",
    "addr:postcode":"98006",
    "addr:street":"144Th Pl Se",
    "iso:country":"US",
    "sg:address":"4646 144th Pl SE",
    "sg:city":"Bellevue",
    "sg:classifiers":[
        {
            "category":"Real Estate",
            "subcategory":"Real Estate Agent",
            "type":"Services"
        }
    ],
    "sg:phone":"+1 425 644 2224",
    "sg:postcode":"98006",
    "sg:province":"WA",
    "wof:name":"Tuazons Properties LLC",
    "wof:placetype":"venue"
},
  "geometry": {"coordinates":[-122.14795700000001,47.561963],"type":"Point"}
}