{
  "type": "Feature",
  "properties": {
    "addr:full":"188 Hansen Ln Woodland WA 98674",
    "addr:housenumber":"188",
    "addr:postcode":"98674",
    "addr:street":"Hansen Ln",
    "iso:country":"US",
    "sg:address":"188 Hansen Ln",
    "sg:city":"Woodland",
    "sg:classifiers":[
        {
            "category":"Organizations",
            "subcategory":"Religious Organization",
            "type":"Services"
        }
    ],
    "sg:phone":"+1 360 225 9551",
    "sg:postcode":"98674",
    "sg:province":"WA",
    "sg:tags":[
        "church"
    ],
    "wof:name":"Woodland Seventh-Day Adventist",
    "wof:placetype":"venue"
},
  "geometry": {"coordinates":[-122.743779,45.908807],"type":"Point"}
}