{
  "type": "Feature",
  "properties": {
    "addr:full":"2851 152nd Ave NE Redmond WA 98052",
    "addr:housenumber":"2851",
    "addr:postcode":"98052",
    "addr:street":"152Nd Ave Ne",
    "iso:country":"US",
    "sg:address":"2851 152nd Ave NE",
    "sg:city":"Redmond",
    "sg:classifiers":[
        {
            "category":"Professional",
            "subcategory":"Accounting & Tax Preparation",
            "type":"Services"
        }
    ],
    "sg:phone":"+1 425 883 6767",
    "sg:postcode":"98052",
    "sg:province":"WA",
    "sg:tags":[
        "accountant"
    ],
    "wof:name":"Janice K Berg CPA",
    "wof:placetype":"venue"
},
  "geometry": {"coordinates":[-122.137698,47.63657],"type":"Point"}
}