{
  "type": "Feature",
  "properties": {
    "addr:full":"8110 164th Ave NE Redmond WA 98052",
    "addr:housenumber":"8110",
    "addr:postcode":"98052",
    "addr:street":"164Th Ave Ne",
    "iso:country":"US",
    "sg:address":"8110 164th Ave NE",
    "sg:city":"Redmond",
    "sg:classifiers":[
        {
            "category":"Restaurant",
            "type":"Food & Drink"
        }
    ],
    "sg:phone":"+1 425 556 9838",
    "sg:postcode":"98052",
    "sg:province":"WA",
    "sg:tags":[
        "french"
    ],
    "sg:website":"www.countrygardenbistro.com",
    "wof:name":"Country Garden Bistro Inc",
    "wof:placetype":"venue"
},
  "geometry": {"coordinates":[-122.12153499999999,47.67662],"type":"Point"}
}