{
  "type": "Feature",
  "properties": {
    "addr:full":"210 N 85th St Seattle WA 98103",
    "addr:housenumber":"210",
    "addr:postcode":"98103",
    "addr:street":"N 85Th St",
    "iso:country":"US",
    "sg:address":"210 N 85th St",
    "sg:city":"Seattle",
    "sg:classifiers":[
        {
            "category":"Bars & Pubs",
            "type":"Food & Drink"
        }
    ],
    "sg:phone":"+1 206 789 1320",
    "sg:postcode":"98103",
    "sg:province":"WA",
    "wof:name":"Bombers LLC",
    "wof:placetype":"venue"
},
  "geometry": {"coordinates":[-122.35539300000001,47.690669],"type":"Point"}
}