{
  "type": "Feature",
  "properties": {
    "addr:full":"3410 1st St Union Gap WA 98903",
    "addr:housenumber":"3410",
    "addr:postcode":"98903",
    "addr:street":"1St St",
    "iso:country":"US",
    "sg:address":"3410 1st St",
    "sg:city":"Union Gap",
    "sg:classifiers":[
        {
            "category":"Organizations",
            "subcategory":"Religious Organization",
            "type":"Services"
        }
    ],
    "sg:phone":"+1 509 453 0047",
    "sg:postcode":"98903",
    "sg:province":"WA",
    "sg:tags":[
        "church"
    ],
    "wof:name":"Oldtown Gateway Assembly",
    "wof:placetype":"venue"
},
  "geometry": {"coordinates":[-120.476645,46.553051],"type":"Point"}
}