{
  "type": "Feature",
  "properties": {
    "addr:full":"46255 6th Ave SW Seattle WA 98146",
    "addr:housenumber":"46255",
    "addr:postcode":"98146",
    "addr:street":"6Th Ave Sw",
    "iso:country":"US",
    "sg:address":"46255 6th Ave SW",
    "sg:city":"Seattle",
    "sg:classifiers":[
        {
            "category":"Manufacturing",
            "subcategory":"Rubber & Plastics",
            "type":"Manufacturing & Wholesale Goods"
        }
    ],
    "sg:phone":"+1 206 937 5398",
    "sg:postcode":"98146",
    "sg:province":"WA",
    "sg:tags":[
        "stamp"
    ],
    "wof:name":"Gemmanna Stamps",
    "wof:placetype":"venue"
},
  "geometry": {"coordinates":[-122.341938,47.506899],"type":"Point"}
}