{
  "type": "Feature",
  "properties": {
    "iso:country":"US",
    "sg:address":"1157 Commerce Ave",
    "sg:city":"Longview",
    "sg:classifiers":[
        {
            "category":"Education",
            "subcategory":"School",
            "type":"Public Place"
        }
    ],
    "sg:phone":"+1 360 575 1234",
    "sg:postcode":"98632",
    "sg:province":"WA",
    "wof:name":"Kinderland Academy & Educare",
    "wof:placetype":"venue"
},
  "geometry": {"coordinates":[-122.935427,46.134463],"type":"Point"}
}