{
  "type": "Feature",
  "properties": {
    "addr:full":"6828 19th St W University Place WA 98466",
    "addr:housenumber":"6828",
    "addr:postcode":"98466",
    "addr:street":"19Th St W;Place",
    "iso:country":"US",
    "sg:address":"6828 19th St W",
    "sg:city":"University Place",
    "sg:classifiers":[
        {
            "category":"Restaurant",
            "type":"Food & Drink"
        }
    ],
    "sg:phone":"+1 253 566 9208",
    "sg:postcode":"98466",
    "sg:province":"WA",
    "wof:name":"Ginza Teriyaki",
    "wof:placetype":"venue"
},
  "geometry": {"coordinates":[-122.52905699999999,47.242627],"type":"Point"}
}