{
  "type": "Feature",
  "properties": {
    "addr:full":"8315 Lake City Way NE Seattle WA 98115",
    "addr:housenumber":"8315",
    "addr:postcode":"98115",
    "addr:street":"Lake City Way Ne",
    "iso:country":"US",
    "sg:address":"8315 Lake City Way NE",
    "sg:city":"Seattle",
    "sg:classifiers":[
        {
            "category":"Building & Trades",
            "subcategory":"Construction",
            "type":"Services"
        }
    ],
    "sg:phone":"+1 206 898 6840",
    "sg:postcode":"98115",
    "sg:province":"WA",
    "sg:tags":[
        "house"
    ],
    "wof:name":"Antibes Const Co",
    "wof:placetype":"venue"
},
  "geometry": {"coordinates":[-122.30914900000001,47.689682],"type":"Point"}
}