{
  "type": "Feature",
  "properties": {
    "addr:full":"11040 19th Ave NE Seattle WA 98125",
    "addr:housenumber":"11040",
    "addr:postcode":"98125",
    "addr:street":"19Th Ave Ne",
    "iso:country":"US",
    "sg:address":"11040 19th Ave NE",
    "sg:city":"Seattle",
    "sg:classifiers":[
        {
            "category":"Professional",
            "subcategory":"Computer Services",
            "type":"Services"
        }
    ],
    "sg:phone":"+1 206 364 4498",
    "sg:postcode":"98125",
    "sg:province":"WA",
    "sg:tags":[
        "home",
        "consulting",
        "page",
        "dev",
        "internet"
    ],
    "wof:name":"Angela Sheppard Web Design",
    "wof:placetype":"venue"
},
  "geometry": {"coordinates":[-122.308052,47.71007],"type":"Point"}
}