{
  "type": "Feature",
  "properties": {
    "addr:full":"10019 NE 26th St Vancouver WA 98662",
    "addr:housenumber":"10019",
    "addr:postcode":"98662",
    "addr:street":"Ne 26Th St",
    "iso:country":"US",
    "sg:address":"10019 NE 26th St",
    "sg:city":"Vancouver",
    "sg:classifiers":[
        {
            "category":"Building & Trades",
            "subcategory":"Plumbing",
            "type":"Services"
        }
    ],
    "sg:phone":"+1 360 896 2953",
    "sg:postcode":"98662",
    "sg:province":"WA",
    "sg:tags":[
        "air",
        "conditioning/hvac",
        "heating",
        "contractor"
    ],
    "sg:website":"www.clarkcountyhvac.com",
    "wof:name":"Comfort Plus Heating",
    "wof:placetype":"venue"
},
  "geometry": {"coordinates":[-122.569596,45.640941],"type":"Point"}
}