{
  "type": "Feature",
  "properties": {
    "addr:full":"5809 24th Ave NW Seattle WA 98107",
    "addr:housenumber":"5809",
    "addr:postcode":"98107",
    "addr:street":"24Th Ave Nw",
    "iso:country":"US",
    "sg:address":"5809 24th Ave NW",
    "sg:city":"Seattle",
    "sg:classifiers":[
        {
            "category":"Restaurant",
            "type":"Food & Drink"
        }
    ],
    "sg:phone":"+1 206 420 3737",
    "sg:postcode":"98107",
    "sg:province":"WA",
    "sg:tags":[
        "sushi",
        "bar",
        "japanese"
    ],
    "sg:website":"www.oshansushi.com",
    "wof:name":"O'Shan Sushi",
    "wof:placetype":"venue"
},
  "geometry": {"coordinates":[-122.387889,47.671428],"type":"Point"}
}