{
  "type": "Feature",
  "properties": {
    "addr:full":"7406 Delaware Ln Vancouver WA 98664",
    "addr:housenumber":"7406",
    "addr:postcode":"98664",
    "addr:street":"Delaware Ln",
    "iso:country":"US",
    "sg:address":"7406 Delaware Ln",
    "sg:city":"Vancouver",
    "sg:classifiers":[
        {
            "category":"Arts & Performance",
            "subcategory":"Arts Center",
            "type":"Entertainment"
        }
    ],
    "sg:phone":"+1 360 694 1192",
    "sg:postcode":"98664",
    "sg:province":"WA",
    "sg:tags":[
        "performing"
    ],
    "wof:name":"Dance Art",
    "wof:placetype":"venue"
},
  "geometry": {"coordinates":[-122.595001,45.6241],"type":"Point"}
}