{
  "type": "Feature",
  "properties": {
    "addr:full":"2221 Oak Rd Lynnwood WA 98087",
    "addr:housenumber":"2221",
    "addr:postcode":"98087",
    "addr:street":"Oak Rd",
    "iso:country":"US",
    "sg:address":"2221 Oak Rd",
    "sg:city":"Lynnwood",
    "sg:classifiers":[
        {
            "category":"Home & Garden",
            "subcategory":"Carpets & Floor Coverings",
            "type":"Retail Goods"
        }
    ],
    "sg:phone":"+1 425 742 6758",
    "sg:postcode":"98087",
    "sg:province":"WA",
    "wof:name":"Alpine House Carpet Inc",
    "wof:placetype":"venue"
},
  "geometry": {"coordinates":[-122.263825,47.857455],"type":"Point"}
}