{
  "type": "Feature",
  "properties": {
    "addr:full":"1730 Front St Lynden WA 98264",
    "addr:housenumber":"1730",
    "addr:postcode":"98264",
    "addr:street":"Front St",
    "iso:country":"US",
    "sg:address":"1730 Front St",
    "sg:city":"Lynden",
    "sg:classifiers":[
        {
            "category":"Home & Garden",
            "subcategory":"Furniture",
            "type":"Retail Goods"
        }
    ],
    "sg:phone":"+1 360 354 4724",
    "sg:postcode":"98264",
    "sg:province":"WA",
    "sg:tags":[
        "floor"
    ],
    "wof:name":"Fairway Country Furnishings",
    "wof:placetype":"venue"
},
  "geometry": {"coordinates":[-122.470288,48.939523],"type":"Point"}
}