{
  "type": "Feature",
  "properties": {
    "addr:full":"7311 Coal Creek Pkwy SE Renton WA 98059",
    "addr:housenumber":"7311",
    "addr:postcode":"98059",
    "addr:street":"Coal Creek Pkwy Se",
    "iso:country":"US",
    "sg:address":"7311 Coal Creek Pkwy SE",
    "sg:city":"Renton",
    "sg:classifiers":[
        {
            "category":"Personal",
            "type":"Services"
        }
    ],
    "sg:phone":"+1 253 797 0157",
    "sg:postcode":"98059",
    "sg:province":"WA",
    "wof:name":"Sportassage",
    "wof:placetype":"venue"
},
  "geometry": {"coordinates":[-122.16456700000001,47.536083],"type":"Point"}
}