{
  "type": "Feature",
  "properties": {
    "addr:full":"9395 Linder Way NW Silverdale WA 98383",
    "addr:housenumber":"9395",
    "addr:postcode":"98383",
    "addr:street":"Linder Way Nw",
    "iso:country":"US",
    "sg:address":"9395 Linder Way NW",
    "sg:city":"Silverdale",
    "sg:classifiers":[
        {
            "category":"Social Services",
            "type":"Services"
        }
    ],
    "sg:phone":"+1 360 698 1321",
    "sg:postcode":"98383",
    "sg:province":"WA",
    "sg:tags":[
        "counselor",
        "marriage",
        "family"
    ],
    "wof:name":"Boltwood & Rommen",
    "wof:placetype":"venue"
},
  "geometry": {"coordinates":[-122.695317,47.647304],"type":"Point"}
}