{
  "type": "Feature",
  "properties": {
    "addr:full":"912 Yakima Ave Prosser WA 99350",
    "addr:housenumber":"912",
    "addr:postcode":"99350",
    "addr:street":"Yakima Ave",
    "iso:country":"US",
    "sg:address":"912 Yakima Ave",
    "sg:city":"Prosser",
    "sg:classifiers":[
        {
            "category":"Organizations",
            "subcategory":"Religious Organization",
            "type":"Services"
        }
    ],
    "sg:phone":"+1 509 786 1594",
    "sg:postcode":"99350",
    "sg:province":"WA",
    "sg:tags":[
        "place",
        "worship",
        "church"
    ],
    "wof:name":"First Presbyterian Church",
    "wof:placetype":"venue"
},
  "geometry": {"coordinates":[-119.77256,46.202068],"type":"Point"}
}