{
  "type": "Feature",
  "properties": {
    "addr:full":"36009 NE 31st Ave La Center WA 98629",
    "addr:housenumber":"36009",
    "addr:postcode":"98629",
    "addr:street":"Ne 31St Ave",
    "iso:country":"US",
    "sg:address":"36009 NE 31st Ave",
    "sg:city":"La Center",
    "sg:classifiers":[
        {
            "category":"Home & Garden",
            "subcategory":"Garden Supply",
            "type":"Retail Goods"
        }
    ],
    "sg:phone":"+1 360 263 1505",
    "sg:postcode":"98629",
    "sg:province":"WA",
    "wof:name":"Dutch Tuch Acres Nursery",
    "wof:placetype":"venue"
},
  "geometry": {"coordinates":[-122.63933400000001,45.878127],"type":"Point"}
}