{
  "type": "Feature",
  "properties": {
    "addr:full":"21724 3rd Ave SE Bothell WA 98021",
    "addr:housenumber":"21724",
    "addr:postcode":"98021",
    "addr:street":"3Rd Ave Se",
    "iso:country":"US",
    "sg:address":"21724 3rd Ave SE",
    "sg:city":"Bothell",
    "sg:classifiers":[
        {
            "category":"Professional",
            "subcategory":"Engineering",
            "type":"Services"
        }
    ],
    "sg:phone":"+1 425 486 0123",
    "sg:postcode":"98021",
    "sg:province":"WA",
    "wof:name":"Product Development Processes",
    "wof:placetype":"venue"
},
  "geometry": {"coordinates":[-122.22771,47.800989],"type":"Point"}
}