{
  "type": "Feature",
  "properties": {
    "iso:country":"US",
    "sg:address":"6475 Seabeck Hwy NW",
    "sg:city":"Bremerton",
    "sg:classifiers":[
        {
            "category":"Education",
            "subcategory":"Special Training",
            "type":"Public Place"
        }
    ],
    "sg:phone":"+1 360 479 5964",
    "sg:postcode":"98312",
    "sg:province":"WA",
    "wof:name":"Kevin F Plymate",
    "wof:placetype":"venue"
},
  "geometry": {"coordinates":[-122.76791799999999,47.629633],"type":"Point"}
}