{
  "type": "Feature",
  "properties": {
    "addr:full":"9247 124th Ave NE Kirkland WA 98033",
    "addr:housenumber":"9247",
    "addr:postcode":"98033",
    "addr:street":"124Th Ave Ne",
    "iso:country":"US",
    "sg:address":"9247 124th Ave NE",
    "sg:city":"Kirkland",
    "sg:classifiers":[
        {
            "category":"Home & Garden",
            "subcategory":"Home Furnishings",
            "type":"Retail Goods"
        }
    ],
    "sg:phone":"+1 425 889 7438",
    "sg:postcode":"98033",
    "sg:province":"WA",
    "wof:name":"Burning Bright",
    "wof:placetype":"venue"
},
  "geometry": {"coordinates":[-122.17604799999999,47.685167],"type":"Point"}
}