{
  "type": "Feature",
  "properties": {
    "addr:full":"4728 SW 244th St Vashon WA 98070",
    "addr:housenumber":"4728",
    "addr:postcode":"98070",
    "addr:street":"Sw 244Th St",
    "iso:country":"US",
    "sg:address":"4728 SW 244th St",
    "sg:city":"Vashon",
    "sg:classifiers":[
        {
            "category":"Real Estate",
            "subcategory":"Real Estate Services",
            "type":"Services"
        },
        {
            "category":"Real Estate",
            "subcategory":"Real Estate Agent",
            "type":"Services"
        }
    ],
    "sg:phone":"+1 206 463 7216",
    "sg:postcode":"98070",
    "sg:province":"WA",
    "sg:tags":[
        "management"
    ],
    "wof:name":"Nurik Limited",
    "wof:placetype":"venue"
},
  "geometry": {"coordinates":[-122.39008800000001,47.38553],"type":"Point"}
}