{
  "type": "Feature",
  "properties": {
    "addr:full":"7321 Greenwood Ave N Seattle WA 98103",
    "addr:housenumber":"7321",
    "addr:postcode":"98103",
    "addr:street":"Greenwood Ave N",
    "iso:country":"US",
    "sg:address":"7321 Greenwood Ave N",
    "sg:city":"Seattle",
    "sg:classifiers":[
        {
            "category":"Shopping",
            "subcategory":"Clothing, Apparel, & Fashions",
            "type":"Retail Goods"
        },
        {
            "category":"Shopping",
            "subcategory":"Hobbies, Toys, & Games",
            "type":"Retail Goods"
        }
    ],
    "sg:phone":"+1 206 781 0138",
    "sg:postcode":"98103",
    "sg:province":"WA",
    "sg:tags":[
        "children's",
        "toy",
        "clothing",
        "store"
    ],
    "sg:website":"www.risingstarsseattle.com",
    "wof:name":"Rising Stars",
    "wof:placetype":"venue"
},
  "geometry": {"coordinates":[-122.35532499999999,47.682356],"type":"Point"}
}