{
  "type": "Feature",
  "properties": {
    "addr:full":"7900 SE 28th St Mercer Island WA 98040",
    "addr:housenumber":"7900",
    "addr:postcode":"98040",
    "addr:street":"Se 28Th St",
    "iso:country":"US",
    "sg:address":"7900 SE 28th St",
    "sg:city":"Mercer Island",
    "sg:classifiers":[
        {
            "category":"Real Estate",
            "subcategory":"Real Estate Services",
            "type":"Services"
        }
    ],
    "sg:phone":"+1 206 236 5648",
    "sg:postcode":"98040",
    "sg:province":"WA",
    "sg:tags":[
        "abstract",
        "title"
    ],
    "wof:name":"Transnation Title Insurance Co",
    "wof:placetype":"venue"
},
  "geometry": {"coordinates":[-122.232586,47.585567],"type":"Point"}
}