{
  "type": "Feature",
  "properties": {
    "addr:full":"371 Dahl Rd Yakima WA 98908",
    "addr:housenumber":"371",
    "addr:postcode":"98908",
    "addr:street":"Dahl Rd",
    "iso:country":"US",
    "sg:address":"371 Dahl Rd",
    "sg:city":"Yakima",
    "sg:classifiers":[
        {
            "category":"Farming",
            "subcategory":"Farm",
            "type":"Manufacturing & Wholesale Goods"
        }
    ],
    "sg:phone":"+1 509 966 0711",
    "sg:postcode":"98908",
    "sg:province":"WA",
    "wof:name":"Mazzola Farms",
    "wof:placetype":"venue"
},
  "geometry": {"coordinates":[-120.624601,46.636454],"type":"Point"}
}