{
  "type": "Feature",
  "properties": {
    "addr:full":"5725 Country Club Dr Langley WA 98260",
    "addr:housenumber":"5725",
    "addr:postcode":"98260",
    "addr:street":"Country Club Dr",
    "iso:country":"US",
    "sg:address":"5725 Country Club Dr",
    "sg:city":"Langley",
    "sg:classifiers":[
        {
            "category":"Retail",
            "subcategory":"Event Space",
            "type":"Services"
        },
        {
            "category":"Organizations",
            "subcategory":"Community Association",
            "type":"Services"
        },
        {
            "category":"Sports & Exercise",
            "subcategory":"Golf",
            "type":"Entertainment"
        }
    ],
    "sg:phone":"+1 360 321 5960",
    "sg:postcode":"98260",
    "sg:province":"WA",
    "sg:tags":[
        "facility",
        "club",
        "hall",
        "course",
        "courses-private",
        "reception",
        "banquet"
    ],
    "wof:name":"Useless Bay Country Club",
    "wof:placetype":"venue"
},
  "geometry": {"coordinates":[-122.48326900000001,48.003551],"type":"Point"}
}