{
  "type": "Feature",
  "properties": {
    "addr:full":"13555 SE 36th St Suite 280 Bellevue WA 98006",
    "addr:housenumber":"13555",
    "addr:postcode":"98006",
    "addr:street":"Se 36Th St Suite 280",
    "iso:country":"US",
    "sg:address":"13555 SE 36th St Suite 280",
    "sg:city":"Bellevue",
    "sg:classifiers":[
        {
            "category":"Communications",
            "type":"Services"
        }
    ],
    "sg:phone":"+1 425 614 4636",
    "sg:postcode":"98006",
    "sg:province":"WA",
    "sg:tags":[
        "medium",
        "mass"
    ],
    "sg:website":"10kinfo.com",
    "wof:name":"10kInfo",
    "wof:placetype":"venue"
},
  "geometry": {"coordinates":[-122.15928700000001,47.579405],"type":"Point"}
}