{
  "type": "Feature",
  "properties": {
    "addr:full":"921 Central Ave N Kent WA 98032",
    "addr:housenumber":"921",
    "addr:postcode":"98032",
    "addr:street":"Central Ave N",
    "iso:country":"US",
    "sg:address":"921 Central Ave N",
    "sg:city":"Kent",
    "sg:classifiers":[
        {
            "category":"Home & Garden",
            "subcategory":"Furniture",
            "type":"Retail Goods"
        },
        {
            "category":"Home & Garden",
            "subcategory":"Home Furnishings",
            "type":"Retail Goods"
        },
        {
            "category":"Home & Garden",
            "subcategory":"Carpets & Floor Coverings",
            "type":"Retail Goods"
        }
    ],
    "sg:phone":"+1 253 852 0300",
    "sg:postcode":"98032",
    "sg:province":"WA",
    "sg:tags":[
        "bedroom",
        "set",
        "store",
        "bed",
        "mattress"
    ],
    "wof:name":"Gallery Furniture & Design Ctr",
    "wof:placetype":"venue"
},
  "geometry": {"coordinates":[-122.23107899999999,47.390486],"type":"Point"}
}