{
  "type": "Feature",
  "properties": {
    "addr:full":"25905 Dockton Rd SW Vashon WA 98070",
    "addr:postcode":"25905;98070",
    "addr:street":"Dockton Rd Sw",
    "iso:country":"US",
    "sg:address":"25905 Dockton Rd SW",
    "sg:city":"Vashon",
    "sg:classifiers":[
        {
            "category":"Professional",
            "subcategory":"Lawyer & Legal Services",
            "type":"Services"
        }
    ],
    "sg:phone":"+1 206 463 4588",
    "sg:postcode":"98070",
    "sg:province":"WA",
    "wof:name":"Ferguson Law Offices Pllc",
    "wof:placetype":"venue"
},
  "geometry": {"coordinates":[-122.450822,47.371622],"type":"Point"}
}