{
  "type": "Feature",
  "properties": {
    "addr:full":"100 Custer Way SW Olympia WA 98501",
    "addr:housenumber":"100",
    "addr:postcode":"98501",
    "addr:street":"Custer Way Sw",
    "iso:country":"US",
    "sg:address":"100 Custer Way SW",
    "sg:city":"Olympia",
    "sg:classifiers":[
        {
            "category":"Manufacturing",
            "subcategory":"Food",
            "type":"Manufacturing & Wholesale Goods"
        }
    ],
    "sg:phone":"+1 360 357 6955",
    "sg:postcode":"98501",
    "sg:province":"WA",
    "sg:tags":[
        "liquor",
        "mfg"
    ],
    "wof:name":"Mark VII",
    "wof:placetype":"venue"
},
  "geometry": {"coordinates":[-122.90538599999999,47.016579],"type":"Point"}
}