{
  "type": "Feature",
  "properties": {
    "addr:full":"900 Poplar Pl S Seattle WA 98144",
    "addr:housenumber":"900",
    "addr:postcode":"98144",
    "addr:street":"Poplar Pl S",
    "iso:country":"US",
    "sg:address":"900 Poplar Pl S",
    "sg:city":"Seattle",
    "sg:classifiers":[
        {
            "category":"Building & Trades",
            "subcategory":"Construction",
            "type":"Services"
        }
    ],
    "sg:phone":"+1 206 498 8866",
    "sg:postcode":"98144",
    "sg:province":"WA",
    "sg:tags":[
        "house"
    ],
    "wof:name":"Baughs Construction",
    "wof:placetype":"venue"
},
  "geometry": {"coordinates":[-122.311785,47.594586],"type":"Point"}
}