{
  "type": "Feature",
  "properties": {
    "addr:full":"211 E Main St Everson WA 98247",
    "addr:housenumber":"211",
    "addr:postcode":"98247",
    "addr:street":"E Main St",
    "iso:country":"US",
    "sg:address":"211 E Main St",
    "sg:city":"Everson",
    "sg:classifiers":[
        {
            "category":"Health Services",
            "subcategory":"Clinic",
            "type":"Services"
        },
        {
            "category":"Health Services",
            "subcategory":"Chiropractor",
            "type":"Services"
        }
    ],
    "sg:phone":"+1 360 966 5844",
    "sg:postcode":"98247",
    "sg:province":"WA",
    "sg:tags":[
        "welfare",
        "chiropractic"
    ],
    "wof:name":"Bedlington Chiropractic Center",
    "wof:placetype":"venue"
},
  "geometry": {"coordinates":[-122.340357,48.920155],"type":"Point"}
}