{
  "type": "Feature",
  "properties": {
    "addr:full":"425 Caines St Friday Harbor WA 98250",
    "addr:housenumber":"425",
    "addr:postcode":"98250",
    "addr:street":"Caines St",
    "iso:country":"US",
    "sg:address":"425 Caines St",
    "sg:city":"Friday Harbor",
    "sg:classifiers":[
        {
            "category":"Professional",
            "subcategory":"Accounting & Tax Preparation",
            "type":"Services"
        }
    ],
    "sg:phone":"+1 360 378 2496",
    "sg:postcode":"98250",
    "sg:province":"WA",
    "sg:tags":[
        "auditing",
        "bookkeeping"
    ],
    "wof:name":"Kennedy McCulloch Cpas",
    "wof:placetype":"venue"
},
  "geometry": {"coordinates":[-123.019724,48.53204],"type":"Point"}
}