{
  "type": "Feature",
  "properties": {
    "addr:full":"2212 NW Market St Seattle WA 98107",
    "addr:housenumber":"2212",
    "addr:postcode":"98107",
    "addr:street":"Nw Market St",
    "iso:country":"US",
    "sg:address":"2212 NW Market St",
    "sg:city":"Seattle",
    "sg:classifiers":[
        {
            "category":"Home & Garden",
            "subcategory":"Home Furnishings",
            "type":"Retail Goods"
        },
        {
            "category":"Professional",
            "subcategory":"Art Services",
            "type":"Services"
        }
    ],
    "sg:phone":"+1 206 784 4761",
    "sg:postcode":"98107",
    "sg:province":"WA",
    "sg:tags":[
        "decor",
        "framing"
    ],
    "sg:website":"www.anniesartandframe.com",
    "wof:name":"Annie's Art and Frame",
    "wof:placetype":"venue"
},
  "geometry": {"coordinates":[-122.385002,47.6688],"type":"Point"}
}