{
  "type": "Feature",
  "properties": {
    "addr:full":"9121 80th Ave SW Lakewood WA 98498",
    "addr:housenumber":"9121",
    "addr:postcode":"98498",
    "addr:street":"80Th Ave Sw",
    "iso:country":"US",
    "sg:address":"9121 80th Ave SW",
    "sg:city":"Lakewood",
    "sg:classifiers":[
        {
            "category":"Building & Trades",
            "subcategory":"Construction",
            "type":"Services"
        }
    ],
    "sg:phone":"+1 253 582 5307",
    "sg:postcode":"98498",
    "sg:province":"WA",
    "sg:tags":[
        "house"
    ],
    "wof:name":"Harman Builders Development",
    "wof:placetype":"venue"
},
  "geometry": {"coordinates":[-122.543539,47.173741],"type":"Point"}
}