{
  "type": "Feature",
  "properties": {
    "addr:full":"4325 John Luhr Rd NE Olympia WA 98516",
    "addr:housenumber":"4325",
    "addr:postcode":"98516",
    "addr:street":"John Luhr Rd Ne",
    "iso:country":"US",
    "sg:address":"4325 John Luhr Rd NE",
    "sg:city":"Olympia",
    "sg:classifiers":[
        {
            "category":"Shopping",
            "subcategory":"Catalog Store",
            "type":"Retail Goods"
        }
    ],
    "sg:phone":"+1 360 491 1980",
    "sg:postcode":"98516",
    "sg:province":"WA",
    "sg:tags":[
        "mail",
        "house"
    ],
    "wof:name":"Fiber Arts",
    "wof:placetype":"venue"
},
  "geometry": {"coordinates":[-122.73099000000001,47.09617],"type":"Point"}
}