{
  "type": "Feature",
  "properties": {
    "addr:full":"3203 E Main Ave Spokane WA 99202",
    "addr:housenumber":"3203",
    "addr:postcode":"99202",
    "addr:street":"E Main Ave",
    "iso:country":"US",
    "sg:address":"3203 E Main Ave",
    "sg:city":"Spokane",
    "sg:classifiers":[
        {
            "category":"Manufacturing",
            "subcategory":"Glass & Minerals",
            "type":"Manufacturing & Wholesale Goods"
        }
    ],
    "sg:phone":"+1 509 535 4624",
    "sg:postcode":"99202",
    "sg:province":"WA",
    "sg:tags":[
        "hydraulic",
        "cement",
        "mfg"
    ],
    "wof:name":"Lafarge North America",
    "wof:placetype":"venue"
},
  "geometry": {"coordinates":[-117.362252,47.659191],"type":"Point"}
}