{
  "type": "Feature",
  "properties": {
    "addr:full":"23781 Montecarlo Pl NW Poulsbo WA 98370",
    "addr:housenumber":"23781",
    "addr:postcode":"98370",
    "addr:street":"Montecarlo Pl Nw",
    "iso:country":"US",
    "sg:address":"23781 Montecarlo Pl NW",
    "sg:city":"Poulsbo",
    "sg:classifiers":[
        {
            "category":"Manufacturing",
            "subcategory":"Watercraft",
            "type":"Manufacturing & Wholesale Goods"
        }
    ],
    "sg:phone":"+1 360 697 2179",
    "sg:postcode":"98370",
    "sg:province":"WA",
    "wof:name":"Mikkelborg Boat Works",
    "wof:placetype":"venue"
},
  "geometry": {"coordinates":[-122.672014,47.778155],"type":"Point"}
}