{
  "type": "Feature",
  "properties": {
    "addr:full":"5100 NE 38th Ave Vancouver WA 98661",
    "addr:housenumber":"5100",
    "addr:postcode":"98661",
    "addr:street":"Ne 38Th Ave",
    "iso:country":"US",
    "sg:address":"5100 NE 38th Ave",
    "sg:city":"Vancouver",
    "sg:classifiers":[
        {
            "category":"Professional",
            "type":"Services"
        }
    ],
    "sg:phone":"+1 360 750 1315",
    "sg:postcode":"98661",
    "sg:province":"WA",
    "wof:name":"Moms Home",
    "wof:placetype":"venue"
},
  "geometry": {"coordinates":[-122.632456,45.65952],"type":"Point"}
}