{
  "type": "Feature",
  "properties": {
    "addr:full":"3705 Factoria Blvd SE Bellevue WA 98006",
    "addr:housenumber":"3705",
    "addr:postcode":"98006",
    "addr:street":"Factoria Blvd Se",
    "iso:country":"US",
    "sg:address":"3705 Factoria Blvd SE",
    "sg:city":"Bellevue",
    "sg:classifiers":[
        {
            "category":"Restaurant",
            "type":"Food & Drink"
        }
    ],
    "sg:phone":"+1 425 747 4637",
    "sg:postcode":"98006",
    "sg:province":"WA",
    "wof:name":"Taco Bell",
    "wof:placetype":"venue"
},
  "geometry": {"coordinates":[-122.16950199999999,47.578167],"type":"Point"}
}