{
  "type": "Feature",
  "properties": {
    "addr:full":"615 Ocean Shores Blvd NW Ocean Shores WA 98569",
    "addr:housenumber":"615",
    "addr:postcode":"98569",
    "addr:street":"Ocean Shores Blvd Nw",
    "iso:country":"US",
    "sg:address":"615 Ocean Shores Blvd NW",
    "sg:city":"Ocean Shores",
    "sg:classifiers":[
        {
            "category":"Personal",
            "type":"Services"
        }
    ],
    "sg:phone":"+1 360 289 3315",
    "sg:postcode":"98569",
    "sg:province":"WA",
    "sg:tags":[
        "eating"
    ],
    "wof:name":"Mariahs Restaurant At Polynesi",
    "wof:placetype":"venue"
},
  "geometry": {"coordinates":[-124.16619,47.006259],"type":"Point"}
}