{
  "type": "Feature",
  "properties": {
    "iso:country":"US",
    "sg:address":"2633 E Beaver Lake Dr SE",
    "sg:city":"Sammamish",
    "sg:classifiers":[
        {
            "category":"Building & Trades",
            "subcategory":"Construction",
            "type":"Services"
        }
    ],
    "sg:phone":"+1 425 392 9315",
    "sg:postcode":"98075",
    "sg:province":"WA",
    "wof:name":"Kovacic Industries",
    "wof:placetype":"venue"
},
  "geometry": {"coordinates":[-121.99802200000001,47.585759],"type":"Point"}
}