{
  "type": "Feature",
  "properties": {
    "addr:full":"1209 Roland St Bellingham WA 98229",
    "addr:housenumber":"1209",
    "addr:postcode":"98229",
    "addr:street":"Roland St",
    "iso:country":"US",
    "sg:address":"1209 Roland St",
    "sg:city":"Bellingham",
    "sg:classifiers":[
        {
            "category":"Professional",
            "type":"Services"
        }
    ],
    "sg:phone":"+1 360 734 0386",
    "sg:postcode":"98229",
    "sg:province":"WA",
    "wof:name":"Groove Merchant Northwest",
    "wof:placetype":"venue"
},
  "geometry": {"coordinates":[-122.43100200000001,48.747925],"type":"Point"}
}