{
  "type": "Feature",
  "properties": {
    "addr:full":"6380 W Shelton Matlock Rd Shelton WA 98584",
    "addr:housenumber":"6380",
    "addr:postcode":"98584",
    "addr:street":"W;Matlock Rd",
    "iso:country":"US",
    "sg:address":"6380 W Shelton Matlock Rd",
    "sg:city":"Shelton",
    "sg:classifiers":[
        {
            "category":"Manufacturing",
            "subcategory":"Lumber",
            "type":"Manufacturing & Wholesale Goods"
        }
    ],
    "sg:phone":"+1 360 426 5951",
    "sg:postcode":"98584",
    "sg:province":"WA",
    "sg:tags":[
        "operation",
        "timber",
        "tract"
    ],
    "wof:name":"Pentony Forestry",
    "wof:placetype":"venue"
},
  "geometry": {"coordinates":[-123.205602,47.218795],"type":"Point"}
}