{
  "type": "Feature",
  "properties": {
    "addr:full":"10515 53rd Ave W Mukilteo WA 98275",
    "addr:housenumber":"10515",
    "addr:postcode":"98275",
    "addr:street":"53Rd Ave W",
    "iso:country":"US",
    "sg:address":"10515 53rd Ave W",
    "sg:city":"Mukilteo",
    "sg:classifiers":[
        {
            "category":"Professional",
            "subcategory":"Management & Consulting",
            "type":"Services"
        }
    ],
    "sg:phone":"+1 425 349 1959",
    "sg:postcode":"98275",
    "sg:province":"WA",
    "sg:tags":[
        "marketing",
        "consultant"
    ],
    "wof:name":"Money Mailer Inc",
    "wof:placetype":"venue"
},
  "geometry": {"coordinates":[-122.30639600000001,47.902362],"type":"Point"}
}