{
  "type": "Feature",
  "properties": {
    "addr:full":"1300 SE Sunnymead Way Pullman WA 99163",
    "addr:housenumber":"1300",
    "addr:postcode":"99163",
    "addr:street":"Se Sunnymead Way",
    "iso:country":"US",
    "sg:address":"1300 SE Sunnymead Way",
    "sg:city":"Pullman",
    "sg:phone":"+1 509 332 5015",
    "sg:postcode":"99163",
    "sg:province":"WA",
    "sg:website":"http://www.ebcpullman.org",
    "wof:name":"Emmanuel Baptist Church",
    "wof:placetype":"venue"
},
  "geometry": {"coordinates":[-117.16819,46.718731],"type":"Point"}
}