{
  "type": "Feature",
  "properties": {
    "iso:country":"US",
    "sg:address":"2412 Spruce St",
    "sg:city":"Bellingham",
    "sg:classifiers":[
        {
            "category":"Building & Trades",
            "subcategory":"Construction",
            "type":"Services"
        }
    ],
    "sg:phone":"+1 360 733 3720",
    "sg:postcode":"98225",
    "sg:province":"WA",
    "sg:tags":[
        "builder",
        "operative"
    ],
    "wof:name":"McFarlane Construction Inc",
    "wof:placetype":"venue"
},
  "geometry": {"coordinates":[-122.503102,48.763019],"type":"Point"}
}