{
  "type": "Feature",
  "properties": {
    "addr:full":"408 Logger St SE Olympia WA 98503",
    "addr:housenumber":"408",
    "addr:postcode":"98503",
    "addr:street":"Logger St Se",
    "iso:country":"US",
    "sg:address":"408 Logger St SE",
    "sg:city":"Olympia",
    "sg:classifiers":[
        {
            "category":"Shopping",
            "type":"Retail Goods"
        }
    ],
    "sg:phone":"+1 360 438 8276",
    "sg:postcode":"98503",
    "sg:province":"WA",
    "sg:tags":[
        "miscellaneous",
        "store"
    ],
    "sg:website":"www.rm-solutions.com",
    "wof:name":"Retail Management Solutions",
    "wof:placetype":"venue"
},
  "geometry": {"coordinates":[-122.782645,47.047413],"type":"Point"}
}