{
  "type": "Feature",
  "properties": {
    "addr:full":"9101 NE 116th Ave Vancouver WA 98662",
    "addr:housenumber":"9101",
    "addr:postcode":"98662",
    "addr:street":"Ne 116Th Ave",
    "iso:country":"US",
    "sg:address":"9101 NE 116th Ave",
    "sg:city":"Vancouver",
    "sg:classifiers":[
        {
            "category":"Building & Trades",
            "subcategory":"Construction",
            "type":"Services"
        }
    ],
    "sg:phone":"+1 360 253 8165",
    "sg:postcode":"98662",
    "sg:province":"WA",
    "sg:tags":[
        "road",
        "contractor"
    ],
    "sg:website":"http://www.pbfconstruction.com",
    "wof:name":"P B F Inc",
    "wof:placetype":"venue"
},
  "geometry": {"coordinates":[-122.553589,45.688499],"type":"Point"}
}