{
  "type": "Feature",
  "properties": {
    "addr:full":"223 Taylor Ave N Ste 211 Seattle WA 98109",
    "addr:housenumber":"223",
    "addr:postcode":"98109",
    "addr:street":"Taylor Ave N Ste 211",
    "iso:country":"US",
    "sg:address":"223 Taylor Ave N Ste 211",
    "sg:city":"Seattle",
    "sg:classifiers":[
        {
            "category":"Real Estate",
            "subcategory":"Real Estate Services",
            "type":"Services"
        }
    ],
    "sg:phone":"+1 206 652 4100",
    "sg:postcode":"98109",
    "sg:province":"WA",
    "sg:tags":[
        "commercial"
    ],
    "wof:name":"Northwest Park Brokerage Inc",
    "wof:placetype":"venue"
},
  "geometry": {"coordinates":[-122.346322,47.619992],"type":"Point"}
}