{
  "type": "Feature",
  "properties": {
    "addr:full":"604 Hill Rd Aberdeen WA 98520",
    "addr:housenumber":"604",
    "addr:postcode":"98520",
    "addr:street":"Hill Rd",
    "iso:country":"US",
    "sg:address":"604 Hill Rd",
    "sg:city":"Aberdeen",
    "sg:classifiers":[
        {
            "category":"Retail",
            "subcategory":"Laundry & Dry Cleaning",
            "type":"Services"
        }
    ],
    "sg:phone":"+1 360 532 1811",
    "sg:postcode":"98520",
    "sg:province":"WA",
    "sg:tags":[
        "drycleaning",
        "plant"
    ],
    "wof:name":"Quality Cleaners",
    "wof:placetype":"venue"
},
  "geometry": {"coordinates":[-123.691655,46.967442],"type":"Point"}
}