{
  "type": "Feature",
  "properties": {
    "addr:full":"4501 S Lucile St Seattle WA 98118",
    "addr:housenumber":"4501",
    "addr:postcode":"98118",
    "addr:street":"S Lucile St",
    "iso:country":"US",
    "sg:address":"4501 S Lucile St",
    "sg:city":"Seattle",
    "sg:classifiers":[
        {
            "category":"Professional",
            "subcategory":"Computer Services",
            "type":"Services"
        }
    ],
    "sg:phone":"+1 206 722 4252",
    "sg:postcode":"98118",
    "sg:province":"WA",
    "sg:tags":[
        "repair"
    ],
    "wof:name":"Sebri Surplus Sebri Systems",
    "wof:placetype":"venue"
},
  "geometry": {"coordinates":[-122.276411,47.552506],"type":"Point"}
}