{
  "type": "Feature",
  "properties": {
    "addr:full":"7620 SE 27th St Mercer Island WA 98040",
    "addr:housenumber":"7620",
    "addr:postcode":"98040",
    "addr:street":"Se 27Th St",
    "iso:country":"US",
    "sg:address":"7620 SE 27th St",
    "sg:city":"Mercer Island",
    "sg:classifiers":[
        {
            "category":"Coffee & Tea",
            "type":"Food & Drink"
        }
    ],
    "sg:phone":"+1 206 275 3115",
    "sg:postcode":"98040",
    "sg:province":"WA",
    "sg:website":"www.starbucks.com",
    "wof:name":"Starbucks",
    "wof:placetype":"venue"
},
  "geometry": {"coordinates":[-122.236906,47.586769],"type":"Point"}
}