{
  "type": "Feature",
  "properties": {
    "addr:full":"29017 NE Healy Rd Amboy WA 98601",
    "addr:housenumber":"29017",
    "addr:postcode":"98601",
    "addr:street":"Ne Healy Rd",
    "iso:country":"US",
    "sg:address":"29017 NE Healy Rd",
    "sg:city":"Amboy",
    "sg:classifiers":[
        {
            "category":"Wholesale",
            "subcategory":"Machinery & Supplies",
            "type":"Manufacturing & Wholesale Goods"
        }
    ],
    "sg:phone":"+1 360 247 5151",
    "sg:postcode":"98601",
    "sg:province":"WA",
    "sg:tags":[
        "mill",
        "paper"
    ],
    "sg:website":"www.nwpulpandpaperequip.com",
    "wof:name":"Northwest Pulp & Paper Equip",
    "wof:placetype":"venue"
},
  "geometry": {"coordinates":[-122.37444600000001,45.929834],"type":"Point"}
}