{
  "type": "Feature",
  "properties": {
    "addr:full":"1511 Lower Deadman Rd Pomeroy WA 99347",
    "addr:housenumber":"1511",
    "addr:postcode":"99347",
    "addr:street":"Lower Deadman Rd",
    "iso:country":"US",
    "sg:address":"1511 Lower Deadman Rd",
    "sg:city":"Pomeroy",
    "sg:classifiers":[
        {
            "category":"Farming",
            "subcategory":"Livestock Farm",
            "type":"Manufacturing & Wholesale Goods"
        }
    ],
    "sg:phone":"+1 509 843 3822",
    "sg:postcode":"99347",
    "sg:province":"WA",
    "sg:tags":[
        "cattle",
        "wheat",
        "pea",
        "barley"
    ],
    "wof:name":"Klaveano Ranches Inc",
    "wof:placetype":"venue"
},
  "geometry": {"coordinates":[-117.751553,46.621255],"type":"Point"}
}