{
  "type": "Feature",
  "properties": {
    "addr:full":"1350 E Fir St Seattle WA 98122",
    "addr:housenumber":"1350",
    "addr:postcode":"98122",
    "addr:street":"E Fir St",
    "iso:country":"US",
    "sg:address":"1350 E Fir St",
    "sg:city":"Seattle",
    "sg:classifiers":[
        {
            "category":"Organizations",
            "subcategory":"Religious Organization",
            "type":"Services"
        }
    ],
    "sg:phone":"+1 206 322 6246",
    "sg:postcode":"98122",
    "sg:province":"WA",
    "sg:tags":[
        "mosque"
    ],
    "wof:name":"Jamaatul Ikhlas",
    "wof:placetype":"venue"
},
  "geometry": {"coordinates":[-122.314548,47.602755],"type":"Point"}
}