{
  "type": "Feature",
  "properties": {
    "addr:full":"11341 Sunnyside Ave N Seattle WA 98133",
    "addr:housenumber":"11341",
    "addr:postcode":"98133",
    "addr:street":"Sunnyside Ave N",
    "iso:country":"US",
    "sg:address":"11341 Sunnyside Ave N",
    "sg:city":"Seattle",
    "sg:classifiers":[
        {
            "category":"Social Services",
            "subcategory":"Child Care",
            "type":"Services"
        }
    ],
    "sg:phone":"+1 206 361 6754",
    "sg:postcode":"98133",
    "sg:province":"WA",
    "sg:tags":[
        "day"
    ],
    "wof:name":"Sparrows Nest Preschool",
    "wof:placetype":"venue"
},
  "geometry": {"coordinates":[-122.330127,47.712065],"type":"Point"}
}