{
  "type": "Feature",
  "properties": {
    "addr:full":"4810 E Jaremko Dr Mead WA 99021",
    "addr:housenumber":"4810",
    "addr:postcode":"99021",
    "addr:street":"E Jaremko Dr Mead",
    "iso:country":"US",
    "sg:address":"4810 E Jaremko Dr",
    "sg:city":"Mead",
    "sg:classifiers":[
        {
            "category":"Professional",
            "subcategory":"Advertising",
            "type":"Services"
        }
    ],
    "sg:phone":"+1 509 464 2622",
    "sg:postcode":"99021",
    "sg:province":"WA",
    "wof:name":"Tubeart Signs & Sport Displays",
    "wof:placetype":"venue"
},
  "geometry": {"coordinates":[-117.34019499999999,47.792583],"type":"Point"}
}