{
  "type": "Feature",
  "properties": {
    "addr:full":"3503 S Bay Rd NE Olympia WA 98506",
    "addr:housenumber":"3503",
    "addr:postcode":"98506",
    "addr:street":"S Bay Rd Ne",
    "iso:country":"US",
    "sg:address":"3503 S Bay Rd NE",
    "sg:city":"Olympia",
    "sg:classifiers":[
        {
            "category":"Shopping",
            "type":"Retail Goods"
        }
    ],
    "sg:phone":"+1 360 491 6100",
    "sg:postcode":"98506",
    "sg:province":"WA",
    "sg:tags":[
        "pet",
        "shop"
    ],
    "wof:name":"Pet Store At South Bay Fd",
    "wof:placetype":"venue"
},
  "geometry": {"coordinates":[-122.843403,47.082831],"type":"Point"}
}