{
  "type": "Feature",
  "properties": {
    "addr:full":"12269 56th Pl S Seattle WA 98178",
    "addr:housenumber":"12269",
    "addr:postcode":"98178",
    "addr:street":"56Th Pl S",
    "iso:country":"US",
    "sg:address":"12269 56th Pl S",
    "sg:city":"Seattle",
    "sg:classifiers":[
        {
            "category":"Structure",
            "subcategory":"Office Building",
            "type":"Public Place"
        }
    ],
    "sg:phone":"+1 206 772 4348",
    "sg:postcode":"98178",
    "sg:province":"WA",
    "sg:tags":[
        "park"
    ],
    "wof:name":"P J Properties",
    "wof:placetype":"venue"
},
  "geometry": {"coordinates":[-122.261533,47.491301],"type":"Point"}
}