{
  "type": "Feature",
  "properties": {
    "addr:full":"268 E Driftwood Shores Rd Stanwood WA 98282",
    "addr:housenumber":"268",
    "addr:postcode":"98282",
    "addr:street":"E Driftwood Shores Rd",
    "iso:country":"US",
    "sg:address":"268 E Driftwood Shores Rd",
    "sg:city":"Stanwood",
    "sg:classifiers":[
        {
            "category":"Professional",
            "type":"Services"
        }
    ],
    "sg:phone":"+1 360 387 0888",
    "sg:postcode":"98282",
    "sg:province":"WA",
    "wof:name":"Reconveyance Professionals",
    "wof:placetype":"venue"
},
  "geometry": {"coordinates":[-122.46596599999999,48.195579],"type":"Point"}
}