{
  "type": "Feature",
  "properties": {
    "iso:country":"US",
    "sg:address":"15822 28th Ave NE",
    "sg:city":"Seattle",
    "sg:classifiers":[
        {
            "category":"Shopping",
            "subcategory":"Jewelry",
            "type":"Retail Goods"
        }
    ],
    "sg:phone":"+1 206 361 8472",
    "sg:postcode":"98155",
    "sg:province":"WA",
    "wof:name":"Time Pieces",
    "wof:placetype":"venue"
},
  "geometry": {"coordinates":[-122.297967,47.744456],"type":"Point"}
}