{
  "type": "Feature",
  "properties": {
    "addr:full":"4432 192nd Pl SE Issaquah WA 98027",
    "addr:housenumber":"4432",
    "addr:postcode":"98027",
    "addr:street":"192Nd Pl Se",
    "iso:country":"US",
    "sg:address":"4432 192nd Pl SE",
    "sg:city":"Issaquah",
    "sg:classifiers":[
        {
            "category":"Education",
            "subcategory":"Special Training",
            "type":"Public Place"
        },
        {
            "category":"Shopping",
            "subcategory":"Crafts & Fabrics",
            "type":"Retail Goods"
        }
    ],
    "sg:phone":"+1 425 401 8510",
    "sg:postcode":"98027",
    "sg:province":"WA",
    "sg:tags":[
        "school",
        "instruction",
        "art"
    ],
    "wof:name":"Anne E Hall",
    "wof:placetype":"venue"
},
  "geometry": {"coordinates":[-122.08413400000001,47.565387],"type":"Point"}
}