{
  "type": "Feature",
  "properties": {
    "iso:country":"US",
    "sg:address":"2000 116th Ave NE",
    "sg:city":"Bellevue",
    "sg:classifiers":[
        {
            "category":"Health Services",
            "subcategory":"Health Practitioner",
            "type":"Services"
        }
    ],
    "sg:phone":"+1 425 709 2436",
    "sg:postcode":"98004",
    "sg:province":"WA",
    "sg:tags":[
        "acupuncture"
    ],
    "wof:name":"Chen Acupuncture & Accprssr",
    "wof:placetype":"venue"
},
  "geometry": {"coordinates":[-122.18563399999999,47.629663],"type":"Point"}
}