{
  "type": "Feature",
  "properties": {
    "addr:full":"4017 177th Ave SE Bellevue WA 98008",
    "addr:housenumber":"4017",
    "addr:postcode":"98008",
    "addr:street":"177Th Ave Se",
    "iso:country":"US",
    "sg:address":"4017 177th Ave SE",
    "sg:city":"Bellevue",
    "sg:classifiers":[
        {
            "category":"Wholesale",
            "subcategory":"Machinery & Supplies",
            "type":"Manufacturing & Wholesale Goods"
        }
    ],
    "sg:phone":"+1 425 401 5272",
    "sg:postcode":"98008",
    "sg:province":"WA",
    "sg:tags":[
        "equipment",
        "industrial"
    ],
    "wof:name":"Cds Heavy Equipment Sales",
    "wof:placetype":"venue"
},
  "geometry": {"coordinates":[-122.10550000000001,47.571533],"type":"Point"}
}