{
  "type": "Feature",
  "properties": {
    "addr:full":"9000 Renton Ave S Seattle WA 98118",
    "addr:housenumber":"9000",
    "addr:postcode":"98118",
    "addr:street":"Renton Ave S",
    "iso:country":"US",
    "sg:address":"9000 Renton Ave S",
    "sg:city":"Seattle",
    "sg:classifiers":[
        {
            "category":"Insurance",
            "subcategory":"Insurance Agent",
            "type":"Services"
        }
    ],
    "sg:phone":"+1 206 722 8881",
    "sg:postcode":"98118",
    "sg:province":"WA",
    "wof:name":"Freeman Mona Insurance",
    "wof:placetype":"venue"
},
  "geometry": {"coordinates":[-122.274327,47.521504],"type":"Point"}
}