{
  "type": "Feature",
  "properties": {
    "addr:full":"12215 Aurora Ave N Seattle WA 98133",
    "addr:housenumber":"12215",
    "addr:postcode":"98133",
    "addr:street":"Aurora Ave N",
    "iso:country":"US",
    "sg:address":"12215 Aurora Ave N",
    "sg:city":"Seattle",
    "sg:classifiers":[
        {
            "category":"Autos & Motor Vehicles",
            "subcategory":"Auto Supplies",
            "type":"Retail Goods"
        }
    ],
    "sg:phone":"+1 206 387 0402",
    "sg:postcode":"98133",
    "sg:province":"WA",
    "sg:tags":[
        "tire"
    ],
    "wof:name":"Les Schwab Tire Centers Inc",
    "wof:placetype":"venue"
},
  "geometry": {"coordinates":[-122.345001,47.717701],"type":"Point"}
}