{
  "type": "Feature",
  "properties": {
    "addr:full":"4050 NE North Shore Rd Belfair WA 98528",
    "addr:housenumber":"4050",
    "addr:postcode":"98528",
    "addr:street":"Ne North Shore Rd",
    "iso:country":"US",
    "sg:address":"4050 NE North Shore Rd",
    "sg:city":"Belfair",
    "sg:classifiers":[
        {
            "category":"Restaurant",
            "type":"Food & Drink"
        }
    ],
    "sg:phone":"+1 360 275 9330",
    "sg:postcode":"98528",
    "sg:province":"WA",
    "wof:name":"Beach House Also",
    "wof:placetype":"venue"
},
  "geometry": {"coordinates":[-122.906702,47.417512],"type":"Point"}
}