{
  "type": "Feature",
  "properties": {
    "addr:full":"1333 Eufaula Heights Rd Longview WA 98632",
    "addr:housenumber":"1333",
    "addr:postcode":"98632",
    "addr:street":"Eufaula Heights Rd",
    "iso:country":"US",
    "sg:address":"1333 Eufaula Heights Rd",
    "sg:city":"Longview",
    "sg:classifiers":[
        {
            "category":"Retail",
            "subcategory":"Auto Repair",
            "type":"Services"
        }
    ],
    "sg:phone":"+1 360 401 4170",
    "sg:postcode":"98632",
    "sg:province":"WA",
    "sg:tags":[
        "body",
        "technician"
    ],
    "wof:name":"Rods-N-Bobs",
    "wof:placetype":"venue"
},
  "geometry": {"coordinates":[-123.065822,46.22077],"type":"Point"}
}