{
  "type": "Feature",
  "properties": {
    "iso:country":"US",
    "sg:address":"703 Front St",
    "sg:city":"Leavenworth",
    "sg:classifiers":[
        {
            "category":"Food & Beverages",
            "subcategory":"Liquor & Beverages",
            "type":"Retail Goods"
        },
        {
            "category":"Food & Beverages",
            "subcategory":"Bakery",
            "type":"Retail Goods"
        }
    ],
    "sg:phone":"+1 509 548 7216",
    "sg:postcode":"98826",
    "sg:province":"WA",
    "sg:tags":[
        "eating",
        "wine"
    ],
    "wof:name":"Monaco's Corner Store",
    "wof:placetype":"venue"
},
  "geometry": {"coordinates":[-120.662876,47.594666],"type":"Point"}
}