{
  "type": "Feature",
  "properties": {
    "addr:full":"3300 Meridian Ave N # 206 Seattle WA 98103",
    "addr:housenumber":"3300",
    "addr:postcode":"98103",
    "addr:street":"Meridian Ave N # 206",
    "iso:country":"US",
    "sg:address":"3300 Meridian Ave N # 206",
    "sg:city":"Seattle",
    "sg:classifiers":[
        {
            "category":"Professional",
            "subcategory":"Art Services",
            "type":"Services"
        }
    ],
    "sg:phone":"+1 206 547 4011",
    "sg:postcode":"98103",
    "sg:province":"WA",
    "sg:tags":[
        "interior",
        "designer",
        "decorator"
    ],
    "wof:name":"Designers Process Jmb Designs",
    "wof:placetype":"venue"
},
  "geometry": {"coordinates":[-122.333893,47.646858],"type":"Point"}
}