{
  "type": "Feature",
  "properties": {
    "addr:full":"305 Marshall St Davenport WA 99122",
    "addr:housenumber":"305",
    "addr:postcode":"99122",
    "addr:street":"Marshall St",
    "iso:country":"US",
    "sg:address":"305 Marshall St",
    "sg:city":"Davenport",
    "sg:classifiers":[
        {
            "category":"Farming",
            "subcategory":"Farm",
            "type":"Manufacturing & Wholesale Goods"
        }
    ],
    "sg:phone":"+1 509 725 3210",
    "sg:postcode":"99122",
    "sg:province":"WA",
    "wof:name":"Colbert Farms, Inc.",
    "wof:placetype":"venue"
},
  "geometry": {"coordinates":[-118.144794,47.651619],"type":"Point"}
}