{
  "type": "Feature",
  "properties": {
    "addr:full":"10424 SE 240th St Kent WA 98031",
    "addr:housenumber":"10424",
    "addr:postcode":"98031",
    "addr:street":"Se 240Th St",
    "iso:country":"US",
    "sg:address":"10424 SE 240th St",
    "sg:city":"Kent",
    "sg:classifiers":[
        {
            "category":"Food & Beverages",
            "subcategory":"Groceries & Convenience Stores",
            "type":"Retail Goods"
        }
    ],
    "sg:phone":"+1 253 852 1269",
    "sg:postcode":"98031",
    "sg:province":"WA",
    "sg:tags":[
        "supermarket"
    ],
    "wof:name":"Safeway 372",
    "wof:placetype":"venue"
},
  "geometry": {"coordinates":[-122.202015,47.387032],"type":"Point"}
}