{
  "type": "Feature",
  "properties": {
    "addr:full":"2355 Griffin Ave Enumclaw WA 98022",
    "addr:housenumber":"2355",
    "addr:postcode":"98022",
    "addr:street":"Griffin Ave",
    "iso:country":"US",
    "sg:address":"2355 Griffin Ave",
    "sg:city":"Enumclaw",
    "sg:classifiers":[
        {
            "category":"Wholesale",
            "subcategory":"Machinery & Supplies",
            "type":"Manufacturing & Wholesale Goods"
        }
    ],
    "sg:phone":"+1 360 802 9443",
    "sg:postcode":"98022",
    "sg:province":"WA",
    "sg:tags":[
        "compressor",
        "gas"
    ],
    "wof:name":"Gardner Denver Inc",
    "wof:placetype":"venue"
},
  "geometry": {"coordinates":[-121.99937799999999,47.206658],"type":"Point"}
}