{
  "type": "Feature",
  "properties": {
    "addr:full":"4406 Drake Dr Yakima WA 98908",
    "addr:housenumber":"4406",
    "addr:postcode":"98908",
    "addr:street":"Drake Dr",
    "iso:country":"US",
    "sg:address":"4406 Drake Dr",
    "sg:city":"Yakima",
    "sg:classifiers":[
        {
            "category":"Professional",
            "type":"Services"
        }
    ],
    "sg:phone":"+1 509 965 4078",
    "sg:postcode":"98908",
    "sg:province":"WA",
    "wof:name":"Chris Reinmuth",
    "wof:placetype":"venue"
},
  "geometry": {"coordinates":[-120.568411,46.595251],"type":"Point"}
}