{
  "type": "Feature",
  "properties": {
    "addr:full":"404 S 1st St Selah WA 98942",
    "addr:housenumber":"404",
    "addr:postcode":"98942",
    "addr:street":"S 1St St",
    "iso:country":"US",
    "sg:address":"404 S 1st St",
    "sg:city":"Selah",
    "sg:classifiers":[
        {
            "category":"Building & Trades",
            "subcategory":"Plumbing",
            "type":"Services"
        }
    ],
    "sg:phone":"+1 509 949 1275",
    "sg:postcode":"98942",
    "sg:province":"WA",
    "sg:tags":[
        "repair",
        "contractor"
    ],
    "wof:name":"Septic Design Specialist Inc",
    "wof:placetype":"venue"
},
  "geometry": {"coordinates":[-120.530451,46.647037],"type":"Point"}
}