{
  "type": "Feature",
  "properties": {
    "addr:full":"9512 1st Ave NE Apt 304 Seattle WA 98115",
    "addr:housenumber":"9512;304",
    "addr:postcode":"98115",
    "addr:street":"1St Ave Ne Apt",
    "iso:country":"US",
    "sg:address":"9512 1st Ave NE Apt 304",
    "sg:city":"Seattle",
    "sg:classifiers":[
        {
            "category":"Professional",
            "type":"Services"
        }
    ],
    "sg:phone":"+1 206 465 2208",
    "sg:postcode":"98115",
    "sg:province":"WA",
    "sg:tags":[
        "motion",
        "technician",
        "picture"
    ],
    "wof:name":"Westbound Films, Inc.",
    "wof:placetype":"venue"
},
  "geometry": {"coordinates":[-122.328461,47.697764],"type":"Point"}
}