{
  "type": "Feature",
  "properties": {
    "addr:full":"Salon Taylor 1425 Market Street Kirkland WA 98033",
    "addr:housenumber":"1425",
    "addr:postcode":"98033",
    "addr:street":"Market Street",
    "iso:country":"US",
    "sg:address":"Salon Taylor 1425 Market Street",
    "sg:city":"Kirkland",
    "sg:classifiers":[
        {
            "category":"Personal",
            "subcategory":"Beauty Salon",
            "type":"Services"
        }
    ],
    "sg:phone":"+1 425 221 0057",
    "sg:postcode":"98033",
    "sg:province":"WA",
    "sg:tags":[
        "spa"
    ],
    "wof:name":"Marilyn Michael",
    "wof:placetype":"venue"
},
  "geometry": {"coordinates":[-122.209746,47.687302],"type":"Point"}
}