{
  "type": "Feature",
  "properties": {
    "addr:full":"14614 SE 29th St Vancouver WA 98683",
    "addr:postcode":"14614;98683",
    "addr:street":"Se 29Th St",
    "iso:country":"US",
    "sg:address":"14614 SE 29th St",
    "sg:city":"Vancouver",
    "sg:classifiers":[
        {
            "category":"Professional",
            "type":"Services"
        }
    ],
    "sg:phone":"+1 360 892 8892",
    "sg:postcode":"98683",
    "sg:province":"WA",
    "wof:name":"Peter Wright",
    "wof:placetype":"venue"
},
  "geometry": {"coordinates":[-122.52206700000001,45.599836],"type":"Point"}
}