{
  "type": "Feature",
  "properties": {
    "addr:full":"18411 Aurora Ave N Shoreline WA 98133",
    "addr:housenumber":"18411",
    "addr:postcode":"98133",
    "addr:street":"Aurora Ave N",
    "iso:country":"US",
    "sg:address":"18411 Aurora Ave N",
    "sg:city":"Shoreline",
    "sg:classifiers":[
        {
            "category":"Restaurant",
            "type":"Food & Drink"
        }
    ],
    "sg:phone":"+1 206 546 2900",
    "sg:postcode":"98133",
    "sg:province":"WA",
    "sg:tags":[
        "eating"
    ],
    "wof:name":"Spiro's Pizza & Pasta",
    "wof:placetype":"venue"
},
  "geometry": {"coordinates":[-122.346041,47.762421],"type":"Point"}
}