{
  "type": "Feature",
  "properties": {
    "iso:country":"US",
    "sg:address":"21213 SE 268th Pl",
    "sg:city":"Maple Valley",
    "sg:classifiers":[
        {
            "category":"Manufacturing",
            "subcategory":"Tools & Machinery",
            "type":"Manufacturing & Wholesale Goods"
        }
    ],
    "sg:phone":"+1 425 432 3204",
    "sg:postcode":"98038",
    "sg:province":"WA",
    "sg:tags":[
        "machine",
        "mfg"
    ],
    "wof:name":"Baker JC & Co",
    "wof:placetype":"venue"
},
  "geometry": {"coordinates":[-122.05729700000001,47.360962],"type":"Point"}
}