{
  "type": "Feature",
  "properties": {
    "addr:full":"817 NE 91st St Seattle WA 98115",
    "addr:housenumber":"817",
    "addr:postcode":"98115",
    "addr:street":"Ne 91St St",
    "iso:country":"US",
    "sg:address":"817 NE 91st St",
    "sg:city":"Seattle",
    "sg:classifiers":[
        {
            "category":"Professional",
            "subcategory":"Business Services",
            "type":"Services"
        }
    ],
    "sg:phone":"+1 206 729 5681",
    "sg:postcode":"98115",
    "sg:province":"WA",
    "wof:name":"Om Room Productions",
    "wof:placetype":"venue"
},
  "geometry": {"coordinates":[-122.317745,47.694847],"type":"Point"}
}