{
  "type": "Feature",
  "properties": {
    "addr:full":"33501 First Way Street Seattle WA 98101",
    "addr:postcode":"33501;98101",
    "addr:street":"First Way Street",
    "iso:country":"US",
    "sg:address":"33501 First Way Street",
    "sg:city":"Seattle",
    "sg:classifiers":[
        {
            "category":"Health Services",
            "subcategory":"Doctor",
            "type":"Services"
        }
    ],
    "sg:phone":"+1 206 341 1007",
    "sg:postcode":"98101",
    "sg:province":"WA",
    "wof:name":"McDonald Brian MD",
    "wof:placetype":"venue"
},
  "geometry": {"coordinates":[-122.332998,47.61039],"type":"Point"}
}