{
  "type": "Feature",
  "properties": {
    "addr:full":"12210 118th Ave SE Rainier WA 98576",
    "addr:housenumber":"12210",
    "addr:postcode":"98576",
    "addr:street":"118Th Ave Se",
    "iso:country":"US",
    "sg:address":"12210 118th Ave SE",
    "sg:city":"Rainier",
    "sg:classifiers":[
        {
            "category":"Place Of Worship",
            "subcategory":"Church",
            "type":"Public Place"
        },
        {
            "category":"Place Of Worship",
            "type":"Public Place"
        }
    ],
    "sg:phone":"+1 360 446 3215",
    "sg:postcode":"98576",
    "sg:province":"WA",
    "sg:tags":[
        "churches-non-denominational"
    ],
    "wof:name":"Oakridge Ministries",
    "wof:placetype":"venue"
},
  "geometry": {"coordinates":[-122.68488600000001,46.916129],"type":"Point"}
}