{
  "type": "Feature",
  "properties": {
    "addr:full":"30416 N Elk Chattaroy Rd Chattaroy WA 99003",
    "addr:housenumber":"30416",
    "addr:postcode":"99003",
    "addr:street":"N Elk Chattaroy Rd",
    "iso:country":"US",
    "sg:address":"30416 N Elk Chattaroy Rd",
    "sg:city":"Chattaroy",
    "sg:classifiers":[
        {
            "category":"Real Estate",
            "subcategory":"Real Estate Agent",
            "type":"Services"
        }
    ],
    "sg:phone":"+1 509 292 2929",
    "sg:postcode":"99003",
    "sg:province":"WA",
    "wof:name":"Northern Lights Realty",
    "wof:placetype":"venue"
},
  "geometry": {"coordinates":[-117.25865899999999,47.933965],"type":"Point"}
}