{
  "type": "Feature",
  "properties": {
    "addr:full":"12012 Kellogg Lake Rd Sultan WA 98294",
    "addr:housenumber":"12012",
    "addr:postcode":"98294",
    "addr:street":"Kellogg Lake Rd",
    "iso:country":"US",
    "sg:address":"12012 Kellogg Lake Rd",
    "sg:city":"Sultan",
    "sg:classifiers":[
        {
            "category":"Retail",
            "subcategory":"Auto Repair",
            "type":"Services"
        }
    ],
    "sg:phone":"+1 360 799 1327",
    "sg:postcode":"98294",
    "sg:province":"WA",
    "sg:tags":[
        "automotive"
    ],
    "wof:name":"Divers Street Rods Inc",
    "wof:placetype":"venue"
},
  "geometry": {"coordinates":[-121.740923,47.893734],"type":"Point"}
}