{
  "type": "Feature",
  "properties": {
    "addr:full":"1815 138th St S Tacoma WA 98444",
    "addr:housenumber":"1815",
    "addr:postcode":"98444",
    "addr:street":"138Th St S",
    "iso:country":"US",
    "sg:address":"1815 138th St S",
    "sg:city":"Tacoma",
    "sg:classifiers":[
        {
            "category":"Building & Trades",
            "subcategory":"Construction",
            "type":"Services"
        }
    ],
    "sg:phone":"+1 253 537 3079",
    "sg:postcode":"98444",
    "sg:province":"WA",
    "sg:tags":[
        "house"
    ],
    "wof:name":"Lubbesmeyer Family LLC",
    "wof:placetype":"venue"
},
  "geometry": {"coordinates":[-122.461448,47.131683],"type":"Point"}
}