{
  "type": "Feature",
  "properties": {
    "addr:full":"611 E Sunset Dr Bellingham WA 98225",
    "addr:housenumber":"611",
    "addr:postcode":"98225",
    "addr:street":"E Sunset Dr",
    "iso:country":"US",
    "sg:address":"611 E Sunset Dr",
    "sg:city":"Bellingham",
    "sg:classifiers":[
        {
            "category":"Professional",
            "subcategory":"Business Services",
            "type":"Services"
        }
    ],
    "sg:phone":"+1 360 733 4072",
    "sg:postcode":"98225",
    "sg:province":"WA",
    "wof:name":"Elliot Enterprises",
    "wof:placetype":"venue"
},
  "geometry": {"coordinates":[-122.469245,48.769698],"type":"Point"}
}