{
  "type": "Feature",
  "properties": {
    "addr:full":"3939 154th Ave SE Bellevue WA 98006",
    "addr:housenumber":"3939",
    "addr:postcode":"98006",
    "addr:street":"154Th Ave Se",
    "iso:country":"US",
    "sg:address":"3939 154th Ave SE",
    "sg:city":"Bellevue",
    "sg:classifiers":[
        {
            "category":"Shopping",
            "subcategory":"Beauty & Cosmetics",
            "type":"Retail Goods"
        }
    ],
    "sg:phone":"+1 425 746 3808",
    "sg:postcode":"98006",
    "sg:province":"WA",
    "sg:tags":[
        "supply"
    ],
    "sg:website":"www.katanaedge.com",
    "wof:name":"Katana Edge",
    "wof:placetype":"venue"
},
  "geometry": {"coordinates":[-122.13548299999999,47.575007],"type":"Point"}
}