{
  "type": "Feature",
  "properties": {
    "addr:full":"31003 Pacific Hwy S Federal Way WA 98003",
    "addr:housenumber":"31003",
    "addr:postcode":"98003",
    "addr:street":"Pacific Hwy S Federal Way",
    "iso:country":"US",
    "sg:address":"31003 Pacific Hwy S",
    "sg:city":"Federal Way",
    "sg:classifiers":[
        {
            "category":"Health Services",
            "subcategory":"Doctor",
            "type":"Services"
        }
    ],
    "sg:phone":"+1 253 839 6544",
    "sg:postcode":"98003",
    "sg:province":"WA",
    "wof:name":"Dennis J Litowitz DDS Inc",
    "wof:placetype":"venue"
},
  "geometry": {"coordinates":[-122.313434,47.322395],"type":"Point"}
}