{
  "type": "Feature",
  "properties": {
    "addr:full":"1523 2nd Ave Seattle WA 98101",
    "addr:housenumber":"1523",
    "addr:postcode":"98101",
    "addr:street":"2Nd Ave",
    "iso:country":"US",
    "sg:address":"1523 2nd Ave",
    "sg:city":"Seattle",
    "sg:classifiers":[
        {
            "category":"Food & Beverages",
            "subcategory":"Groceries & Convenience Stores",
            "type":"Retail Goods"
        }
    ],
    "sg:phone":"+1 206 405 4490",
    "sg:postcode":"98101",
    "sg:province":"WA",
    "wof:name":"Auntie Stellas Market",
    "wof:placetype":"venue"
},
  "geometry": {"coordinates":[-122.33974000000001,47.610015],"type":"Point"}
}