{
  "type": "Feature",
  "properties": {
    "iso:country":"US",
    "sg:address":"8321 State Rte 410",
    "sg:city":"Naches",
    "sg:classifiers":[
        {
            "category":"Professional",
            "subcategory":"Management & Consulting",
            "type":"Services"
        }
    ],
    "sg:phone":"+1 509 658 2599",
    "sg:postcode":"98937",
    "sg:province":"WA",
    "wof:name":"Dan Groves",
    "wof:placetype":"venue"
},
  "geometry": {"coordinates":[-120.91734599999999,46.807538],"type":"Point"}
}