{
  "type": "Feature",
  "properties": {
    "addr:full":"6821 W Clearwater Ave Kennewick WA 99336",
    "addr:housenumber":"6821",
    "addr:postcode":"99336",
    "addr:street":"W Clearwater Ave",
    "iso:country":"US",
    "sg:address":"6821 W Clearwater Ave",
    "sg:city":"Kennewick",
    "sg:classifiers":[
        {
            "category":"Wholesale",
            "subcategory":"Construction Materials",
            "type":"Manufacturing & Wholesale Goods"
        }
    ],
    "sg:phone":"+1 509 735 4235",
    "sg:postcode":"99336",
    "sg:province":"WA",
    "wof:name":"Wayne - Dalton",
    "wof:placetype":"venue"
},
  "geometry": {"coordinates":[-119.214127,46.210244],"type":"Point"}
}