{
  "type": "Feature",
  "properties": {
    "addr:full":"2255 NE 65th St Seattle WA 98115",
    "addr:housenumber":"2255",
    "addr:postcode":"98115",
    "addr:street":"Ne 65Th St",
    "iso:country":"US",
    "sg:address":"2255 NE 65th St",
    "sg:city":"Seattle",
    "sg:phone":"+1 206 524 5555",
    "sg:postcode":"98115",
    "sg:province":"WA",
    "wof:name":"Hot Dish",
    "wof:placetype":"venue"
},
  "geometry": {"coordinates":[-122.303241,47.67578],"type":"Point"}
}