{
  "type": "Feature",
  "properties": {
    "addr:full":"933 Pleasant Ave Bremerton WA 98337",
    "addr:housenumber":"933",
    "addr:postcode":"98337",
    "addr:street":"Pleasant Ave",
    "iso:country":"US",
    "sg:address":"933 Pleasant Ave",
    "sg:city":"Bremerton",
    "sg:classifiers":[
        {
            "category":"Professional",
            "subcategory":"Testing Lab",
            "type":"Services"
        }
    ],
    "sg:phone":"+1 360 405 0430",
    "sg:postcode":"98337",
    "sg:province":"WA",
    "sg:tags":[
        "laboratory"
    ],
    "wof:name":"Anywher Cpr & 1st Aid Co",
    "wof:placetype":"venue"
},
  "geometry": {"coordinates":[-122.62590899999999,47.567487],"type":"Point"}
}