{
  "type": "Feature",
  "properties": {
    "addr:full":"4213 W Garden Springs Rd Spokane WA 99224",
    "addr:housenumber":"4213",
    "addr:postcode":"99224",
    "addr:street":"W Garden Springs Rd",
    "iso:country":"US",
    "sg:address":"4213 W Garden Springs Rd",
    "sg:city":"Spokane",
    "sg:classifiers":[
        {
            "category":"Organizations",
            "subcategory":"Religious Organization",
            "type":"Services"
        }
    ],
    "sg:phone":"+1 509 838 9707",
    "sg:postcode":"99224",
    "sg:province":"WA",
    "sg:tags":[
        "church"
    ],
    "wof:name":"Life Springs Fellowship Church",
    "wof:placetype":"venue"
},
  "geometry": {"coordinates":[-117.48153499999999,47.63199],"type":"Point"}
}