{
  "type": "Feature",
  "properties": {
    "iso:country":"US",
    "sg:address":"5510 SW Luana Beach Rd",
    "sg:city":"Vashon",
    "sg:classifiers":[
        {
            "category":"Wholesale",
            "subcategory":"Seafood",
            "type":"Manufacturing & Wholesale Goods"
        }
    ],
    "sg:phone":"+1 206 920 8002",
    "sg:postcode":"98070",
    "sg:province":"WA",
    "wof:name":"Viking Maid Seafoods",
    "wof:placetype":"venue"
},
  "geometry": {"coordinates":[-122.404607,47.397661],"type":"Point"}
}