{
  "type": "Feature",
  "properties": {
    "addr:full":"208 Airport Way Warden WA 98802",
    "addr:housenumber":"208",
    "addr:postcode":"98802",
    "addr:street":"Airport Way",
    "iso:country":"US",
    "sg:address":"208 Airport Way",
    "sg:city":"Warden",
    "sg:classifiers":[
        {
            "category":"Wholesale",
            "subcategory":"Farm Supplies",
            "type":"Manufacturing & Wholesale Goods"
        }
    ],
    "sg:phone":"+1 509 349 8250",
    "sg:postcode":"98802",
    "sg:province":"WA",
    "sg:tags":[
        "fertilizer"
    ],
    "wof:name":"Bullseye Fertilizer & Chemical",
    "wof:placetype":"venue"
},
  "geometry": {"coordinates":[-120.208253,47.404763],"type":"Point"}
}