{
  "type": "Feature",
  "properties": {
    "addr:full":"8730 Rainier Avenue S Seattle WA 98118",
    "addr:housenumber":"8730",
    "addr:postcode":"98118",
    "addr:street":"Rainier Avenue S",
    "iso:country":"US",
    "sg:address":"8730 Rainier Avenue S",
    "sg:city":"Seattle",
    "sg:classifiers":[
        {
            "category":"Health Services",
            "subcategory":"Dentist",
            "type":"Services"
        }
    ],
    "sg:phone":"+1 206 721 8730",
    "sg:postcode":"98118",
    "sg:province":"WA",
    "wof:name":"South Rainier Dentistry",
    "wof:placetype":"venue"
},
  "geometry": {"coordinates":[-122.270139,47.525327],"type":"Point"}
}