{
  "type": "Feature",
  "properties": {
    "addr:full":"133 Winslow Way E Apt 2 Bainbridge Island WA 98110",
    "addr:housenumber":"133;2",
    "addr:postcode":"98110",
    "addr:street":"Winslow Way E Apt",
    "iso:country":"US",
    "sg:address":"133 Winslow Way E Apt 2",
    "sg:city":"Bainbridge Island",
    "sg:classifiers":[
        {
            "category":"Banks & Credit Unions",
            "subcategory":"Atm",
            "type":"Services"
        }
    ],
    "sg:phone":"+1 206 842 3638",
    "sg:postcode":"98110",
    "sg:province":"WA",
    "sg:tags":[
        "bankruptcy"
    ],
    "sg:website":"www.bainbridgerealproperties.com",
    "wof:name":"Michael P Klein Attorney At Law",
    "wof:placetype":"venue"
},
  "geometry": {"coordinates":[-122.520679,47.62477],"type":"Point"}
}