{
  "type": "Feature",
  "properties": {
    "addr:full":"3830 Snyder Ln Gig Harbor WA 98335",
    "addr:housenumber":"3830",
    "addr:postcode":"98335",
    "addr:street":"Snyder Ln",
    "iso:country":"US",
    "sg:address":"3830 Snyder Ln",
    "sg:city":"Gig Harbor",
    "sg:classifiers":[
        {
            "category":"Professional",
            "subcategory":"Business Services",
            "type":"Services"
        }
    ],
    "sg:phone":"+1 253 858 8080",
    "sg:postcode":"98335",
    "sg:province":"WA",
    "sg:tags":[
        "interior",
        "consultant",
        "design",
        "decorator"
    ],
    "wof:name":"Design Interiors",
    "wof:placetype":"venue"
},
  "geometry": {"coordinates":[-122.59063399999999,47.32671],"type":"Point"}
}