{
  "type": "Feature",
  "properties": {
    "addr:full":"2107 S 1st St Yakima WA 98903",
    "addr:housenumber":"2107",
    "addr:postcode":"98903",
    "addr:street":"S 1St St",
    "iso:country":"US",
    "sg:address":"2107 S 1st St",
    "sg:city":"Yakima",
    "sg:classifiers":[
        {
            "category":"Home & Garden",
            "subcategory":"Furniture",
            "type":"Retail Goods"
        }
    ],
    "sg:phone":"+1 509 469 8550",
    "sg:postcode":"98903",
    "sg:province":"WA",
    "sg:tags":[
        "bed"
    ],
    "wof:name":"Mattress Outlet",
    "wof:placetype":"venue"
},
  "geometry": {"coordinates":[-120.487459,46.570547],"type":"Point"}
}