{
  "type": "Feature",
  "properties": {
    "addr:full":"9832 Airport Way Snohomish WA 98296",
    "addr:housenumber":"9832",
    "addr:postcode":"98296",
    "addr:street":"Airport Way",
    "iso:country":"US",
    "sg:address":"9832 Airport Way",
    "sg:city":"Snohomish",
    "sg:classifiers":[
        {
            "category":"Building & Trades",
            "subcategory":"Construction",
            "type":"Services"
        }
    ],
    "sg:phone":"+1 360 568 4801",
    "sg:postcode":"98296",
    "sg:province":"WA",
    "sg:tags":[
        "excavating",
        "contractor"
    ],
    "sg:website":"www.harveytrucking.com",
    "wof:name":"Lance Harvey Trucking",
    "wof:placetype":"venue"
},
  "geometry": {"coordinates":[-122.098771,47.907501],"type":"Point"}
}