{
  "type": "Feature",
  "properties": {
    "addr:full":"12516 NE 72nd St Vancouver WA 98682",
    "addr:housenumber":"12516",
    "addr:postcode":"98682",
    "addr:street":"Ne 72Nd St",
    "iso:country":"US",
    "sg:address":"12516 NE 72nd St",
    "sg:city":"Vancouver",
    "sg:classifiers":[
        {
            "category":"Professional",
            "subcategory":"Business Services",
            "type":"Services"
        }
    ],
    "sg:phone":"+1 360 944 1325",
    "sg:postcode":"98682",
    "sg:province":"WA",
    "wof:name":"Aurora Enterprises",
    "wof:placetype":"venue"
},
  "geometry": {"coordinates":[-122.543768,45.675094],"type":"Point"}
}