{
  "type": "Feature",
  "properties": {
    "addr:full":"112 12th Ave Seattle WA 98122",
    "addr:housenumber":"112",
    "addr:postcode":"98122",
    "addr:street":"12Th Ave",
    "iso:country":"US",
    "sg:address":"112 12th Ave",
    "sg:city":"Seattle",
    "sg:classifiers":[
        {
            "category":"Restaurant",
            "type":"Food & Drink"
        }
    ],
    "sg:phone":"+1 206 323 9336",
    "sg:postcode":"98122",
    "sg:province":"WA",
    "wof:name":"Country Fisherman Restaurant",
    "wof:placetype":"venue"
},
  "geometry": {"coordinates":[-122.316783,47.601692],"type":"Point"}
}