{
  "type": "Feature",
  "properties": {
    "addr:full":"1510 3rd St Marysville WA 98270",
    "addr:housenumber":"1510",
    "addr:postcode":"98270",
    "addr:street":"3Rd St",
    "iso:country":"US",
    "sg:address":"1510 3rd St",
    "sg:city":"Marysville",
    "sg:classifiers":[
        {
            "category":"Shopping",
            "subcategory":"Books",
            "type":"Retail Goods"
        }
    ],
    "sg:phone":"+1 360 659 4997",
    "sg:postcode":"98270",
    "sg:province":"WA",
    "sg:tags":[
        "merchandise"
    ],
    "sg:website":"www.marysvillebookworks.com",
    "wof:name":"Bookworks",
    "wof:placetype":"venue"
},
  "geometry": {"coordinates":[-122.175408,48.050841],"type":"Point"}
}