{
  "type": "Feature",
  "properties": {
    "addr:full":"20617 Mountain Hwy E Spanaway WA 98387",
    "addr:housenumber":"20617",
    "addr:postcode":"98387",
    "addr:street":"Mountain Hwy E",
    "iso:country":"US",
    "sg:address":"20617 Mountain Hwy E",
    "sg:city":"Spanaway",
    "sg:classifiers":[
        {
            "category":"Manufacturing",
            "subcategory":"Building Materials",
            "type":"Manufacturing & Wholesale Goods"
        }
    ],
    "sg:phone":"+1 253 847 2204",
    "sg:postcode":"98387",
    "sg:province":"WA",
    "sg:tags":[
        "wooden",
        "truss",
        "mfg"
    ],
    "wof:name":"Tacoma Truss Systems Inc",
    "wof:placetype":"venue"
},
  "geometry": {"coordinates":[-122.41419500000001,47.068394],"type":"Point"}
}