{
  "type": "Feature",
  "properties": {
    "addr:full":"5716 95th Pl SW Mukilteo WA 98275",
    "addr:housenumber":"5716",
    "addr:postcode":"98275",
    "addr:street":"95Th Pl Sw",
    "iso:country":"US",
    "sg:address":"5716 95th Pl SW",
    "sg:city":"Mukilteo",
    "sg:classifiers":[
        {
            "category":"Education",
            "subcategory":"School",
            "type":"Public Place"
        }
    ],
    "sg:phone":"+1 425 355 0240",
    "sg:postcode":"98275",
    "sg:province":"WA",
    "wof:name":"Foreign Language For Youth",
    "wof:placetype":"venue"
},
  "geometry": {"coordinates":[-122.31066300000001,47.911867],"type":"Point"}
}