{
  "type": "Feature",
  "properties": {
    "addr:full":"4438 Pacific Ave SE Lacey WA 98503",
    "addr:housenumber":"4438",
    "addr:postcode":"98503",
    "addr:street":"Pacific Ave Se",
    "iso:country":"US",
    "sg:address":"4438 Pacific Ave SE",
    "sg:city":"Lacey",
    "sg:classifiers":[
        {
            "category":"Social Services",
            "type":"Services"
        }
    ],
    "sg:phone":"+1 360 491 0920",
    "sg:postcode":"98503",
    "sg:province":"WA",
    "wof:name":"Damon Counseling Services",
    "wof:placetype":"venue"
},
  "geometry": {"coordinates":[-122.826385,47.037901],"type":"Point"}
}