{
  "type": "Feature",
  "properties": {
    "addr:full":"4210 150th Ave SE Bellevue WA 98006",
    "addr:housenumber":"4210",
    "addr:postcode":"98006",
    "addr:street":"150Th Ave Se",
    "iso:country":"US",
    "sg:address":"4210 150th Ave SE",
    "sg:city":"Bellevue",
    "sg:classifiers":[
        {
            "category":"Real Estate",
            "subcategory":"Architect",
            "type":"Services"
        }
    ],
    "sg:phone":"+1 425 747 5778",
    "sg:postcode":"98006",
    "sg:province":"WA",
    "sg:tags":[
        "architectural"
    ],
    "wof:name":"Clark Group Architects",
    "wof:placetype":"venue"
},
  "geometry": {"coordinates":[-122.14138199999999,47.570043],"type":"Point"}
}