{
  "type": "Feature",
  "properties": {
    "addr:full":"550 Main St Ste B Edmonds WA 98020",
    "addr:housenumber":"550",
    "addr:postcode":"98020",
    "addr:street":"Main St Ste B",
    "iso:country":"US",
    "sg:address":"550 Main St Ste B",
    "sg:city":"Edmonds",
    "sg:classifiers":[
        {
            "category":"Personal",
            "subcategory":"Beauty Salon",
            "type":"Services"
        },
        {
            "category":"Personal",
            "subcategory":"Skin Care",
            "type":"Services"
        }
    ],
    "sg:phone":"+1 425 778 6322",
    "sg:postcode":"98020",
    "sg:province":"WA",
    "sg:website":"http://www.borovina.com",
    "wof:name":"Ombu Salon & Spa Llp",
    "wof:placetype":"venue"
},
  "geometry": {"coordinates":[-122.376395,47.810532],"type":"Point"}
}