{
  "type": "Feature",
  "properties": {
    "addr:full":"2006 196th St SW Lynnwood WA 98036",
    "addr:housenumber":"2006",
    "addr:postcode":"98036",
    "addr:street":"196Th St Sw",
    "iso:country":"US",
    "sg:address":"2006 196th St SW",
    "sg:city":"Lynnwood",
    "sg:classifiers":[
        {
            "category":"Wholesale",
            "subcategory":"Electrical",
            "type":"Manufacturing & Wholesale Goods"
        }
    ],
    "sg:phone":"+1 425 774 5554",
    "sg:postcode":"98036",
    "sg:province":"WA",
    "sg:tags":[
        "communication",
        "radio",
        "system"
    ],
    "wof:name":"Advanced Electronic Applctns",
    "wof:placetype":"venue"
},
  "geometry": {"coordinates":[-122.26168,47.820522],"type":"Point"}
}