{
  "type": "Feature",
  "properties": {
    "addr:full":"5718 NE Gamblewood Rd Kingston WA 98346",
    "addr:housenumber":"5718",
    "addr:postcode":"98346",
    "addr:street":"Ne Gamblewood Rd",
    "iso:country":"US",
    "sg:address":"5718 NE Gamblewood Rd",
    "sg:city":"Kingston",
    "sg:classifiers":[
        {
            "category":"Education",
            "subcategory":"School",
            "type":"Public Place"
        }
    ],
    "sg:phone":"+1 360 297 7383",
    "sg:postcode":"98346",
    "sg:province":"WA",
    "sg:tags":[
        "sewing"
    ],
    "wof:name":"Manzanita Mystic",
    "wof:placetype":"venue"
},
  "geometry": {"coordinates":[-122.572817,47.813669],"type":"Point"}
}