{
  "type": "Feature",
  "properties": {
    "addr:full":"1 Oneonta Dr Wenatchee WA 98801",
    "addr:housenumber":"1",
    "addr:postcode":"98801",
    "addr:street":"Oneonta Dr",
    "iso:country":"US",
    "sg:address":"1 Oneonta Dr",
    "sg:city":"Wenatchee",
    "sg:classifiers":[
        {
            "category":"Farming",
            "subcategory":"Orchard",
            "type":"Manufacturing & Wholesale Goods"
        },
        {
            "category":"Retail",
            "subcategory":"Storage",
            "type":"Services"
        },
        {
            "category":"Sports & Exercise",
            "subcategory":"Playing Field",
            "type":"Entertainment"
        }
    ],
    "sg:phone":"+1 509 663 2788",
    "sg:postcode":"98801",
    "sg:province":"WA",
    "sg:tags":[
        "packer",
        "vegetable",
        "warehouse",
        "fruit",
        "cold"
    ],
    "wof:name":"Bear Mountain Ranch Golf Course",
    "wof:placetype":"venue"
},
  "geometry": {"coordinates":[-120.316879,47.43832],"type":"Point"}
}