{
  "type": "Feature",
  "properties": {
    "addr:full":"601 NW Market St Seattle WA 98107",
    "addr:housenumber":"601",
    "addr:postcode":"98107",
    "addr:street":"Nw Market St",
    "iso:country":"US",
    "sg:address":"601 NW Market St",
    "sg:city":"Seattle",
    "sg:classifiers":[
        {
            "category":"Retail",
            "subcategory":"Auto Repair",
            "type":"Services"
        }
    ],
    "sg:phone":"+1 206 784 5759",
    "sg:postcode":"98107",
    "sg:province":"WA",
    "sg:tags":[
        "body"
    ],
    "wof:name":"D & G Auto Repair",
    "wof:placetype":"venue"
},
  "geometry": {"coordinates":[-122.36404,47.668513],"type":"Point"}
}