{
  "type": "Feature",
  "properties": {
    "addr:full":"6466 Marshall Ave SW Seattle WA 98136",
    "addr:housenumber":"6466",
    "addr:postcode":"98136",
    "addr:street":"Marshall Ave Sw",
    "iso:country":"US",
    "sg:address":"6466 Marshall Ave SW",
    "sg:city":"Seattle",
    "sg:classifiers":[
        {
            "category":"Professional",
            "subcategory":"Management & Consulting",
            "type":"Services"
        }
    ],
    "sg:phone":"+1 206 937 5298",
    "sg:postcode":"98136",
    "sg:province":"WA",
    "sg:tags":[
        "marketing",
        "consultant"
    ],
    "wof:name":"Baker Bakr Mktg Cmmnctions LLC",
    "wof:placetype":"venue"
},
  "geometry": {"coordinates":[-122.393345,47.544297],"type":"Point"}
}