{
  "type": "Feature",
  "properties": {
    "iso:country":"US",
    "sg:address":"306 Insel Rd",
    "sg:city":"Woodland",
    "sg:classifiers":[
        {
            "category":"Manufacturing",
            "subcategory":"Lumber",
            "type":"Manufacturing & Wholesale Goods"
        }
    ],
    "sg:phone":"+1 360 225 8833",
    "sg:postcode":"98674",
    "sg:province":"WA",
    "sg:tags":[
        "logging"
    ],
    "wof:name":"Billy Carl Mc Lendon",
    "wof:placetype":"venue"
},
  "geometry": {"coordinates":[-122.733878,45.92346],"type":"Point"}
}