{
  "type": "Feature",
  "properties": {
    "addr:full":"20801 Rd 1 SE Warden WA 98857",
    "addr:postcode":"20801;98857",
    "addr:street":"Rd 1 Se Warden",
    "iso:country":"US",
    "sg:address":"20801 Rd 1 SE",
    "sg:city":"Warden",
    "sg:classifiers":[
        {
            "category":"Farming",
            "subcategory":"Farm & Veterinary Services",
            "type":"Manufacturing & Wholesale Goods"
        }
    ],
    "sg:phone":"+1 509 349 2935",
    "sg:postcode":"98857",
    "sg:province":"WA",
    "sg:tags":[
        "livestock"
    ],
    "wof:name":"Reyburn Inc",
    "wof:placetype":"venue"
},
  "geometry": {"coordinates":[-119.072754,47.071547],"type":"Point"}
}