{
  "type": "Feature",
  "properties": {
    "addr:full":"3004 96th St S Lakewood WA 98499",
    "addr:housenumber":"3004",
    "addr:postcode":"98499",
    "addr:street":"96Th St S",
    "iso:country":"US",
    "sg:address":"3004 96th St S",
    "sg:city":"Lakewood",
    "sg:classifiers":[
        {
            "category":"Wholesale",
            "subcategory":"Machinery & Supplies",
            "type":"Manufacturing & Wholesale Goods"
        },
        {
            "category":"Manufacturing",
            "subcategory":"Chemicals & Compounds",
            "type":"Manufacturing & Wholesale Goods"
        }
    ],
    "sg:phone":"+1 253 581 2323",
    "sg:postcode":"98499",
    "sg:province":"WA",
    "sg:tags":[
        "product",
        "floor",
        "distributor",
        "care",
        "janitor",
        "manufacturer"
    ],
    "wof:name":"Tower Industries Inc",
    "wof:placetype":"venue"
},
  "geometry": {"coordinates":[-122.47277,47.170209],"type":"Point"}
}