{
  "type": "Feature",
  "properties": {
    "addr:full":"18409 NW Montreux Dr Issaquah WA 98027",
    "addr:housenumber":"18409",
    "addr:postcode":"98027",
    "addr:street":"Nw Montreux Dr",
    "iso:country":"US",
    "sg:address":"18409 NW Montreux Dr",
    "sg:city":"Issaquah",
    "sg:classifiers":[
        {
            "category":"Banks & Credit Unions",
            "subcategory":"Bank",
            "type":"Services"
        }
    ],
    "sg:phone":"+1 425 562 4582",
    "sg:postcode":"98027",
    "sg:province":"WA",
    "sg:tags":[
        "federal",
        "agency"
    ],
    "wof:name":"America Beehive Co",
    "wof:placetype":"venue"
},
  "geometry": {"coordinates":[-122.09537899999999,47.554062],"type":"Point"}
}