{
  "type": "Feature",
  "properties": {
    "addr:full":"4505 44th Ave SW Seattle WA 98116",
    "addr:housenumber":"4505",
    "addr:postcode":"98116",
    "addr:street":"44Th Ave Sw",
    "iso:country":"US",
    "sg:address":"4505 44th Ave SW",
    "sg:city":"Seattle",
    "sg:classifiers":[
        {
            "category":"Social Services",
            "type":"Services"
        }
    ],
    "sg:phone":"+1 206 932 2393",
    "sg:postcode":"98116",
    "sg:province":"WA",
    "wof:name":"Hall Adam C MA",
    "wof:placetype":"venue"
},
  "geometry": {"coordinates":[-122.38820800000001,47.561173],"type":"Point"}
}