{
  "type": "Feature",
  "properties": {
    "addr:full":"3002 NW Market Street Seattle WA 98107",
    "addr:housenumber":"3002",
    "addr:postcode":"98107",
    "addr:street":"Nw Market Street",
    "iso:country":"US",
    "sg:address":"3002 NW Market Street",
    "sg:city":"Seattle",
    "sg:classifiers":[
        {
            "category":"Personal",
            "subcategory":"Massage",
            "type":"Services"
        }
    ],
    "sg:phone":"+1 206 518 7404",
    "sg:postcode":"98107",
    "sg:province":"WA",
    "sg:website":"www.UrbanReflexology.com",
    "wof:name":"Urban Reflexology",
    "wof:placetype":"venue"
},
  "geometry": {"coordinates":[-122.39570000000001,47.668647],"type":"Point"}
}