{
  "type": "Feature",
  "properties": {
    "addr:full":"6109 E Clements Ln Spokane WA 99217",
    "addr:housenumber":"6109",
    "addr:postcode":"99217",
    "addr:street":"E Clements Ln",
    "iso:country":"US",
    "sg:address":"6109 E Clements Ln",
    "sg:city":"Spokane",
    "sg:classifiers":[
        {
            "category":"Real Estate",
            "subcategory":"Real Estate Agent",
            "type":"Services"
        }
    ],
    "sg:phone":"+1 509 489 2208",
    "sg:postcode":"99217",
    "sg:province":"WA",
    "wof:name":"Appraisal Institute",
    "wof:placetype":"venue"
},
  "geometry": {"coordinates":[-117.32165000000001,47.713142],"type":"Point"}
}