{
  "type": "Feature",
  "properties": {
    "addr:full":"3523 W Hood Ave Kennewick WA 99336",
    "addr:housenumber":"3523",
    "addr:postcode":"99336",
    "addr:street":"W Hood Ave",
    "iso:country":"US",
    "sg:address":"3523 W Hood Ave",
    "sg:city":"Kennewick",
    "sg:classifiers":[
        {
            "category":"Personal",
            "subcategory":"Beauty Salon",
            "type":"Services"
        }
    ],
    "sg:phone":"+1 509 737 0355",
    "sg:postcode":"99336",
    "sg:province":"WA",
    "sg:tags":[
        "shop"
    ],
    "wof:name":"One Touch Salon",
    "wof:placetype":"venue"
},
  "geometry": {"coordinates":[-119.1705,46.215874],"type":"Point"}
}