{
  "type": "Feature",
  "properties": {
    "iso:country":"US",
    "sg:address":"10500 NE 8th St",
    "sg:city":"Bellevue",
    "sg:classifiers":[
        {
            "category":"Shopping",
            "subcategory":"Clothing, Apparel, & Fashions",
            "type":"Retail Goods"
        }
    ],
    "sg:phone":"+1 425 637 6747",
    "sg:postcode":"98004",
    "sg:province":"WA",
    "wof:name":"Foerester Fur Corporation",
    "wof:placetype":"venue"
},
  "geometry": {"coordinates":[-122.199912,47.617499],"type":"Point"}
}