{
  "type": "Feature",
  "properties": {
    "addr:full":"6622 N Perry St Spokane WA 99217",
    "addr:housenumber":"6622",
    "addr:postcode":"99217",
    "addr:street":"N Perry St",
    "iso:country":"US",
    "sg:address":"6622 N Perry St",
    "sg:city":"Spokane",
    "sg:classifiers":[
        {
            "category":"Retail",
            "subcategory":"Auto Rental",
            "type":"Services"
        }
    ],
    "sg:phone":"+1 509 484 8662",
    "sg:postcode":"99217",
    "sg:province":"WA",
    "sg:tags":[
        "renting",
        "truck",
        "leasing"
    ],
    "wof:name":"U-Haul Co",
    "wof:placetype":"venue"
},
  "geometry": {"coordinates":[-117.389912,47.718419],"type":"Point"}
}