{
  "type": "Feature",
  "properties": {
    "addr:full":"3208 W Wernett Rd Pasco WA 99301",
    "addr:housenumber":"3208",
    "addr:postcode":"99301",
    "addr:street":"W Wernett Rd",
    "iso:country":"US",
    "sg:address":"3208 W Wernett Rd",
    "sg:city":"Pasco",
    "sg:classifiers":[
        {
            "category":"Manufacturing",
            "subcategory":"Signs",
            "type":"Manufacturing & Wholesale Goods"
        }
    ],
    "sg:phone":"+1 509 544 8960",
    "sg:postcode":"99301",
    "sg:province":"WA",
    "sg:tags":[
        "specialty",
        "mfg"
    ],
    "wof:name":"B&R Signs",
    "wof:placetype":"venue"
},
  "geometry": {"coordinates":[-119.13401,46.248754],"type":"Point"}
}