{
  "type": "Feature",
  "properties": {
    "iso:country":"US",
    "sg:address":"4949 Woodcock Rd",
    "sg:city":"Sequim",
    "sg:classifiers":[
        {
            "category":"Social Services",
            "type":"Services"
        }
    ],
    "sg:phone":"+1 360 681 2250",
    "sg:postcode":"98382",
    "sg:province":"WA",
    "wof:name":"Parenting Matters Foundation",
    "wof:placetype":"venue"
},
  "geometry": {"coordinates":[-123.10914099999999,48.116104],"type":"Point"}
}