{
  "type": "Feature",
  "properties": {
    "addr:full":"205 SW 152nd St Burien WA 98166",
    "addr:housenumber":"205",
    "addr:postcode":"98166",
    "addr:street":"Sw 152Nd St",
    "iso:country":"US",
    "sg:address":"205 SW 152nd St",
    "sg:city":"Burien",
    "sg:classifiers":[
        {
            "category":"Bars & Pubs",
            "type":"Food & Drink"
        },
        {
            "category":"Restaurant",
            "type":"Food & Drink"
        }
    ],
    "sg:phone":"+1 206 244 4084",
    "sg:postcode":"98166",
    "sg:province":"WA",
    "sg:tags":[
        "thai",
        "lunch",
        "asian",
        "breakfast",
        "brunch",
        "pan"
    ],
    "sg:website":"http://yosbistro.com",
    "wof:name":"Yo's Bistro",
    "wof:placetype":"venue"
},
  "geometry": {"coordinates":[-122.336625,47.466861],"type":"Point"}
}