{
  "type": "Feature",
  "properties": {
    "addr:full":"1501 S Snoqualmie St Seattle WA 98108",
    "addr:housenumber":"1501",
    "addr:postcode":"98108",
    "addr:street":"S Snoqualmie St",
    "iso:country":"US",
    "sg:address":"1501 S Snoqualmie St",
    "sg:city":"Seattle",
    "sg:classifiers":[
        {
            "category":"Personal",
            "type":"Services"
        },
        {
            "category":"Professional",
            "subcategory":"Art Services",
            "type":"Services"
        }
    ],
    "sg:phone":"+1 206 767 5183",
    "sg:postcode":"98108",
    "sg:province":"WA",
    "sg:tags":[
        "photography",
        "videography",
        "wedding"
    ],
    "wof:name":"Eunice Gong Photography",
    "wof:placetype":"venue"
},
  "geometry": {"coordinates":[-122.31345399999999,47.561691],"type":"Point"}
}