{
  "type": "Feature",
  "properties": {
    "iso:country":"US",
    "sg:address":"16534 5th Ave S",
    "sg:city":"Seattle",
    "sg:classifiers":[
        {
            "category":"Personal",
            "subcategory":"Beauty Salon",
            "type":"Services"
        }
    ],
    "sg:phone":"+1 206 242 7753",
    "sg:postcode":"98148",
    "sg:province":"WA",
    "sg:tags":[
        "shop"
    ],
    "wof:name":"Company-Hrcutters-Hairdressers",
    "wof:placetype":"venue"
},
  "geometry": {"coordinates":[-122.32744700000001,47.453386],"type":"Point"}
}