{
  "type": "Feature",
  "properties": {
    "addr:full":"7602 89th Ave SW Lakewood WA 98498",
    "addr:housenumber":"7602",
    "addr:postcode":"98498",
    "addr:street":"89Th Ave Sw",
    "iso:country":"US",
    "sg:address":"7602 89th Ave SW",
    "sg:city":"Lakewood",
    "sg:classifiers":[
        {
            "category":"Building & Trades",
            "subcategory":"Construction",
            "type":"Services"
        }
    ],
    "sg:phone":"+1 253 584 9477",
    "sg:postcode":"98498",
    "sg:province":"WA",
    "sg:tags":[
        "house"
    ],
    "wof:name":"George Lightner & Associates",
    "wof:placetype":"venue"
},
  "geometry": {"coordinates":[-122.555504,47.187404],"type":"Point"}
}