{
  "type": "Feature",
  "properties": {
    "addr:full":"206 SW 112th St Seattle WA 98146",
    "addr:housenumber":"206",
    "addr:postcode":"98146",
    "addr:street":"Sw 112Th St",
    "iso:country":"US",
    "sg:address":"206 SW 112th St",
    "sg:city":"Seattle",
    "sg:classifiers":[
        {
            "category":"Professional",
            "subcategory":"Employment Agencies",
            "type":"Services"
        }
    ],
    "sg:phone":"+1 206 243 2561",
    "sg:postcode":"98146",
    "sg:province":"WA",
    "sg:tags":[
        "job"
    ],
    "wof:name":"Olympus Electronics Inc",
    "wof:placetype":"venue"
},
  "geometry": {"coordinates":[-122.33771400000001,47.503155],"type":"Point"}
}