{
  "type": "Feature",
  "properties": {
    "addr:full":"702 Franklin Ave Sunnyside WA 98944",
    "addr:housenumber":"702",
    "addr:postcode":"98944",
    "addr:street":"Franklin Ave",
    "iso:country":"US",
    "sg:address":"702 Franklin Ave",
    "sg:city":"Sunnyside",
    "sg:classifiers":[
        {
            "category":"Health Services",
            "subcategory":"Doctor",
            "type":"Services"
        },
        {
            "category":"Health Services",
            "subcategory":"Clinic",
            "type":"Services"
        },
        {
            "category":"Personal",
            "type":"Services"
        }
    ],
    "sg:phone":"+1 509 837 7700",
    "sg:postcode":"98944",
    "sg:province":"WA",
    "sg:tags":[
        "physician",
        "information",
        "surgeons",
        "outpatient",
        "counselors-licensed",
        "treatment",
        "medicine",
        "professional",
        "addiction",
        "alcoholism"
    ],
    "sg:website":"http://www.meritresourceservices.org",
    "wof:name":"Merit Resource Service",
    "wof:placetype":"venue"
},
  "geometry": {"coordinates":[-120.01149100000001,46.322479],"type":"Point"}
}