{
  "type": "Feature",
  "properties": {
    "iso:country":"US",
    "sg:address":"3101 W Clearwater Ave",
    "sg:city":"Kennewick",
    "sg:classifiers":[
        {
            "category":"Home & Garden",
            "subcategory":"Furniture",
            "type":"Retail Goods"
        }
    ],
    "sg:phone":"+1 509 783 3175",
    "sg:postcode":"99336",
    "sg:province":"WA",
    "sg:tags":[
        "futon",
        "accessory"
    ],
    "wof:name":"International Futon Co",
    "wof:placetype":"venue"
},
  "geometry": {"coordinates":[-119.163096,46.212285],"type":"Point"}
}