{
  "type": "Feature",
  "properties": {
    "addr:full":"7530 34th Ave NW Seattle WA 98117",
    "addr:housenumber":"7530",
    "addr:postcode":"98117",
    "addr:street":"34Th Ave Nw",
    "iso:country":"US",
    "sg:address":"7530 34th Ave NW",
    "sg:city":"Seattle",
    "sg:classifiers":[
        {
            "category":"Professional",
            "subcategory":"Art Services",
            "type":"Services"
        }
    ],
    "sg:phone":"+1 206 783 5227",
    "sg:postcode":"98117",
    "sg:province":"WA",
    "sg:tags":[
        "photography",
        "commercial"
    ],
    "wof:name":"Arthur & Assoc",
    "wof:placetype":"venue"
},
  "geometry": {"coordinates":[-122.400347,47.684657],"type":"Point"}
}