{
  "type": "Feature",
  "properties": {
    "iso:country":"US",
    "sg:address":"2109 196th St SW",
    "sg:city":"Lynnwood",
    "sg:classifiers":[
        {
            "category":"Home & Garden",
            "subcategory":"Household Appliances",
            "type":"Retail Goods"
        }
    ],
    "sg:phone":"+1 425 771 3621",
    "sg:postcode":"98036",
    "sg:province":"WA",
    "sg:tags":[
        "cleaners",
        "vacuum",
        "repair"
    ],
    "wof:name":"Alderwood Vacuum Sales & Svcs",
    "wof:placetype":"venue"
},
  "geometry": {"coordinates":[-122.26164,47.820667],"type":"Point"}
}