{
  "type": "Feature",
  "properties": {
    "addr:full":"5780 Vista Dr Ferndale WA 98248",
    "addr:housenumber":"5780",
    "addr:postcode":"98248",
    "addr:street":"Vista Dr",
    "iso:country":"US",
    "sg:address":"5780 Vista Dr",
    "sg:city":"Ferndale",
    "sg:classifiers":[
        {
            "category":"Building & Trades",
            "subcategory":"Construction",
            "type":"Services"
        }
    ],
    "sg:phone":"+1 360 380 6722",
    "sg:postcode":"98248",
    "sg:province":"WA",
    "sg:tags":[
        "house"
    ],
    "wof:name":"Kestrel Homes Inc",
    "wof:placetype":"venue"
},
  "geometry": {"coordinates":[-122.596103,48.852023],"type":"Point"}
}