{
  "type": "Feature",
  "properties": {
    "addr:full":"1275 12th Ave NW Ste 13 Issaquah WA 98027",
    "addr:housenumber":"1275",
    "addr:postcode":"98027",
    "addr:street":"12Th Ave Nw Ste 13",
    "iso:country":"US",
    "sg:address":"1275 12th Ave NW Ste 13",
    "sg:city":"Issaquah",
    "sg:classifiers":[
        {
            "category":"Manufacturing",
            "subcategory":"Paper Products",
            "type":"Manufacturing & Wholesale Goods"
        }
    ],
    "sg:phone":"+1 425 837 8090",
    "sg:postcode":"98027",
    "sg:province":"WA",
    "sg:tags":[
        "products-wholesale",
        "manufacturer"
    ],
    "sg:website":"http://www.seaport-intl.com",
    "wof:name":"Seaport International, Inc.",
    "wof:placetype":"venue"
},
  "geometry": {"coordinates":[-122.05744,47.545384],"type":"Point"}
}