{
  "type": "Feature",
  "properties": {
    "addr:full":"407 Valley Ave NE Puyallup WA 98372",
    "addr:housenumber":"407",
    "addr:postcode":"98372",
    "addr:street":"Valley Ave Ne",
    "iso:country":"US",
    "sg:address":"407 Valley Ave NE",
    "sg:city":"Puyallup",
    "sg:classifiers":[
        {
            "category":"Real Estate",
            "subcategory":"Real Estate Operator",
            "type":"Services"
        }
    ],
    "sg:phone":"+1 253 840 8500",
    "sg:postcode":"98372",
    "sg:province":"WA",
    "sg:tags":[
        "apartment"
    ],
    "sg:website":"www.meridianpointe.com",
    "wof:name":"Meridian Point Apts",
    "wof:placetype":"venue"
},
  "geometry": {"coordinates":[-122.293008,47.20615],"type":"Point"}
}