{
  "type": "Feature",
  "properties": {
    "addr:full":"13072 Stratford Rd NE Moses Lake WA 98837",
    "addr:housenumber":"13072",
    "addr:postcode":"98837",
    "addr:street":"Stratford Rd Ne",
    "iso:country":"US",
    "sg:address":"13072 Stratford Rd NE",
    "sg:city":"Moses Lake",
    "sg:classifiers":[
        {
            "category":"Farming",
            "subcategory":"Livestock Farm",
            "type":"Manufacturing & Wholesale Goods"
        }
    ],
    "sg:phone":"+1 509 765 9026",
    "sg:postcode":"98837",
    "sg:province":"WA",
    "sg:tags":[
        "beef",
        "feedlot",
        "cattle"
    ],
    "wof:name":"Dennis Plemons",
    "wof:placetype":"venue"
},
  "geometry": {"coordinates":[-119.277097,47.292901],"type":"Point"}
}