{
  "type": "Feature",
  "properties": {
    "addr:full":"32808 13th Ave SW Federal Way WA 98023",
    "addr:housenumber":"32808",
    "addr:postcode":"98023",
    "addr:street":"13Th Ave Sw Federal Way",
    "iso:country":"US",
    "sg:address":"32808 13th Ave SW",
    "sg:city":"Federal Way",
    "sg:classifiers":[
        {
            "category":"Professional",
            "subcategory":"Management & Consulting",
            "type":"Services"
        }
    ],
    "sg:phone":"+1 253 838 6494",
    "sg:postcode":"98023",
    "sg:province":"WA",
    "sg:tags":[
        "retail",
        "direct",
        "sales"
    ],
    "wof:name":"Dingman & Associates",
    "wof:placetype":"venue"
},
  "geometry": {"coordinates":[-122.352429,47.307279],"type":"Point"}
}