{
  "type": "Feature",
  "properties": {
    "addr:full":"1505 Columbia St Vancouver WA 98660",
    "addr:housenumber":"1505",
    "addr:postcode":"98660",
    "addr:street":"Columbia St",
    "iso:country":"US",
    "sg:address":"1505 Columbia St",
    "sg:city":"Vancouver",
    "sg:classifiers":[
        {
            "category":"Retail",
            "subcategory":"Auto Repair",
            "type":"Services"
        }
    ],
    "sg:phone":"+1 360 694 7599",
    "sg:postcode":"98660",
    "sg:province":"WA",
    "sg:tags":[
        "body",
        "shop",
        "repairing",
        "automobile"
    ],
    "wof:name":"Dings Frame & Axle",
    "wof:placetype":"venue"
},
  "geometry": {"coordinates":[-122.674004,45.633099],"type":"Point"}
}