{
  "type": "Feature",
  "properties": {
    "iso:country":"US",
    "sg:address":"1131 Highland Ave",
    "sg:city":"Bremerton",
    "sg:classifiers":[
        {
            "category":"Manufacturing",
            "subcategory":"Glass & Minerals",
            "type":"Manufacturing & Wholesale Goods"
        }
    ],
    "sg:phone":"+1 360 479 2125",
    "sg:postcode":"98337",
    "sg:province":"WA",
    "sg:tags":[
        "product",
        "mfg"
    ],
    "wof:name":"Creo Glass Corp",
    "wof:placetype":"venue"
},
  "geometry": {"coordinates":[-122.62555399999999,47.572318],"type":"Point"}
}