{
  "type": "Feature",
  "properties": {
    "addr:full":"404 Bell St Edmonds WA 98020",
    "addr:housenumber":"404",
    "addr:postcode":"98020",
    "addr:street":"Bell",
    "iso:country":"US",
    "sg:address":"404 Bell St",
    "sg:city":"Edmonds",
    "sg:classifiers":[
        {
            "category":"Organizations",
            "subcategory":"Religious Organization",
            "type":"Services"
        }
    ],
    "sg:phone":"+1 425 776 9800",
    "sg:postcode":"98020",
    "sg:province":"WA",
    "sg:tags":[
        "church"
    ],
    "sg:website":"www.northsoundchurch.com",
    "wof:name":"North Sound Church",
    "wof:placetype":"venue"
},
  "geometry": {"coordinates":[-122.376644,47.811541],"type":"Point"}
}