{
  "type": "Feature",
  "properties": {
    "addr:full":"6616 166th Ave E Sumner WA 98390",
    "addr:housenumber":"6616",
    "addr:postcode":"98390",
    "addr:street":"166Th Ave E",
    "iso:country":"US",
    "sg:address":"6616 166th Ave E",
    "sg:city":"Sumner",
    "sg:classifiers":[
        {
            "category":"Autos & Motor Vehicles",
            "subcategory":"Automobile Sales",
            "type":"Retail Goods"
        }
    ],
    "sg:phone":"+1 253 863 2211",
    "sg:postcode":"98390",
    "sg:province":"WA",
    "sg:tags":[
        "new",
        "truck",
        "car"
    ],
    "sg:website":"http://www.ford.com/footer/dealer-directory?Criteria=/WA/Sumner",
    "wof:name":"Riverside Ford Inc",
    "wof:placetype":"venue"
},
  "geometry": {"coordinates":[-122.208152,47.197369],"type":"Point"}
}