{
  "type": "Feature",
  "properties": {
    "addr:full":"Bldg Lakewood WA 98439",
    "addr:postcode":"98439",
    "iso:country":"US",
    "sg:address":"Bldg",
    "sg:city":"Lakewood",
    "sg:classifiers":[
        {
            "category":"Shopping",
            "subcategory":"Optician",
            "type":"Retail Goods"
        }
    ],
    "sg:phone":"+1 253 588 9288",
    "sg:postcode":"98439",
    "sg:province":"WA",
    "sg:tags":[
        "eyewear"
    ],
    "wof:name":"National Vision Optical",
    "wof:placetype":"venue"
},
  "geometry": {"coordinates":[-122.522003,47.1213],"type":"Point"}
}