{
  "type": "Feature",
  "properties": {
    "addr:full":"213 N I St Tacoma WA 98403",
    "addr:housenumber":"213",
    "addr:postcode":"98403",
    "addr:street":"N I St",
    "iso:country":"US",
    "sg:address":"213 N I St",
    "sg:city":"Tacoma",
    "sg:classifiers":[
        {
            "category":"Shopping",
            "subcategory":"Used Merchandise",
            "type":"Retail Goods"
        }
    ],
    "sg:phone":"+1 253 272 9828",
    "sg:postcode":"98403",
    "sg:province":"WA",
    "wof:name":"Collectors Nook",
    "wof:placetype":"venue"
},
  "geometry": {"coordinates":[-122.453007,47.262767],"type":"Point"}
}