{
  "type": "Feature",
  "properties": {
    "addr:full":"41104 S Morton Rd Kennewick WA 99337",
    "addr:housenumber":"41104",
    "addr:postcode":"99337",
    "addr:street":"S Morton Rd",
    "iso:country":"US",
    "sg:address":"41104 S Morton Rd",
    "sg:city":"Kennewick",
    "sg:classifiers":[
        {
            "category":"Wholesale",
            "subcategory":"Home Furnishings",
            "type":"Manufacturing & Wholesale Goods"
        }
    ],
    "sg:phone":"+1 509 586 2026",
    "sg:postcode":"99337",
    "sg:province":"WA",
    "sg:tags":[
        "floor",
        "covering"
    ],
    "wof:name":"Bear Bottoms Floor Coverings",
    "wof:placetype":"venue"
},
  "geometry": {"coordinates":[-119.023499,46.147384],"type":"Point"}
}