{
  "type": "Feature",
  "properties": {
    "iso:country":"US",
    "sg:address":"1618 22nd St",
    "sg:city":"Anacortes",
    "sg:classifiers":[
        {
            "category":"Recreation",
            "subcategory":"Marina",
            "type":"Entertainment"
        }
    ],
    "sg:phone":"+1 360 293 4155",
    "sg:postcode":"98221",
    "sg:province":"WA",
    "sg:tags":[
        "repairing",
        "boat"
    ],
    "wof:name":"R & D Enterprises",
    "wof:placetype":"venue"
},
  "geometry": {"coordinates":[-122.62347800000001,48.504645],"type":"Point"}
}