{
  "type": "Feature",
  "properties": {
    "addr:full":"1717 Pacific Ave Tacoma WA 98402",
    "addr:housenumber":"1717",
    "addr:postcode":"98402",
    "addr:street":"Pacific Ave",
    "iso:country":"US",
    "sg:address":"1717 Pacific Ave",
    "sg:city":"Tacoma",
    "sg:classifiers":[
        {
            "category":"Government",
            "subcategory":"Court House",
            "type":"Public Place"
        }
    ],
    "sg:phone":"+1 253 593 6751",
    "sg:postcode":"98402",
    "sg:province":"WA",
    "wof:name":"U S Magistrate",
    "wof:placetype":"venue"
},
  "geometry": {"coordinates":[-122.436702,47.245264],"type":"Point"}
}