{
  "type": "Feature",
  "properties": {
    "addr:full":"465 NE Midway Blvd Oak Harbor WA 98277",
    "addr:housenumber":"465",
    "addr:postcode":"98277",
    "addr:street":"Ne Midway Blvd",
    "iso:country":"US",
    "sg:address":"465 NE Midway Blvd",
    "sg:city":"Oak Harbor",
    "sg:classifiers":[
        {
            "category":"Shopping",
            "subcategory":"Department Store",
            "type":"Retail Goods"
        }
    ],
    "sg:phone":"+1 360 675 0660",
    "sg:postcode":"98277",
    "sg:province":"WA",
    "wof:name":"Sears Roebuck & Co",
    "wof:placetype":"venue"
},
  "geometry": {"coordinates":[-122.643327,48.299882],"type":"Point"}
}