{
  "type": "Feature",
  "properties": {
    "addr:full":"13407 NE 20th St Ste 5 Bellevue WA 98005",
    "addr:housenumber":"13407",
    "addr:postcode":"98005",
    "addr:street":"Ne 20Th St Ste 5",
    "iso:country":"US",
    "sg:address":"13407 NE 20th St Ste 5",
    "sg:city":"Bellevue",
    "sg:classifiers":[
        {
            "category":"Sports & Exercise",
            "subcategory":"Tennis Court",
            "type":"Entertainment"
        }
    ],
    "sg:phone":"+1 425 644 7833",
    "sg:postcode":"98005",
    "sg:province":"WA",
    "wof:name":"Seattle Pacific Table Tennis Club",
    "wof:placetype":"venue"
},
  "geometry": {"coordinates":[-122.16083500000001,47.628016],"type":"Point"}
}