{
  "type": "Feature",
  "properties": {
    "addr:full":"6516 38th Ave NE Seattle WA 98115",
    "addr:housenumber":"6516",
    "addr:postcode":"98115",
    "addr:street":"38Th Ave Ne",
    "iso:country":"US",
    "sg:address":"6516 38th Ave NE",
    "sg:city":"Seattle",
    "sg:classifiers":[
        {
            "category":"Building & Trades",
            "subcategory":"Construction",
            "type":"Services"
        }
    ],
    "sg:phone":"+1 206 524 9198",
    "sg:postcode":"98115",
    "sg:province":"WA",
    "sg:tags":[
        "contractor"
    ],
    "wof:name":"Chris Custom Tile",
    "wof:placetype":"venue"
},
  "geometry": {"coordinates":[-122.287012,47.677501],"type":"Point"}
}