{
  "type": "Feature",
  "properties": {
    "addr:full":"109 W Yakima Ave Selah WA 98942",
    "addr:housenumber":"109",
    "addr:postcode":"98942",
    "addr:street":"W Yakima Ave",
    "iso:country":"US",
    "sg:address":"109 W Yakima Ave",
    "sg:city":"Selah",
    "sg:classifiers":[
        {
            "category":"Health Services",
            "subcategory":"Dentist",
            "type":"Services"
        }
    ],
    "sg:phone":"+1 509 697 4821",
    "sg:postcode":"98942",
    "sg:province":"WA",
    "wof:name":"King, Jennifer K Dds",
    "wof:placetype":"venue"
},
  "geometry": {"coordinates":[-120.530552,46.652293],"type":"Point"}
}