{
  "type": "Feature",
  "properties": {
    "addr:full":"1918 Kansas Ave Anacortes WA 98221",
    "addr:housenumber":"1918",
    "addr:postcode":"98221",
    "addr:street":"Kansas Ave",
    "iso:country":"US",
    "sg:address":"1918 Kansas Ave",
    "sg:city":"Anacortes",
    "sg:classifiers":[
        {
            "category":"Professional",
            "subcategory":"Management & Consulting",
            "type":"Services"
        }
    ],
    "sg:phone":"+1 360 588 0360",
    "sg:postcode":"98221",
    "sg:province":"WA",
    "sg:tags":[
        "consultant"
    ],
    "wof:name":"NSC",
    "wof:placetype":"venue"
},
  "geometry": {"coordinates":[-122.650142,48.501274],"type":"Point"}
}