{
  "type": "Feature",
  "properties": {
    "iso:country":"US",
    "sg:address":"2495 Cape George Rd",
    "sg:city":"Port Townsend",
    "sg:classifiers":[
        {
            "category":"Building & Trades",
            "subcategory":"Plumbing",
            "type":"Services"
        }
    ],
    "sg:phone":"+1 360 385 7155",
    "sg:postcode":"98368",
    "sg:province":"WA",
    "sg:tags":[
        "hauler",
        "waste",
        "portable",
        "liquid",
        "sanitation"
    ],
    "wof:name":"Good Man Sanitation",
    "wof:placetype":"venue"
},
  "geometry": {"coordinates":[-122.86592,48.102374],"type":"Point"}
}