{
  "type": "Feature",
  "properties": {
    "addr:full":"122 E Poplar St Walla Walla WA 99362",
    "addr:housenumber":"122",
    "addr:postcode":"99362",
    "addr:street":"E Poplar St",
    "iso:country":"US",
    "sg:address":"122 E Poplar St",
    "sg:city":"Walla Walla",
    "sg:classifiers":[
        {
            "category":"Government",
            "subcategory":"Office",
            "type":"Public Place"
        }
    ],
    "sg:phone":"+1 509 527 4502",
    "sg:postcode":"99362",
    "sg:province":"WA",
    "sg:tags":[
        "social"
    ],
    "wof:name":"Vocational Rehabilitation",
    "wof:placetype":"venue"
},
  "geometry": {"coordinates":[-118.33562499999999,46.065849],"type":"Point"}
}