{
  "type": "Feature",
  "properties": {
    "addr:full":"32526 112th Pl SE Auburn WA 98092",
    "addr:housenumber":"32526",
    "addr:postcode":"98092",
    "addr:street":"112Th Pl Se",
    "iso:country":"US",
    "sg:address":"32526 112th Pl SE",
    "sg:city":"Auburn",
    "sg:classifiers":[
        {
            "category":"Building & Trades",
            "subcategory":"Construction",
            "type":"Services"
        }
    ],
    "sg:phone":"+1 253 261 7515",
    "sg:postcode":"98092",
    "sg:province":"WA",
    "sg:tags":[
        "concrete",
        "contractor"
    ],
    "wof:name":"Billet Concrete Inc",
    "wof:placetype":"venue"
},
  "geometry": {"coordinates":[-122.191749,47.310649],"type":"Point"}
}