{
  "type": "Feature",
  "properties": {
    "addr:full":"349 S Shore Rd Quinault WA 98575",
    "addr:housenumber":"349",
    "addr:postcode":"98575",
    "addr:street":"S Shore Rd",
    "iso:country":"US",
    "sg:address":"349 S Shore Rd",
    "sg:city":"Quinault",
    "sg:classifiers":[
        {
            "category":"Travel",
            "subcategory":"Hotels & Motels",
            "type":"Entertainment"
        }
    ],
    "sg:phone":"+1 360 288 2900",
    "sg:postcode":"98575",
    "sg:province":"WA",
    "wof:name":"Lake Quinault Lodge",
    "wof:placetype":"venue"
},
  "geometry": {"coordinates":[-123.846963,47.467281],"type":"Point"}
}