{
  "type": "Feature",
  "properties": {
    "addr:full":"306 N Rivard Rd Moxee WA 98936",
    "addr:housenumber":"306",
    "addr:postcode":"98936",
    "addr:street":"N Rivard Rd",
    "iso:country":"US",
    "sg:address":"306 N Rivard Rd",
    "sg:city":"Moxee",
    "sg:classifiers":[
        {
            "category":"Real Estate",
            "subcategory":"Real Estate Operator",
            "type":"Services"
        }
    ],
    "sg:phone":"+1 509 452 9246",
    "sg:postcode":"98936",
    "sg:province":"WA",
    "sg:tags":[
        "apartment"
    ],
    "wof:name":"Rivard Apartments",
    "wof:placetype":"venue"
},
  "geometry": {"coordinates":[-120.385536,46.55803],"type":"Point"}
}