{
  "type": "Feature",
  "properties": {
    "addr:full":"7515 13th Ave SE Lacey WA 98503",
    "addr:housenumber":"7515",
    "addr:postcode":"98503",
    "addr:street":"13Th Ave Se",
    "iso:country":"US",
    "sg:address":"7515 13th Ave SE",
    "sg:city":"Lacey",
    "sg:classifiers":[
        {
            "category":"Building & Trades",
            "subcategory":"Construction",
            "type":"Services"
        }
    ],
    "sg:phone":"+1 360 491 0588",
    "sg:postcode":"98503",
    "sg:province":"WA",
    "wof:name":"Dale L Brigham",
    "wof:placetype":"venue"
},
  "geometry": {"coordinates":[-122.78032899999999,47.036216],"type":"Point"}
}