{
  "type": "Feature",
  "properties": {
    "addr:full":"2560 Donald Wapato Rd Wapato WA 98951",
    "addr:housenumber":"2560",
    "addr:postcode":"98951",
    "addr:street":"Donald Wapato Rd",
    "iso:country":"US",
    "sg:address":"2560 Donald Wapato Rd",
    "sg:city":"Wapato",
    "sg:classifiers":[
        {
            "category":"Food & Beverages",
            "subcategory":"Fruits & Vegetables",
            "type":"Retail Goods"
        }
    ],
    "sg:phone":"+1 509 877 3115",
    "sg:postcode":"98951",
    "sg:province":"WA",
    "sg:tags":[
        "market"
    ],
    "wof:name":"Donald Fruit & Mercantile",
    "wof:placetype":"venue"
},
  "geometry": {"coordinates":[-120.396298,46.474881],"type":"Point"}
}