{
  "type": "Feature",
  "properties": {
    "addr:full":"802 SE Everett Mall Way Everett WA 98208",
    "addr:housenumber":"802",
    "addr:postcode":"98208",
    "addr:street":"Se Everett Mall Way",
    "iso:country":"US",
    "sg:address":"802 SE Everett Mall Way",
    "sg:city":"Everett",
    "sg:classifiers":[
        {
            "category":"Home & Garden",
            "subcategory":"Furniture",
            "type":"Retail Goods"
        }
    ],
    "sg:phone":"+1 425 355 5900",
    "sg:postcode":"98208",
    "sg:province":"WA",
    "sg:tags":[
        "store"
    ],
    "wof:name":"International Furniture",
    "wof:placetype":"venue"
},
  "geometry": {"coordinates":[-122.221925,47.909968],"type":"Point"}
}