{
  "type": "Feature",
  "properties": {
    "addr:full":"1014 Franklin St Vancouver WA 98660",
    "addr:housenumber":"1014",
    "addr:postcode":"98660",
    "addr:street":"Franklin St",
    "iso:country":"US",
    "sg:address":"1014 Franklin St",
    "sg:city":"Vancouver",
    "sg:classifiers":[
        {
            "category":"Professional",
            "subcategory":"Lawyer & Legal Services",
            "type":"Services"
        }
    ],
    "sg:phone":"+1 360 750 5607",
    "sg:postcode":"98660",
    "sg:province":"WA",
    "sg:tags":[
        "personal",
        "injury"
    ],
    "wof:name":"Lavallee Therese Atty",
    "wof:placetype":"venue"
},
  "geometry": {"coordinates":[-122.677002,45.629101],"type":"Point"}
}