{
  "type": "Feature",
  "properties": {
    "addr:full":"12209 NE Fourth Plain Rd Ste A Vancouver WA 98682",
    "addr:housenumber":"12209",
    "addr:postcode":"98682",
    "addr:street":"Ne Fourth Plain Rd Ste A",
    "iso:country":"US",
    "sg:address":"12209 NE Fourth Plain Rd Ste A",
    "sg:city":"Vancouver",
    "sg:classifiers":[
        {
            "category":"Retail",
            "subcategory":"Auto Repair",
            "type":"Services"
        }
    ],
    "sg:phone":"+1 360 253 7111",
    "sg:postcode":"98682",
    "sg:province":"WA",
    "wof:name":"Independent Auto Inc",
    "wof:placetype":"venue"
},
  "geometry": {"coordinates":[-122.546997,45.6684],"type":"Point"}
}