{
  "type": "Feature",
  "properties": {
    "addr:full":"13102 NE 20th St Bellevue WA 98005",
    "addr:housenumber":"13102",
    "addr:postcode":"98005",
    "addr:street":"Ne 20Th St",
    "iso:country":"US",
    "sg:address":"13102 NE 20th St",
    "sg:city":"Bellevue",
    "sg:classifiers":[
        {
            "category":"Shopping",
            "type":"Retail Goods"
        }
    ],
    "sg:phone":"+1 425 869 2463",
    "sg:postcode":"98005",
    "sg:province":"WA",
    "sg:website":"ambientetile.com",
    "wof:name":"Ambiente European Tile Design",
    "wof:placetype":"venue"
},
  "geometry": {"coordinates":[-122.164993,47.628071],"type":"Point"}
}