{
  "type": "Feature",
  "properties": {
    "addr:full":"12 Bailey Ln Lyle WA 98635",
    "addr:housenumber":"12",
    "addr:postcode":"98635",
    "addr:street":"Bailey Ln",
    "iso:country":"US",
    "sg:address":"12 Bailey Ln",
    "sg:city":"Lyle",
    "sg:classifiers":[
        {
            "category":"Freight",
            "type":"Transportation"
        }
    ],
    "sg:phone":"+1 509 365 2460",
    "sg:postcode":"98635",
    "sg:province":"WA",
    "sg:tags":[
        "logging"
    ],
    "wof:name":"Tanner Ranch",
    "wof:placetype":"venue"
},
  "geometry": {"coordinates":[-121.306073,45.730351],"type":"Point"}
}