{
  "type": "Feature",
  "properties": {
    "addr:full":"4002 Foxhall Dr NE Olympia WA 98516",
    "addr:housenumber":"4002",
    "addr:postcode":"98516",
    "addr:street":"Foxhall Dr Ne",
    "iso:country":"US",
    "sg:address":"4002 Foxhall Dr NE",
    "sg:city":"Olympia",
    "sg:classifiers":[
        {
            "category":"Retail",
            "subcategory":"Repair Shop",
            "type":"Services"
        }
    ],
    "sg:phone":"+1 360 455 9405",
    "sg:postcode":"98516",
    "sg:province":"WA",
    "wof:name":"Coteys Upholstery",
    "wof:placetype":"venue"
},
  "geometry": {"coordinates":[-122.815793,47.090662],"type":"Point"}
}