{
  "type": "Feature",
  "properties": {
    "addr:full":"202 3rd Ave S Edmonds WA 98020",
    "addr:housenumber":"202",
    "addr:postcode":"98020",
    "addr:street":"3Rd Ave S",
    "iso:country":"US",
    "sg:address":"202 3rd Ave S",
    "sg:city":"Edmonds",
    "sg:classifiers":[
        {
            "category":"Travel",
            "subcategory":"Hotels & Motels",
            "type":"Entertainment"
        }
    ],
    "sg:phone":"+1 425 775 1600",
    "sg:postcode":"98020",
    "sg:province":"WA",
    "sg:tags":[
        "operation"
    ],
    "wof:name":"Inn At Third & Dayton",
    "wof:placetype":"venue"
},
  "geometry": {"coordinates":[-122.380377,47.80848],"type":"Point"}
}