{
  "type": "Feature",
  "properties": {
    "addr:full":"13100 48th Ave S Tukwila WA 98168",
    "addr:housenumber":"13100",
    "addr:postcode":"98168",
    "addr:street":"48Th Ave S",
    "iso:country":"US",
    "sg:address":"13100 48th Ave S",
    "sg:city":"Tukwila",
    "sg:classifiers":[
        {
            "category":"Building & Trades",
            "subcategory":"Locksmith",
            "type":"Services"
        }
    ],
    "sg:phone":"+1 253 336 5037",
    "sg:postcode":"98168",
    "sg:province":"WA",
    "sg:tags":[
        "key"
    ],
    "wof:name":"Locksmith 24 Hour",
    "wof:placetype":"venue"
},
  "geometry": {"coordinates":[-122.27327200000001,47.482653],"type":"Point"}
}