{
  "type": "Feature",
  "properties": {
    "addr:full":"1002 21st St SE Puyallup WA 98372",
    "addr:housenumber":"1002",
    "addr:postcode":"98372",
    "addr:street":"21St St Se",
    "iso:country":"US",
    "sg:address":"1002 21st St SE",
    "sg:city":"Puyallup",
    "sg:classifiers":[
        {
            "category":"Banks & Credit Unions",
            "subcategory":"Investment Brokerage",
            "type":"Services"
        }
    ],
    "sg:phone":"+1 253 445 4415",
    "sg:postcode":"98372",
    "sg:province":"WA",
    "sg:tags":[
        "tape",
        "video",
        "sale",
        "dvds-rental"
    ],
    "wof:name":"Technical Balance Inc",
    "wof:placetype":"venue"
},
  "geometry": {"coordinates":[-122.26692199999999,47.182513],"type":"Point"}
}