{
  "type": "Feature",
  "properties": {
    "addr:full":"1720 S Gold St Centralia WA 98531",
    "addr:housenumber":"1720",
    "addr:postcode":"98531",
    "addr:street":"S Gold St",
    "iso:country":"US",
    "sg:address":"1720 S Gold St",
    "sg:city":"Centralia",
    "sg:classifiers":[
        {
            "category":"Recreation",
            "subcategory":"Dog Park",
            "type":"Entertainment"
        },
        {
            "category":"Shopping",
            "subcategory":"Pets & Pet Supplies",
            "type":"Retail Goods"
        },
        {
            "category":"Retail",
            "subcategory":"Animal Services",
            "type":"Services"
        },
        {
            "category":"Retail",
            "subcategory":"Pet Boarding",
            "type":"Services"
        }
    ],
    "sg:phone":"+1 360 807 5293",
    "sg:postcode":"98531",
    "sg:province":"WA",
    "sg:tags":[
        "training",
        "day",
        "grooming",
        "kennel",
        "store",
        "care"
    ],
    "wof:name":"Picky Puppy",
    "wof:placetype":"venue"
},
  "geometry": {"coordinates":[-122.957269,46.695035],"type":"Point"}
}