{
  "type": "Feature",
  "properties": {
    "addr:full":"4120 Ingleside Loop SE Lacey WA 98503",
    "addr:housenumber":"4120",
    "addr:postcode":"98503",
    "addr:street":"Ingleside Loop Se",
    "iso:country":"US",
    "sg:address":"4120 Ingleside Loop SE",
    "sg:city":"Lacey",
    "sg:classifiers":[
        {
            "category":"Personal",
            "subcategory":"Beauty Salon",
            "type":"Services"
        }
    ],
    "sg:phone":"+1 360 280 2298",
    "sg:postcode":"98503",
    "sg:province":"WA",
    "wof:name":"Jeannie's Hair Salon",
    "wof:placetype":"venue"
},
  "geometry": {"coordinates":[-122.83134,47.010135],"type":"Point"}
}