{
  "type": "Feature",
  "properties": {
    "addr:full":"2711 Sunset Ln NE Renton WA 98056",
    "addr:housenumber":"2711",
    "addr:postcode":"98056",
    "addr:street":"Sunset Ln Ne",
    "iso:country":"US",
    "sg:address":"2711 Sunset Ln NE",
    "sg:city":"Renton",
    "sg:classifiers":[
        {
            "category":"Freight",
            "type":"Transportation"
        }
    ],
    "sg:phone":"+1 425 687 6915",
    "sg:postcode":"98056",
    "sg:province":"WA",
    "sg:tags":[
        "operator",
        "local",
        "trucking"
    ],
    "wof:name":"V&G Trucking Co",
    "wof:placetype":"venue"
},
  "geometry": {"coordinates":[-122.18129500000001,47.500028],"type":"Point"}
}