{
  "type": "Feature",
  "properties": {
    "addr:full":"8965 Watson Pl NE Bremerton WA 98311",
    "addr:housenumber":"8965",
    "addr:postcode":"98311",
    "addr:street":"Watson Pl Ne",
    "iso:country":"US",
    "sg:address":"8965 Watson Pl NE",
    "sg:city":"Bremerton",
    "sg:classifiers":[
        {
            "category":"Professional",
            "subcategory":"Computer Services",
            "type":"Services"
        }
    ],
    "sg:phone":"+1 360 692 1801",
    "sg:postcode":"98311",
    "sg:province":"WA",
    "sg:tags":[
        "programing",
        "custom"
    ],
    "wof:name":"Larry Joseph Rickwartz",
    "wof:placetype":"venue"
},
  "geometry": {"coordinates":[-122.64674100000001,47.644935],"type":"Point"}
}