{
  "type": "Feature",
  "properties": {
    "addr:full":"1809 7th Ave Seattle WA 98101",
    "addr:housenumber":"1809",
    "addr:postcode":"98101",
    "addr:street":"7Th Ave",
    "iso:country":"US",
    "sg:address":"1809 7th Ave",
    "sg:city":"Seattle",
    "sg:classifiers":[
        {
            "category":"Professional",
            "subcategory":"Lawyer & Legal Services",
            "type":"Services"
        }
    ],
    "sg:phone":"+1 206 682 1116",
    "sg:postcode":"98101",
    "sg:province":"WA",
    "wof:name":"Finegold Laurence B",
    "wof:placetype":"venue"
},
  "geometry": {"coordinates":[-122.334999,47.613602],"type":"Point"}
}