{
  "type": "Feature",
  "properties": {
    "addr:full":"855 NW 6th Ave Camas WA 98607",
    "addr:housenumber":"855",
    "addr:postcode":"98607",
    "addr:street":"Nw 6Th Ave",
    "iso:country":"US",
    "sg:address":"855 NW 6th Ave",
    "sg:city":"Camas",
    "sg:classifiers":[
        {
            "category":"Personal",
            "subcategory":"Massage",
            "type":"Services"
        },
        {
            "category":"Health Services",
            "subcategory":"Health Practitioner",
            "type":"Services"
        },
        {
            "category":"Health Services",
            "subcategory":"Chiropractor",
            "type":"Services"
        }
    ],
    "sg:phone":"+1 360 834 7300",
    "sg:postcode":"98607",
    "sg:province":"WA",
    "sg:tags":[
        "nutritionist",
        "therapist",
        "chiropractic"
    ],
    "sg:website":"www.columbiachiroandmassage.com",
    "wof:name":"Columbia Chiropractic & Massage",
    "wof:placetype":"venue"
},
  "geometry": {"coordinates":[-122.418678,45.584376],"type":"Point"}
}