{
  "type": "Feature",
  "properties": {
    "addr:full":"7016 S 196th St Kent WA 98032",
    "addr:housenumber":"7016",
    "addr:postcode":"98032",
    "addr:street":"S 196Th St",
    "iso:country":"US",
    "sg:address":"7016 S 196th St",
    "sg:city":"Kent",
    "sg:classifiers":[
        {
            "category":"Manufacturing",
            "subcategory":"Tools & Machinery",
            "type":"Manufacturing & Wholesale Goods"
        },
        {
            "category":"Retail",
            "subcategory":"Repair Shop",
            "type":"Services"
        },
        {
            "category":"Retail",
            "subcategory":"Auto Repair",
            "type":"Services"
        }
    ],
    "sg:phone":"+1 253 395 8852",
    "sg:postcode":"98032",
    "sg:province":"WA",
    "sg:tags":[
        "machine",
        "automobile",
        "machinery-rebuild"
    ],
    "wof:name":"Industrial Repair Service",
    "wof:placetype":"venue"
},
  "geometry": {"coordinates":[-122.246326,47.426682],"type":"Point"}
}