{
  "type": "Feature",
  "properties": {
    "addr:full":"18601 NE 133rd St Woodinville WA 98072",
    "addr:housenumber":"18601",
    "addr:postcode":"98072",
    "addr:street":"Ne 133Rd St",
    "iso:country":"US",
    "sg:address":"18601 NE 133rd St",
    "sg:city":"Woodinville",
    "sg:classifiers":[
        {
            "category":"Professional",
            "subcategory":"Art Services",
            "type":"Services"
        }
    ],
    "sg:phone":"+1 425 869 8820",
    "sg:postcode":"98072",
    "sg:province":"WA",
    "sg:tags":[
        "commercial",
        "design"
    ],
    "wof:name":"Holum Design",
    "wof:placetype":"venue"
},
  "geometry": {"coordinates":[-122.09012800000001,47.718942],"type":"Point"}
}