{
  "type": "Feature",
  "properties": {
    "addr:full":"24001 E Mission Ave Liberty Lake WA 99019",
    "addr:housenumber":"24001",
    "addr:postcode":"99019",
    "addr:street":"E Mission Ave",
    "iso:country":"US",
    "sg:address":"24001 E Mission Ave",
    "sg:city":"Liberty Lake",
    "sg:classifiers":[
        {
            "category":"Restaurant",
            "type":"Food & Drink"
        }
    ],
    "sg:phone":"+1 509 921 4310",
    "sg:postcode":"99019",
    "sg:province":"WA",
    "sg:tags":[
        "eating"
    ],
    "wof:name":"Sodexho Inc",
    "wof:placetype":"venue"
},
  "geometry": {"coordinates":[-117.078903,47.67131],"type":"Point"}
}