{
  "type": "Feature",
  "properties": {
    "addr:full":"9449 151st Ave NE Redmond WA 98052",
    "addr:housenumber":"9449",
    "addr:postcode":"98052",
    "addr:street":"151St Ave Ne",
    "iso:country":"US",
    "sg:address":"9449 151st Ave NE",
    "sg:city":"Redmond",
    "sg:classifiers":[
        {
            "category":"Home & Garden",
            "subcategory":"Home Furnishings",
            "type":"Retail Goods"
        }
    ],
    "sg:phone":"+1 425 869 0543",
    "sg:postcode":"98052",
    "sg:province":"WA",
    "sg:tags":[
        "decor"
    ],
    "sg:website":"www.starryeyedinteriors.com/",
    "wof:name":"Starry Eyed Interiors",
    "wof:placetype":"venue"
},
  "geometry": {"coordinates":[-122.139977,47.685565],"type":"Point"}
}