{
  "type": "Feature",
  "properties": {
    "addr:full":"605 Thomas St Seattle WA 98109",
    "addr:housenumber":"605",
    "addr:postcode":"98109",
    "addr:street":"Thomas St",
    "iso:country":"US",
    "sg:address":"605 Thomas St",
    "sg:city":"Seattle",
    "sg:classifiers":[
        {
            "category":"Professional",
            "subcategory":"Lawyer & Legal Services",
            "type":"Services"
        }
    ],
    "sg:phone":"+1 206 374 0205",
    "sg:postcode":"98109",
    "sg:province":"WA",
    "wof:name":"Sullivan & Golden",
    "wof:placetype":"venue"
},
  "geometry": {"coordinates":[-122.345001,47.620998],"type":"Point"}
}