{
  "type": "Feature",
  "properties": {
    "addr:full":"415 W Wishkah St Aberdeen WA 98520",
    "addr:housenumber":"415",
    "addr:postcode":"98520",
    "addr:street":"W Wishkah St",
    "iso:country":"US",
    "sg:address":"415 W Wishkah St",
    "sg:city":"Aberdeen",
    "sg:classifiers":[
        {
            "category":"Government",
            "subcategory":"Office",
            "type":"Public Place"
        }
    ],
    "sg:phone":"+1 360 533 8200",
    "sg:postcode":"98520",
    "sg:province":"WA",
    "sg:tags":[
        "industry",
        "labor"
    ],
    "wof:name":"Labor and Industries Wash Dept",
    "wof:placetype":"venue"
},
  "geometry": {"coordinates":[-123.821544,46.972282],"type":"Point"}
}