{
  "type": "Feature",
  "properties": {
    "iso:country":"US",
    "sg:address":"923 Kincaid Ave",
    "sg:city":"Sumner",
    "sg:classifiers":[
        {
            "category":"Shopping",
            "subcategory":"Gifts & Souvenirs",
            "type":"Retail Goods"
        }
    ],
    "sg:phone":"+1 253 826 0533",
    "sg:postcode":"98390",
    "sg:province":"WA",
    "wof:name":"Collectable Cat",
    "wof:placetype":"venue"
},
  "geometry": {"coordinates":[-122.24173,47.20305],"type":"Point"}
}