{
  "type": "Feature",
  "properties": {
    "addr:full":"4305 N Best Rd Spokane WA 99216",
    "addr:housenumber":"4305",
    "addr:postcode":"99216",
    "addr:street":"N Best Rd",
    "iso:country":"US",
    "sg:address":"4305 N Best Rd",
    "sg:city":"Spokane",
    "sg:classifiers":[
        {
            "category":"Shopping",
            "subcategory":"Florist",
            "type":"Retail Goods"
        }
    ],
    "sg:phone":"+1 509 928 8540",
    "sg:postcode":"99216",
    "sg:province":"WA",
    "wof:name":"Armours Flowers",
    "wof:placetype":"venue"
},
  "geometry": {"coordinates":[-117.213185,47.697148],"type":"Point"}
}