{
  "type": "Feature",
  "properties": {
    "addr:full":"19822 50th Ave W Lynnwood WA 98036",
    "addr:housenumber":"19822",
    "addr:postcode":"98036",
    "addr:street":"50Th Ave W",
    "iso:country":"US",
    "sg:address":"19822 50th Ave W",
    "sg:city":"Lynnwood",
    "sg:classifiers":[
        {
            "category":"Professional",
            "type":"Services"
        }
    ],
    "sg:phone":"+1 425 712 9713",
    "sg:postcode":"98036",
    "sg:province":"WA",
    "wof:name":"Fun Tshirts Etc",
    "wof:placetype":"venue"
},
  "geometry": {"coordinates":[-122.300563,47.817507],"type":"Point"}
}