{
  "type": "Feature",
  "properties": {
    "addr:full":"2200 F St Bellingham WA 98225",
    "addr:housenumber":"2200",
    "addr:postcode":"98225",
    "addr:street":"F St",
    "iso:country":"US",
    "sg:address":"2200 F St",
    "sg:city":"Bellingham",
    "sg:classifiers":[
        {
            "category":"Organizations",
            "subcategory":"Religious Organization",
            "type":"Services"
        }
    ],
    "sg:phone":"+1 360 734 6707",
    "sg:postcode":"98225",
    "sg:province":"WA",
    "wof:name":"Bccc",
    "wof:placetype":"venue"
},
  "geometry": {"coordinates":[-122.47940199999999,48.760672],"type":"Point"}
}