{
  "type": "Feature",
  "properties": {
    "addr:full":"945 Hildebrand Ln NE Bainbridge Isle WA 98110",
    "addr:housenumber":"945",
    "addr:postcode":"98110",
    "addr:street":"Hildebrand Ln Ne;Isle",
    "iso:country":"US",
    "sg:address":"945 Hildebrand Ln NE",
    "sg:city":"Bainbridge Isle",
    "sg:classifiers":[
        {
            "category":"Education",
            "subcategory":"Dance Studio",
            "type":"Public Place"
        }
    ],
    "sg:phone":"+1 206 842 1205",
    "sg:postcode":"98110",
    "sg:province":"WA",
    "sg:tags":[
        "instruction",
        "dancing"
    ],
    "wof:name":"Bainbridge Ballet",
    "wof:placetype":"venue"
},
  "geometry": {"coordinates":[-122.517391,47.632694],"type":"Point"}
}