{
  "type": "Feature",
  "properties": {
    "addr:full":"1057 Greenwood Blvd SW Issaquah WA 98027",
    "addr:housenumber":"1057",
    "addr:postcode":"98027",
    "addr:street":"Greenwood Blvd Sw",
    "iso:country":"US",
    "sg:address":"1057 Greenwood Blvd SW",
    "sg:city":"Issaquah",
    "sg:classifiers":[
        {
            "category":"Professional",
            "subcategory":"Computer Services",
            "type":"Services"
        }
    ],
    "sg:phone":"+1 425 269 7488",
    "sg:postcode":"98027",
    "sg:province":"WA",
    "sg:tags":[
        "prepackaged",
        "software"
    ],
    "wof:name":"Myles Connors Software",
    "wof:placetype":"venue"
},
  "geometry": {"coordinates":[-122.04727,47.520652],"type":"Point"}
}