{
  "type": "Feature",
  "properties": {
    "addr:full":"1200 Fort Vancouver Way Vancouver WA 98663",
    "addr:housenumber":"1200",
    "addr:postcode":"98663",
    "addr:street":"Fort Vancouver Way",
    "iso:country":"US",
    "sg:address":"1200 Fort Vancouver Way",
    "sg:city":"Vancouver",
    "sg:classifiers":[
        {
            "category":"Building & Trades",
            "subcategory":"Locksmith",
            "type":"Services"
        }
    ],
    "sg:phone":"+1 360 713 5776",
    "sg:postcode":"98663",
    "sg:province":"WA",
    "sg:tags":[
        "key"
    ],
    "wof:name":"A A A Cheap Locksmith",
    "wof:placetype":"venue"
},
  "geometry": {"coordinates":[-122.662541,45.630105],"type":"Point"}
}