{
  "type": "Feature",
  "properties": {
    "addr:full":"6538 US Hwy 101 Amanda Park WA 98526",
    "addr:housenumber":"6538",
    "addr:postcode":"98526",
    "addr:street":"Us Hwy 101 Amanda Park",
    "iso:country":"US",
    "sg:address":"6538 US Hwy 101",
    "sg:city":"Amanda Park",
    "sg:classifiers":[
        {
            "category":"Home & Garden",
            "subcategory":"Building Materials",
            "type":"Retail Goods"
        }
    ],
    "sg:phone":"+1 360 288 2310",
    "sg:postcode":"98526",
    "sg:province":"WA",
    "sg:tags":[
        "roofing"
    ],
    "wof:name":"A & O Shingles",
    "wof:placetype":"venue"
},
  "geometry": {"coordinates":[-123.933031,47.479991],"type":"Point"}
}