{
  "type": "Feature",
  "properties": {
    "addr:full":"122 11th Ave E Seattle WA 98102",
    "addr:housenumber":"122",
    "addr:postcode":"98102",
    "addr:street":"11Th Ave E",
    "iso:country":"US",
    "sg:address":"122 11th Ave E",
    "sg:city":"Seattle",
    "sg:classifiers":[
        {
            "category":"Manufacturing",
            "subcategory":"Jewelry",
            "type":"Manufacturing & Wholesale Goods"
        }
    ],
    "sg:phone":"+1 206 324 2748",
    "sg:postcode":"98102",
    "sg:province":"WA",
    "sg:tags":[
        "stone",
        "manufacturer",
        "jewelers-wholesale",
        "jewels-imitation"
    ],
    "wof:name":"Attachments",
    "wof:placetype":"venue"
},
  "geometry": {"coordinates":[-122.31820999999999,47.619005],"type":"Point"}
}