{
  "type": "Feature",
  "properties": {
    "addr:full":"1960 Black Lake Blvd SW Olympia WA 98512",
    "addr:housenumber":"1960",
    "addr:postcode":"98512",
    "addr:street":"Black Lake Blvd Sw",
    "iso:country":"US",
    "sg:address":"1960 Black Lake Blvd SW",
    "sg:city":"Olympia",
    "sg:classifiers":[
        {
            "category":"Personal",
            "subcategory":"Beauty Salon",
            "type":"Services"
        },
        {
            "category":"Personal",
            "subcategory":"Skin Care",
            "type":"Services"
        }
    ],
    "sg:phone":"+1 360 350 4999",
    "sg:postcode":"98512",
    "sg:province":"WA",
    "sg:tags":[
        "hair",
        "stylist"
    ],
    "sg:website":"http://www.robertallansalon.com",
    "wof:name":"Robert Allan Salon",
    "wof:placetype":"venue"
},
  "geometry": {"coordinates":[-122.94304099999999,47.03058],"type":"Point"}
}