{
  "type": "Feature",
  "properties": {
    "addr:full":"165 S Post St Spokane WA 99201",
    "addr:housenumber":"165",
    "addr:postcode":"99201",
    "addr:street":"S Post St",
    "iso:country":"US",
    "sg:address":"165 S Post St",
    "sg:city":"Spokane",
    "sg:classifiers":[
        {
            "category":"Professional",
            "subcategory":"Computer Services",
            "type":"Services"
        }
    ],
    "sg:phone":"+1 509 869 0227",
    "sg:postcode":"99201",
    "sg:province":"WA",
    "sg:tags":[
        "web",
        "design",
        "site"
    ],
    "wof:name":"Aegismedia",
    "wof:placetype":"venue"
},
  "geometry": {"coordinates":[-117.42339800000001,47.655192],"type":"Point"}
}