{
  "type": "Feature",
  "properties": {
    "addr:full":"17527 160th St SE Monroe WA 98272",
    "addr:housenumber":"17527",
    "addr:postcode":"98272",
    "addr:street":"160Th St Se",
    "iso:country":"US",
    "sg:address":"17527 160th St SE",
    "sg:city":"Monroe",
    "sg:classifiers":[
        {
            "category":"Building & Trades",
            "subcategory":"Construction",
            "type":"Services"
        }
    ],
    "sg:phone":"+1 360 794 6061",
    "sg:postcode":"98272",
    "sg:province":"WA",
    "sg:tags":[
        "steel",
        "general",
        "contractor"
    ],
    "wof:name":"S W Gohl Construction Inc",
    "wof:placetype":"venue"
},
  "geometry": {"coordinates":[-121.992181,47.852284],"type":"Point"}
}