{
  "type": "Feature",
  "properties": {
    "addr:full":"268 E Main St Auburn WA 98002",
    "addr:housenumber":"268",
    "addr:postcode":"98002",
    "addr:street":"E Main St",
    "iso:country":"US",
    "sg:address":"268 E Main St",
    "sg:city":"Auburn",
    "sg:classifiers":[
        {
            "category":"Organizations",
            "subcategory":"Religious Organization",
            "type":"Services"
        }
    ],
    "sg:phone":"+1 253 833 5810",
    "sg:postcode":"98002",
    "sg:province":"WA",
    "sg:tags":[
        "church"
    ],
    "wof:name":"Christian Science Reading Room",
    "wof:placetype":"venue"
},
  "geometry": {"coordinates":[-122.226236,47.307399],"type":"Point"}
}