{
  "type": "Feature",
  "properties": {
    "addr:full":"4502 E Buckeye Ave Spokane WA 99217",
    "addr:housenumber":"4502",
    "addr:postcode":"99217",
    "addr:street":"E Buckeye Ave",
    "iso:country":"US",
    "sg:address":"4502 E Buckeye Ave",
    "sg:city":"Spokane",
    "sg:classifiers":[
        {
            "category":"Manufacturing",
            "subcategory":"Food",
            "type":"Manufacturing & Wholesale Goods"
        }
    ],
    "sg:phone":"+1 509 489 0588",
    "sg:postcode":"99217",
    "sg:province":"WA",
    "sg:tags":[
        "mfg"
    ],
    "wof:name":"Arbor Crest Winery",
    "wof:placetype":"venue"
},
  "geometry": {"coordinates":[-117.343391,47.682556],"type":"Point"}
}