{
  "type": "Feature",
  "properties": {
    "addr:full":"516 N Park St Chewelah WA 99109",
    "addr:housenumber":"516",
    "addr:postcode":"99109",
    "addr:street":"N Park St",
    "iso:country":"US",
    "sg:address":"516 N Park St",
    "sg:city":"Chewelah",
    "sg:classifiers":[
        {
            "category":"Restaurant",
            "type":"Food & Drink"
        }
    ],
    "sg:phone":"+1 509 935 3401",
    "sg:postcode":"99109",
    "sg:province":"WA",
    "wof:name":"Zips",
    "wof:placetype":"venue"
},
  "geometry": {"coordinates":[-117.715541,48.280192],"type":"Point"}
}