{
  "type": "Feature",
  "properties": {
    "addr:full":"9525 N Davies Rd Lake Stevens WA 98258",
    "addr:housenumber":"9525",
    "addr:postcode":"98258",
    "addr:street":"N Davies Rd",
    "iso:country":"US",
    "sg:address":"9525 N Davies Rd",
    "sg:city":"Lake Stevens",
    "sg:classifiers":[
        {
            "category":"Social Services",
            "subcategory":"Adult Care",
            "type":"Services"
        }
    ],
    "sg:phone":"+1 425 334 3105",
    "sg:postcode":"98258",
    "sg:province":"WA",
    "sg:tags":[
        "home"
    ],
    "wof:name":"Lakeview Adult Homes",
    "wof:placetype":"venue"
},
  "geometry": {"coordinates":[-122.1031,48.004741],"type":"Point"}
}