{
  "type": "Feature",
  "properties": {
    "addr:full":"8830 Wallingford Ave N Seattle WA 98103",
    "addr:housenumber":"8830",
    "addr:postcode":"98103",
    "addr:street":"Wallingford Ave N",
    "iso:country":"US",
    "sg:address":"8830 Wallingford Ave N",
    "sg:city":"Seattle",
    "sg:classifiers":[
        {
            "category":"Retail",
            "subcategory":"Car Wash",
            "type":"Services"
        }
    ],
    "sg:phone":"+1 206 528 0630",
    "sg:postcode":"98103",
    "sg:province":"WA",
    "sg:tags":[
        "carwash"
    ],
    "wof:name":"Wash Citizens C Powell",
    "wof:placetype":"venue"
},
  "geometry": {"coordinates":[-122.336403,47.693862],"type":"Point"}
}