{
  "type": "Feature",
  "properties": {
    "addr:full":"4052 28th Ave SW Seattle WA 98126",
    "addr:housenumber":"4052",
    "addr:postcode":"98126",
    "addr:street":"28Th Ave Sw",
    "iso:country":"US",
    "sg:address":"4052 28th Ave SW",
    "sg:city":"Seattle",
    "sg:classifiers":[
        {
            "category":"Professional",
            "subcategory":"Lawyer & Legal Services",
            "type":"Services"
        }
    ],
    "sg:phone":"+1 206 933 8378",
    "sg:postcode":"98126",
    "sg:province":"WA",
    "sg:tags":[
        "attorney"
    ],
    "wof:name":"Jack A Ginsberg",
    "wof:placetype":"venue"
},
  "geometry": {"coordinates":[-122.36803,47.566901],"type":"Point"}
}