{
  "type": "Feature",
  "properties": {
    "addr:full":"10527 Kendrick St SW Lakewood WA 98499",
    "addr:housenumber":"10527",
    "addr:postcode":"98499",
    "addr:street":"Kendrick St Sw",
    "iso:country":"US",
    "sg:address":"10527 Kendrick St SW",
    "sg:city":"Lakewood",
    "sg:classifiers":[
        {
            "category":"Organizations",
            "subcategory":"Community Association",
            "type":"Services"
        }
    ],
    "sg:phone":"+1 253 589 8989",
    "sg:postcode":"98499",
    "sg:province":"WA",
    "wof:name":"Boys Girls Clubs S Puget Sound",
    "wof:placetype":"venue"
},
  "geometry": {"coordinates":[-122.49806599999999,47.160227],"type":"Point"}
}