{
  "type": "Feature",
  "properties": {
    "addr:full":"8917 NE 15th Ave Vancouver WA 98665",
    "addr:housenumber":"8917",
    "addr:postcode":"98665",
    "addr:street":"Ne 15Th Ave",
    "iso:country":"US",
    "sg:address":"8917 NE 15th Ave",
    "sg:city":"Vancouver",
    "sg:classifiers":[
        {
            "category":"Real Estate",
            "subcategory":"Real Estate Operator",
            "type":"Services"
        }
    ],
    "sg:phone":"+1 360 573 4987",
    "sg:postcode":"98665",
    "sg:province":"WA",
    "sg:tags":[
        "building",
        "apartment"
    ],
    "wof:name":"Greenwood Acres Apartments",
    "wof:placetype":"venue"
},
  "geometry": {"coordinates":[-122.65656300000001,45.687199],"type":"Point"}
}