{
  "type": "Feature",
  "properties": {
    "addr:full":"10532 NE 68th St Kirkland WA 98033",
    "addr:housenumber":"10532",
    "addr:postcode":"98033",
    "addr:street":"Ne 68Th St",
    "iso:country":"US",
    "sg:address":"10532 NE 68th St",
    "sg:city":"Kirkland",
    "sg:classifiers":[
        {
            "category":"Building & Trades",
            "subcategory":"Construction",
            "type":"Services"
        }
    ],
    "sg:phone":"+1 425 889 9713",
    "sg:postcode":"98033",
    "sg:province":"WA",
    "sg:tags":[
        "contractor"
    ],
    "wof:name":"Hm Design Build Llc",
    "wof:placetype":"venue"
},
  "geometry": {"coordinates":[-122.19899700000001,47.666801],"type":"Point"}
}