{
  "type": "Feature",
  "properties": {
    "addr:full":"1513 13th St Anacortes WA 98221",
    "addr:housenumber":"1513",
    "addr:postcode":"98221",
    "addr:street":"13Th St",
    "iso:country":"US",
    "sg:address":"1513 13th St",
    "sg:city":"Anacortes",
    "sg:classifiers":[
        {
            "category":"Shopping",
            "subcategory":"Crafts & Fabrics",
            "type":"Retail Goods"
        }
    ],
    "sg:phone":"+1 360 299 8945",
    "sg:postcode":"98221",
    "sg:province":"WA",
    "sg:tags":[
        "sewing"
    ],
    "wof:name":"Ariadne Designs",
    "wof:placetype":"venue"
},
  "geometry": {"coordinates":[-122.621871,48.511783],"type":"Point"}
}