{
  "type": "Feature",
  "properties": {
    "addr:full":"1240 W Sims Way Port Townsend WA 98368",
    "addr:housenumber":"1240",
    "addr:postcode":"98368",
    "addr:street":"W Sims Way",
    "iso:country":"US",
    "sg:address":"1240 W Sims Way",
    "sg:city":"Port Townsend",
    "sg:classifiers":[
        {
            "category":"Freight",
            "type":"Transportation"
        }
    ],
    "sg:phone":"+1 360 379 1156",
    "sg:postcode":"98368",
    "sg:province":"WA",
    "sg:tags":[
        "courier"
    ],
    "wof:name":"Mail Plus",
    "wof:placetype":"venue"
},
  "geometry": {"coordinates":[-122.791042,48.102934],"type":"Point"}
}