{
  "type": "Feature",
  "properties": {
    "addr:full":"2406 Port Of Tacoma Rd Tacoma WA 98421",
    "addr:housenumber":"2406",
    "addr:postcode":"98421",
    "addr:street":"Port Of Tacoma Rd",
    "iso:country":"US",
    "sg:address":"2406 Port Of Tacoma Rd",
    "sg:city":"Tacoma",
    "sg:classifiers":[
        {
            "category":"Wholesale",
            "subcategory":"Petroleum",
            "type":"Manufacturing & Wholesale Goods"
        },
        {
            "category":"Building & Trades",
            "subcategory":"Construction",
            "type":"Services"
        },
        {
            "category":"Utilities",
            "subcategory":"Natural Gas",
            "type":"Services"
        }
    ],
    "sg:phone":"+1 253 475 7600",
    "sg:postcode":"98421",
    "sg:province":"WA",
    "sg:tags":[
        "propane",
        "system",
        "contractor",
        "air conditioning",
        "gasoline-wholesale"
    ],
    "wof:name":"Pacific Coast Oil",
    "wof:placetype":"venue"
},
  "geometry": {"coordinates":[-122.39059,47.258534],"type":"Point"}
}