{
  "type": "Feature",
  "properties": {
    "addr:full":"157 Yesler Way Seattle WA 98104",
    "addr:housenumber":"157",
    "addr:postcode":"98104",
    "addr:street":"Yesler Way",
    "iso:country":"US",
    "sg:address":"157 Yesler Way",
    "sg:city":"Seattle",
    "sg:classifiers":[
        {
            "category":"Professional",
            "subcategory":"Management & Consulting",
            "type":"Services"
        }
    ],
    "sg:phone":"+1 206 682 6820",
    "sg:postcode":"98104",
    "sg:province":"WA",
    "wof:name":"Market Stratagies",
    "wof:placetype":"venue"
},
  "geometry": {"coordinates":[-122.332035,47.601642],"type":"Point"}
}