{
  "type": "Feature",
  "properties": {
    "addr:full":"16808 SE McGillivray Blvd Vancouver WA 98683",
    "addr:postcode":"16808;98683",
    "addr:street":"Se Mcgillivray Blvd",
    "iso:country":"US",
    "sg:address":"16808 SE McGillivray Blvd",
    "sg:city":"Vancouver",
    "sg:classifiers":[
        {
            "category":"Social Services",
            "subcategory":"Child Care",
            "type":"Services"
        },
        {
            "category":"Education",
            "subcategory":"Preschool",
            "type":"Public Place"
        },
        {
            "category":"Education",
            "subcategory":"School",
            "type":"Public Place"
        }
    ],
    "sg:phone":"+1 360 882 3090",
    "sg:postcode":"98683",
    "sg:province":"WA",
    "sg:tags":[
        "elementary",
        "day"
    ],
    "sg:website":"www.kindercare.com",
    "wof:name":"Kindercare Learning Centers",
    "wof:placetype":"venue"
},
  "geometry": {"coordinates":[-122.49893299999999,45.606078],"type":"Point"}
}