{
  "type": "Feature",
  "properties": {
    "addr:full":"1300 Esther St Vancouver WA 98660",
    "addr:housenumber":"1300",
    "addr:postcode":"98660",
    "addr:street":"Esther St",
    "iso:country":"US",
    "sg:address":"1300 Esther St",
    "sg:city":"Vancouver",
    "sg:classifiers":[
        {
            "category":"Health Services",
            "subcategory":"Doctor",
            "type":"Services"
        }
    ],
    "sg:phone":"+1 360 693 4701",
    "sg:postcode":"98660",
    "sg:province":"WA",
    "sg:tags":[
        "dentist"
    ],
    "wof:name":"Charles R Dufort DDS",
    "wof:placetype":"venue"
},
  "geometry": {"coordinates":[-122.675932,45.631804],"type":"Point"}
}