{
  "type": "Feature",
  "properties": {
    "iso:country":"US",
    "sg:address":"2413 Eureka Ave",
    "sg:city":"Centralia",
    "sg:classifiers":[
        {
            "category":"Shopping",
            "subcategory":"Florist",
            "type":"Retail Goods"
        }
    ],
    "sg:phone":"+1 360 736 9874",
    "sg:postcode":"98531",
    "sg:province":"WA",
    "wof:name":"Swensons Flower Patch",
    "wof:placetype":"venue"
},
  "geometry": {"coordinates":[-122.947728,46.749078],"type":"Point"}
}