{
  "type": "Feature",
  "properties": {
    "addr:full":"2414 S Zillah St Kennewick WA 99337",
    "addr:housenumber":"2414",
    "addr:postcode":"99337",
    "addr:street":"S Zillah St",
    "iso:country":"US",
    "sg:address":"2414 S Zillah St",
    "sg:city":"Kennewick",
    "sg:classifiers":[
        {
            "category":"Retail",
            "subcategory":"Repair Shop",
            "type":"Services"
        }
    ],
    "sg:phone":"+1 509 586 0567",
    "sg:postcode":"99337",
    "sg:province":"WA",
    "sg:tags":[
        "welding"
    ],
    "wof:name":"Dougs Welding",
    "wof:placetype":"venue"
},
  "geometry": {"coordinates":[-119.152305,46.186115],"type":"Point"}
}