{
  "type": "Feature",
  "properties": {
    "iso:country":"US",
    "sg:address":"316 Occidental Ave S",
    "sg:city":"Seattle",
    "sg:classifiers":[
        {
            "category":"Building & Trades",
            "subcategory":"Construction",
            "type":"Services"
        }
    ],
    "sg:phone":"+1 206 621 7769",
    "sg:postcode":"98104",
    "sg:province":"WA",
    "sg:tags":[
        "maintenance",
        "contractor"
    ],
    "wof:name":"Accurate Maintenance Inc",
    "wof:placetype":"venue"
},
  "geometry": {"coordinates":[-122.332809,47.599338],"type":"Point"}
}