{
  "type": "Feature",
  "properties": {
    "addr:full":"408 SW 126th St Seattle WA 98146",
    "addr:housenumber":"408",
    "addr:postcode":"98146",
    "addr:street":"Sw 126Th St",
    "iso:country":"US",
    "sg:address":"408 SW 126th St",
    "sg:city":"Seattle",
    "sg:classifiers":[
        {
            "category":"Real Estate",
            "subcategory":"Real Estate Services",
            "type":"Services"
        },
        {
            "category":"Building & Trades",
            "subcategory":"Cleaning & Sanitation",
            "type":"Services"
        }
    ],
    "sg:phone":"+1 206 431 0940",
    "sg:postcode":"98146",
    "sg:province":"WA",
    "sg:tags":[
        "window",
        "maintenance",
        "cleaners-interior"
    ],
    "wof:name":"A Better View Window Cleaning",
    "wof:placetype":"venue"
},
  "geometry": {"coordinates":[-122.339274,47.490299],"type":"Point"}
}