{
  "type": "Feature",
  "properties": {
    "addr:full":"8600 Lake City Way NE Seattle WA 98115",
    "addr:housenumber":"8600",
    "addr:postcode":"98115",
    "addr:street":"Lake City Way Ne",
    "iso:country":"US",
    "sg:address":"8600 Lake City Way NE",
    "sg:city":"Seattle",
    "sg:classifiers":[
        {
            "category":"Professional",
            "subcategory":"Employment Agencies",
            "type":"Services"
        }
    ],
    "sg:phone":"+1 206 527 0250",
    "sg:postcode":"98115",
    "sg:province":"WA",
    "wof:name":"Talents West",
    "wof:placetype":"venue"
},
  "geometry": {"coordinates":[-122.306999,47.6912],"type":"Point"}
}