{
  "type": "Feature",
  "properties": {
    "addr:full":"159 W Cedar Loop Colville WA 99114",
    "addr:housenumber":"159",
    "addr:postcode":"99114",
    "addr:street":"W Cedar Loop",
    "iso:country":"US",
    "sg:address":"159 W Cedar Loop",
    "sg:city":"Colville",
    "sg:classifiers":[
        {
            "category":"Building & Trades",
            "subcategory":"Equipment Rental",
            "type":"Services"
        }
    ],
    "sg:phone":"+1 509 684 2703",
    "sg:postcode":"99114",
    "sg:province":"WA",
    "wof:name":"K & L Rentals LLC",
    "wof:placetype":"venue"
},
  "geometry": {"coordinates":[-117.898298,48.528029],"type":"Point"}
}