{
  "type": "Feature",
  "properties": {
    "addr:full":"3916 15th Place W Seattle WA 98119",
    "addr:housenumber":"3916",
    "addr:postcode":"98119",
    "addr:street":"15Th Place W",
    "iso:country":"US",
    "sg:address":"3916 15th Place W",
    "sg:city":"Seattle",
    "sg:classifiers":[
        {
            "category":"Professional",
            "subcategory":"Art Services",
            "type":"Services"
        }
    ],
    "sg:phone":"+1 206 547 5487",
    "sg:postcode":"98119",
    "sg:province":"WA",
    "sg:tags":[
        "graphic",
        "design"
    ],
    "wof:name":"Reid Signs",
    "wof:placetype":"venue"
},
  "geometry": {"coordinates":[-122.37704100000001,47.655469],"type":"Point"}
}