{
  "type": "Feature",
  "properties": {
    "addr:full":"7031 A St Tacoma WA 98408",
    "addr:housenumber":"7031",
    "addr:postcode":"98408",
    "addr:street":"A St",
    "iso:country":"US",
    "sg:address":"7031 A St",
    "sg:city":"Tacoma",
    "sg:classifiers":[
        {
            "category":"Recreation",
            "subcategory":"Arcade",
            "type":"Entertainment"
        }
    ],
    "sg:phone":"+1 253 474 8156",
    "sg:postcode":"98408",
    "sg:province":"WA",
    "sg:tags":[
        "device",
        "operator",
        "amusement"
    ],
    "wof:name":"Disc Trek Enterprise",
    "wof:placetype":"venue"
},
  "geometry": {"coordinates":[-122.431304,47.192188],"type":"Point"}
}