{
  "type": "Feature",
  "properties": {
    "addr:full":"411 Cunningham Rd Kelso WA 98626",
    "addr:housenumber":"411",
    "addr:postcode":"98626",
    "addr:street":"Cunningham Rd",
    "iso:country":"US",
    "sg:address":"411 Cunningham Rd",
    "sg:city":"Kelso",
    "sg:classifiers":[
        {
            "category":"Professional",
            "subcategory":"Advertising",
            "type":"Services"
        }
    ],
    "sg:phone":"+1 360 423 0993",
    "sg:postcode":"98626",
    "sg:province":"WA",
    "sg:tags":[
        "counselor",
        "agency"
    ],
    "wof:name":"Advantage Media Inc",
    "wof:placetype":"venue"
},
  "geometry": {"coordinates":[-122.82355699999999,46.095715],"type":"Point"}
}