{
  "type": "Feature",
  "properties": {
    "addr:full":"1812 S J St Tacoma WA 98405",
    "addr:housenumber":"1812",
    "addr:postcode":"98405",
    "addr:street":"S J St",
    "iso:country":"US",
    "sg:address":"1812 S J St",
    "sg:city":"Tacoma",
    "sg:classifiers":[
        {
            "category":"Personal",
            "type":"Services"
        }
    ],
    "sg:phone":"+1 253 566 1616",
    "sg:postcode":"98405",
    "sg:province":"WA",
    "sg:tags":[
        "consultant",
        "program",
        "health",
        "fitness"
    ],
    "wof:name":"Health Enhancement Corp",
    "wof:placetype":"venue"
},
  "geometry": {"coordinates":[-122.448509,47.24403],"type":"Point"}
}