{
  "type": "Feature",
  "properties": {
    "addr:full":"11816 Pacific Ave S Tacoma WA 98444",
    "addr:housenumber":"11816",
    "addr:postcode":"98444",
    "addr:street":"Pacific Ave S",
    "iso:country":"US",
    "sg:address":"11816 Pacific Ave S",
    "sg:city":"Tacoma",
    "sg:classifiers":[
        {
            "category":"Food & Beverages",
            "subcategory":"Meat & Fish",
            "type":"Retail Goods"
        }
    ],
    "sg:phone":"+1 253 531 7798",
    "sg:postcode":"98444",
    "sg:province":"WA",
    "wof:name":"Parkland Quality Meats",
    "wof:placetype":"venue"
},
  "geometry": {"coordinates":[-122.434454,47.149082],"type":"Point"}
}