{
  "type": "Feature",
  "properties": {
    "addr:full":"311 River Rd Ste 102 Puyallup WA 98371",
    "addr:housenumber":"311",
    "addr:postcode":"98371",
    "addr:street":"River Rd Ste 102",
    "iso:country":"US",
    "sg:address":"311 River Rd Ste 102",
    "sg:city":"Puyallup",
    "sg:classifiers":[
        {
            "category":"Professional",
            "subcategory":"Accounting & Tax Preparation",
            "type":"Services"
        },
        {
            "category":"Banks & Credit Unions",
            "subcategory":"Financial Services",
            "type":"Services"
        }
    ],
    "sg:phone":"+1 253 848 0666",
    "sg:postcode":"98371",
    "sg:province":"WA",
    "sg:tags":[
        "return",
        "preparation-business",
        "taxes-consultants",
        "loan",
        "reporting",
        "representative",
        "alternative",
        "bookkeeping"
    ],
    "sg:website":"http://www.hrblock.com",
    "wof:name":"H&R Block",
    "wof:placetype":"venue"
},
  "geometry": {"coordinates":[-122.297296,47.199658],"type":"Point"}
}