{
  "type": "Feature",
  "properties": {
    "addr:full":"8334 Rainier Ave Seattle WA 98118",
    "addr:housenumber":"8334",
    "addr:postcode":"98118",
    "addr:street":"Rainier Ave",
    "iso:country":"US",
    "sg:address":"8334 Rainier Ave",
    "sg:city":"Seattle",
    "sg:classifiers":[
        {
            "category":"Building & Trades",
            "subcategory":"Cleaning & Sanitation",
            "type":"Services"
        }
    ],
    "sg:phone":"+1 206 941 0794",
    "sg:postcode":"98118",
    "sg:province":"WA",
    "sg:tags":[
        "maintenance"
    ],
    "wof:name":"Warfa Cleaning Service",
    "wof:placetype":"venue"
},
  "geometry": {"coordinates":[-122.269914,47.529267],"type":"Point"}
}