{
  "type": "Feature",
  "properties": {
    "addr:full":"304 N Pearl St Ellensburg WA 98926",
    "addr:housenumber":"304",
    "addr:postcode":"98926",
    "addr:street":"N Pearl St",
    "iso:country":"US",
    "sg:address":"304 N Pearl St",
    "sg:city":"Ellensburg",
    "sg:classifiers":[
        {
            "category":"Shopping",
            "subcategory":"Gifts & Souvenirs",
            "type":"Retail Goods"
        }
    ],
    "sg:phone":"+1 509 962 2769",
    "sg:postcode":"98926",
    "sg:province":"WA",
    "wof:name":"Gifts of Crow",
    "wof:placetype":"venue"
},
  "geometry": {"coordinates":[-120.54716999999999,46.995458],"type":"Point"}
}