{
  "type": "Feature",
  "properties": {
    "addr:full":"4337 University Way NE Seattle WA 98105",
    "addr:housenumber":"4337",
    "addr:postcode":"98105",
    "addr:street":"University Way Ne",
    "iso:country":"US",
    "sg:address":"4337 University Way NE",
    "sg:city":"Seattle",
    "sg:classifiers":[
        {
            "category":"Restaurant",
            "type":"Food & Drink"
        }
    ],
    "sg:phone":"+1 206 632 1588",
    "sg:postcode":"98105",
    "sg:province":"WA",
    "sg:tags":[
        "sushi",
        "bar",
        "japanese"
    ],
    "wof:name":"Tokyo Garden Teriyaki",
    "wof:placetype":"venue"
},
  "geometry": {"coordinates":[-122.31329100000001,47.660905],"type":"Point"}
}