{
  "type": "Feature",
  "properties": {
    "iso:country":"US",
    "sg:address":"11412 62nd Ave E",
    "sg:city":"Puyallup",
    "sg:classifiers":[
        {
            "category":"Building & Trades",
            "subcategory":"Construction",
            "type":"Services"
        }
    ],
    "sg:phone":"+1 253 841 3759",
    "sg:postcode":"98373",
    "sg:province":"WA",
    "sg:tags":[
        "concrete",
        "contractor"
    ],
    "wof:name":"Brundage-Bone Concrete Pumping",
    "wof:placetype":"venue"
},
  "geometry": {"coordinates":[-122.346828,47.153075],"type":"Point"}
}