{
  "type": "Feature",
  "properties": {
    "addr:full":"16995 Lemolo Shore Dr NE Poulsbo WA 98370",
    "addr:housenumber":"16995",
    "addr:postcode":"98370",
    "addr:street":"Lemolo Shore Dr Ne",
    "iso:country":"US",
    "sg:address":"16995 Lemolo Shore Dr NE",
    "sg:city":"Poulsbo",
    "sg:classifiers":[
        {
            "category":"Building & Trades",
            "subcategory":"Construction",
            "type":"Services"
        }
    ],
    "sg:phone":"+1 360 779 1800",
    "sg:postcode":"98370",
    "sg:province":"WA",
    "sg:tags":[
        "industrial",
        "commercial"
    ],
    "wof:name":"Cleveland Construction Inc",
    "wof:placetype":"venue"
},
  "geometry": {"coordinates":[-122.62270100000001,47.717887],"type":"Point"}
}