{
  "type": "Feature",
  "properties": {
    "addr:full":"613 W Stevens Ave Sultan WA 98294",
    "addr:housenumber":"613",
    "addr:postcode":"98294",
    "addr:street":"W Stevens Ave",
    "iso:country":"US",
    "sg:address":"613 W Stevens Ave",
    "sg:city":"Sultan",
    "sg:classifiers":[
        {
            "category":"Restaurant",
            "type":"Food & Drink"
        },
        {
            "category":"Food & Beverages",
            "subcategory":"Groceries & Convenience Stores",
            "type":"Retail Goods"
        }
    ],
    "sg:phone":"+1 360 793 2615",
    "sg:postcode":"98294",
    "sg:province":"WA",
    "sg:tags":[
        "shop",
        "sandwich",
        "pizza"
    ],
    "wof:name":"Sultan Pizza & Subs",
    "wof:placetype":"venue"
},
  "geometry": {"coordinates":[-121.82751500000001,47.858918],"type":"Point"}
}