{
  "type": "Feature",
  "properties": {
    "iso:country":"US",
    "sg:address":"1738 SE 8th Ave",
    "sg:city":"Camas",
    "sg:classifiers":[
        {
            "category":"Recreation",
            "type":"Entertainment"
        }
    ],
    "sg:phone":"+1 360 833 1208",
    "sg:postcode":"98607",
    "sg:province":"WA",
    "sg:tags":[
        "amusement"
    ],
    "wof:name":"Upper Deck Training Ctr Inc",
    "wof:placetype":"venue"
},
  "geometry": {"coordinates":[-122.389262,45.580867],"type":"Point"}
}