{
  "type": "Feature",
  "properties": {
    "addr:full":"8017 20th Ave NW Seattle WA 98117",
    "addr:housenumber":"8017",
    "addr:postcode":"98117",
    "addr:street":"20Th Ave Nw",
    "iso:country":"US",
    "sg:address":"8017 20th Ave NW",
    "sg:city":"Seattle",
    "sg:classifiers":[
        {
            "category":"Education",
            "subcategory":"School",
            "type":"Public Place"
        }
    ],
    "sg:phone":"+1 206 784 8008",
    "sg:postcode":"98117",
    "sg:province":"WA",
    "wof:name":"Musicworks",
    "wof:placetype":"venue"
},
  "geometry": {"coordinates":[-122.382147,47.687148],"type":"Point"}
}