{
  "type": "Feature",
  "properties": {
    "addr:full":"511 S Sullivan Rd Spokane Valley WA 99037",
    "addr:housenumber":"511",
    "addr:postcode":"99037",
    "addr:street":"S Sullivan Rd",
    "iso:country":"US",
    "sg:address":"511 S Sullivan Rd",
    "sg:city":"Spokane Valley",
    "sg:classifiers":[
        {
            "category":"Shopping",
            "subcategory":"Computers & Home Electronics",
            "type":"Retail Goods"
        }
    ],
    "sg:phone":"+1 509 891 8854",
    "sg:postcode":"99037",
    "sg:province":"WA",
    "sg:tags":[
        "equipment",
        "dealer"
    ],
    "wof:name":"White's Computers",
    "wof:placetype":"venue"
},
  "geometry": {"coordinates":[-117.196609,47.653369],"type":"Point"}
}