{
  "type": "Feature",
  "properties": {
    "addr:full":"1207 S Jackson St Seattle WA 98144",
    "addr:housenumber":"1207",
    "addr:postcode":"98144",
    "addr:street":"S Jackson St",
    "iso:country":"US",
    "sg:address":"1207 S Jackson St",
    "sg:city":"Seattle",
    "sg:classifiers":[
        {
            "category":"Bars & Pubs",
            "type":"Food & Drink"
        }
    ],
    "sg:phone":"+1 206 334 2709",
    "sg:postcode":"98144",
    "sg:province":"WA",
    "sg:tags":[
        "drinking"
    ],
    "wof:name":"Kissime Lounge",
    "wof:placetype":"venue"
},
  "geometry": {"coordinates":[-122.314201,47.599132],"type":"Point"}
}