{
  "type": "Feature",
  "properties": {
    "addr:full":"757 Rainier Ave Renton WA 98055",
    "addr:housenumber":"757",
    "addr:postcode":"98055",
    "addr:street":"Rainier Ave",
    "iso:country":"US",
    "sg:address":"757 Rainier Ave",
    "sg:city":"Renton",
    "sg:classifiers":[
        {
            "category":"Restaurant",
            "type":"Food & Drink"
        }
    ],
    "sg:phone":"+1 425 793 0404",
    "sg:postcode":"98055",
    "sg:province":"WA",
    "sg:tags":[
        "eating"
    ],
    "wof:name":"Dam Lien",
    "wof:placetype":"venue"
},
  "geometry": {"coordinates":[-122.219194,47.494017],"type":"Point"}
}