{
  "type": "Feature",
  "properties": {
    "addr:full":"318 W 5th St Aberdeen WA 98520",
    "addr:housenumber":"318",
    "addr:postcode":"98520",
    "addr:street":"W 5Th St",
    "iso:country":"US",
    "sg:address":"318 W 5th St",
    "sg:city":"Aberdeen",
    "sg:classifiers":[
        {
            "category":"Personal",
            "subcategory":"Beauty Salon",
            "type":"Services"
        }
    ],
    "sg:phone":"+1 360 532 8012",
    "sg:postcode":"98520",
    "sg:province":"WA",
    "sg:tags":[
        "shop"
    ],
    "wof:name":"Jennifers",
    "wof:placetype":"venue"
},
  "geometry": {"coordinates":[-123.825773,46.977676],"type":"Point"}
}