{
  "type": "Feature",
  "properties": {
    "addr:full":"23175 Indianola Rd NE Poulsbo WA 98370",
    "addr:housenumber":"23175",
    "addr:postcode":"98370",
    "addr:street":"Indianola Rd Ne",
    "iso:country":"US",
    "sg:address":"23175 Indianola Rd NE",
    "sg:city":"Poulsbo",
    "sg:classifiers":[
        {
            "category":"Farming",
            "subcategory":"Aquatic Farm",
            "type":"Manufacturing & Wholesale Goods"
        }
    ],
    "sg:phone":"+1 360 598 3142",
    "sg:postcode":"98370",
    "sg:province":"WA",
    "sg:tags":[
        "fish"
    ],
    "wof:name":"Grovers Creek Salmon Hatchery",
    "wof:placetype":"venue"
},
  "geometry": {"coordinates":[-122.555421,47.771392],"type":"Point"}
}