{
  "type": "Feature",
  "properties": {
    "iso:country":"US",
    "sg:address":"7314 44th Ave NE",
    "sg:city":"Marysville",
    "sg:classifiers":[
        {
            "category":"Organizations",
            "subcategory":"Religious Organization",
            "type":"Services"
        }
    ],
    "sg:phone":"+1 360 659 7335",
    "sg:postcode":"98270",
    "sg:province":"WA",
    "sg:website":"www.ac3.org",
    "wof:name":"Allen Creek Community Church",
    "wof:placetype":"venue"
},
  "geometry": {"coordinates":[-122.171757,48.063814],"type":"Point"}
}