{
  "type": "Feature",
  "properties": {
    "addr:full":"50 Oakshott Rd Colville WA 99114",
    "addr:housenumber":"50",
    "addr:postcode":"99114",
    "addr:street":"Oakshott Rd",
    "iso:country":"US",
    "sg:address":"50 Oakshott Rd",
    "sg:city":"Colville",
    "sg:classifiers":[
        {
            "category":"Home & Garden",
            "subcategory":"Household Appliances",
            "type":"Retail Goods"
        }
    ],
    "sg:phone":"+1 509 684 8237",
    "sg:postcode":"99114",
    "sg:province":"WA",
    "wof:name":"Appliance Parts & More",
    "wof:placetype":"venue"
},
  "geometry": {"coordinates":[-117.931226,48.543408],"type":"Point"}
}