{
  "type": "Feature",
  "properties": {
    "addr:full":"2824 NE Logan St Issaquah WA 98029",
    "addr:housenumber":"2824",
    "addr:postcode":"98029",
    "addr:street":"Ne Logan St",
    "iso:country":"US",
    "sg:address":"2824 NE Logan St",
    "sg:city":"Issaquah",
    "sg:classifiers":[
        {
            "category":"Communications",
            "type":"Services"
        }
    ],
    "sg:phone":"+1 425 576 5299",
    "sg:postcode":"98029",
    "sg:province":"WA",
    "wof:name":"Jeremy Kuno Media",
    "wof:placetype":"venue"
},
  "geometry": {"coordinates":[-121.99682300000001,47.551628],"type":"Point"}
}