{
  "type": "Feature",
  "properties": {
    "addr:full":"36710 SE 20th St Washougal WA 98671",
    "addr:postcode":"36710;98671",
    "addr:street":"Se 20Th St",
    "iso:country":"US",
    "sg:address":"36710 SE 20th St",
    "sg:city":"Washougal",
    "sg:classifiers":[
        {
            "category":"Sports & Exercise",
            "subcategory":"Ice Rink",
            "type":"Entertainment"
        }
    ],
    "sg:phone":"+1 360 835 8485",
    "sg:postcode":"98671",
    "sg:province":"WA",
    "sg:tags":[
        "skating"
    ],
    "wof:name":"Sk8 4 Kix Skate School",
    "wof:placetype":"venue"
},
  "geometry": {"coordinates":[-122.289461,45.60857],"type":"Point"}
}