{
  "type": "Feature",
  "properties": {
    "addr:full":"1422 S Ferdinand Dr Tacoma WA 98405",
    "addr:housenumber":"1422",
    "addr:postcode":"98405",
    "addr:street":"S Ferdinand Dr",
    "iso:country":"US",
    "sg:address":"1422 S Ferdinand Dr",
    "sg:city":"Tacoma",
    "sg:classifiers":[
        {
            "category":"Building & Trades",
            "subcategory":"Plumbing",
            "type":"Services"
        }
    ],
    "sg:phone":"+1 253 851 1940",
    "sg:postcode":"98405",
    "sg:province":"WA",
    "sg:tags":[
        "plumbing",
        "contractor"
    ],
    "wof:name":"A-1 Budget Plumbing",
    "wof:placetype":"venue"
},
  "geometry": {"coordinates":[-122.501717,47.246758],"type":"Point"}
}