{
  "type": "Feature",
  "properties": {
    "addr:full":"11035 NE 14th St Bellevue WA 98004",
    "addr:housenumber":"11035",
    "addr:postcode":"98004",
    "addr:street":"Ne 14Th St",
    "iso:country":"US",
    "sg:address":"11035 NE 14th St",
    "sg:city":"Bellevue",
    "sg:classifiers":[
        {
            "category":"Home & Garden",
            "subcategory":"Garden Supply",
            "type":"Retail Goods"
        }
    ],
    "sg:phone":"+1 425 401 1083",
    "sg:postcode":"98004",
    "sg:province":"WA",
    "sg:tags":[
        "wholesale",
        "sale",
        "internet"
    ],
    "wof:name":"Master Garden Products",
    "wof:placetype":"venue"
},
  "geometry": {"coordinates":[-122.191278,47.62319],"type":"Point"}
}