{
  "type": "Feature",
  "properties": {
    "addr:full":"93 Wall St Seattle WA 98121",
    "addr:housenumber":"93",
    "addr:postcode":"98121",
    "addr:street":"Wall St",
    "iso:country":"US",
    "sg:address":"93 Wall St",
    "sg:city":"Seattle",
    "sg:classifiers":[
        {
            "category":"Shopping",
            "subcategory":"Clothing, Apparel, & Fashions",
            "type":"Retail Goods"
        },
        {
            "category":"Personal",
            "subcategory":"Hair Removal",
            "type":"Services"
        },
        {
            "category":"Personal",
            "subcategory":"Skin Care",
            "type":"Services"
        }
    ],
    "sg:phone":"+1 206 267 2929",
    "sg:postcode":"98121",
    "sg:province":"WA",
    "sg:tags":[
        "lingerie"
    ],
    "sg:website":"www.waxon.com",
    "wof:name":"Wax On Spa",
    "wof:placetype":"venue"
},
  "geometry": {"coordinates":[-122.348895,47.614636],"type":"Point"}
}