{
  "type": "Feature",
  "properties": {
    "addr:full":"2901 S 260th Ln Kent WA 98032",
    "addr:housenumber":"2901",
    "addr:postcode":"98032",
    "addr:street":"S 260Th Ln",
    "iso:country":"US",
    "sg:address":"2901 S 260th Ln",
    "sg:city":"Kent",
    "sg:classifiers":[
        {
            "category":"Retail",
            "subcategory":"Repair Shop",
            "type":"Services"
        }
    ],
    "sg:phone":"+1 253 945 0204",
    "sg:postcode":"98032",
    "sg:province":"WA",
    "wof:name":"Silvias Professional Cleaning",
    "wof:placetype":"venue"
},
  "geometry": {"coordinates":[-122.295146,47.368663],"type":"Point"}
}