{
  "type": "Feature",
  "properties": {
    "addr:full":"2808 E Sanson Ave Spokane WA 99217",
    "addr:housenumber":"2808",
    "addr:postcode":"99217",
    "addr:street":"E Sanson Ave",
    "iso:country":"US",
    "sg:address":"2808 E Sanson Ave",
    "sg:city":"Spokane",
    "sg:classifiers":[
        {
            "category":"Real Estate",
            "subcategory":"Real Estate Operator",
            "type":"Services"
        }
    ],
    "sg:phone":"+1 509 489 7271",
    "sg:postcode":"99217",
    "sg:province":"WA",
    "sg:tags":[
        "building",
        "apartment"
    ],
    "wof:name":"Hillyard Plaza Apartments LP",
    "wof:placetype":"venue"
},
  "geometry": {"coordinates":[-117.36926099999999,47.706738],"type":"Point"}
}