{
  "type": "Feature",
  "properties": {
    "addr:full":"904 W Main St Centralia WA 98531",
    "addr:housenumber":"904",
    "addr:postcode":"98531",
    "addr:street":"W Main St",
    "iso:country":"US",
    "sg:address":"904 W Main St",
    "sg:city":"Centralia",
    "sg:classifiers":[
        {
            "category":"Manufacturing",
            "subcategory":"Lumber",
            "type":"Manufacturing & Wholesale Goods"
        }
    ],
    "sg:phone":"+1 360 736 8453",
    "sg:postcode":"98531",
    "sg:province":"WA",
    "sg:tags":[
        "forester"
    ],
    "sg:website":"www.wtmtrees.com",
    "wof:name":"Washington Timberlands Mgmt",
    "wof:placetype":"venue"
},
  "geometry": {"coordinates":[-122.96460399999999,46.718244],"type":"Point"}
}