{
  "type": "Feature",
  "properties": {
    "addr:full":"877B E Pole Rd Lynden WA 98264",
    "addr:postcode":"98264",
    "addr:street":"E Pole Rd",
    "iso:country":"US",
    "sg:address":"877B E Pole Rd",
    "sg:city":"Lynden",
    "sg:classifiers":[
        {
            "category":"Professional",
            "subcategory":"Computer Services",
            "type":"Services"
        }
    ],
    "sg:phone":"+1 360 656 6577",
    "sg:postcode":"98264",
    "sg:province":"WA",
    "sg:tags":[
        "graphic"
    ],
    "wof:name":"Gg Graphix",
    "wof:placetype":"venue"
},
  "geometry": {"coordinates":[-122.45037600000001,48.891718],"type":"Point"}
}