{
  "type": "Feature",
  "properties": {
    "iso:country":"US",
    "sg:address":"7646 S K St",
    "sg:city":"Tacoma",
    "sg:classifiers":[
        {
            "category":"Professional",
            "type":"Services"
        }
    ],
    "sg:phone":"+1 253 475 3328",
    "sg:postcode":"98408",
    "sg:province":"WA",
    "wof:name":"Access Limos Service",
    "wof:placetype":"venue"
},
  "geometry": {"coordinates":[-122.44866500000001,47.186541],"type":"Point"}
}