{
  "type": "Feature",
  "properties": {
    "addr:full":"118 Mountain Ests Chehalis WA 98532",
    "addr:housenumber":"118",
    "addr:postcode":"98532",
    "addr:street":"Mountain Ests",
    "iso:country":"US",
    "sg:address":"118 Mountain Ests",
    "sg:city":"Chehalis",
    "sg:classifiers":[
        {
            "category":"Recreation",
            "type":"Entertainment"
        }
    ],
    "sg:phone":"+1 360 748 1823",
    "sg:postcode":"98532",
    "sg:province":"WA",
    "sg:tags":[
        "club",
        "membership"
    ],
    "wof:name":"Little League Baseball In",
    "wof:placetype":"venue"
},
  "geometry": {"coordinates":[-122.85848300000001,46.588343],"type":"Point"}
}