{
  "type": "Feature",
  "properties": {
    "addr:full":"14005 SE 46th St Bellevue WA 98006",
    "addr:postcode":"14005;98006",
    "addr:street":"Se 46Th St",
    "iso:country":"US",
    "sg:address":"14005 SE 46th St",
    "sg:city":"Bellevue",
    "sg:classifiers":[
        {
            "category":"Professional",
            "subcategory":"Management & Consulting",
            "type":"Services"
        }
    ],
    "sg:phone":"+1 425 747 6605",
    "sg:postcode":"98006",
    "sg:province":"WA",
    "sg:tags":[
        "business"
    ],
    "wof:name":"Thomas A Waldeck",
    "wof:placetype":"venue"
},
  "geometry": {"coordinates":[-122.15290899999999,47.561843],"type":"Point"}
}