{
  "type": "Feature",
  "properties": {
    "addr:full":"911 Hildebrand Lane NE Bainbridge Island WA 98110",
    "addr:housenumber":"911",
    "addr:postcode":"98110",
    "addr:street":"Hildebrand Lane Ne",
    "iso:country":"US",
    "sg:address":"911 Hildebrand Lane NE",
    "sg:city":"Bainbridge Island",
    "sg:classifiers":[
        {
            "category":"Banks & Credit Unions",
            "subcategory":"Financial Services",
            "type":"Services"
        }
    ],
    "sg:phone":"+1 206 842 9347",
    "sg:postcode":"98110",
    "sg:province":"WA",
    "sg:tags":[
        "broker",
        "mortgage"
    ],
    "wof:name":"Cfa Escrow",
    "wof:placetype":"venue"
},
  "geometry": {"coordinates":[-122.517049,47.632282],"type":"Point"}
}