{
  "type": "Feature",
  "properties": {
    "addr:full":"1001 Senna St Ste Ofc Omak WA 98841",
    "addr:housenumber":"1001",
    "addr:postcode":"98841",
    "addr:street":"Senna St Ste",
    "iso:country":"US",
    "sg:address":"1001 Senna St Ste Ofc",
    "sg:city":"Omak",
    "sg:classifiers":[
        {
            "category":"Health Services",
            "subcategory":"Nursing And Care Facility",
            "type":"Services"
        },
        {
            "category":"Health Services",
            "subcategory":"Health Practitioner",
            "type":"Services"
        },
        {
            "category":"Social Services",
            "subcategory":"Retirement Home",
            "type":"Services"
        }
    ],
    "sg:phone":"+1 509 826 3590",
    "sg:postcode":"98841",
    "sg:province":"WA",
    "sg:tags":[
        "living",
        "assisted",
        "homes-intermediate"
    ],
    "wof:name":"Apple Springs Retirement & Assisted Living",
    "wof:placetype":"venue"
},
  "geometry": {"coordinates":[-119.505814,48.423592],"type":"Point"}
}