{
  "type": "Feature",
  "properties": {
    "addr:full":"15303 179th Ave NE Woodinville WA 98072",
    "addr:housenumber":"15303",
    "addr:postcode":"98072",
    "addr:street":"179Th Ave Ne",
    "iso:country":"US",
    "sg:address":"15303 179th Ave NE",
    "sg:city":"Woodinville",
    "sg:classifiers":[
        {
            "category":"Professional",
            "type":"Services"
        }
    ],
    "sg:phone":"+1 425 485 8881",
    "sg:postcode":"98072",
    "sg:province":"WA",
    "wof:name":"Kemcor Inc",
    "wof:placetype":"venue"
},
  "geometry": {"coordinates":[-122.100937,47.737042],"type":"Point"}
}