{
  "type": "Feature",
  "properties": {
    "addr:full":"11050 5th Ave NE Ste 206 Seattle WA 98125",
    "addr:housenumber":"11050",
    "addr:postcode":"98125",
    "addr:street":"5Th Ave Ne Ste 206",
    "iso:country":"US",
    "sg:address":"11050 5th Ave NE Ste 206",
    "sg:city":"Seattle",
    "sg:classifiers":[
        {
            "category":"Insurance",
            "subcategory":"Insurance Agent",
            "type":"Services"
        },
        {
            "category":"Insurance",
            "subcategory":"Hazard Insurance",
            "type":"Services"
        }
    ],
    "sg:phone":"+1 206 361 9693",
    "sg:postcode":"98125",
    "sg:province":"WA",
    "sg:tags":[
        "business",
        "commercial",
        "fidelity",
        "surety",
        "bond"
    ],
    "sg:website":"http://www.cbmsofwa.com",
    "wof:name":"Construction Bonding & Management Services Of Washington Inc",
    "wof:placetype":"venue"
},
  "geometry": {"coordinates":[-122.3233,47.709116],"type":"Point"}
}