{
  "type": "Feature",
  "properties": {
    "addr:full":"11443 Rainier Ave Seattle WA 98178",
    "addr:housenumber":"11443",
    "addr:postcode":"98178",
    "addr:street":"Rainier Ave",
    "iso:country":"US",
    "sg:address":"11443 Rainier Ave",
    "sg:city":"Seattle",
    "sg:classifiers":[
        {
            "category":"Shopping",
            "subcategory":"Used Merchandise",
            "type":"Retail Goods"
        }
    ],
    "sg:phone":"+1 425 254 8700",
    "sg:postcode":"98178",
    "sg:province":"WA",
    "sg:tags":[
        "shop",
        "consignment"
    ],
    "wof:name":"Ginger's Klosett",
    "wof:placetype":"venue"
},
  "geometry": {"coordinates":[-122.221422,47.50055],"type":"Point"}
}