{
  "type": "Feature",
  "properties": {
    "addr:full":"1323 S Ash St Spokane WA 99204",
    "addr:housenumber":"1323",
    "addr:postcode":"99204",
    "addr:street":"S Ash St",
    "iso:country":"US",
    "sg:address":"1323 S Ash St",
    "sg:city":"Spokane",
    "sg:classifiers":[
        {
            "category":"Health Services",
            "subcategory":"Clinic",
            "type":"Services"
        }
    ],
    "sg:phone":"+1 509 242 4325",
    "sg:postcode":"99204",
    "sg:province":"WA",
    "sg:tags":[
        "specialty",
        "outpatient"
    ],
    "wof:name":"Healing Therapies of Spokane",
    "wof:placetype":"venue"
},
  "geometry": {"coordinates":[-117.436525,47.643315],"type":"Point"}
}