{
  "type": "Feature",
  "properties": {
    "addr:full":"2919 Pine St Everett WA 98201",
    "addr:housenumber":"2919",
    "addr:postcode":"98201",
    "addr:street":"Pine St",
    "iso:country":"US",
    "sg:address":"2919 Pine St",
    "sg:city":"Everett",
    "sg:classifiers":[
        {
            "category":"Manufacturing",
            "subcategory":"Tools & Machinery",
            "type":"Manufacturing & Wholesale Goods"
        }
    ],
    "sg:phone":"+1 425 787 8868",
    "sg:postcode":"98201",
    "sg:province":"WA",
    "sg:tags":[
        "machine",
        "shop"
    ],
    "wof:name":"Advanced Designs",
    "wof:placetype":"venue"
},
  "geometry": {"coordinates":[-122.192381,47.976943],"type":"Point"}
}