{
  "type": "Feature",
  "properties": {
    "addr:full":"1802 N Shore Rd Newport WA 99156",
    "addr:housenumber":"1802",
    "addr:postcode":"99156",
    "addr:street":"N Shore Rd",
    "iso:country":"US",
    "sg:address":"1802 N Shore Rd",
    "sg:city":"Newport",
    "sg:classifiers":[
        {
            "category":"Manufacturing",
            "subcategory":"Lumber",
            "type":"Manufacturing & Wholesale Goods"
        }
    ],
    "sg:phone":"+1 509 447 3028",
    "sg:postcode":"99156",
    "sg:province":"WA",
    "sg:tags":[
        "forestry"
    ],
    "wof:name":"Wildwood Forestry",
    "wof:placetype":"venue"
},
  "geometry": {"coordinates":[-117.24159299999999,48.118491],"type":"Point"}
}