{
  "type": "Feature",
  "properties": {
    "addr:full":"32610 Pacific Hwy S Federal Way WA 98003",
    "addr:housenumber":"32610",
    "addr:postcode":"98003",
    "addr:street":"Pacific Hwy S Federal Way",
    "iso:country":"US",
    "sg:address":"32610 Pacific Hwy S",
    "sg:city":"Federal Way",
    "sg:classifiers":[
        {
            "category":"Retail",
            "subcategory":"Auto Repair",
            "type":"Services"
        }
    ],
    "sg:phone":"+1 253 927 4449",
    "sg:postcode":"98003",
    "sg:province":"WA",
    "sg:tags":[
        "glass",
        "replacement"
    ],
    "wof:name":"Speedy Auto Glass",
    "wof:placetype":"venue"
},
  "geometry": {"coordinates":[-122.31332399999999,47.309794],"type":"Point"}
}