{
  "type": "Feature",
  "properties": {
    "addr:full":"14517 SE Rivercrest Dr Vancouver WA 98683",
    "addr:postcode":"14517;98683",
    "addr:street":"Se Rivercrest Dr",
    "iso:country":"US",
    "sg:address":"14517 SE Rivercrest Dr",
    "sg:city":"Vancouver",
    "sg:classifiers":[
        {
            "category":"Professional",
            "subcategory":"Engineering",
            "type":"Services"
        }
    ],
    "sg:phone":"+1 360 883 9033",
    "sg:postcode":"98683",
    "sg:province":"WA",
    "sg:tags":[
        "engineer"
    ],
    "wof:name":"Breshears/Thornton Engineering",
    "wof:placetype":"venue"
},
  "geometry": {"coordinates":[-122.521225,45.595436],"type":"Point"}
}