{
  "type": "Feature",
  "properties": {
    "addr:full":"425 E Perry St Aberdeen WA 98520",
    "addr:housenumber":"425",
    "addr:postcode":"98520",
    "addr:street":"E Perry St",
    "iso:country":"US",
    "sg:address":"425 E Perry St",
    "sg:city":"Aberdeen",
    "sg:classifiers":[
        {
            "category":"Professional",
            "subcategory":"Advertising",
            "type":"Services"
        }
    ],
    "sg:phone":"+1 360 537 8216",
    "sg:postcode":"98520",
    "sg:province":"WA",
    "sg:tags":[
        "mail",
        "logging",
        "direct"
    ],
    "wof:name":"Weyerhaeuser Bay Cy Sort Yard",
    "wof:placetype":"venue"
},
  "geometry": {"coordinates":[-123.785557,46.96692],"type":"Point"}
}