{
  "type": "Feature",
  "properties": {
    "addr:full":"22826 56th Ave W Mountlake Terrace WA 98043",
    "addr:housenumber":"22826",
    "addr:postcode":"98043",
    "addr:street":"56Th Ave W",
    "iso:country":"US",
    "sg:address":"22826 56th Ave W",
    "sg:city":"Mountlake Terrace",
    "sg:classifiers":[
        {
            "category":"Restaurant",
            "type":"Food & Drink"
        }
    ],
    "sg:phone":"+1 425 712 9112",
    "sg:postcode":"98043",
    "sg:province":"WA",
    "sg:tags":[
        "eating"
    ],
    "wof:name":"Cafe On Terrace",
    "wof:placetype":"venue"
},
  "geometry": {"coordinates":[-122.30855,47.790483],"type":"Point"}
}