{
  "type": "Feature",
  "properties": {
    "addr:full":"2909 Cherokee Blvd SE Puyallup WA 98374",
    "addr:housenumber":"2909",
    "addr:postcode":"98374",
    "addr:street":"Cherokee Blvd Se",
    "iso:country":"US",
    "sg:address":"2909 Cherokee Blvd SE",
    "sg:city":"Puyallup",
    "sg:classifiers":[
        {
            "category":"Home & Garden",
            "subcategory":"Household Appliances",
            "type":"Retail Goods"
        }
    ],
    "sg:phone":"+1 253 845 8003",
    "sg:postcode":"98374",
    "sg:province":"WA",
    "wof:name":"Dotties Kitchen Center",
    "wof:placetype":"venue"
},
  "geometry": {"coordinates":[-122.254262,47.166881],"type":"Point"}
}