{
  "type": "Feature",
  "properties": {
    "addr:full":"11660 NE 155th St Bothell WA 98011",
    "addr:housenumber":"11660",
    "addr:postcode":"98011",
    "addr:street":"Ne 155Th St",
    "iso:country":"US",
    "sg:address":"11660 NE 155th St",
    "sg:city":"Bothell",
    "sg:classifiers":[
        {
            "category":"Professional",
            "subcategory":"Computer Services",
            "type":"Services"
        }
    ],
    "sg:phone":"+1 425 489 1376",
    "sg:postcode":"98011",
    "sg:province":"WA",
    "sg:tags":[
        "related"
    ],
    "wof:name":"Softouch",
    "wof:placetype":"venue"
},
  "geometry": {"coordinates":[-122.184038,47.739236],"type":"Point"}
}