{
  "type": "Feature",
  "properties": {
    "addr:full":"1955 Prospect Ave NE Olympia WA 98506",
    "addr:housenumber":"1955",
    "addr:postcode":"98506",
    "addr:street":"Prospect Ave Ne",
    "iso:country":"US",
    "sg:address":"1955 Prospect Ave NE",
    "sg:city":"Olympia",
    "sg:classifiers":[
        {
            "category":"Cinema",
            "subcategory":"Movie Rental",
            "type":"Entertainment"
        }
    ],
    "sg:phone":"+1 360 352 8041",
    "sg:postcode":"98506",
    "sg:province":"WA",
    "sg:tags":[
        "video",
        "tape"
    ],
    "wof:name":"Trinity Audio/Video",
    "wof:placetype":"venue"
},
  "geometry": {"coordinates":[-122.874983,47.049116],"type":"Point"}
}