{
  "type": "Feature",
  "properties": {
    "addr:full":"675 S Lane St Seattle WA 98104",
    "addr:housenumber":"675",
    "addr:postcode":"98104",
    "addr:street":"S Lane",
    "iso:country":"US",
    "sg:address":"675 S Lane St",
    "sg:city":"Seattle",
    "sg:classifiers":[
        {
            "category":"Banks & Credit Unions",
            "subcategory":"Investment Brokerage",
            "type":"Services"
        }
    ],
    "sg:phone":"+1 206 624 3114",
    "sg:postcode":"98104",
    "sg:province":"WA",
    "sg:tags":[
        "advisory",
        "financial"
    ],
    "wof:name":"Gilbralter Financial",
    "wof:placetype":"venue"
},
  "geometry": {"coordinates":[-122.32411399999999,47.596595],"type":"Point"}
}