{
  "type": "Feature",
  "properties": {
    "addr:full":"1700 W 4th Plain Blvd Vancouver WA 98660",
    "addr:housenumber":"1700",
    "addr:postcode":"98660",
    "addr:street":"W 4Th Plain Blvd",
    "iso:country":"US",
    "sg:address":"1700 W 4th Plain Blvd",
    "sg:city":"Vancouver",
    "sg:classifiers":[
        {
            "category":"Building & Trades",
            "subcategory":"Landscaping Services",
            "type":"Services"
        }
    ],
    "sg:phone":"+1 360 253 6579",
    "sg:postcode":"98660",
    "sg:province":"WA",
    "sg:website":"www.barkdusters.com",
    "wof:name":"Barkdusters, Inc.",
    "wof:placetype":"venue"
},
  "geometry": {"coordinates":[-122.688596,45.640791],"type":"Point"}
}