{
  "type": "Feature",
  "properties": {
    "addr:full":"1107 Oak St Milton WA 98354",
    "addr:housenumber":"1107",
    "addr:postcode":"98354",
    "addr:street":"Oak St",
    "iso:country":"US",
    "sg:address":"1107 Oak St",
    "sg:city":"Milton",
    "sg:classifiers":[
        {
            "category":"Shopping",
            "subcategory":"Used Merchandise",
            "type":"Retail Goods"
        }
    ],
    "sg:phone":"+1 253 922 7885",
    "sg:postcode":"98354",
    "sg:province":"WA",
    "sg:tags":[
        "antique"
    ],
    "wof:name":"Golden Memories Antiques Gifts",
    "wof:placetype":"venue"
},
  "geometry": {"coordinates":[-122.320504,47.246496],"type":"Point"}
}