{
  "type": "Feature",
  "properties": {
    "addr:full":"400 1st Ave N Algona WA 98001",
    "addr:housenumber":"400",
    "addr:postcode":"98001",
    "addr:street":"1St Ave N Algona",
    "iso:country":"US",
    "sg:address":"400 1st Ave N",
    "sg:city":"Algona",
    "sg:classifiers":[
        {
            "category":"Restaurant",
            "type":"Food & Drink"
        }
    ],
    "sg:phone":"+1 253 735 9295",
    "sg:postcode":"98001",
    "sg:province":"WA",
    "sg:tags":[
        "delicatessen",
        "eating"
    ],
    "wof:name":"Algona Teriyaki",
    "wof:placetype":"venue"
},
  "geometry": {"coordinates":[-122.24910199999999,47.279095],"type":"Point"}
}