{
  "type": "Feature",
  "properties": {
    "iso:country":"US",
    "sg:address":"7555 Dowerdell Ln W",
    "sg:city":"Lakewood",
    "sg:classifiers":[
        {
            "category":"Shopping",
            "subcategory":"Clothing, Apparel, & Fashions",
            "type":"Retail Goods"
        }
    ],
    "sg:phone":"+1 253 582 0222",
    "sg:postcode":"98499",
    "sg:province":"WA",
    "sg:tags":[
        "navy",
        "army"
    ],
    "wof:name":"Crests Unlimited",
    "wof:placetype":"venue"
},
  "geometry": {"coordinates":[-122.52643999999999,47.189463],"type":"Point"}
}