{
  "type": "Feature",
  "properties": {
    "addr:full":"8165 Guide Meridian Rd Lynden WA 98264",
    "addr:housenumber":"8165",
    "addr:postcode":"98264",
    "addr:street":"Guide Meridian Rd",
    "iso:country":"US",
    "sg:address":"8165 Guide Meridian Rd",
    "sg:city":"Lynden",
    "sg:classifiers":[
        {
            "category":"Autos & Motor Vehicles",
            "subcategory":"Recreational Vehicle Sales",
            "type":"Retail Goods"
        }
    ],
    "sg:phone":"+1 360 354 4477",
    "sg:postcode":"98264",
    "sg:province":"WA",
    "wof:name":"Wts",
    "wof:placetype":"venue"
},
  "geometry": {"coordinates":[-122.485467,48.937673],"type":"Point"}
}