{
  "type": "Feature",
  "properties": {
    "addr:full":"14748 E Indiana Ave Spokane WA 99216",
    "addr:housenumber":"14748",
    "addr:postcode":"99216",
    "addr:street":"E Indiana Ave",
    "iso:country":"US",
    "sg:address":"14748 E Indiana Ave",
    "sg:city":"Spokane",
    "sg:classifiers":[
        {
            "category":"Home & Garden",
            "subcategory":"Home Furnishings",
            "type":"Retail Goods"
        }
    ],
    "sg:phone":"+1 509 893 3555",
    "sg:postcode":"99216",
    "sg:province":"WA",
    "wof:name":"Pier 1imports//",
    "wof:placetype":"venue"
},
  "geometry": {"coordinates":[-117.205406,47.675664],"type":"Point"}
}