{
  "type": "Feature",
  "properties": {
    "addr:full":"2121 Olympic Hwy N Shelton WA 98584",
    "addr:housenumber":"2121",
    "addr:postcode":"98584",
    "addr:street":"Olympic Hwy N",
    "iso:country":"US",
    "sg:address":"2121 Olympic Hwy N",
    "sg:city":"Shelton",
    "sg:classifiers":[
        {
            "category":"Travel",
            "subcategory":"Travel Agent",
            "type":"Entertainment"
        }
    ],
    "sg:phone":"+1 360 426 8274",
    "sg:postcode":"98584",
    "sg:province":"WA",
    "sg:tags":[
        "agency"
    ],
    "wof:name":"My Travel Agent",
    "wof:placetype":"venue"
},
  "geometry": {"coordinates":[-123.12159,47.22347],"type":"Point"}
}