{
  "type": "Feature",
  "properties": {
    "addr:full":"1431 Bonsella St Walla Walla WA 99362",
    "addr:housenumber":"1431",
    "addr:postcode":"99362",
    "addr:street":"Bonsella St",
    "iso:country":"US",
    "sg:address":"1431 Bonsella St",
    "sg:city":"Walla Walla",
    "sg:classifiers":[
        {
            "category":"Professional",
            "type":"Services"
        }
    ],
    "sg:phone":"+1 509 526 7170",
    "sg:postcode":"99362",
    "sg:province":"WA",
    "wof:name":"Martin D Tawnya",
    "wof:placetype":"venue"
},
  "geometry": {"coordinates":[-118.321185,46.079462],"type":"Point"}
}