{
  "type": "Feature",
  "properties": {
    "addr:full":"1201 SE Tech Center Dr Vancouver WA 98683",
    "addr:housenumber":"1201",
    "addr:postcode":"98683",
    "addr:street":"Se Tech Center Dr",
    "iso:country":"US",
    "sg:address":"1201 SE Tech Center Dr",
    "sg:city":"Vancouver",
    "sg:classifiers":[
        {
            "category":"Government",
            "subcategory":"Police Station",
            "type":"Public Place"
        }
    ],
    "sg:phone":"+1 360 696 8100",
    "sg:postcode":"98683",
    "sg:province":"WA",
    "sg:tags":[
        "department"
    ],
    "sg:website":"www.vanpolice.org",
    "wof:name":"Vancouver Police East Precinct",
    "wof:placetype":"venue"
},
  "geometry": {"coordinates":[-122.49887099999999,45.612364],"type":"Point"}
}