{
  "type": "Feature",
  "properties": {
    "addr:full":"2809 Meridian Ave E Edgewood WA 98371",
    "addr:housenumber":"2809",
    "addr:postcode":"98371",
    "addr:street":"Meridian Ave E",
    "iso:country":"US",
    "sg:address":"2809 Meridian Ave E",
    "sg:city":"Edgewood",
    "sg:classifiers":[
        {
            "category":"Health Services",
            "subcategory":"Nursing And Care Facility",
            "type":"Services"
        },
        {
            "category":"Health Services",
            "subcategory":"Chiropractor",
            "type":"Services"
        }
    ],
    "sg:phone":"+1 253 840 1100",
    "sg:postcode":"98371",
    "sg:province":"WA",
    "sg:tags":[
        "management",
        "pain",
        "chiropractic"
    ],
    "sg:website":"http://www.liveharmonyhealth.com",
    "wof:name":"Harmony Health Chiropractic & Massage",
    "wof:placetype":"venue"
},
  "geometry": {"coordinates":[-122.293999,47.231912],"type":"Point"}
}