{
  "type": "Feature",
  "properties": {
    "addr:full":"2100 SE 164th Ave Vancouver WA 98683",
    "addr:housenumber":"2100",
    "addr:postcode":"98683",
    "addr:street":"Se 164Th Ave",
    "iso:country":"US",
    "sg:address":"2100 SE 164th Ave",
    "sg:city":"Vancouver",
    "sg:classifiers":[
        {
            "category":"Cinema",
            "subcategory":"Movie Rental",
            "type":"Entertainment"
        }
    ],
    "sg:phone":"+1 360 253 5300",
    "sg:postcode":"98683",
    "sg:province":"WA",
    "sg:tags":[
        "game",
        "video"
    ],
    "sg:website":"www.blockbuster.com",
    "wof:name":"Blockbuster Video",
    "wof:placetype":"venue"
},
  "geometry": {"coordinates":[-122.503998,45.605999],"type":"Point"}
}