{
  "type": "Feature",
  "properties": {
    "addr:full":"1888 SE Sedgwick Rd Port Orchard WA 98366",
    "addr:housenumber":"1888",
    "addr:postcode":"98366",
    "addr:street":"Se Sedgwick Rd",
    "iso:country":"US",
    "sg:address":"1888 SE Sedgwick Rd",
    "sg:city":"Port Orchard",
    "sg:classifiers":[
        {
            "category":"Shopping",
            "subcategory":"Tobacco",
            "type":"Retail Goods"
        }
    ],
    "sg:phone":"+1 360 895 1601",
    "sg:postcode":"98366",
    "sg:province":"WA",
    "sg:tags":[
        "cigarette",
        "cigar",
        "dealer"
    ],
    "wof:name":"1 Tobacco",
    "wof:placetype":"venue"
},
  "geometry": {"coordinates":[-122.62918500000001,47.50484],"type":"Point"}
}