{
  "type": "Feature",
  "properties": {
    "addr:full":"507 Olive Way Seattle WA 98101",
    "addr:housenumber":"507",
    "addr:postcode":"98101",
    "addr:street":"Olive Way",
    "iso:country":"US",
    "sg:address":"507 Olive Way",
    "sg:city":"Seattle",
    "sg:classifiers":[
        {
            "category":"Shopping",
            "subcategory":"Florist",
            "type":"Retail Goods"
        }
    ],
    "sg:phone":"+1 206 340 1502",
    "sg:postcode":"98101",
    "sg:province":"WA",
    "sg:website":"www.trudysflowers.com",
    "wof:name":"Trudy's Flowers",
    "wof:placetype":"venue"
},
  "geometry": {"coordinates":[-122.33699799999999,47.612801],"type":"Point"}
}