{
  "type": "Feature",
  "properties": {
    "addr:full":"616 S Warner St Tacoma WA 98405",
    "addr:housenumber":"616",
    "addr:postcode":"98405",
    "addr:street":"S Warner St",
    "iso:country":"US",
    "sg:address":"616 S Warner St",
    "sg:city":"Tacoma",
    "sg:classifiers":[
        {
            "category":"Shopping",
            "subcategory":"Beauty & Cosmetics",
            "type":"Retail Goods"
        }
    ],
    "sg:phone":"+1 253 759 5569",
    "sg:postcode":"98405",
    "sg:province":"WA",
    "sg:tags":[
        "merchandise",
        "business"
    ],
    "wof:name":"Cast of Thousands",
    "wof:placetype":"venue"
},
  "geometry": {"coordinates":[-122.48077000000001,47.254524],"type":"Point"}
}