{
  "type": "Feature",
  "properties": {
    "addr:full":"1101 2nd Ave Seattle WA 98101",
    "addr:housenumber":"1101",
    "addr:postcode":"98101",
    "addr:street":"2Nd Ave",
    "iso:country":"US",
    "sg:address":"1101 2nd Ave",
    "sg:city":"Seattle",
    "sg:classifiers":[
        {
            "category":"Building & Trades",
            "subcategory":"Locksmith",
            "type":"Services"
        }
    ],
    "sg:phone":"+1 253 649 7054",
    "sg:postcode":"98101",
    "sg:province":"WA",
    "sg:tags":[
        "key"
    ],
    "wof:name":"Locksmith and Lockout Service Seattle",
    "wof:placetype":"venue"
},
  "geometry": {"coordinates":[-122.33612100000001,47.606009],"type":"Point"}
}