{
  "type": "Feature",
  "properties": {
    "addr:full":"1354 S Basin Rd Colville WA 99114",
    "addr:housenumber":"1354",
    "addr:postcode":"99114",
    "addr:street":"S Basin Rd",
    "iso:country":"US",
    "sg:address":"1354 S Basin Rd",
    "sg:city":"Colville",
    "sg:classifiers":[
        {
            "category":"Retail",
            "subcategory":"Auto Repair",
            "type":"Services"
        }
    ],
    "sg:phone":"+1 509 684 2987",
    "sg:postcode":"99114",
    "sg:province":"WA",
    "sg:tags":[
        "general"
    ],
    "wof:name":"Griffs Auto Repair",
    "wof:placetype":"venue"
},
  "geometry": {"coordinates":[-117.998402,48.434995],"type":"Point"}
}