{
  "type": "Feature",
  "properties": {
    "addr:full":"903 North 130 Th St #110 Seattle WA 98188",
    "addr:housenumber":"903",
    "addr:postcode":"98188",
    "addr:street":"North 130 Th St # 110",
    "iso:country":"US",
    "sg:address":"903 North 130 Th St #110",
    "sg:city":"Seattle",
    "sg:classifiers":[
        {
            "category":"Retail",
            "subcategory":"Laundry & Dry Cleaning",
            "type":"Services"
        },
        {
            "category":"Personal",
            "type":"Services"
        },
        {
            "category":"Building & Trades",
            "subcategory":"Cleaning & Sanitation",
            "type":"Services"
        }
    ],
    "sg:phone":"+1 206 624 9717",
    "sg:postcode":"98188",
    "sg:province":"WA",
    "sg:tags":[
        "house",
        "washing",
        "chimney"
    ],
    "wof:name":"aaa cleaning",
    "wof:placetype":"venue"
},
  "geometry": {"coordinates":[-122.346555,47.723221],"type":"Point"}
}