{
  "type": "Feature",
  "properties": {
    "addr:full":"10102 E Knox Ave Spokane Valley WA 99206",
    "addr:housenumber":"10102",
    "addr:postcode":"99206",
    "addr:street":"E Knox Ave",
    "iso:country":"US",
    "sg:address":"10102 E Knox Ave",
    "sg:city":"Spokane Valley",
    "sg:classifiers":[
        {
            "category":"Wholesale",
            "subcategory":"Electrical",
            "type":"Manufacturing & Wholesale Goods"
        }
    ],
    "sg:phone":"+1 509 534 6055",
    "sg:postcode":"99206",
    "sg:province":"WA",
    "sg:tags":[
        "fire",
        "equipment",
        "alarm",
        "system"
    ],
    "sg:website":"www.simplex.com",
    "wof:name":"Simplex Grinnell",
    "wof:placetype":"venue"
},
  "geometry": {"coordinates":[-117.26882999999999,47.676866],"type":"Point"}
}