{
  "type": "Feature",
  "properties": {
    "addr:full":"6339 Noon Rd Everson WA 98247",
    "addr:housenumber":"6339",
    "addr:postcode":"98247",
    "addr:street":"Noon Rd",
    "iso:country":"US",
    "sg:address":"6339 Noon Rd",
    "sg:city":"Everson",
    "sg:classifiers":[
        {
            "category":"Social Services",
            "subcategory":"Adult Care",
            "type":"Services"
        },
        {
            "category":"Social Services",
            "subcategory":"Retirement Home",
            "type":"Services"
        }
    ],
    "sg:phone":"+1 360 318 1051",
    "sg:postcode":"98247",
    "sg:province":"WA",
    "sg:tags":[
        "convalescent",
        "centers-adult",
        "nursing",
        "day"
    ],
    "sg:website":"http://www.alovingheartafh.com",
    "wof:name":"A Loving Heart Adult Family Home, Inc.",
    "wof:placetype":"venue"
},
  "geometry": {"coordinates":[-122.397941,48.870925],"type":"Point"}
}