{
  "type": "Feature",
  "properties": {
    "iso:country":"US",
    "sg:address":"2012 W Montgomery Ave",
    "sg:city":"Spokane",
    "sg:classifiers":[
        {
            "category":"Retail",
            "subcategory":"Auto Repair",
            "type":"Services"
        }
    ],
    "sg:phone":"+1 509 328 1744",
    "sg:postcode":"99205",
    "sg:province":"WA",
    "sg:tags":[
        "automotive"
    ],
    "wof:name":"Glass Medic Windshield RE",
    "wof:placetype":"venue"
},
  "geometry": {"coordinates":[-117.44274900000001,47.678624],"type":"Point"}
}