{
  "type": "Feature",
  "properties": {
    "addr:full":"7527 Trowbridge Ave SE Olympia WA 98513",
    "addr:housenumber":"7527",
    "addr:postcode":"98513",
    "addr:street":"Trowbridge Ave Se",
    "iso:country":"US",
    "sg:address":"7527 Trowbridge Ave SE",
    "sg:city":"Olympia",
    "sg:classifiers":[
        {
            "category":"Professional",
            "type":"Services"
        }
    ],
    "sg:phone":"+1 360 446 3266",
    "sg:postcode":"98513",
    "sg:province":"WA",
    "wof:name":"Deborah Ann Aitkin",
    "wof:placetype":"venue"
},
  "geometry": {"coordinates":[-122.786142,46.960803],"type":"Point"}
}