{
  "type": "Feature",
  "properties": {
    "addr:full":"945 S College Ave College Place WA 99324",
    "addr:housenumber":"945",
    "addr:postcode":"99324",
    "addr:street":"S College Ave",
    "iso:country":"US",
    "sg:address":"945 S College Ave",
    "sg:city":"College Place",
    "sg:classifiers":[
        {
            "category":"Real Estate",
            "subcategory":"Developer",
            "type":"Services"
        }
    ],
    "sg:phone":"+1 509 529 2406",
    "sg:postcode":"99324",
    "sg:province":"WA",
    "sg:tags":[
        "development",
        "home"
    ],
    "wof:name":"W Paul Gatewood Construction",
    "wof:placetype":"venue"
},
  "geometry": {"coordinates":[-118.38847699999999,46.04069],"type":"Point"}
}