{
  "type": "Feature",
  "properties": {
    "addr:full":"14214 Glen Acres Rd SW Vashon WA 98070",
    "addr:housenumber":"14214",
    "addr:postcode":"98070",
    "addr:street":"Glen Acres Rd Sw",
    "iso:country":"US",
    "sg:address":"14214 Glen Acres Rd SW",
    "sg:city":"Vashon",
    "sg:classifiers":[
        {
            "category":"Health Services",
            "subcategory":"Doctor",
            "type":"Services"
        }
    ],
    "sg:phone":"+1 206 567 4626",
    "sg:postcode":"98070",
    "sg:province":"WA",
    "sg:tags":[
        "psychoanalyst"
    ],
    "wof:name":"Nan E Mc Gehee",
    "wof:placetype":"venue"
},
  "geometry": {"coordinates":[-122.449579,47.477331],"type":"Point"}
}