{
  "type": "Feature",
  "properties": {
    "addr:full":"1201 S Vale St Seattle WA 98108",
    "addr:housenumber":"1201",
    "addr:postcode":"98108",
    "addr:street":"S Vale St",
    "iso:country":"US",
    "sg:address":"1201 S Vale St",
    "sg:city":"Seattle",
    "sg:classifiers":[
        {
            "category":"Shopping",
            "subcategory":"Music",
            "type":"Retail Goods"
        }
    ],
    "sg:phone":"+1 206 762 5638",
    "sg:postcode":"98108",
    "sg:province":"WA",
    "sg:tags":[
        "dvd's"
    ],
    "sg:website":"www.georgetownrecords.net",
    "wof:name":"Georgetown Records",
    "wof:placetype":"venue"
},
  "geometry": {"coordinates":[-122.31703899999999,47.549118],"type":"Point"}
}