{
  "type": "Feature",
  "properties": {
    "addr:full":"3808 S Mead St Seattle WA 98118",
    "addr:housenumber":"3808",
    "addr:postcode":"98118",
    "addr:street":"S Mead St",
    "iso:country":"US",
    "sg:address":"3808 S Mead St",
    "sg:city":"Seattle",
    "sg:classifiers":[
        {
            "category":"Social Services",
            "subcategory":"Child Care",
            "type":"Services"
        }
    ],
    "sg:phone":"+1 206 722 4672",
    "sg:postcode":"98118",
    "sg:province":"WA",
    "sg:tags":[
        "day"
    ],
    "wof:name":"B & T Preschool Academy",
    "wof:placetype":"venue"
},
  "geometry": {"coordinates":[-122.283997,47.550301],"type":"Point"}
}