{
  "type": "Feature",
  "properties": {
    "addr:full":"1601 5th Ave Seattle WA 98101",
    "addr:housenumber":"1601",
    "addr:postcode":"98101",
    "addr:street":"5Th Ave",
    "iso:country":"US",
    "sg:address":"1601 5th Ave",
    "sg:city":"Seattle",
    "sg:classifiers":[
        {
            "category":"Food & Beverages",
            "subcategory":"Candy",
            "type":"Retail Goods"
        }
    ],
    "sg:phone":"+1 206 623 0454",
    "sg:postcode":"98101",
    "sg:province":"WA",
    "sg:tags":[
        "confectionery",
        "store"
    ],
    "wof:name":"Candytyme",
    "wof:placetype":"venue"
},
  "geometry": {"coordinates":[-122.33699799999999,47.611698],"type":"Point"}
}