{
  "type": "Feature",
  "properties": {
    "addr:full":"11911 NE 1st St Ste 310 Bellevue WA 98005",
    "addr:housenumber":"11911",
    "addr:postcode":"98005",
    "addr:street":"Ne 1St St Ste 310",
    "iso:country":"US",
    "sg:address":"11911 NE 1st St Ste 310",
    "sg:city":"Bellevue",
    "sg:classifiers":[
        {
            "category":"Wholesale",
            "subcategory":"Fruits & Vegetables",
            "type":"Manufacturing & Wholesale Goods"
        }
    ],
    "sg:phone":"+1 425 456 3670",
    "sg:postcode":"98005",
    "sg:province":"WA",
    "sg:tags":[
        "vegetables-wholesale"
    ],
    "sg:website":"http://www.agrimaxintl.com",
    "wof:name":"Agrimax International",
    "wof:placetype":"venue"
},
  "geometry": {"coordinates":[-122.18321899999999,47.610766],"type":"Point"}
}