{
  "type": "Feature",
  "properties": {
    "addr:full":"5425 132nd St NE Marysville WA 98271",
    "addr:housenumber":"5425",
    "addr:postcode":"98271",
    "addr:street":"132Nd St Ne",
    "iso:country":"US",
    "sg:address":"5425 132nd St NE",
    "sg:city":"Marysville",
    "sg:classifiers":[
        {
            "category":"Building & Trades",
            "subcategory":"Electrical",
            "type":"Services"
        }
    ],
    "sg:phone":"+1 360 659 8819",
    "sg:postcode":"98271",
    "sg:province":"WA",
    "sg:tags":[
        "electrician"
    ],
    "sg:website":"http://www.actionelectric.com",
    "wof:name":"Action Electric, Inc",
    "wof:placetype":"venue"
},
  "geometry": {"coordinates":[-122.15759300000001,48.114651],"type":"Point"}
}