{
  "type": "Feature",
  "properties": {
    "addr:full":"103 E 4th Ave Ellensburg WA 98926",
    "addr:housenumber":"103",
    "addr:postcode":"98926",
    "addr:street":"E 4Th Ave",
    "iso:country":"US",
    "sg:address":"103 E 4th Ave",
    "sg:city":"Ellensburg",
    "sg:classifiers":[
        {
            "category":"Wholesale",
            "subcategory":"Construction Materials",
            "type":"Manufacturing & Wholesale Goods"
        }
    ],
    "sg:phone":"+1 509 962 5422",
    "sg:postcode":"98926",
    "sg:province":"WA",
    "sg:tags":[
        "lumber"
    ],
    "wof:name":"Matheus Lumber Company",
    "wof:placetype":"venue"
},
  "geometry": {"coordinates":[-120.54591499999999,46.9956],"type":"Point"}
}