{
  "type": "Feature",
  "properties": {
    "addr:full":"798 Ocean Shores Blvd NW Ocean Shores WA 98569",
    "addr:housenumber":"798",
    "addr:postcode":"98569",
    "addr:street":"Ocean Shores Blvd Nw",
    "iso:country":"US",
    "sg:address":"798 Ocean Shores Blvd NW",
    "sg:city":"Ocean Shores",
    "sg:classifiers":[
        {
            "category":"Shopping",
            "subcategory":"Hobbies, Toys, & Games",
            "type":"Retail Goods"
        }
    ],
    "sg:phone":"+1 360 289 9304",
    "sg:postcode":"98569",
    "sg:province":"WA",
    "sg:tags":[
        "supply"
    ],
    "wof:name":"Mac's Fun & Games",
    "wof:placetype":"venue"
},
  "geometry": {"coordinates":[-124.166158,47.010574],"type":"Point"}
}