{
  "type": "Feature",
  "properties": {
    "addr:full":"9751 NE 126th Pl Kirkland WA 98034",
    "addr:housenumber":"9751",
    "addr:postcode":"98034",
    "addr:street":"Ne 126Th Pl",
    "iso:country":"US",
    "sg:address":"9751 NE 126th Pl",
    "sg:city":"Kirkland",
    "sg:classifiers":[
        {
            "category":"Building & Trades",
            "subcategory":"Locksmith",
            "type":"Services"
        }
    ],
    "sg:phone":"+1 206 577 5613",
    "sg:postcode":"98034",
    "sg:province":"WA",
    "sg:tags":[
        "key"
    ],
    "wof:name":"Citywide Locksmith",
    "wof:placetype":"venue"
},
  "geometry": {"coordinates":[-122.21181,47.713372],"type":"Point"}
}