{
  "type": "Feature",
  "properties": {
    "addr:full":"1620 Chestnut St Clarkston WA 99403",
    "addr:housenumber":"1620",
    "addr:postcode":"99403",
    "addr:street":"Chestnut St",
    "iso:country":"US",
    "sg:address":"1620 Chestnut St",
    "sg:city":"Clarkston",
    "sg:classifiers":[
        {
            "category":"Real Estate",
            "subcategory":"Real Estate Operator",
            "type":"Services"
        }
    ],
    "sg:phone":"+1 509 751 1100",
    "sg:postcode":"99403",
    "sg:province":"WA",
    "sg:tags":[
        "apartment"
    ],
    "wof:name":"Five Star Properties",
    "wof:placetype":"venue"
},
  "geometry": {"coordinates":[-117.07646099999999,46.412072],"type":"Point"}
}