{
  "type": "Feature",
  "properties": {
    "addr:full":"22322 62nd Ave E Spanaway WA 98387",
    "addr:housenumber":"22322",
    "addr:postcode":"98387",
    "addr:street":"62Nd Ave E",
    "iso:country":"US",
    "sg:address":"22322 62nd Ave E",
    "sg:city":"Spanaway",
    "sg:classifiers":[
        {
            "category":"Wholesale",
            "subcategory":"Machinery & Supplies",
            "type":"Manufacturing & Wholesale Goods"
        }
    ],
    "sg:phone":"+1 253 847 4179",
    "sg:postcode":"98387",
    "sg:province":"WA",
    "sg:tags":[
        "equipment",
        "baker"
    ],
    "wof:name":"Certified Foodservice Equip",
    "wof:placetype":"venue"
},
  "geometry": {"coordinates":[-122.347877,47.058966],"type":"Point"}
}