{
  "type": "Feature",
  "properties": {
    "addr:full":"8124 Birch Bay Dr Blaine WA 98230",
    "addr:housenumber":"8124",
    "addr:postcode":"98230",
    "addr:street":"Birch Bay Dr",
    "iso:country":"US",
    "sg:address":"8124 Birch Bay Dr",
    "sg:city":"Blaine",
    "sg:classifiers":[
        {
            "category":"Restaurant",
            "type":"Food & Drink"
        }
    ],
    "sg:phone":"+1 360 371 5910",
    "sg:postcode":"98230",
    "sg:province":"WA",
    "sg:tags":[
        "eating"
    ],
    "wof:name":"Thai Steak House",
    "wof:placetype":"venue"
},
  "geometry": {"coordinates":[-122.75419599999999,48.938072],"type":"Point"}
}