{
  "type": "Feature",
  "properties": {
    "addr:full":"1213 NE 127th St Seattle WA 98125",
    "addr:housenumber":"1213",
    "addr:postcode":"98125",
    "addr:street":"Ne 127Th St",
    "iso:country":"US",
    "sg:address":"1213 NE 127th St",
    "sg:city":"Seattle",
    "sg:classifiers":[
        {
            "category":"Professional",
            "type":"Services"
        }
    ],
    "sg:phone":"+1 206 363 7754",
    "sg:postcode":"98125",
    "sg:province":"WA",
    "wof:name":"Yvonne M Schwalier",
    "wof:placetype":"venue"
},
  "geometry": {"coordinates":[-122.314149,47.721156],"type":"Point"}
}