{
  "type": "Feature",
  "properties": {
    "addr:full":"6549 6th Ave NW Seattle WA 98117",
    "addr:housenumber":"6549",
    "addr:postcode":"98117",
    "addr:street":"6Th Ave Nw",
    "iso:country":"US",
    "sg:address":"6549 6th Ave NW",
    "sg:city":"Seattle",
    "sg:classifiers":[
        {
            "category":"Professional",
            "subcategory":"Computer Services",
            "type":"Services"
        }
    ],
    "sg:phone":"+1 206 782 4035",
    "sg:postcode":"98117",
    "sg:province":"WA",
    "sg:tags":[
        "repair"
    ],
    "sg:website":"www.altonworks.com",
    "wof:name":"Alton Works",
    "wof:placetype":"venue"
},
  "geometry": {"coordinates":[-122.363675,47.677454],"type":"Point"}
}