{
  "type": "Feature",
  "properties": {
    "addr:full":"103 Palouse St Wenatchee WA 98801",
    "addr:housenumber":"103",
    "addr:postcode":"98801",
    "addr:street":"Palouse St",
    "iso:country":"US",
    "sg:address":"103 Palouse St",
    "sg:city":"Wenatchee",
    "sg:classifiers":[
        {
            "category":"Real Estate",
            "subcategory":"Architect",
            "type":"Services"
        }
    ],
    "sg:phone":"+1 509 663 6679",
    "sg:postcode":"98801",
    "sg:province":"WA",
    "wof:name":"CBJ Architects",
    "wof:placetype":"venue"
},
  "geometry": {"coordinates":[-120.31259900000001,47.424163],"type":"Point"}
}