{
  "type": "Feature",
  "properties": {
    "addr:full":"31 N Cowiche Rd Cowiche WA 98923",
    "addr:housenumber":"31",
    "addr:postcode":"98923",
    "addr:street":"N Cowiche Rd",
    "iso:country":"US",
    "sg:address":"31 N Cowiche Rd",
    "sg:city":"Cowiche",
    "sg:classifiers":[
        {
            "category":"Government",
            "subcategory":"Fire Station",
            "type":"Public Place"
        }
    ],
    "sg:phone":"+1 509 678 4563",
    "sg:postcode":"98923",
    "sg:province":"WA",
    "sg:tags":[
        "department"
    ],
    "wof:name":"Cowiche Fire Dept",
    "wof:placetype":"venue"
},
  "geometry": {"coordinates":[-120.710233,46.675503],"type":"Point"}
}