{
  "type": "Feature",
  "properties": {
    "iso:country":"US",
    "sg:address":"271 Snowberry Ln",
    "sg:city":"Washougal",
    "sg:classifiers":[
        {
            "category":"Building & Trades",
            "subcategory":"Construction",
            "type":"Services"
        }
    ],
    "sg:phone":"+1 360 837 3471",
    "sg:postcode":"98671",
    "sg:province":"WA",
    "sg:tags":[
        "excavation",
        "contractor"
    ],
    "wof:name":"Archer Mt Construction Inc",
    "wof:placetype":"venue"
},
  "geometry": {"coordinates":[-122.118629,45.600161],"type":"Point"}
}