{
  "type": "Feature",
  "properties": {
    "addr:full":"16990 Sargent Ln Burlington WA 98233",
    "addr:housenumber":"16990",
    "addr:postcode":"98233",
    "addr:street":"Sargent Ln",
    "iso:country":"US",
    "sg:address":"16990 Sargent Ln",
    "sg:city":"Burlington",
    "sg:classifiers":[
        {
            "category":"Autos & Motor Vehicles",
            "subcategory":"Automobile Sales",
            "type":"Retail Goods"
        }
    ],
    "sg:phone":"+1 360 757 1863",
    "sg:postcode":"98233",
    "sg:province":"WA",
    "sg:tags":[
        "used"
    ],
    "wof:name":"Port Angeles Auto",
    "wof:placetype":"venue"
},
  "geometry": {"coordinates":[-122.37927500000001,48.46721],"type":"Point"}
}