{
  "type": "Feature",
  "properties": {
    "addr:full":"15709 S Cheney Spokane Rd Cheney WA 99004",
    "addr:housenumber":"15709",
    "addr:postcode":"99004",
    "addr:street":"S Cheney Spokane Rd",
    "iso:country":"US",
    "sg:address":"15709 S Cheney Spokane Rd",
    "sg:city":"Cheney",
    "sg:classifiers":[
        {
            "category":"Manufacturing",
            "subcategory":"Apparel",
            "type":"Manufacturing & Wholesale Goods"
        }
    ],
    "sg:phone":"+1 509 235 5742",
    "sg:postcode":"99004",
    "sg:province":"WA",
    "sg:tags":[
        "clothing",
        "mfg"
    ],
    "wof:name":"Blue Balls Clothing Company",
    "wof:placetype":"venue"
},
  "geometry": {"coordinates":[-117.538528,47.510048],"type":"Point"}
}