{
  "type": "Feature",
  "properties": {
    "addr:full":"24222 92nd Ave W Edmonds WA 98020",
    "addr:housenumber":"24222",
    "addr:postcode":"98020",
    "addr:street":"92Nd Ave W",
    "iso:country":"US",
    "sg:address":"24222 92nd Ave W",
    "sg:city":"Edmonds",
    "sg:classifiers":[
        {
            "category":"Wholesale",
            "subcategory":"Machinery & Supplies",
            "type":"Manufacturing & Wholesale Goods"
        }
    ],
    "sg:phone":"+1 206 542 1966",
    "sg:postcode":"98020",
    "sg:province":"WA",
    "sg:tags":[
        "instrument",
        "surveying"
    ],
    "wof:name":"Electronic Data Solutions",
    "wof:placetype":"venue"
},
  "geometry": {"coordinates":[-122.35593,47.779422],"type":"Point"}
}