{
  "type": "Feature",
  "properties": {
    "addr:full":"720 132nd St SW Ste 207 Everett WA 98204",
    "addr:housenumber":"720",
    "addr:postcode":"98204",
    "addr:street":"132Nd St Sw Ste 207",
    "iso:country":"US",
    "sg:address":"720 132nd St SW Ste 207",
    "sg:city":"Everett",
    "sg:classifiers":[
        {
            "category":"Home & Garden",
            "subcategory":"Home Furnishings",
            "type":"Retail Goods"
        },
        {
            "category":"Building & Trades",
            "subcategory":"Construction",
            "type":"Services"
        },
        {
            "category":"Real Estate",
            "subcategory":"Architect",
            "type":"Services"
        }
    ],
    "sg:phone":"+1 425 745 9701",
    "sg:postcode":"98204",
    "sg:province":"WA",
    "sg:tags":[
        "planning",
        "residential",
        "designer",
        "design",
        "contractor"
    ],
    "wof:name":"Dream Home Design Inc",
    "wof:placetype":"venue"
},
  "geometry": {"coordinates":[-122.243275,47.878689],"type":"Point"}
}