{
  "type": "Feature",
  "properties": {
    "addr:full":"245 N Oak St Colville WA 99114",
    "addr:housenumber":"245",
    "addr:postcode":"99114",
    "addr:street":"N Oak St",
    "iso:country":"US",
    "sg:address":"245 N Oak St",
    "sg:city":"Colville",
    "sg:classifiers":[
        {
            "category":"Health Services",
            "subcategory":"Doctor",
            "type":"Services"
        }
    ],
    "sg:phone":"+1 509 684 5066",
    "sg:postcode":"99114",
    "sg:province":"WA",
    "sg:tags":[
        "dentist"
    ],
    "wof:name":"John H Leng DDS",
    "wof:placetype":"venue"
},
  "geometry": {"coordinates":[-117.90443999999999,48.546079],"type":"Point"}
}