{
  "type": "Feature",
  "properties": {
    "addr:full":"1930 W Riverside Ave Spokane WA 99201",
    "addr:housenumber":"1930",
    "addr:postcode":"99201",
    "addr:street":"W Riverside Ave",
    "iso:country":"US",
    "sg:address":"1930 W Riverside Ave",
    "sg:city":"Spokane",
    "sg:classifiers":[
        {
            "category":"Insurance",
            "subcategory":"Insurance Agent",
            "type":"Services"
        }
    ],
    "sg:phone":"+1 509 747 4670",
    "sg:postcode":"99201",
    "sg:province":"WA",
    "wof:name":"A G States Agency LLC",
    "wof:placetype":"venue"
},
  "geometry": {"coordinates":[-117.441153,47.657258],"type":"Point"}
}