{
  "type": "Feature",
  "properties": {
    "addr:full":"11811 Mukilteo Speedway Mukilteo WA 98275",
    "addr:housenumber":"11811",
    "addr:postcode":"98275",
    "addr:street":"Mukilteo Speedway",
    "iso:country":"US",
    "sg:address":"11811 Mukilteo Speedway",
    "sg:city":"Mukilteo",
    "sg:classifiers":[
        {
            "category":"Retail",
            "subcategory":"Animal Services",
            "type":"Services"
        }
    ],
    "sg:phone":"+1 425 348 8872",
    "sg:postcode":"98275",
    "sg:province":"WA",
    "sg:tags":[
        "pet",
        "grooming",
        "washing"
    ],
    "wof:name":"Blue Ribbon Pet Salon",
    "wof:placetype":"venue"
},
  "geometry": {"coordinates":[-122.287961,47.894869],"type":"Point"}
}