{
  "type": "Feature",
  "properties": {
    "addr:full":"900 SHERIDAN RD SUITE 101 BREMERTON WA 98310",
    "addr:housenumber":"900",
    "addr:postcode":"98310",
    "addr:street":"Sheridan Rd Suite 101",
    "iso:country":"US",
    "sg:address":"900 SHERIDAN RD SUITE 101",
    "sg:city":"BREMERTON",
    "sg:classifiers":[
        {
            "category":"Health Services",
            "subcategory":"Doctor",
            "type":"Services"
        },
        {
            "category":"Health Services",
            "subcategory":"Podiatrist",
            "type":"Services"
        }
    ],
    "sg:phone":"+1 360 377 2233",
    "sg:postcode":"98310",
    "sg:province":"WA",
    "sg:tags":[
        "medicine",
        "physician",
        "orthopedics",
        "surgeons",
        "sport"
    ],
    "sg:website":"http://www.kitsapfootandankle.net/",
    "wof:name":"Kitsap Foot & Ankle Clinic",
    "wof:placetype":"venue"
},
  "geometry": {"coordinates":[-122.634446,47.58838],"type":"Point"}
}