{
  "type": "Feature",
  "properties": {
    "addr:full":"1322 3rd St SE Puyallup WA 98372",
    "addr:housenumber":"1322",
    "addr:postcode":"98372",
    "addr:street":"3Rd St Se",
    "iso:country":"US",
    "sg:address":"1322 3rd St SE",
    "sg:city":"Puyallup",
    "sg:classifiers":[
        {
            "category":"Health Services",
            "subcategory":"Doctor",
            "type":"Services"
        }
    ],
    "sg:phone":"+1 253 841 4296",
    "sg:postcode":"98372",
    "sg:province":"WA",
    "sg:tags":[
        "physician"
    ],
    "wof:name":"Rainier Oncology Prof Svcs",
    "wof:placetype":"venue"
},
  "geometry": {"coordinates":[-122.2912,47.178913],"type":"Point"}
}