{
  "type": "Feature",
  "properties": {
    "addr:full":"3005 S Gum St Kennewick WA 99337",
    "addr:housenumber":"3005",
    "addr:postcode":"99337",
    "addr:street":"S Gum St",
    "iso:country":"US",
    "sg:address":"3005 S Gum St",
    "sg:city":"Kennewick",
    "sg:classifiers":[
        {
            "category":"Building & Trades",
            "subcategory":"Construction",
            "type":"Services"
        }
    ],
    "sg:phone":"+1 509 586 3329",
    "sg:postcode":"99337",
    "sg:province":"WA",
    "sg:tags":[
        "contractor"
    ],
    "wof:name":"Parker Excavating",
    "wof:placetype":"venue"
},
  "geometry": {"coordinates":[-119.10700199999999,46.179901],"type":"Point"}
}