{
  "type": "Feature",
  "properties": {
    "addr:full":"1230 Lewis River Rd Woodland WA 98674",
    "addr:housenumber":"1230",
    "addr:postcode":"98674",
    "addr:street":"Lewis River Rd",
    "iso:country":"US",
    "sg:address":"1230 Lewis River Rd",
    "sg:city":"Woodland",
    "sg:classifiers":[
        {
            "category":"Food & Beverages",
            "subcategory":"Liquor & Beverages",
            "type":"Retail Goods"
        }
    ],
    "sg:phone":"+1 360 225 8717",
    "sg:postcode":"98674",
    "sg:province":"WA",
    "wof:name":"Liquor Store",
    "wof:placetype":"venue"
},
  "geometry": {"coordinates":[-122.740402,45.910207],"type":"Point"}
}