{
  "type": "Feature",
  "properties": {
    "addr:full":"2011 152nd Ave NE Redmond WA 98052",
    "addr:housenumber":"2011",
    "addr:postcode":"98052",
    "addr:street":"152Nd Ave Ne",
    "iso:country":"US",
    "sg:address":"2011 152nd Ave NE",
    "sg:city":"Redmond",
    "sg:classifiers":[
        {
            "category":"Place Of Worship",
            "subcategory":"Church",
            "type":"Public Place"
        },
        {
            "category":"Place Of Worship",
            "type":"Public Place"
        }
    ],
    "sg:phone":"+1 425 747 4456",
    "sg:postcode":"98052",
    "sg:province":"WA",
    "sg:tags":[
        "churches-interdenominational",
        "churches-various",
        "denomination"
    ],
    "wof:name":"Full Gospel Christian Center",
    "wof:placetype":"venue"
},
  "geometry": {"coordinates":[-122.137742,47.628424],"type":"Point"}
}