{
  "type": "Feature",
  "properties": {
    "iso:country":"US",
    "sg:address":"2712 SW 115th St",
    "sg:city":"Seattle",
    "sg:classifiers":[
        {
            "category":"Professional",
            "subcategory":"Management & Consulting",
            "type":"Services"
        }
    ],
    "sg:phone":"+1 206 244 2445",
    "sg:postcode":"98146",
    "sg:province":"WA",
    "sg:tags":[
        "business"
    ],
    "wof:name":"M CC and Associates",
    "wof:placetype":"venue"
},
  "geometry": {"coordinates":[-122.36772000000001,47.500463],"type":"Point"}
}