{
  "type": "Feature",
  "properties": {
    "addr:full":"1445 NW 56th St Seattle WA 98107",
    "addr:housenumber":"1445",
    "addr:postcode":"98107",
    "addr:street":"Nw 56Th St",
    "iso:country":"US",
    "sg:address":"1445 NW 56th St",
    "sg:city":"Seattle",
    "sg:classifiers":[
        {
            "category":"Professional",
            "subcategory":"Management & Consulting",
            "type":"Services"
        }
    ],
    "sg:phone":"+1 206 281 7145",
    "sg:postcode":"98107",
    "sg:province":"WA",
    "sg:tags":[
        "vessel",
        "organizing",
        "business",
        "services-household",
        "fishing"
    ],
    "wof:name":"Autumn Dawn Partnership",
    "wof:placetype":"venue"
},
  "geometry": {"coordinates":[-122.374813,47.669465],"type":"Point"}
}