{
  "type": "Feature",
  "properties": {
    "addr:full":"1913 W 9th Ave Kennewick WA 99336",
    "addr:housenumber":"1913",
    "addr:postcode":"99336",
    "addr:street":"W 9Th Ave",
    "iso:country":"US",
    "sg:address":"1913 W 9th Ave",
    "sg:city":"Kennewick",
    "sg:phone":"+1 509 585 9893",
    "sg:postcode":"99336",
    "sg:province":"WA",
    "wof:name":"Dependable Plumbing & Water Conditioning Inc",
    "wof:placetype":"venue"
},
  "geometry": {"coordinates":[-119.145318,46.200039],"type":"Point"}
}