{
  "type": "Feature",
  "properties": {
    "addr:full":"3509 109th St SW Everett WA 98204",
    "addr:housenumber":"3509",
    "addr:postcode":"98204",
    "addr:street":"109Th St Sw",
    "iso:country":"US",
    "sg:address":"3509 109th St SW",
    "sg:city":"Everett",
    "sg:classifiers":[
        {
            "category":"Government",
            "subcategory":"Office",
            "type":"Public Place"
        }
    ],
    "sg:phone":"+1 425 423 7635",
    "sg:postcode":"98204",
    "sg:province":"WA",
    "wof:name":"Department Emergency Managment",
    "wof:placetype":"venue"
},
  "geometry": {"coordinates":[-122.278868,47.899133],"type":"Point"}
}