{
  "type": "Feature",
  "properties": {
    "addr:full":"23 E Main St Walla Walla WA 99362",
    "addr:housenumber":"23",
    "addr:postcode":"99362",
    "addr:street":"E Main St",
    "iso:country":"US",
    "sg:address":"23 E Main St",
    "sg:city":"Walla Walla",
    "sg:classifiers":[
        {
            "category":"Shopping",
            "subcategory":"Florist",
            "type":"Retail Goods"
        }
    ],
    "sg:phone":"+1 509 525 8173",
    "sg:postcode":"99362",
    "sg:province":"WA",
    "wof:name":"Ocons Flowers",
    "wof:placetype":"venue"
},
  "geometry": {"coordinates":[-118.338583,46.067069],"type":"Point"}
}