{
  "type": "Feature",
  "properties": {
    "addr:full":"1075 Bellevue Way NE Ste B2 Bellevue WA 98004",
    "addr:housenumber":"1075",
    "addr:postcode":"98004",
    "addr:street":"Bellevue Way Ne Ste B2",
    "iso:country":"US",
    "sg:address":"1075 Bellevue Way NE Ste B2",
    "sg:city":"Bellevue",
    "sg:classifiers":[
        {
            "category":"Personal",
            "subcategory":"Beauty Salon",
            "type":"Services"
        },
        {
            "category":"Personal",
            "subcategory":"Skin Care",
            "type":"Services"
        },
        {
            "category":"Personal",
            "subcategory":"Nail Salon",
            "type":"Services"
        }
    ],
    "sg:phone":"+1 425 455 9135",
    "sg:postcode":"98004",
    "sg:province":"WA",
    "sg:tags":[
        "hair"
    ],
    "sg:website":"www.jbusalon.com/",
    "wof:name":"Just Between Us",
    "wof:placetype":"venue"
},
  "geometry": {"coordinates":[-122.201712,47.620118],"type":"Point"}
}