{
  "type": "Feature",
  "properties": {
    "addr:full":"7210 Roosevelt Way NE Seattle WA 98115",
    "addr:housenumber":"7210",
    "addr:postcode":"98115",
    "addr:street":"Roosevelt Way Ne",
    "iso:country":"US",
    "sg:address":"7210 Roosevelt Way NE",
    "sg:city":"Seattle",
    "sg:classifiers":[
        {
            "category":"Health Services",
            "subcategory":"Podiatrist",
            "type":"Services"
        }
    ],
    "sg:phone":"+1 206 386 9668",
    "sg:postcode":"98115",
    "sg:province":"WA",
    "sg:tags":[
        "physician",
        "surgeons"
    ],
    "wof:name":"Lo Anthony Dpm",
    "wof:placetype":"venue"
},
  "geometry": {"coordinates":[-122.31748399999999,47.680941],"type":"Point"}
}