{
  "type": "Feature",
  "properties": {
    "addr:full":"91 Fraser Dr Pasco WA 99301",
    "addr:housenumber":"91",
    "addr:postcode":"99301",
    "addr:street":"Fraser Dr",
    "iso:country":"US",
    "sg:address":"91 Fraser Dr",
    "sg:city":"Pasco",
    "sg:classifiers":[
        {
            "category":"Building & Trades",
            "subcategory":"Landscaping Services",
            "type":"Services"
        }
    ],
    "sg:phone":"+1 509 546 2449",
    "sg:postcode":"99301",
    "sg:province":"WA",
    "sg:tags":[
        "landscape",
        "contractor"
    ],
    "wof:name":"Bagley Landscape Construction",
    "wof:placetype":"venue"
},
  "geometry": {"coordinates":[-119.241021,46.330626],"type":"Point"}
}