{
  "type": "Feature",
  "properties": {
    "iso:country":"US",
    "sg:address":"2801 W Nob Hill Blvd",
    "sg:city":"Yakima",
    "sg:classifiers":[
        {
            "category":"Shopping",
            "subcategory":"Bicycles & Sporting Goods",
            "type":"Retail Goods"
        }
    ],
    "sg:phone":"+1 509 453 6040",
    "sg:postcode":"98902",
    "sg:province":"WA",
    "sg:website":"www.big5sportinggoods.com",
    "wof:name":"Big 5 Sporting Goods 169",
    "wof:placetype":"venue"
},
  "geometry": {"coordinates":[-120.546835,46.585435],"type":"Point"}
}