{
  "type": "Feature",
  "properties": {
    "addr:full":"15526 Hwy 99 Lynnwood WA 98087",
    "addr:housenumber":"15526",
    "addr:postcode":"98087",
    "addr:street":"Hwy 99",
    "iso:country":"US",
    "sg:address":"15526 Hwy 99",
    "sg:city":"Lynnwood",
    "sg:classifiers":[
        {
            "category":"Shopping",
            "subcategory":"Bicycles & Sporting Goods",
            "type":"Retail Goods"
        }
    ],
    "sg:phone":"+1 425 743 9505",
    "sg:postcode":"98087",
    "sg:province":"WA",
    "sg:tags":[
        "tackle",
        "fishing"
    ],
    "wof:name":"Ted's Sport Ctr",
    "wof:placetype":"venue"
},
  "geometry": {"coordinates":[-122.28793,47.858052],"type":"Point"}
}