{
  "type": "Feature",
  "properties": {
    "addr:full":"17530 NE Union Hill Rd Redmond WA 98052",
    "addr:housenumber":"17530",
    "addr:postcode":"98052",
    "addr:street":"Ne Union Hill Rd",
    "iso:country":"US",
    "sg:address":"17530 NE Union Hill Rd",
    "sg:city":"Redmond",
    "sg:classifiers":[
        {
            "category":"Personal",
            "type":"Services"
        },
        {
            "category":"Health Services",
            "subcategory":"Health Practitioner",
            "type":"Services"
        }
    ],
    "sg:phone":"+1 425 558 4314",
    "sg:postcode":"98052",
    "sg:province":"WA",
    "sg:tags":[
        "therapist",
        "massage"
    ],
    "wof:name":"Inga Massage Therapist Lovic",
    "wof:placetype":"venue"
},
  "geometry": {"coordinates":[-122.106685,47.674932],"type":"Point"}
}