{
  "type": "Feature",
  "properties": {
    "addr:full":"1710 N Hamilton St Spokane WA 99207",
    "addr:housenumber":"1710",
    "addr:postcode":"99207",
    "addr:street":"N Hamilton St",
    "iso:country":"US",
    "sg:address":"1710 N Hamilton St",
    "sg:city":"Spokane",
    "sg:classifiers":[
        {
            "category":"Restaurant",
            "type":"Food & Drink"
        }
    ],
    "sg:menulink":"http://www.allmenus.com/wa/spokane/145326-subway/menu/",
    "sg:phone":"+1 509 484 6647",
    "sg:postcode":"99207",
    "sg:province":"WA",
    "sg:tags":[
        "american",
        "sandwich"
    ],
    "wof:name":"Subway",
    "wof:placetype":"venue"
},
  "geometry": {"coordinates":[-117.39633600000001,47.673065],"type":"Point"}
}