{
  "type": "Feature",
  "properties": {
    "addr:full":"2401 Westhaven Dr Westport WA 98595",
    "addr:housenumber":"2401",
    "addr:postcode":"98595",
    "addr:street":"Westhaven Dr",
    "iso:country":"US",
    "sg:address":"2401 Westhaven Dr",
    "sg:city":"Westport",
    "sg:classifiers":[
        {
            "category":"Shopping",
            "subcategory":"Gifts & Souvenirs",
            "type":"Retail Goods"
        }
    ],
    "sg:phone":"+1 360 268 1412",
    "sg:postcode":"98595",
    "sg:province":"WA",
    "sg:tags":[
        "shop"
    ],
    "wof:name":"Castaways Cafe & Gifts",
    "wof:placetype":"venue"
},
  "geometry": {"coordinates":[-124.11350299999999,46.909287],"type":"Point"}
}