{
  "type": "Feature",
  "properties": {
    "iso:country":"US",
    "sg:address":"751 N Main St",
    "sg:city":"Colville",
    "sg:classifiers":[
        {
            "category":"Professional",
            "subcategory":"Management & Consulting",
            "type":"Services"
        }
    ],
    "sg:phone":"+1 509 684 3147",
    "sg:postcode":"99114",
    "sg:province":"WA",
    "wof:name":"J Copeland Marketing",
    "wof:placetype":"venue"
},
  "geometry": {"coordinates":[-117.905996,48.551023],"type":"Point"}
}