{
  "type": "Feature",
  "properties": {
    "addr:full":"2510 Sandy Dr Centralia WA 98531",
    "addr:housenumber":"2510",
    "addr:postcode":"98531",
    "addr:street":"Sandy Dr",
    "iso:country":"US",
    "sg:address":"2510 Sandy Dr",
    "sg:city":"Centralia",
    "sg:classifiers":[
        {
            "category":"Building & Trades",
            "subcategory":"Construction",
            "type":"Services"
        }
    ],
    "sg:phone":"+1 360 736 5873",
    "sg:postcode":"98531",
    "sg:province":"WA",
    "sg:tags":[
        "house"
    ],
    "wof:name":"Creative Builders Llc",
    "wof:placetype":"venue"
},
  "geometry": {"coordinates":[-122.98513800000001,46.726933],"type":"Point"}
}