{
  "type": "Feature",
  "properties": {
    "addr:full":"1351 Hudson St Longview WA 98632",
    "addr:housenumber":"1351",
    "addr:postcode":"98632",
    "addr:street":"Hudson St",
    "iso:country":"US",
    "sg:address":"1351 Hudson St",
    "sg:city":"Longview",
    "sg:classifiers":[
        {
            "category":"Government",
            "subcategory":"Police Station",
            "type":"Public Place"
        }
    ],
    "sg:phone":"+1 360 577 3157",
    "sg:postcode":"98632",
    "sg:province":"WA",
    "sg:tags":[
        "department"
    ],
    "sg:website":"www.ci.longview.wa.us",
    "wof:name":"Longview Police Dept",
    "wof:placetype":"venue"
},
  "geometry": {"coordinates":[-122.935181,46.137075],"type":"Point"}
}