{
  "type": "Feature",
  "properties": {
    "addr:full":"12315 NE 152nd Ave Brush Prairie WA 98606",
    "addr:housenumber":"12315",
    "addr:postcode":"98606",
    "addr:street":"Ne 152Nd Ave",
    "iso:country":"US",
    "sg:address":"12315 NE 152nd Ave",
    "sg:city":"Brush Prairie",
    "sg:classifiers":[
        {
            "category":"Building & Trades",
            "subcategory":"Plumbing",
            "type":"Services"
        }
    ],
    "sg:phone":"+1 360 256 4122",
    "sg:postcode":"98606",
    "sg:province":"WA",
    "sg:tags":[
        "heating",
        "contractor"
    ],
    "wof:name":"Air-America Inc",
    "wof:placetype":"venue"
},
  "geometry": {"coordinates":[-122.516268,45.709651],"type":"Point"}
}