{
  "type": "Feature",
  "properties": {
    "addr:full":"2614 NE 25th St Renton WA 98056",
    "addr:housenumber":"2614",
    "addr:postcode":"98056",
    "addr:street":"Ne 25Th St",
    "iso:country":"US",
    "sg:address":"2614 NE 25th St",
    "sg:city":"Renton",
    "sg:classifiers":[
        {
            "category":"Shopping",
            "subcategory":"Clothing, Apparel, & Fashions",
            "type":"Retail Goods"
        }
    ],
    "sg:phone":"+1 206 529 8104",
    "sg:postcode":"98056",
    "sg:province":"WA",
    "sg:tags":[
        "men's",
        "women's",
        "apparel",
        "jean",
        "clothing",
        "store"
    ],
    "sg:website":"http://www.luckybrandjeans.com",
    "wof:name":"Lucky Brand Jeans",
    "wof:placetype":"venue"
},
  "geometry": {"coordinates":[-122.18392799999999,47.514137],"type":"Point"}
}