{
  "type": "Feature",
  "properties": {
    "addr:full":"19325 Filbert Rd Bothell WA 98012",
    "addr:housenumber":"19325",
    "addr:postcode":"98012",
    "addr:street":"Filbert Rd",
    "iso:country":"US",
    "sg:address":"19325 Filbert Rd",
    "sg:city":"Bothell",
    "sg:classifiers":[
        {
            "category":"Farming",
            "subcategory":"Nursery",
            "type":"Manufacturing & Wholesale Goods"
        }
    ],
    "sg:phone":"+1 425 776 6972",
    "sg:postcode":"98012",
    "sg:province":"WA",
    "sg:tags":[
        "ornamental"
    ],
    "wof:name":"Lynnwood Nursery",
    "wof:placetype":"venue"
},
  "geometry": {"coordinates":[-122.236799,47.823527],"type":"Point"}
}