{
  "type": "Feature",
  "properties": {
    "addr:full":"4220 S Crestline St Spokane WA 99203",
    "addr:housenumber":"4220",
    "addr:postcode":"99203",
    "addr:street":"S Crestline St",
    "iso:country":"US",
    "sg:address":"4220 S Crestline St",
    "sg:city":"Spokane",
    "sg:classifiers":[
        {
            "category":"Building & Trades",
            "subcategory":"Construction",
            "type":"Services"
        }
    ],
    "sg:phone":"+1 509 448 3160",
    "sg:postcode":"99203",
    "sg:province":"WA",
    "sg:tags":[
        "contractor"
    ],
    "wof:name":"Doering Construction",
    "wof:placetype":"venue"
},
  "geometry": {"coordinates":[-117.37928100000001,47.613785],"type":"Point"}
}