{
  "type": "Feature",
  "properties": {
    "addr:full":"500 Pacific Ave Bremerton WA 98337",
    "addr:housenumber":"500",
    "addr:postcode":"98337",
    "addr:street":"Pacific Ave",
    "iso:country":"US",
    "sg:address":"500 Pacific Ave",
    "sg:city":"Bremerton",
    "sg:classifiers":[
        {
            "category":"Insurance",
            "subcategory":"Insurance Agent",
            "type":"Services"
        }
    ],
    "sg:phone":"+1 360 479 0200",
    "sg:postcode":"98337",
    "sg:province":"WA",
    "wof:name":"Ward North America Holding",
    "wof:placetype":"venue"
},
  "geometry": {"coordinates":[-122.626913,47.567298],"type":"Point"}
}