{
  "type": "Feature",
  "properties": {
    "addr:full":"29018 State Rte 410 Buckley WA 98321",
    "addr:housenumber":"29018",
    "addr:postcode":"98321",
    "addr:street":"State Rte 410",
    "iso:country":"US",
    "sg:address":"29018 State Rte 410",
    "sg:city":"Buckley",
    "sg:classifiers":[
        {
            "category":"Shopping",
            "subcategory":"Used Merchandise",
            "type":"Retail Goods"
        }
    ],
    "sg:phone":"+1 360 829 2234",
    "sg:postcode":"98321",
    "sg:province":"WA",
    "wof:name":"Readers Delight",
    "wof:placetype":"venue"
},
  "geometry": {"coordinates":[-122.03636299999999,47.157745],"type":"Point"}
}