{
  "type": "Feature",
  "properties": {
    "addr:full":"172 143rd Pl NE Bellevue WA 98007",
    "addr:housenumber":"172",
    "addr:postcode":"98007",
    "addr:street":"143Rd Pl Ne",
    "iso:country":"US",
    "sg:address":"172 143rd Pl NE",
    "sg:city":"Bellevue",
    "sg:classifiers":[
        {
            "category":"Personal",
            "subcategory":"Adult",
            "type":"Services"
        }
    ],
    "sg:phone":"+1 425 747 0976",
    "sg:postcode":"98007",
    "sg:province":"WA",
    "wof:name":"Richard Bales",
    "wof:placetype":"venue"
},
  "geometry": {"coordinates":[-122.148872,47.610956],"type":"Point"}
}