{
  "type": "Feature",
  "properties": {
    "iso:country":"US",
    "sg:address":"15208 NE 110th Pl",
    "sg:city":"Redmond",
    "sg:classifiers":[
        {
            "category":"Wholesale",
            "subcategory":"Machinery & Supplies",
            "type":"Manufacturing & Wholesale Goods"
        }
    ],
    "sg:phone":"+1 425 867 2400",
    "sg:postcode":"98052",
    "sg:province":"WA",
    "sg:tags":[
        "equipment",
        "industrial"
    ],
    "wof:name":"Henderson Enterprises Inc",
    "wof:placetype":"venue"
},
  "geometry": {"coordinates":[-122.135666,47.699197],"type":"Point"}
}