{
  "type": "Feature",
  "properties": {
    "addr:full":"13507 E Meridian Ave Puyallup WA 98373",
    "addr:housenumber":"13507",
    "addr:postcode":"98373",
    "addr:street":"E Meridian Ave",
    "iso:country":"US",
    "sg:address":"13507 E Meridian Ave",
    "sg:city":"Puyallup",
    "sg:classifiers":[
        {
            "category":"Retail",
            "subcategory":"Laundry & Dry Cleaning",
            "type":"Services"
        }
    ],
    "sg:phone":"+1 253 845 0027",
    "sg:postcode":"98373",
    "sg:province":"WA",
    "sg:tags":[
        "garment",
        "agent"
    ],
    "wof:name":"Miong Sea",
    "wof:placetype":"venue"
},
  "geometry": {"coordinates":[-122.292951,47.135759],"type":"Point"}
}