{
  "type": "Feature",
  "properties": {
    "addr:full":"4545 329th Pl SE Fall City WA 98024",
    "addr:housenumber":"4545",
    "addr:postcode":"98024",
    "addr:street":"329Th Pl Se",
    "iso:country":"US",
    "sg:address":"4545 329th Pl SE",
    "sg:city":"Fall City",
    "sg:classifiers":[
        {
            "category":"Professional",
            "subcategory":"Engineering",
            "type":"Services"
        }
    ],
    "sg:phone":"+1 425 222 4116",
    "sg:postcode":"98024",
    "sg:province":"WA",
    "wof:name":"Haff Engineering & MGT Svcs",
    "wof:placetype":"venue"
},
  "geometry": {"coordinates":[-121.90151,47.562587],"type":"Point"}
}