{
  "type": "Feature",
  "properties": {
    "addr:full":"29322 52nd Ave S Auburn WA 98001",
    "addr:housenumber":"29322",
    "addr:postcode":"98001",
    "addr:street":"52Nd Ave S",
    "iso:country":"US",
    "sg:address":"29322 52nd Ave S",
    "sg:city":"Auburn",
    "sg:classifiers":[
        {
            "category":"Building & Trades",
            "subcategory":"Construction",
            "type":"Services"
        }
    ],
    "sg:phone":"+1 253 839 0920",
    "sg:postcode":"98001",
    "sg:province":"WA",
    "sg:tags":[
        "home",
        "nonresidential",
        "contractor"
    ],
    "wof:name":"Ross O Brody Construction",
    "wof:placetype":"venue"
},
  "geometry": {"coordinates":[-122.269361,47.339882],"type":"Point"}
}