{
  "type": "Feature",
  "properties": {
    "addr:full":"5309 Blackhawk Ct SW Lakewood WA 98499",
    "addr:housenumber":"5309",
    "addr:postcode":"98499",
    "addr:street":"Blackhawk Ct Sw",
    "iso:country":"US",
    "sg:address":"5309 Blackhawk Ct SW",
    "sg:city":"Lakewood",
    "sg:classifiers":[
        {
            "category":"Food & Beverages",
            "subcategory":"Groceries & Convenience Stores",
            "type":"Retail Goods"
        }
    ],
    "sg:phone":"+1 253 588 2680",
    "sg:postcode":"98499",
    "sg:province":"WA",
    "wof:name":"Big City Bagels & Deli",
    "wof:placetype":"venue"
},
  "geometry": {"coordinates":[-122.509002,47.151337],"type":"Point"}
}