{
  "type": "Feature",
  "properties": {
    "addr:full":"10500 NE 8th St Bellevue WA 98004",
    "addr:housenumber":"10500",
    "addr:postcode":"98004",
    "addr:street":"Ne 8Th St",
    "iso:country":"US",
    "sg:address":"10500 NE 8th St",
    "sg:city":"Bellevue",
    "sg:classifiers":[
        {
            "category":"Building & Trades",
            "subcategory":"Construction",
            "type":"Services"
        }
    ],
    "sg:phone":"+1 425 233 8079",
    "sg:postcode":"98004",
    "sg:province":"WA",
    "sg:tags":[
        "interior",
        "design"
    ],
    "sg:website":"www.noonmeme.com",
    "wof:name":"Noon Meme Designs",
    "wof:placetype":"venue"
},
  "geometry": {"coordinates":[-122.20038099999999,47.617484],"type":"Point"}
}