{
  "type": "Feature",
  "properties": {
    "addr:full":"15015 Main St Bellevue WA 98007",
    "addr:housenumber":"15015",
    "addr:postcode":"98007",
    "addr:street":"Main St",
    "iso:country":"US",
    "sg:address":"15015 Main St",
    "sg:city":"Bellevue",
    "sg:classifiers":[
        {
            "category":"Sports & Exercise",
            "subcategory":"Gym",
            "type":"Entertainment"
        }
    ],
    "sg:phone":"+1 425 644 1042",
    "sg:postcode":"98007",
    "sg:province":"WA",
    "sg:tags":[
        "club",
        "health",
        "studio",
        "gymnasium"
    ],
    "wof:name":"Curves For Women",
    "wof:placetype":"venue"
},
  "geometry": {"coordinates":[-122.13976599999999,47.609771],"type":"Point"}
}