{
  "type": "Feature",
  "properties": {
    "addr:full":"120 Chilvers Rd Chehalis WA 98532",
    "addr:housenumber":"120",
    "addr:postcode":"98532",
    "addr:street":"Chilvers Rd",
    "iso:country":"US",
    "sg:address":"120 Chilvers Rd",
    "sg:city":"Chehalis",
    "sg:classifiers":[
        {
            "category":"Organizations",
            "subcategory":"Religious Organization",
            "type":"Services"
        }
    ],
    "sg:phone":"+1 360 748 4330",
    "sg:postcode":"98532",
    "sg:province":"WA",
    "sg:tags":[
        "church"
    ],
    "wof:name":"Seventh-Day Adventist Church",
    "wof:placetype":"venue"
},
  "geometry": {"coordinates":[-123.020101,46.646806],"type":"Point"}
}