{
  "type": "Feature",
  "properties": {
    "addr:full":"10505 248th Street Ct E Graham WA 98338",
    "addr:housenumber":"10505",
    "addr:postcode":"98338",
    "addr:street":"248Th Street Ct E",
    "iso:country":"US",
    "sg:address":"10505 248th Street Ct E",
    "sg:city":"Graham",
    "sg:classifiers":[
        {
            "category":"Wholesale",
            "subcategory":"Furniture",
            "type":"Manufacturing & Wholesale Goods"
        }
    ],
    "sg:phone":"+1 253 846 2662",
    "sg:postcode":"98338",
    "sg:province":"WA",
    "sg:tags":[
        "furniture-wholesale",
        "manufacturer"
    ],
    "wof:name":"Kinney's Carpentry",
    "wof:placetype":"venue"
},
  "geometry": {"coordinates":[-122.29146,47.030728],"type":"Point"}
}