{
  "type": "Feature",
  "properties": {
    "addr:full":"1807 Springwater Ave Wenatchee WA 98801",
    "addr:housenumber":"1807",
    "addr:postcode":"98801",
    "addr:street":"Springwater Ave",
    "iso:country":"US",
    "sg:address":"1807 Springwater Ave",
    "sg:city":"Wenatchee",
    "sg:classifiers":[
        {
            "category":"Professional",
            "type":"Services"
        }
    ],
    "sg:phone":"+1 509 662 9294",
    "sg:postcode":"98801",
    "sg:province":"WA",
    "wof:name":"Mountain Air Alpacas",
    "wof:placetype":"venue"
},
  "geometry": {"coordinates":[-120.346782,47.436986],"type":"Point"}
}