{
  "type": "Feature",
  "properties": {
    "addr:full":"11045 Dayton Ave N Seattle WA 98133",
    "addr:housenumber":"11045",
    "addr:postcode":"98133",
    "addr:street":"Dayton Ave N",
    "iso:country":"US",
    "sg:address":"11045 Dayton Ave N",
    "sg:city":"Seattle",
    "sg:classifiers":[
        {
            "category":"Personal",
            "type":"Services"
        }
    ],
    "sg:phone":"+1 206 571 8449",
    "sg:postcode":"98133",
    "sg:province":"WA",
    "sg:tags":[
        "towing"
    ],
    "wof:name":"Eagle Towing Service",
    "wof:placetype":"venue"
},
  "geometry": {"coordinates":[-122.353223,47.710026],"type":"Point"}
}