{
  "type": "Feature",
  "properties": {
    "addr:full":"109 Main St Edmonds WA 98020",
    "addr:housenumber":"109",
    "addr:postcode":"98020",
    "addr:street":"Main St",
    "iso:country":"US",
    "sg:address":"109 Main St",
    "sg:city":"Edmonds",
    "sg:classifiers":[
        {
            "category":"Cafe",
            "type":"Food & Drink"
        }
    ],
    "sg:menulink":"http://www.allmenus.com/wa/edmonds/58982-cafe-de-paris/menu/",
    "sg:phone":"+1 425 771 2350",
    "sg:postcode":"98020",
    "sg:province":"WA",
    "sg:tags":[
        "french"
    ],
    "wof:name":"Cafe De Paris",
    "wof:placetype":"venue"
},
  "geometry": {"coordinates":[-122.38169000000001,47.81219],"type":"Point"}
}