{
  "type": "Feature",
  "properties": {
    "addr:full":"14216 SE Eastgate Dr Bellevue WA 98006",
    "addr:postcode":"14216;98006",
    "addr:street":"Se Eastgate Dr",
    "iso:country":"US",
    "sg:address":"14216 SE Eastgate Dr",
    "sg:city":"Bellevue",
    "sg:classifiers":[
        {
            "category":"Social Services",
            "subcategory":"Job Training",
            "type":"Services"
        }
    ],
    "sg:phone":"+1 425 746 8116",
    "sg:postcode":"98006",
    "sg:province":"WA",
    "sg:tags":[
        "employment"
    ],
    "wof:name":"Common Good Works Corporation",
    "wof:placetype":"venue"
},
  "geometry": {"coordinates":[-122.150369,47.575716],"type":"Point"}
}