{
  "type": "Feature",
  "properties": {
    "addr:full":"16826 E Interurban Blvd Snohomish WA 98296",
    "addr:housenumber":"16826",
    "addr:postcode":"98296",
    "addr:street":"E Interurban Blvd",
    "iso:country":"US",
    "sg:address":"16826 E Interurban Blvd",
    "sg:city":"Snohomish",
    "sg:classifiers":[
        {
            "category":"Professional",
            "subcategory":"Management & Consulting",
            "type":"Services"
        }
    ],
    "sg:phone":"+1 425 418 0055",
    "sg:postcode":"98296",
    "sg:province":"WA",
    "sg:tags":[
        "aviation",
        "consultant"
    ],
    "wof:name":"Docherty Aviation",
    "wof:placetype":"venue"
},
  "geometry": {"coordinates":[-122.115219,47.844461],"type":"Point"}
}