{
  "type": "Feature",
  "properties": {
    "iso:country":"US",
    "sg:address":"335 Sylvia St N",
    "sg:city":"Montesano",
    "sg:classifiers":[
        {
            "category":"Building & Trades",
            "subcategory":"Construction",
            "type":"Services"
        }
    ],
    "sg:phone":"+1 360 249 4994",
    "sg:postcode":"98563",
    "sg:province":"WA",
    "sg:tags":[
        "house"
    ],
    "wof:name":"Mike Ramsey Construction",
    "wof:placetype":"venue"
},
  "geometry": {"coordinates":[-123.59835699999999,46.984047],"type":"Point"}
}