{
  "type": "Feature",
  "properties": {
    "addr:full":"4526 S Regal St Spokane WA 99223",
    "addr:housenumber":"4526",
    "addr:postcode":"99223",
    "addr:street":"S Regal St",
    "iso:country":"US",
    "sg:address":"4526 S Regal St",
    "sg:city":"Spokane",
    "sg:classifiers":[
        {
            "category":"Personal",
            "subcategory":"Beauty Salon",
            "type":"Services"
        }
    ],
    "sg:phone":"+1 509 443 6556",
    "sg:postcode":"99223",
    "sg:province":"WA",
    "sg:tags":[
        "shop"
    ],
    "wof:name":"Hair Company",
    "wof:placetype":"venue"
},
  "geometry": {"coordinates":[-117.368241,47.611636],"type":"Point"}
}