{
  "type": "Feature",
  "properties": {
    "addr:full":"5007 Doon Way Anacortes WA 98221",
    "addr:housenumber":"5007",
    "addr:postcode":"98221",
    "addr:street":"Doon Way",
    "iso:country":"US",
    "sg:address":"5007 Doon Way",
    "sg:city":"Anacortes",
    "sg:classifiers":[
        {
            "category":"Building & Trades",
            "subcategory":"Construction",
            "type":"Services"
        }
    ],
    "sg:phone":"+1 360 293 7836",
    "sg:postcode":"98221",
    "sg:province":"WA",
    "sg:tags":[
        "consultant",
        "management"
    ],
    "wof:name":"Mechanical Tunneling Consulting",
    "wof:placetype":"venue"
},
  "geometry": {"coordinates":[-122.67424099999999,48.490269],"type":"Point"}
}