{
  "type": "Feature",
  "properties": {
    "addr:full":"5010 Auburn Way S Auburn WA 98092",
    "addr:housenumber":"5010",
    "addr:postcode":"98092",
    "addr:street":"Auburn Way S",
    "iso:country":"US",
    "sg:address":"5010 Auburn Way S",
    "sg:city":"Auburn",
    "sg:classifiers":[
        {
            "category":"Organizations",
            "subcategory":"Religious Organization",
            "type":"Services"
        }
    ],
    "sg:phone":"+1 253 833 5853",
    "sg:postcode":"98092",
    "sg:province":"WA",
    "wof:name":"AAA Church",
    "wof:placetype":"venue"
},
  "geometry": {"coordinates":[-122.16520199999999,47.280045],"type":"Point"}
}