{
  "type": "Feature",
  "properties": {
    "addr:full":"609 W Washington St Sequim WA 98382",
    "addr:housenumber":"609",
    "addr:postcode":"98382",
    "addr:street":"W Washington St",
    "iso:country":"US",
    "sg:address":"609 W Washington St",
    "sg:city":"Sequim",
    "sg:classifiers":[
        {
            "category":"Restaurant",
            "type":"Food & Drink"
        }
    ],
    "sg:phone":"+1 360 683 5809",
    "sg:postcode":"98382",
    "sg:province":"WA",
    "sg:tags":[
        "pizza",
        "italian"
    ],
    "wof:name":"Tarcisio Italian Place",
    "wof:placetype":"venue"
},
  "geometry": {"coordinates":[-123.116167,48.079715],"type":"Point"}
}