{
  "type": "Feature",
  "properties": {
    "addr:full":"60 Wolf Creek Rd Winthrop WA 98862",
    "addr:housenumber":"60",
    "addr:postcode":"98862",
    "addr:street":"Wolf Creek Rd",
    "iso:country":"US",
    "sg:address":"60 Wolf Creek Rd",
    "sg:city":"Winthrop",
    "sg:classifiers":[
        {
            "category":"Travel",
            "subcategory":"Hotels & Motels",
            "type":"Entertainment"
        }
    ],
    "sg:phone":"+1 509 997 2193",
    "sg:postcode":"98862",
    "sg:province":"WA",
    "wof:name":"Cottonwood Cottage",
    "wof:placetype":"venue"
},
  "geometry": {"coordinates":[-120.21077,48.475999],"type":"Point"}
}