{
  "type": "Feature",
  "properties": {
    "iso:country":"US",
    "sg:address":"511 W 6th St",
    "sg:city":"Cle Elum",
    "sg:classifiers":[
        {
            "category":"Wholesale",
            "subcategory":"Furniture",
            "type":"Manufacturing & Wholesale Goods"
        }
    ],
    "sg:phone":"+1 509 674 5392",
    "sg:postcode":"98922",
    "sg:province":"WA",
    "wof:name":"Wild N Woody Furniture Co",
    "wof:placetype":"venue"
},
  "geometry": {"coordinates":[-120.945825,47.200029],"type":"Point"}
}