{
  "type": "Feature",
  "properties": {
    "addr:full":"1101 SE Tech Center Dr # 115 Vancouver WA 98683",
    "addr:housenumber":"1101",
    "addr:postcode":"98683",
    "addr:street":"Se Tech Center Dr # 115",
    "iso:country":"US",
    "sg:address":"1101 SE Tech Center Dr # 115",
    "sg:city":"Vancouver",
    "sg:classifiers":[
        {
            "category":"Animal Shelter",
            "type":"Public Place"
        }
    ],
    "sg:phone":"+1 360 885 2011",
    "sg:postcode":"98683",
    "sg:province":"WA",
    "sg:tags":[
        "wildlife",
        "refuge"
    ],
    "wof:name":"D U",
    "wof:placetype":"venue"
},
  "geometry": {"coordinates":[-122.495949,45.613392],"type":"Point"}
}