{
  "type": "Feature",
  "properties": {
    "addr:full":"7530 204th St NE Arlington WA 98223",
    "addr:housenumber":"7530",
    "addr:postcode":"98223",
    "addr:street":"204Th St Ne",
    "iso:country":"US",
    "sg:address":"7530 204th St NE",
    "sg:city":"Arlington",
    "sg:classifiers":[
        {
            "category":"Health Services",
            "subcategory":"Doctor",
            "type":"Services"
        }
    ],
    "sg:phone":"+1 360 435 8812",
    "sg:postcode":"98223",
    "sg:province":"WA",
    "sg:tags":[
        "physician",
        "family",
        "practice",
        "surgeons",
        "medicine",
        "surgeon"
    ],
    "wof:name":"Chaffee Charles T MD",
    "wof:placetype":"venue"
},
  "geometry": {"coordinates":[-122.129805,48.180837],"type":"Point"}
}