{
  "type": "Feature",
  "properties": {
    "addr:full":"10411 1st Ave S Seattle WA 98168",
    "addr:housenumber":"10411",
    "addr:postcode":"98168",
    "addr:street":"1St Ave S",
    "iso:country":"US",
    "sg:address":"10411 1st Ave S",
    "sg:city":"Seattle",
    "sg:classifiers":[
        {
            "category":"Professional",
            "subcategory":"Art Services",
            "type":"Services"
        }
    ],
    "sg:phone":"+1 206 764 5772",
    "sg:postcode":"98168",
    "sg:province":"WA",
    "sg:tags":[
        "commercial",
        "design"
    ],
    "wof:name":"Sumac Graphics",
    "wof:placetype":"venue"
},
  "geometry": {"coordinates":[-122.333703,47.508648],"type":"Point"}
}