{
  "type": "Feature",
  "properties": {
    "addr:full":"22600 NE 142nd Pl Woodinville WA 98077",
    "addr:housenumber":"22600",
    "addr:postcode":"98077",
    "addr:street":"Ne 142Nd Pl",
    "iso:country":"US",
    "sg:address":"22600 NE 142nd Pl",
    "sg:city":"Woodinville",
    "sg:classifiers":[
        {
            "category":"Professional",
            "subcategory":"Art Services",
            "type":"Services"
        }
    ],
    "sg:phone":"+1 425 702 8892",
    "sg:postcode":"98077",
    "sg:province":"WA",
    "sg:tags":[
        "photography",
        "commercial"
    ],
    "wof:name":"Spectare Media LLC",
    "wof:placetype":"venue"
},
  "geometry": {"coordinates":[-122.03647599999999,47.729259],"type":"Point"}
}