{
  "type": "Feature",
  "properties": {
    "addr:full":"1001 W Augusta Ave Spokane WA 99205",
    "addr:housenumber":"1001",
    "addr:postcode":"99205",
    "addr:street":"W Augusta Ave",
    "iso:country":"US",
    "sg:address":"1001 W Augusta Ave",
    "sg:city":"Spokane",
    "sg:classifiers":[
        {
            "category":"Professional",
            "type":"Services"
        }
    ],
    "sg:phone":"+1 509 329 1005",
    "sg:postcode":"99205",
    "sg:province":"WA",
    "wof:name":"Carlson Gallery",
    "wof:placetype":"venue"
},
  "geometry": {"coordinates":[-117.42821499999999,47.673121],"type":"Point"}
}