{
  "type": "Feature",
  "properties": {
    "addr:full":"555 Northgate Mall Seattle WA 98125",
    "addr:housenumber":"555",
    "addr:postcode":"98125",
    "addr:street":"Northgate Mall",
    "iso:country":"US",
    "sg:address":"555 Northgate Mall",
    "sg:city":"Seattle",
    "sg:classifiers":[
        {
            "category":"Autos & Motor Vehicles",
            "subcategory":"Auto Supplies",
            "type":"Retail Goods"
        }
    ],
    "sg:phone":"+1 206 364 4342",
    "sg:postcode":"98125",
    "sg:province":"WA",
    "sg:tags":[
        "battery"
    ],
    "wof:name":"Battery One Stop",
    "wof:placetype":"venue"
},
  "geometry": {"coordinates":[-122.323756,47.707266],"type":"Point"}
}