{
  "type": "Feature",
  "properties": {
    "addr:full":"355 NW Chehalis Ave Chehalis WA 98532",
    "addr:housenumber":"355",
    "addr:postcode":"98532",
    "addr:street":"Nw Chehalis Ave",
    "iso:country":"US",
    "sg:address":"355 NW Chehalis Ave",
    "sg:city":"Chehalis",
    "sg:classifiers":[
        {
            "category":"Food & Beverages",
            "subcategory":"Groceries & Convenience Stores",
            "type":"Retail Goods"
        },
        {
            "category":"Restaurant",
            "type":"Food & Drink"
        }
    ],
    "sg:phone":"+1 360 748 6021",
    "sg:postcode":"98532",
    "sg:province":"WA",
    "sg:tags":[
        "caterer"
    ],
    "wof:name":"Chehalis Dell",
    "wof:placetype":"venue"
},
  "geometry": {"coordinates":[-122.970198,46.663677],"type":"Point"}
}