{
  "type": "Feature",
  "properties": {
    "addr:full":"1001 Pacific Ave Tacoma WA 98402",
    "addr:housenumber":"1001",
    "addr:postcode":"98402",
    "addr:street":"Pacific Ave",
    "iso:country":"US",
    "sg:address":"1001 Pacific Ave",
    "sg:city":"Tacoma",
    "sg:classifiers":[
        {
            "category":"Professional",
            "subcategory":"Lawyer & Legal Services",
            "type":"Services"
        }
    ],
    "sg:phone":"+1 253 779 4000",
    "sg:postcode":"98402",
    "sg:province":"WA",
    "sg:tags":[
        "attorney"
    ],
    "wof:name":"Goodstein Law Group Pllc",
    "wof:placetype":"venue"
},
  "geometry": {"coordinates":[-122.438631,47.253377],"type":"Point"}
}