{
  "type": "Feature",
  "properties": {
    "addr:full":"1107 Mount Vernon Terminal RR Mt Vernon WA 98273",
    "addr:housenumber":"1107",
    "addr:postcode":"98273",
    "addr:street":"Rr Mt Vernon",
    "iso:country":"US",
    "sg:address":"1107 Mount Vernon Terminal RR",
    "sg:city":"Mt Vernon",
    "sg:classifiers":[
        {
            "category":"Real Estate",
            "subcategory":"Real Estate Agent",
            "type":"Services"
        }
    ],
    "sg:phone":"+1 360 428 8102",
    "sg:postcode":"98273",
    "sg:province":"WA",
    "wof:name":"Pacific Northwest Properties",
    "wof:placetype":"venue"
},
  "geometry": {"coordinates":[-122.340536,48.414791],"type":"Point"}
}