{
  "type": "Feature",
  "properties": {
    "addr:full":"1104 Brotherson Rd Apt 1 Centralia WA 98531",
    "addr:housenumber":"1104;1",
    "addr:postcode":"98531",
    "addr:street":"Brotherson Rd Apt",
    "iso:country":"US",
    "sg:address":"1104 Brotherson Rd Apt 1",
    "sg:city":"Centralia",
    "sg:classifiers":[
        {
            "category":"Real Estate",
            "subcategory":"Real Estate Services",
            "type":"Services"
        },
        {
            "category":"Real Estate",
            "subcategory":"Real Estate Operator",
            "type":"Services"
        }
    ],
    "sg:phone":"+1 360 736 3047",
    "sg:postcode":"98531",
    "sg:province":"WA",
    "sg:tags":[
        "vacancy",
        "apartment",
        "rental",
        "finder",
        "listing"
    ],
    "wof:name":"Brotherson Apts",
    "wof:placetype":"venue"
},
  "geometry": {"coordinates":[-122.97090900000001,46.708019],"type":"Point"}
}