{
  "type": "Feature",
  "properties": {
    "addr:full":"Greenlake Park 7201 E Green Lake Dr N Seattle WA 98115",
    "addr:housenumber":"7201",
    "addr:postcode":"98115",
    "addr:street":"Greenlake;E Green Lake Dr N",
    "iso:country":"US",
    "sg:address":"Greenlake Park 7201 E Green Lake Dr N",
    "sg:city":"Seattle",
    "sg:classifiers":[
        {
            "category":"Recreation",
            "type":"Entertainment"
        }
    ],
    "sg:postcode":"98115",
    "sg:province":"WA",
    "sg:tags":[
        "active",
        "life"
    ],
    "sg:website":"www.irongirl.com/Home_Page.htm",
    "wof:name":"Aflac Iron Girl",
    "wof:placetype":"venue"
},
  "geometry": {"coordinates":[-122.32586499999999,47.680296],"type":"Point"}
}