{
  "type": "Feature",
  "properties": {
    "addr:full":"1409 275th Pl Ocean Park WA 98640",
    "addr:housenumber":"1409",
    "addr:postcode":"98640",
    "addr:street":"275Th Pl;Park",
    "iso:country":"US",
    "sg:address":"1409 275th Pl",
    "sg:city":"Ocean Park",
    "sg:classifiers":[
        {
            "category":"Retail",
            "subcategory":"Repair Shop",
            "type":"Services"
        }
    ],
    "sg:phone":"+1 360 665 3514",
    "sg:postcode":"98640",
    "sg:province":"WA",
    "wof:name":"Farwest Co",
    "wof:placetype":"venue"
},
  "geometry": {"coordinates":[-124.05180900000001,46.501832],"type":"Point"}
}