{
  "type": "Feature",
  "properties": {
    "addr:full":"11001 E Montgomery Dr Spokane Valley WA 99206",
    "addr:housenumber":"11001",
    "addr:postcode":"99206",
    "addr:street":"E Montgomery Dr",
    "iso:country":"US",
    "sg:address":"11001 E Montgomery Dr",
    "sg:city":"Spokane Valley",
    "sg:classifiers":[
        {
            "category":"Building & Trades",
            "subcategory":"Construction",
            "type":"Services"
        }
    ],
    "sg:phone":"+1 509 534 0451",
    "sg:postcode":"99206",
    "sg:province":"WA",
    "sg:tags":[
        "general",
        "commercial",
        "contractor"
    ],
    "sg:website":"www.lydigspokane.com",
    "wof:name":"Lydig Construction Inc",
    "wof:placetype":"venue"
},
  "geometry": {"coordinates":[-117.261061,47.680662],"type":"Point"}
}