{
  "type": "Feature",
  "properties": {
    "addr:full":"36021 Allen Rd S Roy WA 98580",
    "addr:housenumber":"36021",
    "addr:postcode":"98580",
    "addr:street":"Allen Rd S",
    "iso:country":"US",
    "sg:address":"36021 Allen Rd S",
    "sg:city":"Roy",
    "sg:classifiers":[
        {
            "category":"Retail",
            "subcategory":"Repair Shop",
            "type":"Services"
        }
    ],
    "sg:phone":"+1 360 458 6036",
    "sg:postcode":"98580",
    "sg:province":"WA",
    "wof:name":"J&L Repair",
    "wof:placetype":"venue"
},
  "geometry": {"coordinates":[-122.46931600000001,46.930127],"type":"Point"}
}