{
  "type": "Feature",
  "properties": {
    "addr:full":"3200 St Johns Blvd Vancouver WA 98661",
    "addr:housenumber":"3200",
    "addr:postcode":"98661",
    "addr:street":"St Johns Blvd",
    "iso:country":"US",
    "sg:address":"3200 St Johns Blvd",
    "sg:city":"Vancouver",
    "sg:classifiers":[
        {
            "category":"Place Of Worship",
            "subcategory":"Church",
            "type":"Public Place"
        },
        {
            "category":"Place Of Worship",
            "type":"Public Place"
        }
    ],
    "sg:phone":"+1 360 695 8632",
    "sg:postcode":"98661",
    "sg:province":"WA",
    "sg:tags":[
        "churches-seventh-day",
        "adventist",
        "christian",
        "churches-advent"
    ],
    "wof:name":"Clark County Adventist Community Center",
    "wof:placetype":"venue"
},
  "geometry": {"coordinates":[-122.644783,45.644169],"type":"Point"}
}