{
  "type": "Feature",
  "properties": {
    "addr:full":"1620 W 2nd St Aberdeen WA 98520",
    "addr:housenumber":"1620",
    "addr:postcode":"98520",
    "addr:street":"W 2Nd St",
    "iso:country":"US",
    "sg:address":"1620 W 2nd St",
    "sg:city":"Aberdeen",
    "sg:classifiers":[
        {
            "category":"Manufacturing",
            "subcategory":"Lumber",
            "type":"Manufacturing & Wholesale Goods"
        }
    ],
    "sg:phone":"+1 360 538 1402",
    "sg:postcode":"98520",
    "sg:province":"WA",
    "sg:tags":[
        "operation",
        "timber",
        "tract"
    ],
    "wof:name":"Quality Cutting Inc",
    "wof:placetype":"venue"
},
  "geometry": {"coordinates":[-123.835137,46.971548],"type":"Point"}
}