{
  "type": "Feature",
  "properties": {
    "addr:full":"45 Imhoff Rd Tonasket WA 98855",
    "addr:housenumber":"45",
    "addr:postcode":"98855",
    "addr:street":"Imhoff Rd",
    "iso:country":"US",
    "sg:address":"45 Imhoff Rd",
    "sg:city":"Tonasket",
    "sg:classifiers":[
        {
            "category":"Organizations",
            "subcategory":"Professional Association",
            "type":"Services"
        }
    ],
    "sg:phone":"+1 509 486 4941",
    "sg:postcode":"98855",
    "sg:province":"WA",
    "wof:name":"O K Ranch",
    "wof:placetype":"venue"
},
  "geometry": {"coordinates":[-119.428346,48.7785],"type":"Point"}
}