{
  "type": "Feature",
  "properties": {
    "addr:full":"227210 E Game Farm Rd Kennewick WA 99337",
    "addr:housenumber":"227210",
    "addr:postcode":"99337",
    "addr:street":"E Game Farm Rd",
    "iso:country":"US",
    "sg:address":"227210 E Game Farm Rd",
    "sg:city":"Kennewick",
    "sg:classifiers":[
        {
            "category":"Retail",
            "subcategory":"Animal Services",
            "type":"Services"
        }
    ],
    "sg:phone":"+1 509 586 6653",
    "sg:postcode":"99337",
    "sg:province":"WA",
    "wof:name":"Triple J Equestrian Center",
    "wof:placetype":"venue"
},
  "geometry": {"coordinates":[-119.023903,46.153696],"type":"Point"}
}