{
  "type": "Feature",
  "properties": {
    "addr:full":"31051 51st Ave SW Federal Way WA 98023",
    "addr:housenumber":"31051",
    "addr:postcode":"98023",
    "addr:street":"51St Ave Sw Federal Way",
    "iso:country":"US",
    "sg:address":"31051 51st Ave SW",
    "sg:city":"Federal Way",
    "sg:classifiers":[
        {
            "category":"Professional",
            "subcategory":"Business Services",
            "type":"Services"
        }
    ],
    "sg:phone":"+1 253 838 2458",
    "sg:postcode":"98023",
    "sg:province":"WA",
    "wof:name":"Dissmore Financial Svcs LLC",
    "wof:placetype":"venue"
},
  "geometry": {"coordinates":[-122.398128,47.323938],"type":"Point"}
}