{
  "type": "Feature",
  "properties": {
    "addr:full":"22450 Miller Bay Rd NE Poulsbo WA 98370",
    "addr:housenumber":"22450",
    "addr:postcode":"98370",
    "addr:street":"Miller Bay Rd Ne",
    "iso:country":"US",
    "sg:address":"22450 Miller Bay Rd NE",
    "sg:city":"Poulsbo",
    "sg:classifiers":[
        {
            "category":"Building & Trades",
            "subcategory":"Construction",
            "type":"Services"
        }
    ],
    "sg:phone":"+1 360 697 4149",
    "sg:postcode":"98370",
    "sg:province":"WA",
    "sg:tags":[
        "slope",
        "retaining"
    ],
    "wof:name":"Sound Integrity Construction",
    "wof:placetype":"venue"
},
  "geometry": {"coordinates":[-122.561629,47.766271],"type":"Point"}
}