{
  "type": "Feature",
  "properties": {
    "addr:full":"2873 Haxton Way Bellingham WA 98226",
    "addr:housenumber":"2873",
    "addr:postcode":"98226",
    "addr:street":"Haxton Way",
    "iso:country":"US",
    "sg:address":"2873 Haxton Way",
    "sg:city":"Bellingham",
    "sg:classifiers":[
        {
            "category":"Building & Trades",
            "subcategory":"Construction",
            "type":"Services"
        }
    ],
    "sg:phone":"+1 360 758 2075",
    "sg:postcode":"98226",
    "sg:province":"WA",
    "sg:tags":[
        "general",
        "contractor"
    ],
    "wof:name":"S & T Construction",
    "wof:placetype":"venue"
},
  "geometry": {"coordinates":[-122.66536600000001,48.744186],"type":"Point"}
}