{
  "type": "Feature",
  "properties": {
    "addr:full":"724 N 72nd St Seattle WA 98103",
    "addr:housenumber":"724",
    "addr:postcode":"98103",
    "addr:street":"N 72Nd St",
    "iso:country":"US",
    "sg:address":"724 N 72nd St",
    "sg:city":"Seattle",
    "sg:classifiers":[
        {
            "category":"Professional",
            "type":"Services"
        }
    ],
    "sg:phone":"+1 206 782 8835",
    "sg:postcode":"98103",
    "sg:province":"WA",
    "wof:name":"Annette Cottrell",
    "wof:placetype":"venue"
},
  "geometry": {"coordinates":[-122.347267,47.681123],"type":"Point"}
}