{
  "type": "Feature",
  "properties": {
    "addr:full":"5964 Church Rd Ferndale WA 98248",
    "addr:housenumber":"5964",
    "addr:postcode":"98248",
    "addr:street":"Church Rd",
    "iso:country":"US",
    "sg:address":"5964 Church Rd",
    "sg:city":"Ferndale",
    "sg:classifiers":[
        {
            "category":"Building & Trades",
            "subcategory":"Landscaping Services",
            "type":"Services"
        }
    ],
    "sg:phone":"+1 360 384 5927",
    "sg:postcode":"98248",
    "sg:province":"WA",
    "wof:name":"Fast Horticultural Services",
    "wof:placetype":"venue"
},
  "geometry": {"coordinates":[-122.616636,48.85773],"type":"Point"}
}