{
  "type": "Feature",
  "properties": {
    "addr:full":"3350 Monte Villa Pkwy Bothell WA 98021",
    "addr:housenumber":"3350",
    "addr:postcode":"98021",
    "addr:street":"Monte Villa Pkwy",
    "iso:country":"US",
    "sg:address":"3350 Monte Villa Pkwy",
    "sg:city":"Bothell",
    "sg:classifiers":[
        {
            "category":"Professional",
            "subcategory":"Engineering",
            "type":"Services"
        }
    ],
    "sg:phone":"+1 425 951 4800",
    "sg:postcode":"98021",
    "sg:province":"WA",
    "sg:tags":[
        "civil",
        "architectural"
    ],
    "wof:name":"W & H Pacific Inc",
    "wof:placetype":"venue"
},
  "geometry": {"coordinates":[-122.189609,47.778032],"type":"Point"}
}