{
  "type": "Feature",
  "properties": {
    "iso:country":"US",
    "sg:address":"1352 State Ave",
    "sg:city":"Marysville",
    "sg:classifiers":[
        {
            "category":"Bars & Pubs",
            "type":"Food & Drink"
        }
    ],
    "sg:phone":"+1 360 658 7747",
    "sg:postcode":"98270",
    "sg:province":"WA",
    "sg:tags":[
        "drinking"
    ],
    "wof:name":"J R Phinickeys",
    "wof:placetype":"venue"
},
  "geometry": {"coordinates":[-122.176844,48.066057],"type":"Point"}
}