{
  "type": "Feature",
  "properties": {
    "addr:full":"407 S 5th Ave Sequim WA 98382",
    "addr:housenumber":"407",
    "addr:postcode":"98382",
    "addr:street":"S 5Th Ave",
    "iso:country":"US",
    "sg:address":"407 S 5th Ave",
    "sg:city":"Sequim",
    "sg:classifiers":[
        {
            "category":"Building & Trades",
            "subcategory":"Plumbing",
            "type":"Services"
        },
        {
            "category":"Home & Garden",
            "subcategory":"Building Materials",
            "type":"Retail Goods"
        },
        {
            "category":"Building & Trades",
            "subcategory":"Construction",
            "type":"Services"
        },
        {
            "category":"Utilities",
            "subcategory":"Sewage",
            "type":"Services"
        }
    ],
    "sg:phone":"+1 360 457 1206",
    "sg:postcode":"98382",
    "sg:province":"WA",
    "sg:tags":[
        "heater",
        "plumber",
        "excavation",
        "contractor",
        "water",
        "sewer",
        "cleaning",
        "plumbing-drain"
    ],
    "sg:website":"http://national.citysearch.com/profile/external/603453022/sequim_wa/roto_rooter_plumbing_drain_services.html?publisher=yellowpages&reference_id=1&placement=ypwebsitemip",
    "wof:name":"Roto-Rooter Plumbing & Drain Services",
    "wof:placetype":"venue"
},
  "geometry": {"coordinates":[-123.11316600000001,48.076885],"type":"Point"}
}