{
  "type": "Feature",
  "properties": {
    "addr:full":"482 228th Ave NE Sammamish WA 98074",
    "addr:housenumber":"482",
    "addr:postcode":"98074",
    "addr:street":"228Th Ave Ne",
    "iso:country":"US",
    "sg:address":"482 228th Ave NE",
    "sg:city":"Sammamish",
    "sg:classifiers":[
        {
            "category":"Government",
            "subcategory":"Office",
            "type":"Public Place"
        }
    ],
    "sg:phone":"+1 206 205 8380",
    "sg:postcode":"98074",
    "sg:province":"WA",
    "sg:tags":[
        "court"
    ],
    "wof:name":"Executive Services Dept",
    "wof:placetype":"venue"
},
  "geometry": {"coordinates":[-122.035391,47.613065],"type":"Point"}
}