{
  "type": "Feature",
  "properties": {
    "addr:full":"650 NE Midway Blvd Oak Harbor WA 98277",
    "addr:housenumber":"650",
    "addr:postcode":"98277",
    "addr:street":"Ne Midway Blvd",
    "iso:country":"US",
    "sg:address":"650 NE Midway Blvd",
    "sg:city":"Oak Harbor",
    "sg:classifiers":[
        {
            "category":"Banks & Credit Unions",
            "subcategory":"Bank",
            "type":"Services"
        }
    ],
    "sg:phone":"+1 360 679 9755",
    "sg:postcode":"98277",
    "sg:province":"WA",
    "sg:tags":[
        "loan",
        "real estate"
    ],
    "wof:name":"Ak USA Mortgage Co",
    "wof:placetype":"venue"
},
  "geometry": {"coordinates":[-122.643176,48.299529],"type":"Point"}
}