{
  "type": "Feature",
  "properties": {
    "addr:full":"720 N 2nd St Tacoma WA 98403",
    "addr:housenumber":"720",
    "addr:postcode":"98403",
    "addr:street":"N 2Nd St",
    "iso:country":"US",
    "sg:address":"720 N 2nd St",
    "sg:city":"Tacoma",
    "sg:classifiers":[
        {
            "category":"Real Estate",
            "subcategory":"Real Estate Operator",
            "type":"Services"
        }
    ],
    "sg:phone":"+1 253 272 0803",
    "sg:postcode":"98403",
    "sg:province":"WA",
    "sg:tags":[
        "building",
        "apartment"
    ],
    "wof:name":"Casablanca Apartments",
    "wof:placetype":"venue"
},
  "geometry": {"coordinates":[-122.45097,47.263376],"type":"Point"}
}