{
  "type": "Feature",
  "properties": {
    "addr:full":"5030 Evergreen Way Everett WA 98203",
    "addr:housenumber":"5030",
    "addr:postcode":"98203",
    "addr:street":"Evergreen Way",
    "iso:country":"US",
    "sg:address":"5030 Evergreen Way",
    "sg:city":"Everett",
    "sg:classifiers":[
        {
            "category":"Restaurant",
            "type":"Food & Drink"
        }
    ],
    "sg:phone":"+1 425 252 2435",
    "sg:postcode":"98203",
    "sg:province":"WA",
    "wof:name":"Gianni's Ristorante Italiano",
    "wof:placetype":"venue"
},
  "geometry": {"coordinates":[-122.214457,47.94982],"type":"Point"}
}