{
  "type": "Feature",
  "properties": {
    "addr:full":"41 W Riverside Ave Spokane WA 99201",
    "addr:housenumber":"41",
    "addr:postcode":"99201",
    "addr:street":"W Riverside Ave",
    "iso:country":"US",
    "sg:address":"41 W Riverside Ave",
    "sg:city":"Spokane",
    "sg:classifiers":[
        {
            "category":"Building & Trades",
            "subcategory":"Construction",
            "type":"Services"
        }
    ],
    "sg:phone":"+1 509 747 5618",
    "sg:postcode":"99201",
    "sg:province":"WA",
    "sg:tags":[
        "general",
        "contractor"
    ],
    "wof:name":"TFB Inc",
    "wof:placetype":"venue"
},
  "geometry": {"coordinates":[-117.41283199999999,47.657901],"type":"Point"}
}