{
  "type": "Feature",
  "properties": {
    "addr:full":"6924 22nd St W Tacoma WA 98466",
    "addr:housenumber":"6924",
    "addr:postcode":"98466",
    "addr:street":"22Nd St W",
    "iso:country":"US",
    "sg:address":"6924 22nd St W",
    "sg:city":"Tacoma",
    "sg:classifiers":[
        {
            "category":"Manufacturing",
            "subcategory":"Printing",
            "type":"Manufacturing & Wholesale Goods"
        }
    ],
    "sg:phone":"+1 253 565 4713",
    "sg:postcode":"98466",
    "sg:province":"WA",
    "sg:tags":[
        "printer"
    ],
    "wof:name":"Pacific Business Printing",
    "wof:placetype":"venue"
},
  "geometry": {"coordinates":[-122.52958099999999,47.240294],"type":"Point"}
}