{
  "type": "Feature",
  "properties": {
    "addr:full":"808 3rd Ave Seattle WA 98104",
    "addr:housenumber":"808",
    "addr:postcode":"98104",
    "addr:street":"3Rd Ave",
    "iso:country":"US",
    "sg:address":"808 3rd Ave",
    "sg:city":"Seattle",
    "sg:classifiers":[
        {
            "category":"Fast Food",
            "type":"Food & Drink"
        },
        {
            "category":"Food & Beverages",
            "subcategory":"Bakery",
            "type":"Retail Goods"
        }
    ],
    "sg:phone":"+1 206 624 7574",
    "sg:postcode":"98104",
    "sg:province":"WA",
    "sg:tags":[
        "sandwich"
    ],
    "sg:website":"www.subway.com",
    "wof:name":"Subway",
    "wof:placetype":"venue"
},
  "geometry": {"coordinates":[-122.333,47.604599],"type":"Point"}
}