{
  "type": "Feature",
  "properties": {
    "addr:full":"6219 116th Street Ct E Puyallup WA 98373",
    "addr:housenumber":"6219",
    "addr:postcode":"98373",
    "addr:street":"116Th Street Ct E",
    "iso:country":"US",
    "sg:address":"6219 116th Street Ct E",
    "sg:city":"Puyallup",
    "sg:classifiers":[
        {
            "category":"Professional",
            "subcategory":"Management & Consulting",
            "type":"Services"
        },
        {
            "category":"Professional",
            "subcategory":"Advertising",
            "type":"Services"
        }
    ],
    "sg:phone":"+1 253 539 2206",
    "sg:postcode":"98373",
    "sg:province":"WA",
    "sg:tags":[
        "marketing",
        "program",
        "consultant"
    ],
    "wof:name":"Seddon Marketing Inc",
    "wof:placetype":"venue"
},
  "geometry": {"coordinates":[-122.34656,47.150686],"type":"Point"}
}