{
  "type": "Feature",
  "properties": {
    "addr:full":"336 S Sherman St Spokane WA 99202",
    "addr:housenumber":"336",
    "addr:postcode":"99202",
    "addr:street":"S Sherman St",
    "iso:country":"US",
    "sg:address":"336 S Sherman St",
    "sg:city":"Spokane",
    "sg:classifiers":[
        {
            "category":"Real Estate",
            "subcategory":"Architect",
            "type":"Services"
        }
    ],
    "sg:phone":"+1 509 327 1091",
    "sg:postcode":"99202",
    "sg:province":"WA",
    "sg:tags":[
        "architectural"
    ],
    "wof:name":"Steven R Radkey",
    "wof:placetype":"venue"
},
  "geometry": {"coordinates":[-117.403195,47.652725],"type":"Point"}
}