{
  "type": "Feature",
  "properties": {
    "addr:full":"2294 State Rte 109 Ocean City WA 98550",
    "addr:housenumber":"2294",
    "addr:postcode":"98550",
    "addr:street":"State Rte 109",
    "iso:country":"US",
    "sg:address":"2294 State Rte 109",
    "sg:city":"Ocean City",
    "sg:classifiers":[
        {
            "category":"Organizations",
            "subcategory":"Community Association",
            "type":"Services"
        }
    ],
    "sg:phone":"+1 360 289 2948",
    "sg:postcode":"98550",
    "sg:province":"WA",
    "sg:tags":[
        "military"
    ],
    "wof:name":"Veterans Of Foreign Wars",
    "wof:placetype":"venue"
},
  "geometry": {"coordinates":[-124.156443,47.043789],"type":"Point"}
}