{
  "type": "Feature",
  "properties": {
    "addr:full":"2101 E State Hwy 302 Belfair WA 98528",
    "addr:housenumber":"2101",
    "addr:postcode":"98528",
    "addr:street":"E State Hwy 302",
    "iso:country":"US",
    "sg:address":"2101 E State Hwy 302",
    "sg:city":"Belfair",
    "sg:classifiers":[
        {
            "category":"Building & Trades",
            "subcategory":"Construction",
            "type":"Services"
        }
    ],
    "sg:phone":"+1 360 275 5651",
    "sg:postcode":"98528",
    "sg:province":"WA",
    "sg:tags":[
        "house"
    ],
    "wof:name":"Modern Builders Inc",
    "wof:placetype":"venue"
},
  "geometry": {"coordinates":[-122.81309299999999,47.397544],"type":"Point"}
}