{
  "type": "Feature",
  "properties": {
    "iso:country":"US",
    "sg:address":"918 W Locust St",
    "sg:city":"Centralia",
    "sg:classifiers":[
        {
            "category":"Real Estate",
            "subcategory":"Surveying",
            "type":"Services"
        }
    ],
    "sg:phone":"+1 360 736 0394",
    "sg:postcode":"98531",
    "sg:province":"WA",
    "sg:tags":[
        "surveyor"
    ],
    "wof:name":"Schinnell Surveying & Mapping",
    "wof:placetype":"venue"
},
  "geometry": {"coordinates":[-122.964966,46.717276],"type":"Point"}
}