{
  "type": "Feature",
  "properties": {
    "addr:full":"1441 N Northlake Way Seattle WA 98103",
    "addr:housenumber":"1441",
    "addr:postcode":"98103",
    "addr:street":"N Northlake Way",
    "iso:country":"US",
    "sg:address":"1441 N Northlake Way",
    "sg:city":"Seattle",
    "sg:classifiers":[
        {
            "category":"Real Estate",
            "subcategory":"Real Estate Services",
            "type":"Services"
        }
    ],
    "sg:phone":"+1 206 632 2894",
    "sg:postcode":"98103",
    "sg:province":"WA",
    "sg:tags":[
        "management",
        "property"
    ],
    "wof:name":"Martin Management Company",
    "wof:placetype":"venue"
},
  "geometry": {"coordinates":[-122.339996,47.647701],"type":"Point"}
}