{
  "type": "Feature",
  "properties": {
    "addr:full":"6987 Perimeter Rd S Seattle WA 98108",
    "addr:housenumber":"6987",
    "addr:postcode":"98108",
    "addr:street":"Perimeter Rd S",
    "iso:country":"US",
    "sg:address":"6987 Perimeter Rd S",
    "sg:city":"Seattle",
    "sg:classifiers":[
        {
            "category":"Manufacturing",
            "subcategory":"Aerospace",
            "type":"Manufacturing & Wholesale Goods"
        }
    ],
    "sg:phone":"+1 206 767 7048",
    "sg:postcode":"98108",
    "sg:province":"WA",
    "sg:tags":[
        "aircraft",
        "component"
    ],
    "wof:name":"Dassault Falcon Jet",
    "wof:placetype":"venue"
},
  "geometry": {"coordinates":[-122.307407,47.541422],"type":"Point"}
}