{
  "type": "Feature",
  "properties": {
    "addr:full":"1633 Birchwood Ave # 102 Bellingham WA 98225",
    "addr:housenumber":"1633",
    "addr:postcode":"98225",
    "addr:street":"Birchwood Ave # 102",
    "iso:country":"US",
    "sg:address":"1633 Birchwood Ave # 102",
    "sg:city":"Bellingham",
    "sg:classifiers":[
        {
            "category":"Health Services",
            "subcategory":"Chiropractor",
            "type":"Services"
        }
    ],
    "sg:phone":"+1 360 715 8722",
    "sg:postcode":"98225",
    "sg:province":"WA",
    "sg:tags":[
        "chiropractic"
    ],
    "wof:name":"Randall W Hill Dc",
    "wof:placetype":"venue"
},
  "geometry": {"coordinates":[-122.492144,48.77532],"type":"Point"}
}