{
  "type": "Feature",
  "properties": {
    "addr:full":"919 S King St Seattle WA 98104",
    "addr:housenumber":"919",
    "addr:postcode":"98104",
    "addr:street":"S King St",
    "iso:country":"US",
    "sg:address":"919 S King St",
    "sg:city":"Seattle",
    "sg:classifiers":[
        {
            "category":"Social Services",
            "type":"Services"
        }
    ],
    "sg:phone":"+1 206 292 5714",
    "sg:postcode":"98104",
    "sg:province":"WA",
    "sg:tags":[
        "food",
        "banks"
    ],
    "wof:name":"Asian Counseling & Referral",
    "wof:placetype":"venue"
},
  "geometry": {"coordinates":[-122.320718,47.598265],"type":"Point"}
}