{
  "type": "Feature",
  "properties": {
    "addr:full":"3830 Driftwood Dr Clinton WA 98236",
    "addr:housenumber":"3830",
    "addr:postcode":"98236",
    "addr:street":"Driftwood Dr",
    "iso:country":"US",
    "sg:address":"3830 Driftwood Dr",
    "sg:city":"Clinton",
    "sg:classifiers":[
        {
            "category":"Retail",
            "subcategory":"Repair Shop",
            "type":"Services"
        }
    ],
    "sg:phone":"+1 360 579 2180",
    "sg:postcode":"98236",
    "sg:province":"WA",
    "wof:name":"Home Theater Audio Concep",
    "wof:placetype":"venue"
},
  "geometry": {"coordinates":[-122.407899,47.917798],"type":"Point"}
}