{
  "type": "Feature",
  "properties": {
    "addr:full":"3584 Krug Rd Connell WA 99326",
    "addr:housenumber":"3584",
    "addr:postcode":"99326",
    "addr:street":"Krug Rd",
    "iso:country":"US",
    "sg:address":"3584 Krug Rd",
    "sg:city":"Connell",
    "sg:classifiers":[
        {
            "category":"Professional",
            "subcategory":"Management & Consulting",
            "type":"Services"
        },
        {
            "category":"Farming",
            "subcategory":"Farm",
            "type":"Manufacturing & Wholesale Goods"
        }
    ],
    "sg:phone":"+1 509 234 8746",
    "sg:postcode":"99326",
    "sg:province":"WA",
    "sg:website":"http://www.paradisefarms.net",
    "wof:name":"Paradise Farms, A Partnership",
    "wof:placetype":"venue"
},
  "geometry": {"coordinates":[-118.98205,46.733418],"type":"Point"}
}