{
  "type": "Feature",
  "properties": {
    "addr:full":"911 N L St Tacoma WA 98403",
    "addr:housenumber":"911",
    "addr:postcode":"98403",
    "addr:street":"N L St",
    "iso:country":"US",
    "sg:address":"911 N L St",
    "sg:city":"Tacoma",
    "sg:classifiers":[
        {
            "category":"Professional",
            "subcategory":"Advertising",
            "type":"Services"
        }
    ],
    "sg:phone":"+1 253 627 6506",
    "sg:postcode":"98403",
    "sg:province":"WA",
    "wof:name":"Global Advertising",
    "wof:placetype":"venue"
},
  "geometry": {"coordinates":[-122.464568,47.263249],"type":"Point"}
}