{
  "type": "Feature",
  "properties": {
    "iso:country":"US",
    "sg:address":"915 2nd Ave",
    "sg:city":"Seattle",
    "sg:classifiers":[
        {
            "category":"Government",
            "subcategory":"Office",
            "type":"Public Place"
        }
    ],
    "sg:phone":"+1 206 220 6450",
    "sg:postcode":"98174",
    "sg:province":"WA",
    "sg:tags":[
        "sector",
        "enforcement",
        "agency",
        "commercial",
        "regulation",
        "law"
    ],
    "wof:name":"Seattle III Field Office",
    "wof:placetype":"venue"
},
  "geometry": {"coordinates":[-122.19109899999999,47.67678],"type":"Point"}
}