{
  "type": "Feature",
  "properties": {
    "addr:full":"2020 Grant Ave S Apt A101 Renton WA 98055",
    "addr:housenumber":"2020",
    "addr:postcode":"98055",
    "addr:street":"Grant Ave S Apt A101",
    "iso:country":"US",
    "sg:address":"2020 Grant Ave S Apt A101",
    "sg:city":"Renton",
    "sg:classifiers":[
        {
            "category":"Real Estate",
            "subcategory":"Real Estate Services",
            "type":"Services"
        }
    ],
    "sg:phone":"+1 425 226 2406",
    "sg:postcode":"98055",
    "sg:province":"WA",
    "sg:tags":[
        "management",
        "condominium"
    ],
    "wof:name":"Rolling Hills Condominium",
    "wof:placetype":"venue"
},
  "geometry": {"coordinates":[-122.19923799999999,47.462],"type":"Point"}
}