{
  "type": "Feature",
  "properties": {
    "addr:full":"10523 SE 32nd St Bellevue WA 98004",
    "addr:housenumber":"10523",
    "addr:postcode":"98004",
    "addr:street":"Se 32Nd St",
    "iso:country":"US",
    "sg:address":"10523 SE 32nd St",
    "sg:city":"Bellevue",
    "sg:classifiers":[
        {
            "category":"Wholesale",
            "subcategory":"Books, Periodicals, & Newspapers",
            "type":"Manufacturing & Wholesale Goods"
        }
    ],
    "sg:phone":"+1 425 451 9339",
    "sg:postcode":"98004",
    "sg:province":"WA",
    "sg:tags":[
        "publisher",
        "book"
    ],
    "wof:name":"Aspen Needleworks",
    "wof:placetype":"venue"
},
  "geometry": {"coordinates":[-122.200064,47.582033],"type":"Point"}
}