{
  "type": "Feature",
  "properties": {
    "addr:full":"29063 Beach Dr NE Poulsbo WA 98370",
    "addr:housenumber":"29063",
    "addr:postcode":"98370",
    "addr:street":"Beach Dr Ne",
    "iso:country":"US",
    "sg:address":"29063 Beach Dr NE",
    "sg:city":"Poulsbo",
    "sg:classifiers":[
        {
            "category":"Professional",
            "subcategory":"Business Services",
            "type":"Services"
        }
    ],
    "sg:phone":"+1 360 598 1621",
    "sg:postcode":"98370",
    "sg:province":"WA",
    "wof:name":"Bruces Enterprises Inc",
    "wof:placetype":"venue"
},
  "geometry": {"coordinates":[-122.64037,47.82861],"type":"Point"}
}