{
  "type": "Feature",
  "properties": {
    "addr:full":"1707 Edmonds Ave SE Renton WA 98058",
    "addr:housenumber":"1707",
    "addr:postcode":"98058",
    "addr:street":"Edmonds Ave Se",
    "iso:country":"US",
    "sg:address":"1707 Edmonds Ave SE",
    "sg:city":"Renton",
    "sg:classifiers":[
        {
            "category":"Place Of Worship",
            "subcategory":"Church",
            "type":"Public Place"
        },
        {
            "category":"Place Of Worship",
            "type":"Public Place"
        }
    ],
    "sg:phone":"+1 425 226 3080",
    "sg:postcode":"98058",
    "sg:province":"WA",
    "sg:tags":[
        "testament",
        "churches-church",
        "christ-new",
        "christ"
    ],
    "sg:website":"http://www.uccrenton.org",
    "wof:name":"United Christian Church",
    "wof:placetype":"venue"
},
  "geometry": {"coordinates":[-122.18592599999999,47.46499],"type":"Point"}
}