{
  "type": "Feature",
  "properties": {
    "addr:full":"2423 E Spring St Seattle WA 98122",
    "addr:housenumber":"2423",
    "addr:postcode":"98122",
    "addr:street":"E Spring St",
    "iso:country":"US",
    "sg:address":"2423 E Spring St",
    "sg:city":"Seattle",
    "sg:classifiers":[
        {
            "category":"Social Services",
            "type":"Services"
        }
    ],
    "sg:phone":"+1 206 324 5460",
    "sg:postcode":"98122",
    "sg:province":"WA",
    "wof:name":"Phoenix Counseling Servic",
    "wof:placetype":"venue"
},
  "geometry": {"coordinates":[-122.300326,47.611498],"type":"Point"}
}