{
  "type": "Feature",
  "properties": {
    "addr:full":"190 E Main St Othello WA 99344",
    "addr:housenumber":"190",
    "addr:postcode":"99344",
    "addr:street":"E Main St",
    "iso:country":"US",
    "sg:address":"190 E Main St",
    "sg:city":"Othello",
    "sg:classifiers":[
        {
            "category":"Professional",
            "subcategory":"Lawyer & Legal Services",
            "type":"Services"
        }
    ],
    "sg:phone":"+1 509 488 3303",
    "sg:postcode":"99344",
    "sg:province":"WA",
    "sg:tags":[
        "attorney",
        "practice"
    ],
    "wof:name":"Felice Stephen J",
    "wof:placetype":"venue"
},
  "geometry": {"coordinates":[-119.172628,46.826171],"type":"Point"}
}