{
  "type": "Feature",
  "properties": {
    "addr:full":"505 SW 12th St Renton WA 98057",
    "addr:housenumber":"505",
    "addr:postcode":"98057",
    "addr:street":"Sw 12Th St",
    "iso:country":"US",
    "sg:address":"505 SW 12th St",
    "sg:city":"Renton",
    "sg:classifiers":[
        {
            "category":"Wholesale",
            "subcategory":"Construction Materials",
            "type":"Manufacturing & Wholesale Goods"
        }
    ],
    "sg:phone":"+1 425 255 8753",
    "sg:postcode":"98057",
    "sg:province":"WA",
    "sg:tags":[
        "terrazzo"
    ],
    "wof:name":"General Terrazzo & Tile Co.",
    "wof:placetype":"venue"
},
  "geometry": {"coordinates":[-122.22341,47.469025],"type":"Point"}
}