{
  "type": "Feature",
  "properties": {
    "addr:full":"10114 417th St E Eatonville WA 98328",
    "addr:housenumber":"10114",
    "addr:postcode":"98328",
    "addr:street":"417Th St E",
    "iso:country":"US",
    "sg:address":"10114 417th St E",
    "sg:city":"Eatonville",
    "sg:classifiers":[
        {
            "category":"Retail",
            "subcategory":"Auto Repair",
            "type":"Services"
        }
    ],
    "sg:phone":"+1 360 832 4870",
    "sg:postcode":"98328",
    "sg:province":"WA",
    "sg:tags":[
        "general"
    ],
    "wof:name":"Dg Ranch",
    "wof:placetype":"venue"
},
  "geometry": {"coordinates":[-122.298394,46.877392],"type":"Point"}
}