{
  "type": "Feature",
  "properties": {
    "addr:full":"2803 W Washington Ave Yakima WA 98903",
    "addr:housenumber":"2803",
    "addr:postcode":"98903",
    "addr:street":"W Washington Ave",
    "iso:country":"US",
    "sg:address":"2803 W Washington Ave",
    "sg:city":"Yakima",
    "sg:classifiers":[
        {
            "category":"Building & Trades",
            "subcategory":"Landscaping Services",
            "type":"Services"
        }
    ],
    "sg:phone":"+1 509 945 1141",
    "sg:postcode":"98903",
    "sg:province":"WA",
    "sg:tags":[
        "lawn",
        "maintenance",
        "grounds"
    ],
    "wof:name":"New Horizons Tree Trimming",
    "wof:placetype":"venue"
},
  "geometry": {"coordinates":[-120.556624,46.574445],"type":"Point"}
}