{
  "type": "Feature",
  "properties": {
    "addr:full":"1550 Thompson Dr Bremerton WA 98337",
    "addr:housenumber":"1550",
    "addr:postcode":"98337",
    "addr:street":"Thompson Dr",
    "iso:country":"US",
    "sg:address":"1550 Thompson Dr",
    "sg:city":"Bremerton",
    "sg:classifiers":[
        {
            "category":"Home & Garden",
            "subcategory":"Building Materials",
            "type":"Retail Goods"
        }
    ],
    "sg:phone":"+1 360 479 2558",
    "sg:postcode":"98337",
    "sg:province":"WA",
    "wof:name":"Glass & Mirror Outfitters",
    "wof:placetype":"venue"
},
  "geometry": {"coordinates":[-122.643304,47.577148],"type":"Point"}
}