{
  "type": "Feature",
  "properties": {
    "addr:full":"4502 14th Ave NW Seattle WA 98107",
    "addr:housenumber":"4502",
    "addr:postcode":"98107",
    "addr:street":"14Th Ave Nw",
    "iso:country":"US",
    "sg:address":"4502 14th Ave NW",
    "sg:city":"Seattle",
    "sg:classifiers":[
        {
            "category":"Farming",
            "subcategory":"Fish & Marine Products",
            "type":"Manufacturing & Wholesale Goods"
        },
        {
            "category":"Food & Beverages",
            "subcategory":"Meat & Fish",
            "type":"Retail Goods"
        }
    ],
    "sg:phone":"+1 206 545 9501",
    "sg:postcode":"98107",
    "sg:province":"WA",
    "sg:tags":[
        "hatchery",
        "seafood-wholesale"
    ],
    "wof:name":"Baranof Fisheries",
    "wof:placetype":"venue"
},
  "geometry": {"coordinates":[-122.37359499999999,47.66147],"type":"Point"}
}