{
  "type": "Feature",
  "properties": {
    "addr:full":"29116 40th Ave S Roy WA 98580",
    "addr:housenumber":"29116",
    "addr:postcode":"98580",
    "addr:street":"40Th Ave S Roy",
    "iso:country":"US",
    "sg:address":"29116 40th Ave S",
    "sg:city":"Roy",
    "sg:classifiers":[
        {
            "category":"Recreation",
            "type":"Entertainment"
        }
    ],
    "sg:phone":"+1 253 843 1252",
    "sg:postcode":"98580",
    "sg:province":"WA",
    "wof:name":"Silverbrook Stables",
    "wof:placetype":"venue"
},
  "geometry": {"coordinates":[-122.48405200000001,46.99236],"type":"Point"}
}