{
  "type": "Feature",
  "properties": {
    "addr:full":"130 SW 112th St Seattle WA 98146",
    "addr:housenumber":"130",
    "addr:postcode":"98146",
    "addr:street":"Sw 112Th St",
    "iso:country":"US",
    "sg:address":"130 SW 112th St",
    "sg:city":"Seattle",
    "sg:classifiers":[
        {
            "category":"Real Estate",
            "subcategory":"Real Estate Services",
            "type":"Services"
        }
    ],
    "sg:phone":"+1 866 308 2658",
    "sg:postcode":"98146",
    "sg:province":"WA",
    "sg:tags":[
        "apartment",
        "management",
        "rental",
        "finder"
    ],
    "sg:website":"http://www.forrent.com/apartment-community-profile/1007974.php?cmp=CAC-CSearchProfile",
    "wof:name":"Garden Pointe",
    "wof:placetype":"venue"
},
  "geometry": {"coordinates":[-122.335482,47.503104],"type":"Point"}
}