{
  "type": "Feature",
  "properties": {
    "addr:full":"3393 Alm Rd Everson WA 98247",
    "addr:housenumber":"3393",
    "addr:postcode":"98247",
    "addr:street":"Alm Rd",
    "iso:country":"US",
    "sg:address":"3393 Alm Rd",
    "sg:city":"Everson",
    "sg:classifiers":[
        {
            "category":"Building & Trades",
            "subcategory":"Construction",
            "type":"Services"
        }
    ],
    "sg:phone":"+1 360 966 5306",
    "sg:postcode":"98247",
    "sg:province":"WA",
    "sg:tags":[
        "floor",
        "laying",
        "contractor"
    ],
    "wof:name":"Ron Gray Carpet Service",
    "wof:placetype":"venue"
},
  "geometry": {"coordinates":[-122.304695,48.942001],"type":"Point"}
}