{
  "type": "Feature",
  "properties": {
    "addr:full":"3100 NW Bucklin Hill Rd Ste 114 Silverdale WA 98383",
    "addr:housenumber":"3100;114",
    "addr:postcode":"98383",
    "addr:street":"Nw Bucklin Hill Rd Ste",
    "iso:country":"US",
    "sg:address":"3100 NW Bucklin Hill Rd Ste 114",
    "sg:city":"Silverdale",
    "sg:classifiers":[
        {
            "category":"Airline",
            "type":"Transportation"
        },
        {
            "category":"Travel",
            "subcategory":"Travel Agent",
            "type":"Entertainment"
        },
        {
            "category":"Marine",
            "type":"Transportation"
        }
    ],
    "sg:phone":"+1 360 698 1938",
    "sg:postcode":"98383",
    "sg:province":"WA",
    "sg:tags":[
        "ticket",
        "agency",
        "cruise"
    ],
    "wof:name":"Classic Journeys Inc",
    "wof:placetype":"venue"
},
  "geometry": {"coordinates":[-122.691524,47.650509],"type":"Point"}
}