{
  "type": "Feature",
  "properties": {
    "addr:full":"525 N 3rd Ave Pasco WA 99301",
    "addr:housenumber":"525",
    "addr:postcode":"99301",
    "addr:street":"N 3Rd Ave",
    "iso:country":"US",
    "sg:address":"525 N 3rd Ave",
    "sg:city":"Pasco",
    "sg:classifiers":[
        {
            "category":"Social Services",
            "type":"Services"
        },
        {
            "category":"Government",
            "subcategory":"Office",
            "type":"Public Place"
        }
    ],
    "sg:phone":"+1 509 545 3401",
    "sg:postcode":"99301",
    "sg:province":"WA",
    "sg:tags":[
        "township",
        "government-city",
        "village"
    ],
    "wof:name":"City of Pasco Finance Division",
    "wof:placetype":"venue"
},
  "geometry": {"coordinates":[-119.092483,46.235119],"type":"Point"}
}