{
  "type": "Feature",
  "properties": {
    "addr:full":"13817 9th Pl S Burien WA 98168",
    "addr:housenumber":"13817",
    "addr:postcode":"98168",
    "addr:street":"9Th Pl S Burien",
    "iso:country":"US",
    "sg:address":"13817 9th Pl S",
    "sg:city":"Burien",
    "sg:classifiers":[
        {
            "category":"Building & Trades",
            "subcategory":"Locksmith",
            "type":"Services"
        }
    ],
    "sg:phone":"+1 206 777 1059",
    "sg:postcode":"98168",
    "sg:province":"WA",
    "sg:tags":[
        "key"
    ],
    "wof:name":"1 24 7 A Locks Service",
    "wof:placetype":"venue"
},
  "geometry": {"coordinates":[-122.321572,47.479613],"type":"Point"}
}