{
  "type": "Feature",
  "properties": {
    "iso:country":"US",
    "sg:address":"8702 N Division St",
    "sg:city":"Spokane",
    "sg:classifiers":[
        {
            "category":"Government",
            "subcategory":"Office",
            "type":"Public Place"
        }
    ],
    "sg:phone":"+1 509 625 5347",
    "sg:postcode":"99218",
    "sg:province":"WA",
    "sg:tags":[
        "wildlife"
    ],
    "wof:name":"Fish & Wildlife Wash Dept",
    "wof:placetype":"venue"
},
  "geometry": {"coordinates":[-117.411359,47.739566],"type":"Point"}
}