{
  "type": "Feature",
  "properties": {
    "addr:full":"480 Ryan Rd Buckley WA 98321",
    "addr:housenumber":"480",
    "addr:postcode":"98321",
    "addr:street":"Ryan Rd",
    "iso:country":"US",
    "sg:address":"480 Ryan Rd",
    "sg:city":"Buckley",
    "sg:classifiers":[
        {
            "category":"Personal",
            "type":"Services"
        }
    ],
    "sg:phone":"+1 360 829 1421",
    "sg:postcode":"98321",
    "sg:province":"WA",
    "wof:name":"Paula Muth Massage Therapy",
    "wof:placetype":"venue"
},
  "geometry": {"coordinates":[-122.02966000000001,47.156553],"type":"Point"}
}