{
  "type": "Feature",
  "properties": {
    "addr:full":"796 State Hwy 28 W Soap Lake WA 98851",
    "addr:housenumber":"796",
    "addr:postcode":"98851",
    "addr:street":"State Hwy 28 W Soap",
    "iso:country":"US",
    "sg:address":"796 State Hwy 28 W",
    "sg:city":"Soap Lake",
    "sg:classifiers":[
        {
            "category":"Food & Beverages",
            "subcategory":"Fruits & Vegetables",
            "type":"Retail Goods"
        }
    ],
    "sg:phone":"+1 509 246 0174",
    "sg:postcode":"98851",
    "sg:province":"WA",
    "wof:name":"Gallaway Fruit & Produce",
    "wof:placetype":"venue"
},
  "geometry": {"coordinates":[-119.528246,47.343936],"type":"Point"}
}