{
  "type": "Feature",
  "properties": {
    "addr:full":"18102 80th Ave NE Kenmore WA 98028",
    "addr:housenumber":"18102",
    "addr:postcode":"98028",
    "addr:street":"80Th Ave Ne",
    "iso:country":"US",
    "sg:address":"18102 80th Ave NE",
    "sg:city":"Kenmore",
    "sg:classifiers":[
        {
            "category":"Shopping",
            "type":"Retail Goods"
        }
    ],
    "sg:phone":"+1 425 402 6097",
    "sg:postcode":"98028",
    "sg:province":"WA",
    "sg:tags":[
        "merchandise"
    ],
    "wof:name":"Hills Pet",
    "wof:placetype":"venue"
},
  "geometry": {"coordinates":[-122.233599,47.758416],"type":"Point"}
}