{
  "type": "Feature",
  "properties": {
    "addr:full":"7615 Fair Oaks Rd SE Olympia WA 98513",
    "addr:housenumber":"7615",
    "addr:postcode":"olympia;98513",
    "addr:street":"Fair Oaks Rd Se",
    "iso:country":"US",
    "sg:address":"7615 Fair Oaks Rd SE",
    "sg:city":"Olympia",
    "sg:classifiers":[
        {
            "category":"Social Services",
            "type":"Services"
        }
    ],
    "sg:phone":"+1 360 456 8557",
    "sg:postcode":"98513",
    "sg:province":"WA",
    "wof:name":"Cobbs Collectibles",
    "wof:placetype":"venue"
},
  "geometry": {"coordinates":[-122.785753,46.995078],"type":"Point"}
}