{
  "type": "Feature",
  "properties": {
    "iso:country":"US",
    "sg:address":"11002 Pacific Hwy SW",
    "sg:city":"Tacoma",
    "sg:classifiers":[
        {
            "category":"Wholesale",
            "subcategory":"Durable Goods & Equipment",
            "type":"Manufacturing & Wholesale Goods"
        }
    ],
    "sg:phone":"+1 253 984 8592",
    "sg:postcode":"98499",
    "sg:province":"WA",
    "sg:tags":[
        "exporter"
    ],
    "wof:name":"Jk International Corp",
    "wof:placetype":"venue"
},
  "geometry": {"coordinates":[-122.49091900000001,47.157321],"type":"Point"}
}