{
  "type": "Feature",
  "properties": {
    "addr:full":"1360 Sunset Ave Ferndale WA 98248",
    "addr:housenumber":"1360",
    "addr:postcode":"98248",
    "addr:street":"Sunset Ave",
    "iso:country":"US",
    "sg:address":"1360 Sunset Ave",
    "sg:city":"Ferndale",
    "sg:classifiers":[
        {
            "category":"Shopping",
            "type":"Retail Goods"
        }
    ],
    "sg:phone":"+1 360 384 1858",
    "sg:postcode":"98248",
    "sg:province":"WA",
    "sg:tags":[
        "prosthetic",
        "devices"
    ],
    "wof:name":"Cascade Prosthetics Orthotics",
    "wof:placetype":"venue"
},
  "geometry": {"coordinates":[-122.55609,48.822636],"type":"Point"}
}