{
  "type": "Feature",
  "properties": {
    "addr:full":"1470 20th Ave Seattle WA 98122",
    "addr:housenumber":"1470",
    "addr:postcode":"98122",
    "addr:street":"20Th Ave",
    "iso:country":"US",
    "sg:address":"1470 20th Ave",
    "sg:city":"Seattle",
    "sg:classifiers":[
        {
            "category":"Personal",
            "subcategory":"Beauty Salon",
            "type":"Services"
        }
    ],
    "sg:phone":"+1 206 322 3613",
    "sg:postcode":"98122",
    "sg:province":"WA",
    "sg:tags":[
        "shop"
    ],
    "wof:name":"Virgies Beauty Salon",
    "wof:placetype":"venue"
},
  "geometry": {"coordinates":[-122.30612600000001,47.614438],"type":"Point"}
}