{
  "type": "Feature",
  "properties": {
    "addr:full":"2367 Back Forty Ln NW Poulsbo WA 98370",
    "addr:housenumber":"2367",
    "addr:postcode":"98370",
    "addr:street":"Back Forty Ln Nw",
    "iso:country":"US",
    "sg:address":"2367 Back Forty Ln NW",
    "sg:city":"Poulsbo",
    "sg:classifiers":[
        {
            "category":"Wholesale",
            "subcategory":"Plants",
            "type":"Manufacturing & Wholesale Goods"
        }
    ],
    "sg:phone":"+1 360 779 2288",
    "sg:postcode":"98370",
    "sg:province":"WA",
    "sg:tags":[
        "supply"
    ],
    "wof:name":"Mountainview Gardens",
    "wof:placetype":"venue"
},
  "geometry": {"coordinates":[-122.68326399999999,47.750353],"type":"Point"}
}