{
  "type": "Feature",
  "properties": {
    "addr:full":"744 Seahorse Ave NE Ocean Shores WA 98569",
    "addr:housenumber":"744",
    "addr:postcode":"98569",
    "addr:street":"Seahorse Ave Ne",
    "iso:country":"US",
    "sg:address":"744 Seahorse Ave NE",
    "sg:city":"Ocean Shores",
    "sg:classifiers":[
        {
            "category":"Building & Trades",
            "subcategory":"Cleaning & Sanitation",
            "type":"Services"
        }
    ],
    "sg:phone":"+1 360 289 3243",
    "sg:postcode":"98569",
    "sg:province":"WA",
    "sg:tags":[
        "janitor"
    ],
    "wof:name":"North Beach Home Maintenance",
    "wof:placetype":"venue"
},
  "geometry": {"coordinates":[-124.159716,47.01079],"type":"Point"}
}