{
  "type": "Feature",
  "properties": {
    "addr:full":"16184 Penn Rd Mt Vernon WA 98273",
    "addr:housenumber":"16184",
    "addr:postcode":"98273",
    "addr:street":"Penn Rd",
    "iso:country":"US",
    "sg:address":"16184 Penn Rd",
    "sg:city":"Mt Vernon",
    "sg:classifiers":[
        {
            "category":"Professional",
            "subcategory":"Lawyer & Legal Services",
            "type":"Services"
        }
    ],
    "sg:phone":"+1 360 424 7108",
    "sg:postcode":"98273",
    "sg:province":"WA",
    "sg:tags":[
        "attorney"
    ],
    "wof:name":"Fresh Start Bankruptcy",
    "wof:placetype":"venue"
},
  "geometry": {"coordinates":[-122.367822,48.41151],"type":"Point"}
}