{
  "type": "Feature",
  "properties": {
    "addr:full":"27811 50th Pl S Auburn WA 98001",
    "addr:housenumber":"27811",
    "addr:postcode":"98001",
    "addr:street":"50Th Pl S",
    "iso:country":"US",
    "sg:address":"27811 50th Pl S",
    "sg:city":"Auburn",
    "sg:classifiers":[
        {
            "category":"Personal",
            "subcategory":"Beauty Salon",
            "type":"Services"
        }
    ],
    "sg:phone":"+1 206 227 5152",
    "sg:postcode":"98001",
    "sg:province":"WA",
    "sg:tags":[
        "shop"
    ],
    "wof:name":"Nathalie Beauty Salon",
    "wof:placetype":"venue"
},
  "geometry": {"coordinates":[-122.27135699999999,47.352284],"type":"Point"}
}