{
  "type": "Feature",
  "properties": {
    "addr:full":"909 N 18th Ave Yakima WA 98902",
    "addr:housenumber":"909",
    "addr:postcode":"98902",
    "addr:street":"N 18Th Ave",
    "iso:country":"US",
    "sg:address":"909 N 18th Ave",
    "sg:city":"Yakima",
    "sg:classifiers":[
        {
            "category":"Building & Trades",
            "subcategory":"Plumbing",
            "type":"Services"
        }
    ],
    "sg:phone":"+1 509 248 3883",
    "sg:postcode":"98902",
    "sg:province":"WA",
    "sg:tags":[
        "heating",
        "contractor"
    ],
    "wof:name":"Johnson Mechanical Corp",
    "wof:placetype":"venue"
},
  "geometry": {"coordinates":[-120.533062,46.613403],"type":"Point"}
}