{
  "type": "Feature",
  "properties": {
    "addr:full":"806 E 8th St Port Angeles WA 98362",
    "addr:housenumber":"806",
    "addr:postcode":"98362",
    "addr:street":"E 8Th St",
    "iso:country":"US",
    "sg:address":"806 E 8th St",
    "sg:city":"Port Angeles",
    "sg:classifiers":[
        {
            "category":"Health Services",
            "subcategory":"Doctor",
            "type":"Services"
        }
    ],
    "sg:phone":"+1 360 452 7666",
    "sg:postcode":"98362",
    "sg:province":"WA",
    "sg:tags":[
        "dentist"
    ],
    "wof:name":"Gerald Biss Family Dentistry",
    "wof:placetype":"venue"
},
  "geometry": {"coordinates":[-123.426244,48.107621],"type":"Point"}
}