{
  "type": "Feature",
  "properties": {
    "addr:full":"1500 NE 112th Ave Vancouver WA 98684",
    "addr:housenumber":"1500",
    "addr:postcode":"98684",
    "addr:street":"Ne 112Th Ave",
    "iso:country":"US",
    "sg:address":"1500 NE 112th Ave",
    "sg:city":"Vancouver",
    "sg:classifiers":[
        {
            "category":"Social Services",
            "type":"Services"
        }
    ],
    "sg:phone":"+1 360 892 9050",
    "sg:postcode":"98684",
    "sg:province":"WA",
    "sg:tags":[
        "organization",
        "welfare"
    ],
    "sg:website":"www.salvationarmy.com",
    "wof:name":"Salvation Army",
    "wof:placetype":"venue"
},
  "geometry": {"coordinates":[-122.55791600000001,45.632763],"type":"Point"}
}