{
  "type": "Feature",
  "properties": {
    "addr:full":"13819 51st Ave NW Gig Harbor WA 98332",
    "addr:housenumber":"13819",
    "addr:postcode":"98332",
    "addr:street":"51St Ave Nw",
    "iso:country":"US",
    "sg:address":"13819 51st Ave NW",
    "sg:city":"Gig Harbor",
    "sg:phone":"+1 253 278 6319",
    "sg:postcode":"98332",
    "sg:province":"WA",
    "sg:tags":[
        "automotive",
        "lubricant"
    ],
    "wof:name":"Jrp Sales",
    "wof:placetype":"venue"
},
  "geometry": {"coordinates":[-122.60591100000001,47.388869],"type":"Point"}
}