{
  "type": "Feature",
  "properties": {
    "addr:full":"3640 Factoria Blvd SE Ste E Bellevue WA 98006",
    "addr:housenumber":"3640",
    "addr:postcode":"98006",
    "addr:street":"Factoria Blvd Se Ste E",
    "iso:country":"US",
    "sg:address":"3640 Factoria Blvd SE Ste E",
    "sg:city":"Bellevue",
    "sg:classifiers":[
        {
            "category":"Food & Beverages",
            "subcategory":"Bakery",
            "type":"Retail Goods"
        }
    ],
    "sg:phone":"+1 425 643 0292",
    "sg:postcode":"98006",
    "sg:province":"WA",
    "sg:tags":[
        "sandwich"
    ],
    "wof:name":"Sacks Gourmet Sandwiches",
    "wof:placetype":"venue"
},
  "geometry": {"coordinates":[-122.168999,47.578899],"type":"Point"}
}