{
  "type": "Feature",
  "properties": {
    "addr:full":"1969 W Hampton Rd Othello WA 99344",
    "addr:housenumber":"1969",
    "addr:postcode":"99344",
    "addr:street":"W Hampton Rd",
    "iso:country":"US",
    "sg:address":"1969 W Hampton Rd",
    "sg:city":"Othello",
    "sg:classifiers":[
        {
            "category":"Retail",
            "subcategory":"Veterinary Services",
            "type":"Services"
        }
    ],
    "sg:phone":"+1 509 488 3569",
    "sg:postcode":"99344",
    "sg:province":"WA",
    "sg:tags":[
        "practice",
        "livestock"
    ],
    "wof:name":"Veterinary Medical Clinic PS",
    "wof:placetype":"venue"
},
  "geometry": {"coordinates":[-119.152976,46.782405],"type":"Point"}
}