{
  "type": "Feature",
  "properties": {
    "addr:full":"213 N Bend Blvd N North Bend WA 98045",
    "addr:housenumber":"213",
    "addr:postcode":"98045",
    "addr:street":"N Bend Blvd N",
    "iso:country":"US",
    "sg:address":"213 N Bend Blvd N",
    "sg:city":"North Bend",
    "sg:classifiers":[
        {
            "category":"Shopping",
            "subcategory":"Florist",
            "type":"Retail Goods"
        }
    ],
    "sg:phone":"+1 425 888 2900",
    "sg:postcode":"98045",
    "sg:province":"WA",
    "wof:name":"Alpine Blossom Florist",
    "wof:placetype":"venue"
},
  "geometry": {"coordinates":[-121.787481,47.494943],"type":"Point"}
}