{
  "type": "Feature",
  "properties": {
    "addr:full":"915 SE 164th Ave Vancouver WA 98683",
    "addr:housenumber":"915",
    "addr:postcode":"98683",
    "addr:street":"Se 164Th Ave",
    "iso:country":"US",
    "sg:address":"915 SE 164th Ave",
    "sg:city":"Vancouver",
    "sg:classifiers":[
        {
            "category":"Restaurant",
            "type":"Food & Drink"
        }
    ],
    "sg:menulink":"http://www.allmenus.com/wa/vancouver/51873-chipotle/menu/",
    "sg:phone":"+1 360 256 2355",
    "sg:postcode":"98683",
    "sg:province":"WA",
    "sg:tags":[
        "mexican"
    ],
    "wof:name":"Chipotle",
    "wof:placetype":"venue"
},
  "geometry": {"coordinates":[-122.504189,45.615295],"type":"Point"}
}