{
  "type": "Feature",
  "properties": {
    "addr:full":"2501 Queets Ave Hoquiam WA 98550",
    "addr:housenumber":"2501",
    "addr:postcode":"98550",
    "addr:street":"Queets Ave",
    "iso:country":"US",
    "sg:address":"2501 Queets Ave",
    "sg:city":"Hoquiam",
    "sg:classifiers":[
        {
            "category":"Wholesale",
            "subcategory":"Non-durable Goods",
            "type":"Manufacturing & Wholesale Goods"
        }
    ],
    "sg:phone":"+1 360 538 0883",
    "sg:postcode":"98550",
    "sg:province":"WA",
    "wof:name":"Myvi",
    "wof:placetype":"venue"
},
  "geometry": {"coordinates":[-123.867563,46.97801],"type":"Point"}
}