{
  "type": "Feature",
  "properties": {
    "addr:full":"15615 272nd Ave E Buckley WA 98321",
    "addr:housenumber":"15615",
    "addr:postcode":"98321",
    "addr:street":"272Nd Ave E",
    "iso:country":"US",
    "sg:address":"15615 272nd Ave E",
    "sg:city":"Buckley",
    "sg:classifiers":[
        {
            "category":"Shopping",
            "subcategory":"Antiques",
            "type":"Retail Goods"
        }
    ],
    "sg:phone":"+1 360 886 8142",
    "sg:postcode":"98321",
    "sg:province":"WA",
    "sg:tags":[
        "dealers-wholesale"
    ],
    "wof:name":"Samuel Compton",
    "wof:placetype":"venue"
},
  "geometry": {"coordinates":[-122.067986,47.116195],"type":"Point"}
}