{
  "type": "Feature",
  "properties": {
    "addr:full":"6300 9th Ave NE Seattle WA 98115",
    "addr:housenumber":"6300",
    "addr:postcode":"98115",
    "addr:street":"9Th Ave Ne",
    "iso:country":"US",
    "sg:address":"6300 9th Ave NE",
    "sg:city":"Seattle",
    "sg:classifiers":[
        {
            "category":"Health Services",
            "subcategory":"Doctor",
            "type":"Services"
        }
    ],
    "sg:phone":"+1 206 524 0863",
    "sg:postcode":"98115",
    "sg:province":"WA",
    "wof:name":"Simon Michelle Nd PHD",
    "wof:placetype":"venue"
},
  "geometry": {"coordinates":[-122.318001,47.674301],"type":"Point"}
}