{
  "type": "Feature",
  "properties": {
    "addr:full":"915 E Rainier St Othello WA 99344",
    "addr:housenumber":"915",
    "addr:postcode":"99344",
    "addr:street":"E Rainier St",
    "iso:country":"US",
    "sg:address":"915 E Rainier St",
    "sg:city":"Othello",
    "sg:classifiers":[
        {
            "category":"Place Of Worship",
            "subcategory":"Church",
            "type":"Public Place"
        },
        {
            "category":"Place Of Worship",
            "type":"Public Place"
        },
        {
            "category":"Organizations",
            "subcategory":"Religious Organization",
            "type":"Services"
        }
    ],
    "sg:phone":"+1 509 488 2208",
    "sg:postcode":"99344",
    "sg:province":"WA",
    "sg:tags":[
        "churches-interdenominational",
        "churches-various",
        "denomination"
    ],
    "wof:name":"Othello Christian Church",
    "wof:placetype":"venue"
},
  "geometry": {"coordinates":[-119.16180199999999,46.831989],"type":"Point"}
}