{
  "type": "Feature",
  "properties": {
    "addr:full":"6419 Lakewood Dr W Tacoma WA 98467",
    "addr:housenumber":"6419",
    "addr:postcode":"98467",
    "addr:street":"Lakewood Dr W",
    "iso:country":"US",
    "sg:address":"6419 Lakewood Dr W",
    "sg:city":"Tacoma",
    "sg:classifiers":[
        {
            "category":"Real Estate",
            "subcategory":"Real Estate Agent",
            "type":"Services"
        }
    ],
    "sg:phone":"+1 253 564 3230",
    "sg:postcode":"98467",
    "sg:province":"WA",
    "sg:tags":[
        "appraiser"
    ],
    "wof:name":"Strickland Heischman & Hoss",
    "wof:placetype":"venue"
},
  "geometry": {"coordinates":[-122.508602,47.198339],"type":"Point"}
}