{
  "type": "Feature",
  "properties": {
    "addr:full":"6312 E F St Tacoma WA 98404",
    "addr:housenumber":"6312",
    "addr:postcode":"98404",
    "addr:street":"E F St",
    "iso:country":"US",
    "sg:address":"6312 E F St",
    "sg:city":"Tacoma",
    "sg:classifiers":[
        {
            "category":"Organizations",
            "subcategory":"Religious Organization",
            "type":"Services"
        }
    ],
    "sg:phone":"+1 253 472 6343",
    "sg:postcode":"98404",
    "sg:province":"WA",
    "sg:tags":[
        "church"
    ],
    "wof:name":"Calvary United Methodist Chr",
    "wof:placetype":"venue"
},
  "geometry": {"coordinates":[-122.42364499999999,47.199169],"type":"Point"}
}