{
  "type": "Feature",
  "properties": {
    "addr:full":"2821 S Walden St Seattle WA 98144",
    "addr:housenumber":"2821",
    "addr:postcode":"98144",
    "addr:street":"S Walden St",
    "iso:country":"US",
    "sg:address":"2821 S Walden St",
    "sg:city":"Seattle",
    "sg:classifiers":[
        {
            "category":"Health Services",
            "subcategory":"Nursing And Care Facility",
            "type":"Services"
        }
    ],
    "sg:phone":"+1 206 725 2800",
    "sg:postcode":"98144",
    "sg:province":"WA",
    "sg:tags":[
        "skilled"
    ],
    "wof:name":"Washington Center",
    "wof:placetype":"venue"
},
  "geometry": {"coordinates":[-122.29526300000001,47.572544],"type":"Point"}
}