{
  "type": "Feature",
  "properties": {
    "addr:full":"1431 Market St Kirkland WA 98033",
    "addr:housenumber":"1431",
    "addr:postcode":"98033",
    "addr:street":"Market St",
    "iso:country":"US",
    "sg:address":"1431 Market St",
    "sg:city":"Kirkland",
    "sg:classifiers":[
        {
            "category":"Food & Beverages",
            "subcategory":"Groceries & Convenience Stores",
            "type":"Retail Goods"
        }
    ],
    "sg:phone":"+1 425 889 5977",
    "sg:postcode":"98033",
    "sg:province":"WA",
    "wof:name":"Zip Market",
    "wof:placetype":"venue"
},
  "geometry": {"coordinates":[-122.209999,47.687302],"type":"Point"}
}