{
  "type": "Feature",
  "properties": {
    "addr:full":"2220 NW Bucklin Hill Rd Silverdale WA 98383",
    "addr:housenumber":"2220",
    "addr:postcode":"98383",
    "addr:street":"Nw Bucklin Hill Rd",
    "iso:country":"US",
    "sg:address":"2220 NW Bucklin Hill Rd",
    "sg:city":"Silverdale",
    "sg:classifiers":[
        {
            "category":"Retail",
            "subcategory":"Laundry & Dry Cleaning",
            "type":"Services"
        }
    ],
    "sg:phone":"+1 360 692 8616",
    "sg:postcode":"98383",
    "sg:province":"WA",
    "sg:tags":[
        "drycleaning",
        "plant"
    ],
    "wof:name":"Ultra Custom Cleaners",
    "wof:placetype":"venue"
},
  "geometry": {"coordinates":[-122.68198099999999,47.650619],"type":"Point"}
}