{
  "type": "Feature",
  "properties": {
    "iso:country":"US",
    "sg:address":"6691 Heron Way",
    "sg:city":"Nine Mile Falls",
    "sg:classifiers":[
        {
            "category":"Building & Trades",
            "subcategory":"Landscaping Services",
            "type":"Services"
        }
    ],
    "sg:phone":"+1 509 276 6332",
    "sg:postcode":"99026",
    "sg:province":"WA",
    "wof:name":"Glesk Gardening Service",
    "wof:placetype":"venue"
},
  "geometry": {"coordinates":[-117.661244,47.887475],"type":"Point"}
}