{
  "type": "Feature",
  "properties": {
    "addr:full":"21007 SE 42nd St Sammamish WA 98075",
    "addr:postcode":"21007;98075",
    "addr:street":"Se 42Nd St",
    "iso:country":"US",
    "sg:address":"21007 SE 42nd St",
    "sg:city":"Sammamish",
    "sg:classifiers":[
        {
            "category":"Wholesale",
            "subcategory":"Electrical",
            "type":"Manufacturing & Wholesale Goods"
        }
    ],
    "sg:phone":"+1 425 391 3550",
    "sg:postcode":"98075",
    "sg:province":"WA",
    "wof:name":"Nca Northwest",
    "wof:placetype":"venue"
},
  "geometry": {"coordinates":[-122.059871,47.570161],"type":"Point"}
}