{
  "type": "Feature",
  "properties": {
    "iso:country":"US",
    "sg:address":"808 S 7th Ave",
    "sg:city":"Yakima",
    "sg:classifiers":[
        {
            "category":"Autos & Motor Vehicles",
            "subcategory":"Motorcycle Sales",
            "type":"Retail Goods"
        },
        {
            "category":"Manufacturing",
            "subcategory":"Motor Vehicles & Parts",
            "type":"Manufacturing & Wholesale Goods"
        }
    ],
    "sg:phone":"+1 509 453 6715",
    "sg:postcode":"98902",
    "sg:province":"WA",
    "sg:website":"www.firecreekacc.com",
    "wof:name":"Firecreek Accessories Inc",
    "wof:placetype":"venue"
},
  "geometry": {"coordinates":[-120.515451,46.590131],"type":"Point"}
}