{
  "type": "Feature",
  "properties": {
    "addr:full":"814 6th St Clarkston WA 99403",
    "addr:housenumber":"814",
    "addr:postcode":"99403",
    "addr:street":"6Th St",
    "iso:country":"US",
    "sg:address":"814 6th St",
    "sg:city":"Clarkston",
    "sg:classifiers":[
        {
            "category":"Organizations",
            "subcategory":"Community Association",
            "type":"Services"
        }
    ],
    "sg:phone":"+1 509 758 6292",
    "sg:postcode":"99403",
    "sg:province":"WA",
    "wof:name":"Lodge 751 - Lewis - Clark",
    "wof:placetype":"venue"
},
  "geometry": {"coordinates":[-117.04564499999999,46.414241],"type":"Point"}
}