{
  "type": "Feature",
  "properties": {
    "addr:full":"3902 SW 106th St Seattle WA 98146",
    "addr:housenumber":"3902",
    "addr:postcode":"98146",
    "addr:street":"Sw 106Th St",
    "iso:country":"US",
    "sg:address":"3902 SW 106th St",
    "sg:city":"Seattle",
    "sg:classifiers":[
        {
            "category":"Professional",
            "subcategory":"Business Services",
            "type":"Services"
        }
    ],
    "sg:phone":"+1 206 935 4961",
    "sg:postcode":"98146",
    "sg:province":"WA",
    "wof:name":"Akimibo Service",
    "wof:placetype":"venue"
},
  "geometry": {"coordinates":[-122.382885,47.508324],"type":"Point"}
}