{
  "type": "Feature",
  "properties": {
    "addr:full":"1600 E Jefferson St Seattle WA 98122",
    "addr:housenumber":"1600",
    "addr:postcode":"98122",
    "addr:street":"E Jefferson St",
    "iso:country":"US",
    "sg:address":"1600 E Jefferson St",
    "sg:city":"Seattle",
    "sg:classifiers":[
        {
            "category":"Health Services",
            "subcategory":"Doctor",
            "type":"Services"
        }
    ],
    "sg:phone":"+1 206 320 5685",
    "sg:postcode":"98122",
    "sg:province":"WA",
    "sg:tags":[
        "medical"
    ],
    "wof:name":"Teresa A Thornberg MD",
    "wof:placetype":"venue"
},
  "geometry": {"coordinates":[-122.31025099999999,47.606173],"type":"Point"}
}