{
  "type": "Feature",
  "properties": {
    "addr:full":"3238 23rd Ave W Seattle WA 98199",
    "addr:housenumber":"3238",
    "addr:postcode":"98199",
    "addr:street":"23Rd Ave W",
    "iso:country":"US",
    "sg:address":"3238 23rd Ave W",
    "sg:city":"Seattle",
    "sg:classifiers":[
        {
            "category":"Building & Trades",
            "subcategory":"Construction",
            "type":"Services"
        }
    ],
    "sg:phone":"+1 206 283 5553",
    "sg:postcode":"98199",
    "sg:province":"WA",
    "sg:tags":[
        "hanging",
        "contractor"
    ],
    "wof:name":"Pride In Painting",
    "wof:placetype":"venue"
},
  "geometry": {"coordinates":[-122.385902,47.649963],"type":"Point"}
}