{
  "type": "Feature",
  "properties": {
    "addr:full":"624 Kittitas St Wenatchee WA 98801",
    "addr:housenumber":"624",
    "addr:postcode":"98801",
    "addr:street":"Kittitas St",
    "iso:country":"US",
    "sg:address":"624 Kittitas St",
    "sg:city":"Wenatchee",
    "sg:classifiers":[
        {
            "category":"Wholesale",
            "subcategory":"Durable Goods & Equipment",
            "type":"Manufacturing & Wholesale Goods"
        }
    ],
    "sg:phone":"+1 509 663 4828",
    "sg:postcode":"98801",
    "sg:province":"WA",
    "wof:name":"Stonewall Audio",
    "wof:placetype":"venue"
},
  "geometry": {"coordinates":[-120.316323,47.416916],"type":"Point"}
}