{
  "type": "Feature",
  "properties": {
    "iso:country":"US",
    "sg:address":"10001 Mickelberry Rd NW",
    "sg:city":"Silverdale",
    "sg:classifiers":[
        {
            "category":"Professional",
            "type":"Services"
        }
    ],
    "sg:phone":"+1 360 307 9811",
    "sg:postcode":"98383",
    "sg:province":"WA",
    "sg:tags":[
        "establishment"
    ],
    "wof:name":"Llnen's 'n Things",
    "wof:placetype":"venue"
},
  "geometry": {"coordinates":[-122.68238599999999,47.657454],"type":"Point"}
}