{
  "type": "Feature",
  "properties": {
    "addr:full":"4843 Auto Center Way Bremerton WA 98312",
    "addr:housenumber":"4843",
    "addr:postcode":"98312",
    "addr:street":"Auto Center Way",
    "iso:country":"US",
    "sg:address":"4843 Auto Center Way",
    "sg:city":"Bremerton",
    "sg:classifiers":[
        {
            "category":"Professional",
            "subcategory":"Art Services",
            "type":"Services"
        },
        {
            "category":"Building & Trades",
            "subcategory":"Electrical",
            "type":"Services"
        }
    ],
    "sg:phone":"+1 360 373 1900",
    "sg:postcode":"98312",
    "sg:province":"WA",
    "sg:tags":[
        "consultant",
        "lighting",
        "designer",
        "electrician"
    ],
    "sg:website":"http://www.ahearnelectric.net",
    "wof:name":"Ahearn Electric",
    "wof:placetype":"venue"
},
  "geometry": {"coordinates":[-122.67840200000001,47.562727],"type":"Point"}
}