{
  "type": "Feature",
  "properties": {
    "addr:full":"16300 Christensen Rd Seattle WA 98188",
    "addr:postcode":"16300;98188",
    "addr:street":"Christensen Rd",
    "iso:country":"US",
    "sg:address":"16300 Christensen Rd",
    "sg:city":"Seattle",
    "sg:classifiers":[
        {
            "category":"Manufacturing",
            "subcategory":"Aerospace",
            "type":"Manufacturing & Wholesale Goods"
        },
        {
            "category":"Home & Garden",
            "subcategory":"Household Appliances",
            "type":"Retail Goods"
        }
    ],
    "sg:phone":"+1 206 835 9880",
    "sg:postcode":"98188",
    "sg:province":"WA",
    "sg:tags":[
        "equipment",
        "aircraft",
        "commercial",
        "mfg"
    ],
    "wof:name":"Fuji Industrial USA Inc",
    "wof:placetype":"venue"
},
  "geometry": {"coordinates":[-122.248548,47.457859],"type":"Point"}
}