{
  "type": "Feature",
  "properties": {
    "addr:full":"1095 Andover Park E Seattle WA 98188",
    "addr:housenumber":"1095",
    "addr:postcode":"98188",
    "addr:street":"Andover Park E",
    "iso:country":"US",
    "sg:address":"1095 Andover Park E",
    "sg:city":"Seattle",
    "sg:classifiers":[
        {
            "category":"Retail",
            "subcategory":"Repair Shop",
            "type":"Services"
        }
    ],
    "sg:phone":"+1 206 574 0375",
    "sg:postcode":"98188",
    "sg:province":"WA",
    "sg:tags":[
        "equipment",
        "transportation"
    ],
    "wof:name":"ZF Marine",
    "wof:placetype":"venue"
},
  "geometry": {"coordinates":[-122.251105,47.445359],"type":"Point"}
}