{
  "type": "Feature",
  "properties": {
    "addr:full":"5974 N Fork Rd Deming WA 98244",
    "addr:housenumber":"5974",
    "addr:postcode":"98244",
    "addr:street":"N Fork Rd",
    "iso:country":"US",
    "sg:address":"5974 N Fork Rd",
    "sg:city":"Deming",
    "sg:classifiers":[
        {
            "category":"Building & Trades",
            "subcategory":"Construction",
            "type":"Services"
        }
    ],
    "sg:phone":"+1 360 592 2923",
    "sg:postcode":"98244",
    "sg:province":"WA",
    "sg:tags":[
        "heavy"
    ],
    "wof:name":"Mark White Enterprise",
    "wof:placetype":"venue"
},
  "geometry": {"coordinates":[-122.142072,48.886399],"type":"Point"}
}