{
  "type": "Feature",
  "properties": {
    "addr:full":"11012 126th Ave NE Kirkland WA 98033",
    "addr:housenumber":"11012",
    "addr:postcode":"98033",
    "addr:street":"126Th Ave Ne",
    "iso:country":"US",
    "sg:address":"11012 126th Ave NE",
    "sg:city":"Kirkland",
    "sg:classifiers":[
        {
            "category":"Shopping",
            "subcategory":"Photographic Equipment",
            "type":"Retail Goods"
        }
    ],
    "sg:phone":"+1 425 822 7608",
    "sg:postcode":"98033",
    "sg:province":"WA",
    "sg:tags":[
        "supply"
    ],
    "wof:name":"Creative Memories",
    "wof:placetype":"venue"
},
  "geometry": {"coordinates":[-122.173543,47.700275],"type":"Point"}
}