{
  "type": "Feature",
  "properties": {
    "iso:country":"US",
    "sg:address":"16125 256th Ave E",
    "sg:city":"Buckley",
    "sg:classifiers":[
        {
            "category":"Building & Trades",
            "subcategory":"Cleaning & Sanitation",
            "type":"Services"
        }
    ],
    "sg:phone":"+1 253 863 6890",
    "sg:postcode":"98321",
    "sg:province":"WA",
    "sg:tags":[
        "janitor"
    ],
    "wof:name":"Bonney Lake Janitorial Svc",
    "wof:placetype":"venue"
},
  "geometry": {"coordinates":[-122.088916,47.110154],"type":"Point"}
}