{
  "type": "Feature",
  "properties": {
    "addr:full":"667 120th Ave NE Ste 2A #161 Bellevue WA 98005",
    "addr:housenumber":"667",
    "addr:postcode":"98005",
    "addr:street":"120Th Ave Ne Ste 2A # 161",
    "iso:country":"US",
    "sg:address":"667 120th Ave NE Ste 2A #161",
    "sg:city":"Bellevue",
    "sg:classifiers":[
        {
            "category":"Professional",
            "subcategory":"Art Services",
            "type":"Services"
        }
    ],
    "sg:phone":"+1 425 829 0532",
    "sg:postcode":"98005",
    "sg:province":"WA",
    "sg:tags":[
        "photographer"
    ],
    "sg:website":"www.photosbyrachelle.com/",
    "wof:name":"Photos by Rachelle",
    "wof:placetype":"venue"
},
  "geometry": {"coordinates":[-122.18033800000001,47.616146],"type":"Point"}
}