{
  "type": "Feature",
  "properties": {
    "addr:full":"2120 NE 47th St Seattle WA 98105",
    "addr:housenumber":"2120",
    "addr:postcode":"98105",
    "addr:street":"Ne 47Th St",
    "iso:country":"US",
    "sg:address":"2120 NE 47th St",
    "sg:city":"Seattle",
    "sg:classifiers":[
        {
            "category":"Organizations",
            "subcategory":"Community Association",
            "type":"Services"
        }
    ],
    "sg:phone":"+1 206 527 7900",
    "sg:postcode":"98105",
    "sg:province":"WA",
    "sg:tags":[
        "sorority",
        "fraternity"
    ],
    "wof:name":"Phi Kappa Psi",
    "wof:placetype":"venue"
},
  "geometry": {"coordinates":[-122.305273,47.663059],"type":"Point"}
}