{
  "type": "Feature",
  "properties": {
    "addr:full":"116 Mission Creek Rd Cashmere WA 98815",
    "addr:housenumber":"116",
    "addr:postcode":"98815",
    "addr:street":"Mission Creek Rd",
    "iso:country":"US",
    "sg:address":"116 Mission Creek Rd",
    "sg:city":"Cashmere",
    "sg:classifiers":[
        {
            "category":"Manufacturing",
            "subcategory":"Tools & Machinery",
            "type":"Manufacturing & Wholesale Goods"
        }
    ],
    "sg:phone":"+1 509 782 3789",
    "sg:postcode":"98815",
    "sg:province":"WA",
    "sg:tags":[
        "machine",
        "product",
        "wood",
        "mfg"
    ],
    "wof:name":"Eagle Rock Lath and Supply",
    "wof:placetype":"venue"
},
  "geometry": {"coordinates":[-120.472143,47.516869],"type":"Point"}
}