{
  "type": "Feature",
  "properties": {
    "addr:full":"1200 NE 45th St Seattle WA 98105",
    "addr:housenumber":"1200",
    "addr:postcode":"98105",
    "addr:street":"Ne 45Th St",
    "iso:country":"US",
    "sg:address":"1200 NE 45th St",
    "sg:city":"Seattle",
    "sg:classifiers":[
        {
            "category":"Banks & Credit Unions",
            "subcategory":"Bank",
            "type":"Services"
        }
    ],
    "sg:phone":"+1 206 632 3322",
    "sg:postcode":"98105",
    "sg:province":"WA",
    "wof:name":"United Savings & Loan Bank",
    "wof:placetype":"venue"
},
  "geometry": {"coordinates":[-122.31500200000001,47.661201],"type":"Point"}
}