{
  "type": "Feature",
  "properties": {
    "addr:full":"5617 N Grove Dr Mukilteo WA 98275",
    "addr:housenumber":"5617",
    "addr:postcode":"98275",
    "addr:street":"N Grove Dr",
    "iso:country":"US",
    "sg:address":"5617 N Grove Dr",
    "sg:city":"Mukilteo",
    "sg:classifiers":[
        {
            "category":"Professional",
            "type":"Services"
        }
    ],
    "sg:phone":"+1 425 349 3465",
    "sg:postcode":"98275",
    "sg:province":"WA",
    "wof:name":"James K McMartin",
    "wof:placetype":"venue"
},
  "geometry": {"coordinates":[-122.31064600000001,47.893365],"type":"Point"}
}