{
  "type": "Feature",
  "properties": {
    "addr:full":"208401 E Cochran Rd Kennewick WA 99337",
    "addr:housenumber":"208401",
    "addr:postcode":"99337",
    "addr:street":"E Cochran Rd",
    "iso:country":"US",
    "sg:address":"208401 E Cochran Rd",
    "sg:city":"Kennewick",
    "sg:classifiers":[
        {
            "category":"Home & Garden",
            "subcategory":"Furniture",
            "type":"Retail Goods"
        }
    ],
    "sg:phone":"+1 509 528 2549",
    "sg:postcode":"99337",
    "sg:province":"WA",
    "wof:name":"Rustic Elegance",
    "wof:placetype":"venue"
},
  "geometry": {"coordinates":[-119.063626,46.161399],"type":"Point"}
}