{
  "type": "Feature",
  "properties": {
    "addr:full":"14217 214th St SE Snohomish WA 98296",
    "addr:housenumber":"14217",
    "addr:postcode":"98296",
    "addr:street":"214Th St Se",
    "iso:country":"US",
    "sg:address":"14217 214th St SE",
    "sg:city":"Snohomish",
    "sg:classifiers":[
        {
            "category":"Professional",
            "subcategory":"Art Services",
            "type":"Services"
        }
    ],
    "sg:phone":"+1 425 481 7595",
    "sg:postcode":"98296",
    "sg:province":"WA",
    "sg:tags":[
        "interior",
        "designer",
        "decorator"
    ],
    "wof:name":"Tina's Home Furnishings",
    "wof:placetype":"venue"
},
  "geometry": {"coordinates":[-122.041572,47.802719],"type":"Point"}
}