{
  "type": "Feature",
  "properties": {
    "addr:full":"4753 Roosevelt Way NE Seattle WA 98105",
    "addr:housenumber":"4753",
    "addr:postcode":"98105",
    "addr:street":"Roosevelt Way Ne",
    "iso:country":"US",
    "sg:address":"4753 Roosevelt Way NE",
    "sg:city":"Seattle",
    "sg:classifiers":[
        {
            "category":"Shopping",
            "subcategory":"Books",
            "type":"Retail Goods"
        }
    ],
    "sg:phone":"+1 206 547 7667",
    "sg:postcode":"98105",
    "sg:province":"WA",
    "sg:tags":[
        "bookstore"
    ],
    "wof:name":"Cinema Books",
    "wof:placetype":"venue"
},
  "geometry": {"coordinates":[-122.318001,47.663601],"type":"Point"}
}