{
  "type": "Feature",
  "properties": {
    "addr:full":"301 SW 27th St Renton WA 98057",
    "addr:housenumber":"301",
    "addr:postcode":"98057",
    "addr:street":"Sw 27Th St",
    "iso:country":"US",
    "sg:address":"301 SW 27th St",
    "sg:city":"Renton",
    "sg:classifiers":[
        {
            "category":"Professional",
            "subcategory":"Art Services",
            "type":"Services"
        }
    ],
    "sg:phone":"+1 425 251 6560",
    "sg:postcode":"98057",
    "sg:province":"WA",
    "sg:tags":[
        "development",
        "package",
        "designing"
    ],
    "wof:name":"Graphics Sheets Unlimited",
    "wof:placetype":"venue"
},
  "geometry": {"coordinates":[-122.22242799999999,47.455468],"type":"Point"}
}