{
  "type": "Feature",
  "properties": {
    "addr:full":"5700 100th St SW Ste 200 Lakewood WA 98499",
    "addr:housenumber":"5700",
    "addr:postcode":"98499",
    "addr:street":"100Th St Sw Ste 200",
    "iso:country":"US",
    "sg:address":"5700 100th St SW Ste 200",
    "sg:city":"Lakewood",
    "sg:classifiers":[
        {
            "category":"Shopping",
            "subcategory":"Pets & Pet Supplies",
            "type":"Retail Goods"
        },
        {
            "category":"Retail",
            "subcategory":"Pet Boarding",
            "type":"Services"
        }
    ],
    "sg:phone":"+1 253 984 6903",
    "sg:postcode":"98499",
    "sg:province":"WA",
    "sg:tags":[
        "boarding/pet",
        "store",
        "sitting"
    ],
    "sg:website":"www.petco.com",
    "wof:name":"Petco",
    "wof:placetype":"venue"
},
  "geometry": {"coordinates":[-122.49900100000001,47.166599],"type":"Point"}
}