{
  "type": "Feature",
  "properties": {
    "addr:full":"2100 N 45th St Seattle WA 98103",
    "addr:housenumber":"2100",
    "addr:postcode":"98103",
    "addr:street":"N 45Th St",
    "iso:country":"US",
    "sg:address":"2100 N 45th St",
    "sg:city":"Seattle",
    "sg:classifiers":[
        {
            "category":"Coffee & Tea",
            "type":"Food & Drink"
        }
    ],
    "sg:phone":"+1 206 632 5259",
    "sg:postcode":"98103",
    "sg:province":"WA",
    "sg:website":"www.tullyscoffeeshops.com",
    "wof:name":"Tully's Coffee",
    "wof:placetype":"venue"
},
  "geometry": {"coordinates":[-122.334,47.661301],"type":"Point"}
}