{
  "type": "Feature",
  "properties": {
    "addr:full":"3550 S Holly St Seattle WA 98118",
    "addr:housenumber":"3550",
    "addr:postcode":"98118",
    "addr:street":"S Holly St",
    "iso:country":"US",
    "sg:address":"3550 S Holly St",
    "sg:city":"Seattle",
    "sg:classifiers":[
        {
            "category":"Organizations",
            "subcategory":"Religious Organization",
            "type":"Services"
        }
    ],
    "sg:phone":"+1 206 723 3177",
    "sg:postcode":"98118",
    "sg:province":"WA",
    "wof:name":"Samoan Cngrgtion Chrstn Church",
    "wof:placetype":"venue"
},
  "geometry": {"coordinates":[-122.287634,47.542574],"type":"Point"}
}