{
  "type": "Feature",
  "properties": {
    "addr:full":"405 W Stewart Ave Puyallup WA 98371",
    "addr:housenumber":"405",
    "addr:postcode":"98371",
    "addr:street":"W Stewart Ave",
    "iso:country":"US",
    "sg:address":"405 W Stewart Ave",
    "sg:city":"Puyallup",
    "sg:classifiers":[
        {
            "category":"Government",
            "subcategory":"Jail",
            "type":"Public Place"
        }
    ],
    "sg:phone":"+1 253 840 4664",
    "sg:postcode":"98371",
    "sg:province":"WA",
    "sg:tags":[
        "govt",
        "state",
        "institution"
    ],
    "wof:name":"Corrections Dept",
    "wof:placetype":"venue"
},
  "geometry": {"coordinates":[-122.29889,47.193809],"type":"Point"}
}