{
  "type": "Feature",
  "properties": {
    "addr:full":"8441 37th Ave S Seattle WA 98118",
    "addr:housenumber":"8441",
    "addr:postcode":"98118",
    "addr:street":"37Th Ave S",
    "iso:country":"US",
    "sg:address":"8441 37th Ave S",
    "sg:city":"Seattle",
    "sg:classifiers":[
        {
            "category":"Building & Trades",
            "subcategory":"Cleaning & Sanitation",
            "type":"Services"
        }
    ],
    "sg:phone":"+1 206 329 6243",
    "sg:postcode":"98118",
    "sg:province":"WA",
    "sg:tags":[
        "janitorial"
    ],
    "wof:name":"Saechao  KAO",
    "wof:placetype":"venue"
},
  "geometry": {"coordinates":[-122.286035,47.52647],"type":"Point"}
}