{
  "type": "Feature",
  "properties": {
    "addr:full":"710 L St Port Townsend WA 98368",
    "addr:housenumber":"710",
    "addr:postcode":"98368",
    "addr:street":"L St",
    "iso:country":"US",
    "sg:address":"710 L St",
    "sg:city":"Port Townsend",
    "sg:classifiers":[
        {
            "category":"Building & Trades",
            "subcategory":"Construction",
            "type":"Services"
        }
    ],
    "sg:phone":"+1 360 385 6958",
    "sg:postcode":"98368",
    "sg:province":"WA",
    "sg:tags":[
        "house"
    ],
    "wof:name":"Goldenberg Construction",
    "wof:placetype":"venue"
},
  "geometry": {"coordinates":[-122.769611,48.124536],"type":"Point"}
}