{
  "type": "Feature",
  "properties": {
    "addr:full":"18118 Sundown Ct SE Yelm WA 98597",
    "addr:housenumber":"18118",
    "addr:postcode":"98597",
    "addr:street":"Sundown Ct Se",
    "iso:country":"US",
    "sg:address":"18118 Sundown Ct SE",
    "sg:city":"Yelm",
    "sg:classifiers":[
        {
            "category":"Wholesale",
            "subcategory":"Durable Goods & Equipment",
            "type":"Manufacturing & Wholesale Goods"
        }
    ],
    "sg:phone":"+1 360 894 5462",
    "sg:postcode":"98597",
    "sg:province":"WA",
    "wof:name":"T V R Sign",
    "wof:placetype":"venue"
},
  "geometry": {"coordinates":[-122.46809500000001,46.824199],"type":"Point"}
}