{
  "type": "Feature",
  "properties": {
    "addr:full":"1921 3rd Ave Seattle WA 98101",
    "addr:housenumber":"1921",
    "addr:postcode":"98101",
    "addr:street":"3Rd Ave",
    "iso:country":"US",
    "sg:address":"1921 3rd Ave",
    "sg:city":"Seattle",
    "sg:classifiers":[
        {
            "category":"Building & Trades",
            "subcategory":"Landscaping Services",
            "type":"Services"
        }
    ],
    "sg:phone":"+1 206 448 8122",
    "sg:postcode":"98101",
    "sg:province":"WA",
    "sg:tags":[
        "lawn"
    ],
    "wof:name":"Demo & Landscaping By Rl Williamson",
    "wof:placetype":"venue"
},
  "geometry": {"coordinates":[-122.339904,47.611762],"type":"Point"}
}