{
  "type": "Feature",
  "properties": {
    "addr:full":"12935 Reo Rd SE Rainier WA 98576",
    "addr:housenumber":"12935",
    "addr:postcode":"98576",
    "addr:street":"Reo Rd Se",
    "iso:country":"US",
    "sg:address":"12935 Reo Rd SE",
    "sg:city":"Rainier",
    "sg:classifiers":[
        {
            "category":"Manufacturing",
            "subcategory":"Building Materials",
            "type":"Manufacturing & Wholesale Goods"
        }
    ],
    "sg:phone":"+1 360 446 4114",
    "sg:postcode":"98576",
    "sg:province":"WA",
    "sg:tags":[
        "mfg",
        "wood",
        "kitchen",
        "cabinet"
    ],
    "wof:name":"Lb Steele Cabinet Co",
    "wof:placetype":"venue"
},
  "geometry": {"coordinates":[-122.705485,46.900186],"type":"Point"}
}