{
  "type": "Feature",
  "properties": {
    "addr:full":"7916 Noble View Ln NW Olympia WA 98502",
    "addr:housenumber":"7916",
    "addr:postcode":"olympia wa 98502",
    "addr:street":"Noble View Ln Nw",
    "iso:country":"US",
    "sg:address":"7916 Noble View Ln NW",
    "sg:city":"Olympia",
    "sg:classifiers":[
        {
            "category":"Farming",
            "subcategory":"Farm",
            "type":"Manufacturing & Wholesale Goods"
        }
    ],
    "sg:phone":"+1 360 866 8354",
    "sg:postcode":"98502",
    "sg:province":"WA",
    "sg:tags":[
        "crop",
        "general"
    ],
    "wof:name":"Noble View Farm Llamas",
    "wof:placetype":"venue"
},
  "geometry": {"coordinates":[-122.941067,47.146377],"type":"Point"}
}