{
  "type": "Feature",
  "properties": {
    "addr:full":"19905 190th Ave NE Woodinville WA 98077",
    "addr:housenumber":"19905",
    "addr:postcode":"98077",
    "addr:street":"190Th Ave Ne",
    "iso:country":"US",
    "sg:address":"19905 190th Ave NE",
    "sg:city":"Woodinville",
    "sg:classifiers":[
        {
            "category":"Professional",
            "subcategory":"Business Services",
            "type":"Services"
        }
    ],
    "sg:phone":"+1 425 844 1414",
    "sg:postcode":"98077",
    "sg:province":"WA",
    "wof:name":"Mind Group Inc",
    "wof:placetype":"venue"
},
  "geometry": {"coordinates":[-122.085596,47.771481],"type":"Point"}
}