{
  "type": "Feature",
  "properties": {
    "addr:full":"406 SE Washington St Wilbur WA 99185",
    "addr:housenumber":"406",
    "addr:postcode":"99185",
    "addr:street":"Se Washington St",
    "iso:country":"US",
    "sg:address":"406 SE Washington St",
    "sg:city":"Wilbur",
    "sg:classifiers":[
        {
            "category":"Professional",
            "subcategory":"Art Services",
            "type":"Services"
        }
    ],
    "sg:phone":"+1 509 647 0505",
    "sg:postcode":"99185",
    "sg:province":"WA",
    "sg:tags":[
        "commercial",
        "design"
    ],
    "wof:name":"Country Roads Cottage",
    "wof:placetype":"venue"
},
  "geometry": {"coordinates":[-118.701244,47.753602],"type":"Point"}
}