{
  "type": "Feature",
  "properties": {
    "addr:full":"2725 56th Ave SW Seattle WA 98116",
    "addr:housenumber":"2725",
    "addr:postcode":"98116",
    "addr:street":"56Th Ave Sw",
    "iso:country":"US",
    "sg:address":"2725 56th Ave SW",
    "sg:city":"Seattle",
    "sg:classifiers":[
        {
            "category":"Building & Trades",
            "subcategory":"Construction",
            "type":"Services"
        }
    ],
    "sg:phone":"+1 206 937 4658",
    "sg:postcode":"98116",
    "sg:province":"WA",
    "wof:name":"Carmacon Inc",
    "wof:placetype":"venue"
},
  "geometry": {"coordinates":[-122.403899,47.578759],"type":"Point"}
}