{
  "type": "Feature",
  "properties": {
    "addr:full":"1115 NW 92nd St Seattle WA 98117",
    "addr:housenumber":"1115",
    "addr:postcode":"98117",
    "addr:street":"Nw 92Nd St",
    "iso:country":"US",
    "sg:address":"1115 NW 92nd St",
    "sg:city":"Seattle",
    "sg:classifiers":[
        {
            "category":"Freight",
            "type":"Transportation"
        }
    ],
    "sg:phone":"+1 206 783 9023",
    "sg:postcode":"98117",
    "sg:province":"WA",
    "sg:tags":[
        "operator",
        "trucking"
    ],
    "wof:name":"Mr Als Trucking",
    "wof:placetype":"venue"
},
  "geometry": {"coordinates":[-122.37128,47.695987],"type":"Point"}
}