{
  "type": "Feature",
  "properties": {
    "addr:full":"701 5th Ave Seattle WA 98104",
    "addr:housenumber":"701",
    "addr:postcode":"98104",
    "addr:street":"5Th Ave",
    "iso:country":"US",
    "sg:address":"701 5th Ave",
    "sg:city":"Seattle",
    "sg:classifiers":[
        {
            "category":"Recreation",
            "subcategory":"Marina",
            "type":"Entertainment"
        }
    ],
    "sg:phone":"+1 206 749 0094",
    "sg:postcode":"98104",
    "sg:province":"WA",
    "wof:name":"Marina Alverez",
    "wof:placetype":"venue"
},
  "geometry": {"coordinates":[-122.329826,47.604431],"type":"Point"}
}