{
  "type": "Feature",
  "properties": {
    "addr:full":"2200 112th Ave NE Ste 200 Bellevue WA 98004",
    "addr:housenumber":"2200",
    "addr:postcode":"98004",
    "addr:street":"112Th Ave Ne Ste 200",
    "iso:country":"US",
    "sg:address":"2200 112th Ave NE Ste 200",
    "sg:city":"Bellevue",
    "sg:classifiers":[
        {
            "category":"Professional",
            "subcategory":"Lawyer & Legal Services",
            "type":"Services"
        }
    ],
    "sg:phone":"+1 425 462 1235",
    "sg:postcode":"98004",
    "sg:province":"WA",
    "wof:name":"Cespedes Rene",
    "wof:placetype":"venue"
},
  "geometry": {"coordinates":[-122.190662,47.629943],"type":"Point"}
}