{
  "type": "Feature",
  "properties": {
    "addr:full":"729 122nd Ave NE Bellevue WA 98005",
    "addr:housenumber":"729",
    "addr:postcode":"98005",
    "addr:street":"122Nd Ave Ne",
    "iso:country":"US",
    "sg:address":"729 122nd Ave NE",
    "sg:city":"Bellevue",
    "sg:classifiers":[
        {
            "category":"Professional",
            "subcategory":"Art Services",
            "type":"Services"
        }
    ],
    "sg:phone":"+1 425 646 2866",
    "sg:postcode":"98005",
    "sg:province":"WA",
    "sg:tags":[
        "commercial",
        "design"
    ],
    "wof:name":"Morton Creative",
    "wof:placetype":"venue"
},
  "geometry": {"coordinates":[-122.178423,47.616562],"type":"Point"}
}