{
  "type": "Feature",
  "properties": {
    "addr:full":"9113 NE 117th Ave Vancouver WA 98662",
    "addr:housenumber":"9113",
    "addr:postcode":"98662",
    "addr:street":"Ne 117Th Ave",
    "iso:country":"US",
    "sg:address":"9113 NE 117th Ave",
    "sg:city":"Vancouver",
    "sg:classifiers":[
        {
            "category":"Shopping",
            "subcategory":"Florist",
            "type":"Retail Goods"
        },
        {
            "category":"Shopping",
            "subcategory":"Clothing, Apparel, & Fashions",
            "type":"Retail Goods"
        }
    ],
    "sg:phone":"+1 360 256 4753",
    "sg:postcode":"98662",
    "sg:province":"WA",
    "sg:tags":[
        "shop",
        "bridal",
        "wear"
    ],
    "wof:name":"Magnolia Flower & Bridal Shop",
    "wof:placetype":"venue"
},
  "geometry": {"coordinates":[-122.552504,45.687984],"type":"Point"}
}