{
  "type": "Feature",
  "properties": {
    "addr:full":"5444 E Blaisdell Ln Port Orchard WA 98366",
    "addr:housenumber":"5444",
    "addr:postcode":"98366",
    "addr:street":"E Blaisdell Ln",
    "iso:country":"US",
    "sg:address":"5444 E Blaisdell Ln",
    "sg:city":"Port Orchard",
    "sg:classifiers":[
        {
            "category":"Professional",
            "subcategory":"Business Services",
            "type":"Services"
        }
    ],
    "sg:phone":"+1 360 895 3405",
    "sg:postcode":"98366",
    "sg:province":"WA",
    "sg:tags":[
        "transcribing",
        "disc"
    ],
    "wof:name":"Care Transcription Svc",
    "wof:placetype":"venue"
},
  "geometry": {"coordinates":[-122.583112,47.569662],"type":"Point"}
}