{
  "type": "Feature",
  "properties": {
    "addr:full":"1715 Merlot Rd Richland WA 99352",
    "addr:housenumber":"1715",
    "addr:postcode":"99352",
    "addr:street":"Merlot Rd",
    "iso:country":"US",
    "sg:address":"1715 Merlot Rd",
    "sg:city":"Richland",
    "sg:classifiers":[
        {
            "category":"Building & Trades",
            "subcategory":"Plumbing",
            "type":"Services"
        }
    ],
    "sg:phone":"+1 509 967 9181",
    "sg:postcode":"99352",
    "sg:province":"WA",
    "sg:tags":[
        "contractor"
    ],
    "wof:name":"Cole Drain & Plumbing Repair",
    "wof:placetype":"venue"
},
  "geometry": {"coordinates":[-119.29723300000001,46.239858],"type":"Point"}
}