{
  "type": "Feature",
  "properties": {
    "addr:full":"14926 Aurora Avenue N Shoreline WA 98133",
    "addr:housenumber":"14926",
    "addr:postcode":"98133",
    "addr:street":"Aurora Avenue N",
    "iso:country":"US",
    "sg:address":"14926 Aurora Avenue N",
    "sg:city":"Shoreline",
    "sg:classifiers":[
        {
            "category":"Health Services",
            "subcategory":"Optometrist",
            "type":"Services"
        },
        {
            "category":"Shopping",
            "subcategory":"Optician",
            "type":"Retail Goods"
        }
    ],
    "sg:phone":"+1 206 364 6000",
    "sg:postcode":"98133",
    "sg:province":"WA",
    "sg:tags":[
        "eyewear"
    ],
    "wof:name":"Min Paul H OD",
    "wof:placetype":"venue"
},
  "geometry": {"coordinates":[-122.345174,47.737245],"type":"Point"}
}