{
  "type": "Feature",
  "properties": {
    "addr:full":"2181 E Beach Rd Port Angeles WA 98363",
    "addr:housenumber":"2181",
    "addr:postcode":"98363",
    "addr:street":"E Beach Rd",
    "iso:country":"US",
    "sg:address":"2181 E Beach Rd",
    "sg:city":"Port Angeles",
    "sg:classifiers":[
        {
            "category":"Real Estate",
            "subcategory":"Real Estate Operator",
            "type":"Services"
        }
    ],
    "sg:phone":"+1 360 928 3454",
    "sg:postcode":"98363",
    "sg:province":"WA",
    "sg:tags":[
        "campground",
        "farm",
        "lease",
        "tree",
        "operates"
    ],
    "wof:name":"Port Crescent Beach Park",
    "wof:placetype":"venue"
},
  "geometry": {"coordinates":[-123.765863,48.092893],"type":"Point"}
}