{
  "type": "Feature",
  "properties": {
    "addr:full":"3514 S Morrill Dr Spokane WA 99223",
    "addr:housenumber":"3514",
    "addr:postcode":"99223",
    "addr:street":"S Morrill Dr",
    "iso:country":"US",
    "sg:address":"3514 S Morrill Dr",
    "sg:city":"Spokane",
    "sg:classifiers":[
        {
            "category":"Professional",
            "type":"Services"
        }
    ],
    "sg:phone":"+1 509 443 1864",
    "sg:postcode":"99223",
    "sg:province":"WA",
    "wof:name":"Fabulous Estate Sls",
    "wof:placetype":"venue"
},
  "geometry": {"coordinates":[-117.344376,47.622582],"type":"Point"}
}