{
  "type": "Feature",
  "properties": {
    "addr:full":"907 T St Vancouver WA 98661",
    "addr:housenumber":"907",
    "addr:postcode":"98661",
    "addr:street":"T St",
    "iso:country":"US",
    "sg:address":"907 T St",
    "sg:city":"Vancouver",
    "sg:classifiers":[
        {
            "category":"Building & Trades",
            "subcategory":"Construction",
            "type":"Services"
        }
    ],
    "sg:phone":"+1 360 608 4960",
    "sg:postcode":"98661",
    "sg:province":"WA",
    "sg:tags":[
        "house"
    ],
    "wof:name":"P M S Professional Maint Svc",
    "wof:placetype":"venue"
},
  "geometry": {"coordinates":[-122.65114800000001,45.628257],"type":"Point"}
}