{
  "type": "Feature",
  "properties": {
    "addr:full":"651 Senz Rd Sequim WA 98382",
    "addr:housenumber":"651",
    "addr:postcode":"98382",
    "addr:street":"Senz Rd",
    "iso:country":"US",
    "sg:address":"651 Senz Rd",
    "sg:city":"Sequim",
    "sg:classifiers":[
        {
            "category":"Food & Beverages",
            "subcategory":"Meat & Fish",
            "type":"Retail Goods"
        }
    ],
    "sg:phone":"+1 360 681 4242",
    "sg:postcode":"98382",
    "sg:province":"WA",
    "sg:tags":[
        "seafood"
    ],
    "wof:name":"Crab Barn",
    "wof:placetype":"venue"
},
  "geometry": {"coordinates":[-123.16401999999999,48.057853],"type":"Point"}
}