{
  "type": "Feature",
  "properties": {
    "addr:full":"14314 Greenwood Ave N Seattle WA 98133",
    "addr:housenumber":"14314",
    "addr:postcode":"98133",
    "addr:street":"Greenwood Ave N",
    "iso:country":"US",
    "sg:address":"14314 Greenwood Ave N",
    "sg:city":"Seattle",
    "sg:classifiers":[
        {
            "category":"Restaurant",
            "type":"Food & Drink"
        }
    ],
    "sg:phone":"+1 206 363 0526",
    "sg:postcode":"98133",
    "sg:province":"WA",
    "wof:name":"Fu Man Dumpling House",
    "wof:placetype":"venue"
},
  "geometry": {"coordinates":[-122.35556800000001,47.732455],"type":"Point"}
}