{
  "type": "Feature",
  "properties": {
    "addr:full":"327 W Brooks St Goldendale WA 98620",
    "addr:housenumber":"327",
    "addr:postcode":"98620",
    "addr:street":"W Brooks St",
    "iso:country":"US",
    "sg:address":"327 W Brooks St",
    "sg:city":"Goldendale",
    "sg:classifiers":[
        {
            "category":"Government",
            "subcategory":"Fire Station",
            "type":"Public Place"
        }
    ],
    "sg:phone":"+1 509 773 4246",
    "sg:postcode":"98620",
    "sg:province":"WA",
    "sg:tags":[
        "protection"
    ],
    "wof:name":"County of Klickitat",
    "wof:placetype":"venue"
},
  "geometry": {"coordinates":[-120.826791,45.817903],"type":"Point"}
}