{
  "type": "Feature",
  "properties": {
    "addr:full":"4654 Guide Meridian Bellingham WA 98226",
    "addr:housenumber":"4654",
    "addr:postcode":"98226",
    "addr:street":"Guide Meridian",
    "iso:country":"US",
    "sg:address":"4654 Guide Meridian",
    "sg:city":"Bellingham",
    "sg:classifiers":[
        {
            "category":"Professional",
            "subcategory":"Art Services",
            "type":"Services"
        }
    ],
    "sg:phone":"+1 360 733 3530",
    "sg:postcode":"98226",
    "sg:province":"WA",
    "sg:tags":[
        "designer",
        "display",
        "producer"
    ],
    "wof:name":"International Composite Design",
    "wof:placetype":"venue"
},
  "geometry": {"coordinates":[-122.488575,48.861261],"type":"Point"}
}