{
  "type": "Feature",
  "properties": {
    "addr:full":"609 W Washington St Ste 1 Sequim WA 98382",
    "addr:housenumber":"609",
    "addr:postcode":"98382",
    "addr:street":"W Washington St Ste 1",
    "iso:country":"US",
    "sg:address":"609 W Washington St Ste 1",
    "sg:city":"Sequim",
    "sg:classifiers":[
        {
            "category":"Home & Garden",
            "subcategory":"Building Materials",
            "type":"Retail Goods"
        },
        {
            "category":"Building & Trades",
            "subcategory":"Construction",
            "type":"Services"
        }
    ],
    "sg:phone":"+1 360 452 2988",
    "sg:postcode":"98382",
    "sg:province":"WA",
    "sg:tags":[
        "industrial",
        "supply",
        "specialty",
        "system",
        "acoustical",
        "equipment",
        "heating",
        "contractors-commercial",
        "insulation",
        "contractor",
        "drywall",
        "air conditioning"
    ],
    "wof:name":"Dj Concepts",
    "wof:placetype":"venue"
},
  "geometry": {"coordinates":[-123.116167,48.079715],"type":"Point"}
}