{
  "type": "Feature",
  "properties": {
    "addr:full":"3200 SE 164th Ave Ste 219 Vancouver WA 98683",
    "addr:housenumber":"3200",
    "addr:postcode":"98683",
    "addr:street":"Se 164Th Ave Ste 219",
    "iso:country":"US",
    "sg:address":"3200 SE 164th Ave Ste 219",
    "sg:city":"Vancouver",
    "sg:classifiers":[
        {
            "category":"Restaurant",
            "type":"Food & Drink"
        }
    ],
    "sg:phone":"+1 360 254 1250",
    "sg:postcode":"98683",
    "sg:province":"WA",
    "sg:tags":[
        "hawaiian"
    ],
    "sg:website":"http://www.bacchusrestaurant.biz",
    "wof:name":"Island Hawaiian Restaurant",
    "wof:placetype":"venue"
},
  "geometry": {"coordinates":[-122.50386,45.598052],"type":"Point"}
}