{
  "type": "Feature",
  "properties": {
    "addr:full":"935 Industry Dr Seattle WA 98188",
    "addr:housenumber":"935",
    "addr:postcode":"98188",
    "addr:street":"Industry Dr",
    "iso:country":"US",
    "sg:address":"935 Industry Dr",
    "sg:city":"Seattle",
    "sg:classifiers":[
        {
            "category":"Manufacturing",
            "subcategory":"Food",
            "type":"Manufacturing & Wholesale Goods"
        }
    ],
    "sg:phone":"+1 206 574 0577",
    "sg:postcode":"98188",
    "sg:province":"WA",
    "sg:tags":[
        "deserts"
    ],
    "wof:name":"Seattles Fvrite Gurmet Cookies",
    "wof:placetype":"venue"
},
  "geometry": {"coordinates":[-122.24847800000001,47.449726],"type":"Point"}
}