{
  "type": "Feature",
  "properties": {
    "addr:full":"1011 E 1st St Cle Elum WA 98922",
    "addr:housenumber":"1011",
    "addr:postcode":"98922",
    "addr:street":"E 1St St",
    "iso:country":"US",
    "sg:address":"1011 E 1st St",
    "sg:city":"Cle Elum",
    "sg:classifiers":[
        {
            "category":"Restaurant",
            "type":"Food & Drink"
        }
    ],
    "sg:phone":"+1 509 674 2254",
    "sg:postcode":"98922",
    "sg:province":"WA",
    "sg:tags":[
        "fast"
    ],
    "wof:name":"Mc Kean's Drive In",
    "wof:placetype":"venue"
},
  "geometry": {"coordinates":[-120.91648600000001,47.192112],"type":"Point"}
}