{
  "type": "Feature",
  "properties": {
    "addr:full":"8312 166th Street Ct NW Gig Harbor WA 98329",
    "addr:housenumber":"8312",
    "addr:postcode":"98329",
    "addr:street":"166Th Street",
    "iso:country":"US",
    "sg:address":"8312 166th Street Ct NW",
    "sg:city":"Gig Harbor",
    "sg:classifiers":[
        {
            "category":"Building & Trades",
            "subcategory":"Construction",
            "type":"Services"
        }
    ],
    "sg:phone":"+1 253 857 3418",
    "sg:postcode":"98329",
    "sg:province":"WA",
    "sg:tags":[
        "house"
    ],
    "wof:name":"William Easley Construction",
    "wof:placetype":"venue"
},
  "geometry": {"coordinates":[-122.651549,47.408733],"type":"Point"}
}