{
  "type": "Feature",
  "properties": {
    "addr:full":"12404 NE 6th Pl Bellevue WA 98005",
    "addr:housenumber":"12404",
    "addr:postcode":"98005",
    "addr:street":"Ne 6Th Pl",
    "iso:country":"US",
    "sg:address":"12404 NE 6th Pl",
    "sg:city":"Bellevue",
    "sg:classifiers":[
        {
            "category":"Building & Trades",
            "subcategory":"Construction",
            "type":"Services"
        }
    ],
    "sg:phone":"+1 425 454 7563",
    "sg:postcode":"98005",
    "sg:province":"WA",
    "sg:tags":[
        "wallcoverings-installation",
        "wallpaper",
        "painting",
        "contractor"
    ],
    "wof:name":"Harris Enterprises",
    "wof:placetype":"venue"
},
  "geometry": {"coordinates":[-122.17480399999999,47.615958],"type":"Point"}
}