{
  "type": "Feature",
  "properties": {
    "iso:country":"US",
    "sg:address":"21705 58th Ave W",
    "sg:city":"Mountlake Ter",
    "sg:classifiers":[
        {
            "category":"Organizations",
            "subcategory":"Religious Organization",
            "type":"Services"
        }
    ],
    "sg:phone":"+1 425 771 8343",
    "sg:postcode":"98043",
    "sg:province":"WA",
    "sg:tags":[
        "personal",
        "church"
    ],
    "sg:website":"www.nbcnow.com",
    "wof:name":"New Beginnings Church",
    "wof:placetype":"venue"
},
  "geometry": {"coordinates":[-122.31061699999999,47.801991],"type":"Point"}
}