{
  "type": "Feature",
  "properties": {
    "addr:full":"82 Veys Dr Kelso WA 98626",
    "addr:housenumber":"82",
    "addr:postcode":"98626",
    "addr:street":"Veys Dr",
    "iso:country":"US",
    "sg:address":"82 Veys Dr",
    "sg:city":"Kelso",
    "sg:classifiers":[
        {
            "category":"Retail",
            "subcategory":"Laundry & Dry Cleaning",
            "type":"Services"
        }
    ],
    "sg:phone":"+1 360 425 3837",
    "sg:postcode":"98626",
    "sg:province":"WA",
    "wof:name":"Dirt Slayers Carpet Care",
    "wof:placetype":"venue"
},
  "geometry": {"coordinates":[-122.904129,46.160607],"type":"Point"}
}