{
  "type": "Feature",
  "properties": {
    "addr:full":"212 Market St Kirkland WA 98033",
    "addr:housenumber":"212",
    "addr:postcode":"98033",
    "addr:street":"Market St",
    "iso:country":"US",
    "sg:address":"212 Market St",
    "sg:city":"Kirkland",
    "sg:classifiers":[
        {
            "category":"Building & Trades",
            "subcategory":"Plumbing",
            "type":"Services"
        }
    ],
    "sg:phone":"+1 425 822 2055",
    "sg:postcode":"98033",
    "sg:province":"WA",
    "sg:tags":[
        "contractor"
    ],
    "sg:website":"www.bestplumbing.com",
    "wof:name":"Best Plumbing",
    "wof:placetype":"venue"
},
  "geometry": {"coordinates":[-122.209,47.677299],"type":"Point"}
}