{
  "type": "Feature",
  "properties": {
    "addr:full":"16021 NE 93rd St Vancouver WA 98682",
    "addr:housenumber":"16021",
    "addr:postcode":"98682",
    "addr:street":"Ne 93Rd St",
    "iso:country":"US",
    "sg:address":"16021 NE 93rd St",
    "sg:city":"Vancouver",
    "sg:classifiers":[
        {
            "category":"Structure",
            "subcategory":"Office Building",
            "type":"Public Place"
        }
    ],
    "sg:phone":"+1 360 256 9797",
    "sg:postcode":"98682",
    "sg:province":"WA",
    "sg:tags":[
        "park"
    ],
    "wof:name":"Pdx/Vnc Properties",
    "wof:placetype":"venue"
},
  "geometry": {"coordinates":[-122.507808,45.68988],"type":"Point"}
}