{
  "type": "Feature",
  "properties": {
    "addr:full":"11420 Virginia Ln Sedro Woolley WA 98284",
    "addr:housenumber":"11420",
    "addr:postcode":"98284",
    "addr:street":"Virginia Ln",
    "iso:country":"US",
    "sg:address":"11420 Virginia Ln",
    "sg:city":"Sedro Woolley",
    "sg:classifiers":[
        {
            "category":"Manufacturing",
            "subcategory":"Tools & Machinery",
            "type":"Manufacturing & Wholesale Goods"
        }
    ],
    "sg:phone":"+1 360 856 4158",
    "sg:postcode":"98284",
    "sg:province":"WA",
    "sg:tags":[
        "process",
        "control",
        "mfg",
        "instrument"
    ],
    "wof:name":"Gug Enterprises",
    "wof:placetype":"venue"
},
  "geometry": {"coordinates":[-122.149939,48.479677],"type":"Point"}
}