{
  "type": "Feature",
  "properties": {
    "addr:full":"425 Pike Street Seattle WA 98101",
    "addr:housenumber":"425",
    "addr:postcode":"98101",
    "addr:street":"Pike Street",
    "iso:country":"US",
    "sg:address":"425 Pike Street",
    "sg:city":"Seattle",
    "sg:classifiers":[
        {
            "category":"Professional",
            "subcategory":"Lawyer & Legal Services",
            "type":"Services"
        }
    ],
    "sg:phone":"+1 206 682 0171",
    "sg:postcode":"98101",
    "sg:province":"WA",
    "wof:name":"Bittner James U Atty",
    "wof:placetype":"venue"
},
  "geometry": {"coordinates":[-122.336399,47.610359],"type":"Point"}
}