{
  "type": "Feature",
  "properties": {
    "addr:full":"800 Ocean Shores Blvd NW Ocean Shores WA 98569",
    "addr:housenumber":"800",
    "addr:postcode":"98569",
    "addr:street":"Ocean Shores Blvd Nw",
    "iso:country":"US",
    "sg:address":"800 Ocean Shores Blvd NW",
    "sg:city":"Ocean Shores",
    "sg:classifiers":[
        {
            "category":"Retail",
            "subcategory":"Veterinary Services",
            "type":"Services"
        }
    ],
    "sg:phone":"+1 360 289 2030",
    "sg:postcode":"98569",
    "sg:province":"WA",
    "sg:tags":[
        "veterinarian"
    ],
    "wof:name":"Ocean Shores Animal Hospital",
    "wof:placetype":"venue"
},
  "geometry": {"coordinates":[-124.16616999999999,47.011423],"type":"Point"}
}