{
  "type": "Feature",
  "properties": {
    "iso:country":"US",
    "sg:address":"4238 268th Ave NE",
    "sg:city":"Redmond",
    "sg:classifiers":[
        {
            "category":"Manufacturing",
            "subcategory":"Printing",
            "type":"Manufacturing & Wholesale Goods"
        }
    ],
    "sg:phone":"+1 425 868 7878",
    "sg:postcode":"98053",
    "sg:province":"WA",
    "sg:tags":[
        "book"
    ],
    "wof:name":"Girshav Publishing Co",
    "wof:placetype":"venue"
},
  "geometry": {"coordinates":[-121.981286,47.645524],"type":"Point"}
}