{
  "type": "Feature",
  "properties": {
    "addr:full":"11222 Roosevelt Way NE Seattle WA 98125",
    "addr:housenumber":"11222",
    "addr:postcode":"98125",
    "addr:street":"Roosevelt Way Ne",
    "iso:country":"US",
    "sg:address":"11222 Roosevelt Way NE",
    "sg:city":"Seattle",
    "sg:classifiers":[
        {
            "category":"Professional",
            "subcategory":"Lawyer & Legal Services",
            "type":"Services"
        }
    ],
    "sg:phone":"+1 206 254 1234",
    "sg:postcode":"98125",
    "sg:province":"WA",
    "sg:tags":[
        "attorney",
        "family",
        "divorce",
        "practice",
        "plan",
        "law"
    ],
    "wof:name":"Anderson, Sherri M, Law Offices Of",
    "wof:placetype":"venue"
},
  "geometry": {"coordinates":[-122.31769199999999,47.710356],"type":"Point"}
}