{
  "type": "Feature",
  "properties": {
    "addr:full":"536 Rainier Ave S Renton WA 98055",
    "addr:housenumber":"536",
    "addr:postcode":"98055",
    "addr:street":"Rainier Ave S Renton",
    "iso:country":"US",
    "sg:address":"536 Rainier Ave S",
    "sg:city":"Renton",
    "sg:classifiers":[
        {
            "category":"Food & Beverages",
            "subcategory":"Groceries & Convenience Stores",
            "type":"Retail Goods"
        }
    ],
    "sg:phone":"+1 425 271 4968",
    "sg:postcode":"98055",
    "sg:province":"WA",
    "wof:name":"101 Deli & Grocery Mart II",
    "wof:placetype":"venue"
},
  "geometry": {"coordinates":[-122.214996,47.475201],"type":"Point"}
}