{
  "type": "Feature",
  "properties": {
    "addr:full":"1403 S 30th Ave Yakima WA 98902",
    "addr:housenumber":"1403",
    "addr:postcode":"98902",
    "addr:street":"S 30Th Ave",
    "iso:country":"US",
    "sg:address":"1403 S 30th Ave",
    "sg:city":"Yakima",
    "sg:classifiers":[
        {
            "category":"Manufacturing",
            "subcategory":"Textiles",
            "type":"Manufacturing & Wholesale Goods"
        }
    ],
    "sg:phone":"+1 509 577 0439",
    "sg:postcode":"98902",
    "sg:province":"WA",
    "sg:tags":[
        "mfg"
    ],
    "wof:name":"Sisters Handwoven Origina",
    "wof:placetype":"venue"
},
  "geometry": {"coordinates":[-120.549415,46.580167],"type":"Point"}
}