{
  "type": "Feature",
  "properties": {
    "iso:country":"US",
    "sg:address":"7801 NE 21st St",
    "sg:city":"Vancouver",
    "sg:classifiers":[
        {
            "category":"Building & Trades",
            "subcategory":"Construction",
            "type":"Services"
        }
    ],
    "sg:phone":"+1 360 883 6739",
    "sg:postcode":"98664",
    "sg:province":"WA",
    "sg:tags":[
        "hanging",
        "contractor"
    ],
    "wof:name":"Rhino Painting & Patching",
    "wof:placetype":"venue"
},
  "geometry": {"coordinates":[-122.593434,45.637875],"type":"Point"}
}