{
  "type": "Feature",
  "properties": {
    "addr:full":"550 Gage Blvd # 2 Richland WA 99352",
    "addr:housenumber":"550",
    "addr:postcode":"99352",
    "addr:street":"Gage Blvd # 2",
    "iso:country":"US",
    "sg:address":"550 Gage Blvd # 2",
    "sg:city":"Richland",
    "sg:classifiers":[
        {
            "category":"Health Services",
            "subcategory":"Doctor",
            "type":"Services"
        },
        {
            "category":"Health Services",
            "subcategory":"Clinic",
            "type":"Services"
        }
    ],
    "sg:phone":"+1 509 628 1362",
    "sg:postcode":"99352",
    "sg:province":"WA",
    "sg:tags":[
        "physician",
        "family",
        "practice",
        "surgeons",
        "manipulative",
        "osteopathic",
        "treatment",
        "medicine",
        "surgeon"
    ],
    "sg:website":"http://www.picmc.com",
    "wof:name":"Nelson, Charles L, Do - Physicians Immediate Care",
    "wof:placetype":"venue"
},
  "geometry": {"coordinates":[-119.263628,46.22713],"type":"Point"}
}