{
  "type": "Feature",
  "properties": {
    "addr:full":"1900 Rudkin Rd Union Gap WA 98903",
    "addr:postcode":"1900;98903",
    "addr:street":"Rudkin Rd",
    "iso:country":"US",
    "sg:address":"1900 Rudkin Rd",
    "sg:city":"Union Gap",
    "sg:classifiers":[
        {
            "category":"Home & Garden",
            "subcategory":"Carpets & Floor Coverings",
            "type":"Retail Goods"
        }
    ],
    "sg:phone":"+1 509 575 1526",
    "sg:postcode":"98903",
    "sg:province":"WA",
    "sg:tags":[
        "dealer",
        "rug"
    ],
    "wof:name":"End Of The Roll",
    "wof:placetype":"venue"
},
  "geometry": {"coordinates":[-120.472413,46.576245],"type":"Point"}
}