{
  "type": "Feature",
  "properties": {
    "addr:full":"15730 1st Ave S Burien WA 98148",
    "addr:housenumber":"15730",
    "addr:postcode":"98148",
    "addr:street":"1St Ave S Burien",
    "iso:country":"US",
    "sg:address":"15730 1st Ave S",
    "sg:city":"Burien",
    "sg:classifiers":[
        {
            "category":"Fast Food",
            "type":"Food & Drink"
        },
        {
            "category":"Restaurant",
            "type":"Food & Drink"
        },
        {
            "category":"Professional",
            "type":"Services"
        }
    ],
    "sg:phone":"+1 206 431 8600",
    "sg:postcode":"98148",
    "sg:province":"WA",
    "sg:tags":[
        "style",
        "family",
        "delivery",
        "lunch",
        "take",
        "brunch",
        "breakfast",
        "pizza"
    ],
    "sg:website":"http://www.roundtablepizza.com",
    "wof:name":"Round Table Pizza",
    "wof:placetype":"venue"
},
  "geometry": {"coordinates":[-122.33390300000001,47.462126],"type":"Point"}
}