{
  "type": "Feature",
  "properties": {
    "addr:full":"6200 13th Ave S Seattle WA 98108",
    "addr:housenumber":"6200",
    "addr:postcode":"98108",
    "addr:street":"13Th Ave S",
    "iso:country":"US",
    "sg:address":"6200 13th Ave S",
    "sg:city":"Seattle",
    "sg:classifiers":[
        {
            "category":"Health Services",
            "subcategory":"Dentist",
            "type":"Services"
        }
    ],
    "sg:phone":"+1 206 461 6943",
    "sg:postcode":"98108",
    "sg:province":"WA",
    "sg:tags":[
        "clinic",
        "dental"
    ],
    "wof:name":"Georgetown Dental Clinic",
    "wof:placetype":"venue"
},
  "geometry": {"coordinates":[-122.316109,47.547939],"type":"Point"}
}