{
  "type": "Feature",
  "properties": {
    "addr:full":"1757 244th Ave NE Sammamish WA 98074",
    "addr:housenumber":"1757",
    "addr:postcode":"98074",
    "addr:street":"244Th Ave Ne",
    "iso:country":"US",
    "sg:address":"1757 244th Ave NE",
    "sg:city":"Sammamish",
    "sg:classifiers":[
        {
            "category":"Organizations",
            "subcategory":"Religious Organization",
            "type":"Services"
        }
    ],
    "sg:phone":"+1 425 868 2123",
    "sg:postcode":"98074",
    "sg:province":"WA",
    "sg:tags":[
        "church"
    ],
    "sg:website":"www.goodsamepiscopal.org",
    "wof:name":"Good Samaritan Episcpal Church",
    "wof:placetype":"venue"
},
  "geometry": {"coordinates":[-122.013946,47.625604],"type":"Point"}
}