{
  "type": "Feature",
  "properties": {
    "addr:full":"4712 Brookdale Rd E Tacoma WA 98446",
    "addr:housenumber":"4712",
    "addr:postcode":"98446",
    "addr:street":"Brookdale Rd E",
    "iso:country":"US",
    "sg:address":"4712 Brookdale Rd E",
    "sg:city":"Tacoma",
    "sg:classifiers":[
        {
            "category":"Professional",
            "subcategory":"Business Services",
            "type":"Services"
        }
    ],
    "sg:phone":"+1 253 307 9680",
    "sg:postcode":"98446",
    "sg:province":"WA",
    "sg:website":"www.artprocessstudio.com",
    "wof:name":"Art Process Studio",
    "wof:placetype":"venue"
},
  "geometry": {"coordinates":[-122.36795100000001,47.114678],"type":"Point"}
}