{
  "type": "Feature",
  "properties": {
    "iso:country":"US",
    "sg:address":"23005 NE 77th St",
    "sg:city":"Redmond",
    "sg:classifiers":[
        {
            "category":"Banks & Credit Unions",
            "subcategory":"Bank",
            "type":"Services"
        }
    ],
    "sg:phone":"+1 425 868 6810",
    "sg:postcode":"98053",
    "sg:province":"WA",
    "sg:tags":[
        "loan",
        "broker"
    ],
    "wof:name":"American Lending Corp",
    "wof:placetype":"venue"
},
  "geometry": {"coordinates":[-122.030415,47.672786],"type":"Point"}
}