{
  "type": "Feature",
  "properties": {
    "iso:country":"US",
    "sg:address":"11150 NE Wing Point Dr",
    "sg:city":"Bainbridge Island",
    "sg:classifiers":[
        {
            "category":"Professional",
            "subcategory":"Research",
            "type":"Services"
        }
    ],
    "sg:phone":"+1 206 842 5178",
    "sg:postcode":"98110",
    "sg:province":"WA",
    "sg:tags":[
        "commercial",
        "physical"
    ],
    "wof:name":"Ocean Connection",
    "wof:placetype":"venue"
},
  "geometry": {"coordinates":[-122.498147,47.625269],"type":"Point"}
}