{
  "type": "Feature",
  "properties": {
    "addr:full":"2500 NE 65th Ave Vancouver WA 98661",
    "addr:housenumber":"2500",
    "addr:postcode":"98661",
    "addr:street":"Ne 65Th Ave",
    "iso:country":"US",
    "sg:address":"2500 NE 65th Ave",
    "sg:city":"Vancouver",
    "sg:classifiers":[
        {
            "category":"Social Services",
            "subcategory":"Child Care",
            "type":"Services"
        }
    ],
    "sg:phone":"+1 360 750 7501",
    "sg:postcode":"98661",
    "sg:province":"WA",
    "sg:tags":[
        "day"
    ],
    "wof:name":"Southwest Washington Child Care Consortium",
    "wof:placetype":"venue"
},
  "geometry": {"coordinates":[-122.605003,45.639702],"type":"Point"}
}