{
  "type": "Feature",
  "properties": {
    "addr:full":"10518 S Tacoma Way Lakewood WA 98499",
    "addr:housenumber":"10518",
    "addr:postcode":"98499",
    "addr:street":"S Tacoma Way",
    "iso:country":"US",
    "sg:address":"10518 S Tacoma Way",
    "sg:city":"Lakewood",
    "sg:classifiers":[
        {
            "category":"Personal",
            "subcategory":"Beauty Salon",
            "type":"Services"
        }
    ],
    "sg:phone":"+1 253 589 5229",
    "sg:postcode":"98499",
    "sg:province":"WA",
    "sg:tags":[
        "shop"
    ],
    "wof:name":"Gloria Wright",
    "wof:placetype":"venue"
},
  "geometry": {"coordinates":[-122.48406300000001,47.162171],"type":"Point"}
}