{
  "type": "Feature",
  "properties": {
    "addr:full":"1145 Broadway Plz Tacoma WA 98402",
    "addr:housenumber":"1145",
    "addr:postcode":"98402",
    "addr:street":"Broadway",
    "iso:country":"US",
    "sg:address":"1145 Broadway Plz",
    "sg:city":"Tacoma",
    "sg:classifiers":[
        {
            "category":"Banks & Credit Unions",
            "subcategory":"Investment Brokerage",
            "type":"Services"
        }
    ],
    "sg:phone":"+1 253 272 7700",
    "sg:postcode":"98402",
    "sg:province":"WA",
    "sg:tags":[
        "security"
    ],
    "sg:website":"www.agedwards.com",
    "wof:name":"A G Edwards & Sons Inc",
    "wof:placetype":"venue"
},
  "geometry": {"coordinates":[-122.43958600000001,47.251635],"type":"Point"}
}