{
  "type": "Feature",
  "properties": {
    "addr:full":"8708 Johnson Point Rd NE Olympia WA 98516",
    "addr:housenumber":"8708",
    "addr:postcode":"98516",
    "addr:street":"Johnson Point Rd Ne",
    "iso:country":"US",
    "sg:address":"8708 Johnson Point Rd NE",
    "sg:city":"Olympia",
    "sg:classifiers":[
        {
            "category":"Insurance",
            "subcategory":"Insurance Agent",
            "type":"Services"
        }
    ],
    "sg:phone":"+1 360 754 7424",
    "sg:postcode":"98516",
    "sg:province":"WA",
    "wof:name":"Met Life",
    "wof:placetype":"venue"
},
  "geometry": {"coordinates":[-122.81759099999999,47.164851],"type":"Point"}
}