{
  "type": "Feature",
  "properties": {
    "addr:full":"1602 W James Ln Apt L2 Kent WA 98032",
    "addr:housenumber":"1602",
    "addr:postcode":"98032",
    "addr:street":"W James Ln Apt",
    "iso:country":"US",
    "sg:address":"1602 W James Ln Apt L2",
    "sg:city":"Kent",
    "sg:classifiers":[
        {
            "category":"Manufacturing",
            "subcategory":"Buildings",
            "type":"Manufacturing & Wholesale Goods"
        },
        {
            "category":"Building & Trades",
            "subcategory":"Construction",
            "type":"Services"
        }
    ],
    "sg:phone":"+1 253 856 2157",
    "sg:postcode":"98032",
    "sg:province":"WA",
    "sg:tags":[
        "home",
        "builder",
        "contractor"
    ],
    "wof:name":"Andys Construction",
    "wof:placetype":"venue"
},
  "geometry": {"coordinates":[-122.25198399999999,47.384659],"type":"Point"}
}