{
  "type": "Feature",
  "properties": {
    "addr:full":"14700 NE 8th St Bellevue WA 98007",
    "addr:housenumber":"14700",
    "addr:postcode":"98007",
    "addr:street":"Ne 8Th St",
    "iso:country":"US",
    "sg:address":"14700 NE 8th St",
    "sg:city":"Bellevue",
    "sg:classifiers":[
        {
            "category":"Health Services",
            "subcategory":"Doctor",
            "type":"Services"
        }
    ],
    "sg:phone":"+1 425 644 7444",
    "sg:postcode":"98007",
    "sg:province":"WA",
    "sg:tags":[
        "dentist"
    ],
    "wof:name":"Cascadia Dental Specialists",
    "wof:placetype":"venue"
},
  "geometry": {"coordinates":[-122.143725,47.617123],"type":"Point"}
}