{
  "type": "Feature",
  "properties": {
    "addr:full":"7735 NE Hwy 99 Vancouver WA 98665",
    "addr:housenumber":"7735",
    "addr:postcode":"98665",
    "addr:street":"Ne Hwy 99",
    "iso:country":"US",
    "sg:address":"7735 NE Hwy 99",
    "sg:city":"Vancouver",
    "sg:classifiers":[
        {
            "category":"Health Services",
            "subcategory":"Doctor",
            "type":"Services"
        }
    ],
    "sg:phone":"+1 360 571 8181",
    "sg:postcode":"98665",
    "sg:province":"WA",
    "wof:name":"Gentech Dentist",
    "wof:placetype":"venue"
},
  "geometry": {"coordinates":[-122.66254000000001,45.675582],"type":"Point"}
}