{
  "type": "Feature",
  "properties": {
    "iso:country":"US",
    "sg:address":"3036 68th Ave W",
    "sg:city":"Tacoma",
    "sg:classifiers":[
        {
            "category":"Recreation",
            "subcategory":"Arcade",
            "type":"Entertainment"
        },
        {
            "category":"Cinema",
            "subcategory":"Movie Rental",
            "type":"Entertainment"
        }
    ],
    "sg:phone":"+1 253 564 7892",
    "sg:postcode":"98466",
    "sg:province":"WA",
    "sg:tags":[
        "leasing",
        "machine",
        "game",
        "video",
        "through",
        "coin",
        "merchandise"
    ],
    "wof:name":"Masterman Vending Co Inc",
    "wof:placetype":"venue"
},
  "geometry": {"coordinates":[-122.52772899999999,47.232123],"type":"Point"}
}