{
  "type": "Feature",
  "properties": {
    "addr:full":"11039 Woodward Ave S Seattle WA 98178",
    "addr:housenumber":"11039",
    "addr:postcode":"98178",
    "addr:street":"Woodward Ave S",
    "iso:country":"US",
    "sg:address":"11039 Woodward Ave S",
    "sg:city":"Seattle",
    "sg:classifiers":[
        {
            "category":"Health Services",
            "subcategory":"Nursing And Care Facility",
            "type":"Services"
        }
    ],
    "sg:phone":"+1 206 772 9097",
    "sg:postcode":"98178",
    "sg:province":"WA",
    "wof:name":"Jubilee Adult Family Home",
    "wof:placetype":"venue"
},
  "geometry": {"coordinates":[-122.238789,47.5038],"type":"Point"}
}