{
  "type": "Feature",
  "properties": {
    "addr:full":"11023 NE 143rd St Kirkland WA 98034",
    "addr:housenumber":"11023",
    "addr:postcode":"98034",
    "addr:street":"Ne 143Rd St",
    "iso:country":"US",
    "sg:address":"11023 NE 143rd St",
    "sg:city":"Kirkland",
    "sg:classifiers":[
        {
            "category":"Professional",
            "type":"Services"
        }
    ],
    "sg:phone":"+1 425 488 8209",
    "sg:postcode":"98034",
    "sg:province":"WA",
    "wof:name":"Steven Haynes",
    "wof:placetype":"venue"
},
  "geometry": {"coordinates":[-122.19477999999999,47.730709],"type":"Point"}
}