{
  "type": "Feature",
  "properties": {
    "addr:full":"526 Tucannon Rd Dayton WA 99328",
    "addr:housenumber":"526",
    "addr:postcode":"99328",
    "addr:street":"Tucannon Rd",
    "iso:country":"US",
    "sg:address":"526 Tucannon Rd",
    "sg:city":"Dayton",
    "sg:classifiers":[
        {
            "category":"Food & Beverages",
            "subcategory":"Groceries & Convenience Stores",
            "type":"Retail Goods"
        }
    ],
    "sg:phone":"+1 509 382 4947",
    "sg:postcode":"99328",
    "sg:province":"WA",
    "wof:name":"Crissy's Quick Stop",
    "wof:placetype":"venue"
},
  "geometry": {"coordinates":[-117.89588999999999,46.465919],"type":"Point"}
}