{
  "type": "Feature",
  "properties": {
    "addr:full":"218 3rd Ave SW Quincy WA 98848",
    "addr:housenumber":"218",
    "addr:postcode":"98848",
    "addr:street":"3Rd Ave Sw",
    "iso:country":"US",
    "sg:address":"218 3rd Ave SW",
    "sg:city":"Quincy",
    "sg:classifiers":[
        {
            "category":"Freight",
            "type":"Transportation"
        }
    ],
    "sg:phone":"+1 509 787 2303",
    "sg:postcode":"98848",
    "sg:province":"WA",
    "sg:tags":[
        "commercial",
        "storage"
    ],
    "wof:name":"Patton's Mini Storage Rentals",
    "wof:placetype":"venue"
},
  "geometry": {"coordinates":[-119.858566,47.235634],"type":"Point"}
}