{
  "type": "Feature",
  "properties": {
    "addr:full":"521 Front St Lynden WA 98264",
    "addr:housenumber":"521",
    "addr:postcode":"98264",
    "addr:street":"Front St",
    "iso:country":"US",
    "sg:address":"521 Front St",
    "sg:city":"Lynden",
    "sg:classifiers":[
        {
            "category":"Retail",
            "subcategory":"Repair Shop",
            "type":"Services"
        }
    ],
    "sg:phone":"+1 360 354 2410",
    "sg:postcode":"98264",
    "sg:province":"WA",
    "sg:tags":[
        "watch"
    ],
    "wof:name":"Keith's Watch Repair",
    "wof:placetype":"venue"
},
  "geometry": {"coordinates":[-122.45320599999999,48.942622],"type":"Point"}
}