{
  "type": "Feature",
  "properties": {
    "addr:full":"9020 N Fairview Rd Spokane WA 99217",
    "addr:housenumber":"9020",
    "addr:postcode":"99217",
    "addr:street":"N Fairview Rd",
    "iso:country":"US",
    "sg:address":"9020 N Fairview Rd",
    "sg:city":"Spokane",
    "sg:classifiers":[
        {
            "category":"Wholesale",
            "subcategory":"Stationery",
            "type":"Manufacturing & Wholesale Goods"
        }
    ],
    "sg:phone":"+1 509 467 0687",
    "sg:postcode":"99217",
    "sg:province":"WA",
    "sg:tags":[
        "supply"
    ],
    "wof:name":"Northern Forms",
    "wof:placetype":"venue"
},
  "geometry": {"coordinates":[-117.362157,47.739696],"type":"Point"}
}