{
  "type": "Feature",
  "properties": {
    "addr:full":"806 E Roy St Seattle WA 98102",
    "addr:housenumber":"806",
    "addr:postcode":"98102",
    "addr:street":"E Roy St",
    "iso:country":"US",
    "sg:address":"806 E Roy St",
    "sg:city":"Seattle",
    "sg:classifiers":[
        {
            "category":"Real Estate",
            "subcategory":"Real Estate Operator",
            "type":"Services"
        }
    ],
    "sg:phone":"+1 206 324 0543",
    "sg:postcode":"98102",
    "sg:province":"WA",
    "sg:tags":[
        "building",
        "nonresidential"
    ],
    "wof:name":"Johnson Meeker Property Invest",
    "wof:placetype":"venue"
},
  "geometry": {"coordinates":[-122.322012,47.625191],"type":"Point"}
}