{
  "type": "Feature",
  "properties": {
    "addr:full":"2220 77th Ave SE Mercer Island WA 98040",
    "addr:housenumber":"2220",
    "addr:postcode":"98040",
    "addr:street":"77Th Ave Se",
    "iso:country":"US",
    "sg:address":"2220 77th Ave SE",
    "sg:city":"Mercer Island",
    "sg:classifiers":[
        {
            "category":"Wholesale",
            "subcategory":"Home Furnishings",
            "type":"Manufacturing & Wholesale Goods"
        }
    ],
    "sg:phone":"+1 206 232 9991",
    "sg:postcode":"98040",
    "sg:province":"WA",
    "sg:tags":[
        "linen"
    ],
    "wof:name":"Complements",
    "wof:placetype":"venue"
},
  "geometry": {"coordinates":[-122.234936,47.590038],"type":"Point"}
}