{
  "type": "Feature",
  "properties": {
    "addr:full":"1502 Pike St NW Auburn WA 98001",
    "addr:housenumber":"1502",
    "addr:postcode":"98001",
    "addr:street":"Pike St Nw",
    "iso:country":"US",
    "sg:address":"1502 Pike St NW",
    "sg:city":"Auburn",
    "sg:classifiers":[
        {
            "category":"Real Estate",
            "subcategory":"Real Estate Agent",
            "type":"Services"
        }
    ],
    "sg:phone":"+1 253 833 1531",
    "sg:postcode":"98001",
    "sg:province":"WA",
    "sg:tags":[
        "management"
    ],
    "wof:name":"Hart Industrial Parks",
    "wof:placetype":"venue"
},
  "geometry": {"coordinates":[-122.25197,47.326112],"type":"Point"}
}