{
  "type": "Feature",
  "properties": {
    "addr:full":"30405 SE 84th St Issaquah WA 98027",
    "addr:housenumber":"30405",
    "addr:postcode":"98027",
    "addr:street":"Se 84Th St",
    "iso:country":"US",
    "sg:address":"30405 SE 84th St",
    "sg:city":"Issaquah",
    "sg:classifiers":[
        {
            "category":"Utilities",
            "subcategory":"Fuel Oil & Lpg",
            "type":"Services"
        }
    ],
    "sg:phone":"+1 425 222 3868",
    "sg:postcode":"98027",
    "sg:province":"WA",
    "sg:tags":[
        "liquefied",
        "gas",
        "petroleum"
    ],
    "wof:name":"Suburban Propane",
    "wof:placetype":"venue"
},
  "geometry": {"coordinates":[-121.93454199999999,47.52555],"type":"Point"}
}