{
  "type": "Feature",
  "properties": {
    "addr:full":"14615 15th Avenue NE Shoreline WA 98155",
    "addr:housenumber":"14615",
    "addr:postcode":"98155",
    "addr:street":"15Th Avenue Ne",
    "iso:country":"US",
    "sg:address":"14615 15th Avenue NE",
    "sg:city":"Shoreline",
    "sg:classifiers":[
        {
            "category":"Coffee & Tea",
            "type":"Food & Drink"
        }
    ],
    "sg:phone":"+1 206 365 3834",
    "sg:postcode":"98155",
    "sg:province":"WA",
    "wof:name":"Coffee Shack",
    "wof:placetype":"venue"
},
  "geometry": {"coordinates":[-122.312929,47.735058],"type":"Point"}
}