{
  "type": "Feature",
  "properties": {
    "addr:full":"4817 6th Ave NW Marysville WA 98271",
    "addr:housenumber":"4817",
    "addr:postcode":"98271",
    "addr:street":"6Th Ave Nw",
    "iso:country":"US",
    "sg:address":"4817 6th Ave NW",
    "sg:city":"Marysville",
    "sg:classifiers":[
        {
            "category":"Manufacturing",
            "subcategory":"Signs",
            "type":"Manufacturing & Wholesale Goods"
        }
    ],
    "sg:phone":"+1 360 658 8402",
    "sg:postcode":"98271",
    "sg:province":"WA",
    "sg:tags":[
        "specialty",
        "mfg"
    ],
    "wof:name":"RC Neon Signs",
    "wof:placetype":"venue"
},
  "geometry": {"coordinates":[-122.240998,48.040317],"type":"Point"}
}