{
  "type": "Feature",
  "properties": {
    "addr:full":"4502 S Steele St Tacoma WA 98409",
    "addr:housenumber":"4502",
    "addr:postcode":"98409",
    "addr:street":"S Steele St",
    "iso:country":"US",
    "sg:address":"4502 S Steele St",
    "sg:city":"Tacoma",
    "sg:classifiers":[
        {
            "category":"Restaurant",
            "type":"Food & Drink"
        }
    ],
    "sg:menulink":"http://www.allmenus.com/wa/tacoma/95968-charleys-grilled-subs/menu/",
    "sg:phone":"+1 253 475 0800",
    "sg:postcode":"98409",
    "sg:province":"WA",
    "sg:tags":[
        "wrap",
        "american",
        "sandwich"
    ],
    "wof:name":"Charley's Grilled Subs",
    "wof:placetype":"venue"
},
  "geometry": {"coordinates":[-122.467608,47.217853],"type":"Point"}
}