{
  "type": "Feature",
  "properties": {
    "addr:full":"1998 Midway Ln Bellingham WA 98226",
    "addr:housenumber":"1998",
    "addr:postcode":"98226",
    "addr:street":"Midway Ln",
    "iso:country":"US",
    "sg:address":"1998 Midway Ln",
    "sg:city":"Bellingham",
    "sg:classifiers":[
        {
            "category":"Retail",
            "subcategory":"Storage",
            "type":"Services"
        }
    ],
    "sg:phone":"+1 360 733 1032",
    "sg:postcode":"98226",
    "sg:province":"WA",
    "sg:tags":[
        "self"
    ],
    "wof:name":"Bellingar Storage Inc",
    "wof:placetype":"venue"
},
  "geometry": {"coordinates":[-122.45070699999999,48.785856],"type":"Point"}
}