{
  "type": "Feature",
  "properties": {
    "addr:full":"2110 NE 51st St Vancouver WA 98663",
    "addr:housenumber":"2110",
    "addr:postcode":"98663",
    "addr:street":"Ne 51St St",
    "iso:country":"US",
    "sg:address":"2110 NE 51st St",
    "sg:city":"Vancouver",
    "sg:classifiers":[
        {
            "category":"Building & Trades",
            "subcategory":"Plumbing",
            "type":"Services"
        }
    ],
    "sg:phone":"+1 360 695 0789",
    "sg:postcode":"98663",
    "sg:province":"WA",
    "sg:tags":[
        "air",
        "heating",
        "conditioning",
        "contractor"
    ],
    "wof:name":"Airtech",
    "wof:placetype":"venue"
},
  "geometry": {"coordinates":[-122.650904,45.659085],"type":"Point"}
}