{
  "type": "Feature",
  "properties": {
    "addr:full":"3513 NE 45th St Seattle WA 98105",
    "addr:housenumber":"3513",
    "addr:postcode":"98105",
    "addr:street":"Ne 45Th St",
    "iso:country":"US",
    "sg:address":"3513 NE 45th St",
    "sg:city":"Seattle",
    "sg:classifiers":[
        {
            "category":"Professional",
            "subcategory":"Employment Agencies",
            "type":"Services"
        }
    ],
    "sg:phone":"+1 206 971 3680",
    "sg:postcode":"98105",
    "sg:province":"WA",
    "sg:tags":[
        "opportunity"
    ],
    "wof:name":"Global Employment Network",
    "wof:placetype":"venue"
},
  "geometry": {"coordinates":[-122.291141,47.661124],"type":"Point"}
}