{
  "type": "Feature",
  "properties": {
    "addr:full":"510 W 14th St Vancouver WA 98660",
    "addr:housenumber":"510",
    "addr:postcode":"98660",
    "addr:street":"W 14Th St",
    "iso:country":"US",
    "sg:address":"510 W 14th St",
    "sg:city":"Vancouver",
    "sg:classifiers":[
        {
            "category":"Professional",
            "type":"Services"
        }
    ],
    "sg:phone":"+1 360 695 1804",
    "sg:postcode":"98660",
    "sg:province":"WA",
    "sg:tags":[
        "establishment"
    ],
    "wof:name":"Franklin Commons",
    "wof:placetype":"venue"
},
  "geometry": {"coordinates":[-122.67698,45.631878],"type":"Point"}
}