{
  "type": "Feature",
  "properties": {
    "addr:full":"934 S Nevada Dr Longview WA 98632",
    "addr:housenumber":"934",
    "addr:postcode":"98632",
    "addr:street":"S Nevada Dr",
    "iso:country":"US",
    "sg:address":"934 S Nevada Dr",
    "sg:city":"Longview",
    "sg:classifiers":[
        {
            "category":"Professional",
            "subcategory":"Business Services",
            "type":"Services"
        }
    ],
    "sg:phone":"+1 360 501 2658",
    "sg:postcode":"98632",
    "sg:province":"WA",
    "wof:name":"Tarassa D Whiper",
    "wof:placetype":"venue"
},
  "geometry": {"coordinates":[-122.936167,46.165848],"type":"Point"}
}