{
  "type": "Feature",
  "properties": {
    "addr:full":"12010 Rd E SE Othello WA 99344",
    "addr:housenumber":"12010",
    "addr:postcode":"99344",
    "addr:street":"Rd E Se Othello",
    "iso:country":"US",
    "sg:address":"12010 Rd E SE",
    "sg:city":"Othello",
    "sg:classifiers":[
        {
            "category":"Professional",
            "type":"Services"
        }
    ],
    "sg:phone":"+1 509 346 1338",
    "sg:postcode":"99344",
    "sg:province":"WA",
    "sg:tags":[
        "establishment"
    ],
    "wof:name":"Grant Co Fire Dist 11",
    "wof:placetype":"venue"
},
  "geometry": {"coordinates":[-119.389413,46.912383],"type":"Point"}
}