{
  "type": "Feature",
  "properties": {
    "addr:full":"10832 36th Ave SW Seattle WA 98146",
    "addr:housenumber":"10832",
    "addr:postcode":"98146",
    "addr:street":"36Th Ave Sw",
    "iso:country":"US",
    "sg:address":"10832 36th Ave SW",
    "sg:city":"Seattle",
    "sg:classifiers":[
        {
            "category":"Professional",
            "subcategory":"Management & Consulting",
            "type":"Services"
        }
    ],
    "sg:phone":"+1 206 901 0330",
    "sg:postcode":"98146",
    "sg:province":"WA",
    "sg:tags":[
        "business"
    ],
    "wof:name":"Ronald L Oldham",
    "wof:placetype":"venue"
},
  "geometry": {"coordinates":[-122.377585,47.5053],"type":"Point"}
}