{
  "type": "Feature",
  "properties": {
    "addr:full":"802 Woods Rd Sunnyside WA 98944",
    "addr:housenumber":"802",
    "addr:postcode":"98944",
    "addr:street":"Woods Rd",
    "iso:country":"US",
    "sg:address":"802 Woods Rd",
    "sg:city":"Sunnyside",
    "sg:classifiers":[
        {
            "category":"Real Estate",
            "subcategory":"Real Estate Operator",
            "type":"Services"
        }
    ],
    "sg:phone":"+1 509 837 6039",
    "sg:postcode":"98944",
    "sg:province":"WA",
    "sg:tags":[
        "property",
        "lessor"
    ],
    "wof:name":"Norlene L Mc Clure",
    "wof:placetype":"venue"
},
  "geometry": {"coordinates":[-120.017354,46.334263],"type":"Point"}
}