{
  "type": "Feature",
  "properties": {
    "addr:full":"17408 NE 45th St Redmond WA 98052",
    "addr:housenumber":"17408",
    "addr:postcode":"98052",
    "addr:street":"Ne 45Th St",
    "iso:country":"US",
    "sg:address":"17408 NE 45th St",
    "sg:city":"Redmond",
    "sg:classifiers":[
        {
            "category":"Banks & Credit Unions",
            "subcategory":"Financial Services",
            "type":"Services"
        }
    ],
    "sg:phone":"+1 425 556 5400",
    "sg:postcode":"98052",
    "sg:province":"WA",
    "sg:tags":[
        "investor"
    ],
    "wof:name":"Christopher A Snare",
    "wof:placetype":"venue"
},
  "geometry": {"coordinates":[-122.111261,47.649943],"type":"Point"}
}