{
  "type": "Feature",
  "properties": {
    "addr:full":"12111 E Sprague Ave Spokane WA 99206",
    "addr:housenumber":"12111",
    "addr:postcode":"99206",
    "addr:street":"E Sprague Ave",
    "iso:country":"US",
    "sg:address":"12111 E Sprague Ave",
    "sg:city":"Spokane",
    "sg:classifiers":[
        {
            "category":"Wholesale",
            "subcategory":"Stationery",
            "type":"Manufacturing & Wholesale Goods"
        }
    ],
    "sg:phone":"+1 509 924 1665",
    "sg:postcode":"99206",
    "sg:province":"WA",
    "sg:tags":[
        "cards",
        "greeting"
    ],
    "wof:name":"Card Shop",
    "wof:placetype":"venue"
},
  "geometry": {"coordinates":[-117.239873,47.657137],"type":"Point"}
}