{
  "type": "Feature",
  "properties": {
    "iso:country":"US",
    "sg:address":"4301 S Pine St",
    "sg:city":"Tacoma",
    "sg:classifiers":[
        {
            "category":"Professional",
            "subcategory":"Accounting & Tax Preparation",
            "type":"Services"
        }
    ],
    "sg:phone":"+1 253 471 0492",
    "sg:postcode":"98409",
    "sg:province":"WA",
    "sg:tags":[
        "accountant"
    ],
    "wof:name":"Scott D Boyd CPA PS",
    "wof:placetype":"venue"
},
  "geometry": {"coordinates":[-122.473551,47.219047],"type":"Point"}
}