{
  "type": "Feature",
  "properties": {
    "addr:full":"20909 Highway 99 Lynnwood WA 98036",
    "addr:housenumber":"20909",
    "addr:postcode":"98036",
    "addr:street":"Highway 99",
    "iso:country":"US",
    "sg:address":"20909 Highway 99",
    "sg:city":"Lynnwood",
    "sg:phone":"+1 425 778 2186",
    "sg:postcode":"98036",
    "sg:province":"WA",
    "wof:name":"Prime Auto Body Repair, LLC",
    "wof:placetype":"venue"
},
  "geometry": {"coordinates":[-122.32487,47.809187],"type":"Point"}
}