{
  "type": "Feature",
  "properties": {
    "addr:full":"32034 23rd Ave S Federal Way WA 98003",
    "addr:housenumber":"32034",
    "addr:postcode":"98003",
    "addr:street":"23Rd Ave S Federal Way",
    "iso:country":"US",
    "sg:address":"32034 23rd Ave S",
    "sg:city":"Federal Way",
    "sg:classifiers":[
        {
            "category":"Restaurant",
            "type":"Food & Drink"
        }
    ],
    "sg:phone":"+1 253 946 5718",
    "sg:postcode":"98003",
    "sg:province":"WA",
    "sg:tags":[
        "eating"
    ],
    "wof:name":"Egg Roll King",
    "wof:placetype":"venue"
},
  "geometry": {"coordinates":[-122.303551,47.314612],"type":"Point"}
}