{
  "type": "Feature",
  "properties": {
    "addr:full":"1624 4th Ave E Olympia WA 98506",
    "addr:housenumber":"1624",
    "addr:postcode":"98506",
    "addr:street":"4Th Ave E",
    "iso:country":"US",
    "sg:address":"1624 4th Ave E",
    "sg:city":"Olympia",
    "sg:classifiers":[
        {
            "category":"Insurance",
            "subcategory":"Insurance Agent",
            "type":"Services"
        }
    ],
    "sg:phone":"+1 360 352 9797",
    "sg:postcode":"98506",
    "sg:province":"WA",
    "wof:name":"John D Aakre FIC",
    "wof:placetype":"venue"
},
  "geometry": {"coordinates":[-122.879329,47.046128],"type":"Point"}
}