{
  "type": "Feature",
  "properties": {
    "addr:full":"2925 Fairview Ave E Seattle WA 98102",
    "addr:housenumber":"2925",
    "addr:postcode":"98102",
    "addr:street":"Fairview Ave E",
    "iso:country":"US",
    "sg:address":"2925 Fairview Ave E",
    "sg:city":"Seattle",
    "sg:classifiers":[
        {
            "category":"Recreation",
            "subcategory":"Marina",
            "type":"Entertainment"
        }
    ],
    "sg:phone":"+1 206 329 4459",
    "sg:postcode":"98102",
    "sg:province":"WA",
    "sg:tags":[
        "rent",
        "boat"
    ],
    "wof:name":"Thunderbird Marina",
    "wof:placetype":"venue"
},
  "geometry": {"coordinates":[-122.327072,47.645621],"type":"Point"}
}