{
  "type": "Feature",
  "properties": {
    "iso:country":"US",
    "sg:address":"890 W Golden Pheasant Rd",
    "sg:city":"Shelton",
    "sg:classifiers":[
        {
            "category":"Retail",
            "subcategory":"Repair Shop",
            "type":"Services"
        },
        {
            "category":"Wholesale",
            "subcategory":"Auto Parts",
            "type":"Manufacturing & Wholesale Goods"
        }
    ],
    "sg:phone":"+1 360 427 1725",
    "sg:postcode":"98584",
    "sg:province":"WA",
    "sg:tags":[
        "vehicle",
        "motor",
        "cushion",
        "supply"
    ],
    "sg:website":"www.americancushionind.com",
    "wof:name":"American Cushion Industries",
    "wof:placetype":"venue"
},
  "geometry": {"coordinates":[-123.097919,47.170767],"type":"Point"}
}