{
  "type": "Feature",
  "properties": {
    "addr:full":"203 E Augusta Ave Spokane WA 99207",
    "addr:housenumber":"203",
    "addr:postcode":"99207",
    "addr:street":"E Augusta Ave",
    "iso:country":"US",
    "sg:address":"203 E Augusta Ave",
    "sg:city":"Spokane",
    "sg:classifiers":[
        {
            "category":"Wholesale",
            "subcategory":"Electrical",
            "type":"Manufacturing & Wholesale Goods"
        }
    ],
    "sg:phone":"+1 509 325 4500",
    "sg:postcode":"99207",
    "sg:province":"WA",
    "sg:tags":[
        "equipment",
        "electric",
        "supply"
    ],
    "wof:name":"Columbia Electric Supply",
    "wof:placetype":"venue"
},
  "geometry": {"coordinates":[-117.406312,47.672882],"type":"Point"}
}