{
  "type": "Feature",
  "properties": {
    "addr:full":"18733 Hwy 99 Lynnwood WA 98037",
    "addr:housenumber":"18733",
    "addr:postcode":"98037",
    "addr:street":"Hwy 99",
    "iso:country":"US",
    "sg:address":"18733 Hwy 99",
    "sg:city":"Lynnwood",
    "sg:classifiers":[
        {
            "category":"Food & Beverages",
            "subcategory":"Groceries & Convenience Stores",
            "type":"Retail Goods"
        }
    ],
    "sg:phone":"+1 425 774 9888",
    "sg:postcode":"98037",
    "sg:province":"WA",
    "wof:name":"7-Eleven",
    "wof:placetype":"venue"
},
  "geometry": {"coordinates":[-122.307907,47.829436],"type":"Point"}
}