{
  "type": "Feature",
  "properties": {
    "addr:full":"510 SE Old Arcadia Rd Shelton WA 98584",
    "addr:housenumber":"510",
    "addr:postcode":"98584",
    "addr:street":"Se Old Arcadia Rd",
    "iso:country":"US",
    "sg:address":"510 SE Old Arcadia Rd",
    "sg:city":"Shelton",
    "sg:classifiers":[
        {
            "category":"Shopping",
            "subcategory":"Gifts & Souvenirs",
            "type":"Retail Goods"
        }
    ],
    "sg:phone":"+1 360 426 8111",
    "sg:postcode":"98584",
    "sg:province":"WA",
    "sg:tags":[
        "shop"
    ],
    "wof:name":"Cove Crystal Shop",
    "wof:placetype":"venue"
},
  "geometry": {"coordinates":[-123.044714,47.199865],"type":"Point"}
}