{
  "type": "Feature",
  "properties": {
    "addr:full":"14701 Purdy Dr NW Gig Harbor WA 98332",
    "addr:housenumber":"14701",
    "addr:postcode":"98332",
    "addr:street":"Purdy Dr Nw",
    "iso:country":"US",
    "sg:address":"14701 Purdy Dr NW",
    "sg:city":"Gig Harbor",
    "sg:classifiers":[
        {
            "category":"Shopping",
            "type":"Retail Goods"
        }
    ],
    "sg:phone":"+1 253 853 4633",
    "sg:postcode":"98332",
    "sg:province":"WA",
    "sg:tags":[
        "merchandise"
    ],
    "wof:name":"L & R Enterprises",
    "wof:placetype":"venue"
},
  "geometry": {"coordinates":[-122.626069,47.393259],"type":"Point"}
}