{
  "type": "Feature",
  "properties": {
    "addr:full":"3552 Saturday Ave Malaga WA 98828",
    "addr:housenumber":"3552",
    "addr:postcode":"98828",
    "addr:street":"Saturday Ave",
    "iso:country":"US",
    "sg:address":"3552 Saturday Ave",
    "sg:city":"Malaga",
    "sg:classifiers":[
        {
            "category":"Building & Trades",
            "subcategory":"Construction",
            "type":"Services"
        }
    ],
    "sg:phone":"+1 509 665 9798",
    "sg:postcode":"98828",
    "sg:province":"WA",
    "sg:tags":[
        "excavation",
        "contractor"
    ],
    "wof:name":"P J Excavation Inc",
    "wof:placetype":"venue"
},
  "geometry": {"coordinates":[-120.18655200000001,47.365764],"type":"Point"}
}