{
  "type": "Feature",
  "properties": {
    "addr:full":"425 N Columbia Center Blvd Kennewick WA 99336",
    "addr:housenumber":"425",
    "addr:postcode":"99336",
    "addr:street":"N Columbia Center Blvd",
    "iso:country":"US",
    "sg:address":"425 N Columbia Center Blvd",
    "sg:city":"Kennewick",
    "sg:classifiers":[
        {
            "category":"Cinema",
            "subcategory":"Movie Rental",
            "type":"Entertainment"
        }
    ],
    "sg:phone":"+1 509 783 8528",
    "sg:postcode":"99336",
    "sg:province":"WA",
    "sg:tags":[
        "video",
        "tape"
    ],
    "wof:name":"Video Tek",
    "wof:placetype":"venue"
},
  "geometry": {"coordinates":[-119.225678,46.211616],"type":"Point"}
}