{
  "type": "Feature",
  "properties": {
    "addr:full":"520 Pike St Seattle WA 98101",
    "addr:housenumber":"520",
    "addr:postcode":"98101",
    "addr:street":"Pike St",
    "iso:country":"US",
    "sg:address":"520 Pike St",
    "sg:city":"Seattle",
    "sg:classifiers":[
        {
            "category":"Manufacturing",
            "subcategory":"Electronics",
            "type":"Manufacturing & Wholesale Goods"
        },
        {
            "category":"Professional",
            "subcategory":"Computer Services",
            "type":"Services"
        }
    ],
    "sg:phone":"+1 206 812 1290",
    "sg:postcode":"98101",
    "sg:province":"WA",
    "sg:tags":[
        "semiconductor",
        "consultant",
        "contracting",
        "devices",
        "engineer"
    ],
    "wof:name":"Equator Technologies Inc",
    "wof:placetype":"venue"
},
  "geometry": {"coordinates":[-122.33465700000001,47.61111],"type":"Point"}
}