{
  "type": "Feature",
  "properties": {
    "addr:full":"10500 NE 8th St Ste 218 Bellevue WA 98004",
    "addr:housenumber":"10500",
    "addr:postcode":"98004",
    "addr:street":"Ne 8Th St Ste 218",
    "iso:country":"US",
    "sg:address":"10500 NE 8th St Ste 218",
    "sg:city":"Bellevue",
    "sg:classifiers":[
        {
            "category":"Deli",
            "type":"Food & Drink"
        },
        {
            "category":"Food & Beverages",
            "subcategory":"Bakery",
            "type":"Retail Goods"
        }
    ],
    "sg:phone":"+1 425 646 7222",
    "sg:postcode":"98004",
    "sg:province":"WA",
    "sg:tags":[
        "sandwich"
    ],
    "wof:name":"Wintergarden Deli Llc",
    "wof:placetype":"venue"
},
  "geometry": {"coordinates":[-122.200371,47.617602],"type":"Point"}
}