{
  "type": "Feature",
  "properties": {
    "addr:full":"1404 Riverside Dr Mount Vernon WA 98273",
    "addr:housenumber":"1404",
    "addr:postcode":"98273",
    "addr:street":"Riverside Dr",
    "iso:country":"US",
    "sg:address":"1404 Riverside Dr",
    "sg:city":"Mount Vernon",
    "sg:classifiers":[
        {
            "category":"Professional",
            "type":"Services"
        }
    ],
    "sg:phone":"+1 360 424 8190",
    "sg:postcode":"98273",
    "sg:province":"WA",
    "wof:name":"Classic Services",
    "wof:placetype":"venue"
},
  "geometry": {"coordinates":[-122.335093,48.435149],"type":"Point"}
}