{
  "type": "Feature",
  "properties": {
    "addr:full":"1100 Freeway Dr Mount Vernon WA 98273",
    "addr:housenumber":"1100",
    "addr:postcode":"98273",
    "addr:street":"Freeway Dr",
    "iso:country":"US",
    "sg:address":"1100 Freeway Dr",
    "sg:city":"Mount Vernon",
    "sg:classifiers":[
        {
            "category":"Autos & Motor Vehicles",
            "subcategory":"Automobile Sales",
            "type":"Retail Goods"
        }
    ],
    "sg:phone":"+1 360 424 3231",
    "sg:postcode":"98273",
    "sg:province":"WA",
    "sg:tags":[
        "car"
    ],
    "sg:website":"www.bladechevy.com",
    "wof:name":"Blade Chevrolet",
    "wof:placetype":"venue"
},
  "geometry": {"coordinates":[-122.34200300000001,48.430901],"type":"Point"}
}