{
  "type": "Feature",
  "properties": {
    "addr:full":"6108 Community Pl SW Ste 1 Lakewood WA 98499",
    "addr:housenumber":"6108",
    "addr:postcode":"98499",
    "addr:street":"Community Pl Sw Ste 1",
    "iso:country":"US",
    "sg:address":"6108 Community Pl SW Ste 1",
    "sg:city":"Lakewood",
    "sg:classifiers":[
        {
            "category":"Professional",
            "subcategory":"Lawyer & Legal Services",
            "type":"Services"
        }
    ],
    "sg:phone":"+1 253 588 5266",
    "sg:postcode":"98499",
    "sg:province":"WA",
    "sg:tags":[
        "divorce",
        "law",
        "family"
    ],
    "wof:name":"Ek Riley Investments",
    "wof:placetype":"venue"
},
  "geometry": {"coordinates":[-122.518676,47.174263],"type":"Point"}
}