{
  "type": "Feature",
  "properties": {
    "addr:full":"5107 State Hwy 3 Port Orchard WA 98367",
    "addr:housenumber":"5107",
    "addr:postcode":"98367",
    "addr:street":"State Hwy 3",
    "iso:country":"US",
    "sg:address":"5107 State Hwy 3",
    "sg:city":"Port Orchard",
    "sg:classifiers":[
        {
            "category":"Building & Trades",
            "subcategory":"Construction",
            "type":"Services"
        }
    ],
    "sg:phone":"+1 360 674 2100",
    "sg:postcode":"98367",
    "sg:province":"WA",
    "sg:tags":[
        "excavation",
        "contractor",
        "underground",
        "general",
        "road",
        "utility"
    ],
    "wof:name":"Stan Palmer Construction Inc",
    "wof:placetype":"venue"
},
  "geometry": {"coordinates":[-122.738354,47.513398],"type":"Point"}
}