{
  "type": "Feature",
  "properties": {
    "addr:full":"62 Naselle Rd Naselle WA 98638",
    "addr:housenumber":"62",
    "addr:postcode":"98638",
    "addr:street":"Naselle Rd",
    "iso:country":"US",
    "sg:address":"62 Naselle Rd",
    "sg:city":"Naselle",
    "sg:classifiers":[
        {
            "category":"Utilities",
            "subcategory":"Mobile Phone",
            "type":"Services"
        }
    ],
    "sg:phone":"+1 360 484 7711",
    "sg:postcode":"98638",
    "sg:province":"WA",
    "sg:tags":[
        "telephone",
        "cellular"
    ],
    "wof:name":"Crescomm Wireless",
    "wof:placetype":"venue"
},
  "geometry": {"coordinates":[-123.80257,46.374532],"type":"Point"}
}