{
  "type": "Feature",
  "properties": {
    "iso:country":"US",
    "sg:address":"171 Sinclair Ln",
    "sg:city":"Selah",
    "sg:classifiers":[
        {
            "category":"Building & Trades",
            "subcategory":"Construction",
            "type":"Services"
        }
    ],
    "sg:phone":"+1 509 698 3578",
    "sg:postcode":"98942",
    "sg:province":"WA",
    "sg:tags":[
        "general",
        "contractor"
    ],
    "wof:name":"Cornerstone Contractors Inc",
    "wof:placetype":"venue"
},
  "geometry": {"coordinates":[-120.54657,46.726427],"type":"Point"}
}