{
  "type": "Feature",
  "properties": {
    "addr:full":"18106 128th Pl SE Snohomish WA 98290",
    "addr:housenumber":"18106",
    "addr:postcode":"98290",
    "addr:street":"128Th Pl Se",
    "iso:country":"US",
    "sg:address":"18106 128th Pl SE",
    "sg:city":"Snohomish",
    "sg:classifiers":[
        {
            "category":"Communications",
            "subcategory":"Film & Video Production",
            "type":"Services"
        }
    ],
    "sg:phone":"+1 360 794 5619",
    "sg:postcode":"98290",
    "sg:province":"WA",
    "sg:tags":[
        "motion",
        "audio"
    ],
    "wof:name":"J 5 Productions",
    "wof:placetype":"venue"
},
  "geometry": {"coordinates":[-121.987852,47.880794],"type":"Point"}
}