{
  "type": "Feature",
  "properties": {
    "addr:full":"1613 W Dravus St Seattle WA 98119",
    "addr:housenumber":"1613",
    "addr:postcode":"98119",
    "addr:street":"W Dravus St",
    "iso:country":"US",
    "sg:address":"1613 W Dravus St",
    "sg:city":"Seattle",
    "sg:classifiers":[
        {
            "category":"Retail",
            "subcategory":"Laundry & Dry Cleaning",
            "type":"Services"
        }
    ],
    "sg:phone":"+1 206 283 7505",
    "sg:postcode":"98119",
    "sg:province":"WA",
    "sg:tags":[
        "cleaners"
    ],
    "wof:name":"Aaron's Fine Drycleaning",
    "wof:placetype":"venue"
},
  "geometry": {"coordinates":[-122.378761,47.648388],"type":"Point"}
}