{
  "type": "Feature",
  "properties": {
    "addr:full":"2120 91st Ave W Tacoma WA 98466",
    "addr:housenumber":"2120",
    "addr:postcode":"98466",
    "addr:street":"91St Ave W",
    "iso:country":"US",
    "sg:address":"2120 91st Ave W",
    "sg:city":"Tacoma",
    "sg:classifiers":[
        {
            "category":"Building & Trades",
            "subcategory":"Construction",
            "type":"Services"
        }
    ],
    "sg:phone":"+1 253 564 5771",
    "sg:postcode":"98466",
    "sg:province":"WA",
    "sg:tags":[
        "floor",
        "laying",
        "contractor"
    ],
    "wof:name":"Gary N Sandberg",
    "wof:placetype":"venue"
},
  "geometry": {"coordinates":[-122.559162,47.24099],"type":"Point"}
}