{
  "type": "Feature",
  "properties": {
    "addr:full":"1715 N Oak St Colfax WA 99111",
    "addr:housenumber":"1715",
    "addr:postcode":"99111",
    "addr:street":"N Oak St",
    "iso:country":"US",
    "sg:address":"1715 N Oak St",
    "sg:city":"Colfax",
    "sg:classifiers":[
        {
            "category":"Retail",
            "subcategory":"Veterinary Services",
            "type":"Services"
        }
    ],
    "sg:phone":"+1 509 397 2971",
    "sg:postcode":"99111",
    "sg:province":"WA",
    "wof:name":"Colfax Cat Clinic",
    "wof:placetype":"venue"
},
  "geometry": {"coordinates":[-117.358102,46.899091],"type":"Point"}
}