{
  "type": "Feature",
  "properties": {
    "iso:country":"US",
    "sg:address":"15422 Westshore Dr SE",
    "sg:city":"Yelm",
    "sg:classifiers":[
        {
            "category":"Manufacturing",
            "subcategory":"Retail Goods",
            "type":"Manufacturing & Wholesale Goods"
        }
    ],
    "sg:phone":"+1 360 894 3965",
    "sg:postcode":"98597",
    "sg:province":"WA",
    "sg:tags":[
        "product",
        "mfg"
    ],
    "wof:name":"Eager Beaver Stump Grinding",
    "wof:placetype":"venue"
},
  "geometry": {"coordinates":[-122.573183,46.863282],"type":"Point"}
}