{
  "type": "Feature",
  "properties": {
    "addr:full":"15600 Redmond Wy Redmond WA 98052",
    "addr:housenumber":"15600",
    "addr:postcode":"98052",
    "addr:street":"Redmond Wy",
    "iso:country":"US",
    "sg:address":"15600 Redmond Wy",
    "sg:city":"Redmond",
    "sg:classifiers":[
        {
            "category":"Autos & Motor Vehicles",
            "subcategory":"Automobile Sales",
            "type":"Retail Goods"
        }
    ],
    "sg:phone":"+1 425 880 2499",
    "sg:postcode":"98052",
    "sg:province":"WA",
    "sg:tags":[
        "limo"
    ],
    "sg:website":"www.redmondlimo.net",
    "wof:name":"Redmond Limo",
    "wof:placetype":"venue"
},
  "geometry": {"coordinates":[-122.131249,47.674364],"type":"Point"}
}