{
  "type": "Feature",
  "properties": {
    "addr:full":"108 Cherry St Seattle WA 98104",
    "addr:housenumber":"108",
    "addr:postcode":"98104",
    "addr:street":"Cherry St",
    "iso:country":"US",
    "sg:address":"108 Cherry St",
    "sg:city":"Seattle",
    "sg:classifiers":[
        {
            "category":"Restaurant",
            "type":"Food & Drink"
        }
    ],
    "sg:phone":"+1 206 624 5687",
    "sg:postcode":"98104",
    "sg:province":"WA",
    "sg:tags":[
        "greek",
        "mediterranean"
    ],
    "wof:name":"Zaina",
    "wof:placetype":"venue"
},
  "geometry": {"coordinates":[-122.334,47.602798],"type":"Point"}
}