{
  "type": "Feature",
  "properties": {
    "addr:full":"1651 S King St Seattle WA 98144",
    "addr:housenumber":"1651",
    "addr:postcode":"98144",
    "addr:street":"S King St",
    "iso:country":"US",
    "sg:address":"1651 S King St",
    "sg:city":"Seattle",
    "sg:classifiers":[
        {
            "category":"Place Of Worship",
            "subcategory":"Temple",
            "type":"Public Place"
        }
    ],
    "sg:phone":"+1 206 323 2269",
    "sg:postcode":"98144",
    "sg:province":"WA",
    "sg:tags":[
        "buddhist"
    ],
    "wof:name":"Vietnamese Buddhist Association",
    "wof:placetype":"venue"
},
  "geometry": {"coordinates":[-122.30999799999999,47.5984],"type":"Point"}
}