{
  "type": "Feature",
  "properties": {
    "addr:full":"12061 124th Ave NE Kirkland WA 98034",
    "addr:housenumber":"12061",
    "addr:postcode":"98034",
    "addr:street":"124Th Ave Ne",
    "iso:country":"US",
    "sg:address":"12061 124th Ave NE",
    "sg:city":"Kirkland",
    "sg:classifiers":[
        {
            "category":"Food & Beverages",
            "subcategory":"Ethnic Foods",
            "type":"Retail Goods"
        }
    ],
    "sg:phone":"+1 425 823 6100",
    "sg:postcode":"98034",
    "sg:province":"WA",
    "sg:website":"www.afspice.com/index.html",
    "wof:name":"African Spice Foods",
    "wof:placetype":"venue"
},
  "geometry": {"coordinates":[-122.175698,47.706807],"type":"Point"}
}