{
  "type": "Feature",
  "properties": {
    "iso:country":"US",
    "sg:address":"15914 NE 78th St",
    "sg:city":"Vancouver",
    "sg:classifiers":[
        {
            "category":"Building & Trades",
            "subcategory":"Plumbing",
            "type":"Services"
        }
    ],
    "sg:phone":"+1 360 892 1284",
    "sg:postcode":"98682",
    "sg:province":"WA",
    "sg:tags":[
        "mechanical",
        "contractor"
    ],
    "wof:name":"Arrow Industrial Mechanical Co",
    "wof:placetype":"venue"
},
  "geometry": {"coordinates":[-122.505909,45.679395],"type":"Point"}
}