{
  "type": "Feature",
  "properties": {
    "addr:full":"4460 Pacific Ave SE Lacey WA 98503",
    "addr:housenumber":"4460",
    "addr:postcode":"98503",
    "addr:street":"Pacific Ave Se",
    "iso:country":"US",
    "sg:address":"4460 Pacific Ave SE",
    "sg:city":"Lacey",
    "sg:classifiers":[
        {
            "category":"Banks & Credit Unions",
            "subcategory":"Bank",
            "type":"Services"
        }
    ],
    "sg:phone":"+1 360 455 1301",
    "sg:postcode":"98503",
    "sg:province":"WA",
    "sg:tags":[
        "loan"
    ],
    "wof:name":"GMAC Mortgage",
    "wof:placetype":"venue"
},
  "geometry": {"coordinates":[-122.826825,47.037978],"type":"Point"}
}