{
  "type": "Feature",
  "properties": {
    "addr:full":"980 Badger Pocket Rd Ellensburg WA 98926",
    "addr:housenumber":"980",
    "addr:postcode":"98926",
    "addr:street":"Badger Pocket Rd",
    "iso:country":"US",
    "sg:address":"980 Badger Pocket Rd",
    "sg:city":"Ellensburg",
    "sg:classifiers":[
        {
            "category":"Freight",
            "type":"Transportation"
        }
    ],
    "sg:phone":"+1 509 968 4594",
    "sg:postcode":"98926",
    "sg:province":"WA",
    "sg:tags":[
        "trucking"
    ],
    "wof:name":"Pat Johnson Trucking",
    "wof:placetype":"venue"
},
  "geometry": {"coordinates":[-120.412417,46.967496],"type":"Point"}
}