{
  "type": "Feature",
  "properties": {
    "addr:full":"2781 State Rte 109 Ocean City WA 98569",
    "addr:housenumber":"2781",
    "addr:postcode":"98569",
    "addr:street":"State Rte 109",
    "iso:country":"US",
    "sg:address":"2781 State Rte 109",
    "sg:city":"Ocean City",
    "sg:classifiers":[
        {
            "category":"Travel",
            "subcategory":"Campground",
            "type":"Entertainment"
        }
    ],
    "sg:phone":"+1 360 289 3656",
    "sg:postcode":"98569",
    "sg:province":"WA",
    "sg:tags":[
        "recreational",
        "trailer",
        "parks",
        "vehicle"
    ],
    "wof:name":"Ocean Mist Rv Resort",
    "wof:placetype":"venue"
},
  "geometry": {"coordinates":[-124.167508,47.081298],"type":"Point"}
}