{
  "type": "Feature",
  "properties": {
    "addr:full":"5004 Kitsap Way Bremerton WA 98312",
    "addr:housenumber":"5004",
    "addr:postcode":"98312",
    "addr:street":"Kitsap Way",
    "iso:country":"US",
    "sg:address":"5004 Kitsap Way",
    "sg:city":"Bremerton",
    "sg:classifiers":[
        {
            "category":"Restaurant",
            "type":"Food & Drink"
        }
    ],
    "sg:phone":"+1 360 479 8941",
    "sg:postcode":"98312",
    "sg:province":"WA",
    "sg:website":"www.dennys.com",
    "wof:name":"Denny's",
    "wof:placetype":"venue"
},
  "geometry": {"coordinates":[-122.68331000000001,47.569692],"type":"Point"}
}