{
  "type": "Feature",
  "properties": {
    "addr:full":"1041 Bay St Port Orchard WA 98366",
    "addr:housenumber":"1041",
    "addr:postcode":"98366",
    "addr:street":"Bay St",
    "iso:country":"US",
    "sg:address":"1041 Bay St",
    "sg:city":"Port Orchard",
    "sg:classifiers":[
        {
            "category":"Insurance",
            "subcategory":"Insurance Agent",
            "type":"Services"
        }
    ],
    "sg:phone":"+1 360 876 8555",
    "sg:postcode":"98366",
    "sg:province":"WA",
    "sg:website":"www.aflac.com",
    "wof:name":"Aflac Insurance",
    "wof:placetype":"venue"
},
  "geometry": {"coordinates":[-122.631725,47.542796],"type":"Point"}
}