{
  "type": "Feature",
  "properties": {
    "addr:full":"1149 8th St Clarkston WA 99403",
    "addr:housenumber":"1149",
    "addr:postcode":"99403",
    "addr:street":"8Th St",
    "iso:country":"US",
    "sg:address":"1149 8th St",
    "sg:city":"Clarkston",
    "sg:classifiers":[
        {
            "category":"Professional",
            "subcategory":"Computer Services",
            "type":"Services"
        }
    ],
    "sg:phone":"+1 509 758 3048",
    "sg:postcode":"99403",
    "sg:province":"WA",
    "sg:tags":[
        "datum"
    ],
    "wof:name":"Sheila F Kom",
    "wof:placetype":"venue"
},
  "geometry": {"coordinates":[-117.048095,46.408171],"type":"Point"}
}