{
  "type": "Feature",
  "properties": {
    "iso:country":"US",
    "sg:address":"9252 Morning Side Dr NW",
    "sg:city":"Silverdale",
    "sg:classifiers":[
        {
            "category":"Professional",
            "subcategory":"Art Services",
            "type":"Services"
        }
    ],
    "sg:phone":"+1 360 692 1097",
    "sg:postcode":"98383",
    "sg:province":"WA",
    "sg:tags":[
        "commercial",
        "design"
    ],
    "wof:name":"George Steed Aviation Art",
    "wof:placetype":"venue"
},
  "geometry": {"coordinates":[-122.709469,47.649052],"type":"Point"}
}