{
  "type": "Feature",
  "properties": {
    "addr:full":"110 E Rees Ave Walla Walla WA 99362",
    "addr:housenumber":"110",
    "addr:postcode":"99362",
    "addr:street":"E Rees Ave",
    "iso:country":"US",
    "sg:address":"110 E Rees Ave",
    "sg:city":"Walla Walla",
    "sg:classifiers":[
        {
            "category":"Retail",
            "subcategory":"Auto Repair",
            "type":"Services"
        }
    ],
    "sg:phone":"+1 509 525 0703",
    "sg:postcode":"99362",
    "sg:province":"WA",
    "sg:tags":[
        "repairing",
        "automobile",
        "general"
    ],
    "wof:name":"Job's Truck & Auto Repair",
    "wof:placetype":"venue"
},
  "geometry": {"coordinates":[-118.34007099999999,46.07523],"type":"Point"}
}