{
  "type": "Feature",
  "properties": {
    "addr:full":"539 6th Ave W Omak WA 98841",
    "addr:housenumber":"539",
    "addr:postcode":"98841",
    "addr:street":"6Th Ave W",
    "iso:country":"US",
    "sg:address":"539 6th Ave W",
    "sg:city":"Omak",
    "sg:classifiers":[
        {
            "category":"Building & Trades",
            "subcategory":"Electrical",
            "type":"Services"
        }
    ],
    "sg:phone":"+1 509 826 4975",
    "sg:postcode":"98841",
    "sg:province":"WA",
    "sg:tags":[
        "electric",
        "contractor"
    ],
    "wof:name":"Mc Candish Electrical",
    "wof:placetype":"venue"
},
  "geometry": {"coordinates":[-119.53852500000001,48.402468],"type":"Point"}
}