{
  "type": "Feature",
  "properties": {
    "addr:full":"5022 Rainier Ave Seattle WA 98118",
    "addr:housenumber":"5022",
    "addr:postcode":"98118",
    "addr:street":"Rainier Ave",
    "iso:country":"US",
    "sg:address":"5022 Rainier Ave",
    "sg:city":"Seattle",
    "sg:classifiers":[
        {
            "category":"Shopping",
            "type":"Retail Goods"
        }
    ],
    "sg:phone":"+1 206 723 0446",
    "sg:postcode":"98118",
    "sg:province":"WA",
    "sg:tags":[
        "merchandise"
    ],
    "wof:name":"City Rims Dubb The",
    "wof:placetype":"venue"
},
  "geometry": {"coordinates":[-122.283609,47.556191],"type":"Point"}
}