{
  "type": "Feature",
  "properties": {
    "addr:full":"6826 Cliff Avenue Kp S Longbranch WA 98351",
    "addr:housenumber":"6826",
    "addr:postcode":"98351",
    "addr:street":"Cliff Avenue Kp S",
    "iso:country":"US",
    "sg:address":"6826 Cliff Avenue Kp S",
    "sg:city":"Longbranch",
    "sg:classifiers":[
        {
            "category":"Manufacturing",
            "subcategory":"Apparel",
            "type":"Manufacturing & Wholesale Goods"
        }
    ],
    "sg:phone":"+1 253 884 2253",
    "sg:postcode":"98351",
    "sg:province":"WA",
    "sg:tags":[
        "product",
        "mfg"
    ],
    "wof:name":"Standout Yacht Fittings",
    "wof:placetype":"venue"
},
  "geometry": {"coordinates":[-122.746797,47.193484],"type":"Point"}
}