{
  "type": "Feature",
  "properties": {
    "addr:full":"1502 54th Ave E Fife WA 98424",
    "addr:housenumber":"1502",
    "addr:postcode":"98424",
    "addr:street":"54Th Ave E",
    "iso:country":"US",
    "sg:address":"1502 54th Ave E",
    "sg:city":"Fife",
    "sg:classifiers":[
        {
            "category":"Freight",
            "type":"Transportation"
        }
    ],
    "sg:phone":"+1 253 922 3552",
    "sg:postcode":"98424",
    "sg:province":"WA",
    "sg:tags":[
        "trucking"
    ],
    "wof:name":"City Delivery",
    "wof:placetype":"venue"
},
  "geometry": {"coordinates":[-122.357045,47.243102],"type":"Point"}
}