{
  "type": "Feature",
  "properties": {
    "addr:full":"21993 Grip Rd Sedro Woolley WA 98284",
    "addr:housenumber":"21993",
    "addr:postcode":"98284",
    "addr:street":"Grip Rd",
    "iso:country":"US",
    "sg:address":"21993 Grip Rd",
    "sg:city":"Sedro Woolley",
    "sg:classifiers":[
        {
            "category":"Professional",
            "subcategory":"Research",
            "type":"Services"
        },
        {
            "category":"Professional",
            "subcategory":"Management & Consulting",
            "type":"Services"
        }
    ],
    "sg:phone":"+1 360 856 2139",
    "sg:postcode":"98284",
    "sg:province":"WA",
    "sg:tags":[
        "consultant",
        "commercial",
        "business",
        "physical"
    ],
    "wof:name":"Aqua Terr Systems Inc",
    "wof:placetype":"venue"
},
  "geometry": {"coordinates":[-122.256242,48.558037],"type":"Point"}
}