{
  "type": "Feature",
  "properties": {
    "addr:full":"22926 25th Ave W Lynnwood WA 98036",
    "addr:housenumber":"22926",
    "addr:postcode":"98036",
    "addr:street":"25Th Ave W",
    "iso:country":"US",
    "sg:address":"22926 25th Ave W",
    "sg:city":"Lynnwood",
    "sg:classifiers":[
        {
            "category":"Retail",
            "subcategory":"Animal Services",
            "type":"Services"
        }
    ],
    "sg:phone":"+1 425 776 3021",
    "sg:postcode":"98036",
    "sg:province":"WA",
    "wof:name":"Pride & Joy Pet Grooming",
    "wof:placetype":"venue"
},
  "geometry": {"coordinates":[-122.266752,47.790752],"type":"Point"}
}