{
  "type": "Feature",
  "properties": {
    "addr:full":"212 Kay Ave Burlington WA 98233",
    "addr:housenumber":"212",
    "addr:postcode":"98233",
    "addr:street":"Kay Ave",
    "iso:country":"US",
    "sg:address":"212 Kay Ave",
    "sg:city":"Burlington",
    "sg:classifiers":[
        {
            "category":"Building & Trades",
            "subcategory":"Construction",
            "type":"Services"
        }
    ],
    "sg:phone":"+1 360 757 4240",
    "sg:postcode":"98233",
    "sg:province":"WA",
    "sg:tags":[
        "house"
    ],
    "wof:name":"Lee Brothers Construction",
    "wof:placetype":"venue"
},
  "geometry": {"coordinates":[-122.33333399999999,48.462964],"type":"Point"}
}