{
  "type": "Feature",
  "properties": {
    "addr:full":"8015 Steilacoom Blvd SW Lakewood WA 98498",
    "addr:housenumber":"8015",
    "addr:postcode":"98498",
    "addr:street":"Steilacoom Blvd Sw",
    "iso:country":"US",
    "sg:address":"8015 Steilacoom Blvd SW",
    "sg:city":"Lakewood",
    "sg:classifiers":[
        {
            "category":"Recreation",
            "type":"Entertainment"
        }
    ],
    "sg:phone":"+1 253 589 6924",
    "sg:postcode":"98498",
    "sg:province":"WA",
    "sg:tags":[
        "martial",
        "arts",
        "instruction"
    ],
    "wof:name":"Washington Karate Association",
    "wof:placetype":"venue"
},
  "geometry": {"coordinates":[-122.545779,47.180014],"type":"Point"}
}