{
  "type": "Feature",
  "properties": {
    "addr:full":"4618 Darlington Ln Everett WA 98203",
    "addr:housenumber":"4618",
    "addr:postcode":"98203",
    "addr:street":"Darlington Ln",
    "iso:country":"US",
    "sg:address":"4618 Darlington Ln",
    "sg:city":"Everett",
    "sg:classifiers":[
        {
            "category":"Shopping",
            "type":"Retail Goods"
        }
    ],
    "sg:phone":"+1 425 347 3201",
    "sg:postcode":"98203",
    "sg:province":"WA",
    "sg:tags":[
        "merchandise"
    ],
    "wof:name":"Pet Productions of Lynnwood",
    "wof:placetype":"venue"
},
  "geometry": {"coordinates":[-122.253975,47.955995],"type":"Point"}
}