{
  "type": "Feature",
  "properties": {
    "addr:full":"300 E 24th St Vancouver WA 98663",
    "addr:housenumber":"300",
    "addr:postcode":"98663",
    "addr:street":"E 24Th St",
    "iso:country":"US",
    "sg:address":"300 E 24th St",
    "sg:city":"Vancouver",
    "sg:classifiers":[
        {
            "category":"Health Services",
            "subcategory":"Dentist",
            "type":"Services"
        }
    ],
    "sg:phone":"+1 360 694 4000",
    "sg:postcode":"98663",
    "sg:province":"WA",
    "wof:name":"Kim Joseph J DDS PS DDS PC",
    "wof:placetype":"venue"
},
  "geometry": {"coordinates":[-122.669236,45.638697],"type":"Point"}
}