{
  "type": "Feature",
  "properties": {
    "addr:full":"1633 121st St S Tacoma WA 98444",
    "addr:housenumber":"1633",
    "addr:postcode":"98444",
    "addr:street":"121St St S",
    "iso:country":"US",
    "sg:address":"1633 121st St S",
    "sg:city":"Tacoma",
    "sg:classifiers":[
        {
            "category":"Retail",
            "subcategory":"Animal Services",
            "type":"Services"
        }
    ],
    "sg:phone":"+1 253 539 0868",
    "sg:postcode":"98444",
    "sg:province":"WA",
    "sg:tags":[
        "pet",
        "grooming",
        "washing"
    ],
    "wof:name":"Katz's & Dawgs Grooming",
    "wof:placetype":"venue"
},
  "geometry": {"coordinates":[-122.45746200000001,47.147857],"type":"Point"}
}