{
  "type": "Feature",
  "properties": {
    "addr:full":"1703 Hartford Rd Yakima WA 98901",
    "addr:housenumber":"1703",
    "addr:postcode":"98901",
    "addr:street":"Hartford Rd",
    "iso:country":"US",
    "sg:address":"1703 Hartford Rd",
    "sg:city":"Yakima",
    "sg:classifiers":[
        {
            "category":"Building & Trades",
            "subcategory":"Landscaping Services",
            "type":"Services"
        }
    ],
    "sg:phone":"+1 509 453 4183",
    "sg:postcode":"98901",
    "sg:province":"WA",
    "wof:name":"Felixs Lawn Service",
    "wof:placetype":"venue"
},
  "geometry": {"coordinates":[-120.47846699999999,46.61397],"type":"Point"}
}