{
  "type": "Feature",
  "properties": {
    "iso:country":"US",
    "sg:address":"6715 Corson Ave S",
    "sg:city":"Seattle",
    "sg:classifiers":[
        {
            "category":"Freight",
            "type":"Transportation"
        }
    ],
    "sg:phone":"+1 206 767 0481",
    "sg:postcode":"98108",
    "sg:province":"WA",
    "sg:tags":[
        "interstate",
        "local",
        "trucking"
    ],
    "wof:name":"Highway Enterprises Inc",
    "wof:placetype":"venue"
},
  "geometry": {"coordinates":[-122.323093,47.543185],"type":"Point"}
}