{
  "type": "Feature",
  "properties": {
    "addr:full":"16260 Redmond Way Redmond WA 98052",
    "addr:housenumber":"16260",
    "addr:postcode":"98052",
    "addr:street":"Redmond Way",
    "iso:country":"US",
    "sg:address":"16260 Redmond Way",
    "sg:city":"Redmond",
    "sg:classifiers":[
        {
            "category":"Personal",
            "subcategory":"Beauty Salon",
            "type":"Services"
        }
    ],
    "sg:phone":"+1 425 867 1611",
    "sg:postcode":"98052",
    "sg:province":"WA",
    "wof:name":"A Classa Full Svc Salon",
    "wof:placetype":"venue"
},
  "geometry": {"coordinates":[-122.123439,47.674545],"type":"Point"}
}