{
  "type": "Feature",
  "properties": {
    "addr:full":"3033 NW 66th St Seattle WA 98117",
    "addr:housenumber":"3033",
    "addr:postcode":"98117",
    "addr:street":"Nw 66Th St",
    "iso:country":"US",
    "sg:address":"3033 NW 66th St",
    "sg:city":"Seattle",
    "sg:classifiers":[
        {
            "category":"Landmark",
            "subcategory":"Tourist Information",
            "type":"Public Place"
        },
        {
            "category":"Landmark",
            "subcategory":"Tourist Attraction",
            "type":"Public Place"
        }
    ],
    "sg:phone":"+1 206 789 9156",
    "sg:postcode":"98117",
    "sg:province":"WA",
    "sg:tags":[
        "tour",
        "tours-operators",
        "promoter",
        "sightseeing"
    ],
    "wof:name":"Rc Touring Inc",
    "wof:placetype":"venue"
},
  "geometry": {"coordinates":[-122.396563,47.676614],"type":"Point"}
}