{
  "type": "Feature",
  "properties": {
    "addr:full":"7711 NE 167th St Kenmore WA 98028",
    "addr:housenumber":"7711",
    "addr:postcode":"98028",
    "addr:street":"Ne 167Th St",
    "iso:country":"US",
    "sg:address":"7711 NE 167th St",
    "sg:city":"Kenmore",
    "sg:classifiers":[
        {
            "category":"Building & Trades",
            "subcategory":"Construction",
            "type":"Services"
        }
    ],
    "sg:phone":"+1 425 481 5110",
    "sg:postcode":"98028",
    "sg:province":"WA",
    "sg:tags":[
        "house"
    ],
    "wof:name":"Northlake Cnstr & Remodel",
    "wof:placetype":"venue"
},
  "geometry": {"coordinates":[-122.23759099999999,47.749653],"type":"Point"}
}