{
  "type": "Feature",
  "properties": {
    "addr:full":"1621 E Olive Way Seattle WA 98102",
    "addr:housenumber":"1621",
    "addr:postcode":"98102",
    "addr:street":"E Olive Way",
    "iso:country":"US",
    "sg:address":"1621 E Olive Way",
    "sg:city":"Seattle",
    "sg:classifiers":[
        {
            "category":"Restaurant",
            "type":"Food & Drink"
        }
    ],
    "sg:phone":"+1 206 324 2577",
    "sg:postcode":"98102",
    "sg:province":"WA",
    "wof:name":"Glo's",
    "wof:placetype":"venue"
},
  "geometry": {"coordinates":[-122.32488600000001,47.619107],"type":"Point"}
}