{
  "type": "Feature",
  "properties": {
    "iso:country":"US",
    "sg:address":"914 Randolph Ave",
    "sg:city":"Seattle",
    "sg:classifiers":[
        {
            "category":"Shopping",
            "subcategory":"Gifts & Souvenirs",
            "type":"Retail Goods"
        }
    ],
    "sg:phone":"+1 206 323 7395",
    "sg:postcode":"98122",
    "sg:province":"WA",
    "wof:name":"Present Perfect",
    "wof:placetype":"venue"
},
  "geometry": {"coordinates":[-122.285909,47.610969],"type":"Point"}
}