{
  "type": "Feature",
  "properties": {
    "addr:full":"11303 Hwy 99 Everett WA 98204",
    "addr:housenumber":"11303",
    "addr:postcode":"98204",
    "addr:street":"Hwy 99",
    "iso:country":"US",
    "sg:address":"11303 Hwy 99",
    "sg:city":"Everett",
    "sg:classifiers":[
        {
            "category":"Retail",
            "subcategory":"Auto Repair",
            "type":"Services"
        }
    ],
    "sg:phone":"+1 425 347 8812",
    "sg:postcode":"98204",
    "sg:province":"WA",
    "sg:tags":[
        "shop",
        "automobile",
        "machine",
        "automotive",
        "general"
    ],
    "wof:name":"Jay's Automotive Machine Shop",
    "wof:placetype":"venue"
},
  "geometry": {"coordinates":[-122.252413,47.895722],"type":"Point"}
}