{
  "type": "Feature",
  "properties": {
    "addr:full":"4011 Commonwealth Rd Yakima WA 98901",
    "addr:housenumber":"4011",
    "addr:postcode":"98901",
    "addr:street":"Commonwealth Rd",
    "iso:country":"US",
    "sg:address":"4011 Commonwealth Rd",
    "sg:city":"Yakima",
    "sg:classifiers":[
        {
            "category":"Social Services",
            "subcategory":"Child Care",
            "type":"Services"
        }
    ],
    "sg:phone":"+1 509 457 5779",
    "sg:postcode":"98901",
    "sg:province":"WA",
    "sg:tags":[
        "kindergarten",
        "academic",
        "school"
    ],
    "wof:name":"Kreative Kids Preschool",
    "wof:placetype":"venue"
},
  "geometry": {"coordinates":[-120.44745,46.607397],"type":"Point"}
}