{
  "type": "Feature",
  "properties": {
    "addr:full":"2631 143rd St SW Apt B Lynnwood WA 98087",
    "addr:housenumber":"2631",
    "addr:postcode":"98087",
    "addr:street":"143Rd St Sw;B",
    "iso:country":"US",
    "sg:address":"2631 143rd St SW Apt B",
    "sg:city":"Lynnwood",
    "sg:classifiers":[
        {
            "category":"Banks & Credit Unions",
            "subcategory":"Investment Brokerage",
            "type":"Services"
        },
        {
            "category":"Banks & Credit Unions",
            "subcategory":"Financial Services",
            "type":"Services"
        }
    ],
    "sg:phone":"+1 425 922 8722",
    "sg:postcode":"98087",
    "sg:province":"WA",
    "sg:tags":[
        "advisory",
        "planner"
    ],
    "wof:name":"Heck Financial",
    "wof:placetype":"venue"
},
  "geometry": {"coordinates":[-122.270365,47.868776],"type":"Point"}
}