{
  "type": "Feature",
  "properties": {
    "addr:full":"7611 S 115th St Seattle WA 98178",
    "addr:housenumber":"7611",
    "addr:postcode":"98178",
    "addr:street":"S 115Th St",
    "iso:country":"US",
    "sg:address":"7611 S 115th St",
    "sg:city":"Seattle",
    "sg:classifiers":[
        {
            "category":"Professional",
            "subcategory":"Management & Consulting",
            "type":"Services"
        }
    ],
    "sg:phone":"+1 206 722 4400",
    "sg:postcode":"98178",
    "sg:province":"WA",
    "wof:name":"Brim Donahoe & Assoc",
    "wof:placetype":"venue"
},
  "geometry": {"coordinates":[-122.23559899999999,47.500576],"type":"Point"}
}