{
  "type": "Feature",
  "properties": {
    "addr:full":"19112 E 8th Ave Greenacres WA 99016",
    "addr:housenumber":"19112",
    "addr:postcode":"99016",
    "addr:street":"E 8Th Ave",
    "iso:country":"US",
    "sg:address":"19112 E 8th Ave",
    "sg:city":"Greenacres",
    "sg:classifiers":[
        {
            "category":"Professional",
            "subcategory":"Computer Services",
            "type":"Services"
        }
    ],
    "sg:phone":"+1 509 924 9365",
    "sg:postcode":"99016",
    "sg:province":"WA",
    "sg:tags":[
        "related"
    ],
    "wof:name":"Allen Thelen",
    "wof:placetype":"venue"
},
  "geometry": {"coordinates":[-117.14355399999999,47.649519],"type":"Point"}
}