{
  "type": "Feature",
  "properties": {
    "addr:full":"604 9th St Benton City WA 99320",
    "addr:housenumber":"604",
    "addr:postcode":"99320",
    "addr:street":"9Th St",
    "iso:country":"US",
    "sg:address":"604 9th St",
    "sg:city":"Benton City",
    "sg:classifiers":[
        {
            "category":"Health Services",
            "subcategory":"Health Practitioner",
            "type":"Services"
        }
    ],
    "sg:phone":"+1 509 588 2924",
    "sg:postcode":"99320",
    "sg:province":"WA",
    "sg:tags":[
        "therapist",
        "physical"
    ],
    "wof:name":"Benton City Physical Therapy",
    "wof:placetype":"venue"
},
  "geometry": {"coordinates":[-119.48755,46.263804],"type":"Point"}
}