{
  "type": "Feature",
  "properties": {
    "addr:full":"4820 NE 4th St Renton WA 98059",
    "addr:housenumber":"4820",
    "addr:postcode":"98059",
    "addr:street":"Ne 4Th St",
    "iso:country":"US",
    "sg:address":"4820 NE 4th St",
    "sg:city":"Renton",
    "sg:classifiers":[
        {
            "category":"Health Services",
            "subcategory":"Health Practitioner",
            "type":"Services"
        }
    ],
    "sg:phone":"+1 425 235 9505",
    "sg:postcode":"98059",
    "sg:province":"WA",
    "sg:tags":[
        "therapist",
        "physical"
    ],
    "wof:name":"Schoos Gil",
    "wof:placetype":"venue"
},
  "geometry": {"coordinates":[-122.157156,47.488587],"type":"Point"}
}