{
  "type": "Feature",
  "properties": {
    "addr:full":"5101 38th Ave NW Gig Harbor WA 98335",
    "addr:housenumber":"5101",
    "addr:postcode":"98335",
    "addr:street":"38Th Ave Nw",
    "iso:country":"US",
    "sg:address":"5101 38th Ave NW",
    "sg:city":"Gig Harbor",
    "sg:classifiers":[
        {
            "category":"Building & Trades",
            "subcategory":"Construction",
            "type":"Services"
        }
    ],
    "sg:phone":"+1 253 851 8841",
    "sg:postcode":"98335",
    "sg:province":"WA",
    "sg:tags":[
        "concrete",
        "contractor"
    ],
    "wof:name":"Patriot Concrete Forming Inc",
    "wof:placetype":"venue"
},
  "geometry": {"coordinates":[-122.58982399999999,47.304894],"type":"Point"}
}