{
  "type": "Feature",
  "properties": {
    "addr:full":"711 N Lincoln St Spokane WA 99201",
    "addr:housenumber":"711",
    "addr:postcode":"99201",
    "addr:street":"N Lincoln St",
    "iso:country":"US",
    "sg:address":"711 N Lincoln St",
    "sg:city":"Spokane",
    "sg:classifiers":[
        {
            "category":"Professional",
            "subcategory":"Lawyer & Legal Services",
            "type":"Services"
        }
    ],
    "sg:phone":"+1 509 323 4847",
    "sg:postcode":"99201",
    "sg:province":"WA",
    "sg:tags":[
        "attorney",
        "criminal",
        "law"
    ],
    "wof:name":"Anna Cutler",
    "wof:placetype":"venue"
},
  "geometry": {"coordinates":[-117.425088,47.662879],"type":"Point"}
}