{
  "type": "Feature",
  "properties": {
    "addr:full":"8600 Nels Nelson Rd NW Bremerton WA 98311",
    "addr:postcode":"8600;98311",
    "addr:street":"Nels Nelson Rd Nw",
    "iso:country":"US",
    "sg:address":"8600 Nels Nelson Rd NW",
    "sg:city":"Bremerton",
    "sg:classifiers":[
        {
            "category":"Social Services",
            "subcategory":"Child Care",
            "type":"Services"
        }
    ],
    "sg:phone":"+1 360 698 0706",
    "sg:postcode":"98311",
    "sg:province":"WA",
    "sg:tags":[
        "kindergarten",
        "academic",
        "school"
    ],
    "wof:name":"Barker Creek Montessori",
    "wof:placetype":"venue"
},
  "geometry": {"coordinates":[-122.66086799999999,47.640571],"type":"Point"}
}