{
  "type": "Feature",
  "properties": {
    "addr:full":"860 S Cambridge St Seattle WA 98108",
    "addr:housenumber":"860",
    "addr:postcode":"98108",
    "addr:street":"S Cambridge St",
    "iso:country":"US",
    "sg:address":"860 S Cambridge St",
    "sg:city":"Seattle",
    "sg:classifiers":[
        {
            "category":"Building & Trades",
            "subcategory":"Equipment Rental",
            "type":"Services"
        }
    ],
    "sg:phone":"+1 206 381 1616",
    "sg:postcode":"98108",
    "sg:province":"WA",
    "sg:tags":[
        "staging"
    ],
    "wof:name":"Proline Audio Visual Rentals",
    "wof:placetype":"venue"
},
  "geometry": {"coordinates":[-122.32232500000001,47.518934],"type":"Point"}
}