{
  "type": "Feature",
  "properties": {
    "addr:full":"800 Bellevue Pl E Ste 400 Seattle WA 98102",
    "addr:housenumber":"800",
    "addr:postcode":"98102",
    "addr:street":"Bellevue Pl E Ste 400",
    "iso:country":"US",
    "sg:address":"800 Bellevue Pl E Ste 400",
    "sg:city":"Seattle",
    "sg:classifiers":[
        {
            "category":"Personal",
            "type":"Services"
        }
    ],
    "sg:phone":"+1 800 633 4237",
    "sg:postcode":"98102",
    "sg:province":"WA",
    "sg:tags":[
        "assistant"
    ],
    "wof:name":"Regus/ HQ",
    "wof:placetype":"venue"
},
  "geometry": {"coordinates":[-122.32656900000001,47.62698],"type":"Point"}
}