{
  "type": "Feature",
  "properties": {
    "addr:full":"9629 Evergreen Way Everett WA 98204",
    "addr:housenumber":"9629",
    "addr:postcode":"98204",
    "addr:street":"Evergreen Way",
    "iso:country":"US",
    "sg:address":"9629 Evergreen Way",
    "sg:city":"Everett",
    "sg:classifiers":[
        {
            "category":"Restaurant",
            "type":"Food & Drink"
        }
    ],
    "sg:phone":"+1 425 710 9164",
    "sg:postcode":"98204",
    "sg:province":"WA",
    "sg:tags":[
        "eating"
    ],
    "wof:name":"La Malinche",
    "wof:placetype":"venue"
},
  "geometry": {"coordinates":[-122.23885300000001,47.910257],"type":"Point"}
}