{
  "type": "Feature",
  "properties": {
    "addr:full":"1250 Basin St SW Ephrata WA 98823",
    "addr:housenumber":"1250",
    "addr:postcode":"98823",
    "addr:street":"Basin St Sw",
    "iso:country":"US",
    "sg:address":"1250 Basin St SW",
    "sg:city":"Ephrata",
    "sg:classifiers":[
        {
            "category":"Real Estate",
            "subcategory":"Developer",
            "type":"Services"
        }
    ],
    "sg:phone":"+1 509 754 1318",
    "sg:postcode":"98823",
    "sg:province":"WA",
    "sg:tags":[
        "company",
        "land"
    ],
    "wof:name":"Grand County Land Co",
    "wof:placetype":"venue"
},
  "geometry": {"coordinates":[-119.56036,47.30841],"type":"Point"}
}