{
  "type": "Feature",
  "properties": {
    "addr:full":"112 E 1st Ave Spokane WA 99202",
    "addr:housenumber":"112",
    "addr:postcode":"99202",
    "addr:street":"E 1St Ave",
    "iso:country":"US",
    "sg:address":"112 E 1st Ave",
    "sg:city":"Spokane",
    "sg:classifiers":[
        {
            "category":"Restaurant",
            "type":"Food & Drink"
        }
    ],
    "sg:phone":"+1 509 998 7143",
    "sg:postcode":"99202",
    "sg:province":"WA",
    "sg:tags":[
        "eating"
    ],
    "wof:name":"Dezys Coffee N More",
    "wof:placetype":"venue"
},
  "geometry": {"coordinates":[-117.40833499999999,47.656551],"type":"Point"}
}