{
  "type": "Feature",
  "properties": {
    "addr:full":"2219 2nd Avenue Apt 301 Seattle WA 98121",
    "addr:housenumber":"2219;301",
    "addr:postcode":"98121",
    "addr:street":"2Nd Avenue Apt",
    "iso:country":"US",
    "sg:address":"2219 2nd Avenue Apt 301",
    "sg:city":"Seattle",
    "sg:classifiers":[
        {
            "category":"Real Estate",
            "subcategory":"Real Estate Operator",
            "type":"Services"
        }
    ],
    "sg:phone":"+1 206 728 9515",
    "sg:postcode":"98121",
    "sg:province":"WA",
    "sg:tags":[
        "apartment"
    ],
    "wof:name":"Josef F Stanzl Dba Concept One Apartments",
    "wof:placetype":"venue"
},
  "geometry": {"coordinates":[-122.34464699999999,47.613421],"type":"Point"}
}