{
  "type": "Feature",
  "properties": {
    "addr:full":"2443 S Arthur Ct Kennewick WA 99338",
    "addr:housenumber":"2443",
    "addr:postcode":"99338",
    "addr:street":"S Arthur Ct",
    "iso:country":"US",
    "sg:address":"2443 S Arthur Ct",
    "sg:city":"Kennewick",
    "sg:classifiers":[
        {
            "category":"Shopping",
            "subcategory":"Gifts & Souvenirs",
            "type":"Retail Goods"
        }
    ],
    "sg:phone":"+1 509 735 0664",
    "sg:postcode":"99338",
    "sg:province":"WA",
    "wof:name":"Warm Fuzzies",
    "wof:placetype":"venue"
},
  "geometry": {"coordinates":[-119.18458200000001,46.187087],"type":"Point"}
}