{
  "type": "Feature",
  "properties": {
    "addr:full":"5701 6th Ave S Seattle WA 98108",
    "addr:housenumber":"5701",
    "addr:postcode":"98108",
    "addr:street":"6Th Ave S",
    "iso:country":"US",
    "sg:address":"5701 6th Ave S",
    "sg:city":"Seattle",
    "sg:classifiers":[
        {
            "category":"Home & Garden",
            "subcategory":"Building Materials",
            "type":"Retail Goods"
        }
    ],
    "sg:phone":"+1 206 433 1583",
    "sg:postcode":"98108",
    "sg:province":"WA",
    "sg:tags":[
        "windows"
    ],
    "wof:name":"Archtiectural Import Northwest",
    "wof:placetype":"venue"
},
  "geometry": {"coordinates":[-122.326942,47.551057],"type":"Point"}
}