{
  "type": "Feature",
  "properties": {
    "addr:full":"5111 Claremont Way Everett WA 98203",
    "addr:housenumber":"5111",
    "addr:postcode":"98203",
    "addr:street":"Claremont Way",
    "iso:country":"US",
    "sg:address":"5111 Claremont Way",
    "sg:city":"Everett",
    "sg:classifiers":[
        {
            "category":"Restaurant",
            "type":"Food & Drink"
        }
    ],
    "sg:phone":"+1 425 259 7206",
    "sg:postcode":"98203",
    "sg:province":"WA",
    "sg:website":"http://www.evergreenlanes.net",
    "wof:name":"Evergreen Lanes Restaurant",
    "wof:placetype":"venue"
},
  "geometry": {"coordinates":[-122.21264499999999,47.950612],"type":"Point"}
}