{
  "type": "Feature",
  "properties": {
    "addr:full":"1521 NW Market St Seattle WA 98107",
    "addr:housenumber":"1521",
    "addr:postcode":"98107",
    "addr:street":"Nw Market St",
    "iso:country":"US",
    "sg:address":"1521 NW Market St",
    "sg:city":"Seattle",
    "sg:classifiers":[
        {
            "category":"Government",
            "subcategory":"Fire Station",
            "type":"Public Place"
        }
    ],
    "sg:phone":"+1 206 386 1400",
    "sg:postcode":"98107",
    "sg:province":"WA",
    "sg:tags":[
        "protection"
    ],
    "wof:name":"Fire Station 18",
    "wof:placetype":"venue"
},
  "geometry": {"coordinates":[-122.378705,47.668594],"type":"Point"}
}