{
  "type": "Feature",
  "properties": {
    "iso:country":"US",
    "sg:address":"410 S Park Rd",
    "sg:city":"Spokane Valley",
    "sg:classifiers":[
        {
            "category":"Retail",
            "subcategory":"Laundry & Dry Cleaning",
            "type":"Services"
        }
    ],
    "sg:phone":"+1 509 536 3260",
    "sg:postcode":"99212",
    "sg:province":"WA",
    "sg:tags":[
        "cleaners",
        "rug",
        "carpet"
    ],
    "wof:name":"Creative Carpet Care",
    "wof:placetype":"venue"
},
  "geometry": {"coordinates":[-117.30419500000001,47.652835],"type":"Point"}
}