{
  "type": "Feature",
  "properties": {
    "addr:full":"5412 29th St NE Tacoma WA 98422",
    "addr:housenumber":"5412",
    "addr:postcode":"98422",
    "addr:street":"29Th St Ne",
    "iso:country":"US",
    "sg:address":"5412 29th St NE",
    "sg:city":"Tacoma",
    "sg:classifiers":[
        {
            "category":"Education",
            "subcategory":"School",
            "type":"Public Place"
        }
    ],
    "sg:phone":"+1 253 571 6933",
    "sg:postcode":"98422",
    "sg:province":"WA",
    "wof:name":"Northeast Tacoma Elementary School",
    "wof:placetype":"venue"
},
  "geometry": {"coordinates":[-122.374483,47.282758],"type":"Point"}
}