{
  "type": "Feature",
  "properties": {
    "addr:full":"19910 Viking Ave NW Poulsbo WA 98370",
    "addr:housenumber":"19910",
    "addr:postcode":"98370",
    "addr:street":"Viking Ave Nw",
    "iso:country":"US",
    "sg:address":"19910 Viking Ave NW",
    "sg:city":"Poulsbo",
    "sg:classifiers":[
        {
            "category":"Shopping",
            "subcategory":"Computers & Home Electronics",
            "type":"Retail Goods"
        },
        {
            "category":"Building & Trades",
            "subcategory":"Electrical",
            "type":"Services"
        }
    ],
    "sg:phone":"+1 360 930 3041",
    "sg:postcode":"98370",
    "sg:province":"WA",
    "sg:tags":[
        "theater",
        "consumer",
        "electrician",
        "system"
    ],
    "sg:website":"http://www.mdelectronics.net",
    "wof:name":"MD Electronics",
    "wof:placetype":"venue"
},
  "geometry": {"coordinates":[-122.656561,47.74354],"type":"Point"}
}