{
  "type": "Feature",
  "properties": {
    "addr:full":"611 E 30th Ave Spokane WA 99203",
    "addr:housenumber":"611",
    "addr:postcode":"99203",
    "addr:street":"E 30Th Ave",
    "iso:country":"US",
    "sg:address":"611 E 30th Ave",
    "sg:city":"Spokane",
    "sg:classifiers":[
        {
            "category":"Sports & Exercise",
            "subcategory":"Gym",
            "type":"Entertainment"
        }
    ],
    "sg:phone":"+1 509 838 5444",
    "sg:postcode":"99203",
    "sg:province":"WA",
    "sg:tags":[
        "fitness",
        "physical",
        "facility"
    ],
    "wof:name":"Renaissance Fitness For Women",
    "wof:placetype":"venue"
},
  "geometry": {"coordinates":[-117.40173,47.627329],"type":"Point"}
}