{
  "type": "Feature",
  "properties": {
    "addr:full":"3455 Emma Rd Bellingham WA 98226",
    "addr:housenumber":"3455",
    "addr:postcode":"98226",
    "addr:street":"Emma Rd",
    "iso:country":"US",
    "sg:address":"3455 Emma Rd",
    "sg:city":"Bellingham",
    "sg:classifiers":[
        {
            "category":"Utilities",
            "type":"Services"
        }
    ],
    "sg:phone":"+1 360 758 2236",
    "sg:postcode":"98226",
    "sg:province":"WA",
    "sg:tags":[
        "other",
        "electric",
        "combined"
    ],
    "wof:name":"Dynamic Energy Corp",
    "wof:placetype":"venue"
},
  "geometry": {"coordinates":[-122.671436,48.735423],"type":"Point"}
}