{
  "type": "Feature",
  "properties": {
    "addr:full":"5117 Panther Lake Rd Snohomish WA 98290",
    "addr:housenumber":"5117",
    "addr:postcode":"98290",
    "addr:street":"Panther Lake Rd",
    "iso:country":"US",
    "sg:address":"5117 Panther Lake Rd",
    "sg:city":"Snohomish",
    "sg:classifiers":[
        {
            "category":"Professional",
            "subcategory":"Business Services",
            "type":"Services"
        },
        {
            "category":"Building & Trades",
            "subcategory":"Construction",
            "type":"Services"
        }
    ],
    "sg:phone":"+1 425 760 1567",
    "sg:postcode":"98290",
    "sg:province":"WA",
    "sg:tags":[
        "concrete",
        "contractor"
    ],
    "wof:name":"J P Design Build",
    "wof:placetype":"venue"
},
  "geometry": {"coordinates":[-122.011107,47.94981],"type":"Point"}
}