{
  "type": "Feature",
  "properties": {
    "addr:full":"338 S 6th St Sunnyside WA 98944",
    "addr:housenumber":"338",
    "addr:postcode":"98944",
    "addr:street":"S 6Th St",
    "iso:country":"US",
    "sg:address":"338 S 6th St",
    "sg:city":"Sunnyside",
    "sg:classifiers":[
        {
            "category":"Manufacturing",
            "subcategory":"Printing",
            "type":"Manufacturing & Wholesale Goods"
        }
    ],
    "sg:phone":"+1 509 839 2931",
    "sg:postcode":"98944",
    "sg:province":"WA",
    "sg:tags":[
        "printer"
    ],
    "wof:name":"Northwest Publishing",
    "wof:placetype":"venue"
},
  "geometry": {"coordinates":[-120.01286,46.324844],"type":"Point"}
}