{
  "type": "Feature",
  "properties": {
    "iso:country":"US",
    "sg:address":"1017 S Boone St",
    "sg:city":"Aberdeen",
    "sg:classifiers":[
        {
            "category":"Personal",
            "subcategory":"Tanning Parlor",
            "type":"Services"
        }
    ],
    "sg:phone":"+1 360 532 1036",
    "sg:postcode":"98520",
    "sg:province":"WA",
    "sg:tags":[
        "salon"
    ],
    "wof:name":"California Rayz",
    "wof:placetype":"venue"
},
  "geometry": {"coordinates":[-123.80310299999999,46.961065],"type":"Point"}
}