{
  "type": "Feature",
  "properties": {
    "addr:full":"11712 E Sprague Ave Spokane Valley WA 99206",
    "addr:housenumber":"11712",
    "addr:postcode":"99206",
    "addr:street":"E Sprague Ave",
    "iso:country":"US",
    "sg:address":"11712 E Sprague Ave",
    "sg:city":"Spokane Valley",
    "sg:classifiers":[
        {
            "category":"Government",
            "subcategory":"Post Office",
            "type":"Public Place"
        }
    ],
    "sg:phone":"+1 509 891 7168",
    "sg:postcode":"99206",
    "sg:province":"WA",
    "sg:tags":[
        "postal",
        "us"
    ],
    "wof:name":"US Post Office",
    "wof:placetype":"venue"
},
  "geometry": {"coordinates":[-117.248751,47.656978],"type":"Point"}
}