{
  "type": "Feature",
  "properties": {
    "addr:full":"919 Division St NW Olympia WA 98502",
    "addr:housenumber":"919",
    "addr:postcode":"olympia wa 98502",
    "addr:street":"Division St Nw",
    "iso:country":"US",
    "sg:address":"919 Division St NW",
    "sg:city":"Olympia",
    "sg:classifiers":[
        {
            "category":"Organizations",
            "subcategory":"Religious Organization",
            "type":"Services"
        }
    ],
    "sg:phone":"+1 360 352 4214",
    "sg:postcode":"98502",
    "sg:province":"WA",
    "wof:name":"Calvary Chapel",
    "wof:placetype":"venue"
},
  "geometry": {"coordinates":[-122.925647,47.053785],"type":"Point"}
}