{
  "type": "Feature",
  "properties": {
    "addr:full":"1715 W Stewart Ave Puyallup WA 98371",
    "addr:housenumber":"1715",
    "addr:postcode":"98371",
    "addr:street":"W Stewart Ave",
    "iso:country":"US",
    "sg:address":"1715 W Stewart Ave",
    "sg:city":"Puyallup",
    "sg:classifiers":[
        {
            "category":"Wholesale",
            "subcategory":"Machinery & Supplies",
            "type":"Manufacturing & Wholesale Goods"
        }
    ],
    "sg:phone":"+1 253 840 0737",
    "sg:postcode":"98371",
    "sg:province":"WA",
    "sg:tags":[
        "equipment",
        "irrigation",
        "system"
    ],
    "wof:name":"Artistic Enterprises",
    "wof:placetype":"venue"
},
  "geometry": {"coordinates":[-122.317336,47.196756],"type":"Point"}
}