{
  "type": "Feature",
  "properties": {
    "addr:full":"11243 Champagne Point Rd NE Kirkland WA 98034",
    "addr:housenumber":"11243",
    "addr:postcode":"98034",
    "addr:street":"Champagne Point Rd Ne",
    "iso:country":"US",
    "sg:address":"11243 Champagne Point Rd NE",
    "sg:city":"Kirkland",
    "sg:classifiers":[
        {
            "category":"Professional",
            "type":"Services"
        }
    ],
    "sg:phone":"+1 425 823 5131",
    "sg:postcode":"98034",
    "sg:province":"WA",
    "wof:name":"Flight Attendants For Wor",
    "wof:placetype":"venue"
},
  "geometry": {"coordinates":[-122.24172299999999,47.701342],"type":"Point"}
}