{
  "type": "Feature",
  "properties": {
    "addr:full":"1175 Center Dr Ste 130 Dupont WA 98327",
    "addr:housenumber":"1175",
    "addr:postcode":"98327",
    "addr:street":"Center Dr Ste 130 Dupont",
    "iso:country":"US",
    "sg:address":"1175 Center Dr Ste 130",
    "sg:city":"Dupont",
    "sg:classifiers":[
        {
            "category":"Health Services",
            "subcategory":"Doctor",
            "type":"Services"
        }
    ],
    "sg:phone":"+1 253 964 5260",
    "sg:postcode":"98327",
    "sg:province":"WA",
    "sg:tags":[
        "practice",
        "family"
    ],
    "sg:website":"www.fhshealth.org/fmg/fmgc_DuPon...",
    "wof:name":"DuPont Medical Clinic",
    "wof:placetype":"venue"
},
  "geometry": {"coordinates":[-122.640001,47.108986],"type":"Point"}
}