{
  "type": "Feature",
  "properties": {
    "addr:full":"13014 118th Pl NE Kirkland WA 98034",
    "addr:housenumber":"13014",
    "addr:postcode":"98034",
    "addr:street":"118Th Pl Ne",
    "iso:country":"US",
    "sg:address":"13014 118th Pl NE",
    "sg:city":"Kirkland",
    "sg:classifiers":[
        {
            "category":"Building & Trades",
            "subcategory":"Locksmith",
            "type":"Services"
        }
    ],
    "sg:phone":"+1 206 577 5617",
    "sg:postcode":"98034",
    "sg:province":"WA",
    "sg:tags":[
        "key"
    ],
    "wof:name":"24 Hour Locksmith",
    "wof:placetype":"venue"
},
  "geometry": {"coordinates":[-122.183543,47.716872],"type":"Point"}
}