{
  "type": "Feature",
  "properties": {
    "addr:full":"17715 46th Ave SE Bothell WA 98012",
    "addr:housenumber":"17715",
    "addr:postcode":"98012",
    "addr:street":"46Th Ave Se",
    "iso:country":"US",
    "sg:address":"17715 46th Ave SE",
    "sg:city":"Bothell",
    "sg:classifiers":[
        {
            "category":"Professional",
            "subcategory":"Computer Services",
            "type":"Services"
        },
        {
            "category":"Internet Cafe",
            "subcategory":"None",
            "type":"Food & Drink"
        }
    ],
    "sg:phone":"+1 425 481 9500",
    "sg:postcode":"98012",
    "sg:province":"WA",
    "sg:tags":[
        "product",
        "software"
    ],
    "wof:name":"Kuantum Solutions, Inc",
    "wof:placetype":"venue"
},
  "geometry": {"coordinates":[-122.170798,47.835092],"type":"Point"}
}