{
  "type": "Feature",
  "properties": {
    "addr:full":"4135 Providence Point Dr SE Issaquah WA 98029",
    "addr:housenumber":"4135",
    "addr:postcode":"98029",
    "addr:street":"Providence Point Dr Se",
    "iso:country":"US",
    "sg:address":"4135 Providence Point Dr SE",
    "sg:city":"Issaquah",
    "sg:classifiers":[
        {
            "category":"Restaurant",
            "type":"Food & Drink"
        }
    ],
    "sg:phone":"+1 425 391 3335",
    "sg:postcode":"98029",
    "sg:province":"WA",
    "wof:name":"Bake's Place At Providence Pnt",
    "wof:placetype":"venue"
},
  "geometry": {"coordinates":[-122.044113,47.57002],"type":"Point"}
}