{
  "type": "Feature",
  "properties": {
    "addr:full":"9921 N Nevada St Spokane WA 99218",
    "addr:housenumber":"9921",
    "addr:postcode":"99218",
    "addr:street":"N Nevada St",
    "iso:country":"US",
    "sg:address":"9921 N Nevada St",
    "sg:city":"Spokane",
    "sg:classifiers":[
        {
            "category":"Real Estate",
            "subcategory":"Real Estate Services",
            "type":"Services"
        },
        {
            "category":"Structure",
            "subcategory":"Office Building",
            "type":"Public Place"
        },
        {
            "category":"Real Estate",
            "subcategory":"Real Estate Agent",
            "type":"Services"
        }
    ],
    "sg:phone":"+1 509 464 1379",
    "sg:postcode":"99218",
    "sg:province":"WA",
    "sg:tags":[
        "management",
        "park"
    ],
    "wof:name":"Nevada Street Properties",
    "wof:placetype":"venue"
},
  "geometry": {"coordinates":[-117.395335,47.747609],"type":"Point"}
}