{
  "type": "Feature",
  "properties": {
    "addr:full":"19707 44th Ave W Lynnwood WA 98036",
    "addr:housenumber":"19707",
    "addr:postcode":"98036",
    "addr:street":"44Th Ave W",
    "iso:country":"US",
    "sg:address":"19707 44th Ave W",
    "sg:city":"Lynnwood",
    "sg:classifiers":[
        {
            "category":"Professional",
            "subcategory":"Lawyer & Legal Services",
            "type":"Services"
        }
    ],
    "sg:phone":"+1 425 774 8291",
    "sg:postcode":"98036",
    "sg:province":"WA",
    "wof:name":"Arrabito John",
    "wof:placetype":"venue"
},
  "geometry": {"coordinates":[-122.292293,47.820212],"type":"Point"}
}