{
  "type": "Feature",
  "properties": {
    "addr:full":"513 1st St Cheney WA 99004",
    "addr:housenumber":"513",
    "addr:postcode":"99004",
    "addr:street":"1St St",
    "iso:country":"US",
    "sg:address":"513 1st St",
    "sg:city":"Cheney",
    "sg:classifiers":[
        {
            "category":"Professional",
            "type":"Services"
        },
        {
            "category":"Restaurant",
            "type":"Food & Drink"
        }
    ],
    "sg:phone":"+1 509 235 8943",
    "sg:postcode":"99004",
    "sg:province":"WA",
    "sg:tags":[
        "caterer"
    ],
    "wof:name":"Cheney Delights",
    "wof:placetype":"venue"
},
  "geometry": {"coordinates":[-117.57507200000001,47.487614],"type":"Point"}
}