{
  "type": "Feature",
  "properties": {
    "addr:full":"4420 Meridian St Bellingham WA 98226",
    "addr:housenumber":"4420",
    "addr:postcode":"98226",
    "addr:street":"Meridian St",
    "iso:country":"US",
    "sg:address":"4420 Meridian St",
    "sg:city":"Bellingham",
    "sg:classifiers":[
        {
            "category":"Restaurant",
            "type":"Food & Drink"
        }
    ],
    "sg:menulink":"http://www.allmenus.com/wa/bellingham/213031-mcdonalds/menu/",
    "sg:phone":"+1 360 671 1129",
    "sg:postcode":"98226",
    "sg:province":"WA",
    "sg:tags":[
        "burger",
        "american"
    ],
    "wof:name":"McDonald's",
    "wof:placetype":"venue"
},
  "geometry": {"coordinates":[-122.486017,48.801549],"type":"Point"}
}