{
  "type": "Feature",
  "properties": {
    "addr:full":"9025 Beacon Ave Vancouver WA 98664",
    "addr:housenumber":"9025",
    "addr:postcode":"98664",
    "addr:street":"Beacon Ave",
    "iso:country":"US",
    "sg:address":"9025 Beacon Ave",
    "sg:city":"Vancouver",
    "sg:classifiers":[
        {
            "category":"Professional",
            "subcategory":"Management & Consulting",
            "type":"Services"
        }
    ],
    "sg:phone":"+1 360 737 1810",
    "sg:postcode":"98664",
    "sg:province":"WA",
    "wof:name":"Hoteltechs",
    "wof:placetype":"venue"
},
  "geometry": {"coordinates":[-122.579669,45.615025],"type":"Point"}
}