{
  "type": "Feature",
  "properties": {
    "addr:full":"7806 NE 94th Ave Vancouver WA 98662",
    "addr:housenumber":"7806",
    "addr:postcode":"98662",
    "addr:street":"Ne 94Th Ave",
    "iso:country":"US",
    "sg:address":"7806 NE 94th Ave",
    "sg:city":"Vancouver",
    "sg:classifiers":[
        {
            "category":"Personal",
            "type":"Services"
        },
        {
            "category":"Professional",
            "subcategory":"Business Services",
            "type":"Services"
        },
        {
            "category":"Shopping",
            "subcategory":"Discount & Variety Stores",
            "type":"Retail Goods"
        },
        {
            "category":"Home & Garden",
            "subcategory":"Furniture",
            "type":"Retail Goods"
        }
    ],
    "sg:phone":"+1 360 260 9019",
    "sg:postcode":"98662",
    "sg:province":"WA",
    "sg:tags":[
        "liquidation",
        "liquidator",
        "auction",
        "estates-sales",
        "appraisal"
    ],
    "wof:name":"Advanced Liquidator",
    "wof:placetype":"venue"
},
  "geometry": {"coordinates":[-122.576071,45.678849],"type":"Point"}
}