{
  "type": "Feature",
  "properties": {
    "addr:full":"2811 Niagara St Bellingham WA 98226",
    "addr:housenumber":"2811",
    "addr:postcode":"98226",
    "addr:street":"Niagara St",
    "iso:country":"US",
    "sg:address":"2811 Niagara St",
    "sg:city":"Bellingham",
    "sg:classifiers":[
        {
            "category":"Shopping",
            "type":"Retail Goods"
        }
    ],
    "sg:phone":"+1 360 733 6699",
    "sg:postcode":"98226",
    "sg:province":"WA",
    "sg:tags":[
        "merchandise"
    ],
    "wof:name":"Rmks Stamp & Coins",
    "wof:placetype":"venue"
},
  "geometry": {"coordinates":[-122.43309600000001,48.767193],"type":"Point"}
}