{
  "type": "Feature",
  "properties": {
    "addr:full":"574 Russell Rd Forks WA 98331",
    "addr:housenumber":"574",
    "addr:postcode":"98331",
    "addr:street":"Russell Rd",
    "iso:country":"US",
    "sg:address":"574 Russell Rd",
    "sg:city":"Forks",
    "sg:classifiers":[
        {
            "category":"Retail",
            "subcategory":"Auto Repair",
            "type":"Services"
        }
    ],
    "sg:phone":"+1 360 374 5411",
    "sg:postcode":"98331",
    "sg:province":"WA",
    "sg:tags":[
        "general"
    ],
    "wof:name":"Eagle Auto Repair & Towing",
    "wof:placetype":"venue"
},
  "geometry": {"coordinates":[-124.40171100000001,47.945567],"type":"Point"}
}