{
  "type": "Feature",
  "properties": {
    "addr:full":"1408 S Cloverdale St 100 Seattle WA 98108",
    "addr:housenumber":"1408;100",
    "addr:postcode":"98108",
    "addr:street":"S Cloverdale St",
    "iso:country":"US",
    "sg:address":"1408 S Cloverdale St 100",
    "sg:city":"Seattle",
    "sg:classifiers":[
        {
            "category":"Professional",
            "subcategory":"Advertising",
            "type":"Services"
        },
        {
            "category":"Communications",
            "type":"Services"
        }
    ],
    "sg:phone":"+1 206 841 5762",
    "sg:postcode":"98108",
    "sg:province":"WA",
    "sg:tags":[
        "marketing",
        "design",
        "web"
    ],
    "sg:website":"seattleorganicseo.com",
    "wof:name":"Seattle Organic SEO Marketing Services",
    "wof:placetype":"venue"
},
  "geometry": {"coordinates":[-122.31379800000001,47.526464],"type":"Point"}
}