{
  "type": "Feature",
  "properties": {
    "addr:full":"20120 Vashon Hwy SW Vashon WA 98070",
    "addr:housenumber":"20120",
    "addr:postcode":"98070",
    "addr:street":"Vashon Hwy Sw",
    "iso:country":"US",
    "sg:address":"20120 Vashon Hwy SW",
    "sg:city":"Vashon",
    "sg:classifiers":[
        {
            "category":"Education",
            "subcategory":"School",
            "type":"Public Place"
        }
    ],
    "sg:phone":"+1 206 463 9171",
    "sg:postcode":"98070",
    "sg:province":"WA",
    "sg:tags":[
        "independent",
        "district"
    ],
    "wof:name":"Family Link/Student Link",
    "wof:placetype":"venue"
},
  "geometry": {"coordinates":[-122.460415,47.423502],"type":"Point"}
}