{
  "type": "Feature",
  "properties": {
    "addr:full":"11109 NE 60th St Kirkland WA 98033",
    "addr:housenumber":"11109",
    "addr:postcode":"98033",
    "addr:street":"Ne 60Th St",
    "iso:country":"US",
    "sg:address":"11109 NE 60th St",
    "sg:city":"Kirkland",
    "sg:classifiers":[
        {
            "category":"Building & Trades",
            "subcategory":"Construction",
            "type":"Services"
        }
    ],
    "sg:phone":"+1 425 868 4301",
    "sg:postcode":"98033",
    "sg:province":"WA",
    "sg:tags":[
        "altering",
        "remodeling",
        "contractor"
    ],
    "sg:website":"http://www.hamishanderson.com",
    "wof:name":"Hamish Anderson Custom Homes Inc",
    "wof:placetype":"venue"
},
  "geometry": {"coordinates":[-122.192761,47.661091],"type":"Point"}
}