{
  "type": "Feature",
  "properties": {
    "addr:full":"12727 NE Northup Way Ste 22 Bellevue WA 98005",
    "addr:housenumber":"12727",
    "addr:postcode":"98005",
    "addr:street":"Ne Northup Way Ste 22",
    "iso:country":"US",
    "sg:address":"12727 NE Northup Way Ste 22",
    "sg:city":"Bellevue",
    "sg:classifiers":[
        {
            "category":"Health Services",
            "subcategory":"Clinic",
            "type":"Services"
        },
        {
            "category":"Health Services",
            "subcategory":"Health Practitioner",
            "type":"Services"
        }
    ],
    "sg:phone":"+1 503 560 0085",
    "sg:postcode":"98005",
    "sg:province":"WA",
    "sg:tags":[
        "loss",
        "naturopathic/holistic",
        "weight"
    ],
    "sg:website":"www.originholistic.com",
    "wof:name":"Origin Holistic",
    "wof:placetype":"venue"
},
  "geometry": {"coordinates":[-122.170438,47.62724],"type":"Point"}
}