{
  "type": "Feature",
  "properties": {
    "addr:full":"680 Alpowa Creek Rd Clarkston WA 99347",
    "addr:housenumber":"680",
    "addr:postcode":"99347",
    "addr:street":"Alpowa Creek Rd",
    "iso:country":"US",
    "sg:address":"680 Alpowa Creek Rd",
    "sg:city":"Clarkston",
    "sg:phone":"+1 509 843 1482",
    "sg:postcode":"99347",
    "sg:province":"WA",
    "sg:tags":[
        "farm",
        "wheat",
        "beef",
        "feedlot",
        "cattle"
    ],
    "wof:name":"Lyle Landkammer",
    "wof:placetype":"venue"
},
  "geometry": {"coordinates":[-117.389917,46.40649],"type":"Point"}
}