{
  "type": "Feature",
  "properties": {
    "iso:country":"US",
    "sg:address":"17071 157th St SE",
    "sg:city":"Monroe",
    "sg:classifiers":[
        {
            "category":"Wholesale",
            "subcategory":"Non-durable Goods",
            "type":"Manufacturing & Wholesale Goods"
        }
    ],
    "sg:phone":"+1 360 805 3132",
    "sg:postcode":"98272",
    "sg:province":"WA",
    "wof:name":"Merchpol Imports",
    "wof:placetype":"venue"
},
  "geometry": {"coordinates":[-122.00469099999999,47.85502],"type":"Point"}
}