{
  "type": "Feature",
  "properties": {
    "addr:full":"13224 46th Pl W Mukilteo WA 98275",
    "addr:housenumber":"13224",
    "addr:postcode":"98275",
    "addr:street":"46Th Pl W",
    "iso:country":"US",
    "sg:address":"13224 46th Pl W",
    "sg:city":"Mukilteo",
    "sg:classifiers":[
        {
            "category":"Professional",
            "type":"Services"
        }
    ],
    "sg:phone":"+1 425 745 4907",
    "sg:postcode":"98275",
    "sg:province":"WA",
    "wof:name":"Young & Hahn Corp",
    "wof:placetype":"venue"
},
  "geometry": {"coordinates":[-122.295907,47.878359],"type":"Point"}
}