{
  "type": "Feature",
  "properties": {
    "addr:full":"2850 SW Yancy St Seattle WA 98126",
    "addr:housenumber":"2850",
    "addr:postcode":"98126",
    "addr:street":"Sw Yancy St",
    "iso:country":"US",
    "sg:address":"2850 SW Yancy St",
    "sg:city":"Seattle",
    "sg:classifiers":[
        {
            "category":"Banks & Credit Unions",
            "subcategory":"Investment Brokerage",
            "type":"Services"
        }
    ],
    "sg:phone":"+1 206 913 0066",
    "sg:postcode":"98126",
    "sg:province":"WA",
    "wof:name":"Woodinville Business Center 1",
    "wof:placetype":"venue"
},
  "geometry": {"coordinates":[-122.370312,47.567683],"type":"Point"}
}