{
  "type": "Feature",
  "properties": {
    "addr:full":"7009 W Willamette Ave Kennewick WA 99336",
    "addr:housenumber":"7009",
    "addr:postcode":"99336",
    "addr:street":"W Willamette Ave",
    "iso:country":"US",
    "sg:address":"7009 W Willamette Ave",
    "sg:city":"Kennewick",
    "sg:classifiers":[
        {
            "category":"Retail",
            "subcategory":"Animal Services",
            "type":"Services"
        }
    ],
    "sg:phone":"+1 509 968 4178",
    "sg:postcode":"99336",
    "sg:province":"WA",
    "wof:name":"Naneum Creek Kennels",
    "wof:placetype":"venue"
},
  "geometry": {"coordinates":[-119.216054,46.228543],"type":"Point"}
}