{
  "type": "Feature",
  "properties": {
    "addr:full":"1008 140th Ave NE Bellevue WA 98005",
    "addr:housenumber":"1008",
    "addr:postcode":"98005",
    "addr:street":"140Th Ave Ne",
    "iso:country":"US",
    "sg:address":"1008 140th Ave NE",
    "sg:city":"Bellevue",
    "sg:classifiers":[
        {
            "category":"Banks & Credit Unions",
            "subcategory":"Bank",
            "type":"Services"
        }
    ],
    "sg:phone":"+1 425 641 4500",
    "sg:postcode":"98005",
    "sg:province":"WA",
    "sg:tags":[
        "escrow"
    ],
    "wof:name":"Columbia Escrow Svc",
    "wof:placetype":"venue"
},
  "geometry": {"coordinates":[-122.15355599999999,47.619414],"type":"Point"}
}