{
  "type": "Feature",
  "properties": {
    "addr:full":"9827 124th Ave SE Renton WA 98056",
    "addr:housenumber":"9827",
    "addr:postcode":"98056",
    "addr:street":"124Th Ave Se",
    "iso:country":"US",
    "sg:address":"9827 124th Ave SE",
    "sg:city":"Renton",
    "sg:classifiers":[
        {
            "category":"Social Services",
            "type":"Services"
        }
    ],
    "sg:phone":"+1 425 277 3235",
    "sg:postcode":"98056",
    "sg:province":"WA",
    "wof:name":"Bethesda Adult Family Hom",
    "wof:placetype":"venue"
},
  "geometry": {"coordinates":[-122.174767,47.514503],"type":"Point"}
}