{
  "type": "Feature",
  "properties": {
    "addr:full":"20342 Widme Rd NE Poulsbo WA 98370",
    "addr:housenumber":"20342",
    "addr:postcode":"98370",
    "addr:street":"Widme Rd Ne",
    "iso:country":"US",
    "sg:address":"20342 Widme Rd NE",
    "sg:city":"Poulsbo",
    "sg:classifiers":[
        {
            "category":"Food & Beverages",
            "subcategory":"Specialty",
            "type":"Retail Goods"
        }
    ],
    "sg:phone":"+1 360 598 5892",
    "sg:postcode":"98370",
    "sg:province":"WA",
    "wof:name":"Heron Botanicals",
    "wof:placetype":"venue"
},
  "geometry": {"coordinates":[-122.590283,47.744713],"type":"Point"}
}