{
  "type": "Feature",
  "properties": {
    "addr:full":"210 W Sprague Ave Spokane WA 99201",
    "addr:housenumber":"210",
    "addr:postcode":"99201",
    "addr:street":"W Sprague Ave",
    "iso:country":"US",
    "sg:address":"210 W Sprague Ave",
    "sg:city":"Spokane",
    "sg:classifiers":[
        {
            "category":"Social Services",
            "type":"Services"
        }
    ],
    "sg:phone":"+1 509 747 8224",
    "sg:postcode":"99201",
    "sg:province":"WA",
    "sg:tags":[
        "counselor",
        "marriage",
        "family"
    ],
    "sg:website":"www.lssinw.org",
    "wof:name":"Lutheran Social Svc",
    "wof:placetype":"venue"
},
  "geometry": {"coordinates":[-117.41479,47.657316],"type":"Point"}
}