{
  "type": "Feature",
  "properties": {
    "addr:full":"20696 Bond Rd NE Poulsbo WA 98370",
    "addr:housenumber":"20696",
    "addr:postcode":"98370",
    "addr:street":"Bond Rd Ne",
    "iso:country":"US",
    "sg:address":"20696 Bond Rd NE",
    "sg:city":"Poulsbo",
    "sg:classifiers":[
        {
            "category":"Personal",
            "subcategory":"Beauty Salon",
            "type":"Services"
        }
    ],
    "sg:phone":"+1 360 779 5999",
    "sg:postcode":"98370",
    "sg:province":"WA",
    "sg:tags":[
        "treatment",
        "skin"
    ],
    "wof:name":"North West Skin Cancer Co",
    "wof:placetype":"venue"
},
  "geometry": {"coordinates":[-122.650446,47.74723],"type":"Point"}
}