{
  "type": "Feature",
  "properties": {
    "addr:full":"111 E Hanzlik Ct Allyn WA 98524",
    "addr:housenumber":"111",
    "addr:postcode":"98524",
    "addr:street":"E Hanzlik Ct",
    "iso:country":"US",
    "sg:address":"111 E Hanzlik Ct",
    "sg:city":"Allyn",
    "sg:classifiers":[
        {
            "category":"Farming",
            "subcategory":"Farm",
            "type":"Manufacturing & Wholesale Goods"
        }
    ],
    "sg:phone":"+1 360 275 5745",
    "sg:postcode":"98524",
    "sg:province":"WA",
    "wof:name":"Irish Mist Farm",
    "wof:placetype":"venue"
},
  "geometry": {"coordinates":[-122.837104,47.363862],"type":"Point"}
}