{
  "type": "Feature",
  "properties": {
    "addr:full":"4632 Fowler Ave Ofc Everett WA 98203",
    "addr:housenumber":"4632",
    "addr:postcode":"98203",
    "addr:street":"Fowler Ave",
    "iso:country":"US",
    "sg:address":"4632 Fowler Ave Ofc",
    "sg:city":"Everett",
    "sg:classifiers":[
        {
            "category":"Real Estate",
            "subcategory":"Real Estate Services",
            "type":"Services"
        },
        {
            "category":"Real Estate",
            "subcategory":"Real Estate Operator",
            "type":"Services"
        }
    ],
    "sg:phone":"+1 425 252 1772",
    "sg:postcode":"98203",
    "sg:province":"WA",
    "sg:tags":[
        "vacancy",
        "apartment",
        "rental",
        "finder",
        "listing"
    ],
    "wof:name":"Forest Park Estates",
    "wof:placetype":"venue"
},
  "geometry": {"coordinates":[-122.219594,47.956231],"type":"Point"}
}