{
  "type": "Feature",
  "properties": {
    "addr:full":"12505 NE 23rd Pl Bellevue WA 98005",
    "addr:housenumber":"12505",
    "addr:postcode":"98005",
    "addr:street":"Ne 23Rd Pl",
    "iso:country":"US",
    "sg:address":"12505 NE 23rd Pl",
    "sg:city":"Bellevue",
    "sg:classifiers":[
        {
            "category":"Wholesale",
            "subcategory":"Home Furnishings",
            "type":"Manufacturing & Wholesale Goods"
        }
    ],
    "sg:phone":"+1 425 396 5782",
    "sg:postcode":"98005",
    "sg:province":"WA",
    "sg:tags":[
        "exporter"
    ],
    "wof:name":"Export Los Angeles LLC",
    "wof:placetype":"venue"
},
  "geometry": {"coordinates":[-122.1728,47.631204],"type":"Point"}
}