{
  "type": "Feature",
  "properties": {
    "addr:full":"3520 Paine Ave # Everett WA 98201",
    "addr:housenumber":"3520",
    "addr:postcode":"98201",
    "addr:street":"Paine Ave #",
    "iso:country":"US",
    "sg:address":"3520 Paine Ave #",
    "sg:city":"Everett",
    "sg:classifiers":[
        {
            "category":"Manufacturing",
            "subcategory":"Rubber & Plastics",
            "type":"Manufacturing & Wholesale Goods"
        },
        {
            "category":"Wholesale",
            "subcategory":"Machinery & Supplies",
            "type":"Manufacturing & Wholesale Goods"
        },
        {
            "category":"Building & Trades",
            "subcategory":"Equipment Rental",
            "type":"Services"
        }
    ],
    "sg:phone":"+1 425 258 3476",
    "sg:postcode":"98201",
    "sg:province":"WA",
    "sg:tags":[
        "industrial",
        "hose",
        "tubing-rubber",
        "hydraulic"
    ],
    "sg:website":"http://northsoundhoseeverett.com",
    "wof:name":"North Sound Hose & Fittings",
    "wof:placetype":"venue"
},
  "geometry": {"coordinates":[-122.198396,47.970693],"type":"Point"}
}