{
  "type": "Feature",
  "properties": {
    "addr:full":"1314 Broadway St Longview WA 98632",
    "addr:housenumber":"1314",
    "addr:postcode":"98632",
    "addr:street":"Broadway St",
    "iso:country":"US",
    "sg:address":"1314 Broadway St",
    "sg:city":"Longview",
    "sg:classifiers":[
        {
            "category":"Personal",
            "subcategory":"Beauty Salon",
            "type":"Services"
        }
    ],
    "sg:phone":"+1 360 636 4041",
    "sg:postcode":"98632",
    "sg:province":"WA",
    "wof:name":"Esteem Salon",
    "wof:placetype":"venue"
},
  "geometry": {"coordinates":[-122.93405,46.138434],"type":"Point"}
}