{
  "type": "Feature",
  "properties": {
    "addr:full":"1741 4th Ave S Seattle WA 98134",
    "addr:housenumber":"1741",
    "addr:postcode":"98134",
    "addr:street":"4Th Ave S",
    "iso:country":"US",
    "sg:address":"1741 4th Ave S",
    "sg:city":"Seattle",
    "sg:classifiers":[
        {
            "category":"Banks & Credit Unions",
            "subcategory":"Bank",
            "type":"Services"
        }
    ],
    "sg:phone":"+1 206 622 1850",
    "sg:postcode":"98134",
    "sg:province":"WA",
    "wof:name":"Express Credit Union",
    "wof:placetype":"venue"
},
  "geometry": {"coordinates":[-122.329559,47.586856],"type":"Point"}
}