{
  "type": "Feature",
  "properties": {
    "addr:full":"111 E Wishkah St Aberdeen WA 98520",
    "addr:housenumber":"111",
    "addr:postcode":"98520",
    "addr:street":"E Wishkah St",
    "iso:country":"US",
    "sg:address":"111 E Wishkah St",
    "sg:city":"Aberdeen",
    "sg:classifiers":[
        {
            "category":"Shopping",
            "subcategory":"Hobbies, Toys, & Games",
            "type":"Retail Goods"
        }
    ],
    "sg:phone":"+1 360 533 8639",
    "sg:postcode":"98520",
    "sg:province":"WA",
    "sg:tags":[
        "toy",
        "store",
        "supply"
    ],
    "wof:name":"The Store",
    "wof:placetype":"venue"
},
  "geometry": {"coordinates":[-123.817744,46.974346],"type":"Point"}
}