{
  "type": "Feature",
  "properties": {
    "addr:full":"102 S 5th St Satsop WA 98591",
    "addr:housenumber":"102",
    "addr:postcode":"98591",
    "addr:street":"S 5Th St",
    "iso:country":"US",
    "sg:address":"102 S 5th St",
    "sg:city":"Satsop",
    "sg:classifiers":[
        {
            "category":"Government",
            "subcategory":"Post Office",
            "type":"Public Place"
        }
    ],
    "sg:phone":"+1 360 482 3432",
    "sg:postcode":"98591",
    "sg:province":"WA",
    "wof:name":"US Post Office",
    "wof:placetype":"venue"
},
  "geometry": {"coordinates":[-122.849628,46.440094],"type":"Point"}
}