{
  "type": "Feature",
  "properties": {
    "addr:full":"12302 NE 124th St Kirkland WA 98034",
    "addr:housenumber":"12302",
    "addr:postcode":"98034",
    "addr:street":"Ne 124Th St",
    "iso:country":"US",
    "sg:address":"12302 NE 124th St",
    "sg:city":"Kirkland",
    "sg:classifiers":[
        {
            "category":"Retail",
            "subcategory":"Car Wash",
            "type":"Services"
        }
    ],
    "sg:phone":"+1 425 823 4700",
    "sg:postcode":"98034",
    "sg:province":"WA",
    "sg:tags":[
        "carwash"
    ],
    "wof:name":"Brown Bear Car Wash",
    "wof:placetype":"venue"
},
  "geometry": {"coordinates":[-122.177002,47.708801],"type":"Point"}
}