{
  "type": "Feature",
  "properties": {
    "addr:full":"7627 Kerbaugh Rd NE Olympia WA 98516",
    "addr:housenumber":"7627",
    "addr:postcode":"98516",
    "addr:street":"Kerbaugh Rd Ne",
    "iso:country":"US",
    "sg:address":"7627 Kerbaugh Rd NE",
    "sg:city":"Olympia",
    "sg:classifiers":[
        {
            "category":"Building & Trades",
            "subcategory":"Construction",
            "type":"Services"
        }
    ],
    "sg:phone":"+1 360 357 4130",
    "sg:postcode":"98516",
    "sg:province":"WA",
    "sg:tags":[
        "house",
        "speculative",
        "family",
        "contractor"
    ],
    "wof:name":"G M Carlson Co Inc",
    "wof:placetype":"venue"
},
  "geometry": {"coordinates":[-122.82311900000001,47.146648],"type":"Point"}
}