{
  "type": "Feature",
  "properties": {
    "addr:full":"194 W Washington St Sequim WA 98382",
    "addr:housenumber":"194",
    "addr:postcode":"98382",
    "addr:street":"W Washington St",
    "iso:country":"US",
    "sg:address":"194 W Washington St",
    "sg:city":"Sequim",
    "sg:classifiers":[
        {
            "category":"Retail",
            "subcategory":"Car Wash",
            "type":"Services"
        }
    ],
    "sg:phone":"+1 360 683 6226",
    "sg:postcode":"98382",
    "sg:province":"WA",
    "sg:tags":[
        "polishing",
        "washing"
    ],
    "wof:name":"Kettel's Brushless Car Wash",
    "wof:placetype":"venue"
},
  "geometry": {"coordinates":[-123.103325,48.079726],"type":"Point"}
}