{
  "type": "Feature",
  "properties": {
    "addr:full":"2704 NE 85th Ave Vancouver WA 98662",
    "addr:housenumber":"2704",
    "addr:postcode":"98662",
    "addr:street":"Ne 85Th Ave",
    "iso:country":"US",
    "sg:address":"2704 NE 85th Ave",
    "sg:city":"Vancouver",
    "sg:classifiers":[
        {
            "category":"Building & Trades",
            "subcategory":"Cleaning & Sanitation",
            "type":"Services"
        }
    ],
    "sg:phone":"+1 360 883 2352",
    "sg:postcode":"98662",
    "sg:province":"WA",
    "sg:tags":[
        "maintenance"
    ],
    "wof:name":"Lyubas Housecleaning",
    "wof:placetype":"venue"
},
  "geometry": {"coordinates":[-122.58644700000001,45.641641],"type":"Point"}
}