{
  "type": "Feature",
  "properties": {
    "addr:full":"187 Kirkland Rd Chehalis WA 98532",
    "addr:housenumber":"187",
    "addr:postcode":"98532",
    "addr:street":"Kirkland Rd",
    "iso:country":"US",
    "sg:address":"187 Kirkland Rd",
    "sg:city":"Chehalis",
    "sg:classifiers":[
        {
            "category":"Building & Trades",
            "subcategory":"Construction",
            "type":"Services"
        }
    ],
    "sg:phone":"+1 360 740 1193",
    "sg:postcode":"98532",
    "sg:province":"WA",
    "sg:tags":[
        "grading",
        "contractor"
    ],
    "wof:name":"Public Works Div-Vegetation",
    "wof:placetype":"venue"
},
  "geometry": {"coordinates":[-122.902644,46.605282],"type":"Point"}
}