{
  "type": "Feature",
  "properties": {
    "addr:full":"3665 Stone Way N Seattle WA 98103",
    "addr:housenumber":"3665",
    "addr:postcode":"98103",
    "addr:street":"Stone Way N",
    "iso:country":"US",
    "sg:address":"3665 Stone Way N",
    "sg:city":"Seattle",
    "sg:phone":"+1 206 634 2240",
    "sg:postcode":"98103",
    "sg:province":"WA",
    "sg:website":"http://www.stoneway.com",
    "wof:name":"Stoneway Electric Supply",
    "wof:placetype":"venue"
},
  "geometry": {"coordinates":[-122.342597,47.651934],"type":"Point"}
}