{
  "type": "Feature",
  "properties": {
    "addr:full":"5164 Bounty Loop Freeland WA 98253",
    "addr:housenumber":"5164",
    "addr:postcode":"98253",
    "addr:street":"Bounty Loop",
    "iso:country":"US",
    "sg:address":"5164 Bounty Loop",
    "sg:city":"Freeland",
    "sg:classifiers":[
        {
            "category":"Building & Trades",
            "subcategory":"Construction",
            "type":"Services"
        }
    ],
    "sg:phone":"+1 360 331 3721",
    "sg:postcode":"98253",
    "sg:province":"WA",
    "sg:tags":[
        "restoration",
        "cleaning",
        "patio",
        "deck"
    ],
    "wof:name":"A A Double Pressure Washing",
    "wof:placetype":"venue"
},
  "geometry": {"coordinates":[-122.57086,48.029877],"type":"Point"}
}