{
  "type": "Feature",
  "properties": {
    "addr:full":"403 Maple Ave Ste A Snohomish WA 98290",
    "addr:housenumber":"403",
    "addr:postcode":"98290",
    "addr:street":"Maple Ave Ste A Snohomish",
    "iso:country":"US",
    "sg:address":"403 Maple Ave Ste A",
    "sg:city":"Snohomish",
    "sg:classifiers":[
        {
            "category":"Shopping",
            "subcategory":"Hobbies, Toys, & Games",
            "type":"Retail Goods"
        },
        {
            "category":"Health Services",
            "subcategory":"Medical Lab",
            "type":"Services"
        },
        {
            "category":"Food & Beverages",
            "subcategory":"Farmers Market",
            "type":"Retail Goods"
        }
    ],
    "sg:phone":"+1 360 568 2191",
    "sg:postcode":"98290",
    "sg:province":"WA",
    "sg:tags":[
        "shop",
        "beekeeping",
        "supply",
        "beekeeper",
        "hobby",
        "model"
    ],
    "wof:name":"Beez Neez",
    "wof:placetype":"venue"
},
  "geometry": {"coordinates":[-122.08878300000001,47.91583],"type":"Point"}
}