{
  "type": "Feature",
  "properties": {
    "addr:full":"1700 E Evergreen Blvd Vancouver WA 98661",
    "addr:housenumber":"1700",
    "addr:postcode":"98661",
    "addr:street":"E Evergreen Blvd",
    "iso:country":"US",
    "sg:address":"1700 E Evergreen Blvd",
    "sg:city":"Vancouver",
    "sg:classifiers":[
        {
            "category":"Professional",
            "subcategory":"Management & Consulting",
            "type":"Services"
        }
    ],
    "sg:phone":"+1 360 696 4003",
    "sg:postcode":"98661",
    "sg:province":"WA",
    "sg:tags":[
        "selling",
        "establishment",
        "direct"
    ],
    "wof:name":"Patricia A Running",
    "wof:placetype":"venue"
},
  "geometry": {"coordinates":[-122.653336,45.625917],"type":"Point"}
}