{
  "type": "Feature",
  "properties": {
    "addr:full":"3121 Hanson Rd Ellensburg WA 98926",
    "addr:housenumber":"3121",
    "addr:postcode":"98926",
    "addr:street":"Hanson Rd",
    "iso:country":"US",
    "sg:address":"3121 Hanson Rd",
    "sg:city":"Ellensburg",
    "sg:phone":"+1 509 925 9283",
    "sg:postcode":"98926",
    "sg:province":"WA",
    "sg:tags":[
        "farm",
        "wheat"
    ],
    "wof:name":"Clarence Harrell",
    "wof:placetype":"venue"
},
  "geometry": {"coordinates":[-120.62027500000001,46.985506],"type":"Point"}
}