{
  "type": "Feature",
  "properties": {
    "addr:full":"10013 Shoultes Rd Marysville WA 98270",
    "addr:housenumber":"10013",
    "addr:postcode":"98270",
    "addr:street":"Shoultes Rd",
    "iso:country":"US",
    "sg:address":"10013 Shoultes Rd",
    "sg:city":"Marysville",
    "sg:classifiers":[
        {
            "category":"Utilities",
            "subcategory":"Telephone",
            "type":"Services"
        }
    ],
    "sg:phone":"+1 360 653 6968",
    "sg:postcode":"98270",
    "sg:province":"WA",
    "sg:tags":[
        "communications"
    ],
    "wof:name":"Business Design Network",
    "wof:placetype":"venue"
},
  "geometry": {"coordinates":[-122.17131000000001,48.08595],"type":"Point"}
}