{
  "type": "Feature",
  "properties": {
    "addr:full":"15615 NE 8th St Bellevue WA 98008",
    "addr:housenumber":"15615",
    "addr:postcode":"98008",
    "addr:street":"Ne 8Th St",
    "iso:country":"US",
    "sg:address":"15615 NE 8th St",
    "sg:city":"Bellevue",
    "sg:classifiers":[
        {
            "category":"Autos & Motor Vehicles",
            "subcategory":"Fuel & Gas Station",
            "type":"Retail Goods"
        }
    ],
    "sg:phone":"+1 425 957 0306",
    "sg:postcode":"98008",
    "sg:province":"WA",
    "wof:name":"Union 76",
    "wof:placetype":"venue"
},
  "geometry": {"coordinates":[-122.132254,47.616892],"type":"Point"}
}