{
  "type": "Feature",
  "properties": {
    "addr:full":"2107 Elliott Ave Ste 208 Seattle WA 98121",
    "addr:housenumber":"2107",
    "addr:postcode":"98121",
    "addr:street":"Elliott Ave Ste 208",
    "iso:country":"US",
    "sg:address":"2107 Elliott Ave Ste 208",
    "sg:city":"Seattle",
    "sg:classifiers":[
        {
            "category":"Professional",
            "subcategory":"Art Services",
            "type":"Services"
        }
    ],
    "sg:phone":"+1 206 325 5702",
    "sg:postcode":"98121",
    "sg:province":"WA",
    "sg:tags":[
        "graphic",
        "design"
    ],
    "sg:website":"studiomotif.com",
    "wof:name":"Studio Motif Graphic Design",
    "wof:placetype":"venue"
},
  "geometry": {"coordinates":[-122.345198,47.611174],"type":"Point"}
}