{
  "type": "Feature",
  "properties": {
    "addr:full":"29705 40th Pl S Auburn WA 98001",
    "addr:housenumber":"29705",
    "addr:postcode":"98001",
    "addr:street":"40Th Pl S",
    "iso:country":"US",
    "sg:address":"29705 40th Pl S",
    "sg:city":"Auburn",
    "sg:classifiers":[
        {
            "category":"Professional",
            "subcategory":"Employment Agencies",
            "type":"Services"
        }
    ],
    "sg:phone":"+1 253 839 2840",
    "sg:postcode":"98001",
    "sg:province":"WA",
    "sg:tags":[
        "help",
        "supply"
    ],
    "wof:name":"Office Relief",
    "wof:placetype":"venue"
},
  "geometry": {"coordinates":[-122.283676,47.334906],"type":"Point"}
}