{
  "type": "Feature",
  "properties": {
    "addr:full":"16420 SE McGillivray Blvd Vancouver WA 98683",
    "addr:postcode":"16420;98683",
    "addr:street":"Se Mcgillivray Blvd",
    "iso:country":"US",
    "sg:address":"16420 SE McGillivray Blvd",
    "sg:city":"Vancouver",
    "sg:classifiers":[
        {
            "category":"Personal",
            "subcategory":"Beauty Salon",
            "type":"Services"
        }
    ],
    "sg:phone":"+1 360 944 8648",
    "sg:postcode":"98683",
    "sg:province":"WA",
    "sg:tags":[
        "shop"
    ],
    "wof:name":"Joyce Snogren",
    "wof:placetype":"venue"
},
  "geometry": {"coordinates":[-122.502905,45.604422],"type":"Point"}
}