{
  "type": "Feature",
  "properties": {
    "addr:full":"526 12th St SE Auburn WA 98002",
    "addr:housenumber":"526",
    "addr:postcode":"98002",
    "addr:street":"12Th St Se",
    "iso:country":"US",
    "sg:address":"526 12th St SE",
    "sg:city":"Auburn",
    "sg:classifiers":[
        {
            "category":"Organizations",
            "subcategory":"Religious Organization",
            "type":"Services"
        }
    ],
    "sg:phone":"+1 253 833 2990",
    "sg:postcode":"98002",
    "sg:province":"WA",
    "wof:name":"White River Presbyterian",
    "wof:placetype":"venue"
},
  "geometry": {"coordinates":[-122.22098800000001,47.297193],"type":"Point"}
}