{
  "type": "Feature",
  "properties": {
    "addr:full":"11781 Water Tank Rd Burlington WA 98233",
    "addr:housenumber":"11781",
    "addr:postcode":"98233",
    "addr:street":"Water Tank Rd",
    "iso:country":"US",
    "sg:address":"11781 Water Tank Rd",
    "sg:city":"Burlington",
    "sg:classifiers":[
        {
            "category":"Wholesale",
            "subcategory":"Durable Goods & Equipment",
            "type":"Manufacturing & Wholesale Goods"
        }
    ],
    "sg:phone":"+1 360 757 2047",
    "sg:postcode":"98233",
    "sg:province":"WA",
    "sg:tags":[
        "personal"
    ],
    "wof:name":"Jamaica Me Tan",
    "wof:placetype":"venue"
},
  "geometry": {"coordinates":[-122.413065,48.475002],"type":"Point"}
}