{
  "type": "Feature",
  "properties": {
    "addr:full":"4616 62nd Ave W Tacoma WA 98466",
    "addr:housenumber":"4616",
    "addr:postcode":"98466",
    "addr:street":"62Nd Ave W",
    "iso:country":"US",
    "sg:address":"4616 62nd Ave W",
    "sg:city":"Tacoma",
    "sg:classifiers":[
        {
            "category":"Building & Trades",
            "subcategory":"Construction",
            "type":"Services"
        }
    ],
    "sg:phone":"+1 253 566 8012",
    "sg:postcode":"98466",
    "sg:province":"WA",
    "sg:tags":[
        "general",
        "contractor"
    ],
    "wof:name":"Butler's Handyman Construction",
    "wof:placetype":"venue"
},
  "geometry": {"coordinates":[-122.52046799999999,47.214903],"type":"Point"}
}