{
  "type": "Feature",
  "properties": {
    "iso:country":"US",
    "sg:address":"8725 126th Ave NE",
    "sg:city":"Kirkland",
    "sg:classifiers":[
        {
            "category":"Building & Trades",
            "subcategory":"Construction",
            "type":"Services"
        }
    ],
    "sg:phone":"+1 425 822 9880",
    "sg:postcode":"98033",
    "sg:province":"WA",
    "sg:tags":[
        "hanging",
        "contractor"
    ],
    "wof:name":"Masters Painters",
    "wof:placetype":"venue"
},
  "geometry": {"coordinates":[-122.172889,47.681315],"type":"Point"}
}