{
  "type": "Feature",
  "properties": {
    "addr:full":"5421 Sunnyside Blvd Marysville WA 98270",
    "addr:housenumber":"5421",
    "addr:postcode":"98270",
    "addr:street":"Sunnyside Blvd",
    "iso:country":"US",
    "sg:address":"5421 Sunnyside Blvd",
    "sg:city":"Marysville",
    "sg:classifiers":[
        {
            "category":"Professional",
            "type":"Services"
        }
    ],
    "sg:phone":"+1 425 697 7113",
    "sg:postcode":"98270",
    "sg:province":"WA",
    "wof:name":"American Structures",
    "wof:placetype":"venue"
},
  "geometry": {"coordinates":[-122.147457,48.045475],"type":"Point"}
}