{
  "type": "Feature",
  "properties": {
    "iso:country":"US",
    "sg:address":"1560 SE 9th Ave",
    "sg:city":"Oak Harbor",
    "sg:classifiers":[
        {
            "category":"Organizations",
            "subcategory":"Religious Organization",
            "type":"Services"
        }
    ],
    "sg:phone":"+1 360 679 6959",
    "sg:postcode":"98277",
    "sg:province":"WA",
    "wof:name":"Calvary Chapel Of Oak Harbor",
    "wof:placetype":"venue"
},
  "geometry": {"coordinates":[-122.640889,48.290825],"type":"Point"}
}