{
  "type": "Feature",
  "properties": {
    "addr:full":"10513 Silverdale Way NW # 8 Silverdale WA 98383",
    "addr:housenumber":"10513",
    "addr:postcode":"98383",
    "addr:street":"Silverdale Way Nw #",
    "iso:country":"US",
    "sg:address":"10513 Silverdale Way NW # 8",
    "sg:city":"Silverdale",
    "sg:classifiers":[
        {
            "category":"Health Services",
            "subcategory":"Doctor",
            "type":"Services"
        },
        {
            "category":"Health Services",
            "subcategory":"Clinic",
            "type":"Services"
        }
    ],
    "sg:phone":"+1 360 662 0256",
    "sg:postcode":"98383",
    "sg:province":"WA",
    "sg:tags":[
        "physician",
        "family",
        "practice",
        "surgeons",
        "osteopathic",
        "medicine"
    ],
    "wof:name":"William E Minteer",
    "wof:placetype":"venue"
},
  "geometry": {"coordinates":[-122.68651800000001,47.65861],"type":"Point"}
}