{
  "type": "Feature",
  "properties": {
    "addr:full":"11546 15th Ave NE Seattle WA 98125",
    "addr:housenumber":"11546",
    "addr:postcode":"98125",
    "addr:street":"15Th Ave Ne",
    "iso:country":"US",
    "sg:address":"11546 15th Ave NE",
    "sg:city":"Seattle",
    "sg:classifiers":[
        {
            "category":"Restaurant",
            "type":"Food & Drink"
        }
    ],
    "sg:phone":"+1 206 362 4901",
    "sg:postcode":"98125",
    "sg:province":"WA",
    "sg:tags":[
        "ethiopian"
    ],
    "wof:name":"Enat Ethiopian Restaurant",
    "wof:placetype":"venue"
},
  "geometry": {"coordinates":[-122.31199599999999,47.712898],"type":"Point"}
}