{
  "type": "Feature",
  "properties": {
    "addr:full":"15221 Aurora Ave N Seattle WA 98133",
    "addr:housenumber":"15221",
    "addr:postcode":"98133",
    "addr:street":"Aurora Ave N",
    "iso:country":"US",
    "sg:address":"15221 Aurora Ave N",
    "sg:city":"Seattle",
    "sg:classifiers":[
        {
            "category":"Restaurant",
            "type":"Food & Drink"
        }
    ],
    "sg:phone":"+1 206 365 1018",
    "sg:postcode":"98133",
    "sg:province":"WA",
    "sg:tags":[
        "eating"
    ],
    "wof:name":"U Grill Inc",
    "wof:placetype":"venue"
},
  "geometry": {"coordinates":[-122.345342,47.740121],"type":"Point"}
}