{
  "type": "Feature",
  "properties": {
    "addr:full":"1118 Iler Ln Yakima WA 98901",
    "addr:housenumber":"1118",
    "addr:postcode":"98901",
    "addr:street":"Iler Ln",
    "iso:country":"US",
    "sg:address":"1118 Iler Ln",
    "sg:city":"Yakima",
    "sg:classifiers":[
        {
            "category":"Retail",
            "subcategory":"Auto Repair",
            "type":"Services"
        }
    ],
    "sg:phone":"+1 509 457 4690",
    "sg:postcode":"98901",
    "sg:province":"WA",
    "sg:tags":[
        "wrecker"
    ],
    "wof:name":"Hinds Towing",
    "wof:placetype":"venue"
},
  "geometry": {"coordinates":[-120.484669,46.57948],"type":"Point"}
}