{
  "type": "Feature",
  "properties": {
    "addr:full":"1445 Elliott Avenue W Seattle WA 98119",
    "addr:housenumber":"1445",
    "addr:postcode":"98119",
    "addr:street":"Elliott Avenue W",
    "iso:country":"US",
    "sg:address":"1445 Elliott Avenue W",
    "sg:city":"Seattle",
    "sg:classifiers":[
        {
            "category":"Winery",
            "type":"Food & Drink"
        }
    ],
    "sg:phone":"+1 206 284 2635",
    "sg:postcode":"98119",
    "sg:province":"WA",
    "sg:website":"www.wardjohnsonwinery.com/",
    "wof:name":"Ward Johnson Winery",
    "wof:placetype":"venue"
},
  "geometry": {"coordinates":[-122.374464,47.631319],"type":"Point"}
}