{
  "type": "Feature",
  "properties": {
    "addr:full":"23022 172nd Ave SE Kent WA 98042",
    "addr:housenumber":"23022",
    "addr:postcode":"98042",
    "addr:street":"172Nd Ave Se",
    "iso:country":"US",
    "sg:address":"23022 172nd Ave SE",
    "sg:city":"Kent",
    "sg:classifiers":[
        {
            "category":"Farming",
            "subcategory":"Farm & Veterinary Services",
            "type":"Manufacturing & Wholesale Goods"
        }
    ],
    "sg:phone":"+1 253 631 3172",
    "sg:postcode":"98042",
    "sg:province":"WA",
    "sg:tags":[
        "livestock"
    ],
    "wof:name":"Linds Mobile Frm Slaughtering",
    "wof:placetype":"venue"
},
  "geometry": {"coordinates":[-122.112139,47.395848],"type":"Point"}
}