{
  "type": "Feature",
  "properties": {
    "addr:full":"91 NE Midway Blvd Oak Harbor WA 98277",
    "addr:housenumber":"91",
    "addr:postcode":"98277",
    "addr:street":"Ne Midway Blvd",
    "iso:country":"US",
    "sg:address":"91 NE Midway Blvd",
    "sg:city":"Oak Harbor",
    "sg:classifiers":[
        {
            "category":"Shopping",
            "subcategory":"Florist",
            "type":"Retail Goods"
        }
    ],
    "sg:phone":"+1 360 679 2525",
    "sg:postcode":"98277",
    "sg:province":"WA",
    "sg:website":"www.midwayflorist.com",
    "wof:name":"Midway Florist Inc",
    "wof:placetype":"venue"
},
  "geometry": {"coordinates":[-122.643327,48.300598],"type":"Point"}
}