{
  "type": "Feature",
  "properties": {
    "addr:full":"309 2nd St SE Ste 100 Auburn WA 98002",
    "addr:housenumber":"309",
    "addr:postcode":"98002",
    "addr:street":"2Nd St Se Ste 100",
    "iso:country":"US",
    "sg:address":"309 2nd St SE Ste 100",
    "sg:city":"Auburn",
    "sg:classifiers":[
        {
            "category":"Health Services",
            "subcategory":"Dentist",
            "type":"Services"
        }
    ],
    "sg:phone":"+1 253 833 9066",
    "sg:postcode":"98002",
    "sg:province":"WA",
    "wof:name":"Sabbagh Emily M",
    "wof:placetype":"venue"
},
  "geometry": {"coordinates":[-122.225593,47.305735],"type":"Point"}
}