{
  "type": "Feature",
  "properties": {
    "addr:full":"6208 125th Ave SE Bellevue WA 98006",
    "addr:housenumber":"6208",
    "addr:postcode":"98006",
    "addr:street":"125Th Ave Se",
    "iso:country":"US",
    "sg:address":"6208 125th Ave SE",
    "sg:city":"Bellevue",
    "sg:classifiers":[
        {
            "category":"Communications",
            "subcategory":"Film & Video Production",
            "type":"Services"
        }
    ],
    "sg:phone":"+1 425 373 5999",
    "sg:postcode":"98006",
    "sg:province":"WA",
    "sg:tags":[
        "motion",
        "tv",
        "radio",
        "companies-film"
    ],
    "wof:name":"Classical Music Visuals, Ltd",
    "wof:placetype":"venue"
},
  "geometry": {"coordinates":[-122.17418000000001,47.547238],"type":"Point"}
}