{
  "type": "Feature",
  "properties": {
    "addr:full":"3202 Armstrong Ln NE Bremerton WA 98310",
    "addr:housenumber":"3202",
    "addr:postcode":"98310",
    "addr:street":"Armstrong Ln Ne",
    "iso:country":"US",
    "sg:address":"3202 Armstrong Ln NE",
    "sg:city":"Bremerton",
    "sg:classifiers":[
        {
            "category":"Utilities",
            "subcategory":"Telephone",
            "type":"Services"
        }
    ],
    "sg:phone":"+1 360 377 7912",
    "sg:postcode":"98310",
    "sg:province":"WA",
    "sg:tags":[
        "telecommunication"
    ],
    "wof:name":"Telecommunications Enterprises",
    "wof:placetype":"venue"
},
  "geometry": {"coordinates":[-122.603961,47.595099],"type":"Point"}
}