{
  "type": "Feature",
  "properties": {
    "addr:full":"3111 SE 192nd Ave Vancouver WA 98683",
    "addr:housenumber":"3111",
    "addr:postcode":"98683",
    "addr:street":"Se 192Nd Ave",
    "iso:country":"US",
    "sg:address":"3111 SE 192nd Ave",
    "sg:city":"Vancouver",
    "sg:classifiers":[
        {
            "category":"Social Services",
            "subcategory":"Child Care",
            "type":"Services"
        },
        {
            "category":"Education",
            "subcategory":"Preschool",
            "type":"Public Place"
        }
    ],
    "sg:phone":"+1 360 253 2988",
    "sg:postcode":"98683",
    "sg:province":"WA",
    "sg:tags":[
        "kindergarten",
        "nursery",
        "day"
    ],
    "sg:website":"www.goddardschools.com",
    "wof:name":"The Goddard School",
    "wof:placetype":"venue"
},
  "geometry": {"coordinates":[-122.47805200000001,45.598368],"type":"Point"}
}