{
  "type": "Feature",
  "properties": {
    "addr:full":"627 E Francis Ave Spokane WA 99208",
    "addr:housenumber":"627",
    "addr:postcode":"99208",
    "addr:street":"E Francis Ave",
    "iso:country":"US",
    "sg:address":"627 E Francis Ave",
    "sg:city":"Spokane",
    "sg:classifiers":[
        {
            "category":"Personal",
            "type":"Services"
        }
    ],
    "sg:phone":"+1 509 487 0007",
    "sg:postcode":"99208",
    "sg:province":"WA",
    "sg:tags":[
        "towing"
    ],
    "sg:website":"http://www.nelsonsautobody.com",
    "wof:name":"Nelson's Auto Repair-Towing-Auto Body",
    "wof:placetype":"venue"
},
  "geometry": {"coordinates":[-117.400278,47.715107],"type":"Point"}
}