{
  "type": "Feature",
  "properties": {
    "iso:country":"US",
    "sg:address":"4476 W Van Giesen St",
    "sg:city":"Richland",
    "sg:classifiers":[
        {
            "category":"Health Services",
            "subcategory":"Doctor",
            "type":"Services"
        }
    ],
    "sg:phone":"+1 509 967 3421",
    "sg:postcode":"99353",
    "sg:province":"WA",
    "sg:tags":[
        "dentist"
    ],
    "wof:name":"West Richland Family Dntl Ctr",
    "wof:placetype":"venue"
},
  "geometry": {"coordinates":[-119.346317,46.300264],"type":"Point"}
}