{
  "type": "Feature",
  "properties": {
    "addr:full":"3510 NE 53rd St Vancouver WA 98661",
    "addr:housenumber":"3510",
    "addr:postcode":"98661",
    "addr:street":"Ne 53Rd St",
    "iso:country":"US",
    "sg:address":"3510 NE 53rd St",
    "sg:city":"Vancouver",
    "sg:classifiers":[
        {
            "category":"Building & Trades",
            "subcategory":"Construction",
            "type":"Services"
        }
    ],
    "sg:phone":"+1 360 695 5649",
    "sg:postcode":"98661",
    "sg:province":"WA",
    "sg:tags":[
        "concrete",
        "contractor"
    ],
    "wof:name":"Roy's Construction",
    "wof:placetype":"venue"
},
  "geometry": {"coordinates":[-122.63285399999999,45.660713],"type":"Point"}
}