{
  "type": "Feature",
  "properties": {
    "addr:full":"161 Ave de Oro Friday Harbor WA 98250",
    "addr:housenumber":"161",
    "addr:postcode":"98250",
    "addr:street":"Ave De Oro",
    "iso:country":"US",
    "sg:address":"161 Ave de Oro",
    "sg:city":"Friday Harbor",
    "sg:classifiers":[
        {
            "category":"Restaurant",
            "type":"Food & Drink"
        }
    ],
    "sg:phone":"+1 360 378 3288",
    "sg:postcode":"98250",
    "sg:province":"WA",
    "sg:tags":[
        "eating"
    ],
    "wof:name":"Shin Taco",
    "wof:placetype":"venue"
},
  "geometry": {"coordinates":[-123.077022,48.591378],"type":"Point"}
}