{
  "type": "Feature",
  "properties": {
    "addr:full":"437 29th St NE Puyallup WA 98372",
    "addr:housenumber":"437",
    "addr:postcode":"98372",
    "addr:street":"29Th St Ne",
    "iso:country":"US",
    "sg:address":"437 29th St NE",
    "sg:city":"Puyallup",
    "sg:classifiers":[
        {
            "category":"Banks & Credit Unions",
            "subcategory":"Bank",
            "type":"Services"
        }
    ],
    "sg:phone":"+1 253 604 4715",
    "sg:postcode":"98372",
    "sg:province":"WA",
    "sg:tags":[
        "saving",
        "commercial"
    ],
    "wof:name":"Buffalo Federal Saving Bank",
    "wof:placetype":"venue"
},
  "geometry": {"coordinates":[-122.255223,47.19418],"type":"Point"}
}