{
  "type": "Feature",
  "properties": {
    "addr:full":"85 S Atlantic St Ste 104 Seattle WA 98134",
    "addr:housenumber":"85",
    "addr:postcode":"98134",
    "addr:street":"S Atlantic St Ste 104",
    "iso:country":"US",
    "sg:address":"85 S Atlantic St Ste 104",
    "sg:city":"Seattle",
    "sg:classifiers":[
        {
            "category":"Organizations",
            "subcategory":"Community Association",
            "type":"Services"
        }
    ],
    "sg:phone":"+1 206 262 9830",
    "sg:postcode":"98134",
    "sg:province":"WA",
    "sg:tags":[
        "program",
        "incentive"
    ],
    "sg:website":"http://www.foodexp.com",
    "wof:name":"Food Express Inc.",
    "wof:placetype":"venue"
},
  "geometry": {"coordinates":[-122.335335,47.590328],"type":"Point"}
}