{
  "type": "Feature",
  "properties": {
    "iso:country":"US",
    "sg:address":"21112 72nd Ave S",
    "sg:city":"Kent",
    "sg:classifiers":[
        {
            "category":"Manufacturing",
            "subcategory":"Tools & Machinery",
            "type":"Manufacturing & Wholesale Goods"
        }
    ],
    "sg:phone":"+1 253 872 2180",
    "sg:postcode":"98032",
    "sg:province":"WA",
    "sg:tags":[
        "food",
        "equipment",
        "product",
        "commercial",
        "mfg"
    ],
    "wof:name":"Lucks Food Equipment Company",
    "wof:placetype":"venue"
},
  "geometry": {"coordinates":[-122.244004,47.412933],"type":"Point"}
}