{
  "type": "Feature",
  "properties": {
    "addr:full":"1341 5th Ave Seattle WA 98101",
    "addr:housenumber":"1341",
    "addr:postcode":"98101",
    "addr:street":"5Th Ave",
    "iso:country":"US",
    "sg:address":"1341 5th Ave",
    "sg:city":"Seattle",
    "sg:classifiers":[
        {
            "category":"Shopping",
            "subcategory":"Jewelry",
            "type":"Retail Goods"
        }
    ],
    "sg:phone":"+1 206 623 2528",
    "sg:postcode":"98101",
    "sg:province":"WA",
    "sg:tags":[
        "diamond",
        "watch",
        "jeweler"
    ],
    "sg:website":"http://seattle.citysearch.com/profile/external/10767642/seattle_wa/fox_s_gem_shop.html?publisher=yellowpages&reference_id=1&placement=ypwebsitemip",
    "wof:name":"Fox's Gem Shop",
    "wof:placetype":"venue"
},
  "geometry": {"coordinates":[-122.334999,47.609402],"type":"Point"}
}