{
  "type": "Feature",
  "properties": {
    "addr:full":"7520 28th St W University Place WA 98466",
    "addr:housenumber":"7520",
    "addr:postcode":"98466",
    "addr:street":"28Th St W;Place",
    "iso:country":"US",
    "sg:address":"7520 28th St W",
    "sg:city":"University Place",
    "sg:classifiers":[
        {
            "category":"Personal",
            "subcategory":"Beauty Salon",
            "type":"Services"
        }
    ],
    "sg:phone":"+1 253 565 0319",
    "sg:postcode":"98466",
    "sg:province":"WA",
    "wof:name":"That's Just Doozie",
    "wof:placetype":"venue"
},
  "geometry": {"coordinates":[-122.538768,47.234444],"type":"Point"}
}