{
  "type": "Feature",
  "properties": {
    "addr:full":"4056 45th Ave SW Seattle WA 98116",
    "addr:housenumber":"4056",
    "addr:postcode":"98116",
    "addr:street":"45Th Ave Sw",
    "iso:country":"US",
    "sg:address":"4056 45th Ave SW",
    "sg:city":"Seattle",
    "sg:classifiers":[
        {
            "category":"Professional",
            "type":"Services"
        }
    ],
    "sg:phone":"+1 206 937 6225",
    "sg:postcode":"98116",
    "sg:province":"WA",
    "wof:name":"Willem C Buys Services",
    "wof:placetype":"venue"
},
  "geometry": {"coordinates":[-122.389371,47.567647],"type":"Point"}
}