{
  "type": "Feature",
  "properties": {
    "addr:full":"342 NW 84th St Seattle WA 98117",
    "addr:housenumber":"342",
    "addr:postcode":"98117",
    "addr:street":"Nw 84Th St",
    "iso:country":"US",
    "sg:address":"342 NW 84th St",
    "sg:city":"Seattle",
    "sg:classifiers":[
        {
            "category":"Shopping",
            "subcategory":"Department Store",
            "type":"Retail Goods"
        }
    ],
    "sg:phone":"+1 206 841 7693",
    "sg:postcode":"98117",
    "sg:province":"WA",
    "sg:tags":[
        "variety"
    ],
    "wof:name":"Five Dollar Cover Seattle",
    "wof:placetype":"venue"
},
  "geometry": {"coordinates":[-122.361789,47.68985],"type":"Point"}
}