{
  "type": "Feature",
  "properties": {
    "addr:full":"18717 Westside Hwy SW Vashon WA 98070",
    "addr:housenumber":"18717",
    "addr:postcode":"98070",
    "addr:street":"Westside Hwy Sw",
    "iso:country":"US",
    "sg:address":"18717 Westside Hwy SW",
    "sg:city":"Vashon",
    "sg:classifiers":[
        {
            "category":"Professional",
            "subcategory":"Detective & Security Services",
            "type":"Services"
        }
    ],
    "sg:phone":"+1 206 354 2069",
    "sg:postcode":"98070",
    "sg:province":"WA",
    "sg:tags":[
        "information",
        "bureau"
    ],
    "wof:name":"Brookline Home Services",
    "wof:placetype":"venue"
},
  "geometry": {"coordinates":[-122.50273799999999,47.438206],"type":"Point"}
}