{
  "type": "Feature",
  "properties": {
    "addr:full":"4810 Yelm Hwy SE Olympia WA 98503",
    "addr:housenumber":"4810",
    "addr:postcode":"98503",
    "addr:street":"Yelm Hwy Se",
    "iso:country":"US",
    "sg:address":"4810 Yelm Hwy SE",
    "sg:city":"Olympia",
    "sg:classifiers":[
        {
            "category":"Banks & Credit Unions",
            "subcategory":"Investment Brokerage",
            "type":"Services"
        }
    ],
    "sg:phone":"+1 360 486 0370",
    "sg:postcode":"98503",
    "sg:province":"WA",
    "sg:tags":[
        "security"
    ],
    "wof:name":"Edward Jones Co",
    "wof:placetype":"venue"
},
  "geometry": {"coordinates":[-122.82316899999999,46.996238],"type":"Point"}
}