{
  "type": "Feature",
  "properties": {
    "addr:full":"1558 N Suko Rd Ritzville WA 99169",
    "addr:housenumber":"1558",
    "addr:postcode":"99169",
    "addr:street":"N Suko Rd",
    "iso:country":"US",
    "sg:address":"1558 N Suko Rd",
    "sg:city":"Ritzville",
    "sg:classifiers":[
        {
            "category":"Farming",
            "subcategory":"Farm",
            "type":"Manufacturing & Wholesale Goods"
        }
    ],
    "sg:phone":"+1 509 659 1239",
    "sg:postcode":"99169",
    "sg:province":"WA",
    "sg:tags":[
        "crop",
        "general"
    ],
    "wof:name":"Kiesz Farms Inc",
    "wof:placetype":"venue"
},
  "geometry": {"coordinates":[-118.408828,47.140949],"type":"Point"}
}