{
  "type": "Feature",
  "properties": {
    "addr:full":"1046 1st Ave S Seattle WA 98134",
    "addr:housenumber":"1046",
    "addr:postcode":"98134",
    "addr:street":"1St Ave S",
    "iso:country":"US",
    "sg:address":"1046 1st Ave S",
    "sg:city":"Seattle",
    "sg:classifiers":[
        {
            "category":"Autos & Motor Vehicles",
            "subcategory":"Fuel & Gas Station",
            "type":"Retail Goods"
        }
    ],
    "sg:phone":"+1 206 682 1147",
    "sg:postcode":"98134",
    "sg:province":"WA",
    "sg:tags":[
        "station",
        "gasoline"
    ],
    "wof:name":"Stadium Markets",
    "wof:placetype":"venue"
},
  "geometry": {"coordinates":[-122.33412,47.593941],"type":"Point"}
}