{
  "type": "Feature",
  "properties": {
    "addr:full":"3118 N Gove St Tacoma WA 98407",
    "addr:housenumber":"3118",
    "addr:postcode":"98407",
    "addr:street":"N Gove St",
    "iso:country":"US",
    "sg:address":"3118 N Gove St",
    "sg:city":"Tacoma",
    "sg:classifiers":[
        {
            "category":"Professional",
            "subcategory":"Computer Services",
            "type":"Services"
        }
    ],
    "sg:phone":"+1 253 759 0688",
    "sg:postcode":"98407",
    "sg:province":"WA",
    "sg:tags":[
        "related"
    ],
    "wof:name":"Desktop Computer Services",
    "wof:placetype":"venue"
},
  "geometry": {"coordinates":[-122.49993600000001,47.277591],"type":"Point"}
}