{
  "type": "Feature",
  "properties": {
    "addr:full":"1101 Oxford Ave Richland WA 99352",
    "addr:housenumber":"1101",
    "addr:postcode":"99352",
    "addr:street":"Oxford Ave",
    "iso:country":"US",
    "sg:address":"1101 Oxford Ave",
    "sg:city":"Richland",
    "sg:classifiers":[
        {
            "category":"Professional",
            "subcategory":"Engineering",
            "type":"Services"
        }
    ],
    "sg:phone":"+1 509 627 2709",
    "sg:postcode":"99352",
    "sg:province":"WA",
    "wof:name":"Renato S Mercado",
    "wof:placetype":"venue"
},
  "geometry": {"coordinates":[-119.26118,46.239977],"type":"Point"}
}