{
  "type": "Feature",
  "properties": {
    "addr:full":"800 E Providence Ave Spokane WA 99207",
    "addr:housenumber":"800",
    "addr:postcode":"99207",
    "addr:street":"E Providence Ave",
    "iso:country":"US",
    "sg:address":"800 E Providence Ave",
    "sg:city":"Spokane",
    "sg:classifiers":[
        {
            "category":"Education",
            "subcategory":"School",
            "type":"Public Place"
        }
    ],
    "sg:phone":"+1 509 354 3556",
    "sg:postcode":"99207",
    "sg:province":"WA",
    "wof:name":"Spokane Public Sch Dist 81 Exp",
    "wof:placetype":"venue"
},
  "geometry": {"coordinates":[-117.397858,47.692322],"type":"Point"}
}