{
  "type": "Feature",
  "properties": {
    "addr:full":"7216 5th Ave NW Seattle WA 98117",
    "addr:housenumber":"7216",
    "addr:postcode":"98117",
    "addr:street":"5Th Ave Nw",
    "iso:country":"US",
    "sg:address":"7216 5th Ave NW",
    "sg:city":"Seattle",
    "sg:classifiers":[
        {
            "category":"Shopping",
            "subcategory":"Discount & Variety Stores",
            "type":"Retail Goods"
        }
    ],
    "sg:phone":"+1 206 781 0168",
    "sg:postcode":"98117",
    "sg:province":"WA",
    "sg:tags":[
        "merchandise",
        "general"
    ],
    "sg:website":"www.akettlecorn.com",
    "wof:name":"Amareka Kettle Corn",
    "wof:placetype":"venue"
},
  "geometry": {"coordinates":[-122.362415,47.681611],"type":"Point"}
}