{
  "type": "Feature",
  "properties": {
    "addr:full":"1202 Auburn Way S Auburn WA 98002",
    "addr:housenumber":"1202",
    "addr:postcode":"98002",
    "addr:street":"Auburn Way S",
    "iso:country":"US",
    "sg:address":"1202 Auburn Way S",
    "sg:city":"Auburn",
    "sg:classifiers":[
        {
            "category":"Travel",
            "subcategory":"Hotels & Motels",
            "type":"Entertainment"
        }
    ],
    "sg:phone":"+1 253 833 7470",
    "sg:postcode":"98002",
    "sg:province":"WA",
    "sg:tags":[
        "lodging"
    ],
    "wof:name":"Auburn Motel",
    "wof:placetype":"venue"
},
  "geometry": {"coordinates":[-122.217669,47.297284],"type":"Point"}
}