{
  "type": "Feature",
  "properties": {
    "addr:full":"112 N University Rd Spokane Valley WA 99206",
    "addr:housenumber":"112",
    "addr:postcode":"99206",
    "addr:street":"N University Rd",
    "iso:country":"US",
    "sg:address":"112 N University Rd",
    "sg:city":"Spokane Valley",
    "sg:classifiers":[
        {
            "category":"Professional",
            "subcategory":"Accounting & Tax Preparation",
            "type":"Services"
        }
    ],
    "sg:phone":"+1 509 922 4994",
    "sg:postcode":"99206",
    "sg:province":"WA",
    "sg:tags":[
        "accountant"
    ],
    "wof:name":"Kent J Berreth",
    "wof:placetype":"venue"
},
  "geometry": {"coordinates":[-117.261261,47.657294],"type":"Point"}
}