{
  "type": "Feature",
  "properties": {
    "addr:full":"1318 S Canyon Rd Ellensburg WA 98926",
    "addr:housenumber":"1318",
    "addr:postcode":"98926",
    "addr:street":"S Canyon Rd",
    "iso:country":"US",
    "sg:address":"1318 S Canyon Rd",
    "sg:city":"Ellensburg",
    "sg:phone":"+1 509 925 7898",
    "sg:postcode":"98926",
    "sg:province":"WA",
    "wof:name":"Los Cabos",
    "wof:placetype":"venue"
},
  "geometry": {"coordinates":[-120.54470000000001,46.979643],"type":"Point"}
}