{
  "type": "Feature",
  "properties": {
    "addr:full":"1122 E Pike St Ste 1290 Seattle WA 98122",
    "addr:housenumber":"1122",
    "addr:postcode":"98122",
    "addr:street":"E Pike St Ste 1290",
    "iso:country":"US",
    "sg:address":"1122 E Pike St Ste 1290",
    "sg:city":"Seattle",
    "sg:classifiers":[
        {
            "category":"Banks & Credit Unions",
            "subcategory":"Investment Brokerage",
            "type":"Services"
        }
    ],
    "sg:phone":"+1 206 736 5235",
    "sg:postcode":"98122",
    "sg:province":"WA",
    "wof:name":"Reign Capital Management",
    "wof:placetype":"venue"
},
  "geometry": {"coordinates":[-122.31783900000001,47.614094],"type":"Point"}
}