{
  "type": "Feature",
  "properties": {
    "addr:full":"5111 E Russell Rd Colbert WA 99005",
    "addr:housenumber":"5111",
    "addr:postcode":"99005",
    "addr:street":"E Russell Rd Colbert",
    "iso:country":"US",
    "sg:address":"5111 E Russell Rd",
    "sg:city":"Colbert",
    "sg:classifiers":[
        {
            "category":"Building & Trades",
            "subcategory":"Construction",
            "type":"Services"
        }
    ],
    "sg:phone":"+1 509 238 6232",
    "sg:postcode":"99005",
    "sg:province":"WA",
    "sg:tags":[
        "contractor"
    ],
    "wof:name":"Kitchen World",
    "wof:placetype":"venue"
},
  "geometry": {"coordinates":[-117.337827,47.869431],"type":"Point"}
}