{
  "type": "Feature",
  "properties": {
    "addr:full":"1519 NE 50th St Seattle WA 98105",
    "addr:housenumber":"1519",
    "addr:postcode":"98105",
    "addr:street":"Ne 50Th St",
    "iso:country":"US",
    "sg:address":"1519 NE 50th St",
    "sg:city":"Seattle",
    "sg:classifiers":[
        {
            "category":"Real Estate",
            "subcategory":"Real Estate Operator",
            "type":"Services"
        }
    ],
    "sg:phone":"+1 206 525 9444",
    "sg:postcode":"98105",
    "sg:province":"WA",
    "sg:tags":[
        "building",
        "apartment"
    ],
    "wof:name":"Royal Manor Apartments",
    "wof:placetype":"venue"
},
  "geometry": {"coordinates":[-122.31094400000001,47.664809],"type":"Point"}
}