{
  "type": "Feature",
  "properties": {
    "addr:full":"12215 79th Ave S Seattle WA 98178",
    "addr:housenumber":"12215",
    "addr:postcode":"98178",
    "addr:street":"79Th Ave S",
    "iso:country":"US",
    "sg:address":"12215 79th Ave S",
    "sg:city":"Seattle",
    "sg:classifiers":[
        {
            "category":"Health Services",
            "subcategory":"Clinic",
            "type":"Services"
        }
    ],
    "sg:phone":"+1 206 772 8940",
    "sg:postcode":"98178",
    "sg:province":"WA",
    "sg:tags":[
        "home",
        "care"
    ],
    "wof:name":"Carols Home Care",
    "wof:placetype":"venue"
},
  "geometry": {"coordinates":[-122.234511,47.492752],"type":"Point"}
}