{
  "type": "Feature",
  "properties": {
    "addr:full":"637 N Keller Ave East Wenatchee WA 98802",
    "addr:housenumber":"637",
    "addr:postcode":"98802",
    "addr:street":"N Keller Ave",
    "iso:country":"US",
    "sg:address":"637 N Keller Ave",
    "sg:city":"East Wenatchee",
    "sg:classifiers":[
        {
            "category":"Building & Trades",
            "subcategory":"Construction",
            "type":"Services"
        }
    ],
    "sg:phone":"+1 509 884 3784",
    "sg:postcode":"98802",
    "sg:province":"WA",
    "sg:tags":[
        "general",
        "contractor"
    ],
    "wof:name":"Da Va Construction",
    "wof:placetype":"venue"
},
  "geometry": {"coordinates":[-120.26214299999999,47.414742],"type":"Point"}
}