{
  "type": "Feature",
  "properties": {
    "addr:full":"2007 92nd Ave E Puyallup WA 98371",
    "addr:housenumber":"2007",
    "addr:postcode":"98371",
    "addr:street":"92Nd Ave E",
    "iso:country":"US",
    "sg:address":"2007 92nd Ave E",
    "sg:city":"Puyallup",
    "sg:classifiers":[
        {
            "category":"Building & Trades",
            "subcategory":"Construction",
            "type":"Services"
        }
    ],
    "sg:phone":"+1 253 350 7040",
    "sg:postcode":"98371",
    "sg:province":"WA",
    "sg:tags":[
        "residential",
        "general",
        "contractor"
    ],
    "wof:name":"MRC Construction",
    "wof:placetype":"venue"
},
  "geometry": {"coordinates":[-122.307097,47.238727],"type":"Point"}
}