{
  "type": "Feature",
  "properties": {
    "addr:full":"1020 Sehome Ave Bellingham WA 98229",
    "addr:housenumber":"1020",
    "addr:postcode":"98229",
    "addr:street":"Sehome Ave",
    "iso:country":"US",
    "sg:address":"1020 Sehome Ave",
    "sg:city":"Bellingham",
    "sg:classifiers":[
        {
            "category":"Manufacturing",
            "subcategory":"Chemicals & Compounds",
            "type":"Manufacturing & Wholesale Goods"
        }
    ],
    "sg:phone":"+1 360 738 8121",
    "sg:postcode":"98229",
    "sg:province":"WA",
    "sg:tags":[
        "preparation",
        "mfg"
    ],
    "wof:name":"Sweet Earth Grdn & Essentials",
    "wof:placetype":"venue"
},
  "geometry": {"coordinates":[-122.44225299999999,48.709736],"type":"Point"}
}