{
  "type": "Feature",
  "properties": {
    "addr:full":"PO Box 820729 Vancouver WA 98682",
    "addr:housenumber":"po",
    "addr:postcode":"98682",
    "addr:street":"Box 820729",
    "iso:country":"US",
    "sg:address":"PO Box 820729",
    "sg:city":"Vancouver",
    "sg:classifiers":[
        {
            "category":"Building & Trades",
            "subcategory":"Cleaning & Sanitation",
            "type":"Services"
        }
    ],
    "sg:phone":"+1 360 256 9250",
    "sg:postcode":"98682",
    "sg:province":"WA",
    "sg:tags":[
        "carpet"
    ],
    "wof:name":"Clean-World Maintenance",
    "wof:placetype":"venue"
},
  "geometry": {"coordinates":[-122.51300000000001,45.668098],"type":"Point"}
}