{
  "type": "Feature",
  "properties": {
    "iso:country":"US",
    "sg:address":"7125 E Trent Ave",
    "sg:city":"Spokane Valley",
    "sg:classifiers":[
        {
            "category":"Shopping",
            "subcategory":"Crafts & Fabrics",
            "type":"Retail Goods"
        }
    ],
    "sg:phone":"+1 509 924 9004",
    "sg:postcode":"99212",
    "sg:province":"WA",
    "sg:tags":[
        "shop"
    ],
    "sg:website":"www.sewingstudio.com",
    "wof:name":"Sewing Studio",
    "wof:placetype":"venue"
},
  "geometry": {"coordinates":[-117.30804999999999,47.676047],"type":"Point"}
}