{
  "type": "Feature",
  "properties": {
    "addr:full":"2556 Jackson Hwy Chehalis WA 98532",
    "addr:housenumber":"2556",
    "addr:postcode":"98532",
    "addr:street":"Jackson Hwy",
    "iso:country":"US",
    "sg:address":"2556 Jackson Hwy",
    "sg:city":"Chehalis",
    "sg:classifiers":[
        {
            "category":"Professional",
            "subcategory":"Business Services",
            "type":"Services"
        }
    ],
    "sg:phone":"+1 360 748 6393",
    "sg:postcode":"98532",
    "sg:province":"WA",
    "sg:tags":[
        "water",
        "treatment"
    ],
    "sg:website":"www.waterdocs.com",
    "wof:name":"Water Doctor Of Washington",
    "wof:placetype":"venue"
},
  "geometry": {"coordinates":[-122.925673,46.637352],"type":"Point"}
}