{
  "type": "Feature",
  "properties": {
    "addr:full":"1203 N 40th Ave Yakima WA 98908",
    "addr:housenumber":"1203",
    "addr:postcode":"98908",
    "addr:street":"N 40Th Ave",
    "iso:country":"US",
    "sg:address":"1203 N 40th Ave",
    "sg:city":"Yakima",
    "sg:classifiers":[
        {
            "category":"Wholesale",
            "subcategory":"Hardware",
            "type":"Manufacturing & Wholesale Goods"
        }
    ],
    "sg:phone":"+1 509 577 8723",
    "sg:postcode":"98908",
    "sg:province":"WA",
    "wof:name":"Right Hardware Sales & Rental",
    "wof:placetype":"venue"
},
  "geometry": {"coordinates":[-120.560877,46.620967],"type":"Point"}
}