{
  "type": "Feature",
  "properties": {
    "addr:full":"12803 Ambaum Boulevard SW Burien WA 98146",
    "addr:housenumber":"12803",
    "addr:postcode":"98146",
    "addr:street":"Ambaum Boulevard Sw",
    "iso:country":"US",
    "sg:address":"12803 Ambaum Boulevard SW",
    "sg:city":"Burien",
    "sg:classifiers":[
        {
            "category":"Bars & Pubs",
            "subcategory":"Nightclub",
            "type":"Food & Drink"
        }
    ],
    "sg:phone":"+1 206 248 3113",
    "sg:postcode":"98146",
    "sg:province":"WA",
    "sg:tags":[
        "nightlife"
    ],
    "wof:name":"Mario's Sports Bar & Grill",
    "wof:placetype":"venue"
},
  "geometry": {"coordinates":[-122.349874,47.488249],"type":"Point"}
}