{
  "type": "Feature",
  "properties": {
    "addr:full":"4524 60th Ave W Tacoma WA 98466",
    "addr:housenumber":"4524",
    "addr:postcode":"98466",
    "addr:street":"60Th Ave W",
    "iso:country":"US",
    "sg:address":"4524 60th Ave W",
    "sg:city":"Tacoma",
    "sg:classifiers":[
        {
            "category":"Retail",
            "subcategory":"Repair Shop",
            "type":"Services"
        }
    ],
    "sg:phone":"+1 253 564 1887",
    "sg:postcode":"98466",
    "sg:province":"WA",
    "wof:name":"Ulysses Harden",
    "wof:placetype":"venue"
},
  "geometry": {"coordinates":[-122.51740599999999,47.216803],"type":"Point"}
}