{
  "type": "Feature",
  "properties": {
    "iso:country":"US",
    "sg:address":"2837 Rocky Point Rd NW",
    "sg:city":"Bremerton",
    "sg:classifiers":[
        {
            "category":"Professional",
            "type":"Services"
        }
    ],
    "sg:phone":"+1 360 373 7491",
    "sg:postcode":"98312",
    "sg:province":"WA",
    "wof:name":"Rocky Point Services",
    "wof:placetype":"venue"
},
  "geometry": {"coordinates":[-122.669496,47.589713],"type":"Point"}
}