{
  "type": "Feature",
  "properties": {
    "addr:full":"22507 137th St NE Granite Falls WA 98252",
    "addr:housenumber":"22507",
    "addr:postcode":"98252",
    "addr:street":"137Th St Ne",
    "iso:country":"US",
    "sg:address":"22507 137th St NE",
    "sg:city":"Granite Falls",
    "sg:classifiers":[
        {
            "category":"Real Estate",
            "subcategory":"Real Estate Agent",
            "type":"Services"
        }
    ],
    "sg:phone":"+1 360 691 3352",
    "sg:postcode":"98252",
    "sg:province":"WA",
    "wof:name":"Amanda Flynn",
    "wof:placetype":"venue"
},
  "geometry": {"coordinates":[-121.926607,48.119689],"type":"Point"}
}