{
  "type": "Feature",
  "properties": {
    "addr:full":"1722 NE 16th Loop Battle Ground WA 98604",
    "addr:housenumber":"1722",
    "addr:postcode":"98604",
    "addr:street":"Ne 16Th Loop",
    "iso:country":"US",
    "sg:address":"1722 NE 16th Loop",
    "sg:city":"Battle Ground",
    "sg:classifiers":[
        {
            "category":"Manufacturing",
            "subcategory":"Glass & Minerals",
            "type":"Manufacturing & Wholesale Goods"
        }
    ],
    "sg:phone":"+1 360 901 7731",
    "sg:postcode":"98604",
    "sg:province":"WA",
    "sg:tags":[
        "concrete",
        "product",
        "mfg"
    ],
    "wof:name":"Minkas Garden",
    "wof:placetype":"venue"
},
  "geometry": {"coordinates":[-122.52119999999999,45.793407],"type":"Point"}
}