{
  "type": "Feature",
  "properties": {
    "addr:full":"2024 71st St NE Marysville WA 98271",
    "addr:housenumber":"2024",
    "addr:postcode":"98271",
    "addr:street":"71St St Ne",
    "iso:country":"US",
    "sg:address":"2024 71st St NE",
    "sg:city":"Marysville",
    "sg:classifiers":[
        {
            "category":"Building & Trades",
            "subcategory":"Construction",
            "type":"Services"
        }
    ],
    "sg:phone":"+1 425 344 5536",
    "sg:postcode":"98271",
    "sg:province":"WA",
    "sg:tags":[
        "contractor"
    ],
    "wof:name":"Dombravskiy Corp",
    "wof:placetype":"venue"
},
  "geometry": {"coordinates":[-122.202771,48.060613],"type":"Point"}
}