{
  "type": "Feature",
  "properties": {
    "addr:full":"1620 26th Ave Seattle WA 98122",
    "addr:housenumber":"1620",
    "addr:postcode":"98122",
    "addr:street":"26Th Ave",
    "iso:country":"US",
    "sg:address":"1620 26th Ave",
    "sg:city":"Seattle",
    "sg:classifiers":[
        {
            "category":"Professional",
            "subcategory":"Accounting & Tax Preparation",
            "type":"Services"
        }
    ],
    "sg:phone":"+1 206 280 3634",
    "sg:postcode":"98122",
    "sg:province":"WA",
    "sg:tags":[
        "return"
    ],
    "wof:name":"Donald Fleeks",
    "wof:placetype":"venue"
},
  "geometry": {"coordinates":[-122.29870099999999,47.616226],"type":"Point"}
}