{
  "type": "Feature",
  "properties": {
    "addr:full":"4427 6th Ave Tacoma WA 98406",
    "addr:housenumber":"4427",
    "addr:postcode":"98406",
    "addr:street":"6Th Ave",
    "iso:country":"US",
    "sg:address":"4427 6th Ave",
    "sg:city":"Tacoma",
    "sg:phone":"+1 253 752 8790",
    "sg:postcode":"98406",
    "sg:province":"WA",
    "sg:website":"http://www.tacotime.com",
    "wof:name":"TacoTime",
    "wof:placetype":"venue"
},
  "geometry": {"coordinates":[-122.49654700000001,47.255329],"type":"Point"}
}