{
  "type": "Feature",
  "properties": {
    "addr:full":"18007 63rd Pl W Lynnwood WA 98037",
    "addr:housenumber":"18007",
    "addr:postcode":"98037",
    "addr:street":"63Rd Pl W",
    "iso:country":"US",
    "sg:address":"18007 63rd Pl W",
    "sg:city":"Lynnwood",
    "sg:classifiers":[
        {
            "category":"Shopping",
            "subcategory":"Used Merchandise",
            "type":"Retail Goods"
        }
    ],
    "sg:phone":"+1 425 771 6052",
    "sg:postcode":"98037",
    "sg:province":"WA",
    "wof:name":"Antique Friendly",
    "wof:placetype":"venue"
},
  "geometry": {"coordinates":[-122.31768700000001,47.835292],"type":"Point"}
}