{
  "type": "Feature",
  "properties": {
    "addr:full":"505 N Argonne Rd Spokane Valley WA 99212",
    "addr:housenumber":"505",
    "addr:postcode":"99212",
    "addr:street":"N Argonne Rd",
    "iso:country":"US",
    "sg:address":"505 N Argonne Rd",
    "sg:city":"Spokane Valley",
    "sg:classifiers":[
        {
            "category":"Social Services",
            "type":"Services"
        }
    ],
    "sg:phone":"+1 509 893 3456",
    "sg:postcode":"99212",
    "sg:province":"WA",
    "sg:tags":[
        "counselor",
        "marriage",
        "family"
    ],
    "wof:name":"Back To The Garden Counseling",
    "wof:placetype":"venue"
},
  "geometry": {"coordinates":[-117.282915,47.661354],"type":"Point"}
}