{
  "type": "Feature",
  "properties": {
    "addr:full":"1700 Railroad Ave Mount Vernon WA 98273",
    "addr:housenumber":"1700",
    "addr:postcode":"98273",
    "addr:street":"Railroad Ave",
    "iso:country":"US",
    "sg:address":"1700 Railroad Ave",
    "sg:city":"Mount Vernon",
    "sg:classifiers":[
        {
            "category":"Building & Trades",
            "subcategory":"Electrical",
            "type":"Services"
        }
    ],
    "sg:phone":"+1 360 336 6188",
    "sg:postcode":"98273",
    "sg:province":"WA",
    "sg:tags":[
        "electrician"
    ],
    "sg:website":"www.ackermannelectric.com",
    "wof:name":"Ackermann Electric Co",
    "wof:placetype":"venue"
},
  "geometry": {"coordinates":[-122.333,48.425098],"type":"Point"}
}