{
  "type": "Feature",
  "properties": {
    "iso:country":"US",
    "sg:address":"123 S Gold St",
    "sg:city":"Centralia",
    "sg:classifiers":[
        {
            "category":"Education",
            "subcategory":"School",
            "type":"Public Place"
        }
    ],
    "sg:phone":"+1 360 330 7644",
    "sg:postcode":"98531",
    "sg:province":"WA",
    "wof:name":"Centralia School District Mntc",
    "wof:placetype":"venue"
},
  "geometry": {"coordinates":[-122.95215399999999,46.715577],"type":"Point"}
}