{
  "type": "Feature",
  "properties": {
    "addr:full":"500 Columbia St Ste D Woodland WA 98674",
    "addr:housenumber":"500",
    "addr:postcode":"98674",
    "addr:street":"Columbia St Ste D",
    "iso:country":"US",
    "sg:address":"500 Columbia St Ste D",
    "sg:city":"Woodland",
    "sg:classifiers":[
        {
            "category":"Restaurant",
            "type":"Food & Drink"
        }
    ],
    "sg:phone":"+1 360 225 8719",
    "sg:postcode":"98674",
    "sg:province":"WA",
    "sg:tags":[
        "mexican"
    ],
    "wof:name":"Guadalajara",
    "wof:placetype":"venue"
},
  "geometry": {"coordinates":[-122.74627700000001,45.910671],"type":"Point"}
}