{
  "type": "Feature",
  "properties": {
    "addr:full":"2700 Maple St Bremerton WA 98310",
    "addr:housenumber":"2700",
    "addr:postcode":"98310",
    "addr:street":"Maple St",
    "iso:country":"US",
    "sg:address":"2700 Maple St",
    "sg:city":"Bremerton",
    "sg:classifiers":[
        {
            "category":"Real Estate",
            "subcategory":"Real Estate Agent",
            "type":"Services"
        }
    ],
    "sg:phone":"+1 206 373 8501",
    "sg:postcode":"98310",
    "sg:province":"WA",
    "sg:tags":[
        "building",
        "operator",
        "apartment"
    ],
    "wof:name":"Maple Manor Apartments",
    "wof:placetype":"venue"
},
  "geometry": {"coordinates":[-122.615393,47.585736],"type":"Point"}
}