{
  "type": "Feature",
  "properties": {
    "addr:full":"4618 Lake Washington Blvd NE Kirkland WA 98033",
    "addr:housenumber":"4618",
    "addr:postcode":"98033",
    "addr:street":"Lake Washington Blvd Ne",
    "iso:country":"US",
    "sg:address":"4618 Lake Washington Blvd NE",
    "sg:city":"Kirkland",
    "sg:classifiers":[
        {
            "category":"Building & Trades",
            "subcategory":"Locksmith",
            "type":"Services"
        }
    ],
    "sg:phone":"+1 425 636 1916",
    "sg:postcode":"98033",
    "sg:province":"WA",
    "sg:tags":[
        "key"
    ],
    "wof:name":"Any Time 24 Locksmith",
    "wof:placetype":"venue"
},
  "geometry": {"coordinates":[-122.203898,47.651072],"type":"Point"}
}