{
  "type": "Feature",
  "properties": {
    "addr:full":"2400 Camden St Richland WA 99352",
    "addr:housenumber":"2400",
    "addr:postcode":"99352",
    "addr:street":"Camden St",
    "iso:country":"US",
    "sg:address":"2400 Camden St",
    "sg:city":"Richland",
    "sg:classifiers":[
        {
            "category":"Personal",
            "subcategory":"Beauty Salon",
            "type":"Services"
        }
    ],
    "sg:phone":"+1 509 946 1734",
    "sg:postcode":"99352",
    "sg:province":"WA",
    "wof:name":"Mike's Place",
    "wof:placetype":"venue"
},
  "geometry": {"coordinates":[-119.29743000000001,46.267456],"type":"Point"}
}