{
  "type": "Feature",
  "properties": {
    "iso:country":"US",
    "sg:address":"654 Basin St SW",
    "sg:city":"Ephrata",
    "sg:classifiers":[
        {
            "category":"Autos & Motor Vehicles",
            "subcategory":"Auto Supplies",
            "type":"Retail Goods"
        }
    ],
    "sg:phone":"+1 509 754 1332",
    "sg:postcode":"98823",
    "sg:province":"WA",
    "wof:name":"Schucks Auto Supply 4367",
    "wof:placetype":"venue"
},
  "geometry": {"coordinates":[-119.556028,47.314434],"type":"Point"}
}