{
  "type": "Feature",
  "properties": {
    "addr:full":"5968 Locust Ln Cashmere WA 98815",
    "addr:housenumber":"5968",
    "addr:postcode":"98815",
    "addr:street":"Locust Ln",
    "iso:country":"US",
    "sg:address":"5968 Locust Ln",
    "sg:city":"Cashmere",
    "sg:classifiers":[
        {
            "category":"Retail",
            "subcategory":"Auto Repair",
            "type":"Services"
        }
    ],
    "sg:phone":"+1 509 782 2337",
    "sg:postcode":"98815",
    "sg:province":"WA",
    "sg:tags":[
        "shop",
        "automobile",
        "machine"
    ],
    "wof:name":"Newberry's Repair & R V",
    "wof:placetype":"venue"
},
  "geometry": {"coordinates":[-120.492915,47.524268],"type":"Point"}
}