{
  "type": "Feature",
  "properties": {
    "addr:full":"2716 NE 82nd Cir Vancouver WA 98665",
    "addr:housenumber":"2716",
    "addr:postcode":"98665",
    "addr:street":"Ne 82Nd Cir",
    "iso:country":"US",
    "sg:address":"2716 NE 82nd Cir",
    "sg:city":"Vancouver",
    "sg:classifiers":[
        {
            "category":"Social Services",
            "subcategory":"Adult Care",
            "type":"Services"
        },
        {
            "category":"Banks & Credit Unions",
            "subcategory":"Financial Services",
            "type":"Services"
        }
    ],
    "sg:phone":"+1 360 574 4228",
    "sg:postcode":"98665",
    "sg:province":"WA",
    "sg:tags":[
        "residential",
        "consulting",
        "business",
        "guardianship"
    ],
    "wof:name":"Ambers Guardianship Services",
    "wof:placetype":"venue"
},
  "geometry": {"coordinates":[-122.642112,45.681336],"type":"Point"}
}