{
  "type": "Feature",
  "properties": {
    "addr:full":"11042 Parke Creek Rd Ellensburg WA 98926",
    "addr:housenumber":"11042",
    "addr:postcode":"98926",
    "addr:street":"Parke Creek Rd",
    "iso:country":"US",
    "sg:address":"11042 Parke Creek Rd",
    "sg:city":"Ellensburg",
    "sg:classifiers":[
        {
            "category":"Social Services",
            "subcategory":"Child Care",
            "type":"Services"
        },
        {
            "category":"Government",
            "subcategory":"Office",
            "type":"Public Place"
        }
    ],
    "sg:phone":"+1 509 968 3924",
    "sg:postcode":"98926",
    "sg:province":"WA",
    "sg:tags":[
        "government-state",
        "foster",
        "agency"
    ],
    "wof:name":"Park Creek Group Home",
    "wof:placetype":"venue"
},
  "geometry": {"coordinates":[-120.320588,47.015877],"type":"Point"}
}