{
  "type": "Feature",
  "properties": {
    "addr:full":"5400 Carillon Pt Kirkland WA 98033",
    "addr:housenumber":"5400",
    "addr:postcode":"98033",
    "addr:street":"Carillon Pt",
    "iso:country":"US",
    "sg:address":"5400 Carillon Pt",
    "sg:city":"Kirkland",
    "sg:classifiers":[
        {
            "category":"Professional",
            "subcategory":"Lawyer & Legal Services",
            "type":"Services"
        }
    ],
    "sg:phone":"+1 425 576 4194",
    "sg:postcode":"98033",
    "sg:province":"WA",
    "wof:name":"Holly Hohlbein",
    "wof:placetype":"venue"
},
  "geometry": {"coordinates":[-122.206422,47.656579],"type":"Point"}
}