{
  "type": "Feature",
  "properties": {
    "addr:full":"17525 NE 40th St Redmond WA 98052",
    "addr:housenumber":"17525",
    "addr:postcode":"98052",
    "addr:street":"Ne 40Th St",
    "iso:country":"US",
    "sg:address":"17525 NE 40th St",
    "sg:city":"Redmond",
    "sg:classifiers":[
        {
            "category":"Professional",
            "subcategory":"Management & Consulting",
            "type":"Services"
        }
    ],
    "sg:phone":"+1 425 881 6336",
    "sg:postcode":"98052",
    "sg:province":"WA",
    "wof:name":"Oestreich Associates",
    "wof:placetype":"venue"
},
  "geometry": {"coordinates":[-122.10649600000001,47.646038],"type":"Point"}
}