{
  "type": "Feature",
  "properties": {
    "addr:full":"5231 W Owens Rd Deer Park WA 99006",
    "addr:housenumber":"5231",
    "addr:postcode":"99006",
    "addr:street":"W Owens Rd",
    "iso:country":"US",
    "sg:address":"5231 W Owens Rd",
    "sg:city":"Deer Park",
    "sg:classifiers":[
        {
            "category":"Retail",
            "subcategory":"Repair Shop",
            "type":"Services"
        }
    ],
    "sg:phone":"+1 509 276 8541",
    "sg:postcode":"99006",
    "sg:province":"WA",
    "wof:name":"Nortwest Mri Services Inc",
    "wof:placetype":"venue"
},
  "geometry": {"coordinates":[-117.485033,47.917896],"type":"Point"}
}