{
  "type": "Feature",
  "properties": {
    "addr:full":"7114 87th St SW Lakewood WA 98499",
    "addr:housenumber":"7114",
    "addr:postcode":"98499",
    "addr:street":"87Th St Sw",
    "iso:country":"US",
    "sg:address":"7114 87th St SW",
    "sg:city":"Lakewood",
    "sg:classifiers":[
        {
            "category":"Professional",
            "subcategory":"Accounting & Tax Preparation",
            "type":"Services"
        }
    ],
    "sg:phone":"+1 253 588 9181",
    "sg:postcode":"98499",
    "sg:province":"WA",
    "sg:tags":[
        "return",
        "billing"
    ],
    "wof:name":"Bonafied Bookkeeping & Tax Service",
    "wof:placetype":"venue"
},
  "geometry": {"coordinates":[-122.532138,47.178661],"type":"Point"}
}