{
  "type": "Feature",
  "properties": {
    "addr:full":"12545 Dodson Rd N Ephrata WA 98823",
    "addr:housenumber":"12545",
    "addr:postcode":"98823",
    "addr:street":"Dodson Rd N",
    "iso:country":"US",
    "sg:address":"12545 Dodson Rd N",
    "sg:city":"Ephrata",
    "sg:classifiers":[
        {
            "category":"Building & Trades",
            "subcategory":"Construction",
            "type":"Services"
        }
    ],
    "sg:phone":"+1 509 754 9712",
    "sg:postcode":"98823",
    "sg:province":"WA",
    "sg:tags":[
        "excavating",
        "contractor"
    ],
    "wof:name":"Grant County Sewage Design Svc",
    "wof:placetype":"venue"
},
  "geometry": {"coordinates":[-119.554964,47.270055],"type":"Point"}
}