{
  "type": "Feature",
  "properties": {
    "addr:full":"1800 Cooper Pt Rd NW Olympia WA 98502",
    "addr:housenumber":"1800",
    "addr:postcode":"olympia wa 98502",
    "addr:street":"Cooper Pt Rd Nw",
    "iso:country":"US",
    "sg:address":"1800 Cooper Pt Rd NW",
    "sg:city":"Olympia",
    "sg:classifiers":[
        {
            "category":"Organizations",
            "subcategory":"Professional Association",
            "type":"Services"
        }
    ],
    "sg:phone":"+1 360 352 4848",
    "sg:postcode":"98502",
    "sg:province":"WA",
    "wof:name":"W S M A",
    "wof:placetype":"venue"
},
  "geometry": {"coordinates":[-122.941238,47.061245],"type":"Point"}
}