{
  "type": "Feature",
  "properties": {
    "addr:full":"2703 4th Ave W Seattle WA 98119",
    "addr:housenumber":"2703",
    "addr:postcode":"98119",
    "addr:street":"4Th Ave W",
    "iso:country":"US",
    "sg:address":"2703 4th Ave W",
    "sg:city":"Seattle",
    "sg:classifiers":[
        {
            "category":"Professional",
            "subcategory":"Business Services",
            "type":"Services"
        }
    ],
    "sg:phone":"+1 206 283 6451",
    "sg:postcode":"98119",
    "sg:province":"WA",
    "sg:tags":[
        "management"
    ],
    "wof:name":"Rowen And Co",
    "wof:placetype":"venue"
},
  "geometry": {"coordinates":[-122.362228,47.644118],"type":"Point"}
}