{
  "type": "Feature",
  "properties": {
    "addr:full":"15650 NE 24th St Ste C3 Bellevue WA 98008",
    "addr:housenumber":"15650",
    "addr:postcode":"98008",
    "addr:street":"Ne 24Th St Ste C3",
    "iso:country":"US",
    "sg:address":"15650 NE 24th St Ste C3",
    "sg:city":"Bellevue",
    "sg:classifiers":[
        {
            "category":"Manufacturing",
            "subcategory":"Buildings",
            "type":"Manufacturing & Wholesale Goods"
        },
        {
            "category":"Building & Trades",
            "subcategory":"Construction",
            "type":"Services"
        }
    ],
    "sg:phone":"+1 425 746 6397",
    "sg:postcode":"98008",
    "sg:province":"WA",
    "sg:tags":[
        "industrial",
        "altering",
        "consultant",
        "builder",
        "contractor",
        "contractors-commercial",
        "home",
        "remodeling"
    ],
    "wof:name":"Cornell's Quality Const",
    "wof:placetype":"venue"
},
  "geometry": {"coordinates":[-122.13200399999999,47.631599],"type":"Point"}
}