{
  "type": "Feature",
  "properties": {
    "iso:country":"US",
    "sg:address":"1048 NW Gladiola Ct",
    "sg:city":"Silverdale",
    "sg:classifiers":[
        {
            "category":"Organizations",
            "subcategory":"Religious Organization",
            "type":"Services"
        }
    ],
    "sg:phone":"+1 360 692 4360",
    "sg:postcode":"98383",
    "sg:province":"WA",
    "wof:name":"Spirit Of Life Ministries",
    "wof:placetype":"venue"
},
  "geometry": {"coordinates":[-122.66218600000001,47.663869],"type":"Point"}
}