{
  "type": "Feature",
  "properties": {
    "iso:country":"US",
    "sg:address":"982 E St",
    "sg:city":"Washougal",
    "sg:classifiers":[
        {
            "category":"Retail",
            "subcategory":"Repair Shop",
            "type":"Services"
        }
    ],
    "sg:phone":"+1 360 835 3516",
    "sg:postcode":"98671",
    "sg:province":"WA",
    "sg:tags":[
        "gas",
        "appliance"
    ],
    "wof:name":"G P & W Systems Inc",
    "wof:placetype":"venue"
},
  "geometry": {"coordinates":[-122.35977200000001,45.581244],"type":"Point"}
}