{
  "type": "Feature",
  "properties": {
    "addr:full":"575 Bertrand Dr Lynden WA 98264",
    "addr:housenumber":"575",
    "addr:postcode":"98264",
    "addr:street":"Bertrand Dr",
    "iso:country":"US",
    "sg:address":"575 Bertrand Dr",
    "sg:city":"Lynden",
    "sg:classifiers":[
        {
            "category":"Manufacturing",
            "subcategory":"Toys & Sporting Goods",
            "type":"Manufacturing & Wholesale Goods"
        }
    ],
    "sg:phone":"+1 360 354 1496",
    "sg:postcode":"98264",
    "sg:province":"WA",
    "sg:tags":[
        "mfg"
    ],
    "wof:name":"Lb Custom Rods",
    "wof:placetype":"venue"
},
  "geometry": {"coordinates":[-122.509519,48.95382],"type":"Point"}
}