{
  "type": "Feature",
  "properties": {
    "iso:country":"US",
    "sg:address":"2903 W Plath Ave",
    "sg:city":"Yakima",
    "sg:classifiers":[
        {
            "category":"Banks & Credit Unions",
            "subcategory":"Financial Services",
            "type":"Services"
        }
    ],
    "sg:phone":"+1 509 454 8441",
    "sg:postcode":"98902",
    "sg:province":"WA",
    "sg:tags":[
        "investor"
    ],
    "wof:name":"Wbnj Investments LLC",
    "wof:placetype":"venue"
},
  "geometry": {"coordinates":[-120.5496,46.57925],"type":"Point"}
}