{
  "type": "Feature",
  "properties": {
    "addr:full":"822 Pioneer Ave W Montesano WA 98563",
    "addr:housenumber":"822",
    "addr:postcode":"98563",
    "addr:street":"Pioneer Ave W Montesano",
    "iso:country":"US",
    "sg:address":"822 Pioneer Ave W",
    "sg:city":"Montesano",
    "sg:classifiers":[
        {
            "category":"Travel",
            "subcategory":"Hotels & Motels",
            "type":"Entertainment"
        }
    ],
    "sg:phone":"+1 360 249 3931",
    "sg:postcode":"98563",
    "sg:province":"WA",
    "sg:tags":[
        "operation"
    ],
    "wof:name":"Plumb Tree Motel & Apartments",
    "wof:placetype":"venue"
},
  "geometry": {"coordinates":[-123.609978,46.978009],"type":"Point"}
}