{
  "type": "Feature",
  "properties": {
    "addr:full":"1489 130th Ave NE Bellevue WA 98005",
    "addr:housenumber":"1489",
    "addr:postcode":"98005",
    "addr:street":"130Th Ave Ne",
    "iso:country":"US",
    "sg:address":"1489 130th Ave NE",
    "sg:city":"Bellevue",
    "sg:classifiers":[
        {
            "category":"Professional",
            "subcategory":"Engineering",
            "type":"Services"
        }
    ],
    "sg:phone":"+1 425 453 2140",
    "sg:postcode":"98005",
    "sg:province":"WA",
    "sg:tags":[
        "contracting",
        "mechanical"
    ],
    "wof:name":"Bellevue Mechanical",
    "wof:placetype":"venue"
},
  "geometry": {"coordinates":[-122.167137,47.623502],"type":"Point"}
}