{
  "type": "Feature",
  "properties": {
    "addr:full":"214 Naches Ave Naches WA 98937",
    "addr:housenumber":"214",
    "addr:postcode":"98937",
    "addr:street":"Naches Ave",
    "iso:country":"US",
    "sg:address":"214 Naches Ave",
    "sg:city":"Naches",
    "sg:classifiers":[
        {
            "category":"Building & Trades",
            "subcategory":"Construction",
            "type":"Services"
        }
    ],
    "sg:phone":"+1 509 653 1764",
    "sg:postcode":"98937",
    "sg:province":"WA",
    "sg:tags":[
        "excavation",
        "contractor",
        "general"
    ],
    "wof:name":"Absolute Building and Excavati",
    "wof:placetype":"venue"
},
  "geometry": {"coordinates":[-120.701104,46.731881],"type":"Point"}
}