{
  "type": "Feature",
  "properties": {
    "addr:full":"1818 NE 96th St Seattle WA 98115",
    "addr:housenumber":"1818",
    "addr:postcode":"98115",
    "addr:street":"Ne 96Th St",
    "iso:country":"US",
    "sg:address":"1818 NE 96th St",
    "sg:city":"Seattle",
    "sg:classifiers":[
        {
            "category":"Professional",
            "type":"Services"
        }
    ],
    "sg:phone":"+1 206 714 7473",
    "sg:postcode":"98115",
    "sg:province":"WA",
    "wof:name":"Cedar Marketing Communications",
    "wof:placetype":"venue"
},
  "geometry": {"coordinates":[-122.30694200000001,47.698985],"type":"Point"}
}