{
  "type": "Feature",
  "properties": {
    "addr:full":"114 E 1st St Port Angeles WA 98362",
    "addr:housenumber":"114",
    "addr:postcode":"98362",
    "addr:street":"E 1St St",
    "iso:country":"US",
    "sg:address":"114 E 1st St",
    "sg:city":"Port Angeles",
    "sg:classifiers":[
        {
            "category":"Health Services",
            "subcategory":"Optometrist",
            "type":"Services"
        }
    ],
    "sg:phone":"+1 360 374 2050",
    "sg:postcode":"98362",
    "sg:province":"WA",
    "wof:name":"Forks Vision Clinic",
    "wof:placetype":"venue"
},
  "geometry": {"coordinates":[-123.43337200000001,48.118844],"type":"Point"}
}