{
  "type": "Feature",
  "properties": {
    "addr:full":"10501 Creek St SE Yelm WA 98597",
    "addr:housenumber":"10501",
    "addr:postcode":"98597",
    "addr:street":"Creek St Se",
    "iso:country":"US",
    "sg:address":"10501 Creek St SE",
    "sg:city":"Yelm",
    "sg:classifiers":[
        {
            "category":"Professional",
            "subcategory":"Lawyer & Legal Services",
            "type":"Services"
        }
    ],
    "sg:phone":"+1 360 458 7799",
    "sg:postcode":"98597",
    "sg:province":"WA",
    "sg:tags":[
        "attorney"
    ],
    "wof:name":"Bernard Lee Perez Attorney",
    "wof:placetype":"venue"
},
  "geometry": {"coordinates":[-122.589938,46.933204],"type":"Point"}
}