{
  "type": "Feature",
  "properties": {
    "addr:full":"24399 244th St SW Mountlake Terrace WA 98043",
    "addr:housenumber":"24399",
    "addr:postcode":"98043",
    "addr:street":"244Th St Sw",
    "iso:country":"US",
    "sg:address":"24399 244th St SW",
    "sg:city":"Mountlake Terrace",
    "sg:classifiers":[
        {
            "category":"Restaurant",
            "type":"Food & Drink"
        }
    ],
    "sg:menulink":"http://www.allmenus.com/wa/edmonds/46427-canyons-mountlake/menu/",
    "sg:phone":"+1 425 744 1525",
    "sg:postcode":"98043",
    "sg:province":"WA",
    "sg:tags":[
        "american"
    ],
    "wof:name":"Canyons-mountlake",
    "wof:placetype":"venue"
},
  "geometry": {"coordinates":[-122.312656,47.777587],"type":"Point"}
}