{
  "type": "Feature",
  "properties": {
    "addr:full":"19501 144th Ave NE Woodinville WA 98072",
    "addr:housenumber":"19501",
    "addr:postcode":"98072",
    "addr:street":"144Th Ave Ne",
    "iso:country":"US",
    "sg:address":"19501 144th Ave NE",
    "sg:city":"Woodinville",
    "sg:classifiers":[
        {
            "category":"Manufacturing",
            "subcategory":"Aerospace",
            "type":"Manufacturing & Wholesale Goods"
        },
        {
            "category":"Airport",
            "type":"Transportation"
        }
    ],
    "sg:phone":"+1 425 415 6052",
    "sg:postcode":"98072",
    "sg:province":"WA",
    "sg:tags":[
        "aircraft",
        "mfg",
        "support",
        "airline"
    ],
    "wof:name":"Dara Aviation",
    "wof:placetype":"venue"
},
  "geometry": {"coordinates":[-122.147837,47.768986],"type":"Point"}
}