{
  "type": "Feature",
  "properties": {
    "addr:full":"23326 State Hwy 3 Poulsbo WA 98370",
    "addr:housenumber":"23326",
    "addr:postcode":"98370",
    "addr:street":"State Hwy 3",
    "iso:country":"US",
    "sg:address":"23326 State Hwy 3",
    "sg:city":"Poulsbo",
    "sg:classifiers":[
        {
            "category":"Shopping",
            "type":"Retail Goods"
        },
        {
            "category":"Retail",
            "subcategory":"Animal Services",
            "type":"Services"
        }
    ],
    "sg:phone":"+1 360 697 4363",
    "sg:postcode":"98370",
    "sg:province":"WA",
    "sg:tags":[
        "training",
        "dog",
        "merchandise"
    ],
    "wof:name":"Teacher's Pet Dog Training",
    "wof:placetype":"venue"
},
  "geometry": {"coordinates":[-122.65068599999999,47.770432],"type":"Point"}
}