{
  "type": "Feature",
  "properties": {
    "addr:full":"4732 Brooklyn Ave NE Seattle WA 98105",
    "addr:housenumber":"4732",
    "addr:postcode":"98105",
    "addr:street":"Brooklyn Ave Ne",
    "iso:country":"US",
    "sg:address":"4732 Brooklyn Ave NE",
    "sg:city":"Seattle",
    "sg:classifiers":[
        {
            "category":"Shopping",
            "subcategory":"Pharmacy",
            "type":"Retail Goods"
        },
        {
            "category":"Food & Beverages",
            "subcategory":"Groceries & Convenience Stores",
            "type":"Retail Goods"
        }
    ],
    "sg:phone":"+1 206 522 4565",
    "sg:postcode":"98105",
    "sg:province":"WA",
    "sg:tags":[
        "drugstore"
    ],
    "sg:website":"www.safeway.com",
    "wof:name":"Safeway",
    "wof:placetype":"venue"
},
  "geometry": {"coordinates":[-122.314196,47.663316],"type":"Point"}
}