{
  "type": "Feature",
  "properties": {
    "addr:full":"7004 W Williams Rd Benton City WA 99320",
    "addr:housenumber":"7004",
    "addr:postcode":"99320",
    "addr:street":"W Williams Rd",
    "iso:country":"US",
    "sg:address":"7004 W Williams Rd",
    "sg:city":"Benton City",
    "sg:classifiers":[
        {
            "category":"Farming",
            "subcategory":"Orchard",
            "type":"Manufacturing & Wholesale Goods"
        },
        {
            "category":"Wholesale",
            "subcategory":"Fruits & Vegetables",
            "type":"Manufacturing & Wholesale Goods"
        }
    ],
    "sg:phone":"+1 509 588 2717",
    "sg:postcode":"99320",
    "sg:province":"WA",
    "sg:tags":[
        "tree",
        "shipper"
    ],
    "wof:name":"Wild Willow Company",
    "wof:placetype":"venue"
},
  "geometry": {"coordinates":[-119.504766,46.279068],"type":"Point"}
}