{
  "type": "Feature",
  "properties": {
    "iso:country":"US",
    "sg:address":"4210 187th Ave SE",
    "sg:city":"Issaquah",
    "sg:classifiers":[
        {
            "category":"Professional",
            "subcategory":"Business Services",
            "type":"Services"
        }
    ],
    "sg:phone":"+1 425 747 7079",
    "sg:postcode":"98027",
    "sg:province":"WA",
    "wof:name":"Surroundings",
    "wof:placetype":"venue"
},
  "geometry": {"coordinates":[-122.09018,47.568992],"type":"Point"}
}