{
  "type": "Feature",
  "properties": {
    "addr:full":"951 Charvet Rd Grandview WA 98930",
    "addr:housenumber":"951",
    "addr:postcode":"98930",
    "addr:street":"Charvet Rd",
    "iso:country":"US",
    "sg:address":"951 Charvet Rd",
    "sg:city":"Grandview",
    "sg:classifiers":[
        {
            "category":"Farming",
            "subcategory":"Farm",
            "type":"Manufacturing & Wholesale Goods"
        }
    ],
    "sg:phone":"+1 509 882 2385",
    "sg:postcode":"98930",
    "sg:province":"WA",
    "sg:tags":[
        "crop",
        "general"
    ],
    "wof:name":"Stanley D Maas",
    "wof:placetype":"venue"
},
  "geometry": {"coordinates":[-119.95133199999999,46.236588],"type":"Point"}
}