{
  "type": "Feature",
  "properties": {
    "addr:full":"4598 Dunn St NE Moses Lake WA 98837",
    "addr:housenumber":"4598",
    "addr:postcode":"98837",
    "addr:street":"Dunn St Ne",
    "iso:country":"US",
    "sg:address":"4598 Dunn St NE",
    "sg:city":"Moses Lake",
    "sg:phone":"+1 509 765 3763",
    "sg:postcode":"98837",
    "sg:province":"WA",
    "sg:tags":[
        "farm",
        "field",
        "crop"
    ],
    "wof:name":"Fred Huston",
    "wof:placetype":"venue"
},
  "geometry": {"coordinates":[-119.24503300000001,47.146531],"type":"Point"}
}