{
  "type": "Feature",
  "properties": {
    "addr:full":"303 47th St Port Townsend WA 98368",
    "addr:housenumber":"303",
    "addr:postcode":"98368",
    "addr:street":"47Th St",
    "iso:country":"US",
    "sg:address":"303 47th St",
    "sg:city":"Port Townsend",
    "sg:classifiers":[
        {
            "category":"Shopping",
            "subcategory":"Jewelry",
            "type":"Retail Goods"
        }
    ],
    "sg:phone":"+1 360 385 6051",
    "sg:postcode":"98368",
    "sg:province":"WA",
    "wof:name":"Jewelry By Etta",
    "wof:placetype":"venue"
},
  "geometry": {"coordinates":[-122.780655,48.133985],"type":"Point"}
}