{
  "type": "Feature",
  "properties": {
    "addr:full":"24415 SE 216th St Maple Valley WA 98038",
    "addr:postcode":"24415;98038",
    "addr:street":"Se 216Th St",
    "iso:country":"US",
    "sg:address":"24415 SE 216th St",
    "sg:city":"Maple Valley",
    "sg:classifiers":[
        {
            "category":"Arena",
            "subcategory":"Sports Club",
            "type":"Entertainment"
        }
    ],
    "sg:phone":"+1 425 432 2428",
    "sg:postcode":"98038",
    "sg:province":"WA",
    "wof:name":"Maple Valley Jr Football",
    "wof:placetype":"venue"
},
  "geometry": {"coordinates":[-122.00949799999999,47.408141],"type":"Point"}
}