{
  "type": "Feature",
  "properties": {
    "addr:full":"15236 172nd Ave SE Monroe WA 98272",
    "addr:housenumber":"15236",
    "addr:postcode":"98272",
    "addr:street":"172Nd Ave Se",
    "iso:country":"US",
    "sg:address":"15236 172nd Ave SE",
    "sg:city":"Monroe",
    "sg:classifiers":[
        {
            "category":"Restaurant",
            "type":"Food & Drink"
        }
    ],
    "sg:phone":"+1 425 232 7705",
    "sg:postcode":"98272",
    "sg:province":"WA",
    "sg:tags":[
        "eating"
    ],
    "wof:name":"Ssl Refreshments",
    "wof:placetype":"venue"
},
  "geometry": {"coordinates":[-122.000263,47.860325],"type":"Point"}
}