{
  "type": "Feature",
  "properties": {
    "addr:full":"401 NE Northlake Way Seattle WA 98105",
    "addr:housenumber":"401",
    "addr:postcode":"98105",
    "addr:street":"Ne Northlake Way",
    "iso:country":"US",
    "sg:address":"401 NE Northlake Way",
    "sg:city":"Seattle",
    "sg:classifiers":[
        {
            "category":"Restaurant",
            "type":"Food & Drink"
        }
    ],
    "sg:phone":"+1 206 632 0767",
    "sg:postcode":"98105",
    "sg:province":"WA",
    "wof:name":"Indian Salmon House",
    "wof:placetype":"venue"
},
  "geometry": {"coordinates":[-122.32399700000001,47.653999],"type":"Point"}
}