{
  "type": "Feature",
  "properties": {
    "iso:country":"US",
    "sg:address":"2731 Wetmore Ave",
    "sg:city":"Everett",
    "sg:classifiers":[
        {
            "category":"Social Services",
            "type":"Services"
        }
    ],
    "sg:phone":"+1 425 258 2519",
    "sg:postcode":"98201",
    "sg:province":"WA",
    "sg:tags":[
        "probation"
    ],
    "wof:name":"Federal Probation & Parole",
    "wof:placetype":"venue"
},
  "geometry": {"coordinates":[-122.20709600000001,47.981027],"type":"Point"}
}