{
  "type": "Feature",
  "properties": {
    "addr:full":"504 Washington St Vancouver WA 98660",
    "addr:housenumber":"504",
    "addr:postcode":"98660",
    "addr:street":"Washington St",
    "iso:country":"US",
    "sg:address":"504 Washington St",
    "sg:city":"Vancouver",
    "sg:classifiers":[
        {
            "category":"Professional",
            "type":"Services"
        }
    ],
    "sg:phone":"+1 360 694 9052",
    "sg:postcode":"98660",
    "sg:province":"WA",
    "sg:tags":[
        "establishment"
    ],
    "wof:name":"Diamond A Designs",
    "wof:placetype":"venue"
},
  "geometry": {"coordinates":[-122.67283500000001,45.625659],"type":"Point"}
}