{
  "type": "Feature",
  "properties": {
    "addr:full":"7252 Autumn Ave SE Snoqualmie WA 98065",
    "addr:housenumber":"7252",
    "addr:postcode":"98065",
    "addr:street":"Autumn Ave Se",
    "iso:country":"US",
    "sg:address":"7252 Autumn Ave SE",
    "sg:city":"Snoqualmie",
    "sg:classifiers":[
        {
            "category":"Shopping",
            "subcategory":"Gifts & Souvenirs",
            "type":"Retail Goods"
        }
    ],
    "sg:phone":"+1 425 396 5157",
    "sg:postcode":"98065",
    "sg:province":"WA",
    "wof:name":"Create Your World",
    "wof:placetype":"venue"
},
  "geometry": {"coordinates":[-121.87057900000001,47.536064],"type":"Point"}
}