{
  "type": "Feature",
  "properties": {
    "addr:full":"2595 Sequim-Dungeness Way Sequim WA 98382",
    "addr:housenumber":"2595",
    "addr:postcode":"98382",
    "addr:street":"Sequim-Dungeness Way",
    "iso:country":"US",
    "sg:address":"2595 Sequim-Dungeness Way",
    "sg:city":"Sequim",
    "sg:classifiers":[
        {
            "category":"Retail",
            "subcategory":"Repair Shop",
            "type":"Services"
        }
    ],
    "sg:phone":"+1 360 683 3483",
    "sg:postcode":"98382",
    "sg:province":"WA",
    "sg:tags":[
        "upholsterer"
    ],
    "wof:name":"Dahll's Upholstery",
    "wof:placetype":"venue"
},
  "geometry": {"coordinates":[-123.10221300000001,48.116323],"type":"Point"}
}