{
  "type": "Feature",
  "properties": {
    "addr:full":"3257 16th Ave W Seattle WA 98119",
    "addr:housenumber":"3257",
    "addr:postcode":"98119",
    "addr:street":"16Th Ave W",
    "iso:country":"US",
    "sg:address":"3257 16th Ave W",
    "sg:city":"Seattle",
    "sg:classifiers":[
        {
            "category":"Manufacturing",
            "subcategory":"Printing",
            "type":"Manufacturing & Wholesale Goods"
        }
    ],
    "sg:phone":"+1 206 217 0204",
    "sg:postcode":"98119",
    "sg:province":"WA",
    "sg:tags":[
        "publisher"
    ],
    "wof:name":"Eastland Press",
    "wof:placetype":"venue"
},
  "geometry": {"coordinates":[-122.377579,47.651641],"type":"Point"}
}