{
  "type": "Feature",
  "properties": {
    "addr:full":"1845 N Bristol St Tacoma WA 98406",
    "addr:housenumber":"1845",
    "addr:postcode":"98406",
    "addr:street":"N Bristol St",
    "iso:country":"US",
    "sg:address":"1845 N Bristol St",
    "sg:city":"Tacoma",
    "sg:classifiers":[
        {
            "category":"Professional",
            "subcategory":"Management & Consulting",
            "type":"Services"
        }
    ],
    "sg:phone":"+1 253 759 1424",
    "sg:postcode":"98406",
    "sg:province":"WA",
    "sg:tags":[
        "construction"
    ],
    "wof:name":"C & C General Contractors LLC",
    "wof:placetype":"venue"
},
  "geometry": {"coordinates":[-122.519801,47.268658],"type":"Point"}
}