{
  "type": "Feature",
  "properties": {
    "iso:country":"US",
    "sg:address":"14527 28th Ave NE",
    "sg:city":"Seattle",
    "sg:classifiers":[
        {
            "category":"Professional",
            "type":"Services"
        }
    ],
    "sg:phone":"+1 206 367 8352",
    "sg:postcode":"98155",
    "sg:province":"WA",
    "wof:name":"Sandra L Sato",
    "wof:placetype":"venue"
},
  "geometry": {"coordinates":[-122.297974,47.73536],"type":"Point"}
}