{
  "type": "Feature",
  "properties": {
    "addr:full":"2902 W Chestnut Ave Yakima WA 98902",
    "addr:housenumber":"2902",
    "addr:postcode":"98902",
    "addr:street":"W Chestnut Ave",
    "iso:country":"US",
    "sg:address":"2902 W Chestnut Ave",
    "sg:city":"Yakima",
    "sg:classifiers":[
        {
            "category":"Professional",
            "subcategory":"Detective & Security Services",
            "type":"Services"
        }
    ],
    "sg:phone":"+1 509 249 0028",
    "sg:postcode":"98902",
    "sg:province":"WA",
    "sg:tags":[
        "guard"
    ],
    "wof:name":"Erin M Sigler",
    "wof:placetype":"venue"
},
  "geometry": {"coordinates":[-120.54876,46.59624],"type":"Point"}
}