{
  "type": "Feature",
  "properties": {
    "addr:full":"13328 Dreger Rd E Wilbur WA 99185",
    "addr:housenumber":"13328",
    "addr:postcode":"99185",
    "addr:street":"Dreger Rd E Wilbur",
    "iso:country":"US",
    "sg:address":"13328 Dreger Rd E",
    "sg:city":"Wilbur",
    "sg:phone":"+1 509 647 5784",
    "sg:postcode":"99185",
    "sg:province":"WA",
    "sg:tags":[
        "wheat",
        "beef",
        "farm",
        "cash",
        "grain",
        "cattle",
        "feedlot"
    ],
    "wof:name":"William Dreger & Sons",
    "wof:placetype":"venue"
},
  "geometry": {"coordinates":[-118.700616,47.699723],"type":"Point"}
}