{
  "type": "Feature",
  "properties": {
    "addr:full":"210 E Pacific Ave Spokane WA 99202",
    "addr:housenumber":"210",
    "addr:postcode":"99202",
    "addr:street":"E Pacific Ave",
    "iso:country":"US",
    "sg:address":"210 E Pacific Ave",
    "sg:city":"Spokane",
    "sg:classifiers":[
        {
            "category":"Home & Garden",
            "subcategory":"Building Materials",
            "type":"Retail Goods"
        }
    ],
    "sg:phone":"+1 509 456 8801",
    "sg:postcode":"99202",
    "sg:province":"WA",
    "wof:name":"Stained Glass Overlay Desgr GL",
    "wof:placetype":"venue"
},
  "geometry": {"coordinates":[-117.406781,47.655532],"type":"Point"}
}