{
  "type": "Feature",
  "properties": {
    "addr:full":"2200 M Ave Anacortes WA 98221",
    "addr:housenumber":"2200",
    "addr:postcode":"98221",
    "addr:street":"M Ave",
    "iso:country":"US",
    "sg:address":"2200 M Ave",
    "sg:city":"Anacortes",
    "sg:classifiers":[
        {
            "category":"Education",
            "subcategory":"School",
            "type":"Public Place"
        }
    ],
    "sg:phone":"+1 360 293 3149",
    "sg:postcode":"98221",
    "sg:province":"WA",
    "sg:tags":[
        "elementary"
    ],
    "sg:website":"http://www.ams.asd103.org",
    "wof:name":"Island View Elementary School",
    "wof:placetype":"venue"
},
  "geometry": {"coordinates":[-122.61743199999999,48.504539],"type":"Point"}
}