{
  "type": "Feature",
  "properties": {
    "addr:full":"14124 83rd Pl NE Bothell WA 98011",
    "addr:housenumber":"14124",
    "addr:postcode":"98011",
    "addr:street":"83Rd Pl Ne",
    "iso:country":"US",
    "sg:address":"14124 83rd Pl NE",
    "sg:city":"Bothell",
    "sg:classifiers":[
        {
            "category":"Insurance",
            "subcategory":"Insurance Agent",
            "type":"Services"
        }
    ],
    "sg:phone":"+1 425 823 5507",
    "sg:postcode":"98011",
    "sg:province":"WA",
    "sg:tags":[
        "adjuster"
    ],
    "wof:name":"Express Health Claims",
    "wof:placetype":"venue"
},
  "geometry": {"coordinates":[-122.22989099999999,47.728227],"type":"Point"}
}