{
  "type": "Feature",
  "properties": {
    "addr:full":"3328 NE 3rd Ave Camas WA 98607",
    "addr:housenumber":"3328",
    "addr:postcode":"98607",
    "addr:street":"Ne 3Rd Ave",
    "iso:country":"US",
    "sg:address":"3328 NE 3rd Ave",
    "sg:city":"Camas",
    "sg:classifiers":[
        {
            "category":"Wholesale",
            "subcategory":"Medical Equipment & Supplies",
            "type":"Manufacturing & Wholesale Goods"
        },
        {
            "category":"Shopping",
            "subcategory":"Pharmacy",
            "type":"Retail Goods"
        }
    ],
    "sg:phone":"+1 360 835 7577",
    "sg:postcode":"98607",
    "sg:province":"WA",
    "sg:tags":[
        "health",
        "aid",
        "home",
        "care",
        "drugstore",
        "first"
    ],
    "sg:website":"http://www.walgreens.com",
    "wof:name":"Walgreen Drug Stores",
    "wof:placetype":"venue"
},
  "geometry": {"coordinates":[-122.37015700000001,45.585237],"type":"Point"}
}