{
  "type": "Feature",
  "properties": {
    "addr:full":"29507 32nd Pl S Auburn WA 98001",
    "addr:housenumber":"29507",
    "addr:postcode":"98001",
    "addr:street":"32Nd Pl S",
    "iso:country":"US",
    "sg:address":"29507 32nd Pl S",
    "sg:city":"Auburn",
    "sg:classifiers":[
        {
            "category":"Building & Trades",
            "subcategory":"Construction",
            "type":"Services"
        }
    ],
    "sg:phone":"+1 253 839 6832",
    "sg:postcode":"98001",
    "sg:province":"WA",
    "sg:tags":[
        "wallcoverings-installation",
        "wallpaper",
        "painting",
        "contractor"
    ],
    "wof:name":"Faux Pro",
    "wof:placetype":"venue"
},
  "geometry": {"coordinates":[-122.291521,47.337728],"type":"Point"}
}