{
  "type": "Feature",
  "properties": {
    "addr:full":"921 S Peabody St Port Angeles WA 98362",
    "addr:housenumber":"921",
    "addr:postcode":"98362",
    "addr:street":"S Peabody St",
    "iso:country":"US",
    "sg:address":"921 S Peabody St",
    "sg:city":"Port Angeles",
    "sg:classifiers":[
        {
            "category":"Shopping",
            "subcategory":"Bicycles & Sporting Goods",
            "type":"Retail Goods"
        }
    ],
    "sg:phone":"+1 360 452 2029",
    "sg:postcode":"98362",
    "sg:province":"WA",
    "wof:name":"Bucks Tackle & Mfg",
    "wof:placetype":"venue"
},
  "geometry": {"coordinates":[-123.43445,48.109638],"type":"Point"}
}