{
  "type": "Feature",
  "properties": {
    "iso:country":"US",
    "sg:address":"125 SW 12th Cir",
    "sg:city":"Battle Ground",
    "sg:classifiers":[
        {
            "category":"Recreation",
            "type":"Entertainment"
        }
    ],
    "sg:phone":"+1 360 687 2643",
    "sg:postcode":"98604",
    "sg:province":"WA",
    "sg:tags":[
        "club",
        "membership"
    ],
    "wof:name":"Fc Vancouver Soccer Club",
    "wof:placetype":"venue"
},
  "geometry": {"coordinates":[-122.538398,45.771592],"type":"Point"}
}