{
  "type": "Feature",
  "properties": {
    "iso:country":"US",
    "sg:address":"101 W 8th Ave",
    "sg:city":"Spokane",
    "sg:classifiers":[
        {
            "category":"Health Services",
            "subcategory":"Health Practitioner",
            "type":"Services"
        },
        {
            "category":"Health Services",
            "subcategory":"Doctor",
            "type":"Services"
        }
    ],
    "sg:phone":"+1 509 474 4922",
    "sg:postcode":"99204",
    "sg:province":"WA",
    "sg:tags":[
        "physician",
        "surgeon",
        "psychologist"
    ],
    "wof:name":"Spokane Radiation Oncology",
    "wof:placetype":"venue"
},
  "geometry": {"coordinates":[-117.411562,47.648106],"type":"Point"}
}