{
  "type": "Feature",
  "properties": {
    "addr:full":"410 N 62nd Ave Yakima WA 98908",
    "addr:housenumber":"410",
    "addr:postcode":"98908",
    "addr:street":"N 62Nd Ave",
    "iso:country":"US",
    "sg:address":"410 N 62nd Ave",
    "sg:city":"Yakima",
    "sg:classifiers":[
        {
            "category":"Professional",
            "subcategory":"Accounting & Tax Preparation",
            "type":"Services"
        }
    ],
    "sg:phone":"+1 509 966 9196",
    "sg:postcode":"98908",
    "sg:province":"WA",
    "sg:tags":[
        "bookkeeping"
    ],
    "wof:name":"Affil Accounting",
    "wof:placetype":"venue"
},
  "geometry": {"coordinates":[-120.59192,46.605127],"type":"Point"}
}