{
  "type": "Feature",
  "properties": {
    "addr:full":"15030 Bothell Way NE Lake Forest Park WA 98155",
    "addr:housenumber":"15030",
    "addr:postcode":"98155",
    "addr:street":"Bothell Way Ne;Park",
    "iso:country":"US",
    "sg:address":"15030 Bothell Way NE",
    "sg:city":"Lake Forest Park",
    "sg:classifiers":[
        {
            "category":"Restaurant",
            "type":"Food & Drink"
        }
    ],
    "sg:phone":"+1 206 362 7427",
    "sg:postcode":"98155",
    "sg:province":"WA",
    "sg:tags":[
        "barbeque"
    ],
    "sg:website":"www.raininribsbbq.com/",
    "wof:name":"Rainin Ribs BBQ & Smokehouse",
    "wof:placetype":"venue"
},
  "geometry": {"coordinates":[-122.28996600000001,47.738634],"type":"Point"}
}