{
  "type": "Feature",
  "properties": {
    "iso:country":"US",
    "sg:address":"1880 Birch Bay Lynden Rd",
    "sg:city":"Ferndale",
    "sg:classifiers":[
        {
            "category":"Farming",
            "subcategory":"Farm",
            "type":"Manufacturing & Wholesale Goods"
        }
    ],
    "sg:phone":"+1 360 366 5931",
    "sg:postcode":"98248",
    "sg:province":"WA",
    "sg:tags":[
        "crop",
        "general"
    ],
    "wof:name":"Smit Farm",
    "wof:placetype":"venue"
},
  "geometry": {"coordinates":[-122.581726,48.935457],"type":"Point"}
}