{
  "type": "Feature",
  "properties": {
    "addr:full":"5210 NE 56th Ave Vancouver WA 98661",
    "addr:housenumber":"5210",
    "addr:postcode":"98661",
    "addr:street":"Ne 56Th Ave",
    "iso:country":"US",
    "sg:address":"5210 NE 56th Ave",
    "sg:city":"Vancouver",
    "sg:classifiers":[
        {
            "category":"Professional",
            "subcategory":"Engineering",
            "type":"Services"
        }
    ],
    "sg:phone":"+1 360 696 2249",
    "sg:postcode":"98661",
    "sg:province":"WA",
    "wof:name":"Hawkins Engineering Intl",
    "wof:placetype":"venue"
},
  "geometry": {"coordinates":[-122.614541,45.659771],"type":"Point"}
}