{
  "type": "Feature",
  "properties": {
    "addr:full":"11210 Woodland Ave E Puyallup WA 98373",
    "addr:housenumber":"11210",
    "addr:postcode":"98373",
    "addr:street":"Woodland Ave E",
    "iso:country":"US",
    "sg:address":"11210 Woodland Ave E",
    "sg:city":"Puyallup",
    "sg:classifiers":[
        {
            "category":"Building & Trades",
            "subcategory":"Construction",
            "type":"Services"
        }
    ],
    "sg:phone":"+1 253 840 1849",
    "sg:postcode":"98373",
    "sg:province":"WA",
    "sg:tags":[
        "house"
    ],
    "wof:name":"Hi-Line Homes",
    "wof:placetype":"venue"
},
  "geometry": {"coordinates":[-122.336175,47.153602],"type":"Point"}
}