{
  "type": "Feature",
  "properties": {
    "addr:full":"905 124th St S Tacoma WA 98444",
    "addr:housenumber":"905",
    "addr:postcode":"98444",
    "addr:street":"124Th St S",
    "iso:country":"US",
    "sg:address":"905 124th St S",
    "sg:city":"Tacoma",
    "sg:classifiers":[
        {
            "category":"Education",
            "subcategory":"College",
            "type":"Public Place"
        }
    ],
    "sg:phone":"+1 253 535 7350",
    "sg:postcode":"98444",
    "sg:province":"WA",
    "sg:tags":[
        "academic",
        "school"
    ],
    "sg:website":"www.plu.edu",
    "wof:name":"Athletic Dept",
    "wof:placetype":"venue"
},
  "geometry": {"coordinates":[-122.444717,47.144168],"type":"Point"}
}