{
  "type": "Feature",
  "properties": {
    "iso:country":"US",
    "sg:address":"21503 Poplar Way",
    "sg:city":"Lynnwood",
    "sg:classifiers":[
        {
            "category":"Building & Trades",
            "subcategory":"Construction",
            "type":"Services"
        }
    ],
    "sg:phone":"+1 425 771 3377",
    "sg:postcode":"98036",
    "sg:province":"WA",
    "sg:tags":[
        "house"
    ],
    "wof:name":"Sather Construction",
    "wof:placetype":"venue"
},
  "geometry": {"coordinates":[-122.272284,47.804294],"type":"Point"}
}