{
  "type": "Feature",
  "properties": {
    "addr:full":"1622 46th Ave SW Seattle WA 98116",
    "addr:housenumber":"1622",
    "addr:postcode":"98116",
    "addr:street":"46Th Ave Sw",
    "iso:country":"US",
    "sg:address":"1622 46th Ave SW",
    "sg:city":"Seattle",
    "sg:classifiers":[
        {
            "category":"Professional",
            "subcategory":"Advertising",
            "type":"Services"
        }
    ],
    "sg:phone":"+1 206 933 8823",
    "sg:postcode":"98116",
    "sg:province":"WA",
    "sg:tags":[
        "agency"
    ],
    "sg:website":"http://www.chuckpennington.com",
    "wof:name":"Pennington",
    "wof:placetype":"venue"
},
  "geometry": {"coordinates":[-122.390291,47.589083],"type":"Point"}
}