{
  "type": "Feature",
  "properties": {
    "addr:full":"1505 Pike Pl Seattle WA 98101",
    "addr:housenumber":"1505",
    "addr:postcode":"98101",
    "addr:street":"Pike Pl",
    "iso:country":"US",
    "sg:address":"1505 Pike Pl",
    "sg:city":"Seattle",
    "sg:classifiers":[
        {
            "category":"Restaurant",
            "type":"Food & Drink"
        }
    ],
    "sg:phone":"+1 206 223 1848",
    "sg:postcode":"98101",
    "sg:province":"WA",
    "sg:tags":[
        "delicatessen"
    ],
    "wof:name":"Dish D'Lish",
    "wof:placetype":"venue"
},
  "geometry": {"coordinates":[-122.340658,47.608656],"type":"Point"}
}