{
  "type": "Feature",
  "properties": {
    "addr:full":"3301 Clerf Rd Ellensburg WA 98926",
    "addr:housenumber":"3301",
    "addr:postcode":"98926",
    "addr:street":"Clerf Rd",
    "iso:country":"US",
    "sg:address":"3301 Clerf Rd",
    "sg:city":"Ellensburg",
    "sg:classifiers":[
        {
            "category":"Restaurant",
            "type":"Food & Drink"
        }
    ],
    "sg:phone":"+1 509 968 4482",
    "sg:postcode":"98926",
    "sg:province":"WA",
    "sg:tags":[
        "house",
        "steak",
        "barbecue"
    ],
    "wof:name":"Rodeo City Bbq",
    "wof:placetype":"venue"
},
  "geometry": {"coordinates":[-120.37321799999999,46.985766],"type":"Point"}
}