{
  "type": "Feature",
  "properties": {
    "addr:full":"30307 Mountain Loop Hwy Granite Falls WA 98252",
    "addr:housenumber":"30307",
    "addr:postcode":"98252",
    "addr:street":"Mountain Loop Hwy",
    "iso:country":"US",
    "sg:address":"30307 Mountain Loop Hwy",
    "sg:city":"Granite Falls",
    "sg:classifiers":[
        {
            "category":"Retail",
            "subcategory":"Repair Shop",
            "type":"Services"
        }
    ],
    "sg:phone":"+1 360 691 7350",
    "sg:postcode":"98252",
    "sg:province":"WA",
    "wof:name":"Final Touch Uphl & Design",
    "wof:placetype":"venue"
},
  "geometry": {"coordinates":[-121.823312,48.102259],"type":"Point"}
}