{
  "type": "Feature",
  "properties": {
    "addr:full":"3609 S Lincoln Dr Spokane WA 99203",
    "addr:housenumber":"3609",
    "addr:postcode":"99203",
    "addr:street":"S Lincoln Dr",
    "iso:country":"US",
    "sg:address":"3609 S Lincoln Dr",
    "sg:city":"Spokane",
    "sg:classifiers":[
        {
            "category":"Government",
            "subcategory":"Office",
            "type":"Public Place"
        }
    ],
    "sg:phone":"+1 509 838 4301",
    "sg:postcode":"99203",
    "sg:province":"WA",
    "sg:tags":[
        "development",
        "real estate",
        "developer"
    ],
    "wof:name":"Erickson Development Co L",
    "wof:placetype":"venue"
},
  "geometry": {"coordinates":[-117.41793800000001,47.62162],"type":"Point"}
}