{
  "type": "Feature",
  "properties": {
    "iso:country":"US",
    "sg:address":"6132 State Rte 20",
    "sg:city":"Port Townsend",
    "sg:classifiers":[
        {
            "category":"Building & Trades",
            "subcategory":"Construction",
            "type":"Services"
        }
    ],
    "sg:phone":"+1 360 385 4335",
    "sg:postcode":"98368",
    "sg:province":"WA",
    "sg:tags":[
        "residential"
    ],
    "wof:name":"Rons Construction",
    "wof:placetype":"venue"
},
  "geometry": {"coordinates":[-122.819728,48.046084],"type":"Point"}
}