{
  "type": "Feature",
  "properties": {
    "addr:full":"14900 Interurban Ave S Ste 271 Seattle WA 98168",
    "addr:housenumber":"14900",
    "addr:postcode":"98168",
    "addr:street":"Interurban Ave S Ste 271",
    "iso:country":"US",
    "sg:address":"14900 Interurban Ave S Ste 271",
    "sg:city":"Seattle",
    "sg:classifiers":[
        {
            "category":"Communications",
            "type":"Services"
        },
        {
            "category":"Professional",
            "subcategory":"Computer Services",
            "type":"Services"
        }
    ],
    "sg:phone":"+1 877 387 4824",
    "sg:postcode":"98168",
    "sg:province":"WA",
    "sg:tags":[
        "repair",
        "design",
        "web"
    ],
    "sg:website":"www.ets4tech.com/index.php",
    "wof:name":"Executive Technology Services, Inc.",
    "wof:placetype":"venue"
},
  "geometry": {"coordinates":[-122.252432,47.469042],"type":"Point"}
}