{
  "type": "Feature",
  "properties": {
    "addr:full":"2120 State Ave NE Olympia WA 98506",
    "addr:housenumber":"2120",
    "addr:postcode":"98506",
    "addr:street":"State Ave Ne",
    "iso:country":"US",
    "sg:address":"2120 State Ave NE",
    "sg:city":"Olympia",
    "sg:classifiers":[
        {
            "category":"Health Services",
            "subcategory":"Clinic",
            "type":"Services"
        },
        {
            "category":"Social Services",
            "subcategory":"Job Training",
            "type":"Services"
        }
    ],
    "sg:phone":"+1 360 943 5512",
    "sg:postcode":"98506",
    "sg:province":"WA",
    "sg:tags":[
        "rehabilitation",
        "outpatient",
        "specialty"
    ],
    "wof:name":"Rehabilitation Evaluation Ctr",
    "wof:placetype":"venue"
},
  "geometry": {"coordinates":[-122.87189100000001,47.046945],"type":"Point"}
}