{
  "type": "Feature",
  "properties": {
    "addr:full":"5950 S 180th St Seattle WA 98188",
    "addr:housenumber":"5950",
    "addr:postcode":"98188",
    "addr:street":"S 180Th St",
    "iso:country":"US",
    "sg:address":"5950 S 180th St",
    "sg:city":"Seattle",
    "sg:classifiers":[
        {
            "category":"Home & Garden",
            "subcategory":"Furniture",
            "type":"Retail Goods"
        }
    ],
    "sg:phone":"+1 206 575 0811",
    "sg:postcode":"98188",
    "sg:province":"WA",
    "wof:name":"Sansaco Home Furnishings",
    "wof:placetype":"venue"
},
  "geometry": {"coordinates":[-122.259351,47.441476],"type":"Point"}
}