{
  "type": "Feature",
  "properties": {
    "addr:full":"2836 78th Ave SE Unit 401 Mercer Island WA 98040",
    "addr:housenumber":"2836;401",
    "addr:postcode":"98040",
    "addr:street":"78Th Ave Se Unit",
    "iso:country":"US",
    "sg:address":"2836 78th Ave SE Unit 401",
    "sg:city":"Mercer Island",
    "sg:classifiers":[
        {
            "category":"Real Estate",
            "subcategory":"Real Estate Operator",
            "type":"Services"
        }
    ],
    "sg:phone":"+1 206 230 0238",
    "sg:postcode":"98040",
    "sg:province":"WA",
    "sg:tags":[
        "apartment"
    ],
    "wof:name":"Avellino Development Co Llc",
    "wof:placetype":"venue"
},
  "geometry": {"coordinates":[-122.233403,47.585079],"type":"Point"}
}