{
  "type": "Feature",
  "properties": {
    "addr:full":"400 Pine Street Seattle WA 98101",
    "addr:housenumber":"400",
    "addr:postcode":"98101",
    "addr:street":"Pine Street",
    "iso:country":"US",
    "sg:address":"400 Pine Street",
    "sg:city":"Seattle",
    "sg:classifiers":[
        {
            "category":"Arts & Performance",
            "subcategory":"Art Gallery",
            "type":"Entertainment"
        },
        {
            "category":"Shopping",
            "subcategory":"Crafts & Fabrics",
            "type":"Retail Goods"
        }
    ],
    "sg:phone":"+1 206 682 6462",
    "sg:postcode":"98101",
    "sg:province":"WA",
    "wof:name":"Fire Works Gallery",
    "wof:placetype":"venue"
},
  "geometry": {"coordinates":[-122.33758899999999,47.611271],"type":"Point"}
}