{
  "type": "Feature",
  "properties": {
    "addr:full":"2326 228th St SE Bothell WA 98021",
    "addr:housenumber":"2326",
    "addr:postcode":"98021",
    "addr:street":"228Th St Se",
    "iso:country":"US",
    "sg:address":"2326 228th St SE",
    "sg:city":"Bothell",
    "sg:classifiers":[
        {
            "category":"Professional",
            "subcategory":"Computer Services",
            "type":"Services"
        },
        {
            "category":"Communications",
            "type":"Services"
        },
        {
            "category":"Communications",
            "subcategory":"Television Station",
            "type":"Services"
        }
    ],
    "sg:phone":"+1 866 310 4761",
    "sg:postcode":"98021",
    "sg:province":"WA",
    "sg:tags":[
        "satellite",
        "cable",
        "tv",
        "isp",
        "system",
        "equipment",
        "internet",
        "provider"
    ],
    "sg:website":"http://www.directsattv.com/directv/?tfid=ypm",
    "wof:name":"Direct Sat TV - An Authorized DIRECTV Dealer",
    "wof:placetype":"venue"
},
  "geometry": {"coordinates":[-122.201734,47.791311],"type":"Point"}
}