{
  "type": "Feature",
  "properties": {
    "addr:full":"20610 NE 29th Ave Ridgefield WA 98642",
    "addr:housenumber":"20610",
    "addr:postcode":"98642",
    "addr:street":"Ne 29Th Ave",
    "iso:country":"US",
    "sg:address":"20610 NE 29th Ave",
    "sg:city":"Ridgefield",
    "sg:phone":"+1 360 887 4673",
    "sg:postcode":"98642",
    "sg:province":"WA",
    "sg:tags":[
        "farm",
        "soybean"
    ],
    "wof:name":"Hills Dell Unlimited",
    "wof:placetype":"venue"
},
  "geometry": {"coordinates":[-122.64111800000001,45.771824],"type":"Point"}
}