{
  "type": "Feature",
  "properties": {
    "addr:full":"6373 N Villier Rd Nine Mile Falls WA 99026",
    "addr:housenumber":"6373",
    "addr:postcode":"99026",
    "addr:street":"N Villier Rd",
    "iso:country":"US",
    "sg:address":"6373 N Villier Rd",
    "sg:city":"Nine Mile Falls",
    "sg:classifiers":[
        {
            "category":"Professional",
            "subcategory":"Computer Services",
            "type":"Services"
        }
    ],
    "sg:phone":"+1 509 276 9760",
    "sg:postcode":"99026",
    "sg:province":"WA",
    "sg:tags":[
        "prepackaged",
        "software"
    ],
    "wof:name":"Rse Software Inc",
    "wof:placetype":"venue"
},
  "geometry": {"coordinates":[-117.643034,47.837876],"type":"Point"}
}