{
  "type": "Feature",
  "properties": {
    "addr:full":"6201 22nd Ave NW Apt 4 Seattle WA 98107",
    "addr:housenumber":"6201;4",
    "addr:postcode":"98107",
    "addr:street":"22Nd Ave Nw Apt",
    "iso:country":"US",
    "sg:address":"6201 22nd Ave NW Apt 4",
    "sg:city":"Seattle",
    "sg:classifiers":[
        {
            "category":"Building & Trades",
            "subcategory":"Construction",
            "type":"Services"
        }
    ],
    "sg:phone":"+1 206 257 8352",
    "sg:postcode":"98107",
    "sg:province":"WA",
    "sg:tags":[
        "wallcoverings-installation",
        "wallpaper",
        "painting",
        "contractor"
    ],
    "wof:name":"Fouche Painting",
    "wof:placetype":"venue"
},
  "geometry": {"coordinates":[-122.384773,47.67382],"type":"Point"}
}