{
  "type": "Feature",
  "properties": {
    "addr:full":"3933 Balsam Ave NE Olympia WA 98506",
    "addr:housenumber":"3933",
    "addr:postcode":"98506",
    "addr:street":"Balsam Ave Ne",
    "iso:country":"US",
    "sg:address":"3933 Balsam Ave NE",
    "sg:city":"Olympia",
    "sg:classifiers":[
        {
            "category":"Building & Trades",
            "subcategory":"Plumbing",
            "type":"Services"
        }
    ],
    "sg:phone":"+1 360 923 1080",
    "sg:postcode":"98506",
    "sg:province":"WA",
    "sg:tags":[
        "tank",
        "septic"
    ],
    "wof:name":"Net Septic",
    "wof:placetype":"venue"
},
  "geometry": {"coordinates":[-122.83669,47.054984],"type":"Point"}
}