{
  "type": "Feature",
  "properties": {
    "addr:full":"1811 Baker Way Kelso WA 98626",
    "addr:housenumber":"1811",
    "addr:postcode":"98626",
    "addr:street":"Baker Way",
    "iso:country":"US",
    "sg:address":"1811 Baker Way",
    "sg:city":"Kelso",
    "sg:classifiers":[
        {
            "category":"Home & Garden",
            "subcategory":"Furniture",
            "type":"Retail Goods"
        }
    ],
    "sg:phone":"+1 360 578 9396",
    "sg:postcode":"98626",
    "sg:province":"WA",
    "sg:tags":[
        "cabinet",
        "kitchen"
    ],
    "wof:name":"Kitchen Broker LTD",
    "wof:placetype":"venue"
},
  "geometry": {"coordinates":[-122.894026,46.120841],"type":"Point"}
}