{
  "type": "Feature",
  "properties": {
    "addr:full":"8209 Ravenna Ave NE Seattle WA 98115",
    "addr:housenumber":"8209",
    "addr:postcode":"98115",
    "addr:street":"Ravenna Ave Ne",
    "iso:country":"US",
    "sg:address":"8209 Ravenna Ave NE",
    "sg:city":"Seattle",
    "sg:classifiers":[
        {
            "category":"Professional",
            "type":"Services"
        }
    ],
    "sg:phone":"+1 206 522 5648",
    "sg:postcode":"98115",
    "sg:province":"WA",
    "wof:name":"Brian Keith Lorette",
    "wof:placetype":"venue"
},
  "geometry": {"coordinates":[-122.301559,47.689408],"type":"Point"}
}