{
  "type": "Feature",
  "properties": {
    "addr:full":"76 S Washington St Seattle WA 98104",
    "addr:housenumber":"76",
    "addr:postcode":"98104",
    "addr:street":"S Washington St",
    "iso:country":"US",
    "sg:address":"76 S Washington St",
    "sg:city":"Seattle",
    "sg:classifiers":[
        {
            "category":"Real Estate",
            "subcategory":"Real Estate Agent",
            "type":"Services"
        }
    ],
    "sg:phone":"+1 206 915 5060",
    "sg:postcode":"98104",
    "sg:province":"WA",
    "sg:tags":[
        "investment"
    ],
    "wof:name":"Alastar Inc",
    "wof:placetype":"venue"
},
  "geometry": {"coordinates":[-122.33467400000001,47.600958],"type":"Point"}
}