{
  "type": "Feature",
  "properties": {
    "addr:full":"222 Park Ln Kirkland WA 98033",
    "addr:housenumber":"222",
    "addr:postcode":"98033",
    "addr:street":"Park Ln",
    "iso:country":"US",
    "sg:address":"222 Park Ln",
    "sg:city":"Kirkland",
    "sg:classifiers":[
        {
            "category":"Professional",
            "type":"Services"
        }
    ],
    "sg:phone":"+1 425 828 6657",
    "sg:postcode":"98033",
    "sg:province":"WA",
    "wof:name":"Articles LLC",
    "wof:placetype":"venue"
},
  "geometry": {"coordinates":[-122.203667,47.676518],"type":"Point"}
}