{
  "type": "Feature",
  "properties": {
    "addr:full":"1917 Cole St Enumclaw WA 98022",
    "addr:housenumber":"1917",
    "addr:postcode":"98022",
    "addr:street":"Cole St",
    "iso:country":"US",
    "sg:address":"1917 Cole St",
    "sg:city":"Enumclaw",
    "sg:classifiers":[
        {
            "category":"Personal",
            "subcategory":"Beauty Salon",
            "type":"Services"
        }
    ],
    "sg:phone":"+1 360 825 4175",
    "sg:postcode":"98022",
    "sg:province":"WA",
    "wof:name":"Event Fx",
    "wof:placetype":"venue"
},
  "geometry": {"coordinates":[-121.98760299999999,47.205653],"type":"Point"}
}