{
  "type": "Feature",
  "properties": {
    "addr:full":"32 Silverpine Dr Ste 106 Bremerton WA 98311",
    "addr:housenumber":"32",
    "addr:postcode":"98311",
    "addr:street":"Silverpine Dr Ste 106",
    "iso:country":"US",
    "sg:address":"32 Silverpine Dr Ste 106",
    "sg:city":"Bremerton",
    "sg:classifiers":[
        {
            "category":"Personal",
            "subcategory":"Beauty Salon",
            "type":"Services"
        }
    ],
    "sg:phone":"+1 360 308 8796",
    "sg:postcode":"98311",
    "sg:province":"WA",
    "sg:tags":[
        "hair"
    ],
    "wof:name":"Shear Elegance",
    "wof:placetype":"venue"
},
  "geometry": {"coordinates":[-122.159497,47.483585],"type":"Point"}
}