{
  "type": "Feature",
  "properties": {
    "addr:full":"627 S 37th St Washougal WA 98671",
    "addr:housenumber":"627",
    "addr:postcode":"98671",
    "addr:street":"S 37Th St",
    "iso:country":"US",
    "sg:address":"627 S 37th St",
    "sg:city":"Washougal",
    "sg:classifiers":[
        {
            "category":"Manufacturing",
            "subcategory":"Rubber & Plastics",
            "type":"Manufacturing & Wholesale Goods"
        }
    ],
    "sg:phone":"+1 360 835 8523",
    "sg:postcode":"98671",
    "sg:province":"WA",
    "sg:tags":[
        "product",
        "piping",
        "mfg"
    ],
    "wof:name":"Advanced Drainage Systems",
    "wof:placetype":"venue"
},
  "geometry": {"coordinates":[-122.32983299999999,45.565214],"type":"Point"}
}