{
  "type": "Feature",
  "properties": {
    "addr:full":"1600 Mt Baker Pl NE Renton WA 98059",
    "addr:housenumber":"1600",
    "addr:postcode":"98059",
    "addr:street":"Mt Baker Pl Ne",
    "iso:country":"US",
    "sg:address":"1600 Mt Baker Pl NE",
    "sg:city":"Renton",
    "sg:classifiers":[
        {
            "category":"Professional",
            "subcategory":"Advertising",
            "type":"Services"
        },
        {
            "category":"Manufacturing",
            "subcategory":"Signs",
            "type":"Manufacturing & Wholesale Goods"
        }
    ],
    "sg:phone":"+1 425 572 6178",
    "sg:postcode":"98059",
    "sg:province":"WA",
    "sg:tags":[
        "specialty"
    ],
    "sg:website":"http://www.qcgraphicsllc.com",
    "wof:name":"Qc Grachics &",
    "wof:placetype":"venue"
},
  "geometry": {"coordinates":[-122.144318,47.50634],"type":"Point"}
}