{
  "type": "Feature",
  "properties": {
    "addr:full":"3681 Estes Rd Pullman WA 99163",
    "addr:housenumber":"3681",
    "addr:postcode":"99163",
    "addr:street":"Estes Rd",
    "iso:country":"US",
    "sg:address":"3681 Estes Rd",
    "sg:city":"Pullman",
    "sg:phone":"+1 509 872 2205",
    "sg:postcode":"99163",
    "sg:province":"WA",
    "sg:tags":[
        "beef",
        "farm",
        "crop",
        "field",
        "cattle",
        "feedlot"
    ],
    "wof:name":"Roy Nunn",
    "wof:placetype":"venue"
},
  "geometry": {"coordinates":[-117.05462199999999,46.799594],"type":"Point"}
}