{
  "type": "Feature",
  "properties": {
    "addr:full":"12715 240th St NE Arlington WA 98223",
    "addr:housenumber":"12715",
    "addr:postcode":"98223",
    "addr:street":"240Th St Ne",
    "iso:country":"US",
    "sg:address":"12715 240th St NE",
    "sg:city":"Arlington",
    "sg:classifiers":[
        {
            "category":"Manufacturing",
            "subcategory":"Wood Products",
            "type":"Manufacturing & Wholesale Goods"
        }
    ],
    "sg:phone":"+1 360 435 6062",
    "sg:postcode":"98223",
    "sg:province":"WA",
    "sg:tags":[
        "mfg"
    ],
    "wof:name":"Whitt Charlie Wood Carving",
    "wof:placetype":"venue"
},
  "geometry": {"coordinates":[-122.052837,48.212872],"type":"Point"}
}