{
  "type": "Feature",
  "properties": {
    "iso:country":"US",
    "sg:address":"228 Chapman Rd",
    "sg:city":"Castle Rock",
    "sg:classifiers":[
        {
            "category":"Real Estate",
            "subcategory":"Real Estate Agent",
            "type":"Services"
        }
    ],
    "sg:phone":"+1 360 274 4721",
    "sg:postcode":"98611",
    "sg:province":"WA",
    "wof:name":"Edgewater Mobile Estates",
    "wof:placetype":"venue"
},
  "geometry": {"coordinates":[-122.920558,46.307723],"type":"Point"}
}