{
  "type": "Feature",
  "properties": {
    "iso:country":"US",
    "sg:address":"201 NE Park Plaza Dr",
    "sg:city":"Vancouver",
    "sg:classifiers":[
        {
            "category":"Professional",
            "subcategory":"Research",
            "type":"Services"
        }
    ],
    "sg:phone":"+1 360 750 0300",
    "sg:postcode":"98684",
    "sg:province":"WA",
    "sg:tags":[
        "foundation",
        "philanthropic"
    ],
    "wof:name":"Lematta Foundation",
    "wof:placetype":"venue"
},
  "geometry": {"coordinates":[-122.53898,45.621265],"type":"Point"}
}