{
  "type": "Feature",
  "properties": {
    "addr:full":"1212 N Washington St Spokane WA 99201",
    "addr:housenumber":"1212",
    "addr:postcode":"99201",
    "addr:street":"N Washington St",
    "iso:country":"US",
    "sg:address":"1212 N Washington St",
    "sg:city":"Spokane",
    "sg:classifiers":[
        {
            "category":"Professional",
            "subcategory":"Engineering",
            "type":"Services"
        },
        {
            "category":"Internet Cafe",
            "subcategory":"None",
            "type":"Food & Drink"
        },
        {
            "category":"Professional",
            "subcategory":"Computer Services",
            "type":"Services"
        }
    ],
    "sg:phone":"+1 509 326 4500",
    "sg:postcode":"99201",
    "sg:province":"WA",
    "sg:tags":[
        "product",
        "designer",
        "consultant",
        "system",
        "integration",
        "software",
        "engineer"
    ],
    "sg:website":"http://www.hitechnique.com/EXPERT-HELP",
    "wof:name":"Hitechnique",
    "wof:placetype":"venue"
},
  "geometry": {"coordinates":[-117.417321,47.668233],"type":"Point"}
}