{
  "type": "Feature",
  "properties": {
    "addr:full":"4402 B St NW Auburn WA 98001",
    "addr:housenumber":"4402",
    "addr:postcode":"98001",
    "addr:street":"B St Nw",
    "iso:country":"US",
    "sg:address":"4402 B St NW",
    "sg:city":"Auburn",
    "sg:classifiers":[
        {
            "category":"Wholesale",
            "subcategory":"Machinery & Supplies",
            "type":"Manufacturing & Wholesale Goods"
        },
        {
            "category":"Wholesale",
            "subcategory":"Construction Materials",
            "type":"Manufacturing & Wholesale Goods"
        },
        {
            "category":"Retail",
            "subcategory":"Storage",
            "type":"Services"
        }
    ],
    "sg:phone":"+1 253 813 0770",
    "sg:postcode":"98001",
    "sg:province":"WA",
    "sg:tags":[
        "pallet",
        "equipment",
        "handling",
        "container",
        "skid"
    ],
    "sg:website":"http://www.rainierpallet.com",
    "wof:name":"Rainier Pallet & Crating Corp",
    "wof:placetype":"venue"
},
  "geometry": {"coordinates":[-122.23235099999999,47.347067],"type":"Point"}
}