{
  "type": "Feature",
  "properties": {
    "addr:full":"898 Valentine Ave SE Pacific WA 98047",
    "addr:housenumber":"898",
    "addr:postcode":"98047",
    "addr:street":"Valentine Ave Se",
    "iso:country":"US",
    "sg:address":"898 Valentine Ave SE",
    "sg:city":"Pacific",
    "sg:classifiers":[
        {
            "category":"Manufacturing",
            "subcategory":"Tools & Machinery",
            "type":"Manufacturing & Wholesale Goods"
        },
        {
            "category":"Home & Garden",
            "subcategory":"Hardware",
            "type":"Retail Goods"
        }
    ],
    "sg:phone":"+1 253 863 0106",
    "sg:postcode":"98047",
    "sg:province":"WA",
    "sg:tags":[
        "nut",
        "fasteners-industrial",
        "bolt"
    ],
    "wof:name":"Quest Fastener & Industrial Supply, Inc.",
    "wof:placetype":"venue"
},
  "geometry": {"coordinates":[-122.248751,47.252751],"type":"Point"}
}