{
  "type": "Feature",
  "properties": {
    "addr:full":"4730 Colby Ave Everett WA 98203",
    "addr:housenumber":"4730",
    "addr:postcode":"98203",
    "addr:street":"Colby Ave",
    "iso:country":"US",
    "sg:address":"4730 Colby Ave",
    "sg:city":"Everett",
    "sg:classifiers":[
        {
            "category":"Education",
            "subcategory":"School",
            "type":"Public Place"
        }
    ],
    "sg:phone":"+1 425 385 4000",
    "sg:postcode":"98203",
    "sg:province":"WA",
    "wof:name":"Everett Administrative & Sprt",
    "wof:placetype":"venue"
},
  "geometry": {"coordinates":[-122.207393,47.954172],"type":"Point"}
}