{
  "type": "Feature",
  "properties": {
    "iso:country":"US",
    "sg:address":"2808 Butler Creek Rd",
    "sg:city":"Sedro Woolley",
    "sg:classifiers":[
        {
            "category":"Manufacturing",
            "subcategory":"Musical Instruments",
            "type":"Manufacturing & Wholesale Goods"
        }
    ],
    "sg:phone":"+1 360 724 7016",
    "sg:postcode":"98284",
    "sg:province":"WA",
    "sg:tags":[
        "mfg"
    ],
    "wof:name":"Rogers Music",
    "wof:placetype":"venue"
},
  "geometry": {"coordinates":[-122.31974200000001,48.606176],"type":"Point"}
}