{
  "type": "Feature",
  "properties": {
    "addr:full":"9100 5th Ave NE Seattle WA 98115",
    "addr:housenumber":"9100",
    "addr:postcode":"98115",
    "addr:street":"5Th Ave Ne",
    "iso:country":"US",
    "sg:address":"9100 5th Ave NE",
    "sg:city":"Seattle",
    "sg:classifiers":[
        {
            "category":"Education",
            "subcategory":"Special Training",
            "type":"Public Place"
        }
    ],
    "sg:phone":"+1 206 526 2662",
    "sg:postcode":"98115",
    "sg:province":"WA",
    "sg:tags":[
        "school",
        "language"
    ],
    "sg:website":"www.learninglanguageclinic.org/W...",
    "wof:name":"Learning & Language Clinic",
    "wof:placetype":"venue"
},
  "geometry": {"coordinates":[-122.322998,47.695],"type":"Point"}
}