{
  "type": "Feature",
  "properties": {
    "addr:full":"2069 Main Street Ferndale WA 98248",
    "addr:housenumber":"2069",
    "addr:postcode":"98248",
    "addr:street":"Main Street",
    "iso:country":"US",
    "sg:address":"2069 Main Street",
    "sg:city":"Ferndale",
    "sg:classifiers":[
        {
            "category":"Professional",
            "subcategory":"Computer Services",
            "type":"Services"
        }
    ],
    "sg:phone":"+1 360 746 0485",
    "sg:postcode":"98248",
    "sg:province":"WA",
    "sg:tags":[
        "personal-seo",
        "reputation-management",
        "search-engine-optimization",
        "marketing",
        "brand",
        "personal"
    ],
    "sg:website":"http://www.peoplepond.com",
    "wof:name":"PeoplePond",
    "wof:placetype":"venue"
},
  "geometry": {"coordinates":[-122.593,48.847252],"type":"Point"}
}