{
  "type": "Feature",
  "properties": {
    "addr:full":"5631 Tacoma Mall Blvd Tacoma WA 98409",
    "addr:housenumber":"5631",
    "addr:postcode":"98409",
    "addr:street":"Tacoma Mall Blvd",
    "iso:country":"US",
    "sg:address":"5631 Tacoma Mall Blvd",
    "sg:city":"Tacoma",
    "sg:classifiers":[
        {
            "category":"Organizations",
            "subcategory":"Professional Association",
            "type":"Services"
        }
    ],
    "sg:phone":"+1 253 396 0131",
    "sg:postcode":"98409",
    "sg:province":"WA",
    "wof:name":"Evergreen Building Prod Assn",
    "wof:placetype":"venue"
},
  "geometry": {"coordinates":[-122.463909,47.204682],"type":"Point"}
}