{
  "type": "Feature",
  "properties": {
    "addr:full":"16113 NE 29th Ave Ridgefield WA 98642",
    "addr:housenumber":"16113",
    "addr:postcode":"98642",
    "addr:street":"Ne 29Th Ave",
    "iso:country":"US",
    "sg:address":"16113 NE 29th Ave",
    "sg:city":"Ridgefield",
    "sg:classifiers":[
        {
            "category":"Professional",
            "subcategory":"Business Services",
            "type":"Services"
        }
    ],
    "sg:phone":"+1 360 546 5891",
    "sg:postcode":"98642",
    "sg:province":"WA",
    "sg:tags":[
        "medical"
    ],
    "wof:name":"Derma Vive Skincare",
    "wof:placetype":"venue"
},
  "geometry": {"coordinates":[-122.640957,45.738519],"type":"Point"}
}