{
  "type": "Feature",
  "properties": {
    "addr:full":"5804 204th St SW Lynnwood WA 98036",
    "addr:housenumber":"5804",
    "addr:postcode":"98036",
    "addr:street":"204Th St Sw",
    "iso:country":"US",
    "sg:address":"5804 204th St SW",
    "sg:city":"Lynnwood",
    "sg:classifiers":[
        {
            "category":"Wholesale",
            "subcategory":"Non-durable Goods",
            "type":"Manufacturing & Wholesale Goods"
        }
    ],
    "sg:phone":"+1 425 678 4983",
    "sg:postcode":"98036",
    "sg:province":"WA",
    "sg:tags":[
        "dry",
        "goods-wholesale"
    ],
    "wof:name":"Convoy Supply Inc",
    "wof:placetype":"venue"
},
  "geometry": {"coordinates":[-122.311413,47.813855],"type":"Point"}
}