{
  "type": "Feature",
  "properties": {
    "addr:full":"1210 132nd St SE Bothell WA 98012",
    "addr:housenumber":"1210",
    "addr:postcode":"98012",
    "addr:street":"132Nd St Se",
    "iso:country":"US",
    "sg:address":"1210 132nd St SE",
    "sg:city":"Bothell",
    "sg:classifiers":[
        {
            "category":"Organizations",
            "subcategory":"Religious Organization",
            "type":"Services"
        }
    ],
    "sg:phone":"+1 425 338 7845",
    "sg:postcode":"98012",
    "sg:province":"WA",
    "sg:tags":[
        "child",
        "day",
        "care"
    ],
    "wof:name":"Cedar Cross Untd Mthdst Church",
    "wof:placetype":"venue"
},
  "geometry": {"coordinates":[-122.216815,47.878411],"type":"Point"}
}