{
  "type": "Feature",
  "properties": {
    "addr:full":"209 N Bend Blvd N North Bend WA 98045",
    "addr:housenumber":"209",
    "addr:postcode":"98045",
    "addr:street":"N Bend Blvd N",
    "iso:country":"US",
    "sg:address":"209 N Bend Blvd N",
    "sg:city":"North Bend",
    "sg:classifiers":[
        {
            "category":"Wholesale",
            "subcategory":"Hardware",
            "type":"Manufacturing & Wholesale Goods"
        }
    ],
    "sg:phone":"+1 425 831 6800",
    "sg:postcode":"98045",
    "sg:province":"WA",
    "sg:tags":[
        "furnace"
    ],
    "wof:name":"A & E Heating Inc",
    "wof:placetype":"venue"
},
  "geometry": {"coordinates":[-121.787452,47.494984],"type":"Point"}
}