{
  "type": "Feature",
  "properties": {
    "iso:country":"US",
    "sg:address":"2001 N Walnut St",
    "sg:city":"Ellensburg",
    "sg:classifiers":[
        {
            "category":"Professional",
            "subcategory":"Management & Consulting",
            "type":"Services"
        }
    ],
    "sg:phone":"+1 509 899 4603",
    "sg:postcode":"98926",
    "sg:province":"WA",
    "sg:tags":[
        "public",
        "relations"
    ],
    "wof:name":"Ackerman Associates",
    "wof:placetype":"venue"
},
  "geometry": {"coordinates":[-120.539706,47.011424],"type":"Point"}
}