{
  "type": "Feature",
  "properties": {
    "addr:full":"1528 7th Ave Seattle WA 98101",
    "addr:housenumber":"1528",
    "addr:postcode":"98101",
    "addr:street":"7Th Ave",
    "iso:country":"US",
    "sg:address":"1528 7th Ave",
    "sg:city":"Seattle",
    "sg:classifiers":[
        {
            "category":"Sports & Exercise",
            "subcategory":"Gym",
            "type":"Entertainment"
        }
    ],
    "sg:phone":"+1 206 382 1344",
    "sg:postcode":"98101",
    "sg:province":"WA",
    "sg:tags":[
        "fitness",
        "physical",
        "facility"
    ],
    "wof:name":"Reini Essential Skin Care & Sp",
    "wof:placetype":"venue"
},
  "geometry": {"coordinates":[-122.333977,47.612301],"type":"Point"}
}