{
  "type": "Feature",
  "properties": {
    "addr:full":"2856 80th Ave SE Mercer Island WA 98040",
    "addr:housenumber":"2856",
    "addr:postcode":"98040",
    "addr:street":"80Th Ave Se",
    "iso:country":"US",
    "sg:address":"2856 80th Ave SE",
    "sg:city":"Mercer Island",
    "sg:classifiers":[
        {
            "category":"Wholesale",
            "subcategory":"Construction Materials",
            "type":"Manufacturing & Wholesale Goods"
        }
    ],
    "sg:phone":"+1 206 236 7544",
    "sg:postcode":"98040",
    "sg:province":"WA",
    "sg:tags":[
        "building",
        "stone"
    ],
    "wof:name":"Natural Stone & Tile Co Inc",
    "wof:placetype":"venue"
},
  "geometry": {"coordinates":[-122.231672,47.584192],"type":"Point"}
}