{
  "type": "Feature",
  "properties": {
    "addr:full":"1717 Old Milton Hwy Walla Walla WA 99362",
    "addr:housenumber":"1717",
    "addr:postcode":"99362",
    "addr:street":"Old Milton Hwy",
    "iso:country":"US",
    "sg:address":"1717 Old Milton Hwy",
    "sg:city":"Walla Walla",
    "sg:classifiers":[
        {
            "category":"Professional",
            "subcategory":"Business Services",
            "type":"Services"
        }
    ],
    "sg:phone":"+1 509 522 9419",
    "sg:postcode":"99362",
    "sg:province":"WA",
    "sg:tags":[
        "interior",
        "residential",
        "design",
        "commercial"
    ],
    "wof:name":"DGS Interiors",
    "wof:placetype":"venue"
},
  "geometry": {"coordinates":[-118.368439,46.023986],"type":"Point"}
}