{
  "type": "Feature",
  "properties": {
    "addr:full":"3965 Evanston Ave N Seattle WA 98103",
    "addr:housenumber":"3965",
    "addr:postcode":"98103",
    "addr:street":"Evanston Ave N",
    "iso:country":"US",
    "sg:address":"3965 Evanston Ave N",
    "sg:city":"Seattle",
    "sg:classifiers":[
        {
            "category":"Professional",
            "subcategory":"Business Services",
            "type":"Services"
        }
    ],
    "sg:phone":"+1 206 634 2872",
    "sg:postcode":"98103",
    "sg:province":"WA",
    "sg:tags":[
        "commercial",
        "designers-industrial"
    ],
    "wof:name":"Brent Evan Markee",
    "wof:placetype":"venue"
},
  "geometry": {"coordinates":[-122.351181,47.655143],"type":"Point"}
}