{
  "type": "Feature",
  "properties": {
    "addr:full":"710 9th Ave Seattle WA 98104",
    "addr:housenumber":"710",
    "addr:postcode":"98104",
    "addr:street":"9Th Ave",
    "iso:country":"US",
    "sg:address":"710 9th Ave",
    "sg:city":"Seattle",
    "sg:classifiers":[
        {
            "category":"Professional",
            "subcategory":"Lawyer & Legal Services",
            "type":"Services"
        }
    ],
    "sg:phone":"+1 206 682 0610",
    "sg:postcode":"98104",
    "sg:province":"WA",
    "wof:name":"Dalton John T",
    "wof:placetype":"venue"
},
  "geometry": {"coordinates":[-122.325996,47.6068],"type":"Point"}
}