{
  "type": "Feature",
  "properties": {
    "addr:full":"7351 E Green Lake Dr N Seattle WA 98115",
    "addr:housenumber":"7351",
    "addr:postcode":"98115",
    "addr:street":"E Green Lake Dr N",
    "iso:country":"US",
    "sg:address":"7351 E Green Lake Dr N",
    "sg:city":"Seattle",
    "sg:classifiers":[
        {
            "category":"Government",
            "subcategory":"Office",
            "type":"Public Place"
        }
    ],
    "sg:phone":"+1 206 527 0171",
    "sg:postcode":"98115",
    "sg:province":"WA",
    "sg:tags":[
        "charter",
        "yard",
        "store",
        "village",
        "rental",
        "boat"
    ],
    "sg:website":"www.goodsport.net",
    "wof:name":"Greenlake Boat Rentals",
    "wof:placetype":"venue"
},
  "geometry": {"coordinates":[-122.327003,47.6814],"type":"Point"}
}