{
  "type": "Feature",
  "properties": {
    "addr:full":"1319 O Ave Anacortes WA 98221",
    "addr:housenumber":"1319",
    "addr:postcode":"98221",
    "addr:street":"O Ave",
    "iso:country":"US",
    "sg:address":"1319 O Ave",
    "sg:city":"Anacortes",
    "sg:classifiers":[
        {
            "category":"Retail",
            "subcategory":"Auto Repair",
            "type":"Services"
        }
    ],
    "sg:phone":"+1 360 299 1270",
    "sg:postcode":"98221",
    "sg:province":"WA",
    "sg:tags":[
        "automotive",
        "automobile",
        "lubrication"
    ],
    "wof:name":"Fidalgo Bay Express Lube",
    "wof:placetype":"venue"
},
  "geometry": {"coordinates":[-122.614059,48.511648],"type":"Point"}
}