{
  "type": "Feature",
  "properties": {
    "addr:full":"13713 50th Ave W Edmonds WA 98026",
    "addr:housenumber":"13713",
    "addr:postcode":"98026",
    "addr:street":"50Th Ave W",
    "iso:country":"US",
    "sg:address":"13713 50th Ave W",
    "sg:city":"Edmonds",
    "sg:classifiers":[
        {
            "category":"Retail",
            "subcategory":"Portrait Studio",
            "type":"Services"
        }
    ],
    "sg:phone":"+1 425 745 8286",
    "sg:postcode":"98026",
    "sg:province":"WA",
    "sg:tags":[
        "photo"
    ],
    "wof:name":"Silver Fox Studios",
    "wof:placetype":"venue"
},
  "geometry": {"coordinates":[-122.301666,47.872953],"type":"Point"}
}