{
  "type": "Feature",
  "properties": {
    "addr:full":"Good Shepherd Ctr 4649 Sunnyside Ave N 4th Fl Seattle WA 98103",
    "addr:housenumber":"4649",
    "addr:postcode":"98103",
    "addr:street":"Sunnyside Ave N 4Th",
    "iso:country":"US",
    "sg:address":"Good Shepherd Ctr 4649 Sunnyside Ave N 4th Fl",
    "sg:city":"Seattle",
    "sg:classifiers":[
        {
            "category":"Arts & Performance",
            "subcategory":"Music",
            "type":"Entertainment"
        }
    ],
    "sg:phone":"+1 206 789 1939",
    "sg:postcode":"98103",
    "sg:province":"WA",
    "sg:tags":[
        "venue"
    ],
    "sg:website":"chapelspace.blogspot.com/",
    "wof:name":"Chapel Performance Space",
    "wof:placetype":"venue"
},
  "geometry": {"coordinates":[-122.330167,47.663269],"type":"Point"}
}