{
  "type": "Feature",
  "properties": {
    "addr:full":"4562 167th Ave SE Issaquah WA 98027",
    "addr:housenumber":"4562",
    "addr:postcode":"98027",
    "addr:street":"167Th Ave Se",
    "iso:country":"US",
    "sg:address":"4562 167th Ave SE",
    "sg:city":"Issaquah",
    "sg:classifiers":[
        {
            "category":"Farming",
            "subcategory":"Fish & Marine Products",
            "type":"Manufacturing & Wholesale Goods"
        }
    ],
    "sg:phone":"+1 425 643 9185",
    "sg:postcode":"98027",
    "sg:province":"WA",
    "sg:tags":[
        "actuary"
    ],
    "wof:name":"Actuaries Northwest",
    "wof:placetype":"venue"
},
  "geometry": {"coordinates":[-122.117272,47.563385],"type":"Point"}
}