{
  "type": "Feature",
  "properties": {
    "addr:full":"1251 17th Ave E Seattle WA 98112",
    "addr:housenumber":"1251",
    "addr:postcode":"98112",
    "addr:street":"17Th Ave E",
    "iso:country":"US",
    "sg:address":"1251 17th Ave E",
    "sg:city":"Seattle",
    "sg:classifiers":[
        {
            "category":"Building & Trades",
            "subcategory":"Landscaping Services",
            "type":"Services"
        }
    ],
    "sg:phone":"+1 206 328 3202",
    "sg:postcode":"98112",
    "sg:province":"WA",
    "wof:name":"Katzman Madelyn Gardening",
    "wof:placetype":"venue"
},
  "geometry": {"coordinates":[-122.309972,47.632035],"type":"Point"}
}