{
  "type": "Feature",
  "properties": {
    "addr:full":"11086 Rhody Dr Port Hadlock WA 98339",
    "addr:housenumber":"11086",
    "addr:postcode":"98339",
    "addr:street":"Rhody Dr",
    "iso:country":"US",
    "sg:address":"11086 Rhody Dr",
    "sg:city":"Port Hadlock",
    "sg:classifiers":[
        {
            "category":"Organizations",
            "subcategory":"Non-profit Organization",
            "type":"Services"
        }
    ],
    "sg:phone":"+1 360 385 4855",
    "sg:postcode":"98339",
    "sg:province":"WA",
    "sg:tags":[
        "information",
        "alcoholism",
        "treatment"
    ],
    "wof:name":"Turning Point Recovery",
    "wof:placetype":"venue"
},
  "geometry": {"coordinates":[-122.78360600000001,48.035031],"type":"Point"}
}