{
  "type": "Feature",
  "properties": {
    "addr:full":"3519 Black Lake Blvd SW Tumwater WA 98512",
    "addr:housenumber":"3519",
    "addr:postcode":"98512",
    "addr:street":"Black Lake Blvd Sw",
    "iso:country":"US",
    "sg:address":"3519 Black Lake Blvd SW",
    "sg:city":"Tumwater",
    "sg:classifiers":[
        {
            "category":"Personal",
            "type":"Services"
        },
        {
            "category":"Retail",
            "subcategory":"Auto Rental",
            "type":"Services"
        }
    ],
    "sg:phone":"+1 800 468 4285",
    "sg:postcode":"98512",
    "sg:province":"WA",
    "sg:tags":[
        "mover",
        "truck"
    ],
    "wof:name":"U-Haul Co.",
    "wof:placetype":"venue"
},
  "geometry": {"coordinates":[-122.961755,47.014336],"type":"Point"}
}