{
  "type": "Feature",
  "properties": {
    "addr:full":"1101 Jerome Ave Yakima WA 98902",
    "addr:housenumber":"1101",
    "addr:postcode":"98902",
    "addr:street":"Jerome Ave",
    "iso:country":"US",
    "sg:address":"1101 Jerome Ave",
    "sg:city":"Yakima",
    "sg:classifiers":[
        {
            "category":"Education",
            "subcategory":"Special Training",
            "type":"Public Place"
        }
    ],
    "sg:phone":"+1 509 576 9740",
    "sg:postcode":"98902",
    "sg:province":"WA",
    "sg:tags":[
        "educational"
    ],
    "wof:name":"Robert Briceno Ed Svc",
    "wof:placetype":"venue"
},
  "geometry": {"coordinates":[-120.522719,46.608872],"type":"Point"}
}