{
  "type": "Feature",
  "properties": {
    "addr:full":"3399 E Harbor Rd Langley WA 98260",
    "addr:housenumber":"3399 e",
    "addr:postcode":"98260",
    "addr:street":"Harbor Rd",
    "iso:country":"US",
    "sg:address":"3399 E Harbor Rd",
    "sg:city":"Langley",
    "sg:classifiers":[
        {
            "category":"Wholesale",
            "subcategory":"Construction Materials",
            "type":"Manufacturing & Wholesale Goods"
        }
    ],
    "sg:phone":"+1 360 730 2056",
    "sg:postcode":"98260",
    "sg:province":"WA",
    "wof:name":"Island Lumber Mill",
    "wof:placetype":"venue"
},
  "geometry": {"coordinates":[-122.517307,48.087717],"type":"Point"}
}