{
  "type": "Feature",
  "properties": {
    "iso:country":"US",
    "sg:address":"301 W Poplar St",
    "sg:city":"Walla Walla",
    "sg:classifiers":[
        {
            "category":"Health Services",
            "subcategory":"Doctor",
            "type":"Services"
        }
    ],
    "sg:phone":"+1 509 525 1084",
    "sg:postcode":"99362",
    "sg:province":"WA",
    "sg:tags":[
        "medical"
    ],
    "wof:name":"Falcon Jennings C II",
    "wof:placetype":"venue"
},
  "geometry": {"coordinates":[-118.341854,46.063449],"type":"Point"}
}