{
  "type": "Feature",
  "properties": {
    "iso:country":"US",
    "sg:address":"521 Laurel St",
    "sg:city":"Shelton",
    "sg:classifiers":[
        {
            "category":"Building & Trades",
            "subcategory":"Construction",
            "type":"Services"
        }
    ],
    "sg:phone":"+1 360 427 4501",
    "sg:postcode":"98584",
    "sg:province":"WA",
    "sg:tags":[
        "tile",
        "dealer",
        "contractor"
    ],
    "wof:name":"Free Lance Ceramic Tile Design",
    "wof:placetype":"venue"
},
  "geometry": {"coordinates":[-123.104975,47.217892],"type":"Point"}
}