{
  "type": "Feature",
  "properties": {
    "addr:full":"158 SW 148th St Burien WA 98166",
    "addr:housenumber":"158",
    "addr:postcode":"98166",
    "addr:street":"Sw 148Th St",
    "iso:country":"US",
    "sg:address":"158 SW 148th St",
    "sg:city":"Burien",
    "sg:classifiers":[
        {
            "category":"Shopping",
            "subcategory":"Clothing, Apparel, & Fashions",
            "type":"Retail Goods"
        }
    ],
    "sg:phone":"+1 206 243 7472",
    "sg:postcode":"98166",
    "sg:province":"WA",
    "sg:tags":[
        "accessory",
        "clothing",
        "women's"
    ],
    "sg:website":"fashionbug.charmingshoppes.com",
    "wof:name":"Fashion Bug",
    "wof:placetype":"venue"
},
  "geometry": {"coordinates":[-122.335999,47.4706],"type":"Point"}
}