{
  "type": "Feature",
  "properties": {
    "addr:full":"724 Ericksen Avenue NE Bainbridge Island WA 98110",
    "addr:housenumber":"724",
    "addr:postcode":"98110",
    "addr:street":"Ericksen Avenue Ne",
    "iso:country":"US",
    "sg:address":"724 Ericksen Avenue NE",
    "sg:city":"Bainbridge Island",
    "sg:classifiers":[
        {
            "category":"Real Estate",
            "subcategory":"Architect",
            "type":"Services"
        }
    ],
    "sg:phone":"+1 206 842 1613",
    "sg:postcode":"98110",
    "sg:province":"WA",
    "sg:website":"www.kdgarchitecture.com",
    "wof:name":"Kdg Arcitechure PS",
    "wof:placetype":"venue"
},
  "geometry": {"coordinates":[-122.51698500000001,47.630603],"type":"Point"}
}