{
  "type": "Feature",
  "properties": {
    "addr:full":"241 Riverside Ave Winthrop WA 98862",
    "addr:housenumber":"241",
    "addr:postcode":"98862",
    "addr:street":"Riverside Ave",
    "iso:country":"US",
    "sg:address":"241 Riverside Ave",
    "sg:city":"Winthrop",
    "sg:classifiers":[
        {
            "category":"Shopping",
            "subcategory":"Gifts & Souvenirs",
            "type":"Retail Goods"
        }
    ],
    "sg:phone":"+1 509 996 3500",
    "sg:postcode":"98862",
    "sg:province":"WA",
    "sg:tags":[
        "shop"
    ],
    "wof:name":"White Buck Trading Co",
    "wof:placetype":"venue"
},
  "geometry": {"coordinates":[-120.18242100000001,48.476202],"type":"Point"}
}