{
  "type": "Feature",
  "properties": {
    "addr:full":"601 N 34th St Ste C Seattle WA 98103",
    "addr:housenumber":"601",
    "addr:postcode":"98103",
    "addr:street":"N 34Th St Ste C",
    "iso:country":"US",
    "sg:address":"601 N 34th St Ste C",
    "sg:city":"Seattle",
    "sg:classifiers":[
        {
            "category":"Health Services",
            "subcategory":"Doctor",
            "type":"Services"
        },
        {
            "category":"Personal",
            "subcategory":"Hair Removal",
            "type":"Services"
        },
        {
            "category":"Personal",
            "subcategory":"Day Spa",
            "type":"Services"
        }
    ],
    "sg:phone":"+1 206 467 1000",
    "sg:postcode":"98103",
    "sg:province":"WA",
    "sg:tags":[
        "surgeon",
        "cosmetic",
        "dermatologist"
    ],
    "sg:website":"www.agelessinseattle.com",
    "wof:name":"Ageless",
    "wof:placetype":"venue"
},
  "geometry": {"coordinates":[-122.35055199999999,47.649612],"type":"Point"}
}