{
  "type": "Feature",
  "properties": {
    "addr:full":"22 Hemlock Y Rd Carson WA 98610",
    "addr:housenumber":"22",
    "addr:postcode":"98610",
    "addr:street":"Hemlock Y Rd",
    "iso:country":"US",
    "sg:address":"22 Hemlock Y Rd",
    "sg:city":"Carson",
    "sg:classifiers":[
        {
            "category":"Food & Beverages",
            "subcategory":"Groceries & Convenience Stores",
            "type":"Retail Goods"
        }
    ],
    "sg:phone":"+1 509 427 2717",
    "sg:postcode":"98610",
    "sg:province":"WA",
    "wof:name":"Stabler Country Store",
    "wof:placetype":"venue"
},
  "geometry": {"coordinates":[-121.90836299999999,45.807874],"type":"Point"}
}