{
  "type": "Feature",
  "properties": {
    "addr:full":"1605 116th Ave NE Bellevue WA 98004",
    "addr:housenumber":"1605",
    "addr:postcode":"98004",
    "addr:street":"116Th Ave Ne",
    "iso:country":"US",
    "sg:address":"1605 116th Ave NE",
    "sg:city":"Bellevue",
    "sg:classifiers":[
        {
            "category":"Professional",
            "subcategory":"Employment Agencies",
            "type":"Services"
        }
    ],
    "sg:phone":"+1 425 646 0905",
    "sg:postcode":"98004",
    "sg:province":"WA",
    "sg:tags":[
        "consultant",
        "search",
        "executive"
    ],
    "wof:name":"Black & Deering",
    "wof:placetype":"venue"
},
  "geometry": {"coordinates":[-122.185742,47.624619],"type":"Point"}
}