{
  "type": "Feature",
  "properties": {
    "addr:full":"1629 Queen Anne Ave. N #100 Seattle WA 98109",
    "addr:housenumber":"1629",
    "addr:postcode":"98109",
    "addr:street":"Queen Anne Ave. N # 100",
    "iso:country":"US",
    "sg:address":"1629 Queen Anne Ave. N #100",
    "sg:city":"Seattle",
    "sg:classifiers":[
        {
            "category":"Shopping",
            "subcategory":"Clothing, Apparel, & Fashions",
            "type":"Retail Goods"
        }
    ],
    "sg:phone":"+1 206 285 2184",
    "sg:postcode":"98109",
    "sg:province":"WA",
    "sg:tags":[
        "clothing",
        "women's"
    ],
    "sg:website":"www.skookumclothing.com",
    "wof:name":"Skookum Clothing Northwest",
    "wof:placetype":"venue"
},
  "geometry": {"coordinates":[-122.35674899999999,47.618614],"type":"Point"}
}