{
  "type": "Feature",
  "properties": {
    "addr:full":"4250 Fremont Ave N Seattle WA 98103",
    "addr:housenumber":"4250",
    "addr:postcode":"98103",
    "addr:street":"Fremont Ave N",
    "iso:country":"US",
    "sg:address":"4250 Fremont Ave N",
    "sg:city":"Seattle",
    "sg:classifiers":[
        {
            "category":"Shopping",
            "subcategory":"Clothing, Apparel, & Fashions",
            "type":"Retail Goods"
        }
    ],
    "sg:phone":"+1 206 545 8683",
    "sg:postcode":"98103",
    "sg:province":"WA",
    "wof:name":"Northwest Garment & Gear Repr",
    "wof:placetype":"venue"
},
  "geometry": {"coordinates":[-122.34993799999999,47.658742],"type":"Point"}
}