{
  "type": "Feature",
  "properties": {
    "addr:full":"600 Queen Anne Ave N Seattle WA 98109",
    "addr:housenumber":"600",
    "addr:postcode":"98109",
    "addr:street":"Queen Anne Ave N",
    "iso:country":"US",
    "sg:address":"600 Queen Anne Ave N",
    "sg:city":"Seattle",
    "sg:classifiers":[
        {
            "category":"Coffee & Tea",
            "type":"Food & Drink"
        }
    ],
    "sg:phone":"+1 206 282 1549",
    "sg:postcode":"98109",
    "sg:province":"WA",
    "sg:website":"www.caffeladro.com",
    "wof:name":"Caffe Ladro",
    "wof:placetype":"venue"
},
  "geometry": {"coordinates":[-122.35700199999999,47.624802],"type":"Point"}
}