{
  "type": "Feature",
  "properties": {
    "addr:full":"39919 90th Ave E Eatonville WA 98328",
    "addr:housenumber":"39919",
    "addr:postcode":"98328",
    "addr:street":"90Th Ave E",
    "iso:country":"US",
    "sg:address":"39919 90th Ave E",
    "sg:city":"Eatonville",
    "sg:classifiers":[
        {
            "category":"Social Services",
            "subcategory":"Adult Care",
            "type":"Services"
        }
    ],
    "sg:phone":"+1 360 832 3372",
    "sg:postcode":"98328",
    "sg:province":"WA",
    "sg:tags":[
        "home"
    ],
    "wof:name":"Vicki's Care Home",
    "wof:placetype":"venue"
},
  "geometry": {"coordinates":[-122.31359,46.891044],"type":"Point"}
}