{
  "type": "Feature",
  "properties": {
    "addr:full":"12627 SE 276th Pl Kent WA 98030",
    "addr:postcode":"12627;98030",
    "addr:street":"Se 276Th Pl",
    "iso:country":"US",
    "sg:address":"12627 SE 276th Pl",
    "sg:city":"Kent",
    "sg:classifiers":[
        {
            "category":"Professional",
            "subcategory":"Management & Consulting",
            "type":"Services"
        }
    ],
    "sg:phone":"+1 253 813 1466",
    "sg:postcode":"98030",
    "sg:province":"WA",
    "sg:tags":[
        "computer"
    ],
    "wof:name":"Slt",
    "wof:placetype":"venue"
},
  "geometry": {"coordinates":[-122.171628,47.353898],"type":"Point"}
}