{
  "type": "Feature",
  "properties": {
    "addr:full":"902 E 1st St Port Angeles WA 98362",
    "addr:housenumber":"902",
    "addr:postcode":"98362",
    "addr:street":"E 1St St",
    "iso:country":"US",
    "sg:address":"902 E 1st St",
    "sg:city":"Port Angeles",
    "sg:classifiers":[
        {
            "category":"Banks & Credit Unions",
            "subcategory":"Bank",
            "type":"Services"
        }
    ],
    "sg:phone":"+1 360 565 1234",
    "sg:postcode":"98362",
    "sg:province":"WA",
    "sg:tags":[
        "depository",
        "banking"
    ],
    "wof:name":"First Place Postal",
    "wof:placetype":"venue"
},
  "geometry": {"coordinates":[-123.418921,48.112964],"type":"Point"}
}