{
  "type": "Feature",
  "properties": {
    "iso:country":"US",
    "sg:address":"1005 4th St",
    "sg:city":"Anacortes",
    "sg:classifiers":[
        {
            "category":"Bars & Pubs",
            "type":"Food & Drink"
        }
    ],
    "sg:phone":"+1 360 299 2755",
    "sg:postcode":"98221",
    "sg:province":"WA",
    "sg:tags":[
        "lounge",
        "cocktail"
    ],
    "wof:name":"Johnny Picasso's Crmc Lounge",
    "wof:placetype":"venue"
},
  "geometry": {"coordinates":[-122.614018,48.51903],"type":"Point"}
}