{
  "type": "Feature",
  "properties": {
    "addr:full":"9509 Roosevelt Way NE Seattle WA 98115",
    "addr:housenumber":"9509",
    "addr:postcode":"98115",
    "addr:street":"Roosevelt Way Ne",
    "iso:country":"US",
    "sg:address":"9509 Roosevelt Way NE",
    "sg:city":"Seattle",
    "sg:classifiers":[
        {
            "category":"Structure",
            "subcategory":"Office Building",
            "type":"Public Place"
        }
    ],
    "sg:phone":"+1 206 329 1505",
    "sg:postcode":"98115",
    "sg:province":"WA",
    "sg:tags":[
        "park"
    ],
    "wof:name":"Aboretum Properties Inc",
    "wof:placetype":"venue"
},
  "geometry": {"coordinates":[-122.317612,47.697742],"type":"Point"}
}