{
  "type": "Feature",
  "properties": {
    "addr:full":"6505 168th St SW Lynnwood WA 98037",
    "addr:housenumber":"6505",
    "addr:postcode":"98037",
    "addr:street":"168Th St Sw",
    "iso:country":"US",
    "sg:address":"6505 168th St SW",
    "sg:city":"Lynnwood",
    "sg:classifiers":[
        {
            "category":"Education",
            "subcategory":"School",
            "type":"Public Place"
        }
    ],
    "sg:phone":"+1 425 670 7754",
    "sg:postcode":"98037",
    "sg:province":"WA",
    "sg:tags":[
        "elementary"
    ],
    "sg:website":"www.edmonds.wednet.edu",
    "wof:name":"Meadowdale Elementary School",
    "wof:placetype":"venue"
},
  "geometry": {"coordinates":[-122.320999,47.846701],"type":"Point"}
}