{
  "type": "Feature",
  "properties": {
    "addr:full":"155 Paradise Acres Kalama WA 98625",
    "addr:housenumber":"155",
    "addr:postcode":"98625",
    "addr:street":"Paradise Acres Kalama",
    "iso:country":"US",
    "sg:address":"155 Paradise Acres",
    "sg:city":"Kalama",
    "sg:classifiers":[
        {
            "category":"Manufacturing",
            "subcategory":"Lumber",
            "type":"Manufacturing & Wholesale Goods"
        }
    ],
    "sg:phone":"+1 360 673 2312",
    "sg:postcode":"98625",
    "sg:province":"WA",
    "sg:tags":[
        "mill"
    ],
    "wof:name":"Pac Enterprises LLC",
    "wof:placetype":"venue"
},
  "geometry": {"coordinates":[-122.81510400000001,45.989332],"type":"Point"}
}