{
  "type": "Feature",
  "properties": {
    "addr:full":"2617 242nd Pl Ocean Park WA 98640",
    "addr:housenumber":"2617",
    "addr:postcode":"98640",
    "addr:street":"242Nd Pl;Park",
    "iso:country":"US",
    "sg:address":"2617 242nd Pl",
    "sg:city":"Ocean Park",
    "sg:classifiers":[
        {
            "category":"Freight",
            "type":"Transportation"
        }
    ],
    "sg:phone":"+1 360 665 4894",
    "sg:postcode":"98640",
    "sg:province":"WA",
    "sg:tags":[
        "operator",
        "local",
        "trucking"
    ],
    "wof:name":"Chopards Recycling & Hauling",
    "wof:placetype":"venue"
},
  "geometry": {"coordinates":[-124.03888000000001,46.477534],"type":"Point"}
}