{
  "type": "Feature",
  "properties": {
    "addr:full":"22405 Vashon Hwy SW Vashon WA 98070",
    "addr:housenumber":"22405",
    "addr:postcode":"98070",
    "addr:street":"Vashon Hwy Sw",
    "iso:country":"US",
    "sg:address":"22405 Vashon Hwy SW",
    "sg:city":"Vashon",
    "sg:classifiers":[
        {
            "category":"Insurance",
            "subcategory":"Hazard Insurance",
            "type":"Services"
        }
    ],
    "sg:phone":"+1 206 463 6680",
    "sg:postcode":"98070",
    "sg:province":"WA",
    "wof:name":"Du Four Des Champs K",
    "wof:placetype":"venue"
},
  "geometry": {"coordinates":[-122.465828,47.403862],"type":"Point"}
}