{
  "type": "Feature",
  "properties": {
    "iso:country":"US",
    "sg:address":"2720 Clare Ave",
    "sg:city":"Bremerton",
    "sg:classifiers":[
        {
            "category":"Health Services",
            "subcategory":"Doctor",
            "type":"Services"
        }
    ],
    "sg:phone":"+1 360 479 6154",
    "sg:postcode":"98310",
    "sg:province":"WA",
    "sg:tags":[
        "oncologist",
        "hematologist"
    ],
    "wof:name":"Johnson Joseph L",
    "wof:placetype":"venue"
},
  "geometry": {"coordinates":[-122.629109,47.58442],"type":"Point"}
}