{
  "type": "Feature",
  "properties": {
    "addr:full":"201 8th Ave S Edmonds WA 98020",
    "addr:housenumber":"201",
    "addr:postcode":"98020",
    "addr:street":"8Th Ave S",
    "iso:country":"US",
    "sg:address":"201 8th Ave S",
    "sg:city":"Edmonds",
    "sg:classifiers":[
        {
            "category":"Professional",
            "type":"Services"
        }
    ],
    "sg:phone":"+1 425 771 9277",
    "sg:postcode":"98020",
    "sg:province":"WA",
    "wof:name":"Christian F International",
    "wof:placetype":"venue"
},
  "geometry": {"coordinates":[-122.36951500000001,47.808882],"type":"Point"}
}