{
  "type": "Feature",
  "properties": {
    "addr:full":"210 W Broadway Ave Ritzville WA 99169",
    "addr:housenumber":"210",
    "addr:postcode":"99169",
    "addr:street":"W Broadway Ave",
    "iso:country":"US",
    "sg:address":"210 W Broadway Ave",
    "sg:city":"Ritzville",
    "sg:classifiers":[
        {
            "category":"Government",
            "subcategory":"Office",
            "type":"Public Place"
        }
    ],
    "sg:phone":"+1 509 659 3214",
    "sg:postcode":"99169",
    "sg:province":"WA",
    "sg:tags":[
        "agricultural",
        "regulation",
        "marketing"
    ],
    "wof:name":"Wsu Co Op Extension",
    "wof:placetype":"venue"
},
  "geometry": {"coordinates":[-118.382492,47.126855],"type":"Point"}
}