{
  "type": "Feature",
  "properties": {
    "addr:full":"1342 Lum Rd Centralia WA 98531",
    "addr:housenumber":"1342",
    "addr:postcode":"98531",
    "addr:street":"Lum Rd",
    "iso:country":"US",
    "sg:address":"1342 Lum Rd",
    "sg:city":"Centralia",
    "sg:classifiers":[
        {
            "category":"Shopping",
            "subcategory":"Department Store",
            "type":"Retail Goods"
        },
        {
            "category":"Real Estate",
            "subcategory":"Real Estate Operator",
            "type":"Services"
        }
    ],
    "sg:phone":"+1 360 736 3327",
    "sg:postcode":"98531",
    "sg:province":"WA",
    "sg:tags":[
        "building",
        "nonresidential"
    ],
    "wof:name":"Centralia Factory Outlet Ctr",
    "wof:placetype":"venue"
},
  "geometry": {"coordinates":[-122.97754500000001,46.730305],"type":"Point"}
}