{
  "type": "Feature",
  "properties": {
    "addr:full":"8105 Vernon Rd Everett WA 98205",
    "addr:housenumber":"8105",
    "addr:postcode":"98205",
    "addr:street":"Vernon Rd",
    "iso:country":"US",
    "sg:address":"8105 Vernon Rd",
    "sg:city":"Everett",
    "sg:classifiers":[
        {
            "category":"Shopping",
            "subcategory":"Books",
            "type":"Retail Goods"
        }
    ],
    "sg:phone":"+1 425 335 0709",
    "sg:postcode":"98205",
    "sg:province":"WA",
    "wof:name":"Don Quixote Book Store Inc",
    "wof:placetype":"venue"
},
  "geometry": {"coordinates":[-122.116315,48.000266],"type":"Point"}
}