{
  "type": "Feature",
  "properties": {
    "addr:full":"17709 SE 272nd St Kent WA 98042",
    "addr:postcode":"17709;98042",
    "addr:street":"Se 272Nd St",
    "iso:country":"US",
    "sg:address":"17709 SE 272nd St",
    "sg:city":"Kent",
    "sg:classifiers":[
        {
            "category":"Autos & Motor Vehicles",
            "subcategory":"Auto Supplies",
            "type":"Retail Goods"
        }
    ],
    "sg:phone":"+1 253 631 5645",
    "sg:postcode":"98042",
    "sg:province":"WA",
    "wof:name":"Schucks Auto Supply 4349",
    "wof:placetype":"venue"
},
  "geometry": {"coordinates":[-122.10567899999999,47.357986],"type":"Point"}
}