{
  "type": "Feature",
  "properties": {
    "addr:full":"1156 Griffin Ave Enumclaw WA 98022",
    "addr:housenumber":"1156",
    "addr:postcode":"98022",
    "addr:street":"Griffin Ave",
    "iso:country":"US",
    "sg:address":"1156 Griffin Ave",
    "sg:city":"Enumclaw",
    "sg:classifiers":[
        {
            "category":"Banks & Credit Unions",
            "subcategory":"Investment Brokerage",
            "type":"Services"
        }
    ],
    "sg:phone":"+1 360 825 8080",
    "sg:postcode":"98022",
    "sg:province":"WA",
    "sg:tags":[
        "security"
    ],
    "wof:name":"Mike J Holston Mortgage Svcs",
    "wof:placetype":"venue"
},
  "geometry": {"coordinates":[-121.98921300000001,47.203337],"type":"Point"}
}