{
  "type": "Feature",
  "properties": {
    "addr:full":"12810 SE 22nd Pl Bellevue WA 98005",
    "addr:housenumber":"12810",
    "addr:postcode":"98005",
    "addr:street":"Se 22Nd Pl",
    "iso:country":"US",
    "sg:address":"12810 SE 22nd Pl",
    "sg:city":"Bellevue",
    "sg:classifiers":[
        {
            "category":"Professional",
            "subcategory":"Business Services",
            "type":"Services"
        }
    ],
    "sg:phone":"+1 425 641 0410",
    "sg:postcode":"98005",
    "sg:province":"WA",
    "wof:name":"Marty Applequist Interior",
    "wof:placetype":"venue"
},
  "geometry": {"coordinates":[-122.169476,47.590919],"type":"Point"}
}