{
  "type": "Feature",
  "properties": {
    "addr:full":"6204 8th Avenue NW Seattle WA 98107",
    "addr:housenumber":"6204",
    "addr:postcode":"98107",
    "addr:street":"8Th Avenue Nw",
    "iso:country":"US",
    "sg:address":"6204 8th Avenue NW",
    "sg:city":"Seattle",
    "sg:classifiers":[
        {
            "category":"Health Services",
            "subcategory":"Chiropractor",
            "type":"Services"
        }
    ],
    "sg:phone":"+1 206 782 3080",
    "sg:postcode":"98107",
    "sg:province":"WA",
    "wof:name":"Gallegos Sari Nd Lm Lac",
    "wof:placetype":"venue"
},
  "geometry": {"coordinates":[-122.36588500000001,47.674258],"type":"Point"}
}