{
  "type": "Feature",
  "properties": {
    "addr:full":"1420 5th Ave Ste 3010 Seattle WA 98101",
    "addr:housenumber":"1420",
    "addr:postcode":"98101",
    "addr:street":"5Th Ave Ste 3010",
    "iso:country":"US",
    "sg:address":"1420 5th Ave Ste 3010",
    "sg:city":"Seattle",
    "sg:classifiers":[
        {
            "category":"Professional",
            "subcategory":"Lawyer & Legal Services",
            "type":"Services"
        }
    ],
    "sg:phone":"+1 206 622 1711",
    "sg:postcode":"98101",
    "sg:province":"WA",
    "wof:name":"Turetsky Matt",
    "wof:placetype":"venue"
},
  "geometry": {"coordinates":[-122.33485,47.609929],"type":"Point"}
}