{
  "type": "Feature",
  "properties": {
    "addr:full":"5339 Heights Ln NE Olympia WA 98506",
    "addr:housenumber":"5339",
    "addr:postcode":"98506",
    "addr:street":"Heights Ln Ne",
    "iso:country":"US",
    "sg:address":"5339 Heights Ln NE",
    "sg:city":"Olympia",
    "sg:classifiers":[
        {
            "category":"Building & Trades",
            "subcategory":"Cleaning & Sanitation",
            "type":"Services"
        }
    ],
    "sg:phone":"+1 360 943 4377",
    "sg:postcode":"98506",
    "sg:province":"WA",
    "sg:tags":[
        "maintenance"
    ],
    "wof:name":"South Sound Maintenance",
    "wof:placetype":"venue"
},
  "geometry": {"coordinates":[-122.87307699999999,47.114769],"type":"Point"}
}