{
  "type": "Feature",
  "properties": {
    "addr:full":"3849 74th Ave SE Olympia WA 98501",
    "addr:housenumber":"3849",
    "addr:postcode":"98501",
    "addr:street":"74Th Ave Se",
    "iso:country":"US",
    "sg:address":"3849 74th Ave SE",
    "sg:city":"Olympia",
    "sg:classifiers":[
        {
            "category":"Organizations",
            "subcategory":"Religious Organization",
            "type":"Services"
        }
    ],
    "sg:phone":"+1 360 923 1875",
    "sg:postcode":"98501",
    "sg:province":"WA",
    "wof:name":"Olympia Ctr For Spiritual Lrng",
    "wof:placetype":"venue"
},
  "geometry": {"coordinates":[-122.84396599999999,46.97959],"type":"Point"}
}