{
  "type": "Feature",
  "properties": {
    "addr:full":"1554 NE Fairgrounds Rd Bremerton WA 98311",
    "addr:housenumber":"1554",
    "addr:postcode":"98311",
    "addr:street":"Ne Fairgrounds Rd",
    "iso:country":"US",
    "sg:address":"1554 NE Fairgrounds Rd",
    "sg:city":"Bremerton",
    "sg:phone":"+1 360 307 0323",
    "sg:postcode":"98311",
    "sg:province":"WA",
    "sg:website":"http://www.subway.com",
    "wof:name":"Subway",
    "wof:placetype":"venue"
},
  "geometry": {"coordinates":[-122.629541,47.632252],"type":"Point"}
}