{
  "type": "Feature",
  "properties": {
    "addr:full":"325 118th Ave SE Ste 200 Bellevue WA 98005",
    "addr:housenumber":"325",
    "addr:postcode":"98005",
    "addr:street":"118Th Ave Se Ste 200",
    "iso:country":"US",
    "sg:address":"325 118th Ave SE Ste 200",
    "sg:city":"Bellevue",
    "sg:classifiers":[
        {
            "category":"Community Center",
            "subcategory":"Social",
            "type":"Public Place"
        }
    ],
    "sg:phone":"+1 425 882 0838",
    "sg:postcode":"98005",
    "sg:province":"WA",
    "sg:tags":[
        "club"
    ],
    "sg:website":"www.eventsandadventures.com",
    "wof:name":"Events & Adventures",
    "wof:placetype":"venue"
},
  "geometry": {"coordinates":[-122.18389000000001,47.607552],"type":"Point"}
}