{
  "type": "Feature",
  "properties": {
    "addr:full":"17844 110th Ave SE Renton WA 98055",
    "addr:housenumber":"17844",
    "addr:postcode":"98055",
    "addr:street":"110Th Ave Se",
    "iso:country":"US",
    "sg:address":"17844 110th Ave SE",
    "sg:city":"Renton",
    "sg:classifiers":[
        {
            "category":"Professional",
            "type":"Services"
        }
    ],
    "sg:phone":"+1 425 271 0166",
    "sg:postcode":"98055",
    "sg:province":"WA",
    "wof:name":"Self Discovery Unlimited Inc",
    "wof:placetype":"venue"
},
  "geometry": {"coordinates":[-122.19416,47.444643],"type":"Point"}
}