{
  "type": "Feature",
  "properties": {
    "addr:full":"28114 N Newport Hwy Chattaroy WA 99003",
    "addr:housenumber":"28114",
    "addr:postcode":"99003",
    "addr:street":"N Newport Hwy Chattaroy",
    "iso:country":"US",
    "sg:address":"28114 N Newport Hwy",
    "sg:city":"Chattaroy",
    "sg:classifiers":[
        {
            "category":"Personal",
            "subcategory":"Beauty Salon",
            "type":"Services"
        }
    ],
    "sg:phone":"+1 509 238 0200",
    "sg:postcode":"99003",
    "sg:province":"WA",
    "wof:name":"Attitudes Salon",
    "wof:placetype":"venue"
},
  "geometry": {"coordinates":[-117.350131,47.911535],"type":"Point"}
}