{
  "type": "Feature",
  "properties": {
    "addr:full":"16618 35th Street Ct E Sumner WA 98391",
    "addr:housenumber":"16618",
    "addr:postcode":"98391",
    "addr:street":"35Th Street Ct E",
    "iso:country":"US",
    "sg:address":"16618 35th Street Ct E",
    "sg:city":"Sumner",
    "sg:classifiers":[
        {
            "category":"Education",
            "subcategory":"Special Training",
            "type":"Public Place"
        }
    ],
    "sg:phone":"+1 253 862 6883",
    "sg:postcode":"98391",
    "sg:province":"WA",
    "wof:name":"Power Athletics",
    "wof:placetype":"venue"
},
  "geometry": {"coordinates":[-122.207678,47.22477],"type":"Point"}
}