{
  "type": "Feature",
  "properties": {
    "addr:full":"4620 John Luhr Rd NE Olympia WA 98516",
    "addr:housenumber":"4620",
    "addr:postcode":"98516",
    "addr:street":"John Luhr Rd Ne",
    "iso:country":"US",
    "sg:address":"4620 John Luhr Rd NE",
    "sg:city":"Olympia",
    "sg:classifiers":[
        {
            "category":"Social Services",
            "type":"Services"
        }
    ],
    "sg:phone":"+1 360 789 8364",
    "sg:postcode":"98516",
    "sg:province":"WA",
    "sg:tags":[
        "management"
    ],
    "wof:name":"Eldercare Resources",
    "wof:placetype":"venue"
},
  "geometry": {"coordinates":[-122.73077600000001,47.099319],"type":"Point"}
}