{
  "type": "Feature",
  "properties": {
    "iso:country":"US",
    "sg:address":"20119 SE 424th St",
    "sg:city":"Enumclaw",
    "sg:classifiers":[
        {
            "category":"Professional",
            "subcategory":"Business Services",
            "type":"Services"
        }
    ],
    "sg:phone":"+1 360 735 4400",
    "sg:postcode":"98022",
    "sg:province":"WA",
    "wof:name":"Gilded Nest",
    "wof:placetype":"venue"
},
  "geometry": {"coordinates":[-122.073975,47.220968],"type":"Point"}
}