{
  "type": "Feature",
  "properties": {
    "addr:full":"1221 N 16th Ave Yakima WA 98902",
    "addr:housenumber":"1221",
    "addr:postcode":"98902",
    "addr:street":"N 16Th Ave",
    "iso:country":"US",
    "sg:address":"1221 N 16th Ave",
    "sg:city":"Yakima",
    "sg:classifiers":[
        {
            "category":"Health Services",
            "subcategory":"Clinic",
            "type":"Services"
        }
    ],
    "sg:phone":"+1 509 457 8333",
    "sg:postcode":"98902",
    "sg:province":"WA",
    "sg:tags":[
        "dialysis"
    ],
    "sg:website":"www.davita.com",
    "wof:name":"Yakima Dialysis",
    "wof:placetype":"venue"
},
  "geometry": {"coordinates":[-120.530314,46.617808],"type":"Point"}
}