{
  "type": "Feature",
  "properties": {
    "addr:full":"2922 5th Ave W Seattle WA 98119",
    "addr:housenumber":"2922",
    "addr:postcode":"98119",
    "addr:street":"5Th Ave W",
    "iso:country":"US",
    "sg:address":"2922 5th Ave W",
    "sg:city":"Seattle",
    "sg:classifiers":[
        {
            "category":"Professional",
            "type":"Services"
        }
    ],
    "sg:phone":"+1 206 301 9110",
    "sg:postcode":"98119",
    "sg:province":"WA",
    "wof:name":"Cathy A Hern",
    "wof:placetype":"venue"
},
  "geometry": {"coordinates":[-122.363393,47.646459],"type":"Point"}
}