{
  "type": "Feature",
  "properties": {
    "addr:full":"962 Denny Way Seattle WA 98109",
    "addr:housenumber":"962",
    "addr:postcode":"98109",
    "addr:street":"Denny Way",
    "iso:country":"US",
    "sg:address":"962 Denny Way",
    "sg:city":"Seattle",
    "sg:classifiers":[
        {
            "category":"Retail",
            "subcategory":"Auto Repair",
            "type":"Services"
        }
    ],
    "sg:phone":"+1 206 625 9398",
    "sg:postcode":"98109",
    "sg:province":"WA",
    "sg:tags":[
        "body"
    ],
    "wof:name":"Classic Interior Restorations",
    "wof:placetype":"venue"
},
  "geometry": {"coordinates":[-122.337428,47.618605],"type":"Point"}
}