{
  "type": "Feature",
  "properties": {
    "iso:country":"US",
    "sg:address":"652 Industry Dr",
    "sg:city":"Tukwila",
    "sg:classifiers":[
        {
            "category":"Freight",
            "type":"Transportation"
        }
    ],
    "sg:phone":"+1 206 575 0447",
    "sg:postcode":"98188",
    "sg:province":"WA",
    "wof:name":"Breda Transportation Inc Prod",
    "wof:placetype":"venue"
},
  "geometry": {"coordinates":[-122.249263,47.453901],"type":"Point"}
}