{
  "type": "Feature",
  "properties": {
    "iso:country":"US",
    "sg:address":"5300 W Clearwater Ave",
    "sg:city":"Kennewick",
    "sg:classifiers":[
        {
            "category":"Shopping",
            "subcategory":"Bicycles & Sporting Goods",
            "type":"Retail Goods"
        }
    ],
    "sg:phone":"+1 509 783 6772",
    "sg:postcode":"99336",
    "sg:province":"WA",
    "sg:tags":[
        "equipment",
        "skateboard"
    ],
    "wof:name":"Dusty's Ski's & Snowboards",
    "wof:placetype":"venue"
},
  "geometry": {"coordinates":[-119.19293399999999,46.212501],"type":"Point"}
}