{
  "type": "Feature",
  "properties": {
    "addr:full":"1309 NE 199th St Ridgefield WA 98642",
    "addr:housenumber":"1309",
    "addr:postcode":"98642",
    "addr:street":"Ne 199Th St",
    "iso:country":"US",
    "sg:address":"1309 NE 199th St",
    "sg:city":"Ridgefield",
    "sg:classifiers":[
        {
            "category":"Shopping",
            "type":"Retail Goods"
        }
    ],
    "sg:phone":"+1 800 852 0468",
    "sg:postcode":"98642",
    "sg:province":"WA",
    "sg:tags":[
        "awning",
        "canopy"
    ],
    "sg:website":"http://www.pcawning.com",
    "wof:name":"Pacific Coast Awning Co, Inc",
    "wof:placetype":"venue"
},
  "geometry": {"coordinates":[-122.660866,45.765168],"type":"Point"}
}