{
  "type": "Feature",
  "properties": {
    "addr:full":"864 Main St Pomeroy WA 99347",
    "addr:housenumber":"864",
    "addr:postcode":"99347",
    "addr:street":"Main St",
    "iso:country":"US",
    "sg:address":"864 Main St",
    "sg:city":"Pomeroy",
    "sg:classifiers":[
        {
            "category":"Personal",
            "subcategory":"Beauty Salon",
            "type":"Services"
        }
    ],
    "sg:phone":"+1 509 843 3534",
    "sg:postcode":"99347",
    "sg:province":"WA",
    "sg:tags":[
        "shop"
    ],
    "wof:name":"Kathys Hair Port",
    "wof:placetype":"venue"
},
  "geometry": {"coordinates":[-117.59774899999999,46.474282],"type":"Point"}
}