{
  "type": "Feature",
  "properties": {
    "iso:country":"US",
    "sg:address":"22030 20th Ave SE",
    "sg:city":"Bothell",
    "sg:classifiers":[
        {
            "category":"Professional",
            "type":"Services"
        }
    ],
    "sg:phone":"+1 425 482 1108",
    "sg:postcode":"98021",
    "sg:province":"WA",
    "sg:tags":[
        "establishment"
    ],
    "wof:name":"Ekos Corp",
    "wof:placetype":"venue"
},
  "geometry": {"coordinates":[-122.20488,47.796823],"type":"Point"}
}