{
  "type": "Feature",
  "properties": {
    "addr:full":"1100 Dexter Ave N Suite 100 Seattle WA 98109",
    "addr:housenumber":"1100",
    "addr:postcode":"98109",
    "addr:street":"Dexter Ave N Suite 100",
    "iso:country":"US",
    "sg:address":"1100 Dexter Ave N Suite 100",
    "sg:city":"Seattle",
    "sg:classifiers":[
        {
            "category":"Professional",
            "subcategory":"Advertising",
            "type":"Services"
        }
    ],
    "sg:phone":"+1 206 601 3670",
    "sg:postcode":"98109",
    "sg:province":"WA",
    "sg:tags":[
        "real-estate",
        "marketing",
        "commercial",
        "mobile"
    ],
    "sg:website":"http://www.comient.com",
    "wof:name":"Comient",
    "wof:placetype":"venue"
},
  "geometry": {"coordinates":[-122.342232,47.629381],"type":"Point"}
}