{
  "type": "Feature",
  "properties": {
    "addr:full":"1322 1st St Cheney WA 99004",
    "addr:housenumber":"1322",
    "addr:postcode":"99004",
    "addr:street":"1St St",
    "iso:country":"US",
    "sg:address":"1322 1st St",
    "sg:city":"Cheney",
    "sg:classifiers":[
        {
            "category":"Health Services",
            "subcategory":"Chiropractor",
            "type":"Services"
        }
    ],
    "sg:phone":"+1 509 235 8471",
    "sg:postcode":"99004",
    "sg:province":"WA",
    "wof:name":"Chiropractic Center of Cheney",
    "wof:placetype":"venue"
},
  "geometry": {"coordinates":[-117.567494,47.493974],"type":"Point"}
}