{
  "type": "Feature",
  "properties": {
    "addr:full":"613 N 35th St Seattle WA 98103",
    "addr:housenumber":"613",
    "addr:postcode":"98103",
    "addr:street":"N 35Th St",
    "iso:country":"US",
    "sg:address":"613 N 35th St",
    "sg:city":"Seattle",
    "sg:classifiers":[
        {
            "category":"Wholesale",
            "subcategory":"Durable Goods & Equipment",
            "type":"Manufacturing & Wholesale Goods"
        }
    ],
    "sg:phone":"+1 206 633 4455",
    "sg:postcode":"98103",
    "sg:province":"WA",
    "sg:tags":[
        "cleaning",
        "purifying",
        "manufacturer",
        "representative",
        "air"
    ],
    "sg:website":"http://www.davidevans.com",
    "wof:name":"David Evans Co",
    "wof:placetype":"venue"
},
  "geometry": {"coordinates":[-122.35117099999999,47.650707],"type":"Point"}
}