{
  "type": "Feature",
  "properties": {
    "addr:full":"4605 E Sprague Ave Spokane Valley WA 99212",
    "addr:housenumber":"4605",
    "addr:postcode":"99212",
    "addr:street":"E Sprague Ave",
    "iso:country":"US",
    "sg:address":"4605 E Sprague Ave",
    "sg:city":"Spokane Valley",
    "sg:classifiers":[
        {
            "category":"Autos & Motor Vehicles",
            "subcategory":"Automobile Sales",
            "type":"Retail Goods"
        }
    ],
    "sg:phone":"+1 509 534 2173",
    "sg:postcode":"99212",
    "sg:province":"WA",
    "sg:tags":[
        "car",
        "dealer"
    ],
    "wof:name":"Best Bet Auto Sales",
    "wof:placetype":"venue"
},
  "geometry": {"coordinates":[-117.342741,47.657295],"type":"Point"}
}