{
  "type": "Feature",
  "properties": {
    "addr:full":"1627 Evergreen St Walla Walla WA 99362",
    "addr:housenumber":"1627",
    "addr:postcode":"99362",
    "addr:street":"Evergreen St",
    "iso:country":"US",
    "sg:address":"1627 Evergreen St",
    "sg:city":"Walla Walla",
    "sg:classifiers":[
        {
            "category":"Social Services",
            "subcategory":"Job Training",
            "type":"Services"
        }
    ],
    "sg:phone":"+1 509 525 3532",
    "sg:postcode":"99362",
    "sg:province":"WA",
    "wof:name":"Blue Mountain Industries",
    "wof:placetype":"venue"
},
  "geometry": {"coordinates":[-118.31384300000001,46.073798],"type":"Point"}
}