{
  "type": "Feature",
  "properties": {
    "addr:full":"807 3rd St Clarkston WA 99403",
    "addr:housenumber":"807",
    "addr:postcode":"99403",
    "addr:street":"3Rd St",
    "iso:country":"US",
    "sg:address":"807 3rd St",
    "sg:city":"Clarkston",
    "sg:classifiers":[
        {
            "category":"Professional",
            "type":"Services"
        }
    ],
    "sg:phone":"+1 509 758 8330",
    "sg:postcode":"99403",
    "sg:province":"WA",
    "wof:name":"Shafii Bahman",
    "wof:placetype":"venue"
},
  "geometry": {"coordinates":[-117.041545,46.414389],"type":"Point"}
}