{
  "type": "Feature",
  "properties": {
    "addr:full":"6601 S Warner St Tacoma WA 98409",
    "addr:housenumber":"6601",
    "addr:postcode":"98409",
    "addr:street":"S Warner St",
    "iso:country":"US",
    "sg:address":"6601 S Warner St",
    "sg:city":"Tacoma",
    "sg:classifiers":[
        {
            "category":"Real Estate",
            "subcategory":"Real Estate Agent",
            "type":"Services"
        }
    ],
    "sg:phone":"+1 253 474 1394",
    "sg:postcode":"98409",
    "sg:province":"WA",
    "wof:name":"Crawford Real Estate",
    "wof:placetype":"venue"
},
  "geometry": {"coordinates":[-122.481145,47.195626],"type":"Point"}
}