{
  "type": "Feature",
  "properties": {
    "addr:full":"817 S Shelley Lake Ln Veradale WA 99037",
    "addr:housenumber":"817",
    "addr:postcode":"99037",
    "addr:street":"S Shelley Lake Ln",
    "iso:country":"US",
    "sg:address":"817 S Shelley Lake Ln",
    "sg:city":"Veradale",
    "sg:classifiers":[
        {
            "category":"Sports & Exercise",
            "subcategory":"Race Track",
            "type":"Entertainment"
        }
    ],
    "sg:phone":"+1 509 838 3796",
    "sg:postcode":"99037",
    "sg:province":"WA",
    "sg:tags":[
        "operation",
        "racing",
        "or"
    ],
    "wof:name":"R&O Harder Racing Inc",
    "wof:placetype":"venue"
},
  "geometry": {"coordinates":[-117.18198,47.648197],"type":"Point"}
}