{
  "type": "Feature",
  "properties": {
    "addr:full":"363 S Barr Rd Port Angeles WA 98362",
    "addr:housenumber":"363",
    "addr:postcode":"98362",
    "addr:street":"S Barr Rd",
    "iso:country":"US",
    "sg:address":"363 S Barr Rd",
    "sg:city":"Port Angeles",
    "sg:classifiers":[
        {
            "category":"Building & Trades",
            "subcategory":"Construction",
            "type":"Services"
        }
    ],
    "sg:phone":"+1 360 457 8388",
    "sg:postcode":"98362",
    "sg:province":"WA",
    "sg:tags":[
        "specializing",
        "well",
        "drilling",
        "contractor"
    ],
    "wof:name":"Louie's Well Drilling",
    "wof:placetype":"venue"
},
  "geometry": {"coordinates":[-123.237909,48.085965],"type":"Point"}
}