{
  "type": "Feature",
  "properties": {
    "addr:full":"12720 Gateway Dr Seattle WA 98168",
    "addr:housenumber":"12720",
    "addr:postcode":"98168",
    "addr:street":"Gateway Dr",
    "iso:country":"US",
    "sg:address":"12720 Gateway Dr",
    "sg:city":"Seattle",
    "sg:classifiers":[
        {
            "category":"Shopping",
            "subcategory":"Computers & Home Electronics",
            "type":"Retail Goods"
        },
        {
            "category":"Professional",
            "subcategory":"Computer Services",
            "type":"Services"
        }
    ],
    "sg:phone":"+1 206 433 0883",
    "sg:postcode":"98168",
    "sg:province":"WA",
    "sg:tags":[
        "equipment",
        "design",
        "system",
        "dealer"
    ],
    "wof:name":"Entre Computer Center",
    "wof:placetype":"venue"
},
  "geometry": {"coordinates":[-122.27549500000001,47.488586],"type":"Point"}
}