{
  "type": "Feature",
  "properties": {
    "addr:full":"2515 57th Ave SW Seattle WA 98116",
    "addr:housenumber":"2515",
    "addr:postcode":"98116",
    "addr:street":"57Th Ave Sw",
    "iso:country":"US",
    "sg:address":"2515 57th Ave SW",
    "sg:city":"Seattle",
    "sg:classifiers":[
        {
            "category":"Building & Trades",
            "subcategory":"Construction",
            "type":"Services"
        }
    ],
    "sg:phone":"+1 206 850 3452",
    "sg:postcode":"98116",
    "sg:province":"WA",
    "sg:tags":[
        "contractor"
    ],
    "wof:name":"Florentian Tile & Stone Works",
    "wof:placetype":"venue"
},
  "geometry": {"coordinates":[-122.405305,47.580131],"type":"Point"}
}