{
  "type": "Feature",
  "properties": {
    "iso:country":"US",
    "sg:address":"9319 167th Ave NE",
    "sg:city":"Redmond",
    "sg:classifiers":[
        {
            "category":"Building & Trades",
            "subcategory":"Construction",
            "type":"Services"
        }
    ],
    "sg:phone":"+1 425 883 3632",
    "sg:postcode":"98052",
    "sg:province":"WA",
    "sg:tags":[
        "residential",
        "handyman",
        "remodel",
        "contractor"
    ],
    "wof:name":"Old & New",
    "wof:placetype":"venue"
},
  "geometry": {"coordinates":[-122.11686400000001,47.684945],"type":"Point"}
}