{
  "type": "Feature",
  "properties": {
    "addr:full":"28304 183rd Ave SE Kent WA 98042",
    "addr:housenumber":"28304",
    "addr:postcode":"98042",
    "addr:street":"183Rd Ave Se",
    "iso:country":"US",
    "sg:address":"28304 183rd Ave SE",
    "sg:city":"Kent",
    "sg:classifiers":[
        {
            "category":"Real Estate",
            "subcategory":"Real Estate Operator",
            "type":"Services"
        }
    ],
    "sg:phone":"+1 253 630 8420",
    "sg:postcode":"98042",
    "sg:province":"WA",
    "sg:tags":[
        "building",
        "nonresidential"
    ],
    "wof:name":"Diversfied Property Acquistion",
    "wof:placetype":"venue"
},
  "geometry": {"coordinates":[-122.098167,47.347798],"type":"Point"}
}