{
  "type": "Feature",
  "properties": {
    "addr:full":"31708 7th Ave S Federal Way WA 98003",
    "addr:housenumber":"31708",
    "addr:postcode":"98003",
    "addr:street":"7Th Ave S Federal Way",
    "iso:country":"US",
    "sg:address":"31708 7th Ave S",
    "sg:city":"Federal Way",
    "sg:classifiers":[
        {
            "category":"Professional",
            "subcategory":"Computer Services",
            "type":"Services"
        }
    ],
    "sg:phone":"+1 253 839 5248",
    "sg:postcode":"98003",
    "sg:province":"WA",
    "sg:tags":[
        "programing",
        "custom"
    ],
    "wof:name":"James M Thrush",
    "wof:placetype":"venue"
},
  "geometry": {"coordinates":[-122.32600100000001,47.316697],"type":"Point"}
}