{
  "type": "Feature",
  "properties": {
    "addr:full":"10600 Roosevelt Way NE Seattle WA 98125",
    "addr:housenumber":"10600",
    "addr:postcode":"98125",
    "addr:street":"Roosevelt Way Ne",
    "iso:country":"US",
    "sg:address":"10600 Roosevelt Way NE",
    "sg:city":"Seattle",
    "sg:classifiers":[
        {
            "category":"Education",
            "subcategory":"Special Training",
            "type":"Public Place"
        }
    ],
    "sg:phone":"+1 206 669 2822",
    "sg:postcode":"98125",
    "sg:province":"WA",
    "wof:name":"Hong Kong Driving School",
    "wof:placetype":"venue"
},
  "geometry": {"coordinates":[-122.317757,47.706733],"type":"Point"}
}