{
  "type": "Feature",
  "properties": {
    "iso:country":"US",
    "sg:address":"17619 316th St NE",
    "sg:city":"Arlington",
    "sg:classifiers":[
        {
            "category":"Government",
            "subcategory":"Office",
            "type":"Public Place"
        },
        {
            "category":"Farming",
            "subcategory":"Aquatic Farm",
            "type":"Manufacturing & Wholesale Goods"
        }
    ],
    "sg:phone":"+1 360 435 3206",
    "sg:postcode":"98223",
    "sg:province":"WA",
    "sg:tags":[
        "fish",
        "conservation"
    ],
    "wof:name":"Arlington Fish Hatchery",
    "wof:placetype":"venue"
},
  "geometry": {"coordinates":[-121.989425,48.282556],"type":"Point"}
}