{
  "type": "Feature",
  "properties": {
    "addr:full":"3815 Bakerview Spr Bellingham WA 98226",
    "addr:housenumber":"3815",
    "addr:postcode":"98226",
    "addr:street":"Bakerview Spr",
    "iso:country":"US",
    "sg:address":"3815 Bakerview Spr",
    "sg:city":"Bellingham",
    "sg:classifiers":[
        {
            "category":"Freight",
            "type":"Transportation"
        }
    ],
    "sg:phone":"+1 360 676 0976",
    "sg:postcode":"98226",
    "sg:province":"WA",
    "sg:tags":[
        "warehouse"
    ],
    "wof:name":"Glas-Aire Industries Inc",
    "wof:placetype":"venue"
},
  "geometry": {"coordinates":[-122.44806,48.782305],"type":"Point"}
}