{
  "type": "Feature",
  "properties": {
    "addr:full":"806 E Roy St Seattle WA 98102",
    "addr:housenumber":"806",
    "addr:postcode":"98102",
    "addr:street":"E Roy St",
    "iso:country":"US",
    "sg:address":"806 E Roy St",
    "sg:city":"Seattle",
    "sg:classifiers":[
        {
            "category":"Restaurant",
            "type":"Food & Drink"
        }
    ],
    "sg:menulink":"http://www.allmenus.com/wa/seattle/3614-bacchus/menu/",
    "sg:phone":"+1 206 325 2888",
    "sg:postcode":"98102",
    "sg:province":"WA",
    "sg:tags":[
        "soup",
        "seafood",
        "american",
        "salad"
    ],
    "wof:name":"Bacchus",
    "wof:placetype":"venue"
},
  "geometry": {"coordinates":[-122.32186900000001,47.625134],"type":"Point"}
}