{
  "type": "Feature",
  "properties": {
    "addr:full":"2217 177th Pl NE Redmond WA 98052",
    "addr:housenumber":"2217",
    "addr:postcode":"98052",
    "addr:street":"177Th Pl Ne",
    "iso:country":"US",
    "sg:address":"2217 177th Pl NE",
    "sg:city":"Redmond",
    "sg:classifiers":[
        {
            "category":"Banks & Credit Unions",
            "subcategory":"Investment Brokerage",
            "type":"Services"
        },
        {
            "category":"Banks & Credit Unions",
            "subcategory":"Financial Services",
            "type":"Services"
        }
    ],
    "sg:phone":"+1 425 373 9429",
    "sg:postcode":"98052",
    "sg:province":"WA",
    "sg:tags":[
        "advisory",
        "planner"
    ],
    "wof:name":"Sexton",
    "wof:placetype":"venue"
},
  "geometry": {"coordinates":[-122.10361,47.628836],"type":"Point"}
}