{
  "type": "Feature",
  "properties": {
    "addr:full":"1509 Western Ave Seattle WA 98101",
    "addr:housenumber":"1509",
    "addr:postcode":"98101",
    "addr:street":"Western Ave",
    "iso:country":"US",
    "sg:address":"1509 Western Ave",
    "sg:city":"Seattle",
    "sg:classifiers":[
        {
            "category":"Food & Beverages",
            "subcategory":"Specialty",
            "type":"Retail Goods"
        },
        {
            "category":"Shopping",
            "subcategory":"Gifts & Souvenirs",
            "type":"Retail Goods"
        },
        {
            "category":"Food & Beverages",
            "subcategory":"Fruits & Vegetables",
            "type":"Retail Goods"
        },
        {
            "category":"Food & Beverages",
            "subcategory":"Groceries & Convenience Stores",
            "type":"Retail Goods"
        }
    ],
    "sg:phone":"+1 206 682 7274",
    "sg:postcode":"98101",
    "sg:province":"WA",
    "sg:tags":[
        "shop",
        "herb",
        "spice"
    ],
    "sg:website":"www.worldspice.com",
    "wof:name":"World Spice Merchants",
    "wof:placetype":"venue"
},
  "geometry": {"coordinates":[-122.341176,47.608445],"type":"Point"}
}