{
  "type": "Feature",
  "properties": {
    "addr:full":"200 SE Phillips Rd Shelton WA 98584",
    "addr:housenumber":"200",
    "addr:postcode":"98584",
    "addr:street":"Se Phillips Rd",
    "iso:country":"US",
    "sg:address":"200 SE Phillips Rd",
    "sg:city":"Shelton",
    "sg:classifiers":[
        {
            "category":"Building & Trades",
            "subcategory":"Construction",
            "type":"Services"
        }
    ],
    "sg:phone":"+1 360 427 0340",
    "sg:postcode":"98584",
    "sg:province":"WA",
    "sg:tags":[
        "carpenter"
    ],
    "wof:name":"Daves Home Improvement Co",
    "wof:placetype":"venue"
},
  "geometry": {"coordinates":[-123.02824099999999,47.162644],"type":"Point"}
}