{
  "type": "Feature",
  "properties": {
    "addr:full":"33497 State Rte 2 E Davenport WA 99122",
    "addr:housenumber":"33497",
    "addr:postcode":"99122",
    "addr:street":"State Rte 2 E",
    "iso:country":"US",
    "sg:address":"33497 State Rte 2 E",
    "sg:city":"Davenport",
    "sg:phone":"+1 509 725 2601",
    "sg:postcode":"99122",
    "sg:province":"WA",
    "sg:tags":[
        "farm",
        "wheat"
    ],
    "wof:name":"Eugene Stuckle",
    "wof:placetype":"venue"
},
  "geometry": {"coordinates":[-118.269025,47.642738],"type":"Point"}
}