{
  "type": "Feature",
  "properties": {
    "addr:full":"7357 35th Ave SW Seattle WA 98126",
    "addr:housenumber":"7357",
    "addr:postcode":"98126",
    "addr:street":"35Th Ave Sw",
    "iso:country":"US",
    "sg:address":"7357 35th Ave SW",
    "sg:city":"Seattle",
    "sg:classifiers":[
        {
            "category":"Personal",
            "subcategory":"Beauty Salon",
            "type":"Services"
        }
    ],
    "sg:phone":"+1 206 937 5678",
    "sg:postcode":"98126",
    "sg:province":"WA",
    "sg:tags":[
        "hair"
    ],
    "wof:name":"Salon Julian",
    "wof:placetype":"venue"
},
  "geometry": {"coordinates":[-122.37660200000001,47.536094],"type":"Point"}
}