{
  "type": "Feature",
  "properties": {
    "addr:full":"3162 State Rte 6 Chehalis WA 98532",
    "addr:housenumber":"3162",
    "addr:postcode":"98532",
    "addr:street":"State Rte 6",
    "iso:country":"US",
    "sg:address":"3162 State Rte 6",
    "sg:city":"Chehalis",
    "sg:classifiers":[
        {
            "category":"Farming",
            "subcategory":"Nursery",
            "type":"Manufacturing & Wholesale Goods"
        }
    ],
    "sg:phone":"+1 360 245 4411",
    "sg:postcode":"98532",
    "sg:province":"WA",
    "sg:tags":[
        "ornamental"
    ],
    "wof:name":"Black Cat Nursery",
    "wof:placetype":"venue"
},
  "geometry": {"coordinates":[-123.182974,46.634255],"type":"Point"}
}