{
  "type": "Feature",
  "properties": {
    "addr:full":"417 University St Seattle WA 98101",
    "addr:housenumber":"417",
    "addr:postcode":"98101",
    "addr:street":"University St",
    "iso:country":"US",
    "sg:address":"417 University St",
    "sg:city":"Seattle",
    "sg:classifiers":[
        {
            "category":"Manufacturing",
            "subcategory":"Leather Goods",
            "type":"Manufacturing & Wholesale Goods"
        }
    ],
    "sg:phone":"+1 206 382 1772",
    "sg:postcode":"98101",
    "sg:province":"WA",
    "wof:name":"The Coach Store",
    "wof:placetype":"venue"
},
  "geometry": {"coordinates":[-122.334999,47.608501],"type":"Point"}
}