{
  "type": "Feature",
  "properties": {
    "addr:full":"24023 62nd Way S Kent WA 98032",
    "addr:housenumber":"24023",
    "addr:postcode":"98032",
    "addr:street":"62Nd Way S",
    "iso:country":"US",
    "sg:address":"24023 62nd Way S",
    "sg:city":"Kent",
    "sg:classifiers":[
        {
            "category":"Health Services",
            "subcategory":"Chiropractor",
            "type":"Services"
        }
    ],
    "sg:phone":"+1 206 373 9902",
    "sg:postcode":"98032",
    "sg:province":"WA",
    "wof:name":"Randy Clark",
    "wof:placetype":"venue"
},
  "geometry": {"coordinates":[-122.25647499999999,47.386734],"type":"Point"}
}