{
  "type": "Feature",
  "properties": {
    "addr:full":"21734 NE 201st Ct Woodinville WA 98077",
    "addr:housenumber":"21734",
    "addr:postcode":"98077",
    "addr:street":"Ne 201St Ct",
    "iso:country":"US",
    "sg:address":"21734 NE 201st Ct",
    "sg:city":"Woodinville",
    "sg:classifiers":[
        {
            "category":"Professional",
            "subcategory":"Management & Consulting",
            "type":"Services"
        }
    ],
    "sg:phone":"+1 425 788 0304",
    "sg:postcode":"98077",
    "sg:province":"WA",
    "sg:tags":[
        "computer",
        "business",
        "related"
    ],
    "wof:name":"Simple Solutions Computing",
    "wof:placetype":"venue"
},
  "geometry": {"coordinates":[-122.046831,47.773642],"type":"Point"}
}