{
  "type": "Feature",
  "properties": {
    "addr:full":"415 15th Ave E Seattle WA 98112",
    "addr:housenumber":"415",
    "addr:postcode":"98112",
    "addr:street":"15Th Ave E",
    "iso:country":"US",
    "sg:address":"415 15th Ave E",
    "sg:city":"Seattle",
    "sg:classifiers":[
        {
            "category":"Retail",
            "subcategory":"Laundry & Dry Cleaning",
            "type":"Services"
        }
    ],
    "sg:phone":"+1 206 322 4665",
    "sg:postcode":"98112",
    "sg:province":"WA",
    "sg:tags":[
        "drycleaning",
        "plant"
    ],
    "wof:name":"Superb Cleaners",
    "wof:placetype":"venue"
},
  "geometry": {"coordinates":[-122.31300400000001,47.622799],"type":"Point"}
}