{
  "type": "Feature",
  "properties": {
    "addr:full":"624 172nd St NW Arlington WA 98223",
    "addr:housenumber":"624",
    "addr:postcode":"98223",
    "addr:street":"172Nd St Nw",
    "iso:country":"US",
    "sg:address":"624 172nd St NW",
    "sg:city":"Arlington",
    "sg:classifiers":[
        {
            "category":"Wholesale",
            "subcategory":"Jewelry",
            "type":"Manufacturing & Wholesale Goods"
        }
    ],
    "sg:phone":"+1 360 652 1682",
    "sg:postcode":"98223",
    "sg:province":"WA",
    "sg:tags":[
        "stone"
    ],
    "wof:name":"Elegantly Yours",
    "wof:placetype":"venue"
},
  "geometry": {"coordinates":[-122.241753,48.151906],"type":"Point"}
}