{
  "type": "Feature",
  "properties": {
    "addr:full":"3525 Ensign Rd NE Olympia WA 98506",
    "addr:housenumber":"3525",
    "addr:postcode":"98506",
    "addr:street":"Ensign Rd Ne",
    "iso:country":"US",
    "sg:address":"3525 Ensign Rd NE",
    "sg:city":"Olympia",
    "sg:classifiers":[
        {
            "category":"Health Services",
            "subcategory":"Doctor",
            "type":"Services"
        }
    ],
    "sg:phone":"+1 360 754 2212",
    "sg:postcode":"98506",
    "sg:province":"WA",
    "sg:tags":[
        "physician",
        "surgeon"
    ],
    "wof:name":"Robert GR Lang Inc",
    "wof:placetype":"venue"
},
  "geometry": {"coordinates":[-122.84326900000001,47.051094],"type":"Point"}
}