{
  "type": "Feature",
  "properties": {
    "addr:full":"1021 118th Ave SE Bellevue WA 98005",
    "addr:housenumber":"1021",
    "addr:postcode":"98005",
    "addr:street":"118Th Ave Se",
    "iso:country":"US",
    "sg:address":"1021 118th Ave SE",
    "sg:city":"Bellevue",
    "sg:classifiers":[
        {
            "category":"Building & Trades",
            "subcategory":"Landscaping Services",
            "type":"Services"
        }
    ],
    "sg:phone":"+1 206 363 5613",
    "sg:postcode":"98005",
    "sg:province":"WA",
    "sg:tags":[
        "tree"
    ],
    "sg:website":"www.davey.com",
    "wof:name":"Davey Tree & Lawn Care",
    "wof:placetype":"venue"
},
  "geometry": {"coordinates":[-122.18289799999999,47.594787],"type":"Point"}
}