{
  "type": "Feature",
  "properties": {
    "addr:full":"245 25th Ave Longview WA 98632",
    "addr:housenumber":"245",
    "addr:postcode":"98632",
    "addr:street":"25Th Ave",
    "iso:country":"US",
    "sg:address":"245 25th Ave",
    "sg:city":"Longview",
    "sg:classifiers":[
        {
            "category":"Cinema",
            "subcategory":"Movie Rental",
            "type":"Entertainment"
        }
    ],
    "sg:phone":"+1 360 501 4384",
    "sg:postcode":"98632",
    "sg:province":"WA",
    "sg:tags":[
        "video",
        "tape"
    ],
    "wof:name":"Johnsons Family Videostore",
    "wof:placetype":"venue"
},
  "geometry": {"coordinates":[-122.96013000000001,46.123663],"type":"Point"}
}