{
  "type": "Feature",
  "properties": {
    "addr:full":"3948 Delphi Rd SW Olympia WA 98512",
    "addr:housenumber":"3948",
    "addr:postcode":"98512",
    "addr:street":"Delphi Rd Sw",
    "iso:country":"US",
    "sg:address":"3948 Delphi Rd SW",
    "sg:city":"Olympia",
    "sg:classifiers":[
        {
            "category":"Government",
            "subcategory":"Office",
            "type":"Public Place"
        }
    ],
    "sg:phone":"+1 360 866 6395",
    "sg:postcode":"98512",
    "sg:province":"WA",
    "sg:tags":[
        "educational",
        "program",
        "administrative"
    ],
    "wof:name":"Delphinia Community",
    "wof:placetype":"venue"
},
  "geometry": {"coordinates":[-122.99705,47.018625],"type":"Point"}
}