{
  "type": "Feature",
  "properties": {
    "addr:full":"410 N Park St Aberdeen WA 98520",
    "addr:housenumber":"410",
    "addr:postcode":"98520",
    "addr:street":"N Park St",
    "iso:country":"US",
    "sg:address":"410 N Park St",
    "sg:city":"Aberdeen",
    "sg:classifiers":[
        {
            "category":"Manufacturing",
            "subcategory":"Signs",
            "type":"Manufacturing & Wholesale Goods"
        }
    ],
    "sg:phone":"+1 360 537 0924",
    "sg:postcode":"98520",
    "sg:province":"WA",
    "sg:tags":[
        "specialty",
        "mfg"
    ],
    "wof:name":"Pro Art Signs",
    "wof:placetype":"venue"
},
  "geometry": {"coordinates":[-123.83035599999999,46.974025],"type":"Point"}
}