{
  "type": "Feature",
  "properties": {
    "addr:full":"4000 E Madison Street Suite 201 Seattle WA 98112",
    "addr:housenumber":"4000",
    "addr:postcode":"98112",
    "addr:street":"E Madison Street Suite 201",
    "iso:country":"US",
    "sg:address":"4000 E Madison Street Suite 201",
    "sg:city":"Seattle",
    "sg:classifiers":[
        {
            "category":"Health Services",
            "subcategory":"Dentist",
            "type":"Services"
        }
    ],
    "sg:phone":"+1 206 323 5677",
    "sg:postcode":"98112",
    "sg:province":"WA",
    "wof:name":"Caggiano Mark DDS PS",
    "wof:placetype":"venue"
},
  "geometry": {"coordinates":[-122.281218,47.633666],"type":"Point"}
}