{
  "type": "Feature",
  "properties": {
    "addr:full":"13800 SE 43rd St Bellevue WA 98006",
    "addr:housenumber":"13800",
    "addr:postcode":"98006",
    "addr:street":"Se 43Rd St",
    "iso:country":"US",
    "sg:address":"13800 SE 43rd St",
    "sg:city":"Bellevue",
    "sg:classifiers":[
        {
            "category":"Real Estate",
            "subcategory":"Architect",
            "type":"Services"
        }
    ],
    "sg:phone":"+1 425 643 8260",
    "sg:postcode":"98006",
    "sg:province":"WA",
    "wof:name":"Akhavan Architecture",
    "wof:placetype":"venue"
},
  "geometry": {"coordinates":[-122.15590899999999,47.569289],"type":"Point"}
}