{
  "type": "Feature",
  "properties": {
    "addr:full":"19351 8th Ave NE Poulsbo WA 98370",
    "addr:housenumber":"19351",
    "addr:postcode":"98370",
    "addr:street":"8Th Ave Ne",
    "iso:country":"US",
    "sg:address":"19351 8th Ave NE",
    "sg:city":"Poulsbo",
    "sg:classifiers":[
        {
            "category":"Education",
            "subcategory":"Junior College",
            "type":"Public Place"
        }
    ],
    "sg:phone":"+1 360 697 0125",
    "sg:postcode":"98370",
    "sg:province":"WA",
    "sg:tags":[
        "technical",
        "institute"
    ],
    "sg:website":"www.glenedeninstitute.com",
    "wof:name":"Glen Eden Institute",
    "wof:placetype":"venue"
},
  "geometry": {"coordinates":[-122.639465,47.738701],"type":"Point"}
}