{
  "type": "Feature",
  "properties": {
    "addr:full":"2406 Mount Pleasant Rd Kelso WA 98626",
    "addr:housenumber":"2406",
    "addr:postcode":"98626",
    "addr:street":"Mount Pleasant Rd",
    "iso:country":"US",
    "sg:address":"2406 Mount Pleasant Rd",
    "sg:city":"Kelso",
    "sg:classifiers":[
        {
            "category":"Building & Trades",
            "subcategory":"Construction",
            "type":"Services"
        }
    ],
    "sg:phone":"+1 360 414 3257",
    "sg:postcode":"98626",
    "sg:province":"WA",
    "sg:tags":[
        "application",
        "spray",
        "foam",
        "coating"
    ],
    "wof:name":"Spray Applied Technologies LLC",
    "wof:placetype":"venue"
},
  "geometry": {"coordinates":[-122.802637,46.076055],"type":"Point"}
}