{
  "type": "Feature",
  "properties": {
    "addr:full":"11302 Steele St S Ste A Lakewood WA 98499",
    "addr:housenumber":"11302",
    "addr:postcode":"98499",
    "addr:street":"Steele St S Ste A",
    "iso:country":"US",
    "sg:address":"11302 Steele St S Ste A",
    "sg:city":"Lakewood",
    "sg:classifiers":[
        {
            "category":"Autos & Motor Vehicles",
            "subcategory":"Automobile Sales",
            "type":"Retail Goods"
        }
    ],
    "sg:phone":"+1 253 537 3718",
    "sg:postcode":"98499",
    "sg:province":"WA",
    "sg:tags":[
        "automotive"
    ],
    "wof:name":"The Last Muffler Shop",
    "wof:placetype":"venue"
},
  "geometry": {"coordinates":[-122.468493,47.154772],"type":"Point"}
}