{
  "type": "Feature",
  "properties": {
    "addr:full":"7501 68th Ave NE Marysville WA 98270",
    "addr:housenumber":"7501",
    "addr:postcode":"98270",
    "addr:street":"68Th Ave Ne",
    "iso:country":"US",
    "sg:address":"7501 68th Ave NE",
    "sg:city":"Marysville",
    "sg:classifiers":[
        {
            "category":"Arts & Performance",
            "subcategory":"Theater",
            "type":"Entertainment"
        }
    ],
    "sg:phone":"+1 360 659 5331",
    "sg:postcode":"98270",
    "sg:province":"WA",
    "sg:tags":[
        "pianist"
    ],
    "wof:name":"Lucile A Young",
    "wof:placetype":"venue"
},
  "geometry": {"coordinates":[-122.13836000000001,48.062121],"type":"Point"}
}