{
  "type": "Feature",
  "properties": {
    "addr:full":"18623 Highway 99 Ste 210 Lynnwood WA 98037",
    "addr:housenumber":"18623",
    "addr:postcode":"98037",
    "addr:street":"Highway 99 Ste 210",
    "iso:country":"US",
    "sg:address":"18623 Highway 99 Ste 210",
    "sg:city":"Lynnwood",
    "sg:classifiers":[
        {
            "category":"Health Services",
            "subcategory":"Dentist",
            "type":"Services"
        }
    ],
    "sg:phone":"+1 425 275 9977",
    "sg:postcode":"98037",
    "sg:province":"WA",
    "sg:tags":[
        "equipment",
        "dental",
        "clinic",
        "supply"
    ],
    "wof:name":"Ivy Dental",
    "wof:placetype":"venue"
},
  "geometry": {"coordinates":[-122.30751100000001,47.829949],"type":"Point"}
}