{
  "type": "Feature",
  "properties": {
    "addr:full":"642 W Grumman St Pasco WA 99301",
    "addr:housenumber":"642",
    "addr:postcode":"99301",
    "addr:street":"W Grumman St",
    "iso:country":"US",
    "sg:address":"642 W Grumman St",
    "sg:city":"Pasco",
    "sg:classifiers":[
        {
            "category":"Manufacturing",
            "subcategory":"Food",
            "type":"Manufacturing & Wholesale Goods"
        }
    ],
    "sg:phone":"+1 509 545 6155",
    "sg:postcode":"99301",
    "sg:province":"WA",
    "sg:tags":[
        "coffee",
        "mfg",
        "roasted"
    ],
    "wof:name":"Farmers Brothers Coffee",
    "wof:placetype":"venue"
},
  "geometry": {"coordinates":[-119.10351,46.263601],"type":"Point"}
}