{
  "type": "Feature",
  "properties": {
    "iso:country":"US",
    "sg:address":"8540 Oxford Dr SE",
    "sg:city":"Lacey",
    "sg:classifiers":[
        {
            "category":"Professional",
            "subcategory":"Management & Consulting",
            "type":"Services"
        }
    ],
    "sg:phone":"+1 360 790 0517",
    "sg:postcode":"98503",
    "sg:province":"WA",
    "wof:name":"Empower Communications LLC",
    "wof:placetype":"venue"
},
  "geometry": {"coordinates":[-122.75851299999999,47.012249],"type":"Point"}
}