{
  "type": "Feature",
  "properties": {
    "addr:full":"11620 Pacific Hwy SW Tacoma WA 98499",
    "addr:housenumber":"11620",
    "addr:postcode":"98499",
    "addr:street":"Pacific Hwy Sw",
    "iso:country":"US",
    "sg:address":"11620 Pacific Hwy SW",
    "sg:city":"Tacoma",
    "sg:classifiers":[
        {
            "category":"Food & Beverages",
            "subcategory":"Groceries & Convenience Stores",
            "type":"Retail Goods"
        }
    ],
    "sg:phone":"+1 253 583 0355",
    "sg:postcode":"98499",
    "sg:province":"WA",
    "sg:tags":[
        "grocer"
    ],
    "wof:name":"Fiaola Specialty Sales",
    "wof:placetype":"venue"
},
  "geometry": {"coordinates":[-122.499602,47.152109],"type":"Point"}
}