{
  "type": "Feature",
  "properties": {
    "addr:full":"2500 81st Ave SE Ste 341 Mercer Island WA 98040",
    "addr:housenumber":"2500",
    "addr:postcode":"98040",
    "addr:street":"81St Ave Se Ste 341",
    "iso:country":"US",
    "sg:address":"2500 81st Ave SE Ste 341",
    "sg:city":"Mercer Island",
    "sg:classifiers":[
        {
            "category":"Building & Trades",
            "subcategory":"Construction",
            "type":"Services"
        }
    ],
    "sg:phone":"+1 425 830 8183",
    "sg:postcode":"98040",
    "sg:province":"WA",
    "sg:tags":[
        "contractor"
    ],
    "sg:website":"www.greencollarcrewus.com",
    "wof:name":"Green Collar Crew",
    "wof:placetype":"venue"
},
  "geometry": {"coordinates":[-122.230673,47.588512],"type":"Point"}
}