{
  "type": "Feature",
  "properties": {
    "addr:full":"21463 Little Mountain Rd Mt Vernon WA 98274",
    "addr:housenumber":"21463",
    "addr:postcode":"98274",
    "addr:street":"Little Mountain Rd",
    "iso:country":"US",
    "sg:address":"21463 Little Mountain Rd",
    "sg:city":"Mt Vernon",
    "sg:classifiers":[
        {
            "category":"Recreation",
            "type":"Entertainment"
        }
    ],
    "sg:phone":"+1 360 424 7630",
    "sg:postcode":"98274",
    "sg:province":"WA",
    "sg:tags":[
        "stable"
    ],
    "wof:name":"Lang's Horse & Pony Farm",
    "wof:placetype":"venue"
},
  "geometry": {"coordinates":[-122.282617,48.394752],"type":"Point"}
}