{
  "type": "Feature",
  "properties": {
    "addr:full":"3305 W Rockwell Ave Spokane WA 99205",
    "addr:housenumber":"3305",
    "addr:postcode":"99205",
    "addr:street":"W Rockwell Ave",
    "iso:country":"US",
    "sg:address":"3305 W Rockwell Ave",
    "sg:city":"Spokane",
    "sg:classifiers":[
        {
            "category":"Social Services",
            "subcategory":"Adult Care",
            "type":"Services"
        }
    ],
    "sg:phone":"+1 509 328 4289",
    "sg:postcode":"99205",
    "sg:province":"WA",
    "sg:tags":[
        "residential"
    ],
    "wof:name":"Judys Best Care",
    "wof:placetype":"venue"
},
  "geometry": {"coordinates":[-117.462327,47.696209],"type":"Point"}
}