{
  "type": "Feature",
  "properties": {
    "addr:full":"316 116th Ave NE Bellevue WA 98004",
    "addr:housenumber":"316",
    "addr:postcode":"98004",
    "addr:street":"116Th Ave Ne",
    "iso:country":"US",
    "sg:address":"316 116th Ave NE",
    "sg:city":"Bellevue",
    "sg:classifiers":[
        {
            "category":"Autos & Motor Vehicles",
            "subcategory":"Automobile Sales",
            "type":"Retail Goods"
        }
    ],
    "sg:phone":"+1 206 223 9312",
    "sg:postcode":"98004",
    "sg:province":"WA",
    "sg:tags":[
        "car"
    ],
    "wof:name":"Dodge of Bellevue",
    "wof:placetype":"venue"
},
  "geometry": {"coordinates":[-122.18438999999999,47.613223],"type":"Point"}
}