{
  "type": "Feature",
  "properties": {
    "iso:country":"US",
    "sg:address":"703 3rd St",
    "sg:city":"Mattawa",
    "sg:classifiers":[
        {
            "category":"Retail",
            "subcategory":"Repair Shop",
            "type":"Services"
        }
    ],
    "sg:phone":"+1 509 932 4740",
    "sg:postcode":"99349",
    "sg:province":"WA",
    "sg:tags":[
        "welding"
    ],
    "wof:name":"Parker Fabrication & Welding",
    "wof:placetype":"venue"
},
  "geometry": {"coordinates":[-119.896204,46.73495],"type":"Point"}
}