{
  "type": "Feature",
  "properties": {
    "addr:full":"6200 Capitol Blvd S Olympia WA 98501",
    "addr:housenumber":"6200",
    "addr:postcode":"98501",
    "addr:street":"Capitol Blvd S",
    "iso:country":"US",
    "sg:address":"6200 Capitol Blvd S",
    "sg:city":"Olympia",
    "sg:classifiers":[
        {
            "category":"Shopping",
            "subcategory":"Bicycles & Sporting Goods",
            "type":"Retail Goods"
        }
    ],
    "sg:phone":"+1 360 352 5161",
    "sg:postcode":"98501",
    "sg:province":"WA",
    "wof:name":"Tumwater Sports Center",
    "wof:placetype":"venue"
},
  "geometry": {"coordinates":[-122.90761500000001,46.992635],"type":"Point"}
}