{
  "type": "Feature",
  "properties": {
    "addr:full":"510 Dutterow Rd SE Olympia WA 98513",
    "addr:housenumber":"510",
    "addr:postcode":"olympia;98513",
    "addr:street":"Dutterow Rd Se",
    "iso:country":"US",
    "sg:address":"510 Dutterow Rd SE",
    "sg:city":"Olympia",
    "sg:classifiers":[
        {
            "category":"Building & Trades",
            "subcategory":"Cleaning & Sanitation",
            "type":"Services"
        }
    ],
    "sg:phone":"+1 360 455 4761",
    "sg:postcode":"98513",
    "sg:province":"WA",
    "sg:tags":[
        "maintenance"
    ],
    "wof:name":"Dust Bunnies",
    "wof:placetype":"venue"
},
  "geometry": {"coordinates":[-122.74138000000001,47.053062],"type":"Point"}
}