{
  "type": "Feature",
  "properties": {
    "addr:full":"2703 W Northwest Blvd Spokane WA 99205",
    "addr:housenumber":"2703",
    "addr:postcode":"99205",
    "addr:street":"W Northwest Blvd",
    "iso:country":"US",
    "sg:address":"2703 W Northwest Blvd",
    "sg:city":"Spokane",
    "sg:classifiers":[
        {
            "category":"Social Services",
            "subcategory":"Child Care",
            "type":"Services"
        }
    ],
    "sg:phone":"+1 509 325 3021",
    "sg:postcode":"99205",
    "sg:province":"WA",
    "wof:name":"Bright Stars Early Learning",
    "wof:placetype":"venue"
},
  "geometry": {"coordinates":[-117.451217,47.686099],"type":"Point"}
}