{
  "type": "Feature",
  "properties": {
    "addr:full":"9403 43rd Avct SW Lakewood WA 98499",
    "addr:housenumber":"9403",
    "addr:postcode":"98499",
    "addr:street":"43Rd Avct Sw",
    "iso:country":"US",
    "sg:address":"9403 43rd Avct SW",
    "sg:city":"Lakewood",
    "sg:classifiers":[
        {
            "category":"Freight",
            "type":"Transportation"
        }
    ],
    "sg:phone":"+1 253 896 5075",
    "sg:postcode":"98499",
    "sg:province":"WA",
    "sg:tags":[
        "warehouse",
        "self",
        "storage"
    ],
    "wof:name":"Tab Warehouse & Distribution",
    "wof:placetype":"venue"
},
  "geometry": {"coordinates":[-122.49441899999999,47.172062],"type":"Point"}
}