{
  "type": "Feature",
  "properties": {
    "addr:full":"3925 134th St NE Marysville WA 98271",
    "addr:housenumber":"3925",
    "addr:postcode":"98271",
    "addr:street":"134Th St Ne",
    "iso:country":"US",
    "sg:address":"3925 134th St NE",
    "sg:city":"Marysville",
    "sg:classifiers":[
        {
            "category":"Manufacturing",
            "subcategory":"Food",
            "type":"Manufacturing & Wholesale Goods"
        }
    ],
    "sg:phone":"+1 360 653 1661",
    "sg:postcode":"98271",
    "sg:province":"WA",
    "sg:tags":[
        "vegetable",
        "processor"
    ],
    "wof:name":"Hendrickson Farms",
    "wof:placetype":"venue"
},
  "geometry": {"coordinates":[-122.17827800000001,48.117195],"type":"Point"}
}