{
  "type": "Feature",
  "properties": {
    "addr:full":"307 SE Craddick Rd Shelton WA 98584",
    "addr:housenumber":"307",
    "addr:postcode":"98584",
    "addr:street":"Se Craddick Rd",
    "iso:country":"US",
    "sg:address":"307 SE Craddick Rd",
    "sg:city":"Shelton",
    "sg:classifiers":[
        {
            "category":"Education",
            "subcategory":"Special Training",
            "type":"Public Place"
        }
    ],
    "sg:phone":"+1 360 432 9424",
    "sg:postcode":"98584",
    "sg:province":"WA",
    "sg:tags":[
        "aid",
        "instruction",
        "first"
    ],
    "wof:name":"Emergency Medical Training",
    "wof:placetype":"venue"
},
  "geometry": {"coordinates":[-123.088342,47.106941],"type":"Point"}
}