{
  "type": "Feature",
  "properties": {
    "iso:country":"US",
    "sg:address":"10005 E Montgomery Dr",
    "sg:city":"Spokane Valley",
    "sg:classifiers":[
        {
            "category":"Building & Trades",
            "subcategory":"Electrical",
            "type":"Services"
        },
        {
            "category":"Manufacturing",
            "subcategory":"Tools & Machinery",
            "type":"Manufacturing & Wholesale Goods"
        }
    ],
    "sg:phone":"+1 509 926 3428",
    "sg:postcode":"99206",
    "sg:province":"WA",
    "sg:tags":[
        "fire",
        "equipment",
        "protection",
        "electrical",
        "contractor"
    ],
    "wof:name":"Patriot Fire Protection Inc",
    "wof:placetype":"venue"
},
  "geometry": {"coordinates":[-117.268784,47.680004],"type":"Point"}
}