{
  "type": "Feature",
  "properties": {
    "addr:full":"303 N 50th Ave Longview WA 98632",
    "addr:housenumber":"303",
    "addr:postcode":"98632",
    "addr:street":"N 50Th Ave",
    "iso:country":"US",
    "sg:address":"303 N 50th Ave",
    "sg:city":"Longview",
    "sg:classifiers":[
        {
            "category":"Health Services",
            "subcategory":"Health Practitioner",
            "type":"Services"
        }
    ],
    "sg:phone":"+1 360 425 4156",
    "sg:postcode":"98632",
    "sg:province":"WA",
    "wof:name":"Evergreen Hippotherapy",
    "wof:placetype":"venue"
},
  "geometry": {"coordinates":[-122.997041,46.184688],"type":"Point"}
}