{
  "type": "Feature",
  "properties": {
    "addr:full":"1968 Old CC Rd Addy WA 99101",
    "addr:housenumber":"1968",
    "addr:postcode":"99101",
    "addr:street":"Old Cc Rd",
    "iso:country":"US",
    "sg:address":"1968 Old CC Rd",
    "sg:city":"Addy",
    "sg:classifiers":[
        {
            "category":"Building & Trades",
            "subcategory":"Construction",
            "type":"Services"
        }
    ],
    "sg:phone":"+1 509 935 9855",
    "sg:postcode":"99101",
    "sg:province":"WA",
    "sg:tags":[
        "house"
    ],
    "wof:name":"Cabin Creek Construction",
    "wof:placetype":"venue"
},
  "geometry": {"coordinates":[-117.987267,48.318662],"type":"Point"}
}