{
  "type": "Feature",
  "properties": {
    "addr:full":"302 S 1st St Yakima WA 98901",
    "addr:housenumber":"302",
    "addr:postcode":"98901",
    "addr:street":"S 1St St",
    "iso:country":"US",
    "sg:address":"302 S 1st St",
    "sg:city":"Yakima",
    "sg:classifiers":[
        {
            "category":"Manufacturing",
            "subcategory":"Furniture",
            "type":"Manufacturing & Wholesale Goods"
        }
    ],
    "sg:phone":"+1 509 452 8247",
    "sg:postcode":"98901",
    "sg:province":"WA",
    "sg:tags":[
        "household",
        "wood",
        "mfg"
    ],
    "wof:name":"Pine Shop The",
    "wof:placetype":"venue"
},
  "geometry": {"coordinates":[-120.503747,46.597203],"type":"Point"}
}