{
  "type": "Feature",
  "properties": {
    "addr:full":"47782 Moen Rd Concrete WA 98237",
    "addr:postcode":"47782;98237",
    "addr:street":"Moen Rd",
    "iso:country":"US",
    "sg:address":"47782 Moen Rd",
    "sg:city":"Concrete",
    "sg:classifiers":[
        {
            "category":"Shopping",
            "subcategory":"Beauty & Cosmetics",
            "type":"Retail Goods"
        }
    ],
    "sg:phone":"+1 360 853 8506",
    "sg:postcode":"98237",
    "sg:province":"WA",
    "sg:tags":[
        "merchandise"
    ],
    "wof:name":"Mary Kay Cosmetics",
    "wof:placetype":"venue"
},
  "geometry": {"coordinates":[-121.706452,48.515999],"type":"Point"}
}