{
  "type": "Feature",
  "properties": {
    "addr:full":"17524 SE 45th St Bellevue WA 98006",
    "addr:housenumber":"17524",
    "addr:postcode":"98006",
    "addr:street":"Se 45Th St",
    "iso:country":"US",
    "sg:address":"17524 SE 45th St",
    "sg:city":"Bellevue",
    "sg:classifiers":[
        {
            "category":"Professional",
            "subcategory":"Business Services",
            "type":"Services"
        }
    ],
    "sg:phone":"+1 425 373 5421",
    "sg:postcode":"98006",
    "sg:province":"WA",
    "sg:tags":[
        "consulting"
    ],
    "wof:name":"Lift Business Advisors Inc",
    "wof:placetype":"venue"
},
  "geometry": {"coordinates":[-122.10704699999999,47.565608],"type":"Point"}
}