{
  "type": "Feature",
  "properties": {
    "addr:full":"1111 W 14th St Port Angeles WA 98363",
    "addr:housenumber":"1111",
    "addr:postcode":"98363",
    "addr:street":"W 14Th St",
    "iso:country":"US",
    "sg:address":"1111 W 14th St",
    "sg:city":"Port Angeles",
    "sg:classifiers":[
        {
            "category":"Building & Trades",
            "subcategory":"Cleaning & Sanitation",
            "type":"Services"
        }
    ],
    "sg:phone":"+1 360 452 3762",
    "sg:postcode":"98363",
    "sg:province":"WA",
    "sg:tags":[
        "janitor"
    ],
    "wof:name":"Monson Janitorial",
    "wof:placetype":"venue"
},
  "geometry": {"coordinates":[-123.466069,48.116317],"type":"Point"}
}