{
  "type": "Feature",
  "properties": {
    "addr:full":"16011 NE 153rd St Woodinville WA 98072",
    "addr:housenumber":"16011",
    "addr:postcode":"98072",
    "addr:street":"Ne 153Rd St",
    "iso:country":"US",
    "sg:address":"16011 NE 153rd St",
    "sg:city":"Woodinville",
    "sg:classifiers":[
        {
            "category":"Professional",
            "subcategory":"Art Services",
            "type":"Services"
        }
    ],
    "sg:phone":"+1 425 398 8362",
    "sg:postcode":"98072",
    "sg:province":"WA",
    "sg:tags":[
        "graphic",
        "designer"
    ],
    "wof:name":"Jim Millar",
    "wof:placetype":"venue"
},
  "geometry": {"coordinates":[-122.12575200000001,47.73826],"type":"Point"}
}