{
  "type": "Feature",
  "properties": {
    "addr:full":"1845 Whitman St Walla Walla WA 99362",
    "addr:housenumber":"1845",
    "addr:postcode":"99362",
    "addr:street":"Whitman St",
    "iso:country":"US",
    "sg:address":"1845 Whitman St",
    "sg:city":"Walla Walla",
    "sg:classifiers":[
        {
            "category":"Autos & Motor Vehicles",
            "subcategory":"Motorcycle Sales",
            "type":"Retail Goods"
        }
    ],
    "sg:phone":"+1 509 430 8709",
    "sg:postcode":"99362",
    "sg:province":"WA",
    "sg:tags":[
        "apparel",
        "parts",
        "custom"
    ],
    "wof:name":"Fletcher Boys Rolling",
    "wof:placetype":"venue"
},
  "geometry": {"coordinates":[-118.298072,46.064151],"type":"Point"}
}