{
  "type": "Feature",
  "properties": {
    "addr:full":"333 Mount Vernon Terminal RR Mt Vernon WA 98273",
    "addr:housenumber":"333",
    "addr:postcode":"98273",
    "addr:street":"Mount;Vernon",
    "iso:country":"US",
    "sg:address":"333 Mount Vernon Terminal RR",
    "sg:city":"Mt Vernon",
    "sg:classifiers":[
        {
            "category":"Government",
            "subcategory":"Office",
            "type":"Public Place"
        }
    ],
    "sg:phone":"+1 360 466 4345",
    "sg:postcode":"98273",
    "sg:province":"WA",
    "sg:tags":[
        "state"
    ],
    "wof:name":"Fisheries Dept",
    "wof:placetype":"venue"
},
  "geometry": {"coordinates":[-122.338285,48.420668],"type":"Point"}
}