{
  "type": "Feature",
  "properties": {
    "addr:full":"3400 188th St SW Suite 540 Lynnwood WA 98037",
    "addr:housenumber":"3400",
    "addr:postcode":"98037",
    "addr:street":"188Th St Sw Suite 540",
    "iso:country":"US",
    "sg:address":"3400 188th St SW Suite 540",
    "sg:city":"Lynnwood",
    "sg:classifiers":[
        {
            "category":"Professional",
            "subcategory":"Lawyer & Legal Services",
            "type":"Services"
        }
    ],
    "sg:phone":"+1 425 953 5282",
    "sg:postcode":"98037",
    "sg:province":"WA",
    "sg:tags":[
        "attorney",
        "criminal",
        "family",
        "accident",
        "personal",
        "automobile",
        "wills",
        "damage",
        "business",
        "planning",
        "real estate",
        "trust",
        "injury",
        "property",
        "law"
    ],
    "wof:name":"Arndt & Walker Attorneys at Law",
    "wof:placetype":"venue"
},
  "geometry": {"coordinates":[-122.27909,47.828197],"type":"Point"}
}