{
  "type": "Feature",
  "properties": {
    "addr:full":"21709 82nd Ave W Edmonds WA 98026",
    "addr:housenumber":"21709",
    "addr:postcode":"98026",
    "addr:street":"82Nd Ave W",
    "iso:country":"US",
    "sg:address":"21709 82nd Ave W",
    "sg:city":"Edmonds",
    "sg:classifiers":[
        {
            "category":"Professional",
            "subcategory":"Art Services",
            "type":"Services"
        }
    ],
    "sg:phone":"+1 425 771 6528",
    "sg:postcode":"98026",
    "sg:province":"WA",
    "sg:tags":[
        "commercial",
        "design"
    ],
    "wof:name":"Sound Web Designs",
    "wof:placetype":"venue"
},
  "geometry": {"coordinates":[-122.34331299999999,47.802422],"type":"Point"}
}