{
  "type": "Feature",
  "properties": {
    "addr:full":"1410 Bay Ave Ocean Park WA 98640",
    "addr:housenumber":"1410",
    "addr:postcode":"98640",
    "addr:street":"Bay Ave",
    "iso:country":"US",
    "sg:address":"1410 Bay Ave",
    "sg:city":"Ocean Park",
    "sg:classifiers":[
        {
            "category":"Social Services",
            "type":"Services"
        }
    ],
    "sg:phone":"+1 360 665 3557",
    "sg:postcode":"98640",
    "sg:province":"WA",
    "wof:name":"Sound Counseling Service",
    "wof:placetype":"venue"
},
  "geometry": {"coordinates":[-124.050082,46.491423],"type":"Point"}
}