{
  "type": "Feature",
  "properties": {
    "iso:country":"US",
    "sg:address":"12016 SE McGillivray Blvd",
    "sg:city":"Vancouver",
    "sg:classifiers":[
        {
            "category":"Education",
            "subcategory":"Special Training",
            "type":"Public Place"
        }
    ],
    "sg:phone":"+1 360 944 8085",
    "sg:postcode":"98683",
    "sg:province":"WA",
    "wof:name":"Washington SW Music Studios",
    "wof:placetype":"venue"
},
  "geometry": {"coordinates":[-122.54825700000001,45.612916],"type":"Point"}
}