{
  "type": "Feature",
  "properties": {
    "addr:full":"5409 17th Ave NW Seattle WA 98107",
    "addr:housenumber":"5409",
    "addr:postcode":"98107",
    "addr:street":"17Th Ave Nw",
    "iso:country":"US",
    "sg:address":"5409 17th Ave NW",
    "sg:city":"Seattle",
    "sg:classifiers":[
        {
            "category":"Health Services",
            "subcategory":"Health Practitioner",
            "type":"Services"
        }
    ],
    "sg:phone":"+1 206 784 7471",
    "sg:postcode":"98107",
    "sg:province":"WA",
    "sg:tags":[
        "therapy",
        "physical"
    ],
    "sg:website":"www.bend2mend.com/",
    "wof:name":"Bend to Mend Physical Therapy",
    "wof:placetype":"venue"
},
  "geometry": {"coordinates":[-122.37890899999999,47.667707],"type":"Point"}
}