{
  "type": "Feature",
  "properties": {
    "addr:full":"304 36th St Bellingham WA 98225",
    "addr:housenumber":"304",
    "addr:postcode":"98225",
    "addr:street":"36Th St",
    "iso:country":"US",
    "sg:address":"304 36th St",
    "sg:city":"Bellingham",
    "sg:classifiers":[
        {
            "category":"Professional",
            "subcategory":"Engineering",
            "type":"Services"
        }
    ],
    "sg:phone":"+1 360 733 3598",
    "sg:postcode":"98225",
    "sg:province":"WA",
    "sg:tags":[
        "engineer"
    ],
    "wof:name":"Hydro-Care International Inc",
    "wof:placetype":"venue"
},
  "geometry": {"coordinates":[-122.469785,48.733176],"type":"Point"}
}