{
  "type": "Feature",
  "properties": {
    "addr:full":"701 N Garrison Rd Vancouver WA 98664",
    "addr:housenumber":"701",
    "addr:postcode":"98664",
    "addr:street":"N Garrison Rd",
    "iso:country":"US",
    "sg:address":"701 N Garrison Rd",
    "sg:city":"Vancouver",
    "sg:classifiers":[
        {
            "category":"Organizations",
            "subcategory":"Religious Organization",
            "type":"Services"
        }
    ],
    "sg:phone":"+1 360 993 1296",
    "sg:postcode":"98664",
    "sg:province":"WA",
    "sg:tags":[
        "place",
        "worship",
        "church"
    ],
    "wof:name":"New Life Christian Center",
    "wof:placetype":"venue"
},
  "geometry": {"coordinates":[-122.591264,45.625251],"type":"Point"}
}