{
  "type": "Feature",
  "properties": {
    "addr:full":"25 35th Ave NW Gig Harbor WA 98335",
    "addr:housenumber":"25",
    "addr:postcode":"98335",
    "addr:street":"35Th Ave Nw",
    "iso:country":"US",
    "sg:address":"25 35th Ave NW",
    "sg:city":"Gig Harbor",
    "sg:classifiers":[
        {
            "category":"Professional",
            "subcategory":"Computer Services",
            "type":"Services"
        }
    ],
    "sg:phone":"+1 253 858 2856",
    "sg:postcode":"98335",
    "sg:province":"WA",
    "sg:tags":[
        "prepackaged",
        "software"
    ],
    "wof:name":"Exodus Software",
    "wof:placetype":"venue"
},
  "geometry": {"coordinates":[-122.585813,47.257036],"type":"Point"}
}