{
  "type": "Feature",
  "properties": {
    "addr:full":"421 E Kennewick Ave Kennewick WA 99336",
    "addr:housenumber":"421",
    "addr:postcode":"99336",
    "addr:street":"E Kennewick Ave",
    "iso:country":"US",
    "sg:address":"421 E Kennewick Ave",
    "sg:city":"Kennewick",
    "sg:classifiers":[
        {
            "category":"Building & Trades",
            "subcategory":"Electrical",
            "type":"Services"
        }
    ],
    "sg:phone":"+1 509 735 6943",
    "sg:postcode":"99336",
    "sg:province":"WA",
    "sg:tags":[
        "security",
        "electronic",
        "system"
    ],
    "wof:name":"ADT Security Services Inc",
    "wof:placetype":"venue"
},
  "geometry": {"coordinates":[-119.10880299999999,46.208521],"type":"Point"}
}