{
  "type": "Feature",
  "properties": {
    "addr:full":"306 S Adams St Ritzville WA 99169",
    "addr:housenumber":"306",
    "addr:postcode":"99169",
    "addr:street":"S Adams St",
    "iso:country":"US",
    "sg:address":"306 S Adams St",
    "sg:city":"Ritzville",
    "sg:classifiers":[
        {
            "category":"Retail",
            "subcategory":"Auto Repair",
            "type":"Services"
        }
    ],
    "sg:phone":"+1 509 659 0146",
    "sg:postcode":"99169",
    "sg:province":"WA",
    "sg:tags":[
        "general"
    ],
    "wof:name":"Waynes Auto Repair",
    "wof:placetype":"venue"
},
  "geometry": {"coordinates":[-118.37772200000001,47.123932],"type":"Point"}
}