{
  "type": "Feature",
  "properties": {
    "addr:full":"44025 State Rte 161 Eatonville WA 98328",
    "addr:housenumber":"44025",
    "addr:postcode":"98328",
    "addr:street":"State Rte 161",
    "iso:country":"US",
    "sg:address":"44025 State Rte 161",
    "sg:city":"Eatonville",
    "sg:classifiers":[
        {
            "category":"Retail",
            "subcategory":"Repair Shop",
            "type":"Services"
        }
    ],
    "sg:phone":"+1 360 832 6541",
    "sg:postcode":"98328",
    "sg:province":"WA",
    "sg:tags":[
        "welding"
    ],
    "wof:name":"Eatonville Portable Welding",
    "wof:placetype":"venue"
},
  "geometry": {"coordinates":[-122.279285,46.855101],"type":"Point"}
}