{
  "type": "Feature",
  "properties": {
    "addr:full":"847 Minard Ave NW Ocean Shores WA 98569",
    "addr:housenumber":"847",
    "addr:postcode":"98569",
    "addr:street":"Minard Ave Nw",
    "iso:country":"US",
    "sg:address":"847 Minard Ave NW",
    "sg:city":"Ocean Shores",
    "sg:classifiers":[
        {
            "category":"Building & Trades",
            "subcategory":"Construction",
            "type":"Services"
        }
    ],
    "sg:phone":"+1 360 289 8030",
    "sg:postcode":"98569",
    "sg:province":"WA",
    "sg:tags":[
        "house"
    ],
    "wof:name":"Ocean Beach Construction",
    "wof:placetype":"venue"
},
  "geometry": {"coordinates":[-124.162994,47.013716],"type":"Point"}
}