{
  "type": "Feature",
  "properties": {
    "addr:full":"5870 S 194th St Kent WA 98032",
    "addr:housenumber":"5870",
    "addr:postcode":"98032",
    "addr:street":"S 194Th St",
    "iso:country":"US",
    "sg:address":"5870 S 194th St",
    "sg:city":"Kent",
    "sg:classifiers":[
        {
            "category":"Wholesale",
            "subcategory":"Medical Equipment & Supplies",
            "type":"Manufacturing & Wholesale Goods"
        },
        {
            "category":"Shopping",
            "subcategory":"Pharmacy",
            "type":"Retail Goods"
        },
        {
            "category":"Health Services",
            "subcategory":"Dentist",
            "type":"Services"
        }
    ],
    "sg:phone":"+1 206 243 4214",
    "sg:postcode":"98032",
    "sg:province":"WA",
    "sg:tags":[
        "instrument",
        "surgical",
        "care",
        "dental",
        "home"
    ],
    "sg:website":"http://www.myotronics.com",
    "wof:name":"Myo-Tronics",
    "wof:placetype":"venue"
},
  "geometry": {"coordinates":[-122.265531,47.425855],"type":"Point"}
}