{
  "type": "Feature",
  "properties": {
    "addr:full":"1842 Iron St Ste B Bellingham WA 98225",
    "addr:housenumber":"1842",
    "addr:postcode":"98225",
    "addr:street":"Iron St Ste B",
    "iso:country":"US",
    "sg:address":"1842 Iron St Ste B",
    "sg:city":"Bellingham",
    "sg:classifiers":[
        {
            "category":"Health Services",
            "subcategory":"Chiropractor",
            "type":"Services"
        }
    ],
    "sg:phone":"+1 360 676 1140",
    "sg:postcode":"98225",
    "sg:province":"WA",
    "sg:tags":[
        "chiropractic"
    ],
    "wof:name":"Bellingham Chiropractic Center Inc PS",
    "wof:placetype":"venue"
},
  "geometry": {"coordinates":[-122.466362,48.754719],"type":"Point"}
}