{
  "type": "Feature",
  "properties": {
    "addr:full":"4701 NE 4th St Renton WA 98059",
    "addr:housenumber":"4701",
    "addr:postcode":"98059",
    "addr:street":"Ne 4Th St",
    "iso:country":"US",
    "sg:address":"4701 NE 4th St",
    "sg:city":"Renton",
    "sg:classifiers":[
        {
            "category":"Ice Cream",
            "type":"Food & Drink"
        }
    ],
    "sg:menulink":"http://www.allmenus.com/wa/east-seattle/192753-dairy-queen/menu/",
    "sg:phone":"+1 425 227 7118",
    "sg:postcode":"98059",
    "sg:province":"WA",
    "sg:tags":[
        "burger",
        "american"
    ],
    "wof:name":"Dairy Queen",
    "wof:placetype":"venue"
},
  "geometry": {"coordinates":[-122.156279,47.488514],"type":"Point"}
}