{
  "type": "Feature",
  "properties": {
    "addr:full":"619 N 35th St Ste 330M Seattle WA 98103",
    "addr:housenumber":"619",
    "addr:postcode":"98103",
    "addr:street":"N 35Th St Ste 330M",
    "iso:country":"US",
    "sg:address":"619 N 35th St Ste 330M",
    "sg:city":"Seattle",
    "sg:classifiers":[
        {
            "category":"Travel",
            "subcategory":"Travel Agent",
            "type":"Entertainment"
        }
    ],
    "sg:phone":"+1 206 547 8361",
    "sg:postcode":"98103",
    "sg:province":"WA",
    "sg:website":"www.elizabethholmes.com",
    "wof:name":"Elizabeth Holmes Travel Inc",
    "wof:placetype":"venue"
},
  "geometry": {"coordinates":[-122.350998,47.6507],"type":"Point"}
}