{
  "type": "Feature",
  "properties": {
    "addr:full":"261 5th St Bremerton WA 98337",
    "addr:housenumber":"261",
    "addr:postcode":"98337",
    "addr:street":"5Th St",
    "iso:country":"US",
    "sg:address":"261 5th St",
    "sg:city":"Bremerton",
    "sg:classifiers":[
        {
            "category":"Professional",
            "type":"Services"
        }
    ],
    "sg:phone":"+1 360 373 3325",
    "sg:postcode":"98337",
    "sg:province":"WA",
    "sg:tags":[
        "establishment"
    ],
    "wof:name":"Pacific Associates",
    "wof:placetype":"venue"
},
  "geometry": {"coordinates":[-122.62649999999999,47.566474],"type":"Point"}
}