{
  "type": "Feature",
  "properties": {
    "addr:full":"1565 6th Ave S Seattle WA 98134",
    "addr:housenumber":"1565",
    "addr:postcode":"98134",
    "addr:street":"6Th Ave S",
    "iso:country":"US",
    "sg:address":"1565 6th Ave S",
    "sg:city":"Seattle",
    "sg:classifiers":[
        {
            "category":"Professional",
            "subcategory":"Computer Services",
            "type":"Services"
        }
    ],
    "sg:phone":"+1 866 972 6938",
    "sg:postcode":"98134",
    "sg:province":"WA",
    "sg:tags":[
        "repair",
        "equipment-service"
    ],
    "sg:website":"http://www.repc.com",
    "wof:name":"RE-PC Recycled Computers & Peripherals",
    "wof:placetype":"venue"
},
  "geometry": {"coordinates":[-122.325976,47.589638],"type":"Point"}
}