{
  "type": "Feature",
  "properties": {
    "addr:full":"3502 Inverness Dr NE Tacoma WA 98422",
    "addr:housenumber":"3502",
    "addr:postcode":"98422",
    "addr:street":"Inverness Dr Ne",
    "iso:country":"US",
    "sg:address":"3502 Inverness Dr NE",
    "sg:city":"Tacoma",
    "sg:classifiers":[
        {
            "category":"Sports & Exercise",
            "subcategory":"Gym",
            "type":"Entertainment"
        }
    ],
    "sg:phone":"+1 253 927 4460",
    "sg:postcode":"98422",
    "sg:province":"WA",
    "sg:tags":[
        "fitness",
        "physical",
        "facility"
    ],
    "wof:name":"N S T Inc",
    "wof:placetype":"venue"
},
  "geometry": {"coordinates":[-122.403052,47.291497],"type":"Point"}
}