{
  "type": "Feature",
  "properties": {
    "addr:full":"23953 SE 7th St Sammamish WA 98074",
    "addr:housenumber":"23953",
    "addr:postcode":"98074",
    "addr:street":"Se 7Th St",
    "iso:country":"US",
    "sg:address":"23953 SE 7th St",
    "sg:city":"Sammamish",
    "sg:classifiers":[
        {
            "category":"Professional",
            "subcategory":"Employment Agencies",
            "type":"Services"
        }
    ],
    "sg:phone":"+1 425 369 9700",
    "sg:postcode":"98074",
    "sg:province":"WA",
    "wof:name":"Emerald Exactive Search",
    "wof:placetype":"venue"
},
  "geometry": {"coordinates":[-122.020618,47.602579],"type":"Point"}
}