{
  "type": "Feature",
  "properties": {
    "addr:full":"1111 S Thor St Spokane WA 99202",
    "addr:housenumber":"1111",
    "addr:postcode":"99202",
    "addr:street":"S Thor St",
    "iso:country":"US",
    "sg:address":"1111 S Thor St",
    "sg:city":"Spokane",
    "sg:classifiers":[
        {
            "category":"Social Services",
            "subcategory":"Child Care",
            "type":"Services"
        }
    ],
    "sg:phone":"+1 509 534 7755",
    "sg:postcode":"99202",
    "sg:province":"WA",
    "wof:name":"Bethel Christian Preschool",
    "wof:placetype":"venue"
},
  "geometry": {"coordinates":[-117.36027799999999,47.644634],"type":"Point"}
}