{
  "type": "Feature",
  "properties": {
    "addr:full":"710 Lebo Blvd Bremerton WA 98310",
    "addr:housenumber":"710",
    "addr:postcode":"98310",
    "addr:street":"Lebo Blvd",
    "iso:country":"US",
    "sg:address":"710 Lebo Blvd",
    "sg:city":"Bremerton",
    "sg:classifiers":[
        {
            "category":"Health Services",
            "subcategory":"Chiropractor",
            "type":"Services"
        }
    ],
    "sg:phone":"+1 360 377 1626",
    "sg:postcode":"98310",
    "sg:province":"WA",
    "wof:name":"Goodman Chiropractic Svc",
    "wof:placetype":"venue"
},
  "geometry": {"coordinates":[-122.62718,47.581635],"type":"Point"}
}