{
  "type": "Feature",
  "properties": {
    "addr:full":"6132 Evergreen Way Everett WA 98203",
    "addr:housenumber":"6132",
    "addr:postcode":"98203",
    "addr:street":"Evergreen Way",
    "iso:country":"US",
    "sg:address":"6132 Evergreen Way",
    "sg:city":"Everett",
    "sg:classifiers":[
        {
            "category":"Autos & Motor Vehicles",
            "subcategory":"Fuel & Gas Station",
            "type":"Retail Goods"
        }
    ],
    "sg:phone":"+1 425 353 6264",
    "sg:postcode":"98203",
    "sg:province":"WA",
    "sg:tags":[
        "grocery",
        "gasoline"
    ],
    "wof:name":"99 Market",
    "wof:placetype":"venue"
},
  "geometry": {"coordinates":[-122.217343,47.942777],"type":"Point"}
}