{
  "type": "Feature",
  "properties": {
    "addr:full":"7453 Thiel Rd Lynden WA 98264",
    "addr:housenumber":"7453",
    "addr:postcode":"98264",
    "addr:street":"Thiel Rd",
    "iso:country":"US",
    "sg:address":"7453 Thiel Rd",
    "sg:city":"Lynden",
    "sg:classifiers":[
        {
            "category":"Professional",
            "subcategory":"Engineering",
            "type":"Services"
        }
    ],
    "sg:phone":"+1 360 354 5637",
    "sg:postcode":"98264",
    "sg:province":"WA",
    "wof:name":"Schoutn Construction",
    "wof:placetype":"venue"
},
  "geometry": {"coordinates":[-122.420073,48.909138],"type":"Point"}
}