{
  "type": "Feature",
  "properties": {
    "iso:country":"US",
    "sg:address":"1331 Hoctor Rd",
    "sg:city":"Goldendale",
    "sg:classifiers":[
        {
            "category":"Manufacturing",
            "subcategory":"Tools & Machinery",
            "type":"Manufacturing & Wholesale Goods"
        }
    ],
    "sg:phone":"+1 509 773 6027",
    "sg:postcode":"98620",
    "sg:province":"WA",
    "sg:tags":[
        "windmill",
        "generating",
        "electric"
    ],
    "wof:name":"Mariah Energy Group LLC",
    "wof:placetype":"venue"
},
  "geometry": {"coordinates":[-120.51774,45.779771],"type":"Point"}
}