{
  "type": "Feature",
  "properties": {
    "iso:country":"US",
    "sg:address":"23424 68th Ave S",
    "sg:city":"Kent",
    "sg:classifiers":[
        {
            "category":"Wholesale",
            "subcategory":"Non-durable Goods",
            "type":"Manufacturing & Wholesale Goods"
        }
    ],
    "sg:phone":"+1 253 852 0886",
    "sg:postcode":"98032",
    "sg:province":"WA",
    "sg:tags":[
        "equipment",
        "transportation"
    ],
    "wof:name":"Catic Seatle",
    "wof:placetype":"venue"
},
  "geometry": {"coordinates":[-122.248947,47.389515],"type":"Point"}
}