{
  "type": "Feature",
  "properties": {
    "addr:full":"3754 S 172nd St Seattle WA 98188",
    "addr:housenumber":"3754",
    "addr:postcode":"98188",
    "addr:street":"S 172Nd St",
    "iso:country":"US",
    "sg:address":"3754 S 172nd St",
    "sg:city":"Seattle",
    "sg:classifiers":[
        {
            "category":"Organizations",
            "subcategory":"Religious Organization",
            "type":"Services"
        }
    ],
    "sg:phone":"+1 206 248 3340",
    "sg:postcode":"98188",
    "sg:province":"WA",
    "wof:name":"McMicken Heights Church",
    "wof:placetype":"venue"
},
  "geometry": {"coordinates":[-122.28574999999999,47.449594],"type":"Point"}
}