{
  "type": "Feature",
  "properties": {
    "addr:full":"102 23rd Ave SE Ste A Puyallup WA 98372",
    "addr:housenumber":"102",
    "addr:postcode":"98372",
    "addr:street":"23Rd Ave Se Ste A",
    "iso:country":"US",
    "sg:address":"102 23rd Ave SE Ste A",
    "sg:city":"Puyallup",
    "sg:classifiers":[
        {
            "category":"Health Services",
            "subcategory":"Doctor",
            "type":"Services"
        }
    ],
    "sg:phone":"+1 253 446 0311",
    "sg:postcode":"98372",
    "sg:province":"WA",
    "sg:tags":[
        "physician",
        "rheumatology",
        "arthritis",
        "surgeons",
        "surgeon"
    ],
    "wof:name":"Nancy S Karr Md Rheumatology",
    "wof:placetype":"venue"
},
  "geometry": {"coordinates":[-122.293463,47.1698],"type":"Point"}
}