{
  "type": "Feature",
  "properties": {
    "iso:country":"US",
    "sg:address":"1100 Olive Way",
    "sg:city":"Seattle",
    "sg:classifiers":[
        {
            "category":"Professional",
            "subcategory":"Management & Consulting",
            "type":"Services"
        }
    ],
    "sg:phone":"+1 253 284 8100",
    "sg:postcode":"98101",
    "sg:province":"WA",
    "sg:tags":[
        "application",
        "develops",
        "maintains",
        "security"
    ],
    "wof:name":"PRI",
    "wof:placetype":"venue"
},
  "geometry": {"coordinates":[-122.329638,47.615925],"type":"Point"}
}