{
  "type": "Feature",
  "properties": {
    "addr:full":"718 Sycamore St Clarkston WA 99403",
    "addr:housenumber":"718",
    "addr:postcode":"99403",
    "addr:street":"Sycamore St",
    "iso:country":"US",
    "sg:address":"718 Sycamore St",
    "sg:city":"Clarkston",
    "sg:classifiers":[
        {
            "category":"Organizations",
            "subcategory":"Religious Organization",
            "type":"Services"
        }
    ],
    "sg:phone":"+1 509 751 9513",
    "sg:postcode":"99403",
    "sg:province":"WA",
    "wof:name":"Fathers House Fellowship Intl",
    "wof:placetype":"venue"
},
  "geometry": {"coordinates":[-117.047027,46.412775],"type":"Point"}
}