{
  "type": "Feature",
  "properties": {
    "addr:full":"1327 Whitehouse Ave Buckley WA 98321",
    "addr:housenumber":"1327",
    "addr:postcode":"98321",
    "addr:street":"Whitehouse Ave",
    "iso:country":"US",
    "sg:address":"1327 Whitehouse Ave",
    "sg:city":"Buckley",
    "sg:classifiers":[
        {
            "category":"Professional",
            "subcategory":"Accounting & Tax Preparation",
            "type":"Services"
        }
    ],
    "sg:phone":"+1 360 829 8095",
    "sg:postcode":"98321",
    "sg:province":"WA",
    "wof:name":"Pacific NW Medical Billing",
    "wof:placetype":"venue"
},
  "geometry": {"coordinates":[-122.019566,47.167484],"type":"Point"}
}