{
  "type": "Feature",
  "properties": {
    "addr:full":"10116 NE 8th St Bellevue WA 98004",
    "addr:housenumber":"10116",
    "addr:postcode":"98004",
    "addr:street":"Ne 8Th St",
    "iso:country":"US",
    "sg:address":"10116 NE 8th St",
    "sg:city":"Bellevue",
    "sg:classifiers":[
        {
            "category":"Food & Beverages",
            "subcategory":"Groceries & Convenience Stores",
            "type":"Retail Goods"
        }
    ],
    "sg:phone":"+1 425 455 0870",
    "sg:postcode":"98004",
    "sg:province":"WA",
    "sg:website":"www.qfc.com",
    "wof:name":"QFC Quality Food Center",
    "wof:placetype":"venue"
},
  "geometry": {"coordinates":[-122.204201,47.617451],"type":"Point"}
}