{
  "type": "Feature",
  "properties": {
    "addr:full":"3012 22nd Ave S Seattle WA 98144",
    "addr:housenumber":"3012",
    "addr:postcode":"98144",
    "addr:street":"22Nd Ave S",
    "iso:country":"US",
    "sg:address":"3012 22nd Ave S",
    "sg:city":"Seattle",
    "sg:classifiers":[
        {
            "category":"Building & Trades",
            "subcategory":"Construction",
            "type":"Services"
        }
    ],
    "sg:phone":"+1 206 769 4351",
    "sg:postcode":"98144",
    "sg:province":"WA",
    "sg:tags":[
        "painting",
        "contractor"
    ],
    "wof:name":"Ackerlund Brothers Painting",
    "wof:placetype":"venue"
},
  "geometry": {"coordinates":[-122.304266,47.575984],"type":"Point"}
}