{
  "type": "Feature",
  "properties": {
    "addr:full":"3170 Progressive Rd Wapato WA 98951",
    "addr:housenumber":"3170",
    "addr:postcode":"98951",
    "addr:street":"Progressive Rd",
    "iso:country":"US",
    "sg:address":"3170 Progressive Rd",
    "sg:city":"Wapato",
    "sg:classifiers":[
        {
            "category":"Shopping",
            "type":"Retail Goods"
        }
    ],
    "sg:phone":"+1 509 877 2248",
    "sg:postcode":"98951",
    "sg:province":"WA",
    "sg:tags":[
        "merchandise"
    ],
    "wof:name":"Elite Designs",
    "wof:placetype":"venue"
},
  "geometry": {"coordinates":[-120.464445,46.419124],"type":"Point"}
}