{
  "type": "Feature",
  "properties": {
    "addr:full":"1825 Leslie Rd Richland WA 99352",
    "addr:housenumber":"1825",
    "addr:postcode":"99352",
    "addr:street":"Leslie Rd",
    "iso:country":"US",
    "sg:address":"1825 Leslie Rd",
    "sg:city":"Richland",
    "sg:classifiers":[
        {
            "category":"Structure",
            "subcategory":"Office Building",
            "type":"Public Place"
        }
    ],
    "sg:phone":"+1 509 627 1981",
    "sg:postcode":"99352",
    "sg:province":"WA",
    "sg:tags":[
        "park"
    ],
    "wof:name":"Cap Properties",
    "wof:placetype":"venue"
},
  "geometry": {"coordinates":[-119.264824,46.2267],"type":"Point"}
}