{
  "type": "Feature",
  "properties": {
    "addr:full":"18528 Brittany Dr SW Seattle WA 98166",
    "addr:postcode":"18528;98166",
    "addr:street":"Brittany Dr Sw",
    "iso:country":"US",
    "sg:address":"18528 Brittany Dr SW",
    "sg:city":"Seattle",
    "sg:classifiers":[
        {
            "category":"Travel",
            "subcategory":"Bed & Breakfast",
            "type":"Entertainment"
        }
    ],
    "sg:phone":"+1 206 244 8092",
    "sg:postcode":"98166",
    "sg:province":"WA",
    "sg:tags":[
        "house"
    ],
    "wof:name":"Tahn Associates LLC",
    "wof:placetype":"venue"
},
  "geometry": {"coordinates":[-122.34842,47.435987],"type":"Point"}
}