{
  "type": "Feature",
  "properties": {
    "addr:full":"220 S Lincoln St Port Angeles WA 98362",
    "addr:housenumber":"220",
    "addr:postcode":"98362",
    "addr:street":"S Lincoln St",
    "iso:country":"US",
    "sg:address":"220 S Lincoln St",
    "sg:city":"Port Angeles",
    "sg:classifiers":[
        {
            "category":"Banks & Credit Unions",
            "subcategory":"Bank",
            "type":"Services"
        }
    ],
    "sg:phone":"+1 360 452 3883",
    "sg:postcode":"98362",
    "sg:province":"WA",
    "wof:name":"Strait View Credit Union",
    "wof:placetype":"venue"
},
  "geometry": {"coordinates":[-123.432688,48.117243],"type":"Point"}
}