{
  "type": "Feature",
  "properties": {
    "addr:full":"21632 Rd 24.1 SW Mattawa WA 99349",
    "addr:housenumber":"21632;24.1",
    "addr:postcode":"99349",
    "addr:street":"Rd;Sw Mattawa",
    "iso:country":"US",
    "sg:address":"21632 Rd 24.1 SW",
    "sg:city":"Mattawa",
    "sg:classifiers":[
        {
            "category":"Farming",
            "subcategory":"Farm",
            "type":"Manufacturing & Wholesale Goods"
        }
    ],
    "sg:phone":"+1 509 932 5355",
    "sg:postcode":"99349",
    "sg:province":"WA",
    "sg:tags":[
        "crop",
        "general"
    ],
    "wof:name":"Kc Farms",
    "wof:placetype":"venue"
},
  "geometry": {"coordinates":[-119.94693700000001,46.735513],"type":"Point"}
}