{
  "type": "Feature",
  "properties": {
    "addr:full":"18317 NE 76th St Redmond WA 98052",
    "addr:housenumber":"18317",
    "addr:postcode":"98052",
    "addr:street":"Ne 76Th St",
    "iso:country":"US",
    "sg:address":"18317 NE 76th St",
    "sg:city":"Redmond",
    "sg:phone":"+1 425 883 4408",
    "sg:postcode":"98052",
    "sg:province":"WA",
    "wof:name":"Keller Supply Co",
    "wof:placetype":"venue"
},
  "geometry": {"coordinates":[-122.099413,47.672102],"type":"Point"}
}