{
  "type": "Feature",
  "properties": {
    "addr:full":"1106 S Jurupa St Kennewick WA 99338",
    "addr:housenumber":"1106",
    "addr:postcode":"99338",
    "addr:street":"S Jurupa St",
    "iso:country":"US",
    "sg:address":"1106 S Jurupa St",
    "sg:city":"Kennewick",
    "sg:classifiers":[
        {
            "category":"Wholesale",
            "subcategory":"Wine & Distilled Alcoholic Beverages",
            "type":"Manufacturing & Wholesale Goods"
        }
    ],
    "sg:phone":"+1 509 627 4986",
    "sg:postcode":"99338",
    "sg:province":"WA",
    "sg:tags":[
        "vineyard",
        "grape",
        "winery",
        "operates"
    ],
    "wof:name":"Badger Mtn Vnyrd Powers Winery",
    "wof:placetype":"venue"
},
  "geometry": {"coordinates":[-119.29152000000001,46.209159],"type":"Point"}
}