{
  "type": "Feature",
  "properties": {
    "iso:country":"US",
    "sg:address":"7219 25th St W",
    "sg:city":"Tacoma",
    "sg:classifiers":[
        {
            "category":"Building & Trades",
            "subcategory":"Construction",
            "type":"Services"
        }
    ],
    "sg:phone":"+1 253 566 3585",
    "sg:postcode":"98466",
    "sg:province":"WA",
    "sg:tags":[
        "roofing",
        "contractor"
    ],
    "wof:name":"Light House Construction Inc",
    "wof:placetype":"venue"
},
  "geometry": {"coordinates":[-122.536869,47.237702],"type":"Point"}
}