{
  "type": "Feature",
  "properties": {
    "addr:full":"3471 Duckabush Rd Brinnon WA 98320",
    "addr:housenumber":"3471",
    "addr:postcode":"98320",
    "addr:street":"Duckabush Rd",
    "iso:country":"US",
    "sg:address":"3471 Duckabush Rd",
    "sg:city":"Brinnon",
    "sg:classifiers":[
        {
            "category":"Home & Garden",
            "subcategory":"Furniture",
            "type":"Retail Goods"
        },
        {
            "category":"Wholesale",
            "subcategory":"Home Furnishings",
            "type":"Manufacturing & Wholesale Goods"
        }
    ],
    "sg:phone":"+1 360 796 3365",
    "sg:postcode":"98320",
    "sg:province":"WA",
    "sg:tags":[
        "equipment-wholesale",
        "kitchen",
        "equipment-household",
        "manufacturer",
        "cabinet"
    ],
    "wof:name":"Sandquist Cabinets",
    "wof:placetype":"venue"
},
  "geometry": {"coordinates":[-122.973406,47.674148],"type":"Point"}
}