{
  "type": "Feature",
  "properties": {
    "addr:full":"7625 156th St SE Snohomish WA 98296",
    "addr:housenumber":"7625",
    "addr:postcode":"98296",
    "addr:street":"156Th St Se",
    "iso:country":"US",
    "sg:address":"7625 156th St SE",
    "sg:city":"Snohomish",
    "sg:classifiers":[
        {
            "category":"Professional",
            "subcategory":"Accounting & Tax Preparation",
            "type":"Services"
        }
    ],
    "sg:phone":"+1 360 668 1225",
    "sg:postcode":"98296",
    "sg:province":"WA",
    "wof:name":"Custom Ledger Business Svcs",
    "wof:placetype":"venue"
},
  "geometry": {"coordinates":[-122.130365,47.855979],"type":"Point"}
}