{
  "type": "Feature",
  "properties": {
    "addr:full":"7509 Canyon Rd E Puyallup WA 98371",
    "addr:housenumber":"7509",
    "addr:postcode":"98371",
    "addr:street":"Canyon Rd E",
    "iso:country":"US",
    "sg:address":"7509 Canyon Rd E",
    "sg:city":"Puyallup",
    "sg:classifiers":[
        {
            "category":"Freight",
            "type":"Transportation"
        }
    ],
    "sg:phone":"+1 253 537 7379",
    "sg:postcode":"98371",
    "sg:province":"WA",
    "sg:tags":[
        "trucking"
    ],
    "wof:name":"Gratzer & Co",
    "wof:placetype":"venue"
},
  "geometry": {"coordinates":[-122.357208,47.189297],"type":"Point"}
}