{
  "type": "Feature",
  "properties": {
    "addr:full":"2331 Colby Ave Everett WA 98201",
    "addr:housenumber":"2331",
    "addr:postcode":"98201",
    "addr:street":"Colby Ave",
    "iso:country":"US",
    "sg:address":"2331 Colby Ave",
    "sg:city":"Everett",
    "sg:classifiers":[
        {
            "category":"Real Estate",
            "subcategory":"Real Estate Operator",
            "type":"Services"
        }
    ],
    "sg:phone":"+1 425 252 7687",
    "sg:postcode":"98201",
    "sg:province":"WA",
    "sg:tags":[
        "apartment"
    ],
    "wof:name":"Edison Apartments",
    "wof:placetype":"venue"
},
  "geometry": {"coordinates":[-122.208364,47.986295],"type":"Point"}
}