{
  "type": "Feature",
  "properties": {
    "addr:full":"4442 San Juan Ave Port Townsend WA 98368",
    "addr:housenumber":"4442",
    "addr:postcode":"98368",
    "addr:street":"San Juan Ave",
    "iso:country":"US",
    "sg:address":"4442 San Juan Ave",
    "sg:city":"Port Townsend",
    "sg:classifiers":[
        {
            "category":"Arts & Performance",
            "subcategory":"Theater",
            "type":"Entertainment"
        }
    ],
    "sg:phone":"+1 360 385 6873",
    "sg:postcode":"98368",
    "sg:province":"WA",
    "sg:tags":[
        "theatrical"
    ],
    "wof:name":"Oracle",
    "wof:placetype":"venue"
},
  "geometry": {"coordinates":[-122.777717,48.131022],"type":"Point"}
}