{
  "type": "Feature",
  "properties": {
    "addr:full":"143 Gamble Ln Port Ludlow WA 98365",
    "addr:housenumber":"143",
    "addr:postcode":"98365",
    "addr:street":"Gamble Ln",
    "iso:country":"US",
    "sg:address":"143 Gamble Ln",
    "sg:city":"Port Ludlow",
    "sg:classifiers":[
        {
            "category":"Banks & Credit Unions",
            "subcategory":"Investment Brokerage",
            "type":"Services"
        }
    ],
    "sg:phone":"+1 360 437 0949",
    "sg:postcode":"98365",
    "sg:province":"WA",
    "sg:tags":[
        "funds",
        "mutual",
        "security"
    ],
    "wof:name":"Mutual Service Corporation",
    "wof:placetype":"venue"
},
  "geometry": {"coordinates":[-122.685714,47.926776],"type":"Point"}
}