{
  "type": "Feature",
  "properties": {
    "addr:full":"19501 144th Ave NE Woodinville WA 98072",
    "addr:housenumber":"19501",
    "addr:postcode":"98072",
    "addr:street":"144Th Ave Ne",
    "iso:country":"US",
    "sg:address":"19501 144th Ave NE",
    "sg:city":"Woodinville",
    "sg:classifiers":[
        {
            "category":"Wholesale",
            "subcategory":"Machinery & Supplies",
            "type":"Manufacturing & Wholesale Goods"
        },
        {
            "category":"Wholesale",
            "subcategory":"Durable Goods & Equipment",
            "type":"Manufacturing & Wholesale Goods"
        }
    ],
    "sg:phone":"+1 425 483 5613",
    "sg:postcode":"98072",
    "sg:province":"WA",
    "sg:tags":[
        "industrial",
        "representative",
        "manufacturer"
    ],
    "wof:name":"Control Factors Inc",
    "wof:placetype":"venue"
},
  "geometry": {"coordinates":[-122.147837,47.768986],"type":"Point"}
}