{
  "type": "Feature",
  "properties": {
    "iso:country":"US",
    "sg:address":"8322 Beaver Valley Rd",
    "sg:city":"Chimacum",
    "sg:classifiers":[
        {
            "category":"Retail",
            "subcategory":"Auto Repair",
            "type":"Services"
        }
    ],
    "sg:phone":"+1 360 732 4388",
    "sg:postcode":"98325",
    "sg:province":"WA",
    "sg:tags":[
        "body",
        "automobile",
        "painting"
    ],
    "wof:name":"Riggle Auto Body",
    "wof:placetype":"venue"
},
  "geometry": {"coordinates":[-122.758695,48.006876],"type":"Point"}
}