{
  "type": "Feature",
  "properties": {
    "addr:full":"2401 Utah Ave S Ste 305 Seattle WA 98134",
    "addr:housenumber":"2401",
    "addr:postcode":"98134",
    "addr:street":"Utah Ave S Ste 305",
    "iso:country":"US",
    "sg:address":"2401 Utah Ave S Ste 305",
    "sg:city":"Seattle",
    "sg:classifiers":[
        {
            "category":"Real Estate",
            "subcategory":"Real Estate Services",
            "type":"Services"
        },
        {
            "category":"Real Estate",
            "subcategory":"Real Estate Agent",
            "type":"Services"
        }
    ],
    "sg:phone":"+1 206 287 9055",
    "sg:postcode":"98134",
    "sg:province":"WA",
    "sg:tags":[
        "management"
    ],
    "wof:name":"Merrill Place",
    "wof:placetype":"venue"
},
  "geometry": {"coordinates":[-122.335121,47.581902],"type":"Point"}
}