{
  "type": "Feature",
  "properties": {
    "addr:full":"2000 Mallard Ln Aberdeen WA 98520",
    "addr:housenumber":"2000",
    "addr:postcode":"98520",
    "addr:street":"Mallard Ln",
    "iso:country":"US",
    "sg:address":"2000 Mallard Ln",
    "sg:city":"Aberdeen",
    "sg:classifiers":[
        {
            "category":"Building & Trades",
            "subcategory":"Construction",
            "type":"Services"
        }
    ],
    "sg:phone":"+1 360 538 4357",
    "sg:postcode":"98520",
    "sg:province":"WA",
    "sg:tags":[
        "general",
        "contractor"
    ],
    "wof:name":"B Pitts Construction Inc",
    "wof:placetype":"venue"
},
  "geometry": {"coordinates":[-123.697121,46.963452],"type":"Point"}
}