{
  "type": "Feature",
  "properties": {
    "iso:country":"US",
    "sg:address":"1235 Fowler St",
    "sg:city":"Raymond",
    "sg:classifiers":[
        {
            "category":"Utilities",
            "subcategory":"Telephone",
            "type":"Services"
        }
    ],
    "sg:phone":"+1 360 942 2278",
    "sg:postcode":"98577",
    "sg:province":"WA",
    "sg:tags":[
        "communications"
    ],
    "wof:name":"Traditions Old & New",
    "wof:placetype":"venue"
},
  "geometry": {"coordinates":[-123.739018,46.670852],"type":"Point"}
}