{
  "type": "Feature",
  "properties": {
    "addr:full":"2319 N 45th St Penthouse 1 Seattle WA 98103",
    "addr:housenumber":"2319;1",
    "addr:postcode":"98103",
    "addr:street":"N 45Th St",
    "iso:country":"US",
    "sg:address":"2319 N 45th St Penthouse 1",
    "sg:city":"Seattle",
    "sg:classifiers":[
        {
            "category":"Professional",
            "subcategory":"Art Services",
            "type":"Services"
        }
    ],
    "sg:phone":"+1 206 219 9751",
    "sg:postcode":"98103",
    "sg:province":"WA",
    "sg:tags":[
        "photographer"
    ],
    "sg:website":"www.boudoirphotographyseattle.com",
    "wof:name":"Belle Boudoir Photography",
    "wof:placetype":"venue"
},
  "geometry": {"coordinates":[-122.330506,47.661353],"type":"Point"}
}