{
  "type": "Feature",
  "properties": {
    "addr:full":"2912 Wilson Ave Bellingham WA 98225",
    "addr:housenumber":"2912",
    "addr:postcode":"98225",
    "addr:street":"Wilson Ave",
    "iso:country":"US",
    "sg:address":"2912 Wilson Ave",
    "sg:city":"Bellingham",
    "sg:classifiers":[
        {
            "category":"Real Estate",
            "subcategory":"Real Estate Agent",
            "type":"Services"
        }
    ],
    "sg:phone":"+1 360 671 6415",
    "sg:postcode":"98225",
    "sg:province":"WA",
    "wof:name":"Pacific Coast Realty",
    "wof:placetype":"venue"
},
  "geometry": {"coordinates":[-122.47925499999999,48.716358],"type":"Point"}
}