{
  "type": "Feature",
  "properties": {
    "iso:country":"US",
    "sg:address":"875 124th Ave NE",
    "sg:city":"Bellevue",
    "sg:classifiers":[
        {
            "category":"Professional",
            "subcategory":"Research",
            "type":"Services"
        }
    ],
    "sg:phone":"+1 425 226 7357",
    "sg:postcode":"98005",
    "sg:province":"WA",
    "sg:tags":[
        "educational"
    ],
    "wof:name":"Delta Society National Office",
    "wof:placetype":"venue"
},
  "geometry": {"coordinates":[-122.175055,47.618439],"type":"Point"}
}