{
  "type": "Feature",
  "properties": {
    "addr:full":"11507 105th Pl SW Vashon WA 98070",
    "addr:housenumber":"11507",
    "addr:postcode":"98070",
    "addr:street":"105Th Pl Sw",
    "iso:country":"US",
    "sg:address":"11507 105th Pl SW",
    "sg:city":"Vashon",
    "sg:classifiers":[
        {
            "category":"Utilities",
            "subcategory":"Water",
            "type":"Services"
        }
    ],
    "sg:phone":"+1 206 567 4688",
    "sg:postcode":"98070",
    "sg:province":"WA",
    "sg:tags":[
        "company",
        "sewage",
        "supply"
    ],
    "wof:name":"Burton Water Company",
    "wof:placetype":"venue"
},
  "geometry": {"coordinates":[-122.468667,47.502945],"type":"Point"}
}