{
  "type": "Feature",
  "properties": {
    "addr:full":"510 E Main Ave Puyallup WA 98372",
    "addr:housenumber":"510",
    "addr:postcode":"98372",
    "addr:street":"E Main Ave",
    "iso:country":"US",
    "sg:address":"510 E Main Ave",
    "sg:city":"Puyallup",
    "sg:classifiers":[
        {
            "category":"Government",
            "subcategory":"Office",
            "type":"Public Place"
        }
    ],
    "sg:phone":"+1 253 840 4766",
    "sg:postcode":"98372",
    "sg:province":"WA",
    "sg:tags":[
        "state",
        "resource",
        "social"
    ],
    "wof:name":"Vocational Rehabilitation",
    "wof:placetype":"venue"
},
  "geometry": {"coordinates":[-122.287706,47.191892],"type":"Point"}
}