{
  "type": "Feature",
  "properties": {
    "addr:full":"701 5th Ave S Seattle WA 98104",
    "addr:housenumber":"701",
    "addr:postcode":"98104",
    "addr:street":"5Th Ave S",
    "iso:country":"US",
    "sg:address":"701 5th Ave S",
    "sg:city":"Seattle",
    "sg:classifiers":[
        {
            "category":"Professional",
            "subcategory":"Lawyer & Legal Services",
            "type":"Services"
        }
    ],
    "sg:phone":"+1 206 587 5700",
    "sg:postcode":"98104",
    "sg:province":"WA",
    "wof:name":"Monahan & Biagi Pllc",
    "wof:placetype":"venue"
},
  "geometry": {"coordinates":[-122.327718,47.59581],"type":"Point"}
}