{
  "type": "Feature",
  "properties": {
    "addr:full":"1901 NE 14th St Renton WA 98056",
    "addr:housenumber":"1901",
    "addr:postcode":"98056",
    "addr:street":"Ne 14Th St",
    "iso:country":"US",
    "sg:address":"1901 NE 14th St",
    "sg:city":"Renton",
    "sg:classifiers":[
        {
            "category":"Building & Trades",
            "subcategory":"Construction",
            "type":"Services"
        }
    ],
    "sg:phone":"+1 425 226 7468",
    "sg:postcode":"98056",
    "sg:province":"WA",
    "sg:tags":[
        "hanging",
        "contractor"
    ],
    "wof:name":"Van Beek Painting Inc",
    "wof:placetype":"venue"
},
  "geometry": {"coordinates":[-122.192643,47.50467],"type":"Point"}
}