{
  "type": "Feature",
  "properties": {
    "addr:full":"5510 N Market St Spokane WA 99208",
    "addr:housenumber":"5510",
    "addr:postcode":"99208",
    "addr:street":"N Market St",
    "iso:country":"US",
    "sg:address":"5510 N Market St",
    "sg:city":"Spokane",
    "sg:classifiers":[
        {
            "category":"Bars & Pubs",
            "type":"Food & Drink"
        }
    ],
    "sg:phone":"+1 509 489 2073",
    "sg:postcode":"99208",
    "sg:province":"WA",
    "sg:tags":[
        "drinking"
    ],
    "wof:name":"Big Sky's",
    "wof:placetype":"venue"
},
  "geometry": {"coordinates":[-117.364699,47.708478],"type":"Point"}
}