{
  "type": "Feature",
  "properties": {
    "addr:full":"220 Reynolds Ln Selah WA 98942",
    "addr:housenumber":"220",
    "addr:postcode":"98942",
    "addr:street":"Reynolds Ln",
    "iso:country":"US",
    "sg:address":"220 Reynolds Ln",
    "sg:city":"Selah",
    "sg:classifiers":[
        {
            "category":"Wholesale",
            "subcategory":"Farm Supplies",
            "type":"Manufacturing & Wholesale Goods"
        }
    ],
    "sg:phone":"+1 509 697 4647",
    "sg:postcode":"98942",
    "sg:province":"WA",
    "sg:tags":[
        "feed",
        "concentrate",
        "supplement"
    ],
    "wof:name":"Dynamite Specialty Products",
    "wof:placetype":"venue"
},
  "geometry": {"coordinates":[-120.528553,46.682331],"type":"Point"}
}