{
  "type": "Feature",
  "properties": {
    "addr:full":"13128 Totem Lake Blvd NE Kirkland WA 98034",
    "addr:housenumber":"13128",
    "addr:postcode":"98034",
    "addr:street":"Totem Lake Blvd Ne",
    "iso:country":"US",
    "sg:address":"13128 Totem Lake Blvd NE",
    "sg:city":"Kirkland",
    "sg:classifiers":[
        {
            "category":"Health Services",
            "subcategory":"Clinic",
            "type":"Services"
        }
    ],
    "sg:phone":"+1 425 899 4030",
    "sg:postcode":"98034",
    "sg:province":"WA",
    "sg:tags":[
        "counseling",
        "mental"
    ],
    "wof:name":"Hager Margaret G Ms",
    "wof:placetype":"venue"
},
  "geometry": {"coordinates":[-122.185997,47.717899],"type":"Point"}
}