{
  "type": "Feature",
  "properties": {
    "addr:full":"7010 33rd Ave SE Lacey WA 98503",
    "addr:housenumber":"7010",
    "addr:postcode":"98503",
    "addr:street":"33Rd Ave Se",
    "iso:country":"US",
    "sg:address":"7010 33rd Ave SE",
    "sg:city":"Lacey",
    "sg:classifiers":[
        {
            "category":"Professional",
            "subcategory":"Management & Consulting",
            "type":"Services"
        }
    ],
    "sg:phone":"+1 360 491 2703",
    "sg:postcode":"98503",
    "sg:province":"WA",
    "sg:tags":[
        "business"
    ],
    "wof:name":"Gss Associates",
    "wof:placetype":"venue"
},
  "geometry": {"coordinates":[-122.784268,47.017461],"type":"Point"}
}