{
  "type": "Feature",
  "properties": {
    "iso:country":"US",
    "sg:address":"3908 161st Ave SE",
    "sg:city":"Bellevue",
    "sg:classifiers":[
        {
            "category":"Professional",
            "subcategory":"Management & Consulting",
            "type":"Services"
        }
    ],
    "sg:phone":"+1 425 562 1726",
    "sg:postcode":"98006",
    "sg:province":"WA",
    "sg:tags":[
        "business"
    ],
    "wof:name":"N3e Consulting LLC",
    "wof:placetype":"venue"
},
  "geometry": {"coordinates":[-122.125968,47.574528],"type":"Point"}
}