{
  "type": "Feature",
  "properties": {
    "addr:full":"12413 E Meridian Ave Puyallup WA 98373",
    "addr:housenumber":"12413",
    "addr:postcode":"98373",
    "addr:street":"E Meridian Ave",
    "iso:country":"US",
    "sg:address":"12413 E Meridian Ave",
    "sg:city":"Puyallup",
    "sg:classifiers":[
        {
            "category":"Banks & Credit Unions",
            "subcategory":"Bank",
            "type":"Services"
        }
    ],
    "sg:phone":"+1 253 435 1240",
    "sg:postcode":"98373",
    "sg:province":"WA",
    "sg:tags":[
        "personal",
        "institution"
    ],
    "wof:name":"Advance America",
    "wof:placetype":"venue"
},
  "geometry": {"coordinates":[-122.292883,47.14379],"type":"Point"}
}