{
  "type": "Feature",
  "properties": {
    "addr:full":"601 Bridge St Clarkston WA 99403",
    "addr:housenumber":"601",
    "addr:postcode":"99403",
    "addr:street":"Bridge St",
    "iso:country":"US",
    "sg:address":"601 Bridge St",
    "sg:city":"Clarkston",
    "sg:classifiers":[
        {
            "category":"Restaurant",
            "type":"Food & Drink"
        }
    ],
    "sg:phone":"+1 509 780 1005",
    "sg:postcode":"99403",
    "sg:province":"WA",
    "sg:tags":[
        "eating"
    ],
    "wof:name":"Little Reds Boathouse",
    "wof:placetype":"venue"
},
  "geometry": {"coordinates":[-117.04687,46.41993],"type":"Point"}
}