{
  "type": "Feature",
  "properties": {
    "addr:full":"4940 Orvas Ct SE Olympia WA 98501",
    "addr:housenumber":"4940",
    "addr:postcode":"98501",
    "addr:street":"Orvas Ct Se",
    "iso:country":"US",
    "sg:address":"4940 Orvas Ct SE",
    "sg:city":"Olympia",
    "sg:classifiers":[
        {
            "category":"Manufacturing",
            "subcategory":"Aerospace",
            "type":"Manufacturing & Wholesale Goods"
        }
    ],
    "sg:phone":"+1 360 357 4727",
    "sg:postcode":"98501",
    "sg:province":"WA",
    "sg:tags":[
        "aircraft",
        "mfg"
    ],
    "wof:name":"Turtle Airships Inc",
    "wof:placetype":"venue"
},
  "geometry": {"coordinates":[-122.877773,47.003152],"type":"Point"}
}