{
  "type": "Feature",
  "properties": {
    "addr:full":"327 Broadway E Seattle WA 98102",
    "addr:housenumber":"327",
    "addr:postcode":"98102",
    "addr:street":"Broadway",
    "iso:country":"US",
    "sg:address":"327 Broadway E",
    "sg:city":"Seattle",
    "sg:classifiers":[
        {
            "category":"Restaurant",
            "type":"Food & Drink"
        }
    ],
    "sg:phone":"+1 206 267 1530",
    "sg:postcode":"98102",
    "sg:province":"WA",
    "sg:tags":[
        "pizza"
    ],
    "wof:name":"Pizza Passion",
    "wof:placetype":"venue"
},
  "geometry": {"coordinates":[-122.32088299999999,47.621337],"type":"Point"}
}