{
  "type": "Feature",
  "properties": {
    "addr:full":"1131 SW 7th St Renton WA 98057",
    "addr:housenumber":"1131",
    "addr:postcode":"98057",
    "addr:street":"Sw 7Th St",
    "iso:country":"US",
    "sg:address":"1131 SW 7th St",
    "sg:city":"Renton",
    "sg:classifiers":[
        {
            "category":"Social Services",
            "type":"Services"
        }
    ],
    "sg:phone":"+1 206 826 1685",
    "sg:postcode":"98057",
    "sg:province":"WA",
    "sg:tags":[
        "program",
        "services-information",
        "referral"
    ],
    "wof:name":"Good Shepherd Communities",
    "wof:placetype":"venue"
},
  "geometry": {"coordinates":[-122.232732,47.473768],"type":"Point"}
}