{
  "type": "Feature",
  "properties": {
    "addr:full":"1823 Queen Anne Ave N Ste 102 Seattle WA 98109",
    "addr:housenumber":"1823",
    "addr:postcode":"98109",
    "addr:street":"Queen Anne Ave N Ste 102",
    "iso:country":"US",
    "sg:address":"1823 Queen Anne Ave N Ste 102",
    "sg:city":"Seattle",
    "sg:classifiers":[
        {
            "category":"Health Services",
            "subcategory":"Health Practitioner",
            "type":"Services"
        }
    ],
    "sg:phone":"+1 206 706 3747",
    "sg:postcode":"98109",
    "sg:province":"WA",
    "sg:tags":[
        "acupuncture"
    ],
    "wof:name":"Erin King, LAc",
    "wof:placetype":"venue"
},
  "geometry": {"coordinates":[-122.356983,47.635024],"type":"Point"}
}