{
  "type": "Feature",
  "properties": {
    "addr:full":"9 N Washington St Spokane WA 99201",
    "addr:housenumber":"9",
    "addr:postcode":"99201",
    "addr:street":"N Washington St",
    "iso:country":"US",
    "sg:address":"9 N Washington St",
    "sg:city":"Spokane",
    "sg:classifiers":[
        {
            "category":"Restaurant",
            "type":"Food & Drink"
        }
    ],
    "sg:phone":"+1 509 838 0260",
    "sg:postcode":"99201",
    "sg:province":"WA",
    "sg:tags":[
        "eating"
    ],
    "wof:name":"Mootsys North 9 Pizza",
    "wof:placetype":"venue"
},
  "geometry": {"coordinates":[-117.41810099999999,47.657895],"type":"Point"}
}