{
  "type": "Feature",
  "properties": {
    "addr:full":"620 Bender Ln Montesano WA 98563",
    "addr:housenumber":"620",
    "addr:postcode":"98563",
    "addr:street":"Bender Ln",
    "iso:country":"US",
    "sg:address":"620 Bender Ln",
    "sg:city":"Montesano",
    "sg:classifiers":[
        {
            "category":"Shopping",
            "type":"Retail Goods"
        }
    ],
    "sg:phone":"+1 360 249 5072",
    "sg:postcode":"98563",
    "sg:province":"WA",
    "sg:tags":[
        "merchandise"
    ],
    "wof:name":"Bird Feeder",
    "wof:placetype":"venue"
},
  "geometry": {"coordinates":[-123.581428,46.986398],"type":"Point"}
}