{
  "type": "Feature",
  "properties": {
    "addr:full":"11920 Cemetery Rd E Eatonville WA 98328",
    "addr:housenumber":"11920",
    "addr:postcode":"98328",
    "addr:street":"Cemetery Rd E",
    "iso:country":"US",
    "sg:address":"11920 Cemetery Rd E",
    "sg:city":"Eatonville",
    "sg:classifiers":[
        {
            "category":"Professional",
            "subcategory":"Art Services",
            "type":"Services"
        }
    ],
    "sg:phone":"+1 360 569 2550",
    "sg:postcode":"98328",
    "sg:province":"WA",
    "sg:tags":[
        "commercial",
        "design"
    ],
    "wof:name":"Jak Kelso Graphic Arts",
    "wof:placetype":"venue"
},
  "geometry": {"coordinates":[-122.274781,46.788881],"type":"Point"}
}