{
  "type": "Feature",
  "properties": {
    "addr:full":"19709 Highway 99 Ste D Lynnwood WA 98036",
    "addr:housenumber":"19709",
    "addr:postcode":"98036",
    "addr:street":"Highway 99 Ste D",
    "iso:country":"US",
    "sg:address":"19709 Highway 99 Ste D",
    "sg:city":"Lynnwood",
    "sg:classifiers":[
        {
            "category":"Personal",
            "subcategory":"Beauty Salon",
            "type":"Services"
        }
    ],
    "sg:phone":"+1 425 771 1049",
    "sg:postcode":"98036",
    "sg:province":"WA",
    "wof:name":"New Dimension Salon Hair Nails",
    "wof:placetype":"venue"
},
  "geometry": {"coordinates":[-122.316008,47.820133],"type":"Point"}
}