{
  "type": "Feature",
  "properties": {
    "addr:full":"130 E Sunset Way Issaquah WA 98027",
    "addr:housenumber":"130",
    "addr:postcode":"98027",
    "addr:street":"E Sunset Way",
    "iso:country":"US",
    "sg:address":"130 E Sunset Way",
    "sg:city":"Issaquah",
    "sg:classifiers":[
        {
            "category":"Government",
            "subcategory":"Office",
            "type":"Public Place"
        }
    ],
    "sg:phone":"+1 425 837 3033",
    "sg:postcode":"98027",
    "sg:province":"WA",
    "sg:tags":[
        "executive"
    ],
    "wof:name":"Executive Department",
    "wof:placetype":"venue"
},
  "geometry": {"coordinates":[-122.03482099999999,47.530175],"type":"Point"}
}