{
  "type": "Feature",
  "properties": {
    "addr:full":"217 Pine St Ste 700 Seattle WA 98101",
    "addr:housenumber":"217",
    "addr:postcode":"98101",
    "addr:street":"Pine St Ste 700",
    "iso:country":"US",
    "sg:address":"217 Pine St Ste 700",
    "sg:city":"Seattle",
    "sg:classifiers":[
        {
            "category":"Real Estate",
            "subcategory":"Architect",
            "type":"Services"
        }
    ],
    "sg:phone":"+1 206 624 2777",
    "sg:postcode":"98101",
    "sg:province":"WA",
    "wof:name":"Stemper Sm Architects",
    "wof:placetype":"venue"
},
  "geometry": {"coordinates":[-122.33941799999999,47.610357],"type":"Point"}
}