{
  "type": "Feature",
  "properties": {
    "addr:full":"2651 SE Mile Hill Dr Port Orchard WA 98366",
    "addr:housenumber":"2651",
    "addr:postcode":"98366",
    "addr:street":"Se Mile Hill Dr",
    "iso:country":"US",
    "sg:address":"2651 SE Mile Hill Dr",
    "sg:city":"Port Orchard",
    "sg:classifiers":[
        {
            "category":"Shopping",
            "subcategory":"Gifts & Souvenirs",
            "type":"Retail Goods"
        }
    ],
    "sg:phone":"+1 360 876 5193",
    "sg:postcode":"98366",
    "sg:province":"WA",
    "wof:name":"First Base Trading Cards",
    "wof:placetype":"venue"
},
  "geometry": {"coordinates":[-122.614828,47.534104],"type":"Point"}
}