{
  "type": "Feature",
  "properties": {
    "iso:country":"US",
    "sg:address":"1554 School Ave",
    "sg:city":"Walla Walla",
    "sg:classifiers":[
        {
            "category":"Farming",
            "subcategory":"Vineyard",
            "type":"Manufacturing & Wholesale Goods"
        }
    ],
    "sg:phone":"+1 509 522 1127",
    "sg:postcode":"99362",
    "sg:province":"WA",
    "sg:tags":[
        "grape"
    ],
    "wof:name":"Patrick M Paul Vineyards",
    "wof:placetype":"venue"
},
  "geometry": {"coordinates":[-118.29921899999999,46.051659],"type":"Point"}
}