{
  "type": "Feature",
  "properties": {
    "addr:full":"1102 SE 195th Ave Camas WA 98607",
    "addr:housenumber":"1102",
    "addr:postcode":"98607",
    "addr:street":"Se 195Th Ave",
    "iso:country":"US",
    "sg:address":"1102 SE 195th Ave",
    "sg:city":"Camas",
    "sg:classifiers":[
        {
            "category":"Retail",
            "subcategory":"Auto Repair",
            "type":"Services"
        }
    ],
    "sg:phone":"+1 360 834 7577",
    "sg:postcode":"98607",
    "sg:province":"WA",
    "sg:tags":[
        "general"
    ],
    "wof:name":"Rowe Brothers Rebuilders",
    "wof:placetype":"venue"
},
  "geometry": {"coordinates":[-122.473018,45.61359],"type":"Point"}
}