{
  "type": "Feature",
  "properties": {
    "addr:full":"2030 Toledo St Bellingham WA 98229",
    "addr:housenumber":"2030",
    "addr:postcode":"98229",
    "addr:street":"Toledo St",
    "iso:country":"US",
    "sg:address":"2030 Toledo St",
    "sg:city":"Bellingham",
    "sg:classifiers":[
        {
            "category":"Autos & Motor Vehicles",
            "subcategory":"Boat Sales",
            "type":"Retail Goods"
        },
        {
            "category":"Manufacturing",
            "subcategory":"Motor Vehicles & Parts",
            "type":"Manufacturing & Wholesale Goods"
        }
    ],
    "sg:phone":"+1 360 671 5068",
    "sg:postcode":"98229",
    "sg:province":"WA",
    "sg:tags":[
        "dealer",
        "equipment",
        "transportation",
        "sales",
        "mfg"
    ],
    "wof:name":"Quality Trailers Inc",
    "wof:placetype":"venue"
},
  "geometry": {"coordinates":[-122.450654,48.757348],"type":"Point"}
}