{
  "type": "Feature",
  "properties": {
    "addr:full":"1901 Queen Anne Avenue N Seattle WA 98109",
    "addr:housenumber":"1901",
    "addr:postcode":"98109",
    "addr:street":"Queen Anne Avenue N",
    "iso:country":"US",
    "sg:address":"1901 Queen Anne Avenue N",
    "sg:city":"Seattle",
    "sg:classifiers":[
        {
            "category":"Personal",
            "subcategory":"Beauty Salon",
            "type":"Services"
        }
    ],
    "sg:phone":"+1 206 282 5318",
    "sg:postcode":"98109",
    "sg:province":"WA",
    "sg:tags":[
        "hair"
    ],
    "wof:name":"Hair Design by Helen",
    "wof:placetype":"venue"
},
  "geometry": {"coordinates":[-122.357133,47.636059],"type":"Point"}
}