{
  "type": "Feature",
  "properties": {
    "iso:country":"US",
    "sg:address":"7801 Greenwood Ave N",
    "sg:city":"Seattle",
    "sg:classifiers":[
        {
            "category":"Health Services",
            "subcategory":"Doctor",
            "type":"Services"
        }
    ],
    "sg:phone":"+1 206 783 4098",
    "sg:postcode":"98103",
    "sg:province":"WA",
    "wof:name":"Robert G McCarter DDS",
    "wof:placetype":"venue"
},
  "geometry": {"coordinates":[-122.3553,47.686212],"type":"Point"}
}