{
  "type": "Feature",
  "properties": {
    "addr:full":"1928 S Tekoa St Spokane WA 99203",
    "addr:housenumber":"1928",
    "addr:postcode":"99203",
    "addr:street":"S Tekoa St",
    "iso:country":"US",
    "sg:address":"1928 S Tekoa St",
    "sg:city":"Spokane",
    "sg:classifiers":[
        {
            "category":"Restaurant",
            "type":"Food & Drink"
        }
    ],
    "sg:phone":"+1 509 456 8066",
    "sg:postcode":"99203",
    "sg:province":"WA",
    "wof:name":"Park Bench",
    "wof:placetype":"venue"
},
  "geometry": {"coordinates":[-117.41016999999999,47.637322],"type":"Point"}
}