{
  "type": "Feature",
  "properties": {
    "addr:full":"320 W Republican St Seattle WA 98119",
    "addr:housenumber":"320",
    "addr:postcode":"98119",
    "addr:street":"W Republican St",
    "iso:country":"US",
    "sg:address":"320 W Republican St",
    "sg:city":"Seattle",
    "sg:classifiers":[
        {
            "category":"Building & Trades",
            "subcategory":"Construction",
            "type":"Services"
        }
    ],
    "sg:phone":"+1 206 352 8505",
    "sg:postcode":"98119",
    "sg:province":"WA",
    "sg:tags":[
        "designer"
    ],
    "wof:name":"Catanga",
    "wof:placetype":"venue"
},
  "geometry": {"coordinates":[-122.361766,47.623368],"type":"Point"}
}