{
  "type": "Feature",
  "properties": {
    "addr:full":"7 Columbia Cir SW Lakewood WA 98499",
    "addr:housenumber":"7",
    "addr:postcode":"98499",
    "addr:street":"Columbia Cir Sw",
    "iso:country":"US",
    "sg:address":"7 Columbia Cir SW",
    "sg:city":"Lakewood",
    "sg:classifiers":[
        {
            "category":"Manufacturing",
            "subcategory":"Tools & Machinery",
            "type":"Manufacturing & Wholesale Goods"
        }
    ],
    "sg:phone":"+1 253 582 3545",
    "sg:postcode":"98499",
    "sg:province":"WA",
    "sg:tags":[
        "industrial",
        "mfg"
    ],
    "wof:name":"Plane Vanes",
    "wof:placetype":"venue"
},
  "geometry": {"coordinates":[-122.513807,47.167535],"type":"Point"}
}