{
  "type": "Feature",
  "properties": {
    "addr:full":"427 35th Ave S Seattle WA 98144",
    "addr:housenumber":"427",
    "addr:postcode":"98144",
    "addr:street":"35Th Ave S",
    "iso:country":"US",
    "sg:address":"427 35th Ave S",
    "sg:city":"Seattle",
    "sg:classifiers":[
        {
            "category":"Professional",
            "subcategory":"Detective & Security Services",
            "type":"Services"
        }
    ],
    "sg:phone":"+1 206 323 7547",
    "sg:postcode":"98144",
    "sg:province":"WA",
    "sg:tags":[
        "information",
        "bureau"
    ],
    "wof:name":"Premiere Global Service",
    "wof:placetype":"venue"
},
  "geometry": {"coordinates":[-122.287751,47.598785],"type":"Point"}
}