{
  "type": "Feature",
  "properties": {
    "addr:full":"417 Pioneer Ave E Montesano WA 98563",
    "addr:housenumber":"417",
    "addr:postcode":"98563",
    "addr:street":"Pioneer Ave E Montesano",
    "iso:country":"US",
    "sg:address":"417 Pioneer Ave E",
    "sg:city":"Montesano",
    "sg:classifiers":[
        {
            "category":"Organizations",
            "subcategory":"Religious Organization",
            "type":"Services"
        }
    ],
    "sg:phone":"+1 360 249 1954",
    "sg:postcode":"98563",
    "sg:province":"WA",
    "sg:tags":[
        "spiritualist"
    ],
    "wof:name":"Spiritual Encounter Center",
    "wof:placetype":"venue"
},
  "geometry": {"coordinates":[-123.59692800000001,46.979474],"type":"Point"}
}