{
  "type": "Feature",
  "properties": {
    "addr:full":"2650 NE John Carlson Rd Bremerton WA 98311",
    "addr:housenumber":"2650",
    "addr:postcode":"98311",
    "addr:street":"Ne John Carlson Rd",
    "iso:country":"US",
    "sg:address":"2650 NE John Carlson Rd",
    "sg:city":"Bremerton",
    "sg:classifiers":[
        {
            "category":"Education",
            "subcategory":"School",
            "type":"Public Place"
        }
    ],
    "sg:phone":"+1 360 662 8600",
    "sg:postcode":"98311",
    "sg:province":"WA",
    "wof:name":"Esquire Hills Elementary Schl",
    "wof:placetype":"venue"
},
  "geometry": {"coordinates":[-122.61333399999999,47.632162],"type":"Point"}
}