{
  "type": "Feature",
  "properties": {
    "addr:full":"11122 E Lake Joy Dr NE Carnation WA 98014",
    "addr:housenumber":"11122",
    "addr:postcode":"98014",
    "addr:street":"E Lake Joy Dr Ne",
    "iso:country":"US",
    "sg:address":"11122 E Lake Joy Dr NE",
    "sg:city":"Carnation",
    "sg:classifiers":[
        {
            "category":"Shopping",
            "subcategory":"Computers & Home Electronics",
            "type":"Retail Goods"
        }
    ],
    "sg:phone":"+1 425 788 8157",
    "sg:postcode":"98014",
    "sg:province":"WA",
    "wof:name":"Dap Computer Services",
    "wof:placetype":"venue"
},
  "geometry": {"coordinates":[-121.86310400000001,47.696032],"type":"Point"}
}