{
  "type": "Feature",
  "properties": {
    "addr:full":"1400 State Ave Marysville WA 98270",
    "addr:housenumber":"1400",
    "addr:postcode":"98270",
    "addr:street":"State Ave",
    "iso:country":"US",
    "sg:address":"1400 State Ave",
    "sg:city":"Marysville",
    "sg:classifiers":[
        {
            "category":"Restaurant",
            "type":"Food & Drink"
        }
    ],
    "sg:phone":"+1 360 658 9711",
    "sg:postcode":"98270",
    "sg:province":"WA",
    "sg:tags":[
        "eating"
    ],
    "wof:name":"Tacos Guaymas",
    "wof:placetype":"venue"
},
  "geometry": {"coordinates":[-122.176935,48.068435],"type":"Point"}
}