{
  "type": "Feature",
  "properties": {
    "addr:full":"1701 Tacoma Ave S Tacoma WA 98402",
    "addr:housenumber":"1701",
    "addr:postcode":"98402",
    "addr:street":"Tacoma Ave S",
    "iso:country":"US",
    "sg:address":"1701 Tacoma Ave S",
    "sg:city":"Tacoma",
    "sg:classifiers":[
        {
            "category":"Professional",
            "subcategory":"Business Services",
            "type":"Services"
        }
    ],
    "sg:phone":"+1 253 383 5564",
    "sg:postcode":"98402",
    "sg:province":"WA",
    "wof:name":"Uptone Recording Studio",
    "wof:placetype":"venue"
},
  "geometry": {"coordinates":[-122.44279899999999,47.24556],"type":"Point"}
}