{
  "type": "Feature",
  "properties": {
    "addr:full":"11213 Sheridan Ave S Tacoma WA 98444",
    "addr:housenumber":"11213",
    "addr:postcode":"98444",
    "addr:street":"Sheridan Ave S",
    "iso:country":"US",
    "sg:address":"11213 Sheridan Ave S",
    "sg:city":"Tacoma",
    "sg:classifiers":[
        {
            "category":"Education",
            "subcategory":"School",
            "type":"Public Place"
        }
    ],
    "sg:phone":"+1 253 298 4200",
    "sg:postcode":"98444",
    "sg:province":"WA",
    "sg:website":"http://www.fp.k12.wa.us",
    "wof:name":"James Sales Elementary School",
    "wof:placetype":"venue"
},
  "geometry": {"coordinates":[-122.452696,47.155392],"type":"Point"}
}