{
  "type": "Feature",
  "properties": {
    "addr:full":"8002 NE Highway 99 # 152 Vancouver WA 98665",
    "addr:housenumber":"8002",
    "addr:postcode":"98665",
    "addr:street":"Ne Highway 99 # 152",
    "iso:country":"US",
    "sg:address":"8002 NE Highway 99 # 152",
    "sg:city":"Vancouver",
    "sg:classifiers":[
        {
            "category":"Manufacturing",
            "subcategory":"Metals",
            "type":"Manufacturing & Wholesale Goods"
        },
        {
            "category":"Shopping",
            "subcategory":"Jewelry",
            "type":"Retail Goods"
        }
    ],
    "sg:phone":"+1 360 573 0291",
    "sg:postcode":"98665",
    "sg:province":"WA",
    "sg:tags":[
        "semi-precious",
        "precious",
        "metals-precious",
        "stone"
    ],
    "wof:name":"West Coast Diamond Co",
    "wof:placetype":"venue"
},
  "geometry": {"coordinates":[-122.661879,45.679669],"type":"Point"}
}