{
  "type": "Feature",
  "properties": {
    "addr:full":"5102 61st St NW Gig Harbor WA 98335",
    "addr:housenumber":"5102",
    "addr:postcode":"98335",
    "addr:street":"61St St Nw",
    "iso:country":"US",
    "sg:address":"5102 61st St NW",
    "sg:city":"Gig Harbor",
    "sg:classifiers":[
        {
            "category":"Shopping",
            "subcategory":"Bicycles & Sporting Goods",
            "type":"Retail Goods"
        }
    ],
    "sg:phone":"+1 253 858 6998",
    "sg:postcode":"98335",
    "sg:province":"WA",
    "wof:name":"Hurt Guns",
    "wof:placetype":"venue"
},
  "geometry": {"coordinates":[-122.60737399999999,47.312624],"type":"Point"}
}