{
  "type": "Feature",
  "properties": {
    "addr:full":"522 Driskill Rd Newport WA 99156",
    "addr:housenumber":"522",
    "addr:postcode":"99156",
    "addr:street":"Driskill Rd",
    "iso:country":"US",
    "sg:address":"522 Driskill Rd",
    "sg:city":"Newport",
    "sg:classifiers":[
        {
            "category":"Building & Trades",
            "subcategory":"Landscaping Services",
            "type":"Services"
        }
    ],
    "sg:phone":"+1 509 447 9299",
    "sg:postcode":"99156",
    "sg:province":"WA",
    "sg:tags":[
        "tree"
    ],
    "wof:name":"Little Logger Tree Service",
    "wof:placetype":"venue"
},
  "geometry": {"coordinates":[-117.174689,48.112711],"type":"Point"}
}