{
  "type": "Feature",
  "properties": {
    "addr:full":"499 Madison Avenue N Bainbridge Island WA 98110",
    "addr:housenumber":"499",
    "addr:postcode":"98110",
    "addr:street":"Madison Avenue N",
    "iso:country":"US",
    "sg:address":"499 Madison Avenue N",
    "sg:city":"Bainbridge Island",
    "sg:classifiers":[
        {
            "category":"Autos & Motor Vehicles",
            "subcategory":"Auto Supplies",
            "type":"Retail Goods"
        }
    ],
    "sg:phone":"+1 206 842 4026",
    "sg:postcode":"98110",
    "sg:province":"WA",
    "sg:tags":[
        "tire"
    ],
    "wof:name":"Madison Avenue Garage",
    "wof:placetype":"venue"
},
  "geometry": {"coordinates":[-122.521165,47.628332],"type":"Point"}
}