{
  "type": "Feature",
  "properties": {
    "addr:full":"10900 Wachusett Rd Woodway WA 98020",
    "addr:postcode":"10900;98020",
    "addr:street":"Wachusett Rd",
    "iso:country":"US",
    "sg:address":"10900 Wachusett Rd",
    "sg:city":"Woodway",
    "sg:classifiers":[
        {
            "category":"Building & Trades",
            "subcategory":"Construction",
            "type":"Services"
        }
    ],
    "sg:phone":"+1 206 542 3382",
    "sg:postcode":"98020",
    "sg:province":"WA",
    "sg:tags":[
        "general",
        "contractor"
    ],
    "wof:name":"Blox LLC",
    "wof:placetype":"venue"
},
  "geometry": {"coordinates":[-122.382864,47.787062],"type":"Point"}
}