{
  "type": "Feature",
  "properties": {
    "addr:full":"1681 S 48th St Tacoma WA 98408",
    "addr:housenumber":"1681",
    "addr:postcode":"98408",
    "addr:street":"S 48Th St",
    "iso:country":"US",
    "sg:address":"1681 S 48th St",
    "sg:city":"Tacoma",
    "sg:classifiers":[
        {
            "category":"Building & Trades",
            "subcategory":"Electrical",
            "type":"Services"
        }
    ],
    "sg:phone":"+1 253 472 1371",
    "sg:postcode":"98408",
    "sg:province":"WA",
    "sg:tags":[
        "electrical",
        "contractor"
    ],
    "wof:name":"Netune LLC",
    "wof:placetype":"venue"
},
  "geometry": {"coordinates":[-122.45722000000001,47.213872],"type":"Point"}
}