{
  "type": "Feature",
  "properties": {
    "addr:full":"305 SE Chkalov Dr Vancouver WA 98683",
    "addr:housenumber":"305",
    "addr:postcode":"98683",
    "addr:street":"Se Chkalov Dr",
    "iso:country":"US",
    "sg:address":"305 SE Chkalov Dr",
    "sg:city":"Vancouver",
    "sg:classifiers":[
        {
            "category":"Retail",
            "subcategory":"Auto Repair",
            "type":"Services"
        }
    ],
    "sg:phone":"+1 360 524 7340",
    "sg:postcode":"98683",
    "sg:province":"WA",
    "sg:tags":[
        "windshield"
    ],
    "wof:name":"Friscoe Auto Glass",
    "wof:placetype":"venue"
},
  "geometry": {"coordinates":[-122.554892,45.617589],"type":"Point"}
}