{
  "type": "Feature",
  "properties": {
    "addr:full":"13630 127th Ave SE Snohomish WA 98290",
    "addr:housenumber":"13630",
    "addr:postcode":"98290",
    "addr:street":"127Th Ave Se",
    "iso:country":"US",
    "sg:address":"13630 127th Ave SE",
    "sg:city":"Snohomish",
    "sg:classifiers":[
        {
            "category":"Building & Trades",
            "subcategory":"Landscaping Services",
            "type":"Services"
        }
    ],
    "sg:phone":"+1 360 568 2758",
    "sg:postcode":"98290",
    "sg:province":"WA",
    "sg:tags":[
        "landscape",
        "contractor"
    ],
    "wof:name":"Plants Plus",
    "wof:placetype":"venue"
},
  "geometry": {"coordinates":[-122.06050399999999,47.872718],"type":"Point"}
}