{
  "type": "Feature",
  "properties": {
    "addr:full":"618 John St Seattle WA 98109",
    "addr:housenumber":"618",
    "addr:postcode":"98109",
    "addr:street":"John St",
    "iso:country":"US",
    "sg:address":"618 John St",
    "sg:city":"Seattle",
    "sg:classifiers":[
        {
            "category":"Professional",
            "subcategory":"Business Services",
            "type":"Services"
        }
    ],
    "sg:phone":"+1 206 728 6065",
    "sg:postcode":"98109",
    "sg:province":"WA",
    "sg:tags":[
        "consultant",
        "coach"
    ],
    "wof:name":"Business Plans & Strategies",
    "wof:placetype":"venue"
},
  "geometry": {"coordinates":[-122.344812,47.619728],"type":"Point"}
}