{
  "type": "Feature",
  "properties": {
    "addr:full":"824 State Ave NE Olympia WA 98506",
    "addr:housenumber":"824",
    "addr:postcode":"98506",
    "addr:street":"State Ave Ne",
    "iso:country":"US",
    "sg:address":"824 State Ave NE",
    "sg:city":"Olympia",
    "sg:classifiers":[
        {
            "category":"Banks & Credit Unions",
            "subcategory":"Financial Services",
            "type":"Services"
        }
    ],
    "sg:phone":"+1 360 528 2944",
    "sg:postcode":"98506",
    "sg:province":"WA",
    "sg:tags":[
        "investor"
    ],
    "wof:name":"Sound Investment Management",
    "wof:placetype":"venue"
},
  "geometry": {"coordinates":[-122.89176500000001,47.046498],"type":"Point"}
}