{
  "type": "Feature",
  "properties": {
    "addr:full":"1118 5th Ave S Okanogan WA 98840",
    "addr:housenumber":"1118",
    "addr:postcode":"98840",
    "addr:street":"5Th Ave S Okanogan",
    "iso:country":"US",
    "sg:address":"1118 5th Ave S",
    "sg:city":"Okanogan",
    "sg:classifiers":[
        {
            "category":"Education",
            "subcategory":"School",
            "type":"Public Place"
        }
    ],
    "sg:phone":"+1 509 422 3580",
    "sg:postcode":"98840",
    "sg:province":"WA",
    "sg:website":"www.oksd.wednet.edu",
    "wof:name":"Grainger Elementary School",
    "wof:placetype":"venue"
},
  "geometry": {"coordinates":[-119.591497,48.358861],"type":"Point"}
}