{
  "type": "Feature",
  "properties": {
    "addr:full":"31810 State Route 20 Oak Harbor WA 98277",
    "addr:housenumber":"31810",
    "addr:postcode":"98277",
    "addr:street":"State Route 20",
    "iso:country":"US",
    "sg:address":"31810 State Route 20",
    "sg:city":"Oak Harbor",
    "sg:classifiers":[
        {
            "category":"Restaurant",
            "type":"Food & Drink"
        }
    ],
    "sg:menulink":"http://www.allmenus.com/wa/north-whidbey/89841-applebees/menu/",
    "sg:phone":"+1 360 679 6100",
    "sg:postcode":"98277",
    "sg:province":"WA",
    "sg:tags":[
        "burger",
        "american",
        "sandwich",
        "soup"
    ],
    "wof:name":"Applebee's",
    "wof:placetype":"venue"
},
  "geometry": {"coordinates":[-122.65732800000001,48.293199],"type":"Point"}
}