{
  "type": "Feature",
  "properties": {
    "addr:full":"7701 S Hosmer St Tacoma WA 98408",
    "addr:housenumber":"7701",
    "addr:postcode":"98408",
    "addr:street":"S Hosmer St",
    "iso:country":"US",
    "sg:address":"7701 S Hosmer St",
    "sg:city":"Tacoma",
    "sg:classifiers":[
        {
            "category":"Food & Beverages",
            "subcategory":"Specialty",
            "type":"Retail Goods"
        }
    ],
    "sg:phone":"+1 253 476 1400",
    "sg:postcode":"98408",
    "sg:province":"WA",
    "sg:tags":[
        "water",
        "bulk",
        "company"
    ],
    "wof:name":"Purified Water To Go",
    "wof:placetype":"venue"
},
  "geometry": {"coordinates":[-122.463111,47.185128],"type":"Point"}
}