{
  "type": "Feature",
  "properties": {
    "addr:full":"1616 W 31st St Vancouver WA 98660",
    "addr:housenumber":"1616",
    "addr:postcode":"98660",
    "addr:street":"W 31St St",
    "iso:country":"US",
    "sg:address":"1616 W 31st St",
    "sg:city":"Vancouver",
    "sg:classifiers":[
        {
            "category":"Manufacturing",
            "subcategory":"Paper Products",
            "type":"Manufacturing & Wholesale Goods"
        }
    ],
    "sg:phone":"+1 360 693 3664",
    "sg:postcode":"98660",
    "sg:province":"WA",
    "sg:tags":[
        "food",
        "sanitary",
        "fiber",
        "container",
        "mfg"
    ],
    "wof:name":"Pacific Lamination",
    "wof:placetype":"venue"
},
  "geometry": {"coordinates":[-122.690422,45.643991],"type":"Point"}
}