{
  "type": "Feature",
  "properties": {
    "addr:full":"6918 E Fourth Plain Blvd Vancouver WA 98661",
    "addr:housenumber":"6918",
    "addr:postcode":"98661",
    "addr:street":"E Fourth Plain Blvd",
    "iso:country":"US",
    "sg:address":"6918 E Fourth Plain Blvd",
    "sg:city":"Vancouver",
    "sg:classifiers":[
        {
            "category":"Professional",
            "subcategory":"Business Services",
            "type":"Services"
        }
    ],
    "sg:phone":"+1 360 693 3700",
    "sg:postcode":"98661",
    "sg:province":"WA",
    "sg:tags":[
        "trade",
        "fair",
        "show"
    ],
    "sg:website":"www.sportexpos.com",
    "wof:name":"International Sportsmen Expstn",
    "wof:placetype":"venue"
},
  "geometry": {"coordinates":[-122.60288799999999,45.644456],"type":"Point"}
}