{
  "type": "Feature",
  "properties": {
    "addr:full":"299 Jones Rd Pe Ell WA 98572",
    "addr:housenumber":"299",
    "addr:postcode":"98572",
    "addr:street":"Jones Rd",
    "iso:country":"US",
    "sg:address":"299 Jones Rd",
    "sg:city":"Pe Ell",
    "sg:classifiers":[
        {
            "category":"Social Services",
            "subcategory":"Adult Care",
            "type":"Services"
        }
    ],
    "sg:phone":"+1 360 291 8816",
    "sg:postcode":"98572",
    "sg:province":"WA",
    "sg:tags":[
        "residential"
    ],
    "wof:name":"Music Fndtion For Vcal Rlztion",
    "wof:placetype":"venue"
},
  "geometry": {"coordinates":[-123.305387,46.58107],"type":"Point"}
}