{
  "type": "Feature",
  "properties": {
    "addr:full":"1403 145th Pl SE Bothell WA 98012",
    "addr:housenumber":"1403",
    "addr:postcode":"98012",
    "addr:street":"145Th Pl Se",
    "iso:country":"US",
    "sg:address":"1403 145th Pl SE",
    "sg:city":"Bothell",
    "sg:classifiers":[
        {
            "category":"Personal",
            "subcategory":"Hair Removal",
            "type":"Services"
        }
    ],
    "sg:phone":"+1 425 337 9999",
    "sg:postcode":"98012",
    "sg:province":"WA",
    "wof:name":"ABC Funding Solutions",
    "wof:placetype":"venue"
},
  "geometry": {"coordinates":[-122.21262900000001,47.866146],"type":"Point"}
}