{
  "type": "Feature",
  "properties": {
    "addr:full":"234 Market St Kirkland WA 98033",
    "addr:housenumber":"234",
    "addr:postcode":"98033",
    "addr:street":"Market St",
    "iso:country":"US",
    "sg:address":"234 Market St",
    "sg:city":"Kirkland",
    "sg:classifiers":[
        {
            "category":"Health Services",
            "subcategory":"Dentist",
            "type":"Services"
        }
    ],
    "sg:phone":"+1 425 827 3097",
    "sg:postcode":"98033",
    "sg:province":"WA",
    "wof:name":"Runion H E III DMD",
    "wof:placetype":"venue"
},
  "geometry": {"coordinates":[-122.209,47.677399],"type":"Point"}
}