{
  "type": "Feature",
  "properties": {
    "iso:country":"US",
    "sg:address":"6695 Regency Dr SE",
    "sg:city":"Port Orchard",
    "sg:classifiers":[
        {
            "category":"Professional",
            "subcategory":"Business Services",
            "type":"Services"
        }
    ],
    "sg:phone":"+1 360 895 5681",
    "sg:postcode":"98367",
    "sg:province":"WA",
    "wof:name":"All About Embroidery",
    "wof:placetype":"venue"
},
  "geometry": {"coordinates":[-122.625077,47.487673],"type":"Point"}
}