{
  "type": "Feature",
  "properties": {
    "addr:full":"611 S 132nd Street Burien WA 98168",
    "addr:housenumber":"611",
    "addr:postcode":"98168",
    "addr:street":"S 132Nd Street",
    "iso:country":"US",
    "sg:address":"611 S 132nd Street",
    "sg:city":"Burien",
    "sg:classifiers":[
        {
            "category":"Education",
            "subcategory":"School",
            "type":"Public Place"
        }
    ],
    "sg:phone":"+1 206 433 2474",
    "sg:postcode":"98168",
    "sg:province":"WA",
    "sg:tags":[
        "high",
        "middle",
        "elementary"
    ],
    "wof:name":"Highline Public Schools",
    "wof:placetype":"venue"
},
  "geometry": {"coordinates":[-122.325553,47.485012],"type":"Point"}
}