{
  "type": "Feature",
  "properties": {
    "addr:full":"852 S Clark Ave Republic WA 99166",
    "addr:housenumber":"852",
    "addr:postcode":"99166",
    "addr:street":"S Clark Ave",
    "iso:country":"US",
    "sg:address":"852 S Clark Ave",
    "sg:city":"Republic",
    "sg:classifiers":[
        {
            "category":"Professional",
            "type":"Services"
        }
    ],
    "sg:phone":"+1 509 775 8010",
    "sg:postcode":"99166",
    "sg:province":"WA",
    "wof:name":"Gold Mntins Gallery-Eureka Art",
    "wof:placetype":"venue"
},
  "geometry": {"coordinates":[-118.73764300000001,48.645628],"type":"Point"}
}