{
  "type": "Feature",
  "properties": {
    "addr:full":"1598 Woods Rd SE Port Orchard WA 98366",
    "addr:housenumber":"1598",
    "addr:postcode":"98366",
    "addr:street":"Woods Rd Se",
    "iso:country":"US",
    "sg:address":"1598 Woods Rd SE",
    "sg:city":"Port Orchard",
    "sg:classifiers":[
        {
            "category":"Food & Beverages",
            "subcategory":"Groceries & Convenience Stores",
            "type":"Retail Goods"
        }
    ],
    "sg:phone":"+1 360 871 6438",
    "sg:postcode":"98366",
    "sg:province":"WA",
    "sg:tags":[
        "grocer"
    ],
    "wof:name":"P J's Market",
    "wof:placetype":"venue"
},
  "geometry": {"coordinates":[-122.567638,47.533988],"type":"Point"}
}