{
  "type": "Feature",
  "properties": {
    "addr:full":"8510 154th Ave NE Redmond WA 98052",
    "addr:housenumber":"8510",
    "addr:postcode":"98052",
    "addr:street":"154Th Ave Ne",
    "iso:country":"US",
    "sg:address":"8510 154th Ave NE",
    "sg:city":"Redmond",
    "sg:classifiers":[
        {
            "category":"Manufacturing",
            "subcategory":"Aerospace",
            "type":"Manufacturing & Wholesale Goods"
        }
    ],
    "sg:phone":"+1 425 883 2525",
    "sg:postcode":"98052",
    "sg:province":"WA",
    "sg:tags":[
        "avionics",
        "supply",
        "equipment",
        "aircraft",
        "part",
        "instrument",
        "supplies-wholesale",
        "manufacturer"
    ],
    "sg:website":"http://www.drs-ss.com",
    "wof:name":"Bae Systems Inc",
    "wof:placetype":"venue"
},
  "geometry": {"coordinates":[-122.13466,47.678661],"type":"Point"}
}