{
  "type": "Feature",
  "properties": {
    "addr:full":"8115 SE Sherley Ave Vancouver WA 98664",
    "addr:housenumber":"8115",
    "addr:postcode":"98664",
    "addr:street":"Se Sherley Ave",
    "iso:country":"US",
    "sg:address":"8115 SE Sherley Ave",
    "sg:city":"Vancouver",
    "sg:classifiers":[
        {
            "category":"Real Estate",
            "subcategory":"Real Estate Agent",
            "type":"Services"
        }
    ],
    "sg:phone":"+1 360 256 0025",
    "sg:postcode":"98664",
    "sg:province":"WA",
    "wof:name":"Aztec Appraisal Corporation",
    "wof:placetype":"venue"
},
  "geometry": {"coordinates":[-122.58569199999999,45.614888],"type":"Point"}
}