{
  "type": "Feature",
  "properties": {
    "addr:full":"15916 Kamb Rd Mount Vernon WA 98273",
    "addr:postcode":"15916;98273",
    "addr:street":"Kamb Rd",
    "iso:country":"US",
    "sg:address":"15916 Kamb Rd",
    "sg:city":"Mount Vernon",
    "sg:classifiers":[
        {
            "category":"Building & Trades",
            "subcategory":"Construction",
            "type":"Services"
        }
    ],
    "sg:phone":"+1 360 424 6017",
    "sg:postcode":"98273",
    "sg:province":"WA",
    "sg:tags":[
        "house"
    ],
    "wof:name":"Schneider Const",
    "wof:placetype":"venue"
},
  "geometry": {"coordinates":[-122.384423,48.414893],"type":"Point"}
}