{
  "type": "Feature",
  "properties": {
    "addr:full":"1908 E Empire Ave Spokane WA 99207",
    "addr:housenumber":"1908",
    "addr:postcode":"99207",
    "addr:street":"E Empire Ave",
    "iso:country":"US",
    "sg:address":"1908 E Empire Ave",
    "sg:city":"Spokane",
    "sg:classifiers":[
        {
            "category":"Professional",
            "subcategory":"Accounting & Tax Preparation",
            "type":"Services"
        }
    ],
    "sg:phone":"+1 509 489 7528",
    "sg:postcode":"99207",
    "sg:province":"WA",
    "wof:name":"R Shelton Inc",
    "wof:placetype":"venue"
},
  "geometry": {"coordinates":[-117.379035,47.692984],"type":"Point"}
}