{
  "type": "Feature",
  "properties": {
    "addr:full":"PO Box 6396 Vancouver WA 98668",
    "addr:housenumber":"po;6396",
    "addr:postcode":"98668",
    "addr:street":"Box",
    "iso:country":"US",
    "sg:address":"PO Box 6396",
    "sg:city":"Vancouver",
    "sg:classifiers":[
        {
            "category":"Building & Trades",
            "subcategory":"Construction",
            "type":"Services"
        }
    ],
    "sg:phone":"+1 360 696 3868",
    "sg:postcode":"98668",
    "sg:province":"WA",
    "sg:tags":[
        "contractor"
    ],
    "wof:name":"Lotus Construction Co",
    "wof:placetype":"venue"
},
  "geometry": {"coordinates":[-122.623001,45.640701],"type":"Point"}
}