{
  "type": "Feature",
  "properties": {
    "addr:full":"7529 36th Ave NE Seattle WA 98115",
    "addr:housenumber":"7529",
    "addr:postcode":"98115",
    "addr:street":"36Th Ave Ne",
    "iso:country":"US",
    "sg:address":"7529 36th Ave NE",
    "sg:city":"Seattle",
    "sg:classifiers":[
        {
            "category":"Professional",
            "type":"Services"
        }
    ],
    "sg:phone":"+1 206 522 4569",
    "sg:postcode":"98115",
    "sg:province":"WA",
    "wof:name":"Tyd",
    "wof:placetype":"venue"
},
  "geometry": {"coordinates":[-122.289553,47.684597],"type":"Point"}
}