{
  "type": "Feature",
  "properties": {
    "addr:full":"117 N 1st St Mount Vernon WA 98273",
    "addr:housenumber":"117",
    "addr:postcode":"98273",
    "addr:street":"N 1St St",
    "iso:country":"US",
    "sg:address":"117 N 1st St",
    "sg:city":"Mount Vernon",
    "sg:classifiers":[
        {
            "category":"Professional",
            "subcategory":"Management & Consulting",
            "type":"Services"
        }
    ],
    "sg:phone":"+1 360 416 7013",
    "sg:postcode":"98273",
    "sg:province":"WA",
    "wof:name":"North Sund Rgnal Spport Netwrk",
    "wof:placetype":"venue"
},
  "geometry": {"coordinates":[-122.337188,48.423224],"type":"Point"}
}