{
  "type": "Feature",
  "properties": {
    "addr:full":"8103 Steilacoom Blvd SW Lakewood WA 98498",
    "addr:housenumber":"8103",
    "addr:postcode":"98498",
    "addr:street":"Steilacoom Blvd Sw",
    "iso:country":"US",
    "sg:address":"8103 Steilacoom Blvd SW",
    "sg:city":"Lakewood",
    "sg:classifiers":[
        {
            "category":"Building & Trades",
            "subcategory":"Landscaping Services",
            "type":"Services"
        },
        {
            "category":"Home & Garden",
            "subcategory":"Garden Supply",
            "type":"Retail Goods"
        },
        {
            "category":"Wholesale",
            "subcategory":"Machinery & Supplies",
            "type":"Manufacturing & Wholesale Goods"
        }
    ],
    "sg:phone":"+1 253 581 6491",
    "sg:postcode":"98498",
    "sg:province":"WA",
    "sg:tags":[
        "lawn",
        "installation",
        "sprinkler",
        "sprinklers-garden",
        "irrigation",
        "system",
        "equipment",
        "maintenance",
        "supervisory"
    ],
    "wof:name":"Robs Sprinkler Service & Installation",
    "wof:placetype":"venue"
},
  "geometry": {"coordinates":[-122.54406,47.179943],"type":"Point"}
}