{
  "type": "Feature",
  "properties": {
    "addr:full":"8301 161st Ave NE # NE Redmond WA 98052",
    "addr:housenumber":"8301",
    "addr:postcode":"98052",
    "addr:street":"161St Ave Ne # Ne",
    "iso:country":"US",
    "sg:address":"8301 161st Ave NE # NE",
    "sg:city":"Redmond",
    "sg:classifiers":[
        {
            "category":"Health Services",
            "subcategory":"Doctor",
            "type":"Services"
        },
        {
            "category":"Health Services",
            "subcategory":"Clinic",
            "type":"Services"
        }
    ],
    "sg:phone":"+1 425 885 3330",
    "sg:postcode":"98052",
    "sg:province":"WA",
    "sg:tags":[
        "counseling",
        "mental"
    ],
    "wof:name":"Jimenez Marcia Houdek PHD",
    "wof:placetype":"venue"
},
  "geometry": {"coordinates":[-122.12608299999999,47.677005],"type":"Point"}
}