{
  "type": "Feature",
  "properties": {
    "addr:full":"3440 NW 57th St Seattle WA 98107",
    "addr:housenumber":"3440",
    "addr:postcode":"98107",
    "addr:street":"Nw 57Th St",
    "iso:country":"US",
    "sg:address":"3440 NW 57th St",
    "sg:city":"Seattle",
    "sg:classifiers":[
        {
            "category":"Insurance",
            "subcategory":"Insurance Agent",
            "type":"Services"
        }
    ],
    "sg:phone":"+1 206 784 2381",
    "sg:postcode":"98107",
    "sg:province":"WA",
    "wof:name":"J W Claseman",
    "wof:placetype":"venue"
},
  "geometry": {"coordinates":[-122.403502,47.670441],"type":"Point"}
}