{
  "type": "Feature",
  "properties": {
    "addr:full":"17445 147th St SE Monroe WA 98272",
    "addr:housenumber":"17445",
    "addr:postcode":"98272",
    "addr:street":"147Th St Se",
    "iso:country":"US",
    "sg:address":"17445 147th St SE",
    "sg:city":"Monroe",
    "sg:classifiers":[
        {
            "category":"Freight",
            "type":"Transportation"
        }
    ],
    "sg:phone":"+1 360 794 5799",
    "sg:postcode":"98272",
    "sg:province":"WA",
    "sg:tags":[
        "commercial",
        "storage",
        "special",
        "general"
    ],
    "wof:name":"Aa All Heated Mini Storage",
    "wof:placetype":"venue"
},
  "geometry": {"coordinates":[-121.997485,47.86473],"type":"Point"}
}