{
  "type": "Feature",
  "properties": {
    "addr:full":"205 Chehalis Valley Dr Chehalis WA 98532",
    "addr:housenumber":"205",
    "addr:postcode":"98532",
    "addr:street":"Chehalis Valley Dr",
    "iso:country":"US",
    "sg:address":"205 Chehalis Valley Dr",
    "sg:city":"Chehalis",
    "sg:classifiers":[
        {
            "category":"Manufacturing",
            "subcategory":"Lumber",
            "type":"Manufacturing & Wholesale Goods"
        }
    ],
    "sg:phone":"+1 360 740 1033",
    "sg:postcode":"98532",
    "sg:province":"WA",
    "sg:tags":[
        "logging"
    ],
    "wof:name":"Teagle Timber Falling Inc",
    "wof:placetype":"venue"
},
  "geometry": {"coordinates":[-122.910706,46.639214],"type":"Point"}
}