{
  "type": "Feature",
  "properties": {
    "addr:full":"2601 Willamette Dr NE Lacey WA 98516",
    "addr:housenumber":"2601",
    "addr:postcode":"98516",
    "addr:street":"Willamette Dr Ne",
    "iso:country":"US",
    "sg:address":"2601 Willamette Dr NE",
    "sg:city":"Lacey",
    "sg:classifiers":[
        {
            "category":"Home & Garden",
            "subcategory":"Building Materials",
            "type":"Retail Goods"
        },
        {
            "category":"Wholesale",
            "subcategory":"Home Furnishings",
            "type":"Manufacturing & Wholesale Goods"
        }
    ],
    "sg:phone":"+1 360 456 6330",
    "sg:postcode":"98516",
    "sg:province":"WA",
    "sg:tags":[
        "hardwood",
        "flooring"
    ],
    "wof:name":"Kelly Goodwin Co",
    "wof:placetype":"venue"
},
  "geometry": {"coordinates":[-122.759028,47.070006],"type":"Point"}
}