{
  "type": "Feature",
  "properties": {
    "addr:full":"1500 Fairview Ave E Ste 300 Seattle WA 98102",
    "addr:housenumber":"1500",
    "addr:postcode":"98102",
    "addr:street":"Fairview Ave E Ste 300",
    "iso:country":"US",
    "sg:address":"1500 Fairview Ave E Ste 300",
    "sg:city":"Seattle",
    "sg:classifiers":[
        {
            "category":"Health Services",
            "subcategory":"Dentist",
            "type":"Services"
        }
    ],
    "sg:phone":"+1 206 922 4200",
    "sg:postcode":"98102",
    "sg:province":"WA",
    "sg:tags":[
        "dentists-cosmetic",
        "denture",
        "dental",
        "clinic",
        "dentistry",
        "implant",
        "dentists-prosthodontists",
        "dentists-implantology"
    ],
    "sg:website":"http://www.dexknows.com/rd?dku=http://eastlakedentalcare.com%3Fmkt=65901",
    "wof:name":"Eastlake Dental Care",
    "wof:placetype":"venue"
},
  "geometry": {"coordinates":[-122.326874,47.631889],"type":"Point"}
}