{
  "type": "Feature",
  "properties": {
    "addr:full":"300 Admiral Way Edmonds WA 98020",
    "addr:housenumber":"300",
    "addr:postcode":"98020",
    "addr:street":"Admiral Way",
    "iso:country":"US",
    "sg:address":"300 Admiral Way",
    "sg:city":"Edmonds",
    "sg:classifiers":[
        {
            "category":"Banks & Credit Unions",
            "subcategory":"Investment Brokerage",
            "type":"Services"
        }
    ],
    "sg:phone":"+1 425 771 2600",
    "sg:postcode":"98020",
    "sg:province":"WA",
    "sg:tags":[
        "consultant",
        "planning",
        "financial"
    ],
    "wof:name":"Karen Briggs",
    "wof:placetype":"venue"
},
  "geometry": {"coordinates":[-122.39140999999999,47.806654],"type":"Point"}
}