{
  "type": "Feature",
  "properties": {
    "addr:full":"6012 S Helena St Spokane WA 99223",
    "addr:housenumber":"6012",
    "addr:postcode":"99223",
    "addr:street":"S Helena St",
    "iso:country":"US",
    "sg:address":"6012 S Helena St",
    "sg:city":"Spokane",
    "sg:classifiers":[
        {
            "category":"Real Estate",
            "subcategory":"Real Estate Operator",
            "type":"Services"
        }
    ],
    "sg:phone":"+1 509 448 0394",
    "sg:postcode":"99223",
    "sg:province":"WA",
    "sg:tags":[
        "property",
        "lessor"
    ],
    "wof:name":"Leland Family LLC",
    "wof:placetype":"venue"
},
  "geometry": {"coordinates":[-117.387314,47.597665],"type":"Point"}
}