{
  "type": "Feature",
  "properties": {
    "addr:full":"15400 SE 30th Pl Suite #105 Bellevue WA 98004",
    "addr:postcode":"15400;98004",
    "addr:street":"Se 30Th Pl Suite # 105",
    "iso:country":"US",
    "sg:address":"15400 SE 30th Pl Suite #105",
    "sg:city":"Bellevue",
    "sg:classifiers":[
        {
            "category":"Professional",
            "subcategory":"Computer Services",
            "type":"Services"
        }
    ],
    "sg:phone":"+1 425 484 1054",
    "sg:postcode":"98004",
    "sg:province":"WA",
    "sg:tags":[
        "event-planning",
        "party-planning",
        "online-invitations",
        "invitations"
    ],
    "sg:website":"http://purpletrail.com",
    "wof:name":"PurpleTrail",
    "wof:placetype":"venue"
},
  "geometry": {"coordinates":[-122.189307,47.583518],"type":"Point"}
}