{
  "type": "Feature",
  "properties": {
    "addr:full":"10014 149th Ave NE Granite Falls WA 98252",
    "addr:housenumber":"10014",
    "addr:postcode":"98252",
    "addr:street":"149Th Ave Ne",
    "iso:country":"US",
    "sg:address":"10014 149th Ave NE",
    "sg:city":"Granite Falls",
    "sg:classifiers":[
        {
            "category":"Professional",
            "subcategory":"Management & Consulting",
            "type":"Services"
        }
    ],
    "sg:phone":"+1 360 691 2172",
    "sg:postcode":"98252",
    "sg:province":"WA",
    "sg:tags":[
        "business"
    ],
    "wof:name":"Spbc",
    "wof:placetype":"venue"
},
  "geometry": {"coordinates":[-122.029336,48.088458],"type":"Point"}
}