{
  "type": "Feature",
  "properties": {
    "addr:full":"1065 12th Ave NW Issaquah WA 98027",
    "addr:housenumber":"1065",
    "addr:postcode":"98027",
    "addr:street":"12Th Ave Nw",
    "iso:country":"US",
    "sg:address":"1065 12th Ave NW",
    "sg:city":"Issaquah",
    "sg:classifiers":[
        {
            "category":"Home & Garden",
            "subcategory":"Household Appliances",
            "type":"Retail Goods"
        }
    ],
    "sg:phone":"+1 425 427 8363",
    "sg:postcode":"98027",
    "sg:province":"WA",
    "wof:name":"Appliance Gourmet",
    "wof:placetype":"venue"
},
  "geometry": {"coordinates":[-122.057599,47.542414],"type":"Point"}
}