{
  "type": "Feature",
  "properties": {
    "addr:full":"4267 148th Ave NE Bellevue WA 98007",
    "addr:housenumber":"4267",
    "addr:postcode":"98007",
    "addr:street":"148Th Ave Ne",
    "iso:country":"US",
    "sg:address":"4267 148th Ave NE",
    "sg:city":"Bellevue",
    "sg:classifiers":[
        {
            "category":"Building & Trades",
            "subcategory":"Construction",
            "type":"Services"
        }
    ],
    "sg:phone":"+1 425 998 8579",
    "sg:postcode":"98007",
    "sg:province":"WA",
    "sg:tags":[
        "interior",
        "design"
    ],
    "sg:website":"janicerward.com",
    "wof:name":"Janice R. Ward Interior Design",
    "wof:placetype":"venue"
},
  "geometry": {"coordinates":[-122.14309900000001,47.6467],"type":"Point"}
}