{
  "type": "Feature",
  "properties": {
    "addr:full":"8200 164th Ave NE Redmond WA 98052",
    "addr:housenumber":"8200",
    "addr:postcode":"98052",
    "addr:street":"164Th Ave Ne",
    "iso:country":"US",
    "sg:address":"8200 164th Ave NE",
    "sg:city":"Redmond",
    "sg:classifiers":[
        {
            "category":"Home & Garden",
            "subcategory":"Furniture",
            "type":"Retail Goods"
        }
    ],
    "sg:phone":"+1 425 885 4222",
    "sg:postcode":"98052",
    "sg:province":"WA",
    "sg:tags":[
        "used",
        "merchandise"
    ],
    "wof:name":"Valley Furniture & Interiors",
    "wof:placetype":"venue"
},
  "geometry": {"coordinates":[-122.121539,47.676086],"type":"Point"}
}