{
  "type": "Feature",
  "properties": {
    "addr:full":"204 E Nora Ave Spokane WA 99207",
    "addr:housenumber":"204",
    "addr:postcode":"99207",
    "addr:street":"E Nora Ave",
    "iso:country":"US",
    "sg:address":"204 E Nora Ave",
    "sg:city":"Spokane",
    "sg:classifiers":[
        {
            "category":"Home & Garden",
            "subcategory":"Building Materials",
            "type":"Retail Goods"
        }
    ],
    "sg:phone":"+1 509 483 6315",
    "sg:postcode":"99207",
    "sg:province":"WA",
    "sg:tags":[
        "glass",
        "window",
        "plate"
    ],
    "wof:name":"Amsbury Glass",
    "wof:placetype":"venue"
},
  "geometry": {"coordinates":[-117.40633699999999,47.673827],"type":"Point"}
}