{
  "type": "Feature",
  "properties": {
    "addr:full":"130 N 3rd Ave Sequim WA 98382",
    "addr:housenumber":"130",
    "addr:postcode":"98382",
    "addr:street":"N 3Rd Ave",
    "iso:country":"US",
    "sg:address":"130 N 3rd Ave",
    "sg:city":"Sequim",
    "sg:classifiers":[
        {
            "category":"Shopping",
            "subcategory":"Jewelry",
            "type":"Retail Goods"
        }
    ],
    "sg:phone":"+1 360 681 3301",
    "sg:postcode":"98382",
    "sg:province":"WA",
    "sg:tags":[
        "clocks"
    ],
    "wof:name":"Village Clock Shoppe",
    "wof:placetype":"venue"
},
  "geometry": {"coordinates":[-123.107792,48.080292],"type":"Point"}
}