{
  "type": "Feature",
  "properties": {
    "addr:full":"501 E 34th St Tacoma WA 98404",
    "addr:housenumber":"501",
    "addr:postcode":"98404",
    "addr:street":"E 34Th St",
    "iso:country":"US",
    "sg:address":"501 E 34th St",
    "sg:city":"Tacoma",
    "sg:classifiers":[
        {
            "category":"Building & Trades",
            "subcategory":"Construction",
            "type":"Services"
        }
    ],
    "sg:phone":"+1 253 573 1260",
    "sg:postcode":"98404",
    "sg:province":"WA",
    "sg:tags":[
        "floor",
        "laying",
        "contractor"
    ],
    "wof:name":"Old Town Hardwood",
    "wof:placetype":"venue"
},
  "geometry": {"coordinates":[-122.424252,47.2312],"type":"Point"}
}