{
  "type": "Feature",
  "properties": {
    "addr:full":"4905 NE 142nd Ave Vancouver WA 98682",
    "addr:housenumber":"4905",
    "addr:postcode":"98682",
    "addr:street":"Ne 142Nd Ave",
    "iso:country":"US",
    "sg:address":"4905 NE 142nd Ave",
    "sg:city":"Vancouver",
    "sg:classifiers":[
        {
            "category":"Social Services",
            "subcategory":"Child Care",
            "type":"Services"
        }
    ],
    "sg:phone":"+1 360 260 1691",
    "sg:postcode":"98682",
    "sg:province":"WA",
    "sg:tags":[
        "day"
    ],
    "wof:name":"Debs Daycare",
    "wof:placetype":"venue"
},
  "geometry": {"coordinates":[-122.526703,45.658675],"type":"Point"}
}