{
  "type": "Feature",
  "properties": {
    "addr:full":"17315 146th Pl NE Woodinville WA 98072",
    "addr:housenumber":"17315",
    "addr:postcode":"98072",
    "addr:street":"146Th Pl Ne",
    "iso:country":"US",
    "sg:address":"17315 146th Pl NE",
    "sg:city":"Woodinville",
    "sg:classifiers":[
        {
            "category":"Manufacturing",
            "subcategory":"Printing",
            "type":"Manufacturing & Wholesale Goods"
        }
    ],
    "sg:phone":"+1 425 398 5992",
    "sg:postcode":"98072",
    "sg:province":"WA",
    "sg:tags":[
        "commercial"
    ],
    "wof:name":"Wordsmith Original LLC",
    "wof:placetype":"venue"
},
  "geometry": {"coordinates":[-122.144696,47.753186],"type":"Point"}
}