{
  "type": "Feature",
  "properties": {
    "addr:full":"101 Sirius Pl Chehalis WA 98532",
    "addr:housenumber":"101",
    "addr:postcode":"98532",
    "addr:street":"Sirius Pl",
    "iso:country":"US",
    "sg:address":"101 Sirius Pl",
    "sg:city":"Chehalis",
    "sg:classifiers":[
        {
            "category":"Building & Trades",
            "subcategory":"Construction",
            "type":"Services"
        }
    ],
    "sg:phone":"+1 360 740 0741",
    "sg:postcode":"98532",
    "sg:province":"WA",
    "sg:tags":[
        "wallcoverings-installation",
        "wallpaper",
        "painting",
        "contractor"
    ],
    "wof:name":"Decorating By Julie",
    "wof:placetype":"venue"
},
  "geometry": {"coordinates":[-122.973381,46.63271],"type":"Point"}
}