{
  "type": "Feature",
  "properties": {
    "addr:full":"400 S Mission St Wenatchee WA 98801",
    "addr:housenumber":"400",
    "addr:postcode":"98801",
    "addr:street":"S;St",
    "iso:country":"US",
    "sg:address":"400 S Mission St",
    "sg:city":"Wenatchee",
    "sg:classifiers":[
        {
            "category":"Health Services",
            "subcategory":"Clinic",
            "type":"Services"
        }
    ],
    "sg:phone":"+1 509 667 2742",
    "sg:postcode":"98801",
    "sg:province":"WA",
    "sg:tags":[
        "agency",
        "welfare"
    ],
    "sg:website":"www.crhomecare.com",
    "wof:name":"Columbia River Home Care",
    "wof:placetype":"venue"
},
  "geometry": {"coordinates":[-120.30758899999999,47.417985],"type":"Point"}
}