{
  "type": "Feature",
  "properties": {
    "addr:full":"14016 Meadowlark Drive Kp N Gig Harbor WA 98329",
    "addr:housenumber":"14016",
    "addr:postcode":"98329",
    "addr:street":"Meadowlark Drive Kp N",
    "iso:country":"US",
    "sg:address":"14016 Meadowlark Drive Kp N",
    "sg:city":"Gig Harbor",
    "sg:classifiers":[
        {
            "category":"Shopping",
            "subcategory":"Discount & Variety Stores",
            "type":"Retail Goods"
        }
    ],
    "sg:phone":"+1 253 884 2134",
    "sg:postcode":"98329",
    "sg:province":"WA",
    "sg:tags":[
        "merchandise",
        "general"
    ],
    "wof:name":"Kristie Mary Hilley",
    "wof:placetype":"venue"
},
  "geometry": {"coordinates":[-122.735291,47.385025],"type":"Point"}
}