{
  "type": "Feature",
  "properties": {
    "addr:full":"1209 S Scheuber Rd Centralia WA 98531",
    "addr:housenumber":"1209",
    "addr:postcode":"98531",
    "addr:street":"S Scheuber Rd",
    "iso:country":"US",
    "sg:address":"1209 S Scheuber Rd",
    "sg:city":"Centralia",
    "sg:classifiers":[
        {
            "category":"Real Estate",
            "subcategory":"Real Estate Agent",
            "type":"Services"
        }
    ],
    "sg:phone":"+1 360 736 3040",
    "sg:postcode":"98531",
    "sg:province":"WA",
    "sg:tags":[
        "cooperative"
    ],
    "wof:name":"Fiddlesticks Cooperative Pre",
    "wof:placetype":"venue"
},
  "geometry": {"coordinates":[-122.987026,46.709114],"type":"Point"}
}