{
  "type": "Feature",
  "properties": {
    "addr:full":"7515 Custer Rd W Lakewood WA 98499",
    "addr:housenumber":"7515",
    "addr:postcode":"98499",
    "addr:street":"Custer Rd W",
    "iso:country":"US",
    "sg:address":"7515 Custer Rd W",
    "sg:city":"Lakewood",
    "sg:classifiers":[
        {
            "category":"Shopping",
            "type":"Retail Goods"
        }
    ],
    "sg:phone":"+1 253 476 4327",
    "sg:postcode":"98499",
    "sg:province":"WA",
    "sg:tags":[
        "hearing",
        "equipment",
        "supply",
        "impaired"
    ],
    "wof:name":"Integrity Hearing Svc PS",
    "wof:placetype":"venue"
},
  "geometry": {"coordinates":[-122.51358500000001,47.188804],"type":"Point"}
}