{
  "type": "Feature",
  "properties": {
    "addr:full":"12721 Bel Red Rd Ste 1 Bellevue WA 98005",
    "addr:housenumber":"12721",
    "addr:postcode":"98005",
    "addr:street":"Bel Red Rd Ste 1",
    "iso:country":"US",
    "sg:address":"12721 Bel Red Rd Ste 1",
    "sg:city":"Bellevue",
    "sg:classifiers":[
        {
            "category":"Real Estate",
            "subcategory":"Real Estate Services",
            "type":"Services"
        }
    ],
    "sg:phone":"+1 425 519 4205",
    "sg:postcode":"98005",
    "sg:province":"WA",
    "sg:tags":[
        "commercial"
    ],
    "wof:name":"The Moore Group",
    "wof:placetype":"venue"
},
  "geometry": {"coordinates":[-122.173799,47.620128],"type":"Point"}
}