{
  "type": "Feature",
  "properties": {
    "addr:full":"1005 E Pike St Seattle WA 98122",
    "addr:housenumber":"1005",
    "addr:postcode":"98122",
    "addr:street":"E Pike St",
    "iso:country":"US",
    "sg:address":"1005 E Pike St",
    "sg:city":"Seattle",
    "sg:classifiers":[
        {
            "category":"Coffee & Tea",
            "type":"Food & Drink"
        },
        {
            "category":"Restaurant",
            "type":"Food & Drink"
        }
    ],
    "sg:phone":"+1 206 709 4440",
    "sg:postcode":"98122",
    "sg:province":"WA",
    "sg:tags":[
        "shop",
        "espresso"
    ],
    "sg:website":"www.caffevita.com/",
    "wof:name":"Caff? Vita",
    "wof:placetype":"venue"
},
  "geometry": {"coordinates":[-122.31905,47.614054],"type":"Point"}
}