{
  "type": "Feature",
  "properties": {
    "iso:country":"US",
    "sg:address":"2708 Westmoor Ct SW",
    "sg:city":"Olympia",
    "sg:classifiers":[
        {
            "category":"Organizations",
            "subcategory":"Non-profit Organization",
            "type":"Services"
        },
        {
            "category":"Health Services",
            "subcategory":"Clinic",
            "type":"Services"
        }
    ],
    "sg:phone":"+1 360 943 8810",
    "sg:postcode":"98502",
    "sg:province":"WA",
    "sg:tags":[
        "information",
        "alcohol",
        "outpatient",
        "drug",
        "treatment",
        "alcoholism"
    ],
    "wof:name":"Northwest Resources II Inc",
    "wof:placetype":"venue"
},
  "geometry": {"coordinates":[-122.935801,47.037578],"type":"Point"}
}