{
  "type": "Feature",
  "properties": {
    "iso:country":"US",
    "sg:address":"2016 Water St",
    "sg:city":"Port Townsend",
    "sg:classifiers":[
        {
            "category":"Building & Trades",
            "subcategory":"Construction",
            "type":"Services"
        }
    ],
    "sg:phone":"+1 360 385 4372",
    "sg:postcode":"98368",
    "sg:province":"WA",
    "sg:tags":[
        "general",
        "contractor"
    ],
    "wof:name":"Discovery Bay Construction Co",
    "wof:placetype":"venue"
},
  "geometry": {"coordinates":[-122.767816,48.10974],"type":"Point"}
}