{
  "type": "Feature",
  "properties": {
    "addr:full":"811 Main St Vancouver WA 98660",
    "addr:housenumber":"811",
    "addr:postcode":"98660",
    "addr:street":"Main St",
    "iso:country":"US",
    "sg:address":"811 Main St",
    "sg:city":"Vancouver",
    "sg:classifiers":[
        {
            "category":"Shopping",
            "subcategory":"Stationery & Office Supplies",
            "type":"Retail Goods"
        }
    ],
    "sg:phone":"+1 360 694 8383",
    "sg:postcode":"98660",
    "sg:province":"WA",
    "sg:tags":[
        "equipment"
    ],
    "wof:name":"Clauson Office Supply Inc",
    "wof:placetype":"venue"
},
  "geometry": {"coordinates":[-122.671997,45.627499],"type":"Point"}
}