{
  "type": "Feature",
  "properties": {
    "addr:full":"10555 Mandus Olson Rd NE Bainbridge Island WA 98110",
    "addr:housenumber":"10555",
    "addr:postcode":"98110",
    "addr:street":"Mandus Olson Rd Ne",
    "iso:country":"US",
    "sg:address":"10555 Mandus Olson Rd NE",
    "sg:city":"Bainbridge Island",
    "sg:classifiers":[
        {
            "category":"Restaurant",
            "type":"Food & Drink"
        }
    ],
    "sg:phone":"+1 206 842 1481",
    "sg:postcode":"98110",
    "sg:province":"WA",
    "sg:tags":[
        "eating"
    ],
    "wof:name":"Epikeehian Cooking Classes",
    "wof:placetype":"venue"
},
  "geometry": {"coordinates":[-122.547983,47.656105],"type":"Point"}
}