{
  "type": "Feature",
  "properties": {
    "addr:full":"104 Young St Grand Coulee WA 99133",
    "addr:housenumber":"104",
    "addr:postcode":"99133",
    "addr:street":"Young St",
    "iso:country":"US",
    "sg:address":"104 Young St",
    "sg:city":"Grand Coulee",
    "sg:classifiers":[
        {
            "category":"Real Estate",
            "subcategory":"Real Estate Operator",
            "type":"Services"
        }
    ],
    "sg:phone":"+1 509 633 2410",
    "sg:postcode":"99133",
    "sg:province":"WA",
    "sg:tags":[
        "mobile",
        "home",
        "site"
    ],
    "wof:name":"Coulee View Mobile Home Park",
    "wof:placetype":"venue"
},
  "geometry": {"coordinates":[-119.00115,47.939519],"type":"Point"}
}