{
  "type": "Feature",
  "properties": {
    "addr:full":"307 S 2nd St Chelan WA 98816",
    "addr:housenumber":"307",
    "addr:postcode":"98816",
    "addr:street":"S 2Nd St",
    "iso:country":"US",
    "sg:address":"307 S 2nd St",
    "sg:city":"Chelan",
    "sg:classifiers":[
        {
            "category":"Real Estate",
            "subcategory":"Surveying",
            "type":"Services"
        }
    ],
    "sg:phone":"+1 509 682 2266",
    "sg:postcode":"98816",
    "sg:province":"WA",
    "sg:tags":[
        "surveyor",
        "land",
        "engineer"
    ],
    "wof:name":"Pinnacle Surveying",
    "wof:placetype":"venue"
},
  "geometry": {"coordinates":[-120.02147100000001,47.838086],"type":"Point"}
}