{
  "type": "Feature",
  "properties": {
    "iso:country":"US",
    "sg:address":"17922 218th Ave NE",
    "sg:city":"Woodinville",
    "sg:classifiers":[
        {
            "category":"Professional",
            "type":"Services"
        }
    ],
    "sg:phone":"+1 425 773 7996",
    "sg:postcode":"98077",
    "sg:province":"WA",
    "wof:name":"Mashie Niblick Golf Shots",
    "wof:placetype":"venue"
},
  "geometry": {"coordinates":[-122.046864,47.75919],"type":"Point"}
}