{
  "type": "Feature",
  "properties": {
    "addr:full":"18201 Olympic Ave S Seattle WA 98188",
    "addr:housenumber":"18201",
    "addr:postcode":"98188",
    "addr:street":"Olympic Ave S",
    "iso:country":"US",
    "sg:address":"18201 Olympic Ave S",
    "sg:city":"Seattle",
    "sg:classifiers":[
        {
            "category":"Wholesale",
            "subcategory":"Metals & Minerals",
            "type":"Manufacturing & Wholesale Goods"
        }
    ],
    "sg:phone":"+1 425 656 0125",
    "sg:postcode":"98188",
    "sg:province":"WA",
    "sg:tags":[
        "industrial",
        "supply"
    ],
    "wof:name":"Tukwila Multalloy Div 9018",
    "wof:placetype":"venue"
},
  "geometry": {"coordinates":[-122.25174199999999,47.436527],"type":"Point"}
}