{
  "type": "Feature",
  "properties": {
    "addr:full":"11910 E Meridian Ave Puyallup WA 98373",
    "addr:housenumber":"11910",
    "addr:postcode":"98373",
    "addr:street":"E Meridian Ave",
    "iso:country":"US",
    "sg:address":"11910 E Meridian Ave",
    "sg:city":"Puyallup",
    "sg:classifiers":[
        {
            "category":"Building & Trades",
            "subcategory":"Cleaning & Sanitation",
            "type":"Services"
        }
    ],
    "sg:phone":"+1 253 770 9550",
    "sg:postcode":"98373",
    "sg:province":"WA",
    "wof:name":"Merry Maids",
    "wof:placetype":"venue"
},
  "geometry": {"coordinates":[-122.29305100000001,47.14829],"type":"Point"}
}