{
  "type": "Feature",
  "properties": {
    "addr:full":"12636 SE 89th Pl Newcastle WA 98056",
    "addr:housenumber":"12636",
    "addr:postcode":"98056",
    "addr:street":"Se 89Th Pl",
    "iso:country":"US",
    "sg:address":"12636 SE 89th Pl",
    "sg:city":"Newcastle",
    "sg:classifiers":[
        {
            "category":"Place Of Worship",
            "type":"Public Place"
        },
        {
            "category":"Organizations",
            "subcategory":"Religious Organization",
            "type":"Services"
        }
    ],
    "sg:phone":"+1 425 228 0810",
    "sg:postcode":"98056",
    "sg:province":"WA",
    "sg:tags":[
        "god",
        "churches-assemblies",
        "church"
    ],
    "sg:website":"http://www.seattlerevivalcenter.com",
    "wof:name":"Seattle Revival Center",
    "wof:placetype":"venue"
},
  "geometry": {"coordinates":[-122.169515,47.522724],"type":"Point"}
}