{
  "type": "Feature",
  "properties": {
    "addr:full":"1507 Liberty St Lynden WA 98264",
    "addr:housenumber":"1507",
    "addr:postcode":"98264",
    "addr:street":"Liberty St",
    "iso:country":"US",
    "sg:address":"1507 Liberty St",
    "sg:city":"Lynden",
    "sg:classifiers":[
        {
            "category":"Professional",
            "subcategory":"Business Services",
            "type":"Services"
        }
    ],
    "sg:phone":"+1 360 354 5548",
    "sg:postcode":"98264",
    "sg:province":"WA",
    "wof:name":"Decks Plus",
    "wof:placetype":"venue"
},
  "geometry": {"coordinates":[-122.469127,48.941571],"type":"Point"}
}