{
  "type": "Feature",
  "properties": {
    "addr:full":"1215 120th Ave NE Ste 206 Bellevue WA 98005",
    "addr:housenumber":"1215",
    "addr:postcode":"98005",
    "addr:street":"120Th Ave Ne Ste 206",
    "iso:country":"US",
    "sg:address":"1215 120th Ave NE Ste 206",
    "sg:city":"Bellevue",
    "sg:classifiers":[
        {
            "category":"Professional",
            "subcategory":"Accounting & Tax Preparation",
            "type":"Services"
        }
    ],
    "sg:phone":"+1 425 646 4988",
    "sg:postcode":"98005",
    "sg:province":"WA",
    "sg:tags":[
        "accountant"
    ],
    "sg:website":"www.ericlongcpa.com",
    "wof:name":"Long Eric CPA",
    "wof:placetype":"venue"
},
  "geometry": {"coordinates":[-122.179682,47.62108],"type":"Point"}
}