{
  "type": "Feature",
  "properties": {
    "addr:full":"13240 NE 20th St Bellevue WA 98005",
    "addr:housenumber":"13240",
    "addr:postcode":"98005",
    "addr:street":"Ne 20Th St",
    "iso:country":"US",
    "sg:address":"13240 NE 20th St",
    "sg:city":"Bellevue",
    "sg:classifiers":[
        {
            "category":"Insurance",
            "subcategory":"Hazard Insurance",
            "type":"Services"
        }
    ],
    "sg:phone":"+1 425 562 9259",
    "sg:postcode":"98005",
    "sg:province":"WA",
    "sg:tags":[
        "profit",
        "sharing",
        "pension",
        "plan"
    ],
    "wof:name":"Flex Plan Svc Inc",
    "wof:placetype":"venue"
},
  "geometry": {"coordinates":[-122.157698,47.628066],"type":"Point"}
}