{
  "type": "Feature",
  "properties": {
    "addr:full":"1309 E 33rd Ave Spokane WA 99203",
    "addr:housenumber":"1309",
    "addr:postcode":"99203",
    "addr:street":"E 33Rd Ave",
    "iso:country":"US",
    "sg:address":"1309 E 33rd Ave",
    "sg:city":"Spokane",
    "sg:classifiers":[
        {
            "category":"Professional",
            "subcategory":"Accounting & Tax Preparation",
            "type":"Services"
        }
    ],
    "sg:phone":"+1 509 624 1685",
    "sg:postcode":"99203",
    "sg:province":"WA",
    "sg:tags":[
        "accountant"
    ],
    "wof:name":"Michael H Craig",
    "wof:placetype":"venue"
},
  "geometry": {"coordinates":[-117.39318400000001,47.624655],"type":"Point"}
}