{
  "type": "Feature",
  "properties": {
    "iso:country":"US",
    "sg:address":"813 W Pacificview Dr",
    "sg:city":"Bellingham",
    "sg:classifiers":[
        {
            "category":"Professional",
            "type":"Services"
        }
    ],
    "sg:phone":"+1 360 734 6086",
    "sg:postcode":"98229",
    "sg:province":"WA",
    "wof:name":"Don McClenahan Consultant",
    "wof:placetype":"venue"
},
  "geometry": {"coordinates":[-122.452089,48.737446],"type":"Point"}
}