{
  "type": "Feature",
  "properties": {
    "addr:full":"8389 Double Ditch Rd Lynden WA 98264",
    "addr:housenumber":"8389",
    "addr:postcode":"98264",
    "addr:street":"Double Ditch Rd",
    "iso:country":"US",
    "sg:address":"8389 Double Ditch Rd",
    "sg:city":"Lynden",
    "sg:classifiers":[
        {
            "category":"Professional",
            "subcategory":"Business Services",
            "type":"Services"
        }
    ],
    "sg:phone":"+1 360 354 4055",
    "sg:postcode":"98264",
    "sg:province":"WA",
    "sg:tags":[
        "drafting"
    ],
    "wof:name":"Sjb Designs",
    "wof:placetype":"venue"
},
  "geometry": {"coordinates":[-122.47463,48.946208],"type":"Point"}
}