{
  "type": "Feature",
  "properties": {
    "addr:full":"2509 152nd Ave NE Redmond WA 98052",
    "addr:housenumber":"2509",
    "addr:postcode":"98052",
    "addr:street":"152Nd Ave Ne",
    "iso:country":"US",
    "sg:address":"2509 152nd Ave NE",
    "sg:city":"Redmond",
    "sg:classifiers":[
        {
            "category":"Wholesale",
            "subcategory":"Computers",
            "type":"Manufacturing & Wholesale Goods"
        }
    ],
    "sg:phone":"+1 425 643 5491",
    "sg:postcode":"98052",
    "sg:province":"WA",
    "wof:name":"Voyagersoft LLC",
    "wof:placetype":"venue"
},
  "geometry": {"coordinates":[-122.13777,47.632801],"type":"Point"}
}