{
  "type": "Feature",
  "properties": {
    "addr:full":"19817 89th Ave S Kent WA 98031",
    "addr:housenumber":"19817",
    "addr:postcode":"98031",
    "addr:street":"89Th Ave S",
    "iso:country":"US",
    "sg:address":"19817 89th Ave S",
    "sg:city":"Kent",
    "sg:classifiers":[
        {
            "category":"Freight",
            "type":"Transportation"
        }
    ],
    "sg:phone":"+1 253 395 9054",
    "sg:postcode":"98031",
    "sg:province":"WA",
    "sg:tags":[
        "public",
        "warehousing"
    ],
    "wof:name":"Tiger Mountain Services",
    "wof:placetype":"venue"
},
  "geometry": {"coordinates":[-122.22222499999999,47.421111],"type":"Point"}
}