{
  "type": "Feature",
  "properties": {
    "addr:full":"2601 W Marina Pl Seattle WA 98199",
    "addr:housenumber":"2601",
    "addr:postcode":"98199",
    "addr:street":"W Marina Pl",
    "iso:country":"US",
    "sg:address":"2601 W Marina Pl",
    "sg:city":"Seattle",
    "sg:classifiers":[
        {
            "category":"Restaurant",
            "type":"Food & Drink"
        }
    ],
    "sg:phone":"+1 206 285 1000",
    "sg:postcode":"98199",
    "sg:province":"WA",
    "sg:tags":[
        "new",
        "seafood",
        "american",
        "hawaiian"
    ],
    "sg:website":"www.palisaderestaurant.com",
    "wof:name":"Palisade Restaurant",
    "wof:placetype":"venue"
},
  "geometry": {"coordinates":[-122.387001,47.6334],"type":"Point"}
}