{
  "type": "Feature",
  "properties": {
    "addr:full":"14525 NE 40th St Bellevue WA 98007",
    "addr:housenumber":"14525",
    "addr:postcode":"98007",
    "addr:street":"Ne 40Th St",
    "iso:country":"US",
    "sg:address":"14525 NE 40th St",
    "sg:city":"Bellevue",
    "sg:classifiers":[
        {
            "category":"Building & Trades",
            "subcategory":"Locksmith",
            "type":"Services"
        }
    ],
    "sg:phone":"+1 425 245 0250",
    "sg:postcode":"98007",
    "sg:province":"WA",
    "sg:tags":[
        "key"
    ],
    "wof:name":"Emergency A Locksmith",
    "wof:placetype":"venue"
},
  "geometry": {"coordinates":[-122.145976,47.645787],"type":"Point"}
}