{
  "type": "Feature",
  "properties": {
    "iso:country":"US",
    "sg:address":"12814 NE 39th St",
    "sg:city":"Bellevue",
    "sg:classifiers":[
        {
            "category":"Professional",
            "subcategory":"Business Services",
            "type":"Services"
        }
    ],
    "sg:phone":"+1 425 558 0233",
    "sg:postcode":"98005",
    "sg:province":"WA",
    "wof:name":"Blue Ribbon Inspection Service",
    "wof:placetype":"venue"
},
  "geometry": {"coordinates":[-122.169675,47.645654],"type":"Point"}
}