{
  "type": "Feature",
  "properties": {
    "iso:country":"US",
    "sg:address":"1125 Cone Way",
    "sg:city":"Kettle Falls",
    "sg:classifiers":[
        {
            "category":"Restaurant",
            "type":"Food & Drink"
        }
    ],
    "sg:phone":"+1 509 738 2566",
    "sg:postcode":"99141",
    "sg:province":"WA",
    "sg:tags":[
        "eating"
    ],
    "wof:name":"Lake Rosevelt Walleye Club",
    "wof:placetype":"venue"
},
  "geometry": {"coordinates":[-118.073114,48.600461],"type":"Point"}
}