{
  "type": "Feature",
  "properties": {
    "addr:full":"902 Ness' Corner Rd Port Hadlock WA 98339",
    "addr:housenumber":"902",
    "addr:postcode":"98339",
    "addr:street":"Ness ' Corner Rd",
    "iso:country":"US",
    "sg:address":"902 Ness' Corner Rd",
    "sg:city":"Port Hadlock",
    "sg:classifiers":[
        {
            "category":"Banks & Credit Unions",
            "subcategory":"Bank",
            "type":"Services"
        }
    ],
    "sg:phone":"+1 360 344 3424",
    "sg:postcode":"98339",
    "sg:province":"WA",
    "wof:name":"Mariner Bank",
    "wof:placetype":"venue"
},
  "geometry": {"coordinates":[-122.76343799999999,48.032263],"type":"Point"}
}