{
  "type": "Feature",
  "properties": {
    "addr:full":"341 NE Tiger Way E Belfair WA 98528",
    "addr:housenumber":"341",
    "addr:postcode":"98528",
    "addr:street":"Ne Tiger Way E",
    "iso:country":"US",
    "sg:address":"341 NE Tiger Way E",
    "sg:city":"Belfair",
    "sg:classifiers":[
        {
            "category":"Building & Trades",
            "subcategory":"Construction",
            "type":"Services"
        }
    ],
    "sg:phone":"+1 360 275 5728",
    "sg:postcode":"98528",
    "sg:province":"WA",
    "sg:tags":[
        "carpentry",
        "contractor"
    ],
    "wof:name":"Turnquist Carpentry & Con",
    "wof:placetype":"venue"
},
  "geometry": {"coordinates":[-122.836662,47.507414],"type":"Point"}
}