{
  "type": "Feature",
  "properties": {
    "addr:full":"505 289th Ave NE Carnation WA 98014",
    "addr:housenumber":"505",
    "addr:postcode":"98014",
    "addr:street":"289Th Ave Ne",
    "iso:country":"US",
    "sg:address":"505 289th Ave NE",
    "sg:city":"Carnation",
    "sg:classifiers":[
        {
            "category":"Farming",
            "subcategory":"Livestock Farm",
            "type":"Manufacturing & Wholesale Goods"
        }
    ],
    "sg:phone":"+1 425 222 3700",
    "sg:postcode":"98014",
    "sg:province":"WA",
    "sg:tags":[
        "beef",
        "feedlot",
        "cattle"
    ],
    "wof:name":"Hawes & Son Farms LLC",
    "wof:placetype":"venue"
},
  "geometry": {"coordinates":[-121.953605,47.615002],"type":"Point"}
}