{
  "type": "Feature",
  "properties": {
    "addr:full":"2901 Firwood Loop SE Olympia WA 98501",
    "addr:housenumber":"2901",
    "addr:postcode":"98501",
    "addr:street":"Firwood Loop Se",
    "iso:country":"US",
    "sg:address":"2901 Firwood Loop SE",
    "sg:city":"Olympia",
    "sg:classifiers":[
        {
            "category":"Real Estate",
            "subcategory":"Real Estate Agent",
            "type":"Services"
        }
    ],
    "sg:phone":"+1 360 456 4998",
    "sg:postcode":"98501",
    "sg:province":"WA",
    "wof:name":"Charmoli Enterprises",
    "wof:placetype":"venue"
},
  "geometry": {"coordinates":[-122.858704,47.002953],"type":"Point"}
}