{
  "type": "Feature",
  "properties": {
    "addr:full":"1740 E Maryland St Bellingham WA 98226",
    "addr:housenumber":"1740",
    "addr:postcode":"98226",
    "addr:street":"E Maryland St",
    "iso:country":"US",
    "sg:address":"1740 E Maryland St",
    "sg:city":"Bellingham",
    "sg:classifiers":[
        {
            "category":"Building & Trades",
            "subcategory":"Landscaping Services",
            "type":"Services"
        }
    ],
    "sg:phone":"+1 360 650 9556",
    "sg:postcode":"98226",
    "sg:province":"WA",
    "wof:name":"R&S Landscaping",
    "wof:placetype":"venue"
},
  "geometry": {"coordinates":[-122.450605,48.766747],"type":"Point"}
}