{
  "type": "Feature",
  "properties": {
    "addr:full":"33417 Tisch Rd S Roy WA 98580",
    "addr:postcode":"33417;98580",
    "addr:street":"Tisch Rd S",
    "iso:country":"US",
    "sg:address":"33417 Tisch Rd S",
    "sg:city":"Roy",
    "sg:classifiers":[
        {
            "category":"Freight",
            "type":"Transportation"
        }
    ],
    "sg:phone":"+1 253 843 1332",
    "sg:postcode":"98580",
    "sg:province":"WA",
    "sg:tags":[
        "local",
        "storage",
        "trucking"
    ],
    "wof:name":"Cherie Ann Cordova",
    "wof:placetype":"venue"
},
  "geometry": {"coordinates":[-122.50743300000001,46.954207],"type":"Point"}
}