{
  "type": "Feature",
  "properties": {
    "addr:full":"9312 N Division St Spokane WA 99218",
    "addr:housenumber":"9312",
    "addr:postcode":"99218",
    "addr:street":"N Division St",
    "iso:country":"US",
    "sg:address":"9312 N Division St",
    "sg:city":"Spokane",
    "sg:classifiers":[
        {
            "category":"Building & Trades",
            "subcategory":"Equipment Rental",
            "type":"Services"
        }
    ],
    "sg:phone":"+1 509 464 4747",
    "sg:postcode":"99218",
    "sg:province":"WA",
    "sg:tags":[
        "leasing",
        "furniture"
    ],
    "wof:name":"Aarons Sales & Lease Ownership",
    "wof:placetype":"venue"
},
  "geometry": {"coordinates":[-117.41139,47.743845],"type":"Point"}
}