{
  "type": "Feature",
  "properties": {
    "addr:full":"14239 SE Petrovitsky Rd Renton WA 98058",
    "addr:postcode":"14239;98058",
    "addr:street":"Se Petrovitsky Rd",
    "iso:country":"US",
    "sg:address":"14239 SE Petrovitsky Rd",
    "sg:city":"Renton",
    "sg:phone":"+1 425 228 2096",
    "sg:postcode":"98058",
    "sg:province":"WA",
    "sg:website":"http://www.greasemonkeyintl.com/",
    "wof:name":"Grease Monkey",
    "wof:placetype":"venue"
},
  "geometry": {"coordinates":[-122.151613,47.444956],"type":"Point"}
}