{
  "type": "Feature",
  "properties": {
    "addr:full":"2909 S 208th St Apt 101 Seatac WA 98198",
    "addr:housenumber":"2909;101",
    "addr:postcode":"98198",
    "addr:street":"S 208Th St Apt",
    "iso:country":"US",
    "sg:address":"2909 S 208th St Apt 101",
    "sg:city":"Seatac",
    "sg:classifiers":[
        {
            "category":"Real Estate",
            "subcategory":"Real Estate Operator",
            "type":"Services"
        }
    ],
    "sg:phone":"+1 206 824 4841",
    "sg:postcode":"98198",
    "sg:province":"WA",
    "sg:tags":[
        "apartment"
    ],
    "wof:name":"Maybill Apartments",
    "wof:placetype":"venue"
},
  "geometry": {"coordinates":[-122.29575,47.415465],"type":"Point"}
}