{
  "type": "Feature",
  "properties": {
    "addr:full":"1914 Bay Ave Aberdeen WA 98520",
    "addr:housenumber":"1914",
    "addr:postcode":"98520",
    "addr:street":"Bay Ave",
    "iso:country":"US",
    "sg:address":"1914 Bay Ave",
    "sg:city":"Aberdeen",
    "sg:classifiers":[
        {
            "category":"Arts & Performance",
            "subcategory":"Theater",
            "type":"Entertainment"
        }
    ],
    "sg:phone":"+1 360 538 1079",
    "sg:postcode":"98520",
    "sg:province":"WA",
    "sg:tags":[
        "group"
    ],
    "wof:name":"Clowning Around",
    "wof:placetype":"venue"
},
  "geometry": {"coordinates":[-123.839063,46.972469],"type":"Point"}
}