{
  "type": "Feature",
  "properties": {
    "addr:full":"4608 NE 4th St Renton WA 98059",
    "addr:housenumber":"4608",
    "addr:postcode":"98059",
    "addr:street":"Ne 4Th St",
    "iso:country":"US",
    "sg:address":"4608 NE 4th St",
    "sg:city":"Renton",
    "sg:classifiers":[
        {
            "category":"Health Services",
            "subcategory":"Chiropractor",
            "type":"Services"
        }
    ],
    "sg:phone":"+1 425 226 6261",
    "sg:postcode":"98059",
    "sg:province":"WA",
    "sg:website":"www.corbinchiropracticclinic.com",
    "wof:name":"Corbin Chiropractic Clinic",
    "wof:placetype":"venue"
},
  "geometry": {"coordinates":[-122.156998,47.4884],"type":"Point"}
}