{
  "type": "Feature",
  "properties": {
    "addr:full":"31532 176th Ave SE Auburn WA 98092",
    "addr:housenumber":"31532",
    "addr:postcode":"98092",
    "addr:street":"176Th Ave Se",
    "iso:country":"US",
    "sg:address":"31532 176th Ave SE",
    "sg:city":"Auburn",
    "sg:classifiers":[
        {
            "category":"Professional",
            "type":"Services"
        }
    ],
    "sg:phone":"+1 253 639 2712",
    "sg:postcode":"98092",
    "sg:province":"WA",
    "wof:name":"Sweet Pea Designs",
    "wof:placetype":"venue"
},
  "geometry": {"coordinates":[-122.107288,47.31754],"type":"Point"}
}