{
  "type": "Feature",
  "properties": {
    "addr:full":"526 Fieldston Rd Bellingham WA 98225",
    "addr:housenumber":"526",
    "addr:postcode":"98225",
    "addr:street":"Fieldston Rd",
    "iso:country":"US",
    "sg:address":"526 Fieldston Rd",
    "sg:city":"Bellingham",
    "sg:classifiers":[
        {
            "category":"Real Estate",
            "subcategory":"Real Estate Agent",
            "type":"Services"
        }
    ],
    "sg:phone":"+1 360 715 3689",
    "sg:postcode":"98225",
    "sg:province":"WA",
    "wof:name":"Muljat Group Real Estate",
    "wof:placetype":"venue"
},
  "geometry": {"coordinates":[-122.510019,48.707878],"type":"Point"}
}