{
  "type": "Feature",
  "properties": {
    "iso:country":"US",
    "sg:address":"17 E 1st Ave",
    "sg:city":"Kennewick",
    "sg:classifiers":[
        {
            "category":"Food & Beverages",
            "subcategory":"Meat & Fish",
            "type":"Retail Goods"
        }
    ],
    "sg:phone":"+1 509 586 6158",
    "sg:postcode":"99336",
    "sg:province":"WA",
    "sg:tags":[
        "plant",
        "eating",
        "packing",
        "mfg"
    ],
    "wof:name":"Chuck's Meat & Lockers",
    "wof:placetype":"venue"
},
  "geometry": {"coordinates":[-119.11556,46.207629],"type":"Point"}
}