{
  "type": "Feature",
  "properties": {
    "addr:full":"11000 NE 84th St Vancouver WA 98662",
    "addr:housenumber":"11000",
    "addr:postcode":"98662",
    "addr:street":"Ne 84Th St",
    "iso:country":"US",
    "sg:address":"11000 NE 84th St",
    "sg:city":"Vancouver",
    "sg:classifiers":[
        {
            "category":"Wholesale",
            "subcategory":"Hardware",
            "type":"Manufacturing & Wholesale Goods"
        }
    ],
    "sg:phone":"+1 360 256 2479",
    "sg:postcode":"98662",
    "sg:province":"WA",
    "sg:tags":[
        "control",
        "equipment",
        "air",
        "pollution"
    ],
    "wof:name":"Dct",
    "wof:placetype":"venue"
},
  "geometry": {"coordinates":[-122.558942,45.683582],"type":"Point"}
}