{
  "type": "Feature",
  "properties": {
    "iso:country":"US",
    "sg:address":"2665 Stryker Ave",
    "sg:city":"Tacoma",
    "sg:classifiers":[
        {
            "category":"Manufacturing",
            "subcategory":"Printing",
            "type":"Manufacturing & Wholesale Goods"
        }
    ],
    "sg:phone":"+1 253 460 2987",
    "sg:postcode":"98433",
    "sg:province":"WA",
    "sg:tags":[
        "newspaper"
    ],
    "wof:name":"Northwest Parent Pubg Inc",
    "wof:placetype":"venue"
},
  "geometry": {"coordinates":[-122.575453,47.069725],"type":"Point"}
}