{
  "type": "Feature",
  "properties": {
    "addr:full":"896 Southcenter Mall Tukwila WA 98188",
    "addr:housenumber":"896",
    "addr:postcode":"98188",
    "addr:street":"Southcenter Mall",
    "iso:country":"US",
    "sg:address":"896 Southcenter Mall",
    "sg:city":"Tukwila",
    "sg:classifiers":[
        {
            "category":"Fast Food",
            "type":"Food & Drink"
        },
        {
            "category":"Restaurant",
            "type":"Food & Drink"
        }
    ],
    "sg:phone":"+1 206 243 6336",
    "sg:postcode":"98188",
    "sg:province":"WA",
    "sg:tags":[
        "take",
        "chinese"
    ],
    "sg:website":"http://www.pandaexpress.com",
    "wof:name":"Panda Express",
    "wof:placetype":"venue"
},
  "geometry": {"coordinates":[-122.258289,47.460665],"type":"Point"}
}