{
  "type": "Feature",
  "properties": {
    "addr:full":"326 NW 85th St Seattle WA 98117",
    "addr:housenumber":"326",
    "addr:postcode":"98117",
    "addr:street":"Nw 85Th St",
    "iso:country":"US",
    "sg:address":"326 NW 85th St",
    "sg:city":"Seattle",
    "sg:classifiers":[
        {
            "category":"Personal",
            "subcategory":"Beauty Salon",
            "type":"Services"
        }
    ],
    "sg:phone":"+1 206 783 2031",
    "sg:postcode":"98117",
    "sg:province":"WA",
    "wof:name":"Vita Beauty Salon",
    "wof:placetype":"venue"
},
  "geometry": {"coordinates":[-122.361358,47.690609],"type":"Point"}
}