{
  "type": "Feature",
  "properties": {
    "addr:full":"14115 107th Avenue Ct E Puyallup WA 98374",
    "addr:housenumber":"14115",
    "addr:postcode":"98374",
    "addr:street":"107Th Avenue Ct E",
    "iso:country":"US",
    "sg:address":"14115 107th Avenue Ct E",
    "sg:city":"Puyallup",
    "sg:classifiers":[
        {
            "category":"Building & Trades",
            "subcategory":"Construction",
            "type":"Services"
        }
    ],
    "sg:phone":"+1 253 848 7994",
    "sg:postcode":"98374",
    "sg:province":"WA",
    "sg:tags":[
        "glazing",
        "contractor"
    ],
    "wof:name":"Kleins Commercial Door Service",
    "wof:placetype":"venue"
},
  "geometry": {"coordinates":[-122.28567099999999,47.130963],"type":"Point"}
}