{
  "type": "Feature",
  "properties": {
    "addr:full":"1501 Pike Pl Seattle WA 98101",
    "addr:housenumber":"1501",
    "addr:postcode":"98101",
    "addr:street":"Pike Pl",
    "iso:country":"US",
    "sg:address":"1501 Pike Pl",
    "sg:city":"Seattle",
    "sg:classifiers":[
        {
            "category":"Shopping",
            "subcategory":"Jewelry",
            "type":"Retail Goods"
        }
    ],
    "sg:phone":"+1 206 622 5039",
    "sg:postcode":"98101",
    "sg:province":"WA",
    "sg:tags":[
        "jeweler"
    ],
    "wof:name":"House of Silver & Gold the",
    "wof:placetype":"venue"
},
  "geometry": {"coordinates":[-122.341003,47.6087],"type":"Point"}
}