{
  "type": "Feature",
  "properties": {
    "addr:full":"1115 13th St Clarkston WA 99403",
    "addr:housenumber":"1115",
    "addr:postcode":"99403",
    "addr:street":"13Th St",
    "iso:country":"US",
    "sg:address":"1115 13th St",
    "sg:city":"Clarkston",
    "sg:classifiers":[
        {
            "category":"Organizations",
            "subcategory":"Religious Organization",
            "type":"Services"
        }
    ],
    "sg:phone":"+1 509 758 7751",
    "sg:postcode":"99403",
    "sg:province":"WA",
    "sg:tags":[
        "churches-lutheran",
        "church"
    ],
    "wof:name":"Our Savior's Lutheran Church",
    "wof:placetype":"venue"
},
  "geometry": {"coordinates":[-117.05863100000001,46.40766],"type":"Point"}
}