{
  "type": "Feature",
  "properties": {
    "addr:full":"1019 E Pike St Seattle WA 98122",
    "addr:housenumber":"1019",
    "addr:postcode":"98122",
    "addr:street":"E Pike St",
    "iso:country":"US",
    "sg:address":"1019 E Pike St",
    "sg:city":"Seattle",
    "sg:classifiers":[
        {
            "category":"Personal",
            "subcategory":"Beauty Salon",
            "type":"Services"
        }
    ],
    "sg:phone":"+1 206 568 3240",
    "sg:postcode":"98122",
    "sg:province":"WA",
    "sg:tags":[
        "spa",
        "day"
    ],
    "sg:website":"www.hothousespa.com",
    "wof:name":"Hothouse Spa & Sauna",
    "wof:placetype":"venue"
},
  "geometry": {"coordinates":[-122.319,47.614101],"type":"Point"}
}