{
  "type": "Feature",
  "properties": {
    "addr:full":"15810 SE 13th St Bellevue WA 98008",
    "addr:postcode":"15810;98008",
    "addr:street":"Se 13Th St",
    "iso:country":"US",
    "sg:address":"15810 SE 13th St",
    "sg:city":"Bellevue",
    "sg:classifiers":[
        {
            "category":"Professional",
            "subcategory":"Management & Consulting",
            "type":"Services"
        }
    ],
    "sg:phone":"+1 425 641 9043",
    "sg:postcode":"98008",
    "sg:province":"WA",
    "sg:tags":[
        "communication",
        "business",
        "consultant"
    ],
    "wof:name":"Allen Hartle",
    "wof:placetype":"venue"
},
  "geometry": {"coordinates":[-122.128591,47.598438],"type":"Point"}
}