{
  "type": "Feature",
  "properties": {
    "addr:full":"10907 Aurora Ave N Seattle WA 98133",
    "addr:housenumber":"10907",
    "addr:postcode":"98133",
    "addr:street":"Aurora Ave N",
    "iso:country":"US",
    "sg:address":"10907 Aurora Ave N",
    "sg:city":"Seattle",
    "sg:classifiers":[
        {
            "category":"Shopping",
            "subcategory":"Pets & Pet Supplies",
            "type":"Retail Goods"
        }
    ],
    "sg:phone":"+1 425 890 3177",
    "sg:postcode":"98133",
    "sg:province":"WA",
    "sg:tags":[
        "training"
    ],
    "sg:website":"www.funquestdogsports.com",
    "wof:name":"FunQuest Dog Sports - Agility Training",
    "wof:placetype":"venue"
},
  "geometry": {"coordinates":[-122.345248,47.708385],"type":"Point"}
}