{
  "type": "Feature",
  "properties": {
    "addr:full":"9328 I- 5 Ephrata WA 98823",
    "addr:housenumber":"9328;5",
    "addr:postcode":"98823",
    "addr:street":"I",
    "iso:country":"US",
    "sg:address":"9328 I- 5",
    "sg:city":"Ephrata",
    "sg:classifiers":[
        {
            "category":"Farming",
            "subcategory":"Farm",
            "type":"Manufacturing & Wholesale Goods"
        }
    ],
    "sg:phone":"+1 509 760 4481",
    "sg:postcode":"98823",
    "sg:province":"WA",
    "sg:tags":[
        "crop",
        "general"
    ],
    "wof:name":"J K Farms",
    "wof:placetype":"venue"
},
  "geometry": {"coordinates":[-119.692813,47.222],"type":"Point"}
}