{
  "type": "Feature",
  "properties": {
    "addr:full":"5894 Everson Goshen Rd Bellingham WA 98226",
    "addr:housenumber":"5894",
    "addr:postcode":"98226",
    "addr:street":"Everson Goshen Rd",
    "iso:country":"US",
    "sg:address":"5894 Everson Goshen Rd",
    "sg:city":"Bellingham",
    "sg:classifiers":[
        {
            "category":"Retail",
            "subcategory":"Auto Repair",
            "type":"Services"
        }
    ],
    "sg:phone":"+1 360 966 4988",
    "sg:postcode":"98226",
    "sg:province":"WA",
    "sg:tags":[
        "transmission"
    ],
    "wof:name":"Whatcom Transmission Service",
    "wof:placetype":"venue"
},
  "geometry": {"coordinates":[-122.376198,48.844534],"type":"Point"}
}