{
  "type": "Feature",
  "properties": {
    "addr:full":"404 S Waugh Rd Mount Vernon WA 98274",
    "addr:housenumber":"404",
    "addr:postcode":"98274",
    "addr:street":"S Waugh Rd",
    "iso:country":"US",
    "sg:address":"404 S Waugh Rd",
    "sg:city":"Mount Vernon",
    "sg:phone":"+1 360 424 6338",
    "sg:postcode":"98274",
    "sg:province":"WA",
    "sg:tags":[
        "farm",
        "grain",
        "cash"
    ],
    "wof:name":"Swanson & Swanson",
    "wof:placetype":"venue"
},
  "geometry": {"coordinates":[-122.286818,48.417367],"type":"Point"}
}