{
  "type": "Feature",
  "properties": {
    "addr:full":"1414 54th Ave E Tacoma WA 98424",
    "addr:housenumber":"1414",
    "addr:postcode":"98424",
    "addr:street":"54Th Ave E",
    "iso:country":"US",
    "sg:address":"1414 54th Ave E",
    "sg:city":"Tacoma",
    "sg:classifiers":[
        {
            "category":"Shopping",
            "subcategory":"Used Merchandise",
            "type":"Retail Goods"
        }
    ],
    "sg:phone":"+1 253 922 1297",
    "sg:postcode":"98424",
    "sg:province":"WA",
    "sg:tags":[
        "antique"
    ],
    "wof:name":"Twice Told Tale Antiques",
    "wof:placetype":"venue"
},
  "geometry": {"coordinates":[-122.35697500000001,47.245981],"type":"Point"}
}