{
  "type": "Feature",
  "properties": {
    "addr:full":"1502 105th Ln SE Olympia WA 98501",
    "addr:housenumber":"1502",
    "addr:postcode":"98501",
    "addr:street":"105Th Ln Se",
    "iso:country":"US",
    "sg:address":"1502 105th Ln SE",
    "sg:city":"Olympia",
    "sg:classifiers":[
        {
            "category":"Professional",
            "type":"Services"
        }
    ],
    "sg:phone":"+1 360 357 6692",
    "sg:postcode":"98501",
    "sg:province":"WA",
    "wof:name":"Alan W Shue",
    "wof:placetype":"venue"
},
  "geometry": {"coordinates":[-122.883459,46.934643],"type":"Point"}
}