{
  "type": "Feature",
  "properties": {
    "addr:full":"1221 1st Ave Seattle WA 98101",
    "addr:housenumber":"1221",
    "addr:postcode":"98101",
    "addr:street":"1St Ave",
    "iso:country":"US",
    "sg:address":"1221 1st Ave",
    "sg:city":"Seattle",
    "sg:classifiers":[
        {
            "category":"Professional",
            "subcategory":"Management & Consulting",
            "type":"Services"
        }
    ],
    "sg:phone":"+1 206 624 8535",
    "sg:postcode":"98101",
    "sg:province":"WA",
    "sg:tags":[
        "consultant",
        "business"
    ],
    "wof:name":"Q-Link Resources",
    "wof:placetype":"venue"
},
  "geometry": {"coordinates":[-122.338173,47.606647],"type":"Point"}
}