{
  "type": "Feature",
  "properties": {
    "addr:full":"3108 E Ferry Ave Spokane WA 99202",
    "addr:housenumber":"3108",
    "addr:postcode":"99202",
    "addr:street":"E Ferry Ave",
    "iso:country":"US",
    "sg:address":"3108 E Ferry Ave",
    "sg:city":"Spokane",
    "sg:classifiers":[
        {
            "category":"Shopping",
            "type":"Retail Goods"
        }
    ],
    "sg:phone":"+1 509 534 5957",
    "sg:postcode":"99202",
    "sg:province":"WA",
    "sg:tags":[
        "merchandise"
    ],
    "wof:name":"Oceanview Aquatics",
    "wof:placetype":"venue"
},
  "geometry": {"coordinates":[-117.362308,47.661014],"type":"Point"}
}