{
  "type": "Feature",
  "properties": {
    "addr:full":"7930 230th St SW Edmonds WA 98026",
    "addr:housenumber":"7930",
    "addr:postcode":"98026",
    "addr:street":"230Th St Sw",
    "iso:country":"US",
    "sg:address":"7930 230th St SW",
    "sg:city":"Edmonds",
    "sg:classifiers":[
        {
            "category":"Professional",
            "subcategory":"Management & Consulting",
            "type":"Services"
        },
        {
            "category":"Insurance",
            "subcategory":"Insurance Agent",
            "type":"Services"
        }
    ],
    "sg:phone":"+1 206 343 5016",
    "sg:postcode":"98026",
    "sg:province":"WA",
    "sg:tags":[
        "business"
    ],
    "wof:name":"Uniersal Corp Benefit Plans",
    "wof:placetype":"venue"
},
  "geometry": {"coordinates":[-122.33929000000001,47.790463],"type":"Point"}
}