{
  "type": "Feature",
  "properties": {
    "addr:full":"3010 59th Ct SE Olympia WA 98501",
    "addr:housenumber":"3010",
    "addr:postcode":"98501",
    "addr:street":"59Th Ct Se",
    "iso:country":"US",
    "sg:address":"3010 59th Ct SE",
    "sg:city":"Olympia",
    "sg:classifiers":[
        {
            "category":"Education",
            "subcategory":"Special Training",
            "type":"Public Place"
        }
    ],
    "sg:phone":"+1 360 923 5815",
    "sg:postcode":"98501",
    "sg:province":"WA",
    "wof:name":"Pamela M Z Firth",
    "wof:placetype":"venue"
},
  "geometry": {"coordinates":[-122.853725,46.995527],"type":"Point"}
}