{
  "type": "Feature",
  "properties": {
    "addr:full":"116 SW 160th St Burien WA 98166",
    "addr:housenumber":"116",
    "addr:postcode":"98166",
    "addr:street":"Sw 160Th St",
    "iso:country":"US",
    "sg:address":"116 SW 160th St",
    "sg:city":"Burien",
    "sg:classifiers":[
        {
            "category":"Health Services",
            "subcategory":"Dentist",
            "type":"Services"
        }
    ],
    "sg:phone":"+1 206 241 6554",
    "sg:postcode":"98166",
    "sg:province":"WA",
    "sg:tags":[
        "dentists-orthodontists"
    ],
    "wof:name":"Rudey Orthodontics",
    "wof:placetype":"venue"
},
  "geometry": {"coordinates":[-122.334986,47.459682],"type":"Point"}
}