{
  "type": "Feature",
  "properties": {
    "addr:full":"18310 Fales Rd Snohomish WA 98296",
    "addr:postcode":"18310;98296",
    "addr:street":"Fales Rd",
    "iso:country":"US",
    "sg:address":"18310 Fales Rd",
    "sg:city":"Snohomish",
    "sg:classifiers":[
        {
            "category":"Building & Trades",
            "subcategory":"Construction",
            "type":"Services"
        }
    ],
    "sg:phone":"+1 360 668 4137",
    "sg:postcode":"98296",
    "sg:province":"WA",
    "sg:tags":[
        "rough",
        "framing",
        "contractor"
    ],
    "wof:name":"Cornelsen Construction Company",
    "wof:placetype":"venue"
},
  "geometry": {"coordinates":[-122.077403,47.830856],"type":"Point"}
}