{
  "type": "Feature",
  "properties": {
    "addr:full":"2131 7th Ave SW Puyallup WA 98371",
    "addr:housenumber":"2131",
    "addr:postcode":"98371",
    "addr:street":"7Th Ave Sw",
    "iso:country":"US",
    "sg:address":"2131 7th Ave SW",
    "sg:city":"Puyallup",
    "sg:classifiers":[
        {
            "category":"Real Estate",
            "subcategory":"Developer",
            "type":"Services"
        }
    ],
    "sg:phone":"+1 253 686 9451",
    "sg:postcode":"98371",
    "sg:province":"WA",
    "wof:name":"Breckenridge Development",
    "wof:placetype":"venue"
},
  "geometry": {"coordinates":[-122.32442399999999,47.186813],"type":"Point"}
}