{
  "type": "Feature",
  "properties": {
    "addr:full":"10302 NE 137th Pl Kirkland WA 98034",
    "addr:housenumber":"10302",
    "addr:postcode":"98034",
    "addr:street":"Ne 137Th Pl",
    "iso:country":"US",
    "sg:address":"10302 NE 137th Pl",
    "sg:city":"Kirkland",
    "sg:classifiers":[
        {
            "category":"Professional",
            "type":"Services"
        }
    ],
    "sg:phone":"+1 425 821 6505",
    "sg:postcode":"98034",
    "sg:province":"WA",
    "wof:name":"Someone Special",
    "wof:placetype":"venue"
},
  "geometry": {"coordinates":[-122.203682,47.723833],"type":"Point"}
}