{
  "type": "Feature",
  "properties": {
    "addr:full":"1203 D St Washougal WA 98671",
    "addr:housenumber":"1203",
    "addr:postcode":"98671",
    "addr:street":"D St",
    "iso:country":"US",
    "sg:address":"1203 D St",
    "sg:city":"Washougal",
    "sg:classifiers":[
        {
            "category":"Professional",
            "subcategory":"Research",
            "type":"Services"
        }
    ],
    "sg:phone":"+1 360 335 0368",
    "sg:postcode":"98671",
    "sg:province":"WA",
    "sg:tags":[
        "environmental",
        "ecological"
    ],
    "wof:name":"MSE Environmental",
    "wof:placetype":"venue"
},
  "geometry": {"coordinates":[-122.358783,45.580083],"type":"Point"}
}