{
  "type": "Feature",
  "properties": {
    "addr:full":"216 S 1st St Rockford WA 99030",
    "addr:housenumber":"216",
    "addr:postcode":"99030",
    "addr:street":"S 1St St",
    "iso:country":"US",
    "sg:address":"216 S 1st St",
    "sg:city":"Rockford",
    "sg:classifiers":[
        {
            "category":"Food & Beverages",
            "subcategory":"Groceries & Convenience Stores",
            "type":"Retail Goods"
        }
    ],
    "sg:phone":"+1 509 291 4351",
    "sg:postcode":"99030",
    "sg:province":"WA",
    "wof:name":"Rockford Mini Mart",
    "wof:placetype":"venue"
},
  "geometry": {"coordinates":[-117.131975,47.450395],"type":"Point"}
}