{
  "type": "Feature",
  "properties": {
    "addr:full":"3004 E Boone Ave Spokane WA 99202",
    "addr:housenumber":"3004",
    "addr:postcode":"99202",
    "addr:street":"E Boone Ave",
    "iso:country":"US",
    "sg:address":"3004 E Boone Ave",
    "sg:city":"Spokane",
    "sg:classifiers":[
        {
            "category":"Freight",
            "type":"Transportation"
        }
    ],
    "sg:phone":"+1 509 536 4848",
    "sg:postcode":"99202",
    "sg:province":"WA",
    "sg:tags":[
        "commercial",
        "storage"
    ],
    "wof:name":"Boone Mini Storage",
    "wof:placetype":"venue"
},
  "geometry": {"coordinates":[-117.36527100000001,47.669094],"type":"Point"}
}