{
  "type": "Feature",
  "properties": {
    "iso:country":"US",
    "sg:address":"2117 NW 95th St",
    "sg:city":"Seattle",
    "sg:classifiers":[
        {
            "category":"Airline",
            "type":"Transportation"
        }
    ],
    "sg:phone":"+1 206 669 2158",
    "sg:postcode":"98117",
    "sg:province":"WA",
    "sg:tags":[
        "scheduled",
        "air"
    ],
    "wof:name":"San Jaun Airlines",
    "wof:placetype":"venue"
},
  "geometry": {"coordinates":[-122.38518000000001,47.698162],"type":"Point"}
}