{
  "type": "Feature",
  "properties": {
    "addr:full":"404 W Clark St Pasco WA 99301",
    "addr:housenumber":"404",
    "addr:postcode":"99301",
    "addr:street":"W Clark St",
    "iso:country":"US",
    "sg:address":"404 W Clark St",
    "sg:city":"Pasco",
    "sg:classifiers":[
        {
            "category":"Government",
            "subcategory":"Office",
            "type":"Public Place"
        }
    ],
    "sg:phone":"+1 509 545 3536",
    "sg:postcode":"99301",
    "sg:province":"WA",
    "wof:name":"Franklin County Marriages",
    "wof:placetype":"venue"
},
  "geometry": {"coordinates":[-119.092648,46.231427],"type":"Point"}
}