{
  "type": "Feature",
  "properties": {
    "addr:full":"15729 24th Dr SE Bothell WA 98012",
    "addr:housenumber":"15729",
    "addr:postcode":"98012",
    "addr:street":"24Th Dr Se",
    "iso:country":"US",
    "sg:address":"15729 24th Dr SE",
    "sg:city":"Bothell",
    "sg:classifiers":[
        {
            "category":"Building & Trades",
            "subcategory":"Construction",
            "type":"Services"
        }
    ],
    "sg:phone":"+1 425 743 3631",
    "sg:postcode":"98012",
    "sg:province":"WA",
    "sg:tags":[
        "home"
    ],
    "wof:name":"Freeman Roy Roofing Co",
    "wof:placetype":"venue"
},
  "geometry": {"coordinates":[-122.199904,47.855041],"type":"Point"}
}