{
  "type": "Feature",
  "properties": {
    "addr:full":"267 Scholze St Leavenworth WA 98826",
    "addr:housenumber":"267",
    "addr:postcode":"98826",
    "addr:street":"Scholze St",
    "iso:country":"US",
    "sg:address":"267 Scholze St",
    "sg:city":"Leavenworth",
    "sg:classifiers":[
        {
            "category":"Real Estate",
            "subcategory":"Real Estate Operator",
            "type":"Services"
        }
    ],
    "sg:phone":"+1 509 548 5791",
    "sg:postcode":"98826",
    "sg:province":"WA",
    "sg:tags":[
        "property",
        "lessor"
    ],
    "wof:name":"Richard Buddrius",
    "wof:placetype":"venue"
},
  "geometry": {"coordinates":[-120.670603,47.589502],"type":"Point"}
}