{
  "type": "Feature",
  "properties": {
    "addr:full":"18620 244th Ave NE Woodinville WA 98077",
    "addr:housenumber":"18620",
    "addr:postcode":"98077",
    "addr:street":"244Th Ave Ne",
    "iso:country":"US",
    "sg:address":"18620 244th Ave NE",
    "sg:city":"Woodinville",
    "sg:classifiers":[
        {
            "category":"Professional",
            "subcategory":"Detective & Security Services",
            "type":"Services"
        }
    ],
    "sg:phone":"+1 425 788 3946",
    "sg:postcode":"98077",
    "sg:province":"WA",
    "sg:tags":[
        "information",
        "bureau"
    ],
    "wof:name":"Aqua Industrial Service Inc",
    "wof:placetype":"venue"
},
  "geometry": {"coordinates":[-122.013223,47.762328],"type":"Point"}
}