{
  "type": "Feature",
  "properties": {
    "addr:full":"936 N 34th Street Suite 300 Seattle WA 98103",
    "addr:housenumber":"936",
    "addr:postcode":"98103",
    "addr:street":"N 34Th Street Suite 300",
    "iso:country":"US",
    "sg:address":"936 N 34th Street Suite 300",
    "sg:city":"Seattle",
    "sg:classifiers":[
        {
            "category":"Professional",
            "subcategory":"Advertising",
            "type":"Services"
        }
    ],
    "sg:phone":"+1 888 897 7225",
    "sg:postcode":"98103",
    "sg:province":"WA",
    "sg:tags":[
        "advertising",
        "banner",
        "display"
    ],
    "sg:website":"http://adready.com",
    "wof:name":"AdReady",
    "wof:placetype":"venue"
},
  "geometry": {"coordinates":[-122.345364,47.649024],"type":"Point"}
}