{
  "type": "Feature",
  "properties": {
    "addr:full":"5655 Wraspir Rd E Odessa WA 99159",
    "addr:housenumber":"5655",
    "addr:postcode":"99159",
    "addr:street":"Wraspir Rd E Odessa",
    "iso:country":"US",
    "sg:address":"5655 Wraspir Rd E",
    "sg:city":"Odessa",
    "sg:classifiers":[
        {
            "category":"Farming",
            "subcategory":"Farm",
            "type":"Manufacturing & Wholesale Goods"
        }
    ],
    "sg:phone":"+1 509 982 2802",
    "sg:postcode":"99159",
    "sg:province":"WA",
    "sg:tags":[
        "crop",
        "general"
    ],
    "wof:name":"M&M Farms Inc",
    "wof:placetype":"venue"
},
  "geometry": {"coordinates":[-118.854737,47.364299],"type":"Point"}
}