{
  "type": "Feature",
  "properties": {
    "addr:full":"4851 S Tacoma Way Tacoma WA 98409",
    "addr:housenumber":"4851",
    "addr:postcode":"98409",
    "addr:street":"S Tacoma Way",
    "iso:country":"US",
    "sg:address":"4851 S Tacoma Way",
    "sg:city":"Tacoma",
    "sg:classifiers":[
        {
            "category":"Recreation",
            "type":"Entertainment"
        }
    ],
    "sg:phone":"+1 253 591 5299",
    "sg:postcode":"98409",
    "sg:province":"WA",
    "sg:tags":[
        "school",
        "public",
        "hall",
        "auditorium"
    ],
    "wof:name":"South Park Community Center",
    "wof:placetype":"venue"
},
  "geometry": {"coordinates":[-122.483688,47.2126],"type":"Point"}
}