{
  "type": "Feature",
  "properties": {
    "addr:full":"720 N Argonne Rd Spokane WA 99212",
    "addr:housenumber":"720",
    "addr:postcode":"99212",
    "addr:street":"N Argonne Rd",
    "iso:country":"US",
    "sg:address":"720 N Argonne Rd",
    "sg:city":"Spokane",
    "sg:classifiers":[
        {
            "category":"Insurance",
            "subcategory":"Insurance Agent",
            "type":"Services"
        }
    ],
    "sg:phone":"+1 509 922 2098",
    "sg:postcode":"99212",
    "sg:province":"WA",
    "wof:name":"Allstate",
    "wof:placetype":"venue"
},
  "geometry": {"coordinates":[-117.282757,47.662922],"type":"Point"}
}