{
  "type": "Feature",
  "properties": {
    "addr:full":"4928 30th Ave S Seattle WA 98108",
    "addr:housenumber":"4928",
    "addr:postcode":"98108",
    "addr:street":"30Th Ave S",
    "iso:country":"US",
    "sg:address":"4928 30th Ave S",
    "sg:city":"Seattle",
    "sg:classifiers":[
        {
            "category":"Organizations",
            "subcategory":"Religious Organization",
            "type":"Services"
        }
    ],
    "sg:phone":"+1 206 725 1298",
    "sg:postcode":"98108",
    "sg:province":"WA",
    "wof:name":"Tibetan Support Network",
    "wof:placetype":"venue"
},
  "geometry": {"coordinates":[-122.29409699999999,47.557982],"type":"Point"}
}