{
  "type": "Feature",
  "properties": {
    "addr:full":"3719 Spokane St Tacoma WA 98404",
    "addr:housenumber":"3719",
    "addr:postcode":"98404",
    "addr:street":"Spokane St",
    "iso:country":"US",
    "sg:address":"3719 Spokane St",
    "sg:city":"Tacoma",
    "sg:classifiers":[
        {
            "category":"Shopping",
            "subcategory":"Music",
            "type":"Retail Goods"
        }
    ],
    "sg:phone":"+1 253 279 6593",
    "sg:postcode":"98404",
    "sg:province":"WA",
    "wof:name":"On Block Records",
    "wof:placetype":"venue"
},
  "geometry": {"coordinates":[-122.41956500000001,47.22342],"type":"Point"}
}