{
  "type": "Feature",
  "properties": {
    "addr:full":"313 Spring St Friday Harbor WA 98250",
    "addr:housenumber":"313",
    "addr:postcode":"98250",
    "addr:street":"Spring St",
    "iso:country":"US",
    "sg:address":"313 Spring St",
    "sg:city":"Friday Harbor",
    "sg:classifiers":[
        {
            "category":"Autos & Motor Vehicles",
            "subcategory":"Boat Sales",
            "type":"Retail Goods"
        },
        {
            "category":"Shopping",
            "subcategory":"Bicycles & Sporting Goods",
            "type":"Retail Goods"
        }
    ],
    "sg:phone":"+1 360 378 1086",
    "sg:postcode":"98250",
    "sg:province":"WA",
    "sg:tags":[
        "equipment",
        "supply"
    ],
    "wof:name":"West Marine Products Inc",
    "wof:placetype":"venue"
},
  "geometry": {"coordinates":[-123.017713,48.533495],"type":"Point"}
}