{
  "type": "Feature",
  "properties": {
    "addr:full":"26312 152nd St SE Monroe WA 98272",
    "addr:housenumber":"26312",
    "addr:postcode":"98272",
    "addr:street":"152Nd St Se",
    "iso:country":"US",
    "sg:address":"26312 152nd St SE",
    "sg:city":"Monroe",
    "sg:classifiers":[
        {
            "category":"Social Services",
            "type":"Services"
        }
    ],
    "sg:phone":"+1 360 863 9733",
    "sg:postcode":"98272",
    "sg:province":"WA",
    "sg:tags":[
        "counseling"
    ],
    "wof:name":"Elijah House",
    "wof:placetype":"venue"
},
  "geometry": {"coordinates":[-121.877703,47.859893],"type":"Point"}
}