{
  "type": "Feature",
  "properties": {
    "iso:country":"US",
    "sg:address":"10316 SE 15th St",
    "sg:city":"Vancouver",
    "sg:classifiers":[
        {
            "category":"Real Estate",
            "subcategory":"Real Estate Operator",
            "type":"Services"
        }
    ],
    "sg:phone":"+1 360 896 3369",
    "sg:postcode":"98664",
    "sg:province":"WA",
    "sg:tags":[
        "property",
        "lessor"
    ],
    "wof:name":"Sharry McNeel Inc",
    "wof:placetype":"venue"
},
  "geometry": {"coordinates":[-122.566728,45.610513],"type":"Point"}
}