{
  "type": "Feature",
  "properties": {
    "addr:full":"8506 E Mill Plain Blvd Vancouver WA 98664",
    "addr:housenumber":"8506",
    "addr:postcode":"98664",
    "addr:street":"E Mill Plain Blvd",
    "iso:country":"US",
    "sg:address":"8506 E Mill Plain Blvd",
    "sg:city":"Vancouver",
    "sg:classifiers":[
        {
            "category":"Shopping",
            "subcategory":"Pharmacy",
            "type":"Retail Goods"
        }
    ],
    "sg:phone":"+1 360 694 3353",
    "sg:postcode":"98664",
    "sg:province":"WA",
    "sg:tags":[
        "gift"
    ],
    "wof:name":"Mike's Eastside Drugs",
    "wof:placetype":"venue"
},
  "geometry": {"coordinates":[-122.583687,45.623151],"type":"Point"}
}