{
  "type": "Feature",
  "properties": {
    "addr:full":"12115 Canyon Rd Ellensburg WA 98926",
    "addr:housenumber":"12115",
    "addr:postcode":"98926",
    "addr:street":"Canyon Rd",
    "iso:country":"US",
    "sg:address":"12115 Canyon Rd",
    "sg:city":"Ellensburg",
    "sg:classifiers":[
        {
            "category":"Restaurant",
            "type":"Food & Drink"
        }
    ],
    "sg:phone":"+1 253 722 5196",
    "sg:postcode":"98926",
    "sg:province":"WA",
    "sg:tags":[
        "mexican"
    ],
    "wof:name":"El Toro Restaurants",
    "wof:placetype":"venue"
},
  "geometry": {"coordinates":[-120.44040699999999,46.807961],"type":"Point"}
}