{
  "type": "Feature",
  "properties": {
    "addr:full":"645 Front St Leavenworth WA 98826",
    "addr:housenumber":"645",
    "addr:postcode":"98826",
    "addr:street":"Front St",
    "iso:country":"US",
    "sg:address":"645 Front St",
    "sg:city":"Leavenworth",
    "sg:classifiers":[
        {
            "category":"Shopping",
            "subcategory":"Clothing, Apparel, & Fashions",
            "type":"Retail Goods"
        }
    ],
    "sg:phone":"+1 509 548 4840",
    "sg:postcode":"98826",
    "sg:province":"WA",
    "wof:name":"Victorian Simplicity",
    "wof:placetype":"venue"
},
  "geometry": {"coordinates":[-120.66251099999999,47.59484],"type":"Point"}
}