{
  "type": "Feature",
  "properties": {
    "addr:full":"3626 NE 45th St Ste 200 Seattle WA 98105",
    "addr:housenumber":"3626",
    "addr:postcode":"98105",
    "addr:street":"Ne 45Th St Ste 200",
    "iso:country":"US",
    "sg:address":"3626 NE 45th St Ste 200",
    "sg:city":"Seattle",
    "sg:classifiers":[
        {
            "category":"Health Services",
            "subcategory":"Dentist",
            "type":"Services"
        }
    ],
    "sg:phone":"+1 206 384 4651",
    "sg:postcode":"98105",
    "sg:province":"WA",
    "sg:website":"www.fidleronthetooth.com",
    "wof:name":"Vicki L Fidler, DDS",
    "wof:placetype":"venue"
},
  "geometry": {"coordinates":[-122.288003,47.661431],"type":"Point"}
}