{
  "type": "Feature",
  "properties": {
    "addr:full":"3403 Lind Ave SW Renton WA 98057",
    "addr:housenumber":"3403",
    "addr:postcode":"98057",
    "addr:street":"Lind Ave Sw",
    "iso:country":"US",
    "sg:address":"3403 Lind Ave SW",
    "sg:city":"Renton",
    "sg:classifiers":[
        {
            "category":"Wholesale",
            "subcategory":"Auto Parts",
            "type":"Manufacturing & Wholesale Goods"
        }
    ],
    "sg:phone":"+1 425 226 1880",
    "sg:postcode":"98057",
    "sg:province":"WA",
    "sg:tags":[
        "automobile"
    ],
    "wof:name":"CPW",
    "wof:placetype":"venue"
},
  "geometry": {"coordinates":[-122.223675,47.449211],"type":"Point"}
}