{
  "type": "Feature",
  "properties": {
    "addr:full":"1445 10th Pl N Edmonds WA 98020",
    "addr:housenumber":"1445",
    "addr:postcode":"98020",
    "addr:street":"10Th Pl N",
    "iso:country":"US",
    "sg:address":"1445 10th Pl N",
    "sg:city":"Edmonds",
    "sg:classifiers":[
        {
            "category":"Building & Trades",
            "subcategory":"Construction",
            "type":"Services"
        }
    ],
    "sg:phone":"+1 425 776 3425",
    "sg:postcode":"98020",
    "sg:province":"WA",
    "sg:tags":[
        "driveway",
        "parking",
        "paving",
        "lot",
        "contractor"
    ],
    "wof:name":"Roberts & Associates",
    "wof:placetype":"venue"
},
  "geometry": {"coordinates":[-122.364817,47.823541],"type":"Point"}
}