{
  "type": "Feature",
  "properties": {
    "addr:full":"14909 NE 31st St Vancouver WA 98682",
    "addr:housenumber":"14909",
    "addr:postcode":"98682",
    "addr:street":"Ne 31St St",
    "iso:country":"US",
    "sg:address":"14909 NE 31st St",
    "sg:city":"Vancouver",
    "sg:classifiers":[
        {
            "category":"Building & Trades",
            "subcategory":"Construction",
            "type":"Services"
        }
    ],
    "sg:phone":"+1 360 256 6489",
    "sg:postcode":"98682",
    "sg:province":"WA",
    "sg:tags":[
        "general",
        "contractor"
    ],
    "wof:name":"Hall Construction",
    "wof:placetype":"venue"
},
  "geometry": {"coordinates":[-122.518855,45.644266],"type":"Point"}
}