{
  "type": "Feature",
  "properties": {
    "addr:full":"960 Park Ave N Ste 104A Renton WA 98055",
    "addr:housenumber":"960;104a",
    "addr:postcode":"98055",
    "addr:street":"Park Ave N Ste",
    "iso:country":"US",
    "sg:address":"960 Park Ave N Ste 104A",
    "sg:city":"Renton",
    "sg:classifiers":[
        {
            "category":"Restaurant",
            "type":"Food & Drink"
        }
    ],
    "sg:phone":"+1 425 917 2193",
    "sg:postcode":"98055",
    "sg:province":"WA",
    "sg:tags":[
        "chinese"
    ],
    "sg:website":"www.pandaexpress.com",
    "wof:name":"Panda Express",
    "wof:placetype":"venue"
},
  "geometry": {"coordinates":[-122.202129,47.498126],"type":"Point"}
}