{
  "type": "Feature",
  "properties": {
    "addr:full":"15 Boyer Ave Walla Walla WA 99362",
    "addr:housenumber":"15",
    "addr:postcode":"99362",
    "addr:street":"Boyer Ave",
    "iso:country":"US",
    "sg:address":"15 Boyer Ave",
    "sg:city":"Walla Walla",
    "sg:classifiers":[
        {
            "category":"Shopping",
            "subcategory":"Used Merchandise",
            "type":"Retail Goods"
        }
    ],
    "sg:phone":"+1 509 526 3141",
    "sg:postcode":"99362",
    "sg:province":"WA",
    "wof:name":"Maxines",
    "wof:placetype":"venue"
},
  "geometry": {"coordinates":[-118.334333,46.069816],"type":"Point"}
}