{
  "type": "Feature",
  "properties": {
    "addr:full":"15105 NE 152nd Ave Brush Prairie WA 98606",
    "addr:housenumber":"15105",
    "addr:postcode":"98606",
    "addr:street":"Ne 152Nd Ave",
    "iso:country":"US",
    "sg:address":"15105 NE 152nd Ave",
    "sg:city":"Brush Prairie",
    "sg:classifiers":[
        {
            "category":"Building & Trades",
            "subcategory":"Construction",
            "type":"Services"
        }
    ],
    "sg:phone":"+1 360 687 0939",
    "sg:postcode":"98606",
    "sg:province":"WA",
    "sg:tags":[
        "tank",
        "removal"
    ],
    "wof:name":"Advanced Envirotech Inc",
    "wof:placetype":"venue"
},
  "geometry": {"coordinates":[-122.51637700000001,45.735519],"type":"Point"}
}