{
  "type": "Feature",
  "properties": {
    "addr:full":"18224 E Norman Ridge Ln Spokane WA 99217",
    "addr:housenumber":"18224",
    "addr:postcode":"99217",
    "addr:street":"E Norman Ridge Ln",
    "iso:country":"US",
    "sg:address":"18224 E Norman Ridge Ln",
    "sg:city":"Spokane",
    "sg:classifiers":[
        {
            "category":"Professional",
            "type":"Services"
        }
    ],
    "sg:phone":"+1 509 927 0838",
    "sg:postcode":"99217",
    "sg:province":"WA",
    "wof:name":"Robert G Campbell",
    "wof:placetype":"venue"
},
  "geometry": {"coordinates":[-117.15713100000001,47.785322],"type":"Point"}
}