{
  "type": "Feature",
  "properties": {
    "addr:full":"3143 E 29th Ave Spokane WA 99223",
    "addr:housenumber":"3143",
    "addr:postcode":"99223",
    "addr:street":"E 29Th Ave",
    "iso:country":"US",
    "sg:address":"3143 E 29th Ave",
    "sg:city":"Spokane",
    "sg:classifiers":[
        {
            "category":"Health Services",
            "subcategory":"Doctor",
            "type":"Services"
        }
    ],
    "sg:phone":"+1 509 536 5900",
    "sg:postcode":"99223",
    "sg:province":"WA",
    "sg:tags":[
        "dentist"
    ],
    "wof:name":"Eastern Washington Dental Surg",
    "wof:placetype":"venue"
},
  "geometry": {"coordinates":[-117.364294,47.628262],"type":"Point"}
}