{
  "type": "Feature",
  "properties": {
    "iso:country":"US",
    "sg:address":"1112 Long Rd",
    "sg:city":"Centralia",
    "sg:classifiers":[
        {
            "category":"Real Estate",
            "subcategory":"Developer",
            "type":"Services"
        },
        {
            "category":"Real Estate",
            "subcategory":"Real Estate Operator",
            "type":"Services"
        }
    ],
    "sg:phone":"+1 360 736 5135",
    "sg:postcode":"98531",
    "sg:province":"WA",
    "sg:tags":[
        "mobile",
        "home",
        "site"
    ],
    "wof:name":"Long Road Mobile Estates",
    "wof:placetype":"venue"
},
  "geometry": {"coordinates":[-122.970865,46.706361],"type":"Point"}
}