{
  "type": "Feature",
  "properties": {
    "addr:full":"10011 270th St NW Stanwood WA 98292",
    "addr:housenumber":"10011",
    "addr:postcode":"98292",
    "addr:street":"270Th St Nw",
    "iso:country":"US",
    "sg:address":"10011 270th St NW",
    "sg:city":"Stanwood",
    "sg:classifiers":[
        {
            "category":"Social Services",
            "type":"Services"
        }
    ],
    "sg:phone":"+1 360 629 6332",
    "sg:postcode":"98292",
    "sg:province":"WA",
    "wof:name":"Liz Lundgren Rn Ms",
    "wof:placetype":"venue"
},
  "geometry": {"coordinates":[-122.367577,48.241544],"type":"Point"}
}