{
  "type": "Feature",
  "properties": {
    "addr:full":"9542 9th Ave NW Seattle WA 98117",
    "addr:housenumber":"9542",
    "addr:postcode":"98117",
    "addr:street":"9Th Ave Nw",
    "iso:country":"US",
    "sg:address":"9542 9th Ave NW",
    "sg:city":"Seattle",
    "sg:classifiers":[
        {
            "category":"Professional",
            "type":"Services"
        }
    ],
    "sg:phone":"+1 206 789 6344",
    "sg:postcode":"98117",
    "sg:province":"WA",
    "wof:name":"Tom Elliott",
    "wof:placetype":"venue"
},
  "geometry": {"coordinates":[-122.36865299999999,47.699062],"type":"Point"}
}