{
  "type": "Feature",
  "properties": {
    "addr:full":"1612 SW 114th St Seattle WA 98146",
    "addr:housenumber":"1612",
    "addr:postcode":"98146",
    "addr:street":"Sw 114Th St",
    "iso:country":"US",
    "sg:address":"1612 SW 114th St",
    "sg:city":"Seattle",
    "sg:classifiers":[
        {
            "category":"Professional",
            "subcategory":"Business Services",
            "type":"Services"
        }
    ],
    "sg:phone":"+1 206 469 2723",
    "sg:postcode":"98146",
    "sg:province":"WA",
    "wof:name":"Miact Investment Corp",
    "wof:placetype":"venue"
},
  "geometry": {"coordinates":[-122.35537100000001,47.501042],"type":"Point"}
}