{
  "type": "Feature",
  "properties": {
    "addr:full":"317 S 5th Ave Pasco WA 99301",
    "addr:housenumber":"317",
    "addr:postcode":"99301",
    "addr:street":"S 5Th Ave",
    "iso:country":"US",
    "sg:address":"317 S 5th Ave",
    "sg:city":"Pasco",
    "sg:classifiers":[
        {
            "category":"Home & Garden",
            "subcategory":"Building Materials",
            "type":"Retail Goods"
        },
        {
            "category":"Manufacturing",
            "subcategory":"Lumber",
            "type":"Manufacturing & Wholesale Goods"
        },
        {
            "category":"Manufacturing",
            "subcategory":"Building Materials",
            "type":"Manufacturing & Wholesale Goods"
        }
    ],
    "sg:phone":"+1 509 547 3301",
    "sg:postcode":"99301",
    "sg:province":"WA",
    "sg:tags":[
        "roofing",
        "supply",
        "lumber-used",
        "equipment",
        "concrete",
        "shape",
        "lumber-wholesale",
        "block"
    ],
    "sg:website":"http://www.westernmaterials.com",
    "wof:name":"Western Materials, Inc.",
    "wof:placetype":"venue"
},
  "geometry": {"coordinates":[-119.09309,46.227958],"type":"Point"}
}