{
  "type": "Feature",
  "properties": {
    "addr:full":"1608 29th Pl SE Puyallup WA 98374",
    "addr:housenumber":"1608",
    "addr:postcode":"98374",
    "addr:street":"29Th Pl Se",
    "iso:country":"US",
    "sg:address":"1608 29th Pl SE",
    "sg:city":"Puyallup",
    "sg:classifiers":[
        {
            "category":"Building & Trades",
            "subcategory":"Construction",
            "type":"Services"
        }
    ],
    "sg:phone":"+1 253 841 4772",
    "sg:postcode":"98374",
    "sg:province":"WA",
    "sg:tags":[
        "house"
    ],
    "wof:name":"Wolfe Enterprises",
    "wof:placetype":"venue"
},
  "geometry": {"coordinates":[-122.273588,47.163612],"type":"Point"}
}