{
  "type": "Feature",
  "properties": {
    "addr:full":"11245 NE 143rd Pl Kirkland WA 98034",
    "addr:housenumber":"11245",
    "addr:postcode":"98034",
    "addr:street":"Ne 143Rd Pl",
    "iso:country":"US",
    "sg:address":"11245 NE 143rd Pl",
    "sg:city":"Kirkland",
    "sg:classifiers":[
        {
            "category":"Shopping",
            "subcategory":"Gifts & Souvenirs",
            "type":"Retail Goods"
        }
    ],
    "sg:phone":"+1 425 488 2962",
    "sg:postcode":"98034",
    "sg:province":"WA",
    "wof:name":"Izms",
    "wof:placetype":"venue"
},
  "geometry": {"coordinates":[-122.190324,47.730861],"type":"Point"}
}