{
  "type": "Feature",
  "properties": {
    "addr:full":"1530 E Marine View Dr Everett WA 98201",
    "addr:housenumber":"1530",
    "addr:postcode":"98201",
    "addr:street":"E Marine View Dr",
    "iso:country":"US",
    "sg:address":"1530 E Marine View Dr",
    "sg:city":"Everett",
    "sg:classifiers":[
        {
            "category":"Freight",
            "type":"Transportation"
        }
    ],
    "sg:phone":"+1 425 252 4928",
    "sg:postcode":"98201",
    "sg:province":"WA",
    "sg:tags":[
        "commercial",
        "storage"
    ],
    "wof:name":"Storehouse",
    "wof:placetype":"venue"
},
  "geometry": {"coordinates":[-122.187112,47.996985],"type":"Point"}
}