{
  "type": "Feature",
  "properties": {
    "addr:full":"3516 S 47th St Tacoma WA 98409",
    "addr:housenumber":"3516",
    "addr:postcode":"98409",
    "addr:street":"S 47Th St",
    "iso:country":"US",
    "sg:address":"3516 S 47th St",
    "sg:city":"Tacoma",
    "sg:classifiers":[
        {
            "category":"Professional",
            "subcategory":"Management & Consulting",
            "type":"Services"
        }
    ],
    "sg:phone":"+1 253 241 8262",
    "sg:postcode":"98409",
    "sg:province":"WA",
    "wof:name":"Interstate Management",
    "wof:placetype":"venue"
},
  "geometry": {"coordinates":[-122.483226,47.214806],"type":"Point"}
}