{
  "type": "Feature",
  "properties": {
    "iso:country":"US",
    "sg:address":"11820 76th Ave S",
    "sg:city":"Seattle",
    "sg:classifiers":[
        {
            "category":"Restaurant",
            "type":"Food & Drink"
        }
    ],
    "sg:phone":"+1 206 772 5639",
    "sg:postcode":"98178",
    "sg:province":"WA",
    "sg:tags":[
        "eating"
    ],
    "wof:name":"Major Ds Catering",
    "wof:placetype":"venue"
},
  "geometry": {"coordinates":[-122.238214,47.497468],"type":"Point"}
}