{
  "type": "Feature",
  "properties": {
    "addr:full":"123 Lake St S Kirkland WA 98033",
    "addr:housenumber":"123",
    "addr:postcode":"98033",
    "addr:street":"Lake St S",
    "iso:country":"US",
    "sg:address":"123 Lake St S",
    "sg:city":"Kirkland",
    "sg:classifiers":[
        {
            "category":"Personal",
            "type":"Services"
        }
    ],
    "sg:phone":"+1 425 828 3888",
    "sg:postcode":"98033",
    "sg:province":"WA",
    "sg:tags":[
        "shopping"
    ],
    "wof:name":"Romax",
    "wof:placetype":"venue"
},
  "geometry": {"coordinates":[-122.206429,47.675187],"type":"Point"}
}