{
  "type": "Feature",
  "properties": {
    "addr:full":"4547 50th Ave SW Seattle WA 98116",
    "addr:housenumber":"4547",
    "addr:postcode":"98116",
    "addr:street":"50Th Ave Sw",
    "iso:country":"US",
    "sg:address":"4547 50th Ave SW",
    "sg:city":"Seattle",
    "sg:classifiers":[
        {
            "category":"Building & Trades",
            "subcategory":"Landscaping Services",
            "type":"Services"
        }
    ],
    "sg:phone":"+1 206 932 4129",
    "sg:postcode":"98116",
    "sg:province":"WA",
    "sg:tags":[
        "spraying"
    ],
    "wof:name":"C & D Spray Svc",
    "wof:placetype":"venue"
},
  "geometry": {"coordinates":[-122.396314,47.561744],"type":"Point"}
}