{
  "type": "Feature",
  "properties": {
    "addr:full":"25807 NE 142nd Ave Battle Ground WA 98604",
    "addr:housenumber":"25807",
    "addr:postcode":"98604",
    "addr:street":"Ne 142Nd Ave",
    "iso:country":"US",
    "sg:address":"25807 NE 142nd Ave",
    "sg:city":"Battle Ground",
    "sg:classifiers":[
        {
            "category":"Freight",
            "type":"Transportation"
        }
    ],
    "sg:phone":"+1 360 666 2204",
    "sg:postcode":"98604",
    "sg:province":"WA",
    "sg:tags":[
        "arrangement"
    ],
    "wof:name":"Jmsc Inc",
    "wof:placetype":"venue"
},
  "geometry": {"coordinates":[-122.527345,45.809943],"type":"Point"}
}