{
  "type": "Feature",
  "properties": {
    "iso:country":"US",
    "sg:address":"71 Kings Ranch Rd",
    "sg:city":"Forks",
    "sg:classifiers":[
        {
            "category":"Retail",
            "subcategory":"Animal Services",
            "type":"Services"
        }
    ],
    "sg:phone":"+1 360 374 6345",
    "sg:postcode":"98331",
    "sg:province":"WA",
    "sg:tags":[
        "farm",
        "chicken"
    ],
    "wof:name":"Kings Ranch",
    "wof:placetype":"venue"
},
  "geometry": {"coordinates":[-124.361312,47.950847],"type":"Point"}
}