{
  "type": "Feature",
  "properties": {
    "iso:country":"US",
    "sg:address":"1300 Dexter Ave N",
    "sg:city":"Seattle",
    "sg:classifiers":[
        {
            "category":"Insurance",
            "subcategory":"Insurance Agent",
            "type":"Services"
        }
    ],
    "sg:phone":"+1 206 281 1266",
    "sg:postcode":"98109",
    "sg:province":"WA",
    "wof:name":"Deans & Homer Ins Managing",
    "wof:placetype":"venue"
},
  "geometry": {"coordinates":[-122.342219,47.630775],"type":"Point"}
}