{
  "type": "Feature",
  "properties": {
    "addr:full":"2805 N Alder St Tacoma WA 98407",
    "addr:housenumber":"2805",
    "addr:postcode":"98407",
    "addr:street":"N Alder St",
    "iso:country":"US",
    "sg:address":"2805 N Alder St",
    "sg:city":"Tacoma",
    "sg:classifiers":[
        {
            "category":"Personal",
            "type":"Services"
        }
    ],
    "sg:phone":"+1 253 752 2035",
    "sg:postcode":"98407",
    "sg:province":"WA",
    "wof:name":"Louise B Anderson Lmp",
    "wof:placetype":"venue"
},
  "geometry": {"coordinates":[-122.477638,47.273744],"type":"Point"}
}