{
  "type": "Feature",
  "properties": {
    "addr:full":"9826 NE 122nd St Kirkland WA 98034",
    "addr:housenumber":"9826",
    "addr:postcode":"98034",
    "addr:street":"Ne 122Nd St",
    "iso:country":"US",
    "sg:address":"9826 NE 122nd St",
    "sg:city":"Kirkland",
    "sg:classifiers":[
        {
            "category":"Professional",
            "subcategory":"Business Services",
            "type":"Services"
        }
    ],
    "sg:phone":"+1 425 825 9597",
    "sg:postcode":"98034",
    "sg:province":"WA",
    "wof:name":"Swift Enterprises",
    "wof:placetype":"venue"
},
  "geometry": {"coordinates":[-122.20918500000001,47.709843],"type":"Point"}
}