{
  "type": "Feature",
  "properties": {
    "addr:full":"3131 Western Ave Seattle WA 98121",
    "addr:housenumber":"3131",
    "addr:postcode":"98121",
    "addr:street":"Western Ave",
    "iso:country":"US",
    "sg:address":"3131 Western Ave",
    "sg:city":"Seattle",
    "sg:classifiers":[
        {
            "category":"Professional",
            "subcategory":"Engineering",
            "type":"Services"
        },
        {
            "category":"Military Area",
            "subcategory":"Coast Guard Base",
            "type":"Public Place"
        }
    ],
    "sg:phone":"+1 206 930 0342",
    "sg:postcode":"98121",
    "sg:province":"WA",
    "sg:tags":[
        "civil",
        "water",
        "storm",
        "drainage",
        "engineer"
    ],
    "wof:name":"Civil Engineering Solutions",
    "wof:placetype":"venue"
},
  "geometry": {"coordinates":[-122.356819,47.61829],"type":"Point"}
}