{
  "type": "Feature",
  "properties": {
    "iso:country":"US",
    "sg:address":"1515 Black Lake Blvd SW",
    "sg:city":"Olympia",
    "sg:classifiers":[
        {
            "category":"Personal",
            "subcategory":"Beauty Salon",
            "type":"Services"
        }
    ],
    "sg:phone":"+1 360 753 8718",
    "sg:postcode":"98502",
    "sg:province":"WA",
    "sg:tags":[
        "shop"
    ],
    "wof:name":"Unique Nails",
    "wof:placetype":"venue"
},
  "geometry": {"coordinates":[-122.93986700000001,47.03331],"type":"Point"}
}