{
  "type": "Feature",
  "properties": {
    "addr:full":"1119 S 62nd St Tacoma WA 98408",
    "addr:housenumber":"1119",
    "addr:postcode":"98408",
    "addr:street":"S 62Nd St",
    "iso:country":"US",
    "sg:address":"1119 S 62nd St",
    "sg:city":"Tacoma",
    "sg:classifiers":[
        {
            "category":"Professional",
            "subcategory":"Computer Services",
            "type":"Services"
        }
    ],
    "sg:phone":"+1 253 472 3420",
    "sg:postcode":"98408",
    "sg:province":"WA",
    "sg:tags":[
        "consulting",
        "management",
        "related"
    ],
    "wof:name":"Magnetic Connections",
    "wof:placetype":"venue"
},
  "geometry": {"coordinates":[-122.45080299999999,47.201107],"type":"Point"}
}