{
  "type": "Feature",
  "properties": {
    "iso:country":"US",
    "sg:address":"9009 State Rte 92",
    "sg:city":"Granite Falls",
    "sg:classifiers":[
        {
            "category":"Shopping",
            "subcategory":"Gifts & Souvenirs",
            "type":"Retail Goods"
        }
    ],
    "sg:phone":"+1 360 691 1108",
    "sg:postcode":"98252",
    "sg:province":"WA",
    "wof:name":"Granite Falls Flowers & Gifts",
    "wof:placetype":"venue"
},
  "geometry": {"coordinates":[-122.002202,48.07836],"type":"Point"}
}