{
  "type": "Feature",
  "properties": {
    "iso:country":"US",
    "sg:address":"1946 Pleasant St",
    "sg:city":"Walla Walla",
    "sg:classifiers":[
        {
            "category":"Shopping",
            "subcategory":"Gifts & Souvenirs",
            "type":"Retail Goods"
        }
    ],
    "sg:phone":"+1 509 525 7315",
    "sg:postcode":"99362",
    "sg:province":"WA",
    "wof:name":"J and P Gift Baskets",
    "wof:placetype":"venue"
},
  "geometry": {"coordinates":[-118.295292,46.062294],"type":"Point"}
}