{
  "type": "Feature",
  "properties": {
    "addr:full":"3505 SE 192nd Ave Vancouver WA 98683",
    "addr:housenumber":"3505",
    "addr:postcode":"98683",
    "addr:street":"Se 192Nd Ave",
    "iso:country":"US",
    "sg:address":"3505 SE 192nd Ave",
    "sg:city":"Vancouver",
    "sg:classifiers":[
        {
            "category":"Food & Beverages",
            "subcategory":"Groceries & Convenience Stores",
            "type":"Retail Goods"
        }
    ],
    "sg:phone":"+1 360 253 3016",
    "sg:postcode":"98683",
    "sg:province":"WA",
    "wof:name":"Q F C Quality Food Centers Inc-Vancouver",
    "wof:placetype":"venue"
},
  "geometry": {"coordinates":[-122.477997,45.595901],"type":"Point"}
}