{
  "type": "Feature",
  "properties": {
    "addr:full":"202 W Prospect St Seattle WA 98119",
    "addr:housenumber":"202",
    "addr:postcode":"98119",
    "addr:street":"W Prospect St",
    "iso:country":"US",
    "sg:address":"202 W Prospect St",
    "sg:city":"Seattle",
    "sg:classifiers":[
        {
            "category":"Health Services",
            "subcategory":"Doctor",
            "type":"Services"
        }
    ],
    "sg:phone":"+1 206 285 1170",
    "sg:postcode":"98119",
    "sg:province":"WA",
    "sg:tags":[
        "surgeon",
        "oral"
    ],
    "wof:name":"Jones Perry J III DDS",
    "wof:placetype":"venue"
},
  "geometry": {"coordinates":[-122.35900100000001,47.628601],"type":"Point"}
}