{
  "type": "Feature",
  "properties": {
    "addr:full":"9125 Bridgeport Way SW Lakewood WA 98499",
    "addr:housenumber":"9125",
    "addr:postcode":"98499",
    "addr:street":"Bridgeport Way Sw",
    "iso:country":"US",
    "sg:address":"9125 Bridgeport Way SW",
    "sg:city":"Lakewood",
    "sg:classifiers":[
        {
            "category":"Health Services",
            "subcategory":"Doctor",
            "type":"Services"
        }
    ],
    "sg:phone":"+1 253 581 6140",
    "sg:postcode":"98499",
    "sg:province":"WA",
    "sg:tags":[
        "surgeon",
        "oral"
    ],
    "wof:name":"Eylander Corbin C DDS",
    "wof:placetype":"venue"
},
  "geometry": {"coordinates":[-122.51799800000001,47.174198],"type":"Point"}
}