{
  "type": "Feature",
  "properties": {
    "addr:full":"37505 28th Ave S Federal Way WA 98003",
    "addr:housenumber":"37505",
    "addr:postcode":"98003",
    "addr:street":"28Th Ave S Federal Way",
    "iso:country":"US",
    "sg:address":"37505 28th Ave S",
    "sg:city":"Federal Way",
    "sg:classifiers":[
        {
            "category":"Organizations",
            "subcategory":"Religious Organization",
            "type":"Services"
        }
    ],
    "sg:phone":"+1 253 835 0830",
    "sg:postcode":"98003",
    "sg:province":"WA",
    "sg:tags":[
        "church"
    ],
    "wof:name":"Federal Way Central Presbyteri",
    "wof:placetype":"venue"
},
  "geometry": {"coordinates":[-122.29801999999999,47.263626],"type":"Point"}
}