{
  "type": "Feature",
  "properties": {
    "addr:full":"900 160th Ave NE Bellevue WA 98008",
    "addr:housenumber":"900",
    "addr:postcode":"98008",
    "addr:street":"160Th Ave Ne",
    "iso:country":"US",
    "sg:address":"900 160th Ave NE",
    "sg:city":"Bellevue",
    "sg:classifiers":[
        {
            "category":"Personal",
            "subcategory":"Beauty Salon",
            "type":"Services"
        }
    ],
    "sg:phone":"+1 425 643 1882",
    "sg:postcode":"98008",
    "sg:province":"WA",
    "sg:tags":[
        "shop"
    ],
    "wof:name":"Vals Mane Attraction",
    "wof:placetype":"venue"
},
  "geometry": {"coordinates":[-122.12815000000001,47.618826],"type":"Point"}
}