{
  "type": "Feature",
  "properties": {
    "addr:full":"2909 W 19th Ave Spokane WA 99224",
    "addr:housenumber":"2909",
    "addr:postcode":"99224",
    "addr:street":"W 19Th Ave",
    "iso:country":"US",
    "sg:address":"2909 W 19th Ave",
    "sg:city":"Spokane",
    "sg:classifiers":[
        {
            "category":"Professional",
            "subcategory":"Business Services",
            "type":"Services"
        }
    ],
    "sg:phone":"+1 509 624 6345",
    "sg:postcode":"99224",
    "sg:province":"WA",
    "wof:name":"Mc Arthur Interests",
    "wof:placetype":"venue"
},
  "geometry": {"coordinates":[-117.45519299999999,47.63739],"type":"Point"}
}