{
  "type": "Feature",
  "properties": {
    "addr:full":"5500 140th Ave NE Bellevue WA 98005",
    "addr:housenumber":"5500",
    "addr:postcode":"98005",
    "addr:street":"140Th Ave Ne",
    "iso:country":"US",
    "sg:address":"5500 140th Ave NE",
    "sg:city":"Bellevue",
    "sg:classifiers":[
        {
            "category":"Restaurant",
            "type":"Food & Drink"
        }
    ],
    "sg:phone":"+1 425 452 7222",
    "sg:postcode":"98005",
    "sg:province":"WA",
    "sg:tags":[
        "traditional",
        "american"
    ],
    "sg:website":"www.bellevuepgc.com",
    "wof:name":"Bellevue Grill",
    "wof:placetype":"venue"
},
  "geometry": {"coordinates":[-122.15314100000001,47.657164],"type":"Point"}
}