{
  "type": "Feature",
  "properties": {
    "addr:full":"2500 Beacon Ave S Seattle WA 98144",
    "addr:housenumber":"2500",
    "addr:postcode":"98144",
    "addr:street":"Beacon Ave S",
    "iso:country":"US",
    "sg:address":"2500 Beacon Ave S",
    "sg:city":"Seattle",
    "sg:classifiers":[
        {
            "category":"Professional",
            "subcategory":"Business Services",
            "type":"Services"
        }
    ],
    "sg:phone":"+1 206 325 3324",
    "sg:postcode":"98144",
    "sg:province":"WA",
    "sg:tags":[
        "telemarketing"
    ],
    "wof:name":"Jazz Promotions",
    "wof:placetype":"venue"
},
  "geometry": {"coordinates":[-122.31341399999999,47.580591],"type":"Point"}
}