{
  "type": "Feature",
  "properties": {
    "addr:full":"19002 SE 15th St Vancouver WA 98683",
    "addr:postcode":"19002;98683",
    "addr:street":"Se 15Th St",
    "iso:country":"US",
    "sg:address":"19002 SE 15th St",
    "sg:city":"Vancouver",
    "sg:classifiers":[
        {
            "category":"Manufacturing",
            "subcategory":"Tools & Machinery",
            "type":"Manufacturing & Wholesale Goods"
        }
    ],
    "sg:phone":"+1 360 254 4346",
    "sg:postcode":"98683",
    "sg:province":"WA",
    "sg:tags":[
        "industry",
        "mfg"
    ],
    "wof:name":"Insanity Still Framing System",
    "wof:placetype":"venue"
},
  "geometry": {"coordinates":[-122.476626,45.610113],"type":"Point"}
}