{
  "type": "Feature",
  "properties": {
    "addr:full":"14056 Rd 12.5 SW Royal City WA 99357",
    "addr:postcode":"14056;99357",
    "addr:street":"Rd;Sw",
    "iso:country":"US",
    "sg:address":"14056 Rd 12.5 SW",
    "sg:city":"Royal City",
    "sg:classifiers":[
        {
            "category":"Farming",
            "subcategory":"Farm",
            "type":"Manufacturing & Wholesale Goods"
        }
    ],
    "sg:phone":"+1 509 346 2900",
    "sg:postcode":"99357",
    "sg:province":"WA",
    "wof:name":"Randy Allred Shop",
    "wof:placetype":"venue"
},
  "geometry": {"coordinates":[-119.802775,46.909003],"type":"Point"}
}