{
  "type": "Feature",
  "properties": {
    "addr:full":"1103 S 42nd Ave Yakima WA 98908",
    "addr:housenumber":"1103",
    "addr:postcode":"98908",
    "addr:street":"S 42Nd Ave",
    "iso:country":"US",
    "sg:address":"1103 S 42nd Ave",
    "sg:city":"Yakima",
    "sg:classifiers":[
        {
            "category":"Banks & Credit Unions",
            "subcategory":"Investment Brokerage",
            "type":"Services"
        }
    ],
    "sg:phone":"+1 509 930 9089",
    "sg:postcode":"98908",
    "sg:province":"WA",
    "sg:tags":[
        "advisory",
        "financial"
    ],
    "wof:name":"Shelgren Financial Group Inc",
    "wof:placetype":"venue"
},
  "geometry": {"coordinates":[-120.56480500000001,46.584295],"type":"Point"}
}