{
  "type": "Feature",
  "properties": {
    "addr:full":"901 Melody Ln Enumclaw WA 98022",
    "addr:housenumber":"901",
    "addr:postcode":"98022",
    "addr:street":"Melody Ln",
    "iso:country":"US",
    "sg:address":"901 Melody Ln",
    "sg:city":"Enumclaw",
    "sg:classifiers":[
        {
            "category":"Education",
            "subcategory":"Special Training",
            "type":"Public Place"
        }
    ],
    "sg:phone":"+1 360 825 7802",
    "sg:postcode":"98022",
    "sg:province":"WA",
    "sg:tags":[
        "educational"
    ],
    "wof:name":"D H Piano Instruction",
    "wof:placetype":"venue"
},
  "geometry": {"coordinates":[-122.00218599999999,47.198048],"type":"Point"}
}