{
  "type": "Feature",
  "properties": {
    "addr:full":"405 University St Seattle WA 98101",
    "addr:housenumber":"405",
    "addr:postcode":"98101",
    "addr:street":"University St",
    "iso:country":"US",
    "sg:address":"405 University St",
    "sg:city":"Seattle",
    "sg:phone":"+1 206 623 8200",
    "sg:postcode":"98101",
    "sg:province":"WA",
    "wof:name":"Luly Yang for Men",
    "wof:placetype":"venue"
},
  "geometry": {"coordinates":[-122.334833,47.608218],"type":"Point"}
}