{
  "type": "Feature",
  "properties": {
    "addr:full":"25818 104th Ave SE Kent WA 98030",
    "addr:housenumber":"25818",
    "addr:postcode":"98030",
    "addr:street":"104Th Ave Se",
    "iso:country":"US",
    "sg:address":"25818 104th Ave SE",
    "sg:city":"Kent",
    "sg:classifiers":[
        {
            "category":"Retail",
            "subcategory":"Laundry & Dry Cleaning",
            "type":"Services"
        }
    ],
    "sg:phone":"+1 253 856 1677",
    "sg:postcode":"98030",
    "sg:province":"WA",
    "sg:tags":[
        "drycleaning",
        "plant"
    ],
    "wof:name":"Regency Cleaners Inc",
    "wof:placetype":"venue"
},
  "geometry": {"coordinates":[-122.202298,47.370881],"type":"Point"}
}