{
  "type": "Feature",
  "properties": {
    "addr:full":"217215 E Finley Rd Kennewick WA 99337",
    "addr:housenumber":"217215",
    "addr:postcode":"99337",
    "addr:street":"E Finley Rd",
    "iso:country":"US",
    "sg:address":"217215 E Finley Rd",
    "sg:city":"Kennewick",
    "sg:classifiers":[
        {
            "category":"Building & Trades",
            "subcategory":"Construction",
            "type":"Services"
        }
    ],
    "sg:phone":"+1 509 531 8269",
    "sg:postcode":"99337",
    "sg:province":"WA",
    "sg:tags":[
        "house"
    ],
    "wof:name":"Windy Acres Construction",
    "wof:placetype":"venue"
},
  "geometry": {"coordinates":[-119.04419799999999,46.187288],"type":"Point"}
}