{
  "type": "Feature",
  "properties": {
    "iso:country":"US",
    "sg:address":"2238 James St",
    "sg:city":"Bellingham",
    "sg:classifiers":[
        {
            "category":"Retail",
            "subcategory":"Repair Shop",
            "type":"Services"
        }
    ],
    "sg:phone":"+1 360 733 7343",
    "sg:postcode":"98225",
    "sg:province":"WA",
    "sg:tags":[
        "tool",
        "parts"
    ],
    "wof:name":"Pro Tool",
    "wof:placetype":"venue"
},
  "geometry": {"coordinates":[-122.464844,48.759883],"type":"Point"}
}