{
  "type": "Feature",
  "properties": {
    "addr:full":"17220 Redmond Way Redmond WA 98052",
    "addr:housenumber":"17220",
    "addr:postcode":"98052",
    "addr:street":"Redmond Way",
    "iso:country":"US",
    "sg:address":"17220 Redmond Way",
    "sg:city":"Redmond",
    "sg:classifiers":[
        {
            "category":"Shopping",
            "subcategory":"Pharmacy",
            "type":"Retail Goods"
        }
    ],
    "sg:phone":"+1 425 883 1516",
    "sg:postcode":"98052",
    "sg:province":"WA",
    "sg:tags":[
        "aid",
        "first",
        "store",
        "drug",
        "supply"
    ],
    "sg:website":"http://www.riteaid.com",
    "wof:name":"Rite Aid",
    "wof:placetype":"venue"
},
  "geometry": {"coordinates":[-122.11103199999999,47.67081],"type":"Point"}
}