{
  "type": "Feature",
  "properties": {
    "addr:full":"550 Sandalwood Pl Moses Lake WA 98837",
    "addr:housenumber":"550",
    "addr:postcode":"98837",
    "addr:street":"Sandalwood Pl",
    "iso:country":"US",
    "sg:address":"550 Sandalwood Pl",
    "sg:city":"Moses Lake",
    "sg:classifiers":[
        {
            "category":"Professional",
            "subcategory":"Business Services",
            "type":"Services"
        }
    ],
    "sg:phone":"+1 509 765 8415",
    "sg:postcode":"98837",
    "sg:province":"WA",
    "wof:name":"Crawford Interiors",
    "wof:placetype":"venue"
},
  "geometry": {"coordinates":[-119.331844,47.099888],"type":"Point"}
}