{
  "type": "Feature",
  "properties": {
    "addr:full":"1847 SW Shoreview Ln Seattle WA 98146",
    "addr:housenumber":"1847",
    "addr:postcode":"98146",
    "addr:street":"Sw Shoreview Ln",
    "iso:country":"US",
    "sg:address":"1847 SW Shoreview Ln",
    "sg:city":"Seattle",
    "sg:classifiers":[
        {
            "category":"Health Services",
            "subcategory":"Doctor",
            "type":"Services"
        }
    ],
    "sg:phone":"+1 206 242 0201",
    "sg:postcode":"98146",
    "sg:province":"WA",
    "sg:tags":[
        "medical"
    ],
    "wof:name":"MD Barbara PS Jessen",
    "wof:placetype":"venue"
},
  "geometry": {"coordinates":[-122.36041299999999,47.488404],"type":"Point"}
}