{
  "type": "Feature",
  "properties": {
    "addr:full":"6405 218th St SW Mountlake Ter WA 98043",
    "addr:housenumber":"6405",
    "addr:postcode":"98043",
    "addr:street":"218Th St Sw Mountlake Ter",
    "iso:country":"US",
    "sg:address":"6405 218th St SW",
    "sg:city":"Mountlake Ter",
    "sg:classifiers":[
        {
            "category":"Bus Charters",
            "type":"Transportation"
        }
    ],
    "sg:phone":"+1 425 697 2580",
    "sg:postcode":"98043",
    "sg:province":"WA",
    "sg:tags":[
        "rental"
    ],
    "wof:name":"Laidlaw Transit Inc",
    "wof:placetype":"venue"
},
  "geometry": {"coordinates":[-122.321912,47.801378],"type":"Point"}
}