{
  "type": "Feature",
  "properties": {
    "addr:full":"19306 Bothell Way NE Bothell WA 98011",
    "addr:housenumber":"19306",
    "addr:postcode":"98011",
    "addr:street":"Bothell Way Ne",
    "iso:country":"US",
    "sg:address":"19306 Bothell Way NE",
    "sg:city":"Bothell",
    "sg:classifiers":[
        {
            "category":"Retail",
            "subcategory":"Repair Shop",
            "type":"Services"
        }
    ],
    "sg:phone":"+1 425 481 8722",
    "sg:postcode":"98011",
    "sg:province":"WA",
    "wof:name":"Burkys Equipment Repair",
    "wof:placetype":"venue"
},
  "geometry": {"coordinates":[-122.21037099999999,47.76733],"type":"Point"}
}