{
  "type": "Feature",
  "properties": {
    "addr:full":"The Shops at The Bravern 700 110th Avenue NE Bellevue WA 98004",
    "addr:housenumber":"700",
    "addr:postcode":"98004",
    "addr:street":"110Th Avenue Ne",
    "iso:country":"US",
    "sg:address":"The Shops at The Bravern 700 110th Avenue NE",
    "sg:city":"Bellevue",
    "sg:classifiers":[
        {
            "category":"Personal",
            "subcategory":"Massage",
            "type":"Services"
        },
        {
            "category":"Personal",
            "subcategory":"Day Spa",
            "type":"Services"
        }
    ],
    "sg:phone":"+1 425 455 3700",
    "sg:postcode":"98004",
    "sg:province":"WA",
    "sg:website":"www.reddoorspas.com",
    "wof:name":"Elizabeth Arden Red \u00a0Door Spas",
    "wof:placetype":"venue"
},
  "geometry": {"coordinates":[-122.19363199999999,47.616444],"type":"Point"}
}