{
  "type": "Feature",
  "properties": {
    "addr:full":"809 Lake City Way NE Seattle WA 98125",
    "addr:housenumber":"809",
    "addr:postcode":"98125",
    "addr:street":"Lake City Way Ne",
    "iso:country":"US",
    "sg:address":"809 Lake City Way NE",
    "sg:city":"Seattle",
    "sg:phone":"+1 206 632 6351",
    "sg:postcode":"98125",
    "sg:province":"WA",
    "wof:name":"Rooster's Espresso Inc",
    "wof:placetype":"venue"
},
  "geometry": {"coordinates":[-122.295151,47.719549],"type":"Point"}
}