{
  "type": "Feature",
  "properties": {
    "addr:full":"1265 S Main St Seattle WA 98144",
    "addr:housenumber":"1265",
    "addr:postcode":"98144",
    "addr:street":"S Main St",
    "iso:country":"US",
    "sg:address":"1265 S Main St",
    "sg:city":"Seattle",
    "sg:classifiers":[
        {
            "category":"Organizations",
            "subcategory":"Non-profit Organization",
            "type":"Services"
        }
    ],
    "sg:phone":"+1 206 568 5400",
    "sg:postcode":"98144",
    "sg:province":"WA",
    "sg:tags":[
        "service/non-profit",
        "community"
    ],
    "wof:name":"Northwest Federation of Commu Nity Organizations",
    "wof:placetype":"venue"
},
  "geometry": {"coordinates":[-122.31500200000001,47.599998],"type":"Point"}
}