{
  "type": "Feature",
  "properties": {
    "addr:full":"Elainegordonamerican Redmond WA 98053",
    "addr:postcode":"98053",
    "addr:street":"Elainegordonamerican",
    "iso:country":"US",
    "sg:address":"Elainegordonamerican",
    "sg:city":"Redmond",
    "sg:classifiers":[
        {
            "category":"Building & Trades",
            "subcategory":"Cleaning & Sanitation",
            "type":"Services"
        }
    ],
    "sg:phone":"+1 425 868 5091",
    "sg:postcode":"98053",
    "sg:province":"WA",
    "sg:tags":[
        "home"
    ],
    "wof:name":"American Maid's-Elaine Gordon'evans'inc",
    "wof:placetype":"venue"
},
  "geometry": {"coordinates":[-122.00900300000001,47.6628],"type":"Point"}
}