{
  "type": "Feature",
  "properties": {
    "addr:full":"1115 S 5th Ave Yakima WA 98902",
    "addr:housenumber":"1115",
    "addr:postcode":"98902",
    "addr:street":"S 5Th Ave",
    "iso:country":"US",
    "sg:address":"1115 S 5th Ave",
    "sg:city":"Yakima",
    "sg:classifiers":[
        {
            "category":"Organizations",
            "subcategory":"Religious Organization",
            "type":"Services"
        }
    ],
    "sg:phone":"+1 509 452 0192",
    "sg:postcode":"98902",
    "sg:province":"WA",
    "wof:name":"Christian Broadway Church",
    "wof:placetype":"venue"
},
  "geometry": {"coordinates":[-120.51204,46.583658],"type":"Point"}
}