{
  "type": "Feature",
  "properties": {
    "addr:full":"14377 Fryelands Blvd Monroe WA 98272",
    "addr:housenumber":"14377",
    "addr:postcode":"98272",
    "addr:street":"Fryelands Blvd",
    "iso:country":"US",
    "sg:address":"14377 Fryelands Blvd",
    "sg:city":"Monroe",
    "sg:classifiers":[
        {
            "category":"Organizations",
            "subcategory":"Religious Organization",
            "type":"Services"
        }
    ],
    "sg:phone":"+1 360 794 4600",
    "sg:postcode":"98272",
    "sg:province":"WA",
    "wof:name":"Cascade Community Church",
    "wof:placetype":"venue"
},
  "geometry": {"coordinates":[-122.009235,47.87046],"type":"Point"}
}