{
  "type": "Feature",
  "properties": {
    "addr:full":"3670 Chico Way NW Bremerton WA 98312",
    "addr:housenumber":"3670",
    "addr:postcode":"98312",
    "addr:street":"Chico Way Nw",
    "iso:country":"US",
    "sg:address":"3670 Chico Way NW",
    "sg:city":"Bremerton",
    "sg:classifiers":[
        {
            "category":"Organizations",
            "subcategory":"Religious Organization",
            "type":"Services"
        }
    ],
    "sg:phone":"+1 360 373 1408",
    "sg:postcode":"98312",
    "sg:province":"WA",
    "wof:name":"Chico Alliance Church",
    "wof:placetype":"venue"
},
  "geometry": {"coordinates":[-122.70939300000001,47.601931],"type":"Point"}
}