{
  "type": "Feature",
  "properties": {
    "addr:full":"8121 W Quinault Ave Kennewick WA 99336",
    "addr:housenumber":"8121",
    "addr:postcode":"99336",
    "addr:street":"W Quinault Ave",
    "iso:country":"US",
    "sg:address":"8121 W Quinault Ave",
    "sg:city":"Kennewick",
    "sg:classifiers":[
        {
            "category":"Banks & Credit Unions",
            "subcategory":"Bank",
            "type":"Services"
        }
    ],
    "sg:phone":"+1 509 735 5364",
    "sg:postcode":"99336",
    "sg:province":"WA",
    "sg:tags":[
        "loan",
        "real estate"
    ],
    "wof:name":"Homestone Mortgage",
    "wof:placetype":"venue"
},
  "geometry": {"coordinates":[-119.22851300000001,46.223068],"type":"Point"}
}