{
  "type": "Feature",
  "properties": {
    "addr:full":"440 Saint St Richland WA 99354",
    "addr:housenumber":"440",
    "addr:postcode":"99354",
    "addr:street":"Saint St",
    "iso:country":"US",
    "sg:address":"440 Saint St",
    "sg:city":"Richland",
    "sg:classifiers":[
        {
            "category":"Farming",
            "subcategory":"Livestock Farm",
            "type":"Manufacturing & Wholesale Goods"
        }
    ],
    "sg:phone":"+1 509 946 4110",
    "sg:postcode":"99354",
    "sg:province":"WA",
    "sg:tags":[
        "equine"
    ],
    "wof:name":"Sand Dunes Ranch",
    "wof:placetype":"venue"
},
  "geometry": {"coordinates":[-119.27279299999999,46.311261],"type":"Point"}
}