{
  "type": "Feature",
  "properties": {
    "addr:full":"13033 Sunrise Dr Mount Vernon WA 98273",
    "addr:housenumber":"13033",
    "addr:postcode":"98273",
    "addr:street":"Sunrise Dr",
    "iso:country":"US",
    "sg:address":"13033 Sunrise Dr",
    "sg:city":"Mount Vernon",
    "sg:classifiers":[
        {
            "category":"Mining & Drilling",
            "type":"Manufacturing & Wholesale Goods"
        }
    ],
    "sg:phone":"+1 360 848 8929",
    "sg:postcode":"98273",
    "sg:province":"WA",
    "sg:tags":[
        "construction",
        "general"
    ],
    "wof:name":"Total Construction Services",
    "wof:placetype":"venue"
},
  "geometry": {"coordinates":[-122.284654,48.457053],"type":"Point"}
}