{
  "type": "Feature",
  "properties": {
    "addr:full":"8102 Evergreen Way Everett WA 98203",
    "addr:housenumber":"8102",
    "addr:postcode":"98203",
    "addr:street":"Evergreen Way",
    "iso:country":"US",
    "sg:address":"8102 Evergreen Way",
    "sg:city":"Everett",
    "sg:classifiers":[
        {
            "category":"Shopping",
            "subcategory":"Department Store",
            "type":"Retail Goods"
        }
    ],
    "sg:phone":"+1 425 353 8103",
    "sg:postcode":"98203",
    "sg:province":"WA",
    "wof:name":"Kmart",
    "wof:placetype":"venue"
},
  "geometry": {"coordinates":[-122.226572,47.923693],"type":"Point"}
}