{
  "type": "Feature",
  "properties": {
    "iso:country":"US",
    "sg:address":"500 Union St",
    "sg:city":"Seattle",
    "sg:classifiers":[
        {
            "category":"Food & Beverages",
            "subcategory":"Groceries & Convenience Stores",
            "type":"Retail Goods"
        }
    ],
    "sg:phone":"+1 206 622 5880",
    "sg:postcode":"98101",
    "sg:province":"WA",
    "wof:name":"Logan Deli & Sundries",
    "wof:placetype":"venue"
},
  "geometry": {"coordinates":[-122.333558,47.610147],"type":"Point"}
}