{
  "type": "Feature",
  "properties": {
    "iso:country":"US",
    "sg:address":"521 Park Ave N",
    "sg:city":"Renton",
    "sg:classifiers":[
        {
            "category":"Professional",
            "subcategory":"Management & Consulting",
            "type":"Services"
        }
    ],
    "sg:phone":"+1 425 255 3751",
    "sg:postcode":"98057",
    "sg:province":"WA",
    "sg:tags":[
        "retail",
        "direct",
        "sales"
    ],
    "wof:name":"Park Ave Distributing",
    "wof:placetype":"venue"
},
  "geometry": {"coordinates":[-122.202219,47.492087],"type":"Point"}
}