{
  "type": "Feature",
  "properties": {
    "addr:full":"4262 Whitman Ave N Seattle WA 98103",
    "addr:housenumber":"4262",
    "addr:postcode":"98103",
    "addr:street":"Whitman Ave N",
    "iso:country":"US",
    "sg:address":"4262 Whitman Ave N",
    "sg:city":"Seattle",
    "sg:classifiers":[
        {
            "category":"Health Services",
            "subcategory":"Health Practitioner",
            "type":"Services"
        }
    ],
    "sg:phone":"+1 206 938 9505",
    "sg:postcode":"98103",
    "sg:province":"WA",
    "sg:tags":[
        "physician"
    ],
    "wof:name":"Alternative Medical Arts Assoc",
    "wof:placetype":"venue"
},
  "geometry": {"coordinates":[-122.345563,47.65935],"type":"Point"}
}