{
  "type": "Feature",
  "properties": {
    "addr:full":"419 Q Ave Anacortes WA 98221",
    "addr:housenumber":"419",
    "addr:postcode":"98221",
    "addr:street":"Q Ave",
    "iso:country":"US",
    "sg:address":"419 Q Ave",
    "sg:city":"Anacortes",
    "sg:classifiers":[
        {
            "category":"Shopping",
            "type":"Retail Goods"
        }
    ],
    "sg:phone":"+1 360 293 7754",
    "sg:postcode":"98221",
    "sg:province":"WA",
    "sg:tags":[
        "coin",
        "dealer",
        "supply"
    ],
    "wof:name":"Allen Construction Co",
    "wof:placetype":"venue"
},
  "geometry": {"coordinates":[-122.610851,48.518935],"type":"Point"}
}