{
  "type": "Feature",
  "properties": {
    "addr:full":"9703 Sand Point Way NE Seattle WA 98115",
    "addr:housenumber":"9703",
    "addr:postcode":"98115",
    "addr:street":"Sand Point Way Ne",
    "iso:country":"US",
    "sg:address":"9703 Sand Point Way NE",
    "sg:city":"Seattle",
    "sg:classifiers":[
        {
            "category":"Banks & Credit Unions",
            "subcategory":"Investment Brokerage",
            "type":"Services"
        }
    ],
    "sg:phone":"+1 206 517 4011",
    "sg:postcode":"98115",
    "sg:province":"WA",
    "sg:tags":[
        "investing"
    ],
    "wof:name":"Ivester & Associates",
    "wof:placetype":"venue"
},
  "geometry": {"coordinates":[-122.27786500000001,47.700365],"type":"Point"}
}