{
  "type": "Feature",
  "properties": {
    "addr:full":"605 D St SW Ephrata WA 98823",
    "addr:housenumber":"605",
    "addr:postcode":"98823",
    "addr:street":"D St Sw",
    "iso:country":"US",
    "sg:address":"605 D St SW",
    "sg:city":"Ephrata",
    "sg:classifiers":[
        {
            "category":"Social Services",
            "subcategory":"Child Care",
            "type":"Services"
        }
    ],
    "sg:phone":"+1 509 754 2466",
    "sg:postcode":"98823",
    "sg:province":"WA",
    "sg:tags":[
        "day"
    ],
    "wof:name":"Suzies Zoo Daycare",
    "wof:placetype":"venue"
},
  "geometry": {"coordinates":[-119.558806,47.315892],"type":"Point"}
}