{
  "type": "Feature",
  "properties": {
    "iso:country":"US",
    "sg:address":"9323 Morris Rd",
    "sg:city":"Blaine",
    "sg:classifiers":[
        {
            "category":"Farming",
            "subcategory":"Farm & Veterinary Services",
            "type":"Manufacturing & Wholesale Goods"
        }
    ],
    "sg:phone":"+1 360 332 5122",
    "sg:postcode":"98230",
    "sg:province":"WA",
    "sg:tags":[
        "livestock"
    ],
    "wof:name":"Atlaska Inc",
    "wof:placetype":"venue"
},
  "geometry": {"coordinates":[-122.64940900000001,48.979536],"type":"Point"}
}