{
  "type": "Feature",
  "properties": {
    "addr:full":"9 Boyer Ave Walla Walla WA 99362",
    "addr:housenumber":"9",
    "addr:postcode":"99362",
    "addr:street":"Boyer Ave",
    "iso:country":"US",
    "sg:address":"9 Boyer Ave",
    "sg:city":"Walla Walla",
    "sg:classifiers":[
        {
            "category":"Banks & Credit Unions",
            "subcategory":"Investment Brokerage",
            "type":"Services"
        }
    ],
    "sg:phone":"+1 509 522 1660",
    "sg:postcode":"99362",
    "sg:province":"WA",
    "sg:tags":[
        "advisory"
    ],
    "wof:name":"American Express",
    "wof:placetype":"venue"
},
  "geometry": {"coordinates":[-118.33416200000001,46.069834],"type":"Point"}
}