{
  "type": "Feature",
  "properties": {
    "addr:full":"109 N University Rd Spokane WA 99206",
    "addr:housenumber":"109",
    "addr:postcode":"99206",
    "addr:street":"N University Rd",
    "iso:country":"US",
    "sg:address":"109 N University Rd",
    "sg:city":"Spokane",
    "sg:classifiers":[
        {
            "category":"Food & Beverages",
            "subcategory":"Specialty",
            "type":"Retail Goods"
        }
    ],
    "sg:phone":"+1 509 892 6671",
    "sg:postcode":"99206",
    "sg:province":"WA",
    "sg:tags":[
        "health",
        "vitamin"
    ],
    "wof:name":"Cruise Ctrl Enrgy Supplements",
    "wof:placetype":"venue"
},
  "geometry": {"coordinates":[-117.261411,47.65732],"type":"Point"}
}