{
  "type": "Feature",
  "properties": {
    "addr:full":"893 US Hwy 97A Chelan WA 98816",
    "addr:housenumber":"893",
    "addr:postcode":"98816",
    "addr:street":"Us Hwy 97A",
    "iso:country":"US",
    "sg:address":"893 US Hwy 97A",
    "sg:city":"Chelan",
    "sg:classifiers":[
        {
            "category":"Farming",
            "subcategory":"Orchard",
            "type":"Manufacturing & Wholesale Goods"
        }
    ],
    "sg:phone":"+1 509 682 5203",
    "sg:postcode":"98816",
    "sg:province":"WA",
    "sg:tags":[
        "deciduous",
        "fruit",
        "tree"
    ],
    "wof:name":"Cascade Foothills Fruit Inc",
    "wof:placetype":"venue"
},
  "geometry": {"coordinates":[-120.08985,47.839721],"type":"Point"}
}