{
  "type": "Feature",
  "properties": {
    "addr:full":"1450 E Ballow Rd Shelton WA 98584",
    "addr:housenumber":"1450",
    "addr:postcode":"98584",
    "addr:street":"E Ballow Rd",
    "iso:country":"US",
    "sg:address":"1450 E Ballow Rd",
    "sg:city":"Shelton",
    "sg:classifiers":[
        {
            "category":"Building & Trades",
            "subcategory":"Plumbing",
            "type":"Services"
        }
    ],
    "sg:phone":"+1 360 427 1228",
    "sg:postcode":"98584",
    "sg:province":"WA",
    "sg:tags":[
        "plumber",
        "industrial",
        "contractors-commercial"
    ],
    "wof:name":"Mike Glaser Plumbing",
    "wof:placetype":"venue"
},
  "geometry": {"coordinates":[-122.86704,47.238605],"type":"Point"}
}