{
  "type": "Feature",
  "properties": {
    "addr:full":"1208 Commerce Ave Longview WA 98632",
    "addr:housenumber":"1208",
    "addr:postcode":"98632",
    "addr:street":"Commerce Ave",
    "iso:country":"US",
    "sg:address":"1208 Commerce Ave",
    "sg:city":"Longview",
    "sg:classifiers":[
        {
            "category":"Tea Room",
            "subcategory":"None",
            "type":"Food & Drink"
        },
        {
            "category":"Coffee & Tea",
            "type":"Food & Drink"
        },
        {
            "category":"Restaurant",
            "type":"Food & Drink"
        }
    ],
    "sg:phone":"+1 360 425 8940",
    "sg:postcode":"98632",
    "sg:province":"WA",
    "sg:tags":[
        "shop",
        "espresso"
    ],
    "wof:name":"Guse's Gourmet Coffee",
    "wof:placetype":"venue"
},
  "geometry": {"coordinates":[-122.93499799999999,46.135579],"type":"Point"}
}