{
  "type": "Feature",
  "properties": {
    "addr:full":"103 Aspen Ln N Pacific WA 98047",
    "addr:housenumber":"103",
    "addr:postcode":"98047",
    "addr:street":"Aspen Ln N Pacific",
    "iso:country":"US",
    "sg:address":"103 Aspen Ln N",
    "sg:city":"Pacific",
    "sg:classifiers":[
        {
            "category":"Wholesale",
            "subcategory":"Chemicals & Plastics",
            "type":"Manufacturing & Wholesale Goods"
        }
    ],
    "sg:phone":"+1 253 334 1040",
    "sg:postcode":"98047",
    "sg:province":"WA",
    "sg:tags":[
        "merchandise"
    ],
    "wof:name":"Vanner Products",
    "wof:placetype":"venue"
},
  "geometry": {"coordinates":[-122.234894,47.269687],"type":"Point"}
}