{
  "type": "Feature",
  "properties": {
    "addr:full":"8551 W Gage Blvd Kennewick WA 99336",
    "addr:housenumber":"8551",
    "addr:postcode":"99336",
    "addr:street":"W Gage Blvd",
    "iso:country":"US",
    "sg:address":"8551 W Gage Blvd",
    "sg:city":"Kennewick",
    "sg:classifiers":[
        {
            "category":"Professional",
            "type":"Services"
        }
    ],
    "sg:phone":"+1 509 783 2004",
    "sg:postcode":"99336",
    "sg:province":"WA",
    "wof:name":"ALC of Tri Cities LLC",
    "wof:placetype":"venue"
},
  "geometry": {"coordinates":[-119.235902,46.227053],"type":"Point"}
}