{
  "type": "Feature",
  "properties": {
    "addr:full":"1125 21st Ave Clarkston WA 99403",
    "addr:housenumber":"1125",
    "addr:postcode":"99403",
    "addr:street":"21St Ave",
    "iso:country":"US",
    "sg:address":"1125 21st Ave",
    "sg:city":"Clarkston",
    "sg:classifiers":[
        {
            "category":"Shopping",
            "subcategory":"Crafts & Fabrics",
            "type":"Retail Goods"
        }
    ],
    "sg:phone":"+1 509 758 3794",
    "sg:postcode":"99403",
    "sg:province":"WA",
    "sg:tags":[
        "sewing"
    ],
    "wof:name":"Quilt Shoppe",
    "wof:placetype":"venue"
},
  "geometry": {"coordinates":[-117.05481399999999,46.390259],"type":"Point"}
}