{
  "type": "Feature",
  "properties": {
    "addr:full":"10859 12th Ave SW Seattle WA 98146",
    "addr:housenumber":"10859",
    "addr:postcode":"98146",
    "addr:street":"12Th Ave Sw",
    "iso:country":"US",
    "sg:address":"10859 12th Ave SW",
    "sg:city":"Seattle",
    "sg:classifiers":[
        {
            "category":"Wholesale",
            "subcategory":"Computers",
            "type":"Manufacturing & Wholesale Goods"
        }
    ],
    "sg:phone":"+1 206 439 7262",
    "sg:postcode":"98146",
    "sg:province":"WA",
    "wof:name":"Brannon Boren",
    "wof:placetype":"venue"
},
  "geometry": {"coordinates":[-122.350072,47.506942],"type":"Point"}
}