{
  "type": "Feature",
  "properties": {
    "addr:full":"Westlake Tower 1735 Westlake Ave N Ste 201 Seattle WA 98109",
    "addr:housenumber":"1735",
    "addr:postcode":"98109",
    "addr:street":"Westlake Ave N Ste 201",
    "iso:country":"US",
    "sg:address":"Westlake Tower 1735 Westlake Ave N Ste 201",
    "sg:city":"Seattle",
    "sg:classifiers":[
        {
            "category":"Personal",
            "subcategory":"Beauty Salon",
            "type":"Services"
        }
    ],
    "sg:phone":"+1 206 284 2569",
    "sg:postcode":"98109",
    "sg:province":"WA",
    "sg:tags":[
        "hair"
    ],
    "sg:website":"www.damesalon.com",
    "wof:name":"Dame",
    "wof:placetype":"venue"
},
  "geometry": {"coordinates":[-122.34086000000001,47.634695],"type":"Point"}
}