{
  "type": "Feature",
  "properties": {
    "addr:full":"902 W State Route 20 Sedro Woolley WA 98284",
    "addr:housenumber":"902",
    "addr:postcode":"98284",
    "addr:street":"W State Route 20",
    "iso:country":"US",
    "sg:address":"902 W State Route 20",
    "sg:city":"Sedro Woolley",
    "sg:classifiers":[
        {
            "category":"Restaurant",
            "type":"Food & Drink"
        }
    ],
    "sg:phone":"+1 360 856 6810",
    "sg:postcode":"98284",
    "sg:province":"WA",
    "sg:tags":[
        "mexican"
    ],
    "wof:name":"Lorenzo's",
    "wof:placetype":"venue"
},
  "geometry": {"coordinates":[-122.225651,48.510577],"type":"Point"}
}