{
  "type": "Feature",
  "properties": {
    "addr:full":"6725 45th Ave S Seattle WA 98118",
    "addr:housenumber":"6725",
    "addr:postcode":"98118",
    "addr:street":"45Th Ave S",
    "iso:country":"US",
    "sg:address":"6725 45th Ave S",
    "sg:city":"Seattle",
    "sg:classifiers":[
        {
            "category":"Organizations",
            "subcategory":"Community Association",
            "type":"Services"
        }
    ],
    "sg:phone":"+1 206 725 3138",
    "sg:postcode":"98118",
    "sg:province":"WA",
    "sg:tags":[
        "club"
    ],
    "wof:name":"Boys & Girls Clubs-King Cnty",
    "wof:placetype":"venue"
},
  "geometry": {"coordinates":[-122.27652999999999,47.540891],"type":"Point"}
}