{
  "type": "Feature",
  "properties": {
    "addr:full":"101 N 2nd St Roslyn WA 98941",
    "addr:housenumber":"101",
    "addr:postcode":"98941",
    "addr:street":"N 2Nd St",
    "iso:country":"US",
    "sg:address":"101 N 2nd St",
    "sg:city":"Roslyn",
    "sg:classifiers":[
        {
            "category":"Cinema",
            "subcategory":"Movie Rental",
            "type":"Entertainment"
        }
    ],
    "sg:phone":"+1 509 649 2606",
    "sg:postcode":"98941",
    "sg:province":"WA",
    "sg:tags":[
        "leasing",
        "video",
        "disc",
        "tape"
    ],
    "wof:name":"Roslyn Video",
    "wof:placetype":"venue"
},
  "geometry": {"coordinates":[-120.994648,47.222415],"type":"Point"}
}