{
  "type": "Feature",
  "properties": {
    "iso:country":"US",
    "sg:address":"101 Alaskan Way S",
    "sg:city":"Seattle",
    "sg:classifiers":[
        {
            "category":"Recreation",
            "type":"Entertainment"
        }
    ],
    "sg:phone":"+1 206 223 1767",
    "sg:postcode":"98104",
    "sg:province":"WA",
    "wof:name":"Submarine Attractions",
    "wof:placetype":"venue"
},
  "geometry": {"coordinates":[-122.335978,47.60088],"type":"Point"}
}