{
  "type": "Feature",
  "properties": {
    "addr:full":"15110 NE 90th St Redmond WA 98052",
    "addr:housenumber":"15110",
    "addr:postcode":"98052",
    "addr:street":"Ne 90Th St",
    "iso:country":"US",
    "sg:address":"15110 NE 90th St",
    "sg:city":"Redmond",
    "sg:classifiers":[
        {
            "category":"Manufacturing",
            "subcategory":"Food",
            "type":"Manufacturing & Wholesale Goods"
        }
    ],
    "sg:phone":"+1 425 881 8181",
    "sg:postcode":"98052",
    "sg:province":"WA",
    "sg:tags":[
        "process",
        "fish"
    ],
    "wof:name":"Fishking Processors-Redmond",
    "wof:placetype":"venue"
},
  "geometry": {"coordinates":[-122.137793,47.682314],"type":"Point"}
}