{
  "type": "Feature",
  "properties": {
    "addr:full":"1410 11th St Bellingham WA 98225",
    "addr:housenumber":"1410",
    "addr:postcode":"98225",
    "addr:street":"11Th St",
    "iso:country":"US",
    "sg:address":"1410 11th St",
    "sg:city":"Bellingham",
    "sg:classifiers":[
        {
            "category":"Personal",
            "subcategory":"Beauty Salon",
            "type":"Services"
        }
    ],
    "sg:phone":"+1 360 733 4477",
    "sg:postcode":"98225",
    "sg:province":"WA",
    "sg:tags":[
        "shop"
    ],
    "wof:name":"Robert Jude Salon",
    "wof:placetype":"venue"
},
  "geometry": {"coordinates":[-122.50345299999999,48.718598],"type":"Point"}
}