{
  "type": "Feature",
  "properties": {
    "addr:full":"428 W Birch St Shelton WA 98584",
    "addr:housenumber":"428",
    "addr:postcode":"98584",
    "addr:street":"W Birch St",
    "iso:country":"US",
    "sg:address":"428 W Birch St",
    "sg:city":"Shelton",
    "sg:classifiers":[
        {
            "category":"Social Services",
            "type":"Services"
        }
    ],
    "sg:phone":"+1 360 432 9825",
    "sg:postcode":"98584",
    "sg:province":"WA",
    "sg:tags":[
        "counseling"
    ],
    "wof:name":"Hendricks Counseling",
    "wof:placetype":"venue"
},
  "geometry": {"coordinates":[-123.103836,47.217167],"type":"Point"}
}