{
  "type": "Feature",
  "properties": {
    "addr:full":"2442 NW Market St Seattle WA 98107",
    "addr:housenumber":"2442",
    "addr:postcode":"98107",
    "addr:street":"Nw Market St",
    "iso:country":"US",
    "sg:address":"2442 NW Market St",
    "sg:city":"Seattle",
    "sg:classifiers":[
        {
            "category":"Building & Trades",
            "subcategory":"Construction",
            "type":"Services"
        }
    ],
    "sg:phone":"+1 206 910 4811",
    "sg:postcode":"98107",
    "sg:province":"WA",
    "sg:tags":[
        "house",
        "ma"
    ],
    "wof:name":"R B M Construction",
    "wof:placetype":"venue"
},
  "geometry": {"coordinates":[-122.38983899999999,47.668742],"type":"Point"}
}