{
  "type": "Feature",
  "properties": {
    "addr:full":"851 6th St Bremerton WA 98337",
    "addr:housenumber":"851",
    "addr:postcode":"98337",
    "addr:street":"6Th St",
    "iso:country":"US",
    "sg:address":"851 6th St",
    "sg:city":"Bremerton",
    "sg:classifiers":[
        {
            "category":"Social Services",
            "subcategory":"Job Training",
            "type":"Services"
        }
    ],
    "sg:phone":"+1 360 415 8595",
    "sg:postcode":"98337",
    "sg:province":"WA",
    "sg:tags":[
        "rehabilitation"
    ],
    "wof:name":"Paul Prachyl Phd Crc",
    "wof:placetype":"venue"
},
  "geometry": {"coordinates":[-122.632458,47.567261],"type":"Point"}
}