{
  "type": "Feature",
  "properties": {
    "addr:full":"16701 Country Club Dr Burlington WA 98233",
    "addr:housenumber":"16701",
    "addr:postcode":"98233",
    "addr:street":"Country Club Dr",
    "iso:country":"US",
    "sg:address":"16701 Country Club Dr",
    "sg:city":"Burlington",
    "sg:classifiers":[
        {
            "category":"Recreation",
            "type":"Entertainment"
        }
    ],
    "sg:phone":"+1 360 757 4081",
    "sg:postcode":"98233",
    "sg:province":"WA",
    "sg:tags":[
        "course",
        "golf"
    ],
    "sg:website":"www.skagitgolfclub.com",
    "wof:name":"Skagit Golf & Country Club",
    "wof:placetype":"venue"
},
  "geometry": {"coordinates":[-122.38337900000001,48.463818],"type":"Point"}
}