{
  "type": "Feature",
  "properties": {
    "addr:full":"1307 Nightingale Rd Wapato WA 98951",
    "addr:housenumber":"1307",
    "addr:postcode":"98951",
    "addr:street":"Nightingale Rd",
    "iso:country":"US",
    "sg:address":"1307 Nightingale Rd",
    "sg:city":"Wapato",
    "sg:classifiers":[
        {
            "category":"Real Estate",
            "subcategory":"Real Estate Services",
            "type":"Services"
        },
        {
            "category":"Real Estate",
            "subcategory":"Real Estate Agent",
            "type":"Services"
        }
    ],
    "sg:phone":"+1 509 877 2745",
    "sg:postcode":"98951",
    "sg:province":"WA",
    "sg:tags":[
        "buyer",
        "broker"
    ],
    "wof:name":"Ardent Realty Group Inc",
    "wof:placetype":"venue"
},
  "geometry": {"coordinates":[-120.324181,46.49183],"type":"Point"}
}