{
  "type": "Feature",
  "properties": {
    "addr:full":"9817 120th St E Puyallup WA 98373",
    "addr:housenumber":"9817",
    "addr:postcode":"98373",
    "addr:street":"120Th St E",
    "iso:country":"US",
    "sg:address":"9817 120th St E",
    "sg:city":"Puyallup",
    "sg:classifiers":[
        {
            "category":"Building & Trades",
            "subcategory":"Construction",
            "type":"Services"
        }
    ],
    "sg:phone":"+1 253 770 4847",
    "sg:postcode":"98373",
    "sg:province":"WA",
    "sg:tags":[
        "house"
    ],
    "wof:name":"L&L Remodeling & Construction",
    "wof:placetype":"venue"
},
  "geometry": {"coordinates":[-122.29466499999999,47.147562],"type":"Point"}
}