{
  "type": "Feature",
  "properties": {
    "addr:full":"7013 187th Dr SE Snohomish WA 98290",
    "addr:housenumber":"7013",
    "addr:postcode":"98290",
    "addr:street":"187Th Dr Se",
    "iso:country":"US",
    "sg:address":"7013 187th Dr SE",
    "sg:city":"Snohomish",
    "sg:classifiers":[
        {
            "category":"Building & Trades",
            "subcategory":"Cleaning & Sanitation",
            "type":"Services"
        }
    ],
    "sg:phone":"+1 360 568 9140",
    "sg:postcode":"98290",
    "sg:province":"WA",
    "sg:tags":[
        "maintenance"
    ],
    "wof:name":"R J Enterprises",
    "wof:placetype":"venue"
},
  "geometry": {"coordinates":[-121.977335,47.930666],"type":"Point"}
}