{
  "type": "Feature",
  "properties": {
    "addr:full":"203 Fredericks St Port Townsend WA 98368",
    "addr:housenumber":"203",
    "addr:postcode":"98368",
    "addr:street":"Fredericks St",
    "iso:country":"US",
    "sg:address":"203 Fredericks St",
    "sg:city":"Port Townsend",
    "sg:classifiers":[
        {
            "category":"Building & Trades",
            "subcategory":"Electrical",
            "type":"Services"
        }
    ],
    "sg:phone":"+1 360 385 3514",
    "sg:postcode":"98368",
    "sg:province":"WA",
    "sg:tags":[
        "electric",
        "contractor"
    ],
    "wof:name":"Starboard Tech",
    "wof:placetype":"venue"
},
  "geometry": {"coordinates":[-122.814554,48.088193],"type":"Point"}
}