{
  "type": "Feature",
  "properties": {
    "addr:full":"1100 University Street Seattle WA 98101",
    "addr:housenumber":"1100",
    "addr:postcode":"98101",
    "addr:street":"University Street",
    "iso:country":"US",
    "sg:address":"1100 University Street",
    "sg:city":"Seattle",
    "sg:classifiers":[
        {
            "category":"Real Estate",
            "subcategory":"Real Estate Operator",
            "type":"Services"
        }
    ],
    "sg:phone":"+1 206 624 3155",
    "sg:postcode":"98101",
    "sg:province":"WA",
    "sg:tags":[
        "apartment"
    ],
    "wof:name":"Panorama House",
    "wof:placetype":"venue"
},
  "geometry": {"coordinates":[-122.327112,47.611493],"type":"Point"}
}