{
  "type": "Feature",
  "properties": {
    "addr:full":"2802 Brentwood Dr SE Lacey WA 98503",
    "addr:housenumber":"2802",
    "addr:postcode":"98503",
    "addr:street":"Brentwood Dr Se",
    "iso:country":"US",
    "sg:address":"2802 Brentwood Dr SE",
    "sg:city":"Lacey",
    "sg:classifiers":[
        {
            "category":"Retail",
            "subcategory":"Portrait Studio",
            "type":"Services"
        }
    ],
    "sg:phone":"+1 360 491 5874",
    "sg:postcode":"98503",
    "sg:province":"WA",
    "sg:tags":[
        "photographer",
        "school"
    ],
    "wof:name":"Clintworth Photography Inc",
    "wof:placetype":"venue"
},
  "geometry": {"coordinates":[-122.811104,47.019326],"type":"Point"}
}