{
  "type": "Feature",
  "properties": {
    "addr:full":"5920 100th St SW Ste 25 Lakewood WA 98499",
    "addr:housenumber":"5920",
    "addr:postcode":"98499",
    "addr:street":"100Th St Sw Ste 25",
    "iso:country":"US",
    "sg:address":"5920 100th St SW Ste 25",
    "sg:city":"Lakewood",
    "sg:classifiers":[
        {
            "category":"Professional",
            "subcategory":"Lawyer & Legal Services",
            "type":"Services"
        }
    ],
    "sg:phone":"+1 253 581 0660",
    "sg:postcode":"98499",
    "sg:province":"WA",
    "sg:tags":[
        "plan"
    ],
    "wof:name":"Faubion Thomas K",
    "wof:placetype":"venue"
},
  "geometry": {"coordinates":[-122.51627000000001,47.166706],"type":"Point"}
}