{
  "type": "Feature",
  "properties": {
    "addr:full":"70 E Juniper St Othello WA 99344",
    "addr:housenumber":"70",
    "addr:postcode":"99344",
    "addr:street":"E Juniper St",
    "iso:country":"US",
    "sg:address":"70 E Juniper St",
    "sg:city":"Othello",
    "sg:classifiers":[
        {
            "category":"Building & Trades",
            "subcategory":"Construction",
            "type":"Services"
        }
    ],
    "sg:phone":"+1 509 488 0752",
    "sg:postcode":"99344",
    "sg:province":"WA",
    "sg:tags":[
        "general",
        "contractor"
    ],
    "wof:name":"K & G Construction",
    "wof:placetype":"venue"
},
  "geometry": {"coordinates":[-119.174772,46.82203],"type":"Point"}
}