{
  "type": "Feature",
  "properties": {
    "iso:country":"US",
    "sg:address":"26119 70th Ave E",
    "sg:city":"Graham",
    "sg:classifiers":[
        {
            "category":"Building & Trades",
            "subcategory":"Construction",
            "type":"Services"
        }
    ],
    "sg:phone":"+1 253 847 6048",
    "sg:postcode":"98338",
    "sg:province":"WA",
    "sg:tags":[
        "contractor"
    ],
    "wof:name":"Gregs Drywall",
    "wof:placetype":"venue"
},
  "geometry": {"coordinates":[-122.33871600000001,47.01989],"type":"Point"}
}