{
  "type": "Feature",
  "properties": {
    "addr:full":"24201 4th Pl W Bothell WA 98021",
    "addr:housenumber":"24201",
    "addr:postcode":"98021",
    "addr:street":"4Th Pl W",
    "iso:country":"US",
    "sg:address":"24201 4th Pl W",
    "sg:city":"Bothell",
    "sg:classifiers":[
        {
            "category":"Professional",
            "subcategory":"Business Services",
            "type":"Services"
        }
    ],
    "sg:phone":"+1 425 483 1089",
    "sg:postcode":"98021",
    "sg:province":"WA",
    "wof:name":"Olympic Recreation Service",
    "wof:placetype":"venue"
},
  "geometry": {"coordinates":[-122.239086,47.778735],"type":"Point"}
}