{
  "type": "Feature",
  "properties": {
    "addr:full":"7842 S 114th St Seattle WA 98178",
    "addr:housenumber":"7842",
    "addr:postcode":"98178",
    "addr:street":"S 114Th St",
    "iso:country":"US",
    "sg:address":"7842 S 114th St",
    "sg:city":"Seattle",
    "sg:classifiers":[
        {
            "category":"Manufacturing",
            "subcategory":"Retail Goods",
            "type":"Manufacturing & Wholesale Goods"
        }
    ],
    "sg:phone":"+1 206 227 1403",
    "sg:postcode":"98178",
    "sg:province":"WA",
    "sg:tags":[
        "product",
        "mfg"
    ],
    "wof:name":"Island Time Creations",
    "wof:placetype":"venue"
},
  "geometry": {"coordinates":[-122.23321300000001,47.501388],"type":"Point"}
}