{
  "type": "Feature",
  "properties": {
    "addr:full":"5808 Greenwood Ave N Seattle WA 98103",
    "addr:housenumber":"5808",
    "addr:postcode":"98103",
    "addr:street":"Greenwood Ave N",
    "iso:country":"US",
    "sg:address":"5808 Greenwood Ave N",
    "sg:city":"Seattle",
    "sg:classifiers":[
        {
            "category":"Health Services",
            "subcategory":"Doctor",
            "type":"Services"
        }
    ],
    "sg:phone":"+1 206 789 6284",
    "sg:postcode":"98103",
    "sg:province":"WA",
    "sg:tags":[
        "medical"
    ],
    "wof:name":"Nancy Lillehei MD",
    "wof:placetype":"venue"
},
  "geometry": {"coordinates":[-122.355284,47.671775],"type":"Point"}
}