{
  "type": "Feature",
  "properties": {
    "addr:full":"321 W Stutler Rd Spokane WA 99224",
    "addr:housenumber":"321",
    "addr:postcode":"99224",
    "addr:street":"W Stutler Rd",
    "iso:country":"US",
    "sg:address":"321 W Stutler Rd",
    "sg:city":"Spokane",
    "sg:classifiers":[
        {
            "category":"Retail",
            "subcategory":"Animal Services",
            "type":"Services"
        }
    ],
    "sg:phone":"+1 509 448 2453",
    "sg:postcode":"99224",
    "sg:province":"WA",
    "wof:name":"Judy K Babb",
    "wof:placetype":"venue"
},
  "geometry": {"coordinates":[-117.41148200000001,47.504428],"type":"Point"}
}