{
  "type": "Feature",
  "properties": {
    "iso:country":"US",
    "sg:address":"8115 E Trent Ave",
    "sg:city":"Spokane Valley",
    "sg:classifiers":[
        {
            "category":"Professional",
            "subcategory":"Accounting & Tax Preparation",
            "type":"Services"
        }
    ],
    "sg:phone":"+1 509 892 5905",
    "sg:postcode":"99212",
    "sg:province":"WA",
    "sg:tags":[
        "accountant"
    ],
    "wof:name":"Robert P Mc Kinley PC",
    "wof:placetype":"venue"
},
  "geometry": {"coordinates":[-117.29356199999999,47.67897],"type":"Point"}
}