{
  "type": "Feature",
  "properties": {
    "addr:full":"4009 15th Ave NE Seattle WA 98105",
    "addr:housenumber":"4009",
    "addr:postcode":"98105",
    "addr:street":"15Th Ave Ne",
    "iso:country":"US",
    "sg:address":"4009 15th Ave NE",
    "sg:city":"Seattle",
    "sg:classifiers":[
        {
            "category":"Real Estate",
            "subcategory":"Real Estate Operator",
            "type":"Services"
        }
    ],
    "sg:phone":"+1 206 547 1203",
    "sg:postcode":"98105",
    "sg:province":"WA",
    "sg:tags":[
        "building",
        "apartment"
    ],
    "wof:name":"Commodore Duchess Apartments",
    "wof:placetype":"venue"
},
  "geometry": {"coordinates":[-122.31199599999999,47.655399],"type":"Point"}
}