{
  "type": "Feature",
  "properties": {
    "addr:full":"8004 Mukilteo Speedway Mukilteo WA 98275",
    "addr:housenumber":"8004",
    "addr:postcode":"98275",
    "addr:street":"Mukilteo Speedway",
    "iso:country":"US",
    "sg:address":"8004 Mukilteo Speedway",
    "sg:city":"Mukilteo",
    "sg:classifiers":[
        {
            "category":"Personal",
            "subcategory":"Barber",
            "type":"Services"
        }
    ],
    "sg:phone":"+1 425 355 4007",
    "sg:postcode":"98275",
    "sg:province":"WA",
    "sg:tags":[
        "shop"
    ],
    "wof:name":"Mukilteo Barber",
    "wof:placetype":"venue"
},
  "geometry": {"coordinates":[-122.300335,47.925224],"type":"Point"}
}