{
  "type": "Feature",
  "properties": {
    "addr:full":"877 S 4th Ave Othello WA 99344",
    "addr:housenumber":"877",
    "addr:postcode":"99344",
    "addr:street":"S 4Th Ave Othello",
    "iso:country":"US",
    "sg:address":"877 S 4th Ave",
    "sg:city":"Othello",
    "sg:classifiers":[
        {
            "category":"Farming",
            "subcategory":"Farm & Veterinary Services",
            "type":"Manufacturing & Wholesale Goods"
        }
    ],
    "sg:phone":"+1 509 488 5364",
    "sg:postcode":"99344",
    "sg:province":"WA",
    "sg:tags":[
        "preparation",
        "soil"
    ],
    "wof:name":"Liftem Tanks Inc",
    "wof:placetype":"venue"
},
  "geometry": {"coordinates":[-119.169991,46.816768],"type":"Point"}
}