{
  "type": "Feature",
  "properties": {
    "addr:full":"1025 Pacific Ave Tacoma WA 98402",
    "addr:housenumber":"1025",
    "addr:postcode":"98402",
    "addr:street":"Pacific Ave",
    "iso:country":"US",
    "sg:address":"1025 Pacific Ave",
    "sg:city":"Tacoma",
    "sg:classifiers":[
        {
            "category":"Restaurant",
            "type":"Food & Drink"
        }
    ],
    "sg:phone":"+1 253 572 2008",
    "sg:postcode":"98402",
    "sg:province":"WA",
    "sg:tags":[
        "operator"
    ],
    "wof:name":"Round Table Pizza",
    "wof:placetype":"venue"
},
  "geometry": {"coordinates":[-122.438596,47.25364],"type":"Point"}
}