{
  "type": "Feature",
  "properties": {
    "addr:full":"724 Ericksen Ave NE Bainbridge Isle WA 98110",
    "addr:housenumber":"724",
    "addr:postcode":"98110",
    "addr:street":"Ericksen Ave Ne;Isle",
    "iso:country":"US",
    "sg:address":"724 Ericksen Ave NE",
    "sg:city":"Bainbridge Isle",
    "sg:classifiers":[
        {
            "category":"Professional",
            "subcategory":"Research",
            "type":"Services"
        }
    ],
    "sg:phone":"+1 206 780 2303",
    "sg:postcode":"98110",
    "sg:province":"WA",
    "sg:tags":[
        "environmental",
        "ecological"
    ],
    "wof:name":"ERM",
    "wof:placetype":"venue"
},
  "geometry": {"coordinates":[-122.516998,47.631942],"type":"Point"}
}