{
  "type": "Feature",
  "properties": {
    "addr:full":"4812 S L St Tacoma WA 98408",
    "addr:housenumber":"4812",
    "addr:postcode":"98408",
    "addr:street":"S L St",
    "iso:country":"US",
    "sg:address":"4812 S L St",
    "sg:city":"Tacoma",
    "sg:classifiers":[
        {
            "category":"Professional",
            "type":"Services"
        }
    ],
    "sg:phone":"+1 253 576 7904",
    "sg:postcode":"98408",
    "sg:province":"WA",
    "wof:name":"Real Quality Services",
    "wof:placetype":"venue"
},
  "geometry": {"coordinates":[-122.44984599999999,47.211897],"type":"Point"}
}