{
  "type": "Feature",
  "properties": {
    "addr:full":"1205 SE Everett Mall Way Everett WA 98208",
    "addr:housenumber":"1205",
    "addr:postcode":"98208",
    "addr:street":"Se Everett Mall Way",
    "iso:country":"US",
    "sg:address":"1205 SE Everett Mall Way",
    "sg:city":"Everett",
    "sg:classifiers":[
        {
            "category":"Restaurant",
            "type":"Food & Drink"
        }
    ],
    "sg:phone":"+1 425 438 8683",
    "sg:postcode":"98208",
    "sg:province":"WA",
    "wof:name":"Tokyo Ninja Japanese Restrnt",
    "wof:placetype":"venue"
},
  "geometry": {"coordinates":[-122.214589,47.912025],"type":"Point"}
}