{
  "type": "Feature",
  "properties": {
    "iso:country":"US",
    "sg:address":"4310 48th Ave NE",
    "sg:city":"Seattle",
    "sg:classifiers":[
        {
            "category":"Professional",
            "subcategory":"Art Services",
            "type":"Services"
        }
    ],
    "sg:phone":"+1 206 525 2221",
    "sg:postcode":"98105",
    "sg:province":"WA",
    "sg:tags":[
        "commercial",
        "design"
    ],
    "wof:name":"Mettler Kent Design Consultant",
    "wof:placetype":"venue"
},
  "geometry": {"coordinates":[-122.27660299999999,47.6605],"type":"Point"}
}