{
  "type": "Feature",
  "properties": {
    "addr:full":"4523 170th Pl NE Redmond WA 98052",
    "addr:housenumber":"4523",
    "addr:postcode":"98052",
    "addr:street":"170Th Pl Ne",
    "iso:country":"US",
    "sg:address":"4523 170th Pl NE",
    "sg:city":"Redmond",
    "sg:classifiers":[
        {
            "category":"Banks & Credit Unions",
            "subcategory":"Investment Brokerage",
            "type":"Services"
        }
    ],
    "sg:phone":"+1 425 881 7724",
    "sg:postcode":"98052",
    "sg:province":"WA",
    "sg:tags":[
        "stock",
        "bond"
    ],
    "wof:name":"AIG Royal Alliance",
    "wof:placetype":"venue"
},
  "geometry": {"coordinates":[-122.11341299999999,47.650567],"type":"Point"}
}