{
  "type": "Feature",
  "properties": {
    "addr:full":"13620 NE 20th St Bellevue WA 98005",
    "addr:housenumber":"13620",
    "addr:postcode":"98005",
    "addr:street":"Ne 20Th St",
    "iso:country":"US",
    "sg:address":"13620 NE 20th St",
    "sg:city":"Bellevue",
    "sg:classifiers":[
        {
            "category":"Wholesale",
            "subcategory":"Construction Materials",
            "type":"Manufacturing & Wholesale Goods"
        }
    ],
    "sg:phone":"+1 425 562 9398",
    "sg:postcode":"98005",
    "sg:province":"WA",
    "wof:name":"Tin Horse Interior",
    "wof:placetype":"venue"
},
  "geometry": {"coordinates":[-122.15371399999999,47.627956],"type":"Point"}
}