{
  "type": "Feature",
  "properties": {
    "addr:full":"5100 S Dawson St Seattle WA 98118",
    "addr:housenumber":"5100",
    "addr:postcode":"98118",
    "addr:street":"S Dawson St",
    "iso:country":"US",
    "sg:address":"5100 S Dawson St",
    "sg:city":"Seattle",
    "sg:classifiers":[
        {
            "category":"Building & Trades",
            "subcategory":"Locksmith",
            "type":"Services"
        }
    ],
    "sg:phone":"+1 253 214 3923",
    "sg:postcode":"98118",
    "sg:province":"WA",
    "sg:tags":[
        "key"
    ],
    "wof:name":"Locksmith 007 Emergency",
    "wof:placetype":"venue"
},
  "geometry": {"coordinates":[-122.26987,47.554987],"type":"Point"}
}