{
  "type": "Feature",
  "properties": {
    "addr:full":"500 NW Market St Seattle WA 98107",
    "addr:housenumber":"500",
    "addr:postcode":"98107",
    "addr:street":"Nw Market St",
    "iso:country":"US",
    "sg:address":"500 NW Market St",
    "sg:city":"Seattle",
    "sg:classifiers":[
        {
            "category":"Professional",
            "type":"Services"
        },
        {
            "category":"Restaurant",
            "type":"Food & Drink"
        }
    ],
    "sg:phone":"+1 206 525 1813",
    "sg:postcode":"98107",
    "sg:province":"WA",
    "sg:tags":[
        "pizza",
        "caterer"
    ],
    "sg:website":"www.veracipizza.com",
    "wof:name":"Veraci Pizza",
    "wof:placetype":"venue"
},
  "geometry": {"coordinates":[-122.36295699999999,47.668712],"type":"Point"}
}