{
  "type": "Feature",
  "properties": {
    "addr:full":"718 Jadwin Ave Richland WA 99352",
    "addr:housenumber":"718",
    "addr:postcode":"99352",
    "addr:street":"Jadwin Ave",
    "iso:country":"US",
    "sg:address":"718 Jadwin Ave",
    "sg:city":"Richland",
    "sg:classifiers":[
        {
            "category":"Professional",
            "subcategory":"Computer Services",
            "type":"Services"
        }
    ],
    "sg:phone":"+1 509 539 2458",
    "sg:postcode":"99352",
    "sg:province":"WA",
    "sg:tags":[
        "programing",
        "custom"
    ],
    "wof:name":"Northwest Spder Tech Group LLC",
    "wof:placetype":"venue"
},
  "geometry": {"coordinates":[-119.27515,46.276302],"type":"Point"}
}