{
  "type": "Feature",
  "properties": {
    "addr:full":"1836 Westlake Ave N Seattle WA 98109",
    "addr:housenumber":"1836",
    "addr:postcode":"98109",
    "addr:street":"Westlake Ave N",
    "iso:country":"US",
    "sg:address":"1836 Westlake Ave N",
    "sg:city":"Seattle",
    "sg:classifiers":[
        {
            "category":"Insurance",
            "subcategory":"Insurance Agent",
            "type":"Services"
        }
    ],
    "sg:phone":"+1 206 378 1132",
    "sg:postcode":"98109",
    "sg:province":"WA",
    "wof:name":"BIM Insurance Marketing Inc",
    "wof:placetype":"venue"
},
  "geometry": {"coordinates":[-122.340344,47.634684],"type":"Point"}
}