{
  "type": "Feature",
  "properties": {
    "addr:full":"2406 SE 179th Ct Vancouver WA 98683",
    "addr:housenumber":"2406",
    "addr:postcode":"98683",
    "addr:street":"Se 179Th Ct",
    "iso:country":"US",
    "sg:address":"2406 SE 179th Ct",
    "sg:city":"Vancouver",
    "sg:classifiers":[
        {
            "category":"Professional",
            "subcategory":"Business Services",
            "type":"Services"
        }
    ],
    "sg:phone":"+1 360 254 3432",
    "sg:postcode":"98683",
    "sg:province":"WA",
    "wof:name":"Simple Pleasures",
    "wof:placetype":"venue"
},
  "geometry": {"coordinates":[-122.48836900000001,45.60335],"type":"Point"}
}