{
  "type": "Feature",
  "properties": {
    "addr:full":"8704 3rd Ave SE Everett WA 98208",
    "addr:housenumber":"8704",
    "addr:postcode":"98208",
    "addr:street":"3Rd Ave Se",
    "iso:country":"US",
    "sg:address":"8704 3rd Ave SE",
    "sg:city":"Everett",
    "sg:classifiers":[
        {
            "category":"Organizations",
            "subcategory":"Religious Organization",
            "type":"Services"
        }
    ],
    "sg:phone":"+1 425 355 0266",
    "sg:postcode":"98208",
    "sg:province":"WA",
    "wof:name":"Berean Bible Fellowship",
    "wof:placetype":"venue"
},
  "geometry": {"coordinates":[-122.228323,47.918883],"type":"Point"}
}