{
  "type": "Feature",
  "properties": {
    "addr:full":"1613 E 5th St Port Angeles WA 98362",
    "addr:housenumber":"1613",
    "addr:postcode":"98362",
    "addr:street":"E 5Th St",
    "iso:country":"US",
    "sg:address":"1613 E 5th St",
    "sg:city":"Port Angeles",
    "sg:classifiers":[
        {
            "category":"Personal",
            "type":"Services"
        }
    ],
    "sg:phone":"+1 360 457 5266",
    "sg:postcode":"98362",
    "sg:province":"WA",
    "wof:name":"Electrolysis Center",
    "wof:placetype":"venue"
},
  "geometry": {"coordinates":[-123.408922,48.104253],"type":"Point"}
}