{
  "type": "Feature",
  "properties": {
    "addr:full":"5304 Collins Rd West Richland WA 99353",
    "addr:housenumber":"5304",
    "addr:postcode":"99353",
    "addr:street":"Collins Rd West",
    "iso:country":"US",
    "sg:address":"5304 Collins Rd",
    "sg:city":"West Richland",
    "sg:classifiers":[
        {
            "category":"Building & Trades",
            "subcategory":"Electrical",
            "type":"Services"
        }
    ],
    "sg:phone":"+1 509 967 9371",
    "sg:postcode":"99353",
    "sg:province":"WA",
    "sg:tags":[
        "electric",
        "contractor"
    ],
    "wof:name":"Trinity Construction",
    "wof:placetype":"venue"
},
  "geometry": {"coordinates":[-119.35429600000001,46.297885],"type":"Point"}
}