{
  "type": "Feature",
  "properties": {
    "addr:full":"3027 Donovan Loop SE Olympia WA 98501",
    "addr:housenumber":"3027",
    "addr:postcode":"98501",
    "addr:street":"Donovan Loop Se",
    "iso:country":"US",
    "sg:address":"3027 Donovan Loop SE",
    "sg:city":"Olympia",
    "sg:classifiers":[
        {
            "category":"Restaurant",
            "type":"Food & Drink"
        }
    ],
    "sg:phone":"+1 360 705 1867",
    "sg:postcode":"98501",
    "sg:province":"WA",
    "sg:tags":[
        "eating"
    ],
    "wof:name":"Java Flow",
    "wof:placetype":"venue"
},
  "geometry": {"coordinates":[-122.855744,47.002654],"type":"Point"}
}