{
  "type": "Feature",
  "properties": {
    "addr:full":"900 Poplar PL S Seattle WA 98144",
    "addr:housenumber":"900",
    "addr:postcode":"98144",
    "addr:street":"Poplar Pl S",
    "iso:country":"US",
    "sg:address":"900 Poplar PL S",
    "sg:city":"Seattle",
    "sg:classifiers":[
        {
            "category":"Manufacturing",
            "subcategory":"Glass & Minerals",
            "type":"Manufacturing & Wholesale Goods"
        },
        {
            "category":"Manufacturing",
            "subcategory":"Building Materials",
            "type":"Manufacturing & Wholesale Goods"
        },
        {
            "category":"Building & Trades",
            "subcategory":"Construction",
            "type":"Services"
        }
    ],
    "sg:phone":"+1 800 875 2250",
    "sg:postcode":"98144",
    "sg:province":"WA",
    "sg:tags":[
        "installation",
        "window",
        "contractor",
        "glass-wholesale",
        "shape",
        "doors",
        "frames",
        "circle",
        "accessory",
        "special",
        "manufacturer"
    ],
    "sg:website":"www.evansglass.com",
    "wof:name":"Evans Glass",
    "wof:placetype":"venue"
},
  "geometry": {"coordinates":[-122.310954,47.593641],"type":"Point"}
}