{
  "type": "Feature",
  "properties": {
    "addr:full":"2333 Parrott Way Kelso WA 98626",
    "addr:housenumber":"2333",
    "addr:postcode":"98626",
    "addr:street":"Parrott Way",
    "iso:country":"US",
    "sg:address":"2333 Parrott Way",
    "sg:city":"Kelso",
    "sg:classifiers":[
        {
            "category":"Wholesale",
            "subcategory":"Hardware",
            "type":"Manufacturing & Wholesale Goods"
        }
    ],
    "sg:phone":"+1 360 636 4263",
    "sg:postcode":"98626",
    "sg:province":"WA",
    "sg:tags":[
        "heater"
    ],
    "wof:name":"Reed Electric",
    "wof:placetype":"venue"
},
  "geometry": {"coordinates":[-122.89554099999999,46.118967],"type":"Point"}
}