{
  "type": "Feature",
  "properties": {
    "addr:full":"853 Desert Aire Dr N Mattawa WA 99349",
    "addr:housenumber":"853",
    "addr:postcode":"99349",
    "addr:street":"Desert Aire Dr N",
    "iso:country":"US",
    "sg:address":"853 Desert Aire Dr N",
    "sg:city":"Mattawa",
    "sg:classifiers":[
        {
            "category":"Professional",
            "subcategory":"Computer Services",
            "type":"Services"
        }
    ],
    "sg:phone":"+1 509 932 6459",
    "sg:postcode":"99349",
    "sg:province":"WA",
    "sg:tags":[
        "related"
    ],
    "wof:name":"Desert Computer Services",
    "wof:placetype":"venue"
},
  "geometry": {"coordinates":[-119.919606,46.697781],"type":"Point"}
}