{
  "type": "Feature",
  "properties": {
    "addr:full":"703 140th St E Tacoma WA 98445",
    "addr:housenumber":"703",
    "addr:postcode":"98445",
    "addr:street":"140Th St",
    "iso:country":"US",
    "sg:address":"703 140th St E",
    "sg:city":"Tacoma",
    "sg:classifiers":[
        {
            "category":"Building & Trades",
            "subcategory":"Cleaning & Sanitation",
            "type":"Services"
        }
    ],
    "sg:phone":"+1 253 640 0648",
    "sg:postcode":"98445",
    "sg:province":"WA",
    "sg:tags":[
        "window"
    ],
    "wof:name":"Above Expectations Window Cleaning",
    "wof:placetype":"venue"
},
  "geometry": {"coordinates":[-122.42231099999999,47.129551],"type":"Point"}
}