{
  "type": "Feature",
  "properties": {
    "addr:full":"127 N Greenacres Rd Spokane Valley WA 99016",
    "addr:housenumber":"127",
    "addr:postcode":"99016",
    "addr:street":"N Greenacres Rd",
    "iso:country":"US",
    "sg:address":"127 N Greenacres Rd",
    "sg:city":"Spokane Valley",
    "sg:classifiers":[
        {
            "category":"Autos & Motor Vehicles",
            "subcategory":"Automobile Sales",
            "type":"Retail Goods"
        }
    ],
    "sg:phone":"+1 509 927 7286",
    "sg:postcode":"99016",
    "sg:province":"WA",
    "sg:tags":[
        "car",
        "dealer"
    ],
    "sg:website":"www.newdealusedcarsinc.com",
    "wof:name":"New Deal Used Cars",
    "wof:placetype":"venue"
},
  "geometry": {"coordinates":[-117.15910100000001,47.659027],"type":"Point"}
}