{
  "type": "Feature",
  "properties": {
    "addr:full":"24526 104th Ave SE Kent WA 98030",
    "addr:housenumber":"24526",
    "addr:postcode":"98030",
    "addr:street":"104Th Ave Se",
    "iso:country":"US",
    "sg:address":"24526 104th Ave SE",
    "sg:city":"Kent",
    "sg:classifiers":[
        {
            "category":"Shopping",
            "subcategory":"Used Merchandise",
            "type":"Retail Goods"
        }
    ],
    "sg:phone":"+1 253 854 8916",
    "sg:postcode":"98030",
    "sg:province":"WA",
    "wof:name":"Accrete Antique & Hardware Sup",
    "wof:placetype":"venue"
},
  "geometry": {"coordinates":[-122.20226599999999,47.380883],"type":"Point"}
}