{
  "type": "Feature",
  "properties": {
    "addr:full":"1200 N 14th Ave Ste 350 Pasco WA 99301",
    "addr:housenumber":"1200",
    "addr:postcode":"99301",
    "addr:street":"N 14Th Ave Ste 350",
    "iso:country":"US",
    "sg:address":"1200 N 14th Ave Ste 350",
    "sg:city":"Pasco",
    "sg:classifiers":[
        {
            "category":"Health Services",
            "subcategory":"Doctor",
            "type":"Services"
        }
    ],
    "sg:phone":"+1 509 545 0210",
    "sg:postcode":"99301",
    "sg:province":"WA",
    "sg:tags":[
        "physician",
        "surgeon"
    ],
    "wof:name":"Carter Enrique MD",
    "wof:placetype":"venue"
},
  "geometry": {"coordinates":[-119.10797599999999,46.238495],"type":"Point"}
}