{
  "type": "Feature",
  "properties": {
    "addr:full":"3817 19th Ave SW Seattle WA 98106",
    "addr:housenumber":"3817",
    "addr:postcode":"98106",
    "addr:street":"19Th Ave Sw",
    "iso:country":"US",
    "sg:address":"3817 19th Ave SW",
    "sg:city":"Seattle",
    "sg:classifiers":[
        {
            "category":"Manufacturing",
            "subcategory":"Electronics",
            "type":"Manufacturing & Wholesale Goods"
        }
    ],
    "sg:phone":"+1 206 850 9521",
    "sg:postcode":"98106",
    "sg:province":"WA",
    "sg:tags":[
        "manufacture",
        "molecular",
        "devices"
    ],
    "wof:name":"Immsolv LLC",
    "wof:placetype":"venue"
},
  "geometry": {"coordinates":[-122.358098,47.568482],"type":"Point"}
}