{
  "type": "Feature",
  "properties": {
    "addr:full":"20350 Van Dyke Rd SW Rochester WA 98579",
    "addr:housenumber":"20350",
    "addr:postcode":"98579",
    "addr:street":"Van Dyke Rd Sw",
    "iso:country":"US",
    "sg:address":"20350 Van Dyke Rd SW",
    "sg:city":"Rochester",
    "sg:classifiers":[
        {
            "category":"Real Estate",
            "subcategory":"Real Estate Agent",
            "type":"Services"
        }
    ],
    "sg:phone":"+1 360 273 5621",
    "sg:postcode":"98579",
    "sg:province":"WA",
    "wof:name":"Lawrence N Benfield",
    "wof:placetype":"venue"
},
  "geometry": {"coordinates":[-123.150137,46.791119],"type":"Point"}
}