{
  "type": "Feature",
  "properties": {
    "addr:full":"1800 S Main St Seattle WA 98122",
    "addr:housenumber":"1800",
    "addr:postcode":"98122",
    "addr:street":"S Main St",
    "iso:country":"US",
    "sg:address":"1800 S Main St",
    "sg:city":"Seattle",
    "sg:classifiers":[
        {
            "category":"Park",
            "type":"Public Place"
        }
    ],
    "sg:postcode":"98122",
    "sg:province":"WA",
    "wof:name":"Pratt Park",
    "wof:placetype":"venue"
},
  "geometry": {"coordinates":[-122.31155,47.600023],"type":"Point"}
}