{
  "type": "Feature",
  "properties": {
    "addr:full":"3934 Pacific Ave SE Lacey WA 98503",
    "addr:housenumber":"3934",
    "addr:postcode":"98503",
    "addr:street":"Pacific Ave Se",
    "iso:country":"US",
    "sg:address":"3934 Pacific Ave SE",
    "sg:city":"Lacey",
    "sg:classifiers":[
        {
            "category":"Autos & Motor Vehicles",
            "subcategory":"Auto Supplies",
            "type":"Retail Goods"
        }
    ],
    "sg:phone":"+1 360 491 2100",
    "sg:postcode":"98503",
    "sg:province":"WA",
    "wof:name":"Schucks Auto Supply 4236",
    "wof:placetype":"venue"
},
  "geometry": {"coordinates":[-122.83409,47.039437],"type":"Point"}
}