{
  "type": "Feature",
  "properties": {
    "addr:full":"1902 W Francis Ave Spokane WA 99205",
    "addr:housenumber":"1902",
    "addr:postcode":"99205",
    "addr:street":"W Francis Ave",
    "iso:country":"US",
    "sg:address":"1902 W Francis Ave",
    "sg:city":"Spokane",
    "sg:classifiers":[
        {
            "category":"Restaurant",
            "type":"Food & Drink"
        }
    ],
    "sg:menulink":"http://www.allmenus.com/wa/spokane/145322-subway/menu/",
    "sg:phone":"+1 509 328 1213",
    "sg:postcode":"99205",
    "sg:province":"WA",
    "sg:tags":[
        "american",
        "sandwich"
    ],
    "wof:name":"Subway",
    "wof:placetype":"venue"
},
  "geometry": {"coordinates":[-117.439943,47.715445],"type":"Point"}
}