{
  "type": "Feature",
  "properties": {
    "addr:full":"3723 6th Ave Tacoma WA 98406",
    "addr:housenumber":"3723",
    "addr:postcode":"98406",
    "addr:street":"6Th Ave",
    "iso:country":"US",
    "sg:address":"3723 6th Ave",
    "sg:city":"Tacoma",
    "sg:classifiers":[
        {
            "category":"Retail",
            "subcategory":"Auto Repair",
            "type":"Services"
        }
    ],
    "sg:phone":"+1 253 759 2044",
    "sg:postcode":"98406",
    "sg:province":"WA",
    "wof:name":"Precision Automotive & Transm",
    "wof:placetype":"venue"
},
  "geometry": {"coordinates":[-122.486363,47.255357],"type":"Point"}
}