{
  "type": "Feature",
  "properties": {
    "addr:full":"3814 Prestwick Ln SE Olympia WA 98501",
    "addr:housenumber":"3814",
    "addr:postcode":"98501",
    "addr:street":"Prestwick Ln Se",
    "iso:country":"US",
    "sg:address":"3814 Prestwick Ln SE",
    "sg:city":"Olympia",
    "sg:classifiers":[
        {
            "category":"Personal",
            "subcategory":"Beauty Salon",
            "type":"Services"
        },
        {
            "category":"Personal",
            "subcategory":"Barber",
            "type":"Services"
        },
        {
            "category":"Personal",
            "subcategory":"Hair Removal",
            "type":"Services"
        },
        {
            "category":"Personal",
            "subcategory":"Day Spa",
            "type":"Services"
        },
        {
            "category":"Personal",
            "subcategory":"Nail Salon",
            "type":"Services"
        }
    ],
    "sg:phone":"+1 360 459 7779",
    "sg:postcode":"98501",
    "sg:province":"WA",
    "wof:name":"Tuscan Sanctuary Salon & Spa",
    "wof:placetype":"venue"
},
  "geometry": {"coordinates":[-122.84324599999999,46.987832],"type":"Point"}
}