{
  "type": "Feature",
  "properties": {
    "addr:full":"1701 N 33rd Pl Mt Vernon WA 98273",
    "addr:housenumber":"1701",
    "addr:postcode":"98273",
    "addr:street":"N 33Rd Pl",
    "iso:country":"US",
    "sg:address":"1701 N 33rd Pl",
    "sg:city":"Mt Vernon",
    "sg:classifiers":[
        {
            "category":"Building & Trades",
            "subcategory":"Plumbing",
            "type":"Services"
        }
    ],
    "sg:phone":"+1 360 661 1630",
    "sg:postcode":"98273",
    "sg:province":"WA",
    "sg:tags":[
        "heating",
        "contractor"
    ],
    "wof:name":"CEM Heating Inc",
    "wof:placetype":"venue"
},
  "geometry": {"coordinates":[-122.297754,48.437138],"type":"Point"}
}