{
  "type": "Feature",
  "properties": {
    "addr:full":"10517 NE 50th Ave Vancouver WA 98686",
    "addr:housenumber":"10517",
    "addr:postcode":"98686",
    "addr:street":"Ne 50Th Ave",
    "iso:country":"US",
    "sg:address":"10517 NE 50th Ave",
    "sg:city":"Vancouver",
    "sg:classifiers":[
        {
            "category":"Professional",
            "subcategory":"Engineering",
            "type":"Services"
        }
    ],
    "sg:phone":"+1 360 571 9309",
    "sg:postcode":"98686",
    "sg:province":"WA",
    "wof:name":"C R M/C C M Engineering Inc",
    "wof:placetype":"venue"
},
  "geometry": {"coordinates":[-122.620397,45.698526],"type":"Point"}
}