{
  "type": "Feature",
  "properties": {
    "addr:full":"1101 S College Ave College Place WA 99324",
    "addr:housenumber":"1101",
    "addr:postcode":"99324",
    "addr:street":"S College Ave",
    "iso:country":"US",
    "sg:address":"1101 S College Ave",
    "sg:city":"College Place",
    "sg:classifiers":[
        {
            "category":"Building & Trades",
            "subcategory":"Landscaping Services",
            "type":"Services"
        }
    ],
    "sg:phone":"+1 509 522 4596",
    "sg:postcode":"99324",
    "sg:province":"WA",
    "sg:tags":[
        "landscape",
        "contractor"
    ],
    "wof:name":"Martinez Maintenance Irrgtn",
    "wof:placetype":"venue"
},
  "geometry": {"coordinates":[-118.38848299999999,46.039244],"type":"Point"}
}