{
  "type": "Feature",
  "properties": {
    "iso:country":"US",
    "sg:address":"15414 NE 46th St",
    "sg:city":"Vancouver",
    "sg:classifiers":[
        {
            "category":"Professional",
            "subcategory":"Business Services",
            "type":"Services"
        }
    ],
    "sg:phone":"+1 360 892 6880",
    "sg:postcode":"98682",
    "sg:province":"WA",
    "wof:name":"Grunau Enterprises",
    "wof:placetype":"venue"
},
  "geometry": {"coordinates":[-122.514212,45.655668],"type":"Point"}
}