{
  "type": "Feature",
  "properties": {
    "addr:full":"1018 S 226th St Seattle WA 98198",
    "addr:housenumber":"1018",
    "addr:postcode":"98198",
    "addr:street":"S 226Th St",
    "iso:country":"US",
    "sg:address":"1018 S 226th St",
    "sg:city":"Seattle",
    "sg:classifiers":[
        {
            "category":"Manufacturing",
            "subcategory":"Wood Products",
            "type":"Manufacturing & Wholesale Goods"
        }
    ],
    "sg:phone":"+1 206 824 1748",
    "sg:postcode":"98198",
    "sg:province":"WA",
    "sg:tags":[
        "mfg"
    ],
    "wof:name":"Door N Craft Inc",
    "wof:placetype":"venue"
},
  "geometry": {"coordinates":[-122.320072,47.399053],"type":"Point"}
}