{
  "type": "Feature",
  "properties": {
    "addr:full":"543 156th Ave SE Bellevue WA 98007",
    "addr:housenumber":"543",
    "addr:postcode":"98007",
    "addr:street":"156Th Ave Se",
    "iso:country":"US",
    "sg:address":"543 156th Ave SE",
    "sg:city":"Bellevue",
    "sg:classifiers":[
        {
            "category":"Real Estate",
            "subcategory":"Real Estate Agent",
            "type":"Services"
        },
        {
            "category":"Real Estate",
            "subcategory":"Real Estate Operator",
            "type":"Services"
        }
    ],
    "sg:phone":"+1 425 746 2900",
    "sg:postcode":"98007",
    "sg:province":"WA",
    "sg:tags":[
        "building",
        "management",
        "operation",
        "industrial",
        "commercial"
    ],
    "wof:name":"Conner & Associates",
    "wof:placetype":"venue"
},
  "geometry": {"coordinates":[-122.131265,47.604383],"type":"Point"}
}