{
  "type": "Feature",
  "properties": {
    "addr:full":"8825 231st Pl SW Edmonds WA 98026",
    "addr:housenumber":"8825",
    "addr:postcode":"98026",
    "addr:street":"231St Pl Sw",
    "iso:country":"US",
    "sg:address":"8825 231st Pl SW",
    "sg:city":"Edmonds",
    "sg:classifiers":[
        {
            "category":"Shopping",
            "subcategory":"Computers & Home Electronics",
            "type":"Retail Goods"
        }
    ],
    "sg:phone":"+1 425 350 0368",
    "sg:postcode":"98026",
    "sg:province":"WA",
    "wof:name":"Sound Satellite",
    "wof:placetype":"venue"
},
  "geometry": {"coordinates":[-122.353746,47.789279],"type":"Point"}
}