{
  "type": "Feature",
  "properties": {
    "iso:country":"US",
    "sg:address":"1124 Columbia St",
    "sg:city":"Seattle",
    "sg:classifiers":[
        {
            "category":"Manufacturing",
            "subcategory":"Chemicals & Compounds",
            "type":"Manufacturing & Wholesale Goods"
        }
    ],
    "sg:phone":"+1 206 587 0774",
    "sg:postcode":"98104",
    "sg:province":"WA",
    "sg:tags":[
        "biological",
        "product"
    ],
    "wof:name":"Finch Technologies",
    "wof:placetype":"venue"
},
  "geometry": {"coordinates":[-122.32294899999999,47.608323],"type":"Point"}
}