{
  "type": "Feature",
  "properties": {
    "addr:full":"23798 Seven Springs Dairy Rd E Davenport WA 99122",
    "addr:housenumber":"23798",
    "addr:postcode":"99122",
    "addr:street":"Seven Springs Dairy Rd E",
    "iso:country":"US",
    "sg:address":"23798 Seven Springs Dairy Rd E",
    "sg:city":"Davenport",
    "sg:classifiers":[
        {
            "category":"Shopping",
            "subcategory":"Beauty & Cosmetics",
            "type":"Retail Goods"
        }
    ],
    "sg:phone":"+1 509 253 4355",
    "sg:postcode":"99122",
    "sg:province":"WA",
    "sg:tags":[
        "perfume",
        "salons-equipment",
        "supply"
    ],
    "wof:name":"Mary Kay Cosmetics",
    "wof:placetype":"venue"
},
  "geometry": {"coordinates":[-118.497621,47.575539],"type":"Point"}
}