{
  "type": "Feature",
  "properties": {
    "addr:full":"7104 180th St SW Edmonds WA 98026",
    "addr:housenumber":"7104",
    "addr:postcode":"98026",
    "addr:street":"180Th St Sw",
    "iso:country":"US",
    "sg:address":"7104 180th St SW",
    "sg:city":"Edmonds",
    "sg:classifiers":[
        {
            "category":"Manufacturing",
            "subcategory":"Glass & Minerals",
            "type":"Manufacturing & Wholesale Goods"
        }
    ],
    "sg:phone":"+1 425 776 8061",
    "sg:postcode":"98026",
    "sg:province":"WA",
    "sg:tags":[
        "product",
        "nonmetallic",
        "mfg"
    ],
    "wof:name":"Sculpting Nature Topiary",
    "wof:placetype":"venue"
},
  "geometry": {"coordinates":[-122.32919,47.835749],"type":"Point"}
}