{
  "type": "Feature",
  "properties": {
    "addr:full":"13375 W Cloquallum Rd Elma WA 98541",
    "addr:housenumber":"13375",
    "addr:postcode":"98541",
    "addr:street":"W Cloquallum Rd",
    "iso:country":"US",
    "sg:address":"13375 W Cloquallum Rd",
    "sg:city":"Elma",
    "sg:classifiers":[
        {
            "category":"Government",
            "subcategory":"Fire Station",
            "type":"Public Place"
        }
    ],
    "sg:phone":"+1 360 482 4610",
    "sg:postcode":"98541",
    "sg:province":"WA",
    "sg:tags":[
        "department"
    ],
    "sg:website":"http://www.mcfd2.org",
    "wof:name":"Mason County Fire District 13",
    "wof:placetype":"venue"
},
  "geometry": {"coordinates":[-123.308111,47.134629],"type":"Point"}
}