{
  "type": "Feature",
  "properties": {
    "addr:full":"10600 Quil Ceda Blvd Marysville WA 98271",
    "addr:housenumber":"10600",
    "addr:postcode":"98271",
    "addr:street":"Quil Ceda Blvd",
    "iso:country":"US",
    "sg:address":"10600 Quil Ceda Blvd",
    "sg:city":"Marysville",
    "sg:classifiers":[
        {
            "category":"Bakery",
            "type":"Food & Drink"
        }
    ],
    "sg:menulink":"http://www.allmenus.com/wa/tulalip/220337-auntie-annes-pretzels/menu/",
    "sg:phone":"+1 360 654 2794",
    "sg:postcode":"98271",
    "sg:province":"WA",
    "sg:tags":[
        "american",
        "pastry"
    ],
    "wof:name":"Auntie Anne's Pretzels",
    "wof:placetype":"venue"
},
  "geometry": {"coordinates":[-122.18916299999999,48.093588],"type":"Point"}
}