{
  "type": "Feature",
  "properties": {
    "addr:full":"4210 Shincke Rd NE Olympia WA 98506",
    "addr:housenumber":"4210",
    "addr:postcode":"98506",
    "addr:street":"Shincke Rd Ne",
    "iso:country":"US",
    "sg:address":"4210 Shincke Rd NE",
    "sg:city":"Olympia",
    "sg:classifiers":[
        {
            "category":"Building & Trades",
            "subcategory":"Construction",
            "type":"Services"
        }
    ],
    "sg:phone":"+1 360 438 9355",
    "sg:postcode":"98506",
    "sg:province":"WA",
    "sg:tags":[
        "water",
        "system",
        "wells",
        "install",
        "drill"
    ],
    "wof:name":"Carpenter Drilling",
    "wof:placetype":"venue"
},
  "geometry": {"coordinates":[-122.844629,47.090983],"type":"Point"}
}