{
  "type": "Feature",
  "properties": {
    "addr:full":"4900 Highland Dr Bellevue WA 98006",
    "addr:housenumber":"4900",
    "addr:postcode":"98006",
    "addr:street":"Highland Dr",
    "iso:country":"US",
    "sg:address":"4900 Highland Dr",
    "sg:city":"Bellevue",
    "sg:classifiers":[
        {
            "category":"Social Services",
            "subcategory":"Child Care",
            "type":"Services"
        }
    ],
    "sg:phone":"+1 425 785 8774",
    "sg:postcode":"98006",
    "sg:province":"WA",
    "sg:tags":[
        "day"
    ],
    "wof:name":"Ilincas Chickadees Day Care",
    "wof:placetype":"venue"
},
  "geometry": {"coordinates":[-122.149703,47.559492],"type":"Point"}
}