{
  "type": "Feature",
  "properties": {
    "addr:full":"220 W Alder St Sequim WA 98382",
    "addr:housenumber":"220",
    "addr:postcode":"98382",
    "addr:street":"W Alder St",
    "iso:country":"US",
    "sg:address":"220 W Alder St",
    "sg:city":"Sequim",
    "sg:classifiers":[
        {
            "category":"Education",
            "subcategory":"School",
            "type":"Public Place"
        }
    ],
    "sg:phone":"+1 360 582 3400",
    "sg:postcode":"98382",
    "sg:province":"WA",
    "sg:website":"http://www.sequimschools.wednet.edu",
    "wof:name":"Sequim Middle School",
    "wof:placetype":"venue"
},
  "geometry": {"coordinates":[-123.105586,48.082399],"type":"Point"}
}