{
  "type": "Feature",
  "properties": {
    "addr:full":"3112 234th Ct SE Sammamish WA 98075",
    "addr:housenumber":"3112",
    "addr:postcode":"98075",
    "addr:street":"234Th Ct Se",
    "iso:country":"US",
    "sg:address":"3112 234th Ct SE",
    "sg:city":"Sammamish",
    "sg:classifiers":[
        {
            "category":"Professional",
            "subcategory":"Management & Consulting",
            "type":"Services"
        }
    ],
    "sg:phone":"+1 425 503 5910",
    "sg:postcode":"98075",
    "sg:province":"WA",
    "sg:tags":[
        "business"
    ],
    "wof:name":"Kch Strategies",
    "wof:placetype":"venue"
},
  "geometry": {"coordinates":[-122.02822999999999,47.5815],"type":"Point"}
}