{
  "type": "Feature",
  "properties": {
    "addr:full":"375 118th Ave SE Bellevue WA 98005",
    "addr:housenumber":"375",
    "addr:postcode":"98005",
    "addr:street":"118Th Ave Se",
    "iso:country":"US",
    "sg:address":"375 118th Ave SE",
    "sg:city":"Bellevue",
    "sg:classifiers":[
        {
            "category":"Social Services",
            "type":"Services"
        },
        {
            "category":"Personal",
            "type":"Services"
        }
    ],
    "sg:phone":"+1 206 441 3556",
    "sg:postcode":"98005",
    "sg:province":"WA",
    "sg:tags":[
        "family",
        "counselors-licensed",
        "individual",
        "marriage",
        "child",
        "professional",
        "counselor"
    ],
    "wof:name":"Bridge Beverly MS LMFT",
    "wof:placetype":"venue"
},
  "geometry": {"coordinates":[-122.182762,47.6066],"type":"Point"}
}