{
  "type": "Feature",
  "properties": {
    "addr:full":"1301 5th Ave Ste 2900 Seattle WA 98101",
    "addr:housenumber":"1301",
    "addr:postcode":"98101",
    "addr:street":"5Th Ave Ste 2900",
    "iso:country":"US",
    "sg:address":"1301 5th Ave Ste 2900",
    "sg:city":"Seattle",
    "sg:classifiers":[
        {
            "category":"Professional",
            "subcategory":"Lawyer & Legal Services",
            "type":"Services"
        }
    ],
    "sg:phone":"+1 206 623 7292",
    "sg:postcode":"98101",
    "sg:province":"WA",
    "sg:tags":[
        "attorney",
        "practice"
    ],
    "wof:name":"Volk Andrew M Atty",
    "wof:placetype":"venue"
},
  "geometry": {"coordinates":[-122.334,47.6087],"type":"Point"}
}