{
  "type": "Feature",
  "properties": {
    "addr:full":"1835 S 216th St Seattle WA 98198",
    "addr:housenumber":"1835",
    "addr:postcode":"98198",
    "addr:street":"S 216Th St",
    "iso:country":"US",
    "sg:address":"1835 S 216th St",
    "sg:city":"Seattle",
    "sg:classifiers":[
        {
            "category":"Building & Trades",
            "subcategory":"Construction",
            "type":"Services"
        }
    ],
    "sg:phone":"+1 206 779 3585",
    "sg:postcode":"98198",
    "sg:province":"WA",
    "sg:tags":[
        "hanging",
        "contractor"
    ],
    "wof:name":"Fat Brush Painting LLC",
    "wof:placetype":"venue"
},
  "geometry": {"coordinates":[-122.309236,47.408233],"type":"Point"}
}