{
  "type": "Feature",
  "properties": {
    "addr:full":"861 SW 126th St Seattle WA 98146",
    "addr:housenumber":"861",
    "addr:postcode":"98146",
    "addr:street":"Sw 126Th St",
    "iso:country":"US",
    "sg:address":"861 SW 126th St",
    "sg:city":"Seattle",
    "sg:classifiers":[
        {
            "category":"Organizations",
            "subcategory":"Religious Organization",
            "type":"Services"
        }
    ],
    "sg:phone":"+1 206 242 7370",
    "sg:postcode":"98146",
    "sg:province":"WA",
    "wof:name":"Saint Bernadette Church",
    "wof:placetype":"venue"
},
  "geometry": {"coordinates":[-122.34681999999999,47.49022],"type":"Point"}
}