{
  "type": "Feature",
  "properties": {
    "addr:full":"11505 SE 168th St Renton WA 98055",
    "addr:housenumber":"11505",
    "addr:postcode":"98055",
    "addr:street":"Se 168Th St",
    "iso:country":"US",
    "sg:address":"11505 SE 168th St",
    "sg:city":"Renton",
    "sg:classifiers":[
        {
            "category":"Food & Beverages",
            "subcategory":"Groceries & Convenience Stores",
            "type":"Retail Goods"
        }
    ],
    "sg:phone":"+1 425 271 8264",
    "sg:postcode":"98055",
    "sg:province":"WA",
    "wof:name":"7-Eleven",
    "wof:placetype":"venue"
},
  "geometry": {"coordinates":[-122.187747,47.452347],"type":"Point"}
}