{
  "type": "Feature",
  "properties": {
    "addr:full":"6000 NE 88th St Vancouver WA 98665",
    "addr:housenumber":"6000",
    "addr:postcode":"98665",
    "addr:street":"Ne 88Th St",
    "iso:country":"US",
    "sg:address":"6000 NE 88th St",
    "sg:city":"Vancouver",
    "sg:classifiers":[
        {
            "category":"Manufacturing",
            "subcategory":"Paper Products",
            "type":"Manufacturing & Wholesale Goods"
        }
    ],
    "sg:phone":"+1 360 546 1530",
    "sg:postcode":"98665",
    "sg:province":"WA",
    "sg:tags":[
        "box",
        "chemical",
        "mfg",
        "bag"
    ],
    "wof:name":"Down River Creative Packaging",
    "wof:placetype":"venue"
},
  "geometry": {"coordinates":[-122.606122,45.686111],"type":"Point"}
}