{
  "type": "Feature",
  "properties": {
    "addr:full":"5303 1st Ave S Ste 100 Seattle WA 98108",
    "addr:housenumber":"5303",
    "addr:postcode":"98108",
    "addr:street":"1St Ave S Ste 100",
    "iso:country":"US",
    "sg:address":"5303 1st Ave S Ste 100",
    "sg:city":"Seattle",
    "sg:classifiers":[
        {
            "category":"Building & Trades",
            "subcategory":"Construction",
            "type":"Services"
        }
    ],
    "sg:phone":"+1 206 418 0235",
    "sg:postcode":"98108",
    "sg:province":"WA",
    "sg:tags":[
        "contractor"
    ],
    "wof:name":"Pennon Construction",
    "wof:placetype":"venue"
},
  "geometry": {"coordinates":[-122.334694,47.55474],"type":"Point"}
}