{
  "type": "Feature",
  "properties": {
    "addr:full":"5301 NE 146th St Vancouver WA 98686",
    "addr:housenumber":"5301",
    "addr:postcode":"98686",
    "addr:street":"Ne 146Th St",
    "iso:country":"US",
    "sg:address":"5301 NE 146th St",
    "sg:city":"Vancouver",
    "sg:classifiers":[
        {
            "category":"Professional",
            "type":"Services"
        }
    ],
    "sg:phone":"+1 360 576 5400",
    "sg:postcode":"98686",
    "sg:province":"WA",
    "wof:name":"Atom Analysis Inc",
    "wof:placetype":"venue"
},
  "geometry": {"coordinates":[-122.618094,45.726829],"type":"Point"}
}