{
  "type": "Feature",
  "properties": {
    "addr:full":"11818 Meridian E Puyallup WA 98373",
    "addr:housenumber":"11818",
    "addr:postcode":"98373",
    "addr:street":"Meridian E",
    "iso:country":"US",
    "sg:address":"11818 Meridian E",
    "sg:city":"Puyallup",
    "sg:classifiers":[
        {
            "category":"Autos & Motor Vehicles",
            "subcategory":"Auto Supplies",
            "type":"Retail Goods"
        },
        {
            "category":"Wholesale",
            "subcategory":"Electrical",
            "type":"Manufacturing & Wholesale Goods"
        },
        {
            "category":"Wholesale",
            "subcategory":"Auto Parts",
            "type":"Manufacturing & Wholesale Goods"
        }
    ],
    "sg:phone":"+1 253 848 1591",
    "sg:postcode":"98373",
    "sg:province":"WA",
    "sg:tags":[
        "battery",
        "automobile",
        "accessory",
        "equipment",
        "truck",
        "engines-supplies"
    ],
    "sg:website":"http://ad.doubleclick.net/clk;221862232;45455595;j?http://www.carquest.com/carquest/store_locator.html",
    "wof:name":"CARQUEST Auto Parts",
    "wof:placetype":"venue"
},
  "geometry": {"coordinates":[-122.29295399999999,47.149151],"type":"Point"}
}