{
  "type": "Feature",
  "properties": {
    "iso:country":"US",
    "sg:address":"3112 W Kennewick Ave",
    "sg:city":"Kennewick",
    "sg:classifiers":[
        {
            "category":"Retail",
            "subcategory":"Laundry & Dry Cleaning",
            "type":"Services"
        }
    ],
    "sg:phone":"+1 509 783 7777",
    "sg:postcode":"99336",
    "sg:province":"WA",
    "sg:tags":[
        "cleaners",
        "plant",
        "drycleaning"
    ],
    "wof:name":"Tri City Cleaners",
    "wof:placetype":"venue"
},
  "geometry": {"coordinates":[-119.16229300000001,46.209528],"type":"Point"}
}