{
  "type": "Feature",
  "properties": {
    "iso:country":"US",
    "sg:address":"481 Woodall Rd",
    "sg:city":"Grandview",
    "sg:classifiers":[
        {
            "category":"Shopping",
            "type":"Retail Goods"
        }
    ],
    "sg:phone":"+1 509 882 3918",
    "sg:postcode":"98930",
    "sg:province":"WA",
    "sg:tags":[
        "merchandise"
    ],
    "wof:name":"Angels of Valley",
    "wof:placetype":"venue"
},
  "geometry": {"coordinates":[-119.915713,46.281912],"type":"Point"}
}