{
  "type": "Feature",
  "properties": {
    "addr:full":"5605 N Market St Spokane WA 99208",
    "addr:housenumber":"5605",
    "addr:postcode":"99208",
    "addr:street":"N Market St",
    "iso:country":"US",
    "sg:address":"5605 N Market St",
    "sg:city":"Spokane",
    "sg:classifiers":[
        {
            "category":"Organizations",
            "subcategory":"Religious Organization",
            "type":"Services"
        }
    ],
    "sg:phone":"+1 509 489 5605",
    "sg:postcode":"99208",
    "sg:province":"WA",
    "sg:tags":[
        "church"
    ],
    "wof:name":"Living Water Christian Fellow",
    "wof:placetype":"venue"
},
  "geometry": {"coordinates":[-117.364847,47.708965],"type":"Point"}
}