{
  "type": "Feature",
  "properties": {
    "addr:full":"35717 N Spotted Rd Clayton WA 99110",
    "addr:housenumber":"35717",
    "addr:postcode":"99110",
    "addr:street":"N Spotted Rd",
    "iso:country":"US",
    "sg:address":"35717 N Spotted Rd",
    "sg:city":"Clayton",
    "sg:classifiers":[
        {
            "category":"Freight",
            "type":"Transportation"
        }
    ],
    "sg:phone":"+1 509 276 8662",
    "sg:postcode":"99110",
    "sg:province":"WA",
    "sg:tags":[
        "commercial",
        "storage"
    ],
    "wof:name":"North Vista RV Park & Mini",
    "wof:placetype":"venue"
},
  "geometry": {"coordinates":[-117.523319,47.979008],"type":"Point"}
}