{
  "type": "Feature",
  "properties": {
    "addr:full":"15208 42nd Ave Ct NW Gig Harbor WA 98332",
    "addr:housenumber":"15208",
    "addr:postcode":"98332",
    "addr:street":"42Nd Ave Ct Nw",
    "iso:country":"US",
    "sg:address":"15208 42nd Ave Ct NW",
    "sg:city":"Gig Harbor",
    "sg:classifiers":[
        {
            "category":"Travel",
            "subcategory":"Travel Agent",
            "type":"Entertainment"
        }
    ],
    "sg:phone":"+1 253 857 7379",
    "sg:postcode":"98332",
    "sg:province":"WA",
    "sg:tags":[
        "cruise"
    ],
    "wof:name":"Specialty Cruises",
    "wof:placetype":"venue"
},
  "geometry": {"coordinates":[-122.59396,47.396744],"type":"Point"}
}