{
  "type": "Feature",
  "properties": {
    "addr:full":"3429 Airport Way S Seattle WA 98134",
    "addr:housenumber":"3429",
    "addr:postcode":"98134",
    "addr:street":"Airport Way S",
    "iso:country":"US",
    "sg:address":"3429 Airport Way S",
    "sg:city":"Seattle",
    "sg:classifiers":[
        {
            "category":"Professional",
            "type":"Services"
        }
    ],
    "sg:phone":"+1 206 464 4209",
    "sg:postcode":"98134",
    "sg:province":"WA",
    "sg:tags":[
        "establishment"
    ],
    "wof:name":"Bigtop Studio",
    "wof:placetype":"venue"
},
  "geometry": {"coordinates":[-122.32260100000001,47.572841],"type":"Point"}
}