{
  "type": "Feature",
  "properties": {
    "addr:full":"808 Bussell Rd Walla Walla WA 99362",
    "addr:housenumber":"808",
    "addr:postcode":"99362",
    "addr:street":"Bussell Rd",
    "iso:country":"US",
    "sg:address":"808 Bussell Rd",
    "sg:city":"Walla Walla",
    "sg:classifiers":[
        {
            "category":"Building & Trades",
            "subcategory":"Construction",
            "type":"Services"
        }
    ],
    "sg:phone":"+1 509 529 0145",
    "sg:postcode":"99362",
    "sg:province":"WA",
    "sg:tags":[
        "residential"
    ],
    "wof:name":"C & C Enterprises",
    "wof:placetype":"venue"
},
  "geometry": {"coordinates":[-118.406392,46.021745],"type":"Point"}
}