{
  "type": "Feature",
  "properties": {
    "addr:full":"1404 12th Ave Seattle WA 98122",
    "addr:housenumber":"1404",
    "addr:postcode":"98122",
    "addr:street":"12Th Ave",
    "iso:country":"US",
    "sg:address":"1404 12th Ave",
    "sg:city":"Seattle",
    "sg:classifiers":[
        {
            "category":"Sports & Exercise",
            "subcategory":"Playing Field",
            "type":"Entertainment"
        }
    ],
    "sg:phone":"+1 206 257 1694",
    "sg:postcode":"98122",
    "sg:province":"WA",
    "sg:tags":[
        "instruction",
        "fitness"
    ],
    "sg:website":"www.barre3.com/seattle/capitolhi...",
    "wof:name":"barre3",
    "wof:placetype":"venue"
},
  "geometry": {"coordinates":[-122.31676,47.612901],"type":"Point"}
}