{
  "type": "Feature",
  "properties": {
    "addr:full":"311 S 1st St Yakima WA 98901",
    "addr:housenumber":"311",
    "addr:postcode":"98901",
    "addr:street":"S 1St St",
    "iso:country":"US",
    "sg:address":"311 S 1st St",
    "sg:city":"Yakima",
    "sg:classifiers":[
        {
            "category":"Autos & Motor Vehicles",
            "subcategory":"Automobile Sales",
            "type":"Retail Goods"
        }
    ],
    "sg:phone":"+1 509 249 8999",
    "sg:postcode":"98901",
    "sg:province":"WA",
    "sg:tags":[
        "car",
        "dealer"
    ],
    "wof:name":"Bob Hall's Hyundai-Yakima",
    "wof:placetype":"venue"
},
  "geometry": {"coordinates":[-120.50363900000001,46.597354],"type":"Point"}
}