{
  "type": "Feature",
  "properties": {
    "addr:full":"4527 University Way NE Seattle WA 98105",
    "addr:housenumber":"4527",
    "addr:postcode":"98105",
    "addr:street":"University Way Ne",
    "iso:country":"US",
    "sg:address":"4527 University Way NE",
    "sg:city":"Seattle",
    "sg:classifiers":[
        {
            "category":"Shopping",
            "type":"Retail Goods"
        }
    ],
    "sg:phone":"+1 206 547 6614",
    "sg:postcode":"98105",
    "sg:province":"WA",
    "sg:tags":[
        "hearing",
        "equipment",
        "supply",
        "impaired"
    ],
    "wof:name":"Accu-Ear",
    "wof:placetype":"venue"
},
  "geometry": {"coordinates":[-122.31318,47.662852],"type":"Point"}
}