{
  "type": "Feature",
  "properties": {
    "addr:full":"6601 Roosevelt Way NE Seattle WA 98115",
    "addr:housenumber":"6601",
    "addr:postcode":"98115",
    "addr:street":"Roosevelt Way Ne",
    "iso:country":"US",
    "sg:address":"6601 Roosevelt Way NE",
    "sg:city":"Seattle",
    "sg:classifiers":[
        {
            "category":"Banks & Credit Unions",
            "subcategory":"Bank",
            "type":"Services"
        }
    ],
    "sg:phone":"+1 206 358 1752",
    "sg:postcode":"98115",
    "sg:province":"WA",
    "sg:tags":[
        "national",
        "commercial"
    ],
    "wof:name":"Bank Of America",
    "wof:placetype":"venue"
},
  "geometry": {"coordinates":[-122.317385,47.677282],"type":"Point"}
}