{
  "type": "Feature",
  "properties": {
    "addr:full":"1725 NW Hall Dr Pullman WA 99163",
    "addr:housenumber":"1725",
    "addr:postcode":"99163",
    "addr:street":"Nw Hall Dr",
    "iso:country":"US",
    "sg:address":"1725 NW Hall Dr",
    "sg:city":"Pullman",
    "sg:classifiers":[
        {
            "category":"Professional",
            "subcategory":"Management & Consulting",
            "type":"Services"
        }
    ],
    "sg:phone":"+1 509 332 0773",
    "sg:postcode":"99163",
    "sg:province":"WA",
    "sg:tags":[
        "professor"
    ],
    "wof:name":"Norman K Whittlesey",
    "wof:placetype":"venue"
},
  "geometry": {"coordinates":[-117.17907099999999,46.743765],"type":"Point"}
}