{
  "type": "Feature",
  "properties": {
    "addr:full":"2003 Western Ave Ste 500 Seattle WA 98121",
    "addr:housenumber":"2003",
    "addr:postcode":"98121",
    "addr:street":"Western Ave Ste 500",
    "iso:country":"US",
    "sg:address":"2003 Western Ave Ste 500",
    "sg:city":"Seattle",
    "sg:classifiers":[
        {
            "category":"Real Estate",
            "subcategory":"Real Estate Operator",
            "type":"Services"
        }
    ],
    "sg:phone":"+1 206 448 1377",
    "sg:postcode":"98121",
    "sg:province":"WA",
    "sg:tags":[
        "apartment"
    ],
    "wof:name":"Popkin Development Corporation",
    "wof:placetype":"venue"
},
  "geometry": {"coordinates":[-122.343718,47.610378],"type":"Point"}
}