{
  "type": "Feature",
  "properties": {
    "addr:full":"345 W Central Ave Spokane WA 99205",
    "addr:housenumber":"345",
    "addr:postcode":"99205",
    "addr:street":"W Central Ave",
    "iso:country":"US",
    "sg:address":"345 W Central Ave",
    "sg:city":"Spokane",
    "sg:classifiers":[
        {
            "category":"Shopping",
            "subcategory":"Gifts & Souvenirs",
            "type":"Retail Goods"
        }
    ],
    "sg:phone":"+1 509 489 1682",
    "sg:postcode":"99205",
    "sg:province":"WA",
    "wof:name":"R & R Treasures",
    "wof:placetype":"venue"
},
  "geometry": {"coordinates":[-117.417438,47.711435],"type":"Point"}
}