{
  "type": "Feature",
  "properties": {
    "addr:full":"6103 S Helena St Spokane WA 99223",
    "addr:housenumber":"6103",
    "addr:postcode":"99223",
    "addr:street":"S Helena St",
    "iso:country":"US",
    "sg:address":"6103 S Helena St",
    "sg:city":"Spokane",
    "sg:classifiers":[
        {
            "category":"Home & Garden",
            "subcategory":"Carpets & Floor Coverings",
            "type":"Retail Goods"
        }
    ],
    "sg:phone":"+1 509 448 0893",
    "sg:postcode":"99223",
    "sg:province":"WA",
    "sg:tags":[
        "building",
        "equipment",
        "installation"
    ],
    "wof:name":"Mc Gowan Enterprises",
    "wof:placetype":"venue"
},
  "geometry": {"coordinates":[-117.387119,47.598396],"type":"Point"}
}