{
  "type": "Feature",
  "properties": {
    "addr:full":"8620 Shadow Wood Dr Everett WA 98208",
    "addr:housenumber":"8620",
    "addr:postcode":"98208",
    "addr:street":"Shadow Wood Dr",
    "iso:country":"US",
    "sg:address":"8620 Shadow Wood Dr",
    "sg:city":"Everett",
    "sg:classifiers":[
        {
            "category":"Retail",
            "subcategory":"Portrait Studio",
            "type":"Services"
        }
    ],
    "sg:phone":"+1 425 337 7563",
    "sg:postcode":"98208",
    "sg:province":"WA",
    "sg:tags":[
        "photo"
    ],
    "wof:name":"Max Gruber",
    "wof:placetype":"venue"
},
  "geometry": {"coordinates":[-122.186891,47.919437],"type":"Point"}
}