{
  "type": "Feature",
  "properties": {
    "addr:full":"4649 Sunnyside Ave N # 1 Seattle WA 98103",
    "addr:housenumber":"4649",
    "addr:postcode":"98103",
    "addr:street":"Sunnyside Ave N # 1",
    "iso:country":"US",
    "sg:address":"4649 Sunnyside Ave N # 1",
    "sg:city":"Seattle",
    "sg:classifiers":[
        {
            "category":"Building & Trades",
            "subcategory":"Landscaping Services",
            "type":"Services"
        }
    ],
    "sg:phone":"+1 206 633 0224",
    "sg:postcode":"98103",
    "sg:province":"WA",
    "sg:tags":[
        "lawn",
        "maintenance"
    ],
    "wof:name":"Natural Lawn & Garden Hot",
    "wof:placetype":"venue"
},
  "geometry": {"coordinates":[-122.330122,47.664125],"type":"Point"}
}