{
  "type": "Feature",
  "properties": {
    "addr:full":"14124 W Hwy 2 Medical Lake WA 99022",
    "addr:housenumber":"14124",
    "addr:postcode":"99022",
    "addr:street":"W Hwy 2",
    "iso:country":"US",
    "sg:address":"14124 W Hwy 2",
    "sg:city":"Medical Lake",
    "sg:classifiers":[
        {
            "category":"Autos & Motor Vehicles",
            "subcategory":"Automobile Sales",
            "type":"Retail Goods"
        }
    ],
    "sg:phone":"+1 509 244 0390",
    "sg:postcode":"99022",
    "sg:province":"WA",
    "sg:tags":[
        "car",
        "dealer"
    ],
    "wof:name":"Airway Heights Truck Store",
    "wof:placetype":"venue"
},
  "geometry": {"coordinates":[-117.60484599999999,47.643042],"type":"Point"}
}