{
  "type": "Feature",
  "properties": {
    "iso:country":"US",
    "sg:address":"401 Evans Black Dr",
    "sg:city":"Seattle",
    "sg:classifiers":[
        {
            "category":"Wholesale",
            "subcategory":"Machinery & Supplies",
            "type":"Manufacturing & Wholesale Goods"
        }
    ],
    "sg:phone":"+1 206 433 8080",
    "sg:postcode":"98188",
    "sg:province":"WA",
    "sg:tags":[
        "adhesive",
        "screen",
        "printing",
        "chem",
        "specialty"
    ],
    "wof:name":"Midwest Sign Screen Prtg Sup",
    "wof:placetype":"venue"
},
  "geometry": {"coordinates":[-122.25228799999999,47.459486],"type":"Point"}
}