{
  "type": "Feature",
  "properties": {
    "addr:full":"30627 82nd Ave NW Stanwood WA 98292",
    "addr:housenumber":"30627",
    "addr:postcode":"98292",
    "addr:street":"82Nd Ave Nw",
    "iso:country":"US",
    "sg:address":"30627 82nd Ave NW",
    "sg:city":"Stanwood",
    "sg:classifiers":[
        {
            "category":"Professional",
            "subcategory":"Business Services",
            "type":"Services"
        }
    ],
    "sg:phone":"+1 360 939 0110",
    "sg:postcode":"98292",
    "sg:province":"WA",
    "wof:name":"Rehab Solutions Inc",
    "wof:placetype":"venue"
},
  "geometry": {"coordinates":[-122.343187,48.272945],"type":"Point"}
}