{
  "type": "Feature",
  "properties": {
    "addr:full":"14306 NE 53rd St Vancouver WA 98682",
    "addr:housenumber":"14306",
    "addr:postcode":"98682",
    "addr:street":"Ne 53Rd St",
    "iso:country":"US",
    "sg:address":"14306 NE 53rd St",
    "sg:city":"Vancouver",
    "sg:classifiers":[
        {
            "category":"Manufacturing",
            "subcategory":"Printing",
            "type":"Manufacturing & Wholesale Goods"
        }
    ],
    "sg:phone":"+1 360 253 9480",
    "sg:postcode":"98682",
    "sg:province":"WA",
    "sg:tags":[
        "lithographic",
        "commercial"
    ],
    "wof:name":"My Sister & I Printing Designs",
    "wof:placetype":"venue"
},
  "geometry": {"coordinates":[-122.525886,45.661103],"type":"Point"}
}