{
  "type": "Feature",
  "properties": {
    "addr:full":"4717 S 19th St Tacoma WA 98405",
    "addr:housenumber":"4717",
    "addr:postcode":"98405",
    "addr:street":"S 19Th St",
    "iso:country":"US",
    "sg:address":"4717 S 19th St",
    "sg:city":"Tacoma",
    "sg:classifiers":[
        {
            "category":"Health Services",
            "subcategory":"Doctor",
            "type":"Services"
        }
    ],
    "sg:phone":"+1 253 248 2020",
    "sg:postcode":"98405",
    "sg:province":"WA",
    "sg:tags":[
        "physician",
        "surgeon"
    ],
    "wof:name":"Eye M D's Of Puget Sound",
    "wof:placetype":"venue"
},
  "geometry": {"coordinates":[-122.499796,47.242938],"type":"Point"}
}