{
  "type": "Feature",
  "properties": {
    "addr:full":"5031 University Way NE Seattle WA 98105",
    "addr:housenumber":"5031",
    "addr:postcode":"98105",
    "addr:street":"University Way Ne",
    "iso:country":"US",
    "sg:address":"5031 University Way NE",
    "sg:city":"Seattle",
    "sg:classifiers":[
        {
            "category":"Shopping",
            "subcategory":"Shoes",
            "type":"Retail Goods"
        }
    ],
    "sg:phone":"+1 206 466 8612",
    "sg:postcode":"98105",
    "sg:province":"WA",
    "wof:name":"Graceful Feet",
    "wof:placetype":"venue"
},
  "geometry": {"coordinates":[-122.313129,47.666201],"type":"Point"}
}