{
  "type": "Feature",
  "properties": {
    "addr:full":"10415 Rosewood Ave Everett WA 98204",
    "addr:housenumber":"10415",
    "addr:postcode":"98204",
    "addr:street":"Rosewood Ave",
    "iso:country":"US",
    "sg:address":"10415 Rosewood Ave",
    "sg:city":"Everett",
    "sg:classifiers":[
        {
            "category":"Building & Trades",
            "subcategory":"Construction",
            "type":"Services"
        }
    ],
    "sg:phone":"+1 425 347 8485",
    "sg:postcode":"98204",
    "sg:province":"WA",
    "sg:tags":[
        "painting",
        "contractor"
    ],
    "wof:name":"Trew Colors",
    "wof:placetype":"venue"
},
  "geometry": {"coordinates":[-122.25977899999999,47.902788],"type":"Point"}
}