{
  "type": "Feature",
  "properties": {
    "addr:full":"5010 May St NW Bremerton WA 98311",
    "addr:housenumber":"5010",
    "addr:postcode":"98311",
    "addr:street":"May St Nw",
    "iso:country":"US",
    "sg:address":"5010 May St NW",
    "sg:city":"Bremerton",
    "sg:classifiers":[
        {
            "category":"Autos & Motor Vehicles",
            "subcategory":"Fuel & Gas Station",
            "type":"Retail Goods"
        },
        {
            "category":"Food & Beverages",
            "subcategory":"Groceries & Convenience Stores",
            "type":"Retail Goods"
        }
    ],
    "sg:phone":"+1 360 479 3323",
    "sg:postcode":"98311",
    "sg:province":"WA",
    "sg:website":"http://www.texaco.com/",
    "wof:name":"Texaco",
    "wof:placetype":"venue"
},
  "geometry": {"coordinates":[-122.655383,47.607277],"type":"Point"}
}