{
  "type": "Feature",
  "properties": {
    "addr:full":"12604 NE 76th St Vancouver WA 98682",
    "addr:housenumber":"12604",
    "addr:postcode":"98682",
    "addr:street":"Ne 76Th St",
    "iso:country":"US",
    "sg:address":"12604 NE 76th St",
    "sg:city":"Vancouver",
    "sg:classifiers":[
        {
            "category":"Building & Trades",
            "subcategory":"Construction",
            "type":"Services"
        }
    ],
    "sg:phone":"+1 360 256 3379",
    "sg:postcode":"98682",
    "sg:province":"WA",
    "sg:tags":[
        "remodeling",
        "contractor"
    ],
    "wof:name":"Custom Remodeling Co",
    "wof:placetype":"venue"
},
  "geometry": {"coordinates":[-122.54207100000001,45.677578],"type":"Point"}
}