{
  "type": "Feature",
  "properties": {
    "addr:full":"11751 Lancaster Rd Saint John WA 99171",
    "addr:housenumber":"11751",
    "addr:postcode":"wa 99171",
    "addr:street":"Lancaster Rd",
    "iso:country":"US",
    "sg:address":"11751 Lancaster Rd",
    "sg:city":"Saint John",
    "sg:classifiers":[
        {
            "category":"Farming",
            "subcategory":"Farm",
            "type":"Manufacturing & Wholesale Goods"
        }
    ],
    "sg:phone":"+1 509 648 3922",
    "sg:postcode":"99171",
    "sg:province":"WA",
    "sg:tags":[
        "crop",
        "general"
    ],
    "wof:name":"Jr Smith Farms Inc",
    "wof:placetype":"venue"
},
  "geometry": {"coordinates":[-117.744146,47.003078],"type":"Point"}
}