{
  "type": "Feature",
  "properties": {
    "addr:full":"2366 Eastlake Ave E Seattle WA 98102",
    "addr:housenumber":"2366",
    "addr:postcode":"98102",
    "addr:street":"Eastlake Ave E",
    "iso:country":"US",
    "sg:address":"2366 Eastlake Ave E",
    "sg:city":"Seattle",
    "sg:classifiers":[
        {
            "category":"Education",
            "subcategory":"Special Training",
            "type":"Public Place"
        }
    ],
    "sg:phone":"+1 206 547 3914",
    "sg:postcode":"98102",
    "sg:province":"WA",
    "wof:name":"Kadima Community Sunday School",
    "wof:placetype":"venue"
},
  "geometry": {"coordinates":[-122.325816,47.641261],"type":"Point"}
}