{
  "type": "Feature",
  "properties": {
    "addr:full":"3606 174th Avenue Kp N Kp N Kpn Lakebay WA 98349",
    "addr:housenumber":"3606",
    "addr:postcode":"98349",
    "addr:street":"174Th Avenue Kp N Kp N;Lakebay",
    "iso:country":"US",
    "sg:address":"3606 174th Avenue Kp N Kp N Kpn",
    "sg:city":"Lakebay",
    "sg:classifiers":[
        {
            "category":"Building & Trades",
            "subcategory":"Construction",
            "type":"Services"
        },
        {
            "category":"Manufacturing",
            "subcategory":"Building Materials",
            "type":"Manufacturing & Wholesale Goods"
        }
    ],
    "sg:phone":"+1 253 884 9058",
    "sg:postcode":"98349",
    "sg:province":"WA",
    "sg:tags":[
        "cabinetmakers-commercial",
        "industrial",
        "maker",
        "cabinet"
    ],
    "wof:name":"Advanced Carpentry Cabinet & Trim",
    "wof:placetype":"venue"
},
  "geometry": {"coordinates":[-122.769801,47.291471],"type":"Point"}
}