{
  "type": "Feature",
  "properties": {
    "addr:full":"1210 Canyon Rd Ellensburg WA 98926",
    "addr:housenumber":"1210",
    "addr:postcode":"98926",
    "addr:street":"Canyon Rd",
    "iso:country":"US",
    "sg:address":"1210 Canyon Rd",
    "sg:city":"Ellensburg",
    "sg:classifiers":[
        {
            "category":"Restaurant",
            "type":"Food & Drink"
        }
    ],
    "sg:phone":"+1 509 925 3474",
    "sg:postcode":"98926",
    "sg:province":"WA",
    "sg:tags":[
        "seafood"
    ],
    "wof:name":"Skippers 5284",
    "wof:placetype":"venue"
},
  "geometry": {"coordinates":[-120.540921,46.97429],"type":"Point"}
}