{
  "type": "Feature",
  "properties": {
    "addr:full":"21740 NE 181st Pl Woodinville WA 98077",
    "addr:housenumber":"21740",
    "addr:postcode":"98077",
    "addr:street":"Ne 181St Pl",
    "iso:country":"US",
    "sg:address":"21740 NE 181st Pl",
    "sg:city":"Woodinville",
    "sg:classifiers":[
        {
            "category":"Professional",
            "subcategory":"Computer Services",
            "type":"Services"
        }
    ],
    "sg:phone":"+1 425 788 7870",
    "sg:postcode":"98077",
    "sg:province":"WA",
    "sg:tags":[
        "prepackaged",
        "software"
    ],
    "wof:name":"Homerun Software Systems LLC",
    "wof:placetype":"venue"
},
  "geometry": {"coordinates":[-122.048559,47.759389],"type":"Point"}
}