{
  "type": "Feature",
  "properties": {
    "addr:full":"10744 5th Ave NE Seattle WA 98125",
    "addr:housenumber":"10744",
    "addr:postcode":"98125",
    "addr:street":"5Th Ave Ne",
    "iso:country":"US",
    "sg:address":"10744 5th Ave NE",
    "sg:city":"Seattle",
    "sg:classifiers":[
        {
            "category":"Food & Beverages",
            "subcategory":"Liquor & Beverages",
            "type":"Retail Goods"
        }
    ],
    "sg:phone":"+1 206 368 4581",
    "sg:postcode":"98125",
    "sg:province":"WA",
    "sg:tags":[
        "beer",
        "spirit",
        "wine"
    ],
    "sg:website":"www.liq.wa.gov/",
    "wof:name":"Washington Liquor Store #69",
    "wof:placetype":"venue"
},
  "geometry": {"coordinates":[-122.32307400000001,47.707836],"type":"Point"}
}