{
  "type": "Feature",
  "properties": {
    "addr:full":"211 Pace Dr East Wenatchee WA 98802",
    "addr:housenumber":"211",
    "addr:postcode":"98802",
    "addr:street":"Pace Dr",
    "iso:country":"US",
    "sg:address":"211 Pace Dr",
    "sg:city":"East Wenatchee",
    "sg:classifiers":[
        {
            "category":"Real Estate",
            "subcategory":"Real Estate Agent",
            "type":"Services"
        }
    ],
    "sg:phone":"+1 509 884 1298",
    "sg:postcode":"98802",
    "sg:province":"WA",
    "wof:name":"William Marlow",
    "wof:placetype":"venue"
},
  "geometry": {"coordinates":[-120.279843,47.402997],"type":"Point"}
}