{
  "type": "Feature",
  "properties": {
    "addr:full":"2001 N Columbia Center Blvd Richland WA 99352",
    "addr:housenumber":"2001",
    "addr:postcode":"99352",
    "addr:street":"N Columbia Center Blvd",
    "iso:country":"US",
    "sg:address":"2001 N Columbia Center Blvd",
    "sg:city":"Richland",
    "sg:classifiers":[
        {
            "category":"Professional",
            "subcategory":"Lawyer & Legal Services",
            "type":"Services"
        }
    ],
    "sg:phone":"+1 509 736 0866",
    "sg:postcode":"99352",
    "sg:province":"WA",
    "sg:tags":[
        "attorney"
    ],
    "wof:name":"Calbom & Schwab",
    "wof:placetype":"venue"
},
  "geometry": {"coordinates":[-119.22335699999999,46.231465],"type":"Point"}
}