{
  "type": "Feature",
  "properties": {
    "addr:full":"900 N 155th St Shoreline WA 98133",
    "addr:housenumber":"900",
    "addr:postcode":"98133",
    "addr:street":"N 155Th St",
    "iso:country":"US",
    "sg:address":"900 N 155th St",
    "sg:city":"Shoreline",
    "sg:classifiers":[
        {
            "category":"Home & Garden",
            "subcategory":"Building Materials",
            "type":"Retail Goods"
        }
    ],
    "sg:phone":"+1 206 365 7320",
    "sg:postcode":"98133",
    "sg:province":"WA",
    "sg:tags":[
        "contractor",
        "floor",
        "painting",
        "covering"
    ],
    "sg:website":"http://seattle.citysearch.com/profile/external/10801745/shoreline_wa/sherwin_williams.html?publisher=yellowpages&reference_id=1&placement=ypwebsitemip",
    "wof:name":"Sherwin-Williams",
    "wof:placetype":"venue"
},
  "geometry": {"coordinates":[-122.346977,47.74155],"type":"Point"}
}