{
  "type": "Feature",
  "properties": {
    "addr:full":"16713 Mountain View Rd Mount Vernon WA 98274",
    "addr:housenumber":"16713",
    "addr:postcode":"98274",
    "addr:street":"Mountain View Rd",
    "iso:country":"US",
    "sg:address":"16713 Mountain View Rd",
    "sg:city":"Mount Vernon",
    "sg:classifiers":[
        {
            "category":"Retail",
            "subcategory":"Laundry & Dry Cleaning",
            "type":"Services"
        }
    ],
    "sg:phone":"+1 360 422 5462",
    "sg:postcode":"98274",
    "sg:province":"WA",
    "wof:name":"Seams Bonnified",
    "wof:placetype":"venue"
},
  "geometry": {"coordinates":[-122.25315999999999,48.403494],"type":"Point"}
}