{
  "type": "Feature",
  "properties": {
    "addr:full":"1725 S Gold St Centralia WA 98531",
    "addr:housenumber":"1725",
    "addr:postcode":"98531",
    "addr:street":"S Gold St",
    "iso:country":"US",
    "sg:address":"1725 S Gold St",
    "sg:city":"Centralia",
    "sg:classifiers":[
        {
            "category":"Professional",
            "subcategory":"Business Services",
            "type":"Services"
        }
    ],
    "sg:phone":"+1 360 736 6256",
    "sg:postcode":"98531",
    "sg:province":"WA",
    "wof:name":"Southwest Wash",
    "wof:placetype":"venue"
},
  "geometry": {"coordinates":[-122.957401,46.696161],"type":"Point"}
}