{
  "type": "Feature",
  "properties": {
    "addr:full":"906 178th Ave NE Bellevue WA 98008",
    "addr:housenumber":"906",
    "addr:postcode":"98008",
    "addr:street":"178Th Ave Ne",
    "iso:country":"US",
    "sg:address":"906 178th Ave NE",
    "sg:city":"Bellevue",
    "sg:classifiers":[
        {
            "category":"Professional",
            "subcategory":"Secretarial Services",
            "type":"Services"
        },
        {
            "category":"Professional",
            "subcategory":"Employment Agencies",
            "type":"Services"
        }
    ],
    "sg:phone":"+1 425 746 4056",
    "sg:postcode":"98008",
    "sg:province":"WA",
    "sg:tags":[
        "typing"
    ],
    "wof:name":"Timely Transcription Services",
    "wof:placetype":"venue"
},
  "geometry": {"coordinates":[-122.103984,47.617984],"type":"Point"}
}