{
  "type": "Feature",
  "properties": {
    "addr:full":"2033 Division St Bellingham WA 98226",
    "addr:housenumber":"2033",
    "addr:postcode":"98226",
    "addr:street":"Division St",
    "iso:country":"US",
    "sg:address":"2033 Division St",
    "sg:city":"Bellingham",
    "sg:classifiers":[
        {
            "category":"Shopping",
            "subcategory":"Gifts & Souvenirs",
            "type":"Retail Goods"
        },
        {
            "category":"Shopping",
            "subcategory":"Music",
            "type":"Retail Goods"
        },
        {
            "category":"Utilities",
            "subcategory":"Mobile Phone",
            "type":"Services"
        },
        {
            "category":"Coffee & Tea",
            "type":"Food & Drink"
        },
        {
            "category":"Shopping",
            "subcategory":"Books",
            "type":"Retail Goods"
        },
        {
            "category":"Wholesale",
            "subcategory":"Books, Periodicals, & Newspapers",
            "type":"Manufacturing & Wholesale Goods"
        }
    ],
    "sg:phone":"+1 360 671 3618",
    "sg:postcode":"98226",
    "sg:province":"WA",
    "sg:tags":[
        "shop",
        "restaurant",
        "espresso",
        "hotspot",
        "magazine",
        "wi-fi",
        "store"
    ],
    "sg:website":"http://www.borders.com",
    "wof:name":"Borders",
    "wof:placetype":"venue"
},
  "geometry": {"coordinates":[-122.450137,48.782231],"type":"Point"}
}