{
  "type": "Feature",
  "properties": {
    "addr:full":"390 S Park St Lynden WA 98264",
    "addr:housenumber":"390",
    "addr:postcode":"98264",
    "addr:street":"S Park St",
    "iso:country":"US",
    "sg:address":"390 S Park St",
    "sg:city":"Lynden",
    "sg:classifiers":[
        {
            "category":"Building & Trades",
            "subcategory":"Landscaping Services",
            "type":"Services"
        }
    ],
    "sg:phone":"+1 360 354 3441",
    "sg:postcode":"98264",
    "sg:province":"WA",
    "wof:name":"Nunnikhoven Ldscp Maint LLC",
    "wof:placetype":"venue"
},
  "geometry": {"coordinates":[-122.457413,48.950795],"type":"Point"}
}