{
  "type": "Feature",
  "properties": {
    "addr:full":"4162 Jackson Hwy Chehalis WA 98532",
    "addr:housenumber":"4162",
    "addr:postcode":"98532",
    "addr:street":"Jackson Hwy",
    "iso:country":"US",
    "sg:address":"4162 Jackson Hwy",
    "sg:city":"Chehalis",
    "sg:classifiers":[
        {
            "category":"Building & Trades",
            "subcategory":"Landscaping Services",
            "type":"Services"
        }
    ],
    "sg:phone":"+1 360 262 0525",
    "sg:postcode":"98532",
    "sg:province":"WA",
    "wof:name":"Schilling Gardens",
    "wof:placetype":"venue"
},
  "geometry": {"coordinates":[-122.822948,46.549064],"type":"Point"}
}