{
  "type": "Feature",
  "properties": {
    "addr:full":"5637 S 295th Pl Auburn WA 98001",
    "addr:housenumber":"5637",
    "addr:postcode":"98001",
    "addr:street":"S 295Th Pl",
    "iso:country":"US",
    "sg:address":"5637 S 295th Pl",
    "sg:city":"Auburn",
    "sg:classifiers":[
        {
            "category":"Taxi",
            "type":"Transportation"
        }
    ],
    "sg:phone":"+1 253 872 5600",
    "sg:postcode":"98001",
    "sg:province":"WA",
    "wof:name":"Yellow Cab",
    "wof:placetype":"venue"
},
  "geometry": {"coordinates":[-122.26306,47.337084],"type":"Point"}
}