{
  "type": "Feature",
  "properties": {
    "addr:full":"811 112th St SW Apt H201 Everett WA 98204",
    "addr:housenumber":"811",
    "addr:postcode":"98204",
    "addr:street":"112Th St Sw;H201",
    "iso:country":"US",
    "sg:address":"811 112th St SW Apt H201",
    "sg:city":"Everett",
    "sg:classifiers":[
        {
            "category":"Shopping",
            "subcategory":"Hobbies, Toys, & Games",
            "type":"Retail Goods"
        }
    ],
    "sg:phone":"+1 425 348 7036",
    "sg:postcode":"98204",
    "sg:province":"WA",
    "sg:tags":[
        "shop",
        "hobby",
        "model",
        "supply"
    ],
    "wof:name":"Bears Playground",
    "wof:placetype":"venue"
},
  "geometry": {"coordinates":[-122.24539300000001,47.896448],"type":"Point"}
}