{
  "type": "Feature",
  "properties": {
    "iso:country":"US",
    "sg:address":"14400 Bel Red Rd",
    "sg:city":"Bellevue",
    "sg:classifiers":[
        {
            "category":"Banks & Credit Unions",
            "subcategory":"Financial Services",
            "type":"Services"
        }
    ],
    "sg:phone":"+1 425 562 1455",
    "sg:postcode":"98007",
    "sg:province":"WA",
    "sg:tags":[
        "company",
        "holding"
    ],
    "wof:name":"North-West Industries",
    "wof:placetype":"venue"
},
  "geometry": {"coordinates":[-122.143101,47.626512],"type":"Point"}
}