{
  "type": "Feature",
  "properties": {
    "addr:full":"16928 Woodinville Redmond Rd NE Woodinville WA 98072",
    "addr:housenumber":"16928",
    "addr:postcode":"98072",
    "addr:street":"Woodinville Redmond Rd Ne",
    "iso:country":"US",
    "sg:address":"16928 Woodinville Redmond Rd NE",
    "sg:city":"Woodinville",
    "sg:classifiers":[
        {
            "category":"Insurance",
            "subcategory":"Insurance Agent",
            "type":"Services"
        }
    ],
    "sg:phone":"+1 425 485 9598",
    "sg:postcode":"98072",
    "sg:province":"WA",
    "sg:website":"www.ushomegrants.com",
    "wof:name":"Federal Realty Group",
    "wof:placetype":"venue"
},
  "geometry": {"coordinates":[-122.16776299999999,47.750856],"type":"Point"}
}