{
  "type": "Feature",
  "properties": {
    "addr:full":"20112 SE 20th Pl Sammamish WA 98075",
    "addr:postcode":"20112;98075",
    "addr:street":"Se 20Th Pl",
    "iso:country":"US",
    "sg:address":"20112 SE 20th Pl",
    "sg:city":"Sammamish",
    "sg:classifiers":[
        {
            "category":"Professional",
            "subcategory":"Computer Services",
            "type":"Services"
        }
    ],
    "sg:phone":"+1 425 241 3940",
    "sg:postcode":"98075",
    "sg:province":"WA",
    "sg:tags":[
        "communications",
        "engineering",
        "consulting",
        "network",
        "system"
    ],
    "wof:name":"Avaliant LLC",
    "wof:placetype":"venue"
},
  "geometry": {"coordinates":[-122.07152499999999,47.591368],"type":"Point"}
}