{
  "type": "Feature",
  "properties": {
    "addr:full":"6708 Carleton Ave S Seattle WA 98108",
    "addr:housenumber":"6708",
    "addr:postcode":"98108",
    "addr:street":"Carleton Ave S",
    "iso:country":"US",
    "sg:address":"6708 Carleton Ave S",
    "sg:city":"Seattle",
    "sg:classifiers":[
        {
            "category":"Wholesale",
            "subcategory":"Non-durable Goods",
            "type":"Manufacturing & Wholesale Goods"
        }
    ],
    "sg:phone":"+1 206 767 2700",
    "sg:postcode":"98108",
    "sg:province":"WA",
    "sg:tags":[
        "dry",
        "goods-wholesale"
    ],
    "wof:name":"A & W Wholesale & Retail Supply",
    "wof:placetype":"venue"
},
  "geometry": {"coordinates":[-122.321696,47.542524],"type":"Point"}
}