{
  "type": "Feature",
  "properties": {
    "iso:country":"US",
    "sg:address":"4215 23rd Ave W",
    "sg:city":"Seattle",
    "sg:classifiers":[
        {
            "category":"Shopping",
            "subcategory":"Bicycles & Sporting Goods",
            "type":"Retail Goods"
        }
    ],
    "sg:phone":"+1 206 213 0823",
    "sg:postcode":"98199",
    "sg:province":"WA",
    "sg:tags":[
        "tackle",
        "fishing"
    ],
    "sg:website":"www.hampidjanusa.com",
    "wof:name":"Hampidjan USA Inc",
    "wof:placetype":"venue"
},
  "geometry": {"coordinates":[-122.38602400000001,47.659341],"type":"Point"}
}