{
  "type": "Feature",
  "properties": {
    "addr:full":"311 Pocket Ln Port Townsend WA 98368",
    "addr:housenumber":"311",
    "addr:postcode":"98368",
    "addr:street":"Pocket Ln",
    "iso:country":"US",
    "sg:address":"311 Pocket Ln",
    "sg:city":"Port Townsend",
    "sg:classifiers":[
        {
            "category":"Professional",
            "subcategory":"Management & Consulting",
            "type":"Services"
        }
    ],
    "sg:phone":"+1 360 385 4889",
    "sg:postcode":"98368",
    "sg:province":"WA",
    "wof:name":"Keith Wheller Consulting",
    "wof:placetype":"venue"
},
  "geometry": {"coordinates":[-122.876766,48.0824],"type":"Point"}
}