{
  "type": "Feature",
  "properties": {
    "addr:full":"164 S Washington St # 600 Spokane WA 99201",
    "addr:housenumber":"164",
    "addr:postcode":"99201",
    "addr:street":"S Washington St # 600",
    "iso:country":"US",
    "sg:address":"164 S Washington St # 600",
    "sg:city":"Spokane",
    "sg:classifiers":[
        {
            "category":"Home & Garden",
            "subcategory":"Building Materials",
            "type":"Retail Goods"
        },
        {
            "category":"Manufacturing",
            "subcategory":"Building Materials",
            "type":"Manufacturing & Wholesale Goods"
        }
    ],
    "sg:phone":"+1 509 838 8060",
    "sg:postcode":"99201",
    "sg:province":"WA",
    "sg:tags":[
        "materials-wholesale",
        "manufacturer"
    ],
    "wof:name":"Greg Shaw & Associates",
    "wof:placetype":"venue"
},
  "geometry": {"coordinates":[-117.41802199999999,47.655164],"type":"Point"}
}