{
  "type": "Feature",
  "properties": {
    "addr:full":"819 N Argonne Rd Spokane Valley WA 99212",
    "addr:housenumber":"819",
    "addr:postcode":"99212",
    "addr:street":"N Argonne Rd",
    "iso:country":"US",
    "sg:address":"819 N Argonne Rd",
    "sg:city":"Spokane Valley",
    "sg:classifiers":[
        {
            "category":"Professional",
            "subcategory":"Accounting & Tax Preparation",
            "type":"Services"
        }
    ],
    "sg:phone":"+1 509 535 7160",
    "sg:postcode":"99212",
    "sg:province":"WA",
    "sg:tags":[
        "bookkeeping",
        "general"
    ],
    "wof:name":"Ferguson Accounting Svc",
    "wof:placetype":"venue"
},
  "geometry": {"coordinates":[-117.282893,47.665882],"type":"Point"}
}