{
  "type": "Feature",
  "properties": {
    "iso:country":"US",
    "sg:address":"8916 Randall Dr NW",
    "sg:city":"Gig Harbor",
    "sg:classifiers":[
        {
            "category":"Shopping",
            "type":"Retail Goods"
        }
    ],
    "sg:phone":"+1 253 858 9077",
    "sg:postcode":"98332",
    "sg:province":"WA",
    "sg:tags":[
        "miscellaneous",
        "store"
    ],
    "wof:name":"Moss",
    "wof:placetype":"venue"
},
  "geometry": {"coordinates":[-122.582474,47.34382],"type":"Point"}
}