{
  "type": "Feature",
  "properties": {
    "addr:full":"10030 Silverdale Way NW Silverdale WA 98383",
    "addr:housenumber":"10030",
    "addr:postcode":"98383",
    "addr:street":"Silverdale Way Nw",
    "iso:country":"US",
    "sg:address":"10030 Silverdale Way NW",
    "sg:city":"Silverdale",
    "sg:classifiers":[
        {
            "category":"Professional",
            "type":"Services"
        }
    ],
    "sg:phone":"+1 360 613 9988",
    "sg:postcode":"98383",
    "sg:province":"WA",
    "wof:name":"Roxio Inc",
    "wof:placetype":"venue"
},
  "geometry": {"coordinates":[-122.68776699999999,47.656277],"type":"Point"}
}