{
  "type": "Feature",
  "properties": {
    "addr:full":"4323 Rucker Ave Everett WA 98203",
    "addr:housenumber":"4323",
    "addr:postcode":"98203",
    "addr:street":"Rucker Ave",
    "iso:country":"US",
    "sg:address":"4323 Rucker Ave",
    "sg:city":"Everett",
    "sg:classifiers":[
        {
            "category":"Personal",
            "type":"Services"
        }
    ],
    "sg:phone":"+1 425 327 8585",
    "sg:postcode":"98203",
    "sg:province":"WA",
    "sg:tags":[
        "therapist",
        "massage"
    ],
    "wof:name":"Kitty Granger",
    "wof:placetype":"venue"
},
  "geometry": {"coordinates":[-122.210554,47.959537],"type":"Point"}
}