{
  "type": "Feature",
  "properties": {
    "addr:full":"700 Holly St Coulee Dam WA 99116",
    "addr:housenumber":"700",
    "addr:postcode":"99116",
    "addr:street":"Holly St;Dam",
    "iso:country":"US",
    "sg:address":"700 Holly St",
    "sg:city":"Coulee Dam",
    "sg:classifiers":[
        {
            "category":"Shopping",
            "subcategory":"Used Merchandise",
            "type":"Retail Goods"
        }
    ],
    "sg:phone":"+1 509 633 2294",
    "sg:postcode":"99116",
    "sg:province":"WA",
    "wof:name":"White Cottage Antiques",
    "wof:placetype":"venue"
},
  "geometry": {"coordinates":[-118.97596900000001,47.968648],"type":"Point"}
}