{
  "type": "Feature",
  "properties": {
    "addr:full":"515 1st Ave W Seattle WA 98119",
    "addr:housenumber":"515",
    "addr:postcode":"98119",
    "addr:street":"1St Ave W",
    "iso:country":"US",
    "sg:address":"515 1st Ave W",
    "sg:city":"Seattle",
    "sg:classifiers":[
        {
            "category":"Professional",
            "subcategory":"Business Services",
            "type":"Services"
        }
    ],
    "sg:phone":"+1 206 378 4431",
    "sg:postcode":"98119",
    "sg:province":"WA",
    "wof:name":"Heidi L Alhadeff",
    "wof:placetype":"venue"
},
  "geometry": {"coordinates":[-122.358093,47.6244],"type":"Point"}
}