{
  "type": "Feature",
  "properties": {
    "addr:full":"100 W Harrison Street Seattle WA 98119",
    "addr:housenumber":"100",
    "addr:postcode":"98119",
    "addr:street":"W Harrison Street",
    "iso:country":"US",
    "sg:address":"100 W Harrison Street",
    "sg:city":"Seattle",
    "sg:classifiers":[
        {
            "category":"Organizations",
            "subcategory":"Non-profit Organization",
            "type":"Services"
        }
    ],
    "sg:phone":"+1 206 270 0072",
    "sg:postcode":"98119",
    "sg:province":"WA",
    "sg:tags":[
        "service/non-profit",
        "community"
    ],
    "sg:website":"www.casams.org",
    "wof:name":"National Casa",
    "wof:placetype":"venue"
},
  "geometry": {"coordinates":[-122.35806100000001,47.622138],"type":"Point"}
}