{
  "type": "Feature",
  "properties": {
    "addr:full":"2801 Alaskan Way Seattle WA 98121",
    "addr:housenumber":"2801",
    "addr:postcode":"98121",
    "addr:street":"Alaskan Way",
    "iso:country":"US",
    "sg:address":"2801 Alaskan Way",
    "sg:city":"Seattle",
    "sg:classifiers":[
        {
            "category":"Real Estate",
            "subcategory":"Real Estate Operator",
            "type":"Services"
        }
    ],
    "sg:phone":"+1 206 215 9700",
    "sg:postcode":"98121",
    "sg:province":"WA",
    "sg:tags":[
        "apartment",
        "complex"
    ],
    "wof:name":"Crown Pointe Apts LP",
    "wof:placetype":"venue"
},
  "geometry": {"coordinates":[-122.354795,47.614881],"type":"Point"}
}