{
  "type": "Feature",
  "properties": {
    "addr:full":"20220 81st Ave W Edmonds WA 98026",
    "addr:housenumber":"20220",
    "addr:postcode":"98026",
    "addr:street":"81St Ave W",
    "iso:country":"US",
    "sg:address":"20220 81st Ave W",
    "sg:city":"Edmonds",
    "sg:classifiers":[
        {
            "category":"Professional",
            "subcategory":"Art Services",
            "type":"Services"
        }
    ],
    "sg:phone":"+1 425 775 4783",
    "sg:postcode":"98026",
    "sg:province":"WA",
    "sg:tags":[
        "commercial",
        "design"
    ],
    "wof:name":"H J T Enterprises",
    "wof:placetype":"venue"
},
  "geometry": {"coordinates":[-122.34270100000001,47.815383],"type":"Point"}
}