{
  "type": "Feature",
  "properties": {
    "addr:full":"1844 114th Ave NE Bellevue WA 98004",
    "addr:housenumber":"1844",
    "addr:postcode":"98004",
    "addr:street":"114Th Ave Ne",
    "iso:country":"US",
    "sg:address":"1844 114th Ave NE",
    "sg:city":"Bellevue",
    "sg:classifiers":[
        {
            "category":"Professional",
            "subcategory":"Engineering",
            "type":"Services"
        }
    ],
    "sg:phone":"+1 425 462 9441",
    "sg:postcode":"98004",
    "sg:province":"WA",
    "sg:tags":[
        "engineer"
    ],
    "sg:website":"www.abossein.com",
    "wof:name":"Abossein Engineering Corp",
    "wof:placetype":"venue"
},
  "geometry": {"coordinates":[-122.187592,47.626789],"type":"Point"}
}