{
  "type": "Feature",
  "properties": {
    "addr:full":"105 S Main St Seattle WA 98104",
    "addr:housenumber":"105",
    "addr:postcode":"98104",
    "addr:street":"S Main St",
    "iso:country":"US",
    "sg:address":"105 S Main St",
    "sg:city":"Seattle",
    "sg:classifiers":[
        {
            "category":"Insurance",
            "subcategory":"Hazard Insurance",
            "type":"Services"
        },
        {
            "category":"Insurance",
            "subcategory":"Insurance Agent",
            "type":"Services"
        }
    ],
    "sg:phone":"+1 206 625 2658",
    "sg:postcode":"98104",
    "sg:province":"WA",
    "sg:tags":[
        "profit",
        "sharing",
        "pension",
        "plan"
    ],
    "sg:website":"www.duncanhaley.com",
    "wof:name":"Duncan & Haley Ltd",
    "wof:placetype":"venue"
},
  "geometry": {"coordinates":[-122.332954,47.599966],"type":"Point"}
}