{
  "type": "Feature",
  "properties": {
    "addr:full":"2120 N 4th Ave Pasco WA 99301",
    "addr:housenumber":"2120",
    "addr:postcode":"99301",
    "addr:street":"N 4Th Ave",
    "iso:country":"US",
    "sg:address":"2120 N 4th Ave",
    "sg:city":"Pasco",
    "sg:classifiers":[
        {
            "category":"Food & Beverages",
            "subcategory":"Bakery",
            "type":"Retail Goods"
        }
    ],
    "sg:phone":"+1 509 547 9031",
    "sg:postcode":"99301",
    "sg:province":"WA",
    "sg:tags":[
        "grocery"
    ],
    "wof:name":"Castilleja Bakery & Grocery",
    "wof:placetype":"venue"
},
  "geometry": {"coordinates":[-119.095001,46.2472],"type":"Point"}
}