{
  "type": "Feature",
  "properties": {
    "addr:full":"612 Stewart St Seattle WA 98101",
    "addr:housenumber":"612",
    "addr:postcode":"98101",
    "addr:street":"Stewart St",
    "iso:country":"US",
    "sg:address":"612 Stewart St",
    "sg:city":"Seattle",
    "sg:classifiers":[
        {
            "category":"Restaurant",
            "type":"Food & Drink"
        }
    ],
    "sg:phone":"+1 206 956 0639",
    "sg:postcode":"98101",
    "sg:province":"WA",
    "wof:name":"Yakima Grill",
    "wof:placetype":"venue"
},
  "geometry": {"coordinates":[-122.33628400000001,47.614254],"type":"Point"}
}