{
  "type": "Feature",
  "properties": {
    "addr:full":"15185 Sunset Ln Mount Vernon WA 98273",
    "addr:housenumber":"15185",
    "addr:postcode":"98273",
    "addr:street":"Sunset Ln",
    "iso:country":"US",
    "sg:address":"15185 Sunset Ln",
    "sg:city":"Mount Vernon",
    "sg:classifiers":[
        {
            "category":"Building & Trades",
            "subcategory":"Plumbing",
            "type":"Services"
        }
    ],
    "sg:phone":"+1 360 848 8683",
    "sg:postcode":"98273",
    "sg:province":"WA",
    "sg:tags":[
        "plumbing",
        "repair",
        "piping",
        "fixture",
        "installation"
    ],
    "wof:name":"A-Plus Service",
    "wof:placetype":"venue"
},
  "geometry": {"coordinates":[-122.361822,48.425591],"type":"Point"}
}