{
  "type": "Feature",
  "properties": {
    "addr:full":"308 NW 46th St Seattle WA 98107",
    "addr:housenumber":"308",
    "addr:postcode":"98107",
    "addr:street":"Nw 46Th St",
    "iso:country":"US",
    "sg:address":"308 NW 46th St",
    "sg:city":"Seattle",
    "sg:classifiers":[
        {
            "category":"Shopping",
            "subcategory":"Books",
            "type":"Retail Goods"
        }
    ],
    "sg:phone":"+1 206 789 9972",
    "sg:postcode":"98107",
    "sg:province":"WA",
    "wof:name":"C2 Consulting",
    "wof:placetype":"venue"
},
  "geometry": {"coordinates":[-122.363947,47.662274],"type":"Point"}
}