{
  "type": "Feature",
  "properties": {
    "addr:full":"308 105th Ave NE Bellevue WA 98004",
    "addr:housenumber":"308",
    "addr:postcode":"98004",
    "addr:street":"105Th Ave Ne",
    "iso:country":"US",
    "sg:address":"308 105th Ave NE",
    "sg:city":"Bellevue",
    "sg:classifiers":[
        {
            "category":"Retail",
            "subcategory":"Photofinishing",
            "type":"Services"
        },
        {
            "category":"Professional",
            "subcategory":"Printing & Photocopies",
            "type":"Services"
        }
    ],
    "sg:phone":"+1 425 462 4755",
    "sg:postcode":"98004",
    "sg:province":"WA",
    "sg:tags":[
        "photo",
        "laboratories-commercial",
        "finishing-custom",
        "laboratory"
    ],
    "wof:name":"Bellevue Photo & Gift",
    "wof:placetype":"venue"
},
  "geometry": {"coordinates":[-122.200197,47.61302],"type":"Point"}
}