{
  "type": "Feature",
  "properties": {
    "addr:full":"1321 Cornwall Ave Bellingham WA 98225",
    "addr:housenumber":"1321",
    "addr:postcode":"98225",
    "addr:street":"Cornwall Ave",
    "iso:country":"US",
    "sg:address":"1321 Cornwall Ave",
    "sg:city":"Bellingham",
    "sg:classifiers":[
        {
            "category":"Retail",
            "subcategory":"Repair Shop",
            "type":"Services"
        }
    ],
    "sg:phone":"+1 360 734 1997",
    "sg:postcode":"98225",
    "sg:province":"WA",
    "wof:name":"Barbo Furniture",
    "wof:placetype":"venue"
},
  "geometry": {"coordinates":[-122.477931,48.750604],"type":"Point"}
}