{
  "type": "Feature",
  "properties": {
    "addr:full":"3615 Walthew St SE Lacey WA 98503",
    "addr:housenumber":"3615",
    "addr:postcode":"98503",
    "addr:street":"Walthew St Se",
    "iso:country":"US",
    "sg:address":"3615 Walthew St SE",
    "sg:city":"Lacey",
    "sg:classifiers":[
        {
            "category":"Professional",
            "subcategory":"Business Services",
            "type":"Services"
        }
    ],
    "sg:phone":"+1 360 491 1054",
    "sg:postcode":"98503",
    "sg:province":"WA",
    "wof:name":"Ncra",
    "wof:placetype":"venue"
},
  "geometry": {"coordinates":[-122.76495199999999,47.013586],"type":"Point"}
}