{
  "type": "Feature",
  "properties": {
    "addr:full":"210 S Washington St Seattle WA 98104",
    "addr:housenumber":"210",
    "addr:postcode":"98104",
    "addr:street":"S Washington St",
    "iso:country":"US",
    "sg:address":"210 S Washington St",
    "sg:city":"Seattle",
    "sg:classifiers":[
        {
            "category":"Home & Garden",
            "subcategory":"Carpets & Floor Coverings",
            "type":"Retail Goods"
        }
    ],
    "sg:phone":"+1 206 652 8374",
    "sg:postcode":"98104",
    "sg:province":"WA",
    "sg:tags":[
        "mattress"
    ],
    "sg:website":"http://www.moderndesignsofas.com",
    "wof:name":"Modern Design Sofas",
    "wof:placetype":"venue"
},
  "geometry": {"coordinates":[-122.331108,47.600861],"type":"Point"}
}