{
  "type": "Feature",
  "properties": {
    "addr:full":"5104 Keystone Pl N Seattle WA 98103",
    "addr:housenumber":"5104",
    "addr:postcode":"98103",
    "addr:street":"Keystone Pl N",
    "iso:country":"US",
    "sg:address":"5104 Keystone Pl N",
    "sg:city":"Seattle",
    "sg:classifiers":[
        {
            "category":"Retail",
            "subcategory":"Portrait Studio",
            "type":"Services"
        }
    ],
    "sg:phone":"+1 206 632 9141",
    "sg:postcode":"98103",
    "sg:province":"WA",
    "sg:tags":[
        "photo"
    ],
    "wof:name":"Drake Photography",
    "wof:placetype":"venue"
},
  "geometry": {"coordinates":[-122.331468,47.666488],"type":"Point"}
}