{
  "type": "Feature",
  "properties": {
    "addr:full":"9720 31st St E Edgewood WA 98371",
    "addr:housenumber":"9720",
    "addr:postcode":"98371",
    "addr:street":"31St St E",
    "iso:country":"US",
    "sg:address":"9720 31st St E",
    "sg:city":"Edgewood",
    "sg:classifiers":[
        {
            "category":"Building & Trades",
            "subcategory":"Construction",
            "type":"Services"
        }
    ],
    "sg:phone":"+1 253 845 5917",
    "sg:postcode":"98371",
    "sg:province":"WA",
    "sg:tags":[
        "wallcoverings-installation",
        "contractor",
        "wallpaper",
        "hanging"
    ],
    "wof:name":"American Wall Covering",
    "wof:placetype":"venue"
},
  "geometry": {"coordinates":[-122.299211,47.229382],"type":"Point"}
}