{
  "type": "Feature",
  "properties": {
    "addr:full":"1200 6th Ave Seattle WA 98101",
    "addr:housenumber":"1200",
    "addr:postcode":"98101",
    "addr:street":"6Th Ave",
    "iso:country":"US",
    "sg:address":"1200 6th Ave",
    "sg:city":"Seattle",
    "sg:classifiers":[
        {
            "category":"Insurance",
            "subcategory":"Hazard Insurance",
            "type":"Services"
        },
        {
            "category":"Insurance",
            "subcategory":"Life Insurance",
            "type":"Services"
        }
    ],
    "sg:phone":"+1 206 587 6555",
    "sg:postcode":"98101",
    "sg:province":"WA",
    "sg:website":"http://www.imu.com",
    "wof:name":"Onebeacon Insurance Company",
    "wof:placetype":"venue"
},
  "geometry": {"coordinates":[-122.331947,47.608429],"type":"Point"}
}