{
  "type": "Feature",
  "properties": {
    "addr:full":"1419 E Lakeshore Dr Lake Stevens WA 98258",
    "addr:housenumber":"1419",
    "addr:postcode":"98258",
    "addr:street":"E Lakeshore Dr",
    "iso:country":"US",
    "sg:address":"1419 E Lakeshore Dr",
    "sg:city":"Lake Stevens",
    "sg:classifiers":[
        {
            "category":"Building & Trades",
            "subcategory":"Plumbing",
            "type":"Services"
        }
    ],
    "sg:phone":"+1 425 334 0325",
    "sg:postcode":"98258",
    "sg:province":"WA",
    "sg:tags":[
        "contractor"
    ],
    "wof:name":"Waters Heating",
    "wof:placetype":"venue"
},
  "geometry": {"coordinates":[-122.06793500000001,48.010446],"type":"Point"}
}