{
  "type": "Feature",
  "properties": {
    "addr:full":"1011 SW Klickitat Way Suite 102 Seattle WA 98134",
    "addr:housenumber":"1011",
    "addr:postcode":"98134",
    "addr:street":"Sw Klickitat Way Suite 102",
    "iso:country":"US",
    "sg:address":"1011 SW Klickitat Way Suite 102",
    "sg:city":"Seattle",
    "sg:classifiers":[
        {
            "category":"Real Estate",
            "subcategory":"Architect",
            "type":"Services"
        }
    ],
    "sg:phone":"+1 206 623 6832",
    "sg:postcode":"98134",
    "sg:province":"WA",
    "wof:name":"Aks PS",
    "wof:placetype":"venue"
},
  "geometry": {"coordinates":[-122.350459,47.570678],"type":"Point"}
}