{
  "type": "Feature",
  "properties": {
    "addr:full":"979 S Clark Ave Republic WA 99166",
    "addr:housenumber":"979",
    "addr:postcode":"99166",
    "addr:street":"S Clark Ave",
    "iso:country":"US",
    "sg:address":"979 S Clark Ave",
    "sg:city":"Republic",
    "sg:classifiers":[
        {
            "category":"Travel",
            "subcategory":"Hotels & Motels",
            "type":"Entertainment"
        }
    ],
    "sg:phone":"+1 509 775 3361",
    "sg:postcode":"99166",
    "sg:province":"WA",
    "wof:name":"Prospector Inn",
    "wof:placetype":"venue"
},
  "geometry": {"coordinates":[-118.73674099999999,48.642396],"type":"Point"}
}