{
  "type": "Feature",
  "properties": {
    "addr:full":"17781 15th Ave NW Seattle WA 98177",
    "addr:housenumber":"17781",
    "addr:postcode":"98177",
    "addr:street":"15Th Ave Nw",
    "iso:country":"US",
    "sg:address":"17781 15th Ave NW",
    "sg:city":"Seattle",
    "sg:classifiers":[
        {
            "category":"Professional",
            "subcategory":"Management & Consulting",
            "type":"Services"
        }
    ],
    "sg:phone":"+1 206 533 9452",
    "sg:postcode":"98177",
    "sg:province":"WA",
    "wof:name":"Janet Peterson Pt",
    "wof:placetype":"venue"
},
  "geometry": {"coordinates":[-122.376743,47.760401],"type":"Point"}
}