{
  "type": "Feature",
  "properties": {
    "addr:full":"230 S Columbia St Wenatchee WA 98801",
    "addr:housenumber":"230",
    "addr:postcode":"98801",
    "addr:street":"S Columbia St",
    "iso:country":"US",
    "sg:address":"230 S Columbia St",
    "sg:city":"Wenatchee",
    "sg:classifiers":[
        {
            "category":"Recreation",
            "type":"Entertainment"
        },
        {
            "category":"Sports & Exercise",
            "subcategory":"Gym",
            "type":"Entertainment"
        }
    ],
    "sg:phone":"+1 509 663 2988",
    "sg:postcode":"98801",
    "sg:province":"WA",
    "sg:tags":[
        "physical",
        "facility",
        "instruction",
        "gymnastic",
        "fitness"
    ],
    "wof:name":"Apple Valley Gymnastics",
    "wof:placetype":"venue"
},
  "geometry": {"coordinates":[-120.308048,47.422204],"type":"Point"}
}