{
  "type": "Feature",
  "properties": {
    "addr:full":"876 S Market Blvd Chehalis WA 98532",
    "addr:housenumber":"876",
    "addr:postcode":"98532",
    "addr:street":"S Market Blvd",
    "iso:country":"US",
    "sg:address":"876 S Market Blvd",
    "sg:city":"Chehalis",
    "sg:classifiers":[
        {
            "category":"Health Services",
            "subcategory":"Chiropractor",
            "type":"Services"
        }
    ],
    "sg:phone":"+1 360 748 1301",
    "sg:postcode":"98532",
    "sg:province":"WA",
    "sg:tags":[
        "chiropractic"
    ],
    "wof:name":"Chehalis Chiropractic Clinic",
    "wof:placetype":"venue"
},
  "geometry": {"coordinates":[-122.956622,46.656289],"type":"Point"}
}