{
  "type": "Feature",
  "properties": {
    "addr:full":"6726 N Parkside Ln Tacoma WA 98407",
    "addr:housenumber":"6726",
    "addr:postcode":"98407",
    "addr:street":"N Parkside Ln",
    "iso:country":"US",
    "sg:address":"6726 N Parkside Ln",
    "sg:city":"Tacoma",
    "sg:classifiers":[
        {
            "category":"Real Estate",
            "subcategory":"Real Estate Services",
            "type":"Services"
        },
        {
            "category":"Real Estate",
            "subcategory":"Real Estate Agent",
            "type":"Services"
        }
    ],
    "sg:phone":"+1 253 761 7475",
    "sg:postcode":"98407",
    "sg:province":"WA",
    "sg:tags":[
        "buyer",
        "broker"
    ],
    "wof:name":"Benash Real Property Exchanges",
    "wof:placetype":"venue"
},
  "geometry": {"coordinates":[-122.52677199999999,47.295721],"type":"Point"}
}