{
  "type": "Feature",
  "properties": {
    "addr:full":"2149 Long Lake Rd SE Port Orchard WA 98366",
    "addr:housenumber":"2149",
    "addr:postcode":"98366",
    "addr:street":"Long Lake Rd Se",
    "iso:country":"US",
    "sg:address":"2149 Long Lake Rd SE",
    "sg:city":"Port Orchard",
    "sg:classifiers":[
        {
            "category":"Real Estate",
            "subcategory":"Real Estate Agent",
            "type":"Services"
        }
    ],
    "sg:phone":"+1 360 871 1460",
    "sg:postcode":"98366",
    "sg:province":"WA",
    "wof:name":"Extreme Property MGT LLC",
    "wof:placetype":"venue"
},
  "geometry": {"coordinates":[-122.579274,47.528242],"type":"Point"}
}