{
  "type": "Feature",
  "properties": {
    "addr:full":"926 19th Ave E Seattle WA 98112",
    "addr:housenumber":"926",
    "addr:postcode":"98112",
    "addr:street":"19Th Ave E",
    "iso:country":"US",
    "sg:address":"926 19th Ave E",
    "sg:city":"Seattle",
    "sg:classifiers":[
        {
            "category":"Health Services",
            "subcategory":"Clinic",
            "type":"Services"
        }
    ],
    "sg:phone":"+1 206 322 8484",
    "sg:postcode":"98112",
    "sg:province":"WA",
    "sg:tags":[
        "specialty",
        "outpatient"
    ],
    "wof:name":"ABC Births",
    "wof:placetype":"venue"
},
  "geometry": {"coordinates":[-122.30720100000001,47.628429],"type":"Point"}
}