{
  "type": "Feature",
  "properties": {
    "addr:full":"237 W 8th St Port Angeles WA 98362",
    "addr:housenumber":"237",
    "addr:postcode":"98362",
    "addr:street":"W 8Th St",
    "iso:country":"US",
    "sg:address":"237 W 8th St",
    "sg:city":"Port Angeles",
    "sg:classifiers":[
        {
            "category":"Social Services",
            "subcategory":"Child Care",
            "type":"Services"
        }
    ],
    "sg:phone":"+1 360 452 8939",
    "sg:postcode":"98362",
    "sg:province":"WA",
    "sg:tags":[
        "daycare",
        "center",
        "preschool"
    ],
    "wof:name":"Banbury Corner Daycare",
    "wof:placetype":"venue"
},
  "geometry": {"coordinates":[-123.44234,48.114321],"type":"Point"}
}