{
  "type": "Feature",
  "properties": {
    "addr:full":"500 E Pike St Seattle WA 98122",
    "addr:housenumber":"500",
    "addr:postcode":"98122",
    "addr:street":"E Pike St",
    "iso:country":"US",
    "sg:address":"500 E Pike St",
    "sg:city":"Seattle",
    "sg:classifiers":[
        {
            "category":"Shopping",
            "subcategory":"Clothing, Apparel, & Fashions",
            "type":"Retail Goods"
        },
        {
            "category":"Shopping",
            "subcategory":"Bridal",
            "type":"Retail Goods"
        }
    ],
    "sg:phone":"+1 206 325 8700",
    "sg:postcode":"98122",
    "sg:province":"WA",
    "sg:tags":[
        "costume"
    ],
    "sg:website":"www.brocklinds.com",
    "wof:name":"Brocklind's",
    "wof:placetype":"venue"
},
  "geometry": {"coordinates":[-122.32547099999999,47.614116],"type":"Point"}
}