{
  "type": "Feature",
  "properties": {
    "iso:country":"US",
    "sg:address":"5214 Pullman Ave NE",
    "sg:city":"Seattle",
    "sg:classifiers":[
        {
            "category":"Professional",
            "type":"Services"
        }
    ],
    "sg:phone":"+1 206 528 1900",
    "sg:postcode":"98105",
    "sg:province":"WA",
    "sg:tags":[
        "communications"
    ],
    "wof:name":"Advance Tax Practioners Inst",
    "wof:placetype":"venue"
},
  "geometry": {"coordinates":[-122.2726,47.669935],"type":"Point"}
}