{
  "type": "Feature",
  "properties": {
    "addr:full":"4419 200th St SW Lynnwood WA 98036",
    "addr:housenumber":"4419",
    "addr:postcode":"98036",
    "addr:street":"200Th St Sw",
    "iso:country":"US",
    "sg:address":"4419 200th St SW",
    "sg:city":"Lynnwood",
    "sg:classifiers":[
        {
            "category":"Food & Beverages",
            "subcategory":"Fruits & Vegetables",
            "type":"Retail Goods"
        }
    ],
    "sg:phone":"+1 425 672 3497",
    "sg:postcode":"98036",
    "sg:province":"WA",
    "wof:name":"J DS Market",
    "wof:placetype":"venue"
},
  "geometry": {"coordinates":[-122.294918,47.817442],"type":"Point"}
}