{
  "type": "Feature",
  "properties": {
    "addr:full":"3550 Meridian St Bellingham WA 98225",
    "addr:housenumber":"3550",
    "addr:postcode":"98225",
    "addr:street":"Meridian St",
    "iso:country":"US",
    "sg:address":"3550 Meridian St",
    "sg:city":"Bellingham",
    "sg:classifiers":[
        {
            "category":"Manufacturing",
            "subcategory":"Printing",
            "type":"Manufacturing & Wholesale Goods"
        }
    ],
    "sg:phone":"+1 360 676 1977",
    "sg:postcode":"98225",
    "sg:province":"WA",
    "sg:tags":[
        "lithographic",
        "printer",
        "commercial"
    ],
    "sg:website":"www.lithtex.com",
    "wof:name":"Lithtex Northwest LLC",
    "wof:placetype":"venue"
},
  "geometry": {"coordinates":[-122.486013,48.777957],"type":"Point"}
}