{
  "type": "Feature",
  "properties": {
    "addr:full":"15611 E Washington Rd Valleyford WA 99036",
    "addr:housenumber":"15611",
    "addr:postcode":"99036",
    "addr:street":"E Washington Rd",
    "iso:country":"US",
    "sg:address":"15611 E Washington Rd",
    "sg:city":"Valleyford",
    "sg:classifiers":[
        {
            "category":"Manufacturing",
            "subcategory":"Tools & Machinery",
            "type":"Manufacturing & Wholesale Goods"
        }
    ],
    "sg:phone":"+1 509 291 3514",
    "sg:postcode":"99036",
    "sg:province":"WA",
    "sg:tags":[
        "distributor",
        "rep",
        "mfg"
    ],
    "wof:name":"Crystalfontz America Inc",
    "wof:placetype":"venue"
},
  "geometry": {"coordinates":[-117.18900499999999,47.529081],"type":"Point"}
}