{
  "type": "Feature",
  "properties": {
    "addr:full":"923 State Ave NE Olympia WA 98506",
    "addr:housenumber":"923",
    "addr:postcode":"98506",
    "addr:street":"State Ave Ne",
    "iso:country":"US",
    "sg:address":"923 State Ave NE",
    "sg:city":"Olympia",
    "sg:classifiers":[
        {
            "category":"Building & Trades",
            "subcategory":"Construction",
            "type":"Services"
        }
    ],
    "sg:phone":"+1 360 943 4029",
    "sg:postcode":"98506",
    "sg:province":"WA",
    "sg:tags":[
        "nonresidential"
    ],
    "wof:name":"Tubular Structures",
    "wof:placetype":"venue"
},
  "geometry": {"coordinates":[-122.890298,47.046439],"type":"Point"}
}