{
  "type": "Feature",
  "properties": {
    "addr:full":"3700 NE 99th Ave Vancouver WA 98662",
    "addr:housenumber":"3700",
    "addr:postcode":"98662",
    "addr:street":"Ne 99Th Ave",
    "iso:country":"US",
    "sg:address":"3700 NE 99th Ave",
    "sg:city":"Vancouver",
    "sg:classifiers":[
        {
            "category":"Building & Trades",
            "subcategory":"Cleaning & Sanitation",
            "type":"Services"
        }
    ],
    "sg:phone":"+1 360 254 1946",
    "sg:postcode":"98662",
    "sg:province":"WA",
    "sg:tags":[
        "maintenance"
    ],
    "wof:name":"Jacque Rubbelke",
    "wof:placetype":"venue"
},
  "geometry": {"coordinates":[-122.570849,45.649686],"type":"Point"}
}