{
  "type": "Feature",
  "properties": {
    "addr:full":"18910 Olympic View Dr Edmonds WA 98020",
    "addr:housenumber":"18910",
    "addr:postcode":"98020",
    "addr:street":"Olympic View Dr",
    "iso:country":"US",
    "sg:address":"18910 Olympic View Dr",
    "sg:city":"Edmonds",
    "sg:classifiers":[
        {
            "category":"Home & Garden",
            "subcategory":"Home Furnishings",
            "type":"Retail Goods"
        }
    ],
    "sg:phone":"+1 425 778 0088",
    "sg:postcode":"98020",
    "sg:province":"WA",
    "sg:tags":[
        "floor",
        "covering"
    ],
    "wof:name":"Designs West",
    "wof:placetype":"venue"
},
  "geometry": {"coordinates":[-122.36183699999999,47.826308],"type":"Point"}
}