{
  "type": "Feature",
  "properties": {
    "addr:full":"2112 W Francis Ave Spokane WA 99205",
    "addr:housenumber":"2112",
    "addr:postcode":"99205",
    "addr:street":"W Francis Ave",
    "iso:country":"US",
    "sg:address":"2112 W Francis Ave",
    "sg:city":"Spokane",
    "sg:classifiers":[
        {
            "category":"Organizations",
            "subcategory":"Religious Organization",
            "type":"Services"
        }
    ],
    "sg:phone":"+1 509 327 6498",
    "sg:postcode":"99205",
    "sg:province":"WA",
    "sg:tags":[
        "church"
    ],
    "wof:name":"Church Of Jesus Christ Of Lds",
    "wof:placetype":"venue"
},
  "geometry": {"coordinates":[-117.44176899999999,47.715525],"type":"Point"}
}