{
  "type": "Feature",
  "properties": {
    "addr:full":"2116 87th Stct NW Gig Harbor WA 98332",
    "addr:housenumber":"2116",
    "addr:postcode":"98332",
    "addr:street":"87Th Stct Nw",
    "iso:country":"US",
    "sg:address":"2116 87th Stct NW",
    "sg:city":"Gig Harbor",
    "sg:classifiers":[
        {
            "category":"Professional",
            "subcategory":"Management & Consulting",
            "type":"Services"
        }
    ],
    "sg:phone":"+1 253 851 7571",
    "sg:postcode":"98332",
    "sg:province":"WA",
    "sg:tags":[
        "selling",
        "establishment",
        "direct"
    ],
    "wof:name":"Harbor Side Marketing Inc",
    "wof:placetype":"venue"
},
  "geometry": {"coordinates":[-122.570407,47.337635],"type":"Point"}
}