{
  "type": "Feature",
  "properties": {
    "iso:country":"US",
    "sg:address":"1540 SW Beeksma Dr",
    "sg:city":"Oak Harbor",
    "sg:classifiers":[
        {
            "category":"Retail",
            "subcategory":"Auto Repair",
            "type":"Services"
        }
    ],
    "sg:phone":"+1 360 679 4200",
    "sg:postcode":"98277",
    "sg:province":"WA",
    "sg:tags":[
        "repairing",
        "automobile"
    ],
    "wof:name":"Mike's Quick-Lube & Auto Rpr",
    "wof:placetype":"venue"
},
  "geometry": {"coordinates":[-122.65778299999999,48.28587],"type":"Point"}
}