{
  "type": "Feature",
  "properties": {
    "addr:full":"510 Capitol Way S Olympia WA 98501",
    "addr:housenumber":"510",
    "addr:postcode":"98501",
    "addr:street":"Capitol Way S",
    "iso:country":"US",
    "sg:address":"510 Capitol Way S",
    "sg:city":"Olympia",
    "sg:classifiers":[
        {
            "category":"Restaurant",
            "type":"Food & Drink"
        }
    ],
    "sg:phone":"+1 360 786 1987",
    "sg:postcode":"98501",
    "sg:province":"WA",
    "wof:name":"Quiznos Sub",
    "wof:placetype":"venue"
},
  "geometry": {"coordinates":[-122.901365,47.043324],"type":"Point"}
}