{
  "type": "Feature",
  "properties": {
    "addr:full":"220 15th St Snohomish WA 98290",
    "addr:housenumber":"220",
    "addr:postcode":"98290",
    "addr:street":"15Th St",
    "iso:country":"US",
    "sg:address":"220 15th St",
    "sg:city":"Snohomish",
    "sg:classifiers":[
        {
            "category":"Building & Trades",
            "subcategory":"Construction",
            "type":"Services"
        }
    ],
    "sg:phone":"+1 425 353 7051",
    "sg:postcode":"98290",
    "sg:province":"WA",
    "sg:tags":[
        "handyman"
    ],
    "wof:name":"Fixit Guy",
    "wof:placetype":"venue"
},
  "geometry": {"coordinates":[-122.08255200000001,47.930144],"type":"Point"}
}