{
  "type": "Feature",
  "properties": {
    "addr:full":"7646 NE Hazel Dell Ave Vancouver WA 98665",
    "addr:housenumber":"7646",
    "addr:postcode":"98665",
    "addr:street":"Ne Hazel Dell Ave",
    "iso:country":"US",
    "sg:address":"7646 NE Hazel Dell Ave",
    "sg:city":"Vancouver",
    "sg:classifiers":[
        {
            "category":"Banks & Credit Unions",
            "subcategory":"Bank",
            "type":"Services"
        }
    ],
    "sg:phone":"+1 360 735 8445",
    "sg:postcode":"98665",
    "sg:province":"WA",
    "sg:tags":[
        "loan",
        "real estate"
    ],
    "wof:name":"National City Mortgage",
    "wof:placetype":"venue"
},
  "geometry": {"coordinates":[-122.668955,45.678132],"type":"Point"}
}