{
  "type": "Feature",
  "properties": {
    "addr:full":"111 N Wright Ave Cle Elum WA 98922",
    "addr:housenumber":"111",
    "addr:postcode":"98922",
    "addr:street":"N Wright Ave",
    "iso:country":"US",
    "sg:address":"111 N Wright Ave",
    "sg:city":"Cle Elum",
    "sg:classifiers":[
        {
            "category":"Personal",
            "type":"Services"
        },
        {
            "category":"Personal",
            "subcategory":"Beauty Salon",
            "type":"Services"
        }
    ],
    "sg:phone":"+1 509 674 6004",
    "sg:postcode":"98922",
    "sg:province":"WA",
    "wof:name":"Sister Moon Massage",
    "wof:placetype":"venue"
},
  "geometry": {"coordinates":[-120.93499199999999,47.19435],"type":"Point"}
}