{
  "type": "Feature",
  "properties": {
    "addr:full":"804 N Emerson Ave Wenatchee WA 98801",
    "addr:housenumber":"804",
    "addr:postcode":"98801",
    "addr:street":"N Emerson Ave",
    "iso:country":"US",
    "sg:address":"804 N Emerson Ave",
    "sg:city":"Wenatchee",
    "sg:classifiers":[
        {
            "category":"Professional",
            "subcategory":"Accounting & Tax Preparation",
            "type":"Services"
        }
    ],
    "sg:phone":"+1 509 663 7802",
    "sg:postcode":"98801",
    "sg:province":"WA",
    "sg:tags":[
        "accountant"
    ],
    "wof:name":"C Ed Cheek & Co",
    "wof:placetype":"venue"
},
  "geometry": {"coordinates":[-120.324043,47.433477],"type":"Point"}
}