{
  "type": "Feature",
  "properties": {
    "addr:full":"11309 Clear Creek Rd NW Silverdale WA 98383",
    "addr:housenumber":"11309",
    "addr:postcode":"98383",
    "addr:street":"Clear Creek Rd Nw",
    "iso:country":"US",
    "sg:address":"11309 Clear Creek Rd NW",
    "sg:city":"Silverdale",
    "sg:classifiers":[
        {
            "category":"Professional",
            "subcategory":"Engineering",
            "type":"Services"
        }
    ],
    "sg:phone":"+1 206 682 5574",
    "sg:postcode":"98383",
    "sg:province":"WA",
    "wof:name":"Map Limited",
    "wof:placetype":"venue"
},
  "geometry": {"coordinates":[-122.692888,47.673967],"type":"Point"}
}