{
  "type": "Feature",
  "properties": {
    "addr:full":"3111 W 5th Ave Spokane WA 99224",
    "addr:housenumber":"3111",
    "addr:postcode":"99224",
    "addr:street":"W 5Th Ave",
    "iso:country":"US",
    "sg:address":"3111 W 5th Ave",
    "sg:city":"Spokane",
    "sg:classifiers":[
        {
            "category":"Building & Trades",
            "subcategory":"Cleaning & Sanitation",
            "type":"Services"
        }
    ],
    "sg:phone":"+1 509 747 5857",
    "sg:postcode":"99224",
    "sg:province":"WA",
    "sg:tags":[
        "maintenance"
    ],
    "wof:name":"Bryans Janitorial & Clea",
    "wof:placetype":"venue"
},
  "geometry": {"coordinates":[-117.458742,47.65183],"type":"Point"}
}