{
  "type": "Feature",
  "properties": {
    "addr:full":"305 Harrison St Seattle Center Food Court Seattle WA 98109",
    "addr:housenumber":"305",
    "addr:postcode":"98109",
    "addr:street":"Harrison St",
    "iso:country":"US",
    "sg:address":"305 Harrison St Seattle Center Food Court",
    "sg:city":"Seattle",
    "sg:classifiers":[
        {
            "category":"Juice Bar",
            "subcategory":"None",
            "type":"Food & Drink"
        }
    ],
    "sg:phone":"+1 206 728 7878",
    "sg:postcode":"98109",
    "sg:province":"WA",
    "sg:tags":[
        "smoothy"
    ],
    "sg:website":"www.orangejulius.com",
    "wof:name":"Orange Julius Grill",
    "wof:placetype":"venue"
},
  "geometry": {"coordinates":[-122.348601,47.622104],"type":"Point"}
}