{
  "type": "Feature",
  "properties": {
    "addr:full":"24304 W Highland Exd Benton City WA 99320",
    "addr:housenumber":"24304",
    "addr:postcode":"99320",
    "addr:street":"W Highland Exd",
    "iso:country":"US",
    "sg:address":"24304 W Highland Exd",
    "sg:city":"Benton City",
    "sg:classifiers":[
        {
            "category":"Autos & Motor Vehicles",
            "subcategory":"Fuel & Gas Station",
            "type":"Retail Goods"
        }
    ],
    "sg:phone":"+1 509 588 3348",
    "sg:postcode":"99320",
    "sg:province":"WA",
    "sg:tags":[
        "sporting",
        "station",
        "gasoline"
    ],
    "wof:name":"Bork & Sons",
    "wof:placetype":"venue"
},
  "geometry": {"coordinates":[-119.54816,46.285879],"type":"Point"}
}