{
  "type": "Feature",
  "properties": {
    "addr:full":"1599 SE Lund Ave Port Orchard WA 98366",
    "addr:housenumber":"1599",
    "addr:postcode":"98366",
    "addr:street":"Se Lund Ave",
    "iso:country":"US",
    "sg:address":"1599 SE Lund Ave",
    "sg:city":"Port Orchard",
    "sg:classifiers":[
        {
            "category":"Restaurant",
            "type":"Food & Drink"
        }
    ],
    "sg:phone":"+1 360 876 0788",
    "sg:postcode":"98366",
    "sg:province":"WA",
    "sg:tags":[
        "eating"
    ],
    "sg:website":"www.shoplocalbiz.com",
    "wof:name":"Puerto Vallarta",
    "wof:placetype":"venue"
},
  "geometry": {"coordinates":[-122.634822,47.520061],"type":"Point"}
}