{
  "type": "Feature",
  "properties": {
    "addr:full":"108 W Helena Ave Ellensburg WA 98926",
    "addr:housenumber":"108",
    "addr:postcode":"98926",
    "addr:street":"W Helena Ave",
    "iso:country":"US",
    "sg:address":"108 W Helena Ave",
    "sg:city":"Ellensburg",
    "sg:classifiers":[
        {
            "category":"Home & Garden",
            "subcategory":"Building Materials",
            "type":"Retail Goods"
        }
    ],
    "sg:phone":"+1 509 962 2352",
    "sg:postcode":"98926",
    "sg:province":"WA",
    "sg:tags":[
        "insulation",
        "product",
        "conservation",
        "energy"
    ],
    "wof:name":"Kool K 9",
    "wof:placetype":"venue"
},
  "geometry": {"coordinates":[-120.54836299999999,47.01392],"type":"Point"}
}