{
  "type": "Feature",
  "properties": {
    "addr:full":"8820 State Rte 532 Stanwood WA 98292",
    "addr:housenumber":"8820",
    "addr:postcode":"98292",
    "addr:street":"State Rte 532",
    "iso:country":"US",
    "sg:address":"8820 State Rte 532",
    "sg:city":"Stanwood",
    "sg:classifiers":[
        {
            "category":"Personal",
            "subcategory":"Tanning Parlor",
            "type":"Services"
        }
    ],
    "sg:phone":"+1 360 629 6896",
    "sg:postcode":"98292",
    "sg:province":"WA",
    "sg:tags":[
        "salon"
    ],
    "wof:name":"Electric Beach",
    "wof:placetype":"venue"
},
  "geometry": {"coordinates":[-122.352186,48.239822],"type":"Point"}
}