{
  "type": "Feature",
  "properties": {
    "addr:full":"2283 Lincoln Ave SE Port Orchard WA 98366",
    "addr:housenumber":"2283",
    "addr:postcode":"98366",
    "addr:street":"Lincoln Ave Se",
    "iso:country":"US",
    "sg:address":"2283 Lincoln Ave SE",
    "sg:city":"Port Orchard",
    "sg:classifiers":[
        {
            "category":"Professional",
            "subcategory":"Computer Services",
            "type":"Services"
        }
    ],
    "sg:phone":"+1 360 876 4879",
    "sg:postcode":"98366",
    "sg:province":"WA",
    "sg:tags":[
        "related"
    ],
    "wof:name":"Jensen",
    "wof:placetype":"venue"
},
  "geometry": {"coordinates":[-122.621019,47.527868],"type":"Point"}
}