{
  "type": "Feature",
  "properties": {
    "addr:full":"22525 SE 64th Pl Issaquah WA 98027",
    "addr:postcode":"22525;98027",
    "addr:street":"Se 64Th Pl",
    "iso:country":"US",
    "sg:address":"22525 SE 64th Pl",
    "sg:city":"Issaquah",
    "sg:classifiers":[
        {
            "category":"Professional",
            "subcategory":"Lawyer & Legal Services",
            "type":"Services"
        }
    ],
    "sg:phone":"+1 425 557 3697",
    "sg:postcode":"98027",
    "sg:province":"WA",
    "sg:tags":[
        "attorney"
    ],
    "wof:name":"Mary Hammerly",
    "wof:placetype":"venue"
},
  "geometry": {"coordinates":[-122.03972899999999,47.544029],"type":"Point"}
}