{
  "type": "Feature",
  "properties": {
    "addr:full":"3024 Issaquah-Pine Lake Rd SE Sammamish WA 98075",
    "addr:housenumber":"3024",
    "addr:postcode":"98075",
    "addr:street":"Issaquah-Pine Lake Rd Se",
    "iso:country":"US",
    "sg:address":"3024 Issaquah-Pine Lake Rd SE",
    "sg:city":"Sammamish",
    "sg:classifiers":[
        {
            "category":"Shopping",
            "subcategory":"Gifts & Souvenirs",
            "type":"Retail Goods"
        }
    ],
    "sg:phone":"+1 425 391 9199",
    "sg:postcode":"98075",
    "sg:province":"WA",
    "sg:tags":[
        "novelty"
    ],
    "wof:name":"Party Carousel",
    "wof:placetype":"venue"
},
  "geometry": {"coordinates":[-122.03202400000001,47.581065],"type":"Point"}
}