{
  "type": "Feature",
  "properties": {
    "addr:full":"2133 38th Ave Longview WA 98632",
    "addr:housenumber":"2133",
    "addr:postcode":"98632",
    "addr:street":"38Th Ave",
    "iso:country":"US",
    "sg:address":"2133 38th Ave",
    "sg:city":"Longview",
    "sg:classifiers":[
        {
            "category":"Retail",
            "subcategory":"Car Wash",
            "type":"Services"
        }
    ],
    "sg:phone":"+1 360 562 5507",
    "sg:postcode":"98632",
    "sg:province":"WA",
    "sg:tags":[
        "automobile",
        "detailing"
    ],
    "wof:name":"Apple Polishing System",
    "wof:placetype":"venue"
},
  "geometry": {"coordinates":[-122.985674,46.153137],"type":"Point"}
}