{
  "type": "Feature",
  "properties": {
    "addr:full":"4634 Pacific Way Longview WA 98632",
    "addr:housenumber":"4634",
    "addr:postcode":"98632",
    "addr:street":"Pacific Way",
    "iso:country":"US",
    "sg:address":"4634 Pacific Way",
    "sg:city":"Longview",
    "sg:classifiers":[
        {
            "category":"Organizations",
            "subcategory":"Religious Organization",
            "type":"Services"
        }
    ],
    "sg:phone":"+1 360 577 0157",
    "sg:postcode":"98632",
    "sg:province":"WA",
    "sg:tags":[
        "church"
    ],
    "wof:name":"Pacific Way Church Of Christ",
    "wof:placetype":"venue"
},
  "geometry": {"coordinates":[-122.98991599999999,46.178582],"type":"Point"}
}