{
  "type": "Feature",
  "properties": {
    "addr:full":"5423 S Martin St Spokane WA 99223",
    "addr:housenumber":"5423",
    "addr:postcode":"99223",
    "addr:street":"S Martin St",
    "iso:country":"US",
    "sg:address":"5423 S Martin St",
    "sg:city":"Spokane",
    "sg:classifiers":[
        {
            "category":"Home & Garden",
            "subcategory":"Carpets & Floor Coverings",
            "type":"Retail Goods"
        }
    ],
    "sg:phone":"+1 509 448 7878",
    "sg:postcode":"99223",
    "sg:province":"WA",
    "sg:tags":[
        "dealer",
        "rug"
    ],
    "wof:name":"Beresford Co",
    "wof:placetype":"venue"
},
  "geometry": {"coordinates":[-117.37974199999999,47.605231],"type":"Point"}
}