{
  "type": "Feature",
  "properties": {
    "addr:full":"5065 SW Waite St Seattle WA 98116",
    "addr:housenumber":"5065",
    "addr:postcode":"98116",
    "addr:street":"Sw Waite St",
    "iso:country":"US",
    "sg:address":"5065 SW Waite St",
    "sg:city":"Seattle",
    "sg:classifiers":[
        {
            "category":"Shopping",
            "subcategory":"Used Merchandise",
            "type":"Retail Goods"
        }
    ],
    "sg:phone":"+1 206 933 0588",
    "sg:postcode":"98116",
    "sg:province":"WA",
    "wof:name":"Wardrobes Consigment",
    "wof:placetype":"venue"
},
  "geometry": {"coordinates":[-122.396764,47.581174],"type":"Point"}
}