{
  "type": "Feature",
  "properties": {
    "iso:country":"US",
    "sg:address":"7753 78th Ave SE",
    "sg:city":"Mercer Island",
    "sg:classifiers":[
        {
            "category":"Professional",
            "type":"Services"
        }
    ],
    "sg:phone":"+1 206 232 8737",
    "sg:postcode":"98040",
    "sg:province":"WA",
    "wof:name":"Arthur Jacobson LLC",
    "wof:placetype":"venue"
},
  "geometry": {"coordinates":[-122.23522199999999,47.532508],"type":"Point"}
}