{
  "type": "Feature",
  "properties": {
    "addr:full":"524 NW 201st Ct Seattle WA 98177",
    "addr:housenumber":"524",
    "addr:postcode":"98177",
    "addr:street":"Nw 201St Ct",
    "iso:country":"US",
    "sg:address":"524 NW 201st Ct",
    "sg:city":"Seattle",
    "sg:classifiers":[
        {
            "category":"Building & Trades",
            "subcategory":"Construction",
            "type":"Services"
        }
    ],
    "sg:phone":"+1 206 660 1882",
    "sg:postcode":"98177",
    "sg:province":"WA",
    "sg:tags":[
        "house"
    ],
    "wof:name":"Precision Asphalt Construction",
    "wof:placetype":"venue"
},
  "geometry": {"coordinates":[-122.36475900000001,47.775705],"type":"Point"}
}