{
  "type": "Feature",
  "properties": {
    "addr:full":"11636 NE 135th St Kirkland WA 98034",
    "addr:housenumber":"11636",
    "addr:postcode":"98034",
    "addr:street":"Ne 135Th St",
    "iso:country":"US",
    "sg:address":"11636 NE 135th St",
    "sg:city":"Kirkland",
    "sg:classifiers":[
        {
            "category":"Professional",
            "subcategory":"Business Services",
            "type":"Services"
        }
    ],
    "sg:phone":"+1 425 820 1827",
    "sg:postcode":"98034",
    "sg:province":"WA",
    "wof:name":"Turf Technology",
    "wof:placetype":"venue"
},
  "geometry": {"coordinates":[-122.18478899999999,47.721454],"type":"Point"}
}