{
  "type": "Feature",
  "properties": {
    "iso:country":"US",
    "sg:address":"2355 Reservation Rd",
    "sg:city":"Oak Harbor",
    "sg:classifiers":[
        {
            "category":"Professional",
            "type":"Services"
        }
    ],
    "sg:phone":"+1 360 679 1971",
    "sg:postcode":"98277",
    "sg:province":"WA",
    "wof:name":"Shirley Ann Cline",
    "wof:placetype":"venue"
},
  "geometry": {"coordinates":[-122.555649,48.296302],"type":"Point"}
}