{
  "type": "Feature",
  "properties": {
    "addr:full":"301 Lincoln Ave Mukilteo WA 98275",
    "addr:housenumber":"301",
    "addr:postcode":"98275",
    "addr:street":"Lincoln Ave",
    "iso:country":"US",
    "sg:address":"301 Lincoln Ave",
    "sg:city":"Mukilteo",
    "sg:classifiers":[
        {
            "category":"Social Services",
            "type":"Services"
        }
    ],
    "sg:phone":"+1 206 527 5492",
    "sg:postcode":"98275",
    "sg:province":"WA",
    "sg:tags":[
        "counselor",
        "marriage",
        "family"
    ],
    "wof:name":"Associated Recovery Therapists",
    "wof:placetype":"venue"
},
  "geometry": {"coordinates":[-122.303354,47.945593],"type":"Point"}
}