{
  "type": "Feature",
  "properties": {
    "addr:full":"512 N L St Tacoma WA 98403",
    "addr:housenumber":"512",
    "addr:postcode":"98403",
    "addr:street":"N L St",
    "iso:country":"US",
    "sg:address":"512 N L St",
    "sg:city":"Tacoma",
    "sg:classifiers":[
        {
            "category":"Real Estate",
            "subcategory":"Real Estate Operator",
            "type":"Services"
        }
    ],
    "sg:phone":"+1 253 383 2177",
    "sg:postcode":"98403",
    "sg:province":"WA",
    "sg:tags":[
        "house",
        "dwelling"
    ],
    "wof:name":"Paul W Post",
    "wof:placetype":"venue"
},
  "geometry": {"coordinates":[-122.459085,47.261308],"type":"Point"}
}