{
  "type": "Feature",
  "properties": {
    "addr:full":"8517 20th St Ct W Tacoma WA 98466",
    "addr:housenumber":"8517",
    "addr:postcode":"98466",
    "addr:street":"20Th St Ct W",
    "iso:country":"US",
    "sg:address":"8517 20th St Ct W",
    "sg:city":"Tacoma",
    "sg:classifiers":[
        {
            "category":"Retail",
            "subcategory":"Repair Shop",
            "type":"Services"
        }
    ],
    "sg:phone":"+1 253 535 2903",
    "sg:postcode":"98466",
    "sg:province":"WA",
    "sg:tags":[
        "electrical",
        "refrigerator",
        "freezer"
    ],
    "wof:name":"Joon's Appliance Repair",
    "wof:placetype":"venue"
},
  "geometry": {"coordinates":[-122.551508,47.240859],"type":"Point"}
}