{
  "type": "Feature",
  "properties": {
    "addr:full":"202 5th Ave NW Puyallup WA 98371",
    "addr:housenumber":"202",
    "addr:postcode":"98371",
    "addr:street":"5Th Ave Nw",
    "iso:country":"US",
    "sg:address":"202 5th Ave NW",
    "sg:city":"Puyallup",
    "sg:classifiers":[
        {
            "category":"Shopping",
            "subcategory":"Crafts & Fabrics",
            "type":"Retail Goods"
        }
    ],
    "sg:phone":"+1 253 840 3072",
    "sg:postcode":"98371",
    "sg:province":"WA",
    "sg:tags":[
        "sewing"
    ],
    "wof:name":"Flamingo Weaving",
    "wof:placetype":"venue"
},
  "geometry": {"coordinates":[-122.296927,47.19534],"type":"Point"}
}