{
  "type": "Feature",
  "properties": {
    "addr:full":"900 2nd St SE Auburn WA 98002",
    "addr:housenumber":"900",
    "addr:postcode":"98002",
    "addr:street":"2Nd St Se",
    "iso:country":"US",
    "sg:address":"900 2nd St SE",
    "sg:city":"Auburn",
    "sg:classifiers":[
        {
            "category":"Building & Trades",
            "subcategory":"Construction",
            "type":"Services"
        }
    ],
    "sg:phone":"+1 253 833 0121",
    "sg:postcode":"98002",
    "sg:province":"WA",
    "sg:tags":[
        "contractor"
    ],
    "wof:name":"C & E Rigging",
    "wof:placetype":"venue"
},
  "geometry": {"coordinates":[-122.217521,47.306107],"type":"Point"}
}