{
  "type": "Feature",
  "properties": {
    "addr:full":"5515 NE 259th St Ridgefield WA 98642",
    "addr:housenumber":"5515",
    "addr:postcode":"98642",
    "addr:street":"Ne 259Th St",
    "iso:country":"US",
    "sg:address":"5515 NE 259th St",
    "sg:city":"Ridgefield",
    "sg:classifiers":[
        {
            "category":"Travel",
            "subcategory":"Campground",
            "type":"Entertainment"
        }
    ],
    "sg:phone":"+1 360 887 8970",
    "sg:postcode":"98642",
    "sg:province":"WA",
    "sg:tags":[
        "trailer",
        "merchandise",
        "general"
    ],
    "wof:name":"Big Fir Campground & Rv Park",
    "wof:placetype":"venue"
},
  "geometry": {"coordinates":[-122.617025,45.808675],"type":"Point"}
}