{
  "type": "Feature",
  "properties": {
    "addr:full":"23117 NE 152nd Ave Battle Ground WA 98604",
    "addr:housenumber":"23117",
    "addr:postcode":"98604",
    "addr:street":"Ne 152Nd Ave",
    "iso:country":"US",
    "sg:address":"23117 NE 152nd Ave",
    "sg:city":"Battle Ground",
    "sg:classifiers":[
        {
            "category":"Professional",
            "subcategory":"Business Services",
            "type":"Services"
        }
    ],
    "sg:phone":"+1 360 687 3924",
    "sg:postcode":"98604",
    "sg:province":"WA",
    "wof:name":"1st Cascade Home Inspection",
    "wof:placetype":"venue"
},
  "geometry": {"coordinates":[-122.51622399999999,45.790351],"type":"Point"}
}