{
  "type": "Feature",
  "properties": {
    "iso:country":"US",
    "sg:address":"1700 132nd St SE",
    "sg:city":"Bothell",
    "sg:classifiers":[
        {
            "category":"Personal",
            "subcategory":"Beauty Salon",
            "type":"Services"
        }
    ],
    "sg:phone":"+1 425 357 9434",
    "sg:postcode":"98012",
    "sg:province":"WA",
    "sg:tags":[
        "shop"
    ],
    "wof:name":"Nina Nails",
    "wof:placetype":"venue"
},
  "geometry": {"coordinates":[-122.209861,47.878181],"type":"Point"}
}