{
  "type": "Feature",
  "properties": {
    "addr:full":"381 129th Pl NE Bellevue WA 98005",
    "addr:housenumber":"381",
    "addr:postcode":"98005",
    "addr:street":"129Th Pl Ne",
    "iso:country":"US",
    "sg:address":"381 129th Pl NE",
    "sg:city":"Bellevue",
    "sg:classifiers":[
        {
            "category":"Professional",
            "subcategory":"Engineering",
            "type":"Services"
        }
    ],
    "sg:phone":"+1 425 454 6307",
    "sg:postcode":"98005",
    "sg:province":"WA",
    "sg:tags":[
        "transportation"
    ],
    "wof:name":"James W Mac Isaac Pe",
    "wof:placetype":"venue"
},
  "geometry": {"coordinates":[-122.167571,47.61437],"type":"Point"}
}