{
  "type": "Feature",
  "properties": {
    "addr:full":"221 S 96th Ave Yakima WA 98908",
    "addr:housenumber":"221",
    "addr:postcode":"98908",
    "addr:street":"S 96Th Ave",
    "iso:country":"US",
    "sg:address":"221 S 96th Ave",
    "sg:city":"Yakima",
    "sg:classifiers":[
        {
            "category":"Freight",
            "type":"Transportation"
        }
    ],
    "sg:phone":"+1 509 966 5295",
    "sg:postcode":"98908",
    "sg:province":"WA",
    "sg:tags":[
        "commercial",
        "storage"
    ],
    "wof:name":"96th Avenue Mini Storage",
    "wof:placetype":"venue"
},
  "geometry": {"coordinates":[-120.63576399999999,46.592817],"type":"Point"}
}