{
  "type": "Feature",
  "properties": {
    "addr:full":"518 W 1st Ave Spokane WA 99201",
    "addr:housenumber":"518",
    "addr:postcode":"99201",
    "addr:street":"W 1St Ave",
    "iso:country":"US",
    "sg:address":"518 W 1st Ave",
    "sg:city":"Spokane",
    "sg:classifiers":[
        {
            "category":"Manufacturing",
            "subcategory":"Printing",
            "type":"Manufacturing & Wholesale Goods"
        }
    ],
    "sg:phone":"+1 509 747 8222",
    "sg:postcode":"99201",
    "sg:province":"WA",
    "sg:tags":[
        "printer"
    ],
    "sg:website":"www.masterscreations.com",
    "wof:name":"Masters & Co Printing Inc",
    "wof:placetype":"venue"
},
  "geometry": {"coordinates":[-117.420875,47.656654],"type":"Point"}
}