{
  "type": "Feature",
  "properties": {
    "addr:full":"9200 35th Ave SW Seattle WA 98126",
    "addr:housenumber":"9200",
    "addr:postcode":"98126",
    "addr:street":"35Th Ave Sw",
    "iso:country":"US",
    "sg:address":"9200 35th Ave SW",
    "sg:city":"Seattle",
    "sg:classifiers":[
        {
            "category":"Autos & Motor Vehicles",
            "subcategory":"Fuel & Gas Station",
            "type":"Retail Goods"
        }
    ],
    "sg:phone":"+1 206 932 4140",
    "sg:postcode":"98126",
    "sg:province":"WA",
    "wof:name":"Propel Biofuels Inc",
    "wof:placetype":"venue"
},
  "geometry": {"coordinates":[-122.376597,47.520178],"type":"Point"}
}