{
  "type": "Feature",
  "properties": {
    "iso:country":"US",
    "sg:address":"1307 E Pine St",
    "sg:city":"Seattle",
    "sg:classifiers":[
        {
            "category":"Real Estate",
            "subcategory":"Real Estate Agent",
            "type":"Services"
        }
    ],
    "sg:phone":"+1 206 322 8438",
    "sg:postcode":"98122",
    "sg:province":"WA",
    "sg:tags":[
        "consultant"
    ],
    "wof:name":"Gerrard Beattie & Knapp Refrl",
    "wof:placetype":"venue"
},
  "geometry": {"coordinates":[-122.314334,47.615204],"type":"Point"}
}