{
  "type": "Feature",
  "properties": {
    "iso:country":"US",
    "sg:address":"3508 Fruitvale Blvd",
    "sg:city":"Yakima",
    "sg:classifiers":[
        {
            "category":"Autos & Motor Vehicles",
            "subcategory":"Fuel & Gas Station",
            "type":"Retail Goods"
        }
    ],
    "sg:phone":"+1 509 248 0860",
    "sg:postcode":"98902",
    "sg:province":"WA",
    "sg:tags":[
        "oil"
    ],
    "wof:name":"Smitty's Conoco",
    "wof:placetype":"venue"
},
  "geometry": {"coordinates":[-120.556252,46.618925],"type":"Point"}
}