{
  "type": "Feature",
  "properties": {
    "addr:full":"219 10th St S Kirkland WA 98033",
    "addr:housenumber":"219",
    "addr:postcode":"98033",
    "addr:street":"10Th St S",
    "iso:country":"US",
    "sg:address":"219 10th St S",
    "sg:city":"Kirkland",
    "sg:classifiers":[
        {
            "category":"Retail",
            "subcategory":"Auto Repair",
            "type":"Services"
        }
    ],
    "sg:phone":"+1 425 827 4210",
    "sg:postcode":"98033",
    "sg:province":"WA",
    "sg:tags":[
        "repairing",
        "automobile"
    ],
    "wof:name":"Genesis Motors Limited",
    "wof:placetype":"venue"
},
  "geometry": {"coordinates":[-122.191002,47.674702],"type":"Point"}
}