{
  "type": "Feature",
  "properties": {
    "addr:full":"8915 26th Ave NE Seattle WA 98115",
    "addr:housenumber":"8915",
    "addr:postcode":"98115",
    "addr:street":"26Th Ave Ne",
    "iso:country":"US",
    "sg:address":"8915 26th Ave NE",
    "sg:city":"Seattle",
    "sg:classifiers":[
        {
            "category":"Professional",
            "subcategory":"Management & Consulting",
            "type":"Services"
        }
    ],
    "sg:phone":"+1 206 729 5018",
    "sg:postcode":"98115",
    "sg:province":"WA",
    "sg:tags":[
        "business"
    ],
    "wof:name":"Safety Learning Institute Inc",
    "wof:placetype":"venue"
},
  "geometry": {"coordinates":[-122.299919,47.692634],"type":"Point"}
}