{
  "type": "Feature",
  "properties": {
    "addr:full":"8601 NE 12th St Medina WA 98039",
    "addr:housenumber":"8601",
    "addr:postcode":"98039",
    "addr:street":"Ne 12Th St",
    "iso:country":"US",
    "sg:address":"8601 NE 12th St",
    "sg:city":"Medina",
    "sg:classifiers":[
        {
            "category":"Education",
            "subcategory":"Special Training",
            "type":"Public Place"
        }
    ],
    "sg:phone":"+1 425 637 9026",
    "sg:postcode":"98039",
    "sg:province":"WA",
    "sg:tags":[
        "instruction",
        "music"
    ],
    "sg:website":"www.eastsidegirlschoir.com",
    "wof:name":"Eastside Girls Choir Ensemble",
    "wof:placetype":"venue"
},
  "geometry": {"coordinates":[-122.22602500000001,47.620965],"type":"Point"}
}