{
  "type": "Feature",
  "properties": {
    "addr:full":"6416 W Okanogan Ave Kennewick WA 99336",
    "addr:housenumber":"6416",
    "addr:postcode":"99336",
    "addr:street":"W Okanogan Ave",
    "iso:country":"US",
    "sg:address":"6416 W Okanogan Ave",
    "sg:city":"Kennewick",
    "sg:classifiers":[
        {
            "category":"Wholesale",
            "subcategory":"Machinery & Supplies",
            "type":"Manufacturing & Wholesale Goods"
        }
    ],
    "sg:phone":"+1 509 735 4489",
    "sg:postcode":"99336",
    "sg:province":"WA",
    "sg:tags":[
        "abrasive",
        "tool",
        "cutting"
    ],
    "wof:name":"BCT Industrial Tool Inc",
    "wof:placetype":"venue"
},
  "geometry": {"coordinates":[-119.209566,46.215978],"type":"Point"}
}