{
  "type": "Feature",
  "properties": {
    "addr:full":"107 S Main St Coupeville WA 98239",
    "addr:housenumber":"107",
    "addr:postcode":"98239",
    "addr:street":"S Main St",
    "iso:country":"US",
    "sg:address":"107 S Main St",
    "sg:city":"Coupeville",
    "sg:classifiers":[
        {
            "category":"Health Services",
            "subcategory":"Doctor",
            "type":"Services"
        }
    ],
    "sg:phone":"+1 360 678 2128",
    "sg:postcode":"98239",
    "sg:province":"WA",
    "sg:tags":[
        "physician",
        "surgeon"
    ],
    "wof:name":"Nw Aesthetic Surgeons",
    "wof:placetype":"venue"
},
  "geometry": {"coordinates":[-122.68607,48.211268],"type":"Point"}
}