{
  "type": "Feature",
  "properties": {
    "addr:full":"15004 62nd Ave E Puyallup WA 98375",
    "addr:housenumber":"15004",
    "addr:postcode":"98375",
    "addr:street":"62Nd Ave E",
    "iso:country":"US",
    "sg:address":"15004 62nd Ave E",
    "sg:city":"Puyallup",
    "sg:classifiers":[
        {
            "category":"Farming",
            "subcategory":"Fish & Marine Products",
            "type":"Manufacturing & Wholesale Goods"
        }
    ],
    "sg:phone":"+1 253 531 3985",
    "sg:postcode":"98375",
    "sg:province":"WA",
    "sg:tags":[
        "fishing"
    ],
    "wof:name":"John T Meyer Fishing",
    "wof:placetype":"venue"
},
  "geometry": {"coordinates":[-122.346732,47.119865],"type":"Point"}
}