{
  "type": "Feature",
  "properties": {
    "addr:full":"11040 Mountain View Skiff Point Bainbridge Island WA 98110",
    "addr:housenumber":"11040",
    "addr:postcode":"98110",
    "addr:street":"Mountain;Skiff",
    "iso:country":"US",
    "sg:address":"11040 Mountain View Skiff Point",
    "sg:city":"Bainbridge Island",
    "sg:classifiers":[
        {
            "category":"Travel",
            "subcategory":"Hotels & Motels",
            "type":"Entertainment"
        },
        {
            "category":"Travel",
            "subcategory":"Bed & Breakfast",
            "type":"Entertainment"
        }
    ],
    "sg:phone":"+1 206 842 7026",
    "sg:postcode":"98110",
    "sg:province":"WA",
    "sg:tags":[
        "house",
        "guest"
    ],
    "wof:name":"Skiff Point Guest House and Retreat",
    "wof:placetype":"venue"
},
  "geometry": {"coordinates":[-122.50299800000001,47.6633],"type":"Point"}
}