{
  "type": "Feature",
  "properties": {
    "addr:full":"3213 NW Bliss Rd Vancouver WA 98685",
    "addr:housenumber":"3213",
    "addr:postcode":"98685",
    "addr:street":"Nw Bliss Rd",
    "iso:country":"US",
    "sg:address":"3213 NW Bliss Rd",
    "sg:city":"Vancouver",
    "sg:classifiers":[
        {
            "category":"Building & Trades",
            "subcategory":"Construction",
            "type":"Services"
        }
    ],
    "sg:phone":"+1 360 571 0555",
    "sg:postcode":"98685",
    "sg:province":"WA",
    "sg:tags":[
        "general",
        "contractor"
    ],
    "wof:name":"Craig Lee Construction",
    "wof:placetype":"venue"
},
  "geometry": {"coordinates":[-122.705534,45.725324],"type":"Point"}
}