{
  "type": "Feature",
  "properties": {
    "iso:country":"US",
    "sg:address":"10924 Mukilteo Speedway",
    "sg:city":"Mukilteo",
    "sg:classifiers":[
        {
            "category":"Restaurant",
            "type":"Food & Drink"
        }
    ],
    "sg:phone":"+1 425 315 0512",
    "sg:postcode":"98275",
    "sg:province":"WA",
    "sg:tags":[
        "eating"
    ],
    "wof:name":"Henry's Donut",
    "wof:placetype":"venue"
},
  "geometry": {"coordinates":[-122.291696,47.899714],"type":"Point"}
}