{
  "type": "Feature",
  "properties": {
    "addr:full":"12514 S Clear Lake Rd Medical Lake WA 99022",
    "addr:housenumber":"12514",
    "addr:postcode":"99022",
    "addr:street":"S Clear Lake Rd",
    "iso:country":"US",
    "sg:address":"12514 S Clear Lake Rd",
    "sg:city":"Medical Lake",
    "sg:classifiers":[
        {
            "category":"Travel",
            "subcategory":"Campground",
            "type":"Entertainment"
        }
    ],
    "sg:phone":"+1 509 299 3717",
    "sg:postcode":"99022",
    "sg:province":"WA",
    "sg:tags":[
        "camp"
    ],
    "wof:name":"Rainbow Cove",
    "wof:placetype":"venue"
},
  "geometry": {"coordinates":[-117.68282000000001,47.538697],"type":"Point"}
}