{
  "type": "Feature",
  "properties": {
    "addr:full":"1201 3rd Ave Seattle WA 98101",
    "addr:housenumber":"1201",
    "addr:postcode":"98101",
    "addr:street":"3Rd Ave",
    "iso:country":"US",
    "sg:address":"1201 3rd Ave",
    "sg:city":"Seattle",
    "sg:classifiers":[
        {
            "category":"Professional",
            "subcategory":"Lawyer & Legal Services",
            "type":"Services"
        }
    ],
    "sg:phone":"+1 206 340 1000",
    "sg:postcode":"98101",
    "sg:province":"WA",
    "sg:tags":[
        "attorney",
        "law",
        "business"
    ],
    "sg:website":"http://www.cozen.com",
    "wof:name":"Cozen O'connor",
    "wof:placetype":"venue"
},
  "geometry": {"coordinates":[-122.335663,47.607391],"type":"Point"}
}