{
  "type": "Feature",
  "properties": {
    "addr:full":"10120 22nd Ave E Tacoma WA 98445",
    "addr:housenumber":"10120",
    "addr:postcode":"98445",
    "addr:street":"22Nd Ave E",
    "iso:country":"US",
    "sg:address":"10120 22nd Ave E",
    "sg:city":"Tacoma",
    "sg:classifiers":[
        {
            "category":"Building & Trades",
            "subcategory":"Construction",
            "type":"Services"
        }
    ],
    "sg:phone":"+1 253 535 9335",
    "sg:postcode":"98445",
    "sg:province":"WA",
    "sg:tags":[
        "home",
        "builder",
        "contractor"
    ],
    "wof:name":"Reding Construction",
    "wof:placetype":"venue"
},
  "geometry": {"coordinates":[-122.400049,47.164938],"type":"Point"}
}