{
  "type": "Feature",
  "properties": {
    "iso:country":"US",
    "sg:address":"925 W Old Kettle Rd",
    "sg:city":"Kettle Falls",
    "sg:classifiers":[
        {
            "category":"Retail",
            "subcategory":"Repair Shop",
            "type":"Services"
        }
    ],
    "sg:phone":"+1 509 738 2867",
    "sg:postcode":"99141",
    "sg:province":"WA",
    "wof:name":"M&R Upholstery",
    "wof:placetype":"venue"
},
  "geometry": {"coordinates":[-118.071202,48.599378],"type":"Point"}
}