{
  "type": "Feature",
  "properties": {
    "addr:full":"1928 S Commons Federal Way WA 98003",
    "addr:housenumber":"1928",
    "addr:postcode":"98003",
    "addr:street":"S Commons",
    "iso:country":"US",
    "sg:address":"1928 S Commons",
    "sg:city":"Federal Way",
    "sg:classifiers":[
        {
            "category":"Ice Cream",
            "type":"Food & Drink"
        }
    ],
    "sg:menulink":"http://www.allmenus.com/wa/auburn/209432-tcby/menu/",
    "sg:postcode":"98003",
    "sg:province":"WA",
    "sg:tags":[
        "smoothy",
        "juice",
        "american"
    ],
    "wof:name":"TCBY",
    "wof:placetype":"venue"
},
  "geometry": {"coordinates":[-122.304008,47.31298],"type":"Point"}
}