{
  "type": "Feature",
  "properties": {
    "addr:full":"1702 Cypress Ct Milton WA 98354",
    "addr:housenumber":"1702",
    "addr:postcode":"98354",
    "addr:street":"Cypress Ct",
    "iso:country":"US",
    "sg:address":"1702 Cypress Ct",
    "sg:city":"Milton",
    "sg:classifiers":[
        {
            "category":"Professional",
            "subcategory":"Management & Consulting",
            "type":"Services"
        }
    ],
    "sg:phone":"+1 253 838 7518",
    "sg:postcode":"98354",
    "sg:province":"WA",
    "sg:tags":[
        "business"
    ],
    "wof:name":"Loren Sebastian De La Osa",
    "wof:placetype":"venue"
},
  "geometry": {"coordinates":[-122.311351,47.25883],"type":"Point"}
}