{
  "type": "Feature",
  "properties": {
    "addr:full":"15370 Rd 12 SW Royal City WA 99357",
    "addr:postcode":"15370;99357",
    "addr:street":"Rd 12 Sw",
    "iso:country":"US",
    "sg:address":"15370 Rd 12 SW",
    "sg:city":"Royal City",
    "sg:classifiers":[
        {
            "category":"Professional",
            "type":"Services"
        }
    ],
    "sg:phone":"+1 509 346 2048",
    "sg:postcode":"99357",
    "sg:province":"WA",
    "sg:tags":[
        "establishment"
    ],
    "wof:name":"Stein-Quail Ridge",
    "wof:placetype":"venue"
},
  "geometry": {"coordinates":[-119.81446099999999,46.914097],"type":"Point"}
}