{
  "type": "Feature",
  "properties": {
    "iso:country":"US",
    "sg:address":"4064 A St",
    "sg:city":"Tacoma",
    "sg:classifiers":[
        {
            "category":"Organizations",
            "subcategory":"Religious Organization",
            "type":"Services"
        }
    ],
    "sg:phone":"+1 253 472 5227",
    "sg:postcode":"98418",
    "sg:province":"WA",
    "sg:tags":[
        "church"
    ],
    "wof:name":"Gospel Hall",
    "wof:placetype":"venue"
},
  "geometry": {"coordinates":[-122.431331,47.218384],"type":"Point"}
}