{
  "type": "Feature",
  "properties": {
    "iso:country":"US",
    "sg:address":"1319 N Argonne Rd",
    "sg:city":"Spokane Valley",
    "sg:classifiers":[
        {
            "category":"Banks & Credit Unions",
            "subcategory":"Bank",
            "type":"Services"
        }
    ],
    "sg:phone":"+1 509 532 1691",
    "sg:postcode":"99212",
    "sg:province":"WA",
    "sg:tags":[
        "firm",
        "loan",
        "broker",
        "mortgage",
        "investment"
    ],
    "wof:name":"Horizon Mortgage & Investment",
    "wof:placetype":"venue"
},
  "geometry": {"coordinates":[-117.282875,47.668586],"type":"Point"}
}