{
  "type": "Feature",
  "properties": {
    "addr:full":"622 N Dick Rd Spokane WA 99212",
    "addr:housenumber":"622",
    "addr:postcode":"99212",
    "addr:street":"N Dick Rd",
    "iso:country":"US",
    "sg:address":"622 N Dick Rd",
    "sg:city":"Spokane",
    "sg:classifiers":[
        {
            "category":"Retail",
            "subcategory":"Repair Shop",
            "type":"Services"
        }
    ],
    "sg:phone":"+1 509 928 4544",
    "sg:postcode":"99212",
    "sg:province":"WA",
    "sg:tags":[
        "electrical"
    ],
    "wof:name":"Pro Flash",
    "wof:placetype":"venue"
},
  "geometry": {"coordinates":[-117.296212,47.663947],"type":"Point"}
}