{
  "type": "Feature",
  "properties": {
    "addr:full":"110 S 4th St Yakima WA 98901",
    "addr:housenumber":"110",
    "addr:postcode":"98901",
    "addr:street":"S 4Th St",
    "iso:country":"US",
    "sg:address":"110 S 4th St",
    "sg:city":"Yakima",
    "sg:phone":"+1 509 248 5565",
    "sg:postcode":"98901",
    "sg:province":"WA",
    "wof:name":"Asian Mart Siam Hse Thai Rest",
    "wof:placetype":"venue"
},
  "geometry": {"coordinates":[-120.500934,46.601852],"type":"Point"}
}