{
  "type": "Feature",
  "properties": {
    "addr:full":"180 E Heights Pl N Belfair WA 98528",
    "addr:housenumber":"180",
    "addr:postcode":"98528",
    "addr:street":"E Heights Pl N",
    "iso:country":"US",
    "sg:address":"180 E Heights Pl N",
    "sg:city":"Belfair",
    "sg:classifiers":[
        {
            "category":"Manufacturing",
            "subcategory":"Lumber",
            "type":"Manufacturing & Wholesale Goods"
        }
    ],
    "sg:phone":"+1 360 275 8248",
    "sg:postcode":"98528",
    "sg:province":"WA",
    "sg:tags":[
        "forestry",
        "consulting"
    ],
    "wof:name":"John K Piety",
    "wof:placetype":"venue"
},
  "geometry": {"coordinates":[-122.932483,47.379801],"type":"Point"}
}