{
  "type": "Feature",
  "properties": {
    "addr:full":"8525 152nd Ave NE Redmond WA 98052",
    "addr:housenumber":"8525",
    "addr:postcode":"98052",
    "addr:street":"152Nd Ave Ne",
    "iso:country":"US",
    "sg:address":"8525 152nd Ave NE",
    "sg:city":"Redmond",
    "sg:classifiers":[
        {
            "category":"Wholesale",
            "subcategory":"Auto Parts",
            "type":"Manufacturing & Wholesale Goods"
        }
    ],
    "sg:phone":"+1 425 861 8119",
    "sg:postcode":"98052",
    "sg:province":"WA",
    "wof:name":"Olympic Brake Supply",
    "wof:placetype":"venue"
},
  "geometry": {"coordinates":[-122.13775699999999,47.682014],"type":"Point"}
}