{
  "type": "Feature",
  "properties": {
    "addr:full":"7840 Old Hwy 99 SE Olympia WA 98501",
    "addr:housenumber":"7840",
    "addr:postcode":"98501",
    "addr:street":"Old Hwy 99 Se",
    "iso:country":"US",
    "sg:address":"7840 Old Hwy 99 SE",
    "sg:city":"Olympia",
    "sg:classifiers":[
        {
            "category":"Retail",
            "subcategory":"Auto Repair",
            "type":"Services"
        }
    ],
    "sg:phone":"+1 360 352 6808",
    "sg:postcode":"98501",
    "sg:province":"WA",
    "sg:tags":[
        "automotive"
    ],
    "wof:name":"Tumwater Muffler & Brake",
    "wof:placetype":"venue"
},
  "geometry": {"coordinates":[-122.893933,46.973606],"type":"Point"}
}