{
  "type": "Feature",
  "properties": {
    "addr:full":"7045 Beach Dr SW Seattle WA 98136",
    "addr:housenumber":"7045",
    "addr:postcode":"98136",
    "addr:street":"Beach Dr Sw",
    "iso:country":"US",
    "sg:address":"7045 Beach Dr SW",
    "sg:city":"Seattle",
    "sg:classifiers":[
        {
            "category":"Real Estate",
            "subcategory":"Real Estate Operator",
            "type":"Services"
        }
    ],
    "sg:phone":"+1 206 938 3129",
    "sg:postcode":"98136",
    "sg:province":"WA",
    "sg:tags":[
        "building",
        "apartment"
    ],
    "wof:name":"Logan Apartments LLC",
    "wof:placetype":"venue"
},
  "geometry": {"coordinates":[-122.39600799999999,47.537111],"type":"Point"}
}