{
  "type": "Feature",
  "properties": {
    "iso:country":"US",
    "sg:address":"396 Dyes View Ct",
    "sg:city":"Bremerton",
    "sg:classifiers":[
        {
            "category":"Professional",
            "type":"Services"
        }
    ],
    "sg:phone":"+1 360 478 0529",
    "sg:postcode":"98311",
    "sg:province":"WA",
    "wof:name":"Eileen S Mitchell",
    "wof:placetype":"venue"
},
  "geometry": {"coordinates":[-122.654471,47.611459],"type":"Point"}
}