{
  "type": "Feature",
  "properties": {
    "addr:full":"7537 Postma Rd Moxee WA 98936",
    "addr:housenumber":"7537",
    "addr:postcode":"98936",
    "addr:street":"Postma Rd",
    "iso:country":"US",
    "sg:address":"7537 Postma Rd",
    "sg:city":"Moxee",
    "sg:classifiers":[
        {
            "category":"Manufacturing",
            "subcategory":"Petroleum Products",
            "type":"Manufacturing & Wholesale Goods"
        }
    ],
    "sg:phone":"+1 800 422 8923",
    "sg:postcode":"98936",
    "sg:province":"WA",
    "sg:tags":[
        "contract"
    ],
    "sg:website":"http://www.farwestfabricators.com",
    "wof:name":"Farwest Fabricators",
    "wof:placetype":"venue"
},
  "geometry": {"coordinates":[-120.401416,46.562554],"type":"Point"}
}