{
  "type": "Feature",
  "properties": {
    "addr:full":"18702 NE Fourth Plain Rd Vancouver WA 98682",
    "addr:housenumber":"18702",
    "addr:postcode":"98682",
    "addr:street":"Ne Fourth Plain Rd",
    "iso:country":"US",
    "sg:address":"18702 NE Fourth Plain Rd",
    "sg:city":"Vancouver",
    "sg:classifiers":[
        {
            "category":"Organizations",
            "subcategory":"Religious Organization",
            "type":"Services"
        }
    ],
    "sg:phone":"+1 360 892 3216",
    "sg:postcode":"98682",
    "sg:province":"WA",
    "wof:name":"Proebstel Evang Free Church",
    "wof:placetype":"venue"
},
  "geometry": {"coordinates":[-122.480149,45.667122],"type":"Point"}
}