{
  "type": "Feature",
  "properties": {
    "addr:full":"10416 NE 156th St Brush Prairie WA 98606",
    "addr:housenumber":"10416",
    "addr:postcode":"98606",
    "addr:street":"Ne 156Th St",
    "iso:country":"US",
    "sg:address":"10416 NE 156th St",
    "sg:city":"Brush Prairie",
    "sg:classifiers":[
        {
            "category":"Professional",
            "subcategory":"Art Services",
            "type":"Services"
        }
    ],
    "sg:phone":"+1 360 254 4638",
    "sg:postcode":"98606",
    "sg:province":"WA",
    "sg:tags":[
        "photography",
        "commercial"
    ],
    "wof:name":"Annette Lynn Pitel",
    "wof:placetype":"venue"
},
  "geometry": {"coordinates":[-122.56796300000001,45.73531],"type":"Point"}
}