{
  "type": "Feature",
  "properties": {
    "addr:full":"6923 Lakewood Dr W Tacoma WA 98467",
    "addr:housenumber":"6923",
    "addr:postcode":"98467",
    "addr:street":"Lakewood Dr W",
    "iso:country":"US",
    "sg:address":"6923 Lakewood Dr W",
    "sg:city":"Tacoma",
    "sg:classifiers":[
        {
            "category":"Professional",
            "subcategory":"Lawyer & Legal Services",
            "type":"Services"
        }
    ],
    "sg:phone":"+1 253 472 3323",
    "sg:postcode":"98467",
    "sg:province":"WA",
    "wof:name":"Coleman Jeanette",
    "wof:placetype":"venue"
},
  "geometry": {"coordinates":[-122.50859800000001,47.195446],"type":"Point"}
}