{
  "type": "Feature",
  "properties": {
    "addr:full":"200 E Main St Everson WA 98247",
    "addr:housenumber":"200",
    "addr:postcode":"98247",
    "addr:street":"E Main St",
    "iso:country":"US",
    "sg:address":"200 E Main St",
    "sg:city":"Everson",
    "sg:classifiers":[
        {
            "category":"Coffee & Tea",
            "type":"Food & Drink"
        },
        {
            "category":"Restaurant",
            "type":"Food & Drink"
        }
    ],
    "sg:phone":"+1 360 966 3608",
    "sg:postcode":"98247",
    "sg:province":"WA",
    "sg:tags":[
        "shop",
        "espresso"
    ],
    "wof:name":"Java Express-O",
    "wof:placetype":"venue"
},
  "geometry": {"coordinates":[-122.341339,48.920151],"type":"Point"}
}