{
  "type": "Feature",
  "properties": {
    "addr:full":"1319 6th St Anacortes WA 98221",
    "addr:housenumber":"1319",
    "addr:postcode":"98221",
    "addr:street":"6Th St",
    "iso:country":"US",
    "sg:address":"1319 6th St",
    "sg:city":"Anacortes",
    "sg:classifiers":[
        {
            "category":"Building & Trades",
            "subcategory":"Construction",
            "type":"Services"
        }
    ],
    "sg:phone":"+1 360 293 9350",
    "sg:postcode":"98221",
    "sg:province":"WA",
    "sg:tags":[
        "wallcoverings-installation",
        "wallpaper",
        "painting",
        "contractor"
    ],
    "wof:name":"Stegman Painting & Wall Covering",
    "wof:placetype":"venue"
},
  "geometry": {"coordinates":[-122.61751099999999,48.517512],"type":"Point"}
}