{
  "type": "Feature",
  "properties": {
    "addr:full":"3405 Marion Pl Greenbank WA 98253",
    "addr:housenumber":"3405",
    "addr:postcode":"98253",
    "addr:street":"Marion Pl",
    "iso:country":"US",
    "sg:address":"3405 Marion Pl",
    "sg:city":"Greenbank",
    "sg:classifiers":[
        {
            "category":"Manufacturing",
            "subcategory":"Tools & Machinery",
            "type":"Manufacturing & Wholesale Goods"
        }
    ],
    "sg:phone":"+1 360 678 8705",
    "sg:postcode":"98253",
    "sg:province":"WA",
    "sg:tags":[
        "safety",
        "lighting",
        "manufacturer"
    ],
    "wof:name":"AG Design & Associates Inc",
    "wof:placetype":"venue"
},
  "geometry": {"coordinates":[-122.56332399999999,48.086813],"type":"Point"}
}