{
  "type": "Feature",
  "properties": {
    "addr:full":"16625 Redmond Way Ste M Redmond WA 98052",
    "addr:housenumber":"16625",
    "addr:postcode":"98052",
    "addr:street":"Redmond Way Ste M",
    "iso:country":"US",
    "sg:address":"16625 Redmond Way Ste M",
    "sg:city":"Redmond",
    "sg:classifiers":[
        {
            "category":"Retail",
            "subcategory":"Car Wash",
            "type":"Services"
        },
        {
            "category":"Sports & Exercise",
            "subcategory":"Ski Slope",
            "type":"Entertainment"
        }
    ],
    "sg:phone":"+1 425 861 5972",
    "sg:postcode":"98052",
    "sg:province":"WA",
    "sg:tags":[
        "instruction"
    ],
    "wof:name":"Lake Washington Snowsports Council",
    "wof:placetype":"venue"
},
  "geometry": {"coordinates":[-122.11865899999999,47.673084],"type":"Point"}
}