{
  "type": "Feature",
  "properties": {
    "addr:full":"20926 Marine View Dr SW Seattle WA 98166",
    "addr:housenumber":"20926",
    "addr:postcode":"98166",
    "addr:street":"Marine View Dr Sw",
    "iso:country":"US",
    "sg:address":"20926 Marine View Dr SW",
    "sg:city":"Seattle",
    "sg:classifiers":[
        {
            "category":"Building & Trades",
            "subcategory":"Construction",
            "type":"Services"
        }
    ],
    "sg:phone":"+1 206 878 8763",
    "sg:postcode":"98166",
    "sg:province":"WA",
    "sg:tags":[
        "house"
    ],
    "wof:name":"McKindley Construction",
    "wof:placetype":"venue"
},
  "geometry": {"coordinates":[-122.338779,47.41535],"type":"Point"}
}