{
  "type": "Feature",
  "properties": {
    "addr:full":"97 Tornquist Rd Mc Cleary WA 98557",
    "addr:housenumber":"97",
    "addr:postcode":"98557",
    "addr:street":"Tornquist Rd",
    "iso:country":"US",
    "sg:address":"97 Tornquist Rd",
    "sg:city":"Mc Cleary",
    "sg:classifiers":[
        {
            "category":"Professional",
            "type":"Services"
        }
    ],
    "sg:phone":"+1 360 495 4319",
    "sg:postcode":"98557",
    "sg:province":"WA",
    "wof:name":"Watts East County Emu Ran",
    "wof:placetype":"venue"
},
  "geometry": {"coordinates":[-123.236896,47.07679],"type":"Point"}
}