{
  "type": "Feature",
  "properties": {
    "addr:full":"6727 Evergreen Way Everett WA 98203",
    "addr:housenumber":"6727",
    "addr:postcode":"98203",
    "addr:street":"Evergreen Way",
    "iso:country":"US",
    "sg:address":"6727 Evergreen Way",
    "sg:city":"Everett",
    "sg:classifiers":[
        {
            "category":"Banks & Credit Unions",
            "subcategory":"Bank",
            "type":"Services"
        }
    ],
    "sg:phone":"+1 425 347 8892",
    "sg:postcode":"98203",
    "sg:province":"WA",
    "wof:name":"US Bank",
    "wof:placetype":"venue"
},
  "geometry": {"coordinates":[-122.218487,47.938117],"type":"Point"}
}