{
  "type": "Feature",
  "properties": {
    "addr:full":"1501 S Gold St Centralia WA 98531",
    "addr:housenumber":"1501",
    "addr:postcode":"98531",
    "addr:street":"S Gold St",
    "iso:country":"US",
    "sg:address":"1501 S Gold St",
    "sg:city":"Centralia",
    "sg:classifiers":[
        {
            "category":"Sports & Exercise",
            "subcategory":"Bowling",
            "type":"Entertainment"
        }
    ],
    "sg:phone":"+1 360 736 4100",
    "sg:postcode":"98531",
    "sg:province":"WA",
    "sg:tags":[
        "center"
    ],
    "wof:name":"Fairway Lanes",
    "wof:placetype":"venue"
},
  "geometry": {"coordinates":[-122.95751199999999,46.69931],"type":"Point"}
}