{
  "type": "Feature",
  "properties": {
    "addr:full":"8706 S 222nd St Kent WA 98031",
    "addr:housenumber":"8706",
    "addr:postcode":"98031",
    "addr:street":"S 222Nd St",
    "iso:country":"US",
    "sg:address":"8706 S 222nd St",
    "sg:city":"Kent",
    "sg:classifiers":[
        {
            "category":"Professional",
            "type":"Services"
        }
    ],
    "sg:phone":"+1 253 437 1388",
    "sg:postcode":"98031",
    "sg:province":"WA",
    "sg:tags":[
        "establishment"
    ],
    "wof:name":"Inspectorate America Corp",
    "wof:placetype":"venue"
},
  "geometry": {"coordinates":[-122.22343100000001,47.403134],"type":"Point"}
}