{
  "type": "Feature",
  "properties": {
    "addr:full":"2804 W Washington Ave Yakima WA 98903",
    "addr:housenumber":"2804",
    "addr:postcode":"98903",
    "addr:street":"W Washington Ave",
    "iso:country":"US",
    "sg:address":"2804 W Washington Ave",
    "sg:city":"Yakima",
    "sg:classifiers":[
        {
            "category":"Manufacturing",
            "subcategory":"Printing",
            "type":"Manufacturing & Wholesale Goods"
        }
    ],
    "sg:phone":"+1 509 248 1129",
    "sg:postcode":"98903",
    "sg:province":"WA",
    "sg:tags":[
        "shop",
        "lettering",
        "screen",
        "painting",
        "sign"
    ],
    "wof:name":"Solar Graphics Inc",
    "wof:placetype":"venue"
},
  "geometry": {"coordinates":[-120.556635,46.574294],"type":"Point"}
}