{
  "type": "Feature",
  "properties": {
    "addr:full":"2456 Strawberry Point Rd Oak Harbor WA 98277",
    "addr:housenumber":"2456",
    "addr:postcode":"98277",
    "addr:street":"Strawberry Point Rd",
    "iso:country":"US",
    "sg:address":"2456 Strawberry Point Rd",
    "sg:city":"Oak Harbor",
    "sg:classifiers":[
        {
            "category":"Shopping",
            "subcategory":"Jewelry",
            "type":"Retail Goods"
        }
    ],
    "sg:phone":"+1 360 678 5960",
    "sg:postcode":"98277",
    "sg:province":"WA",
    "wof:name":"ESpecialle Five Jewelers",
    "wof:placetype":"venue"
},
  "geometry": {"coordinates":[-122.512259,48.30102],"type":"Point"}
}