{
  "type": "Feature",
  "properties": {
    "addr:full":"536 Wells Ave S Suite 119 Renton WA 98057",
    "addr:housenumber":"536",
    "addr:postcode":"98057",
    "addr:street":"Wells Ave S Suite 119",
    "iso:country":"US",
    "sg:address":"536 Wells Ave S Suite 119",
    "sg:city":"Renton",
    "sg:classifiers":[
        {
            "category":"Professional",
            "subcategory":"Accounting & Tax Preparation",
            "type":"Services"
        }
    ],
    "sg:phone":"+1 425 282 6049",
    "sg:postcode":"98057",
    "sg:province":"WA",
    "sg:tags":[
        "accountant"
    ],
    "sg:website":"www.archcpa.com",
    "wof:name":"Arch Accounting",
    "wof:placetype":"venue"
},
  "geometry": {"coordinates":[-122.205225,47.475315],"type":"Point"}
}