{
  "type": "Feature",
  "properties": {
    "addr:full":"13238 4th Ave SW Unit #3 Seattle WA 98146",
    "addr:housenumber":"13238",
    "addr:postcode":"98146",
    "addr:street":"4Th Ave Sw Unit # 3",
    "iso:country":"US",
    "sg:address":"13238 4th Ave SW Unit #3",
    "sg:city":"Seattle",
    "sg:classifiers":[
        {
            "category":"Professional",
            "type":"Services"
        },
        {
            "category":"Building & Trades",
            "subcategory":"Cleaning & Sanitation",
            "type":"Services"
        }
    ],
    "sg:phone":"+1 206 883 3140",
    "sg:postcode":"98146",
    "sg:province":"WA",
    "sg:tags":[
        "home"
    ],
    "sg:website":"www.aguilerascleaning.com",
    "wof:name":"Aguilera's Cleaning Services",
    "wof:placetype":"venue"
},
  "geometry": {"coordinates":[-122.338809,47.48371],"type":"Point"}
}