{
  "type": "Feature",
  "properties": {
    "addr:full":"700 Pat Kennedy Way SW Olympia WA 98501",
    "addr:housenumber":"700",
    "addr:postcode":"98501",
    "addr:street":"Pat Kennedy Way Sw",
    "iso:country":"US",
    "sg:address":"700 Pat Kennedy Way SW",
    "sg:city":"Olympia",
    "sg:classifiers":[
        {
            "category":"Manufacturing",
            "subcategory":"Glass & Minerals",
            "type":"Manufacturing & Wholesale Goods"
        }
    ],
    "sg:phone":"+1 360 956 9002",
    "sg:postcode":"98501",
    "sg:province":"WA",
    "sg:tags":[
        "product",
        "mfg"
    ],
    "wof:name":"Cardinal Cg",
    "wof:placetype":"venue"
},
  "geometry": {"coordinates":[-122.91559700000001,46.969342],"type":"Point"}
}