{
  "type": "Feature",
  "properties": {
    "addr:full":"322 NE Cedar St Camas WA 98607",
    "addr:housenumber":"322",
    "addr:postcode":"98607",
    "addr:street":"Ne Cedar St",
    "iso:country":"US",
    "sg:address":"322 NE Cedar St",
    "sg:city":"Camas",
    "sg:classifiers":[
        {
            "category":"Food & Beverages",
            "subcategory":"Specialty",
            "type":"Retail Goods"
        }
    ],
    "sg:phone":"+1 360 600 9836",
    "sg:postcode":"98607",
    "sg:province":"WA",
    "sg:tags":[
        "sauce",
        "condiment"
    ],
    "sg:website":"www.navidioils.com/",
    "wof:name":"Navidi's Olive Oils & Vinegars",
    "wof:placetype":"venue"
},
  "geometry": {"coordinates":[-122.403757,45.585518],"type":"Point"}
}