{
  "type": "Feature",
  "properties": {
    "addr:full":"4100 SW Edmunds St Seattle WA 98116",
    "addr:housenumber":"4100",
    "addr:postcode":"98116",
    "addr:street":"Sw Edmunds St",
    "iso:country":"US",
    "sg:address":"4100 SW Edmunds St",
    "sg:city":"Seattle",
    "sg:classifiers":[
        {
            "category":"Manufacturing",
            "subcategory":"Tools & Machinery",
            "type":"Manufacturing & Wholesale Goods"
        }
    ],
    "sg:phone":"+1 206 932 2686",
    "sg:postcode":"98116",
    "sg:province":"WA",
    "sg:tags":[
        "instrument",
        "mfg"
    ],
    "wof:name":"Abdo Medical",
    "wof:placetype":"venue"
},
  "geometry": {"coordinates":[-122.38551099999999,47.559317],"type":"Point"}
}