{
  "type": "Feature",
  "properties": {
    "addr:full":"509 W Crow St Kent WA 98032",
    "addr:housenumber":"509",
    "addr:postcode":"98032",
    "addr:street":"W Crow St",
    "iso:country":"US",
    "sg:address":"509 W Crow St",
    "sg:city":"Kent",
    "sg:classifiers":[
        {
            "category":"Building & Trades",
            "subcategory":"Construction",
            "type":"Services"
        }
    ],
    "sg:phone":"+1 206 383 1036",
    "sg:postcode":"98032",
    "sg:province":"WA",
    "sg:tags":[
        "house"
    ],
    "wof:name":"A Brady Company",
    "wof:placetype":"venue"
},
  "geometry": {"coordinates":[-122.23841,47.376462],"type":"Point"}
}