{
  "type": "Feature",
  "properties": {
    "addr:full":"803 39th Ave SW Puyallup WA 98373",
    "addr:housenumber":"803",
    "addr:postcode":"98373",
    "addr:street":"39Th Ave Sw",
    "iso:country":"US",
    "sg:address":"803 39th Ave SW",
    "sg:city":"Puyallup",
    "sg:classifiers":[
        {
            "category":"Professional",
            "subcategory":"Lawyer & Legal Services",
            "type":"Services"
        }
    ],
    "sg:phone":"+1 253 848 4581",
    "sg:postcode":"98373",
    "sg:province":"WA",
    "sg:tags":[
        "attorney"
    ],
    "wof:name":"Pendergrass & Kaukl Inc P S",
    "wof:placetype":"venue"
},
  "geometry": {"coordinates":[-122.302232,47.154912],"type":"Point"}
}