{
  "type": "Feature",
  "properties": {
    "addr:full":"726 W Riverside Ave Spokane WA 99201",
    "addr:housenumber":"726",
    "addr:postcode":"99201",
    "addr:street":"W Riverside Ave",
    "iso:country":"US",
    "sg:address":"726 W Riverside Ave",
    "sg:city":"Spokane",
    "sg:classifiers":[
        {
            "category":"Banks & Credit Unions",
            "subcategory":"Bank",
            "type":"Services"
        }
    ],
    "sg:phone":"+1 509 838 3433",
    "sg:postcode":"99201",
    "sg:province":"WA",
    "wof:name":"Global Credit Union",
    "wof:placetype":"venue"
},
  "geometry": {"coordinates":[-117.42316,47.658003],"type":"Point"}
}