{
  "type": "Feature",
  "properties": {
    "addr:full":"3005 SW 302nd Pl Federal Way WA 98023",
    "addr:housenumber":"3005",
    "addr:postcode":"98023",
    "addr:street":"Sw 302Nd Pl",
    "iso:country":"US",
    "sg:address":"3005 SW 302nd Pl",
    "sg:city":"Federal Way",
    "sg:classifiers":[
        {
            "category":"Building & Trades",
            "subcategory":"Construction",
            "type":"Services"
        }
    ],
    "sg:phone":"+1 253 874 6345",
    "sg:postcode":"98023",
    "sg:province":"WA",
    "sg:tags":[
        "residential"
    ],
    "wof:name":"Manor House Designs",
    "wof:placetype":"venue"
},
  "geometry": {"coordinates":[-122.372641,47.330855],"type":"Point"}
}