{
  "type": "Feature",
  "properties": {
    "addr:full":"9036 Evanston Ave N Seattle WA 98103",
    "addr:housenumber":"9036",
    "addr:postcode":"98103",
    "addr:street":"Evanston Ave N",
    "iso:country":"US",
    "sg:address":"9036 Evanston Ave N",
    "sg:city":"Seattle",
    "sg:classifiers":[
        {
            "category":"Professional",
            "type":"Services"
        }
    ],
    "sg:phone":"+1 206 781 3493",
    "sg:postcode":"98103",
    "sg:province":"WA",
    "sg:tags":[
        "publication",
        "editorial"
    ],
    "wof:name":"Parker Ink",
    "wof:placetype":"venue"
},
  "geometry": {"coordinates":[-122.35124999999999,47.694878],"type":"Point"}
}