{
  "type": "Feature",
  "properties": {
    "addr:full":"2337 138th Ave SE Bellevue WA 98005",
    "addr:housenumber":"2337",
    "addr:postcode":"98005",
    "addr:street":"138Th Ave Se",
    "iso:country":"US",
    "sg:address":"2337 138th Ave SE",
    "sg:city":"Bellevue",
    "sg:classifiers":[
        {
            "category":"Social Services",
            "type":"Services"
        }
    ],
    "sg:phone":"+1 425 746 1479",
    "sg:postcode":"98005",
    "sg:province":"WA",
    "sg:tags":[
        "centers-adult",
        "day",
        "care"
    ],
    "wof:name":"Pleasant Retreat Adult Family Home",
    "wof:placetype":"venue"
},
  "geometry": {"coordinates":[-122.15660200000001,47.589783],"type":"Point"}
}