{
  "type": "Feature",
  "properties": {
    "addr:full":"5136 Guide Meridian Rd Bellingham WA 98226",
    "addr:housenumber":"5136",
    "addr:postcode":"98226",
    "addr:street":"Guide Meridian Rd",
    "iso:country":"US",
    "sg:address":"5136 Guide Meridian Rd",
    "sg:city":"Bellingham",
    "sg:classifiers":[
        {
            "category":"Autos & Motor Vehicles",
            "subcategory":"Automobile Sales",
            "type":"Retail Goods"
        }
    ],
    "sg:phone":"+1 360 398 2260",
    "sg:postcode":"98226",
    "sg:province":"WA",
    "sg:tags":[
        "machinery"
    ],
    "wof:name":"Circle A Trailers Inc",
    "wof:placetype":"venue"
},
  "geometry": {"coordinates":[-122.48593,48.827036],"type":"Point"}
}