{
  "type": "Feature",
  "properties": {
    "addr:full":"316 W Boone Ave Suite 584 Spokane WA 99201",
    "addr:housenumber":"316",
    "addr:postcode":"99201",
    "addr:street":"W Boone Ave Suite 584",
    "iso:country":"US",
    "sg:address":"316 W Boone Ave Suite 584",
    "sg:city":"Spokane",
    "sg:classifiers":[
        {
            "category":"Professional",
            "subcategory":"Employment Agencies",
            "type":"Services"
        }
    ],
    "sg:phone":"+1 509 315 2485",
    "sg:postcode":"99201",
    "sg:province":"WA",
    "sg:tags":[
        "opportunity"
    ],
    "sg:website":"http://www.spherion.com/spokane",
    "wof:name":"Spherion",
    "wof:placetype":"venue"
},
  "geometry": {"coordinates":[-117.41611399999999,47.668091],"type":"Point"}
}