{
  "type": "Feature",
  "properties": {
    "addr:full":"15606 E Sprague Ave Veradale WA 99037",
    "addr:housenumber":"15606",
    "addr:postcode":"99037",
    "addr:street":"E Sprague Ave",
    "iso:country":"US",
    "sg:address":"15606 E Sprague Ave",
    "sg:city":"Veradale",
    "sg:classifiers":[
        {
            "category":"Banks & Credit Unions",
            "subcategory":"Bank",
            "type":"Services"
        }
    ],
    "sg:phone":"+1 509 927 2794",
    "sg:postcode":"99037",
    "sg:province":"WA",
    "sg:tags":[
        "mortgage"
    ],
    "wof:name":"Americanwest Bancorporation",
    "wof:placetype":"venue"
},
  "geometry": {"coordinates":[-117.192041,47.656924],"type":"Point"}
}