{
  "type": "Feature",
  "properties": {
    "addr:full":"194 E Valley Rd Skamokawa WA 98647",
    "addr:housenumber":"194",
    "addr:postcode":"98647",
    "addr:street":"E Valley Rd",
    "iso:country":"US",
    "sg:address":"194 E Valley Rd",
    "sg:city":"Skamokawa",
    "sg:classifiers":[
        {
            "category":"Food & Beverages",
            "subcategory":"Specialty",
            "type":"Retail Goods"
        }
    ],
    "sg:phone":"+1 360 795 3255",
    "sg:postcode":"98647",
    "sg:province":"WA",
    "wof:name":"Debbie Chmbrlain Hrblife Distr",
    "wof:placetype":"venue"
},
  "geometry": {"coordinates":[-123.446364,46.284954],"type":"Point"}
}