{
  "type": "Feature",
  "properties": {
    "addr:full":"2501 SE Columbia Way Ste 300 Vancouver WA 98661",
    "addr:housenumber":"2501",
    "addr:postcode":"98661",
    "addr:street":"Se Columbia Way Ste 300",
    "iso:country":"US",
    "sg:address":"2501 SE Columbia Way Ste 300",
    "sg:city":"Vancouver",
    "sg:classifiers":[
        {
            "category":"Professional",
            "subcategory":"Employment Agencies",
            "type":"Services"
        }
    ],
    "sg:phone":"+1 360 695 0137",
    "sg:postcode":"98661",
    "sg:province":"WA",
    "wof:name":"K-M Services Inc",
    "wof:placetype":"venue"
},
  "geometry": {"coordinates":[-122.652,45.617298],"type":"Point"}
}