{
  "type": "Feature",
  "properties": {
    "addr:full":"1126 W Ainsworth St Pasco WA 99301",
    "addr:housenumber":"1126",
    "addr:postcode":"99301",
    "addr:street":"W Ainsworth St",
    "iso:country":"US",
    "sg:address":"1126 W Ainsworth St",
    "sg:city":"Pasco",
    "sg:classifiers":[
        {
            "category":"Home & Garden",
            "subcategory":"Garden Supply",
            "type":"Retail Goods"
        },
        {
            "category":"Home & Garden",
            "subcategory":"Building Materials",
            "type":"Retail Goods"
        },
        {
            "category":"Shopping",
            "subcategory":"Pets & Pet Supplies",
            "type":"Retail Goods"
        },
        {
            "category":"Building & Trades",
            "subcategory":"Construction",
            "type":"Services"
        }
    ],
    "sg:phone":"+1 509 547 5577",
    "sg:postcode":"99301",
    "sg:province":"WA",
    "sg:tags":[
        "feed",
        "fence",
        "contractor",
        "fertilizer",
        "fence-sales"
    ],
    "sg:website":"http://www.bleyhl.com",
    "wof:name":"Farm Mart 11458",
    "wof:placetype":"venue"
},
  "geometry": {"coordinates":[-119.101411,46.224139],"type":"Point"}
}