{
  "type": "Feature",
  "properties": {
    "addr:full":"10838 26th Ave SW Seattle WA 98146",
    "addr:housenumber":"10838",
    "addr:postcode":"98146",
    "addr:street":"26Th Ave Sw",
    "iso:country":"US",
    "sg:address":"10838 26th Ave SW",
    "sg:city":"Seattle",
    "sg:classifiers":[
        {
            "category":"Professional",
            "subcategory":"Management & Consulting",
            "type":"Services"
        }
    ],
    "sg:phone":"+1 206 522 7716",
    "sg:postcode":"98146",
    "sg:province":"WA",
    "wof:name":"Mary Frances Burns",
    "wof:placetype":"venue"
},
  "geometry": {"coordinates":[-122.365726,47.507419],"type":"Point"}
}