{
  "type": "Feature",
  "properties": {
    "addr:full":"208 207th Ave NE Sammamish WA 98074",
    "addr:housenumber":"208",
    "addr:postcode":"98074",
    "addr:street":"207Th Ave Ne",
    "iso:country":"US",
    "sg:address":"208 207th Ave NE",
    "sg:city":"Sammamish",
    "sg:classifiers":[
        {
            "category":"Real Estate",
            "subcategory":"Real Estate Agent",
            "type":"Services"
        }
    ],
    "sg:phone":"+1 425 466 5178",
    "sg:postcode":"98074",
    "sg:province":"WA",
    "wof:name":"Whistler Condos Direct",
    "wof:placetype":"venue"
},
  "geometry": {"coordinates":[-122.06407299999999,47.612045],"type":"Point"}
}