{
  "type": "Feature",
  "properties": {
    "addr:full":"12623 95th Pl NE Kirkland WA 98034",
    "addr:housenumber":"12623",
    "addr:postcode":"98034",
    "addr:street":"95Th Pl Ne",
    "iso:country":"US",
    "sg:address":"12623 95th Pl NE",
    "sg:city":"Kirkland",
    "sg:classifiers":[
        {
            "category":"Banks & Credit Unions",
            "subcategory":"Financial Services",
            "type":"Services"
        }
    ],
    "sg:phone":"+1 425 821 8251",
    "sg:postcode":"98034",
    "sg:province":"WA",
    "sg:tags":[
        "escrow"
    ],
    "wof:name":"Cameo Escrow",
    "wof:placetype":"venue"
},
  "geometry": {"coordinates":[-122.213623,47.713602],"type":"Point"}
}