{
  "type": "Feature",
  "properties": {
    "addr:full":"1411 Railroad Ave Bellingham WA 98225",
    "addr:housenumber":"1411",
    "addr:postcode":"98225",
    "addr:street":"Railroad",
    "iso:country":"US",
    "sg:address":"1411 Railroad Ave",
    "sg:city":"Bellingham",
    "sg:classifiers":[
        {
            "category":"Shopping",
            "subcategory":"Bicycles & Sporting Goods",
            "type":"Retail Goods"
        }
    ],
    "sg:phone":"+1 360 733 3133",
    "sg:postcode":"98225",
    "sg:province":"WA",
    "wof:name":"Resport Inc",
    "wof:placetype":"venue"
},
  "geometry": {"coordinates":[-122.47525899999999,48.751063],"type":"Point"}
}