{
  "type": "Feature",
  "properties": {
    "iso:country":"US",
    "sg:address":"5317 S Palouse Hwy",
    "sg:city":"Spokane",
    "sg:classifiers":[
        {
            "category":"Professional",
            "type":"Services"
        }
    ],
    "sg:phone":"+1 509 443 1601",
    "sg:postcode":"99223",
    "sg:province":"WA",
    "wof:name":"Federated Services",
    "wof:placetype":"venue"
},
  "geometry": {"coordinates":[-117.35422199999999,47.604168],"type":"Point"}
}