{
  "type": "Feature",
  "properties": {
    "addr:full":"318 E Main St Grandview WA 98930",
    "addr:housenumber":"318",
    "addr:postcode":"98930",
    "addr:street":"E Main St",
    "iso:country":"US",
    "sg:address":"318 E Main St",
    "sg:city":"Grandview",
    "sg:classifiers":[
        {
            "category":"Food & Beverages",
            "subcategory":"Groceries & Convenience Stores",
            "type":"Retail Goods"
        }
    ],
    "sg:phone":"+1 509 882 2085",
    "sg:postcode":"98930",
    "sg:province":"WA",
    "sg:tags":[
        "grocer"
    ],
    "wof:name":"Star Food City",
    "wof:placetype":"venue"
},
  "geometry": {"coordinates":[-119.897769,46.256002],"type":"Point"}
}