{
  "type": "Feature",
  "properties": {
    "addr:full":"267 Monse River Rd Brewster WA 98812",
    "addr:housenumber":"267",
    "addr:postcode":"98812",
    "addr:street":"Monse River Rd",
    "iso:country":"US",
    "sg:address":"267 Monse River Rd",
    "sg:city":"Brewster",
    "sg:classifiers":[
        {
            "category":"Professional",
            "subcategory":"Computer Services",
            "type":"Services"
        }
    ],
    "sg:phone":"+1 509 689 3010",
    "sg:postcode":"98812",
    "sg:province":"WA",
    "sg:tags":[
        "repair"
    ],
    "wof:name":"Computerwise",
    "wof:placetype":"venue"
},
  "geometry": {"coordinates":[-119.707324,48.199671],"type":"Point"}
}