{
  "type": "Feature",
  "properties": {
    "addr:full":"125 S Wenatchee Ave Wenatchee WA 98801",
    "addr:housenumber":"125",
    "addr:postcode":"98801",
    "addr:street":"S Wenatchee Ave",
    "iso:country":"US",
    "sg:address":"125 S Wenatchee Ave",
    "sg:city":"Wenatchee",
    "sg:classifiers":[
        {
            "category":"Home & Garden",
            "subcategory":"Furniture",
            "type":"Retail Goods"
        }
    ],
    "sg:phone":"+1 509 662 4511",
    "sg:postcode":"98801",
    "sg:province":"WA",
    "sg:tags":[
        "store"
    ],
    "wof:name":"Davis Furniture-Sit'n Sleep",
    "wof:placetype":"venue"
},
  "geometry": {"coordinates":[-120.310199,47.423122],"type":"Point"}
}