{
  "type": "Feature",
  "properties": {
    "addr:full":"520 Summit Ave E Seattle WA 98102",
    "addr:housenumber":"520",
    "addr:postcode":"98102",
    "addr:street":"Summit Ave E",
    "iso:country":"US",
    "sg:address":"520 Summit Ave E",
    "sg:city":"Seattle",
    "sg:classifiers":[
        {
            "category":"Food & Beverages",
            "subcategory":"Groceries & Convenience Stores",
            "type":"Retail Goods"
        }
    ],
    "sg:postcode":"98102",
    "sg:province":"WA",
    "wof:name":"Summit Foods",
    "wof:placetype":"venue"
},
  "geometry": {"coordinates":[-122.325329,47.623398],"type":"Point"}
}