{
  "type": "Feature",
  "properties": {
    "addr:full":"19426 327th Ave NE Duvall WA 98019",
    "addr:housenumber":"19426",
    "addr:postcode":"98019",
    "addr:street":"327Th Ave Ne",
    "iso:country":"US",
    "sg:address":"19426 327th Ave NE",
    "sg:city":"Duvall",
    "sg:classifiers":[
        {
            "category":"Shopping",
            "subcategory":"Florist",
            "type":"Retail Goods"
        }
    ],
    "sg:phone":"+1 425 788 0942",
    "sg:postcode":"98019",
    "sg:province":"WA",
    "wof:name":"Kims Floral Creations",
    "wof:placetype":"venue"
},
  "geometry": {"coordinates":[-121.89957200000001,47.763888],"type":"Point"}
}