{
  "type": "Feature",
  "properties": {
    "iso:country":"US",
    "sg:address":"1603 Central St NE",
    "sg:city":"Olympia",
    "sg:classifiers":[
        {
            "category":"Farming",
            "subcategory":"Farm & Veterinary Services",
            "type":"Manufacturing & Wholesale Goods"
        }
    ],
    "sg:phone":"+1 360 534 0346",
    "sg:postcode":"98506",
    "sg:province":"WA",
    "sg:tags":[
        "soil",
        "conservation"
    ],
    "wof:name":"Pacific Rim Soil & Water",
    "wof:placetype":"venue"
},
  "geometry": {"coordinates":[-122.88251,47.059242],"type":"Point"}
}