{
  "type": "Feature",
  "properties": {
    "addr:full":"1900 W Sequim Bay Rd Sequim WA 98382",
    "addr:housenumber":"1900",
    "addr:postcode":"98382",
    "addr:street":"W Sequim Bay Rd",
    "iso:country":"US",
    "sg:address":"1900 W Sequim Bay Rd",
    "sg:city":"Sequim",
    "sg:classifiers":[
        {
            "category":"Building & Trades",
            "subcategory":"Cleaning & Sanitation",
            "type":"Services"
        }
    ],
    "sg:phone":"+1 360 681 7055",
    "sg:postcode":"98382",
    "sg:province":"WA",
    "sg:tags":[
        "maintenance"
    ],
    "wof:name":"Seeview Window Cleaning",
    "wof:placetype":"venue"
},
  "geometry": {"coordinates":[-123.049611,48.070211],"type":"Point"}
}