{
  "type": "Feature",
  "properties": {
    "addr:full":"4812 W Clearwater Ave Kennewick WA 99336",
    "addr:housenumber":"4812",
    "addr:postcode":"99336",
    "addr:street":"W Clearwater Ave",
    "iso:country":"US",
    "sg:address":"4812 W Clearwater Ave",
    "sg:city":"Kennewick",
    "sg:classifiers":[
        {
            "category":"Shopping",
            "subcategory":"Music",
            "type":"Retail Goods"
        }
    ],
    "sg:phone":"+1 509 783 7782",
    "sg:postcode":"99336",
    "sg:province":"WA",
    "wof:name":"Storytellers",
    "wof:placetype":"venue"
},
  "geometry": {"coordinates":[-119.18685000000001,46.212478],"type":"Point"}
}