{
  "type": "Feature",
  "properties": {
    "addr:full":"4234 E Madison St Seattle WA 98112",
    "addr:housenumber":"4234",
    "addr:postcode":"98112",
    "addr:street":"E Madison St",
    "iso:country":"US",
    "sg:address":"4234 E Madison St",
    "sg:city":"Seattle",
    "sg:classifiers":[
        {
            "category":"Restaurant",
            "type":"Food & Drink"
        }
    ],
    "sg:phone":"+1 206 328 1655",
    "sg:postcode":"98112",
    "sg:province":"WA",
    "wof:name":"Hank's By The Lake",
    "wof:placetype":"venue"
},
  "geometry": {"coordinates":[-122.278302,47.635608],"type":"Point"}
}