{
  "type": "Feature",
  "properties": {
    "addr:full":"1015 Pacific Ave Ste 500 Tacoma WA 98402",
    "addr:housenumber":"1015",
    "addr:postcode":"98402",
    "addr:street":"Pacific Ave Ste 500",
    "iso:country":"US",
    "sg:address":"1015 Pacific Ave Ste 500",
    "sg:city":"Tacoma",
    "sg:classifiers":[
        {
            "category":"Manufacturing",
            "subcategory":"Petroleum Products",
            "type":"Manufacturing & Wholesale Goods"
        }
    ],
    "sg:phone":"+1 253 272 4700",
    "sg:postcode":"98402",
    "sg:province":"WA",
    "sg:tags":[
        "contract"
    ],
    "wof:name":"Hbrc",
    "wof:placetype":"venue"
},
  "geometry": {"coordinates":[-122.43876299999999,47.254208],"type":"Point"}
}