{
  "type": "Feature",
  "properties": {
    "addr:full":"2901 E Mill Plain Blvd Vancouver WA 98661",
    "addr:housenumber":"2901",
    "addr:postcode":"98661",
    "addr:street":"E Mill Plain Blvd",
    "iso:country":"US",
    "sg:address":"2901 E Mill Plain Blvd",
    "sg:city":"Vancouver",
    "sg:classifiers":[
        {
            "category":"Social Services",
            "subcategory":"Job Training",
            "type":"Services"
        }
    ],
    "sg:phone":"+1 360 695 2500",
    "sg:postcode":"98661",
    "sg:province":"WA",
    "sg:tags":[
        "career",
        "counseling",
        "school",
        "cooking",
        "vocational"
    ],
    "sg:website":"www.airacademy.com",
    "wof:name":"Airline Travel Career Training",
    "wof:placetype":"venue"
},
  "geometry": {"coordinates":[-122.639999,45.6283],"type":"Point"}
}