{
  "type": "Feature",
  "properties": {
    "addr:full":"6700 15th Ave NW Seattle WA 98117",
    "addr:housenumber":"6700",
    "addr:postcode":"98117",
    "addr:street":"15Th Ave Nw",
    "iso:country":"US",
    "sg:address":"6700 15th Ave NW",
    "sg:city":"Seattle",
    "sg:classifiers":[
        {
            "category":"Personal",
            "type":"Services"
        }
    ],
    "sg:phone":"+1 206 356 2169",
    "sg:postcode":"98117",
    "sg:province":"WA",
    "wof:name":"NW Massage Clinic Pllc",
    "wof:placetype":"venue"
},
  "geometry": {"coordinates":[-122.37676999999999,47.679527],"type":"Point"}
}