{
  "type": "Feature",
  "properties": {
    "iso:country":"US",
    "sg:address":"538 Monumental Rd",
    "sg:city":"Colville",
    "sg:classifiers":[
        {
            "category":"Building & Trades",
            "subcategory":"Construction",
            "type":"Services"
        }
    ],
    "sg:phone":"+1 509 684 3523",
    "sg:postcode":"99114",
    "sg:province":"WA",
    "sg:tags":[
        "residential",
        "general"
    ],
    "wof:name":"R L Johnson Construction",
    "wof:placetype":"venue"
},
  "geometry": {"coordinates":[-118.008426,48.543454],"type":"Point"}
}