{
  "type": "Feature",
  "properties": {
    "addr:full":"6858 Mount Baker Hwy Deming WA 98244",
    "addr:housenumber":"6858",
    "addr:postcode":"98244",
    "addr:street":"Mount Baker Hwy",
    "iso:country":"US",
    "sg:address":"6858 Mount Baker Hwy",
    "sg:city":"Deming",
    "sg:classifiers":[
        {
            "category":"Home & Garden",
            "subcategory":"Garden Supply",
            "type":"Retail Goods"
        }
    ],
    "sg:phone":"+1 360 599 2765",
    "sg:postcode":"98244",
    "sg:province":"WA",
    "wof:name":"Red Mountain Tree Farm",
    "wof:placetype":"venue"
},
  "geometry": {"coordinates":[-122.14712400000001,48.896683],"type":"Point"}
}