{
  "type": "Feature",
  "properties": {
    "addr:full":"7521 126th Ave NE Kirkland WA 98033",
    "addr:housenumber":"7521",
    "addr:postcode":"98033",
    "addr:street":"126Th Ave Ne",
    "iso:country":"US",
    "sg:address":"7521 126th Ave NE",
    "sg:city":"Kirkland",
    "sg:classifiers":[
        {
            "category":"Home & Garden",
            "subcategory":"Building Materials",
            "type":"Retail Goods"
        }
    ],
    "sg:phone":"+1 425 803 3234",
    "sg:postcode":"98033",
    "sg:province":"WA",
    "sg:tags":[
        "glass",
        "leaded"
    ],
    "wof:name":"Cutting Edge Glass Studio Inc",
    "wof:placetype":"venue"
},
  "geometry": {"coordinates":[-122.172082,47.672308],"type":"Point"}
}