{
  "type": "Feature",
  "properties": {
    "addr:full":"220 Louis Perras Rd Colville WA 99114",
    "addr:housenumber":"220",
    "addr:postcode":"99114",
    "addr:street":"Louis Perras Rd",
    "iso:country":"US",
    "sg:address":"220 Louis Perras Rd",
    "sg:city":"Colville",
    "sg:classifiers":[
        {
            "category":"Food & Beverages",
            "subcategory":"Meat & Fish",
            "type":"Retail Goods"
        }
    ],
    "sg:phone":"+1 509 684 5544",
    "sg:postcode":"99114",
    "sg:province":"WA",
    "sg:tags":[
        "cutting"
    ],
    "wof:name":"Ray's Custom Cutting",
    "wof:placetype":"venue"
},
  "geometry": {"coordinates":[-117.91381,48.543076],"type":"Point"}
}