{
  "type": "Feature",
  "properties": {
    "addr:full":"100 N 4th St Coulee City WA 99115",
    "addr:housenumber":"100",
    "addr:postcode":"99115",
    "addr:street":"N 4Th St",
    "iso:country":"US",
    "sg:address":"100 N 4th St",
    "sg:city":"Coulee City",
    "sg:classifiers":[
        {
            "category":"Government",
            "subcategory":"Post Office",
            "type":"Public Place"
        }
    ],
    "sg:phone":"+1 509 632 5751",
    "sg:postcode":"99115",
    "sg:province":"WA",
    "wof:name":"US Post Office",
    "wof:placetype":"venue"
},
  "geometry": {"coordinates":[-119.292942,47.611574],"type":"Point"}
}