{
  "type": "Feature",
  "properties": {
    "addr:full":"2136 N 187th St Shoreline WA 98133",
    "addr:housenumber":"2136",
    "addr:postcode":"98133",
    "addr:street":"N 187Th St",
    "iso:country":"US",
    "sg:address":"2136 N 187th St",
    "sg:city":"Shoreline",
    "sg:classifiers":[
        {
            "category":"Wholesale",
            "subcategory":"Toys & Hobbies",
            "type":"Manufacturing & Wholesale Goods"
        }
    ],
    "sg:phone":"+1 206 363 2166",
    "sg:postcode":"98133",
    "sg:province":"WA",
    "sg:tags":[
        "bingo",
        "supply",
        "equipment",
        "game",
        "gambling",
        "supplies-wholesale",
        "manufacturer"
    ],
    "wof:name":"Vendco Distributing",
    "wof:placetype":"venue"
},
  "geometry": {"coordinates":[-122.33387500000001,47.764591],"type":"Point"}
}