{
  "type": "Feature",
  "properties": {
    "addr:full":"305 W 1st St Sprague WA 99032",
    "addr:housenumber":"305",
    "addr:postcode":"99032",
    "addr:street":"W 1St St",
    "iso:country":"US",
    "sg:address":"305 W 1st St",
    "sg:city":"Sprague",
    "sg:classifiers":[
        {
            "category":"Banks & Credit Unions",
            "subcategory":"Bank",
            "type":"Services"
        }
    ],
    "sg:phone":"+1 509 257 2254",
    "sg:postcode":"99032",
    "sg:province":"WA",
    "sg:tags":[
        "commercial",
        "saving"
    ],
    "sg:website":"http://usbank.com",
    "wof:name":"Us Bank",
    "wof:placetype":"venue"
},
  "geometry": {"coordinates":[-117.97833900000001,47.300037],"type":"Point"}
}