{
  "type": "Feature",
  "properties": {
    "addr:full":"212 NE 164th Ave Ste 6 Vancouver WA 98684",
    "addr:housenumber":"212",
    "addr:postcode":"98684",
    "addr:street":"Ne 164Th Ave Ste 6",
    "iso:country":"US",
    "sg:address":"212 NE 164th Ave Ste 6",
    "sg:city":"Vancouver",
    "sg:phone":"+1 360 891 2825",
    "sg:postcode":"98684",
    "sg:province":"WA",
    "wof:name":"Buck's Pizza",
    "wof:placetype":"venue"
},
  "geometry": {"coordinates":[-122.50427999999999,45.622327],"type":"Point"}
}