{
  "type": "Feature",
  "properties": {
    "addr:full":"3212 W Wheeler St Seattle WA 98199",
    "addr:housenumber":"3212",
    "addr:postcode":"98199",
    "addr:street":"W Wheeler St",
    "iso:country":"US",
    "sg:address":"3212 W Wheeler St",
    "sg:city":"Seattle",
    "sg:classifiers":[
        {
            "category":"Professional",
            "subcategory":"Management & Consulting",
            "type":"Services"
        }
    ],
    "sg:phone":"+1 206 378 1675",
    "sg:postcode":"98199",
    "sg:province":"WA",
    "wof:name":"Four Corners Financial",
    "wof:placetype":"venue"
},
  "geometry": {"coordinates":[-122.39951600000001,47.640107],"type":"Point"}
}