{
  "type": "Feature",
  "properties": {
    "addr:full":"6046 164th Ave SE Bellevue WA 98006",
    "addr:housenumber":"6046",
    "addr:postcode":"98006",
    "addr:street":"164Th Ave Se",
    "iso:country":"US",
    "sg:address":"6046 164th Ave SE",
    "sg:city":"Bellevue",
    "sg:classifiers":[
        {
            "category":"Health Services",
            "subcategory":"Clinic",
            "type":"Services"
        }
    ],
    "sg:phone":"+1 425 747 1383",
    "sg:postcode":"98006",
    "sg:province":"WA",
    "sg:tags":[
        "home",
        "care"
    ],
    "wof:name":"Health Care Consepts",
    "wof:placetype":"venue"
},
  "geometry": {"coordinates":[-122.121438,47.547742],"type":"Point"}
}