{
  "type": "Feature",
  "properties": {
    "addr:full":"4312 Prestwick Ln SE Olympia WA 98501",
    "addr:housenumber":"4312",
    "addr:postcode":"98501",
    "addr:street":"Prestwick Ln Se",
    "iso:country":"US",
    "sg:address":"4312 Prestwick Ln SE",
    "sg:city":"Olympia",
    "sg:classifiers":[
        {
            "category":"Banks & Credit Unions",
            "subcategory":"Financial Services",
            "type":"Services"
        }
    ],
    "sg:phone":"+1 360 923 9108",
    "sg:postcode":"98501",
    "sg:province":"WA",
    "sg:tags":[
        "trust",
        "management"
    ],
    "wof:name":"Klein Family Trust 05 05",
    "wof:placetype":"venue"
},
  "geometry": {"coordinates":[-122.827502,46.984438],"type":"Point"}
}