{
  "type": "Feature",
  "properties": {
    "addr:full":"3988 Redwing Trl NW Bremerton WA 98312",
    "addr:housenumber":"3988",
    "addr:postcode":"98312",
    "addr:street":"Redwing Trl Nw",
    "iso:country":"US",
    "sg:address":"3988 Redwing Trl NW",
    "sg:city":"Bremerton",
    "sg:classifiers":[
        {
            "category":"Professional",
            "subcategory":"Management & Consulting",
            "type":"Services"
        }
    ],
    "sg:phone":"+1 360 830 0219",
    "sg:postcode":"98312",
    "sg:province":"WA",
    "sg:tags":[
        "consultant"
    ],
    "wof:name":"Pollman",
    "wof:placetype":"venue"
},
  "geometry": {"coordinates":[-122.824016,47.597883],"type":"Point"}
}