{
  "type": "Feature",
  "properties": {
    "addr:full":"2304 W Nob Hill Blvd Yakima WA 98902",
    "addr:housenumber":"2304",
    "addr:postcode":"98902",
    "addr:street":"W Nob Hill Blvd",
    "iso:country":"US",
    "sg:address":"2304 W Nob Hill Blvd",
    "sg:city":"Yakima",
    "sg:classifiers":[
        {
            "category":"Restaurant",
            "type":"Food & Drink"
        }
    ],
    "sg:phone":"+1 509 453 9677",
    "sg:postcode":"98902",
    "sg:province":"WA",
    "wof:name":"Skippers Seafood 'n Chowder",
    "wof:placetype":"venue"
},
  "geometry": {"coordinates":[-120.540854,46.585297],"type":"Point"}
}