{
  "type": "Feature",
  "properties": {
    "addr:full":"1801 Taylor Way Tacoma WA 98421",
    "addr:housenumber":"1801",
    "addr:postcode":"98421",
    "addr:street":"Taylor Way",
    "iso:country":"US",
    "sg:address":"1801 Taylor Way",
    "sg:city":"Tacoma",
    "sg:classifiers":[
        {
            "category":"Building & Trades",
            "subcategory":"Equipment Rental",
            "type":"Services"
        }
    ],
    "sg:phone":"+1 253 896 2559",
    "sg:postcode":"98421",
    "sg:province":"WA",
    "sg:tags":[
        "leasing"
    ],
    "wof:name":"T P Leasing",
    "wof:placetype":"venue"
},
  "geometry": {"coordinates":[-122.390322,47.273698],"type":"Point"}
}