{
  "type": "Feature",
  "properties": {
    "addr:full":"1011 Greenleaf Ave Burlington WA 98233",
    "addr:housenumber":"1011",
    "addr:postcode":"98233",
    "addr:street":"Greenleaf Ave",
    "iso:country":"US",
    "sg:address":"1011 Greenleaf Ave",
    "sg:city":"Burlington",
    "sg:classifiers":[
        {
            "category":"Social Services",
            "subcategory":"Adult Care",
            "type":"Services"
        }
    ],
    "sg:phone":"+1 360 755 0102",
    "sg:postcode":"98233",
    "sg:province":"WA",
    "sg:tags":[
        "organization",
        "senior",
        "citizen"
    ],
    "wof:name":"Burlington Senior Citizen Ctr",
    "wof:placetype":"venue"
},
  "geometry": {"coordinates":[-122.321613,48.473269],"type":"Point"}
}