{
  "type": "Feature",
  "properties": {
    "addr:full":"3516 S D St Tacoma WA 98418",
    "addr:housenumber":"3516",
    "addr:postcode":"98418",
    "addr:street":"S D St",
    "iso:country":"US",
    "sg:address":"3516 S D St",
    "sg:city":"Tacoma",
    "sg:classifiers":[
        {
            "category":"Organizations",
            "subcategory":"Religious Organization",
            "type":"Services"
        }
    ],
    "sg:phone":"+1 253 471 3556",
    "sg:postcode":"98418",
    "sg:province":"WA",
    "sg:tags":[
        "church"
    ],
    "wof:name":"Mt Sinai Deliverance Church",
    "wof:placetype":"venue"
},
  "geometry": {"coordinates":[-122.436139,47.228281],"type":"Point"}
}