{
  "type": "Feature",
  "properties": {
    "addr:full":"47 Fuss Rd Menlo WA 98561",
    "addr:housenumber":"47",
    "addr:postcode":"98561",
    "addr:street":"Fuss Rd",
    "iso:country":"US",
    "sg:address":"47 Fuss Rd",
    "sg:city":"Menlo",
    "sg:classifiers":[
        {
            "category":"Building & Trades",
            "subcategory":"Construction",
            "type":"Services"
        }
    ],
    "sg:phone":"+1 360 942 5877",
    "sg:postcode":"98561",
    "sg:province":"WA",
    "sg:tags":[
        "excavating",
        "contractor"
    ],
    "wof:name":"Anderson Construction Co",
    "wof:placetype":"venue"
},
  "geometry": {"coordinates":[-123.656187,46.6201],"type":"Point"}
}