{
  "type": "Feature",
  "properties": {
    "addr:full":"23215 30th Ave S Seattle WA 98198",
    "addr:housenumber":"23215",
    "addr:postcode":"98198",
    "addr:street":"30Th Ave S",
    "iso:country":"US",
    "sg:address":"23215 30th Ave S",
    "sg:city":"Seattle",
    "sg:classifiers":[
        {
            "category":"Banks & Credit Unions",
            "subcategory":"Bank",
            "type":"Services"
        }
    ],
    "sg:phone":"+1 206 870 2770",
    "sg:postcode":"98198",
    "sg:province":"WA",
    "sg:tags":[
        "broker",
        "mortgage"
    ],
    "wof:name":"Discovery Property & Lending",
    "wof:placetype":"venue"
},
  "geometry": {"coordinates":[-122.293319,47.393007],"type":"Point"}
}