{
  "type": "Feature",
  "properties": {
    "iso:country":"US",
    "sg:address":"10302 Summitview Ave",
    "sg:city":"Yakima",
    "sg:classifiers":[
        {
            "category":"Wholesale",
            "subcategory":"Drugs",
            "type":"Manufacturing & Wholesale Goods"
        }
    ],
    "sg:phone":"+1 509 965 9635",
    "sg:postcode":"98908",
    "sg:province":"WA",
    "wof:name":"Pure Essentials By Angela",
    "wof:placetype":"venue"
},
  "geometry": {"coordinates":[-120.642771,46.600216],"type":"Point"}
}