{
  "type": "Feature",
  "properties": {
    "addr:full":"29500 Pacific Hwy S Federal Way WA 98003",
    "addr:housenumber":"29500",
    "addr:postcode":"98003",
    "addr:street":"Pacific Hwy S Federal Way",
    "iso:country":"US",
    "sg:address":"29500 Pacific Hwy S",
    "sg:city":"Federal Way",
    "sg:classifiers":[
        {
            "category":"Utilities",
            "subcategory":"Mobile Phone",
            "type":"Services"
        }
    ],
    "sg:phone":"+1 253 640 1919",
    "sg:postcode":"98003",
    "sg:province":"WA",
    "sg:tags":[
        "communication",
        "radiotelephone"
    ],
    "wof:name":"Advance Wireless",
    "wof:placetype":"venue"
},
  "geometry": {"coordinates":[-122.312136,47.339647],"type":"Point"}
}