{
  "type": "Feature",
  "properties": {
    "addr:full":"12812 101st Avenue Ct E Puyallup WA 98373",
    "addr:housenumber":"12812",
    "addr:postcode":"98373",
    "addr:street":"101St Avenue Ct E",
    "iso:country":"US",
    "sg:address":"12812 101st Avenue Ct E",
    "sg:city":"Puyallup",
    "sg:classifiers":[
        {
            "category":"Insurance",
            "subcategory":"Insurance Agent",
            "type":"Services"
        }
    ],
    "sg:phone":"+1 253 845 9661",
    "sg:postcode":"98373",
    "sg:province":"WA",
    "wof:name":"Mutual Of Omaha Insurance Co",
    "wof:placetype":"venue"
},
  "geometry": {"coordinates":[-122.29366400000001,47.139648],"type":"Point"}
}