{
  "type": "Feature",
  "properties": {
    "iso:country":"US",
    "sg:address":"13326 Vail Cut Off Rd SE",
    "sg:city":"Rainier",
    "sg:classifiers":[
        {
            "category":"Communications",
            "subcategory":"Film & Video Production",
            "type":"Services"
        }
    ],
    "sg:phone":"+1 360 446 3352",
    "sg:postcode":"98576",
    "sg:province":"WA",
    "sg:tags":[
        "motion"
    ],
    "wof:name":"Zero Point Productions",
    "wof:placetype":"venue"
},
  "geometry": {"coordinates":[-122.659423,46.857992],"type":"Point"}
}