{
  "type": "Feature",
  "properties": {
    "addr:full":"1108 E 23rd Ave Kennewick WA 99337",
    "addr:housenumber":"1108",
    "addr:postcode":"99337",
    "addr:street":"E 23Rd Ave",
    "iso:country":"US",
    "sg:address":"1108 E 23rd Ave",
    "sg:city":"Kennewick",
    "sg:classifiers":[
        {
            "category":"Building & Trades",
            "subcategory":"Landscaping Services",
            "type":"Services"
        }
    ],
    "sg:phone":"+1 509 586 1878",
    "sg:postcode":"99337",
    "sg:province":"WA",
    "sg:tags":[
        "landscape",
        "contractor"
    ],
    "wof:name":"A New Look Landscaping",
    "wof:placetype":"venue"
},
  "geometry": {"coordinates":[-119.10596200000001,46.1872],"type":"Point"}
}