{
  "type": "Feature",
  "properties": {
    "addr:full":"13310 120th Ave NE Kirkland WA 98034",
    "addr:housenumber":"13310",
    "addr:postcode":"98034",
    "addr:street":"120Th Ave Ne",
    "iso:country":"US",
    "sg:address":"13310 120th Ave NE",
    "sg:city":"Kirkland",
    "sg:classifiers":[
        {
            "category":"Professional",
            "type":"Services"
        }
    ],
    "sg:phone":"+1 425 823 9487",
    "sg:postcode":"98034",
    "sg:province":"WA",
    "wof:name":"George A Gorveatt",
    "wof:placetype":"venue"
},
  "geometry": {"coordinates":[-122.18039400000001,47.720553],"type":"Point"}
}