{
  "type": "Feature",
  "properties": {
    "addr:full":"720 E Washington St Sequim WA 98382",
    "addr:housenumber":"720",
    "addr:postcode":"98382",
    "addr:street":"E Washington St",
    "iso:country":"US",
    "sg:address":"720 E Washington St",
    "sg:city":"Sequim",
    "sg:classifiers":[
        {
            "category":"Real Estate",
            "subcategory":"Real Estate Agent",
            "type":"Services"
        }
    ],
    "sg:phone":"+1 360 681 4737",
    "sg:postcode":"98382",
    "sg:province":"WA",
    "sg:tags":[
        "management"
    ],
    "wof:name":"Action Property Management",
    "wof:placetype":"venue"
},
  "geometry": {"coordinates":[-123.09304299999999,48.079076],"type":"Point"}
}