{
  "type": "Feature",
  "properties": {
    "addr:full":"146 3rd Ave S Edmonds WA 98020",
    "addr:housenumber":"146",
    "addr:postcode":"98020",
    "addr:street":"3Rd Ave S",
    "iso:country":"US",
    "sg:address":"146 3rd Ave S",
    "sg:city":"Edmonds",
    "sg:classifiers":[
        {
            "category":"Building & Trades",
            "subcategory":"Construction",
            "type":"Services"
        }
    ],
    "sg:phone":"+1 206 583 0238",
    "sg:postcode":"98020",
    "sg:province":"WA",
    "sg:tags":[
        "commercial",
        "contractor"
    ],
    "wof:name":"R Miller Commercial Contrs",
    "wof:placetype":"venue"
},
  "geometry": {"coordinates":[-122.380337,47.809706],"type":"Point"}
}