{
  "type": "Feature",
  "properties": {
    "addr:full":"23812 SE 35th St Issaquah WA 98029",
    "addr:postcode":"23812;98029",
    "addr:street":"Se 35Th St",
    "iso:country":"US",
    "sg:address":"23812 SE 35th St",
    "sg:city":"Issaquah",
    "sg:classifiers":[
        {
            "category":"Banks & Credit Unions",
            "subcategory":"Investment Brokerage",
            "type":"Services"
        }
    ],
    "sg:phone":"+1 425 391 9180",
    "sg:postcode":"98029",
    "sg:province":"WA",
    "sg:tags":[
        "advisory"
    ],
    "wof:name":"Leibsohn Investments 2",
    "wof:placetype":"venue"
},
  "geometry": {"coordinates":[-122.02305200000001,47.578564],"type":"Point"}
}