{
  "type": "Feature",
  "properties": {
    "addr:full":"18110 SE 372nd St Auburn WA 98092",
    "addr:postcode":"18110;98092",
    "addr:street":"Se 372Nd St",
    "iso:country":"US",
    "sg:address":"18110 SE 372nd St",
    "sg:city":"Auburn",
    "sg:classifiers":[
        {
            "category":"Professional",
            "subcategory":"Engineering",
            "type":"Services"
        }
    ],
    "sg:phone":"+1 253 833 1670",
    "sg:postcode":"98092",
    "sg:province":"WA",
    "sg:tags":[
        "consulting",
        "engineer"
    ],
    "wof:name":"Magnaphase Industries Inc",
    "wof:placetype":"venue"
},
  "geometry": {"coordinates":[-122.100793,47.268186],"type":"Point"}
}