{
  "type": "Feature",
  "properties": {
    "addr:full":"1566 Florence St Enumclaw WA 98022",
    "addr:housenumber":"1566",
    "addr:postcode":"98022",
    "addr:street":"Florence St",
    "iso:country":"US",
    "sg:address":"1566 Florence St",
    "sg:city":"Enumclaw",
    "sg:classifiers":[
        {
            "category":"Wholesale",
            "subcategory":"Machinery & Supplies",
            "type":"Manufacturing & Wholesale Goods"
        }
    ],
    "sg:phone":"+1 360 802 9962",
    "sg:postcode":"98022",
    "sg:province":"WA",
    "sg:tags":[
        "industrial"
    ],
    "wof:name":"R & D Tool Distributors",
    "wof:placetype":"venue"
},
  "geometry": {"coordinates":[-122.002938,47.205372],"type":"Point"}
}