{
  "type": "Feature",
  "properties": {
    "addr:full":"8515 14th Ave S Seattle WA 98108",
    "addr:housenumber":"8515",
    "addr:postcode":"98108",
    "addr:street":"14Th Ave S",
    "iso:country":"US",
    "sg:address":"8515 14th Ave S",
    "sg:city":"Seattle",
    "sg:classifiers":[
        {
            "category":"Cinema",
            "subcategory":"Movie Rental",
            "type":"Entertainment"
        }
    ],
    "sg:phone":"+1 206 763 6562",
    "sg:postcode":"98108",
    "sg:province":"WA",
    "sg:tags":[
        "video",
        "tape"
    ],
    "wof:name":"Vidio Mart",
    "wof:placetype":"venue"
},
  "geometry": {"coordinates":[-122.314964,47.528179],"type":"Point"}
}