{
  "type": "Feature",
  "properties": {
    "addr:full":"24691 State Rte 20 Sedro Woolley WA 98284",
    "addr:housenumber":"24691",
    "addr:postcode":"98284",
    "addr:street":"State Rte 20",
    "iso:country":"US",
    "sg:address":"24691 State Rte 20",
    "sg:city":"Sedro Woolley",
    "sg:classifiers":[
        {
            "category":"Manufacturing",
            "subcategory":"Chemicals & Compounds",
            "type":"Manufacturing & Wholesale Goods"
        }
    ],
    "sg:phone":"+1 360 854 9000",
    "sg:postcode":"98284",
    "sg:province":"WA",
    "sg:tags":[
        "mfg",
        "perfume"
    ],
    "wof:name":"Aroma Creations Inc",
    "wof:placetype":"venue"
},
  "geometry": {"coordinates":[-122.212148,48.515183],"type":"Point"}
}