{
  "type": "Feature",
  "properties": {
    "addr:full":"9001 151st Ave NE Redmond WA 98052",
    "addr:housenumber":"9001",
    "addr:postcode":"98052",
    "addr:street":"151St Ave Ne",
    "iso:country":"US",
    "sg:address":"9001 151st Ave NE",
    "sg:city":"Redmond",
    "sg:classifiers":[
        {
            "category":"Building & Trades",
            "subcategory":"Construction",
            "type":"Services"
        }
    ],
    "sg:phone":"+1 425 861 0100",
    "sg:postcode":"98052",
    "sg:province":"WA",
    "sg:tags":[
        "contractor"
    ],
    "sg:website":"www.stonewayroofing.com",
    "wof:name":"Stoneway Roofing Supply Inc",
    "wof:placetype":"venue"
},
  "geometry": {"coordinates":[-122.139999,47.6824],"type":"Point"}
}