{
  "type": "Feature",
  "properties": {
    "addr:full":"19231 36th Ave W Ste J Lynnwood WA 98036",
    "addr:housenumber":"19231",
    "addr:postcode":"98036",
    "addr:street":"36Th Ave W Ste J",
    "iso:country":"US",
    "sg:address":"19231 36th Ave W Ste J",
    "sg:city":"Lynnwood",
    "sg:classifiers":[
        {
            "category":"Transit Center",
            "subcategory":"Freight",
            "type":"Transportation"
        }
    ],
    "sg:phone":"+1 425 774 3363",
    "sg:postcode":"98036",
    "sg:province":"WA",
    "sg:tags":[
        "container",
        "broker"
    ],
    "wof:name":"Damco Maritime",
    "wof:placetype":"venue"
},
  "geometry": {"coordinates":[-122.281792,47.823548],"type":"Point"}
}