{
  "type": "Feature",
  "properties": {
    "addr:full":"5924 6th Ave Tacoma WA 98406",
    "addr:housenumber":"5924",
    "addr:postcode":"98406",
    "addr:street":"6Th Ave",
    "iso:country":"US",
    "sg:address":"5924 6th Ave",
    "sg:city":"Tacoma",
    "sg:classifiers":[
        {
            "category":"Restaurant",
            "type":"Food & Drink"
        }
    ],
    "sg:phone":"+1 253 565 6037",
    "sg:postcode":"98406",
    "sg:province":"WA",
    "sg:tags":[
        "style",
        "family",
        "lunch",
        "american",
        "brunch",
        "breakfast"
    ],
    "sg:website":"http://www.dennys.com",
    "wof:name":"Denny's",
    "wof:placetype":"venue"
},
  "geometry": {"coordinates":[-122.516114,47.25544],"type":"Point"}
}