{
  "type": "Feature",
  "properties": {
    "addr:full":"11104 NE 132nd Pl Kirkland WA 98034",
    "addr:housenumber":"11104",
    "addr:postcode":"98034",
    "addr:street":"Ne 132Nd Pl",
    "iso:country":"US",
    "sg:address":"11104 NE 132nd Pl",
    "sg:city":"Kirkland",
    "sg:classifiers":[
        {
            "category":"Manufacturing",
            "subcategory":"Textiles",
            "type":"Manufacturing & Wholesale Goods"
        }
    ],
    "sg:phone":"+1 425 823 4948",
    "sg:postcode":"98034",
    "sg:province":"WA",
    "sg:tags":[
        "mfg"
    ],
    "wof:name":"Kenngott Fiber LLC",
    "wof:placetype":"venue"
},
  "geometry": {"coordinates":[-122.193172,47.719277],"type":"Point"}
}