{
  "type": "Feature",
  "properties": {
    "addr:full":"1402 140th Pl NE Bellevue WA 98007",
    "addr:housenumber":"1402",
    "addr:postcode":"98007",
    "addr:street":"140Th Pl Ne",
    "iso:country":"US",
    "sg:address":"1402 140th Pl NE",
    "sg:city":"Bellevue",
    "sg:classifiers":[
        {
            "category":"Manufacturing",
            "subcategory":"Food",
            "type":"Manufacturing & Wholesale Goods"
        }
    ],
    "sg:phone":"+1 425 644 5444",
    "sg:postcode":"98007",
    "sg:province":"WA",
    "sg:tags":[
        "fish",
        "by"
    ],
    "wof:name":"H J Baker & Brother Inc",
    "wof:placetype":"venue"
},
  "geometry": {"coordinates":[-122.15219999999999,47.623136],"type":"Point"}
}