{
  "type": "Feature",
  "properties": {
    "addr:full":"4112 Lupine Dr Mount Vernon WA 98274",
    "addr:housenumber":"4112",
    "addr:postcode":"98274",
    "addr:street":"Lupine Dr",
    "iso:country":"US",
    "sg:address":"4112 Lupine Dr",
    "sg:city":"Mount Vernon",
    "sg:classifiers":[
        {
            "category":"Professional",
            "subcategory":"Business Services",
            "type":"Services"
        }
    ],
    "sg:phone":"+1 360 424 5069",
    "sg:postcode":"98274",
    "sg:province":"WA",
    "wof:name":"Details",
    "wof:placetype":"venue"
},
  "geometry": {"coordinates":[-122.28482,48.424151],"type":"Point"}
}