{
  "type": "Feature",
  "properties": {
    "addr:full":"5610 E Lake Sammamish Pkwy SE Issaquah WA 98029",
    "addr:housenumber":"5610",
    "addr:postcode":"98029",
    "addr:street":"E Lake Sammamish Pkwy Se",
    "iso:country":"US",
    "sg:address":"5610 E Lake Sammamish Pkwy SE",
    "sg:city":"Issaquah",
    "sg:classifiers":[
        {
            "category":"Food & Beverages",
            "subcategory":"Groceries & Convenience Stores",
            "type":"Retail Goods"
        }
    ],
    "sg:phone":"+1 425 391 0506",
    "sg:postcode":"98029",
    "sg:province":"WA",
    "wof:name":"Milk Barn Too",
    "wof:placetype":"venue"
},
  "geometry": {"coordinates":[-122.042738,47.549939],"type":"Point"}
}