{
  "type": "Feature",
  "properties": {
    "addr:full":"3701 88th St NE Marysville WA 98270",
    "addr:housenumber":"3701",
    "addr:postcode":"98270",
    "addr:street":"88Th St Ne",
    "iso:country":"US",
    "sg:address":"3701 88th St NE",
    "sg:city":"Marysville",
    "sg:classifiers":[
        {
            "category":"Banks & Credit Unions",
            "subcategory":"Bank",
            "type":"Services"
        }
    ],
    "sg:phone":"+1 360 651 6757",
    "sg:postcode":"98270",
    "sg:province":"WA",
    "sg:tags":[
        "financing"
    ],
    "wof:name":"Household Finance",
    "wof:placetype":"venue"
},
  "geometry": {"coordinates":[-122.181062,48.075814],"type":"Point"}
}