{
  "type": "Feature",
  "properties": {
    "addr:full":"1613 Washington St Wenatchee WA 98801",
    "addr:housenumber":"1613",
    "addr:postcode":"98801",
    "addr:street":"Washington St",
    "iso:country":"US",
    "sg:address":"1613 Washington St",
    "sg:city":"Wenatchee",
    "sg:classifiers":[
        {
            "category":"Utilities",
            "subcategory":"Telephone",
            "type":"Services"
        }
    ],
    "sg:phone":"+1 509 664 8056",
    "sg:postcode":"98801",
    "sg:province":"WA",
    "sg:tags":[
        "messaging",
        "voice",
        "equipment"
    ],
    "sg:website":"www.usasuites.com",
    "wof:name":"Creative Voice Communications",
    "wof:placetype":"venue"
},
  "geometry": {"coordinates":[-120.340777,47.422711],"type":"Point"}
}