{
  "type": "Feature",
  "properties": {
    "addr:full":"5305 E 18th St Vancouver WA 98661",
    "addr:housenumber":"5305",
    "addr:postcode":"98661",
    "addr:street":"E 18Th St",
    "iso:country":"US",
    "sg:address":"5305 E 18th St",
    "sg:city":"Vancouver",
    "sg:classifiers":[
        {
            "category":"Professional",
            "subcategory":"Accounting & Tax Preparation",
            "type":"Services"
        }
    ],
    "sg:phone":"+1 360 750 0751",
    "sg:postcode":"98661",
    "sg:province":"WA",
    "sg:tags":[
        "accountant"
    ],
    "wof:name":"Gurnik & Company Inc",
    "wof:placetype":"venue"
},
  "geometry": {"coordinates":[-122.615443,45.634968],"type":"Point"}
}