{
  "type": "Feature",
  "properties": {
    "addr:full":"1833 Bouslog Rd Burlington WA 98233",
    "addr:housenumber":"1833",
    "addr:postcode":"98233",
    "addr:street":"Bouslog Rd",
    "iso:country":"US",
    "sg:address":"1833 Bouslog Rd",
    "sg:city":"Burlington",
    "sg:classifiers":[
        {
            "category":"Shopping",
            "type":"Retail Goods"
        }
    ],
    "sg:phone":"+1 360 757 6800",
    "sg:postcode":"98233",
    "sg:province":"WA",
    "sg:tags":[
        "truck",
        "merchandise",
        "business"
    ],
    "wof:name":"Packaging Store The",
    "wof:placetype":"venue"
},
  "geometry": {"coordinates":[-122.34515399999999,48.451508],"type":"Point"}
}