{
  "type": "Feature",
  "properties": {
    "addr:full":"24241 SE 44th St Issaquah WA 98029",
    "addr:postcode":"24241;98029",
    "addr:street":"Se 44Th St",
    "iso:country":"US",
    "sg:address":"24241 SE 44th St",
    "sg:city":"Issaquah",
    "sg:classifiers":[
        {
            "category":"Professional",
            "subcategory":"Business Services",
            "type":"Services"
        }
    ],
    "sg:phone":"+1 425 391 3877",
    "sg:postcode":"98029",
    "sg:province":"WA",
    "wof:name":"Digital Dozen LLC",
    "wof:placetype":"venue"
},
  "geometry": {"coordinates":[-122.022031,47.566131],"type":"Point"}
}