{
  "type": "Feature",
  "properties": {
    "iso:country":"US",
    "sg:address":"24704 43rd Ave S",
    "sg:city":"Kent",
    "sg:classifiers":[
        {
            "category":"Wholesale",
            "subcategory":"Hardware",
            "type":"Manufacturing & Wholesale Goods"
        }
    ],
    "sg:phone":"+1 206 583 0350",
    "sg:postcode":"98032",
    "sg:province":"WA",
    "sg:tags":[
        "refrigeration"
    ],
    "wof:name":"Nissei Freezer U S A",
    "wof:placetype":"venue"
},
  "geometry": {"coordinates":[-122.27919900000001,47.379462],"type":"Point"}
}