{
  "type": "Feature",
  "properties": {
    "addr:full":"758 N River Rd Cosmopolis WA 98537",
    "addr:housenumber":"758",
    "addr:postcode":"98537",
    "addr:street":"N River Rd",
    "iso:country":"US",
    "sg:address":"758 N River Rd",
    "sg:city":"Cosmopolis",
    "sg:classifiers":[
        {
            "category":"Building & Trades",
            "subcategory":"Construction",
            "type":"Services"
        }
    ],
    "sg:phone":"+1 360 532 3641",
    "sg:postcode":"98537",
    "sg:province":"WA",
    "sg:tags":[
        "general",
        "contractor"
    ],
    "wof:name":"Thompson Road & Brush",
    "wof:placetype":"venue"
},
  "geometry": {"coordinates":[-123.650229,46.85348],"type":"Point"}
}