{
  "type": "Feature",
  "properties": {
    "addr:full":"5701-C Airport Way S Seattle WA 98108",
    "addr:housenumber":"5701-c",
    "addr:postcode":"98108",
    "addr:street":"Airport Way S",
    "iso:country":"US",
    "sg:address":"5701-C Airport Way S",
    "sg:city":"Seattle",
    "sg:classifiers":[
        {
            "category":"Personal",
            "subcategory":"Hair Removal",
            "type":"Services"
        },
        {
            "category":"Personal",
            "subcategory":"Skin Care",
            "type":"Services"
        }
    ],
    "sg:phone":"+1 206 762 7071",
    "sg:postcode":"98108",
    "sg:province":"WA",
    "sg:website":"www.waxsabbathspa.com",
    "wof:name":"Wax Sabbath Spa",
    "wof:placetype":"venue"
},
  "geometry": {"coordinates":[-122.31918,47.551129],"type":"Point"}
}