{
  "type": "Feature",
  "properties": {
    "addr:full":"27981 Riffe Rd N Reardan WA 99029",
    "addr:postcode":"27981;99029",
    "addr:street":"Riffe Rd N Reardan",
    "iso:country":"US",
    "sg:address":"27981 Riffe Rd N",
    "sg:city":"Reardan",
    "sg:phone":"+1 509 796 4022",
    "sg:postcode":"99029",
    "sg:province":"WA",
    "sg:tags":[
        "farm",
        "wheat",
        "grain",
        "cash"
    ],
    "wof:name":"David L Cassaro",
    "wof:placetype":"venue"
},
  "geometry": {"coordinates":[-117.903248,47.670396],"type":"Point"}
}