{
  "type": "Feature",
  "properties": {
    "addr:full":"6089 Watauga Beach Dr E Port Orchard WA 98366",
    "addr:housenumber":"6089",
    "addr:postcode":"98366",
    "addr:street":"Watauga Beach Dr E",
    "iso:country":"US",
    "sg:address":"6089 Watauga Beach Dr E",
    "sg:city":"Port Orchard",
    "sg:classifiers":[
        {
            "category":"Professional",
            "type":"Services"
        }
    ],
    "sg:phone":"+1 360 871 7717",
    "sg:postcode":"98366",
    "sg:province":"WA",
    "wof:name":"Rod & Nancy Reid",
    "wof:placetype":"venue"
},
  "geometry": {"coordinates":[-122.54967499999999,47.581858],"type":"Point"}
}