{
  "type": "Feature",
  "properties": {
    "addr:full":"13906 SE 60th St Bellevue WA 98006",
    "addr:housenumber":"13906",
    "addr:postcode":"98006",
    "addr:street":"Se 60Th St",
    "iso:country":"US",
    "sg:address":"13906 SE 60th St",
    "sg:city":"Bellevue",
    "sg:classifiers":[
        {
            "category":"Professional",
            "subcategory":"Secretarial Services",
            "type":"Services"
        },
        {
            "category":"Professional",
            "subcategory":"Employment Agencies",
            "type":"Services"
        }
    ],
    "sg:phone":"+1 425 641 9725",
    "sg:postcode":"98006",
    "sg:province":"WA",
    "sg:tags":[
        "typing"
    ],
    "wof:name":"Terry Brashem",
    "wof:placetype":"venue"
},
  "geometry": {"coordinates":[-122.15470999999999,47.550002],"type":"Point"}
}