{
  "type": "Feature",
  "properties": {
    "addr:full":"3824 112th St E Tacoma WA 98446",
    "addr:housenumber":"3824",
    "addr:postcode":"98446",
    "addr:street":"112Th St",
    "iso:country":"US",
    "sg:address":"3824 112th St E",
    "sg:city":"Tacoma",
    "sg:classifiers":[
        {
            "category":"Personal",
            "subcategory":"Beauty Salon",
            "type":"Services"
        }
    ],
    "sg:phone":"+1 253 537 1732",
    "sg:postcode":"98446",
    "sg:province":"WA",
    "wof:name":"Sandy's Budget Hair Care",
    "wof:placetype":"venue"
},
  "geometry": {"coordinates":[-122.375721,47.154697],"type":"Point"}
}