{
  "type": "Feature",
  "properties": {
    "addr:full":"15309 Main St E Sumner WA 98390",
    "addr:housenumber":"15309",
    "addr:postcode":"98390",
    "addr:street":"Main St E",
    "iso:country":"US",
    "sg:address":"15309 Main St E",
    "sg:city":"Sumner",
    "sg:classifiers":[
        {
            "category":"Personal",
            "subcategory":"Beauty Salon",
            "type":"Services"
        }
    ],
    "sg:phone":"+1 253 863 3037",
    "sg:postcode":"98390",
    "sg:province":"WA",
    "sg:tags":[
        "hair",
        "stylist"
    ],
    "wof:name":"Francies Hair & Nail Salon",
    "wof:placetype":"venue"
},
  "geometry": {"coordinates":[-122.22508999999999,47.202665],"type":"Point"}
}