{
  "type": "Feature",
  "properties": {
    "iso:country":"US",
    "sg:address":"1280 SW Lopez Dr",
    "sg:city":"Oak Harbor",
    "sg:classifiers":[
        {
            "category":"Professional",
            "subcategory":"Computer Services",
            "type":"Services"
        }
    ],
    "sg:phone":"+1 360 679 3907",
    "sg:postcode":"98277",
    "sg:province":"WA",
    "sg:tags":[
        "related"
    ],
    "wof:name":"Hg Enterprises",
    "wof:placetype":"venue"
},
  "geometry": {"coordinates":[-122.67229399999999,48.295561],"type":"Point"}
}