{
  "type": "Feature",
  "properties": {
    "addr:full":"686 Sand Rd Port Townsend WA 98368",
    "addr:housenumber":"686",
    "addr:postcode":"98368",
    "addr:street":"Sand Rd",
    "iso:country":"US",
    "sg:address":"686 Sand Rd",
    "sg:city":"Port Townsend",
    "sg:classifiers":[
        {
            "category":"Professional",
            "subcategory":"Lawyer & Legal Services",
            "type":"Services"
        }
    ],
    "sg:phone":"+1 360 385 5613",
    "sg:postcode":"98368",
    "sg:province":"WA",
    "sg:tags":[
        "public"
    ],
    "wof:name":"Public Defenders Office",
    "wof:placetype":"venue"
},
  "geometry": {"coordinates":[-122.84358,48.088908],"type":"Point"}
}