{
  "type": "Feature",
  "properties": {
    "addr:full":"3423 N Park Rd Spokane Valley WA 99212",
    "addr:housenumber":"3423",
    "addr:postcode":"99212",
    "addr:street":"N Park Rd",
    "iso:country":"US",
    "sg:address":"3423 N Park Rd",
    "sg:city":"Spokane Valley",
    "sg:classifiers":[
        {
            "category":"Manufacturing",
            "subcategory":"Metals",
            "type":"Manufacturing & Wholesale Goods"
        },
        {
            "category":"Retail",
            "subcategory":"Repair Shop",
            "type":"Services"
        }
    ],
    "sg:phone":"+1 509 926 3025",
    "sg:postcode":"99212",
    "sg:province":"WA",
    "sg:tags":[
        "product",
        "furniture",
        "fabricated",
        "refinishing",
        "mfg"
    ],
    "wof:name":"Woodriver Co",
    "wof:placetype":"venue"
},
  "geometry": {"coordinates":[-117.30398,47.688468],"type":"Point"}
}