{
  "type": "Feature",
  "properties": {
    "addr:full":"1686 Grant Rd East Wenatchee WA 98802",
    "addr:housenumber":"1686",
    "addr:postcode":"98802",
    "addr:street":"Grant Rd",
    "iso:country":"US",
    "sg:address":"1686 Grant Rd",
    "sg:city":"East Wenatchee",
    "sg:classifiers":[
        {
            "category":"Personal",
            "subcategory":"Barber",
            "type":"Services"
        }
    ],
    "sg:phone":"+1 509 884 8711",
    "sg:postcode":"98802",
    "sg:province":"WA",
    "sg:tags":[
        "shop"
    ],
    "wof:name":"Village Barber Shop",
    "wof:placetype":"venue"
},
  "geometry": {"coordinates":[-120.261472,47.405742],"type":"Point"}
}