{
  "type": "Feature",
  "properties": {
    "addr:full":"1526 Riverside Dr Mount Vernon WA 98273",
    "addr:housenumber":"1526",
    "addr:postcode":"98273",
    "addr:street":"Riverside Dr",
    "iso:country":"US",
    "sg:address":"1526 Riverside Dr",
    "sg:city":"Mount Vernon",
    "sg:classifiers":[
        {
            "category":"Home & Garden",
            "subcategory":"Building Materials",
            "type":"Retail Goods"
        }
    ],
    "sg:phone":"+1 360 424 4489",
    "sg:postcode":"98273",
    "sg:province":"WA",
    "wof:name":"Sherwin-Williams",
    "wof:placetype":"venue"
},
  "geometry": {"coordinates":[-122.335114,48.434102],"type":"Point"}
}