{
  "type": "Feature",
  "properties": {
    "addr:full":"10800 NE Fourth Plain Rd Vancouver WA 98662",
    "addr:housenumber":"10800",
    "addr:postcode":"98662",
    "addr:street":"Ne Fourth Plain Rd",
    "iso:country":"US",
    "sg:address":"10800 NE Fourth Plain Rd",
    "sg:city":"Vancouver",
    "sg:classifiers":[
        {
            "category":"Personal",
            "subcategory":"Nail Salon",
            "type":"Services"
        }
    ],
    "sg:phone":"+1 360 891 5751",
    "sg:postcode":"98662",
    "sg:province":"WA",
    "wof:name":"Star Nails",
    "wof:placetype":"venue"
},
  "geometry": {"coordinates":[-122.56223199999999,45.664753],"type":"Point"}
}