{
  "type": "Feature",
  "properties": {
    "addr:full":"15209 8th Ave S Seattle WA 98148",
    "addr:housenumber":"15209",
    "addr:postcode":"98148",
    "addr:street":"8Th Ave S",
    "iso:country":"US",
    "sg:address":"15209 8th Ave S",
    "sg:city":"Seattle",
    "sg:classifiers":[
        {
            "category":"Health Services",
            "subcategory":"Doctor",
            "type":"Services"
        }
    ],
    "sg:phone":"+1 206 242 7337",
    "sg:postcode":"98148",
    "sg:province":"WA",
    "sg:tags":[
        "medical"
    ],
    "wof:name":"Judith L Marsden MD",
    "wof:placetype":"venue"
},
  "geometry": {"coordinates":[-122.32351300000001,47.466836],"type":"Point"}
}