{
  "type": "Feature",
  "properties": {
    "addr:full":"844 NE 82nd St Seattle WA 98115",
    "addr:housenumber":"844",
    "addr:postcode":"98115",
    "addr:street":"Ne 82Nd St",
    "iso:country":"US",
    "sg:address":"844 NE 82nd St",
    "sg:city":"Seattle",
    "sg:classifiers":[
        {
            "category":"Personal",
            "type":"Services"
        },
        {
            "category":"Professional",
            "subcategory":"Art Services",
            "type":"Services"
        }
    ],
    "sg:phone":"+1 206 525 9519",
    "sg:postcode":"98115",
    "sg:province":"WA",
    "sg:tags":[
        "photography",
        "videography",
        "wedding"
    ],
    "wof:name":"Miriam Uhlig Photography",
    "wof:placetype":"venue"
},
  "geometry": {"coordinates":[-122.319069,47.68821],"type":"Point"}
}