{
  "type": "Feature",
  "properties": {
    "addr:full":"1126 Martin Luther King Jr Way Seattle WA 98122",
    "addr:housenumber":"1126",
    "addr:postcode":"98122",
    "addr:street":"Martin Luther King Jr Way",
    "iso:country":"US",
    "sg:address":"1126 Martin Luther King Jr Way",
    "sg:city":"Seattle",
    "sg:classifiers":[
        {
            "category":"Wholesale",
            "subcategory":"Groceries",
            "type":"Manufacturing & Wholesale Goods"
        },
        {
            "category":"Food & Beverages",
            "subcategory":"Groceries & Convenience Stores",
            "type":"Retail Goods"
        }
    ],
    "sg:phone":"+1 206 302 1005",
    "sg:postcode":"98122",
    "sg:province":"WA",
    "sg:tags":[
        "grocers-wholesale"
    ],
    "sg:website":"http://www.groceryoutlet.com/",
    "wof:name":"Grocery Outlet",
    "wof:placetype":"venue"
},
  "geometry": {"coordinates":[-122.296226,47.612038],"type":"Point"}
}