{
  "type": "Feature",
  "properties": {
    "addr:full":"16120 Meridian E Puyallup WA 98375",
    "addr:housenumber":"16120",
    "addr:postcode":"98375",
    "addr:street":"Meridian E",
    "iso:country":"US",
    "sg:address":"16120 Meridian E",
    "sg:city":"Puyallup",
    "sg:classifiers":[
        {
            "category":"Banks & Credit Unions",
            "subcategory":"Bank",
            "type":"Services"
        },
        {
            "category":"Banks & Credit Unions",
            "subcategory":"Financial Services",
            "type":"Services"
        }
    ],
    "sg:phone":"+1 253 770 5600",
    "sg:postcode":"98375",
    "sg:province":"WA",
    "sg:tags":[
        "saving",
        "loan",
        "commercial"
    ],
    "sg:website":"http://www.firstar.com",
    "wof:name":"Us Bank",
    "wof:placetype":"venue"
},
  "geometry": {"coordinates":[-122.293419,47.11055],"type":"Point"}
}