{
  "type": "Feature",
  "properties": {
    "addr:full":"6526 18th Ave NE Seattle WA 98115",
    "addr:housenumber":"6526",
    "addr:postcode":"98115",
    "addr:street":"18Th Ave Ne",
    "iso:country":"US",
    "sg:address":"6526 18th Ave NE",
    "sg:city":"Seattle",
    "sg:classifiers":[
        {
            "category":"Professional",
            "subcategory":"Management & Consulting",
            "type":"Services"
        }
    ],
    "sg:phone":"+1 206 522 7972",
    "sg:postcode":"98115",
    "sg:province":"WA",
    "sg:tags":[
        "public",
        "relations"
    ],
    "wof:name":"McGaffin Public Relations",
    "wof:placetype":"venue"
},
  "geometry": {"coordinates":[-122.30867600000001,47.677463],"type":"Point"}
}