{
  "type": "Feature",
  "properties": {
    "addr:full":"22832 Rd 6 NE Marlin WA 98832",
    "addr:housenumber":"22832",
    "addr:postcode":"98832",
    "addr:street":"Rd 6 Ne",
    "iso:country":"US",
    "sg:address":"22832 Rd 6 NE",
    "sg:city":"Marlin",
    "sg:classifiers":[
        {
            "category":"Wholesale",
            "subcategory":"Home Furnishings",
            "type":"Manufacturing & Wholesale Goods"
        }
    ],
    "sg:phone":"+1 509 982 0044",
    "sg:postcode":"98832",
    "sg:province":"WA",
    "wof:name":"Sunshine Metals",
    "wof:placetype":"venue"
},
  "geometry": {"coordinates":[-119.0038,47.174163],"type":"Point"}
}