{
  "type": "Feature",
  "properties": {
    "addr:full":"6930 115th Pl SE Renton WA 98056",
    "addr:housenumber":"6930",
    "addr:postcode":"98056",
    "addr:street":"115Th Pl Se",
    "iso:country":"US",
    "sg:address":"6930 115th Pl SE",
    "sg:city":"Renton",
    "sg:classifiers":[
        {
            "category":"Building & Trades",
            "subcategory":"Construction",
            "type":"Services"
        }
    ],
    "sg:phone":"+1 425 271 6437",
    "sg:postcode":"98056",
    "sg:province":"WA",
    "sg:tags":[
        "hanging",
        "contractor"
    ],
    "wof:name":"Pro Painters",
    "wof:placetype":"venue"
},
  "geometry": {"coordinates":[-122.18621899999999,47.541254],"type":"Point"}
}