{
  "type": "Feature",
  "properties": {
    "addr:full":"319 Cain Lake Rd Sedro Woolley WA 98284",
    "addr:housenumber":"319",
    "addr:postcode":"98284",
    "addr:street":"Cain Lake Rd",
    "iso:country":"US",
    "sg:address":"319 Cain Lake Rd",
    "sg:city":"Sedro Woolley",
    "sg:classifiers":[
        {
            "category":"Wholesale",
            "subcategory":"Construction Materials",
            "type":"Manufacturing & Wholesale Goods"
        }
    ],
    "sg:phone":"+1 360 595 2600",
    "sg:postcode":"98284",
    "sg:province":"WA",
    "wof:name":"Mobile Sawmilling",
    "wof:placetype":"venue"
},
  "geometry": {"coordinates":[-122.324761,48.65487],"type":"Point"}
}