{
  "type": "Feature",
  "properties": {
    "addr:full":"565 Andover Park W Seattle WA 98188",
    "addr:housenumber":"565",
    "addr:postcode":"98188",
    "addr:street":"Andover Park W",
    "iso:country":"US",
    "sg:address":"565 Andover Park W",
    "sg:city":"Seattle",
    "sg:classifiers":[
        {
            "category":"Wholesale",
            "subcategory":"Stationery",
            "type":"Manufacturing & Wholesale Goods"
        }
    ],
    "sg:phone":"+1 206 575 9333",
    "sg:postcode":"98188",
    "sg:province":"WA",
    "sg:tags":[
        "supply"
    ],
    "wof:name":"Reynolds and Reynolds Co Inc",
    "wof:placetype":"venue"
},
  "geometry": {"coordinates":[-122.254471,47.451222],"type":"Point"}
}