{
  "type": "Feature",
  "properties": {
    "addr:full":"1191 2nd Ave Seattle WA 98101",
    "addr:housenumber":"1191",
    "addr:postcode":"98101",
    "addr:street":"2Nd Ave",
    "iso:country":"US",
    "sg:address":"1191 2nd Ave",
    "sg:city":"Seattle",
    "sg:classifiers":[
        {
            "category":"Professional",
            "subcategory":"Lawyer & Legal Services",
            "type":"Services"
        }
    ],
    "sg:phone":"+1 206 224 9818",
    "sg:postcode":"98101",
    "sg:province":"WA",
    "wof:name":"Young Denormandie Oscarsson PC",
    "wof:placetype":"venue"
},
  "geometry": {"coordinates":[-122.336096,47.60589],"type":"Point"}
}