{
  "type": "Feature",
  "properties": {
    "addr:full":"400 14th St Benton City WA 99320",
    "addr:housenumber":"400",
    "addr:postcode":"99320",
    "addr:street":"14Th St",
    "iso:country":"US",
    "sg:address":"400 14th St",
    "sg:city":"Benton City",
    "sg:classifiers":[
        {
            "category":"Real Estate",
            "subcategory":"Developer",
            "type":"Services"
        },
        {
            "category":"Real Estate",
            "subcategory":"Real Estate Operator",
            "type":"Services"
        }
    ],
    "sg:phone":"+1 509 588 6969",
    "sg:postcode":"99320",
    "sg:province":"WA",
    "sg:tags":[
        "mobile",
        "home",
        "site"
    ],
    "wof:name":"Hillview Mobile Home Park",
    "wof:placetype":"venue"
},
  "geometry": {"coordinates":[-119.494708,46.260143],"type":"Point"}
}