{
  "type": "Feature",
  "properties": {
    "addr:full":"1752 Bakerview Rd Lopez Island WA 98261",
    "addr:housenumber":"1752",
    "addr:postcode":"98261",
    "addr:street":"Bakerview Rd Lopez Island",
    "iso:country":"US",
    "sg:address":"1752 Bakerview Rd",
    "sg:city":"Lopez Island",
    "sg:classifiers":[
        {
            "category":"Wholesale",
            "subcategory":"Stationery",
            "type":"Manufacturing & Wholesale Goods"
        }
    ],
    "sg:phone":"+1 360 468 3288",
    "sg:postcode":"98261",
    "sg:province":"WA",
    "sg:tags":[
        "product",
        "paper"
    ],
    "wof:name":"Island Paper & Supply Co",
    "wof:placetype":"venue"
},
  "geometry": {"coordinates":[-122.869615,48.517354],"type":"Point"}
}