{
  "type": "Feature",
  "properties": {
    "addr:full":"603 116th St SW Everett WA 98204",
    "addr:housenumber":"603",
    "addr:postcode":"98204",
    "addr:street":"116Th St Sw",
    "iso:country":"US",
    "sg:address":"603 116th St SW",
    "sg:city":"Everett",
    "sg:classifiers":[
        {
            "category":"Retail",
            "subcategory":"Repair Shop",
            "type":"Services"
        }
    ],
    "sg:phone":"+1 425 355 9593",
    "sg:postcode":"98204",
    "sg:province":"WA",
    "wof:name":"Ebel Ulrich Gerd",
    "wof:placetype":"venue"
},
  "geometry": {"coordinates":[-122.24167199999999,47.892758],"type":"Point"}
}