{
  "type": "Feature",
  "properties": {
    "addr:full":"1480 Olney Ave SE Port Orchard WA 98366",
    "addr:housenumber":"1480",
    "addr:postcode":"98366",
    "addr:street":"Olney Ave Se",
    "iso:country":"US",
    "sg:address":"1480 Olney Ave SE",
    "sg:city":"Port Orchard",
    "sg:classifiers":[
        {
            "category":"Restaurant",
            "type":"Food & Drink"
        }
    ],
    "sg:phone":"+1 360 876 0770",
    "sg:postcode":"98366",
    "sg:province":"WA",
    "sg:tags":[
        "eating"
    ],
    "wof:name":"Burger King",
    "wof:placetype":"venue"
},
  "geometry": {"coordinates":[-122.6097,47.534183],"type":"Point"}
}