{
  "type": "Feature",
  "properties": {
    "addr:full":"6419 Phinney Ave N Seattle WA 98103",
    "addr:housenumber":"6419",
    "addr:postcode":"98103",
    "addr:street":"Phinney Ave N",
    "iso:country":"US",
    "sg:address":"6419 Phinney Ave N",
    "sg:city":"Seattle",
    "sg:classifiers":[
        {
            "category":"Shopping",
            "type":"Retail Goods"
        }
    ],
    "sg:phone":"+1 206 706 6860",
    "sg:postcode":"98103",
    "sg:province":"WA",
    "sg:tags":[
        "art",
        "gallery",
        "dealer"
    ],
    "wof:name":"Emerald Bamboo-Fine Arts",
    "wof:placetype":"venue"
},
  "geometry": {"coordinates":[-122.354429,47.675841],"type":"Point"}
}