{
  "type": "Feature",
  "properties": {
    "addr:full":"13210 E 24th Ave Spokane Valley WA 99216",
    "addr:housenumber":"13210",
    "addr:postcode":"99216",
    "addr:street":"E 24Th Ave",
    "iso:country":"US",
    "sg:address":"13210 E 24th Ave",
    "sg:city":"Spokane Valley",
    "sg:classifiers":[
        {
            "category":"Building & Trades",
            "subcategory":"Cleaning & Sanitation",
            "type":"Services"
        }
    ],
    "sg:phone":"+1 509 928 2074",
    "sg:postcode":"99216",
    "sg:province":"WA",
    "sg:tags":[
        "janitor"
    ],
    "wof:name":"Lynda J Gilbert Cleaning",
    "wof:placetype":"venue"
},
  "geometry": {"coordinates":[-117.22735900000001,47.635079],"type":"Point"}
}