{
  "type": "Feature",
  "properties": {
    "addr:full":"5450 Shilshole Ave NW Seattle WA 98107",
    "addr:housenumber":"5450",
    "addr:postcode":"98107",
    "addr:street":"Shilshole Ave Nw",
    "iso:country":"US",
    "sg:address":"5450 Shilshole Ave NW",
    "sg:city":"Seattle",
    "sg:classifiers":[
        {
            "category":"Retail",
            "subcategory":"Auto Repair",
            "type":"Services"
        }
    ],
    "sg:phone":"+1 206 782 1320",
    "sg:postcode":"98107",
    "sg:province":"WA",
    "sg:tags":[
        "automotive"
    ],
    "sg:website":"www.wilsonbrosauto.com",
    "wof:name":"Wilson Bros Automotive",
    "wof:placetype":"venue"
},
  "geometry": {"coordinates":[-122.386205,47.667487],"type":"Point"}
}