{
  "type": "Feature",
  "properties": {
    "addr:full":"28129 192nd Pl SE Kent WA 98042",
    "addr:housenumber":"28129",
    "addr:postcode":"98042",
    "addr:street":"192Nd Pl Se",
    "iso:country":"US",
    "sg:address":"28129 192nd Pl SE",
    "sg:city":"Kent",
    "sg:classifiers":[
        {
            "category":"Banks & Credit Unions",
            "subcategory":"Bank",
            "type":"Services"
        }
    ],
    "sg:phone":"+1 253 630 1405",
    "sg:postcode":"98042",
    "sg:province":"WA",
    "sg:tags":[
        "equipment",
        "financing",
        "leasing"
    ],
    "wof:name":"Money Source Inc",
    "wof:placetype":"venue"
},
  "geometry": {"coordinates":[-122.084585,47.34978],"type":"Point"}
}