{
  "type": "Feature",
  "properties": {
    "addr:full":"259 145th Ave SE Bellevue WA 98007",
    "addr:housenumber":"259",
    "addr:postcode":"98007",
    "addr:street":"145Th Ave Se",
    "iso:country":"US",
    "sg:address":"259 145th Ave SE",
    "sg:city":"Bellevue",
    "sg:classifiers":[
        {
            "category":"Home & Garden",
            "subcategory":"Building Materials",
            "type":"Retail Goods"
        },
        {
            "category":"Building & Trades",
            "subcategory":"Construction",
            "type":"Services"
        }
    ],
    "sg:phone":"+1 425 641 7535",
    "sg:postcode":"98007",
    "sg:province":"WA",
    "sg:tags":[
        "altering",
        "improvement",
        "remodeling",
        "contractor"
    ],
    "wof:name":"Edwards Scott",
    "wof:placetype":"venue"
},
  "geometry": {"coordinates":[-122.14684099999999,47.605361],"type":"Point"}
}