{
  "type": "Feature",
  "properties": {
    "addr:full":"81 S Lucile St Seattle WA 98134",
    "addr:housenumber":"81",
    "addr:postcode":"98134",
    "addr:street":"S Lucile St",
    "iso:country":"US",
    "sg:address":"81 S Lucile St",
    "sg:city":"Seattle",
    "sg:classifiers":[
        {
            "category":"Building & Trades",
            "subcategory":"Locksmith",
            "type":"Services"
        }
    ],
    "sg:phone":"+1 206 607 0818",
    "sg:postcode":"98134",
    "sg:province":"WA",
    "sg:tags":[
        "key"
    ],
    "wof:name":"America 24 Hour Locksmith",
    "wof:placetype":"venue"
},
  "geometry": {"coordinates":[-122.33533,47.553283],"type":"Point"}
}