{
  "type": "Feature",
  "properties": {
    "iso:country":"US",
    "sg:address":"3706 NE 102nd St",
    "sg:city":"Vancouver",
    "sg:classifiers":[
        {
            "category":"Professional",
            "subcategory":"Business Services",
            "type":"Services"
        }
    ],
    "sg:phone":"+1 360 571 5192",
    "sg:postcode":"98686",
    "sg:province":"WA",
    "wof:name":"Robert I Ness",
    "wof:placetype":"venue"
},
  "geometry": {"coordinates":[-122.63243,45.695529],"type":"Point"}
}