{
  "type": "Feature",
  "properties": {
    "addr:full":"95 Burnett Ave S Renton WA 98057",
    "addr:housenumber":"95",
    "addr:postcode":"98057",
    "addr:street":"Burnett Ave S Renton",
    "iso:country":"US",
    "sg:address":"95 Burnett Ave S",
    "sg:city":"Renton",
    "sg:classifiers":[
        {
            "category":"Real Estate",
            "subcategory":"Real Estate Operator",
            "type":"Services"
        }
    ],
    "sg:phone":"+1 425 255 5710",
    "sg:postcode":"98057",
    "sg:province":"WA",
    "sg:tags":[
        "apartment"
    ],
    "wof:name":"95 Burnett Apt Homes",
    "wof:placetype":"venue"
},
  "geometry": {"coordinates":[-122.20800300000001,47.483749],"type":"Point"}
}