{
  "type": "Feature",
  "properties": {
    "addr:full":"1504 NE 234th St Ridgefield WA 98642",
    "addr:housenumber":"1504",
    "addr:postcode":"98642",
    "addr:street":"Ne 234Th St",
    "iso:country":"US",
    "sg:address":"1504 NE 234th St",
    "sg:city":"Ridgefield",
    "sg:classifiers":[
        {
            "category":"Farming",
            "subcategory":"Farm & Veterinary Services",
            "type":"Manufacturing & Wholesale Goods"
        }
    ],
    "sg:phone":"+1 360 887 3128",
    "sg:postcode":"98642",
    "sg:province":"WA",
    "sg:tags":[
        "ginseng",
        "food",
        "production",
        "commercial"
    ],
    "wof:name":"Pacific Rim Ginseng",
    "wof:placetype":"venue"
},
  "geometry": {"coordinates":[-122.65736699999999,45.790363],"type":"Point"}
}