{
  "type": "Feature",
  "properties": {
    "addr:full":"900 4th Ave Seattle WA 98164",
    "addr:housenumber":"900",
    "addr:postcode":"98164",
    "addr:street":"4Th Ave",
    "iso:country":"US",
    "sg:address":"900 4th Ave",
    "sg:city":"Seattle",
    "sg:classifiers":[
        {
            "category":"Banks & Credit Unions",
            "subcategory":"Bank",
            "type":"Services"
        }
    ],
    "sg:phone":"+1 206 382 6000",
    "sg:postcode":"98164",
    "sg:province":"WA",
    "sg:tags":[
        "national",
        "commercial",
        "foreign"
    ],
    "wof:name":"Bank of Tokyo-Mitsubishi Ltd",
    "wof:placetype":"venue"
},
  "geometry": {"coordinates":[-122.332911,47.606086],"type":"Point"}
}