{
  "type": "Feature",
  "properties": {
    "addr:full":"21 Big Foot Ln Sequim WA 98382",
    "addr:housenumber":"21",
    "addr:postcode":"98382",
    "addr:street":"Big Foot Ln",
    "iso:country":"US",
    "sg:address":"21 Big Foot Ln",
    "sg:city":"Sequim",
    "sg:classifiers":[
        {
            "category":"Building & Trades",
            "subcategory":"Construction",
            "type":"Services"
        }
    ],
    "sg:phone":"+1 360 582 9210",
    "sg:postcode":"98382",
    "sg:province":"WA",
    "sg:tags":[
        "residential"
    ],
    "wof:name":"Cole R&E Construction",
    "wof:placetype":"venue"
},
  "geometry": {"coordinates":[-123.057576,48.078431],"type":"Point"}
}