{
  "type": "Feature",
  "properties": {
    "addr:full":"2020 S 320th St Federal Way WA 98003",
    "addr:housenumber":"2020",
    "addr:postcode":"98003",
    "addr:street":"S 320Th St",
    "iso:country":"US",
    "sg:address":"2020 S 320th St",
    "sg:city":"Federal Way",
    "sg:classifiers":[
        {
            "category":"Food & Beverages",
            "subcategory":"Specialty",
            "type":"Retail Goods"
        }
    ],
    "sg:phone":"+1 253 946 9144",
    "sg:postcode":"98003",
    "sg:province":"WA",
    "sg:tags":[
        "health",
        "diet"
    ],
    "sg:website":"www.emeraldcitysmoothie.com",
    "wof:name":"Emerald City Smoothie",
    "wof:placetype":"venue"
},
  "geometry": {"coordinates":[-122.30627,47.315184],"type":"Point"}
}