{
  "type": "Feature",
  "properties": {
    "addr:full":"1244 S Sprague Ave Tacoma WA 98405",
    "addr:housenumber":"1244",
    "addr:postcode":"98405",
    "addr:street":"S Sprague Ave",
    "iso:country":"US",
    "sg:address":"1244 S Sprague Ave",
    "sg:city":"Tacoma",
    "sg:classifiers":[
        {
            "category":"Manufacturing",
            "subcategory":"Building Materials",
            "type":"Manufacturing & Wholesale Goods"
        },
        {
            "category":"Home & Garden",
            "subcategory":"Furniture",
            "type":"Retail Goods"
        }
    ],
    "sg:phone":"+1 253 272 5321",
    "sg:postcode":"98405",
    "sg:province":"WA",
    "sg:tags":[
        "case",
        "mfg",
        "laminated",
        "cabinet",
        "wood",
        "plastic",
        "kitchen"
    ],
    "wof:name":"Alexander's Custom Cabinets",
    "wof:placetype":"venue"
},
  "geometry": {"coordinates":[-122.463003,47.248685],"type":"Point"}
}