{
  "type": "Feature",
  "properties": {
    "addr:full":"18420 33rd Ave W # D Lynnwood WA 98037",
    "addr:housenumber":"18420",
    "addr:postcode":"98037",
    "addr:street":"33Rd Ave W # D",
    "iso:country":"US",
    "sg:address":"18420 33rd Ave W # D",
    "sg:city":"Lynnwood",
    "sg:classifiers":[
        {
            "category":"Shopping",
            "subcategory":"Musical Instruments",
            "type":"Retail Goods"
        },
        {
            "category":"Communications",
            "subcategory":"Film & Video Production",
            "type":"Services"
        },
        {
            "category":"Arts & Performance",
            "subcategory":"Music",
            "type":"Entertainment"
        },
        {
            "category":"Manufacturing",
            "subcategory":"Musical Instruments",
            "type":"Manufacturing & Wholesale Goods"
        }
    ],
    "sg:phone":"+1 425 640 0110",
    "sg:postcode":"98037",
    "sg:province":"WA",
    "sg:tags":[
        "dvd",
        "amplifier",
        "duplicating",
        "cd",
        "guitar",
        "instruments-rental",
        "cassette",
        "instruments-supplies",
        "accessory"
    ],
    "sg:website":"http://www.guitarcenter.com/",
    "wof:name":"Guitar Center",
    "wof:placetype":"venue"
},
  "geometry": {"coordinates":[-122.277674,47.831344],"type":"Point"}
}