{
  "type": "Feature",
  "properties": {
    "addr:full":"2814 E 24th St Vancouver WA 98661",
    "addr:housenumber":"2814",
    "addr:postcode":"98661",
    "addr:street":"E 24Th St",
    "iso:country":"US",
    "sg:address":"2814 E 24th St",
    "sg:city":"Vancouver",
    "sg:classifiers":[
        {
            "category":"Restaurant",
            "type":"Food & Drink"
        }
    ],
    "sg:phone":"+1 360 695 3941",
    "sg:postcode":"98661",
    "sg:province":"WA",
    "sg:tags":[
        "eating"
    ],
    "wof:name":"Scottys Dogs",
    "wof:placetype":"venue"
},
  "geometry": {"coordinates":[-122.64039200000001,45.638667],"type":"Point"}
}