{
  "type": "Feature",
  "properties": {
    "addr:full":"12819 SE 38th St Ste 115 Bellevue WA 98006",
    "addr:postcode":"12819;98006",
    "addr:street":"Se 38Th St Ste 115",
    "iso:country":"US",
    "sg:address":"12819 SE 38th St Ste 115",
    "sg:city":"Bellevue",
    "sg:classifiers":[
        {
            "category":"Professional",
            "type":"Services"
        },
        {
            "category":"Professional",
            "subcategory":"Research",
            "type":"Services"
        }
    ],
    "sg:phone":"+1 425 644 6449",
    "sg:postcode":"98006",
    "sg:province":"WA",
    "sg:tags":[
        "archaeologist",
        "arranged",
        "outfitted",
        "expedition"
    ],
    "wof:name":"Diehold Foundation",
    "wof:placetype":"venue"
},
  "geometry": {"coordinates":[-122.169158,47.576082],"type":"Point"}
}