{
  "type": "Feature",
  "properties": {
    "addr:full":"5508 NW Harney St Vancouver WA 98663",
    "addr:housenumber":"5508",
    "addr:postcode":"98663",
    "addr:street":"Nw Harney St",
    "iso:country":"US",
    "sg:address":"5508 NW Harney St",
    "sg:city":"Vancouver",
    "sg:classifiers":[
        {
            "category":"Shopping",
            "subcategory":"Bicycles & Sporting Goods",
            "type":"Retail Goods"
        }
    ],
    "sg:phone":"+1 360 696 4567",
    "sg:postcode":"98663",
    "sg:province":"WA",
    "wof:name":"Marine Sports",
    "wof:placetype":"venue"
},
  "geometry": {"coordinates":[-122.68051199999999,45.663562],"type":"Point"}
}