{
  "type": "Feature",
  "properties": {
    "addr:full":"509 N Wenatchee Ave Wenatchee WA 98801",
    "addr:housenumber":"509",
    "addr:postcode":"98801",
    "addr:street":"N Wenatchee Ave",
    "iso:country":"US",
    "sg:address":"509 N Wenatchee Ave",
    "sg:city":"Wenatchee",
    "sg:classifiers":[
        {
            "category":"Banks & Credit Unions",
            "subcategory":"Investment Brokerage",
            "type":"Services"
        },
        {
            "category":"Banks & Credit Unions",
            "subcategory":"Bank",
            "type":"Services"
        }
    ],
    "sg:phone":"+1 509 663 6994",
    "sg:postcode":"98801",
    "sg:province":"WA",
    "sg:tags":[
        "mutual",
        "transfer",
        "broker",
        "agent",
        "fund",
        "security",
        "stock",
        "bond"
    ],
    "sg:website":"http://www.lpl.com",
    "wof:name":"LPL Financial Services",
    "wof:placetype":"venue"
},
  "geometry": {"coordinates":[-120.316479,47.430768],"type":"Point"}
}