{
  "type": "Feature",
  "properties": {
    "addr:full":"1513 22nd St NE Auburn WA 98002",
    "addr:housenumber":"1513",
    "addr:postcode":"98002",
    "addr:street":"22Nd St Ne",
    "iso:country":"US",
    "sg:address":"1513 22nd St NE",
    "sg:city":"Auburn",
    "sg:classifiers":[
        {
            "category":"Professional",
            "subcategory":"Business Services",
            "type":"Services"
        }
    ],
    "sg:phone":"+1 253 804 5604",
    "sg:postcode":"98002",
    "sg:province":"WA",
    "wof:name":"Jk Prosperity Group LLC",
    "wof:placetype":"venue"
},
  "geometry": {"coordinates":[-122.208247,47.326146],"type":"Point"}
}