{
  "type": "Feature",
  "properties": {
    "addr:full":"2826 Kauffman Ave Vancouver WA 98660",
    "addr:housenumber":"2826",
    "addr:postcode":"98660",
    "addr:street":"Kauffman Ave",
    "iso:country":"US",
    "sg:address":"2826 Kauffman Ave",
    "sg:city":"Vancouver",
    "sg:classifiers":[
        {
            "category":"Manufacturing",
            "subcategory":"Paper Products",
            "type":"Manufacturing & Wholesale Goods"
        }
    ],
    "sg:phone":"+1 360 693 2610",
    "sg:postcode":"98660",
    "sg:province":"WA",
    "sg:tags":[
        "box",
        "bag",
        "w",
        "mfg"
    ],
    "wof:name":"Commencement Corrigated",
    "wof:placetype":"venue"
},
  "geometry": {"coordinates":[-122.68100800000001,45.641801],"type":"Point"}
}