{
  "type": "Feature",
  "properties": {
    "addr:full":"1531 Grand Ave Seattle WA 98122",
    "addr:housenumber":"1531",
    "addr:postcode":"98122",
    "addr:street":"Grand Ave",
    "iso:country":"US",
    "sg:address":"1531 Grand Ave",
    "sg:city":"Seattle",
    "sg:classifiers":[
        {
            "category":"Professional",
            "subcategory":"Business Services",
            "type":"Services"
        }
    ],
    "sg:phone":"+1 206 860 8124",
    "sg:postcode":"98122",
    "sg:province":"WA",
    "wof:name":"Penelope West",
    "wof:placetype":"venue"
},
  "geometry": {"coordinates":[-122.28415099999999,47.614557],"type":"Point"}
}