{
  "type": "Feature",
  "properties": {
    "addr:full":"703 N 34th St Seattle WA 98103",
    "addr:housenumber":"703",
    "addr:postcode":"98103",
    "addr:street":"N 34Th St",
    "iso:country":"US",
    "sg:address":"703 N 34th St",
    "sg:city":"Seattle",
    "sg:classifiers":[
        {
            "category":"Building & Trades",
            "subcategory":"Locksmith",
            "type":"Services"
        }
    ],
    "sg:phone":"+1 206 774 9362",
    "sg:postcode":"98103",
    "sg:province":"WA",
    "sg:tags":[
        "key"
    ],
    "wof:name":"All Day 24 Hour Available Locksmith",
    "wof:placetype":"venue"
},
  "geometry": {"coordinates":[-122.348693,47.649252],"type":"Point"}
}