{
  "type": "Feature",
  "properties": {
    "addr:full":"401 Broadway E Seattle WA 98102",
    "addr:housenumber":"401",
    "addr:postcode":"98102",
    "addr:street":"Broadway",
    "iso:country":"US",
    "sg:address":"401 Broadway E",
    "sg:city":"Seattle",
    "sg:classifiers":[
        {
            "category":"Personal",
            "subcategory":"Beauty Salon",
            "type":"Services"
        }
    ],
    "sg:phone":"+1 206 325 9916",
    "sg:postcode":"98102",
    "sg:province":"WA",
    "sg:tags":[
        "hair",
        "shop"
    ],
    "wof:name":"City Hair",
    "wof:placetype":"venue"
},
  "geometry": {"coordinates":[-122.321493,47.622559],"type":"Point"}
}