{
  "type": "Feature",
  "properties": {
    "iso:country":"US",
    "sg:address":"3825 52nd Ave NE",
    "sg:city":"Tacoma",
    "sg:classifiers":[
        {
            "category":"Arts & Performance",
            "subcategory":"Theater",
            "type":"Entertainment"
        }
    ],
    "sg:phone":"+1 253 942 4263",
    "sg:postcode":"98422",
    "sg:province":"WA",
    "sg:tags":[
        "live",
        "music"
    ],
    "wof:name":"Blissman Productions",
    "wof:placetype":"venue"
},
  "geometry": {"coordinates":[-122.37720299999999,47.291496],"type":"Point"}
}