{
  "type": "Feature",
  "properties": {
    "addr:full":"1205 19th Ave Milton WA 98354",
    "addr:housenumber":"1205",
    "addr:postcode":"98354",
    "addr:street":"19Th Ave",
    "iso:country":"US",
    "sg:address":"1205 19th Ave",
    "sg:city":"Milton",
    "sg:classifiers":[
        {
            "category":"Government",
            "subcategory":"Office",
            "type":"Public Place"
        }
    ],
    "sg:phone":"+1 253 922 6628",
    "sg:postcode":"98354",
    "sg:province":"WA",
    "sg:tags":[
        "educational",
        "program",
        "administrative"
    ],
    "sg:website":"www.fife.com",
    "wof:name":"Discovery Primary School",
    "wof:placetype":"venue"
},
  "geometry": {"coordinates":[-122.309404,47.25009],"type":"Point"}
}