{
  "type": "Feature",
  "properties": {
    "addr:full":"2366 Eastlake Ave E Rm 214 Seattle WA 98102",
    "addr:housenumber":"2366",
    "addr:postcode":"98102",
    "addr:street":"Eastlake Ave E Rm 214",
    "iso:country":"US",
    "sg:address":"2366 Eastlake Ave E Rm 214",
    "sg:city":"Seattle",
    "sg:classifiers":[
        {
            "category":"Health Services",
            "subcategory":"Clinic",
            "type":"Services"
        }
    ],
    "sg:phone":"+1 206 719 6660",
    "sg:postcode":"98102",
    "sg:province":"WA",
    "sg:tags":[
        "counseling",
        "mental"
    ],
    "sg:website":"www.hypnosisseattle.com/",
    "wof:name":"Hypnosis Seattle",
    "wof:placetype":"venue"
},
  "geometry": {"coordinates":[-122.325852,47.640517],"type":"Point"}
}