{
  "type": "Feature",
  "properties": {
    "addr:full":"3727 Factoria Blvd SE Bellevue WA 98004",
    "addr:housenumber":"3727",
    "addr:postcode":"98004",
    "addr:street":"Factoria Blvd Se",
    "iso:country":"US",
    "sg:address":"3727 Factoria Blvd SE",
    "sg:city":"Bellevue",
    "sg:classifiers":[
        {
            "category":"Coffee & Tea",
            "type":"Food & Drink"
        }
    ],
    "sg:phone":"+1 425 643 3875",
    "sg:postcode":"98004",
    "sg:province":"WA",
    "wof:name":"Jazzed Espresso",
    "wof:placetype":"venue"
},
  "geometry": {"coordinates":[-122.169414,47.577473],"type":"Point"}
}