{
  "type": "Feature",
  "properties": {
    "addr:full":"127 2nd Ave SW Soap Lake WA 98851",
    "addr:housenumber":"127",
    "addr:postcode":"98851",
    "addr:street":"2Nd Ave Sw",
    "iso:country":"US",
    "sg:address":"127 2nd Ave SW",
    "sg:city":"Soap Lake",
    "sg:classifiers":[
        {
            "category":"Organizations",
            "subcategory":"Non-profit Organization",
            "type":"Services"
        }
    ],
    "sg:phone":"+1 509 246 1111",
    "sg:postcode":"98851",
    "sg:province":"WA",
    "wof:name":"Mc Kay Healthcare & Rehab Ctr",
    "wof:placetype":"venue"
},
  "geometry": {"coordinates":[-119.497061,47.387132],"type":"Point"}
}