{
  "type": "Feature",
  "properties": {
    "iso:country":"US",
    "sg:address":"30 E Sprague Ave",
    "sg:city":"Spokane",
    "sg:classifiers":[
        {
            "category":"Wholesale",
            "subcategory":"Toys & Hobbies",
            "type":"Manufacturing & Wholesale Goods"
        },
        {
            "category":"Shopping",
            "subcategory":"Hobbies, Toys, & Games",
            "type":"Retail Goods"
        }
    ],
    "sg:phone":"+1 509 747 1339",
    "sg:postcode":"99202",
    "sg:province":"WA",
    "sg:tags":[
        "bingo",
        "gaming",
        "product",
        "supply"
    ],
    "wof:name":"Spokane Pull Tab & Bingo Supl",
    "wof:placetype":"venue"
},
  "geometry": {"coordinates":[-117.410737,47.657187],"type":"Point"}
}