{
  "type": "Feature",
  "properties": {
    "addr:full":"1332 State Ave Marysville WA 98270",
    "addr:housenumber":"1332",
    "addr:postcode":"98270",
    "addr:street":"State Ave",
    "iso:country":"US",
    "sg:address":"1332 State Ave",
    "sg:city":"Marysville",
    "sg:classifiers":[
        {
            "category":"Cinema",
            "subcategory":"Movie Rental",
            "type":"Entertainment"
        }
    ],
    "sg:phone":"+1 360 653 9235",
    "sg:postcode":"98270",
    "sg:province":"WA",
    "sg:tags":[
        "video",
        "sales"
    ],
    "wof:name":"Video Works",
    "wof:placetype":"venue"
},
  "geometry": {"coordinates":[-122.176845,48.06656],"type":"Point"}
}