{
  "type": "Feature",
  "properties": {
    "addr:full":"12711 145th St E Puyallup WA 98374",
    "addr:housenumber":"12711",
    "addr:postcode":"98374",
    "addr:street":"145Th St E",
    "iso:country":"US",
    "sg:address":"12711 145th St E",
    "sg:city":"Puyallup",
    "sg:classifiers":[
        {
            "category":"Manufacturing",
            "subcategory":"Retail Goods",
            "type":"Manufacturing & Wholesale Goods"
        }
    ],
    "sg:phone":"+1 253 596 0113",
    "sg:postcode":"98374",
    "sg:province":"WA",
    "sg:tags":[
        "product",
        "mfg"
    ],
    "wof:name":"Premier Industries",
    "wof:placetype":"venue"
},
  "geometry": {"coordinates":[-122.257482,47.124592],"type":"Point"}
}