{
  "type": "Feature",
  "properties": {
    "addr:full":"4823 S Thistle St Seattle WA 98118",
    "addr:housenumber":"4823",
    "addr:postcode":"98118",
    "addr:street":"S Thistle St",
    "iso:country":"US",
    "sg:address":"4823 S Thistle St",
    "sg:city":"Seattle",
    "sg:classifiers":[
        {
            "category":"Personal",
            "subcategory":"Barber",
            "type":"Services"
        }
    ],
    "sg:phone":"+1 206 723 1623",
    "sg:postcode":"98118",
    "sg:province":"WA",
    "sg:tags":[
        "shop"
    ],
    "wof:name":"Elme Barber",
    "wof:placetype":"venue"
},
  "geometry": {"coordinates":[-122.27141,47.527833],"type":"Point"}
}