{
  "type": "Feature",
  "properties": {
    "addr:full":"1303 NW 4th St Battle Ground WA 98604",
    "addr:housenumber":"1303",
    "addr:postcode":"98604",
    "addr:street":"Nw 4Th St",
    "iso:country":"US",
    "sg:address":"1303 NW 4th St",
    "sg:city":"Battle Ground",
    "sg:classifiers":[
        {
            "category":"Professional",
            "subcategory":"Computer Services",
            "type":"Services"
        }
    ],
    "sg:phone":"+1 360 936 1562",
    "sg:postcode":"98604",
    "sg:province":"WA",
    "sg:tags":[
        "datum"
    ],
    "wof:name":"Mountain View Processing",
    "wof:placetype":"venue"
},
  "geometry": {"coordinates":[-122.551331,45.783888],"type":"Point"}
}