{
  "type": "Feature",
  "properties": {
    "addr:full":"100 Eastmont Ave East Wenatchee WA 98802",
    "addr:housenumber":"100",
    "addr:postcode":"98802",
    "addr:street":"Eastmont Ave",
    "iso:country":"US",
    "sg:address":"100 Eastmont Ave",
    "sg:city":"East Wenatchee",
    "sg:classifiers":[
        {
            "category":"Restaurant",
            "type":"Food & Drink"
        }
    ],
    "sg:menulink":"http://www.allmenus.com/wa/east-wenatchee/235482-taco-time/menu/",
    "sg:phone":"+1 509 884 0163",
    "sg:postcode":"98802",
    "sg:province":"WA",
    "sg:tags":[
        "american",
        "mexican",
        "tex-mex"
    ],
    "wof:name":"Taco Time",
    "wof:placetype":"venue"
},
  "geometry": {"coordinates":[-120.281886,47.407555],"type":"Point"}
}