{
  "type": "Feature",
  "properties": {
    "addr:full":"2101 NW 77th St Seattle WA 98117",
    "addr:housenumber":"2101",
    "addr:postcode":"98117",
    "addr:street":"Nw 77Th St",
    "iso:country":"US",
    "sg:address":"2101 NW 77th St",
    "sg:city":"Seattle",
    "sg:classifiers":[
        {
            "category":"Government",
            "subcategory":"City Hall",
            "type":"Public Place"
        }
    ],
    "sg:phone":"+1 206 684 4052",
    "sg:postcode":"98117",
    "sg:province":"WA",
    "sg:website":"www.seattle.gov/",
    "wof:name":"Loyal Heights Community Center",
    "wof:placetype":"venue"
},
  "geometry": {"coordinates":[-122.383242,47.684104],"type":"Point"}
}