{
  "type": "Feature",
  "properties": {
    "addr:full":"3518 Black Lake Blvd SW Olympia WA 98512",
    "addr:housenumber":"3518",
    "addr:postcode":"98512",
    "addr:street":"Black Lake Blvd Sw",
    "iso:country":"US",
    "sg:address":"3518 Black Lake Blvd SW",
    "sg:city":"Olympia",
    "sg:classifiers":[
        {
            "category":"Retail",
            "subcategory":"Auto Repair",
            "type":"Services"
        }
    ],
    "sg:phone":"+1 360 705 0224",
    "sg:postcode":"98512",
    "sg:province":"WA",
    "sg:tags":[
        "repairing",
        "automobile",
        "general"
    ],
    "wof:name":"Pacific Automotive Of Tumwater",
    "wof:placetype":"venue"
},
  "geometry": {"coordinates":[-122.961153,47.014923],"type":"Point"}
}