{
  "type": "Feature",
  "properties": {
    "addr:full":"1495 E Columbia St Seattle WA 98122",
    "addr:housenumber":"1495",
    "addr:postcode":"98122",
    "addr:street":"E Columbia St",
    "iso:country":"US",
    "sg:address":"1495 E Columbia St",
    "sg:city":"Seattle",
    "sg:classifiers":[
        {
            "category":"Professional",
            "subcategory":"Business Services",
            "type":"Services"
        }
    ],
    "sg:phone":"+1 206 762 0202",
    "sg:postcode":"98122",
    "sg:province":"WA",
    "wof:name":"Andre Hobson",
    "wof:placetype":"venue"
},
  "geometry": {"coordinates":[-122.31368500000001,47.609138],"type":"Point"}
}