{
  "type": "Feature",
  "properties": {
    "addr:full":"20322 24th Ave NE Seattle WA 98155",
    "addr:housenumber":"20322",
    "addr:postcode":"98155",
    "addr:street":"24Th Ave Ne",
    "iso:country":"US",
    "sg:address":"20322 24th Ave NE",
    "sg:city":"Seattle",
    "sg:classifiers":[
        {
            "category":"Professional",
            "subcategory":"Business Services",
            "type":"Services"
        }
    ],
    "sg:phone":"+1 206 362 0359",
    "sg:postcode":"98155",
    "sg:province":"WA",
    "wof:name":"Quick Hand Work",
    "wof:placetype":"venue"
},
  "geometry": {"coordinates":[-122.304112,47.775107],"type":"Point"}
}