{
  "type": "Feature",
  "properties": {
    "addr:full":"10316 122nd St NW Gig Harbor WA 98329",
    "addr:housenumber":"10316",
    "addr:postcode":"98329",
    "addr:street":"122Nd St Nw",
    "iso:country":"US",
    "sg:address":"10316 122nd St NW",
    "sg:city":"Gig Harbor",
    "sg:classifiers":[
        {
            "category":"Building & Trades",
            "subcategory":"Construction",
            "type":"Services"
        }
    ],
    "sg:phone":"+1 253 549 6248",
    "sg:postcode":"98329",
    "sg:province":"WA",
    "sg:tags":[
        "house",
        "residential"
    ],
    "wof:name":"CDF Home Improvement",
    "wof:placetype":"venue"
},
  "geometry": {"coordinates":[-122.67388,47.369276],"type":"Point"}
}