{
  "type": "Feature",
  "properties": {
    "addr:full":"2353 140th Ave NE Bellevue WA 98005",
    "addr:housenumber":"2353",
    "addr:postcode":"98005",
    "addr:street":"140Th Ave Ne",
    "iso:country":"US",
    "sg:address":"2353 140th Ave NE",
    "sg:city":"Bellevue",
    "sg:classifiers":[
        {
            "category":"Food & Beverages",
            "subcategory":"Groceries & Convenience Stores",
            "type":"Retail Goods"
        }
    ],
    "sg:phone":"+1 425 643 0771",
    "sg:postcode":"98005",
    "sg:province":"WA",
    "sg:website":"www.7-eleven.com",
    "wof:name":"Seven Eleven Food Stores",
    "wof:placetype":"venue"
},
  "geometry": {"coordinates":[-122.153999,47.631302],"type":"Point"}
}