{
  "type": "Feature",
  "properties": {
    "addr:full":"1821 10th Ave W Seattle WA 98119",
    "addr:housenumber":"1821",
    "addr:postcode":"98119",
    "addr:street":"10Th Ave W",
    "iso:country":"US",
    "sg:address":"1821 10th Ave W",
    "sg:city":"Seattle",
    "sg:classifiers":[
        {
            "category":"Home & Garden",
            "subcategory":"Hardware",
            "type":"Retail Goods"
        },
        {
            "category":"Wholesale",
            "subcategory":"Durable Goods & Equipment",
            "type":"Manufacturing & Wholesale Goods"
        },
        {
            "category":"Utilities",
            "subcategory":"Natural Gas",
            "type":"Services"
        },
        {
            "category":"Manufacturing",
            "subcategory":"Building Materials",
            "type":"Manufacturing & Wholesale Goods"
        }
    ],
    "sg:phone":"+1 206 284 9440",
    "sg:postcode":"98119",
    "sg:province":"WA",
    "sg:tags":[
        "filtering",
        "filtration",
        "filters-liquid-wholesale",
        "supply",
        "purification",
        "water",
        "filters-air"
    ],
    "wof:name":"Calhoun & Dejong Incorporated",
    "wof:placetype":"venue"
},
  "geometry": {"coordinates":[-122.370373,47.634984],"type":"Point"}
}