{
  "type": "Feature",
  "properties": {
    "addr:full":"2150 Sunset Ave SW Seattle WA 98116",
    "addr:housenumber":"2150",
    "addr:postcode":"98116",
    "addr:street":"Sunset Ave Sw",
    "iso:country":"US",
    "sg:address":"2150 Sunset Ave SW",
    "sg:city":"Seattle",
    "sg:classifiers":[
        {
            "category":"Professional",
            "subcategory":"Business Services",
            "type":"Services"
        }
    ],
    "sg:phone":"+1 206 932 2298",
    "sg:postcode":"98116",
    "sg:province":"WA",
    "wof:name":"Metcalf Larry Designer",
    "wof:placetype":"venue"
},
  "geometry": {"coordinates":[-122.396478,47.583656],"type":"Point"}
}