{
  "type": "Feature",
  "properties": {
    "addr:full":"4003 State Rte 508 Cinebar WA 98533",
    "addr:housenumber":"4003",
    "addr:postcode":"98533",
    "addr:street":"State Rte 508 Cinebar",
    "iso:country":"US",
    "sg:address":"4003 State Rte 508",
    "sg:city":"Cinebar",
    "sg:classifiers":[
        {
            "category":"Manufacturing",
            "subcategory":"Lumber",
            "type":"Manufacturing & Wholesale Goods"
        }
    ],
    "sg:phone":"+1 360 985 2880",
    "sg:postcode":"98533",
    "sg:province":"WA",
    "sg:tags":[
        "logging"
    ],
    "wof:name":"Chapman Logging",
    "wof:placetype":"venue"
},
  "geometry": {"coordinates":[-122.516199,46.604705],"type":"Point"}
}