{
  "type": "Feature",
  "properties": {
    "addr:full":"20111 E Gilbert Ave Otis Orchards WA 99027",
    "addr:housenumber":"20111",
    "addr:postcode":"99027",
    "addr:street":"E Gilbert Ave",
    "iso:country":"US",
    "sg:address":"20111 E Gilbert Ave",
    "sg:city":"Otis Orchards",
    "sg:classifiers":[
        {
            "category":"Restaurant",
            "type":"Food & Drink"
        }
    ],
    "sg:phone":"+1 509 891 6137",
    "sg:postcode":"99027",
    "sg:province":"WA",
    "sg:tags":[
        "eating"
    ],
    "wof:name":"Lucis Catering",
    "wof:placetype":"venue"
},
  "geometry": {"coordinates":[-117.13518000000001,47.703046],"type":"Point"}
}