{
  "type": "Feature",
  "properties": {
    "addr:full":"125 15th Avenue Seattle WA 98122",
    "addr:housenumber":"125",
    "addr:postcode":"98122",
    "addr:street":"15Th Avenue",
    "iso:country":"US",
    "sg:address":"125 15th Avenue",
    "sg:city":"Seattle",
    "sg:classifiers":[
        {
            "category":"Community Center",
            "type":"Public Place"
        }
    ],
    "sg:phone":"+1 206 901 4343",
    "sg:postcode":"98122",
    "sg:province":"WA",
    "sg:tags":[
        "medical"
    ],
    "wof:name":"Group Health Cooperative",
    "wof:placetype":"venue"
},
  "geometry": {"coordinates":[-122.313068,47.602358],"type":"Point"}
}