{
  "type": "Feature",
  "properties": {
    "addr:full":"220 2nd Ave S Seattle WA 98104",
    "addr:housenumber":"220",
    "addr:postcode":"98104",
    "addr:street":"2Nd Ave S",
    "iso:country":"US",
    "sg:address":"220 2nd Ave S",
    "sg:city":"Seattle",
    "sg:classifiers":[
        {
            "category":"Retail",
            "subcategory":"Repair Shop",
            "type":"Services"
        }
    ],
    "sg:phone":"+1 206 682 8263",
    "sg:postcode":"98104",
    "sg:province":"WA",
    "wof:name":"Kirbys Upholstery",
    "wof:placetype":"venue"
},
  "geometry": {"coordinates":[-122.33150000000001,47.600207],"type":"Point"}
}