{
  "type": "Feature",
  "properties": {
    "addr:full":"7619 156th St E Puyallup WA 98375",
    "addr:housenumber":"7619",
    "addr:postcode":"98375",
    "addr:street":"156Th St E",
    "iso:country":"US",
    "sg:address":"7619 156th St E",
    "sg:city":"Puyallup",
    "sg:classifiers":[
        {
            "category":"Shopping",
            "subcategory":"Hobbies, Toys, & Games",
            "type":"Retail Goods"
        }
    ],
    "sg:phone":"+1 253 537 7216",
    "sg:postcode":"98375",
    "sg:province":"WA",
    "wof:name":"Critters Things By BJ",
    "wof:placetype":"venue"
},
  "geometry": {"coordinates":[-122.326459,47.11479],"type":"Point"}
}