{
  "type": "Feature",
  "properties": {
    "addr:full":"16114 NE 87th St Redmond WA 98052",
    "addr:housenumber":"16114",
    "addr:postcode":"98052",
    "addr:street":"Ne 87Th St",
    "iso:country":"US",
    "sg:address":"16114 NE 87th St",
    "sg:city":"Redmond",
    "sg:classifiers":[
        {
            "category":"Fast Food",
            "type":"Food & Drink"
        },
        {
            "category":"Restaurant",
            "type":"Food & Drink"
        }
    ],
    "sg:phone":"+1 425 952 4200",
    "sg:postcode":"98052",
    "sg:province":"WA",
    "sg:tags":[
        "greek",
        "mediterranean",
        "take"
    ],
    "wof:name":"Gyro World Greek Cafe",
    "wof:placetype":"venue"
},
  "geometry": {"coordinates":[-122.12533500000001,47.67979],"type":"Point"}
}