{
  "type": "Feature",
  "properties": {
    "addr:full":"127 E Cedar St Mc Cleary WA 98557",
    "addr:housenumber":"127",
    "addr:postcode":"98557",
    "addr:street":"E Cedar St Mc Cleary",
    "iso:country":"US",
    "sg:address":"127 E Cedar St",
    "sg:city":"Mc Cleary",
    "sg:classifiers":[
        {
            "category":"Professional",
            "type":"Services"
        }
    ],
    "sg:phone":"+1 360 495 3177",
    "sg:postcode":"98557",
    "sg:province":"WA",
    "wof:name":"Gators Adventures",
    "wof:placetype":"venue"
},
  "geometry": {"coordinates":[-123.263943,47.051043],"type":"Point"}
}