{
  "type": "Feature",
  "properties": {
    "addr:full":"4233 Thackeray Pl NE Seattle WA 98105",
    "addr:housenumber":"4233",
    "addr:postcode":"98105",
    "addr:street":"Thackeray Pl Ne",
    "iso:country":"US",
    "sg:address":"4233 Thackeray Pl NE",
    "sg:city":"Seattle",
    "sg:classifiers":[
        {
            "category":"Retail",
            "subcategory":"Portrait Studio",
            "type":"Services"
        }
    ],
    "sg:phone":"+1 206 545 1844",
    "sg:postcode":"98105",
    "sg:province":"WA",
    "sg:tags":[
        "photographer"
    ],
    "wof:name":"Eye-Scapes",
    "wof:placetype":"venue"
},
  "geometry": {"coordinates":[-122.32629300000001,47.658544],"type":"Point"}
}