{
  "type": "Feature",
  "properties": {
    "addr:full":"3002 Wetmore Ave Everett WA 98201",
    "addr:housenumber":"3002",
    "addr:postcode":"98201",
    "addr:street":"Wetmore Ave",
    "iso:country":"US",
    "sg:address":"3002 Wetmore Ave",
    "sg:city":"Everett",
    "sg:classifiers":[
        {
            "category":"Government",
            "subcategory":"Police Station",
            "type":"Public Place"
        }
    ],
    "sg:phone":"+1 425 257 8400",
    "sg:postcode":"98201",
    "sg:province":"WA",
    "sg:tags":[
        "protection"
    ],
    "wof:name":"Everett Police Department",
    "wof:placetype":"venue"
},
  "geometry": {"coordinates":[-122.207205,47.97658],"type":"Point"}
}