{
  "type": "Feature",
  "properties": {
    "addr:full":"4295 S 137th St Tukwila WA 98168",
    "addr:housenumber":"4295",
    "addr:postcode":"98168",
    "addr:street":"S 137Th St",
    "iso:country":"US",
    "sg:address":"4295 S 137th St",
    "sg:city":"Tukwila",
    "sg:classifiers":[
        {
            "category":"Building & Trades",
            "subcategory":"Cleaning & Sanitation",
            "type":"Services"
        }
    ],
    "sg:phone":"+1 206 262 9487",
    "sg:postcode":"98168",
    "sg:province":"WA",
    "sg:tags":[
        "cleaning-industrial",
        "contractor"
    ],
    "wof:name":"Abc Janitorial Cleaning Service",
    "wof:placetype":"venue"
},
  "geometry": {"coordinates":[-122.27865,47.480468],"type":"Point"}
}