{
  "type": "Feature",
  "properties": {
    "addr:full":"7405 Greenwood Ave N Seattle WA 98103",
    "addr:housenumber":"7405",
    "addr:postcode":"98103",
    "addr:street":"Greenwood Ave N",
    "iso:country":"US",
    "sg:address":"7405 Greenwood Ave N",
    "sg:city":"Seattle",
    "sg:classifiers":[
        {
            "category":"Shopping",
            "subcategory":"Books",
            "type":"Retail Goods"
        }
    ],
    "sg:phone":"+1 206 784 2113",
    "sg:postcode":"98103",
    "sg:province":"WA",
    "sg:tags":[
        "bookstore"
    ],
    "sg:website":"www.santorosbooks.com/",
    "wof:name":"Santoro's Books",
    "wof:placetype":"venue"
},
  "geometry": {"coordinates":[-122.35562,47.682782],"type":"Point"}
}