{
  "type": "Feature",
  "properties": {
    "addr:full":"2727 N Division St Spokane WA 99202",
    "addr:housenumber":"2727",
    "addr:postcode":"99202",
    "addr:street":"N Division St",
    "iso:country":"US",
    "sg:address":"2727 N Division St",
    "sg:city":"Spokane",
    "sg:classifiers":[
        {
            "category":"Retail",
            "subcategory":"Auto Rental",
            "type":"Services"
        }
    ],
    "sg:phone":"+1 509 328 0173",
    "sg:postcode":"99202",
    "sg:province":"WA",
    "sg:tags":[
        "renting",
        "automobile"
    ],
    "wof:name":"Enterprise Rent-A-Car",
    "wof:placetype":"venue"
},
  "geometry": {"coordinates":[-117.41125099999999,47.683427],"type":"Point"}
}