{
  "type": "Feature",
  "properties": {
    "addr:full":"705 Second Ave., Suite 800 Seattle WA 98104",
    "addr:housenumber":"705",
    "addr:postcode":"98104",
    "addr:street":"Second Ave. Suite 800",
    "iso:country":"US",
    "sg:address":"705 Second Ave., Suite 800",
    "sg:city":"Seattle",
    "sg:classifiers":[
        {
            "category":"Professional",
            "subcategory":"Lawyer & Legal Services",
            "type":"Services"
        }
    ],
    "sg:phone":"+1 206 903 1818",
    "sg:postcode":"98104",
    "sg:province":"WA",
    "sg:tags":[
        "attorney",
        "criminal",
        "estate",
        "personal",
        "practice",
        "planning",
        "injury",
        "law"
    ],
    "sg:website":"www.menzerlawfirm.com",
    "wof:name":"Menzer Law Firm",
    "wof:placetype":"venue"
},
  "geometry": {"coordinates":[-122.33364899999999,47.603022],"type":"Point"}
}