{
  "type": "Feature",
  "properties": {
    "addr:full":"22219 6th Ave S Des Moines WA 98198",
    "addr:housenumber":"22219",
    "addr:postcode":"98198",
    "addr:street":"6Th Ave S",
    "iso:country":"US",
    "sg:address":"22219 6th Ave S",
    "sg:city":"Des Moines",
    "sg:classifiers":[
        {
            "category":"Banks & Credit Unions",
            "subcategory":"Investment Brokerage",
            "type":"Services"
        }
    ],
    "sg:phone":"+1 206 246 6655",
    "sg:postcode":"98198",
    "sg:province":"WA",
    "sg:tags":[
        "advisory",
        "financial"
    ],
    "wof:name":"CEB Financial Corp",
    "wof:placetype":"venue"
},
  "geometry": {"coordinates":[-122.327398,47.402024],"type":"Point"}
}