{
  "type": "Feature",
  "properties": {
    "addr:full":"2710 Kulshan St Bellingham WA 98225",
    "addr:housenumber":"2710",
    "addr:postcode":"98225",
    "addr:street":"Kulshan St",
    "iso:country":"US",
    "sg:address":"2710 Kulshan St",
    "sg:city":"Bellingham",
    "sg:classifiers":[
        {
            "category":"Professional",
            "subcategory":"Employment Agencies",
            "type":"Services"
        }
    ],
    "sg:phone":"+1 360 738 3451",
    "sg:postcode":"98225",
    "sg:province":"WA",
    "sg:tags":[
        "help",
        "supply"
    ],
    "wof:name":"Nicole E Atkins Lmp",
    "wof:placetype":"venue"
},
  "geometry": {"coordinates":[-122.487143,48.766806],"type":"Point"}
}