{
  "type": "Feature",
  "properties": {
    "addr:full":"122 Butler Loop Rd Stevenson WA 98648",
    "addr:housenumber":"122",
    "addr:postcode":"98648",
    "addr:street":"Butler Loop Rd",
    "iso:country":"US",
    "sg:address":"122 Butler Loop Rd",
    "sg:city":"Stevenson",
    "sg:classifiers":[
        {
            "category":"Education",
            "subcategory":"School",
            "type":"Public Place"
        }
    ],
    "sg:phone":"+1 509 527 8239",
    "sg:postcode":"98648",
    "sg:province":"WA",
    "sg:tags":[
        "elementary"
    ],
    "sg:website":"http://www.skamania.org",
    "wof:name":"Skamania Elementary School",
    "wof:placetype":"venue"
},
  "geometry": {"coordinates":[-122.05013599999999,45.615866],"type":"Point"}
}