{
  "type": "Feature",
  "properties": {
    "addr:full":"10212 5th Ave NE Ste 100 Seattle WA 98125",
    "addr:housenumber":"10212",
    "addr:postcode":"98125",
    "addr:street":"5Th Ave Ne Ste 100",
    "iso:country":"US",
    "sg:address":"10212 5th Ave NE Ste 100",
    "sg:city":"Seattle",
    "sg:classifiers":[
        {
            "category":"Social Services",
            "type":"Services"
        }
    ],
    "sg:phone":"+1 206 522 9035",
    "sg:postcode":"98125",
    "sg:province":"WA",
    "wof:name":"Julia Putnam",
    "wof:placetype":"venue"
},
  "geometry": {"coordinates":[-122.32315199999999,47.702344],"type":"Point"}
}