{
  "type": "Feature",
  "properties": {
    "addr:full":"6850 35th Ave NE Seattle WA 98115",
    "addr:housenumber":"6850",
    "addr:postcode":"98115",
    "addr:street":"35Th Ave Ne",
    "iso:country":"US",
    "sg:address":"6850 35th Ave NE",
    "sg:city":"Seattle",
    "sg:classifiers":[
        {
            "category":"Health Services",
            "subcategory":"Doctor",
            "type":"Services"
        }
    ],
    "sg:phone":"+1 206 524 8020",
    "sg:postcode":"98115",
    "sg:province":"WA",
    "sg:tags":[
        "dentist"
    ],
    "wof:name":"Damon Orthodontics",
    "wof:placetype":"venue"
},
  "geometry": {"coordinates":[-122.290294,47.678957],"type":"Point"}
}