{
  "type": "Feature",
  "properties": {
    "addr:full":"113 S Eunice St Port Angeles WA 98362",
    "addr:housenumber":"113",
    "addr:postcode":"98362",
    "addr:street":"S Eunice St",
    "iso:country":"US",
    "sg:address":"113 S Eunice St",
    "sg:city":"Port Angeles",
    "sg:classifiers":[
        {
            "category":"Social Services",
            "type":"Services"
        }
    ],
    "sg:phone":"+1 360 452 1775",
    "sg:postcode":"98362",
    "sg:province":"WA",
    "sg:tags":[
        "counselor",
        "marriage",
        "family"
    ],
    "wof:name":"Carol J Hathaway",
    "wof:placetype":"venue"
},
  "geometry": {"coordinates":[-123.422566,48.114408],"type":"Point"}
}