{
  "type": "Feature",
  "properties": {
    "addr:full":"900 Pacific Ave Everett WA 98201",
    "addr:housenumber":"900",
    "addr:postcode":"98201",
    "addr:street":"Pacific Ave",
    "iso:country":"US",
    "sg:address":"900 Pacific Ave",
    "sg:city":"Everett",
    "sg:classifiers":[
        {
            "category":"Health Services",
            "subcategory":"Doctor",
            "type":"Services"
        }
    ],
    "sg:phone":"+1 425 259 3108",
    "sg:postcode":"98201",
    "sg:province":"WA",
    "sg:tags":[
        "physician",
        "surgeon"
    ],
    "wof:name":"Krolak James D MD",
    "wof:placetype":"venue"
},
  "geometry": {"coordinates":[-122.21817,47.97649],"type":"Point"}
}