{
  "type": "Feature",
  "properties": {
    "addr:full":"348 Parkplace Ctr Kirkland WA 98033",
    "addr:housenumber":"348",
    "addr:postcode":"98033",
    "addr:street":"Parkplace Ctr",
    "iso:country":"US",
    "sg:address":"348 Parkplace Ctr",
    "sg:city":"Kirkland",
    "sg:classifiers":[
        {
            "category":"Shopping",
            "subcategory":"Books",
            "type":"Retail Goods"
        },
        {
            "category":"Communications",
            "subcategory":"Newspaper",
            "type":"Services"
        },
        {
            "category":"Wholesale",
            "subcategory":"Stationery",
            "type":"Manufacturing & Wholesale Goods"
        }
    ],
    "sg:phone":"+1 425 828 6546",
    "sg:postcode":"98033",
    "sg:province":"WA",
    "sg:tags":[
        "magazine",
        "bookstore",
        "card"
    ],
    "wof:name":"Parkplace Books",
    "wof:placetype":"venue"
},
  "geometry": {"coordinates":[-122.200996,47.678299],"type":"Point"}
}