{
  "type": "Feature",
  "properties": {
    "iso:country":"US",
    "sg:address":"852 Commerce Ave",
    "sg:city":"Longview",
    "sg:classifiers":[
        {
            "category":"Social Services",
            "subcategory":"Adult Care",
            "type":"Services"
        }
    ],
    "sg:phone":"+1 360 423 2385",
    "sg:postcode":"98632",
    "sg:province":"WA",
    "sg:tags":[
        "therapy",
        "rehabilitation",
        "physical"
    ],
    "wof:name":"Peace Hlth Clmbia Rhbilitation",
    "wof:placetype":"venue"
},
  "geometry": {"coordinates":[-122.937354,46.129262],"type":"Point"}
}