{
  "type": "Feature",
  "properties": {
    "addr:full":"5795 NE Minder Rd Poulsbo WA 98370",
    "addr:housenumber":"5795",
    "addr:postcode":"98370",
    "addr:street":"Ne Minder Rd",
    "iso:country":"US",
    "sg:address":"5795 NE Minder Rd",
    "sg:city":"Poulsbo",
    "sg:classifiers":[
        {
            "category":"Building & Trades",
            "subcategory":"Construction",
            "type":"Services"
        }
    ],
    "sg:phone":"+1 360 297 5890",
    "sg:postcode":"98370",
    "sg:province":"WA",
    "sg:tags":[
        "general",
        "contractor"
    ],
    "wof:name":"North Star Ind Contractors",
    "wof:placetype":"venue"
},
  "geometry": {"coordinates":[-122.573751,47.798349],"type":"Point"}
}