{
  "type": "Feature",
  "properties": {
    "addr:full":"18911 Kelleher Rd Burlington WA 98233",
    "addr:postcode":"18911;98233",
    "addr:street":"Kelleher Rd",
    "iso:country":"US",
    "sg:address":"18911 Kelleher Rd",
    "sg:city":"Burlington",
    "sg:classifiers":[
        {
            "category":"Retail",
            "subcategory":"Animal Services",
            "type":"Services"
        }
    ],
    "sg:phone":"+1 360 757 0445",
    "sg:postcode":"98233",
    "sg:province":"WA",
    "sg:tags":[
        "shelter"
    ],
    "sg:website":"www.skagithumane.com",
    "wof:name":"Humane Society Of Skagit Vly",
    "wof:placetype":"venue"
},
  "geometry": {"coordinates":[-122.339607,48.528674],"type":"Point"}
}