{
  "type": "Feature",
  "properties": {
    "addr:full":"42740 268th Ave SE Enumclaw WA 98022",
    "addr:housenumber":"42740",
    "addr:postcode":"98022",
    "addr:street":"268Th Ave Se",
    "iso:country":"US",
    "sg:address":"42740 268th Ave SE",
    "sg:city":"Enumclaw",
    "sg:classifiers":[
        {
            "category":"Building & Trades",
            "subcategory":"Construction",
            "type":"Services"
        }
    ],
    "sg:phone":"+1 360 825 4728",
    "sg:postcode":"98022",
    "sg:province":"WA",
    "sg:tags":[
        "contractor"
    ],
    "wof:name":"La Gustafson Contracting",
    "wof:placetype":"venue"
},
  "geometry": {"coordinates":[-121.984275,47.217862],"type":"Point"}
}