{
  "type": "Feature",
  "properties": {
    "addr:full":"16404 36th Ave W Lynnwood WA 98037",
    "addr:housenumber":"16404",
    "addr:postcode":"98037",
    "addr:street":"36Th Ave W",
    "iso:country":"US",
    "sg:address":"16404 36th Ave W",
    "sg:city":"Lynnwood",
    "sg:classifiers":[
        {
            "category":"Autos & Motor Vehicles",
            "subcategory":"Fuel & Gas Station",
            "type":"Retail Goods"
        }
    ],
    "sg:phone":"+1 425 787 5810",
    "sg:postcode":"98037",
    "sg:province":"WA",
    "sg:tags":[
        "station",
        "gasoline"
    ],
    "wof:name":"Exxon",
    "wof:placetype":"venue"
},
  "geometry": {"coordinates":[-122.28196699999999,47.849263],"type":"Point"}
}