{
  "type": "Feature",
  "properties": {
    "addr:full":"26920 Pioneer Hwy Stanwood WA 98292",
    "addr:housenumber":"26920",
    "addr:postcode":"98292",
    "addr:street":"Pioneer Hwy",
    "iso:country":"US",
    "sg:address":"26920 Pioneer Hwy",
    "sg:city":"Stanwood",
    "sg:classifiers":[
        {
            "category":"Health Services",
            "subcategory":"Health Practitioner",
            "type":"Services"
        }
    ],
    "sg:phone":"+1 360 629 3684",
    "sg:postcode":"98292",
    "sg:province":"WA",
    "sg:tags":[
        "acupuncture"
    ],
    "wof:name":"Julia C Raneri Acupuncturist",
    "wof:placetype":"venue"
},
  "geometry": {"coordinates":[-122.346254,48.242189],"type":"Point"}
}