{
  "type": "Feature",
  "properties": {
    "iso:country":"US",
    "sg:address":"955 Officers Row",
    "sg:city":"Vancouver",
    "sg:classifiers":[
        {
            "category":"Personal",
            "type":"Services"
        }
    ],
    "sg:phone":"+1 360 694 1664",
    "sg:postcode":"98661",
    "sg:province":"WA",
    "wof:name":"Furst Corrie Hope Lmt",
    "wof:placetype":"venue"
},
  "geometry": {"coordinates":[-122.654022,45.627144],"type":"Point"}
}