{
  "type": "Feature",
  "properties": {
    "addr:full":"3206 16th Ave W Seattle WA 98119",
    "addr:housenumber":"3206",
    "addr:postcode":"98119",
    "addr:street":"16Th Ave W",
    "iso:country":"US",
    "sg:address":"3206 16th Ave W",
    "sg:city":"Seattle",
    "sg:classifiers":[
        {
            "category":"Health Services",
            "subcategory":"Health Practitioner",
            "type":"Services"
        }
    ],
    "sg:phone":"+1 206 284 6349",
    "sg:postcode":"98119",
    "sg:province":"WA",
    "sg:tags":[
        "acupuncture"
    ],
    "wof:name":"Classical Acupuncture",
    "wof:placetype":"venue"
},
  "geometry": {"coordinates":[-122.377415,47.650281],"type":"Point"}
}