{
  "type": "Feature",
  "properties": {
    "addr:full":"11734 239th Ave NE Redmond WA 98053",
    "addr:housenumber":"11734",
    "addr:postcode":"98053",
    "addr:street":"239Th Ave Ne",
    "iso:country":"US",
    "sg:address":"11734 239th Ave NE",
    "sg:city":"Redmond",
    "sg:classifiers":[
        {
            "category":"Personal",
            "type":"Services"
        }
    ],
    "sg:phone":"+1 425 868 0173",
    "sg:postcode":"98053",
    "sg:province":"WA",
    "wof:name":"Pet Sitters Unlimited",
    "wof:placetype":"venue"
},
  "geometry": {"coordinates":[-122.022446,47.702634],"type":"Point"}
}