{
  "type": "Feature",
  "properties": {
    "addr:full":"7011 Sycamore Ave NW Seattle WA 98117",
    "addr:housenumber":"7011",
    "addr:postcode":"98117",
    "addr:street":"Sycamore Ave Nw",
    "iso:country":"US",
    "sg:address":"7011 Sycamore Ave NW",
    "sg:city":"Seattle",
    "sg:classifiers":[
        {
            "category":"Building & Trades",
            "subcategory":"Construction",
            "type":"Services"
        }
    ],
    "sg:phone":"+1 206 784 4932",
    "sg:postcode":"98117",
    "sg:province":"WA",
    "sg:tags":[
        "consultant",
        "industrial",
        "contractors-commercial"
    ],
    "wof:name":"Dtr Enterprises",
    "wof:placetype":"venue"
},
  "geometry": {"coordinates":[-122.358436,47.67969],"type":"Point"}
}