{
  "type": "Feature",
  "properties": {
    "addr:full":"2800 156th Ave SE Ste 120 Bellevue WA 98007",
    "addr:housenumber":"2800",
    "addr:postcode":"98007",
    "addr:street":"156Th Ave Se Ste 120",
    "iso:country":"US",
    "sg:address":"2800 156th Ave SE Ste 120",
    "sg:city":"Bellevue",
    "sg:classifiers":[
        {
            "category":"Professional",
            "type":"Services"
        },
        {
            "category":"Professional",
            "subcategory":"Computer Services",
            "type":"Services"
        }
    ],
    "sg:phone":"+1 425 274 1121",
    "sg:postcode":"98007",
    "sg:province":"WA",
    "sg:tags":[
        "repair"
    ],
    "sg:website":"www.cyberstreams.com",
    "wof:name":"Cyberstreams",
    "wof:placetype":"venue"
},
  "geometry": {"coordinates":[-122.13201100000001,47.584977],"type":"Point"}
}