{
  "type": "Feature",
  "properties": {
    "addr:full":"4523 62nd St NW Gig Harbor WA 98335",
    "addr:housenumber":"4523",
    "addr:postcode":"98335",
    "addr:street":"62Nd St Nw",
    "iso:country":"US",
    "sg:address":"4523 62nd St NW",
    "sg:city":"Gig Harbor",
    "sg:classifiers":[
        {
            "category":"Shopping",
            "subcategory":"Computers & Home Electronics",
            "type":"Retail Goods"
        }
    ],
    "sg:phone":"+1 253 857 2456",
    "sg:postcode":"98335",
    "sg:province":"WA",
    "sg:tags":[
        "equipment",
        "satellite",
        "system"
    ],
    "wof:name":"Hemphill's Satellite Svc",
    "wof:placetype":"venue"
},
  "geometry": {"coordinates":[-122.599368,47.314505],"type":"Point"}
}