{
  "type": "Feature",
  "properties": {
    "addr:full":"210 Thurston Ave NE Olympia WA 98501",
    "addr:housenumber":"210",
    "addr:postcode":"98501",
    "addr:street":"Thurston Ave Ne",
    "iso:country":"US",
    "sg:address":"210 Thurston Ave NE",
    "sg:city":"Olympia",
    "sg:classifiers":[
        {
            "category":"Home & Garden",
            "subcategory":"Building Materials",
            "type":"Retail Goods"
        }
    ],
    "sg:phone":"+1 360 352 2250",
    "sg:postcode":"98501",
    "sg:province":"WA",
    "wof:name":"Windfall Lumber",
    "wof:placetype":"venue"
},
  "geometry": {"coordinates":[-122.89969499999999,47.047668],"type":"Point"}
}