{
  "type": "Feature",
  "properties": {
    "addr:full":"700 NW 185th St Apt 104 Shoreline WA 98177",
    "addr:housenumber":"700;104",
    "addr:postcode":"98177",
    "addr:street":"Nw 185Th St Apt",
    "iso:country":"US",
    "sg:address":"700 NW 185th St Apt 104",
    "sg:city":"Shoreline",
    "sg:phone":"+1 206 542 1637",
    "sg:postcode":"98177",
    "sg:province":"WA",
    "wof:name":"Highlands Apartments",
    "wof:placetype":"venue"
},
  "geometry": {"coordinates":[-122.365173,47.763302],"type":"Point"}
}