{
  "type": "Feature",
  "properties": {
    "iso:country":"US",
    "sg:address":"15515 Manion Way NE",
    "sg:city":"Duvall",
    "sg:classifiers":[
        {
            "category":"Shopping",
            "subcategory":"Used Merchandise",
            "type":"Retail Goods"
        }
    ],
    "sg:phone":"+1 425 788 7920",
    "sg:postcode":"98019",
    "sg:province":"WA",
    "wof:name":"Mc Coy Alana R",
    "wof:placetype":"venue"
},
  "geometry": {"coordinates":[-121.963959,47.738801],"type":"Point"}
}