{
  "type": "Feature",
  "properties": {
    "addr:full":"12911 120th Ave NE Kirkland WA 98034",
    "addr:housenumber":"12911",
    "addr:postcode":"98034",
    "addr:street":"120Th Ave Ne",
    "iso:country":"US",
    "sg:address":"12911 120th Ave NE",
    "sg:city":"Kirkland",
    "sg:classifiers":[
        {
            "category":"Health Services",
            "subcategory":"Doctor",
            "type":"Services"
        }
    ],
    "sg:phone":"+1 425 825 7575",
    "sg:postcode":"98034",
    "sg:province":"WA",
    "wof:name":"Neal Craig DD MD",
    "wof:placetype":"venue"
},
  "geometry": {"coordinates":[-122.203003,47.715401],"type":"Point"}
}