{
  "type": "Feature",
  "properties": {
    "addr:full":"12711 86th Pl NE Kirkland WA 98034",
    "addr:housenumber":"12711",
    "addr:postcode":"98034",
    "addr:street":"86Th Pl Ne",
    "iso:country":"US",
    "sg:address":"12711 86th Pl NE",
    "sg:city":"Kirkland",
    "sg:classifiers":[
        {
            "category":"Building & Trades",
            "subcategory":"Landscaping Services",
            "type":"Services"
        }
    ],
    "sg:phone":"+1 425 823 7715",
    "sg:postcode":"98034",
    "sg:province":"WA",
    "sg:tags":[
        "landscape"
    ],
    "wof:name":"Dominigoes Landscape Maint",
    "wof:placetype":"venue"
},
  "geometry": {"coordinates":[-122.22644200000001,47.715247],"type":"Point"}
}