{
  "type": "Feature",
  "properties": {
    "addr:full":"8856 35th Avenue SW Seattle WA 98126",
    "addr:housenumber":"8856",
    "addr:postcode":"98126",
    "addr:street":"35Th Avenue Sw",
    "iso:country":"US",
    "sg:address":"8856 35th Avenue SW",
    "sg:city":"Seattle",
    "sg:classifiers":[
        {
            "category":"Food & Beverages",
            "subcategory":"Groceries & Convenience Stores",
            "type":"Retail Goods"
        }
    ],
    "sg:phone":"+1 206 938 2018",
    "sg:postcode":"98126",
    "sg:province":"WA",
    "wof:name":"Gasco",
    "wof:placetype":"venue"
},
  "geometry": {"coordinates":[-122.376875,47.522975],"type":"Point"}
}