{
  "type": "Feature",
  "properties": {
    "addr:full":"10843 NE 8th St Ste 200 Bellevue WA 98004",
    "addr:housenumber":"10843",
    "addr:postcode":"98004",
    "addr:street":"Ne 8Th St Ste 200",
    "iso:country":"US",
    "sg:address":"10843 NE 8th St Ste 200",
    "sg:city":"Bellevue",
    "sg:classifiers":[
        {
            "category":"Real Estate",
            "subcategory":"Developer",
            "type":"Services"
        }
    ],
    "sg:phone":"+1 425 688 3085",
    "sg:postcode":"98004",
    "sg:province":"WA",
    "wof:name":"Seco Development Inc",
    "wof:placetype":"venue"
},
  "geometry": {"coordinates":[-122.19574799999999,47.617405],"type":"Point"}
}