{
  "type": "Feature",
  "properties": {
    "addr:full":"7820 27th St W Tacoma WA 98466",
    "addr:housenumber":"7820",
    "addr:postcode":"98466",
    "addr:street":"27Th St W",
    "iso:country":"US",
    "sg:address":"7820 27th St W",
    "sg:city":"Tacoma",
    "sg:classifiers":[
        {
            "category":"Health Services",
            "subcategory":"Chiropractor",
            "type":"Services"
        }
    ],
    "sg:phone":"+1 253 564 2920",
    "sg:postcode":"98466",
    "sg:province":"WA",
    "wof:name":"Mishko John",
    "wof:placetype":"venue"
},
  "geometry": {"coordinates":[-122.542771,47.235202],"type":"Point"}
}