{
  "type": "Feature",
  "properties": {
    "addr:full":"39 S Wenatchee Ave Wenatchee WA 98801",
    "addr:housenumber":"39",
    "addr:postcode":"98801",
    "addr:street":"S Wenatchee Ave",
    "iso:country":"US",
    "sg:address":"39 S Wenatchee Ave",
    "sg:city":"Wenatchee",
    "sg:classifiers":[
        {
            "category":"Health Services",
            "subcategory":"Hospital",
            "type":"Services"
        }
    ],
    "sg:phone":"+1 509 664 5300",
    "sg:postcode":"98801",
    "sg:province":"WA",
    "wof:name":"Lake Chelan Community Hosp",
    "wof:placetype":"venue"
},
  "geometry": {"coordinates":[-120.310839,47.423867],"type":"Point"}
}