{
  "type": "Feature",
  "properties": {
    "addr:full":"181 Laurel Rd Glenwood WA 98619",
    "addr:housenumber":"181",
    "addr:postcode":"98619",
    "addr:street":"Laurel Rd",
    "iso:country":"US",
    "sg:address":"181 Laurel Rd",
    "sg:city":"Glenwood",
    "sg:classifiers":[
        {
            "category":"Farming",
            "subcategory":"Livestock Farm",
            "type":"Manufacturing & Wholesale Goods"
        }
    ],
    "sg:phone":"+1 509 364 3570",
    "sg:postcode":"98619",
    "sg:province":"WA",
    "sg:tags":[
        "beef",
        "feedlot",
        "cattle"
    ],
    "wof:name":"Bill Giersch",
    "wof:placetype":"venue"
},
  "geometry": {"coordinates":[-121.380039,45.938134],"type":"Point"}
}