{
  "type": "Feature",
  "properties": {
    "addr:full":"16505 SE 1st St Ste A Vancouver WA 98684",
    "addr:postcode":"16505;98684",
    "addr:street":"Se 1St St Ste A",
    "iso:country":"US",
    "sg:address":"16505 SE 1st St Ste A",
    "sg:city":"Vancouver",
    "sg:classifiers":[
        {
            "category":"Real Estate",
            "subcategory":"Real Estate Services",
            "type":"Services"
        }
    ],
    "sg:phone":"+1 360 253 6606",
    "sg:postcode":"98684",
    "sg:province":"WA",
    "sg:tags":[
        "vacancy",
        "rental",
        "listing"
    ],
    "wof:name":"Dallesport Investments",
    "wof:placetype":"venue"
},
  "geometry": {"coordinates":[-122.50300799999999,45.621189],"type":"Point"}
}