{
  "type": "Feature",
  "properties": {
    "addr:full":"8220 W Gage Blvd Kennewick WA 99336",
    "addr:housenumber":"8220",
    "addr:postcode":"99336",
    "addr:street":"W Gage Blvd",
    "iso:country":"US",
    "sg:address":"8220 W Gage Blvd",
    "sg:city":"Kennewick",
    "sg:classifiers":[
        {
            "category":"Professional",
            "subcategory":"Business Services",
            "type":"Services"
        }
    ],
    "sg:phone":"+1 509 783 8207",
    "sg:postcode":"99336",
    "sg:province":"WA",
    "sg:tags":[
        "interior",
        "consultant",
        "design",
        "decorator"
    ],
    "wof:name":"Cathryn Boyd Interiors",
    "wof:placetype":"venue"
},
  "geometry": {"coordinates":[-119.233256,46.227175],"type":"Point"}
}