{
  "type": "Feature",
  "properties": {
    "addr:full":"16 Roy St Seattle WA 98109",
    "addr:housenumber":"16",
    "addr:postcode":"98109",
    "addr:street":"Roy St",
    "iso:country":"US",
    "sg:address":"16 Roy St",
    "sg:city":"Seattle",
    "sg:phone":"+1 206 281 1616",
    "sg:postcode":"98109",
    "sg:province":"WA",
    "wof:name":"Emerald City Medical Arts",
    "wof:placetype":"venue"
},
  "geometry": {"coordinates":[-122.3565,47.625481],"type":"Point"}
}