{
  "type": "Feature",
  "properties": {
    "addr:full":"7928 207th Pl NE Redmond WA 98053",
    "addr:housenumber":"7928",
    "addr:postcode":"98053",
    "addr:street":"207Th Pl Ne",
    "iso:country":"US",
    "sg:address":"7928 207th Pl NE",
    "sg:city":"Redmond",
    "sg:classifiers":[
        {
            "category":"Professional",
            "type":"Services"
        }
    ],
    "sg:phone":"+1 425 836 8818",
    "sg:postcode":"98053",
    "sg:province":"WA",
    "wof:name":"Nilsen & Sons",
    "wof:placetype":"venue"
},
  "geometry": {"coordinates":[-122.063496,47.674747],"type":"Point"}
}