{
  "type": "Feature",
  "properties": {
    "addr:full":"8914 Lake City Way NE Seattle WA 98115",
    "addr:housenumber":"8914",
    "addr:postcode":"98115",
    "addr:street":"Lake City Way Ne",
    "iso:country":"US",
    "sg:address":"8914 Lake City Way NE",
    "sg:city":"Seattle",
    "sg:classifiers":[
        {
            "category":"Bars & Pubs",
            "subcategory":"Lounge",
            "type":"Food & Drink"
        },
        {
            "category":"Restaurant",
            "type":"Food & Drink"
        }
    ],
    "sg:phone":"+1 206 522 3863",
    "sg:postcode":"98115",
    "sg:province":"WA",
    "sg:tags":[
        "seafood",
        "pan",
        "cocktail",
        "chinese",
        "asian"
    ],
    "sg:website":"7seasseattle.com",
    "wof:name":"Seven Seas Restaurant",
    "wof:placetype":"venue"
},
  "geometry": {"coordinates":[-122.30500000000001,47.693199],"type":"Point"}
}