{
  "type": "Feature",
  "properties": {
    "addr:full":"6987 Perimeter Rd S # 130 Seattle WA 98108",
    "addr:housenumber":"6987",
    "addr:postcode":"98108",
    "addr:street":"Perimeter Rd S # 130",
    "iso:country":"US",
    "sg:address":"6987 Perimeter Rd S # 130",
    "sg:city":"Seattle",
    "sg:classifiers":[
        {
            "category":"Airline",
            "type":"Transportation"
        },
        {
            "category":"Government",
            "subcategory":"Department Of Motor Vehicles",
            "type":"Public Place"
        }
    ],
    "sg:phone":"+1 206 763 6306",
    "sg:postcode":"98108",
    "sg:province":"WA",
    "sg:tags":[
        "rental",
        "service-air",
        "leasing",
        "aircraft-charter",
        "ambulance"
    ],
    "sg:website":"http://www.execflight.com",
    "wof:name":"Executive Flight, Inc.",
    "wof:placetype":"venue"
},
  "geometry": {"coordinates":[-122.304422,47.538865],"type":"Point"}
}