{
  "type": "Feature",
  "properties": {
    "addr:full":"15923 52nd Pl W Edmonds WA 98026",
    "addr:housenumber":"15923",
    "addr:postcode":"98026",
    "addr:street":"52Nd Pl W",
    "iso:country":"US",
    "sg:address":"15923 52nd Pl W",
    "sg:city":"Edmonds",
    "sg:classifiers":[
        {
            "category":"Building & Trades",
            "subcategory":"Construction",
            "type":"Services"
        }
    ],
    "sg:phone":"+1 425 743 4220",
    "sg:postcode":"98026",
    "sg:province":"WA",
    "sg:tags":[
        "excavating",
        "contractor"
    ],
    "wof:name":"Kunkel Moving & Raising",
    "wof:placetype":"venue"
},
  "geometry": {"coordinates":[-122.304641,47.853883],"type":"Point"}
}