{
  "type": "Feature",
  "properties": {
    "iso:country":"US",
    "sg:address":"613 N Pine St",
    "sg:city":"Ellensburg",
    "sg:classifiers":[
        {
            "category":"Shopping",
            "type":"Retail Goods"
        }
    ],
    "sg:phone":"+1 509 925 7446",
    "sg:postcode":"98926",
    "sg:province":"WA",
    "sg:tags":[
        "commercial",
        "design",
        "merchandise",
        "mfg"
    ],
    "wof:name":"Signdog",
    "wof:placetype":"venue"
},
  "geometry": {"coordinates":[-120.54610599999999,46.998509],"type":"Point"}
}