{
  "type": "Feature",
  "properties": {
    "addr:full":"10620 NE Fourth Plain Rd Vancouver WA 98662",
    "addr:housenumber":"10620",
    "addr:postcode":"98662",
    "addr:street":"Ne Fourth Plain Rd",
    "iso:country":"US",
    "sg:address":"10620 NE Fourth Plain Rd",
    "sg:city":"Vancouver",
    "sg:classifiers":[
        {
            "category":"Cinema",
            "subcategory":"Movie Rental",
            "type":"Entertainment"
        }
    ],
    "sg:phone":"+1 360 253 2806",
    "sg:postcode":"98662",
    "sg:province":"WA",
    "sg:tags":[
        "video",
        "tape"
    ],
    "wof:name":"Adult Video Only",
    "wof:placetype":"venue"
},
  "geometry": {"coordinates":[-122.56374,45.664062],"type":"Point"}
}