{
  "type": "Feature",
  "properties": {
    "addr:full":"1415 75th St SE Everett WA 98203",
    "addr:housenumber":"1415",
    "addr:postcode":"98203",
    "addr:street":"75Th St Se",
    "iso:country":"US",
    "sg:address":"1415 75th St SE",
    "sg:city":"Everett",
    "sg:classifiers":[
        {
            "category":"Manufacturing",
            "subcategory":"Apparel",
            "type":"Manufacturing & Wholesale Goods"
        }
    ],
    "sg:phone":"+1 425 347 1810",
    "sg:postcode":"98203",
    "sg:province":"WA",
    "sg:tags":[
        "sewing",
        "contractor"
    ],
    "wof:name":"Vera's Sewing",
    "wof:placetype":"venue"
},
  "geometry": {"coordinates":[-122.212096,47.930223],"type":"Point"}
}