{
  "type": "Feature",
  "properties": {
    "addr:full":"108 E Spring St Colfax WA 99111",
    "addr:housenumber":"108",
    "addr:postcode":"99111",
    "addr:street":"E Spring St",
    "iso:country":"US",
    "sg:address":"108 E Spring St",
    "sg:city":"Colfax",
    "sg:classifiers":[
        {
            "category":"Personal",
            "subcategory":"Beauty Salon",
            "type":"Services"
        }
    ],
    "sg:phone":"+1 509 397 3005",
    "sg:postcode":"99111",
    "sg:province":"WA",
    "wof:name":"Ford's Fl'Hair",
    "wof:placetype":"venue"
},
  "geometry": {"coordinates":[-117.364625,46.880811],"type":"Point"}
}