{
  "type": "Feature",
  "properties": {
    "addr:full":"200 Lilly Rd NE Olympia WA 98506",
    "addr:housenumber":"200",
    "addr:postcode":"98506",
    "addr:street":"Lilly Rd Ne",
    "iso:country":"US",
    "sg:address":"200 Lilly Rd NE",
    "sg:city":"Olympia",
    "sg:classifiers":[
        {
            "category":"Health Services",
            "subcategory":"Health Practitioner",
            "type":"Services"
        }
    ],
    "sg:phone":"+1 360 923 5588",
    "sg:postcode":"98506",
    "sg:province":"WA",
    "wof:name":"Michelle Monet Lmp Burke",
    "wof:placetype":"venue"
},
  "geometry": {"coordinates":[-122.844441,47.051018],"type":"Point"}
}