{
  "type": "Feature",
  "properties": {
    "addr:full":"11133 S Andrus Rd Cheney WA 99004",
    "addr:housenumber":"11133",
    "addr:postcode":"99004",
    "addr:street":"S Andrus Rd",
    "iso:country":"US",
    "sg:address":"11133 S Andrus Rd",
    "sg:city":"Cheney",
    "sg:classifiers":[
        {
            "category":"Manufacturing",
            "subcategory":"Printing",
            "type":"Manufacturing & Wholesale Goods"
        }
    ],
    "sg:phone":"+1 509 747 3940",
    "sg:postcode":"99004",
    "sg:province":"WA",
    "sg:tags":[
        "periodical"
    ],
    "wof:name":"Express Publications",
    "wof:placetype":"venue"
},
  "geometry": {"coordinates":[-117.530466,47.553696],"type":"Point"}
}