{
  "type": "Feature",
  "properties": {
    "addr:full":"36621 SE David Powell Rd Fall City WA 98024",
    "addr:postcode":"36621;98024",
    "addr:street":"Se David Powell Rd",
    "iso:country":"US",
    "sg:address":"36621 SE David Powell Rd",
    "sg:city":"Fall City",
    "sg:classifiers":[
        {
            "category":"Communications",
            "subcategory":"Film & Video Production",
            "type":"Services"
        }
    ],
    "sg:phone":"+1 425 222 9599",
    "sg:postcode":"98024",
    "sg:province":"WA",
    "sg:tags":[
        "motion"
    ],
    "wof:name":"Fall Line Productions",
    "wof:placetype":"venue"
},
  "geometry": {"coordinates":[-121.849097,47.549105],"type":"Point"}
}