{
  "type": "Feature",
  "properties": {
    "addr:full":"14009 NE 7th Pl Vancouver WA 98685",
    "addr:housenumber":"14009",
    "addr:postcode":"98685",
    "addr:street":"Ne 7Th Pl",
    "iso:country":"US",
    "sg:address":"14009 NE 7th Pl",
    "sg:city":"Vancouver",
    "sg:classifiers":[
        {
            "category":"Health Services",
            "subcategory":"Doctor",
            "type":"Services"
        }
    ],
    "sg:phone":"+1 360 573 5496",
    "sg:postcode":"98685",
    "sg:province":"WA",
    "wof:name":"Majestic Smile",
    "wof:placetype":"venue"
},
  "geometry": {"coordinates":[-122.663854,45.722454],"type":"Point"}
}