{
  "type": "Feature",
  "properties": {
    "addr:full":"160 Harrison Rd Sequim WA 98382",
    "addr:housenumber":"160",
    "addr:postcode":"98382",
    "addr:street":"Harrison Rd",
    "iso:country":"US",
    "sg:address":"160 Harrison Rd",
    "sg:city":"Sequim",
    "sg:classifiers":[
        {
            "category":"Autos & Motor Vehicles",
            "subcategory":"Automobile Sales",
            "type":"Retail Goods"
        },
        {
            "category":"Sports & Exercise",
            "subcategory":"Golf",
            "type":"Entertainment"
        }
    ],
    "sg:phone":"+1 360 683 5343",
    "sg:postcode":"98382",
    "sg:province":"WA",
    "sg:tags":[
        "car",
        "cart",
        "new"
    ],
    "wof:name":"Savvy Inc",
    "wof:placetype":"venue"
},
  "geometry": {"coordinates":[-123.16906400000001,48.076973],"type":"Point"}
}