{
  "type": "Feature",
  "properties": {
    "addr:full":"2421 93rd Ave SW Olympia WA 98512",
    "addr:housenumber":"2421",
    "addr:postcode":"98512",
    "addr:street":"93Rd Ave Sw",
    "iso:country":"US",
    "sg:address":"2421 93rd Ave SW",
    "sg:city":"Olympia",
    "sg:classifiers":[
        {
            "category":"Home & Garden",
            "subcategory":"Building Materials",
            "type":"Retail Goods"
        },
        {
            "category":"Home & Garden",
            "subcategory":"Hardware",
            "type":"Retail Goods"
        }
    ],
    "sg:phone":"+1 360 956 9147",
    "sg:postcode":"98512",
    "sg:province":"WA",
    "wof:name":"Lincoln Creek Lumber Co Inc",
    "wof:placetype":"venue"
},
  "geometry": {"coordinates":[-122.936436,46.952676],"type":"Point"}
}