{
  "type": "Feature",
  "properties": {
    "addr:full":"8697 W Gage Blvd Kennewick WA 99336",
    "addr:housenumber":"8697",
    "addr:postcode":"99336",
    "addr:street":"W Gage Blvd",
    "iso:country":"US",
    "sg:address":"8697 W Gage Blvd",
    "sg:city":"Kennewick",
    "sg:classifiers":[
        {
            "category":"Professional",
            "subcategory":"Art Services",
            "type":"Services"
        },
        {
            "category":"Real Estate",
            "subcategory":"Architect",
            "type":"Services"
        }
    ],
    "sg:phone":"+1 509 591 0868",
    "sg:postcode":"99336",
    "sg:province":"WA",
    "sg:tags":[
        "interior",
        "designer",
        "decorator"
    ],
    "sg:website":"http://www.meierinc.com",
    "wof:name":"MEIER Enterprises Inc",
    "wof:placetype":"venue"
},
  "geometry": {"coordinates":[-119.23806,46.227169],"type":"Point"}
}