{
  "type": "Feature",
  "properties": {
    "iso:country":"US",
    "sg:address":"3280 SE Lund Ave",
    "sg:city":"Port Orchard",
    "sg:classifiers":[
        {
            "category":"Shopping",
            "subcategory":"Bicycles & Sporting Goods",
            "type":"Retail Goods"
        }
    ],
    "sg:phone":"+1 360 874 2460",
    "sg:postcode":"98366",
    "sg:province":"WA",
    "wof:name":"Paradise Paintball",
    "wof:placetype":"venue"
},
  "geometry": {"coordinates":[-122.608682,47.519324],"type":"Point"}
}