{
  "type": "Feature",
  "properties": {
    "addr:full":"999 N Northlake Way Seattle WA 98103",
    "addr:housenumber":"999",
    "addr:postcode":"98103",
    "addr:street":"N Northlake Way",
    "iso:country":"US",
    "sg:address":"999 N Northlake Way",
    "sg:city":"Seattle",
    "sg:classifiers":[
        {
            "category":"Utilities",
            "subcategory":"Telephone",
            "type":"Services"
        }
    ],
    "sg:phone":"+1 206 926 2900",
    "sg:postcode":"98103",
    "sg:province":"WA",
    "sg:tags":[
        "communications",
        "retrieval",
        "information"
    ],
    "wof:name":"Westsidecom Inc",
    "wof:placetype":"venue"
},
  "geometry": {"coordinates":[-122.343898,47.648265],"type":"Point"}
}