{
  "type": "Feature",
  "properties": {
    "addr:full":"2715 S Jackson St Seattle WA 98144",
    "addr:housenumber":"2715",
    "addr:postcode":"98144",
    "addr:street":"S Jackson St",
    "iso:country":"US",
    "sg:address":"2715 S Jackson St",
    "sg:city":"Seattle",
    "sg:classifiers":[
        {
            "category":"Place Of Worship",
            "type":"Public Place"
        },
        {
            "category":"Organizations",
            "subcategory":"Religious Organization",
            "type":"Services"
        }
    ],
    "sg:phone":"+1 206 324 2771",
    "sg:postcode":"98144",
    "sg:province":"WA",
    "sg:tags":[
        "church"
    ],
    "wof:name":"Church Of God Evangelistic Center",
    "wof:placetype":"venue"
},
  "geometry": {"coordinates":[-122.297268,47.599234],"type":"Point"}
}