{
  "type": "Feature",
  "properties": {
    "addr:full":"401 E McLoughlin Blvd Vancouver WA 98663",
    "addr:housenumber":"401",
    "addr:postcode":"98663",
    "addr:street":"E Mcloughlin Blvd",
    "iso:country":"US",
    "sg:address":"401 E McLoughlin Blvd",
    "sg:city":"Vancouver",
    "sg:classifiers":[
        {
            "category":"Professional",
            "subcategory":"Lawyer & Legal Services",
            "type":"Services"
        }
    ],
    "sg:phone":"+1 360 699 1321",
    "sg:postcode":"98663",
    "sg:province":"WA",
    "sg:tags":[
        "divorce",
        "law",
        "family"
    ],
    "wof:name":"Feulner Karen E Atty",
    "wof:placetype":"venue"
},
  "geometry": {"coordinates":[-122.66799899999999,45.634998],"type":"Point"}
}