{
  "type": "Feature",
  "properties": {
    "addr:full":"14410 158th Pl SE Renton WA 98059",
    "addr:housenumber":"14410",
    "addr:postcode":"98059",
    "addr:street":"158Th Pl Se",
    "iso:country":"US",
    "sg:address":"14410 158th Pl SE",
    "sg:city":"Renton",
    "sg:classifiers":[
        {
            "category":"Professional",
            "subcategory":"Business Services",
            "type":"Services"
        }
    ],
    "sg:phone":"+1 425 255 0219",
    "sg:postcode":"98059",
    "sg:province":"WA",
    "wof:name":"Kp Enterprises",
    "wof:placetype":"venue"
},
  "geometry": {"coordinates":[-122.128828,47.472533],"type":"Point"}
}