{
  "type": "Feature",
  "properties": {
    "addr:full":"5926 Sehmel Dr NW Gig Harbor WA 98332",
    "addr:housenumber":"5926",
    "addr:postcode":"98332",
    "addr:street":"Sehmel Dr Nw",
    "iso:country":"US",
    "sg:address":"5926 Sehmel Dr NW",
    "sg:city":"Gig Harbor",
    "sg:classifiers":[
        {
            "category":"Manufacturing",
            "subcategory":"Wood Products",
            "type":"Manufacturing & Wholesale Goods"
        }
    ],
    "sg:phone":"+1 253 858 1075",
    "sg:postcode":"98332",
    "sg:province":"WA",
    "sg:tags":[
        "pallet",
        "skid"
    ],
    "wof:name":"Wollochet Bay Co Nw",
    "wof:placetype":"venue"
},
  "geometry": {"coordinates":[-122.616449,47.35621],"type":"Point"}
}