{
  "type": "Feature",
  "properties": {
    "addr:full":"1906 Academy St Wenatchee WA 98801",
    "addr:housenumber":"1906",
    "addr:postcode":"98801",
    "addr:street":"Academy St",
    "iso:country":"US",
    "sg:address":"1906 Academy St",
    "sg:city":"Wenatchee",
    "sg:classifiers":[
        {
            "category":"Social Services",
            "subcategory":"Child Care",
            "type":"Services"
        }
    ],
    "sg:phone":"+1 509 662 3573",
    "sg:postcode":"98801",
    "sg:province":"WA",
    "wof:name":"Cascade Christian Academy",
    "wof:placetype":"venue"
},
  "geometry": {"coordinates":[-120.347284,47.431303],"type":"Point"}
}