{
  "type": "Feature",
  "properties": {
    "addr:full":"508 W 1st Ave Spokane WA 99201",
    "addr:housenumber":"508",
    "addr:postcode":"99201",
    "addr:street":"W 1St Ave",
    "iso:country":"US",
    "sg:address":"508 W 1st Ave",
    "sg:city":"Spokane",
    "sg:classifiers":[
        {
            "category":"Personal",
            "subcategory":"Beauty Salon",
            "type":"Services"
        }
    ],
    "sg:phone":"+1 509 624 5350",
    "sg:postcode":"99201",
    "sg:province":"WA",
    "wof:name":"First Avenue Salon",
    "wof:placetype":"venue"
},
  "geometry": {"coordinates":[-117.42098,47.656653],"type":"Point"}
}