{
  "type": "Feature",
  "properties": {
    "addr:full":"5714 62nd St NW Gig Harbor WA 98335",
    "addr:housenumber":"5714",
    "addr:postcode":"98335",
    "addr:street":"62Nd St Nw",
    "iso:country":"US",
    "sg:address":"5714 62nd St NW",
    "sg:city":"Gig Harbor",
    "sg:classifiers":[
        {
            "category":"Building & Trades",
            "subcategory":"Construction",
            "type":"Services"
        }
    ],
    "sg:phone":"+1 253 851 3743",
    "sg:postcode":"98335",
    "sg:province":"WA",
    "sg:tags":[
        "contractor"
    ],
    "wof:name":"Becker Construction",
    "wof:placetype":"venue"
},
  "geometry": {"coordinates":[-122.613501,47.313301],"type":"Point"}
}