{
  "type": "Feature",
  "properties": {
    "addr:full":"6046 50th Ave SW Seattle WA 98136",
    "addr:housenumber":"6046",
    "addr:postcode":"98136",
    "addr:street":"50Th Ave Sw",
    "iso:country":"US",
    "sg:address":"6046 50th Ave SW",
    "sg:city":"Seattle",
    "sg:classifiers":[
        {
            "category":"Building & Trades",
            "subcategory":"Landscaping Services",
            "type":"Services"
        }
    ],
    "sg:phone":"+1 425 533 9569",
    "sg:postcode":"98136",
    "sg:province":"WA",
    "wof:name":"Bear Creek Landscapes, LLC",
    "wof:placetype":"venue"
},
  "geometry": {"coordinates":[-122.395574,47.547676],"type":"Point"}
}