{
  "type": "Feature",
  "properties": {
    "addr:full":"1017 W Sylvester St Pasco WA 99301",
    "addr:housenumber":"1017",
    "addr:postcode":"99301",
    "addr:street":"W Sylvester St",
    "iso:country":"US",
    "sg:address":"1017 W Sylvester St",
    "sg:city":"Pasco",
    "sg:classifiers":[
        {
            "category":"Personal",
            "subcategory":"Beauty Salon",
            "type":"Services"
        }
    ],
    "sg:phone":"+1 509 543 9749",
    "sg:postcode":"99301",
    "sg:province":"WA",
    "wof:name":"Imy's Hair Salon",
    "wof:placetype":"venue"
},
  "geometry": {"coordinates":[-119.104806,46.234121],"type":"Point"}
}