{
  "type": "Feature",
  "properties": {
    "iso:country":"US",
    "sg:address":"5552 Campbell Rd",
    "sg:city":"Peshastin",
    "sg:classifiers":[
        {
            "category":"Professional",
            "subcategory":"Art Services",
            "type":"Services"
        }
    ],
    "sg:phone":"+1 509 548 5779",
    "sg:postcode":"98847",
    "sg:province":"WA",
    "sg:tags":[
        "commercial",
        "design"
    ],
    "wof:name":"Goat Mountain Productions",
    "wof:placetype":"venue"
},
  "geometry": {"coordinates":[-120.627385,47.521718],"type":"Point"}
}