{
  "type": "Feature",
  "properties": {
    "addr:full":"6220 Central Park Dr Aberdeen WA 98520",
    "addr:housenumber":"6220",
    "addr:postcode":"98520",
    "addr:street":"Central Park Dr",
    "iso:country":"US",
    "sg:address":"6220 Central Park Dr",
    "sg:city":"Aberdeen",
    "sg:classifiers":[
        {
            "category":"Health Services",
            "subcategory":"Health Practitioner",
            "type":"Services"
        }
    ],
    "sg:phone":"+1 360 533 3082",
    "sg:postcode":"98520",
    "sg:province":"WA",
    "wof:name":"Laurie Connolly-Niels",
    "wof:placetype":"venue"
},
  "geometry": {"coordinates":[-123.705687,46.964388],"type":"Point"}
}