{
  "type": "Feature",
  "properties": {
    "addr:full":"244 Klahhane Rd Sequim WA 98382",
    "addr:housenumber":"244",
    "addr:postcode":"98382",
    "addr:street":"Klahhane Rd",
    "iso:country":"US",
    "sg:address":"244 Klahhane Rd",
    "sg:city":"Sequim",
    "sg:classifiers":[
        {
            "category":"Farming",
            "subcategory":"Farm & Veterinary Services",
            "type":"Manufacturing & Wholesale Goods"
        }
    ],
    "sg:phone":"+1 360 681 7308",
    "sg:postcode":"98382",
    "sg:province":"WA",
    "sg:tags":[
        "crop"
    ],
    "wof:name":"Blue Heaven Farm",
    "wof:placetype":"venue"
},
  "geometry": {"coordinates":[-123.19475300000001,48.123988],"type":"Point"}
}