{
  "type": "Feature",
  "properties": {
    "iso:country":"US",
    "sg:address":"17223 116th Ave SE",
    "sg:city":"Renton",
    "sg:classifiers":[
        {
            "category":"Personal",
            "subcategory":"Beauty Salon",
            "type":"Services"
        }
    ],
    "sg:phone":"+1 425 255 4499",
    "sg:postcode":"98058",
    "sg:province":"WA",
    "sg:tags":[
        "shop"
    ],
    "wof:name":"Loughlins Hair",
    "wof:placetype":"venue"
},
  "geometry": {"coordinates":[-122.186198,47.448753],"type":"Point"}
}