{
  "type": "Feature",
  "properties": {
    "addr:full":"5305 Evergreen Way Everett WA 98203",
    "addr:housenumber":"5305",
    "addr:postcode":"98203",
    "addr:street":"Evergreen Way",
    "iso:country":"US",
    "sg:address":"5305 Evergreen Way",
    "sg:city":"Everett",
    "sg:classifiers":[
        {
            "category":"Wholesale",
            "subcategory":"Computers",
            "type":"Manufacturing & Wholesale Goods"
        }
    ],
    "sg:phone":"+1 425 346 6057",
    "sg:postcode":"98203",
    "sg:province":"WA",
    "wof:name":"Barcode Resale",
    "wof:placetype":"venue"
},
  "geometry": {"coordinates":[-122.21535299999999,47.947481],"type":"Point"}
}