{
  "type": "Feature",
  "properties": {
    "addr:full":"1228 121st Ave SE Lake Stevens WA 98258",
    "addr:housenumber":"1228",
    "addr:postcode":"98258",
    "addr:street":"121St Ave Se",
    "iso:country":"US",
    "sg:address":"1228 121st Ave SE",
    "sg:city":"Lake Stevens",
    "sg:classifiers":[
        {
            "category":"Professional",
            "subcategory":"Business Services",
            "type":"Services"
        }
    ],
    "sg:phone":"+1 425 377 9127",
    "sg:postcode":"98258",
    "sg:province":"WA",
    "sg:tags":[
        "information",
        "referral"
    ],
    "wof:name":"Information Resources Inc",
    "wof:placetype":"venue"
},
  "geometry": {"coordinates":[-122.06904400000001,47.984903],"type":"Point"}
}