{
  "type": "Feature",
  "properties": {
    "addr:full":"3770 SW Grayson St Seattle WA 98126",
    "addr:housenumber":"3770",
    "addr:postcode":"98126",
    "addr:street":"Sw Grayson St",
    "iso:country":"US",
    "sg:address":"3770 SW Grayson St",
    "sg:city":"Seattle",
    "sg:classifiers":[
        {
            "category":"Professional",
            "subcategory":"Art Services",
            "type":"Services"
        }
    ],
    "sg:phone":"+1 206 937 9011",
    "sg:postcode":"98126",
    "sg:province":"WA",
    "sg:tags":[
        "designer",
        "display",
        "producer"
    ],
    "wof:name":"Jeff Larson Design",
    "wof:placetype":"venue"
},
  "geometry": {"coordinates":[-122.379908,47.581847],"type":"Point"}
}