{
  "type": "Feature",
  "properties": {
    "addr:full":"10052 136th Ave NE Kirkland WA 98033",
    "addr:housenumber":"10052",
    "addr:postcode":"98033",
    "addr:street":"136Th Ave Ne",
    "iso:country":"US",
    "sg:address":"10052 136th Ave NE",
    "sg:city":"Kirkland",
    "sg:classifiers":[
        {
            "category":"Building & Trades",
            "subcategory":"Construction",
            "type":"Services"
        }
    ],
    "sg:phone":"+1 425 803 3875",
    "sg:postcode":"98033",
    "sg:province":"WA",
    "sg:tags":[
        "contractor"
    ],
    "sg:website":"www.grburgess.com",
    "wof:name":"Gr Burgess Co",
    "wof:placetype":"venue"
},
  "geometry": {"coordinates":[-122.160004,47.690201],"type":"Point"}
}