{
  "type": "Feature",
  "properties": {
    "addr:full":"11232 120th Ave NE Ste 105 Kirkland WA 98033",
    "addr:housenumber":"11232",
    "addr:postcode":"98033",
    "addr:street":"120Th Ave Ne Ste 105",
    "iso:country":"US",
    "sg:address":"11232 120th Ave NE Ste 105",
    "sg:city":"Kirkland",
    "sg:classifiers":[
        {
            "category":"Arena",
            "subcategory":"Sports Club",
            "type":"Entertainment"
        }
    ],
    "sg:phone":"+1 425 213 9152",
    "sg:postcode":"98033",
    "sg:province":"WA",
    "sg:tags":[
        "martial art"
    ],
    "sg:website":"www.eastsidekyokushin.com",
    "wof:name":"Eastside Kyokushin",
    "wof:placetype":"venue"
},
  "geometry": {"coordinates":[-122.18116000000001,47.700831],"type":"Point"}
}