{
  "type": "Feature",
  "properties": {
    "addr:full":"5930 Silvana Terrace Rd Stanwood WA 98292",
    "addr:housenumber":"5930",
    "addr:postcode":"98292",
    "addr:street":"Silvana Terrace Rd",
    "iso:country":"US",
    "sg:address":"5930 Silvana Terrace Rd",
    "sg:city":"Stanwood",
    "sg:classifiers":[
        {
            "category":"Professional",
            "subcategory":"Art Services",
            "type":"Services"
        }
    ],
    "sg:phone":"+1 360 652 1861",
    "sg:postcode":"98292",
    "sg:province":"WA",
    "sg:tags":[
        "photography",
        "commercial"
    ],
    "wof:name":"Carol Marie Charlson",
    "wof:placetype":"venue"
},
  "geometry": {"coordinates":[-122.31231099999999,48.201683],"type":"Point"}
}