{
  "type": "Feature",
  "properties": {
    "addr:full":"6047 38th Ave NE Seattle WA 98115",
    "addr:housenumber":"6047",
    "addr:postcode":"98115",
    "addr:street":"38Th Ave Ne",
    "iso:country":"US",
    "sg:address":"6047 38th Ave NE",
    "sg:city":"Seattle",
    "sg:classifiers":[
        {
            "category":"Manufacturing",
            "subcategory":"Paper Products",
            "type":"Manufacturing & Wholesale Goods"
        }
    ],
    "sg:phone":"+1 206 526 5729",
    "sg:postcode":"98115",
    "sg:province":"WA",
    "sg:tags":[
        "paper-wholesale",
        "manufacturer"
    ],
    "wof:name":"Paprika Scribes",
    "wof:placetype":"venue"
},
  "geometry": {"coordinates":[-122.286902,47.67301],"type":"Point"}
}