{
  "type": "Feature",
  "properties": {
    "addr:full":"5610 N E St Spokane WA 99205",
    "addr:housenumber":"5610",
    "addr:postcode":"99205",
    "addr:street":"N E St",
    "iso:country":"US",
    "sg:address":"5610 N E St",
    "sg:city":"Spokane",
    "sg:classifiers":[
        {
            "category":"Professional",
            "type":"Services"
        }
    ],
    "sg:phone":"+1 509 328 7621",
    "sg:postcode":"99205",
    "sg:province":"WA",
    "wof:name":"Jesse Harwood",
    "wof:placetype":"venue"
},
  "geometry": {"coordinates":[-117.458259,47.710575],"type":"Point"}
}