{
  "type": "Feature",
  "properties": {
    "addr:full":"9112 46th Pl W Mukilteo WA 98275",
    "addr:housenumber":"9112",
    "addr:postcode":"98275",
    "addr:street":"46Th Pl W",
    "iso:country":"US",
    "sg:address":"9112 46th Pl W",
    "sg:city":"Mukilteo",
    "sg:classifiers":[
        {
            "category":"Manufacturing",
            "subcategory":"Jewelry",
            "type":"Manufacturing & Wholesale Goods"
        }
    ],
    "sg:phone":"+1 425 348 6620",
    "sg:postcode":"98275",
    "sg:province":"WA",
    "sg:tags":[
        "costume",
        "mfg"
    ],
    "wof:name":"Galglass",
    "wof:placetype":"venue"
},
  "geometry": {"coordinates":[-122.29675400000001,47.915559],"type":"Point"}
}