{
  "type": "Feature",
  "properties": {
    "iso:country":"US",
    "sg:address":"4011 Talbot Rd S",
    "sg:city":"Renton",
    "sg:classifiers":[
        {
            "category":"Health Services",
            "subcategory":"Doctor",
            "type":"Services"
        }
    ],
    "sg:phone":"+1 425 251 3455",
    "sg:postcode":"98055",
    "sg:province":"WA",
    "sg:tags":[
        "urologist"
    ],
    "wof:name":"Dr McKay Hunter",
    "wof:placetype":"venue"
},
  "geometry": {"coordinates":[-122.212345,47.442086],"type":"Point"}
}