{
  "type": "Feature",
  "properties": {
    "addr:full":"550 NE Northgate Way Seattle WA 98125",
    "addr:housenumber":"550",
    "addr:postcode":"98125",
    "addr:street":"Ne Northgate Way",
    "iso:country":"US",
    "sg:address":"550 NE Northgate Way",
    "sg:city":"Seattle",
    "sg:classifiers":[
        {
            "category":"Shopping",
            "subcategory":"Jewelry",
            "type":"Retail Goods"
        }
    ],
    "sg:phone":"+1 206 527 1108",
    "sg:postcode":"98125",
    "sg:province":"WA",
    "sg:website":"www.greenlakejewelry.com",
    "wof:name":"Green Lake Jewelry Works",
    "wof:placetype":"venue"
},
  "geometry": {"coordinates":[-122.32199900000001,47.708698],"type":"Point"}
}