{
  "type": "Feature",
  "properties": {
    "addr:full":"10130 NE 111th Pl Kirkland WA 98033",
    "addr:housenumber":"10130",
    "addr:postcode":"98033",
    "addr:street":"Ne 111Th Pl",
    "iso:country":"US",
    "sg:address":"10130 NE 111th Pl",
    "sg:city":"Kirkland",
    "sg:classifiers":[
        {
            "category":"Retail",
            "subcategory":"Photofinishing",
            "type":"Services"
        },
        {
            "category":"Professional",
            "subcategory":"Printing & Photocopies",
            "type":"Services"
        }
    ],
    "sg:phone":"+1 425 827 7462",
    "sg:postcode":"98033",
    "sg:province":"WA",
    "sg:tags":[
        "laboratory",
        "laboratories-commercial",
        "finishing-custom",
        "photo"
    ],
    "wof:name":"Snapshots To Art",
    "wof:placetype":"venue"
},
  "geometry": {"coordinates":[-122.19187100000001,47.690451],"type":"Point"}
}