{
  "type": "Feature",
  "properties": {
    "addr:full":"1923 205th St SW Lynnwood WA 98036",
    "addr:housenumber":"1923",
    "addr:postcode":"98036",
    "addr:street":"205Th St Sw",
    "iso:country":"US",
    "sg:address":"1923 205th St SW",
    "sg:city":"Lynnwood",
    "sg:classifiers":[
        {
            "category":"Communications",
            "subcategory":"Film & Video Production",
            "type":"Services"
        }
    ],
    "sg:phone":"+1 425 672 2772",
    "sg:postcode":"98036",
    "sg:province":"WA",
    "sg:tags":[
        "motion"
    ],
    "wof:name":"Snapdragon Video Productions",
    "wof:placetype":"venue"
},
  "geometry": {"coordinates":[-122.25949199999999,47.812695],"type":"Point"}
}