{
  "type": "Feature",
  "properties": {
    "addr:full":"Crossroads Mall 15600 NE 8th St Bellevue WA 98008",
    "addr:housenumber":"15600",
    "addr:postcode":"98008",
    "addr:street":"Ne 8Th St",
    "iso:country":"US",
    "sg:address":"Crossroads Mall 15600 NE 8th St",
    "sg:city":"Bellevue",
    "sg:classifiers":[
        {
            "category":"Banks & Credit Unions",
            "subcategory":"Investment Brokerage",
            "type":"Services"
        },
        {
            "category":"Shopping",
            "subcategory":"Music",
            "type":"Retail Goods"
        },
        {
            "category":"Shopping",
            "subcategory":"Computers & Home Electronics",
            "type":"Retail Goods"
        }
    ],
    "sg:phone":"+1 425 643 3472",
    "sg:postcode":"98008",
    "sg:province":"WA",
    "sg:tags":[
        "dvd",
        "sale",
        "dvds-rental",
        "video",
        "tape",
        "dvd's",
        "store"
    ],
    "sg:website":"www.silverplatters.com",
    "wof:name":"Silver Platters",
    "wof:placetype":"venue"
},
  "geometry": {"coordinates":[-122.13242099999999,47.617033],"type":"Point"}
}