{
  "type": "Feature",
  "properties": {
    "addr:full":"1605 Tartan Pl Anacortes WA 98221",
    "addr:housenumber":"1605",
    "addr:postcode":"98221",
    "addr:street":"Tartan Pl",
    "iso:country":"US",
    "sg:address":"1605 Tartan Pl",
    "sg:city":"Anacortes",
    "sg:classifiers":[
        {
            "category":"Wholesale",
            "subcategory":"Construction Materials",
            "type":"Manufacturing & Wholesale Goods"
        }
    ],
    "sg:phone":"+1 360 293 2092",
    "sg:postcode":"98221",
    "sg:province":"WA",
    "sg:tags":[
        "export"
    ],
    "wof:name":"Mky Corp",
    "wof:placetype":"venue"
},
  "geometry": {"coordinates":[-122.67345899999999,48.498454],"type":"Point"}
}