{
  "type": "Feature",
  "properties": {
    "addr:full":"1353 Van Dyk Rd Lynden WA 98264",
    "addr:housenumber":"1353",
    "addr:postcode":"98264",
    "addr:street":"Van Dyk Rd",
    "iso:country":"US",
    "sg:address":"1353 Van Dyk Rd",
    "sg:city":"Lynden",
    "sg:classifiers":[
        {
            "category":"Freight",
            "type":"Transportation"
        }
    ],
    "sg:phone":"+1 360 354 2105",
    "sg:postcode":"98264",
    "sg:province":"WA",
    "sg:tags":[
        "operator",
        "local",
        "trucking"
    ],
    "wof:name":"Doug Crabtree Trucking",
    "wof:placetype":"venue"
},
  "geometry": {"coordinates":[-122.416501,48.913131],"type":"Point"}
}