{
  "type": "Feature",
  "properties": {
    "addr:full":"3815 Columbia St Vancouver WA 98660",
    "addr:housenumber":"3815",
    "addr:postcode":"98660",
    "addr:street":"Columbia St",
    "iso:country":"US",
    "sg:address":"3815 Columbia St",
    "sg:city":"Vancouver",
    "sg:classifiers":[
        {
            "category":"Food & Beverages",
            "subcategory":"Groceries & Convenience Stores",
            "type":"Retail Goods"
        }
    ],
    "sg:phone":"+1 360 693 2261",
    "sg:postcode":"98660",
    "sg:province":"WA",
    "wof:name":"Vancouver Food Mart",
    "wof:placetype":"venue"
},
  "geometry": {"coordinates":[-122.673402,45.649861],"type":"Point"}
}