{
  "type": "Feature",
  "properties": {
    "addr:full":"100 Pine St Kelso WA 98626",
    "addr:housenumber":"100",
    "addr:postcode":"98626",
    "addr:street":"Pine St",
    "iso:country":"US",
    "sg:address":"100 Pine St",
    "sg:city":"Kelso",
    "sg:classifiers":[
        {
            "category":"Bars & Pubs",
            "type":"Food & Drink"
        }
    ],
    "sg:phone":"+1 360 577 9993",
    "sg:postcode":"98626",
    "sg:province":"WA",
    "sg:tags":[
        "drinking"
    ],
    "wof:name":"Maltese Tavern",
    "wof:placetype":"venue"
},
  "geometry": {"coordinates":[-122.91204,46.142886],"type":"Point"}
}