{
  "type": "Feature",
  "properties": {
    "addr:full":"612 NE 81st St Vancouver WA 98665",
    "addr:housenumber":"612",
    "addr:postcode":"98665",
    "addr:street":"Ne 81St St",
    "iso:country":"US",
    "sg:address":"612 NE 81st St",
    "sg:city":"Vancouver",
    "sg:classifiers":[
        {
            "category":"Shopping",
            "subcategory":"Clothing, Apparel, & Fashions",
            "type":"Retail Goods"
        }
    ],
    "sg:phone":"+1 360 576 8827",
    "sg:postcode":"98665",
    "sg:province":"WA",
    "sg:tags":[
        "family"
    ],
    "wof:name":"Ross Dress For Less",
    "wof:placetype":"venue"
},
  "geometry": {"coordinates":[-122.66597899999999,45.680818],"type":"Point"}
}