{
  "type": "Feature",
  "properties": {
    "addr:full":"14011 NE 20th Ave Vancouver WA 98686",
    "addr:housenumber":"14011",
    "addr:postcode":"98686",
    "addr:street":"Ne 20Th Ave",
    "iso:country":"US",
    "sg:address":"14011 NE 20th Ave",
    "sg:city":"Vancouver",
    "sg:classifiers":[
        {
            "category":"Organizations",
            "subcategory":"Community Association",
            "type":"Services"
        }
    ],
    "sg:phone":"+1 360 573 2331",
    "sg:postcode":"98686",
    "sg:province":"WA",
    "wof:name":"American Legion Salmon Creek",
    "wof:placetype":"venue"
},
  "geometry": {"coordinates":[-122.65127200000001,45.724681],"type":"Point"}
}