{
  "type": "Feature",
  "properties": {
    "addr:full":"4914 SW Stevens St Seattle WA 98116",
    "addr:housenumber":"4914",
    "addr:postcode":"98116",
    "addr:street":"Sw Stevens St",
    "iso:country":"US",
    "sg:address":"4914 SW Stevens St",
    "sg:city":"Seattle",
    "sg:classifiers":[
        {
            "category":"Freight",
            "type":"Transportation"
        }
    ],
    "sg:phone":"+1 206 935 1431",
    "sg:postcode":"98116",
    "sg:province":"WA",
    "sg:tags":[
        "operator",
        "local",
        "trucking"
    ],
    "wof:name":"Gosal Trucking Ltd",
    "wof:placetype":"venue"
},
  "geometry": {"coordinates":[-122.39529400000001,47.577612],"type":"Point"}
}