{
  "type": "Feature",
  "properties": {
    "addr:full":"1517 SW 104th Street Seattle WA 98146",
    "addr:housenumber":"1517",
    "addr:postcode":"98146",
    "addr:street":"Sw 104Th Street",
    "iso:country":"US",
    "sg:address":"1517 SW 104th Street",
    "sg:city":"Seattle",
    "sg:classifiers":[
        {
            "category":"Building & Trades",
            "subcategory":"Locksmith",
            "type":"Services"
        }
    ],
    "sg:phone":"+1 425 939 6706",
    "sg:postcode":"98146",
    "sg:province":"WA",
    "sg:tags":[
        "key"
    ],
    "wof:name":"Locksmith 24 Hours",
    "wof:placetype":"venue"
},
  "geometry": {"coordinates":[-122.35505499999999,47.509958],"type":"Point"}
}