{
  "type": "Feature",
  "properties": {
    "addr:full":"10203 NE 29th Pl Bellevue WA 98004",
    "addr:housenumber":"10203",
    "addr:postcode":"98004",
    "addr:street":"Ne 29Th Pl",
    "iso:country":"US",
    "sg:address":"10203 NE 29th Pl",
    "sg:city":"Bellevue",
    "sg:classifiers":[
        {
            "category":"Professional",
            "subcategory":"Lawyer & Legal Services",
            "type":"Services"
        }
    ],
    "sg:phone":"+1 425 822 9735",
    "sg:postcode":"98004",
    "sg:province":"WA",
    "sg:tags":[
        "consulting"
    ],
    "wof:name":"James Miles",
    "wof:placetype":"venue"
},
  "geometry": {"coordinates":[-122.20502500000001,47.636907],"type":"Point"}
}