{
  "type": "Feature",
  "properties": {
    "addr:full":"714 W Cooper Montesano WA 98563",
    "addr:housenumber":"714",
    "addr:postcode":"98563",
    "addr:street":"W Cooper Montesano",
    "iso:country":"US",
    "sg:address":"714 W Cooper",
    "sg:city":"Montesano",
    "sg:classifiers":[
        {
            "category":"Banks & Credit Unions",
            "subcategory":"Financial Services",
            "type":"Services"
        }
    ],
    "sg:phone":"+1 360 249 5380",
    "sg:postcode":"98563",
    "sg:province":"WA",
    "sg:tags":[
        "investment",
        "closed"
    ],
    "wof:name":"P&L Investment Club",
    "wof:placetype":"venue"
},
  "geometry": {"coordinates":[-123.610884,46.979518],"type":"Point"}
}