{
  "type": "Feature",
  "properties": {
    "addr:full":"224 N G St Tacoma WA 98403",
    "addr:housenumber":"224",
    "addr:postcode":"98403",
    "addr:street":"N G St",
    "iso:country":"US",
    "sg:address":"224 N G St",
    "sg:city":"Tacoma",
    "sg:classifiers":[
        {
            "category":"Education",
            "subcategory":"Special Training",
            "type":"Public Place"
        }
    ],
    "sg:phone":"+1 253 272 2149",
    "sg:postcode":"98403",
    "sg:province":"WA",
    "wof:name":"Ruben Watson Music Studio",
    "wof:placetype":"venue"
},
  "geometry": {"coordinates":[-122.45166399999999,47.264405],"type":"Point"}
}