{
  "type": "Feature",
  "properties": {
    "addr:full":"16901 SE 144th St Renton WA 98059",
    "addr:postcode":"16901;98059",
    "addr:street":"Se 144Th St",
    "iso:country":"US",
    "sg:address":"16901 SE 144th St",
    "sg:city":"Renton",
    "sg:classifiers":[
        {
            "category":"Professional",
            "subcategory":"Computer Services",
            "type":"Services"
        }
    ],
    "sg:phone":"+1 425 235 0978",
    "sg:postcode":"98059",
    "sg:province":"WA",
    "sg:tags":[
        "related"
    ],
    "wof:name":"Terry G Woodland",
    "wof:placetype":"venue"
},
  "geometry": {"coordinates":[-122.112594,47.473504],"type":"Point"}
}