{
  "type": "Feature",
  "properties": {
    "addr:full":"1002 21st St SE Puyallup WA 98372",
    "addr:housenumber":"1002",
    "addr:postcode":"98372",
    "addr:street":"21St St Se",
    "iso:country":"US",
    "sg:address":"1002 21st St SE",
    "sg:city":"Puyallup",
    "sg:classifiers":[
        {
            "category":"Taxi",
            "type":"Transportation"
        }
    ],
    "sg:phone":"+1 253 848 1838",
    "sg:postcode":"98372",
    "sg:province":"WA",
    "sg:tags":[
        "taxicab"
    ],
    "wof:name":"Willis Enterprise Co",
    "wof:placetype":"venue"
},
  "geometry": {"coordinates":[-122.266891,47.183492],"type":"Point"}
}