{
  "type": "Feature",
  "properties": {
    "addr:full":"203 N Huntington St Kennewick WA 99336",
    "addr:housenumber":"203",
    "addr:postcode":"99336",
    "addr:street":"N Huntington St",
    "iso:country":"US",
    "sg:address":"203 N Huntington St",
    "sg:city":"Kennewick",
    "sg:classifiers":[
        {
            "category":"Food & Beverages",
            "subcategory":"Groceries & Convenience Stores",
            "type":"Retail Goods"
        }
    ],
    "sg:phone":"+1 509 734 7925",
    "sg:postcode":"99336",
    "sg:province":"WA",
    "sg:tags":[
        "market"
    ],
    "wof:name":"Euro Market",
    "wof:placetype":"venue"
},
  "geometry": {"coordinates":[-119.162353,46.210415],"type":"Point"}
}