{
  "type": "Feature",
  "properties": {
    "iso:country":"US",
    "sg:address":"16275 NE 85th St",
    "sg:city":"Redmond",
    "sg:classifiers":[
        {
            "category":"Building & Trades",
            "subcategory":"Cleaning & Sanitation",
            "type":"Services"
        }
    ],
    "sg:phone":"+1 425 821 9435",
    "sg:postcode":"98052",
    "sg:province":"WA",
    "sg:tags":[
        "maintenance"
    ],
    "wof:name":"Jls Enterprises",
    "wof:placetype":"venue"
},
  "geometry": {"coordinates":[-122.125207,47.67844],"type":"Point"}
}