{
  "type": "Feature",
  "properties": {
    "addr:full":"11515 Canyon Rd E Puyallup WA 98373",
    "addr:housenumber":"11515",
    "addr:postcode":"98373",
    "addr:street":"Canyon Rd E",
    "iso:country":"US",
    "sg:address":"11515 Canyon Rd E",
    "sg:city":"Puyallup",
    "sg:classifiers":[
        {
            "category":"Real Estate",
            "subcategory":"Real Estate Agent",
            "type":"Services"
        }
    ],
    "sg:phone":"+1 253 878 1001",
    "sg:postcode":"98373",
    "sg:province":"WA",
    "wof:name":"Greg A Christopher",
    "wof:placetype":"venue"
},
  "geometry": {"coordinates":[-122.35720499999999,47.154336],"type":"Point"}
}