{
  "type": "Feature",
  "properties": {
    "iso:country":"US",
    "sg:address":"1415 S 261st St",
    "sg:city":"Seattle",
    "sg:classifiers":[
        {
            "category":"Building & Trades",
            "subcategory":"Cleaning & Sanitation",
            "type":"Services"
        }
    ],
    "sg:phone":"+1 206 941 6080",
    "sg:postcode":"98198",
    "sg:province":"WA",
    "sg:tags":[
        "maintenance"
    ],
    "wof:name":"Mobile Maintenance Servic",
    "wof:placetype":"venue"
},
  "geometry": {"coordinates":[-122.31482800000001,47.367696],"type":"Point"}
}