{
  "type": "Feature",
  "properties": {
    "addr:full":"61 W Delight Park Rd Shelton WA 98584",
    "addr:housenumber":"61",
    "addr:postcode":"98584",
    "addr:street":"W Delight Park Rd",
    "iso:country":"US",
    "sg:address":"61 W Delight Park Rd",
    "sg:city":"Shelton",
    "sg:classifiers":[
        {
            "category":"Building & Trades",
            "subcategory":"Cleaning & Sanitation",
            "type":"Services"
        }
    ],
    "sg:phone":"+1 360 427 7377",
    "sg:postcode":"98584",
    "sg:province":"WA",
    "sg:tags":[
        "maintenance"
    ],
    "wof:name":"Mrb Janitorial Services",
    "wof:placetype":"venue"
},
  "geometry": {"coordinates":[-123.09722600000001,47.168257],"type":"Point"}
}