{
  "type": "Feature",
  "properties": {
    "addr:full":"835 N Waldemar Ave Pasco WA 99301",
    "addr:housenumber":"835",
    "addr:postcode":"99301",
    "addr:street":"N Waldemar Ave",
    "iso:country":"US",
    "sg:address":"835 N Waldemar Ave",
    "sg:city":"Pasco",
    "sg:classifiers":[
        {
            "category":"Building & Trades",
            "subcategory":"Construction",
            "type":"Services"
        }
    ],
    "sg:phone":"+1 509 373 6554",
    "sg:postcode":"99301",
    "sg:province":"WA",
    "sg:tags":[
        "nonresidential"
    ],
    "wof:name":"Trevor A Mount",
    "wof:placetype":"venue"
},
  "geometry": {"coordinates":[-119.06668500000001,46.241256],"type":"Point"}
}