{
  "type": "Feature",
  "properties": {
    "addr:full":"600 108th Ave NE Bellevue WA 98004",
    "addr:housenumber":"600",
    "addr:postcode":"98004",
    "addr:street":"108Th Ave Ne",
    "iso:country":"US",
    "sg:address":"600 108th Ave NE",
    "sg:city":"Bellevue",
    "sg:classifiers":[
        {
            "category":"Education",
            "subcategory":"Special Training",
            "type":"Public Place"
        },
        {
            "category":"Education",
            "subcategory":"Vocational School",
            "type":"Public Place"
        },
        {
            "category":"Education",
            "subcategory":"University",
            "type":"Public Place"
        },
        {
            "category":"Education",
            "subcategory":"School",
            "type":"Public Place"
        }
    ],
    "sg:phone":"+1 877 268 3879",
    "sg:postcode":"98004",
    "sg:province":"WA",
    "sg:tags":[
        "college",
        "adult",
        "business"
    ],
    "sg:website":"http://www.kelleradvantage.com/landing36/index.html?vc=167328",
    "wof:name":"Keller Graduate School of Management",
    "wof:placetype":"venue"
},
  "geometry": {"coordinates":[-122.196297,47.61552],"type":"Point"}
}