{
  "type": "Feature",
  "properties": {
    "addr:full":"3601 Lincoln Ave NE Renton WA 98056",
    "addr:housenumber":"3601",
    "addr:postcode":"98056",
    "addr:street":"Lincoln Ave Ne",
    "iso:country":"US",
    "sg:address":"3601 Lincoln Ave NE",
    "sg:city":"Renton",
    "sg:classifiers":[
        {
            "category":"Building & Trades",
            "subcategory":"Construction",
            "type":"Services"
        }
    ],
    "sg:phone":"+1 425 941 2328",
    "sg:postcode":"98056",
    "sg:province":"WA",
    "sg:tags":[
        "hanging",
        "contractor"
    ],
    "wof:name":"Faux Walls & More",
    "wof:placetype":"venue"
},
  "geometry": {"coordinates":[-122.19368,47.526306],"type":"Point"}
}