{
  "type": "Feature",
  "properties": {
    "addr:full":"1926 6th Ave S Seattle WA 98134",
    "addr:housenumber":"1926",
    "addr:postcode":"98134",
    "addr:street":"6Th Ave S",
    "iso:country":"US",
    "sg:address":"1926 6th Ave S",
    "sg:city":"Seattle",
    "sg:phone":"+1 206 462 2338",
    "sg:postcode":"98134",
    "sg:province":"WA",
    "sg:website":"http://seattle.citysearch.com/profile/external/651218720/seattle_wa/moe_s_home_seattle.html?publisher=yellowpages&reference_id=15&placement=ypwebsitemip",
    "wof:name":"Moe's Home - Seattle",
    "wof:placetype":"venue"
},
  "geometry": {"coordinates":[-122.325974,47.585922],"type":"Point"}
}