{
  "type": "Feature",
  "properties": {
    "addr:full":"1510 E Maryland St Bellingham WA 98226",
    "addr:housenumber":"1510",
    "addr:postcode":"98226",
    "addr:street":"E Maryland St",
    "iso:country":"US",
    "sg:address":"1510 E Maryland St",
    "sg:city":"Bellingham",
    "sg:classifiers":[
        {
            "category":"Building & Trades",
            "subcategory":"Construction",
            "type":"Services"
        }
    ],
    "sg:phone":"+1 360 650 1495",
    "sg:postcode":"98226",
    "sg:province":"WA",
    "sg:tags":[
        "concrete",
        "contractor"
    ],
    "wof:name":"Concrete Guy",
    "wof:placetype":"venue"
},
  "geometry": {"coordinates":[-122.453418,48.766758],"type":"Point"}
}