{
  "type": "Feature",
  "properties": {
    "iso:country":"US",
    "sg:address":"144 Railroad Ave",
    "sg:city":"Edmonds",
    "sg:classifiers":[
        {
            "category":"Personal",
            "subcategory":"Beauty Salon",
            "type":"Services"
        }
    ],
    "sg:phone":"+1 425 775 9439",
    "sg:postcode":"98020",
    "sg:province":"WA",
    "sg:tags":[
        "hair"
    ],
    "wof:name":"Tedricks Hair N Art Studio",
    "wof:placetype":"venue"
},
  "geometry": {"coordinates":[-122.384649,47.811282],"type":"Point"}
}