{
  "type": "Feature",
  "properties": {
    "addr:full":"184 S Kent Pl East Wenatchee WA 98802",
    "addr:housenumber":"184",
    "addr:postcode":"98802",
    "addr:street":"S Kent Pl",
    "iso:country":"US",
    "sg:address":"184 S Kent Pl",
    "sg:city":"East Wenatchee",
    "sg:classifiers":[
        {
            "category":"Retail",
            "subcategory":"Auto Repair",
            "type":"Services"
        }
    ],
    "sg:phone":"+1 509 884 0532",
    "sg:postcode":"98802",
    "sg:province":"WA",
    "sg:tags":[
        "body"
    ],
    "wof:name":"Maaco Auto Painting",
    "wof:placetype":"venue"
},
  "geometry": {"coordinates":[-120.26119799999999,47.40235],"type":"Point"}
}