{
  "type": "Feature",
  "properties": {
    "addr:full":"7426 Custer Rd W Lakewood WA 98499",
    "addr:housenumber":"7426",
    "addr:postcode":"98499",
    "addr:street":"Custer Rd W",
    "iso:country":"US",
    "sg:address":"7426 Custer Rd W",
    "sg:city":"Lakewood",
    "sg:classifiers":[
        {
            "category":"Retail",
            "subcategory":"Animal Services",
            "type":"Services"
        }
    ],
    "sg:phone":"+1 253 472 4047",
    "sg:postcode":"98499",
    "sg:province":"WA",
    "sg:tags":[
        "pet",
        "salon",
        "washing",
        "grooming",
        "beauty"
    ],
    "wof:name":"Shear Elegance",
    "wof:placetype":"venue"
},
  "geometry": {"coordinates":[-122.51237399999999,47.189649],"type":"Point"}
}