{
  "type": "Feature",
  "properties": {
    "addr:full":"201 E University Way Ellensburg WA 98926",
    "addr:housenumber":"201",
    "addr:postcode":"98926",
    "addr:street":"E University Way",
    "iso:country":"US",
    "sg:address":"201 E University Way",
    "sg:city":"Ellensburg",
    "sg:classifiers":[
        {
            "category":"Shopping",
            "subcategory":"Tobacco",
            "type":"Retail Goods"
        }
    ],
    "sg:phone":"+1 509 925 9054",
    "sg:postcode":"98926",
    "sg:province":"WA",
    "sg:tags":[
        "cigarette",
        "product",
        "cigar",
        "dealer"
    ],
    "wof:name":"Henry's Smokeshop II",
    "wof:placetype":"venue"
},
  "geometry": {"coordinates":[-120.54506499999999,46.999714],"type":"Point"}
}