{
  "type": "Feature",
  "properties": {
    "addr:full":"4805 E Trent Ave Spokane WA 99212",
    "addr:housenumber":"4805",
    "addr:postcode":"99212",
    "addr:street":"E Trent Ave",
    "iso:country":"US",
    "sg:address":"4805 E Trent Ave",
    "sg:city":"Spokane",
    "sg:classifiers":[
        {
            "category":"Wholesale",
            "subcategory":"Machinery & Supplies",
            "type":"Manufacturing & Wholesale Goods"
        }
    ],
    "sg:phone":"+1 509 536 7085",
    "sg:postcode":"99212",
    "sg:province":"WA",
    "sg:tags":[
        "industrial"
    ],
    "wof:name":"Northwest Hose & Fittings Inc",
    "wof:placetype":"venue"
},
  "geometry": {"coordinates":[-117.336099,47.673725],"type":"Point"}
}