{
  "type": "Feature",
  "properties": {
    "addr:full":"3702 Broadway Everett WA 98201",
    "addr:housenumber":"3702",
    "addr:postcode":"98201",
    "addr:street":"Broadway",
    "iso:country":"US",
    "sg:address":"3702 Broadway",
    "sg:city":"Everett",
    "sg:classifiers":[
        {
            "category":"Manufacturing",
            "subcategory":"Petroleum Products",
            "type":"Manufacturing & Wholesale Goods"
        }
    ],
    "sg:phone":"+1 425 252 8220",
    "sg:postcode":"98201",
    "sg:province":"WA",
    "wof:name":"Everett Petroleum",
    "wof:placetype":"venue"
},
  "geometry": {"coordinates":[-122.201151,47.967477],"type":"Point"}
}