{
  "type": "Feature",
  "properties": {
    "addr:full":"1902a S Commons Federal Way WA 98003",
    "addr:housenumber":"1902a",
    "addr:postcode":"98003",
    "addr:street":"S Commons",
    "iso:country":"US",
    "sg:address":"1902a S Commons",
    "sg:city":"Federal Way",
    "sg:classifiers":[
        {
            "category":"Bakery",
            "type":"Food & Drink"
        }
    ],
    "sg:menulink":"http://www.allmenus.com/wa/auburn/220329-auntie-annes-pretzels/menu/",
    "sg:phone":"+1 253 941 9460",
    "sg:postcode":"98003",
    "sg:province":"WA",
    "sg:tags":[
        "american",
        "pastry"
    ],
    "wof:name":"Auntie Anne's Pretzels",
    "wof:placetype":"venue"
},
  "geometry": {"coordinates":[-122.304036,47.312981],"type":"Point"}
}