{
  "type": "Feature",
  "properties": {
    "addr:full":"23916 SE Kent Kangley Rd Maple Valley WA 98038",
    "addr:postcode":"23916;98038",
    "addr:street":"Se Kent Kangley Rd",
    "iso:country":"US",
    "sg:address":"23916 SE Kent Kangley Rd",
    "sg:city":"Maple Valley",
    "sg:classifiers":[
        {
            "category":"Shopping",
            "subcategory":"Musical Instruments",
            "type":"Retail Goods"
        }
    ],
    "sg:phone":"+1 425 413 4343",
    "sg:postcode":"98038",
    "sg:province":"WA",
    "sg:tags":[
        "repair"
    ],
    "wof:name":"Music Trader",
    "wof:placetype":"venue"
},
  "geometry": {"coordinates":[-122.022256,47.361329],"type":"Point"}
}