{
  "type": "Feature",
  "properties": {
    "addr:full":"1025 1st St Wenatchee WA 98801",
    "addr:housenumber":"1025",
    "addr:postcode":"98801",
    "addr:street":"1St St",
    "iso:country":"US",
    "sg:address":"1025 1st St",
    "sg:city":"Wenatchee",
    "sg:classifiers":[
        {
            "category":"Food & Beverages",
            "subcategory":"Specialty",
            "type":"Retail Goods"
        }
    ],
    "sg:phone":"+1 509 665 8262",
    "sg:postcode":"98801",
    "sg:province":"WA",
    "wof:name":"2000 Nutrition System",
    "wof:placetype":"venue"
},
  "geometry": {"coordinates":[-120.32533599999999,47.424901],"type":"Point"}
}