{
  "type": "Feature",
  "properties": {
    "addr:full":"4309 N 35th St Tacoma WA 98407",
    "addr:housenumber":"4309",
    "addr:postcode":"98407",
    "addr:street":"N 35Th St",
    "iso:country":"US",
    "sg:address":"4309 N 35th St",
    "sg:city":"Tacoma",
    "sg:classifiers":[
        {
            "category":"Building & Trades",
            "subcategory":"Construction",
            "type":"Services"
        }
    ],
    "sg:phone":"+1 253 503 7124",
    "sg:postcode":"98407",
    "sg:province":"WA",
    "sg:tags":[
        "residential"
    ],
    "wof:name":"Terry Riley Constructions",
    "wof:placetype":"venue"
},
  "geometry": {"coordinates":[-122.496016,47.279671],"type":"Point"}
}