{
  "type": "Feature",
  "properties": {
    "addr:full":"1530 Stacy Ave Prosser WA 99350",
    "addr:housenumber":"1530",
    "addr:postcode":"99350",
    "addr:street":"Stacy Ave",
    "iso:country":"US",
    "sg:address":"1530 Stacy Ave",
    "sg:city":"Prosser",
    "sg:classifiers":[
        {
            "category":"Retail",
            "subcategory":"Repair Shop",
            "type":"Services"
        }
    ],
    "sg:phone":"+1 509 786 0400",
    "sg:postcode":"99350",
    "sg:province":"WA",
    "sg:tags":[
        "welding"
    ],
    "wof:name":"Tri State Machinery",
    "wof:placetype":"venue"
},
  "geometry": {"coordinates":[-119.76759199999999,46.209634],"type":"Point"}
}