{
  "type": "Feature",
  "properties": {
    "addr:full":"6845 39th Ave NE Seattle WA 98115",
    "addr:housenumber":"6845",
    "addr:postcode":"98115",
    "addr:street":"39Th Ave Ne",
    "iso:country":"US",
    "sg:address":"6845 39th Ave NE",
    "sg:city":"Seattle",
    "sg:classifiers":[
        {
            "category":"Professional",
            "subcategory":"Management & Consulting",
            "type":"Services"
        }
    ],
    "sg:phone":"+1 206 528 1630",
    "sg:postcode":"98115",
    "sg:province":"WA",
    "sg:tags":[
        "resource",
        "human"
    ],
    "wof:name":"Camenga John",
    "wof:placetype":"venue"
},
  "geometry": {"coordinates":[-122.286136,47.679008],"type":"Point"}
}