{
  "type": "Feature",
  "properties": {
    "addr:full":"901 1st St Snohomish WA 98290",
    "addr:housenumber":"901",
    "addr:postcode":"98290",
    "addr:street":"1St St",
    "iso:country":"US",
    "sg:address":"901 1st St",
    "sg:city":"Snohomish",
    "sg:classifiers":[
        {
            "category":"Shopping",
            "subcategory":"Used Merchandise",
            "type":"Retail Goods"
        }
    ],
    "sg:phone":"+1 360 568 1614",
    "sg:postcode":"98290",
    "sg:province":"WA",
    "wof:name":"Brass Lamp Antiques",
    "wof:placetype":"venue"
},
  "geometry": {"coordinates":[-122.094525,47.911356],"type":"Point"}
}