{
  "type": "Feature",
  "properties": {
    "addr:full":"2210 112th St SW Everett WA 98204",
    "addr:housenumber":"2210",
    "addr:postcode":"98204",
    "addr:street":"112Th St Sw",
    "iso:country":"US",
    "sg:address":"2210 112th St SW",
    "sg:city":"Everett",
    "sg:classifiers":[
        {
            "category":"Food & Beverages",
            "subcategory":"Specialty",
            "type":"Retail Goods"
        }
    ],
    "sg:phone":"+1 425 290 9069",
    "sg:postcode":"98204",
    "sg:province":"WA",
    "wof:name":"High Flying Espresso",
    "wof:placetype":"venue"
},
  "geometry": {"coordinates":[-122.263729,47.896504],"type":"Point"}
}