{
  "type": "Feature",
  "properties": {
    "addr:full":"217 S Wapato Ave Wapato WA 98951",
    "addr:housenumber":"217",
    "addr:postcode":"98951",
    "addr:street":"S Wapato Ave",
    "iso:country":"US",
    "sg:address":"217 S Wapato Ave",
    "sg:city":"Wapato",
    "sg:classifiers":[
        {
            "category":"Shopping",
            "subcategory":"Books",
            "type":"Retail Goods"
        }
    ],
    "sg:phone":"+1 509 877 2992",
    "sg:postcode":"98951",
    "sg:province":"WA",
    "sg:tags":[
        "religious"
    ],
    "wof:name":"Emmanuel Christian Book Store",
    "wof:placetype":"venue"
},
  "geometry": {"coordinates":[-120.41977199999999,46.446744],"type":"Point"}
}