{
  "type": "Feature",
  "properties": {
    "addr:full":"2656 E 29th Ave Spokane WA 99223",
    "addr:housenumber":"2656",
    "addr:postcode":"99223",
    "addr:street":"E 29Th Ave",
    "iso:country":"US",
    "sg:address":"2656 E 29th Ave",
    "sg:city":"Spokane",
    "sg:classifiers":[
        {
            "category":"Restaurant",
            "type":"Food & Drink"
        }
    ],
    "sg:phone":"+1 509 443 1446",
    "sg:postcode":"99223",
    "sg:province":"WA",
    "sg:tags":[
        "eating"
    ],
    "wof:name":"Doppio Espresso",
    "wof:placetype":"venue"
},
  "geometry": {"coordinates":[-117.37270100000001,47.628131],"type":"Point"}
}