{
  "type": "Feature",
  "properties": {
    "addr:full":"14303 196th Ct NE Woodinville WA 98077",
    "addr:housenumber":"14303",
    "addr:postcode":"98077",
    "addr:street":"196Th Ct Ne",
    "iso:country":"US",
    "sg:address":"14303 196th Ct NE",
    "sg:city":"Woodinville",
    "sg:classifiers":[
        {
            "category":"Banks & Credit Unions",
            "subcategory":"Investment Brokerage",
            "type":"Services"
        }
    ],
    "sg:phone":"+1 425 497 9097",
    "sg:postcode":"98077",
    "sg:province":"WA",
    "sg:tags":[
        "advisory"
    ],
    "wof:name":"Key Knowledge Investment Corp",
    "wof:placetype":"venue"
},
  "geometry": {"coordinates":[-122.07566300000001,47.730187],"type":"Point"}
}