{
  "type": "Feature",
  "properties": {
    "iso:country":"US",
    "sg:address":"600 Mullis St",
    "sg:city":"Friday Harbor",
    "sg:classifiers":[
        {
            "category":"Retail",
            "subcategory":"Auto Repair",
            "type":"Services"
        }
    ],
    "sg:phone":"+1 360 378 4038",
    "sg:postcode":"98250",
    "sg:province":"WA",
    "sg:tags":[
        "repairing",
        "automobile"
    ],
    "wof:name":"Gary's Automotive Ctr",
    "wof:placetype":"venue"
},
  "geometry": {"coordinates":[-123.022206,48.53011],"type":"Point"}
}