{
  "type": "Feature",
  "properties": {
    "addr:full":"2930 226th St SW Lynnwood WA 98036",
    "addr:housenumber":"2930",
    "addr:postcode":"98036",
    "addr:street":"226Th St Sw",
    "iso:country":"US",
    "sg:address":"2930 226th St SW",
    "sg:city":"Lynnwood",
    "sg:classifiers":[
        {
            "category":"Building & Trades",
            "subcategory":"Construction",
            "type":"Services"
        }
    ],
    "sg:phone":"+1 425 775 8541",
    "sg:postcode":"98036",
    "sg:province":"WA",
    "wof:name":"Jones Truebuilt Construct",
    "wof:placetype":"venue"
},
  "geometry": {"coordinates":[-122.273049,47.793935],"type":"Point"}
}