{
  "type": "Feature",
  "properties": {
    "addr:full":"1240 Marlin Dr SE Port Orchard WA 98366",
    "addr:housenumber":"1240",
    "addr:postcode":"98366",
    "addr:street":"Marlin Dr Se",
    "iso:country":"US",
    "sg:address":"1240 Marlin Dr SE",
    "sg:city":"Port Orchard",
    "sg:classifiers":[
        {
            "category":"Professional",
            "subcategory":"Business Services",
            "type":"Services"
        }
    ],
    "sg:phone":"+1 360 769 2158",
    "sg:postcode":"98366",
    "sg:province":"WA",
    "wof:name":"Wiley Trade Group",
    "wof:placetype":"venue"
},
  "geometry": {"coordinates":[-122.594013,47.537106],"type":"Point"}
}