{
  "type": "Feature",
  "properties": {
    "addr:full":"3904 E Boston St Seattle WA 98112",
    "addr:housenumber":"3904",
    "addr:postcode":"98112",
    "addr:street":"E Boston St",
    "iso:country":"US",
    "sg:address":"3904 E Boston St",
    "sg:city":"Seattle",
    "sg:classifiers":[
        {
            "category":"Real Estate",
            "subcategory":"Developer",
            "type":"Services"
        }
    ],
    "sg:phone":"+1 206 328 1111",
    "sg:postcode":"98112",
    "sg:province":"WA",
    "wof:name":"Better Neighborhoods LLC",
    "wof:placetype":"venue"
},
  "geometry": {"coordinates":[-122.281954,47.638134],"type":"Point"}
}