{
  "type": "Feature",
  "properties": {
    "addr:full":"3307 Evergreen Way Washougal WA 98671",
    "addr:housenumber":"3307",
    "addr:postcode":"98671",
    "addr:street":"Evergreen Way",
    "iso:country":"US",
    "sg:address":"3307 Evergreen Way",
    "sg:city":"Washougal",
    "sg:classifiers":[
        {
            "category":"Personal",
            "subcategory":"Beauty Salon",
            "type":"Services"
        }
    ],
    "sg:phone":"+1 360 335 9245",
    "sg:postcode":"98671",
    "sg:province":"WA",
    "sg:tags":[
        "shop"
    ],
    "wof:name":"Supercuts",
    "wof:placetype":"venue"
},
  "geometry": {"coordinates":[-122.333663,45.577895],"type":"Point"}
}