{
  "type": "Feature",
  "properties": {
    "iso:country":"US",
    "sg:address":"510 W Washington St",
    "sg:city":"Sequim",
    "sg:classifiers":[
        {
            "category":"Banks & Credit Unions",
            "subcategory":"Bank",
            "type":"Services"
        }
    ],
    "sg:phone":"+1 360 683 1888",
    "sg:postcode":"98382",
    "sg:province":"WA",
    "sg:tags":[
        "escrow"
    ],
    "wof:name":"Pacific Escrow Inc",
    "wof:placetype":"venue"
},
  "geometry": {"coordinates":[-123.113404,48.07976],"type":"Point"}
}