{
  "type": "Feature",
  "properties": {
    "addr:full":"3050 15th Ave W Seattle WA 98119",
    "addr:housenumber":"3050",
    "addr:postcode":"98119",
    "addr:street":"15Th Ave W",
    "iso:country":"US",
    "sg:address":"3050 15th Ave W",
    "sg:city":"Seattle",
    "sg:classifiers":[
        {
            "category":"Building & Trades",
            "subcategory":"Construction",
            "type":"Services"
        }
    ],
    "sg:phone":"+1 206 226 7211",
    "sg:postcode":"98119",
    "sg:province":"WA",
    "sg:tags":[
        "general",
        "contractor"
    ],
    "wof:name":"Mc Kee Design",
    "wof:placetype":"venue"
},
  "geometry": {"coordinates":[-122.376065,47.647551],"type":"Point"}
}