{
  "type": "Feature",
  "properties": {
    "addr:full":"1604 Elm St Clarkston WA 99403",
    "addr:housenumber":"1604",
    "addr:postcode":"99403",
    "addr:street":"Elm St",
    "iso:country":"US",
    "sg:address":"1604 Elm St",
    "sg:city":"Clarkston",
    "sg:classifiers":[
        {
            "category":"Professional",
            "type":"Services"
        }
    ],
    "sg:phone":"+1 509 751 9037",
    "sg:postcode":"99403",
    "sg:province":"WA",
    "wof:name":"Clarkston Golf Cart Svc & Repr",
    "wof:placetype":"venue"
},
  "geometry": {"coordinates":[-117.075,46.41477],"type":"Point"}
}