{
  "type": "Feature",
  "properties": {
    "addr:full":"2724 96th St S Lakewood WA 98499",
    "addr:housenumber":"2724",
    "addr:postcode":"98499",
    "addr:street":"96Th St S",
    "iso:country":"US",
    "sg:address":"2724 96th St S",
    "sg:city":"Lakewood",
    "sg:classifiers":[
        {
            "category":"Autos & Motor Vehicles",
            "subcategory":"Auto Supplies",
            "type":"Retail Goods"
        }
    ],
    "sg:phone":"+1 253 588 6600",
    "sg:postcode":"98499",
    "sg:province":"WA",
    "wof:name":"Toms Racing & Prfmce Parts",
    "wof:placetype":"venue"
},
  "geometry": {"coordinates":[-122.47501,47.170216],"type":"Point"}
}