{
  "type": "Feature",
  "properties": {
    "iso:country":"US",
    "sg:address":"17026 8th Ave NE",
    "sg:city":"Seattle",
    "sg:classifiers":[
        {
            "category":"Building & Trades",
            "subcategory":"Electrical",
            "type":"Services"
        }
    ],
    "sg:phone":"+1 206 365 5264",
    "sg:postcode":"98155",
    "sg:province":"WA",
    "sg:tags":[
        "electrical",
        "contractor"
    ],
    "wof:name":"R J Haynes",
    "wof:placetype":"venue"
},
  "geometry": {"coordinates":[-122.321321,47.754754],"type":"Point"}
}