{
  "type": "Feature",
  "properties": {
    "addr:full":"17020 24th Ave SW Seattle WA 98166",
    "addr:housenumber":"17020",
    "addr:postcode":"98166",
    "addr:street":"24Th Ave Sw",
    "iso:country":"US",
    "sg:address":"17020 24th Ave SW",
    "sg:city":"Seattle",
    "sg:classifiers":[
        {
            "category":"Professional",
            "subcategory":"Art Services",
            "type":"Services"
        }
    ],
    "sg:phone":"+1 206 433 8232",
    "sg:postcode":"98166",
    "sg:province":"WA",
    "sg:tags":[
        "commercial",
        "design"
    ],
    "wof:name":"Hearthside Graphics",
    "wof:placetype":"venue"
},
  "geometry": {"coordinates":[-122.36348099999999,47.44977],"type":"Point"}
}