{
  "type": "Feature",
  "properties": {
    "addr:full":"6717 Greenwood Ave N Seattle WA 98103",
    "addr:housenumber":"6717",
    "addr:postcode":"98103",
    "addr:street":"Greenwood Ave N",
    "iso:country":"US",
    "sg:address":"6717 Greenwood Ave N",
    "sg:city":"Seattle",
    "sg:classifiers":[
        {
            "category":"Health Services",
            "subcategory":"Health Practitioner",
            "type":"Services"
        }
    ],
    "sg:phone":"+1 206 310 3272",
    "sg:postcode":"98103",
    "sg:province":"WA",
    "sg:tags":[
        "acupuncture"
    ],
    "sg:website":"www.soundgardenhealing.com",
    "wof:name":"Sound Garden Healing",
    "wof:placetype":"venue"
},
  "geometry": {"coordinates":[-122.35534199999999,47.678303],"type":"Point"}
}