{
  "type": "Feature",
  "properties": {
    "iso:country":"US",
    "sg:address":"277 Cassidy Creek Rd",
    "sg:city":"Sequim",
    "sg:classifiers":[
        {
            "category":"Cinema",
            "subcategory":"Movie Rental",
            "type":"Entertainment"
        }
    ],
    "sg:phone":"+1 360 683 4377",
    "sg:postcode":"98382",
    "sg:province":"WA",
    "sg:tags":[
        "video",
        "tape"
    ],
    "wof:name":"Video Pro",
    "wof:placetype":"venue"
},
  "geometry": {"coordinates":[-123.230717,48.054649],"type":"Point"}
}