{
  "type": "Feature",
  "properties": {
    "addr:full":"1716 S 16th Ave Yakima WA 98902",
    "addr:housenumber":"1716",
    "addr:postcode":"98902",
    "addr:street":"S 16Th Ave",
    "iso:country":"US",
    "sg:address":"1716 S 16th Ave",
    "sg:city":"Yakima",
    "sg:classifiers":[
        {
            "category":"Building & Trades",
            "subcategory":"Electrical",
            "type":"Services"
        }
    ],
    "sg:phone":"+1 509 454 3760",
    "sg:postcode":"98902",
    "sg:province":"WA",
    "sg:tags":[
        "electrical",
        "contractor"
    ],
    "wof:name":"Electrical Inspection",
    "wof:placetype":"venue"
},
  "geometry": {"coordinates":[-120.530388,46.57096],"type":"Point"}
}