{
  "type": "Feature",
  "properties": {
    "addr:full":"512 S Simcoe Ave Wapato WA 98951",
    "addr:housenumber":"512",
    "addr:postcode":"98951",
    "addr:street":"S Simcoe Ave",
    "iso:country":"US",
    "sg:address":"512 S Simcoe Ave",
    "sg:city":"Wapato",
    "sg:classifiers":[
        {
            "category":"Organizations",
            "subcategory":"Religious Organization",
            "type":"Services"
        }
    ],
    "sg:phone":"+1 509 877 4414",
    "sg:postcode":"98951",
    "sg:province":"WA",
    "sg:tags":[
        "church"
    ],
    "wof:name":"Seventh Day Adventist Church",
    "wof:placetype":"venue"
},
  "geometry": {"coordinates":[-120.41861900000001,46.444107],"type":"Point"}
}