{
  "type": "Feature",
  "properties": {
    "iso:country":"US",
    "sg:address":"100 Enchantment Way",
    "sg:city":"Leavenworth",
    "sg:classifiers":[
        {
            "category":"Real Estate",
            "subcategory":"Real Estate Agent",
            "type":"Services"
        }
    ],
    "sg:phone":"+1 509 548 1419",
    "sg:postcode":"98826",
    "sg:province":"WA",
    "wof:name":"Park Village Resort",
    "wof:placetype":"venue"
},
  "geometry": {"coordinates":[-120.669956,47.59064],"type":"Point"}
}