{
  "type": "Feature",
  "properties": {
    "addr:full":"15341 26th Ave NE Seattle WA 98155",
    "addr:housenumber":"15341",
    "addr:postcode":"98155",
    "addr:street":"26Th Ave Ne",
    "iso:country":"US",
    "sg:address":"15341 26th Ave NE",
    "sg:city":"Seattle",
    "sg:classifiers":[
        {
            "category":"Professional",
            "subcategory":"Computer Services",
            "type":"Services"
        }
    ],
    "sg:phone":"+1 206 362 9147",
    "sg:postcode":"98155",
    "sg:province":"WA",
    "sg:tags":[
        "datum"
    ],
    "wof:name":"Writeway Comm",
    "wof:placetype":"venue"
},
  "geometry": {"coordinates":[-122.300764,47.74068],"type":"Point"}
}