{
  "type": "Feature",
  "properties": {
    "addr:full":"814 NE 40th St Seattle WA 98105",
    "addr:housenumber":"814",
    "addr:postcode":"98105",
    "addr:street":"Ne 40Th St",
    "iso:country":"US",
    "sg:address":"814 NE 40th St",
    "sg:city":"Seattle",
    "sg:classifiers":[
        {
            "category":"Social Services",
            "type":"Services"
        }
    ],
    "sg:phone":"+1 206 322 7900",
    "sg:postcode":"98105",
    "sg:province":"WA",
    "sg:tags":[
        "youth",
        "organization",
        "center"
    ],
    "wof:name":"Gay/Lesbian Youth Info Line",
    "wof:placetype":"venue"
},
  "geometry": {"coordinates":[-122.318884,47.655849],"type":"Point"}
}