{
  "type": "Feature",
  "properties": {
    "addr:full":"215 S Lake Roesiger Rd Snohomish WA 98290",
    "addr:housenumber":"215",
    "addr:postcode":"98290",
    "addr:street":"S Lake Roesiger Rd",
    "iso:country":"US",
    "sg:address":"215 S Lake Roesiger Rd",
    "sg:city":"Snohomish",
    "sg:classifiers":[
        {
            "category":"Professional",
            "type":"Services"
        }
    ],
    "sg:phone":"+1 206 501 8214",
    "sg:postcode":"98290",
    "sg:province":"WA",
    "wof:name":"Tony McAuliffe",
    "wof:placetype":"venue"
},
  "geometry": {"coordinates":[-121.898366,47.993118],"type":"Point"}
}