{
  "type": "Feature",
  "properties": {
    "addr:full":"285 Castle Ave Winthrop WA 98862",
    "addr:housenumber":"285",
    "addr:postcode":"98862",
    "addr:street":"Castle Ave",
    "iso:country":"US",
    "sg:address":"285 Castle Ave",
    "sg:city":"Winthrop",
    "sg:classifiers":[
        {
            "category":"Museum",
            "type":"Entertainment"
        }
    ],
    "sg:phone":"+1 509 996 2712",
    "sg:postcode":"98862",
    "sg:province":"WA",
    "wof:name":"Shafer Museum",
    "wof:placetype":"venue"
},
  "geometry": {"coordinates":[-120.184056,48.478006],"type":"Point"}
}