{
  "type": "Feature",
  "properties": {
    "addr:full":"4250 NE 4th St Ste E Renton WA 98059",
    "addr:housenumber":"4250",
    "addr:postcode":"98059",
    "addr:street":"Ne 4Th St Ste E",
    "iso:country":"US",
    "sg:address":"4250 NE 4th St Ste E",
    "sg:city":"Renton",
    "sg:classifiers":[
        {
            "category":"Personal",
            "subcategory":"Barber",
            "type":"Services"
        }
    ],
    "sg:phone":"+1 425 430 9294",
    "sg:postcode":"98059",
    "sg:province":"WA",
    "sg:website":"www.hairmasterssalon.com",
    "wof:name":"Hairmasters",
    "wof:placetype":"venue"
},
  "geometry": {"coordinates":[-122.162136,47.488723],"type":"Point"}
}