{
  "type": "Feature",
  "properties": {
    "addr:full":"6924 229th Pl NE Redmond WA 98053",
    "addr:housenumber":"6924",
    "addr:postcode":"98053",
    "addr:street":"229Th Pl Ne",
    "iso:country":"US",
    "sg:address":"6924 229th Pl NE",
    "sg:city":"Redmond",
    "sg:classifiers":[
        {
            "category":"Professional",
            "subcategory":"Management & Consulting",
            "type":"Services"
        },
        {
            "category":"Building & Trades",
            "subcategory":"Construction",
            "type":"Services"
        }
    ],
    "sg:phone":"+1 425 868 5001",
    "sg:postcode":"98053",
    "sg:province":"WA",
    "sg:tags":[
        "general",
        "contractor"
    ],
    "wof:name":"Breckenridge Construction Inc",
    "wof:placetype":"venue"
},
  "geometry": {"coordinates":[-122.03344,47.667635],"type":"Point"}
}