{
  "type": "Feature",
  "properties": {
    "addr:full":"1205 S 228th St Seattle WA 98198",
    "addr:housenumber":"1205",
    "addr:postcode":"98198",
    "addr:street":"S 228Th St",
    "iso:country":"US",
    "sg:address":"1205 S 228th St",
    "sg:city":"Seattle",
    "sg:classifiers":[
        {
            "category":"Communications",
            "subcategory":"Film & Video Production",
            "type":"Services"
        }
    ],
    "sg:phone":"+1 206 878 1567",
    "sg:postcode":"98198",
    "sg:province":"WA",
    "sg:tags":[
        "motion"
    ],
    "wof:name":"Krays Productions Inc",
    "wof:placetype":"venue"
},
  "geometry": {"coordinates":[-122.317168,47.397613],"type":"Point"}
}