{
  "type": "Feature",
  "properties": {
    "addr:full":"8827 160th St SE Snohomish WA 98296",
    "addr:housenumber":"8827",
    "addr:postcode":"98296",
    "addr:street":"160Th St Se",
    "iso:country":"US",
    "sg:address":"8827 160th St SE",
    "sg:city":"Snohomish",
    "sg:classifiers":[
        {
            "category":"Building & Trades",
            "subcategory":"Construction",
            "type":"Services"
        }
    ],
    "sg:phone":"+1 360 668 2537",
    "sg:postcode":"98296",
    "sg:province":"WA",
    "sg:tags":[
        "contractor"
    ],
    "wof:name":"Crown General Contractors Inc",
    "wof:placetype":"venue"
},
  "geometry": {"coordinates":[-122.11022800000001,47.851971],"type":"Point"}
}