{
  "type": "Feature",
  "properties": {
    "addr:full":"7834 SE 32nd St Mercer Island WA 98040",
    "addr:housenumber":"7834",
    "addr:postcode":"98040",
    "addr:street":"Se 32Nd St",
    "iso:country":"US",
    "sg:address":"7834 SE 32nd St",
    "sg:city":"Mercer Island",
    "sg:classifiers":[
        {
            "category":"Professional",
            "subcategory":"Engineering",
            "type":"Services"
        },
        {
            "category":"Real Estate",
            "subcategory":"Surveying",
            "type":"Services"
        }
    ],
    "sg:phone":"+1 206 232 5282",
    "sg:postcode":"98040",
    "sg:province":"WA",
    "sg:tags":[
        "surveyor"
    ],
    "wof:name":"Bassi Jones & Associates",
    "wof:placetype":"venue"
},
  "geometry": {"coordinates":[-122.232462,47.581898],"type":"Point"}
}