{
  "type": "Feature",
  "properties": {
    "addr:full":"10612 NE 46th St Kirkland WA 98033",
    "addr:housenumber":"10612",
    "addr:postcode":"98033",
    "addr:street":"Ne 46Th St",
    "iso:country":"US",
    "sg:address":"10612 NE 46th St",
    "sg:city":"Kirkland",
    "sg:classifiers":[
        {
            "category":"Professional",
            "subcategory":"Management & Consulting",
            "type":"Services"
        }
    ],
    "sg:phone":"+1 425 889 6838",
    "sg:postcode":"98033",
    "sg:province":"WA",
    "sg:tags":[
        "food",
        "consultant",
        "beverage",
        "facility"
    ],
    "wof:name":"Delicious Dinner At Home",
    "wof:placetype":"venue"
},
  "geometry": {"coordinates":[-122.199174,47.651359],"type":"Point"}
}