{
  "type": "Feature",
  "properties": {
    "addr:full":"16300 Aurora Ave N Shoreline WA 98133",
    "addr:housenumber":"16300",
    "addr:postcode":"98133",
    "addr:street":"Aurora Ave N",
    "iso:country":"US",
    "sg:address":"16300 Aurora Ave N",
    "sg:city":"Shoreline",
    "sg:classifiers":[
        {
            "category":"Travel",
            "subcategory":"Travel Agent",
            "type":"Entertainment"
        }
    ],
    "sg:phone":"+1 206 546 5131",
    "sg:postcode":"98133",
    "sg:province":"WA",
    "sg:tags":[
        "agency",
        "bureau"
    ],
    "wof:name":"Aurora Village Travel Agency",
    "wof:placetype":"venue"
},
  "geometry": {"coordinates":[-122.345404,47.748324],"type":"Point"}
}