{
  "type": "Feature",
  "properties": {
    "addr:full":"22701 12th Pl W Bothell WA 98021",
    "addr:housenumber":"22701",
    "addr:postcode":"98021",
    "addr:street":"12Th Pl W",
    "iso:country":"US",
    "sg:address":"22701 12th Pl W",
    "sg:city":"Bothell",
    "sg:classifiers":[
        {
            "category":"Utilities",
            "subcategory":"Telephone",
            "type":"Services"
        }
    ],
    "sg:phone":"+1 425 985 1829",
    "sg:postcode":"98021",
    "sg:province":"WA",
    "sg:tags":[
        "communications"
    ],
    "wof:name":"Planet Gamecube",
    "wof:placetype":"venue"
},
  "geometry": {"coordinates":[-122.24975999999999,47.792605],"type":"Point"}
}