{
  "type": "Feature",
  "properties": {
    "addr:full":"400 Orchard Rd Pasco WA 99301",
    "addr:housenumber":"400",
    "addr:postcode":"99301",
    "addr:street":"Orchard Rd",
    "iso:country":"US",
    "sg:address":"400 Orchard Rd",
    "sg:city":"Pasco",
    "sg:classifiers":[
        {
            "category":"Farming",
            "subcategory":"Livestock Farm",
            "type":"Manufacturing & Wholesale Goods"
        }
    ],
    "sg:phone":"+1 509 547 3939",
    "sg:postcode":"99301",
    "sg:province":"WA",
    "sg:tags":[
        "animal",
        "general"
    ],
    "wof:name":"Michael N Haverkamp",
    "wof:placetype":"venue"
},
  "geometry": {"coordinates":[-119.12350600000001,46.359626],"type":"Point"}
}