{
  "type": "Feature",
  "properties": {
    "addr:full":"6210 57th Ave SE Olympia WA 98513",
    "addr:housenumber":"6210",
    "addr:postcode":"98513",
    "addr:street":"57Th Ave Se",
    "iso:country":"US",
    "sg:address":"6210 57th Ave SE",
    "sg:city":"Olympia",
    "sg:classifiers":[
        {
            "category":"Real Estate",
            "subcategory":"Real Estate Agent",
            "type":"Services"
        }
    ],
    "sg:phone":"+1 360 412 6730",
    "sg:postcode":"98513",
    "sg:province":"WA",
    "wof:name":"Century 2u Hometown",
    "wof:placetype":"venue"
},
  "geometry": {"coordinates":[-122.79770499999999,46.997557],"type":"Point"}
}