{
  "type": "Feature",
  "properties": {
    "iso:country":"US",
    "sg:address":"138 Workman Rd",
    "sg:city":"Mossyrock",
    "sg:classifiers":[
        {
            "category":"Building & Trades",
            "subcategory":"Construction",
            "type":"Services"
        }
    ],
    "sg:phone":"+1 360 983 3050",
    "sg:postcode":"98564",
    "sg:province":"WA",
    "sg:tags":[
        "new",
        "remodeling",
        "commercial",
        "family",
        "home"
    ],
    "wof:name":"G A C Builders",
    "wof:placetype":"venue"
},
  "geometry": {"coordinates":[-122.43856100000001,46.51793],"type":"Point"}
}