{
  "type": "Feature",
  "properties": {
    "addr:full":"1207 W Yakima Ave Yakima WA 98902",
    "addr:housenumber":"1207",
    "addr:postcode":"98902",
    "addr:street":"W Yakima Ave",
    "iso:country":"US",
    "sg:address":"1207 W Yakima Ave",
    "sg:city":"Yakima",
    "sg:classifiers":[
        {
            "category":"Building & Trades",
            "subcategory":"Cleaning & Sanitation",
            "type":"Services"
        }
    ],
    "sg:phone":"+1 509 453 7849",
    "sg:postcode":"98902",
    "sg:province":"WA",
    "sg:tags":[
        "maintenance",
        "cleaners-interior"
    ],
    "wof:name":"Cromwells Window Service",
    "wof:placetype":"venue"
},
  "geometry": {"coordinates":[-120.52628,46.597413],"type":"Point"}
}