{
  "type": "Feature",
  "properties": {
    "addr:full":"3232 NW 74th St Seattle WA 98117",
    "addr:housenumber":"3232",
    "addr:postcode":"98117",
    "addr:street":"Nw 74Th St",
    "iso:country":"US",
    "sg:address":"3232 NW 74th St",
    "sg:city":"Seattle",
    "sg:classifiers":[
        {
            "category":"Personal",
            "type":"Services"
        },
        {
            "category":"Professional",
            "subcategory":"Art Services",
            "type":"Services"
        }
    ],
    "sg:phone":"+1 206 906 9588",
    "sg:postcode":"98117",
    "sg:province":"WA",
    "sg:tags":[
        "photography",
        "videography",
        "wedding"
    ],
    "wof:name":"Kathryn Barnard Photographer",
    "wof:placetype":"venue"
},
  "geometry": {"coordinates":[-122.39885599999999,47.682358],"type":"Point"}
}