{
  "type": "Feature",
  "properties": {
    "addr:full":"4477 Wenatchee Dr NE Moses Lake WA 98837",
    "addr:housenumber":"4477",
    "addr:postcode":"98837",
    "addr:street":"Wenatchee Dr Ne",
    "iso:country":"US",
    "sg:address":"4477 Wenatchee Dr NE",
    "sg:city":"Moses Lake",
    "sg:classifiers":[
        {
            "category":"Professional",
            "subcategory":"Engineering",
            "type":"Services"
        }
    ],
    "sg:phone":"+1 509 765 1352",
    "sg:postcode":"98837",
    "sg:province":"WA",
    "sg:tags":[
        "engineer"
    ],
    "wof:name":"Dennis H Parr & Assoc",
    "wof:placetype":"venue"
},
  "geometry": {"coordinates":[-119.27475,47.148755],"type":"Point"}
}