{
  "type": "Feature",
  "properties": {
    "addr:full":"550 106th Ave NE Ofc Bellevue WA 98004",
    "addr:housenumber":"550",
    "addr:postcode":"98004",
    "addr:street":"106Th Ave Ne",
    "iso:country":"US",
    "sg:address":"550 106th Ave NE Ofc",
    "sg:city":"Bellevue",
    "sg:classifiers":[
        {
            "category":"Coffee & Tea",
            "type":"Food & Drink"
        }
    ],
    "sg:phone":"+1 425 990 8008",
    "sg:postcode":"98004",
    "sg:province":"WA",
    "wof:name":"Cafe Habits",
    "wof:placetype":"venue"
},
  "geometry": {"coordinates":[-122.19899700000001,47.615101],"type":"Point"}
}