{
  "type": "Feature",
  "properties": {
    "addr:full":"25515 NE 47th Pl Redmond WA 98053",
    "addr:housenumber":"25515",
    "addr:postcode":"98053",
    "addr:street":"Ne 47Th Pl",
    "iso:country":"US",
    "sg:address":"25515 NE 47th Pl",
    "sg:city":"Redmond",
    "sg:classifiers":[
        {
            "category":"Manufacturing",
            "subcategory":"Electronics",
            "type":"Manufacturing & Wholesale Goods"
        }
    ],
    "sg:phone":"+1 425 836 0942",
    "sg:postcode":"98053",
    "sg:province":"WA",
    "sg:tags":[
        "electronic",
        "sensor",
        "mfg"
    ],
    "wof:name":"Chapin Company",
    "wof:placetype":"venue"
},
  "geometry": {"coordinates":[-121.999859,47.650167],"type":"Point"}
}