{
  "type": "Feature",
  "properties": {
    "addr:full":"238 W Sprague Ave Spokane WA 99201",
    "addr:housenumber":"238",
    "addr:postcode":"99201",
    "addr:street":"W Sprague Ave",
    "iso:country":"US",
    "sg:address":"238 W Sprague Ave",
    "sg:city":"Spokane",
    "sg:classifiers":[
        {
            "category":"Organizations",
            "subcategory":"Religious Organization",
            "type":"Services"
        }
    ],
    "sg:phone":"+1 509 456 2576",
    "sg:postcode":"99201",
    "sg:province":"WA",
    "sg:tags":[
        "church"
    ],
    "wof:name":"Truth Ministries",
    "wof:placetype":"venue"
},
  "geometry": {"coordinates":[-117.41453300000001,47.657318],"type":"Point"}
}