{
  "type": "Feature",
  "properties": {
    "addr:full":"25059 NE 42nd Pl Redmond WA 98053",
    "addr:housenumber":"25059",
    "addr:postcode":"98053",
    "addr:street":"Ne 42Nd Pl",
    "iso:country":"US",
    "sg:address":"25059 NE 42nd Pl",
    "sg:city":"Redmond",
    "sg:classifiers":[
        {
            "category":"Shopping",
            "type":"Retail Goods"
        }
    ],
    "sg:phone":"+1 425 836 3500",
    "sg:postcode":"98053",
    "sg:province":"WA",
    "sg:tags":[
        "merchandise"
    ],
    "wof:name":"Casey Lazik Reptiles",
    "wof:placetype":"venue"
},
  "geometry": {"coordinates":[-122.003598,47.646812],"type":"Point"}
}