{
  "type": "Feature",
  "properties": {
    "addr:full":"7938 30th Ave SW Seattle WA 98126",
    "addr:housenumber":"7938",
    "addr:postcode":"98126",
    "addr:street":"30Th Ave Sw",
    "iso:country":"US",
    "sg:address":"7938 30th Ave SW",
    "sg:city":"Seattle",
    "sg:classifiers":[
        {
            "category":"Insurance",
            "subcategory":"Hazard Insurance",
            "type":"Services"
        }
    ],
    "sg:phone":"+1 206 932 8198",
    "sg:postcode":"98126",
    "sg:province":"WA",
    "sg:tags":[
        "carrier"
    ],
    "wof:name":"Connie Browne",
    "wof:placetype":"venue"
},
  "geometry": {"coordinates":[-122.371166,47.530436],"type":"Point"}
}