{
  "type": "Feature",
  "properties": {
    "addr:full":"10234 Martin Way E Olympia WA 98516",
    "addr:housenumber":"10234",
    "addr:postcode":"98516",
    "addr:street":"Martin Way E",
    "iso:country":"US",
    "sg:address":"10234 Martin Way E",
    "sg:city":"Olympia",
    "sg:classifiers":[
        {
            "category":"Tea Room",
            "subcategory":"None",
            "type":"Food & Drink"
        },
        {
            "category":"Coffee & Tea",
            "type":"Food & Drink"
        }
    ],
    "sg:phone":"+1 360 413 9677",
    "sg:postcode":"98516",
    "sg:province":"WA",
    "wof:name":"Hot Shotz At The Lighthouse",
    "wof:placetype":"venue"
},
  "geometry": {"coordinates":[-122.721676,47.065414],"type":"Point"}
}