{
  "type": "Feature",
  "properties": {
    "addr:full":"810 3rd Ave Seattle WA 98104",
    "addr:housenumber":"810",
    "addr:postcode":"98104",
    "addr:street":"3Rd Ave",
    "iso:country":"US",
    "sg:address":"810 3rd Ave",
    "sg:city":"Seattle",
    "sg:classifiers":[
        {
            "category":"Real Estate",
            "subcategory":"Real Estate Agent",
            "type":"Services"
        }
    ],
    "sg:phone":"+1 206 262 2880",
    "sg:postcode":"98104",
    "sg:province":"WA",
    "sg:website":"www.gbsre.com",
    "wof:name":"Gregory Broderick Smith Rl Est",
    "wof:placetype":"venue"
},
  "geometry": {"coordinates":[-122.333259,47.604875],"type":"Point"}
}