{
  "type": "Feature",
  "properties": {
    "addr:full":"1900 W Nickerson St Ste 205 Seattle WA 98119",
    "addr:housenumber":"1900",
    "addr:postcode":"98119",
    "addr:street":"W Nickerson St Ste 205",
    "iso:country":"US",
    "sg:address":"1900 W Nickerson St Ste 205",
    "sg:city":"Seattle",
    "sg:classifiers":[
        {
            "category":"Food & Beverages",
            "subcategory":"Meat & Fish",
            "type":"Retail Goods"
        }
    ],
    "sg:phone":"+1 206 285 2051",
    "sg:postcode":"98119",
    "sg:province":"WA",
    "sg:tags":[
        "seafood",
        "market"
    ],
    "wof:name":"Seafood Trading Inc",
    "wof:placetype":"venue"
},
  "geometry": {"coordinates":[-122.38099699999999,47.6549],"type":"Point"}
}