{
  "type": "Feature",
  "properties": {
    "addr:full":"19908 104th Ave NE Bothell WA 98011",
    "addr:housenumber":"19908",
    "addr:postcode":"98011",
    "addr:street":"104Th Ave Ne",
    "iso:country":"US",
    "sg:address":"19908 104th Ave NE",
    "sg:city":"Bothell",
    "sg:classifiers":[
        {
            "category":"Shopping",
            "subcategory":"Music",
            "type":"Retail Goods"
        }
    ],
    "sg:phone":"+1 425 485 7576",
    "sg:postcode":"98011",
    "sg:province":"WA",
    "wof:name":"G M Music & Gear International",
    "wof:placetype":"venue"
},
  "geometry": {"coordinates":[-122.20155099999999,47.773312],"type":"Point"}
}