{
  "type": "Feature",
  "properties": {
    "addr:full":"1778 E Badger Rd Everson WA 98247",
    "addr:housenumber":"1778",
    "addr:postcode":"98247",
    "addr:street":"E Badger Rd",
    "iso:country":"US",
    "sg:address":"1778 E Badger Rd",
    "sg:city":"Everson",
    "sg:classifiers":[
        {
            "category":"Retail",
            "subcategory":"Repair Shop",
            "type":"Services"
        }
    ],
    "sg:phone":"+1 360 354 5259",
    "sg:postcode":"98247",
    "sg:province":"WA",
    "wof:name":"All County Cleaning",
    "wof:placetype":"venue"
},
  "geometry": {"coordinates":[-122.3925,48.963908],"type":"Point"}
}