{
  "type": "Feature",
  "properties": {
    "addr:full":"6044 Palatine Ave N Seattle WA 98103",
    "addr:housenumber":"6044",
    "addr:postcode":"98103",
    "addr:street":"Palatine Ave N",
    "iso:country":"US",
    "sg:address":"6044 Palatine Ave N",
    "sg:city":"Seattle",
    "sg:classifiers":[
        {
            "category":"Building & Trades",
            "subcategory":"Construction",
            "type":"Services"
        }
    ],
    "sg:phone":"+1 206 783 1551",
    "sg:postcode":"98103",
    "sg:province":"WA",
    "sg:tags":[
        "house"
    ],
    "wof:name":"Bruceaux Construction",
    "wof:placetype":"venue"
},
  "geometry": {"coordinates":[-122.356346,47.673659],"type":"Point"}
}