{
  "type": "Feature",
  "properties": {
    "addr:full":"4241 S Thistle St Seattle WA 98118",
    "addr:housenumber":"4241",
    "addr:postcode":"98118",
    "addr:street":"S Thistle St",
    "iso:country":"US",
    "sg:address":"4241 S Thistle St",
    "sg:city":"Seattle",
    "sg:classifiers":[
        {
            "category":"Wholesale",
            "subcategory":"Durable Goods & Equipment",
            "type":"Manufacturing & Wholesale Goods"
        }
    ],
    "sg:phone":"+1 206 760 0822",
    "sg:postcode":"98118",
    "sg:province":"WA",
    "sg:tags":[
        "exporter"
    ],
    "wof:name":"GGB Cargo Forwarder",
    "wof:placetype":"venue"
},
  "geometry": {"coordinates":[-122.27945200000001,47.527813],"type":"Point"}
}