{
  "type": "Feature",
  "properties": {
    "addr:full":"Carillon Point Ste 2225 Kirkland WA 98033",
    "addr:postcode":"98033",
    "addr:street":"Carillon Point Ste 2225",
    "iso:country":"US",
    "sg:address":"Carillon Point Ste 2225",
    "sg:city":"Kirkland",
    "sg:classifiers":[
        {
            "category":"Sports & Exercise",
            "subcategory":"Gym",
            "type":"Entertainment"
        }
    ],
    "sg:phone":"+1 425 522 4408",
    "sg:postcode":"98033",
    "sg:province":"WA",
    "sg:tags":[
        "trainer"
    ],
    "sg:website":"www.wearesuperfly.com",
    "wof:name":"FlyFitness",
    "wof:placetype":"venue"
},
  "geometry": {"coordinates":[-122.206418,47.656473],"type":"Point"}
}