{
  "type": "Feature",
  "properties": {
    "addr:full":"2018 Everest Ave Richland WA 99354",
    "addr:housenumber":"2018",
    "addr:postcode":"99354",
    "addr:street":"Everest Ave",
    "iso:country":"US",
    "sg:address":"2018 Everest Ave",
    "sg:city":"Richland",
    "sg:classifiers":[
        {
            "category":"Manufacturing",
            "subcategory":"Motor Vehicles & Parts",
            "type":"Manufacturing & Wholesale Goods"
        }
    ],
    "sg:phone":"+1 509 727 7878",
    "sg:postcode":"99354",
    "sg:province":"WA",
    "sg:tags":[
        "mfg"
    ],
    "wof:name":"Performance Street Machines",
    "wof:placetype":"venue"
},
  "geometry": {"coordinates":[-119.275211,46.305547],"type":"Point"}
}