{
  "type": "Feature",
  "properties": {
    "addr:full":"4929 189th St SW Lynnwood WA 98036",
    "addr:housenumber":"4929",
    "addr:postcode":"98036",
    "addr:street":"189Th St Sw",
    "iso:country":"US",
    "sg:address":"4929 189th St SW",
    "sg:city":"Lynnwood",
    "sg:classifiers":[
        {
            "category":"Social Services",
            "subcategory":"Child Care",
            "type":"Services"
        }
    ],
    "sg:phone":"+1 206 391 7630",
    "sg:postcode":"98036",
    "sg:province":"WA",
    "sg:tags":[
        "day"
    ],
    "wof:name":"Life Start Travel",
    "wof:placetype":"venue"
},
  "geometry": {"coordinates":[-122.29970299999999,47.827427],"type":"Point"}
}