{
  "type": "Feature",
  "properties": {
    "addr:full":"9303 E Trent Ave Spokane WA 99206",
    "addr:housenumber":"9303",
    "addr:postcode":"99206",
    "addr:street":"E Trent Ave",
    "iso:country":"US",
    "sg:address":"9303 E Trent Ave",
    "sg:city":"Spokane",
    "sg:classifiers":[
        {
            "category":"Manufacturing",
            "subcategory":"Retail Goods",
            "type":"Manufacturing & Wholesale Goods"
        }
    ],
    "sg:phone":"+1 509 927 8805",
    "sg:postcode":"99206",
    "sg:province":"WA",
    "sg:tags":[
        "product",
        "mfg"
    ],
    "wof:name":"Freewheeler Inc",
    "wof:placetype":"venue"
},
  "geometry": {"coordinates":[-117.278768,47.681953],"type":"Point"}
}