{
  "type": "Feature",
  "properties": {
    "iso:country":"US",
    "sg:address":"9704 151st Avenue Kp N",
    "sg:city":"Gig Harbor",
    "sg:classifiers":[
        {
            "category":"Wholesale",
            "subcategory":"Non-durable Goods",
            "type":"Manufacturing & Wholesale Goods"
        }
    ],
    "sg:phone":"+1 206 985 0880",
    "sg:postcode":"98329",
    "sg:province":"WA",
    "sg:tags":[
        "pet",
        "supply"
    ],
    "wof:name":"Sturdi Products",
    "wof:placetype":"venue"
},
  "geometry": {"coordinates":[-122.738829,47.345904],"type":"Point"}
}