{
  "type": "Feature",
  "properties": {
    "addr:full":"6522 115th Pl SE Bellevue WA 98006",
    "addr:housenumber":"6522",
    "addr:postcode":"98006",
    "addr:street":"115Th Pl Se",
    "iso:country":"US",
    "sg:address":"6522 115th Pl SE",
    "sg:city":"Bellevue",
    "sg:classifiers":[
        {
            "category":"Building & Trades",
            "subcategory":"Construction",
            "type":"Services"
        },
        {
            "category":"Professional",
            "subcategory":"Management & Consulting",
            "type":"Services"
        }
    ],
    "sg:phone":"+1 425 227 0975",
    "sg:postcode":"98006",
    "sg:province":"WA",
    "sg:tags":[
        "project",
        "industry",
        "for"
    ],
    "wof:name":"Andrew Clapham & Assoc LLC",
    "wof:placetype":"venue"
},
  "geometry": {"coordinates":[-122.186322,47.545039],"type":"Point"}
}