{
  "type": "Feature",
  "properties": {
    "addr:full":"111 N Bennett Ln South Bend WA 98555",
    "addr:housenumber":"111",
    "addr:postcode":"98555",
    "addr:street":"N Bennett Ln",
    "iso:country":"US",
    "sg:address":"111 N Bennett Ln",
    "sg:city":"South Bend",
    "sg:classifiers":[
        {
            "category":"Organizations",
            "subcategory":"Religious Organization",
            "type":"Services"
        }
    ],
    "sg:phone":"+1 360 942 5158",
    "sg:postcode":"98555",
    "sg:province":"WA",
    "sg:tags":[
        "church"
    ],
    "wof:name":"Jehovah's Witnesses",
    "wof:placetype":"venue"
},
  "geometry": {"coordinates":[-123.05759999999999,47.509623],"type":"Point"}
}