{
  "type": "Feature",
  "properties": {
    "addr:full":"17609 16th St E Sumner WA 98391",
    "addr:housenumber":"17609",
    "addr:postcode":"98391",
    "addr:street":"16Th St E",
    "iso:country":"US",
    "sg:address":"17609 16th St E",
    "sg:city":"Sumner",
    "sg:classifiers":[
        {
            "category":"Wholesale",
            "subcategory":"Durable Goods & Equipment",
            "type":"Manufacturing & Wholesale Goods"
        }
    ],
    "sg:phone":"+1 253 891 3983",
    "sg:postcode":"98391",
    "sg:province":"WA",
    "sg:tags":[
        "product",
        "safety",
        "install",
        "prevention",
        "fall"
    ],
    "wof:name":"The Fall Guy",
    "wof:placetype":"venue"
},
  "geometry": {"coordinates":[-122.196412,47.243264],"type":"Point"}
}