{
  "type": "Feature",
  "properties": {
    "addr:full":"6806 W 17th Pl Kennewick WA 99338",
    "addr:housenumber":"6806",
    "addr:postcode":"99338",
    "addr:street":"W 17Th Pl",
    "iso:country":"US",
    "sg:address":"6806 W 17th Pl",
    "sg:city":"Kennewick",
    "sg:classifiers":[
        {
            "category":"Recreation",
            "type":"Entertainment"
        }
    ],
    "sg:phone":"+1 509 783 0712",
    "sg:postcode":"99338",
    "sg:province":"WA",
    "wof:name":"Stretch N Grow of Yakima",
    "wof:placetype":"venue"
},
  "geometry": {"coordinates":[-119.212664,46.1943],"type":"Point"}
}