{
  "type": "Feature",
  "properties": {
    "addr:full":"801 NE 65th St Ste C Seattle WA 98115",
    "addr:housenumber":"801",
    "addr:postcode":"98115",
    "addr:street":"Ne 65Th St Ste C",
    "iso:country":"US",
    "sg:address":"801 NE 65th St Ste C",
    "sg:city":"Seattle",
    "sg:classifiers":[
        {
            "category":"Restaurant",
            "type":"Food & Drink"
        },
        {
            "category":"Bars & Pubs",
            "subcategory":"Nightclub",
            "type":"Food & Drink"
        }
    ],
    "sg:phone":"+1 206 523 8888",
    "sg:postcode":"98115",
    "sg:province":"WA",
    "sg:tags":[
        "nightlife"
    ],
    "sg:website":"scarlet-tree.com",
    "wof:name":"Scarlet Tree Restaurant",
    "wof:placetype":"venue"
},
  "geometry": {"coordinates":[-122.320044,47.675845],"type":"Point"}
}