{
  "type": "Feature",
  "properties": {
    "addr:full":"2704 N Hogan St Ste 3 Spokane WA 99207",
    "addr:housenumber":"2704",
    "addr:postcode":"99207",
    "addr:street":"N Hogan St Ste 3",
    "iso:country":"US",
    "sg:address":"2704 N Hogan St Ste 3",
    "sg:city":"Spokane",
    "sg:classifiers":[
        {
            "category":"Professional",
            "subcategory":"Advertising",
            "type":"Services"
        },
        {
            "category":"Manufacturing",
            "subcategory":"Signs",
            "type":"Manufacturing & Wholesale Goods"
        }
    ],
    "sg:phone":"+1 509 484 1107",
    "sg:postcode":"99207",
    "sg:province":"WA",
    "sg:tags":[
        "agency",
        "specialty"
    ],
    "wof:name":"Preferred Advertising & Marketing",
    "wof:placetype":"venue"
},
  "geometry": {"coordinates":[-117.38764999999999,47.682461],"type":"Point"}
}