{
  "type": "Feature",
  "properties": {
    "addr:full":"204 S 45th Ave Yakima WA 98908",
    "addr:housenumber":"204",
    "addr:postcode":"98908",
    "addr:street":"S 45Th Ave",
    "iso:country":"US",
    "sg:address":"204 S 45th Ave",
    "sg:city":"Yakima",
    "sg:classifiers":[
        {
            "category":"Real Estate",
            "subcategory":"Real Estate Operator",
            "type":"Services"
        }
    ],
    "sg:phone":"+1 509 966 4227",
    "sg:postcode":"98908",
    "sg:province":"WA",
    "sg:tags":[
        "apartment",
        "rental"
    ],
    "wof:name":"Galloway Doloris",
    "wof:placetype":"venue"
},
  "geometry": {"coordinates":[-120.568535,46.595797],"type":"Point"}
}