{
  "type": "Feature",
  "properties": {
    "addr:full":"1201 Dexter Ave N Seattle WA 98109",
    "addr:housenumber":"1201",
    "addr:postcode":"98109",
    "addr:street":"Dexter Ave N",
    "iso:country":"US",
    "sg:address":"1201 Dexter Ave N",
    "sg:city":"Seattle",
    "sg:classifiers":[
        {
            "category":"Restaurant",
            "type":"Food & Drink"
        }
    ],
    "sg:phone":"+1 206 282 2113",
    "sg:postcode":"98109",
    "sg:province":"WA",
    "sg:tags":[
        "sushi",
        "bar"
    ],
    "wof:name":"Sushi Bay",
    "wof:placetype":"venue"
},
  "geometry": {"coordinates":[-122.342506,47.629845],"type":"Point"}
}