{
  "type": "Feature",
  "properties": {
    "addr:full":"81 Malfait Tracts Rd Washougal WA 98671",
    "addr:housenumber":"81",
    "addr:postcode":"98671",
    "addr:street":"Malfait Tracts Rd",
    "iso:country":"US",
    "sg:address":"81 Malfait Tracts Rd",
    "sg:city":"Washougal",
    "sg:classifiers":[
        {
            "category":"Professional",
            "subcategory":"Business Services",
            "type":"Services"
        }
    ],
    "sg:phone":"+1 360 837 3533",
    "sg:postcode":"98671",
    "sg:province":"WA",
    "wof:name":"Aldon Enterprises LLC",
    "wof:placetype":"venue"
},
  "geometry": {"coordinates":[-122.24252199999999,45.610453],"type":"Point"}
}