{
  "type": "Feature",
  "properties": {
    "addr:full":"3722 Delphi Rd SW Olympia WA 98512",
    "addr:housenumber":"3722",
    "addr:postcode":"98512",
    "addr:street":"Delphi Rd Sw",
    "iso:country":"US",
    "sg:address":"3722 Delphi Rd SW",
    "sg:city":"Olympia",
    "sg:classifiers":[
        {
            "category":"Farming",
            "subcategory":"Poultry Farm",
            "type":"Manufacturing & Wholesale Goods"
        }
    ],
    "sg:phone":"+1 360 866 7254",
    "sg:postcode":"98512",
    "sg:province":"WA",
    "sg:tags":[
        "chicken",
        "egg"
    ],
    "wof:name":"Lowell Arnold",
    "wof:placetype":"venue"
},
  "geometry": {"coordinates":[-122.997097,47.019655],"type":"Point"}
}