{
  "type": "Feature",
  "properties": {
    "addr:full":"18412 4th Ave S Burien WA 98148",
    "addr:housenumber":"18412",
    "addr:postcode":"98148",
    "addr:street":"4Th Ave S Burien",
    "iso:country":"US",
    "sg:address":"18412 4th Ave S",
    "sg:city":"Burien",
    "sg:classifiers":[
        {
            "category":"Building & Trades",
            "subcategory":"Construction",
            "type":"Services"
        }
    ],
    "sg:phone":"+1 206 835 9733",
    "sg:postcode":"98148",
    "sg:province":"WA",
    "sg:tags":[
        "asbestos",
        "detection",
        "removal"
    ],
    "wof:name":"One Step Environmental Abatement",
    "wof:placetype":"venue"
},
  "geometry": {"coordinates":[-122.32958000000001,47.437687],"type":"Point"}
}