{
  "type": "Feature",
  "properties": {
    "addr:full":"3280 Fourth Parallel Rd Ellensburg WA 98926",
    "addr:housenumber":"3280",
    "addr:postcode":"98926",
    "addr:street":"Fourth Parallel Rd",
    "iso:country":"US",
    "sg:address":"3280 Fourth Parallel Rd",
    "sg:city":"Ellensburg",
    "sg:classifiers":[
        {
            "category":"Farming",
            "subcategory":"Farm",
            "type":"Manufacturing & Wholesale Goods"
        }
    ],
    "sg:phone":"+1 509 968 3797",
    "sg:postcode":"98926",
    "sg:province":"WA",
    "wof:name":"James Engler Shop",
    "wof:placetype":"venue"
},
  "geometry": {"coordinates":[-120.38571399999999,46.911848],"type":"Point"}
}