{
  "type": "Feature",
  "properties": {
    "addr:full":"605 Ramona Ave Wenatchee WA 98801",
    "addr:housenumber":"605",
    "addr:postcode":"98801",
    "addr:street":"Ramona Ave",
    "iso:country":"US",
    "sg:address":"605 Ramona Ave",
    "sg:city":"Wenatchee",
    "sg:classifiers":[
        {
            "category":"Building & Trades",
            "subcategory":"Construction",
            "type":"Services"
        }
    ],
    "sg:phone":"+1 509 886 7747",
    "sg:postcode":"98801",
    "sg:province":"WA",
    "sg:tags":[
        "hanging",
        "contractor"
    ],
    "wof:name":"Clay Garrod",
    "wof:placetype":"venue"
},
  "geometry": {"coordinates":[-120.32865,47.430981],"type":"Point"}
}