{
  "type": "Feature",
  "properties": {
    "addr:full":"2644 Eastwood Ave Richland WA 99352",
    "addr:housenumber":"2644",
    "addr:postcode":"99352",
    "addr:street":"Eastwood Ave",
    "iso:country":"US",
    "sg:address":"2644 Eastwood Ave",
    "sg:city":"Richland",
    "sg:classifiers":[
        {
            "category":"Wholesale",
            "subcategory":"Stationery",
            "type":"Manufacturing & Wholesale Goods"
        }
    ],
    "sg:phone":"+1 509 627 4766",
    "sg:postcode":"99352",
    "sg:province":"WA",
    "sg:tags":[
        "supply"
    ],
    "wof:name":"Office Solutions",
    "wof:placetype":"venue"
},
  "geometry": {"coordinates":[-119.26091099999999,46.215126],"type":"Point"}
}