{
  "type": "Feature",
  "properties": {
    "addr:full":"9057 Washington Ave NW Silverdale WA 98383",
    "addr:housenumber":"9057",
    "addr:postcode":"98383",
    "addr:street":"Washington Ave Nw",
    "iso:country":"US",
    "sg:address":"9057 Washington Ave NW",
    "sg:city":"Silverdale",
    "sg:classifiers":[
        {
            "category":"Professional",
            "subcategory":"Lawyer & Legal Services",
            "type":"Services"
        }
    ],
    "sg:phone":"+1 360 692 4888",
    "sg:postcode":"98383",
    "sg:province":"WA",
    "sg:tags":[
        "attorney"
    ],
    "sg:website":"www.bbroughtonlaw.com",
    "wof:name":"Broughton & Assoc Inc",
    "wof:placetype":"venue"
},
  "geometry": {"coordinates":[-122.695308,47.645951],"type":"Point"}
}