{
  "type": "Feature",
  "properties": {
    "addr:full":"608 Williams Blvd Richland WA 99354",
    "addr:housenumber":"608",
    "addr:postcode":"99354",
    "addr:street":"Williams Blvd",
    "iso:country":"US",
    "sg:address":"608 Williams Blvd",
    "sg:city":"Richland",
    "sg:classifiers":[
        {
            "category":"Restaurant",
            "type":"Food & Drink"
        }
    ],
    "sg:phone":"+1 509 375 4000",
    "sg:postcode":"99354",
    "sg:province":"WA",
    "sg:tags":[
        "caterer"
    ],
    "wof:name":"Castle Catering",
    "wof:placetype":"venue"
},
  "geometry": {"coordinates":[-119.28053300000001,46.285717],"type":"Point"}
}