{
  "type": "Feature",
  "properties": {
    "addr:full":"95 N Buck Way Coupeville WA 98239",
    "addr:housenumber":"95",
    "addr:postcode":"98239",
    "addr:street":"N Buck Way",
    "iso:country":"US",
    "sg:address":"95 N Buck Way",
    "sg:city":"Coupeville",
    "sg:classifiers":[
        {
            "category":"Social Services",
            "type":"Services"
        }
    ],
    "sg:phone":"+1 360 678 8854",
    "sg:postcode":"98239",
    "sg:province":"WA",
    "wof:name":"Sage Endeavors Inc",
    "wof:placetype":"venue"
},
  "geometry": {"coordinates":[-122.620994,48.212687],"type":"Point"}
}