{
  "type": "Feature",
  "properties": {
    "addr:full":"41310 214th Ave SE Enumclaw WA 98022",
    "addr:housenumber":"41310",
    "addr:postcode":"98022",
    "addr:street":"214Th Ave Se",
    "iso:country":"US",
    "sg:address":"41310 214th Ave SE",
    "sg:city":"Enumclaw",
    "sg:classifiers":[
        {
            "category":"Building & Trades",
            "subcategory":"Cleaning & Sanitation",
            "type":"Services"
        }
    ],
    "sg:phone":"+1 360 802 0187",
    "sg:postcode":"98022",
    "sg:province":"WA",
    "sg:tags":[
        "maintenance"
    ],
    "wof:name":"Blue Water Cleaning Services L",
    "wof:placetype":"venue"
},
  "geometry": {"coordinates":[-122.056309,47.231328],"type":"Point"}
}