{
  "type": "Feature",
  "properties": {
    "addr:full":"4500 7th Ave S Seattle WA 98108",
    "addr:housenumber":"4500",
    "addr:postcode":"98108",
    "addr:street":"7Th Ave S",
    "iso:country":"US",
    "sg:address":"4500 7th Ave S",
    "sg:city":"Seattle",
    "sg:classifiers":[
        {
            "category":"Wholesale",
            "subcategory":"Meat",
            "type":"Manufacturing & Wholesale Goods"
        },
        {
            "category":"Farming",
            "subcategory":"Poultry Farm",
            "type":"Manufacturing & Wholesale Goods"
        },
        {
            "category":"Food & Beverages",
            "subcategory":"Meat & Fish",
            "type":"Retail Goods"
        }
    ],
    "sg:phone":"+1 206 622 2622",
    "sg:postcode":"98108",
    "sg:province":"WA",
    "sg:tags":[
        "meat-wholesale",
        "shop",
        "poultry-wholesale"
    ],
    "sg:website":"www.plymouthpoultry.com",
    "wof:name":"Plymouth Poultry Co",
    "wof:placetype":"venue"
},
  "geometry": {"coordinates":[-122.32399700000001,47.562698],"type":"Point"}
}