{
  "type": "Feature",
  "properties": {
    "addr:full":"1345 N Bend Blvd N North Bend WA 98045",
    "addr:housenumber":"1345",
    "addr:postcode":"98045",
    "addr:street":"N Bend Blvd N",
    "iso:country":"US",
    "sg:address":"1345 N Bend Blvd N",
    "sg:city":"North Bend",
    "sg:classifiers":[
        {
            "category":"Education",
            "subcategory":"School",
            "type":"Public Place"
        }
    ],
    "sg:phone":"+1 425 888 9366",
    "sg:postcode":"98045",
    "sg:province":"WA",
    "wof:name":"Edwin R Opstad Elementary Schl",
    "wof:placetype":"venue"
},
  "geometry": {"coordinates":[-121.795118,47.502901],"type":"Point"}
}