{
  "type": "Feature",
  "properties": {
    "addr:full":"762 Stohr Rd Newport WA 99156",
    "addr:housenumber":"762",
    "addr:postcode":"99156",
    "addr:street":"Stohr Rd",
    "iso:country":"US",
    "sg:address":"762 Stohr Rd",
    "sg:city":"Newport",
    "sg:classifiers":[
        {
            "category":"Freight",
            "type":"Transportation"
        }
    ],
    "sg:phone":"+1 509 447 5230",
    "sg:postcode":"99156",
    "sg:province":"WA",
    "sg:tags":[
        "operator",
        "local",
        "trucking"
    ],
    "wof:name":"Worley Hauling",
    "wof:placetype":"venue"
},
  "geometry": {"coordinates":[-117.092472,48.1029],"type":"Point"}
}