{
  "type": "Feature",
  "properties": {
    "addr:full":"6846 Old Forest Ln SE Olympia WA 98501",
    "addr:housenumber":"6846",
    "addr:postcode":"98501",
    "addr:street":"Old Forest Ln Se",
    "iso:country":"US",
    "sg:address":"6846 Old Forest Ln SE",
    "sg:city":"Olympia",
    "sg:classifiers":[
        {
            "category":"Professional",
            "type":"Services"
        }
    ],
    "sg:phone":"+1 360 280 0446",
    "sg:postcode":"98501",
    "sg:province":"WA",
    "wof:name":"Riverwind Flyfishing",
    "wof:placetype":"venue"
},
  "geometry": {"coordinates":[-122.88146,46.986443],"type":"Point"}
}