{
  "type": "Feature",
  "properties": {
    "addr:full":"1963 Woodcock Rd Sequim WA 98382",
    "addr:housenumber":"1963",
    "addr:postcode":"98382",
    "addr:street":"Woodcock Rd",
    "iso:country":"US",
    "sg:address":"1963 Woodcock Rd",
    "sg:city":"Sequim",
    "sg:classifiers":[
        {
            "category":"Travel",
            "subcategory":"Hotels & Motels",
            "type":"Entertainment"
        }
    ],
    "sg:phone":"+1 360 683 7337",
    "sg:postcode":"98382",
    "sg:province":"WA",
    "wof:name":"Homestead Nw Sequim",
    "wof:placetype":"venue"
},
  "geometry": {"coordinates":[-123.174187,48.116112],"type":"Point"}
}