{
  "type": "Feature",
  "properties": {
    "addr:full":"11422 NE 124th St Kirkland WA 98034",
    "addr:housenumber":"11422",
    "addr:postcode":"98034",
    "addr:street":"Ne 124Th St",
    "iso:country":"US",
    "sg:address":"11422 NE 124th St",
    "sg:city":"Kirkland",
    "sg:classifiers":[
        {
            "category":"Restaurant",
            "type":"Food & Drink"
        }
    ],
    "sg:phone":"+1 425 820 3300",
    "sg:postcode":"98034",
    "sg:province":"WA",
    "sg:tags":[
        "pizza"
    ],
    "sg:website":"romios-pizzeria.com/",
    "wof:name":"Romio's Pizza & Pasta",
    "wof:placetype":"venue"
},
  "geometry": {"coordinates":[-122.18877999999999,47.711188],"type":"Point"}
}