{
  "type": "Feature",
  "properties": {
    "addr:full":"6970 California Ave SW Seattle WA 98136",
    "addr:housenumber":"6970",
    "addr:postcode":"98136",
    "addr:street":"California Ave Sw",
    "iso:country":"US",
    "sg:address":"6970 California Ave SW",
    "sg:city":"Seattle",
    "sg:classifiers":[
        {
            "category":"Real Estate",
            "subcategory":"Real Estate Operator",
            "type":"Services"
        }
    ],
    "sg:phone":"+1 206 938 5535",
    "sg:postcode":"98136",
    "sg:province":"WA",
    "sg:tags":[
        "building",
        "apartment"
    ],
    "wof:name":"Watermark At West Seattle",
    "wof:placetype":"venue"
},
  "geometry": {"coordinates":[-122.38718299999999,47.541267],"type":"Point"}
}