{
  "type": "Feature",
  "properties": {
    "addr:full":"15642 SE 139th Pl Renton WA 98059",
    "addr:postcode":"15642;98059",
    "addr:street":"Se 139Th Pl",
    "iso:country":"US",
    "sg:address":"15642 SE 139th Pl",
    "sg:city":"Renton",
    "sg:classifiers":[
        {
            "category":"Shopping",
            "subcategory":"Clothing, Apparel, & Fashions",
            "type":"Retail Goods"
        }
    ],
    "sg:phone":"+1 425 226 6594",
    "sg:postcode":"98059",
    "sg:province":"WA",
    "wof:name":"Embellishments",
    "wof:placetype":"venue"
},
  "geometry": {"coordinates":[-122.130318,47.477912],"type":"Point"}
}