{
  "type": "Feature",
  "properties": {
    "addr:full":"19709 68th Ave E Spanaway WA 98387",
    "addr:housenumber":"19709",
    "addr:postcode":"98387",
    "addr:street":"68Th Ave E",
    "iso:country":"US",
    "sg:address":"19709 68th Ave E",
    "sg:city":"Spanaway",
    "sg:classifiers":[
        {
            "category":"Freight",
            "type":"Transportation"
        }
    ],
    "sg:phone":"+1 253 875 8264",
    "sg:postcode":"98387",
    "sg:province":"WA",
    "sg:tags":[
        "operator",
        "local",
        "trucking"
    ],
    "wof:name":"Woolery Hulk Hauling",
    "wof:placetype":"venue"
},
  "geometry": {"coordinates":[-122.339066,47.076201],"type":"Point"}
}