{
  "type": "Feature",
  "properties": {
    "addr:full":"252 Engel Rd Oakesdale WA 99158",
    "addr:housenumber":"252",
    "addr:postcode":"99158",
    "addr:street":"Engel Rd",
    "iso:country":"US",
    "sg:address":"252 Engel Rd",
    "sg:city":"Oakesdale",
    "sg:phone":"+1 509 285 4129",
    "sg:postcode":"99158",
    "sg:province":"WA",
    "sg:tags":[
        "farm",
        "wheat"
    ],
    "wof:name":"Darrel E Engel",
    "wof:placetype":"venue"
},
  "geometry": {"coordinates":[-117.236504,47.21964],"type":"Point"}
}