{
  "type": "Feature",
  "properties": {
    "addr:full":"508 Forest Cir Lynden WA 98264",
    "addr:housenumber":"508",
    "addr:postcode":"98264",
    "addr:street":"Forest Cir",
    "iso:country":"US",
    "sg:address":"508 Forest Cir",
    "sg:city":"Lynden",
    "sg:classifiers":[
        {
            "category":"Professional",
            "type":"Services"
        }
    ],
    "sg:phone":"+1 360 318 0361",
    "sg:postcode":"98264",
    "sg:province":"WA",
    "wof:name":"House of Hope",
    "wof:placetype":"venue"
},
  "geometry": {"coordinates":[-122.481996,48.943004],"type":"Point"}
}