{
  "type": "Feature",
  "properties": {
    "addr:full":"1412 262nd Pl Ocean Park WA 98640",
    "addr:housenumber":"1412",
    "addr:postcode":"98640",
    "addr:street":"262Nd Pl;Park",
    "iso:country":"US",
    "sg:address":"1412 262nd Pl",
    "sg:city":"Ocean Park",
    "sg:classifiers":[
        {
            "category":"Organizations",
            "subcategory":"Community Association",
            "type":"Services"
        }
    ],
    "sg:phone":"+1 360 665 5846",
    "sg:postcode":"98640",
    "sg:province":"WA",
    "sg:tags":[
        "fraternal"
    ],
    "wof:name":"Ocean Park Eagles Lounge",
    "wof:placetype":"venue"
},
  "geometry": {"coordinates":[-124.05006,46.492324],"type":"Point"}
}