{
  "type": "Feature",
  "properties": {
    "addr:full":"7902 27th St W Tacoma WA 98466",
    "addr:housenumber":"7902",
    "addr:postcode":"98466",
    "addr:street":"27Th St W",
    "iso:country":"US",
    "sg:address":"7902 27th St W",
    "sg:city":"Tacoma",
    "sg:classifiers":[
        {
            "category":"Professional",
            "subcategory":"Management & Consulting",
            "type":"Services"
        }
    ],
    "sg:phone":"+1 253 536 1410",
    "sg:postcode":"98466",
    "sg:province":"WA",
    "wof:name":"H Plus Care",
    "wof:placetype":"venue"
},
  "geometry": {"coordinates":[-122.543706,47.23519],"type":"Point"}
}