{
  "type": "Feature",
  "properties": {
    "addr:full":"33600 US Hwy 97 Oroville WA 98844",
    "addr:postcode":"33600;98844",
    "addr:street":"Us Hwy 97",
    "iso:country":"US",
    "sg:address":"33600 US Hwy 97",
    "sg:city":"Oroville",
    "sg:classifiers":[
        {
            "category":"Real Estate",
            "subcategory":"Real Estate Agent",
            "type":"Services"
        }
    ],
    "sg:phone":"+1 509 476 4567",
    "sg:postcode":"98844",
    "sg:province":"WA",
    "wof:name":"Lakeforest Realty",
    "wof:placetype":"venue"
},
  "geometry": {"coordinates":[-119.458809,48.993829],"type":"Point"}
}