{
  "type": "Feature",
  "properties": {
    "addr:full":"11170 Ridge Rim Trl SE Port Orchard WA 98367",
    "addr:housenumber":"11170",
    "addr:postcode":"98367",
    "addr:street":"Ridge Rim Trl Se",
    "iso:country":"US",
    "sg:address":"11170 Ridge Rim Trl SE",
    "sg:city":"Port Orchard",
    "sg:classifiers":[
        {
            "category":"Farming",
            "subcategory":"Fish & Marine Products",
            "type":"Manufacturing & Wholesale Goods"
        }
    ],
    "sg:phone":"+1 360 876 8309",
    "sg:postcode":"98367",
    "sg:province":"WA",
    "sg:tags":[
        "fishing"
    ],
    "wof:name":"F/V Sound Star",
    "wof:placetype":"venue"
},
  "geometry": {"coordinates":[-122.64423600000001,47.44726],"type":"Point"}
}