{
  "type": "Feature",
  "properties": {
    "addr:full":"23224 34th Ave W Lynnwood WA 98036",
    "addr:housenumber":"23224",
    "addr:postcode":"98036",
    "addr:street":"34Th Ave W",
    "iso:country":"US",
    "sg:address":"23224 34th Ave W",
    "sg:city":"Lynnwood",
    "sg:classifiers":[
        {
            "category":"Wholesale",
            "subcategory":"Machinery & Supplies",
            "type":"Manufacturing & Wholesale Goods"
        }
    ],
    "sg:phone":"+1 425 776 0981",
    "sg:postcode":"98036",
    "sg:province":"WA",
    "sg:tags":[
        "equipment",
        "industrial"
    ],
    "wof:name":"Aj & Sons Inc",
    "wof:placetype":"venue"
},
  "geometry": {"coordinates":[-122.2788,47.784716],"type":"Point"}
}