{
  "type": "Feature",
  "properties": {
    "addr:full":"10009 Bridgeport Way SW Lakewood WA 98499",
    "addr:housenumber":"10009",
    "addr:postcode":"98499",
    "addr:street":"Bridgeport Way Sw",
    "iso:country":"US",
    "sg:address":"10009 Bridgeport Way SW",
    "sg:city":"Lakewood",
    "sg:classifiers":[
        {
            "category":"Shopping",
            "subcategory":"Mobile Phones",
            "type":"Retail Goods"
        }
    ],
    "sg:phone":"+1 253 588 4770",
    "sg:postcode":"98499",
    "sg:province":"WA",
    "wof:name":"Bayside Wireless",
    "wof:placetype":"venue"
},
  "geometry": {"coordinates":[-122.509103,47.166296],"type":"Point"}
}