{
  "type": "Feature",
  "properties": {
    "addr:full":"12371 Timber Ln Sedro Woolley WA 98284",
    "addr:housenumber":"12371",
    "addr:postcode":"98284",
    "addr:street":"Timber Ln",
    "iso:country":"US",
    "sg:address":"12371 Timber Ln",
    "sg:city":"Sedro Woolley",
    "sg:classifiers":[
        {
            "category":"Real Estate",
            "subcategory":"Real Estate Agent",
            "type":"Services"
        }
    ],
    "sg:phone":"+1 360 856 2258",
    "sg:postcode":"98284",
    "sg:province":"WA",
    "wof:name":"Janus Co",
    "wof:placetype":"venue"
},
  "geometry": {"coordinates":[-122.201928,48.465697],"type":"Point"}
}