{
  "type": "Feature",
  "properties": {
    "addr:full":"10008 NE 104th Ave Vancouver WA 98662",
    "addr:housenumber":"10008",
    "addr:postcode":"98662",
    "addr:street":"Ne 104Th Ave",
    "iso:country":"US",
    "sg:address":"10008 NE 104th Ave",
    "sg:city":"Vancouver",
    "sg:classifiers":[
        {
            "category":"Freight",
            "type":"Transportation"
        }
    ],
    "sg:phone":"+1 360 260 4554",
    "sg:postcode":"98662",
    "sg:province":"WA",
    "wof:name":"Asl Transport",
    "wof:placetype":"venue"
},
  "geometry": {"coordinates":[-122.566227,45.694655],"type":"Point"}
}