{
  "type": "Feature",
  "properties": {
    "addr:full":"16149 Redmond Way PMB 496 Redmond WA 98052",
    "addr:housenumber":"16149;496",
    "addr:postcode":"98052",
    "addr:street":"Redmond Way",
    "iso:country":"US",
    "sg:address":"16149 Redmond Way PMB 496",
    "sg:city":"Redmond",
    "sg:classifiers":[
        {
            "category":"Building & Trades",
            "subcategory":"Equipment Rental",
            "type":"Services"
        }
    ],
    "sg:phone":"+1 425 885 4717",
    "sg:postcode":"98052",
    "sg:province":"WA",
    "sg:tags":[
        "supply",
        "contractor"
    ],
    "wof:name":"Nelson Tool & Equipment Llc",
    "wof:placetype":"venue"
},
  "geometry": {"coordinates":[-122.124841,47.674729],"type":"Point"}
}