{
  "type": "Feature",
  "properties": {
    "addr:full":"6900 State Rte 9 Sedro Woolley WA 98284",
    "addr:housenumber":"6900",
    "addr:postcode":"98284",
    "addr:street":"State Rte 9",
    "iso:country":"US",
    "sg:address":"6900 State Rte 9",
    "sg:city":"Sedro Woolley",
    "sg:classifiers":[
        {
            "category":"Shopping",
            "subcategory":"Hobbies, Toys, & Games",
            "type":"Retail Goods"
        }
    ],
    "sg:phone":"+1 360 856 4695",
    "sg:postcode":"98284",
    "sg:province":"WA",
    "wof:name":"Discovery Toys",
    "wof:placetype":"venue"
},
  "geometry": {"coordinates":[-122.225622,48.545153],"type":"Point"}
}