{
  "type": "Feature",
  "properties": {
    "addr:full":"317 NW Gilman Blvd Issaquah WA 98027",
    "addr:housenumber":"317",
    "addr:postcode":"98027",
    "addr:street":"Nw Gilman Blvd",
    "iso:country":"US",
    "sg:address":"317 NW Gilman Blvd",
    "sg:city":"Issaquah",
    "sg:classifiers":[
        {
            "category":"Sports & Exercise",
            "subcategory":"Gym",
            "type":"Entertainment"
        }
    ],
    "sg:phone":"+1 425 837 8710",
    "sg:postcode":"98027",
    "sg:province":"WA",
    "sg:tags":[
        "spa",
        "days"
    ],
    "wof:name":"Pelage Spa & Skin Center",
    "wof:placetype":"venue"
},
  "geometry": {"coordinates":[-122.03939800000001,47.539675],"type":"Point"}
}