{
  "type": "Feature",
  "properties": {
    "addr:full":"6006 E 8th Ave Spokane Valley WA 99212",
    "addr:housenumber":"6006",
    "addr:postcode":"99212",
    "addr:street":"E 8Th Ave",
    "iso:country":"US",
    "sg:address":"6006 E 8th Ave",
    "sg:city":"Spokane Valley",
    "sg:classifiers":[
        {
            "category":"Organizations",
            "subcategory":"Religious Organization",
            "type":"Services"
        }
    ],
    "sg:phone":"+1 509 534 0782",
    "sg:postcode":"99212",
    "sg:province":"WA",
    "sg:tags":[
        "church"
    ],
    "wof:name":"Valley View Baptist Church",
    "wof:placetype":"venue"
},
  "geometry": {"coordinates":[-117.32302300000001,47.649732],"type":"Point"}
}