{
  "type": "Feature",
  "properties": {
    "addr:full":"230 G St SW Issaquah WA 98001",
    "addr:housenumber":"230",
    "addr:postcode":"98001",
    "addr:street":"G St Sw",
    "iso:country":"US",
    "sg:address":"230 G St SW",
    "sg:city":"Issaquah",
    "sg:classifiers":[
        {
            "category":"Professional",
            "subcategory":"Business Services",
            "type":"Services"
        }
    ],
    "sg:phone":"+1 425 894 9849",
    "sg:postcode":"98001",
    "sg:province":"WA",
    "wof:name":"Anderson Residential",
    "wof:placetype":"venue"
},
  "geometry": {"coordinates":[-122.237934,47.306264],"type":"Point"}
}