{
  "type": "Feature",
  "properties": {
    "addr:full":"515 2nd St Snohomish WA 98290",
    "addr:housenumber":"515",
    "addr:postcode":"98290",
    "addr:street":"2Nd St",
    "iso:country":"US",
    "sg:address":"515 2nd St",
    "sg:city":"Snohomish",
    "sg:classifiers":[
        {
            "category":"Restaurant",
            "type":"Food & Drink"
        }
    ],
    "sg:phone":"+1 360 568 4522",
    "sg:postcode":"98290",
    "sg:province":"WA",
    "sg:tags":[
        "mexican"
    ],
    "wof:name":"Ixtapa Restaurant",
    "wof:placetype":"venue"
},
  "geometry": {"coordinates":[-122.087947,47.912713],"type":"Point"}
}