{
  "type": "Feature",
  "properties": {
    "addr:full":"3599 E Ainsworth St Pasco WA 99301",
    "addr:housenumber":"3599",
    "addr:postcode":"99301",
    "addr:street":"E Ainsworth St",
    "iso:country":"US",
    "sg:address":"3599 E Ainsworth St",
    "sg:city":"Pasco",
    "sg:classifiers":[
        {
            "category":"Wholesale",
            "subcategory":"Farm Supplies",
            "type":"Manufacturing & Wholesale Goods"
        }
    ],
    "sg:phone":"+1 509 543 7100",
    "sg:postcode":"99301",
    "sg:province":"WA",
    "sg:tags":[
        "grain"
    ],
    "wof:name":"James Farrell & Co",
    "wof:placetype":"venue"
},
  "geometry": {"coordinates":[-119.054346,46.211255],"type":"Point"}
}