{
  "type": "Feature",
  "properties": {
    "addr:full":"22022 6th Ave S Des Moines WA 98198",
    "addr:housenumber":"22022",
    "addr:postcode":"98198",
    "addr:street":"6Th Ave S",
    "iso:country":"US",
    "sg:address":"22022 6th Ave S",
    "sg:city":"Des Moines",
    "sg:classifiers":[
        {
            "category":"Real Estate",
            "subcategory":"Real Estate Operator",
            "type":"Services"
        }
    ],
    "sg:phone":"+1 206 824 2463",
    "sg:postcode":"98198",
    "sg:province":"WA",
    "sg:tags":[
        "apartment"
    ],
    "wof:name":"El Mirador Apartments",
    "wof:placetype":"venue"
},
  "geometry": {"coordinates":[-122.327269,47.403276],"type":"Point"}
}