{
  "type": "Feature",
  "properties": {
    "addr:full":"3912 W Nob Hill Blvd Yakima WA 98902",
    "addr:housenumber":"3912",
    "addr:postcode":"98902",
    "addr:street":"W Nob Hill Blvd",
    "iso:country":"US",
    "sg:address":"3912 W Nob Hill Blvd",
    "sg:city":"Yakima",
    "sg:classifiers":[
        {
            "category":"Restaurant",
            "type":"Food & Drink"
        }
    ],
    "sg:phone":"+1 509 965 7890",
    "sg:postcode":"98902",
    "sg:province":"WA",
    "sg:tags":[
        "eating"
    ],
    "wof:name":"Arctic Circle",
    "wof:placetype":"venue"
},
  "geometry": {"coordinates":[-120.561882,46.585347],"type":"Point"}
}