{
  "type": "Feature",
  "properties": {
    "addr:full":"8024 S Tacoma Way Tacoma WA 98499",
    "addr:housenumber":"8024",
    "addr:postcode":"98499",
    "addr:street":"S Tacoma Way",
    "iso:country":"US",
    "sg:address":"8024 S Tacoma Way",
    "sg:city":"Tacoma",
    "sg:classifiers":[
        {
            "category":"Shopping",
            "subcategory":"Music",
            "type":"Retail Goods"
        }
    ],
    "sg:phone":"+1 253 581 7947",
    "sg:postcode":"98499",
    "sg:province":"WA",
    "sg:tags":[
        "compact",
        "record",
        "disc",
        "tape"
    ],
    "wof:name":"Golden Oldies Records Tapes",
    "wof:placetype":"venue"
},
  "geometry": {"coordinates":[-122.48375,47.185034],"type":"Point"}
}