{
  "type": "Feature",
  "properties": {
    "addr:full":"1563 6th Ave Seattle WA 98101",
    "addr:housenumber":"1563",
    "addr:postcode":"98101",
    "addr:street":"6Th Ave",
    "iso:country":"US",
    "sg:address":"1563 6th Ave",
    "sg:city":"Seattle",
    "sg:classifiers":[
        {
            "category":"Professional",
            "subcategory":"Detective & Security Services",
            "type":"Services"
        }
    ],
    "sg:phone":"+1 206 623 0758",
    "sg:postcode":"98101",
    "sg:province":"WA",
    "sg:tags":[
        "car",
        "armored"
    ],
    "wof:name":"Brink's Inc",
    "wof:placetype":"venue"
},
  "geometry": {"coordinates":[-122.33500100000001,47.61141],"type":"Point"}
}