{
  "type": "Feature",
  "properties": {
    "iso:country":"US",
    "sg:address":"1012 170th Pl NE",
    "sg:city":"Bellevue",
    "sg:classifiers":[
        {
            "category":"Professional",
            "subcategory":"Art Services",
            "type":"Services"
        }
    ],
    "sg:phone":"+1 425 746 4558",
    "sg:postcode":"98008",
    "sg:province":"WA",
    "sg:tags":[
        "photo",
        "photography",
        "commercial",
        "studio",
        "portrait"
    ],
    "wof:name":"Richard Bush Photography Inc",
    "wof:placetype":"venue"
},
  "geometry": {"coordinates":[-122.114318,47.617866],"type":"Point"}
}