{
  "type": "Feature",
  "properties": {
    "addr:full":"2715 152nd Ave NE Redmond WA 98052",
    "addr:housenumber":"2715",
    "addr:postcode":"98052",
    "addr:street":"152Nd Ave Ne",
    "iso:country":"US",
    "sg:address":"2715 152nd Ave NE",
    "sg:city":"Redmond",
    "sg:classifiers":[
        {
            "category":"Shopping",
            "subcategory":"Computers & Home Electronics",
            "type":"Retail Goods"
        },
        {
            "category":"Professional",
            "subcategory":"Computer Services",
            "type":"Services"
        }
    ],
    "sg:phone":"+1 425 881 5353",
    "sg:postcode":"98052",
    "sg:province":"WA",
    "sg:tags":[
        "leasing"
    ],
    "sg:website":"www.bitbybit.com",
    "wof:name":"Bit-by-Bit Computers Rentals",
    "wof:placetype":"venue"
},
  "geometry": {"coordinates":[-122.13800000000001,47.634899],"type":"Point"}
}