{
  "type": "Feature",
  "properties": {
    "addr:full":"5601 E 18th St Ste 302 Vancouver WA 98661",
    "addr:housenumber":"5601",
    "addr:postcode":"98661",
    "addr:street":"E 18Th St Ste 302",
    "iso:country":"US",
    "sg:address":"5601 E 18th St Ste 302",
    "sg:city":"Vancouver",
    "sg:classifiers":[
        {
            "category":"Sports & Exercise",
            "subcategory":"Playing Field",
            "type":"Entertainment"
        }
    ],
    "sg:postcode":"98661",
    "sg:province":"WA",
    "sg:tags":[
        "instruction",
        "fitness"
    ],
    "sg:website":"www.crossfitepiphany.com/",
    "wof:name":"CrossFit Epiphany",
    "wof:placetype":"venue"
},
  "geometry": {"coordinates":[-122.613822,45.634774],"type":"Point"}
}