{
  "type": "Feature",
  "properties": {
    "addr:full":"9405 Markworth Rd Blaine WA 98230",
    "addr:housenumber":"9405",
    "addr:postcode":"98230",
    "addr:street":"Markworth Rd",
    "iso:country":"US",
    "sg:address":"9405 Markworth Rd",
    "sg:city":"Blaine",
    "sg:classifiers":[
        {
            "category":"Farming",
            "subcategory":"Dairy Farm",
            "type":"Manufacturing & Wholesale Goods"
        }
    ],
    "sg:phone":"+1 360 354 7415",
    "sg:postcode":"98230",
    "sg:province":"WA",
    "wof:name":"T Bar T",
    "wof:placetype":"venue"
},
  "geometry": {"coordinates":[-122.552159,48.980176],"type":"Point"}
}