{
  "type": "Feature",
  "properties": {
    "addr:full":"710 SE Fidalgo Ave Oak Harbor WA 98277",
    "addr:housenumber":"710",
    "addr:postcode":"98277",
    "addr:street":"Se Fidalgo Ave",
    "iso:country":"US",
    "sg:address":"710 SE Fidalgo Ave",
    "sg:city":"Oak Harbor",
    "sg:classifiers":[
        {
            "category":"Personal",
            "subcategory":"Beauty Salon",
            "type":"Services"
        }
    ],
    "sg:phone":"+1 360 675 8412",
    "sg:postcode":"98277",
    "sg:province":"WA",
    "wof:name":"Electric Beach",
    "wof:placetype":"venue"
},
  "geometry": {"coordinates":[-122.64733099999999,48.289407],"type":"Point"}
}