{
  "type": "Feature",
  "properties": {
    "addr:full":"6409 S 194th St Kent WA 98032",
    "addr:housenumber":"6409",
    "addr:postcode":"98032",
    "addr:street":"S 194Th St",
    "iso:country":"US",
    "sg:address":"6409 S 194th St",
    "sg:city":"Kent",
    "sg:classifiers":[
        {
            "category":"Wholesale",
            "subcategory":"Metals & Minerals",
            "type":"Manufacturing & Wholesale Goods"
        }
    ],
    "sg:phone":"+1 253 872 5700",
    "sg:postcode":"98032",
    "sg:province":"WA",
    "sg:tags":[
        "alloy",
        "aircraft"
    ],
    "wof:name":"Tiernay Metals",
    "wof:placetype":"venue"
},
  "geometry": {"coordinates":[-122.251355,47.428426],"type":"Point"}
}