{
  "type": "Feature",
  "properties": {
    "addr:full":"7733 Bagley Avenue N Seattle WA 98103",
    "addr:housenumber":"7733",
    "addr:postcode":"98103",
    "addr:street":"Bagley Avenue N",
    "iso:country":"US",
    "sg:address":"7733 Bagley Avenue N",
    "sg:city":"Seattle",
    "sg:classifiers":[
        {
            "category":"Building & Trades",
            "subcategory":"Construction",
            "type":"Services"
        }
    ],
    "sg:phone":"+1 206 525 4330",
    "sg:postcode":"98103",
    "sg:province":"WA",
    "sg:tags":[
        "contractor"
    ],
    "wof:name":"Arnott Construction",
    "wof:placetype":"venue"
},
  "geometry": {"coordinates":[-122.331738,47.686024],"type":"Point"}
}