{
  "type": "Feature",
  "properties": {
    "addr:full":"1452 Camp David Junior Rd Port Angeles WA 98363",
    "addr:housenumber":"1452",
    "addr:postcode":"98363",
    "addr:street":"Camp;Junior Rd",
    "iso:country":"US",
    "sg:address":"1452 Camp David Junior Rd",
    "sg:city":"Port Angeles",
    "sg:classifiers":[
        {
            "category":"Recreation",
            "type":"Entertainment"
        }
    ],
    "sg:phone":"+1 360 928 3540",
    "sg:postcode":"98363",
    "sg:province":"WA",
    "sg:tags":[
        "parks"
    ],
    "wof:name":"Camp David Jr",
    "wof:placetype":"venue"
},
  "geometry": {"coordinates":[-123.875575,48.066043],"type":"Point"}
}