{
  "type": "Feature",
  "properties": {
    "addr:full":"10548 Fifth Ave NE Seattle WA 98125",
    "addr:housenumber":"10548",
    "addr:postcode":"98125",
    "addr:street":"Fifth Ave Ne",
    "iso:country":"US",
    "sg:address":"10548 Fifth Ave NE",
    "sg:city":"Seattle",
    "sg:classifiers":[
        {
            "category":"Education",
            "subcategory":"Library",
            "type":"Public Place"
        }
    ],
    "sg:phone":"+1 206 386 1980",
    "sg:postcode":"98125",
    "sg:province":"WA",
    "wof:name":"Seattle Public Library - Northgate Branch",
    "wof:placetype":"venue"
},
  "geometry": {"coordinates":[-122.323013,47.705589],"type":"Point"}
}