{
  "type": "Feature",
  "properties": {
    "addr:full":"30520 379th Ave NE Arlington WA 98223",
    "addr:housenumber":"30520",
    "addr:postcode":"98223",
    "addr:street":"379Th Ave Ne",
    "iso:country":"US",
    "sg:address":"30520 379th Ave NE",
    "sg:city":"Arlington",
    "sg:classifiers":[
        {
            "category":"Farming",
            "subcategory":"Farm & Veterinary Services",
            "type":"Manufacturing & Wholesale Goods"
        }
    ],
    "sg:phone":"+1 360 403 0797",
    "sg:postcode":"98223",
    "sg:province":"WA",
    "sg:tags":[
        "livestock"
    ],
    "wof:name":"Alder Ridge Ranch",
    "wof:placetype":"venue"
},
  "geometry": {"coordinates":[-121.717483,48.272394],"type":"Point"}
}