{
  "type": "Feature",
  "properties": {
    "addr:full":"401 Broadway Tacoma WA 98402",
    "addr:housenumber":"401",
    "addr:postcode":"98402",
    "addr:street":"Broadway",
    "iso:country":"US",
    "sg:address":"401 Broadway",
    "sg:city":"Tacoma",
    "sg:classifiers":[
        {
            "category":"Social Services",
            "subcategory":"Job Training",
            "type":"Services"
        }
    ],
    "sg:phone":"+1 253 428 0133",
    "sg:postcode":"98402",
    "sg:province":"WA",
    "sg:tags":[
        "career",
        "counseling",
        "vocational"
    ],
    "wof:name":"True Directions Career",
    "wof:placetype":"venue"
},
  "geometry": {"coordinates":[-122.444812,47.262595],"type":"Point"}
}