{
  "type": "Feature",
  "properties": {
    "iso:country":"US",
    "sg:address":"226 N 1st St",
    "sg:city":"Shelton",
    "sg:classifiers":[
        {
            "category":"Shopping",
            "subcategory":"Computers & Home Electronics",
            "type":"Retail Goods"
        }
    ],
    "sg:phone":"+1 360 427 4360",
    "sg:postcode":"98584",
    "sg:province":"WA",
    "sg:tags":[
        "dish",
        "equipment",
        "satellite",
        "system"
    ],
    "wof:name":"Cable Tech Systems",
    "wof:placetype":"venue"
},
  "geometry": {"coordinates":[-123.09974,47.214329],"type":"Point"}
}