{
  "type": "Feature",
  "properties": {
    "addr:full":"2041 148th Ave NE Bellevue WA 98007",
    "addr:housenumber":"2041",
    "addr:postcode":"98007",
    "addr:street":"148Th Ave Ne",
    "iso:country":"US",
    "sg:address":"2041 148th Ave NE",
    "sg:city":"Bellevue",
    "sg:classifiers":[
        {
            "category":"Building & Trades",
            "subcategory":"Locksmith",
            "type":"Services"
        }
    ],
    "sg:phone":"+1 425 865 9779",
    "sg:postcode":"98007",
    "sg:province":"WA",
    "sg:tags":[
        "key"
    ],
    "wof:name":"Overlake Lock & Key",
    "wof:placetype":"venue"
},
  "geometry": {"coordinates":[-122.14299800000001,47.627899],"type":"Point"}
}