{
  "type": "Feature",
  "properties": {
    "addr:full":"103 W Main Ave Ritzville WA 99169",
    "addr:housenumber":"103",
    "addr:postcode":"99169",
    "addr:street":"W Main Ave",
    "iso:country":"US",
    "sg:address":"103 W Main Ave",
    "sg:city":"Ritzville",
    "sg:classifiers":[
        {
            "category":"Professional",
            "subcategory":"Accounting & Tax Preparation",
            "type":"Services"
        }
    ],
    "sg:phone":"+1 509 659 1922",
    "sg:postcode":"99169",
    "sg:province":"WA",
    "sg:tags":[
        "accountant"
    ],
    "wof:name":"Mc Dirmid Mikkelsen & Secrest",
    "wof:placetype":"venue"
},
  "geometry": {"coordinates":[-118.37993400000001,47.127468],"type":"Point"}
}