{
  "type": "Feature",
  "properties": {
    "addr:full":"2021 Boulevard Rd SE Olympia WA 98501",
    "addr:housenumber":"2021",
    "addr:postcode":"olympia;98501",
    "addr:street":"Boulevard Rd Se",
    "iso:country":"US",
    "sg:address":"2021 Boulevard Rd SE",
    "sg:city":"Olympia",
    "sg:classifiers":[
        {
            "category":"Wholesale",
            "subcategory":"Plants",
            "type":"Manufacturing & Wholesale Goods"
        }
    ],
    "sg:phone":"+1 360 352 1728",
    "sg:postcode":"98501",
    "sg:province":"WA",
    "sg:tags":[
        "nursery"
    ],
    "wof:name":"Boulevard Nursery",
    "wof:placetype":"venue"
},
  "geometry": {"coordinates":[-122.865787,47.032517],"type":"Point"}
}