{
  "type": "Feature",
  "properties": {
    "addr:full":"1206 E Wheeler Rd Moses Lake WA 98837",
    "addr:housenumber":"1206",
    "addr:postcode":"98837",
    "addr:street":"E Wheeler Rd",
    "iso:country":"US",
    "sg:address":"1206 E Wheeler Rd",
    "sg:city":"Moses Lake",
    "sg:classifiers":[
        {
            "category":"Building & Trades",
            "subcategory":"Construction",
            "type":"Services"
        }
    ],
    "sg:phone":"+1 509 765 7582",
    "sg:postcode":"98837",
    "sg:province":"WA",
    "sg:tags":[
        "fire",
        "restoration",
        "damage"
    ],
    "wof:name":"Service Master Cleaning/Rstrtn",
    "wof:placetype":"venue"
},
  "geometry": {"coordinates":[-119.25720699999999,47.131196],"type":"Point"}
}