{
  "type": "Feature",
  "properties": {
    "addr:full":"2802 Shannon Point Rd Anacortes WA 98221",
    "addr:housenumber":"2802",
    "addr:postcode":"98221",
    "addr:street":"Shannon Point Rd",
    "iso:country":"US",
    "sg:address":"2802 Shannon Point Rd",
    "sg:city":"Anacortes",
    "sg:classifiers":[
        {
            "category":"Farming",
            "subcategory":"Farm & Veterinary Services",
            "type":"Manufacturing & Wholesale Goods"
        }
    ],
    "sg:phone":"+1 360 848 1338",
    "sg:postcode":"98221",
    "sg:province":"WA",
    "sg:tags":[
        "crop"
    ],
    "wof:name":"Aqua Solutions",
    "wof:placetype":"venue"
},
  "geometry": {"coordinates":[-122.68377,48.499695],"type":"Point"}
}