{
  "type": "Feature",
  "properties": {
    "addr:full":"351 Lynch Ln Yakima WA 98903",
    "addr:housenumber":"351",
    "addr:postcode":"98903",
    "addr:street":"Lynch Ln",
    "iso:country":"US",
    "sg:address":"351 Lynch Ln",
    "sg:city":"Yakima",
    "sg:classifiers":[
        {
            "category":"Farming",
            "subcategory":"Livestock Farm",
            "type":"Manufacturing & Wholesale Goods"
        }
    ],
    "sg:phone":"+1 509 966 0972",
    "sg:postcode":"98903",
    "sg:province":"WA",
    "sg:tags":[
        "beef",
        "feedlot",
        "cattle"
    ],
    "wof:name":"Umbrella Ranch",
    "wof:placetype":"venue"
},
  "geometry": {"coordinates":[-120.739512,46.53482],"type":"Point"}
}