{
  "type": "Feature",
  "properties": {
    "addr:full":"14144 Hillwood Dr Bow WA 98232",
    "addr:housenumber":"14144",
    "addr:postcode":"98232",
    "addr:street":"Hillwood Dr",
    "iso:country":"US",
    "sg:address":"14144 Hillwood Dr",
    "sg:city":"Bow",
    "sg:classifiers":[
        {
            "category":"Building & Trades",
            "subcategory":"Construction",
            "type":"Services"
        }
    ],
    "sg:phone":"+1 360 757 0404",
    "sg:postcode":"98232",
    "sg:province":"WA",
    "sg:tags":[
        "house",
        "con"
    ],
    "wof:name":"Skagit Drywall Inc",
    "wof:placetype":"venue"
},
  "geometry": {"coordinates":[-122.441723,48.508543],"type":"Point"}
}