{
  "type": "Feature",
  "properties": {
    "addr:full":"18228 Tualco Rd Monroe WA 98272",
    "addr:housenumber":"18228",
    "addr:postcode":"98272",
    "addr:street":"Tualco Rd",
    "iso:country":"US",
    "sg:address":"18228 Tualco Rd",
    "sg:city":"Monroe",
    "sg:classifiers":[
        {
            "category":"Farming",
            "subcategory":"Berry Farm",
            "type":"Manufacturing & Wholesale Goods"
        }
    ],
    "sg:phone":"+1 360 794 7917",
    "sg:postcode":"98272",
    "sg:province":"WA",
    "sg:tags":[
        "raspberry"
    ],
    "wof:name":"Broers Farm Inc",
    "wof:placetype":"venue"
},
  "geometry": {"coordinates":[-121.975894,47.83216],"type":"Point"}
}