{
  "type": "Feature",
  "properties": {
    "addr:full":"21823 30th Dr SE Bothell WA 98021",
    "addr:housenumber":"21823",
    "addr:postcode":"98021",
    "addr:street":"30Th Dr Se",
    "iso:country":"US",
    "sg:address":"21823 30th Dr SE",
    "sg:city":"Bothell",
    "sg:classifiers":[
        {
            "category":"Wholesale",
            "subcategory":"Drugs",
            "type":"Manufacturing & Wholesale Goods"
        }
    ],
    "sg:phone":"+1 425 527 2703",
    "sg:postcode":"98021",
    "sg:province":"WA",
    "sg:tags":[
        "pharmaceutical"
    ],
    "wof:name":"Alder Biopharmaceuticals Inc",
    "wof:placetype":"venue"
},
  "geometry": {"coordinates":[-122.195592,47.79879],"type":"Point"}
}