{
  "type": "Feature",
  "properties": {
    "addr:full":"217 Pine St Okanogan WA 98840",
    "addr:housenumber":"217",
    "addr:postcode":"98840",
    "addr:street":"Pine St",
    "iso:country":"US",
    "sg:address":"217 Pine St",
    "sg:city":"Okanogan",
    "sg:classifiers":[
        {
            "category":"Insurance",
            "subcategory":"Insurance Agent",
            "type":"Services"
        }
    ],
    "sg:phone":"+1 509 422 1456",
    "sg:postcode":"98840",
    "sg:province":"WA",
    "wof:name":"State Farm Insurance",
    "wof:placetype":"venue"
},
  "geometry": {"coordinates":[-119.581547,48.364285],"type":"Point"}
}