{
  "type": "Feature",
  "properties": {
    "addr:full":"30519 Finn Settlement Rd Arlington WA 98223",
    "addr:postcode":"30519;98223",
    "addr:street":"Finn Settlement Rd",
    "iso:country":"US",
    "sg:address":"30519 Finn Settlement Rd",
    "sg:city":"Arlington",
    "sg:classifiers":[
        {
            "category":"Shopping",
            "type":"Retail Goods"
        }
    ],
    "sg:phone":"+1 360 435 7415",
    "sg:postcode":"98223",
    "sg:province":"WA",
    "sg:tags":[
        "art",
        "gallery",
        "dealer"
    ],
    "sg:website":"www.kurtmcvayartglass.com",
    "wof:name":"Kurt Mc Vay Art Glass",
    "wof:placetype":"venue"
},
  "geometry": {"coordinates":[-122.16877599999999,48.271898],"type":"Point"}
}