{
  "type": "Feature",
  "properties": {
    "addr:full":"14010 NE Airport Dr Vancouver WA 98684",
    "addr:housenumber":"14010",
    "addr:postcode":"98684",
    "addr:street":"Ne Airport Dr",
    "iso:country":"US",
    "sg:address":"14010 NE Airport Dr",
    "sg:city":"Vancouver",
    "sg:classifiers":[
        {
            "category":"Professional",
            "type":"Services"
        }
    ],
    "sg:phone":"+1 360 883 3927",
    "sg:postcode":"98684",
    "sg:province":"WA",
    "wof:name":"Bryan Geophysical LLC",
    "wof:placetype":"venue"
},
  "geometry": {"coordinates":[-122.528486,45.623069],"type":"Point"}
}