{
  "type": "Feature",
  "properties": {
    "addr:full":"206 Euclid St Grandview WA 98930",
    "addr:housenumber":"206",
    "addr:postcode":"98930",
    "addr:street":"Euclid St",
    "iso:country":"US",
    "sg:address":"206 Euclid St",
    "sg:city":"Grandview",
    "sg:classifiers":[
        {
            "category":"Food & Beverages",
            "subcategory":"Groceries & Convenience Stores",
            "type":"Retail Goods"
        }
    ],
    "sg:phone":"+1 509 882 1900",
    "sg:postcode":"98930",
    "sg:province":"WA",
    "sg:tags":[
        "grocer"
    ],
    "wof:name":"Grandview Market Place",
    "wof:placetype":"venue"
},
  "geometry": {"coordinates":[-119.915655,46.253815],"type":"Point"}
}