{
  "type": "Feature",
  "properties": {
    "addr:full":"3035 37th Ave SW Tumwater WA 98512",
    "addr:housenumber":"3035",
    "addr:postcode":"98512",
    "addr:street":"37Th Ave Sw",
    "iso:country":"US",
    "sg:address":"3035 37th Ave SW",
    "sg:city":"Tumwater",
    "sg:classifiers":[
        {
            "category":"Wholesale",
            "subcategory":"Groceries",
            "type":"Manufacturing & Wholesale Goods"
        }
    ],
    "sg:phone":"+1 360 352 4121",
    "sg:postcode":"98512",
    "sg:province":"WA",
    "sg:tags":[
        "tea",
        "coffee"
    ],
    "wof:name":"Raven's Brew Coffee Inc",
    "wof:placetype":"venue"
},
  "geometry": {"coordinates":[-122.946478,47.013484],"type":"Point"}
}