{
  "type": "Feature",
  "properties": {
    "addr:full":"415 NE 95th St Seattle WA 98115",
    "addr:housenumber":"415",
    "addr:postcode":"98115",
    "addr:street":"Ne 95Th St",
    "iso:country":"US",
    "sg:address":"415 NE 95th St",
    "sg:city":"Seattle",
    "sg:classifiers":[
        {
            "category":"Wholesale",
            "subcategory":"Durable Goods & Equipment",
            "type":"Manufacturing & Wholesale Goods"
        }
    ],
    "sg:phone":"+1 206 527 8115",
    "sg:postcode":"98115",
    "sg:province":"WA",
    "sg:tags":[
        "exporter"
    ],
    "wof:name":"Amkor International Corp",
    "wof:placetype":"venue"
},
  "geometry": {"coordinates":[-122.323441,47.697619],"type":"Point"}
}