{
  "type": "Feature",
  "properties": {
    "addr:full":"907 Vandercook Way Longview WA 98632",
    "addr:housenumber":"907",
    "addr:postcode":"98632",
    "addr:street":"Vandercook Way",
    "iso:country":"US",
    "sg:address":"907 Vandercook Way",
    "sg:city":"Longview",
    "sg:classifiers":[
        {
            "category":"Banks & Credit Unions",
            "subcategory":"Bank",
            "type":"Services"
        }
    ],
    "sg:phone":"+1 360 577 6672",
    "sg:postcode":"98632",
    "sg:province":"WA",
    "sg:tags":[
        "broker",
        "mortgage"
    ],
    "wof:name":"Aim Mail Centers",
    "wof:placetype":"venue"
},
  "geometry": {"coordinates":[-122.92806,46.142825],"type":"Point"}
}