{
  "type": "Feature",
  "properties": {
    "addr:full":"610 N Mission St Wenatchee WA 98801",
    "addr:housenumber":"610",
    "addr:postcode":"98801",
    "addr:street":"N Mission St",
    "iso:country":"US",
    "sg:address":"610 N Mission St",
    "sg:city":"Wenatchee",
    "sg:classifiers":[
        {
            "category":"Professional",
            "subcategory":"Lawyer & Legal Services",
            "type":"Services"
        }
    ],
    "sg:phone":"+1 509 663 0488",
    "sg:postcode":"98801",
    "sg:province":"WA",
    "wof:name":"Sandra Gaycordell Pf",
    "wof:placetype":"venue"
},
  "geometry": {"coordinates":[-120.318108,47.43074],"type":"Point"}
}