{
  "type": "Feature",
  "properties": {
    "addr:full":"2314 Old Hwy 99 S Mount Vernon WA 98273",
    "addr:housenumber":"2314",
    "addr:postcode":"98273",
    "addr:street":"Old Hwy 99 S",
    "iso:country":"US",
    "sg:address":"2314 Old Hwy 99 S",
    "sg:city":"Mount Vernon",
    "sg:classifiers":[
        {
            "category":"Building & Trades",
            "subcategory":"Equipment Rental",
            "type":"Services"
        }
    ],
    "sg:phone":"+1 360 424 1787",
    "sg:postcode":"98273",
    "sg:province":"WA",
    "sg:tags":[
        "toilet",
        "portable",
        "lease"
    ],
    "wof:name":"AAA Rent A Potty",
    "wof:placetype":"venue"
},
  "geometry": {"coordinates":[-122.335427,48.40396],"type":"Point"}
}