{
  "type": "Feature",
  "properties": {
    "addr:full":"2111 S 90th St Tacoma WA 98444",
    "addr:housenumber":"2111",
    "addr:postcode":"98444",
    "addr:street":"S 90Th St",
    "iso:country":"US",
    "sg:address":"2111 S 90th St",
    "sg:city":"Tacoma",
    "sg:classifiers":[
        {
            "category":"Health Services",
            "subcategory":"Doctor",
            "type":"Services"
        }
    ],
    "sg:phone":"+1 253 539 9700",
    "sg:postcode":"98444",
    "sg:province":"WA",
    "sg:tags":[
        "family",
        "practice",
        "internal",
        "gynecologist",
        "medicine",
        "obstetrician"
    ],
    "sg:website":"www.fhshealth.org",
    "wof:name":"Franciscan Medical Group",
    "wof:placetype":"venue"
},
  "geometry": {"coordinates":[-122.464996,47.1749],"type":"Point"}
}