{
  "type": "Feature",
  "properties": {
    "addr:full":"5408 Koufax Ln Pasco WA 99301",
    "addr:housenumber":"5408",
    "addr:postcode":"99301",
    "addr:street":"Koufax Ln",
    "iso:country":"US",
    "sg:address":"5408 Koufax Ln",
    "sg:city":"Pasco",
    "sg:classifiers":[
        {
            "category":"Shopping",
            "subcategory":"Gifts & Souvenirs",
            "type":"Retail Goods"
        }
    ],
    "sg:phone":"+1 509 542 1098",
    "sg:postcode":"99301",
    "sg:province":"WA",
    "wof:name":"SD Gift & Design",
    "wof:placetype":"venue"
},
  "geometry": {"coordinates":[-119.178394,46.27706],"type":"Point"}
}