{
  "type": "Feature",
  "properties": {
    "addr:full":"715 S 6th Ave Yakima WA 98902",
    "addr:housenumber":"715",
    "addr:postcode":"98902",
    "addr:street":"S 6Th Ave",
    "iso:country":"US",
    "sg:address":"715 S 6th Ave",
    "sg:city":"Yakima",
    "sg:classifiers":[
        {
            "category":"Professional",
            "subcategory":"Business Services",
            "type":"Services"
        }
    ],
    "sg:phone":"+1 509 469 3441",
    "sg:postcode":"98902",
    "sg:province":"WA",
    "wof:name":"Isidro Valencia",
    "wof:placetype":"venue"
},
  "geometry": {"coordinates":[-120.513293,46.589921],"type":"Point"}
}