{
  "type": "Feature",
  "properties": {
    "addr:full":"2906 Campus Prairie Loop NE Lacey WA 98516",
    "addr:housenumber":"2906",
    "addr:postcode":"98516",
    "addr:street":"Campus Prairie Loop Ne",
    "iso:country":"US",
    "sg:address":"2906 Campus Prairie Loop NE",
    "sg:city":"Lacey",
    "sg:classifiers":[
        {
            "category":"Professional",
            "subcategory":"Advertising",
            "type":"Services"
        }
    ],
    "sg:phone":"+1 360 918 8723",
    "sg:postcode":"98516",
    "sg:province":"WA",
    "sg:tags":[
        "marketing",
        "program"
    ],
    "wof:name":"Fusion Sales And Marketing Inc",
    "wof:placetype":"venue"
},
  "geometry": {"coordinates":[-122.74744699999999,47.077723],"type":"Point"}
}