{
  "type": "Feature",
  "properties": {
    "addr:full":"1401 21st St SE Auburn WA 98002",
    "addr:housenumber":"1401",
    "addr:postcode":"98002",
    "addr:street":"21St St Se",
    "iso:country":"US",
    "sg:address":"1401 21st St SE",
    "sg:city":"Auburn",
    "sg:classifiers":[
        {
            "category":"Manufacturing",
            "subcategory":"Electronics",
            "type":"Manufacturing & Wholesale Goods"
        },
        {
            "category":"Professional",
            "subcategory":"Printing & Photocopies",
            "type":"Services"
        }
    ],
    "sg:phone":"+1 253 333 1590",
    "sg:postcode":"98002",
    "sg:province":"WA",
    "sg:tags":[
        "printers-equipment",
        "typesetting",
        "supply"
    ],
    "wof:name":"S B Transcription",
    "wof:placetype":"venue"
},
  "geometry": {"coordinates":[-122.210678,47.290119],"type":"Point"}
}