{
  "type": "Feature",
  "properties": {
    "addr:full":"10411 SE 174th St Renton WA 98055",
    "addr:housenumber":"10411",
    "addr:postcode":"98055",
    "addr:street":"Se 174Th St",
    "iso:country":"US",
    "sg:address":"10411 SE 174th St",
    "sg:city":"Renton",
    "sg:classifiers":[
        {
            "category":"Building & Trades",
            "subcategory":"Cleaning & Sanitation",
            "type":"Services"
        }
    ],
    "sg:phone":"+1 425 430 9674",
    "sg:postcode":"98055",
    "sg:province":"WA",
    "sg:tags":[
        "maintenance"
    ],
    "wof:name":"JB Maintenance",
    "wof:placetype":"venue"
},
  "geometry": {"coordinates":[-122.20108999999999,47.446785],"type":"Point"}
}