{
  "type": "Feature",
  "properties": {
    "addr:full":"4402 N Division St Spokane WA 99207",
    "addr:housenumber":"4402",
    "addr:postcode":"99207",
    "addr:street":"N Division St",
    "iso:country":"US",
    "sg:address":"4402 N Division St",
    "sg:city":"Spokane",
    "sg:classifiers":[
        {
            "category":"Home & Garden",
            "subcategory":"Furniture",
            "type":"Retail Goods"
        }
    ],
    "sg:phone":"+1 509 533 1450",
    "sg:postcode":"99207",
    "sg:province":"WA",
    "sg:tags":[
        "supply"
    ],
    "wof:name":"Walkers Furn Clearance Ctr",
    "wof:placetype":"venue"
},
  "geometry": {"coordinates":[-117.41114899999999,47.698375],"type":"Point"}
}