{
  "type": "Feature",
  "properties": {
    "addr:full":"3315 S 116th St Seattle WA 98168",
    "addr:housenumber":"3315",
    "addr:postcode":"98168",
    "addr:street":"S 116Th St",
    "iso:country":"US",
    "sg:address":"3315 S 116th St",
    "sg:city":"Seattle",
    "sg:classifiers":[
        {
            "category":"Wholesale",
            "subcategory":"Machinery & Supplies",
            "type":"Manufacturing & Wholesale Goods"
        },
        {
            "category":"Manufacturing",
            "subcategory":"Metals",
            "type":"Manufacturing & Wholesale Goods"
        }
    ],
    "sg:phone":"+1 206 244 7895",
    "sg:postcode":"98168",
    "sg:province":"WA",
    "sg:tags":[
        "hardware",
        "caster",
        "industrial",
        "glide"
    ],
    "wof:name":"Industrial Caster & Wheel Co",
    "wof:placetype":"venue"
},
  "geometry": {"coordinates":[-122.289306,47.499164],"type":"Point"}
}