{
  "type": "Feature",
  "properties": {
    "addr:full":"2708 Shelton Ave Yakima WA 98902",
    "addr:housenumber":"2708",
    "addr:postcode":"98902",
    "addr:street":"Shelton Ave",
    "iso:country":"US",
    "sg:address":"2708 Shelton Ave",
    "sg:city":"Yakima",
    "sg:classifiers":[
        {
            "category":"Shopping",
            "type":"Retail Goods"
        }
    ],
    "sg:phone":"+1 509 576 8410",
    "sg:postcode":"98902",
    "sg:province":"WA",
    "sg:tags":[
        "merchandise"
    ],
    "wof:name":"Harrel Images",
    "wof:placetype":"venue"
},
  "geometry": {"coordinates":[-120.548647,46.591568],"type":"Point"}
}