{
  "type": "Feature",
  "properties": {
    "addr:full":"3711 Steelhead Dr Greenbank WA 98253",
    "addr:housenumber":"3711",
    "addr:postcode":"98253",
    "addr:street":"Steelhead Dr Greenbank",
    "iso:country":"US",
    "sg:address":"3711 Steelhead Dr",
    "sg:city":"Greenbank",
    "sg:classifiers":[
        {
            "category":"Building & Trades",
            "subcategory":"Plumbing",
            "type":"Services"
        }
    ],
    "sg:phone":"+1 360 678 6499",
    "sg:postcode":"98253",
    "sg:province":"WA",
    "sg:tags":[
        "contractor"
    ],
    "wof:name":"South Whidbey Plumbing",
    "wof:placetype":"venue"
},
  "geometry": {"coordinates":[-122.610674,48.074123],"type":"Point"}
}