{
  "type": "Feature",
  "properties": {
    "addr:full":"7306 23rd Ave NW Seattle WA 98117",
    "addr:housenumber":"7306",
    "addr:postcode":"98117",
    "addr:street":"23Rd Ave Nw",
    "iso:country":"US",
    "sg:address":"7306 23rd Ave NW",
    "sg:city":"Seattle",
    "sg:classifiers":[
        {
            "category":"Real Estate",
            "subcategory":"Real Estate Operator",
            "type":"Services"
        }
    ],
    "sg:phone":"+1 206 782 5961",
    "sg:postcode":"98117",
    "sg:province":"WA",
    "sg:tags":[
        "building",
        "apartment"
    ],
    "wof:name":"Ocean View Apts Inc",
    "wof:placetype":"venue"
},
  "geometry": {"coordinates":[-122.385311,47.683132],"type":"Point"}
}