{
  "type": "Feature",
  "properties": {
    "iso:country":"US",
    "sg:address":"732 Summitview Ave",
    "sg:city":"Yakima",
    "sg:classifiers":[
        {
            "category":"Freight",
            "type":"Transportation"
        }
    ],
    "sg:phone":"+1 509 575 4760",
    "sg:postcode":"98902",
    "sg:province":"WA",
    "sg:tags":[
        "arrangement"
    ],
    "wof:name":"Main-N-More",
    "wof:placetype":"venue"
},
  "geometry": {"coordinates":[-120.519846,46.5998],"type":"Point"}
}