{
  "type": "Feature",
  "properties": {
    "addr:full":"602 165th St S Spanaway WA 98387",
    "addr:housenumber":"602",
    "addr:postcode":"98387",
    "addr:street":"165Th St S",
    "iso:country":"US",
    "sg:address":"602 165th St S",
    "sg:city":"Spanaway",
    "sg:classifiers":[
        {
            "category":"Retail",
            "subcategory":"Laundry & Dry Cleaning",
            "type":"Services"
        }
    ],
    "sg:phone":"+1 253 531 6403",
    "sg:postcode":"98387",
    "sg:province":"WA",
    "wof:name":"Wizards Carpet Cleaning",
    "wof:placetype":"venue"
},
  "geometry": {"coordinates":[-122.43978199999999,47.107654],"type":"Point"}
}