{
  "type": "Feature",
  "properties": {
    "addr:full":"2031 Franklin Ave E Seattle WA 98102",
    "addr:housenumber":"2031",
    "addr:postcode":"98102",
    "addr:street":"Franklin Ave E",
    "iso:country":"US",
    "sg:address":"2031 Franklin Ave E",
    "sg:city":"Seattle",
    "sg:classifiers":[
        {
            "category":"Organizations",
            "subcategory":"Non-profit Organization",
            "type":"Services"
        }
    ],
    "sg:phone":"+1 206 255 8870",
    "sg:postcode":"98102",
    "sg:province":"WA",
    "sg:tags":[
        "profit"
    ],
    "wof:name":"Investment Forum",
    "wof:placetype":"venue"
},
  "geometry": {"coordinates":[-122.32475599999999,47.638021],"type":"Point"}
}