{
  "type": "Feature",
  "properties": {
    "addr:full":"2514 Park St Bellingham WA 98225",
    "addr:housenumber":"2514",
    "addr:postcode":"98225",
    "addr:street":"Park St",
    "iso:country":"US",
    "sg:address":"2514 Park St",
    "sg:city":"Bellingham",
    "sg:classifiers":[
        {
            "category":"Professional",
            "type":"Services"
        }
    ],
    "sg:phone":"+1 360 933 1919",
    "sg:postcode":"98225",
    "sg:province":"WA",
    "wof:name":"Margaret McGowan",
    "wof:placetype":"venue"
},
  "geometry": {"coordinates":[-122.49059099999999,48.764229],"type":"Point"}
}