{
  "type": "Feature",
  "properties": {
    "addr:full":"1121 S County Line Rd Grandview WA 98930",
    "addr:housenumber":"1121",
    "addr:postcode":"98930",
    "addr:street":"S County Line Rd",
    "iso:country":"US",
    "sg:address":"1121 S County Line Rd",
    "sg:city":"Grandview",
    "sg:classifiers":[
        {
            "category":"Farming",
            "subcategory":"Farm",
            "type":"Manufacturing & Wholesale Goods"
        }
    ],
    "sg:phone":"+1 509 882 5502",
    "sg:postcode":"98930",
    "sg:province":"WA",
    "sg:tags":[
        "crop",
        "general"
    ],
    "wof:name":"Etee Farm",
    "wof:placetype":"venue"
},
  "geometry": {"coordinates":[-119.873705,46.227196],"type":"Point"}
}