{
  "type": "Feature",
  "properties": {
    "addr:full":"6610 Churchill Rd SE Tenino WA 98589",
    "addr:housenumber":"6610",
    "addr:postcode":"98589",
    "addr:street":"Churchill Rd Se Tenino",
    "iso:country":"US",
    "sg:address":"6610 Churchill Rd SE",
    "sg:city":"Tenino",
    "sg:classifiers":[
        {
            "category":"Wholesale",
            "subcategory":"Groceries",
            "type":"Manufacturing & Wholesale Goods"
        }
    ],
    "sg:phone":"+1 360 264 5037",
    "sg:postcode":"98589",
    "sg:province":"WA",
    "wof:name":"World of Star Stuff",
    "wof:placetype":"venue"
},
  "geometry": {"coordinates":[-122.795012,46.850892],"type":"Point"}
}