{
  "type": "Feature",
  "properties": {
    "addr:full":"310 3rd Ave NE Issaquah WA 98027",
    "addr:housenumber":"310",
    "addr:postcode":"ave;98027",
    "addr:street":"3Rd;Ne",
    "iso:country":"US",
    "sg:address":"310 3rd Ave NE",
    "sg:city":"Issaquah",
    "sg:classifiers":[
        {
            "category":"Personal",
            "subcategory":"Beauty Salon",
            "type":"Services"
        },
        {
            "category":"Organizations",
            "subcategory":"Professional Association",
            "type":"Services"
        }
    ],
    "sg:phone":"+1 425 369 9235",
    "sg:postcode":"98027",
    "sg:province":"WA",
    "sg:tags":[
        "shop"
    ],
    "wof:name":"Asian American Affair Assn",
    "wof:placetype":"venue"
},
  "geometry": {"coordinates":[-122.03104999999999,47.532838],"type":"Point"}
}