{
  "type": "Feature",
  "properties": {
    "addr:full":"4881 Forest Ave SE Mercer Island WA 98040",
    "addr:housenumber":"4881",
    "addr:postcode":"98040",
    "addr:street":"Forest Ave Se",
    "iso:country":"US",
    "sg:address":"4881 Forest Ave SE",
    "sg:city":"Mercer Island",
    "sg:classifiers":[
        {
            "category":"Professional",
            "subcategory":"Business Services",
            "type":"Services"
        }
    ],
    "sg:phone":"+1 206 230 5888",
    "sg:postcode":"98040",
    "sg:province":"WA",
    "wof:name":"Itp Group LLC",
    "wof:placetype":"venue"
},
  "geometry": {"coordinates":[-122.230711,47.564889],"type":"Point"}
}