{
  "type": "Feature",
  "properties": {
    "addr:full":"18725 State Rte 9 Mount Vernon WA 98274",
    "addr:housenumber":"18725",
    "addr:postcode":"98274",
    "addr:street":"State Rte 9",
    "iso:country":"US",
    "sg:address":"18725 State Rte 9",
    "sg:city":"Mount Vernon",
    "sg:classifiers":[
        {
            "category":"Building & Trades",
            "subcategory":"Construction",
            "type":"Services"
        }
    ],
    "sg:phone":"+1 360 941 0091",
    "sg:postcode":"98274",
    "sg:province":"WA",
    "sg:tags":[
        "hanging",
        "contractor"
    ],
    "wof:name":"Dakota Art Editions",
    "wof:placetype":"venue"
},
  "geometry": {"coordinates":[-122.214224,48.375166],"type":"Point"}
}