{
  "type": "Feature",
  "properties": {
    "addr:full":"7121 Pumphouse Rd Toppenish WA 98948",
    "addr:postcode":"7121;98948",
    "addr:street":"Pumphouse Rd",
    "iso:country":"US",
    "sg:address":"7121 Pumphouse Rd",
    "sg:city":"Toppenish",
    "sg:phone":"+1 509 945 0570",
    "sg:postcode":"98948",
    "sg:province":"WA",
    "sg:tags":[
        "farm",
        "field",
        "livestock",
        "crop"
    ],
    "wof:name":"Amandas",
    "wof:placetype":"venue"
},
  "geometry": {"coordinates":[-120.478909,46.316313],"type":"Point"}
}