{
  "type": "Feature",
  "properties": {
    "addr:full":"7140 151st Ave NE Redmond WA 98052",
    "addr:housenumber":"7140",
    "addr:postcode":"98052",
    "addr:street":"151St Ave Ne",
    "iso:country":"US",
    "sg:address":"7140 151st Ave NE",
    "sg:city":"Redmond",
    "sg:classifiers":[
        {
            "category":"Professional",
            "subcategory":"Business Services",
            "type":"Services"
        }
    ],
    "sg:phone":"+1 425 246 0720",
    "sg:postcode":"98052",
    "sg:province":"WA",
    "wof:name":"Facilitation Solutions",
    "wof:placetype":"venue"
},
  "geometry": {"coordinates":[-122.138989,47.670351],"type":"Point"}
}