{
  "type": "Feature",
  "properties": {
    "addr:full":"41 NE Midway Blvd Oak Harbor WA 98277",
    "addr:housenumber":"41",
    "addr:postcode":"98277",
    "addr:street":"Ne Midway Blvd",
    "iso:country":"US",
    "sg:address":"41 NE Midway Blvd",
    "sg:city":"Oak Harbor",
    "sg:classifiers":[
        {
            "category":"Retail",
            "subcategory":"Animal Services",
            "type":"Services"
        }
    ],
    "sg:phone":"+1 360 240 1314",
    "sg:postcode":"98277",
    "sg:province":"WA",
    "sg:tags":[
        "pet",
        "grooming",
        "washing"
    ],
    "wof:name":"Heads To Tails Pet Grooming",
    "wof:placetype":"venue"
},
  "geometry": {"coordinates":[-122.643327,48.300693],"type":"Point"}
}