{
  "type": "Feature",
  "properties": {
    "addr:full":"103 NE Terrace Rd Chehalis WA 98532",
    "addr:housenumber":"103",
    "addr:postcode":"98532",
    "addr:street":"Ne Terrace Rd",
    "iso:country":"US",
    "sg:address":"103 NE Terrace Rd",
    "sg:city":"Chehalis",
    "sg:classifiers":[
        {
            "category":"Shopping",
            "subcategory":"Computers & Home Electronics",
            "type":"Retail Goods"
        }
    ],
    "sg:phone":"+1 360 807 6413",
    "sg:postcode":"98532",
    "sg:province":"WA",
    "sg:tags":[
        "equipment",
        "dealer"
    ],
    "wof:name":"Ace Systems LLC",
    "wof:placetype":"venue"
},
  "geometry": {"coordinates":[-122.96402999999999,46.663243],"type":"Point"}
}