{
  "type": "Feature",
  "properties": {
    "addr:full":"20420 56th Ave W Lynnwood WA 98036",
    "addr:housenumber":"20420",
    "addr:postcode":"98036",
    "addr:street":"56Th Ave W",
    "iso:country":"US",
    "sg:address":"20420 56th Ave W",
    "sg:city":"Lynnwood",
    "sg:classifiers":[
        {
            "category":"Building & Trades",
            "subcategory":"Construction",
            "type":"Services"
        }
    ],
    "sg:phone":"+1 425 673 6600",
    "sg:postcode":"98036",
    "sg:province":"WA",
    "sg:tags":[
        "acoustical",
        "tile",
        "computer",
        "flooring",
        "contractor"
    ],
    "wof:name":"Audio Acoustics Inc",
    "wof:placetype":"venue"
},
  "geometry": {"coordinates":[-122.30871399999999,47.812224],"type":"Point"}
}