{
  "type": "Feature",
  "properties": {
    "addr:full":"625 SE Andrews St Issaquah WA 98027",
    "addr:housenumber":"625",
    "addr:postcode":"98027",
    "addr:street":"Se Andrews St",
    "iso:country":"US",
    "sg:address":"625 SE Andrews St",
    "sg:city":"Issaquah",
    "sg:classifiers":[
        {
            "category":"Professional",
            "type":"Services"
        }
    ],
    "sg:phone":"+1 425 427 1360",
    "sg:postcode":"98027",
    "sg:province":"WA",
    "sg:tags":[
        "information",
        "support",
        "library"
    ],
    "wof:name":"Echo Services Inc",
    "wof:placetype":"venue"
},
  "geometry": {"coordinates":[-122.025549,47.528981],"type":"Point"}
}