{
  "type": "Feature",
  "properties": {
    "addr:full":"1402 3rd Ave Seattle WA 98101",
    "addr:housenumber":"1402",
    "addr:postcode":"98101",
    "addr:street":"3Rd Ave",
    "iso:country":"US",
    "sg:address":"1402 3rd Ave",
    "sg:city":"Seattle",
    "sg:classifiers":[
        {
            "category":"Shopping",
            "subcategory":"Computers & Home Electronics",
            "type":"Retail Goods"
        }
    ],
    "sg:phone":"+1 206 682 3424",
    "sg:postcode":"98101",
    "sg:province":"WA",
    "sg:tags":[
        "software"
    ],
    "wof:name":"Info Safe Inc",
    "wof:placetype":"venue"
},
  "geometry": {"coordinates":[-122.33771900000001,47.609766],"type":"Point"}
}