{
  "type": "Feature",
  "properties": {
    "addr:full":"16024 E Sprague Ave Veradale WA 99037",
    "addr:housenumber":"16024",
    "addr:postcode":"99037",
    "addr:street":"E Sprague Ave",
    "iso:country":"US",
    "sg:address":"16024 E Sprague Ave",
    "sg:city":"Veradale",
    "sg:classifiers":[
        {
            "category":"Shopping",
            "type":"Retail Goods"
        }
    ],
    "sg:phone":"+1 509 928 8444",
    "sg:postcode":"99037",
    "sg:province":"WA",
    "sg:tags":[
        "merchandise"
    ],
    "wof:name":"Maxquip Inc",
    "wof:placetype":"venue"
},
  "geometry": {"coordinates":[-117.187184,47.656899],"type":"Point"}
}