{
  "type": "Feature",
  "properties": {
    "addr:full":"18533 W Lake Desire Dr SE Renton WA 98058",
    "addr:housenumber":"18533",
    "addr:postcode":"98058",
    "addr:street":"W Lake Desire Dr Se",
    "iso:country":"US",
    "sg:address":"18533 W Lake Desire Dr SE",
    "sg:city":"Renton",
    "sg:classifiers":[
        {
            "category":"Building & Trades",
            "subcategory":"Construction",
            "type":"Services"
        }
    ],
    "sg:phone":"+1 425 228 8666",
    "sg:postcode":"98058",
    "sg:province":"WA",
    "sg:tags":[
        "carpentry",
        "contractor"
    ],
    "wof:name":"Johns Custom Installation",
    "wof:placetype":"venue"
},
  "geometry": {"coordinates":[-122.106184,47.436699],"type":"Point"}
}