{
  "type": "Feature",
  "properties": {
    "addr:full":"15446 SE 67th St Bellevue WA 98006",
    "addr:postcode":"15446;98006",
    "addr:street":"Se 67Th St",
    "iso:country":"US",
    "sg:address":"15446 SE 67th St",
    "sg:city":"Bellevue",
    "sg:classifiers":[
        {
            "category":"Professional",
            "subcategory":"Management & Consulting",
            "type":"Services"
        }
    ],
    "sg:phone":"+1 425 746 2696",
    "sg:postcode":"98006",
    "sg:province":"WA",
    "wof:name":"Assn Seafood Consult",
    "wof:placetype":"venue"
},
  "geometry": {"coordinates":[-122.134249,47.540421],"type":"Point"}
}