{
  "type": "Feature",
  "properties": {
    "addr:full":"21841 Beachside Dr SE Yelm WA 98597",
    "addr:postcode":"21841;98597",
    "addr:street":"Beachside Dr Se",
    "iso:country":"US",
    "sg:address":"21841 Beachside Dr SE",
    "sg:city":"Yelm",
    "sg:classifiers":[
        {
            "category":"Manufacturing",
            "subcategory":"Printing",
            "type":"Manufacturing & Wholesale Goods"
        }
    ],
    "sg:phone":"+1 360 894 1418",
    "sg:postcode":"98597",
    "sg:province":"WA",
    "sg:tags":[
        "publisher",
        "greeting",
        "card"
    ],
    "wof:name":"Laura & Company Inc",
    "wof:placetype":"venue"
},
  "geometry": {"coordinates":[-122.478886,46.824367],"type":"Point"}
}