{
  "type": "Feature",
  "properties": {
    "addr:full":"4009 Stone Way N Seattle WA 98103",
    "addr:housenumber":"4009",
    "addr:postcode":"98103",
    "addr:street":"Stone Way N",
    "iso:country":"US",
    "sg:address":"4009 Stone Way N",
    "sg:city":"Seattle",
    "sg:classifiers":[
        {
            "category":"Personal",
            "subcategory":"Beauty Salon",
            "type":"Services"
        }
    ],
    "sg:phone":"+1 206 633 0770",
    "sg:postcode":"98103",
    "sg:province":"WA",
    "wof:name":"Fantasies Hair Design & Tnng",
    "wof:placetype":"venue"
},
  "geometry": {"coordinates":[-122.342491,47.655837],"type":"Point"}
}