{
  "type": "Feature",
  "properties": {
    "addr:full":"26915 204th Ave SE Kent WA 98042",
    "addr:housenumber":"26915",
    "addr:postcode":"98042",
    "addr:street":"204Th Ave Se",
    "iso:country":"US",
    "sg:address":"26915 204th Ave SE",
    "sg:city":"Kent",
    "sg:classifiers":[
        {
            "category":"Personal",
            "subcategory":"Beauty Salon",
            "type":"Services"
        }
    ],
    "sg:phone":"+1 253 631 9715",
    "sg:postcode":"98042",
    "sg:province":"WA",
    "sg:tags":[
        "shop"
    ],
    "wof:name":"Normas Country Styling Salon",
    "wof:placetype":"venue"
},
  "geometry": {"coordinates":[-122.06992700000001,47.36085],"type":"Point"}
}