{
  "type": "Feature",
  "properties": {
    "addr:full":"225 Division St Grandview WA 98930",
    "addr:housenumber":"225",
    "addr:postcode":"98930",
    "addr:street":"Division St",
    "iso:country":"US",
    "sg:address":"225 Division St",
    "sg:city":"Grandview",
    "sg:classifiers":[
        {
            "category":"Food & Beverages",
            "subcategory":"Meat & Fish",
            "type":"Retail Goods"
        }
    ],
    "sg:phone":"+1 509 882 1468",
    "sg:postcode":"98930",
    "sg:province":"WA",
    "wof:name":"Carnicera Guerrero",
    "wof:placetype":"venue"
},
  "geometry": {"coordinates":[-119.90187,46.254489],"type":"Point"}
}