{
  "type": "Feature",
  "properties": {
    "addr:full":"1861 Palisade Blvd Du Pont WA 98327",
    "addr:housenumber":"1861",
    "addr:postcode":"98327",
    "addr:street":"Palisade Blvd Du Pont",
    "iso:country":"US",
    "sg:address":"1861 Palisade Blvd",
    "sg:city":"Du Pont",
    "sg:classifiers":[
        {
            "category":"Professional",
            "subcategory":"Business Services",
            "type":"Services"
        }
    ],
    "sg:phone":"+1 253 912 0141",
    "sg:postcode":"98327",
    "sg:province":"WA",
    "wof:name":"Command Technologies Inc",
    "wof:placetype":"venue"
},
  "geometry": {"coordinates":[-122.640565,47.098541],"type":"Point"}
}