{
  "type": "Feature",
  "properties": {
    "addr:full":"12215 Pacific Hwy SW Lakewood WA 98499",
    "addr:housenumber":"12215",
    "addr:postcode":"98499",
    "addr:street":"Pacific Hwy Sw",
    "iso:country":"US",
    "sg:address":"12215 Pacific Hwy SW",
    "sg:city":"Lakewood",
    "sg:classifiers":[
        {
            "category":"Travel",
            "subcategory":"Hotels & Motels",
            "type":"Entertainment"
        },
        {
            "category":"Real Estate",
            "subcategory":"Real Estate Operator",
            "type":"Services"
        }
    ],
    "sg:phone":"+1 253 588 7226",
    "sg:postcode":"98499",
    "sg:province":"WA",
    "sg:tags":[
        "building",
        "operation",
        "apartment"
    ],
    "sg:website":"fortlewismotel.com//",
    "wof:name":"Fort Lewis Apartment-Motel",
    "wof:placetype":"venue"
},
  "geometry": {"coordinates":[-122.50900300000001,47.146198],"type":"Point"}
}