{
  "type": "Feature",
  "properties": {
    "addr:full":"1101 Madison St Seattle WA 98104",
    "addr:housenumber":"1101",
    "addr:postcode":"98104",
    "addr:street":"Madison St",
    "iso:country":"US",
    "sg:address":"1101 Madison St",
    "sg:city":"Seattle",
    "sg:classifiers":[
        {
            "category":"Health Services",
            "subcategory":"Doctor",
            "type":"Services"
        }
    ],
    "sg:phone":"+1 206 505 1101",
    "sg:postcode":"98104",
    "sg:province":"WA",
    "sg:tags":[
        "medical"
    ],
    "wof:name":"Piro Kramar MD",
    "wof:placetype":"venue"
},
  "geometry": {"coordinates":[-122.32402999999999,47.609801],"type":"Point"}
}