{
  "type": "Feature",
  "properties": {
    "addr:full":"1300 114th Ave SE Ste 210 Bellevue WA 98004",
    "addr:housenumber":"1300",
    "addr:postcode":"98004",
    "addr:street":"114Th Ave Se Ste 210",
    "iso:country":"US",
    "sg:address":"1300 114th Ave SE Ste 210",
    "sg:city":"Bellevue",
    "sg:classifiers":[
        {
            "category":"Health Services",
            "subcategory":"Doctor",
            "type":"Services"
        }
    ],
    "sg:phone":"+1 425 503 2750",
    "sg:postcode":"98004",
    "sg:province":"WA",
    "sg:tags":[
        "psychiatrist"
    ],
    "wof:name":"Saltonstall Rebecca MD PS",
    "wof:placetype":"venue"
},
  "geometry": {"coordinates":[-122.206001,47.613899],"type":"Point"}
}