{
  "type": "Feature",
  "properties": {
    "iso:country":"US",
    "sg:address":"1565 S Pearl St",
    "sg:city":"Seattle",
    "sg:classifiers":[
        {
            "category":"Building & Trades",
            "subcategory":"Construction",
            "type":"Services"
        }
    ],
    "sg:phone":"+1 206 763 0220",
    "sg:postcode":"98108",
    "sg:province":"WA",
    "sg:tags":[
        "residential",
        "remodel",
        "contractor"
    ],
    "wof:name":"Parmesan Construction",
    "wof:placetype":"venue"
},
  "geometry": {"coordinates":[-122.31100000000001,47.556644],"type":"Point"}
}