{
  "type": "Feature",
  "properties": {
    "addr:full":"161 S Lincoln St Spokane WA 99201",
    "addr:housenumber":"161",
    "addr:postcode":"99201",
    "addr:street":"S Lincoln St",
    "iso:country":"US",
    "sg:address":"161 S Lincoln St",
    "sg:city":"Spokane",
    "sg:classifiers":[
        {
            "category":"Communications",
            "subcategory":"Film & Video Production",
            "type":"Services"
        },
        {
            "category":"Personal",
            "subcategory":"Beauty Salon",
            "type":"Services"
        }
    ],
    "sg:phone":"+1 509 455 7430",
    "sg:postcode":"99201",
    "sg:province":"WA",
    "sg:tags":[
        "motion",
        "make",
        "studio"
    ],
    "wof:name":"Make Up Studio",
    "wof:placetype":"venue"
},
  "geometry": {"coordinates":[-117.42492,47.655091],"type":"Point"}
}