{
  "type": "Feature",
  "properties": {
    "addr:full":"10604 NE 38th Pl Kirkland WA 98033",
    "addr:housenumber":"10604",
    "addr:postcode":"98033",
    "addr:street":"Ne 38Th Pl",
    "iso:country":"US",
    "sg:address":"10604 NE 38th Pl",
    "sg:city":"Kirkland",
    "sg:classifiers":[
        {
            "category":"Education",
            "subcategory":"Vocational School",
            "type":"Public Place"
        }
    ],
    "sg:phone":"+1 425 576 1155",
    "sg:postcode":"98033",
    "sg:province":"WA",
    "sg:tags":[
        "training",
        "computer"
    ],
    "wof:name":"Information Management",
    "wof:placetype":"venue"
},
  "geometry": {"coordinates":[-122.197112,47.642916],"type":"Point"}
}