{
  "type": "Feature",
  "properties": {
    "addr:full":"1523 Fowler St Richland WA 99352",
    "addr:housenumber":"1523",
    "addr:postcode":"99352",
    "addr:street":"Fowler St",
    "iso:country":"US",
    "sg:address":"1523 Fowler St",
    "sg:city":"Richland",
    "sg:classifiers":[
        {
            "category":"Freight",
            "type":"Transportation"
        }
    ],
    "sg:phone":"+1 509 736 6440",
    "sg:postcode":"99352",
    "sg:province":"WA",
    "sg:tags":[
        "mover",
        "storage",
        "trucking"
    ],
    "wof:name":"Kennewick Transfer & Storage",
    "wof:placetype":"venue"
},
  "geometry": {"coordinates":[-119.220376,46.234836],"type":"Point"}
}