{
  "type": "Feature",
  "properties": {
    "addr:full":"2804 NE 65th Ave Vancouver WA 98661",
    "addr:housenumber":"2804",
    "addr:postcode":"98661",
    "addr:street":"Ne 65Th Ave",
    "iso:country":"US",
    "sg:address":"2804 NE 65th Ave",
    "sg:city":"Vancouver",
    "sg:classifiers":[
        {
            "category":"Personal",
            "type":"Services"
        },
        {
            "category":"Building & Trades",
            "subcategory":"Construction",
            "type":"Services"
        }
    ],
    "sg:phone":"+1 360 993 4800",
    "sg:postcode":"98661",
    "sg:province":"WA",
    "sg:tags":[
        "closet",
        "cabinet",
        "designing",
        "contractor",
        "remodeling",
        "maker"
    ],
    "wof:name":"The Giving Closet",
    "wof:placetype":"venue"
},
  "geometry": {"coordinates":[-122.604935,45.641831],"type":"Point"}
}