{
  "type": "Feature",
  "properties": {
    "addr:full":"14208 E Sprague Ave Spokane Valley WA 99216",
    "addr:housenumber":"14208",
    "addr:postcode":"99216",
    "addr:street":"E Sprague Ave",
    "iso:country":"US",
    "sg:address":"14208 E Sprague Ave",
    "sg:city":"Spokane Valley",
    "sg:classifiers":[
        {
            "category":"Shopping",
            "type":"Retail Goods"
        }
    ],
    "sg:phone":"+1 509 891 9935",
    "sg:postcode":"99216",
    "sg:province":"WA",
    "sg:tags":[
        "art",
        "gallery",
        "merchandise",
        "dealer"
    ],
    "sg:website":"www.owensauction.com",
    "wof:name":"Owens Auction Gallery",
    "wof:placetype":"venue"
},
  "geometry": {"coordinates":[-117.212018,47.656976],"type":"Point"}
}