{
  "type": "Feature",
  "properties": {
    "addr:full":"421 SW 152nd St Burien WA 98166",
    "addr:housenumber":"421",
    "addr:postcode":"98166",
    "addr:street":"Sw 152Nd St",
    "iso:country":"US",
    "sg:address":"421 SW 152nd St",
    "sg:city":"Burien",
    "sg:classifiers":[
        {
            "category":"Shopping",
            "subcategory":"Music",
            "type":"Retail Goods"
        },
        {
            "category":"Shopping",
            "subcategory":"Used Merchandise",
            "type":"Retail Goods"
        }
    ],
    "sg:phone":"+1 206 244 5313",
    "sg:postcode":"98166",
    "sg:province":"WA",
    "sg:tags":[
        "repair",
        "pawnbroker",
        "jeweler"
    ],
    "sg:website":"http://www.jaffesloans.com",
    "wof:name":"Jaffe's Jewelry & Loans",
    "wof:placetype":"venue"
},
  "geometry": {"coordinates":[-122.339707,47.466833],"type":"Point"}
}