{
  "type": "Feature",
  "properties": {
    "addr:full":"702 N 1st St Yakima WA 98901",
    "addr:housenumber":"702",
    "addr:postcode":"98901",
    "addr:street":"N 1St St",
    "iso:country":"US",
    "sg:address":"702 N 1st St",
    "sg:city":"Yakima",
    "sg:classifiers":[
        {
            "category":"Insurance",
            "subcategory":"Insurance Agent",
            "type":"Services"
        }
    ],
    "sg:phone":"+1 509 248 7711",
    "sg:postcode":"98901",
    "sg:province":"WA",
    "sg:website":"www.elliott-insurance.com",
    "wof:name":"Elliott Insurance Svc Inc",
    "wof:placetype":"venue"
},
  "geometry": {"coordinates":[-120.510946,46.611981],"type":"Point"}
}