{
  "type": "Feature",
  "properties": {
    "addr:full":"12014 SE Mill Plain Blvd Vancouver WA 98684",
    "addr:postcode":"12014;98684",
    "addr:street":"Se Mill Plain Blvd",
    "iso:country":"US",
    "sg:address":"12014 SE Mill Plain Blvd",
    "sg:city":"Vancouver",
    "sg:classifiers":[
        {
            "category":"Social Services",
            "type":"Services"
        }
    ],
    "sg:phone":"+1 360 690 8385",
    "sg:postcode":"98684",
    "sg:province":"WA",
    "wof:name":"Partners In Community Car",
    "wof:placetype":"venue"
},
  "geometry": {"coordinates":[-122.54841500000001,45.620406],"type":"Point"}
}