{
  "type": "Feature",
  "properties": {
    "addr:full":"916 153rd Pl SW Lynnwood WA 98087",
    "addr:housenumber":"916",
    "addr:postcode":"98087",
    "addr:street":"153Rd Pl Sw",
    "iso:country":"US",
    "sg:address":"916 153rd Pl SW",
    "sg:city":"Lynnwood",
    "sg:classifiers":[
        {
            "category":"Building & Trades",
            "subcategory":"Landscaping Services",
            "type":"Services"
        }
    ],
    "sg:phone":"+1 425 743 0106",
    "sg:postcode":"98087",
    "sg:province":"WA",
    "wof:name":"Mohorics Gardening Service",
    "wof:placetype":"venue"
},
  "geometry": {"coordinates":[-122.245386,47.858936],"type":"Point"}
}