{
  "type": "Feature",
  "properties": {
    "addr:full":"11738 NE 149th St Kirkland WA 98034",
    "addr:housenumber":"11738",
    "addr:postcode":"98034",
    "addr:street":"Ne 149Th St",
    "iso:country":"US",
    "sg:address":"11738 NE 149th St",
    "sg:city":"Kirkland",
    "sg:classifiers":[
        {
            "category":"Recreation",
            "type":"Entertainment"
        }
    ],
    "sg:phone":"+1 425 488 8424",
    "sg:postcode":"98034",
    "sg:province":"WA",
    "sg:tags":[
        "club",
        "membership"
    ],
    "wof:name":"Highwoodlands Swim Club",
    "wof:placetype":"venue"
},
  "geometry": {"coordinates":[-122.182806,47.736325],"type":"Point"}
}