{
  "type": "Feature",
  "properties": {
    "addr:full":"9010 Wallingford Ave N Seattle WA 98103",
    "addr:housenumber":"9010",
    "addr:postcode":"98103",
    "addr:street":"Wallingford Ave N",
    "iso:country":"US",
    "sg:address":"9010 Wallingford Ave N",
    "sg:city":"Seattle",
    "sg:classifiers":[
        {
            "category":"Wholesale",
            "subcategory":"Jewelry",
            "type":"Manufacturing & Wholesale Goods"
        }
    ],
    "sg:phone":"+1 206 523 2267",
    "sg:postcode":"98103",
    "sg:province":"WA",
    "sg:tags":[
        "finding",
        "supply",
        "jeweler"
    ],
    "wof:name":"Designs By Dale",
    "wof:placetype":"venue"
},
  "geometry": {"coordinates":[-122.33650299999999,47.694318],"type":"Point"}
}