{
  "type": "Feature",
  "properties": {
    "addr:full":"2205 N Woodruff Rd Spokane Valley WA 99206",
    "addr:housenumber":"2205",
    "addr:postcode":"99206",
    "addr:street":"N Woodruff Rd",
    "iso:country":"US",
    "sg:address":"2205 N Woodruff Rd",
    "sg:city":"Spokane Valley",
    "sg:classifiers":[
        {
            "category":"Professional",
            "subcategory":"Research",
            "type":"Services"
        }
    ],
    "sg:phone":"+1 509 924 9236",
    "sg:postcode":"99206",
    "sg:province":"WA",
    "sg:tags":[
        "environmental",
        "ecological"
    ],
    "sg:website":"www.mcs-environmental.com",
    "wof:name":"MCS Enviornmental Inc",
    "wof:placetype":"venue"
},
  "geometry": {"coordinates":[-117.272077,47.678756],"type":"Point"}
}