{
  "type": "Feature",
  "properties": {
    "iso:country":"US",
    "sg:address":"11955 Lakeside Ave NE",
    "sg:city":"Seattle",
    "sg:classifiers":[
        {
            "category":"Shopping",
            "subcategory":"Gifts & Souvenirs",
            "type":"Retail Goods"
        }
    ],
    "sg:phone":"+1 206 364 4341",
    "sg:postcode":"98125",
    "sg:province":"WA",
    "wof:name":"Music of Remembrance",
    "wof:placetype":"venue"
},
  "geometry": {"coordinates":[-122.279673,47.714833],"type":"Point"}
}