{
  "type": "Feature",
  "properties": {
    "addr:full":"3046 S Star Lake Rd Auburn WA 98001",
    "addr:housenumber":"3046",
    "addr:postcode":"98001",
    "addr:street":"S Star Lake Rd",
    "iso:country":"US",
    "sg:address":"3046 S Star Lake Rd",
    "sg:city":"Auburn",
    "sg:classifiers":[
        {
            "category":"Utilities",
            "subcategory":"Telephone",
            "type":"Services"
        }
    ],
    "sg:phone":"+1 253 854 1915",
    "sg:postcode":"98001",
    "sg:province":"WA",
    "sg:tags":[
        "development",
        "web",
        "hosting",
        "internet"
    ],
    "wof:name":"Northwest Products Inc",
    "wof:placetype":"venue"
},
  "geometry": {"coordinates":[-122.293083,47.352787],"type":"Point"}
}