{
  "type": "Feature",
  "properties": {
    "addr:full":"9835 16th Ave SW Unit 1 Seattle WA 98106",
    "addr:housenumber":"9835;1",
    "addr:postcode":"98106",
    "addr:street":"16Th Ave Sw Unit",
    "iso:country":"US",
    "sg:address":"9835 16th Ave SW Unit 1",
    "sg:city":"Seattle",
    "sg:classifiers":[
        {
            "category":"Health Services",
            "subcategory":"Dentist",
            "type":"Services"
        }
    ],
    "sg:phone":"+1 206 763 8883",
    "sg:postcode":"98106",
    "sg:province":"WA",
    "wof:name":"First Impressions Dental and Dentures",
    "wof:placetype":"venue"
},
  "geometry": {"coordinates":[-122.355317,47.515209],"type":"Point"}
}