{
  "type": "Feature",
  "properties": {
    "addr:full":"4702 NE 199th St Ridgefield WA 98642",
    "addr:housenumber":"4702",
    "addr:postcode":"98642",
    "addr:street":"Ne 199Th St",
    "iso:country":"US",
    "sg:address":"4702 NE 199th St",
    "sg:city":"Ridgefield",
    "sg:classifiers":[
        {
            "category":"Building & Trades",
            "subcategory":"Cleaning & Sanitation",
            "type":"Services"
        },
        {
            "category":"Building & Trades",
            "subcategory":"Construction",
            "type":"Services"
        },
        {
            "category":"Building & Trades",
            "subcategory":"Electrical",
            "type":"Services"
        }
    ],
    "sg:phone":"+1 360 335 3711",
    "sg:postcode":"98642",
    "sg:province":"WA",
    "sg:tags":[
        "electrician",
        "duct",
        "system",
        "specialty",
        "heating",
        "contractor",
        "air conditioning"
    ],
    "sg:website":"http://www.washougalelectrichc.com",
    "wof:name":"Washougal Electric, Heating & Cooling",
    "wof:placetype":"venue"
},
  "geometry": {"coordinates":[-122.623535,45.765377],"type":"Point"}
}