{
  "type": "Feature",
  "properties": {
    "iso:country":"US",
    "sg:address":"2426 Greenhaven Pl NW",
    "sg:city":"Bremerton",
    "sg:classifiers":[
        {
            "category":"Professional",
            "subcategory":"Business Services",
            "type":"Services"
        }
    ],
    "sg:phone":"+1 360 792 1357",
    "sg:postcode":"98312",
    "sg:province":"WA",
    "sg:tags":[
        "marine",
        "yacht",
        "broker",
        "supply"
    ],
    "wof:name":"Robert Heays Port Yacht Sales",
    "wof:placetype":"venue"
},
  "geometry": {"coordinates":[-122.702686,47.585733],"type":"Point"}
}