{
  "type": "Feature",
  "properties": {
    "addr:full":"1600 Division Rd Zillah WA 98953",
    "addr:housenumber":"1600",
    "addr:postcode":"98953",
    "addr:street":"Division Rd",
    "iso:country":"US",
    "sg:address":"1600 Division Rd",
    "sg:city":"Zillah",
    "sg:classifiers":[
        {
            "category":"Professional",
            "type":"Services"
        }
    ],
    "sg:phone":"+1 509 829 3422",
    "sg:postcode":"98953",
    "sg:province":"WA",
    "wof:name":"Bonita Criswell",
    "wof:placetype":"venue"
},
  "geometry": {"coordinates":[-120.22566,46.389404],"type":"Point"}
}