{
  "type": "Feature",
  "properties": {
    "addr:full":"414 S University Rd Spokane Valley WA 99206",
    "addr:housenumber":"414",
    "addr:postcode":"99206",
    "addr:street":"S University Rd",
    "iso:country":"US",
    "sg:address":"414 S University Rd",
    "sg:city":"Spokane Valley",
    "sg:classifiers":[
        {
            "category":"Health Services",
            "subcategory":"Nursing And Care Facility",
            "type":"Services"
        }
    ],
    "sg:phone":"+1 509 924 4650",
    "sg:postcode":"99206",
    "sg:province":"WA",
    "sg:tags":[
        "home",
        "skilled",
        "convalescent"
    ],
    "wof:name":"Gardens On University The",
    "wof:placetype":"venue"
},
  "geometry": {"coordinates":[-117.261443,47.651594],"type":"Point"}
}