{
  "type": "Feature",
  "properties": {
    "addr:full":"3809 245th Ave SE Issaquah WA 98029",
    "addr:housenumber":"3809",
    "addr:postcode":"98029",
    "addr:street":"245Th Ave Se",
    "iso:country":"US",
    "sg:address":"3809 245th Ave SE",
    "sg:city":"Issaquah",
    "sg:classifiers":[
        {
            "category":"Professional",
            "type":"Services"
        }
    ],
    "sg:phone":"+1 425 369 9897",
    "sg:postcode":"98029",
    "sg:province":"WA",
    "wof:name":"Digital Blackboard Foundation",
    "wof:placetype":"venue"
},
  "geometry": {"coordinates":[-122.014714,47.574413],"type":"Point"}
}