{
  "type": "Feature",
  "properties": {
    "addr:full":"6210 N Division St Spokane WA 99208",
    "addr:housenumber":"6210",
    "addr:postcode":"99208",
    "addr:street":"N Division St",
    "iso:country":"US",
    "sg:address":"6210 N Division St",
    "sg:city":"Spokane",
    "sg:classifiers":[
        {
            "category":"Shopping",
            "subcategory":"Shoes",
            "type":"Retail Goods"
        }
    ],
    "sg:phone":"+1 509 487 1291",
    "sg:postcode":"99208",
    "sg:province":"WA",
    "wof:name":"SAS Comfort Shoes",
    "wof:placetype":"venue"
},
  "geometry": {"coordinates":[-117.411106,47.714096],"type":"Point"}
}