{
  "type": "Feature",
  "properties": {
    "addr:full":"22117 NE 80th St Redmond WA 98053",
    "addr:housenumber":"22117",
    "addr:postcode":"98053",
    "addr:street":"Ne 80Th St",
    "iso:country":"US",
    "sg:address":"22117 NE 80th St",
    "sg:city":"Redmond",
    "sg:classifiers":[
        {
            "category":"Professional",
            "subcategory":"Engineering",
            "type":"Services"
        }
    ],
    "sg:phone":"+1 425 830 4312",
    "sg:postcode":"98053",
    "sg:province":"WA",
    "wof:name":"Trd Associates LLC",
    "wof:placetype":"venue"
},
  "geometry": {"coordinates":[-122.042894,47.674997],"type":"Point"}
}