{
  "type": "Feature",
  "properties": {
    "addr:full":"2601 W Marina Pl Seattle WA 98199",
    "addr:housenumber":"2601",
    "addr:postcode":"98199",
    "addr:street":"W Marina Pl",
    "iso:country":"US",
    "sg:address":"2601 W Marina Pl",
    "sg:city":"Seattle",
    "sg:classifiers":[
        {
            "category":"Professional",
            "type":"Services"
        }
    ],
    "sg:phone":"+1 206 378 5861",
    "sg:postcode":"98199",
    "sg:province":"WA",
    "wof:name":"Cape Point Systems LLC",
    "wof:placetype":"venue"
},
  "geometry": {"coordinates":[-122.390974,47.631065],"type":"Point"}
}