{
  "type": "Feature",
  "properties": {
    "addr:full":"11120 Evergreen Way Everett WA 98204",
    "addr:housenumber":"11120",
    "addr:postcode":"98204",
    "addr:street":"Evergreen Way",
    "iso:country":"US",
    "sg:address":"11120 Evergreen Way",
    "sg:city":"Everett",
    "sg:classifiers":[
        {
            "category":"Food & Beverages",
            "subcategory":"Groceries & Convenience Stores",
            "type":"Retail Goods"
        }
    ],
    "sg:phone":"+1 425 353 3341",
    "sg:postcode":"98204",
    "sg:province":"WA",
    "sg:tags":[
        "grocer"
    ],
    "wof:name":"Indo Mericana",
    "wof:placetype":"venue"
},
  "geometry": {"coordinates":[-122.24918700000001,47.899416],"type":"Point"}
}