{
  "type": "Feature",
  "properties": {
    "addr:full":"316 W Boone Ave Ste 675 Spokane WA 99201",
    "addr:housenumber":"316",
    "addr:postcode":"99201",
    "addr:street":"W Boone Ave Ste 675",
    "iso:country":"US",
    "sg:address":"316 W Boone Ave Ste 675",
    "sg:city":"Spokane",
    "sg:classifiers":[
        {
            "category":"Professional",
            "subcategory":"Lawyer & Legal Services",
            "type":"Services"
        }
    ],
    "sg:phone":"+1 509 252 0266",
    "sg:postcode":"99201",
    "sg:province":"WA",
    "sg:tags":[
        "attorney",
        "law",
        "personal",
        "damage",
        "property",
        "accident",
        "injury"
    ],
    "sg:website":"http://www.spokaneinjury.com",
    "wof:name":"Bruce M. Nelson, Attorney",
    "wof:placetype":"venue"
},
  "geometry": {"coordinates":[-117.41611399999999,47.668091],"type":"Point"}
}