{
  "type": "Feature",
  "properties": {
    "addr:full":"23909 Paradise Lake Rd Woodinville WA 98077",
    "addr:housenumber":"23909",
    "addr:postcode":"98077",
    "addr:street":"Paradise Lake Rd",
    "iso:country":"US",
    "sg:address":"23909 Paradise Lake Rd",
    "sg:city":"Woodinville",
    "sg:classifiers":[
        {
            "category":"Professional",
            "subcategory":"Engineering",
            "type":"Services"
        }
    ],
    "sg:phone":"+1 425 485 3027",
    "sg:postcode":"98077",
    "sg:province":"WA",
    "sg:tags":[
        "consultant",
        "construction"
    ],
    "wof:name":"Bruce L Blake",
    "wof:placetype":"venue"
},
  "geometry": {"coordinates":[-122.076088,47.779911],"type":"Point"}
}