{
  "type": "Feature",
  "properties": {
    "iso:country":"US",
    "sg:address":"535 E Bluff St",
    "sg:city":"Palouse",
    "sg:classifiers":[
        {
            "category":"Building & Trades",
            "subcategory":"Construction",
            "type":"Services"
        }
    ],
    "sg:phone":"+1 509 332 3461",
    "sg:postcode":"99161",
    "sg:province":"WA",
    "sg:tags":[
        "hanging",
        "contractor"
    ],
    "wof:name":"AC Painting",
    "wof:placetype":"venue"
},
  "geometry": {"coordinates":[-117.070728,46.907635],"type":"Point"}
}