{
  "type": "Feature",
  "properties": {
    "addr:full":"2470 Westlake Ave N Seattle WA 98109",
    "addr:housenumber":"2470",
    "addr:postcode":"98109",
    "addr:street":"Westlake Ave N",
    "iso:country":"US",
    "sg:address":"2470 Westlake Ave N",
    "sg:city":"Seattle",
    "sg:classifiers":[
        {
            "category":"Autos & Motor Vehicles",
            "subcategory":"Boat Sales",
            "type":"Retail Goods"
        },
        {
            "category":"Professional",
            "type":"Services"
        }
    ],
    "sg:phone":"+1 206 957 7095",
    "sg:postcode":"98109",
    "sg:province":"WA",
    "sg:tags":[
        "yacht",
        "broker"
    ],
    "wof:name":"Cape Horn Yacht & Shipbrokers",
    "wof:placetype":"venue"
},
  "geometry": {"coordinates":[-122.341371,47.639163],"type":"Point"}
}