{
  "type": "Feature",
  "properties": {
    "addr:full":"9840 Martin Luther King Way S Seattle WA 98118",
    "addr:housenumber":"9840",
    "addr:postcode":"98118",
    "addr:street":"Martin Luther King Way S",
    "iso:country":"US",
    "sg:address":"9840 Martin Luther King Way S",
    "sg:city":"Seattle",
    "sg:classifiers":[
        {
            "category":"Home & Garden",
            "subcategory":"Furniture",
            "type":"Retail Goods"
        }
    ],
    "sg:phone":"+1 206 725 3793",
    "sg:postcode":"98118",
    "sg:province":"WA",
    "sg:tags":[
        "cabinet"
    ],
    "wof:name":"Cabinets Elite LTD",
    "wof:placetype":"venue"
},
  "geometry": {"coordinates":[-122.278418,47.509806],"type":"Point"}
}