{
  "type": "Feature",
  "properties": {
    "addr:full":"600 N 36th St Ste 214 Seattle WA 98103",
    "addr:housenumber":"600",
    "addr:postcode":"98103",
    "addr:street":"N 36Th St Ste 214",
    "iso:country":"US",
    "sg:address":"600 N 36th St Ste 214",
    "sg:city":"Seattle",
    "sg:classifiers":[
        {
            "category":"Health Services",
            "subcategory":"Health Practitioner",
            "type":"Services"
        }
    ],
    "sg:phone":"+1 206 782 7572",
    "sg:postcode":"98103",
    "sg:province":"WA",
    "sg:tags":[
        "acupuncture"
    ],
    "sg:website":"www.jracupuncture.com",
    "wof:name":"Randall Jessica Lac",
    "wof:placetype":"venue"
},
  "geometry": {"coordinates":[-122.35136900000001,47.651573],"type":"Point"}
}