{
  "type": "Feature",
  "properties": {
    "addr:full":"6394 SE Dandelion Ln Olalla WA 98359",
    "addr:housenumber":"6394",
    "addr:postcode":"98359",
    "addr:street":"Se Dandelion Ln",
    "iso:country":"US",
    "sg:address":"6394 SE Dandelion Ln",
    "sg:city":"Olalla",
    "sg:classifiers":[
        {
            "category":"Social Services",
            "subcategory":"Child Care",
            "type":"Services"
        }
    ],
    "sg:phone":"+1 253 851 1766",
    "sg:postcode":"98359",
    "sg:province":"WA",
    "sg:tags":[
        "day"
    ],
    "wof:name":"Cinder Care Day Care",
    "wof:placetype":"venue"
},
  "geometry": {"coordinates":[-122.569412,47.404382],"type":"Point"}
}