{
  "type": "Feature",
  "properties": {
    "addr:full":"4505 San Juan Ave Anacortes WA 98221",
    "addr:housenumber":"4505",
    "addr:postcode":"98221",
    "addr:street":"San Juan Ave",
    "iso:country":"US",
    "sg:address":"4505 San Juan Ave",
    "sg:city":"Anacortes",
    "sg:classifiers":[
        {
            "category":"Home & Garden",
            "subcategory":"Carpets & Floor Coverings",
            "type":"Retail Goods"
        }
    ],
    "sg:phone":"+1 360 299 1272",
    "sg:postcode":"98221",
    "sg:province":"WA",
    "wof:name":"Rose Floor Covering",
    "wof:placetype":"venue"
},
  "geometry": {"coordinates":[-122.66583799999999,48.497983],"type":"Point"}
}