{
  "type": "Feature",
  "properties": {
    "addr:full":"515 W Columbia St Pasco WA 99301",
    "addr:housenumber":"515",
    "addr:postcode":"99301",
    "addr:street":"W Columbia St",
    "iso:country":"US",
    "sg:address":"515 W Columbia St",
    "sg:city":"Pasco",
    "sg:classifiers":[
        {
            "category":"Wholesale",
            "subcategory":"Stationery",
            "type":"Manufacturing & Wholesale Goods"
        }
    ],
    "sg:phone":"+1 509 547 3141",
    "sg:postcode":"99301",
    "sg:province":"WA",
    "sg:tags":[
        "product",
        "paper"
    ],
    "wof:name":"Columbia Basin Paper & Supply",
    "wof:placetype":"venue"
},
  "geometry": {"coordinates":[-119.092421,46.229444],"type":"Point"}
}