{
  "type": "Feature",
  "properties": {
    "addr:full":"923 S 5th Ave SW Olympia WA 98512",
    "addr:housenumber":"923",
    "addr:postcode":"98512",
    "addr:street":"S 5Th Ave Sw",
    "iso:country":"US",
    "sg:address":"923 S 5th Ave SW",
    "sg:city":"Olympia",
    "sg:classifiers":[
        {
            "category":"Shopping",
            "subcategory":"Used Merchandise",
            "type":"Retail Goods"
        }
    ],
    "sg:phone":"+1 360 786 6032",
    "sg:postcode":"98512",
    "sg:province":"WA",
    "wof:name":"Maureen P Chapman",
    "wof:placetype":"venue"
},
  "geometry": {"coordinates":[-122.910546,47.007505],"type":"Point"}
}