{
  "type": "Feature",
  "properties": {
    "addr:full":"3921 B St NW Auburn WA 98001",
    "addr:housenumber":"3921",
    "addr:postcode":"98001",
    "addr:street":"B St Nw",
    "iso:country":"US",
    "sg:address":"3921 B St NW",
    "sg:city":"Auburn",
    "sg:classifiers":[
        {
            "category":"Retail",
            "subcategory":"Auto Repair",
            "type":"Services"
        }
    ],
    "sg:phone":"+1 253 833 6806",
    "sg:postcode":"98001",
    "sg:province":"WA",
    "sg:tags":[
        "supply",
        "spring",
        "part",
        "automobile"
    ],
    "sg:website":"http://www.gittspring.com",
    "wof:name":"Gitt's Spring",
    "wof:placetype":"venue"
},
  "geometry": {"coordinates":[-122.232274,47.340774],"type":"Point"}
}