{
  "type": "Feature",
  "properties": {
    "addr:full":"23706 Bothell Everett Hwy B Bothell WA 98021",
    "addr:housenumber":"23706",
    "addr:postcode":"98021",
    "addr:street":"Bothell Everett Hwy B",
    "iso:country":"US",
    "sg:address":"23706 Bothell Everett Hwy B",
    "sg:city":"Bothell",
    "sg:classifiers":[
        {
            "category":"Home & Garden",
            "subcategory":"Kitchen Supply",
            "type":"Retail Goods"
        }
    ],
    "sg:phone":"+1 425 402 3484",
    "sg:postcode":"98021",
    "sg:province":"WA",
    "sg:tags":[
        "cutlery"
    ],
    "wof:name":"Bronks Knifeworks",
    "wof:placetype":"venue"
},
  "geometry": {"coordinates":[-122.22058,47.782298],"type":"Point"}
}