{
  "type": "Feature",
  "properties": {
    "addr:full":"3350 Monte Villa Pkwy Bothell WA 98021",
    "addr:housenumber":"3350",
    "addr:postcode":"98021",
    "addr:street":"Monte Villa Pkwy",
    "iso:country":"US",
    "sg:address":"3350 Monte Villa Pkwy",
    "sg:city":"Bothell",
    "sg:classifiers":[
        {
            "category":"Manufacturing",
            "subcategory":"Electronics",
            "type":"Manufacturing & Wholesale Goods"
        }
    ],
    "sg:phone":"+1 425 485 6616",
    "sg:postcode":"98021",
    "sg:province":"WA",
    "sg:tags":[
        "equipment",
        "electronic",
        "supply"
    ],
    "wof:name":"FAI Electronics",
    "wof:placetype":"venue"
},
  "geometry": {"coordinates":[-122.189609,47.778032],"type":"Point"}
}