{
  "type": "Feature",
  "properties": {
    "addr:full":"4504 S Orcas St Seattle WA 98118",
    "addr:housenumber":"4504",
    "addr:postcode":"98118",
    "addr:street":"S Orcas St",
    "iso:country":"US",
    "sg:address":"4504 S Orcas St",
    "sg:city":"Seattle",
    "sg:classifiers":[
        {
            "category":"Organizations",
            "subcategory":"Religious Organization",
            "type":"Services"
        }
    ],
    "sg:phone":"+1 206 722 1236",
    "sg:postcode":"98118",
    "sg:province":"WA",
    "wof:name":"In-Time Ministries Fellowship",
    "wof:placetype":"venue"
},
  "geometry": {"coordinates":[-122.276438,47.551245],"type":"Point"}
}