{
  "type": "Feature",
  "properties": {
    "addr:full":"3676 Smugglers Cove Rd Greenbank WA 98253",
    "addr:housenumber":"3676",
    "addr:postcode":"98253",
    "addr:street":"Smugglers Cove Rd",
    "iso:country":"US",
    "sg:address":"3676 Smugglers Cove Rd",
    "sg:city":"Greenbank",
    "sg:classifiers":[
        {
            "category":"Building & Trades",
            "subcategory":"Construction",
            "type":"Services"
        }
    ],
    "sg:phone":"+1 360 678 4503",
    "sg:postcode":"98253",
    "sg:province":"WA",
    "sg:tags":[
        "concrete",
        "contractor"
    ],
    "wof:name":"Whidstar Homes",
    "wof:placetype":"venue"
},
  "geometry": {"coordinates":[-122.604911,48.076278],"type":"Point"}
}