{
  "type": "Feature",
  "properties": {
    "addr:full":"6715 Old Guide Rd Lynden WA 98264",
    "addr:housenumber":"6715",
    "addr:postcode":"98264",
    "addr:street":"Old Guide Rd",
    "iso:country":"US",
    "sg:address":"6715 Old Guide Rd",
    "sg:city":"Lynden",
    "sg:classifiers":[
        {
            "category":"Building & Trades",
            "subcategory":"Construction",
            "type":"Services"
        }
    ],
    "sg:phone":"+1 360 398 0806",
    "sg:postcode":"98264",
    "sg:province":"WA",
    "sg:tags":[
        "contractor"
    ],
    "wof:name":"Con Tane Inc",
    "wof:placetype":"venue"
},
  "geometry": {"coordinates":[-122.49696299999999,48.886429],"type":"Point"}
}