{
  "type": "Feature",
  "properties": {
    "addr:full":"701 Commercial Ave Anacortes WA 98221",
    "addr:housenumber":"701",
    "addr:postcode":"98221",
    "addr:street":"Commercial Ave",
    "iso:country":"US",
    "sg:address":"701 Commercial Ave",
    "sg:city":"Anacortes",
    "sg:classifiers":[
        {
            "category":"Fast Food",
            "type":"Food & Drink"
        },
        {
            "category":"Coffee & Tea",
            "type":"Food & Drink"
        },
        {
            "category":"Restaurant",
            "type":"Food & Drink"
        }
    ],
    "sg:phone":"+1 360 588 8518",
    "sg:postcode":"98221",
    "sg:province":"WA",
    "sg:tags":[
        "style",
        "family",
        "espresso",
        "lunch",
        "take",
        "brunch",
        "cafeteria",
        "breakfast"
    ],
    "sg:website":"http://www.superpages.com",
    "wof:name":"Island Cafe",
    "wof:placetype":"venue"
},
  "geometry": {"coordinates":[-122.612534,48.516659],"type":"Point"}
}