{
  "type": "Feature",
  "properties": {
    "addr:full":"4214 NE 72nd Ave Vancouver WA 98661",
    "addr:housenumber":"4214",
    "addr:postcode":"98661",
    "addr:street":"Ne 72Nd Ave",
    "iso:country":"US",
    "sg:address":"4214 NE 72nd Ave",
    "sg:city":"Vancouver",
    "sg:classifiers":[
        {
            "category":"Professional",
            "subcategory":"Management & Consulting",
            "type":"Services"
        }
    ],
    "sg:phone":"+1 360 883 5473",
    "sg:postcode":"98661",
    "sg:province":"WA",
    "sg:tags":[
        "logistics"
    ],
    "wof:name":"Cornerstone Logistics",
    "wof:placetype":"venue"
},
  "geometry": {"coordinates":[-122.599305,45.651085],"type":"Point"}
}