{
  "type": "Feature",
  "properties": {
    "addr:full":"38333 324th Pl SE Enumclaw WA 98022",
    "addr:housenumber":"38333",
    "addr:postcode":"98022",
    "addr:street":"324Th Pl Se",
    "iso:country":"US",
    "sg:address":"38333 324th Pl SE",
    "sg:city":"Enumclaw",
    "sg:classifiers":[
        {
            "category":"Farming",
            "subcategory":"Livestock Farm",
            "type":"Manufacturing & Wholesale Goods"
        }
    ],
    "sg:phone":"+1 360 886 9755",
    "sg:postcode":"98022",
    "sg:province":"WA",
    "sg:tags":[
        "animal",
        "general"
    ],
    "wof:name":"Mountain Meadow Farms",
    "wof:placetype":"venue"
},
  "geometry": {"coordinates":[-121.90881299999999,47.257308],"type":"Point"}
}