{
  "type": "Feature",
  "properties": {
    "addr:full":"1809 4th St Marysville WA 98270",
    "addr:housenumber":"1809",
    "addr:postcode":"98270",
    "addr:street":"4Th St",
    "iso:country":"US",
    "sg:address":"1809 4th St",
    "sg:city":"Marysville",
    "sg:classifiers":[
        {
            "category":"Health Services",
            "subcategory":"Doctor",
            "type":"Services"
        }
    ],
    "sg:phone":"+1 360 658 8007",
    "sg:postcode":"98270",
    "sg:province":"WA",
    "sg:tags":[
        "medical"
    ],
    "wof:name":"Abood Joseph Jr DDS",
    "wof:placetype":"venue"
},
  "geometry": {"coordinates":[-122.169749,48.051893],"type":"Point"}
}