{
  "type": "Feature",
  "properties": {
    "addr:full":"2711 NE 106th Pl Seattle WA 98125",
    "addr:housenumber":"2711",
    "addr:postcode":"98125",
    "addr:street":"Ne 106Th Pl",
    "iso:country":"US",
    "sg:address":"2711 NE 106th Pl",
    "sg:city":"Seattle",
    "sg:classifiers":[
        {
            "category":"Building & Trades",
            "subcategory":"Landscaping Services",
            "type":"Services"
        }
    ],
    "sg:phone":"+1 206 306 0673",
    "sg:postcode":"98125",
    "sg:province":"WA",
    "sg:tags":[
        "landscape"
    ],
    "wof:name":"Selc Inc",
    "wof:placetype":"venue"
},
  "geometry": {"coordinates":[-122.298389,47.705663],"type":"Point"}
}