{
  "type": "Feature",
  "properties": {
    "addr:full":"8227 Corliss Ave N Seattle WA 98103",
    "addr:housenumber":"8227",
    "addr:postcode":"98103",
    "addr:street":"Corliss Ave N",
    "iso:country":"US",
    "sg:address":"8227 Corliss Ave N",
    "sg:city":"Seattle",
    "sg:classifiers":[
        {
            "category":"Professional",
            "type":"Services"
        }
    ],
    "sg:phone":"+1 206 525 3994",
    "sg:postcode":"98103",
    "sg:province":"WA",
    "wof:name":"Livak",
    "wof:placetype":"venue"
},
  "geometry": {"coordinates":[-122.33113400000001,47.690228],"type":"Point"}
}