{
  "type": "Feature",
  "properties": {
    "addr:full":"625 8th St Hoquiam WA 98550",
    "addr:housenumber":"625",
    "addr:postcode":"98550",
    "addr:street":"8Th St",
    "iso:country":"US",
    "sg:address":"625 8th St",
    "sg:city":"Hoquiam",
    "sg:classifiers":[
        {
            "category":"Government",
            "subcategory":"Fire Station",
            "type":"Public Place"
        }
    ],
    "sg:phone":"+1 360 532 3324",
    "sg:postcode":"98550",
    "sg:province":"WA",
    "sg:tags":[
        "department"
    ],
    "wof:name":"Hoquiam Fire Dept",
    "wof:placetype":"venue"
},
  "geometry": {"coordinates":[-123.886962,46.974846],"type":"Point"}
}