{
  "type": "Feature",
  "properties": {
    "addr:full":"5803 NE 34th St Apt E Vancouver WA 98661",
    "addr:housenumber":"5803",
    "addr:postcode":"98661",
    "addr:street":"Ne 34Th St Apt E",
    "iso:country":"US",
    "sg:address":"5803 NE 34th St Apt E",
    "sg:city":"Vancouver",
    "sg:classifiers":[
        {
            "category":"Recreation",
            "subcategory":"Campground",
            "type":"Entertainment"
        }
    ],
    "sg:phone":"+1 360 750 5818",
    "sg:postcode":"98661",
    "sg:province":"WA",
    "sg:tags":[
        "recreational",
        "park",
        "vehicle"
    ],
    "wof:name":"Campsite Northwest Campsitenwc",
    "wof:placetype":"venue"
},
  "geometry": {"coordinates":[-122.61200599999999,45.646759],"type":"Point"}
}