{
  "type": "Feature",
  "properties": {
    "addr:full":"18501 Pacific Ave S Spanaway WA 98387",
    "addr:housenumber":"18501",
    "addr:postcode":"98387",
    "addr:street":"Pacific Ave S Spanaway",
    "iso:country":"US",
    "sg:address":"18501 Pacific Ave S",
    "sg:city":"Spanaway",
    "sg:classifiers":[
        {
            "category":"Autos & Motor Vehicles",
            "subcategory":"Recreational Vehicle Sales",
            "type":"Retail Goods"
        }
    ],
    "sg:phone":"+1 253 847 0222",
    "sg:postcode":"98387",
    "sg:province":"WA",
    "sg:tags":[
        "mobile",
        "home",
        "used"
    ],
    "wof:name":"Mobile Corral Inc West",
    "wof:placetype":"venue"
},
  "geometry": {"coordinates":[-122.43496399999999,47.089539],"type":"Point"}
}