{
  "type": "Feature",
  "properties": {
    "addr:full":"5405 Leary Ave NW Seattle WA 98107",
    "addr:housenumber":"5405",
    "addr:postcode":"98107",
    "addr:street":"Leary Ave Nw",
    "iso:country":"US",
    "sg:address":"5405 Leary Ave NW",
    "sg:city":"Seattle",
    "sg:classifiers":[
        {
            "category":"Bars & Pubs",
            "type":"Food & Drink"
        },
        {
            "category":"Restaurant",
            "type":"Food & Drink"
        }
    ],
    "sg:phone":"+1 206 783 7777",
    "sg:postcode":"98107",
    "sg:province":"WA",
    "sg:tags":[
        "style",
        "family",
        "pizza"
    ],
    "sg:website":"www.zaydabuddyspizza.com/",
    "wof:name":"Zayda Buddy's Pizza & Bar",
    "wof:placetype":"venue"
},
  "geometry": {"coordinates":[-122.38247200000001,47.666958],"type":"Point"}
}