{
  "type": "Feature",
  "properties": {
    "addr:full":"408 Antles St Wenatchee WA 98801",
    "addr:housenumber":"408",
    "addr:postcode":"98801",
    "addr:street":"Antles St",
    "iso:country":"US",
    "sg:address":"408 Antles St",
    "sg:city":"Wenatchee",
    "sg:classifiers":[
        {
            "category":"Shopping",
            "subcategory":"Clothing, Apparel, & Fashions",
            "type":"Retail Goods"
        }
    ],
    "sg:phone":"+1 509 663 3654",
    "sg:postcode":"98801",
    "sg:province":"WA",
    "sg:tags":[
        "family"
    ],
    "wof:name":"Manuel Figueroa Sales",
    "wof:placetype":"venue"
},
  "geometry": {"coordinates":[-120.30426900000001,47.400501],"type":"Point"}
}