{
  "type": "Feature",
  "properties": {
    "addr:full":"106 N 10th Ave Pasco WA 99301",
    "addr:housenumber":"106",
    "addr:postcode":"99301",
    "addr:street":"N 10Th Ave",
    "iso:country":"US",
    "sg:address":"106 N 10th Ave",
    "sg:city":"Pasco",
    "sg:classifiers":[
        {
            "category":"Food & Beverages",
            "subcategory":"Groceries & Convenience Stores",
            "type":"Retail Goods"
        }
    ],
    "sg:phone":"+1 509 547 1292",
    "sg:postcode":"99301",
    "sg:province":"WA",
    "wof:name":"Mi Tiendita Mexicana",
    "wof:placetype":"venue"
},
  "geometry": {"coordinates":[-119.100998,46.228699],"type":"Point"}
}