{
  "type": "Feature",
  "properties": {
    "addr:full":"325 S 1st Ave Walla Walla WA 99362",
    "addr:housenumber":"325",
    "addr:postcode":"99362",
    "addr:street":"S 1St Ave",
    "iso:country":"US",
    "sg:address":"325 S 1st Ave",
    "sg:city":"Walla Walla",
    "sg:classifiers":[
        {
            "category":"Organizations",
            "subcategory":"Religious Organization",
            "type":"Services"
        }
    ],
    "sg:phone":"+1 509 525 1093",
    "sg:postcode":"99362",
    "sg:province":"WA",
    "sg:website":"www.pcusa.org",
    "wof:name":"First Presbyterian Church",
    "wof:placetype":"venue"
},
  "geometry": {"coordinates":[-118.335384,46.064035],"type":"Point"}
}