{
  "type": "Feature",
  "properties": {
    "addr:full":"15703 Hwy 99 Lynnwood WA 98087",
    "addr:housenumber":"15703",
    "addr:postcode":"98087",
    "addr:street":"Hwy 99",
    "iso:country":"US",
    "sg:address":"15703 Hwy 99",
    "sg:city":"Lynnwood",
    "sg:classifiers":[
        {
            "category":"Retail",
            "subcategory":"Auto Repair",
            "type":"Services"
        }
    ],
    "sg:phone":"+1 425 220 7539",
    "sg:postcode":"98087",
    "sg:province":"WA",
    "sg:tags":[
        "general"
    ],
    "wof:name":"Evergreen Auto Repair",
    "wof:placetype":"venue"
},
  "geometry": {"coordinates":[-122.289754,47.855995],"type":"Point"}
}