{
  "type": "Feature",
  "properties": {
    "addr:full":"2180 Opdal Rd E Port Orchard WA 98366",
    "addr:housenumber":"2180",
    "addr:postcode":"98366",
    "addr:street":"Opdal Rd E",
    "iso:country":"US",
    "sg:address":"2180 Opdal Rd E",
    "sg:city":"Port Orchard",
    "sg:classifiers":[
        {
            "category":"Professional",
            "type":"Services"
        }
    ],
    "sg:phone":"+1 360 871 2026",
    "sg:postcode":"98366",
    "sg:province":"WA",
    "sg:tags":[
        "establishment"
    ],
    "wof:name":"P T Supre",
    "wof:placetype":"venue"
},
  "geometry": {"coordinates":[-122.57529700000001,47.560385],"type":"Point"}
}