{
  "type": "Feature",
  "properties": {
    "addr:full":"676 Ocean Shores Blvd NW Ocean Shores WA 98569",
    "addr:housenumber":"676",
    "addr:postcode":"98569",
    "addr:street":"Ocean Shores Blvd Nw",
    "iso:country":"US",
    "sg:address":"676 Ocean Shores Blvd NW",
    "sg:city":"Ocean Shores",
    "sg:classifiers":[
        {
            "category":"Travel",
            "subcategory":"Hotels & Motels",
            "type":"Entertainment"
        }
    ],
    "sg:phone":"+1 360 289 3012",
    "sg:postcode":"98569",
    "sg:province":"WA",
    "sg:tags":[
        "operation"
    ],
    "wof:name":"Pacific Nantucket Inn",
    "wof:placetype":"venue"
},
  "geometry": {"coordinates":[-124.165997,47.002053],"type":"Point"}
}