{
  "type": "Feature",
  "properties": {
    "addr:full":"1010 U St NW Auburn WA 98001",
    "addr:housenumber":"1010",
    "addr:postcode":"98001",
    "addr:street":"U St Nw",
    "iso:country":"US",
    "sg:address":"1010 U St NW",
    "sg:city":"Auburn",
    "sg:classifiers":[
        {
            "category":"Manufacturing",
            "subcategory":"Tools & Machinery",
            "type":"Manufacturing & Wholesale Goods"
        }
    ],
    "sg:phone":"+1 253 288 9215",
    "sg:postcode":"98001",
    "sg:province":"WA",
    "sg:tags":[
        "control",
        "material",
        "spill"
    ],
    "wof:name":"Enpac Corp",
    "wof:placetype":"venue"
},
  "geometry": {"coordinates":[-122.257671,47.329612],"type":"Point"}
}