{
  "type": "Feature",
  "properties": {
    "addr:full":"1101 Pacific Ave Tacoma WA 98402",
    "addr:housenumber":"1101",
    "addr:postcode":"98402",
    "addr:street":"Pacific Ave",
    "iso:country":"US",
    "sg:address":"1101 Pacific Ave",
    "sg:city":"Tacoma",
    "sg:classifiers":[
        {
            "category":"Professional",
            "subcategory":"Business Services",
            "type":"Services"
        }
    ],
    "sg:phone":"+1 253 680 7770",
    "sg:postcode":"98402",
    "sg:province":"WA",
    "sg:tags":[
        "consultant",
        "coach"
    ],
    "sg:website":"http://www.score199.mv.com",
    "wof:name":"S C O R E 385",
    "wof:placetype":"venue"
},
  "geometry": {"coordinates":[-122.438637,47.253399],"type":"Point"}
}