{
  "type": "Feature",
  "properties": {
    "addr:full":"756 Officers Row Vancouver WA 98661",
    "addr:housenumber":"756",
    "addr:postcode":"98661",
    "addr:street":"Officers Row",
    "iso:country":"US",
    "sg:address":"756 Officers Row",
    "sg:city":"Vancouver",
    "sg:classifiers":[
        {
            "category":"Professional",
            "subcategory":"Computer Services",
            "type":"Services"
        },
        {
            "category":"Shopping",
            "subcategory":"Computers & Home Electronics",
            "type":"Retail Goods"
        }
    ],
    "sg:phone":"+1 360 737 3734",
    "sg:postcode":"98661",
    "sg:province":"WA",
    "sg:tags":[
        "prepackaged",
        "software"
    ],
    "wof:name":"Prescient Software LLC",
    "wof:placetype":"venue"
},
  "geometry": {"coordinates":[-122.66399199999999,45.629652],"type":"Point"}
}