{
  "type": "Feature",
  "properties": {
    "addr:full":"119 Yesler Wy Seattle WA 98104",
    "addr:housenumber":"119",
    "addr:postcode":"98104",
    "addr:street":"Yesler Wy",
    "iso:country":"US",
    "sg:address":"119 Yesler Wy",
    "sg:city":"Seattle",
    "sg:classifiers":[
        {
            "category":"Education",
            "subcategory":"Music School",
            "type":"Public Place"
        }
    ],
    "sg:phone":"+1 206 622 2277",
    "sg:postcode":"98104",
    "sg:province":"WA",
    "sg:tags":[
        "instrument",
        "teacher",
        "musical"
    ],
    "sg:website":"www.bassnw.com/",
    "wof:name":"Bass NW",
    "wof:placetype":"venue"
},
  "geometry": {"coordinates":[-122.333,47.601601],"type":"Point"}
}