{
  "type": "Feature",
  "properties": {
    "addr:full":"102 15th Ave E Seattle WA 98112",
    "addr:housenumber":"102",
    "addr:postcode":"98112",
    "addr:street":"15Th Ave E",
    "iso:country":"US",
    "sg:address":"102 15th Ave E",
    "sg:city":"Seattle",
    "sg:classifiers":[
        {
            "category":"Food & Beverages",
            "subcategory":"Specialty",
            "type":"Retail Goods"
        }
    ],
    "sg:phone":"+1 206 322 6477",
    "sg:postcode":"98112",
    "sg:province":"WA",
    "sg:tags":[
        "tea",
        "coffee"
    ],
    "wof:name":"Insomniax Coffee",
    "wof:placetype":"venue"
},
  "geometry": {"coordinates":[-122.31264899999999,47.619625],"type":"Point"}
}