{
  "type": "Feature",
  "properties": {
    "addr:full":"1200 6th Ave Seattle WA 98101",
    "addr:housenumber":"1200",
    "addr:postcode":"98101",
    "addr:street":"6Th Ave",
    "iso:country":"US",
    "sg:address":"1200 6th Ave",
    "sg:city":"Seattle",
    "sg:classifiers":[
        {
            "category":"Government",
            "subcategory":"Office",
            "type":"Public Place"
        }
    ],
    "sg:phone":"+1 206 553 8306",
    "sg:postcode":"98101",
    "sg:province":"WA",
    "sg:tags":[
        "violation",
        "environmental",
        "criminal",
        "investigation",
        "la"
    ],
    "wof:name":"C I D Investigations",
    "wof:placetype":"venue"
},
  "geometry": {"coordinates":[-122.33264200000001,47.609158],"type":"Point"}
}