{
  "type": "Feature",
  "properties": {
    "addr:full":"12414 112th Ave E Puyallup WA 98374",
    "addr:housenumber":"12414",
    "addr:postcode":"98374",
    "addr:street":"112Th Ave E",
    "iso:country":"US",
    "sg:address":"12414 112th Ave E",
    "sg:city":"Puyallup",
    "sg:classifiers":[
        {
            "category":"Professional",
            "subcategory":"Management & Consulting",
            "type":"Services"
        }
    ],
    "sg:phone":"+1 253 435 7887",
    "sg:postcode":"98374",
    "sg:province":"WA",
    "sg:tags":[
        "business"
    ],
    "wof:name":"Diane Harrison Consultant",
    "wof:placetype":"venue"
},
  "geometry": {"coordinates":[-122.279325,47.143453],"type":"Point"}
}