{
  "type": "Feature",
  "properties": {
    "iso:country":"US",
    "sg:address":"3312 Woodard Green Dr NE",
    "sg:city":"Olympia",
    "sg:classifiers":[
        {
            "category":"Shopping",
            "subcategory":"Computers & Home Electronics",
            "type":"Retail Goods"
        }
    ],
    "sg:phone":"+1 360 455 9528",
    "sg:postcode":"98506",
    "sg:province":"WA",
    "wof:name":"Keenefisher Computer Services",
    "wof:placetype":"venue"
},
  "geometry": {"coordinates":[-122.84796799999999,47.058739],"type":"Point"}
}