{
  "type": "Feature",
  "properties": {
    "addr:full":"14922 Valley View Dr Mount Vernon WA 98273",
    "addr:housenumber":"14922",
    "addr:postcode":"98273",
    "addr:street":"Valley View Dr",
    "iso:country":"US",
    "sg:address":"14922 Valley View Dr",
    "sg:city":"Mount Vernon",
    "sg:classifiers":[
        {
            "category":"Manufacturing",
            "subcategory":"Glass & Minerals",
            "type":"Manufacturing & Wholesale Goods"
        }
    ],
    "sg:phone":"+1 360 424 5846",
    "sg:postcode":"98273",
    "sg:province":"WA",
    "sg:tags":[
        "mfg"
    ],
    "wof:name":"Sharyn L Sowell",
    "wof:placetype":"venue"
},
  "geometry": {"coordinates":[-122.370671,48.431285],"type":"Point"}
}