{
  "type": "Feature",
  "properties": {
    "addr:full":"219 140th Ave SE Bellevue WA 98005",
    "addr:housenumber":"219",
    "addr:postcode":"98005",
    "addr:street":"140Th Ave Se",
    "iso:country":"US",
    "sg:address":"219 140th Ave SE",
    "sg:city":"Bellevue",
    "sg:classifiers":[
        {
            "category":"Home & Garden",
            "subcategory":"Building Materials",
            "type":"Retail Goods"
        }
    ],
    "sg:phone":"+1 206 300 5487",
    "sg:postcode":"98005",
    "sg:province":"WA",
    "wof:name":"Sib Lumber Co LLC",
    "wof:placetype":"venue"
},
  "geometry": {"coordinates":[-122.153576,47.607822],"type":"Point"}
}