{
  "type": "Feature",
  "properties": {
    "iso:country":"US",
    "sg:address":"16118 72nd Ave W",
    "sg:city":"Edmonds",
    "sg:classifiers":[
        {
            "category":"Banks & Credit Unions",
            "subcategory":"Financial Services",
            "type":"Services"
        }
    ],
    "sg:phone":"+1 425 745 4384",
    "sg:postcode":"98026",
    "sg:province":"WA",
    "sg:tags":[
        "security",
        "investor"
    ],
    "wof:name":"Mutual Bancshares Capital Inc",
    "wof:placetype":"venue"
},
  "geometry": {"coordinates":[-122.330538,47.850293],"type":"Point"}
}