{
  "type": "Feature",
  "properties": {
    "addr:full":"12826 NE 108th Pl Kirkland WA 98033",
    "addr:housenumber":"12826",
    "addr:postcode":"98033",
    "addr:street":"Ne 108Th Pl",
    "iso:country":"US",
    "sg:address":"12826 NE 108th Pl",
    "sg:city":"Kirkland",
    "sg:classifiers":[
        {
            "category":"Banks & Credit Unions",
            "subcategory":"Investment Brokerage",
            "type":"Services"
        }
    ],
    "sg:phone":"+1 425 822 5854",
    "sg:postcode":"98033",
    "sg:province":"WA",
    "sg:tags":[
        "advisory",
        "planner",
        "financial"
    ],
    "wof:name":"Judal Enterprises",
    "wof:placetype":"venue"
},
  "geometry": {"coordinates":[-122.169889,47.697384],"type":"Point"}
}