{
  "type": "Feature",
  "properties": {
    "addr:full":"14210 37th Avenue S Tukwila WA 98168",
    "addr:housenumber":"14210",
    "addr:postcode":"98168",
    "addr:street":"37Th Avenue S",
    "iso:country":"US",
    "sg:address":"14210 37th Avenue S",
    "sg:city":"Tukwila",
    "sg:classifiers":[
        {
            "category":"Real Estate",
            "subcategory":"Real Estate Operator",
            "type":"Services"
        }
    ],
    "sg:phone":"+1 206 248 2323",
    "sg:postcode":"98168",
    "sg:province":"WA",
    "sg:tags":[
        "apartment"
    ],
    "wof:name":"Mountain View Apts",
    "wof:placetype":"venue"
},
  "geometry": {"coordinates":[-122.28664000000001,47.475238],"type":"Point"}
}