{
  "type": "Feature",
  "properties": {
    "addr:full":"2226 1st Ave Seattle WA 98121",
    "addr:housenumber":"2226",
    "addr:postcode":"98121",
    "addr:street":"1St Ave",
    "iso:country":"US",
    "sg:address":"2226 1st Ave",
    "sg:city":"Seattle",
    "sg:classifiers":[
        {
            "category":"Bars & Pubs",
            "subcategory":"Lounge",
            "type":"Food & Drink"
        },
        {
            "category":"Restaurant",
            "type":"Food & Drink"
        }
    ],
    "sg:phone":"+1 206 441 1000",
    "sg:postcode":"98121",
    "sg:province":"WA",
    "sg:tags":[
        "italian"
    ],
    "sg:website":"www.listbelltown.com/",
    "wof:name":"List",
    "wof:placetype":"venue"
},
  "geometry": {"coordinates":[-122.346114,47.613156],"type":"Point"}
}