{
  "type": "Feature",
  "properties": {
    "addr:full":"4770 S Discovery Rd Port Townsend WA 98368",
    "addr:housenumber":"4770",
    "addr:postcode":"98368",
    "addr:street":"S Discovery Rd",
    "iso:country":"US",
    "sg:address":"4770 S Discovery Rd",
    "sg:city":"Port Townsend",
    "sg:classifiers":[
        {
            "category":"Freight",
            "type":"Transportation"
        }
    ],
    "sg:phone":"+1 360 385 5314",
    "sg:postcode":"98368",
    "sg:province":"WA",
    "sg:tags":[
        "courier"
    ],
    "wof:name":"UPS",
    "wof:placetype":"venue"
},
  "geometry": {"coordinates":[-122.822031,48.049498],"type":"Point"}
}