{
  "type": "Feature",
  "properties": {
    "addr:full":"18431 E State Rte 106 Belfair WA 98528",
    "addr:housenumber":"18431",
    "addr:postcode":"98528",
    "addr:street":"E State Rte 106",
    "iso:country":"US",
    "sg:address":"18431 E State Rte 106",
    "sg:city":"Belfair",
    "sg:classifiers":[
        {
            "category":"Professional",
            "subcategory":"Management & Consulting",
            "type":"Services"
        }
    ],
    "sg:phone":"+1 360 275 4621",
    "sg:postcode":"98528",
    "sg:province":"WA",
    "wof:name":"Walterson S Darell",
    "wof:placetype":"venue"
},
  "geometry": {"coordinates":[-122.854552,47.427216],"type":"Point"}
}