{
  "type": "Feature",
  "properties": {
    "addr:full":"415 SE 117th Ave Vancouver WA 98683",
    "addr:housenumber":"415",
    "addr:postcode":"98683",
    "addr:street":"Se 117Th Ave",
    "iso:country":"US",
    "sg:address":"415 SE 117th Ave",
    "sg:city":"Vancouver",
    "sg:classifiers":[
        {
            "category":"Social Services",
            "subcategory":"Retirement Home",
            "type":"Services"
        }
    ],
    "sg:phone":"+1 877 778 2779",
    "sg:postcode":"98683",
    "sg:province":"WA",
    "sg:website":"www.lifestylesllc.com/senior_liv...",
    "wof:name":"The Quarry Senior Living",
    "wof:placetype":"venue"
},
  "geometry": {"coordinates":[-122.55168399999999,45.618109],"type":"Point"}
}