{
  "type": "Feature",
  "properties": {
    "addr:full":"130 2nd Ave Mansfield WA 98830",
    "addr:housenumber":"130",
    "addr:postcode":"98830",
    "addr:street":"2Nd Ave",
    "iso:country":"US",
    "sg:address":"130 2nd Ave",
    "sg:city":"Mansfield",
    "sg:classifiers":[
        {
            "category":"Organizations",
            "subcategory":"Religious Organization",
            "type":"Services"
        }
    ],
    "sg:phone":"+1 509 683 1207",
    "sg:postcode":"98830",
    "sg:province":"WA",
    "sg:tags":[
        "church"
    ],
    "wof:name":"United Protestant Christian",
    "wof:placetype":"venue"
},
  "geometry": {"coordinates":[-119.636911,47.813959],"type":"Point"}
}