{
  "type": "Feature",
  "properties": {
    "addr:full":"221 W 1st Ave Spokane WA 99201",
    "addr:housenumber":"221",
    "addr:postcode":"99201",
    "addr:street":"W 1St Ave",
    "iso:country":"US",
    "sg:address":"221 W 1st Ave",
    "sg:city":"Spokane",
    "sg:classifiers":[
        {
            "category":"Insurance",
            "subcategory":"Insurance Agent",
            "type":"Services"
        }
    ],
    "sg:phone":"+1 509 325 2711",
    "sg:postcode":"99201",
    "sg:province":"WA",
    "sg:website":"www.lqoa.com",
    "wof:name":"Life Quotes Of America Inc",
    "wof:placetype":"venue"
},
  "geometry": {"coordinates":[-117.41553500000001,47.656632],"type":"Point"}
}