{
  "type": "Feature",
  "properties": {
    "addr:full":"4310 70th Ave E Fife WA 98424",
    "addr:housenumber":"4310",
    "addr:postcode":"98424",
    "addr:street":"70Th Ave E",
    "iso:country":"US",
    "sg:address":"4310 70th Ave E",
    "sg:city":"Fife",
    "sg:classifiers":[
        {
            "category":"Manufacturing",
            "subcategory":"Metals",
            "type":"Manufacturing & Wholesale Goods"
        }
    ],
    "sg:phone":"+1 253 922 7390",
    "sg:postcode":"98424",
    "sg:province":"WA",
    "sg:tags":[
        "steel"
    ],
    "sg:website":"www.aco.com",
    "wof:name":"ACO Fabrication Inc",
    "wof:placetype":"venue"
},
  "geometry": {"coordinates":[-122.33659299999999,47.217572],"type":"Point"}
}