{
  "type": "Feature",
  "properties": {
    "addr:full":"436 Proffitt Rd Centralia WA 98531",
    "addr:housenumber":"436",
    "addr:postcode":"98531",
    "addr:street":"Proffitt Rd",
    "iso:country":"US",
    "sg:address":"436 Proffitt Rd",
    "sg:city":"Centralia",
    "sg:classifiers":[
        {
            "category":"Professional",
            "type":"Services"
        },
        {
            "category":"Shopping",
            "subcategory":"Bicycles & Sporting Goods",
            "type":"Retail Goods"
        }
    ],
    "sg:phone":"+1 360 330 9929",
    "sg:postcode":"98531",
    "sg:province":"WA",
    "sg:tags":[
        "establishment"
    ],
    "wof:name":"Proffitt Valley Tack/White",
    "wof:placetype":"venue"
},
  "geometry": {"coordinates":[-122.870242,46.671594],"type":"Point"}
}