{
  "type": "Feature",
  "properties": {
    "addr:full":"12835 Bellevue Redmond Rd Bellevue WA 98005",
    "addr:housenumber":"12835",
    "addr:postcode":"98005",
    "addr:street":"Bellevue Redmond Rd",
    "iso:country":"US",
    "sg:address":"12835 Bellevue Redmond Rd",
    "sg:city":"Bellevue",
    "sg:classifiers":[
        {
            "category":"Professional",
            "type":"Services"
        }
    ],
    "sg:phone":"+1 425 637 0090",
    "sg:postcode":"98005",
    "sg:province":"WA",
    "wof:name":"Qvd USA LLC",
    "wof:placetype":"venue"
},
  "geometry": {"coordinates":[-122.164508,47.621994],"type":"Point"}
}