{
  "type": "Feature",
  "properties": {
    "addr:full":"15501 Waynita Way NE Bothell WA 98011",
    "addr:housenumber":"15501",
    "addr:postcode":"98011",
    "addr:street":"Waynita Way Ne",
    "iso:country":"US",
    "sg:address":"15501 Waynita Way NE",
    "sg:city":"Bothell",
    "sg:classifiers":[
        {
            "category":"Retail",
            "subcategory":"Repair Shop",
            "type":"Services"
        }
    ],
    "sg:phone":"+1 206 992 0066",
    "sg:postcode":"98011",
    "sg:province":"WA",
    "sg:tags":[
        "equipment",
        "industrial"
    ],
    "wof:name":"Eastside Equipment",
    "wof:placetype":"venue"
},
  "geometry": {"coordinates":[-122.21039500000001,47.741574],"type":"Point"}
}