{
  "type": "Feature",
  "properties": {
    "addr:full":"17716 NE 27th St Redmond WA 98052",
    "addr:housenumber":"17716",
    "addr:postcode":"98052",
    "addr:street":"Ne 27Th St",
    "iso:country":"US",
    "sg:address":"17716 NE 27th St",
    "sg:city":"Redmond",
    "sg:classifiers":[
        {
            "category":"Organizations",
            "subcategory":"Membership Organization",
            "type":"Services"
        }
    ],
    "sg:phone":"+1 425 558 4251",
    "sg:postcode":"98052",
    "sg:province":"WA",
    "wof:name":"Great NW Charitable Foundation",
    "wof:placetype":"venue"
},
  "geometry": {"coordinates":[-122.10189699999999,47.634448],"type":"Point"}
}