{
  "type": "Feature",
  "properties": {
    "addr:full":"1701 E Evergreen Blvd Vancouver WA 98661",
    "addr:housenumber":"1701",
    "addr:postcode":"98661",
    "addr:street":"E Evergreen Blvd",
    "iso:country":"US",
    "sg:address":"1701 E Evergreen Blvd",
    "sg:city":"Vancouver",
    "sg:classifiers":[
        {
            "category":"Insurance",
            "subcategory":"Insurance Agent",
            "type":"Services"
        }
    ],
    "sg:phone":"+1 360 992 0826",
    "sg:postcode":"98661",
    "sg:province":"WA",
    "wof:name":"United American Insurance Co",
    "wof:placetype":"venue"
},
  "geometry": {"coordinates":[-122.653336,45.625917],"type":"Point"}
}