{
  "type": "Feature",
  "properties": {
    "addr:full":"7337 39th Ave SW Seattle WA 98136",
    "addr:housenumber":"7337",
    "addr:postcode":"98136",
    "addr:street":"39Th Ave Sw",
    "iso:country":"US",
    "sg:address":"7337 39th Ave SW",
    "sg:city":"Seattle",
    "sg:classifiers":[
        {
            "category":"Recreation",
            "type":"Entertainment"
        }
    ],
    "sg:phone":"+1 206 932 2862",
    "sg:postcode":"98136",
    "sg:province":"WA",
    "sg:tags":[
        "charter",
        "boat"
    ],
    "sg:website":"www.evansmaritime.com",
    "wof:name":"Evans Maritime Co",
    "wof:placetype":"venue"
},
  "geometry": {"coordinates":[-122.382035,47.535779],"type":"Point"}
}