{
  "type": "Feature",
  "properties": {
    "addr:full":"1551 McHugh Ave Enumclaw WA 98022",
    "addr:housenumber":"1551",
    "addr:postcode":"98022",
    "addr:street":"Mchugh Ave",
    "iso:country":"US",
    "sg:address":"1551 McHugh Ave",
    "sg:city":"Enumclaw",
    "sg:classifiers":[
        {
            "category":"Food & Beverages",
            "subcategory":"Groceries & Convenience Stores",
            "type":"Retail Goods"
        }
    ],
    "sg:phone":"+1 360 825 4481",
    "sg:postcode":"98022",
    "sg:province":"WA",
    "sg:tags":[
        "grocer"
    ],
    "wof:name":"Erwin's Grocery",
    "wof:placetype":"venue"
},
  "geometry": {"coordinates":[-121.98858199999999,47.213984],"type":"Point"}
}