{
  "type": "Feature",
  "properties": {
    "addr:full":"1510 E Francis Ave Spokane WA 99208",
    "addr:housenumber":"1510",
    "addr:postcode":"99208",
    "addr:street":"E Francis Ave",
    "iso:country":"US",
    "sg:address":"1510 E Francis Ave",
    "sg:city":"Spokane",
    "sg:classifiers":[
        {
            "category":"Personal",
            "subcategory":"Beauty Salon",
            "type":"Services"
        }
    ],
    "sg:phone":"+1 509 489 5349",
    "sg:postcode":"99208",
    "sg:province":"WA",
    "sg:tags":[
        "shop"
    ],
    "wof:name":"Century Hair Shoppe",
    "wof:placetype":"venue"
},
  "geometry": {"coordinates":[-117.388645,47.714927],"type":"Point"}
}