{
  "type": "Feature",
  "properties": {
    "addr:full":"506 Washington St Vancouver WA 98660",
    "addr:housenumber":"506",
    "addr:postcode":"98660",
    "addr:street":"Washington St",
    "iso:country":"US",
    "sg:address":"506 Washington St",
    "sg:city":"Vancouver",
    "sg:classifiers":[
        {
            "category":"Shopping",
            "subcategory":"Used Merchandise",
            "type":"Retail Goods"
        }
    ],
    "sg:phone":"+1 360 699 5626",
    "sg:postcode":"98660",
    "sg:province":"WA",
    "sg:tags":[
        "instrument",
        "teacher",
        "pawnshop",
        "musical"
    ],
    "wof:name":"Briz Loan & Guitar",
    "wof:placetype":"venue"
},
  "geometry": {"coordinates":[-122.672997,45.625401],"type":"Point"}
}