{
  "type": "Feature",
  "properties": {
    "addr:full":"1212 E Wishkah St Aberdeen WA 98520",
    "addr:housenumber":"1212",
    "addr:postcode":"98520",
    "addr:street":"E Wishkah St",
    "iso:country":"US",
    "sg:address":"1212 E Wishkah St",
    "sg:city":"Aberdeen",
    "sg:phone":"+1 360 533 4830",
    "sg:postcode":"98520",
    "sg:province":"WA",
    "wof:name":"Los Arcos",
    "wof:placetype":"venue"
},
  "geometry": {"coordinates":[-123.830994,46.967844],"type":"Point"}
}