{
  "type": "Feature",
  "properties": {
    "addr:full":"1101 Broadway St Vancouver WA 98660",
    "addr:housenumber":"1101",
    "addr:postcode":"98660",
    "addr:street":"Broadway St",
    "iso:country":"US",
    "sg:address":"1101 Broadway St",
    "sg:city":"Vancouver",
    "sg:classifiers":[
        {
            "category":"Professional",
            "subcategory":"Management & Consulting",
            "type":"Services"
        }
    ],
    "sg:phone":"+1 360 567 1070",
    "sg:postcode":"98660",
    "sg:province":"WA",
    "wof:name":"Southwest Wrkforce Dev Council",
    "wof:placetype":"venue"
},
  "geometry": {"coordinates":[-122.670511,45.630286],"type":"Point"}
}