{
  "type": "Feature",
  "properties": {
    "addr:full":"28411 NE 122nd Ave Battle Ground WA 98604",
    "addr:housenumber":"28411",
    "addr:postcode":"98604",
    "addr:street":"Ne 122Nd Ave",
    "iso:country":"US",
    "sg:address":"28411 NE 122nd Ave",
    "sg:city":"Battle Ground",
    "sg:classifiers":[
        {
            "category":"Wholesale",
            "subcategory":"Farm Supplies",
            "type":"Manufacturing & Wholesale Goods"
        }
    ],
    "sg:phone":"+1 360 666 4738",
    "sg:postcode":"98604",
    "sg:province":"WA",
    "sg:tags":[
        "sewing",
        "livestock"
    ],
    "wof:name":"Between The Oaks",
    "wof:placetype":"venue"
},
  "geometry": {"coordinates":[-122.547708,45.825303],"type":"Point"}
}