{
  "type": "Feature",
  "properties": {
    "addr:full":"40005 NE 193rd Ave Amboy WA 98601",
    "addr:housenumber":"40005",
    "addr:postcode":"98601",
    "addr:street":"Ne 193Rd Ave",
    "iso:country":"US",
    "sg:address":"40005 NE 193rd Ave",
    "sg:city":"Amboy",
    "sg:classifiers":[
        {
            "category":"Building & Trades",
            "subcategory":"Construction",
            "type":"Services"
        }
    ],
    "sg:phone":"+1 360 892 2778",
    "sg:postcode":"98601",
    "sg:province":"WA",
    "sg:tags":[
        "house"
    ],
    "wof:name":"AGC Home Improvement",
    "wof:placetype":"venue"
},
  "geometry": {"coordinates":[-122.473691,45.916283],"type":"Point"}
}