{
  "type": "Feature",
  "properties": {
    "addr:full":"2201 S 64th Ave Yakima WA 98903",
    "addr:housenumber":"2201",
    "addr:postcode":"98903",
    "addr:street":"S 64Th Ave",
    "iso:country":"US",
    "sg:address":"2201 S 64th Ave",
    "sg:city":"Yakima",
    "sg:classifiers":[
        {
            "category":"Real Estate",
            "subcategory":"Real Estate Operator",
            "type":"Services"
        }
    ],
    "sg:phone":"+1 509 972 2347",
    "sg:postcode":"98903",
    "sg:province":"WA",
    "sg:tags":[
        "building",
        "nonresidential"
    ],
    "wof:name":"Minnwash Properties Inc",
    "wof:placetype":"venue"
},
  "geometry": {"coordinates":[-120.593734,46.56644],"type":"Point"}
}