{
  "type": "Feature",
  "properties": {
    "addr:full":"3834 Pacific Ave Tacoma WA 98418",
    "addr:housenumber":"3834",
    "addr:postcode":"98418",
    "addr:street":"Pacific Ave",
    "iso:country":"US",
    "sg:address":"3834 Pacific Ave",
    "sg:city":"Tacoma",
    "sg:classifiers":[
        {
            "category":"Restaurant",
            "type":"Food & Drink"
        }
    ],
    "sg:phone":"+1 253 472 4484",
    "sg:postcode":"98418",
    "sg:province":"WA",
    "sg:tags":[
        "mexican"
    ],
    "wof:name":"Puerto Vallarta",
    "wof:placetype":"venue"
},
  "geometry": {"coordinates":[-122.43404700000001,47.222315],"type":"Point"}
}