{
  "type": "Feature",
  "properties": {
    "addr:full":"10005 SE 235th St A202 Kent WA 98031",
    "addr:postcode":"10005;98031",
    "addr:street":"Se 235Th St",
    "iso:country":"US",
    "sg:address":"10005 SE 235th St A202",
    "sg:city":"Kent",
    "sg:classifiers":[
        {
            "category":"Professional",
            "subcategory":"Research",
            "type":"Services"
        }
    ],
    "sg:phone":"+1 253 852 3706",
    "sg:postcode":"98031",
    "sg:province":"WA",
    "sg:tags":[
        "information",
        "medical"
    ],
    "wof:name":"Dld Research Services",
    "wof:placetype":"venue"
},
  "geometry": {"coordinates":[-122.207374,47.391323],"type":"Point"}
}