{
  "type": "Feature",
  "properties": {
    "addr:full":"18109 NE 76th St Redmond WA 98052",
    "addr:housenumber":"18109",
    "addr:postcode":"98052",
    "addr:street":"Ne 76Th St",
    "iso:country":"US",
    "sg:address":"18109 NE 76th St",
    "sg:city":"Redmond",
    "sg:classifiers":[
        {
            "category":"Shopping",
            "type":"Retail Goods"
        }
    ],
    "sg:phone":"+1 425 881 5050",
    "sg:postcode":"98052",
    "sg:province":"WA",
    "sg:tags":[
        "comparison",
        "mystery"
    ],
    "wof:name":"Mobile Whites",
    "wof:placetype":"venue"
},
  "geometry": {"coordinates":[-122.10006,47.671769],"type":"Point"}
}