{
  "type": "Feature",
  "properties": {
    "addr:full":"9616 36th St E Puyallup WA 98371",
    "addr:housenumber":"9616",
    "addr:postcode":"98371",
    "addr:street":"36Th St E",
    "iso:country":"US",
    "sg:address":"9616 36th St E",
    "sg:city":"Puyallup",
    "sg:classifiers":[
        {
            "category":"Building & Trades",
            "subcategory":"Plumbing",
            "type":"Services"
        }
    ],
    "sg:phone":"+1 253 770 4043",
    "sg:postcode":"98371",
    "sg:province":"WA",
    "sg:tags":[
        "contractor"
    ],
    "wof:name":"Plumbing Express Inc",
    "wof:placetype":"venue"
},
  "geometry": {"coordinates":[-122.302896,47.224825],"type":"Point"}
}