{
  "type": "Feature",
  "properties": {
    "addr:full":"3285 Ferguson Ct SW Olympia WA 98512",
    "addr:housenumber":"3285",
    "addr:postcode":"98512",
    "addr:street":"Ferguson Ct Sw",
    "iso:country":"US",
    "sg:address":"3285 Ferguson Ct SW",
    "sg:city":"Olympia",
    "sg:classifiers":[
        {
            "category":"Building & Trades",
            "subcategory":"Construction",
            "type":"Services"
        }
    ],
    "sg:phone":"+1 360 753 4865",
    "sg:postcode":"98512",
    "sg:province":"WA",
    "sg:tags":[
        "contractor"
    ],
    "wof:name":"Zanetti Custom Exteriors",
    "wof:placetype":"venue"
},
  "geometry": {"coordinates":[-122.9448,47.019228],"type":"Point"}
}