{
  "type": "Feature",
  "properties": {
    "addr:full":"4308 E Trent Ave Spokane WA 99212",
    "addr:housenumber":"4308",
    "addr:postcode":"99212",
    "addr:street":"E Trent Ave",
    "iso:country":"US",
    "sg:address":"4308 E Trent Ave",
    "sg:city":"Spokane",
    "sg:classifiers":[
        {
            "category":"Building & Trades",
            "subcategory":"Equipment Rental",
            "type":"Services"
        }
    ],
    "sg:phone":"+1 509 534 7294",
    "sg:postcode":"99212",
    "sg:province":"WA",
    "sg:tags":[
        "contractor"
    ],
    "wof:name":"United Rentals Trench Safety",
    "wof:placetype":"venue"
},
  "geometry": {"coordinates":[-117.34473199999999,47.671702],"type":"Point"}
}