{
  "type": "Feature",
  "properties": {
    "addr:full":"18325 2nd Ave NE Seattle WA 98155",
    "addr:housenumber":"18325",
    "addr:postcode":"98155",
    "addr:street":"2Nd Ave Ne",
    "iso:country":"US",
    "sg:address":"18325 2nd Ave NE",
    "sg:city":"Seattle",
    "sg:classifiers":[
        {
            "category":"Wholesale",
            "subcategory":"Non-durable Goods",
            "type":"Manufacturing & Wholesale Goods"
        }
    ],
    "sg:phone":"+1 206 440 1803",
    "sg:postcode":"98155",
    "sg:province":"WA",
    "wof:name":"B&B Trading",
    "wof:placetype":"venue"
},
  "geometry": {"coordinates":[-122.328322,47.760862],"type":"Point"}
}