{
  "type": "Feature",
  "properties": {
    "addr:full":"7745 Jenni St NE Olympia WA 98506",
    "addr:housenumber":"7745",
    "addr:postcode":"98506",
    "addr:street":"Jenni St Ne",
    "iso:country":"US",
    "sg:address":"7745 Jenni St NE",
    "sg:city":"Olympia",
    "sg:classifiers":[
        {
            "category":"Building & Trades",
            "subcategory":"Landscaping Services",
            "type":"Services"
        }
    ],
    "sg:phone":"+1 360 754 2846",
    "sg:postcode":"98506",
    "sg:province":"WA",
    "sg:tags":[
        "lawn",
        "maintenance",
        "grounds"
    ],
    "wof:name":"Lady Gardener",
    "wof:placetype":"venue"
},
  "geometry": {"coordinates":[-122.876367,47.144827],"type":"Point"}
}