{
  "type": "Feature",
  "properties": {
    "addr:full":"4303 76th Pl NW Marysville WA 98271",
    "addr:housenumber":"4303",
    "addr:postcode":"98271",
    "addr:street":"76Th Pl Nw",
    "iso:country":"US",
    "sg:address":"4303 76th Pl NW",
    "sg:city":"Marysville",
    "sg:classifiers":[
        {
            "category":"Shopping",
            "subcategory":"Gifts & Souvenirs",
            "type":"Retail Goods"
        }
    ],
    "sg:phone":"+1 360 659 2921",
    "sg:postcode":"98271",
    "sg:province":"WA",
    "wof:name":"Showpieces",
    "wof:placetype":"venue"
},
  "geometry": {"coordinates":[-122.290836,48.065628],"type":"Point"}
}