{
  "type": "Feature",
  "properties": {
    "addr:full":"305 2nd St NE Puyallup WA 98372",
    "addr:housenumber":"305",
    "addr:postcode":"98372",
    "addr:street":"2Nd St Ne",
    "iso:country":"US",
    "sg:address":"305 2nd St NE",
    "sg:city":"Puyallup",
    "sg:classifiers":[
        {
            "category":"Restaurant",
            "type":"Food & Drink"
        },
        {
            "category":"Bakery",
            "type":"Food & Drink"
        },
        {
            "category":"Donuts",
            "subcategory":"None",
            "type":"Food & Drink"
        }
    ],
    "sg:phone":"+1 253 840 9398",
    "sg:postcode":"98372",
    "sg:province":"WA",
    "sg:tags":[
        "shop"
    ],
    "wof:name":"Happy Donut",
    "wof:placetype":"venue"
},
  "geometry": {"coordinates":[-122.29216,47.193421],"type":"Point"}
}