{
  "type": "Feature",
  "properties": {
    "addr:full":"200 W Thomas St Seattle WA 98119",
    "addr:housenumber":"200",
    "addr:postcode":"98119",
    "addr:street":"W Thomas St",
    "iso:country":"US",
    "sg:address":"200 W Thomas St",
    "sg:city":"Seattle",
    "sg:classifiers":[
        {
            "category":"Farming",
            "subcategory":"Fish & Marine Products",
            "type":"Manufacturing & Wholesale Goods"
        }
    ],
    "sg:phone":"+1 206 284 1559",
    "sg:postcode":"98119",
    "sg:province":"WA",
    "sg:tags":[
        "fisherman"
    ],
    "wof:name":"Fishing Co Of Alaska",
    "wof:placetype":"venue"
},
  "geometry": {"coordinates":[-122.360614,47.620954],"type":"Point"}
}