{
  "type": "Feature",
  "properties": {
    "addr:full":"1000 E Elep Ave Colville WA 99114",
    "addr:housenumber":"1000",
    "addr:postcode":"99114",
    "addr:street":"E Elep Ave",
    "iso:country":"US",
    "sg:address":"1000 E Elep Ave",
    "sg:city":"Colville",
    "sg:classifiers":[
        {
            "category":"Health Services",
            "subcategory":"Nursing And Care Facility",
            "type":"Services"
        }
    ],
    "sg:phone":"+1 509 684 2573",
    "sg:postcode":"99114",
    "sg:province":"WA",
    "sg:tags":[
        "home",
        "convalescent"
    ],
    "wof:name":"Pinewood Terrace Nursing Ctr",
    "wof:placetype":"venue"
},
  "geometry": {"coordinates":[-117.892025,48.540026],"type":"Point"}
}