{
  "type": "Feature",
  "properties": {
    "addr:full":"3307 3rd Ave W Seattle WA 98119",
    "addr:housenumber":"3307",
    "addr:postcode":"98119",
    "addr:street":"3Rd Ave W",
    "iso:country":"US",
    "sg:address":"3307 3rd Ave W",
    "sg:city":"Seattle",
    "sg:classifiers":[
        {
            "category":"Personal",
            "type":"Services"
        }
    ],
    "sg:phone":"+1 206 408 1901",
    "sg:postcode":"98119",
    "sg:province":"WA",
    "sg:tags":[
        "home"
    ],
    "sg:website":"www.intelafone.com/",
    "wof:name":"Intelafone",
    "wof:placetype":"venue"
},
  "geometry": {"coordinates":[-122.360907,47.649535],"type":"Point"}
}