{
  "type": "Feature",
  "properties": {
    "addr:full":"311 N Olympic Ave Arlington WA 98223",
    "addr:housenumber":"311",
    "addr:postcode":"98223",
    "addr:street":"N Olympic Ave",
    "iso:country":"US",
    "sg:address":"311 N Olympic Ave",
    "sg:city":"Arlington",
    "sg:classifiers":[
        {
            "category":"Social Services",
            "type":"Services"
        }
    ],
    "sg:phone":"+1 360 435 8433",
    "sg:postcode":"98223",
    "sg:province":"WA",
    "wof:name":"Volunteers of America Inc",
    "wof:placetype":"venue"
},
  "geometry": {"coordinates":[-122.126319,48.195953],"type":"Point"}
}