{
  "type": "Feature",
  "properties": {
    "addr:full":"200 NE Mother Joseph Pl Vancouver WA 98664",
    "addr:housenumber":"200",
    "addr:postcode":"98664",
    "addr:street":"Ne Mother Joseph Pl",
    "iso:country":"US",
    "sg:address":"200 NE Mother Joseph Pl",
    "sg:city":"Vancouver",
    "sg:classifiers":[
        {
            "category":"Health Services",
            "subcategory":"Clinic",
            "type":"Services"
        }
    ],
    "sg:phone":"+1 360 892 5701",
    "sg:postcode":"98664",
    "sg:province":"WA",
    "sg:tags":[
        "welfare"
    ],
    "wof:name":"The Oregon Clinic Pc",
    "wof:placetype":"venue"
},
  "geometry": {"coordinates":[-122.580299,45.622509],"type":"Point"}
}