{
  "type": "Feature",
  "properties": {
    "iso:country":"US",
    "sg:address":"10760 E Lake Joy Dr NE",
    "sg:city":"Carnation",
    "sg:classifiers":[
        {
            "category":"Building & Trades",
            "subcategory":"Landscaping Services",
            "type":"Services"
        }
    ],
    "sg:phone":"+1 425 345 2261",
    "sg:postcode":"98014",
    "sg:province":"WA",
    "wof:name":"Hurley Landscape Nursery",
    "wof:placetype":"venue"
},
  "geometry": {"coordinates":[-121.86403799999999,47.694007],"type":"Point"}
}