{
  "type": "Feature",
  "properties": {
    "addr:full":"6485 NE Silver Springs Ln Poulsbo WA 98370",
    "addr:housenumber":"6485",
    "addr:postcode":"98370",
    "addr:street":"Ne Silver Springs Ln",
    "iso:country":"US",
    "sg:address":"6485 NE Silver Springs Ln",
    "sg:city":"Poulsbo",
    "sg:classifiers":[
        {
            "category":"Professional",
            "type":"Services"
        }
    ],
    "sg:phone":"+1 360 697 6782",
    "sg:postcode":"98370",
    "sg:province":"WA",
    "wof:name":"Larry H Hashman",
    "wof:placetype":"venue"
},
  "geometry": {"coordinates":[-122.563327,47.777714],"type":"Point"}
}