{
  "type": "Feature",
  "properties": {
    "addr:full":"1015 149th Pl SE Bellevue WA 98007",
    "addr:housenumber":"1015",
    "addr:postcode":"98007",
    "addr:street":"149Th Pl Se",
    "iso:country":"US",
    "sg:address":"1015 149th Pl SE",
    "sg:city":"Bellevue",
    "sg:classifiers":[
        {
            "category":"Building & Trades",
            "subcategory":"Electrical",
            "type":"Services"
        }
    ],
    "sg:phone":"+1 425 644 8908",
    "sg:postcode":"98007",
    "sg:province":"WA",
    "sg:tags":[
        "electrical",
        "contractor"
    ],
    "wof:name":"Deco Electric Inc",
    "wof:placetype":"venue"
},
  "geometry": {"coordinates":[-122.13947899999999,47.60066],"type":"Point"}
}