{
  "type": "Feature",
  "properties": {
    "addr:full":"220 Dieckman Rd Chehalis WA 98532",
    "addr:housenumber":"220",
    "addr:postcode":"98532",
    "addr:street":"Dieckman Rd",
    "iso:country":"US",
    "sg:address":"220 Dieckman Rd",
    "sg:city":"Chehalis",
    "sg:classifiers":[
        {
            "category":"Education",
            "subcategory":"School",
            "type":"Public Place"
        }
    ],
    "sg:phone":"+1 360 748 7029",
    "sg:postcode":"98532",
    "sg:province":"WA",
    "wof:name":"Adna Elementary School",
    "wof:placetype":"venue"
},
  "geometry": {"coordinates":[-123.060315,46.635856],"type":"Point"}
}