{
  "type": "Feature",
  "properties": {
    "addr:full":"1101 Alaskan Way Seattle WA 98101",
    "addr:housenumber":"1101",
    "addr:postcode":"98101",
    "addr:street":"Alaskan Way",
    "iso:country":"US",
    "sg:address":"1101 Alaskan Way",
    "sg:city":"Seattle",
    "sg:classifiers":[
        {
            "category":"Shopping",
            "subcategory":"Optician",
            "type":"Retail Goods"
        }
    ],
    "sg:phone":"+1 206 682 8840",
    "sg:postcode":"98101",
    "sg:province":"WA",
    "sg:tags":[
        "eyewear"
    ],
    "sg:website":"www2.sunglasshut.com",
    "wof:name":"Sunglass Hut International",
    "wof:placetype":"venue"
},
  "geometry": {"coordinates":[-122.339128,47.604457],"type":"Point"}
}