{
  "type": "Feature",
  "properties": {
    "addr:full":"7912 Martin Way E Olympia WA 98516",
    "addr:housenumber":"7912",
    "addr:postcode":"98516",
    "addr:street":"Martin Way E",
    "iso:country":"US",
    "sg:address":"7912 Martin Way E",
    "sg:city":"Olympia",
    "sg:classifiers":[
        {
            "category":"Professional",
            "subcategory":"Business Services",
            "type":"Services"
        },
        {
            "category":"Farming",
            "subcategory":"Farm",
            "type":"Manufacturing & Wholesale Goods"
        },
        {
            "category":"Food & Beverages",
            "subcategory":"Meat & Fish",
            "type":"Retail Goods"
        }
    ],
    "sg:phone":"+1 360 489 0128",
    "sg:postcode":"98516",
    "sg:province":"WA",
    "sg:tags":[
        "butchering",
        "market"
    ],
    "sg:website":"http://www.michaelsmeats.net",
    "wof:name":"Michaels Meats",
    "wof:placetype":"venue"
},
  "geometry": {"coordinates":[-122.77195,47.055244],"type":"Point"}
}