{
  "type": "Feature",
  "properties": {
    "addr:full":"701 W 11th St Vancouver WA 98660",
    "addr:housenumber":"701",
    "addr:postcode":"98660",
    "addr:street":"W 11Th St",
    "iso:country":"US",
    "sg:address":"701 W 11th St",
    "sg:city":"Vancouver",
    "sg:classifiers":[
        {
            "category":"Manufacturing",
            "subcategory":"Motor Vehicles & Parts",
            "type":"Manufacturing & Wholesale Goods"
        }
    ],
    "sg:phone":"+1 360 694 8387",
    "sg:postcode":"98660",
    "sg:province":"WA",
    "sg:tags":[
        "automobile",
        "supply"
    ],
    "wof:name":"Tabor's Automotive Machine Inc",
    "wof:placetype":"venue"
},
  "geometry": {"coordinates":[-122.679283,45.629595],"type":"Point"}
}