{
  "type": "Feature",
  "properties": {
    "addr:full":"8905 NW 24th Ave Vancouver WA 98665",
    "addr:housenumber":"8905",
    "addr:postcode":"98665",
    "addr:street":"Nw 24Th Ave",
    "iso:country":"US",
    "sg:address":"8905 NW 24th Ave",
    "sg:city":"Vancouver",
    "sg:classifiers":[
        {
            "category":"Banks & Credit Unions",
            "subcategory":"Investment Brokerage",
            "type":"Services"
        }
    ],
    "sg:phone":"+1 360 576 0100",
    "sg:postcode":"98665",
    "sg:province":"WA",
    "sg:tags":[
        "commodity",
        "contract"
    ],
    "wof:name":"Omurcu Enterprises",
    "wof:placetype":"venue"
},
  "geometry": {"coordinates":[-122.69641799999999,45.687131],"type":"Point"}
}