{
  "type": "Feature",
  "properties": {
    "addr:full":"31405 18th Ave S Federal Way WA 98003",
    "addr:housenumber":"31405",
    "addr:postcode":"98003",
    "addr:street":"18Th Ave S Federal Way",
    "iso:country":"US",
    "sg:address":"31405 18th Ave S",
    "sg:city":"Federal Way",
    "sg:classifiers":[
        {
            "category":"Education",
            "subcategory":"School",
            "type":"Public Place"
        }
    ],
    "sg:phone":"+1 253 945 2000",
    "sg:postcode":"98003",
    "sg:province":"WA",
    "sg:tags":[
        "district"
    ],
    "wof:name":"FEDERAL WAY PUBLIC SCHOOLS",
    "wof:placetype":"venue"
},
  "geometry": {"coordinates":[-122.31086500000001,47.322113],"type":"Point"}
}