{
  "type": "Feature",
  "properties": {
    "addr:full":"320 Marietta Ct Steilacoom WA 98388",
    "addr:housenumber":"320",
    "addr:postcode":"98388",
    "addr:street":"Marietta Ct",
    "iso:country":"US",
    "sg:address":"320 Marietta Ct",
    "sg:city":"Steilacoom",
    "sg:classifiers":[
        {
            "category":"Professional",
            "subcategory":"Art Services",
            "type":"Services"
        }
    ],
    "sg:phone":"+1 253 581 1852",
    "sg:postcode":"98388",
    "sg:province":"WA",
    "sg:tags":[
        "commercial",
        "design"
    ],
    "wof:name":"Four Seasons",
    "wof:placetype":"venue"
},
  "geometry": {"coordinates":[-122.58631099999999,47.174171],"type":"Point"}
}