{
  "type": "Feature",
  "properties": {
    "addr:full":"33925 Eglon Rd NE Kingston WA 98346",
    "addr:postcode":"33925;98346",
    "addr:street":"Eglon Rd Ne",
    "iso:country":"US",
    "sg:address":"33925 Eglon Rd NE",
    "sg:city":"Kingston",
    "sg:classifiers":[
        {
            "category":"Retail",
            "subcategory":"Animal Services",
            "type":"Services"
        }
    ],
    "sg:phone":"+1 360 779 6363",
    "sg:postcode":"98346",
    "sg:province":"WA",
    "wof:name":"Giants Bench Inc",
    "wof:placetype":"venue"
},
  "geometry": {"coordinates":[-122.51937,47.86511],"type":"Point"}
}