{
  "type": "Feature",
  "properties": {
    "addr:full":"2651 NW Four Wheel Dr Seabeck WA 98380",
    "addr:housenumber":"2651",
    "addr:postcode":"98380",
    "addr:street":"Nw Four Wheel Dr",
    "iso:country":"US",
    "sg:address":"2651 NW Four Wheel Dr",
    "sg:city":"Seabeck",
    "sg:classifiers":[
        {
            "category":"Building & Trades",
            "subcategory":"Construction",
            "type":"Services"
        }
    ],
    "sg:phone":"+1 360 830 5391",
    "sg:postcode":"98380",
    "sg:province":"WA",
    "sg:tags":[
        "hanging",
        "contractor"
    ],
    "wof:name":"Twin Cedars Painting",
    "wof:placetype":"venue"
},
  "geometry": {"coordinates":[-122.868441,47.590107],"type":"Point"}
}