{
  "type": "Feature",
  "properties": {
    "addr:full":"5877 Werner Rd Bremerton WA 98312",
    "addr:housenumber":"5877",
    "addr:postcode":"98312",
    "addr:street":"Werner Rd",
    "iso:country":"US",
    "sg:address":"5877 Werner Rd",
    "sg:city":"Bremerton",
    "sg:classifiers":[
        {
            "category":"Wholesale",
            "subcategory":"Groceries",
            "type":"Manufacturing & Wholesale Goods"
        }
    ],
    "sg:phone":"+1 360 478 8920",
    "sg:postcode":"98312",
    "sg:province":"WA",
    "sg:tags":[
        "food",
        "snack"
    ],
    "wof:name":"Frito-Lay",
    "wof:placetype":"venue"
},
  "geometry": {"coordinates":[-122.691603,47.558119],"type":"Point"}
}