{
  "type": "Feature",
  "properties": {
    "addr:full":"1560 N 115th St Ste 205 Seattle WA 98133",
    "addr:housenumber":"1560",
    "addr:postcode":"98133",
    "addr:street":"N 115Th St Ste 205",
    "iso:country":"US",
    "sg:address":"1560 N 115th St Ste 205",
    "sg:city":"Seattle",
    "sg:classifiers":[
        {
            "category":"Health Services",
            "subcategory":"Doctor",
            "type":"Services"
        }
    ],
    "sg:phone":"+1 206 361 9416",
    "sg:postcode":"98133",
    "sg:province":"WA",
    "sg:tags":[
        "cardiologist"
    ],
    "wof:name":"Piccolo Kathryn Arnp",
    "wof:placetype":"venue"
},
  "geometry": {"coordinates":[-122.339152,47.712416],"type":"Point"}
}