{
  "type": "Feature",
  "properties": {
    "addr:full":"2317 NW Market St Seattle WA 98107",
    "addr:housenumber":"2317",
    "addr:postcode":"98107",
    "addr:street":"Nw Market St",
    "iso:country":"US",
    "sg:address":"2317 NW Market St",
    "sg:city":"Seattle",
    "sg:classifiers":[
        {
            "category":"Building & Trades",
            "subcategory":"Locksmith",
            "type":"Services"
        }
    ],
    "sg:phone":"+1 206 777 0061",
    "sg:postcode":"98107",
    "sg:province":"WA",
    "sg:tags":[
        "key"
    ],
    "wof:name":"Aarant Emergency Locksmith",
    "wof:placetype":"venue"
},
  "geometry": {"coordinates":[-122.386329,47.668536],"type":"Point"}
}