{
  "type": "Feature",
  "properties": {
    "addr:full":"3113 Eastlake Ave E Seattle WA 98102",
    "addr:housenumber":"3113",
    "addr:postcode":"98102",
    "addr:street":"Eastlake Ave E",
    "iso:country":"US",
    "sg:address":"3113 Eastlake Ave E",
    "sg:city":"Seattle",
    "sg:classifiers":[
        {
            "category":"Manufacturing",
            "subcategory":"Printing",
            "type":"Manufacturing & Wholesale Goods"
        }
    ],
    "sg:phone":"+1 206 709 8433",
    "sg:postcode":"98102",
    "sg:province":"WA",
    "sg:tags":[
        "processing",
        "desktop"
    ],
    "wof:name":"Angela Seybold",
    "wof:placetype":"venue"
},
  "geometry": {"coordinates":[-122.322873,47.649578],"type":"Point"}
}