{
  "type": "Feature",
  "properties": {
    "addr:full":"2411 S 315th Ln Federal Way WA 98003",
    "addr:housenumber":"2411",
    "addr:postcode":"98003",
    "addr:street":"S 315Th Ln",
    "iso:country":"US",
    "sg:address":"2411 S 315th Ln",
    "sg:city":"Federal Way",
    "sg:classifiers":[
        {
            "category":"Building & Trades",
            "subcategory":"Construction",
            "type":"Services"
        }
    ],
    "sg:phone":"+1 253 221 9469",
    "sg:postcode":"98003",
    "sg:province":"WA",
    "sg:tags":[
        "contractor"
    ],
    "wof:name":"J & L Drywall",
    "wof:placetype":"venue"
},
  "geometry": {"coordinates":[-122.30153199999999,47.319295],"type":"Point"}
}