{
  "type": "Feature",
  "properties": {
    "addr:full":"271 Rainier Ave N Renton WA 98055",
    "addr:housenumber":"271",
    "addr:postcode":"98055",
    "addr:street":"Rainier Ave N",
    "iso:country":"US",
    "sg:address":"271 Rainier Ave N",
    "sg:city":"Renton",
    "sg:classifiers":[
        {
            "category":"Autos & Motor Vehicles",
            "subcategory":"Auto Supplies",
            "type":"Retail Goods"
        }
    ],
    "sg:phone":"+1 425 793 8875",
    "sg:postcode":"98055",
    "sg:province":"WA",
    "sg:tags":[
        "tire"
    ],
    "wof:name":"Rainier Tire Equipment",
    "wof:placetype":"venue"
},
  "geometry": {"coordinates":[-122.218002,47.486801],"type":"Point"}
}