{
  "type": "Feature",
  "properties": {
    "addr:full":"16210 N Yale Rd Colbert WA 99005",
    "addr:housenumber":"16210",
    "addr:postcode":"99005",
    "addr:street":"N Yale Rd Colbert",
    "iso:country":"US",
    "sg:address":"16210 N Yale Rd",
    "sg:city":"Colbert",
    "sg:classifiers":[
        {
            "category":"Shopping",
            "subcategory":"Clothing, Apparel, & Fashions",
            "type":"Retail Goods"
        }
    ],
    "sg:phone":"+1 509 238 6244",
    "sg:postcode":"99005",
    "sg:province":"WA",
    "sg:tags":[
        "hat"
    ],
    "wof:name":"K&D Diversified Products",
    "wof:placetype":"venue"
},
  "geometry": {"coordinates":[-117.346752,47.804661],"type":"Point"}
}