{
  "type": "Feature",
  "properties": {
    "addr:full":"630 SE Benewah St Pullman WA 99163",
    "addr:housenumber":"630",
    "addr:postcode":"99163",
    "addr:street":"Se Benewah St",
    "iso:country":"US",
    "sg:address":"630 SE Benewah St",
    "sg:city":"Pullman",
    "sg:classifiers":[
        {
            "category":"Autos & Motor Vehicles",
            "subcategory":"Auto Supplies",
            "type":"Retail Goods"
        },
        {
            "category":"Retail",
            "subcategory":"Auto Repair",
            "type":"Services"
        }
    ],
    "sg:phone":"+1 509 334 0418",
    "sg:postcode":"99163",
    "sg:province":"WA",
    "sg:tags":[
        "body",
        "automobile",
        "truck",
        "painting",
        "repairing"
    ],
    "wof:name":"Al's Auto Body",
    "wof:placetype":"venue"
},
  "geometry": {"coordinates":[-117.169175,46.724997],"type":"Point"}
}