{
  "type": "Feature",
  "properties": {
    "addr:full":"7411 112th St NE Arlington WA 98223",
    "addr:housenumber":"7411",
    "addr:postcode":"98223",
    "addr:street":"112Th St Ne",
    "iso:country":"US",
    "sg:address":"7411 112th St NE",
    "sg:city":"Arlington",
    "sg:classifiers":[
        {
            "category":"Professional",
            "subcategory":"Computer Services",
            "type":"Services"
        }
    ],
    "sg:phone":"+1 425 238 8437",
    "sg:postcode":"98223",
    "sg:province":"WA",
    "sg:tags":[
        "web",
        "programming",
        "application"
    ],
    "wof:name":"Chumdognet",
    "wof:placetype":"venue"
},
  "geometry": {"coordinates":[-122.127461,48.09649],"type":"Point"}
}