{
  "type": "Feature",
  "properties": {
    "addr:full":"437 Vista Pl Everett WA 98203",
    "addr:housenumber":"437",
    "addr:postcode":"98203",
    "addr:street":"Vista Pl",
    "iso:country":"US",
    "sg:address":"437 Vista Pl",
    "sg:city":"Everett",
    "sg:classifiers":[
        {
            "category":"Professional",
            "subcategory":"Art Services",
            "type":"Services"
        }
    ],
    "sg:phone":"+1 425 259 0739",
    "sg:postcode":"98203",
    "sg:province":"WA",
    "sg:tags":[
        "designer",
        "display",
        "producer"
    ],
    "wof:name":"Ld Design",
    "wof:placetype":"venue"
},
  "geometry": {"coordinates":[-122.234804,47.95345],"type":"Point"}
}