{
  "type": "Feature",
  "properties": {
    "addr:full":"230 Davidson Ave Woodland WA 98674",
    "addr:housenumber":"230",
    "addr:postcode":"98674",
    "addr:street":"Davidson Ave",
    "iso:country":"US",
    "sg:address":"230 Davidson Ave",
    "sg:city":"Woodland",
    "sg:classifiers":[
        {
            "category":"Government",
            "subcategory":"Office",
            "type":"Public Place"
        }
    ],
    "sg:phone":"+1 360 225 8281",
    "sg:postcode":"98674",
    "sg:province":"WA",
    "sg:tags":[
        "city"
    ],
    "wof:name":"Woodland City Clerk",
    "wof:placetype":"venue"
},
  "geometry": {"coordinates":[-122.748301,45.901019],"type":"Point"}
}