{
  "type": "Feature",
  "properties": {
    "addr:full":"3402 E Shore Dr Seattle WA 98112",
    "addr:housenumber":"3402",
    "addr:postcode":"98112",
    "addr:street":"E Shore Dr",
    "iso:country":"US",
    "sg:address":"3402 E Shore Dr",
    "sg:city":"Seattle",
    "sg:classifiers":[
        {
            "category":"Real Estate",
            "subcategory":"Real Estate Operator",
            "type":"Services"
        }
    ],
    "sg:phone":"+1 206 324 4040",
    "sg:postcode":"98112",
    "sg:province":"WA",
    "sg:tags":[
        "building",
        "equipment",
        "apartment"
    ],
    "wof:name":"Cosse International Properties",
    "wof:placetype":"venue"
},
  "geometry": {"coordinates":[-122.287678,47.640211],"type":"Point"}
}