{
  "type": "Feature",
  "properties": {
    "addr:full":"14727 56th Ave NW Stanwood WA 98292",
    "addr:housenumber":"14727",
    "addr:postcode":"98292",
    "addr:street":"56Th Ave Nw",
    "iso:country":"US",
    "sg:address":"14727 56th Ave NW",
    "sg:city":"Stanwood",
    "sg:classifiers":[
        {
            "category":"Shopping",
            "subcategory":"Gifts & Souvenirs",
            "type":"Retail Goods"
        }
    ],
    "sg:phone":"+1 360 652 0671",
    "sg:postcode":"98292",
    "sg:province":"WA",
    "sg:tags":[
        "novelty"
    ],
    "wof:name":"Country Living Productions",
    "wof:placetype":"venue"
},
  "geometry": {"coordinates":[-122.30877,48.12953],"type":"Point"}
}