{
  "type": "Feature",
  "properties": {
    "addr:full":"19200 Aurora Ave N Seattle WA 98133",
    "addr:housenumber":"19200",
    "addr:postcode":"98133",
    "addr:street":"Aurora Ave N",
    "iso:country":"US",
    "sg:address":"19200 Aurora Ave N",
    "sg:city":"Seattle",
    "sg:classifiers":[
        {
            "category":"Food & Beverages",
            "subcategory":"Groceries & Convenience Stores",
            "type":"Retail Goods"
        }
    ],
    "sg:phone":"+1 206 542 3016",
    "sg:postcode":"98133",
    "sg:province":"WA",
    "wof:name":"EZ Stop",
    "wof:placetype":"venue"
},
  "geometry": {"coordinates":[-122.345957,47.770523],"type":"Point"}
}