{
  "type": "Feature",
  "properties": {
    "addr:full":"8614 E Mill Plain Blvd Vancouver WA 98664",
    "addr:housenumber":"8614",
    "addr:postcode":"98664",
    "addr:street":"E Mill Plain Blvd",
    "iso:country":"US",
    "sg:address":"8614 E Mill Plain Blvd",
    "sg:city":"Vancouver",
    "sg:classifiers":[
        {
            "category":"Health Services",
            "subcategory":"Doctor",
            "type":"Services"
        }
    ],
    "sg:phone":"+1 360 892 1635",
    "sg:postcode":"98664",
    "sg:province":"WA",
    "sg:tags":[
        "medical"
    ],
    "wof:name":"Megan Eussen MD",
    "wof:placetype":"venue"
},
  "geometry": {"coordinates":[-122.584641,45.623278],"type":"Point"}
}