{
  "type": "Feature",
  "properties": {
    "addr:full":"5728 S 237th St Kent WA 98032",
    "addr:housenumber":"5728",
    "addr:postcode":"98032",
    "addr:street":"S 237Th St",
    "iso:country":"US",
    "sg:address":"5728 S 237th St",
    "sg:city":"Kent",
    "sg:classifiers":[
        {
            "category":"Professional",
            "subcategory":"Management & Consulting",
            "type":"Services"
        }
    ],
    "sg:phone":"+1 253 951 4095",
    "sg:postcode":"98032",
    "sg:province":"WA",
    "wof:name":"Extraordinary Sales & Mktg",
    "wof:placetype":"venue"
},
  "geometry": {"coordinates":[-122.262783,47.388813],"type":"Point"}
}