{
  "type": "Feature",
  "properties": {
    "addr:full":"901 1st Ave Seattle WA 98104",
    "addr:housenumber":"901",
    "addr:postcode":"98104",
    "addr:street":"1St Ave",
    "iso:country":"US",
    "sg:address":"901 1st Ave",
    "sg:city":"Seattle",
    "sg:classifiers":[
        {
            "category":"Building & Trades",
            "subcategory":"Construction",
            "type":"Services"
        }
    ],
    "sg:phone":"+1 206 719 8290",
    "sg:postcode":"98104",
    "sg:province":"WA",
    "sg:tags":[
        "plastering",
        "contractor"
    ],
    "wof:name":"Artisan Finishes",
    "wof:placetype":"venue"
},
  "geometry": {"coordinates":[-122.33624,47.604693],"type":"Point"}
}