{
  "type": "Feature",
  "properties": {
    "addr:full":"1412 NE 152nd Ave Vancouver WA 98684",
    "addr:housenumber":"1412",
    "addr:postcode":"98684",
    "addr:street":"Ne 152Nd Ave",
    "iso:country":"US",
    "sg:address":"1412 NE 152nd Ave",
    "sg:city":"Vancouver",
    "sg:classifiers":[
        {
            "category":"Professional",
            "subcategory":"Management & Consulting",
            "type":"Services"
        }
    ],
    "sg:phone":"+1 360 828 3634",
    "sg:postcode":"98684",
    "sg:province":"WA",
    "sg:tags":[
        "engineering",
        "business"
    ],
    "wof:name":"Steven & Associates",
    "wof:placetype":"venue"
},
  "geometry": {"coordinates":[-122.517095,45.632915],"type":"Point"}
}