{
  "type": "Feature",
  "properties": {
    "addr:full":"3106 S Raymond Cir Spokane WA 99206",
    "addr:housenumber":"3106",
    "addr:postcode":"99206",
    "addr:street":"S Raymond Cir",
    "iso:country":"US",
    "sg:address":"3106 S Raymond Cir",
    "sg:city":"Spokane",
    "sg:classifiers":[
        {
            "category":"Education",
            "subcategory":"Special Training",
            "type":"Public Place"
        }
    ],
    "sg:phone":"+1 509 868 9931",
    "sg:postcode":"99206",
    "sg:province":"WA",
    "wof:name":"Certified Flight Instructor",
    "wof:placetype":"venue"
},
  "geometry": {"coordinates":[-117.26276900000001,47.630488],"type":"Point"}
}