{
  "type": "Feature",
  "properties": {
    "addr:full":"1083 Lake Washington Blvd N Renton WA 98056",
    "addr:housenumber":"1083",
    "addr:postcode":"98056",
    "addr:street":"Lake Washington Blvd N",
    "iso:country":"US",
    "sg:address":"1083 Lake Washington Blvd N",
    "sg:city":"Renton",
    "sg:classifiers":[
        {
            "category":"Real Estate",
            "subcategory":"Developer",
            "type":"Services"
        }
    ],
    "sg:phone":"+1 425 688 3083",
    "sg:postcode":"98056",
    "sg:province":"WA",
    "wof:name":"Seco Development Inc",
    "wof:placetype":"venue"
},
  "geometry": {"coordinates":[-122.20027399999999,47.501954],"type":"Point"}
}