{
  "type": "Feature",
  "properties": {
    "addr:full":"2403 S Tacoma Way Tacoma WA 98409",
    "addr:housenumber":"2403",
    "addr:postcode":"98409",
    "addr:street":"S Tacoma Way",
    "iso:country":"US",
    "sg:address":"2403 S Tacoma Way",
    "sg:city":"Tacoma",
    "sg:classifiers":[
        {
            "category":"Professional",
            "type":"Services"
        }
    ],
    "sg:phone":"+1 253 471 3545",
    "sg:postcode":"98409",
    "sg:province":"WA",
    "sg:website":"www.gotgrommets.com",
    "wof:name":"Avelate Coach Works",
    "wof:placetype":"venue"
},
  "geometry": {"coordinates":[-122.469528,47.231027],"type":"Point"}
}