{
  "type": "Feature",
  "properties": {
    "addr:full":"1525 A St NE Auburn WA 98002",
    "addr:housenumber":"1525",
    "addr:postcode":"98002",
    "addr:street":"A St Ne",
    "iso:country":"US",
    "sg:address":"1525 A St NE",
    "sg:city":"Auburn",
    "sg:classifiers":[
        {
            "category":"Insurance",
            "subcategory":"Hazard Insurance",
            "type":"Services"
        },
        {
            "category":"Insurance",
            "subcategory":"Insurance Agent",
            "type":"Services"
        },
        {
            "category":"Insurance",
            "subcategory":"Life Insurance",
            "type":"Services"
        }
    ],
    "sg:phone":"+1 253 833 2500",
    "sg:postcode":"98002",
    "sg:province":"WA",
    "sg:tags":[
        "auto"
    ],
    "sg:website":"http://statefarm.mqgroup.com/url.asp?usr=472784",
    "wof:name":"Nadine Toles Ins Agcy Inc - State Farm Insurance Agent",
    "wof:placetype":"venue"
},
  "geometry": {"coordinates":[-122.228814,47.322524],"type":"Point"}
}