{
  "type": "Feature",
  "properties": {
    "addr:full":"714 200th Ave E Sumner WA 98391",
    "addr:housenumber":"714",
    "addr:postcode":"98391",
    "addr:street":"200Th Ave E",
    "iso:country":"US",
    "sg:address":"714 200th Ave E",
    "sg:city":"Sumner",
    "sg:classifiers":[
        {
            "category":"Social Services",
            "subcategory":"Child Care",
            "type":"Services"
        }
    ],
    "sg:phone":"+1 253 863 3589",
    "sg:postcode":"98391",
    "sg:province":"WA",
    "sg:tags":[
        "day"
    ],
    "wof:name":"Margots House Care",
    "wof:placetype":"venue"
},
  "geometry": {"coordinates":[-122.162386,47.250678],"type":"Point"}
}