{
  "type": "Feature",
  "properties": {
    "addr:full":"12525 Totem Lake Blvd NE Kirkland WA 98034",
    "addr:housenumber":"12525",
    "addr:postcode":"98034",
    "addr:street":"Totem Lake Blvd Ne",
    "iso:country":"US",
    "sg:address":"12525 Totem Lake Blvd NE",
    "sg:city":"Kirkland",
    "sg:classifiers":[
        {
            "category":"Retail",
            "subcategory":"Laundry & Dry Cleaning",
            "type":"Services"
        }
    ],
    "sg:phone":"+1 425 821 1755",
    "sg:postcode":"98034",
    "sg:province":"WA",
    "sg:tags":[
        "shop"
    ],
    "wof:name":"Totem Lake Cleaners",
    "wof:placetype":"venue"
},
  "geometry": {"coordinates":[-122.180142,47.710388],"type":"Point"}
}