{
  "type": "Feature",
  "properties": {
    "addr:full":"5885 State Hwy 303 Bremerton WA 98311",
    "addr:housenumber":"5885",
    "addr:postcode":"98311",
    "addr:street":"State Hwy 303",
    "iso:country":"US",
    "sg:address":"5885 State Hwy 303",
    "sg:city":"Bremerton",
    "sg:classifiers":[
        {
            "category":"Wholesale",
            "subcategory":"Groceries",
            "type":"Manufacturing & Wholesale Goods"
        }
    ],
    "sg:phone":"+1 360 415 9427",
    "sg:postcode":"98311",
    "sg:province":"WA",
    "sg:tags":[
        "eating"
    ],
    "wof:name":"Ootopia Coffee Roasters Inc",
    "wof:placetype":"venue"
},
  "geometry": {"coordinates":[-122.628935,47.620279],"type":"Point"}
}