{
  "type": "Feature",
  "properties": {
    "addr:full":"6848 180th Ave NE Redmond WA 98052",
    "addr:housenumber":"6848",
    "addr:postcode":"98052",
    "addr:street":"180Th Ave Ne",
    "iso:country":"US",
    "sg:address":"6848 180th Ave NE",
    "sg:city":"Redmond",
    "sg:classifiers":[
        {
            "category":"Wholesale",
            "subcategory":"Machinery & Supplies",
            "type":"Manufacturing & Wholesale Goods"
        }
    ],
    "sg:phone":"+1 425 883 9945",
    "sg:postcode":"98052",
    "sg:province":"WA",
    "sg:tags":[
        "construction"
    ],
    "wof:name":"Alpine Construction Supply",
    "wof:placetype":"venue"
},
  "geometry": {"coordinates":[-122.100071,47.667392],"type":"Point"}
}