{
  "type": "Feature",
  "properties": {
    "addr:full":"7565 11th Ave NE Seattle WA 98115",
    "addr:housenumber":"7565",
    "addr:postcode":"98115",
    "addr:street":"11Th Ave Ne",
    "iso:country":"US",
    "sg:address":"7565 11th Ave NE",
    "sg:city":"Seattle",
    "sg:classifiers":[
        {
            "category":"Wholesale",
            "subcategory":"Electrical",
            "type":"Manufacturing & Wholesale Goods"
        }
    ],
    "sg:phone":"+1 206 527 1183",
    "sg:postcode":"98115",
    "sg:province":"WA",
    "sg:tags":[
        "equipment",
        "fixture",
        "lighting",
        "product"
    ],
    "wof:name":"Illuminating Ideas",
    "wof:placetype":"venue"
},
  "geometry": {"coordinates":[-122.316002,47.684399],"type":"Point"}
}