{
  "type": "Feature",
  "properties": {
    "addr:full":"4911 N Railroad Ave Pasco WA 99301",
    "addr:housenumber":"4911",
    "addr:postcode":"99301",
    "addr:street":"N Railroad Ave",
    "iso:country":"US",
    "sg:address":"4911 N Railroad Ave",
    "sg:city":"Pasco",
    "sg:classifiers":[
        {
            "category":"Freight",
            "type":"Transportation"
        }
    ],
    "sg:phone":"+1 509 542 0302",
    "sg:postcode":"99301",
    "sg:province":"WA",
    "wof:name":"Express Freight Services",
    "wof:placetype":"venue"
},
  "geometry": {"coordinates":[-119.10136300000001,46.273999],"type":"Point"}
}