{
  "type": "Feature",
  "properties": {
    "addr:full":"7424 Bridgeport Way W Lakewood WA 98499",
    "addr:housenumber":"7424",
    "addr:postcode":"98499",
    "addr:street":"Bridgeport Way W",
    "iso:country":"US",
    "sg:address":"7424 Bridgeport Way W",
    "sg:city":"Lakewood",
    "sg:classifiers":[
        {
            "category":"Health Services",
            "subcategory":"Doctor",
            "type":"Services"
        }
    ],
    "sg:phone":"+1 253 588 6574",
    "sg:postcode":"98499",
    "sg:province":"WA",
    "sg:tags":[
        "physician",
        "medical",
        "surgeon"
    ],
    "wof:name":"M Teresa Clabots MD",
    "wof:placetype":"venue"
},
  "geometry": {"coordinates":[-122.518573,47.190926],"type":"Point"}
}