{
  "type": "Feature",
  "properties": {
    "addr:full":"9620 Dickey Rd NW Silverdale WA 98383",
    "addr:housenumber":"9620",
    "addr:postcode":"98383",
    "addr:street":"Dickey Rd Nw",
    "iso:country":"US",
    "sg:address":"9620 Dickey Rd NW",
    "sg:city":"Silverdale",
    "sg:classifiers":[
        {
            "category":"Professional",
            "type":"Services"
        }
    ],
    "sg:phone":"+1 360 620 8857",
    "sg:postcode":"98383",
    "sg:province":"WA",
    "wof:name":"Let It Shine",
    "wof:placetype":"venue"
},
  "geometry": {"coordinates":[-122.71907400000001,47.649762],"type":"Point"}
}