{
  "type": "Feature",
  "properties": {
    "addr:full":"20201 21st Pl NW Shoreline WA 98177",
    "addr:housenumber":"20201",
    "addr:postcode":"98177",
    "addr:street":"21St Pl Nw",
    "iso:country":"US",
    "sg:address":"20201 21st Pl NW",
    "sg:city":"Shoreline",
    "sg:classifiers":[
        {
            "category":"Food & Beverages",
            "subcategory":"Groceries & Convenience Stores",
            "type":"Retail Goods"
        }
    ],
    "sg:phone":"+1 206 546 5637",
    "sg:postcode":"98177",
    "sg:province":"WA",
    "wof:name":"7-Eleven",
    "wof:placetype":"venue"
},
  "geometry": {"coordinates":[-122.384075,47.77708],"type":"Point"}
}