{
  "type": "Feature",
  "properties": {
    "addr:full":"821 E Columbia Dr Kennewick WA 99336",
    "addr:housenumber":"821",
    "addr:postcode":"99336",
    "addr:street":"E Columbia Dr",
    "iso:country":"US",
    "sg:address":"821 E Columbia Dr",
    "sg:city":"Kennewick",
    "sg:classifiers":[
        {
            "category":"Shopping",
            "subcategory":"Hobbies, Toys, & Games",
            "type":"Retail Goods"
        }
    ],
    "sg:phone":"+1 509 783 7006",
    "sg:postcode":"99336",
    "sg:province":"WA",
    "wof:name":"Toys R Us",
    "wof:placetype":"venue"
},
  "geometry": {"coordinates":[-119.103847,46.212087],"type":"Point"}
}