{
  "type": "Feature",
  "properties": {
    "addr:full":"400 Spring St Seattle WA 98104",
    "addr:housenumber":"400",
    "addr:postcode":"98104",
    "addr:street":"Spring St",
    "iso:country":"US",
    "sg:address":"400 Spring St",
    "sg:city":"Seattle",
    "sg:classifiers":[
        {
            "category":"Travel",
            "subcategory":"Hotels & Motels",
            "type":"Entertainment"
        }
    ],
    "sg:phone":"+1 800 426 1165",
    "sg:postcode":"98104",
    "sg:province":"WA",
    "sg:website":"www.executivehotels.net/seattle",
    "wof:name":"Executive Hotel Pacific",
    "wof:placetype":"venue"
},
  "geometry": {"coordinates":[-122.334,47.606998],"type":"Point"}
}