{
  "type": "Feature",
  "properties": {
    "addr:full":"900 W Casino Rd Everett WA 98204",
    "addr:housenumber":"900",
    "addr:postcode":"98204",
    "addr:street":"W Casino Rd",
    "iso:country":"US",
    "sg:address":"900 W Casino Rd",
    "sg:city":"Everett",
    "sg:classifiers":[
        {
            "category":"Social Services",
            "subcategory":"Child Care",
            "type":"Services"
        }
    ],
    "sg:phone":"+1 425 353 9797",
    "sg:postcode":"98204",
    "sg:province":"WA",
    "sg:tags":[
        "center",
        "preschool"
    ],
    "wof:name":"Northwest Educational Center",
    "wof:placetype":"venue"
},
  "geometry": {"coordinates":[-122.246752,47.921801],"type":"Point"}
}