{
  "type": "Feature",
  "properties": {
    "addr:full":"306 Front St Lynden WA 98264",
    "addr:housenumber":"306",
    "addr:postcode":"98264",
    "addr:street":"Front St",
    "iso:country":"US",
    "sg:address":"306 Front St",
    "sg:city":"Lynden",
    "sg:classifiers":[
        {
            "category":"Manufacturing",
            "subcategory":"Printing",
            "type":"Manufacturing & Wholesale Goods"
        },
        {
            "category":"Shopping",
            "subcategory":"Clothing, Apparel, & Fashions",
            "type":"Retail Goods"
        }
    ],
    "sg:phone":"+1 360 354 2877",
    "sg:postcode":"98264",
    "sg:province":"WA",
    "sg:tags":[
        "engraver",
        "wood"
    ],
    "wof:name":"Hats Off",
    "wof:placetype":"venue"
},
  "geometry": {"coordinates":[-122.450733,48.943538],"type":"Point"}
}