{
  "type": "Feature",
  "properties": {
    "iso:country":"US",
    "sg:address":"4230 Pacific Ave SE",
    "sg:city":"Lacey",
    "sg:classifiers":[
        {
            "category":"Retail",
            "subcategory":"Auto Rental",
            "type":"Services"
        }
    ],
    "sg:phone":"+1 360 754 9656",
    "sg:postcode":"98503",
    "sg:province":"WA",
    "sg:tags":[
        "truck",
        "leasing"
    ],
    "wof:name":"Penske",
    "wof:placetype":"venue"
},
  "geometry": {"coordinates":[-122.83026,47.038444],"type":"Point"}
}