{
  "type": "Feature",
  "properties": {
    "addr:full":"3110 201st St SE Bothell WA 98012",
    "addr:housenumber":"3110",
    "addr:postcode":"98012",
    "addr:street":"201St St Se",
    "iso:country":"US",
    "sg:address":"3110 201st St SE",
    "sg:city":"Bothell",
    "sg:classifiers":[
        {
            "category":"Wholesale",
            "subcategory":"Hardware",
            "type":"Manufacturing & Wholesale Goods"
        }
    ],
    "sg:phone":"+1 425 486 5635",
    "sg:postcode":"98012",
    "sg:province":"WA",
    "wof:name":"Kevin D Solinger/Authoriz",
    "wof:placetype":"venue"
},
  "geometry": {"coordinates":[-122.191356,47.814929],"type":"Point"}
}