{
  "type": "Feature",
  "properties": {
    "addr:full":"206 32nd St Washougal WA 98671",
    "addr:housenumber":"206",
    "addr:postcode":"98671",
    "addr:street":"32Nd St",
    "iso:country":"US",
    "sg:address":"206 32nd St",
    "sg:city":"Washougal",
    "sg:classifiers":[
        {
            "category":"Manufacturing",
            "subcategory":"Wood Products",
            "type":"Manufacturing & Wholesale Goods"
        }
    ],
    "sg:phone":"+1 360 335 0631",
    "sg:postcode":"98671",
    "sg:province":"WA",
    "sg:tags":[
        "mfg"
    ],
    "wof:name":"Affordable Wood Products Mfg",
    "wof:placetype":"venue"
},
  "geometry": {"coordinates":[-122.33684100000001,45.577971],"type":"Point"}
}