{
  "type": "Feature",
  "properties": {
    "addr:full":"2220 Dublin Dr NW Olympia WA 98502",
    "addr:housenumber":"2220",
    "addr:postcode":"olympia wa 98502",
    "addr:street":"Dublin Dr Nw",
    "iso:country":"US",
    "sg:address":"2220 Dublin Dr NW",
    "sg:city":"Olympia",
    "sg:classifiers":[
        {
            "category":"Professional",
            "subcategory":"Art Services",
            "type":"Services"
        }
    ],
    "sg:phone":"+1 360 866 8818",
    "sg:postcode":"98502",
    "sg:province":"WA",
    "sg:tags":[
        "photography",
        "commercial"
    ],
    "wof:name":"Harry Halverson Photogra",
    "wof:placetype":"venue"
},
  "geometry": {"coordinates":[-122.92894800000001,47.124949],"type":"Point"}
}