{
  "type": "Feature",
  "properties": {
    "addr:full":"100 Ruby St SE Ste F Tumwater WA 98501",
    "addr:housenumber":"100",
    "addr:postcode":"98501",
    "addr:street":"Ruby St Se Ste F",
    "iso:country":"US",
    "sg:address":"100 Ruby St SE Ste F",
    "sg:city":"Tumwater",
    "sg:classifiers":[
        {
            "category":"Health Services",
            "subcategory":"Chiropractor",
            "type":"Services"
        }
    ],
    "sg:phone":"+1 360 943 4797",
    "sg:postcode":"98501",
    "sg:province":"WA",
    "sg:tags":[
        "chiropractic"
    ],
    "wof:name":"Chiropractic Arts",
    "wof:placetype":"venue"
},
  "geometry": {"coordinates":[-122.90821099999999,46.998772],"type":"Point"}
}