{
  "type": "Feature",
  "properties": {
    "addr:full":"15107 NE 201st St Woodinville WA 98072",
    "addr:housenumber":"15107",
    "addr:postcode":"98072",
    "addr:street":"Ne 201St St",
    "iso:country":"US",
    "sg:address":"15107 NE 201st St",
    "sg:city":"Woodinville",
    "sg:classifiers":[
        {
            "category":"Communications",
            "type":"Services"
        }
    ],
    "sg:phone":"+1 425 402 4018",
    "sg:postcode":"98072",
    "sg:province":"WA",
    "sg:tags":[
        "communication"
    ],
    "wof:name":"Huff Media",
    "wof:placetype":"venue"
},
  "geometry": {"coordinates":[-122.136582,47.772799],"type":"Point"}
}