{
  "type": "Feature",
  "properties": {
    "iso:country":"US",
    "sg:address":"217 9th St",
    "sg:city":"Leavenworth",
    "sg:classifiers":[
        {
            "category":"Food & Beverages",
            "subcategory":"Meat & Fish",
            "type":"Retail Goods"
        }
    ],
    "sg:phone":"+1 509 782 1040",
    "sg:postcode":"98826",
    "sg:province":"WA",
    "wof:name":"Willis Sausage House",
    "wof:placetype":"venue"
},
  "geometry": {"coordinates":[-120.660982,47.595575],"type":"Point"}
}