{
  "type": "Feature",
  "properties": {
    "addr:full":"10670 14th Ave SW Seattle WA 98146",
    "addr:housenumber":"10670",
    "addr:postcode":"98146",
    "addr:street":"14Th Ave Sw",
    "iso:country":"US",
    "sg:address":"10670 14th Ave SW",
    "sg:city":"Seattle",
    "sg:classifiers":[
        {
            "category":"Real Estate",
            "subcategory":"Real Estate Operator",
            "type":"Services"
        }
    ],
    "sg:phone":"+1 206 244 9797",
    "sg:postcode":"98146",
    "sg:province":"WA",
    "sg:tags":[
        "apartment"
    ],
    "wof:name":"Coronado Springs Apartments",
    "wof:placetype":"venue"
},
  "geometry": {"coordinates":[-122.351567,47.507391],"type":"Point"}
}