{
  "type": "Feature",
  "properties": {
    "addr:full":"22012 Vine Rd Lynnwood WA 98036",
    "addr:housenumber":"22012",
    "addr:postcode":"98036",
    "addr:street":"Vine Rd",
    "iso:country":"US",
    "sg:address":"22012 Vine Rd",
    "sg:city":"Lynnwood",
    "sg:classifiers":[
        {
            "category":"Professional",
            "subcategory":"Lawyer & Legal Services",
            "type":"Services"
        }
    ],
    "sg:phone":"+1 425 776 2627",
    "sg:postcode":"98036",
    "sg:province":"WA",
    "wof:name":"Starks Leona Medical Legal",
    "wof:placetype":"venue"
},
  "geometry": {"coordinates":[-122.26731100000001,47.799418],"type":"Point"}
}