{
  "type": "Feature",
  "properties": {
    "addr:full":"4170 Cordata Pkwy Bellingham WA 98226",
    "addr:housenumber":"4170",
    "addr:postcode":"98226",
    "addr:street":"Cordata Pkwy",
    "iso:country":"US",
    "sg:address":"4170 Cordata Pkwy",
    "sg:city":"Bellingham",
    "sg:classifiers":[
        {
            "category":"Restaurant",
            "type":"Food & Drink"
        },
        {
            "category":"Ice Cream",
            "type":"Food & Drink"
        }
    ],
    "sg:menulink":"http://www.allmenus.com/wa/bellingham/192740-dairy-queen/menu/",
    "sg:phone":"+1 360 738 8013",
    "sg:postcode":"98226",
    "sg:province":"WA",
    "sg:tags":[
        "burger",
        "american",
        "ice",
        "cream"
    ],
    "wof:name":"Dairy Queen",
    "wof:placetype":"venue"
},
  "geometry": {"coordinates":[-122.491291,48.792961],"type":"Point"}
}