{
  "type": "Feature",
  "properties": {
    "addr:full":"12922 E Valleyway Ave Spokane WA 99216",
    "addr:housenumber":"12922",
    "addr:postcode":"99216",
    "addr:street":"E Valleyway Ave",
    "iso:country":"US",
    "sg:address":"12922 E Valleyway Ave",
    "sg:city":"Spokane",
    "sg:classifiers":[
        {
            "category":"Professional",
            "subcategory":"Accounting & Tax Preparation",
            "type":"Services"
        }
    ],
    "sg:phone":"+1 509 928 7184",
    "sg:postcode":"99216",
    "sg:province":"WA",
    "wof:name":"Ajl Bookkeeping Service",
    "wof:placetype":"venue"
},
  "geometry": {"coordinates":[-117.229156,47.660634],"type":"Point"}
}