{
  "type": "Feature",
  "properties": {
    "addr:full":"5741 Tigner Rd Cashmere WA 98815",
    "addr:housenumber":"5741",
    "addr:postcode":"98815",
    "addr:street":"Tigner Rd",
    "iso:country":"US",
    "sg:address":"5741 Tigner Rd",
    "sg:city":"Cashmere",
    "sg:classifiers":[
        {
            "category":"Wholesale",
            "subcategory":"Hardware",
            "type":"Manufacturing & Wholesale Goods"
        }
    ],
    "sg:phone":"+1 509 679 9659",
    "sg:postcode":"98815",
    "sg:province":"WA",
    "sg:tags":[
        "distributor",
        "valve",
        "gas",
        "earthquake"
    ],
    "sg:website":"www.alphasalestech.com",
    "wof:name":"Alpha Sales Technologies",
    "wof:placetype":"venue"
},
  "geometry": {"coordinates":[-120.48845,47.509767],"type":"Point"}
}