{
  "type": "Feature",
  "properties": {
    "addr:full":"1410 W Raye St Seattle WA 98119",
    "addr:housenumber":"1410",
    "addr:postcode":"98119",
    "addr:street":"W Raye St",
    "iso:country":"US",
    "sg:address":"1410 W Raye St",
    "sg:city":"Seattle",
    "sg:classifiers":[
        {
            "category":"Building & Trades",
            "subcategory":"Landscaping Services",
            "type":"Services"
        }
    ],
    "sg:phone":"+1 206 713 4792",
    "sg:postcode":"98119",
    "sg:province":"WA",
    "sg:tags":[
        "landscape"
    ],
    "wof:name":"Reilly Landscape Co",
    "wof:placetype":"venue"
},
  "geometry": {"coordinates":[-122.37616800000001,47.643014],"type":"Point"}
}