{
  "type": "Feature",
  "properties": {
    "addr:full":"2809 NE Sunset Blvd Renton WA 98056",
    "addr:housenumber":"2809",
    "addr:postcode":"98056",
    "addr:street":"Ne Sunset Blvd",
    "iso:country":"US",
    "sg:address":"2809 NE Sunset Blvd",
    "sg:city":"Renton",
    "sg:classifiers":[
        {
            "category":"Food & Beverages",
            "subcategory":"Groceries & Convenience Stores",
            "type":"Retail Goods"
        }
    ],
    "sg:phone":"+1 425 988 2515",
    "sg:postcode":"98056",
    "sg:province":"WA",
    "sg:website":"www.groceryoutlet.com",
    "wof:name":"Grocery Outlet",
    "wof:placetype":"venue"
},
  "geometry": {"coordinates":[-122.179531,47.500547],"type":"Point"}
}