{
  "type": "Feature",
  "properties": {
    "addr:full":"1022 Industry Dr Seattle WA 98188",
    "addr:housenumber":"1022",
    "addr:postcode":"98188",
    "addr:street":"Industry Dr",
    "iso:country":"US",
    "sg:address":"1022 Industry Dr",
    "sg:city":"Seattle",
    "sg:classifiers":[
        {
            "category":"Building & Trades",
            "subcategory":"Construction",
            "type":"Services"
        }
    ],
    "sg:phone":"+1 206 575 2235",
    "sg:postcode":"98188",
    "sg:province":"WA",
    "sg:tags":[
        "contractor"
    ],
    "wof:name":"Thermal Services",
    "wof:placetype":"venue"
},
  "geometry": {"coordinates":[-122.24835299999999,47.448404],"type":"Point"}
}