{
  "type": "Feature",
  "properties": {
    "addr:full":"13319 Solberg Rd SE Yelm WA 98597",
    "addr:postcode":"13319;98597",
    "addr:street":"Solberg Rd Se Yelm",
    "iso:country":"US",
    "sg:address":"13319 Solberg Rd SE",
    "sg:city":"Yelm",
    "sg:classifiers":[
        {
            "category":"Organizations",
            "subcategory":"Religious Organization",
            "type":"Services"
        }
    ],
    "sg:phone":"+1 360 458 2235",
    "sg:postcode":"98597",
    "sg:province":"WA",
    "wof:name":"Not By Might Ministries",
    "wof:placetype":"venue"
},
  "geometry": {"coordinates":[-122.618066,46.893791],"type":"Point"}
}