{
  "type": "Feature",
  "properties": {
    "addr:full":"2224 NW 56th St Seattle WA 98107",
    "addr:housenumber":"2224",
    "addr:postcode":"98107",
    "addr:street":"Nw 56Th St",
    "iso:country":"US",
    "sg:address":"2224 NW 56th St",
    "sg:city":"Seattle",
    "sg:classifiers":[
        {
            "category":"Banks & Credit Unions",
            "subcategory":"Investment Brokerage",
            "type":"Services"
        }
    ],
    "sg:phone":"+1 206 782 8060",
    "sg:postcode":"98107",
    "sg:province":"WA",
    "sg:tags":[
        "security"
    ],
    "wof:name":"Edward Jones Co",
    "wof:placetype":"venue"
},
  "geometry": {"coordinates":[-122.387356,47.669531],"type":"Point"}
}