{
  "type": "Feature",
  "properties": {
    "addr:full":"20014 State Rte 2 Monroe WA 98272",
    "addr:housenumber":"20014",
    "addr:postcode":"98272",
    "addr:street":"State Rte 2",
    "iso:country":"US",
    "sg:address":"20014 State Rte 2",
    "sg:city":"Monroe",
    "sg:classifiers":[
        {
            "category":"Insurance",
            "subcategory":"Insurance Agent",
            "type":"Services"
        }
    ],
    "sg:phone":"+1 425 481 1399",
    "sg:postcode":"98272",
    "sg:province":"WA",
    "wof:name":"Farmers Insurance Group",
    "wof:placetype":"venue"
},
  "geometry": {"coordinates":[-121.955195,47.856305],"type":"Point"}
}