{
  "type": "Feature",
  "properties": {
    "addr:full":"1491 E Mason Ave Buckley WA 98321",
    "addr:housenumber":"1491",
    "addr:postcode":"98321",
    "addr:street":"E Mason Ave",
    "iso:country":"US",
    "sg:address":"1491 E Mason Ave",
    "sg:city":"Buckley",
    "sg:classifiers":[
        {
            "category":"Professional",
            "subcategory":"Computer Services",
            "type":"Services"
        }
    ],
    "sg:phone":"+1 360 829 2606",
    "sg:postcode":"98321",
    "sg:province":"WA",
    "sg:tags":[
        "programing",
        "custom"
    ],
    "wof:name":"Compu Geeks",
    "wof:placetype":"venue"
},
  "geometry": {"coordinates":[-122.01623499999999,47.161432],"type":"Point"}
}