{
  "type": "Feature",
  "properties": {
    "addr:full":"18909 NE 149th St Brush Prairie WA 98606",
    "addr:housenumber":"18909",
    "addr:postcode":"98606",
    "addr:street":"Ne 149Th St",
    "iso:country":"US",
    "sg:address":"18909 NE 149th St",
    "sg:city":"Brush Prairie",
    "sg:classifiers":[
        {
            "category":"Food & Beverages",
            "subcategory":"Bakery",
            "type":"Retail Goods"
        }
    ],
    "sg:phone":"+1 360 882 7520",
    "sg:postcode":"98606",
    "sg:province":"WA",
    "sg:tags":[
        "cookie",
        "cracker"
    ],
    "wof:name":"Nabisco Inc",
    "wof:placetype":"venue"
},
  "geometry": {"coordinates":[-122.483906,45.730266],"type":"Point"}
}