{
  "type": "Feature",
  "properties": {
    "addr:full":"206 E Gowe St Kent WA 98032",
    "addr:housenumber":"206",
    "addr:postcode":"98032",
    "addr:street":"E Gowe St",
    "iso:country":"US",
    "sg:address":"206 E Gowe St",
    "sg:city":"Kent",
    "sg:classifiers":[
        {
            "category":"Retail",
            "subcategory":"Auto Repair",
            "type":"Services"
        }
    ],
    "sg:phone":"+1 253 854 6766",
    "sg:postcode":"98032",
    "sg:province":"WA",
    "sg:tags":[
        "body",
        "automotive"
    ],
    "wof:name":"G M Collision",
    "wof:placetype":"venue"
},
  "geometry": {"coordinates":[-122.23177099999999,47.380886],"type":"Point"}
}