{
  "type": "Feature",
  "properties": {
    "addr:full":"34503 9th Ave S Federal Way WA 98003",
    "addr:housenumber":"34503",
    "addr:postcode":"98003",
    "addr:street":"9Th Ave S Federal Way",
    "iso:country":"US",
    "sg:address":"34503 9th Ave S",
    "sg:city":"Federal Way",
    "sg:classifiers":[
        {
            "category":"Health Services",
            "subcategory":"Doctor",
            "type":"Services"
        }
    ],
    "sg:phone":"+1 253 874 2227",
    "sg:postcode":"98003",
    "sg:province":"WA",
    "sg:tags":[
        "physician",
        "surgeon"
    ],
    "sg:website":"www.fmg.fhshealth.org",
    "wof:name":"Franciscan Medical Group",
    "wof:placetype":"venue"
},
  "geometry": {"coordinates":[-122.32302799999999,47.292468],"type":"Point"}
}