{
  "type": "Feature",
  "properties": {
    "addr:full":"24441 Pacific Hwy S Kent WA 98032",
    "addr:housenumber":"24441",
    "addr:postcode":"98032",
    "addr:street":"Pacific Hwy S",
    "iso:country":"US",
    "sg:address":"24441 Pacific Hwy S",
    "sg:city":"Kent",
    "sg:classifiers":[
        {
            "category":"Retail",
            "subcategory":"Auto Repair",
            "type":"Services"
        }
    ],
    "sg:phone":"+1 253 941 4424",
    "sg:postcode":"98032",
    "sg:province":"WA",
    "sg:tags":[
        "automotive"
    ],
    "wof:name":"Puget Sound Alignment",
    "wof:placetype":"venue"
},
  "geometry": {"coordinates":[-122.297526,47.382206],"type":"Point"}
}