{
  "type": "Feature",
  "properties": {
    "addr:full":"1121 4th Ave W Olympia WA 98502",
    "addr:housenumber":"1121",
    "addr:postcode":"98502",
    "addr:street":"4Th Ave W",
    "iso:country":"US",
    "sg:address":"1121 4th Ave W",
    "sg:city":"Olympia",
    "sg:classifiers":[
        {
            "category":"Shopping",
            "subcategory":"Used Merchandise",
            "type":"Retail Goods"
        }
    ],
    "sg:phone":"+1 360 786 8442",
    "sg:postcode":"98502",
    "sg:province":"WA",
    "wof:name":"Julies Jewels To Junque",
    "wof:placetype":"venue"
},
  "geometry": {"coordinates":[-122.917186,47.044317],"type":"Point"}
}