{
  "type": "Feature",
  "properties": {
    "addr:full":"4818 14th Ave NW Seattle WA 98107",
    "addr:housenumber":"4818",
    "addr:postcode":"98107",
    "addr:street":"14Th Ave Nw",
    "iso:country":"US",
    "sg:address":"4818 14th Ave NW",
    "sg:city":"Seattle",
    "sg:classifiers":[
        {
            "category":"Wholesale",
            "subcategory":"Furniture",
            "type":"Manufacturing & Wholesale Goods"
        }
    ],
    "sg:phone":"+1 206 957 9550",
    "sg:postcode":"98107",
    "sg:province":"WA",
    "sg:tags":[
        "store"
    ],
    "wof:name":"Homesite",
    "wof:placetype":"venue"
},
  "geometry": {"coordinates":[-122.373475,47.663795],"type":"Point"}
}