{
  "type": "Feature",
  "properties": {
    "iso:country":"US",
    "sg:address":"35004 NE 185th Ave",
    "sg:city":"Yacolt",
    "sg:classifiers":[
        {
            "category":"Manufacturing",
            "subcategory":"Aerospace",
            "type":"Manufacturing & Wholesale Goods"
        }
    ],
    "sg:phone":"+1 360 907 0888",
    "sg:postcode":"98675",
    "sg:province":"WA",
    "sg:tags":[
        "aircraft",
        "mfg"
    ],
    "wof:name":"Aviation Innovations LLC",
    "wof:placetype":"venue"
},
  "geometry": {"coordinates":[-122.483113,45.874925],"type":"Point"}
}