{
  "type": "Feature",
  "properties": {
    "addr:full":"1223 Cottage St SE Ephrata WA 98823",
    "addr:housenumber":"1223",
    "addr:postcode":"98823",
    "addr:street":"Cottage St Se",
    "iso:country":"US",
    "sg:address":"1223 Cottage St SE",
    "sg:city":"Ephrata",
    "sg:classifiers":[
        {
            "category":"Building & Trades",
            "subcategory":"Landscaping Services",
            "type":"Services"
        }
    ],
    "sg:phone":"+1 509 754 0995",
    "sg:postcode":"98823",
    "sg:province":"WA",
    "wof:name":"Winskis Lawn Maintenance",
    "wof:placetype":"venue"
},
  "geometry": {"coordinates":[-119.551699,47.308492],"type":"Point"}
}