{
  "type": "Feature",
  "properties": {
    "addr:full":"901 Boren Avenue Suite 1650 Seattle WA 98104",
    "addr:housenumber":"901",
    "addr:postcode":"98104",
    "addr:street":"Boren Avenue Suite 1650",
    "iso:country":"US",
    "sg:address":"901 Boren Avenue Suite 1650",
    "sg:city":"Seattle",
    "sg:classifiers":[
        {
            "category":"Health Services",
            "subcategory":"Doctor",
            "type":"Services"
        }
    ],
    "sg:phone":"+1 206 464 0873",
    "sg:postcode":"98104",
    "sg:province":"WA",
    "sg:tags":[
        "surgeon",
        "cosmetic"
    ],
    "wof:name":"Peters Mary Lee MD",
    "wof:placetype":"venue"
},
  "geometry": {"coordinates":[-122.324493,47.608598],"type":"Point"}
}