{
  "type": "Feature",
  "properties": {
    "iso:country":"US",
    "sg:address":"23004 57th Ave SE",
    "sg:city":"Woodinville",
    "sg:classifiers":[
        {
            "category":"Professional",
            "type":"Services"
        }
    ],
    "sg:phone":"+1 206 669 2068",
    "sg:postcode":"98072",
    "sg:province":"WA",
    "wof:name":"Manage To Serve",
    "wof:placetype":"venue"
},
  "geometry": {"coordinates":[-122.157048,47.789598],"type":"Point"}
}