{
  "type": "Feature",
  "properties": {
    "addr:full":"3420 Chico Way NW Bremerton WA 98312",
    "addr:housenumber":"3420",
    "addr:postcode":"98312",
    "addr:street":"Chico Way Nw",
    "iso:country":"US",
    "sg:address":"3420 Chico Way NW",
    "sg:city":"Bremerton",
    "sg:classifiers":[
        {
            "category":"Retail",
            "subcategory":"Auto Repair",
            "type":"Services"
        }
    ],
    "sg:phone":"+1 360 692 2262",
    "sg:postcode":"98312",
    "sg:province":"WA",
    "sg:tags":[
        "repairing",
        "automobile"
    ],
    "wof:name":"Town & Country Auto Repair",
    "wof:placetype":"venue"
},
  "geometry": {"coordinates":[-122.709304,47.594877],"type":"Point"}
}