{
  "type": "Feature",
  "properties": {
    "addr:full":"3931 Leary Way NW Seattle WA 98107",
    "addr:housenumber":"3931",
    "addr:postcode":"98107",
    "addr:street":"Leary Way Nw",
    "iso:country":"US",
    "sg:address":"3931 Leary Way NW",
    "sg:city":"Seattle",
    "sg:classifiers":[
        {
            "category":"Manufacturing",
            "subcategory":"Retail Goods",
            "type":"Manufacturing & Wholesale Goods"
        }
    ],
    "sg:phone":"+1 206 365 5241",
    "sg:postcode":"98107",
    "sg:province":"WA",
    "sg:tags":[
        "giftware's-wholesale",
        "manufacturer"
    ],
    "wof:name":"Binkley & Assoc",
    "wof:placetype":"venue"
},
  "geometry": {"coordinates":[-122.361086,47.655196],"type":"Point"}
}