{
  "type": "Feature",
  "properties": {
    "addr:full":"204 Butterfield Rd Yakima WA 98901",
    "addr:housenumber":"204",
    "addr:postcode":"98901",
    "addr:street":"Butterfield Rd",
    "iso:country":"US",
    "sg:address":"204 Butterfield Rd",
    "sg:city":"Yakima",
    "sg:classifiers":[
        {
            "category":"Wholesale",
            "subcategory":"Fruits & Vegetables",
            "type":"Manufacturing & Wholesale Goods"
        }
    ],
    "sg:phone":"+1 509 575 6553",
    "sg:postcode":"98901",
    "sg:province":"WA",
    "wof:name":"Max Judy Co",
    "wof:placetype":"venue"
},
  "geometry": {"coordinates":[-120.472397,46.607403],"type":"Point"}
}