{
  "type": "Feature",
  "properties": {
    "addr:full":"621 N Gum St Kennewick WA 99336",
    "addr:housenumber":"621",
    "addr:postcode":"99336",
    "addr:street":"N Gum St",
    "iso:country":"US",
    "sg:address":"621 N Gum St",
    "sg:city":"Kennewick",
    "sg:classifiers":[
        {
            "category":"Retail",
            "subcategory":"Auto Repair",
            "type":"Services"
        }
    ],
    "sg:phone":"+1 509 586 7465",
    "sg:postcode":"99336",
    "sg:province":"WA",
    "sg:tags":[
        "body"
    ],
    "wof:name":"Yuris Autobody",
    "wof:placetype":"venue"
},
  "geometry": {"coordinates":[-119.107377,46.213332],"type":"Point"}
}