{
  "type": "Feature",
  "properties": {
    "addr:full":"4701 Scoon Rd Sunnyside WA 98944",
    "addr:housenumber":"4701",
    "addr:postcode":"98944",
    "addr:street":"Scoon Rd",
    "iso:country":"US",
    "sg:address":"4701 Scoon Rd",
    "sg:city":"Sunnyside",
    "sg:classifiers":[
        {
            "category":"Farming",
            "subcategory":"Dairy Farm",
            "type":"Manufacturing & Wholesale Goods"
        }
    ],
    "sg:phone":"+1 509 839 4123",
    "sg:postcode":"98944",
    "sg:province":"WA",
    "wof:name":"Skyridge Farms",
    "wof:placetype":"venue"
},
  "geometry": {"coordinates":[-120.01982599999999,46.398382],"type":"Point"}
}