{
  "type": "Feature",
  "properties": {
    "addr:full":"421 N Bend Blvd N North Bend WA 98045",
    "addr:housenumber":"421",
    "addr:postcode":"98045",
    "addr:street":"N Bend Blvd N",
    "iso:country":"US",
    "sg:address":"421 N Bend Blvd N",
    "sg:city":"North Bend",
    "sg:classifiers":[
        {
            "category":"Health Services",
            "subcategory":"Doctor",
            "type":"Services"
        }
    ],
    "sg:phone":"+1 425 888 0867",
    "sg:postcode":"98045",
    "sg:province":"WA",
    "sg:tags":[
        "dentist"
    ],
    "wof:name":"Cynthia L Delano DDS",
    "wof:placetype":"venue"
},
  "geometry": {"coordinates":[-121.787544,47.499148],"type":"Point"}
}