{
  "type": "Feature",
  "properties": {
    "addr:full":"6311 288th St S Roy WA 98580",
    "addr:housenumber":"6311",
    "addr:postcode":"98580",
    "addr:street":"288Th St S",
    "iso:country":"US",
    "sg:address":"6311 288th St S",
    "sg:city":"Roy",
    "sg:classifiers":[
        {
            "category":"Retail",
            "subcategory":"Animal Services",
            "type":"Services"
        }
    ],
    "sg:phone":"+1 253 843 2929",
    "sg:postcode":"98580",
    "sg:province":"WA",
    "wof:name":"Ewetopia Herd Dog Training",
    "wof:placetype":"venue"
},
  "geometry": {"coordinates":[-122.521537,46.996238],"type":"Point"}
}