{
  "type": "Feature",
  "properties": {
    "iso:country":"US",
    "sg:address":"4518 88th Ave NW",
    "sg:city":"Gig Harbor",
    "sg:classifiers":[
        {
            "category":"Professional",
            "subcategory":"Business Services",
            "type":"Services"
        }
    ],
    "sg:phone":"+1 253 265 2890",
    "sg:postcode":"98335",
    "sg:province":"WA",
    "wof:name":"Tawnya Casebolt",
    "wof:placetype":"venue"
},
  "geometry": {"coordinates":[-122.65593200000001,47.294399],"type":"Point"}
}