{
  "type": "Feature",
  "properties": {
    "addr:full":"1000 85th Ave SE Olympia WA 98501",
    "addr:housenumber":"1000",
    "addr:postcode":"98501",
    "addr:street":"85Th Ave Se",
    "iso:country":"US",
    "sg:address":"1000 85th Ave SE",
    "sg:city":"Olympia",
    "sg:classifiers":[
        {
            "category":"Airline",
            "type":"Transportation"
        }
    ],
    "sg:phone":"+1 360 754 7200",
    "sg:postcode":"98501",
    "sg:province":"WA",
    "sg:tags":[
        "helicopter",
        "rental"
    ],
    "sg:website":"www.nwhelicopters.com",
    "wof:name":"Northwest Helicopters",
    "wof:placetype":"venue"
},
  "geometry": {"coordinates":[-122.887024,46.963661],"type":"Point"}
}