{
  "type": "Feature",
  "properties": {
    "addr:full":"5601 1st Ave S Seattle WA 98108",
    "addr:housenumber":"5601",
    "addr:postcode":"98108",
    "addr:street":"1St Ave S",
    "iso:country":"US",
    "sg:address":"5601 1st Ave S",
    "sg:city":"Seattle",
    "sg:classifiers":[
        {
            "category":"Wholesale",
            "subcategory":"Machinery & Supplies",
            "type":"Manufacturing & Wholesale Goods"
        }
    ],
    "sg:phone":"+1 206 762 4430",
    "sg:postcode":"98108",
    "sg:province":"WA",
    "sg:tags":[
        "equipment",
        "industrial"
    ],
    "wof:name":"Industrial Distribution Group",
    "wof:placetype":"venue"
},
  "geometry": {"coordinates":[-122.33421800000001,47.551901],"type":"Point"}
}