{
  "type": "Feature",
  "properties": {
    "addr:full":"1323 Harbor Ave SW Seattle WA 98116",
    "addr:housenumber":"1323",
    "addr:postcode":"98116",
    "addr:street":"Harbor Ave Sw",
    "iso:country":"US",
    "sg:address":"1323 Harbor Ave SW",
    "sg:city":"Seattle",
    "sg:classifiers":[
        {
            "category":"Bars & Pubs",
            "type":"Food & Drink"
        }
    ],
    "sg:phone":"+1 206 946 0636",
    "sg:postcode":"98116",
    "sg:province":"WA",
    "sg:tags":[
        "lounge",
        "cocktail"
    ],
    "wof:name":"Saltys At Redondo",
    "wof:placetype":"venue"
},
  "geometry": {"coordinates":[-122.381533,47.589491],"type":"Point"}
}