{
  "type": "Feature",
  "properties": {
    "addr:full":"128 E Main St Walla Walla WA 99362",
    "addr:housenumber":"128",
    "addr:postcode":"99362",
    "addr:street":"E Main St",
    "iso:country":"US",
    "sg:address":"128 E Main St",
    "sg:city":"Walla Walla",
    "sg:classifiers":[
        {
            "category":"Shopping",
            "subcategory":"Gifts & Souvenirs",
            "type":"Retail Goods"
        }
    ],
    "sg:phone":"+1 509 529 2346",
    "sg:postcode":"99362",
    "sg:province":"WA",
    "sg:website":"www.byarrangement.com",
    "wof:name":"By Arrangement",
    "wof:placetype":"venue"
},
  "geometry": {"coordinates":[-118.336562,46.06852],"type":"Point"}
}