{
  "type": "Feature",
  "properties": {
    "iso:country":"US",
    "sg:address":"377 S Burlington Blvd",
    "sg:city":"Burlington",
    "sg:classifiers":[
        {
            "category":"Manufacturing",
            "subcategory":"Buildings",
            "type":"Manufacturing & Wholesale Goods"
        }
    ],
    "sg:phone":"+1 360 755 0341",
    "sg:postcode":"98233",
    "sg:province":"WA",
    "sg:tags":[
        "prefab"
    ],
    "sg:website":"www.coachcorral.com",
    "wof:name":"Coach Corral Mobile Home Sales",
    "wof:placetype":"venue"
},
  "geometry": {"coordinates":[-122.33571999999999,48.473336],"type":"Point"}
}