{
  "type": "Feature",
  "properties": {
    "addr:full":"101 Underhill Rd Bellingham WA 98225",
    "addr:housenumber":"101",
    "addr:postcode":"98225",
    "addr:street":"Underhill Rd",
    "iso:country":"US",
    "sg:address":"101 Underhill Rd",
    "sg:city":"Bellingham",
    "sg:classifiers":[
        {
            "category":"Professional",
            "subcategory":"Management & Consulting",
            "type":"Services"
        }
    ],
    "sg:phone":"+1 360 733 1714",
    "sg:postcode":"98225",
    "sg:province":"WA",
    "wof:name":"Baker Construction Consultants",
    "wof:placetype":"venue"
},
  "geometry": {"coordinates":[-122.50520299999999,48.712848],"type":"Point"}
}