{
  "type": "Feature",
  "properties": {
    "addr:full":"6500 NE St Johns Rd Vancouver WA 98661",
    "addr:housenumber":"6500",
    "addr:postcode":"98661",
    "addr:street":"Ne St Johns Rd",
    "iso:country":"US",
    "sg:address":"6500 NE St Johns Rd",
    "sg:city":"Vancouver",
    "sg:classifiers":[
        {
            "category":"Building & Trades",
            "subcategory":"Cleaning & Sanitation",
            "type":"Services"
        }
    ],
    "sg:phone":"+1 360 253 9304",
    "sg:postcode":"98661",
    "sg:province":"WA",
    "sg:tags":[
        "janitor"
    ],
    "wof:name":"We Clean Everything Inc",
    "wof:placetype":"venue"
},
  "geometry": {"coordinates":[-122.636595,45.669353],"type":"Point"}
}