{
  "type": "Feature",
  "properties": {
    "iso:country":"US",
    "sg:address":"22244 Vetter Rd NE",
    "sg:city":"Poulsbo",
    "sg:classifiers":[
        {
            "category":"Building & Trades",
            "subcategory":"Construction",
            "type":"Services"
        }
    ],
    "sg:phone":"+1 360 697 9290",
    "sg:postcode":"98370",
    "sg:province":"WA",
    "sg:tags":[
        "gen",
        "contractor"
    ],
    "wof:name":"Paul Ogilvie Construction",
    "wof:placetype":"venue"
},
  "geometry": {"coordinates":[-122.65006099999999,47.765249],"type":"Point"}
}