{
  "type": "Feature",
  "properties": {
    "addr:full":"3321 W Alice Ave Spokane WA 99205",
    "addr:housenumber":"3321",
    "addr:postcode":"99205",
    "addr:street":"W Alice Ave",
    "iso:country":"US",
    "sg:address":"3321 W Alice Ave",
    "sg:city":"Spokane",
    "sg:classifiers":[
        {
            "category":"Building & Trades",
            "subcategory":"Construction",
            "type":"Services"
        }
    ],
    "sg:phone":"+1 509 328 4441",
    "sg:postcode":"99205",
    "sg:province":"WA",
    "sg:tags":[
        "concrete",
        "contractor"
    ],
    "wof:name":"Home Foundations Inc",
    "wof:placetype":"venue"
},
  "geometry": {"coordinates":[-117.45921199999999,47.688038],"type":"Point"}
}