{
  "type": "Feature",
  "properties": {
    "addr:full":"12120 10th Dr SE Everett WA 98208",
    "addr:housenumber":"12120",
    "addr:postcode":"98208",
    "addr:street":"10Th Dr Se",
    "iso:country":"US",
    "sg:address":"12120 10th Dr SE",
    "sg:city":"Everett",
    "sg:classifiers":[
        {
            "category":"Building & Trades",
            "subcategory":"Construction",
            "type":"Services"
        }
    ],
    "sg:phone":"+1 425 357 9030",
    "sg:postcode":"98208",
    "sg:province":"WA",
    "sg:tags":[
        "dry wall",
        "contractor"
    ],
    "wof:name":"Lauras Taping & Construction",
    "wof:placetype":"venue"
},
  "geometry": {"coordinates":[-122.218209,47.88572],"type":"Point"}
}