{
  "type": "Feature",
  "properties": {
    "iso:country":"US",
    "sg:address":"221 N Wall St",
    "sg:city":"Spokane",
    "sg:classifiers":[
        {
            "category":"Shopping",
            "subcategory":"Shoes",
            "type":"Retail Goods"
        }
    ],
    "sg:phone":"+1 509 624 7654",
    "sg:postcode":"99201",
    "sg:province":"WA",
    "wof:name":"Runners Soul",
    "wof:placetype":"venue"
},
  "geometry": {"coordinates":[-117.422172,47.659952],"type":"Point"}
}