{
  "type": "Feature",
  "properties": {
    "addr:full":"3418 Malaga Alcoa Hwy Malaga WA 98828",
    "addr:housenumber":"3418",
    "addr:postcode":"98828",
    "addr:street":"Malaga Alcoa Hwy",
    "iso:country":"US",
    "sg:address":"3418 Malaga Alcoa Hwy",
    "sg:city":"Malaga",
    "sg:classifiers":[
        {
            "category":"Freight",
            "type":"Transportation"
        }
    ],
    "sg:phone":"+1 509 663 6154",
    "sg:postcode":"98828",
    "sg:province":"WA",
    "sg:tags":[
        "trucking"
    ],
    "sg:website":"www.northwestchoice.com",
    "wof:name":"Eagle Systems Inc",
    "wof:placetype":"venue"
},
  "geometry": {"coordinates":[-120.202157,47.372386],"type":"Point"}
}