{
  "type": "Feature",
  "properties": {
    "iso:country":"US",
    "sg:address":"3006 S Wiley Rd",
    "sg:city":"Yakima",
    "sg:classifiers":[
        {
            "category":"Education",
            "subcategory":"School",
            "type":"Public Place"
        }
    ],
    "sg:phone":"+1 509 965 2031",
    "sg:postcode":"98903",
    "sg:province":"WA",
    "wof:name":"Ahtanum Valley Elementary Schl",
    "wof:placetype":"venue"
},
  "geometry": {"coordinates":[-120.649895,46.548003],"type":"Point"}
}