{
  "type": "Feature",
  "properties": {
    "addr:full":"3521 Norton Ave Everett WA 98201",
    "addr:housenumber":"3521",
    "addr:postcode":"98201",
    "addr:street":"Norton Ave",
    "iso:country":"US",
    "sg:address":"3521 Norton Ave",
    "sg:city":"Everett",
    "sg:classifiers":[
        {
            "category":"Professional",
            "subcategory":"Art Services",
            "type":"Services"
        }
    ],
    "sg:phone":"+1 425 348 3484",
    "sg:postcode":"98201",
    "sg:province":"WA",
    "sg:tags":[
        "designer",
        "display",
        "producer"
    ],
    "wof:name":"Infinity Design",
    "wof:placetype":"venue"
},
  "geometry": {"coordinates":[-122.21396900000001,47.970752],"type":"Point"}
}