{
  "type": "Feature",
  "properties": {
    "iso:country":"US",
    "sg:address":"22818 34th Ave W",
    "sg:city":"Lynnwood",
    "sg:classifiers":[
        {
            "category":"Building & Trades",
            "subcategory":"Cleaning & Sanitation",
            "type":"Services"
        }
    ],
    "sg:phone":"+1 425 673 8951",
    "sg:postcode":"98036",
    "sg:province":"WA",
    "sg:tags":[
        "maintenance"
    ],
    "wof:name":"Jose V Garcia",
    "wof:placetype":"venue"
},
  "geometry": {"coordinates":[-122.278611,47.789986],"type":"Point"}
}