{
  "type": "Feature",
  "properties": {
    "addr:full":"10508 112th St SW Lakewood WA 98498",
    "addr:housenumber":"10508",
    "addr:postcode":"98498",
    "addr:street":"112Th St Sw",
    "iso:country":"US",
    "sg:address":"10508 112th St SW",
    "sg:city":"Lakewood",
    "sg:classifiers":[
        {
            "category":"Organizations",
            "subcategory":"Religious Organization",
            "type":"Services"
        }
    ],
    "sg:phone":"+1 253 582 1028",
    "sg:postcode":"98498",
    "sg:province":"WA",
    "sg:tags":[
        "church"
    ],
    "wof:name":"St John Bosco Church",
    "wof:placetype":"venue"
},
  "geometry": {"coordinates":[-122.578835,47.155991],"type":"Point"}
}