{
  "type": "Feature",
  "properties": {
    "iso:country":"US",
    "sg:address":"9445 Echo Valley Rd NW",
    "sg:city":"Bremerton",
    "sg:classifiers":[
        {
            "category":"Manufacturing",
            "subcategory":"Wood Products",
            "type":"Manufacturing & Wholesale Goods"
        }
    ],
    "sg:phone":"+1 360 692 4904",
    "sg:postcode":"98312",
    "sg:province":"WA",
    "sg:tags":[
        "box",
        "case",
        "shadow",
        "display"
    ],
    "wof:name":"Shadowboxes Etc",
    "wof:placetype":"venue"
},
  "geometry": {"coordinates":[-122.77594499999999,47.648705],"type":"Point"}
}