{
  "type": "Feature",
  "properties": {
    "addr:full":"2333 Washington St Port Townsend WA 98368",
    "addr:housenumber":"2333",
    "addr:postcode":"98368",
    "addr:street":"Washington St",
    "iso:country":"US",
    "sg:address":"2333 Washington St",
    "sg:city":"Port Townsend",
    "sg:classifiers":[
        {
            "category":"Travel",
            "subcategory":"Hotels & Motels",
            "type":"Entertainment"
        }
    ],
    "sg:phone":"+1 360 385 3747",
    "sg:postcode":"98368",
    "sg:province":"WA",
    "sg:tags":[
        "operation"
    ],
    "wof:name":"Aladdin Motor Inns",
    "wof:placetype":"venue"
},
  "geometry": {"coordinates":[-122.771581,48.108901],"type":"Point"}
}