{
  "type": "Feature",
  "properties": {
    "addr:full":"2706 33rd Ave S Seattle WA 98144",
    "addr:housenumber":"2706",
    "addr:postcode":"98144",
    "addr:street":"33Rd Ave S",
    "iso:country":"US",
    "sg:address":"2706 33rd Ave S",
    "sg:city":"Seattle",
    "sg:classifiers":[
        {
            "category":"Professional",
            "type":"Services"
        }
    ],
    "sg:phone":"+1 206 723 4570",
    "sg:postcode":"98144",
    "sg:province":"WA",
    "wof:name":"Gregg Allen Bauermeister",
    "wof:placetype":"venue"
},
  "geometry": {"coordinates":[-122.290796,47.578423],"type":"Point"}
}