{
  "type": "Feature",
  "properties": {
    "addr:full":"1402 Auburn Way N Ste 2 Auburn WA 98002",
    "addr:housenumber":"1402",
    "addr:postcode":"98002",
    "addr:street":"Auburn Way N Ste 2",
    "iso:country":"US",
    "sg:address":"1402 Auburn Way N Ste 2",
    "sg:city":"Auburn",
    "sg:classifiers":[
        {
            "category":"Professional",
            "subcategory":"Computer Services",
            "type":"Services"
        },
        {
            "category":"Internet Cafe",
            "subcategory":"None",
            "type":"Food & Drink"
        }
    ],
    "sg:phone":"+1 253 333 2111",
    "sg:postcode":"98002",
    "sg:province":"WA",
    "sg:tags":[
        "product",
        "software"
    ],
    "sg:website":"http://www.atlasdevelopment.net",
    "wof:name":"Atlas Development",
    "wof:placetype":"venue"
},
  "geometry": {"coordinates":[-122.221487,47.320238],"type":"Point"}
}