{
  "type": "Feature",
  "properties": {
    "addr:full":"300 N Ely St Kennewick WA 99336",
    "addr:housenumber":"300",
    "addr:postcode":"99336",
    "addr:street":"N Ely St",
    "iso:country":"US",
    "sg:address":"300 N Ely St",
    "sg:city":"Kennewick",
    "sg:classifiers":[
        {
            "category":"Restaurant",
            "type":"Food & Drink"
        }
    ],
    "sg:phone":"+1 509 943 3060",
    "sg:postcode":"99336",
    "sg:province":"WA",
    "sg:tags":[
        "eating"
    ],
    "wof:name":"S & S Hospitality Inc",
    "wof:placetype":"venue"
},
  "geometry": {"coordinates":[-119.15851600000001,46.21339],"type":"Point"}
}