{
  "type": "Feature",
  "properties": {
    "addr:full":"406 McNaught Rd S Roy WA 98580",
    "addr:housenumber":"406",
    "addr:postcode":"98580",
    "addr:street":"Mcnaught Rd S",
    "iso:country":"US",
    "sg:address":"406 McNaught Rd S",
    "sg:city":"Roy",
    "sg:classifiers":[
        {
            "category":"Autos & Motor Vehicles",
            "subcategory":"Automobile Sales",
            "type":"Retail Goods"
        }
    ],
    "sg:phone":"+1 253 843 9779",
    "sg:postcode":"98580",
    "sg:province":"WA",
    "sg:tags":[
        "car",
        "dealer"
    ],
    "wof:name":"Aaron Motors",
    "wof:placetype":"venue"
},
  "geometry": {"coordinates":[-122.543959,47.00183],"type":"Point"}
}