{
  "type": "Feature",
  "properties": {
    "addr:full":"1015 N H St Aberdeen WA 98520",
    "addr:housenumber":"1015",
    "addr:postcode":"98520",
    "addr:street":"N H St",
    "iso:country":"US",
    "sg:address":"1015 N H St",
    "sg:city":"Aberdeen",
    "sg:classifiers":[
        {
            "category":"Building & Trades",
            "subcategory":"Construction",
            "type":"Services"
        }
    ],
    "sg:phone":"+1 360 532 6036",
    "sg:postcode":"98520",
    "sg:province":"WA",
    "sg:tags":[
        "residential",
        "nonresidential"
    ],
    "wof:name":"Silvan Construction Co",
    "wof:placetype":"venue"
},
  "geometry": {"coordinates":[-123.821274,46.981397],"type":"Point"}
}