{
  "type": "Feature",
  "properties": {
    "addr:full":"5532 NE 89th Ave Vancouver WA 98662",
    "addr:housenumber":"5532",
    "addr:postcode":"98662",
    "addr:street":"Ne 89Th Ave",
    "iso:country":"US",
    "sg:address":"5532 NE 89th Ave",
    "sg:city":"Vancouver",
    "sg:classifiers":[
        {
            "category":"Professional",
            "subcategory":"Management & Consulting",
            "type":"Services"
        }
    ],
    "sg:phone":"+1 360 882 4094",
    "sg:postcode":"98662",
    "sg:province":"WA",
    "sg:tags":[
        "business"
    ],
    "wof:name":"Info Dyn Solutions",
    "wof:placetype":"venue"
},
  "geometry": {"coordinates":[-122.581717,45.662583],"type":"Point"}
}