{
  "type": "Feature",
  "properties": {
    "addr:full":"1 S 12th Ave Yakima WA 98902",
    "addr:housenumber":"1",
    "addr:postcode":"98902",
    "addr:street":"S 12Th Ave",
    "iso:country":"US",
    "sg:address":"1 S 12th Ave",
    "sg:city":"Yakima",
    "sg:classifiers":[
        {
            "category":"Autos & Motor Vehicles",
            "subcategory":"Auto Supplies",
            "type":"Retail Goods"
        }
    ],
    "sg:phone":"+1 509 248 7218",
    "sg:postcode":"98902",
    "sg:province":"WA",
    "sg:tags":[
        "automotive",
        "repair"
    ],
    "wof:name":"Yakima Automotive Inc",
    "wof:placetype":"venue"
},
  "geometry": {"coordinates":[-120.525299,46.597172],"type":"Point"}
}