{
  "type": "Feature",
  "properties": {
    "addr:full":"7505 Zier Rd Yakima WA 98908",
    "addr:housenumber":"7505",
    "addr:postcode":"98908",
    "addr:street":"Zier Rd",
    "iso:country":"US",
    "sg:address":"7505 Zier Rd",
    "sg:city":"Yakima",
    "sg:classifiers":[
        {
            "category":"Education",
            "subcategory":"School",
            "type":"Public Place"
        }
    ],
    "sg:phone":"+1 509 972 5800",
    "sg:postcode":"98908",
    "sg:province":"WA",
    "wof:name":"Yakima School District 7",
    "wof:placetype":"venue"
},
  "geometry": {"coordinates":[-120.607769,46.574841],"type":"Point"}
}