{
  "type": "Feature",
  "properties": {
    "addr:full":"21157 SE 280th Pl Maple Valley WA 98038",
    "addr:postcode":"21157;98038",
    "addr:street":"Se 280Th Pl;Valley",
    "iso:country":"US",
    "sg:address":"21157 SE 280th Pl",
    "sg:city":"Maple Valley",
    "sg:classifiers":[
        {
            "category":"Organizations",
            "subcategory":"Political Organization",
            "type":"Services"
        }
    ],
    "sg:phone":"+1 425 413 8135",
    "sg:postcode":"98038",
    "sg:province":"WA",
    "wof:name":"A Peace of Mind",
    "wof:placetype":"venue"
},
  "geometry": {"coordinates":[-122.057757,47.349989],"type":"Point"}
}