{
  "type": "Feature",
  "properties": {
    "addr:full":"506 S Washington Ave Centralia WA 98531",
    "addr:housenumber":"506",
    "addr:postcode":"98531",
    "addr:street":"S Washington Ave",
    "iso:country":"US",
    "sg:address":"506 S Washington Ave",
    "sg:city":"Centralia",
    "sg:classifiers":[
        {
            "category":"Social Services",
            "subcategory":"Child Care",
            "type":"Services"
        }
    ],
    "sg:phone":"+1 360 330 1833",
    "sg:postcode":"98531",
    "sg:province":"WA",
    "sg:tags":[
        "kindergarten",
        "academic",
        "school"
    ],
    "wof:name":"Evergreen Academy",
    "wof:placetype":"venue"
},
  "geometry": {"coordinates":[-122.963093,46.713751],"type":"Point"}
}