{
  "type": "Feature",
  "properties": {
    "iso:country":"US",
    "sg:address":"719 S 1st St",
    "sg:city":"Yakima",
    "sg:classifiers":[
        {
            "category":"Restaurant",
            "type":"Food & Drink"
        }
    ],
    "sg:phone":"+1 509 649 3311",
    "sg:postcode":"98901",
    "sg:province":"WA",
    "wof:name":"2 R Bar & Bistro",
    "wof:placetype":"venue"
},
  "geometry": {"coordinates":[-120.50133,46.592674],"type":"Point"}
}