{
  "type": "Feature",
  "properties": {
    "addr:full":"1330 Boren Ave Seattle WA 98101",
    "addr:housenumber":"1330",
    "addr:postcode":"98101",
    "addr:street":"Boren Ave",
    "iso:country":"US",
    "sg:address":"1330 Boren Ave",
    "sg:city":"Seattle",
    "sg:classifiers":[
        {
            "category":"Shopping",
            "subcategory":"Pets & Pet Supplies",
            "type":"Retail Goods"
        }
    ],
    "sg:phone":"+1 206 484 4722",
    "sg:postcode":"98101",
    "sg:province":"WA",
    "sg:website":"www.playfulpooch.net",
    "wof:name":"Playful Pooch",
    "wof:placetype":"venue"
},
  "geometry": {"coordinates":[-122.327398,47.611807],"type":"Point"}
}