{
  "type": "Feature",
  "properties": {
    "addr:full":"1424 S Bernard St Spokane WA 99203",
    "addr:housenumber":"1424",
    "addr:postcode":"99203",
    "addr:street":"S Bernard St",
    "iso:country":"US",
    "sg:address":"1424 S Bernard St",
    "sg:city":"Spokane",
    "sg:classifiers":[
        {
            "category":"Social Services",
            "type":"Services"
        }
    ],
    "sg:phone":"+1 509 838 7022",
    "sg:postcode":"99203",
    "sg:province":"WA",
    "wof:name":"Sean Mee PHD",
    "wof:placetype":"venue"
},
  "geometry": {"coordinates":[-117.416854,47.641992],"type":"Point"}
}