{
  "type": "Feature",
  "properties": {
    "addr:full":"3808 12th Ave SE Lacey WA 98503",
    "addr:housenumber":"3808",
    "addr:postcode":"98503",
    "addr:street":"12Th Ave Se",
    "iso:country":"US",
    "sg:address":"3808 12th Ave SE",
    "sg:city":"Lacey",
    "sg:classifiers":[
        {
            "category":"Farming",
            "subcategory":"Livestock Farm",
            "type":"Manufacturing & Wholesale Goods"
        }
    ],
    "sg:phone":"+1 360 455 4609",
    "sg:postcode":"98503",
    "sg:province":"WA",
    "sg:tags":[
        "beef",
        "feedlot",
        "cattle"
    ],
    "wof:name":"Randy Smoak",
    "wof:placetype":"venue"
},
  "geometry": {"coordinates":[-122.837654,47.037764],"type":"Point"}
}