{
  "type": "Feature",
  "properties": {
    "addr:full":"818 N Sunrise Blvd Stanwood WA 98282",
    "addr:housenumber":"818",
    "addr:postcode":"98282",
    "addr:street":"N Sunrise Blvd",
    "iso:country":"US",
    "sg:address":"818 N Sunrise Blvd",
    "sg:city":"Stanwood",
    "sg:classifiers":[
        {
            "category":"Real Estate",
            "subcategory":"Real Estate Agent",
            "type":"Services"
        }
    ],
    "sg:phone":"+1 360 387 4663",
    "sg:postcode":"98282",
    "sg:province":"WA",
    "wof:name":"Windermere Camano Island Rlty",
    "wof:placetype":"venue"
},
  "geometry": {"coordinates":[-122.456626,48.242172],"type":"Point"}
}