{
  "type": "Feature",
  "properties": {
    "addr:full":"4800 Jackson Ave SE Port Orchard WA 98366",
    "addr:housenumber":"4800",
    "addr:postcode":"98366",
    "addr:street":"Jackson Ave Se",
    "iso:country":"US",
    "sg:address":"4800 Jackson Ave SE",
    "sg:city":"Port Orchard",
    "sg:classifiers":[
        {
            "category":"Food & Beverages",
            "subcategory":"Groceries & Convenience Stores",
            "type":"Retail Goods"
        }
    ],
    "sg:phone":"+1 360 874 0372",
    "sg:postcode":"98366",
    "sg:province":"WA",
    "wof:name":"Friendly Food Mart",
    "wof:placetype":"venue"
},
  "geometry": {"coordinates":[-122.61006399999999,47.504822],"type":"Point"}
}