{
  "type": "Feature",
  "properties": {
    "addr:full":"2501 14th Ave W Seattle WA 98119",
    "addr:housenumber":"2501",
    "addr:postcode":"98119",
    "addr:street":"14Th Ave W",
    "iso:country":"US",
    "sg:address":"2501 14th Ave W",
    "sg:city":"Seattle",
    "sg:classifiers":[
        {
            "category":"Real Estate",
            "subcategory":"Real Estate Operator",
            "type":"Services"
        }
    ],
    "sg:phone":"+1 206 284 1294",
    "sg:postcode":"98119",
    "sg:province":"WA",
    "sg:tags":[
        "apartment"
    ],
    "wof:name":"Raleigh House",
    "wof:placetype":"venue"
},
  "geometry": {"coordinates":[-122.375,47.641399],"type":"Point"}
}