{
  "type": "Feature",
  "properties": {
    "addr:full":"1280 W Washington St Sequim WA 98382",
    "addr:housenumber":"1280",
    "addr:postcode":"98382",
    "addr:street":"W Washington St",
    "iso:country":"US",
    "sg:address":"1280 W Washington St",
    "sg:city":"Sequim",
    "sg:classifiers":[
        {
            "category":"Restaurant",
            "type":"Food & Drink"
        }
    ],
    "sg:menulink":"http://www.allmenus.com/wa/sequim/177940-jack-in-the-box/menu/",
    "sg:phone":"+1 360 681 4069",
    "sg:postcode":"98382",
    "sg:province":"WA",
    "sg:tags":[
        "burger",
        "american"
    ],
    "wof:name":"Jack in the Box",
    "wof:placetype":"venue"
},
  "geometry": {"coordinates":[-123.14075099999999,48.076753],"type":"Point"}
}