{
  "type": "Feature",
  "properties": {
    "iso:country":"US",
    "sg:address":"420 N Pine St",
    "sg:city":"Ellensburg",
    "sg:classifiers":[
        {
            "category":"Professional",
            "subcategory":"Accounting & Tax Preparation",
            "type":"Services"
        }
    ],
    "sg:phone":"+1 509 925 7932",
    "sg:postcode":"98926",
    "sg:province":"WA",
    "wof:name":"Douglas Butler CPA",
    "wof:placetype":"venue"
},
  "geometry": {"coordinates":[-120.54585,46.996358],"type":"Point"}
}