{
  "type": "Feature",
  "properties": {
    "addr:full":"909 7th St Anacortes WA 98221",
    "addr:housenumber":"909",
    "addr:postcode":"98221",
    "addr:street":"7Th St",
    "iso:country":"US",
    "sg:address":"909 7th St",
    "sg:city":"Anacortes",
    "sg:classifiers":[
        {
            "category":"Professional",
            "subcategory":"Research",
            "type":"Services"
        }
    ],
    "sg:phone":"+1 360 299 9613",
    "sg:postcode":"98221",
    "sg:province":"WA",
    "sg:tags":[
        "organization",
        "noncommercial"
    ],
    "wof:name":"Biz Research Inc",
    "wof:placetype":"venue"
},
  "geometry": {"coordinates":[-122.612441,48.516587],"type":"Point"}
}