{
  "type": "Feature",
  "properties": {
    "addr:full":"110 W Metzler Mill Rd Shelton WA 98584",
    "addr:housenumber":"110",
    "addr:postcode":"98584",
    "addr:street":"W Metzler Mill Rd",
    "iso:country":"US",
    "sg:address":"110 W Metzler Mill Rd",
    "sg:city":"Shelton",
    "sg:classifiers":[
        {
            "category":"Manufacturing",
            "subcategory":"Tools & Machinery",
            "type":"Manufacturing & Wholesale Goods"
        }
    ],
    "sg:phone":"+1 360 426 6901",
    "sg:postcode":"98584",
    "sg:province":"WA",
    "sg:tags":[
        "industrial",
        "mfg"
    ],
    "wof:name":"Lunds Custom Machining Inc",
    "wof:placetype":"venue"
},
  "geometry": {"coordinates":[-123.25441499999999,47.227257],"type":"Point"}
}