{
  "type": "Feature",
  "properties": {
    "addr:full":"301 E Wallace Kneeland Blvd Shelton WA 98584",
    "addr:housenumber":"301",
    "addr:postcode":"98584",
    "addr:street":"E Wallace Kneeland Blvd",
    "iso:country":"US",
    "sg:address":"301 E Wallace Kneeland Blvd",
    "sg:city":"Shelton",
    "sg:classifiers":[
        {
            "category":"Restaurant",
            "type":"Food & Drink"
        }
    ],
    "sg:menulink":"http://www.allmenus.com/wa/shelton/78081-papa-murphys/menu/",
    "sg:phone":"+1 360 427 6400",
    "sg:postcode":"98584",
    "sg:province":"WA",
    "sg:tags":[
        "american",
        "pizza"
    ],
    "wof:name":"Papa Murphy's",
    "wof:placetype":"venue"
},
  "geometry": {"coordinates":[-123.12555399999999,47.231136],"type":"Point"}
}