{
  "type": "Feature",
  "properties": {
    "addr:full":"7324 NE 175th St Kenmore WA 98028",
    "addr:housenumber":"7324",
    "addr:postcode":"98028",
    "addr:street":"Ne 175Th St",
    "iso:country":"US",
    "sg:address":"7324 NE 175th St",
    "sg:city":"Kenmore",
    "sg:classifiers":[
        {
            "category":"Retail",
            "subcategory":"Auto Repair",
            "type":"Services"
        }
    ],
    "sg:phone":"+1 425 489 1097",
    "sg:postcode":"98028",
    "sg:province":"WA",
    "sg:tags":[
        "body",
        "automobile",
        "painting"
    ],
    "wof:name":"European Auto Rebuild",
    "wof:placetype":"venue"
},
  "geometry": {"coordinates":[-122.242791,47.756443],"type":"Point"}
}