{
  "type": "Feature",
  "properties": {
    "iso:country":"US",
    "sg:address":"5920 14th Ave NW",
    "sg:city":"Marysville",
    "sg:classifiers":[
        {
            "category":"Building & Trades",
            "subcategory":"Construction",
            "type":"Services"
        },
        {
            "category":"Manufacturing",
            "subcategory":"Watercraft",
            "type":"Manufacturing & Wholesale Goods"
        }
    ],
    "sg:phone":"+1 360 659 9598",
    "sg:postcode":"98271",
    "sg:province":"WA",
    "sg:tags":[
        "designer",
        "marine",
        "boat",
        "contractor"
    ],
    "wof:name":"Perpetual Marine Svc",
    "wof:placetype":"venue"
},
  "geometry": {"coordinates":[-122.251812,48.047573],"type":"Point"}
}