{
  "type": "Feature",
  "properties": {
    "addr:full":"98 Schouweiler Rd Elma WA 98541",
    "addr:housenumber":"98",
    "addr:postcode":"98541",
    "addr:street":"Schouweiler Rd",
    "iso:country":"US",
    "sg:address":"98 Schouweiler Rd",
    "sg:city":"Elma",
    "sg:classifiers":[
        {
            "category":"Freight",
            "type":"Transportation"
        }
    ],
    "sg:phone":"+1 360 482 3714",
    "sg:postcode":"98541",
    "sg:province":"WA",
    "sg:tags":[
        "special"
    ],
    "wof:name":"All Storage",
    "wof:placetype":"venue"
},
  "geometry": {"coordinates":[-123.445685,46.997056],"type":"Point"}
}