{
  "type": "Feature",
  "properties": {
    "addr:full":"3717 Goldcrest Hts NW Olympia WA 98502",
    "addr:housenumber":"3717",
    "addr:postcode":"olympia wa 98502",
    "addr:street":"Goldcrest Hts Nw",
    "iso:country":"US",
    "sg:address":"3717 Goldcrest Hts NW",
    "sg:city":"Olympia",
    "sg:classifiers":[
        {
            "category":"Building & Trades",
            "subcategory":"Cleaning & Sanitation",
            "type":"Services"
        }
    ],
    "sg:phone":"+1 360 867 0949",
    "sg:postcode":"98502",
    "sg:province":"WA",
    "sg:tags":[
        "maintenance"
    ],
    "wof:name":"Health Maintenance Associates",
    "wof:placetype":"venue"
},
  "geometry": {"coordinates":[-122.94771299999999,47.061557],"type":"Point"}
}