{
  "type": "Feature",
  "properties": {
    "addr:full":"11710 Airport Rd Everett WA 98204",
    "addr:housenumber":"11710",
    "addr:postcode":"98204",
    "addr:street":"Airport Rd",
    "iso:country":"US",
    "sg:address":"11710 Airport Rd",
    "sg:city":"Everett",
    "sg:classifiers":[
        {
            "category":"Wholesale",
            "subcategory":"Auto Parts",
            "type":"Manufacturing & Wholesale Goods"
        }
    ],
    "sg:phone":"+1 425 745 5859",
    "sg:postcode":"98204",
    "sg:province":"WA",
    "sg:tags":[
        "supply"
    ],
    "sg:website":"www.napa.com",
    "wof:name":"NAPA Auto Parts",
    "wof:placetype":"venue"
},
  "geometry": {"coordinates":[-122.260403,47.892357],"type":"Point"}
}