{
  "type": "Feature",
  "properties": {
    "addr:full":"18223 Vashon Hwy SW Vashon WA 98070",
    "addr:housenumber":"18223",
    "addr:postcode":"98070",
    "addr:street":"Vashon Hwy Sw",
    "iso:country":"US",
    "sg:address":"18223 Vashon Hwy SW",
    "sg:city":"Vashon",
    "sg:classifiers":[
        {
            "category":"Farming",
            "subcategory":"Fish & Marine Products",
            "type":"Manufacturing & Wholesale Goods"
        }
    ],
    "sg:phone":"+1 206 463 2280",
    "sg:postcode":"98070",
    "sg:province":"WA",
    "sg:tags":[
        "catching"
    ],
    "wof:name":"Star of Heaven Fisheries Inc",
    "wof:placetype":"venue"
},
  "geometry": {"coordinates":[-122.460571,47.44187],"type":"Point"}
}