{
  "type": "Feature",
  "properties": {
    "addr:full":"3802 Colby Ave Everett WA 98201",
    "addr:housenumber":"3802",
    "addr:postcode":"98201",
    "addr:street":"Colby Ave",
    "iso:country":"US",
    "sg:address":"3802 Colby Ave",
    "sg:city":"Everett",
    "sg:classifiers":[
        {
            "category":"Health Services",
            "subcategory":"Doctor",
            "type":"Services"
        }
    ],
    "sg:phone":"+1 425 258 3522",
    "sg:postcode":"98201",
    "sg:province":"WA",
    "sg:tags":[
        "physician",
        "surgeon"
    ],
    "wof:name":"Western WA Medical Group",
    "wof:placetype":"venue"
},
  "geometry": {"coordinates":[-122.208152,47.966021],"type":"Point"}
}