{
  "type": "Feature",
  "properties": {
    "addr:full":"7605 SE 27th St Mercer Island WA 98040",
    "addr:housenumber":"7605",
    "addr:postcode":"98040",
    "addr:street":"Se 27Th St",
    "iso:country":"US",
    "sg:address":"7605 SE 27th St",
    "sg:city":"Mercer Island",
    "sg:classifiers":[
        {
            "category":"Personal",
            "type":"Services"
        }
    ],
    "sg:phone":"+1 206 232 0842",
    "sg:postcode":"98040",
    "sg:province":"WA",
    "sg:tags":[
        "home"
    ],
    "wof:name":"Island Security",
    "wof:placetype":"venue"
},
  "geometry": {"coordinates":[-122.23742900000001,47.586734],"type":"Point"}
}