{
  "type": "Feature",
  "properties": {
    "addr:full":"5611 125th Ln NE Kirkland WA 98033",
    "addr:housenumber":"5611",
    "addr:postcode":"98033",
    "addr:street":"125Th Ln Ne",
    "iso:country":"US",
    "sg:address":"5611 125th Ln NE",
    "sg:city":"Kirkland",
    "sg:classifiers":[
        {
            "category":"Taxi",
            "type":"Transportation"
        }
    ],
    "sg:phone":"+1 425 576 1616",
    "sg:postcode":"98033",
    "sg:province":"WA",
    "sg:tags":[
        "taxicab"
    ],
    "wof:name":"Checker Deluxe Cab",
    "wof:placetype":"venue"
},
  "geometry": {"coordinates":[-122.17389799999999,47.659261],"type":"Point"}
}