{
  "type": "Feature",
  "properties": {
    "addr:full":"11052 SE Mill Plain Blvd Vancouver WA 98664",
    "addr:housenumber":"11052",
    "addr:postcode":"98664",
    "addr:street":"Se Mill Plain Blvd",
    "iso:country":"US",
    "sg:address":"11052 SE Mill Plain Blvd",
    "sg:city":"Vancouver",
    "sg:classifiers":[
        {
            "category":"Coffee & Tea",
            "type":"Food & Drink"
        }
    ],
    "sg:phone":"+1 360 253 5270",
    "sg:postcode":"98664",
    "sg:province":"WA",
    "wof:name":"Starbucks",
    "wof:placetype":"venue"
},
  "geometry": {"coordinates":[-122.560425,45.6211],"type":"Point"}
}