{
  "type": "Feature",
  "properties": {
    "addr:full":"222 Dexter Ave N Seattle WA 98109",
    "addr:housenumber":"222",
    "addr:postcode":"98109",
    "addr:street":"Dexter Ave N",
    "iso:country":"US",
    "sg:address":"222 Dexter Ave N",
    "sg:city":"Seattle",
    "sg:classifiers":[
        {
            "category":"Professional",
            "subcategory":"Advertising",
            "type":"Services"
        }
    ],
    "sg:phone":"+1 206 223 0055",
    "sg:postcode":"98109",
    "sg:province":"WA",
    "sg:tags":[
        "graphic",
        "design",
        "agency"
    ],
    "sg:website":"www.hl2.com",
    "wof:name":"Horton Lantz & Low",
    "wof:placetype":"venue"
},
  "geometry": {"coordinates":[-122.34231,47.620623],"type":"Point"}
}