{
  "type": "Feature",
  "properties": {
    "addr:full":"30 E Liberty Pl Shelton WA 98584",
    "addr:housenumber":"30",
    "addr:postcode":"98584",
    "addr:street":"E Liberty Pl",
    "iso:country":"US",
    "sg:address":"30 E Liberty Pl",
    "sg:city":"Shelton",
    "sg:classifiers":[
        {
            "category":"Professional",
            "subcategory":"Art Services",
            "type":"Services"
        }
    ],
    "sg:phone":"+1 360 432 9878",
    "sg:postcode":"98584",
    "sg:province":"WA",
    "sg:tags":[
        "designer",
        "display",
        "producer"
    ],
    "wof:name":"Creative Design",
    "wof:placetype":"venue"
},
  "geometry": {"coordinates":[-122.975185,47.224886],"type":"Point"}
}