{
  "type": "Feature",
  "properties": {
    "addr:full":"17048 Holly St SE Yelm WA 98597",
    "addr:housenumber":"17048",
    "addr:postcode":"98597",
    "addr:street":"Holly St Se",
    "iso:country":"US",
    "sg:address":"17048 Holly St SE",
    "sg:city":"Yelm",
    "sg:classifiers":[
        {
            "category":"Building & Trades",
            "subcategory":"Equipment Rental",
            "type":"Services"
        }
    ],
    "sg:phone":"+1 360 458 1878",
    "sg:postcode":"98597",
    "sg:province":"WA",
    "sg:tags":[
        "instruments-rental",
        "musical"
    ],
    "wof:name":"Lucky Draw",
    "wof:placetype":"venue"
},
  "geometry": {"coordinates":[-122.575739,46.964932],"type":"Point"}
}