{
  "type": "Feature",
  "properties": {
    "addr:full":"33431 13th Pl S Federal Way WA 98003",
    "addr:housenumber":"33431",
    "addr:postcode":"98003",
    "addr:street":"13Th Pl S Federal Way",
    "iso:country":"US",
    "sg:address":"33431 13th Pl S",
    "sg:city":"Federal Way",
    "sg:classifiers":[
        {
            "category":"Health Services",
            "subcategory":"Doctor",
            "type":"Services"
        }
    ],
    "sg:phone":"+1 253 838 4557",
    "sg:postcode":"98003",
    "sg:province":"WA",
    "sg:tags":[
        "medical",
        "public"
    ],
    "wof:name":"Health Dept",
    "wof:placetype":"venue"
},
  "geometry": {"coordinates":[-122.316784,47.302577],"type":"Point"}
}