{
  "type": "Feature",
  "properties": {
    "addr:full":"7005 3rd Ave NW Seattle WA 98117",
    "addr:housenumber":"7005",
    "addr:postcode":"98117",
    "addr:street":"3Rd Ave Nw",
    "iso:country":"US",
    "sg:address":"7005 3rd Ave NW",
    "sg:city":"Seattle",
    "sg:classifiers":[
        {
            "category":"Home & Garden",
            "subcategory":"Home Furnishings",
            "type":"Retail Goods"
        }
    ],
    "sg:phone":"+1 206 781 6885",
    "sg:postcode":"98117",
    "sg:province":"WA",
    "wof:name":"Interdyme",
    "wof:placetype":"venue"
},
  "geometry": {"coordinates":[-122.360558,47.680704],"type":"Point"}
}