{
  "type": "Feature",
  "properties": {
    "addr:full":"1504 Fryar Ave Sumner WA 98390",
    "addr:housenumber":"1504",
    "addr:postcode":"98390",
    "addr:street":"Fryar Ave",
    "iso:country":"US",
    "sg:address":"1504 Fryar Ave",
    "sg:city":"Sumner",
    "sg:classifiers":[
        {
            "category":"Building & Trades",
            "subcategory":"Construction",
            "type":"Services"
        }
    ],
    "sg:phone":"+1 253 863 0660",
    "sg:postcode":"98390",
    "sg:province":"WA",
    "sg:tags":[
        "general",
        "commercial",
        "contractor"
    ],
    "wof:name":"Sessler Inc",
    "wof:placetype":"venue"
},
  "geometry": {"coordinates":[-122.242175,47.209697],"type":"Point"}
}