{
  "type": "Feature",
  "properties": {
    "addr:full":"7600 Renton Issaquah Rd SE Issaquah WA 98027",
    "addr:housenumber":"7600",
    "addr:postcode":"98027",
    "addr:street":"Issaquah Rd Se",
    "iso:country":"US",
    "sg:address":"7600 Renton Issaquah Rd SE",
    "sg:city":"Issaquah",
    "sg:classifiers":[
        {
            "category":"Shopping",
            "subcategory":"Florist",
            "type":"Retail Goods"
        }
    ],
    "sg:phone":"+1 425 392 1025",
    "sg:postcode":"98027",
    "sg:province":"WA",
    "sg:tags":[
        "plant"
    ],
    "wof:name":"Squak Mt Greenhouses & Nursery",
    "wof:placetype":"venue"
},
  "geometry": {"coordinates":[-122.062314,47.533997],"type":"Point"}
}