{
  "type": "Feature",
  "properties": {
    "addr:full":"2721 Meridian St Bellingham WA 98225",
    "addr:housenumber":"2721",
    "addr:postcode":"98225",
    "addr:street":"Meridian St",
    "iso:country":"US",
    "sg:address":"2721 Meridian St",
    "sg:city":"Bellingham",
    "sg:classifiers":[
        {
            "category":"Personal",
            "subcategory":"Beauty Salon",
            "type":"Services"
        }
    ],
    "sg:phone":"+1 360 715 1957",
    "sg:postcode":"98225",
    "sg:province":"WA",
    "sg:tags":[
        "shop"
    ],
    "wof:name":"Designs On You",
    "wof:placetype":"venue"
},
  "geometry": {"coordinates":[-122.486159,48.766667],"type":"Point"}
}