{
  "type": "Feature",
  "properties": {
    "iso:country":"US",
    "sg:address":"6251 Kimber Rd",
    "sg:city":"Cashmere",
    "sg:classifiers":[
        {
            "category":"Health Services",
            "subcategory":"Clinic",
            "type":"Services"
        }
    ],
    "sg:phone":"+1 509 782 8078",
    "sg:postcode":"98815",
    "sg:province":"WA",
    "sg:tags":[
        "provide",
        "food",
        "for"
    ],
    "wof:name":"Healling Connections The",
    "wof:placetype":"venue"
},
  "geometry": {"coordinates":[-120.499016,47.520564],"type":"Point"}
}