{
  "type": "Feature",
  "properties": {
    "addr:full":"105 W Main Ave Chewelah WA 99109",
    "addr:housenumber":"105",
    "addr:postcode":"99109",
    "addr:street":"W Main Ave",
    "iso:country":"US",
    "sg:address":"105 W Main Ave",
    "sg:city":"Chewelah",
    "sg:classifiers":[
        {
            "category":"Manufacturing",
            "subcategory":"Lumber",
            "type":"Manufacturing & Wholesale Goods"
        }
    ],
    "sg:phone":"+1 509 935 4515",
    "sg:postcode":"99109",
    "sg:province":"WA",
    "sg:tags":[
        "company",
        "logging"
    ],
    "wof:name":"Hansen Logging",
    "wof:placetype":"venue"
},
  "geometry": {"coordinates":[-117.715491,48.276339],"type":"Point"}
}