{
  "type": "Feature",
  "properties": {
    "addr:full":"600 Royal St Kelso WA 98626",
    "addr:housenumber":"600",
    "addr:postcode":"98626",
    "addr:street":"Royal St",
    "iso:country":"US",
    "sg:address":"600 Royal St",
    "sg:city":"Kelso",
    "sg:classifiers":[
        {
            "category":"Banks & Credit Unions",
            "subcategory":"Bank",
            "type":"Services"
        }
    ],
    "sg:phone":"+1 360 425 8793",
    "sg:postcode":"98626",
    "sg:province":"WA",
    "sg:tags":[
        "loan",
        "real estate"
    ],
    "wof:name":"Ambassador Mortgage",
    "wof:placetype":"venue"
},
  "geometry": {"coordinates":[-122.921567,46.147881],"type":"Point"}
}