{
  "type": "Feature",
  "properties": {
    "addr:full":"1531 Bradner Pl S Seattle WA 98144",
    "addr:housenumber":"1531",
    "addr:postcode":"98144",
    "addr:street":"Bradner Pl S",
    "iso:country":"US",
    "sg:address":"1531 Bradner Pl S",
    "sg:city":"Seattle",
    "sg:classifiers":[
        {
            "category":"Organizations",
            "subcategory":"Religious Organization",
            "type":"Services"
        }
    ],
    "sg:phone":"+1 206 324 8521",
    "sg:postcode":"98144",
    "sg:province":"WA",
    "wof:name":"Our Lady of Mt Virgin Church",
    "wof:placetype":"venue"
},
  "geometry": {"coordinates":[-122.296025,47.588469],"type":"Point"}
}