{
  "type": "Feature",
  "properties": {
    "addr:full":"126 131st St S Tacoma WA 98444",
    "addr:housenumber":"126",
    "addr:postcode":"98444",
    "addr:street":"131St St S",
    "iso:country":"US",
    "sg:address":"126 131st St S",
    "sg:city":"Tacoma",
    "sg:classifiers":[
        {
            "category":"Health Services",
            "subcategory":"Hospital",
            "type":"Services"
        }
    ],
    "sg:phone":"+1 253 531 2460",
    "sg:postcode":"98444",
    "sg:province":"WA",
    "wof:name":"St Clare Hospital",
    "wof:placetype":"venue"
},
  "geometry": {"coordinates":[-122.43413200000001,47.138486],"type":"Point"}
}