{
  "type": "Feature",
  "properties": {
    "addr:full":"19955 Hillvue Pl Burlington WA 98233",
    "addr:postcode":"19955;98233",
    "addr:street":"Hillvue Pl",
    "iso:country":"US",
    "sg:address":"19955 Hillvue Pl",
    "sg:city":"Burlington",
    "sg:classifiers":[
        {
            "category":"Shopping",
            "subcategory":"Beauty & Cosmetics",
            "type":"Retail Goods"
        }
    ],
    "sg:phone":"+1 360 757 0753",
    "sg:postcode":"98233",
    "sg:province":"WA",
    "sg:tags":[
        "merchandise"
    ],
    "wof:name":"Jeannette Hill Avon",
    "wof:placetype":"venue"
},
  "geometry": {"coordinates":[-122.31462000000001,48.484818],"type":"Point"}
}