{
  "type": "Feature",
  "properties": {
    "addr:full":"219 Broadway E Seattle WA 98102",
    "addr:housenumber":"219",
    "addr:postcode":"98102",
    "addr:street":"Broadway",
    "iso:country":"US",
    "sg:address":"219 Broadway E",
    "sg:city":"Seattle",
    "sg:classifiers":[
        {
            "category":"Restaurant",
            "type":"Food & Drink"
        }
    ],
    "sg:phone":"+1 206 323 4472",
    "sg:postcode":"98102",
    "sg:province":"WA",
    "sg:tags":[
        "eating"
    ],
    "wof:name":"Kimchi Bistro",
    "wof:placetype":"venue"
},
  "geometry": {"coordinates":[-122.320966,47.620859],"type":"Point"}
}