{
  "type": "Feature",
  "properties": {
    "addr:full":"6995 Old Military Rd NE Bremerton WA 98311",
    "addr:housenumber":"6995",
    "addr:postcode":"98311",
    "addr:street":"Old Military Rd Ne",
    "iso:country":"US",
    "sg:address":"6995 Old Military Rd NE",
    "sg:city":"Bremerton",
    "sg:classifiers":[
        {
            "category":"Shopping",
            "subcategory":"Florist",
            "type":"Retail Goods"
        }
    ],
    "sg:phone":"+1 360 692 8867",
    "sg:postcode":"98311",
    "sg:province":"WA",
    "wof:name":"Kathleen's Creation",
    "wof:placetype":"venue"
},
  "geometry": {"coordinates":[-122.63686800000001,47.626741],"type":"Point"}
}