{
  "type": "Feature",
  "properties": {
    "addr:full":"525 E Main St Walla Walla WA 99362",
    "addr:housenumber":"525",
    "addr:postcode":"99362",
    "addr:street":"E Main St",
    "iso:country":"US",
    "sg:address":"525 E Main St",
    "sg:city":"Walla Walla",
    "sg:classifiers":[
        {
            "category":"Shopping",
            "subcategory":"Clothing, Apparel, & Fashions",
            "type":"Retail Goods"
        }
    ],
    "sg:phone":"+1 509 525 3252",
    "sg:postcode":"99362",
    "sg:province":"WA",
    "sg:tags":[
        "shop",
        "bridal"
    ],
    "wof:name":"Mann's House Of Brides",
    "wof:placetype":"venue"
},
  "geometry": {"coordinates":[-118.333034,46.071969],"type":"Point"}
}