{
  "type": "Feature",
  "properties": {
    "addr:full":"828 Commercial St Leavenworth WA 98826",
    "addr:housenumber":"828",
    "addr:postcode":"98826",
    "addr:street":"Commercial St",
    "iso:country":"US",
    "sg:address":"828 Commercial St",
    "sg:city":"Leavenworth",
    "sg:classifiers":[
        {
            "category":"Food & Beverages",
            "subcategory":"Bakery",
            "type":"Retail Goods"
        }
    ],
    "sg:phone":"+1 509 548 6592",
    "sg:postcode":"98826",
    "sg:province":"WA",
    "sg:tags":[
        "baker"
    ],
    "wof:name":"Gingerbread Factory",
    "wof:placetype":"venue"
},
  "geometry": {"coordinates":[-120.65647,47.596391],"type":"Point"}
}