{
  "type": "Feature",
  "properties": {
    "addr:full":"10706 Crescent Valley Dr NW Gig Harbor WA 98332",
    "addr:housenumber":"10706",
    "addr:postcode":"98332",
    "addr:street":"Crescent Valley Dr Nw",
    "iso:country":"US",
    "sg:address":"10706 Crescent Valley Dr NW",
    "sg:city":"Gig Harbor",
    "sg:classifiers":[
        {
            "category":"Professional",
            "subcategory":"Business Services",
            "type":"Services"
        }
    ],
    "sg:phone":"+1 253 851 7521",
    "sg:postcode":"98332",
    "sg:province":"WA",
    "wof:name":"Schlemmer Design",
    "wof:placetype":"venue"
},
  "geometry": {"coordinates":[-122.578569,47.355871],"type":"Point"}
}