{
  "type": "Feature",
  "properties": {
    "addr:full":"536 W Railroad Ave Shelton WA 98584",
    "addr:housenumber":"536",
    "addr:postcode":"98584",
    "addr:street":"W Railroad Ave",
    "iso:country":"US",
    "sg:address":"536 W Railroad Ave",
    "sg:city":"Shelton",
    "sg:classifiers":[
        {
            "category":"Health Services",
            "subcategory":"Optometrist",
            "type":"Services"
        }
    ],
    "sg:phone":"+1 360 426 1636",
    "sg:postcode":"98584",
    "sg:province":"WA",
    "wof:name":"George Radich Optometrists",
    "wof:placetype":"venue"
},
  "geometry": {"coordinates":[-123.10571,47.213365],"type":"Point"}
}