{
  "type": "Feature",
  "properties": {
    "addr:full":"1015 8th St Anacortes WA 98221",
    "addr:housenumber":"1015",
    "addr:postcode":"98221",
    "addr:street":"8Th St",
    "iso:country":"US",
    "sg:address":"1015 8th St",
    "sg:city":"Anacortes",
    "sg:classifiers":[
        {
            "category":"Personal",
            "subcategory":"Beauty Salon",
            "type":"Services"
        }
    ],
    "sg:phone":"+1 360 299 9533",
    "sg:postcode":"98221",
    "sg:province":"WA",
    "sg:tags":[
        "shop"
    ],
    "wof:name":"Hair Station",
    "wof:placetype":"venue"
},
  "geometry": {"coordinates":[-122.61396000000001,48.515788],"type":"Point"}
}