{
  "type": "Feature",
  "properties": {
    "addr:full":"2441 76th Ave SE Mercer Island WA 98040",
    "addr:housenumber":"2441",
    "addr:postcode":"98040",
    "addr:street":"76Th Ave Se",
    "iso:country":"US",
    "sg:address":"2441 76th Ave SE",
    "sg:city":"Mercer Island",
    "sg:classifiers":[
        {
            "category":"Wholesale",
            "subcategory":"Plants",
            "type":"Manufacturing & Wholesale Goods"
        },
        {
            "category":"Professional",
            "subcategory":"Business Services",
            "type":"Services"
        }
    ],
    "sg:phone":"+1 206 230 8770",
    "sg:postcode":"98040",
    "sg:province":"WA",
    "sg:tags":[
        "design",
        "maintenance",
        "supply"
    ],
    "sg:website":"www.initialplants.com",
    "wof:name":"Initial Tropical Plants Inc",
    "wof:placetype":"venue"
},
  "geometry": {"coordinates":[-122.23772,47.587559],"type":"Point"}
}