{
  "type": "Feature",
  "properties": {
    "addr:full":"555 Blue Sky Dr Port Townsend WA 98368",
    "addr:housenumber":"555",
    "addr:postcode":"98368",
    "addr:street":"Blue Sky Dr",
    "iso:country":"US",
    "sg:address":"555 Blue Sky Dr",
    "sg:city":"Port Townsend",
    "sg:classifiers":[
        {
            "category":"Professional",
            "subcategory":"Business Services",
            "type":"Services"
        }
    ],
    "sg:phone":"+1 360 385 2559",
    "sg:postcode":"98368",
    "sg:province":"WA",
    "sg:tags":[
        "consultant",
        "management",
        "for",
        "coastal"
    ],
    "wof:name":"Laroche & Associates",
    "wof:placetype":"venue"
},
  "geometry": {"coordinates":[-122.854345,48.077674],"type":"Point"}
}