{
  "type": "Feature",
  "properties": {
    "iso:country":"US",
    "sg:address":"16733 SE 168th St",
    "sg:city":"Renton",
    "sg:classifiers":[
        {
            "category":"Travel",
            "subcategory":"Hotels & Motels",
            "type":"Entertainment"
        }
    ],
    "sg:phone":"+1 509 547 0791",
    "sg:postcode":"98058",
    "sg:province":"WA",
    "wof:name":"Vineyard Inn",
    "wof:placetype":"venue"
},
  "geometry": {"coordinates":[-122.160729,47.450805],"type":"Point"}
}