{
  "type": "Feature",
  "properties": {
    "addr:full":"1805 S 1st St Sunnyside WA 98944",
    "addr:housenumber":"1805",
    "addr:postcode":"98944",
    "addr:street":"S 1St St",
    "iso:country":"US",
    "sg:address":"1805 S 1st St",
    "sg:city":"Sunnyside",
    "sg:classifiers":[
        {
            "category":"Food & Beverages",
            "subcategory":"Specialty",
            "type":"Retail Goods"
        }
    ],
    "sg:phone":"+1 509 839 0243",
    "sg:postcode":"98944",
    "sg:province":"WA",
    "sg:tags":[
        "tea",
        "coffee"
    ],
    "wof:name":"Jump Start Expresso",
    "wof:placetype":"venue"
},
  "geometry": {"coordinates":[-120.02021499999999,46.309202],"type":"Point"}
}