{
  "type": "Feature",
  "properties": {
    "addr:full":"1402 Broadway Everett WA 98201",
    "addr:housenumber":"1402",
    "addr:postcode":"98201",
    "addr:street":"Broadway",
    "iso:country":"US",
    "sg:address":"1402 Broadway",
    "sg:city":"Everett",
    "sg:classifiers":[
        {
            "category":"Building & Trades",
            "subcategory":"Landscaping Services",
            "type":"Services"
        }
    ],
    "sg:phone":"+1 425 252 2384",
    "sg:postcode":"98201",
    "sg:province":"WA",
    "sg:tags":[
        "lawn",
        "garden"
    ],
    "wof:name":"Townsends Landscaping",
    "wof:placetype":"venue"
},
  "geometry": {"coordinates":[-122.20117500000001,47.997686],"type":"Point"}
}