{
  "type": "Feature",
  "properties": {
    "addr:full":"3425 W McGraw St Seattle WA 98199",
    "addr:housenumber":"3425",
    "addr:postcode":"98199",
    "addr:street":"W Mcgraw St",
    "iso:country":"US",
    "sg:address":"3425 W McGraw St",
    "sg:city":"Seattle",
    "sg:classifiers":[
        {
            "category":"Banks & Credit Unions",
            "subcategory":"Bank",
            "type":"Services"
        },
        {
            "category":"Banks & Credit Unions",
            "subcategory":"Financial Services",
            "type":"Services"
        }
    ],
    "sg:phone":"+1 206 358 1920",
    "sg:postcode":"98199",
    "sg:province":"WA",
    "sg:tags":[
        "broker",
        "mortgage"
    ],
    "sg:website":"www.bankofamerica.com",
    "wof:name":"Bank of America",
    "wof:placetype":"venue"
},
  "geometry": {"coordinates":[-122.402,47.6394],"type":"Point"}
}