{
  "type": "Feature",
  "properties": {
    "addr:full":"1321 Queen Anne Ave N Seattle WA 98109",
    "addr:housenumber":"1321",
    "addr:postcode":"98109",
    "addr:street":"Queen Anne Ave N",
    "iso:country":"US",
    "sg:address":"1321 Queen Anne Ave N",
    "sg:city":"Seattle",
    "sg:classifiers":[
        {
            "category":"Real Estate",
            "subcategory":"Real Estate Operator",
            "type":"Services"
        }
    ],
    "sg:phone":"+1 206 285 1835",
    "sg:postcode":"98109",
    "sg:province":"WA",
    "sg:tags":[
        "building",
        "apartment"
    ],
    "wof:name":"Birkeland and Associates",
    "wof:placetype":"venue"
},
  "geometry": {"coordinates":[-122.356674,47.631125],"type":"Point"}
}