{
  "type": "Feature",
  "properties": {
    "addr:full":"9412 E Boone Ave Spokane WA 99206",
    "addr:housenumber":"9412",
    "addr:postcode":"99206",
    "addr:street":"E Boone Ave",
    "iso:country":"US",
    "sg:address":"9412 E Boone Ave",
    "sg:city":"Spokane",
    "sg:classifiers":[
        {
            "category":"Personal",
            "type":"Services"
        }
    ],
    "sg:phone":"+1 509 891 8786",
    "sg:postcode":"99206",
    "sg:province":"WA",
    "wof:name":"Pam Mackey Events",
    "wof:placetype":"venue"
},
  "geometry": {"coordinates":[-117.277766,47.667932],"type":"Point"}
}