{
  "type": "Feature",
  "properties": {
    "addr:full":"270 Williams Lake Rd C Colville WA 99114",
    "addr:housenumber":"270",
    "addr:postcode":"colville wa 99114",
    "addr:street":"Williams Lake Rd",
    "iso:country":"US",
    "sg:address":"270 Williams Lake Rd C",
    "sg:city":"Colville",
    "sg:classifiers":[
        {
            "category":"Shopping",
            "subcategory":"Pets & Pet Supplies",
            "type":"Retail Goods"
        }
    ],
    "sg:phone":"+1 509 435 0416",
    "sg:postcode":"99114",
    "sg:province":"WA",
    "sg:tags":[
        "specialty"
    ],
    "wof:name":"Big Cat Post",
    "wof:placetype":"venue"
},
  "geometry": {"coordinates":[-117.93628,48.574407],"type":"Point"}
}