{
  "type": "Feature",
  "properties": {
    "addr:full":"1312 S Rotchford Dr Veradale WA 99037",
    "addr:housenumber":"1312",
    "addr:postcode":"99037",
    "addr:street":"S Rotchford Dr",
    "iso:country":"US",
    "sg:address":"1312 S Rotchford Dr",
    "sg:city":"Veradale",
    "sg:classifiers":[
        {
            "category":"Building & Trades",
            "subcategory":"Construction",
            "type":"Services"
        }
    ],
    "sg:phone":"+1 509 928 3101",
    "sg:postcode":"99037",
    "sg:province":"WA",
    "sg:tags":[
        "floor",
        "laying",
        "contractor"
    ],
    "wof:name":"Evans Hardwood",
    "wof:placetype":"venue"
},
  "geometry": {"coordinates":[-117.187247,47.647178],"type":"Point"}
}