{
  "type": "Feature",
  "properties": {
    "addr:full":"901 NE Lincoln Rd Poulsbo WA 98370",
    "addr:housenumber":"901",
    "addr:postcode":"98370",
    "addr:street":"Ne Lincoln Rd",
    "iso:country":"US",
    "sg:address":"901 NE Lincoln Rd",
    "sg:city":"Poulsbo",
    "sg:classifiers":[
        {
            "category":"Banks & Credit Unions",
            "subcategory":"Investment Brokerage",
            "type":"Services"
        }
    ],
    "sg:phone":"+1 360 394 0010",
    "sg:postcode":"98370",
    "sg:province":"WA",
    "sg:tags":[
        "consultant",
        "financing"
    ],
    "wof:name":"Discovery Financial",
    "wof:placetype":"venue"
},
  "geometry": {"coordinates":[-122.635561,47.737086],"type":"Point"}
}