{
  "type": "Feature",
  "properties": {
    "addr:full":"325 N Johnson St Kennewick WA 99336",
    "addr:housenumber":"325",
    "addr:postcode":"99336",
    "addr:street":"N Johnson St",
    "iso:country":"US",
    "sg:address":"325 N Johnson St",
    "sg:city":"Kennewick",
    "sg:classifiers":[
        {
            "category":"Organizations",
            "subcategory":"Religious Organization",
            "type":"Services"
        }
    ],
    "sg:phone":"+1 509 735 6163",
    "sg:postcode":"99336",
    "sg:province":"WA",
    "sg:tags":[
        "church"
    ],
    "wof:name":"Church Of Salvation Arc",
    "wof:placetype":"venue"
},
  "geometry": {"coordinates":[-119.166004,46.213255],"type":"Point"}
}