{
  "type": "Feature",
  "properties": {
    "addr:full":"4011 Talbot Rd S Renton WA 98055",
    "addr:housenumber":"4011",
    "addr:postcode":"98055",
    "addr:street":"Talbot Rd S",
    "iso:country":"US",
    "sg:address":"4011 Talbot Rd S",
    "sg:city":"Renton",
    "sg:classifiers":[
        {
            "category":"Health Services",
            "subcategory":"Doctor",
            "type":"Services"
        }
    ],
    "sg:phone":"+1 425 226 4300",
    "sg:postcode":"98055",
    "sg:province":"WA",
    "wof:name":"Joos & Jones & Keogh",
    "wof:placetype":"venue"
},
  "geometry": {"coordinates":[-122.212345,47.442086],"type":"Point"}
}