{
  "type": "Feature",
  "properties": {
    "addr:full":"5201 15th Ave NW Seattle WA 98107",
    "addr:housenumber":"5201",
    "addr:postcode":"98107",
    "addr:street":"15Th Ave Nw",
    "iso:country":"US",
    "sg:address":"5201 15th Ave NW",
    "sg:city":"Seattle",
    "sg:classifiers":[
        {
            "category":"Manufacturing",
            "subcategory":"Printing",
            "type":"Manufacturing & Wholesale Goods"
        }
    ],
    "sg:phone":"+1 206 789 4313",
    "sg:postcode":"98107",
    "sg:province":"WA",
    "sg:tags":[
        "lithographic",
        "commercial"
    ],
    "wof:name":"Pelican Press Inc",
    "wof:placetype":"venue"
},
  "geometry": {"coordinates":[-122.37621799999999,47.667159],"type":"Point"}
}