{
  "type": "Feature",
  "properties": {
    "addr:full":"157 Haight Rd Chehalis WA 98532",
    "addr:housenumber":"157",
    "addr:postcode":"98532",
    "addr:street":"Haight Rd",
    "iso:country":"US",
    "sg:address":"157 Haight Rd",
    "sg:city":"Chehalis",
    "sg:classifiers":[
        {
            "category":"Wholesale",
            "subcategory":"Office Equipment",
            "type":"Manufacturing & Wholesale Goods"
        }
    ],
    "sg:phone":"+1 360 748 0550",
    "sg:postcode":"98532",
    "sg:province":"WA",
    "wof:name":"Tax Shoppe Inc",
    "wof:placetype":"venue"
},
  "geometry": {"coordinates":[-122.953445,46.597988],"type":"Point"}
}