{
  "type": "Feature",
  "properties": {
    "addr:full":"1601 1st Ave Seattle WA 98101",
    "addr:housenumber":"1601",
    "addr:postcode":"98101",
    "addr:street":"1St Ave",
    "iso:country":"US",
    "sg:address":"1601 1st Ave",
    "sg:city":"Seattle",
    "sg:classifiers":[
        {
            "category":"Shopping",
            "subcategory":"Jewelry",
            "type":"Retail Goods"
        }
    ],
    "sg:phone":"+1 206 441 7711",
    "sg:postcode":"98101",
    "sg:province":"WA",
    "sg:tags":[
        "watch"
    ],
    "sg:website":"isadoras.com/",
    "wof:name":"Isadora's Antique Jewlery",
    "wof:placetype":"venue"
},
  "geometry": {"coordinates":[-122.340948,47.609808],"type":"Point"}
}