{
  "type": "Feature",
  "properties": {
    "addr:full":"3211 Ruston Way Tacoma WA 98402",
    "addr:housenumber":"3211",
    "addr:postcode":"98402",
    "addr:street":"Ruston Way",
    "iso:country":"US",
    "sg:address":"3211 Ruston Way",
    "sg:city":"Tacoma",
    "sg:classifiers":[
        {
            "category":"Restaurant",
            "type":"Food & Drink"
        }
    ],
    "sg:menulink":"http://www.allmenus.com/wa/tacoma/106176-katie-downs-waterfront-restaurant/menu/",
    "sg:phone":"+1 253 756 0771",
    "sg:postcode":"98402",
    "sg:province":"WA",
    "sg:tags":[
        "american"
    ],
    "wof:name":"Katie Downs Waterfront Restaurant",
    "wof:placetype":"venue"
},
  "geometry": {"coordinates":[-122.47802799999999,47.280719],"type":"Point"}
}