{
  "type": "Feature",
  "properties": {
    "addr:full":"1082 Curtis St Burlington WA 98233",
    "addr:housenumber":"1082",
    "addr:postcode":"98233",
    "addr:street":"Curtis St",
    "iso:country":"US",
    "sg:address":"1082 Curtis St",
    "sg:city":"Burlington",
    "sg:classifiers":[
        {
            "category":"Building & Trades",
            "subcategory":"Cleaning & Sanitation",
            "type":"Services"
        }
    ],
    "sg:phone":"+1 360 755 5259",
    "sg:postcode":"98233",
    "sg:province":"WA",
    "sg:tags":[
        "maintenance"
    ],
    "wof:name":"Clean Way Janitorial",
    "wof:placetype":"venue"
},
  "geometry": {"coordinates":[-122.32069,48.467493],"type":"Point"}
}