{
  "type": "Feature",
  "properties": {
    "addr:full":"11032 SE 183rd Pl Renton WA 98055",
    "addr:housenumber":"11032",
    "addr:postcode":"98055",
    "addr:street":"Se 183Rd Pl",
    "iso:country":"US",
    "sg:address":"11032 SE 183rd Pl",
    "sg:city":"Renton",
    "sg:classifiers":[
        {
            "category":"Shopping",
            "subcategory":"Gifts & Souvenirs",
            "type":"Retail Goods"
        }
    ],
    "sg:phone":"+1 425 255 0119",
    "sg:postcode":"98055",
    "sg:province":"WA",
    "wof:name":"Gems From Heart",
    "wof:placetype":"venue"
},
  "geometry": {"coordinates":[-122.19339600000001,47.438967],"type":"Point"}
}