{
  "type": "Feature",
  "properties": {
    "addr:full":"210 NE 4th Ave Camas WA 98607",
    "addr:housenumber":"210",
    "addr:postcode":"98607",
    "addr:street":"Ne 4Th Ave",
    "iso:country":"US",
    "sg:address":"210 NE 4th Ave",
    "sg:city":"Camas",
    "sg:classifiers":[
        {
            "category":"Personal",
            "subcategory":"Barber",
            "type":"Services"
        }
    ],
    "sg:phone":"+1 360 834 3238",
    "sg:postcode":"98607",
    "sg:province":"WA",
    "sg:tags":[
        "shop"
    ],
    "wof:name":"Jack's Barber Shop",
    "wof:placetype":"venue"
},
  "geometry": {"coordinates":[-122.404999,45.584999],"type":"Point"}
}