{
  "type": "Feature",
  "properties": {
    "addr:full":"120 W Dayton St Edmonds WA 98020",
    "addr:housenumber":"120",
    "addr:postcode":"98020",
    "addr:street":"W Dayton",
    "iso:country":"US",
    "sg:address":"120 W Dayton St",
    "sg:city":"Edmonds",
    "sg:classifiers":[
        {
            "category":"Travel",
            "subcategory":"Travel Agent",
            "type":"Entertainment"
        }
    ],
    "sg:phone":"+1 206 812 8731",
    "sg:postcode":"98020",
    "sg:province":"WA",
    "sg:tags":[
        "agency"
    ],
    "wof:name":"Global Express Travel & Cruise",
    "wof:placetype":"venue"
},
  "geometry": {"coordinates":[-122.38445400000001,47.809671],"type":"Point"}
}