{
  "type": "Feature",
  "properties": {
    "addr:full":"2402 W Valley Hwy N Auburn WA 98001",
    "addr:housenumber":"2402",
    "addr:postcode":"98001",
    "addr:street":"W Valley Hwy N",
    "iso:country":"US",
    "sg:address":"2402 W Valley Hwy N",
    "sg:city":"Auburn",
    "sg:classifiers":[
        {
            "category":"Wholesale",
            "subcategory":"Auto Parts",
            "type":"Manufacturing & Wholesale Goods"
        }
    ],
    "sg:phone":"+1 253 833 0100",
    "sg:postcode":"98001",
    "sg:province":"WA",
    "sg:website":"www.compspecialties.com",
    "wof:name":"Competition Specialties Inc",
    "wof:placetype":"venue"
},
  "geometry": {"coordinates":[-122.249735,47.328928],"type":"Point"}
}