{
  "type": "Feature",
  "properties": {
    "addr:full":"1425 4th Avenue Suite 308 Seattle WA 98101",
    "addr:housenumber":"1425",
    "addr:postcode":"98101",
    "addr:street":"4Th Avenue Suite 308",
    "iso:country":"US",
    "sg:address":"1425 4th Avenue Suite 308",
    "sg:city":"Seattle",
    "sg:classifiers":[
        {
            "category":"Real Estate",
            "subcategory":"Architect",
            "type":"Services"
        }
    ],
    "sg:phone":"+1 206 621 1298",
    "sg:postcode":"98101",
    "sg:province":"WA",
    "wof:name":"Pehrson Clint Architects",
    "wof:placetype":"venue"
},
  "geometry": {"coordinates":[-122.33596799999999,47.609502],"type":"Point"}
}