{
  "type": "Feature",
  "properties": {
    "iso:country":"US",
    "sg:address":"118 Hillcrest Dr",
    "sg:city":"Elma",
    "sg:classifiers":[
        {
            "category":"Restaurant",
            "type":"Food & Drink"
        }
    ],
    "sg:phone":"+1 360 482 5919",
    "sg:postcode":"98541",
    "sg:province":"WA",
    "sg:tags":[
        "eating"
    ],
    "wof:name":"Bettys Kitchen",
    "wof:placetype":"venue"
},
  "geometry": {"coordinates":[-123.412797,47.015476],"type":"Point"}
}