{
  "type": "Feature",
  "properties": {
    "addr:full":"1738 NW Market St Seattle WA 98107",
    "addr:housenumber":"1738",
    "addr:postcode":"98107",
    "addr:street":"Nw Market St",
    "iso:country":"US",
    "sg:address":"1738 NW Market St",
    "sg:city":"Seattle",
    "sg:classifiers":[
        {
            "category":"Insurance",
            "subcategory":"Insurance Agent",
            "type":"Services"
        }
    ],
    "sg:phone":"+1 206 782 7881",
    "sg:postcode":"98107",
    "sg:province":"WA",
    "wof:name":"Eco Partnership",
    "wof:placetype":"venue"
},
  "geometry": {"coordinates":[-122.379971,47.668745],"type":"Point"}
}