{
  "type": "Feature",
  "properties": {
    "addr:full":"2106 E 11th St Bremerton WA 98310",
    "addr:housenumber":"2106",
    "addr:postcode":"98310",
    "addr:street":"E 11Th St",
    "iso:country":"US",
    "sg:address":"2106 E 11th St",
    "sg:city":"Bremerton",
    "sg:classifiers":[
        {
            "category":"Shopping",
            "subcategory":"Used Merchandise",
            "type":"Retail Goods"
        }
    ],
    "sg:phone":"+1 360 405 1700",
    "sg:postcode":"98310",
    "sg:province":"WA",
    "sg:tags":[
        "antique"
    ],
    "wof:name":"Manette Antiques Art",
    "wof:placetype":"venue"
},
  "geometry": {"coordinates":[-122.614868,47.570347],"type":"Point"}
}