{
  "type": "Feature",
  "properties": {
    "iso:country":"US",
    "sg:address":"1973 Cook Ln",
    "sg:city":"Bremerton",
    "sg:classifiers":[
        {
            "category":"Building & Trades",
            "subcategory":"Construction",
            "type":"Services"
        }
    ],
    "sg:phone":"+1 360 479 7962",
    "sg:postcode":"98312",
    "sg:province":"WA",
    "sg:tags":[
        "contractor"
    ],
    "wof:name":"Broussard Home Svc",
    "wof:placetype":"venue"
},
  "geometry": {"coordinates":[-122.69978,47.566826],"type":"Point"}
}