{
  "type": "Feature",
  "properties": {
    "addr:full":"4151 SW Rose St Seattle WA 98136",
    "addr:housenumber":"4151",
    "addr:postcode":"98136",
    "addr:street":"Sw Rose St",
    "iso:country":"US",
    "sg:address":"4151 SW Rose St",
    "sg:city":"Seattle",
    "sg:classifiers":[
        {
            "category":"Insurance",
            "subcategory":"Insurance Agent",
            "type":"Services"
        }
    ],
    "sg:phone":"+1 206 937 0190",
    "sg:postcode":"98136",
    "sg:province":"WA",
    "wof:name":"Hill David C Insurance",
    "wof:placetype":"venue"
},
  "geometry": {"coordinates":[-122.386932,47.529193],"type":"Point"}
}