{
  "type": "Feature",
  "properties": {
    "addr:full":"11012 38th Dr SE Everett WA 98208",
    "addr:housenumber":"11012",
    "addr:postcode":"98208",
    "addr:street":"38Th Dr Se",
    "iso:country":"US",
    "sg:address":"11012 38th Dr SE",
    "sg:city":"Everett",
    "sg:classifiers":[
        {
            "category":"Professional",
            "subcategory":"Engineering",
            "type":"Services"
        }
    ],
    "sg:phone":"+1 425 337 5902",
    "sg:postcode":"98208",
    "sg:province":"WA",
    "sg:tags":[
        "engineer"
    ],
    "wof:name":"Virtual Engineering Assoc",
    "wof:placetype":"venue"
},
  "geometry": {"coordinates":[-122.181141,47.898135],"type":"Point"}
}