{
  "type": "Feature",
  "properties": {
    "addr:full":"23445 State Rte 231 N Edwall WA 99008",
    "addr:housenumber":"23445",
    "addr:postcode":"99008",
    "addr:street":"State Rte 231 N Edwall",
    "iso:country":"US",
    "sg:address":"23445 State Rte 231 N",
    "sg:city":"Edwall",
    "sg:phone":"+1 509 796 3237",
    "sg:postcode":"99008",
    "sg:province":"WA",
    "sg:tags":[
        "farm",
        "grain",
        "cash"
    ],
    "wof:name":"Eugene & Joanne Krupke",
    "wof:placetype":"venue"
},
  "geometry": {"coordinates":[-117.940697,47.602384],"type":"Point"}
}