{
  "type": "Feature",
  "properties": {
    "addr:full":"9612 40th Ave SW Lakewood WA 98499",
    "addr:housenumber":"9612",
    "addr:postcode":"98499",
    "addr:street":"40Th Ave Sw",
    "iso:country":"US",
    "sg:address":"9612 40th Ave SW",
    "sg:city":"Lakewood",
    "sg:classifiers":[
        {
            "category":"Home & Garden",
            "subcategory":"Building Materials",
            "type":"Retail Goods"
        },
        {
            "category":"Building & Trades",
            "subcategory":"Construction",
            "type":"Services"
        }
    ],
    "sg:phone":"+1 253 588 2337",
    "sg:postcode":"98499",
    "sg:province":"WA",
    "sg:tags":[
        "glass",
        "window",
        "contractor",
        "plate"
    ],
    "wof:name":"Viking Glass Company",
    "wof:placetype":"venue"
},
  "geometry": {"coordinates":[-122.490852,47.167315],"type":"Point"}
}