{
  "type": "Feature",
  "properties": {
    "addr:full":"1270 Naff Rd Colville WA 99114",
    "addr:housenumber":"1270",
    "addr:postcode":"99114",
    "addr:street":"Naff Rd",
    "iso:country":"US",
    "sg:address":"1270 Naff Rd",
    "sg:city":"Colville",
    "sg:classifiers":[
        {
            "category":"Professional",
            "type":"Services"
        }
    ],
    "sg:phone":"+1 509 684 4444",
    "sg:postcode":"99114",
    "sg:province":"WA",
    "wof:name":"Lemco Ent",
    "wof:placetype":"venue"
},
  "geometry": {"coordinates":[-117.983243,48.408378],"type":"Point"}
}