{
  "type": "Feature",
  "properties": {
    "addr:full":"7110 NE 219th St Battle Ground WA 98604",
    "addr:housenumber":"7110",
    "addr:postcode":"98604",
    "addr:street":"Ne 219Th St",
    "iso:country":"US",
    "sg:address":"7110 NE 219th St",
    "sg:city":"Battle Ground",
    "sg:classifiers":[
        {
            "category":"Food & Beverages",
            "subcategory":"Groceries & Convenience Stores",
            "type":"Retail Goods"
        }
    ],
    "sg:phone":"+1 360 687 4455",
    "sg:postcode":"98604",
    "sg:province":"WA",
    "sg:tags":[
        "station",
        "gas"
    ],
    "wof:name":"Wild Willies Dollars Corner",
    "wof:placetype":"venue"
},
  "geometry": {"coordinates":[-122.60199900000001,45.780188],"type":"Point"}
}