{
  "type": "Feature",
  "properties": {
    "iso:country":"US",
    "sg:address":"12376 Reservation Rd",
    "sg:city":"Anacortes",
    "sg:classifiers":[
        {
            "category":"Autos & Motor Vehicles",
            "subcategory":"Automobile Sales",
            "type":"Retail Goods"
        }
    ],
    "sg:phone":"+1 360 588 8119",
    "sg:postcode":"98221",
    "sg:province":"WA",
    "sg:tags":[
        "used"
    ],
    "wof:name":"Orion Towing",
    "wof:placetype":"venue"
},
  "geometry": {"coordinates":[-122.543841,48.463339],"type":"Point"}
}