{
  "type": "Feature",
  "properties": {
    "addr:full":"2519 NE 159th St Ridgefield WA 98642",
    "addr:housenumber":"2519",
    "addr:postcode":"98642",
    "addr:street":"Ne 159Th St",
    "iso:country":"US",
    "sg:address":"2519 NE 159th St",
    "sg:city":"Ridgefield",
    "sg:classifiers":[
        {
            "category":"Retail",
            "subcategory":"Portrait Studio",
            "type":"Services"
        }
    ],
    "sg:phone":"+1 360 573 6000",
    "sg:postcode":"98642",
    "sg:province":"WA",
    "sg:tags":[
        "photo"
    ],
    "wof:name":"Natural Highlights Photography",
    "wof:placetype":"venue"
},
  "geometry": {"coordinates":[-122.641183,45.736238],"type":"Point"}
}