{
  "type": "Feature",
  "properties": {
    "addr:full":"711 N 35th St #B Seattle WA 98103",
    "addr:housenumber":"711",
    "addr:postcode":"98103",
    "addr:street":"N 35Th St # B",
    "iso:country":"US",
    "sg:address":"711 N 35th St #B",
    "sg:city":"Seattle",
    "sg:classifiers":[
        {
            "category":"Shopping",
            "subcategory":"Shoes",
            "type":"Retail Goods"
        }
    ],
    "sg:phone":"+1 206 547 2071",
    "sg:postcode":"98103",
    "sg:province":"WA",
    "sg:tags":[
        "store"
    ],
    "sg:website":"www.lolapopseattle.com",
    "wof:name":"Lola Pop",
    "wof:placetype":"venue"
},
  "geometry": {"coordinates":[-122.349667,47.650494],"type":"Point"}
}