{
  "type": "Feature",
  "properties": {
    "addr:full":"16000 Bothell Everett Hwy Bothell WA 98012",
    "addr:housenumber":"16000",
    "addr:postcode":"98012",
    "addr:street":"Bothell Everett Hwy",
    "iso:country":"US",
    "sg:address":"16000 Bothell Everett Hwy",
    "sg:city":"Bothell",
    "sg:classifiers":[
        {
            "category":"Social Services",
            "type":"Services"
        }
    ],
    "sg:phone":"+1 425 745 0911",
    "sg:postcode":"98012",
    "sg:province":"WA",
    "wof:name":"McCashen Karen MA",
    "wof:placetype":"venue"
},
  "geometry": {"coordinates":[-122.218339,47.853062],"type":"Point"}
}