{
  "type": "Feature",
  "properties": {
    "addr:full":"14712 Bothell Way NE Lake Forest Park WA 98155",
    "addr:housenumber":"14712",
    "addr:postcode":"98155",
    "addr:street":"Bothell Way Ne;Park",
    "iso:country":"US",
    "sg:address":"14712 Bothell Way NE",
    "sg:city":"Lake Forest Park",
    "sg:classifiers":[
        {
            "category":"Manufacturing",
            "subcategory":"Printing",
            "type":"Manufacturing & Wholesale Goods"
        }
    ],
    "sg:phone":"+1 206 417 2363",
    "sg:postcode":"98155",
    "sg:province":"WA",
    "sg:tags":[
        "publisher"
    ],
    "wof:name":"American System Publications",
    "wof:placetype":"venue"
},
  "geometry": {"coordinates":[-122.292131,47.73623],"type":"Point"}
}