{
  "type": "Feature",
  "properties": {
    "addr:full":"14170 NE Woodinville Duvall Rd Woodinville WA 98072",
    "addr:housenumber":"14170",
    "addr:postcode":"98072",
    "addr:street":"Ne Woodinville Duvall Rd",
    "iso:country":"US",
    "sg:address":"14170 NE Woodinville Duvall Rd",
    "sg:city":"Woodinville",
    "sg:classifiers":[
        {
            "category":"Coffee & Tea",
            "type":"Food & Drink"
        },
        {
            "category":"Restaurant",
            "type":"Food & Drink"
        }
    ],
    "sg:phone":"+1 425 489 1403",
    "sg:postcode":"98072",
    "sg:province":"WA",
    "sg:tags":[
        "espresso"
    ],
    "sg:website":"http://www.cafejuanita.com",
    "wof:name":"Woodinville Cafe",
    "wof:placetype":"venue"
},
  "geometry": {"coordinates":[-122.150507,47.754634],"type":"Point"}
}