{
  "type": "Feature",
  "properties": {
    "addr:full":"19329 89th Ave NE Bothell WA 98011",
    "addr:housenumber":"19329",
    "addr:postcode":"98011",
    "addr:street":"89Th Ave Ne",
    "iso:country":"US",
    "sg:address":"19329 89th Ave NE",
    "sg:city":"Bothell",
    "sg:classifiers":[
        {
            "category":"Professional",
            "subcategory":"Art Services",
            "type":"Services"
        }
    ],
    "sg:phone":"+1 425 482 9365",
    "sg:postcode":"98011",
    "sg:province":"WA",
    "sg:tags":[
        "organization",
        "photography",
        "commercial",
        "membership"
    ],
    "wof:name":"Gods World Photography",
    "wof:placetype":"venue"
},
  "geometry": {"coordinates":[-122.22229400000001,47.768135],"type":"Point"}
}