{
  "type": "Feature",
  "properties": {
    "addr:full":"2517 5th Avenue Seattle WA 98121",
    "addr:housenumber":"2517",
    "addr:postcode":"98121",
    "addr:street":"5Th Avenue",
    "iso:country":"US",
    "sg:address":"2517 5th Avenue",
    "sg:city":"Seattle",
    "sg:classifiers":[
        {
            "category":"Health Services",
            "subcategory":"Clinic",
            "type":"Services"
        },
        {
            "category":"Sports & Exercise",
            "subcategory":"Gym",
            "type":"Entertainment"
        }
    ],
    "sg:phone":"+1 206 728 4243",
    "sg:postcode":"98121",
    "sg:province":"WA",
    "sg:tags":[
        "trainer",
        "counseling",
        "mental"
    ],
    "sg:website":"coachstacey.net",
    "wof:name":"COACH Consulting Services",
    "wof:placetype":"venue"
},
  "geometry": {"coordinates":[-122.345545,47.617468],"type":"Point"}
}