{
  "type": "Feature",
  "properties": {
    "addr:full":"9116 NE 95th St Vancouver WA 98662",
    "addr:housenumber":"9116",
    "addr:postcode":"98662",
    "addr:street":"Ne 95Th St",
    "iso:country":"US",
    "sg:address":"9116 NE 95th St",
    "sg:city":"Vancouver",
    "sg:classifiers":[
        {
            "category":"Building & Trades",
            "subcategory":"Construction",
            "type":"Services"
        }
    ],
    "sg:phone":"+1 360 892 7708",
    "sg:postcode":"98662",
    "sg:province":"WA",
    "sg:tags":[
        "contractor"
    ],
    "wof:name":"A & P Siding LLC",
    "wof:placetype":"venue"
},
  "geometry": {"coordinates":[-122.577395,45.690439],"type":"Point"}
}