{
  "type": "Feature",
  "properties": {
    "addr:full":"3805 196th St SW Lynnwood WA 98036",
    "addr:housenumber":"3805",
    "addr:postcode":"98036",
    "addr:street":"196Th St Sw",
    "iso:country":"US",
    "sg:address":"3805 196th St SW",
    "sg:city":"Lynnwood",
    "sg:phone":"+1 425 771 4630",
    "sg:postcode":"98036",
    "sg:province":"WA",
    "wof:name":"Taco Guayamos Y Mas",
    "wof:placetype":"venue"
},
  "geometry": {"coordinates":[-122.284414,47.82093],"type":"Point"}
}