{
  "type": "Feature",
  "properties": {
    "addr:full":"2100 N National Ave Chehalis WA 98532",
    "addr:housenumber":"2100",
    "addr:postcode":"98532",
    "addr:street":"N National Ave",
    "iso:country":"US",
    "sg:address":"2100 N National Ave",
    "sg:city":"Chehalis",
    "sg:classifiers":[
        {
            "category":"Cafe",
            "type":"Food & Drink"
        }
    ],
    "sg:menulink":"http://www.allmenus.com/wa/centralia-chehalis/69060-kong-cafe/menu/",
    "sg:phone":"+1 360 999 9999",
    "sg:postcode":"98532",
    "sg:province":"WA",
    "sg:tags":[
        "american",
        "hot",
        "dog"
    ],
    "wof:name":"Kong Cafe",
    "wof:placetype":"venue"
},
  "geometry": {"coordinates":[-122.963272,46.67972],"type":"Point"}
}