{
  "type": "Feature",
  "properties": {
    "addr:full":"17532 1st Ave NW Shoreline WA 98177",
    "addr:housenumber":"17532",
    "addr:postcode":"98177",
    "addr:street":"1St Ave Nw",
    "iso:country":"US",
    "sg:address":"17532 1st Ave NW",
    "sg:city":"Shoreline",
    "sg:classifiers":[
        {
            "category":"Banks & Credit Unions",
            "subcategory":"Financial Services",
            "type":"Services"
        }
    ],
    "sg:phone":"+1 206 542 8562",
    "sg:postcode":"98177",
    "sg:province":"WA",
    "sg:tags":[
        "commercial",
        "investor",
        "real estate"
    ],
    "wof:name":"Mhb Investments",
    "wof:placetype":"venue"
},
  "geometry": {"coordinates":[-122.358479,47.75664],"type":"Point"}
}