{
  "type": "Feature",
  "properties": {
    "addr:full":"13603 100th Avenue NE Kirkland WA 98034",
    "addr:housenumber":"13603",
    "addr:postcode":"98034",
    "addr:street":"100Th Avenue Ne",
    "iso:country":"US",
    "sg:address":"13603 100th Avenue NE",
    "sg:city":"Kirkland",
    "sg:classifiers":[
        {
            "category":"Retail",
            "subcategory":"Veterinary Services",
            "type":"Services"
        }
    ],
    "sg:phone":"+1 888 821 6165",
    "sg:postcode":"98034",
    "sg:province":"WA",
    "sg:tags":[
        "veterinarian"
    ],
    "sg:website":"www.eaeamc.com/index.asp",
    "wof:name":"Eastside Avian And Exotic Medical Center",
    "wof:placetype":"venue"
},
  "geometry": {"coordinates":[-122.20773199999999,47.722246],"type":"Point"}
}