{
  "type": "Feature",
  "properties": {
    "addr:full":"3115 S 19th St Tacoma WA 98405",
    "addr:housenumber":"3115",
    "addr:postcode":"98405",
    "addr:street":"S 19Th St",
    "iso:country":"US",
    "sg:address":"3115 S 19th St",
    "sg:city":"Tacoma",
    "sg:classifiers":[
        {
            "category":"Personal",
            "subcategory":"Beauty Salon",
            "type":"Services"
        }
    ],
    "sg:phone":"+1 253 272 3152",
    "sg:postcode":"98405",
    "sg:province":"WA",
    "sg:tags":[
        "shop"
    ],
    "wof:name":"Hairs To You",
    "wof:placetype":"venue"
},
  "geometry": {"coordinates":[-122.479038,47.242847],"type":"Point"}
}