{
  "type": "Feature",
  "properties": {
    "iso:country":"US",
    "sg:address":"19509 Bothell Way NE",
    "sg:city":"Bothell",
    "sg:classifiers":[
        {
            "category":"Retail",
            "subcategory":"Veterinary Services",
            "type":"Services"
        }
    ],
    "sg:phone":"+1 425 481 9400",
    "sg:postcode":"98011",
    "sg:province":"WA",
    "wof:name":"Jon A Bruhn Dvm",
    "wof:placetype":"venue"
},
  "geometry": {"coordinates":[-122.211119,47.76854],"type":"Point"}
}