{
  "type": "Feature",
  "properties": {
    "addr:full":"4200 Chilberg Ave SW Seattle WA 98116",
    "addr:housenumber":"4200",
    "addr:postcode":"98116",
    "addr:street":"Chilberg Ave Sw",
    "iso:country":"US",
    "sg:address":"4200 Chilberg Ave SW",
    "sg:city":"Seattle",
    "sg:classifiers":[
        {
            "category":"Real Estate",
            "subcategory":"Architect",
            "type":"Services"
        }
    ],
    "sg:phone":"+1 206 932 4470",
    "sg:postcode":"98116",
    "sg:province":"WA",
    "sg:tags":[
        "architectural"
    ],
    "wof:name":"Janice Nyman Architects",
    "wof:placetype":"venue"
},
  "geometry": {"coordinates":[-122.406757,47.565309],"type":"Point"}
}