{
  "type": "Feature",
  "properties": {
    "addr:full":"13041 34th Ave S Seattle WA 98168",
    "addr:housenumber":"13041",
    "addr:postcode":"98168",
    "addr:street":"34Th Ave S",
    "iso:country":"US",
    "sg:address":"13041 34th Ave S",
    "sg:city":"Seattle",
    "sg:classifiers":[
        {
            "category":"Professional",
            "subcategory":"Secretarial Services",
            "type":"Services"
        }
    ],
    "sg:phone":"+1 206 243 9948",
    "sg:postcode":"98168",
    "sg:province":"WA",
    "sg:tags":[
        "reporting"
    ],
    "wof:name":"Kit S Transcription Service",
    "wof:placetype":"venue"
},
  "geometry": {"coordinates":[-122.289198,47.485048],"type":"Point"}
}