{
  "type": "Feature",
  "properties": {
    "addr:full":"2227 Washington St Port Townsend WA 98368",
    "addr:housenumber":"2227",
    "addr:postcode":"98368",
    "addr:street":"Washington St",
    "iso:country":"US",
    "sg:address":"2227 Washington St",
    "sg:city":"Port Townsend",
    "sg:classifiers":[
        {
            "category":"Retail",
            "subcategory":"Auto Repair",
            "type":"Services"
        }
    ],
    "sg:phone":"+1 360 385 3780",
    "sg:postcode":"98368",
    "sg:province":"WA",
    "sg:tags":[
        "repairing",
        "automobile"
    ],
    "wof:name":"Townsend Electric",
    "wof:placetype":"venue"
},
  "geometry": {"coordinates":[-122.770825,48.109259],"type":"Point"}
}