{
  "type": "Feature",
  "properties": {
    "addr:full":"16695 Agate Point Rd NE Bainbridge Island WA 98110",
    "addr:housenumber":"16695",
    "addr:postcode":"98110",
    "addr:street":"Agate Point Rd Ne",
    "iso:country":"US",
    "sg:address":"16695 Agate Point Rd NE",
    "sg:city":"Bainbridge Island",
    "sg:classifiers":[
        {
            "category":"Social Services",
            "subcategory":"Child Care",
            "type":"Services"
        }
    ],
    "sg:phone":"+1 206 842 2223",
    "sg:postcode":"98110",
    "sg:province":"WA",
    "sg:tags":[
        "day"
    ],
    "wof:name":"Life Learning Unlimited",
    "wof:placetype":"venue"
},
  "geometry": {"coordinates":[-122.547882,47.712816],"type":"Point"}
}