{
  "type": "Feature",
  "properties": {
    "addr:full":"24823 Pacific Hwy S Kent WA 98032",
    "addr:housenumber":"24823",
    "addr:postcode":"98032",
    "addr:street":"Pacific Hwy S",
    "iso:country":"US",
    "sg:address":"24823 Pacific Hwy S",
    "sg:city":"Kent",
    "sg:classifiers":[
        {
            "category":"Food & Beverages",
            "subcategory":"Groceries & Convenience Stores",
            "type":"Retail Goods"
        }
    ],
    "sg:phone":"+1 253 839 0252",
    "sg:postcode":"98032",
    "sg:province":"WA",
    "wof:name":"Bombay Bazarre",
    "wof:placetype":"venue"
},
  "geometry": {"coordinates":[-122.29943299999999,47.37693],"type":"Point"}
}