{
  "type": "Feature",
  "properties": {
    "addr:full":"185 Kangas Rd Toledo WA 98591",
    "addr:housenumber":"185",
    "addr:postcode":"98591",
    "addr:street":"Kangas Rd",
    "iso:country":"US",
    "sg:address":"185 Kangas Rd",
    "sg:city":"Toledo",
    "sg:classifiers":[
        {
            "category":"Retail",
            "subcategory":"Auto Repair",
            "type":"Services"
        }
    ],
    "sg:phone":"+1 360 864 2798",
    "sg:postcode":"98591",
    "sg:province":"WA",
    "sg:tags":[
        "body",
        "automobile",
        "buses-distributors",
        "painting",
        "manufacturer"
    ],
    "wof:name":"Howard's Body Shop",
    "wof:placetype":"venue"
},
  "geometry": {"coordinates":[-122.81396599999999,46.433032],"type":"Point"}
}