{
  "type": "Feature",
  "properties": {
    "addr:full":"446 Spring Ln Sedro Woolley WA 98284",
    "addr:housenumber":"446",
    "addr:postcode":"98284",
    "addr:street":"Spring Ln",
    "iso:country":"US",
    "sg:address":"446 Spring Ln",
    "sg:city":"Sedro Woolley",
    "sg:classifiers":[
        {
            "category":"Freight",
            "type":"Transportation"
        }
    ],
    "sg:phone":"+1 360 421 0528",
    "sg:postcode":"98284",
    "sg:province":"WA",
    "sg:tags":[
        "passenger",
        "local"
    ],
    "wof:name":"Exec Services",
    "wof:placetype":"venue"
},
  "geometry": {"coordinates":[-122.256151,48.50764],"type":"Point"}
}