{
  "type": "Feature",
  "properties": {
    "addr:full":"2700 NE Univ Village Mall Seattle WA 98105",
    "addr:housenumber":"2700",
    "addr:postcode":"98105",
    "addr:street":"Ne Univ Village Mall",
    "iso:country":"US",
    "sg:address":"2700 NE Univ Village Mall",
    "sg:city":"Seattle",
    "sg:classifiers":[
        {
            "category":"Shopping",
            "subcategory":"Pharmacy",
            "type":"Retail Goods"
        }
    ],
    "sg:phone":"+1 206 525 0601",
    "sg:postcode":"98105",
    "sg:province":"WA",
    "sg:tags":[
        "drugstore"
    ],
    "sg:website":"www.bartelldrugs.com",
    "wof:name":"Bartell Drugs",
    "wof:placetype":"venue"
},
  "geometry": {"coordinates":[-122.305424,47.664215],"type":"Point"}
}