{
  "type": "Feature",
  "properties": {
    "addr:full":"13421 NE 20th St Ste A Bellevue WA 98005",
    "addr:housenumber":"13421",
    "addr:postcode":"98005",
    "addr:street":"Ne 20Th St Ste A",
    "iso:country":"US",
    "sg:address":"13421 NE 20th St Ste A",
    "sg:city":"Bellevue",
    "sg:classifiers":[
        {
            "category":"Retail",
            "subcategory":"Auto Repair",
            "type":"Services"
        }
    ],
    "sg:phone":"+1 425 746 4787",
    "sg:postcode":"98005",
    "sg:province":"WA",
    "wof:name":"Harvey's Auto Service",
    "wof:placetype":"venue"
},
  "geometry": {"coordinates":[-122.160004,47.627998],"type":"Point"}
}