{
  "type": "Feature",
  "properties": {
    "iso:country":"US",
    "sg:address":"10001 114th Ave NE",
    "sg:city":"Kirkland",
    "sg:classifiers":[
        {
            "category":"Professional",
            "subcategory":"Business Services",
            "type":"Services"
        }
    ],
    "sg:phone":"+1 425 827 8374",
    "sg:postcode":"98033",
    "sg:province":"WA",
    "sg:tags":[
        "consulting",
        "management"
    ],
    "wof:name":"Stellar Meetings & Events",
    "wof:placetype":"venue"
},
  "geometry": {"coordinates":[-122.18859,47.690037],"type":"Point"}
}