{
  "type": "Feature",
  "properties": {
    "addr:full":"17563 Ervine Ln Mount Vernon WA 98274",
    "addr:postcode":"17563;98274",
    "addr:street":"Ervine Ln",
    "iso:country":"US",
    "sg:address":"17563 Ervine Ln",
    "sg:city":"Mount Vernon",
    "sg:classifiers":[
        {
            "category":"Manufacturing",
            "subcategory":"Wood Products",
            "type":"Manufacturing & Wholesale Goods"
        }
    ],
    "sg:phone":"+1 360 424 1757",
    "sg:postcode":"98274",
    "sg:province":"WA",
    "sg:tags":[
        "mfg"
    ],
    "wof:name":"Skraps",
    "wof:placetype":"venue"
},
  "geometry": {"coordinates":[-122.278023,48.392402],"type":"Point"}
}