{
  "type": "Feature",
  "properties": {
    "iso:country":"US",
    "sg:address":"12505 SE 69th Way",
    "sg:city":"Renton",
    "sg:classifiers":[
        {
            "category":"Building & Trades",
            "subcategory":"Construction",
            "type":"Services"
        }
    ],
    "sg:phone":"+1 425 235 4392",
    "sg:postcode":"98056",
    "sg:province":"WA",
    "sg:tags":[
        "contractor"
    ],
    "wof:name":"Stormy Mountain Tile Co",
    "wof:placetype":"venue"
},
  "geometry": {"coordinates":[-122.170879,47.540688],"type":"Point"}
}