{
  "type": "Feature",
  "properties": {
    "addr:full":"739 N 4th Ave Walla Walla WA 99362",
    "addr:housenumber":"739",
    "addr:postcode":"99362",
    "addr:street":"N 4Th Ave",
    "iso:country":"US",
    "sg:address":"739 N 4th Ave",
    "sg:city":"Walla Walla",
    "sg:classifiers":[
        {
            "category":"Health Services",
            "subcategory":"Nursing And Care Facility",
            "type":"Services"
        }
    ],
    "sg:phone":"+1 509 525 3777",
    "sg:postcode":"99362",
    "sg:province":"WA",
    "wof:name":"Twiced Loved Care Center",
    "wof:placetype":"venue"
},
  "geometry": {"coordinates":[-118.346059,46.073291],"type":"Point"}
}