{
  "type": "Feature",
  "properties": {
    "addr:full":"705 SE Victory Ave Vancouver WA 98661",
    "addr:housenumber":"705",
    "addr:postcode":"98661",
    "addr:street":"Se Victory Ave",
    "iso:country":"US",
    "sg:address":"705 SE Victory Ave",
    "sg:city":"Vancouver",
    "sg:classifiers":[
        {
            "category":"Manufacturing",
            "subcategory":"Building Materials",
            "type":"Manufacturing & Wholesale Goods"
        }
    ],
    "sg:phone":"+1 360 693 9160",
    "sg:postcode":"98661",
    "sg:province":"WA",
    "sg:tags":[
        "corrugated",
        "mfg"
    ],
    "wof:name":"Sunrise Washington",
    "wof:placetype":"venue"
},
  "geometry": {"coordinates":[-122.636144,45.615732],"type":"Point"}
}