{
  "type": "Feature",
  "properties": {
    "iso:country":"US",
    "sg:address":"2904 Main St",
    "sg:city":"Vancouver",
    "sg:classifiers":[
        {
            "category":"Health Services",
            "subcategory":"Health Practitioner",
            "type":"Services"
        }
    ],
    "sg:phone":"+1 360 263 4082",
    "sg:postcode":"98663",
    "sg:province":"WA",
    "wof:name":"Lane Vandersluis Inc",
    "wof:placetype":"venue"
},
  "geometry": {"coordinates":[-122.670002,45.643173],"type":"Point"}
}