{
  "type": "Feature",
  "properties": {
    "addr:full":"14105 11th Dr SE Bothell WA 98012",
    "addr:housenumber":"14105",
    "addr:postcode":"98012",
    "addr:street":"11Th Dr Se",
    "iso:country":"US",
    "sg:address":"14105 11th Dr SE",
    "sg:city":"Bothell",
    "sg:classifiers":[
        {
            "category":"Recreation",
            "type":"Entertainment"
        }
    ],
    "sg:phone":"+1 425 450 3307",
    "sg:postcode":"98012",
    "sg:province":"WA",
    "sg:tags":[
        "club",
        "membership"
    ],
    "wof:name":"Mill Creek Little League",
    "wof:placetype":"venue"
},
  "geometry": {"coordinates":[-122.217044,47.870119],"type":"Point"}
}