{
  "type": "Feature",
  "properties": {
    "addr:full":"1182 E Lakeshore Dr W Shelton WA 98584",
    "addr:housenumber":"1182",
    "addr:postcode":"98584",
    "addr:street":"E Lakeshore Dr W",
    "iso:country":"US",
    "sg:address":"1182 E Lakeshore Dr W",
    "sg:city":"Shelton",
    "sg:classifiers":[
        {
            "category":"Shopping",
            "subcategory":"Catalog Store",
            "type":"Retail Goods"
        }
    ],
    "sg:phone":"+1 360 426 2167",
    "sg:postcode":"98584",
    "sg:province":"WA",
    "sg:tags":[
        "mail",
        "house"
    ],
    "wof:name":"Jtd Arts",
    "wof:placetype":"venue"
},
  "geometry": {"coordinates":[-122.96877600000001,47.227204],"type":"Point"}
}