{
  "type": "Feature",
  "properties": {
    "addr:full":"225 Sunset Blvd N Renton WA 98055",
    "addr:housenumber":"225",
    "addr:postcode":"98055",
    "addr:street":"Sunset Blvd N",
    "iso:country":"US",
    "sg:address":"225 Sunset Blvd N",
    "sg:city":"Renton",
    "sg:classifiers":[
        {
            "category":"Shopping",
            "subcategory":"Jewelry",
            "type":"Retail Goods"
        }
    ],
    "sg:phone":"+1 425 917 8117",
    "sg:postcode":"98055",
    "sg:province":"WA",
    "sg:website":"www.superpawn.com",
    "wof:name":"Superpawn",
    "wof:placetype":"venue"
},
  "geometry": {"coordinates":[-122.195999,47.485699],"type":"Point"}
}