{
  "type": "Feature",
  "properties": {
    "addr:full":"623 1st St Hoquiam WA 98550",
    "addr:housenumber":"623",
    "addr:postcode":"98550",
    "addr:street":"1St St",
    "iso:country":"US",
    "sg:address":"623 1st St",
    "sg:city":"Hoquiam",
    "sg:classifiers":[
        {
            "category":"Wholesale",
            "subcategory":"Machinery & Supplies",
            "type":"Manufacturing & Wholesale Goods"
        }
    ],
    "sg:phone":"+1 360 532 3380",
    "sg:postcode":"98550",
    "sg:province":"WA",
    "sg:tags":[
        "equipment",
        "industrial"
    ],
    "wof:name":"Anderson Pressure Washing Svc",
    "wof:placetype":"venue"
},
  "geometry": {"coordinates":[-123.894683,46.980257],"type":"Point"}
}