{
  "type": "Feature",
  "properties": {
    "addr:full":"5521 Chuckanut Dr Bow WA 98232",
    "addr:housenumber":"5521",
    "addr:postcode":"98232",
    "addr:street":"Chuckanut Dr",
    "iso:country":"US",
    "sg:address":"5521 Chuckanut Dr",
    "sg:city":"Bow",
    "sg:classifiers":[
        {
            "category":"Restaurant",
            "type":"Food & Drink"
        }
    ],
    "sg:phone":"+1 360 766 6667",
    "sg:postcode":"98232",
    "sg:province":"WA",
    "sg:website":"www.rhodycafe.com",
    "wof:name":"Rhododendron Cafe",
    "wof:placetype":"venue"
},
  "geometry": {"coordinates":[-122.42209699999999,48.565279],"type":"Point"}
}