{
  "type": "Feature",
  "properties": {
    "addr:full":"12804 NE 85th St Ste B Kirkland WA 98033",
    "addr:housenumber":"12804",
    "addr:postcode":"98033",
    "addr:street":"Ne 85Th St Ste B",
    "iso:country":"US",
    "sg:address":"12804 NE 85th St Ste B",
    "sg:city":"Kirkland",
    "sg:classifiers":[
        {
            "category":"Retail",
            "subcategory":"Laundry & Dry Cleaning",
            "type":"Services"
        }
    ],
    "sg:phone":"+1 425 889 2046",
    "sg:postcode":"98033",
    "sg:province":"WA",
    "wof:name":"Best Cleaners",
    "wof:placetype":"venue"
},
  "geometry": {"coordinates":[-122.195999,47.676701],"type":"Point"}
}