{
  "type": "Feature",
  "properties": {
    "addr:full":"1409 32nd St Bellingham WA 98225",
    "addr:housenumber":"1409",
    "addr:postcode":"98225",
    "addr:street":"32Nd St",
    "iso:country":"US",
    "sg:address":"1409 32nd St",
    "sg:city":"Bellingham",
    "sg:classifiers":[
        {
            "category":"Retail",
            "subcategory":"Auto Repair",
            "type":"Services"
        }
    ],
    "sg:phone":"+1 360 676 8403",
    "sg:postcode":"98225",
    "sg:province":"WA",
    "sg:tags":[
        "motors-repairing",
        "engines-rebuild",
        "outboard",
        "exchange"
    ],
    "wof:name":"Jeri D Heidingsfelder",
    "wof:placetype":"venue"
},
  "geometry": {"coordinates":[-122.47541200000001,48.719133],"type":"Point"}
}