{
  "type": "Feature",
  "properties": {
    "addr:full":"306 Geissler Rd Montesano WA 98563",
    "addr:housenumber":"306",
    "addr:postcode":"98563",
    "addr:street":"Geissler Rd",
    "iso:country":"US",
    "sg:address":"306 Geissler Rd",
    "sg:city":"Montesano",
    "sg:classifiers":[
        {
            "category":"Manufacturing",
            "subcategory":"Lumber",
            "type":"Manufacturing & Wholesale Goods"
        }
    ],
    "sg:phone":"+1 360 249 3375",
    "sg:postcode":"98563",
    "sg:province":"WA",
    "sg:tags":[
        "product",
        "special",
        "sawmill"
    ],
    "wof:name":"D & B Cedar",
    "wof:placetype":"venue"
},
  "geometry": {"coordinates":[-123.686448,47.004702],"type":"Point"}
}