{
  "type": "Feature",
  "properties": {
    "addr:full":"2501 James St Bellingham WA 98225",
    "addr:housenumber":"2501",
    "addr:postcode":"98225",
    "addr:street":"James St",
    "iso:country":"US",
    "sg:address":"2501 James St",
    "sg:city":"Bellingham",
    "sg:classifiers":[
        {
            "category":"Banks & Credit Unions",
            "subcategory":"Bank",
            "type":"Services"
        }
    ],
    "sg:phone":"+1 360 734 5790",
    "sg:postcode":"98225",
    "sg:province":"WA",
    "sg:tags":[
        "state",
        "mortgage"
    ],
    "sg:website":"www.gapacefcu.org",
    "wof:name":"Gapac Employees Federal Cr Un",
    "wof:placetype":"venue"
},
  "geometry": {"coordinates":[-122.46491899999999,48.764312],"type":"Point"}
}