{
  "type": "Feature",
  "properties": {
    "addr:full":"846 Arden Hill Rd Colville WA 99114",
    "addr:housenumber":"846",
    "addr:postcode":"99114",
    "addr:street":"Arden Hill Rd",
    "iso:country":"US",
    "sg:address":"846 Arden Hill Rd",
    "sg:city":"Colville",
    "sg:classifiers":[
        {
            "category":"Organizations",
            "subcategory":"Religious Organization",
            "type":"Services"
        }
    ],
    "sg:phone":"+1 509 684 8700",
    "sg:postcode":"99114",
    "sg:province":"WA",
    "wof:name":"Freedom Covenant Church",
    "wof:placetype":"venue"
},
  "geometry": {"coordinates":[-117.903457,48.44063],"type":"Point"}
}