{
  "type": "Feature",
  "properties": {
    "addr:full":"8612 Berkeley St SW Lakewood WA 98498",
    "addr:housenumber":"8612",
    "addr:postcode":"98498",
    "addr:street":"Berkeley St Sw",
    "iso:country":"US",
    "sg:address":"8612 Berkeley St SW",
    "sg:city":"Lakewood",
    "sg:classifiers":[
        {
            "category":"Professional",
            "type":"Services"
        }
    ],
    "sg:phone":"+1 253 588 3728",
    "sg:postcode":"98498",
    "sg:province":"WA",
    "wof:name":"Marian L Fina",
    "wof:placetype":"venue"
},
  "geometry": {"coordinates":[-122.561319,47.121828],"type":"Point"}
}