{
  "type": "Feature",
  "properties": {
    "addr:full":"8135 1st Ave S Seattle WA 98108",
    "addr:housenumber":"8135",
    "addr:postcode":"98108",
    "addr:street":"1St Ave S",
    "iso:country":"US",
    "sg:address":"8135 1st Ave S",
    "sg:city":"Seattle",
    "sg:classifiers":[
        {
            "category":"Manufacturing",
            "subcategory":"Metals",
            "type":"Manufacturing & Wholesale Goods"
        }
    ],
    "sg:phone":"+1 206 762 5855",
    "sg:postcode":"98108",
    "sg:province":"WA",
    "sg:tags":[
        "laboratory",
        "testing",
        "business"
    ],
    "wof:name":"Mapsco",
    "wof:placetype":"venue"
},
  "geometry": {"coordinates":[-122.334897,47.528006],"type":"Point"}
}