{
  "type": "Feature",
  "properties": {
    "addr:full":"616 Lilly Rd NE Apt 213 Olympia WA 98506",
    "addr:housenumber":"616;213",
    "addr:postcode":"olympia;98506",
    "addr:street":"Lilly Rd Ne Apt",
    "iso:country":"US",
    "sg:address":"616 Lilly Rd NE Apt 213",
    "sg:city":"Olympia",
    "sg:classifiers":[
        {
            "category":"Manufacturing",
            "subcategory":"Lumber",
            "type":"Manufacturing & Wholesale Goods"
        }
    ],
    "sg:phone":"+1 360 765 3700",
    "sg:postcode":"98506",
    "sg:province":"WA",
    "sg:tags":[
        "logging"
    ],
    "wof:name":"Anderson Tree Farm",
    "wof:placetype":"venue"
},
  "geometry": {"coordinates":[-122.844418,47.055002],"type":"Point"}
}