{
  "type": "Feature",
  "properties": {
    "addr:full":"11201 SE Kent Kangley Rd Kent WA 98030",
    "addr:postcode":"11201;98030",
    "addr:street":"Se Kent Kangley Rd",
    "iso:country":"US",
    "sg:address":"11201 SE Kent Kangley Rd",
    "sg:city":"Kent",
    "sg:classifiers":[
        {
            "category":"Personal",
            "type":"Services"
        }
    ],
    "sg:phone":"+1 253 638 7249",
    "sg:postcode":"98030",
    "sg:province":"WA",
    "sg:tags":[
        "massage"
    ],
    "wof:name":"Sandy Malick-Lipscomb Lmp",
    "wof:placetype":"venue"
},
  "geometry": {"coordinates":[-122.19152099999999,47.368679],"type":"Point"}
}