{
  "type": "Feature",
  "properties": {
    "iso:country":"US",
    "sg:address":"696 Water St",
    "sg:city":"Port Townsend",
    "sg:classifiers":[
        {
            "category":"Shopping",
            "subcategory":"Books",
            "type":"Retail Goods"
        }
    ],
    "sg:phone":"+1 360 385 4464",
    "sg:postcode":"98368",
    "sg:province":"WA",
    "sg:website":"www.phoenixrising-pt.com",
    "wof:name":"Phoenix Rising",
    "wof:placetype":"venue"
},
  "geometry": {"coordinates":[-122.754172,48.115338],"type":"Point"}
}