{
  "type": "Feature",
  "properties": {
    "addr:full":"10702 NE 42nd Pl Kirkland WA 98033",
    "addr:housenumber":"10702",
    "addr:postcode":"98033",
    "addr:street":"Ne 42Nd Pl",
    "iso:country":"US",
    "sg:address":"10702 NE 42nd Pl",
    "sg:city":"Kirkland",
    "sg:classifiers":[
        {
            "category":"Banks & Credit Unions",
            "subcategory":"Financial Services",
            "type":"Services"
        }
    ],
    "sg:phone":"+1 425 822 8165",
    "sg:postcode":"98033",
    "sg:province":"WA",
    "sg:tags":[
        "investor"
    ],
    "wof:name":"Limmat Ventures I LLC",
    "wof:placetype":"venue"
},
  "geometry": {"coordinates":[-122.197429,47.648482],"type":"Point"}
}