{
  "type": "Feature",
  "properties": {
    "addr:full":"4803 196th St SE Bothell WA 98012",
    "addr:housenumber":"4803",
    "addr:postcode":"98012",
    "addr:street":"196Th St Se",
    "iso:country":"US",
    "sg:address":"4803 196th St SE",
    "sg:city":"Bothell",
    "sg:classifiers":[
        {
            "category":"Professional",
            "type":"Services"
        }
    ],
    "sg:phone":"+1 425 487 3861",
    "sg:postcode":"98012",
    "sg:province":"WA",
    "wof:name":"Jill Miller Alke",
    "wof:placetype":"venue"
},
  "geometry": {"coordinates":[-122.16958700000001,47.819894],"type":"Point"}
}