{
  "type": "Feature",
  "properties": {
    "addr:full":"18 N University Rd Spokane WA 99206",
    "addr:housenumber":"18",
    "addr:postcode":"99206",
    "addr:street":"N University Rd",
    "iso:country":"US",
    "sg:address":"18 N University Rd",
    "sg:city":"Spokane",
    "sg:classifiers":[
        {
            "category":"Social Services",
            "subcategory":"Child Care",
            "type":"Services"
        }
    ],
    "sg:phone":"+1 509 926 5600",
    "sg:postcode":"99206",
    "sg:province":"WA",
    "sg:tags":[
        "day"
    ],
    "wof:name":"Primary Bginning Child Dev Ctr",
    "wof:placetype":"venue"
},
  "geometry": {"coordinates":[-117.26125500000001,47.657962],"type":"Point"}
}