{
  "type": "Feature",
  "properties": {
    "addr:full":"5225 268th St NW Stanwood WA 98292",
    "addr:housenumber":"5225",
    "addr:postcode":"98292",
    "addr:street":"268Th St Nw",
    "iso:country":"US",
    "sg:address":"5225 268th St NW",
    "sg:city":"Stanwood",
    "sg:classifiers":[
        {
            "category":"Farming",
            "subcategory":"Farm & Veterinary Services",
            "type":"Manufacturing & Wholesale Goods"
        }
    ],
    "sg:phone":"+1 360 629 2844",
    "sg:postcode":"98292",
    "sg:province":"WA",
    "sg:tags":[
        "livestock"
    ],
    "wof:name":"Davies Doug Sheep Goat Shering",
    "wof:placetype":"venue"
},
  "geometry": {"coordinates":[-122.302886,48.239367],"type":"Point"}
}