{
  "type": "Feature",
  "properties": {
    "addr:full":"4510 36th Ave W Seattle WA 98199",
    "addr:housenumber":"4510",
    "addr:postcode":"98199",
    "addr:street":"36Th Ave W",
    "iso:country":"US",
    "sg:address":"4510 36th Ave W",
    "sg:city":"Seattle",
    "sg:classifiers":[
        {
            "category":"Building & Trades",
            "subcategory":"Plumbing",
            "type":"Services"
        }
    ],
    "sg:phone":"+1 206 285 2656",
    "sg:postcode":"98199",
    "sg:province":"WA",
    "sg:tags":[
        "concrete",
        "contractor"
    ],
    "wof:name":"Jay Cement Contractors",
    "wof:placetype":"venue"
},
  "geometry": {"coordinates":[-122.403496,47.662205],"type":"Point"}
}