{
  "type": "Feature",
  "properties": {
    "iso:country":"US",
    "sg:address":"18 86th Dr SE",
    "sg:city":"Everett",
    "sg:classifiers":[
        {
            "category":"Shopping",
            "subcategory":"Gifts & Souvenirs",
            "type":"Retail Goods"
        }
    ],
    "sg:phone":"+1 425 335 4432",
    "sg:postcode":"98205",
    "sg:province":"WA",
    "wof:name":"Hannahs Home",
    "wof:placetype":"venue"
},
  "geometry": {"coordinates":[-122.114321,47.996504],"type":"Point"}
}