{
  "type": "Feature",
  "properties": {
    "addr:full":"2011 NE 45th St. Seattle WA 98105",
    "addr:housenumber":"2011",
    "addr:postcode":"98105",
    "addr:street":"Ne 45Th St.",
    "iso:country":"US",
    "sg:address":"2011 NE 45th St.",
    "sg:city":"Seattle",
    "sg:classifiers":[
        {
            "category":"Education",
            "subcategory":"University",
            "type":"Public Place"
        }
    ],
    "sg:postcode":"98105",
    "sg:province":"WA",
    "sg:tags":[
        "housing"
    ],
    "sg:website":"www.hfs.washington.edu",
    "wof:name":"Hansee Hall",
    "wof:placetype":"venue"
},
  "geometry": {"coordinates":[-122.306235,47.661236],"type":"Point"}
}