{
  "type": "Feature",
  "properties": {
    "addr:full":"13400 NE 20th St Bellevue WA 98005",
    "addr:housenumber":"13400",
    "addr:postcode":"98005",
    "addr:street":"Ne 20Th St",
    "iso:country":"US",
    "sg:address":"13400 NE 20th St",
    "sg:city":"Bellevue",
    "sg:classifiers":[
        {
            "category":"Building & Trades",
            "subcategory":"Equipment Rental",
            "type":"Services"
        },
        {
            "category":"Banks & Credit Unions",
            "subcategory":"Bank",
            "type":"Services"
        }
    ],
    "sg:phone":"+1 425 455 9983",
    "sg:postcode":"98005",
    "sg:province":"WA",
    "sg:tags":[
        "leasing",
        "business"
    ],
    "sg:website":"www.leaseapp.com",
    "wof:name":"Capital Funding Group",
    "wof:placetype":"venue"
},
  "geometry": {"coordinates":[-122.16003600000001,47.628088],"type":"Point"}
}