{
  "type": "Feature",
  "properties": {
    "addr:full":"2601 State Rte 109 Ocean City WA 98569",
    "addr:housenumber":"2601",
    "addr:postcode":"98569",
    "addr:street":"State Rte 109",
    "iso:country":"US",
    "sg:address":"2601 State Rte 109",
    "sg:city":"Ocean City",
    "sg:classifiers":[
        {
            "category":"Travel",
            "subcategory":"Hotels & Motels",
            "type":"Entertainment"
        }
    ],
    "sg:phone":"+1 360 289 4116",
    "sg:postcode":"98569",
    "sg:province":"WA",
    "sg:tags":[
        "operator",
        "operation",
        "dwelling"
    ],
    "wof:name":"North Beach Motel",
    "wof:placetype":"venue"
},
  "geometry": {"coordinates":[-124.165441,47.071889],"type":"Point"}
}