{
  "type": "Feature",
  "properties": {
    "addr:full":"4124 University Way NE Seattle WA 98105",
    "addr:housenumber":"4124",
    "addr:postcode":"98105",
    "addr:street":"University Way Ne",
    "iso:country":"US",
    "sg:address":"4124 University Way NE",
    "sg:city":"Seattle",
    "sg:classifiers":[
        {
            "category":"Restaurant",
            "type":"Food & Drink"
        }
    ],
    "sg:phone":"+1 206 632 6975",
    "sg:postcode":"98105",
    "sg:province":"WA",
    "sg:tags":[
        "japanese"
    ],
    "wof:name":"Ichiro Teriyaki",
    "wof:placetype":"venue"
},
  "geometry": {"coordinates":[-122.31300400000001,47.6576],"type":"Point"}
}