{
  "type": "Feature",
  "properties": {
    "addr:full":"9598 Ridgetop Blvd NW Silverdale WA 98383",
    "addr:housenumber":"9598",
    "addr:postcode":"98383",
    "addr:street":"Ridgetop Blvd Nw",
    "iso:country":"US",
    "sg:address":"9598 Ridgetop Blvd NW",
    "sg:city":"Silverdale",
    "sg:classifiers":[
        {
            "category":"Restaurant",
            "type":"Food & Drink"
        }
    ],
    "sg:phone":"+1 360 613 0544",
    "sg:postcode":"98383",
    "sg:province":"WA",
    "wof:name":"Wendys",
    "wof:placetype":"venue"
},
  "geometry": {"coordinates":[-122.68029199999999,47.654105],"type":"Point"}
}