{
  "type": "Feature",
  "properties": {
    "addr:full":"14247 Ambaum Blvd SW Burien WA 98166",
    "addr:housenumber":"14247",
    "addr:postcode":"98166",
    "addr:street":"Ambaum Blvd Sw",
    "iso:country":"US",
    "sg:address":"14247 Ambaum Blvd SW",
    "sg:city":"Burien",
    "sg:classifiers":[
        {
            "category":"Health Services",
            "subcategory":"Doctor",
            "type":"Services"
        }
    ],
    "sg:phone":"+1 206 244 4488",
    "sg:postcode":"98166",
    "sg:province":"WA",
    "sg:tags":[
        "dentist"
    ],
    "wof:name":"Alicia Chou Family Dentistry",
    "wof:placetype":"venue"
},
  "geometry": {"coordinates":[-122.347553,47.474709],"type":"Point"}
}