{
  "type": "Feature",
  "properties": {
    "addr:full":"5555 Ocean Beach Hwy Longview WA 98632",
    "addr:housenumber":"5555",
    "addr:postcode":"98632",
    "addr:street":"Ocean Beach Hwy",
    "iso:country":"US",
    "sg:address":"5555 Ocean Beach Hwy",
    "sg:city":"Longview",
    "sg:classifiers":[
        {
            "category":"Social Services",
            "subcategory":"Child Care",
            "type":"Services"
        }
    ],
    "sg:phone":"+1 360 425 6926",
    "sg:postcode":"98632",
    "sg:province":"WA",
    "wof:name":"Wee Care Day Care",
    "wof:placetype":"venue"
},
  "geometry": {"coordinates":[-123.014565,46.170744],"type":"Point"}
}