{
  "type": "Feature",
  "properties": {
    "iso:country":"US",
    "sg:address":"521 S Bernard St",
    "sg:city":"Spokane",
    "sg:classifiers":[
        {
            "category":"Health Services",
            "subcategory":"Health Practitioner",
            "type":"Services"
        }
    ],
    "sg:phone":"+1 509 747 1094",
    "sg:postcode":"99204",
    "sg:province":"WA",
    "sg:tags":[
        "nutritionist"
    ],
    "wof:name":"Nutritional Wisdom",
    "wof:placetype":"venue"
},
  "geometry": {"coordinates":[-117.416346,47.650634],"type":"Point"}
}