{
  "type": "Feature",
  "properties": {
    "addr:full":"176 Riverside Ave Winthrop WA 98862",
    "addr:housenumber":"176",
    "addr:postcode":"98862",
    "addr:street":"Riverside Ave",
    "iso:country":"US",
    "sg:address":"176 Riverside Ave",
    "sg:city":"Winthrop",
    "sg:classifiers":[
        {
            "category":"Restaurant",
            "type":"Food & Drink"
        }
    ],
    "sg:phone":"+1 509 996 2411",
    "sg:postcode":"98862",
    "sg:province":"WA",
    "wof:name":"Three Fingered Jacks Saloon",
    "wof:placetype":"venue"
},
  "geometry": {"coordinates":[-120.185497,48.477768],"type":"Point"}
}