{
  "type": "Feature",
  "properties": {
    "addr:full":"137 Naylor Rd Mossyrock WA 98564",
    "addr:housenumber":"137",
    "addr:postcode":"98564",
    "addr:street":"Naylor Rd",
    "iso:country":"US",
    "sg:address":"137 Naylor Rd",
    "sg:city":"Mossyrock",
    "sg:classifiers":[
        {
            "category":"Home & Garden",
            "subcategory":"Garden Supply",
            "type":"Retail Goods"
        }
    ],
    "sg:phone":"+1 360 983 8244",
    "sg:postcode":"98564",
    "sg:province":"WA",
    "sg:tags":[
        "tree",
        "christmas"
    ],
    "wof:name":"Burton, John",
    "wof:placetype":"venue"
},
  "geometry": {"coordinates":[-122.445486,46.51048],"type":"Point"}
}