{
  "type": "Feature",
  "properties": {
    "addr:full":"510 Easy St Pasco WA 99301",
    "addr:housenumber":"510",
    "addr:postcode":"99301",
    "addr:street":"Easy St",
    "iso:country":"US",
    "sg:address":"510 Easy St",
    "sg:city":"Pasco",
    "sg:phone":"+1 509 545 6124",
    "sg:postcode":"99301",
    "sg:province":"WA",
    "sg:tags":[
        "farm",
        "irish",
        "potato"
    ],
    "wof:name":"Eickmeyer Farms Inc",
    "wof:placetype":"venue"
},
  "geometry": {"coordinates":[-119.220347,46.307322],"type":"Point"}
}