{
  "type": "Feature",
  "properties": {
    "addr:full":"119 W 2nd St South Bend WA 98586",
    "addr:housenumber":"119",
    "addr:postcode":"98586",
    "addr:street":"W 2Nd St",
    "iso:country":"US",
    "sg:address":"119 W 2nd St",
    "sg:city":"South Bend",
    "sg:classifiers":[
        {
            "category":"Freight",
            "type":"Transportation"
        }
    ],
    "sg:phone":"+1 360 875 5217",
    "sg:postcode":"98586",
    "sg:province":"WA",
    "sg:tags":[
        "operator",
        "local",
        "trucking"
    ],
    "wof:name":"Mel Gibbons Trucking Inc",
    "wof:placetype":"venue"
},
  "geometry": {"coordinates":[-123.802238,46.660678],"type":"Point"}
}