{
  "type": "Feature",
  "properties": {
    "addr:full":"3902 W Valley Hwy N Auburn WA 98001",
    "addr:housenumber":"3902",
    "addr:postcode":"98001",
    "addr:street":"W Valley Hwy N",
    "iso:country":"US",
    "sg:address":"3902 W Valley Hwy N",
    "sg:city":"Auburn",
    "sg:classifiers":[
        {
            "category":"Wholesale",
            "subcategory":"Groceries",
            "type":"Manufacturing & Wholesale Goods"
        }
    ],
    "sg:phone":"+1 253 333 9275",
    "sg:postcode":"98001",
    "sg:province":"WA",
    "sg:tags":[
        "eating"
    ],
    "wof:name":"Poverty Bay Coffee Company",
    "wof:placetype":"venue"
},
  "geometry": {"coordinates":[-122.24972099999999,47.343397],"type":"Point"}
}