{
  "type": "Feature",
  "properties": {
    "addr:full":"22101 Indianola Rd NE Poulsbo WA 98370",
    "addr:housenumber":"22101",
    "addr:postcode":"98370",
    "addr:street":"Indianola Rd Ne",
    "iso:country":"US",
    "sg:address":"22101 Indianola Rd NE",
    "sg:city":"Poulsbo",
    "sg:classifiers":[
        {
            "category":"Building & Trades",
            "subcategory":"Construction",
            "type":"Services"
        }
    ],
    "sg:phone":"+1 360 697 2859",
    "sg:postcode":"98370",
    "sg:province":"WA",
    "sg:tags":[
        "industrial"
    ],
    "wof:name":"LDR Construction Inc",
    "wof:placetype":"venue"
},
  "geometry": {"coordinates":[-122.551863,47.763087],"type":"Point"}
}