{
  "type": "Feature",
  "properties": {
    "addr:full":"13230 116th Ave NE Kirkland WA 98034",
    "addr:housenumber":"13230",
    "addr:postcode":"98034",
    "addr:street":"116Th Ave Ne",
    "iso:country":"US",
    "sg:address":"13230 116th Ave NE",
    "sg:city":"Kirkland",
    "sg:classifiers":[
        {
            "category":"Building & Trades",
            "subcategory":"Construction",
            "type":"Services"
        }
    ],
    "sg:phone":"+1 206 679 5744",
    "sg:postcode":"98034",
    "sg:province":"WA",
    "sg:tags":[
        "house"
    ],
    "wof:name":"St Aubin Painting & Cnstr Inc",
    "wof:placetype":"venue"
},
  "geometry": {"coordinates":[-122.186317,47.71893],"type":"Point"}
}