{
  "type": "Feature",
  "properties": {
    "addr:full":"267 Stevens Ave NW Renton WA 98057",
    "addr:housenumber":"267",
    "addr:postcode":"98057",
    "addr:street":"Stevens Ave Nw",
    "iso:country":"US",
    "sg:address":"267 Stevens Ave NW",
    "sg:city":"Renton",
    "sg:classifiers":[
        {
            "category":"Building & Trades",
            "subcategory":"Construction",
            "type":"Services"
        }
    ],
    "sg:phone":"+1 425 271 5396",
    "sg:postcode":"98057",
    "sg:province":"WA",
    "sg:tags":[
        "painting",
        "contractor"
    ],
    "wof:name":"Happy Helper",
    "wof:placetype":"venue"
},
  "geometry": {"coordinates":[-122.22307000000001,47.486494],"type":"Point"}
}