{
  "type": "Feature",
  "properties": {
    "addr:full":"7342 15th Ave NW Seattle WA 98117",
    "addr:housenumber":"7342",
    "addr:postcode":"98117",
    "addr:street":"15Th Ave Nw",
    "iso:country":"US",
    "sg:address":"7342 15th Ave NW",
    "sg:city":"Seattle",
    "sg:classifiers":[
        {
            "category":"Communications",
            "subcategory":"Newspaper",
            "type":"Services"
        }
    ],
    "sg:phone":"+1 206 789 8116",
    "sg:postcode":"98117",
    "sg:province":"WA",
    "sg:tags":[
        "print",
        "medium"
    ],
    "wof:name":"Northwest Yachting Magazine",
    "wof:placetype":"venue"
},
  "geometry": {"coordinates":[-122.376999,47.6819],"type":"Point"}
}