{
  "type": "Feature",
  "properties": {
    "addr:full":"3100 Riviera Blvd Malaga WA 98828",
    "addr:housenumber":"3100",
    "addr:postcode":"98828",
    "addr:street":"Riviera Blvd",
    "iso:country":"US",
    "sg:address":"3100 Riviera Blvd",
    "sg:city":"Malaga",
    "sg:classifiers":[
        {
            "category":"Shopping",
            "subcategory":"Bicycles & Sporting Goods",
            "type":"Retail Goods"
        }
    ],
    "sg:phone":"+1 509 662 7760",
    "sg:postcode":"98828",
    "sg:province":"WA",
    "wof:name":"Wenatchee Adventure Sport",
    "wof:placetype":"venue"
},
  "geometry": {"coordinates":[-120.222934,47.36483],"type":"Point"}
}