{
  "type": "Feature",
  "properties": {
    "addr:full":"1118 110th Ave E Edgewood WA 98372",
    "addr:housenumber":"1118",
    "addr:postcode":"98372",
    "addr:street":"110Th Ave E",
    "iso:country":"US",
    "sg:address":"1118 110th Ave E",
    "sg:city":"Edgewood",
    "sg:classifiers":[
        {
            "category":"Building & Trades",
            "subcategory":"Landscaping Services",
            "type":"Services"
        },
        {
            "category":"Professional",
            "type":"Services"
        }
    ],
    "sg:phone":"+1 253 927 5812",
    "sg:postcode":"98372",
    "sg:province":"WA",
    "sg:tags":[
        "forestry",
        "consulting",
        "forester"
    ],
    "sg:website":"http://www.johnschulz.net",
    "wof:name":"John Schulz Forest & Tmber Con",
    "wof:placetype":"venue"
},
  "geometry": {"coordinates":[-122.282117,47.247623],"type":"Point"}
}