{
  "type": "Feature",
  "properties": {
    "addr:full":"2421 S Union Ave Tacoma WA 98405",
    "addr:housenumber":"2421",
    "addr:postcode":"98405",
    "addr:street":"S Union Ave",
    "iso:country":"US",
    "sg:address":"2421 S Union Ave",
    "sg:city":"Tacoma",
    "sg:classifiers":[
        {
            "category":"Wholesale",
            "subcategory":"Furniture",
            "type":"Manufacturing & Wholesale Goods"
        }
    ],
    "sg:phone":"+1 253 539 5688",
    "sg:postcode":"98405",
    "sg:province":"WA",
    "wof:name":"Interior Details Inc",
    "wof:placetype":"venue"
},
  "geometry": {"coordinates":[-122.48166399999999,47.23633],"type":"Point"}
}