{
  "type": "Feature",
  "properties": {
    "addr:full":"1003 S Ruby St Ellensburg WA 98926",
    "addr:housenumber":"1003",
    "addr:postcode":"98926",
    "addr:street":"S Ruby St",
    "iso:country":"US",
    "sg:address":"1003 S Ruby St",
    "sg:city":"Ellensburg",
    "sg:classifiers":[
        {
            "category":"Manufacturing",
            "subcategory":"Petroleum Products",
            "type":"Manufacturing & Wholesale Goods"
        },
        {
            "category":"Manufacturing",
            "subcategory":"Building Materials",
            "type":"Manufacturing & Wholesale Goods"
        }
    ],
    "sg:phone":"+1 509 933 1102",
    "sg:postcode":"98926",
    "sg:province":"WA",
    "sg:tags":[
        "metal",
        "work",
        "sheet",
        "contract"
    ],
    "wof:name":"Haytools Inc",
    "wof:placetype":"venue"
},
  "geometry": {"coordinates":[-120.54453100000001,46.98392],"type":"Point"}
}