{
  "type": "Feature",
  "properties": {
    "addr:full":"33101 Pacific Hwy S Federal Way WA 98003",
    "addr:housenumber":"33101",
    "addr:postcode":"98003",
    "addr:street":"Pacific Hwy S Federal Way",
    "iso:country":"US",
    "sg:address":"33101 Pacific Hwy S",
    "sg:city":"Federal Way",
    "sg:classifiers":[
        {
            "category":"Autos & Motor Vehicles",
            "subcategory":"Fuel & Gas Station",
            "type":"Retail Goods"
        }
    ],
    "sg:phone":"+1 253 838 2060",
    "sg:postcode":"98003",
    "sg:province":"WA",
    "sg:tags":[
        "oil"
    ],
    "wof:name":"Ernie's Fuel Stop",
    "wof:placetype":"venue"
},
  "geometry": {"coordinates":[-122.31348300000001,47.305655],"type":"Point"}
}