{
  "type": "Feature",
  "properties": {
    "addr:full":"10992 Central Valley Rd NW Poulsbo WA 98370",
    "addr:postcode":"10992;98370",
    "addr:street":"Central Valley Rd Nw",
    "iso:country":"US",
    "sg:address":"10992 Central Valley Rd NW",
    "sg:city":"Poulsbo",
    "sg:classifiers":[
        {
            "category":"Professional",
            "type":"Services"
        }
    ],
    "sg:phone":"+1 360 698 3915",
    "sg:postcode":"98370",
    "sg:province":"WA",
    "wof:name":"Laura Medchill",
    "wof:placetype":"venue"
},
  "geometry": {"coordinates":[-122.650119,47.661429],"type":"Point"}
}