{
  "type": "Feature",
  "properties": {
    "addr:full":"1219 S 2nd St Mount Vernon WA 98273",
    "addr:housenumber":"1219",
    "addr:postcode":"98273",
    "addr:street":"S 2Nd St",
    "iso:country":"US",
    "sg:address":"1219 S 2nd St",
    "sg:city":"Mount Vernon",
    "sg:classifiers":[
        {
            "category":"Banks & Credit Unions",
            "subcategory":"Investment Brokerage",
            "type":"Services"
        }
    ],
    "sg:phone":"+1 360 336 0914",
    "sg:postcode":"98273",
    "sg:province":"WA",
    "sg:tags":[
        "investing"
    ],
    "wof:name":"Linsco Private Ledger",
    "wof:placetype":"venue"
},
  "geometry": {"coordinates":[-122.33801,48.413703],"type":"Point"}
}