{
  "type": "Feature",
  "properties": {
    "addr:full":"12202 NE 24th St Vancouver WA 98684",
    "addr:housenumber":"12202",
    "addr:postcode":"98684",
    "addr:street":"Ne 24Th St",
    "iso:country":"US",
    "sg:address":"12202 NE 24th St",
    "sg:city":"Vancouver",
    "sg:classifiers":[
        {
            "category":"Professional",
            "subcategory":"Engineering",
            "type":"Services"
        }
    ],
    "sg:phone":"+1 360 892 5740",
    "sg:postcode":"98684",
    "sg:province":"WA",
    "sg:tags":[
        "engineer"
    ],
    "wof:name":"David Kelly Traffic Engineer",
    "wof:placetype":"venue"
},
  "geometry": {"coordinates":[-122.547021,45.639657],"type":"Point"}
}