{
  "type": "Feature",
  "properties": {
    "addr:full":"10977 NE State Highway 104 Kingston WA 98346",
    "addr:housenumber":"10977",
    "addr:postcode":"98346",
    "addr:street":"Ne State Highway 104",
    "iso:country":"US",
    "sg:address":"10977 NE State Highway 104",
    "sg:city":"Kingston",
    "sg:classifiers":[
        {
            "category":"Fast Food",
            "type":"Food & Drink"
        },
        {
            "category":"Restaurant",
            "type":"Food & Drink"
        }
    ],
    "sg:phone":"+1 360 297 4350",
    "sg:postcode":"98346",
    "sg:province":"WA",
    "sg:tags":[
        "hamburger",
        "hot",
        "dog",
        "american",
        "take",
        "chicken"
    ],
    "sg:website":"http://www.mcdonalds.com",
    "wof:name":"McDonald's",
    "wof:placetype":"venue"
},
  "geometry": {"coordinates":[-122.499888,47.801232],"type":"Point"}
}