{
  "type": "Feature",
  "properties": {
    "addr:full":"17839 Aurora Ave N Shoreline WA 98133",
    "addr:housenumber":"17839",
    "addr:postcode":"98133",
    "addr:street":"Aurora Ave N",
    "iso:country":"US",
    "sg:address":"17839 Aurora Ave N",
    "sg:city":"Shoreline",
    "sg:classifiers":[
        {
            "category":"Place Of Worship",
            "subcategory":"Church",
            "type":"Public Place"
        },
        {
            "category":"Place Of Worship",
            "type":"Public Place"
        }
    ],
    "sg:phone":"+1 206 542 2484",
    "sg:postcode":"98133",
    "sg:province":"WA",
    "sg:tags":[
        "christ",
        "churches-community"
    ],
    "wof:name":"Asian American Community Church Of Seatt",
    "wof:placetype":"venue"
},
  "geometry": {"coordinates":[-122.34605000000001,47.758676],"type":"Point"}
}