{
  "type": "Feature",
  "properties": {
    "addr:full":"5931 Guide Meridian Rd Bellingham WA 98226",
    "addr:housenumber":"5931",
    "addr:postcode":"98226",
    "addr:street":"Guide Meridian Rd",
    "iso:country":"US",
    "sg:address":"5931 Guide Meridian Rd",
    "sg:city":"Bellingham",
    "sg:classifiers":[
        {
            "category":"Professional",
            "subcategory":"Business Services",
            "type":"Services"
        }
    ],
    "sg:phone":"+1 360 398 8198",
    "sg:postcode":"98226",
    "sg:province":"WA",
    "wof:name":"Xinix Packaging Corporation",
    "wof:placetype":"venue"
},
  "geometry": {"coordinates":[-122.48603799999999,48.85623],"type":"Point"}
}