{
  "type": "Feature",
  "properties": {
    "addr:full":"17404 Meridian E Puyallup WA 98375",
    "addr:housenumber":"17404",
    "addr:postcode":"98375",
    "addr:street":"Meridian E",
    "iso:country":"US",
    "sg:address":"17404 Meridian E",
    "sg:city":"Puyallup",
    "sg:classifiers":[
        {
            "category":"Retail",
            "subcategory":"Auto Repair",
            "type":"Services"
        }
    ],
    "sg:phone":"+1 253 268 5531",
    "sg:postcode":"98375",
    "sg:province":"WA",
    "sg:tags":[
        "windshield"
    ],
    "wof:name":"Apollo Auto Glass",
    "wof:placetype":"venue"
},
  "geometry": {"coordinates":[-122.293532,47.099175],"type":"Point"}
}