{
  "type": "Feature",
  "properties": {
    "addr:full":"19081 Angeline Ave NE Suquamish WA 98392",
    "addr:housenumber":"19081",
    "addr:postcode":"98392",
    "addr:street":"Angeline Ave Ne",
    "iso:country":"US",
    "sg:address":"19081 Angeline Ave NE",
    "sg:city":"Suquamish",
    "sg:classifiers":[
        {
            "category":"Building & Trades",
            "subcategory":"Construction",
            "type":"Services"
        }
    ],
    "sg:phone":"+1 360 598 6631",
    "sg:postcode":"98392",
    "sg:province":"WA",
    "sg:tags":[
        "contractor"
    ],
    "wof:name":"Renaissance Tile Inc",
    "wof:placetype":"venue"
},
  "geometry": {"coordinates":[-122.55059900000001,47.736183],"type":"Point"}
}