{
  "type": "Feature",
  "properties": {
    "addr:full":"9826 NE 132nd St Kirkland WA 98034",
    "addr:housenumber":"9826",
    "addr:postcode":"98034",
    "addr:street":"Ne 132Nd St",
    "iso:country":"US",
    "sg:address":"9826 NE 132nd St",
    "sg:city":"Kirkland",
    "sg:classifiers":[
        {
            "category":"Food & Beverages",
            "subcategory":"Groceries & Convenience Stores",
            "type":"Retail Goods"
        }
    ],
    "sg:phone":"+1 425 823 6000",
    "sg:postcode":"98034",
    "sg:province":"WA",
    "wof:name":"Albertsons Supermarkets",
    "wof:placetype":"venue"
},
  "geometry": {"coordinates":[-122.209,47.718399],"type":"Point"}
}