{
  "type": "Feature",
  "properties": {
    "addr:full":"85 Tennant Way Longview WA 98632",
    "addr:housenumber":"85",
    "addr:postcode":"98632",
    "addr:street":"Tennant Way",
    "iso:country":"US",
    "sg:address":"85 Tennant Way",
    "sg:city":"Longview",
    "sg:classifiers":[
        {
            "category":"Government",
            "subcategory":"Office",
            "type":"Public Place"
        }
    ],
    "sg:phone":"+1 360 577 3126",
    "sg:postcode":"98632",
    "sg:province":"WA",
    "sg:tags":[
        "county",
        "program"
    ],
    "wof:name":"Cowlitz County Solid Waste",
    "wof:placetype":"venue"
},
  "geometry": {"coordinates":[-122.903217,46.109723],"type":"Point"}
}