{
  "type": "Feature",
  "properties": {
    "addr:full":"24905 55th Ave NE Arlington WA 98223",
    "addr:housenumber":"24905",
    "addr:postcode":"98223",
    "addr:street":"55Th Ave Ne",
    "iso:country":"US",
    "sg:address":"24905 55th Ave NE",
    "sg:city":"Arlington",
    "sg:classifiers":[
        {
            "category":"Building & Trades",
            "subcategory":"Construction",
            "type":"Services"
        }
    ],
    "sg:phone":"+1 360 403 9939",
    "sg:postcode":"98223",
    "sg:province":"WA",
    "sg:tags":[
        "system",
        "specialty",
        "heating",
        "contractor",
        "air conditioning"
    ],
    "wof:name":"Air Care Systems Hvac, Inc.",
    "wof:placetype":"venue"
},
  "geometry": {"coordinates":[-122.15567,48.221823],"type":"Point"}
}