{
  "type": "Feature",
  "properties": {
    "addr:full":"3930 Meridian St Ste 103 Bellingham WA 98226",
    "addr:housenumber":"3930",
    "addr:postcode":"98226",
    "addr:street":"Meridian St Ste 103",
    "iso:country":"US",
    "sg:address":"3930 Meridian St Ste 103",
    "sg:city":"Bellingham",
    "sg:classifiers":[
        {
            "category":"Shopping",
            "subcategory":"Beauty & Cosmetics",
            "type":"Retail Goods"
        },
        {
            "category":"Personal",
            "subcategory":"Beauty Salon",
            "type":"Services"
        }
    ],
    "sg:phone":"+1 360 647 6189",
    "sg:postcode":"98226",
    "sg:province":"WA",
    "sg:tags":[
        "supply",
        "perfume",
        "hair",
        "equipment",
        "salons-equipment",
        "accessory"
    ],
    "sg:website":"http://www.sallybeauty.com/",
    "wof:name":"Sally Beauty Supply",
    "wof:placetype":"venue"
},
  "geometry": {"coordinates":[-122.486091,48.786835],"type":"Point"}
}