{
  "type": "Feature",
  "properties": {
    "addr:full":"1143 Tacoma Ave S Tacoma WA 98402",
    "addr:housenumber":"1143",
    "addr:postcode":"98402",
    "addr:street":"Tacoma Ave S",
    "iso:country":"US",
    "sg:address":"1143 Tacoma Ave S",
    "sg:city":"Tacoma",
    "sg:classifiers":[
        {
            "category":"Social Services",
            "type":"Services"
        }
    ],
    "sg:phone":"+1 253 597 4804",
    "sg:postcode":"98402",
    "sg:province":"WA",
    "sg:tags":[
        "grocery"
    ],
    "wof:name":"King Center",
    "wof:placetype":"venue"
},
  "geometry": {"coordinates":[-122.444197,47.252185],"type":"Point"}
}