{
  "type": "Feature",
  "properties": {
    "addr:full":"409 N Argonne Rd Spokane Valley WA 99212",
    "addr:housenumber":"409",
    "addr:postcode":"99212",
    "addr:street":"N Argonne Rd",
    "iso:country":"US",
    "sg:address":"409 N Argonne Rd",
    "sg:city":"Spokane Valley",
    "sg:classifiers":[
        {
            "category":"Health Services",
            "subcategory":"Chiropractor",
            "type":"Services"
        }
    ],
    "sg:phone":"+1 509 924 7311",
    "sg:postcode":"99212",
    "sg:province":"WA",
    "sg:website":"www.sports-chiro.com",
    "wof:name":"Chiropractic Plus",
    "wof:placetype":"venue"
},
  "geometry": {"coordinates":[-117.282917,47.662342],"type":"Point"}
}