{
  "type": "Feature",
  "properties": {
    "addr:full":"625 6th St Clarkston WA 99403",
    "addr:housenumber":"625",
    "addr:postcode":"99403",
    "addr:street":"6Th St",
    "iso:country":"US",
    "sg:address":"625 6th St",
    "sg:city":"Clarkston",
    "sg:classifiers":[
        {
            "category":"Health Services",
            "subcategory":"Doctor",
            "type":"Services"
        }
    ],
    "sg:phone":"+1 509 758 3384",
    "sg:postcode":"99403",
    "sg:province":"WA",
    "sg:tags":[
        "dentist"
    ],
    "wof:name":"Perfection Dental",
    "wof:placetype":"venue"
},
  "geometry": {"coordinates":[-117.045475,46.417673],"type":"Point"}
}