{
  "type": "Feature",
  "properties": {
    "addr:full":"5315 NE 42nd St Seattle WA 98105",
    "addr:housenumber":"5315",
    "addr:postcode":"98105",
    "addr:street":"Ne 42Nd St",
    "iso:country":"US",
    "sg:address":"5315 NE 42nd St",
    "sg:city":"Seattle",
    "sg:classifiers":[
        {
            "category":"Recreation",
            "type":"Entertainment"
        }
    ],
    "sg:phone":"+1 206 525 9099",
    "sg:postcode":"98105",
    "sg:province":"WA",
    "sg:tags":[
        "water",
        "slide"
    ],
    "wof:name":"Slidewaters",
    "wof:placetype":"venue"
},
  "geometry": {"coordinates":[-122.270034,47.658638],"type":"Point"}
}