{
  "type": "Feature",
  "properties": {
    "addr:full":"22 Front St NW Coupeville WA 98239",
    "addr:housenumber":"22",
    "addr:postcode":"98239",
    "addr:street":"Front St Nw",
    "iso:country":"US",
    "sg:address":"22 Front St NW",
    "sg:city":"Coupeville",
    "sg:classifiers":[
        {
            "category":"Shopping",
            "subcategory":"Gifts & Souvenirs",
            "type":"Retail Goods"
        }
    ],
    "sg:phone":"+1 360 678 3565",
    "sg:postcode":"98239",
    "sg:province":"WA",
    "sg:tags":[
        "shop"
    ],
    "sg:website":"www.nauticalnnice.com",
    "wof:name":"Nautical 'N' Nice",
    "wof:placetype":"venue"
},
  "geometry": {"coordinates":[-122.687271,48.221156],"type":"Point"}
}