{
  "type": "Feature",
  "properties": {
    "addr:full":"3400 33rd Ave SW Seattle WA 98126",
    "addr:housenumber":"3400",
    "addr:postcode":"98126",
    "addr:street":"33Rd Ave Sw",
    "iso:country":"US",
    "sg:address":"3400 33rd Ave SW",
    "sg:city":"Seattle",
    "sg:classifiers":[
        {
            "category":"Professional",
            "subcategory":"Business Services",
            "type":"Services"
        }
    ],
    "sg:phone":"+1 206 935 2645",
    "sg:postcode":"98126",
    "sg:province":"WA",
    "sg:tags":[
        "design",
        "consulting",
        "art",
        "publishing"
    ],
    "wof:name":"Paba Group LLC",
    "wof:placetype":"venue"
},
  "geometry": {"coordinates":[-122.37419199999999,47.572202],"type":"Point"}
}