{
  "type": "Feature",
  "properties": {
    "addr:full":"731 S 50th St Tacoma WA 98408",
    "addr:housenumber":"731",
    "addr:postcode":"98408",
    "addr:street":"S 50Th St",
    "iso:country":"US",
    "sg:address":"731 S 50th St",
    "sg:city":"Tacoma",
    "sg:classifiers":[
        {
            "category":"Personal",
            "type":"Services"
        }
    ],
    "sg:phone":"+1 253 473 6741",
    "sg:postcode":"98408",
    "sg:province":"WA",
    "sg:tags":[
        "therapist",
        "massage"
    ],
    "wof:name":"Dynamic Massage Therapy",
    "wof:placetype":"venue"
},
  "geometry": {"coordinates":[-122.44107099999999,47.211894],"type":"Point"}
}