{
  "type": "Feature",
  "properties": {
    "iso:country":"US",
    "sg:address":"1100 Lewandowski Rd",
    "sg:city":"Sunnyside",
    "sg:classifiers":[
        {
            "category":"Recreation",
            "type":"Entertainment"
        }
    ],
    "sg:phone":"+1 509 839 7712",
    "sg:postcode":"98944",
    "sg:province":"WA",
    "wof:name":"Lower Valley Roller Hockey",
    "wof:placetype":"venue"
},
  "geometry": {"coordinates":[-119.96655,46.379107],"type":"Point"}
}