{
  "type": "Feature",
  "properties": {
    "addr:full":"19511 81st Pl W Edmonds WA 98026",
    "addr:housenumber":"19511",
    "addr:postcode":"98026",
    "addr:street":"81St Pl W",
    "iso:country":"US",
    "sg:address":"19511 81st Pl W",
    "sg:city":"Edmonds",
    "sg:classifiers":[
        {
            "category":"Communications",
            "type":"Services"
        }
    ],
    "sg:phone":"+1 425 670 1943",
    "sg:postcode":"98026",
    "sg:province":"WA",
    "sg:tags":[
        "communication"
    ],
    "wof:name":"Urbanistic Communications",
    "wof:placetype":"venue"
},
  "geometry": {"coordinates":[-122.34330799999999,47.823188],"type":"Point"}
}