{
  "type": "Feature",
  "properties": {
    "addr:full":"1901 W Main St Battle Ground WA 98604",
    "addr:housenumber":"1901",
    "addr:postcode":"98604",
    "addr:street":"W Main St",
    "iso:country":"US",
    "sg:address":"1901 W Main St",
    "sg:city":"Battle Ground",
    "sg:classifiers":[
        {
            "category":"Restaurant",
            "type":"Food & Drink"
        }
    ],
    "sg:phone":"+1 360 687 7121",
    "sg:postcode":"98604",
    "sg:province":"WA",
    "sg:tags":[
        "pizza"
    ],
    "sg:website":"www.egwa.com/rockys.htm",
    "wof:name":"Rocky's Pizza",
    "wof:placetype":"venue"
},
  "geometry": {"coordinates":[-122.55694099999999,45.780527],"type":"Point"}
}