{
  "type": "Feature",
  "properties": {
    "addr:full":"4503 E 5th St Vancouver WA 98661",
    "addr:housenumber":"4503",
    "addr:postcode":"98661",
    "addr:street":"E 5Th St",
    "iso:country":"US",
    "sg:address":"4503 E 5th St",
    "sg:city":"Vancouver",
    "sg:classifiers":[
        {
            "category":"Transit Center",
            "subcategory":"Freight",
            "type":"Transportation"
        }
    ],
    "sg:phone":"+1 360 828 8656",
    "sg:postcode":"98661",
    "sg:province":"WA",
    "sg:tags":[
        "trucking-heavy",
        "hauling"
    ],
    "wof:name":"Transcontinental Express",
    "wof:placetype":"venue"
},
  "geometry": {"coordinates":[-122.62282500000001,45.619982],"type":"Point"}
}