{
  "type": "Feature",
  "properties": {
    "addr:full":"3925 S 15th St Ridgefield WA 98642",
    "addr:housenumber":"3925",
    "addr:postcode":"98642",
    "addr:street":"S 15Th St",
    "iso:country":"US",
    "sg:address":"3925 S 15th St",
    "sg:city":"Ridgefield",
    "sg:classifiers":[
        {
            "category":"Building & Trades",
            "subcategory":"Landscaping Services",
            "type":"Services"
        }
    ],
    "sg:phone":"+1 360 887 3725",
    "sg:postcode":"98642",
    "sg:province":"WA",
    "wof:name":"Rain Forest Property Maintenan",
    "wof:placetype":"venue"
},
  "geometry": {"coordinates":[-122.708978,45.804731],"type":"Point"}
}