{
  "type": "Feature",
  "properties": {
    "addr:full":"1615 Valley Ave E Sumner WA 98390",
    "addr:housenumber":"1615",
    "addr:postcode":"98390",
    "addr:street":"Valley Ave E",
    "iso:country":"US",
    "sg:address":"1615 Valley Ave E",
    "sg:city":"Sumner",
    "sg:classifiers":[
        {
            "category":"Personal",
            "type":"Services"
        }
    ],
    "sg:phone":"+1 253 863 5406",
    "sg:postcode":"98390",
    "sg:province":"WA",
    "wof:name":"Partys By Mel",
    "wof:placetype":"venue"
},
  "geometry": {"coordinates":[-122.229381,47.209675],"type":"Point"}
}