{
  "type": "Feature",
  "properties": {
    "iso:country":"US",
    "sg:address":"14462 56th Ave S",
    "sg:city":"Tukwila",
    "sg:classifiers":[
        {
            "category":"Professional",
            "subcategory":"Business Services",
            "type":"Services"
        }
    ],
    "sg:phone":"+1 206 433 1161",
    "sg:postcode":"98168",
    "sg:province":"WA",
    "wof:name":"Christian Asset Retrieval",
    "wof:placetype":"venue"
},
  "geometry": {"coordinates":[-122.264152,47.473795],"type":"Point"}
}