{
  "type": "Feature",
  "properties": {
    "addr:full":"2704 W Valley Rd Friday Harbor WA 98250",
    "addr:housenumber":"2704",
    "addr:postcode":"98250",
    "addr:street":"W Valley Rd",
    "iso:country":"US",
    "sg:address":"2704 W Valley Rd",
    "sg:city":"Friday Harbor",
    "sg:classifiers":[
        {
            "category":"Retail",
            "subcategory":"Animal Services",
            "type":"Services"
        }
    ],
    "sg:phone":"+1 360 378 2510",
    "sg:postcode":"98250",
    "sg:province":"WA",
    "wof:name":"Troutbeck Farm",
    "wof:placetype":"venue"
},
  "geometry": {"coordinates":[-123.138957,48.571346],"type":"Point"}
}