{
  "type": "Feature",
  "properties": {
    "addr:full":"7517 78th Ave SE Mercer Island WA 98040",
    "addr:housenumber":"7517",
    "addr:postcode":"98040",
    "addr:street":"78Th Ave Se",
    "iso:country":"US",
    "sg:address":"7517 78th Ave SE",
    "sg:city":"Mercer Island",
    "sg:classifiers":[
        {
            "category":"Professional",
            "subcategory":"Management & Consulting",
            "type":"Services"
        }
    ],
    "sg:phone":"+1 206 275 1840",
    "sg:postcode":"98040",
    "sg:province":"WA",
    "sg:tags":[
        "business"
    ],
    "wof:name":"Pacific Integral LLC",
    "wof:placetype":"venue"
},
  "geometry": {"coordinates":[-122.23521,47.535157],"type":"Point"}
}