{
  "type": "Feature",
  "properties": {
    "addr:full":"555 Prospect St Seattle WA 98109",
    "addr:housenumber":"555",
    "addr:postcode":"98109",
    "addr:street":"Prospect St",
    "iso:country":"US",
    "sg:address":"555 Prospect St",
    "sg:city":"Seattle",
    "sg:classifiers":[
        {
            "category":"Manufacturing",
            "subcategory":"Jewelry",
            "type":"Manufacturing & Wholesale Goods"
        }
    ],
    "sg:phone":"+1 206 281 9207",
    "sg:postcode":"98109",
    "sg:province":"WA",
    "sg:tags":[
        "costume",
        "mfg"
    ],
    "wof:name":"Infantino Creations",
    "wof:placetype":"venue"
},
  "geometry": {"coordinates":[-122.345,47.628825],"type":"Point"}
}