{
  "type": "Feature",
  "properties": {
    "addr:full":"10811 Main St Bellevue WA 98004",
    "addr:housenumber":"10811",
    "addr:postcode":"98004",
    "addr:street":"Main St",
    "iso:country":"US",
    "sg:address":"10811 Main St",
    "sg:city":"Bellevue",
    "sg:classifiers":[
        {
            "category":"Communications",
            "type":"Services"
        },
        {
            "category":"Professional",
            "subcategory":"Computer Services",
            "type":"Services"
        }
    ],
    "sg:phone":"+1 425 709 3800",
    "sg:postcode":"98004",
    "sg:province":"WA",
    "sg:tags":[
        "design",
        "system"
    ],
    "wof:name":"Broadstream Communications Inc",
    "wof:placetype":"venue"
},
  "geometry": {"coordinates":[-122.194109,47.610017],"type":"Point"}
}