{
  "type": "Feature",
  "properties": {
    "addr:full":"416 S Vancouver St Kennewick WA 99336",
    "addr:housenumber":"416",
    "addr:postcode":"99336",
    "addr:street":"S Vancouver St",
    "iso:country":"US",
    "sg:address":"416 S Vancouver St",
    "sg:city":"Kennewick",
    "sg:classifiers":[
        {
            "category":"Shopping",
            "subcategory":"Books",
            "type":"Retail Goods"
        }
    ],
    "sg:phone":"+1 509 585 6275",
    "sg:postcode":"99336",
    "sg:province":"WA",
    "sg:tags":[
        "dealer"
    ],
    "wof:name":"Cornerstone Bookstore Cafe",
    "wof:placetype":"venue"
},
  "geometry": {"coordinates":[-119.14846199999999,46.204345],"type":"Point"}
}