{
  "type": "Feature",
  "properties": {
    "addr:full":"901 5th Ave Ste 3850 Seattle WA 98164",
    "addr:housenumber":"901",
    "addr:postcode":"98164",
    "addr:street":"5Th Ave Ste 3850",
    "iso:country":"US",
    "sg:address":"901 5th Ave Ste 3850",
    "sg:city":"Seattle",
    "sg:classifiers":[
        {
            "category":"Professional",
            "subcategory":"Employment Agencies",
            "type":"Services"
        }
    ],
    "sg:phone":"+1 206 622 6323",
    "sg:postcode":"98164",
    "sg:province":"WA",
    "wof:name":"Lab Support On Assignment",
    "wof:placetype":"venue"
},
  "geometry": {"coordinates":[-122.331423,47.605895],"type":"Point"}
}