{
  "type": "Feature",
  "properties": {
    "addr:full":"2417 Pacific Ave SE Olympia WA 98501",
    "addr:housenumber":"2417",
    "addr:postcode":"98501",
    "addr:street":"Pacific Ave Se",
    "iso:country":"US",
    "sg:address":"2417 Pacific Ave SE",
    "sg:city":"Olympia",
    "sg:classifiers":[
        {
            "category":"Professional",
            "subcategory":"Management & Consulting",
            "type":"Services"
        }
    ],
    "sg:phone":"+1 360 943 6635",
    "sg:postcode":"98501",
    "sg:province":"WA",
    "sg:tags":[
        "consultant",
        "business"
    ],
    "wof:name":"Morris & Assoc",
    "wof:placetype":"venue"
},
  "geometry": {"coordinates":[-122.867454,47.045185],"type":"Point"}
}