{
  "type": "Feature",
  "properties": {
    "addr:full":"1304 Division Ave Tacoma WA 98403",
    "addr:housenumber":"1304",
    "addr:postcode":"98403",
    "addr:street":"Division Ave",
    "iso:country":"US",
    "sg:address":"1304 Division Ave",
    "sg:city":"Tacoma",
    "sg:classifiers":[
        {
            "category":"Retail",
            "subcategory":"Portrait Studio",
            "type":"Services"
        }
    ],
    "sg:phone":"+1 253 573 3000",
    "sg:postcode":"98403",
    "sg:province":"WA",
    "sg:tags":[
        "photographer",
        "photo"
    ],
    "wof:name":"Chris Springer Photography",
    "wof:placetype":"venue"
},
  "geometry": {"coordinates":[-122.455512,47.259943],"type":"Point"}
}