{
  "type": "Feature",
  "properties": {
    "addr:full":"19953 Ballinger Way NE Shoreline WA 98155",
    "addr:housenumber":"19953",
    "addr:postcode":"98155",
    "addr:street":"Ballinger Way Ne",
    "iso:country":"US",
    "sg:address":"19953 Ballinger Way NE",
    "sg:city":"Shoreline",
    "sg:classifiers":[
        {
            "category":"Restaurant",
            "type":"Food & Drink"
        }
    ],
    "sg:phone":"+1 206 363 5051",
    "sg:postcode":"98155",
    "sg:province":"WA",
    "sg:tags":[
        "mexican"
    ],
    "wof:name":"Tido Mexico",
    "wof:placetype":"venue"
},
  "geometry": {"coordinates":[-122.30841100000001,47.773891],"type":"Point"}
}