{
  "type": "Feature",
  "properties": {
    "addr:full":"13659 Cedar Glen Ln SE Olalla WA 98359",
    "addr:housenumber":"13659",
    "addr:postcode":"98359",
    "addr:street":"Cedar Glen Ln Se",
    "iso:country":"US",
    "sg:address":"13659 Cedar Glen Ln SE",
    "sg:city":"Olalla",
    "sg:classifiers":[
        {
            "category":"Recreation",
            "type":"Entertainment"
        }
    ],
    "sg:phone":"+1 253 857 7506",
    "sg:postcode":"98359",
    "sg:province":"WA",
    "sg:tags":[
        "stable"
    ],
    "wof:name":"Pets Galore Horseback Rides",
    "wof:placetype":"venue"
},
  "geometry": {"coordinates":[-122.587405,47.427243],"type":"Point"}
}