{
  "type": "Feature",
  "properties": {
    "iso:country":"US",
    "sg:address":"9806 270th St NW",
    "sg:city":"Stanwood",
    "sg:classifiers":[
        {
            "category":"Professional",
            "subcategory":"Business Services",
            "type":"Services"
        }
    ],
    "sg:phone":"+1 360 629 2502",
    "sg:postcode":"98292",
    "sg:province":"WA",
    "wof:name":"Rapattoni Gis",
    "wof:placetype":"venue"
},
  "geometry": {"coordinates":[-122.365944,48.241557],"type":"Point"}
}