{
  "type": "Feature",
  "properties": {
    "iso:country":"US",
    "sg:address":"3003 Judson St",
    "sg:city":"Gig Harbor",
    "sg:classifiers":[
        {
            "category":"Real Estate",
            "subcategory":"Real Estate Agent",
            "type":"Services"
        }
    ],
    "sg:phone":"+1 253 858 9607",
    "sg:postcode":"98335",
    "sg:province":"WA",
    "sg:tags":[
        "appraiser"
    ],
    "wof:name":"Brookes/Blaine Appraisal Svc",
    "wof:placetype":"venue"
},
  "geometry": {"coordinates":[-122.57993,47.328077],"type":"Point"}
}