{
  "type": "Feature",
  "properties": {
    "addr:full":"1608 23rd Ave Longview WA 98632",
    "addr:housenumber":"1608",
    "addr:postcode":"98632",
    "addr:street":"23Rd Ave",
    "iso:country":"US",
    "sg:address":"1608 23rd Ave",
    "sg:city":"Longview",
    "sg:classifiers":[
        {
            "category":"Building & Trades",
            "subcategory":"Construction",
            "type":"Services"
        }
    ],
    "sg:phone":"+1 360 352 6295",
    "sg:postcode":"98632",
    "sg:province":"WA",
    "sg:tags":[
        "contractor"
    ],
    "wof:name":"Roof Guyz",
    "wof:placetype":"venue"
},
  "geometry": {"coordinates":[-122.94508500000001,46.145382],"type":"Point"}
}