{
  "type": "Feature",
  "properties": {
    "addr:full":"205 Columbia St Seattle WA 98104",
    "addr:housenumber":"205",
    "addr:postcode":"98104",
    "addr:street":"Columbia St",
    "iso:country":"US",
    "sg:address":"205 Columbia St",
    "sg:city":"Seattle",
    "sg:classifiers":[
        {
            "category":"Real Estate",
            "subcategory":"Real Estate Agent",
            "type":"Services"
        }
    ],
    "sg:phone":"+1 206 623 8809",
    "sg:postcode":"98104",
    "sg:province":"WA",
    "wof:name":"National Bldg M Smith",
    "wof:placetype":"venue"
},
  "geometry": {"coordinates":[-122.332801,47.604072],"type":"Point"}
}