{
  "type": "Feature",
  "properties": {
    "addr:full":"5172 State Rte 194 Colfax WA 99111",
    "addr:housenumber":"5172",
    "addr:postcode":"99111",
    "addr:street":"State Rte 194",
    "iso:country":"US",
    "sg:address":"5172 State Rte 194",
    "sg:city":"Colfax",
    "sg:phone":"+1 509 397 3376",
    "sg:postcode":"99111",
    "sg:province":"WA",
    "sg:tags":[
        "farm",
        "wheat"
    ],
    "wof:name":"Buck C Lavon",
    "wof:placetype":"venue"
},
  "geometry": {"coordinates":[-117.45805799999999,46.752044],"type":"Point"}
}