{
  "type": "Feature",
  "properties": {
    "addr:full":"13256 NE 20th St Ste 17 Bellevue WA 98005",
    "addr:housenumber":"13256",
    "addr:postcode":"98005",
    "addr:street":"Ne 20Th St Ste 17",
    "iso:country":"US",
    "sg:address":"13256 NE 20th St Ste 17",
    "sg:city":"Bellevue",
    "sg:classifiers":[
        {
            "category":"Banks & Credit Unions",
            "subcategory":"Financial Services",
            "type":"Services"
        }
    ],
    "sg:phone":"+1 425 373 5033",
    "sg:postcode":"98005",
    "sg:province":"WA",
    "sg:tags":[
        "broker",
        "mortgage"
    ],
    "wof:name":"Choice Mortgage One",
    "wof:placetype":"venue"
},
  "geometry": {"coordinates":[-122.16300200000001,47.628101],"type":"Point"}
}