{
  "type": "Feature",
  "properties": {
    "addr:full":"17408 36th Ave E Tacoma WA 98446",
    "addr:housenumber":"17408",
    "addr:postcode":"98446",
    "addr:street":"36Th Ave E",
    "iso:country":"US",
    "sg:address":"17408 36th Ave E",
    "sg:city":"Tacoma",
    "sg:classifiers":[
        {
            "category":"Education",
            "subcategory":"School",
            "type":"Public Place"
        }
    ],
    "sg:phone":"+1 253 537 9339",
    "sg:postcode":"98446",
    "sg:province":"WA",
    "wof:name":"Cascade Christian Schools",
    "wof:placetype":"venue"
},
  "geometry": {"coordinates":[-122.381073,47.099598],"type":"Point"}
}