{
  "type": "Feature",
  "properties": {
    "addr:full":"210 NE Hill Rd Belfair WA 98528",
    "addr:housenumber":"210",
    "addr:postcode":"98528",
    "addr:street":"Ne Hill Rd",
    "iso:country":"US",
    "sg:address":"210 NE Hill Rd",
    "sg:city":"Belfair",
    "sg:classifiers":[
        {
            "category":"Retail",
            "subcategory":"Auto Repair",
            "type":"Services"
        }
    ],
    "sg:phone":"+1 360 275 3685",
    "sg:postcode":"98528",
    "sg:province":"WA",
    "sg:tags":[
        "general"
    ],
    "wof:name":"Raines Auto Repair",
    "wof:placetype":"venue"
},
  "geometry": {"coordinates":[-122.820864,47.474702],"type":"Point"}
}