{
  "type": "Feature",
  "properties": {
    "addr:full":"7830 Timber Hill Dr Everett WA 98203",
    "addr:housenumber":"7830",
    "addr:postcode":"98203",
    "addr:street":"Timber Hill Dr",
    "iso:country":"US",
    "sg:address":"7830 Timber Hill Dr",
    "sg:city":"Everett",
    "sg:classifiers":[
        {
            "category":"Building & Trades",
            "subcategory":"Construction",
            "type":"Services"
        }
    ],
    "sg:phone":"+1 425 347 1371",
    "sg:postcode":"98203",
    "sg:province":"WA",
    "sg:tags":[
        "contractor"
    ],
    "wof:name":"Sheppard Construction",
    "wof:placetype":"venue"
},
  "geometry": {"coordinates":[-122.20104000000001,47.92642],"type":"Point"}
}