{
  "type": "Feature",
  "properties": {
    "iso:country":"US",
    "sg:address":"14715 Pacific Ave S",
    "sg:city":"Tacoma",
    "sg:classifiers":[
        {
            "category":"Building & Trades",
            "subcategory":"Cleaning & Sanitation",
            "type":"Services"
        }
    ],
    "sg:phone":"+1 253 548 0948",
    "sg:postcode":"98444",
    "sg:province":"WA",
    "sg:tags":[
        "apartment",
        "remodeling",
        "maintenance"
    ],
    "wof:name":"Back To Basics Maint & Cons",
    "wof:placetype":"venue"
},
  "geometry": {"coordinates":[-122.434777,47.123356],"type":"Point"}
}