{
  "type": "Feature",
  "properties": {
    "addr:full":"364 N 1st St Kalama WA 98625",
    "addr:housenumber":"364",
    "addr:postcode":"98625",
    "addr:street":"N 1St St",
    "iso:country":"US",
    "sg:address":"364 N 1st St",
    "sg:city":"Kalama",
    "sg:classifiers":[
        {
            "category":"Shopping",
            "subcategory":"Used Merchandise",
            "type":"Retail Goods"
        }
    ],
    "sg:phone":"+1 360 673 5400",
    "sg:postcode":"98625",
    "sg:province":"WA",
    "sg:tags":[
        "antique"
    ],
    "wof:name":"Columbia Antiques & Cllctbls",
    "wof:placetype":"venue"
},
  "geometry": {"coordinates":[-122.84540200000001,46.009997],"type":"Point"}
}