{
  "type": "Feature",
  "properties": {
    "addr:full":"620 112th St SE Unit 114 Everett WA 98208",
    "addr:housenumber":"620;114",
    "addr:postcode":"98208",
    "addr:street":"112Th St Se Unit",
    "iso:country":"US",
    "sg:address":"620 112th St SE Unit 114",
    "sg:city":"Everett",
    "sg:classifiers":[
        {
            "category":"Real Estate",
            "subcategory":"Real Estate Services",
            "type":"Services"
        }
    ],
    "sg:phone":"+1 425 355 5292",
    "sg:postcode":"98208",
    "sg:province":"WA",
    "sg:tags":[
        "inspection"
    ],
    "wof:name":"Interactive Enterprises",
    "wof:placetype":"venue"
},
  "geometry": {"coordinates":[-122.223732,47.896488],"type":"Point"}
}