{
  "type": "Feature",
  "properties": {
    "addr:full":"3807 14th Ave W Seattle WA 98119",
    "addr:housenumber":"3807",
    "addr:postcode":"98119",
    "addr:street":"14Th Ave W",
    "iso:country":"US",
    "sg:address":"3807 14th Ave W",
    "sg:city":"Seattle",
    "sg:classifiers":[
        {
            "category":"Restaurant",
            "type":"Food & Drink"
        },
        {
            "category":"Food & Beverages",
            "subcategory":"Meat & Fish",
            "type":"Retail Goods"
        }
    ],
    "sg:phone":"+1 206 285 4904",
    "sg:postcode":"98119",
    "sg:province":"WA",
    "sg:tags":[
        "seafood",
        "seafood-wholesale",
        "market"
    ],
    "wof:name":"North Point Seafood",
    "wof:placetype":"venue"
},
  "geometry": {"coordinates":[-122.37490099999999,47.654083],"type":"Point"}
}