{
  "type": "Feature",
  "properties": {
    "addr:full":"7122 Jennie Ln Spokane WA 99212",
    "addr:postcode":"7122;99212",
    "addr:street":"Jennie Ln",
    "iso:country":"US",
    "sg:address":"7122 Jennie Ln",
    "sg:city":"Spokane",
    "sg:classifiers":[
        {
            "category":"Retail",
            "subcategory":"Laundry & Dry Cleaning",
            "type":"Services"
        }
    ],
    "sg:phone":"+1 509 535 3583",
    "sg:postcode":"99212",
    "sg:province":"WA",
    "sg:tags":[
        "drycleaning",
        "plant"
    ],
    "wof:name":"Elite",
    "wof:placetype":"venue"
},
  "geometry": {"coordinates":[-117.296741,47.63104],"type":"Point"}
}