{
  "type": "Feature",
  "properties": {
    "addr:full":"6505 W Soledad Ln Cheney WA 99004",
    "addr:housenumber":"6505",
    "addr:postcode":"99004",
    "addr:street":"W Soledad Ln",
    "iso:country":"US",
    "sg:address":"6505 W Soledad Ln",
    "sg:city":"Cheney",
    "sg:classifiers":[
        {
            "category":"Professional",
            "subcategory":"Computer Services",
            "type":"Services"
        }
    ],
    "sg:phone":"+1 509 235 8439",
    "sg:postcode":"99004",
    "sg:province":"WA",
    "sg:tags":[
        "consultant",
        "designer"
    ],
    "wof:name":"Computer Golf Systems",
    "wof:placetype":"venue"
},
  "geometry": {"coordinates":[-117.505379,47.423839],"type":"Point"}
}