{
  "type": "Feature",
  "properties": {
    "addr:full":"301 NW 82nd St Seattle WA 98117",
    "addr:housenumber":"301",
    "addr:postcode":"98117",
    "addr:street":"Nw 82Nd St",
    "iso:country":"US",
    "sg:address":"301 NW 82nd St",
    "sg:city":"Seattle",
    "sg:classifiers":[
        {
            "category":"Shopping",
            "subcategory":"Clothing, Apparel, & Fashions",
            "type":"Retail Goods"
        }
    ],
    "sg:phone":"+1 206 782 5332",
    "sg:postcode":"98117",
    "sg:province":"WA",
    "sg:tags":[
        "theatrical",
        "costume"
    ],
    "wof:name":"Gala Costumes",
    "wof:placetype":"venue"
},
  "geometry": {"coordinates":[-122.363325,47.688384],"type":"Point"}
}