{
  "type": "Feature",
  "properties": {
    "addr:full":"21611 116th St SE Snohomish WA 98290",
    "addr:housenumber":"21611",
    "addr:postcode":"98290",
    "addr:street":"116Th St Se",
    "iso:country":"US",
    "sg:address":"21611 116th St SE",
    "sg:city":"Snohomish",
    "sg:classifiers":[
        {
            "category":"Recreation",
            "type":"Entertainment"
        }
    ],
    "sg:phone":"+1 360 794 3800",
    "sg:postcode":"98290",
    "sg:province":"WA",
    "sg:tags":[
        "stable"
    ],
    "wof:name":"Academy Of Horsemanship",
    "wof:placetype":"venue"
},
  "geometry": {"coordinates":[-121.93934400000001,47.892441],"type":"Point"}
}