{
  "type": "Feature",
  "properties": {
    "addr:full":"5317 S Palouse Hwy Spokane WA 99223",
    "addr:housenumber":"5317",
    "addr:postcode":"99223",
    "addr:street":"S Palouse Hwy",
    "iso:country":"US",
    "sg:address":"5317 S Palouse Hwy",
    "sg:city":"Spokane",
    "sg:classifiers":[
        {
            "category":"Real Estate",
            "subcategory":"Real Estate Operator",
            "type":"Services"
        }
    ],
    "sg:phone":"+1 509 443 8789",
    "sg:postcode":"99223",
    "sg:province":"WA",
    "sg:tags":[
        "apartment"
    ],
    "wof:name":"Hilby Station",
    "wof:placetype":"venue"
},
  "geometry": {"coordinates":[-117.35422199999999,47.604168],"type":"Point"}
}