{
  "type": "Feature",
  "properties": {
    "addr:full":"12504 Gilbert Rd Yakima WA 98903",
    "addr:housenumber":"12504",
    "addr:postcode":"98903",
    "addr:street":"Gilbert Rd",
    "iso:country":"US",
    "sg:address":"12504 Gilbert Rd",
    "sg:city":"Yakima",
    "sg:classifiers":[
        {
            "category":"Organizations",
            "subcategory":"Religious Organization",
            "type":"Services"
        }
    ],
    "sg:phone":"+1 509 966 2383",
    "sg:postcode":"98903",
    "sg:province":"WA",
    "sg:website":"www.wileyheightscovenant.org",
    "wof:name":"Wiley Heights Covenant Church",
    "wof:placetype":"venue"
},
  "geometry": {"coordinates":[-120.670693,46.551411],"type":"Point"}
}