{
  "type": "Feature",
  "properties": {
    "addr:full":"10808 S Gardner Rd Cheney WA 99004",
    "addr:housenumber":"10808",
    "addr:postcode":"99004",
    "addr:street":"S Gardner Rd",
    "iso:country":"US",
    "sg:address":"10808 S Gardner Rd",
    "sg:city":"Cheney",
    "sg:classifiers":[
        {
            "category":"Insurance",
            "subcategory":"Insurance Agent",
            "type":"Services"
        }
    ],
    "sg:phone":"+1 509 448 3849",
    "sg:postcode":"99004",
    "sg:province":"WA",
    "wof:name":"Jerry Rowley Financial Services",
    "wof:placetype":"venue"
},
  "geometry": {"coordinates":[-117.486422,47.554153],"type":"Point"}
}