{
  "type": "Feature",
  "properties": {
    "addr:full":"3015 Colby Ave Everett WA 98201",
    "addr:housenumber":"3015",
    "addr:postcode":"98201",
    "addr:street":"Colby Ave",
    "iso:country":"US",
    "sg:address":"3015 Colby Ave",
    "sg:city":"Everett",
    "sg:classifiers":[
        {
            "category":"Professional",
            "subcategory":"Lawyer & Legal Services",
            "type":"Services"
        }
    ],
    "sg:phone":"+1 425 258 1924",
    "sg:postcode":"98201",
    "sg:province":"WA",
    "sg:tags":[
        "attorney"
    ],
    "wof:name":"Brian K Hammer Law Office",
    "wof:placetype":"venue"
},
  "geometry": {"coordinates":[-122.20846,47.97672],"type":"Point"}
}