{
  "type": "Feature",
  "properties": {
    "iso:country":"US",
    "sg:address":"13705 Bel Red Rd",
    "sg:city":"Bellevue",
    "sg:classifiers":[
        {
            "category":"Professional",
            "subcategory":"Management & Consulting",
            "type":"Services"
        }
    ],
    "sg:phone":"+1 425 747 0748",
    "sg:postcode":"98005",
    "sg:province":"WA",
    "sg:tags":[
        "consultant",
        "educational"
    ],
    "wof:name":"Diane Dorow Educational Cnslnt",
    "wof:placetype":"venue"
},
  "geometry": {"coordinates":[-122.155142,47.624004],"type":"Point"}
}