{
  "type": "Feature",
  "properties": {
    "iso:country":"US",
    "sg:address":"1504 S Latawah St",
    "sg:city":"Spokane",
    "sg:classifiers":[
        {
            "category":"Building & Trades",
            "subcategory":"Electrical",
            "type":"Services"
        }
    ],
    "sg:phone":"+1 509 456 6902",
    "sg:postcode":"99203",
    "sg:province":"WA",
    "sg:tags":[
        "installation"
    ],
    "wof:name":"Anthony D Sebastian Svc",
    "wof:placetype":"venue"
},
  "geometry": {"coordinates":[-117.40531900000001,47.641978],"type":"Point"}
}