{
  "type": "Feature",
  "properties": {
    "addr:full":"2612 Main St Union Gap WA 98903",
    "addr:housenumber":"2612",
    "addr:postcode":"98903",
    "addr:street":"Main St",
    "iso:country":"US",
    "sg:address":"2612 Main St",
    "sg:city":"Union Gap",
    "sg:classifiers":[
        {
            "category":"Autos & Motor Vehicles",
            "subcategory":"Auto Supplies",
            "type":"Retail Goods"
        }
    ],
    "sg:phone":"+1 509 248 3523",
    "sg:postcode":"98903",
    "sg:province":"WA",
    "sg:tags":[
        "tire"
    ],
    "wof:name":"Frank's Tire Store",
    "wof:placetype":"venue"
},
  "geometry": {"coordinates":[-120.47875000000001,46.562477],"type":"Point"}
}