{
  "type": "Feature",
  "properties": {
    "addr:full":"167 Case Rd Oak Harbor WA 98277",
    "addr:housenumber":"167",
    "addr:postcode":"98277",
    "addr:street":"Case Rd",
    "iso:country":"US",
    "sg:address":"167 Case Rd",
    "sg:city":"Oak Harbor",
    "sg:classifiers":[
        {
            "category":"Organizations",
            "subcategory":"Community Association",
            "type":"Services"
        }
    ],
    "sg:phone":"+1 360 675 2510",
    "sg:postcode":"98277",
    "sg:province":"WA",
    "wof:name":"Independent Order Odd Fellows",
    "wof:placetype":"venue"
},
  "geometry": {"coordinates":[-122.625884,48.318341],"type":"Point"}
}