{
  "type": "Feature",
  "properties": {
    "iso:country":"US",
    "sg:address":"19009 62nd Ave NE",
    "sg:city":"Arlington",
    "sg:classifiers":[
        {
            "category":"Manufacturing",
            "subcategory":"Tools & Machinery",
            "type":"Manufacturing & Wholesale Goods"
        }
    ],
    "sg:phone":"+1 360 435 6030",
    "sg:postcode":"98223",
    "sg:province":"WA",
    "sg:tags":[
        "equipment",
        "conversion",
        "electronic",
        "power",
        "mfg"
    ],
    "wof:name":"Outback Power Systems Inc",
    "wof:placetype":"venue"
},
  "geometry": {"coordinates":[-122.1482,48.170253],"type":"Point"}
}