{
  "type": "Feature",
  "properties": {
    "addr:full":"14184 NE Woodinville Duvall Rd Woodinville WA 98072",
    "addr:housenumber":"14184",
    "addr:postcode":"98072",
    "addr:street":"Ne Woodinville Duvall Rd",
    "iso:country":"US",
    "sg:address":"14184 NE Woodinville Duvall Rd",
    "sg:city":"Woodinville",
    "sg:classifiers":[
        {
            "category":"Banks & Credit Unions",
            "subcategory":"Investment Brokerage",
            "type":"Services"
        },
        {
            "category":"Banks & Credit Unions",
            "subcategory":"Bank",
            "type":"Services"
        },
        {
            "category":"Banks & Credit Unions",
            "subcategory":"Financial Services",
            "type":"Services"
        }
    ],
    "sg:phone":"+1 877 900 7057",
    "sg:postcode":"98072",
    "sg:province":"WA",
    "sg:tags":[
        "advisory",
        "mutual",
        "retirement",
        "annuity",
        "broker",
        "fund",
        "planning",
        "plan",
        "consultant",
        "security",
        "bond",
        "insurance",
        "stock"
    ],
    "sg:website":"http://edwardjones.com",
    "wof:name":"Edward Jones - BERT MILLS",
    "wof:placetype":"venue"
},
  "geometry": {"coordinates":[-122.150272,47.754732],"type":"Point"}
}