{
  "type": "Feature",
  "properties": {
    "addr:full":"14603 35th Ave S Tukwila WA 98168",
    "addr:housenumber":"14603",
    "addr:postcode":"98168",
    "addr:street":"35Th Ave S",
    "iso:country":"US",
    "sg:address":"14603 35th Ave S",
    "sg:city":"Tukwila",
    "sg:classifiers":[
        {
            "category":"Personal",
            "type":"Services"
        },
        {
            "category":"Professional",
            "type":"Services"
        },
        {
            "category":"Shopping",
            "subcategory":"Party Supplies",
            "type":"Retail Goods"
        },
        {
            "category":"Personal",
            "subcategory":"Skin Care",
            "type":"Services"
        }
    ],
    "sg:phone":"+1 206 246 2292",
    "sg:postcode":"98168",
    "sg:province":"WA",
    "sg:tags":[
        "linen",
        "favors",
        "entertainment",
        "children's",
        "planning",
        "event"
    ],
    "sg:website":"http://www.expresslinenservice.com",
    "wof:name":"Express Linen Service, LLC",
    "wof:placetype":"venue"
},
  "geometry": {"coordinates":[-122.28831700000001,47.472273],"type":"Point"}
}