{
  "type": "Feature",
  "properties": {
    "addr:full":"1604 149th Pl SE Bellevue WA 98007",
    "addr:housenumber":"1604",
    "addr:postcode":"98007",
    "addr:street":"149Th Pl Se",
    "iso:country":"US",
    "sg:address":"1604 149th Pl SE",
    "sg:city":"Bellevue",
    "sg:classifiers":[
        {
            "category":"Professional",
            "subcategory":"Lawyer & Legal Services",
            "type":"Services"
        }
    ],
    "sg:phone":"+1 425 641 7092",
    "sg:postcode":"98007",
    "sg:province":"WA",
    "wof:name":"Deepak A Katara Attorney",
    "wof:placetype":"venue"
},
  "geometry": {"coordinates":[-122.140596,47.595731],"type":"Point"}
}