{
  "type": "Feature",
  "properties": {
    "addr:full":"24012 NE 132nd Ave Battle Ground WA 98604",
    "addr:housenumber":"24012",
    "addr:postcode":"98604",
    "addr:street":"Ne 132Nd Ave",
    "iso:country":"US",
    "sg:address":"24012 NE 132nd Ave",
    "sg:city":"Battle Ground",
    "sg:classifiers":[
        {
            "category":"Professional",
            "subcategory":"Engineering",
            "type":"Services"
        }
    ],
    "sg:phone":"+1 360 666 0055",
    "sg:postcode":"98604",
    "sg:province":"WA",
    "sg:tags":[
        "engineer"
    ],
    "wof:name":"Cooper Zietz Engineers Inc",
    "wof:placetype":"venue"
},
  "geometry": {"coordinates":[-122.53715099999999,45.796048],"type":"Point"}
}