{
  "type": "Feature",
  "properties": {
    "addr:full":"2704 E Everett Ave Spokane WA 99217",
    "addr:housenumber":"2704",
    "addr:postcode":"99217",
    "addr:street":"E Everett Ave",
    "iso:country":"US",
    "sg:address":"2704 E Everett Ave",
    "sg:city":"Spokane",
    "sg:classifiers":[
        {
            "category":"Real Estate",
            "subcategory":"Real Estate Agent",
            "type":"Services"
        }
    ],
    "sg:phone":"+1 509 484 1074",
    "sg:postcode":"99217",
    "sg:province":"WA",
    "wof:name":"Scott D Marion Properties",
    "wof:placetype":"venue"
},
  "geometry": {"coordinates":[-117.368211,47.705737],"type":"Point"}
}