{
  "type": "Feature",
  "properties": {
    "addr:full":"17241 SE 272nd St Covington WA 98042",
    "addr:postcode":"17241;98042",
    "addr:street":"Se 272Nd St",
    "iso:country":"US",
    "sg:address":"17241 SE 272nd St",
    "sg:city":"Covington",
    "sg:classifiers":[
        {
            "category":"Shopping",
            "subcategory":"Pharmacy",
            "type":"Retail Goods"
        }
    ],
    "sg:phone":"+1 253 631 1200",
    "sg:postcode":"98042",
    "sg:province":"WA",
    "sg:tags":[
        "drug",
        "store"
    ],
    "wof:name":"Covington Pharmacy Inc",
    "wof:placetype":"venue"
},
  "geometry": {"coordinates":[-122.11126299999999,47.358104],"type":"Point"}
}