{
  "type": "Feature",
  "properties": {
    "addr:full":"12717 4th Ave W Everett WA 98204",
    "addr:housenumber":"12717",
    "addr:postcode":"98204",
    "addr:street":"4Th Ave W",
    "iso:country":"US",
    "sg:address":"12717 4th Ave W",
    "sg:city":"Everett",
    "sg:classifiers":[
        {
            "category":"Cinema",
            "subcategory":"Movie Rental",
            "type":"Entertainment"
        }
    ],
    "sg:phone":"+1 425 267 9735",
    "sg:postcode":"98204",
    "sg:province":"WA",
    "sg:tags":[
        "video",
        "tape"
    ],
    "wof:name":"Blockbuster",
    "wof:placetype":"venue"
},
  "geometry": {"coordinates":[-122.238739,47.882848],"type":"Point"}
}