{
  "type": "Feature",
  "properties": {
    "iso:country":"US",
    "sg:address":"3230 Herren Ave",
    "sg:city":"Bremerton",
    "sg:classifiers":[
        {
            "category":"Autos & Motor Vehicles",
            "subcategory":"Auto Supplies",
            "type":"Retail Goods"
        }
    ],
    "sg:phone":"+1 360 373 1278",
    "sg:postcode":"98310",
    "sg:province":"WA",
    "wof:name":"Got Torque",
    "wof:placetype":"venue"
},
  "geometry": {"coordinates":[-122.63014,47.593779],"type":"Point"}
}