{
  "type": "Feature",
  "properties": {
    "addr:full":"2501 Fairview Ave E Seattle WA 98102",
    "addr:housenumber":"2501",
    "addr:postcode":"98102",
    "addr:street":"Fairview Ave E",
    "iso:country":"US",
    "sg:address":"2501 Fairview Ave E",
    "sg:city":"Seattle",
    "sg:classifiers":[
        {
            "category":"Restaurant",
            "type":"Food & Drink"
        }
    ],
    "sg:phone":"+1 206 325 7111",
    "sg:postcode":"98102",
    "sg:province":"WA",
    "wof:name":"Cafe Ambrosia",
    "wof:placetype":"venue"
},
  "geometry": {"coordinates":[-122.329483,47.640905],"type":"Point"}
}