{
  "type": "Feature",
  "properties": {
    "addr:full":"8015 N Stephanie St Spokane WA 99208",
    "addr:housenumber":"8015",
    "addr:postcode":"99208",
    "addr:street":"N Stephanie St",
    "iso:country":"US",
    "sg:address":"8015 N Stephanie St",
    "sg:city":"Spokane",
    "sg:classifiers":[
        {
            "category":"Real Estate",
            "subcategory":"Real Estate Agent",
            "type":"Services"
        }
    ],
    "sg:phone":"+1 509 326 4130",
    "sg:postcode":"99208",
    "sg:province":"WA",
    "wof:name":"Lembeck Appraisal & Consulting",
    "wof:placetype":"venue"
},
  "geometry": {"coordinates":[-117.488275,47.732406],"type":"Point"}
}