{
  "type": "Feature",
  "properties": {
    "addr:full":"5310 W Monroe Rd Deer Park WA 99006",
    "addr:housenumber":"5310",
    "addr:postcode":"99006",
    "addr:street":"W Monroe Rd",
    "iso:country":"US",
    "sg:address":"5310 W Monroe Rd",
    "sg:city":"Deer Park",
    "sg:classifiers":[
        {
            "category":"Retail",
            "subcategory":"Portrait Studio",
            "type":"Services"
        }
    ],
    "sg:phone":"+1 509 262 9700",
    "sg:postcode":"99006",
    "sg:province":"WA",
    "sg:tags":[
        "photo"
    ],
    "wof:name":"Rosewood Photography",
    "wof:placetype":"venue"
},
  "geometry": {"coordinates":[-117.488274,47.954076],"type":"Point"}
}