{
  "type": "Feature",
  "properties": {
    "addr:full":"1721 Benson Rd Point Roberts WA 98281",
    "addr:housenumber":"1721",
    "addr:postcode":"98281",
    "addr:street":"Benson Rd",
    "iso:country":"US",
    "sg:address":"1721 Benson Rd",
    "sg:city":"Point Roberts",
    "sg:classifiers":[
        {
            "category":"Building & Trades",
            "subcategory":"Construction",
            "type":"Services"
        }
    ],
    "sg:phone":"+1 360 945 1053",
    "sg:postcode":"98281",
    "sg:province":"WA",
    "sg:tags":[
        "hanging",
        "contractor"
    ],
    "wof:name":"AC Custom Painting",
    "wof:placetype":"venue"
},
  "geometry": {"coordinates":[-123.06116299999999,48.988341],"type":"Point"}
}