{
  "type": "Feature",
  "properties": {
    "addr:full":"4416 W Court St Pasco WA 99301",
    "addr:housenumber":"4416",
    "addr:postcode":"99301",
    "addr:street":"W Court St",
    "iso:country":"US",
    "sg:address":"4416 W Court St",
    "sg:city":"Pasco",
    "sg:classifiers":[
        {
            "category":"Professional",
            "subcategory":"Accounting & Tax Preparation",
            "type":"Services"
        }
    ],
    "sg:phone":"+1 509 547 5525",
    "sg:postcode":"99301",
    "sg:province":"WA",
    "sg:tags":[
        "firm"
    ],
    "wof:name":"William Wilkins",
    "wof:placetype":"venue"
},
  "geometry": {"coordinates":[-119.15021900000001,46.241493],"type":"Point"}
}