{
  "type": "Feature",
  "properties": {
    "iso:country":"US",
    "sg:address":"2611 N Stevens St",
    "sg:city":"Tacoma",
    "sg:classifiers":[
        {
            "category":"Health Services",
            "subcategory":"Chiropractor",
            "type":"Services"
        }
    ],
    "sg:phone":"+1 253 759 1566",
    "sg:postcode":"98407",
    "sg:province":"WA",
    "wof:name":"Randy K Eaton DC",
    "wof:placetype":"venue"
},
  "geometry": {"coordinates":[-122.49612500000001,47.271896],"type":"Point"}
}