{
  "type": "Feature",
  "properties": {
    "addr:full":"3421 N Machias Rd Lake Stevens WA 98258",
    "addr:housenumber":"3421",
    "addr:postcode":"98258",
    "addr:street":"N Machias Rd",
    "iso:country":"US",
    "sg:address":"3421 N Machias Rd",
    "sg:city":"Lake Stevens",
    "sg:classifiers":[
        {
            "category":"Shopping",
            "subcategory":"Hobbies, Toys, & Games",
            "type":"Retail Goods"
        }
    ],
    "sg:phone":"+1 425 334 6969",
    "sg:postcode":"98258",
    "sg:province":"WA",
    "wof:name":"Finders Keepers",
    "wof:placetype":"venue"
},
  "geometry": {"coordinates":[-122.05329500000001,48.027432],"type":"Point"}
}