{
  "type": "Feature",
  "properties": {
    "addr:full":"650 NW Lafayette St Chehalis WA 98532",
    "addr:housenumber":"650",
    "addr:postcode":"98532",
    "addr:street":"Nw Lafayette St",
    "iso:country":"US",
    "sg:address":"650 NW Lafayette St",
    "sg:city":"Chehalis",
    "sg:classifiers":[
        {
            "category":"Home & Garden",
            "subcategory":"Furniture",
            "type":"Retail Goods"
        }
    ],
    "sg:phone":"+1 360 748 0116",
    "sg:postcode":"98532",
    "sg:province":"WA",
    "sg:tags":[
        "cabinet"
    ],
    "wof:name":"Palmer Lumber Millwork Div",
    "wof:placetype":"venue"
},
  "geometry": {"coordinates":[-122.976327,46.669503],"type":"Point"}
}