{
  "type": "Feature",
  "properties": {
    "addr:full":"1103 29th St Anacortes WA 98221",
    "addr:housenumber":"1103",
    "addr:postcode":"98221",
    "addr:street":"29Th St",
    "iso:country":"US",
    "sg:address":"1103 29th St",
    "sg:city":"Anacortes",
    "sg:classifiers":[
        {
            "category":"Real Estate",
            "subcategory":"Real Estate Operator",
            "type":"Services"
        }
    ],
    "sg:phone":"+1 360 293 1336",
    "sg:postcode":"98221",
    "sg:province":"WA",
    "sg:tags":[
        "building",
        "apartment"
    ],
    "wof:name":"Silverwood Senior Complex",
    "wof:placetype":"venue"
},
  "geometry": {"coordinates":[-122.616105,48.498769],"type":"Point"}
}