{
  "type": "Feature",
  "properties": {
    "addr:full":"27 W Indiana Ave Spokane WA 99205",
    "addr:housenumber":"27",
    "addr:postcode":"99205",
    "addr:street":"W Indiana Ave",
    "iso:country":"US",
    "sg:address":"27 W Indiana Ave",
    "sg:city":"Spokane",
    "sg:classifiers":[
        {
            "category":"Shopping",
            "subcategory":"Computers & Home Electronics",
            "type":"Retail Goods"
        }
    ],
    "sg:phone":"+1 509 328 0706",
    "sg:postcode":"99205",
    "sg:province":"WA",
    "sg:tags":[
        "equipment",
        "visual",
        "audio",
        "rental"
    ],
    "wof:name":"Inland Audio Visual Company",
    "wof:placetype":"venue"
},
  "geometry": {"coordinates":[-117.412369,47.674918],"type":"Point"}
}