{
  "type": "Feature",
  "properties": {
    "addr:full":"14925 Ambaum Boulevard SW Burien WA 98166",
    "addr:housenumber":"14925",
    "addr:postcode":"98166",
    "addr:street":"Ambaum Boulevard Sw",
    "iso:country":"US",
    "sg:address":"14925 Ambaum Boulevard SW",
    "sg:city":"Burien",
    "sg:classifiers":[
        {
            "category":"Retail",
            "subcategory":"Auto Repair",
            "type":"Services"
        }
    ],
    "sg:phone":"+1 206 243 2587",
    "sg:postcode":"98166",
    "sg:province":"WA",
    "wof:name":"Aaable Transmission",
    "wof:placetype":"venue"
},
  "geometry": {"coordinates":[-122.345974,47.46882],"type":"Point"}
}