{
  "type": "Feature",
  "properties": {
    "addr:full":"11219 NE 132nd St Kirkland WA 98034",
    "addr:housenumber":"11219",
    "addr:postcode":"98034",
    "addr:street":"Ne 132Nd St",
    "iso:country":"US",
    "sg:address":"11219 NE 132nd St",
    "sg:city":"Kirkland",
    "sg:classifiers":[
        {
            "category":"Building & Trades",
            "subcategory":"Construction",
            "type":"Services"
        }
    ],
    "sg:phone":"+1 425 821 2888",
    "sg:postcode":"98034",
    "sg:province":"WA",
    "sg:tags":[
        "drywall",
        "contractor"
    ],
    "wof:name":"Custom Hand Texturing",
    "wof:placetype":"venue"
},
  "geometry": {"coordinates":[-122.191332,47.718523],"type":"Point"}
}