{
  "type": "Feature",
  "properties": {
    "addr:full":"6824 189th Pl SW Lynnwood WA 98036",
    "addr:housenumber":"6824",
    "addr:postcode":"98036",
    "addr:street":"189Th Pl Sw",
    "iso:country":"US",
    "sg:address":"6824 189th Pl SW",
    "sg:city":"Lynnwood",
    "sg:classifiers":[
        {
            "category":"Professional",
            "subcategory":"Management & Consulting",
            "type":"Services"
        }
    ],
    "sg:phone":"+1 206 683 6814",
    "sg:postcode":"98036",
    "sg:province":"WA",
    "sg:tags":[
        "consultant",
        "general"
    ],
    "wof:name":"Mark McKay",
    "wof:placetype":"venue"
},
  "geometry": {"coordinates":[-122.32821199999999,47.827163],"type":"Point"}
}