{
  "type": "Feature",
  "properties": {
    "addr:full":"6069 Hannegan Rd Bellingham WA 98226",
    "addr:housenumber":"6069",
    "addr:postcode":"98226",
    "addr:street":"Hannegan Rd",
    "iso:country":"US",
    "sg:address":"6069 Hannegan Rd",
    "sg:city":"Bellingham",
    "sg:classifiers":[
        {
            "category":"Wholesale",
            "subcategory":"Seafood",
            "type":"Manufacturing & Wholesale Goods"
        }
    ],
    "sg:phone":"+1 360 398 7402",
    "sg:postcode":"98226",
    "sg:province":"WA",
    "sg:tags":[
        "food"
    ],
    "wof:name":"Salmon Etc",
    "wof:placetype":"venue"
},
  "geometry": {"coordinates":[-122.442882,48.856278],"type":"Point"}
}