{
  "type": "Feature",
  "properties": {
    "addr:full":"135 7th Ave Kirkland WA 98033",
    "addr:housenumber":"135",
    "addr:postcode":"98033",
    "addr:street":"7Th Ave",
    "iso:country":"US",
    "sg:address":"135 7th Ave",
    "sg:city":"Kirkland",
    "sg:classifiers":[
        {
            "category":"Shopping",
            "subcategory":"Musical Instruments",
            "type":"Retail Goods"
        }
    ],
    "sg:phone":"+1 425 836 3860",
    "sg:postcode":"98033",
    "sg:province":"WA",
    "sg:tags":[
        "piano",
        "organ"
    ],
    "sg:website":"http://www.wildespianos.com",
    "wof:name":"Wildes Pianos",
    "wof:placetype":"venue"
},
  "geometry": {"coordinates":[-122.207624,47.680407],"type":"Point"}
}