{
  "type": "Feature",
  "properties": {
    "addr:full":"3233 180th Pl SW Lynnwood WA 98037",
    "addr:housenumber":"3233",
    "addr:postcode":"98037",
    "addr:street":"180Th Pl Sw",
    "iso:country":"US",
    "sg:address":"3233 180th Pl SW",
    "sg:city":"Lynnwood",
    "sg:classifiers":[
        {
            "category":"Freight",
            "type":"Transportation"
        }
    ],
    "sg:phone":"+1 425 775 8725",
    "sg:postcode":"98037",
    "sg:province":"WA",
    "sg:tags":[
        "operator",
        "local",
        "trucking"
    ],
    "wof:name":"All Ports Trucking",
    "wof:placetype":"venue"
},
  "geometry": {"coordinates":[-122.277925,47.835077],"type":"Point"}
}