{
  "type": "Feature",
  "properties": {
    "addr:full":"251 E Clonakilty Ct Shelton WA 98584",
    "addr:housenumber":"251",
    "addr:postcode":"98584",
    "addr:street":"E Clonakilty Ct",
    "iso:country":"US",
    "sg:address":"251 E Clonakilty Ct",
    "sg:city":"Shelton",
    "sg:classifiers":[
        {
            "category":"Personal",
            "type":"Services"
        }
    ],
    "sg:phone":"+1 360 432 1939",
    "sg:postcode":"98584",
    "sg:province":"WA",
    "wof:name":"American Shake & Shingle",
    "wof:placetype":"venue"
},
  "geometry": {"coordinates":[-123.039935,47.282186],"type":"Point"}
}