{
  "type": "Feature",
  "properties": {
    "addr:full":"3039 N Monroe St Spokane WA 99205",
    "addr:housenumber":"3039",
    "addr:postcode":"99205",
    "addr:street":"N Monroe St",
    "iso:country":"US",
    "sg:address":"3039 N Monroe St",
    "sg:city":"Spokane",
    "sg:classifiers":[
        {
            "category":"Food & Beverages",
            "subcategory":"Groceries & Convenience Stores",
            "type":"Retail Goods"
        }
    ],
    "sg:phone":"+1 509 327 8112",
    "sg:postcode":"99205",
    "sg:province":"WA",
    "sg:tags":[
        "grocer"
    ],
    "wof:name":"Sure Save Grocery",
    "wof:placetype":"venue"
},
  "geometry": {"coordinates":[-117.426703,47.685538],"type":"Point"}
}