{
  "type": "Feature",
  "properties": {
    "iso:country":"US",
    "sg:address":"172 131st Ave NE",
    "sg:city":"Bellevue",
    "sg:classifiers":[
        {
            "category":"Professional",
            "subcategory":"Business Services",
            "type":"Services"
        }
    ],
    "sg:phone":"+1 425 454 2021",
    "sg:postcode":"98005",
    "sg:province":"WA",
    "sg:tags":[
        "interior",
        "designer",
        "decorator",
        "workroom"
    ],
    "sg:website":"www.bristaldesign.com",
    "wof:name":"Bristal Design Group Inc",
    "wof:placetype":"venue"
},
  "geometry": {"coordinates":[-122.16471900000001,47.612465],"type":"Point"}
}