{
  "type": "Feature",
  "properties": {
    "iso:country":"US",
    "sg:address":"2112 Simpson Ave",
    "sg:city":"Hoquiam",
    "sg:classifiers":[
        {
            "category":"Recreation",
            "type":"Entertainment"
        }
    ],
    "sg:phone":"+1 360 532 4483",
    "sg:postcode":"98550",
    "sg:province":"WA",
    "wof:name":"Harborena Roller Skating Rink",
    "wof:placetype":"venue"
},
  "geometry": {"coordinates":[-123.874134,46.975268],"type":"Point"}
}