{
  "type": "Feature",
  "properties": {
    "addr:full":"11003 SW Bank Rd Vashon WA 98070",
    "addr:housenumber":"11003",
    "addr:postcode":"98070",
    "addr:street":"Sw Bank Rd",
    "iso:country":"US",
    "sg:address":"11003 SW Bank Rd",
    "sg:city":"Vashon",
    "sg:classifiers":[
        {
            "category":"Home & Garden",
            "subcategory":"Garden Supply",
            "type":"Retail Goods"
        }
    ],
    "sg:phone":"+1 206 463 2735",
    "sg:postcode":"98070",
    "sg:province":"WA",
    "wof:name":"Augie Takatsuka",
    "wof:placetype":"venue"
},
  "geometry": {"coordinates":[-122.47470800000001,47.447259],"type":"Point"}
}