{
  "type": "Feature",
  "properties": {
    "addr:full":"308 E 28th St Apt C Vancouver WA 98663",
    "addr:housenumber":"308",
    "addr:postcode":"98663",
    "addr:street":"E 28Th St Apt C",
    "iso:country":"US",
    "sg:address":"308 E 28th St Apt C",
    "sg:city":"Vancouver",
    "sg:classifiers":[
        {
            "category":"Real Estate",
            "subcategory":"Real Estate Operator",
            "type":"Services"
        }
    ],
    "sg:phone":"+1 360 694 3453",
    "sg:postcode":"98663",
    "sg:province":"WA",
    "sg:tags":[
        "apartment"
    ],
    "wof:name":"Apartments Colonial Park",
    "wof:placetype":"venue"
},
  "geometry": {"coordinates":[-122.667531,45.641594],"type":"Point"}
}