{
  "type": "Feature",
  "properties": {
    "addr:full":"19915 NE Redmond Rd Redmond WA 98053",
    "addr:housenumber":"19915",
    "addr:postcode":"98053",
    "addr:street":"Ne Redmond Rd",
    "iso:country":"US",
    "sg:address":"19915 NE Redmond Rd",
    "sg:city":"Redmond",
    "sg:classifiers":[
        {
            "category":"Professional",
            "subcategory":"Secretarial Services",
            "type":"Services"
        }
    ],
    "sg:phone":"+1 425 868 6162",
    "sg:postcode":"98053",
    "sg:province":"WA",
    "sg:tags":[
        "reporting"
    ],
    "wof:name":"Aquatic Biotics",
    "wof:placetype":"venue"
},
  "geometry": {"coordinates":[-122.073008,47.697516],"type":"Point"}
}