{
  "type": "Feature",
  "properties": {
    "addr:full":"3051 78th Ave SE Mercer Island WA 98040",
    "addr:housenumber":"3051",
    "addr:postcode":"98040",
    "addr:street":"78Th Ave Se",
    "iso:country":"US",
    "sg:address":"3051 78th Ave SE",
    "sg:city":"Mercer Island",
    "sg:classifiers":[
        {
            "category":"Travel",
            "subcategory":"Travel Agent",
            "type":"Entertainment"
        }
    ],
    "sg:phone":"+1 206 236 0990",
    "sg:postcode":"98040",
    "sg:province":"WA",
    "sg:tags":[
        "agency"
    ],
    "wof:name":"Cruise Professionals",
    "wof:placetype":"venue"
},
  "geometry": {"coordinates":[-122.23372500000001,47.582083],"type":"Point"}
}