{
  "type": "Feature",
  "properties": {
    "addr:full":"775 Pearl Hill Rd NE Bridgeport WA 98813",
    "addr:housenumber":"775",
    "addr:postcode":"98813",
    "addr:street":"Pearl Hill Rd Ne",
    "iso:country":"US",
    "sg:address":"775 Pearl Hill Rd NE",
    "sg:city":"Bridgeport",
    "sg:classifiers":[
        {
            "category":"Farming",
            "subcategory":"Livestock Farm",
            "type":"Manufacturing & Wholesale Goods"
        }
    ],
    "sg:phone":"+1 509 686 9582",
    "sg:postcode":"98813",
    "sg:province":"WA",
    "sg:tags":[
        "animal",
        "general"
    ],
    "wof:name":"Troutman Ranches",
    "wof:placetype":"venue"
},
  "geometry": {"coordinates":[-119.60095699999999,47.999097],"type":"Point"}
}