{
  "type": "Feature",
  "properties": {
    "addr:full":"1185 Fox Hollow Rd Sequim WA 98382",
    "addr:housenumber":"1185",
    "addr:postcode":"98382",
    "addr:street":"Fox Hollow Rd",
    "iso:country":"US",
    "sg:address":"1185 Fox Hollow Rd",
    "sg:city":"Sequim",
    "sg:classifiers":[
        {
            "category":"Personal",
            "subcategory":"Beauty Salon",
            "type":"Services"
        }
    ],
    "sg:phone":"+1 360 681 2098",
    "sg:postcode":"98382",
    "sg:province":"WA",
    "sg:tags":[
        "shop"
    ],
    "wof:name":"Illusions By Design",
    "wof:placetype":"venue"
},
  "geometry": {"coordinates":[-123.09548100000001,48.057606],"type":"Point"}
}