{
  "type": "Feature",
  "properties": {
    "addr:full":"978 W Sequim Bay Rd Sequim WA 98382",
    "addr:housenumber":"978",
    "addr:postcode":"98382",
    "addr:street":"W Sequim Bay Rd",
    "iso:country":"US",
    "sg:address":"978 W Sequim Bay Rd",
    "sg:city":"Sequim",
    "sg:classifiers":[
        {
            "category":"Professional",
            "subcategory":"Detective & Security Services",
            "type":"Services"
        },
        {
            "category":"Professional",
            "subcategory":"Business Services",
            "type":"Services"
        }
    ],
    "sg:phone":"+1 360 681 4695",
    "sg:postcode":"98382",
    "sg:province":"WA",
    "sg:tags":[
        "investigator"
    ],
    "wof:name":"Innerpole Investigations Inc",
    "wof:placetype":"venue"
},
  "geometry": {"coordinates":[-123.06311700000001,48.0759],"type":"Point"}
}