{
  "type": "Feature",
  "properties": {
    "addr:full":"27207 Pacific Hwy S Kent WA 98003",
    "addr:housenumber":"27207",
    "addr:postcode":"98003",
    "addr:street":"Pacific Hwy S",
    "iso:country":"US",
    "sg:address":"27207 Pacific Hwy S",
    "sg:city":"Kent",
    "sg:classifiers":[
        {
            "category":"Retail",
            "subcategory":"Laundry & Dry Cleaning",
            "type":"Services"
        }
    ],
    "sg:phone":"+1 253 839 8451",
    "sg:postcode":"98003",
    "sg:province":"WA",
    "sg:tags":[
        "drycleaning",
        "plant"
    ],
    "wof:name":"Redondo One Hour Cleaners",
    "wof:placetype":"venue"
},
  "geometry": {"coordinates":[-122.309506,47.357911],"type":"Point"}
}