{
  "type": "Feature",
  "properties": {
    "addr:full":"2136 James St Bellingham WA 98225",
    "addr:housenumber":"2136",
    "addr:postcode":"98225",
    "addr:street":"James St",
    "iso:country":"US",
    "sg:address":"2136 James St",
    "sg:city":"Bellingham",
    "sg:classifiers":[
        {
            "category":"Insurance",
            "subcategory":"Hazard Insurance",
            "type":"Services"
        },
        {
            "category":"Insurance",
            "subcategory":"Insurance Agent",
            "type":"Services"
        },
        {
            "category":"Insurance",
            "subcategory":"Life Insurance",
            "type":"Services"
        },
        {
            "category":"Insurance",
            "subcategory":"Title Insurance",
            "type":"Services"
        }
    ],
    "sg:phone":"+1 360 676 8893",
    "sg:postcode":"98225",
    "sg:province":"WA",
    "sg:tags":[
        "auto",
        "commercial",
        "business",
        "homeowner"
    ],
    "sg:website":"http://www.farmersagent.com/shouston/",
    "wof:name":"James Houston Insurance Agency Inc - Farmers Insurance",
    "wof:placetype":"venue"
},
  "geometry": {"coordinates":[-122.46492000000001,48.758241],"type":"Point"}
}