{
  "type": "Feature",
  "properties": {
    "addr:full":"5735 27th Ave NE Seattle WA 98105",
    "addr:housenumber":"5735",
    "addr:postcode":"98105",
    "addr:street":"27Th Ave Ne",
    "iso:country":"US",
    "sg:address":"5735 27th Ave NE",
    "sg:city":"Seattle",
    "sg:classifiers":[
        {
            "category":"Professional",
            "type":"Services"
        }
    ],
    "sg:phone":"+1 206 522 1550",
    "sg:postcode":"98105",
    "sg:province":"WA",
    "sg:tags":[
        "writer"
    ],
    "wof:name":"Elizabeth Smoots Health",
    "wof:placetype":"venue"
},
  "geometry": {"coordinates":[-122.298604,47.671901],"type":"Point"}
}