{
  "type": "Feature",
  "properties": {
    "iso:country":"US",
    "sg:address":"16511 75th St E",
    "sg:city":"Sumner",
    "sg:classifiers":[
        {
            "category":"Wholesale",
            "subcategory":"Auto Parts",
            "type":"Manufacturing & Wholesale Goods"
        }
    ],
    "sg:phone":"+1 253 826 4272",
    "sg:postcode":"98390",
    "sg:province":"WA",
    "wof:name":"Murray Sales Co",
    "wof:placetype":"venue"
},
  "geometry": {"coordinates":[-122.212153,47.18931],"type":"Point"}
}