{
  "type": "Feature",
  "properties": {
    "addr:full":"530 SE Barrington Dr Oak Harbor WA 98277",
    "addr:postcode":"530;98277",
    "addr:street":"Se Barrington Dr",
    "iso:country":"US",
    "sg:address":"530 SE Barrington Dr",
    "sg:city":"Oak Harbor",
    "sg:classifiers":[
        {
            "category":"Personal",
            "subcategory":"Barber",
            "type":"Services"
        }
    ],
    "sg:phone":"+1 360 240 8820",
    "sg:postcode":"98277",
    "sg:province":"WA",
    "wof:name":"Bay Watch Barber Shop",
    "wof:placetype":"venue"
},
  "geometry": {"coordinates":[-122.64942000000001,48.290091],"type":"Point"}
}