{
  "type": "Feature",
  "properties": {
    "addr:full":"16711 NE 169th Ct Woodinville WA 98072",
    "addr:housenumber":"16711",
    "addr:postcode":"98072",
    "addr:street":"Ne 169Th Ct",
    "iso:country":"US",
    "sg:address":"16711 NE 169th Ct",
    "sg:city":"Woodinville",
    "sg:classifiers":[
        {
            "category":"Professional",
            "type":"Services"
        }
    ],
    "sg:phone":"+1 425 481 2973",
    "sg:postcode":"98072",
    "sg:province":"WA",
    "wof:name":"Lavender & Roses",
    "wof:placetype":"venue"
},
  "geometry": {"coordinates":[-122.116722,47.749982],"type":"Point"}
}