{
  "type": "Feature",
  "properties": {
    "addr:full":"800 E Denny Way Seattle WA 98122",
    "addr:housenumber":"800",
    "addr:postcode":"98122",
    "addr:street":"E Denny Way",
    "iso:country":"US",
    "sg:address":"800 E Denny Way",
    "sg:city":"Seattle",
    "sg:classifiers":[
        {
            "category":"Building & Trades",
            "subcategory":"Locksmith",
            "type":"Services"
        }
    ],
    "sg:phone":"+1 206 494 9359",
    "sg:postcode":"98122",
    "sg:province":"WA",
    "sg:tags":[
        "key"
    ],
    "wof:name":"24 Emergency Locksmith",
    "wof:placetype":"venue"
},
  "geometry": {"coordinates":[-122.32219000000001,47.618897],"type":"Point"}
}