{
  "type": "Feature",
  "properties": {
    "addr:full":"Julia's On Broadway 300 Broadway E. Seattle WA 98122",
    "addr:housenumber":"300",
    "addr:postcode":"98122",
    "addr:street":"Broadway E.",
    "iso:country":"US",
    "sg:address":"Julia's On Broadway 300 Broadway E.",
    "sg:city":"Seattle",
    "sg:classifiers":[
        {
            "category":"Arts & Performance",
            "subcategory":"Arts Center",
            "type":"Entertainment"
        }
    ],
    "sg:phone":"+1 206 334 0513",
    "sg:postcode":"98122",
    "sg:province":"WA",
    "sg:tags":[
        "performing"
    ],
    "wof:name":"Le Faux",
    "wof:placetype":"venue"
},
  "geometry": {"coordinates":[-122.32087799999999,47.621096],"type":"Point"}
}