{
  "type": "Feature",
  "properties": {
    "addr:full":"915 SW Dash Point Rd Federal Way WA 98023",
    "addr:housenumber":"915",
    "addr:postcode":"98023",
    "addr:street":"Sw Dash Point Rd",
    "iso:country":"US",
    "sg:address":"915 SW Dash Point Rd",
    "sg:city":"Federal Way",
    "sg:classifiers":[
        {
            "category":"Building & Trades",
            "subcategory":"Cleaning & Sanitation",
            "type":"Services"
        }
    ],
    "sg:phone":"+1 253 941 7923",
    "sg:postcode":"98023",
    "sg:province":"WA",
    "sg:tags":[
        "janitorial"
    ],
    "wof:name":"Imran & Assoc",
    "wof:placetype":"venue"
},
  "geometry": {"coordinates":[-122.346515,47.330702],"type":"Point"}
}