{
  "type": "Feature",
  "properties": {
    "addr:full":"211 Lenora St Apt 609 Seattle WA 98121",
    "addr:housenumber":"211;609",
    "addr:postcode":"98121",
    "addr:street":"Lenora St Apt",
    "iso:country":"US",
    "sg:address":"211 Lenora St Apt 609",
    "sg:city":"Seattle",
    "sg:classifiers":[
        {
            "category":"Recreation",
            "type":"Entertainment"
        }
    ],
    "sg:phone":"+1 206 736 5529",
    "sg:postcode":"98121",
    "sg:province":"WA",
    "sg:tags":[
        "entertainers-family",
        "business"
    ],
    "wof:name":"Metronome Entertainment",
    "wof:placetype":"venue"
},
  "geometry": {"coordinates":[-122.34298200000001,47.612585],"type":"Point"}
}