{
  "type": "Feature",
  "properties": {
    "addr:full":"833 Foster Rd NE Bremerton WA 98311",
    "addr:housenumber":"833",
    "addr:postcode":"98311",
    "addr:street":"Foster Rd Ne",
    "iso:country":"US",
    "sg:address":"833 Foster Rd NE",
    "sg:city":"Bremerton",
    "sg:classifiers":[
        {
            "category":"Banks & Credit Unions",
            "subcategory":"Financial Services",
            "type":"Services"
        }
    ],
    "sg:phone":"+1 360 692 1830",
    "sg:postcode":"98311",
    "sg:province":"WA",
    "sg:tags":[
        "patent"
    ],
    "wof:name":"Levit - E  LLC",
    "wof:placetype":"venue"
},
  "geometry": {"coordinates":[-122.64160800000001,47.641294],"type":"Point"}
}