{
  "type": "Feature",
  "properties": {
    "addr:full":"116 217th Pl SE Bothell WA 98021",
    "addr:housenumber":"116",
    "addr:postcode":"98021",
    "addr:street":"217Th Pl Se",
    "iso:country":"US",
    "sg:address":"116 217th Pl SE",
    "sg:city":"Bothell",
    "sg:classifiers":[
        {
            "category":"Retail",
            "subcategory":"Repair Shop",
            "type":"Services"
        },
        {
            "category":"Home & Garden",
            "subcategory":"Furniture",
            "type":"Retail Goods"
        }
    ],
    "sg:phone":"+1 425 486 1968",
    "sg:postcode":"98021",
    "sg:province":"WA",
    "sg:tags":[
        "refinish",
        "store"
    ],
    "sg:website":"http://furnituremedicbyray.com",
    "wof:name":"Furniture Medic By Pfaff",
    "wof:placetype":"venue"
},
  "geometry": {"coordinates":[-122.23146800000001,47.801055],"type":"Point"}
}