{
  "type": "Feature",
  "properties": {
    "addr:full":"11204 SE 256th St Kent WA 98030",
    "addr:postcode":"11204;98030",
    "addr:street":"Se 256Th St",
    "iso:country":"US",
    "sg:address":"11204 SE 256th St",
    "sg:city":"Kent",
    "sg:classifiers":[
        {
            "category":"Health Services",
            "subcategory":"Doctor",
            "type":"Services"
        }
    ],
    "sg:phone":"+1 253 852 3645",
    "sg:postcode":"98030",
    "sg:province":"WA",
    "sg:tags":[
        "business"
    ],
    "wof:name":"Paul M Hoot DDS",
    "wof:placetype":"venue"
},
  "geometry": {"coordinates":[-122.193431,47.37253],"type":"Point"}
}