{
  "type": "Feature",
  "properties": {
    "addr:full":"4406 141st St SE Snohomish WA 98296",
    "addr:housenumber":"4406",
    "addr:postcode":"98296",
    "addr:street":"141St St Se",
    "iso:country":"US",
    "sg:address":"4406 141st St SE",
    "sg:city":"Snohomish",
    "sg:classifiers":[
        {
            "category":"Professional",
            "subcategory":"Business Services",
            "type":"Services"
        }
    ],
    "sg:phone":"+1 425 379 0210",
    "sg:postcode":"98296",
    "sg:province":"WA",
    "wof:name":"Property Inspections Northwest",
    "wof:placetype":"venue"
},
  "geometry": {"coordinates":[-122.17578399999999,47.868548],"type":"Point"}
}