{
  "type": "Feature",
  "properties": {
    "addr:full":"15224 NE 95th St Redmond WA 98052",
    "addr:housenumber":"15224",
    "addr:postcode":"98052",
    "addr:street":"Ne 95Th St",
    "iso:country":"US",
    "sg:address":"15224 NE 95th St",
    "sg:city":"Redmond",
    "sg:classifiers":[
        {
            "category":"Manufacturing",
            "subcategory":"Tools & Machinery",
            "type":"Manufacturing & Wholesale Goods"
        }
    ],
    "sg:phone":"+1 425 881 7117",
    "sg:postcode":"98052",
    "sg:province":"WA",
    "sg:tags":[
        "analytical",
        "devices",
        "mfg"
    ],
    "wof:name":"Lasentec",
    "wof:placetype":"venue"
},
  "geometry": {"coordinates":[-122.13714,47.685925],"type":"Point"}
}