{
  "type": "Feature",
  "properties": {
    "addr:full":"3257 16th Avenue W Seattle WA 98119",
    "addr:housenumber":"3257",
    "addr:postcode":"98119",
    "addr:street":"16Th Avenue W",
    "iso:country":"US",
    "sg:address":"3257 16th Avenue W",
    "sg:city":"Seattle",
    "sg:classifiers":[
        {
            "category":"Health Services",
            "subcategory":"Chiropractor",
            "type":"Services"
        }
    ],
    "sg:phone":"+1 206 285 1068",
    "sg:postcode":"98119",
    "sg:province":"WA",
    "wof:name":"The Chiropractic Centre",
    "wof:placetype":"venue"
},
  "geometry": {"coordinates":[-122.377653,47.649097],"type":"Point"}
}