{
  "type": "Feature",
  "properties": {
    "addr:full":"13510 100th Ave NE Kirkland WA 98034",
    "addr:housenumber":"13510",
    "addr:postcode":"98034",
    "addr:street":"100Th Ave Ne",
    "iso:country":"US",
    "sg:address":"13510 100th Ave NE",
    "sg:city":"Kirkland",
    "sg:classifiers":[
        {
            "category":"Coffee & Tea",
            "type":"Food & Drink"
        }
    ],
    "sg:phone":"+1 425 820 5820",
    "sg:postcode":"98034",
    "sg:province":"WA",
    "wof:name":"Get Up and Go",
    "wof:placetype":"venue"
},
  "geometry": {"coordinates":[-122.208,47.722301],"type":"Point"}
}