{
  "type": "Feature",
  "properties": {
    "iso:country":"US",
    "sg:address":"6245 Hannegan Rd",
    "sg:city":"Everson",
    "sg:classifiers":[
        {
            "category":"Farming",
            "subcategory":"Dairy Farm",
            "type":"Manufacturing & Wholesale Goods"
        }
    ],
    "sg:phone":"+1 360 398 2676",
    "sg:postcode":"98247",
    "sg:province":"WA",
    "wof:name":"H & H Farms",
    "wof:placetype":"venue"
},
  "geometry": {"coordinates":[-122.442717,48.864497],"type":"Point"}
}