{
  "type": "Feature",
  "properties": {
    "iso:country":"US",
    "sg:address":"927 S Perry St",
    "sg:city":"Spokane",
    "sg:classifiers":[
        {
            "category":"Organizations",
            "subcategory":"Religious Organization",
            "type":"Services"
        }
    ],
    "sg:phone":"+1 509 534 7954",
    "sg:postcode":"99202",
    "sg:province":"WA",
    "sg:tags":[
        "church"
    ],
    "wof:name":"Spokane Buddhist Church",
    "wof:placetype":"venue"
},
  "geometry": {"coordinates":[-117.389841,47.646585],"type":"Point"}
}