{
  "type": "Feature",
  "properties": {
    "addr:full":"8531 Lake City Way NE Seattle WA 98115",
    "addr:housenumber":"8531",
    "addr:postcode":"98115",
    "addr:street":"Lake City Way Ne",
    "iso:country":"US",
    "sg:address":"8531 Lake City Way NE",
    "sg:city":"Seattle",
    "sg:classifiers":[
        {
            "category":"Autos & Motor Vehicles",
            "subcategory":"Automobile Sales",
            "type":"Retail Goods"
        }
    ],
    "sg:phone":"+1 206 524 4250",
    "sg:postcode":"98115",
    "sg:province":"WA",
    "sg:tags":[
        "dealers-used",
        "car",
        "used",
        "cars-wholesale",
        "new"
    ],
    "sg:website":"www.ssmotorsseattle.com",
    "wof:name":"SS Motors",
    "wof:placetype":"venue"
},
  "geometry": {"coordinates":[-122.307767,47.690633],"type":"Point"}
}