{
  "type": "Feature",
  "properties": {
    "addr:full":"2618 6th Ave Tacoma WA 98406",
    "addr:housenumber":"2618",
    "addr:postcode":"98406",
    "addr:street":"6Th Ave",
    "iso:country":"US",
    "sg:address":"2618 6th Ave",
    "sg:city":"Tacoma",
    "sg:classifiers":[
        {
            "category":"Restaurant",
            "type":"Food & Drink"
        }
    ],
    "sg:phone":"+1 253 572 2787",
    "sg:postcode":"98406",
    "sg:province":"WA",
    "wof:name":"Shakbrah Java",
    "wof:placetype":"venue"
},
  "geometry": {"coordinates":[-122.47121799999999,47.255365],"type":"Point"}
}