{
  "type": "Feature",
  "properties": {
    "addr:full":"1048 14th Ave Longview WA 98632",
    "addr:housenumber":"1048",
    "addr:postcode":"98632",
    "addr:street":"14Th Ave",
    "iso:country":"US",
    "sg:address":"1048 14th Ave",
    "sg:city":"Longview",
    "sg:classifiers":[
        {
            "category":"Personal",
            "subcategory":"Beauty Salon",
            "type":"Services"
        }
    ],
    "sg:phone":"+1 360 578 5131",
    "sg:postcode":"98632",
    "sg:province":"WA",
    "sg:tags":[
        "shop"
    ],
    "wof:name":"Unique Hair & Nails",
    "wof:placetype":"venue"
},
  "geometry": {"coordinates":[-122.937235,46.133071],"type":"Point"}
}