{
  "type": "Feature",
  "properties": {
    "addr:full":"6181 Oceanside Pl NE Bremerton WA 98311",
    "addr:housenumber":"6181",
    "addr:postcode":"98311",
    "addr:street":"Oceanside Pl Ne",
    "iso:country":"US",
    "sg:address":"6181 Oceanside Pl NE",
    "sg:city":"Bremerton",
    "sg:classifiers":[
        {
            "category":"Shopping",
            "subcategory":"Gifts & Souvenirs",
            "type":"Retail Goods"
        }
    ],
    "sg:phone":"+1 360 373 7668",
    "sg:postcode":"98311",
    "sg:province":"WA",
    "wof:name":"Smith Sales & Marketing",
    "wof:placetype":"venue"
},
  "geometry": {"coordinates":[-122.597677,47.619325],"type":"Point"}
}