{
  "type": "Feature",
  "properties": {
    "addr:full":"5893 Northwest Rd Ferndale WA 98248",
    "addr:housenumber":"5893",
    "addr:postcode":"98248",
    "addr:street":"Northwest Rd",
    "iso:country":"US",
    "sg:address":"5893 Northwest Rd",
    "sg:city":"Ferndale",
    "sg:classifiers":[
        {
            "category":"Farming",
            "subcategory":"Fish & Marine Products",
            "type":"Manufacturing & Wholesale Goods"
        }
    ],
    "sg:phone":"+1 360 384 1490",
    "sg:postcode":"98248",
    "sg:province":"WA",
    "sg:tags":[
        "fishing"
    ],
    "wof:name":"Sea Diamond Fishing Company",
    "wof:placetype":"venue"
},
  "geometry": {"coordinates":[-122.54098500000001,48.854949],"type":"Point"}
}