{
  "type": "Feature",
  "properties": {
    "addr:full":"11636 NE 149th St Kirkland WA 98034",
    "addr:housenumber":"11636",
    "addr:postcode":"98034",
    "addr:street":"Ne 149Th St",
    "iso:country":"US",
    "sg:address":"11636 NE 149th St",
    "sg:city":"Kirkland",
    "sg:classifiers":[
        {
            "category":"Real Estate",
            "subcategory":"Real Estate Agent",
            "type":"Services"
        }
    ],
    "sg:phone":"+1 425 402 8193",
    "sg:postcode":"98034",
    "sg:province":"WA",
    "sg:tags":[
        "business"
    ],
    "wof:name":"Regional Appraisal NW",
    "wof:placetype":"venue"
},
  "geometry": {"coordinates":[-122.18501999999999,47.736323],"type":"Point"}
}