{
  "type": "Feature",
  "properties": {
    "addr:full":"811 Krough Rd Prosser WA 98930",
    "addr:housenumber":"811",
    "addr:postcode":"98930",
    "addr:street":"Krough Rd",
    "iso:country":"US",
    "sg:address":"811 Krough Rd",
    "sg:city":"Prosser",
    "sg:classifiers":[
        {
            "category":"Farming",
            "subcategory":"Vineyard",
            "type":"Manufacturing & Wholesale Goods"
        }
    ],
    "sg:phone":"+1 509 786 4909",
    "sg:postcode":"98930",
    "sg:province":"WA",
    "sg:tags":[
        "grape"
    ],
    "wof:name":"Van Nostern Jaynetta",
    "wof:placetype":"venue"
},
  "geometry": {"coordinates":[-119.872608,46.208003],"type":"Point"}
}