{
  "type": "Feature",
  "properties": {
    "addr:full":"1169 3rd Ave Longview WA 98632",
    "addr:housenumber":"1169",
    "addr:postcode":"98632",
    "addr:street":"3Rd Ave",
    "iso:country":"US",
    "sg:address":"1169 3rd Ave",
    "sg:city":"Longview",
    "sg:classifiers":[
        {
            "category":"Retail",
            "subcategory":"Auto Repair",
            "type":"Services"
        }
    ],
    "sg:phone":"+1 360 577 6545",
    "sg:postcode":"98632",
    "sg:province":"WA",
    "sg:tags":[
        "repairing",
        "automobile",
        "automotive",
        "general"
    ],
    "wof:name":"Bob Cope's Auto Clinic Towing",
    "wof:placetype":"venue"
},
  "geometry": {"coordinates":[-122.92482800000001,46.129153],"type":"Point"}
}