{
  "type": "Feature",
  "properties": {
    "addr:full":"222 Williams Ave S Renton WA 98057",
    "addr:housenumber":"222",
    "addr:postcode":"98057",
    "addr:street":"Williams Ave S Renton",
    "iso:country":"US",
    "sg:address":"222 Williams Ave S",
    "sg:city":"Renton",
    "sg:classifiers":[
        {
            "category":"Social Services",
            "type":"Services"
        },
        {
            "category":"Personal",
            "type":"Services"
        },
        {
            "category":"Place Of Worship",
            "type":"Public Place"
        }
    ],
    "sg:phone":"+1 425 271 9711",
    "sg:postcode":"98057",
    "sg:province":"WA",
    "sg:tags":[
        "family",
        "professional",
        "child",
        "counselors-licensed",
        "individual",
        "marriage",
        "church",
        "counseling",
        "counselor"
    ],
    "wof:name":"Lutheran Counseling Network",
    "wof:placetype":"venue"
},
  "geometry": {"coordinates":[-122.206632,47.480889],"type":"Point"}
}