{
  "type": "Feature",
  "properties": {
    "addr:full":"13474 Airport Cutoff Rd Port Townsend WA 98368",
    "addr:housenumber":"13474",
    "addr:postcode":"98368",
    "addr:street":"Airport Cutoff Rd",
    "iso:country":"US",
    "sg:address":"13474 Airport Cutoff Rd",
    "sg:city":"Port Townsend",
    "sg:classifiers":[
        {
            "category":"Organizations",
            "subcategory":"Religious Organization",
            "type":"Services"
        }
    ],
    "sg:phone":"+1 360 385 6469",
    "sg:postcode":"98368",
    "sg:province":"WA",
    "wof:name":"Calvary Chapel Port Townsend",
    "wof:placetype":"venue"
},
  "geometry": {"coordinates":[-122.810841,48.062751],"type":"Point"}
}