{
  "type": "Feature",
  "properties": {
    "addr:full":"1420 NE 3rd Ave Camas WA 98607",
    "addr:housenumber":"1420",
    "addr:postcode":"98607",
    "addr:street":"Ne 3Rd Ave",
    "iso:country":"US",
    "sg:address":"1420 NE 3rd Ave",
    "sg:city":"Camas",
    "sg:classifiers":[
        {
            "category":"Organizations",
            "subcategory":"Religious Organization",
            "type":"Services"
        }
    ],
    "sg:phone":"+1 360 834 2332",
    "sg:postcode":"98607",
    "sg:province":"WA",
    "wof:name":"First Baptist Church",
    "wof:placetype":"venue"
},
  "geometry": {"coordinates":[-122.393997,45.588799],"type":"Point"}
}