{
  "type": "Feature",
  "properties": {
    "addr:full":"16607 Smokey Point Blvd Arlington WA 98223",
    "addr:housenumber":"16607",
    "addr:postcode":"98223",
    "addr:street":"Smokey Point Blvd",
    "iso:country":"US",
    "sg:address":"16607 Smokey Point Blvd",
    "sg:city":"Arlington",
    "sg:classifiers":[
        {
            "category":"Autos & Motor Vehicles",
            "subcategory":"Auto Supplies",
            "type":"Retail Goods"
        }
    ],
    "sg:phone":"+1 360 658 8666",
    "sg:postcode":"98223",
    "sg:province":"WA",
    "sg:tags":[
        "tire"
    ],
    "wof:name":"Les Schwab Tire Ctr",
    "wof:placetype":"venue"
},
  "geometry": {"coordinates":[-122.18305700000001,48.147621],"type":"Point"}
}