{
  "type": "Feature",
  "properties": {
    "addr:full":"723 NE Northgate Way Un620 Seattle WA 98125",
    "addr:housenumber":"723",
    "addr:postcode":"un620;98125",
    "addr:street":"Ne Northgate Way",
    "iso:country":"US",
    "sg:address":"723 NE Northgate Way Un620",
    "sg:city":"Seattle",
    "sg:classifiers":[
        {
            "category":"Shopping",
            "subcategory":"Jewelry",
            "type":"Retail Goods"
        },
        {
            "category":"Manufacturing",
            "subcategory":"Jewelry",
            "type":"Manufacturing & Wholesale Goods"
        }
    ],
    "sg:phone":"+1 206 361 3677",
    "sg:postcode":"98125",
    "sg:province":"WA",
    "sg:tags":[
        "stone",
        "designer",
        "watch",
        "jeweler",
        "precious",
        "semi-precious",
        "appraiser"
    ],
    "sg:website":"http://www.fredmeyerjewelers.com/",
    "wof:name":"Fred Meyer Jewelers",
    "wof:placetype":"venue"
},
  "geometry": {"coordinates":[-122.32123,47.708554],"type":"Point"}
}