{
  "type": "Feature",
  "properties": {
    "addr:full":"511 100th Ave NE Bellevue WA 98004",
    "addr:housenumber":"511",
    "addr:postcode":"98004",
    "addr:street":"100Th Ave Ne",
    "iso:country":"US",
    "sg:address":"511 100th Ave NE",
    "sg:city":"Bellevue",
    "sg:classifiers":[
        {
            "category":"Real Estate",
            "subcategory":"Real Estate Operator",
            "type":"Services"
        }
    ],
    "sg:phone":"+1 425 688 9270",
    "sg:postcode":"98004",
    "sg:province":"WA",
    "sg:tags":[
        "apartment"
    ],
    "wof:name":"Bellevue Continental Apts",
    "wof:placetype":"venue"
},
  "geometry": {"coordinates":[-122.20717,47.615099],"type":"Point"}
}