{
  "type": "Feature",
  "properties": {
    "addr:full":"201 NE Park Plaza Dr Ste 244 Vancouver WA 98684",
    "addr:housenumber":"201",
    "addr:postcode":"98684",
    "addr:street":"Ne Park Plaza Dr Ste 244",
    "iso:country":"US",
    "sg:address":"201 NE Park Plaza Dr Ste 244",
    "sg:city":"Vancouver",
    "sg:classifiers":[
        {
            "category":"Professional",
            "subcategory":"Accounting & Tax Preparation",
            "type":"Services"
        }
    ],
    "sg:phone":"+1 360 750 6884",
    "sg:postcode":"98684",
    "sg:province":"WA",
    "sg:tags":[
        "accountant"
    ],
    "wof:name":"Tax Advisors Pllc",
    "wof:placetype":"venue"
},
  "geometry": {"coordinates":[-122.539463,45.622449],"type":"Point"}
}