{
  "type": "Feature",
  "properties": {
    "addr:full":"860 SW 143rd Street Burien WA 98166",
    "addr:housenumber":"860",
    "addr:postcode":"98166",
    "addr:street":"Sw 143Rd Street",
    "iso:country":"US",
    "sg:address":"860 SW 143rd Street",
    "sg:city":"Burien",
    "sg:classifiers":[
        {
            "category":"Professional",
            "subcategory":"Lawyer & Legal Services",
            "type":"Services"
        }
    ],
    "sg:phone":"+1 206 242 9876",
    "sg:postcode":"98166",
    "sg:province":"WA",
    "wof:name":"Linn Schisel & Demarco Attorneys At Law",
    "wof:placetype":"venue"
},
  "geometry": {"coordinates":[-122.347238,47.474628],"type":"Point"}
}