{
  "type": "Feature",
  "properties": {
    "addr:full":"2502 Hartford Dr Lake Stevens WA 98258",
    "addr:housenumber":"2502",
    "addr:postcode":"98258",
    "addr:street":"Hartford Dr",
    "iso:country":"US",
    "sg:address":"2502 Hartford Dr",
    "sg:city":"Lake Stevens",
    "sg:classifiers":[
        {
            "category":"Retail",
            "subcategory":"Car Wash",
            "type":"Services"
        }
    ],
    "sg:phone":"+1 425 334 8837",
    "sg:postcode":"98258",
    "sg:province":"WA",
    "sg:tags":[
        "carwash"
    ],
    "wof:name":"S A E Auto Detail",
    "wof:placetype":"venue"
},
  "geometry": {"coordinates":[-122.054568,48.021091],"type":"Point"}
}