{
  "type": "Feature",
  "properties": {
    "addr:full":"5705 Evergreen Way Everett WA 98203",
    "addr:housenumber":"5705",
    "addr:postcode":"98203",
    "addr:street":"Evergreen Way",
    "iso:country":"US",
    "sg:address":"5705 Evergreen Way",
    "sg:city":"Everett",
    "sg:classifiers":[
        {
            "category":"Professional",
            "subcategory":"Lawyer & Legal Services",
            "type":"Services"
        }
    ],
    "sg:phone":"+1 425 353 7909",
    "sg:postcode":"98203",
    "sg:province":"WA",
    "sg:tags":[
        "attorney",
        "law",
        "family",
        "divorce",
        "practice",
        "immigration",
        "criminal"
    ],
    "wof:name":"KC Celebi Attorney At Law",
    "wof:placetype":"venue"
},
  "geometry": {"coordinates":[-122.216612,47.944815],"type":"Point"}
}