{
  "type": "Feature",
  "properties": {
    "addr:full":"26036 NE 209th St Battle Ground WA 98604",
    "addr:housenumber":"26036",
    "addr:postcode":"98604",
    "addr:street":"Ne 209Th St",
    "iso:country":"US",
    "sg:address":"26036 NE 209th St",
    "sg:city":"Battle Ground",
    "sg:classifiers":[
        {
            "category":"Wholesale",
            "subcategory":"Electrical",
            "type":"Manufacturing & Wholesale Goods"
        }
    ],
    "sg:phone":"+1 360 687 4400",
    "sg:postcode":"98604",
    "sg:province":"WA",
    "sg:tags":[
        "electronic"
    ],
    "wof:name":"Sitka Technologies Inc",
    "wof:placetype":"venue"
},
  "geometry": {"coordinates":[-122.405501,45.773779],"type":"Point"}
}