{
  "type": "Feature",
  "properties": {
    "addr:full":"8998 S March Point Rd Anacortes WA 98221",
    "addr:housenumber":"8998",
    "addr:postcode":"98221",
    "addr:street":"S March Point Rd",
    "iso:country":"US",
    "sg:address":"8998 S March Point Rd",
    "sg:city":"Anacortes",
    "sg:classifiers":[
        {
            "category":"Building & Trades",
            "subcategory":"Equipment Rental",
            "type":"Services"
        }
    ],
    "sg:phone":"+1 360 293 7788",
    "sg:postcode":"98221",
    "sg:province":"WA",
    "wof:name":"Birch Equipment Rental & Sales",
    "wof:placetype":"venue"
},
  "geometry": {"coordinates":[-122.554799,48.462268],"type":"Point"}
}