{
  "type": "Feature",
  "properties": {
    "addr:full":"2870 Wild Rhody Ln NW Poulsbo WA 98370",
    "addr:housenumber":"2870",
    "addr:postcode":"98370",
    "addr:street":"Wild Rhody Ln Nw",
    "iso:country":"US",
    "sg:address":"2870 Wild Rhody Ln NW",
    "sg:city":"Poulsbo",
    "sg:classifiers":[
        {
            "category":"Professional",
            "subcategory":"Computer Services",
            "type":"Services"
        }
    ],
    "sg:phone":"+1 360 779 4886",
    "sg:postcode":"98370",
    "sg:province":"WA",
    "sg:tags":[
        "programing",
        "custom"
    ],
    "wof:name":"Kitsap Programming Servic",
    "wof:placetype":"venue"
},
  "geometry": {"coordinates":[-122.687934,47.710287],"type":"Point"}
}