{
  "type": "Feature",
  "properties": {
    "addr:full":"535 SE Water St Pullman WA 99163",
    "addr:housenumber":"535",
    "addr:postcode":"99163",
    "addr:street":"Se Water St",
    "iso:country":"US",
    "sg:address":"535 SE Water St",
    "sg:city":"Pullman",
    "sg:classifiers":[
        {
            "category":"Professional",
            "type":"Services"
        }
    ],
    "sg:phone":"+1 509 335 0729",
    "sg:postcode":"99163",
    "sg:province":"WA",
    "sg:tags":[
        "consultant",
        "scientific"
    ],
    "wof:name":"Cobbold  Rowland",
    "wof:placetype":"venue"
},
  "geometry": {"coordinates":[-117.177621,46.725033],"type":"Point"}
}