{
  "type": "Feature",
  "properties": {
    "addr:full":"808 Howell St Fl 4 Seattle WA 98101",
    "addr:housenumber":"808;4",
    "addr:postcode":"98101",
    "addr:street":"Howell St",
    "iso:country":"US",
    "sg:address":"808 Howell St Fl 4",
    "sg:city":"Seattle",
    "sg:classifiers":[
        {
            "category":"Professional",
            "subcategory":"Computer Services",
            "type":"Services"
        }
    ],
    "sg:phone":"+1 206 438 7800",
    "sg:postcode":"98101",
    "sg:province":"WA",
    "sg:tags":[
        "isp",
        "provider",
        "internet"
    ],
    "sg:website":"http://www.megapath.com",
    "wof:name":"Ssl Vpn Division",
    "wof:placetype":"venue"
},
  "geometry": {"coordinates":[-122.33393,47.614118],"type":"Point"}
}