{
  "type": "Feature",
  "properties": {
    "addr:full":"2711 12th St Everett WA 98201",
    "addr:housenumber":"2711",
    "addr:postcode":"98201",
    "addr:street":"12Th St",
    "iso:country":"US",
    "sg:address":"2711 12th St",
    "sg:city":"Everett",
    "sg:classifiers":[
        {
            "category":"Retail",
            "subcategory":"Portrait Studio",
            "type":"Services"
        }
    ],
    "sg:phone":"+1 425 501 6647",
    "sg:postcode":"98201",
    "sg:province":"WA",
    "sg:tags":[
        "photo"
    ],
    "wof:name":"RMR Photographer",
    "wof:placetype":"venue"
},
  "geometry": {"coordinates":[-122.193888,48.001424],"type":"Point"}
}