{
  "type": "Feature",
  "properties": {
    "addr:full":"17329 140th Ave NE Woodinville WA 98072",
    "addr:housenumber":"17329",
    "addr:postcode":"98072",
    "addr:street":"140Th Ave Ne",
    "iso:country":"US",
    "sg:address":"17329 140th Ave NE",
    "sg:city":"Woodinville",
    "sg:classifiers":[
        {
            "category":"Personal",
            "subcategory":"Beauty Salon",
            "type":"Services"
        }
    ],
    "sg:phone":"+1 425 487 9948",
    "sg:postcode":"98072",
    "sg:province":"WA",
    "wof:name":"Beautiful Nails & Skin Care",
    "wof:placetype":"venue"
},
  "geometry": {"coordinates":[-122.152711,47.753174],"type":"Point"}
}