{
  "type": "Feature",
  "properties": {
    "addr:full":"308 W Emma St Union Gap WA 98903",
    "addr:housenumber":"308",
    "addr:postcode":"98903",
    "addr:street":"W Emma St",
    "iso:country":"US",
    "sg:address":"308 W Emma St",
    "sg:city":"Union Gap",
    "sg:classifiers":[
        {
            "category":"Health Services",
            "subcategory":"Nursing And Care Facility",
            "type":"Services"
        }
    ],
    "sg:phone":"+1 509 248 1985",
    "sg:postcode":"98903",
    "sg:province":"WA",
    "sg:tags":[
        "home",
        "convalescent"
    ],
    "wof:name":"Parkside Nursing Care Ctr",
    "wof:placetype":"venue"
},
  "geometry": {"coordinates":[-120.480108,46.552884],"type":"Point"}
}