{
  "type": "Feature",
  "properties": {
    "addr:full":"102 N 15th St Mount Vernon WA 98273",
    "addr:housenumber":"102",
    "addr:postcode":"98273",
    "addr:street":"N 15Th St",
    "iso:country":"US",
    "sg:address":"102 N 15th St",
    "sg:city":"Mount Vernon",
    "sg:classifiers":[
        {
            "category":"Health Services",
            "subcategory":"Optometrist",
            "type":"Services"
        }
    ],
    "sg:phone":"+1 360 424 4181",
    "sg:postcode":"98273",
    "sg:province":"WA",
    "wof:name":"Jones Tod W OD",
    "wof:placetype":"venue"
},
  "geometry": {"coordinates":[-122.322998,48.421299],"type":"Point"}
}