{
  "type": "Feature",
  "properties": {
    "iso:country":"US",
    "sg:address":"2410 N 4th Ave",
    "sg:city":"Pasco",
    "sg:classifiers":[
        {
            "category":"Wholesale",
            "subcategory":"Machinery & Supplies",
            "type":"Manufacturing & Wholesale Goods"
        }
    ],
    "sg:phone":"+1 509 547 1761",
    "sg:postcode":"99301",
    "sg:province":"WA",
    "sg:tags":[
        "equipment",
        "irrigation",
        "system"
    ],
    "wof:name":"Irrigation Specialists Inc",
    "wof:placetype":"venue"
},
  "geometry": {"coordinates":[-119.094797,46.249711],"type":"Point"}
}