{
  "type": "Feature",
  "properties": {
    "iso:country":"US",
    "sg:address":"931 Wilbert Ave",
    "sg:city":"Bremerton",
    "sg:classifiers":[
        {
            "category":"Professional",
            "subcategory":"Computer Services",
            "type":"Services"
        }
    ],
    "sg:phone":"+1 360 479 0572",
    "sg:postcode":"98312",
    "sg:province":"WA",
    "sg:tags":[
        "programing",
        "custom"
    ],
    "wof:name":"Simitar",
    "wof:placetype":"venue"
},
  "geometry": {"coordinates":[-122.65938,47.570455],"type":"Point"}
}