{
  "type": "Feature",
  "properties": {
    "addr:full":"14629 NE 37th Pl Bellevue WA 98007",
    "addr:housenumber":"14629",
    "addr:postcode":"98007",
    "addr:street":"Ne 37Th Pl",
    "iso:country":"US",
    "sg:address":"14629 NE 37th Pl",
    "sg:city":"Bellevue",
    "sg:classifiers":[
        {
            "category":"Real Estate",
            "subcategory":"Real Estate Services",
            "type":"Services"
        },
        {
            "category":"Real Estate",
            "subcategory":"Real Estate Operator",
            "type":"Services"
        }
    ],
    "sg:phone":"+1 866 532 8350",
    "sg:postcode":"98007",
    "sg:province":"WA",
    "sg:tags":[
        "apartment",
        "property",
        "management"
    ],
    "sg:website":"www.ArchstoneRedmondCourt.com",
    "wof:name":"Archstone Redmond Court",
    "wof:placetype":"venue"
},
  "geometry": {"coordinates":[-122.14571599999999,47.643692],"type":"Point"}
}