{
  "type": "Feature",
  "properties": {
    "addr:full":"11209 Des Moines Memorial Dr Seattle WA 98168",
    "addr:housenumber":"11209",
    "addr:postcode":"98168",
    "addr:street":"Des Moines Memorial Dr",
    "iso:country":"US",
    "sg:address":"11209 Des Moines Memorial Dr",
    "sg:city":"Seattle",
    "sg:classifiers":[
        {
            "category":"Building & Trades",
            "subcategory":"Locksmith",
            "type":"Services"
        }
    ],
    "sg:phone":"+1 253 336 5032",
    "sg:postcode":"98168",
    "sg:province":"WA",
    "sg:tags":[
        "key"
    ],
    "wof:name":"Locksmith 24 Hour Emergency",
    "wof:placetype":"venue"
},
  "geometry": {"coordinates":[-122.30526399999999,47.502828],"type":"Point"}
}