{
  "type": "Feature",
  "properties": {
    "addr:full":"128 118th Dr NE Lake Stevens WA 98258",
    "addr:housenumber":"128",
    "addr:postcode":"98258",
    "addr:street":"118Th Dr Ne",
    "iso:country":"US",
    "sg:address":"128 118th Dr NE",
    "sg:city":"Lake Stevens",
    "sg:classifiers":[
        {
            "category":"Professional",
            "type":"Services"
        }
    ],
    "sg:phone":"+1 425 334 2175",
    "sg:postcode":"98258",
    "sg:province":"WA",
    "wof:name":"Family Systems",
    "wof:placetype":"venue"
},
  "geometry": {"coordinates":[-122.07154800000001,47.998712],"type":"Point"}
}