{
  "type": "Feature",
  "properties": {
    "addr:full":"2527 W Kennewick Ave Kennewick WA 99336",
    "addr:housenumber":"2527",
    "addr:postcode":"99336",
    "addr:street":"W Kennewick Ave",
    "iso:country":"US",
    "sg:address":"2527 W Kennewick Ave",
    "sg:city":"Kennewick",
    "sg:classifiers":[
        {
            "category":"Home & Garden",
            "subcategory":"Carpets & Floor Coverings",
            "type":"Retail Goods"
        }
    ],
    "sg:phone":"+1 509 582 4878",
    "sg:postcode":"99336",
    "sg:province":"WA",
    "wof:name":"Mr Carpet of Tri Cities",
    "wof:placetype":"venue"
},
  "geometry": {"coordinates":[-119.155675,46.209379],"type":"Point"}
}