{
  "type": "Feature",
  "properties": {
    "addr:full":"5625 3rd Ave Ferndale WA 98248",
    "addr:housenumber":"5625",
    "addr:postcode":"98248",
    "addr:street":"3Rd Ave",
    "iso:country":"US",
    "sg:address":"5625 3rd Ave",
    "sg:city":"Ferndale",
    "sg:classifiers":[
        {
            "category":"Restaurant",
            "type":"Food & Drink"
        }
    ],
    "sg:phone":"+1 360 384 4600",
    "sg:postcode":"98248",
    "sg:province":"WA",
    "wof:name":"Kowloon Inn",
    "wof:placetype":"venue"
},
  "geometry": {"coordinates":[-122.59323999999999,48.846203],"type":"Point"}
}