{
  "type": "Feature",
  "properties": {
    "addr:full":"4922 Waschke Rd Bellingham WA 98226",
    "addr:housenumber":"4922",
    "addr:postcode":"98226",
    "addr:street":"Waschke Rd",
    "iso:country":"US",
    "sg:address":"4922 Waschke Rd",
    "sg:city":"Bellingham",
    "sg:classifiers":[
        {
            "category":"Autos & Motor Vehicles",
            "subcategory":"Fuel & Gas Station",
            "type":"Retail Goods"
        }
    ],
    "sg:phone":"+1 360 384 6489",
    "sg:postcode":"98226",
    "sg:province":"WA",
    "sg:tags":[
        "station",
        "gasoline"
    ],
    "wof:name":"Timothy Lee Brinkley",
    "wof:placetype":"venue"
},
  "geometry": {"coordinates":[-122.52981800000001,48.821697],"type":"Point"}
}