{
  "type": "Feature",
  "properties": {
    "addr:full":"1100 Vandercook Way Longview WA 98632",
    "addr:housenumber":"1100",
    "addr:postcode":"98632",
    "addr:street":"Vandercook Way",
    "iso:country":"US",
    "sg:address":"1100 Vandercook Way",
    "sg:city":"Longview",
    "sg:classifiers":[
        {
            "category":"Autos & Motor Vehicles",
            "subcategory":"Automobile Sales",
            "type":"Retail Goods"
        },
        {
            "category":"Autos & Motor Vehicles",
            "subcategory":"Auto Supplies",
            "type":"Retail Goods"
        },
        {
            "category":"Retail",
            "subcategory":"Auto Repair",
            "type":"Services"
        }
    ],
    "sg:phone":"+1 360 200 4237",
    "sg:postcode":"98632",
    "sg:province":"WA",
    "sg:tags":[
        "body",
        "repairing",
        "car",
        "part",
        "new",
        "painting"
    ],
    "sg:website":"http://www.stirlingautogroup.com",
    "wof:name":"Stirling Pontiac Buick GMC",
    "wof:placetype":"venue"
},
  "geometry": {"coordinates":[-122.930138,46.141991],"type":"Point"}
}