{
  "type": "Feature",
  "properties": {
    "addr:full":"2044 N Ashland Ave East Wenatchee WA 98802",
    "addr:housenumber":"2044",
    "addr:postcode":"98802",
    "addr:street":"N Ashland Ave",
    "iso:country":"US",
    "sg:address":"2044 N Ashland Ave",
    "sg:city":"East Wenatchee",
    "sg:classifiers":[
        {
            "category":"Building & Trades",
            "subcategory":"Construction",
            "type":"Services"
        }
    ],
    "sg:phone":"+1 509 884 4939",
    "sg:postcode":"98802",
    "sg:province":"WA",
    "sg:tags":[
        "contractor"
    ],
    "wof:name":"Solinger Floor Covering",
    "wof:placetype":"venue"
},
  "geometry": {"coordinates":[-120.295411,47.43709],"type":"Point"}
}