{
  "type": "Feature",
  "properties": {
    "addr:full":"28715 18th Ave S Federal Way WA 98003",
    "addr:housenumber":"28715",
    "addr:postcode":"98003",
    "addr:street":"18Th Ave S Federal Way",
    "iso:country":"US",
    "sg:address":"28715 18th Ave S",
    "sg:city":"Federal Way",
    "sg:classifiers":[
        {
            "category":"Social Services",
            "subcategory":"Child Care",
            "type":"Services"
        }
    ],
    "sg:phone":"+1 253 941 5815",
    "sg:postcode":"98003",
    "sg:province":"WA",
    "sg:tags":[
        "school",
        "day"
    ],
    "wof:name":"Kindercare Child Care Network",
    "wof:placetype":"venue"
},
  "geometry": {"coordinates":[-122.310681,47.344165],"type":"Point"}
}