{
  "type": "Feature",
  "properties": {
    "addr:full":"89 E Delaware Ave Republic WA 99166",
    "addr:housenumber":"89",
    "addr:postcode":"99166",
    "addr:street":"E Delaware Ave",
    "iso:country":"US",
    "sg:address":"89 E Delaware Ave",
    "sg:city":"Republic",
    "sg:classifiers":[
        {
            "category":"Government",
            "subcategory":"Office",
            "type":"Public Place"
        }
    ],
    "sg:phone":"+1 509 775 2287",
    "sg:postcode":"99166",
    "sg:province":"WA",
    "sg:tags":[
        "state",
        "resource"
    ],
    "wof:name":"Home & Community Svc",
    "wof:placetype":"venue"
},
  "geometry": {"coordinates":[-118.73580699999999,48.648946],"type":"Point"}
}