{
  "type": "Feature",
  "properties": {
    "addr:full":"520 Pear St SE Olympia WA 98501",
    "addr:housenumber":"520",
    "addr:postcode":"98501",
    "addr:street":"Pear St Se",
    "iso:country":"US",
    "sg:address":"520 Pear St SE",
    "sg:city":"Olympia",
    "sg:classifiers":[
        {
            "category":"Government",
            "subcategory":"Office",
            "type":"Public Place"
        }
    ],
    "sg:phone":"+1 360 753 8482",
    "sg:postcode":"98501",
    "sg:province":"WA",
    "sg:tags":[
        "village"
    ],
    "wof:name":"Olympia Engineering & Project",
    "wof:placetype":"venue"
},
  "geometry": {"coordinates":[-122.891097,47.044089],"type":"Point"}
}