{
  "type": "Feature",
  "properties": {
    "addr:full":"11207 Crockett St SW Olympia WA 98512",
    "addr:housenumber":"11207",
    "addr:postcode":"98512",
    "addr:street":"Crockett St Sw",
    "iso:country":"US",
    "sg:address":"11207 Crockett St SW",
    "sg:city":"Olympia",
    "sg:classifiers":[
        {
            "category":"Recreation",
            "type":"Entertainment"
        }
    ],
    "sg:phone":"+1 360 352 4203",
    "sg:postcode":"98512",
    "sg:province":"WA",
    "sg:tags":[
        "stable"
    ],
    "wof:name":"Rushing Wind",
    "wof:placetype":"venue"
},
  "geometry": {"coordinates":[-122.971183,46.924771],"type":"Point"}
}