{
  "type": "Feature",
  "properties": {
    "addr:full":"411 13th St Everett WA 98201",
    "addr:housenumber":"411",
    "addr:postcode":"98201",
    "addr:street":"13Th St",
    "iso:country":"US",
    "sg:address":"411 13th St",
    "sg:city":"Everett",
    "sg:classifiers":[
        {
            "category":"Building & Trades",
            "subcategory":"Construction",
            "type":"Services"
        }
    ],
    "sg:phone":"+1 425 259 0118",
    "sg:postcode":"98201",
    "sg:province":"WA",
    "sg:tags":[
        "heavy",
        "general",
        "marine",
        "contractor"
    ],
    "sg:website":"www.americanconstco.com",
    "wof:name":"American Construction Co Inc",
    "wof:placetype":"venue"
},
  "geometry": {"coordinates":[-122.220366,48.000354],"type":"Point"}
}