{
  "type": "Feature",
  "properties": {
    "iso:country":"US",
    "sg:address":"133 3rd Ave SE",
    "sg:city":"Pacific",
    "sg:classifiers":[
        {
            "category":"Government",
            "subcategory":"Police Station",
            "type":"Public Place"
        }
    ],
    "sg:phone":"+1 253 833 8486",
    "sg:postcode":"98047",
    "sg:province":"WA",
    "sg:tags":[
        "protection"
    ],
    "wof:name":"Pacific City Police",
    "wof:placetype":"venue"
},
  "geometry": {"coordinates":[-122.248328,47.264711],"type":"Point"}
}