{
  "type": "Feature",
  "properties": {
    "addr:full":"12 W 9th Ave Spokane WA 99204",
    "addr:housenumber":"12",
    "addr:postcode":"99204",
    "addr:street":"W 9Th Ave",
    "iso:country":"US",
    "sg:address":"12 W 9th Ave",
    "sg:city":"Spokane",
    "sg:classifiers":[
        {
            "category":"Health Services",
            "subcategory":"Nursing And Care Facility",
            "type":"Services"
        }
    ],
    "sg:phone":"+1 509 838 2594",
    "sg:postcode":"99204",
    "sg:province":"WA",
    "sg:tags":[
        "home",
        "retirement",
        "community"
    ],
    "wof:name":"Mount St Joseph",
    "wof:placetype":"venue"
},
  "geometry": {"coordinates":[-117.41366499999999,47.647424],"type":"Point"}
}