{
  "type": "Feature",
  "properties": {
    "addr:full":"18468 8th Ave NE Poulsbo WA 98370",
    "addr:housenumber":"18468",
    "addr:postcode":"98370",
    "addr:street":"8Th Ave Ne",
    "iso:country":"US",
    "sg:address":"18468 8th Ave NE",
    "sg:city":"Poulsbo",
    "sg:classifiers":[
        {
            "category":"Organizations",
            "subcategory":"Membership Organization",
            "type":"Services"
        }
    ],
    "sg:phone":"+1 360 779 2986",
    "sg:postcode":"98370",
    "sg:province":"WA",
    "wof:name":"Washington State Coach Assn",
    "wof:placetype":"venue"
},
  "geometry": {"coordinates":[-122.638665,47.730391],"type":"Point"}
}