{
  "type": "Feature",
  "properties": {
    "addr:full":"3321 Mount Pleasant Rd Kelso WA 98626",
    "addr:housenumber":"3321",
    "addr:postcode":"98626",
    "addr:street":"Mount Pleasant Rd",
    "iso:country":"US",
    "sg:address":"3321 Mount Pleasant Rd",
    "sg:city":"Kelso",
    "sg:classifiers":[
        {
            "category":"Manufacturing",
            "subcategory":"Signs",
            "type":"Manufacturing & Wholesale Goods"
        }
    ],
    "sg:phone":"+1 360 636 4693",
    "sg:postcode":"98626",
    "sg:province":"WA",
    "sg:tags":[
        "game",
        "mfg"
    ],
    "wof:name":"R E B Magnetics",
    "wof:placetype":"venue"
},
  "geometry": {"coordinates":[-122.778023,46.080398],"type":"Point"}
}