{
  "type": "Feature",
  "properties": {
    "addr:full":"6920 Coal Creek Pkwy SE Ste. 8 Newcastle WA 98059",
    "addr:housenumber":"6920",
    "addr:postcode":"98059",
    "addr:street":"Coal Creek Pkwy Se Ste. 8",
    "iso:country":"US",
    "sg:address":"6920 Coal Creek Pkwy SE Ste. 8",
    "sg:city":"Newcastle",
    "sg:classifiers":[
        {
            "category":"Personal",
            "type":"Services"
        },
        {
            "category":"Sports & Exercise",
            "subcategory":"Gym",
            "type":"Entertainment"
        },
        {
            "category":"Health Services",
            "subcategory":"Health Practitioner",
            "type":"Services"
        },
        {
            "category":"Arena",
            "subcategory":"Sports Club",
            "type":"Entertainment"
        }
    ],
    "sg:phone":"+1 800 615 7352",
    "sg:postcode":"98059",
    "sg:province":"WA",
    "sg:tags":[
        "trainer",
        "control",
        "weight",
        "consultant",
        "program",
        "fitness",
        "physical"
    ],
    "sg:website":"http://seattle.citysearch.com/profile/external/37040189/newcastle_wa/curves.html?publisher=yellowpages&reference_id=1&placement=ypwebsitemip",
    "wof:name":"Curves",
    "wof:placetype":"venue"
},
  "geometry": {"coordinates":[-122.16600800000001,47.539021],"type":"Point"}
}