{
  "type": "Feature",
  "properties": {
    "addr:full":"2728 S 125th Pl Seattle WA 98168",
    "addr:housenumber":"2728",
    "addr:postcode":"98168",
    "addr:street":"S 125Th Pl",
    "iso:country":"US",
    "sg:address":"2728 S 125th Pl",
    "sg:city":"Seattle",
    "sg:classifiers":[
        {
            "category":"Personal",
            "type":"Services"
        }
    ],
    "sg:phone":"+1 206 242 0490",
    "sg:postcode":"98168",
    "sg:province":"WA",
    "sg:tags":[
        "towing"
    ],
    "wof:name":"D M Towing",
    "wof:placetype":"venue"
},
  "geometry": {"coordinates":[-122.297752,47.490662],"type":"Point"}
}