{
  "type": "Feature",
  "properties": {
    "addr:full":"686 Old Arden Hwy Lot 10 Colville WA 99114",
    "addr:housenumber":"686;10",
    "addr:postcode":"colville;99114",
    "addr:street":"Old Arden Hwy Lot",
    "iso:country":"US",
    "sg:address":"686 Old Arden Hwy Lot 10",
    "sg:city":"Colville",
    "sg:classifiers":[
        {
            "category":"Personal",
            "subcategory":"Barber",
            "type":"Services"
        }
    ],
    "sg:phone":"+1 509 684 6690",
    "sg:postcode":"99114",
    "sg:province":"WA",
    "wof:name":"Joyces Hair Fashions",
    "wof:placetype":"venue"
},
  "geometry": {"coordinates":[-117.87344400000001,48.454411],"type":"Point"}
}