{
  "type": "Feature",
  "properties": {
    "addr:full":"4205 165th Ave SE Snohomish WA 98290",
    "addr:housenumber":"4205",
    "addr:postcode":"98290",
    "addr:street":"165Th Ave Se",
    "iso:country":"US",
    "sg:address":"4205 165th Ave SE",
    "sg:city":"Snohomish",
    "sg:classifiers":[
        {
            "category":"Retail",
            "subcategory":"Animal Services",
            "type":"Services"
        }
    ],
    "sg:phone":"+1 425 335 0645",
    "sg:postcode":"98290",
    "sg:province":"WA",
    "sg:tags":[
        "breeder",
        "dog"
    ],
    "wof:name":"Wags & Wiggles Teacups",
    "wof:placetype":"venue"
},
  "geometry": {"coordinates":[-122.007901,47.960668],"type":"Point"}
}