{
  "type": "Feature",
  "properties": {
    "addr:full":"1697 N Western Ave Wenatchee WA 98801",
    "addr:housenumber":"1697",
    "addr:postcode":"98801",
    "addr:street":"N Western Ave",
    "iso:country":"US",
    "sg:address":"1697 N Western Ave",
    "sg:city":"Wenatchee",
    "sg:classifiers":[
        {
            "category":"Wholesale",
            "subcategory":"Fruits & Vegetables",
            "type":"Manufacturing & Wholesale Goods"
        }
    ],
    "sg:phone":"+1 509 663 8567",
    "sg:postcode":"98801",
    "sg:province":"WA",
    "sg:tags":[
        "shipper"
    ],
    "sg:website":"www.gwpmarketing.com",
    "wof:name":"Gwin White & Prince",
    "wof:placetype":"venue"
},
  "geometry": {"coordinates":[-120.34630300000001,47.447902],"type":"Point"}
}