{
  "type": "Feature",
  "properties": {
    "addr:full":"415 S Pioneer Way Moses Lake WA 98837",
    "addr:housenumber":"415",
    "addr:postcode":"98837",
    "addr:street":"S Pioneer Way",
    "iso:country":"US",
    "sg:address":"415 S Pioneer Way",
    "sg:city":"Moses Lake",
    "sg:classifiers":[
        {
            "category":"Autos & Motor Vehicles",
            "subcategory":"Automobile Sales",
            "type":"Retail Goods"
        },
        {
            "category":"Retail",
            "subcategory":"Auto Repair",
            "type":"Services"
        }
    ],
    "sg:phone":"+1 509 766 2886",
    "sg:postcode":"98837",
    "sg:province":"WA",
    "sg:tags":[
        "car",
        "dealer",
        "general"
    ],
    "wof:name":"Inland Auto Center",
    "wof:placetype":"venue"
},
  "geometry": {"coordinates":[-119.271579,47.131991],"type":"Point"}
}