{
  "type": "Feature",
  "properties": {
    "addr:full":"9822 15th Ave SW Bldg A Seattle WA 98106",
    "addr:housenumber":"9822",
    "addr:postcode":"98106",
    "addr:street":"15Th Ave Sw Bldg A",
    "iso:country":"US",
    "sg:address":"9822 15th Ave SW Bldg A",
    "sg:city":"Seattle",
    "sg:classifiers":[
        {
            "category":"Food & Beverages",
            "subcategory":"Liquor & Beverages",
            "type":"Retail Goods"
        }
    ],
    "sg:phone":"+1 206 764 4020",
    "sg:postcode":"98106",
    "sg:province":"WA",
    "sg:tags":[
        "beer",
        "spirit",
        "wine"
    ],
    "wof:name":"Washington State Liquor Store",
    "wof:placetype":"venue"
},
  "geometry": {"coordinates":[-122.35471800000001,47.549472],"type":"Point"}
}