{
  "type": "Feature",
  "properties": {
    "addr:full":"7809 NE 94th Ave Vancouver WA 98662",
    "addr:housenumber":"7809",
    "addr:postcode":"98662",
    "addr:street":"Ne 94Th Ave",
    "iso:country":"US",
    "sg:address":"7809 NE 94th Ave",
    "sg:city":"Vancouver",
    "sg:classifiers":[
        {
            "category":"Health Services",
            "subcategory":"Chiropractor",
            "type":"Services"
        }
    ],
    "sg:phone":"+1 360 944 1800",
    "sg:postcode":"98662",
    "sg:province":"WA",
    "sg:tags":[
        "chiropractic"
    ],
    "wof:name":"Chandler Janell Dc",
    "wof:placetype":"venue"
},
  "geometry": {"coordinates":[-122.576071,45.678862],"type":"Point"}
}