{
  "type": "Feature",
  "properties": {
    "addr:full":"7205 Lillooet Loop Aberdeen WA 98520",
    "addr:housenumber":"7205",
    "addr:postcode":"98520",
    "addr:street":"Lillooet Loop",
    "iso:country":"US",
    "sg:address":"7205 Lillooet Loop",
    "sg:city":"Aberdeen",
    "sg:classifiers":[
        {
            "category":"Building & Trades",
            "subcategory":"Construction",
            "type":"Services"
        }
    ],
    "sg:phone":"+1 360 532 9463",
    "sg:postcode":"98520",
    "sg:province":"WA",
    "sg:tags":[
        "excavating",
        "contractor"
    ],
    "wof:name":"George Yakovich Trucking",
    "wof:placetype":"venue"
},
  "geometry": {"coordinates":[-123.68306200000001,46.971769],"type":"Point"}
}