{
  "type": "Feature",
  "properties": {
    "addr:full":"12621 Military Rd S Seattle WA 98168",
    "addr:housenumber":"12621",
    "addr:postcode":"98168",
    "addr:street":"Military Rd S",
    "iso:country":"US",
    "sg:address":"12621 Military Rd S",
    "sg:city":"Seattle",
    "sg:classifiers":[
        {
            "category":"Personal",
            "subcategory":"Beauty Salon",
            "type":"Services"
        }
    ],
    "sg:phone":"+1 206 242 4884",
    "sg:postcode":"98168",
    "sg:province":"WA",
    "sg:tags":[
        "shop"
    ],
    "wof:name":"Bettys Beauty Shop",
    "wof:placetype":"venue"
},
  "geometry": {"coordinates":[-122.298542,47.490694],"type":"Point"}
}