{
  "type": "Feature",
  "properties": {
    "addr:full":"2008 C St Vancouver WA 98663",
    "addr:housenumber":"2008",
    "addr:postcode":"98663",
    "addr:street":"C St",
    "iso:country":"US",
    "sg:address":"2008 C St",
    "sg:city":"Vancouver",
    "sg:classifiers":[
        {
            "category":"Insurance",
            "subcategory":"Hazard Insurance",
            "type":"Services"
        }
    ],
    "sg:phone":"+1 360 695 9918",
    "sg:postcode":"98663",
    "sg:province":"WA",
    "sg:tags":[
        "fund"
    ],
    "wof:name":"Hartke Tom & Associates",
    "wof:placetype":"venue"
},
  "geometry": {"coordinates":[-122.669332,45.637627],"type":"Point"}
}