{
  "type": "Feature",
  "properties": {
    "addr:full":"216 N 40th Ave Yakima WA 98908",
    "addr:housenumber":"216",
    "addr:postcode":"98908",
    "addr:street":"N 40Th Ave",
    "iso:country":"US",
    "sg:address":"216 N 40th Ave",
    "sg:city":"Yakima",
    "sg:classifiers":[
        {
            "category":"Shopping",
            "subcategory":"Clothing, Apparel, & Fashions",
            "type":"Retail Goods"
        }
    ],
    "sg:phone":"+1 509 966 3399",
    "sg:postcode":"98908",
    "sg:province":"WA",
    "sg:tags":[
        "wig",
        "toupee",
        "hairpiece"
    ],
    "wof:name":"Computer Image Hair Design",
    "wof:placetype":"venue"
},
  "geometry": {"coordinates":[-120.56203600000001,46.601478],"type":"Point"}
}