{
  "type": "Feature",
  "properties": {
    "iso:country":"US",
    "sg:address":"4016 52nd Avenue Ct NW",
    "sg:city":"Gig Harbor",
    "sg:classifiers":[
        {
            "category":"Utilities",
            "subcategory":"Telephone",
            "type":"Services"
        }
    ],
    "sg:phone":"+1 253 851 3796",
    "sg:postcode":"98335",
    "sg:province":"WA",
    "sg:tags":[
        "communications"
    ],
    "wof:name":"Interlaced",
    "wof:placetype":"venue"
},
  "geometry": {"coordinates":[-122.60819600000001,47.294028],"type":"Point"}
}