{
  "type": "Feature",
  "properties": {
    "addr:full":"18610 SE Covington Sawyer Rd Kent WA 98042",
    "addr:postcode":"18610;98042",
    "addr:street":"Se;Sawyer Rd",
    "iso:country":"US",
    "sg:address":"18610 SE Covington Sawyer Rd",
    "sg:city":"Kent",
    "sg:classifiers":[
        {
            "category":"Government",
            "subcategory":"Fire Station",
            "type":"Public Place"
        }
    ],
    "sg:phone":"+1 253 631 5310",
    "sg:postcode":"98042",
    "sg:province":"WA",
    "sg:tags":[
        "department"
    ],
    "wof:name":"Fire Dept",
    "wof:placetype":"venue"
},
  "geometry": {"coordinates":[-122.093343,47.34163],"type":"Point"}
}