{
  "type": "Feature",
  "properties": {
    "addr:full":"757 S 3rd St Mccleary WA 98557",
    "addr:housenumber":"757",
    "addr:postcode":"98557",
    "addr:street":"S 3Rd St",
    "iso:country":"US",
    "sg:address":"757 S 3rd St",
    "sg:city":"Mccleary",
    "sg:classifiers":[
        {
            "category":"Retail",
            "subcategory":"Auto Repair",
            "type":"Services"
        }
    ],
    "sg:phone":"+1 360 495 3624",
    "sg:postcode":"98557",
    "sg:province":"WA",
    "sg:tags":[
        "repairing",
        "automobile"
    ],
    "wof:name":"D J's Custom Exhaust",
    "wof:placetype":"venue"
},
  "geometry": {"coordinates":[-123.264059,47.049591],"type":"Point"}
}