{
  "type": "Feature",
  "properties": {
    "addr:full":"7602 182nd St E Puyallup WA 98375",
    "addr:housenumber":"7602",
    "addr:postcode":"98375",
    "addr:street":"182Nd St E",
    "iso:country":"US",
    "sg:address":"7602 182nd St E",
    "sg:city":"Puyallup",
    "sg:classifiers":[
        {
            "category":"Manufacturing",
            "subcategory":"Lumber",
            "type":"Manufacturing & Wholesale Goods"
        }
    ],
    "sg:phone":"+1 253 847 8464",
    "sg:postcode":"98375",
    "sg:province":"WA",
    "sg:tags":[
        "forestry"
    ],
    "wof:name":"Evergreen Reforestation",
    "wof:placetype":"venue"
},
  "geometry": {"coordinates":[-122.328473,47.090951],"type":"Point"}
}