{
  "type": "Feature",
  "properties": {
    "addr:full":"1322 E 3rd St Port Angeles WA 98362",
    "addr:housenumber":"1322",
    "addr:postcode":"98362",
    "addr:street":"E 3Rd St",
    "iso:country":"US",
    "sg:address":"1322 E 3rd St",
    "sg:city":"Port Angeles",
    "sg:classifiers":[
        {
            "category":"Shopping",
            "subcategory":"Crafts & Fabrics",
            "type":"Retail Goods"
        }
    ],
    "sg:phone":"+1 360 452 4053",
    "sg:postcode":"98362",
    "sg:province":"WA",
    "sg:tags":[
        "sewing"
    ],
    "wof:name":"Nimble Fingers",
    "wof:placetype":"venue"
},
  "geometry": {"coordinates":[-123.412817,48.108061],"type":"Point"}
}