{
  "type": "Feature",
  "properties": {
    "iso:country":"US",
    "sg:address":"10640 Forest Ave S",
    "sg:city":"Seattle",
    "sg:classifiers":[
        {
            "category":"Professional",
            "subcategory":"Business Services",
            "type":"Services"
        }
    ],
    "sg:phone":"+1 206 265 0629",
    "sg:postcode":"98178",
    "sg:province":"WA",
    "wof:name":"IB Strategy Group",
    "wof:placetype":"venue"
},
  "geometry": {"coordinates":[-122.23643300000001,47.506645],"type":"Point"}
}