{
  "type": "Feature",
  "properties": {
    "addr:full":"6828 38th Ave NW Gig Harbor WA 98335",
    "addr:housenumber":"6828",
    "addr:postcode":"98335",
    "addr:street":"38Th Ave Nw",
    "iso:country":"US",
    "sg:address":"6828 38th Ave NW",
    "sg:city":"Gig Harbor",
    "sg:classifiers":[
        {
            "category":"Home & Garden",
            "subcategory":"Building Materials",
            "type":"Retail Goods"
        }
    ],
    "sg:phone":"+1 253 858 9175",
    "sg:postcode":"98335",
    "sg:province":"WA",
    "sg:tags":[
        "marble"
    ],
    "wof:name":"Niebergall Marble Refinishing",
    "wof:placetype":"venue"
},
  "geometry": {"coordinates":[-122.589731,47.317405],"type":"Point"}
}