{
  "type": "Feature",
  "properties": {
    "addr:full":"1020 Anderson Dr Aberdeen WA 98520",
    "addr:housenumber":"1020",
    "addr:postcode":"98520",
    "addr:street":"Anderson Dr",
    "iso:country":"US",
    "sg:address":"1020 Anderson Dr",
    "sg:city":"Aberdeen",
    "sg:classifiers":[
        {
            "category":"Health Services",
            "subcategory":"Doctor",
            "type":"Services"
        }
    ],
    "sg:phone":"+1 360 533 6063",
    "sg:postcode":"98520",
    "sg:province":"WA",
    "sg:tags":[
        "medical"
    ],
    "wof:name":"Family Medicine Grays Hbr Pllc",
    "wof:placetype":"venue"
},
  "geometry": {"coordinates":[-123.846548,46.981515],"type":"Point"}
}