{
  "type": "Feature",
  "properties": {
    "addr:full":"980 Edmonds Ave NE Renton WA 98056",
    "addr:housenumber":"980",
    "addr:postcode":"98056",
    "addr:street":"Edmonds Ave Ne",
    "iso:country":"US",
    "sg:address":"980 Edmonds Ave NE",
    "sg:city":"Renton",
    "sg:classifiers":[
        {
            "category":"Building & Trades",
            "subcategory":"Construction",
            "type":"Services"
        }
    ],
    "sg:phone":"+1 425 591 1184",
    "sg:postcode":"98056",
    "sg:province":"WA",
    "sg:tags":[
        "contractor"
    ],
    "wof:name":"Chavez Marble Installations",
    "wof:placetype":"venue"
},
  "geometry": {"coordinates":[-122.185604,47.498602],"type":"Point"}
}