{
  "type": "Feature",
  "properties": {
    "addr:full":"1235 10th Ave W Seattle WA 98119",
    "addr:housenumber":"1235",
    "addr:postcode":"98119",
    "addr:street":"10Th Ave W",
    "iso:country":"US",
    "sg:address":"1235 10th Ave W",
    "sg:city":"Seattle",
    "sg:classifiers":[
        {
            "category":"Professional",
            "subcategory":"Business Services",
            "type":"Services"
        }
    ],
    "sg:phone":"+1 206 282 7524",
    "sg:postcode":"98119",
    "sg:province":"WA",
    "sg:tags":[
        "designer",
        "display",
        "producer"
    ],
    "wof:name":"Becky Birinyi Designs",
    "wof:placetype":"venue"
},
  "geometry": {"coordinates":[-122.370453,47.63052],"type":"Point"}
}