{
  "type": "Feature",
  "properties": {
    "addr:full":"39614 N Tamarack Ln Deer Park WA 99006",
    "addr:housenumber":"39614",
    "addr:postcode":"99006",
    "addr:street":"N Tamarack Ln",
    "iso:country":"US",
    "sg:address":"39614 N Tamarack Ln",
    "sg:city":"Deer Park",
    "sg:classifiers":[
        {
            "category":"Building & Trades",
            "subcategory":"Electrical",
            "type":"Services"
        }
    ],
    "sg:phone":"+1 509 276 2609",
    "sg:postcode":"99006",
    "sg:province":"WA",
    "sg:tags":[
        "electrical",
        "contractor"
    ],
    "wof:name":"Trump Electric",
    "wof:placetype":"venue"
},
  "geometry": {"coordinates":[-117.439415,48.014734],"type":"Point"}
}