{
  "type": "Feature",
  "properties": {
    "iso:country":"US",
    "sg:address":"1914 10th St",
    "sg:city":"Anacortes",
    "sg:classifiers":[
        {
            "category":"Professional",
            "subcategory":"Advertising",
            "type":"Services"
        }
    ],
    "sg:phone":"+1 360 293 3922",
    "sg:postcode":"98221",
    "sg:province":"WA",
    "wof:name":"Totem",
    "wof:placetype":"venue"
},
  "geometry": {"coordinates":[-122.62805400000001,48.514417],"type":"Point"}
}