{
  "type": "Feature",
  "properties": {
    "addr:full":"371 Lucy Ln Zillah WA 98953",
    "addr:housenumber":"371",
    "addr:postcode":"98953",
    "addr:street":"Lucy Ln",
    "iso:country":"US",
    "sg:address":"371 Lucy Ln",
    "sg:city":"Zillah",
    "sg:classifiers":[
        {
            "category":"Farming",
            "subcategory":"Orchard",
            "type":"Manufacturing & Wholesale Goods"
        }
    ],
    "sg:phone":"+1 509 829 5912",
    "sg:postcode":"98953",
    "sg:province":"WA",
    "sg:tags":[
        "fruit",
        "tree",
        "feedlot",
        "beef",
        "cattle"
    ],
    "wof:name":"Mary Ruth Jones",
    "wof:placetype":"venue"
},
  "geometry": {"coordinates":[-120.230205,46.396195],"type":"Point"}
}