{
  "type": "Feature",
  "properties": {
    "addr:full":"16 W Harrison St Seattle WA 98119",
    "addr:housenumber":"16",
    "addr:postcode":"98119",
    "addr:street":"W Harrison St",
    "iso:country":"US",
    "sg:address":"16 W Harrison St",
    "sg:city":"Seattle",
    "sg:classifiers":[
        {
            "category":"Personal",
            "subcategory":"Tanning Parlor",
            "type":"Services"
        }
    ],
    "sg:phone":"+1 206 235 9690",
    "sg:postcode":"98119",
    "sg:province":"WA",
    "sg:website":"www.sunlessstudios.com",
    "wof:name":"Sunless Studios",
    "wof:placetype":"venue"
},
  "geometry": {"coordinates":[-122.35695200000001,47.622115],"type":"Point"}
}