{
  "type": "Feature",
  "properties": {
    "addr:full":"200 E Market St Aberdeen WA 98520",
    "addr:housenumber":"200",
    "addr:postcode":"98520",
    "addr:street":"E Market St",
    "iso:country":"US",
    "sg:address":"200 E Market St",
    "sg:city":"Aberdeen",
    "sg:classifiers":[
        {
            "category":"Government",
            "subcategory":"Office",
            "type":"Public Place"
        }
    ],
    "sg:phone":"+1 360 533 4100",
    "sg:postcode":"98520",
    "sg:province":"WA",
    "sg:tags":[
        "executive"
    ],
    "wof:name":"City of Aberdeen",
    "wof:placetype":"venue"
},
  "geometry": {"coordinates":[-123.816461,46.976268],"type":"Point"}
}