{
  "type": "Feature",
  "properties": {
    "addr:full":"204 Main Ave Morton WA 98356",
    "addr:housenumber":"204",
    "addr:postcode":"98356",
    "addr:street":"Main Ave",
    "iso:country":"US",
    "sg:address":"204 Main Ave",
    "sg:city":"Morton",
    "sg:classifiers":[
        {
            "category":"Restaurant",
            "type":"Food & Drink"
        }
    ],
    "sg:phone":"+1 360 496 0041",
    "sg:postcode":"98356",
    "sg:province":"WA",
    "sg:tags":[
        "eating"
    ],
    "wof:name":"Diggers Diner & Pizzeria",
    "wof:placetype":"venue"
},
  "geometry": {"coordinates":[-122.269053,46.557562],"type":"Point"}
}