{
  "type": "Feature",
  "properties": {
    "addr:full":"516 SE Chkalov Dr Ste 45 Vancouver WA 98683",
    "addr:housenumber":"516",
    "addr:postcode":"98683",
    "addr:street":"Se Chkalov Dr Ste 45",
    "iso:country":"US",
    "sg:address":"516 SE Chkalov Dr Ste 45",
    "sg:city":"Vancouver",
    "sg:classifiers":[
        {
            "category":"Restaurant",
            "type":"Food & Drink"
        }
    ],
    "sg:phone":"+1 360 891 1490",
    "sg:postcode":"98683",
    "sg:province":"WA",
    "sg:tags":[
        "greek"
    ],
    "wof:name":"Jerusalem Cafe",
    "wof:placetype":"venue"
},
  "geometry": {"coordinates":[-122.554835,45.616751],"type":"Point"}
}