{
  "type": "Feature",
  "properties": {
    "addr:full":"1700 E Cherry St Seattle WA 98122",
    "addr:housenumber":"1700",
    "addr:postcode":"98122",
    "addr:street":"E Cherry St",
    "iso:country":"US",
    "sg:address":"1700 E Cherry St",
    "sg:city":"Seattle",
    "sg:classifiers":[
        {
            "category":"Government",
            "subcategory":"Office",
            "type":"Public Place"
        }
    ],
    "sg:phone":"+1 206 720 3190",
    "sg:postcode":"98122",
    "sg:province":"WA",
    "sg:tags":[
        "government-state"
    ],
    "wof:name":"Quality Control",
    "wof:placetype":"venue"
},
  "geometry": {"coordinates":[-122.310211,47.608028],"type":"Point"}
}