{
  "type": "Feature",
  "properties": {
    "addr:full":"106 N Laurel St Port Angeles WA 98362",
    "addr:housenumber":"106",
    "addr:postcode":"98362",
    "addr:street":"N Laurel St",
    "iso:country":"US",
    "sg:address":"106 N Laurel St",
    "sg:city":"Port Angeles",
    "sg:classifiers":[
        {
            "category":"Retail",
            "subcategory":"Photofinishing",
            "type":"Services"
        }
    ],
    "sg:phone":"+1 360 461 2720",
    "sg:postcode":"98362",
    "sg:province":"WA",
    "sg:tags":[
        "laboratory"
    ],
    "wof:name":"Studio 106 Digital Lab & Photo",
    "wof:placetype":"venue"
},
  "geometry": {"coordinates":[-123.432784,48.119866],"type":"Point"}
}