{
  "type": "Feature",
  "properties": {
    "addr:full":"1906 155th Ave NE Snohomish WA 98290",
    "addr:housenumber":"1906",
    "addr:postcode":"98290",
    "addr:street":"155Th Ave Ne",
    "iso:country":"US",
    "sg:address":"1906 155th Ave NE",
    "sg:city":"Snohomish",
    "sg:classifiers":[
        {
            "category":"Retail",
            "subcategory":"Repair Shop",
            "type":"Services"
        }
    ],
    "sg:phone":"+1 425 334 4770",
    "sg:postcode":"98290",
    "sg:province":"WA",
    "wof:name":"Glass Weld NW",
    "wof:placetype":"venue"
},
  "geometry": {"coordinates":[-122.02249399999999,48.015138],"type":"Point"}
}