{
  "type": "Feature",
  "properties": {
    "addr:full":"907 Pine St Seattle WA 98101",
    "addr:housenumber":"907",
    "addr:postcode":"98101",
    "addr:street":"Pine St",
    "iso:country":"US",
    "sg:address":"907 Pine St",
    "sg:city":"Seattle",
    "sg:classifiers":[
        {
            "category":"Airport",
            "type":"Transportation"
        }
    ],
    "sg:phone":"+1 206 835 7501",
    "sg:postcode":"98101",
    "sg:province":"WA",
    "wof:name":"Se-TAC International Airport",
    "wof:placetype":"venue"
},
  "geometry": {"coordinates":[-122.33093599999999,47.613899],"type":"Point"}
}