{
  "type": "Feature",
  "properties": {
    "addr:full":"10708 Country Club Ln S Seattle WA 98168",
    "addr:housenumber":"10708",
    "addr:postcode":"98168",
    "addr:street":"Country Club Ln",
    "iso:country":"US",
    "sg:address":"10708 Country Club Ln S",
    "sg:city":"Seattle",
    "sg:classifiers":[
        {
            "category":"Building & Trades",
            "subcategory":"Construction",
            "type":"Services"
        }
    ],
    "sg:phone":"+1 206 246 0982",
    "sg:postcode":"98168",
    "sg:province":"WA",
    "sg:tags":[
        "roofing",
        "industrial",
        "contractors-commercial",
        "contractor"
    ],
    "wof:name":"Kobel Roofing & Construction",
    "wof:placetype":"venue"
},
  "geometry": {"coordinates":[-122.313166,47.506315],"type":"Point"}
}