{
  "type": "Feature",
  "properties": {
    "addr:full":"2114 22nd Ave S Seattle WA 98144",
    "addr:housenumber":"2114",
    "addr:postcode":"98144",
    "addr:street":"22Nd Ave S",
    "iso:country":"US",
    "sg:address":"2114 22nd Ave S",
    "sg:city":"Seattle",
    "sg:classifiers":[
        {
            "category":"Retail",
            "subcategory":"Portrait Studio",
            "type":"Services"
        }
    ],
    "sg:phone":"+1 206 328 9095",
    "sg:postcode":"98144",
    "sg:province":"WA",
    "sg:tags":[
        "photographer"
    ],
    "wof:name":"J Warren Photography",
    "wof:placetype":"venue"
},
  "geometry": {"coordinates":[-122.304177,47.58378],"type":"Point"}
}