{
  "type": "Feature",
  "properties": {
    "addr:full":"101 Stewart Street Suite 1040 Seattle WA 98101",
    "addr:housenumber":"101",
    "addr:postcode":"98101",
    "addr:street":"Stewart Street Suite 1040",
    "iso:country":"US",
    "sg:address":"101 Stewart Street Suite 1040",
    "sg:city":"Seattle",
    "sg:classifiers":[
        {
            "category":"Professional",
            "subcategory":"Accounting & Tax Preparation",
            "type":"Services"
        }
    ],
    "sg:phone":"+1 206 621 9636",
    "sg:postcode":"98101",
    "sg:province":"WA",
    "sg:tags":[
        "accountant"
    ],
    "wof:name":"Christopfel Robert A Mba CPA",
    "wof:placetype":"venue"
},
  "geometry": {"coordinates":[-122.341324,47.61029],"type":"Point"}
}