{
  "type": "Feature",
  "properties": {
    "addr:full":"105 Mc Neil St Starbuck WA 99328",
    "addr:housenumber":"105",
    "addr:postcode":"99328",
    "addr:street":"Mc Neil St",
    "iso:country":"US",
    "sg:address":"105 Mc Neil St",
    "sg:city":"Starbuck",
    "sg:classifiers":[
        {
            "category":"Shopping",
            "subcategory":"Bicycles & Sporting Goods",
            "type":"Retail Goods"
        }
    ],
    "sg:phone":"+1 509 399 2015",
    "sg:postcode":"99328",
    "sg:province":"WA",
    "sg:tags":[
        "tackle",
        "fishing"
    ],
    "wof:name":"Darver Tackle",
    "wof:placetype":"venue"
},
  "geometry": {"coordinates":[-118.12737300000001,46.519255],"type":"Point"}
}