{
  "type": "Feature",
  "properties": {
    "addr:full":"126 Alder Spring Rd Lyle WA 98635",
    "addr:housenumber":"126",
    "addr:postcode":"98635",
    "addr:street":"Alder Spring Rd",
    "iso:country":"US",
    "sg:address":"126 Alder Spring Rd",
    "sg:city":"Lyle",
    "sg:classifiers":[
        {
            "category":"Education",
            "subcategory":"Special Training",
            "type":"Public Place"
        }
    ],
    "sg:phone":"+1 509 365 3972",
    "sg:postcode":"98635",
    "sg:province":"WA",
    "wof:name":"Institute For Earth Education",
    "wof:placetype":"venue"
},
  "geometry": {"coordinates":[-121.237196,45.706166],"type":"Point"}
}