{
  "type": "Feature",
  "properties": {
    "iso:country":"US",
    "sg:address":"6585 NE Columbia St",
    "sg:city":"Suquamish",
    "sg:classifiers":[
        {
            "category":"Building & Trades",
            "subcategory":"Landscaping Services",
            "type":"Services"
        }
    ],
    "sg:phone":"+1 360 598 3069",
    "sg:postcode":"98392",
    "sg:province":"WA",
    "sg:tags":[
        "landscape"
    ],
    "wof:name":"Shirley J Madle",
    "wof:placetype":"venue"
},
  "geometry": {"coordinates":[-122.560755,47.734614],"type":"Point"}
}