{
  "type": "Feature",
  "properties": {
    "addr:full":"2739 E Madison St Seattle WA 98112",
    "addr:housenumber":"2739",
    "addr:postcode":"98112",
    "addr:street":"E Madison St",
    "iso:country":"US",
    "sg:address":"2739 E Madison St",
    "sg:city":"Seattle",
    "sg:classifiers":[
        {
            "category":"Restaurant",
            "type":"Food & Drink"
        }
    ],
    "sg:phone":"+1 206 720 0335",
    "sg:postcode":"98112",
    "sg:province":"WA",
    "wof:name":"Teriyaki Seven",
    "wof:placetype":"venue"
},
  "geometry": {"coordinates":[-122.296997,47.6227],"type":"Point"}
}