{
  "type": "Feature",
  "properties": {
    "addr:full":"23 Ringold River Rd Mesa WA 99343",
    "addr:housenumber":"23",
    "addr:postcode":"99343",
    "addr:street":"Ringold River Rd",
    "iso:country":"US",
    "sg:address":"23 Ringold River Rd",
    "sg:city":"Mesa",
    "sg:classifiers":[
        {
            "category":"Farming",
            "subcategory":"Orchard",
            "type":"Manufacturing & Wholesale Goods"
        }
    ],
    "sg:phone":"+1 509 269 4332",
    "sg:postcode":"99343",
    "sg:province":"WA",
    "sg:tags":[
        "fruit",
        "tree"
    ],
    "wof:name":"McInturf Cherry Orchard",
    "wof:placetype":"venue"
},
  "geometry": {"coordinates":[-119.251693,46.494637],"type":"Point"}
}