{
  "type": "Feature",
  "properties": {
    "addr:full":"1723 S Huntington St Kennewick WA 99337",
    "addr:housenumber":"1723",
    "addr:postcode":"99337",
    "addr:street":"S Huntington St",
    "iso:country":"US",
    "sg:address":"1723 S Huntington St",
    "sg:city":"Kennewick",
    "sg:classifiers":[
        {
            "category":"Social Services",
            "subcategory":"Child Care",
            "type":"Services"
        }
    ],
    "sg:phone":"+1 509 586 9213",
    "sg:postcode":"99337",
    "sg:province":"WA",
    "sg:tags":[
        "day"
    ],
    "wof:name":"Little Peopless Workshop",
    "wof:placetype":"venue"
},
  "geometry": {"coordinates":[-119.162255,46.192435],"type":"Point"}
}