{
  "type": "Feature",
  "properties": {
    "addr:full":"1502 S Hazelwood Rd Spokane WA 99224",
    "addr:housenumber":"1502",
    "addr:postcode":"99224",
    "addr:street":"S Hazelwood Rd",
    "iso:country":"US",
    "sg:address":"1502 S Hazelwood Rd",
    "sg:city":"Spokane",
    "sg:classifiers":[
        {
            "category":"Professional",
            "subcategory":"Art Services",
            "type":"Services"
        }
    ],
    "sg:phone":"+1 509 747 8435",
    "sg:postcode":"99224",
    "sg:province":"WA",
    "sg:tags":[
        "fabricator",
        "designer"
    ],
    "wof:name":"Wayne Russell Company",
    "wof:placetype":"venue"
},
  "geometry": {"coordinates":[-117.555812,47.636848],"type":"Point"}
}