{
  "type": "Feature",
  "properties": {
    "addr:full":"1067 NW Luoto Rd Poulsbo WA 98370",
    "addr:housenumber":"1067",
    "addr:postcode":"98370",
    "addr:street":"Nw Luoto Rd",
    "iso:country":"US",
    "sg:address":"1067 NW Luoto Rd",
    "sg:city":"Poulsbo",
    "sg:classifiers":[
        {
            "category":"Professional",
            "subcategory":"Art Services",
            "type":"Services"
        }
    ],
    "sg:phone":"+1 360 779 6929",
    "sg:postcode":"98370",
    "sg:province":"WA",
    "sg:tags":[
        "motion",
        "commercial",
        "prod",
        "design"
    ],
    "wof:name":"One Acre Plus",
    "wof:placetype":"venue"
},
  "geometry": {"coordinates":[-122.663312,47.704467],"type":"Point"}
}