{
  "type": "Feature",
  "properties": {
    "addr:full":"390 N Cherry Dr Pasco WA 99301",
    "addr:housenumber":"390",
    "addr:postcode":"99301",
    "addr:street":"N Cherry Dr",
    "iso:country":"US",
    "sg:address":"390 N Cherry Dr",
    "sg:city":"Pasco",
    "sg:phone":"+1 509 266 4202",
    "sg:postcode":"99301",
    "sg:province":"WA",
    "sg:tags":[
        "farm",
        "field",
        "grape",
        "crop",
        "vineyard"
    ],
    "wof:name":"Mc Call Brothers Inc",
    "wof:placetype":"venue"
},
  "geometry": {"coordinates":[-119.175912,46.409395],"type":"Point"}
}