{
  "type": "Feature",
  "properties": {
    "addr:full":"317 Glen Ave Snohomish WA 98290",
    "addr:housenumber":"317",
    "addr:postcode":"98290",
    "addr:street":"Glen Ave",
    "iso:country":"US",
    "sg:address":"317 Glen Ave",
    "sg:city":"Snohomish",
    "sg:classifiers":[
        {
            "category":"Travel",
            "subcategory":"Hotels & Motels",
            "type":"Entertainment"
        }
    ],
    "sg:phone":"+1 360 568 2042",
    "sg:postcode":"98290",
    "sg:province":"WA",
    "sg:tags":[
        "operation"
    ],
    "wof:name":"Redmond House Bed & Breakfast",
    "wof:placetype":"venue"
},
  "geometry": {"coordinates":[-122.091459,47.91553],"type":"Point"}
}