{
  "type": "Feature",
  "properties": {
    "addr:full":"2036 4th Ave E Olympia WA 98506",
    "addr:housenumber":"2036",
    "addr:postcode":"98506",
    "addr:street":"4Th Ave E",
    "iso:country":"US",
    "sg:address":"2036 4th Ave E",
    "sg:city":"Olympia",
    "sg:classifiers":[
        {
            "category":"Retail",
            "subcategory":"Auto Repair",
            "type":"Services"
        }
    ],
    "sg:phone":"+1 360 943 8240",
    "sg:postcode":"98506",
    "sg:province":"WA",
    "sg:tags":[
        "repairing",
        "automobile"
    ],
    "sg:website":"www.jerrysautomotiveandtowing.com",
    "wof:name":"Jerry's Automotive & Towing",
    "wof:placetype":"venue"
},
  "geometry": {"coordinates":[-122.87197,47.046107],"type":"Point"}
}