{
  "type": "Feature",
  "properties": {
    "addr:full":"5521 116th Ave NE Kirkland WA 98033",
    "addr:housenumber":"5521",
    "addr:postcode":"98033",
    "addr:street":"116Th Ave Ne",
    "iso:country":"US",
    "sg:address":"5521 116th Ave NE",
    "sg:city":"Kirkland",
    "sg:classifiers":[
        {
            "category":"Building & Trades",
            "subcategory":"Construction",
            "type":"Services"
        }
    ],
    "sg:phone":"+1 425 822 8746",
    "sg:postcode":"98033",
    "sg:province":"WA",
    "sg:tags":[
        "specializing",
        "subcontractor",
        "drywall"
    ],
    "wof:name":"Campbell & Campbell Inc",
    "wof:placetype":"venue"
},
  "geometry": {"coordinates":[-122.185672,47.657857],"type":"Point"}
}