{
  "type": "Feature",
  "properties": {
    "addr:full":"824 Mullis St Friday Harbor WA 98250",
    "addr:housenumber":"824",
    "addr:postcode":"98250",
    "addr:street":"Mullis St",
    "iso:country":"US",
    "sg:address":"824 Mullis St",
    "sg:city":"Friday Harbor",
    "sg:phone":"+1 360 370 5511",
    "sg:postcode":"98250",
    "sg:province":"WA",
    "sg:tags":[
        "liquefied",
        "product",
        "gas",
        "petroleum"
    ],
    "wof:name":"Vander Yacht Propane Inc",
    "wof:placetype":"venue"
},
  "geometry": {"coordinates":[-123.023105,48.526414],"type":"Point"}
}