{
  "type": "Feature",
  "properties": {
    "addr:full":"327 NE 5th Ave Camas WA 98607",
    "addr:housenumber":"327",
    "addr:postcode":"98607",
    "addr:street":"Ne 5Th Ave",
    "iso:country":"US",
    "sg:address":"327 NE 5th Ave",
    "sg:city":"Camas",
    "sg:classifiers":[
        {
            "category":"Health Services",
            "subcategory":"Doctor",
            "type":"Services"
        }
    ],
    "sg:phone":"+1 360 834 3141",
    "sg:postcode":"98607",
    "sg:province":"WA",
    "sg:tags":[
        "practice",
        "family"
    ],
    "wof:name":"Hagen David J MD",
    "wof:placetype":"venue"
},
  "geometry": {"coordinates":[-122.404999,45.586201],"type":"Point"}
}