{
  "type": "Feature",
  "properties": {
    "addr:full":"1115 S 9th St Sunnyside WA 98944",
    "addr:housenumber":"1115",
    "addr:postcode":"98944",
    "addr:street":"S 9Th St",
    "iso:country":"US",
    "sg:address":"1115 S 9th St",
    "sg:city":"Sunnyside",
    "sg:classifiers":[
        {
            "category":"Social Services",
            "subcategory":"Child Care",
            "type":"Services"
        }
    ],
    "sg:phone":"+1 509 836 2479",
    "sg:postcode":"98944",
    "sg:province":"WA",
    "sg:tags":[
        "center",
        "day"
    ],
    "wof:name":"Sunnyside Rhs",
    "wof:placetype":"venue"
},
  "geometry": {"coordinates":[-120.008539,46.317241],"type":"Point"}
}