{
  "type": "Feature",
  "properties": {
    "addr:full":"7619 139th Street Ct E Puyallup WA 98373",
    "addr:housenumber":"7619",
    "addr:postcode":"98373",
    "addr:street":"139Th Street Ct E",
    "iso:country":"US",
    "sg:address":"7619 139th Street Ct E",
    "sg:city":"Puyallup",
    "sg:classifiers":[
        {
            "category":"Wholesale",
            "subcategory":"Electrical",
            "type":"Manufacturing & Wholesale Goods"
        }
    ],
    "sg:phone":"+1 253 539 4600",
    "sg:postcode":"98373",
    "sg:province":"WA",
    "sg:tags":[
        "control"
    ],
    "wof:name":"NCS Corp",
    "wof:placetype":"venue"
},
  "geometry": {"coordinates":[-122.32849,47.129776],"type":"Point"}
}