{
  "type": "Feature",
  "properties": {
    "addr:full":"202 E Pioneer Ave Puyallup WA 98372",
    "addr:housenumber":"202",
    "addr:postcode":"98372",
    "addr:street":"E Pioneer Ave",
    "iso:country":"US",
    "sg:address":"202 E Pioneer Ave",
    "sg:city":"Puyallup",
    "sg:classifiers":[
        {
            "category":"Shopping",
            "subcategory":"Hobbies, Toys, & Games",
            "type":"Retail Goods"
        }
    ],
    "sg:phone":"+1 253 845 9759",
    "sg:postcode":"98372",
    "sg:province":"WA",
    "wof:name":"Trackside Trains",
    "wof:placetype":"venue"
},
  "geometry": {"coordinates":[-122.29130600000001,47.190374],"type":"Point"}
}