{
  "type": "Feature",
  "properties": {
    "addr:full":"4701 NE 72nd Ave Ofc Vancouver WA 98661",
    "addr:housenumber":"4701",
    "addr:postcode":"98661",
    "addr:street":"Ne 72Nd Ave",
    "iso:country":"US",
    "sg:address":"4701 NE 72nd Ave Ofc",
    "sg:city":"Vancouver",
    "sg:classifiers":[
        {
            "category":"Real Estate",
            "subcategory":"Real Estate Operator",
            "type":"Services"
        }
    ],
    "sg:phone":"+1 360 896 8151",
    "sg:postcode":"98661",
    "sg:province":"WA",
    "sg:tags":[
        "apartment"
    ],
    "wof:name":"Brentwood Apartments the",
    "wof:placetype":"venue"
},
  "geometry": {"coordinates":[-122.59899900000001,45.655899],"type":"Point"}
}