{
  "type": "Feature",
  "properties": {
    "addr:full":"3123 NE 4th St Renton WA 98056",
    "addr:housenumber":"3123",
    "addr:postcode":"98056",
    "addr:street":"Ne 4Th St",
    "iso:country":"US",
    "sg:address":"3123 NE 4th St",
    "sg:city":"Renton",
    "sg:classifiers":[
        {
            "category":"Autos & Motor Vehicles",
            "subcategory":"Auto Supplies",
            "type":"Retail Goods"
        }
    ],
    "sg:phone":"+1 425 226 6706",
    "sg:postcode":"98056",
    "sg:province":"WA",
    "sg:tags":[
        "tire"
    ],
    "sg:website":"www.discounttire.com/makeappt",
    "wof:name":"Discount Tire",
    "wof:placetype":"venue"
},
  "geometry": {"coordinates":[-122.17706800000001,47.48805],"type":"Point"}
}