{
  "type": "Feature",
  "properties": {
    "addr:full":"73535 N Pederson Rd West Richland WA 99353",
    "addr:housenumber":"73535",
    "addr:postcode":"99353",
    "addr:street":"N Pederson Rd West",
    "iso:country":"US",
    "sg:address":"73535 N Pederson Rd",
    "sg:city":"West Richland",
    "sg:classifiers":[
        {
            "category":"Recreation",
            "type":"Entertainment"
        }
    ],
    "sg:phone":"+1 509 308 7666",
    "sg:postcode":"99353",
    "sg:province":"WA",
    "sg:tags":[
        "guide"
    ],
    "wof:name":"Sunrise Guide Svc",
    "wof:placetype":"venue"
},
  "geometry": {"coordinates":[-119.361814,46.317042],"type":"Point"}
}