{
  "type": "Feature",
  "properties": {
    "addr:full":"3108 E Mill Plain Blvd Vancouver WA 98661",
    "addr:housenumber":"3108",
    "addr:postcode":"98661",
    "addr:street":"E Mill Plain Blvd",
    "iso:country":"US",
    "sg:address":"3108 E Mill Plain Blvd",
    "sg:city":"Vancouver",
    "sg:classifiers":[
        {
            "category":"Building & Trades",
            "subcategory":"Cleaning & Sanitation",
            "type":"Services"
        }
    ],
    "sg:phone":"+1 360 253 3179",
    "sg:postcode":"98661",
    "sg:province":"WA",
    "sg:tags":[
        "house"
    ],
    "wof:name":"A B Cleaning & Janitorial",
    "wof:placetype":"venue"
},
  "geometry": {"coordinates":[-122.63771,45.628275],"type":"Point"}
}