{
  "type": "Feature",
  "properties": {
    "addr:full":"16505 SE 1st St Vancouver WA 98684",
    "addr:postcode":"16505;98684",
    "addr:street":"Se 1St St",
    "iso:country":"US",
    "sg:address":"16505 SE 1st St",
    "sg:city":"Vancouver",
    "sg:classifiers":[
        {
            "category":"Restaurant",
            "type":"Food & Drink"
        }
    ],
    "sg:phone":"+1 360 253 2394",
    "sg:postcode":"98684",
    "sg:province":"WA",
    "sg:tags":[
        "italian",
        "pizza"
    ],
    "sg:website":"www.leonardospizzeria.com",
    "wof:name":"Leonardo's Pizzeria",
    "wof:placetype":"venue"
},
  "geometry": {"coordinates":[-122.502408,45.620761],"type":"Point"}
}