{
  "type": "Feature",
  "properties": {
    "addr:full":"2040 152nd Ave NE Redmond WA 98052",
    "addr:housenumber":"2040",
    "addr:postcode":"98052",
    "addr:street":"152Nd Ave Ne",
    "iso:country":"US",
    "sg:address":"2040 152nd Ave NE",
    "sg:city":"Redmond",
    "sg:classifiers":[
        {
            "category":"Retail",
            "subcategory":"Auto Repair",
            "type":"Services"
        }
    ],
    "sg:phone":"+1 425 373 5729",
    "sg:postcode":"98052",
    "sg:province":"WA",
    "sg:tags":[
        "general"
    ],
    "wof:name":"Auto Pro",
    "wof:placetype":"venue"
},
  "geometry": {"coordinates":[-122.13764999999999,47.628575],"type":"Point"}
}