{
  "type": "Feature",
  "properties": {
    "addr:full":"1908 S 341st Pl Federal Way WA 98003",
    "addr:housenumber":"1908",
    "addr:postcode":"98003",
    "addr:street":"S 341St Pl",
    "iso:country":"US",
    "sg:address":"1908 S 341st Pl",
    "sg:city":"Federal Way",
    "sg:classifiers":[
        {
            "category":"Manufacturing",
            "subcategory":"Metals",
            "type":"Manufacturing & Wholesale Goods"
        }
    ],
    "sg:phone":"+1 253 874 1223",
    "sg:postcode":"98003",
    "sg:province":"WA",
    "sg:tags":[
        "product",
        "wire",
        "fabricated",
        "mfg"
    ],
    "wof:name":"United Subcontractors Inc",
    "wof:placetype":"venue"
},
  "geometry": {"coordinates":[-122.30788200000001,47.296212],"type":"Point"}
}