{
  "type": "Feature",
  "properties": {
    "addr:full":"350 E Delaware Ave Stop 9 Republic WA 99166",
    "addr:housenumber":"350",
    "addr:postcode":"99166",
    "addr:street":"E Delaware Ave Stop;Republic",
    "iso:country":"US",
    "sg:address":"350 E Delaware Ave Stop 9",
    "sg:city":"Republic",
    "sg:classifiers":[
        {
            "category":"Government",
            "subcategory":"Office",
            "type":"Public Place"
        }
    ],
    "sg:phone":"+1 509 775 5235",
    "sg:postcode":"99166",
    "sg:province":"WA",
    "sg:tags":[
        "parish",
        "government-county"
    ],
    "sg:website":"http://www.dailyevergreen.com",
    "wof:name":"Wsu Co-Op Extension",
    "wof:placetype":"venue"
},
  "geometry": {"coordinates":[-118.73417999999999,48.648995],"type":"Point"}
}