{
  "type": "Feature",
  "properties": {
    "addr:full":"2707 N Yakima Ave Tacoma WA 98406",
    "addr:housenumber":"2707",
    "addr:postcode":"98406",
    "addr:street":"N Yakima Ave",
    "iso:country":"US",
    "sg:address":"2707 N Yakima Ave",
    "sg:city":"Tacoma",
    "sg:classifiers":[
        {
            "category":"Organizations",
            "subcategory":"Religious Organization",
            "type":"Services"
        }
    ],
    "sg:phone":"+1 253 761 9971",
    "sg:postcode":"98406",
    "sg:province":"WA",
    "sg:tags":[
        "church"
    ],
    "wof:name":"Tapestry Covenant Church",
    "wof:placetype":"venue"
},
  "geometry": {"coordinates":[-122.470353,47.268755],"type":"Point"}
}