{
  "type": "Feature",
  "properties": {
    "addr:full":"5321 Illahee Rd NE Bremerton WA 98311",
    "addr:housenumber":"5321",
    "addr:postcode":"98311",
    "addr:street":"Illahee Rd Ne",
    "iso:country":"US",
    "sg:address":"5321 Illahee Rd NE",
    "sg:city":"Bremerton",
    "sg:classifiers":[
        {
            "category":"Retail",
            "subcategory":"Portrait Studio",
            "type":"Services"
        }
    ],
    "sg:phone":"+1 360 377 9494",
    "sg:postcode":"98311",
    "sg:province":"WA",
    "sg:tags":[
        "photographer"
    ],
    "wof:name":"Forever Yours Photos",
    "wof:placetype":"venue"
},
  "geometry": {"coordinates":[-122.59703399999999,47.611889],"type":"Point"}
}