{
  "type": "Feature",
  "properties": {
    "addr:full":"2814 W Lynn St Seattle WA 98199",
    "addr:housenumber":"2814",
    "addr:postcode":"98199",
    "addr:street":"W Lynn St",
    "iso:country":"US",
    "sg:address":"2814 W Lynn St",
    "sg:city":"Seattle",
    "sg:classifiers":[
        {
            "category":"Professional",
            "subcategory":"Accounting & Tax Preparation",
            "type":"Services"
        }
    ],
    "sg:phone":"+1 206 285 9084",
    "sg:postcode":"98199",
    "sg:province":"WA",
    "wof:name":"Lori R Cleaves CPA",
    "wof:placetype":"venue"
},
  "geometry": {"coordinates":[-122.394104,47.638908],"type":"Point"}
}