{
  "type": "Feature",
  "properties": {
    "addr:full":"23422 Pacific Hwy S Kent WA 98032",
    "addr:housenumber":"23422",
    "addr:postcode":"98032",
    "addr:street":"Pacific Hwy S",
    "iso:country":"US",
    "sg:address":"23422 Pacific Hwy S",
    "sg:city":"Kent",
    "sg:classifiers":[
        {
            "category":"Restaurant",
            "type":"Food & Drink"
        }
    ],
    "sg:phone":"+1 206 878 2608",
    "sg:postcode":"98032",
    "sg:province":"WA",
    "sg:tags":[
        "eating"
    ],
    "wof:name":"Jims Espresso",
    "wof:placetype":"venue"
},
  "geometry": {"coordinates":[-122.29515600000001,47.391801],"type":"Point"}
}