{
  "type": "Feature",
  "properties": {
    "addr:full":"10408 Silverdale Way NW Silverdale WA 98383",
    "addr:housenumber":"10408",
    "addr:postcode":"98383",
    "addr:street":"Silverdale Way Nw",
    "iso:country":"US",
    "sg:address":"10408 Silverdale Way NW",
    "sg:city":"Silverdale",
    "sg:classifiers":[
        {
            "category":"Personal",
            "subcategory":"Beauty Salon",
            "type":"Services"
        }
    ],
    "sg:phone":"+1 360 698 1880",
    "sg:postcode":"98383",
    "sg:province":"WA",
    "wof:name":"Hair Attractions Silverdale",
    "wof:placetype":"venue"
},
  "geometry": {"coordinates":[-122.68709699999999,47.65726],"type":"Point"}
}