{
  "type": "Feature",
  "properties": {
    "addr:full":"767 Village Cir NW Bainbridge Island WA 98110",
    "addr:housenumber":"767",
    "addr:postcode":"98110",
    "addr:street":"Village Cir Nw",
    "iso:country":"US",
    "sg:address":"767 Village Cir NW",
    "sg:city":"Bainbridge Island",
    "sg:classifiers":[
        {
            "category":"Professional",
            "subcategory":"Business Services",
            "type":"Services"
        }
    ],
    "sg:phone":"+1 206 842 7211",
    "sg:postcode":"98110",
    "sg:province":"WA",
    "sg:tags":[
        "investigation"
    ],
    "wof:name":"Douglas K Leroy",
    "wof:placetype":"venue"
},
  "geometry": {"coordinates":[-122.52995,47.630922],"type":"Point"}
}