{
  "type": "Feature",
  "properties": {
    "addr:full":"3029 E Sinto Ave Spokane WA 99202",
    "addr:housenumber":"3029",
    "addr:postcode":"99202",
    "addr:street":"E Sinto Ave",
    "iso:country":"US",
    "sg:address":"3029 E Sinto Ave",
    "sg:city":"Spokane",
    "sg:classifiers":[
        {
            "category":"Retail",
            "subcategory":"Auto Repair",
            "type":"Services"
        }
    ],
    "sg:phone":"+1 509 533 9235",
    "sg:postcode":"99202",
    "sg:province":"WA",
    "sg:tags":[
        "repairing",
        "automobile",
        "general"
    ],
    "wof:name":"Automotive Repair Service",
    "wof:placetype":"venue"
},
  "geometry": {"coordinates":[-117.365621,47.671014],"type":"Point"}
}