{
  "type": "Feature",
  "properties": {
    "addr:full":"12802 New 125th Way Kirkland WA 98033",
    "addr:housenumber":"12802",
    "addr:postcode":"98033",
    "addr:street":"New 125Th Way",
    "iso:country":"US",
    "sg:address":"12802 New 125th Way",
    "sg:city":"Kirkland",
    "sg:classifiers":[
        {
            "category":"Professional",
            "subcategory":"Computer Services",
            "type":"Services"
        }
    ],
    "sg:phone":"+1 425 821 0574",
    "sg:postcode":"98033",
    "sg:province":"WA",
    "sg:tags":[
        "repair"
    ],
    "wof:name":"Tec Works Inc",
    "wof:placetype":"venue"
},
  "geometry": {"coordinates":[-122.1734,47.716383],"type":"Point"}
}