{
  "type": "Feature",
  "properties": {
    "addr:full":"19100 Huntington St SW Rochester WA 98579",
    "addr:housenumber":"19100",
    "addr:postcode":"98579",
    "addr:street":"Huntington St Sw",
    "iso:country":"US",
    "sg:address":"19100 Huntington St SW",
    "sg:city":"Rochester",
    "sg:classifiers":[
        {
            "category":"Professional",
            "type":"Services"
        }
    ],
    "sg:phone":"+1 360 357 6385",
    "sg:postcode":"98579",
    "sg:province":"WA",
    "wof:name":"Nicelydone Inc",
    "wof:placetype":"venue"
},
  "geometry": {"coordinates":[-123.057777,46.807288],"type":"Point"}
}