{
  "type": "Feature",
  "properties": {
    "addr:full":"129 Broadway E Seattle WA 98102",
    "addr:housenumber":"129",
    "addr:postcode":"98102",
    "addr:street":"Broadway",
    "iso:country":"US",
    "sg:address":"129 Broadway E",
    "sg:city":"Seattle",
    "sg:classifiers":[
        {
            "category":"Cinema",
            "subcategory":"Movie Rental",
            "type":"Entertainment"
        }
    ],
    "sg:phone":"+1 206 325 5044",
    "sg:postcode":"98102",
    "sg:province":"WA",
    "sg:tags":[
        "video",
        "tape"
    ],
    "sg:website":"www.hollywoodvideo.com",
    "wof:name":"Hollywood Video",
    "wof:placetype":"venue"
},
  "geometry": {"coordinates":[-122.32094600000001,47.619571],"type":"Point"}
}