{
  "type": "Feature",
  "properties": {
    "addr:full":"117 E Rose St Walla Walla WA 99362",
    "addr:housenumber":"117",
    "addr:postcode":"99362",
    "addr:street":"E Rose St",
    "iso:country":"US",
    "sg:address":"117 E Rose St",
    "sg:city":"Walla Walla",
    "sg:classifiers":[
        {
            "category":"Professional",
            "subcategory":"Accounting & Tax Preparation",
            "type":"Services"
        }
    ],
    "sg:phone":"+1 509 529 1068",
    "sg:postcode":"99362",
    "sg:province":"WA",
    "wof:name":"Professional Computer Services",
    "wof:placetype":"venue"
},
  "geometry": {"coordinates":[-118.33768000000001,46.069306],"type":"Point"}
}