{
  "type": "Feature",
  "properties": {
    "addr:full":"2146 NW Shy Bear Way Issaquah WA 98027",
    "addr:housenumber":"2146",
    "addr:postcode":"98027",
    "addr:street":"Nw Shy Bear Way",
    "iso:country":"US",
    "sg:address":"2146 NW Shy Bear Way",
    "sg:city":"Issaquah",
    "sg:classifiers":[
        {
            "category":"Utilities",
            "subcategory":"Cable",
            "type":"Services"
        }
    ],
    "sg:phone":"+1 425 891 9227",
    "sg:postcode":"98027",
    "sg:province":"WA",
    "sg:tags":[
        "television"
    ],
    "wof:name":"Cable Guy",
    "wof:placetype":"venue"
},
  "geometry": {"coordinates":[-122.069001,47.530519],"type":"Point"}
}