{
  "type": "Feature",
  "properties": {
    "addr:full":"14912 83rd Ave NW Gig Harbor WA 98329",
    "addr:housenumber":"14912",
    "addr:postcode":"98329",
    "addr:street":"83Rd Ave Nw",
    "iso:country":"US",
    "sg:address":"14912 83rd Ave NW",
    "sg:city":"Gig Harbor",
    "sg:classifiers":[
        {
            "category":"Retail",
            "subcategory":"Repair Shop",
            "type":"Services"
        }
    ],
    "sg:phone":"+1 253 857 2899",
    "sg:postcode":"98329",
    "sg:province":"WA",
    "sg:tags":[
        "equipment",
        "industrial"
    ],
    "wof:name":"Gardner Enterprises Inc",
    "wof:placetype":"venue"
},
  "geometry": {"coordinates":[-122.64945,47.393859],"type":"Point"}
}