{
  "type": "Feature",
  "properties": {
    "addr:full":"2001 Western Ave Seattle WA 98121",
    "addr:housenumber":"2001",
    "addr:postcode":"98121",
    "addr:street":"Western Ave",
    "iso:country":"US",
    "sg:address":"2001 Western Ave",
    "sg:city":"Seattle",
    "sg:classifiers":[
        {
            "category":"Health Services",
            "subcategory":"Health Practitioner",
            "type":"Services"
        }
    ],
    "sg:phone":"+1 206 443 0868",
    "sg:postcode":"98121",
    "sg:province":"WA",
    "sg:tags":[
        "psychologist"
    ],
    "wof:name":"Peters Linda Phd",
    "wof:placetype":"venue"
},
  "geometry": {"coordinates":[-122.34369700000001,47.61034],"type":"Point"}
}