{
  "type": "Feature",
  "properties": {
    "addr:full":"3812 W Jay St Pasco WA 99301",
    "addr:housenumber":"3812",
    "addr:postcode":"99301",
    "addr:street":"W Jay St",
    "iso:country":"US",
    "sg:address":"3812 W Jay St",
    "sg:city":"Pasco",
    "sg:classifiers":[
        {
            "category":"Insurance",
            "subcategory":"Insurance Agent",
            "type":"Services"
        }
    ],
    "sg:phone":"+1 509 545 4820",
    "sg:postcode":"99301",
    "sg:province":"WA",
    "wof:name":"Grants Transcription Service",
    "wof:placetype":"venue"
},
  "geometry": {"coordinates":[-119.14313,46.24781],"type":"Point"}
}