{
  "type": "Feature",
  "properties": {
    "addr:full":"1610 SW 168th St Seattle WA 98166",
    "addr:housenumber":"1610",
    "addr:postcode":"98166",
    "addr:street":"Sw 168Th St",
    "iso:country":"US",
    "sg:address":"1610 SW 168th St",
    "sg:city":"Seattle",
    "sg:classifiers":[
        {
            "category":"Professional",
            "subcategory":"Business Services",
            "type":"Services"
        }
    ],
    "sg:phone":"+1 206 241 9099",
    "sg:postcode":"98166",
    "sg:province":"WA",
    "sg:tags":[
        "development",
        "accounting",
        "forensic",
        "lead"
    ],
    "wof:name":"RB & P",
    "wof:placetype":"venue"
},
  "geometry": {"coordinates":[-122.35784099999999,47.452422],"type":"Point"}
}