{
  "type": "Feature",
  "properties": {
    "addr:full":"4511 E Russell Rd Colbert WA 99005",
    "addr:housenumber":"4511",
    "addr:postcode":"99005",
    "addr:street":"E Russell Rd Colbert",
    "iso:country":"US",
    "sg:address":"4511 E Russell Rd",
    "sg:city":"Colbert",
    "sg:classifiers":[
        {
            "category":"Farming",
            "subcategory":"Nursery",
            "type":"Manufacturing & Wholesale Goods"
        }
    ],
    "sg:phone":"+1 509 238 4048",
    "sg:postcode":"99005",
    "sg:province":"WA",
    "sg:tags":[
        "ornamental"
    ],
    "wof:name":"Halloman Nursery",
    "wof:placetype":"venue"
},
  "geometry": {"coordinates":[-117.341244,47.8695],"type":"Point"}
}