{
  "type": "Feature",
  "properties": {
    "addr:full":"3700 W Commodore Way Seattle WA 98199",
    "addr:housenumber":"3700",
    "addr:postcode":"98199",
    "addr:street":"W Commodore Way",
    "iso:country":"US",
    "sg:address":"3700 W Commodore Way",
    "sg:city":"Seattle",
    "sg:classifiers":[
        {
            "category":"Recreation",
            "subcategory":"Boat Charter",
            "type":"Entertainment"
        }
    ],
    "sg:phone":"+1 206 284 2270",
    "sg:postcode":"98199",
    "sg:province":"WA",
    "sg:tags":[
        "boat-rental"
    ],
    "wof:name":"Commodore Marine Corp Inc",
    "wof:placetype":"venue"
},
  "geometry": {"coordinates":[-122.405811,47.666015],"type":"Point"}
}