{
  "type": "Feature",
  "properties": {
    "addr:full":"1905 Broadway Bellingham WA 98225",
    "addr:housenumber":"1905",
    "addr:postcode":"98225",
    "addr:street":"Broadway",
    "iso:country":"US",
    "sg:address":"1905 Broadway",
    "sg:city":"Bellingham",
    "sg:classifiers":[
        {
            "category":"Professional",
            "subcategory":"Engineering",
            "type":"Services"
        },
        {
            "category":"Government",
            "subcategory":"Office",
            "type":"Public Place"
        }
    ],
    "sg:phone":"+1 360 650 9000",
    "sg:postcode":"98225",
    "sg:province":"WA",
    "sg:tags":[
        "management"
    ],
    "wof:name":"Hydrologic Services Company",
    "wof:placetype":"venue"
},
  "geometry": {"coordinates":[-122.48624100000001,48.761322],"type":"Point"}
}