{
  "type": "Feature",
  "properties": {
    "addr:full":"701 S Lander St Seattle WA 98134",
    "addr:housenumber":"701",
    "addr:postcode":"98134",
    "addr:street":"S Lander St",
    "iso:country":"US",
    "sg:address":"701 S Lander St",
    "sg:city":"Seattle",
    "sg:classifiers":[
        {
            "category":"Building & Trades",
            "subcategory":"Construction",
            "type":"Services"
        }
    ],
    "sg:phone":"+1 206 625 0515",
    "sg:postcode":"98134",
    "sg:province":"WA",
    "sg:tags":[
        "wallcoverings-installation",
        "wallpaper",
        "painting",
        "contractor"
    ],
    "wof:name":"Morgan'sfine Finishing",
    "wof:placetype":"venue"
},
  "geometry": {"coordinates":[-122.32531400000001,47.5798],"type":"Point"}
}