{
  "type": "Feature",
  "properties": {
    "addr:full":"1715 N Lafayette Ave Bremerton WA 98312",
    "addr:housenumber":"1715",
    "addr:postcode":"98312",
    "addr:street":"N Lafayette Ave",
    "iso:country":"US",
    "sg:address":"1715 N Lafayette Ave",
    "sg:city":"Bremerton",
    "sg:classifiers":[
        {
            "category":"Building & Trades",
            "subcategory":"Construction",
            "type":"Services"
        }
    ],
    "sg:phone":"+1 206 852 6372",
    "sg:postcode":"98312",
    "sg:province":"WA",
    "sg:tags":[
        "consulting",
        "commercial"
    ],
    "wof:name":"NBD",
    "wof:placetype":"venue"
},
  "geometry": {"coordinates":[-122.656657,47.578243],"type":"Point"}
}