{
  "type": "Feature",
  "properties": {
    "addr:full":"110 Main St Ste 101 Edmonds WA 98020",
    "addr:housenumber":"110",
    "addr:postcode":"98020",
    "addr:street":"Main St Ste 101",
    "iso:country":"US",
    "sg:address":"110 Main St Ste 101",
    "sg:city":"Edmonds",
    "sg:classifiers":[
        {
            "category":"Health Services",
            "subcategory":"Chiropractor",
            "type":"Services"
        }
    ],
    "sg:phone":"+1 425 774 2804",
    "sg:postcode":"98020",
    "sg:province":"WA",
    "sg:tags":[
        "chiropractic"
    ],
    "wof:name":"Center For Structural Medicine",
    "wof:placetype":"venue"
},
  "geometry": {"coordinates":[-122.38184099999999,47.812231],"type":"Point"}
}