{
  "type": "Feature",
  "properties": {
    "addr:full":"102 N 3rd St Yakima WA 98901",
    "addr:housenumber":"102",
    "addr:postcode":"98901",
    "addr:street":"N 3Rd St",
    "iso:country":"US",
    "sg:address":"102 N 3rd St",
    "sg:city":"Yakima",
    "sg:classifiers":[
        {
            "category":"Education",
            "subcategory":"Library",
            "type":"Public Place"
        }
    ],
    "sg:phone":"+1 509 452 8541",
    "sg:postcode":"98901",
    "sg:province":"WA",
    "sg:website":"www.yvrl.org",
    "wof:name":"Yakima Valley Regional Library",
    "wof:placetype":"venue"
},
  "geometry": {"coordinates":[-120.50435400000001,46.605388],"type":"Point"}
}