{
  "type": "Feature",
  "properties": {
    "addr:full":"6813 245th Ave E Buckley WA 98321",
    "addr:housenumber":"6813",
    "addr:postcode":"98321",
    "addr:street":"245Th Ave E",
    "iso:country":"US",
    "sg:address":"6813 245th Ave E",
    "sg:city":"Buckley",
    "sg:classifiers":[
        {
            "category":"Building & Trades",
            "subcategory":"Construction",
            "type":"Services"
        }
    ],
    "sg:phone":"+1 253 826 1741",
    "sg:postcode":"98321",
    "sg:province":"WA",
    "sg:tags":[
        "house"
    ],
    "wof:name":"Diamond Construction",
    "wof:placetype":"venue"
},
  "geometry": {"coordinates":[-122.10275,47.195091],"type":"Point"}
}