{
  "type": "Feature",
  "properties": {
    "addr:full":"4253 Woodland Park Ave N Seattle WA 98103",
    "addr:housenumber":"4253",
    "addr:postcode":"98103",
    "addr:street":"Woodland Park Ave N",
    "iso:country":"US",
    "sg:address":"4253 Woodland Park Ave N",
    "sg:city":"Seattle",
    "sg:classifiers":[
        {
            "category":"Health Services",
            "subcategory":"Doctor",
            "type":"Services"
        }
    ],
    "sg:phone":"+1 206 623 0644",
    "sg:postcode":"98103",
    "sg:province":"WA",
    "sg:tags":[
        "medicine",
        "physician",
        "forensic",
        "surgeons"
    ],
    "wof:name":"Emerald City Forensics Inc.",
    "wof:placetype":"venue"
},
  "geometry": {"coordinates":[-122.344612,47.658715],"type":"Point"}
}