{
  "type": "Feature",
  "properties": {
    "addr:full":"15531 SE 37th St Bellevue WA 98006",
    "addr:postcode":"15531;98006",
    "addr:street":"Se 37Th St",
    "iso:country":"US",
    "sg:address":"15531 SE 37th St",
    "sg:city":"Bellevue",
    "sg:classifiers":[
        {
            "category":"Travel",
            "subcategory":"Hotels & Motels",
            "type":"Entertainment"
        },
        {
            "category":"Building & Trades",
            "subcategory":"Construction",
            "type":"Services"
        },
        {
            "category":"Recreation",
            "subcategory":"Campground",
            "type":"Entertainment"
        }
    ],
    "sg:phone":"+1 425 747 9181",
    "sg:postcode":"98006",
    "sg:province":"WA",
    "sg:tags":[
        "vehicle",
        "manufactured",
        "housing-communities",
        "recreational",
        "park",
        "lodging"
    ],
    "sg:website":"http://www.trailerinnsrv.com",
    "wof:name":"Trailer Inns R.V. Park",
    "wof:placetype":"venue"
},
  "geometry": {"coordinates":[-122.133072,47.577595],"type":"Point"}
}