{
  "type": "Feature",
  "properties": {
    "addr:full":"1012 SW Trenton St Seattle WA 98106",
    "addr:housenumber":"1012",
    "addr:postcode":"98106",
    "addr:street":"Sw Trenton St",
    "iso:country":"US",
    "sg:address":"1012 SW Trenton St",
    "sg:city":"Seattle",
    "sg:classifiers":[
        {
            "category":"Education",
            "subcategory":"School",
            "type":"Public Place"
        }
    ],
    "sg:phone":"+1 206 281 6480",
    "sg:postcode":"98106",
    "sg:province":"WA",
    "wof:name":"Highland Park Elementary Schl",
    "wof:placetype":"venue"
},
  "geometry": {"coordinates":[-122.349181,47.524734],"type":"Point"}
}