{
  "type": "Feature",
  "properties": {
    "addr:full":"2185 Little Kalama River Rd Woodland WA 98674",
    "addr:housenumber":"2185",
    "addr:postcode":"98674",
    "addr:street":"Little Kalama River Rd",
    "iso:country":"US",
    "sg:address":"2185 Little Kalama River Rd",
    "sg:city":"Woodland",
    "sg:classifiers":[
        {
            "category":"Building & Trades",
            "subcategory":"Landscaping Services",
            "type":"Services"
        }
    ],
    "sg:phone":"+1 360 225 1626",
    "sg:postcode":"98674",
    "sg:province":"WA",
    "sg:tags":[
        "landscape"
    ],
    "wof:name":"Cedars Landscaping Vancou",
    "wof:placetype":"venue"
},
  "geometry": {"coordinates":[-122.66896,45.986681],"type":"Point"}
}