{
  "type": "Feature",
  "properties": {
    "addr:full":"4105 26th Ave SW Seattle WA 98106",
    "addr:housenumber":"4105",
    "addr:postcode":"98106",
    "addr:street":"26Th Ave Sw",
    "iso:country":"US",
    "sg:address":"4105 26th Ave SW",
    "sg:city":"Seattle",
    "sg:classifiers":[
        {
            "category":"Professional",
            "subcategory":"Business Services",
            "type":"Services"
        }
    ],
    "sg:phone":"+1 206 325 9311",
    "sg:postcode":"98106",
    "sg:province":"WA",
    "sg:tags":[
        "interior",
        "consultant",
        "design",
        "decorator"
    ],
    "wof:name":"Dana Hamel Interior Design",
    "wof:placetype":"venue"
},
  "geometry": {"coordinates":[-122.36544000000001,47.567619],"type":"Point"}
}