{
  "type": "Feature",
  "properties": {
    "addr:full":"3218 Porter St Enumclaw WA 98022",
    "addr:housenumber":"3218",
    "addr:postcode":"98022",
    "addr:street":"Porter St",
    "iso:country":"US",
    "sg:address":"3218 Porter St",
    "sg:city":"Enumclaw",
    "sg:classifiers":[
        {
            "category":"Building & Trades",
            "subcategory":"Landscaping Services",
            "type":"Services"
        }
    ],
    "sg:phone":"+1 360 825 3433",
    "sg:postcode":"98022",
    "sg:province":"WA",
    "sg:tags":[
        "landscape"
    ],
    "wof:name":"Alpine Landscape & Maintenance",
    "wof:placetype":"venue"
},
  "geometry": {"coordinates":[-121.98970300000001,47.213707],"type":"Point"}
}