{
  "type": "Feature",
  "properties": {
    "addr:full":"8523 Greenwood Ave N Seattle WA 98103",
    "addr:housenumber":"8523",
    "addr:postcode":"98103",
    "addr:street":"Greenwood Ave N",
    "iso:country":"US",
    "sg:address":"8523 Greenwood Ave N",
    "sg:city":"Seattle",
    "sg:classifiers":[
        {
            "category":"Building & Trades",
            "subcategory":"Locksmith",
            "type":"Services"
        }
    ],
    "sg:phone":"+1 206 905 6136",
    "sg:postcode":"98103",
    "sg:province":"WA",
    "sg:tags":[
        "key"
    ],
    "wof:name":"Locksmith",
    "wof:placetype":"venue"
},
  "geometry": {"coordinates":[-122.355504,47.690769],"type":"Point"}
}