{
  "type": "Feature",
  "properties": {
    "addr:full":"4503 N Market St Spokane WA 99207",
    "addr:housenumber":"4503",
    "addr:postcode":"99207",
    "addr:street":"N Market St",
    "iso:country":"US",
    "sg:address":"4503 N Market St",
    "sg:city":"Spokane",
    "sg:classifiers":[
        {
            "category":"Autos & Motor Vehicles",
            "subcategory":"Automobile Sales",
            "type":"Retail Goods"
        }
    ],
    "sg:phone":"+1 509 483 8311",
    "sg:postcode":"99207",
    "sg:province":"WA",
    "sg:tags":[
        "dealers-used",
        "car",
        "used",
        "cars-wholesale",
        "new"
    ],
    "wof:name":"Paradise Motors",
    "wof:placetype":"venue"
},
  "geometry": {"coordinates":[-117.365013,47.698845],"type":"Point"}
}