{
  "type": "Feature",
  "properties": {
    "addr:full":"7620 SE Evergreen Hwy Vancouver WA 98664",
    "addr:housenumber":"7620",
    "addr:postcode":"98664",
    "addr:street":"Se Evergreen Hwy",
    "iso:country":"US",
    "sg:address":"7620 SE Evergreen Hwy",
    "sg:city":"Vancouver",
    "sg:classifiers":[
        {
            "category":"Professional",
            "subcategory":"Management & Consulting",
            "type":"Services"
        }
    ],
    "sg:phone":"+1 360 737 1618",
    "sg:postcode":"98664",
    "sg:province":"WA",
    "sg:tags":[
        "business"
    ],
    "wof:name":"Harris Consult Group",
    "wof:placetype":"venue"
},
  "geometry": {"coordinates":[-122.593829,45.611446],"type":"Point"}
}