{
  "type": "Feature",
  "properties": {
    "addr:full":"3853 NE 93rd St Seattle WA 98115",
    "addr:housenumber":"3853",
    "addr:postcode":"98115",
    "addr:street":"Ne 93Rd St",
    "iso:country":"US",
    "sg:address":"3853 NE 93rd St",
    "sg:city":"Seattle",
    "sg:classifiers":[
        {
            "category":"Education",
            "subcategory":"Special Training",
            "type":"Public Place"
        }
    ],
    "sg:phone":"+1 206 892 0292",
    "sg:postcode":"98115",
    "sg:province":"WA",
    "sg:tags":[
        "aid",
        "instruction",
        "safety",
        "first"
    ],
    "wof:name":"Ian J Zelo",
    "wof:placetype":"venue"
},
  "geometry": {"coordinates":[-122.286508,47.695971],"type":"Point"}
}