{
  "type": "Feature",
  "properties": {
    "addr:full":"515 W Harrison St Kent WA 98032",
    "addr:housenumber":"515",
    "addr:postcode":"98032",
    "addr:street":"W Harrison St",
    "iso:country":"US",
    "sg:address":"515 W Harrison St",
    "sg:city":"Kent",
    "sg:classifiers":[
        {
            "category":"Organizations",
            "subcategory":"Religious Organization",
            "type":"Services"
        }
    ],
    "sg:phone":"+1 253 520 7405",
    "sg:postcode":"98032",
    "sg:province":"WA",
    "wof:name":"Jubilee Covenant Center",
    "wof:placetype":"venue"
},
  "geometry": {"coordinates":[-122.237528,47.382196],"type":"Point"}
}