{
  "type": "Feature",
  "properties": {
    "addr:full":"2712 Summit Ave Everett WA 98201",
    "addr:housenumber":"2712",
    "addr:postcode":"98201",
    "addr:street":"Summit Ave",
    "iso:country":"US",
    "sg:address":"2712 Summit Ave",
    "sg:city":"Everett",
    "sg:classifiers":[
        {
            "category":"Shopping",
            "subcategory":"Bicycles & Sporting Goods",
            "type":"Retail Goods"
        }
    ],
    "sg:phone":"+1 425 258 2683",
    "sg:postcode":"98201",
    "sg:province":"WA",
    "wof:name":"Reloaded Paintball Unlimited",
    "wof:placetype":"venue"
},
  "geometry": {"coordinates":[-122.18400800000001,47.980936],"type":"Point"}
}