{
  "type": "Feature",
  "properties": {
    "addr:full":"17335 SE 270th Pl Kent WA 98042",
    "addr:postcode":"17335;98042",
    "addr:street":"Se 270Th Pl",
    "iso:country":"US",
    "sg:address":"17335 SE 270th Pl",
    "sg:city":"Kent",
    "sg:classifiers":[
        {
            "category":"Restaurant",
            "type":"Food & Drink"
        }
    ],
    "sg:menulink":"http://www.allmenus.com/wa/tahoma-maple-valley/240534-panda-express/menu/",
    "sg:phone":"+1 253 638 1079",
    "sg:postcode":"98042",
    "sg:province":"WA",
    "sg:tags":[
        "asian",
        "chinese"
    ],
    "wof:name":"Panda Express",
    "wof:placetype":"venue"
},
  "geometry": {"coordinates":[-122.11011000000001,47.359386],"type":"Point"}
}