{
  "type": "Feature",
  "properties": {
    "addr:full":"1725 SE Blairmont Dr Vancouver WA 98683",
    "addr:housenumber":"1725",
    "addr:postcode":"98683",
    "addr:street":"Se Blairmont Dr",
    "iso:country":"US",
    "sg:address":"1725 SE Blairmont Dr",
    "sg:city":"Vancouver",
    "sg:classifiers":[
        {
            "category":"Communications",
            "subcategory":"Film & Video Production",
            "type":"Services"
        }
    ],
    "sg:phone":"+1 503 703 6656",
    "sg:postcode":"98683",
    "sg:province":"WA",
    "sg:tags":[
        "motion"
    ],
    "wof:name":"Liquid Cinema Productions",
    "wof:placetype":"venue"
},
  "geometry": {"coordinates":[-122.519639,45.609505],"type":"Point"}
}