{
  "type": "Feature",
  "properties": {
    "addr:full":"5105A Capitol Blvd SW Tumwater WA 98501",
    "addr:housenumber":"5105a",
    "addr:postcode":"98501",
    "addr:street":"Capitol Blvd Sw",
    "iso:country":"US",
    "sg:address":"5105A Capitol Blvd SW",
    "sg:city":"Tumwater",
    "sg:classifiers":[
        {
            "category":"Personal",
            "type":"Services"
        },
        {
            "category":"Sports & Exercise",
            "subcategory":"Gym",
            "type":"Entertainment"
        },
        {
            "category":"Health Services",
            "subcategory":"Health Practitioner",
            "type":"Services"
        },
        {
            "category":"Arena",
            "subcategory":"Sports Club",
            "type":"Entertainment"
        }
    ],
    "sg:phone":"+1 800 615 7352",
    "sg:postcode":"98501",
    "sg:province":"WA",
    "sg:tags":[
        "trainer",
        "control",
        "weight",
        "consultant",
        "program",
        "fitness",
        "physical"
    ],
    "sg:website":"http://national.citysearch.com/profile/external/38050521/tumwater_wa/curves.html?publisher=yellowpages&reference_id=1&placement=ypwebsitemip",
    "wof:name":"Curves",
    "wof:placetype":"venue"
},
  "geometry": {"coordinates":[-122.909583,47.001752],"type":"Point"}
}