{
  "type": "Feature",
  "properties": {
    "addr:full":"1751 Center St Tacoma WA 98409",
    "addr:housenumber":"1751",
    "addr:postcode":"98409",
    "addr:street":"Center St",
    "iso:country":"US",
    "sg:address":"1751 Center St",
    "sg:city":"Tacoma",
    "sg:classifiers":[
        {
            "category":"Manufacturing",
            "subcategory":"Tools & Machinery",
            "type":"Manufacturing & Wholesale Goods"
        }
    ],
    "sg:phone":"+1 253 572 3407",
    "sg:postcode":"98409",
    "sg:province":"WA",
    "sg:tags":[
        "pattern",
        "industrial",
        "mfg"
    ],
    "wof:name":"Bobco Pattern Mfg",
    "wof:placetype":"venue"
},
  "geometry": {"coordinates":[-122.46034299999999,47.233855],"type":"Point"}
}