{
  "type": "Feature",
  "properties": {
    "addr:full":"51 Bayview Dr Point Roberts WA 98281",
    "addr:housenumber":"51",
    "addr:postcode":"98281",
    "addr:street":"Bayview Dr",
    "iso:country":"US",
    "sg:address":"51 Bayview Dr",
    "sg:city":"Point Roberts",
    "sg:classifiers":[
        {
            "category":"Professional",
            "subcategory":"Computer Services",
            "type":"Services"
        }
    ],
    "sg:phone":"+1 360 945 2677",
    "sg:postcode":"98281",
    "sg:province":"WA",
    "sg:tags":[
        "development",
        "software"
    ],
    "wof:name":"Infobuild Networks Inc",
    "wof:placetype":"venue"
},
  "geometry": {"coordinates":[-123.03535599999999,49.001346],"type":"Point"}
}