{
  "type": "Feature",
  "properties": {
    "addr:full":"10416 5th Avenue NE Seattle WA 98125",
    "addr:housenumber":"10416",
    "addr:postcode":"98125",
    "addr:street":"5Th Avenue Ne",
    "iso:country":"US",
    "sg:address":"10416 5th Avenue NE",
    "sg:city":"Seattle",
    "sg:classifiers":[
        {
            "category":"Health Services",
            "subcategory":"Doctor",
            "type":"Services"
        }
    ],
    "sg:phone":"+1 206 517 6700",
    "sg:postcode":"98125",
    "sg:province":"WA",
    "sg:tags":[
        "medicine",
        "practice",
        "internal",
        "family"
    ],
    "sg:website":"www.pacificmedicalcenters.org",
    "wof:name":"Ways Martha MD",
    "wof:placetype":"venue"
},
  "geometry": {"coordinates":[-122.32297800000001,47.704377],"type":"Point"}
}