{
  "type": "Feature",
  "properties": {
    "addr:full":"409 N Thierman Rd Spokane Valley WA 99212",
    "addr:housenumber":"409",
    "addr:postcode":"99212",
    "addr:street":"N Thierman Rd",
    "iso:country":"US",
    "sg:address":"409 N Thierman Rd",
    "sg:city":"Spokane Valley",
    "sg:classifiers":[
        {
            "category":"Wholesale",
            "subcategory":"Construction Materials",
            "type":"Manufacturing & Wholesale Goods"
        }
    ],
    "sg:phone":"+1 509 921 0430",
    "sg:postcode":"99212",
    "sg:province":"WA",
    "sg:tags":[
        "nailing",
        "machinery"
    ],
    "wof:name":"Modern Staple Inc",
    "wof:placetype":"venue"
},
  "geometry": {"coordinates":[-117.314797,47.661663],"type":"Point"}
}