{
  "type": "Feature",
  "properties": {
    "addr:full":"167 Sosua Ct Burbank WA 99323",
    "addr:postcode":"99323",
    "addr:street":"167;Ct",
    "iso:country":"US",
    "sg:address":"167 Sosua Ct",
    "sg:city":"Burbank",
    "sg:classifiers":[
        {
            "category":"Building & Trades",
            "subcategory":"Construction",
            "type":"Services"
        }
    ],
    "sg:phone":"+1 509 545 9689",
    "sg:postcode":"99323",
    "sg:province":"WA",
    "sg:tags":[
        "heavy"
    ],
    "wof:name":"Harvill Irrigation Welding",
    "wof:placetype":"venue"
},
  "geometry": {"coordinates":[-118.892736,46.227613],"type":"Point"}
}