{
  "type": "Feature",
  "properties": {
    "addr:full":"103 Merlot Dr Prosser WA 99350",
    "addr:housenumber":"103",
    "addr:postcode":"99350",
    "addr:street":"Merlot Dr",
    "iso:country":"US",
    "sg:address":"103 Merlot Dr",
    "sg:city":"Prosser",
    "sg:classifiers":[
        {
            "category":"Restaurant",
            "type":"Food & Drink"
        }
    ],
    "sg:menulink":"http://www.allmenus.com/wa/northwest-benton/212752-mcdonalds/menu/",
    "sg:phone":"+1 509 786 7222",
    "sg:postcode":"99350",
    "sg:province":"WA",
    "sg:tags":[
        "burger",
        "american"
    ],
    "wof:name":"McDonald's",
    "wof:placetype":"venue"
},
  "geometry": {"coordinates":[-119.786958,46.219971],"type":"Point"}
}