{
  "type": "Feature",
  "properties": {
    "addr:full":"70 Sunrise Rd Lopez Island WA 98261",
    "addr:housenumber":"70",
    "addr:postcode":"98261",
    "addr:street":"Sunrise Rd Lopez Island",
    "iso:country":"US",
    "sg:address":"70 Sunrise Rd",
    "sg:city":"Lopez Island",
    "sg:classifiers":[
        {
            "category":"Organizations",
            "subcategory":"Religious Organization",
            "type":"Services"
        }
    ],
    "sg:phone":"+1 360 468 3477",
    "sg:postcode":"98261",
    "sg:province":"WA",
    "sg:tags":[
        "church"
    ],
    "wof:name":"Grace Episcopal Church",
    "wof:placetype":"venue"
},
  "geometry": {"coordinates":[-122.87017,48.496999],"type":"Point"}
}