{
  "type": "Feature",
  "properties": {
    "addr:full":"12305 Sandridge Rd Long Beach WA 98631",
    "addr:housenumber":"12305",
    "addr:postcode":"98631",
    "addr:street":"Sandridge Rd",
    "iso:country":"US",
    "sg:address":"12305 Sandridge Rd",
    "sg:city":"Long Beach",
    "sg:classifiers":[
        {
            "category":"Professional",
            "subcategory":"Lawyer & Legal Services",
            "type":"Services"
        }
    ],
    "sg:phone":"+1 360 642 2332",
    "sg:postcode":"98631",
    "sg:province":"WA",
    "wof:name":"Guy M Glenn",
    "wof:placetype":"venue"
},
  "geometry": {"coordinates":[-124.025194,46.390711],"type":"Point"}
}