{
  "type": "Feature",
  "properties": {
    "addr:full":"1473 N Goerig St Woodland WA 98674",
    "addr:housenumber":"1473",
    "addr:postcode":"98674",
    "addr:street":"N Goerig St",
    "iso:country":"US",
    "sg:address":"1473 N Goerig St",
    "sg:city":"Woodland",
    "sg:classifiers":[
        {
            "category":"Real Estate",
            "subcategory":"Real Estate Operator",
            "type":"Services"
        }
    ],
    "sg:phone":"+1 360 225 5293",
    "sg:postcode":"98674",
    "sg:province":"WA",
    "sg:tags":[
        "building",
        "apartment"
    ],
    "wof:name":"Jefferson Place Apartments",
    "wof:placetype":"venue"
},
  "geometry": {"coordinates":[-122.741339,45.913677],"type":"Point"}
}