{
  "type": "Feature",
  "properties": {
    "addr:full":"660 Goerig St Woodland WA 98674",
    "addr:housenumber":"660",
    "addr:postcode":"98674",
    "addr:street":"Goerig St",
    "iso:country":"US",
    "sg:address":"660 Goerig St",
    "sg:city":"Woodland",
    "sg:classifiers":[
        {
            "category":"Real Estate",
            "subcategory":"Real Estate Agent",
            "type":"Services"
        }
    ],
    "sg:phone":"+1 360 225 6939",
    "sg:postcode":"98674",
    "sg:province":"WA",
    "wof:name":"Re/Max",
    "wof:placetype":"venue"
},
  "geometry": {"coordinates":[-122.74526299999999,45.902296],"type":"Point"}
}