{
  "type": "Feature",
  "properties": {
    "addr:full":"20936 108th Ave SE Kent WA 98031",
    "addr:housenumber":"20936",
    "addr:postcode":"98031",
    "addr:street":"108Th Ave Se",
    "iso:country":"US",
    "sg:address":"20936 108th Ave SE",
    "sg:city":"Kent",
    "sg:classifiers":[
        {
            "category":"Food & Beverages",
            "subcategory":"Groceries & Convenience Stores",
            "type":"Retail Goods"
        }
    ],
    "sg:phone":"+1 253 850 8906",
    "sg:postcode":"98031",
    "sg:province":"WA",
    "sg:tags":[
        "eating"
    ],
    "wof:name":"India Bazaar",
    "wof:placetype":"venue"
},
  "geometry": {"coordinates":[-122.19697600000001,47.415651],"type":"Point"}
}