{
  "type": "Feature",
  "properties": {
    "addr:full":"2104 W 34th Ave Kennewick WA 99337",
    "addr:housenumber":"2104",
    "addr:postcode":"99337",
    "addr:street":"W 34Th Ave",
    "iso:country":"US",
    "sg:address":"2104 W 34th Ave",
    "sg:city":"Kennewick",
    "sg:classifiers":[
        {
            "category":"Professional",
            "subcategory":"Accounting & Tax Preparation",
            "type":"Services"
        }
    ],
    "sg:phone":"+1 509 366 9775",
    "sg:postcode":"99337",
    "sg:province":"WA",
    "sg:tags":[
        "auditing",
        "bookkeeping"
    ],
    "wof:name":"Kay Mamiya CPA",
    "wof:placetype":"venue"
},
  "geometry": {"coordinates":[-119.149602,46.178891],"type":"Point"}
}