{
  "type": "Feature",
  "properties": {
    "iso:country":"US",
    "sg:address":"2284 NE 60th St",
    "sg:city":"Seattle",
    "sg:classifiers":[
        {
            "category":"Professional",
            "subcategory":"Computer Services",
            "type":"Services"
        }
    ],
    "sg:phone":"+1 206 525 7502",
    "sg:postcode":"98115",
    "sg:province":"WA",
    "sg:tags":[
        "prepackaged",
        "software"
    ],
    "wof:name":"Lawrence Group The LLC",
    "wof:placetype":"venue"
},
  "geometry": {"coordinates":[-122.301997,47.672143],"type":"Point"}
}