{
  "type": "Feature",
  "properties": {
    "addr:full":"1304 S Canyon Rd Ellensburg WA 98926",
    "addr:housenumber":"1304",
    "addr:postcode":"98926",
    "addr:street":"S Canyon Rd",
    "iso:country":"US",
    "sg:address":"1304 S Canyon Rd",
    "sg:city":"Ellensburg",
    "sg:phone":"+1 509 925 6101",
    "sg:postcode":"98926",
    "sg:province":"WA",
    "sg:website":"http://www.mcdonalds.com",
    "wof:name":"McDonald's",
    "wof:placetype":"venue"
},
  "geometry": {"coordinates":[-120.544854,46.979871],"type":"Point"}
}