{
  "type": "Feature",
  "properties": {
    "addr:full":"9112 NW 27th Ave Vancouver WA 98665",
    "addr:housenumber":"9112",
    "addr:postcode":"98665",
    "addr:street":"Nw 27Th Ave",
    "iso:country":"US",
    "sg:address":"9112 NW 27th Ave",
    "sg:city":"Vancouver",
    "sg:classifiers":[
        {
            "category":"Building & Trades",
            "subcategory":"Construction",
            "type":"Services"
        }
    ],
    "sg:phone":"+1 360 518 5891",
    "sg:postcode":"98665",
    "sg:province":"WA",
    "sg:tags":[
        "steel",
        "erection",
        "structural"
    ],
    "wof:name":"Redi Rock NW",
    "wof:placetype":"venue"
},
  "geometry": {"coordinates":[-122.69846200000001,45.689422],"type":"Point"}
}