{
  "type": "Feature",
  "properties": {
    "addr:full":"201 Division St Grandview WA 98930",
    "addr:housenumber":"201",
    "addr:postcode":"98930",
    "addr:street":"Division St",
    "iso:country":"US",
    "sg:address":"201 Division St",
    "sg:city":"Grandview",
    "sg:classifiers":[
        {
            "category":"Restaurant",
            "type":"Food & Drink"
        }
    ],
    "sg:phone":"+1 509 882 3554",
    "sg:postcode":"98930",
    "sg:province":"WA",
    "sg:tags":[
        "eating"
    ],
    "wof:name":"El Palenque Restaurant",
    "wof:placetype":"venue"
},
  "geometry": {"coordinates":[-119.901946,46.254801],"type":"Point"}
}