{
  "type": "Feature",
  "properties": {
    "addr:full":"2201 34th Avenue W Seattle WA 98199",
    "addr:housenumber":"2201",
    "addr:postcode":"98199",
    "addr:street":"34Th Avenue W",
    "iso:country":"US",
    "sg:address":"2201 34th Avenue W",
    "sg:city":"Seattle",
    "sg:classifiers":[
        {
            "category":"Retail",
            "subcategory":"Veterinary Services",
            "type":"Services"
        }
    ],
    "sg:phone":"+1 206 285 0515",
    "sg:postcode":"98199",
    "sg:province":"WA",
    "sg:tags":[
        "veterinarian"
    ],
    "wof:name":"Gane Kirsty DVM",
    "wof:placetype":"venue"
},
  "geometry": {"coordinates":[-122.401111,47.639301],"type":"Point"}
}