{
  "type": "Feature",
  "properties": {
    "addr:full":"2211 Lummi Shore Rd Bellingham WA 98226",
    "addr:postcode":"2211;98226",
    "addr:street":"Lummi Shore Rd",
    "iso:country":"US",
    "sg:address":"2211 Lummi Shore Rd",
    "sg:city":"Bellingham",
    "sg:classifiers":[
        {
            "category":"Building & Trades",
            "subcategory":"Cleaning & Sanitation",
            "type":"Services"
        }
    ],
    "sg:phone":"+1 360 758 2831",
    "sg:postcode":"98226",
    "sg:province":"WA",
    "sg:tags":[
        "maintenance"
    ],
    "wof:name":"Angels At Work Cleaning Servic",
    "wof:placetype":"venue"
},
  "geometry": {"coordinates":[-122.645736,48.722954],"type":"Point"}
}