{
  "type": "Feature",
  "properties": {
    "addr:full":"8621 N Division St Spokane WA 99208",
    "addr:housenumber":"8621",
    "addr:postcode":"99208",
    "addr:street":"N Division St",
    "iso:country":"US",
    "sg:address":"8621 N Division St",
    "sg:city":"Spokane",
    "sg:classifiers":[
        {
            "category":"Professional",
            "type":"Services"
        }
    ],
    "sg:phone":"+1 509 789 1895",
    "sg:postcode":"99208",
    "sg:province":"WA",
    "wof:name":"Nationwide Debt Recovery Servi",
    "wof:placetype":"venue"
},
  "geometry": {"coordinates":[-117.411479,47.735734],"type":"Point"}
}