{
  "type": "Feature",
  "properties": {
    "addr:full":"13026 4th Ave W Everett WA 98204",
    "addr:housenumber":"13026",
    "addr:postcode":"98204",
    "addr:street":"4Th Ave W",
    "iso:country":"US",
    "sg:address":"13026 4th Ave W",
    "sg:city":"Everett",
    "sg:classifiers":[
        {
            "category":"Wholesale",
            "subcategory":"Durable Goods & Equipment",
            "type":"Manufacturing & Wholesale Goods"
        }
    ],
    "sg:phone":"+1 425 347 5196",
    "sg:postcode":"98204",
    "sg:province":"WA",
    "wof:name":"Lutz Wholesale Co",
    "wof:placetype":"venue"
},
  "geometry": {"coordinates":[-122.238889,47.880681],"type":"Point"}
}