{
  "type": "Feature",
  "properties": {
    "addr:full":"3016 NE Blakeley St Seattle WA 98105",
    "addr:housenumber":"3016",
    "addr:postcode":"98105",
    "addr:street":"Ne Blakeley St",
    "iso:country":"US",
    "sg:address":"3016 NE Blakeley St",
    "sg:city":"Seattle",
    "sg:classifiers":[
        {
            "category":"Manufacturing",
            "subcategory":"Tools & Machinery",
            "type":"Manufacturing & Wholesale Goods"
        }
    ],
    "sg:phone":"+1 206 524 6625",
    "sg:postcode":"98105",
    "sg:province":"WA",
    "sg:tags":[
        "supply",
        "equipment",
        "mfg",
        "flow",
        "meter",
        "radar",
        "fuel"
    ],
    "sg:website":"http://www.floscan.com",
    "wof:name":"Floscan",
    "wof:placetype":"venue"
},
  "geometry": {"coordinates":[-122.295491,47.66454],"type":"Point"}
}