{
  "type": "Feature",
  "properties": {
    "addr:full":"344 Mackenzie Dr Stanwood WA 98282",
    "addr:housenumber":"344",
    "addr:postcode":"98282",
    "addr:street":"Mackenzie Dr",
    "iso:country":"US",
    "sg:address":"344 Mackenzie Dr",
    "sg:city":"Stanwood",
    "sg:classifiers":[
        {
            "category":"Professional",
            "subcategory":"Business Services",
            "type":"Services"
        }
    ],
    "sg:phone":"+1 360 387 3177",
    "sg:postcode":"98282",
    "sg:province":"WA",
    "wof:name":"S&D Enterprises",
    "wof:placetype":"venue"
},
  "geometry": {"coordinates":[-122.46888300000001,48.223816],"type":"Point"}
}