{
  "type": "Feature",
  "properties": {
    "addr:full":"8954 Aurora Ave N Seattle WA 98103",
    "addr:housenumber":"8954",
    "addr:postcode":"98103",
    "addr:street":"Aurora Ave N",
    "iso:country":"US",
    "sg:address":"8954 Aurora Ave N",
    "sg:city":"Seattle",
    "sg:classifiers":[
        {
            "category":"Retail",
            "subcategory":"Repair Shop",
            "type":"Services"
        }
    ],
    "sg:phone":"+1 206 525 5799",
    "sg:postcode":"98103",
    "sg:province":"WA",
    "sg:tags":[
        "caning"
    ],
    "wof:name":"Edholms Chair Caning",
    "wof:placetype":"venue"
},
  "geometry": {"coordinates":[-122.344489,47.693785],"type":"Point"}
}