{
  "type": "Feature",
  "properties": {
    "addr:full":"2663 Saint Helens Ct Clarkston WA 99403",
    "addr:housenumber":"2663",
    "addr:postcode":"99403",
    "addr:street":"Saint Helens Ct",
    "iso:country":"US",
    "sg:address":"2663 Saint Helens Ct",
    "sg:city":"Clarkston",
    "sg:classifiers":[
        {
            "category":"Autos & Motor Vehicles",
            "subcategory":"Boat Sales",
            "type":"Retail Goods"
        },
        {
            "category":"Retail",
            "subcategory":"Repair Shop",
            "type":"Services"
        }
    ],
    "sg:phone":"+1 509 758 8796",
    "sg:postcode":"99403",
    "sg:province":"WA",
    "sg:tags":[
        "equipment",
        "upholsterer",
        "supply"
    ],
    "wof:name":"Entrup Upholstery",
    "wof:placetype":"venue"
},
  "geometry": {"coordinates":[-117.097386,46.382258],"type":"Point"}
}