{
  "type": "Feature",
  "properties": {
    "addr:full":"6542 Old Guide Rd Lynden WA 98264",
    "addr:housenumber":"6542",
    "addr:postcode":"98264",
    "addr:street":"Old Guide Rd",
    "iso:country":"US",
    "sg:address":"6542 Old Guide Rd",
    "sg:city":"Lynden",
    "sg:classifiers":[
        {
            "category":"Building & Trades",
            "subcategory":"Construction",
            "type":"Services"
        }
    ],
    "sg:phone":"+1 360 398 1301",
    "sg:postcode":"98264",
    "sg:province":"WA",
    "sg:tags":[
        "contractor"
    ],
    "wof:name":"David Angus Worrell",
    "wof:placetype":"venue"
},
  "geometry": {"coordinates":[-122.49685700000001,48.879522],"type":"Point"}
}