{
  "type": "Feature",
  "properties": {
    "addr:full":"9232 Wallingford Ave N Seattle WA 98103",
    "addr:housenumber":"9232",
    "addr:postcode":"98103",
    "addr:street":"Wallingford Ave N",
    "iso:country":"US",
    "sg:address":"9232 Wallingford Ave N",
    "sg:city":"Seattle",
    "sg:classifiers":[
        {
            "category":"Community Center",
            "subcategory":"Youth",
            "type":"Public Place"
        }
    ],
    "sg:phone":"+1 206 898 8986",
    "sg:postcode":"98103",
    "sg:province":"WA",
    "wof:name":"Barefoot Girl",
    "wof:placetype":"venue"
},
  "geometry": {"coordinates":[-122.336507,47.69656],"type":"Point"}
}