{
  "type": "Feature",
  "properties": {
    "addr:full":"315 F St SW Quincy WA 98848",
    "addr:housenumber":"315",
    "addr:postcode":"98848",
    "addr:street":"F St Sw",
    "iso:country":"US",
    "sg:address":"315 F St SW",
    "sg:city":"Quincy",
    "sg:classifiers":[
        {
            "category":"Autos & Motor Vehicles",
            "subcategory":"Auto Supplies",
            "type":"Retail Goods"
        }
    ],
    "sg:phone":"+1 509 787 1551",
    "sg:postcode":"98848",
    "sg:province":"WA",
    "sg:tags":[
        "tire"
    ],
    "sg:website":"http://www.lesschwab.com",
    "wof:name":"Les Schwab Tire Centers",
    "wof:placetype":"venue"
},
  "geometry": {"coordinates":[-119.858898,47.233336],"type":"Point"}
}