{
  "type": "Feature",
  "properties": {
    "addr:full":"1722 Nob Hill Ave N Seattle WA 98109",
    "addr:housenumber":"1722",
    "addr:postcode":"98109",
    "addr:street":"Nob Hill Ave N",
    "iso:country":"US",
    "sg:address":"1722 Nob Hill Ave N",
    "sg:city":"Seattle",
    "sg:classifiers":[
        {
            "category":"Professional",
            "type":"Services"
        }
    ],
    "sg:phone":"+1 206 283 0866",
    "sg:postcode":"98109",
    "sg:province":"WA",
    "wof:name":"Nancy E Reichley",
    "wof:placetype":"venue"
},
  "geometry": {"coordinates":[-122.350689,47.634666],"type":"Point"}
}