{
  "type": "Feature",
  "properties": {
    "addr:full":"7503 196th St SW Lynnwood WA 98036",
    "addr:housenumber":"7503",
    "addr:postcode":"98036",
    "addr:street":"196Th St Sw",
    "iso:country":"US",
    "sg:address":"7503 196th St SW",
    "sg:city":"Lynnwood",
    "sg:classifiers":[
        {
            "category":"Health Services",
            "subcategory":"Chiropractor",
            "type":"Services"
        }
    ],
    "sg:phone":"+1 425 775 8000",
    "sg:postcode":"98036",
    "sg:province":"WA",
    "sg:tags":[
        "chiropractic"
    ],
    "wof:name":"Felber Susan DC",
    "wof:placetype":"venue"
},
  "geometry": {"coordinates":[-122.334937,47.821434],"type":"Point"}
}