{
  "type": "Feature",
  "properties": {
    "addr:full":"12421 103rd Avenue NE Kirkland WA 98034",
    "addr:housenumber":"12421",
    "addr:postcode":"98034",
    "addr:street":"103Rd Avenue Ne",
    "iso:country":"US",
    "sg:address":"12421 103rd Avenue NE",
    "sg:city":"Kirkland",
    "sg:classifiers":[
        {
            "category":"Park",
            "type":"Public Place"
        }
    ],
    "sg:postcode":"98034",
    "sg:province":"WA",
    "wof:name":"North Kirkland Community Center & Park",
    "wof:placetype":"venue"
},
  "geometry": {"coordinates":[-122.20371799999999,47.712667],"type":"Point"}
}