{
  "type": "Feature",
  "properties": {
    "addr:full":"14310 SE 12th St Bellevue WA 98007",
    "addr:housenumber":"14310",
    "addr:postcode":"98007",
    "addr:street":"Se 12Th St",
    "iso:country":"US",
    "sg:address":"14310 SE 12th St",
    "sg:city":"Bellevue",
    "sg:classifiers":[
        {
            "category":"Place Of Worship",
            "subcategory":"Church",
            "type":"Public Place"
        }
    ],
    "sg:phone":"+1 425 450 9899",
    "sg:postcode":"98007",
    "sg:province":"WA",
    "sg:website":"www.cornerstoneseattle.com",
    "wof:name":"Cornerstone Christian Fellowship",
    "wof:placetype":"venue"
},
  "geometry": {"coordinates":[-122.149176,47.599989],"type":"Point"}
}