{
  "type": "Feature",
  "properties": {
    "iso:country":"US",
    "sg:address":"619 McKinnon Ave",
    "sg:city":"Sumner",
    "sg:classifiers":[
        {
            "category":"Wholesale",
            "subcategory":"Medical Equipment & Supplies",
            "type":"Manufacturing & Wholesale Goods"
        }
    ],
    "sg:phone":"+1 253 862 8112",
    "sg:postcode":"98390",
    "sg:province":"WA",
    "sg:tags":[
        "physician",
        "surgeon"
    ],
    "sg:website":"www.whitmiremedical.com",
    "wof:name":"Whitmire Medical",
    "wof:placetype":"venue"
},
  "geometry": {"coordinates":[-122.245857,47.199822],"type":"Point"}
}