{
  "type": "Feature",
  "properties": {
    "addr:full":"11717 NE 78th Way Vancouver WA 98682",
    "addr:housenumber":"11717",
    "addr:postcode":"98682",
    "addr:street":"Ne 78Th Way",
    "iso:country":"US",
    "sg:address":"11717 NE 78th Way",
    "sg:city":"Vancouver",
    "sg:classifiers":[
        {
            "category":"Utilities",
            "subcategory":"Mobile Phone",
            "type":"Services"
        }
    ],
    "sg:phone":"+1 360 885 9457",
    "sg:postcode":"98682",
    "sg:province":"WA",
    "sg:tags":[
        "telephone",
        "cellular"
    ],
    "wof:name":"Radio Shack",
    "wof:placetype":"venue"
},
  "geometry": {"coordinates":[-122.551029,45.678992],"type":"Point"}
}