{
  "type": "Feature",
  "properties": {
    "iso:country":"US",
    "sg:address":"14729 SE 279th Pl",
    "sg:city":"Kent",
    "sg:classifiers":[
        {
            "category":"Professional",
            "subcategory":"Management & Consulting",
            "type":"Services"
        }
    ],
    "sg:phone":"+1 253 740 6937",
    "sg:postcode":"98042",
    "sg:province":"WA",
    "sg:tags":[
        "business"
    ],
    "wof:name":"McClures Professional Consult",
    "wof:placetype":"venue"
},
  "geometry": {"coordinates":[-122.144113,47.351077],"type":"Point"}
}