{
  "type": "Feature",
  "properties": {
    "addr:full":"14200 NE Salmon Creek Ave Vancouver WA 98686",
    "addr:housenumber":"14200",
    "addr:postcode":"98686",
    "addr:street":"Ne Salmon Creek Ave",
    "iso:country":"US",
    "sg:address":"14200 NE Salmon Creek Ave",
    "sg:city":"Vancouver",
    "sg:classifiers":[
        {
            "category":"Shopping",
            "subcategory":"Stationery & Office Supplies",
            "type":"Retail Goods"
        },
        {
            "category":"Manufacturing",
            "subcategory":"Paper Products",
            "type":"Manufacturing & Wholesale Goods"
        }
    ],
    "sg:phone":"+1 360 573 0447",
    "sg:postcode":"98686",
    "sg:province":"WA",
    "sg:tags":[
        "stationery-wholesale",
        "store",
        "manufacturer"
    ],
    "wof:name":"Bookie The At W S U",
    "wof:placetype":"venue"
},
  "geometry": {"coordinates":[-122.63331100000001,45.724664],"type":"Point"}
}