{
  "type": "Feature",
  "properties": {
    "addr:full":"12625 NE 80th St Kirkland WA 98033",
    "addr:housenumber":"12625",
    "addr:postcode":"98033",
    "addr:street":"Ne 80Th St",
    "iso:country":"US",
    "sg:address":"12625 NE 80th St",
    "sg:city":"Kirkland",
    "sg:classifiers":[
        {
            "category":"Building & Trades",
            "subcategory":"Locksmith",
            "type":"Services"
        }
    ],
    "sg:phone":"+1 425 605 4822",
    "sg:postcode":"98033",
    "sg:province":"WA",
    "sg:tags":[
        "key"
    ],
    "wof:name":"24 Hour A Kirkland Emergency Locksmith",
    "wof:placetype":"venue"
},
  "geometry": {"coordinates":[-122.17151800000001,47.67516],"type":"Point"}
}