{
  "type": "Feature",
  "properties": {
    "addr:full":"609 Salmon Creek Rd Okanogan WA 98840",
    "addr:housenumber":"609",
    "addr:postcode":"98840",
    "addr:street":"Salmon Creek Rd",
    "iso:country":"US",
    "sg:address":"609 Salmon Creek Rd",
    "sg:city":"Okanogan",
    "sg:classifiers":[
        {
            "category":"Professional",
            "type":"Services"
        }
    ],
    "sg:phone":"+1 509 422 4551",
    "sg:postcode":"98840",
    "sg:province":"WA",
    "wof:name":"Ponderosa Outdoors",
    "wof:placetype":"venue"
},
  "geometry": {"coordinates":[-119.639002,48.425078],"type":"Point"}
}