{
  "type": "Feature",
  "properties": {
    "addr:full":"213 E Champion St Bellingham WA 98225",
    "addr:housenumber":"213",
    "addr:postcode":"98225",
    "addr:street":"E Champion St",
    "iso:country":"US",
    "sg:address":"213 E Champion St",
    "sg:city":"Bellingham",
    "sg:classifiers":[
        {
            "category":"Health Services",
            "subcategory":"Clinic",
            "type":"Services"
        }
    ],
    "sg:phone":"+1 360 752 2577",
    "sg:postcode":"98225",
    "sg:province":"WA",
    "sg:tags":[
        "specialty",
        "outpatient"
    ],
    "wof:name":"Rainbow Center",
    "wof:placetype":"venue"
},
  "geometry": {"coordinates":[-122.474298,48.75077],"type":"Point"}
}