{
  "type": "Feature",
  "properties": {
    "iso:country":"US",
    "sg:address":"18214 NE 92nd Ct",
    "sg:city":"Redmond",
    "sg:classifiers":[
        {
            "category":"Building & Trades",
            "subcategory":"Construction",
            "type":"Services"
        }
    ],
    "sg:phone":"+1 425 830 3512",
    "sg:postcode":"98052",
    "sg:province":"WA",
    "sg:tags":[
        "contractor"
    ],
    "wof:name":"Aqua Structures",
    "wof:placetype":"venue"
},
  "geometry": {"coordinates":[-122.09598099999999,47.68349],"type":"Point"}
}