{
  "type": "Feature",
  "properties": {
    "addr:full":"1307 Central Ave S Kent WA 98032",
    "addr:housenumber":"1307",
    "addr:postcode":"98032",
    "addr:street":"Central Ave S",
    "iso:country":"US",
    "sg:address":"1307 Central Ave S",
    "sg:city":"Kent",
    "sg:classifiers":[
        {
            "category":"Professional",
            "subcategory":"Business Services",
            "type":"Services"
        }
    ],
    "sg:phone":"+1 253 859 2280",
    "sg:postcode":"98032",
    "sg:province":"WA",
    "wof:name":"Illustrations In Ice",
    "wof:placetype":"venue"
},
  "geometry": {"coordinates":[-122.23037600000001,47.373085],"type":"Point"}
}