{
  "type": "Feature",
  "properties": {
    "addr:full":"4611 W Clearwater Ave Kennewick WA 99336",
    "addr:housenumber":"4611",
    "addr:postcode":"99336",
    "addr:street":"W Clearwater Ave",
    "iso:country":"US",
    "sg:address":"4611 W Clearwater Ave",
    "sg:city":"Kennewick",
    "sg:classifiers":[
        {
            "category":"Building & Trades",
            "subcategory":"Cleaning & Sanitation",
            "type":"Services"
        },
        {
            "category":"Health Services",
            "subcategory":"Clinic",
            "type":"Services"
        }
    ],
    "sg:phone":"+1 509 783 4109",
    "sg:postcode":"99336",
    "sg:province":"WA",
    "sg:tags":[
        "home",
        "janitor",
        "care"
    ],
    "wof:name":"Classic Home Care Inc",
    "wof:placetype":"venue"
},
  "geometry": {"coordinates":[-119.184648,46.212322],"type":"Point"}
}