{
  "type": "Feature",
  "properties": {
    "addr:full":"16320 NE 202nd Ave Brush Prairie WA 98606",
    "addr:housenumber":"16320",
    "addr:postcode":"98606",
    "addr:street":"Ne 202Nd Ave",
    "iso:country":"US",
    "sg:address":"16320 NE 202nd Ave",
    "sg:city":"Brush Prairie",
    "sg:classifiers":[
        {
            "category":"Shopping",
            "subcategory":"Used Merchandise",
            "type":"Retail Goods"
        }
    ],
    "sg:phone":"+1 360 256 8822",
    "sg:postcode":"98606",
    "sg:province":"WA",
    "sg:tags":[
        "home",
        "furnishing"
    ],
    "wof:name":"Kurea Furnishings Inc",
    "wof:placetype":"venue"
},
  "geometry": {"coordinates":[-122.46605599999999,45.740547],"type":"Point"}
}