{
  "type": "Feature",
  "properties": {
    "addr:full":"4110 Main St Union Gap WA 98903",
    "addr:housenumber":"4110",
    "addr:postcode":"98903",
    "addr:street":"Main St",
    "iso:country":"US",
    "sg:address":"4110 Main St",
    "sg:city":"Union Gap",
    "sg:classifiers":[
        {
            "category":"Shopping",
            "subcategory":"Hobbies, Toys, & Games",
            "type":"Retail Goods"
        }
    ],
    "sg:phone":"+1 509 453 8959",
    "sg:postcode":"98903",
    "sg:province":"WA",
    "sg:tags":[
        "model",
        "swimming",
        "pool",
        "supply"
    ],
    "sg:website":"www.thecloverleaf.com",
    "wof:name":"Clover Leaf",
    "wof:placetype":"venue"
},
  "geometry": {"coordinates":[-120.47595800000001,46.545771],"type":"Point"}
}