{
  "type": "Feature",
  "properties": {
    "addr:full":"3811 Grandview St Gig Harbor WA 98335",
    "addr:housenumber":"3811",
    "addr:postcode":"98335",
    "addr:street":"Grandview St",
    "iso:country":"US",
    "sg:address":"3811 Grandview St",
    "sg:city":"Gig Harbor",
    "sg:classifiers":[
        {
            "category":"Social Services",
            "subcategory":"Child Care",
            "type":"Services"
        }
    ],
    "sg:phone":"+1 253 851 1777",
    "sg:postcode":"98335",
    "sg:province":"WA",
    "sg:tags":[
        "day"
    ],
    "wof:name":"Kindercare Child Care Network",
    "wof:placetype":"venue"
},
  "geometry": {"coordinates":[-122.591421,47.323268],"type":"Point"}
}