{
  "type": "Feature",
  "properties": {
    "addr:full":"2710 Meridian St Bellingham WA 98225",
    "addr:housenumber":"2710",
    "addr:postcode":"98225",
    "addr:street":"Meridian St",
    "iso:country":"US",
    "sg:address":"2710 Meridian St",
    "sg:city":"Bellingham",
    "sg:classifiers":[
        {
            "category":"Health Services",
            "subcategory":"Medical Lab",
            "type":"Services"
        }
    ],
    "sg:phone":"+1 360 676 9065",
    "sg:postcode":"98225",
    "sg:province":"WA",
    "sg:tags":[
        "laboratory",
        "dental"
    ],
    "wof:name":"Northwest Denture Centers Inc",
    "wof:placetype":"venue"
},
  "geometry": {"coordinates":[-122.486009,48.766795],"type":"Point"}
}