{
  "type": "Feature",
  "properties": {
    "addr:full":"14102 NE 21st Street Bellevue WA 98007",
    "addr:housenumber":"14102",
    "addr:postcode":"98007",
    "addr:street":"Ne 21St Street",
    "iso:country":"US",
    "sg:address":"14102 NE 21st Street",
    "sg:city":"Bellevue",
    "sg:classifiers":[
        {
            "category":"Wholesale",
            "subcategory":"Home Furnishings",
            "type":"Manufacturing & Wholesale Goods"
        }
    ],
    "sg:phone":"+1 425 644 7181",
    "sg:postcode":"98007",
    "sg:province":"WA",
    "sg:tags":[
        "blind",
        "shade"
    ],
    "sg:website":"www.blindalley.com",
    "wof:name":"Blind Alley",
    "wof:placetype":"venue"
},
  "geometry": {"coordinates":[-122.152384,47.628692],"type":"Point"}
}