{
  "type": "Feature",
  "properties": {
    "addr:full":"222 Columbia St NW Olympia WA 98501",
    "addr:housenumber":"222",
    "addr:postcode":"olympia wa 98501",
    "addr:street":"Columbia St Nw",
    "iso:country":"US",
    "sg:address":"222 Columbia St NW",
    "sg:city":"Olympia",
    "sg:classifiers":[
        {
            "category":"Organizations",
            "subcategory":"Professional Association",
            "type":"Services"
        }
    ],
    "sg:phone":"+1 360 586 7787",
    "sg:postcode":"98501",
    "sg:province":"WA",
    "sg:tags":[
        "center",
        "volunteer"
    ],
    "wof:name":"Volunteer Ctr Lws Msn & Thrstn",
    "wof:placetype":"venue"
},
  "geometry": {"coordinates":[-122.903058,47.04632],"type":"Point"}
}