{
  "type": "Feature",
  "properties": {
    "addr:full":"1001 Hildebrand Ln NE Bainbridge Island WA 98110",
    "addr:housenumber":"1001",
    "addr:postcode":"98110",
    "addr:street":"Hildebrand Ln Ne",
    "iso:country":"US",
    "sg:address":"1001 Hildebrand Ln NE",
    "sg:city":"Bainbridge Island",
    "sg:classifiers":[
        {
            "category":"Insurance",
            "subcategory":"Insurance Agent",
            "type":"Services"
        }
    ],
    "sg:phone":"+1 206 855 0855",
    "sg:postcode":"98110",
    "sg:province":"WA",
    "wof:name":"Jason Turinsky",
    "wof:placetype":"venue"
},
  "geometry": {"coordinates":[-122.517083,47.633009],"type":"Point"}
}