{
  "type": "Feature",
  "properties": {
    "addr:full":"7809 NE Vancouver Plaza Dr Ste 160 Vancouver WA 98662",
    "addr:housenumber":"7809",
    "addr:postcode":"98662",
    "addr:street":"Ne Vancouver Plaza Dr Ste 160",
    "iso:country":"US",
    "sg:address":"7809 NE Vancouver Plaza Dr Ste 160",
    "sg:city":"Vancouver",
    "sg:classifiers":[
        {
            "category":"Insurance",
            "subcategory":"Health Insurance",
            "type":"Services"
        }
    ],
    "sg:phone":"+1 360 260 2671",
    "sg:postcode":"98662",
    "sg:province":"WA",
    "sg:tags":[
        "market"
    ],
    "sg:website":"www.gnc.com",
    "wof:name":"General Nutrition Cntr",
    "wof:placetype":"venue"
},
  "geometry": {"coordinates":[-122.593002,45.6511],"type":"Point"}
}