{
  "type": "Feature",
  "properties": {
    "addr:full":"6810 S 180th St Seattle WA 98188",
    "addr:housenumber":"6810",
    "addr:postcode":"98188",
    "addr:street":"S 180Th St",
    "iso:country":"US",
    "sg:address":"6810 S 180th St",
    "sg:city":"Seattle",
    "sg:classifiers":[
        {
            "category":"Freight",
            "type":"Transportation"
        }
    ],
    "sg:phone":"+1 206 394 0327",
    "sg:postcode":"98188",
    "sg:province":"WA",
    "sg:tags":[
        "operator",
        "trucking"
    ],
    "wof:name":"Cardinal Freight Carriers Inc",
    "wof:placetype":"venue"
},
  "geometry": {"coordinates":[-122.246583,47.441314],"type":"Point"}
}