{
  "type": "Feature",
  "properties": {
    "addr:full":"721 S 219th St Des Moines WA 98198",
    "addr:housenumber":"721",
    "addr:postcode":"98198",
    "addr:street":"S 219Th St",
    "iso:country":"US",
    "sg:address":"721 S 219th St",
    "sg:city":"Des Moines",
    "sg:classifiers":[
        {
            "category":"Shopping",
            "subcategory":"Florist",
            "type":"Retail Goods"
        }
    ],
    "sg:phone":"+1 206 824 5920",
    "sg:postcode":"98198",
    "sg:province":"WA",
    "wof:name":"Des Moines Florist Inc",
    "wof:placetype":"venue"
},
  "geometry": {"coordinates":[-122.32496500000001,47.405717],"type":"Point"}
}