{
  "type": "Feature",
  "properties": {
    "addr:full":"603 S Sprague Ave Tacoma WA 98405",
    "addr:housenumber":"603",
    "addr:postcode":"98405",
    "addr:street":"S Sprague Ave",
    "iso:country":"US",
    "sg:address":"603 S Sprague Ave",
    "sg:city":"Tacoma",
    "sg:classifiers":[
        {
            "category":"Retail",
            "subcategory":"Auto Repair",
            "type":"Services"
        }
    ],
    "sg:phone":"+1 253 627 8267",
    "sg:postcode":"98405",
    "sg:province":"WA",
    "sg:tags":[
        "repairing",
        "automobile"
    ],
    "wof:name":"Bucky's",
    "wof:placetype":"venue"
},
  "geometry": {"coordinates":[-122.46290500000001,47.255055],"type":"Point"}
}