{
  "type": "Feature",
  "properties": {
    "addr:full":"140 Lakeside Ave Seattle WA 98122",
    "addr:housenumber":"140",
    "addr:postcode":"98122",
    "addr:street":"Lakeside Ave",
    "iso:country":"US",
    "sg:address":"140 Lakeside Ave",
    "sg:city":"Seattle",
    "sg:classifiers":[
        {
            "category":"Personal",
            "type":"Services"
        }
    ],
    "sg:phone":"+1 206 325 7010",
    "sg:postcode":"98122",
    "sg:province":"WA",
    "sg:tags":[
        "assistant"
    ],
    "wof:name":"Reef Resources",
    "wof:placetype":"venue"
},
  "geometry": {"coordinates":[-122.285228,47.601936],"type":"Point"}
}