{
  "type": "Feature",
  "properties": {
    "addr:full":"1921 SW 322nd Pl Federal Way WA 98023",
    "addr:housenumber":"1921",
    "addr:postcode":"98023",
    "addr:street":"Sw 322Nd Pl",
    "iso:country":"US",
    "sg:address":"1921 SW 322nd Pl",
    "sg:city":"Federal Way",
    "sg:classifiers":[
        {
            "category":"Shopping",
            "subcategory":"Catalog Store",
            "type":"Retail Goods"
        }
    ],
    "sg:phone":"+1 253 838 4475",
    "sg:postcode":"98023",
    "sg:province":"WA",
    "sg:tags":[
        "house",
        "mail"
    ],
    "wof:name":"Early Bird Entertainment",
    "wof:placetype":"venue"
},
  "geometry": {"coordinates":[-122.35920900000001,47.313319],"type":"Point"}
}