{
  "type": "Feature",
  "properties": {
    "iso:country":"US",
    "sg:address":"1520 4th Ave",
    "sg:city":"Seattle",
    "sg:classifiers":[
        {
            "category":"Professional",
            "type":"Services"
        }
    ],
    "sg:phone":"+1 206 903 8147",
    "sg:postcode":"98101",
    "sg:province":"WA",
    "sg:tags":[
        "establishment"
    ],
    "wof:name":"Guardent",
    "wof:placetype":"venue"
},
  "geometry": {"coordinates":[-122.33673899999999,47.610356],"type":"Point"}
}