{
  "type": "Feature",
  "properties": {
    "addr:full":"2802 E Madison St Seattle WA 98112",
    "addr:housenumber":"2802",
    "addr:postcode":"98112",
    "addr:street":"E Madison St",
    "iso:country":"US",
    "sg:address":"2802 E Madison St",
    "sg:city":"Seattle",
    "sg:classifiers":[
        {
            "category":"Home & Garden",
            "subcategory":"Home Furnishings",
            "type":"Retail Goods"
        }
    ],
    "sg:phone":"+1 206 322 9890",
    "sg:postcode":"98112",
    "sg:province":"WA",
    "sg:tags":[
        "decor"
    ],
    "wof:name":"Red Ticking",
    "wof:placetype":"venue"
},
  "geometry": {"coordinates":[-122.295998,47.6236],"type":"Point"}
}