{
  "type": "Feature",
  "properties": {
    "addr:full":"8790 Van Belle Rd Sunnyside WA 98944",
    "addr:housenumber":"8790",
    "addr:postcode":"98944",
    "addr:street":"Van Belle Rd",
    "iso:country":"US",
    "sg:address":"8790 Van Belle Rd",
    "sg:city":"Sunnyside",
    "sg:classifiers":[
        {
            "category":"Organizations",
            "subcategory":"Membership Organization",
            "type":"Services"
        }
    ],
    "sg:phone":"+1 509 837 6767",
    "sg:postcode":"98944",
    "sg:province":"WA",
    "wof:name":"Sunnyside Garden Club",
    "wof:placetype":"venue"
},
  "geometry": {"coordinates":[-119.994969,46.345547],"type":"Point"}
}