{
  "type": "Feature",
  "properties": {
    "addr:full":"8540 NE 110th Pl Kirkland WA 98034",
    "addr:housenumber":"8540",
    "addr:postcode":"98034",
    "addr:street":"Ne 110Th Pl",
    "iso:country":"US",
    "sg:address":"8540 NE 110th Pl",
    "sg:city":"Kirkland",
    "sg:classifiers":[
        {
            "category":"Retail",
            "subcategory":"Veterinary Services",
            "type":"Services"
        }
    ],
    "sg:phone":"+1 425 823 1193",
    "sg:postcode":"98034",
    "sg:province":"WA",
    "sg:tags":[
        "veterinarian"
    ],
    "wof:name":"Clark L A DVM",
    "wof:placetype":"venue"
},
  "geometry": {"coordinates":[-122.227997,47.702499],"type":"Point"}
}