{
  "type": "Feature",
  "properties": {
    "addr:full":"16701 Pacific Ave S Spanaway WA 98387",
    "addr:housenumber":"16701",
    "addr:postcode":"98387",
    "addr:street":"Pacific Ave S Spanaway",
    "iso:country":"US",
    "sg:address":"16701 Pacific Ave S",
    "sg:city":"Spanaway",
    "sg:classifiers":[
        {
            "category":"Bars & Pubs",
            "type":"Food & Drink"
        }
    ],
    "sg:phone":"+1 253 535 0218",
    "sg:postcode":"98387",
    "sg:province":"WA",
    "sg:tags":[
        "tavern"
    ],
    "wof:name":"T J's Tavern",
    "wof:placetype":"venue"
},
  "geometry": {"coordinates":[-122.43483000000001,47.10556],"type":"Point"}
}