{
  "type": "Feature",
  "properties": {
    "addr:full":"112 S Lincoln St Port Angeles WA 98362",
    "addr:housenumber":"112",
    "addr:postcode":"98362",
    "addr:street":"S Lincoln St",
    "iso:country":"US",
    "sg:address":"112 S Lincoln St",
    "sg:city":"Port Angeles",
    "sg:classifiers":[
        {
            "category":"Shopping",
            "subcategory":"Books",
            "type":"Retail Goods"
        }
    ],
    "sg:phone":"+1 360 565 1280",
    "sg:postcode":"98362",
    "sg:province":"WA",
    "sg:tags":[
        "tape",
        "video",
        "rental"
    ],
    "wof:name":"Anime House",
    "wof:placetype":"venue"
},
  "geometry": {"coordinates":[-123.43178,48.118196],"type":"Point"}
}