{
  "type": "Feature",
  "properties": {
    "addr:full":"24526 59th Ave SW Vashon WA 98070",
    "addr:housenumber":"24526",
    "addr:postcode":"98070",
    "addr:street":"59Th Ave Sw",
    "iso:country":"US",
    "sg:address":"24526 59th Ave SW",
    "sg:city":"Vashon",
    "sg:classifiers":[
        {
            "category":"Real Estate",
            "subcategory":"Real Estate Agent",
            "type":"Services"
        }
    ],
    "sg:phone":"+1 206 463 5101",
    "sg:postcode":"98070",
    "sg:province":"WA",
    "wof:name":"Parker Plaza",
    "wof:placetype":"venue"
},
  "geometry": {"coordinates":[-122.407574,47.382961],"type":"Point"}
}