{
  "type": "Feature",
  "properties": {
    "addr:full":"2980 Squalicum Pkwy Bellingham WA 98225",
    "addr:housenumber":"2980",
    "addr:postcode":"98225",
    "addr:street":"Squalicum Pkwy",
    "iso:country":"US",
    "sg:address":"2980 Squalicum Pkwy",
    "sg:city":"Bellingham",
    "sg:classifiers":[
        {
            "category":"Health Services",
            "subcategory":"Doctor",
            "type":"Services"
        },
        {
            "category":"Health Services",
            "subcategory":"Dentist",
            "type":"Services"
        }
    ],
    "sg:phone":"+1 360 647 4262",
    "sg:postcode":"98225",
    "sg:province":"WA",
    "sg:tags":[
        "dentists-oral",
        "physician",
        "maxillofacial",
        "surgeons",
        "surgery",
        "oral"
    ],
    "wof:name":"Subedar Ashoka DMD",
    "wof:placetype":"venue"
},
  "geometry": {"coordinates":[-122.472898,48.772124],"type":"Point"}
}