{
  "type": "Feature",
  "properties": {
    "addr:full":"3020 36th Ave W Seattle WA 98199",
    "addr:housenumber":"3020",
    "addr:postcode":"98199",
    "addr:street":"36Th Ave W",
    "iso:country":"US",
    "sg:address":"3020 36th Ave W",
    "sg:city":"Seattle",
    "sg:classifiers":[
        {
            "category":"Arts & Performance",
            "subcategory":"Theater",
            "type":"Entertainment"
        }
    ],
    "sg:phone":"+1 206 999 9115",
    "sg:postcode":"98199",
    "sg:province":"WA",
    "sg:tags":[
        "entertainer"
    ],
    "sg:website":"www.yourpartygirls.com",
    "wof:name":"ABBY&Yourpartygirls.Com",
    "wof:placetype":"venue"
},
  "geometry": {"coordinates":[-122.40353899999999,47.648447],"type":"Point"}
}