{
  "type": "Feature",
  "properties": {
    "addr:full":"1406 S Lilac Ln Liberty Lake WA 99019",
    "addr:housenumber":"1406",
    "addr:postcode":"99019",
    "addr:street":"S Lilac Ln",
    "iso:country":"US",
    "sg:address":"1406 S Lilac Ln",
    "sg:city":"Liberty Lake",
    "sg:classifiers":[
        {
            "category":"Professional",
            "subcategory":"Art Services",
            "type":"Services"
        }
    ],
    "sg:phone":"+1 509 255 5335",
    "sg:postcode":"99019",
    "sg:province":"WA",
    "sg:tags":[
        "commercial",
        "design"
    ],
    "wof:name":"Robin Lynn Curtis",
    "wof:placetype":"venue"
},
  "geometry": {"coordinates":[-117.09059499999999,47.643915],"type":"Point"}
}