{
  "type": "Feature",
  "properties": {
    "addr:full":"1310 Firland Dr Puyallup WA 98371",
    "addr:housenumber":"1310",
    "addr:postcode":"98371",
    "addr:street":"Firland Dr",
    "iso:country":"US",
    "sg:address":"1310 Firland Dr",
    "sg:city":"Puyallup",
    "sg:classifiers":[
        {
            "category":"Wholesale",
            "subcategory":"Vending Machines",
            "type":"Manufacturing & Wholesale Goods"
        }
    ],
    "sg:phone":"+1 253 841 0861",
    "sg:postcode":"98371",
    "sg:province":"WA",
    "sg:tags":[
        "operator"
    ],
    "wof:name":"PB&j Vending",
    "wof:placetype":"venue"
},
  "geometry": {"coordinates":[-122.324341,47.181253],"type":"Point"}
}