{
  "type": "Feature",
  "properties": {
    "addr:full":"120 Ave D Snohomish WA 98290",
    "addr:housenumber":"120",
    "addr:postcode":"98290",
    "addr:street":"Ave D",
    "iso:country":"US",
    "sg:address":"120 Ave D",
    "sg:city":"Snohomish",
    "sg:classifiers":[
        {
            "category":"Shopping",
            "type":"Retail Goods"
        }
    ],
    "sg:phone":"+1 360 568 7738",
    "sg:postcode":"98290",
    "sg:province":"WA",
    "sg:tags":[
        "merchandise",
        "business"
    ],
    "wof:name":"Awards and Engraving Northwest",
    "wof:placetype":"venue"
},
  "geometry": {"coordinates":[-122.098629,47.912688],"type":"Point"}
}