{
  "type": "Feature",
  "properties": {
    "iso:country":"US",
    "sg:address":"531 N Dune Rd",
    "sg:city":"Moses Lake",
    "sg:classifiers":[
        {
            "category":"Retail",
            "subcategory":"Repair Shop",
            "type":"Services"
        }
    ],
    "sg:phone":"+1 509 764 6686",
    "sg:postcode":"98837",
    "sg:province":"WA",
    "sg:tags":[
        "taxidermist"
    ],
    "wof:name":"Dresser's Artistic Design",
    "wof:placetype":"venue"
},
  "geometry": {"coordinates":[-119.28944,47.137202],"type":"Point"}
}