{
  "type": "Feature",
  "properties": {
    "addr:full":"2013 NW 62nd St Seattle WA 98107",
    "addr:housenumber":"2013",
    "addr:postcode":"98107",
    "addr:street":"Nw 62Nd St",
    "iso:country":"US",
    "sg:address":"2013 NW 62nd St",
    "sg:city":"Seattle",
    "sg:classifiers":[
        {
            "category":"Retail",
            "subcategory":"Laundry & Dry Cleaning",
            "type":"Services"
        },
        {
            "category":"Building & Trades",
            "subcategory":"Construction",
            "type":"Services"
        },
        {
            "category":"Building & Trades",
            "subcategory":"Cleaning & Sanitation",
            "type":"Services"
        }
    ],
    "sg:phone":"+1 206 782 2494",
    "sg:postcode":"98107",
    "sg:province":"WA",
    "sg:tags":[
        "repair",
        "cleaner",
        "house",
        "contractor",
        "window",
        "maintenance",
        "home",
        "painting"
    ],
    "wof:name":"Capitol Cleaning Services Inc",
    "wof:placetype":"venue"
},
  "geometry": {"coordinates":[-122.382463,47.673847],"type":"Point"}
}