{
  "type": "Feature",
  "properties": {
    "iso:country":"US",
    "sg:address":"2528 276th St NW",
    "sg:city":"Stanwood",
    "sg:classifiers":[
        {
            "category":"Freight",
            "type":"Transportation"
        }
    ],
    "sg:phone":"+1 360 629 2766",
    "sg:postcode":"98292",
    "sg:province":"WA",
    "sg:tags":[
        "operator",
        "local",
        "trucking"
    ],
    "wof:name":"Jeffrey I Utgard",
    "wof:placetype":"venue"
},
  "geometry": {"coordinates":[-122.267764,48.246337],"type":"Point"}
}