{
  "type": "Feature",
  "properties": {
    "addr:full":"17807 Pacific Ave S Spanaway WA 98387",
    "addr:housenumber":"17807",
    "addr:postcode":"98387",
    "addr:street":"Pacific Ave S Spanaway",
    "iso:country":"US",
    "sg:address":"17807 Pacific Ave S",
    "sg:city":"Spanaway",
    "sg:classifiers":[
        {
            "category":"Restaurant",
            "type":"Food & Drink"
        }
    ],
    "sg:phone":"+1 253 847 5455",
    "sg:postcode":"98387",
    "sg:province":"WA",
    "wof:name":"Hidalgo Mexican Restaurant",
    "wof:placetype":"venue"
},
  "geometry": {"coordinates":[-122.43497499999999,47.095395],"type":"Point"}
}