{
  "type": "Feature",
  "properties": {
    "addr:full":"1262 State Ave Marysville WA 98270",
    "addr:housenumber":"1262",
    "addr:postcode":"98270",
    "addr:street":"State Ave",
    "iso:country":"US",
    "sg:address":"1262 State Ave",
    "sg:city":"Marysville",
    "sg:classifiers":[
        {
            "category":"Restaurant",
            "type":"Food & Drink"
        }
    ],
    "sg:menulink":"http://www.allmenus.com/wa/marysville/78041-papa-murphys/menu/",
    "sg:phone":"+1 360 651 7272",
    "sg:postcode":"98270",
    "sg:province":"WA",
    "sg:tags":[
        "american",
        "pizza"
    ],
    "wof:name":"Papa Murphy's",
    "wof:placetype":"venue"
},
  "geometry": {"coordinates":[-122.17671199999999,48.063399],"type":"Point"}
}