{
  "type": "Feature",
  "properties": {
    "addr:full":"305 Harrison St Seattle Center - Center House Seattle WA 98109",
    "addr:housenumber":"305",
    "addr:postcode":"98109",
    "addr:street":"Harrison St",
    "iso:country":"US",
    "sg:address":"305 Harrison St Seattle Center - Center House",
    "sg:city":"Seattle",
    "sg:classifiers":[
        {
            "category":"Restaurant",
            "type":"Food & Drink"
        }
    ],
    "sg:phone":"+1 206 443 0728",
    "sg:postcode":"98109",
    "sg:province":"WA",
    "sg:tags":[
        "japanese"
    ],
    "sg:website":"www.seattlecenter.com/attraction...",
    "wof:name":"Teriyaki Tokyo",
    "wof:placetype":"venue"
},
  "geometry": {"coordinates":[-122.348601,47.622104],"type":"Point"}
}