{
  "type": "Feature",
  "properties": {
    "addr:full":"702 R Ave Anacortes WA 98221",
    "addr:housenumber":"702",
    "addr:postcode":"98221",
    "addr:street":"R Ave",
    "iso:country":"US",
    "sg:address":"702 R Ave",
    "sg:city":"Anacortes",
    "sg:classifiers":[
        {
            "category":"Building & Trades",
            "subcategory":"Construction",
            "type":"Services"
        }
    ],
    "sg:phone":"+1 360 293 8888",
    "sg:postcode":"98221",
    "sg:province":"WA",
    "sg:tags":[
        "designer",
        "marine",
        "contractor"
    ],
    "wof:name":"Transpac Marinas Inc",
    "wof:placetype":"venue"
},
  "geometry": {"coordinates":[-122.609503,48.51662],"type":"Point"}
}