{
  "type": "Feature",
  "properties": {
    "addr:full":"505 E Saint Thomas More Way Spokane WA 99208",
    "addr:housenumber":"505",
    "addr:postcode":"99208",
    "addr:street":"E;More Way",
    "iso:country":"US",
    "sg:address":"505 E Saint Thomas More Way",
    "sg:city":"Spokane",
    "sg:classifiers":[
        {
            "category":"Organizations",
            "subcategory":"Religious Organization",
            "type":"Services"
        },
        {
            "category":"Education",
            "subcategory":"School",
            "type":"Public Place"
        }
    ],
    "sg:phone":"+1 509 466 3811",
    "sg:postcode":"99208",
    "sg:province":"WA",
    "sg:tags":[
        "elementary",
        "catholic"
    ],
    "wof:name":"St Thomas More Catholic School",
    "wof:placetype":"venue"
},
  "geometry": {"coordinates":[-117.45081,47.732527],"type":"Point"}
}