{
  "type": "Feature",
  "properties": {
    "addr:full":"1412 158th St E Tacoma WA 98445",
    "addr:housenumber":"1412",
    "addr:postcode":"98445",
    "addr:street":"158Th St",
    "iso:country":"US",
    "sg:address":"1412 158th St E",
    "sg:city":"Tacoma",
    "sg:classifiers":[
        {
            "category":"Building & Trades",
            "subcategory":"Cleaning & Sanitation",
            "type":"Services"
        }
    ],
    "sg:phone":"+1 253 531 2013",
    "sg:postcode":"98445",
    "sg:province":"WA",
    "sg:tags":[
        "maintenance"
    ],
    "wof:name":"J&W Services",
    "wof:placetype":"venue"
},
  "geometry": {"coordinates":[-122.410551,47.113168],"type":"Point"}
}