{
  "type": "Feature",
  "properties": {
    "addr:full":"5723 N 26th St Tacoma WA 98407",
    "addr:housenumber":"5723",
    "addr:postcode":"98407",
    "addr:street":"N 26Th St",
    "iso:country":"US",
    "sg:address":"5723 N 26th St",
    "sg:city":"Tacoma",
    "sg:classifiers":[
        {
            "category":"Banks & Credit Unions",
            "subcategory":"Bank",
            "type":"Services"
        }
    ],
    "sg:phone":"+1 253 761 1834",
    "sg:postcode":"98407",
    "sg:province":"WA",
    "wof:name":"Washington Mutual",
    "wof:placetype":"venue"
},
  "geometry": {"coordinates":[-122.515683,47.271165],"type":"Point"}
}