{
  "type": "Feature",
  "properties": {
    "addr:full":"829 N 10th St Ste G Renton WA 98055",
    "addr:housenumber":"829",
    "addr:postcode":"98055",
    "addr:street":"N 10Th St Ste G",
    "iso:country":"US",
    "sg:address":"829 N 10th St Ste G",
    "sg:city":"Renton",
    "sg:classifiers":[
        {
            "category":"Restaurant",
            "type":"Food & Drink"
        }
    ],
    "sg:phone":"+1 425 228 2800",
    "sg:postcode":"98055",
    "sg:province":"WA",
    "sg:tags":[
        "sushi",
        "bar",
        "japanese"
    ],
    "wof:name":"Izakaya Sushi",
    "wof:placetype":"venue"
},
  "geometry": {"coordinates":[-122.205262,47.497604],"type":"Point"}
}