{
  "type": "Feature",
  "properties": {
    "addr:full":"580 Hemlock Way Edmonds WA 98020",
    "addr:housenumber":"580",
    "addr:postcode":"98020",
    "addr:street":"Hemlock Way",
    "iso:country":"US",
    "sg:address":"580 Hemlock Way",
    "sg:city":"Edmonds",
    "sg:classifiers":[
        {
            "category":"Insurance",
            "subcategory":"Insurance Agent",
            "type":"Services"
        }
    ],
    "sg:phone":"+1 425 771 7100",
    "sg:postcode":"98020",
    "sg:province":"WA",
    "wof:name":"Vanhollebeke Insur Fincl Svcs",
    "wof:placetype":"venue"
},
  "geometry": {"coordinates":[-122.37692199999999,47.804629],"type":"Point"}
}