{
  "type": "Feature",
  "properties": {
    "addr:full":"5620 200th St SW Lynnwood WA 98036",
    "addr:housenumber":"5620",
    "addr:postcode":"98036",
    "addr:street":"200Th St Sw",
    "iso:country":"US",
    "sg:address":"5620 200th St SW",
    "sg:city":"Lynnwood",
    "sg:classifiers":[
        {
            "category":"Building & Trades",
            "subcategory":"Equipment Rental",
            "type":"Services"
        }
    ],
    "sg:phone":"+1 425 672 9272",
    "sg:postcode":"98036",
    "sg:province":"WA",
    "wof:name":"Jacqueline Lee Mettler",
    "wof:placetype":"venue"
},
  "geometry": {"coordinates":[-122.31043699999999,47.817421],"type":"Point"}
}