{
  "type": "Feature",
  "properties": {
    "addr:full":"14413 SE 132nd St Renton WA 98059",
    "addr:postcode":"14413;98059",
    "addr:street":"Se 132Nd St",
    "iso:country":"US",
    "sg:address":"14413 SE 132nd St",
    "sg:city":"Renton",
    "sg:classifiers":[
        {
            "category":"Building & Trades",
            "subcategory":"Construction",
            "type":"Services"
        }
    ],
    "sg:phone":"+1 425 235 8680",
    "sg:postcode":"98059",
    "sg:province":"WA",
    "sg:tags":[
        "hanging",
        "contractor"
    ],
    "wof:name":"Horizon Painting Services",
    "wof:placetype":"venue"
},
  "geometry": {"coordinates":[-122.145849,47.484885],"type":"Point"}
}