{
  "type": "Feature",
  "properties": {
    "addr:full":"1302 SE Everett Mall Way Everett WA 98208",
    "addr:housenumber":"1302",
    "addr:postcode":"98208",
    "addr:street":"Se Everett Mall Way",
    "iso:country":"US",
    "sg:address":"1302 SE Everett Mall Way",
    "sg:city":"Everett",
    "sg:classifiers":[
        {
            "category":"Autos & Motor Vehicles",
            "subcategory":"Auto Supplies",
            "type":"Retail Goods"
        },
        {
            "category":"Retail",
            "subcategory":"Auto Repair",
            "type":"Services"
        }
    ],
    "sg:phone":"+1 425 356 6775",
    "sg:postcode":"98208",
    "sg:province":"WA",
    "sg:tags":[
        "oil",
        "tire",
        "automobile",
        "accessory",
        "lube",
        "part",
        "supplies-used",
        "brake",
        "rebuilt"
    ],
    "sg:website":"http://www.sears.com/shc/s/v_10153_12605_Automotive?adCell=AH",
    "wof:name":"Sears Auto Center",
    "wof:placetype":"venue"
},
  "geometry": {"coordinates":[-122.21472,47.911914],"type":"Point"}
}