{
  "type": "Feature",
  "properties": {
    "addr:full":"1624 Grove St Marysville WA 98270",
    "addr:housenumber":"1624",
    "addr:postcode":"98270",
    "addr:street":"Grove St",
    "iso:country":"US",
    "sg:address":"1624 Grove St",
    "sg:city":"Marysville",
    "sg:classifiers":[
        {
            "category":"Social Services",
            "type":"Services"
        }
    ],
    "sg:phone":"+1 360 651 0535",
    "sg:postcode":"98270",
    "sg:province":"WA",
    "sg:tags":[
        "counseling"
    ],
    "wof:name":"Roberts Joy",
    "wof:placetype":"venue"
},
  "geometry": {"coordinates":[-122.173541,48.061183],"type":"Point"}
}