{
  "type": "Feature",
  "properties": {
    "addr:full":"919 Lakeridge Way SW Olympia WA 98502",
    "addr:housenumber":"919",
    "addr:postcode":"98502",
    "addr:street":"Lakeridge Way Sw",
    "iso:country":"US",
    "sg:address":"919 Lakeridge Way SW",
    "sg:city":"Olympia",
    "sg:classifiers":[
        {
            "category":"Government",
            "subcategory":"Office",
            "type":"Public Place"
        }
    ],
    "sg:phone":"+1 360 664 8717",
    "sg:postcode":"98502",
    "sg:province":"WA",
    "wof:name":"Hearings Administrative Ofc",
    "wof:placetype":"venue"
},
  "geometry": {"coordinates":[-122.913428,47.027279],"type":"Point"}
}