{
  "type": "Feature",
  "properties": {
    "addr:full":"18849 State Hwy 305 Poulsbo WA 98370",
    "addr:housenumber":"18849",
    "addr:postcode":"98370",
    "addr:street":"State Hwy 305",
    "iso:country":"US",
    "sg:address":"18849 State Hwy 305",
    "sg:city":"Poulsbo",
    "sg:classifiers":[
        {
            "category":"Professional",
            "type":"Services"
        }
    ],
    "sg:phone":"+1 360 697 3928",
    "sg:postcode":"98370",
    "sg:province":"WA",
    "wof:name":"Al White",
    "wof:placetype":"venue"
},
  "geometry": {"coordinates":[-122.637725,47.736249],"type":"Point"}
}