{
  "type": "Feature",
  "properties": {
    "addr:full":"4805 Beacon Ave S Seattle WA 98108",
    "addr:housenumber":"4805",
    "addr:postcode":"98108",
    "addr:street":"Beacon Ave S",
    "iso:country":"US",
    "sg:address":"4805 Beacon Ave S",
    "sg:city":"Seattle",
    "sg:classifiers":[
        {
            "category":"Personal",
            "subcategory":"Beauty Salon",
            "type":"Services"
        }
    ],
    "sg:phone":"+1 206 762 1385",
    "sg:postcode":"98108",
    "sg:province":"WA",
    "wof:name":"Eleonora Beauty Salon",
    "wof:placetype":"venue"
},
  "geometry": {"coordinates":[-122.304637,47.559571],"type":"Point"}
}