{
  "type": "Feature",
  "properties": {
    "addr:full":"13631 NE 126th Pl Kirkland WA 98034",
    "addr:housenumber":"13631",
    "addr:postcode":"98034",
    "addr:street":"Ne 126Th Pl",
    "iso:country":"US",
    "sg:address":"13631 NE 126th Pl",
    "sg:city":"Kirkland",
    "sg:classifiers":[
        {
            "category":"Retail",
            "subcategory":"Auto Repair",
            "type":"Services"
        }
    ],
    "sg:phone":"+1 425 814 4846",
    "sg:postcode":"98034",
    "sg:province":"WA",
    "sg:tags":[
        "general"
    ],
    "wof:name":"Rodriguez Automotive",
    "wof:placetype":"venue"
},
  "geometry": {"coordinates":[-122.159875,47.71398],"type":"Point"}
}