{
  "type": "Feature",
  "properties": {
    "addr:full":"1417 W Pinehill Rd Spokane WA 99218",
    "addr:housenumber":"1417",
    "addr:postcode":"99218",
    "addr:street":"W Pinehill Rd",
    "iso:country":"US",
    "sg:address":"1417 W Pinehill Rd",
    "sg:city":"Spokane",
    "sg:classifiers":[
        {
            "category":"Building & Trades",
            "subcategory":"Construction",
            "type":"Services"
        }
    ],
    "sg:phone":"+1 509 467 3320",
    "sg:postcode":"99218",
    "sg:province":"WA",
    "sg:tags":[
        "home",
        "general",
        "family",
        "contractor"
    ],
    "wof:name":"Caleighs Quality Craftsman",
    "wof:placetype":"venue"
},
  "geometry": {"coordinates":[-117.43663100000001,47.76719],"type":"Point"}
}