{
  "type": "Feature",
  "properties": {
    "addr:full":"340 N River Ave Buckley WA 98321",
    "addr:housenumber":"340",
    "addr:postcode":"98321",
    "addr:street":"N River Ave",
    "iso:country":"US",
    "sg:address":"340 N River Ave",
    "sg:city":"Buckley",
    "sg:classifiers":[
        {
            "category":"Education",
            "subcategory":"School",
            "type":"Public Place"
        }
    ],
    "sg:phone":"+1 360 829 3354",
    "sg:postcode":"98321",
    "sg:province":"WA",
    "wof:name":"Elk Ridge Elementary School",
    "wof:placetype":"venue"
},
  "geometry": {"coordinates":[-122.024438,47.166938],"type":"Point"}
}