{
  "type": "Feature",
  "properties": {
    "addr:full":"116 SW 148th S Burien WA 98166",
    "addr:housenumber":"116",
    "addr:postcode":"98166",
    "addr:street":"Sw 148Th S Burien",
    "iso:country":"US",
    "sg:address":"116 SW 148th S",
    "sg:city":"Burien",
    "sg:classifiers":[
        {
            "category":"Restaurant",
            "type":"Food & Drink"
        }
    ],
    "sg:phone":"+1 206 243 4500",
    "sg:postcode":"98166",
    "sg:province":"WA",
    "sg:tags":[
        "pizza"
    ],
    "wof:name":"Pizza Palace",
    "wof:placetype":"venue"
},
  "geometry": {"coordinates":[-122.335836,47.4705],"type":"Point"}
}