{
  "type": "Feature",
  "properties": {
    "addr:full":"42419 N Jefferson Rd Elk WA 99009",
    "addr:housenumber":"42419",
    "addr:postcode":"99009",
    "addr:street":"N Jefferson Rd",
    "iso:country":"US",
    "sg:address":"42419 N Jefferson Rd",
    "sg:city":"Elk",
    "sg:classifiers":[
        {
            "category":"Building & Trades",
            "subcategory":"Construction",
            "type":"Services"
        }
    ],
    "sg:phone":"+1 509 292 2639",
    "sg:postcode":"99009",
    "sg:province":"WA",
    "wof:name":"Jack Oliver Construction",
    "wof:placetype":"venue"
},
  "geometry": {"coordinates":[-117.18686,48.044379],"type":"Point"}
}