{
  "type": "Feature",
  "properties": {
    "addr:full":"16 Williams Rd White Salmon WA 98672",
    "addr:housenumber":"16",
    "addr:postcode":"98672",
    "addr:street":"Williams Rd",
    "iso:country":"US",
    "sg:address":"16 Williams Rd",
    "sg:city":"White Salmon",
    "sg:classifiers":[
        {
            "category":"Freight",
            "type":"Transportation"
        }
    ],
    "sg:phone":"+1 509 493 2050",
    "sg:postcode":"98672",
    "sg:province":"WA",
    "sg:tags":[
        "operator",
        "local",
        "trucking"
    ],
    "wof:name":"Art Walker Inc",
    "wof:placetype":"venue"
},
  "geometry": {"coordinates":[-121.48164300000001,45.761867],"type":"Point"}
}