{
  "type": "Feature",
  "properties": {
    "addr:full":"601 E 18th St La Center WA 98629",
    "addr:housenumber":"601",
    "addr:postcode":"98629",
    "addr:street":"E 18Th St",
    "iso:country":"US",
    "sg:address":"601 E 18th St",
    "sg:city":"La Center",
    "sg:phone":"+1 360 263 6224",
    "sg:postcode":"98629",
    "sg:province":"WA",
    "sg:tags":[
        "gas"
    ],
    "wof:name":"Turner Gas Co",
    "wof:placetype":"venue"
},
  "geometry": {"coordinates":[-122.6664,45.871679],"type":"Point"}
}