{
  "type": "Feature",
  "properties": {
    "addr:full":"4504 E Valley Hwy E Sumner WA 98390",
    "addr:housenumber":"4504",
    "addr:postcode":"98390",
    "addr:street":"E Valley Hwy E",
    "iso:country":"US",
    "sg:address":"4504 E Valley Hwy E",
    "sg:city":"Sumner",
    "sg:classifiers":[
        {
            "category":"Freight",
            "type":"Transportation"
        }
    ],
    "sg:phone":"+1 253 804 0500",
    "sg:postcode":"98390",
    "sg:province":"WA",
    "sg:tags":[
        "operator",
        "te",
        "truck"
    ],
    "wof:name":"Farwest Freight Systems Inc",
    "wof:placetype":"venue"
},
  "geometry": {"coordinates":[-122.22661600000001,47.214771],"type":"Point"}
}