{
  "type": "Feature",
  "properties": {
    "addr:full":"1776 Boston St Richland WA 99354",
    "addr:housenumber":"1776",
    "addr:postcode":"99354",
    "addr:street":"Boston St",
    "iso:country":"US",
    "sg:address":"1776 Boston St",
    "sg:city":"Richland",
    "sg:classifiers":[
        {
            "category":"Building & Trades",
            "subcategory":"Landscaping Services",
            "type":"Services"
        }
    ],
    "sg:phone":"+1 509 946 7547",
    "sg:postcode":"99354",
    "sg:province":"WA",
    "sg:tags":[
        "landscape",
        "contractor"
    ],
    "wof:name":"Winners Circle Enterprises",
    "wof:placetype":"venue"
},
  "geometry": {"coordinates":[-119.294735,46.297933],"type":"Point"}
}