{
  "type": "Feature",
  "properties": {
    "addr:full":"22523 Treefarm Ln NE Poulsbo WA 98370",
    "addr:postcode":"22523;98370",
    "addr:street":"Treefarm Ln Ne",
    "iso:country":"US",
    "sg:address":"22523 Treefarm Ln NE",
    "sg:city":"Poulsbo",
    "sg:classifiers":[
        {
            "category":"Utilities",
            "subcategory":"Mobile Phone",
            "type":"Services"
        }
    ],
    "sg:phone":"+1 360 710 4063",
    "sg:postcode":"98370",
    "sg:province":"WA",
    "sg:tags":[
        "communications",
        "trailer"
    ],
    "wof:name":"Skybusters",
    "wof:placetype":"venue"
},
  "geometry": {"coordinates":[-122.616454,47.776431],"type":"Point"}
}