{
  "type": "Feature",
  "properties": {
    "addr:full":"24040 SE Black Nugget Rd Issaquah WA 98029",
    "addr:postcode":"24040;98029",
    "addr:street":"Se;Nugget Rd",
    "iso:country":"US",
    "sg:address":"24040 SE Black Nugget Rd",
    "sg:city":"Issaquah",
    "sg:classifiers":[
        {
            "category":"Shopping",
            "subcategory":"Gifts & Souvenirs",
            "type":"Retail Goods"
        }
    ],
    "sg:phone":"+1 425 313 5081",
    "sg:postcode":"98029",
    "sg:province":"WA",
    "wof:name":"El Nido",
    "wof:placetype":"venue"
},
  "geometry": {"coordinates":[-122.019745,47.550237],"type":"Point"}
}