{
  "type": "Feature",
  "properties": {
    "addr:full":"5199 76th St SW Mukilteo WA 98275",
    "addr:housenumber":"5199",
    "addr:postcode":"98275",
    "addr:street":"76Th St Sw",
    "iso:country":"US",
    "sg:address":"5199 76th St SW",
    "sg:city":"Mukilteo",
    "sg:classifiers":[
        {
            "category":"Restaurant",
            "type":"Food & Drink"
        }
    ],
    "sg:menulink":"http://www.allmenus.com/wa/everett/55340-tasti-thai/menu/",
    "sg:phone":"+1 425 775 2141",
    "sg:postcode":"98275",
    "sg:province":"WA",
    "sg:tags":[
        "thai",
        "asian"
    ],
    "wof:name":"Tasti Thai",
    "wof:placetype":"venue"
},
  "geometry": {"coordinates":[-122.30144799999999,47.929082],"type":"Point"}
}