{
  "type": "Feature",
  "properties": {
    "addr:full":"1712 NW 85th St Seattle WA 98117",
    "addr:housenumber":"1712",
    "addr:postcode":"98117",
    "addr:street":"Nw 85Th St",
    "iso:country":"US",
    "sg:address":"1712 NW 85th St",
    "sg:city":"Seattle",
    "sg:classifiers":[
        {
            "category":"Professional",
            "subcategory":"Computer Services",
            "type":"Services"
        }
    ],
    "sg:phone":"+1 206 789 4694",
    "sg:postcode":"98117",
    "sg:province":"WA",
    "sg:tags":[
        "datum"
    ],
    "wof:name":"P&E Productions",
    "wof:placetype":"venue"
},
  "geometry": {"coordinates":[-122.379942,47.690672],"type":"Point"}
}