{
  "type": "Feature",
  "properties": {
    "addr:full":"14844 260th Ave SE Issaquah WA 98027",
    "addr:housenumber":"14844",
    "addr:postcode":"98027",
    "addr:street":"260Th Ave Se",
    "iso:country":"US",
    "sg:address":"14844 260th Ave SE",
    "sg:city":"Issaquah",
    "sg:classifiers":[
        {
            "category":"Wholesale",
            "subcategory":"Toys & Hobbies",
            "type":"Manufacturing & Wholesale Goods"
        }
    ],
    "sg:phone":"+1 425 392 2230",
    "sg:postcode":"98027",
    "sg:province":"WA",
    "wof:name":"Mowrey Dunning Sales Inc",
    "wof:placetype":"venue"
},
  "geometry": {"coordinates":[-121.993702,47.468853],"type":"Point"}
}