{
  "type": "Feature",
  "properties": {
    "addr:full":"10822 Stedman Rd SE Olympia WA 98513",
    "addr:housenumber":"10822",
    "addr:postcode":"olympia;98513",
    "addr:street":"Stedman Rd Se",
    "iso:country":"US",
    "sg:address":"10822 Stedman Rd SE",
    "sg:city":"Olympia",
    "sg:classifiers":[
        {
            "category":"Home & Garden",
            "subcategory":"Building Materials",
            "type":"Retail Goods"
        }
    ],
    "sg:phone":"+1 360 491 8003",
    "sg:postcode":"98513",
    "sg:province":"WA",
    "sg:tags":[
        "door"
    ],
    "sg:website":"www.olydoors.com",
    "wof:name":"Olympia Overhead Doors",
    "wof:placetype":"venue"
},
  "geometry": {"coordinates":[-122.80955299999999,46.931971],"type":"Point"}
}