{
  "type": "Feature",
  "properties": {
    "addr:full":"1009 196th St E Spanaway WA 98387",
    "addr:housenumber":"1009",
    "addr:postcode":"98387",
    "addr:street":"196Th St E",
    "iso:country":"US",
    "sg:address":"1009 196th St E",
    "sg:city":"Spanaway",
    "sg:classifiers":[
        {
            "category":"Building & Trades",
            "subcategory":"Plumbing",
            "type":"Services"
        }
    ],
    "sg:phone":"+1 253 847 0421",
    "sg:postcode":"98387",
    "sg:province":"WA",
    "sg:tags":[
        "plumbing",
        "contractor"
    ],
    "wof:name":"Smith Plumbing and Drain LLC",
    "wof:placetype":"venue"
},
  "geometry": {"coordinates":[-122.41649700000001,47.078939],"type":"Point"}
}