{
  "type": "Feature",
  "properties": {
    "addr:full":"3856 23rd Ave SW Seattle WA 98106",
    "addr:housenumber":"3856",
    "addr:postcode":"98106",
    "addr:street":"23Rd Ave Sw",
    "iso:country":"US",
    "sg:address":"3856 23rd Ave SW",
    "sg:city":"Seattle",
    "sg:classifiers":[
        {
            "category":"Communications",
            "type":"Services"
        }
    ],
    "sg:phone":"+1 206 935 1165",
    "sg:postcode":"98106",
    "sg:province":"WA",
    "sg:tags":[
        "recording",
        "rehearsal",
        "studio"
    ],
    "wof:name":"Secrets Studio Records Inc",
    "wof:placetype":"venue"
},
  "geometry": {"coordinates":[-122.36199999999999,47.569199],"type":"Point"}
}