{
  "type": "Feature",
  "properties": {
    "addr:full":"7609 NW 3rd Ave Vancouver WA 98665",
    "addr:housenumber":"7609",
    "addr:postcode":"98665",
    "addr:street":"Nw 3Rd Ave",
    "iso:country":"US",
    "sg:address":"7609 NW 3rd Ave",
    "sg:city":"Vancouver",
    "sg:classifiers":[
        {
            "category":"Manufacturing",
            "subcategory":"Apparel",
            "type":"Manufacturing & Wholesale Goods"
        }
    ],
    "sg:phone":"+1 360 993 2885",
    "sg:postcode":"98665",
    "sg:province":"WA",
    "sg:tags":[
        "dress",
        "mfg"
    ],
    "wof:name":"Ms Nelly S Williams",
    "wof:placetype":"venue"
},
  "geometry": {"coordinates":[-122.6735,45.67774],"type":"Point"}
}