{
  "type": "Feature",
  "properties": {
    "addr:full":"201 Auburn Way S Auburn WA 98002",
    "addr:housenumber":"201",
    "addr:postcode":"98002",
    "addr:street":"Auburn Way S",
    "iso:country":"US",
    "sg:address":"201 Auburn Way S",
    "sg:city":"Auburn",
    "sg:classifiers":[
        {
            "category":"Food & Beverages",
            "subcategory":"Groceries & Convenience Stores",
            "type":"Retail Goods"
        }
    ],
    "sg:phone":"+1 253 833 8272",
    "sg:postcode":"98002",
    "sg:province":"WA",
    "wof:name":"Auburn Way Shell Food Mart",
    "wof:placetype":"venue"
},
  "geometry": {"coordinates":[-122.225689,47.304157],"type":"Point"}
}