{
  "type": "Feature",
  "properties": {
    "addr:full":"2500 116th Ave NE Ste 2 Bellevue WA 98004",
    "addr:housenumber":"2500",
    "addr:postcode":"98004",
    "addr:street":"116Th Ave Ne Ste 2",
    "iso:country":"US",
    "sg:address":"2500 116th Ave NE Ste 2",
    "sg:city":"Bellevue",
    "sg:classifiers":[
        {
            "category":"Building & Trades",
            "subcategory":"Construction",
            "type":"Services"
        }
    ],
    "sg:phone":"+1 425 828 6180",
    "sg:postcode":"98004",
    "sg:province":"WA",
    "sg:tags":[
        "management"
    ],
    "wof:name":"Associated Construction Cons",
    "wof:placetype":"venue"
},
  "geometry": {"coordinates":[-122.185638,47.632519],"type":"Point"}
}