{
  "type": "Feature",
  "properties": {
    "addr:full":"2116 E Section St Mount Vernon WA 98274",
    "addr:housenumber":"2116",
    "addr:postcode":"98274",
    "addr:street":"E Section St",
    "iso:country":"US",
    "sg:address":"2116 E Section St",
    "sg:city":"Mount Vernon",
    "sg:classifiers":[
        {
            "category":"Health Services",
            "subcategory":"Doctor",
            "type":"Services"
        }
    ],
    "sg:phone":"+1 360 428 1700",
    "sg:postcode":"98274",
    "sg:province":"WA",
    "sg:tags":[
        "physician",
        "surgeon",
        "practice",
        "family"
    ],
    "sg:website":"www.ncfp.net",
    "wof:name":"North Cascade Family Physicians PS",
    "wof:placetype":"venue"
},
  "geometry": {"coordinates":[-122.31500200000001,48.413601],"type":"Point"}
}