{
  "type": "Feature",
  "properties": {
    "addr:full":"195 Front St N Issaquah WA 98027",
    "addr:housenumber":"195",
    "addr:postcode":"98027",
    "addr:street":"Front St N",
    "iso:country":"US",
    "sg:address":"195 Front St N",
    "sg:city":"Issaquah",
    "sg:classifiers":[
        {
            "category":"Building & Trades",
            "subcategory":"Landscaping Services",
            "type":"Services"
        }
    ],
    "sg:phone":"+1 425 392 2394",
    "sg:postcode":"98027",
    "sg:province":"WA",
    "sg:tags":[
        "designer",
        "landscape"
    ],
    "wof:name":"Jane Garrison Landscape Arch",
    "wof:placetype":"venue"
},
  "geometry": {"coordinates":[-122.03654,47.532422],"type":"Point"}
}