{
  "type": "Feature",
  "properties": {
    "iso:country":"US",
    "sg:address":"2130 S 248th St",
    "sg:city":"Seattle",
    "sg:classifiers":[
        {
            "category":"Organizations",
            "subcategory":"Religious Organization",
            "type":"Services"
        }
    ],
    "sg:phone":"+1 206 878 2013",
    "sg:postcode":"98198",
    "sg:province":"WA",
    "wof:name":"Marcus Whitman Presbt Church",
    "wof:placetype":"venue"
},
  "geometry": {"coordinates":[-122.305238,47.379587],"type":"Point"}
}