{
  "type": "Feature",
  "properties": {
    "addr:full":"2069 W Hwy 26 Othello WA 99344",
    "addr:housenumber":"2069",
    "addr:postcode":"99344",
    "addr:street":"W Hwy 26 Othello",
    "iso:country":"US",
    "sg:address":"2069 W Hwy 26",
    "sg:city":"Othello",
    "sg:classifiers":[
        {
            "category":"Government",
            "subcategory":"Police Station",
            "type":"Public Place"
        }
    ],
    "sg:phone":"+1 509 488 2061",
    "sg:postcode":"99344",
    "sg:province":"WA",
    "sg:tags":[
        "sheriff"
    ],
    "sg:website":"www.co.adams.wa.us",
    "wof:name":"Adams County Sheriff",
    "wof:placetype":"venue"
},
  "geometry": {"coordinates":[-119.16961000000001,46.811519],"type":"Point"}
}