{
  "type": "Feature",
  "properties": {
    "addr:full":"1741 First Ave S Seattle WA 98134",
    "addr:housenumber":"1741",
    "addr:postcode":"98134",
    "addr:street":"First Ave S",
    "iso:country":"US",
    "sg:address":"1741 First Ave S",
    "sg:city":"Seattle",
    "sg:classifiers":[
        {
            "category":"Communications",
            "type":"Services"
        }
    ],
    "sg:phone":"+1 206 971 4200",
    "sg:postcode":"98134",
    "sg:province":"WA",
    "sg:tags":[
        "medium",
        "mass"
    ],
    "sg:website":"www.tm.com",
    "wof:name":"TM Advertising",
    "wof:placetype":"venue"
},
  "geometry": {"coordinates":[-122.334222,47.587766],"type":"Point"}
}