{
  "type": "Feature",
  "properties": {
    "addr:full":"17211 NE 27th Ave Ridgefield WA 98642",
    "addr:housenumber":"17211",
    "addr:postcode":"98642",
    "addr:street":"Ne 27Th Ave",
    "iso:country":"US",
    "sg:address":"17211 NE 27th Ave",
    "sg:city":"Ridgefield",
    "sg:classifiers":[
        {
            "category":"Retail",
            "subcategory":"Auto Repair",
            "type":"Services"
        }
    ],
    "sg:phone":"+1 360 574 7633",
    "sg:postcode":"98642",
    "sg:province":"WA",
    "sg:tags":[
        "automotive"
    ],
    "wof:name":"Wicks n Sticks",
    "wof:placetype":"venue"
},
  "geometry": {"coordinates":[-122.64345400000001,45.74638],"type":"Point"}
}