{
  "type": "Feature",
  "properties": {
    "addr:full":"1116 N 20th Ave Pasco WA 99301",
    "addr:housenumber":"1116",
    "addr:postcode":"99301",
    "addr:street":"N 20Th Ave",
    "iso:country":"US",
    "sg:address":"1116 N 20th Ave",
    "sg:city":"Pasco",
    "sg:classifiers":[
        {
            "category":"Social Services",
            "subcategory":"Child Care",
            "type":"Services"
        }
    ],
    "sg:phone":"+1 509 547 8277",
    "sg:postcode":"99301",
    "sg:province":"WA",
    "sg:tags":[
        "day"
    ],
    "wof:name":"Emmanuel Baptist Day Care Ctr",
    "wof:placetype":"venue"
},
  "geometry": {"coordinates":[-119.11748,46.239123],"type":"Point"}
}