{
  "type": "Feature",
  "properties": {
    "iso:country":"US",
    "sg:address":"6403 E Mill Plain Blvd",
    "sg:city":"Vancouver",
    "sg:classifiers":[
        {
            "category":"Food & Beverages",
            "subcategory":"Specialty",
            "type":"Retail Goods"
        }
    ],
    "sg:phone":"+1 360 750 9773",
    "sg:postcode":"98661",
    "sg:province":"WA",
    "sg:tags":[
        "bars",
        "espresso"
    ],
    "wof:name":"Hot Shots",
    "wof:placetype":"venue"
},
  "geometry": {"coordinates":[-122.601742,45.626767],"type":"Point"}
}