{
  "type": "Feature",
  "properties": {
    "addr:full":"2114 SW Andover St D210 Seattle WA 98106",
    "addr:housenumber":"2114",
    "addr:postcode":"98106",
    "addr:street":"Sw Andover St",
    "iso:country":"US",
    "sg:address":"2114 SW Andover St D210",
    "sg:city":"Seattle",
    "sg:classifiers":[
        {
            "category":"Health Services",
            "subcategory":"Podiatrist",
            "type":"Services"
        }
    ],
    "sg:phone":"+1 206 985 4000",
    "sg:postcode":"98106",
    "sg:province":"WA",
    "sg:tags":[
        "equipment",
        "supply"
    ],
    "wof:name":"Schryver Medical Sales And Marketing",
    "wof:placetype":"venue"
},
  "geometry": {"coordinates":[-122.360263,47.568352],"type":"Point"}
}