{
  "type": "Feature",
  "properties": {
    "addr:full":"727 River Rd Puyallup WA 98371",
    "addr:housenumber":"727",
    "addr:postcode":"98371",
    "addr:street":"River Rd",
    "iso:country":"US",
    "sg:address":"727 River Rd",
    "sg:city":"Puyallup",
    "sg:classifiers":[
        {
            "category":"Cinema",
            "subcategory":"Movie Rental",
            "type":"Entertainment"
        }
    ],
    "sg:phone":"+1 253 848 5008",
    "sg:postcode":"98371",
    "sg:province":"WA",
    "sg:tags":[
        "video",
        "tape"
    ],
    "wof:name":"Video World Inc",
    "wof:placetype":"venue"
},
  "geometry": {"coordinates":[-122.305252,47.201685],"type":"Point"}
}