{
  "type": "Feature",
  "properties": {
    "addr:full":"1070 NE Goldie St Oak Harbor WA 98277",
    "addr:housenumber":"1070",
    "addr:postcode":"98277",
    "addr:street":"Ne Goldie St",
    "iso:country":"US",
    "sg:address":"1070 NE Goldie St",
    "sg:city":"Oak Harbor",
    "sg:classifiers":[
        {
            "category":"Real Estate",
            "subcategory":"Real Estate Agent",
            "type":"Services"
        }
    ],
    "sg:phone":"+1 360 679 4600",
    "sg:postcode":"98277",
    "sg:province":"WA",
    "sg:tags":[
        "management"
    ],
    "wof:name":"Cascade Property Services LLC",
    "wof:placetype":"venue"
},
  "geometry": {"coordinates":[-122.643805,48.308602],"type":"Point"}
}