{
  "type": "Feature",
  "properties": {
    "addr:full":"5045 S Yakima Ave Tacoma WA 98408",
    "addr:housenumber":"5045",
    "addr:postcode":"98408",
    "addr:street":"S Yakima Ave",
    "iso:country":"US",
    "sg:address":"5045 S Yakima Ave",
    "sg:city":"Tacoma",
    "sg:classifiers":[
        {
            "category":"Building & Trades",
            "subcategory":"Plumbing",
            "type":"Services"
        }
    ],
    "sg:phone":"+1 253 474 9928",
    "sg:postcode":"98408",
    "sg:province":"WA",
    "sg:tags":[
        "ventilation",
        "air",
        "heating",
        "conditioning",
        "contractor"
    ],
    "wof:name":"Wilson Air Technologies",
    "wof:placetype":"venue"
},
  "geometry": {"coordinates":[-122.443119,47.210408],"type":"Point"}
}