{
  "type": "Feature",
  "properties": {
    "addr:full":"1027 108th Ave SE Bellevue WA 98004",
    "addr:housenumber":"1027",
    "addr:postcode":"98004",
    "addr:street":"108Th Ave Se",
    "iso:country":"US",
    "sg:address":"1027 108th Ave SE",
    "sg:city":"Bellevue",
    "sg:classifiers":[
        {
            "category":"Building & Trades",
            "subcategory":"Locksmith",
            "type":"Services"
        }
    ],
    "sg:phone":"+1 425 738 4060",
    "sg:postcode":"98004",
    "sg:province":"WA",
    "sg:tags":[
        "key"
    ],
    "wof:name":"Always Available 7 Day Assistance of Bellevue Locksmith",
    "wof:placetype":"venue"
},
  "geometry": {"coordinates":[-122.196506,47.601213],"type":"Point"}
}