{
  "type": "Feature",
  "properties": {
    "addr:full":"322 N 2nd St Shelton WA 98584",
    "addr:housenumber":"322",
    "addr:postcode":"98584",
    "addr:street":"N 2Nd St",
    "iso:country":"US",
    "sg:address":"322 N 2nd St",
    "sg:city":"Shelton",
    "sg:classifiers":[
        {
            "category":"Banks & Credit Unions",
            "subcategory":"Investment Brokerage",
            "type":"Services"
        }
    ],
    "sg:phone":"+1 360 426 5986",
    "sg:postcode":"98584",
    "sg:province":"WA",
    "sg:tags":[
        "stock",
        "bond"
    ],
    "wof:name":"Betty J Barber",
    "wof:placetype":"venue"
},
  "geometry": {"coordinates":[-123.1009,47.214627],"type":"Point"}
}