{
  "type": "Feature",
  "properties": {
    "addr:full":"2812 140th Ave SW Tenino WA 98589",
    "addr:housenumber":"2812",
    "addr:postcode":"98589",
    "addr:street":"140Th Ave Sw",
    "iso:country":"US",
    "sg:address":"2812 140th Ave SW",
    "sg:city":"Tenino",
    "sg:classifiers":[
        {
            "category":"Farming",
            "subcategory":"Nursery",
            "type":"Manufacturing & Wholesale Goods"
        }
    ],
    "sg:phone":"+1 360 357 7299",
    "sg:postcode":"98589",
    "sg:province":"WA",
    "sg:tags":[
        "ornamental"
    ],
    "wof:name":"Bastians Bamboo",
    "wof:placetype":"venue"
},
  "geometry": {"coordinates":[-122.95000899999999,46.883639],"type":"Point"}
}