{
  "type": "Feature",
  "properties": {
    "addr:full":"1514 S 1st St Yakima WA 98901",
    "addr:housenumber":"1514",
    "addr:postcode":"98901",
    "addr:street":"S 1St St",
    "iso:country":"US",
    "sg:address":"1514 S 1st St",
    "sg:city":"Yakima",
    "sg:classifiers":[
        {
            "category":"Restaurant",
            "type":"Food & Drink"
        }
    ],
    "sg:phone":"+1 509 248 1609",
    "sg:postcode":"98901",
    "sg:province":"WA",
    "sg:tags":[
        "mexican"
    ],
    "wof:name":"El-Grullense Restaurant",
    "wof:placetype":"venue"
},
  "geometry": {"coordinates":[-120.49479599999999,46.58252],"type":"Point"}
}