{
  "type": "Feature",
  "properties": {
    "addr:full":"20237 Asotin Creek Rd Asotin WA 99402",
    "addr:postcode":"20237;99402",
    "addr:street":"Asotin Creek Rd",
    "iso:country":"US",
    "sg:address":"20237 Asotin Creek Rd",
    "sg:city":"Asotin",
    "sg:classifiers":[
        {
            "category":"Freight",
            "type":"Transportation"
        }
    ],
    "sg:phone":"+1 509 243 1185",
    "sg:postcode":"99402",
    "sg:province":"WA",
    "sg:tags":[
        "trucking"
    ],
    "wof:name":"M & L Trucking",
    "wof:placetype":"venue"
},
  "geometry": {"coordinates":[-117.27245600000001,46.295544],"type":"Point"}
}