{
  "type": "Feature",
  "properties": {
    "addr:full":"29312 SE 408th St Enumclaw WA 98022",
    "addr:postcode":"29312;98022",
    "addr:street":"Se 408Th St",
    "iso:country":"US",
    "sg:address":"29312 SE 408th St",
    "sg:city":"Enumclaw",
    "sg:classifiers":[
        {
            "category":"Building & Trades",
            "subcategory":"Construction",
            "type":"Services"
        }
    ],
    "sg:phone":"+1 360 825 4623",
    "sg:postcode":"98022",
    "sg:province":"WA",
    "sg:tags":[
        "excavation",
        "contractor"
    ],
    "wof:name":"Wheeler Const",
    "wof:placetype":"venue"
},
  "geometry": {"coordinates":[-121.951319,47.235324],"type":"Point"}
}