{
  "type": "Feature",
  "properties": {
    "addr:full":"1676 Galbraith Ln Bellingham WA 98229",
    "addr:housenumber":"1676",
    "addr:postcode":"98229",
    "addr:street":"Galbraith Ln",
    "iso:country":"US",
    "sg:address":"1676 Galbraith Ln",
    "sg:city":"Bellingham",
    "sg:classifiers":[
        {
            "category":"Building & Trades",
            "subcategory":"Landscaping Services",
            "type":"Services"
        }
    ],
    "sg:phone":"+1 360 676 8183",
    "sg:postcode":"98229",
    "sg:province":"WA",
    "wof:name":"Wordens Tractor Works",
    "wof:placetype":"venue"
},
  "geometry": {"coordinates":[-122.42392700000001,48.699612],"type":"Point"}
}