{
  "type": "Feature",
  "properties": {
    "addr:full":"7722 30th St W Tacoma WA 98466",
    "addr:housenumber":"7722",
    "addr:postcode":"98466",
    "addr:street":"30Th St W",
    "iso:country":"US",
    "sg:address":"7722 30th St W",
    "sg:city":"Tacoma",
    "sg:classifiers":[
        {
            "category":"Professional",
            "subcategory":"Computer Services",
            "type":"Services"
        }
    ],
    "sg:phone":"+1 253 564 0740",
    "sg:postcode":"98466",
    "sg:province":"WA",
    "sg:tags":[
        "programing",
        "custom"
    ],
    "wof:name":"Microbytes",
    "wof:placetype":"venue"
},
  "geometry": {"coordinates":[-122.541805,47.232488],"type":"Point"}
}