{
  "type": "Feature",
  "properties": {
    "addr:full":"1628 N 201st St Seattle WA 98133",
    "addr:housenumber":"1628",
    "addr:postcode":"98133",
    "addr:street":"N 201St St",
    "iso:country":"US",
    "sg:address":"1628 N 201st St",
    "sg:city":"Seattle",
    "sg:classifiers":[
        {
            "category":"Building & Trades",
            "subcategory":"Plumbing",
            "type":"Services"
        }
    ],
    "sg:phone":"+1 206 546 5555",
    "sg:postcode":"98133",
    "sg:province":"WA",
    "sg:tags":[
        "repair",
        "air",
        "heating",
        "conditioning"
    ],
    "wof:name":"Silver Freeze  Inc",
    "wof:placetype":"venue"
},
  "geometry": {"coordinates":[-122.33926,47.774875],"type":"Point"}
}