{
  "type": "Feature",
  "properties": {
    "addr:full":"702 S Matthews Rd Ellensburg WA 98926",
    "addr:housenumber":"702",
    "addr:postcode":"98926",
    "addr:street":"S Matthews Rd",
    "iso:country":"US",
    "sg:address":"702 S Matthews Rd",
    "sg:city":"Ellensburg",
    "sg:classifiers":[
        {
            "category":"Building & Trades",
            "subcategory":"Construction",
            "type":"Services"
        }
    ],
    "sg:phone":"+1 509 925 9875",
    "sg:postcode":"98926",
    "sg:province":"WA",
    "sg:tags":[
        "general",
        "contractor"
    ],
    "wof:name":"Arbor Design & Woodwork",
    "wof:placetype":"venue"
},
  "geometry": {"coordinates":[-120.515637,46.987298],"type":"Point"}
}