{
  "type": "Feature",
  "properties": {
    "addr:full":"9223 27th Ave NW Seattle WA 98117",
    "addr:housenumber":"9223",
    "addr:postcode":"98117",
    "addr:street":"27Th Ave Nw",
    "iso:country":"US",
    "sg:address":"9223 27th Ave NW",
    "sg:city":"Seattle",
    "sg:classifiers":[
        {
            "category":"Structure",
            "subcategory":"Office Building",
            "type":"Public Place"
        }
    ],
    "sg:phone":"+1 206 783 6612",
    "sg:postcode":"98117",
    "sg:province":"WA",
    "sg:tags":[
        "park"
    ],
    "wof:name":"Ksn Properties",
    "wof:placetype":"venue"
},
  "geometry": {"coordinates":[-122.39173099999999,47.696146],"type":"Point"}
}