{
  "type": "Feature",
  "properties": {
    "addr:full":"1705 W Wild Rose Rd Colbert WA 99005",
    "addr:housenumber":"1705",
    "addr:postcode":"99005",
    "addr:street":"W Wild Rose Rd Colbert",
    "iso:country":"US",
    "sg:address":"1705 W Wild Rose Rd",
    "sg:city":"Colbert",
    "sg:classifiers":[
        {
            "category":"Manufacturing",
            "subcategory":"Tools & Machinery",
            "type":"Manufacturing & Wholesale Goods"
        }
    ],
    "sg:phone":"+1 509 276 2172",
    "sg:postcode":"99005",
    "sg:province":"WA",
    "sg:tags":[
        "machine",
        "shop"
    ],
    "wof:name":"Perfection Machine & Repair",
    "wof:placetype":"venue"
},
  "geometry": {"coordinates":[-117.43898799999999,47.874573],"type":"Point"}
}