{
  "type": "Feature",
  "properties": {
    "addr:full":"9707 NE 14th St Bellevue WA 98004",
    "addr:housenumber":"9707",
    "addr:postcode":"98004",
    "addr:street":"Ne 14Th St",
    "iso:country":"US",
    "sg:address":"9707 NE 14th St",
    "sg:city":"Bellevue",
    "sg:classifiers":[
        {
            "category":"Shopping",
            "subcategory":"Clothing, Apparel, & Fashions",
            "type":"Retail Goods"
        }
    ],
    "sg:phone":"+1 425 454 8332",
    "sg:postcode":"98004",
    "sg:province":"WA",
    "wof:name":"Silk Merchants",
    "wof:placetype":"venue"
},
  "geometry": {"coordinates":[-122.209954,47.622852],"type":"Point"}
}