{
  "type": "Feature",
  "properties": {
    "addr:full":"24324 Military Rd S Kent WA 98032",
    "addr:housenumber":"24324",
    "addr:postcode":"98032",
    "addr:street":"Military Rd S",
    "iso:country":"US",
    "sg:address":"24324 Military Rd S",
    "sg:city":"Kent",
    "sg:classifiers":[
        {
            "category":"Communications",
            "subcategory":"Film & Video Production",
            "type":"Services"
        }
    ],
    "sg:phone":"+1 206 870 7702",
    "sg:postcode":"98032",
    "sg:province":"WA",
    "sg:tags":[
        "motion"
    ],
    "wof:name":"Nakajin Productions",
    "wof:placetype":"venue"
},
  "geometry": {"coordinates":[-122.28632,47.383282],"type":"Point"}
}