{
  "type": "Feature",
  "properties": {
    "addr:full":"2900 S College St Seattle WA 98144",
    "addr:housenumber":"2900",
    "addr:postcode":"98144",
    "addr:street":"S College St",
    "iso:country":"US",
    "sg:address":"2900 S College St",
    "sg:city":"Seattle",
    "sg:classifiers":[
        {
            "category":"Education",
            "subcategory":"University",
            "type":"Public Place"
        }
    ],
    "sg:phone":"+1 800 433 3243",
    "sg:postcode":"98144",
    "sg:province":"WA",
    "sg:tags":[
        "college"
    ],
    "wof:name":"South College Street Park",
    "wof:placetype":"venue"
},
  "geometry": {"coordinates":[-122.29512,47.582909],"type":"Point"}
}