{
  "type": "Feature",
  "properties": {
    "addr:full":"1221 Madison Street Suite 1026 Seattle WA 98104",
    "addr:housenumber":"1221",
    "addr:postcode":"98104",
    "addr:street":"Madison Street Suite 1026",
    "iso:country":"US",
    "sg:address":"1221 Madison Street Suite 1026",
    "sg:city":"Seattle",
    "sg:classifiers":[
        {
            "category":"Health Services",
            "subcategory":"Doctor",
            "type":"Services"
        }
    ],
    "sg:phone":"+1 206 215 2243",
    "sg:postcode":"98104",
    "sg:province":"WA",
    "wof:name":"Lucas Sylvia M MD PHD",
    "wof:placetype":"venue"
},
  "geometry": {"coordinates":[-122.32387900000001,47.609982],"type":"Point"}
}