{
  "type": "Feature",
  "properties": {
    "addr:full":"12730 43rd Ave NE Marysville WA 98271",
    "addr:housenumber":"12730",
    "addr:postcode":"98271",
    "addr:street":"43Rd Ave Ne",
    "iso:country":"US",
    "sg:address":"12730 43rd Ave NE",
    "sg:city":"Marysville",
    "sg:classifiers":[
        {
            "category":"Manufacturing",
            "subcategory":"Printing",
            "type":"Manufacturing & Wholesale Goods"
        }
    ],
    "sg:phone":"+1 360 653 4169",
    "sg:postcode":"98271",
    "sg:province":"WA",
    "sg:tags":[
        "book"
    ],
    "wof:name":"Creative Horizons Publish",
    "wof:placetype":"venue"
},
  "geometry": {"coordinates":[-122.17340299999999,48.110902],"type":"Point"}
}