{
  "type": "Feature",
  "properties": {
    "addr:full":"906 7th Ave S Edmonds WA 98020",
    "addr:housenumber":"906",
    "addr:postcode":"98020",
    "addr:street":"7Th Ave S",
    "iso:country":"US",
    "sg:address":"906 7th Ave S",
    "sg:city":"Edmonds",
    "sg:classifiers":[
        {
            "category":"Building & Trades",
            "subcategory":"Construction",
            "type":"Services"
        }
    ],
    "sg:phone":"+1 425 776 1090",
    "sg:postcode":"98020",
    "sg:province":"WA",
    "sg:tags":[
        "house"
    ],
    "wof:name":"Torgerson Construction",
    "wof:placetype":"venue"
},
  "geometry": {"coordinates":[-122.37228,47.803308],"type":"Point"}
}