{
  "type": "Feature",
  "properties": {
    "addr:full":"9237 Rainier Ave Seattle WA 98118",
    "addr:housenumber":"9237",
    "addr:postcode":"98118",
    "addr:street":"Rainier Ave",
    "iso:country":"US",
    "sg:address":"9237 Rainier Ave",
    "sg:city":"Seattle",
    "sg:classifiers":[
        {
            "category":"Food & Beverages",
            "subcategory":"Groceries & Convenience Stores",
            "type":"Retail Goods"
        }
    ],
    "sg:phone":"+1 206 721 0640",
    "sg:postcode":"98118",
    "sg:province":"WA",
    "sg:tags":[
        "grocer"
    ],
    "wof:name":"Asia America Market",
    "wof:placetype":"venue"
},
  "geometry": {"coordinates":[-122.268874,47.519787],"type":"Point"}
}