{
  "type": "Feature",
  "properties": {
    "addr:full":"2401 4th Ave Seattle WA 98121",
    "addr:housenumber":"2401",
    "addr:postcode":"98121",
    "addr:street":"4Th Ave",
    "iso:country":"US",
    "sg:address":"2401 4th Ave",
    "sg:city":"Seattle",
    "sg:classifiers":[
        {
            "category":"Banks & Credit Unions",
            "subcategory":"Bank",
            "type":"Services"
        }
    ],
    "sg:phone":"+1 206 727 4295",
    "sg:postcode":"98121",
    "sg:province":"WA",
    "sg:tags":[
        "loan",
        "real estate"
    ],
    "wof:name":"Alaska USA Mortgage Co",
    "wof:placetype":"venue"
},
  "geometry": {"coordinates":[-122.34529499999999,47.616171],"type":"Point"}
}