{
  "type": "Feature",
  "properties": {
    "addr:full":"216 E Main St Walla Walla WA 99362",
    "addr:housenumber":"216",
    "addr:postcode":"99362",
    "addr:street":"E Main St",
    "iso:country":"US",
    "sg:address":"216 E Main St",
    "sg:city":"Walla Walla",
    "sg:classifiers":[
        {
            "category":"Food & Beverages",
            "subcategory":"Bakery",
            "type":"Retail Goods"
        }
    ],
    "sg:phone":"+1 509 529 3186",
    "sg:postcode":"99362",
    "sg:province":"WA",
    "wof:name":"Ze Bagel LLC",
    "wof:placetype":"venue"
},
  "geometry": {"coordinates":[-118.33559200000001,46.069427],"type":"Point"}
}