{
  "type": "Feature",
  "properties": {
    "addr:full":"2815 Wetmore Ave Everett WA 98201",
    "addr:housenumber":"2815",
    "addr:postcode":"98201",
    "addr:street":"Wetmore Ave",
    "iso:country":"US",
    "sg:address":"2815 Wetmore Ave",
    "sg:city":"Everett",
    "sg:classifiers":[
        {
            "category":"Shopping",
            "subcategory":"Clothing, Apparel, & Fashions",
            "type":"Retail Goods"
        }
    ],
    "sg:phone":"+1 425 303 9520",
    "sg:postcode":"98201",
    "sg:province":"WA",
    "sg:tags":[
        "product",
        "specialty"
    ],
    "wof:name":"Chinook",
    "wof:placetype":"venue"
},
  "geometry": {"coordinates":[-122.20712399999999,47.980018],"type":"Point"}
}