{
  "type": "Feature",
  "properties": {
    "iso:country":"US",
    "sg:address":"192 Rondale Dr",
    "sg:city":"Sequim",
    "sg:classifiers":[
        {
            "category":"Restaurant",
            "type":"Food & Drink"
        }
    ],
    "sg:phone":"+1 360 683 4962",
    "sg:postcode":"98382",
    "sg:province":"WA",
    "sg:tags":[
        "eating"
    ],
    "wof:name":"Candlelight & Roses",
    "wof:placetype":"venue"
},
  "geometry": {"coordinates":[-123.141797,48.071512],"type":"Point"}
}