{
  "type": "Feature",
  "properties": {
    "addr:full":"2623 SW 109th St Seattle WA 98146",
    "addr:housenumber":"2623",
    "addr:postcode":"98146",
    "addr:street":"Sw 109Th St",
    "iso:country":"US",
    "sg:address":"2623 SW 109th St",
    "sg:city":"Seattle",
    "sg:classifiers":[
        {
            "category":"Professional",
            "subcategory":"Management & Consulting",
            "type":"Services"
        }
    ],
    "sg:phone":"+1 206 243 9770",
    "sg:postcode":"98146",
    "sg:province":"WA",
    "sg:tags":[
        "counselor",
        "relation",
        "public"
    ],
    "wof:name":"Pate Julee A Daniels Pate",
    "wof:placetype":"venue"
},
  "geometry": {"coordinates":[-122.36664399999999,47.505497],"type":"Point"}
}