{
  "type": "Feature",
  "properties": {
    "addr:full":"1919 1st Ave Seattle WA 98101",
    "addr:housenumber":"1919",
    "addr:postcode":"98101",
    "addr:street":"1St Ave",
    "iso:country":"US",
    "sg:address":"1919 1st Ave",
    "sg:city":"Seattle",
    "sg:classifiers":[
        {
            "category":"Restaurant",
            "type":"Food & Drink"
        }
    ],
    "sg:phone":"+1 206 441 3354",
    "sg:postcode":"98101",
    "sg:province":"WA",
    "sg:tags":[
        "caterer"
    ],
    "wof:name":"Du Jour",
    "wof:placetype":"venue"
},
  "geometry": {"coordinates":[-122.342502,47.610868],"type":"Point"}
}