{
  "type": "Feature",
  "properties": {
    "addr:full":"25101 SE 208th St Maple Valley WA 98038",
    "addr:housenumber":"25101",
    "addr:postcode":"98038",
    "addr:street":"Se 208Th St",
    "iso:country":"US",
    "sg:address":"25101 SE 208th St",
    "sg:city":"Maple Valley",
    "sg:classifiers":[
        {
            "category":"Professional",
            "subcategory":"Business Services",
            "type":"Services"
        }
    ],
    "sg:phone":"+1 425 432 7925",
    "sg:postcode":"98038",
    "sg:province":"WA",
    "wof:name":"Nld Enterprises Inc",
    "wof:placetype":"venue"
},
  "geometry": {"coordinates":[-122.00867,47.415386],"type":"Point"}
}