{
  "type": "Feature",
  "properties": {
    "addr:full":"17725 NE 65th St Redmond WA 98052",
    "addr:housenumber":"17725",
    "addr:postcode":"98052",
    "addr:street":"Ne 65Th St",
    "iso:country":"US",
    "sg:address":"17725 NE 65th St",
    "sg:city":"Redmond",
    "sg:classifiers":[
        {
            "category":"Real Estate",
            "subcategory":"Real Estate Services",
            "type":"Services"
        }
    ],
    "sg:phone":"+1 425 861 8875",
    "sg:postcode":"98052",
    "sg:province":"WA",
    "sg:tags":[
        "rental"
    ],
    "wof:name":"Photobooth Services",
    "wof:placetype":"venue"
},
  "geometry": {"coordinates":[-122.100932,47.663941],"type":"Point"}
}