{
  "type": "Feature",
  "properties": {
    "addr:full":"160 Roy St Seattle WA 98109",
    "addr:housenumber":"160",
    "addr:postcode":"98109",
    "addr:street":"Roy St",
    "iso:country":"US",
    "sg:address":"160 Roy St",
    "sg:city":"Seattle",
    "sg:classifiers":[
        {
            "category":"Government",
            "subcategory":"Court House",
            "type":"Public Place"
        }
    ],
    "sg:phone":"+1 206 281 6854",
    "sg:postcode":"98109",
    "sg:province":"WA",
    "sg:tags":[
        "legislator"
    ],
    "wof:name":"Washington Senate",
    "wof:placetype":"venue"
},
  "geometry": {"coordinates":[-122.353836,47.625463],"type":"Point"}
}