{
  "type": "Feature",
  "properties": {
    "addr:full":"1027 Lawrence St Port Townsend WA 98368",
    "addr:housenumber":"1027",
    "addr:postcode":"98368",
    "addr:street":"Lawrence St",
    "iso:country":"US",
    "sg:address":"1027 Lawrence St",
    "sg:city":"Port Townsend",
    "sg:classifiers":[
        {
            "category":"Social Services",
            "type":"Services"
        }
    ],
    "sg:phone":"+1 360 643 0105",
    "sg:postcode":"98368",
    "sg:province":"WA",
    "sg:tags":[
        "counselor",
        "marriage",
        "family"
    ],
    "wof:name":"Judith Rothstein",
    "wof:placetype":"venue"
},
  "geometry": {"coordinates":[-122.76081600000001,48.117215],"type":"Point"}
}