{
  "type": "Feature",
  "properties": {
    "addr:full":"1111 102nd Ave NE Bellevue WA 98004",
    "addr:housenumber":"1111",
    "addr:postcode":"98004",
    "addr:street":"102Nd Ave Ne",
    "iso:country":"US",
    "sg:address":"1111 102nd Ave NE",
    "sg:city":"Bellevue",
    "sg:classifiers":[
        {
            "category":"Retail",
            "subcategory":"Repair Shop",
            "type":"Services"
        }
    ],
    "sg:phone":"+1 425 992 7770",
    "sg:postcode":"98004",
    "sg:province":"WA",
    "sg:tags":[
        "electrical"
    ],
    "wof:name":"My Sweeper",
    "wof:placetype":"venue"
},
  "geometry": {"coordinates":[-122.204441,47.619385],"type":"Point"}
}