{
  "type": "Feature",
  "properties": {
    "addr:full":"3002 W Illinois St Bellingham WA 98225",
    "addr:housenumber":"3002",
    "addr:postcode":"98225",
    "addr:street":"W Illinois St",
    "iso:country":"US",
    "sg:address":"3002 W Illinois St",
    "sg:city":"Bellingham",
    "sg:classifiers":[
        {
            "category":"Wholesale",
            "subcategory":"Metals & Minerals",
            "type":"Manufacturing & Wholesale Goods"
        }
    ],
    "sg:phone":"+1 360 756 6200",
    "sg:postcode":"98225",
    "sg:province":"WA",
    "sg:tags":[
        "steel",
        "warehouse"
    ],
    "wof:name":"Morse Steel Svc",
    "wof:placetype":"venue"
},
  "geometry": {"coordinates":[-122.509539,48.768163],"type":"Point"}
}