{
  "type": "Feature",
  "properties": {
    "addr:full":"204 E Stanley St Granite Falls WA 98252",
    "addr:housenumber":"204",
    "addr:postcode":"98252",
    "addr:street":"E Stanley St",
    "iso:country":"US",
    "sg:address":"204 E Stanley St",
    "sg:city":"Granite Falls",
    "sg:classifiers":[
        {
            "category":"Autos & Motor Vehicles",
            "subcategory":"Automobile Sales",
            "type":"Retail Goods"
        }
    ],
    "sg:phone":"+1 360 691 6911",
    "sg:postcode":"98252",
    "sg:province":"WA",
    "sg:tags":[
        "car",
        "dealer"
    ],
    "wof:name":"Mountain Loop Motor Cars",
    "wof:placetype":"venue"
},
  "geometry": {"coordinates":[-121.967383,48.083332],"type":"Point"}
}