{
  "type": "Feature",
  "properties": {
    "addr:full":"40 Glenn Rd N Montesano WA 98563",
    "addr:housenumber":"40",
    "addr:postcode":"98563",
    "addr:street":"Glenn Rd N Montesano",
    "iso:country":"US",
    "sg:address":"40 Glenn Rd N",
    "sg:city":"Montesano",
    "sg:classifiers":[
        {
            "category":"Building & Trades",
            "subcategory":"Construction",
            "type":"Services"
        }
    ],
    "sg:phone":"+1 360 249 2353",
    "sg:postcode":"98563",
    "sg:province":"WA",
    "sg:tags":[
        "contractor"
    ],
    "wof:name":"L & R Seal Coating",
    "wof:placetype":"venue"
},
  "geometry": {"coordinates":[-123.553932,46.98847],"type":"Point"}
}