{
  "type": "Feature",
  "properties": {
    "addr:full":"1120 N 3rd Ave Kelso WA 98626",
    "addr:housenumber":"1120",
    "addr:postcode":"98626",
    "addr:street":"N 3Rd Ave",
    "iso:country":"US",
    "sg:address":"1120 N 3rd Ave",
    "sg:city":"Kelso",
    "sg:classifiers":[
        {
            "category":"Place Of Worship",
            "subcategory":"Church",
            "type":"Public Place"
        },
        {
            "category":"Place Of Worship",
            "type":"Public Place"
        },
        {
            "category":"Organizations",
            "subcategory":"Religious Organization",
            "type":"Services"
        }
    ],
    "sg:phone":"+1 360 636 1214",
    "sg:postcode":"98626",
    "sg:province":"WA",
    "sg:tags":[
        "god",
        "churches-church",
        "churches-pentecostal"
    ],
    "wof:name":"Spirit Of Life Church Of God",
    "wof:placetype":"venue"
},
  "geometry": {"coordinates":[-122.907675,46.151964],"type":"Point"}
}