{
  "type": "Feature",
  "properties": {
    "addr:full":"408 39th Ave E Seattle WA 98112",
    "addr:housenumber":"408",
    "addr:postcode":"98112",
    "addr:street":"39Th Ave E",
    "iso:country":"US",
    "sg:address":"408 39th Ave E",
    "sg:city":"Seattle",
    "sg:classifiers":[
        {
            "category":"Banks & Credit Unions",
            "subcategory":"Financial Services",
            "type":"Services"
        }
    ],
    "sg:phone":"+1 206 325 1238",
    "sg:postcode":"98112",
    "sg:province":"WA",
    "sg:tags":[
        "investor"
    ],
    "wof:name":"Newsom Investments LLC",
    "wof:placetype":"venue"
},
  "geometry": {"coordinates":[-122.283091,47.623528],"type":"Point"}
}