{
  "type": "Feature",
  "properties": {
    "addr:full":"6918 N Crestline St Spokane WA 99217",
    "addr:housenumber":"6918",
    "addr:postcode":"99217",
    "addr:street":"N Crestline St",
    "iso:country":"US",
    "sg:address":"6918 N Crestline St",
    "sg:city":"Spokane",
    "sg:classifiers":[
        {
            "category":"Recreation",
            "type":"Entertainment"
        }
    ],
    "sg:phone":"+1 509 467 7446",
    "sg:postcode":"99217",
    "sg:province":"WA",
    "wof:name":"Maveric Jr Rodeo Association",
    "wof:placetype":"venue"
},
  "geometry": {"coordinates":[-117.378794,47.71992],"type":"Point"}
}