{
  "type": "Feature",
  "properties": {
    "addr:full":"2106 SE 160th Pl Vancouver WA 98683",
    "addr:housenumber":"2106",
    "addr:postcode":"98683",
    "addr:street":"Se 160Th Pl",
    "iso:country":"US",
    "sg:address":"2106 SE 160th Pl",
    "sg:city":"Vancouver",
    "sg:classifiers":[
        {
            "category":"Real Estate",
            "subcategory":"Real Estate Agent",
            "type":"Services"
        }
    ],
    "sg:phone":"+1 360 254 3799",
    "sg:postcode":"98683",
    "sg:province":"WA",
    "wof:name":"Petrie Ron Appraisals",
    "wof:placetype":"venue"
},
  "geometry": {"coordinates":[-122.507993,45.605943],"type":"Point"}
}