{
  "type": "Feature",
  "properties": {
    "iso:country":"US",
    "sg:address":"321 Parish Rd",
    "sg:city":"Selah",
    "sg:classifiers":[
        {
            "category":"Building & Trades",
            "subcategory":"Landscaping Services",
            "type":"Services"
        }
    ],
    "sg:phone":"+1 509 698 3724",
    "sg:postcode":"98942",
    "sg:province":"WA",
    "wof:name":"Growmaster",
    "wof:placetype":"venue"
},
  "geometry": {"coordinates":[-120.57670899999999,46.694828],"type":"Point"}
}