{
  "type": "Feature",
  "properties": {
    "addr:full":"530 Dexter Avenue N Seattle WA 98109",
    "addr:housenumber":"530",
    "addr:postcode":"98109",
    "addr:street":"Dexter Avenue N",
    "iso:country":"US",
    "sg:address":"530 Dexter Avenue N",
    "sg:city":"Seattle",
    "sg:classifiers":[
        {
            "category":"Organizations",
            "subcategory":"Non-profit Organization",
            "type":"Services"
        }
    ],
    "sg:phone":"+1 206 749 4089",
    "sg:postcode":"98109",
    "sg:province":"WA",
    "sg:tags":[
        "service/non-profit",
        "community"
    ],
    "wof:name":"The Leukemia & Lymphoma Society",
    "wof:placetype":"venue"
},
  "geometry": {"coordinates":[-122.342387,47.623541],"type":"Point"}
}