{
  "type": "Feature",
  "properties": {
    "addr:full":"2483 Birch Ave N Seattle WA 98109",
    "addr:housenumber":"2483",
    "addr:postcode":"98109",
    "addr:street":"Birch Ave N",
    "iso:country":"US",
    "sg:address":"2483 Birch Ave N",
    "sg:city":"Seattle",
    "sg:classifiers":[
        {
            "category":"Real Estate",
            "subcategory":"Real Estate Services",
            "type":"Services"
        }
    ],
    "sg:phone":"+1 206 352 0200",
    "sg:postcode":"98109",
    "sg:province":"WA",
    "sg:website":"www.domaineseattle.com/",
    "wof:name":"Domaine",
    "wof:placetype":"venue"
},
  "geometry": {"coordinates":[-122.34655600000001,47.642046],"type":"Point"}
}