{
  "type": "Feature",
  "properties": {
    "addr:full":"5005 3rd Ave S Seattle WA 98134",
    "addr:housenumber":"5005",
    "addr:postcode":"98134",
    "addr:street":"3Rd Ave S",
    "iso:country":"US",
    "sg:address":"5005 3rd Ave S",
    "sg:city":"Seattle",
    "sg:classifiers":[
        {
            "category":"Personal",
            "type":"Services"
        },
        {
            "category":"Real Estate",
            "subcategory":"Architect",
            "type":"Services"
        }
    ],
    "sg:phone":"+1 206 762 3311",
    "sg:postcode":"98134",
    "sg:province":"WA",
    "sg:tags":[
        "local"
    ],
    "wof:name":"McKinstry Company",
    "wof:placetype":"venue"
},
  "geometry": {"coordinates":[-122.33093700000001,47.557399],"type":"Point"}
}