{
  "type": "Feature",
  "properties": {
    "addr:full":"14021 NE 8th St Bellevue WA 98007",
    "addr:housenumber":"14021",
    "addr:postcode":"98007",
    "addr:street":"Ne 8Th St",
    "iso:country":"US",
    "sg:address":"14021 NE 8th St",
    "sg:city":"Bellevue",
    "sg:classifiers":[
        {
            "category":"Professional",
            "subcategory":"Accounting & Tax Preparation",
            "type":"Services"
        }
    ],
    "sg:phone":"+1 425 746 2950",
    "sg:postcode":"98007",
    "sg:province":"WA",
    "sg:tags":[
        "accountant",
        "keeping"
    ],
    "wof:name":"Better Bottom Line",
    "wof:placetype":"venue"
},
  "geometry": {"coordinates":[-122.152242,47.617064],"type":"Point"}
}