{
  "type": "Feature",
  "properties": {
    "addr:full":"4425 Ocean Beach Hwy Longview WA 98632",
    "addr:housenumber":"4425",
    "addr:postcode":"98632",
    "addr:street":"Ocean Beach Hwy",
    "iso:country":"US",
    "sg:address":"4425 Ocean Beach Hwy",
    "sg:city":"Longview",
    "sg:classifiers":[
        {
            "category":"Manufacturing",
            "subcategory":"Tools & Machinery",
            "type":"Manufacturing & Wholesale Goods"
        }
    ],
    "sg:phone":"+1 360 636 1967",
    "sg:postcode":"98632",
    "sg:province":"WA",
    "sg:tags":[
        "construction",
        "mfg"
    ],
    "wof:name":"Ryans Tractor",
    "wof:placetype":"venue"
},
  "geometry": {"coordinates":[-122.99827000000001,46.162749],"type":"Point"}
}