{
  "type": "Feature",
  "properties": {
    "addr:full":"119 W Main Ave Ritzville WA 99169",
    "addr:housenumber":"119",
    "addr:postcode":"99169",
    "addr:street":"W Main Ave",
    "iso:country":"US",
    "sg:address":"119 W Main Ave",
    "sg:city":"Ritzville",
    "sg:classifiers":[
        {
            "category":"Bars & Pubs",
            "type":"Food & Drink"
        }
    ],
    "sg:phone":"+1 509 659 0222",
    "sg:postcode":"99169",
    "sg:province":"WA",
    "wof:name":"Pastime",
    "wof:placetype":"venue"
},
  "geometry": {"coordinates":[-118.38002299999999,47.127365],"type":"Point"}
}