{
  "type": "Feature",
  "properties": {
    "addr:full":"555 NE Northgate Way Seattle WA 98125",
    "addr:housenumber":"555",
    "addr:postcode":"98125",
    "addr:street":"Ne Northgate Way",
    "iso:country":"US",
    "sg:address":"555 NE Northgate Way",
    "sg:city":"Seattle",
    "sg:classifiers":[
        {
            "category":"Restaurant",
            "type":"Food & Drink"
        }
    ],
    "sg:menulink":"http://www.allmenus.com/wa/seattle/9037-red-robin/menu/",
    "sg:phone":"+1 206 365 0933",
    "sg:postcode":"98125",
    "sg:province":"WA",
    "sg:tags":[
        "american"
    ],
    "wof:name":"Red Robin",
    "wof:placetype":"venue"
},
  "geometry": {"coordinates":[-122.322749,47.708565],"type":"Point"}
}