{
  "type": "Feature",
  "properties": {
    "addr:full":"11400 SE 6th St Bellevue WA 98004",
    "addr:postcode":"11400;98004",
    "addr:street":"Se 6Th St",
    "iso:country":"US",
    "sg:address":"11400 SE 6th St",
    "sg:city":"Bellevue",
    "sg:classifiers":[
        {
            "category":"Banks & Credit Unions",
            "subcategory":"Financial Services",
            "type":"Services"
        }
    ],
    "sg:phone":"+1 425 453 4590",
    "sg:postcode":"98004",
    "sg:province":"WA",
    "sg:tags":[
        "management",
        "asset",
        "venture",
        "capital"
    ],
    "wof:name":"F C M",
    "wof:placetype":"venue"
},
  "geometry": {"coordinates":[-122.18957899999999,47.604653],"type":"Point"}
}