{
  "type": "Feature",
  "properties": {
    "addr:full":"26394 NW Edgewater Blvd Poulsbo WA 98370",
    "addr:housenumber":"26394",
    "addr:postcode":"98370",
    "addr:street":"Nw Edgewater Blvd",
    "iso:country":"US",
    "sg:address":"26394 NW Edgewater Blvd",
    "sg:city":"Poulsbo",
    "sg:classifiers":[
        {
            "category":"Personal",
            "subcategory":"Beauty Salon",
            "type":"Services"
        }
    ],
    "sg:phone":"+1 360 779 7071",
    "sg:postcode":"98370",
    "sg:province":"WA",
    "sg:tags":[
        "shop"
    ],
    "wof:name":"Linda's Hair Cupboard",
    "wof:placetype":"venue"
},
  "geometry": {"coordinates":[-122.663768,47.801078],"type":"Point"}
}