{
  "type": "Feature",
  "properties": {
    "addr:full":"12513 NE 144th St Kirkland WA 98034",
    "addr:housenumber":"12513",
    "addr:postcode":"98034",
    "addr:street":"Ne 144Th St",
    "iso:country":"US",
    "sg:address":"12513 NE 144th St",
    "sg:city":"Kirkland",
    "sg:classifiers":[
        {
            "category":"Retail",
            "subcategory":"Self-service Laundry",
            "type":"Services"
        }
    ],
    "sg:phone":"+1 425 820 0341",
    "sg:postcode":"98034",
    "sg:province":"WA",
    "sg:tags":[
        "operated",
        "washer",
        "coin",
        "dryer"
    ],
    "sg:website":"http://www.maytagseattle.com",
    "wof:name":"Eastside Maytag Laundry",
    "wof:placetype":"venue"
},
  "geometry": {"coordinates":[-122.17396100000001,47.731281],"type":"Point"}
}