{
  "type": "Feature",
  "properties": {
    "addr:full":"4121 N 18th St Tacoma WA 98406",
    "addr:housenumber":"4121",
    "addr:postcode":"98406",
    "addr:street":"N 18Th St",
    "iso:country":"US",
    "sg:address":"4121 N 18th St",
    "sg:city":"Tacoma",
    "sg:classifiers":[
        {
            "category":"Social Services",
            "subcategory":"Child Care",
            "type":"Services"
        }
    ],
    "sg:phone":"+1 253 759 0914",
    "sg:postcode":"98406",
    "sg:province":"WA",
    "sg:tags":[
        "day"
    ],
    "wof:name":"C Campanoli",
    "wof:placetype":"venue"
},
  "geometry": {"coordinates":[-122.492937,47.265552],"type":"Point"}
}