{
  "type": "Feature",
  "properties": {
    "addr:full":"785 Tumbleweed Ln Burbank WA 99323",
    "addr:housenumber":"785",
    "addr:postcode":"99323",
    "addr:street":"Tumbleweed Ln",
    "iso:country":"US",
    "sg:address":"785 Tumbleweed Ln",
    "sg:city":"Burbank",
    "sg:classifiers":[
        {
            "category":"Building & Trades",
            "subcategory":"Plumbing",
            "type":"Services"
        }
    ],
    "sg:phone":"+1 509 588 5295",
    "sg:postcode":"99323",
    "sg:province":"WA",
    "sg:tags":[
        "contractor"
    ],
    "wof:name":"AAA Drilling Co",
    "wof:placetype":"venue"
},
  "geometry": {"coordinates":[-118.889298,46.234876],"type":"Point"}
}