{
  "type": "Feature",
  "properties": {
    "addr:full":"1420 Kope Rd Bellingham WA 98226",
    "addr:housenumber":"1420",
    "addr:postcode":"98226",
    "addr:street":"Kope Rd",
    "iso:country":"US",
    "sg:address":"1420 Kope Rd",
    "sg:city":"Bellingham",
    "sg:classifiers":[
        {
            "category":"Manufacturing",
            "subcategory":"Lumber",
            "type":"Manufacturing & Wholesale Goods"
        }
    ],
    "sg:phone":"+1 360 384 4628",
    "sg:postcode":"98226",
    "sg:province":"WA",
    "sg:tags":[
        "timberland",
        "operation",
        "timber",
        "tract"
    ],
    "wof:name":"Pheifer Timbercutting Inc",
    "wof:placetype":"venue"
},
  "geometry": {"coordinates":[-122.55693100000001,48.816937],"type":"Point"}
}