{
  "type": "Feature",
  "properties": {
    "addr:full":"113 Avenue A Snohomish WA 98290",
    "addr:housenumber":"113",
    "addr:postcode":"98290",
    "addr:street":"Avenue A Snohomish",
    "iso:country":"US",
    "sg:address":"113 Avenue A",
    "sg:city":"Snohomish",
    "sg:classifiers":[
        {
            "category":"Personal",
            "subcategory":"Beauty Salon",
            "type":"Services"
        }
    ],
    "sg:phone":"+1 425 334 1177",
    "sg:postcode":"98290",
    "sg:province":"WA",
    "wof:name":"Salon Solo",
    "wof:placetype":"venue"
},
  "geometry": {"coordinates":[-122.094488,47.911539],"type":"Point"}
}