{
  "type": "Feature",
  "properties": {
    "addr:full":"11717 25th Ave NE Seattle WA 98125",
    "addr:housenumber":"11717",
    "addr:postcode":"98125",
    "addr:street":"25Th Ave Ne",
    "iso:country":"US",
    "sg:address":"11717 25th Ave NE",
    "sg:city":"Seattle",
    "sg:classifiers":[
        {
            "category":"Professional",
            "subcategory":"Management & Consulting",
            "type":"Services"
        }
    ],
    "sg:phone":"+1 206 365 7899",
    "sg:postcode":"98125",
    "sg:province":"WA",
    "sg:tags":[
        "business"
    ],
    "wof:name":"R W Cook Associates",
    "wof:placetype":"venue"
},
  "geometry": {"coordinates":[-122.30188,47.715591],"type":"Point"}
}