{
  "type": "Feature",
  "properties": {
    "addr:full":"2207 6th Ave Tacoma WA 98403",
    "addr:housenumber":"2207",
    "addr:postcode":"98403",
    "addr:street":"6Th Ave",
    "iso:country":"US",
    "sg:address":"2207 6th Ave",
    "sg:city":"Tacoma",
    "sg:classifiers":[
        {
            "category":"Place Of Worship",
            "subcategory":"Church",
            "type":"Public Place"
        },
        {
            "category":"Recreation",
            "type":"Entertainment"
        }
    ],
    "sg:phone":"+1 253 627 4526",
    "sg:postcode":"98403",
    "sg:province":"WA",
    "sg:tags":[
        "ceremony",
        "chapel",
        "marriage",
        "wedding"
    ],
    "wof:name":"Celebrations Ceremonies By Chi",
    "wof:placetype":"venue"
},
  "geometry": {"coordinates":[-122.46610699999999,47.255429],"type":"Point"}
}