{
  "type": "Feature",
  "properties": {
    "addr:full":"22207 NE 109th St Vancouver WA 98682",
    "addr:housenumber":"22207",
    "addr:postcode":"98682",
    "addr:street":"Ne 109Th St",
    "iso:country":"US",
    "sg:address":"22207 NE 109th St",
    "sg:city":"Vancouver",
    "sg:classifiers":[
        {
            "category":"Building & Trades",
            "subcategory":"Plumbing",
            "type":"Services"
        }
    ],
    "sg:phone":"+1 360 892 6121",
    "sg:postcode":"98682",
    "sg:province":"WA",
    "sg:tags":[
        "plumber",
        "industrial",
        "contractors-commercial"
    ],
    "wof:name":"Seekins Plumbing",
    "wof:placetype":"venue"
},
  "geometry": {"coordinates":[-122.445049,45.70125],"type":"Point"}
}