{
  "type": "Feature",
  "properties": {
    "addr:full":"2809 NE 55th St Seattle WA 98105",
    "addr:housenumber":"2809",
    "addr:postcode":"98105",
    "addr:street":"Ne 55Th St",
    "iso:country":"US",
    "sg:address":"2809 NE 55th St",
    "sg:city":"Seattle",
    "sg:classifiers":[
        {
            "category":"Shopping",
            "subcategory":"Beauty & Cosmetics",
            "type":"Retail Goods"
        }
    ],
    "sg:phone":"+1 206 729 7546",
    "sg:postcode":"98105",
    "sg:province":"WA",
    "sg:tags":[
        "supply"
    ],
    "sg:website":"www.sweetbeautyspa.com/",
    "wof:name":"Sweet Beauty Organic Chocolate Spa",
    "wof:placetype":"venue"
},
  "geometry": {"coordinates":[-122.297141,47.668534],"type":"Point"}
}