{
  "type": "Feature",
  "properties": {
    "addr:full":"201 S Dawes St Kennewick WA 99336",
    "addr:housenumber":"201",
    "addr:postcode":"99336",
    "addr:street":"S Dawes St",
    "iso:country":"US",
    "sg:address":"201 S Dawes St",
    "sg:city":"Kennewick",
    "sg:classifiers":[
        {
            "category":"Education",
            "subcategory":"School",
            "type":"Public Place"
        }
    ],
    "sg:phone":"+1 509 734 3580",
    "sg:postcode":"99336",
    "sg:province":"WA",
    "wof:name":"Edison Elementary School",
    "wof:placetype":"venue"
},
  "geometry": {"coordinates":[-119.190699,46.207789],"type":"Point"}
}