{
  "type": "Feature",
  "properties": {
    "addr:full":"14224 Frans Dr Stanwood WA 98292",
    "addr:postcode":"14224;98292",
    "addr:street":"Frans Dr",
    "iso:country":"US",
    "sg:address":"14224 Frans Dr",
    "sg:city":"Stanwood",
    "sg:classifiers":[
        {
            "category":"Wholesale",
            "subcategory":"Apparel",
            "type":"Manufacturing & Wholesale Goods"
        }
    ],
    "sg:phone":"+1 360 652 7845",
    "sg:postcode":"98292",
    "sg:province":"WA",
    "sg:tags":[
        "footwear"
    ],
    "wof:name":"Justin Boot Co",
    "wof:placetype":"venue"
},
  "geometry": {"coordinates":[-122.364026,48.126792],"type":"Point"}
}