{
  "type": "Feature",
  "properties": {
    "addr:full":"13326 17th Ave NE Seattle WA 98125",
    "addr:housenumber":"13326",
    "addr:postcode":"98125",
    "addr:street":"17Th Ave Ne",
    "iso:country":"US",
    "sg:address":"13326 17th Ave NE",
    "sg:city":"Seattle",
    "sg:classifiers":[
        {
            "category":"Shopping",
            "type":"Retail Goods"
        }
    ],
    "sg:phone":"+1 206 366 8324",
    "sg:postcode":"98125",
    "sg:province":"WA",
    "sg:tags":[
        "product"
    ],
    "wof:name":"Enviroganics International",
    "wof:placetype":"venue"
},
  "geometry": {"coordinates":[-122.310793,47.725375],"type":"Point"}
}