{
  "type": "Feature",
  "properties": {
    "addr:full":"14820 Redmond Way Redmond WA 98052",
    "addr:housenumber":"14820",
    "addr:postcode":"98052",
    "addr:street":"Redmond Way",
    "iso:country":"US",
    "sg:address":"14820 Redmond Way",
    "sg:city":"Redmond",
    "sg:classifiers":[
        {
            "category":"Professional",
            "subcategory":"Computer Services",
            "type":"Services"
        }
    ],
    "sg:phone":"+1 206 948 2640",
    "sg:postcode":"98052",
    "sg:province":"WA",
    "sg:tags":[
        "related"
    ],
    "wof:name":"Accelera Technologies LLC",
    "wof:placetype":"venue"
},
  "geometry": {"coordinates":[-122.14140399999999,47.6752],"type":"Point"}
}