{
  "type": "Feature",
  "properties": {
    "addr:full":"121 Maple Ln Mineral WA 98355",
    "addr:housenumber":"121",
    "addr:postcode":"98355",
    "addr:street":"Maple Ln",
    "iso:country":"US",
    "sg:address":"121 Maple Ln",
    "sg:city":"Mineral",
    "sg:classifiers":[
        {
            "category":"Wholesale",
            "subcategory":"Machinery & Supplies",
            "type":"Manufacturing & Wholesale Goods"
        }
    ],
    "sg:phone":"+1 360 492 3100",
    "sg:postcode":"98355",
    "sg:province":"WA",
    "sg:tags":[
        "gasket"
    ],
    "wof:name":"Rembos Hi-Pro",
    "wof:placetype":"venue"
},
  "geometry": {"coordinates":[-122.182456,46.716849],"type":"Point"}
}