{
  "type": "Feature",
  "properties": {
    "addr:full":"1017 Tacoma Ave Sunnyside WA 98944",
    "addr:housenumber":"1017",
    "addr:postcode":"98944",
    "addr:street":"Tacoma Ave",
    "iso:country":"US",
    "sg:address":"1017 Tacoma Ave",
    "sg:city":"Sunnyside",
    "sg:classifiers":[
        {
            "category":"Health Services",
            "subcategory":"Doctor",
            "type":"Services"
        }
    ],
    "sg:phone":"+1 509 837 5611",
    "sg:postcode":"98944",
    "sg:province":"WA",
    "sg:tags":[
        "physician",
        "surgeon"
    ],
    "wof:name":"Surgeon's Office",
    "wof:placetype":"venue"
},
  "geometry": {"coordinates":[-120.00718000000001,46.322276],"type":"Point"}
}