{
  "type": "Feature",
  "properties": {
    "iso:country":"US",
    "sg:address":"1119 Easy St",
    "sg:city":"Wenatchee",
    "sg:classifiers":[
        {
            "category":"Professional",
            "subcategory":"Accounting & Tax Preparation",
            "type":"Services"
        }
    ],
    "sg:phone":"+1 509 662 6953",
    "sg:postcode":"98801",
    "sg:province":"WA",
    "wof:name":"Numbers",
    "wof:placetype":"venue"
},
  "geometry": {"coordinates":[-120.36988700000001,47.476957],"type":"Point"}
}