{
  "type": "Feature",
  "properties": {
    "addr:full":"815 117th St S Tacoma WA 98444",
    "addr:housenumber":"815",
    "addr:postcode":"98444",
    "addr:street":"117Th St S",
    "iso:country":"US",
    "sg:address":"815 117th St S",
    "sg:city":"Tacoma",
    "sg:classifiers":[
        {
            "category":"Arts & Performance",
            "subcategory":"Theater",
            "type":"Entertainment"
        }
    ],
    "sg:phone":"+1 206 696 2877",
    "sg:postcode":"98444",
    "sg:province":"WA",
    "sg:tags":[
        "entertainer"
    ],
    "wof:name":"Midnight Passions",
    "wof:placetype":"venue"
},
  "geometry": {"coordinates":[-122.443776,47.150569],"type":"Point"}
}