{
  "type": "Feature",
  "properties": {
    "addr:full":"840 Ocean Beach Hwy Longview WA 98632",
    "addr:housenumber":"840",
    "addr:postcode":"98632",
    "addr:street":"Ocean Beach Hwy",
    "iso:country":"US",
    "sg:address":"840 Ocean Beach Hwy",
    "sg:city":"Longview",
    "sg:classifiers":[
        {
            "category":"Shopping",
            "subcategory":"Crafts & Fabrics",
            "type":"Retail Goods"
        }
    ],
    "sg:phone":"+1 360 423 8530",
    "sg:postcode":"98632",
    "sg:province":"WA",
    "sg:tags":[
        "sewing",
        "supply"
    ],
    "sg:website":"www.joann.com",
    "wof:name":"Jo-Ann Fabrics & Crafts",
    "wof:placetype":"venue"
},
  "geometry": {"coordinates":[-122.92383599999999,46.146187],"type":"Point"}
}