{
  "type": "Feature",
  "properties": {
    "addr:full":"22515 N Elk Chattaroy Rd Colbert WA 99005",
    "addr:housenumber":"22515",
    "addr:postcode":"99005",
    "addr:street":"N Elk Chattaroy Rd Colbert",
    "iso:country":"US",
    "sg:address":"22515 N Elk Chattaroy Rd",
    "sg:city":"Colbert",
    "sg:classifiers":[
        {
            "category":"Building & Trades",
            "subcategory":"Construction",
            "type":"Services"
        }
    ],
    "sg:phone":"+1 509 238 6607",
    "sg:postcode":"99005",
    "sg:province":"WA",
    "sg:tags":[
        "heavy"
    ],
    "wof:name":"Spokane County Utilities",
    "wof:placetype":"venue"
},
  "geometry": {"coordinates":[-117.34684799999999,47.86302],"type":"Point"}
}