{
  "type": "Feature",
  "properties": {
    "iso:country":"US",
    "sg:address":"12561 116th Ave NE",
    "sg:city":"Kirkland",
    "sg:classifiers":[
        {
            "category":"Real Estate",
            "subcategory":"Real Estate Agent",
            "type":"Services"
        }
    ],
    "sg:phone":"+1 425 821 3535",
    "sg:postcode":"98034",
    "sg:province":"WA",
    "wof:name":"Dream Realty & Mortgage",
    "wof:placetype":"venue"
},
  "geometry": {"coordinates":[-122.186607,47.711504],"type":"Point"}
}