{
  "type": "Feature",
  "properties": {
    "addr:full":"1616 Cornwall Ave Bellingham WA 98225",
    "addr:housenumber":"1616",
    "addr:postcode":"98225",
    "addr:street":"Cornwall Ave",
    "iso:country":"US",
    "sg:address":"1616 Cornwall Ave",
    "sg:city":"Bellingham",
    "sg:classifiers":[
        {
            "category":"Government",
            "subcategory":"Office",
            "type":"Public Place"
        }
    ],
    "sg:phone":"+1 360 676 2165",
    "sg:postcode":"98225",
    "sg:province":"WA",
    "sg:tags":[
        "policy"
    ],
    "wof:name":"Local Government Audit Teams",
    "wof:placetype":"venue"
},
  "geometry": {"coordinates":[-122.475246,48.752756],"type":"Point"}
}