{
  "type": "Feature",
  "properties": {
    "addr:full":"12026 NE 85th St Kirkland WA 98033",
    "addr:housenumber":"12026",
    "addr:postcode":"98033",
    "addr:street":"Ne 85Th St",
    "iso:country":"US",
    "sg:address":"12026 NE 85th St",
    "sg:city":"Kirkland",
    "sg:classifiers":[
        {
            "category":"Restaurant",
            "type":"Food & Drink"
        }
    ],
    "sg:phone":"+1 425 827 5252",
    "sg:postcode":"98033",
    "sg:province":"WA",
    "sg:tags":[
        "pizza"
    ],
    "sg:website":"www.pizzahut.com",
    "wof:name":"Pizza Hut",
    "wof:placetype":"venue"
},
  "geometry": {"coordinates":[-122.18000000000001,47.6791],"type":"Point"}
}