{
  "type": "Feature",
  "properties": {
    "addr:full":"5629 E Broadway Ave Spokane Valley WA 99212",
    "addr:housenumber":"5629",
    "addr:postcode":"99212",
    "addr:street":"E Broadway Ave",
    "iso:country":"US",
    "sg:address":"5629 E Broadway Ave",
    "sg:city":"Spokane Valley",
    "sg:classifiers":[
        {
            "category":"Wholesale",
            "subcategory":"Electrical",
            "type":"Manufacturing & Wholesale Goods"
        }
    ],
    "sg:phone":"+1 509 536 8787",
    "sg:postcode":"99212",
    "sg:province":"WA",
    "sg:tags":[
        "electric",
        "motor"
    ],
    "wof:name":"Dykman Electrical Inc",
    "wof:placetype":"venue"
},
  "geometry": {"coordinates":[-117.326182,47.664422],"type":"Point"}
}