{
  "type": "Feature",
  "properties": {
    "addr:full":"970 S Clark Ave Republic WA 99166",
    "addr:housenumber":"970",
    "addr:postcode":"99166",
    "addr:street":"S Clark Ave",
    "iso:country":"US",
    "sg:address":"970 S Clark Ave",
    "sg:city":"Republic",
    "sg:classifiers":[
        {
            "category":"Education",
            "subcategory":"College",
            "type":"Public Place"
        }
    ],
    "sg:phone":"+1 509 775 3675",
    "sg:postcode":"99166",
    "sg:province":"WA",
    "sg:tags":[
        "academic",
        "school"
    ],
    "wof:name":"Community College Ctr",
    "wof:placetype":"venue"
},
  "geometry": {"coordinates":[-118.73687099999999,48.642657],"type":"Point"}
}