{
  "type": "Feature",
  "properties": {
    "addr:full":"716 3rd Ave SE Quincy WA 98848",
    "addr:housenumber":"716",
    "addr:postcode":"98848",
    "addr:street":"3Rd Ave Se",
    "iso:country":"US",
    "sg:address":"716 3rd Ave SE",
    "sg:city":"Quincy",
    "sg:classifiers":[
        {
            "category":"Organizations",
            "subcategory":"Religious Organization",
            "type":"Services"
        }
    ],
    "sg:phone":"+1 509 787 2824",
    "sg:postcode":"98848",
    "sg:province":"WA",
    "sg:tags":[
        "churches-lutheran"
    ],
    "wof:name":"St Paul Lutheran Church Inc",
    "wof:placetype":"venue"
},
  "geometry": {"coordinates":[-119.84818300000001,47.232824],"type":"Point"}
}