{
  "type": "Feature",
  "properties": {
    "addr:full":"1530 15th Ave Longview WA 98632",
    "addr:housenumber":"1530",
    "addr:postcode":"98632",
    "addr:street":"15Th Ave",
    "iso:country":"US",
    "sg:address":"1530 15th Ave",
    "sg:city":"Longview",
    "sg:classifiers":[
        {
            "category":"Restaurant",
            "type":"Food & Drink"
        }
    ],
    "sg:phone":"+1 360 577 4247",
    "sg:postcode":"98632",
    "sg:province":"WA",
    "sg:tags":[
        "eating"
    ],
    "wof:name":"Jitters Inc",
    "wof:placetype":"venue"
},
  "geometry": {"coordinates":[-122.935076,46.142213],"type":"Point"}
}