{
  "type": "Feature",
  "properties": {
    "addr:full":"33422 192nd Ave SE Auburn WA 98092",
    "addr:housenumber":"33422",
    "addr:postcode":"98092",
    "addr:street":"192Nd Ave Se",
    "iso:country":"US",
    "sg:address":"33422 192nd Ave SE",
    "sg:city":"Auburn",
    "sg:classifiers":[
        {
            "category":"Real Estate",
            "subcategory":"Real Estate Operator",
            "type":"Services"
        }
    ],
    "sg:phone":"+1 253 833 9407",
    "sg:postcode":"98092",
    "sg:province":"WA",
    "sg:tags":[
        "mobile",
        "home",
        "site"
    ],
    "wof:name":"Park Places Estates",
    "wof:placetype":"venue"
},
  "geometry": {"coordinates":[-122.086422,47.301606],"type":"Point"}
}