{
  "type": "Feature",
  "properties": {
    "iso:country":"US",
    "sg:address":"23830 Hwy 99",
    "sg:city":"Edmonds",
    "sg:classifiers":[
        {
            "category":"Social Services",
            "type":"Services"
        }
    ],
    "sg:phone":"+1 425 697 5642",
    "sg:postcode":"98026",
    "sg:province":"WA",
    "sg:tags":[
        "counseling"
    ],
    "wof:name":"Korean Community Counseling",
    "wof:placetype":"venue"
},
  "geometry": {"coordinates":[-122.344989,47.781445],"type":"Point"}
}