{
  "type": "Feature",
  "properties": {
    "addr:full":"34 S A St Washougal WA 98671",
    "addr:housenumber":"34",
    "addr:postcode":"98671",
    "addr:street":"S A St",
    "iso:country":"US",
    "sg:address":"34 S A St",
    "sg:city":"Washougal",
    "sg:classifiers":[
        {
            "category":"Recreation",
            "type":"Entertainment"
        }
    ],
    "sg:phone":"+1 360 835 3119",
    "sg:postcode":"98671",
    "sg:province":"WA",
    "sg:tags":[
        "club",
        "membership"
    ],
    "wof:name":"Dolphin Yacht Club",
    "wof:placetype":"venue"
},
  "geometry": {"coordinates":[-122.380394,45.578944],"type":"Point"}
}