{
  "type": "Feature",
  "properties": {
    "addr:full":"26730 191st Pl SE Kent WA 98042",
    "addr:housenumber":"26730",
    "addr:postcode":"98042",
    "addr:street":"191St Pl Se",
    "iso:country":"US",
    "sg:address":"26730 191st Pl SE",
    "sg:city":"Kent",
    "sg:classifiers":[
        {
            "category":"Travel",
            "subcategory":"Hotels & Motels",
            "type":"Entertainment"
        }
    ],
    "sg:phone":"+1 253 638 9800",
    "sg:postcode":"98042",
    "sg:province":"WA",
    "sg:tags":[
        "operation"
    ],
    "wof:name":"Xinn Development Corp",
    "wof:placetype":"venue"
},
  "geometry": {"coordinates":[-122.08600199999999,47.361965],"type":"Point"}
}