{
  "type": "Feature",
  "properties": {
    "addr:full":"2315 Fir Ct Milton WA 98354",
    "addr:housenumber":"2315",
    "addr:postcode":"98354",
    "addr:street":"Fir Ct",
    "iso:country":"US",
    "sg:address":"2315 Fir Ct",
    "sg:city":"Milton",
    "sg:classifiers":[
        {
            "category":"Manufacturing",
            "subcategory":"Apparel",
            "type":"Manufacturing & Wholesale Goods"
        }
    ],
    "sg:phone":"+1 253 686 0299",
    "sg:postcode":"98354",
    "sg:province":"WA",
    "sg:tags":[
        "leather",
        "clothing",
        "mfg"
    ],
    "wof:name":"Bikermayhem",
    "wof:placetype":"venue"
},
  "geometry": {"coordinates":[-122.302871,47.253122],"type":"Point"}
}