{
  "type": "Feature",
  "properties": {
    "iso:country":"US",
    "sg:address":"2855 103rd Ave SE",
    "sg:city":"Bellevue",
    "sg:classifiers":[
        {
            "category":"Professional",
            "subcategory":"Management & Consulting",
            "type":"Services"
        }
    ],
    "sg:phone":"+1 425 454 2573",
    "sg:postcode":"98004",
    "sg:province":"WA",
    "wof:name":"Karen Scott Consulting Srvices",
    "wof:placetype":"venue"
},
  "geometry": {"coordinates":[-122.2033,47.584762],"type":"Point"}
}