{
  "type": "Feature",
  "properties": {
    "addr:full":"400 E Columbia Dr Kennewick WA 99336",
    "addr:housenumber":"400",
    "addr:postcode":"99336",
    "addr:street":"E Columbia Dr",
    "iso:country":"US",
    "sg:address":"400 E Columbia Dr",
    "sg:city":"Kennewick",
    "sg:classifiers":[
        {
            "category":"Fast Food",
            "type":"Food & Drink"
        },
        {
            "category":"Restaurant",
            "type":"Food & Drink"
        }
    ],
    "sg:phone":"+1 509 586 7591",
    "sg:postcode":"99336",
    "sg:province":"WA",
    "sg:tags":[
        "seafood",
        "hamburger",
        "dog",
        "hot"
    ],
    "wof:name":"Zip's Hamburgers & Fish",
    "wof:placetype":"venue"
},
  "geometry": {"coordinates":[-119.111,46.211899],"type":"Point"}
}