{
  "type": "Feature",
  "properties": {
    "addr:full":"1958 Harvard Ave E # 305 Seattle WA 98102",
    "addr:housenumber":"1958",
    "addr:postcode":"98102",
    "addr:street":"Harvard Ave E # 305",
    "iso:country":"US",
    "sg:address":"1958 Harvard Ave E # 305",
    "sg:city":"Seattle",
    "sg:classifiers":[
        {
            "category":"Real Estate",
            "subcategory":"Real Estate Services",
            "type":"Services"
        }
    ],
    "sg:phone":"+1 206 709 9737",
    "sg:postcode":"98102",
    "sg:province":"WA",
    "sg:tags":[
        "inspection"
    ],
    "wof:name":"Janus Home Insp",
    "wof:placetype":"venue"
},
  "geometry": {"coordinates":[-122.322435,47.636243],"type":"Point"}
}