{
  "type": "Feature",
  "properties": {
    "addr:full":"1212 SW 354th Pl Federal Way WA 98023",
    "addr:housenumber":"1212",
    "addr:postcode":"98023",
    "addr:street":"Sw 354Th Pl",
    "iso:country":"US",
    "sg:address":"1212 SW 354th Pl",
    "sg:city":"Federal Way",
    "sg:classifiers":[
        {
            "category":"Retail",
            "subcategory":"Portrait Studio",
            "type":"Services"
        }
    ],
    "sg:phone":"+1 253 874 2303",
    "sg:postcode":"98023",
    "sg:province":"WA",
    "sg:tags":[
        "photo"
    ],
    "wof:name":"Hershman Photography",
    "wof:placetype":"venue"
},
  "geometry": {"coordinates":[-122.351806,47.283896],"type":"Point"}
}