{
  "type": "Feature",
  "properties": {
    "addr:full":"2301 NW 65th St Seattle WA 98117",
    "addr:housenumber":"2301",
    "addr:postcode":"98117",
    "addr:street":"Nw 65Th St",
    "iso:country":"US",
    "sg:address":"2301 NW 65th St",
    "sg:city":"Seattle",
    "sg:classifiers":[
        {
            "category":"Personal",
            "subcategory":"Beauty Salon",
            "type":"Services"
        }
    ],
    "sg:phone":"+1 206 527 7646",
    "sg:postcode":"98117",
    "sg:province":"WA",
    "sg:tags":[
        "shop"
    ],
    "wof:name":"Designs By Melinda",
    "wof:placetype":"venue"
},
  "geometry": {"coordinates":[-122.387547,47.675934],"type":"Point"}
}