{
  "type": "Feature",
  "properties": {
    "addr:full":"28239 Riffe Rd N Reardan WA 99029",
    "addr:postcode":"28239;99029",
    "addr:street":"Riffe Rd N Reardan",
    "iso:country":"US",
    "sg:address":"28239 Riffe Rd N",
    "sg:city":"Reardan",
    "sg:classifiers":[
        {
            "category":"Real Estate",
            "subcategory":"Real Estate Operator",
            "type":"Services"
        }
    ],
    "sg:phone":"+1 509 796 3592",
    "sg:postcode":"99029",
    "sg:province":"WA",
    "sg:tags":[
        "property",
        "lessor"
    ],
    "wof:name":"Harold Wegner",
    "wof:placetype":"venue"
},
  "geometry": {"coordinates":[-117.92768700000001,47.688774],"type":"Point"}
}