{
  "type": "Feature",
  "properties": {
    "addr:full":"2500 116th Ave NE Ste 3 Bellevue WA 98004",
    "addr:housenumber":"2500",
    "addr:postcode":"98004",
    "addr:street":"116Th Ave Ne Ste 3",
    "iso:country":"US",
    "sg:address":"2500 116th Ave NE Ste 3",
    "sg:city":"Bellevue",
    "sg:classifiers":[
        {
            "category":"Professional",
            "type":"Services"
        },
        {
            "category":"Professional",
            "subcategory":"Printing & Photocopies",
            "type":"Services"
        },
        {
            "category":"Government",
            "subcategory":"Post Office",
            "type":"Public Place"
        }
    ],
    "sg:phone":"+1 425 822 1984",
    "sg:postcode":"98004",
    "sg:province":"WA",
    "sg:tags":[
        "services-commercial",
        "processing",
        "list",
        "data",
        "mailing"
    ],
    "wof:name":"Labels & Lists, Inc",
    "wof:placetype":"venue"
},
  "geometry": {"coordinates":[-122.185638,47.632519],"type":"Point"}
}