{
  "type": "Feature",
  "properties": {
    "addr:full":"342 SW Pacific Ave Chehalis WA 98532",
    "addr:housenumber":"342",
    "addr:postcode":"98532",
    "addr:street":"Sw Pacific Ave",
    "iso:country":"US",
    "sg:address":"342 SW Pacific Ave",
    "sg:city":"Chehalis",
    "sg:classifiers":[
        {
            "category":"Personal",
            "subcategory":"Beauty Salon",
            "type":"Services"
        }
    ],
    "sg:phone":"+1 360 740 0888",
    "sg:postcode":"98532",
    "sg:province":"WA",
    "sg:tags":[
        "treatment",
        "skin"
    ],
    "wof:name":"Ontos Inc",
    "wof:placetype":"venue"
},
  "geometry": {"coordinates":[-122.965537,46.656616],"type":"Point"}
}