{
  "type": "Feature",
  "properties": {
    "addr:full":"1110 Landon Ave Yakima WA 98902",
    "addr:housenumber":"1110",
    "addr:postcode":"98902",
    "addr:street":"Landon Ave",
    "iso:country":"US",
    "sg:address":"1110 Landon Ave",
    "sg:city":"Yakima",
    "sg:classifiers":[
        {
            "category":"Building & Trades",
            "subcategory":"Construction",
            "type":"Services"
        }
    ],
    "sg:phone":"+1 509 452 6639",
    "sg:postcode":"98902",
    "sg:province":"WA",
    "sg:tags":[
        "tile",
        "dealer"
    ],
    "wof:name":"Benji's Custom Tile & Design",
    "wof:placetype":"venue"
},
  "geometry": {"coordinates":[-120.50560400000001,46.583599],"type":"Point"}
}