{
  "type": "Feature",
  "properties": {
    "iso:country":"US",
    "sg:address":"2215 W Maxwell Ave",
    "sg:city":"Spokane",
    "sg:classifiers":[
        {
            "category":"Building & Trades",
            "subcategory":"Construction",
            "type":"Services"
        }
    ],
    "sg:phone":"+1 509 328 6571",
    "sg:postcode":"99201",
    "sg:province":"WA",
    "sg:tags":[
        "painter"
    ],
    "wof:name":"Aaron J Wagner Painting",
    "wof:placetype":"venue"
},
  "geometry": {"coordinates":[-117.444619,47.670735],"type":"Point"}
}