{
  "type": "Feature",
  "properties": {
    "addr:full":"2306 Sirkka St Centralia WA 98531",
    "addr:housenumber":"2306",
    "addr:postcode":"98531",
    "addr:street":"Sirkka St",
    "iso:country":"US",
    "sg:address":"2306 Sirkka St",
    "sg:city":"Centralia",
    "sg:classifiers":[
        {
            "category":"Professional",
            "subcategory":"Computer Services",
            "type":"Services"
        }
    ],
    "sg:phone":"+1 360 438 9139",
    "sg:postcode":"98531",
    "sg:province":"WA",
    "wof:name":"Cpr Computer and Printer Repr",
    "wof:placetype":"venue"
},
  "geometry": {"coordinates":[-122.948787,46.745641],"type":"Point"}
}