{
  "type": "Feature",
  "properties": {
    "addr:full":"20871 Bulson Rd Mt Vernon WA 98274",
    "addr:housenumber":"20871",
    "addr:postcode":"98274",
    "addr:street":"Bulson Rd",
    "iso:country":"US",
    "sg:address":"20871 Bulson Rd",
    "sg:city":"Mt Vernon",
    "sg:classifiers":[
        {
            "category":"Building & Trades",
            "subcategory":"Construction",
            "type":"Services"
        }
    ],
    "sg:phone":"+1 360 293 8139",
    "sg:postcode":"98274",
    "sg:province":"WA",
    "sg:tags":[
        "roofing",
        "contractor"
    ],
    "wof:name":"Gibbs Roof Co",
    "wof:placetype":"venue"
},
  "geometry": {"coordinates":[-122.312607,48.342837],"type":"Point"}
}