{
  "type": "Feature",
  "properties": {
    "addr:full":"11520 Fremont Ave N Seattle WA 98133",
    "addr:housenumber":"11520",
    "addr:postcode":"98133",
    "addr:street":"Fremont Ave N",
    "iso:country":"US",
    "sg:address":"11520 Fremont Ave N",
    "sg:city":"Seattle",
    "sg:classifiers":[
        {
            "category":"Professional",
            "type":"Services"
        }
    ],
    "sg:phone":"+1 206 362 9375",
    "sg:postcode":"98133",
    "sg:province":"WA",
    "wof:name":"Bruce David Woolsey",
    "wof:placetype":"venue"
},
  "geometry": {"coordinates":[-122.350157,47.713962],"type":"Point"}
}