{
  "type": "Feature",
  "properties": {
    "addr:full":"49 Columbia Point Dr Richland WA 99352",
    "addr:housenumber":"49",
    "addr:postcode":"99352",
    "addr:street":"Columbia Point Dr",
    "iso:country":"US",
    "sg:address":"49 Columbia Point Dr",
    "sg:city":"Richland",
    "sg:classifiers":[
        {
            "category":"Fast Food",
            "type":"Food & Drink"
        },
        {
            "category":"Restaurant",
            "type":"Food & Drink"
        }
    ],
    "sg:phone":"+1 509 943 8544",
    "sg:postcode":"99352",
    "sg:province":"WA",
    "sg:tags":[
        "american",
        "hot",
        "hamburger",
        "dog"
    ],
    "sg:website":"http://www.jackinthebox.com",
    "wof:name":"Jack in the Box",
    "wof:placetype":"venue"
},
  "geometry": {"coordinates":[-119.265671,46.264597],"type":"Point"}
}