{
  "type": "Feature",
  "properties": {
    "addr:full":"1834 Evergreen St Walla Walla WA 99362",
    "addr:housenumber":"1834",
    "addr:postcode":"99362",
    "addr:street":"Evergreen St",
    "iso:country":"US",
    "sg:address":"1834 Evergreen St",
    "sg:city":"Walla Walla",
    "sg:classifiers":[
        {
            "category":"Professional",
            "subcategory":"Computer Services",
            "type":"Services"
        }
    ],
    "sg:phone":"+1 509 200 0254",
    "sg:postcode":"99362",
    "sg:province":"WA",
    "sg:tags":[
        "repair"
    ],
    "wof:name":"Shuriken Computers",
    "wof:placetype":"venue"
},
  "geometry": {"coordinates":[-118.30788,46.073561],"type":"Point"}
}