{
  "type": "Feature",
  "properties": {
    "addr:full":"17014 Park Ave Mt Vernon WA 98274",
    "addr:housenumber":"17014",
    "addr:postcode":"98274",
    "addr:street":"Park Ave",
    "iso:country":"US",
    "sg:address":"17014 Park Ave",
    "sg:city":"Mt Vernon",
    "sg:classifiers":[
        {
            "category":"Building & Trades",
            "subcategory":"Construction",
            "type":"Services"
        }
    ],
    "sg:phone":"+1 360 428 3808",
    "sg:postcode":"98274",
    "sg:province":"WA",
    "sg:tags":[
        "contractor"
    ],
    "wof:name":"Enders Construction",
    "wof:placetype":"venue"
},
  "geometry": {"coordinates":[-122.32186400000001,48.399246],"type":"Point"}
}