{
  "type": "Feature",
  "properties": {
    "addr:full":"2204 Towhee Ln Richland WA 99353",
    "addr:housenumber":"2204",
    "addr:postcode":"99353",
    "addr:street":"Towhee Ln",
    "iso:country":"US",
    "sg:address":"2204 Towhee Ln",
    "sg:city":"Richland",
    "sg:classifiers":[
        {
            "category":"Professional",
            "subcategory":"Art Services",
            "type":"Services"
        }
    ],
    "sg:phone":"+1 509 967 9424",
    "sg:postcode":"99353",
    "sg:province":"WA",
    "sg:tags":[
        "photography",
        "commercial"
    ],
    "wof:name":"Same",
    "wof:placetype":"venue"
},
  "geometry": {"coordinates":[-119.349951,46.280577],"type":"Point"}
}