{
  "type": "Feature",
  "properties": {
    "addr:full":"17515 Albany St SW Rochester WA 98579",
    "addr:housenumber":"17515",
    "addr:postcode":"98579",
    "addr:street":"Albany St Sw",
    "iso:country":"US",
    "sg:address":"17515 Albany St SW",
    "sg:city":"Rochester",
    "sg:classifiers":[
        {
            "category":"Manufacturing",
            "subcategory":"Food",
            "type":"Manufacturing & Wholesale Goods"
        }
    ],
    "sg:phone":"+1 360 273 4700",
    "sg:postcode":"98579",
    "sg:province":"WA",
    "sg:tags":[
        "product",
        "mfg"
    ],
    "wof:name":"Worlds Finest Chocolate Inc",
    "wof:placetype":"venue"
},
  "geometry": {"coordinates":[-123.096979,46.833072],"type":"Point"}
}