{
  "type": "Feature",
  "properties": {
    "addr:full":"14611 NE 79th St Vancouver WA 98682",
    "addr:housenumber":"14611",
    "addr:postcode":"98682",
    "addr:street":"Ne 79Th St",
    "iso:country":"US",
    "sg:address":"14611 NE 79th St",
    "sg:city":"Vancouver",
    "sg:classifiers":[
        {
            "category":"Building & Trades",
            "subcategory":"Construction",
            "type":"Services"
        }
    ],
    "sg:phone":"+1 360 891 1325",
    "sg:postcode":"98682",
    "sg:province":"WA",
    "sg:tags":[
        "house"
    ],
    "wof:name":"Bpn Construction",
    "wof:placetype":"venue"
},
  "geometry": {"coordinates":[-122.522104,45.67983],"type":"Point"}
}