{
  "type": "Feature",
  "properties": {
    "addr:full":"4824 G Loop Bow WA 98232",
    "addr:housenumber":"4824",
    "addr:postcode":"98232",
    "addr:street":"G Loop",
    "iso:country":"US",
    "sg:address":"4824 G Loop",
    "sg:city":"Bow",
    "sg:classifiers":[
        {
            "category":"Shopping",
            "subcategory":"Used Merchandise",
            "type":"Retail Goods"
        }
    ],
    "sg:phone":"+1 360 766 7107",
    "sg:postcode":"98232",
    "sg:province":"WA",
    "wof:name":"Anitas Upscale Resale",
    "wof:placetype":"venue"
},
  "geometry": {"coordinates":[-122.530933,48.57427],"type":"Point"}
}