{
  "type": "Feature",
  "properties": {
    "addr:full":"2303 Hendricks Rd Connell WA 99326",
    "addr:housenumber":"2303",
    "addr:postcode":"99326",
    "addr:street":"Hendricks Rd",
    "iso:country":"US",
    "sg:address":"2303 Hendricks Rd",
    "sg:city":"Connell",
    "sg:classifiers":[
        {
            "category":"Banks & Credit Unions",
            "subcategory":"Financial Services",
            "type":"Services"
        }
    ],
    "sg:phone":"+1 509 234 0230",
    "sg:postcode":"99326",
    "sg:province":"WA",
    "sg:tags":[
        "investor"
    ],
    "wof:name":"Desert West Investors LTD",
    "wof:placetype":"venue"
},
  "geometry": {"coordinates":[-119.038749,46.665658],"type":"Point"}
}