{
  "type": "Feature",
  "properties": {
    "addr:full":"8630 Martin Way E Lacey WA 98516",
    "addr:housenumber":"8630",
    "addr:postcode":"98516",
    "addr:street":"Martin Way E",
    "iso:country":"US",
    "sg:address":"8630 Martin Way E",
    "sg:city":"Lacey",
    "sg:classifiers":[
        {
            "category":"Personal",
            "subcategory":"Beauty Salon",
            "type":"Services"
        }
    ],
    "sg:phone":"+1 360 493 8200",
    "sg:postcode":"98516",
    "sg:province":"WA",
    "wof:name":"Hawks Prairie Hair Salon",
    "wof:placetype":"venue"
},
  "geometry": {"coordinates":[-122.755139,47.0587],"type":"Point"}
}