{
  "type": "Feature",
  "properties": {
    "addr:full":"2803 N Hogan St Spokane WA 99207",
    "addr:housenumber":"2803",
    "addr:postcode":"99207",
    "addr:street":"N Hogan St",
    "iso:country":"US",
    "sg:address":"2803 N Hogan St",
    "sg:city":"Spokane",
    "sg:classifiers":[
        {
            "category":"Home & Garden",
            "subcategory":"Furniture",
            "type":"Retail Goods"
        }
    ],
    "sg:phone":"+1 509 483 2744",
    "sg:postcode":"99207",
    "sg:province":"WA",
    "sg:tags":[
        "work",
        "cabinet"
    ],
    "wof:name":"Euro Style Cabinets",
    "wof:placetype":"venue"
},
  "geometry": {"coordinates":[-117.387733,47.683449],"type":"Point"}
}