{
  "type": "Feature",
  "properties": {
    "addr:full":"2109 196th St SW Lynnwood WA 98036",
    "addr:housenumber":"2109",
    "addr:postcode":"98036",
    "addr:street":"196Th St Sw",
    "iso:country":"US",
    "sg:address":"2109 196th St SW",
    "sg:city":"Lynnwood",
    "sg:classifiers":[
        {
            "category":"Personal",
            "type":"Services"
        }
    ],
    "sg:phone":"+1 425 640 2221",
    "sg:postcode":"98036",
    "sg:province":"WA",
    "sg:tags":[
        "therapist",
        "massage"
    ],
    "wof:name":"Organic Therapy By Laura Ls",
    "wof:placetype":"venue"
},
  "geometry": {"coordinates":[-122.26164,47.820667],"type":"Point"}
}