{
  "type": "Feature",
  "properties": {
    "addr:full":"27605 96th St E Buckley WA 98321",
    "addr:housenumber":"27605",
    "addr:postcode":"98321",
    "addr:street":"96Th St",
    "iso:country":"US",
    "sg:address":"27605 96th St E",
    "sg:city":"Buckley",
    "sg:classifiers":[
        {
            "category":"Manufacturing",
            "subcategory":"Tools & Machinery",
            "type":"Manufacturing & Wholesale Goods"
        }
    ],
    "sg:phone":"+1 360 829 5022",
    "sg:postcode":"98321",
    "sg:province":"WA",
    "sg:tags":[
        "die",
        "maker"
    ],
    "wof:name":"Four Star Machining",
    "wof:placetype":"venue"
},
  "geometry": {"coordinates":[-122.076958,47.170275],"type":"Point"}
}