{
  "type": "Feature",
  "properties": {
    "addr:full":"11303 Wide Hollow Rd Yakima WA 98908",
    "addr:housenumber":"11303",
    "addr:postcode":"98908",
    "addr:street":"Wide Hollow Rd",
    "iso:country":"US",
    "sg:address":"11303 Wide Hollow Rd",
    "sg:city":"Yakima",
    "sg:classifiers":[
        {
            "category":"Building & Trades",
            "subcategory":"Construction",
            "type":"Services"
        }
    ],
    "sg:phone":"+1 509 965 0946",
    "sg:postcode":"98908",
    "sg:province":"WA",
    "sg:tags":[
        "excavation",
        "work"
    ],
    "wof:name":"Vic Mason Excavating",
    "wof:placetype":"venue"
},
  "geometry": {"coordinates":[-120.66217899999999,46.582225],"type":"Point"}
}