{
  "type": "Feature",
  "properties": {
    "addr:full":"632 NW 75th St Seattle WA 98117",
    "addr:housenumber":"632",
    "addr:postcode":"98117",
    "addr:street":"Nw 75Th St",
    "iso:country":"US",
    "sg:address":"632 NW 75th St",
    "sg:city":"Seattle",
    "sg:classifiers":[
        {
            "category":"Arts & Performance",
            "subcategory":"Music",
            "type":"Entertainment"
        }
    ],
    "sg:phone":"+1 206 781 9665",
    "sg:postcode":"98117",
    "sg:province":"WA",
    "sg:tags":[
        "arranger",
        "composer"
    ],
    "wof:name":"Greenwood Cello Studio",
    "wof:placetype":"venue"
},
  "geometry": {"coordinates":[-122.364214,47.683283],"type":"Point"}
}