{
  "type": "Feature",
  "properties": {
    "addr:full":"7979 Rd N SW Quincy WA 98848",
    "addr:housenumber":"7979",
    "addr:postcode":"98848",
    "addr:street":"Rd N Sw",
    "iso:country":"US",
    "sg:address":"7979 Rd N SW",
    "sg:city":"Quincy",
    "sg:classifiers":[
        {
            "category":"Farming",
            "subcategory":"Farm",
            "type":"Manufacturing & Wholesale Goods"
        }
    ],
    "sg:phone":"+1 509 787 4618",
    "sg:postcode":"98848",
    "sg:province":"WA",
    "sg:tags":[
        "crop",
        "general"
    ],
    "wof:name":"Larry Vandiest",
    "wof:placetype":"venue"
},
  "geometry": {"coordinates":[-119.79208800000001,46.972373],"type":"Point"}
}