{
  "type": "Feature",
  "properties": {
    "addr:full":"16815 Redmond Way Redmond WA 98052",
    "addr:housenumber":"16815",
    "addr:postcode":"98052",
    "addr:street":"Redmond Way",
    "iso:country":"US",
    "sg:address":"16815 Redmond Way",
    "sg:city":"Redmond",
    "sg:classifiers":[
        {
            "category":"Professional",
            "type":"Services"
        },
        {
            "category":"Professional",
            "subcategory":"Business Services",
            "type":"Services"
        },
        {
            "category":"Professional",
            "subcategory":"Printing & Photocopies",
            "type":"Services"
        },
        {
            "category":"Shopping",
            "subcategory":"Stationery & Office Supplies",
            "type":"Retail Goods"
        },
        {
            "category":"Manufacturing",
            "subcategory":"Printing",
            "type":"Manufacturing & Wholesale Goods"
        },
        {
            "category":"Manufacturing",
            "subcategory":"Signs",
            "type":"Manufacturing & Wholesale Goods"
        }
    ],
    "sg:phone":"+1 425 882 1949",
    "sg:postcode":"98052",
    "sg:province":"WA",
    "sg:tags":[
        "machine",
        "document",
        "duplicating",
        "shipping",
        "materials-shipping",
        "packaging",
        "packing",
        "imaging",
        "copying",
        "digital",
        "copy"
    ],
    "sg:website":"http://www.fedex.com/Dropoff/start?FY11-FXO-YELLOWPAGES",
    "wof:name":"FedEx Office Print & Ship Center",
    "wof:placetype":"venue"
},
  "geometry": {"coordinates":[-122.115118,47.671998],"type":"Point"}
}