{
  "type": "Feature",
  "properties": {
    "addr:full":"18721 Division Ave NE Suquamish WA 98392",
    "addr:housenumber":"18721",
    "addr:postcode":"98392",
    "addr:street":"Division Ave Ne",
    "iso:country":"US",
    "sg:address":"18721 Division Ave NE",
    "sg:city":"Suquamish",
    "sg:classifiers":[
        {
            "category":"Building & Trades",
            "subcategory":"Plumbing",
            "type":"Services"
        }
    ],
    "sg:phone":"+1 360 598 4636",
    "sg:postcode":"98392",
    "sg:province":"WA",
    "sg:tags":[
        "plumbing",
        "contractor"
    ],
    "wof:name":"Kitsap Peninsula Plumbing",
    "wof:placetype":"venue"
},
  "geometry": {"coordinates":[-122.558295,47.732256],"type":"Point"}
}