{
  "type": "Feature",
  "properties": {
    "addr:full":"5709 Putnam Rd Everson WA 98247",
    "addr:housenumber":"5709",
    "addr:postcode":"98247",
    "addr:street":"Putnam Rd",
    "iso:country":"US",
    "sg:address":"5709 Putnam Rd",
    "sg:city":"Everson",
    "sg:classifiers":[
        {
            "category":"Building & Trades",
            "subcategory":"Construction",
            "type":"Services"
        }
    ],
    "sg:phone":"+1 360 592 9039",
    "sg:postcode":"98247",
    "sg:province":"WA",
    "sg:tags":[
        "house"
    ],
    "wof:name":"Johnson Builders",
    "wof:placetype":"venue"
},
  "geometry": {"coordinates":[-122.277665,48.846387],"type":"Point"}
}