{
  "type": "Feature",
  "properties": {
    "addr:full":"11202 Steele St S Lakewood WA 98499",
    "addr:housenumber":"11202",
    "addr:postcode":"98499",
    "addr:street":"Steele St S",
    "iso:country":"US",
    "sg:address":"11202 Steele St S",
    "sg:city":"Lakewood",
    "sg:classifiers":[
        {
            "category":"Autos & Motor Vehicles",
            "subcategory":"Fuel & Gas Station",
            "type":"Retail Goods"
        }
    ],
    "sg:phone":"+1 253 539 9522",
    "sg:postcode":"98499",
    "sg:province":"WA",
    "wof:name":"Steele Steeet 76",
    "wof:placetype":"venue"
},
  "geometry": {"coordinates":[-122.468002,47.155602],"type":"Point"}
}