{
  "type": "Feature",
  "properties": {
    "addr:full":"400 NW 163rd St Shoreline WA 98177",
    "addr:housenumber":"400",
    "addr:postcode":"98177",
    "addr:street":"Nw 163Rd St",
    "iso:country":"US",
    "sg:address":"400 NW 163rd St",
    "sg:city":"Shoreline",
    "sg:classifiers":[
        {
            "category":"Wholesale",
            "subcategory":"Durable Goods & Equipment",
            "type":"Manufacturing & Wholesale Goods"
        }
    ],
    "sg:phone":"+1 206 542 4448",
    "sg:postcode":"98177",
    "sg:province":"WA",
    "sg:tags":[
        "representative",
        "manufacturer"
    ],
    "wof:name":"Alpha Northwest Sales",
    "wof:placetype":"venue"
},
  "geometry": {"coordinates":[-122.36375,47.747161],"type":"Point"}
}