{
  "type": "Feature",
  "properties": {
    "addr:full":"822 Alabama St Bellingham WA 98225",
    "addr:housenumber":"822",
    "addr:postcode":"98225",
    "addr:street":"Alabama St",
    "iso:country":"US",
    "sg:address":"822 Alabama St",
    "sg:city":"Bellingham",
    "sg:classifiers":[
        {
            "category":"Health Services",
            "subcategory":"Chiropractor",
            "type":"Services"
        }
    ],
    "sg:phone":"+1 360 733 0887",
    "sg:postcode":"98225",
    "sg:province":"WA",
    "wof:name":"Pain Relief Center",
    "wof:placetype":"venue"
},
  "geometry": {"coordinates":[-122.46368099999999,48.76295],"type":"Point"}
}