{
  "type": "Feature",
  "properties": {
    "addr:full":"27235 104th Dr NW Stanwood WA 98292",
    "addr:housenumber":"27235",
    "addr:postcode":"98292",
    "addr:street":"104Th Dr Nw",
    "iso:country":"US",
    "sg:address":"27235 104th Dr NW",
    "sg:city":"Stanwood",
    "sg:classifiers":[
        {
            "category":"Professional",
            "subcategory":"Business Services",
            "type":"Services"
        }
    ],
    "sg:phone":"+1 360 629 9295",
    "sg:postcode":"98292",
    "sg:province":"WA",
    "wof:name":"Northwest Liquidators",
    "wof:placetype":"venue"
},
  "geometry": {"coordinates":[-122.374099,48.244456],"type":"Point"}
}