{
  "type": "Feature",
  "properties": {
    "addr:full":"3820 E Mercer Way Mercer Island WA 98040",
    "addr:housenumber":"3820",
    "addr:postcode":"98040",
    "addr:street":"E Mercer Way",
    "iso:country":"US",
    "sg:address":"3820 E Mercer Way",
    "sg:city":"Mercer Island",
    "sg:classifiers":[
        {
            "category":"Health Services",
            "subcategory":"Clinic",
            "type":"Services"
        }
    ],
    "sg:phone":"+1 206 275 0984",
    "sg:postcode":"98040",
    "sg:province":"WA",
    "sg:tags":[
        "kidney",
        "dialysis"
    ],
    "wof:name":"Liberty Dialysis LLC",
    "wof:placetype":"venue"
},
  "geometry": {"coordinates":[-122.206057,47.576675],"type":"Point"}
}