{
  "type": "Feature",
  "properties": {
    "addr:full":"241 Main Ave Morton WA 98356",
    "addr:housenumber":"241",
    "addr:postcode":"98356",
    "addr:street":"Main Ave",
    "iso:country":"US",
    "sg:address":"241 Main Ave",
    "sg:city":"Morton",
    "sg:classifiers":[
        {
            "category":"Food & Beverages",
            "subcategory":"Meat & Fish",
            "type":"Retail Goods"
        }
    ],
    "sg:phone":"+1 360 496 5327",
    "sg:postcode":"98356",
    "sg:province":"WA",
    "sg:tags":[
        "market"
    ],
    "sg:website":"http://www.mortonmeatco.com",
    "wof:name":"Morton Meat Co",
    "wof:placetype":"venue"
},
  "geometry": {"coordinates":[-122.276623,46.558289],"type":"Point"}
}