{
  "type": "Feature",
  "properties": {
    "addr:full":"4911 197th Ave E Sumner WA 98391",
    "addr:housenumber":"4911",
    "addr:postcode":"98391",
    "addr:street":"197Th Ave E",
    "iso:country":"US",
    "sg:address":"4911 197th Ave E",
    "sg:city":"Sumner",
    "sg:classifiers":[
        {
            "category":"Building & Trades",
            "subcategory":"Construction",
            "type":"Services"
        }
    ],
    "sg:phone":"+1 253 862 8206",
    "sg:postcode":"98391",
    "sg:province":"WA",
    "sg:tags":[
        "house",
        "nonresidential"
    ],
    "wof:name":"Swain Builders",
    "wof:placetype":"venue"
},
  "geometry": {"coordinates":[-122.16392999999999,47.207739],"type":"Point"}
}