{
  "type": "Feature",
  "properties": {
    "addr:full":"1001 7th Ave NW Puyallup WA 98371",
    "addr:housenumber":"1001",
    "addr:postcode":"98371",
    "addr:street":"7Th Ave Nw",
    "iso:country":"US",
    "sg:address":"1001 7th Ave NW",
    "sg:city":"Puyallup",
    "sg:classifiers":[
        {
            "category":"Shopping",
            "subcategory":"Discount & Variety Stores",
            "type":"Retail Goods"
        }
    ],
    "sg:phone":"+1 253 845 8706",
    "sg:postcode":"98371",
    "sg:province":"WA",
    "sg:tags":[
        "merchandise",
        "general"
    ],
    "wof:name":"Watering Can",
    "wof:placetype":"venue"
},
  "geometry": {"coordinates":[-122.30488099999999,47.197007],"type":"Point"}
}