{
  "type": "Feature",
  "properties": {
    "addr:full":"134 Basin St NW Ephrata WA 98823",
    "addr:housenumber":"134",
    "addr:postcode":"98823",
    "addr:street":"Basin St Nw",
    "iso:country":"US",
    "sg:address":"134 Basin St NW",
    "sg:city":"Ephrata",
    "sg:classifiers":[
        {
            "category":"Shopping",
            "type":"Retail Goods"
        }
    ],
    "sg:phone":"+1 509 754 9361",
    "sg:postcode":"98823",
    "sg:province":"WA",
    "sg:tags":[
        "mexican"
    ],
    "wof:name":"El Girasol Tienda Mexicana",
    "wof:placetype":"venue"
},
  "geometry": {"coordinates":[-119.550376,47.32225],"type":"Point"}
}