{
  "type": "Feature",
  "properties": {
    "addr:full":"1329 Commerce Ave Longview WA 98632",
    "addr:housenumber":"1329",
    "addr:postcode":"98632",
    "addr:street":"Commerce Ave",
    "iso:country":"US",
    "sg:address":"1329 Commerce Ave",
    "sg:city":"Longview",
    "sg:classifiers":[
        {
            "category":"Professional",
            "type":"Services"
        }
    ],
    "sg:phone":"+1 360 423 1511",
    "sg:postcode":"98632",
    "sg:province":"WA",
    "wof:name":"Whats Up Stairs",
    "wof:placetype":"venue"
},
  "geometry": {"coordinates":[-122.93408599999999,46.137989],"type":"Point"}
}