{
  "type": "Feature",
  "properties": {
    "addr:full":"2817 13th St SE Puyallup WA 98374",
    "addr:housenumber":"2817",
    "addr:postcode":"98374",
    "addr:street":"13Th St Se",
    "iso:country":"US",
    "sg:address":"2817 13th St SE",
    "sg:city":"Puyallup",
    "sg:classifiers":[
        {
            "category":"Building & Trades",
            "subcategory":"Construction",
            "type":"Services"
        }
    ],
    "sg:phone":"+1 253 770 2045",
    "sg:postcode":"98374",
    "sg:province":"WA",
    "sg:tags":[
        "hanging",
        "contractor"
    ],
    "wof:name":"Garys Painting Service",
    "wof:placetype":"venue"
},
  "geometry": {"coordinates":[-122.277811,47.164318],"type":"Point"}
}