{
  "type": "Feature",
  "properties": {
    "addr:full":"2714 NE 100th St Vancouver WA 98686",
    "addr:housenumber":"2714",
    "addr:postcode":"98686",
    "addr:street":"Ne 100Th St",
    "iso:country":"US",
    "sg:address":"2714 NE 100th St",
    "sg:city":"Vancouver",
    "sg:classifiers":[
        {
            "category":"Education",
            "subcategory":"Special Training",
            "type":"Public Place"
        }
    ],
    "sg:phone":"+1 360 891 2127",
    "sg:postcode":"98686",
    "sg:province":"WA",
    "sg:tags":[
        "program"
    ],
    "wof:name":"A P & Assoc Inc",
    "wof:placetype":"venue"
},
  "geometry": {"coordinates":[-122.64357800000001,45.694108],"type":"Point"}
}