{
  "type": "Feature",
  "properties": {
    "addr:full":"14275 Interurban Ave S Tukwila WA 98168",
    "addr:housenumber":"14275",
    "addr:postcode":"98168",
    "addr:street":"Interurban Ave S",
    "iso:country":"US",
    "sg:address":"14275 Interurban Ave S",
    "sg:city":"Tukwila",
    "sg:classifiers":[
        {
            "category":"Organizations",
            "subcategory":"Religious Organization",
            "type":"Services"
        }
    ],
    "sg:phone":"+1 206 241 7686",
    "sg:postcode":"98168",
    "sg:province":"WA",
    "sg:tags":[
        "church"
    ],
    "wof:name":"Ebenezer Church Of God-Christ",
    "wof:placetype":"venue"
},
  "geometry": {"coordinates":[-122.257462,47.475178],"type":"Point"}
}