{
  "type": "Feature",
  "properties": {
    "iso:country":"US",
    "sg:address":"1707 S Lincoln St",
    "sg:city":"Spokane",
    "sg:classifiers":[
        {
            "category":"Retail",
            "subcategory":"Portrait Studio",
            "type":"Services"
        }
    ],
    "sg:phone":"+1 509 459 0766",
    "sg:postcode":"99203",
    "sg:province":"WA",
    "sg:tags":[
        "photo"
    ],
    "wof:name":"Portrait Creations",
    "wof:placetype":"venue"
},
  "geometry": {"coordinates":[-117.424046,47.639839],"type":"Point"}
}