{
  "type": "Feature",
  "properties": {
    "addr:full":"1211 S Judkins St Apt D Seattle WA 98144",
    "addr:housenumber":"1211",
    "addr:postcode":"98144",
    "addr:street":"S Judkins St Apt D",
    "iso:country":"US",
    "sg:address":"1211 S Judkins St Apt D",
    "sg:city":"Seattle",
    "sg:classifiers":[
        {
            "category":"Building & Trades",
            "subcategory":"Electrical",
            "type":"Services"
        }
    ],
    "sg:phone":"+1 206 971 6555",
    "sg:postcode":"98144",
    "sg:province":"WA",
    "sg:tags":[
        "electrician"
    ],
    "wof:name":"Mcdermott Electric",
    "wof:placetype":"venue"
},
  "geometry": {"coordinates":[-122.317151,47.59154],"type":"Point"}
}