{
  "type": "Feature",
  "properties": {
    "addr:full":"3019 Judson St Gig Harbor WA 98335",
    "addr:housenumber":"3019",
    "addr:postcode":"98335",
    "addr:street":"Judson St",
    "iso:country":"US",
    "sg:address":"3019 Judson St",
    "sg:city":"Gig Harbor",
    "sg:classifiers":[
        {
            "category":"Real Estate",
            "subcategory":"Architect",
            "type":"Services"
        }
    ],
    "sg:phone":"+1 253 973 6680",
    "sg:postcode":"98335",
    "sg:province":"WA",
    "wof:name":"Castino Architecture",
    "wof:placetype":"venue"
},
  "geometry": {"coordinates":[-122.579793,47.328078],"type":"Point"}
}