{
  "type": "Feature",
  "properties": {
    "addr:full":"221 S Havana St Spokane WA 99202",
    "addr:housenumber":"221",
    "addr:postcode":"99202",
    "addr:street":"S Havana St",
    "iso:country":"US",
    "sg:address":"221 S Havana St",
    "sg:city":"Spokane",
    "sg:classifiers":[
        {
            "category":"Insurance",
            "subcategory":"Insurance Agent",
            "type":"Services"
        }
    ],
    "sg:phone":"+1 509 535 6641",
    "sg:postcode":"99202",
    "sg:province":"WA",
    "wof:name":"Hermance Insurance",
    "wof:placetype":"venue"
},
  "geometry": {"coordinates":[-117.346908,47.655164],"type":"Point"}
}