{
  "type": "Feature",
  "properties": {
    "addr:full":"1650 134th Ave SE Bellevue WA 98005",
    "addr:housenumber":"1650",
    "addr:postcode":"98005",
    "addr:street":"134Th Ave Se",
    "iso:country":"US",
    "sg:address":"1650 134th Ave SE",
    "sg:city":"Bellevue",
    "sg:classifiers":[
        {
            "category":"Professional",
            "subcategory":"Computer Services",
            "type":"Services"
        }
    ],
    "sg:phone":"+1 206 601 5787",
    "sg:postcode":"98005",
    "sg:province":"WA",
    "sg:tags":[
        "related"
    ],
    "wof:name":"Davis Technology Inc",
    "wof:placetype":"venue"
},
  "geometry": {"coordinates":[-122.16145899999999,47.596458],"type":"Point"}
}