{
  "type": "Feature",
  "properties": {
    "addr:full":"31722 E Eugene St Carnation WA 98014",
    "addr:housenumber":"31722",
    "addr:postcode":"98014",
    "addr:street":"E Eugene St",
    "iso:country":"US",
    "sg:address":"31722 E Eugene St",
    "sg:city":"Carnation",
    "sg:classifiers":[
        {
            "category":"Restaurant",
            "type":"Food & Drink"
        }
    ],
    "sg:phone":"+1 425 333 6585",
    "sg:postcode":"98014",
    "sg:province":"WA",
    "sg:tags":[
        "pizza"
    ],
    "wof:name":"Blake's Pizzeria & Ice Cream",
    "wof:placetype":"venue"
},
  "geometry": {"coordinates":[-121.916746,47.646864],"type":"Point"}
}