{
  "type": "Feature",
  "properties": {
    "addr:full":"13122 86th Pl NE Kirkland WA 98034",
    "addr:housenumber":"13122",
    "addr:postcode":"98034",
    "addr:street":"86Th Pl Ne",
    "iso:country":"US",
    "sg:address":"13122 86th Pl NE",
    "sg:city":"Kirkland",
    "sg:classifiers":[
        {
            "category":"Building & Trades",
            "subcategory":"Locksmith",
            "type":"Services"
        }
    ],
    "sg:phone":"+1 425 636 2292",
    "sg:postcode":"98034",
    "sg:province":"WA",
    "sg:tags":[
        "key"
    ],
    "wof:name":"Local 24 Locksmith",
    "wof:placetype":"venue"
},
  "geometry": {"coordinates":[-122.226586,47.717637],"type":"Point"}
}