{
  "type": "Feature",
  "properties": {
    "addr:full":"302 9th St Wenatchee WA 98801",
    "addr:housenumber":"302",
    "addr:postcode":"98801",
    "addr:street":"9Th St",
    "iso:country":"US",
    "sg:address":"302 9th St",
    "sg:city":"Wenatchee",
    "sg:classifiers":[
        {
            "category":"Shopping",
            "type":"Retail Goods"
        }
    ],
    "sg:phone":"+1 509 886 9000",
    "sg:postcode":"98801",
    "sg:province":"WA",
    "sg:tags":[
        "funeral",
        "merchandise",
        "monument"
    ],
    "wof:name":"Cascade Memorial Center",
    "wof:placetype":"venue"
},
  "geometry": {"coordinates":[-120.322593,47.434325],"type":"Point"}
}