{
  "type": "Feature",
  "properties": {
    "addr:full":"19109 Dellwood Dr Edmonds WA 98026",
    "addr:housenumber":"19109",
    "addr:postcode":"98026",
    "addr:street":"Dellwood Dr",
    "iso:country":"US",
    "sg:address":"19109 Dellwood Dr",
    "sg:city":"Edmonds",
    "sg:classifiers":[
        {
            "category":"Professional",
            "subcategory":"Engineering",
            "type":"Services"
        }
    ],
    "sg:phone":"+1 425 776 0681",
    "sg:postcode":"98026",
    "sg:province":"WA",
    "wof:name":"Oceantech",
    "wof:placetype":"venue"
},
  "geometry": {"coordinates":[-122.336788,47.825894],"type":"Point"}
}