{
  "type": "Feature",
  "properties": {
    "iso:country":"US",
    "sg:address":"819 50th St SE",
    "sg:city":"Auburn",
    "sg:classifiers":[
        {
            "category":"Personal",
            "subcategory":"Beauty Salon",
            "type":"Services"
        }
    ],
    "sg:phone":"+1 253 735 8693",
    "sg:postcode":"98092",
    "sg:province":"WA",
    "sg:tags":[
        "shop"
    ],
    "wof:name":"Debbie Do's",
    "wof:placetype":"venue"
},
  "geometry": {"coordinates":[-122.21863500000001,47.264302],"type":"Point"}
}