{
  "type": "Feature",
  "properties": {
    "addr:full":"1048 W James St Kent WA 98032",
    "addr:housenumber":"1048",
    "addr:postcode":"98032",
    "addr:street":"W James St",
    "iso:country":"US",
    "sg:address":"1048 W James St",
    "sg:city":"Kent",
    "sg:classifiers":[
        {
            "category":"Insurance",
            "subcategory":"Insurance Agent",
            "type":"Services"
        }
    ],
    "sg:phone":"+1 253 854 3021",
    "sg:postcode":"98032",
    "sg:province":"WA",
    "wof:name":"Don Gregory Agency Inc",
    "wof:placetype":"venue"
},
  "geometry": {"coordinates":[-122.24435200000001,47.386634],"type":"Point"}
}