{
  "type": "Feature",
  "properties": {
    "addr:full":"767 16th Pl Mukilteo WA 98275",
    "addr:housenumber":"767",
    "addr:postcode":"98275",
    "addr:street":"16Th Pl",
    "iso:country":"US",
    "sg:address":"767 16th Pl",
    "sg:city":"Mukilteo",
    "sg:classifiers":[
        {
            "category":"Building & Trades",
            "subcategory":"Construction",
            "type":"Services"
        }
    ],
    "sg:phone":"+1 425 347 6808",
    "sg:postcode":"98275",
    "sg:province":"WA",
    "sg:tags":[
        "heavy"
    ],
    "wof:name":"16th Place LLC",
    "wof:placetype":"venue"
},
  "geometry": {"coordinates":[-122.301377,47.936586],"type":"Point"}
}