{
  "type": "Feature",
  "properties": {
    "addr:full":"531 W Washington St Sequim WA 98382",
    "addr:housenumber":"531",
    "addr:postcode":"98382",
    "addr:street":"W Washington St",
    "iso:country":"US",
    "sg:address":"531 W Washington St",
    "sg:city":"Sequim",
    "sg:phone":"+1 360 683 4788",
    "sg:postcode":"98382",
    "sg:province":"WA",
    "sg:website":"http://www.el-cazador.com",
    "wof:name":"El Cazador",
    "wof:placetype":"venue"
},
  "geometry": {"coordinates":[-123.11352100000001,48.079685],"type":"Point"}
}