{
  "type": "Feature",
  "properties": {
    "addr:full":"22500 SE 64th Pl Ste 220 Issaquah WA 98027",
    "addr:postcode":"22500;98027",
    "addr:street":"Se 64Th Pl Ste 220",
    "iso:country":"US",
    "sg:address":"22500 SE 64th Pl Ste 220",
    "sg:city":"Issaquah",
    "sg:classifiers":[
        {
            "category":"Banks & Credit Unions",
            "subcategory":"Bank",
            "type":"Services"
        },
        {
            "category":"Banks & Credit Unions",
            "subcategory":"Financial Services",
            "type":"Services"
        }
    ],
    "sg:phone":"+1 425 391 1860",
    "sg:postcode":"98027",
    "sg:province":"WA",
    "sg:tags":[
        "commercial",
        "loan",
        "saving"
    ],
    "sg:website":"http://www.wellsfargo.com",
    "wof:name":"Wells Fargo Bank",
    "wof:placetype":"venue"
},
  "geometry": {"coordinates":[-122.03997,47.54409],"type":"Point"}
}