{
  "type": "Feature",
  "properties": {
    "addr:full":"20719 106th Pl SE Kent WA 98031",
    "addr:housenumber":"20719",
    "addr:postcode":"98031",
    "addr:street":"106Th Pl Se",
    "iso:country":"US",
    "sg:address":"20719 106th Pl SE",
    "sg:city":"Kent",
    "sg:classifiers":[
        {
            "category":"Professional",
            "subcategory":"Business Services",
            "type":"Services"
        }
    ],
    "sg:phone":"+1 206 852 7906",
    "sg:postcode":"98031",
    "sg:province":"WA",
    "wof:name":"Kathleen L Herington",
    "wof:placetype":"venue"
},
  "geometry": {"coordinates":[-122.199061,47.416004],"type":"Point"}
}