{
  "type": "Feature",
  "properties": {
    "addr:full":"909 E College Way Mount Vernon WA 98273",
    "addr:housenumber":"909",
    "addr:postcode":"98273",
    "addr:street":"E College Way",
    "iso:country":"US",
    "sg:address":"909 E College Way",
    "sg:city":"Mount Vernon",
    "sg:classifiers":[
        {
            "category":"Retail",
            "subcategory":"Car Wash",
            "type":"Services"
        }
    ],
    "sg:phone":"+1 360 424 5257",
    "sg:postcode":"98273",
    "sg:province":"WA",
    "wof:name":"Innovative Car Wash Systems",
    "wof:placetype":"venue"
},
  "geometry": {"coordinates":[-122.328579,48.435905],"type":"Point"}
}