{
  "type": "Feature",
  "properties": {
    "addr:full":"314 W 39th St Vancouver WA 98660",
    "addr:housenumber":"314",
    "addr:postcode":"98660",
    "addr:street":"W 39Th St",
    "iso:country":"US",
    "sg:address":"314 W 39th St",
    "sg:city":"Vancouver",
    "sg:classifiers":[
        {
            "category":"Manufacturing",
            "subcategory":"Retail Goods",
            "type":"Manufacturing & Wholesale Goods"
        }
    ],
    "sg:phone":"+1 360 693 4201",
    "sg:postcode":"98660",
    "sg:province":"WA",
    "sg:tags":[
        "mfg",
        "hard",
        "floor",
        "covering"
    ],
    "wof:name":"Waids Floorcovering",
    "wof:placetype":"venue"
},
  "geometry": {"coordinates":[-122.674745,45.650058],"type":"Point"}
}