{
  "type": "Feature",
  "properties": {
    "addr:full":"6 S 2nd St Yakima WA 98901",
    "addr:housenumber":"6",
    "addr:postcode":"98901",
    "addr:street":"S 2Nd St",
    "iso:country":"US",
    "sg:address":"6 S 2nd St",
    "sg:city":"Yakima",
    "sg:classifiers":[
        {
            "category":"Professional",
            "subcategory":"Accounting & Tax Preparation",
            "type":"Services"
        }
    ],
    "sg:phone":"+1 509 469 8471",
    "sg:postcode":"98901",
    "sg:province":"WA",
    "sg:tags":[
        "accountant"
    ],
    "wof:name":"Accounting Consulting Taxation",
    "wof:placetype":"venue"
},
  "geometry": {"coordinates":[-120.50408,46.601341],"type":"Point"}
}