{
  "type": "Feature",
  "properties": {
    "iso:country":"US",
    "sg:address":"12128 N Division St",
    "sg:city":"Spokane",
    "sg:classifiers":[
        {
            "category":"Professional",
            "subcategory":"Engineering",
            "type":"Services"
        }
    ],
    "sg:phone":"+1 509 467 8554",
    "sg:postcode":"99218",
    "sg:province":"WA",
    "sg:tags":[
        "engineer"
    ],
    "wof:name":"Criterium-Pfaff Engineers",
    "wof:placetype":"venue"
},
  "geometry": {"coordinates":[-117.405846,47.764888],"type":"Point"}
}