{
  "type": "Feature",
  "properties": {
    "addr:full":"5900 92nd Ave SE Mercer Island WA 98040",
    "addr:housenumber":"5900",
    "addr:postcode":"98040",
    "addr:street":"92Nd Ave Se",
    "iso:country":"US",
    "sg:address":"5900 92nd Ave SE",
    "sg:city":"Mercer Island",
    "sg:classifiers":[
        {
            "category":"Shopping",
            "subcategory":"Florist",
            "type":"Retail Goods"
        }
    ],
    "sg:phone":"+1 206 232 4747",
    "sg:postcode":"98040",
    "sg:province":"WA",
    "wof:name":"Nlh Enterprises",
    "wof:placetype":"venue"
},
  "geometry": {"coordinates":[-122.21657999999999,47.549679],"type":"Point"}
}