{
  "type": "Feature",
  "properties": {
    "addr:full":"6416 Francis Ave N Seattle WA 98103",
    "addr:housenumber":"6416",
    "addr:postcode":"98103",
    "addr:street":"Francis Ave N",
    "iso:country":"US",
    "sg:address":"6416 Francis Ave N",
    "sg:city":"Seattle",
    "sg:classifiers":[
        {
            "category":"Communications",
            "subcategory":"Film & Video Production",
            "type":"Services"
        }
    ],
    "sg:phone":"+1 206 547 0671",
    "sg:postcode":"98103",
    "sg:province":"WA",
    "sg:tags":[
        "motion"
    ],
    "wof:name":"Merwin Productions Inc",
    "wof:placetype":"venue"
},
  "geometry": {"coordinates":[-122.35332699999999,47.675934],"type":"Point"}
}