{
  "type": "Feature",
  "properties": {
    "addr:full":"1223 NE 108th Ave Vancouver WA 98664",
    "addr:housenumber":"1223",
    "addr:postcode":"98664",
    "addr:street":"Ne 108Th Ave",
    "iso:country":"US",
    "sg:address":"1223 NE 108th Ave",
    "sg:city":"Vancouver",
    "sg:classifiers":[
        {
            "category":"Building & Trades",
            "subcategory":"Construction",
            "type":"Services"
        }
    ],
    "sg:phone":"+1 360 254 3072",
    "sg:postcode":"98664",
    "sg:province":"WA",
    "sg:tags":[
        "residential"
    ],
    "wof:name":"James L Judkins",
    "wof:placetype":"venue"
},
  "geometry": {"coordinates":[-122.56231099999999,45.630992],"type":"Point"}
}