{
  "type": "Feature",
  "properties": {
    "iso:country":"US",
    "sg:address":"112 New Haven Ln",
    "sg:city":"Port Angeles",
    "sg:classifiers":[
        {
            "category":"Professional",
            "type":"Services"
        }
    ],
    "sg:phone":"+1 623 875 5119",
    "sg:postcode":"98362",
    "sg:province":"WA",
    "wof:name":"Art of Bronze",
    "wof:placetype":"venue"
},
  "geometry": {"coordinates":[-123.323364,48.102282],"type":"Point"}
}