{
  "type": "Feature",
  "properties": {
    "addr:full":"1744 Pine Creek Rd Tonasket WA 98855",
    "addr:housenumber":"1744",
    "addr:postcode":"98855",
    "addr:street":"Pine Creek Rd",
    "iso:country":"US",
    "sg:address":"1744 Pine Creek Rd",
    "sg:city":"Tonasket",
    "sg:classifiers":[
        {
            "category":"Manufacturing",
            "subcategory":"Lumber",
            "type":"Manufacturing & Wholesale Goods"
        }
    ],
    "sg:phone":"+1 509 486 2541",
    "sg:postcode":"98855",
    "sg:province":"WA",
    "sg:tags":[
        "logging"
    ],
    "wof:name":"Ayers Logging Inc",
    "wof:placetype":"venue"
},
  "geometry": {"coordinates":[-119.51481800000001,48.65677],"type":"Point"}
}