{
  "type": "Feature",
  "properties": {
    "addr:full":"3496 E Smith Rd Bellingham WA 98226",
    "addr:housenumber":"3496",
    "addr:postcode":"98226",
    "addr:street":"E Smith Rd",
    "iso:country":"US",
    "sg:address":"3496 E Smith Rd",
    "sg:city":"Bellingham",
    "sg:classifiers":[
        {
            "category":"Transit Center",
            "subcategory":"Freight",
            "type":"Transportation"
        }
    ],
    "sg:phone":"+1 360 592 5691",
    "sg:postcode":"98226",
    "sg:province":"WA",
    "sg:tags":[
        "trucking-light",
        "hauling"
    ],
    "wof:name":"Lowboy Specialties Inc",
    "wof:placetype":"venue"
},
  "geometry": {"coordinates":[-122.302076,48.83226],"type":"Point"}
}