{
  "type": "Feature",
  "properties": {
    "iso:country":"US",
    "sg:address":"3650 131st Ave SE",
    "sg:city":"Bellevue",
    "sg:classifiers":[
        {
            "category":"Communications",
            "subcategory":"Radio Station",
            "type":"Services"
        }
    ],
    "sg:phone":"+1 425 373 5545",
    "sg:postcode":"98006",
    "sg:province":"WA",
    "sg:tags":[
        "broadcast"
    ],
    "wof:name":"Krwm Radio 1069",
    "wof:placetype":"venue"
},
  "geometry": {"coordinates":[-122.165963,47.578721],"type":"Point"}
}