{
  "type": "Feature",
  "properties": {
    "addr:full":"409 S Columbia St Wenatchee WA 98801",
    "addr:housenumber":"409",
    "addr:postcode":"98801",
    "addr:street":"S Columbia St",
    "iso:country":"US",
    "sg:address":"409 S Columbia St",
    "sg:city":"Wenatchee",
    "sg:classifiers":[
        {
            "category":"Railroad",
            "type":"Transportation"
        }
    ],
    "sg:phone":"+1 509 664 2222",
    "sg:postcode":"98801",
    "sg:province":"WA",
    "sg:website":"www.bnsf.com",
    "wof:name":"BNSF Railway Co",
    "wof:placetype":"venue"
},
  "geometry": {"coordinates":[-120.305187,47.419031],"type":"Point"}
}