{
  "type": "Feature",
  "properties": {
    "addr:full":"1910 McNair Ave Union Gap WA 98903",
    "addr:housenumber":"1910",
    "addr:postcode":"98903",
    "addr:street":"Mcnair Ave",
    "iso:country":"US",
    "sg:address":"1910 McNair Ave",
    "sg:city":"Union Gap",
    "sg:classifiers":[
        {
            "category":"Freight",
            "type":"Transportation"
        }
    ],
    "sg:phone":"+1 509 575 4665",
    "sg:postcode":"98903",
    "sg:province":"WA",
    "sg:tags":[
        "delivery"
    ],
    "wof:name":"Western Parcel Express",
    "wof:placetype":"venue"
},
  "geometry": {"coordinates":[-120.47260300000001,46.574786],"type":"Point"}
}