{
  "type": "Feature",
  "properties": {
    "addr:full":"4210 B St NW Auburn WA 98001",
    "addr:housenumber":"4210",
    "addr:postcode":"98001",
    "addr:street":"B St Nw",
    "iso:country":"US",
    "sg:address":"4210 B St NW",
    "sg:city":"Auburn",
    "sg:classifiers":[
        {
            "category":"Home & Garden",
            "subcategory":"Building Materials",
            "type":"Retail Goods"
        },
        {
            "category":"Professional",
            "subcategory":"Printing & Photocopies",
            "type":"Services"
        },
        {
            "category":"Manufacturing",
            "subcategory":"Building Materials",
            "type":"Manufacturing & Wholesale Goods"
        },
        {
            "category":"Building & Trades",
            "subcategory":"Locksmith",
            "type":"Services"
        }
    ],
    "sg:phone":"+1 253 520 8008",
    "sg:postcode":"98001",
    "sg:province":"WA",
    "sg:tags":[
        "repair",
        "industrial-sales",
        "door",
        "garage",
        "doors-commercial",
        "opener",
        "device",
        "door-overhead",
        "type",
        "doors-operating"
    ],
    "sg:website":"http://www.wayne-dalton.com/dealeraccess/dealer_detail1.asp?dealerid=756",
    "wof:name":"Wayne-Dalton Genie Sales Center of Seattle",
    "wof:placetype":"venue"
},
  "geometry": {"coordinates":[-122.232331,47.344861],"type":"Point"}
}