{
  "type": "Feature",
  "properties": {
    "addr:full":"127 N 85th St Seattle WA 98103",
    "addr:housenumber":"127",
    "addr:postcode":"98103",
    "addr:street":"N 85Th St",
    "iso:country":"US",
    "sg:address":"127 N 85th St",
    "sg:city":"Seattle",
    "sg:classifiers":[
        {
            "category":"Retail",
            "subcategory":"Photofinishing",
            "type":"Services"
        }
    ],
    "sg:phone":"+1 206 783 5070",
    "sg:postcode":"98103",
    "sg:province":"WA",
    "sg:tags":[
        "photo",
        "finishing"
    ],
    "wof:name":"General Photo",
    "wof:placetype":"venue"
},
  "geometry": {"coordinates":[-122.356882,47.690528],"type":"Point"}
}