{
  "type": "Feature",
  "properties": {
    "addr:full":"191 Cascade Mall Dr Burlington WA 98233",
    "addr:housenumber":"191",
    "addr:postcode":"98233",
    "addr:street":"Cascade Mall Dr",
    "iso:country":"US",
    "sg:address":"191 Cascade Mall Dr",
    "sg:city":"Burlington",
    "sg:classifiers":[
        {
            "category":"Personal",
            "subcategory":"Beauty Salon",
            "type":"Services"
        }
    ],
    "sg:phone":"+1 360 757 2916",
    "sg:postcode":"98233",
    "sg:province":"WA",
    "sg:tags":[
        "shop"
    ],
    "sg:website":"www.greatclips.com",
    "wof:name":"Great Clips",
    "wof:placetype":"venue"
},
  "geometry": {"coordinates":[-122.338769,48.464678],"type":"Point"}
}