{
  "type": "Feature",
  "properties": {
    "addr:full":"8001 NE 8th St Medina WA 98039",
    "addr:housenumber":"8001",
    "addr:postcode":"98039",
    "addr:street":"Ne 8Th St",
    "iso:country":"US",
    "sg:address":"8001 NE 8th St",
    "sg:city":"Medina",
    "sg:classifiers":[
        {
            "category":"Education",
            "subcategory":"School",
            "type":"Public Place"
        }
    ],
    "sg:phone":"+1 425 456 5400",
    "sg:postcode":"98039",
    "sg:province":"WA",
    "sg:tags":[
        "high",
        "middle",
        "elementary"
    ],
    "sg:website":"www.bsd405.org",
    "wof:name":"Bellevue Public Schools District 405",
    "wof:placetype":"venue"
},
  "geometry": {"coordinates":[-122.23200199999999,47.617599],"type":"Point"}
}