{
  "type": "Feature",
  "properties": {
    "addr:full":"1000 Lenora St Seattle WA 98121",
    "addr:housenumber":"1000",
    "addr:postcode":"98121",
    "addr:street":"Lenora St",
    "iso:country":"US",
    "sg:address":"1000 Lenora St",
    "sg:city":"Seattle",
    "sg:classifiers":[
        {
            "category":"Manufacturing",
            "subcategory":"Furniture",
            "type":"Manufacturing & Wholesale Goods"
        }
    ],
    "sg:phone":"+1 206 621 0118",
    "sg:postcode":"98121",
    "sg:province":"WA",
    "wof:name":"Hayes Showroom",
    "wof:placetype":"venue"
},
  "geometry": {"coordinates":[-122.33528099999999,47.618494],"type":"Point"}
}