{
  "type": "Feature",
  "properties": {
    "iso:country":"US",
    "sg:address":"936 Pacific Ave",
    "sg:city":"Tacoma",
    "sg:classifiers":[
        {
            "category":"Real Estate",
            "subcategory":"Developer",
            "type":"Services"
        }
    ],
    "sg:phone":"+1 253 274 9700",
    "sg:postcode":"98402",
    "sg:province":"WA",
    "wof:name":"Metropolitan Development Group",
    "wof:placetype":"venue"
},
  "geometry": {"coordinates":[-122.438997,47.254772],"type":"Point"}
}