{
  "type": "Feature",
  "properties": {
    "addr:full":"1153 3rd Ave Longview WA 98632",
    "addr:housenumber":"1153",
    "addr:postcode":"98632",
    "addr:street":"3Rd Ave",
    "iso:country":"US",
    "sg:address":"1153 3rd Ave",
    "sg:city":"Longview",
    "sg:classifiers":[
        {
            "category":"Social Services",
            "type":"Services"
        }
    ],
    "sg:phone":"+1 360 575 9562",
    "sg:postcode":"98632",
    "sg:province":"WA",
    "wof:name":"The Rock",
    "wof:placetype":"venue"
},
  "geometry": {"coordinates":[-122.92471500000001,46.129617],"type":"Point"}
}