{
  "type": "Feature",
  "properties": {
    "addr:full":"105 Park Dr Everson WA 98247",
    "addr:housenumber":"105",
    "addr:postcode":"98247",
    "addr:street":"Park Dr Everson",
    "iso:country":"US",
    "sg:address":"105 Park Dr",
    "sg:city":"Everson",
    "sg:classifiers":[
        {
            "category":"Government",
            "subcategory":"Office",
            "type":"Public Place"
        }
    ],
    "sg:phone":"+1 360 966 0282",
    "sg:postcode":"98247",
    "sg:province":"WA",
    "sg:tags":[
        "village"
    ],
    "wof:name":"Everson Sewage Treatment Plant",
    "wof:placetype":"venue"
},
  "geometry": {"coordinates":[-122.349881,48.920649],"type":"Point"}
}