{
  "type": "Feature",
  "properties": {
    "addr:full":"10224 7th Ave SW Seattle WA 98146",
    "addr:housenumber":"10224",
    "addr:postcode":"98146",
    "addr:street":"7Th Ave Sw",
    "iso:country":"US",
    "sg:address":"10224 7th Ave SW",
    "sg:city":"Seattle",
    "sg:classifiers":[
        {
            "category":"Professional",
            "type":"Services"
        }
    ],
    "sg:phone":"+1 206 767 7789",
    "sg:postcode":"98146",
    "sg:province":"WA",
    "wof:name":"Yts Inc",
    "wof:placetype":"venue"
},
  "geometry": {"coordinates":[-122.343576,47.51075],"type":"Point"}
}