{
  "type": "Feature",
  "properties": {
    "addr:full":"816 Camano Ave Langley WA 98260",
    "addr:housenumber":"816",
    "addr:postcode":"98260",
    "addr:street":"Camano Ave",
    "iso:country":"US",
    "sg:address":"816 Camano Ave",
    "sg:city":"Langley",
    "sg:classifiers":[
        {
            "category":"Social Services",
            "type":"Services"
        }
    ],
    "sg:phone":"+1 360 221 4767",
    "sg:postcode":"98260",
    "sg:province":"WA",
    "sg:tags":[
        "pregnancy",
        "counseling",
        "information"
    ],
    "wof:name":"Pregnancy Aid Of Whidbey Isle",
    "wof:placetype":"venue"
},
  "geometry": {"coordinates":[-122.40213199999999,48.03322],"type":"Point"}
}