{
  "type": "Feature",
  "properties": {
    "addr:full":"18438 231st Ave SE Maple Valley WA 98038",
    "addr:housenumber":"18438",
    "addr:postcode":"98038",
    "addr:street":"231St Ave Se;Valley",
    "iso:country":"US",
    "sg:address":"18438 231st Ave SE",
    "sg:city":"Maple Valley",
    "sg:classifiers":[
        {
            "category":"Building & Trades",
            "subcategory":"Landscaping Services",
            "type":"Services"
        }
    ],
    "sg:phone":"+1 425 432 2838",
    "sg:postcode":"98038",
    "sg:province":"WA",
    "sg:tags":[
        "landscape",
        "contractor"
    ],
    "wof:name":"Arrow Landscape Company",
    "wof:placetype":"venue"
},
  "geometry": {"coordinates":[-122.033286,47.436151],"type":"Point"}
}