{
  "type": "Feature",
  "properties": {
    "addr:full":"3050 E Ames Lake Dr NE Redmond WA 98053",
    "addr:housenumber":"3050",
    "addr:postcode":"98053",
    "addr:street":"E Ames Lake Dr Ne",
    "iso:country":"US",
    "sg:address":"3050 E Ames Lake Dr NE",
    "sg:city":"Redmond",
    "sg:classifiers":[
        {
            "category":"Community Center",
            "type":"Public Place"
        }
    ],
    "sg:phone":"+1 206 386 2379",
    "sg:postcode":"98053",
    "sg:province":"WA",
    "sg:tags":[
        "medical"
    ],
    "wof:name":"Swedish Medical Center",
    "wof:placetype":"venue"
},
  "geometry": {"coordinates":[-121.959264,47.634912],"type":"Point"}
}