{
  "type": "Feature",
  "properties": {
    "addr:full":"18008 Bellflower Rd Bothell WA 98012",
    "addr:housenumber":"18008",
    "addr:postcode":"98012",
    "addr:street":"Bellflower Rd",
    "iso:country":"US",
    "sg:address":"18008 Bellflower Rd",
    "sg:city":"Bothell",
    "sg:classifiers":[
        {
            "category":"Professional",
            "subcategory":"Business Services",
            "type":"Services"
        }
    ],
    "sg:phone":"+1 425 776 8764",
    "sg:postcode":"98012",
    "sg:province":"WA",
    "wof:name":"Richard & Margaret Middlebrook",
    "wof:placetype":"venue"
},
  "geometry": {"coordinates":[-122.23195200000001,47.834275],"type":"Point"}
}