{
  "type": "Feature",
  "properties": {
    "addr:full":"216 S Cambrian Ave Bremerton WA 98312",
    "addr:housenumber":"216",
    "addr:postcode":"98312",
    "addr:street":"S Cambrian Ave",
    "iso:country":"US",
    "sg:address":"216 S Cambrian Ave",
    "sg:city":"Bremerton",
    "sg:classifiers":[
        {
            "category":"Building & Trades",
            "subcategory":"Construction",
            "type":"Services"
        }
    ],
    "sg:phone":"+1 360 479 2032",
    "sg:postcode":"98312",
    "sg:province":"WA",
    "sg:tags":[
        "contractor"
    ],
    "wof:name":"T R Freeman",
    "wof:placetype":"venue"
},
  "geometry": {"coordinates":[-122.655441,47.560403],"type":"Point"}
}