{
  "type": "Feature",
  "properties": {
    "addr:full":"663 Burchett Rd Onalaska WA 98570",
    "addr:housenumber":"663",
    "addr:postcode":"98570",
    "addr:street":"Burchett Rd",
    "iso:country":"US",
    "sg:address":"663 Burchett Rd",
    "sg:city":"Onalaska",
    "sg:classifiers":[
        {
            "category":"Farming",
            "subcategory":"Dairy Farm",
            "type":"Manufacturing & Wholesale Goods"
        }
    ],
    "sg:phone":"+1 360 985 2675",
    "sg:postcode":"98570",
    "sg:province":"WA",
    "wof:name":"Violet Anderson",
    "wof:placetype":"venue"
},
  "geometry": {"coordinates":[-122.713294,46.561137],"type":"Point"}
}