{
  "type": "Feature",
  "properties": {
    "addr:full":"1764 NW 56th St Seattle WA 98107",
    "addr:housenumber":"1764",
    "addr:postcode":"98107",
    "addr:street":"Nw 56Th St",
    "iso:country":"US",
    "sg:address":"1764 NW 56th St",
    "sg:city":"Seattle",
    "sg:classifiers":[
        {
            "category":"Shopping",
            "subcategory":"Shoes",
            "type":"Retail Goods"
        }
    ],
    "sg:phone":"+1 206 781 2645",
    "sg:postcode":"98107",
    "sg:province":"WA",
    "wof:name":"Dr Z Coil",
    "wof:placetype":"venue"
},
  "geometry": {"coordinates":[-122.38165600000001,47.669523],"type":"Point"}
}