{
  "type": "Feature",
  "properties": {
    "addr:full":"803 36th Ave E Seattle WA 98112",
    "addr:housenumber":"803",
    "addr:postcode":"98112",
    "addr:street":"36Th Ave E",
    "iso:country":"US",
    "sg:address":"803 36th Ave E",
    "sg:city":"Seattle",
    "sg:classifiers":[
        {
            "category":"Professional",
            "subcategory":"Research",
            "type":"Services"
        }
    ],
    "sg:phone":"+1 206 322 0522",
    "sg:postcode":"98112",
    "sg:province":"WA",
    "sg:tags":[
        "economic",
        "analysis"
    ],
    "wof:name":"Watterson West Group Inc",
    "wof:placetype":"venue"
},
  "geometry": {"coordinates":[-122.28688,47.626172],"type":"Point"}
}