{
  "type": "Feature",
  "properties": {
    "addr:full":"151 S Worthen St Wenatchee WA 98801",
    "addr:housenumber":"151",
    "addr:postcode":"98801",
    "addr:street":"S Worthen St",
    "iso:country":"US",
    "sg:address":"151 S Worthen St",
    "sg:city":"Wenatchee",
    "sg:classifiers":[
        {
            "category":"Utilities",
            "subcategory":"Mobile Phone",
            "type":"Services"
        }
    ],
    "sg:phone":"+1 509 664 6600",
    "sg:postcode":"98801",
    "sg:province":"WA",
    "sg:tags":[
        "communication",
        "radiotelephone",
        "merchandise"
    ],
    "wof:name":"Verizon",
    "wof:placetype":"venue"
},
  "geometry": {"coordinates":[-120.304985,47.421888],"type":"Point"}
}