{
  "type": "Feature",
  "properties": {
    "addr:full":"1060 SW 20th St Chehalis WA 98532",
    "addr:housenumber":"1060",
    "addr:postcode":"98532",
    "addr:street":"Sw 20Th St",
    "iso:country":"US",
    "sg:address":"1060 SW 20th St",
    "sg:city":"Chehalis",
    "sg:classifiers":[
        {
            "category":"Autos & Motor Vehicles",
            "subcategory":"Automobile Sales",
            "type":"Retail Goods"
        }
    ],
    "sg:phone":"+1 360 748 1330",
    "sg:postcode":"98532",
    "sg:province":"WA",
    "sg:tags":[
        "school"
    ],
    "wof:name":"Chehalis Middle School",
    "wof:placetype":"venue"
},
  "geometry": {"coordinates":[-122.941789,46.643232],"type":"Point"}
}