{
  "type": "Feature",
  "properties": {
    "addr:full":"126 W Canyonview Dr Longview WA 98632",
    "addr:housenumber":"126",
    "addr:postcode":"98632",
    "addr:street":"W Canyonview Dr",
    "iso:country":"US",
    "sg:address":"126 W Canyonview Dr",
    "sg:city":"Longview",
    "sg:classifiers":[
        {
            "category":"Shopping",
            "subcategory":"Clothing, Apparel, & Fashions",
            "type":"Retail Goods"
        }
    ],
    "sg:phone":"+1 360 575 9943",
    "sg:postcode":"98632",
    "sg:province":"WA",
    "sg:tags":[
        "leather"
    ],
    "wof:name":"Leather Source",
    "wof:placetype":"venue"
},
  "geometry": {"coordinates":[-122.93189,46.1604],"type":"Point"}
}