{
  "type": "Feature",
  "properties": {
    "addr:full":"3800 Old Lewis River Rd Woodland WA 98674",
    "addr:housenumber":"3800",
    "addr:postcode":"98674",
    "addr:street":"Old Lewis River Rd",
    "iso:country":"US",
    "sg:address":"3800 Old Lewis River Rd",
    "sg:city":"Woodland",
    "sg:classifiers":[
        {
            "category":"Real Estate",
            "subcategory":"Developer",
            "type":"Services"
        }
    ],
    "sg:phone":"+1 360 225 9994",
    "sg:postcode":"98674",
    "sg:province":"WA",
    "sg:tags":[
        "cemetery"
    ],
    "wof:name":"Cemetery District No 2",
    "wof:placetype":"venue"
},
  "geometry": {"coordinates":[-122.633833,45.938413],"type":"Point"}
}