{
  "type": "Feature",
  "properties": {
    "addr:full":"1403 E Washington Ave Yakima WA 98903",
    "addr:housenumber":"1403",
    "addr:postcode":"98903",
    "addr:street":"E Washington Ave",
    "iso:country":"US",
    "sg:address":"1403 E Washington Ave",
    "sg:city":"Yakima",
    "sg:classifiers":[
        {
            "category":"Shopping",
            "type":"Retail Goods"
        }
    ],
    "sg:phone":"+1 509 469 9933",
    "sg:postcode":"98903",
    "sg:province":"WA",
    "sg:tags":[
        "merchandise",
        "animal"
    ],
    "wof:name":"Petsmart",
    "wof:placetype":"venue"
},
  "geometry": {"coordinates":[-120.477772,46.570442],"type":"Point"}
}