{
  "type": "Feature",
  "properties": {
    "addr:full":"1214 McCormick St SE Olympia WA 98501",
    "addr:housenumber":"1214",
    "addr:postcode":"98501",
    "addr:street":"Mccormick St Se",
    "iso:country":"US",
    "sg:address":"1214 McCormick St SE",
    "sg:city":"Olympia",
    "sg:classifiers":[
        {
            "category":"Professional",
            "subcategory":"Management & Consulting",
            "type":"Services"
        }
    ],
    "sg:phone":"+1 360 754 1123",
    "sg:postcode":"98501",
    "sg:province":"WA",
    "sg:tags":[
        "environmental",
        "construction"
    ],
    "wof:name":"Conrex Inc",
    "wof:placetype":"venue"
},
  "geometry": {"coordinates":[-122.879063,47.037663],"type":"Point"}
}