{
  "type": "Feature",
  "properties": {
    "addr:full":"3214 W Mcgraw St Seattle WA 98199",
    "addr:housenumber":"3214",
    "addr:postcode":"98199",
    "addr:street":"W Mcgraw St",
    "iso:country":"US",
    "sg:address":"3214 W Mcgraw St",
    "sg:city":"Seattle",
    "sg:classifiers":[
        {
            "category":"Insurance",
            "subcategory":"Insurance Agent",
            "type":"Services"
        },
        {
            "category":"Insurance",
            "subcategory":"Hazard Insurance",
            "type":"Services"
        },
        {
            "category":"Insurance",
            "subcategory":"Title Insurance",
            "type":"Services"
        },
        {
            "category":"Insurance",
            "subcategory":"Life Insurance",
            "type":"Services"
        }
    ],
    "sg:phone":"+1 206 281 7087",
    "sg:postcode":"98199",
    "sg:province":"WA",
    "sg:tags":[
        "business",
        "auto",
        "commercial",
        "homeowner",
        "motorcycle",
        "renter"
    ],
    "wof:name":"Allstate Insurance Company - John Davis",
    "wof:placetype":"venue"
},
  "geometry": {"coordinates":[-122.39855300000001,47.639568],"type":"Point"}
}