{
  "type": "Feature",
  "properties": {
    "addr:full":"8714 27th Ave NE Tulalip WA 98271",
    "addr:housenumber":"8714",
    "addr:postcode":"98271",
    "addr:street":"27Th Ave Ne",
    "iso:country":"US",
    "sg:address":"8714 27th Ave NE",
    "sg:city":"Tulalip",
    "sg:classifiers":[
        {
            "category":"Manufacturing",
            "subcategory":"Tools & Machinery",
            "type":"Manufacturing & Wholesale Goods"
        }
    ],
    "sg:phone":"+1 360 691 5305",
    "sg:postcode":"98271",
    "sg:province":"WA",
    "sg:tags":[
        "machine",
        "shop"
    ],
    "wof:name":"Ross Manufacturing",
    "wof:placetype":"venue"
},
  "geometry": {"coordinates":[-122.19481500000001,48.074697],"type":"Point"}
}