{
  "type": "Feature",
  "properties": {
    "addr:full":"2720 Thompson Rd Langley WA 98260",
    "addr:housenumber":"2720",
    "addr:postcode":"98260",
    "addr:street":"Thompson Rd",
    "iso:country":"US",
    "sg:address":"2720 Thompson Rd",
    "sg:city":"Langley",
    "sg:classifiers":[
        {
            "category":"Farming",
            "subcategory":"Farm",
            "type":"Manufacturing & Wholesale Goods"
        }
    ],
    "sg:phone":"+1 360 321 5220",
    "sg:postcode":"98260",
    "sg:province":"WA",
    "wof:name":"High Country Farm",
    "wof:placetype":"venue"
},
  "geometry": {"coordinates":[-122.47311000000001,48.012306],"type":"Point"}
}