{
  "type": "Feature",
  "properties": {
    "addr:full":"13427 Kellogg Lake Rd Sultan WA 98294",
    "addr:housenumber":"13427",
    "addr:postcode":"98294",
    "addr:street":"Kellogg Lake Rd",
    "iso:country":"US",
    "sg:address":"13427 Kellogg Lake Rd",
    "sg:city":"Sultan",
    "sg:classifiers":[
        {
            "category":"Building & Trades",
            "subcategory":"Cleaning & Sanitation",
            "type":"Services"
        }
    ],
    "sg:phone":"+1 360 793 2087",
    "sg:postcode":"98294",
    "sg:province":"WA",
    "sg:tags":[
        "maintenance"
    ],
    "wof:name":"Scrub Right Cleaning",
    "wof:placetype":"venue"
},
  "geometry": {"coordinates":[-121.734628,47.87672],"type":"Point"}
}