{
  "type": "Feature",
  "properties": {
    "addr:full":"8409 272nd Avenue Ct E Buckley WA 98321",
    "addr:housenumber":"8409",
    "addr:postcode":"98321",
    "addr:street":"272Nd Avenue Ct E",
    "iso:country":"US",
    "sg:address":"8409 272nd Avenue Ct E",
    "sg:city":"Buckley",
    "sg:classifiers":[
        {
            "category":"Shopping",
            "subcategory":"Used Merchandise",
            "type":"Retail Goods"
        }
    ],
    "sg:phone":"+1 360 829 0943",
    "sg:postcode":"98321",
    "sg:province":"WA",
    "wof:name":"Silver Lining Antiques",
    "wof:placetype":"venue"
},
  "geometry": {"coordinates":[-122.065985,47.179547],"type":"Point"}
}