{
  "type": "Feature",
  "properties": {
    "addr:full":"20321 22nd Ave E Spanaway WA 98387",
    "addr:housenumber":"20321",
    "addr:postcode":"98387",
    "addr:street":"22Nd Ave E",
    "iso:country":"US",
    "sg:address":"20321 22nd Ave E",
    "sg:city":"Spanaway",
    "sg:classifiers":[
        {
            "category":"Health Services",
            "subcategory":"Health Practitioner",
            "type":"Services"
        }
    ],
    "sg:phone":"+1 253 847 7044",
    "sg:postcode":"98387",
    "sg:province":"WA",
    "wof:name":"Earl Olson Lmp",
    "wof:placetype":"venue"
},
  "geometry": {"coordinates":[-122.400447,47.072556],"type":"Point"}
}