{
  "type": "Feature",
  "properties": {
    "addr:full":"910 Black Lake Blvd SW Olympia WA 98502",
    "addr:housenumber":"910",
    "addr:postcode":"98502",
    "addr:street":"Black Lake Blvd Sw",
    "iso:country":"US",
    "sg:address":"910 Black Lake Blvd SW",
    "sg:city":"Olympia",
    "sg:classifiers":[
        {
            "category":"Banks & Credit Unions",
            "subcategory":"Bank",
            "type":"Services"
        }
    ],
    "sg:phone":"+1 360 754 3630",
    "sg:postcode":"98502",
    "sg:province":"WA",
    "sg:tags":[
        "national",
        "commercial"
    ],
    "wof:name":"Bank of America",
    "wof:placetype":"venue"
},
  "geometry": {"coordinates":[-122.934658,47.037436],"type":"Point"}
}