{
  "type": "Feature",
  "properties": {
    "addr:full":"9918 E 9th Ave Spokane WA 99206",
    "addr:housenumber":"9918",
    "addr:postcode":"99206",
    "addr:street":"E 9Th Ave",
    "iso:country":"US",
    "sg:address":"9918 E 9th Ave",
    "sg:city":"Spokane",
    "sg:classifiers":[
        {
            "category":"Building & Trades",
            "subcategory":"Construction",
            "type":"Services"
        }
    ],
    "sg:phone":"+1 509 921 6463",
    "sg:postcode":"99206",
    "sg:province":"WA",
    "sg:tags":[
        "concrete",
        "contractor"
    ],
    "wof:name":"Bonnett Concrete",
    "wof:placetype":"venue"
},
  "geometry": {"coordinates":[-117.270802,47.64869],"type":"Point"}
}