{
  "type": "Feature",
  "properties": {
    "addr:full":"6026 142nd Ct NE Redmond WA 98052",
    "addr:housenumber":"6026",
    "addr:postcode":"98052",
    "addr:street":"142Nd Ct Ne",
    "iso:country":"US",
    "sg:address":"6026 142nd Ct NE",
    "sg:city":"Redmond",
    "sg:classifiers":[
        {
            "category":"Professional",
            "type":"Services"
        }
    ],
    "sg:phone":"+1 425 882 0666",
    "sg:postcode":"98052",
    "sg:province":"WA",
    "wof:name":"Chinese Acupuncture Center LLC",
    "wof:placetype":"venue"
},
  "geometry": {"coordinates":[-122.150993,47.660786],"type":"Point"}
}