{
  "type": "Feature",
  "properties": {
    "addr:full":"1634 77th Ave NE Medina WA 98039",
    "addr:housenumber":"1634",
    "addr:postcode":"98039",
    "addr:street":"77Th Ave Ne Medina",
    "iso:country":"US",
    "sg:address":"1634 77th Ave NE",
    "sg:city":"Medina",
    "sg:classifiers":[
        {
            "category":"Professional",
            "subcategory":"Management & Consulting",
            "type":"Services"
        }
    ],
    "sg:phone":"+1 206 321 2727",
    "sg:postcode":"98039",
    "sg:province":"WA",
    "sg:tags":[
        "business"
    ],
    "wof:name":"Joseph Okonek & Associates",
    "wof:placetype":"venue"
},
  "geometry": {"coordinates":[-122.237234,47.629157],"type":"Point"}
}