{
  "type": "Feature",
  "properties": {
    "addr:full":"3980 Grandview Rd Ferndale WA 98248",
    "addr:housenumber":"3980",
    "addr:postcode":"98248",
    "addr:street":"Grandview Rd",
    "iso:country":"US",
    "sg:address":"3980 Grandview Rd",
    "sg:city":"Ferndale",
    "sg:classifiers":[
        {
            "category":"Manufacturing",
            "subcategory":"Metals",
            "type":"Manufacturing & Wholesale Goods"
        }
    ],
    "sg:phone":"+1 360 366 9360",
    "sg:postcode":"98248",
    "sg:province":"WA",
    "sg:tags":[
        "fabricator",
        "aluminum"
    ],
    "wof:name":"Master Marine Prod & Altech",
    "wof:placetype":"venue"
},
  "geometry": {"coordinates":[-122.680126,48.892111],"type":"Point"}
}