{
  "type": "Feature",
  "properties": {
    "addr:full":"69 Chase Ave Manson WA 98831",
    "addr:housenumber":"69",
    "addr:postcode":"98831",
    "addr:street":"Chase Ave",
    "iso:country":"US",
    "sg:address":"69 Chase Ave",
    "sg:city":"Manson",
    "sg:classifiers":[
        {
            "category":"Autos & Motor Vehicles",
            "subcategory":"Automobile Sales",
            "type":"Retail Goods"
        }
    ],
    "sg:phone":"+1 509 687 8088",
    "sg:postcode":"98831",
    "sg:province":"WA",
    "sg:tags":[
        "performance",
        "race",
        "dealer"
    ],
    "wof:name":"Wild Nights Racing",
    "wof:placetype":"venue"
},
  "geometry": {"coordinates":[-120.16281600000001,47.890013],"type":"Point"}
}