{
  "type": "Feature",
  "properties": {
    "addr:full":"24211 Timber Ln Edmonds WA 98020",
    "addr:housenumber":"24211",
    "addr:postcode":"98020",
    "addr:street":"Timber Ln",
    "iso:country":"US",
    "sg:address":"24211 Timber Ln",
    "sg:city":"Edmonds",
    "sg:classifiers":[
        {
            "category":"Autos & Motor Vehicles",
            "subcategory":"Automobile Sales",
            "type":"Retail Goods"
        }
    ],
    "sg:phone":"+1 206 459 2294",
    "sg:postcode":"98020",
    "sg:province":"WA",
    "sg:tags":[
        "used"
    ],
    "wof:name":"Beltsinvest USA Inc",
    "wof:placetype":"venue"
},
  "geometry": {"coordinates":[-122.382801,47.779708],"type":"Point"}
}