{
  "type": "Feature",
  "properties": {
    "addr:full":"425 16th St Bellingham WA 98225",
    "addr:housenumber":"425",
    "addr:postcode":"98225",
    "addr:street":"16Th St",
    "iso:country":"US",
    "sg:address":"425 16th St",
    "sg:city":"Bellingham",
    "sg:classifiers":[
        {
            "category":"Professional",
            "subcategory":"Business Services",
            "type":"Services"
        },
        {
            "category":"Building & Trades",
            "subcategory":"Construction",
            "type":"Services"
        }
    ],
    "sg:phone":"+1 360 752 1269",
    "sg:postcode":"98225",
    "sg:province":"WA",
    "sg:tags":[
        "house",
        "general",
        "contractor"
    ],
    "wof:name":"Nicksic Construction Inc",
    "wof:placetype":"venue"
},
  "geometry": {"coordinates":[-122.497113,48.731145],"type":"Point"}
}