{
  "type": "Feature",
  "properties": {
    "addr:full":"1049 SE City Beach St Oak Harbor WA 98277",
    "addr:housenumber":"1049",
    "addr:postcode":"98277",
    "addr:street":"Se City;St",
    "iso:country":"US",
    "sg:address":"1049 SE City Beach St",
    "sg:city":"Oak Harbor",
    "sg:classifiers":[
        {
            "category":"Health Services",
            "subcategory":"Doctor",
            "type":"Services"
        }
    ],
    "sg:phone":"+1 360 675 7678",
    "sg:postcode":"98277",
    "sg:province":"WA",
    "sg:tags":[
        "physician",
        "surgeon"
    ],
    "wof:name":"Oak Harbor Internal Medicine",
    "wof:placetype":"venue"
},
  "geometry": {"coordinates":[-122.653434,48.289476],"type":"Point"}
}