{
  "type": "Feature",
  "properties": {
    "addr:full":"270 Brown Rd Ellensburg WA 98926",
    "addr:housenumber":"270",
    "addr:postcode":"98926",
    "addr:street":"Brown Rd",
    "iso:country":"US",
    "sg:address":"270 Brown Rd",
    "sg:city":"Ellensburg",
    "sg:classifiers":[
        {
            "category":"Freight",
            "type":"Transportation"
        }
    ],
    "sg:phone":"+1 509 962 2712",
    "sg:postcode":"98926",
    "sg:province":"WA",
    "sg:tags":[
        "operator",
        "local",
        "trucking"
    ],
    "wof:name":"Robert Gordon",
    "wof:placetype":"venue"
},
  "geometry": {"coordinates":[-120.59836199999999,47.001654],"type":"Point"}
}