{
  "type": "Feature",
  "properties": {
    "addr:full":"2615 Simpson Ave Aberdeen WA 98520",
    "addr:housenumber":"2615",
    "addr:postcode":"98520",
    "addr:street":"Simpson Ave",
    "iso:country":"US",
    "sg:address":"2615 Simpson Ave",
    "sg:city":"Aberdeen",
    "sg:classifiers":[
        {
            "category":"Retail",
            "subcategory":"Car Wash",
            "type":"Services"
        }
    ],
    "sg:phone":"+1 360 533 8081",
    "sg:postcode":"98520",
    "sg:province":"WA",
    "sg:tags":[
        "carwash",
        "consulting",
        "business"
    ],
    "wof:name":"Gull Car Wash",
    "wof:placetype":"venue"
},
  "geometry": {"coordinates":[-123.850116,46.975039],"type":"Point"}
}