{
  "type": "Feature",
  "properties": {
    "addr:full":"3721 Kitsap Way Bremerton WA 98312",
    "addr:housenumber":"3721",
    "addr:postcode":"98312",
    "addr:street":"Kitsap Way",
    "iso:country":"US",
    "sg:address":"3721 Kitsap Way",
    "sg:city":"Bremerton",
    "sg:classifiers":[
        {
            "category":"Utilities",
            "subcategory":"Mobile Phone",
            "type":"Services"
        }
    ],
    "sg:phone":"+1 253 853 5300",
    "sg:postcode":"98312",
    "sg:province":"WA",
    "sg:tags":[
        "telephone",
        "cellular"
    ],
    "wof:name":"Complete Wireless Ctr",
    "wof:placetype":"venue"
},
  "geometry": {"coordinates":[-122.66437999999999,47.570355],"type":"Point"}
}