{
  "type": "Feature",
  "properties": {
    "iso:country":"US",
    "sg:address":"4005 20th Ave W",
    "sg:city":"Seattle",
    "sg:classifiers":[
        {
            "category":"Insurance",
            "subcategory":"Insurance Agent",
            "type":"Services"
        }
    ],
    "sg:phone":"+1 206 217 0033",
    "sg:postcode":"98199",
    "sg:province":"WA",
    "sg:tags":[
        "agency"
    ],
    "sg:website":"www.hortonmarine.com",
    "wof:name":"Eugene Horton & Associates",
    "wof:placetype":"venue"
},
  "geometry": {"coordinates":[-122.381208,47.655028],"type":"Point"}
}