{
  "type": "Feature",
  "properties": {
    "addr:full":"9511 Silverdale Way NW Silverdale WA 98383",
    "addr:housenumber":"9511",
    "addr:postcode":"98383",
    "addr:street":"Silverdale Way Nw",
    "iso:country":"US",
    "sg:address":"9511 Silverdale Way NW",
    "sg:city":"Silverdale",
    "sg:classifiers":[
        {
            "category":"Retail",
            "subcategory":"Self-service Laundry",
            "type":"Services"
        }
    ],
    "sg:phone":"+1 360 509 0117",
    "sg:postcode":"98383",
    "sg:province":"WA",
    "wof:name":"Sudseez Inc",
    "wof:placetype":"venue"
},
  "geometry": {"coordinates":[-122.69537200000001,47.648823],"type":"Point"}
}