{
  "type": "Feature",
  "properties": {
    "iso:country":"US",
    "sg:address":"2513 Victor St",
    "sg:city":"Bellingham",
    "sg:classifiers":[
        {
            "category":"Wholesale",
            "subcategory":"Machinery & Supplies",
            "type":"Manufacturing & Wholesale Goods"
        }
    ],
    "sg:phone":"+1 360 733 0093",
    "sg:postcode":"98225",
    "sg:province":"WA",
    "sg:tags":[
        "equipment",
        "industrial"
    ],
    "wof:name":"Michael Flaherty Woodwork",
    "wof:placetype":"venue"
},
  "geometry": {"coordinates":[-122.495322,48.764266],"type":"Point"}
}