{
  "type": "Feature",
  "properties": {
    "addr:full":"2932 142nd Ave E Sumner WA 98390",
    "addr:housenumber":"2932",
    "addr:postcode":"98390",
    "addr:street":"142Nd Ave E",
    "iso:country":"US",
    "sg:address":"2932 142nd Ave E",
    "sg:city":"Sumner",
    "sg:classifiers":[
        {
            "category":"Professional",
            "subcategory":"Employment Agencies",
            "type":"Services"
        }
    ],
    "sg:phone":"+1 253 446 3032",
    "sg:postcode":"98390",
    "sg:province":"WA",
    "sg:tags":[
        "help",
        "supply"
    ],
    "wof:name":"Adecco Staffing",
    "wof:placetype":"venue"
},
  "geometry": {"coordinates":[-122.24006199999999,47.22863],"type":"Point"}
}