{
  "type": "Feature",
  "properties": {
    "addr:full":"7009 California Ave SW Seattle WA 98136",
    "addr:housenumber":"7009",
    "addr:postcode":"98136",
    "addr:street":"California Ave Sw",
    "iso:country":"US",
    "sg:address":"7009 California Ave SW",
    "sg:city":"Seattle",
    "sg:classifiers":[
        {
            "category":"Shopping",
            "subcategory":"Gifts & Souvenirs",
            "type":"Retail Goods"
        }
    ],
    "sg:phone":"+1 206 938 3469",
    "sg:postcode":"98136",
    "sg:province":"WA",
    "sg:tags":[
        "balloon",
        "artist"
    ],
    "wof:name":"Helium Roses",
    "wof:placetype":"venue"
},
  "geometry": {"coordinates":[-122.387345,47.539962],"type":"Point"}
}