{
  "type": "Feature",
  "properties": {
    "addr:full":"17723 NE 192nd Ave Brush Prairie WA 98606",
    "addr:housenumber":"17723",
    "addr:postcode":"98606",
    "addr:street":"Ne 192Nd Ave",
    "iso:country":"US",
    "sg:address":"17723 NE 192nd Ave",
    "sg:city":"Brush Prairie",
    "sg:classifiers":[
        {
            "category":"Building & Trades",
            "subcategory":"Construction",
            "type":"Services"
        }
    ],
    "sg:phone":"+1 360 256 7716",
    "sg:postcode":"98606",
    "sg:province":"WA",
    "sg:tags":[
        "house"
    ],
    "wof:name":"Custom Builders Northwest Inc",
    "wof:placetype":"venue"
},
  "geometry": {"coordinates":[-122.476208,45.748933],"type":"Point"}
}