{
  "type": "Feature",
  "properties": {
    "addr:full":"1009 4th Ave E Olympia WA 98506",
    "addr:housenumber":"1009",
    "addr:postcode":"98506",
    "addr:street":"4Th Ave E",
    "iso:country":"US",
    "sg:address":"1009 4th Ave E",
    "sg:city":"Olympia",
    "sg:classifiers":[
        {
            "category":"Recreation",
            "type":"Entertainment"
        }
    ],
    "sg:phone":"+1 360 753 0772",
    "sg:postcode":"98506",
    "sg:province":"WA",
    "sg:tags":[
        "instruction",
        "yoga"
    ],
    "sg:website":"www.olyyoga.com",
    "wof:name":"Olympia Yoga Center",
    "wof:placetype":"venue"
},
  "geometry": {"coordinates":[-122.888603,47.045709],"type":"Point"}
}