{
  "type": "Feature",
  "properties": {
    "addr:full":"318 W 8th St Port Angeles WA 98362",
    "addr:housenumber":"318",
    "addr:postcode":"98362",
    "addr:street":"W 8Th St",
    "iso:country":"US",
    "sg:address":"318 W 8th St",
    "sg:city":"Port Angeles",
    "sg:classifiers":[
        {
            "category":"Social Services",
            "type":"Services"
        }
    ],
    "sg:phone":"+1 360 457 0201",
    "sg:postcode":"98362",
    "sg:province":"WA",
    "sg:tags":[
        "organization",
        "welfare"
    ],
    "wof:name":"Frichette Associates",
    "wof:placetype":"venue"
},
  "geometry": {"coordinates":[-123.444749,48.115164],"type":"Point"}
}