{
  "type": "Feature",
  "properties": {
    "addr:full":"8063 Hwy 10 Ellensburg WA 98926",
    "addr:housenumber":"8063",
    "addr:postcode":"98926",
    "addr:street":"Hwy 10",
    "iso:country":"US",
    "sg:address":"8063 Hwy 10",
    "sg:city":"Ellensburg",
    "sg:classifiers":[
        {
            "category":"Utilities",
            "subcategory":"Water",
            "type":"Services"
        }
    ],
    "sg:phone":"+1 509 962 9583",
    "sg:postcode":"98926",
    "sg:province":"WA",
    "sg:tags":[
        "company",
        "sewage"
    ],
    "wof:name":"Cascade Irrigation Dist",
    "wof:placetype":"venue"
},
  "geometry": {"coordinates":[-120.648222,47.061869],"type":"Point"}
}