{
  "type": "Feature",
  "properties": {
    "addr:full":"522 E Market St Aberdeen WA 98520",
    "addr:housenumber":"522",
    "addr:postcode":"98520",
    "addr:street":"E Market St",
    "iso:country":"US",
    "sg:address":"522 E Market St",
    "sg:city":"Aberdeen",
    "sg:classifiers":[
        {
            "category":"Building & Trades",
            "subcategory":"Construction",
            "type":"Services"
        }
    ],
    "sg:phone":"+1 360 532 7335",
    "sg:postcode":"98520",
    "sg:province":"WA",
    "sg:tags":[
        "roofing",
        "contractor"
    ],
    "wof:name":"A 1 Roofing",
    "wof:placetype":"venue"
},
  "geometry": {"coordinates":[-123.813104,46.978031],"type":"Point"}
}