{
  "type": "Feature",
  "properties": {
    "addr:full":"300 S Grand Ave Pullman WA 99163",
    "addr:housenumber":"300",
    "addr:postcode":"99163",
    "addr:street":"S Grand Ave",
    "iso:country":"US",
    "sg:address":"300 S Grand Ave",
    "sg:city":"Pullman",
    "sg:classifiers":[
        {
            "category":"Bars & Pubs",
            "type":"Food & Drink"
        },
        {
            "category":"Restaurant",
            "type":"Food & Drink"
        }
    ],
    "sg:phone":"+1 509 334 0477",
    "sg:postcode":"99163",
    "sg:province":"WA",
    "sg:tags":[
        "thai",
        "asian",
        "pan"
    ],
    "wof:name":"Thai Ginger Restaurant & Bar",
    "wof:placetype":"venue"
},
  "geometry": {"coordinates":[-117.183159,46.728359],"type":"Point"}
}