{
  "type": "Feature",
  "properties": {
    "addr:full":"1919 Yelm Hwy SE Olympia WA 98501",
    "addr:housenumber":"1919",
    "addr:postcode":"98501",
    "addr:street":"Yelm Hwy Se",
    "iso:country":"US",
    "sg:address":"1919 Yelm Hwy SE",
    "sg:city":"Olympia",
    "sg:classifiers":[
        {
            "category":"Building & Trades",
            "subcategory":"Landscaping Services",
            "type":"Services"
        }
    ],
    "sg:phone":"+1 360 705 1435",
    "sg:postcode":"98501",
    "sg:province":"WA",
    "sg:tags":[
        "tree",
        "gardener"
    ],
    "wof:name":"Tree Movers Nw Inc",
    "wof:placetype":"venue"
},
  "geometry": {"coordinates":[-122.874639,47.003589],"type":"Point"}
}