{
  "type": "Feature",
  "properties": {
    "addr:full":"148 SW 152nd St Seattle WA 98166",
    "addr:housenumber":"148",
    "addr:postcode":"98166",
    "addr:street":"Sw 152Nd St",
    "iso:country":"US",
    "sg:address":"148 SW 152nd St",
    "sg:city":"Seattle",
    "sg:classifiers":[
        {
            "category":"Wholesale",
            "subcategory":"Seafood",
            "type":"Manufacturing & Wholesale Goods"
        }
    ],
    "sg:phone":"+1 206 909 1912",
    "sg:postcode":"98166",
    "sg:province":"WA",
    "wof:name":"Annies Fish Bar & Seafoods",
    "wof:placetype":"venue"
},
  "geometry": {"coordinates":[-122.336029,47.466947],"type":"Point"}
}