{
  "type": "Feature",
  "properties": {
    "addr:full":"351 Pease Rd Burlington WA 98233",
    "addr:housenumber":"351",
    "addr:postcode":"98233",
    "addr:street":"Pease Rd",
    "iso:country":"US",
    "sg:address":"351 Pease Rd",
    "sg:city":"Burlington",
    "sg:classifiers":[
        {
            "category":"Restaurant",
            "type":"Food & Drink"
        }
    ],
    "sg:phone":"+1 360 757 1015",
    "sg:postcode":"98233",
    "sg:province":"WA",
    "sg:tags":[
        "shop",
        "coffee"
    ],
    "wof:name":"Common Ground Coffee House",
    "wof:placetype":"venue"
},
  "geometry": {"coordinates":[-122.330512,48.457295],"type":"Point"}
}