{
  "type": "Feature",
  "properties": {
    "addr:full":"717 S 219th St Des Moines WA 98198",
    "addr:housenumber":"717",
    "addr:postcode":"98198",
    "addr:street":"S 219Th St",
    "iso:country":"US",
    "sg:address":"717 S 219th St",
    "sg:city":"Des Moines",
    "sg:classifiers":[
        {
            "category":"Personal",
            "subcategory":"Beauty Salon",
            "type":"Services"
        }
    ],
    "sg:phone":"+1 206 824 6606",
    "sg:postcode":"98198",
    "sg:province":"WA",
    "wof:name":"Fresh Look Hair Salon",
    "wof:placetype":"venue"
},
  "geometry": {"coordinates":[-122.324927,47.405718],"type":"Point"}
}