{
  "type": "Feature",
  "properties": {
    "addr:full":"2249 Schaefer Dr Clarkston WA 99403",
    "addr:housenumber":"2249",
    "addr:postcode":"99403",
    "addr:street":"Schaefer Dr",
    "iso:country":"US",
    "sg:address":"2249 Schaefer Dr",
    "sg:city":"Clarkston",
    "sg:classifiers":[
        {
            "category":"Retail",
            "subcategory":"Repair Shop",
            "type":"Services"
        }
    ],
    "sg:phone":"+1 509 758 6477",
    "sg:postcode":"99403",
    "sg:province":"WA",
    "wof:name":"Jane Herwegh Museum Services",
    "wof:placetype":"venue"
},
  "geometry": {"coordinates":[-117.05582,46.3863],"type":"Point"}
}