{
  "type": "Feature",
  "properties": {
    "addr:full":"6209 92nd St SW Mukilteo WA 98275",
    "addr:housenumber":"6209",
    "addr:postcode":"98275",
    "addr:street":"92Nd St Sw",
    "iso:country":"US",
    "sg:address":"6209 92nd St SW",
    "sg:city":"Mukilteo",
    "sg:classifiers":[
        {
            "category":"Health Services",
            "subcategory":"Doctor",
            "type":"Services"
        }
    ],
    "sg:phone":"+1 425 348 9151",
    "sg:postcode":"98275",
    "sg:province":"WA",
    "sg:tags":[
        "dentist"
    ],
    "wof:name":"Oliver William DDS Msd",
    "wof:placetype":"venue"
},
  "geometry": {"coordinates":[-122.317806,47.914868],"type":"Point"}
}