{
  "type": "Feature",
  "properties": {
    "addr:full":"110 N 1st St Mt Vernon WA 98273",
    "addr:housenumber":"110",
    "addr:postcode":"98273",
    "addr:street":"N 1St St",
    "iso:country":"US",
    "sg:address":"110 N 1st St",
    "sg:city":"Mt Vernon",
    "sg:classifiers":[
        {
            "category":"Organizations",
            "subcategory":"Membership Organization",
            "type":"Services"
        }
    ],
    "sg:phone":"+1 360 419 0988",
    "sg:postcode":"98273",
    "sg:province":"WA",
    "wof:name":"Friends Of Skagit County",
    "wof:placetype":"venue"
},
  "geometry": {"coordinates":[-122.33703800000001,48.423248],"type":"Point"}
}