{
  "type": "Feature",
  "properties": {
    "addr:full":"3001 E Yesler Way Seattle WA 98122",
    "addr:housenumber":"3001",
    "addr:postcode":"98122",
    "addr:street":"E Yesler Way",
    "iso:country":"US",
    "sg:address":"3001 E Yesler Way",
    "sg:city":"Seattle",
    "sg:classifiers":[
        {
            "category":"Banks & Credit Unions",
            "subcategory":"Financial Services",
            "type":"Services"
        }
    ],
    "sg:phone":"+1 206 682 2255",
    "sg:postcode":"98122",
    "sg:province":"WA",
    "sg:tags":[
        "investor"
    ],
    "wof:name":"M A Wyman Lumber Co",
    "wof:placetype":"venue"
},
  "geometry": {"coordinates":[-122.292519,47.601645],"type":"Point"}
}