{
  "type": "Feature",
  "properties": {
    "addr:full":"4010 Lake Washington Blvd NE Kirkland WA 98033",
    "addr:housenumber":"4010",
    "addr:postcode":"98033",
    "addr:street":"Lake Washington Blvd Ne",
    "iso:country":"US",
    "sg:address":"4010 Lake Washington Blvd NE",
    "sg:city":"Kirkland",
    "sg:classifiers":[
        {
            "category":"Professional",
            "subcategory":"Lawyer & Legal Services",
            "type":"Services"
        }
    ],
    "sg:phone":"+1 425 576 1656",
    "sg:postcode":"98033",
    "sg:province":"WA",
    "sg:tags":[
        "attorney"
    ],
    "sg:website":"www.seattlepatent.com",
    "wof:name":"Gary C Cohn",
    "wof:placetype":"venue"
},
  "geometry": {"coordinates":[-122.202832,47.647403],"type":"Point"}
}