{
  "type": "Feature",
  "properties": {
    "addr:full":"30629 4th Ave S Federal Way WA 98003",
    "addr:housenumber":"30629",
    "addr:postcode":"98003",
    "addr:street":"4Th Ave S Federal Way",
    "iso:country":"US",
    "sg:address":"30629 4th Ave S",
    "sg:city":"Federal Way",
    "sg:classifiers":[
        {
            "category":"Manufacturing",
            "subcategory":"Apparel",
            "type":"Manufacturing & Wholesale Goods"
        }
    ],
    "sg:phone":"+1 253 839 4243",
    "sg:postcode":"98003",
    "sg:province":"WA",
    "sg:tags":[
        "outerwear",
        "mfg"
    ],
    "wof:name":"Shirley Woods Designs",
    "wof:placetype":"venue"
},
  "geometry": {"coordinates":[-122.32939399999999,47.326074],"type":"Point"}
}