{
  "type": "Feature",
  "properties": {
    "addr:full":"3227 W Jump Off Joe Rd Valley WA 99181",
    "addr:housenumber":"3227",
    "addr:postcode":"99181",
    "addr:street":"W Jump Off Joe Rd",
    "iso:country":"US",
    "sg:address":"3227 W Jump Off Joe Rd",
    "sg:city":"Valley",
    "sg:classifiers":[
        {
            "category":"Organizations",
            "subcategory":"Religious Organization",
            "type":"Services"
        }
    ],
    "sg:phone":"+1 509 937 4311",
    "sg:postcode":"99181",
    "sg:province":"WA",
    "sg:tags":[
        "church"
    ],
    "wof:name":"Pinegrove Mennonite Church",
    "wof:placetype":"venue"
},
  "geometry": {"coordinates":[-117.70332500000001,48.152905],"type":"Point"}
}