{
  "type": "Feature",
  "properties": {
    "addr:full":"13002 SE 206th Pl Kent WA 98031",
    "addr:housenumber":"13002",
    "addr:postcode":"98031",
    "addr:street":"Se 206Th Pl",
    "iso:country":"US",
    "sg:address":"13002 SE 206th Pl",
    "sg:city":"Kent",
    "sg:classifiers":[
        {
            "category":"Professional",
            "type":"Services"
        }
    ],
    "sg:phone":"+1 253 638 1400",
    "sg:postcode":"98031",
    "sg:province":"WA",
    "wof:name":"Athomedr Co",
    "wof:placetype":"venue"
},
  "geometry": {"coordinates":[-122.166417,47.417399],"type":"Point"}
}