{
  "type": "Feature",
  "properties": {
    "iso:country":"US",
    "sg:address":"14229 55th Ave S",
    "sg:city":"Seattle",
    "sg:classifiers":[
        {
            "category":"Wholesale",
            "subcategory":"Construction Materials",
            "type":"Manufacturing & Wholesale Goods"
        }
    ],
    "sg:phone":"+1 206 246 0234",
    "sg:postcode":"98168",
    "sg:province":"WA",
    "wof:name":"Perkins Dan Co",
    "wof:placetype":"venue"
},
  "geometry": {"coordinates":[-122.266006,47.476267],"type":"Point"}
}