{
  "type": "Feature",
  "properties": {
    "addr:full":"1734 Central Ave S Kent WA 98032",
    "addr:housenumber":"1734",
    "addr:postcode":"98032",
    "addr:street":"Central Ave S",
    "iso:country":"US",
    "sg:address":"1734 Central Ave S",
    "sg:city":"Kent",
    "sg:classifiers":[
        {
            "category":"Bars & Pubs",
            "type":"Food & Drink"
        },
        {
            "category":"Restaurant",
            "type":"Food & Drink"
        }
    ],
    "sg:phone":"+1 253 850 7799",
    "sg:postcode":"98032",
    "sg:province":"WA",
    "sg:tags":[
        "style",
        "family"
    ],
    "wof:name":"Charles T & C Restaurant",
    "wof:placetype":"venue"
},
  "geometry": {"coordinates":[-122.229919,47.363999],"type":"Point"}
}