{
  "type": "Feature",
  "properties": {
    "addr:full":"3022 177th Ave NE Redmond WA 98052",
    "addr:housenumber":"3022",
    "addr:postcode":"98052",
    "addr:street":"177Th Ave Ne",
    "iso:country":"US",
    "sg:address":"3022 177th Ave NE",
    "sg:city":"Redmond",
    "sg:classifiers":[
        {
            "category":"Transit Center",
            "subcategory":"Freight",
            "type":"Transportation"
        },
        {
            "category":"Freight",
            "type":"Transportation"
        }
    ],
    "sg:phone":"+1 425 861 9511",
    "sg:postcode":"98052",
    "sg:province":"WA",
    "sg:tags":[
        "local",
        "trucking-motor",
        "trucking"
    ],
    "wof:name":"Port Side Trucking Inc",
    "wof:placetype":"venue"
},
  "geometry": {"coordinates":[-122.103588,47.637277],"type":"Point"}
}