{
  "type": "Feature",
  "properties": {
    "addr:full":"7405 Vickery Ave E Tacoma WA 98443",
    "addr:housenumber":"7405",
    "addr:postcode":"98443",
    "addr:street":"Vickery Ave E",
    "iso:country":"US",
    "sg:address":"7405 Vickery Ave E",
    "sg:city":"Tacoma",
    "sg:classifiers":[
        {
            "category":"Organizations",
            "subcategory":"Religious Organization",
            "type":"Services"
        }
    ],
    "sg:phone":"+1 253 538 1900",
    "sg:postcode":"98443",
    "sg:province":"WA",
    "sg:tags":[
        "church"
    ],
    "wof:name":"New Life Chr-God Seventh Day",
    "wof:placetype":"venue"
},
  "geometry": {"coordinates":[-122.378469,47.189985],"type":"Point"}
}