{
  "type": "Feature",
  "properties": {
    "addr:full":"601 Union Street Suite 5500 Seattle WA 98101",
    "addr:housenumber":"601",
    "addr:postcode":"98101",
    "addr:street":"Union Street Suite 5500",
    "iso:country":"US",
    "sg:address":"601 Union Street Suite 5500",
    "sg:city":"Seattle",
    "sg:classifiers":[
        {
            "category":"Professional",
            "subcategory":"Lawyer & Legal Services",
            "type":"Services"
        }
    ],
    "sg:phone":"+1 206 521 3859",
    "sg:postcode":"98101",
    "sg:province":"WA",
    "wof:name":"Bush Gayle E",
    "wof:placetype":"venue"
},
  "geometry": {"coordinates":[-122.33353700000001,47.610155],"type":"Point"}
}