{
  "type": "Feature",
  "properties": {
    "addr:full":"811 W Park St Pasco WA 99301",
    "addr:housenumber":"811",
    "addr:postcode":"99301",
    "addr:street":"W Park St",
    "iso:country":"US",
    "sg:address":"811 W Park St",
    "sg:city":"Pasco",
    "sg:classifiers":[
        {
            "category":"Professional",
            "subcategory":"Research",
            "type":"Services"
        }
    ],
    "sg:phone":"+1 509 547 0687",
    "sg:postcode":"99301",
    "sg:province":"WA",
    "sg:tags":[
        "organization",
        "noncommercial"
    ],
    "wof:name":"Vickis Medical Transcribing",
    "wof:placetype":"venue"
},
  "geometry": {"coordinates":[-119.100543,46.235802],"type":"Point"}
}