{
  "type": "Feature",
  "properties": {
    "addr:full":"619 Western Ave 201 Seattle WA 98104",
    "addr:housenumber":"619;201",
    "addr:postcode":"98104",
    "addr:street":"Western Ave",
    "iso:country":"US",
    "sg:address":"619 Western Ave 201",
    "sg:city":"Seattle",
    "sg:classifiers":[
        {
            "category":"Arts & Performance",
            "subcategory":"Art Gallery",
            "type":"Entertainment"
        }
    ],
    "sg:phone":"+1 206 621 1937",
    "sg:postcode":"98104",
    "sg:province":"WA",
    "sg:tags":[
        "fine",
        "artist"
    ],
    "wof:name":"Flynn Gillies",
    "wof:placetype":"venue"
},
  "geometry": {"coordinates":[-122.335487,47.6018],"type":"Point"}
}