{
  "type": "Feature",
  "properties": {
    "addr:full":"5874 Mertz Rd Bellingham WA 98226",
    "addr:postcode":"5874;98226",
    "addr:street":"Mertz Rd",
    "iso:country":"US",
    "sg:address":"5874 Mertz Rd",
    "sg:city":"Bellingham",
    "sg:classifiers":[
        {
            "category":"Professional",
            "type":"Services"
        }
    ],
    "sg:phone":"+1 360 398 1431",
    "sg:postcode":"98226",
    "sg:province":"WA",
    "wof:name":"Art Impressions West Inc",
    "wof:placetype":"venue"
},
  "geometry": {"coordinates":[-122.417703,48.848616],"type":"Point"}
}