{
  "type": "Feature",
  "properties": {
    "addr:full":"4147 Hamlin Rd Malaga WA 98828",
    "addr:housenumber":"4147",
    "addr:postcode":"98828",
    "addr:street":"Hamlin Rd",
    "iso:country":"US",
    "sg:address":"4147 Hamlin Rd",
    "sg:city":"Malaga",
    "sg:classifiers":[
        {
            "category":"Manufacturing",
            "subcategory":"Food",
            "type":"Manufacturing & Wholesale Goods"
        }
    ],
    "sg:phone":"+1 509 888 9463",
    "sg:postcode":"98828",
    "sg:province":"WA",
    "sg:tags":[
        "winery"
    ],
    "wof:name":"St Laurent Winery",
    "wof:placetype":"venue"
},
  "geometry": {"coordinates":[-120.229062,47.357804],"type":"Point"}
}