{
  "type": "Feature",
  "properties": {
    "addr:full":"701 E F St Tacoma WA 98421",
    "addr:housenumber":"701",
    "addr:postcode":"98421",
    "addr:street":"E F St",
    "iso:country":"US",
    "sg:address":"701 E F St",
    "sg:city":"Tacoma",
    "sg:classifiers":[
        {
            "category":"Building & Trades",
            "subcategory":"Construction",
            "type":"Services"
        }
    ],
    "sg:phone":"+1 253 572 7432",
    "sg:postcode":"98421",
    "sg:province":"WA",
    "sg:tags":[
        "general",
        "contractor"
    ],
    "wof:name":"General Construction Co",
    "wof:placetype":"venue"
},
  "geometry": {"coordinates":[-122.428513,47.254768],"type":"Point"}
}