{
  "type": "Feature",
  "properties": {
    "addr:full":"2547 Perkins Lane W Seattle WA 98199",
    "addr:housenumber":"2547",
    "addr:postcode":"98199",
    "addr:street":"Perkins Lane W",
    "iso:country":"US",
    "sg:address":"2547 Perkins Lane W",
    "sg:city":"Seattle",
    "sg:classifiers":[
        {
            "category":"Professional",
            "subcategory":"Lawyer & Legal Services",
            "type":"Services"
        }
    ],
    "sg:phone":"+1 206 285 1707",
    "sg:postcode":"98199",
    "sg:province":"WA",
    "wof:name":"Kenworthy Lise Atty At Law",
    "wof:placetype":"venue"
},
  "geometry": {"coordinates":[-122.41616999999999,47.642453],"type":"Point"}
}