{
  "type": "Feature",
  "properties": {
    "addr:full":"12417 NE 124th St Kirkland WA 98034",
    "addr:housenumber":"12417",
    "addr:postcode":"98034",
    "addr:street":"Ne 124Th St",
    "iso:country":"US",
    "sg:address":"12417 NE 124th St",
    "sg:city":"Kirkland",
    "sg:classifiers":[
        {
            "category":"Autos & Motor Vehicles",
            "subcategory":"Auto Supplies",
            "type":"Retail Goods"
        },
        {
            "category":"Retail",
            "subcategory":"Auto Repair",
            "type":"Services"
        }
    ],
    "sg:phone":"+1 425 821 7172",
    "sg:postcode":"98034",
    "sg:province":"WA",
    "sg:tags":[
        "engine",
        "shop",
        "rebuilding",
        "car",
        "exchange",
        "machine",
        "equipment",
        "automobile",
        "performance",
        "sport",
        "racing",
        "engines-rebuild"
    ],
    "sg:website":"http://www.cdengines.com",
    "wof:name":"C & D Engine Performance",
    "wof:placetype":"venue"
},
  "geometry": {"coordinates":[-122.17565399999999,47.708854],"type":"Point"}
}