{
  "type": "Feature",
  "properties": {
    "addr:full":"9010 Miller Rd NE Bainbridge Island WA 98110",
    "addr:housenumber":"9010",
    "addr:postcode":"98110",
    "addr:street":"Miller Rd Ne",
    "iso:country":"US",
    "sg:address":"9010 Miller Rd NE",
    "sg:city":"Bainbridge Island",
    "sg:classifiers":[
        {
            "category":"Sports & Exercise",
            "subcategory":"Gym",
            "type":"Entertainment"
        }
    ],
    "sg:phone":"+1 206 842 0622",
    "sg:postcode":"98110",
    "sg:province":"WA",
    "sg:tags":[
        "fitness",
        "physical",
        "facility"
    ],
    "wof:name":"N I A Technique",
    "wof:placetype":"venue"
},
  "geometry": {"coordinates":[-122.565383,47.644146],"type":"Point"}
}