{
  "type": "Feature",
  "properties": {
    "addr:full":"9565 Silver Lake Rd Maple Falls WA 98266",
    "addr:housenumber":"9565",
    "addr:postcode":"98266",
    "addr:street":"Silver Lake Rd",
    "iso:country":"US",
    "sg:address":"9565 Silver Lake Rd",
    "sg:city":"Maple Falls",
    "sg:classifiers":[
        {
            "category":"Building & Trades",
            "subcategory":"Construction",
            "type":"Services"
        }
    ],
    "sg:phone":"+1 360 599 2182",
    "sg:postcode":"98266",
    "sg:province":"WA",
    "sg:tags":[
        "masonry",
        "contractor"
    ],
    "wof:name":"Mountain Man Masonry Inc",
    "wof:placetype":"venue"
},
  "geometry": {"coordinates":[-122.068541,48.996783],"type":"Point"}
}