{
  "type": "Feature",
  "properties": {
    "addr:full":"812 5th Ave N Seattle WA 98109",
    "addr:housenumber":"812",
    "addr:postcode":"98109",
    "addr:street":"5Th Ave N",
    "iso:country":"US",
    "sg:address":"812 5th Ave N",
    "sg:city":"Seattle",
    "sg:classifiers":[
        {
            "category":"Health Services",
            "subcategory":"Dentist",
            "type":"Services"
        }
    ],
    "sg:phone":"+1 206 284 0566",
    "sg:postcode":"98109",
    "sg:province":"WA",
    "wof:name":"J Darrel Jensen DDS",
    "wof:placetype":"venue"
},
  "geometry": {"coordinates":[-122.34741,47.626847],"type":"Point"}
}