{
  "type": "Feature",
  "properties": {
    "addr:full":"203 SW Alder Rd Napavine WA 98532",
    "addr:housenumber":"203",
    "addr:postcode":"98532",
    "addr:street":"Sw Alder Rd",
    "iso:country":"US",
    "sg:address":"203 SW Alder Rd",
    "sg:city":"Napavine",
    "sg:classifiers":[
        {
            "category":"Retail",
            "subcategory":"Auto Repair",
            "type":"Services"
        }
    ],
    "sg:phone":"+1 360 262 0526",
    "sg:postcode":"98532",
    "sg:province":"WA",
    "sg:tags":[
        "repairing",
        "automobile"
    ],
    "wof:name":"Ken's Equipment Repair",
    "wof:placetype":"venue"
},
  "geometry": {"coordinates":[-122.911198,46.575524],"type":"Point"}
}