{
  "type": "Feature",
  "properties": {
    "addr:full":"4742 42nd Avenue SW Seattle WA 98116",
    "addr:housenumber":"4742",
    "addr:postcode":"98116",
    "addr:street":"42Nd Avenue Sw",
    "iso:country":"US",
    "sg:address":"4742 42nd Avenue SW",
    "sg:city":"Seattle",
    "sg:classifiers":[
        {
            "category":"Building & Trades",
            "subcategory":"Plumbing",
            "type":"Services"
        }
    ],
    "sg:phone":"+1 206 579 2849",
    "sg:postcode":"98116",
    "sg:province":"WA",
    "sg:website":"www.jlrplumbing.com",
    "wof:name":"JLR Plumbing",
    "wof:placetype":"venue"
},
  "geometry": {"coordinates":[-122.385481,47.559946],"type":"Point"}
}