{
  "type": "Feature",
  "properties": {
    "addr:full":"13754 Aurora Ave N Seattle WA 98133",
    "addr:housenumber":"13754",
    "addr:postcode":"98133",
    "addr:street":"Aurora Ave N",
    "iso:country":"US",
    "sg:address":"13754 Aurora Ave N",
    "sg:city":"Seattle",
    "sg:classifiers":[
        {
            "category":"Personal",
            "subcategory":"Beauty Salon",
            "type":"Services"
        }
    ],
    "sg:phone":"+1 206 363 1098",
    "sg:postcode":"98133",
    "sg:province":"WA",
    "sg:tags":[
        "shop"
    ],
    "wof:name":"Everyday Hair Fashion",
    "wof:placetype":"venue"
},
  "geometry": {"coordinates":[-122.344981,47.730161],"type":"Point"}
}