{
  "type": "Feature",
  "properties": {
    "addr:full":"3627 18th Ave S Seattle WA 98144",
    "addr:housenumber":"3627",
    "addr:postcode":"98144",
    "addr:street":"18Th Ave S",
    "iso:country":"US",
    "sg:address":"3627 18th Ave S",
    "sg:city":"Seattle",
    "sg:classifiers":[
        {
            "category":"Retail",
            "subcategory":"Auto Repair",
            "type":"Services"
        }
    ],
    "sg:phone":"+1 206 767 2550",
    "sg:postcode":"98144",
    "sg:province":"WA",
    "wof:name":"Garage Tuner Automotive",
    "wof:placetype":"venue"
},
  "geometry": {"coordinates":[-122.307558,47.571926],"type":"Point"}
}