{
  "type": "Feature",
  "properties": {
    "addr:full":"201 107th St SW Everett WA 98204",
    "addr:housenumber":"201",
    "addr:postcode":"98204",
    "addr:street":"107Th St Sw",
    "iso:country":"US",
    "sg:address":"201 107th St SW",
    "sg:city":"Everett",
    "sg:classifiers":[
        {
            "category":"Shopping",
            "subcategory":"Shoes",
            "type":"Retail Goods"
        }
    ],
    "sg:phone":"+1 425 355 0913",
    "sg:postcode":"98204",
    "sg:province":"WA",
    "sg:tags":[
        "sportswear"
    ],
    "wof:name":"Club Shred",
    "wof:placetype":"venue"
},
  "geometry": {"coordinates":[-122.236296,47.901001],"type":"Point"}
}