{
  "type": "Feature",
  "properties": {
    "addr:full":"1909 3rd St SE East Wenatchee WA 98802",
    "addr:housenumber":"1909",
    "addr:postcode":"98802",
    "addr:street":"3Rd St Se",
    "iso:country":"US",
    "sg:address":"1909 3rd St SE",
    "sg:city":"East Wenatchee",
    "sg:classifiers":[
        {
            "category":"Building & Trades",
            "subcategory":"Cleaning & Sanitation",
            "type":"Services"
        }
    ],
    "sg:phone":"+1 509 860 3234",
    "sg:postcode":"98802",
    "sg:province":"WA",
    "sg:tags":[
        "maintenance"
    ],
    "wof:name":"Graystone Commercial Cleaning",
    "wof:placetype":"venue"
},
  "geometry": {"coordinates":[-120.25907100000001,47.400445],"type":"Point"}
}