{
  "type": "Feature",
  "properties": {
    "addr:full":"5116 Kenilworth Pl NE Seattle WA 98105",
    "addr:housenumber":"5116",
    "addr:postcode":"98105",
    "addr:street":"Kenilworth Pl Ne",
    "iso:country":"US",
    "sg:address":"5116 Kenilworth Pl NE",
    "sg:city":"Seattle",
    "sg:classifiers":[
        {
            "category":"Personal",
            "subcategory":"Hair Removal",
            "type":"Services"
        }
    ],
    "sg:phone":"+1 206 749 9400",
    "sg:postcode":"98105",
    "sg:province":"WA",
    "wof:name":"Samurai EC",
    "wof:placetype":"venue"
},
  "geometry": {"coordinates":[-122.26990600000001,47.666495],"type":"Point"}
}