{
  "type": "Feature",
  "properties": {
    "addr:full":"9932 Vernon Rd Lake Stevens WA 98258",
    "addr:housenumber":"9932",
    "addr:postcode":"98258",
    "addr:street":"Vernon Rd",
    "iso:country":"US",
    "sg:address":"9932 Vernon Rd",
    "sg:city":"Lake Stevens",
    "sg:classifiers":[
        {
            "category":"Real Estate",
            "subcategory":"Developer",
            "type":"Services"
        }
    ],
    "sg:phone":"+1 425 335 5898",
    "sg:postcode":"98258",
    "sg:province":"WA",
    "wof:name":"Rmj Assoc",
    "wof:placetype":"venue"
},
  "geometry": {"coordinates":[-122.09699000000001,48.017055],"type":"Point"}
}