{
  "type": "Feature",
  "properties": {
    "addr:full":"122 E Russ St Cle Elum WA 98922",
    "addr:housenumber":"122",
    "addr:postcode":"98922",
    "addr:street":"E Russ St",
    "iso:country":"US",
    "sg:address":"122 E Russ St",
    "sg:city":"Cle Elum",
    "sg:classifiers":[
        {
            "category":"Freight",
            "type":"Transportation"
        }
    ],
    "sg:phone":"+1 509 674 4267",
    "sg:postcode":"98922",
    "sg:province":"WA",
    "sg:tags":[
        "commercial",
        "storage"
    ],
    "wof:name":"Norris Storage",
    "wof:placetype":"venue"
},
  "geometry": {"coordinates":[-120.938193,47.19282],"type":"Point"}
}