{
  "type": "Feature",
  "properties": {
    "iso:country":"US",
    "sg:address":"1615 SE Bleasner Dr",
    "sg:city":"Pullman",
    "sg:classifiers":[
        {
            "category":"Real Estate",
            "subcategory":"Real Estate Operator",
            "type":"Services"
        }
    ],
    "sg:phone":"+1 509 332 5631",
    "sg:postcode":"99163",
    "sg:province":"WA",
    "sg:tags":[
        "apartment"
    ],
    "wof:name":"Wilru Apartments",
    "wof:placetype":"venue"
},
  "geometry": {"coordinates":[-117.162661,46.720299],"type":"Point"}
}