{
  "type": "Feature",
  "properties": {
    "addr:full":"17911 NE Peg Rd Yacolt WA 98675",
    "addr:housenumber":"17911",
    "addr:postcode":"98675",
    "addr:street":"Ne Peg Rd",
    "iso:country":"US",
    "sg:address":"17911 NE Peg Rd",
    "sg:city":"Yacolt",
    "sg:classifiers":[
        {
            "category":"Building & Trades",
            "subcategory":"Construction",
            "type":"Services"
        }
    ],
    "sg:phone":"+1 360 686 3776",
    "sg:postcode":"98675",
    "sg:province":"WA",
    "sg:tags":[
        "well",
        "drilling"
    ],
    "wof:name":"Don Pitner Jr Well Drilling",
    "wof:placetype":"venue"
},
  "geometry": {"coordinates":[-122.483812,45.891671],"type":"Point"}
}