{
  "type": "Feature",
  "properties": {
    "addr:full":"14250 SE 13th Pl Bellevue WA 98007",
    "addr:housenumber":"14250",
    "addr:postcode":"98007",
    "addr:street":"Se 13Th Pl",
    "iso:country":"US",
    "sg:address":"14250 SE 13th Pl",
    "sg:city":"Bellevue",
    "sg:classifiers":[
        {
            "category":"Health Services",
            "subcategory":"Clinic",
            "type":"Services"
        }
    ],
    "sg:phone":"+1 425 643 8101",
    "sg:postcode":"98007",
    "sg:province":"WA",
    "sg:tags":[
        "home"
    ],
    "wof:name":"Jodem Home Health Care",
    "wof:placetype":"venue"
},
  "geometry": {"coordinates":[-122.149523,47.599945],"type":"Point"}
}