{
  "type": "Feature",
  "properties": {
    "addr:full":"1619 N State St Bellingham WA 98225",
    "addr:housenumber":"1619",
    "addr:postcode":"98225",
    "addr:street":"N State St",
    "iso:country":"US",
    "sg:address":"1619 N State St",
    "sg:city":"Bellingham",
    "sg:classifiers":[
        {
            "category":"Professional",
            "subcategory":"Detective & Security Services",
            "type":"Services"
        },
        {
            "category":"Shopping",
            "type":"Retail Goods"
        },
        {
            "category":"Building & Trades",
            "subcategory":"Locksmith",
            "type":"Services"
        }
    ],
    "sg:phone":"+1 360 746 0586",
    "sg:postcode":"98225",
    "sg:province":"WA",
    "sg:tags":[
        "control",
        "monitoring",
        "lock",
        "safe",
        "system",
        "equipment",
        "consultant",
        "vault"
    ],
    "sg:website":"http://www.securitysolutionsnw.com",
    "wof:name":"Security Solutions NW",
    "wof:placetype":"venue"
},
  "geometry": {"coordinates":[-122.47168000000001,48.752041],"type":"Point"}
}