{
  "type": "Feature",
  "properties": {
    "addr:full":"71 Columbia St Seattle WA 98104",
    "addr:housenumber":"71",
    "addr:postcode":"98104",
    "addr:street":"Columbia",
    "iso:country":"US",
    "sg:address":"71 Columbia St",
    "sg:city":"Seattle",
    "sg:classifiers":[
        {
            "category":"Professional",
            "subcategory":"Advertising",
            "type":"Services"
        }
    ],
    "sg:phone":"+1 206 343 9000",
    "sg:postcode":"98104",
    "sg:province":"WA",
    "sg:tags":[
        "agency"
    ],
    "wof:name":"Harmonica",
    "wof:placetype":"venue"
},
  "geometry": {"coordinates":[-122.33667199999999,47.602574],"type":"Point"}
}