{
  "type": "Feature",
  "properties": {
    "addr:full":"1426 Commerce Ave Longview WA 98632",
    "addr:housenumber":"1426",
    "addr:postcode":"98632",
    "addr:street":"Commerce Ave",
    "iso:country":"US",
    "sg:address":"1426 Commerce Ave",
    "sg:city":"Longview",
    "sg:classifiers":[
        {
            "category":"Health Services",
            "subcategory":"Optometrist",
            "type":"Services"
        }
    ],
    "sg:phone":"+1 360 423 7650",
    "sg:postcode":"98632",
    "sg:province":"WA",
    "wof:name":"Charles Wardle & Assoc",
    "wof:placetype":"venue"
},
  "geometry": {"coordinates":[-122.933414,46.139277],"type":"Point"}
}