{
  "type": "Feature",
  "properties": {
    "addr:full":"707 S Lane St Seattle WA 98104",
    "addr:housenumber":"707",
    "addr:postcode":"98104",
    "addr:street":"S Lane",
    "iso:country":"US",
    "sg:address":"707 S Lane St",
    "sg:city":"Seattle",
    "sg:classifiers":[
        {
            "category":"Banks & Credit Unions",
            "subcategory":"Bank",
            "type":"Services"
        },
        {
            "category":"Shopping",
            "subcategory":"Antiques",
            "type":"Retail Goods"
        },
        {
            "category":"Shopping",
            "subcategory":"Used Merchandise",
            "type":"Retail Goods"
        }
    ],
    "sg:phone":"+1 206 287 9888",
    "sg:postcode":"98104",
    "sg:province":"WA",
    "sg:tags":[
        "shop",
        "second",
        "resale",
        "hand"
    ],
    "wof:name":"Arts Of China",
    "wof:placetype":"venue"
},
  "geometry": {"coordinates":[-122.32365900000001,47.596668],"type":"Point"}
}