{
  "type": "Feature",
  "properties": {
    "addr:full":"4750 Lake Washington Blvd NE Renton WA 98056",
    "addr:housenumber":"4750",
    "addr:postcode":"98056",
    "addr:street":"Lake Washington Blvd Ne",
    "iso:country":"US",
    "sg:address":"4750 Lake Washington Blvd NE",
    "sg:city":"Renton",
    "sg:classifiers":[
        {
            "category":"Building & Trades",
            "subcategory":"Locksmith",
            "type":"Services"
        }
    ],
    "sg:phone":"+1 425 818 2820",
    "sg:postcode":"98056",
    "sg:province":"WA",
    "sg:tags":[
        "key"
    ],
    "wof:name":"A Renton Emergency A Locksmith",
    "wof:placetype":"venue"
},
  "geometry": {"coordinates":[-122.199286,47.531449],"type":"Point"}
}