{
  "type": "Feature",
  "properties": {
    "addr:full":"11405 34th Dr SE Everett WA 98208",
    "addr:housenumber":"11405",
    "addr:postcode":"98208",
    "addr:street":"34Th Dr Se",
    "iso:country":"US",
    "sg:address":"11405 34th Dr SE",
    "sg:city":"Everett",
    "sg:classifiers":[
        {
            "category":"Professional",
            "subcategory":"Computer Services",
            "type":"Services"
        }
    ],
    "sg:phone":"+1 425 379 6110",
    "sg:postcode":"98208",
    "sg:province":"WA",
    "sg:tags":[
        "internet"
    ],
    "wof:name":"Neighbortel",
    "wof:placetype":"venue"
},
  "geometry": {"coordinates":[-122.186503,47.893009],"type":"Point"}
}