{
  "type": "Feature",
  "properties": {
    "addr:full":"2500 E Valley Rd Renton WA 98057",
    "addr:housenumber":"2500",
    "addr:postcode":"98057",
    "addr:street":"E Valley Rd",
    "iso:country":"US",
    "sg:address":"2500 E Valley Rd",
    "sg:city":"Renton",
    "sg:classifiers":[
        {
            "category":"Government",
            "subcategory":"Office",
            "type":"Public Place"
        }
    ],
    "sg:phone":"+1 425 227 2171",
    "sg:postcode":"98057",
    "sg:province":"WA",
    "sg:tags":[
        "transportation"
    ],
    "wof:name":"Manufacturing Insptn Dst Off",
    "wof:placetype":"venue"
},
  "geometry": {"coordinates":[-122.218025,47.457882],"type":"Point"}
}