{
  "type": "Feature",
  "properties": {
    "addr:full":"13705 115th Ave NE Kirkland WA 98034",
    "addr:housenumber":"13705",
    "addr:postcode":"98034",
    "addr:street":"115Th Ave Ne",
    "iso:country":"US",
    "sg:address":"13705 115th Ave NE",
    "sg:city":"Kirkland",
    "sg:classifiers":[
        {
            "category":"Insurance",
            "subcategory":"Insurance Agent",
            "type":"Services"
        }
    ],
    "sg:phone":"+1 425 821 7555",
    "sg:postcode":"98034",
    "sg:province":"WA",
    "wof:name":"Alan C WYNN Insurance",
    "wof:placetype":"venue"
},
  "geometry": {"coordinates":[-122.18816099999999,47.724257],"type":"Point"}
}