{
  "type": "Feature",
  "properties": {
    "addr:full":"5316 Keystone Pl N Seattle WA 98103",
    "addr:housenumber":"5316",
    "addr:postcode":"98103",
    "addr:street":"Keystone Pl N",
    "iso:country":"US",
    "sg:address":"5316 Keystone Pl N",
    "sg:city":"Seattle",
    "sg:classifiers":[
        {
            "category":"Shopping",
            "subcategory":"Computers & Home Electronics",
            "type":"Retail Goods"
        }
    ],
    "sg:phone":"+1 206 547 0720",
    "sg:postcode":"98103",
    "sg:province":"WA",
    "wof:name":"Keystone Flashcom",
    "wof:placetype":"venue"
},
  "geometry": {"coordinates":[-122.33239500000001,47.667882],"type":"Point"}
}