{
  "type": "Feature",
  "properties": {
    "addr:full":"1402 Auburn Way N Auburn WA 98002",
    "addr:housenumber":"1402",
    "addr:postcode":"98002",
    "addr:street":"Auburn Way N",
    "iso:country":"US",
    "sg:address":"1402 Auburn Way N",
    "sg:city":"Auburn",
    "sg:classifiers":[
        {
            "category":"Restaurant",
            "type":"Food & Drink"
        }
    ],
    "sg:phone":"+1 253 931 5539",
    "sg:postcode":"98002",
    "sg:province":"WA",
    "sg:tags":[
        "eating",
        "trucking"
    ],
    "wof:name":"Frank W Callender",
    "wof:placetype":"venue"
},
  "geometry": {"coordinates":[-122.221487,47.320238],"type":"Point"}
}