{
  "type": "Feature",
  "properties": {
    "addr:full":"6523 California Ave SW #230 230 Seattle WA 98136",
    "addr:housenumber":"6523;230",
    "addr:postcode":"98136",
    "addr:street":"California Ave Sw # 230",
    "iso:country":"US",
    "sg:address":"6523 California Ave SW #230 230",
    "sg:city":"Seattle",
    "sg:classifiers":[
        {
            "category":"Professional",
            "subcategory":"Lawyer & Legal Services",
            "type":"Services"
        }
    ],
    "sg:phone":"+1 206 696 5802",
    "sg:postcode":"98136",
    "sg:province":"WA",
    "sg:website":"www.bayview-legal.com",
    "wof:name":"Bayview Legal",
    "wof:placetype":"venue"
},
  "geometry": {"coordinates":[-122.38736,47.54412],"type":"Point"}
}