{
  "type": "Feature",
  "properties": {
    "addr:full":"914 288th Stct E Roy WA 98580",
    "addr:housenumber":"914",
    "addr:postcode":"98580",
    "addr:street":"288Th Stct E Roy",
    "iso:country":"US",
    "sg:address":"914 288th Stct E",
    "sg:city":"Roy",
    "sg:classifiers":[
        {
            "category":"Manufacturing",
            "subcategory":"Retail Goods",
            "type":"Manufacturing & Wholesale Goods"
        }
    ],
    "sg:phone":"+1 253 843 0504",
    "sg:postcode":"98580",
    "sg:province":"WA",
    "sg:tags":[
        "product",
        "mfg"
    ],
    "wof:name":"Cal Fisher Industries Inc",
    "wof:placetype":"venue"
},
  "geometry": {"coordinates":[-122.41714,46.994261],"type":"Point"}
}