{
  "type": "Feature",
  "properties": {
    "addr:full":"1135 116th Ave NE Ste 600 Bellevue WA 98004",
    "addr:housenumber":"1135",
    "addr:postcode":"98004",
    "addr:street":"116Th Ave Ne Ste 600",
    "iso:country":"US",
    "sg:address":"1135 116th Ave NE Ste 600",
    "sg:city":"Bellevue",
    "sg:classifiers":[
        {
            "category":"Health Services",
            "subcategory":"Doctor",
            "type":"Services"
        }
    ],
    "sg:phone":"+1 425 454 2656",
    "sg:postcode":"98004",
    "sg:province":"WA",
    "sg:tags":[
        "cardiologist"
    ],
    "wof:name":"Kozlowski Christopher M MD",
    "wof:placetype":"venue"
},
  "geometry": {"coordinates":[-122.185912,47.621424],"type":"Point"}
}