{
  "type": "Feature",
  "properties": {
    "addr:full":"9110 Roy Rd NE Bremerton WA 98311",
    "addr:housenumber":"9110",
    "addr:postcode":"98311",
    "addr:street":"Roy Rd Ne",
    "iso:country":"US",
    "sg:address":"9110 Roy Rd NE",
    "sg:city":"Bremerton",
    "sg:classifiers":[
        {
            "category":"Shopping",
            "subcategory":"Gifts & Souvenirs",
            "type":"Retail Goods"
        }
    ],
    "sg:phone":"+1 360 509 6892",
    "sg:postcode":"98311",
    "sg:province":"WA",
    "wof:name":"Crafts & Curios",
    "wof:placetype":"venue"
},
  "geometry": {"coordinates":[-122.610857,47.644504],"type":"Point"}
}