{
  "type": "Feature",
  "properties": {
    "addr:full":"811 7th St SE Puyallup WA 98372",
    "addr:housenumber":"811",
    "addr:postcode":"98372",
    "addr:street":"7Th St Se",
    "iso:country":"US",
    "sg:address":"811 7th St SE",
    "sg:city":"Puyallup",
    "sg:classifiers":[
        {
            "category":"Building & Trades",
            "subcategory":"Construction",
            "type":"Services"
        }
    ],
    "sg:phone":"+1 253 536 5583",
    "sg:postcode":"98372",
    "sg:province":"WA",
    "sg:tags":[
        "contractor"
    ],
    "wof:name":"Dependable Roofing",
    "wof:placetype":"venue"
},
  "geometry": {"coordinates":[-122.28556500000001,47.18541],"type":"Point"}
}