{
  "type": "Feature",
  "properties": {
    "addr:full":"19040 NE 133rd Ct Woodinville WA 98077",
    "addr:housenumber":"19040",
    "addr:postcode":"98077",
    "addr:street":"Ne 133Rd Ct",
    "iso:country":"US",
    "sg:address":"19040 NE 133rd Ct",
    "sg:city":"Woodinville",
    "sg:classifiers":[
        {
            "category":"Real Estate",
            "subcategory":"Real Estate Agent",
            "type":"Services"
        }
    ],
    "sg:phone":"+1 425 867 5374",
    "sg:postcode":"98077",
    "sg:province":"WA",
    "wof:name":"Pine Place Apartments",
    "wof:placetype":"venue"
},
  "geometry": {"coordinates":[-122.084456,47.718351],"type":"Point"}
}