{
  "type": "Feature",
  "properties": {
    "addr:full":"1440 Abernathy Creek Rd Longview WA 98632",
    "addr:housenumber":"1440",
    "addr:postcode":"98632",
    "addr:street":"Abernathy Creek Rd",
    "iso:country":"US",
    "sg:address":"1440 Abernathy Creek Rd",
    "sg:city":"Longview",
    "sg:classifiers":[
        {
            "category":"Government",
            "subcategory":"Office",
            "type":"Public Place"
        }
    ],
    "sg:phone":"+1 360 425 6072",
    "sg:postcode":"98632",
    "sg:province":"WA",
    "sg:tags":[
        "hatchery",
        "fish",
        "technology",
        "center"
    ],
    "wof:name":"Abernathy Fish Technology Ctr",
    "wof:placetype":"venue"
},
  "geometry": {"coordinates":[-123.147627,46.215277],"type":"Point"}
}