{
  "type": "Feature",
  "properties": {
    "addr:full":"610 Front St Mukilteo WA 98275",
    "addr:housenumber":"610",
    "addr:postcode":"98275",
    "addr:street":"Front St",
    "iso:country":"US",
    "sg:address":"610 Front St",
    "sg:city":"Mukilteo",
    "sg:classifiers":[
        {
            "category":"Home & Garden",
            "subcategory":"Building Materials",
            "type":"Retail Goods"
        }
    ],
    "sg:phone":"+1 425 252 4454",
    "sg:postcode":"98275",
    "sg:province":"WA",
    "sg:tags":[
        "overhead",
        "door",
        "motor"
    ],
    "wof:name":"Attco",
    "wof:placetype":"venue"
},
  "geometry": {"coordinates":[-122.305224,47.948665],"type":"Point"}
}