{
  "type": "Feature",
  "properties": {
    "addr:full":"190 Martin Rd Toppenish WA 98948",
    "addr:housenumber":"190",
    "addr:postcode":"98948",
    "addr:street":"Martin Rd",
    "iso:country":"US",
    "sg:address":"190 Martin Rd",
    "sg:city":"Toppenish",
    "sg:classifiers":[
        {
            "category":"Retail",
            "subcategory":"Repair Shop",
            "type":"Services"
        }
    ],
    "sg:phone":"+1 509 877 4077",
    "sg:postcode":"98948",
    "sg:province":"WA",
    "wof:name":"Mikes Repair Service",
    "wof:placetype":"venue"
},
  "geometry": {"coordinates":[-120.385936,46.412608],"type":"Point"}
}