{
  "type": "Feature",
  "properties": {
    "iso:country":"US",
    "sg:address":"2200 Talley Way",
    "sg:city":"Kelso",
    "sg:classifiers":[
        {
            "category":"Manufacturing",
            "subcategory":"Tools & Machinery",
            "type":"Manufacturing & Wholesale Goods"
        }
    ],
    "sg:phone":"+1 360 578 0320",
    "sg:postcode":"98626",
    "sg:province":"WA",
    "sg:tags":[
        "surgical",
        "mfg"
    ],
    "wof:name":"John K Beckwith",
    "wof:placetype":"venue"
},
  "geometry": {"coordinates":[-122.89520400000001,46.122319],"type":"Point"}
}