{
  "type": "Feature",
  "properties": {
    "addr:full":"316 E 1st St Aberdeen WA 98520",
    "addr:housenumber":"316",
    "addr:postcode":"98520",
    "addr:street":"E 1St St",
    "iso:country":"US",
    "sg:address":"316 E 1st St",
    "sg:city":"Aberdeen",
    "sg:classifiers":[
        {
            "category":"Organizations",
            "subcategory":"Labor Organization",
            "type":"Services"
        }
    ],
    "sg:phone":"+1 360 532 6840",
    "sg:postcode":"98520",
    "sg:province":"WA",
    "wof:name":"Carpenters & Pile Drivers",
    "wof:placetype":"venue"
},
  "geometry": {"coordinates":[-123.816367,46.977643],"type":"Point"}
}