{
  "type": "Feature",
  "properties": {
    "addr:full":"2375 130th Ave NE Bellevue WA 98005",
    "addr:housenumber":"2375",
    "addr:postcode":"98005",
    "addr:street":"130Th Ave Ne",
    "iso:country":"US",
    "sg:address":"2375 130th Ave NE",
    "sg:city":"Bellevue",
    "sg:classifiers":[
        {
            "category":"Real Estate",
            "subcategory":"Real Estate Agent",
            "type":"Services"
        }
    ],
    "sg:phone":"+1 425 861 4000",
    "sg:postcode":"98005",
    "sg:province":"WA",
    "wof:name":"Realty Ventures Corporation",
    "wof:placetype":"venue"
},
  "geometry": {"coordinates":[-122.16805100000001,47.630751],"type":"Point"}
}