{
  "type": "Feature",
  "properties": {
    "iso:country":"US",
    "sg:address":"1377 20th St",
    "sg:city":"Anacortes",
    "sg:classifiers":[
        {
            "category":"Travel",
            "subcategory":"Hotels & Motels",
            "type":"Entertainment"
        }
    ],
    "sg:phone":"+1 360 293 5314",
    "sg:postcode":"98221",
    "sg:province":"WA",
    "wof:name":"Campbell Lake Lodging",
    "wof:placetype":"venue"
},
  "geometry": {"coordinates":[-122.61802900000001,48.506087],"type":"Point"}
}