{
  "type": "Feature",
  "properties": {
    "addr:full":"13333 Lake City Way NE Seattle WA 98125",
    "addr:housenumber":"13333",
    "addr:postcode":"98125",
    "addr:street":"Lake City Way Ne",
    "iso:country":"US",
    "sg:address":"13333 Lake City Way NE",
    "sg:city":"Seattle",
    "sg:classifiers":[
        {
            "category":"Home & Garden",
            "subcategory":"Furniture",
            "type":"Retail Goods"
        }
    ],
    "sg:postcode":"98125",
    "sg:province":"WA",
    "sg:tags":[
        "store"
    ],
    "sg:website":"www.awindowtochina.com",
    "wof:name":"A Window To China",
    "wof:placetype":"venue"
},
  "geometry": {"coordinates":[-122.29299899999999,47.725399],"type":"Point"}
}