{
  "type": "Feature",
  "properties": {
    "addr:full":"1208 NE 64th St Seattle WA 98115",
    "addr:housenumber":"1208",
    "addr:postcode":"98115",
    "addr:street":"Ne 64Th St",
    "iso:country":"US",
    "sg:address":"1208 NE 64th St",
    "sg:city":"Seattle",
    "sg:classifiers":[
        {
            "category":"Education",
            "subcategory":"Special Training",
            "type":"Public Place"
        }
    ],
    "sg:phone":"+1 206 525 7575",
    "sg:postcode":"98115",
    "sg:province":"WA",
    "wof:name":"Aaron Malver Piano Studio",
    "wof:placetype":"venue"
},
  "geometry": {"coordinates":[-122.31441700000001,47.675052],"type":"Point"}
}