{
  "type": "Feature",
  "properties": {
    "addr:full":"2061 NE Sawdust Hill Rd Poulsbo WA 98370",
    "addr:housenumber":"2061",
    "addr:postcode":"98370",
    "addr:street":"Ne Sawdust Hill Rd",
    "iso:country":"US",
    "sg:address":"2061 NE Sawdust Hill Rd",
    "sg:city":"Poulsbo",
    "sg:classifiers":[
        {
            "category":"Real Estate",
            "subcategory":"Architect",
            "type":"Services"
        }
    ],
    "sg:phone":"+1 360 697 8500",
    "sg:postcode":"98370",
    "sg:province":"WA",
    "sg:tags":[
        "building",
        "designer"
    ],
    "wof:name":"Evergreen Home Design",
    "wof:placetype":"venue"
},
  "geometry": {"coordinates":[-122.63283800000001,47.773589],"type":"Point"}
}