{
  "type": "Feature",
  "properties": {
    "addr:full":"100 W. Harrison Street Seattle WA 98119",
    "addr:housenumber":"100",
    "addr:postcode":"98119",
    "addr:street":"W. Harrison Street",
    "iso:country":"US",
    "sg:address":"100 W. Harrison Street",
    "sg:city":"Seattle",
    "sg:classifiers":[
        {
            "category":"Health Services",
            "subcategory":"Clinic",
            "type":"Services"
        }
    ],
    "sg:phone":"+1 206 378 0599",
    "sg:postcode":"98119",
    "sg:province":"WA",
    "sg:tags":[
        "counseling",
        "mental"
    ],
    "wof:name":"Devine Roberta PHD",
    "wof:placetype":"venue"
},
  "geometry": {"coordinates":[-122.358255,47.623044],"type":"Point"}
}