{
  "type": "Feature",
  "properties": {
    "addr:full":"21906 41st Pl W Mountlake Terrace WA 98043",
    "addr:housenumber":"21906",
    "addr:postcode":"98043",
    "addr:street":"41St Pl W",
    "iso:country":"US",
    "sg:address":"21906 41st Pl W",
    "sg:city":"Mountlake Terrace",
    "sg:classifiers":[
        {
            "category":"Taxi",
            "type":"Transportation"
        }
    ],
    "sg:phone":"+1 425 771 7203",
    "sg:postcode":"98043",
    "sg:province":"WA",
    "sg:tags":[
        "taxicab"
    ],
    "wof:name":"Tiger Taxi Service",
    "wof:placetype":"venue"
},
  "geometry": {"coordinates":[-122.288444,47.794391],"type":"Point"}
}