{
  "type": "Feature",
  "properties": {
    "addr:full":"2210 SE 187th Ave Vancouver WA 98683",
    "addr:housenumber":"2210",
    "addr:postcode":"98683",
    "addr:street":"Se 187Th Ave",
    "iso:country":"US",
    "sg:address":"2210 SE 187th Ave",
    "sg:city":"Vancouver",
    "sg:classifiers":[
        {
            "category":"Professional",
            "subcategory":"Management & Consulting",
            "type":"Services"
        }
    ],
    "sg:phone":"+1 360 882 8756",
    "sg:postcode":"98683",
    "sg:province":"WA",
    "sg:tags":[
        "business"
    ],
    "wof:name":"Chris Olsen Consulting",
    "wof:placetype":"venue"
},
  "geometry": {"coordinates":[-122.480738,45.605606],"type":"Point"}
}