{
  "type": "Feature",
  "properties": {
    "addr:full":"7300 196th St SW Lynnwood WA 98036",
    "addr:housenumber":"7300",
    "addr:postcode":"98036",
    "addr:street":"196Th St Sw",
    "iso:country":"US",
    "sg:address":"7300 196th St SW",
    "sg:city":"Lynnwood",
    "sg:classifiers":[
        {
            "category":"Shopping",
            "subcategory":"Clothing, Apparel, & Fashions",
            "type":"Retail Goods"
        }
    ],
    "sg:phone":"+1 425 771 4225",
    "sg:postcode":"98036",
    "sg:province":"WA",
    "wof:name":"Yesterday's Consignment Shoppe",
    "wof:placetype":"venue"
},
  "geometry": {"coordinates":[-122.33392000000001,47.821442],"type":"Point"}
}