{
  "type": "Feature",
  "properties": {
    "iso:country":"US",
    "sg:address":"2803 E 11th Ave",
    "sg:city":"Spokane",
    "sg:classifiers":[
        {
            "category":"Social Services",
            "type":"Services"
        }
    ],
    "sg:phone":"+1 509 536 0843",
    "sg:postcode":"99202",
    "sg:province":"WA",
    "sg:tags":[
        "counselor",
        "marriage",
        "family"
    ],
    "wof:name":"Phoenix Institute",
    "wof:placetype":"venue"
},
  "geometry": {"coordinates":[-117.370418,47.645451],"type":"Point"}
}