{
  "type": "Feature",
  "properties": {
    "iso:country":"US",
    "sg:address":"1200 Harris Ave",
    "sg:city":"Bellingham",
    "sg:classifiers":[
        {
            "category":"Personal",
            "subcategory":"Beauty Salon",
            "type":"Services"
        }
    ],
    "sg:phone":"+1 360 738 9100",
    "sg:postcode":"98225",
    "sg:province":"WA",
    "sg:tags":[
        "shop"
    ],
    "wof:name":"Myspa",
    "wof:placetype":"venue"
},
  "geometry": {"coordinates":[-122.501058,48.720132],"type":"Point"}
}