{
  "type": "Feature",
  "properties": {
    "addr:full":"1017 N Wenatchee Ave Wenatchee WA 98801",
    "addr:housenumber":"1017",
    "addr:postcode":"98801",
    "addr:street":"N Wenatchee Ave",
    "iso:country":"US",
    "sg:address":"1017 N Wenatchee Ave",
    "sg:city":"Wenatchee",
    "sg:classifiers":[
        {
            "category":"Travel",
            "subcategory":"Hotels & Motels",
            "type":"Entertainment"
        }
    ],
    "sg:phone":"+1 509 665 8585",
    "sg:postcode":"98801",
    "sg:province":"WA",
    "wof:name":"Sukhjivan Diamond Hotel Corporation",
    "wof:placetype":"venue"
},
  "geometry": {"coordinates":[-120.321271,47.436667],"type":"Point"}
}