{
  "type": "Feature",
  "properties": {
    "addr:full":"1020 108th Ave NE Bellevue WA 98004",
    "addr:housenumber":"1020",
    "addr:postcode":"98004",
    "addr:street":"108Th Ave Ne",
    "iso:country":"US",
    "sg:address":"1020 108th Ave NE",
    "sg:city":"Bellevue",
    "sg:classifiers":[
        {
            "category":"Shopping",
            "subcategory":"Computers & Home Electronics",
            "type":"Retail Goods"
        }
    ],
    "sg:phone":"+1 425 454 1024",
    "sg:postcode":"98004",
    "sg:province":"WA",
    "sg:tags":[
        "software"
    ],
    "wof:name":"Abodio Software",
    "wof:placetype":"venue"
},
  "geometry": {"coordinates":[-122.19624399999999,47.619855],"type":"Point"}
}