{
  "type": "Feature",
  "properties": {
    "addr:full":"1015 S 128th St Seattle WA 98168",
    "addr:housenumber":"1015",
    "addr:postcode":"98168",
    "addr:street":"S 128Th St",
    "iso:country":"US",
    "sg:address":"1015 S 128th St",
    "sg:city":"Seattle",
    "sg:classifiers":[
        {
            "category":"Place Of Worship",
            "subcategory":"Church",
            "type":"Public Place"
        },
        {
            "category":"Place Of Worship",
            "type":"Public Place"
        },
        {
            "category":"Education",
            "subcategory":"Preschool",
            "type":"Public Place"
        }
    ],
    "sg:phone":"+1 206 242 9936",
    "sg:postcode":"98168",
    "sg:province":"WA",
    "sg:tags":[
        "kindergarten",
        "churches-presbyterian",
        "churches-presbyterian-arp"
    ],
    "wof:name":"Curiosity Corner",
    "wof:placetype":"venue"
},
  "geometry": {"coordinates":[-122.32028800000001,47.488543],"type":"Point"}
}