{
  "type": "Feature",
  "properties": {
    "addr:full":"11201 SE 8th St Bellevue WA 98004",
    "addr:postcode":"11201;98004",
    "addr:street":"Se 8Th St",
    "iso:country":"US",
    "sg:address":"11201 SE 8th St",
    "sg:city":"Bellevue",
    "sg:classifiers":[
        {
            "category":"Health Services",
            "subcategory":"Doctor",
            "type":"Services"
        }
    ],
    "sg:phone":"+1 425 454 0255",
    "sg:postcode":"98004",
    "sg:province":"WA",
    "wof:name":"Vandenbelt Russell MD",
    "wof:placetype":"venue"
},
  "geometry": {"coordinates":[-122.191002,47.601501],"type":"Point"}
}