{
  "type": "Feature",
  "properties": {
    "addr:full":"1810 S 120th Street Seattle WA 98168",
    "addr:housenumber":"1810",
    "addr:postcode":"98168",
    "addr:street":"S 120Th Street",
    "iso:country":"US",
    "sg:address":"1810 S 120th Street",
    "sg:city":"Seattle",
    "sg:classifiers":[
        {
            "category":"Restaurant",
            "type":"Food & Drink"
        }
    ],
    "sg:phone":"+1 206 241 9377",
    "sg:postcode":"98168",
    "sg:province":"WA",
    "wof:name":"New Teriyaki Wok",
    "wof:placetype":"venue"
},
  "geometry": {"coordinates":[-122.309555,47.495667],"type":"Point"}
}