{
  "type": "Feature",
  "properties": {
    "addr:full":"15413 102nd Ave NE Bothell WA 98011",
    "addr:housenumber":"15413",
    "addr:postcode":"98011",
    "addr:street":"102Nd Ave Ne",
    "iso:country":"US",
    "sg:address":"15413 102nd Ave NE",
    "sg:city":"Bothell",
    "sg:classifiers":[
        {
            "category":"Social Services",
            "subcategory":"Child Care",
            "type":"Services"
        }
    ],
    "sg:phone":"+1 425 488 8025",
    "sg:postcode":"98011",
    "sg:province":"WA",
    "sg:tags":[
        "elementary",
        "kindergarten",
        "school",
        "academic"
    ],
    "wof:name":"Active Learning Center Preschool",
    "wof:placetype":"venue"
},
  "geometry": {"coordinates":[-122.204002,47.739601],"type":"Point"}
}