{
  "type": "Feature",
  "properties": {
    "addr:full":"15206 18th Ave W Lynnwood WA 98087",
    "addr:housenumber":"15206",
    "addr:postcode":"98087",
    "addr:street":"18Th Ave W",
    "iso:country":"US",
    "sg:address":"15206 18th Ave W",
    "sg:city":"Lynnwood",
    "sg:classifiers":[
        {
            "category":"Education",
            "subcategory":"Dance Studio",
            "type":"Public Place"
        }
    ],
    "sg:phone":"+1 425 745 9977",
    "sg:postcode":"98087",
    "sg:province":"WA",
    "sg:tags":[
        "instruction",
        "dancing"
    ],
    "wof:name":"Morning Star Korean Cultural",
    "wof:placetype":"venue"
},
  "geometry": {"coordinates":[-122.257808,47.858171],"type":"Point"}
}