{
  "type": "Feature",
  "properties": {
    "addr:full":"3021 McCormick St SE Olympia WA 98501",
    "addr:housenumber":"3021",
    "addr:postcode":"98501",
    "addr:street":"Mccormick St Se",
    "iso:country":"US",
    "sg:address":"3021 McCormick St SE",
    "sg:city":"Olympia",
    "sg:classifiers":[
        {
            "category":"Social Services",
            "subcategory":"Child Care",
            "type":"Services"
        }
    ],
    "sg:phone":"+1 360 786 5775",
    "sg:postcode":"98501",
    "sg:province":"WA",
    "sg:tags":[
        "day"
    ],
    "wof:name":"Rose Garden Day Care",
    "wof:placetype":"venue"
},
  "geometry": {"coordinates":[-122.87708600000001,47.02088],"type":"Point"}
}