{
  "type": "Feature",
  "properties": {
    "addr:full":"10214 SE Mill Plain Blvd Vancouver WA 98664",
    "addr:housenumber":"10214",
    "addr:postcode":"98664",
    "addr:street":"Se Mill Plain Blvd",
    "iso:country":"US",
    "sg:address":"10214 SE Mill Plain Blvd",
    "sg:city":"Vancouver",
    "sg:classifiers":[
        {
            "category":"Personal",
            "subcategory":"Beauty Salon",
            "type":"Services"
        }
    ],
    "sg:phone":"+1 360 892 0315",
    "sg:postcode":"98664",
    "sg:province":"WA",
    "sg:tags":[
        "shop"
    ],
    "wof:name":"Diana's Beauty Salon",
    "wof:placetype":"venue"
},
  "geometry": {"coordinates":[-122.567266,45.621049],"type":"Point"}
}