{
  "type": "Feature",
  "properties": {
    "iso:country":"US",
    "sg:address":"14924 Sunrise Dr NE",
    "sg:city":"Bainbridge Isle",
    "sg:classifiers":[
        {
            "category":"Arts & Performance",
            "subcategory":"Theater",
            "type":"Entertainment"
        },
        {
            "category":"Professional",
            "type":"Services"
        }
    ],
    "sg:phone":"+1 206 780 5443",
    "sg:postcode":"98110",
    "sg:province":"WA",
    "wof:name":"Ovation Musical Theatre Bainbr",
    "wof:placetype":"venue"
},
  "geometry": {"coordinates":[-122.510296,47.699581],"type":"Point"}
}