{
  "type": "Feature",
  "properties": {
    "addr:full":"15105 Main St E Unit 106 Sumner WA 98390",
    "addr:housenumber":"15105;106",
    "addr:postcode":"98390",
    "addr:street":"Main St E Unit",
    "iso:country":"US",
    "sg:address":"15105 Main St E Unit 106",
    "sg:city":"Sumner",
    "sg:classifiers":[
        {
            "category":"Personal",
            "subcategory":"Beauty Salon",
            "type":"Services"
        },
        {
            "category":"Personal",
            "subcategory":"Nail Salon",
            "type":"Services"
        }
    ],
    "sg:phone":"+1 253 863 4051",
    "sg:postcode":"98390",
    "sg:province":"WA",
    "wof:name":"Nails Center Facial & Waxing",
    "wof:placetype":"venue"
},
  "geometry": {"coordinates":[-122.22821500000001,47.20266],"type":"Point"}
}