{
  "type": "Feature",
  "properties": {
    "addr:full":"6540 Martin Way E Olympia WA 98516",
    "addr:housenumber":"6540",
    "addr:postcode":"98516",
    "addr:street":"Martin Way E",
    "iso:country":"US",
    "sg:address":"6540 Martin Way E",
    "sg:city":"Olympia",
    "sg:classifiers":[
        {
            "category":"Autos & Motor Vehicles",
            "subcategory":"Boat Sales",
            "type":"Retail Goods"
        }
    ],
    "sg:phone":"+1 360 491 8690",
    "sg:postcode":"98516",
    "sg:province":"WA",
    "wof:name":"Value Marine Inc",
    "wof:placetype":"venue"
},
  "geometry": {"coordinates":[-122.791714,47.051387],"type":"Point"}
}