{
  "type": "Feature",
  "properties": {
    "iso:country":"US",
    "sg:address":"407 W Main St",
    "sg:city":"Battle Ground",
    "sg:classifiers":[
        {
            "category":"Manufacturing",
            "subcategory":"Printing",
            "type":"Manufacturing & Wholesale Goods"
        }
    ],
    "sg:phone":"+1 360 687 2824",
    "sg:postcode":"98604",
    "sg:province":"WA",
    "sg:tags":[
        "commercial"
    ],
    "wof:name":"Don's Printing & Stationery",
    "wof:placetype":"venue"
},
  "geometry": {"coordinates":[-122.541742,45.780721],"type":"Point"}
}