{
  "type": "Feature",
  "properties": {
    "addr:full":"3245 Mt Baker Hwy Bellingham WA 98226",
    "addr:housenumber":"3245",
    "addr:postcode":"98226",
    "addr:street":"Mt Baker Hwy",
    "iso:country":"US",
    "sg:address":"3245 Mt Baker Hwy",
    "sg:city":"Bellingham",
    "sg:classifiers":[
        {
            "category":"Education",
            "subcategory":"Library",
            "type":"Public Place"
        }
    ],
    "sg:phone":"+1 360 592 5297",
    "sg:postcode":"98226",
    "sg:province":"WA",
    "wof:name":"Karla Ruth Buckingham",
    "wof:placetype":"venue"
},
  "geometry": {"coordinates":[-122.316513,48.824782],"type":"Point"}
}