{
  "type": "Feature",
  "properties": {
    "addr:full":"1584 McNeil St Dupont WA 98327",
    "addr:housenumber":"1584",
    "addr:postcode":"98327",
    "addr:street":"Mcneil St Dupont",
    "iso:country":"US",
    "sg:address":"1584 McNeil St",
    "sg:city":"Dupont",
    "sg:classifiers":[
        {
            "category":"Wholesale",
            "subcategory":"Electrical",
            "type":"Manufacturing & Wholesale Goods"
        }
    ],
    "sg:phone":"+1 253 912 4629",
    "sg:postcode":"98327",
    "sg:province":"WA",
    "sg:tags":[
        "fire",
        "equipment",
        "protection"
    ],
    "wof:name":"Fire Protection Inc",
    "wof:placetype":"venue"
},
  "geometry": {"coordinates":[-122.64276099999999,47.092956],"type":"Point"}
}