{
  "type": "Feature",
  "properties": {
    "addr:full":"1100 Poplar Pl S Seattle WA 98144",
    "addr:housenumber":"1100",
    "addr:postcode":"98144",
    "addr:street":"Poplar Pl S",
    "iso:country":"US",
    "sg:address":"1100 Poplar Pl S",
    "sg:city":"Seattle",
    "sg:classifiers":[
        {
            "category":"Retail",
            "subcategory":"Storage",
            "type":"Services"
        }
    ],
    "sg:phone":"+1 206 973 2458",
    "sg:postcode":"98144",
    "sg:province":"WA",
    "sg:tags":[
        "self"
    ],
    "sg:website":"www.urbanstorage.com/self_storag...",
    "wof:name":"Seattle Self Storage",
    "wof:placetype":"venue"
},
  "geometry": {"coordinates":[-122.31100600000001,47.593137],"type":"Point"}
}