{
  "type": "Feature",
  "properties": {
    "addr:full":"7803 NE Fourth Plain Rd Vancouver WA 98662",
    "addr:housenumber":"7803",
    "addr:postcode":"98662",
    "addr:street":"Ne Fourth Plain Rd",
    "iso:country":"US",
    "sg:address":"7803 NE Fourth Plain Rd",
    "sg:city":"Vancouver",
    "sg:classifiers":[
        {
            "category":"Banks & Credit Unions",
            "subcategory":"Bank",
            "type":"Services"
        }
    ],
    "sg:phone":"+1 360 253 9484",
    "sg:postcode":"98662",
    "sg:province":"WA",
    "wof:name":"Vantel Federal Credit Union",
    "wof:placetype":"venue"
},
  "geometry": {"coordinates":[-122.592299,45.646532],"type":"Point"}
}