{
  "type": "Feature",
  "properties": {
    "addr:full":"11714 NE Crestwood Dr Vancouver WA 98684",
    "addr:housenumber":"11714",
    "addr:postcode":"98684",
    "addr:street":"Ne Crestwood Dr",
    "iso:country":"US",
    "sg:address":"11714 NE Crestwood Dr",
    "sg:city":"Vancouver",
    "sg:classifiers":[
        {
            "category":"Insurance",
            "subcategory":"Hazard Insurance",
            "type":"Services"
        }
    ],
    "sg:phone":"+1 360 566 6995",
    "sg:postcode":"98684",
    "sg:province":"WA",
    "sg:website":"pinoteam.com#cid=yelp",
    "wof:name":"Pino Insurance Agency LLC",
    "wof:placetype":"venue"
},
  "geometry": {"coordinates":[-122.551722,45.622621],"type":"Point"}
}