{
  "type": "Feature",
  "properties": {
    "addr:full":"8811 S Tacoma Way Lakewood WA 98499",
    "addr:housenumber":"8811",
    "addr:postcode":"98499",
    "addr:street":"S Tacoma Way",
    "iso:country":"US",
    "sg:address":"8811 S Tacoma Way",
    "sg:city":"Lakewood",
    "sg:classifiers":[
        {
            "category":"Professional",
            "type":"Services"
        }
    ],
    "sg:phone":"+1 253 581 1777",
    "sg:postcode":"98499",
    "sg:province":"WA",
    "wof:name":"Farwest Home Korea",
    "wof:placetype":"venue"
},
  "geometry": {"coordinates":[-122.48372999999999,47.176745],"type":"Point"}
}