{
  "type": "Feature",
  "properties": {
    "addr:full":"7518 Ray Nash Dr NW Gig Harbor WA 98335",
    "addr:housenumber":"7518",
    "addr:postcode":"98335",
    "addr:street":"Ray Nash Dr Nw",
    "iso:country":"US",
    "sg:address":"7518 Ray Nash Dr NW",
    "sg:city":"Gig Harbor",
    "sg:classifiers":[
        {
            "category":"Banks & Credit Unions",
            "subcategory":"Bank",
            "type":"Services"
        }
    ],
    "sg:phone":"+1 253 853 2666",
    "sg:postcode":"98335",
    "sg:province":"WA",
    "sg:tags":[
        "institution",
        "business"
    ],
    "wof:name":"GE",
    "wof:placetype":"venue"
},
  "geometry": {"coordinates":[-122.65579700000001,47.323614],"type":"Point"}
}