{
  "type": "Feature",
  "properties": {
    "addr:full":"3209 NE 26th Ct Renton WA 98056",
    "addr:housenumber":"3209",
    "addr:postcode":"98056",
    "addr:street":"Ne 26Th Ct",
    "iso:country":"US",
    "sg:address":"3209 NE 26th Ct",
    "sg:city":"Renton",
    "sg:classifiers":[
        {
            "category":"Building & Trades",
            "subcategory":"Landscaping Services",
            "type":"Services"
        }
    ],
    "sg:phone":"+1 425 254 0427",
    "sg:postcode":"98056",
    "sg:province":"WA",
    "wof:name":"Jonathan P Mow",
    "wof:placetype":"venue"
},
  "geometry": {"coordinates":[-122.17742200000001,47.515003],"type":"Point"}
}