{
  "type": "Feature",
  "properties": {
    "addr:full":"3410 Harney St Vancouver WA 98660",
    "addr:housenumber":"3410",
    "addr:postcode":"98660",
    "addr:street":"Harney St",
    "iso:country":"US",
    "sg:address":"3410 Harney St",
    "sg:city":"Vancouver",
    "sg:classifiers":[
        {
            "category":"Manufacturing",
            "subcategory":"Tools & Machinery",
            "type":"Manufacturing & Wholesale Goods"
        }
    ],
    "sg:phone":"+1 360 693 3590",
    "sg:postcode":"98660",
    "sg:province":"WA",
    "sg:tags":[
        "mfr",
        "calligraphy"
    ],
    "wof:name":"Black Cat Studio",
    "wof:placetype":"venue"
},
  "geometry": {"coordinates":[-122.679636,45.646042],"type":"Point"}
}