{
  "type": "Feature",
  "properties": {
    "addr:full":"706 S 38th St Tacoma WA 98418",
    "addr:housenumber":"706",
    "addr:postcode":"98418",
    "addr:street":"S 38Th St",
    "iso:country":"US",
    "sg:address":"706 S 38th St",
    "sg:city":"Tacoma",
    "sg:classifiers":[
        {
            "category":"Manufacturing",
            "subcategory":"Electronics",
            "type":"Manufacturing & Wholesale Goods"
        }
    ],
    "sg:phone":"+1 253 472 9648",
    "sg:postcode":"98418",
    "sg:province":"WA",
    "sg:tags":[
        "communication",
        "equipment"
    ],
    "wof:name":"Brother Elite Svc",
    "wof:placetype":"venue"
},
  "geometry": {"coordinates":[-122.441833,47.222993],"type":"Point"}
}