{
  "type": "Feature",
  "properties": {
    "addr:full":"3403 E Moody Rd Mead WA 99021",
    "addr:housenumber":"3403",
    "addr:postcode":"99021",
    "addr:street":"E Moody Rd",
    "iso:country":"US",
    "sg:address":"3403 E Moody Rd",
    "sg:city":"Mead",
    "sg:classifiers":[
        {
            "category":"Building & Trades",
            "subcategory":"Plumbing",
            "type":"Services"
        }
    ],
    "sg:phone":"+1 509 688 5974",
    "sg:postcode":"99021",
    "sg:province":"WA",
    "sg:tags":[
        "plumber",
        "industrial",
        "contractors-commercial"
    ],
    "wof:name":"Edge Plumbing",
    "wof:placetype":"venue"
},
  "geometry": {"coordinates":[-117.361451,47.797816],"type":"Point"}
}