{
  "type": "Feature",
  "properties": {
    "iso:country":"US",
    "sg:address":"24 W Tipi Ct",
    "sg:city":"Elma",
    "sg:classifiers":[
        {
            "category":"Shopping",
            "type":"Retail Goods"
        }
    ],
    "sg:phone":"+1 360 482 6809",
    "sg:postcode":"98584",
    "sg:province":"WA",
    "sg:tags":[
        "product",
        "wood"
    ],
    "wof:name":"Distinctive Woodcraft",
    "wof:placetype":"venue"
},
  "geometry": {"coordinates":[-123.333551,47.134695],"type":"Point"}
}