{
  "type": "Feature",
  "properties": {
    "addr:full":"500 Lilly Rd NE Olympia WA 98506",
    "addr:housenumber":"500",
    "addr:postcode":"98506",
    "addr:street":"Lilly Rd Ne",
    "iso:country":"US",
    "sg:address":"500 Lilly Rd NE",
    "sg:city":"Olympia",
    "sg:classifiers":[
        {
            "category":"Deli",
            "type":"Food & Drink"
        },
        {
            "category":"Restaurant",
            "type":"Food & Drink"
        }
    ],
    "sg:phone":"+1 360 413 8776",
    "sg:postcode":"98506",
    "sg:province":"WA",
    "sg:tags":[
        "delicatessen"
    ],
    "wof:name":"Bean Town",
    "wof:placetype":"venue"
},
  "geometry": {"coordinates":[-122.84439999999999,47.052923],"type":"Point"}
}