{
  "type": "Feature",
  "properties": {
    "addr:full":"319 S 11th Ave Yakima WA 98902",
    "addr:housenumber":"319",
    "addr:postcode":"98902",
    "addr:street":"S 11Th Ave",
    "iso:country":"US",
    "sg:address":"319 S 11th Ave",
    "sg:city":"Yakima",
    "sg:classifiers":[
        {
            "category":"Health Services",
            "subcategory":"Clinic",
            "type":"Services"
        }
    ],
    "sg:phone":"+1 509 248 0820",
    "sg:postcode":"98902",
    "sg:province":"WA",
    "wof:name":"Inland Medical Evaluations",
    "wof:placetype":"venue"
},
  "geometry": {"coordinates":[-120.521895,46.593253],"type":"Point"}
}