{
  "type": "Feature",
  "properties": {
    "addr:full":"811 First Ave Ste 480 Seattle WA 98104",
    "addr:housenumber":"811",
    "addr:postcode":"98104",
    "addr:street":"First Ave Ste 480",
    "iso:country":"US",
    "sg:address":"811 First Ave Ste 480",
    "sg:city":"Seattle",
    "sg:classifiers":[
        {
            "category":"Retail",
            "subcategory":"Animal Services",
            "type":"Services"
        }
    ],
    "sg:phone":"+1 866 795 8440",
    "sg:postcode":"98104",
    "sg:province":"WA",
    "sg:tags":[
        "pet"
    ],
    "sg:website":"www.pethub.com",
    "wof:name":"PetHub",
    "wof:placetype":"venue"
},
  "geometry": {"coordinates":[-122.335384,47.603579],"type":"Point"}
}