{
  "type": "Feature",
  "properties": {
    "addr:full":"7540 N Fork Rd SE Snoqualmie WA 98065",
    "addr:housenumber":"7540",
    "addr:postcode":"98065",
    "addr:street":"N Fork Rd Se",
    "iso:country":"US",
    "sg:address":"7540 N Fork Rd SE",
    "sg:city":"Snoqualmie",
    "sg:classifiers":[
        {
            "category":"Building & Trades",
            "subcategory":"Construction",
            "type":"Services"
        }
    ],
    "sg:phone":"+1 425 454 6010",
    "sg:postcode":"98065",
    "sg:province":"WA",
    "sg:tags":[
        "home",
        "family",
        "contractor"
    ],
    "wof:name":"Oliveres Dan",
    "wof:placetype":"venue"
},
  "geometry": {"coordinates":[-121.762728,47.532785],"type":"Point"}
}