{
  "type": "Feature",
  "properties": {
    "addr:full":"83 S King St Ste 100 Seattle WA 98104",
    "addr:housenumber":"83",
    "addr:postcode":"98104",
    "addr:street":"S King St Ste 100",
    "iso:country":"US",
    "sg:address":"83 S King St Ste 100",
    "sg:city":"Seattle",
    "sg:classifiers":[
        {
            "category":"Sports & Exercise",
            "subcategory":"Gym",
            "type":"Entertainment"
        }
    ],
    "sg:phone":"+1 206 467 1800",
    "sg:postcode":"98104",
    "sg:province":"WA",
    "sg:website":"www.seattlefitness.com",
    "wof:name":"Seattle Fitness Inc",
    "wof:placetype":"venue"
},
  "geometry": {"coordinates":[-122.33550099999999,47.598322],"type":"Point"}
}