{
  "type": "Feature",
  "properties": {
    "addr:full":"4925 NE 86th St Seattle WA 98115",
    "addr:housenumber":"4925",
    "addr:postcode":"98115",
    "addr:street":"Ne 86Th St",
    "iso:country":"US",
    "sg:address":"4925 NE 86th St",
    "sg:city":"Seattle",
    "sg:classifiers":[
        {
            "category":"Education",
            "subcategory":"Vocational School",
            "type":"Public Place"
        }
    ],
    "sg:phone":"+1 206 525 7537",
    "sg:postcode":"98115",
    "sg:province":"WA",
    "sg:tags":[
        "cooking"
    ],
    "sg:website":"www.bon-vivant.com/",
    "wof:name":"Bon Vivant School of Cooking",
    "wof:placetype":"venue"
},
  "geometry": {"coordinates":[-122.275002,47.691399],"type":"Point"}
}