{
  "type": "Feature",
  "properties": {
    "addr:full":"3800 Aurora Ave N Seattle WA 98103",
    "addr:housenumber":"3800",
    "addr:postcode":"98103",
    "addr:street":"Aurora Ave N",
    "iso:country":"US",
    "sg:address":"3800 Aurora Ave N",
    "sg:city":"Seattle",
    "sg:classifiers":[
        {
            "category":"Social Services",
            "type":"Services"
        }
    ],
    "sg:phone":"+1 206 523 2551",
    "sg:postcode":"98103",
    "sg:province":"WA",
    "sg:tags":[
        "organization",
        "welfare"
    ],
    "wof:name":"Epilepsy Assoc-Western",
    "wof:placetype":"venue"
},
  "geometry": {"coordinates":[-122.34725299999999,47.652736],"type":"Point"}
}