{
  "type": "Feature",
  "properties": {
    "addr:full":"427 Kirkland Rd Chehalis WA 98532",
    "addr:housenumber":"427",
    "addr:postcode":"98532",
    "addr:street":"Kirkland Rd",
    "iso:country":"US",
    "sg:address":"427 Kirkland Rd",
    "sg:city":"Chehalis",
    "sg:classifiers":[
        {
            "category":"Wholesale",
            "subcategory":"Farm Supplies",
            "type":"Manufacturing & Wholesale Goods"
        }
    ],
    "sg:phone":"+1 360 262 3281",
    "sg:postcode":"98532",
    "sg:province":"WA",
    "sg:tags":[
        "livestock"
    ],
    "wof:name":"Herren Livestock Hauling Inc",
    "wof:placetype":"venue"
},
  "geometry": {"coordinates":[-122.894188,46.60364],"type":"Point"}
}