{
  "type": "Feature",
  "properties": {
    "addr:full":"72 Jamestown Beach Ln Sequim WA 98382",
    "addr:housenumber":"72",
    "addr:postcode":"98382",
    "addr:street":"Jamestown Beach Ln",
    "iso:country":"US",
    "sg:address":"72 Jamestown Beach Ln",
    "sg:city":"Sequim",
    "sg:classifiers":[
        {
            "category":"Arts & Performance",
            "subcategory":"Theater",
            "type":"Entertainment"
        }
    ],
    "sg:phone":"+1 360 681 2196",
    "sg:postcode":"98382",
    "sg:province":"WA",
    "sg:tags":[
        "theatrical"
    ],
    "wof:name":"Monster Robet",
    "wof:placetype":"venue"
},
  "geometry": {"coordinates":[-123.094504,48.132561],"type":"Point"}
}