{
  "type": "Feature",
  "properties": {
    "addr:full":"14150 Juanita Dr NE Bothell WA 98011",
    "addr:housenumber":"14150",
    "addr:postcode":"98011",
    "addr:street":"Juanita Dr Ne",
    "iso:country":"US",
    "sg:address":"14150 Juanita Dr NE",
    "sg:city":"Bothell",
    "sg:classifiers":[
        {
            "category":"Banks & Credit Unions",
            "subcategory":"Bank",
            "type":"Services"
        }
    ],
    "sg:phone":"+1 425 823 9302",
    "sg:postcode":"98011",
    "sg:province":"WA",
    "sg:tags":[
        "national",
        "commercial"
    ],
    "wof:name":"Keybank National Association",
    "wof:placetype":"venue"
},
  "geometry": {"coordinates":[-122.24466700000001,47.729853],"type":"Point"}
}