{
  "type": "Feature",
  "properties": {
    "addr:full":"201 W Sprague Ave Spokane WA 99201",
    "addr:housenumber":"201",
    "addr:postcode":"99201",
    "addr:street":"W Sprague Ave",
    "iso:country":"US",
    "sg:address":"201 W Sprague Ave",
    "sg:city":"Spokane",
    "sg:classifiers":[
        {
            "category":"Building & Trades",
            "subcategory":"Cleaning & Sanitation",
            "type":"Services"
        }
    ],
    "sg:phone":"+1 509 835 4958",
    "sg:postcode":"99201",
    "sg:province":"WA",
    "sg:tags":[
        "janitor"
    ],
    "wof:name":"Professional Building Maintnce",
    "wof:placetype":"venue"
},
  "geometry": {"coordinates":[-117.41488,47.657165],"type":"Point"}
}