{
  "type": "Feature",
  "properties": {
    "addr:full":"5119 S Sunward Dr Spokane WA 99223",
    "addr:housenumber":"5119",
    "addr:postcode":"99223",
    "addr:street":"S Sunward Dr",
    "iso:country":"US",
    "sg:address":"5119 S Sunward Dr",
    "sg:city":"Spokane",
    "sg:classifiers":[
        {
            "category":"Manufacturing",
            "subcategory":"Toys & Sporting Goods",
            "type":"Manufacturing & Wholesale Goods"
        }
    ],
    "sg:phone":"+1 509 443 8975",
    "sg:postcode":"99223",
    "sg:province":"WA",
    "sg:tags":[
        "mfg"
    ],
    "wof:name":"Main Street Board Games",
    "wof:placetype":"venue"
},
  "geometry": {"coordinates":[-117.34290900000001,47.605931],"type":"Point"}
}