{
  "type": "Feature",
  "properties": {
    "addr:full":"2024 Willow Ln W Tacoma WA 98466",
    "addr:housenumber":"2024",
    "addr:postcode":"98466",
    "addr:street":"Willow Ln W",
    "iso:country":"US",
    "sg:address":"2024 Willow Ln W",
    "sg:city":"Tacoma",
    "sg:classifiers":[
        {
            "category":"Museum",
            "type":"Entertainment"
        }
    ],
    "sg:phone":"+1 425 252 2335",
    "sg:postcode":"98466",
    "sg:province":"WA",
    "sg:tags":[
        "gallery"
    ],
    "wof:name":"USS Ranger Cv 61",
    "wof:placetype":"venue"
},
  "geometry": {"coordinates":[-122.539867,47.24156],"type":"Point"}
}