{
  "type": "Feature",
  "properties": {
    "addr:full":"1860 58th St NE Tacoma WA 98422",
    "addr:housenumber":"1860",
    "addr:postcode":"98422",
    "addr:street":"58Th St Ne",
    "iso:country":"US",
    "sg:address":"1860 58th St NE",
    "sg:city":"Tacoma",
    "sg:classifiers":[
        {
            "category":"Health Services",
            "subcategory":"Doctor",
            "type":"Services"
        }
    ],
    "sg:phone":"+1 253 927 7147",
    "sg:postcode":"98422",
    "sg:province":"WA",
    "wof:name":"Snoring & Sleep Apn",
    "wof:placetype":"venue"
},
  "geometry": {"coordinates":[-122.42182099999999,47.308772],"type":"Point"}
}