{
  "type": "Feature",
  "properties": {
    "addr:full":"506 N 40th St Yakima WA 98901",
    "addr:housenumber":"506",
    "addr:postcode":"98901",
    "addr:street":"N 40Th St",
    "iso:country":"US",
    "sg:address":"506 N 40th St",
    "sg:city":"Yakima",
    "sg:classifiers":[
        {
            "category":"Health Services",
            "subcategory":"Doctor",
            "type":"Services"
        }
    ],
    "sg:phone":"+1 509 494 7141",
    "sg:postcode":"98901",
    "sg:province":"WA",
    "sg:tags":[
        "physician",
        "surgeon"
    ],
    "wof:name":"Center For Retinal Laser Eye",
    "wof:placetype":"venue"
},
  "geometry": {"coordinates":[-120.447199,46.610728],"type":"Point"}
}