{
  "type": "Feature",
  "properties": {
    "addr:full":"11 NW 12th St Battle Ground WA 98604",
    "addr:housenumber":"11",
    "addr:postcode":"98604",
    "addr:street":"Nw 12Th St",
    "iso:country":"US",
    "sg:address":"11 NW 12th St",
    "sg:city":"Battle Ground",
    "sg:classifiers":[
        {
            "category":"Building & Trades",
            "subcategory":"Construction",
            "type":"Services"
        }
    ],
    "sg:phone":"+1 360 607 0000",
    "sg:postcode":"98604",
    "sg:province":"WA",
    "wof:name":"Special T Construction Inc",
    "wof:placetype":"venue"
},
  "geometry": {"coordinates":[-122.538454,45.789323],"type":"Point"}
}