{
  "type": "Feature",
  "properties": {
    "addr:full":"396 Miller Rd Friday Harbor WA 98250",
    "addr:housenumber":"396",
    "addr:postcode":"98250",
    "addr:street":"Miller Rd",
    "iso:country":"US",
    "sg:address":"396 Miller Rd",
    "sg:city":"Friday Harbor",
    "sg:classifiers":[
        {
            "category":"Retail",
            "subcategory":"Repair Shop",
            "type":"Services"
        }
    ],
    "sg:phone":"+1 360 378 4052",
    "sg:postcode":"98250",
    "sg:province":"WA",
    "wof:name":"William Richard Morrison",
    "wof:placetype":"venue"
},
  "geometry": {"coordinates":[-123.089905,48.565419],"type":"Point"}
}