{
  "type": "Feature",
  "properties": {
    "addr:full":"3515 S 15th St Tacoma WA 98405",
    "addr:housenumber":"3515",
    "addr:postcode":"98405",
    "addr:street":"S 15Th St",
    "iso:country":"US",
    "sg:address":"3515 S 15th St",
    "sg:city":"Tacoma",
    "sg:classifiers":[
        {
            "category":"Real Estate",
            "subcategory":"Real Estate Operator",
            "type":"Services"
        }
    ],
    "sg:phone":"+1 253 377 5783",
    "sg:postcode":"98405",
    "sg:province":"WA",
    "sg:tags":[
        "building",
        "nonresidential"
    ],
    "wof:name":"4117 Bridgeport LLC",
    "wof:placetype":"venue"
},
  "geometry": {"coordinates":[-122.48348300000001,47.246572],"type":"Point"}
}