{
  "type": "Feature",
  "properties": {
    "addr:full":"6285 Airport Way S Seattle WA 98108",
    "addr:housenumber":"6285",
    "addr:postcode":"98108",
    "addr:street":"Airport Way S",
    "iso:country":"US",
    "sg:address":"6285 Airport Way S",
    "sg:city":"Seattle",
    "sg:classifiers":[
        {
            "category":"Freight",
            "type":"Transportation"
        }
    ],
    "sg:phone":"+1 206 762 3338",
    "sg:postcode":"98108",
    "sg:province":"WA",
    "sg:tags":[
        "hauling",
        "trucking"
    ],
    "wof:name":"A A Dumptruck Svc",
    "wof:placetype":"venue"
},
  "geometry": {"coordinates":[-122.31356100000001,47.547121],"type":"Point"}
}