{
  "type": "Feature",
  "properties": {
    "addr:full":"1140 Marshall Ave Enumclaw WA 98022",
    "addr:housenumber":"1140",
    "addr:postcode":"98022",
    "addr:street":"Marshall Ave",
    "iso:country":"US",
    "sg:address":"1140 Marshall Ave",
    "sg:city":"Enumclaw",
    "sg:classifiers":[
        {
            "category":"Personal",
            "subcategory":"Beauty Salon",
            "type":"Services"
        }
    ],
    "sg:phone":"+1 360 825 2995",
    "sg:postcode":"98022",
    "sg:province":"WA",
    "sg:tags":[
        "hair",
        "stylist"
    ],
    "wof:name":"D And G Hair Design",
    "wof:placetype":"venue"
},
  "geometry": {"coordinates":[-121.987782,47.204708],"type":"Point"}
}