{
  "type": "Feature",
  "properties": {
    "addr:full":"1310 116th Ave NE Bellevue WA 98004",
    "addr:housenumber":"1310",
    "addr:postcode":"98004",
    "addr:street":"116Th Ave Ne",
    "iso:country":"US",
    "sg:address":"1310 116th Ave NE",
    "sg:city":"Bellevue",
    "sg:classifiers":[
        {
            "category":"Community Center",
            "type":"Public Place"
        }
    ],
    "sg:phone":"+1 425 637 9729",
    "sg:postcode":"98004",
    "sg:province":"WA",
    "sg:tags":[
        "medical"
    ],
    "sg:website":"www.cdiradiology.com/",
    "wof:name":"Center for Diagnostic Imaging",
    "wof:placetype":"venue"
},
  "geometry": {"coordinates":[-122.18489,47.621948],"type":"Point"}
}