{
  "type": "Feature",
  "properties": {
    "addr:full":"116 N Walnut Rd Spokane WA 99206",
    "addr:housenumber":"116",
    "addr:postcode":"99206",
    "addr:street":"N Walnut Rd",
    "iso:country":"US",
    "sg:address":"116 N Walnut Rd",
    "sg:city":"Spokane",
    "sg:classifiers":[
        {
            "category":"Organizations",
            "subcategory":"Religious Organization",
            "type":"Services"
        }
    ],
    "sg:phone":"+1 509 922 9678",
    "sg:postcode":"99206",
    "sg:province":"WA",
    "wof:name":"Scripture Applications Service",
    "wof:placetype":"venue"
},
  "geometry": {"coordinates":[-117.27070399999999,47.659611],"type":"Point"}
}