{
  "type": "Feature",
  "properties": {
    "addr:full":"10407 192nd Ave NE Redmond WA 98053",
    "addr:housenumber":"10407",
    "addr:postcode":"98053",
    "addr:street":"192Nd Ave Ne",
    "iso:country":"US",
    "sg:address":"10407 192nd Ave NE",
    "sg:city":"Redmond",
    "sg:classifiers":[
        {
            "category":"Farming",
            "subcategory":"Farm",
            "type":"Manufacturing & Wholesale Goods"
        }
    ],
    "sg:phone":"+1 425 868 1777",
    "sg:postcode":"98053",
    "sg:province":"WA",
    "sg:tags":[
        "crop",
        "general"
    ],
    "wof:name":"Emerald Equestrian Farms",
    "wof:placetype":"venue"
},
  "geometry": {"coordinates":[-122.084113,47.69183],"type":"Point"}
}