{
  "type": "Feature",
  "properties": {
    "addr:full":"1315 E Lewis St Pasco WA 99301",
    "addr:housenumber":"1315",
    "addr:postcode":"99301",
    "addr:street":"E Lewis St",
    "iso:country":"US",
    "sg:address":"1315 E Lewis St",
    "sg:city":"Pasco",
    "sg:classifiers":[
        {
            "category":"Personal",
            "subcategory":"Beauty Salon",
            "type":"Services"
        }
    ],
    "sg:phone":"+1 509 542 9383",
    "sg:postcode":"99301",
    "sg:province":"WA",
    "wof:name":"Arcoiris Family Hair Salo",
    "wof:placetype":"venue"
},
  "geometry": {"coordinates":[-119.079846,46.233469],"type":"Point"}
}