{
  "type": "Feature",
  "properties": {
    "addr:full":"12459 Holmes Point Dr NE Kirkland WA 98034",
    "addr:housenumber":"12459",
    "addr:postcode":"98034",
    "addr:street":"Holmes Point Dr Ne",
    "iso:country":"US",
    "sg:address":"12459 Holmes Point Dr NE",
    "sg:city":"Kirkland",
    "sg:classifiers":[
        {
            "category":"Banks & Credit Unions",
            "subcategory":"Financial Services",
            "type":"Services"
        }
    ],
    "sg:phone":"+1 425 823 1798",
    "sg:postcode":"98034",
    "sg:province":"WA",
    "sg:tags":[
        "trust",
        "management"
    ],
    "wof:name":"S Joyce Johansen Living Trust",
    "wof:placetype":"venue"
},
  "geometry": {"coordinates":[-122.255768,47.713331],"type":"Point"}
}