{
  "type": "Feature",
  "properties": {
    "addr:full":"5116 111th St SW Lakewood WA 98499",
    "addr:housenumber":"5116",
    "addr:postcode":"98499",
    "addr:street":"111Th St Sw",
    "iso:country":"US",
    "sg:address":"5116 111th St SW",
    "sg:city":"Lakewood",
    "sg:classifiers":[
        {
            "category":"Food & Beverages",
            "subcategory":"Meat & Fish",
            "type":"Retail Goods"
        }
    ],
    "sg:phone":"+1 253 588 7979",
    "sg:postcode":"98499",
    "sg:province":"WA",
    "sg:tags":[
        "shop"
    ],
    "sg:website":"www.aameats.net",
    "wof:name":"A A Meats",
    "wof:placetype":"venue"
},
  "geometry": {"coordinates":[-122.504997,47.156399],"type":"Point"}
}