{
  "type": "Feature",
  "properties": {
    "addr:full":"410 NE 70th St Apt 602 Seattle WA 98115",
    "addr:housenumber":"410;602",
    "addr:postcode":"98115",
    "addr:street":"Ne 70Th St Apt",
    "iso:country":"US",
    "sg:address":"410 NE 70th St Apt 602",
    "sg:city":"Seattle",
    "sg:classifiers":[
        {
            "category":"Professional",
            "subcategory":"Accounting & Tax Preparation",
            "type":"Services"
        }
    ],
    "sg:phone":"+1 206 545 1811",
    "sg:postcode":"98115",
    "sg:province":"WA",
    "sg:tags":[
        "public",
        "accountants-certified"
    ],
    "wof:name":"Donald W Laurie E Torcaso",
    "wof:placetype":"venue"
},
  "geometry": {"coordinates":[-122.324611,47.67904],"type":"Point"}
}