{
  "type": "Feature",
  "properties": {
    "addr:full":"29613 NE 61st Ave La Center WA 98629",
    "addr:housenumber":"29613",
    "addr:postcode":"98629",
    "addr:street":"Ne 61St Ave",
    "iso:country":"US",
    "sg:address":"29613 NE 61st Ave",
    "sg:city":"La Center",
    "sg:classifiers":[
        {
            "category":"Retail",
            "subcategory":"Auto Repair",
            "type":"Services"
        }
    ],
    "sg:phone":"+1 360 263 2500",
    "sg:postcode":"98629",
    "sg:province":"WA",
    "sg:tags":[
        "general"
    ],
    "wof:name":"Als Automotive",
    "wof:placetype":"venue"
},
  "geometry": {"coordinates":[-122.610398,45.835985],"type":"Point"}
}