{
  "type": "Feature",
  "properties": {
    "iso:country":"US",
    "sg:address":"13 158th Pl NE",
    "sg:city":"Bellevue",
    "sg:classifiers":[
        {
            "category":"Wholesale",
            "subcategory":"Dairy",
            "type":"Manufacturing & Wholesale Goods"
        }
    ],
    "sg:phone":"+1 425 641 9160",
    "sg:postcode":"98008",
    "sg:province":"WA",
    "sg:tags":[
        "frozen",
        "dessert",
        "ice",
        "cream"
    ],
    "wof:name":"Ice Cream Unlimited",
    "wof:placetype":"venue"
},
  "geometry": {"coordinates":[-122.128558,47.610417],"type":"Point"}
}