{
  "type": "Feature",
  "properties": {
    "addr:full":"408 NW 179th St Ridgefield WA 98642",
    "addr:housenumber":"408",
    "addr:postcode":"98642",
    "addr:street":"Nw 179Th St",
    "iso:country":"US",
    "sg:address":"408 NW 179th St",
    "sg:city":"Ridgefield",
    "sg:classifiers":[
        {
            "category":"Building & Trades",
            "subcategory":"Construction",
            "type":"Services"
        }
    ],
    "sg:phone":"+1 360 573 3414",
    "sg:postcode":"98642",
    "sg:province":"WA",
    "wof:name":"Paveco Paving & Seal Coating",
    "wof:placetype":"venue"
},
  "geometry": {"coordinates":[-122.67071300000001,45.75075],"type":"Point"}
}