{
  "type": "Feature",
  "properties": {
    "addr:full":"644 NE Lincoln Rd Poulsbo WA 98370",
    "addr:housenumber":"644",
    "addr:postcode":"98370",
    "addr:street":"Ne Lincoln Rd",
    "iso:country":"US",
    "sg:address":"644 NE Lincoln Rd",
    "sg:city":"Poulsbo",
    "sg:classifiers":[
        {
            "category":"Professional",
            "subcategory":"Management & Consulting",
            "type":"Services"
        }
    ],
    "sg:phone":"+1 360 377 0053",
    "sg:postcode":"98370",
    "sg:province":"WA",
    "sg:tags":[
        "consultant",
        "energy",
        "conservation"
    ],
    "wof:name":"Kitsap Community Resources",
    "wof:placetype":"venue"
},
  "geometry": {"coordinates":[-122.640401,47.735415],"type":"Point"}
}