{
  "type": "Feature",
  "properties": {
    "iso:country":"US",
    "sg:address":"1418 S Pioneer Way",
    "sg:city":"Moses Lake",
    "sg:classifiers":[
        {
            "category":"Professional",
            "subcategory":"Lawyer & Legal Services",
            "type":"Services"
        }
    ],
    "sg:phone":"+1 509 766 2883",
    "sg:postcode":"98837",
    "sg:province":"WA",
    "sg:tags":[
        "attorney"
    ],
    "wof:name":"Phelps & Assoc",
    "wof:placetype":"venue"
},
  "geometry": {"coordinates":[-119.261709,47.11435],"type":"Point"}
}