{
  "type": "Feature",
  "properties": {
    "addr:full":"14024 Burn Rd Arlington WA 98223",
    "addr:postcode":"14024;98223",
    "addr:street":"Burn Rd",
    "iso:country":"US",
    "sg:address":"14024 Burn Rd",
    "sg:city":"Arlington",
    "sg:classifiers":[
        {
            "category":"Farming",
            "subcategory":"Livestock Farm",
            "type":"Manufacturing & Wholesale Goods"
        }
    ],
    "sg:phone":"+1 360 691 7784",
    "sg:postcode":"98223",
    "sg:province":"WA",
    "sg:tags":[
        "beef",
        "feedlot",
        "cattle"
    ],
    "wof:name":"Rnbs Beef",
    "wof:placetype":"venue"
},
  "geometry": {"coordinates":[-122.046154,48.124944],"type":"Point"}
}