{
  "type": "Feature",
  "properties": {
    "addr:full":"3347 4th Ave S Seattle WA 98134",
    "addr:housenumber":"3347",
    "addr:postcode":"98134",
    "addr:street":"4Th Ave S",
    "iso:country":"US",
    "sg:address":"3347 4th Ave S",
    "sg:city":"Seattle",
    "sg:classifiers":[
        {
            "category":"Home & Garden",
            "subcategory":"Household Appliances",
            "type":"Retail Goods"
        }
    ],
    "sg:phone":"+1 206 624 4394",
    "sg:postcode":"98134",
    "sg:province":"WA",
    "sg:website":"www.aquaquip.com",
    "wof:name":"Aqua Quip",
    "wof:placetype":"venue"
},
  "geometry": {"coordinates":[-122.32910200000001,47.574119],"type":"Point"}
}