{
  "type": "Feature",
  "properties": {
    "addr:full":"5031 Sheridan Dr SE Lacey WA 98503",
    "addr:housenumber":"5031",
    "addr:postcode":"98503",
    "addr:street":"Sheridan Dr Se",
    "iso:country":"US",
    "sg:address":"5031 Sheridan Dr SE",
    "sg:city":"Lacey",
    "sg:classifiers":[
        {
            "category":"Shopping",
            "subcategory":"Used Merchandise",
            "type":"Retail Goods"
        }
    ],
    "sg:phone":"+1 360 491 5010",
    "sg:postcode":"98503",
    "sg:province":"WA",
    "wof:name":"Dj Antiques",
    "wof:placetype":"venue"
},
  "geometry": {"coordinates":[-122.81493500000001,47.028303],"type":"Point"}
}