{
  "type": "Feature",
  "properties": {
    "addr:full":"6507 Swans Trail Rd Snohomish WA 98290",
    "addr:housenumber":"6507",
    "addr:postcode":"98290",
    "addr:street":"Swans Trail Rd",
    "iso:country":"US",
    "sg:address":"6507 Swans Trail Rd",
    "sg:city":"Snohomish",
    "sg:classifiers":[
        {
            "category":"Health Services",
            "subcategory":"Nursing And Care Facility",
            "type":"Services"
        }
    ],
    "sg:phone":"+1 425 334 9849",
    "sg:postcode":"98290",
    "sg:province":"WA",
    "sg:tags":[
        "skilled"
    ],
    "wof:name":"Heritage Hall",
    "wof:placetype":"venue"
},
  "geometry": {"coordinates":[-122.14122,47.936124],"type":"Point"}
}