{
  "type": "Feature",
  "properties": {
    "iso:country":"US",
    "sg:address":"3208 Tarabachia St",
    "sg:city":"Gig Harbor",
    "sg:classifiers":[
        {
            "category":"Personal",
            "subcategory":"Beauty Salon",
            "type":"Services"
        }
    ],
    "sg:phone":"+1 253 851 2883",
    "sg:postcode":"98335",
    "sg:province":"WA",
    "wof:name":"Athena's Salon & Spa",
    "wof:placetype":"venue"
},
  "geometry": {"coordinates":[-122.581648,47.32882],"type":"Point"}
}