{
  "type": "Feature",
  "properties": {
    "addr:full":"1509 1st Ave Seattle WA 98101",
    "addr:housenumber":"1509",
    "addr:postcode":"98101",
    "addr:street":"1St Ave",
    "iso:country":"US",
    "sg:address":"1509 1st Ave",
    "sg:city":"Seattle",
    "sg:classifiers":[
        {
            "category":"Food & Beverages",
            "subcategory":"Groceries & Convenience Stores",
            "type":"Retail Goods"
        }
    ],
    "sg:phone":"+1 206 682 8140",
    "sg:postcode":"98101",
    "sg:province":"WA",
    "wof:name":"Kosher Delight",
    "wof:placetype":"venue"
},
  "geometry": {"coordinates":[-122.34092699999999,47.609698],"type":"Point"}
}