{
  "type": "Feature",
  "properties": {
    "addr:full":"1101 1st St Davenport WA 99122",
    "addr:housenumber":"1101",
    "addr:postcode":"99122",
    "addr:street":"1St St",
    "iso:country":"US",
    "sg:address":"1101 1st St",
    "sg:city":"Davenport",
    "sg:classifiers":[
        {
            "category":"Place Of Worship",
            "subcategory":"Church",
            "type":"Public Place"
        },
        {
            "category":"Place Of Worship",
            "type":"Public Place"
        },
        {
            "category":"Organizations",
            "subcategory":"Religious Organization",
            "type":"Services"
        }
    ],
    "sg:phone":"+1 509 725 3270",
    "sg:postcode":"99122",
    "sg:province":"WA",
    "sg:tags":[
        "churches-non-denominational"
    ],
    "wof:name":"Trinity Bible Fellowship",
    "wof:placetype":"venue"
},
  "geometry": {"coordinates":[-118.142174,47.649231],"type":"Point"}
}