{
  "type": "Feature",
  "properties": {
    "addr:full":"851 Dalles Mountain Rd Centerville WA 98613",
    "addr:housenumber":"851",
    "addr:postcode":"98613",
    "addr:street":"Dalles Mountain Rd",
    "iso:country":"US",
    "sg:address":"851 Dalles Mountain Rd",
    "sg:city":"Centerville",
    "sg:classifiers":[
        {
            "category":"Farming",
            "subcategory":"Farm",
            "type":"Manufacturing & Wholesale Goods"
        }
    ],
    "sg:phone":"+1 509 773 5176",
    "sg:postcode":"98613",
    "sg:province":"WA",
    "sg:tags":[
        "crop",
        "general"
    ],
    "wof:name":"Garner Brothers Corp",
    "wof:placetype":"venue"
},
  "geometry": {"coordinates":[-120.924318,45.70874],"type":"Point"}
}