{
  "type": "Feature",
  "properties": {
    "addr:full":"2112 Madison St Everett WA 98203",
    "addr:housenumber":"2112",
    "addr:postcode":"98203",
    "addr:street":"Madison St",
    "iso:country":"US",
    "sg:address":"2112 Madison St",
    "sg:city":"Everett",
    "sg:classifiers":[
        {
            "category":"Insurance",
            "subcategory":"Insurance Agent",
            "type":"Services"
        }
    ],
    "sg:phone":"+1 425 353 4333",
    "sg:postcode":"98203",
    "sg:province":"WA",
    "wof:name":"Larry Conley Insurance",
    "wof:placetype":"venue"
},
  "geometry": {"coordinates":[-122.203816,47.936166],"type":"Point"}
}