{
  "type": "Feature",
  "properties": {
    "addr:full":"1110 Broadway Everett WA 98201",
    "addr:housenumber":"1110",
    "addr:postcode":"98201",
    "addr:street":"Broadway",
    "iso:country":"US",
    "sg:address":"1110 Broadway",
    "sg:city":"Everett",
    "sg:classifiers":[
        {
            "category":"Autos & Motor Vehicles",
            "subcategory":"Automobile Sales",
            "type":"Retail Goods"
        },
        {
            "category":"Home & Garden",
            "subcategory":"Home Furnishings",
            "type":"Retail Goods"
        },
        {
            "category":"Manufacturing",
            "subcategory":"Building Materials",
            "type":"Manufacturing & Wholesale Goods"
        },
        {
            "category":"Recreation",
            "subcategory":"Barbecue",
            "type":"Entertainment"
        }
    ],
    "sg:phone":"+1 425 259 4621",
    "sg:postcode":"98201",
    "sg:province":"WA",
    "sg:tags":[
        "grill",
        "mantel",
        "supply",
        "equipment",
        "stoves-heating",
        "fireplace"
    ],
    "sg:website":"http://www.andersonfireplace.net",
    "wof:name":"Anderson Fireplace & Spas",
    "wof:placetype":"venue"
},
  "geometry": {"coordinates":[-122.200929,48.002618],"type":"Point"}
}