{
  "type": "Feature",
  "properties": {
    "addr:full":"302 1st St Kirkland WA 98033",
    "addr:housenumber":"302",
    "addr:postcode":"98033",
    "addr:street":"1St St",
    "iso:country":"US",
    "sg:address":"302 1st St",
    "sg:city":"Kirkland",
    "sg:classifiers":[
        {
            "category":"Social Services",
            "type":"Services"
        }
    ],
    "sg:phone":"+1 425 889 7880",
    "sg:postcode":"98033",
    "sg:province":"WA",
    "sg:website":"www.hope-link.org",
    "wof:name":"Hopelink",
    "wof:placetype":"venue"
},
  "geometry": {"coordinates":[-122.208276,47.678045],"type":"Point"}
}