{
  "type": "Feature",
  "properties": {
    "addr:full":"4300 Yaksum Canyon Rd Cashmere WA 98815",
    "addr:postcode":"4300;98815",
    "addr:street":"Yaksum Canyon Rd",
    "iso:country":"US",
    "sg:address":"4300 Yaksum Canyon Rd",
    "sg:city":"Cashmere",
    "sg:classifiers":[
        {
            "category":"Professional",
            "subcategory":"Business Services",
            "type":"Services"
        }
    ],
    "sg:phone":"+1 509 782 3729",
    "sg:postcode":"98815",
    "sg:province":"WA",
    "wof:name":"Quality Fruit Inspection Svc",
    "wof:placetype":"venue"
},
  "geometry": {"coordinates":[-120.46904000000001,47.494733],"type":"Point"}
}