{
  "type": "Feature",
  "properties": {
    "iso:country":"US",
    "sg:address":"9921 35th Ave NE",
    "sg:city":"Marysville",
    "sg:classifiers":[
        {
            "category":"Health Services",
            "subcategory":"Clinic",
            "type":"Services"
        }
    ],
    "sg:phone":"+1 360 651 2837",
    "sg:postcode":"98270",
    "sg:province":"WA",
    "sg:tags":[
        "home",
        "care"
    ],
    "wof:name":"Rose Cottage Adult Family Home",
    "wof:placetype":"venue"
},
  "geometry": {"coordinates":[-122.183747,48.085345],"type":"Point"}
}