{
  "type": "Feature",
  "properties": {
    "addr:full":"11419 Madera Dr SW Lakewood WA 98499",
    "addr:housenumber":"11419",
    "addr:postcode":"98499",
    "addr:street":"Madera Dr Sw",
    "iso:country":"US",
    "sg:address":"11419 Madera Dr SW",
    "sg:city":"Lakewood",
    "sg:classifiers":[
        {
            "category":"Manufacturing",
            "subcategory":"Tools & Machinery",
            "type":"Manufacturing & Wholesale Goods"
        }
    ],
    "sg:phone":"+1 253 596 3675",
    "sg:postcode":"98499",
    "sg:province":"WA",
    "sg:tags":[
        "instrument",
        "medical",
        "design"
    ],
    "wof:name":"Lumen Medical",
    "wof:placetype":"venue"
},
  "geometry": {"coordinates":[-122.52595700000001,47.154035],"type":"Point"}
}