{
  "type": "Feature",
  "properties": {
    "addr:full":"555 Dayton St Edmonds WA 98020",
    "addr:housenumber":"555",
    "addr:postcode":"98020",
    "addr:street":"Dayton",
    "iso:country":"US",
    "sg:address":"555 Dayton St",
    "sg:city":"Edmonds",
    "sg:classifiers":[
        {
            "category":"Travel",
            "subcategory":"Travel Agent",
            "type":"Entertainment"
        }
    ],
    "sg:phone":"+1 425 697 5013",
    "sg:postcode":"98020",
    "sg:province":"WA",
    "sg:tags":[
        "operator",
        "tour",
        "tours",
        "promoter"
    ],
    "sg:website":"www.all-mountain.com",
    "wof:name":"All Mountain Vacations",
    "wof:placetype":"venue"
},
  "geometry": {"coordinates":[-122.37620200000001,47.809784],"type":"Point"}
}