{
  "type": "Feature",
  "properties": {
    "iso:country":"US",
    "sg:address":"2020 Vintage Rd",
    "sg:city":"Zillah",
    "sg:classifiers":[
        {
            "category":"Food & Beverages",
            "subcategory":"Liquor & Beverages",
            "type":"Retail Goods"
        }
    ],
    "sg:phone":"+1 509 829 3094",
    "sg:postcode":"98953",
    "sg:province":"WA",
    "wof:name":"Washington Wine & Beverage Co",
    "wof:placetype":"venue"
},
  "geometry": {"coordinates":[-120.240877,46.455969],"type":"Point"}
}