{
  "type": "Feature",
  "properties": {
    "addr:full":"234 1st Ave NW Ephrata WA 98823",
    "addr:housenumber":"234",
    "addr:postcode":"98823",
    "addr:street":"1St Ave Nw",
    "iso:country":"US",
    "sg:address":"234 1st Ave NW",
    "sg:city":"Ephrata",
    "sg:classifiers":[
        {
            "category":"Organizations",
            "subcategory":"Non-profit Organization",
            "type":"Services"
        }
    ],
    "sg:phone":"+1 509 754 4596",
    "sg:postcode":"98823",
    "sg:province":"WA",
    "wof:name":"Columbia Basin Foundation",
    "wof:placetype":"venue"
},
  "geometry": {"coordinates":[-119.552001,47.321882],"type":"Point"}
}