{
  "type": "Feature",
  "properties": {
    "addr:full":"200 W Thomas St Seattle WA 98119",
    "addr:housenumber":"200",
    "addr:postcode":"98119",
    "addr:street":"W Thomas St",
    "iso:country":"US",
    "sg:address":"200 W Thomas St",
    "sg:city":"Seattle",
    "sg:classifiers":[
        {
            "category":"Professional",
            "subcategory":"Engineering",
            "type":"Services"
        }
    ],
    "sg:phone":"+1 206 494 9400",
    "sg:postcode":"98119",
    "sg:province":"WA",
    "sg:tags":[
        "engineer"
    ],
    "sg:website":"www.harrisgroup.com",
    "wof:name":"Harris Group Inc",
    "wof:placetype":"venue"
},
  "geometry": {"coordinates":[-122.360614,47.620954],"type":"Point"}
}