{
  "type": "Feature",
  "properties": {
    "addr:full":"404 N Sampson St Ellensburg WA 98926",
    "addr:housenumber":"404",
    "addr:postcode":"98926",
    "addr:street":"N Sampson St",
    "iso:country":"US",
    "sg:address":"404 N Sampson St",
    "sg:city":"Ellensburg",
    "sg:classifiers":[
        {
            "category":"Professional",
            "subcategory":"Business Services",
            "type":"Services"
        }
    ],
    "sg:phone":"+1 509 962 2977",
    "sg:postcode":"98926",
    "sg:province":"WA",
    "sg:tags":[
        "good"
    ],
    "wof:name":"Jeffrey Leighton Snedeker",
    "wof:placetype":"venue"
},
  "geometry": {"coordinates":[-120.54039899999999,46.99665],"type":"Point"}
}