{
  "type": "Feature",
  "properties": {
    "addr:full":"7911 W Grandridge Blvd Kennewick WA 99336",
    "addr:housenumber":"7911",
    "addr:postcode":"99336",
    "addr:street":"W Grandridge Blvd",
    "iso:country":"US",
    "sg:address":"7911 W Grandridge Blvd",
    "sg:city":"Kennewick",
    "sg:classifiers":[
        {
            "category":"Personal",
            "subcategory":"Beauty Salon",
            "type":"Services"
        }
    ],
    "sg:phone":"+1 509 737 8510",
    "sg:postcode":"99336",
    "sg:province":"WA",
    "wof:name":"Debbie's",
    "wof:placetype":"venue"
},
  "geometry": {"coordinates":[-119.22899,46.218508],"type":"Point"}
}