{
  "type": "Feature",
  "properties": {
    "addr:full":"2639 NW Market St Seattle WA 98107",
    "addr:housenumber":"2639",
    "addr:postcode":"98107",
    "addr:street":"Nw Market St",
    "iso:country":"US",
    "sg:address":"2639 NW Market St",
    "sg:city":"Seattle",
    "sg:classifiers":[
        {
            "category":"Retail",
            "subcategory":"Auto Repair",
            "type":"Services"
        }
    ],
    "sg:phone":"+1 206 789 5455",
    "sg:postcode":"98107",
    "sg:province":"WA",
    "sg:website":"xrayautomotive.com",
    "wof:name":"X-Ray Auto",
    "wof:placetype":"venue"
},
  "geometry": {"coordinates":[-122.39099899999999,47.668598],"type":"Point"}
}