{
  "type": "Feature",
  "properties": {
    "addr:full":"1204 Skyridge St SE Lacey WA 98503",
    "addr:housenumber":"1204",
    "addr:postcode":"98503",
    "addr:street":"Skyridge St Se",
    "iso:country":"US",
    "sg:address":"1204 Skyridge St SE",
    "sg:city":"Lacey",
    "sg:classifiers":[
        {
            "category":"Retail",
            "subcategory":"Repair Shop",
            "type":"Services"
        }
    ],
    "sg:phone":"+1 360 456 2664",
    "sg:postcode":"98503",
    "sg:province":"WA",
    "sg:tags":[
        "upholstery"
    ],
    "wof:name":"Tillmon & Daughter",
    "wof:placetype":"venue"
},
  "geometry": {"coordinates":[-122.776076,47.038081],"type":"Point"}
}