{
  "type": "Feature",
  "properties": {
    "addr:full":"4012 N Orchard St Tacoma WA 98407",
    "addr:housenumber":"4012",
    "addr:postcode":"98407",
    "addr:street":"N Orchard St",
    "iso:country":"US",
    "sg:address":"4012 N Orchard St",
    "sg:city":"Tacoma",
    "sg:classifiers":[
        {
            "category":"Building & Trades",
            "subcategory":"Cleaning & Sanitation",
            "type":"Services"
        }
    ],
    "sg:phone":"+1 253 752 7286",
    "sg:postcode":"98407",
    "sg:province":"WA",
    "sg:tags":[
        "protection",
        "fabric",
        "furniture"
    ],
    "wof:name":"Glow Carpet Glow, Inc",
    "wof:placetype":"venue"
},
  "geometry": {"coordinates":[-122.50514200000001,47.28577],"type":"Point"}
}