{
  "type": "Feature",
  "properties": {
    "addr:full":"122 S Monroe St Spokane WA 99201",
    "addr:housenumber":"122",
    "addr:postcode":"99201",
    "addr:street":"S Monroe St",
    "iso:country":"US",
    "sg:address":"122 S Monroe St",
    "sg:city":"Spokane",
    "sg:classifiers":[
        {
            "category":"Communications",
            "subcategory":"Film & Video Production",
            "type":"Services"
        }
    ],
    "sg:phone":"+1 509 455 6310",
    "sg:postcode":"99201",
    "sg:province":"WA",
    "sg:tags":[
        "taping"
    ],
    "wof:name":"Corner Booth Productions",
    "wof:placetype":"venue"
},
  "geometry": {"coordinates":[-117.426608,47.656427],"type":"Point"}
}