{
  "type": "Feature",
  "properties": {
    "addr:full":"6817 27th St W University Place WA 98466",
    "addr:housenumber":"6817",
    "addr:postcode":"98466",
    "addr:street":"27Th St W;Place",
    "iso:country":"US",
    "sg:address":"6817 27th St W",
    "sg:city":"University Place",
    "sg:classifiers":[
        {
            "category":"Government",
            "subcategory":"Post Office",
            "type":"Public Place"
        }
    ],
    "sg:phone":"+1 253 000 1111",
    "sg:postcode":"98466",
    "sg:province":"WA",
    "wof:name":"US Post Office",
    "wof:placetype":"venue"
},
  "geometry": {"coordinates":[-122.527005,47.235508],"type":"Point"}
}