{
  "type": "Feature",
  "properties": {
    "iso:country":"US",
    "sg:address":"321 W Indiana Ave",
    "sg:city":"Spokane",
    "sg:classifiers":[
        {
            "category":"Shopping",
            "subcategory":"Clothing, Apparel, & Fashions",
            "type":"Retail Goods"
        }
    ],
    "sg:phone":"+1 509 328 4670",
    "sg:postcode":"99205",
    "sg:province":"WA",
    "sg:tags":[
        "sewing"
    ],
    "wof:name":"Allinda Yarns",
    "wof:placetype":"venue"
},
  "geometry": {"coordinates":[-117.417039,47.674839],"type":"Point"}
}