{
  "type": "Feature",
  "properties": {
    "iso:country":"US",
    "sg:address":"3606 Hopewell Rd",
    "sg:city":"Everson",
    "sg:classifiers":[
        {
            "category":"Farming",
            "subcategory":"Livestock Farm",
            "type":"Manufacturing & Wholesale Goods"
        }
    ],
    "sg:phone":"+1 360 966 0266",
    "sg:postcode":"98247",
    "sg:province":"WA",
    "sg:tags":[
        "specialty",
        "animal"
    ],
    "wof:name":"Saber Tooth Worm Farm",
    "wof:placetype":"venue"
},
  "geometry": {"coordinates":[-122.291788,48.883737],"type":"Point"}
}