{
  "type": "Feature",
  "properties": {
    "iso:country":"US",
    "sg:address":"2724 Pacific Ave SE",
    "sg:city":"Olympia",
    "sg:classifiers":[
        {
            "category":"Organizations",
            "subcategory":"Professional Association",
            "type":"Services"
        }
    ],
    "sg:phone":"+1 360 754 1912",
    "sg:postcode":"98501",
    "sg:province":"WA",
    "sg:tags":[
        "business"
    ],
    "wof:name":"Independent Towers Washington",
    "wof:placetype":"venue"
},
  "geometry": {"coordinates":[-122.863243,47.044204],"type":"Point"}
}