{
  "type": "Feature",
  "properties": {
    "addr:full":"3830 204th St SW Lynnwood WA 98036",
    "addr:housenumber":"3830",
    "addr:postcode":"98036",
    "addr:street":"204Th St Sw",
    "iso:country":"US",
    "sg:address":"3830 204th St SW",
    "sg:city":"Lynnwood",
    "sg:classifiers":[
        {
            "category":"Retail",
            "subcategory":"Auto Repair",
            "type":"Services"
        }
    ],
    "sg:phone":"+1 425 776 6749",
    "sg:postcode":"98036",
    "sg:province":"WA",
    "sg:tags":[
        "general"
    ],
    "wof:name":"Larch Way Auto",
    "wof:placetype":"venue"
},
  "geometry": {"coordinates":[-122.289339,47.813694],"type":"Point"}
}