{
  "type": "Feature",
  "properties": {
    "addr:full":"7406 Greenwood Ave N Seattle WA 98103",
    "addr:housenumber":"7406",
    "addr:postcode":"98103",
    "addr:street":"Greenwood Ave N",
    "iso:country":"US",
    "sg:address":"7406 Greenwood Ave N",
    "sg:city":"Seattle",
    "sg:classifiers":[
        {
            "category":"Arts & Performance",
            "subcategory":"Art Gallery",
            "type":"Entertainment"
        }
    ],
    "sg:phone":"+1 206 913 2470",
    "sg:postcode":"98103",
    "sg:province":"WA",
    "sg:website":"www.assembleshop.com",
    "wof:name":"Assemble Gallery & Studio",
    "wof:placetype":"venue"
},
  "geometry": {"coordinates":[-122.354996,47.682835],"type":"Point"}
}