{
  "type": "Feature",
  "properties": {
    "addr:full":"17402 N Brookside Ln Colbert WA 99005",
    "addr:housenumber":"17402",
    "addr:postcode":"99005",
    "addr:street":"N Brookside Ln Colbert",
    "iso:country":"US",
    "sg:address":"17402 N Brookside Ln",
    "sg:city":"Colbert",
    "sg:classifiers":[
        {
            "category":"Insurance",
            "subcategory":"Insurance Agent",
            "type":"Services"
        }
    ],
    "sg:phone":"+1 509 466 7914",
    "sg:postcode":"99005",
    "sg:province":"WA",
    "wof:name":"Wall Street Properties",
    "wof:placetype":"venue"
},
  "geometry": {"coordinates":[-117.35605,47.815068],"type":"Point"}
}