{
  "type": "Feature",
  "properties": {
    "addr:full":"622 Western Ave Seattle WA 98104",
    "addr:housenumber":"622",
    "addr:postcode":"98104",
    "addr:street":"Western Ave",
    "iso:country":"US",
    "sg:address":"622 Western Ave",
    "sg:city":"Seattle",
    "sg:classifiers":[
        {
            "category":"Real Estate",
            "subcategory":"Real Estate Services",
            "type":"Services"
        },
        {
            "category":"Banks & Credit Unions",
            "subcategory":"Financial Services",
            "type":"Services"
        }
    ],
    "sg:phone":"+1 206 957 3332",
    "sg:postcode":"98104",
    "sg:province":"WA",
    "sg:tags":[
        "loan",
        "processing"
    ],
    "wof:name":"Liberty Home Loan",
    "wof:placetype":"venue"
},
  "geometry": {"coordinates":[-122.335487,47.601807],"type":"Point"}
}