{
  "type": "Feature",
  "properties": {
    "addr:full":"2101 112th Ave NE Ste 100 Bellevue WA 98004",
    "addr:housenumber":"2101",
    "addr:postcode":"98004",
    "addr:street":"112Th Ave Ne Ste 100",
    "iso:country":"US",
    "sg:address":"2101 112th Ave NE Ste 100",
    "sg:city":"Bellevue",
    "sg:classifiers":[
        {
            "category":"Banks & Credit Unions",
            "subcategory":"Investment Brokerage",
            "type":"Services"
        },
        {
            "category":"Banks & Credit Unions",
            "subcategory":"Financial Services",
            "type":"Services"
        }
    ],
    "sg:phone":"+1 425 373 9087",
    "sg:postcode":"98004",
    "sg:province":"WA",
    "sg:tags":[
        "investing",
        "advisory",
        "planner"
    ],
    "wof:name":"Westrum Janice K M S Financial Services",
    "wof:placetype":"venue"
},
  "geometry": {"coordinates":[-122.191002,47.629002],"type":"Point"}
}