{
  "type": "Feature",
  "properties": {
    "addr:full":"3925 88th St NE Marysville WA 98270",
    "addr:housenumber":"3925",
    "addr:postcode":"98270",
    "addr:street":"88Th St Ne",
    "iso:country":"US",
    "sg:address":"3925 88th St NE",
    "sg:city":"Marysville",
    "sg:classifiers":[
        {
            "category":"Retail",
            "subcategory":"Auto Repair",
            "type":"Services"
        }
    ],
    "sg:phone":"+1 360 653 4027",
    "sg:postcode":"98270",
    "sg:province":"WA",
    "sg:tags":[
        "repairing",
        "automobile"
    ],
    "wof:name":"Superior Performance Auto Svc",
    "wof:placetype":"venue"
},
  "geometry": {"coordinates":[-122.17877799999999,48.075748],"type":"Point"}
}