{
  "type": "Feature",
  "properties": {
    "iso:country":"US",
    "sg:address":"3005 112th Ave NE",
    "sg:city":"Bellevue",
    "sg:classifiers":[
        {
            "category":"Health Services",
            "subcategory":"Clinic",
            "type":"Services"
        }
    ],
    "sg:phone":"+1 425 803 9030",
    "sg:postcode":"98004",
    "sg:province":"WA",
    "sg:tags":[
        "organization",
        "maintenance"
    ],
    "sg:website":"www.gwla.com",
    "wof:name":"Great West Healthcare",
    "wof:placetype":"venue"
},
  "geometry": {"coordinates":[-122.193314,47.636705],"type":"Point"}
}