{
  "type": "Feature",
  "properties": {
    "addr:full":"9602 Double Ditch Rd Lynden WA 98264",
    "addr:housenumber":"9602",
    "addr:postcode":"98264",
    "addr:street":"Double Ditch Rd",
    "iso:country":"US",
    "sg:address":"9602 Double Ditch Rd",
    "sg:city":"Lynden",
    "sg:classifiers":[
        {
            "category":"Building & Trades",
            "subcategory":"Construction",
            "type":"Services"
        }
    ],
    "sg:phone":"+1 360 318 0535",
    "sg:postcode":"98264",
    "sg:province":"WA",
    "sg:tags":[
        "excavation",
        "contractor"
    ],
    "wof:name":"Derek Dekoster",
    "wof:placetype":"venue"
},
  "geometry": {"coordinates":[-122.47398,48.990342],"type":"Point"}
}