{
  "type": "Feature",
  "properties": {
    "addr:full":"501 E 18th Ave Ellensburg WA 98926",
    "addr:housenumber":"501",
    "addr:postcode":"98926",
    "addr:street":"E 18Th Ave",
    "iso:country":"US",
    "sg:address":"501 E 18th Ave",
    "sg:city":"Ellensburg",
    "sg:classifiers":[
        {
            "category":"Real Estate",
            "subcategory":"Real Estate Operator",
            "type":"Services"
        }
    ],
    "sg:phone":"+1 509 962 5508",
    "sg:postcode":"98926",
    "sg:province":"WA",
    "sg:tags":[
        "building",
        "apartment"
    ],
    "wof:name":"University Place Apartments",
    "wof:placetype":"venue"
},
  "geometry": {"coordinates":[-120.54074900000001,47.01044],"type":"Point"}
}