{
  "type": "Feature",
  "properties": {
    "addr:full":"6216 51st Ave NW Gig Harbor WA 98335",
    "addr:housenumber":"6216",
    "addr:postcode":"98335",
    "addr:street":"51St Ave Nw",
    "iso:country":"US",
    "sg:address":"6216 51st Ave NW",
    "sg:city":"Gig Harbor",
    "sg:classifiers":[
        {
            "category":"Professional",
            "subcategory":"Business Services",
            "type":"Services"
        }
    ],
    "sg:phone":"+1 253 853 4260",
    "sg:postcode":"98335",
    "sg:province":"WA",
    "wof:name":"Doumar Enterprises",
    "wof:placetype":"venue"
},
  "geometry": {"coordinates":[-122.60659099999999,47.314877],"type":"Point"}
}