{
  "type": "Feature",
  "properties": {
    "addr:full":"827 NW 49th St Seattle WA 98107",
    "addr:housenumber":"827",
    "addr:postcode":"98107",
    "addr:street":"Nw 49Th St",
    "iso:country":"US",
    "sg:address":"827 NW 49th St",
    "sg:city":"Seattle",
    "sg:classifiers":[
        {
            "category":"Shopping",
            "subcategory":"Hobbies, Toys, & Games",
            "type":"Retail Goods"
        }
    ],
    "sg:phone":"+1 206 526 1096",
    "sg:postcode":"98107",
    "sg:province":"WA",
    "sg:tags":[
        "supply"
    ],
    "sg:website":"www.cheapass.com",
    "wof:name":"Cheapass Games",
    "wof:placetype":"venue"
},
  "geometry": {"coordinates":[-122.368213,47.664306],"type":"Point"}
}