{
  "type": "Feature",
  "properties": {
    "addr:full":"5412 81st Avenue Ct W Tacoma WA 98467",
    "addr:housenumber":"5412",
    "addr:postcode":"98467",
    "addr:street":"81St Avenue Ct W",
    "iso:country":"US",
    "sg:address":"5412 81st Avenue Ct W",
    "sg:city":"Tacoma",
    "sg:classifiers":[
        {
            "category":"Wholesale",
            "subcategory":"Stationery",
            "type":"Manufacturing & Wholesale Goods"
        }
    ],
    "sg:phone":"+1 253 565 6913",
    "sg:postcode":"98467",
    "sg:province":"WA",
    "sg:tags":[
        "supply"
    ],
    "wof:name":"Forms 2",
    "wof:placetype":"venue"
},
  "geometry": {"coordinates":[-122.545647,47.207266],"type":"Point"}
}