{
  "type": "Feature",
  "properties": {
    "addr:full":"39933 SE Moffet Rd Washougal WA 98671",
    "addr:housenumber":"39933",
    "addr:postcode":"98671",
    "addr:street":"Se Moffet Rd",
    "iso:country":"US",
    "sg:address":"39933 SE Moffet Rd",
    "sg:city":"Washougal",
    "sg:classifiers":[
        {
            "category":"Farming",
            "subcategory":"Livestock Farm",
            "type":"Manufacturing & Wholesale Goods"
        }
    ],
    "sg:phone":"+1 360 835 8007",
    "sg:postcode":"98671",
    "sg:province":"WA",
    "sg:tags":[
        "equine"
    ],
    "wof:name":"K & D Mules",
    "wof:placetype":"venue"
},
  "geometry": {"coordinates":[-122.262615,45.601685],"type":"Point"}
}