{
  "type": "Feature",
  "properties": {
    "addr:full":"5050 State Highway 303 NE Ste 50 Bremerton WA 98311",
    "addr:housenumber":"5050;50",
    "addr:postcode":"98311",
    "addr:street":"State Highway 303 Ne Ste",
    "iso:country":"US",
    "sg:address":"5050 State Highway 303 NE Ste 50",
    "sg:city":"Bremerton",
    "sg:classifiers":[
        {
            "category":"Personal",
            "subcategory":"Beauty Salon",
            "type":"Services"
        }
    ],
    "sg:phone":"+1 360 479 3943",
    "sg:postcode":"98311",
    "sg:province":"WA",
    "sg:website":"http://www.perfectlooksalons.com",
    "wof:name":"Perfect Look Salons",
    "wof:placetype":"venue"
},
  "geometry": {"coordinates":[-122.62885300000001,47.609901],"type":"Point"}
}