{
  "type": "Feature",
  "properties": {
    "addr:full":"701 26th St SE Auburn WA 98002",
    "addr:housenumber":"701",
    "addr:postcode":"98002",
    "addr:street":"26Th St Se",
    "iso:country":"US",
    "sg:address":"701 26th St SE",
    "sg:city":"Auburn",
    "sg:classifiers":[
        {
            "category":"Wholesale",
            "subcategory":"Durable Goods & Equipment",
            "type":"Manufacturing & Wholesale Goods"
        }
    ],
    "sg:phone":"+1 253 833 8332",
    "sg:postcode":"98002",
    "sg:province":"WA",
    "sg:tags":[
        "dry",
        "goods-wholesale"
    ],
    "wof:name":"Harding Design & Supply",
    "wof:placetype":"venue"
},
  "geometry": {"coordinates":[-122.220049,47.285519],"type":"Point"}
}