{
  "type": "Feature",
  "properties": {
    "addr:full":"200 N Pacific Ave Kelso WA 98626",
    "addr:housenumber":"200",
    "addr:postcode":"98626",
    "addr:street":"N Pacific Ave",
    "iso:country":"US",
    "sg:address":"200 N Pacific Ave",
    "sg:city":"Kelso",
    "sg:classifiers":[
        {
            "category":"Professional",
            "subcategory":"Management & Consulting",
            "type":"Services"
        }
    ],
    "sg:phone":"+1 360 636 2820",
    "sg:postcode":"98626",
    "sg:province":"WA",
    "sg:tags":[
        "business"
    ],
    "wof:name":"Wm Dennis & Assoc",
    "wof:placetype":"venue"
},
  "geometry": {"coordinates":[-122.910782,46.146342],"type":"Point"}
}