{
  "type": "Feature",
  "properties": {
    "iso:country":"US",
    "sg:address":"2334 Reservoir Rd",
    "sg:city":"Clarkston",
    "sg:classifiers":[
        {
            "category":"Building & Trades",
            "subcategory":"Cleaning & Sanitation",
            "type":"Services"
        }
    ],
    "sg:phone":"+1 509 758 7899",
    "sg:postcode":"99403",
    "sg:province":"WA",
    "sg:tags":[
        "maintenance"
    ],
    "wof:name":"Advanced Cleaning Svc",
    "wof:placetype":"venue"
},
  "geometry": {"coordinates":[-117.089056,46.382983],"type":"Point"}
}