{
  "type": "Feature",
  "properties": {
    "addr:full":"20207 NE 163rd St Woodinville WA 98077",
    "addr:housenumber":"20207",
    "addr:postcode":"98077",
    "addr:street":"Ne 163Rd St",
    "iso:country":"US",
    "sg:address":"20207 NE 163rd St",
    "sg:city":"Woodinville",
    "sg:classifiers":[
        {
            "category":"Communications",
            "type":"Services"
        }
    ],
    "sg:phone":"+1 425 788 5361",
    "sg:postcode":"98077",
    "sg:province":"WA",
    "sg:tags":[
        "data"
    ],
    "wof:name":"Mrv Communications Inc",
    "wof:placetype":"venue"
},
  "geometry": {"coordinates":[-122.067993,47.74587],"type":"Point"}
}