{
  "type": "Feature",
  "properties": {
    "addr:full":"2215 N 30th St Ste 100 Tacoma WA 98403",
    "addr:housenumber":"2215",
    "addr:postcode":"98403",
    "addr:street":"N 30Th St Ste 100",
    "iso:country":"US",
    "sg:address":"2215 N 30th St Ste 100",
    "sg:city":"Tacoma",
    "sg:classifiers":[
        {
            "category":"Real Estate",
            "subcategory":"Real Estate Services",
            "type":"Services"
        },
        {
            "category":"Banks & Credit Unions",
            "subcategory":"Financial Services",
            "type":"Services"
        }
    ],
    "sg:phone":"+1 253 274 0464",
    "sg:postcode":"98403",
    "sg:province":"WA",
    "sg:tags":[
        "loan",
        "processing"
    ],
    "sg:website":"https://www.wellsfargo.com/mortgage/",
    "wof:name":"Wells Fargo Home Mortgage",
    "wof:placetype":"venue"
},
  "geometry": {"coordinates":[-122.46553,47.274778],"type":"Point"}
}