{
  "type": "Feature",
  "properties": {
    "addr:full":"2019 3rd Ave Ste 200 Seattle WA 98121",
    "addr:housenumber":"2019",
    "addr:postcode":"98121",
    "addr:street":"3Rd Ave Ste 200",
    "iso:country":"US",
    "sg:address":"2019 3rd Ave Ste 200",
    "sg:city":"Seattle",
    "sg:classifiers":[
        {
            "category":"Real Estate",
            "subcategory":"Architect",
            "type":"Services"
        }
    ],
    "sg:phone":"+1 206 441 1106",
    "sg:postcode":"98121",
    "sg:province":"WA",
    "sg:tags":[
        "architects'",
        "specification",
        "builders'",
        "construction",
        "architectural"
    ],
    "wof:name":"Scott A Huntley, A.I.A., P.S.",
    "wof:placetype":"venue"
},
  "geometry": {"coordinates":[-122.34112399999999,47.612542],"type":"Point"}
}