{
  "type": "Feature",
  "properties": {
    "addr:full":"136 Stewart Rd SW Pacific WA 98047",
    "addr:housenumber":"136",
    "addr:postcode":"98047",
    "addr:street":"Stewart Rd Sw",
    "iso:country":"US",
    "sg:address":"136 Stewart Rd SW",
    "sg:city":"Pacific",
    "sg:classifiers":[
        {
            "category":"Deli",
            "type":"Food & Drink"
        }
    ],
    "sg:phone":"+1 253 863 9124",
    "sg:postcode":"98047",
    "sg:province":"WA",
    "sg:tags":[
        "delicatessen"
    ],
    "wof:name":"Rise & Shine Bakery & Deli",
    "wof:placetype":"venue"
},
  "geometry": {"coordinates":[-122.252962,47.250123],"type":"Point"}
}