{
  "type": "Feature",
  "properties": {
    "addr:full":"2462 Dexter Ave N Seattle WA 98109",
    "addr:housenumber":"2462",
    "addr:postcode":"98109",
    "addr:street":"Dexter Ave N",
    "iso:country":"US",
    "sg:address":"2462 Dexter Ave N",
    "sg:city":"Seattle",
    "sg:classifiers":[
        {
            "category":"Shopping",
            "subcategory":"Shoes",
            "type":"Retail Goods"
        }
    ],
    "sg:phone":"+1 206 282 0633",
    "sg:postcode":"98109",
    "sg:province":"WA",
    "wof:name":"Laced Up",
    "wof:placetype":"venue"
},
  "geometry": {"coordinates":[-122.344667,47.642025],"type":"Point"}
}