{
  "type": "Feature",
  "properties": {
    "addr:full":"117 Main St Kirkland WA 98033",
    "addr:housenumber":"117",
    "addr:postcode":"98033",
    "addr:street":"Main St",
    "iso:country":"US",
    "sg:address":"117 Main St",
    "sg:city":"Kirkland",
    "sg:classifiers":[
        {
            "category":"Personal",
            "subcategory":"Beauty Salon",
            "type":"Services"
        }
    ],
    "sg:phone":"+1 425 828 0457",
    "sg:postcode":"98033",
    "sg:province":"WA",
    "sg:tags":[
        "shop"
    ],
    "wof:name":"Alis Design",
    "wof:placetype":"venue"
},
  "geometry": {"coordinates":[-122.20488899999999,47.677084],"type":"Point"}
}