{
  "type": "Feature",
  "properties": {
    "addr:full":"852 NW 85th St Seattle WA 98117",
    "addr:housenumber":"852",
    "addr:postcode":"98117",
    "addr:street":"Nw 85Th St",
    "iso:country":"US",
    "sg:address":"852 NW 85th St",
    "sg:city":"Seattle",
    "sg:classifiers":[
        {
            "category":"Building & Trades",
            "subcategory":"Cleaning & Sanitation",
            "type":"Services"
        },
        {
            "category":"Retail",
            "subcategory":"Repair Shop",
            "type":"Services"
        },
        {
            "category":"Retail",
            "subcategory":"Laundry & Dry Cleaning",
            "type":"Services"
        }
    ],
    "sg:phone":"+1 206 783 1003",
    "sg:postcode":"98117",
    "sg:province":"WA",
    "sg:tags":[
        "cleaner",
        "upholstery",
        "upholsterer",
        "damage",
        "rug",
        "water",
        "restoration",
        "carpet"
    ],
    "sg:website":"http://www.chemdry.com",
    "wof:name":"Chem-Dry",
    "wof:placetype":"venue"
},
  "geometry": {"coordinates":[-122.36730900000001,47.690651],"type":"Point"}
}