{
  "type": "Feature",
  "properties": {
    "addr:full":"2830 140th Ave NE Bellevue WA 98005",
    "addr:housenumber":"2830",
    "addr:postcode":"98005",
    "addr:street":"140Th Ave Ne",
    "iso:country":"US",
    "sg:address":"2830 140th Ave NE",
    "sg:city":"Bellevue",
    "sg:classifiers":[
        {
            "category":"Real Estate",
            "subcategory":"Real Estate Agent",
            "type":"Services"
        }
    ],
    "sg:phone":"+1 425 453 7233",
    "sg:postcode":"98005",
    "sg:province":"WA",
    "wof:name":"Crescent Springs Management",
    "wof:placetype":"venue"
},
  "geometry": {"coordinates":[-122.15358999999999,47.636153],"type":"Point"}
}