{
  "type": "Feature",
  "properties": {
    "addr:full":"205 NE Birch St Issaquah WA 98027",
    "addr:housenumber":"205",
    "addr:postcode":"98027",
    "addr:street":"Ne Birch St",
    "iso:country":"US",
    "sg:address":"205 NE Birch St",
    "sg:city":"Issaquah",
    "sg:classifiers":[
        {
            "category":"Manufacturing",
            "subcategory":"Tools & Machinery",
            "type":"Manufacturing & Wholesale Goods"
        },
        {
            "category":"Manufacturing",
            "subcategory":"Metals",
            "type":"Manufacturing & Wholesale Goods"
        }
    ],
    "sg:phone":"+1 425 392 4279",
    "sg:postcode":"98027",
    "sg:province":"WA",
    "sg:tags":[
        "metal-wholesale",
        "springs-wholesale",
        "manufacturer"
    ],
    "wof:name":"Erickson John Company",
    "wof:placetype":"venue"
},
  "geometry": {"coordinates":[-122.03278299999999,47.53192],"type":"Point"}
}