{
  "type": "Feature",
  "properties": {
    "iso:country":"US",
    "sg:address":"2015 112th St S",
    "sg:city":"Tacoma",
    "sg:classifiers":[
        {
            "category":"Home & Garden",
            "subcategory":"Building Materials",
            "type":"Retail Goods"
        }
    ],
    "sg:phone":"+1 253 588 6604",
    "sg:postcode":"98444",
    "sg:province":"WA",
    "sg:tags":[
        "roofing"
    ],
    "sg:website":"www.alliedbuilding.com",
    "wof:name":"Allied Building Products Corp",
    "wof:placetype":"venue"
},
  "geometry": {"coordinates":[-122.467928,47.155882],"type":"Point"}
}