{
  "type": "Feature",
  "properties": {
    "addr:full":"19231 40th Ave NW Stanwood WA 98292",
    "addr:housenumber":"19231",
    "addr:postcode":"98292",
    "addr:street":"40Th Ave Nw",
    "iso:country":"US",
    "sg:address":"19231 40th Ave NW",
    "sg:city":"Stanwood",
    "sg:classifiers":[
        {
            "category":"Building & Trades",
            "subcategory":"Landscaping Services",
            "type":"Services"
        }
    ],
    "sg:phone":"+1 206 919 2134",
    "sg:postcode":"98292",
    "sg:province":"WA",
    "wof:name":"Ward & Sons Quality Ldscp Svc",
    "wof:placetype":"venue"
},
  "geometry": {"coordinates":[-122.28612800000001,48.169807],"type":"Point"}
}