{
  "type": "Feature",
  "properties": {
    "addr:full":"777 N 5th Ave Sequim WA 98382",
    "addr:housenumber":"777",
    "addr:postcode":"98382",
    "addr:street":"N 5Th Ave",
    "iso:country":"US",
    "sg:address":"777 N 5th Ave",
    "sg:city":"Sequim",
    "sg:classifiers":[
        {
            "category":"Health Services",
            "subcategory":"Doctor",
            "type":"Services"
        }
    ],
    "sg:phone":"+1 360 582 2830",
    "sg:postcode":"98382",
    "sg:province":"WA",
    "sg:tags":[
        "physician",
        "surgeon",
        "medical"
    ],
    "wof:name":"Valley Dermatology PS Inc",
    "wof:placetype":"venue"
},
  "geometry": {"coordinates":[-123.113203,48.087233],"type":"Point"}
}