{
  "type": "Feature",
  "properties": {
    "addr:full":"16243 SE 8th St Bellevue WA 98008",
    "addr:housenumber":"16243",
    "addr:postcode":"98008",
    "addr:street":"Se 8Th St",
    "iso:country":"US",
    "sg:address":"16243 SE 8th St",
    "sg:city":"Bellevue",
    "sg:classifiers":[
        {
            "category":"Personal",
            "subcategory":"Barber",
            "type":"Services"
        }
    ],
    "sg:phone":"+1 425 641 8499",
    "sg:postcode":"98008",
    "sg:province":"WA",
    "sg:tags":[
        "shop"
    ],
    "wof:name":"Bills Place",
    "wof:placetype":"venue"
},
  "geometry": {"coordinates":[-122.12553200000001,47.603017],"type":"Point"}
}