{
  "type": "Feature",
  "properties": {
    "addr:full":"15406 Garden St Sumner WA 98390",
    "addr:housenumber":"15406",
    "addr:postcode":"98390",
    "addr:street":"Garden St",
    "iso:country":"US",
    "sg:address":"15406 Garden St",
    "sg:city":"Sumner",
    "sg:classifiers":[
        {
            "category":"Building & Trades",
            "subcategory":"Cleaning & Sanitation",
            "type":"Services"
        }
    ],
    "sg:phone":"+1 253 863 6466",
    "sg:postcode":"98390",
    "sg:province":"WA",
    "sg:tags":[
        "agency",
        "employment",
        "maintenance"
    ],
    "wof:name":"Deep Cleaning",
    "wof:placetype":"venue"
},
  "geometry": {"coordinates":[-122.222675,47.204601],"type":"Point"}
}