{
  "type": "Feature",
  "properties": {
    "addr:full":"4067 149th Ave SE Bellevue WA 98006",
    "addr:housenumber":"4067",
    "addr:postcode":"98006",
    "addr:street":"149Th Ave Se",
    "iso:country":"US",
    "sg:address":"4067 149th Ave SE",
    "sg:city":"Bellevue",
    "sg:classifiers":[
        {
            "category":"Education",
            "subcategory":"Special Training",
            "type":"Public Place"
        }
    ],
    "sg:phone":"+1 425 653 0337",
    "sg:postcode":"98006",
    "sg:province":"WA",
    "wof:name":"Ultimate Vision",
    "wof:placetype":"venue"
},
  "geometry": {"coordinates":[-122.142636,47.572708],"type":"Point"}
}