{
  "type": "Feature",
  "properties": {
    "addr:full":"1420 King St Bellingham WA 98229",
    "addr:housenumber":"1420",
    "addr:postcode":"98229",
    "addr:street":"King St",
    "iso:country":"US",
    "sg:address":"1420 King St",
    "sg:city":"Bellingham",
    "sg:classifiers":[
        {
            "category":"Health Services",
            "subcategory":"Health Practitioner",
            "type":"Services"
        }
    ],
    "sg:phone":"+1 360 650 1040",
    "sg:postcode":"98229",
    "sg:province":"WA",
    "wof:name":"Cindy Lmp Maxwell",
    "wof:placetype":"venue"
},
  "geometry": {"coordinates":[-122.46370899999999,48.747663],"type":"Point"}
}