{
  "type": "Feature",
  "properties": {
    "addr:full":"921 Big Burn Pl Forks WA 98331",
    "addr:housenumber":"921",
    "addr:postcode":"98331",
    "addr:street":"Big Burn Pl",
    "iso:country":"US",
    "sg:address":"921 Big Burn Pl",
    "sg:city":"Forks",
    "sg:classifiers":[
        {
            "category":"Professional",
            "type":"Services"
        }
    ],
    "sg:phone":"+1 360 374 5035",
    "sg:postcode":"98331",
    "sg:province":"WA",
    "wof:name":"American Eagle Systems & Repai",
    "wof:placetype":"venue"
},
  "geometry": {"coordinates":[-124.377494,47.961211],"type":"Point"}
}