{
  "type": "Feature",
  "properties": {
    "addr:full":"1511 Walnut St Everett WA 98201",
    "addr:housenumber":"1511",
    "addr:postcode":"98201",
    "addr:street":"Walnut St",
    "iso:country":"US",
    "sg:address":"1511 Walnut St",
    "sg:city":"Everett",
    "sg:classifiers":[
        {
            "category":"Food & Beverages",
            "subcategory":"Groceries & Convenience Stores",
            "type":"Retail Goods"
        }
    ],
    "sg:phone":"+1 425 783 3409",
    "sg:postcode":"98201",
    "sg:province":"WA",
    "wof:name":"RK Markets Inc",
    "wof:placetype":"venue"
},
  "geometry": {"coordinates":[-122.18906699999999,47.99633],"type":"Point"}
}