{
  "type": "Feature",
  "properties": {
    "addr:full":"15 S Benton St Kennewick WA 99336",
    "addr:housenumber":"15",
    "addr:postcode":"99336",
    "addr:street":"S Benton St",
    "iso:country":"US",
    "sg:address":"15 S Benton St",
    "sg:city":"Kennewick",
    "sg:classifiers":[
        {
            "category":"Retail",
            "subcategory":"Repair Shop",
            "type":"Services"
        }
    ],
    "sg:phone":"+1 509 582 6212",
    "sg:postcode":"99336",
    "sg:province":"WA",
    "sg:tags":[
        "contractor"
    ],
    "wof:name":"Cliffs Septic Tank Service",
    "wof:placetype":"venue"
},
  "geometry": {"coordinates":[-119.119895,46.207782],"type":"Point"}
}