{
  "type": "Feature",
  "properties": {
    "addr:full":"604 Galer St Seattle WA 98109",
    "addr:housenumber":"604",
    "addr:postcode":"98109",
    "addr:street":"Galer St",
    "iso:country":"US",
    "sg:address":"604 Galer St",
    "sg:city":"Seattle",
    "sg:classifiers":[
        {
            "category":"Professional",
            "subcategory":"Computer Services",
            "type":"Services"
        }
    ],
    "sg:phone":"+1 206 352 9894",
    "sg:postcode":"98109",
    "sg:province":"WA",
    "sg:tags":[
        "programing",
        "custom"
    ],
    "wof:name":"Project Weed Inc",
    "wof:placetype":"venue"
},
  "geometry": {"coordinates":[-122.344961,47.632297],"type":"Point"}
}