{
  "type": "Feature",
  "properties": {
    "addr:full":"9517 35th Avenue NE Seattle WA 98115",
    "addr:housenumber":"9517",
    "addr:postcode":"98115",
    "addr:street":"35Th Avenue Ne",
    "iso:country":"US",
    "sg:address":"9517 35th Avenue NE",
    "sg:city":"Seattle",
    "sg:classifiers":[
        {
            "category":"Building & Trades",
            "subcategory":"Construction",
            "type":"Services"
        }
    ],
    "sg:phone":"+1 206 529 1000",
    "sg:postcode":"98115",
    "sg:province":"WA",
    "sg:tags":[
        "contractor"
    ],
    "wof:name":"Jrj Development",
    "wof:placetype":"venue"
},
  "geometry": {"coordinates":[-122.290474,47.697476],"type":"Point"}
}