{
  "type": "Feature",
  "properties": {
    "addr:full":"11639 Fay Rd NE Carnation WA 98014",
    "addr:housenumber":"11639",
    "addr:postcode":"98014",
    "addr:street":"Fay Rd Ne",
    "iso:country":"US",
    "sg:address":"11639 Fay Rd NE",
    "sg:city":"Carnation",
    "sg:classifiers":[
        {
            "category":"Professional",
            "subcategory":"Management & Consulting",
            "type":"Services"
        }
    ],
    "sg:phone":"+1 425 788 5557",
    "sg:postcode":"98014",
    "sg:province":"WA",
    "sg:tags":[
        "business"
    ],
    "wof:name":"Dove Group",
    "wof:placetype":"venue"
},
  "geometry": {"coordinates":[-121.921323,47.701828],"type":"Point"}
}