{
  "type": "Feature",
  "properties": {
    "addr:full":"502 W Main St Elma WA 98541",
    "addr:housenumber":"502",
    "addr:postcode":"98541",
    "addr:street":"W Main St",
    "iso:country":"US",
    "sg:address":"502 W Main St",
    "sg:city":"Elma",
    "sg:classifiers":[
        {
            "category":"Organizations",
            "subcategory":"Religious Organization",
            "type":"Services"
        }
    ],
    "sg:phone":"+1 360 482 3528",
    "sg:postcode":"98541",
    "sg:province":"WA",
    "sg:tags":[
        "church"
    ],
    "wof:name":"Grace Community Church",
    "wof:placetype":"venue"
},
  "geometry": {"coordinates":[-123.406539,47.004015],"type":"Point"}
}