{
  "type": "Feature",
  "properties": {
    "addr:full":"20 University St Seattle WA 98101",
    "addr:housenumber":"20",
    "addr:postcode":"98101",
    "addr:street":"University St",
    "iso:country":"US",
    "sg:address":"20 University St",
    "sg:city":"Seattle",
    "sg:classifiers":[
        {
            "category":"Manufacturing",
            "subcategory":"Printing",
            "type":"Manufacturing & Wholesale Goods"
        }
    ],
    "sg:phone":"+1 206 543 2670",
    "sg:postcode":"98101",
    "sg:province":"WA",
    "sg:tags":[
        "newspaper",
        "publishing"
    ],
    "wof:name":"The Daily",
    "wof:placetype":"venue"
},
  "geometry": {"coordinates":[-122.34021199999999,47.605951],"type":"Point"}
}