{
  "type": "Feature",
  "properties": {
    "addr:full":"505 Mount Jupiter Dr SW Issaquah WA 98027",
    "addr:housenumber":"505",
    "addr:postcode":"98027",
    "addr:street":"Mount Jupiter Dr Sw",
    "iso:country":"US",
    "sg:address":"505 Mount Jupiter Dr SW",
    "sg:city":"Issaquah",
    "sg:classifiers":[
        {
            "category":"Professional",
            "subcategory":"Business Services",
            "type":"Services"
        }
    ],
    "sg:phone":"+1 425 391 8490",
    "sg:postcode":"98027",
    "sg:province":"WA",
    "wof:name":"Oakshaw LLC",
    "wof:placetype":"venue"
},
  "geometry": {"coordinates":[-122.049825,47.526018],"type":"Point"}
}