{
  "type": "Feature",
  "properties": {
    "addr:full":"720 3rd Avenue Seattle WA 98104",
    "addr:housenumber":"720",
    "addr:postcode":"98104",
    "addr:street":"3Rd Avenue",
    "iso:country":"US",
    "sg:address":"720 3rd Avenue",
    "sg:city":"Seattle",
    "sg:classifiers":[
        {
            "category":"Professional",
            "subcategory":"Lawyer & Legal Services",
            "type":"Services"
        }
    ],
    "sg:phone":"+1 206 622 8953",
    "sg:postcode":"98104",
    "sg:province":"WA",
    "wof:name":"Johansen Helen M Atty",
    "wof:placetype":"venue"
},
  "geometry": {"coordinates":[-122.33223599999999,47.603639],"type":"Point"}
}