{
  "type": "Feature",
  "properties": {
    "addr:full":"2101 4th Ave Seattle WA 98121",
    "addr:housenumber":"2101",
    "addr:postcode":"98121",
    "addr:street":"4Th Ave",
    "iso:country":"US",
    "sg:address":"2101 4th Ave",
    "sg:city":"Seattle",
    "sg:classifiers":[
        {
            "category":"Communications",
            "type":"Services"
        }
    ],
    "sg:phone":"+1 206 256 2455",
    "sg:postcode":"98121",
    "sg:province":"WA",
    "wof:name":"BFG Communication Inc",
    "wof:placetype":"venue"
},
  "geometry": {"coordinates":[-122.342636,47.614599],"type":"Point"}
}