{
  "type": "Feature",
  "properties": {
    "addr:full":"12731 25th Ave SE Everett WA 98208",
    "addr:housenumber":"12731",
    "addr:postcode":"98208",
    "addr:street":"25Th Ave Se",
    "iso:country":"US",
    "sg:address":"12731 25th Ave SE",
    "sg:city":"Everett",
    "sg:classifiers":[
        {
            "category":"Professional",
            "subcategory":"Advertising",
            "type":"Services"
        }
    ],
    "sg:phone":"+1 425 337 9307",
    "sg:postcode":"98208",
    "sg:province":"WA",
    "sg:tags":[
        "agency"
    ],
    "wof:name":"Parliamentary Procedure",
    "wof:placetype":"venue"
},
  "geometry": {"coordinates":[-122.19869199999999,47.883512],"type":"Point"}
}