{
  "type": "Feature",
  "properties": {
    "addr:full":"17106 SE 47th Ct Bellevue WA 98006",
    "addr:postcode":"17106;98006",
    "addr:street":"Se 47Th Ct",
    "iso:country":"US",
    "sg:address":"17106 SE 47th Ct",
    "sg:city":"Bellevue",
    "sg:classifiers":[
        {
            "category":"Professional",
            "subcategory":"Accounting & Tax Preparation",
            "type":"Services"
        }
    ],
    "sg:phone":"+1 425 641 7540",
    "sg:postcode":"98006",
    "sg:province":"WA",
    "sg:tags":[
        "consulting",
        "management",
        "s"
    ],
    "wof:name":"Nylee Enterprises Inc",
    "wof:placetype":"venue"
},
  "geometry": {"coordinates":[-122.111941,47.561497],"type":"Point"}
}