{
  "type": "Feature",
  "properties": {
    "iso:country":"US",
    "sg:address":"205 E Casino Rd",
    "sg:city":"Everett",
    "sg:classifiers":[
        {
            "category":"Professional",
            "subcategory":"Computer Services",
            "type":"Services"
        }
    ],
    "sg:phone":"+1 425 355 5917",
    "sg:postcode":"98208",
    "sg:province":"WA",
    "sg:tags":[
        "related"
    ],
    "wof:name":"Vr Computing",
    "wof:placetype":"venue"
},
  "geometry": {"coordinates":[-122.230423,47.921995],"type":"Point"}
}