{
  "type": "Feature",
  "properties": {
    "addr:full":"11523 Avondale Rd NE Redmond WA 98052",
    "addr:housenumber":"11523",
    "addr:postcode":"98052",
    "addr:street":"Avondale Rd Ne",
    "iso:country":"US",
    "sg:address":"11523 Avondale Rd NE",
    "sg:city":"Redmond",
    "sg:classifiers":[
        {
            "category":"Personal",
            "subcategory":"Beauty Salon",
            "type":"Services"
        },
        {
            "category":"Personal",
            "subcategory":"Barber",
            "type":"Services"
        }
    ],
    "sg:phone":"+1 425 895 1648",
    "sg:postcode":"98052",
    "sg:province":"WA",
    "sg:tags":[
        "hair",
        "accessory",
        "stylist",
        "supply"
    ],
    "sg:website":"http://www.greatclips.com/",
    "wof:name":"Great Clips",
    "wof:placetype":"venue"
},
  "geometry": {"coordinates":[-122.09289099999999,47.702376],"type":"Point"}
}