{
  "type": "Feature",
  "properties": {
    "addr:full":"3346 Alm Rd Everson WA 98247",
    "addr:housenumber":"3346",
    "addr:postcode":"98247",
    "addr:street":"Alm Rd",
    "iso:country":"US",
    "sg:address":"3346 Alm Rd",
    "sg:city":"Everson",
    "sg:classifiers":[
        {
            "category":"Building & Trades",
            "subcategory":"Construction",
            "type":"Services"
        }
    ],
    "sg:phone":"+1 360 966 7923",
    "sg:postcode":"98247",
    "sg:province":"WA",
    "sg:tags":[
        "house"
    ],
    "wof:name":"Zylstra Construction",
    "wof:placetype":"venue"
},
  "geometry": {"coordinates":[-122.306962,48.942924],"type":"Point"}
}