{
  "type": "Feature",
  "properties": {
    "addr:full":"17736 15th Ave NW Shoreline WA 98177",
    "addr:housenumber":"17736",
    "addr:postcode":"98177",
    "addr:street":"15Th Ave Nw",
    "iso:country":"US",
    "sg:address":"17736 15th Ave NW",
    "sg:city":"Shoreline",
    "sg:classifiers":[
        {
            "category":"Professional",
            "subcategory":"Management & Consulting",
            "type":"Services"
        }
    ],
    "sg:phone":"+1 206 546 3466",
    "sg:postcode":"98177",
    "sg:province":"WA",
    "sg:tags":[
        "science",
        "consultant",
        "academic"
    ],
    "wof:name":"Azs Consulting",
    "wof:placetype":"venue"
},
  "geometry": {"coordinates":[-122.37667999999999,47.758648],"type":"Point"}
}