{
  "type": "Feature",
  "properties": {
    "addr:full":"22002 26th Ave SE Bothell WA 98021",
    "addr:housenumber":"22002",
    "addr:postcode":"98021",
    "addr:street":"26Th Ave Se",
    "iso:country":"US",
    "sg:address":"22002 26th Ave SE",
    "sg:city":"Bothell",
    "sg:classifiers":[
        {
            "category":"Professional",
            "subcategory":"Business Services",
            "type":"Services"
        }
    ],
    "sg:phone":"+1 425 424 2663",
    "sg:postcode":"98021",
    "sg:province":"WA",
    "sg:tags":[
        "biotechnology"
    ],
    "wof:name":"Skeletech Inc",
    "wof:placetype":"venue"
},
  "geometry": {"coordinates":[-122.19814,47.796553],"type":"Point"}
}