{
  "type": "Feature",
  "properties": {
    "addr:full":"14619 NE 31st St Bellevue WA 98007",
    "addr:housenumber":"14619",
    "addr:postcode":"98007",
    "addr:street":"Ne 31St St",
    "iso:country":"US",
    "sg:address":"14619 NE 31st St",
    "sg:city":"Bellevue",
    "sg:classifiers":[
        {
            "category":"Manufacturing",
            "subcategory":"Tools & Machinery",
            "type":"Manufacturing & Wholesale Goods"
        }
    ],
    "sg:phone":"+1 425 941 9653",
    "sg:postcode":"98007",
    "sg:province":"WA",
    "sg:tags":[
        "industrial",
        "mfg"
    ],
    "wof:name":"Jade Ring Controls",
    "wof:placetype":"venue"
},
  "geometry": {"coordinates":[-122.146586,47.637807],"type":"Point"}
}