{
  "type": "Feature",
  "properties": {
    "iso:country":"US",
    "sg:address":"40 NE Rhine Village Dr",
    "sg:city":"White Salmon",
    "sg:classifiers":[
        {
            "category":"Professional",
            "type":"Services"
        }
    ],
    "sg:phone":"+1 509 493 3215",
    "sg:postcode":"98672",
    "sg:province":"WA",
    "sg:tags":[
        "establishment"
    ],
    "wof:name":"Bingen Sub Station",
    "wof:placetype":"venue"
},
  "geometry": {"coordinates":[-121.469083,45.722207],"type":"Point"}
}