{
  "type": "Feature",
  "properties": {
    "addr:full":"710 SE Everett Rd Camas WA 98607",
    "addr:housenumber":"710",
    "addr:postcode":"98607",
    "addr:street":"Se Everett Rd",
    "iso:country":"US",
    "sg:address":"710 SE Everett Rd",
    "sg:city":"Camas",
    "sg:classifiers":[
        {
            "category":"Building & Trades",
            "subcategory":"Equipment Rental",
            "type":"Services"
        }
    ],
    "sg:phone":"+1 360 833 1098",
    "sg:postcode":"98607",
    "sg:province":"WA",
    "wof:name":"1914 House",
    "wof:placetype":"venue"
},
  "geometry": {"coordinates":[-122.403881,45.616985],"type":"Point"}
}