{
  "type": "Feature",
  "properties": {
    "addr:full":"4569 Lynwood Center Rd NE Bainbridge Island WA 98110",
    "addr:housenumber":"4569",
    "addr:postcode":"98110",
    "addr:street":"Lynwood Center Rd Ne",
    "iso:country":"US",
    "sg:address":"4569 Lynwood Center Rd NE",
    "sg:city":"Bainbridge Island",
    "sg:classifiers":[
        {
            "category":"Professional",
            "subcategory":"Business Services",
            "type":"Services"
        }
    ],
    "sg:phone":"+1 206 780 9017",
    "sg:postcode":"98110",
    "sg:province":"WA",
    "sg:tags":[
        "merchandise"
    ],
    "wof:name":"Rjs Engraving & Signs",
    "wof:placetype":"venue"
},
  "geometry": {"coordinates":[-122.547619,47.605138],"type":"Point"}
}