{
  "type": "Feature",
  "properties": {
    "addr:full":"9024 132nd Pl SE Renton WA 98059",
    "addr:housenumber":"9024",
    "addr:postcode":"98059",
    "addr:street":"132Nd Pl Se",
    "iso:country":"US",
    "sg:address":"9024 132nd Pl SE",
    "sg:city":"Renton",
    "sg:classifiers":[
        {
            "category":"Travel",
            "subcategory":"Hotels & Motels",
            "type":"Entertainment"
        }
    ],
    "sg:phone":"+1 425 235 1994",
    "sg:postcode":"98059",
    "sg:province":"WA",
    "sg:tags":[
        "membership",
        "lodging"
    ],
    "wof:name":"Alpha Delta Kappa Sororit",
    "wof:placetype":"venue"
},
  "geometry": {"coordinates":[-122.163695,47.522564],"type":"Point"}
}