{
  "type": "Feature",
  "properties": {
    "addr:full":"12624 288th St E Graham WA 98338",
    "addr:housenumber":"12624",
    "addr:postcode":"98338",
    "addr:street":"288Th St E",
    "iso:country":"US",
    "sg:address":"12624 288th St E",
    "sg:city":"Graham",
    "sg:classifiers":[
        {
            "category":"Retail",
            "subcategory":"Animal Services",
            "type":"Services"
        }
    ],
    "sg:phone":"+1 253 677 4586",
    "sg:postcode":"98338",
    "sg:province":"WA",
    "wof:name":"Cr Stables",
    "wof:placetype":"venue"
},
  "geometry": {"coordinates":[-122.26369099999999,46.994417],"type":"Point"}
}