{
  "type": "Feature",
  "properties": {
    "addr:full":"9834 16th Ave SW Seattle WA 98106",
    "addr:housenumber":"9834",
    "addr:postcode":"98106",
    "addr:street":"16Th Ave Sw",
    "iso:country":"US",
    "sg:address":"9834 16th Ave SW",
    "sg:city":"Seattle",
    "sg:classifiers":[
        {
            "category":"Local Transit",
            "type":"Transportation"
        }
    ],
    "sg:phone":"+1 206 766 8258",
    "sg:postcode":"98106",
    "sg:province":"WA",
    "sg:tags":[
        "airport"
    ],
    "wof:name":"Airport Shuttle Express",
    "wof:placetype":"venue"
},
  "geometry": {"coordinates":[-122.355056,47.514017],"type":"Point"}
}