{
  "type": "Feature",
  "properties": {
    "addr:full":"20320 NE Allworth Rd Battle Ground WA 98604",
    "addr:housenumber":"20320",
    "addr:postcode":"98604",
    "addr:street":"Ne Allworth Rd",
    "iso:country":"US",
    "sg:address":"20320 NE Allworth Rd",
    "sg:city":"Battle Ground",
    "sg:classifiers":[
        {
            "category":"Building & Trades",
            "subcategory":"Plumbing",
            "type":"Services"
        }
    ],
    "sg:phone":"+1 360 687 4983",
    "sg:postcode":"98604",
    "sg:province":"WA",
    "sg:tags":[
        "conditioning",
        "contractor"
    ],
    "wof:name":"Ryans",
    "wof:placetype":"venue"
},
  "geometry": {"coordinates":[-122.463294,45.79957],"type":"Point"}
}