{
  "type": "Feature",
  "properties": {
    "addr:full":"15005 NW Holly Rd Seabeck WA 98380",
    "addr:housenumber":"15005",
    "addr:postcode":"98380",
    "addr:street":"Nw Holly Rd",
    "iso:country":"US",
    "sg:address":"15005 NW Holly Rd",
    "sg:city":"Seabeck",
    "sg:classifiers":[
        {
            "category":"Building & Trades",
            "subcategory":"Construction",
            "type":"Services"
        }
    ],
    "sg:phone":"+1 360 731 0760",
    "sg:postcode":"98380",
    "sg:province":"WA",
    "sg:tags":[
        "excavation",
        "contractor"
    ],
    "wof:name":"M D Dozer Service Inc",
    "wof:placetype":"venue"
},
  "geometry": {"coordinates":[-122.850685,47.593202],"type":"Point"}
}