{
  "type": "Feature",
  "properties": {
    "addr:full":"107 E Jewett Blvd White Salmon WA 98672",
    "addr:housenumber":"107",
    "addr:postcode":"98672",
    "addr:street":"E Jewett Blvd",
    "iso:country":"US",
    "sg:address":"107 E Jewett Blvd",
    "sg:city":"White Salmon",
    "sg:classifiers":[
        {
            "category":"Social Services",
            "subcategory":"Job Training",
            "type":"Services"
        }
    ],
    "sg:phone":"+1 509 493 1210",
    "sg:postcode":"98672",
    "sg:province":"WA",
    "sg:tags":[
        "rehab",
        "government"
    ],
    "wof:name":"Employment Security",
    "wof:placetype":"venue"
},
  "geometry": {"coordinates":[-121.48667500000001,45.727752],"type":"Point"}
}