{
  "type": "Feature",
  "properties": {
    "iso:country":"US",
    "sg:address":"1200 Union Ave NE",
    "sg:city":"Renton",
    "sg:classifiers":[
        {
            "category":"Wholesale",
            "subcategory":"Machinery & Supplies",
            "type":"Manufacturing & Wholesale Goods"
        }
    ],
    "sg:phone":"+1 425 255 5926",
    "sg:postcode":"98059",
    "sg:province":"WA",
    "sg:tags":[
        "equipment",
        "welding"
    ],
    "wof:name":"D & B Welding Supply",
    "wof:placetype":"venue"
},
  "geometry": {"coordinates":[-122.164615,47.50372],"type":"Point"}
}