{
  "type": "Feature",
  "properties": {
    "addr:full":"600 Pine St Ste 110 Seattle WA 98101",
    "addr:housenumber":"600",
    "addr:postcode":"98101",
    "addr:street":"Pine St Ste 110",
    "iso:country":"US",
    "sg:address":"600 Pine St Ste 110",
    "sg:city":"Seattle",
    "sg:classifiers":[
        {
            "category":"Shopping",
            "subcategory":"Clothing, Apparel, & Fashions",
            "type":"Retail Goods"
        }
    ],
    "sg:phone":"+1 206 264 0372",
    "sg:postcode":"98101",
    "sg:province":"WA",
    "sg:tags":[
        "accessory",
        "clothing",
        "store",
        "women's"
    ],
    "wof:name":"Coach",
    "wof:placetype":"venue"
},
  "geometry": {"coordinates":[-122.33538799999999,47.612099],"type":"Point"}
}