{
  "type": "Feature",
  "properties": {
    "addr:full":"3426 Meridian Rd SE Olympia WA 98513",
    "addr:housenumber":"3426",
    "addr:postcode":"olympia;98513",
    "addr:street":"Meridian Rd Se",
    "iso:country":"US",
    "sg:address":"3426 Meridian Rd SE",
    "sg:city":"Olympia",
    "sg:classifiers":[
        {
            "category":"Professional",
            "subcategory":"Engineering",
            "type":"Services"
        }
    ],
    "sg:phone":"+1 360 701 1470",
    "sg:postcode":"98513",
    "sg:province":"WA",
    "sg:tags":[
        "management"
    ],
    "wof:name":"Cobb Engrg & Prj Managment",
    "wof:placetype":"venue"
},
  "geometry": {"coordinates":[-122.727572,47.017803],"type":"Point"}
}