{
  "type": "Feature",
  "properties": {
    "addr:full":"1707 N Cincinnati St Spokane WA 99207",
    "addr:housenumber":"1707",
    "addr:postcode":"99207",
    "addr:street":"N Cincinnati St",
    "iso:country":"US",
    "sg:address":"1707 N Cincinnati St",
    "sg:city":"Spokane",
    "sg:classifiers":[
        {
            "category":"Building & Trades",
            "subcategory":"Construction",
            "type":"Services"
        }
    ],
    "sg:phone":"+1 509 489 3552",
    "sg:postcode":"99207",
    "sg:province":"WA",
    "sg:tags":[
        "contractor"
    ],
    "wof:name":"Heritage Roofing",
    "wof:placetype":"venue"
},
  "geometry": {"coordinates":[-117.398118,47.673192],"type":"Point"}
}