{
  "type": "Feature",
  "properties": {
    "addr:full":"913 Front St Leavenworth WA 98826",
    "addr:housenumber":"913",
    "addr:postcode":"98826",
    "addr:street":"Front St",
    "iso:country":"US",
    "sg:address":"913 Front St",
    "sg:city":"Leavenworth",
    "sg:classifiers":[
        {
            "category":"Retail",
            "subcategory":"Portrait Studio",
            "type":"Services"
        }
    ],
    "sg:phone":"+1 509 548 5585",
    "sg:postcode":"98826",
    "sg:province":"WA",
    "sg:tags":[
        "photo"
    ],
    "wof:name":"Kinney Photography",
    "wof:placetype":"venue"
},
  "geometry": {"coordinates":[-120.659701,47.596275],"type":"Point"}
}