{
  "type": "Feature",
  "properties": {
    "iso:country":"US",
    "sg:address":"12027 176th Ave SE",
    "sg:city":"Renton",
    "sg:classifiers":[
        {
            "category":"Building & Trades",
            "subcategory":"Construction",
            "type":"Services"
        }
    ],
    "sg:phone":"+1 425 235 2261",
    "sg:postcode":"98059",
    "sg:province":"WA",
    "sg:tags":[
        "backhoe",
        "contractor",
        "dump",
        "trucking"
    ],
    "wof:name":"Sams Backhoe Service",
    "wof:placetype":"venue"
},
  "geometry": {"coordinates":[-122.106261,47.495279],"type":"Point"}
}