{
  "type": "Feature",
  "properties": {
    "addr:full":"680 W Avery Rd Winlock WA 98596",
    "addr:housenumber":"680",
    "addr:postcode":"98596",
    "addr:street":"W Avery Rd",
    "iso:country":"US",
    "sg:address":"680 W Avery Rd",
    "sg:city":"Winlock",
    "sg:classifiers":[
        {
            "category":"Real Estate",
            "subcategory":"Real Estate Agent",
            "type":"Services"
        }
    ],
    "sg:phone":"+1 360 266 9619",
    "sg:postcode":"98596",
    "sg:province":"WA",
    "wof:name":"Becker T D Appraisal Services",
    "wof:placetype":"venue"
},
  "geometry": {"coordinates":[-122.935694,46.547089],"type":"Point"}
}