{
  "type": "Feature",
  "properties": {
    "addr:full":"1101 N Columbia St Ellensburg WA 98926",
    "addr:housenumber":"1101",
    "addr:postcode":"98926",
    "addr:street":"N Columbia St",
    "iso:country":"US",
    "sg:address":"1101 N Columbia St",
    "sg:city":"Ellensburg",
    "sg:classifiers":[
        {
            "category":"Building & Trades",
            "subcategory":"Construction",
            "type":"Services"
        }
    ],
    "sg:phone":"+1 509 925 2649",
    "sg:postcode":"98926",
    "sg:province":"WA",
    "sg:tags":[
        "house"
    ],
    "wof:name":"Lee Dale William Jr Cnstr",
    "wof:placetype":"venue"
},
  "geometry": {"coordinates":[-120.552274,47.002663],"type":"Point"}
}