{
  "type": "Feature",
  "properties": {
    "addr:full":"10740 Glen Acres Dr S Seattle WA 98168",
    "addr:housenumber":"10740",
    "addr:postcode":"98168",
    "addr:street":"Glen Acres Dr S",
    "iso:country":"US",
    "sg:address":"10740 Glen Acres Dr S",
    "sg:city":"Seattle",
    "sg:classifiers":[
        {
            "category":"Professional",
            "subcategory":"Management & Consulting",
            "type":"Services"
        }
    ],
    "sg:phone":"+1 206 244 9832",
    "sg:postcode":"98168",
    "sg:province":"WA",
    "sg:tags":[
        "des",
        "commercial",
        "business"
    ],
    "wof:name":"Studio Four Marketing",
    "wof:placetype":"venue"
},
  "geometry": {"coordinates":[-122.32072599999999,47.507986],"type":"Point"}
}