{
  "type": "Feature",
  "properties": {
    "addr:full":"111 E Lincoln Rd Spokane WA 99217",
    "addr:housenumber":"111",
    "addr:postcode":"99217",
    "addr:street":"E Lincoln Rd",
    "iso:country":"US",
    "sg:address":"111 E Lincoln Rd",
    "sg:city":"Spokane",
    "sg:classifiers":[
        {
            "category":"Personal",
            "subcategory":"Beauty Salon",
            "type":"Services"
        }
    ],
    "sg:phone":"+1 509 464 3616",
    "sg:postcode":"99217",
    "sg:province":"WA",
    "sg:tags":[
        "shop"
    ],
    "wof:name":"Hair & Nails By Heather",
    "wof:placetype":"venue"
},
  "geometry": {"coordinates":[-117.405232,47.729518],"type":"Point"}
}