{
  "type": "Feature",
  "properties": {
    "addr:full":"1569 S Seashore Dr Tacoma WA 98465",
    "addr:housenumber":"1569",
    "addr:postcode":"98465",
    "addr:street":"S Seashore Dr",
    "iso:country":"US",
    "sg:address":"1569 S Seashore Dr",
    "sg:city":"Tacoma",
    "sg:classifiers":[
        {
            "category":"Building & Trades",
            "subcategory":"Construction",
            "type":"Services"
        }
    ],
    "sg:phone":"+1 253 564 4120",
    "sg:postcode":"98465",
    "sg:province":"WA",
    "sg:tags":[
        "altering",
        "remodeling",
        "contractor"
    ],
    "sg:website":"http://www.masterbuilt-estatehomes.com",
    "wof:name":"Master Built Homes",
    "wof:placetype":"venue"
},
  "geometry": {"coordinates":[-122.553646,47.245659],"type":"Point"}
}