{
  "type": "Feature",
  "properties": {
    "addr:full":"8327 S Tacoma Way Lakewood WA 98499",
    "addr:housenumber":"8327",
    "addr:postcode":"98499",
    "addr:street":"S Tacoma Way",
    "iso:country":"US",
    "sg:address":"8327 S Tacoma Way",
    "sg:city":"Lakewood",
    "sg:classifiers":[
        {
            "category":"Shopping",
            "subcategory":"Shoes",
            "type":"Retail Goods"
        },
        {
            "category":"Shopping",
            "subcategory":"Clothing, Apparel, & Fashions",
            "type":"Retail Goods"
        }
    ],
    "sg:phone":"+1 253 582 9283",
    "sg:postcode":"98499",
    "sg:province":"WA",
    "sg:tags":[
        "boot"
    ],
    "wof:name":"El Morro Boots",
    "wof:placetype":"venue"
},
  "geometry": {"coordinates":[-122.48370799999999,47.182394],"type":"Point"}
}