{
  "type": "Feature",
  "properties": {
    "iso:country":"US",
    "sg:address":"3627 Wheaton Way",
    "sg:city":"Bremerton",
    "sg:classifiers":[
        {
            "category":"Shopping",
            "subcategory":"Crafts & Fabrics",
            "type":"Retail Goods"
        }
    ],
    "sg:phone":"+1 360 792 2221",
    "sg:postcode":"98310",
    "sg:province":"WA",
    "sg:tags":[
        "yarn"
    ],
    "wof:name":"Sweet Stitch Yarn Co",
    "wof:placetype":"venue"
},
  "geometry": {"coordinates":[-122.629419,47.599089],"type":"Point"}
}