{
  "type": "Feature",
  "properties": {
    "addr:full":"2257 W Eagle Ln SW Olympia WA 98512",
    "addr:housenumber":"2257",
    "addr:postcode":"98512",
    "addr:street":"W Eagle Ln Sw",
    "iso:country":"US",
    "sg:address":"2257 W Eagle Ln SW",
    "sg:city":"Olympia",
    "sg:classifiers":[
        {
            "category":"Real Estate",
            "subcategory":"Developer",
            "type":"Services"
        }
    ],
    "sg:phone":"+1 360 754 1880",
    "sg:postcode":"98512",
    "sg:province":"WA",
    "sg:tags":[
        "mobile",
        "home"
    ],
    "wof:name":"Eagles Landing Senior Park",
    "wof:placetype":"venue"
},
  "geometry": {"coordinates":[-122.930193,47.000419],"type":"Point"}
}