{
  "type": "Feature",
  "properties": {
    "addr:full":"814 S Wenatchee Ave Wenatchee WA 98801",
    "addr:housenumber":"814",
    "addr:postcode":"98801",
    "addr:street":"S Wenatchee Ave",
    "iso:country":"US",
    "sg:address":"814 S Wenatchee Ave",
    "sg:city":"Wenatchee",
    "sg:classifiers":[
        {
            "category":"Home & Garden",
            "subcategory":"Furniture",
            "type":"Retail Goods"
        }
    ],
    "sg:phone":"+1 509 665 8252",
    "sg:postcode":"98801",
    "sg:province":"WA",
    "wof:name":"Muebleria De Descuentos",
    "wof:placetype":"venue"
},
  "geometry": {"coordinates":[-120.302132,47.413149],"type":"Point"}
}