{
  "type": "Feature",
  "properties": {
    "addr:full":"4309 Forest Ave SE Mercer Island WA 98040",
    "addr:housenumber":"4309",
    "addr:postcode":"98040",
    "addr:street":"Forest Ave Se",
    "iso:country":"US",
    "sg:address":"4309 Forest Ave SE",
    "sg:city":"Mercer Island",
    "sg:classifiers":[
        {
            "category":"Professional",
            "type":"Services"
        }
    ],
    "sg:phone":"+1 206 236 1522",
    "sg:postcode":"98040",
    "sg:province":"WA",
    "wof:name":"Dennis E Stanley",
    "wof:placetype":"venue"
},
  "geometry": {"coordinates":[-122.23126000000001,47.566283],"type":"Point"}
}