{
  "type": "Feature",
  "properties": {
    "addr:full":"821 E 34th Ave Spokane WA 99203",
    "addr:housenumber":"821",
    "addr:postcode":"99203",
    "addr:street":"E 34Th Ave",
    "iso:country":"US",
    "sg:address":"821 E 34th Ave",
    "sg:city":"Spokane",
    "sg:classifiers":[
        {
            "category":"Education",
            "subcategory":"Special Training",
            "type":"Public Place"
        }
    ],
    "sg:phone":"+1 509 456 7328",
    "sg:postcode":"99203",
    "sg:province":"WA",
    "sg:tags":[
        "educational"
    ],
    "wof:name":"Educational Concepts",
    "wof:placetype":"venue"
},
  "geometry": {"coordinates":[-117.398178,47.623601],"type":"Point"}
}