{
  "type": "Feature",
  "properties": {
    "addr:full":"5123 Rose Ave NE Bainbridge Island WA 98110",
    "addr:housenumber":"5123",
    "addr:postcode":"98110",
    "addr:street":"Rose Ave Ne",
    "iso:country":"US",
    "sg:address":"5123 Rose Ave NE",
    "sg:city":"Bainbridge Island",
    "sg:classifiers":[
        {
            "category":"Real Estate",
            "subcategory":"Architect",
            "type":"Services"
        }
    ],
    "sg:phone":"+1 206 842 0806",
    "sg:postcode":"98110",
    "sg:province":"WA",
    "sg:tags":[
        "architectural"
    ],
    "wof:name":"Kdg Architecture PS",
    "wof:placetype":"venue"
},
  "geometry": {"coordinates":[-122.521028,47.611113],"type":"Point"}
}