{
  "type": "Feature",
  "properties": {
    "addr:full":"2918 78th Ave SE Mercer Island WA 98040",
    "addr:housenumber":"2918",
    "addr:postcode":"98040",
    "addr:street":"78Th Ave Se",
    "iso:country":"US",
    "sg:address":"2918 78th Ave SE",
    "sg:city":"Mercer Island",
    "sg:classifiers":[
        {
            "category":"Banks & Credit Unions",
            "subcategory":"Bank",
            "type":"Services"
        }
    ],
    "sg:phone":"+1 206 236 0300",
    "sg:postcode":"98040",
    "sg:province":"WA",
    "sg:tags":[
        "federal",
        "savings"
    ],
    "wof:name":"First Security",
    "wof:placetype":"venue"
},
  "geometry": {"coordinates":[-122.233548,47.583784],"type":"Point"}
}