{
  "type": "Feature",
  "properties": {
    "addr:full":"501 E Nelson Rd Moses Lake WA 98837",
    "addr:housenumber":"501",
    "addr:postcode":"98837",
    "addr:street":"E Nelson Rd",
    "iso:country":"US",
    "sg:address":"501 E Nelson Rd",
    "sg:city":"Moses Lake",
    "sg:classifiers":[
        {
            "category":"Real Estate",
            "subcategory":"Real Estate Agent",
            "type":"Services"
        }
    ],
    "sg:phone":"+1 509 764 7769",
    "sg:postcode":"98837",
    "sg:province":"WA",
    "wof:name":"St Marie Properties NW",
    "wof:placetype":"venue"
},
  "geometry": {"coordinates":[-119.269419,47.116507],"type":"Point"}
}