{
  "type": "Feature",
  "properties": {
    "addr:full":"3717 58th Ave SW Seattle WA 98116",
    "addr:housenumber":"3717",
    "addr:postcode":"98116",
    "addr:street":"58Th Ave Sw",
    "iso:country":"US",
    "sg:address":"3717 58th Ave SW",
    "sg:city":"Seattle",
    "sg:classifiers":[
        {
            "category":"Professional",
            "subcategory":"Business Services",
            "type":"Services"
        }
    ],
    "sg:phone":"+1 206 932 0421",
    "sg:postcode":"98116",
    "sg:province":"WA",
    "wof:name":"Michele Sullivan Design",
    "wof:placetype":"venue"
},
  "geometry": {"coordinates":[-122.4071,47.569183],"type":"Point"}
}