{
  "type": "Feature",
  "properties": {
    "addr:full":"10611 18th Ave E Tacoma WA 98445",
    "addr:housenumber":"10611",
    "addr:postcode":"98445",
    "addr:street":"18Th Ave E",
    "iso:country":"US",
    "sg:address":"10611 18th Ave E",
    "sg:city":"Tacoma",
    "sg:classifiers":[
        {
            "category":"Freight",
            "type":"Transportation"
        }
    ],
    "sg:phone":"+1 253 536 1260",
    "sg:postcode":"98445",
    "sg:province":"WA",
    "sg:tags":[
        "general"
    ],
    "wof:name":"Freeway Self Storage",
    "wof:placetype":"venue"
},
  "geometry": {"coordinates":[-122.405343,47.160556],"type":"Point"}
}