{
  "type": "Feature",
  "properties": {
    "addr:full":"1006 91st Ave NE Bellevue WA 98004",
    "addr:housenumber":"1006",
    "addr:postcode":"98004",
    "addr:street":"91St Ave Ne",
    "iso:country":"US",
    "sg:address":"1006 91st Ave NE",
    "sg:city":"Bellevue",
    "sg:classifiers":[
        {
            "category":"Place Of Worship",
            "subcategory":"Church",
            "type":"Public Place"
        },
        {
            "category":"Place Of Worship",
            "type":"Public Place"
        }
    ],
    "sg:phone":"+1 425 455 5201",
    "sg:postcode":"98004",
    "sg:province":"WA",
    "sg:tags":[
        "churches-episcopal-anglican",
        "churches-episcopal"
    ],
    "sg:website":"http://www.christianepiscopalchurch.org",
    "wof:name":"Christian Episcopal Church",
    "wof:placetype":"venue"
},
  "geometry": {"coordinates":[-122.21894,47.619309],"type":"Point"}
}