{
  "type": "Feature",
  "properties": {
    "addr:full":"4660 Whitman Ln SE Lacey WA 98513",
    "addr:housenumber":"4660",
    "addr:postcode":"98513",
    "addr:street":"Whitman Ln Se",
    "iso:country":"US",
    "sg:address":"4660 Whitman Ln SE",
    "sg:city":"Lacey",
    "sg:classifiers":[
        {
            "category":"Food & Beverages",
            "subcategory":"Liquor & Beverages",
            "type":"Retail Goods"
        }
    ],
    "sg:phone":"+1 360 455 3337",
    "sg:postcode":"98513",
    "sg:province":"WA",
    "sg:tags":[
        "store"
    ],
    "wof:name":"Rainier Park Liquor & Beverage",
    "wof:placetype":"venue"
},
  "geometry": {"coordinates":[-122.827575,46.995147],"type":"Point"}
}