{
  "type": "Feature",
  "properties": {
    "addr:full":"405 W Main St Coulee City WA 99115",
    "addr:housenumber":"405",
    "addr:postcode":"99115",
    "addr:street":"W Main St",
    "iso:country":"US",
    "sg:address":"405 W Main St",
    "sg:city":"Coulee City",
    "sg:classifiers":[
        {
            "category":"Education",
            "subcategory":"Library",
            "type":"Public Place"
        }
    ],
    "sg:phone":"+1 509 632 8751",
    "sg:postcode":"99115",
    "sg:province":"WA",
    "wof:name":"Coulee City Public Library",
    "wof:placetype":"venue"
},
  "geometry": {"coordinates":[-119.293789,47.611055],"type":"Point"}
}