{
  "type": "Feature",
  "properties": {
    "addr:full":"8415 87th Ave SW Lakewood WA 98498",
    "addr:housenumber":"8415",
    "addr:postcode":"98498",
    "addr:street":"87Th Ave Sw",
    "iso:country":"US",
    "sg:address":"8415 87th Ave SW",
    "sg:city":"Lakewood",
    "sg:classifiers":[
        {
            "category":"Restaurant",
            "type":"Food & Drink"
        }
    ],
    "sg:phone":"+1 253 582 6789",
    "sg:postcode":"98498",
    "sg:province":"WA",
    "wof:name":"Kin Ja Teriyaki",
    "wof:placetype":"venue"
},
  "geometry": {"coordinates":[-122.55300099999999,47.180099],"type":"Point"}
}