{
  "type": "Feature",
  "properties": {
    "addr:full":"11625 NE 95th St Kirkland WA 98033",
    "addr:housenumber":"11625",
    "addr:postcode":"98033",
    "addr:street":"Ne 95Th St",
    "iso:country":"US",
    "sg:address":"11625 NE 95th St",
    "sg:city":"Kirkland",
    "sg:classifiers":[
        {
            "category":"Manufacturing",
            "subcategory":"Toys & Sporting Goods",
            "type":"Manufacturing & Wholesale Goods"
        },
        {
            "category":"Wholesale",
            "subcategory":"Construction Materials",
            "type":"Manufacturing & Wholesale Goods"
        }
    ],
    "sg:phone":"+1 425 827 9648",
    "sg:postcode":"98033",
    "sg:province":"WA",
    "sg:tags":[
        "goods-wholesale",
        "sailmaker",
        "manufacturer"
    ],
    "sg:website":"http://www.dynamicsails.com",
    "wof:name":"Neil Pryde Sails",
    "wof:placetype":"venue"
},
  "geometry": {"coordinates":[-122.185438,47.686441],"type":"Point"}
}