{
  "type": "Feature",
  "properties": {
    "addr:full":"210 N Bolivar Rd Spokane WA 99216",
    "addr:housenumber":"210",
    "addr:postcode":"99216",
    "addr:street":"N Bolivar Rd",
    "iso:country":"US",
    "sg:address":"210 N Bolivar Rd",
    "sg:city":"Spokane",
    "sg:classifiers":[
        {
            "category":"Professional",
            "type":"Services"
        }
    ],
    "sg:phone":"+1 509 893 9134",
    "sg:postcode":"99216",
    "sg:province":"WA",
    "wof:name":"Rose Quilt House Wild",
    "wof:placetype":"venue"
},
  "geometry": {"coordinates":[-117.216009,47.657066],"type":"Point"}
}