{
  "type": "Feature",
  "properties": {
    "iso:country":"US",
    "sg:address":"320 Dora Ave",
    "sg:city":"Bremerton",
    "sg:classifiers":[
        {
            "category":"Building & Trades",
            "subcategory":"Construction",
            "type":"Services"
        }
    ],
    "sg:phone":"+1 360 373 2591",
    "sg:postcode":"98312",
    "sg:province":"WA",
    "sg:tags":[
        "general",
        "contractor"
    ],
    "wof:name":"Bruce Construction Co",
    "wof:placetype":"venue"
},
  "geometry": {"coordinates":[-122.666051,47.567244],"type":"Point"}
}