{
  "type": "Feature",
  "properties": {
    "iso:country":"US",
    "sg:address":"23920 SE Kent Kangley Rd",
    "sg:city":"Maple Valley",
    "sg:classifiers":[
        {
            "category":"Home & Garden",
            "subcategory":"Hardware",
            "type":"Retail Goods"
        },
        {
            "category":"Retail",
            "subcategory":"Funeral Services",
            "type":"Services"
        }
    ],
    "sg:phone":"+1 425 432 2677",
    "sg:postcode":"98038",
    "sg:province":"WA",
    "sg:website":"www.woodworkershop.com",
    "wof:name":"Johnson's Home & Garden",
    "wof:placetype":"venue"
},
  "geometry": {"coordinates":[-122.022306,47.361325],"type":"Point"}
}