{
  "type": "Feature",
  "properties": {
    "addr:full":"47225 Sauk Prairie Rd Darrington WA 98241",
    "addr:postcode":"47225;98241",
    "addr:street":"Prairie Rd",
    "iso:country":"US",
    "sg:address":"47225 Sauk Prairie Rd",
    "sg:city":"Darrington",
    "sg:classifiers":[
        {
            "category":"Airline",
            "type":"Transportation"
        }
    ],
    "sg:phone":"+1 360 436 1302",
    "sg:postcode":"98241",
    "sg:province":"WA",
    "sg:tags":[
        "helicopter",
        "charter"
    ],
    "wof:name":"HI Line Helicopters Inc",
    "wof:placetype":"venue"
},
  "geometry": {"coordinates":[-121.59469,48.261832],"type":"Point"}
}