{
  "type": "Feature",
  "properties": {
    "addr:full":"1111 228th St SE Bothell WA 98021",
    "addr:housenumber":"1111",
    "addr:postcode":"98021",
    "addr:street":"228Th St Se",
    "iso:country":"US",
    "sg:address":"1111 228th St SE",
    "sg:city":"Bothell",
    "sg:classifiers":[
        {
            "category":"Restaurant",
            "type":"Food & Drink"
        }
    ],
    "sg:phone":"+1 425 481 7588",
    "sg:postcode":"98021",
    "sg:province":"WA",
    "sg:tags":[
        "eating"
    ],
    "wof:name":"Magic Dragon",
    "wof:placetype":"venue"
},
  "geometry": {"coordinates":[-122.21774600000001,47.791333],"type":"Point"}
}