{
  "type": "Feature",
  "properties": {
    "addr:full":"12817 17th St. Vancouver WA 98684",
    "addr:housenumber":"12817",
    "addr:postcode":"98684",
    "addr:street":"17Th St.",
    "iso:country":"US",
    "sg:address":"12817 17th St.",
    "sg:city":"Vancouver",
    "sg:classifiers":[
        {
            "category":"Personal",
            "type":"Services"
        }
    ],
    "sg:phone":"+1 360 608 2129",
    "sg:postcode":"98684",
    "sg:province":"WA",
    "sg:tags":[
        "home"
    ],
    "sg:website":"westcoastsiding.net/",
    "wof:name":"West Coast Exteriors",
    "wof:placetype":"venue"
},
  "geometry": {"coordinates":[-122.540797,45.634097],"type":"Point"}
}