{
  "type": "Feature",
  "properties": {
    "addr:full":"22801 44th Ave W Mountlake Ter WA 98043",
    "addr:housenumber":"22801",
    "addr:postcode":"98043",
    "addr:street":"44Th Ave W Mountlake Ter",
    "iso:country":"US",
    "sg:address":"22801 44th Ave W",
    "sg:city":"Mountlake Ter",
    "sg:classifiers":[
        {
            "category":"Autos & Motor Vehicles",
            "subcategory":"Fuel & Gas Station",
            "type":"Retail Goods"
        }
    ],
    "sg:phone":"+1 425 774 6220",
    "sg:postcode":"98043",
    "sg:province":"WA",
    "sg:tags":[
        "oil"
    ],
    "wof:name":"Mountlake Terrace Chevron",
    "wof:placetype":"venue"
},
  "geometry": {"coordinates":[-122.29222900000001,47.791889],"type":"Point"}
}