{
  "type": "Feature",
  "properties": {
    "addr:full":"3410 A St SE Auburn WA 98002",
    "addr:housenumber":"3410",
    "addr:postcode":"98002",
    "addr:street":"A St Se",
    "iso:country":"US",
    "sg:address":"3410 A St SE",
    "sg:city":"Auburn",
    "sg:classifiers":[
        {
            "category":"Manufacturing",
            "subcategory":"Metals",
            "type":"Manufacturing & Wholesale Goods"
        }
    ],
    "sg:phone":"+1 253 735 0156",
    "sg:postcode":"98002",
    "sg:province":"WA",
    "sg:tags":[
        "stamping",
        "sheet",
        "fabrication"
    ],
    "wof:name":"Imaginetics Inc",
    "wof:placetype":"venue"
},
  "geometry": {"coordinates":[-122.228812,47.277406],"type":"Point"}
}