{
  "type": "Feature",
  "properties": {
    "addr:full":"16010 State Hwy 27 Rockford WA 99030",
    "addr:housenumber":"16010",
    "addr:postcode":"99030",
    "addr:street":"State Hwy 27",
    "iso:country":"US",
    "sg:address":"16010 State Hwy 27",
    "sg:city":"Rockford",
    "sg:classifiers":[
        {
            "category":"Building & Trades",
            "subcategory":"Electrical",
            "type":"Services"
        }
    ],
    "sg:phone":"+1 509 922 8403",
    "sg:postcode":"99030",
    "sg:province":"WA",
    "sg:tags":[
        "electrical",
        "contractor"
    ],
    "wof:name":"Stranberg Electric Inc",
    "wof:placetype":"venue"
},
  "geometry": {"coordinates":[-117.174494,47.50926],"type":"Point"}
}