{
  "type": "Feature",
  "properties": {
    "addr:full":"511 16th Ave S Seattle WA 98144",
    "addr:housenumber":"511",
    "addr:postcode":"98144",
    "addr:street":"16Th Ave S",
    "iso:country":"US",
    "sg:address":"511 16th Ave S",
    "sg:city":"Seattle",
    "sg:classifiers":[
        {
            "category":"Education",
            "subcategory":"School",
            "type":"Public Place"
        }
    ],
    "sg:phone":"+1 206 760 1526",
    "sg:postcode":"98144",
    "sg:province":"WA",
    "wof:name":"Lake Wash Girls Middle Schl",
    "wof:placetype":"venue"
},
  "geometry": {"coordinates":[-122.31166,47.597573],"type":"Point"}
}