{
  "type": "Feature",
  "properties": {
    "addr:full":"607 21st Ave Longview WA 98632",
    "addr:housenumber":"607",
    "addr:postcode":"98632",
    "addr:street":"21St Ave",
    "iso:country":"US",
    "sg:address":"607 21st Ave",
    "sg:city":"Longview",
    "sg:classifiers":[
        {
            "category":"Retail",
            "subcategory":"Auto Repair",
            "type":"Services"
        }
    ],
    "sg:phone":"+1 360 423 5790",
    "sg:postcode":"98632",
    "sg:province":"WA",
    "sg:tags":[
        "assistance",
        "roadside"
    ],
    "wof:name":"Fairchild Joseph Enterprises",
    "wof:placetype":"venue"
},
  "geometry": {"coordinates":[-122.94800499999999,46.129226],"type":"Point"}
}