{
  "type": "Feature",
  "properties": {
    "addr:full":"11111 NE 8th St Ste 125 Bellevue WA 98004",
    "addr:housenumber":"11111",
    "addr:postcode":"98004",
    "addr:street":"Ne 8Th St Ste 125",
    "iso:country":"US",
    "sg:address":"11111 NE 8th St Ste 125",
    "sg:city":"Bellevue",
    "sg:classifiers":[
        {
            "category":"Restaurant",
            "type":"Food & Drink"
        }
    ],
    "sg:phone":"+1 425 440 0880",
    "sg:postcode":"98004",
    "sg:province":"WA",
    "sg:tags":[
        "steakhouse"
    ],
    "sg:website":"www.johnhowiesteak.com",
    "wof:name":"John Howie Steak",
    "wof:placetype":"venue"
},
  "geometry": {"coordinates":[-122.191794,47.616455],"type":"Point"}
}