{
  "type": "Feature",
  "properties": {
    "addr:full":"440 Elm Ln Pasco WA 99301",
    "addr:housenumber":"440",
    "addr:postcode":"99301",
    "addr:street":"Elm Ln",
    "iso:country":"US",
    "sg:address":"440 Elm Ln",
    "sg:city":"Pasco",
    "sg:classifiers":[
        {
            "category":"Education",
            "subcategory":"Special Training",
            "type":"Public Place"
        }
    ],
    "sg:phone":"+1 509 948 1883",
    "sg:postcode":"99301",
    "sg:province":"WA",
    "wof:name":"Exact English",
    "wof:placetype":"venue"
},
  "geometry": {"coordinates":[-119.107702,46.430793],"type":"Point"}
}