{
  "type": "Feature",
  "properties": {
    "addr:full":"6725 Greenwood Ave N Seattle WA 98103",
    "addr:housenumber":"6725",
    "addr:postcode":"98103",
    "addr:street":"Greenwood Ave N",
    "iso:country":"US",
    "sg:address":"6725 Greenwood Ave N",
    "sg:city":"Seattle",
    "sg:classifiers":[
        {
            "category":"Health Services",
            "subcategory":"Dentist",
            "type":"Services"
        }
    ],
    "sg:phone":"+1 206 284 2483",
    "sg:postcode":"98103",
    "sg:province":"WA",
    "sg:website":"www.espressodental.com/",
    "wof:name":"Espresso Dental - Dr. Connie Manuel DDS",
    "wof:placetype":"venue"
},
  "geometry": {"coordinates":[-122.355525,47.678475],"type":"Point"}
}