{
  "type": "Feature",
  "properties": {
    "addr:full":"511 Crestloch Rd Pasco WA 99301",
    "addr:housenumber":"511",
    "addr:postcode":"99301",
    "addr:street":"Crestloch Rd",
    "iso:country":"US",
    "sg:address":"511 Crestloch Rd",
    "sg:city":"Pasco",
    "sg:phone":"+1 509 542 0718",
    "sg:postcode":"99301",
    "sg:province":"WA",
    "sg:tags":[
        "farm",
        "field",
        "crop"
    ],
    "wof:name":"Clark Family Farm",
    "wof:placetype":"venue"
},
  "geometry": {"coordinates":[-119.078459,46.35881],"type":"Point"}
}