{
  "type": "Feature",
  "properties": {
    "addr:full":"118 N 2nd St Shelton WA 98584",
    "addr:housenumber":"118",
    "addr:postcode":"98584",
    "addr:street":"N 2Nd St",
    "iso:country":"US",
    "sg:address":"118 N 2nd St",
    "sg:city":"Shelton",
    "sg:classifiers":[
        {
            "category":"Personal",
            "subcategory":"Beauty Salon",
            "type":"Services"
        }
    ],
    "sg:phone":"+1 360 426 2141",
    "sg:postcode":"98584",
    "sg:province":"WA",
    "sg:tags":[
        "care",
        "skin"
    ],
    "wof:name":"2nd Street Design Studio",
    "wof:placetype":"venue"
},
  "geometry": {"coordinates":[-123.101282,47.213143],"type":"Point"}
}