{
  "type": "Feature",
  "properties": {
    "addr:full":"3838 NE 98th St Seattle WA 98115",
    "addr:housenumber":"3838",
    "addr:postcode":"98115",
    "addr:street":"Ne 98Th St",
    "iso:country":"US",
    "sg:address":"3838 NE 98th St",
    "sg:city":"Seattle",
    "sg:classifiers":[
        {
            "category":"Restaurant",
            "type":"Food & Drink"
        }
    ],
    "sg:phone":"+1 206 440 5676",
    "sg:postcode":"98115",
    "sg:province":"WA",
    "sg:tags":[
        "caterer"
    ],
    "wof:name":"Express Meals",
    "wof:placetype":"venue"
},
  "geometry": {"coordinates":[-122.285692,47.700234],"type":"Point"}
}