{
  "type": "Feature",
  "properties": {
    "addr:full":"1930 NW 30th Cir Camas WA 98607",
    "addr:housenumber":"1930",
    "addr:postcode":"98607",
    "addr:street":"Nw 30Th Cir",
    "iso:country":"US",
    "sg:address":"1930 NW 30th Cir",
    "sg:city":"Camas",
    "sg:classifiers":[
        {
            "category":"Professional",
            "type":"Services"
        }
    ],
    "sg:phone":"+1 360 834 1055",
    "sg:postcode":"98607",
    "sg:province":"WA",
    "wof:name":"Art Niche",
    "wof:placetype":"venue"
},
  "geometry": {"coordinates":[-122.42942499999999,45.601149],"type":"Point"}
}