{
  "type": "Feature",
  "properties": {
    "addr:full":"911 Crestloch Rd Pasco WA 99301",
    "addr:housenumber":"911",
    "addr:postcode":"99301",
    "addr:street":"Crestloch Rd",
    "iso:country":"US",
    "sg:address":"911 Crestloch Rd",
    "sg:city":"Pasco",
    "sg:classifiers":[
        {
            "category":"Farming",
            "subcategory":"Farm",
            "type":"Manufacturing & Wholesale Goods"
        }
    ],
    "sg:phone":"+1 509 545 9290",
    "sg:postcode":"99301",
    "sg:province":"WA",
    "sg:tags":[
        "crop",
        "general"
    ],
    "wof:name":"Seneca Foods Corp",
    "wof:placetype":"venue"
},
  "geometry": {"coordinates":[-119.073671,46.361071],"type":"Point"}
}