{
  "type": "Feature",
  "properties": {
    "addr:full":"3410 Gravelly Beach Loop NW Olympia WA 98502",
    "addr:housenumber":"3410",
    "addr:postcode":"olympia wa 98502",
    "addr:street":"Gravelly Beach Loop Nw",
    "iso:country":"US",
    "sg:address":"3410 Gravelly Beach Loop NW",
    "sg:city":"Olympia",
    "sg:classifiers":[
        {
            "category":"Structure",
            "subcategory":"Office Building",
            "type":"Public Place"
        }
    ],
    "sg:phone":"+1 360 866 2676",
    "sg:postcode":"98502",
    "sg:province":"WA",
    "sg:tags":[
        "park"
    ],
    "wof:name":"Brubaker Properties",
    "wof:placetype":"venue"
},
  "geometry": {"coordinates":[-122.968452,47.104912],"type":"Point"}
}