{
  "type": "Feature",
  "properties": {
    "addr:full":"1804 S 66th Ave Yakima WA 98908",
    "addr:housenumber":"1804",
    "addr:postcode":"98908",
    "addr:street":"S 66Th Ave",
    "iso:country":"US",
    "sg:address":"1804 S 66th Ave",
    "sg:city":"Yakima",
    "sg:classifiers":[
        {
            "category":"Building & Trades",
            "subcategory":"Cleaning & Sanitation",
            "type":"Services"
        }
    ],
    "sg:phone":"+1 509 966 2334",
    "sg:postcode":"98908",
    "sg:province":"WA",
    "sg:tags":[
        "janitor"
    ],
    "wof:name":"Valley Custodial Svc & Supply",
    "wof:placetype":"venue"
},
  "geometry": {"coordinates":[-120.597633,46.571939],"type":"Point"}
}