{
  "type": "Feature",
  "properties": {
    "addr:full":"10219 185th Ave SW Rochester WA 98579",
    "addr:housenumber":"10219",
    "addr:postcode":"98579",
    "addr:street":"185Th Ave Sw",
    "iso:country":"US",
    "sg:address":"10219 185th Ave SW",
    "sg:city":"Rochester",
    "sg:classifiers":[
        {
            "category":"Real Estate",
            "subcategory":"Real Estate Agent",
            "type":"Services"
        }
    ],
    "sg:phone":"+1 360 273 0195",
    "sg:postcode":"98579",
    "sg:province":"WA",
    "sg:tags":[
        "industrial",
        "machinery",
        "mfg"
    ],
    "wof:name":"Machine Master",
    "wof:placetype":"venue"
},
  "geometry": {"coordinates":[-123.101136,46.818721],"type":"Point"}
}