{
  "type": "Feature",
  "properties": {
    "addr:full":"13346 1st Ave NE Seattle WA 98125",
    "addr:housenumber":"13346",
    "addr:postcode":"98125",
    "addr:street":"1St Ave Ne",
    "iso:country":"US",
    "sg:address":"13346 1st Ave NE",
    "sg:city":"Seattle",
    "sg:classifiers":[
        {
            "category":"Manufacturing",
            "subcategory":"Signs",
            "type":"Manufacturing & Wholesale Goods"
        }
    ],
    "sg:phone":"+1 206 361 6600",
    "sg:postcode":"98125",
    "sg:province":"WA",
    "wof:name":"Federal Signs",
    "wof:placetype":"venue"
},
  "geometry": {"coordinates":[-122.32886999999999,47.726802],"type":"Point"}
}