{
  "type": "Feature",
  "properties": {
    "addr:full":"5718 Kirkwood Pl N Seattle WA 98103",
    "addr:housenumber":"5718",
    "addr:postcode":"98103",
    "addr:street":"Kirkwood Pl N",
    "iso:country":"US",
    "sg:address":"5718 Kirkwood Pl N",
    "sg:city":"Seattle",
    "sg:classifiers":[
        {
            "category":"Professional",
            "subcategory":"Business Services",
            "type":"Services"
        }
    ],
    "sg:phone":"+1 206 523 1488",
    "sg:postcode":"98103",
    "sg:province":"WA",
    "wof:name":"Stephen Spickard",
    "wof:placetype":"venue"
},
  "geometry": {"coordinates":[-122.33331200000001,47.671501],"type":"Point"}
}