{
  "type": "Feature",
  "properties": {
    "iso:country":"US",
    "sg:address":"4210 Gardenspot Rd",
    "sg:city":"Loon Lake",
    "sg:classifiers":[
        {
            "category":"Building & Trades",
            "subcategory":"Construction",
            "type":"Services"
        }
    ],
    "sg:phone":"+1 509 233 8877",
    "sg:postcode":"99148",
    "sg:province":"WA",
    "sg:tags":[
        "carpentry",
        "contractor"
    ],
    "wof:name":"Commercial Doors Inc",
    "wof:placetype":"venue"
},
  "geometry": {"coordinates":[-117.58989,48.068967],"type":"Point"}
}