{
  "type": "Feature",
  "properties": {
    "addr:full":"500 W Fir St Sequim WA 98382",
    "addr:housenumber":"500",
    "addr:postcode":"98382",
    "addr:street":"W Fir St",
    "iso:country":"US",
    "sg:address":"500 W Fir St",
    "sg:city":"Sequim",
    "sg:classifiers":[
        {
            "category":"Health Services",
            "subcategory":"Doctor",
            "type":"Services"
        }
    ],
    "sg:phone":"+1 360 582 1500",
    "sg:postcode":"98382",
    "sg:province":"WA",
    "sg:tags":[
        "physician",
        "surgeon"
    ],
    "wof:name":"Paulus D Tsai MD",
    "wof:placetype":"venue"
},
  "geometry": {"coordinates":[-123.113145,48.08331],"type":"Point"}
}