{
  "type": "Feature",
  "properties": {
    "addr:full":"18708 85th Pl W Edmonds WA 98026",
    "addr:housenumber":"18708",
    "addr:postcode":"98026",
    "addr:street":"85Th Pl W",
    "iso:country":"US",
    "sg:address":"18708 85th Pl W",
    "sg:city":"Edmonds",
    "sg:classifiers":[
        {
            "category":"Home & Garden",
            "subcategory":"Building Materials",
            "type":"Retail Goods"
        }
    ],
    "sg:phone":"+1 425 672 2437",
    "sg:postcode":"98026",
    "sg:province":"WA",
    "wof:name":"Stutzgaard Stained Glass",
    "wof:placetype":"venue"
},
  "geometry": {"coordinates":[-122.34889200000001,47.829579],"type":"Point"}
}