{
  "type": "Feature",
  "properties": {
    "addr:full":"1005 SE 98th Ave Vancouver WA 98664",
    "addr:housenumber":"1005",
    "addr:postcode":"98664",
    "addr:street":"Se 98Th Ave",
    "iso:country":"US",
    "sg:address":"1005 SE 98th Ave",
    "sg:city":"Vancouver",
    "sg:classifiers":[
        {
            "category":"Building & Trades",
            "subcategory":"Construction",
            "type":"Services"
        }
    ],
    "sg:phone":"+1 360 883 0649",
    "sg:postcode":"98664",
    "sg:province":"WA",
    "sg:tags":[
        "general",
        "contractor"
    ],
    "wof:name":"Barton House Works",
    "wof:placetype":"venue"
},
  "geometry": {"coordinates":[-122.57225800000001,45.612863],"type":"Point"}
}