{
  "type": "Feature",
  "properties": {
    "addr:full":"342 Sunset Hwy Cashmere WA 98815",
    "addr:housenumber":"342",
    "addr:postcode":"98815",
    "addr:street":"Sunset Hwy Cashmere",
    "iso:country":"US",
    "sg:address":"342 Sunset Hwy",
    "sg:city":"Cashmere",
    "sg:classifiers":[
        {
            "category":"Food & Beverages",
            "subcategory":"Liquor & Beverages",
            "type":"Retail Goods"
        }
    ],
    "sg:phone":"+1 509 782 3496",
    "sg:postcode":"98815",
    "sg:province":"WA",
    "sg:tags":[
        "beer",
        "spirit",
        "wine"
    ],
    "wof:name":"Old Mission Spirits",
    "wof:placetype":"venue"
},
  "geometry": {"coordinates":[-120.474251,47.521072],"type":"Point"}
}