{
  "type": "Feature",
  "properties": {
    "addr:full":"6732 Beverly Blvd Everett WA 98203",
    "addr:housenumber":"6732",
    "addr:postcode":"98203",
    "addr:street":"Beverly Blvd",
    "iso:country":"US",
    "sg:address":"6732 Beverly Blvd",
    "sg:city":"Everett",
    "sg:classifiers":[
        {
            "category":"Food & Beverages",
            "subcategory":"Specialty",
            "type":"Retail Goods"
        },
        {
            "category":"Restaurant",
            "type":"Food & Drink"
        }
    ],
    "sg:phone":"+1 425 355 3563",
    "sg:postcode":"98203",
    "sg:province":"WA",
    "sg:tags":[
        "tea",
        "coffee",
        "eating"
    ],
    "wof:name":"Beverly Park Espresso",
    "wof:placetype":"venue"
},
  "geometry": {"coordinates":[-122.209964,47.93742],"type":"Point"}
}