{
  "type": "Feature",
  "properties": {
    "addr:full":"4217 Wheaton Way Bremerton WA 98310",
    "addr:housenumber":"4217",
    "addr:postcode":"98310",
    "addr:street":"Wheaton Way",
    "iso:country":"US",
    "sg:address":"4217 Wheaton Way",
    "sg:city":"Bremerton",
    "sg:classifiers":[
        {
            "category":"Personal",
            "subcategory":"Beauty Salon",
            "type":"Services"
        }
    ],
    "sg:phone":"+1 360 373 3885",
    "sg:postcode":"98310",
    "sg:province":"WA",
    "sg:tags":[
        "shop"
    ],
    "wof:name":"Beaches Salon",
    "wof:placetype":"venue"
},
  "geometry": {"coordinates":[-122.62891999999999,47.606777],"type":"Point"}
}