{
  "type": "Feature",
  "properties": {
    "addr:full":"828 Rainier Ave S Seattle WA 98144",
    "addr:housenumber":"828",
    "addr:postcode":"98144",
    "addr:street":"Rainier Ave S",
    "iso:country":"US",
    "sg:address":"828 Rainier Ave S",
    "sg:city":"Seattle",
    "sg:classifiers":[
        {
            "category":"Restaurant",
            "type":"Food & Drink"
        }
    ],
    "sg:postcode":"98144",
    "sg:province":"WA",
    "sg:tags":[
        "fusion",
        "asian"
    ],
    "sg:website":"www.ricenroll.com/",
    "wof:name":"Rice-N-Roll",
    "wof:placetype":"venue"
},
  "geometry": {"coordinates":[-122.311311,47.595589],"type":"Point"}
}