{
  "type": "Feature",
  "properties": {
    "addr:full":"720 Washington St Woodland WA 98674",
    "addr:housenumber":"720",
    "addr:postcode":"98674",
    "addr:street":"Washington St",
    "iso:country":"US",
    "sg:address":"720 Washington St",
    "sg:city":"Woodland",
    "sg:classifiers":[
        {
            "category":"Professional",
            "type":"Services"
        }
    ],
    "sg:phone":"+1 360 225 0645",
    "sg:postcode":"98674",
    "sg:province":"WA",
    "wof:name":"Diversity Northwest",
    "wof:placetype":"venue"
},
  "geometry": {"coordinates":[-122.75349799999999,45.907916],"type":"Point"}
}