{
  "type": "Feature",
  "properties": {
    "addr:full":"1501 Market St Tacoma WA 98402",
    "addr:housenumber":"1501",
    "addr:postcode":"98402",
    "addr:street":"Market St",
    "iso:country":"US",
    "sg:address":"1501 Market St",
    "sg:city":"Tacoma",
    "sg:classifiers":[
        {
            "category":"Professional",
            "type":"Services"
        }
    ],
    "sg:phone":"+1 253 572 5979",
    "sg:postcode":"98402",
    "sg:province":"WA",
    "sg:tags":[
        "establishment"
    ],
    "wof:name":"Trammell Crow Co",
    "wof:placetype":"venue"
},
  "geometry": {"coordinates":[-122.44013099999999,47.246896],"type":"Point"}
}