{
  "type": "Feature",
  "properties": {
    "addr:full":"898 SW Fleet St Oak Harbor WA 98277",
    "addr:housenumber":"898",
    "addr:postcode":"98277",
    "addr:street":"Sw Fleet St",
    "iso:country":"US",
    "sg:address":"898 SW Fleet St",
    "sg:city":"Oak Harbor",
    "sg:classifiers":[
        {
            "category":"Professional",
            "type":"Services"
        }
    ],
    "sg:phone":"+1 360 675 4873",
    "sg:postcode":"98277",
    "sg:province":"WA",
    "wof:name":"Educational & Research Service",
    "wof:placetype":"venue"
},
  "geometry": {"coordinates":[-122.66493699999999,48.290991],"type":"Point"}
}