{
  "type": "Feature",
  "properties": {
    "addr:full":"8611 NE 137th St Kirkland WA 98034",
    "addr:housenumber":"8611",
    "addr:postcode":"98034",
    "addr:street":"Ne 137Th St",
    "iso:country":"US",
    "sg:address":"8611 NE 137th St",
    "sg:city":"Kirkland",
    "sg:classifiers":[
        {
            "category":"Professional",
            "subcategory":"Computer Services",
            "type":"Services"
        }
    ],
    "sg:phone":"+1 425 823 8077",
    "sg:postcode":"98034",
    "sg:province":"WA",
    "sg:tags":[
        "datum"
    ],
    "wof:name":"John Kutz Design",
    "wof:placetype":"venue"
},
  "geometry": {"coordinates":[-122.22726400000001,47.722787],"type":"Point"}
}