{
  "type": "Feature",
  "properties": {
    "addr:full":"209 Euclid Ave Seattle WA 98122",
    "addr:housenumber":"209",
    "addr:postcode":"98122",
    "addr:street":"Euclid Ave",
    "iso:country":"US",
    "sg:address":"209 Euclid Ave",
    "sg:city":"Seattle",
    "sg:classifiers":[
        {
            "category":"Health Services",
            "subcategory":"Doctor",
            "type":"Services"
        }
    ],
    "sg:phone":"+1 206 568 4916",
    "sg:postcode":"98122",
    "sg:province":"WA",
    "sg:tags":[
        "medical"
    ],
    "wof:name":"Jacqueline Jaspan MD",
    "wof:placetype":"venue"
},
  "geometry": {"coordinates":[-122.28849,47.602634],"type":"Point"}
}