{
  "type": "Feature",
  "properties": {
    "addr:full":"4604 130th Pl NE Marysville WA 98271",
    "addr:housenumber":"4604",
    "addr:postcode":"98271",
    "addr:street":"130Th Pl Ne",
    "iso:country":"US",
    "sg:address":"4604 130th Pl NE",
    "sg:city":"Marysville",
    "sg:classifiers":[
        {
            "category":"Manufacturing",
            "subcategory":"Electronics",
            "type":"Manufacturing & Wholesale Goods"
        }
    ],
    "sg:phone":"+1 360 658 0733",
    "sg:postcode":"98271",
    "sg:province":"WA",
    "sg:tags":[
        "connector",
        "electronic",
        "mfg"
    ],
    "wof:name":"Wizard Electronics",
    "wof:placetype":"venue"
},
  "geometry": {"coordinates":[-122.16873,48.113249],"type":"Point"}
}