{
  "type": "Feature",
  "properties": {
    "addr:full":"12518 Reservoir Rd E Puyallup WA 98374",
    "addr:housenumber":"12518",
    "addr:postcode":"98374",
    "addr:street":"Reservoir Rd E",
    "iso:country":"US",
    "sg:address":"12518 Reservoir Rd E",
    "sg:city":"Puyallup",
    "sg:classifiers":[
        {
            "category":"Professional",
            "subcategory":"Business Services",
            "type":"Services"
        }
    ],
    "sg:phone":"+1 253 677 7847",
    "sg:postcode":"98374",
    "sg:province":"WA",
    "wof:name":"Merchant Services",
    "wof:placetype":"venue"
},
  "geometry": {"coordinates":[-122.26310100000001,47.136335],"type":"Point"}
}