{
  "type": "Feature",
  "properties": {
    "addr:full":"90 Access Rd Connell WA 99326",
    "addr:housenumber":"90",
    "addr:postcode":"99326",
    "addr:street":"Access Rd",
    "iso:country":"US",
    "sg:address":"90 Access Rd",
    "sg:city":"Connell",
    "sg:classifiers":[
        {
            "category":"Retail",
            "subcategory":"Auto Repair",
            "type":"Services"
        }
    ],
    "sg:phone":"+1 509 234 6848",
    "sg:postcode":"99326",
    "sg:province":"WA",
    "sg:tags":[
        "automotive"
    ],
    "wof:name":"All State Auto Electric",
    "wof:placetype":"venue"
},
  "geometry": {"coordinates":[-118.88512900000001,46.664524],"type":"Point"}
}