{
  "type": "Feature",
  "properties": {
    "addr:full":"22391 Foss Rd NE Poulsbo WA 98370",
    "addr:postcode":"22391;98370",
    "addr:street":"Foss Rd Ne",
    "iso:country":"US",
    "sg:address":"22391 Foss Rd NE",
    "sg:city":"Poulsbo",
    "sg:classifiers":[
        {
            "category":"Professional",
            "type":"Services"
        }
    ],
    "sg:phone":"+1 360 779 1357",
    "sg:postcode":"98370",
    "sg:province":"WA",
    "wof:name":"Fitch Services",
    "wof:placetype":"venue"
},
  "geometry": {"coordinates":[-122.61248999999999,47.766141],"type":"Point"}
}