{
  "type": "Feature",
  "properties": {
    "addr:full":"1421 Lake Washington Blvd S Seattle WA 98127",
    "addr:housenumber":"1421",
    "addr:postcode":"98127",
    "addr:street":"Lake Washington Blvd S",
    "iso:country":"US",
    "sg:address":"1421 Lake Washington Blvd S",
    "sg:city":"Seattle",
    "sg:classifiers":[
        {
            "category":"Shopping",
            "subcategory":"Pets & Pet Supplies",
            "type":"Retail Goods"
        }
    ],
    "sg:phone":"+1 206 324 7387",
    "sg:postcode":"98127",
    "sg:province":"WA",
    "sg:tags":[
        "store"
    ],
    "sg:website":"darwinsnaturalpet.com",
    "wof:name":"Darwin's Natural Pet Products",
    "wof:placetype":"venue"
},
  "geometry": {"coordinates":[-122.289175,47.589764],"type":"Point"}
}