{
  "type": "Feature",
  "properties": {
    "addr:full":"2069 Main St Ferndale WA 98248",
    "addr:housenumber":"2069",
    "addr:postcode":"98248",
    "addr:street":"Main St",
    "iso:country":"US",
    "sg:address":"2069 Main St",
    "sg:city":"Ferndale",
    "sg:classifiers":[
        {
            "category":"Manufacturing",
            "subcategory":"Buildings",
            "type":"Manufacturing & Wholesale Goods"
        },
        {
            "category":"Building & Trades",
            "subcategory":"Construction",
            "type":"Services"
        }
    ],
    "sg:phone":"+1 360 384 6561",
    "sg:postcode":"98248",
    "sg:province":"WA",
    "sg:tags":[
        "industrial",
        "system",
        "specialty",
        "builder",
        "heating",
        "contractor",
        "contractors-commercial",
        "home",
        "air conditioning"
    ],
    "wof:name":"Bell Enterprises",
    "wof:placetype":"venue"
},
  "geometry": {"coordinates":[-122.593315,48.847494],"type":"Point"}
}