{
  "type": "Feature",
  "properties": {
    "addr:full":"2601 N Capitol Ave Pasco WA 99301",
    "addr:housenumber":"2601",
    "addr:postcode":"99301",
    "addr:street":"N Capitol Ave",
    "iso:country":"US",
    "sg:address":"2601 N Capitol Ave",
    "sg:city":"Pasco",
    "sg:classifiers":[
        {
            "category":"Building & Trades",
            "subcategory":"Pest Control",
            "type":"Services"
        }
    ],
    "sg:phone":"+1 509 545 4083",
    "sg:postcode":"99301",
    "sg:province":"WA",
    "wof:name":"Franklin County Mosquito Control District",
    "wof:placetype":"venue"
},
  "geometry": {"coordinates":[-119.076972,46.256254],"type":"Point"}
}