{
  "type": "Feature",
  "properties": {
    "addr:full":"19834 141st Pl NE Woodinville WA 98072",
    "addr:housenumber":"19834",
    "addr:postcode":"98072",
    "addr:street":"141St Pl Ne",
    "iso:country":"US",
    "sg:address":"19834 141st Pl NE",
    "sg:city":"Woodinville",
    "sg:classifiers":[
        {
            "category":"Wholesale",
            "subcategory":"Machinery & Supplies",
            "type":"Manufacturing & Wholesale Goods"
        }
    ],
    "sg:phone":"+1 425 481 4797",
    "sg:postcode":"98072",
    "sg:province":"WA",
    "sg:tags":[
        "equipment",
        "metalworking"
    ],
    "wof:name":"Benoit Sheet Metal Equipment",
    "wof:placetype":"venue"
},
  "geometry": {"coordinates":[-122.150991,47.771255],"type":"Point"}
}