{
  "type": "Feature",
  "properties": {
    "addr:full":"1000 S Pekin Rd Woodland WA 98674",
    "addr:housenumber":"1000",
    "addr:postcode":"98674",
    "addr:street":"S Pekin Rd",
    "iso:country":"US",
    "sg:address":"1000 S Pekin Rd",
    "sg:city":"Woodland",
    "sg:classifiers":[
        {
            "category":"Building & Trades",
            "subcategory":"Construction",
            "type":"Services"
        },
        {
            "category":"Home & Garden",
            "subcategory":"Garden Supply",
            "type":"Retail Goods"
        }
    ],
    "sg:phone":"+1 360 225 7755",
    "sg:postcode":"98674",
    "sg:province":"WA",
    "sg:tags":[
        "water",
        "heavy"
    ],
    "sg:website":"www.ladybugfishandpond.com",
    "wof:name":"Lady Bug Fish & Pond",
    "wof:placetype":"venue"
},
  "geometry": {"coordinates":[-122.73475500000001,45.877455],"type":"Point"}
}