{
  "type": "Feature",
  "properties": {
    "addr:full":"800 5th Ave Ste 2600 Seattle WA 98104",
    "addr:housenumber":"800",
    "addr:postcode":"98104",
    "addr:street":"5Th Ave Ste 2600",
    "iso:country":"US",
    "sg:address":"800 5th Ave Ste 2600",
    "sg:city":"Seattle",
    "sg:classifiers":[
        {
            "category":"Landmark",
            "subcategory":"Tourist Information",
            "type":"Public Place"
        },
        {
            "category":"Landmark",
            "subcategory":"Tourist Attraction",
            "type":"Public Place"
        }
    ],
    "sg:phone":"+1 206 749 9312",
    "sg:postcode":"98104",
    "sg:province":"WA",
    "sg:tags":[
        "tour",
        "tours-operators",
        "promoter",
        "sightseeing"
    ],
    "wof:name":"Princess Tours",
    "wof:placetype":"venue"
},
  "geometry": {"coordinates":[-122.33049800000001,47.605129],"type":"Point"}
}