{
  "type": "Feature",
  "properties": {
    "addr:full":"5612 163rd St E Puyallup WA 98375",
    "addr:housenumber":"5612",
    "addr:postcode":"98375",
    "addr:street":"163Rd St E",
    "iso:country":"US",
    "sg:address":"5612 163rd St E",
    "sg:city":"Puyallup",
    "sg:classifiers":[
        {
            "category":"Professional",
            "subcategory":"Business Services",
            "type":"Services"
        }
    ],
    "sg:phone":"+1 253 539 4242",
    "sg:postcode":"98375",
    "sg:province":"WA",
    "sg:tags":[
        "liquidator"
    ],
    "wof:name":"E G Liquidation Specialists",
    "wof:placetype":"venue"
},
  "geometry": {"coordinates":[-122.35718300000001,47.107443],"type":"Point"}
}