{
  "type": "Feature",
  "properties": {
    "addr:full":"6309 NE St Johns Rd Vancouver WA 98661",
    "addr:housenumber":"6309",
    "addr:postcode":"98661",
    "addr:street":"Ne St Johns Rd",
    "iso:country":"US",
    "sg:address":"6309 NE St Johns Rd",
    "sg:city":"Vancouver",
    "sg:classifiers":[
        {
            "category":"Autos & Motor Vehicles",
            "subcategory":"Auto Supplies",
            "type":"Retail Goods"
        },
        {
            "category":"Manufacturing",
            "subcategory":"Glass & Minerals",
            "type":"Manufacturing & Wholesale Goods"
        },
        {
            "category":"Retail",
            "subcategory":"Auto Repair",
            "type":"Services"
        }
    ],
    "sg:phone":"+1 360 693 9956",
    "sg:postcode":"98661",
    "sg:province":"WA",
    "sg:tags":[
        "plate",
        "coating",
        "glass-auto",
        "tinting",
        "window",
        "windshield"
    ],
    "wof:name":"Renos Auto Glass",
    "wof:placetype":"venue"
},
  "geometry": {"coordinates":[-122.636471,45.666982],"type":"Point"}
}