{
  "type": "Feature",
  "properties": {
    "addr:full":"18305 Bellflower Rd Bothell WA 98012",
    "addr:housenumber":"18305",
    "addr:postcode":"98012",
    "addr:street":"Bellflower Rd",
    "iso:country":"US",
    "sg:address":"18305 Bellflower Rd",
    "sg:city":"Bothell",
    "sg:classifiers":[
        {
            "category":"Building & Trades",
            "subcategory":"Construction",
            "type":"Services"
        }
    ],
    "sg:phone":"+1 425 712 9014",
    "sg:postcode":"98012",
    "sg:province":"WA",
    "sg:tags":[
        "house"
    ],
    "wof:name":"Greenleaf Construction",
    "wof:placetype":"venue"
},
  "geometry": {"coordinates":[-122.231734,47.832247],"type":"Point"}
}