{
  "type": "Feature",
  "properties": {
    "addr:full":"19250 Aurora Ave N Seattle WA 98133",
    "addr:housenumber":"19250",
    "addr:postcode":"98133",
    "addr:street":"Aurora Ave N",
    "iso:country":"US",
    "sg:address":"19250 Aurora Ave N",
    "sg:city":"Seattle",
    "sg:classifiers":[
        {
            "category":"Building & Trades",
            "subcategory":"Construction",
            "type":"Services"
        }
    ],
    "sg:phone":"+1 206 542 4468",
    "sg:postcode":"98133",
    "sg:province":"WA",
    "wof:name":"Pave Master",
    "wof:placetype":"venue"
},
  "geometry": {"coordinates":[-122.345876,47.770064],"type":"Point"}
}