{
  "type": "Feature",
  "properties": {
    "addr:full":"17006 106th Ave SE Renton WA 98055",
    "addr:housenumber":"17006",
    "addr:postcode":"98055",
    "addr:street":"106Th Ave Se",
    "iso:country":"US",
    "sg:address":"17006 106th Ave SE",
    "sg:city":"Renton",
    "sg:classifiers":[
        {
            "category":"Professional",
            "subcategory":"Art Services",
            "type":"Services"
        }
    ],
    "sg:phone":"+1 425 271 6628",
    "sg:postcode":"98055",
    "sg:province":"WA",
    "sg:tags":[
        "commercial",
        "design"
    ],
    "wof:name":"Bina Designs",
    "wof:placetype":"venue"
},
  "geometry": {"coordinates":[-122.19942399999999,47.452174],"type":"Point"}
}