{
  "type": "Feature",
  "properties": {
    "addr:full":"12204 NE 124th Street Kirkland WA 98034",
    "addr:housenumber":"12204",
    "addr:postcode":"98034",
    "addr:street":"Ne 124Th Street",
    "iso:country":"US",
    "sg:address":"12204 NE 124th Street",
    "sg:city":"Kirkland",
    "sg:classifiers":[
        {
            "category":"Travel",
            "subcategory":"Hotels & Motels",
            "type":"Entertainment"
        }
    ],
    "sg:phone":"+1 425 821 8300",
    "sg:postcode":"98034",
    "sg:province":"WA",
    "sg:website":"www.choicehotels.com",
    "wof:name":"Comfort Inn",
    "wof:placetype":"venue"
},
  "geometry": {"coordinates":[-122.17794600000001,47.708938],"type":"Point"}
}