{
  "type": "Feature",
  "properties": {
    "addr:full":"835 Puget Dr E Port Orchard WA 98366",
    "addr:housenumber":"835",
    "addr:postcode":"98366",
    "addr:street":"Puget Dr E",
    "iso:country":"US",
    "sg:address":"835 Puget Dr E",
    "sg:city":"Port Orchard",
    "sg:classifiers":[
        {
            "category":"Retail",
            "subcategory":"Repair Shop",
            "type":"Services"
        }
    ],
    "sg:phone":"+1 360 871 5442",
    "sg:postcode":"98366",
    "sg:province":"WA",
    "wof:name":"Enviro Septic Design",
    "wof:placetype":"venue"
},
  "geometry": {"coordinates":[-122.546717,47.544211],"type":"Point"}
}