{
  "type": "Feature",
  "properties": {
    "addr:full":"3622 NE 6th St Renton WA 98056",
    "addr:housenumber":"3622",
    "addr:postcode":"98056",
    "addr:street":"Ne 6Th St",
    "iso:country":"US",
    "sg:address":"3622 NE 6th St",
    "sg:city":"Renton",
    "sg:classifiers":[
        {
            "category":"Professional",
            "subcategory":"Computer Services",
            "type":"Services"
        }
    ],
    "sg:phone":"+1 425 228 0113",
    "sg:postcode":"98056",
    "sg:province":"WA",
    "sg:tags":[
        "related"
    ],
    "wof:name":"Gmg Enterprises",
    "wof:placetype":"venue"
},
  "geometry": {"coordinates":[-122.170732,47.492271],"type":"Point"}
}