{
  "type": "Feature",
  "properties": {
    "addr:full":"21005 81st Ave Ct E Spanaway WA 98387",
    "addr:housenumber":"21005",
    "addr:postcode":"98387",
    "addr:street":"81St Ave Ct E",
    "iso:country":"US",
    "sg:address":"21005 81st Ave Ct E",
    "sg:city":"Spanaway",
    "sg:classifiers":[
        {
            "category":"Shopping",
            "subcategory":"Gifts & Souvenirs",
            "type":"Retail Goods"
        }
    ],
    "sg:phone":"+1 253 686 1341",
    "sg:postcode":"98387",
    "sg:province":"WA",
    "wof:name":"Cedar Hollow Creations",
    "wof:placetype":"venue"
},
  "geometry": {"coordinates":[-122.32168900000001,47.070635],"type":"Point"}
}