{
  "type": "Feature",
  "properties": {
    "addr:full":"6350 State Rte 104 Kingston WA 98346",
    "addr:housenumber":"6350",
    "addr:postcode":"98346",
    "addr:street":"State Rte 104",
    "iso:country":"US",
    "sg:address":"6350 State Rte 104",
    "sg:city":"Kingston",
    "sg:classifiers":[
        {
            "category":"Education",
            "subcategory":"Special Training",
            "type":"Public Place"
        }
    ],
    "sg:phone":"+1 360 297 2781",
    "sg:postcode":"98346",
    "sg:province":"WA",
    "wof:name":"Miller Bay Piano Studio",
    "wof:placetype":"venue"
},
  "geometry": {"coordinates":[-122.56604799999999,47.805194],"type":"Point"}
}