{
  "type": "Feature",
  "properties": {
    "addr:full":"4720 Center St Tacoma WA 98409",
    "addr:housenumber":"4720",
    "addr:postcode":"98409",
    "addr:street":"Center St",
    "iso:country":"US",
    "sg:address":"4720 Center St",
    "sg:city":"Tacoma",
    "sg:classifiers":[
        {
            "category":"Banks & Credit Unions",
            "subcategory":"Bank",
            "type":"Services"
        }
    ],
    "sg:phone":"+1 253 584 2260",
    "sg:postcode":"98409",
    "sg:province":"WA",
    "wof:name":"Harborstone Credit Union",
    "wof:placetype":"venue"
},
  "geometry": {"coordinates":[-122.499827,47.234299],"type":"Point"}
}