{
  "type": "Feature",
  "properties": {
    "iso:country":"US",
    "sg:address":"1708 S State St",
    "sg:city":"Tacoma",
    "sg:classifiers":[
        {
            "category":"Education",
            "subcategory":"Dance Studio",
            "type":"Public Place"
        }
    ],
    "sg:phone":"+1 253 565 1487",
    "sg:postcode":"98405",
    "sg:province":"WA",
    "sg:tags":[
        "instruction",
        "dancing"
    ],
    "wof:name":"Funtime Dance Studio",
    "wof:placetype":"venue"
},
  "geometry": {"coordinates":[-122.46564600000001,47.243847],"type":"Point"}
}