{
  "type": "Feature",
  "properties": {
    "addr:full":"2331 Franklin Ave E Seattle WA 98102",
    "addr:housenumber":"2331",
    "addr:postcode":"98102",
    "addr:street":"Franklin Ave E",
    "iso:country":"US",
    "sg:address":"2331 Franklin Ave E",
    "sg:city":"Seattle",
    "sg:classifiers":[
        {
            "category":"Retail",
            "subcategory":"Repair Shop",
            "type":"Services"
        }
    ],
    "sg:phone":"+1 206 324 4773",
    "sg:postcode":"98102",
    "sg:province":"WA",
    "wof:name":"Jack S Piano Service",
    "wof:placetype":"venue"
},
  "geometry": {"coordinates":[-122.324752,47.641678],"type":"Point"}
}