{
  "type": "Feature",
  "properties": {
    "addr:full":"1801 24th Ave S Seattle WA 98144",
    "addr:housenumber":"1801",
    "addr:postcode":"98144",
    "addr:street":"24Th Ave S",
    "iso:country":"US",
    "sg:address":"1801 24th Ave S",
    "sg:city":"Seattle",
    "sg:classifiers":[
        {
            "category":"Organizations",
            "subcategory":"Religious Organization",
            "type":"Services"
        }
    ],
    "sg:phone":"+1 206 323 5990",
    "sg:postcode":"98144",
    "sg:province":"WA",
    "sg:tags":[
        "place",
        "worship",
        "church"
    ],
    "sg:website":"http://www.jpresby.org",
    "wof:name":"Japanese Presbyterian Church",
    "wof:placetype":"venue"
},
  "geometry": {"coordinates":[-122.301598,47.58691],"type":"Point"}
}