{
  "type": "Feature",
  "properties": {
    "addr:full":"6700 NE 162nd Ave Vancouver WA 98682",
    "addr:housenumber":"6700",
    "addr:postcode":"98682",
    "addr:street":"Ne 162Nd Ave",
    "iso:country":"US",
    "sg:address":"6700 NE 162nd Ave",
    "sg:city":"Vancouver",
    "sg:classifiers":[
        {
            "category":"Home & Garden",
            "subcategory":"Carpets & Floor Coverings",
            "type":"Retail Goods"
        }
    ],
    "sg:phone":"+1 360 448 7770",
    "sg:postcode":"98682",
    "sg:province":"WA",
    "sg:tags":[
        "mattress"
    ],
    "wof:name":"Parklane Mattresses",
    "wof:placetype":"venue"
},
  "geometry": {"coordinates":[-122.505943,45.670767],"type":"Point"}
}