{
  "type": "Feature",
  "properties": {
    "addr:full":"9423 56th Ave W Mukilteo WA 98275",
    "addr:housenumber":"9423",
    "addr:postcode":"98275",
    "addr:street":"56Th Ave W",
    "iso:country":"US",
    "sg:address":"9423 56th Ave W",
    "sg:city":"Mukilteo",
    "sg:classifiers":[
        {
            "category":"Restaurant",
            "type":"Food & Drink"
        }
    ],
    "sg:phone":"+1 425 743 3654",
    "sg:postcode":"98275",
    "sg:province":"WA",
    "sg:tags":[
        "eating"
    ],
    "wof:name":"Ulis Famous Sausage LLC",
    "wof:placetype":"venue"
},
  "geometry": {"coordinates":[-122.30898500000001,47.912423],"type":"Point"}
}