{
  "type": "Feature",
  "properties": {
    "addr:full":"703 G St Washougal WA 98671",
    "addr:housenumber":"703",
    "addr:postcode":"98671",
    "addr:street":"G St",
    "iso:country":"US",
    "sg:address":"703 G St",
    "sg:city":"Washougal",
    "sg:classifiers":[
        {
            "category":"Freight",
            "type":"Transportation"
        }
    ],
    "sg:phone":"+1 360 835 5920",
    "sg:postcode":"98671",
    "sg:province":"WA",
    "sg:tags":[
        "commercial",
        "storage",
        "general"
    ],
    "wof:name":"6th Street Storage",
    "wof:placetype":"venue"
},
  "geometry": {"coordinates":[-122.36747099999999,45.58313],"type":"Point"}
}