{
  "type": "Feature",
  "properties": {
    "addr:full":"18723 E 2nd Ave Spokane Valley WA 99016",
    "addr:housenumber":"18723",
    "addr:postcode":"99016",
    "addr:street":"E 2Nd Ave",
    "iso:country":"US",
    "sg:address":"18723 E 2nd Ave",
    "sg:city":"Spokane Valley",
    "sg:classifiers":[
        {
            "category":"Wholesale",
            "subcategory":"Construction Materials",
            "type":"Manufacturing & Wholesale Goods"
        }
    ],
    "sg:phone":"+1 509 953 6951",
    "sg:postcode":"99016",
    "sg:province":"WA",
    "sg:tags":[
        "molding"
    ],
    "wof:name":"Creative Moldings",
    "wof:placetype":"venue"
},
  "geometry": {"coordinates":[-117.14712299999999,47.655132],"type":"Point"}
}