{
  "type": "Feature",
  "properties": {
    "addr:full":"1109 211th Pl NE Sammamish WA 98074",
    "addr:housenumber":"1109",
    "addr:postcode":"98074",
    "addr:street":"211Th Pl Ne",
    "iso:country":"US",
    "sg:address":"1109 211th Pl NE",
    "sg:city":"Sammamish",
    "sg:classifiers":[
        {
            "category":"Building & Trades",
            "subcategory":"Construction",
            "type":"Services"
        }
    ],
    "sg:phone":"+1 425 868 7641",
    "sg:postcode":"98074",
    "sg:province":"WA",
    "sg:tags":[
        "wallcoverings-installation",
        "wallpaper",
        "painting",
        "contractor"
    ],
    "wof:name":"Dexteriors Painting",
    "wof:placetype":"venue"
},
  "geometry": {"coordinates":[-122.058091,47.618528],"type":"Point"}
}