{
  "type": "Feature",
  "properties": {
    "addr:full":"221 W Heron St Aberdeen WA 98520",
    "addr:housenumber":"221",
    "addr:postcode":"98520",
    "addr:street":"W Heron St",
    "iso:country":"US",
    "sg:address":"221 W Heron St",
    "sg:city":"Aberdeen",
    "sg:classifiers":[
        {
            "category":"Coffee & Tea",
            "type":"Food & Drink"
        }
    ],
    "sg:menulink":"http://www.allmenus.com/wa/aberdeen-hoquiam/117705-starbucks-coffee/menu/",
    "sg:phone":"+1 360 533 1955",
    "sg:postcode":"98520",
    "sg:province":"WA",
    "sg:tags":[
        "american"
    ],
    "wof:name":"Starbucks Coffee",
    "wof:placetype":"venue"
},
  "geometry": {"coordinates":[-123.81850799999999,46.972717],"type":"Point"}
}