{
  "type": "Feature",
  "properties": {
    "addr:full":"600 Pine St Suite 235 Seattle WA 98101",
    "addr:housenumber":"600",
    "addr:postcode":"98101",
    "addr:street":"Pine St Suite 235",
    "iso:country":"US",
    "sg:address":"600 Pine St Suite 235",
    "sg:city":"Seattle",
    "sg:classifiers":[
        {
            "category":"Wholesale",
            "subcategory":"Electrical",
            "type":"Manufacturing & Wholesale Goods"
        },
        {
            "category":"Shopping",
            "subcategory":"Computers & Home Electronics",
            "type":"Retail Goods"
        },
        {
            "category":"Communications",
            "type":"Services"
        }
    ],
    "sg:phone":"+1 206 707 8986",
    "sg:postcode":"98101",
    "sg:province":"WA",
    "sg:tags":[
        "sound",
        "television",
        "theater",
        "equipment-wholesale",
        "stereo",
        "system",
        "high",
        "equipment",
        "stereophonic",
        "video",
        "equipment-dealers",
        "radio",
        "fidelity",
        "audio",
        "consumer",
        "store",
        "manufacturer"
    ],
    "sg:website":"http://seattle.citysearch.com/profile/external/11415962/seattle_wa/bose.html?publisher=yellowpages&reference_id=1&placement=ypwebsitemip",
    "wof:name":"Bose",
    "wof:placetype":"venue"
},
  "geometry": {"coordinates":[-122.33538799999999,47.612099],"type":"Point"}
}