{
  "type": "Feature",
  "properties": {
    "addr:full":"310 N 1st St La Conner WA 98257",
    "addr:housenumber":"310",
    "addr:postcode":"98257",
    "addr:street":"N 1St St",
    "iso:country":"US",
    "sg:address":"310 N 1st St",
    "sg:city":"La Conner",
    "sg:classifiers":[
        {
            "category":"Recreation",
            "type":"Entertainment"
        }
    ],
    "sg:phone":"+1 360 466 4902",
    "sg:postcode":"98257",
    "sg:province":"WA",
    "sg:tags":[
        "hall",
        "auditorium"
    ],
    "sg:website":"www.swinomishyachtclub.org",
    "wof:name":"Swinomish Yacht Club",
    "wof:placetype":"venue"
},
  "geometry": {"coordinates":[-122.49588300000001,48.392713],"type":"Point"}
}