{
  "type": "Feature",
  "properties": {
    "addr:full":"8301 Zangle Rd NE Olympia WA 98506",
    "addr:housenumber":"8301",
    "addr:postcode":"98506",
    "addr:street":"Zangle Rd Ne",
    "iso:country":"US",
    "sg:address":"8301 Zangle Rd NE",
    "sg:city":"Olympia",
    "sg:classifiers":[
        {
            "category":"Personal",
            "subcategory":"Beauty Salon",
            "type":"Services"
        }
    ],
    "sg:phone":"+1 360 352 1834",
    "sg:postcode":"98506",
    "sg:province":"WA",
    "sg:tags":[
        "shop"
    ],
    "wof:name":"Rick Martin Haircutter",
    "wof:placetype":"venue"
},
  "geometry": {"coordinates":[-122.878945,47.151164],"type":"Point"}
}