{
  "type": "Feature",
  "properties": {
    "addr:full":"836 NE Northgate Way Seattle WA 98125",
    "addr:housenumber":"836",
    "addr:postcode":"98125",
    "addr:street":"Ne Northgate Way",
    "iso:country":"US",
    "sg:address":"836 NE Northgate Way",
    "sg:city":"Seattle",
    "sg:classifiers":[
        {
            "category":"Health Services",
            "subcategory":"Doctor",
            "type":"Services"
        }
    ],
    "sg:phone":"+1 206 784 0737",
    "sg:postcode":"98125",
    "sg:province":"WA",
    "sg:website":"www.ushealthworks.com",
    "wof:name":"US Healthworks Medical Clinic",
    "wof:placetype":"venue"
},
  "geometry": {"coordinates":[-122.318944,47.708586],"type":"Point"}
}