{
  "type": "Feature",
  "properties": {
    "addr:full":"701 Sleater Kinney Rd SE Lacey WA 98503",
    "addr:housenumber":"701",
    "addr:postcode":"98503",
    "addr:street":"Sleater Kinney Rd Se",
    "iso:country":"US",
    "sg:address":"701 Sleater Kinney Rd SE",
    "sg:city":"Lacey",
    "sg:classifiers":[
        {
            "category":"Banks & Credit Unions",
            "subcategory":"Bank",
            "type":"Services"
        }
    ],
    "sg:phone":"+1 360 491 4430",
    "sg:postcode":"98503",
    "sg:province":"WA",
    "sg:tags":[
        "personal",
        "institution"
    ],
    "wof:name":"American General Finance Inc",
    "wof:placetype":"venue"
},
  "geometry": {"coordinates":[-122.833844,47.042349],"type":"Point"}
}