{
  "type": "Feature",
  "properties": {
    "addr:full":"600 N 85th St Ste C101 Seattle WA 98127",
    "addr:housenumber":"600",
    "addr:postcode":"98127",
    "addr:street":"N 85Th St Ste C101",
    "iso:country":"US",
    "sg:address":"600 N 85th St Ste C101",
    "sg:city":"Seattle",
    "sg:classifiers":[
        {
            "category":"Professional",
            "subcategory":"Lawyer & Legal Services",
            "type":"Services"
        }
    ],
    "sg:phone":"+1 206 347 0521",
    "sg:postcode":"98127",
    "sg:province":"WA",
    "sg:website":"www.divorce-washington.info",
    "wof:name":"Divorce Washington",
    "wof:placetype":"venue"
},
  "geometry": {"coordinates":[-122.35126099999999,47.690578],"type":"Point"}
}