{
  "type": "Feature",
  "properties": {
    "addr:full":"6716 E Side Dr NE Tacoma WA 98422",
    "addr:housenumber":"6716",
    "addr:postcode":"98422",
    "addr:street":"E Side Dr Ne",
    "iso:country":"US",
    "sg:address":"6716 E Side Dr NE",
    "sg:city":"Tacoma",
    "sg:classifiers":[
        {
            "category":"Personal",
            "subcategory":"Beauty Salon",
            "type":"Services"
        }
    ],
    "sg:phone":"+1 253 927 5461",
    "sg:postcode":"98422",
    "sg:province":"WA",
    "sg:tags":[
        "treatment",
        "skin"
    ],
    "wof:name":"Skin By Design",
    "wof:placetype":"venue"
},
  "geometry": {"coordinates":[-122.434619,47.30238],"type":"Point"}
}