{
  "type": "Feature",
  "properties": {
    "addr:full":"116 Slater St S Kirkland WA 98033",
    "addr:housenumber":"116",
    "addr:postcode":"98033",
    "addr:street":"Slater St S",
    "iso:country":"US",
    "sg:address":"116 Slater St S",
    "sg:city":"Kirkland",
    "sg:classifiers":[
        {
            "category":"Manufacturing",
            "subcategory":"Building Materials",
            "type":"Manufacturing & Wholesale Goods"
        }
    ],
    "sg:phone":"+1 425 820 5688",
    "sg:postcode":"98033",
    "sg:province":"WA",
    "sg:tags":[
        "hardware",
        "mfg"
    ],
    "wof:name":"Pcs Mill Work Inc",
    "wof:placetype":"venue"
},
  "geometry": {"coordinates":[-122.18846000000001,47.674103],"type":"Point"}
}