{
  "type": "Feature",
  "properties": {
    "addr:full":"3030 43rd Ave W Seattle WA 98199",
    "addr:housenumber":"3030",
    "addr:postcode":"98199",
    "addr:street":"43Rd Ave W",
    "iso:country":"US",
    "sg:address":"3030 43rd Ave W",
    "sg:city":"Seattle",
    "sg:classifiers":[
        {
            "category":"Professional",
            "subcategory":"Business Services",
            "type":"Services"
        }
    ],
    "sg:phone":"+1 206 542 9144",
    "sg:postcode":"98199",
    "sg:province":"WA",
    "sg:tags":[
        "mail",
        "shipping"
    ],
    "wof:name":"H & H Enterprises",
    "wof:placetype":"venue"
},
  "geometry": {"coordinates":[-122.411974,47.647015],"type":"Point"}
}