{
  "type": "Feature",
  "properties": {
    "iso:country":"US",
    "sg:address":"23427 20th Ave SE",
    "sg:city":"Bothell",
    "sg:classifiers":[
        {
            "category":"Professional",
            "subcategory":"Lawyer & Legal Services",
            "type":"Services"
        }
    ],
    "sg:phone":"+1 425 486 9413",
    "sg:postcode":"98021",
    "sg:province":"WA",
    "wof:name":"CF Enterprises LLC",
    "wof:placetype":"venue"
},
  "geometry": {"coordinates":[-122.204936,47.785505],"type":"Point"}
}