{
  "type": "Feature",
  "properties": {
    "addr:full":"2209 SW 356th St Federal Way WA 98023",
    "addr:housenumber":"2209",
    "addr:postcode":"98023",
    "addr:street":"Sw 356Th St",
    "iso:country":"US",
    "sg:address":"2209 SW 356th St",
    "sg:city":"Federal Way",
    "sg:classifiers":[
        {
            "category":"Professional",
            "subcategory":"Computer Services",
            "type":"Services"
        }
    ],
    "sg:phone":"+1 253 906 9987",
    "sg:postcode":"98023",
    "sg:province":"WA",
    "sg:tags":[
        "repair"
    ],
    "wof:name":"Rodney A Wray",
    "wof:placetype":"venue"
},
  "geometry": {"coordinates":[-122.362092,47.282646],"type":"Point"}
}