{
  "type": "Feature",
  "properties": {
    "addr:full":"9304 NE 14th Way Vancouver WA 98664",
    "addr:housenumber":"9304",
    "addr:postcode":"98664",
    "addr:street":"Ne 14Th Way",
    "iso:country":"US",
    "sg:address":"9304 NE 14th Way",
    "sg:city":"Vancouver",
    "sg:classifiers":[
        {
            "category":"Building & Trades",
            "subcategory":"Electrical",
            "type":"Services"
        }
    ],
    "sg:phone":"+1 360 256 0936",
    "sg:postcode":"98664",
    "sg:province":"WA",
    "sg:tags":[
        "electrical",
        "contractor"
    ],
    "wof:name":"Big Sky Electric Inc",
    "wof:placetype":"venue"
},
  "geometry": {"coordinates":[-122.57735099999999,45.631518],"type":"Point"}
}