{
  "type": "Feature",
  "properties": {
    "addr:full":"9330 15th Ave S Seattle WA 98108",
    "addr:housenumber":"9330",
    "addr:postcode":"98108",
    "addr:street":"15Th Ave S",
    "iso:country":"US",
    "sg:address":"9330 15th Ave S",
    "sg:city":"Seattle",
    "sg:classifiers":[
        {
            "category":"Manufacturing",
            "subcategory":"Metals",
            "type":"Manufacturing & Wholesale Goods"
        }
    ],
    "sg:phone":"+1 206 762 2707",
    "sg:postcode":"98108",
    "sg:province":"WA",
    "sg:tags":[
        "spinning",
        "stampings",
        "mfg"
    ],
    "wof:name":"Custom Metal Spinning LLC",
    "wof:placetype":"venue"
},
  "geometry": {"coordinates":[-122.313602,47.519182],"type":"Point"}
}