{
  "type": "Feature",
  "properties": {
    "iso:country":"US",
    "sg:address":"708 Burchett Rd",
    "sg:city":"Onalaska",
    "sg:classifiers":[
        {
            "category":"Building & Trades",
            "subcategory":"Construction",
            "type":"Services"
        }
    ],
    "sg:phone":"+1 360 985 7594",
    "sg:postcode":"98570",
    "sg:province":"WA",
    "wof:name":"Critz Building",
    "wof:placetype":"venue"
},
  "geometry": {"coordinates":[-122.660888,46.561012],"type":"Point"}
}