{
  "type": "Feature",
  "properties": {
    "addr:full":"1709 Bel-Aire Ave Aberdeen WA 98520",
    "addr:housenumber":"1709",
    "addr:postcode":"98520",
    "addr:street":"Bel-Aire Ave",
    "iso:country":"US",
    "sg:address":"1709 Bel-Aire Ave",
    "sg:city":"Aberdeen",
    "sg:classifiers":[
        {
            "category":"Professional",
            "subcategory":"Business Services",
            "type":"Services"
        }
    ],
    "sg:phone":"+1 360 538 1484",
    "sg:postcode":"98520",
    "sg:province":"WA",
    "wof:name":"Lynn Aue Sewing Services",
    "wof:placetype":"venue"
},
  "geometry": {"coordinates":[-123.827065,46.989814],"type":"Point"}
}