{
  "type": "Feature",
  "properties": {
    "addr:full":"1551 Center St Tacoma WA 98409",
    "addr:housenumber":"1551",
    "addr:postcode":"98409",
    "addr:street":"Center St",
    "iso:country":"US",
    "sg:address":"1551 Center St",
    "sg:city":"Tacoma",
    "sg:classifiers":[
        {
            "category":"Building & Trades",
            "subcategory":"Construction",
            "type":"Services"
        }
    ],
    "sg:phone":"+1 253 272 4643",
    "sg:postcode":"98409",
    "sg:province":"WA",
    "sg:tags":[
        "masonry",
        "contractor"
    ],
    "wof:name":"Artistic Stoneworks",
    "wof:placetype":"venue"
},
  "geometry": {"coordinates":[-122.45516000000001,47.233762],"type":"Point"}
}