{
  "type": "Feature",
  "properties": {
    "addr:full":"14005 35th Ave NE Seattle WA 98125",
    "addr:housenumber":"14005",
    "addr:postcode":"98125",
    "addr:street":"35Th Ave Ne",
    "iso:country":"US",
    "sg:address":"14005 35th Ave NE",
    "sg:city":"Seattle",
    "sg:classifiers":[
        {
            "category":"Restaurant",
            "type":"Food & Drink"
        }
    ],
    "sg:phone":"+1 206 272 9600",
    "sg:postcode":"98125",
    "sg:province":"WA",
    "sg:tags":[
        "eating"
    ],
    "wof:name":"Quiznos Subs",
    "wof:placetype":"venue"
},
  "geometry": {"coordinates":[-122.29112499999999,47.731893],"type":"Point"}
}