{
  "type": "Feature",
  "properties": {
    "addr:full":"8124 N Jefferson Dr Spokane WA 99208",
    "addr:housenumber":"8124",
    "addr:postcode":"99208",
    "addr:street":"N Jefferson Dr",
    "iso:country":"US",
    "sg:address":"8124 N Jefferson Dr",
    "sg:city":"Spokane",
    "sg:classifiers":[
        {
            "category":"Professional",
            "subcategory":"Employment Agencies",
            "type":"Services"
        }
    ],
    "sg:phone":"+1 509 466 8628",
    "sg:postcode":"99208",
    "sg:province":"WA",
    "sg:tags":[
        "help",
        "supply"
    ],
    "wof:name":"Aced Transcription",
    "wof:placetype":"venue"
},
  "geometry": {"coordinates":[-117.429169,47.728339],"type":"Point"}
}