{
  "type": "Feature",
  "properties": {
    "addr:full":"4502 Cherry Creek Rd Saint John WA 99171",
    "addr:housenumber":"4502",
    "addr:postcode":"wa 99171",
    "addr:street":"Cherry Creek Rd",
    "iso:country":"US",
    "sg:address":"4502 Cherry Creek Rd",
    "sg:city":"Saint John",
    "sg:phone":"+1 509 648 3424",
    "sg:postcode":"99171",
    "sg:province":"WA",
    "sg:tags":[
        "wheat",
        "barley",
        "beef",
        "cattle"
    ],
    "wof:name":"L M Farms Joint Venture",
    "wof:placetype":"venue"
},
  "geometry": {"coordinates":[-117.76147899999999,47.044246],"type":"Point"}
}