{
  "type": "Feature",
  "properties": {
    "addr:full":"205 N Main St Colville WA 99114",
    "addr:housenumber":"205",
    "addr:postcode":"99114",
    "addr:street":"N Main St",
    "iso:country":"US",
    "sg:address":"205 N Main St",
    "sg:city":"Colville",
    "sg:classifiers":[
        {
            "category":"Health Services",
            "subcategory":"Medical Lab",
            "type":"Services"
        }
    ],
    "sg:phone":"+1 509 684 8620",
    "sg:postcode":"99114",
    "sg:province":"WA",
    "sg:tags":[
        "laboratory",
        "dental"
    ],
    "wof:name":"Mc Elvain Dental Laboratory",
    "wof:placetype":"venue"
},
  "geometry": {"coordinates":[-117.905888,48.546511],"type":"Point"}
}