{
  "type": "Feature",
  "properties": {
    "addr:full":"207 W Charron Rd Moxee WA 98936",
    "addr:housenumber":"207",
    "addr:postcode":"98936",
    "addr:street":"W Charron Rd",
    "iso:country":"US",
    "sg:address":"207 W Charron Rd",
    "sg:city":"Moxee",
    "sg:classifiers":[
        {
            "category":"Manufacturing",
            "subcategory":"Tools & Machinery",
            "type":"Manufacturing & Wholesale Goods"
        }
    ],
    "sg:phone":"+1 509 575 6322",
    "sg:postcode":"98936",
    "sg:province":"WA",
    "sg:tags":[
        "power",
        "mechanical"
    ],
    "wof:name":"Moxee Innovations Corp",
    "wof:placetype":"venue"
},
  "geometry": {"coordinates":[-120.38678,46.556786],"type":"Point"}
}