{
  "type": "Feature",
  "properties": {
    "addr:full":"1325 F St Washougal WA 98671",
    "addr:housenumber":"1325",
    "addr:postcode":"98671",
    "addr:street":"F St",
    "iso:country":"US",
    "sg:address":"1325 F St",
    "sg:city":"Washougal",
    "sg:classifiers":[
        {
            "category":"Shopping",
            "subcategory":"Computers & Home Electronics",
            "type":"Retail Goods"
        }
    ],
    "sg:phone":"+1 360 835 2300",
    "sg:postcode":"98671",
    "sg:province":"WA",
    "sg:tags":[
        "department",
        "store"
    ],
    "wof:name":"Hunters Supply",
    "wof:placetype":"venue"
},
  "geometry": {"coordinates":[-122.357572,45.582066],"type":"Point"}
}