{
  "type": "Feature",
  "properties": {
    "addr:full":"19406 68th Dr NE Arlington WA 98223",
    "addr:housenumber":"19406",
    "addr:postcode":"98223",
    "addr:street":"68Th Dr Ne",
    "iso:country":"US",
    "sg:address":"19406 68th Dr NE",
    "sg:city":"Arlington",
    "sg:classifiers":[
        {
            "category":"Manufacturing",
            "subcategory":"Lumber",
            "type":"Manufacturing & Wholesale Goods"
        }
    ],
    "sg:phone":"+1 360 435 2175",
    "sg:postcode":"98223",
    "sg:province":"WA",
    "sg:tags":[
        "re",
        "mfg",
        "finger",
        "joint"
    ],
    "wof:name":"West Coast Forest Products",
    "wof:placetype":"venue"
},
  "geometry": {"coordinates":[-122.138893,48.170408],"type":"Point"}
}