{
  "type": "Feature",
  "properties": {
    "addr:full":"4860 Seafair Dr Blaine WA 98230",
    "addr:housenumber":"4860",
    "addr:postcode":"98230",
    "addr:street":"Seafair Dr",
    "iso:country":"US",
    "sg:address":"4860 Seafair Dr",
    "sg:city":"Blaine",
    "sg:classifiers":[
        {
            "category":"Professional",
            "subcategory":"Business Services",
            "type":"Services"
        }
    ],
    "sg:phone":"+1 360 371 2432",
    "sg:postcode":"98230",
    "sg:province":"WA",
    "wof:name":"Suzanne Eleanor Phillips",
    "wof:placetype":"venue"
},
  "geometry": {"coordinates":[-122.74597300000001,48.948262],"type":"Point"}
}