{
  "type": "Feature",
  "properties": {
    "addr:full":"2710 1st Ave S Seattle WA 98134",
    "addr:housenumber":"2710",
    "addr:postcode":"98134",
    "addr:street":"1St Ave S",
    "iso:country":"US",
    "sg:address":"2710 1st Ave S",
    "sg:city":"Seattle",
    "sg:classifiers":[
        {
            "category":"Shopping",
            "subcategory":"Clothing, Apparel, & Fashions",
            "type":"Retail Goods"
        }
    ],
    "sg:phone":"+1 206 262 4740",
    "sg:postcode":"98134",
    "sg:province":"WA",
    "sg:tags":[
        "t"
    ],
    "wof:name":"Compleat Sportswear Inc",
    "wof:placetype":"venue"
},
  "geometry": {"coordinates":[-122.334129,47.577831],"type":"Point"}
}