{
  "type": "Feature",
  "properties": {
    "addr:full":"1016 S 3rd St Mt Vernon WA 98273",
    "addr:housenumber":"1016",
    "addr:postcode":"98273",
    "addr:street":"S 3Rd St",
    "iso:country":"US",
    "sg:address":"1016 S 3rd St",
    "sg:city":"Mt Vernon",
    "sg:classifiers":[
        {
            "category":"Professional",
            "subcategory":"Accounting & Tax Preparation",
            "type":"Services"
        }
    ],
    "sg:phone":"+1 360 424 4000",
    "sg:postcode":"98273",
    "sg:province":"WA",
    "sg:tags":[
        "return",
        "filing"
    ],
    "wof:name":"Fiducial Fohn Spink",
    "wof:placetype":"venue"
},
  "geometry": {"coordinates":[-122.336579,48.415559],"type":"Point"}
}