{
  "type": "Feature",
  "properties": {
    "addr:full":"3403 Russet Rd Lynnwood WA 98036",
    "addr:housenumber":"3403",
    "addr:postcode":"98036",
    "addr:street":"Russet Rd",
    "iso:country":"US",
    "sg:address":"3403 Russet Rd",
    "sg:city":"Lynnwood",
    "sg:classifiers":[
        {
            "category":"Farming",
            "subcategory":"Nursery",
            "type":"Manufacturing & Wholesale Goods"
        }
    ],
    "sg:phone":"+1 425 775 0317",
    "sg:postcode":"98036",
    "sg:province":"WA",
    "sg:tags":[
        "ornamental"
    ],
    "wof:name":"Kerstons Nursery",
    "wof:placetype":"venue"
},
  "geometry": {"coordinates":[-122.277772,47.800654],"type":"Point"}
}