{
  "type": "Feature",
  "properties": {
    "addr:full":"824 12th Ave Seattle WA 98122",
    "addr:housenumber":"824",
    "addr:postcode":"98122",
    "addr:street":"12Th Ave",
    "iso:country":"US",
    "sg:address":"824 12th Ave",
    "sg:city":"Seattle",
    "sg:classifiers":[
        {
            "category":"Wholesale",
            "subcategory":"Home Furnishings",
            "type":"Manufacturing & Wholesale Goods"
        }
    ],
    "sg:phone":"+1 206 324 3379",
    "sg:postcode":"98122",
    "sg:province":"WA",
    "sg:tags":[
        "picture",
        "frame"
    ],
    "wof:name":"Plasteel Frames",
    "wof:placetype":"venue"
},
  "geometry": {"coordinates":[-122.316705,47.610106],"type":"Point"}
}