{
  "type": "Feature",
  "properties": {
    "iso:country":"US",
    "sg:address":"18615 110th Ave E",
    "sg:city":"Graham",
    "sg:classifiers":[
        {
            "category":"Sports & Exercise",
            "subcategory":"Golf",
            "type":"Entertainment"
        }
    ],
    "sg:phone":"+1 253 846 0926",
    "sg:postcode":"98338",
    "sg:province":"WA",
    "sg:tags":[
        "course"
    ],
    "wof:name":"Lipoma Firs Golf Course",
    "wof:placetype":"venue"
},
  "geometry": {"coordinates":[-122.284046,47.069351],"type":"Point"}
}