{
  "type": "Feature",
  "properties": {
    "addr:full":"19502 56th Ave W Lynnwood WA 98036",
    "addr:housenumber":"19502",
    "addr:postcode":"98036",
    "addr:street":"56Th Ave W",
    "iso:country":"US",
    "sg:address":"19502 56th Ave W",
    "sg:city":"Lynnwood",
    "sg:classifiers":[
        {
            "category":"Organizations",
            "subcategory":"Non-profit Organization",
            "type":"Services"
        }
    ],
    "sg:phone":"+1 425 672 8995",
    "sg:postcode":"98036",
    "sg:province":"WA",
    "sg:tags":[
        "social"
    ],
    "wof:name":"Community Spport Solutions Inc",
    "wof:placetype":"venue"
},
  "geometry": {"coordinates":[-122.308362,47.822246],"type":"Point"}
}