{
  "type": "Feature",
  "properties": {
    "addr:full":"7902 NE St Johns Rd Vancouver WA 98665",
    "addr:housenumber":"7902",
    "addr:postcode":"98665",
    "addr:street":"Ne St Johns Rd",
    "iso:country":"US",
    "sg:address":"7902 NE St Johns Rd",
    "sg:city":"Vancouver",
    "sg:classifiers":[
        {
            "category":"Professional",
            "subcategory":"Computer Services",
            "type":"Services"
        }
    ],
    "sg:phone":"+1 360 576 3576",
    "sg:postcode":"98665",
    "sg:province":"WA",
    "sg:tags":[
        "web",
        "design",
        "hosting",
        "site"
    ],
    "wof:name":"Nu Wave Health Inc",
    "wof:placetype":"venue"
},
  "geometry": {"coordinates":[-122.62560499999999,45.67911],"type":"Point"}
}