{
  "type": "Feature",
  "properties": {
    "addr:full":"3244 139th Ave SE Bellevue WA 98005",
    "addr:housenumber":"3244",
    "addr:postcode":"98005",
    "addr:street":"139Th Ave Se",
    "iso:country":"US",
    "sg:address":"3244 139th Ave SE",
    "sg:city":"Bellevue",
    "sg:classifiers":[
        {
            "category":"Travel",
            "subcategory":"Hotels & Motels",
            "type":"Entertainment"
        }
    ],
    "sg:phone":"+1 425 747 2705",
    "sg:postcode":"98005",
    "sg:province":"WA",
    "sg:website":"www.hotel-sierra.com",
    "wof:name":"Hotel Sierra Bellevue",
    "wof:placetype":"venue"
},
  "geometry": {"coordinates":[-122.15484499999999,47.581018],"type":"Point"}
}