{
  "type": "Feature",
  "properties": {
    "iso:country":"US",
    "sg:address":"4953 Elm St",
    "sg:city":"Everett",
    "sg:classifiers":[
        {
            "category":"Personal",
            "type":"Services"
        }
    ],
    "sg:phone":"+1 360 201 0177",
    "sg:postcode":"98203",
    "sg:province":"WA",
    "wof:name":"Seth L Patrick Lmt",
    "wof:placetype":"venue"
},
  "geometry": {"coordinates":[-122.232747,47.951903],"type":"Point"}
}