{
  "type": "Feature",
  "properties": {
    "addr:full":"4102 E Meridian Ave Puyallup WA 98373",
    "addr:housenumber":"4102",
    "addr:postcode":"98373",
    "addr:street":"E Meridian Ave",
    "iso:country":"US",
    "sg:address":"4102 E Meridian Ave",
    "sg:city":"Puyallup",
    "sg:classifiers":[
        {
            "category":"Personal",
            "type":"Services"
        }
    ],
    "sg:phone":"+1 253 435 8061",
    "sg:postcode":"98373",
    "sg:province":"WA",
    "sg:tags":[
        "wear",
        "formal"
    ],
    "sg:website":"www.menswarehouse.com",
    "wof:name":"Men's Wearhouse",
    "wof:placetype":"venue"
},
  "geometry": {"coordinates":[-122.29289,47.153029],"type":"Point"}
}