{
  "type": "Feature",
  "properties": {
    "addr:full":"1601 Lind Ave SW Fl 1 Renton WA 98057",
    "addr:housenumber":"1601;1",
    "addr:postcode":"98057",
    "addr:street":"Lind Ave Sw",
    "iso:country":"US",
    "sg:address":"1601 Lind Ave SW Fl 1",
    "sg:city":"Renton",
    "sg:classifiers":[
        {
            "category":"Travel",
            "subcategory":"Travel Agent",
            "type":"Entertainment"
        }
    ],
    "sg:phone":"+1 425 917 9800",
    "sg:postcode":"98057",
    "sg:province":"WA",
    "sg:tags":[
        "agency",
        "services-commercial"
    ],
    "wof:name":"World Wide Travel Service Inc",
    "wof:placetype":"venue"
},
  "geometry": {"coordinates":[-122.223349,47.465415],"type":"Point"}
}