{
  "type": "Feature",
  "properties": {
    "addr:full":"1140 140th Ave NE Bellevue WA 98005",
    "addr:housenumber":"1140",
    "addr:postcode":"98005",
    "addr:street":"140Th Ave Ne",
    "iso:country":"US",
    "sg:address":"1140 140th Ave NE",
    "sg:city":"Bellevue",
    "sg:classifiers":[
        {
            "category":"Building & Trades",
            "subcategory":"Construction",
            "type":"Services"
        }
    ],
    "sg:phone":"+1 425 746 6440",
    "sg:postcode":"98005",
    "sg:province":"WA",
    "sg:tags":[
        "general",
        "contractor"
    ],
    "wof:name":"Greycen Construction",
    "wof:placetype":"venue"
},
  "geometry": {"coordinates":[-122.153572,47.620633],"type":"Point"}
}