{
  "type": "Feature",
  "properties": {
    "addr:full":"12345 30th Ave NE Ste A Seattle WA 98125",
    "addr:housenumber":"12345",
    "addr:postcode":"98125",
    "addr:street":"30Th Ave Ne Ste A",
    "iso:country":"US",
    "sg:address":"12345 30th Ave NE Ste A",
    "sg:city":"Seattle",
    "sg:classifiers":[
        {
            "category":"Health Services",
            "subcategory":"Chiropractor",
            "type":"Services"
        }
    ],
    "sg:phone":"+1 206 227 5133",
    "sg:postcode":"98125",
    "sg:province":"WA",
    "sg:website":"www.chiropracticatthecenter.com",
    "wof:name":"Chiropractic At The Center",
    "wof:placetype":"venue"
},
  "geometry": {"coordinates":[-122.29677599999999,47.71871],"type":"Point"}
}