{
  "type": "Feature",
  "properties": {
    "addr:full":"12229 131st Pl NE Kirkland WA 98034",
    "addr:housenumber":"12229",
    "addr:postcode":"98034",
    "addr:street":"131St Pl Ne",
    "iso:country":"US",
    "sg:address":"12229 131st Pl NE",
    "sg:city":"Kirkland",
    "sg:classifiers":[
        {
            "category":"Real Estate",
            "subcategory":"Real Estate Operator",
            "type":"Services"
        }
    ],
    "sg:phone":"+1 425 820 2281",
    "sg:postcode":"98034",
    "sg:province":"WA",
    "sg:tags":[
        "apartment"
    ],
    "wof:name":"Cedar Heights Apartments",
    "wof:placetype":"venue"
},
  "geometry": {"coordinates":[-122.164001,47.709702],"type":"Point"}
}