{
  "type": "Feature",
  "properties": {
    "addr:full":"920 N Valley Mall Pkwy East Wenatchee WA 98802",
    "addr:housenumber":"920",
    "addr:postcode":"98802",
    "addr:street":"N Valley Mall Pkwy",
    "iso:country":"US",
    "sg:address":"920 N Valley Mall Pkwy",
    "sg:city":"East Wenatchee",
    "sg:classifiers":[
        {
            "category":"Building & Trades",
            "subcategory":"Construction",
            "type":"Services"
        }
    ],
    "sg:phone":"+1 509 669 9882",
    "sg:postcode":"98802",
    "sg:province":"WA",
    "sg:tags":[
        "hanging",
        "contractor"
    ],
    "wof:name":"Allstar Painting",
    "wof:placetype":"venue"
},
  "geometry": {"coordinates":[-120.29360699999999,47.416048],"type":"Point"}
}