{
  "type": "Feature",
  "properties": {
    "addr:full":"200 Auburn Ave Auburn WA 98002",
    "addr:housenumber":"200",
    "addr:postcode":"98002",
    "addr:street":"Auburn Ave",
    "iso:country":"US",
    "sg:address":"200 Auburn Ave",
    "sg:city":"Auburn",
    "sg:classifiers":[
        {
            "category":"Health Services",
            "subcategory":"Doctor",
            "type":"Services"
        },
        {
            "category":"Health Services",
            "subcategory":"Clinic",
            "type":"Services"
        }
    ],
    "sg:phone":"+1 253 833 1987",
    "sg:postcode":"98002",
    "sg:province":"WA",
    "sg:tags":[
        "physician",
        "surgeon",
        "osteopathic"
    ],
    "wof:name":"Auburn Federal Way Surgeons",
    "wof:placetype":"venue"
},
  "geometry": {"coordinates":[-122.227707,47.309143],"type":"Point"}
}