{
  "type": "Feature",
  "properties": {
    "addr:full":"8805 SE 40th St Mercer Island WA 98040",
    "addr:housenumber":"8805",
    "addr:postcode":"98040",
    "addr:street":"Se 40Th St",
    "iso:country":"US",
    "sg:address":"8805 SE 40th St",
    "sg:city":"Mercer Island",
    "sg:classifiers":[
        {
            "category":"Education",
            "subcategory":"Preschool",
            "type":"Public Place"
        },
        {
            "category":"Education",
            "subcategory":"School",
            "type":"Public Place"
        }
    ],
    "sg:phone":"+1 206 236 1380",
    "sg:postcode":"98040",
    "sg:province":"WA",
    "sg:tags":[
        "elementary"
    ],
    "wof:name":"Pixie Hill Preschool",
    "wof:placetype":"venue"
},
  "geometry": {"coordinates":[-122.220708,47.574551],"type":"Point"}
}