{
  "type": "Feature",
  "properties": {
    "addr:full":"2003 Western Ave Seattle WA 98121",
    "addr:housenumber":"2003",
    "addr:postcode":"98121",
    "addr:street":"Western Ave",
    "iso:country":"US",
    "sg:address":"2003 Western Ave",
    "sg:city":"Seattle",
    "sg:classifiers":[
        {
            "category":"Professional",
            "subcategory":"Engineering",
            "type":"Services"
        },
        {
            "category":"Professional",
            "subcategory":"Management & Consulting",
            "type":"Services"
        }
    ],
    "sg:phone":"+1 206 448 2123",
    "sg:postcode":"98121",
    "sg:province":"WA",
    "sg:tags":[
        "town",
        "city",
        "regional",
        "planner",
        "engineer"
    ],
    "wof:name":"Bucher Willis & Ratliff Corp",
    "wof:placetype":"venue"
},
  "geometry": {"coordinates":[-122.34437,47.610842],"type":"Point"}
}