{
  "type": "Feature",
  "properties": {
    "addr:full":"32061 Pacific Hwy S Federal Way WA 98003",
    "addr:housenumber":"32061",
    "addr:postcode":"98003",
    "addr:street":"Pacific Hwy S Federal Way",
    "iso:country":"US",
    "sg:address":"32061 Pacific Hwy S",
    "sg:city":"Federal Way",
    "sg:classifiers":[
        {
            "category":"Shopping",
            "subcategory":"Hobbies, Toys, & Games",
            "type":"Retail Goods"
        }
    ],
    "sg:phone":"+1 253 946 1191",
    "sg:postcode":"98003",
    "sg:province":"WA",
    "sg:tags":[
        "arts",
        "craft",
        "specialty"
    ],
    "wof:name":"Michaels 8900",
    "wof:placetype":"venue"
},
  "geometry": {"coordinates":[-122.31346600000001,47.314873],"type":"Point"}
}