{
  "type": "Feature",
  "properties": {
    "addr:full":"407 Fairview St SE Olympia WA 98501",
    "addr:housenumber":"407",
    "addr:postcode":"98501",
    "addr:street":"Fairview St Se",
    "iso:country":"US",
    "sg:address":"407 Fairview St SE",
    "sg:city":"Olympia",
    "sg:classifiers":[
        {
            "category":"Freight",
            "type":"Transportation"
        }
    ],
    "sg:phone":"+1 360 943 8313",
    "sg:postcode":"98501",
    "sg:province":"WA",
    "sg:tags":[
        "operator",
        "local",
        "trucking"
    ],
    "wof:name":"Black Cat Trucking",
    "wof:placetype":"venue"
},
  "geometry": {"coordinates":[-122.875688,47.045245],"type":"Point"}
}