{
  "type": "Feature",
  "properties": {
    "addr:full":"808 W Main Ave Ste 109 Spokane WA 99201",
    "addr:housenumber":"808",
    "addr:postcode":"99201",
    "addr:street":"W Main Ave Ste 109",
    "iso:country":"US",
    "sg:address":"808 W Main Ave Ste 109",
    "sg:city":"Spokane",
    "sg:classifiers":[
        {
            "category":"Shopping",
            "subcategory":"Clothing, Apparel, & Fashions",
            "type":"Retail Goods"
        }
    ],
    "sg:phone":"+1 509 455 9914",
    "sg:postcode":"99201",
    "sg:province":"WA",
    "sg:tags":[
        "apparel",
        "accessory",
        "women's"
    ],
    "sg:website":"http://www.anntaylor.com",
    "wof:name":"Ann Taylor",
    "wof:placetype":"venue"
},
  "geometry": {"coordinates":[-117.423647,47.659036],"type":"Point"}
}