{
  "type": "Feature",
  "properties": {
    "addr:full":"12707 30th Ave NE Seattle WA 98125",
    "addr:housenumber":"12707",
    "addr:postcode":"98125",
    "addr:street":"30Th Ave Ne",
    "iso:country":"US",
    "sg:address":"12707 30th Ave NE",
    "sg:city":"Seattle",
    "sg:classifiers":[
        {
            "category":"Government",
            "subcategory":"Office",
            "type":"Public Place"
        }
    ],
    "sg:phone":"+1 206 684 7526",
    "sg:postcode":"98125",
    "sg:province":"WA",
    "sg:tags":[
        "government-city",
        "government-united",
        "township",
        "state",
        "village"
    ],
    "sg:website":"http://www.seattlemonorail.com",
    "wof:name":"Neighborhood Svc Ctr",
    "wof:placetype":"venue"
},
  "geometry": {"coordinates":[-122.29631999999999,47.721199],"type":"Point"}
}