{
  "type": "Feature",
  "properties": {
    "addr:full":"615 W 11th St Vancouver WA 98660",
    "addr:housenumber":"615",
    "addr:postcode":"98660",
    "addr:street":"W 11Th St",
    "iso:country":"US",
    "sg:address":"615 W 11th St",
    "sg:city":"Vancouver",
    "sg:classifiers":[
        {
            "category":"Organizations",
            "subcategory":"Labor Organization",
            "type":"Services"
        }
    ],
    "sg:phone":"+1 360 694 7699",
    "sg:postcode":"98660",
    "sg:province":"WA",
    "sg:website":"http://www.uswa.org",
    "wof:name":"Uswa",
    "wof:placetype":"venue"
},
  "geometry": {"coordinates":[-122.67726999999999,45.629591],"type":"Point"}
}