{
  "type": "Feature",
  "properties": {
    "addr:full":"300 Kelso Dr Kelso WA 98626",
    "addr:housenumber":"300",
    "addr:postcode":"98626",
    "addr:street":"Kelso Dr",
    "iso:country":"US",
    "sg:address":"300 Kelso Dr",
    "sg:city":"Kelso",
    "sg:classifiers":[
        {
            "category":"Restaurant",
            "type":"Food & Drink"
        }
    ],
    "sg:menulink":"http://www.allmenus.com/wa/longview-kelso/212683-mcdonalds/menu/",
    "sg:phone":"+1 360 636 1340",
    "sg:postcode":"98626",
    "sg:province":"WA",
    "sg:tags":[
        "burger",
        "american"
    ],
    "wof:name":"McDonald's",
    "wof:placetype":"venue"
},
  "geometry": {"coordinates":[-122.89988700000001,46.151602],"type":"Point"}
}