{
  "type": "Feature",
  "properties": {
    "iso:country":"US",
    "sg:address":"1154 16th Ave E",
    "sg:city":"Seattle",
    "sg:classifiers":[
        {
            "category":"Communications",
            "subcategory":"Film & Video Production",
            "type":"Services"
        }
    ],
    "sg:phone":"+1 206 323 8761",
    "sg:postcode":"98112",
    "sg:province":"WA",
    "sg:tags":[
        "motion"
    ],
    "wof:name":"Michaels Video Production",
    "wof:placetype":"venue"
},
  "geometry": {"coordinates":[-122.31119099999999,47.628908],"type":"Point"}
}