{
  "type": "Feature",
  "properties": {
    "addr:full":"10837 Bill Point Bluff NE Bainbridge Island WA 98110",
    "addr:housenumber":"10837",
    "addr:postcode":"98110",
    "addr:street":"Bill Point Bluff Ne",
    "iso:country":"US",
    "sg:address":"10837 Bill Point Bluff NE",
    "sg:city":"Bainbridge Island",
    "sg:classifiers":[
        {
            "category":"Professional",
            "type":"Services"
        }
    ],
    "sg:phone":"+1 206 383 9468",
    "sg:postcode":"98110",
    "sg:province":"WA",
    "wof:name":"Westsound Professional Service",
    "wof:placetype":"venue"
},
  "geometry": {"coordinates":[-122.499996,47.610808],"type":"Point"}
}