{
  "type": "Feature",
  "properties": {
    "addr:full":"1959 NW Dock Pl Unit 2000 Seattle WA 98107",
    "addr:housenumber":"1959;unit 2000",
    "addr:postcode":"98107",
    "addr:street":"Nw Dock Pl",
    "iso:country":"US",
    "sg:address":"1959 NW Dock Pl Unit 2000",
    "sg:city":"Seattle",
    "sg:classifiers":[
        {
            "category":"Arts & Performance",
            "subcategory":"Arts Center",
            "type":"Entertainment"
        },
        {
            "category":"Military Area",
            "subcategory":"Naval Base",
            "type":"Public Place"
        }
    ],
    "sg:phone":"+1 206 285 9432",
    "sg:postcode":"98107",
    "sg:province":"WA",
    "sg:tags":[
        "surveyors-cargo",
        "surveyor",
        "marine"
    ],
    "wof:name":"Bowditch Marine, Inc.",
    "wof:placetype":"venue"
},
  "geometry": {"coordinates":[-122.381434,47.664175],"type":"Point"}
}