{
  "type": "Feature",
  "properties": {
    "addr:full":"8700 NE Vancouver Mall Dr Ste 120 Vancouver WA 98662",
    "addr:housenumber":"8700",
    "addr:postcode":"98662",
    "addr:street":"Ne Vancouver Mall Dr Ste 120",
    "iso:country":"US",
    "sg:address":"8700 NE Vancouver Mall Dr Ste 120",
    "sg:city":"Vancouver",
    "sg:classifiers":[
        {
            "category":"Coffee & Tea",
            "type":"Food & Drink"
        }
    ],
    "sg:phone":"+1 360 896 0640",
    "sg:postcode":"98662",
    "sg:province":"WA",
    "sg:website":"www.starbucks.com",
    "wof:name":"Starbucks",
    "wof:placetype":"venue"
},
  "geometry": {"coordinates":[-122.585678,45.656319],"type":"Point"}
}