{
  "type": "Feature",
  "properties": {
    "addr:full":"8675 SE 76th Pl Mercer Island WA 98040",
    "addr:housenumber":"8675",
    "addr:postcode":"98040",
    "addr:street":"Se 76Th Pl",
    "iso:country":"US",
    "sg:address":"8675 SE 76th Pl",
    "sg:city":"Mercer Island",
    "sg:classifiers":[
        {
            "category":"Professional",
            "subcategory":"Business Services",
            "type":"Services"
        }
    ],
    "sg:phone":"+1 206 236 7395",
    "sg:postcode":"98040",
    "sg:province":"WA",
    "wof:name":"Irene H Gallagher Business",
    "wof:placetype":"venue"
},
  "geometry": {"coordinates":[-122.223124,47.534099],"type":"Point"}
}