{
  "type": "Feature",
  "properties": {
    "addr:full":"720 Sleater Kinney Rd SE Lacey WA 98503",
    "addr:housenumber":"720",
    "addr:postcode":"98503",
    "addr:street":"Sleater Kinney Rd Se",
    "iso:country":"US",
    "sg:address":"720 Sleater Kinney Rd SE",
    "sg:city":"Lacey",
    "sg:classifiers":[
        {
            "category":"Restaurant",
            "type":"Food & Drink"
        }
    ],
    "sg:phone":"+1 360 491 3251",
    "sg:postcode":"98503",
    "sg:province":"WA",
    "sg:tags":[
        "delicatessen"
    ],
    "wof:name":"Oskar's German & European Deli",
    "wof:placetype":"venue"
},
  "geometry": {"coordinates":[-122.833692,47.042596],"type":"Point"}
}