{
  "type": "Feature",
  "properties": {
    "addr:full":"121 Alder St SW Ephrata WA 98823",
    "addr:housenumber":"121",
    "addr:postcode":"98823",
    "addr:street":"Alder St Sw",
    "iso:country":"US",
    "sg:address":"121 Alder St SW",
    "sg:city":"Ephrata",
    "sg:classifiers":[
        {
            "category":"Government",
            "subcategory":"Office",
            "type":"Public Place"
        }
    ],
    "sg:phone":"+1 509 754 4601",
    "sg:postcode":"98823",
    "sg:province":"WA",
    "sg:tags":[
        "legislative",
        "body"
    ],
    "wof:name":"City of Ephrata",
    "wof:placetype":"venue"
},
  "geometry": {"coordinates":[-119.551153,47.318997],"type":"Point"}
}