{
  "type": "Feature",
  "properties": {
    "addr:full":"409 E D St Granger WA 98932",
    "addr:housenumber":"409",
    "addr:postcode":"98932",
    "addr:street":"E D St",
    "iso:country":"US",
    "sg:address":"409 E D St",
    "sg:city":"Granger",
    "sg:classifiers":[
        {
            "category":"Real Estate",
            "subcategory":"Real Estate Operator",
            "type":"Services"
        }
    ],
    "sg:phone":"+1 509 854 2200",
    "sg:postcode":"98932",
    "sg:province":"WA",
    "sg:tags":[
        "building",
        "apartment"
    ],
    "wof:name":"San Isidoro Plaza",
    "wof:placetype":"venue"
},
  "geometry": {"coordinates":[-120.18929,46.338579],"type":"Point"}
}