{
  "type": "Feature",
  "properties": {
    "addr:full":"39407 NE 216th Ave Amboy WA 98601",
    "addr:housenumber":"39407",
    "addr:postcode":"98601",
    "addr:street":"Ne 216Th Ave",
    "iso:country":"US",
    "sg:address":"39407 NE 216th Ave",
    "sg:city":"Amboy",
    "sg:classifiers":[
        {
            "category":"Organizations",
            "subcategory":"Religious Organization",
            "type":"Services"
        }
    ],
    "sg:phone":"+1 360 247 5189",
    "sg:postcode":"98601",
    "sg:province":"WA",
    "sg:tags":[
        "church"
    ],
    "wof:name":"Amboy Seventh Day Adventist",
    "wof:placetype":"venue"
},
  "geometry": {"coordinates":[-122.448956,45.907562],"type":"Point"}
}