{
  "type": "Feature",
  "properties": {
    "addr:full":"1919 Yelm Hwy SE Olympia WA 98501",
    "addr:housenumber":"1919",
    "addr:postcode":"98501",
    "addr:street":"Yelm Hwy Se",
    "iso:country":"US",
    "sg:address":"1919 Yelm Hwy SE",
    "sg:city":"Olympia",
    "sg:classifiers":[
        {
            "category":"Manufacturing",
            "subcategory":"Lumber",
            "type":"Manufacturing & Wholesale Goods"
        }
    ],
    "sg:phone":"+1 360 943 1723",
    "sg:postcode":"98501",
    "sg:province":"WA",
    "sg:tags":[
        "forestry",
        "consulting"
    ],
    "wof:name":"Washington Forestry Cons",
    "wof:placetype":"venue"
},
  "geometry": {"coordinates":[-122.87367,47.0035],"type":"Point"}
}