{
  "type": "Feature",
  "properties": {
    "addr:full":"203 W Alder St Walla Walla WA 99362",
    "addr:housenumber":"203",
    "addr:postcode":"99362",
    "addr:street":"W Alder St",
    "iso:country":"US",
    "sg:address":"203 W Alder St",
    "sg:city":"Walla Walla",
    "sg:classifiers":[
        {
            "category":"Shopping",
            "subcategory":"Used Merchandise",
            "type":"Retail Goods"
        },
        {
            "category":"Shopping",
            "subcategory":"Jewelry",
            "type":"Retail Goods"
        }
    ],
    "sg:phone":"+1 509 525 7001",
    "sg:postcode":"99362",
    "sg:province":"WA",
    "sg:tags":[
        "shop",
        "pawnbroker",
        "pawn"
    ],
    "wof:name":"H & H Sports and Loan",
    "wof:placetype":"venue"
},
  "geometry": {"coordinates":[-118.34124300000001,46.064747],"type":"Point"}
}