{
  "type": "Feature",
  "properties": {
    "addr:full":"16116 Vancil Loop SE Yelm WA 98597",
    "addr:housenumber":"16116",
    "addr:postcode":"98597",
    "addr:street":"Vancil Loop Se",
    "iso:country":"US",
    "sg:address":"16116 Vancil Loop SE",
    "sg:city":"Yelm",
    "sg:classifiers":[
        {
            "category":"Professional",
            "subcategory":"Business Services",
            "type":"Services"
        }
    ],
    "sg:phone":"+1 360 458 4968",
    "sg:postcode":"98597",
    "sg:province":"WA",
    "wof:name":"Luciano Aquisitions LLC",
    "wof:placetype":"venue"
},
  "geometry": {"coordinates":[-122.597494,46.933689],"type":"Point"}
}