{
  "type": "Feature",
  "properties": {
    "addr:full":"4036 E Madison Street Seattle WA 98112",
    "addr:housenumber":"4036",
    "addr:postcode":"98112",
    "addr:street":"E Madison Street",
    "iso:country":"US",
    "sg:address":"4036 E Madison Street",
    "sg:city":"Seattle",
    "sg:classifiers":[
        {
            "category":"Coffee & Tea",
            "type":"Food & Drink"
        }
    ],
    "sg:phone":"+1 206 329 6659",
    "sg:postcode":"98112",
    "sg:province":"WA",
    "wof:name":"Tully's Coffee",
    "wof:placetype":"venue"
},
  "geometry": {"coordinates":[-122.280067,47.634258],"type":"Point"}
}