{
  "type": "Feature",
  "properties": {
    "addr:full":"633 4th Ave S Okanogan WA 98840",
    "addr:housenumber":"633",
    "addr:postcode":"98840",
    "addr:street":"4Th Ave S Okanogan",
    "iso:country":"US",
    "sg:address":"633 4th Ave S",
    "sg:city":"Okanogan",
    "sg:classifiers":[
        {
            "category":"Real Estate",
            "subcategory":"Real Estate Operator",
            "type":"Services"
        }
    ],
    "sg:phone":"+1 509 422 5608",
    "sg:postcode":"98840",
    "sg:province":"WA",
    "sg:tags":[
        "building",
        "apartment"
    ],
    "wof:name":"United Marketing",
    "wof:placetype":"venue"
},
  "geometry": {"coordinates":[-119.58667800000001,48.361691],"type":"Point"}
}