{
  "type": "Feature",
  "properties": {
    "iso:country":"US",
    "sg:address":"8061 22nd Ave NW",
    "sg:city":"Seattle",
    "sg:classifiers":[
        {
            "category":"Professional",
            "type":"Services"
        }
    ],
    "sg:phone":"+1 206 270 9311",
    "sg:postcode":"98117",
    "sg:province":"WA",
    "sg:tags":[
        "establishment"
    ],
    "wof:name":"ABI",
    "wof:placetype":"venue"
},
  "geometry": {"coordinates":[-122.384412,47.688325],"type":"Point"}
}