{
  "type": "Feature",
  "properties": {
    "addr:full":"1014 4th Ave E Olympia WA 98506",
    "addr:housenumber":"1014",
    "addr:postcode":"98506",
    "addr:street":"4Th Ave E",
    "iso:country":"US",
    "sg:address":"1014 4th Ave E",
    "sg:city":"Olympia",
    "sg:classifiers":[
        {
            "category":"Health Services",
            "subcategory":"Clinic",
            "type":"Services"
        }
    ],
    "sg:phone":"+1 360 352 4868",
    "sg:postcode":"98506",
    "sg:province":"WA",
    "sg:tags":[
        "childbirth",
        "education"
    ],
    "wof:name":"Mary Sheridan Foundation",
    "wof:placetype":"venue"
},
  "geometry": {"coordinates":[-122.888683,47.045849],"type":"Point"}
}