{
  "type": "Feature",
  "properties": {
    "addr:full":"1603 Broadmoor Dr E Seattle WA 98112",
    "addr:housenumber":"1603",
    "addr:postcode":"98112",
    "addr:street":"Broadmoor Dr E",
    "iso:country":"US",
    "sg:address":"1603 Broadmoor Dr E",
    "sg:city":"Seattle",
    "sg:classifiers":[
        {
            "category":"Real Estate",
            "subcategory":"Real Estate Operator",
            "type":"Services"
        }
    ],
    "sg:phone":"+1 206 623 8930",
    "sg:postcode":"98112",
    "sg:province":"WA",
    "sg:tags":[
        "building",
        "apartment"
    ],
    "wof:name":"Bayview Village Apartments",
    "wof:placetype":"venue"
},
  "geometry": {"coordinates":[-122.28835100000001,47.632272],"type":"Point"}
}