{
  "type": "Feature",
  "properties": {
    "addr:full":"39308 SE Nichols Hill Rd Washougal WA 98671",
    "addr:housenumber":"39308",
    "addr:postcode":"98671",
    "addr:street":"Se Nichols Hill Rd",
    "iso:country":"US",
    "sg:address":"39308 SE Nichols Hill Rd",
    "sg:city":"Washougal",
    "sg:classifiers":[
        {
            "category":"Freight",
            "type":"Transportation"
        }
    ],
    "sg:phone":"+1 360 835 2460",
    "sg:postcode":"98671",
    "sg:province":"WA",
    "sg:tags":[
        "operator",
        "local",
        "trucking"
    ],
    "wof:name":"HI Tech Movers Inc",
    "wof:placetype":"venue"
},
  "geometry": {"coordinates":[-122.27954099999999,45.605033],"type":"Point"}
}