{
  "type": "Feature",
  "properties": {
    "addr:full":"3018 S Grand Blvd Spokane WA 99203",
    "addr:housenumber":"3018",
    "addr:postcode":"99203",
    "addr:street":"S Grand Blvd",
    "iso:country":"US",
    "sg:address":"3018 S Grand Blvd",
    "sg:city":"Spokane",
    "sg:classifiers":[
        {
            "category":"Personal",
            "subcategory":"Beauty Salon",
            "type":"Services"
        }
    ],
    "sg:phone":"+1 509 456 3726",
    "sg:postcode":"99203",
    "sg:province":"WA",
    "sg:tags":[
        "nail",
        "shop",
        "manicuring"
    ],
    "wof:name":"Famous Nails 2",
    "wof:placetype":"venue"
},
  "geometry": {"coordinates":[-117.401804,47.627095],"type":"Point"}
}