{
  "type": "Feature",
  "properties": {
    "addr:full":"20323 100th Ave SE Kent WA 98031",
    "addr:housenumber":"20323",
    "addr:postcode":"98031",
    "addr:street":"100Th Ave Se",
    "iso:country":"US",
    "sg:address":"20323 100th Ave SE",
    "sg:city":"Kent",
    "sg:classifiers":[
        {
            "category":"Retail",
            "subcategory":"Car Wash",
            "type":"Services"
        }
    ],
    "sg:phone":"+1 253 872 0410",
    "sg:postcode":"98031",
    "sg:province":"WA",
    "wof:name":"Atheletic Repair Eqp Wash",
    "wof:placetype":"venue"
},
  "geometry": {"coordinates":[-122.207476,47.420163],"type":"Point"}
}