{
  "type": "Feature",
  "properties": {
    "addr:full":"5008 Point Ct SE Olympia WA 98513",
    "addr:housenumber":"5008",
    "addr:postcode":"98513",
    "addr:street":"Point Ct Se",
    "iso:country":"US",
    "sg:address":"5008 Point Ct SE",
    "sg:city":"Olympia",
    "sg:classifiers":[
        {
            "category":"Professional",
            "subcategory":"Lawyer & Legal Services",
            "type":"Services"
        }
    ],
    "sg:phone":"+1 360 352 4780",
    "sg:postcode":"98513",
    "sg:province":"WA",
    "sg:tags":[
        "plan"
    ],
    "wof:name":"Benjamin & Healy P",
    "wof:placetype":"venue"
},
  "geometry": {"coordinates":[-122.78003,47.002781],"type":"Point"}
}