{
  "type": "Feature",
  "properties": {
    "addr:full":"11019 SE 27th Pl Bellevue WA 98004",
    "addr:housenumber":"11019",
    "addr:postcode":"98004",
    "addr:street":"Se 27Th Pl",
    "iso:country":"US",
    "sg:address":"11019 SE 27th Pl",
    "sg:city":"Bellevue",
    "sg:classifiers":[
        {
            "category":"Manufacturing",
            "subcategory":"Jewelry",
            "type":"Manufacturing & Wholesale Goods"
        }
    ],
    "sg:phone":"+1 425 453 9406",
    "sg:postcode":"98004",
    "sg:province":"WA",
    "sg:tags":[
        "stone",
        "manufacturer",
        "jewelers-wholesale",
        "jewels-imitation"
    ],
    "wof:name":"Ellendee Co",
    "wof:placetype":"venue"
},
  "geometry": {"coordinates":[-122.19368900000001,47.586081],"type":"Point"}
}