{
  "type": "Feature",
  "properties": {
    "addr:full":"1311 Central Ave S Kent WA 98032",
    "addr:housenumber":"1311",
    "addr:postcode":"98032",
    "addr:street":"Central Ave S",
    "iso:country":"US",
    "sg:address":"1311 Central Ave S",
    "sg:city":"Kent",
    "sg:classifiers":[
        {
            "category":"Professional",
            "subcategory":"Management & Consulting",
            "type":"Services"
        },
        {
            "category":"Wholesale",
            "subcategory":"Machinery & Supplies",
            "type":"Manufacturing & Wholesale Goods"
        }
    ],
    "sg:phone":"+1 253 854 9954",
    "sg:postcode":"98032",
    "sg:province":"WA",
    "sg:tags":[
        "industrial",
        "equipment",
        "science",
        "academic",
        "consultant"
    ],
    "wof:name":"Balance Dynamics Inc",
    "wof:placetype":"venue"
},
  "geometry": {"coordinates":[-122.229949,47.367993],"type":"Point"}
}