{
  "type": "Feature",
  "properties": {
    "addr:full":"8815 20th Avenue SW Seattle WA 98106",
    "addr:housenumber":"8815",
    "addr:postcode":"98106",
    "addr:street":"20Th Avenue Sw",
    "iso:country":"US",
    "sg:address":"8815 20th Avenue SW",
    "sg:city":"Seattle",
    "sg:classifiers":[
        {
            "category":"Banks & Credit Unions",
            "subcategory":"Financial Services",
            "type":"Services"
        }
    ],
    "sg:phone":"+1 206 767 9797",
    "sg:postcode":"98106",
    "sg:province":"WA",
    "sg:tags":[
        "broker",
        "mortgage"
    ],
    "wof:name":"United Mortgage",
    "wof:placetype":"venue"
},
  "geometry": {"coordinates":[-122.358959,47.523996],"type":"Point"}
}