{
  "type": "Feature",
  "properties": {
    "iso:country":"US",
    "sg:address":"2907 NW 85th St",
    "sg:city":"Seattle",
    "sg:classifiers":[
        {
            "category":"Freight",
            "type":"Transportation"
        }
    ],
    "sg:phone":"+1 206 783 2850",
    "sg:postcode":"98117",
    "sg:province":"WA",
    "sg:tags":[
        "operator",
        "local",
        "trucking"
    ],
    "wof:name":"Action Delivery Service",
    "wof:placetype":"venue"
},
  "geometry": {"coordinates":[-122.395698,47.690494],"type":"Point"}
}