{
  "type": "Feature",
  "properties": {
    "iso:country":"US",
    "sg:address":"115 W Magnolia St",
    "sg:city":"Bellingham",
    "sg:classifiers":[
        {
            "category":"Social Services",
            "type":"Services"
        }
    ],
    "sg:phone":"+1 360 734 6939",
    "sg:postcode":"98225",
    "sg:province":"WA",
    "wof:name":"Sharon OConnell MA Ccdcii",
    "wof:placetype":"venue"
},
  "geometry": {"coordinates":[-122.47864300000001,48.751282],"type":"Point"}
}