{
  "type": "Feature",
  "properties": {
    "addr:full":"9102 12th Ave NE Seattle WA 98115",
    "addr:housenumber":"9102",
    "addr:postcode":"98115",
    "addr:street":"12Th Ave Ne",
    "iso:country":"US",
    "sg:address":"9102 12th Ave NE",
    "sg:city":"Seattle",
    "sg:classifiers":[
        {
            "category":"Professional",
            "subcategory":"Management & Consulting",
            "type":"Services"
        }
    ],
    "sg:phone":"+1 206 522 5574",
    "sg:postcode":"98115",
    "sg:province":"WA",
    "sg:tags":[
        "consultant",
        "restaurant"
    ],
    "wof:name":"Restaurant Solutions",
    "wof:placetype":"venue"
},
  "geometry": {"coordinates":[-122.31485000000001,47.694919],"type":"Point"}
}