{
  "type": "Feature",
  "properties": {
    "addr:full":"2700 E Lake Sammamish Pkwy SE Sammamish WA 98075",
    "addr:housenumber":"2700",
    "addr:postcode":"98075",
    "addr:street":"E Lake Sammamish Pkwy Se",
    "iso:country":"US",
    "sg:address":"2700 E Lake Sammamish Pkwy SE",
    "sg:city":"Sammamish",
    "sg:classifiers":[
        {
            "category":"Airline",
            "type":"Transportation"
        },
        {
            "category":"Travel",
            "subcategory":"Travel Agent",
            "type":"Entertainment"
        }
    ],
    "sg:phone":"+1 425 677 7278",
    "sg:postcode":"98075",
    "sg:province":"WA",
    "sg:tags":[
        "ticket",
        "agency"
    ],
    "wof:name":"Sunfolk Group",
    "wof:placetype":"venue"
},
  "geometry": {"coordinates":[-122.08247299999999,47.585326],"type":"Point"}
}