{
  "type": "Feature",
  "properties": {
    "addr:full":"515 Summit Lake Shore Rd NW Olympia WA 98502",
    "addr:housenumber":"515",
    "addr:postcode":"olympia wa 98502",
    "addr:street":"Summit Lake Shore Rd Nw",
    "iso:country":"US",
    "sg:address":"515 Summit Lake Shore Rd NW",
    "sg:city":"Olympia",
    "sg:classifiers":[
        {
            "category":"Shopping",
            "type":"Retail Goods"
        }
    ],
    "sg:phone":"+1 360 866 7739",
    "sg:postcode":"98502",
    "sg:province":"WA",
    "sg:tags":[
        "water",
        "equipment",
        "pump",
        "purification"
    ],
    "wof:name":"Strong Don Pump Sales & Svc",
    "wof:placetype":"venue"
},
  "geometry": {"coordinates":[-123.115576,47.047847],"type":"Point"}
}