{
  "type": "Feature",
  "properties": {
    "addr:full":"15203 NE 95th St Redmond WA 98052",
    "addr:housenumber":"15203",
    "addr:postcode":"98052",
    "addr:street":"Ne 95Th St",
    "iso:country":"US",
    "sg:address":"15203 NE 95th St",
    "sg:city":"Redmond",
    "sg:classifiers":[
        {
            "category":"Building & Trades",
            "subcategory":"Construction",
            "type":"Services"
        }
    ],
    "sg:phone":"+1 425 881 9771",
    "sg:postcode":"98052",
    "sg:province":"WA",
    "sg:tags":[
        "roofing"
    ],
    "sg:website":"www.larryhaight.com",
    "wof:name":"Larry Haight's Residential Roofing Company",
    "wof:placetype":"venue"
},
  "geometry": {"coordinates":[-122.13718,47.685459],"type":"Point"}
}