{
  "type": "Feature",
  "properties": {
    "addr:full":"711 N Stratford Rd Moses Lake WA 98837",
    "addr:housenumber":"711",
    "addr:postcode":"98837",
    "addr:street":"N Stratford Rd",
    "iso:country":"US",
    "sg:address":"711 N Stratford Rd",
    "sg:city":"Moses Lake",
    "sg:classifiers":[
        {
            "category":"Shopping",
            "subcategory":"Crafts & Fabrics",
            "type":"Retail Goods"
        }
    ],
    "sg:phone":"+1 509 764 4706",
    "sg:postcode":"98837",
    "sg:province":"WA",
    "sg:tags":[
        "shop",
        "sewing"
    ],
    "wof:name":"Country Fabrics",
    "wof:placetype":"venue"
},
  "geometry": {"coordinates":[-119.278243,47.141953],"type":"Point"}
}