{
  "type": "Feature",
  "properties": {
    "addr:full":"1509 Bonneville Ave Everett WA 98290",
    "addr:housenumber":"1509",
    "addr:postcode":"98290",
    "addr:street":"Bonneville Ave",
    "iso:country":"US",
    "sg:address":"1509 Bonneville Ave",
    "sg:city":"Everett",
    "sg:classifiers":[
        {
            "category":"Building & Trades",
            "subcategory":"Construction",
            "type":"Services"
        }
    ],
    "sg:phone":"+1 425 290 7827",
    "sg:postcode":"98290",
    "sg:province":"WA",
    "sg:tags":[
        "downspouts",
        "gutter"
    ],
    "wof:name":"Puget Gutters",
    "wof:placetype":"venue"
},
  "geometry": {"coordinates":[-122.102373,47.929528],"type":"Point"}
}