{
  "type": "Feature",
  "properties": {
    "addr:full":"2525 103rd Ave SE Everett WA 98205",
    "addr:housenumber":"2525",
    "addr:postcode":"98205",
    "addr:street":"103Rd Ave Se",
    "iso:country":"US",
    "sg:address":"2525 103rd Ave SE",
    "sg:city":"Everett",
    "sg:classifiers":[
        {
            "category":"Retail",
            "subcategory":"Repair Shop",
            "type":"Services"
        }
    ],
    "sg:phone":"+1 425 335 0974",
    "sg:postcode":"98205",
    "sg:province":"WA",
    "wof:name":"Deishers Custom Upholstery",
    "wof:placetype":"venue"
},
  "geometry": {"coordinates":[-122.093035,47.973658],"type":"Point"}
}