{
  "type": "Feature",
  "properties": {
    "addr:full":"801 Northern Pacific Rd SE Yelm WA 98597",
    "addr:housenumber":"801",
    "addr:postcode":"98597",
    "addr:street":"Northern Pacific Rd Se Yelm",
    "iso:country":"US",
    "sg:address":"801 Northern Pacific Rd SE",
    "sg:city":"Yelm",
    "sg:classifiers":[
        {
            "category":"Retail",
            "subcategory":"Auto Rental",
            "type":"Services"
        }
    ],
    "sg:phone":"+1 360 458 8589",
    "sg:postcode":"98597",
    "sg:province":"WA",
    "sg:tags":[
        "renting",
        "truck",
        "leasing"
    ],
    "wof:name":"Penske Truck Leasing",
    "wof:placetype":"venue"
},
  "geometry": {"coordinates":[-122.589817,46.952075],"type":"Point"}
}