{
  "type": "Feature",
  "properties": {
    "addr:full":"404 1st St SE East Wenatchee WA 98802",
    "addr:housenumber":"404",
    "addr:postcode":"98802",
    "addr:street":"1St St Se",
    "iso:country":"US",
    "sg:address":"404 1st St SE",
    "sg:city":"East Wenatchee",
    "sg:classifiers":[
        {
            "category":"Shopping",
            "subcategory":"Computers & Home Electronics",
            "type":"Retail Goods"
        }
    ],
    "sg:phone":"+1 360 458 2551",
    "sg:postcode":"98802",
    "sg:province":"WA",
    "sg:tags":[
        "equipment",
        "dealer"
    ],
    "wof:name":"Yelm Marin Computer",
    "wof:placetype":"venue"
},
  "geometry": {"coordinates":[-120.283539,47.403602],"type":"Point"}
}