{
  "type": "Feature",
  "properties": {
    "addr:full":"8833 Pacific Ave S Tacoma WA 98444",
    "addr:housenumber":"8833",
    "addr:postcode":"98444",
    "addr:street":"Pacific Ave S",
    "iso:country":"US",
    "sg:address":"8833 Pacific Ave S",
    "sg:city":"Tacoma",
    "sg:classifiers":[
        {
            "category":"Professional",
            "subcategory":"Accounting & Tax Preparation",
            "type":"Services"
        }
    ],
    "sg:phone":"+1 253 536 5908",
    "sg:postcode":"98444",
    "sg:province":"WA",
    "sg:tags":[
        "return",
        "filing"
    ],
    "wof:name":"WISE Accounting & Tax",
    "wof:placetype":"venue"
},
  "geometry": {"coordinates":[-122.434006,47.17614],"type":"Point"}
}