{
  "type": "Feature",
  "properties": {
    "addr:full":"4601 11th Ave NW Seattle WA 98107",
    "addr:housenumber":"4601",
    "addr:postcode":"98107",
    "addr:street":"11Th Ave Nw",
    "iso:country":"US",
    "sg:address":"4601 11th Ave NW",
    "sg:city":"Seattle",
    "sg:classifiers":[
        {
            "category":"Manufacturing",
            "subcategory":"Tools & Machinery",
            "type":"Manufacturing & Wholesale Goods"
        },
        {
            "category":"Manufacturing",
            "subcategory":"Electronics",
            "type":"Manufacturing & Wholesale Goods"
        },
        {
            "category":"Wholesale",
            "subcategory":"Construction Materials",
            "type":"Manufacturing & Wholesale Goods"
        },
        {
            "category":"Wholesale",
            "subcategory":"Electrical",
            "type":"Manufacturing & Wholesale Goods"
        },
        {
            "category":"Shopping",
            "subcategory":"Computers & Home Electronics",
            "type":"Retail Goods"
        }
    ],
    "sg:phone":"+1 206 781 9560",
    "sg:postcode":"98107",
    "sg:province":"WA",
    "sg:tags":[
        "control",
        "electric",
        "supply",
        "consumer",
        "system",
        "equipment-testing",
        "regulators-wholesale",
        "equipment",
        "controls",
        "supplies-wholesale",
        "manufacturer"
    ],
    "sg:website":"http://www.platt.com",
    "wof:name":"Platt Electric Supply Inc",
    "wof:placetype":"venue"
},
  "geometry": {"coordinates":[-122.370773,47.662201],"type":"Point"}
}