{
  "type": "Feature",
  "properties": {
    "addr:full":"15305 Waller Rd E Tacoma WA 98446",
    "addr:housenumber":"15305",
    "addr:postcode":"98446",
    "addr:street":"Waller Rd E",
    "iso:country":"US",
    "sg:address":"15305 Waller Rd E",
    "sg:city":"Tacoma",
    "sg:classifiers":[
        {
            "category":"Education",
            "subcategory":"School",
            "type":"Public Place"
        }
    ],
    "sg:phone":"+1 253 683 8700",
    "sg:postcode":"98446",
    "sg:province":"WA",
    "sg:website":"www.bethelsd.org",
    "wof:name":"Naches Trail Elementary School",
    "wof:placetype":"venue"
},
  "geometry": {"coordinates":[-122.389154,47.1177],"type":"Point"}
}