{
  "type": "Feature",
  "properties": {
    "addr:full":"3315 15th St Everett WA 98201",
    "addr:housenumber":"3315",
    "addr:postcode":"98201",
    "addr:street":"15Th St",
    "iso:country":"US",
    "sg:address":"3315 15th St",
    "sg:city":"Everett",
    "sg:classifiers":[
        {
            "category":"Manufacturing",
            "subcategory":"Petroleum Products",
            "type":"Manufacturing & Wholesale Goods"
        }
    ],
    "sg:phone":"+1 425 339 8340",
    "sg:postcode":"98201",
    "sg:province":"WA",
    "sg:tags":[
        "mixture",
        "paving",
        "asphalt",
        "mfg"
    ],
    "wof:name":"Wilder Paving Products",
    "wof:placetype":"venue"
},
  "geometry": {"coordinates":[-122.185389,47.997592],"type":"Point"}
}