{
  "type": "Feature",
  "properties": {
    "addr:full":"1202 S Woodlawn St Tacoma WA 98465",
    "addr:housenumber":"1202",
    "addr:postcode":"98465",
    "addr:street":"S Woodlawn St",
    "iso:country":"US",
    "sg:address":"1202 S Woodlawn St",
    "sg:city":"Tacoma",
    "sg:classifiers":[
        {
            "category":"Building & Trades",
            "subcategory":"Construction",
            "type":"Services"
        }
    ],
    "sg:phone":"+1 253 565 2969",
    "sg:postcode":"98465",
    "sg:province":"WA",
    "sg:tags":[
        "hanging",
        "contractor"
    ],
    "wof:name":"Imperial Painting",
    "wof:placetype":"venue"
},
  "geometry": {"coordinates":[-122.51447,47.247059],"type":"Point"}
}