{
  "type": "Feature",
  "properties": {
    "addr:full":"2801 NE 130th St Seattle WA 98125",
    "addr:housenumber":"2801",
    "addr:postcode":"98125",
    "addr:street":"Ne 130Th St",
    "iso:country":"US",
    "sg:address":"2801 NE 130th St",
    "sg:city":"Seattle",
    "sg:classifiers":[
        {
            "category":"Farming",
            "subcategory":"Fish & Marine Products",
            "type":"Manufacturing & Wholesale Goods"
        }
    ],
    "sg:phone":"+1 206 354 3879",
    "sg:postcode":"98125",
    "sg:province":"WA",
    "sg:tags":[
        "wildlife",
        "biology"
    ],
    "wof:name":"Sara Finneseth",
    "wof:placetype":"venue"
},
  "geometry": {"coordinates":[-122.29698399999999,47.72283],"type":"Point"}
}