{
  "type": "Feature",
  "properties": {
    "addr:full":"2002 E Union St Seattle WA 98122",
    "addr:housenumber":"2002",
    "addr:postcode":"98122",
    "addr:street":"E Union St",
    "iso:country":"US",
    "sg:address":"2002 E Union St",
    "sg:city":"Seattle",
    "sg:classifiers":[
        {
            "category":"Professional",
            "subcategory":"Art Services",
            "type":"Services"
        }
    ],
    "sg:phone":"+1 206 860 2811",
    "sg:postcode":"98122",
    "sg:province":"WA",
    "sg:tags":[
        "photographer"
    ],
    "sg:website":"www.classicimagephoto.net",
    "wof:name":"Classic Image Photography",
    "wof:placetype":"venue"
},
  "geometry": {"coordinates":[-122.306209,47.612906],"type":"Point"}
}