{
  "type": "Feature",
  "properties": {
    "addr:full":"43422 228th Ave SE Enumclaw WA 98022",
    "addr:housenumber":"43422",
    "addr:postcode":"98022",
    "addr:street":"228Th Ave Se",
    "iso:country":"US",
    "sg:address":"43422 228th Ave SE",
    "sg:city":"Enumclaw",
    "sg:classifiers":[
        {
            "category":"Professional",
            "subcategory":"Detective & Security Services",
            "type":"Services"
        }
    ],
    "sg:phone":"+1 360 825 1519",
    "sg:postcode":"98022",
    "sg:province":"WA",
    "sg:tags":[
        "guard"
    ],
    "wof:name":"Gary Raley",
    "wof:placetype":"venue"
},
  "geometry": {"coordinates":[-122.03745000000001,47.211776],"type":"Point"}
}