{
  "type": "Feature",
  "properties": {
    "addr:full":"1629 127th Pl SE Everett WA 98208",
    "addr:housenumber":"1629",
    "addr:postcode":"98208",
    "addr:street":"127Th Pl Se",
    "iso:country":"US",
    "sg:address":"1629 127th Pl SE",
    "sg:city":"Everett",
    "sg:classifiers":[
        {
            "category":"Professional",
            "subcategory":"Accounting & Tax Preparation",
            "type":"Services"
        }
    ],
    "sg:phone":"+1 425 337 5748",
    "sg:postcode":"98208",
    "sg:province":"WA",
    "wof:name":"Cnc Services",
    "wof:placetype":"venue"
},
  "geometry": {"coordinates":[-122.20846299999999,47.882412],"type":"Point"}
}