{
  "type": "Feature",
  "properties": {
    "addr:full":"4302 N Division St Spokane WA 99207",
    "addr:housenumber":"4302",
    "addr:postcode":"99207",
    "addr:street":"N Division St",
    "iso:country":"US",
    "sg:address":"4302 N Division St",
    "sg:city":"Spokane",
    "sg:classifiers":[
        {
            "category":"Food & Beverages",
            "subcategory":"Candy",
            "type":"Retail Goods"
        }
    ],
    "sg:phone":"+1 509 489 6837",
    "sg:postcode":"99207",
    "sg:province":"WA",
    "sg:tags":[
        "confectionery"
    ],
    "wof:name":"See's Candies",
    "wof:placetype":"venue"
},
  "geometry": {"coordinates":[-117.411142,47.697249],"type":"Point"}
}