{
  "type": "Feature",
  "properties": {
    "addr:full":"12604 189th Avenue Kp N Gig Harbor WA 98329",
    "addr:housenumber":"12604",
    "addr:postcode":"98329",
    "addr:street":"189Th Avenue Kp N",
    "iso:country":"US",
    "sg:address":"12604 189th Avenue Kp N",
    "sg:city":"Gig Harbor",
    "sg:classifiers":[
        {
            "category":"Retail",
            "subcategory":"Veterinary Services",
            "type":"Services"
        }
    ],
    "sg:phone":"+1 360 876 1544",
    "sg:postcode":"98329",
    "sg:province":"WA",
    "wof:name":"Pacific Equine Hospital",
    "wof:placetype":"venue"
},
  "geometry": {"coordinates":[-122.789355,47.372826],"type":"Point"}
}