{
  "type": "Feature",
  "properties": {
    "addr:full":"13421 Ambaum Blvd SW Burien WA 98146",
    "addr:housenumber":"13421",
    "addr:postcode":"98146",
    "addr:street":"Ambaum Blvd Sw",
    "iso:country":"US",
    "sg:address":"13421 Ambaum Blvd SW",
    "sg:city":"Burien",
    "sg:classifiers":[
        {
            "category":"Retail",
            "subcategory":"Repair Shop",
            "type":"Services"
        }
    ],
    "sg:phone":"+1 206 243 3159",
    "sg:postcode":"98146",
    "sg:province":"WA",
    "sg:tags":[
        "reupholstery",
        "furniture"
    ],
    "wof:name":"Alleycat Auto Upholstery",
    "wof:placetype":"venue"
},
  "geometry": {"coordinates":[-122.349998,47.4893],"type":"Point"}
}