{
  "type": "Feature",
  "properties": {
    "addr:full":"1101 N Northlake Way #201 Seattle WA 98103",
    "addr:housenumber":"1101",
    "addr:postcode":"98103",
    "addr:street":"N Northlake Way # 201",
    "iso:country":"US",
    "sg:address":"1101 N Northlake Way #201",
    "sg:city":"Seattle",
    "sg:classifiers":[
        {
            "category":"Building & Trades",
            "subcategory":"Construction",
            "type":"Services"
        },
        {
            "category":"Real Estate",
            "subcategory":"Architect",
            "type":"Services"
        }
    ],
    "sg:phone":"+1 206 286 1692",
    "sg:postcode":"98103",
    "sg:province":"WA",
    "sg:tags":[
        "contractor"
    ],
    "sg:website":"www.ctabuilds.com",
    "wof:name":"CTA Design Builders",
    "wof:placetype":"venue"
},
  "geometry": {"coordinates":[-122.345034,47.648504],"type":"Point"}
}