{
  "type": "Feature",
  "properties": {
    "addr:full":"17544 Midvale Ave N # 106 Shoreline WA 98133",
    "addr:housenumber":"17544",
    "addr:postcode":"98133",
    "addr:street":"Midvale Ave N # 106",
    "iso:country":"US",
    "sg:address":"17544 Midvale Ave N # 106",
    "sg:city":"Shoreline",
    "sg:classifiers":[
        {
            "category":"Real Estate",
            "subcategory":"Real Estate Services",
            "type":"Services"
        }
    ],
    "sg:phone":"+1 206 542 3300",
    "sg:postcode":"98133",
    "sg:province":"WA",
    "sg:tags":[
        "management",
        "condominium"
    ],
    "sg:website":"http://www.realtyescrow.net",
    "wof:name":"Shenandoah Homeowners Association",
    "wof:placetype":"venue"
},
  "geometry": {"coordinates":[-122.344264,47.756074],"type":"Point"}
}