{
  "type": "Feature",
  "properties": {
    "iso:country":"US",
    "sg:address":"7908 28th Ave SW",
    "sg:city":"Seattle",
    "sg:classifiers":[
        {
            "category":"Personal",
            "type":"Services"
        }
    ],
    "sg:phone":"+1 206 935 3644",
    "sg:postcode":"98126",
    "sg:province":"WA",
    "wof:name":"Ray Handyman",
    "wof:placetype":"venue"
},
  "geometry": {"coordinates":[-122.368471,47.530156],"type":"Point"}
}