{
  "type": "Feature",
  "properties": {
    "addr:full":"313 Robert Bush Dr South Bend WA 98586",
    "addr:housenumber":"313",
    "addr:postcode":"98586",
    "addr:street":"Robert Bush Dr",
    "iso:country":"US",
    "sg:address":"313 Robert Bush Dr",
    "sg:city":"South Bend",
    "sg:classifiers":[
        {
            "category":"Food & Beverages",
            "subcategory":"Meat & Fish",
            "type":"Retail Goods"
        }
    ],
    "sg:phone":"+1 360 875 5507",
    "sg:postcode":"98586",
    "sg:province":"WA",
    "sg:tags":[
        "seafood"
    ],
    "sg:website":"www.eastpointseafood.com",
    "wof:name":"Dungeoness Development",
    "wof:placetype":"venue"
},
  "geometry": {"coordinates":[-123.805255,46.66398],"type":"Point"}
}