{
  "type": "Feature",
  "properties": {
    "addr:full":"510 Cedar Canyon Pl Port Orchard WA 98366",
    "addr:housenumber":"510",
    "addr:postcode":"98366",
    "addr:street":"Cedar Canyon Pl",
    "iso:country":"US",
    "sg:address":"510 Cedar Canyon Pl",
    "sg:city":"Port Orchard",
    "sg:classifiers":[
        {
            "category":"Building & Trades",
            "subcategory":"Construction",
            "type":"Services"
        }
    ],
    "sg:phone":"+1 360 876 3050",
    "sg:postcode":"98366",
    "sg:province":"WA",
    "sg:tags":[
        "water",
        "main",
        "contractor",
        "road",
        "general"
    ],
    "wof:name":"Blue Cascade Construction Inc",
    "wof:placetype":"venue"
},
  "geometry": {"coordinates":[-122.658962,47.525732],"type":"Point"}
}