{
  "type": "Feature",
  "properties": {
    "addr:full":"1503 Carr Blvd Bremerton WA 98312",
    "addr:housenumber":"1503",
    "addr:postcode":"98312",
    "addr:street":"Carr Blvd",
    "iso:country":"US",
    "sg:address":"1503 Carr Blvd",
    "sg:city":"Bremerton",
    "sg:classifiers":[
        {
            "category":"Real Estate",
            "subcategory":"Real Estate Services",
            "type":"Services"
        },
        {
            "category":"Real Estate",
            "subcategory":"Real Estate Agent",
            "type":"Services"
        }
    ],
    "sg:phone":"+1 360 551 2934",
    "sg:postcode":"98312",
    "sg:province":"WA",
    "sg:tags":[
        "buyer",
        "broker"
    ],
    "wof:name":"Primetime Real Estate",
    "wof:placetype":"venue"
},
  "geometry": {"coordinates":[-122.692071,47.574588],"type":"Point"}
}