{
  "type": "Feature",
  "properties": {
    "iso:country":"US",
    "sg:address":"3615 65th Ave W",
    "sg:city":"Tacoma",
    "sg:classifiers":[
        {
            "category":"Building & Trades",
            "subcategory":"Construction",
            "type":"Services"
        }
    ],
    "sg:phone":"+1 253 565 0629",
    "sg:postcode":"98466",
    "sg:province":"WA",
    "sg:tags":[
        "concrete",
        "contractor"
    ],
    "wof:name":"Blanchfield Concrete Form",
    "wof:placetype":"venue"
},
  "geometry": {"coordinates":[-122.523646,47.224857],"type":"Point"}
}