{
  "type": "Feature",
  "properties": {
    "addr:full":"12206 N Normandie St Spokane WA 99218",
    "addr:housenumber":"12206",
    "addr:postcode":"99218",
    "addr:street":"N Normandie St",
    "iso:country":"US",
    "sg:address":"12206 N Normandie St",
    "sg:city":"Spokane",
    "sg:classifiers":[
        {
            "category":"Building & Trades",
            "subcategory":"Construction",
            "type":"Services"
        }
    ],
    "sg:phone":"+1 509 466 8946",
    "sg:postcode":"99218",
    "sg:province":"WA",
    "sg:tags":[
        "home",
        "builder"
    ],
    "wof:name":"Gene Plett Construction",
    "wof:placetype":"venue"
},
  "geometry": {"coordinates":[-117.411635,47.768059],"type":"Point"}
}