{
  "type": "Feature",
  "properties": {
    "addr:full":"915 Rucker Ave Everett WA 98201",
    "addr:housenumber":"915",
    "addr:postcode":"98201",
    "addr:street":"Rucker Ave",
    "iso:country":"US",
    "sg:address":"915 Rucker Ave",
    "sg:city":"Everett",
    "sg:classifiers":[
        {
            "category":"Shopping",
            "type":"Retail Goods"
        }
    ],
    "sg:phone":"+1 425 252 1060",
    "sg:postcode":"98201",
    "sg:province":"WA",
    "sg:tags":[
        "cosmetic",
        "perfume"
    ],
    "wof:name":"Timmi Davis",
    "wof:placetype":"venue"
},
  "geometry": {"coordinates":[-122.210719,48.004533],"type":"Point"}
}