{
  "type": "Feature",
  "properties": {
    "addr:full":"1040 S 320th St Federal Way WA 98003",
    "addr:housenumber":"1040",
    "addr:postcode":"98003",
    "addr:street":"S 320Th St",
    "iso:country":"US",
    "sg:address":"1040 S 320th St",
    "sg:city":"Federal Way",
    "sg:classifiers":[
        {
            "category":"Education",
            "subcategory":"Special Training",
            "type":"Public Place"
        }
    ],
    "sg:phone":"+1 253 941 5190",
    "sg:postcode":"98003",
    "sg:province":"WA",
    "wof:name":"Setri Sacred & Secular Educatn",
    "wof:placetype":"venue"
},
  "geometry": {"coordinates":[-122.319273,47.315239],"type":"Point"}
}