{
  "type": "Feature",
  "properties": {
    "addr:full":"152 Budgett Ln Chehalis WA 98532",
    "addr:housenumber":"152",
    "addr:postcode":"98532",
    "addr:street":"Budgett Ln",
    "iso:country":"US",
    "sg:address":"152 Budgett Ln",
    "sg:city":"Chehalis",
    "sg:classifiers":[
        {
            "category":"Professional",
            "type":"Services"
        }
    ],
    "sg:phone":"+1 360 748 3818",
    "sg:postcode":"98532",
    "sg:province":"WA",
    "wof:name":"Sepracor",
    "wof:placetype":"venue"
},
  "geometry": {"coordinates":[-123.063502,46.619799],"type":"Point"}
}