{
  "type": "Feature",
  "properties": {
    "addr:full":"2000 14th Ave S Seattle WA 98144",
    "addr:housenumber":"2000",
    "addr:postcode":"98144",
    "addr:street":"14Th Ave S",
    "iso:country":"US",
    "sg:address":"2000 14th Ave S",
    "sg:city":"Seattle",
    "sg:classifiers":[
        {
            "category":"Real Estate",
            "subcategory":"Real Estate Agent",
            "type":"Services"
        }
    ],
    "sg:phone":"+1 206 324 0606",
    "sg:postcode":"98144",
    "sg:province":"WA",
    "sg:tags":[
        "building",
        "operator",
        "apartment",
        "broker"
    ],
    "wof:name":"Beacon Hill Realty",
    "wof:placetype":"venue"
},
  "geometry": {"coordinates":[-122.31468599999999,47.584545],"type":"Point"}
}