{
  "type": "Feature",
  "properties": {
    "addr:full":"238 Lakeshore Dr Pateros WA 98831",
    "addr:housenumber":"238",
    "addr:postcode":"98831",
    "addr:street":"Lakeshore Dr",
    "iso:country":"US",
    "sg:address":"238 Lakeshore Dr",
    "sg:city":"Pateros",
    "sg:classifiers":[
        {
            "category":"Personal",
            "subcategory":"Beauty Salon",
            "type":"Services"
        }
    ],
    "sg:phone":"+1 509 923 2828",
    "sg:postcode":"98831",
    "sg:province":"WA",
    "sg:tags":[
        "shop"
    ],
    "wof:name":"Shannons Clip Joint",
    "wof:placetype":"venue"
},
  "geometry": {"coordinates":[-120.160049,47.887689],"type":"Point"}
}