{
  "type": "Feature",
  "properties": {
    "addr:full":"130 N Broadway Ave Othello WA 99344",
    "addr:housenumber":"130",
    "addr:postcode":"99344",
    "addr:street":"N Broadway Ave Othello",
    "iso:country":"US",
    "sg:address":"130 N Broadway Ave",
    "sg:city":"Othello",
    "sg:classifiers":[
        {
            "category":"Cinema",
            "subcategory":"Movie Theater",
            "type":"Entertainment"
        }
    ],
    "sg:phone":"+1 509 488 9796",
    "sg:postcode":"99344",
    "sg:province":"WA",
    "sg:tags":[
        "motion",
        "picture"
    ],
    "wof:name":"Reicherts Enterprises",
    "wof:placetype":"venue"
},
  "geometry": {"coordinates":[-119.175426,46.827905],"type":"Point"}
}