{
  "type": "Feature",
  "properties": {
    "addr:full":"4704 S Washington St Tacoma WA 98409",
    "addr:housenumber":"4704",
    "addr:postcode":"98409",
    "addr:street":"S Washington St",
    "iso:country":"US",
    "sg:address":"4704 S Washington St",
    "sg:city":"Tacoma",
    "sg:classifiers":[
        {
            "category":"Wholesale",
            "subcategory":"Machinery & Supplies",
            "type":"Manufacturing & Wholesale Goods"
        },
        {
            "category":"Retail",
            "subcategory":"Repair Shop",
            "type":"Services"
        }
    ],
    "sg:phone":"+1 253 474 0148",
    "sg:postcode":"98409",
    "sg:province":"WA",
    "sg:tags":[
        "installs",
        "compressor",
        "pump",
        "test",
        "tank"
    ],
    "wof:name":"Don Golden Company Inc",
    "wof:placetype":"venue"
},
  "geometry": {"coordinates":[-122.48506999999999,47.213628],"type":"Point"}
}