{
  "type": "Feature",
  "properties": {
    "addr:full":"502 S M St Fl 2 Tacoma WA 98405",
    "addr:housenumber":"502;2",
    "addr:postcode":"98405",
    "addr:street":"S M St",
    "iso:country":"US",
    "sg:address":"502 S M St Fl 2",
    "sg:city":"Tacoma",
    "sg:classifiers":[
        {
            "category":"Health Services",
            "subcategory":"Nursing And Care Facility",
            "type":"Services"
        }
    ],
    "sg:phone":"+1 253 473 7636",
    "sg:postcode":"98405",
    "sg:province":"WA",
    "sg:tags":[
        "nurse",
        "practice-arnp",
        "nurses-advanced"
    ],
    "wof:name":"Hansmrier, Julana Arnp",
    "wof:placetype":"venue"
},
  "geometry": {"coordinates":[-122.455996,47.257879],"type":"Point"}
}