{
  "type": "Feature",
  "properties": {
    "addr:full":"3135 Canberra Dr Walla Walla WA 99362",
    "addr:housenumber":"3135",
    "addr:postcode":"99362",
    "addr:street":"Canberra Dr",
    "iso:country":"US",
    "sg:address":"3135 Canberra Dr",
    "sg:city":"Walla Walla",
    "sg:classifiers":[
        {
            "category":"Shopping",
            "subcategory":"Bicycles & Sporting Goods",
            "type":"Retail Goods"
        }
    ],
    "sg:phone":"+1 509 525 1275",
    "sg:postcode":"99362",
    "sg:province":"WA",
    "wof:name":"S&S Sales",
    "wof:placetype":"venue"
},
  "geometry": {"coordinates":[-118.32566,46.028104],"type":"Point"}
}