{
  "type": "Feature",
  "properties": {
    "addr:full":"2111 W Commodore Way Seattle WA 98199",
    "addr:housenumber":"2111",
    "addr:postcode":"98199",
    "addr:street":"W Commodore Way",
    "iso:country":"US",
    "sg:address":"2111 W Commodore Way",
    "sg:city":"Seattle",
    "sg:classifiers":[
        {
            "category":"Retail",
            "subcategory":"Repair Shop",
            "type":"Services"
        },
        {
            "category":"Wholesale",
            "subcategory":"Durable Goods & Equipment",
            "type":"Manufacturing & Wholesale Goods"
        }
    ],
    "sg:phone":"+1 206 343 9570",
    "sg:postcode":"98199",
    "sg:province":"WA",
    "sg:tags":[
        "laboratory",
        "supply",
        "shopping",
        "refrigeration"
    ],
    "sg:website":"www.ebls.com",
    "wof:name":"Elliott Bay Laboratory Services Inc",
    "wof:placetype":"venue"
},
  "geometry": {"coordinates":[-122.38400300000001,47.659302],"type":"Point"}
}