{
  "type": "Feature",
  "properties": {
    "iso:country":"US",
    "sg:address":"3106 W Nob Hill Blvd",
    "sg:city":"Yakima",
    "sg:classifiers":[
        {
            "category":"Wholesale",
            "subcategory":"Electrical",
            "type":"Manufacturing & Wholesale Goods"
        }
    ],
    "sg:phone":"+1 509 248 5687",
    "sg:postcode":"98902",
    "sg:province":"WA",
    "sg:tags":[
        "fire",
        "alarm",
        "system"
    ],
    "wof:name":"Mansfield Alarm Co Inc",
    "wof:placetype":"venue"
},
  "geometry": {"coordinates":[-120.551379,46.585382],"type":"Point"}
}