{
  "type": "Feature",
  "properties": {
    "addr:full":"11900 SE 7th St Vancouver WA 98683",
    "addr:housenumber":"11900",
    "addr:postcode":"98683",
    "addr:street":"Se 7Th St",
    "iso:country":"US",
    "sg:address":"11900 SE 7th St",
    "sg:city":"Vancouver",
    "sg:classifiers":[
        {
            "category":"Shopping",
            "subcategory":"Gifts & Souvenirs",
            "type":"Retail Goods"
        }
    ],
    "sg:phone":"+1 360 256 0710",
    "sg:postcode":"98683",
    "sg:province":"WA",
    "wof:name":"Dereks Enterprises",
    "wof:placetype":"venue"
},
  "geometry": {"coordinates":[-122.550764,45.616145],"type":"Point"}
}