{
  "type": "Feature",
  "properties": {
    "addr:full":"714 20th Ave E Seattle WA 98112",
    "addr:housenumber":"714",
    "addr:postcode":"98112",
    "addr:street":"20Th Ave E",
    "iso:country":"US",
    "sg:address":"714 20th Ave E",
    "sg:city":"Seattle",
    "sg:classifiers":[
        {
            "category":"Professional",
            "subcategory":"Lawyer & Legal Services",
            "type":"Services"
        }
    ],
    "sg:phone":"+1 206 322 3852",
    "sg:postcode":"98112",
    "sg:province":"WA",
    "wof:name":"Lonergan Charles R Jr Atty",
    "wof:placetype":"venue"
},
  "geometry": {"coordinates":[-122.306,47.6255],"type":"Point"}
}