{
  "type": "Feature",
  "properties": {
    "addr:full":"8603 161st St E Puyallup WA 98375",
    "addr:housenumber":"8603",
    "addr:postcode":"98375",
    "addr:street":"161St St E",
    "iso:country":"US",
    "sg:address":"8603 161st St E",
    "sg:city":"Puyallup",
    "sg:classifiers":[
        {
            "category":"Home & Garden",
            "subcategory":"Furniture",
            "type":"Retail Goods"
        }
    ],
    "sg:phone":"+1 253 922 6218",
    "sg:postcode":"98375",
    "sg:province":"WA",
    "wof:name":"Portal Northwest Inc",
    "wof:placetype":"venue"
},
  "geometry": {"coordinates":[-122.31417500000001,47.110523],"type":"Point"}
}