{
  "type": "Feature",
  "properties": {
    "addr:full":"220 E Main St Fairfield WA 99012",
    "addr:housenumber":"220",
    "addr:postcode":"99012",
    "addr:street":"E Main St",
    "iso:country":"US",
    "sg:address":"220 E Main St",
    "sg:city":"Fairfield",
    "sg:classifiers":[
        {
            "category":"Government",
            "subcategory":"Post Office",
            "type":"Public Place"
        }
    ],
    "sg:phone":"+1 509 283 2513",
    "sg:postcode":"99012",
    "sg:province":"WA",
    "wof:name":"US Post Office",
    "wof:placetype":"venue"
},
  "geometry": {"coordinates":[-117.172005,47.385217],"type":"Point"}
}