{
  "type": "Feature",
  "properties": {
    "addr:full":"7324 NE 155th St Kenmore WA 98028",
    "addr:housenumber":"7324",
    "addr:postcode":"98028",
    "addr:street":"Ne 155Th St",
    "iso:country":"US",
    "sg:address":"7324 NE 155th St",
    "sg:city":"Kenmore",
    "sg:classifiers":[
        {
            "category":"Building & Trades",
            "subcategory":"Electrical",
            "type":"Services"
        }
    ],
    "sg:phone":"+1 425 487 8601",
    "sg:postcode":"98028",
    "sg:province":"WA",
    "sg:tags":[
        "electrical",
        "contractor"
    ],
    "wof:name":"G & N Electrical Contractor",
    "wof:placetype":"venue"
},
  "geometry": {"coordinates":[-122.243488,47.740779],"type":"Point"}
}