{
  "type": "Feature",
  "properties": {
    "addr:full":"1628 Dexter Ave N Seattle WA 98109",
    "addr:housenumber":"1628",
    "addr:postcode":"98109",
    "addr:street":"Dexter Ave N",
    "iso:country":"US",
    "sg:address":"1628 Dexter Ave N",
    "sg:city":"Seattle",
    "sg:classifiers":[
        {
            "category":"Restaurant",
            "type":"Food & Drink"
        }
    ],
    "sg:phone":"+1 206 283 7786",
    "sg:postcode":"98109",
    "sg:province":"WA",
    "sg:tags":[
        "eating"
    ],
    "wof:name":"Dexter & Hayes Public House",
    "wof:placetype":"venue"
},
  "geometry": {"coordinates":[-122.34200300000001,47.6334],"type":"Point"}
}