{
  "type": "Feature",
  "properties": {
    "addr:full":"17921 Bothell Everett Hwy Bothell WA 98012",
    "addr:housenumber":"17921",
    "addr:postcode":"98012",
    "addr:street":"Bothell Everett Hwy",
    "iso:country":"US",
    "sg:address":"17921 Bothell Everett Hwy",
    "sg:city":"Bothell",
    "sg:classifiers":[
        {
            "category":"Organizations",
            "subcategory":"Religious Organization",
            "type":"Services"
        }
    ],
    "sg:phone":"+1 425 487 1888",
    "sg:postcode":"98012",
    "sg:province":"WA",
    "wof:name":"Gathering Place",
    "wof:placetype":"venue"
},
  "geometry": {"coordinates":[-122.21132299999999,47.835585],"type":"Point"}
}