{
  "type": "Feature",
  "properties": {
    "addr:full":"655 Swanson Gulch Rd Manson WA 98831",
    "addr:housenumber":"655",
    "addr:postcode":"98831",
    "addr:street":"Swanson Gulch Rd",
    "iso:country":"US",
    "sg:address":"655 Swanson Gulch Rd",
    "sg:city":"Manson",
    "sg:classifiers":[
        {
            "category":"Manufacturing",
            "subcategory":"Buildings",
            "type":"Manufacturing & Wholesale Goods"
        },
        {
            "category":"Building & Trades",
            "subcategory":"Construction",
            "type":"Services"
        }
    ],
    "sg:phone":"+1 509 687 9259",
    "sg:postcode":"98831",
    "sg:province":"WA",
    "sg:tags":[
        "industrial",
        "excavation",
        "builder",
        "system",
        "specialty",
        "heating",
        "contractor",
        "contractors-commercial",
        "home",
        "air conditioning",
        "road"
    ],
    "wof:name":"Dan's Backhoe Service",
    "wof:placetype":"venue"
},
  "geometry": {"coordinates":[-120.08405999999999,47.903613],"type":"Point"}
}