{
  "type": "Feature",
  "properties": {
    "addr:full":"5525 University Way NE Seattle WA 98105",
    "addr:housenumber":"5525",
    "addr:postcode":"98105",
    "addr:street":"University Way Ne",
    "iso:country":"US",
    "sg:address":"5525 University Way NE",
    "sg:city":"Seattle",
    "sg:classifiers":[
        {
            "category":"Professional",
            "subcategory":"Management & Consulting",
            "type":"Services"
        }
    ],
    "sg:phone":"+1 206 542 7423",
    "sg:postcode":"98105",
    "sg:province":"WA",
    "wof:name":"Westland Associates Intl LLC",
    "wof:placetype":"venue"
},
  "geometry": {"coordinates":[-122.31309899999999,47.669213],"type":"Point"}
}