{
  "type": "Feature",
  "properties": {
    "addr:full":"616 Lilly Rd NE Olympia WA 98506",
    "addr:housenumber":"616",
    "addr:postcode":"98506",
    "addr:street":"Lilly Rd Ne",
    "iso:country":"US",
    "sg:address":"616 Lilly Rd NE",
    "sg:city":"Olympia",
    "sg:classifiers":[
        {
            "category":"Health Services",
            "subcategory":"Nursing And Care Facility",
            "type":"Services"
        }
    ],
    "sg:phone":"+1 360 456 0601",
    "sg:postcode":"98506",
    "sg:province":"WA",
    "sg:tags":[
        "home",
        "retirement",
        "community"
    ],
    "wof:name":"Merrill Gardens At Olympia",
    "wof:placetype":"venue"
},
  "geometry": {"coordinates":[-122.844334,47.054957],"type":"Point"}
}