{
  "type": "Feature",
  "properties": {
    "addr:full":"1602 Garfield Farmington Rd Farmington WA 99128",
    "addr:housenumber":"1602",
    "addr:postcode":"99128",
    "addr:street":"Garfield Farmington Rd",
    "iso:country":"US",
    "sg:address":"1602 Garfield Farmington Rd",
    "sg:city":"Farmington",
    "sg:classifiers":[
        {
            "category":"Place Of Worship",
            "type":"Public Place"
        }
    ],
    "sg:phone":"+1 509 287 2051",
    "sg:postcode":"99128",
    "sg:province":"WA",
    "sg:tags":[
        "church"
    ],
    "wof:name":"Shane Saint John",
    "wof:placetype":"venue"
},
  "geometry": {"coordinates":[-117.061167,47.068394],"type":"Point"}
}