{
  "type": "Feature",
  "properties": {
    "addr:full":"2008 NE 98th Loop Vancouver WA 98664",
    "addr:housenumber":"2008",
    "addr:postcode":"98664",
    "addr:street":"Ne 98Th Loop",
    "iso:country":"US",
    "sg:address":"2008 NE 98th Loop",
    "sg:city":"Vancouver",
    "sg:classifiers":[
        {
            "category":"Education",
            "subcategory":"Special Training",
            "type":"Public Place"
        }
    ],
    "sg:phone":"+1 360 260 2227",
    "sg:postcode":"98664",
    "sg:province":"WA",
    "sg:tags":[
        "program"
    ],
    "wof:name":"Industrial Training Cnslnts",
    "wof:placetype":"venue"
},
  "geometry": {"coordinates":[-122.57185,45.636543],"type":"Point"}
}