{
  "type": "Feature",
  "properties": {
    "addr:full":"10722 5TH AVE NE SEATTLE WA 98125",
    "addr:housenumber":"10722",
    "addr:postcode":"98125",
    "addr:street":"5Th Ave Ne",
    "iso:country":"US",
    "sg:address":"10722 5TH AVE NE",
    "sg:city":"SEATTLE",
    "sg:classifiers":[
        {
            "category":"Shopping",
            "subcategory":"Stationery & Office Supplies",
            "type":"Retail Goods"
        },
        {
            "category":"Personal",
            "type":"Services"
        },
        {
            "category":"Sports & Exercise",
            "subcategory":"Gym",
            "type":"Entertainment"
        },
        {
            "category":"Education",
            "subcategory":"Special Training",
            "type":"Public Place"
        },
        {
            "category":"Arena",
            "subcategory":"Sports Club",
            "type":"Entertainment"
        }
    ],
    "sg:phone":"+1 206 792 5534",
    "sg:postcode":"98125",
    "sg:province":"WA",
    "sg:tags":[
        "consultant",
        "instruction",
        "self defense",
        "equipment",
        "program",
        "health",
        "fitness",
        "martial art",
        "physical"
    ],
    "sg:website":"http://www.mkgseattle.com/page.asp?content_id=8835",
    "wof:name":"MKG Martial Arts",
    "wof:placetype":"venue"
},
  "geometry": {"coordinates":[-122.32325899999999,47.7076],"type":"Point"}
}