{
  "type": "Feature",
  "properties": {
    "addr:full":"2231 SW 346th St Federal Way WA 98023",
    "addr:housenumber":"2231",
    "addr:postcode":"98023",
    "addr:street":"Sw 346Th St",
    "iso:country":"US",
    "sg:address":"2231 SW 346th St",
    "sg:city":"Federal Way",
    "sg:classifiers":[
        {
            "category":"Building & Trades",
            "subcategory":"Plumbing",
            "type":"Services"
        }
    ],
    "sg:phone":"+1 206 354 0463",
    "sg:postcode":"98023",
    "sg:province":"WA",
    "sg:tags":[
        "contractor"
    ],
    "wof:name":"Sareese Mechanical",
    "wof:placetype":"venue"
},
  "geometry": {"coordinates":[-122.36544499999999,47.291824],"type":"Point"}
}