{
  "type": "Feature",
  "properties": {
    "addr:full":"10700 SE 174th St Renton WA 98055",
    "addr:postcode":"10700;98055",
    "addr:street":"Se 174Th St",
    "iso:country":"US",
    "sg:address":"10700 SE 174th St",
    "sg:city":"Renton",
    "sg:classifiers":[
        {
            "category":"Government",
            "subcategory":"Office",
            "type":"Public Place"
        }
    ],
    "sg:phone":"+1 206 296 4955",
    "sg:postcode":"98055",
    "sg:province":"WA",
    "sg:tags":[
        "administrative",
        "program",
        "health"
    ],
    "wof:name":"Health Dept",
    "wof:placetype":"venue"
},
  "geometry": {"coordinates":[-122.198492,47.446674],"type":"Point"}
}