{
  "type": "Feature",
  "properties": {
    "addr:full":"13204 168th Ave SE Renton WA 98059",
    "addr:housenumber":"13204",
    "addr:postcode":"98059",
    "addr:street":"168Th Ave Se",
    "iso:country":"US",
    "sg:address":"13204 168th Ave SE",
    "sg:city":"Renton",
    "sg:classifiers":[
        {
            "category":"Building & Trades",
            "subcategory":"Construction",
            "type":"Services"
        }
    ],
    "sg:phone":"+1 425 255 6011",
    "sg:postcode":"98059",
    "sg:province":"WA",
    "sg:tags":[
        "bulldozing"
    ],
    "wof:name":"Behnkes Dozing & Construction",
    "wof:placetype":"venue"
},
  "geometry": {"coordinates":[-122.116466,47.482582],"type":"Point"}
}