{
  "type": "Feature",
  "properties": {
    "addr:full":"621 W Mallon Ave Spokane WA 99201",
    "addr:housenumber":"621",
    "addr:postcode":"99201",
    "addr:street":"W Mallon Ave",
    "iso:country":"US",
    "sg:address":"621 W Mallon Ave",
    "sg:city":"Spokane",
    "sg:classifiers":[
        {
            "category":"Personal",
            "subcategory":"Nail Salon",
            "type":"Services"
        }
    ],
    "sg:phone":"+1 509 326 1727",
    "sg:postcode":"99201",
    "sg:province":"WA",
    "wof:name":"Marguerite's Nail Boutique",
    "wof:placetype":"venue"
},
  "geometry": {"coordinates":[-117.420908,47.665352],"type":"Point"}
}