{
  "type": "Feature",
  "properties": {
    "addr:full":"2007 S State St Seattle WA 98144",
    "addr:housenumber":"2007",
    "addr:postcode":"98144",
    "addr:street":"S State St",
    "iso:country":"US",
    "sg:address":"2007 S State St",
    "sg:city":"Seattle",
    "sg:classifiers":[
        {
            "category":"Autos & Motor Vehicles",
            "subcategory":"Auto Supplies",
            "type":"Retail Goods"
        }
    ],
    "sg:phone":"+1 206 323 2552",
    "sg:postcode":"98144",
    "sg:province":"WA",
    "sg:tags":[
        "tire"
    ],
    "wof:name":"Darrell's Auto Sport",
    "wof:placetype":"venue"
},
  "geometry": {"coordinates":[-122.305291,47.587662],"type":"Point"}
}