{
  "type": "Feature",
  "properties": {
    "addr:full":"3335 Frances Dr SE Lacey WA 98503",
    "addr:housenumber":"3335",
    "addr:postcode":"98503",
    "addr:street":"Frances Dr Se",
    "iso:country":"US",
    "sg:address":"3335 Frances Dr SE",
    "sg:city":"Lacey",
    "sg:classifiers":[
        {
            "category":"Building & Trades",
            "subcategory":"Construction",
            "type":"Services"
        }
    ],
    "sg:phone":"+1 360 493 0507",
    "sg:postcode":"98503",
    "sg:province":"WA",
    "sg:tags":[
        "residential",
        "contractor"
    ],
    "wof:name":"Better Homes Home Improvement",
    "wof:placetype":"venue"
},
  "geometry": {"coordinates":[-122.76779500000001,47.01649],"type":"Point"}
}