{
  "type": "Feature",
  "properties": {
    "addr:full":"990 S Jackson St Seattle WA 98104",
    "addr:housenumber":"990",
    "addr:postcode":"98104",
    "addr:street":"S Jackson St",
    "iso:country":"US",
    "sg:address":"990 S Jackson St",
    "sg:city":"Seattle",
    "sg:classifiers":[
        {
            "category":"Professional",
            "type":"Services"
        }
    ],
    "sg:phone":"+1 206 227 6752",
    "sg:postcode":"98104",
    "sg:province":"WA",
    "wof:name":"J&T Sweety Home",
    "wof:placetype":"venue"
},
  "geometry": {"coordinates":[-122.320021,47.599258],"type":"Point"}
}