{
  "type": "Feature",
  "properties": {
    "addr:full":"317 Main St Edmonds WA 98020",
    "addr:housenumber":"317",
    "addr:postcode":"98020",
    "addr:street":"Main St",
    "iso:country":"US",
    "sg:address":"317 Main St",
    "sg:city":"Edmonds",
    "sg:classifiers":[
        {
            "category":"Personal",
            "subcategory":"Beauty Salon",
            "type":"Services"
        }
    ],
    "sg:phone":"+1 425 744 1866",
    "sg:postcode":"98020",
    "sg:province":"WA",
    "sg:tags":[
        "shop"
    ],
    "wof:name":"Picture Perfect Kids",
    "wof:placetype":"venue"
},
  "geometry": {"coordinates":[-122.37860000000001,47.811128],"type":"Point"}
}