{
  "type": "Feature",
  "properties": {
    "addr:full":"5705 143rd Pl SE Bellevue WA 98006",
    "addr:housenumber":"5705",
    "addr:postcode":"98006",
    "addr:street":"143Rd Pl Se",
    "iso:country":"US",
    "sg:address":"5705 143rd Pl SE",
    "sg:city":"Bellevue",
    "sg:classifiers":[
        {
            "category":"Professional",
            "subcategory":"Management & Consulting",
            "type":"Services"
        }
    ],
    "sg:phone":"+1 425 643 2363",
    "sg:postcode":"98006",
    "sg:province":"WA",
    "sg:tags":[
        "consultant",
        "coach",
        "business"
    ],
    "wof:name":"Lynn Withrow Consulting",
    "wof:placetype":"venue"
},
  "geometry": {"coordinates":[-122.15013999999999,47.550943],"type":"Point"}
}