{
  "type": "Feature",
  "properties": {
    "addr:full":"2784 NE Athens Way Bremerton WA 98311",
    "addr:housenumber":"2784",
    "addr:postcode":"98311",
    "addr:street":"Ne Athens Way",
    "iso:country":"US",
    "sg:address":"2784 NE Athens Way",
    "sg:city":"Bremerton",
    "sg:classifiers":[
        {
            "category":"Professional",
            "subcategory":"Business Services",
            "type":"Services"
        },
        {
            "category":"Professional",
            "subcategory":"Secretarial Services",
            "type":"Services"
        }
    ],
    "sg:phone":"+1 360 698 5059",
    "sg:postcode":"98311",
    "sg:province":"WA",
    "sg:tags":[
        "transcription",
        "reporting"
    ],
    "wof:name":"Bakers Court Transcription SE",
    "wof:placetype":"venue"
},
  "geometry": {"coordinates":[-122.61479,47.622614],"type":"Point"}
}