{
  "type": "Feature",
  "properties": {
    "addr:full":"250 N Teanaway Ave Cle Elum WA 98922",
    "addr:housenumber":"250",
    "addr:postcode":"98922",
    "addr:street":"N Teanaway Ave",
    "iso:country":"US",
    "sg:address":"250 N Teanaway Ave",
    "sg:city":"Cle Elum",
    "sg:classifiers":[
        {
            "category":"Professional",
            "type":"Services"
        }
    ],
    "sg:phone":"+1 509 674 7324",
    "sg:postcode":"98922",
    "sg:province":"WA",
    "wof:name":"Eckmanjon",
    "wof:placetype":"venue"
},
  "geometry": {"coordinates":[-120.926089,47.193823],"type":"Point"}
}