{
  "type": "Feature",
  "properties": {
    "iso:country":"US",
    "sg:address":"1927 Elevator Way",
    "sg:city":"Vancouver",
    "sg:classifiers":[
        {
            "category":"Professional",
            "subcategory":"Business Services",
            "type":"Services"
        }
    ],
    "sg:phone":"+1 360 750 3699",
    "sg:postcode":"98660",
    "sg:province":"WA",
    "wof:name":"National Quality Inspections",
    "wof:placetype":"venue"
},
  "geometry": {"coordinates":[-122.69278300000001,45.63319],"type":"Point"}
}