{
  "type": "Feature",
  "properties": {
    "addr:full":"5102 20th St E Tacoma WA 98424",
    "addr:housenumber":"5102",
    "addr:postcode":"98424",
    "addr:street":"20Th St",
    "iso:country":"US",
    "sg:address":"5102 20th St E",
    "sg:city":"Tacoma",
    "sg:classifiers":[
        {
            "category":"Wholesale",
            "subcategory":"Office Equipment",
            "type":"Manufacturing & Wholesale Goods"
        }
    ],
    "sg:phone":"+1 253 572 6400",
    "sg:postcode":"98424",
    "sg:province":"WA",
    "sg:tags":[
        "machine",
        "duplicating",
        "copying"
    ],
    "sg:website":"www.pacificoffice.com",
    "wof:name":"PACIFIC Office Automation",
    "wof:placetype":"venue"
},
  "geometry": {"coordinates":[-122.347128,47.238898],"type":"Point"}
}