{
  "type": "Feature",
  "properties": {
    "addr:full":"2101 4th Avenue Seattle WA 98121",
    "addr:housenumber":"2101",
    "addr:postcode":"98121",
    "addr:street":"4Th Avenue",
    "iso:country":"US",
    "sg:address":"2101 4th Avenue",
    "sg:city":"Seattle",
    "sg:classifiers":[
        {
            "category":"Professional",
            "subcategory":"Lawyer & Legal Services",
            "type":"Services"
        }
    ],
    "sg:phone":"+1 206 448 1230",
    "sg:postcode":"98121",
    "sg:province":"WA",
    "wof:name":"Ziontz Alvin J Atty",
    "wof:placetype":"venue"
},
  "geometry": {"coordinates":[-122.348371,47.615696],"type":"Point"}
}