{
  "type": "Feature",
  "properties": {
    "addr:full":"2717 SE Arthur Ct Port Orchard WA 98367",
    "addr:housenumber":"2717",
    "addr:postcode":"98367",
    "addr:street":"Se Arthur Ct",
    "iso:country":"US",
    "sg:address":"2717 SE Arthur Ct",
    "sg:city":"Port Orchard",
    "sg:classifiers":[
        {
            "category":"Manufacturing",
            "subcategory":"Metals",
            "type":"Manufacturing & Wholesale Goods"
        }
    ],
    "sg:phone":"+1 360 895 0519",
    "sg:postcode":"98367",
    "sg:province":"WA",
    "sg:tags":[
        "steel",
        "product",
        "mfg"
    ],
    "wof:name":"Friendship Baskets",
    "wof:placetype":"venue"
},
  "geometry": {"coordinates":[-122.615196,47.46628],"type":"Point"}
}