{
  "type": "Feature",
  "properties": {
    "addr:full":"318 W Brooks St Goldendale WA 98620",
    "addr:housenumber":"318",
    "addr:postcode":"98620",
    "addr:street":"W Brooks St",
    "iso:country":"US",
    "sg:address":"318 W Brooks St",
    "sg:city":"Goldendale",
    "sg:classifiers":[
        {
            "category":"Home & Garden",
            "subcategory":"Home Furnishings",
            "type":"Retail Goods"
        },
        {
            "category":"Building & Trades",
            "subcategory":"Construction",
            "type":"Services"
        },
        {
            "category":"Manufacturing",
            "subcategory":"Building Materials",
            "type":"Manufacturing & Wholesale Goods"
        },
        {
            "category":"Home & Garden",
            "subcategory":"Furniture",
            "type":"Retail Goods"
        }
    ],
    "sg:phone":"+1 509 773 3770",
    "sg:postcode":"98620",
    "sg:province":"WA",
    "sg:tags":[
        "industrial",
        "cabinetmakers-commercial",
        "cabinet",
        "refacing",
        "resurfacing",
        "maker",
        "cabinets-refinishing",
        "kitchen"
    ],
    "wof:name":"Shenandoah Custom Cabinets",
    "wof:placetype":"venue"
},
  "geometry": {"coordinates":[-120.82696,45.817825],"type":"Point"}
}