{
  "type": "Feature",
  "properties": {
    "addr:full":"1806 NW 189th St A Ridgefield WA 98642",
    "addr:housenumber":"1806",
    "addr:postcode":"98642",
    "addr:street":"Nw 189Th St",
    "iso:country":"US",
    "sg:address":"1806 NW 189th St A",
    "sg:city":"Ridgefield",
    "sg:classifiers":[
        {
            "category":"Personal",
            "subcategory":"Tattoo Parlor",
            "type":"Services"
        },
        {
            "category":"Personal",
            "subcategory":"Piercing",
            "type":"Services"
        }
    ],
    "sg:phone":"+1 360 263 4327",
    "sg:postcode":"98642",
    "sg:province":"WA",
    "sg:tags":[
        "body"
    ],
    "wof:name":"Pink Box Tattoo",
    "wof:placetype":"venue"
},
  "geometry": {"coordinates":[-122.689305,45.757751],"type":"Point"}
}