{
  "type": "Feature",
  "properties": {
    "addr:full":"720 3rd Ave Seattle WA 98104",
    "addr:housenumber":"720",
    "addr:postcode":"98104",
    "addr:street":"3Rd Ave",
    "iso:country":"US",
    "sg:address":"720 3rd Ave",
    "sg:city":"Seattle",
    "sg:classifiers":[
        {
            "category":"Insurance",
            "subcategory":"Hazard Insurance",
            "type":"Services"
        }
    ],
    "sg:phone":"+1 206 622 3270",
    "sg:postcode":"98104",
    "sg:province":"WA",
    "sg:tags":[
        "company"
    ],
    "wof:name":"United States Fidelty Guaranty",
    "wof:placetype":"venue"
},
  "geometry": {"coordinates":[-122.332562,47.604089],"type":"Point"}
}