{
  "type": "Feature",
  "properties": {
    "addr:full":"1616 Washington St Manson WA 98831",
    "addr:housenumber":"1616",
    "addr:postcode":"98831",
    "addr:street":"Washington St",
    "iso:country":"US",
    "sg:address":"1616 Washington St",
    "sg:city":"Manson",
    "sg:classifiers":[
        {
            "category":"Manufacturing",
            "subcategory":"Apparel",
            "type":"Manufacturing & Wholesale Goods"
        },
        {
            "category":"Retail",
            "subcategory":"Laundry & Dry Cleaning",
            "type":"Services"
        }
    ],
    "sg:phone":"+1 509 687 2095",
    "sg:postcode":"98831",
    "sg:province":"WA",
    "sg:tags":[
        "sewing",
        "contractor"
    ],
    "wof:name":"Sew - What",
    "wof:placetype":"venue"
},
  "geometry": {"coordinates":[-120.184583,47.912471],"type":"Point"}
}