{
  "type": "Feature",
  "properties": {
    "addr:full":"4496 NE N Tolo Rd Bainbridge Island WA 98110",
    "addr:housenumber":"4496",
    "addr:postcode":"98110",
    "addr:street":"Ne N Tolo Rd",
    "iso:country":"US",
    "sg:address":"4496 NE N Tolo Rd",
    "sg:city":"Bainbridge Island",
    "sg:classifiers":[
        {
            "category":"Professional",
            "subcategory":"Advertising",
            "type":"Services"
        }
    ],
    "sg:phone":"+1 206 842 0603",
    "sg:postcode":"98110",
    "sg:province":"WA",
    "sg:tags":[
        "representative"
    ],
    "wof:name":"Outer Planet Inc",
    "wof:placetype":"venue"
},
  "geometry": {"coordinates":[-122.585353,47.659835],"type":"Point"}
}