{
  "type": "Feature",
  "properties": {
    "addr:full":"3203 N 26th St Tacoma WA 98407",
    "addr:housenumber":"3203",
    "addr:postcode":"98407",
    "addr:street":"N 26Th St",
    "iso:country":"US",
    "sg:address":"3203 N 26th St",
    "sg:city":"Tacoma",
    "sg:classifiers":[
        {
            "category":"Personal",
            "subcategory":"Beauty Salon",
            "type":"Services"
        }
    ],
    "sg:phone":"+1 253 759 6956",
    "sg:postcode":"98407",
    "sg:province":"WA",
    "sg:tags":[
        "shop"
    ],
    "wof:name":"Crystal Nails",
    "wof:placetype":"venue"
},
  "geometry": {"coordinates":[-122.47935699999999,47.271157],"type":"Point"}
}