{
  "type": "Feature",
  "properties": {
    "addr:full":"705 Christman Pl Port Angeles WA 98362",
    "addr:housenumber":"705",
    "addr:postcode":"98362",
    "addr:street":"Christman Pl",
    "iso:country":"US",
    "sg:address":"705 Christman Pl",
    "sg:city":"Port Angeles",
    "sg:classifiers":[
        {
            "category":"Professional",
            "subcategory":"Business Services",
            "type":"Services"
        }
    ],
    "sg:phone":"+1 360 452 3540",
    "sg:postcode":"98362",
    "sg:province":"WA",
    "sg:tags":[
        "interior",
        "consultant",
        "design",
        "decorator"
    ],
    "wof:name":"Distinctive Designs-Julie Inc",
    "wof:placetype":"venue"
},
  "geometry": {"coordinates":[-123.40392199999999,48.100877],"type":"Point"}
}