{
  "type": "Feature",
  "properties": {
    "addr:full":"2527 W Kennewick Ave Kennewick WA 99336",
    "addr:housenumber":"2527",
    "addr:postcode":"99336",
    "addr:street":"W Kennewick Ave",
    "iso:country":"US",
    "sg:address":"2527 W Kennewick Ave",
    "sg:city":"Kennewick",
    "sg:classifiers":[
        {
            "category":"Shopping",
            "subcategory":"Clothing, Apparel, & Fashions",
            "type":"Retail Goods"
        }
    ],
    "sg:phone":"+1 509 521 0470",
    "sg:postcode":"99336",
    "sg:province":"WA",
    "wof:name":"Sand & Shore LLC",
    "wof:placetype":"venue"
},
  "geometry": {"coordinates":[-119.155675,46.209379],"type":"Point"}
}