{
  "type": "Feature",
  "properties": {
    "addr:full":"633 Pioneer Ave W Montesano WA 98563",
    "addr:housenumber":"633",
    "addr:postcode":"98563",
    "addr:street":"Pioneer Ave W Montesano",
    "iso:country":"US",
    "sg:address":"633 Pioneer Ave W",
    "sg:city":"Montesano",
    "sg:classifiers":[
        {
            "category":"Home & Garden",
            "subcategory":"Furniture",
            "type":"Retail Goods"
        }
    ],
    "sg:phone":"+1 360 249 3682",
    "sg:postcode":"98563",
    "sg:province":"WA",
    "sg:tags":[
        "kitchen",
        "cabinet"
    ],
    "wof:name":"Grays Harbor Cabinet",
    "wof:placetype":"venue"
},
  "geometry": {"coordinates":[-123.60669,46.978949],"type":"Point"}
}