{
  "type": "Feature",
  "properties": {
    "addr:full":"358 E Birch Ave Colville WA 99114",
    "addr:housenumber":"358",
    "addr:postcode":"99114",
    "addr:street":"E Birch Ave",
    "iso:country":"US",
    "sg:address":"358 E Birch Ave",
    "sg:city":"Colville",
    "sg:classifiers":[
        {
            "category":"Professional",
            "subcategory":"Lawyer & Legal Services",
            "type":"Services"
        }
    ],
    "sg:phone":"+1 509 685 1230",
    "sg:postcode":"99114",
    "sg:province":"WA",
    "wof:name":"Bruce Pruitthamm Attorney",
    "wof:placetype":"venue"
},
  "geometry": {"coordinates":[-117.902074,48.542221],"type":"Point"}
}