{
  "type": "Feature",
  "properties": {
    "addr:full":"6005 N Jensen Rd Spokane WA 99217",
    "addr:housenumber":"6005",
    "addr:postcode":"99217",
    "addr:street":"N Jensen Rd",
    "iso:country":"US",
    "sg:address":"6005 N Jensen Rd",
    "sg:city":"Spokane",
    "sg:classifiers":[
        {
            "category":"Retail",
            "subcategory":"Portrait Studio",
            "type":"Services"
        }
    ],
    "sg:phone":"+1 509 927 7296",
    "sg:postcode":"99217",
    "sg:province":"WA",
    "sg:tags":[
        "photo"
    ],
    "wof:name":"Chamberlain Photography",
    "wof:placetype":"venue"
},
  "geometry": {"coordinates":[-117.293688,47.712441],"type":"Point"}
}