{
  "type": "Feature",
  "properties": {
    "addr:full":"125 N 105th St Seattle WA 98133",
    "addr:housenumber":"125",
    "addr:postcode":"98133",
    "addr:street":"N 105Th St",
    "iso:country":"US",
    "sg:address":"125 N 105th St",
    "sg:city":"Seattle",
    "sg:classifiers":[
        {
            "category":"Education",
            "subcategory":"Special Training",
            "type":"Public Place"
        }
    ],
    "sg:phone":"+1 206 973 7476",
    "sg:postcode":"98133",
    "sg:province":"WA",
    "sg:tags":[
        "educational"
    ],
    "wof:name":"Noble Global",
    "wof:placetype":"venue"
},
  "geometry": {"coordinates":[-122.357437,47.705109],"type":"Point"}
}