{
  "type": "Feature",
  "properties": {
    "addr:full":"4392 239th Pl SE Issaquah WA 98029",
    "addr:housenumber":"4392",
    "addr:postcode":"98029",
    "addr:street":"239Th Pl Se",
    "iso:country":"US",
    "sg:address":"4392 239th Pl SE",
    "sg:city":"Issaquah",
    "sg:classifiers":[
        {
            "category":"Professional",
            "subcategory":"Business Services",
            "type":"Services"
        }
    ],
    "sg:phone":"+1 425 557 6428",
    "sg:postcode":"98029",
    "sg:province":"WA",
    "wof:name":"Personalized Interiors",
    "wof:placetype":"venue"
},
  "geometry": {"coordinates":[-122.021424,47.567009],"type":"Point"}
}