{
  "type": "Feature",
  "properties": {
    "addr:full":"3111 S 273rd St Auburn WA 98001",
    "addr:housenumber":"3111",
    "addr:postcode":"98001",
    "addr:street":"S 273Rd St",
    "iso:country":"US",
    "sg:address":"3111 S 273rd St",
    "sg:city":"Auburn",
    "sg:classifiers":[
        {
            "category":"Building & Trades",
            "subcategory":"Construction",
            "type":"Services"
        }
    ],
    "sg:phone":"+1 253 653 4138",
    "sg:postcode":"98001",
    "sg:province":"WA",
    "sg:tags":[
        "house"
    ],
    "wof:name":"Kin Tuhan",
    "wof:placetype":"venue"
},
  "geometry": {"coordinates":[-122.292751,47.356458],"type":"Point"}
}