{
  "type": "Feature",
  "properties": {
    "addr:full":"401 Central Ave Bellingham WA 98225",
    "addr:housenumber":"401",
    "addr:postcode":"98225",
    "addr:street":"Central Ave",
    "iso:country":"US",
    "sg:address":"401 Central Ave",
    "sg:city":"Bellingham",
    "sg:classifiers":[
        {
            "category":"Professional",
            "subcategory":"Lawyer & Legal Services",
            "type":"Services"
        }
    ],
    "sg:phone":"+1 360 734 8127",
    "sg:postcode":"98225",
    "sg:province":"WA",
    "sg:tags":[
        "practice",
        "attorney",
        "criminal",
        "law"
    ],
    "wof:name":"Matt Peach",
    "wof:placetype":"venue"
},
  "geometry": {"coordinates":[-122.481056,48.75388],"type":"Point"}
}