{
  "type": "Feature",
  "properties": {
    "addr:full":"13215 SE Mill Plain Blvd Vancouver WA 98684",
    "addr:housenumber":"13215",
    "addr:postcode":"98684",
    "addr:street":"Se Mill Plain Blvd",
    "iso:country":"US",
    "sg:address":"13215 SE Mill Plain Blvd",
    "sg:city":"Vancouver",
    "sg:classifiers":[
        {
            "category":"Shopping",
            "subcategory":"Computers & Home Electronics",
            "type":"Retail Goods"
        }
    ],
    "sg:phone":"+1 360 892 8061",
    "sg:postcode":"98684",
    "sg:province":"WA",
    "sg:website":"www.rivercitymusic.us",
    "wof:name":"River City Music Inc",
    "wof:placetype":"venue"
},
  "geometry": {"coordinates":[-122.535004,45.618698],"type":"Point"}
}