{
  "type": "Feature",
  "properties": {
    "addr:full":"405 Auburn Way N Auburn WA 98002",
    "addr:housenumber":"405",
    "addr:postcode":"98002",
    "addr:street":"Auburn Way N",
    "iso:country":"US",
    "sg:address":"405 Auburn Way N",
    "sg:city":"Auburn",
    "sg:classifiers":[
        {
            "category":"Shopping",
            "subcategory":"Florist",
            "type":"Retail Goods"
        }
    ],
    "sg:phone":"+1 253 833 8110",
    "sg:postcode":"98002",
    "sg:province":"WA",
    "sg:tags":[
        "balloon",
        "decorator"
    ],
    "wof:name":"Buds & Blooms",
    "wof:placetype":"venue"
},
  "geometry": {"coordinates":[-122.226045,47.310761],"type":"Point"}
}