{
  "type": "Feature",
  "properties": {
    "addr:full":"4628 168th St SW Lynnwood WA 98037",
    "addr:housenumber":"4628",
    "addr:postcode":"98037",
    "addr:street":"168Th St Sw",
    "iso:country":"US",
    "sg:address":"4628 168th St SW",
    "sg:city":"Lynnwood",
    "sg:classifiers":[
        {
            "category":"Retail",
            "subcategory":"Car Wash",
            "type":"Services"
        }
    ],
    "sg:phone":"+1 425 745 6560",
    "sg:postcode":"98037",
    "sg:province":"WA",
    "sg:tags":[
        "polishing",
        "washing"
    ],
    "wof:name":"Whale Of A Wash",
    "wof:placetype":"venue"
},
  "geometry": {"coordinates":[-122.295092,47.846457],"type":"Point"}
}