{
  "type": "Feature",
  "properties": {
    "addr:full":"1607 S 341st Pl Federal Way WA 98003",
    "addr:housenumber":"1607",
    "addr:postcode":"98003",
    "addr:street":"S 341St Pl",
    "iso:country":"US",
    "sg:address":"1607 S 341st Pl",
    "sg:city":"Federal Way",
    "sg:classifiers":[
        {
            "category":"Professional",
            "subcategory":"Lawyer & Legal Services",
            "type":"Services"
        }
    ],
    "sg:phone":"+1 253 838 6633",
    "sg:postcode":"98003",
    "sg:province":"WA",
    "wof:name":"Lutz Law Offices PA",
    "wof:placetype":"venue"
},
  "geometry": {"coordinates":[-122.31045899999999,47.295684],"type":"Point"}
}