{
  "type": "Feature",
  "properties": {
    "addr:full":"27458 108th Ave SE Kent WA 98030",
    "addr:housenumber":"27458",
    "addr:postcode":"98030",
    "addr:street":"108Th Ave Se",
    "iso:country":"US",
    "sg:address":"27458 108th Ave SE",
    "sg:city":"Kent",
    "sg:classifiers":[
        {
            "category":"Social Services",
            "subcategory":"Adult Care",
            "type":"Services"
        }
    ],
    "sg:phone":"+1 253 859 5808",
    "sg:postcode":"98030",
    "sg:province":"WA",
    "sg:tags":[
        "residential"
    ],
    "wof:name":"Rogojan Joana",
    "wof:placetype":"venue"
},
  "geometry": {"coordinates":[-122.196957,47.35548],"type":"Point"}
}