{
  "type": "Feature",
  "properties": {
    "addr:full":"2515 140th Ave NE Bellevue WA 98005",
    "addr:housenumber":"2515",
    "addr:postcode":"98005",
    "addr:street":"140Th Ave Ne",
    "iso:country":"US",
    "sg:address":"2515 140th Ave NE",
    "sg:city":"Bellevue",
    "sg:classifiers":[
        {
            "category":"Manufacturing",
            "subcategory":"Electronics",
            "type":"Manufacturing & Wholesale Goods"
        }
    ],
    "sg:phone":"+1 425 922 3867",
    "sg:postcode":"98005",
    "sg:province":"WA",
    "sg:tags":[
        "electronic",
        "component",
        "mfg"
    ],
    "wof:name":"Ernit LLC",
    "wof:placetype":"venue"
},
  "geometry": {"coordinates":[-122.153795,47.632911],"type":"Point"}
}