{
  "type": "Feature",
  "properties": {
    "addr:full":"25830 122nd Ave SE Kent WA 98030",
    "addr:housenumber":"25830",
    "addr:postcode":"98030",
    "addr:street":"122Nd Ave Se",
    "iso:country":"US",
    "sg:address":"25830 122nd Ave SE",
    "sg:city":"Kent",
    "sg:classifiers":[
        {
            "category":"Building & Trades",
            "subcategory":"Cleaning & Sanitation",
            "type":"Services"
        }
    ],
    "sg:phone":"+1 253 639 4687",
    "sg:postcode":"98030",
    "sg:province":"WA",
    "sg:tags":[
        "maintenance"
    ],
    "wof:name":"Best Way Cleaning Service",
    "wof:placetype":"venue"
},
  "geometry": {"coordinates":[-122.178833,47.369717],"type":"Point"}
}