{
  "type": "Feature",
  "properties": {
    "addr:full":"841 Central Ave N Suite C-124 Kent WA 98032",
    "addr:housenumber":"841",
    "addr:postcode":"98032",
    "addr:street":"Central Ave N Suite C-124",
    "iso:country":"US",
    "sg:address":"841 Central Ave N Suite C-124",
    "sg:city":"Kent",
    "sg:classifiers":[
        {
            "category":"Banks & Credit Unions",
            "subcategory":"Financial Services",
            "type":"Services"
        }
    ],
    "sg:phone":"+1 206 592 0755",
    "sg:postcode":"98032",
    "sg:province":"WA",
    "sg:tags":[
        "escrow"
    ],
    "wof:name":"NorthWest Escrow Services Corporation",
    "wof:placetype":"venue"
},
  "geometry": {"coordinates":[-122.231093,47.388665],"type":"Point"}
}