{
  "type": "Feature",
  "properties": {
    "addr:full":"132 W Division Ave Ephrata WA 98823",
    "addr:housenumber":"132",
    "addr:postcode":"98823",
    "addr:street":"W Division Ave",
    "iso:country":"US",
    "sg:address":"132 W Division Ave",
    "sg:city":"Ephrata",
    "sg:classifiers":[
        {
            "category":"Food & Beverages",
            "subcategory":"Liquor & Beverages",
            "type":"Retail Goods"
        }
    ],
    "sg:phone":"+1 509 754 4963",
    "sg:postcode":"98823",
    "sg:province":"WA",
    "wof:name":"Washington State Liquor Store",
    "wof:placetype":"venue"
},
  "geometry": {"coordinates":[-119.55126300000001,47.320413],"type":"Point"}
}