{
  "type": "Feature",
  "properties": {
    "addr:full":"18225 NE 76th St Redmond WA 98052",
    "addr:housenumber":"18225",
    "addr:postcode":"98052",
    "addr:street":"Ne 76Th St",
    "iso:country":"US",
    "sg:address":"18225 NE 76th St",
    "sg:city":"Redmond",
    "sg:classifiers":[
        {
            "category":"Manufacturing",
            "subcategory":"Aerospace",
            "type":"Manufacturing & Wholesale Goods"
        },
        {
            "category":"Manufacturing",
            "subcategory":"Musical Instruments",
            "type":"Manufacturing & Wholesale Goods"
        }
    ],
    "sg:phone":"+1 425 885 4353",
    "sg:postcode":"98052",
    "sg:province":"WA",
    "sg:tags":[
        "avionics",
        "supply",
        "equipment",
        "aircraft",
        "part",
        "nautical",
        "supplies-wholesale",
        "manufacturer"
    ],
    "wof:name":"Idd Aerospace",
    "wof:placetype":"venue"
},
  "geometry": {"coordinates":[-122.099609,47.672043],"type":"Point"}
}