{
  "type": "Feature",
  "properties": {
    "addr:full":"2204 N Water St Ellensburg WA 98926",
    "addr:housenumber":"2204",
    "addr:postcode":"98926",
    "addr:street":"N Water St",
    "iso:country":"US",
    "sg:address":"2204 N Water St",
    "sg:city":"Ellensburg",
    "sg:classifiers":[
        {
            "category":"Building & Trades",
            "subcategory":"Construction",
            "type":"Services"
        }
    ],
    "sg:phone":"+1 509 962 4648",
    "sg:postcode":"98926",
    "sg:province":"WA",
    "sg:tags":[
        "asbestos",
        "detection",
        "removal"
    ],
    "wof:name":"Pro Tek Services",
    "wof:placetype":"venue"
},
  "geometry": {"coordinates":[-120.550285,47.014164],"type":"Point"}
}