{
  "type": "Feature",
  "properties": {
    "addr:full":"14909 Union Ave SW Lakewood WA 98498",
    "addr:housenumber":"14909",
    "addr:postcode":"98498",
    "addr:street":"Union Ave Sw",
    "iso:country":"US",
    "sg:address":"14909 Union Ave SW",
    "sg:city":"Lakewood",
    "sg:classifiers":[
        {
            "category":"Building & Trades",
            "subcategory":"Locksmith",
            "type":"Services"
        }
    ],
    "sg:phone":"+1 253 414 1131",
    "sg:postcode":"98498",
    "sg:province":"WA",
    "sg:tags":[
        "key"
    ],
    "wof:name":"Emergency 1 Locksmith",
    "wof:placetype":"venue"
},
  "geometry": {"coordinates":[-122.551669,47.122692],"type":"Point"}
}