{
  "type": "Feature",
  "properties": {
    "addr:full":"5618 SW Admiral Way Seattle WA 98116",
    "addr:housenumber":"5618",
    "addr:postcode":"98116",
    "addr:street":"Sw Admiral Way",
    "iso:country":"US",
    "sg:address":"5618 SW Admiral Way",
    "sg:city":"Seattle",
    "sg:classifiers":[
        {
            "category":"Manufacturing",
            "subcategory":"Food",
            "type":"Manufacturing & Wholesale Goods"
        }
    ],
    "sg:phone":"+1 206 388 3880",
    "sg:postcode":"98116",
    "sg:province":"WA",
    "sg:tags":[
        "processing"
    ],
    "wof:name":"Dr Susanna's World Baby Foods",
    "wof:placetype":"venue"
},
  "geometry": {"coordinates":[-122.403795,47.577126],"type":"Point"}
}