{
  "type": "Feature",
  "properties": {
    "iso:country":"US",
    "sg:address":"2211 W Broadway Ave",
    "sg:city":"Spokane",
    "sg:classifiers":[
        {
            "category":"Organizations",
            "subcategory":"Religious Organization",
            "type":"Services"
        }
    ],
    "sg:phone":"+1 509 325 5441",
    "sg:postcode":"99201",
    "sg:province":"WA",
    "wof:name":"Sister Ministries",
    "wof:placetype":"venue"
},
  "geometry": {"coordinates":[-117.444676,47.664373],"type":"Point"}
}