{
  "type": "Feature",
  "properties": {
    "addr:full":"170 N Burlington Blvd Burlington WA 98233",
    "addr:housenumber":"170",
    "addr:postcode":"98233",
    "addr:street":"N Burlington Blvd",
    "iso:country":"US",
    "sg:address":"170 N Burlington Blvd",
    "sg:city":"Burlington",
    "sg:classifiers":[
        {
            "category":"Home & Garden",
            "subcategory":"Hardware",
            "type":"Retail Goods"
        }
    ],
    "sg:phone":"+1 360 755 0977",
    "sg:postcode":"98233",
    "sg:province":"WA",
    "sg:tags":[
        "nut",
        "bolt"
    ],
    "wof:name":"Pats General Store True Value",
    "wof:placetype":"venue"
},
  "geometry": {"coordinates":[-122.33551799999999,48.475772],"type":"Point"}
}