{
  "type": "Feature",
  "properties": {
    "addr:full":"620 Pacific Way Long Beach WA 98631",
    "addr:housenumber":"620",
    "addr:postcode":"98631",
    "addr:street":"Pacific Way",
    "iso:country":"US",
    "sg:address":"620 Pacific Way",
    "sg:city":"Long Beach",
    "sg:classifiers":[
        {
            "category":"Travel",
            "subcategory":"Hotels & Motels",
            "type":"Entertainment"
        }
    ],
    "sg:phone":"+1 360 642 3455",
    "sg:postcode":"98631",
    "sg:province":"WA",
    "sg:tags":[
        "operation",
        "book"
    ],
    "wof:name":"Whales Tale Motel",
    "wof:placetype":"venue"
},
  "geometry": {"coordinates":[-124.054604,46.348702],"type":"Point"}
}