{
  "type": "Feature",
  "properties": {
    "iso:country":"US",
    "sg:address":"8421 27th St W",
    "sg:city":"University Place",
    "sg:classifiers":[
        {
            "category":"Personal",
            "subcategory":"Beauty Salon",
            "type":"Services"
        }
    ],
    "sg:phone":"+1 253 460 0400",
    "sg:postcode":"98466",
    "sg:province":"WA",
    "sg:tags":[
        "manicuring"
    ],
    "wof:name":"D & V Nails",
    "wof:placetype":"venue"
},
  "geometry": {"coordinates":[-122.54837499999999,47.235297],"type":"Point"}
}