{
  "type": "Feature",
  "properties": {
    "addr:full":"2771 Hemlock St Bremerton WA 98310",
    "addr:housenumber":"2771",
    "addr:postcode":"98310",
    "addr:street":"Hemlock St",
    "iso:country":"US",
    "sg:address":"2771 Hemlock St",
    "sg:city":"Bremerton",
    "sg:classifiers":[
        {
            "category":"Health Services",
            "subcategory":"Doctor",
            "type":"Services"
        }
    ],
    "sg:phone":"+1 360 377 7634",
    "sg:postcode":"98310",
    "sg:province":"WA",
    "sg:tags":[
        "physician"
    ],
    "wof:name":"Cogen & Higley",
    "wof:placetype":"venue"
},
  "geometry": {"coordinates":[-122.62780600000001,47.583885],"type":"Point"}
}