{
  "type": "Feature",
  "properties": {
    "addr:full":"13916 94th Ave NE Kirkland WA 98034",
    "addr:housenumber":"13916",
    "addr:postcode":"98034",
    "addr:street":"94Th Ave Ne",
    "iso:country":"US",
    "sg:address":"13916 94th Ave NE",
    "sg:city":"Kirkland",
    "sg:classifiers":[
        {
            "category":"Real Estate",
            "subcategory":"Real Estate Operator",
            "type":"Services"
        }
    ],
    "sg:phone":"+1 425 820 7680",
    "sg:postcode":"98034",
    "sg:province":"WA",
    "sg:tags":[
        "building",
        "nonresidential"
    ],
    "wof:name":"Wls Properties Inc",
    "wof:placetype":"venue"
},
  "geometry": {"coordinates":[-122.214923,47.724773],"type":"Point"}
}