{
  "type": "Feature",
  "properties": {
    "addr:full":"39871 N Shore Dr Loon Lake WA 99148",
    "addr:housenumber":"39871",
    "addr:postcode":"99148",
    "addr:street":"N Shore Dr",
    "iso:country":"US",
    "sg:address":"39871 N Shore Dr",
    "sg:city":"Loon Lake",
    "sg:classifiers":[
        {
            "category":"Home & Garden",
            "subcategory":"Building Materials",
            "type":"Retail Goods"
        }
    ],
    "sg:phone":"+1 509 233 2605",
    "sg:postcode":"99148",
    "sg:province":"WA",
    "wof:name":"Windshield Doctor",
    "wof:placetype":"venue"
},
  "geometry": {"coordinates":[-117.625488,48.057711],"type":"Point"}
}