{
  "type": "Feature",
  "properties": {
    "iso:country":"US",
    "sg:address":"14720 NE 91st St",
    "sg:city":"Redmond",
    "sg:classifiers":[
        {
            "category":"Professional",
            "subcategory":"Business Services",
            "type":"Services"
        },
        {
            "category":"Wholesale",
            "subcategory":"Durable Goods & Equipment",
            "type":"Manufacturing & Wholesale Goods"
        }
    ],
    "sg:phone":"+1 425 881 2180",
    "sg:postcode":"98052",
    "sg:province":"WA",
    "sg:tags":[
        "motion",
        "production",
        "representative",
        "manufacturer"
    ],
    "wof:name":"Future Sales Inc",
    "wof:placetype":"venue"
},
  "geometry": {"coordinates":[-122.1459,47.683373],"type":"Point"}
}