{
  "type": "Feature",
  "properties": {
    "addr:full":"511 N 1st St Yakima WA 98901",
    "addr:housenumber":"511",
    "addr:postcode":"98901",
    "addr:street":"N 1St St",
    "iso:country":"US",
    "sg:address":"511 N 1st St",
    "sg:city":"Yakima",
    "sg:classifiers":[
        {
            "category":"Banks & Credit Unions",
            "subcategory":"Bank",
            "type":"Services"
        }
    ],
    "sg:phone":"+1 509 469 9572",
    "sg:postcode":"98901",
    "sg:province":"WA",
    "sg:tags":[
        "money",
        "transfer"
    ],
    "wof:name":"Dolex Dollar Express",
    "wof:placetype":"venue"
},
  "geometry": {"coordinates":[-120.50963,46.609635],"type":"Point"}
}