{
  "type": "Feature",
  "properties": {
    "addr:full":"1504 E Cambridge Ln Spokane WA 99203",
    "addr:housenumber":"1504",
    "addr:postcode":"99203",
    "addr:street":"E Cambridge Ln",
    "iso:country":"US",
    "sg:address":"1504 E Cambridge Ln",
    "sg:city":"Spokane",
    "sg:classifiers":[
        {
            "category":"Wholesale",
            "subcategory":"Groceries",
            "type":"Manufacturing & Wholesale Goods"
        }
    ],
    "sg:phone":"+1 509 747 5332",
    "sg:postcode":"99203",
    "sg:province":"WA",
    "wof:name":"Tobys Inc",
    "wof:placetype":"venue"
},
  "geometry": {"coordinates":[-117.389026,47.625252],"type":"Point"}
}