{
  "type": "Feature",
  "properties": {
    "iso:country":"US",
    "sg:address":"12600 SE 38th St",
    "sg:city":"Bellevue",
    "sg:classifiers":[
        {
            "category":"Health Services",
            "subcategory":"Doctor",
            "type":"Services"
        }
    ],
    "sg:phone":"+1 425 747 6640",
    "sg:postcode":"98006",
    "sg:province":"WA",
    "sg:tags":[
        "dentist"
    ],
    "wof:name":"Factoria Family Dentistry",
    "wof:placetype":"venue"
},
  "geometry": {"coordinates":[-122.171239,47.576933],"type":"Point"}
}