{
  "type": "Feature",
  "properties": {
    "iso:country":"US",
    "sg:address":"17226 SE 46th St",
    "sg:city":"Bellevue",
    "sg:classifiers":[
        {
            "category":"Professional",
            "type":"Services"
        }
    ],
    "sg:phone":"+1 425 957 1775",
    "sg:postcode":"98006",
    "sg:province":"WA",
    "wof:name":"My Sewing Room",
    "wof:placetype":"venue"
},
  "geometry": {"coordinates":[-122.10811,47.563702],"type":"Point"}
}