{
  "type": "Feature",
  "properties": {
    "addr:full":"80 Vista Dr Republic WA 99166",
    "addr:housenumber":"80",
    "addr:postcode":"99166",
    "addr:street":"Vista Dr",
    "iso:country":"US",
    "sg:address":"80 Vista Dr",
    "sg:city":"Republic",
    "sg:classifiers":[
        {
            "category":"Manufacturing",
            "subcategory":"Lumber",
            "type":"Manufacturing & Wholesale Goods"
        }
    ],
    "sg:phone":"+1 509 775 2208",
    "sg:postcode":"99166",
    "sg:province":"WA",
    "sg:tags":[
        "logging"
    ],
    "wof:name":"Wolf Camp Logging",
    "wof:placetype":"venue"
},
  "geometry": {"coordinates":[-118.706665,48.739625],"type":"Point"}
}