{
  "type": "Feature",
  "properties": {
    "addr:full":"9709 NE 139th St Kirkland WA 98034",
    "addr:housenumber":"9709",
    "addr:postcode":"98034",
    "addr:street":"Ne 139Th St",
    "iso:country":"US",
    "sg:address":"9709 NE 139th St",
    "sg:city":"Kirkland",
    "sg:classifiers":[
        {
            "category":"Food & Beverages",
            "subcategory":"Specialty",
            "type":"Retail Goods"
        }
    ],
    "sg:phone":"+1 425 823 7768",
    "sg:postcode":"98034",
    "sg:province":"WA",
    "sg:tags":[
        "supplement",
        "vitamin"
    ],
    "wof:name":"Cmp",
    "wof:placetype":"venue"
},
  "geometry": {"coordinates":[-122.21131699999999,47.725345],"type":"Point"}
}