{
  "type": "Feature",
  "properties": {
    "addr:full":"12062 Slater Ave NE Kirkland WA 98034",
    "addr:housenumber":"12062",
    "addr:postcode":"98034",
    "addr:street":"Slater Ave Ne",
    "iso:country":"US",
    "sg:address":"12062 Slater Ave NE",
    "sg:city":"Kirkland",
    "sg:classifiers":[
        {
            "category":"Real Estate",
            "subcategory":"Real Estate Operator",
            "type":"Services"
        }
    ],
    "sg:phone":"+1 425 820 0139",
    "sg:postcode":"98034",
    "sg:province":"WA",
    "sg:tags":[
        "apartment"
    ],
    "wof:name":"Chateau Creste Apartments",
    "wof:placetype":"venue"
},
  "geometry": {"coordinates":[-122.170998,47.709099],"type":"Point"}
}