{
  "type": "Feature",
  "properties": {
    "addr:full":"8661 S 208th St Kent WA 98031",
    "addr:housenumber":"8661",
    "addr:postcode":"98031",
    "addr:street":"S 208Th St",
    "iso:country":"US",
    "sg:address":"8661 S 208th St",
    "sg:city":"Kent",
    "sg:classifiers":[
        {
            "category":"Professional",
            "type":"Services"
        }
    ],
    "sg:phone":"+1 253 872 3750",
    "sg:postcode":"98031",
    "sg:province":"WA",
    "wof:name":"Trammell Pro Company",
    "wof:placetype":"venue"
},
  "geometry": {"coordinates":[-122.22503399999999,47.415592],"type":"Point"}
}