{
  "type": "Feature",
  "properties": {
    "iso:country":"US",
    "sg:address":"2226 Virginia Ave",
    "sg:city":"Everett",
    "sg:classifiers":[
        {
            "category":"Shopping",
            "subcategory":"Hobbies, Toys, & Games",
            "type":"Retail Goods"
        }
    ],
    "sg:phone":"+1 425 348 9858",
    "sg:postcode":"98201",
    "sg:province":"WA",
    "sg:tags":[
        "florist"
    ],
    "wof:name":"Wild Flower Cottage",
    "wof:placetype":"venue"
},
  "geometry": {"coordinates":[-122.197165,47.987429],"type":"Point"}
}