{
  "type": "Feature",
  "properties": {
    "addr:full":"15657 Yokeko Dr Anacortes WA 98221",
    "addr:housenumber":"15657",
    "addr:postcode":"98221",
    "addr:street":"Yokeko Dr",
    "iso:country":"US",
    "sg:address":"15657 Yokeko Dr",
    "sg:city":"Anacortes",
    "sg:classifiers":[
        {
            "category":"Professional",
            "type":"Services"
        },
        {
            "category":"Government",
            "subcategory":"Office",
            "type":"Public Place"
        }
    ],
    "sg:phone":"+1 360 588 1917",
    "sg:postcode":"98221",
    "sg:province":"WA",
    "sg:tags":[
        "salmon",
        "recovery",
        "preservation"
    ],
    "wof:name":"North West Chinook Recovery",
    "wof:placetype":"venue"
},
  "geometry": {"coordinates":[-122.615892,48.414977],"type":"Point"}
}