{
  "type": "Feature",
  "properties": {
    "addr:full":"15524 SE Mill Plain Blvd Ste 100 Vancouver WA 98684",
    "addr:postcode":"15524;98684",
    "addr:street":"Se Mill Plain Blvd Ste 100",
    "iso:country":"US",
    "sg:address":"15524 SE Mill Plain Blvd Ste 100",
    "sg:city":"Vancouver",
    "sg:classifiers":[
        {
            "category":"Real Estate",
            "subcategory":"Real Estate Services",
            "type":"Services"
        },
        {
            "category":"Real Estate",
            "subcategory":"Real Estate Agent",
            "type":"Services"
        }
    ],
    "sg:phone":"+1 360 695 9292",
    "sg:postcode":"98684",
    "sg:province":"WA",
    "sg:tags":[
        "buyer",
        "broker"
    ],
    "sg:website":"http://www.handrisrealty.com",
    "wof:name":"Handris Realty Co",
    "wof:placetype":"venue"
},
  "geometry": {"coordinates":[-122.512642,45.616452],"type":"Point"}
}