{
  "type": "Feature",
  "properties": {
    "iso:country":"US",
    "sg:address":"11814 NE 142nd Pl",
    "sg:city":"Kirkland",
    "sg:classifiers":[
        {
            "category":"Building & Trades",
            "subcategory":"Construction",
            "type":"Services"
        }
    ],
    "sg:phone":"+1 425 821 0383",
    "sg:postcode":"98034",
    "sg:province":"WA",
    "sg:tags":[
        "drywall",
        "contractor"
    ],
    "wof:name":"Camwal Inc",
    "wof:placetype":"venue"
},
  "geometry": {"coordinates":[-122.182013,47.729157],"type":"Point"}
}