{
  "type": "Feature",
  "properties": {
    "addr:full":"116 A Ave Conconully WA 98819",
    "addr:housenumber":"116 a",
    "addr:postcode":"98819",
    "addr:street":"Ave Conconully",
    "iso:country":"US",
    "sg:address":"116 A Ave",
    "sg:city":"Conconully",
    "sg:classifiers":[
        {
            "category":"Travel",
            "subcategory":"Hotels & Motels",
            "type":"Entertainment"
        }
    ],
    "sg:phone":"+1 509 826 0132",
    "sg:postcode":"98819",
    "sg:province":"WA",
    "wof:name":"Jack's Rv Park & Motel",
    "wof:placetype":"venue"
},
  "geometry": {"coordinates":[-119.749313,48.559538],"type":"Point"}
}