{
  "type": "Feature",
  "properties": {
    "addr:full":"22525 SE 64th Pl Issaquah WA 98027",
    "addr:postcode":"22525;98027",
    "addr:street":"Se 64Th Pl",
    "iso:country":"US",
    "sg:address":"22525 SE 64th Pl",
    "sg:city":"Issaquah",
    "sg:classifiers":[
        {
            "category":"Building & Trades",
            "subcategory":"Equipment Rental",
            "type":"Services"
        }
    ],
    "sg:phone":"+1 425 557 5920",
    "sg:postcode":"98027",
    "sg:province":"WA",
    "wof:name":"Northwest Corporate Leasing",
    "wof:placetype":"venue"
},
  "geometry": {"coordinates":[-122.03972899999999,47.544029],"type":"Point"}
}