{
  "type": "Feature",
  "properties": {
    "addr:full":"11719 103rd Ave NE Kirkland WA 98034",
    "addr:housenumber":"11719",
    "addr:postcode":"98034",
    "addr:street":"103Rd Ave Ne",
    "iso:country":"US",
    "sg:address":"11719 103rd Ave NE",
    "sg:city":"Kirkland",
    "sg:classifiers":[
        {
            "category":"Professional",
            "subcategory":"Research",
            "type":"Services"
        }
    ],
    "sg:phone":"+1 425 785 5584",
    "sg:postcode":"98034",
    "sg:province":"WA",
    "sg:tags":[
        "nonphysical",
        "commercial"
    ],
    "wof:name":"Definitive Market Research",
    "wof:placetype":"venue"
},
  "geometry": {"coordinates":[-122.20337600000001,47.705292],"type":"Point"}
}