{
  "type": "Feature",
  "properties": {
    "addr:full":"5325 13th Ave S Seattle WA 98108",
    "addr:housenumber":"5325",
    "addr:postcode":"98108",
    "addr:street":"13Th Ave S",
    "iso:country":"US",
    "sg:address":"5325 13th Ave S",
    "sg:city":"Seattle",
    "sg:classifiers":[
        {
            "category":"Building & Trades",
            "subcategory":"Construction",
            "type":"Services"
        }
    ],
    "sg:phone":"+1 206 852 3614",
    "sg:postcode":"98108",
    "sg:province":"WA",
    "sg:tags":[
        "ind",
        "painting",
        "contractor"
    ],
    "wof:name":"A Color Coat Painting Co",
    "wof:placetype":"venue"
},
  "geometry": {"coordinates":[-122.316209,47.55437],"type":"Point"}
}