{
  "type": "Feature",
  "properties": {
    "addr:full":"7270 W Mercer Way Mercer Island WA 98040",
    "addr:housenumber":"7270",
    "addr:postcode":"98040",
    "addr:street":"W Mercer Way",
    "iso:country":"US",
    "sg:address":"7270 W Mercer Way",
    "sg:city":"Mercer Island",
    "sg:classifiers":[
        {
            "category":"Banks & Credit Unions",
            "subcategory":"Financial Services",
            "type":"Services"
        }
    ],
    "sg:phone":"+1 206 232 6893",
    "sg:postcode":"98040",
    "sg:province":"WA",
    "sg:tags":[
        "management",
        "open",
        "investment"
    ],
    "wof:name":"Hardinge Company Inc",
    "wof:placetype":"venue"
},
  "geometry": {"coordinates":[-122.24005099999999,47.536899],"type":"Point"}
}