{
  "type": "Feature",
  "properties": {
    "addr:full":"12941 NE 147th Pl Woodinville WA 98072",
    "addr:housenumber":"12941",
    "addr:postcode":"98072",
    "addr:street":"Ne 147Th Pl",
    "iso:country":"US",
    "sg:address":"12941 NE 147th Pl",
    "sg:city":"Woodinville",
    "sg:classifiers":[
        {
            "category":"Health Services",
            "subcategory":"Doctor",
            "type":"Services"
        },
        {
            "category":"Health Services",
            "subcategory":"Hospital",
            "type":"Services"
        }
    ],
    "sg:phone":"+1 425 806 8830",
    "sg:postcode":"98072",
    "sg:province":"WA",
    "sg:tags":[
        "consultant",
        "medical",
        "practice",
        "nursing",
        "home"
    ],
    "wof:name":"Nbc Consultants Inc",
    "wof:placetype":"venue"
},
  "geometry": {"coordinates":[-122.16836000000001,47.735054],"type":"Point"}
}