{
  "type": "Feature",
  "properties": {
    "addr:full":"411 Oregon Way Longview WA 98632",
    "addr:housenumber":"411",
    "addr:postcode":"98632",
    "addr:street":"Oregon Way",
    "iso:country":"US",
    "sg:address":"411 Oregon Way",
    "sg:city":"Longview",
    "sg:classifiers":[
        {
            "category":"Professional",
            "subcategory":"Business Services",
            "type":"Services"
        }
    ],
    "sg:phone":"+1 360 577 8222",
    "sg:postcode":"98632",
    "sg:province":"WA",
    "wof:name":"North County Sales & Svc",
    "wof:placetype":"venue"
},
  "geometry": {"coordinates":[-122.94721,46.120286],"type":"Point"}
}