{
  "type": "Feature",
  "properties": {
    "addr:full":"1312 W 5th Ave Spokane WA 99204",
    "addr:housenumber":"1312",
    "addr:postcode":"99204",
    "addr:street":"W 5Th Ave",
    "iso:country":"US",
    "sg:address":"1312 W 5th Ave",
    "sg:city":"Spokane",
    "sg:classifiers":[
        {
            "category":"Professional",
            "subcategory":"Art Services",
            "type":"Services"
        }
    ],
    "sg:phone":"+1 509 747 4181",
    "sg:postcode":"99204",
    "sg:province":"WA",
    "sg:tags":[
        "commercial",
        "graphic",
        "design",
        "designer"
    ],
    "sg:website":"www.tshirtfetish.com",
    "wof:name":"Wild Bill Graphics",
    "wof:placetype":"venue"
},
  "geometry": {"coordinates":[-117.432303,47.651433],"type":"Point"}
}