{
  "type": "Feature",
  "properties": {
    "addr:full":"600 1st Ave Ste 430-A Seattle WA 98104",
    "addr:housenumber":"600",
    "addr:postcode":"98104",
    "addr:street":"1St Ave Ste 430-A",
    "iso:country":"US",
    "sg:address":"600 1st Ave Ste 430-A",
    "sg:city":"Seattle",
    "sg:classifiers":[
        {
            "category":"Health Services",
            "subcategory":"Clinic",
            "type":"Services"
        },
        {
            "category":"Professional",
            "subcategory":"Management & Consulting",
            "type":"Services"
        }
    ],
    "sg:phone":"+1 206 321 2887",
    "sg:postcode":"98104",
    "sg:province":"WA",
    "sg:tags":[
        "counseling",
        "life",
        "coach",
        "mental"
    ],
    "sg:website":"www.bestlives.com",
    "wof:name":"Christine Wylde, MA LMHC",
    "wof:placetype":"venue"
},
  "geometry": {"coordinates":[-122.334085,47.601726],"type":"Point"}
}