{
  "type": "Feature",
  "properties": {
    "addr:full":"19221 62nd Ave S Kent WA 98032",
    "addr:housenumber":"19221",
    "addr:postcode":"98032",
    "addr:street":"62Nd Ave S",
    "iso:country":"US",
    "sg:address":"19221 62nd Ave S",
    "sg:city":"Kent",
    "sg:classifiers":[
        {
            "category":"Communications",
            "subcategory":"Film & Video Production",
            "type":"Services"
        }
    ],
    "sg:phone":"+1 253 872 9640",
    "sg:postcode":"98032",
    "sg:province":"WA",
    "sg:tags":[
        "supply",
        "equipment",
        "cutting",
        "die"
    ],
    "wof:name":"Steel Rule Concepts",
    "wof:placetype":"venue"
},
  "geometry": {"coordinates":[-122.256783,47.431129],"type":"Point"}
}