{
  "type": "Feature",
  "properties": {
    "addr:full":"10831 Vancil Rd SE Yelm WA 98597",
    "addr:housenumber":"10831",
    "addr:postcode":"98597",
    "addr:street":"Vancil Rd Se Yelm",
    "iso:country":"US",
    "sg:address":"10831 Vancil Rd SE",
    "sg:city":"Yelm",
    "sg:classifiers":[
        {
            "category":"Sports & Exercise",
            "subcategory":"Race Track",
            "type":"Entertainment"
        }
    ],
    "sg:phone":"+1 360 458 7506",
    "sg:postcode":"98597",
    "sg:province":"WA",
    "sg:tags":[
        "operation",
        "racing",
        "or"
    ],
    "wof:name":"Edwards Racing",
    "wof:placetype":"venue"
},
  "geometry": {"coordinates":[-122.595511,46.931224],"type":"Point"}
}