{
  "type": "Feature",
  "properties": {
    "addr:full":"1820 Cornwall Ave Bellingham WA 98225",
    "addr:housenumber":"1820",
    "addr:postcode":"98225",
    "addr:street":"Cornwall Ave",
    "iso:country":"US",
    "sg:address":"1820 Cornwall Ave",
    "sg:city":"Bellingham",
    "sg:classifiers":[
        {
            "category":"Arts & Performance",
            "subcategory":"Dance",
            "type":"Entertainment"
        }
    ],
    "sg:phone":"+1 360 734 1595",
    "sg:postcode":"98225",
    "sg:province":"WA",
    "sg:tags":[
        "instruction",
        "dancing"
    ],
    "wof:name":"Dance Studio, The",
    "wof:placetype":"venue"
},
  "geometry": {"coordinates":[-122.47508999999999,48.753474],"type":"Point"}
}