{
  "type": "Feature",
  "properties": {
    "addr:full":"2771 152nd Ave NE Redmond WA 98052",
    "addr:housenumber":"2771",
    "addr:postcode":"98052",
    "addr:street":"152Nd Ave Ne",
    "iso:country":"US",
    "sg:address":"2771 152nd Ave NE",
    "sg:city":"Redmond",
    "sg:classifiers":[
        {
            "category":"Professional",
            "subcategory":"Computer Services",
            "type":"Services"
        }
    ],
    "sg:phone":"+1 425 883 7100",
    "sg:postcode":"98052",
    "sg:province":"WA",
    "sg:tags":[
        "programing",
        "custom"
    ],
    "wof:name":"Summit Software",
    "wof:placetype":"venue"
},
  "geometry": {"coordinates":[-122.137744,47.636632],"type":"Point"}
}