{
  "type": "Feature",
  "properties": {
    "addr:full":"425 W Walla Walla Hwy Colfax WA 99111",
    "addr:housenumber":"425",
    "addr:postcode":"99111",
    "addr:street":"W Walla Walla Hwy",
    "iso:country":"US",
    "sg:address":"425 W Walla Walla Hwy",
    "sg:city":"Colfax",
    "sg:classifiers":[
        {
            "category":"Autos & Motor Vehicles",
            "subcategory":"Auto Supplies",
            "type":"Retail Goods"
        },
        {
            "category":"Wholesale",
            "subcategory":"Electrical",
            "type":"Manufacturing & Wholesale Goods"
        },
        {
            "category":"Wholesale",
            "subcategory":"Auto Parts",
            "type":"Manufacturing & Wholesale Goods"
        }
    ],
    "sg:phone":"+1 509 397 4371",
    "sg:postcode":"99111",
    "sg:province":"WA",
    "sg:tags":[
        "battery",
        "automobile",
        "accessory",
        "equipment",
        "truck",
        "engines-supplies"
    ],
    "sg:website":"http://ad.doubleclick.net/clk;221862232;45455595;j?http://www.carquest.com/carquest/store_locator.html",
    "wof:name":"CARQUEST Auto Parts",
    "wof:placetype":"venue"
},
  "geometry": {"coordinates":[-117.371493,46.890966],"type":"Point"}
}