{
  "type": "Feature",
  "properties": {
    "iso:country":"US",
    "sg:address":"3811 E Sprague Ave",
    "sg:city":"Spokane",
    "sg:classifiers":[
        {
            "category":"Manufacturing",
            "subcategory":"Furniture",
            "type":"Manufacturing & Wholesale Goods"
        },
        {
            "category":"Home & Garden",
            "subcategory":"Home Furnishings",
            "type":"Retail Goods"
        }
    ],
    "sg:phone":"+1 509 534 8000",
    "sg:postcode":"99202",
    "sg:province":"WA",
    "sg:tags":[
        "venetian",
        "blind",
        "drapery",
        "mfg"
    ],
    "wof:name":"American Drapery Blind & Crpt",
    "wof:placetype":"venue"
},
  "geometry": {"coordinates":[-117.35319,47.657378],"type":"Point"}
}