{
  "type": "Feature",
  "properties": {
    "addr:full":"3401 Big Alkali Rd Hay WA 99136",
    "addr:housenumber":"3401",
    "addr:postcode":"99136",
    "addr:street":"Big Alkali Rd",
    "iso:country":"US",
    "sg:address":"3401 Big Alkali Rd",
    "sg:city":"Hay",
    "sg:phone":"+1 509 549 3329",
    "sg:postcode":"99136",
    "sg:province":"WA",
    "sg:tags":[
        "farm",
        "wheat"
    ],
    "wof:name":"Lucky Valley Inc",
    "wof:placetype":"venue"
},
  "geometry": {"coordinates":[-117.909649,46.679683],"type":"Point"}
}