{
  "type": "Feature",
  "properties": {
    "iso:country":"US",
    "sg:address":"18009 108th Ave NE",
    "sg:city":"Bothell",
    "sg:classifiers":[
        {
            "category":"Professional",
            "subcategory":"Art Services",
            "type":"Services"
        }
    ],
    "sg:phone":"+1 425 398 8230",
    "sg:postcode":"98011",
    "sg:province":"WA",
    "sg:tags":[
        "graphic",
        "design"
    ],
    "wof:name":"Leslie C Laas Designs",
    "wof:placetype":"venue"
},
  "geometry": {"coordinates":[-122.196381,47.758956],"type":"Point"}
}