{
  "type": "Feature",
  "properties": {
    "addr:full":"16817 Smokey Point Blvd Arlington WA 98223",
    "addr:housenumber":"16817",
    "addr:postcode":"98223",
    "addr:street":"Smokey Point Blvd",
    "iso:country":"US",
    "sg:address":"16817 Smokey Point Blvd",
    "sg:city":"Arlington",
    "sg:classifiers":[
        {
            "category":"Insurance",
            "subcategory":"Hazard Insurance",
            "type":"Services"
        },
        {
            "category":"Insurance",
            "subcategory":"Insurance Agent",
            "type":"Services"
        },
        {
            "category":"Insurance",
            "subcategory":"Life Insurance",
            "type":"Services"
        },
        {
            "category":"Insurance",
            "subcategory":"Title Insurance",
            "type":"Services"
        }
    ],
    "sg:phone":"+1 360 658 5532",
    "sg:postcode":"98223",
    "sg:province":"WA",
    "sg:tags":[
        "auto",
        "commercial",
        "business",
        "homeowner"
    ],
    "sg:website":"http://www.farmers.com",
    "wof:name":"Robert R Curtis Insurance Agency - Farmers Insurance",
    "wof:placetype":"venue"
},
  "geometry": {"coordinates":[-122.18293,48.148809],"type":"Point"}
}