{
  "type": "Feature",
  "properties": {
    "addr:full":"107 E Holland Ave Spokane WA 99218",
    "addr:housenumber":"107",
    "addr:postcode":"99218",
    "addr:street":"E Holland Ave",
    "iso:country":"US",
    "sg:address":"107 E Holland Ave",
    "sg:city":"Spokane",
    "sg:classifiers":[
        {
            "category":"Health Services",
            "subcategory":"Doctor",
            "type":"Services"
        }
    ],
    "sg:phone":"+1 509 466 3960",
    "sg:postcode":"99218",
    "sg:province":"WA",
    "sg:tags":[
        "medicine",
        "physician",
        "practice",
        "surgeons",
        "family"
    ],
    "sg:website":"http://www.hartfamilymedicinespokane.com",
    "wof:name":"Hart Family Medicine PLLC",
    "wof:placetype":"venue"
},
  "geometry": {"coordinates":[-117.40867299999999,47.743938],"type":"Point"}
}