{
  "type": "Feature",
  "properties": {
    "addr:full":"13898 Chinook Cir NW Bremerton WA 98312",
    "addr:housenumber":"13898",
    "addr:postcode":"98312",
    "addr:street":"Chinook Cir Nw",
    "iso:country":"US",
    "sg:address":"13898 Chinook Cir NW",
    "sg:city":"Bremerton",
    "sg:classifiers":[
        {
            "category":"Professional",
            "type":"Services"
        }
    ],
    "sg:phone":"+1 360 830 4947",
    "sg:postcode":"98312",
    "sg:province":"WA",
    "sg:tags":[
        "establishment"
    ],
    "wof:name":"Bluestar Inc",
    "wof:placetype":"venue"
},
  "geometry": {"coordinates":[-122.836108,47.598188],"type":"Point"}
}