{
  "type": "Feature",
  "properties": {
    "addr:full":"13431 Solberg Rd SE Yelm WA 98597",
    "addr:postcode":"13431;98597",
    "addr:street":"Solberg Rd Se Yelm",
    "iso:country":"US",
    "sg:address":"13431 Solberg Rd SE",
    "sg:city":"Yelm",
    "sg:classifiers":[
        {
            "category":"Farming",
            "subcategory":"Livestock Farm",
            "type":"Manufacturing & Wholesale Goods"
        }
    ],
    "sg:phone":"+1 360 458 5251",
    "sg:postcode":"98597",
    "sg:province":"WA",
    "sg:tags":[
        "beef",
        "feedlot",
        "cattle"
    ],
    "wof:name":"Morton A Kimball",
    "wof:placetype":"venue"
},
  "geometry": {"coordinates":[-122.618067,46.891857],"type":"Point"}
}