{
  "type": "Feature",
  "properties": {
    "addr:full":"9122 S Tacoma Way Tacoma WA 98499",
    "addr:housenumber":"9122",
    "addr:postcode":"98499",
    "addr:street":"S Tacoma Way",
    "iso:country":"US",
    "sg:address":"9122 S Tacoma Way",
    "sg:city":"Tacoma",
    "sg:classifiers":[
        {
            "category":"Retail",
            "subcategory":"Portrait Studio",
            "type":"Services"
        }
    ],
    "sg:phone":"+1 253 582 5795",
    "sg:postcode":"98499",
    "sg:province":"WA",
    "sg:tags":[
        "photographer"
    ],
    "wof:name":"Pro Photo Studio",
    "wof:placetype":"venue"
},
  "geometry": {"coordinates":[-122.483825,47.174096],"type":"Point"}
}