{
  "type": "Feature",
  "properties": {
    "addr:full":"1060 State Ave Marysville WA 98270",
    "addr:housenumber":"1060",
    "addr:postcode":"98270",
    "addr:street":"State Ave",
    "iso:country":"US",
    "sg:address":"1060 State Ave",
    "sg:city":"Marysville",
    "sg:classifiers":[
        {
            "category":"Personal",
            "type":"Services"
        },
        {
            "category":"Personal",
            "subcategory":"Tattoo Parlor",
            "type":"Services"
        }
    ],
    "sg:phone":"+1 360 651 0866",
    "sg:postcode":"98270",
    "sg:province":"WA",
    "sg:tags":[
        "tattooing"
    ],
    "wof:name":"Electra Tattoo",
    "wof:placetype":"venue"
},
  "geometry": {"coordinates":[-122.176852,48.060348],"type":"Point"}
}