{
  "type": "Feature",
  "properties": {
    "addr:full":"4630 Oregon Way Clayton WA 99110",
    "addr:housenumber":"4630",
    "addr:postcode":"99110",
    "addr:street":"Oregon Way",
    "iso:country":"US",
    "sg:address":"4630 Oregon Way",
    "sg:city":"Clayton",
    "sg:classifiers":[
        {
            "category":"Home & Garden",
            "subcategory":"Furniture",
            "type":"Retail Goods"
        }
    ],
    "sg:phone":"+1 509 939 3860",
    "sg:postcode":"99110",
    "sg:province":"WA",
    "sg:tags":[
        "store"
    ],
    "wof:name":"Rustic Creations Inc",
    "wof:placetype":"venue"
},
  "geometry": {"coordinates":[-117.56359999999999,48.033402],"type":"Point"}
}