{
  "type": "Feature",
  "properties": {
    "addr:full":"13709 NE 42nd Ave Vancouver WA 98686",
    "addr:housenumber":"13709",
    "addr:postcode":"98686",
    "addr:street":"Ne 42Nd Ave",
    "iso:country":"US",
    "sg:address":"13709 NE 42nd Ave",
    "sg:city":"Vancouver",
    "sg:classifiers":[
        {
            "category":"Manufacturing",
            "subcategory":"Chemicals & Compounds",
            "type":"Manufacturing & Wholesale Goods"
        }
    ],
    "sg:phone":"+1 360 574 7745",
    "sg:postcode":"98686",
    "sg:province":"WA",
    "sg:tags":[
        "grocery"
    ],
    "wof:name":"Conopco Inc",
    "wof:placetype":"venue"
},
  "geometry": {"coordinates":[-122.629132,45.722109],"type":"Point"}
}