{
  "type": "Feature",
  "properties": {
    "addr:full":"22105 SE 20th St Sammamish WA 98075",
    "addr:postcode":"22105;98075",
    "addr:street":"Se 20Th St",
    "iso:country":"US",
    "sg:address":"22105 SE 20th St",
    "sg:city":"Sammamish",
    "sg:classifiers":[
        {
            "category":"Sports & Exercise",
            "subcategory":"Gym",
            "type":"Entertainment"
        }
    ],
    "sg:phone":"+1 425 241 1122",
    "sg:postcode":"98075",
    "sg:province":"WA",
    "sg:tags":[
        "fitness",
        "physical",
        "facility"
    ],
    "wof:name":"Ultimate Kids Activity Center",
    "wof:placetype":"venue"
},
  "geometry": {"coordinates":[-122.043256,47.591837],"type":"Point"}
}