{
  "type": "Feature",
  "properties": {
    "addr:full":"16111 N Yale Rd Colbert WA 99005",
    "addr:housenumber":"16111",
    "addr:postcode":"99005",
    "addr:street":"N Yale Rd Colbert",
    "iso:country":"US",
    "sg:address":"16111 N Yale Rd",
    "sg:city":"Colbert",
    "sg:classifiers":[
        {
            "category":"Building & Trades",
            "subcategory":"Construction",
            "type":"Services"
        }
    ],
    "sg:phone":"+1 509 238 2116",
    "sg:postcode":"99005",
    "sg:province":"WA",
    "sg:tags":[
        "house"
    ],
    "wof:name":"Phase 2 Construction Inc",
    "wof:placetype":"venue"
},
  "geometry": {"coordinates":[-117.346892,47.803744],"type":"Point"}
}