{
  "type": "Feature",
  "properties": {
    "addr:full":"2810 216th Ave SE Sammamish WA 98075",
    "addr:housenumber":"2810",
    "addr:postcode":"98075",
    "addr:street":"216Th Ave Se",
    "iso:country":"US",
    "sg:address":"2810 216th Ave SE",
    "sg:city":"Sammamish",
    "sg:classifiers":[
        {
            "category":"Personal",
            "type":"Services"
        }
    ],
    "sg:phone":"+1 425 313 5600",
    "sg:postcode":"98075",
    "sg:province":"WA",
    "wof:name":"Premiere Nannies Inc",
    "wof:placetype":"venue"
},
  "geometry": {"coordinates":[-122.051489,47.582842],"type":"Point"}
}