{
  "type": "Feature",
  "properties": {
    "addr:full":"1050 168th Ave SE Bellevue WA 98008",
    "addr:housenumber":"1050",
    "addr:postcode":"98008",
    "addr:street":"168Th Ave Se",
    "iso:country":"US",
    "sg:address":"1050 168th Ave SE",
    "sg:city":"Bellevue",
    "sg:classifiers":[
        {
            "category":"Shopping",
            "subcategory":"Florist",
            "type":"Retail Goods"
        }
    ],
    "sg:phone":"+1 425 603 0612",
    "sg:postcode":"98008",
    "sg:province":"WA",
    "wof:name":"Bellflowers",
    "wof:placetype":"venue"
},
  "geometry": {"coordinates":[-122.116232,47.60094],"type":"Point"}
}