{
  "type": "Feature",
  "properties": {
    "addr:full":"315 N 85th Street Seattle WA 98103",
    "addr:housenumber":"315",
    "addr:postcode":"98103",
    "addr:street":"N 85Th Street",
    "iso:country":"US",
    "sg:address":"315 N 85th Street",
    "sg:city":"Seattle",
    "sg:classifiers":[
        {
            "category":"Retail",
            "subcategory":"Repair Shop",
            "type":"Services"
        },
        {
            "category":"Building & Trades",
            "subcategory":"Construction",
            "type":"Services"
        },
        {
            "category":"Home & Garden",
            "subcategory":"Furniture",
            "type":"Retail Goods"
        }
    ],
    "sg:phone":"+1 206 297 1884",
    "sg:postcode":"98103",
    "sg:province":"WA",
    "sg:tags":[
        "interior",
        "reupholstery",
        "design",
        "store"
    ],
    "sg:website":"www.joslinupholstery.com",
    "wof:name":"Joslin Upholstery & Interior",
    "wof:placetype":"venue"
},
  "geometry": {"coordinates":[-122.354809,47.690698],"type":"Point"}
}