{
  "type": "Feature",
  "properties": {
    "iso:country":"US",
    "sg:address":"1215 E Sprague Ave",
    "sg:city":"Spokane",
    "sg:classifiers":[
        {
            "category":"Manufacturing",
            "subcategory":"Printing",
            "type":"Manufacturing & Wholesale Goods"
        }
    ],
    "sg:phone":"+1 509 535 1595",
    "sg:postcode":"99202",
    "sg:province":"WA",
    "sg:tags":[
        "publishing"
    ],
    "wof:name":"Aj Printing",
    "wof:placetype":"venue"
},
  "geometry": {"coordinates":[-117.38995,47.657289],"type":"Point"}
}