{
  "type": "Feature",
  "properties": {
    "addr:full":"12815 120th Ave NE Ste C Kirkland WA 98034",
    "addr:housenumber":"12815",
    "addr:postcode":"98034",
    "addr:street":"120Th Ave Ne Ste C",
    "iso:country":"US",
    "sg:address":"12815 120th Ave NE Ste C",
    "sg:city":"Kirkland",
    "sg:classifiers":[
        {
            "category":"Health Services",
            "subcategory":"Doctor",
            "type":"Services"
        }
    ],
    "sg:phone":"+1 425 821 6363",
    "sg:postcode":"98034",
    "sg:province":"WA",
    "sg:tags":[
        "dermatologist"
    ],
    "sg:website":"www.lakewashingtondermatology.com",
    "wof:name":"Susan H Kim, MD",
    "wof:placetype":"venue"
},
  "geometry": {"coordinates":[-122.18153,47.715273],"type":"Point"}
}