{
  "type": "Feature",
  "properties": {
    "iso:country":"US",
    "sg:address":"6349 Garcia Blvd",
    "sg:city":"Tacoma",
    "sg:classifiers":[
        {
            "category":"Social Services",
            "type":"Services"
        }
    ],
    "sg:phone":"+1 253 964 3039",
    "sg:postcode":"98433",
    "sg:province":"WA",
    "sg:tags":[
        "child",
        "family",
        "care"
    ],
    "wof:name":"Miss Melindas Daycare",
    "wof:placetype":"venue"
},
  "geometry": {"coordinates":[-122.564311,47.104504],"type":"Point"}
}