{
  "type": "Feature",
  "properties": {
    "addr:full":"16101 NE 87th St Redmond WA 98052",
    "addr:housenumber":"16101",
    "addr:postcode":"98052",
    "addr:street":"Ne 87Th St",
    "iso:country":"US",
    "sg:address":"16101 NE 87th St",
    "sg:city":"Redmond",
    "sg:classifiers":[
        {
            "category":"Shopping",
            "subcategory":"Bicycles & Sporting Goods",
            "type":"Retail Goods"
        },
        {
            "category":"Shopping",
            "subcategory":"Shoes",
            "type":"Retail Goods"
        }
    ],
    "sg:phone":"+1 425 882 1456",
    "sg:postcode":"98052",
    "sg:province":"WA",
    "sg:tags":[
        "store"
    ],
    "sg:website":"www.athleticsupply.com",
    "wof:name":"Athletic Supply",
    "wof:placetype":"venue"
},
  "geometry": {"coordinates":[-122.12599899999999,47.679699],"type":"Point"}
}