{
  "type": "Feature",
  "properties": {
    "addr:full":"2003 W Dravus St Seattle WA 98199",
    "addr:housenumber":"2003",
    "addr:postcode":"98199",
    "addr:street":"W Dravus St",
    "iso:country":"US",
    "sg:address":"2003 W Dravus St",
    "sg:city":"Seattle",
    "sg:classifiers":[
        {
            "category":"Building & Trades",
            "subcategory":"Locksmith",
            "type":"Services"
        }
    ],
    "sg:phone":"+1 206 212 1509",
    "sg:postcode":"98199",
    "sg:province":"WA",
    "sg:tags":[
        "key"
    ],
    "wof:name":"Locksmith Around the Clock Seattle",
    "wof:placetype":"venue"
},
  "geometry": {"coordinates":[-122.38200999999999,47.648313],"type":"Point"}
}