{
  "type": "Feature",
  "properties": {
    "addr:full":"9951 Mickelberry Rd NW Silverdale WA 98383",
    "addr:housenumber":"9951",
    "addr:postcode":"98383",
    "addr:street":"Mickelberry Rd Nw",
    "iso:country":"US",
    "sg:address":"9951 Mickelberry Rd NW",
    "sg:city":"Silverdale",
    "sg:classifiers":[
        {
            "category":"Health Services",
            "subcategory":"Doctor",
            "type":"Services"
        }
    ],
    "sg:phone":"+1 360 692 7318",
    "sg:postcode":"98383",
    "sg:province":"WA",
    "sg:tags":[
        "physician",
        "surgeon"
    ],
    "wof:name":"Olympic Dermatology",
    "wof:placetype":"venue"
},
  "geometry": {"coordinates":[-122.682388,47.657685],"type":"Point"}
}