{
  "type": "Feature",
  "properties": {
    "addr:full":"5000 25th Ave NE Suite 8306 Seattle WA 98105",
    "addr:housenumber":"5000",
    "addr:postcode":"98105",
    "addr:street":"25Th Ave Ne Suite 8306",
    "iso:country":"US",
    "sg:address":"5000 25th Ave NE Suite 8306",
    "sg:city":"Seattle",
    "sg:classifiers":[
        {
            "category":"Professional",
            "subcategory":"Research",
            "type":"Services"
        },
        {
            "category":"Professional",
            "subcategory":"Advertising",
            "type":"Services"
        },
        {
            "category":"Professional",
            "subcategory":"Computer Services",
            "type":"Services"
        }
    ],
    "sg:phone":"+1 206 569 5699",
    "sg:postcode":"98105",
    "sg:province":"WA",
    "sg:tags":[
        "web",
        "consultant",
        "marketing",
        "site",
        "analysis",
        "hosting",
        "design",
        "internet",
        "market"
    ],
    "sg:website":"http://www.KaisoSolutions.com",
    "wof:name":"Kaiso Solutions - Seattle Web Design",
    "wof:placetype":"venue"
},
  "geometry": {"coordinates":[-122.300765,47.665294],"type":"Point"}
}