{
  "type": "Feature",
  "properties": {
    "iso:country":"US",
    "sg:address":"12214 237th Avenue Ct E",
    "sg:city":"Buckley",
    "sg:classifiers":[
        {
            "category":"Building & Trades",
            "subcategory":"Construction",
            "type":"Services"
        }
    ],
    "sg:phone":"+1 360 897 6358",
    "sg:postcode":"98321",
    "sg:province":"WA",
    "sg:tags":[
        "house"
    ],
    "wof:name":"Petersons Home Repair",
    "wof:placetype":"venue"
},
  "geometry": {"coordinates":[-122.112793,47.145141],"type":"Point"}
}