{
  "type": "Feature",
  "properties": {
    "addr:full":"5016 Rainier Avenue S Seattle WA 98118",
    "addr:housenumber":"5016",
    "addr:postcode":"98118",
    "addr:street":"Rainier Avenue S",
    "iso:country":"US",
    "sg:address":"5016 Rainier Avenue S",
    "sg:city":"Seattle",
    "sg:classifiers":[
        {
            "category":"Building & Trades",
            "subcategory":"Locksmith",
            "type":"Services"
        }
    ],
    "sg:phone":"+1 206 722 5414",
    "sg:postcode":"98118",
    "sg:province":"WA",
    "sg:tags":[
        "key"
    ],
    "wof:name":"0 Number Number Number Number 0 0 24 Hour Locksmith",
    "wof:placetype":"venue"
},
  "geometry": {"coordinates":[-122.28444500000001,47.556593],"type":"Point"}
}