{
  "type": "Feature",
  "properties": {
    "addr:full":"700 Lindberg Ln Moses Lake WA 98837",
    "addr:housenumber":"700",
    "addr:postcode":"98837",
    "addr:street":"Lindberg Ln",
    "iso:country":"US",
    "sg:address":"700 Lindberg Ln",
    "sg:city":"Moses Lake",
    "sg:classifiers":[
        {
            "category":"Education",
            "subcategory":"School",
            "type":"Public Place"
        }
    ],
    "sg:phone":"+1 509 766 2655",
    "sg:postcode":"98837",
    "sg:province":"WA",
    "wof:name":"Larson Heights Elementary Schl",
    "wof:placetype":"venue"
},
  "geometry": {"coordinates":[-119.324601,47.167021],"type":"Point"}
}