{
  "type": "Feature",
  "properties": {
    "iso:country":"US",
    "sg:address":"16495 NE 74th St",
    "sg:city":"Redmond",
    "sg:classifiers":[
        {
            "category":"Wholesale",
            "subcategory":"Meat",
            "type":"Manufacturing & Wholesale Goods"
        }
    ],
    "sg:phone":"+1 425 885 0346",
    "sg:postcode":"98052",
    "sg:province":"WA",
    "wof:name":"Hickory Farms Inc",
    "wof:placetype":"venue"
},
  "geometry": {"coordinates":[-122.119716,47.670277],"type":"Point"}
}