{
  "type": "Feature",
  "properties": {
    "addr:full":"25101 Pacific Hwy S Kent WA 98032",
    "addr:housenumber":"25101",
    "addr:postcode":"98032",
    "addr:street":"Pacific Hwy S",
    "iso:country":"US",
    "sg:address":"25101 Pacific Hwy S",
    "sg:city":"Kent",
    "sg:classifiers":[
        {
            "category":"Autos & Motor Vehicles",
            "subcategory":"Auto Supplies",
            "type":"Retail Goods"
        }
    ],
    "sg:phone":"+1 253 941 8185",
    "sg:postcode":"98032",
    "sg:province":"WA",
    "wof:name":"Les Schwab Tires",
    "wof:placetype":"venue"
},
  "geometry": {"coordinates":[-122.30001300000001,47.376066],"type":"Point"}
}