{
  "type": "Feature",
  "properties": {
    "addr:full":"2707 NE Blakeley St Seattle WA 98105",
    "addr:housenumber":"2707",
    "addr:postcode":"98105",
    "addr:street":"Ne Blakeley St",
    "iso:country":"US",
    "sg:address":"2707 NE Blakeley St",
    "sg:city":"Seattle",
    "sg:classifiers":[
        {
            "category":"Professional",
            "subcategory":"Computer Services",
            "type":"Services"
        }
    ],
    "sg:phone":"+1 206 523 4152",
    "sg:postcode":"98105",
    "sg:province":"WA",
    "sg:tags":[
        "software"
    ],
    "wof:name":"Omni Group The",
    "wof:placetype":"venue"
},
  "geometry": {"coordinates":[-122.296835,47.665884],"type":"Point"}
}