{
  "type": "Feature",
  "properties": {
    "iso:country":"US",
    "sg:address":"200 Tennessee Rd",
    "sg:city":"Winlock",
    "sg:classifiers":[
        {
            "category":"Personal",
            "type":"Services"
        }
    ],
    "sg:phone":"+1 360 785 3745",
    "sg:postcode":"98596",
    "sg:province":"WA",
    "wof:name":"Samuel Boyd Blomgren",
    "wof:placetype":"venue"
},
  "geometry": {"coordinates":[-122.949465,46.507035],"type":"Point"}
}