{
  "type": "Feature",
  "properties": {
    "addr:full":"4207 Wheaton Way Bremerton WA 98310",
    "addr:housenumber":"4207",
    "addr:postcode":"98310",
    "addr:street":"Wheaton Way",
    "iso:country":"US",
    "sg:address":"4207 Wheaton Way",
    "sg:city":"Bremerton",
    "sg:classifiers":[
        {
            "category":"Home & Garden",
            "subcategory":"Home Furnishings",
            "type":"Retail Goods"
        }
    ],
    "sg:phone":"+1 360 373 4631",
    "sg:postcode":"98310",
    "sg:province":"WA",
    "sg:tags":[
        "stove",
        "wood",
        "burning"
    ],
    "wof:name":"Northwest Fireplace & Gas Syst",
    "wof:placetype":"venue"
},
  "geometry": {"coordinates":[-122.628917,47.606848],"type":"Point"}
}