{
  "type": "Feature",
  "properties": {
    "addr:full":"2321 E Winger Rd Spokane WA 99208",
    "addr:housenumber":"2321",
    "addr:postcode":"99208",
    "addr:street":"E Winger Rd",
    "iso:country":"US",
    "sg:address":"2321 E Winger Rd",
    "sg:city":"Spokane",
    "sg:classifiers":[
        {
            "category":"Professional",
            "subcategory":"Computer Services",
            "type":"Services"
        }
    ],
    "sg:phone":"+1 509 467 0414",
    "sg:postcode":"99208",
    "sg:province":"WA",
    "sg:tags":[
        "software",
        "programing",
        "custom"
    ],
    "wof:name":"Robert F Parks Computer Consult",
    "wof:placetype":"venue"
},
  "geometry": {"coordinates":[-117.375754,47.780122],"type":"Point"}
}