{
  "type": "Feature",
  "properties": {
    "addr:full":"20032 82nd Ave W Edmonds WA 98026",
    "addr:housenumber":"20032",
    "addr:postcode":"98026",
    "addr:street":"82Nd Ave W",
    "iso:country":"US",
    "sg:address":"20032 82nd Ave W",
    "sg:city":"Edmonds",
    "sg:classifiers":[
        {
            "category":"Building & Trades",
            "subcategory":"Electrical",
            "type":"Services"
        }
    ],
    "sg:phone":"+1 425 774 3929",
    "sg:postcode":"98026",
    "sg:province":"WA",
    "sg:tags":[
        "industrial",
        "electrician",
        "contractors-commercial",
        "electric"
    ],
    "wof:name":"Blue Ribbon Electric Inc",
    "wof:placetype":"venue"
},
  "geometry": {"coordinates":[-122.344007,47.81742],"type":"Point"}
}