{
  "type": "Feature",
  "properties": {
    "addr:full":"20814 Bulson Rd Mt Vernon WA 98274",
    "addr:postcode":"20814;98274",
    "addr:street":"Bulson Rd",
    "iso:country":"US",
    "sg:address":"20814 Bulson Rd",
    "sg:city":"Mt Vernon",
    "sg:classifiers":[
        {
            "category":"Manufacturing",
            "subcategory":"Retail Goods",
            "type":"Manufacturing & Wholesale Goods"
        }
    ],
    "sg:phone":"+1 360 445 2892",
    "sg:postcode":"98274",
    "sg:province":"WA",
    "sg:tags":[
        "manufacturer"
    ],
    "wof:name":"J T Mfg",
    "wof:placetype":"venue"
},
  "geometry": {"coordinates":[-122.312726,48.343723],"type":"Point"}
}