{
  "type": "Feature",
  "properties": {
    "addr:full":"304 Crimmins Rd Castle Rock WA 98611",
    "addr:housenumber":"304",
    "addr:postcode":"98611",
    "addr:street":"Crimmins Rd",
    "iso:country":"US",
    "sg:address":"304 Crimmins Rd",
    "sg:city":"Castle Rock",
    "sg:classifiers":[
        {
            "category":"Farming",
            "subcategory":"Poultry Farm",
            "type":"Manufacturing & Wholesale Goods"
        }
    ],
    "sg:phone":"+1 360 274 7544",
    "sg:postcode":"98611",
    "sg:province":"WA",
    "sg:tags":[
        "chicken"
    ],
    "wof:name":"Crimmins Poultry Farm",
    "wof:placetype":"venue"
},
  "geometry": {"coordinates":[-122.989439,46.252527],"type":"Point"}
}