{
  "type": "Feature",
  "properties": {
    "addr:full":"904 N 4th Ave Walla Walla WA 99362",
    "addr:housenumber":"904",
    "addr:postcode":"99362",
    "addr:street":"N 4Th Ave",
    "iso:country":"US",
    "sg:address":"904 N 4th Ave",
    "sg:city":"Walla Walla",
    "sg:classifiers":[
        {
            "category":"Building & Trades",
            "subcategory":"Plumbing",
            "type":"Services"
        }
    ],
    "sg:phone":"+1 509 525 4868",
    "sg:postcode":"99362",
    "sg:province":"WA",
    "sg:tags":[
        "air",
        "heating",
        "refrigeration",
        "conditioning",
        "contractor"
    ],
    "wof:name":"Blue Mountain Refrigeration",
    "wof:placetype":"venue"
},
  "geometry": {"coordinates":[-118.345906,46.075527],"type":"Point"}
}