{
  "type": "Feature",
  "properties": {
    "addr:full":"609 N Western Ave Wenatchee WA 98801",
    "addr:housenumber":"609",
    "addr:postcode":"98801",
    "addr:street":"N Western Ave",
    "iso:country":"US",
    "sg:address":"609 N Western Ave",
    "sg:city":"Wenatchee",
    "sg:classifiers":[
        {
            "category":"Organizations",
            "subcategory":"Religious Organization",
            "type":"Services"
        }
    ],
    "sg:phone":"+1 509 663 6926",
    "sg:postcode":"98801",
    "sg:province":"WA",
    "wof:name":"Community Svc Center",
    "wof:placetype":"venue"
},
  "geometry": {"coordinates":[-120.346136,47.430996],"type":"Point"}
}