{
  "type": "Feature",
  "properties": {
    "addr:full":"8415 Maple St SW Lakewood WA 98498",
    "addr:housenumber":"8415",
    "addr:postcode":"98498",
    "addr:street":"Maple St Sw",
    "iso:country":"US",
    "sg:address":"8415 Maple St SW",
    "sg:city":"Lakewood",
    "sg:classifiers":[
        {
            "category":"Organizations",
            "subcategory":"Religious Organization",
            "type":"Services"
        }
    ],
    "sg:phone":"+1 253 584 1864",
    "sg:postcode":"98498",
    "sg:province":"WA",
    "sg:tags":[
        "church"
    ],
    "wof:name":"Tillicum Baptist Church Inc",
    "wof:placetype":"venue"
},
  "geometry": {"coordinates":[-122.55332199999999,47.125557],"type":"Point"}
}