{
  "type": "Feature",
  "properties": {
    "addr:full":"223 S Adams Rd Spokane WA 99216",
    "addr:housenumber":"223",
    "addr:postcode":"99216",
    "addr:street":"S Adams Rd",
    "iso:country":"US",
    "sg:address":"223 S Adams Rd",
    "sg:city":"Spokane",
    "sg:classifiers":[
        {
            "category":"Manufacturing",
            "subcategory":"Tools & Machinery",
            "type":"Manufacturing & Wholesale Goods"
        }
    ],
    "sg:phone":"+1 509 991 5874",
    "sg:postcode":"99216",
    "sg:province":"WA",
    "sg:tags":[
        "machine",
        "mfg"
    ],
    "wof:name":"Machine Tool Supply",
    "wof:placetype":"venue"
},
  "geometry": {"coordinates":[-117.207322,47.65473],"type":"Point"}
}