{
  "type": "Feature",
  "properties": {
    "addr:full":"745 Broadway Tacoma WA 98402",
    "addr:housenumber":"745",
    "addr:postcode":"98402",
    "addr:street":"Broadway",
    "iso:country":"US",
    "sg:address":"745 Broadway",
    "sg:city":"Tacoma",
    "sg:classifiers":[
        {
            "category":"Shopping",
            "subcategory":"Used Merchandise",
            "type":"Retail Goods"
        }
    ],
    "sg:phone":"+1 253 572 0935",
    "sg:postcode":"98402",
    "sg:province":"WA",
    "sg:tags":[
        "antique"
    ],
    "wof:name":"Essence Of Time",
    "wof:placetype":"venue"
},
  "geometry": {"coordinates":[-122.44058099999999,47.255801],"type":"Point"}
}