{
  "type": "Feature",
  "properties": {
    "addr:full":"6475 Clover Valley Rd SE Port Orchard WA 98367",
    "addr:housenumber":"6475",
    "addr:postcode":"98367",
    "addr:street":"Clover Valley Rd Se",
    "iso:country":"US",
    "sg:address":"6475 Clover Valley Rd SE",
    "sg:city":"Port Orchard",
    "sg:classifiers":[
        {
            "category":"Shopping",
            "subcategory":"Bicycles & Sporting Goods",
            "type":"Retail Goods"
        }
    ],
    "sg:phone":"+1 360 871 2709",
    "sg:postcode":"98367",
    "sg:province":"WA",
    "sg:tags":[
        "gun",
        "gunsmith"
    ],
    "wof:name":"John's Gun & Tackle",
    "wof:placetype":"venue"
},
  "geometry": {"coordinates":[-122.594446,47.490081],"type":"Point"}
}