{
  "type": "Feature",
  "properties": {
    "addr:full":"510 Allen St Kelso WA 98626",
    "addr:housenumber":"510",
    "addr:postcode":"98626",
    "addr:street":"Allen St",
    "iso:country":"US",
    "sg:address":"510 Allen St",
    "sg:city":"Kelso",
    "sg:classifiers":[
        {
            "category":"Social Services",
            "type":"Services"
        }
    ],
    "sg:phone":"+1 360 577 4929",
    "sg:postcode":"98626",
    "sg:province":"WA",
    "sg:tags":[
        "organization",
        "welfare"
    ],
    "wof:name":"Senior Information & Referral",
    "wof:placetype":"venue"
},
  "geometry": {"coordinates":[-122.907385,46.144203],"type":"Point"}
}