{
  "type": "Feature",
  "properties": {
    "addr:full":"5131 S Director St Seattle WA 98118",
    "addr:housenumber":"5131",
    "addr:postcode":"98118",
    "addr:street":"S Director St",
    "iso:country":"US",
    "sg:address":"5131 S Director St",
    "sg:city":"Seattle",
    "sg:classifiers":[
        {
            "category":"Manufacturing",
            "subcategory":"Food",
            "type":"Manufacturing & Wholesale Goods"
        }
    ],
    "sg:phone":"+1 206 725 0121",
    "sg:postcode":"98118",
    "sg:province":"WA",
    "sg:tags":[
        "packer",
        "fish",
        "canning",
        "salmon"
    ],
    "wof:name":"Dressel-Collins Fish Co Inc",
    "wof:placetype":"venue"
},
  "geometry": {"coordinates":[-122.268046,47.521821],"type":"Point"}
}