{
  "type": "Feature",
  "properties": {
    "addr:full":"200 N Quetilquasoon Rd Manson WA 98831",
    "addr:housenumber":"200",
    "addr:postcode":"98831",
    "addr:street":"N Quetilquasoon Rd",
    "iso:country":"US",
    "sg:address":"200 N Quetilquasoon Rd",
    "sg:city":"Manson",
    "sg:classifiers":[
        {
            "category":"Professional",
            "type":"Services"
        }
    ],
    "sg:phone":"+1 509 687 2206",
    "sg:postcode":"98831",
    "sg:province":"WA",
    "wof:name":"Seasons Lake Chelan",
    "wof:placetype":"venue"
},
  "geometry": {"coordinates":[-120.153245,47.886936],"type":"Point"}
}