{
  "type": "Feature",
  "properties": {
    "addr:full":"1175 NW Gilman Blvd Issaquah WA 98027",
    "addr:housenumber":"1175",
    "addr:postcode":"98027",
    "addr:street":"Nw Gilman Blvd",
    "iso:country":"US",
    "sg:address":"1175 NW Gilman Blvd",
    "sg:city":"Issaquah",
    "sg:classifiers":[
        {
            "category":"Food & Beverages",
            "subcategory":"Liquor & Beverages",
            "type":"Retail Goods"
        }
    ],
    "sg:phone":"+1 425 313 1817",
    "sg:postcode":"98027",
    "sg:province":"WA",
    "sg:tags":[
        "alcoholic"
    ],
    "wof:name":"Washington State Lq Str 99",
    "wof:placetype":"venue"
},
  "geometry": {"coordinates":[-122.05547300000001,47.545549],"type":"Point"}
}