{
  "type": "Feature",
  "properties": {
    "addr:full":"18420 68th Ave S Ste 101 Kent WA 98032",
    "addr:housenumber":"18420",
    "addr:postcode":"98032",
    "addr:street":"68Th Ave S Ste 101",
    "iso:country":"US",
    "sg:address":"18420 68th Ave S Ste 101",
    "sg:city":"Kent",
    "sg:classifiers":[
        {
            "category":"Manufacturing",
            "subcategory":"Glass & Minerals",
            "type":"Manufacturing & Wholesale Goods"
        }
    ],
    "sg:phone":"+1 425 251 8340",
    "sg:postcode":"98032",
    "sg:province":"WA",
    "sg:tags":[
        "shape",
        "circle",
        "special"
    ],
    "sg:website":"http://www.trivitro.com",
    "wof:name":"Trivitro Corporation",
    "wof:placetype":"venue"
},
  "geometry": {"coordinates":[-122.24879799999999,47.43235],"type":"Point"}
}