{
  "type": "Feature",
  "properties": {
    "addr:full":"14317 Golden Given Rd E Tacoma WA 98445",
    "addr:housenumber":"14317",
    "addr:postcode":"98445",
    "addr:street":"Golden Given Rd E",
    "iso:country":"US",
    "sg:address":"14317 Golden Given Rd E",
    "sg:city":"Tacoma",
    "sg:classifiers":[
        {
            "category":"Building & Trades",
            "subcategory":"Construction",
            "type":"Services"
        }
    ],
    "sg:phone":"+1 253 536 2416",
    "sg:postcode":"98445",
    "sg:province":"WA",
    "sg:tags":[
        "contractor"
    ],
    "wof:name":"Strub Fencing",
    "wof:placetype":"venue"
},
  "geometry": {"coordinates":[-122.415291,47.126644],"type":"Point"}
}