{
  "type": "Feature",
  "properties": {
    "addr:full":"2115 112th Ave NE Bellevue WA 98004",
    "addr:housenumber":"2115",
    "addr:postcode":"98004",
    "addr:street":"112Th Ave Ne",
    "iso:country":"US",
    "sg:address":"2115 112th Ave NE",
    "sg:city":"Bellevue",
    "sg:classifiers":[
        {
            "category":"Food & Beverages",
            "subcategory":"Specialty",
            "type":"Retail Goods"
        }
    ],
    "sg:phone":"+1 425 637 1400",
    "sg:postcode":"98004",
    "sg:province":"WA",
    "wof:name":"Herbs Ayush Inc",
    "wof:placetype":"venue"
},
  "geometry": {"coordinates":[-122.19104,47.624266],"type":"Point"}
}