{
  "type": "Feature",
  "properties": {
    "addr:full":"124 W 34th Ave Spokane WA 99203",
    "addr:housenumber":"124",
    "addr:postcode":"99203",
    "addr:street":"W 34Th Ave",
    "iso:country":"US",
    "sg:address":"124 W 34th Ave",
    "sg:city":"Spokane",
    "sg:classifiers":[
        {
            "category":"Manufacturing",
            "subcategory":"Printing",
            "type":"Manufacturing & Wholesale Goods"
        }
    ],
    "sg:phone":"+1 509 744 0345",
    "sg:postcode":"99203",
    "sg:province":"WA",
    "sg:tags":[
        "publishing"
    ],
    "wof:name":"Pipestone Press",
    "wof:placetype":"venue"
},
  "geometry": {"coordinates":[-117.414863,47.623214],"type":"Point"}
}