{
  "type": "Feature",
  "properties": {
    "addr:full":"6000 SE 20th St Mercer Island WA 98040",
    "addr:housenumber":"6000",
    "addr:postcode":"98040",
    "addr:street":"Se 20Th St",
    "iso:country":"US",
    "sg:address":"6000 SE 20th St",
    "sg:city":"Mercer Island",
    "sg:classifiers":[
        {
            "category":"Building & Trades",
            "subcategory":"Construction",
            "type":"Services"
        }
    ],
    "sg:phone":"+1 206 232 2183",
    "sg:postcode":"98040",
    "sg:province":"WA",
    "sg:tags":[
        "residential"
    ],
    "wof:name":"Flip Builders",
    "wof:placetype":"venue"
},
  "geometry": {"coordinates":[-122.252622,47.592396],"type":"Point"}
}