{
  "type": "Feature",
  "properties": {
    "addr:full":"12039 SE Kent Kangley Rd Kent WA 98030",
    "addr:postcode":"12039;98030",
    "addr:street":"Se Kent Kangley Rd",
    "iso:country":"US",
    "sg:address":"12039 SE Kent Kangley Rd",
    "sg:city":"Kent",
    "sg:classifiers":[
        {
            "category":"Building & Trades",
            "subcategory":"Construction",
            "type":"Services"
        }
    ],
    "sg:phone":"+1 253 852 6582",
    "sg:postcode":"98030",
    "sg:province":"WA",
    "sg:tags":[
        "carpentry",
        "contractor"
    ],
    "wof:name":"Red Flannel Wood Works",
    "wof:placetype":"venue"
},
  "geometry": {"coordinates":[-122.179197,47.364001],"type":"Point"}
}