{
  "type": "Feature",
  "properties": {
    "addr:full":"5913 Noon Rd Bellingham WA 98226",
    "addr:postcode":"5913;98226",
    "addr:street":"Noon Rd",
    "iso:country":"US",
    "sg:address":"5913 Noon Rd",
    "sg:city":"Bellingham",
    "sg:classifiers":[
        {
            "category":"Professional",
            "type":"Services"
        }
    ],
    "sg:phone":"+1 360 671 1154",
    "sg:postcode":"98226",
    "sg:province":"WA",
    "wof:name":"Donald S Rubenack & Janet A Ru",
    "wof:placetype":"venue"
},
  "geometry": {"coordinates":[-122.398228,48.861774],"type":"Point"}
}