{
  "type": "Feature",
  "properties": {
    "addr:full":"8803 71st St NW Gig Harbor WA 98335",
    "addr:housenumber":"8803",
    "addr:postcode":"98335",
    "addr:street":"71St St Nw",
    "iso:country":"US",
    "sg:address":"8803 71st St NW",
    "sg:city":"Gig Harbor",
    "sg:classifiers":[
        {
            "category":"Building & Trades",
            "subcategory":"Landscaping Services",
            "type":"Services"
        }
    ],
    "sg:phone":"+1 253 851 9621",
    "sg:postcode":"98335",
    "sg:province":"WA",
    "wof:name":"Garden Solutions",
    "wof:placetype":"venue"
},
  "geometry": {"coordinates":[-122.656052,47.321392],"type":"Point"}
}