{
  "type": "Feature",
  "properties": {
    "addr:full":"9227 9th Ave SW Seattle WA 98106",
    "addr:housenumber":"9227",
    "addr:postcode":"98106",
    "addr:street":"9Th Ave Sw",
    "iso:country":"US",
    "sg:address":"9227 9th Ave SW",
    "sg:city":"Seattle",
    "sg:classifiers":[
        {
            "category":"Building & Trades",
            "subcategory":"Locksmith",
            "type":"Services"
        }
    ],
    "sg:phone":"+1 206 701 6616",
    "sg:postcode":"98106",
    "sg:province":"WA",
    "sg:tags":[
        "key"
    ],
    "wof:name":"Locksmith A 1 Emergency 24 Hour",
    "wof:placetype":"venue"
},
  "geometry": {"coordinates":[-122.34692,47.519837],"type":"Point"}
}