{
  "type": "Feature",
  "properties": {
    "addr:full":"2311 Milton Way Milton WA 98354",
    "addr:housenumber":"2311",
    "addr:postcode":"98354",
    "addr:street":"Milton Way",
    "iso:country":"US",
    "sg:address":"2311 Milton Way",
    "sg:city":"Milton",
    "sg:classifiers":[
        {
            "category":"Professional",
            "type":"Services"
        }
    ],
    "sg:phone":"+1 253 942 8066",
    "sg:postcode":"98354",
    "sg:province":"WA",
    "sg:tags":[
        "establishment"
    ],
    "wof:name":"None",
    "wof:placetype":"venue"
},
  "geometry": {"coordinates":[-122.30426199999999,47.250033],"type":"Point"}
}