{
  "type": "Feature",
  "properties": {
    "iso:country":"US",
    "sg:address":"16946 State Rte 536",
    "sg:city":"Mount Vernon",
    "sg:classifiers":[
        {
            "category":"Organizations",
            "subcategory":"Religious Organization",
            "type":"Services"
        }
    ],
    "sg:phone":"+1 360 428 7012",
    "sg:postcode":"98273",
    "sg:province":"WA",
    "wof:name":"Bible Baptist Church",
    "wof:placetype":"venue"
},
  "geometry": {"coordinates":[-122.378733,48.436318],"type":"Point"}
}