{
  "type": "Feature",
  "properties": {
    "addr:full":"5744 NE Wild Cherry Ln Bainbridge Island WA 98110",
    "addr:housenumber":"5744",
    "addr:postcode":"98110",
    "addr:street":"Ne Wild Cherry Ln",
    "iso:country":"US",
    "sg:address":"5744 NE Wild Cherry Ln",
    "sg:city":"Bainbridge Island",
    "sg:classifiers":[
        {
            "category":"Banks & Credit Unions",
            "subcategory":"Financial Services",
            "type":"Services"
        }
    ],
    "sg:phone":"+1 206 780 9391",
    "sg:postcode":"98110",
    "sg:province":"WA",
    "sg:tags":[
        "investor"
    ],
    "wof:name":"CJS Investments I LLC",
    "wof:placetype":"venue"
},
  "geometry": {"coordinates":[-122.570922,47.639576],"type":"Point"}
}