{
  "type": "Feature",
  "properties": {
    "addr:full":"62 N Kirkpatrick Rd Omak WA 98841",
    "addr:housenumber":"62",
    "addr:postcode":"98841",
    "addr:street":"N Kirkpatrick Rd",
    "iso:country":"US",
    "sg:address":"62 N Kirkpatrick Rd",
    "sg:city":"Omak",
    "sg:classifiers":[
        {
            "category":"Food & Beverages",
            "subcategory":"Bakery",
            "type":"Retail Goods"
        }
    ],
    "sg:phone":"+1 509 826 0706",
    "sg:postcode":"98841",
    "sg:province":"WA",
    "sg:tags":[
        "baker"
    ],
    "wof:name":"Sharon's Sweet Creations",
    "wof:placetype":"venue"
},
  "geometry": {"coordinates":[-119.56541900000001,48.424436],"type":"Point"}
}