{
  "type": "Feature",
  "properties": {
    "addr:full":"2820 S Orcas St Seattle WA 98108",
    "addr:housenumber":"2820",
    "addr:postcode":"98108",
    "addr:street":"S Orcas St",
    "iso:country":"US",
    "sg:address":"2820 S Orcas St",
    "sg:city":"Seattle",
    "sg:classifiers":[
        {
            "category":"Social Services",
            "subcategory":"Child Care",
            "type":"Services"
        }
    ],
    "sg:phone":"+1 206 722 0887",
    "sg:postcode":"98108",
    "sg:province":"WA",
    "sg:tags":[
        "day"
    ],
    "wof:name":"Primm Dba Dearborn",
    "wof:placetype":"venue"
},
  "geometry": {"coordinates":[-122.296299,47.551011],"type":"Point"}
}