{
  "type": "Feature",
  "properties": {
    "addr:full":"2155 N Northlake Way Seattle WA 98103",
    "addr:housenumber":"2155",
    "addr:postcode":"98103",
    "addr:street":"N Northlake Way",
    "iso:country":"US",
    "sg:address":"2155 N Northlake Way",
    "sg:city":"Seattle",
    "sg:classifiers":[
        {
            "category":"Personal",
            "subcategory":"Adult",
            "type":"Services"
        }
    ],
    "sg:phone":"+1 206 632 1337",
    "sg:postcode":"98103",
    "sg:province":"WA",
    "sg:tags":[
        "midwife"
    ],
    "wof:name":"Aleutian Spray Fisheries",
    "wof:placetype":"venue"
},
  "geometry": {"coordinates":[-122.332942,47.647312],"type":"Point"}
}