{
  "type": "Feature",
  "properties": {
    "iso:country":"US",
    "sg:address":"108 N Washington St",
    "sg:city":"Spokane",
    "sg:classifiers":[
        {
            "category":"Real Estate",
            "subcategory":"Real Estate Agent",
            "type":"Services"
        }
    ],
    "sg:phone":"+1 509 624 1019",
    "sg:postcode":"99201",
    "sg:province":"WA",
    "sg:tags":[
        "investment"
    ],
    "sg:website":"www.sdsrealty.com",
    "wof:name":"SDS Realty Co",
    "wof:placetype":"venue"
},
  "geometry": {"coordinates":[-117.41795500000001,47.658416],"type":"Point"}
}