{
  "type": "Feature",
  "properties": {
    "addr:full":"15015 E 32nd Ave Veradale WA 99037",
    "addr:housenumber":"15015",
    "addr:postcode":"99037",
    "addr:street":"E 32Nd Ave",
    "iso:country":"US",
    "sg:address":"15015 E 32nd Ave",
    "sg:city":"Veradale",
    "sg:classifiers":[
        {
            "category":"Shopping",
            "subcategory":"Catalog Store",
            "type":"Retail Goods"
        }
    ],
    "sg:phone":"+1 509 928 6043",
    "sg:postcode":"99037",
    "sg:province":"WA",
    "sg:tags":[
        "mail",
        "house"
    ],
    "wof:name":"Veradale Enterprises",
    "wof:placetype":"venue"
},
  "geometry": {"coordinates":[-117.20524399999999,47.627923],"type":"Point"}
}