{
  "type": "Feature",
  "properties": {
    "addr:full":"2803 Boylston Ave E Seattle WA 98102",
    "addr:housenumber":"2803",
    "addr:postcode":"98102",
    "addr:street":"Boylston Ave E",
    "iso:country":"US",
    "sg:address":"2803 Boylston Ave E",
    "sg:city":"Seattle",
    "sg:classifiers":[
        {
            "category":"Professional",
            "subcategory":"Lawyer & Legal Services",
            "type":"Services"
        }
    ],
    "sg:phone":"+1 206 568 1777",
    "sg:postcode":"98102",
    "sg:province":"WA",
    "wof:name":"Zundel Terry Atty",
    "wof:placetype":"venue"
},
  "geometry": {"coordinates":[-122.32399700000001,47.646099],"type":"Point"}
}