{
  "type": "Feature",
  "properties": {
    "addr:full":"20201 NE 112th Ave Battle Ground WA 98604",
    "addr:housenumber":"20201",
    "addr:postcode":"98604",
    "addr:street":"Ne 112Th Ave",
    "iso:country":"US",
    "sg:address":"20201 NE 112th Ave",
    "sg:city":"Battle Ground",
    "sg:classifiers":[
        {
            "category":"Retail",
            "subcategory":"Animal Services",
            "type":"Services"
        }
    ],
    "sg:phone":"+1 360 666 3260",
    "sg:postcode":"98604",
    "sg:province":"WA",
    "sg:tags":[
        "training",
        "dog"
    ],
    "wof:name":"Man's Best Friend",
    "wof:placetype":"venue"
},
  "geometry": {"coordinates":[-122.55789,45.766838],"type":"Point"}
}