{
  "type": "Feature",
  "properties": {
    "addr:full":"21228 3rd Ave S Seattle WA 98198",
    "addr:housenumber":"21228",
    "addr:postcode":"98198",
    "addr:street":"3Rd Ave S",
    "iso:country":"US",
    "sg:address":"21228 3rd Ave S",
    "sg:city":"Seattle",
    "sg:classifiers":[
        {
            "category":"Professional",
            "subcategory":"Business Services",
            "type":"Services"
        }
    ],
    "sg:phone":"+1 206 824 7882",
    "sg:postcode":"98198",
    "sg:province":"WA",
    "wof:name":"Steven P Bekkerus",
    "wof:placetype":"venue"
},
  "geometry": {"coordinates":[-122.33161699999999,47.411239],"type":"Point"}
}