{
  "type": "Feature",
  "properties": {
    "addr:full":"418 137th St SW Everett WA 98208",
    "addr:housenumber":"418",
    "addr:postcode":"98208",
    "addr:street":"137Th St Sw",
    "iso:country":"US",
    "sg:address":"418 137th St SW",
    "sg:city":"Everett",
    "sg:classifiers":[
        {
            "category":"Home & Garden",
            "subcategory":"Carpets & Floor Coverings",
            "type":"Retail Goods"
        }
    ],
    "sg:phone":"+1 425 741 9460",
    "sg:postcode":"98208",
    "sg:province":"WA",
    "wof:name":"Mitchells",
    "wof:placetype":"venue"
},
  "geometry": {"coordinates":[-122.23903,47.87391],"type":"Point"}
}