{
  "type": "Feature",
  "properties": {
    "addr:full":"4040 7th Ave NE Seattle WA 98105",
    "addr:housenumber":"4040",
    "addr:postcode":"98105",
    "addr:street":"7Th Ave Ne",
    "iso:country":"US",
    "sg:address":"4040 7th Ave NE",
    "sg:city":"Seattle",
    "sg:classifiers":[
        {
            "category":"Real Estate",
            "subcategory":"Real Estate Operator",
            "type":"Services"
        }
    ],
    "sg:phone":"+1 206 547 2243",
    "sg:postcode":"98105",
    "sg:province":"WA",
    "sg:tags":[
        "apartment"
    ],
    "wof:name":"Lake View Apartments",
    "wof:placetype":"venue"
},
  "geometry": {"coordinates":[-122.320999,47.6562],"type":"Point"}
}