{
  "type": "Feature",
  "properties": {
    "addr:full":"707 N Emerson Ave Wenatchee WA 98801",
    "addr:housenumber":"707",
    "addr:postcode":"98801",
    "addr:street":"N Emerson Ave",
    "iso:country":"US",
    "sg:address":"707 N Emerson Ave",
    "sg:city":"Wenatchee",
    "sg:classifiers":[
        {
            "category":"Health Services",
            "subcategory":"Doctor",
            "type":"Services"
        }
    ],
    "sg:phone":"+1 509 662 6109",
    "sg:postcode":"98801",
    "sg:province":"WA",
    "sg:tags":[
        "physician",
        "pediatrics",
        "family",
        "cardiology",
        "gynecology",
        "practice",
        "surgeons",
        "medicine",
        "otorhinolaryngology",
        "throat",
        "internal",
        "nose",
        "obstetrics",
        "dermatology",
        "surgeon",
        "ear"
    ],
    "wof:name":"Wenatchee Family Practice",
    "wof:placetype":"venue"
},
  "geometry": {"coordinates":[-120.321646,47.430462],"type":"Point"}
}