{
  "type": "Feature",
  "properties": {
    "addr:full":"4320 E Trent Ave Spokane WA 99212",
    "addr:housenumber":"4320",
    "addr:postcode":"99212",
    "addr:street":"E Trent Ave",
    "iso:country":"US",
    "sg:address":"4320 E Trent Ave",
    "sg:city":"Spokane",
    "sg:classifiers":[
        {
            "category":"Wholesale",
            "subcategory":"Stationery",
            "type":"Manufacturing & Wholesale Goods"
        }
    ],
    "sg:phone":"+1 509 535 0164",
    "sg:postcode":"99212",
    "sg:province":"WA",
    "sg:tags":[
        "product",
        "paper"
    ],
    "sg:website":"www.unisourcelink.com",
    "wof:name":"Unisource",
    "wof:placetype":"venue"
},
  "geometry": {"coordinates":[-117.345022,47.671591],"type":"Point"}
}