{
  "type": "Feature",
  "properties": {
    "addr:full":"14525 148th Ave NE Woodinville WA 98072",
    "addr:housenumber":"14525",
    "addr:postcode":"98072",
    "addr:street":"148Th Ave Ne",
    "iso:country":"US",
    "sg:address":"14525 148th Ave NE",
    "sg:city":"Woodinville",
    "sg:classifiers":[
        {
            "category":"Arts & Performance",
            "subcategory":"Art Gallery",
            "type":"Entertainment"
        },
        {
            "category":"Home & Garden",
            "subcategory":"Home Furnishings",
            "type":"Retail Goods"
        }
    ],
    "sg:phone":"+1 206 669 5218",
    "sg:postcode":"98072",
    "sg:province":"WA",
    "sg:tags":[
        "decor"
    ],
    "sg:website":"www.applefarmvillage.com",
    "wof:name":"Apple Farm Village",
    "wof:placetype":"venue"
},
  "geometry": {"coordinates":[-122.142247,47.733602],"type":"Point"}
}