{
  "type": "Feature",
  "properties": {
    "iso:country":"US",
    "sg:address":"716 S College Ave",
    "sg:city":"College Place",
    "sg:classifiers":[
        {
            "category":"Health Services",
            "subcategory":"Chiropractor",
            "type":"Services"
        }
    ],
    "sg:phone":"+1 509 525 7661",
    "sg:postcode":"99324",
    "sg:province":"WA",
    "wof:name":"College Place Chiropractic",
    "wof:placetype":"venue"
},
  "geometry": {"coordinates":[-118.388616,46.042794],"type":"Point"}
}