{
  "type": "Feature",
  "properties": {
    "addr:full":"783 S Roberts Bluff Rd Coupeville WA 98239",
    "addr:housenumber":"783",
    "addr:postcode":"98239",
    "addr:street":"S Roberts Bluff Rd",
    "iso:country":"US",
    "sg:address":"783 S Roberts Bluff Rd",
    "sg:city":"Coupeville",
    "sg:classifiers":[
        {
            "category":"Retail",
            "subcategory":"Animal Services",
            "type":"Services"
        }
    ],
    "sg:phone":"+1 360 678 4335",
    "sg:postcode":"98239",
    "sg:province":"WA",
    "sg:tags":[
        "horse",
        "training"
    ],
    "wof:name":"Island Learning Ctr",
    "wof:placetype":"venue"
},
  "geometry": {"coordinates":[-122.587096,48.182115],"type":"Point"}
}