{
  "type": "Feature",
  "properties": {
    "addr:full":"620 1st Ave Pioneer Square Seattle WA 98104",
    "addr:housenumber":"620",
    "addr:postcode":"98104",
    "addr:street":"1St Ave",
    "iso:country":"US",
    "sg:address":"620 1st Ave Pioneer Square",
    "sg:city":"Seattle",
    "sg:classifiers":[
        {
            "category":"Shopping",
            "subcategory":"Clothing, Apparel, & Fashions",
            "type":"Retail Goods"
        }
    ],
    "sg:phone":"+1 866 666 6985",
    "sg:postcode":"98104",
    "sg:province":"WA",
    "sg:tags":[
        "men's",
        "clothing"
    ],
    "sg:website":"www.utilikilts.com",
    "wof:name":"Utilikilts Flagship Retail Store",
    "wof:placetype":"venue"
},
  "geometry": {"coordinates":[-122.334121,47.601915],"type":"Point"}
}