{
  "type": "Feature",
  "properties": {
    "addr:full":"1331 Baywood Ave Richland WA 99352",
    "addr:housenumber":"1331",
    "addr:postcode":"99352",
    "addr:street":"Baywood Ave",
    "iso:country":"US",
    "sg:address":"1331 Baywood Ave",
    "sg:city":"Richland",
    "sg:classifiers":[
        {
            "category":"Government",
            "subcategory":"Office",
            "type":"Public Place"
        }
    ],
    "sg:phone":"+1 509 628 8505",
    "sg:postcode":"99352",
    "sg:province":"WA",
    "sg:tags":[
        "cancer",
        "research"
    ],
    "wof:name":"Smart Space Bullets Inc",
    "wof:placetype":"venue"
},
  "geometry": {"coordinates":[-119.26910100000001,46.237658],"type":"Point"}
}