{
  "type": "Feature",
  "properties": {
    "addr:full":"3922 Britton Rd Bellingham WA 98226",
    "addr:housenumber":"3922",
    "addr:postcode":"98226",
    "addr:street":"Britton Rd",
    "iso:country":"US",
    "sg:address":"3922 Britton Rd",
    "sg:city":"Bellingham",
    "sg:classifiers":[
        {
            "category":"Retail",
            "subcategory":"Repair Shop",
            "type":"Services"
        }
    ],
    "sg:phone":"+1 360 733 2569",
    "sg:postcode":"98226",
    "sg:province":"WA",
    "sg:tags":[
        "upholsterer"
    ],
    "wof:name":"Classic Upholstery",
    "wof:placetype":"venue"
},
  "geometry": {"coordinates":[-122.409958,48.782376],"type":"Point"}
}