{
  "type": "Feature",
  "properties": {
    "addr:full":"610 Market St Kirkland WA 98033",
    "addr:housenumber":"610",
    "addr:postcode":"98033",
    "addr:street":"Market St",
    "iso:country":"US",
    "sg:address":"610 Market St",
    "sg:city":"Kirkland",
    "sg:classifiers":[
        {
            "category":"Professional",
            "subcategory":"Art Services",
            "type":"Services"
        },
        {
            "category":"Professional",
            "subcategory":"Advertising",
            "type":"Services"
        }
    ],
    "sg:phone":"+1 425 827 2506",
    "sg:postcode":"98033",
    "sg:province":"WA",
    "sg:tags":[
        "commercial",
        "counselor",
        "design",
        "agency"
    ],
    "sg:website":"www.hodgsonmeyers.com",
    "wof:name":"Hodgson/Meyers",
    "wof:placetype":"venue"
},
  "geometry": {"coordinates":[-122.20964499999999,47.680374],"type":"Point"}
}