{
  "type": "Feature",
  "properties": {
    "addr:full":"1201 Andover Park E Seattle WA 98188",
    "addr:housenumber":"1201",
    "addr:postcode":"98188",
    "addr:street":"Andover Park E",
    "iso:country":"US",
    "sg:address":"1201 Andover Park E",
    "sg:city":"Seattle",
    "sg:classifiers":[
        {
            "category":"Wholesale",
            "subcategory":"Non-durable Goods",
            "type":"Manufacturing & Wholesale Goods"
        }
    ],
    "sg:phone":"+1 206 575 3037",
    "sg:postcode":"98188",
    "sg:province":"WA",
    "sg:tags":[
        "packaging",
        "material"
    ],
    "wof:name":"Peterson Pack Systems Inc",
    "wof:placetype":"venue"
},
  "geometry": {"coordinates":[-122.25115099999999,47.443263],"type":"Point"}
}