{
  "type": "Feature",
  "properties": {
    "addr:full":"204 S Oak St Colville WA 99114",
    "addr:housenumber":"204",
    "addr:postcode":"99114",
    "addr:street":"S Oak St",
    "iso:country":"US",
    "sg:address":"204 S Oak St",
    "sg:city":"Colville",
    "sg:classifiers":[
        {
            "category":"Government",
            "subcategory":"Post Office",
            "type":"Public Place"
        }
    ],
    "sg:phone":"+1 509 684 2241",
    "sg:postcode":"99114",
    "sg:province":"WA",
    "wof:name":"US Post Office",
    "wof:placetype":"venue"
},
  "geometry": {"coordinates":[-117.904247,48.543337],"type":"Point"}
}