{
  "type": "Feature",
  "properties": {
    "addr:full":"91 Savannah Ln Sequim WA 98382",
    "addr:housenumber":"91",
    "addr:postcode":"98382",
    "addr:street":"Savannah Ln",
    "iso:country":"US",
    "sg:address":"91 Savannah Ln",
    "sg:city":"Sequim",
    "sg:classifiers":[
        {
            "category":"Place Of Worship",
            "subcategory":"Church",
            "type":"Public Place"
        },
        {
            "category":"Place Of Worship",
            "type":"Public Place"
        }
    ],
    "sg:phone":"+1 360 681 4367",
    "sg:postcode":"98382",
    "sg:province":"WA",
    "sg:tags":[
        "christ",
        "churches-community"
    ],
    "sg:website":"http://www.ehcchurch.org",
    "wof:name":"Eastern Hills Community Church",
    "wof:placetype":"venue"
},
  "geometry": {"coordinates":[-123.17700000000001,48.092403],"type":"Point"}
}