{
  "type": "Feature",
  "properties": {
    "addr:full":"2520 Commercial Ave Anacortes WA 98221",
    "addr:housenumber":"2520",
    "addr:postcode":"98221",
    "addr:street":"Commercial Ave",
    "iso:country":"US",
    "sg:address":"2520 Commercial Ave",
    "sg:city":"Anacortes",
    "sg:classifiers":[
        {
            "category":"Restaurant",
            "type":"Food & Drink"
        }
    ],
    "sg:phone":"+1 360 588 1288",
    "sg:postcode":"98221",
    "sg:province":"WA",
    "sg:tags":[
        "eating"
    ],
    "wof:name":"Esteban's Taqueria",
    "wof:placetype":"venue"
},
  "geometry": {"coordinates":[-122.612819,48.501902],"type":"Point"}
}