{
  "type": "Feature",
  "properties": {
    "addr:full":"3401 6th Ave Tacoma WA 98406",
    "addr:housenumber":"3401",
    "addr:postcode":"98406",
    "addr:street":"6Th Ave",
    "iso:country":"US",
    "sg:address":"3401 6th Ave",
    "sg:city":"Tacoma",
    "sg:classifiers":[
        {
            "category":"Professional",
            "subcategory":"Lawyer & Legal Services",
            "type":"Services"
        }
    ],
    "sg:phone":"+1 253 761 7791",
    "sg:postcode":"98406",
    "sg:province":"WA",
    "sg:tags":[
        "attorney"
    ],
    "wof:name":"James E Oliver Law Offices",
    "wof:placetype":"venue"
},
  "geometry": {"coordinates":[-122.48217,47.255275],"type":"Point"}
}