{
  "type": "Feature",
  "properties": {
    "addr:full":"10943 NE State Highway 104 Kingston WA 98346",
    "addr:housenumber":"10943",
    "addr:postcode":"98346",
    "addr:street":"Ne State Highway 104",
    "iso:country":"US",
    "sg:address":"10943 NE State Highway 104",
    "sg:city":"Kingston",
    "sg:classifiers":[
        {
            "category":"Banks & Credit Unions",
            "subcategory":"Financial Services",
            "type":"Services"
        },
        {
            "category":"Banks & Credit Unions",
            "subcategory":"Bank",
            "type":"Services"
        },
        {
            "category":"Banks & Credit Unions",
            "subcategory":"Atm",
            "type":"Services"
        }
    ],
    "sg:phone":"+1 360 692 0107",
    "sg:postcode":"98346",
    "sg:province":"WA",
    "sg:tags":[
        "saving",
        "loan",
        "commercial",
        "banking",
        "location",
        "internet"
    ],
    "sg:website":"http://locators.bankofamerica.com/a/BC-9089",
    "wof:name":"Bank Of America",
    "wof:placetype":"venue"
},
  "geometry": {"coordinates":[-122.50000799999999,47.801281],"type":"Point"}
}