{
  "type": "Feature",
  "properties": {
    "addr:full":"1900 Black Lake Blvd SW Olympia WA 98512",
    "addr:housenumber":"1900",
    "addr:postcode":"98512",
    "addr:street":"Black Lake Blvd Sw",
    "iso:country":"US",
    "sg:address":"1900 Black Lake Blvd SW",
    "sg:city":"Olympia",
    "sg:classifiers":[
        {
            "category":"Real Estate",
            "subcategory":"Real Estate Operator",
            "type":"Services"
        }
    ],
    "sg:phone":"+1 360 352 5670",
    "sg:postcode":"98512",
    "sg:province":"WA",
    "sg:tags":[
        "building",
        "apartment"
    ],
    "wof:name":"Black Lake Apartment",
    "wof:placetype":"venue"
},
  "geometry": {"coordinates":[-122.943029,47.030685],"type":"Point"}
}