{
  "type": "Feature",
  "properties": {
    "addr:full":"94 Mountain View Dr Brewster WA 98812",
    "addr:housenumber":"94",
    "addr:postcode":"98812",
    "addr:street":"Mountain View Dr",
    "iso:country":"US",
    "sg:address":"94 Mountain View Dr",
    "sg:city":"Brewster",
    "sg:classifiers":[
        {
            "category":"Utilities",
            "subcategory":"Water",
            "type":"Services"
        }
    ],
    "sg:phone":"+1 509 689 2634",
    "sg:postcode":"98812",
    "sg:province":"WA",
    "sg:tags":[
        "irrigation",
        "conservation",
        "company",
        "sewage"
    ],
    "wof:name":"Brewster Flat Irrigation Dst",
    "wof:placetype":"venue"
},
  "geometry": {"coordinates":[-119.74978,48.122725],"type":"Point"}
}