{
  "type": "Feature",
  "properties": {
    "addr:full":"2303 N 45th St Seattle WA 98103",
    "addr:housenumber":"2303",
    "addr:postcode":"98103",
    "addr:street":"N 45Th St",
    "iso:country":"US",
    "sg:address":"2303 N 45th St",
    "sg:city":"Seattle",
    "sg:classifiers":[
        {
            "category":"Professional",
            "type":"Services"
        }
    ],
    "sg:phone":"+1 206 547 1681",
    "sg:postcode":"98103",
    "sg:province":"WA",
    "sg:tags":[
        "establishment"
    ],
    "wof:name":"ALS Open Road Inc",
    "wof:placetype":"venue"
},
  "geometry": {"coordinates":[-122.330181,47.661292],"type":"Point"}
}