{
  "type": "Feature",
  "properties": {
    "addr:full":"212 W Pioneer Puyallup WA 98371",
    "addr:housenumber":"212",
    "addr:postcode":"98371",
    "addr:street":"W Pioneer",
    "iso:country":"US",
    "sg:address":"212 W Pioneer",
    "sg:city":"Puyallup",
    "sg:classifiers":[
        {
            "category":"Social Services",
            "type":"Services"
        }
    ],
    "sg:phone":"+1 253 841 5548",
    "sg:postcode":"98371",
    "sg:province":"WA",
    "wof:name":"Puyallup Senior Center",
    "wof:placetype":"venue"
},
  "geometry": {"coordinates":[-122.29624800000001,47.190358],"type":"Point"}
}