{
  "type": "Feature",
  "properties": {
    "addr:full":"23480 120th Ave SE Kent WA 98031",
    "addr:housenumber":"23480",
    "addr:postcode":"98031",
    "addr:street":"120Th Ave Se",
    "iso:country":"US",
    "sg:address":"23480 120th Ave SE",
    "sg:city":"Kent",
    "sg:classifiers":[
        {
            "category":"Education",
            "subcategory":"School",
            "type":"Public Place"
        }
    ],
    "sg:phone":"+1 253 373 7383",
    "sg:postcode":"98031",
    "sg:province":"WA",
    "wof:name":"Meridian Junior High School",
    "wof:placetype":"venue"
},
  "geometry": {"coordinates":[-122.181353,47.391256],"type":"Point"}
}