{
  "type": "Feature",
  "properties": {
    "addr:full":"23 S Wenatchee Ave Wenatchee WA 98801",
    "addr:housenumber":"23",
    "addr:postcode":"98801",
    "addr:street":"S Wenatchee Ave",
    "iso:country":"US",
    "sg:address":"23 S Wenatchee Ave",
    "sg:city":"Wenatchee",
    "sg:classifiers":[
        {
            "category":"Utilities",
            "subcategory":"Mobile Phone",
            "type":"Services"
        }
    ],
    "sg:phone":"+1 509 663 6163",
    "sg:postcode":"98801",
    "sg:province":"WA",
    "sg:tags":[
        "telephone",
        "cellular"
    ],
    "wof:name":"Sprint Net",
    "wof:placetype":"venue"
},
  "geometry": {"coordinates":[-120.31072399999999,47.423656],"type":"Point"}
}