{
  "type": "Feature",
  "properties": {
    "addr:full":"7544 Sunnyside Ave N Seattle WA 98103",
    "addr:housenumber":"7544",
    "addr:postcode":"98103",
    "addr:street":"Sunnyside Ave N",
    "iso:country":"US",
    "sg:address":"7544 Sunnyside Ave N",
    "sg:city":"Seattle",
    "sg:classifiers":[
        {
            "category":"Utilities",
            "subcategory":"Telephone",
            "type":"Services"
        }
    ],
    "sg:phone":"+1 206 650 0350",
    "sg:postcode":"98103",
    "sg:province":"WA",
    "sg:tags":[
        "communications"
    ],
    "wof:name":"Atomic Telecom",
    "wof:placetype":"venue"
},
  "geometry": {"coordinates":[-122.329291,47.684655],"type":"Point"}
}