{
  "type": "Feature",
  "properties": {
    "addr:full":"10022 Marine View Dr Mukilteo WA 98275",
    "addr:housenumber":"10022",
    "addr:postcode":"98275",
    "addr:street":"Marine View Dr",
    "iso:country":"US",
    "sg:address":"10022 Marine View Dr",
    "sg:city":"Mukilteo",
    "sg:classifiers":[
        {
            "category":"Professional",
            "subcategory":"Business Services",
            "type":"Services"
        }
    ],
    "sg:phone":"+1 425 348 3250",
    "sg:postcode":"98275",
    "sg:province":"WA",
    "wof:name":"Sisom & Assoc Inc",
    "wof:placetype":"venue"
},
  "geometry": {"coordinates":[-122.32152499999999,47.907398],"type":"Point"}
}