{
  "type": "Feature",
  "properties": {
    "addr:full":"760 Shockley Rd Richland WA 99352",
    "addr:housenumber":"760",
    "addr:postcode":"99352",
    "addr:street":"Shockley Rd",
    "iso:country":"US",
    "sg:address":"760 Shockley Rd",
    "sg:city":"Richland",
    "sg:classifiers":[
        {
            "category":"Farming",
            "subcategory":"Orchard",
            "type":"Manufacturing & Wholesale Goods"
        }
    ],
    "sg:phone":"+1 509 627 4166",
    "sg:postcode":"99352",
    "sg:province":"WA",
    "wof:name":"Brian Whitfield",
    "wof:placetype":"venue"
},
  "geometry": {"coordinates":[-119.303302,46.242157],"type":"Point"}
}