{
  "type": "Feature",
  "properties": {
    "addr:full":"1318 Pear St NE Olympia WA 98506",
    "addr:housenumber":"1318",
    "addr:postcode":"98506",
    "addr:street":"Pear St Ne",
    "iso:country":"US",
    "sg:address":"1318 Pear St NE",
    "sg:city":"Olympia",
    "sg:classifiers":[
        {
            "category":"Building & Trades",
            "subcategory":"Landscaping Services",
            "type":"Services"
        }
    ],
    "sg:phone":"+1 360 754 1648",
    "sg:postcode":"98506",
    "sg:province":"WA",
    "sg:tags":[
        "landscape"
    ],
    "wof:name":"Scenic Landscape",
    "wof:placetype":"venue"
},
  "geometry": {"coordinates":[-122.89104399999999,47.056963],"type":"Point"}
}