{
  "type": "Feature",
  "properties": {
    "addr:full":"4723 N Napa St Spokane WA 99207",
    "addr:housenumber":"4723",
    "addr:postcode":"99207",
    "addr:street":"N Napa St",
    "iso:country":"US",
    "sg:address":"4723 N Napa St",
    "sg:city":"Spokane",
    "sg:classifiers":[
        {
            "category":"Professional",
            "subcategory":"Business Services",
            "type":"Services"
        }
    ],
    "sg:phone":"+1 509 484 4627",
    "sg:postcode":"99207",
    "sg:province":"WA",
    "wof:name":"Ajb Enterprises",
    "wof:placetype":"venue"
},
  "geometry": {"coordinates":[-117.38115999999999,47.702203],"type":"Point"}
}