{
  "type": "Feature",
  "properties": {
    "addr:full":"7323 Sand Point Way NE Seattle WA 98115",
    "addr:housenumber":"7323",
    "addr:postcode":"98115",
    "addr:street":"Sand Point Way Ne",
    "iso:country":"US",
    "sg:address":"7323 Sand Point Way NE",
    "sg:city":"Seattle",
    "sg:classifiers":[
        {
            "category":"Real Estate",
            "subcategory":"Real Estate Operator",
            "type":"Services"
        }
    ],
    "sg:phone":"+1 206 232 1568",
    "sg:postcode":"98115",
    "sg:province":"WA",
    "sg:tags":[
        "building",
        "apartment"
    ],
    "wof:name":"Sand Point Court Assn LLP",
    "wof:placetype":"venue"
},
  "geometry": {"coordinates":[-122.263766,47.682813],"type":"Point"}
}