{
  "type": "Feature",
  "properties": {
    "addr:full":"706 N Miller St Wenatchee WA 98801",
    "addr:housenumber":"706",
    "addr:postcode":"98801",
    "addr:street":"N Miller St",
    "iso:country":"US",
    "sg:address":"706 N Miller St",
    "sg:city":"Wenatchee",
    "sg:classifiers":[
        {
            "category":"Autos & Motor Vehicles",
            "subcategory":"Fuel & Gas Station",
            "type":"Retail Goods"
        }
    ],
    "sg:phone":"+1 509 663 4708",
    "sg:postcode":"98801",
    "sg:province":"WA",
    "sg:tags":[
        "station",
        "gasoline"
    ],
    "wof:name":"Bloomfield Mini Mart & Deli",
    "wof:placetype":"venue"
},
  "geometry": {"coordinates":[-120.32484599999999,47.432421],"type":"Point"}
}