{
  "type": "Feature",
  "properties": {
    "addr:full":"168 Frigate St NW Ocean Shores WA 98569",
    "addr:housenumber":"168",
    "addr:postcode":"98569",
    "addr:street":"Frigate St Nw",
    "iso:country":"US",
    "sg:address":"168 Frigate St NW",
    "sg:city":"Ocean Shores",
    "sg:classifiers":[
        {
            "category":"Personal",
            "subcategory":"Beauty Salon",
            "type":"Services"
        }
    ],
    "sg:phone":"+1 360 289 2783",
    "sg:postcode":"98569",
    "sg:province":"WA",
    "wof:name":"Rocky's Custom Hair",
    "wof:placetype":"venue"
},
  "geometry": {"coordinates":[-124.163303,46.999775],"type":"Point"}
}