{
  "type": "Feature",
  "properties": {
    "addr:full":"16220 140th Pl NE Woodinville WA 98072",
    "addr:housenumber":"16220",
    "addr:postcode":"98072",
    "addr:street":"140Th Pl Ne",
    "iso:country":"US",
    "sg:address":"16220 140th Pl NE",
    "sg:city":"Woodinville",
    "sg:classifiers":[
        {
            "category":"Social Services",
            "subcategory":"Child Care",
            "type":"Services"
        }
    ],
    "sg:phone":"+1 425 483 0302",
    "sg:postcode":"98072",
    "sg:province":"WA",
    "sg:tags":[
        "center"
    ],
    "wof:name":"Woodinville Childrens Center",
    "wof:placetype":"venue"
},
  "geometry": {"coordinates":[-122.14694799999999,47.743457],"type":"Point"}
}