{
  "type": "Feature",
  "properties": {
    "addr:full":"5601 W Charlene Ct Spokane WA 99208",
    "addr:housenumber":"5601",
    "addr:postcode":"99208",
    "addr:street":"W Charlene Ct",
    "iso:country":"US",
    "sg:address":"5601 W Charlene Ct",
    "sg:city":"Spokane",
    "sg:classifiers":[
        {
            "category":"Retail",
            "subcategory":"Animal Services",
            "type":"Services"
        }
    ],
    "sg:phone":"+1 509 473 2007",
    "sg:postcode":"99208",
    "sg:province":"WA",
    "sg:tags":[
        "pet",
        "exercising",
        "sitting"
    ],
    "sg:website":"http://www.socialsecurityadminastration.com",
    "wof:name":"Tracy L Fetch",
    "wof:placetype":"venue"
},
  "geometry": {"coordinates":[-117.49176799999999,47.738708],"type":"Point"}
}