{
  "type": "Feature",
  "properties": {
    "addr:full":"9312 S Tacoma Way Lakewood WA 98499",
    "addr:housenumber":"9312",
    "addr:postcode":"98499",
    "addr:street":"S Tacoma Way",
    "iso:country":"US",
    "sg:address":"9312 S Tacoma Way",
    "sg:city":"Lakewood",
    "sg:phone":"+1 253 582 2211",
    "sg:postcode":"98499",
    "sg:province":"WA",
    "wof:name":"Pho Hoa",
    "wof:placetype":"venue"
},
  "geometry": {"coordinates":[-122.483729,47.172886],"type":"Point"}
}