{
  "type": "Feature",
  "properties": {
    "addr:full":"348 W Olympic Pl Seattle WA 98119",
    "addr:housenumber":"348",
    "addr:postcode":"98119",
    "addr:street":"W Olympic Pl",
    "iso:country":"US",
    "sg:address":"348 W Olympic Pl",
    "sg:city":"Seattle",
    "sg:classifiers":[
        {
            "category":"Insurance",
            "subcategory":"Insurance Agent",
            "type":"Services"
        }
    ],
    "sg:phone":"+1 206 443 6214",
    "sg:postcode":"98119",
    "sg:province":"WA",
    "wof:name":"A T Lloyds Inc",
    "wof:placetype":"venue"
},
  "geometry": {"coordinates":[-122.362793,47.626812],"type":"Point"}
}