{
  "type": "Feature",
  "properties": {
    "addr:full":"2206 Talbot Rd S Renton WA 98055",
    "addr:housenumber":"2206",
    "addr:postcode":"98055",
    "addr:street":"Talbot Rd S",
    "iso:country":"US",
    "sg:address":"2206 Talbot Rd S",
    "sg:city":"Renton",
    "sg:classifiers":[
        {
            "category":"Building & Trades",
            "subcategory":"Construction",
            "type":"Services"
        }
    ],
    "sg:phone":"+1 425 255 9432",
    "sg:postcode":"98055",
    "sg:province":"WA",
    "sg:tags":[
        "concrete",
        "contractor"
    ],
    "wof:name":"Solid Rock Concrete",
    "wof:placetype":"venue"
},
  "geometry": {"coordinates":[-122.21135,47.460062],"type":"Point"}
}