{
  "type": "Feature",
  "properties": {
    "addr:full":"220 E Wellesley Ave Spokane WA 99207",
    "addr:housenumber":"220",
    "addr:postcode":"99207",
    "addr:street":"E Wellesley Ave",
    "iso:country":"US",
    "sg:address":"220 E Wellesley Ave",
    "sg:city":"Spokane",
    "sg:classifiers":[
        {
            "category":"Organizations",
            "subcategory":"Community Association",
            "type":"Services"
        }
    ],
    "sg:phone":"+1 509 483 2910",
    "sg:postcode":"99207",
    "sg:province":"WA",
    "sg:tags":[
        "blind"
    ],
    "wof:name":"National Federation-The Blind",
    "wof:placetype":"venue"
},
  "geometry": {"coordinates":[-117.407343,47.700653],"type":"Point"}
}