{
  "type": "Feature",
  "properties": {
    "addr:full":"5607 Rainier Ave S Seattle WA 98118",
    "addr:housenumber":"5607",
    "addr:postcode":"98118",
    "addr:street":"Rainier Ave S",
    "iso:country":"US",
    "sg:address":"5607 Rainier Ave S",
    "sg:city":"Seattle",
    "sg:classifiers":[
        {
            "category":"Restaurant",
            "type":"Food & Drink"
        }
    ],
    "sg:phone":"+1 206 420 1349",
    "sg:postcode":"98118",
    "sg:province":"WA",
    "sg:tags":[
        "pizza"
    ],
    "sg:website":"www.eymanspizza.com",
    "wof:name":"Eymans Pizza",
    "wof:placetype":"venue"
},
  "geometry": {"coordinates":[-122.278302,47.551657],"type":"Point"}
}