{
  "type": "Feature",
  "properties": {
    "addr:full":"335 Snowberry Ln Goldendale WA 98620",
    "addr:housenumber":"335",
    "addr:postcode":"98620",
    "addr:street":"Snowberry Ln",
    "iso:country":"US",
    "sg:address":"335 Snowberry Ln",
    "sg:city":"Goldendale",
    "sg:classifiers":[
        {
            "category":"Wholesale",
            "subcategory":"Farm Supplies",
            "type":"Manufacturing & Wholesale Goods"
        }
    ],
    "sg:phone":"+1 509 773 3895",
    "sg:postcode":"98620",
    "sg:province":"WA",
    "sg:tags":[
        "livestock"
    ],
    "wof:name":"Klickitat Creek Farm",
    "wof:placetype":"venue"
},
  "geometry": {"coordinates":[-120.71750400000001,45.872893],"type":"Point"}
}