{
  "type": "Feature",
  "properties": {
    "addr:full":"138 W 1st St Port Angeles WA 98362",
    "addr:housenumber":"138",
    "addr:postcode":"98362",
    "addr:street":"W 1St St",
    "iso:country":"US",
    "sg:address":"138 W 1st St",
    "sg:city":"Port Angeles",
    "sg:classifiers":[
        {
            "category":"Government",
            "subcategory":"Office",
            "type":"Public Place"
        }
    ],
    "sg:phone":"+1 360 457 4311",
    "sg:postcode":"98362",
    "sg:province":"WA",
    "sg:tags":[
        "customs"
    ],
    "wof:name":"Customs Border Protection Bur",
    "wof:placetype":"venue"
},
  "geometry": {"coordinates":[-123.434892,48.119456],"type":"Point"}
}