{
  "type": "Feature",
  "properties": {
    "addr:full":"103 S Tower Ave Centralia WA 98531",
    "addr:housenumber":"103",
    "addr:postcode":"98531",
    "addr:street":"S Tower Ave",
    "iso:country":"US",
    "sg:address":"103 S Tower Ave",
    "sg:city":"Centralia",
    "sg:classifiers":[
        {
            "category":"Shopping",
            "subcategory":"Used Merchandise",
            "type":"Retail Goods"
        }
    ],
    "sg:phone":"+1 360 736 1673",
    "sg:postcode":"98531",
    "sg:province":"WA",
    "sg:tags":[
        "antique"
    ],
    "wof:name":"Second Blessings",
    "wof:placetype":"venue"
},
  "geometry": {"coordinates":[-122.954396,46.716236],"type":"Point"}
}