{
  "type": "Feature",
  "properties": {
    "addr:full":"1228 Wetmore Ave Everett WA 98201",
    "addr:housenumber":"1228",
    "addr:postcode":"98201",
    "addr:street":"Wetmore Ave",
    "iso:country":"US",
    "sg:address":"1228 Wetmore Ave",
    "sg:city":"Everett",
    "sg:classifiers":[
        {
            "category":"Professional",
            "type":"Services"
        }
    ],
    "sg:phone":"+1 425 259 2448",
    "sg:postcode":"98201",
    "sg:province":"WA",
    "sg:tags":[
        "writer"
    ],
    "wof:name":"Nancy Louise Gosen Svc",
    "wof:placetype":"venue"
},
  "geometry": {"coordinates":[-122.206745,48.000726],"type":"Point"}
}