{
  "type": "Feature",
  "properties": {
    "iso:country":"US",
    "sg:address":"1509 Harrison Ave",
    "sg:city":"Centralia",
    "sg:classifiers":[
        {
            "category":"Health Services",
            "subcategory":"Nursing And Care Facility",
            "type":"Services"
        }
    ],
    "sg:phone":"+1 360 736 0112",
    "sg:postcode":"98531",
    "sg:province":"WA",
    "sg:tags":[
        "intermediate"
    ],
    "wof:name":"Sharon Care Centeri",
    "wof:placetype":"venue"
},
  "geometry": {"coordinates":[-122.98943800000001,46.735403],"type":"Point"}
}