{
  "type": "Feature",
  "properties": {
    "addr:full":"32812 Pacific Hwy S Federal Way WA 98003",
    "addr:housenumber":"32812",
    "addr:postcode":"98003",
    "addr:street":"Pacific Hwy S Federal Way",
    "iso:country":"US",
    "sg:address":"32812 Pacific Hwy S",
    "sg:city":"Federal Way",
    "sg:classifiers":[
        {
            "category":"Banks & Credit Unions",
            "subcategory":"Financial Services",
            "type":"Services"
        }
    ],
    "sg:phone":"+1 253 838 0367",
    "sg:postcode":"98003",
    "sg:province":"WA",
    "sg:tags":[
        "investor"
    ],
    "wof:name":"Husby Company Inc",
    "wof:placetype":"venue"
},
  "geometry": {"coordinates":[-122.31333100000001,47.306474],"type":"Point"}
}