{
  "type": "Feature",
  "properties": {
    "iso:country":"US",
    "sg:address":"317 Trailblazer St SE",
    "sg:city":"Lacey",
    "sg:classifiers":[
        {
            "category":"Communications",
            "subcategory":"Film & Video Production",
            "type":"Services"
        }
    ],
    "sg:phone":"+1 360 412 5255",
    "sg:postcode":"98503",
    "sg:province":"WA",
    "sg:tags":[
        "motion"
    ],
    "wof:name":"Bluesday Production Co",
    "wof:placetype":"venue"
},
  "geometry": {"coordinates":[-122.770869,47.051459],"type":"Point"}
}