{
  "type": "Feature",
  "properties": {
    "addr:full":"16735 30th Ave NE Seattle WA 98155",
    "addr:housenumber":"16735",
    "addr:postcode":"98155",
    "addr:street":"30Th Ave Ne",
    "iso:country":"US",
    "sg:address":"16735 30th Ave NE",
    "sg:city":"Seattle",
    "sg:classifiers":[
        {
            "category":"Professional",
            "subcategory":"Art Services",
            "type":"Services"
        }
    ],
    "sg:phone":"+1 206 361 0655",
    "sg:postcode":"98155",
    "sg:province":"WA",
    "sg:tags":[
        "commercial",
        "design"
    ],
    "wof:name":"Sancho Design",
    "wof:placetype":"venue"
},
  "geometry": {"coordinates":[-122.296904,47.750447],"type":"Point"}
}