{
  "type": "Feature",
  "properties": {
    "addr:full":"1651 Silver Lake Rd Oak Harbor WA 98277",
    "addr:housenumber":"1651",
    "addr:postcode":"98277",
    "addr:street":"Silver Lake Rd",
    "iso:country":"US",
    "sg:address":"1651 Silver Lake Rd",
    "sg:city":"Oak Harbor",
    "sg:classifiers":[
        {
            "category":"Farming",
            "subcategory":"Livestock Farm",
            "type":"Manufacturing & Wholesale Goods"
        }
    ],
    "sg:phone":"+1 360 679 6888",
    "sg:postcode":"98277",
    "sg:province":"WA",
    "wof:name":"Elderflower Farm",
    "wof:placetype":"venue"
},
  "geometry": {"coordinates":[-122.524811,48.318141],"type":"Point"}
}