{
  "type": "Feature",
  "properties": {
    "addr:full":"325 5th Ave N Seattle WA 98109",
    "addr:housenumber":"325",
    "addr:postcode":"98109",
    "addr:street":"5Th Ave N",
    "iso:country":"US",
    "sg:address":"325 5th Ave N",
    "sg:city":"Seattle",
    "sg:classifiers":[
        {
            "category":"Bars & Pubs",
            "type":"Food & Drink"
        }
    ],
    "sg:menulink":"http://www.allmenus.com/wa/seattle/275714-revolution-bar--grill/menu/",
    "sg:phone":"+1 206 770 2777",
    "sg:postcode":"98109",
    "sg:province":"WA",
    "sg:tags":[
        "new",
        "american"
    ],
    "wof:name":"Revolution Bar & Grill",
    "wof:placetype":"venue"
},
  "geometry": {"coordinates":[-122.347764,47.621082],"type":"Point"}
}