{
  "type": "Feature",
  "properties": {
    "addr:full":"15163 NE 24th St Redmond WA 98052",
    "addr:housenumber":"15163",
    "addr:postcode":"98052",
    "addr:street":"Ne 24Th St",
    "iso:country":"US",
    "sg:address":"15163 NE 24th St",
    "sg:city":"Redmond",
    "sg:classifiers":[
        {
            "category":"Restaurant",
            "type":"Food & Drink"
        }
    ],
    "sg:phone":"+1 425 643 4443",
    "sg:postcode":"98052",
    "sg:province":"WA",
    "sg:tags":[
        "eating"
    ],
    "wof:name":"Milt's Barbeque",
    "wof:placetype":"venue"
},
  "geometry": {"coordinates":[-122.13800000000001,47.631599],"type":"Point"}
}