{
  "type": "Feature",
  "properties": {
    "addr:full":"1030 E Ash St Othello WA 99344",
    "addr:housenumber":"1030",
    "addr:postcode":"99344",
    "addr:street":"E Ash St",
    "iso:country":"US",
    "sg:address":"1030 E Ash St",
    "sg:city":"Othello",
    "sg:classifiers":[
        {
            "category":"Professional",
            "subcategory":"Management & Consulting",
            "type":"Services"
        }
    ],
    "sg:phone":"+1 509 488 5118",
    "sg:postcode":"99344",
    "sg:province":"WA",
    "sg:tags":[
        "retail",
        "direct",
        "sales"
    ],
    "wof:name":"Joe Swan",
    "wof:placetype":"venue"
},
  "geometry": {"coordinates":[-119.159387,46.818638],"type":"Point"}
}