{
  "type": "Feature",
  "properties": {
    "addr:full":"108 W Fremont Ave Selah WA 98942",
    "addr:housenumber":"108",
    "addr:postcode":"98942",
    "addr:street":"W Fremont Ave",
    "iso:country":"US",
    "sg:address":"108 W Fremont Ave",
    "sg:city":"Selah",
    "sg:classifiers":[
        {
            "category":"Banks & Credit Unions",
            "subcategory":"Bank",
            "type":"Services"
        }
    ],
    "sg:phone":"+1 509 697 7000",
    "sg:postcode":"98942",
    "sg:province":"WA",
    "sg:tags":[
        "commercial"
    ],
    "wof:name":"Selah National Bank",
    "wof:placetype":"venue"
},
  "geometry": {"coordinates":[-120.533044,46.655925],"type":"Point"}
}