{
  "type": "Feature",
  "properties": {
    "addr:full":"13011 E Meridian Ave Puyallup WA 98373",
    "addr:housenumber":"13011",
    "addr:postcode":"98373",
    "addr:street":"E Meridian Ave",
    "iso:country":"US",
    "sg:address":"13011 E Meridian Ave",
    "sg:city":"Puyallup",
    "sg:classifiers":[
        {
            "category":"Manufacturing",
            "subcategory":"Toys & Sporting Goods",
            "type":"Manufacturing & Wholesale Goods"
        }
    ],
    "sg:phone":"+1 253 841 3776",
    "sg:postcode":"98373",
    "sg:province":"WA",
    "sg:tags":[
        "mfg"
    ],
    "wof:name":"Mermaids Cove",
    "wof:placetype":"venue"
},
  "geometry": {"coordinates":[-122.292941,47.138355],"type":"Point"}
}