{
  "type": "Feature",
  "properties": {
    "addr:full":"9825 225th Ave NE Redmond WA 98053",
    "addr:housenumber":"9825",
    "addr:postcode":"98053",
    "addr:street":"225Th Ave Ne",
    "iso:country":"US",
    "sg:address":"9825 225th Ave NE",
    "sg:city":"Redmond",
    "sg:classifiers":[
        {
            "category":"Manufacturing",
            "subcategory":"Electronics",
            "type":"Manufacturing & Wholesale Goods"
        },
        {
            "category":"Shopping",
            "subcategory":"Computers & Home Electronics",
            "type":"Retail Goods"
        }
    ],
    "sg:phone":"+1 425 522 4979",
    "sg:postcode":"98053",
    "sg:province":"WA",
    "sg:tags":[
        "supplies-wholesale",
        "manufacturer",
        "electronic",
        "consumer",
        "equipment"
    ],
    "wof:name":"Virtual Supply, Inc.",
    "wof:placetype":"venue"
},
  "geometry": {"coordinates":[-122.04012400000001,47.686891],"type":"Point"}
}