{
  "type": "Feature",
  "properties": {
    "addr:full":"16934 116th Ave SE Renton WA 98058",
    "addr:housenumber":"16934",
    "addr:postcode":"98058",
    "addr:street":"116Th Ave Se",
    "iso:country":"US",
    "sg:address":"16934 116th Ave SE",
    "sg:city":"Renton",
    "sg:classifiers":[
        {
            "category":"Food & Beverages",
            "subcategory":"Specialty",
            "type":"Retail Goods"
        },
        {
            "category":"Restaurant",
            "type":"Food & Drink"
        }
    ],
    "sg:phone":"+1 425 277 1571",
    "sg:postcode":"98058",
    "sg:province":"WA",
    "sg:tags":[
        "eating",
        "bars",
        "espresso"
    ],
    "wof:name":"Friendly Bean Espresso",
    "wof:placetype":"venue"
},
  "geometry": {"coordinates":[-122.185998,47.450895],"type":"Point"}
}