{
  "type": "Feature",
  "properties": {
    "addr:full":"214 N Howard St Spokane WA 99201",
    "addr:housenumber":"214",
    "addr:postcode":"99201",
    "addr:street":"N Howard St",
    "iso:country":"US",
    "sg:address":"214 N Howard St",
    "sg:city":"Spokane",
    "sg:classifiers":[
        {
            "category":"Bars & Pubs",
            "subcategory":"Wine Bar",
            "type":"Food & Drink"
        }
    ],
    "sg:menulink":"http://www.allmenus.com/wa/spokane/278517-mizuna-restaurant-and-wine-bar/menu/",
    "sg:phone":"+1 509 747 2004",
    "sg:postcode":"99201",
    "sg:province":"WA",
    "sg:tags":[
        "vegetarian",
        "american"
    ],
    "wof:name":"Mizuna Restaurant and Wine Bar",
    "wof:placetype":"venue"
},
  "geometry": {"coordinates":[-117.420874,47.659296],"type":"Point"}
}