{
  "type": "Feature",
  "properties": {
    "addr:full":"4502 NE 130th St Vancouver WA 98686",
    "addr:housenumber":"4502",
    "addr:postcode":"98686",
    "addr:street":"Ne 130Th St",
    "iso:country":"US",
    "sg:address":"4502 NE 130th St",
    "sg:city":"Vancouver",
    "sg:classifiers":[
        {
            "category":"Building & Trades",
            "subcategory":"Landscaping Services",
            "type":"Services"
        }
    ],
    "sg:phone":"+1 360 891 4496",
    "sg:postcode":"98686",
    "sg:province":"WA",
    "sg:tags":[
        "lawn",
        "maintenance",
        "grounds"
    ],
    "wof:name":"Distinctive Landscape",
    "wof:placetype":"venue"
},
  "geometry": {"coordinates":[-122.623924,45.715819],"type":"Point"}
}