{
  "type": "Feature",
  "properties": {
    "addr:full":"12721 Renton Avenue S Seattle WA 98178",
    "addr:housenumber":"12721",
    "addr:postcode":"98178",
    "addr:street":"Renton Avenue S",
    "iso:country":"US",
    "sg:address":"12721 Renton Avenue S",
    "sg:city":"Seattle",
    "sg:classifiers":[
        {
            "category":"Autos & Motor Vehicles",
            "subcategory":"Automobile Sales",
            "type":"Retail Goods"
        }
    ],
    "sg:phone":"+1 206 632 5162",
    "sg:postcode":"98178",
    "sg:province":"WA",
    "sg:tags":[
        "limo"
    ],
    "wof:name":"Beeline Tours Ltd",
    "wof:placetype":"venue"
},
  "geometry": {"coordinates":[-122.236509,47.489149],"type":"Point"}
}