{
  "type": "Feature",
  "properties": {
    "addr:full":"26625 40th Ave S Kent WA 98032",
    "addr:housenumber":"26625",
    "addr:postcode":"98032",
    "addr:street":"40Th Ave S",
    "iso:country":"US",
    "sg:address":"26625 40th Ave S",
    "sg:city":"Kent",
    "sg:classifiers":[
        {
            "category":"Professional",
            "type":"Services"
        }
    ],
    "sg:phone":"+1 253 335 1393",
    "sg:postcode":"98032",
    "sg:province":"WA",
    "wof:name":"Spa Delphi",
    "wof:placetype":"venue"
},
  "geometry": {"coordinates":[-122.283964,47.361589],"type":"Point"}
}