{
  "type": "Feature",
  "properties": {
    "addr:full":"1010 Jadwin Ave Richland WA 99352",
    "addr:housenumber":"1010",
    "addr:postcode":"99352",
    "addr:street":"Jadwin Ave",
    "iso:country":"US",
    "sg:address":"1010 Jadwin Ave",
    "sg:city":"Richland",
    "sg:classifiers":[
        {
            "category":"Personal",
            "subcategory":"Barber",
            "type":"Services"
        }
    ],
    "sg:phone":"+1 509 943 8303",
    "sg:postcode":"99352",
    "sg:province":"WA",
    "sg:tags":[
        "shop"
    ],
    "wof:name":"Country Cuts",
    "wof:placetype":"venue"
},
  "geometry": {"coordinates":[-119.27790299999999,46.285516],"type":"Point"}
}