{
  "type": "Feature",
  "properties": {
    "addr:full":"10404 Silverdale Way NW Silverdale WA 98383",
    "addr:housenumber":"10404",
    "addr:postcode":"98383",
    "addr:street":"Silverdale Way Nw",
    "iso:country":"US",
    "sg:address":"10404 Silverdale Way NW",
    "sg:city":"Silverdale",
    "sg:classifiers":[
        {
            "category":"Restaurant",
            "type":"Food & Drink"
        }
    ],
    "sg:phone":"+1 360 337 2501",
    "sg:postcode":"98383",
    "sg:province":"WA",
    "sg:tags":[
        "eating"
    ],
    "wof:name":"Phad Thai Restaurant",
    "wof:placetype":"venue"
},
  "geometry": {"coordinates":[-122.687091,47.657276],"type":"Point"}
}