{
  "type": "Feature",
  "properties": {
    "addr:full":"3000 Rockefeller Ave Everett WA 98201",
    "addr:postcode":"3000;98201",
    "addr:street":"Rockefeller Ave",
    "iso:country":"US",
    "sg:address":"3000 Rockefeller Ave",
    "sg:city":"Everett",
    "sg:classifiers":[
        {
            "category":"Government",
            "subcategory":"Police Station",
            "type":"Public Place"
        }
    ],
    "sg:phone":"+1 425 407 3911",
    "sg:postcode":"98201",
    "sg:province":"WA",
    "sg:tags":[
        "dispatch"
    ],
    "wof:name":"Snopac 911",
    "wof:placetype":"venue"
},
  "geometry": {"coordinates":[-122.20573400000001,47.976586],"type":"Point"}
}