{
  "type": "Feature",
  "properties": {
    "addr:full":"9734 65th Ln SE Olympia WA 98513",
    "addr:housenumber":"9734",
    "addr:postcode":"98513",
    "addr:street":"65Th Ln Se",
    "iso:country":"US",
    "sg:address":"9734 65th Ln SE",
    "sg:city":"Olympia",
    "sg:classifiers":[
        {
            "category":"Farming",
            "subcategory":"Livestock Farm",
            "type":"Manufacturing & Wholesale Goods"
        }
    ],
    "sg:phone":"+1 360 459 3288",
    "sg:postcode":"98513",
    "sg:province":"WA",
    "sg:tags":[
        "equine"
    ],
    "wof:name":"Denvic Farm",
    "wof:placetype":"venue"
},
  "geometry": {"coordinates":[-122.734154,46.988776],"type":"Point"}
}