{
  "type": "Feature",
  "properties": {
    "addr:full":"24416 183rd Ct SE Kent WA 98042",
    "addr:housenumber":"24416",
    "addr:postcode":"98042",
    "addr:street":"183Rd Ct Se",
    "iso:country":"US",
    "sg:address":"24416 183rd Ct SE",
    "sg:city":"Kent",
    "sg:classifiers":[
        {
            "category":"Building & Trades",
            "subcategory":"Construction",
            "type":"Services"
        }
    ],
    "sg:phone":"+1 253 630 4333",
    "sg:postcode":"98042",
    "sg:province":"WA",
    "sg:tags":[
        "system",
        "specialty",
        "heating",
        "contractor",
        "air conditioning"
    ],
    "wof:name":"Mvg",
    "wof:placetype":"venue"
},
  "geometry": {"coordinates":[-122.09803599999999,47.383472],"type":"Point"}
}