{
  "type": "Feature",
  "properties": {
    "addr:full":"107 Washington Ave Bremerton WA 98337",
    "addr:housenumber":"107",
    "addr:postcode":"98337",
    "addr:street":"Washington Ave",
    "iso:country":"US",
    "sg:address":"107 Washington Ave",
    "sg:city":"Bremerton",
    "sg:classifiers":[
        {
            "category":"Insurance",
            "subcategory":"Hazard Insurance",
            "type":"Services"
        }
    ],
    "sg:phone":"+1 360 479 2910",
    "sg:postcode":"98337",
    "sg:province":"WA",
    "sg:tags":[
        "commercial",
        "business"
    ],
    "wof:name":"Cmg Insurance",
    "wof:placetype":"venue"
},
  "geometry": {"coordinates":[-122.625203,47.563871],"type":"Point"}
}