{
  "type": "Feature",
  "properties": {
    "addr:full":"10135 183rd Way SW Rochester WA 98579",
    "addr:housenumber":"10135",
    "addr:postcode":"98579",
    "addr:street":"183Rd Way Sw",
    "iso:country":"US",
    "sg:address":"10135 183rd Way SW",
    "sg:city":"Rochester",
    "sg:classifiers":[
        {
            "category":"Shopping",
            "subcategory":"Used Merchandise",
            "type":"Retail Goods"
        }
    ],
    "sg:phone":"+1 360 273 8544",
    "sg:postcode":"98579",
    "sg:province":"WA",
    "sg:tags":[
        "antique"
    ],
    "wof:name":"Johnny's",
    "wof:placetype":"venue"
},
  "geometry": {"coordinates":[-123.09058400000001,46.820684],"type":"Point"}
}