{
  "type": "Feature",
  "properties": {
    "addr:full":"5327 25th Ave S Seattle WA 98108",
    "addr:housenumber":"5327",
    "addr:postcode":"98108",
    "addr:street":"25Th Ave S",
    "iso:country":"US",
    "sg:address":"5327 25th Ave S",
    "sg:city":"Seattle",
    "sg:classifiers":[
        {
            "category":"Wholesale",
            "subcategory":"Toys & Hobbies",
            "type":"Manufacturing & Wholesale Goods"
        }
    ],
    "sg:phone":"+1 206 725 6853",
    "sg:postcode":"98108",
    "sg:province":"WA",
    "wof:name":"E&G Crafts",
    "wof:placetype":"venue"
},
  "geometry": {"coordinates":[-122.30049699999999,47.553936],"type":"Point"}
}