{
  "type": "Feature",
  "properties": {
    "iso:country":"US",
    "sg:address":"8610 S 235th Pl",
    "sg:city":"Kent",
    "sg:classifiers":[
        {
            "category":"Manufacturing",
            "subcategory":"Lumber",
            "type":"Manufacturing & Wholesale Goods"
        }
    ],
    "sg:phone":"+1 253 854 2713",
    "sg:postcode":"98031",
    "sg:province":"WA",
    "sg:tags":[
        "individual"
    ],
    "wof:name":"Seabury  Jaron",
    "wof:placetype":"venue"
},
  "geometry": {"coordinates":[-122.228303,47.392599],"type":"Point"}
}