{
  "type": "Feature",
  "properties": {
    "addr:full":"18920 217th Ave E Orting WA 98360",
    "addr:housenumber":"18920",
    "addr:postcode":"98360",
    "addr:street":"217Th Ave E",
    "iso:country":"US",
    "sg:address":"18920 217th Ave E",
    "sg:city":"Orting",
    "sg:classifiers":[
        {
            "category":"Building & Trades",
            "subcategory":"Construction",
            "type":"Services"
        }
    ],
    "sg:phone":"+1 360 893 8301",
    "sg:postcode":"98360",
    "sg:province":"WA",
    "sg:tags":[
        "hanging",
        "contractor"
    ],
    "wof:name":"Armstrong Enterprises",
    "wof:placetype":"venue"
},
  "geometry": {"coordinates":[-122.14016599999999,47.084115],"type":"Point"}
}