{
  "type": "Feature",
  "properties": {
    "addr:full":"7505 204th St NE Arlington WA 98223",
    "addr:housenumber":"7505",
    "addr:postcode":"98223",
    "addr:street":"204Th St Ne",
    "iso:country":"US",
    "sg:address":"7505 204th St NE",
    "sg:city":"Arlington",
    "sg:classifiers":[
        {
            "category":"Restaurant",
            "type":"Food & Drink"
        }
    ],
    "sg:menulink":"http://www.allmenus.com/wa/arlington/145083-subway/menu/",
    "sg:phone":"+1 360 403 7065",
    "sg:postcode":"98223",
    "sg:province":"WA",
    "sg:tags":[
        "american",
        "sandwich"
    ],
    "wof:name":"Subway",
    "wof:placetype":"venue"
},
  "geometry": {"coordinates":[-122.128891,48.180813],"type":"Point"}
}