{
  "type": "Feature",
  "properties": {
    "addr:full":"9720 E Shannon Ave Spokane WA 99206",
    "addr:housenumber":"9720",
    "addr:postcode":"99206",
    "addr:street":"E Shannon Ave",
    "iso:country":"US",
    "sg:address":"9720 E Shannon Ave",
    "sg:city":"Spokane",
    "sg:classifiers":[
        {
            "category":"Wholesale",
            "subcategory":"Vending Machines",
            "type":"Manufacturing & Wholesale Goods"
        }
    ],
    "sg:phone":"+1 509 924 6912",
    "sg:postcode":"99206",
    "sg:province":"WA",
    "sg:tags":[
        "operator"
    ],
    "wof:name":"Dj S All In One Vending",
    "wof:placetype":"venue"
},
  "geometry": {"coordinates":[-117.27372800000001,47.675986],"type":"Point"}
}