{
  "type": "Feature",
  "properties": {
    "addr:full":"309 E 2nd Ave Ellensburg WA 98926",
    "addr:housenumber":"309",
    "addr:postcode":"98926",
    "addr:street":"E 2Nd Ave",
    "iso:country":"US",
    "sg:address":"309 E 2nd Ave",
    "sg:city":"Ellensburg",
    "sg:classifiers":[
        {
            "category":"Health Services",
            "subcategory":"Doctor",
            "type":"Services"
        }
    ],
    "sg:phone":"+1 509 962 6172",
    "sg:postcode":"98926",
    "sg:province":"WA",
    "wof:name":"David L Wright DDS",
    "wof:placetype":"venue"
},
  "geometry": {"coordinates":[-120.543137,46.993588],"type":"Point"}
}