{
  "type": "Feature",
  "properties": {
    "addr:full":"2805 SW Roxbury St Seattle WA 98126",
    "addr:housenumber":"2805",
    "addr:postcode":"98126",
    "addr:street":"Sw Roxbury St",
    "iso:country":"US",
    "sg:address":"2805 SW Roxbury St",
    "sg:city":"Seattle",
    "sg:classifiers":[
        {
            "category":"Autos & Motor Vehicles",
            "subcategory":"Fuel & Gas Station",
            "type":"Retail Goods"
        },
        {
            "category":"Retail",
            "subcategory":"Car Wash",
            "type":"Services"
        },
        {
            "category":"Food & Beverages",
            "subcategory":"Groceries & Convenience Stores",
            "type":"Retail Goods"
        }
    ],
    "sg:phone":"+1 206 937 9553",
    "sg:postcode":"98126",
    "sg:province":"WA",
    "sg:website":"http://www.shell.com",
    "wof:name":"Roxbury Shell",
    "wof:placetype":"venue"
},
  "geometry": {"coordinates":[-122.36900300000001,47.5173],"type":"Point"}
}