{
  "type": "Feature",
  "properties": {
    "addr:full":"15551 Midvale Ave N Seattle WA 98133",
    "addr:housenumber":"15551",
    "addr:postcode":"98133",
    "addr:street":"Midvale Ave N",
    "iso:country":"US",
    "sg:address":"15551 Midvale Ave N",
    "sg:city":"Seattle",
    "sg:classifiers":[
        {
            "category":"Manufacturing",
            "subcategory":"Paper Products",
            "type":"Manufacturing & Wholesale Goods"
        }
    ],
    "sg:phone":"+1 206 261 7238",
    "sg:postcode":"98133",
    "sg:province":"WA",
    "sg:tags":[
        "mill",
        "operation"
    ],
    "wof:name":"Ambient Art",
    "wof:placetype":"venue"
},
  "geometry": {"coordinates":[-122.344048,47.742619],"type":"Point"}
}