{
  "type": "Feature",
  "properties": {
    "addr:full":"2505 2nd Ave Ste 106 Seattle WA 98121",
    "addr:housenumber":"2505",
    "addr:postcode":"98121",
    "addr:street":"2Nd Ave Ste 106",
    "iso:country":"US",
    "sg:address":"2505 2nd Ave Ste 106",
    "sg:city":"Seattle",
    "sg:classifiers":[
        {
            "category":"Personal",
            "subcategory":"Beauty Salon",
            "type":"Services"
        }
    ],
    "sg:phone":"+1 206 838 8626",
    "sg:postcode":"98121",
    "sg:province":"WA",
    "sg:tags":[
        "spa"
    ],
    "sg:website":"www.joevir.com",
    "wof:name":"Joevir",
    "wof:placetype":"venue"
},
  "geometry": {"coordinates":[-122.34795699999999,47.615439],"type":"Point"}
}