{
  "type": "Feature",
  "properties": {
    "iso:country":"US",
    "sg:address":"14919 Orting Kapowsin Hwy E",
    "sg:city":"Orting",
    "sg:classifiers":[
        {
            "category":"Government",
            "subcategory":"Fire Station",
            "type":"Public Place"
        }
    ],
    "sg:phone":"+1 360 893 7857",
    "sg:postcode":"98360",
    "sg:province":"WA",
    "sg:tags":[
        "protection"
    ],
    "wof:name":"Pierce County Fire District 18",
    "wof:placetype":"venue"
},
  "geometry": {"coordinates":[-122.215934,47.081728],"type":"Point"}
}