{
  "type": "Feature",
  "properties": {
    "addr:full":"1090 Silver Lake Rd Oak Harbor WA 98277",
    "addr:housenumber":"1090",
    "addr:postcode":"98277",
    "addr:street":"Silver Lake Rd",
    "iso:country":"US",
    "sg:address":"1090 Silver Lake Rd",
    "sg:city":"Oak Harbor",
    "sg:classifiers":[
        {
            "category":"Retail",
            "subcategory":"Portrait Studio",
            "type":"Services"
        }
    ],
    "sg:phone":"+1 360 679 4194",
    "sg:postcode":"98277",
    "sg:province":"WA",
    "sg:tags":[
        "photo"
    ],
    "wof:name":"One Moores Point of View",
    "wof:placetype":"venue"
},
  "geometry": {"coordinates":[-122.55711100000001,48.317947],"type":"Point"}
}