{
  "type": "Feature",
  "properties": {
    "addr:full":"1494 Eastmont Ave East Wenatchee WA 98802",
    "addr:housenumber":"1494",
    "addr:postcode":"98802",
    "addr:street":"Eastmont Ave",
    "iso:country":"US",
    "sg:address":"1494 Eastmont Ave",
    "sg:city":"East Wenatchee",
    "sg:classifiers":[
        {
            "category":"Professional",
            "subcategory":"Management & Consulting",
            "type":"Services"
        }
    ],
    "sg:phone":"+1 509 886 3630",
    "sg:postcode":"98802",
    "sg:province":"WA",
    "sg:tags":[
        "consultant",
        "security",
        "system"
    ],
    "wof:name":"Robert Associates Inc",
    "wof:placetype":"venue"
},
  "geometry": {"coordinates":[-120.28178,47.427556],"type":"Point"}
}