{
  "type": "Feature",
  "properties": {
    "addr:full":"309 S G St Tacoma WA 98405",
    "addr:housenumber":"309",
    "addr:postcode":"98405",
    "addr:street":"S G St",
    "iso:country":"US",
    "sg:address":"309 S G St",
    "sg:city":"Tacoma",
    "sg:classifiers":[
        {
            "category":"Health Services",
            "subcategory":"Doctor",
            "type":"Services"
        }
    ],
    "sg:phone":"+1 253 272 1865",
    "sg:postcode":"98405",
    "sg:province":"WA",
    "sg:tags":[
        "physician",
        "surgeon"
    ],
    "wof:name":"Silkworth Clinic",
    "wof:placetype":"venue"
},
  "geometry": {"coordinates":[-122.44745399999999,47.259914],"type":"Point"}
}