{
  "type": "Feature",
  "properties": {
    "addr:full":"2405 SW 151st St Burien WA 98166",
    "addr:housenumber":"2405",
    "addr:postcode":"98166",
    "addr:street":"Sw 151St St",
    "iso:country":"US",
    "sg:address":"2405 SW 151st St",
    "sg:city":"Burien",
    "sg:classifiers":[
        {
            "category":"Conference Center",
            "type":"Public Place"
        }
    ],
    "sg:phone":"+1 206 244 4002",
    "sg:postcode":"98166",
    "sg:province":"WA",
    "sg:tags":[
        "lecture",
        "speakers",
        "seminar"
    ],
    "wof:name":"Dennis Mcinteer",
    "wof:placetype":"venue"
},
  "geometry": {"coordinates":[-122.363536,47.467564],"type":"Point"}
}