{
  "type": "Feature",
  "properties": {
    "addr:full":"12805 Chain Lake Rd Snohomish WA 98290",
    "addr:housenumber":"12805",
    "addr:postcode":"98290",
    "addr:street":"Chain Lake Rd",
    "iso:country":"US",
    "sg:address":"12805 Chain Lake Rd",
    "sg:city":"Snohomish",
    "sg:classifiers":[
        {
            "category":"Retail",
            "subcategory":"Repair Shop",
            "type":"Services"
        }
    ],
    "sg:phone":"+1 360 794 7320",
    "sg:postcode":"98290",
    "sg:province":"WA",
    "sg:tags":[
        "welding"
    ],
    "wof:name":"Bywater Welding",
    "wof:placetype":"venue"
},
  "geometry": {"coordinates":[-121.969151,47.880583],"type":"Point"}
}