{
  "type": "Feature",
  "properties": {
    "addr:full":"5041 35th Ave NE Seattle WA 98105",
    "addr:housenumber":"5041",
    "addr:postcode":"98105",
    "addr:street":"35Th Ave Ne",
    "iso:country":"US",
    "sg:address":"5041 35th Ave NE",
    "sg:city":"Seattle",
    "sg:classifiers":[
        {
            "category":"Real Estate",
            "subcategory":"Developer",
            "type":"Services"
        }
    ],
    "sg:phone":"+1 206 522 0996",
    "sg:postcode":"98105",
    "sg:province":"WA",
    "sg:tags":[
        "cemetery"
    ],
    "wof:name":"Calvary Catholic Cemetery",
    "wof:placetype":"venue"
},
  "geometry": {"coordinates":[-122.29025300000001,47.666389],"type":"Point"}
}