{
  "type": "Feature",
  "properties": {
    "addr:full":"404 N 2nd St Roslyn WA 98941",
    "addr:housenumber":"404",
    "addr:postcode":"98941",
    "addr:street":"N 2Nd St",
    "iso:country":"US",
    "sg:address":"404 N 2nd St",
    "sg:city":"Roslyn",
    "sg:classifiers":[
        {
            "category":"Building & Trades",
            "subcategory":"Landscaping Services",
            "type":"Services"
        }
    ],
    "sg:phone":"+1 509 649 2387",
    "sg:postcode":"98941",
    "sg:province":"WA",
    "sg:tags":[
        "tree"
    ],
    "wof:name":"Maple's Tree Specialist",
    "wof:placetype":"venue"
},
  "geometry": {"coordinates":[-120.99722800000001,47.225686],"type":"Point"}
}