{
  "type": "Feature",
  "properties": {
    "addr:full":"9590 Windsong Loop NE Bainbridge Isle WA 98110",
    "addr:housenumber":"9590",
    "addr:postcode":"98110",
    "addr:street":"Windsong Loop Ne;Isle",
    "iso:country":"US",
    "sg:address":"9590 Windsong Loop NE",
    "sg:city":"Bainbridge Isle",
    "sg:classifiers":[
        {
            "category":"Building & Trades",
            "subcategory":"Construction",
            "type":"Services"
        }
    ],
    "sg:phone":"+1 206 842 3514",
    "sg:postcode":"98110",
    "sg:province":"WA",
    "sg:tags":[
        "residential",
        "carpenter",
        "contractor"
    ],
    "wof:name":"Sensitive Carpenters The",
    "wof:placetype":"venue"
},
  "geometry": {"coordinates":[-122.52263499999999,47.666034],"type":"Point"}
}