{
  "type": "Feature",
  "properties": {
    "addr:full":"901 S West Blvd Aberdeen WA 98520",
    "addr:housenumber":"901",
    "addr:postcode":"98520",
    "addr:street":"S West Blvd",
    "iso:country":"US",
    "sg:address":"901 S West Blvd",
    "sg:city":"Aberdeen",
    "sg:classifiers":[
        {
            "category":"Building & Trades",
            "subcategory":"Cleaning & Sanitation",
            "type":"Services"
        }
    ],
    "sg:phone":"+1 360 537 1305",
    "sg:postcode":"98520",
    "sg:province":"WA",
    "sg:tags":[
        "maintenance"
    ],
    "wof:name":"Executive Cleaning Service",
    "wof:placetype":"venue"
},
  "geometry": {"coordinates":[-123.781156,46.963221],"type":"Point"}
}