{
  "type": "Feature",
  "properties": {
    "addr:full":"9701 74th Ave E Puyallup WA 98373",
    "addr:housenumber":"9701",
    "addr:postcode":"98373",
    "addr:street":"74Th Ave E",
    "iso:country":"US",
    "sg:address":"9701 74th Ave E",
    "sg:city":"Puyallup",
    "sg:classifiers":[
        {
            "category":"Personal",
            "type":"Services"
        }
    ],
    "sg:phone":"+1 253 224 9635",
    "sg:postcode":"98373",
    "sg:province":"WA",
    "wof:name":"Angela Bouma Lmp",
    "wof:placetype":"venue"
},
  "geometry": {"coordinates":[-122.330777,47.167771],"type":"Point"}
}