{
  "type": "Feature",
  "properties": {
    "iso:country":"US",
    "sg:address":"14611 W Tepee Rd",
    "sg:city":"Spokane",
    "sg:classifiers":[
        {
            "category":"Professional",
            "subcategory":"Management & Consulting",
            "type":"Services"
        }
    ],
    "sg:phone":"+1 509 244 3111",
    "sg:postcode":"99224",
    "sg:province":"WA",
    "wof:name":"Bell Innovations",
    "wof:placetype":"venue"
},
  "geometry": {"coordinates":[-117.61161800000001,47.724468],"type":"Point"}
}