{
  "type": "Feature",
  "properties": {
    "addr:full":"3805 N Market St Spokane WA 99207",
    "addr:housenumber":"3805",
    "addr:postcode":"99207",
    "addr:street":"N Market St",
    "iso:country":"US",
    "sg:address":"3805 N Market St",
    "sg:city":"Spokane",
    "sg:classifiers":[
        {
            "category":"Manufacturing",
            "subcategory":"Leather Goods",
            "type":"Manufacturing & Wholesale Goods"
        },
        {
            "category":"Shopping",
            "subcategory":"Shoes",
            "type":"Retail Goods"
        }
    ],
    "sg:phone":"+1 509 483 1248",
    "sg:postcode":"99207",
    "sg:province":"WA",
    "sg:tags":[
        "cut",
        "findings",
        "mfg",
        "m",
        "boot",
        "footwear",
        "shoe",
        "stock"
    ],
    "sg:website":"www.nicksboots.com",
    "wof:name":"Nick's Custom Boots",
    "wof:placetype":"venue"
},
  "geometry": {"coordinates":[-117.36512999999999,47.693401],"type":"Point"}
}