{
  "type": "Feature",
  "properties": {
    "addr:full":"31307 SE 354th St Enumclaw WA 98022",
    "addr:postcode":"31307;98022",
    "addr:street":"Se 354Th St",
    "iso:country":"US",
    "sg:address":"31307 SE 354th St",
    "sg:city":"Enumclaw",
    "sg:classifiers":[
        {
            "category":"Manufacturing",
            "subcategory":"Metals",
            "type":"Manufacturing & Wholesale Goods"
        }
    ],
    "sg:phone":"+1 360 886 7787",
    "sg:postcode":"98022",
    "sg:province":"WA",
    "sg:tags":[
        "mfg"
    ],
    "wof:name":"T & T Pressure Washing",
    "wof:placetype":"venue"
},
  "geometry": {"coordinates":[-121.92717500000001,47.283044],"type":"Point"}
}