{
  "type": "Feature",
  "properties": {
    "addr:full":"11615 Hwy 99 Everett WA 98204",
    "addr:housenumber":"11615",
    "addr:postcode":"98204",
    "addr:street":"Hwy 99",
    "iso:country":"US",
    "sg:address":"11615 Hwy 99",
    "sg:city":"Everett",
    "sg:classifiers":[
        {
            "category":"Retail",
            "subcategory":"Portrait Studio",
            "type":"Services"
        }
    ],
    "sg:phone":"+1 425 348 3983",
    "sg:postcode":"98204",
    "sg:province":"WA",
    "sg:tags":[
        "photo"
    ],
    "wof:name":"Noble Enterprises",
    "wof:placetype":"venue"
},
  "geometry": {"coordinates":[-122.25429200000001,47.893569],"type":"Point"}
}