{
  "type": "Feature",
  "properties": {
    "iso:country":"US",
    "sg:address":"1802 12th Ave NW",
    "sg:city":"Issaquah",
    "sg:classifiers":[
        {
            "category":"Shopping",
            "subcategory":"Hobbies, Toys, & Games",
            "type":"Retail Goods"
        }
    ],
    "sg:phone":"+1 425 369 2333",
    "sg:postcode":"98027",
    "sg:province":"WA",
    "wof:name":"Toys 2 Cool",
    "wof:placetype":"venue"
},
  "geometry": {"coordinates":[-122.057253,47.548744],"type":"Point"}
}