{
  "type": "Feature",
  "properties": {
    "addr:full":"601 NE Anna Rd Poulsbo WA 98370",
    "addr:housenumber":"601",
    "addr:postcode":"98370",
    "addr:street":"Ne Anna Rd",
    "iso:country":"US",
    "sg:address":"601 NE Anna Rd",
    "sg:city":"Poulsbo",
    "sg:classifiers":[
        {
            "category":"Wholesale",
            "subcategory":"Plants",
            "type":"Manufacturing & Wholesale Goods"
        }
    ],
    "sg:phone":"+1 360 697 1696",
    "sg:postcode":"98370",
    "sg:province":"WA",
    "sg:tags":[
        "supply"
    ],
    "wof:name":"Woodland Gardens",
    "wof:placetype":"venue"
},
  "geometry": {"coordinates":[-122.645803,47.690311],"type":"Point"}
}