{
  "type": "Feature",
  "properties": {
    "addr:full":"7240 Ledroit Ct SW Seattle WA 98136",
    "addr:housenumber":"7240",
    "addr:postcode":"98136",
    "addr:street":"Ledroit Ct Sw",
    "iso:country":"US",
    "sg:address":"7240 Ledroit Ct SW",
    "sg:city":"Seattle",
    "sg:classifiers":[
        {
            "category":"Shopping",
            "subcategory":"Hobbies, Toys, & Games",
            "type":"Retail Goods"
        }
    ],
    "sg:phone":"+1 206 933 9688",
    "sg:postcode":"98136",
    "sg:province":"WA",
    "wof:name":"Frankiez World",
    "wof:placetype":"venue"
},
  "geometry": {"coordinates":[-122.39472499999999,47.538434],"type":"Point"}
}