{
  "type": "Feature",
  "properties": {
    "addr:full":"18905 33rd Ave W Ste 207 Lynnwood WA 98036",
    "addr:housenumber":"18905",
    "addr:postcode":"98036",
    "addr:street":"33Rd Ave W Ste 207",
    "iso:country":"US",
    "sg:address":"18905 33rd Ave W Ste 207",
    "sg:city":"Lynnwood",
    "sg:classifiers":[
        {
            "category":"Social Services",
            "type":"Services"
        }
    ],
    "sg:phone":"+1 425 775 7658",
    "sg:postcode":"98036",
    "sg:province":"WA",
    "sg:tags":[
        "consultant",
        "security",
        "representative"
    ],
    "sg:website":"http://www.ssa.gov",
    "wof:name":"Social Security Administration",
    "wof:placetype":"venue"
},
  "geometry": {"coordinates":[-122.27773999999999,47.825381],"type":"Point"}
}