{
  "type": "Feature",
  "properties": {
    "addr:full":"133 Mashell Ave Eatonville WA 98328",
    "addr:housenumber":"133",
    "addr:postcode":"98328",
    "addr:street":"Mashell Ave",
    "iso:country":"US",
    "sg:address":"133 Mashell Ave",
    "sg:city":"Eatonville",
    "sg:classifiers":[
        {
            "category":"Professional",
            "subcategory":"Advertising",
            "type":"Services"
        }
    ],
    "sg:phone":"+1 360 832 3411",
    "sg:postcode":"98328",
    "sg:province":"WA",
    "sg:website":"www.dispatchnews.com",
    "wof:name":"Dispatch",
    "wof:placetype":"venue"
},
  "geometry": {"coordinates":[-122.266639,46.868618],"type":"Point"}
}