{
  "type": "Feature",
  "properties": {
    "addr:full":"4004 100th St SW Lakewood WA 98499",
    "addr:housenumber":"4004",
    "addr:postcode":"98499",
    "addr:street":"100Th St Sw",
    "iso:country":"US",
    "sg:address":"4004 100th St SW",
    "sg:city":"Lakewood",
    "sg:classifiers":[
        {
            "category":"Building & Trades",
            "subcategory":"Construction",
            "type":"Services"
        }
    ],
    "sg:phone":"+1 253 581 3390",
    "sg:postcode":"98499",
    "sg:province":"WA",
    "sg:tags":[
        "contractor"
    ],
    "wof:name":"Kimrey Construction",
    "wof:placetype":"venue"
},
  "geometry": {"coordinates":[-122.49099699999999,47.167301],"type":"Point"}
}