{
  "type": "Feature",
  "properties": {
    "addr:full":"9500 NE 191st St Bothell WA 98011",
    "addr:housenumber":"9500",
    "addr:postcode":"98011",
    "addr:street":"Ne 191St St",
    "iso:country":"US",
    "sg:address":"9500 NE 191st St",
    "sg:city":"Bothell",
    "sg:classifiers":[
        {
            "category":"Organizations",
            "subcategory":"Religious Organization",
            "type":"Services"
        }
    ],
    "sg:phone":"+1 425 483 0900",
    "sg:postcode":"98011",
    "sg:province":"WA",
    "sg:tags":[
        "child",
        "day",
        "care"
    ],
    "wof:name":"Living Hope Christian Church",
    "wof:placetype":"venue"
},
  "geometry": {"coordinates":[-122.210674,47.765807],"type":"Point"}
}