{
  "type": "Feature",
  "properties": {
    "addr:full":"15925 SE 44th Way Issaquah WA 98027",
    "addr:postcode":"15925;98027",
    "addr:street":"Se 44Th Way",
    "iso:country":"US",
    "sg:address":"15925 SE 44th Way",
    "sg:city":"Issaquah",
    "sg:classifiers":[
        {
            "category":"Shopping",
            "subcategory":"Clothing, Apparel, & Fashions",
            "type":"Retail Goods"
        }
    ],
    "sg:phone":"+1 425 746 1930",
    "sg:postcode":"98027",
    "sg:province":"WA",
    "sg:tags":[
        "consultant"
    ],
    "wof:name":"Roberts Designs",
    "wof:placetype":"venue"
},
  "geometry": {"coordinates":[-122.125936,47.566825],"type":"Point"}
}