{
  "type": "Feature",
  "properties": {
    "iso:country":"US",
    "sg:address":"4511 S Pass Rd",
    "sg:city":"Sumas",
    "sg:classifiers":[
        {
            "category":"Building & Trades",
            "subcategory":"Landscaping Services",
            "type":"Services"
        }
    ],
    "sg:phone":"+1 360 966 5107",
    "sg:postcode":"98295",
    "sg:province":"WA",
    "wof:name":"Hedgehog Yard & Plant Services",
    "wof:placetype":"venue"
},
  "geometry": {"coordinates":[-122.241544,48.940393],"type":"Point"}
}