{
  "type": "Feature",
  "properties": {
    "addr:full":"672 S Orcas St Seattle WA 98108",
    "addr:housenumber":"672",
    "addr:postcode":"98108",
    "addr:street":"S Orcas St",
    "iso:country":"US",
    "sg:address":"672 S Orcas St",
    "sg:city":"Seattle",
    "sg:classifiers":[
        {
            "category":"Shopping",
            "type":"Retail Goods"
        }
    ],
    "sg:phone":"+1 206 767 6847",
    "sg:postcode":"98108",
    "sg:province":"WA",
    "sg:tags":[
        "dry",
        "ice"
    ],
    "wof:name":"American Dry Ice Corp",
    "wof:placetype":"venue"
},
  "geometry": {"coordinates":[-122.324924,47.551545],"type":"Point"}
}