{
  "type": "Feature",
  "properties": {
    "addr:full":"614 Regents Blvd Tacoma WA 98466",
    "addr:housenumber":"614",
    "addr:postcode":"98466",
    "addr:street":"Regents Blvd",
    "iso:country":"US",
    "sg:address":"614 Regents Blvd",
    "sg:city":"Tacoma",
    "sg:classifiers":[
        {
            "category":"Professional",
            "subcategory":"Computer Services",
            "type":"Services"
        }
    ],
    "sg:phone":"+1 253 564 4000",
    "sg:postcode":"98466",
    "sg:province":"WA",
    "sg:tags":[
        "programing",
        "custom"
    ],
    "wof:name":"Fransen King Ltd",
    "wof:placetype":"venue"
},
  "geometry": {"coordinates":[-122.513989,47.237714],"type":"Point"}
}