{
  "type": "Feature",
  "properties": {
    "addr:full":"1878 Marketplace Dr Burlington WA 98233",
    "addr:housenumber":"1878",
    "addr:postcode":"98233",
    "addr:street":"Marketplace Dr",
    "iso:country":"US",
    "sg:address":"1878 Marketplace Dr",
    "sg:city":"Burlington",
    "sg:classifiers":[
        {
            "category":"Shopping",
            "subcategory":"Computers & Home Electronics",
            "type":"Retail Goods"
        }
    ],
    "sg:phone":"+1 360 757 2745",
    "sg:postcode":"98233",
    "sg:province":"WA",
    "sg:tags":[
        "game",
        "video"
    ],
    "wof:name":"Game Stop Corp",
    "wof:placetype":"venue"
},
  "geometry": {"coordinates":[-122.33825400000001,48.449753],"type":"Point"}
}