{
  "type": "Feature",
  "properties": {
    "addr:full":"601 108th Ave NE Suite 2250 Bellevue WA 98004",
    "addr:housenumber":"601",
    "addr:postcode":"98004",
    "addr:street":"108Th Ave Ne Suite 2250",
    "iso:country":"US",
    "sg:address":"601 108th Ave NE Suite 2250",
    "sg:city":"Bellevue",
    "sg:classifiers":[
        {
            "category":"Real Estate",
            "subcategory":"Architect",
            "type":"Services"
        }
    ],
    "sg:phone":"+1 425 641 9200",
    "sg:postcode":"98004",
    "sg:province":"WA",
    "sg:website":"www.jpcarchitects.com",
    "wof:name":"JPC Architects",
    "wof:placetype":"venue"
},
  "geometry": {"coordinates":[-122.196285,47.615611],"type":"Point"}
}