{
  "type": "Feature",
  "properties": {
    "addr:full":"14822 113th Street Kp N Gig Harbor WA 98329",
    "addr:housenumber":"14822",
    "addr:postcode":"98329",
    "addr:street":"113Th Street Kp N",
    "iso:country":"US",
    "sg:address":"14822 113th Street Kp N",
    "sg:city":"Gig Harbor",
    "sg:classifiers":[
        {
            "category":"Building & Trades",
            "subcategory":"Construction",
            "type":"Services"
        }
    ],
    "sg:phone":"+1 253 884 9669",
    "sg:postcode":"98329",
    "sg:province":"WA",
    "sg:tags":[
        "contractor"
    ],
    "wof:name":"Jon B Warfield & Sons Mas",
    "wof:placetype":"venue"
},
  "geometry": {"coordinates":[-122.734523,47.36],"type":"Point"}
}