{
  "type": "Feature",
  "properties": {
    "addr:full":"4318 6th Ave Tacoma WA 98406",
    "addr:housenumber":"4318",
    "addr:postcode":"98406",
    "addr:street":"6Th Ave",
    "iso:country":"US",
    "sg:address":"4318 6th Ave",
    "sg:city":"Tacoma",
    "sg:classifiers":[
        {
            "category":"Personal",
            "subcategory":"Barber",
            "type":"Services"
        }
    ],
    "sg:phone":"+1 253 759 5208",
    "sg:postcode":"98406",
    "sg:province":"WA",
    "wof:name":"Gordon's Barber Shop",
    "wof:placetype":"venue"
},
  "geometry": {"coordinates":[-122.494287,47.255316],"type":"Point"}
}