{
  "type": "Feature",
  "properties": {
    "addr:full":"13248 10th Ave S Burien WA 98168",
    "addr:housenumber":"13248",
    "addr:postcode":"98168",
    "addr:street":"10Th Ave S Burien",
    "iso:country":"US",
    "sg:address":"13248 10th Ave S",
    "sg:city":"Burien",
    "sg:classifiers":[
        {
            "category":"Retail",
            "subcategory":"Laundry & Dry Cleaning",
            "type":"Services"
        },
        {
            "category":"Building & Trades",
            "subcategory":"Cleaning & Sanitation",
            "type":"Services"
        }
    ],
    "sg:phone":"+1 206 762 3547",
    "sg:postcode":"98168",
    "sg:province":"WA",
    "sg:tags":[
        "cleaner",
        "upholstery",
        "fabric",
        "rug",
        "protection",
        "furniture",
        "carpet"
    ],
    "wof:name":"Protech",
    "wof:placetype":"venue"
},
  "geometry": {"coordinates":[-122.32070899999999,47.483403],"type":"Point"}
}