{
  "type": "Feature",
  "properties": {
    "addr:full":"11004 SE 173rd St Renton WA 98055",
    "addr:postcode":"11004;98055",
    "addr:street":"Se 173Rd St",
    "iso:country":"US",
    "sg:address":"11004 SE 173rd St",
    "sg:city":"Renton",
    "sg:classifiers":[
        {
            "category":"Personal",
            "subcategory":"Beauty Salon",
            "type":"Services"
        }
    ],
    "sg:phone":"+1 425 277 6619",
    "sg:postcode":"98055",
    "sg:province":"WA",
    "sg:tags":[
        "shop"
    ],
    "wof:name":"KB Salon",
    "wof:placetype":"venue"
},
  "geometry": {"coordinates":[-122.19417199999999,47.447559],"type":"Point"}
}