{
  "type": "Feature",
  "properties": {
    "addr:full":"1405 Boylston Avenue Seattle WA 98122",
    "addr:housenumber":"1405",
    "addr:postcode":"98122",
    "addr:street":"Boylston Avenue",
    "iso:country":"US",
    "sg:address":"1405 Boylston Avenue",
    "sg:city":"Seattle",
    "sg:classifiers":[
        {
            "category":"Professional",
            "subcategory":"Art Services",
            "type":"Services"
        }
    ],
    "sg:phone":"+1 206 322 4323",
    "sg:postcode":"98122",
    "sg:province":"WA",
    "sg:tags":[
        "graphic",
        "design"
    ],
    "sg:website":"www.catchstudio.com",
    "wof:name":"Catch Design Studio",
    "wof:placetype":"venue"
},
  "geometry": {"coordinates":[-122.323547,47.613076],"type":"Point"}
}