{
  "type": "Feature",
  "properties": {
    "addr:full":"260 Monroe Rd Port Angeles WA 98362",
    "addr:housenumber":"260",
    "addr:postcode":"98362",
    "addr:street":"Monroe Rd",
    "iso:country":"US",
    "sg:address":"260 Monroe Rd",
    "sg:city":"Port Angeles",
    "sg:classifiers":[
        {
            "category":"Retail",
            "subcategory":"Funeral Services",
            "type":"Services"
        }
    ],
    "sg:phone":"+1 360 681 4922",
    "sg:postcode":"98362",
    "sg:province":"WA",
    "wof:name":"Sequim Snset Crmtion Brial Svc",
    "wof:placetype":"venue"
},
  "geometry": {"coordinates":[-123.386411,48.100907],"type":"Point"}
}