{
  "type": "Feature",
  "properties": {
    "addr:full":"2626 Cascade St Clarkston WA 99403",
    "addr:housenumber":"2626",
    "addr:postcode":"99403",
    "addr:street":"Cascade St",
    "iso:country":"US",
    "sg:address":"2626 Cascade St",
    "sg:city":"Clarkston",
    "sg:classifiers":[
        {
            "category":"Social Services",
            "subcategory":"Child Care",
            "type":"Services"
        }
    ],
    "sg:phone":"+1 509 758 8382",
    "sg:postcode":"99403",
    "sg:province":"WA",
    "sg:tags":[
        "nursery",
        "day"
    ],
    "wof:name":"Tendercare Daycare",
    "wof:placetype":"venue"
},
  "geometry": {"coordinates":[-117.092084,46.384344],"type":"Point"}
}