{
  "type": "Feature",
  "properties": {
    "addr:full":"2259 NW 63rd St Seattle WA 98107",
    "addr:housenumber":"2259",
    "addr:postcode":"98107",
    "addr:street":"Nw 63Rd St",
    "iso:country":"US",
    "sg:address":"2259 NW 63rd St",
    "sg:city":"Seattle",
    "sg:classifiers":[
        {
            "category":"Home & Garden",
            "subcategory":"Carpets & Floor Coverings",
            "type":"Retail Goods"
        }
    ],
    "sg:phone":"+1 206 654 4456",
    "sg:postcode":"98107",
    "sg:province":"WA",
    "sg:tags":[
        "rug"
    ],
    "wof:name":"Elite Fire & Safety",
    "wof:placetype":"venue"
},
  "geometry": {"coordinates":[-122.38642400000001,47.674557],"type":"Point"}
}