{
  "type": "Feature",
  "properties": {
    "addr:full":"510 N Market Blvd Chehalis WA 98532",
    "addr:housenumber":"510",
    "addr:postcode":"98532",
    "addr:street":"N Market Blvd",
    "iso:country":"US",
    "sg:address":"510 N Market Blvd",
    "sg:city":"Chehalis",
    "sg:classifiers":[
        {
            "category":"Shopping",
            "subcategory":"Crafts & Fabrics",
            "type":"Retail Goods"
        }
    ],
    "sg:phone":"+1 360 748 3295",
    "sg:postcode":"98532",
    "sg:province":"WA",
    "sg:tags":[
        "shop",
        "repair",
        "sewing"
    ],
    "wof:name":"Billie's Designer Fabrics",
    "wof:placetype":"venue"
},
  "geometry": {"coordinates":[-122.97117299999999,46.666115],"type":"Point"}
}