{
  "type": "Feature",
  "properties": {
    "addr:full":"2988 Jackson Hwy Chehalis WA 98532",
    "addr:housenumber":"2988",
    "addr:postcode":"98532",
    "addr:street":"Jackson Hwy",
    "iso:country":"US",
    "sg:address":"2988 Jackson Hwy",
    "sg:city":"Chehalis",
    "sg:classifiers":[
        {
            "category":"Autos & Motor Vehicles",
            "subcategory":"Fuel & Gas Station",
            "type":"Retail Goods"
        }
    ],
    "sg:phone":"+1 360 748 3017",
    "sg:postcode":"98532",
    "sg:province":"WA",
    "sg:tags":[
        "independent",
        "grocery",
        "store"
    ],
    "wof:name":"Bobs Corner Market",
    "wof:placetype":"venue"
},
  "geometry": {"coordinates":[-122.88936099999999,46.61699],"type":"Point"}
}