{
  "type": "Feature",
  "properties": {
    "addr:full":"3202 N 33rd St Tacoma WA 98407",
    "addr:housenumber":"3202",
    "addr:postcode":"98407",
    "addr:street":"N 33Rd St",
    "iso:country":"US",
    "sg:address":"3202 N 33rd St",
    "sg:city":"Tacoma",
    "sg:classifiers":[
        {
            "category":"Health Services",
            "subcategory":"Doctor",
            "type":"Services"
        }
    ],
    "sg:phone":"+1 253 761 0380",
    "sg:postcode":"98407",
    "sg:province":"WA",
    "sg:tags":[
        "medical"
    ],
    "wof:name":"Dr Neil Mullen",
    "wof:placetype":"venue"
},
  "geometry": {"coordinates":[-122.478498,47.277547],"type":"Point"}
}