{
  "type": "Feature",
  "properties": {
    "addr:full":"2932 Colby Ave Everett WA 98201",
    "addr:housenumber":"2932",
    "addr:postcode":"98201",
    "addr:street":"Colby Ave",
    "iso:country":"US",
    "sg:address":"2932 Colby Ave",
    "sg:city":"Everett",
    "sg:classifiers":[
        {
            "category":"Food & Beverages",
            "subcategory":"Groceries & Convenience Stores",
            "type":"Retail Goods"
        }
    ],
    "sg:phone":"+1 425 783 0383",
    "sg:postcode":"98201",
    "sg:province":"WA",
    "wof:name":"Colby Halal Market",
    "wof:placetype":"venue"
},
  "geometry": {"coordinates":[-122.20868900000001,47.978321],"type":"Point"}
}