{
  "type": "Feature",
  "properties": {
    "addr:full":"14601 Ambaum Blvd SW Burien WA 98166",
    "addr:housenumber":"14601",
    "addr:postcode":"98166",
    "addr:street":"Ambaum Blvd Sw",
    "iso:country":"US",
    "sg:address":"14601 Ambaum Blvd SW",
    "sg:city":"Burien",
    "sg:classifiers":[
        {
            "category":"Retail",
            "subcategory":"Auto Repair",
            "type":"Services"
        }
    ],
    "sg:phone":"+1 206 243 9473",
    "sg:postcode":"98166",
    "sg:province":"WA",
    "sg:website":"http://www.yireautocare.com",
    "wof:name":"Yire Automotive Care",
    "wof:placetype":"venue"
},
  "geometry": {"coordinates":[-122.347183,47.472198],"type":"Point"}
}