{
  "type": "Feature",
  "properties": {
    "addr:full":"1617 102nd Pl NE Bellevue WA 98004",
    "addr:housenumber":"1617",
    "addr:postcode":"98004",
    "addr:street":"102Nd Pl Ne",
    "iso:country":"US",
    "sg:address":"1617 102nd Pl NE",
    "sg:city":"Bellevue",
    "sg:classifiers":[
        {
            "category":"Shopping",
            "subcategory":"Clothing, Apparel, & Fashions",
            "type":"Retail Goods"
        }
    ],
    "sg:phone":"+1 425 455 3085",
    "sg:postcode":"98004",
    "sg:province":"WA",
    "wof:name":"NNette Fashion Design &",
    "wof:placetype":"venue"
},
  "geometry": {"coordinates":[-122.204173,47.62579],"type":"Point"}
}