{
  "type": "Feature",
  "properties": {
    "addr:full":"506 4th Ave E Olympia WA 98501",
    "addr:housenumber":"506",
    "addr:postcode":"98501",
    "addr:street":"4Th Ave E",
    "iso:country":"US",
    "sg:address":"506 4th Ave E",
    "sg:city":"Olympia",
    "sg:classifiers":[
        {
            "category":"Manufacturing",
            "subcategory":"Building Materials",
            "type":"Manufacturing & Wholesale Goods"
        }
    ],
    "sg:phone":"+1 360 339 4958",
    "sg:postcode":"98501",
    "sg:province":"WA",
    "sg:tags":[
        "fireplace"
    ],
    "sg:website":"http://www.olympiafireplace.com",
    "wof:name":"Olympia Fireplace & Spa",
    "wof:placetype":"venue"
},
  "geometry": {"coordinates":[-122.89665100000001,47.045266],"type":"Point"}
}