{
  "type": "Feature",
  "properties": {
    "addr:full":"23969 NE State Rte 3 Belfair WA 98528",
    "addr:housenumber":"23969",
    "addr:postcode":"98528",
    "addr:street":"Ne State Rte 3",
    "iso:country":"US",
    "sg:address":"23969 NE State Rte 3",
    "sg:city":"Belfair",
    "sg:classifiers":[
        {
            "category":"Food & Beverages",
            "subcategory":"Specialty",
            "type":"Retail Goods"
        }
    ],
    "sg:phone":"+1 360 277 9434",
    "sg:postcode":"98528",
    "sg:province":"WA",
    "wof:name":"Dragouns Lear",
    "wof:placetype":"venue"
},
  "geometry": {"coordinates":[-122.823145,47.452966],"type":"Point"}
}