{
  "type": "Feature",
  "properties": {
    "addr:full":"3449 Lasco Ln NE Moses Lake WA 98837",
    "addr:housenumber":"3449",
    "addr:postcode":"98837",
    "addr:street":"Lasco Ln Ne",
    "iso:country":"US",
    "sg:address":"3449 Lasco Ln NE",
    "sg:city":"Moses Lake",
    "sg:classifiers":[
        {
            "category":"Building & Trades",
            "subcategory":"Construction",
            "type":"Services"
        }
    ],
    "sg:phone":"+1 509 764 4790",
    "sg:postcode":"98837",
    "sg:province":"WA",
    "sg:tags":[
        "commercial"
    ],
    "wof:name":"Legacy Construction Group Inc",
    "wof:placetype":"venue"
},
  "geometry": {"coordinates":[-119.256511,47.134898],"type":"Point"}
}