{
  "type": "Feature",
  "properties": {
    "addr:full":"1521 S 92nd Pl Seattle WA 98108",
    "addr:housenumber":"1521",
    "addr:postcode":"98108",
    "addr:street":"S 92Nd Pl",
    "iso:country":"US",
    "sg:address":"1521 S 92nd Pl",
    "sg:city":"Seattle",
    "sg:classifiers":[
        {
            "category":"Building & Trades",
            "subcategory":"Construction",
            "type":"Services"
        }
    ],
    "sg:phone":"+1 206 442 9019",
    "sg:postcode":"98108",
    "sg:province":"WA",
    "sg:tags":[
        "covering",
        "floor",
        "contractor"
    ],
    "wof:name":"McCanns Floor Covering Inc",
    "wof:placetype":"venue"
},
  "geometry": {"coordinates":[-122.311178,47.520956],"type":"Point"}
}