{
  "type": "Feature",
  "properties": {
    "addr:full":"4805 22nd Ave SE Lacey WA 98503",
    "addr:housenumber":"4805",
    "addr:postcode":"98503",
    "addr:street":"22Nd Ave Se",
    "iso:country":"US",
    "sg:address":"4805 22nd Ave SE",
    "sg:city":"Lacey",
    "sg:classifiers":[
        {
            "category":"Social Services",
            "subcategory":"Adult Care",
            "type":"Services"
        }
    ],
    "sg:phone":"+1 360 923 9326",
    "sg:postcode":"98503",
    "sg:province":"WA",
    "sg:tags":[
        "residential"
    ],
    "wof:name":"Milagros F Byers",
    "wof:placetype":"venue"
},
  "geometry": {"coordinates":[-122.819844,47.027324],"type":"Point"}
}