{
  "type": "Feature",
  "properties": {
    "addr:full":"1716 SW Trenton St Seattle WA 98106",
    "addr:housenumber":"1716",
    "addr:postcode":"98106",
    "addr:street":"Sw Trenton St",
    "iso:country":"US",
    "sg:address":"1716 SW Trenton St",
    "sg:city":"Seattle",
    "sg:classifiers":[
        {
            "category":"Professional",
            "type":"Services"
        }
    ],
    "sg:phone":"+1 206 762 7385",
    "sg:postcode":"98106",
    "sg:province":"WA",
    "wof:name":"Hurst Services",
    "wof:placetype":"venue"
},
  "geometry": {"coordinates":[-122.35763,47.524773],"type":"Point"}
}