{
  "type": "Feature",
  "properties": {
    "addr:full":"13618 54th Dr NE Marysville WA 98271",
    "addr:housenumber":"13618",
    "addr:postcode":"98271",
    "addr:street":"54Th Dr Ne",
    "iso:country":"US",
    "sg:address":"13618 54th Dr NE",
    "sg:city":"Marysville",
    "sg:classifiers":[
        {
            "category":"Manufacturing",
            "subcategory":"Tools & Machinery",
            "type":"Manufacturing & Wholesale Goods"
        }
    ],
    "sg:phone":"+1 360 659 4210",
    "sg:postcode":"98271",
    "sg:province":"WA",
    "sg:tags":[
        "machine",
        "vending",
        "mfg"
    ],
    "wof:name":"Kenneth R Laffin",
    "wof:placetype":"venue"
},
  "geometry": {"coordinates":[-122.158389,48.117493],"type":"Point"}
}