{
  "type": "Feature",
  "properties": {
    "addr:full":"2401 Utah Ave S Seattle WA 98134",
    "addr:housenumber":"2401",
    "addr:postcode":"98134",
    "addr:street":"Utah Ave S",
    "iso:country":"US",
    "sg:address":"2401 Utah Ave S",
    "sg:city":"Seattle",
    "sg:classifiers":[
        {
            "category":"Coffee & Tea",
            "type":"Food & Drink"
        }
    ],
    "sg:phone":"+1 206 447 1575",
    "sg:postcode":"98134",
    "sg:province":"WA",
    "sg:website":"www.starbucks.com",
    "wof:name":"Starbuck's",
    "wof:placetype":"venue"
},
  "geometry": {"coordinates":[-122.335157,47.581917],"type":"Point"}
}