{
  "type": "Feature",
  "properties": {
    "addr:full":"5706 NW el Rey Dr Camas WA 98607",
    "addr:housenumber":"5706",
    "addr:postcode":"98607",
    "addr:street":"Nw El Rey Dr",
    "iso:country":"US",
    "sg:address":"5706 NW el Rey Dr",
    "sg:city":"Camas",
    "sg:classifiers":[
        {
            "category":"Wholesale",
            "subcategory":"Furniture",
            "type":"Manufacturing & Wholesale Goods"
        }
    ],
    "sg:phone":"+1 360 834 5387",
    "sg:postcode":"98607",
    "sg:province":"WA",
    "sg:tags":[
        "interior",
        "consulting",
        "design"
    ],
    "wof:name":"Vivid Design",
    "wof:placetype":"venue"
},
  "geometry": {"coordinates":[-122.440369,45.624611],"type":"Point"}
}