{
  "type": "Feature",
  "properties": {
    "addr:full":"8701 NE 54th St Vancouver WA 98662",
    "addr:housenumber":"8701",
    "addr:postcode":"98662",
    "addr:street":"Ne 54Th St",
    "iso:country":"US",
    "sg:address":"8701 NE 54th St",
    "sg:city":"Vancouver",
    "sg:classifiers":[
        {
            "category":"Education",
            "subcategory":"Dance Studio",
            "type":"Public Place"
        },
        {
            "category":"Education",
            "subcategory":"Special Training",
            "type":"Public Place"
        }
    ],
    "sg:phone":"+1 360 699 7150",
    "sg:postcode":"98662",
    "sg:province":"WA",
    "sg:tags":[
        "instruction",
        "dancing"
    ],
    "wof:name":"Groove Nation Hip Hop Dance AC",
    "wof:placetype":"venue"
},
  "geometry": {"coordinates":[-122.58263599999999,45.661722],"type":"Point"}
}