{
  "type": "Feature",
  "properties": {
    "addr:full":"2033 6th Ave Seattle WA 98121",
    "addr:housenumber":"2033",
    "addr:postcode":"98121",
    "addr:street":"6Th Ave",
    "iso:country":"US",
    "sg:address":"2033 6th Ave",
    "sg:city":"Seattle",
    "sg:classifiers":[
        {
            "category":"Health Services",
            "subcategory":"Doctor",
            "type":"Services"
        },
        {
            "category":"Health Services",
            "subcategory":"Clinic",
            "type":"Services"
        },
        {
            "category":"Health Services",
            "subcategory":"Medical Lab",
            "type":"Services"
        }
    ],
    "sg:phone":"+1 206 724 0029",
    "sg:postcode":"98121",
    "sg:province":"WA",
    "sg:tags":[
        "medicine",
        "physician",
        "practice",
        "surgeons",
        "family"
    ],
    "wof:name":"Royal Media Group",
    "wof:placetype":"venue"
},
  "geometry": {"coordinates":[-122.338734,47.614639],"type":"Point"}
}