{
  "type": "Feature",
  "properties": {
    "addr:full":"1322 Harrison Ave Centralia WA 98531",
    "addr:housenumber":"1322",
    "addr:postcode":"98531",
    "addr:street":"Harrison Ave",
    "iso:country":"US",
    "sg:address":"1322 Harrison Ave",
    "sg:city":"Centralia",
    "sg:classifiers":[
        {
            "category":"Real Estate",
            "subcategory":"Real Estate Operator",
            "type":"Services"
        }
    ],
    "sg:phone":"+1 360 736 5037",
    "sg:postcode":"98531",
    "sg:province":"WA",
    "sg:tags":[
        "building",
        "apartment"
    ],
    "wof:name":"Candlewood Apts",
    "wof:placetype":"venue"
},
  "geometry": {"coordinates":[-122.985287,46.731289],"type":"Point"}
}