{
  "type": "Feature",
  "properties": {
    "addr:full":"3567 NW Randall Way Silverdale WA 98383",
    "addr:housenumber":"3567",
    "addr:postcode":"98383",
    "addr:street":"Nw Randall Way",
    "iso:country":"US",
    "sg:address":"3567 NW Randall Way",
    "sg:city":"Silverdale",
    "sg:classifiers":[
        {
            "category":"Shopping",
            "subcategory":"Hobbies, Toys, & Games",
            "type":"Retail Goods"
        }
    ],
    "sg:phone":"+1 360 698 1882",
    "sg:postcode":"98383",
    "sg:province":"WA",
    "sg:tags":[
        "toy",
        "store",
        "supply"
    ],
    "sg:website":"http://www.toysrus.com",
    "wof:name":"Toys \"R\" Us",
    "wof:placetype":"venue"
},
  "geometry": {"coordinates":[-122.69553999999999,47.653901],"type":"Point"}
}