{
  "type": "Feature",
  "properties": {
    "iso:country":"US",
    "sg:address":"3033 W Alpine Dr",
    "sg:city":"Bellingham",
    "sg:classifiers":[
        {
            "category":"Food & Beverages",
            "subcategory":"Groceries & Convenience Stores",
            "type":"Retail Goods"
        }
    ],
    "sg:phone":"+1 360 756 1695",
    "sg:postcode":"98226",
    "sg:province":"WA",
    "sg:tags":[
        "product"
    ],
    "wof:name":"Frontier Custom Foods Inc",
    "wof:placetype":"venue"
},
  "geometry": {"coordinates":[-122.430814,48.771281],"type":"Point"}
}