{
  "type": "Feature",
  "properties": {
    "addr:full":"1525 Broadway St Longview WA 98632",
    "addr:housenumber":"1525",
    "addr:postcode":"98632",
    "addr:street":"Broadway St",
    "iso:country":"US",
    "sg:address":"1525 Broadway St",
    "sg:city":"Longview",
    "sg:classifiers":[
        {
            "category":"Utilities",
            "subcategory":"Refuse",
            "type":"Services"
        },
        {
            "category":"Utilities",
            "subcategory":"Recycling",
            "type":"Services"
        },
        {
            "category":"Government",
            "subcategory":"Office",
            "type":"Public Place"
        }
    ],
    "sg:phone":"+1 360 442 5222",
    "sg:postcode":"98632",
    "sg:province":"WA",
    "sg:tags":[
        "garbage",
        "collection",
        "removal",
        "rubbish",
        "village",
        "township",
        "government-city"
    ],
    "wof:name":"City of Longview Garbage/Recycling/Collection",
    "wof:placetype":"venue"
},
  "geometry": {"coordinates":[-122.936818,46.138956],"type":"Point"}
}