{
  "type": "Feature",
  "properties": {
    "addr:full":"15333 NE 90th St Redmond WA 98052",
    "addr:housenumber":"15333",
    "addr:postcode":"98052",
    "addr:street":"Ne 90Th St",
    "iso:country":"US",
    "sg:address":"15333 NE 90th St",
    "sg:city":"Redmond",
    "sg:classifiers":[
        {
            "category":"Manufacturing",
            "subcategory":"Tools & Machinery",
            "type":"Manufacturing & Wholesale Goods"
        }
    ],
    "sg:phone":"+1 425 885 4404",
    "sg:postcode":"98052",
    "sg:province":"WA",
    "sg:tags":[
        "process",
        "control",
        "mfg",
        "environmental",
        "instrument"
    ],
    "wof:name":"Sage Electronics Incorporated",
    "wof:placetype":"venue"
},
  "geometry": {"coordinates":[-122.136347,47.682145],"type":"Point"}
}