{
  "type": "Feature",
  "properties": {
    "addr:full":"21010 NE 133rd St Woodinville WA 98077",
    "addr:housenumber":"21010",
    "addr:postcode":"98077",
    "addr:street":"Ne 133Rd St",
    "iso:country":"US",
    "sg:address":"21010 NE 133rd St",
    "sg:city":"Woodinville",
    "sg:classifiers":[
        {
            "category":"Building & Trades",
            "subcategory":"Electrical",
            "type":"Services"
        }
    ],
    "sg:phone":"+1 425 885 2235",
    "sg:postcode":"98077",
    "sg:province":"WA",
    "sg:tags":[
        "electrical",
        "contractor"
    ],
    "wof:name":"Frontier Electric Inc",
    "wof:placetype":"venue"
},
  "geometry": {"coordinates":[-122.054092,47.718735],"type":"Point"}
}