{
  "type": "Feature",
  "properties": {
    "addr:full":"1218 Third Avenue Suite 300 Seattle WA 98101",
    "addr:housenumber":"1218",
    "addr:postcode":"98101",
    "addr:street":"Third Avenue Suite 300",
    "iso:country":"US",
    "sg:address":"1218 Third Avenue Suite 300",
    "sg:city":"Seattle",
    "sg:classifiers":[
        {
            "category":"Professional",
            "subcategory":"Computer Services",
            "type":"Services"
        }
    ],
    "sg:postcode":"98101",
    "sg:province":"WA",
    "sg:tags":[
        "lawyers",
        "reviews",
        "legal"
    ],
    "sg:website":"http://avvo.com",
    "wof:name":"Avvo",
    "wof:placetype":"venue"
},
  "geometry": {"coordinates":[-122.513099,47.597581],"type":"Point"}
}