{
  "type": "Feature",
  "properties": {
    "addr:full":"11516 SE Mill Plain Blvd. Vancouver WA 98684",
    "addr:postcode":"11516;98684",
    "addr:street":"Se Mill Plain Blvd.",
    "iso:country":"US",
    "sg:address":"11516 SE Mill Plain Blvd.",
    "sg:city":"Vancouver",
    "sg:classifiers":[
        {
            "category":"Banks & Credit Unions",
            "subcategory":"Financial Services",
            "type":"Services"
        }
    ],
    "sg:phone":"+1 360 567 0183",
    "sg:postcode":"98684",
    "sg:province":"WA",
    "sg:tags":[
        "broker",
        "mortgage"
    ],
    "sg:website":"www.cfmortgage.net",
    "wof:name":"Columbia First Mortgage",
    "wof:placetype":"venue"
},
  "geometry": {"coordinates":[-122.55368,45.621592],"type":"Point"}
}