{
  "type": "Feature",
  "properties": {
    "addr:full":"22237 76th Ave S Kent WA 98032",
    "addr:housenumber":"22237",
    "addr:postcode":"98032",
    "addr:street":"76Th Ave S",
    "iso:country":"US",
    "sg:address":"22237 76th Ave S",
    "sg:city":"Kent",
    "sg:classifiers":[
        {
            "category":"Manufacturing",
            "subcategory":"Retail Goods",
            "type":"Manufacturing & Wholesale Goods"
        },
        {
            "category":"Wholesale",
            "subcategory":"Chemicals & Plastics",
            "type":"Manufacturing & Wholesale Goods"
        }
    ],
    "sg:phone":"+1 253 872 8067",
    "sg:postcode":"98032",
    "sg:province":"WA",
    "sg:tags":[
        "resin",
        "manufacturer"
    ],
    "wof:name":"Interplastic Corporation",
    "wof:placetype":"venue"
},
  "geometry": {"coordinates":[-122.23878999999999,47.40202],"type":"Point"}
}