{
  "type": "Feature",
  "properties": {
    "iso:country":"US",
    "sg:address":"4823 186th Pl SW",
    "sg:city":"Lynnwood",
    "sg:classifiers":[
        {
            "category":"Professional",
            "subcategory":"Management & Consulting",
            "type":"Services"
        }
    ],
    "sg:phone":"+1 425 640 7281",
    "sg:postcode":"98037",
    "sg:province":"WA",
    "wof:name":"NW Brown Inc",
    "wof:placetype":"venue"
},
  "geometry": {"coordinates":[-122.298304,47.829809],"type":"Point"}
}