{
  "type": "Feature",
  "properties": {
    "addr:full":"1607 E Isaacs Ave Walla Walla WA 99362",
    "addr:housenumber":"1607",
    "addr:postcode":"99362",
    "addr:street":"E Isaacs Ave",
    "iso:country":"US",
    "sg:address":"1607 E Isaacs Ave",
    "sg:city":"Walla Walla",
    "sg:classifiers":[
        {
            "category":"Food & Beverages",
            "subcategory":"Specialty",
            "type":"Retail Goods"
        }
    ],
    "sg:phone":"+1 509 525 5710",
    "sg:postcode":"99362",
    "sg:province":"WA",
    "sg:tags":[
        "bars",
        "espresso"
    ],
    "wof:name":"Coffee Cravings",
    "wof:placetype":"venue"
},
  "geometry": {"coordinates":[-118.312545,46.075055],"type":"Point"}
}