{
  "type": "Feature",
  "properties": {
    "addr:full":"414 SW 4th St College Place WA 99324",
    "addr:housenumber":"414",
    "addr:postcode":"99324",
    "addr:street":"Sw 4Th St",
    "iso:country":"US",
    "sg:address":"414 SW 4th St",
    "sg:city":"College Place",
    "sg:classifiers":[
        {
            "category":"Banks & Credit Unions",
            "subcategory":"Financial Services",
            "type":"Services"
        }
    ],
    "sg:phone":"+1 509 522 4939",
    "sg:postcode":"99324",
    "sg:province":"WA",
    "sg:tags":[
        "management",
        "open",
        "investment"
    ],
    "wof:name":"Ben Wiedemann",
    "wof:placetype":"venue"
},
  "geometry": {"coordinates":[-118.398882,46.045769],"type":"Point"}
}