{
  "type": "Feature",
  "properties": {
    "addr:full":"6211 NE 182nd St Kenmore WA 98028",
    "addr:housenumber":"6211",
    "addr:postcode":"98028",
    "addr:street":"Ne 182Nd St",
    "iso:country":"US",
    "sg:address":"6211 NE 182nd St",
    "sg:city":"Kenmore",
    "sg:classifiers":[
        {
            "category":"Place Of Worship",
            "subcategory":"Church",
            "type":"Public Place"
        },
        {
            "category":"Place Of Worship",
            "type":"Public Place"
        }
    ],
    "sg:phone":"+1 425 486 3777",
    "sg:postcode":"98028",
    "sg:province":"WA",
    "sg:tags":[
        "churches-episcopal-anglican",
        "churches-episcopal"
    ],
    "wof:name":"Church Of The Redeemer",
    "wof:placetype":"venue"
},
  "geometry": {"coordinates":[-122.260026,47.760194],"type":"Point"}
}