{
  "type": "Feature",
  "properties": {
    "addr:full":"17011 174th Ave NE Woodinville WA 98072",
    "addr:housenumber":"17011",
    "addr:postcode":"98072",
    "addr:street":"174Th Ave Ne",
    "iso:country":"US",
    "sg:address":"17011 174th Ave NE",
    "sg:city":"Woodinville",
    "sg:classifiers":[
        {
            "category":"Building & Trades",
            "subcategory":"Construction",
            "type":"Services"
        }
    ],
    "sg:phone":"+1 425 481 7271",
    "sg:postcode":"98072",
    "sg:province":"WA",
    "sg:tags":[
        "fork",
        "trucks-industrial",
        "lift"
    ],
    "wof:name":"Westco Lifts",
    "wof:placetype":"venue"
},
  "geometry": {"coordinates":[-122.107325,47.749837],"type":"Point"}
}