{
  "type": "Feature",
  "properties": {
    "addr:full":"3003 Tieton Dr Yakima WA 98902",
    "addr:housenumber":"3003",
    "addr:postcode":"98902",
    "addr:street":"Tieton Dr",
    "iso:country":"US",
    "sg:address":"3003 Tieton Dr",
    "sg:city":"Yakima",
    "sg:classifiers":[
        {
            "category":"Shopping",
            "subcategory":"Beauty & Cosmetics",
            "type":"Retail Goods"
        }
    ],
    "sg:phone":"+1 509 225 4555",
    "sg:postcode":"98902",
    "sg:province":"WA",
    "sg:tags":[
        "merchandise"
    ],
    "wof:name":"Cascade Cosmetic & Recnstrctve",
    "wof:placetype":"venue"
},
  "geometry": {"coordinates":[-120.550005,46.592817],"type":"Point"}
}