{
  "type": "Feature",
  "properties": {
    "addr:full":"10300 28th Ave W Everett WA 98204",
    "addr:housenumber":"10300",
    "addr:postcode":"98204",
    "addr:street":"28Th Ave W",
    "iso:country":"US",
    "sg:address":"10300 28th Ave W",
    "sg:city":"Everett",
    "sg:classifiers":[
        {
            "category":"Professional",
            "subcategory":"Engineering",
            "type":"Services"
        },
        {
            "category":"Manufacturing",
            "subcategory":"Aerospace",
            "type":"Manufacturing & Wholesale Goods"
        }
    ],
    "sg:phone":"+1 425 355 4088",
    "sg:postcode":"98204",
    "sg:province":"WA",
    "sg:tags":[
        "avionics",
        "instrument",
        "supply",
        "equipment",
        "aircraft",
        "part",
        "maintenance"
    ],
    "sg:website":"http://www.crownaviation.com/index.htm",
    "wof:name":"Crown Aviation, LLC",
    "wof:placetype":"venue"
},
  "geometry": {"coordinates":[-122.270105,47.905578],"type":"Point"}
}