{
  "type": "Feature",
  "properties": {
    "addr:full":"4828 SW Hunter Rd Port Orchard WA 98367",
    "addr:housenumber":"4828",
    "addr:postcode":"98367",
    "addr:street":"Sw Hunter Rd",
    "iso:country":"US",
    "sg:address":"4828 SW Hunter Rd",
    "sg:city":"Port Orchard",
    "sg:classifiers":[
        {
            "category":"Retail",
            "subcategory":"Repair Shop",
            "type":"Services"
        }
    ],
    "sg:phone":"+1 360 876 2049",
    "sg:postcode":"98367",
    "sg:province":"WA",
    "wof:name":"Trek Enterprises",
    "wof:placetype":"venue"
},
  "geometry": {"coordinates":[-122.716874,47.417089],"type":"Point"}
}