{
  "type": "Feature",
  "properties": {
    "addr:full":"6412 24th Avenue NW Seattle WA 98107",
    "addr:housenumber":"6412",
    "addr:postcode":"98107",
    "addr:street":"24Th Avenue Nw",
    "iso:country":"US",
    "sg:address":"6412 24th Avenue NW",
    "sg:city":"Seattle",
    "sg:classifiers":[
        {
            "category":"Personal",
            "subcategory":"Barber",
            "type":"Services"
        }
    ],
    "sg:phone":"+1 206 782 2173",
    "sg:postcode":"98107",
    "sg:province":"WA",
    "wof:name":"2 1-2 Happy Barbers",
    "wof:placetype":"venue"
},
  "geometry": {"coordinates":[-122.387426,47.675877],"type":"Point"}
}