{
  "type": "Feature",
  "properties": {
    "addr:full":"307 McRae Rd NW Arlington WA 98223",
    "addr:housenumber":"307",
    "addr:postcode":"98223",
    "addr:street":"Mcrae Rd Nw",
    "iso:country":"US",
    "sg:address":"307 McRae Rd NW",
    "sg:city":"Arlington",
    "sg:classifiers":[
        {
            "category":"Manufacturing",
            "subcategory":"Lumber",
            "type":"Manufacturing & Wholesale Goods"
        }
    ],
    "sg:phone":"+1 360 652 0771",
    "sg:postcode":"98223",
    "sg:province":"WA",
    "sg:tags":[
        "logging"
    ],
    "wof:name":"1776 Logging",
    "wof:placetype":"venue"
},
  "geometry": {"coordinates":[-122.23758100000001,48.143513],"type":"Point"}
}