{
  "type": "Feature",
  "properties": {
    "addr:full":"7423 North St SW Lakewood WA 98498",
    "addr:housenumber":"7423",
    "addr:postcode":"98498",
    "addr:street":"North St Sw",
    "iso:country":"US",
    "sg:address":"7423 North St SW",
    "sg:city":"Lakewood",
    "sg:classifiers":[
        {
            "category":"Building & Trades",
            "subcategory":"Locksmith",
            "type":"Services"
        }
    ],
    "sg:phone":"+1 253 414 9015",
    "sg:postcode":"98498",
    "sg:province":"WA",
    "sg:tags":[
        "key"
    ],
    "wof:name":"Locks 1 2 3 Locksmith",
    "wof:placetype":"venue"
},
  "geometry": {"coordinates":[-122.535297,47.141377],"type":"Point"}
}