{
  "type": "Feature",
  "properties": {
    "addr:full":"119 Pine St Ste 400 Seattle WA 98101",
    "addr:housenumber":"119",
    "addr:postcode":"98101",
    "addr:street":"Pine St Ste 400",
    "iso:country":"US",
    "sg:address":"119 Pine St Ste 400",
    "sg:city":"Seattle",
    "sg:classifiers":[
        {
            "category":"Real Estate",
            "subcategory":"Architect",
            "type":"Services"
        }
    ],
    "sg:phone":"+1 206 624 8154",
    "sg:postcode":"98101",
    "sg:province":"WA",
    "wof:name":"Hewitt Architects",
    "wof:placetype":"venue"
},
  "geometry": {"coordinates":[-122.341003,47.609901],"type":"Point"}
}