{
  "type": "Feature",
  "properties": {
    "addr:full":"10846 Myers Way S Seattle WA 98168",
    "addr:housenumber":"10846",
    "addr:postcode":"98168",
    "addr:street":"Myers Way S",
    "iso:country":"US",
    "sg:address":"10846 Myers Way S",
    "sg:city":"Seattle",
    "sg:classifiers":[
        {
            "category":"Manufacturing",
            "subcategory":"Tools & Machinery",
            "type":"Manufacturing & Wholesale Goods"
        }
    ],
    "sg:phone":"+1 206 243 3797",
    "sg:postcode":"98168",
    "sg:province":"WA",
    "sg:tags":[
        "die",
        "maker",
        "punch",
        "mfg"
    ],
    "wof:name":"M&M Grinding",
    "wof:placetype":"venue"
},
  "geometry": {"coordinates":[-122.333315,47.505742],"type":"Point"}
}