{
  "type": "Feature",
  "properties": {
    "addr:full":"17911 NE 10th St Bellevue WA 98008",
    "addr:housenumber":"17911",
    "addr:postcode":"98008",
    "addr:street":"Ne 10Th St",
    "iso:country":"US",
    "sg:address":"17911 NE 10th St",
    "sg:city":"Bellevue",
    "sg:classifiers":[
        {
            "category":"Wholesale",
            "subcategory":"Medical Equipment & Supplies",
            "type":"Manufacturing & Wholesale Goods"
        }
    ],
    "sg:phone":"+1 425 641 7142",
    "sg:postcode":"98008",
    "sg:province":"WA",
    "sg:tags":[
        "apparatus",
        "x-ray"
    ],
    "sg:website":"http://www.lwresearch.com",
    "wof:name":"L & W Research Inc",
    "wof:placetype":"venue"
},
  "geometry": {"coordinates":[-122.10097,47.618932],"type":"Point"}
}