{
  "type": "Feature",
  "properties": {
    "addr:full":"3323 157th Ave SE Snohomish WA 98290",
    "addr:housenumber":"3323",
    "addr:postcode":"98290",
    "addr:street":"157Th Ave Se",
    "iso:country":"US",
    "sg:address":"3323 157th Ave SE",
    "sg:city":"Snohomish",
    "sg:classifiers":[
        {
            "category":"Shopping",
            "subcategory":"Florist",
            "type":"Retail Goods"
        }
    ],
    "sg:phone":"+1 425 334 2690",
    "sg:postcode":"98290",
    "sg:province":"WA",
    "wof:name":"Country Blossoms Florist",
    "wof:placetype":"venue"
},
  "geometry": {"coordinates":[-122.018534,47.966309],"type":"Point"}
}