{
  "type": "Feature",
  "properties": {
    "addr:full":"3515 278th St E Spanaway WA 98387",
    "addr:housenumber":"3515",
    "addr:postcode":"98387",
    "addr:street":"278Th St E",
    "iso:country":"US",
    "sg:address":"3515 278th St E",
    "sg:city":"Spanaway",
    "sg:classifiers":[
        {
            "category":"Building & Trades",
            "subcategory":"Construction",
            "type":"Services"
        }
    ],
    "sg:phone":"+1 253 847 2624",
    "sg:postcode":"98387",
    "sg:province":"WA",
    "sg:tags":[
        "excavating",
        "contractor"
    ],
    "wof:name":"Butler Dozing",
    "wof:placetype":"venue"
},
  "geometry": {"coordinates":[-122.37972600000001,47.0037],"type":"Point"}
}