{
  "type": "Feature",
  "properties": {
    "addr:full":"51 Pine Ct Port Hadlock WA 98339",
    "addr:housenumber":"51",
    "addr:postcode":"98339",
    "addr:street":"Pine Ct;Hadlock",
    "iso:country":"US",
    "sg:address":"51 Pine Ct",
    "sg:city":"Port Hadlock",
    "sg:classifiers":[
        {
            "category":"Building & Trades",
            "subcategory":"Landscaping Services",
            "type":"Services"
        }
    ],
    "sg:phone":"+1 360 385 6663",
    "sg:postcode":"98339",
    "sg:province":"WA",
    "sg:tags":[
        "landscape",
        "contractor"
    ],
    "wof:name":"Quality Landscapes",
    "wof:placetype":"venue"
},
  "geometry": {"coordinates":[-122.775477,48.041382],"type":"Point"}
}