{
  "type": "Feature",
  "properties": {
    "addr:full":"815 Auburn Way S Auburn WA 98002",
    "addr:housenumber":"815",
    "addr:postcode":"98002",
    "addr:street":"Auburn Way S",
    "iso:country":"US",
    "sg:address":"815 Auburn Way S",
    "sg:city":"Auburn",
    "sg:classifiers":[
        {
            "category":"Restaurant",
            "type":"Food & Drink"
        }
    ],
    "sg:phone":"+1 253 333 2300",
    "sg:postcode":"98002",
    "sg:province":"WA",
    "sg:tags":[
        "barbecue"
    ],
    "wof:name":"Harleys Barbeque",
    "wof:placetype":"venue"
},
  "geometry": {"coordinates":[-122.22411700000001,47.300382],"type":"Point"}
}