{
  "type": "Feature",
  "properties": {
    "addr:full":"13749 Midvale Ave N Seattle WA 98133",
    "addr:housenumber":"13749",
    "addr:postcode":"98133",
    "addr:street":"Midvale Ave N",
    "iso:country":"US",
    "sg:address":"13749 Midvale Ave N",
    "sg:city":"Seattle",
    "sg:classifiers":[
        {
            "category":"Professional",
            "type":"Services"
        }
    ],
    "sg:phone":"+1 206 366 2926",
    "sg:postcode":"98133",
    "sg:province":"WA",
    "wof:name":"Gio Tovrena",
    "wof:placetype":"venue"
},
  "geometry": {"coordinates":[-122.34377499999999,47.729506],"type":"Point"}
}