{
  "type": "Feature",
  "properties": {
    "addr:full":"2133 Aberdeen Ave NE Renton WA 98056",
    "addr:housenumber":"2133",
    "addr:postcode":"98056",
    "addr:street":"Aberdeen Ave Ne",
    "iso:country":"US",
    "sg:address":"2133 Aberdeen Ave NE",
    "sg:city":"Renton",
    "sg:classifiers":[
        {
            "category":"Building & Trades",
            "subcategory":"Construction",
            "type":"Services"
        }
    ],
    "sg:phone":"+1 206 261 4076",
    "sg:postcode":"98056",
    "sg:province":"WA",
    "sg:tags":[
        "carpet",
        "laying",
        "contractor"
    ],
    "wof:name":"Bayside Carpet Installation",
    "wof:placetype":"venue"
},
  "geometry": {"coordinates":[-122.191121,47.511088],"type":"Point"}
}