{
  "type": "Feature",
  "properties": {
    "addr:full":"2012 NE 65th St Seattle WA 98115",
    "addr:housenumber":"2012",
    "addr:postcode":"98115",
    "addr:street":"Ne 65Th St",
    "iso:country":"US",
    "sg:address":"2012 NE 65th St",
    "sg:city":"Seattle",
    "sg:classifiers":[
        {
            "category":"Social Services",
            "type":"Services"
        }
    ],
    "sg:phone":"+1 206 329 6133",
    "sg:postcode":"98115",
    "sg:province":"WA",
    "wof:name":"Family Spport Cunseling Cnsltn",
    "wof:placetype":"venue"
},
  "geometry": {"coordinates":[-122.305627,47.675851],"type":"Point"}
}