{
  "type": "Feature",
  "properties": {
    "addr:full":"950 SE Regatta Dr Oak Harbor WA 98277",
    "addr:housenumber":"950",
    "addr:postcode":"98277",
    "addr:street":"Se Regatta Dr",
    "iso:country":"US",
    "sg:address":"950 SE Regatta Dr",
    "sg:city":"Oak Harbor",
    "sg:classifiers":[
        {
            "category":"Social Services",
            "subcategory":"Child Care",
            "type":"Services"
        }
    ],
    "sg:phone":"+1 360 679 2936",
    "sg:postcode":"98277",
    "sg:province":"WA",
    "sg:tags":[
        "day"
    ],
    "wof:name":"Skagit Valley Day Care Center",
    "wof:placetype":"venue"
},
  "geometry": {"coordinates":[-122.63575400000001,48.290936],"type":"Point"}
}