{
  "type": "Feature",
  "properties": {
    "addr:full":"2334 SW Spokane St Seattle WA 98106",
    "addr:housenumber":"2334",
    "addr:postcode":"98106",
    "addr:street":"Sw Spokane St",
    "iso:country":"US",
    "sg:address":"2334 SW Spokane St",
    "sg:city":"Seattle",
    "sg:classifiers":[
        {
            "category":"Manufacturing",
            "subcategory":"Tools & Machinery",
            "type":"Manufacturing & Wholesale Goods"
        }
    ],
    "sg:phone":"+1 206 937 2662",
    "sg:postcode":"98106",
    "sg:province":"WA",
    "sg:tags":[
        "machine",
        "shop"
    ],
    "wof:name":"J & D Machine & Gear Inc",
    "wof:placetype":"venue"
},
  "geometry": {"coordinates":[-122.36276700000001,47.571572],"type":"Point"}
}