{
  "type": "Feature",
  "properties": {
    "addr:full":"133 Maple Ave Snohomish WA 98290",
    "addr:housenumber":"133",
    "addr:postcode":"98290",
    "addr:street":"Maple Ave",
    "iso:country":"US",
    "sg:address":"133 Maple Ave",
    "sg:city":"Snohomish",
    "sg:classifiers":[
        {
            "category":"Education",
            "subcategory":"Dance Studio",
            "type":"Public Place"
        }
    ],
    "sg:phone":"+1 360 568 2448",
    "sg:postcode":"98290",
    "sg:province":"WA",
    "sg:tags":[
        "school"
    ],
    "wof:name":"Ballet Plus Foundation",
    "wof:placetype":"venue"
},
  "geometry": {"coordinates":[-122.090604,47.911155],"type":"Point"}
}