{
  "type": "Feature",
  "properties": {
    "addr:full":"2232 1st Ave Seattle WA 98121",
    "addr:housenumber":"2232",
    "addr:postcode":"98121",
    "addr:street":"1St Ave",
    "iso:country":"US",
    "sg:address":"2232 1st Ave",
    "sg:city":"Seattle",
    "sg:classifiers":[
        {
            "category":"Shopping",
            "subcategory":"Clothing, Apparel, & Fashions",
            "type":"Retail Goods"
        }
    ],
    "sg:phone":"+1 206 441 3442",
    "sg:postcode":"98121",
    "sg:province":"WA",
    "sg:tags":[
        "accessory"
    ],
    "sg:website":"www.karandannenbergclothier.blog...",
    "wof:name":"Karan Dannenberg Clothier",
    "wof:placetype":"venue"
},
  "geometry": {"coordinates":[-122.346001,47.6133],"type":"Point"}
}