{
  "type": "Feature",
  "properties": {
    "addr:full":"494 7th Ave S Okanogan WA 98840",
    "addr:housenumber":"494",
    "addr:postcode":"98840",
    "addr:street":"7Th Ave S Okanogan",
    "iso:country":"US",
    "sg:address":"494 7th Ave S",
    "sg:city":"Okanogan",
    "sg:classifiers":[
        {
            "category":"Personal",
            "subcategory":"Beauty Salon",
            "type":"Services"
        }
    ],
    "sg:phone":"+1 509 422 5455",
    "sg:postcode":"98840",
    "sg:province":"WA",
    "sg:tags":[
        "shop"
    ],
    "wof:name":"Three Nails Woodworking",
    "wof:placetype":"venue"
},
  "geometry": {"coordinates":[-119.587937,48.364028],"type":"Point"}
}