{
  "type": "Feature",
  "properties": {
    "iso:country":"US",
    "sg:address":"821 E Broadway Ave",
    "sg:city":"Moses Lake",
    "sg:classifiers":[
        {
            "category":"Retail",
            "subcategory":"Laundry & Dry Cleaning",
            "type":"Services"
        }
    ],
    "sg:phone":"+1 509 766 0202",
    "sg:postcode":"98837",
    "sg:province":"WA",
    "sg:tags":[
        "cleaners",
        "plant",
        "drycleaning"
    ],
    "wof:name":"Neighborhood Dry Cleaners",
    "wof:placetype":"venue"
},
  "geometry": {"coordinates":[-119.26662,47.137001],"type":"Point"}
}