{
  "type": "Feature",
  "properties": {
    "addr:full":"412 HUBBARD RD LYNNWOOD WA 98036",
    "addr:housenumber":"412",
    "addr:postcode":"98036",
    "addr:street":"Hubbard Rd",
    "iso:country":"US",
    "sg:address":"412 HUBBARD RD",
    "sg:city":"LYNNWOOD",
    "sg:classifiers":[
        {
            "category":"Building & Trades",
            "subcategory":"Landscaping Services",
            "type":"Services"
        },
        {
            "category":"Farming",
            "subcategory":"Farm",
            "type":"Manufacturing & Wholesale Goods"
        }
    ],
    "sg:phone":"+1 425 273 1642",
    "sg:postcode":"98036",
    "sg:province":"WA",
    "sg:tags":[
        "lawn",
        "hydroseeding",
        "landscape",
        "contractor"
    ],
    "sg:website":"http://www.nwhydroseeding.com",
    "wof:name":"Northwest Hydroseeding",
    "wof:placetype":"venue"
},
  "geometry": {"coordinates":[-122.238483,47.807073],"type":"Point"}
}