{
  "type": "Feature",
  "properties": {
    "addr:full":"14710 Woodinville-Redmond Rd NE Woodinville WA 98072",
    "addr:housenumber":"14710",
    "addr:postcode":"98072",
    "addr:street":"Woodinville-Redmond Rd Ne",
    "iso:country":"US",
    "sg:address":"14710 Woodinville-Redmond Rd NE",
    "sg:city":"Woodinville",
    "sg:classifiers":[
        {
            "category":"Winery",
            "type":"Food & Drink"
        }
    ],
    "sg:phone":"+1 425 481 5502",
    "sg:postcode":"98072",
    "sg:province":"WA",
    "sg:website":"www.januikwinery.com",
    "wof:name":"Januik Winery",
    "wof:placetype":"venue"
},
  "geometry": {"coordinates":[-122.153465,47.734472],"type":"Point"}
}