{
  "type": "Feature",
  "properties": {
    "addr:full":"32440 SE 54th St Fall City WA 98024",
    "addr:postcode":"32440;98024",
    "addr:street":"Se 54Th St",
    "iso:country":"US",
    "sg:address":"32440 SE 54th St",
    "sg:city":"Fall City",
    "sg:classifiers":[
        {
            "category":"Health Services",
            "subcategory":"Doctor",
            "type":"Services"
        }
    ],
    "sg:phone":"+1 425 222 3593",
    "sg:postcode":"98024",
    "sg:province":"WA",
    "sg:tags":[
        "dentist"
    ],
    "wof:name":"American Dental Support",
    "wof:placetype":"venue"
},
  "geometry": {"coordinates":[-121.91227600000001,47.55244],"type":"Point"}
}