{
  "type": "Feature",
  "properties": {
    "addr:full":"17005 E Sprague Ave Spokane Valley WA 99037",
    "addr:housenumber":"17005",
    "addr:postcode":"99037",
    "addr:street":"E Sprague Ave",
    "iso:country":"US",
    "sg:address":"17005 E Sprague Ave",
    "sg:city":"Spokane Valley",
    "sg:classifiers":[
        {
            "category":"Restaurant",
            "type":"Food & Drink"
        }
    ],
    "sg:phone":"+1 509 928 0513",
    "sg:postcode":"99037",
    "sg:province":"WA",
    "sg:tags":[
        "drinking",
        "eating"
    ],
    "wof:name":"King's Restaurant",
    "wof:placetype":"venue"
},
  "geometry": {"coordinates":[-117.175139,47.657007],"type":"Point"}
}