{
  "type": "Feature",
  "properties": {
    "addr:full":"13912 McAuley Rd Yakima WA 98908",
    "addr:housenumber":"13912",
    "addr:postcode":"98908",
    "addr:street":"Mcauley Rd",
    "iso:country":"US",
    "sg:address":"13912 McAuley Rd",
    "sg:city":"Yakima",
    "sg:classifiers":[
        {
            "category":"Shopping",
            "type":"Retail Goods"
        }
    ],
    "sg:phone":"+1 509 965 1127",
    "sg:postcode":"98908",
    "sg:province":"WA",
    "sg:tags":[
        "alarm"
    ],
    "wof:name":"Alarm Specialties Inc",
    "wof:placetype":"venue"
},
  "geometry": {"coordinates":[-120.69375599999999,46.585763],"type":"Point"}
}