{
  "type": "Feature",
  "properties": {
    "addr:full":"12108 SE 310th St Auburn WA 98092",
    "addr:housenumber":"12108",
    "addr:postcode":"98092",
    "addr:street":"Se 310Th St",
    "iso:country":"US",
    "sg:address":"12108 SE 310th St",
    "sg:city":"Auburn",
    "sg:classifiers":[
        {
            "category":"Real Estate",
            "subcategory":"Real Estate Agent",
            "type":"Services"
        }
    ],
    "sg:phone":"+1 253 833 2766",
    "sg:postcode":"98092",
    "sg:province":"WA",
    "wof:name":"American Realty Appraisal",
    "wof:placetype":"venue"
},
  "geometry": {"coordinates":[-122.17992099999999,47.324383],"type":"Point"}
}