{
  "type": "Feature",
  "properties": {
    "iso:country":"US",
    "sg:address":"516 W Main St",
    "sg:city":"Dayton",
    "sg:classifiers":[
        {
            "category":"Banks & Credit Unions",
            "subcategory":"Bank",
            "type":"Services"
        }
    ],
    "sg:phone":"+1 509 382 2563",
    "sg:postcode":"99328",
    "sg:province":"WA",
    "sg:tags":[
        "money",
        "transfer"
    ],
    "wof:name":"Western Union",
    "wof:placetype":"venue"
},
  "geometry": {"coordinates":[-117.989501,46.31569],"type":"Point"}
}