{
  "type": "Feature",
  "properties": {
    "addr:full":"16210 32nd Ave SE Bothell WA 98012",
    "addr:housenumber":"16210",
    "addr:postcode":"98012",
    "addr:street":"32Nd Ave Se",
    "iso:country":"US",
    "sg:address":"16210 32nd Ave SE",
    "sg:city":"Bothell",
    "sg:classifiers":[
        {
            "category":"Building & Trades",
            "subcategory":"Construction",
            "type":"Services"
        }
    ],
    "sg:phone":"+1 425 481 5756",
    "sg:postcode":"98012",
    "sg:province":"WA",
    "sg:tags":[
        "contractor"
    ],
    "wof:name":"Roofing Technical Services LLC",
    "wof:placetype":"venue"
},
  "geometry": {"coordinates":[-122.19049099999999,47.84997],"type":"Point"}
}