{
  "type": "Feature",
  "properties": {
    "addr:full":"401 E Pine St Seattle WA 98122",
    "addr:housenumber":"401",
    "addr:postcode":"98122",
    "addr:street":"E Pine St",
    "iso:country":"US",
    "sg:address":"401 E Pine St",
    "sg:city":"Seattle",
    "sg:classifiers":[
        {
            "category":"Home & Garden",
            "subcategory":"Furniture",
            "type":"Retail Goods"
        }
    ],
    "sg:phone":"+1 206 568 4782",
    "sg:postcode":"98122",
    "sg:province":"WA",
    "sg:tags":[
        "store"
    ],
    "sg:website":"www.area51seattle.com",
    "wof:name":"Area 51",
    "wof:placetype":"venue"
},
  "geometry": {"coordinates":[-122.326787,47.615241],"type":"Point"}
}