{
  "type": "Feature",
  "properties": {
    "addr:full":"1200 112th Ave NE Bellevue WA 98004",
    "addr:housenumber":"1200",
    "addr:postcode":"98004",
    "addr:street":"112Th Ave Ne",
    "iso:country":"US",
    "sg:address":"1200 112th Ave NE",
    "sg:city":"Bellevue",
    "sg:classifiers":[
        {
            "category":"Professional",
            "subcategory":"Management & Consulting",
            "type":"Services"
        }
    ],
    "sg:phone":"+1 425 450 7726",
    "sg:postcode":"98004",
    "sg:province":"WA",
    "sg:tags":[
        "environmental",
        "consultant"
    ],
    "wof:name":"Delta Environmental Cons",
    "wof:placetype":"venue"
},
  "geometry": {"coordinates":[-122.190973,47.623259],"type":"Point"}
}