{
  "type": "Feature",
  "properties": {
    "addr:full":"7336 24th Ave NW Seattle WA 98117",
    "addr:housenumber":"7336",
    "addr:postcode":"98117",
    "addr:street":"24Th Ave Nw",
    "iso:country":"US",
    "sg:address":"7336 24th Ave NW",
    "sg:city":"Seattle",
    "sg:classifiers":[
        {
            "category":"Personal",
            "type":"Services"
        }
    ],
    "sg:phone":"+1 206 784 1815",
    "sg:postcode":"98117",
    "sg:province":"WA",
    "wof:name":"Marshall Karri Lmp",
    "wof:placetype":"venue"
},
  "geometry": {"coordinates":[-122.387484,47.682841],"type":"Point"}
}