{
  "type": "Feature",
  "properties": {
    "addr:full":"1900 Rocky Creek Rd Colville WA 99114",
    "addr:housenumber":"1900",
    "addr:postcode":"99114",
    "addr:street":"Rocky Creek Rd",
    "iso:country":"US",
    "sg:address":"1900 Rocky Creek Rd",
    "sg:city":"Colville",
    "sg:phone":"+1 509 685 1548",
    "sg:postcode":"99114",
    "sg:province":"WA",
    "sg:tags":[
        "farm",
        "irish",
        "potato"
    ],
    "wof:name":"Olsen Farms",
    "wof:placetype":"venue"
},
  "geometry": {"coordinates":[-117.667434,48.724378],"type":"Point"}
}