{
  "type": "Feature",
  "properties": {
    "addr:full":"4364 Springdale Hunters Rd Springdale WA 99173",
    "addr:housenumber":"4364",
    "addr:postcode":"99173",
    "addr:street":"Springdale Hunters Rd",
    "iso:country":"US",
    "sg:address":"4364 Springdale Hunters Rd",
    "sg:city":"Springdale",
    "sg:classifiers":[
        {
            "category":"Retail",
            "subcategory":"Auto Repair",
            "type":"Services"
        }
    ],
    "sg:phone":"+1 509 258 9154",
    "sg:postcode":"99173",
    "sg:province":"WA",
    "sg:tags":[
        "body",
        "work"
    ],
    "wof:name":"Tna Fabrication",
    "wof:placetype":"venue"
},
  "geometry": {"coordinates":[-117.82231299999999,48.049114],"type":"Point"}
}