{
  "type": "Feature",
  "properties": {
    "addr:full":"2612 Pacific Hwy E Tacoma WA 98424",
    "addr:housenumber":"2612",
    "addr:postcode":"98424",
    "addr:street":"Pacific Hwy E",
    "iso:country":"US",
    "sg:address":"2612 Pacific Hwy E",
    "sg:city":"Tacoma",
    "sg:classifiers":[
        {
            "category":"Wholesale",
            "subcategory":"Electrical",
            "type":"Manufacturing & Wholesale Goods"
        }
    ],
    "sg:phone":"+1 253 922 7890",
    "sg:postcode":"98424",
    "sg:province":"WA",
    "sg:tags":[
        "communication",
        "radio",
        "system"
    ],
    "sg:website":"www.psicompany.com",
    "wof:name":"Puget Sound Instrument Inc",
    "wof:placetype":"venue"
},
  "geometry": {"coordinates":[-122.39532699999999,47.243123],"type":"Point"}
}