{
  "type": "Feature",
  "properties": {
    "addr:full":"27754 197th Ave SE Kent WA 98042",
    "addr:housenumber":"27754",
    "addr:postcode":"98042",
    "addr:street":"197Th Ave Se",
    "iso:country":"US",
    "sg:address":"27754 197th Ave SE",
    "sg:city":"Kent",
    "sg:classifiers":[
        {
            "category":"Shopping",
            "subcategory":"Clothing, Apparel, & Fashions",
            "type":"Retail Goods"
        }
    ],
    "sg:phone":"+1 253 630 0886",
    "sg:postcode":"98042",
    "sg:province":"WA",
    "sg:tags":[
        "riding",
        "equipment"
    ],
    "sg:website":"www.thehatlady.com",
    "wof:name":"Hat Lady",
    "wof:placetype":"venue"
},
  "geometry": {"coordinates":[-122.07937099999999,47.353132],"type":"Point"}
}