{
  "type": "Feature",
  "properties": {
    "addr:full":"916 S 200th St Des Moines WA 98198",
    "addr:housenumber":"916",
    "addr:postcode":"98198",
    "addr:street":"S 200Th St",
    "iso:country":"US",
    "sg:address":"916 S 200th St",
    "sg:city":"Des Moines",
    "sg:classifiers":[
        {
            "category":"Wholesale",
            "subcategory":"Machinery & Supplies",
            "type":"Manufacturing & Wholesale Goods"
        }
    ],
    "sg:phone":"+1 206 824 1030",
    "sg:postcode":"98198",
    "sg:province":"WA",
    "sg:tags":[
        "equipment",
        "plastic"
    ],
    "wof:name":"Del R Clement Inc",
    "wof:placetype":"venue"
},
  "geometry": {"coordinates":[-122.321636,47.423068],"type":"Point"}
}