{
  "type": "Feature",
  "properties": {
    "addr:full":"117 Cedar Ridge Dr Centralia WA 98531",
    "addr:housenumber":"117",
    "addr:postcode":"98531",
    "addr:street":"Cedar Ridge Dr",
    "iso:country":"US",
    "sg:address":"117 Cedar Ridge Dr",
    "sg:city":"Centralia",
    "sg:classifiers":[
        {
            "category":"Education",
            "subcategory":"Special Training",
            "type":"Public Place"
        }
    ],
    "sg:phone":"+1 360 736 7176",
    "sg:postcode":"98531",
    "sg:province":"WA",
    "wof:name":"Rainbow Mountain Gardens",
    "wof:placetype":"venue"
},
  "geometry": {"coordinates":[-122.995918,46.699916],"type":"Point"}
}