{
  "type": "Feature",
  "properties": {
    "addr:full":"13809 Bingham Ave E Tacoma WA 98446",
    "addr:housenumber":"13809",
    "addr:postcode":"98446",
    "addr:street":"Bingham Ave E",
    "iso:country":"US",
    "sg:address":"13809 Bingham Ave E",
    "sg:city":"Tacoma",
    "sg:classifiers":[
        {
            "category":"Building & Trades",
            "subcategory":"Construction",
            "type":"Services"
        }
    ],
    "sg:phone":"+1 253 535 8850",
    "sg:postcode":"98446",
    "sg:province":"WA",
    "sg:tags":[
        "general",
        "contractor"
    ],
    "wof:name":"Built Rite Construction",
    "wof:placetype":"venue"
},
  "geometry": {"coordinates":[-122.367991,47.129737],"type":"Point"}
}