{
  "type": "Feature",
  "properties": {
    "addr:full":"1800 136th Pl NE Bellevue WA 98005",
    "addr:housenumber":"1800",
    "addr:postcode":"98005",
    "addr:street":"136Th Pl Ne",
    "iso:country":"US",
    "sg:address":"1800 136th Pl NE",
    "sg:city":"Bellevue",
    "sg:classifiers":[
        {
            "category":"Food & Beverages",
            "subcategory":"Specialty",
            "type":"Retail Goods"
        }
    ],
    "sg:phone":"+1 425 562 1281",
    "sg:postcode":"98005",
    "sg:province":"WA",
    "sg:tags":[
        "vitamin"
    ],
    "sg:website":"www.esteemproducts.com",
    "wof:name":"Esteem Products LTD",
    "wof:placetype":"venue"
},
  "geometry": {"coordinates":[-122.157758,47.626155],"type":"Point"}
}