{
  "type": "Feature",
  "properties": {
    "iso:country":"US",
    "sg:address":"11231 1st Ave NW",
    "sg:city":"Seattle",
    "sg:classifiers":[
        {
            "category":"Banks & Credit Unions",
            "subcategory":"Bank",
            "type":"Services"
        }
    ],
    "sg:phone":"+1 206 364 9991",
    "sg:postcode":"98177",
    "sg:province":"WA",
    "sg:tags":[
        "personal",
        "institution"
    ],
    "wof:name":"Kroen Group USA Inc",
    "wof:placetype":"venue"
},
  "geometry": {"coordinates":[-122.35825,47.711051],"type":"Point"}
}