{
  "type": "Feature",
  "properties": {
    "addr:full":"3005 112th Ave NE Bellevue WA 98004",
    "addr:housenumber":"3005",
    "addr:postcode":"98004",
    "addr:street":"112Th Ave Ne",
    "iso:country":"US",
    "sg:address":"3005 112th Ave NE",
    "sg:city":"Bellevue",
    "sg:classifiers":[
        {
            "category":"Insurance",
            "subcategory":"Insurance Agent",
            "type":"Services"
        }
    ],
    "sg:phone":"+1 425 827 2282",
    "sg:postcode":"98004",
    "sg:province":"WA",
    "wof:name":"One Health Plan of Washington",
    "wof:placetype":"venue"
},
  "geometry": {"coordinates":[-122.193314,47.636705],"type":"Point"}
}