{
  "type": "Feature",
  "properties": {
    "addr:full":"2616 N Farr Ln Spokane Valley WA 99206",
    "addr:housenumber":"2616",
    "addr:postcode":"99206",
    "addr:street":"N Farr Ln",
    "iso:country":"US",
    "sg:address":"2616 N Farr Ln",
    "sg:city":"Spokane Valley",
    "sg:classifiers":[
        {
            "category":"Food & Beverages",
            "subcategory":"Bakery",
            "type":"Retail Goods"
        }
    ],
    "sg:phone":"+1 509 922 4729",
    "sg:postcode":"99206",
    "sg:province":"WA",
    "sg:tags":[
        "baker"
    ],
    "wof:name":"Orowheat Bakers Inc",
    "wof:placetype":"venue"
},
  "geometry": {"coordinates":[-117.27457,47.678772],"type":"Point"}
}