{
  "type": "Feature",
  "properties": {
    "addr:full":"1700 NE 199th St Ridgefield WA 98642",
    "addr:housenumber":"1700",
    "addr:postcode":"98642",
    "addr:street":"Ne 199Th St",
    "iso:country":"US",
    "sg:address":"1700 NE 199th St",
    "sg:city":"Ridgefield",
    "sg:classifiers":[
        {
            "category":"Building & Trades",
            "subcategory":"Plumbing",
            "type":"Services"
        }
    ],
    "sg:phone":"+1 360 887 1720",
    "sg:postcode":"98642",
    "sg:province":"WA",
    "sg:tags":[
        "contractor"
    ],
    "wof:name":"Gvc Plumbing",
    "wof:placetype":"venue"
},
  "geometry": {"coordinates":[-122.649939,45.765287],"type":"Point"}
}