{
  "type": "Feature",
  "properties": {
    "addr:full":"3860 US Hwy 97A Wenatchee WA 98801",
    "addr:housenumber":"3860",
    "addr:postcode":"98801",
    "addr:street":"Us Hwy 97A",
    "iso:country":"US",
    "sg:address":"3860 US Hwy 97A",
    "sg:city":"Wenatchee",
    "sg:classifiers":[
        {
            "category":"Government",
            "subcategory":"Office",
            "type":"Public Place"
        }
    ],
    "sg:phone":"+1 509 662 0452",
    "sg:postcode":"98801",
    "sg:province":"WA",
    "sg:tags":[
        "state"
    ],
    "wof:name":"Wildlife Dept",
    "wof:placetype":"venue"
},
  "geometry": {"coordinates":[-120.31739899999999,47.486089],"type":"Point"}
}