{
  "type": "Feature",
  "properties": {
    "addr:full":"1924 Trigg Rd Ferndale WA 98248",
    "addr:housenumber":"1924",
    "addr:postcode":"98248",
    "addr:street":"Trigg Rd",
    "iso:country":"US",
    "sg:address":"1924 Trigg Rd",
    "sg:city":"Ferndale",
    "sg:classifiers":[
        {
            "category":"Travel",
            "subcategory":"Campground",
            "type":"Entertainment"
        }
    ],
    "sg:phone":"+1 360 384 3147",
    "sg:postcode":"98248",
    "sg:province":"WA",
    "sg:tags":[
        "campsite",
        "trailer",
        "parks"
    ],
    "wof:name":"Duncans Mobile Home & R V Crt",
    "wof:placetype":"venue"
},
  "geometry": {"coordinates":[-122.58683600000001,48.877364],"type":"Point"}
}