{
  "type": "Feature",
  "properties": {
    "addr:full":"4708 NE 125th Cir Vancouver WA 98686",
    "addr:housenumber":"4708",
    "addr:postcode":"98686",
    "addr:street":"Ne 125Th Cir",
    "iso:country":"US",
    "sg:address":"4708 NE 125th Cir",
    "sg:city":"Vancouver",
    "sg:classifiers":[
        {
            "category":"Arts & Performance",
            "subcategory":"Theater",
            "type":"Entertainment"
        }
    ],
    "sg:phone":"+1 360 573 9421",
    "sg:postcode":"98686",
    "sg:province":"WA",
    "sg:tags":[
        "group"
    ],
    "wof:name":"5 Guys Named Moe",
    "wof:placetype":"venue"
},
  "geometry": {"coordinates":[-122.62139500000001,45.711879],"type":"Point"}
}