{
  "type": "Feature",
  "properties": {
    "addr:full":"12301 NE 10th Pl Ste 303 Bellevue WA 98005",
    "addr:housenumber":"12301",
    "addr:postcode":"98005",
    "addr:street":"Ne 10Th Pl Ste 303",
    "iso:country":"US",
    "sg:address":"12301 NE 10th Pl Ste 303",
    "sg:city":"Bellevue",
    "sg:classifiers":[
        {
            "category":"Real Estate",
            "subcategory":"Real Estate Services",
            "type":"Services"
        }
    ],
    "sg:phone":"+1 425 454 8900",
    "sg:postcode":"98005",
    "sg:province":"WA",
    "sg:tags":[
        "management",
        "property"
    ],
    "sg:website":"www.sherronassociates.com",
    "wof:name":"Sherron Associates",
    "wof:placetype":"venue"
},
  "geometry": {"coordinates":[-122.17675199999999,47.618631],"type":"Point"}
}