{
  "type": "Feature",
  "properties": {
    "addr:full":"2214 E 34th St Tacoma WA 98404",
    "addr:housenumber":"2214",
    "addr:postcode":"98404",
    "addr:street":"E 34Th St",
    "iso:country":"US",
    "sg:address":"2214 E 34th St",
    "sg:city":"Tacoma",
    "sg:classifiers":[
        {
            "category":"Freight",
            "type":"Transportation"
        }
    ],
    "sg:phone":"+1 253 627 0754",
    "sg:postcode":"98404",
    "sg:province":"WA",
    "sg:tags":[
        "operator",
        "local",
        "trucking"
    ],
    "wof:name":"Tallies Mail Delivery",
    "wof:placetype":"venue"
},
  "geometry": {"coordinates":[-122.397113,47.23395],"type":"Point"}
}