{
  "type": "Feature",
  "properties": {
    "iso:country":"US",
    "sg:address":"19222 SE 259th Pl",
    "sg:city":"Kent",
    "sg:classifiers":[
        {
            "category":"Shopping",
            "subcategory":"Clothing, Apparel, & Fashions",
            "type":"Retail Goods"
        }
    ],
    "sg:phone":"+1 253 630 2372",
    "sg:postcode":"98042",
    "sg:province":"WA",
    "wof:name":"Aunt Nancy Olde Fashion",
    "wof:placetype":"venue"
},
  "geometry": {"coordinates":[-122.083214,47.369213],"type":"Point"}
}