{
  "type": "Feature",
  "properties": {
    "addr:full":"3301 G St Vancouver WA 98663",
    "addr:housenumber":"3301",
    "addr:postcode":"98663",
    "addr:street":"G St",
    "iso:country":"US",
    "sg:address":"3301 G St",
    "sg:city":"Vancouver",
    "sg:classifiers":[
        {
            "category":"Wholesale",
            "subcategory":"Machinery & Supplies",
            "type":"Manufacturing & Wholesale Goods"
        }
    ],
    "sg:phone":"+1 360 906 0266",
    "sg:postcode":"98663",
    "sg:province":"WA",
    "sg:tags":[
        "equipment",
        "transportation",
        "legal"
    ],
    "wof:name":"Seatbeltcom",
    "wof:placetype":"venue"
},
  "geometry": {"coordinates":[-122.66512899999999,45.645806],"type":"Point"}
}