{
  "type": "Feature",
  "properties": {
    "addr:full":"3614 Summitview Ave Yakima WA 98902",
    "addr:housenumber":"3614",
    "addr:postcode":"98902",
    "addr:street":"Summitview Ave",
    "iso:country":"US",
    "sg:address":"3614 Summitview Ave",
    "sg:city":"Yakima",
    "sg:classifiers":[
        {
            "category":"Social Services",
            "subcategory":"Child Care",
            "type":"Services"
        }
    ],
    "sg:phone":"+1 509 965 6886",
    "sg:postcode":"98902",
    "sg:province":"WA",
    "sg:tags":[
        "day"
    ],
    "wof:name":"Dayna's Daycare",
    "wof:placetype":"venue"
},
  "geometry": {"coordinates":[-120.55844,46.599923],"type":"Point"}
}