{
  "type": "Feature",
  "properties": {
    "addr:full":"1314 S GRAND BLVD #2 SPOKANE WA 99202",
    "addr:housenumber":"1314",
    "addr:postcode":"99202",
    "addr:street":"S Grand Blvd # 2",
    "iso:country":"US",
    "sg:address":"1314 S GRAND BLVD #2",
    "sg:city":"SPOKANE",
    "sg:classifiers":[
        {
            "category":"Sports & Exercise",
            "subcategory":"Gym",
            "type":"Entertainment"
        },
        {
            "category":"Organizations",
            "subcategory":"Membership Organization",
            "type":"Services"
        }
    ],
    "sg:phone":"+1 509 999 6680",
    "sg:postcode":"99202",
    "sg:province":"WA",
    "sg:tags":[
        "club",
        "program",
        "physical",
        "private",
        "fitness"
    ],
    "sg:website":"http://www.SpokaneFitnessCoach.com",
    "wof:name":"Physzique - Spokane Fitness Solutions",
    "wof:placetype":"venue"
},
  "geometry": {"coordinates":[-117.40952,47.643666],"type":"Point"}
}