{
  "type": "Feature",
  "properties": {
    "addr:full":"3727 E Queen Ave Spokane WA 99217",
    "addr:housenumber":"3727",
    "addr:postcode":"99217",
    "addr:street":"E Queen Ave",
    "iso:country":"US",
    "sg:address":"3727 E Queen Ave",
    "sg:city":"Spokane",
    "sg:classifiers":[
        {
            "category":"Freight",
            "type":"Transportation"
        }
    ],
    "sg:phone":"+1 509 484 3548",
    "sg:postcode":"99217",
    "sg:province":"WA",
    "sg:tags":[
        "storage"
    ],
    "wof:name":"Guardian Self Storage",
    "wof:placetype":"venue"
},
  "geometry": {"coordinates":[-117.354479,47.704409],"type":"Point"}
}