{
  "type": "Feature",
  "properties": {
    "addr:full":"32858 US Hwy 97 Oroville WA 98844",
    "addr:postcode":"32858;98844",
    "addr:street":"Us Hwy 97",
    "iso:country":"US",
    "sg:address":"32858 US Hwy 97",
    "sg:city":"Oroville",
    "sg:classifiers":[
        {
            "category":"Freight",
            "type":"Transportation"
        }
    ],
    "sg:phone":"+1 509 476 3452",
    "sg:postcode":"98844",
    "sg:province":"WA",
    "sg:tags":[
        "hauling",
        "trucking"
    ],
    "wof:name":"Oroville Transit Trucking",
    "wof:placetype":"venue"
},
  "geometry": {"coordinates":[-119.42583399999999,48.894324],"type":"Point"}
}