{
  "type": "Feature",
  "properties": {
    "addr:full":"1404 Riverside Dr Ste B Mount Vernon WA 98273",
    "addr:housenumber":"1404",
    "addr:postcode":"98273",
    "addr:street":"Riverside Dr Ste B",
    "iso:country":"US",
    "sg:address":"1404 Riverside Dr Ste B",
    "sg:city":"Mount Vernon",
    "sg:classifiers":[
        {
            "category":"Organizations",
            "subcategory":"Religious Organization",
            "type":"Services"
        }
    ],
    "sg:phone":"+1 360 424 1014",
    "sg:postcode":"98273",
    "sg:province":"WA",
    "sg:website":"www.cefonline.com",
    "wof:name":"Child Evangelism Fellowship",
    "wof:placetype":"venue"
},
  "geometry": {"coordinates":[-122.33523599999999,48.433095],"type":"Point"}
}