{
  "type": "Feature",
  "properties": {
    "addr:full":"1631 E Agate Loop Rd Shelton WA 98584",
    "addr:housenumber":"1631",
    "addr:postcode":"98584",
    "addr:street":"E Agate Loop Rd",
    "iso:country":"US",
    "sg:address":"1631 E Agate Loop Rd",
    "sg:city":"Shelton",
    "sg:classifiers":[
        {
            "category":"Organizations",
            "subcategory":"Community Association",
            "type":"Services"
        }
    ],
    "sg:phone":"+1 360 426 9369",
    "sg:postcode":"98584",
    "sg:province":"WA",
    "wof:name":"Agate Grange",
    "wof:placetype":"venue"
},
  "geometry": {"coordinates":[-123.028634,47.216413],"type":"Point"}
}