{
  "type": "Feature",
  "properties": {
    "addr:full":"1624 39th Ave E Seattle WA 98112",
    "addr:housenumber":"1624",
    "addr:postcode":"98112",
    "addr:street":"39Th Ave E",
    "iso:country":"US",
    "sg:address":"1624 39th Ave E",
    "sg:city":"Seattle",
    "sg:classifiers":[
        {
            "category":"Professional",
            "subcategory":"Advertising",
            "type":"Services"
        }
    ],
    "sg:phone":"+1 206 323 5722",
    "sg:postcode":"98112",
    "sg:province":"WA",
    "wof:name":"Media Online",
    "wof:placetype":"venue"
},
  "geometry": {"coordinates":[-122.28258599999999,47.634434],"type":"Point"}
}