{
  "type": "Feature",
  "properties": {
    "addr:full":"2326 I St NE Auburn WA 98002",
    "addr:housenumber":"2326",
    "addr:postcode":"98002",
    "addr:street":"I St Ne",
    "iso:country":"US",
    "sg:address":"2326 I St NE",
    "sg:city":"Auburn",
    "sg:classifiers":[
        {
            "category":"Professional",
            "type":"Services"
        }
    ],
    "sg:phone":"+1 253 951 7571",
    "sg:postcode":"98002",
    "sg:province":"WA",
    "wof:name":"Coolstopshopcom",
    "wof:placetype":"venue"
},
  "geometry": {"coordinates":[-122.219365,47.327162],"type":"Point"}
}