{
  "type": "Feature",
  "properties": {
    "addr:full":"4616 25th Ave NE Ste 543 Seattle WA 98105",
    "addr:housenumber":"4616",
    "addr:postcode":"98105",
    "addr:street":"25Th Ave Ne Ste 543",
    "iso:country":"US",
    "sg:address":"4616 25th Ave NE Ste 543",
    "sg:city":"Seattle",
    "sg:classifiers":[
        {
            "category":"Building & Trades",
            "subcategory":"Construction",
            "type":"Services"
        }
    ],
    "sg:phone":"+1 206 714 8553",
    "sg:postcode":"98105",
    "sg:province":"WA",
    "sg:tags":[
        "contractor"
    ],
    "sg:website":"www.timwmasonry.com",
    "wof:name":"Tim Wheeler Masonry Construction",
    "wof:placetype":"venue"
},
  "geometry": {"coordinates":[-122.300872,47.662748],"type":"Point"}
}