{
  "type": "Feature",
  "properties": {
    "addr:full":"15627 SE 175th St Renton WA 98058",
    "addr:postcode":"15627;98058",
    "addr:street":"Se 175Th St",
    "iso:country":"US",
    "sg:address":"15627 SE 175th St",
    "sg:city":"Renton",
    "sg:classifiers":[
        {
            "category":"Real Estate",
            "subcategory":"Real Estate Agent",
            "type":"Services"
        }
    ],
    "sg:phone":"+1 206 356 2213",
    "sg:postcode":"98058",
    "sg:province":"WA",
    "wof:name":"Stephen Berry",
    "wof:placetype":"venue"
},
  "geometry": {"coordinates":[-122.13097500000001,47.445663],"type":"Point"}
}