{
  "type": "Feature",
  "properties": {
    "addr:full":"1936 1st Ave Seattle WA 98101",
    "addr:housenumber":"1936",
    "addr:postcode":"98101",
    "addr:street":"1St Ave",
    "iso:country":"US",
    "sg:address":"1936 1st Ave",
    "sg:city":"Seattle",
    "sg:classifiers":[
        {
            "category":"Shopping",
            "subcategory":"Clothing, Apparel, & Fashions",
            "type":"Retail Goods"
        }
    ],
    "sg:phone":"+1 206 956 0983",
    "sg:postcode":"98101",
    "sg:province":"WA",
    "sg:tags":[
        "clothing",
        "women's"
    ],
    "wof:name":"Uri",
    "wof:placetype":"venue"
},
  "geometry": {"coordinates":[-122.34200300000001,47.610802],"type":"Point"}
}