{
  "type": "Feature",
  "properties": {
    "addr:full":"13321 E 32nd Ave Spokane Valley WA 99216",
    "addr:housenumber":"13321",
    "addr:postcode":"99216",
    "addr:street":"E 32Nd Ave",
    "iso:country":"US",
    "sg:address":"13321 E 32nd Ave",
    "sg:city":"Spokane Valley",
    "sg:classifiers":[
        {
            "category":"Food & Beverages",
            "subcategory":"Specialty",
            "type":"Retail Goods"
        }
    ],
    "sg:phone":"+1 509 927 0050",
    "sg:postcode":"99216",
    "sg:province":"WA",
    "sg:tags":[
        "bars",
        "espresso"
    ],
    "wof:name":"Sipz",
    "wof:placetype":"venue"
},
  "geometry": {"coordinates":[-117.224951,47.627954],"type":"Point"}
}