{
  "type": "Feature",
  "properties": {
    "iso:country":"US",
    "sg:address":"3167 Hunter Ct",
    "sg:city":"Enumclaw",
    "sg:classifiers":[
        {
            "category":"Professional",
            "type":"Services"
        }
    ],
    "sg:phone":"+1 360 802 5130",
    "sg:postcode":"98022",
    "sg:province":"WA",
    "wof:name":"Alive",
    "wof:placetype":"venue"
},
  "geometry": {"coordinates":[-122.009745,47.211233],"type":"Point"}
}