{
  "type": "Feature",
  "properties": {
    "addr:full":"3770 Beaver Creek Ln Clinton WA 98236",
    "addr:housenumber":"3770",
    "addr:postcode":"98236",
    "addr:street":"Beaver Creek Ln",
    "iso:country":"US",
    "sg:address":"3770 Beaver Creek Ln",
    "sg:city":"Clinton",
    "sg:classifiers":[
        {
            "category":"Professional",
            "subcategory":"Management & Consulting",
            "type":"Services"
        }
    ],
    "sg:phone":"+1 360 341 4510",
    "sg:postcode":"98236",
    "sg:province":"WA",
    "sg:tags":[
        "business"
    ],
    "wof:name":"Telesource",
    "wof:placetype":"venue"
},
  "geometry": {"coordinates":[-122.402895,47.965615],"type":"Point"}
}