{
  "type": "Feature",
  "properties": {
    "addr:full":"1001 Summitview Ave Yakima WA 98902",
    "addr:housenumber":"1001",
    "addr:postcode":"98902",
    "addr:street":"Summitview Ave",
    "iso:country":"US",
    "sg:address":"1001 Summitview Ave",
    "sg:city":"Yakima",
    "sg:classifiers":[
        {
            "category":"Health Services",
            "subcategory":"Chiropractor",
            "type":"Services"
        }
    ],
    "sg:phone":"+1 509 453 0300",
    "sg:postcode":"98902",
    "sg:province":"WA",
    "sg:tags":[
        "chiropractic"
    ],
    "wof:name":"Degooyer Kerry H DC",
    "wof:placetype":"venue"
},
  "geometry": {"coordinates":[-120.523651,46.59985],"type":"Point"}
}