{
  "type": "Feature",
  "properties": {
    "addr:full":"6421 Lake Shore Dr Clinton WA 98236",
    "addr:housenumber":"6421",
    "addr:postcode":"98236",
    "addr:street":"Lake Shore Dr",
    "iso:country":"US",
    "sg:address":"6421 Lake Shore Dr",
    "sg:city":"Clinton",
    "sg:classifiers":[
        {
            "category":"Building & Trades",
            "subcategory":"Construction",
            "type":"Services"
        }
    ],
    "sg:phone":"+1 360 341 9464",
    "sg:postcode":"98236",
    "sg:province":"WA",
    "sg:tags":[
        "dry wall",
        "contractor"
    ],
    "wof:name":"Superior Drywall",
    "wof:placetype":"venue"
},
  "geometry": {"coordinates":[-122.37915700000001,47.975805],"type":"Point"}
}