{
  "type": "Feature",
  "properties": {
    "addr:full":"4050 Westside Hwy Castle Rock WA 98611",
    "addr:housenumber":"4050",
    "addr:postcode":"98611",
    "addr:street":"Westside Hwy",
    "iso:country":"US",
    "sg:address":"4050 Westside Hwy",
    "sg:city":"Castle Rock",
    "sg:classifiers":[
        {
            "category":"Building & Trades",
            "subcategory":"Landscaping Services",
            "type":"Services"
        }
    ],
    "sg:phone":"+1 360 274 7302",
    "sg:postcode":"98611",
    "sg:province":"WA",
    "sg:tags":[
        "landscape"
    ],
    "wof:name":"Flintstone",
    "wof:placetype":"venue"
},
  "geometry": {"coordinates":[-122.90431100000001,46.2542],"type":"Point"}
}