{
  "type": "Feature",
  "properties": {
    "addr:full":"1025 S Gold St Centralia WA 98531",
    "addr:housenumber":"1025",
    "addr:postcode":"98531",
    "addr:street":"S Gold St",
    "iso:country":"US",
    "sg:address":"1025 S Gold St",
    "sg:city":"Centralia",
    "sg:classifiers":[
        {
            "category":"Autos & Motor Vehicles",
            "subcategory":"Auto Supplies",
            "type":"Retail Goods"
        },
        {
            "category":"Personal",
            "type":"Services"
        },
        {
            "category":"Retail",
            "subcategory":"Auto Repair",
            "type":"Services"
        }
    ],
    "sg:phone":"+1 360 748 4118",
    "sg:postcode":"98531",
    "sg:province":"WA",
    "sg:tags":[
        "towing",
        "tire"
    ],
    "wof:name":"Grant's Towing & Automotive",
    "wof:placetype":"venue"
},
  "geometry": {"coordinates":[-122.955459,46.705843],"type":"Point"}
}