{
  "type": "Feature",
  "properties": {
    "addr:full":"3518 Fremont Avenue N. #352 Seattle WA 98103",
    "addr:housenumber":"3518",
    "addr:postcode":"98103",
    "addr:street":"Fremont Avenue N. # 352",
    "iso:country":"US",
    "sg:address":"3518 Fremont Avenue N. #352",
    "sg:city":"Seattle",
    "sg:classifiers":[
        {
            "category":"Food & Beverages",
            "subcategory":"Farmers Market",
            "type":"Retail Goods"
        },
        {
            "category":"Food & Beverages",
            "subcategory":"Groceries & Convenience Stores",
            "type":"Retail Goods"
        }
    ],
    "sg:phone":"+1 206 276 1731",
    "sg:postcode":"98103",
    "sg:province":"WA",
    "sg:website":"www.growingwashington.org",
    "wof:name":"Growing Washington",
    "wof:placetype":"venue"
},
  "geometry": {"coordinates":[-122.349852,47.650793],"type":"Point"}
}