{
  "type": "Feature",
  "properties": {
    "addr:full":"1350 Gilbert Rd Zillah WA 98953",
    "addr:housenumber":"1350",
    "addr:postcode":"98953",
    "addr:street":"Gilbert Rd",
    "iso:country":"US",
    "sg:address":"1350 Gilbert Rd",
    "sg:city":"Zillah",
    "sg:classifiers":[
        {
            "category":"Building & Trades",
            "subcategory":"Construction",
            "type":"Services"
        }
    ],
    "sg:phone":"+1 509 829 6634",
    "sg:postcode":"98953",
    "sg:province":"WA",
    "sg:tags":[
        "general",
        "contractor"
    ],
    "wof:name":"Golden Great NW Construction",
    "wof:placetype":"venue"
},
  "geometry": {"coordinates":[-120.295154,46.447422],"type":"Point"}
}