{
  "type": "Feature",
  "properties": {
    "addr:full":"1115 NW 51st St Seattle WA 98107",
    "addr:housenumber":"1115",
    "addr:postcode":"98107",
    "addr:street":"Nw 51St St",
    "iso:country":"US",
    "sg:address":"1115 NW 51st St",
    "sg:city":"Seattle",
    "sg:classifiers":[
        {
            "category":"Building & Trades",
            "subcategory":"Plumbing",
            "type":"Services"
        },
        {
            "category":"Home & Garden",
            "subcategory":"Building Materials",
            "type":"Retail Goods"
        },
        {
            "category":"Building & Trades",
            "subcategory":"Construction",
            "type":"Services"
        },
        {
            "category":"Utilities",
            "subcategory":"Sewage",
            "type":"Services"
        }
    ],
    "sg:phone":"+1 206 337 2116",
    "sg:postcode":"98107",
    "sg:province":"WA",
    "sg:tags":[
        "heater",
        "plumber",
        "heating",
        "specialty",
        "water",
        "sewer",
        "cleaning",
        "contractor",
        "plumbing-drain"
    ],
    "sg:website":"http://www.alligatorsewer.com",
    "wof:name":"Alligator Sewer & Drain Cleaning Service",
    "wof:placetype":"venue"
},
  "geometry": {"coordinates":[-122.371162,47.66572],"type":"Point"}
}