{
  "type": "Feature",
  "properties": {
    "addr:full":"300 SE Pioneer St Pullman WA 99163",
    "addr:housenumber":"300",
    "addr:postcode":"99163",
    "addr:street":"Se Pioneer St",
    "iso:country":"US",
    "sg:address":"300 SE Pioneer St",
    "sg:city":"Pullman",
    "sg:classifiers":[
        {
            "category":"Professional",
            "subcategory":"Lawyer & Legal Services",
            "type":"Services"
        }
    ],
    "sg:phone":"+1 509 334 0498",
    "sg:postcode":"99163",
    "sg:province":"WA",
    "sg:tags":[
        "attorney",
        "practice"
    ],
    "wof:name":"Dorothy L Wiley Atty",
    "wof:placetype":"venue"
},
  "geometry": {"coordinates":[-117.18013000000001,46.727619],"type":"Point"}
}