{
  "type": "Feature",
  "properties": {
    "addr:full":"450 12th Ave Seattle WA 98122",
    "addr:housenumber":"450",
    "addr:postcode":"98122",
    "addr:street":"12Th Ave",
    "iso:country":"US",
    "sg:address":"450 12th Ave",
    "sg:city":"Seattle",
    "sg:classifiers":[
        {
            "category":"Personal",
            "subcategory":"Beauty Salon",
            "type":"Services"
        }
    ],
    "sg:phone":"+1 206 323 9095",
    "sg:postcode":"98122",
    "sg:province":"WA",
    "wof:name":"Concepts By Design",
    "wof:placetype":"venue"
},
  "geometry": {"coordinates":[-122.31670699999999,47.606176],"type":"Point"}
}