{
  "type": "Feature",
  "properties": {
    "addr:full":"10405 NE 9th Ave Apt H4 Vancouver WA 98685",
    "addr:housenumber":"10405",
    "addr:postcode":"98685",
    "addr:street":"Ne 9Th Ave Apt H4",
    "iso:country":"US",
    "sg:address":"10405 NE 9th Ave Apt H4",
    "sg:city":"Vancouver",
    "sg:classifiers":[
        {
            "category":"Arts & Performance",
            "subcategory":"Art Gallery",
            "type":"Entertainment"
        }
    ],
    "sg:phone":"+1 360 695 9134",
    "sg:postcode":"98685",
    "sg:province":"WA",
    "sg:tags":[
        "fine",
        "artist"
    ],
    "wof:name":"Wanda Mcevoy Artist",
    "wof:placetype":"venue"
},
  "geometry": {"coordinates":[-122.66309800000001,45.696593],"type":"Point"}
}