{
  "type": "Feature",
  "properties": {
    "addr:full":"2317 W 2nd Ave Apt 108 Spokane WA 99201",
    "addr:housenumber":"2317;108",
    "addr:postcode":"99201",
    "addr:street":"W 2Nd Ave Apt",
    "iso:country":"US",
    "sg:address":"2317 W 2nd Ave Apt 108",
    "sg:city":"Spokane",
    "sg:classifiers":[
        {
            "category":"Real Estate",
            "subcategory":"Real Estate Operator",
            "type":"Services"
        }
    ],
    "sg:phone":"+1 509 747 6788",
    "sg:postcode":"99201",
    "sg:province":"WA",
    "sg:tags":[
        "apartment"
    ],
    "wof:name":"Western Property Management",
    "wof:placetype":"venue"
},
  "geometry": {"coordinates":[-117.446416,47.654531],"type":"Point"}
}