{
  "type": "Feature",
  "properties": {
    "addr:full":"8243 Sims Rd Sedro Woolley WA 98284",
    "addr:housenumber":"8243",
    "addr:postcode":"98284",
    "addr:street":"Sims Rd",
    "iso:country":"US",
    "sg:address":"8243 Sims Rd",
    "sg:city":"Sedro Woolley",
    "sg:classifiers":[
        {
            "category":"Farming",
            "subcategory":"Orchard",
            "type":"Manufacturing & Wholesale Goods"
        }
    ],
    "sg:phone":"+1 360 856 6986",
    "sg:postcode":"98284",
    "sg:province":"WA",
    "sg:tags":[
        "fruit",
        "tree"
    ],
    "wof:name":"Perkins Variety Apples Inc",
    "wof:placetype":"venue"
},
  "geometry": {"coordinates":[-122.156254,48.52605],"type":"Point"}
}