{
  "type": "Feature",
  "properties": {
    "addr:full":"2910 129th Ave SE Bellevue WA 98005",
    "addr:housenumber":"2910",
    "addr:postcode":"98005",
    "addr:street":"129Th Ave Se",
    "iso:country":"US",
    "sg:address":"2910 129th Ave SE",
    "sg:city":"Bellevue",
    "sg:classifiers":[
        {
            "category":"Social Services",
            "subcategory":"Child Care",
            "type":"Services"
        }
    ],
    "sg:phone":"+1 425 747 6988",
    "sg:postcode":"98005",
    "sg:province":"WA",
    "sg:tags":[
        "day"
    ],
    "wof:name":"Joan Dubois Daycare",
    "wof:placetype":"venue"
},
  "geometry": {"coordinates":[-122.167862,47.584593],"type":"Point"}
}