{
  "type": "Feature",
  "properties": {
    "addr:full":"9726 Evanston Ave N Seattle WA 98103",
    "addr:housenumber":"9726",
    "addr:postcode":"98103",
    "addr:street":"Evanston Ave N",
    "iso:country":"US",
    "sg:address":"9726 Evanston Ave N",
    "sg:city":"Seattle",
    "sg:classifiers":[
        {
            "category":"Manufacturing",
            "subcategory":"Jewelry",
            "type":"Manufacturing & Wholesale Goods"
        }
    ],
    "sg:phone":"+1 206 783 7135",
    "sg:postcode":"98103",
    "sg:province":"WA",
    "sg:tags":[
        "stone",
        "manufacturer",
        "jewelers-wholesale",
        "jewels-imitation"
    ],
    "wof:name":"Polymer Clayworks",
    "wof:placetype":"venue"
},
  "geometry": {"coordinates":[-122.35124399999999,47.700119],"type":"Point"}
}