{
  "type": "Feature",
  "properties": {
    "addr:full":"2271 NE 51st St Seattle WA 98105",
    "addr:housenumber":"2271",
    "addr:postcode":"98105",
    "addr:street":"Ne 51St St",
    "iso:country":"US",
    "sg:address":"2271 NE 51st St",
    "sg:city":"Seattle",
    "sg:classifiers":[
        {
            "category":"Health Services",
            "subcategory":"Health Practitioner",
            "type":"Services"
        }
    ],
    "sg:phone":"+1 206 522 8553",
    "sg:postcode":"98105",
    "sg:province":"WA",
    "sg:tags":[
        "sleep",
        "treatment",
        "disorders-information"
    ],
    "wof:name":"Donald J Ross",
    "wof:placetype":"venue"
},
  "geometry": {"coordinates":[-122.302594,47.665723],"type":"Point"}
}