{
  "type": "Feature",
  "properties": {
    "addr:full":"713 NE 4th Ave Camas WA 98607",
    "addr:housenumber":"713",
    "addr:postcode":"98607",
    "addr:street":"Ne 4Th Ave",
    "iso:country":"US",
    "sg:address":"713 NE 4th Ave",
    "sg:city":"Camas",
    "sg:classifiers":[
        {
            "category":"Health Services",
            "subcategory":"Health Practitioner",
            "type":"Services"
        }
    ],
    "sg:phone":"+1 360 834 2347",
    "sg:postcode":"98607",
    "sg:province":"WA",
    "wof:name":"Chris DSC Fanning",
    "wof:placetype":"venue"
},
  "geometry": {"coordinates":[-122.401533,45.587277],"type":"Point"}
}