{
  "type": "Feature",
  "properties": {
    "addr:full":"10118 NE 43rd Ave Vancouver WA 98686",
    "addr:housenumber":"10118",
    "addr:postcode":"98686",
    "addr:street":"Ne 43Rd Ave",
    "iso:country":"US",
    "sg:address":"10118 NE 43rd Ave",
    "sg:city":"Vancouver",
    "sg:classifiers":[
        {
            "category":"Shopping",
            "subcategory":"Antiques",
            "type":"Retail Goods"
        },
        {
            "category":"Shopping",
            "subcategory":"Catalog Store",
            "type":"Retail Goods"
        },
        {
            "category":"Shopping",
            "type":"Retail Goods"
        }
    ],
    "sg:phone":"+1 360 571 9367",
    "sg:postcode":"98686",
    "sg:province":"WA",
    "sg:tags":[
        "collectible",
        "order",
        "mail",
        "online"
    ],
    "wof:name":"Netters Novelties",
    "wof:placetype":"venue"
},
  "geometry": {"coordinates":[-122.627724,45.694833],"type":"Point"}
}