{
  "type": "Feature",
  "properties": {
    "addr:full":"821 Lyons Rd Ellensburg WA 98926",
    "addr:housenumber":"821",
    "addr:postcode":"98926",
    "addr:street":"Lyons Rd",
    "iso:country":"US",
    "sg:address":"821 Lyons Rd",
    "sg:city":"Ellensburg",
    "sg:classifiers":[
        {
            "category":"Personal",
            "type":"Services"
        }
    ],
    "sg:phone":"+1 509 962 9753",
    "sg:postcode":"98926",
    "sg:province":"WA",
    "wof:name":"Scribner Meats",
    "wof:placetype":"venue"
},
  "geometry": {"coordinates":[-120.486211,47.021925],"type":"Point"}
}