{
  "type": "Feature",
  "properties": {
    "addr:full":"5000 20th Avenue N.W. Seattle WA 98107",
    "addr:housenumber":"5000",
    "addr:postcode":"98107",
    "addr:street":"20Th Avenue N.W.",
    "iso:country":"US",
    "sg:address":"5000 20th Avenue N.W.",
    "sg:city":"Seattle",
    "sg:classifiers":[
        {
            "category":"Shopping",
            "subcategory":"Crafts & Fabrics",
            "type":"Retail Goods"
        }
    ],
    "sg:phone":"+1 206 323 0404",
    "sg:postcode":"98107",
    "sg:province":"WA",
    "sg:tags":[
        "art"
    ],
    "sg:website":"threadshop@thread.net",
    "wof:name":"Thread Shop",
    "wof:placetype":"venue"
},
  "geometry": {"coordinates":[-122.38200399999999,47.665699],"type":"Point"}
}