{
  "type": "Feature",
  "properties": {
    "addr:full":"2315 E Pike St Seattle WA 98122",
    "addr:housenumber":"2315",
    "addr:postcode":"98122",
    "addr:street":"E Pike St",
    "iso:country":"US",
    "sg:address":"2315 E Pike St",
    "sg:city":"Seattle",
    "sg:classifiers":[
        {
            "category":"Real Estate",
            "subcategory":"Architect",
            "type":"Services"
        }
    ],
    "sg:phone":"+1 206 763 8496",
    "sg:postcode":"98122",
    "sg:province":"WA",
    "sg:tags":[
        "architectural"
    ],
    "wof:name":"Travers Mark Architect",
    "wof:placetype":"venue"
},
  "geometry": {"coordinates":[-122.302002,47.614201],"type":"Point"}
}