{
  "type": "Feature",
  "properties": {
    "addr:full":"10236 13th Ave S Seattle WA 98168",
    "addr:housenumber":"10236",
    "addr:postcode":"98168",
    "addr:street":"13Th Ave S",
    "iso:country":"US",
    "sg:address":"10236 13th Ave S",
    "sg:city":"Seattle",
    "sg:classifiers":[
        {
            "category":"Professional",
            "type":"Services"
        }
    ],
    "sg:phone":"+1 206 767 2797",
    "sg:postcode":"98168",
    "sg:province":"WA",
    "wof:name":"TN T Services",
    "wof:placetype":"venue"
},
  "geometry": {"coordinates":[-122.31666300000001,47.510642],"type":"Point"}
}