{
  "type": "Feature",
  "properties": {
    "addr:full":"8308 55th Ave NE Marysville WA 98270",
    "addr:housenumber":"8308",
    "addr:postcode":"98270",
    "addr:street":"55Th Ave Ne",
    "iso:country":"US",
    "sg:address":"8308 55th Ave NE",
    "sg:city":"Marysville",
    "sg:classifiers":[
        {
            "category":"Organizations",
            "subcategory":"Religious Organization",
            "type":"Services"
        }
    ],
    "sg:phone":"+1 360 659 2603",
    "sg:postcode":"98270",
    "sg:province":"WA",
    "sg:tags":[
        "clergy"
    ],
    "wof:name":"Newton H Waldrop",
    "wof:placetype":"venue"
},
  "geometry": {"coordinates":[-122.156053,48.07024],"type":"Point"}
}