{
  "type": "Feature",
  "properties": {
    "addr:full":"30103 SE Lake Retreat North Dr Ravensdale WA 98051",
    "addr:postcode":"30103;98051",
    "addr:street":"Se Lake;North Dr Ravensdale",
    "iso:country":"US",
    "sg:address":"30103 SE Lake Retreat North Dr",
    "sg:city":"Ravensdale",
    "sg:classifiers":[
        {
            "category":"Professional",
            "subcategory":"Engineering",
            "type":"Services"
        }
    ],
    "sg:phone":"+1 425 432 4101",
    "sg:postcode":"98051",
    "sg:province":"WA",
    "wof:name":"Peter A Opsahl Strl Engrg",
    "wof:placetype":"venue"
},
  "geometry": {"coordinates":[-121.94510200000001,47.354265],"type":"Point"}
}