{
  "type": "Feature",
  "properties": {
    "addr:full":"6425 W John Day Ave Kennewick WA 99336",
    "addr:housenumber":"6425",
    "addr:postcode":"99336",
    "addr:street":"W John Day Ave",
    "iso:country":"US",
    "sg:address":"6425 W John Day Ave",
    "sg:city":"Kennewick",
    "sg:classifiers":[
        {
            "category":"Wholesale",
            "subcategory":"Hardware",
            "type":"Manufacturing & Wholesale Goods"
        }
    ],
    "sg:phone":"+1 509 735 0427",
    "sg:postcode":"99336",
    "sg:province":"WA",
    "wof:name":"Gensco-Albina Inc",
    "wof:placetype":"venue"
},
  "geometry": {"coordinates":[-119.2034,46.218124],"type":"Point"}
}