{
  "type": "Feature",
  "properties": {
    "addr:full":"261 Madison Ave S Bainbridge Isle WA 98110",
    "addr:housenumber":"261",
    "addr:postcode":"98110",
    "addr:street":"Madison Ave S Bainbridge Isle",
    "iso:country":"US",
    "sg:address":"261 Madison Ave S",
    "sg:city":"Bainbridge Isle",
    "sg:classifiers":[
        {
            "category":"Professional",
            "subcategory":"Management & Consulting",
            "type":"Services"
        }
    ],
    "sg:phone":"+1 206 842 5180",
    "sg:postcode":"98110",
    "sg:province":"WA",
    "sg:tags":[
        "consultant",
        "business"
    ],
    "wof:name":"Norman Down",
    "wof:placetype":"venue"
},
  "geometry": {"coordinates":[-122.521052,47.623675],"type":"Point"}
}