{
  "type": "Feature",
  "properties": {
    "addr:full":"10504 Canyon Rd E Puyallup WA 98373",
    "addr:housenumber":"10504",
    "addr:postcode":"98373",
    "addr:street":"Canyon Rd E",
    "iso:country":"US",
    "sg:address":"10504 Canyon Rd E",
    "sg:city":"Puyallup",
    "sg:classifiers":[
        {
            "category":"Autos & Motor Vehicles",
            "subcategory":"Fuel & Gas Station",
            "type":"Retail Goods"
        }
    ],
    "sg:phone":"+1 253 536 0943",
    "sg:postcode":"98373",
    "sg:province":"WA",
    "sg:tags":[
        "grocery",
        "station",
        "gasoline"
    ],
    "wof:name":"BP",
    "wof:placetype":"venue"
},
  "geometry": {"coordinates":[-122.35720999999999,47.160792],"type":"Point"}
}