{
  "type": "Feature",
  "properties": {
    "addr:full":"4075 Auburn Way N Auburn WA 98002",
    "addr:housenumber":"4075",
    "addr:postcode":"98002",
    "addr:street":"Auburn Way N",
    "iso:country":"US",
    "sg:address":"4075 Auburn Way N",
    "sg:city":"Auburn",
    "sg:classifiers":[
        {
            "category":"Banks & Credit Unions",
            "subcategory":"Bank",
            "type":"Services"
        }
    ],
    "sg:phone":"+1 253 520 9300",
    "sg:postcode":"98002",
    "sg:province":"WA",
    "sg:tags":[
        "cashing",
        "check"
    ],
    "wof:name":"Easy Money",
    "wof:placetype":"venue"
},
  "geometry": {"coordinates":[-122.22238,47.343868],"type":"Point"}
}