{
  "type": "Feature",
  "properties": {
    "iso:country":"US",
    "sg:address":"341 NE 167th St",
    "sg:city":"Shoreline",
    "sg:classifiers":[
        {
            "category":"Social Services",
            "subcategory":"Job Training",
            "type":"Services"
        }
    ],
    "sg:phone":"+1 206 362 8831",
    "sg:postcode":"98155",
    "sg:province":"WA",
    "sg:tags":[
        "rehabilitation"
    ],
    "wof:name":"Center For Self-Reliant Healng",
    "wof:placetype":"venue"
},
  "geometry": {"coordinates":[-122.324066,47.750328],"type":"Point"}
}