{
  "type": "Feature",
  "properties": {
    "addr:full":"8220 SE 67th St Mercer Island WA 98040",
    "addr:housenumber":"8220",
    "addr:postcode":"98040",
    "addr:street":"Se 67Th St",
    "iso:country":"US",
    "sg:address":"8220 SE 67th St",
    "sg:city":"Mercer Island",
    "sg:classifiers":[
        {
            "category":"Professional",
            "subcategory":"Accounting & Tax Preparation",
            "type":"Services"
        }
    ],
    "sg:phone":"+1 206 236 0796",
    "sg:postcode":"98040",
    "sg:province":"WA",
    "wof:name":"Stacy Bjarnason Bookkeeping",
    "wof:placetype":"venue"
},
  "geometry": {"coordinates":[-122.22777499999999,47.542848],"type":"Point"}
}