{
  "type": "Feature",
  "properties": {
    "iso:country":"US",
    "sg:address":"13122 SE 240th St",
    "sg:city":"Kent",
    "sg:classifiers":[
        {
            "category":"Food & Beverages",
            "subcategory":"Groceries & Convenience Stores",
            "type":"Retail Goods"
        }
    ],
    "sg:phone":"+1 253 631 8512",
    "sg:postcode":"98031",
    "sg:province":"WA",
    "wof:name":"76 Circle K",
    "wof:placetype":"venue"
},
  "geometry": {"coordinates":[-122.166591,47.386992],"type":"Point"}
}