{
  "type": "Feature",
  "properties": {
    "addr:full":"37423 239th Ave SE Enumclaw WA 98022",
    "addr:housenumber":"37423",
    "addr:postcode":"98022",
    "addr:street":"239Th Ave Se",
    "iso:country":"US",
    "sg:address":"37423 239th Ave SE",
    "sg:city":"Enumclaw",
    "sg:classifiers":[
        {
            "category":"Building & Trades",
            "subcategory":"Plumbing",
            "type":"Services"
        }
    ],
    "sg:phone":"+1 360 825 6999",
    "sg:postcode":"98022",
    "sg:province":"WA",
    "sg:tags":[
        "contractor"
    ],
    "wof:name":"Alley Plumbing",
    "wof:placetype":"venue"
},
  "geometry": {"coordinates":[-122.024001,47.264457],"type":"Point"}
}