{
  "type": "Feature",
  "properties": {
    "addr:full":"1601 E Fourth Plain Blvd Vancouver WA 98661",
    "addr:housenumber":"1601",
    "addr:postcode":"98661",
    "addr:street":"E Fourth Plain Blvd",
    "iso:country":"US",
    "sg:address":"1601 E Fourth Plain Blvd",
    "sg:city":"Vancouver",
    "sg:classifiers":[
        {
            "category":"Health Services",
            "subcategory":"Hospital",
            "type":"Services"
        }
    ],
    "sg:phone":"+1 360 906 8336",
    "sg:postcode":"98661",
    "sg:province":"WA",
    "sg:tags":[
        "mental"
    ],
    "wof:name":"Mental Health Northwest",
    "wof:placetype":"venue"
},
  "geometry": {"coordinates":[-122.65488499999999,45.639354],"type":"Point"}
}