{
  "type": "Feature",
  "properties": {
    "iso:country":"US",
    "sg:address":"23212 53rd Ave SE",
    "sg:city":"Bothell",
    "sg:classifiers":[
        {
            "category":"Professional",
            "subcategory":"Business Services",
            "type":"Services"
        }
    ],
    "sg:phone":"+1 425 481 9345",
    "sg:postcode":"98021",
    "sg:province":"WA",
    "wof:name":"Pivotal Z",
    "wof:placetype":"venue"
},
  "geometry": {"coordinates":[-122.162122,47.786096],"type":"Point"}
}