{
  "type": "Feature",
  "properties": {
    "addr:full":"326 Olga Rd Eastsound WA 98245",
    "addr:housenumber":"326",
    "addr:postcode":"98245",
    "addr:street":"Olga Rd",
    "iso:country":"US",
    "sg:address":"326 Olga Rd",
    "sg:city":"Eastsound",
    "sg:classifiers":[
        {
            "category":"Restaurant",
            "type":"Food & Drink"
        }
    ],
    "sg:phone":"+1 360 376 5886",
    "sg:postcode":"98245",
    "sg:province":"WA",
    "sg:tags":[
        "operation",
        "eating"
    ],
    "wof:name":"Ships Bay Oyster House",
    "wof:placetype":"venue"
},
  "geometry": {"coordinates":[-122.88456100000001,48.695653],"type":"Point"}
}