{
  "type": "Feature",
  "properties": {
    "iso:country":"US",
    "sg:address":"6116 30th Ave NW",
    "sg:city":"Seattle",
    "sg:classifiers":[
        {
            "category":"Shopping",
            "subcategory":"Musical Instruments",
            "type":"Retail Goods"
        }
    ],
    "sg:phone":"+1 206 789 4760",
    "sg:postcode":"98107",
    "sg:province":"WA",
    "wof:name":"Filimonov Fine Instruments",
    "wof:placetype":"venue"
},
  "geometry": {"coordinates":[-122.39559800000001,47.673582],"type":"Point"}
}