{
  "type": "Feature",
  "properties": {
    "addr:full":"734 10th Ave E Seattle WA 98102",
    "addr:housenumber":"734",
    "addr:postcode":"98102",
    "addr:street":"10Th Ave E",
    "iso:country":"US",
    "sg:address":"734 10th Ave E",
    "sg:city":"Seattle",
    "sg:classifiers":[
        {
            "category":"Real Estate",
            "subcategory":"Developer",
            "type":"Services"
        }
    ],
    "sg:phone":"+1 206 866 0124",
    "sg:postcode":"98102",
    "sg:province":"WA",
    "wof:name":"Emerald Group Developments",
    "wof:placetype":"venue"
},
  "geometry": {"coordinates":[-122.320257,47.625659],"type":"Point"}
}