{
  "type": "Feature",
  "properties": {
    "addr:full":"5916 NE 60th St Seattle WA 98115",
    "addr:housenumber":"5916",
    "addr:postcode":"98115",
    "addr:street":"Ne 60Th St",
    "iso:country":"US",
    "sg:address":"5916 NE 60th St",
    "sg:city":"Seattle",
    "sg:classifiers":[
        {
            "category":"Manufacturing",
            "subcategory":"Lumber",
            "type":"Manufacturing & Wholesale Goods"
        }
    ],
    "sg:phone":"+1 206 523 9641",
    "sg:postcode":"98115",
    "sg:province":"WA",
    "sg:tags":[
        "operation",
        "timber",
        "logging",
        "tract"
    ],
    "wof:name":"C & K Properties/C & K",
    "wof:placetype":"venue"
},
  "geometry": {"coordinates":[-122.263597,47.672176],"type":"Point"}
}