{
  "type": "Feature",
  "properties": {
    "addr:full":"2468 168th Pl NE Bellevue WA 98008",
    "addr:housenumber":"2468",
    "addr:postcode":"98008",
    "addr:street":"168Th Pl Ne",
    "iso:country":"US",
    "sg:address":"2468 168th Pl NE",
    "sg:city":"Bellevue",
    "sg:classifiers":[
        {
            "category":"Personal",
            "subcategory":"Massage",
            "type":"Services"
        }
    ],
    "sg:phone":"+1 425 497 0243",
    "sg:postcode":"98008",
    "sg:province":"WA",
    "wof:name":"Nirvana Health Massage",
    "wof:placetype":"venue"
},
  "geometry": {"coordinates":[-122.116061,47.632103],"type":"Point"}
}