{
  "type": "Feature",
  "properties": {
    "addr:full":"4109 S Green St Kennewick WA 99337",
    "addr:housenumber":"4109",
    "addr:postcode":"99337",
    "addr:street":"S Green St",
    "iso:country":"US",
    "sg:address":"4109 S Green St",
    "sg:city":"Kennewick",
    "sg:classifiers":[
        {
            "category":"Building & Trades",
            "subcategory":"Construction",
            "type":"Services"
        }
    ],
    "sg:phone":"+1 509 585 8989",
    "sg:postcode":"99337",
    "sg:province":"WA",
    "wof:name":"James D Wilhelm",
    "wof:placetype":"venue"
},
  "geometry": {"coordinates":[-119.160951,46.171426],"type":"Point"}
}