{
  "type": "Feature",
  "properties": {
    "addr:full":"25617 98th Ave S Kent WA 98030",
    "addr:housenumber":"25617",
    "addr:postcode":"98030",
    "addr:street":"98Th Ave S",
    "iso:country":"US",
    "sg:address":"25617 98th Ave S",
    "sg:city":"Kent",
    "sg:classifiers":[
        {
            "category":"Building & Trades",
            "subcategory":"Construction",
            "type":"Services"
        }
    ],
    "sg:phone":"+1 206 227 7478",
    "sg:postcode":"98030",
    "sg:province":"WA",
    "sg:tags":[
        "house"
    ],
    "wof:name":"Modern Age Builders",
    "wof:placetype":"venue"
},
  "geometry": {"coordinates":[-122.209829,47.373246],"type":"Point"}
}