{
  "type": "Feature",
  "properties": {
    "addr:full":"2115 NW Poplar Way Issaquah WA 98027",
    "addr:housenumber":"2115",
    "addr:postcode":"98027",
    "addr:street":"Nw Poplar Way",
    "iso:country":"US",
    "sg:address":"2115 NW Poplar Way",
    "sg:city":"Issaquah",
    "sg:classifiers":[
        {
            "category":"Personal",
            "type":"Services"
        },
        {
            "category":"Arena",
            "subcategory":"Sports Club",
            "type":"Entertainment"
        },
        {
            "category":"Sports & Exercise",
            "subcategory":"Tennis Court",
            "type":"Entertainment"
        }
    ],
    "sg:phone":"+1 425 313 3131",
    "sg:postcode":"98027",
    "sg:province":"WA",
    "sg:tags":[
        "trainer",
        "courts-private",
        "consultant",
        "health",
        "fitness",
        "physical"
    ],
    "sg:website":"http://www.samsclub.com",
    "wof:name":"Sammamish Club",
    "wof:placetype":"venue"
},
  "geometry": {"coordinates":[-122.06553700000001,47.54955],"type":"Point"}
}