{
  "type": "Feature",
  "properties": {
    "addr:full":"3920 Capitol Mall Dr SW Olympia WA 98502",
    "addr:housenumber":"3920",
    "addr:postcode":"98502",
    "addr:street":"Capitol Mall Dr Sw",
    "iso:country":"US",
    "sg:address":"3920 Capitol Mall Dr SW",
    "sg:city":"Olympia",
    "sg:classifiers":[
        {
            "category":"Health Services",
            "subcategory":"Doctor",
            "type":"Services"
        }
    ],
    "sg:phone":"+1 360 705 1259",
    "sg:postcode":"98502",
    "sg:province":"WA",
    "sg:tags":[
        "medical"
    ],
    "wof:name":"Richard Hennegan PC",
    "wof:placetype":"venue"
},
  "geometry": {"coordinates":[-122.950312,47.041584],"type":"Point"}
}