{
  "type": "Feature",
  "properties": {
    "addr:full":"2818 98th Ave NE Bellevue WA 98004",
    "addr:housenumber":"2818",
    "addr:postcode":"98004",
    "addr:street":"98Th Ave Ne",
    "iso:country":"US",
    "sg:address":"2818 98th Ave NE",
    "sg:city":"Bellevue",
    "sg:classifiers":[
        {
            "category":"Professional",
            "subcategory":"Employment Agencies",
            "type":"Services"
        }
    ],
    "sg:phone":"+1 425 531 1443",
    "sg:postcode":"98004",
    "sg:province":"WA",
    "wof:name":"Bancpros Inc",
    "wof:placetype":"venue"
},
  "geometry": {"coordinates":[-122.20963,47.636356],"type":"Point"}
}