{
  "type": "Feature",
  "properties": {
    "addr:full":"7221 5th Ave NW Seattle WA 98117",
    "addr:housenumber":"7221",
    "addr:postcode":"98117",
    "addr:street":"5Th Ave Nw",
    "iso:country":"US",
    "sg:address":"7221 5th Ave NW",
    "sg:city":"Seattle",
    "sg:classifiers":[
        {
            "category":"Health Services",
            "subcategory":"Health Practitioner",
            "type":"Services"
        }
    ],
    "sg:phone":"+1 206 729 1166",
    "sg:postcode":"98117",
    "sg:province":"WA",
    "wof:name":"Philip Hirsch",
    "wof:placetype":"venue"
},
  "geometry": {"coordinates":[-122.362566,47.681568],"type":"Point"}
}