{
  "type": "Feature",
  "properties": {
    "addr:full":"4221 S Willow St Seattle WA 98118",
    "addr:housenumber":"4221",
    "addr:postcode":"98118",
    "addr:street":"S Willow St",
    "iso:country":"US",
    "sg:address":"4221 S Willow St",
    "sg:city":"Seattle",
    "sg:classifiers":[
        {
            "category":"Professional",
            "subcategory":"Management & Consulting",
            "type":"Services"
        }
    ],
    "sg:phone":"+1 206 789 3898",
    "sg:postcode":"98118",
    "sg:province":"WA",
    "sg:tags":[
        "consultant",
        "business"
    ],
    "wof:name":"Business Technology Inc",
    "wof:placetype":"venue"
},
  "geometry": {"coordinates":[-122.278272,47.540594],"type":"Point"}
}