{
  "type": "Feature",
  "properties": {
    "addr:full":"710 5th Ave NW Issaquah WA 98027",
    "addr:housenumber":"710",
    "addr:postcode":"98027",
    "addr:street":"5Th Ave Nw",
    "iso:country":"US",
    "sg:address":"710 5th Ave NW",
    "sg:city":"Issaquah",
    "sg:classifiers":[
        {
            "category":"Communications",
            "subcategory":"Film & Video Production",
            "type":"Services"
        }
    ],
    "sg:phone":"+1 425 392 3495",
    "sg:postcode":"98027",
    "sg:province":"WA",
    "sg:tags":[
        "motion"
    ],
    "wof:name":"Paradisevalley Productions",
    "wof:placetype":"venue"
},
  "geometry": {"coordinates":[-122.044212,47.537508],"type":"Point"}
}