{
  "type": "Feature",
  "properties": {
    "addr:full":"400 A St Friday Harbor WA 98250",
    "addr:housenumber":"400",
    "addr:postcode":"98250",
    "addr:street":"A St",
    "iso:country":"US",
    "sg:address":"400 A St",
    "sg:city":"Friday Harbor",
    "sg:classifiers":[
        {
            "category":"Freight",
            "type":"Transportation"
        }
    ],
    "sg:phone":"+1 360 378 2012",
    "sg:postcode":"98250",
    "sg:province":"WA",
    "sg:tags":[
        "trucking"
    ],
    "wof:name":"Friday Harbor Freight Lines",
    "wof:placetype":"venue"
},
  "geometry": {"coordinates":[-123.015142,48.532577],"type":"Point"}
}