{
  "type": "Feature",
  "properties": {
    "addr:full":"1107 Harrison Ave NW Olympia WA 98502",
    "addr:housenumber":"1107",
    "addr:postcode":"olympia wa 98502",
    "addr:street":"Harrison Ave Nw",
    "iso:country":"US",
    "sg:address":"1107 Harrison Ave NW",
    "sg:city":"Olympia",
    "sg:classifiers":[
        {
            "category":"Social Services",
            "subcategory":"Job Training",
            "type":"Services"
        }
    ],
    "sg:phone":"+1 360 754 0701",
    "sg:postcode":"98502",
    "sg:province":"WA",
    "sg:tags":[
        "career",
        "counseling",
        "vocational"
    ],
    "sg:website":"www.grantcounseling.com",
    "wof:name":"Grant & Assoc",
    "wof:placetype":"venue"
},
  "geometry": {"coordinates":[-122.916698,47.045789],"type":"Point"}
}