{
  "type": "Feature",
  "properties": {
    "addr:full":"11425 W Sunset Hwy Airway Heights WA 99001",
    "addr:housenumber":"11425",
    "addr:postcode":"99001",
    "addr:street":"W Sunset Hwy Airway Heights",
    "iso:country":"US",
    "sg:address":"11425 W Sunset Hwy",
    "sg:city":"Airway Heights",
    "sg:classifiers":[
        {
            "category":"Retail",
            "subcategory":"Auto Repair",
            "type":"Services"
        }
    ],
    "sg:phone":"+1 509 244 9277",
    "sg:postcode":"99001",
    "sg:province":"WA",
    "sg:tags":[
        "body",
        "automobile",
        "painting",
        "automotive"
    ],
    "wof:name":"City West Auto Body Inc",
    "wof:placetype":"venue"
},
  "geometry": {"coordinates":[-117.570459,47.642857],"type":"Point"}
}