{
  "type": "Feature",
  "properties": {
    "addr:full":"1313 Commerce Ave Longview WA 98632",
    "addr:housenumber":"1313",
    "addr:postcode":"98632",
    "addr:street":"Commerce Ave",
    "iso:country":"US",
    "sg:address":"1313 Commerce Ave",
    "sg:city":"Longview",
    "sg:classifiers":[
        {
            "category":"Shopping",
            "subcategory":"Crafts & Fabrics",
            "type":"Retail Goods"
        }
    ],
    "sg:phone":"+1 360 577 0130",
    "sg:postcode":"98632",
    "sg:province":"WA",
    "sg:tags":[
        "yarn"
    ],
    "wof:name":"Evies Yarn Emporium",
    "wof:placetype":"venue"
},
  "geometry": {"coordinates":[-122.933994,46.138204],"type":"Point"}
}