{
  "type": "Feature",
  "properties": {
    "addr:full":"11997 Mayfair Ave SW Port Orchard WA 98367",
    "addr:housenumber":"11997",
    "addr:postcode":"98367",
    "addr:street":"Mayfair Ave Sw Port Orchard",
    "iso:country":"US",
    "sg:address":"11997 Mayfair Ave SW",
    "sg:city":"Port Orchard",
    "sg:classifiers":[
        {
            "category":"Professional",
            "type":"Services"
        }
    ],
    "sg:phone":"+1 360 874 8160",
    "sg:postcode":"98367",
    "sg:province":"WA",
    "wof:name":"Kerson Services",
    "wof:placetype":"venue"
},
  "geometry": {"coordinates":[-122.658394,47.439681],"type":"Point"}
}