{
  "type": "Feature",
  "properties": {
    "addr:full":"8119 Jamieson Ct SW Olympia WA 98512",
    "addr:housenumber":"8119",
    "addr:postcode":"98512",
    "addr:street":"Jamieson Ct Sw",
    "iso:country":"US",
    "sg:address":"8119 Jamieson Ct SW",
    "sg:city":"Olympia",
    "sg:classifiers":[
        {
            "category":"Professional",
            "subcategory":"Detective & Security Services",
            "type":"Services"
        }
    ],
    "sg:phone":"+1 360 970 1535",
    "sg:postcode":"98512",
    "sg:province":"WA",
    "sg:tags":[
        "information",
        "bureau"
    ],
    "wof:name":"Kk Outdoor Services",
    "wof:placetype":"venue"
},
  "geometry": {"coordinates":[-122.97981299999999,46.968243],"type":"Point"}
}