{
  "type": "Feature",
  "properties": {
    "addr:full":"2114 Highway 395 S Chewelah WA 99109",
    "addr:housenumber":"2114",
    "addr:postcode":"99109",
    "addr:street":"Highway 395 S Chewelah",
    "iso:country":"US",
    "sg:address":"2114 Highway 395 S",
    "sg:city":"Chewelah",
    "sg:classifiers":[
        {
            "category":"Wholesale",
            "subcategory":"Hardware",
            "type":"Manufacturing & Wholesale Goods"
        },
        {
            "category":"Home & Garden",
            "subcategory":"Garden Supply",
            "type":"Retail Goods"
        },
        {
            "category":"Retail",
            "subcategory":"Repair Shop",
            "type":"Services"
        }
    ],
    "sg:phone":"+1 509 935 8829",
    "sg:postcode":"99109",
    "sg:province":"WA",
    "sg:tags":[
        "renting",
        "lawn",
        "outdoor",
        "power",
        "landscaping",
        "equipment-sales",
        "equipment",
        "saw"
    ],
    "sg:website":"http://www.stihldealer.net/default-dealer-043326.aspx",
    "wof:name":"Hartill's Mountain Saw & Tractor",
    "wof:placetype":"venue"
},
  "geometry": {"coordinates":[-117.80409400000001,48.313455],"type":"Point"}
}