{
  "type": "Feature",
  "properties": {
    "addr:full":"11316 SE Mill Plain Blvd Vancouver WA 98684",
    "addr:housenumber":"11316",
    "addr:postcode":"98684",
    "addr:street":"Se Mill Plain Blvd",
    "iso:country":"US",
    "sg:address":"11316 SE Mill Plain Blvd",
    "sg:city":"Vancouver",
    "sg:classifiers":[
        {
            "category":"Autos & Motor Vehicles",
            "subcategory":"Fuel & Gas Station",
            "type":"Retail Goods"
        }
    ],
    "sg:phone":"+1 360 260 0881",
    "sg:postcode":"98684",
    "sg:province":"WA",
    "sg:tags":[
        "station",
        "gasoline"
    ],
    "wof:name":"Circle K Store",
    "wof:placetype":"venue"
},
  "geometry": {"coordinates":[-122.554917,45.621062],"type":"Point"}
}