{
  "type": "Feature",
  "properties": {
    "addr:full":"1110 S 56th St Tacoma WA 98408",
    "addr:housenumber":"1110",
    "addr:postcode":"98408",
    "addr:street":"S 56Th St",
    "iso:country":"US",
    "sg:address":"1110 S 56th St",
    "sg:city":"Tacoma",
    "sg:classifiers":[
        {
            "category":"Freight",
            "type":"Transportation"
        }
    ],
    "sg:phone":"+1 253 472 6839",
    "sg:postcode":"98408",
    "sg:province":"WA",
    "sg:tags":[
        "mover"
    ],
    "wof:name":"Smooth Movers",
    "wof:placetype":"venue"
},
  "geometry": {"coordinates":[-122.449686,47.206362],"type":"Point"}
}