{
  "type": "Feature",
  "properties": {
    "iso:country":"US",
    "sg:address":"14717 E 12th Ave",
    "sg:city":"Spokane Valley",
    "sg:classifiers":[
        {
            "category":"Building & Trades",
            "subcategory":"Cleaning & Sanitation",
            "type":"Services"
        }
    ],
    "sg:phone":"+1 509 924 3680",
    "sg:postcode":"99037",
    "sg:province":"WA",
    "sg:tags":[
        "house",
        "maintenance"
    ],
    "wof:name":"White Glove Housekeeping",
    "wof:placetype":"venue"
},
  "geometry": {"coordinates":[-117.206304,47.646138],"type":"Point"}
}