{
  "type": "Feature",
  "properties": {
    "addr:full":"1815 S 324th Pl Federal Way WA 98003",
    "addr:housenumber":"1815",
    "addr:postcode":"98003",
    "addr:street":"S 324Th Pl",
    "iso:country":"US",
    "sg:address":"1815 S 324th Pl",
    "sg:city":"Federal Way",
    "sg:classifiers":[
        {
            "category":"Health Services",
            "subcategory":"Doctor",
            "type":"Services"
        }
    ],
    "sg:phone":"+1 253 838 3180",
    "sg:postcode":"98003",
    "sg:province":"WA",
    "sg:tags":[
        "warehouse",
        "mini",
        "dentist",
        "storage"
    ],
    "wof:name":"Alpine Dentistry",
    "wof:placetype":"venue"
},
  "geometry": {"coordinates":[-122.31127600000001,47.311036],"type":"Point"}
}