{
  "type": "Feature",
  "properties": {
    "addr:full":"12930 E Marginal Way S Seattle WA 98168",
    "addr:housenumber":"12930",
    "addr:postcode":"98168",
    "addr:street":"E Marginal Way S",
    "iso:country":"US",
    "sg:address":"12930 E Marginal Way S",
    "sg:city":"Seattle",
    "sg:classifiers":[
        {
            "category":"Restaurant",
            "type":"Food & Drink"
        }
    ],
    "sg:phone":"+1 206 246 0100",
    "sg:postcode":"98168",
    "sg:province":"WA",
    "sg:tags":[
        "eating"
    ],
    "wof:name":"Sandys Corner Expresso",
    "wof:placetype":"venue"
},
  "geometry": {"coordinates":[-122.283519,47.488205],"type":"Point"}
}