{
  "type": "Feature",
  "properties": {
    "addr:full":"19605 W Snoqualmie River Rd NE Duvall WA 98019",
    "addr:housenumber":"19605",
    "addr:postcode":"98019",
    "addr:street":"W Snoqualmie River Rd Ne",
    "iso:country":"US",
    "sg:address":"19605 W Snoqualmie River Rd NE",
    "sg:city":"Duvall",
    "sg:classifiers":[
        {
            "category":"Farming",
            "subcategory":"Dairy Farm",
            "type":"Manufacturing & Wholesale Goods"
        }
    ],
    "sg:phone":"+1 425 788 1114",
    "sg:postcode":"98019",
    "sg:province":"WA",
    "wof:name":"Green Acres Dairy LLC",
    "wof:placetype":"venue"
},
  "geometry": {"coordinates":[-121.96585399999999,47.763837],"type":"Point"}
}