{
  "type": "Feature",
  "properties": {
    "addr:full":"12612 NE 187th St Bothell WA 98011",
    "addr:housenumber":"12612",
    "addr:postcode":"98011",
    "addr:street":"Ne 187Th St",
    "iso:country":"US",
    "sg:address":"12612 NE 187th St",
    "sg:city":"Bothell",
    "sg:classifiers":[
        {
            "category":"Communications",
            "subcategory":"Film & Video Production",
            "type":"Services"
        }
    ],
    "sg:phone":"+1 425 485 5187",
    "sg:postcode":"98011",
    "sg:province":"WA",
    "sg:tags":[
        "motion"
    ],
    "wof:name":"Booyah Films",
    "wof:placetype":"venue"
},
  "geometry": {"coordinates":[-122.171654,47.762394],"type":"Point"}
}