{
  "type": "Feature",
  "properties": {
    "addr:full":"1306 W Washington St Pasco WA 99301",
    "addr:housenumber":"1306",
    "addr:postcode":"99301",
    "addr:street":"W Washington St",
    "iso:country":"US",
    "sg:address":"1306 W Washington St",
    "sg:city":"Pasco",
    "sg:classifiers":[
        {
            "category":"Retail",
            "subcategory":"Laundry & Dry Cleaning",
            "type":"Services"
        }
    ],
    "sg:phone":"+1 509 545 2703",
    "sg:postcode":"99301",
    "sg:province":"WA",
    "sg:tags":[
        "linen",
        "supply"
    ],
    "wof:name":"Cintas Corp",
    "wof:placetype":"venue"
},
  "geometry": {"coordinates":[-119.106977,46.224017],"type":"Point"}
}