{
  "type": "Feature",
  "properties": {
    "addr:full":"1004 M Ave Anacortes WA 98221",
    "addr:housenumber":"1004",
    "addr:postcode":"98221",
    "addr:street":"M Ave",
    "iso:country":"US",
    "sg:address":"1004 M Ave",
    "sg:city":"Anacortes",
    "sg:classifiers":[
        {
            "category":"Health Services",
            "subcategory":"Health Practitioner",
            "type":"Services"
        }
    ],
    "sg:phone":"+1 360 299 3024",
    "sg:postcode":"98221",
    "sg:province":"WA",
    "wof:name":"Davida Lmt Bent",
    "wof:placetype":"venue"
},
  "geometry": {"coordinates":[-122.617352,48.514228],"type":"Point"}
}