{
  "type": "Feature",
  "properties": {
    "addr:full":"1026 Lee Blvd Richland WA 99352",
    "addr:housenumber":"1026",
    "addr:postcode":"99352",
    "addr:street":"Lee Blvd",
    "iso:country":"US",
    "sg:address":"1026 Lee Blvd",
    "sg:city":"Richland",
    "sg:classifiers":[
        {
            "category":"Restaurant",
            "type":"Food & Drink"
        }
    ],
    "sg:phone":"+1 509 946 4525",
    "sg:postcode":"99352",
    "sg:province":"WA",
    "wof:name":"Monterosso's Italian Rstrnt",
    "wof:placetype":"venue"
},
  "geometry": {"coordinates":[-119.278357,46.274911],"type":"Point"}
}