{
  "type": "Feature",
  "properties": {
    "addr:full":"376 Coltsfoot Ln Oak Harbor WA 98277",
    "addr:housenumber":"376",
    "addr:postcode":"98277",
    "addr:street":"Coltsfoot Ln",
    "iso:country":"US",
    "sg:address":"376 Coltsfoot Ln",
    "sg:city":"Oak Harbor",
    "sg:classifiers":[
        {
            "category":"Building & Trades",
            "subcategory":"Landscaping Services",
            "type":"Services"
        }
    ],
    "sg:phone":"+1 360 675 1657",
    "sg:postcode":"98277",
    "sg:province":"WA",
    "sg:tags":[
        "landscape",
        "contractor"
    ],
    "wof:name":"Economy Landscaping",
    "wof:placetype":"venue"
},
  "geometry": {"coordinates":[-122.636106,48.338535],"type":"Point"}
}