{
  "type": "Feature",
  "properties": {
    "addr:full":"2632 Rudkin Rd Union Gap WA 98903",
    "addr:housenumber":"2632",
    "addr:postcode":"98903",
    "addr:street":"Rudkin Rd",
    "iso:country":"US",
    "sg:address":"2632 Rudkin Rd",
    "sg:city":"Union Gap",
    "sg:classifiers":[
        {
            "category":"Banks & Credit Unions",
            "subcategory":"Bank",
            "type":"Services"
        }
    ],
    "sg:phone":"+1 509 248 5522",
    "sg:postcode":"98903",
    "sg:province":"WA",
    "sg:website":"www.sthwycu.com",
    "wof:name":"State Highway District 5CU",
    "wof:placetype":"venue"
},
  "geometry": {"coordinates":[-120.475296,46.56143],"type":"Point"}
}