{
  "type": "Feature",
  "properties": {
    "addr:full":"18272 N Frontage Rd E Moses Lake WA 98837",
    "addr:housenumber":"18272",
    "addr:postcode":"98837",
    "addr:street":"N Frontage Rd E",
    "iso:country":"US",
    "sg:address":"18272 N Frontage Rd E",
    "sg:city":"Moses Lake",
    "sg:phone":"+1 509 765 6056",
    "sg:postcode":"98837",
    "sg:province":"WA",
    "sg:tags":[
        "farm",
        "field",
        "crop"
    ],
    "wof:name":"Schwab & Counsell Inc",
    "wof:placetype":"venue"
},
  "geometry": {"coordinates":[-119.103503,47.08703],"type":"Point"}
}