{
  "type": "Feature",
  "properties": {
    "addr:full":"417 W 32nd Ave Spokane WA 99203",
    "addr:housenumber":"417",
    "addr:postcode":"99203",
    "addr:street":"W 32Nd Ave",
    "iso:country":"US",
    "sg:address":"417 W 32nd Ave",
    "sg:city":"Spokane",
    "sg:classifiers":[
        {
            "category":"Health Services",
            "subcategory":"Health Practitioner",
            "type":"Services"
        }
    ],
    "sg:phone":"+1 509 624 0623",
    "sg:postcode":"99203",
    "sg:province":"WA",
    "wof:name":"Michael W Gurian",
    "wof:placetype":"venue"
},
  "geometry": {"coordinates":[-117.417008,47.625399],"type":"Point"}
}