{
  "type": "Feature",
  "properties": {
    "addr:full":"808 Valley Ave NW Puyallup WA 98371",
    "addr:housenumber":"808",
    "addr:postcode":"98371",
    "addr:street":"Valley Ave Nw",
    "iso:country":"US",
    "sg:address":"808 Valley Ave NW",
    "sg:city":"Puyallup",
    "sg:classifiers":[
        {
            "category":"Recreation",
            "type":"Entertainment"
        }
    ],
    "sg:phone":"+1 253 841 5457",
    "sg:postcode":"98371",
    "sg:province":"WA",
    "sg:tags":[
        "gymnasium",
        "center"
    ],
    "sg:website":"www.ci.puyallup.wa.us",
    "wof:name":"Puyallup Recreation Ctr",
    "wof:placetype":"venue"
},
  "geometry": {"coordinates":[-122.302913,47.209778],"type":"Point"}
}