{
  "type": "Feature",
  "properties": {
    "addr:full":"40400 Harts Lake Valley Rd Roy WA 98580",
    "addr:postcode":"40400;98580",
    "addr:street":"Harts Lake Valley Rd",
    "iso:country":"US",
    "sg:address":"40400 Harts Lake Valley Rd",
    "sg:city":"Roy",
    "sg:classifiers":[
        {
            "category":"Manufacturing",
            "subcategory":"Food",
            "type":"Manufacturing & Wholesale Goods"
        },
        {
            "category":"Wholesale",
            "subcategory":"Dairy",
            "type":"Manufacturing & Wholesale Goods"
        }
    ],
    "sg:phone":"+1 360 458 7774",
    "sg:postcode":"98580",
    "sg:province":"WA",
    "sg:tags":[
        "processing",
        "milk",
        "bottle"
    ],
    "wof:name":"Wilcox Dairy Farms LLC",
    "wof:placetype":"venue"
},
  "geometry": {"coordinates":[-122.480943,46.890724],"type":"Point"}
}