{
  "type": "Feature",
  "properties": {
    "addr:full":"1700 E Beech St Yakima WA 98901",
    "addr:housenumber":"1700",
    "addr:postcode":"98901",
    "addr:street":"E Beech St",
    "iso:country":"US",
    "sg:address":"1700 E Beech St",
    "sg:city":"Yakima",
    "sg:classifiers":[
        {
            "category":"Recreation",
            "type":"Entertainment"
        }
    ],
    "sg:phone":"+1 509 248 6315",
    "sg:postcode":"98901",
    "sg:province":"WA",
    "wof:name":"Speed Sports Etc",
    "wof:placetype":"venue"
},
  "geometry": {"coordinates":[-120.48153000000001,46.597924],"type":"Point"}
}