{
  "type": "Feature",
  "properties": {
    "addr:full":"410 Williams Ave S Renton WA 98057",
    "addr:housenumber":"410",
    "addr:postcode":"98057",
    "addr:street":"Williams Ave S Renton",
    "iso:country":"US",
    "sg:address":"410 Williams Ave S",
    "sg:city":"Renton",
    "sg:classifiers":[
        {
            "category":"Health Services",
            "subcategory":"Health Practitioner",
            "type":"Services"
        }
    ],
    "sg:phone":"+1 425 228 3906",
    "sg:postcode":"98057",
    "sg:province":"WA",
    "sg:tags":[
        "acupuncture",
        "medicine",
        "alternative"
    ],
    "wof:name":"Southcnter Physcl Thrapy Assoc",
    "wof:placetype":"venue"
},
  "geometry": {"coordinates":[-122.20667299999999,47.477991],"type":"Point"}
}