{
  "type": "Feature",
  "properties": {
    "addr:full":"1427 20th St NW Auburn WA 98001",
    "addr:housenumber":"1427",
    "addr:postcode":"98001",
    "addr:street":"20Th St Nw",
    "iso:country":"US",
    "sg:address":"1427 20th St NW",
    "sg:city":"Auburn",
    "sg:classifiers":[
        {
            "category":"Manufacturing",
            "subcategory":"Tools & Machinery",
            "type":"Manufacturing & Wholesale Goods"
        }
    ],
    "sg:phone":"+1 253 852 6552",
    "sg:postcode":"98001",
    "sg:province":"WA",
    "sg:tags":[
        "machine",
        "shop",
        "industrial",
        "mfg"
    ],
    "wof:name":"G M S Metalworks",
    "wof:placetype":"venue"
},
  "geometry": {"coordinates":[-122.250224,47.326214],"type":"Point"}
}