{
  "type": "Feature",
  "properties": {
    "addr:full":"660 Swift Blvd Richland WA 99352",
    "addr:housenumber":"660",
    "addr:postcode":"99352",
    "addr:street":"Swift Blvd",
    "iso:country":"US",
    "sg:address":"660 Swift Blvd",
    "sg:city":"Richland",
    "sg:classifiers":[
        {
            "category":"Professional",
            "subcategory":"Lawyer & Legal Services",
            "type":"Services"
        }
    ],
    "sg:phone":"+1 509 943 4681",
    "sg:postcode":"99352",
    "sg:province":"WA",
    "sg:tags":[
        "attorney",
        "law",
        "family"
    ],
    "sg:website":"http://www.akwalaw.com",
    "wof:name":"Armstrong Klym Waite & Atwood PS",
    "wof:placetype":"venue"
},
  "geometry": {"coordinates":[-119.276212,46.280437],"type":"Point"}
}