{
  "type": "Feature",
  "properties": {
    "addr:full":"4201 202nd Ave NE Sammamish WA 98074",
    "addr:housenumber":"4201",
    "addr:postcode":"98074",
    "addr:street":"202Nd Ave Ne",
    "iso:country":"US",
    "sg:address":"4201 202nd Ave NE",
    "sg:city":"Sammamish",
    "sg:classifiers":[
        {
            "category":"Professional",
            "subcategory":"Employment Agencies",
            "type":"Services"
        }
    ],
    "sg:phone":"+1 425 830 6925",
    "sg:postcode":"98074",
    "sg:province":"WA",
    "wof:name":"Global It Recruiting",
    "wof:placetype":"venue"
},
  "geometry": {"coordinates":[-122.06943099999999,47.648863],"type":"Point"}
}