{
  "type": "Feature",
  "properties": {
    "addr:full":"3941 B St NW Auburn WA 98001",
    "addr:housenumber":"3941",
    "addr:postcode":"98001",
    "addr:street":"B St Nw",
    "iso:country":"US",
    "sg:address":"3941 B St NW",
    "sg:city":"Auburn",
    "sg:classifiers":[
        {
            "category":"Manufacturing",
            "subcategory":"Tools & Machinery",
            "type":"Manufacturing & Wholesale Goods"
        }
    ],
    "sg:phone":"+1 253 872 0305",
    "sg:postcode":"98001",
    "sg:province":"WA",
    "sg:tags":[
        "equipment",
        "industrial",
        "supply"
    ],
    "wof:name":"Application Specialties Inc",
    "wof:placetype":"venue"
},
  "geometry": {"coordinates":[-122.232373,47.340488],"type":"Point"}
}