{
  "type": "Feature",
  "properties": {
    "addr:full":"14016 NE 82nd St Vancouver WA 98682",
    "addr:housenumber":"14016",
    "addr:postcode":"98682",
    "addr:street":"Ne 82Nd St",
    "iso:country":"US",
    "sg:address":"14016 NE 82nd St",
    "sg:city":"Vancouver",
    "sg:classifiers":[
        {
            "category":"Building & Trades",
            "subcategory":"Construction",
            "type":"Services"
        }
    ],
    "sg:phone":"+1 360 944 6634",
    "sg:postcode":"98682",
    "sg:province":"WA",
    "wof:name":"Joudrey Construction",
    "wof:placetype":"venue"
},
  "geometry": {"coordinates":[-122.52881499999999,45.681945],"type":"Point"}
}