{
  "type": "Feature",
  "properties": {
    "addr:full":"13300 Lake City Way NE Seattle WA 98125",
    "addr:housenumber":"13300",
    "addr:postcode":"98125",
    "addr:street":"Lake City Way Ne",
    "iso:country":"US",
    "sg:address":"13300 Lake City Way NE",
    "sg:city":"Seattle",
    "sg:classifiers":[
        {
            "category":"Autos & Motor Vehicles",
            "subcategory":"Auto Supplies",
            "type":"Retail Goods"
        }
    ],
    "sg:phone":"+1 206 365 2273",
    "sg:postcode":"98125",
    "sg:province":"WA",
    "sg:tags":[
        "part"
    ],
    "sg:website":"www.zipweb.com/?businessname=cas...",
    "wof:name":"Casa Blanca Auto Sales",
    "wof:placetype":"venue"
},
  "geometry": {"coordinates":[-122.29199,47.724756],"type":"Point"}
}