{
  "type": "Feature",
  "properties": {
    "addr:full":"1421 Mount Baker Hwy Bellingham WA 98226",
    "addr:housenumber":"1421",
    "addr:postcode":"98226",
    "addr:street":"Mount Baker Hwy",
    "iso:country":"US",
    "sg:address":"1421 Mount Baker Hwy",
    "sg:city":"Bellingham",
    "sg:classifiers":[
        {
            "category":"Professional",
            "type":"Services"
        }
    ],
    "sg:phone":"+1 360 734 3494",
    "sg:postcode":"98226",
    "sg:province":"WA",
    "wof:name":"Wisteria Corp",
    "wof:placetype":"venue"
},
  "geometry": {"coordinates":[-122.41181899999999,48.796457],"type":"Point"}
}