{
  "type": "Feature",
  "properties": {
    "addr:full":"707 Auburn Way N Auburn WA 98002",
    "addr:housenumber":"707",
    "addr:postcode":"98002",
    "addr:street":"Auburn Way N",
    "iso:country":"US",
    "sg:address":"707 Auburn Way N",
    "sg:city":"Auburn",
    "sg:classifiers":[
        {
            "category":"Social Services",
            "type":"Services"
        },
        {
            "category":"Professional",
            "subcategory":"Employment Agencies",
            "type":"Services"
        },
        {
            "category":"Organizations",
            "subcategory":"Community Association",
            "type":"Services"
        },
        {
            "category":"Organizations",
            "subcategory":"Membership Organization",
            "type":"Services"
        }
    ],
    "sg:phone":"+1 253 939 5789",
    "sg:postcode":"98002",
    "sg:province":"WA",
    "sg:tags":[
        "workers'",
        "military",
        "veteran",
        "placement",
        "volunteer"
    ],
    "sg:website":"http://www.legion.org",
    "wof:name":"American Legion",
    "wof:placetype":"venue"
},
  "geometry": {"coordinates":[-122.22545599999999,47.313105],"type":"Point"}
}