{
  "type": "Feature",
  "properties": {
    "addr:full":"968 Lloyd Rd Manson WA 98831",
    "addr:housenumber":"968",
    "addr:postcode":"98831",
    "addr:street":"Lloyd Rd",
    "iso:country":"US",
    "sg:address":"968 Lloyd Rd",
    "sg:city":"Manson",
    "sg:classifiers":[
        {
            "category":"Building & Trades",
            "subcategory":"Construction",
            "type":"Services"
        }
    ],
    "sg:phone":"+1 509 697 5033",
    "sg:postcode":"98831",
    "sg:province":"WA",
    "sg:tags":[
        "wallcoverings-installation",
        "wallpaper",
        "painting",
        "contractor"
    ],
    "wof:name":"Cathead",
    "wof:placetype":"venue"
},
  "geometry": {"coordinates":[-120.138609,47.889183],"type":"Point"}
}