{
  "type": "Feature",
  "properties": {
    "addr:full":"1206 S C St Port Angeles WA 98363",
    "addr:housenumber":"1206",
    "addr:postcode":"98363",
    "addr:street":"S C St",
    "iso:country":"US",
    "sg:address":"1206 S C St",
    "sg:city":"Port Angeles",
    "sg:classifiers":[
        {
            "category":"Building & Trades",
            "subcategory":"Electrical",
            "type":"Services"
        }
    ],
    "sg:phone":"+1 360 452 9104",
    "sg:postcode":"98363",
    "sg:province":"WA",
    "sg:tags":[
        "electric",
        "contractor"
    ],
    "wof:name":"Straits Electric",
    "wof:placetype":"venue"
},
  "geometry": {"coordinates":[-123.460249,48.116805],"type":"Point"}
}