{
  "type": "Feature",
  "properties": {
    "iso:country":"US",
    "sg:address":"525 W Casino Rd",
    "sg:city":"Everett",
    "sg:classifiers":[
        {
            "category":"Organizations",
            "subcategory":"Community Association",
            "type":"Services"
        }
    ],
    "sg:phone":"+1 425 355 6899",
    "sg:postcode":"98204",
    "sg:province":"WA",
    "wof:name":"Casino Road Boys & Girls Club",
    "wof:placetype":"venue"
},
  "geometry": {"coordinates":[-122.240719,47.92192],"type":"Point"}
}