{
  "type": "Feature",
  "properties": {
    "iso:country":"US",
    "sg:address":"177 S Division St",
    "sg:city":"Spokane",
    "sg:classifiers":[
        {
            "category":"Food & Beverages",
            "subcategory":"Groceries & Convenience Stores",
            "type":"Retail Goods"
        }
    ],
    "sg:phone":"+1 509 838 5505",
    "sg:postcode":"99202",
    "sg:province":"WA",
    "wof:name":"7-Eleven",
    "wof:placetype":"venue"
},
  "geometry": {"coordinates":[-117.411231,47.654557],"type":"Point"}
}