{
  "type": "Feature",
  "properties": {
    "addr:full":"2007 Cornell Ave Yakima WA 98903",
    "addr:housenumber":"2007",
    "addr:postcode":"98903",
    "addr:street":"Cornell Ave",
    "iso:country":"US",
    "sg:address":"2007 Cornell Ave",
    "sg:city":"Yakima",
    "sg:classifiers":[
        {
            "category":"Place Of Worship",
            "subcategory":"Church",
            "type":"Public Place"
        },
        {
            "category":"Place Of Worship",
            "type":"Public Place"
        },
        {
            "category":"Organizations",
            "subcategory":"Religious Organization",
            "type":"Services"
        }
    ],
    "sg:phone":"+1 509 452 1764",
    "sg:postcode":"98903",
    "sg:province":"WA",
    "sg:tags":[
        "churches-pentecostal-independent",
        "churches-pentecostal"
    ],
    "wof:name":"New Hope Chapel",
    "wof:placetype":"venue"
},
  "geometry": {"coordinates":[-120.514805,46.567966],"type":"Point"}
}