{
  "type": "Feature",
  "properties": {
    "addr:full":"5016 NE St Johns Rd Vancouver WA 98661",
    "addr:housenumber":"5016",
    "addr:postcode":"98661",
    "addr:street":"Ne St Johns Rd",
    "iso:country":"US",
    "sg:address":"5016 NE St Johns Rd",
    "sg:city":"Vancouver",
    "sg:classifiers":[
        {
            "category":"Building & Trades",
            "subcategory":"Construction",
            "type":"Services"
        }
    ],
    "sg:phone":"+1 360 993 7747",
    "sg:postcode":"98661",
    "sg:province":"WA",
    "sg:tags":[
        "contractor"
    ],
    "sg:website":"http://www.rncconstruction.com",
    "wof:name":"Rnc Construction",
    "wof:placetype":"venue"
},
  "geometry": {"coordinates":[-122.636009,45.658106],"type":"Point"}
}