{
  "type": "Feature",
  "properties": {
    "addr:full":"263 Russell Rd Winlock WA 98596",
    "addr:housenumber":"263",
    "addr:postcode":"98596",
    "addr:street":"Russell Rd",
    "iso:country":"US",
    "sg:address":"263 Russell Rd",
    "sg:city":"Winlock",
    "sg:classifiers":[
        {
            "category":"Farming",
            "subcategory":"Livestock Farm",
            "type":"Manufacturing & Wholesale Goods"
        }
    ],
    "sg:phone":"+1 360 785 3803",
    "sg:postcode":"98596",
    "sg:province":"WA",
    "sg:tags":[
        "beef",
        "feedlot",
        "cattle"
    ],
    "wof:name":"Charlotte Fossett",
    "wof:placetype":"venue"
},
  "geometry": {"coordinates":[-122.959925,46.483066],"type":"Point"}
}