{
  "type": "Feature",
  "properties": {
    "addr:full":"512 E Birch St Waterville WA 98858",
    "addr:housenumber":"512",
    "addr:postcode":"98858",
    "addr:street":"E Birch St",
    "iso:country":"US",
    "sg:address":"512 E Birch St",
    "sg:city":"Waterville",
    "sg:classifiers":[
        {
            "category":"Farming",
            "subcategory":"Farm",
            "type":"Manufacturing & Wholesale Goods"
        }
    ],
    "sg:phone":"+1 509 745 8255",
    "sg:postcode":"98858",
    "sg:province":"WA",
    "wof:name":"Gormley Farms",
    "wof:placetype":"venue"
},
  "geometry": {"coordinates":[-120.065941,47.645478],"type":"Point"}
}