{
  "type": "Feature",
  "properties": {
    "addr:full":"3905 Factoria Sq Mall SE Bellevue WA 98006",
    "addr:housenumber":"3905",
    "addr:postcode":"98006",
    "addr:street":"Factoria Sq Mall Se",
    "iso:country":"US",
    "sg:address":"3905 Factoria Sq Mall SE",
    "sg:city":"Bellevue",
    "sg:classifiers":[
        {
            "category":"Retail",
            "subcategory":"Portrait Studio",
            "type":"Services"
        },
        {
            "category":"Shopping",
            "subcategory":"Pharmacy",
            "type":"Retail Goods"
        }
    ],
    "sg:phone":"+1 425 644 2925",
    "sg:postcode":"98006",
    "sg:province":"WA",
    "sg:tags":[
        "photography",
        "drugstore",
        "store"
    ],
    "wof:name":"Rite Aid",
    "wof:placetype":"venue"
},
  "geometry": {"coordinates":[-122.171997,47.574699],"type":"Point"}
}