{
  "type": "Feature",
  "properties": {
    "addr:full":"14707 Bothell Way NE Shoreline WA 98155",
    "addr:housenumber":"14707",
    "addr:postcode":"98155",
    "addr:street":"Bothell Way Ne",
    "iso:country":"US",
    "sg:address":"14707 Bothell Way NE",
    "sg:city":"Shoreline",
    "sg:phone":"+1 206 367 5562",
    "sg:postcode":"98155",
    "sg:province":"WA",
    "wof:name":"Flo-Anna's Diner",
    "wof:placetype":"venue"
},
  "geometry": {"coordinates":[-122.29242499999999,47.735549],"type":"Point"}
}