{
  "type": "Feature",
  "properties": {
    "iso:country":"US",
    "sg:address":"2411 R Ave",
    "sg:city":"Anacortes",
    "sg:classifiers":[
        {
            "category":"Building & Trades",
            "subcategory":"Construction",
            "type":"Services"
        }
    ],
    "sg:phone":"+1 360 299 0802",
    "sg:postcode":"98221",
    "sg:province":"WA",
    "sg:tags":[
        "industrial"
    ],
    "wof:name":"Timec",
    "wof:placetype":"venue"
},
  "geometry": {"coordinates":[-122.609461,48.502791],"type":"Point"}
}