{
  "type": "Feature",
  "properties": {
    "addr:full":"1730 1st Ave S Seattle WA 98134",
    "addr:housenumber":"1730",
    "addr:postcode":"98134",
    "addr:street":"1St Ave S",
    "iso:country":"US",
    "sg:address":"1730 1st Ave S",
    "sg:city":"Seattle",
    "sg:classifiers":[
        {
            "category":"Wholesale",
            "subcategory":"Electrical",
            "type":"Manufacturing & Wholesale Goods"
        }
    ],
    "sg:phone":"+1 206 622 8401",
    "sg:postcode":"98134",
    "sg:province":"WA",
    "sg:tags":[
        "refrigerator",
        "freezer"
    ],
    "wof:name":"Arctic Commercial Refrig Inc",
    "wof:placetype":"venue"
},
  "geometry": {"coordinates":[-122.334124,47.586424],"type":"Point"}
}