{
  "type": "Feature",
  "properties": {
    "iso:country":"US",
    "sg:address":"500 S Myrtle St",
    "sg:city":"Seattle",
    "sg:classifiers":[
        {
            "category":"Manufacturing",
            "subcategory":"Metals",
            "type":"Manufacturing & Wholesale Goods"
        }
    ],
    "sg:phone":"+1 206 762 0737",
    "sg:postcode":"98108",
    "sg:province":"WA",
    "sg:tags":[
        "boiler",
        "mfg"
    ],
    "wof:name":"Seattle Boiler Works Inc",
    "wof:placetype":"venue"
},
  "geometry": {"coordinates":[-122.325643,47.539407],"type":"Point"}
}