{
  "type": "Feature",
  "properties": {
    "addr:full":"5939 Artist Dr Ferndale WA 98248",
    "addr:postcode":"5939;98248",
    "addr:street":"Artist Dr",
    "iso:country":"US",
    "sg:address":"5939 Artist Dr",
    "sg:city":"Ferndale",
    "sg:classifiers":[
        {
            "category":"Professional",
            "type":"Services"
        }
    ],
    "sg:phone":"+1 360 384 4299",
    "sg:postcode":"98248",
    "sg:province":"WA",
    "wof:name":"Sheahan M Griffitts",
    "wof:placetype":"venue"
},
  "geometry": {"coordinates":[-122.603593,48.857452],"type":"Point"}
}