{
  "type": "Feature",
  "properties": {
    "addr:full":"4000 Country Ln NW Bremerton WA 98312",
    "addr:housenumber":"4000",
    "addr:postcode":"98312",
    "addr:street":"Country Ln Nw",
    "iso:country":"US",
    "sg:address":"4000 Country Ln NW",
    "sg:city":"Bremerton",
    "sg:classifiers":[
        {
            "category":"Building & Trades",
            "subcategory":"Plumbing",
            "type":"Services"
        }
    ],
    "sg:phone":"+1 360 373 2100",
    "sg:postcode":"98312",
    "sg:province":"WA",
    "sg:tags":[
        "mechanical",
        "contractor"
    ],
    "wof:name":"Kelly Company",
    "wof:placetype":"venue"
},
  "geometry": {"coordinates":[-122.70594,47.588772],"type":"Point"}
}