{
  "type": "Feature",
  "properties": {
    "addr:full":"5605 Old Gardiner Rd Port Townsend WA 98368",
    "addr:housenumber":"5605",
    "addr:postcode":"98368",
    "addr:street":"Old Gardiner Rd",
    "iso:country":"US",
    "sg:address":"5605 Old Gardiner Rd",
    "sg:city":"Port Townsend",
    "sg:classifiers":[
        {
            "category":"Restaurant",
            "type":"Food & Drink"
        }
    ],
    "sg:phone":"+1 360 385 3840",
    "sg:postcode":"98368",
    "sg:province":"WA",
    "sg:tags":[
        "eating"
    ],
    "wof:name":"Bay House",
    "wof:placetype":"venue"
},
  "geometry": {"coordinates":[-122.87131100000001,48.002679],"type":"Point"}
}