{
  "type": "Feature",
  "properties": {
    "iso:country":"US",
    "sg:address":"1801 W Valley Hwy N",
    "sg:city":"Auburn",
    "sg:classifiers":[
        {
            "category":"Wholesale",
            "subcategory":"Medical Equipment & Supplies",
            "type":"Manufacturing & Wholesale Goods"
        }
    ],
    "sg:phone":"+1 253 833 7070",
    "sg:postcode":"98001",
    "sg:province":"WA",
    "sg:tags":[
        "dental"
    ],
    "wof:name":"Sullivan Schein Dental",
    "wof:placetype":"venue"
},
  "geometry": {"coordinates":[-122.249906,47.323608],"type":"Point"}
}