{
  "type": "Feature",
  "properties": {
    "addr:full":"4517 NE 54th St Seattle WA 98105",
    "addr:housenumber":"4517",
    "addr:postcode":"98105",
    "addr:street":"Ne 54Th St",
    "iso:country":"US",
    "sg:address":"4517 NE 54th St",
    "sg:city":"Seattle",
    "sg:classifiers":[
        {
            "category":"Professional",
            "subcategory":"Management & Consulting",
            "type":"Services"
        }
    ],
    "sg:phone":"+1 206 528 7557",
    "sg:postcode":"98105",
    "sg:province":"WA",
    "wof:name":"Ldp Consulting",
    "wof:placetype":"venue"
},
  "geometry": {"coordinates":[-122.278519,47.667685],"type":"Point"}
}