{
  "type": "Feature",
  "properties": {
    "addr:full":"10 Cove Ave S Apt 37 Wenatchee WA 98801",
    "addr:housenumber":"10;37",
    "addr:postcode":"98801",
    "addr:street":"Cove Ave S Apt",
    "iso:country":"US",
    "sg:address":"10 Cove Ave S Apt 37",
    "sg:city":"Wenatchee",
    "sg:classifiers":[
        {
            "category":"Professional",
            "subcategory":"Printing & Photocopies",
            "type":"Services"
        }
    ],
    "sg:phone":"+1 509 393 8286",
    "sg:postcode":"98801",
    "sg:province":"WA",
    "sg:tags":[
        "photographers-commercial"
    ],
    "wof:name":"Reminiscent Images",
    "wof:placetype":"venue"
},
  "geometry": {"coordinates":[-120.33269199999999,47.422598],"type":"Point"}
}