{
  "type": "Feature",
  "properties": {
    "addr:full":"1950 Alaskan Way Ofc Seattle WA 98101",
    "addr:housenumber":"1950",
    "addr:postcode":"98101",
    "addr:street":"Alaskan Way",
    "iso:country":"US",
    "sg:address":"1950 Alaskan Way Ofc",
    "sg:city":"Seattle",
    "sg:classifiers":[
        {
            "category":"Social Services",
            "subcategory":"Child Care",
            "type":"Services"
        }
    ],
    "sg:phone":"+1 206 441 3357",
    "sg:postcode":"98101",
    "sg:province":"WA",
    "sg:tags":[
        "nursery",
        "day"
    ],
    "wof:name":"Dcc Tycoons Inc",
    "wof:placetype":"venue"
},
  "geometry": {"coordinates":[-122.345108,47.609291],"type":"Point"}
}