{
  "type": "Feature",
  "properties": {
    "addr:full":"8657 9th Ave SW Seattle WA 98106",
    "addr:housenumber":"8657",
    "addr:postcode":"98106",
    "addr:street":"9Th Ave Sw",
    "iso:country":"US",
    "sg:address":"8657 9th Ave SW",
    "sg:city":"Seattle",
    "sg:classifiers":[
        {
            "category":"Personal",
            "subcategory":"Beauty Salon",
            "type":"Services"
        }
    ],
    "sg:phone":"+1 206 763 7876",
    "sg:postcode":"98106",
    "sg:province":"WA",
    "sg:tags":[
        "hair"
    ],
    "wof:name":"Royal Cuts",
    "wof:placetype":"venue"
},
  "geometry": {"coordinates":[-122.34681500000001,47.525158],"type":"Point"}
}