{
  "type": "Feature",
  "properties": {
    "addr:full":"908 Monroe Ave Toppenish WA 98948",
    "addr:housenumber":"908",
    "addr:postcode":"98948",
    "addr:street":"Monroe Ave",
    "iso:country":"US",
    "sg:address":"908 Monroe Ave",
    "sg:city":"Toppenish",
    "sg:classifiers":[
        {
            "category":"Social Services",
            "subcategory":"Child Care",
            "type":"Services"
        }
    ],
    "sg:phone":"+1 509 865 2219",
    "sg:postcode":"98948",
    "sg:province":"WA",
    "sg:tags":[
        "nursery",
        "day"
    ],
    "wof:name":"Belans Child Development Ctr",
    "wof:placetype":"venue"
},
  "geometry": {"coordinates":[-120.323886,46.3798],"type":"Point"}
}