{
  "type": "Feature",
  "properties": {
    "iso:country":"US",
    "sg:address":"102 E 1st St",
    "sg:city":"Cle Elum",
    "sg:classifiers":[
        {
            "category":"Building & Trades",
            "subcategory":"Equipment Rental",
            "type":"Services"
        }
    ],
    "sg:phone":"+1 509 674 2202",
    "sg:postcode":"98922",
    "sg:province":"WA",
    "wof:name":"Rentals In Dearmins Equipment",
    "wof:placetype":"venue"
},
  "geometry": {"coordinates":[-120.936503,47.194562],"type":"Point"}
}