{
  "type": "Feature",
  "properties": {
    "addr:full":"8904 S Tacoma Way Ste 2 Lakewood WA 98499",
    "addr:housenumber":"8904",
    "addr:postcode":"98499",
    "addr:street":"S Tacoma Way Ste 2",
    "iso:country":"US",
    "sg:address":"8904 S Tacoma Way Ste 2",
    "sg:city":"Lakewood",
    "sg:classifiers":[
        {
            "category":"Banks & Credit Unions",
            "subcategory":"Financial Services",
            "type":"Services"
        }
    ],
    "sg:phone":"+1 253 984 6669",
    "sg:postcode":"98499",
    "sg:province":"WA",
    "sg:tags":[
        "cashing",
        "loan",
        "check"
    ],
    "sg:website":"www.moneytreeinc.com",
    "wof:name":"Moneytree",
    "wof:placetype":"venue"
},
  "geometry": {"coordinates":[-122.484504,47.176186],"type":"Point"}
}