{
  "type": "Feature",
  "properties": {
    "addr:full":"2020 Terry Ave Seattle WA 98121",
    "addr:housenumber":"2020",
    "addr:postcode":"98121",
    "addr:street":"Terry Ave",
    "iso:country":"US",
    "sg:address":"2020 Terry Ave",
    "sg:city":"Seattle",
    "sg:classifiers":[
        {
            "category":"Restaurant",
            "type":"Food & Drink"
        }
    ],
    "sg:phone":"+1 206 328 0404",
    "sg:postcode":"98121",
    "sg:province":"WA",
    "sg:tags":[
        "eating"
    ],
    "wof:name":"Coffee Selam",
    "wof:placetype":"venue"
},
  "geometry": {"coordinates":[-122.33595099999999,47.617716],"type":"Point"}
}