{
  "type": "Feature",
  "properties": {
    "addr:full":"1526 Dickinson Ave Shelton WA 98584",
    "addr:housenumber":"1526",
    "addr:postcode":"98584",
    "addr:street":"Dickinson Ave",
    "iso:country":"US",
    "sg:address":"1526 Dickinson Ave",
    "sg:city":"Shelton",
    "sg:classifiers":[
        {
            "category":"Food & Beverages",
            "subcategory":"Groceries & Convenience Stores",
            "type":"Retail Goods"
        }
    ],
    "sg:phone":"+1 360 427 1776",
    "sg:postcode":"98584",
    "sg:province":"WA",
    "wof:name":"Inland Market",
    "wof:placetype":"venue"
},
  "geometry": {"coordinates":[-123.080634,47.200834],"type":"Point"}
}