{
  "type": "Feature",
  "properties": {
    "addr:full":"705 S Naches Ave Wapato WA 98951",
    "addr:housenumber":"705",
    "addr:postcode":"98951",
    "addr:street":"S Naches Ave",
    "iso:country":"US",
    "sg:address":"705 S Naches Ave",
    "sg:city":"Wapato",
    "sg:classifiers":[
        {
            "category":"Farming",
            "subcategory":"Farm & Veterinary Services",
            "type":"Manufacturing & Wholesale Goods"
        }
    ],
    "sg:phone":"+1 509 877 3232",
    "sg:postcode":"98951",
    "sg:province":"WA",
    "sg:tags":[
        "crop"
    ],
    "wof:name":"Lujano Jose & Son Grafting Svc",
    "wof:placetype":"venue"
},
  "geometry": {"coordinates":[-120.425122,46.442314],"type":"Point"}
}