{
  "type": "Feature",
  "properties": {
    "addr:full":"1002 Oakhurst Dr Elma WA 98541",
    "addr:housenumber":"1002",
    "addr:postcode":"98541",
    "addr:street":"Oakhurst Dr",
    "iso:country":"US",
    "sg:address":"1002 Oakhurst Dr",
    "sg:city":"Elma",
    "sg:classifiers":[
        {
            "category":"Freight",
            "type":"Transportation"
        }
    ],
    "sg:phone":"+1 360 482 2432",
    "sg:postcode":"98541",
    "sg:province":"WA",
    "sg:tags":[
        "commercial",
        "storage"
    ],
    "wof:name":"Elma Mini Storage",
    "wof:placetype":"venue"
},
  "geometry": {"coordinates":[-123.390073,47.00904],"type":"Point"}
}