{
  "type": "Feature",
  "properties": {
    "addr:full":"16716 Highway 99 Suite C Lynnwood WA 98037",
    "addr:housenumber":"16716",
    "addr:postcode":"98037",
    "addr:street":"Highway 99 Suite C",
    "iso:country":"US",
    "sg:address":"16716 Highway 99 Suite C",
    "sg:city":"Lynnwood",
    "sg:phone":"+1 425 787 0646",
    "sg:postcode":"98037",
    "sg:province":"WA",
    "sg:website":"http://hstrial-lcorona3.homestead.com",
    "wof:name":"Casa Corona",
    "wof:placetype":"venue"
},
  "geometry": {"coordinates":[-122.294495,47.847234],"type":"Point"}
}