{
  "type": "Feature",
  "properties": {
    "addr:full":"108 W 1st Ave Ritzville WA 99169",
    "addr:housenumber":"108",
    "addr:postcode":"99169",
    "addr:street":"W 1St Ave",
    "iso:country":"US",
    "sg:address":"108 W 1st Ave",
    "sg:city":"Ritzville",
    "sg:classifiers":[
        {
            "category":"Wholesale",
            "subcategory":"Painting Supplies",
            "type":"Manufacturing & Wholesale Goods"
        },
        {
            "category":"Home & Garden",
            "subcategory":"Garden Supply",
            "type":"Retail Goods"
        },
        {
            "category":"Wholesale",
            "subcategory":"Construction Materials",
            "type":"Manufacturing & Wholesale Goods"
        },
        {
            "category":"Home & Garden",
            "subcategory":"Hardware",
            "type":"Retail Goods"
        }
    ],
    "sg:phone":"+1 509 659 0381",
    "sg:postcode":"99169",
    "sg:province":"WA",
    "sg:tags":[
        "lawn",
        "paint",
        "equipment",
        "part",
        "plumbing",
        "fixtures",
        "store"
    ],
    "sg:website":"http://www.truevalue.com",
    "wof:name":"True Value Hardware",
    "wof:placetype":"venue"
},
  "geometry": {"coordinates":[-118.37785700000001,47.126237],"type":"Point"}
}