{
  "type": "Feature",
  "properties": {
    "addr:full":"3058 31st Ave W Seattle WA 98199",
    "addr:housenumber":"3058",
    "addr:postcode":"98199",
    "addr:street":"31St Ave W",
    "iso:country":"US",
    "sg:address":"3058 31st Ave W",
    "sg:city":"Seattle",
    "sg:classifiers":[
        {
            "category":"Education",
            "subcategory":"Music School",
            "type":"Public Place"
        }
    ],
    "sg:phone":"+1 206 612 9555",
    "sg:postcode":"98199",
    "sg:province":"WA",
    "sg:tags":[
        "instrument",
        "teacher",
        "musical"
    ],
    "sg:website":"magnoliamusicschool.com",
    "wof:name":"Magnolia School of Music",
    "wof:placetype":"venue"
},
  "geometry": {"coordinates":[-122.396638,47.648556],"type":"Point"}
}