{
  "type": "Feature",
  "properties": {
    "iso:country":"US",
    "sg:address":"10411 N Nevada St",
    "sg:city":"Spokane",
    "sg:classifiers":[
        {
            "category":"Professional",
            "type":"Services"
        }
    ],
    "sg:phone":"+1 509 466 5548",
    "sg:postcode":"99218",
    "sg:province":"WA",
    "wof:name":"Nsc-Hico Villa",
    "wof:placetype":"venue"
},
  "geometry": {"coordinates":[-117.395252,47.75132],"type":"Point"}
}