{
  "type": "Feature",
  "properties": {
    "iso:country":"US",
    "sg:address":"4802 111th Ave NE",
    "sg:city":"Kirkland",
    "sg:classifiers":[
        {
            "category":"Wholesale",
            "subcategory":"Furniture",
            "type":"Manufacturing & Wholesale Goods"
        }
    ],
    "sg:phone":"+1 425 822 4495",
    "sg:postcode":"98033",
    "sg:province":"WA",
    "wof:name":"Rogers Sales",
    "wof:placetype":"venue"
},
  "geometry": {"coordinates":[-122.19306899999999,47.653304],"type":"Point"}
}