{
  "type": "Feature",
  "properties": {
    "iso:country":"US",
    "sg:address":"3840 Airport Way",
    "sg:city":"East Wenatchee",
    "sg:classifiers":[
        {
            "category":"Professional",
            "type":"Services"
        }
    ],
    "sg:phone":"+1 509 665 3530",
    "sg:postcode":"98802",
    "sg:province":"WA",
    "wof:name":"US Forrest Service",
    "wof:placetype":"venue"
},
  "geometry": {"coordinates":[-120.209838,47.40573],"type":"Point"}
}