{
  "type": "Feature",
  "properties": {
    "addr:full":"4000 SW 104th St Seattle WA 98146",
    "addr:housenumber":"4000",
    "addr:postcode":"98146",
    "addr:street":"Sw 104Th St",
    "iso:country":"US",
    "sg:address":"4000 SW 104th St",
    "sg:city":"Seattle",
    "sg:classifiers":[
        {
            "category":"Shopping",
            "type":"Retail Goods"
        }
    ],
    "sg:phone":"+1 206 988 1719",
    "sg:postcode":"98146",
    "sg:province":"WA",
    "sg:website":"www.bodysenseinc.com",
    "wof:name":"BodySense",
    "wof:placetype":"venue"
},
  "geometry": {"coordinates":[-122.38339499999999,47.510262],"type":"Point"}
}