{
  "type": "Feature",
  "properties": {
    "addr:full":"3600 Fremont Ln N Seattle WA 98103",
    "addr:housenumber":"3600",
    "addr:postcode":"98103",
    "addr:street":"Fremont Ln N",
    "iso:country":"US",
    "sg:address":"3600 Fremont Ln N",
    "sg:city":"Seattle",
    "sg:classifiers":[
        {
            "category":"Building & Trades",
            "subcategory":"Construction",
            "type":"Services"
        }
    ],
    "sg:phone":"+1 206 633 5774",
    "sg:postcode":"98103",
    "sg:province":"WA",
    "sg:tags":[
        "general",
        "contractor"
    ],
    "wof:name":"Constructors Pamco",
    "wof:placetype":"venue"
},
  "geometry": {"coordinates":[-122.349253,47.652727],"type":"Point"}
}