{
  "type": "Feature",
  "properties": {
    "addr:full":"10424 Upper Preston Rd SE Issaquah WA 98027",
    "addr:housenumber":"10424",
    "addr:postcode":"98027",
    "addr:street":"Upper Preston Rd Se",
    "iso:country":"US",
    "sg:address":"10424 Upper Preston Rd SE",
    "sg:city":"Issaquah",
    "sg:classifiers":[
        {
            "category":"Personal",
            "type":"Services"
        }
    ],
    "sg:phone":"+1 206 669 0306",
    "sg:postcode":"98027",
    "sg:province":"WA",
    "wof:name":"NVF Enterprises",
    "wof:placetype":"venue"
},
  "geometry": {"coordinates":[-121.90946,47.507684],"type":"Point"}
}