{
  "type": "Feature",
  "properties": {
    "addr:full":"8404 27th St W University Place WA 98466",
    "addr:housenumber":"8404",
    "addr:postcode":"98466",
    "addr:street":"27Th St W;Place",
    "iso:country":"US",
    "sg:address":"8404 27th St W",
    "sg:city":"University Place",
    "sg:classifiers":[
        {
            "category":"Recreation",
            "type":"Entertainment"
        }
    ],
    "sg:phone":"+1 253 851 2355",
    "sg:postcode":"98466",
    "sg:province":"WA",
    "sg:tags":[
        "psychic",
        "medium"
    ],
    "wof:name":"Creative Clairvoyance & Healin",
    "wof:placetype":"venue"
},
  "geometry": {"coordinates":[-122.54849,47.235149],"type":"Point"}
}