{
  "type": "Feature",
  "properties": {
    "addr:full":"1710 Kentucky St Bellingham WA 98229",
    "addr:housenumber":"1710",
    "addr:postcode":"98229",
    "addr:street":"Kentucky St",
    "iso:country":"US",
    "sg:address":"1710 Kentucky St",
    "sg:city":"Bellingham",
    "sg:classifiers":[
        {
            "category":"Real Estate",
            "subcategory":"Real Estate Services",
            "type":"Services"
        },
        {
            "category":"Building & Trades",
            "subcategory":"Cleaning & Sanitation",
            "type":"Services"
        }
    ],
    "sg:phone":"+1 360 676 1880",
    "sg:postcode":"98229",
    "sg:province":"WA",
    "sg:tags":[
        "maintenance",
        "cleaners-interior"
    ],
    "wof:name":"Mountain Bay Maintenance Inc",
    "wof:placetype":"venue"
},
  "geometry": {"coordinates":[-122.45062900000001,48.75774],"type":"Point"}
}