{
  "type": "Feature",
  "properties": {
    "addr:full":"3519 NW 372nd St La Center WA 98629",
    "addr:housenumber":"3519",
    "addr:postcode":"98629",
    "addr:street":"Nw 372Nd St",
    "iso:country":"US",
    "sg:address":"3519 NW 372nd St",
    "sg:city":"La Center",
    "sg:classifiers":[
        {
            "category":"Farming",
            "subcategory":"Farm",
            "type":"Manufacturing & Wholesale Goods"
        }
    ],
    "sg:phone":"+1 360 263 4216",
    "sg:postcode":"98629",
    "sg:province":"WA",
    "sg:tags":[
        "food",
        "covered",
        "crop"
    ],
    "wof:name":"Paulas Magical Mushrooms LLC",
    "wof:placetype":"venue"
},
  "geometry": {"coordinates":[-122.708427,45.890002],"type":"Point"}
}