{
  "type": "Feature",
  "properties": {
    "addr:full":"2526 118th Dr NE Lake Stevens WA 98258",
    "addr:housenumber":"2526",
    "addr:postcode":"98258",
    "addr:street":"118Th Dr Ne",
    "iso:country":"US",
    "sg:address":"2526 118th Dr NE",
    "sg:city":"Lake Stevens",
    "sg:classifiers":[
        {
            "category":"Banks & Credit Unions",
            "subcategory":"Bank",
            "type":"Services"
        }
    ],
    "sg:phone":"+1 425 334 6655",
    "sg:postcode":"98258",
    "sg:province":"WA",
    "sg:tags":[
        "mortgage"
    ],
    "wof:name":"Ponderosa Mortgage Co",
    "wof:placetype":"venue"
},
  "geometry": {"coordinates":[-122.071302,48.02043],"type":"Point"}
}