{
  "type": "Feature",
  "properties": {
    "addr:full":"1933 NW 95th St Seattle WA 98117",
    "addr:housenumber":"1933",
    "addr:postcode":"98117",
    "addr:street":"Nw 95Th St",
    "iso:country":"US",
    "sg:address":"1933 NW 95th St",
    "sg:city":"Seattle",
    "sg:classifiers":[
        {
            "category":"Real Estate",
            "subcategory":"Real Estate Agent",
            "type":"Services"
        }
    ],
    "sg:phone":"+1 206 789 2054",
    "sg:postcode":"98117",
    "sg:province":"WA",
    "wof:name":"Crystal 523 LLC",
    "wof:placetype":"venue"
},
  "geometry": {"coordinates":[-122.38279799999999,47.698165],"type":"Point"}
}