{
  "type": "Feature",
  "properties": {
    "addr:full":"6022 Margo Pl SE Olympia WA 98501",
    "addr:housenumber":"6022",
    "addr:postcode":"98501",
    "addr:street":"Margo Pl Se",
    "iso:country":"US",
    "sg:address":"6022 Margo Pl SE",
    "sg:city":"Olympia",
    "sg:classifiers":[
        {
            "category":"Education",
            "subcategory":"Special Training",
            "type":"Public Place"
        }
    ],
    "sg:phone":"+1 360 943 2851",
    "sg:postcode":"98501",
    "sg:province":"WA",
    "wof:name":"Schuster Kathleen E - Pia",
    "wof:placetype":"venue"
},
  "geometry": {"coordinates":[-122.905613,46.995007],"type":"Point"}
}