{
  "type": "Feature",
  "properties": {
    "addr:full":"582 Gold Creek Loop Rd Colville WA 99114",
    "addr:housenumber":"582",
    "addr:postcode":"99114",
    "addr:street":"Gold Creek Loop Rd",
    "iso:country":"US",
    "sg:address":"582 Gold Creek Loop Rd",
    "sg:city":"Colville",
    "sg:classifiers":[
        {
            "category":"Wholesale",
            "subcategory":"Machinery & Supplies",
            "type":"Manufacturing & Wholesale Goods"
        }
    ],
    "sg:phone":"+1 509 684 4031",
    "sg:postcode":"99114",
    "sg:province":"WA",
    "sg:tags":[
        "instrument",
        "surveying"
    ],
    "wof:name":"Van Horn & Watson",
    "wof:placetype":"venue"
},
  "geometry": {"coordinates":[-117.96697399999999,48.566494],"type":"Point"}
}