{
  "type": "Feature",
  "properties": {
    "addr:full":"20823 Kaster Rd NW Poulsbo WA 98370",
    "addr:postcode":"20823;98370",
    "addr:street":"Kaster Rd Nw",
    "iso:country":"US",
    "sg:address":"20823 Kaster Rd NW",
    "sg:city":"Poulsbo",
    "sg:classifiers":[
        {
            "category":"Building & Trades",
            "subcategory":"Cleaning & Sanitation",
            "type":"Services"
        }
    ],
    "sg:phone":"+1 206 842 9499",
    "sg:postcode":"98370",
    "sg:province":"WA",
    "sg:tags":[
        "fireplace",
        "chimney"
    ],
    "wof:name":"Phyrebird Chimney Svc",
    "wof:placetype":"venue"
},
  "geometry": {"coordinates":[-122.66807300000001,47.754033],"type":"Point"}
}