{
  "type": "Feature",
  "properties": {
    "iso:country":"US",
    "sg:address":"5010 S Inglewood Dr",
    "sg:city":"Langley",
    "sg:classifiers":[
        {
            "category":"Travel",
            "subcategory":"Hotels & Motels",
            "type":"Entertainment"
        }
    ],
    "sg:phone":"+1 360 221 8641",
    "sg:postcode":"98260",
    "sg:province":"WA",
    "sg:tags":[
        "operation"
    ],
    "wof:name":"Inglewood Haven",
    "wof:placetype":"venue"
},
  "geometry": {"coordinates":[-122.426885,48.024105],"type":"Point"}
}