{
  "type": "Feature",
  "properties": {
    "addr:full":"7905 Steilacoom Blvd SW Lakewood WA 98498",
    "addr:housenumber":"7905",
    "addr:postcode":"98498",
    "addr:street":"Steilacoom Blvd Sw",
    "iso:country":"US",
    "sg:address":"7905 Steilacoom Blvd SW",
    "sg:city":"Lakewood",
    "sg:classifiers":[
        {
            "category":"Health Services",
            "subcategory":"Clinic",
            "type":"Services"
        }
    ],
    "sg:phone":"+1 253 884 0123",
    "sg:postcode":"98498",
    "sg:province":"WA",
    "sg:tags":[
        "home"
    ],
    "sg:website":"www.goodtobehomecare.com",
    "wof:name":"Good To Be Home Care",
    "wof:placetype":"venue"
},
  "geometry": {"coordinates":[-122.538489,47.17827],"type":"Point"}
}