{
  "type": "Feature",
  "properties": {
    "addr:full":"504 Hillside Dr Yakima WA 98903",
    "addr:housenumber":"504",
    "addr:postcode":"98903",
    "addr:street":"Hillside Dr",
    "iso:country":"US",
    "sg:address":"504 Hillside Dr",
    "sg:city":"Yakima",
    "sg:classifiers":[
        {
            "category":"Building & Trades",
            "subcategory":"Construction",
            "type":"Services"
        }
    ],
    "sg:phone":"+1 509 248 3413",
    "sg:postcode":"98903",
    "sg:province":"WA",
    "sg:tags":[
        "siding",
        "contractor"
    ],
    "wof:name":"Easy Sider & Window Company",
    "wof:placetype":"venue"
},
  "geometry": {"coordinates":[-120.51455,46.541122],"type":"Point"}
}