{
  "type": "Feature",
  "properties": {
    "addr:full":"12606 64th Ave W Edmonds WA 98026",
    "addr:housenumber":"12606",
    "addr:postcode":"98026",
    "addr:street":"64Th Ave W",
    "iso:country":"US",
    "sg:address":"12606 64th Ave W",
    "sg:city":"Edmonds",
    "sg:classifiers":[
        {
            "category":"Wholesale",
            "subcategory":"Machinery & Supplies",
            "type":"Manufacturing & Wholesale Goods"
        }
    ],
    "sg:phone":"+1 425 743 4814",
    "sg:postcode":"98026",
    "sg:province":"WA",
    "sg:tags":[
        "equipment",
        "industrial"
    ],
    "wof:name":"Ideal Enterprises",
    "wof:placetype":"venue"
},
  "geometry": {"coordinates":[-122.31992099999999,47.883434],"type":"Point"}
}