{
  "type": "Feature",
  "properties": {
    "addr:full":"1200 Dupont St Bellingham WA 98225",
    "addr:housenumber":"1200",
    "addr:postcode":"98225",
    "addr:street":"Dupont St",
    "iso:country":"US",
    "sg:address":"1200 Dupont St",
    "sg:city":"Bellingham",
    "sg:classifiers":[
        {
            "category":"Professional",
            "subcategory":"Business Services",
            "type":"Services"
        }
    ],
    "sg:phone":"+1 360 715 0038",
    "sg:postcode":"98225",
    "sg:province":"WA",
    "wof:name":"Nationwide Business Resources",
    "wof:placetype":"venue"
},
  "geometry": {"coordinates":[-122.48683800000001,48.758742],"type":"Point"}
}