{
  "type": "Feature",
  "properties": {
    "addr:full":"13035 Gateway Drive Suite 119 Tukwila WA 98168",
    "addr:housenumber":"13035",
    "addr:postcode":"98168",
    "addr:street":"Gateway Drive Suite 119",
    "iso:country":"US",
    "sg:address":"13035 Gateway Drive Suite 119",
    "sg:city":"Tukwila",
    "sg:classifiers":[
        {
            "category":"Utilities",
            "type":"Services"
        }
    ],
    "sg:phone":"+1 206 242 1400",
    "sg:postcode":"98168",
    "sg:province":"WA",
    "sg:tags":[
        "provider",
        "internet"
    ],
    "wof:name":"Eschelon Telecom",
    "wof:placetype":"venue"
},
  "geometry": {"coordinates":[-122.273957,47.486846],"type":"Point"}
}