{
  "type": "Feature",
  "properties": {
    "addr:full":"401 Puget St NE Olympia WA 98506",
    "addr:housenumber":"401",
    "addr:postcode":"98506",
    "addr:street":"Puget St Ne",
    "iso:country":"US",
    "sg:address":"401 Puget St NE",
    "sg:city":"Olympia",
    "sg:classifiers":[
        {
            "category":"Home & Garden",
            "subcategory":"Hardware",
            "type":"Retail Goods"
        }
    ],
    "sg:phone":"+1 360 956 1153",
    "sg:postcode":"98506",
    "sg:province":"WA",
    "wof:name":"Tech Hardware Computers",
    "wof:placetype":"venue"
},
  "geometry": {"coordinates":[-122.887625,47.049572],"type":"Point"}
}