{
  "type": "Feature",
  "properties": {
    "addr:full":"9844 30th Ave SW Seattle WA 98126",
    "addr:housenumber":"9844",
    "addr:postcode":"98126",
    "addr:street":"30Th Ave Sw",
    "iso:country":"US",
    "sg:address":"9844 30th Ave SW",
    "sg:city":"Seattle",
    "sg:classifiers":[
        {
            "category":"Professional",
            "subcategory":"Computer Services",
            "type":"Services"
        }
    ],
    "sg:phone":"+1 206 935 5477",
    "sg:postcode":"98126",
    "sg:province":"WA",
    "sg:tags":[
        "related"
    ],
    "wof:name":"Pennie Jo Ledford",
    "wof:placetype":"venue"
},
  "geometry": {"coordinates":[-122.371049,47.514166],"type":"Point"}
}