{
  "type": "Feature",
  "properties": {
    "iso:country":"US",
    "sg:address":"1447 3rd Ave",
    "sg:city":"Longview",
    "sg:classifiers":[
        {
            "category":"Professional",
            "subcategory":"Lawyer & Legal Services",
            "type":"Services"
        }
    ],
    "sg:phone":"+1 360 425 4470",
    "sg:postcode":"98632",
    "sg:province":"WA",
    "sg:tags":[
        "attorney"
    ],
    "sg:website":"www.longviewlaw.com",
    "wof:name":"Crandall O'Neill Mc Reary",
    "wof:placetype":"venue"
},
  "geometry": {"coordinates":[-122.922321,46.136004],"type":"Point"}
}