{
  "type": "Feature",
  "properties": {
    "iso:country":"US",
    "sg:address":"1520 Broadway Ave",
    "sg:city":"Everett",
    "sg:classifiers":[
        {
            "category":"Wholesale",
            "subcategory":"Machinery & Supplies",
            "type":"Manufacturing & Wholesale Goods"
        }
    ],
    "sg:phone":"+1 425 339 9300",
    "sg:postcode":"98201",
    "sg:province":"WA",
    "sg:tags":[
        "equipment",
        "construction",
        "logging"
    ],
    "wof:name":"Everett Equipment Inc",
    "wof:placetype":"venue"
},
  "geometry": {"coordinates":[-122.201201,47.996606],"type":"Point"}
}