{
  "type": "Feature",
  "properties": {
    "addr:full":"3420 C St NE Ste 301 Auburn WA 98002",
    "addr:housenumber":"3420",
    "addr:postcode":"98002",
    "addr:street":"C St Ne Ste 301",
    "iso:country":"US",
    "sg:address":"3420 C St NE Ste 301",
    "sg:city":"Auburn",
    "sg:classifiers":[
        {
            "category":"Manufacturing",
            "subcategory":"Metals",
            "type":"Manufacturing & Wholesale Goods"
        },
        {
            "category":"Building & Trades",
            "subcategory":"Construction",
            "type":"Services"
        },
        {
            "category":"Retail",
            "subcategory":"Auto Repair",
            "type":"Services"
        }
    ],
    "sg:phone":"+1 253 939 6446",
    "sg:postcode":"98002",
    "sg:province":"WA",
    "sg:tags":[
        "shop",
        "steel",
        "automobile",
        "machine",
        "detailers",
        "metal-wholesale",
        "structural",
        "manufacturer"
    ],
    "wof:name":"Excel Manufacturing Inc",
    "wof:placetype":"venue"
},
  "geometry": {"coordinates":[-122.226561,47.33741],"type":"Point"}
}