{
  "type": "Feature",
  "properties": {
    "addr:full":"1210 N 45th St Seattle WA 98103",
    "addr:housenumber":"1210",
    "addr:postcode":"98103",
    "addr:street":"N 45Th St",
    "iso:country":"US",
    "sg:address":"1210 N 45th St",
    "sg:city":"Seattle",
    "sg:classifiers":[
        {
            "category":"Health Services",
            "subcategory":"Chiropractor",
            "type":"Services"
        }
    ],
    "sg:phone":"+1 206 633 1806",
    "sg:postcode":"98103",
    "sg:province":"WA",
    "wof:name":"Wallingford Chiropractic Clinic",
    "wof:placetype":"venue"
},
  "geometry": {"coordinates":[-122.343008,47.661547],"type":"Point"}
}