{
  "type": "Feature",
  "properties": {
    "addr:full":"14700 NE 8th St Suite 115 Bellevue WA 98007",
    "addr:housenumber":"14700",
    "addr:postcode":"98007",
    "addr:street":"Ne 8Th St Suite 115",
    "iso:country":"US",
    "sg:address":"14700 NE 8th St Suite 115",
    "sg:city":"Bellevue",
    "sg:classifiers":[
        {
            "category":"Personal",
            "subcategory":"Massage",
            "type":"Services"
        },
        {
            "category":"Health Services",
            "subcategory":"Chiropractor",
            "type":"Services"
        }
    ],
    "sg:phone":"+1 425 644 8386",
    "sg:postcode":"98007",
    "sg:province":"WA",
    "sg:tags":[
        "chiropractic"
    ],
    "sg:website":"www.bv.wellnessone.net",
    "wof:name":"Wellness One",
    "wof:placetype":"venue"
},
  "geometry": {"coordinates":[-122.144785,47.617362],"type":"Point"}
}