{
  "type": "Feature",
  "properties": {
    "addr:full":"17907 38th Ave E Tacoma WA 98446",
    "addr:housenumber":"17907",
    "addr:postcode":"98446",
    "addr:street":"38Th Ave E",
    "iso:country":"US",
    "sg:address":"17907 38th Ave E",
    "sg:city":"Tacoma",
    "sg:classifiers":[
        {
            "category":"Freight",
            "type":"Transportation"
        }
    ],
    "sg:phone":"+1 253 847 9235",
    "sg:postcode":"98446",
    "sg:province":"WA",
    "sg:tags":[
        "operator",
        "local",
        "trucking"
    ],
    "wof:name":"Reh Trucking",
    "wof:placetype":"venue"
},
  "geometry": {"coordinates":[-122.37893800000001,47.094656],"type":"Point"}
}