{
  "type": "Feature",
  "properties": {
    "addr:full":"14515 48th Avenue Ct NW Gig Harbor WA 98332",
    "addr:housenumber":"14515",
    "addr:postcode":"98332",
    "addr:street":"48Th Avenue Ct Nw",
    "iso:country":"US",
    "sg:address":"14515 48th Avenue Ct NW",
    "sg:city":"Gig Harbor",
    "sg:classifiers":[
        {
            "category":"Professional",
            "type":"Services"
        }
    ],
    "sg:phone":"+1 253 851 8644",
    "sg:postcode":"98332",
    "sg:province":"WA",
    "wof:name":"Harrison Jeffrey",
    "wof:placetype":"venue"
},
  "geometry": {"coordinates":[-122.602863,47.39021],"type":"Point"}
}