{
  "type": "Feature",
  "properties": {
    "addr:full":"113 17th Ave E Seattle WA 98112",
    "addr:housenumber":"113",
    "addr:postcode":"98112",
    "addr:street":"17Th Ave E",
    "iso:country":"US",
    "sg:address":"113 17th Ave E",
    "sg:city":"Seattle",
    "sg:classifiers":[
        {
            "category":"Manufacturing",
            "subcategory":"Glass & Minerals",
            "type":"Manufacturing & Wholesale Goods"
        }
    ],
    "sg:phone":"+1 206 720 6042",
    "sg:postcode":"98112",
    "sg:province":"WA",
    "sg:tags":[
        "product",
        "mfg"
    ],
    "wof:name":"Dogged Enterprises Inc",
    "wof:placetype":"venue"
},
  "geometry": {"coordinates":[-122.31020599999999,47.619529],"type":"Point"}
}