{
  "type": "Feature",
  "properties": {
    "addr:full":"14576 NE 95th St Redmond WA 98052",
    "addr:housenumber":"14576",
    "addr:postcode":"98052",
    "addr:street":"Ne 95Th St",
    "iso:country":"US",
    "sg:address":"14576 NE 95th St",
    "sg:city":"Redmond",
    "sg:classifiers":[
        {
            "category":"Wholesale",
            "subcategory":"Machinery & Supplies",
            "type":"Manufacturing & Wholesale Goods"
        }
    ],
    "sg:phone":"+1 425 869 1233",
    "sg:postcode":"98052",
    "sg:province":"WA",
    "sg:tags":[
        "rep",
        "mfg"
    ],
    "sg:website":"www.correctequipment.com",
    "wof:name":"Correct Equipment Inc",
    "wof:placetype":"venue"
},
  "geometry": {"coordinates":[-122.14562599999999,47.685594],"type":"Point"}
}