{
  "type": "Feature",
  "properties": {
    "iso:country":"US",
    "sg:address":"4022 N 15th St",
    "sg:city":"Tacoma",
    "sg:classifiers":[
        {
            "category":"Building & Trades",
            "subcategory":"Cleaning & Sanitation",
            "type":"Services"
        }
    ],
    "sg:phone":"+1 253 761 8286",
    "sg:postcode":"98406",
    "sg:province":"WA",
    "sg:tags":[
        "maintenance"
    ],
    "wof:name":"Mom & Pops Cleaning Service",
    "wof:placetype":"venue"
},
  "geometry": {"coordinates":[-122.491477,47.263578],"type":"Point"}
}