{
  "type": "Feature",
  "properties": {
    "iso:country":"US",
    "sg:address":"18219 E Appleway Ave",
    "sg:city":"Greenacres",
    "sg:classifiers":[
        {
            "category":"Restaurant",
            "type":"Food & Drink"
        }
    ],
    "sg:phone":"+1 509 921 5948",
    "sg:postcode":"99016",
    "sg:province":"WA",
    "sg:tags":[
        "eating"
    ],
    "wof:name":"Pete's Pizza",
    "wof:placetype":"venue"
},
  "geometry": {"coordinates":[-117.16233099999999,47.658543],"type":"Point"}
}