{
  "type": "Feature",
  "properties": {
    "addr:full":"2705 S 240th St Kent WA 98032",
    "addr:housenumber":"2705",
    "addr:postcode":"98032",
    "addr:street":"S 240Th St",
    "iso:country":"US",
    "sg:address":"2705 S 240th St",
    "sg:city":"Kent",
    "sg:classifiers":[
        {
            "category":"Professional",
            "subcategory":"Employment Agencies",
            "type":"Services"
        }
    ],
    "sg:phone":"+1 206 878 0888",
    "sg:postcode":"98032",
    "sg:province":"WA",
    "sg:tags":[
        "help",
        "supply"
    ],
    "wof:name":"Olh Trucking",
    "wof:placetype":"venue"
},
  "geometry": {"coordinates":[-122.29867299999999,47.386442],"type":"Point"}
}