{
  "type": "Feature",
  "properties": {
    "iso:country":"US",
    "sg:address":"4774 S Hansen Dr",
    "sg:city":"Clinton",
    "sg:classifiers":[
        {
            "category":"Building & Trades",
            "subcategory":"Construction",
            "type":"Services"
        }
    ],
    "sg:phone":"+1 360 341 2787",
    "sg:postcode":"98236",
    "sg:province":"WA",
    "sg:tags":[
        "contractor"
    ],
    "wof:name":"Judd Lotts Construction",
    "wof:placetype":"venue"
},
  "geometry": {"coordinates":[-122.35790299999999,47.982582],"type":"Point"}
}