{
  "type": "Feature",
  "properties": {
    "addr:full":"4306 S Myrtle St Seattle WA 98118",
    "addr:housenumber":"4306",
    "addr:postcode":"98118",
    "addr:street":"S Myrtle St",
    "iso:country":"US",
    "sg:address":"4306 S Myrtle St",
    "sg:city":"Seattle",
    "sg:classifiers":[
        {
            "category":"Wholesale",
            "subcategory":"Apparel",
            "type":"Manufacturing & Wholesale Goods"
        }
    ],
    "sg:phone":"+1 206 722 6611",
    "sg:postcode":"98118",
    "sg:province":"WA",
    "sg:tags":[
        "clothing"
    ],
    "wof:name":"Mbm & Assoc",
    "wof:placetype":"venue"
},
  "geometry": {"coordinates":[-122.27812,47.538966],"type":"Point"}
}