{
  "type": "Feature",
  "properties": {
    "addr:full":"3420 NE 55th St Seattle WA 98105",
    "addr:housenumber":"3420",
    "addr:postcode":"98105",
    "addr:street":"Ne 55Th St",
    "iso:country":"US",
    "sg:address":"3420 NE 55th St",
    "sg:city":"Seattle",
    "sg:classifiers":[
        {
            "category":"Personal",
            "subcategory":"Barber",
            "type":"Services"
        }
    ],
    "sg:phone":"+1 206 523 6600",
    "sg:postcode":"98105",
    "sg:province":"WA",
    "wof:name":"Starline Barber Shop",
    "wof:placetype":"venue"
},
  "geometry": {"coordinates":[-122.290916,47.668526],"type":"Point"}
}