{
  "type": "Feature",
  "properties": {
    "addr:full":"1110 W Pioneer Ave Puyallup WA 98371",
    "addr:housenumber":"1110",
    "addr:postcode":"98371",
    "addr:street":"W Pioneer Ave",
    "iso:country":"US",
    "sg:address":"1110 W Pioneer Ave",
    "sg:city":"Puyallup",
    "sg:classifiers":[
        {
            "category":"Education",
            "subcategory":"School",
            "type":"Public Place"
        }
    ],
    "sg:phone":"+1 253 841 8737",
    "sg:postcode":"98371",
    "sg:province":"WA",
    "sg:website":"www.puyallupschools.com",
    "wof:name":"Maplewood Elementary School",
    "wof:placetype":"venue"
},
  "geometry": {"coordinates":[-122.309532,47.190274],"type":"Point"}
}