{
  "type": "Feature",
  "properties": {
    "iso:country":"US",
    "sg:address":"1170 SW Bay St",
    "sg:city":"Port Orchard",
    "sg:classifiers":[
        {
            "category":"Professional",
            "type":"Services"
        },
        {
            "category":"Retail",
            "subcategory":"Animal Services",
            "type":"Services"
        }
    ],
    "sg:phone":"+1 360 876 5510",
    "sg:postcode":"98366",
    "sg:province":"WA",
    "sg:tags":[
        "pet",
        "grooming",
        "washing"
    ],
    "wof:name":"Groomery",
    "wof:placetype":"venue"
},
  "geometry": {"coordinates":[-122.66218000000001,47.539185],"type":"Point"}
}