{
  "type": "Feature",
  "properties": {
    "addr:full":"1511 Rosenkranz Rd Tieton WA 98947",
    "addr:housenumber":"1511",
    "addr:postcode":"98947",
    "addr:street":"Rosenkranz Rd",
    "iso:country":"US",
    "sg:address":"1511 Rosenkranz Rd",
    "sg:city":"Tieton",
    "sg:classifiers":[
        {
            "category":"Farming",
            "subcategory":"Orchard",
            "type":"Manufacturing & Wholesale Goods"
        }
    ],
    "sg:phone":"+1 509 673 9321",
    "sg:postcode":"98947",
    "sg:province":"WA",
    "sg:tags":[
        "fruit",
        "tree"
    ],
    "wof:name":"Terry Lee Hudson",
    "wof:placetype":"venue"
},
  "geometry": {"coordinates":[-120.74181799999999,46.709323],"type":"Point"}
}