{
  "type": "Feature",
  "properties": {
    "addr:full":"16855 Redmond Way Redmond WA 98052",
    "addr:housenumber":"16855",
    "addr:postcode":"98052",
    "addr:street":"Redmond Way",
    "iso:country":"US",
    "sg:address":"16855 Redmond Way",
    "sg:city":"Redmond",
    "sg:classifiers":[
        {
            "category":"Restaurant",
            "type":"Food & Drink"
        }
    ],
    "sg:phone":"+1 425 885 0605",
    "sg:postcode":"98052",
    "sg:province":"WA",
    "sg:tags":[
        "eating",
        "caterer"
    ],
    "wof:name":"Dana's Catering",
    "wof:placetype":"venue"
},
  "geometry": {"coordinates":[-122.114915,47.671936],"type":"Point"}
}