{
  "type": "Feature",
  "properties": {
    "addr:full":"25512 Minkler Rd Sedro Woolley WA 98284",
    "addr:postcode":"25512;98284",
    "addr:street":"Minkler Rd",
    "iso:country":"US",
    "sg:address":"25512 Minkler Rd",
    "sg:city":"Sedro Woolley",
    "sg:classifiers":[
        {
            "category":"Shopping",
            "subcategory":"Books",
            "type":"Retail Goods"
        }
    ],
    "sg:phone":"+1 360 856 1199",
    "sg:postcode":"98284",
    "sg:province":"WA",
    "wof:name":"Orchid Book Ranch",
    "wof:placetype":"venue"
},
  "geometry": {"coordinates":[-122.192578,48.512992],"type":"Point"}
}