{
  "type": "Feature",
  "properties": {
    "addr:full":"6333 2nd Ave SW Olympia WA 98512",
    "addr:housenumber":"6333",
    "addr:postcode":"98512",
    "addr:street":"2Nd Ave Sw",
    "iso:country":"US",
    "sg:address":"6333 2nd Ave SW",
    "sg:city":"Olympia",
    "sg:classifiers":[
        {
            "category":"Real Estate",
            "subcategory":"Real Estate Operator",
            "type":"Services"
        }
    ],
    "sg:phone":"+1 360 402 0649",
    "sg:postcode":"98512",
    "sg:province":"WA",
    "sg:tags":[
        "building",
        "nonresidential"
    ],
    "wof:name":"L & M Properties",
    "wof:placetype":"venue"
},
  "geometry": {"coordinates":[-123.005214,47.04683],"type":"Point"}
}