{
  "type": "Feature",
  "properties": {
    "addr:full":"500 Front St Lynden WA 98264",
    "addr:housenumber":"500",
    "addr:postcode":"98264",
    "addr:street":"Front St",
    "iso:country":"US",
    "sg:address":"500 Front St",
    "sg:city":"Lynden",
    "sg:classifiers":[
        {
            "category":"Health Services",
            "subcategory":"Doctor",
            "type":"Services"
        }
    ],
    "sg:phone":"+1 360 354 4200",
    "sg:postcode":"98264",
    "sg:province":"WA",
    "sg:tags":[
        "medical"
    ],
    "wof:name":"Dickson Medical Clinic",
    "wof:placetype":"venue"
},
  "geometry": {"coordinates":[-122.453067,48.942769],"type":"Point"}
}