{
  "type": "Feature",
  "properties": {
    "addr:full":"911 Main St #10 Vancouver WA 98660",
    "addr:housenumber":"911",
    "addr:postcode":"98660",
    "addr:street":"Main St # 10",
    "iso:country":"US",
    "sg:address":"911 Main St #10",
    "sg:city":"Vancouver",
    "sg:classifiers":[
        {
            "category":"Professional",
            "subcategory":"Business Services",
            "type":"Services"
        }
    ],
    "sg:phone":"+1 360 693 7100",
    "sg:postcode":"98660",
    "sg:province":"WA",
    "sg:tags":[
        "consultant",
        "coach"
    ],
    "sg:website":"http://www.ctslanguagelink.com",
    "wof:name":"CTS Language Link",
    "wof:placetype":"venue"
},
  "geometry": {"coordinates":[-122.671621,45.628087],"type":"Point"}
}