{
  "type": "Feature",
  "properties": {
    "iso:country":"US",
    "sg:address":"4331 Stikes Dr SE",
    "sg:city":"Lacey",
    "sg:classifiers":[
        {
            "category":"Retail",
            "subcategory":"Portrait Studio",
            "type":"Services"
        }
    ],
    "sg:phone":"+1 360 456 7674",
    "sg:postcode":"98503",
    "sg:province":"WA",
    "sg:tags":[
        "photographer"
    ],
    "wof:name":"Photography By Arthur Uchytil",
    "wof:placetype":"venue"
},
  "geometry": {"coordinates":[-122.819203,47.008239],"type":"Point"}
}