{
  "type": "Feature",
  "properties": {
    "addr:full":"222 N Mission St Wenatchee WA 98801",
    "addr:housenumber":"222",
    "addr:postcode":"98801",
    "addr:street":"N Mission St",
    "iso:country":"US",
    "sg:address":"222 N Mission St",
    "sg:city":"Wenatchee",
    "sg:classifiers":[
        {
            "category":"Health Services",
            "subcategory":"Doctor",
            "type":"Services"
        }
    ],
    "sg:phone":"+1 509 662 1648",
    "sg:postcode":"98801",
    "sg:province":"WA",
    "wof:name":"Mehrer Richard K DDS",
    "wof:placetype":"venue"
},
  "geometry": {"coordinates":[-120.31510299999999,47.427043],"type":"Point"}
}