{
  "type": "Feature",
  "properties": {
    "addr:full":"21220 Monument Rd SW Vashon WA 98070",
    "addr:postcode":"21220;98070",
    "addr:street":"Monument Rd Sw",
    "iso:country":"US",
    "sg:address":"21220 Monument Rd SW",
    "sg:city":"Vashon",
    "sg:classifiers":[
        {
            "category":"Retail",
            "subcategory":"Portrait Studio",
            "type":"Services"
        }
    ],
    "sg:phone":"+1 206 463 4348",
    "sg:postcode":"98070",
    "sg:province":"WA",
    "sg:tags":[
        "photographer",
        "photo"
    ],
    "wof:name":"Crescent Studios",
    "wof:placetype":"venue"
},
  "geometry": {"coordinates":[-122.44972199999999,47.414055],"type":"Point"}
}