{
  "type": "Feature",
  "properties": {
    "addr:full":"1841 NE Mission Creek Rd Belfair WA 98528",
    "addr:housenumber":"1841",
    "addr:postcode":"98528",
    "addr:street":"Ne Mission Creek Rd",
    "iso:country":"US",
    "sg:address":"1841 NE Mission Creek Rd",
    "sg:city":"Belfair",
    "sg:classifiers":[
        {
            "category":"Shopping",
            "type":"Retail Goods"
        }
    ],
    "sg:phone":"+1 360 275 6834",
    "sg:postcode":"98528",
    "sg:province":"WA",
    "sg:tags":[
        "merchandise"
    ],
    "wof:name":"Wreaths By Suzanne",
    "wof:placetype":"venue"
},
  "geometry": {"coordinates":[-122.866128,47.451942],"type":"Point"}
}