{
  "type": "Feature",
  "properties": {
    "addr:full":"420 Basin St SW Ephrata WA 98823",
    "addr:housenumber":"420",
    "addr:postcode":"98823",
    "addr:street":"Basin St Sw",
    "iso:country":"US",
    "sg:address":"420 Basin St SW",
    "sg:city":"Ephrata",
    "sg:classifiers":[
        {
            "category":"Professional",
            "subcategory":"Management & Consulting",
            "type":"Services"
        }
    ],
    "sg:phone":"+1 509 754 4050",
    "sg:postcode":"98823",
    "sg:province":"WA",
    "sg:tags":[
        "business",
        "real estate"
    ],
    "wof:name":"Economic",
    "wof:placetype":"venue"
},
  "geometry": {"coordinates":[-119.55462199999999,47.316392],"type":"Point"}
}