{
  "type": "Feature",
  "properties": {
    "addr:full":"1308 S Tyler St Tacoma WA 98405",
    "addr:housenumber":"1308",
    "addr:postcode":"98405",
    "addr:street":"S Tyler St",
    "iso:country":"US",
    "sg:address":"1308 S Tyler St",
    "sg:city":"Tacoma",
    "sg:classifiers":[
        {
            "category":"Professional",
            "subcategory":"Advertising",
            "type":"Services"
        }
    ],
    "sg:phone":"+1 253 404 1069",
    "sg:postcode":"98405",
    "sg:province":"WA",
    "sg:tags":[
        "agency"
    ],
    "wof:name":"Adlib Advertising & Creations",
    "wof:placetype":"venue"
},
  "geometry": {"coordinates":[-122.493048,47.248144],"type":"Point"}
}