{
  "type": "Feature",
  "properties": {
    "addr:full":"412 E Alder Ave Ritzville WA 99169",
    "addr:housenumber":"412",
    "addr:postcode":"99169",
    "addr:street":"E Alder Ave",
    "iso:country":"US",
    "sg:address":"412 E Alder Ave",
    "sg:city":"Ritzville",
    "sg:classifiers":[
        {
            "category":"Fast Food",
            "type":"Food & Drink"
        },
        {
            "category":"Restaurant",
            "type":"Food & Drink"
        }
    ],
    "sg:phone":"+1 509 659 1249",
    "sg:postcode":"99169",
    "sg:province":"WA",
    "wof:name":"Roni Kinny",
    "wof:placetype":"venue"
},
  "geometry": {"coordinates":[-118.37878000000001,47.131057],"type":"Point"}
}