{
  "type": "Feature",
  "properties": {
    "addr:full":"20317 244th Ave SE Maple Valley WA 98038",
    "addr:housenumber":"20317",
    "addr:postcode":"98038",
    "addr:street":"244Th Ave Se;Valley",
    "iso:country":"US",
    "sg:address":"20317 244th Ave SE",
    "sg:city":"Maple Valley",
    "sg:classifiers":[
        {
            "category":"Manufacturing",
            "subcategory":"Tools & Machinery",
            "type":"Manufacturing & Wholesale Goods"
        }
    ],
    "sg:phone":"+1 425 433 1141",
    "sg:postcode":"98038",
    "sg:province":"WA",
    "sg:tags":[
        "machine",
        "shop"
    ],
    "wof:name":"United Manufacturing Products",
    "wof:placetype":"venue"
},
  "geometry": {"coordinates":[-122.015744,47.419606],"type":"Point"}
}