{
  "type": "Feature",
  "properties": {
    "addr:full":"917 Triple Crown Way #100 Yakima WA 98908",
    "addr:housenumber":"917",
    "addr:postcode":"98908",
    "addr:street":"Triple Crown Way # 100",
    "iso:country":"US",
    "sg:address":"917 Triple Crown Way #100",
    "sg:city":"Yakima",
    "sg:classifiers":[
        {
            "category":"Professional",
            "subcategory":"Lawyer & Legal Services",
            "type":"Services"
        }
    ],
    "sg:phone":"+1 509 494 8181",
    "sg:postcode":"98908",
    "sg:province":"WA",
    "sg:tags":[
        "attorney",
        "property",
        "personal",
        "practice",
        "worker",
        "damage",
        "labor",
        "benefit",
        "accident",
        "employee",
        "injury",
        "employment",
        "compensation",
        "law"
    ],
    "sg:website":"http://www.rmboggslaw.com",
    "wof:name":"Boggs Robert M Law Offices",
    "wof:placetype":"venue"
},
  "geometry": {"coordinates":[-120.562859,46.612698],"type":"Point"}
}