{
  "type": "Feature",
  "properties": {
    "addr:full":"8895 Madison Ave NE Bainbridge Isle WA 98110",
    "addr:housenumber":"8895",
    "addr:postcode":"98110",
    "addr:street":"Madison Ave Ne;Isle",
    "iso:country":"US",
    "sg:address":"8895 Madison Ave NE",
    "sg:city":"Bainbridge Isle",
    "sg:classifiers":[
        {
            "category":"Government",
            "subcategory":"Fire Station",
            "type":"Public Place"
        }
    ],
    "sg:phone":"+1 206 842 7686",
    "sg:postcode":"98110",
    "sg:province":"WA",
    "sg:tags":[
        "department"
    ],
    "sg:website":"www.bifd.org",
    "wof:name":"Bainbridge Island Fire Dept",
    "wof:placetype":"venue"
},
  "geometry": {"coordinates":[-122.521096,47.643142],"type":"Point"}
}