{
  "type": "Feature",
  "properties": {
    "addr:full":"926 E 8th Ave Spokane WA 99202",
    "addr:housenumber":"926",
    "addr:postcode":"99202",
    "addr:street":"E 8Th Ave",
    "iso:country":"US",
    "sg:address":"926 E 8th Ave",
    "sg:city":"Spokane",
    "sg:classifiers":[
        {
            "category":"Real Estate",
            "subcategory":"Real Estate Operator",
            "type":"Services"
        }
    ],
    "sg:phone":"+1 509 534 2339",
    "sg:postcode":"99202",
    "sg:province":"WA",
    "sg:tags":[
        "building",
        "apartment"
    ],
    "wof:name":"Hifumi En",
    "wof:placetype":"venue"
},
  "geometry": {"coordinates":[-117.39723600000001,47.648077],"type":"Point"}
}