{
  "type": "Feature",
  "properties": {
    "addr:full":"18705 SE 284th Pl Kent WA 98042",
    "addr:postcode":"18705;98042",
    "addr:street":"Se 284Th Pl",
    "iso:country":"US",
    "sg:address":"18705 SE 284th Pl",
    "sg:city":"Kent",
    "sg:classifiers":[
        {
            "category":"Manufacturing",
            "subcategory":"Metals",
            "type":"Manufacturing & Wholesale Goods"
        }
    ],
    "sg:phone":"+1 253 804 2712",
    "sg:postcode":"98042",
    "sg:province":"WA",
    "sg:tags":[
        "hardware",
        "sporting",
        "mfg"
    ],
    "wof:name":"Vision Tech U S A Inc",
    "wof:placetype":"venue"
},
  "geometry": {"coordinates":[-122.091538,47.346939],"type":"Point"}
}