{
  "type": "Feature",
  "properties": {
    "addr:full":"56206 S Sloan Rd Kennewick WA 99337",
    "addr:housenumber":"56206",
    "addr:postcode":"99337",
    "addr:street":"S Sloan Rd",
    "iso:country":"US",
    "sg:address":"56206 S Sloan Rd",
    "sg:city":"Kennewick",
    "sg:classifiers":[
        {
            "category":"Building & Trades",
            "subcategory":"Landscaping Services",
            "type":"Services"
        },
        {
            "category":"Farming",
            "subcategory":"Orchard",
            "type":"Manufacturing & Wholesale Goods"
        }
    ],
    "sg:phone":"+1 509 582 2512",
    "sg:postcode":"99337",
    "sg:province":"WA",
    "sg:tags":[
        "tree"
    ],
    "wof:name":"Byrds & Barns",
    "wof:placetype":"venue"
},
  "geometry": {"coordinates":[-119.03425,46.126363],"type":"Point"}
}