{
  "type": "Feature",
  "properties": {
    "addr:full":"4901 Auto Center Blvd Bremerton WA 98312",
    "addr:housenumber":"4901",
    "addr:postcode":"98312",
    "addr:street":"Auto Center Blvd",
    "iso:country":"US",
    "sg:address":"4901 Auto Center Blvd",
    "sg:city":"Bremerton",
    "sg:classifiers":[
        {
            "category":"Freight",
            "type":"Transportation"
        }
    ],
    "sg:phone":"+1 360 373 2521",
    "sg:postcode":"98312",
    "sg:province":"WA",
    "sg:tags":[
        "mover"
    ],
    "wof:name":"Merchants Moving & Storage",
    "wof:placetype":"venue"
},
  "geometry": {"coordinates":[-122.681134,47.561434],"type":"Point"}
}