{
  "type": "Feature",
  "properties": {
    "addr:full":"119 12th Ave Seattle WA 98122",
    "addr:housenumber":"119",
    "addr:postcode":"98122",
    "addr:street":"12Th Ave",
    "iso:country":"US",
    "sg:address":"119 12th Ave",
    "sg:city":"Seattle",
    "sg:classifiers":[
        {
            "category":"Museum",
            "type":"Entertainment"
        }
    ],
    "sg:phone":"+1 206 325 8943",
    "sg:postcode":"98122",
    "sg:province":"WA",
    "sg:tags":[
        "gallery"
    ],
    "wof:name":"Ayala",
    "wof:placetype":"venue"
},
  "geometry": {"coordinates":[-122.316858,47.602312],"type":"Point"}
}