{
  "type": "Feature",
  "properties": {
    "addr:full":"5625 119th Avenue SE Bellevue WA 98006",
    "addr:housenumber":"5625",
    "addr:postcode":"98006",
    "addr:street":"119Th Avenue Se",
    "iso:country":"US",
    "sg:address":"5625 119th Avenue SE",
    "sg:city":"Bellevue",
    "sg:classifiers":[
        {
            "category":"Restaurant",
            "type":"Food & Drink"
        }
    ],
    "sg:phone":"+1 425 644 0150",
    "sg:postcode":"98006",
    "sg:province":"WA",
    "sg:tags":[
        "pizza"
    ],
    "sg:website":"www.saharapizza.com/",
    "wof:name":"Sahara Pizza",
    "wof:placetype":"venue"
},
  "geometry": {"coordinates":[-122.179084,47.552141],"type":"Point"}
}