{
  "type": "Feature",
  "properties": {
    "addr:full":"177 Telegraph Rd Bellingham WA 98226",
    "addr:housenumber":"177",
    "addr:postcode":"98226",
    "addr:street":"Telegraph Rd",
    "iso:country":"US",
    "sg:address":"177 Telegraph Rd",
    "sg:city":"Bellingham",
    "sg:classifiers":[
        {
            "category":"Professional",
            "type":"Services"
        }
    ],
    "sg:phone":"+1 360 398 2705",
    "sg:postcode":"98226",
    "sg:province":"WA",
    "wof:name":"Grand View Sign & Awning",
    "wof:placetype":"venue"
},
  "geometry": {"coordinates":[-122.47920499999999,48.784559],"type":"Point"}
}