{
  "type": "Feature",
  "properties": {
    "addr:full":"114 Lind St Mount Vernon WA 98273",
    "addr:housenumber":"114",
    "addr:postcode":"98273",
    "addr:street":"Lind St",
    "iso:country":"US",
    "sg:address":"114 Lind St",
    "sg:city":"Mount Vernon",
    "sg:classifiers":[
        {
            "category":"Building & Trades",
            "subcategory":"Pest Control",
            "type":"Services"
        }
    ],
    "sg:phone":"+1 360 336 3639",
    "sg:postcode":"98273",
    "sg:province":"WA",
    "wof:name":"Partners Insulation Inc",
    "wof:placetype":"venue"
},
  "geometry": {"coordinates":[-122.33231499999999,48.40921],"type":"Point"}
}