{
  "type": "Feature",
  "properties": {
    "addr:full":"5326 Green Hills Ave NE Tacoma WA 98422",
    "addr:housenumber":"5326",
    "addr:postcode":"98422",
    "addr:street":"Green Hills Ave Ne",
    "iso:country":"US",
    "sg:address":"5326 Green Hills Ave NE",
    "sg:city":"Tacoma",
    "sg:classifiers":[
        {
            "category":"Home & Garden",
            "subcategory":"Home Furnishings",
            "type":"Retail Goods"
        }
    ],
    "sg:phone":"+1 253 238 6984",
    "sg:postcode":"98422",
    "sg:province":"WA",
    "sg:tags":[
        "planning",
        "design"
    ],
    "wof:name":"Hm Design",
    "wof:placetype":"venue"
},
  "geometry": {"coordinates":[-122.423731,47.305859],"type":"Point"}
}