{
  "type": "Feature",
  "properties": {
    "addr:full":"8141 Sparrow Ct SE Olympia WA 98513",
    "addr:housenumber":"8141",
    "addr:postcode":"98513",
    "addr:street":"Sparrow Ct Se",
    "iso:country":"US",
    "sg:address":"8141 Sparrow Ct SE",
    "sg:city":"Olympia",
    "sg:classifiers":[
        {
            "category":"Autos & Motor Vehicles",
            "subcategory":"Auto Supplies",
            "type":"Retail Goods"
        }
    ],
    "sg:phone":"+1 360 438 1763",
    "sg:postcode":"98513",
    "sg:province":"WA",
    "wof:name":"Western Mustang Supply",
    "wof:placetype":"venue"
},
  "geometry": {"coordinates":[-122.780232,46.96924],"type":"Point"}
}