{
  "type": "Feature",
  "properties": {
    "addr:full":"120 Andover Park E Seattle WA 98188",
    "addr:housenumber":"120",
    "addr:postcode":"98188",
    "addr:street":"Andover Park E",
    "iso:country":"US",
    "sg:address":"120 Andover Park E",
    "sg:city":"Seattle",
    "sg:classifiers":[
        {
            "category":"Wholesale",
            "subcategory":"Groceries",
            "type":"Manufacturing & Wholesale Goods"
        }
    ],
    "sg:phone":"+1 206 242 3261",
    "sg:postcode":"98188",
    "sg:province":"WA",
    "sg:tags":[
        "food",
        "import",
        "product",
        "filipino"
    ],
    "wof:name":"Jade King L L C",
    "wof:placetype":"venue"
},
  "geometry": {"coordinates":[-122.249917,47.46091],"type":"Point"}
}