{
  "type": "Feature",
  "properties": {
    "iso:country":"US",
    "sg:address":"1201 3rd Ave",
    "sg:city":"Seattle",
    "sg:classifiers":[
        {
            "category":"Real Estate",
            "subcategory":"Developer",
            "type":"Services"
        }
    ],
    "sg:phone":"+1 206 622 2001",
    "sg:postcode":"98101",
    "sg:province":"WA",
    "wof:name":"Greenspace Inc",
    "wof:placetype":"venue"
},
  "geometry": {"coordinates":[-122.335978,47.607761],"type":"Point"}
}