{
  "type": "Feature",
  "properties": {
    "addr:full":"4051 56th Ave SW Seattle WA 98116",
    "addr:housenumber":"4051",
    "addr:postcode":"98116",
    "addr:street":"56Th Ave Sw",
    "iso:country":"US",
    "sg:address":"4051 56th Ave SW",
    "sg:city":"Seattle",
    "sg:classifiers":[
        {
            "category":"Building & Trades",
            "subcategory":"Construction",
            "type":"Services"
        }
    ],
    "sg:phone":"+1 206 937 4192",
    "sg:postcode":"98116",
    "sg:province":"WA",
    "sg:tags":[
        "nonresidential"
    ],
    "wof:name":"Ballard Industrial Contractors",
    "wof:placetype":"venue"
},
  "geometry": {"coordinates":[-122.40394499999999,47.567651],"type":"Point"}
}