{
  "type": "Feature",
  "properties": {
    "addr:full":"14510 NE 77th St Redmond WA 98052",
    "addr:housenumber":"14510",
    "addr:postcode":"98052",
    "addr:street":"Ne 77Th St",
    "iso:country":"US",
    "sg:address":"14510 NE 77th St",
    "sg:city":"Redmond",
    "sg:classifiers":[
        {
            "category":"Professional",
            "type":"Services"
        }
    ],
    "sg:phone":"+1 425 869 5550",
    "sg:postcode":"98052",
    "sg:province":"WA",
    "wof:name":"Steven D Kitterman Inc",
    "wof:placetype":"venue"
},
  "geometry": {"coordinates":[-122.145335,47.673786],"type":"Point"}
}