{
  "type": "Feature",
  "properties": {
    "addr:full":"16308 95th Ave SE Snohomish WA 98296",
    "addr:housenumber":"16308",
    "addr:postcode":"98296",
    "addr:street":"95Th Ave Se",
    "iso:country":"US",
    "sg:address":"16308 95th Ave SE",
    "sg:city":"Snohomish",
    "sg:classifiers":[
        {
            "category":"Professional",
            "type":"Services"
        }
    ],
    "sg:phone":"+1 360 668 6176",
    "sg:postcode":"98296",
    "sg:province":"WA",
    "wof:name":"Lorie M Bolduc",
    "wof:placetype":"venue"
},
  "geometry": {"coordinates":[-122.10463300000001,47.849039],"type":"Point"}
}