{
  "type": "Feature",
  "properties": {
    "addr:full":"677 120th Ave NE Bellevue WA 98005",
    "addr:housenumber":"677",
    "addr:postcode":"98005",
    "addr:street":"120Th Ave Ne",
    "iso:country":"US",
    "sg:address":"677 120th Ave NE",
    "sg:city":"Bellevue",
    "sg:classifiers":[
        {
            "category":"Manufacturing",
            "subcategory":"Food",
            "type":"Manufacturing & Wholesale Goods"
        }
    ],
    "sg:phone":"+1 206 334 8534",
    "sg:postcode":"98005",
    "sg:province":"WA",
    "sg:tags":[
        "white",
        "mfg",
        "powder",
        "chocolate"
    ],
    "wof:name":"Costellinis LLC",
    "wof:placetype":"venue"
},
  "geometry": {"coordinates":[-122.180373,47.615833],"type":"Point"}
}