{
  "type": "Feature",
  "properties": {
    "addr:full":"714 N 101st St Seattle WA 98133",
    "addr:housenumber":"714",
    "addr:postcode":"98133",
    "addr:street":"N 101St St",
    "iso:country":"US",
    "sg:address":"714 N 101st St",
    "sg:city":"Seattle",
    "sg:classifiers":[
        {
            "category":"Professional",
            "subcategory":"Art Services",
            "type":"Services"
        }
    ],
    "sg:phone":"+1 206 427 1395",
    "sg:postcode":"98133",
    "sg:province":"WA",
    "sg:tags":[
        "commercial",
        "design"
    ],
    "wof:name":"Logorepaircom",
    "wof:placetype":"venue"
},
  "geometry": {"coordinates":[-122.34747900000001,47.702236],"type":"Point"}
}