{
  "type": "Feature",
  "properties": {
    "addr:full":"111 S Shore Rd Newport WA 99156",
    "addr:housenumber":"111",
    "addr:postcode":"99156",
    "addr:street":"S Shore Rd",
    "iso:country":"US",
    "sg:address":"111 S Shore Rd",
    "sg:city":"Newport",
    "sg:classifiers":[
        {
            "category":"Real Estate",
            "subcategory":"Real Estate Operator",
            "type":"Services"
        }
    ],
    "sg:phone":"+1 509 447 5540",
    "sg:postcode":"99156",
    "sg:province":"WA",
    "sg:tags":[
        "mobile",
        "home",
        "site"
    ],
    "wof:name":"Harbor Resort",
    "wof:placetype":"venue"
},
  "geometry": {"coordinates":[-117.19658200000001,48.123269],"type":"Point"}
}