{
  "type": "Feature",
  "properties": {
    "addr:full":"11312 200th St E Graham WA 98338",
    "addr:housenumber":"11312",
    "addr:postcode":"98338",
    "addr:street":"200Th St E",
    "iso:country":"US",
    "sg:address":"11312 200th St E",
    "sg:city":"Graham",
    "sg:classifiers":[
        {
            "category":"Professional",
            "subcategory":"Advertising",
            "type":"Services"
        },
        {
            "category":"Professional",
            "subcategory":"Computer Services",
            "type":"Services"
        },
        {
            "category":"Internet Cafe",
            "subcategory":"None",
            "type":"Food & Drink"
        }
    ],
    "sg:phone":"+1 253 847 6827",
    "sg:postcode":"98338",
    "sg:province":"WA",
    "sg:tags":[
        "product",
        "agency",
        "software"
    ],
    "sg:website":"http://www.nutricheck.net",
    "wof:name":"Nutricheck Usa",
    "wof:placetype":"venue"
},
  "geometry": {"coordinates":[-122.27951299999999,47.074636],"type":"Point"}
}