{
  "type": "Feature",
  "properties": {
    "addr:full":"15625 NE 8th St Bellevue WA 98008",
    "addr:housenumber":"15625",
    "addr:postcode":"98008",
    "addr:street":"Ne 8Th St",
    "iso:country":"US",
    "sg:address":"15625 NE 8th St",
    "sg:city":"Bellevue",
    "sg:classifiers":[
        {
            "category":"Home & Garden",
            "subcategory":"Household Appliances",
            "type":"Retail Goods"
        }
    ],
    "sg:phone":"+1 425 746 0550",
    "sg:postcode":"98008",
    "sg:province":"WA",
    "sg:website":"www.crossroadsappliance.com",
    "wof:name":"Crossroads Appliance",
    "wof:placetype":"venue"
},
  "geometry": {"coordinates":[-122.131675,47.616391],"type":"Point"}
}