{
  "type": "Feature",
  "properties": {
    "addr:full":"3501 Colby Ave Everett WA 98201",
    "addr:housenumber":"3501",
    "addr:postcode":"98201",
    "addr:street":"Colby Ave",
    "iso:country":"US",
    "sg:address":"3501 Colby Ave",
    "sg:city":"Everett",
    "sg:classifiers":[
        {
            "category":"Government",
            "subcategory":"Court House",
            "type":"Public Place"
        }
    ],
    "sg:phone":"+1 425 339 1760",
    "sg:postcode":"98201",
    "sg:province":"WA",
    "sg:tags":[
        "state",
        "counsel"
    ],
    "wof:name":"Attorney General",
    "wof:placetype":"venue"
},
  "geometry": {"coordinates":[-122.208243,47.969944],"type":"Point"}
}