{
  "type": "Feature",
  "properties": {
    "addr:full":"2614 NE 46th St University Village Seattle WA 98105",
    "addr:housenumber":"2614",
    "addr:postcode":"98105",
    "addr:street":"Ne 46Th St",
    "iso:country":"US",
    "sg:address":"2614 NE 46th St University Village",
    "sg:city":"Seattle",
    "sg:classifiers":[
        {
            "category":"Restaurant",
            "type":"Food & Drink"
        }
    ],
    "sg:phone":"+1 206 524 2242",
    "sg:postcode":"98105",
    "sg:province":"WA",
    "sg:tags":[
        "tex-mex"
    ],
    "sg:website":"www.sonrisamodernmex.com",
    "wof:name":"Sonrisa",
    "wof:placetype":"venue"
},
  "geometry": {"coordinates":[-122.299277,47.661733],"type":"Point"}
}