{
  "type": "Feature",
  "properties": {
    "addr:full":"11127 47th Ave NE Marysville WA 98271",
    "addr:housenumber":"11127",
    "addr:postcode":"98271",
    "addr:street":"47Th Ave Ne",
    "iso:country":"US",
    "sg:address":"11127 47th Ave NE",
    "sg:city":"Marysville",
    "sg:classifiers":[
        {
            "category":"Social Services",
            "subcategory":"Adult Care",
            "type":"Services"
        }
    ],
    "sg:phone":"+1 360 659 1986",
    "sg:postcode":"98271",
    "sg:province":"WA",
    "sg:tags":[
        "residential"
    ],
    "wof:name":"Rhonda Griffin Respite Care",
    "wof:placetype":"venue"
},
  "geometry": {"coordinates":[-122.16767,48.095931],"type":"Point"}
}