{
  "type": "Feature",
  "properties": {
    "addr:full":"1209 W 39th St Vancouver WA 98660",
    "addr:housenumber":"1209",
    "addr:postcode":"98660",
    "addr:street":"W 39Th St",
    "iso:country":"US",
    "sg:address":"1209 W 39th St",
    "sg:city":"Vancouver",
    "sg:classifiers":[
        {
            "category":"Building & Trades",
            "subcategory":"Electrical",
            "type":"Services"
        }
    ],
    "sg:phone":"+1 360 721 1926",
    "sg:postcode":"98660",
    "sg:province":"WA",
    "sg:tags":[
        "electrical",
        "contractor"
    ],
    "wof:name":"Triumph Floors",
    "wof:placetype":"venue"
},
  "geometry": {"coordinates":[-122.685034,45.650012],"type":"Point"}
}