{
  "type": "Feature",
  "properties": {
    "addr:full":"2726 Simpson Ave Aberdeen WA 98520",
    "addr:housenumber":"2726",
    "addr:postcode":"98520",
    "addr:street":"Simpson Ave",
    "iso:country":"US",
    "sg:address":"2726 Simpson Ave",
    "sg:city":"Aberdeen",
    "sg:classifiers":[
        {
            "category":"Food & Beverages",
            "subcategory":"Specialty",
            "type":"Retail Goods"
        }
    ],
    "sg:phone":"+1 360 532 2131",
    "sg:postcode":"98520",
    "sg:province":"WA",
    "wof:name":"Sunrider Distributor",
    "wof:placetype":"venue"
},
  "geometry": {"coordinates":[-123.851663,46.975206],"type":"Point"}
}