{
  "type": "Feature",
  "properties": {
    "addr:full":"12972 N Ovenell Ln Burlington WA 98233",
    "addr:housenumber":"12972",
    "addr:postcode":"98233",
    "addr:street":"N Ovenell Ln",
    "iso:country":"US",
    "sg:address":"12972 N Ovenell Ln",
    "sg:city":"Burlington",
    "sg:classifiers":[
        {
            "category":"Retail",
            "subcategory":"Animal Services",
            "type":"Services"
        }
    ],
    "sg:phone":"+1 360 757 0126",
    "sg:postcode":"98233",
    "sg:province":"WA",
    "sg:tags":[
        "pet",
        "breeder"
    ],
    "wof:name":"ABS Atkins Breeding Svc",
    "wof:placetype":"venue"
},
  "geometry": {"coordinates":[-122.392124,48.457658],"type":"Point"}
}