{
  "type": "Feature",
  "properties": {
    "addr:full":"2901 Bridgeport Way W University Place WA 98466",
    "addr:housenumber":"2901",
    "addr:postcode":"98466",
    "addr:street":"Bridgeport Way W;Place",
    "iso:country":"US",
    "sg:address":"2901 Bridgeport Way W",
    "sg:city":"University Place",
    "sg:classifiers":[
        {
            "category":"Health Services",
            "subcategory":"Nursing And Care Facility",
            "type":"Services"
        }
    ],
    "sg:phone":"+1 253 671 7000",
    "sg:postcode":"98466",
    "sg:province":"WA",
    "sg:tags":[
        "hospice"
    ],
    "sg:website":"www.fhshealth.org",
    "wof:name":"Franciscan Hospice",
    "wof:placetype":"venue"
},
  "geometry": {"coordinates":[-122.537042,47.232624],"type":"Point"}
}