{
  "type": "Feature",
  "properties": {
    "addr:full":"3603 P St Vancouver WA 98663",
    "addr:housenumber":"3603 p",
    "addr:postcode":"98663",
    "addr:street":"St",
    "iso:country":"US",
    "sg:address":"3603 P St",
    "sg:city":"Vancouver",
    "sg:classifiers":[
        {
            "category":"Wholesale",
            "subcategory":"Construction Materials",
            "type":"Manufacturing & Wholesale Goods"
        }
    ],
    "sg:phone":"+1 360 695 9967",
    "sg:postcode":"98663",
    "sg:province":"WA",
    "wof:name":"El Wood Transcription",
    "wof:placetype":"venue"
},
  "geometry": {"coordinates":[-122.655244,45.64716],"type":"Point"}
}