{
  "type": "Feature",
  "properties": {
    "addr:full":"1261 Auburn Way N Auburn WA 98002",
    "addr:housenumber":"1261",
    "addr:postcode":"98002",
    "addr:street":"Auburn Way N",
    "iso:country":"US",
    "sg:address":"1261 Auburn Way N",
    "sg:city":"Auburn",
    "sg:classifiers":[
        {
            "category":"Professional",
            "subcategory":"Business Services",
            "type":"Services"
        }
    ],
    "sg:phone":"+1 253 939 2849",
    "sg:postcode":"98002",
    "sg:province":"WA",
    "sg:tags":[
        "financial"
    ],
    "wof:name":"Harbor Financial Services Inc",
    "wof:placetype":"venue"
},
  "geometry": {"coordinates":[-122.22157300000001,47.319691],"type":"Point"}
}