{
  "type": "Feature",
  "properties": {
    "addr:full":"2126 Pacific St Bellingham WA 98229",
    "addr:housenumber":"2126",
    "addr:postcode":"98229",
    "addr:street":"Pacific St",
    "iso:country":"US",
    "sg:address":"2126 Pacific St",
    "sg:city":"Bellingham",
    "sg:classifiers":[
        {
            "category":"Retail",
            "subcategory":"Auto Repair",
            "type":"Services"
        }
    ],
    "sg:phone":"+1 360 733 9032",
    "sg:postcode":"98229",
    "sg:province":"WA",
    "sg:tags":[
        "repairing",
        "automobile",
        "general"
    ],
    "wof:name":"Rising Sun Motors 1",
    "wof:placetype":"venue"
},
  "geometry": {"coordinates":[-122.45614,48.758749],"type":"Point"}
}