{
  "type": "Feature",
  "properties": {
    "addr:full":"301 S 9th Ave Yakima WA 98902",
    "addr:housenumber":"301",
    "addr:postcode":"98902",
    "addr:street":"S 9Th Ave",
    "iso:country":"US",
    "sg:address":"301 S 9th Ave",
    "sg:city":"Yakima",
    "sg:classifiers":[
        {
            "category":"Organizations",
            "subcategory":"Religious Organization",
            "type":"Services"
        }
    ],
    "sg:phone":"+1 509 248 5939",
    "sg:postcode":"98902",
    "sg:province":"WA",
    "sg:tags":[
        "church"
    ],
    "wof:name":"Iglesia 1 Corintios 13",
    "wof:placetype":"venue"
},
  "geometry": {"coordinates":[-120.51902200000001,46.593661],"type":"Point"}
}