{
  "type": "Feature",
  "properties": {
    "addr:full":"1401 Washington St Vancouver WA 98660",
    "addr:housenumber":"1401",
    "addr:postcode":"98660",
    "addr:street":"Washington St",
    "iso:country":"US",
    "sg:address":"1401 Washington St",
    "sg:city":"Vancouver",
    "sg:classifiers":[
        {
            "category":"Retail",
            "subcategory":"Laundry & Dry Cleaning",
            "type":"Services"
        }
    ],
    "sg:phone":"+1 360 696 1751",
    "sg:postcode":"98660",
    "sg:province":"WA",
    "sg:tags":[
        "cleaner"
    ],
    "wof:name":"Q C Cleaners",
    "wof:placetype":"venue"
},
  "geometry": {"coordinates":[-122.672997,45.632],"type":"Point"}
}