{
  "type": "Feature",
  "properties": {
    "addr:full":"2261 Mount Baker Hwy Bellingham WA 98226",
    "addr:housenumber":"2261",
    "addr:postcode":"98226",
    "addr:street":"Mount Baker Hwy",
    "iso:country":"US",
    "sg:address":"2261 Mount Baker Hwy",
    "sg:city":"Bellingham",
    "sg:classifiers":[
        {
            "category":"Building & Trades",
            "subcategory":"Construction",
            "type":"Services"
        },
        {
            "category":"Home & Garden",
            "subcategory":"Furniture",
            "type":"Retail Goods"
        }
    ],
    "sg:phone":"+1 360 738 1242",
    "sg:postcode":"98226",
    "sg:province":"WA",
    "sg:tags":[
        "house",
        "cabinet",
        "contractor",
        "carpentry"
    ],
    "wof:name":"Old Timer Builders",
    "wof:placetype":"venue"
},
  "geometry": {"coordinates":[-122.36773100000001,48.803875],"type":"Point"}
}