{
  "type": "Feature",
  "properties": {
    "addr:full":"14212 Ambaum Blvd SW Ste 106 Burien WA 98166",
    "addr:housenumber":"14212",
    "addr:postcode":"98166",
    "addr:street":"Ambaum Blvd Sw Ste 106",
    "iso:country":"US",
    "sg:address":"14212 Ambaum Blvd SW Ste 106",
    "sg:city":"Burien",
    "sg:classifiers":[
        {
            "category":"Health Services",
            "subcategory":"Doctor",
            "type":"Services"
        }
    ],
    "sg:phone":"+1 206 248 3668",
    "sg:postcode":"98166",
    "sg:province":"WA",
    "sg:tags":[
        "podiatrist"
    ],
    "wof:name":"Johnson Daniel K DPM",
    "wof:placetype":"venue"
},
  "geometry": {"coordinates":[-122.348,47.475498],"type":"Point"}
}