{
  "type": "Feature",
  "properties": {
    "addr:full":"3124 W Mcgraw St Seattle WA 98199",
    "addr:housenumber":"3124",
    "addr:postcode":"98199",
    "addr:street":"W Mcgraw St",
    "iso:country":"US",
    "sg:address":"3124 W Mcgraw St",
    "sg:city":"Seattle",
    "sg:classifiers":[
        {
            "category":"Social Services",
            "type":"Services"
        },
        {
            "category":"Professional",
            "subcategory":"Employment Agencies",
            "type":"Services"
        }
    ],
    "sg:phone":"+1 206 706 2859",
    "sg:postcode":"98199",
    "sg:province":"WA",
    "sg:tags":[
        "workers'",
        "placement",
        "volunteer"
    ],
    "wof:name":"Danny Schneller Foundation",
    "wof:placetype":"venue"
},
  "geometry": {"coordinates":[-122.39731999999999,47.639548],"type":"Point"}
}