{
  "type": "Feature",
  "properties": {
    "addr:full":"220 E Wellesley Ave 109A Spokane WA 99207",
    "addr:housenumber":"220;109a",
    "addr:postcode":"99207",
    "addr:street":"E Wellesley Ave",
    "iso:country":"US",
    "sg:address":"220 E Wellesley Ave 109A",
    "sg:city":"Spokane",
    "sg:classifiers":[
        {
            "category":"Health Services",
            "subcategory":"Doctor",
            "type":"Services"
        }
    ],
    "sg:phone":"+1 509 484 6276",
    "sg:postcode":"99207",
    "sg:province":"WA",
    "sg:tags":[
        "physician",
        "surgeon",
        "radiology",
        "surgeons",
        "pediatrics-radiology"
    ],
    "wof:name":"V Patrick Hughes Md",
    "wof:placetype":"venue"
},
  "geometry": {"coordinates":[-117.407028,47.700725],"type":"Point"}
}