{
  "type": "Feature",
  "properties": {
    "addr:full":"10707 Pacific Ave S #D Tacoma WA 98444",
    "addr:housenumber":"10707",
    "addr:postcode":"98444",
    "addr:street":"Pacific Ave S # D",
    "iso:country":"US",
    "sg:address":"10707 Pacific Ave S #D",
    "sg:city":"Tacoma",
    "sg:classifiers":[
        {
            "category":"Banks & Credit Unions",
            "subcategory":"Financial Services",
            "type":"Services"
        }
    ],
    "sg:phone":"+1 253 537 2234",
    "sg:postcode":"98444",
    "sg:province":"WA",
    "sg:tags":[
        "cashing",
        "loan",
        "payday",
        "alternative",
        "check"
    ],
    "sg:website":"http://www.acecashexpress.com",
    "wof:name":"ACE Cash Express",
    "wof:placetype":"venue"
},
  "geometry": {"coordinates":[-122.434228,47.15991],"type":"Point"}
}