{
  "type": "Feature",
  "properties": {
    "addr:full":"12733 Lake City Way NE Ste 201 Seattle WA 98125",
    "addr:housenumber":"12733",
    "addr:postcode":"98125",
    "addr:street":"Lake City Way Ne Ste 201",
    "iso:country":"US",
    "sg:address":"12733 Lake City Way NE Ste 201",
    "sg:city":"Seattle",
    "sg:classifiers":[
        {
            "category":"Health Services",
            "subcategory":"Dentist",
            "type":"Services"
        }
    ],
    "sg:phone":"+1 206 365 2244",
    "sg:postcode":"98125",
    "sg:province":"WA",
    "wof:name":"Seng Yea DDS",
    "wof:placetype":"venue"
},
  "geometry": {"coordinates":[-122.293972,47.721264],"type":"Point"}
}