{
  "type": "Feature",
  "properties": {
    "iso:country":"US",
    "sg:address":"1011 Colchester Dr E",
    "sg:city":"Port Orchard",
    "sg:classifiers":[
        {
            "category":"Banks & Credit Unions",
            "subcategory":"Financial Services",
            "type":"Services"
        }
    ],
    "sg:phone":"+1 360 871 6163",
    "sg:postcode":"98366",
    "sg:province":"WA",
    "sg:tags":[
        "trust",
        "investment",
        "real estate"
    ],
    "wof:name":"Patrick Projects LLC",
    "wof:placetype":"venue"
},
  "geometry": {"coordinates":[-122.541253,47.542906],"type":"Point"}
}