{
  "type": "Feature",
  "properties": {
    "addr:full":"904 S 50th Ave Yakima WA 98908",
    "addr:housenumber":"904",
    "addr:postcode":"98908",
    "addr:street":"S 50Th Ave",
    "iso:country":"US",
    "sg:address":"904 S 50th Ave",
    "sg:city":"Yakima",
    "sg:classifiers":[
        {
            "category":"Real Estate",
            "subcategory":"Real Estate Operator",
            "type":"Services"
        }
    ],
    "sg:phone":"+1 509 965 4716",
    "sg:postcode":"98908",
    "sg:province":"WA",
    "sg:tags":[
        "apartment"
    ],
    "wof:name":"Ford Property Imp",
    "wof:placetype":"venue"
},
  "geometry": {"coordinates":[-120.574493,46.58897],"type":"Point"}
}