{
  "type": "Feature",
  "properties": {
    "addr:full":"2535 Crites St SW Ste 3 Tumwater WA 98512",
    "addr:postcode":"2535;98512",
    "addr:street":"Crites St Sw Ste 3",
    "iso:country":"US",
    "sg:address":"2535 Crites St SW Ste 3",
    "sg:city":"Tumwater",
    "sg:classifiers":[
        {
            "category":"Food & Beverages",
            "subcategory":"Liquor & Beverages",
            "type":"Retail Goods"
        },
        {
            "category":"Wholesale",
            "subcategory":"Wine & Distilled Alcoholic Beverages",
            "type":"Manufacturing & Wholesale Goods"
        }
    ],
    "sg:phone":"+1 360 704 3364",
    "sg:postcode":"98512",
    "sg:province":"WA",
    "sg:tags":[
        "broker"
    ],
    "sg:website":"http://www.viniferaimports.com",
    "wof:name":"Vinifera Northwest",
    "wof:placetype":"venue"
},
  "geometry": {"coordinates":[-122.946375,47.023986],"type":"Point"}
}