{
  "type": "Feature",
  "properties": {
    "addr:full":"18325 N Atlantic Rd Colbert WA 99005",
    "addr:housenumber":"18325",
    "addr:postcode":"99005",
    "addr:street":"N Atlantic Rd Colbert",
    "iso:country":"US",
    "sg:address":"18325 N Atlantic Rd",
    "sg:city":"Colbert",
    "sg:classifiers":[
        {
            "category":"Building & Trades",
            "subcategory":"Construction",
            "type":"Services"
        }
    ],
    "sg:phone":"+1 509 466 7495",
    "sg:postcode":"99005",
    "sg:province":"WA",
    "sg:tags":[
        "house"
    ],
    "wof:name":"Rudys Remodel Design Co",
    "wof:placetype":"venue"
},
  "geometry": {"coordinates":[-117.413224,47.823915],"type":"Point"}
}