{
  "type": "Feature",
  "properties": {
    "addr:full":"10423 2nd Ave S Seattle WA 98168",
    "addr:housenumber":"10423",
    "addr:postcode":"98168",
    "addr:street":"2Nd Ave S",
    "iso:country":"US",
    "sg:address":"10423 2nd Ave S",
    "sg:city":"Seattle",
    "sg:classifiers":[
        {
            "category":"Manufacturing",
            "subcategory":"Tools & Machinery",
            "type":"Manufacturing & Wholesale Goods"
        }
    ],
    "sg:phone":"+1 206 433 8275",
    "sg:postcode":"98168",
    "sg:province":"WA",
    "sg:tags":[
        "product",
        "mfg",
        "food",
        "baker",
        "supply",
        "equipment"
    ],
    "wof:name":"R&R Service",
    "wof:placetype":"venue"
},
  "geometry": {"coordinates":[-122.33111100000001,47.509632],"type":"Point"}
}