{
  "type": "Feature",
  "properties": {
    "addr:full":"2217 NE 139th St Vancouver WA 98686",
    "addr:housenumber":"2217",
    "addr:postcode":"98686",
    "addr:street":"Ne 139Th St",
    "iso:country":"US",
    "sg:address":"2217 NE 139th St",
    "sg:city":"Vancouver",
    "sg:classifiers":[
        {
            "category":"Building & Trades",
            "subcategory":"Electrical",
            "type":"Services"
        }
    ],
    "sg:phone":"+1 360 576 9700",
    "sg:postcode":"98686",
    "sg:province":"WA",
    "sg:tags":[
        "electric",
        "contractor"
    ],
    "wof:name":"Electrix",
    "wof:placetype":"venue"
},
  "geometry": {"coordinates":[-122.650308,45.721787],"type":"Point"}
}