{
  "type": "Feature",
  "properties": {
    "addr:full":"14020 NE 62nd St Redmond WA 98052",
    "addr:housenumber":"14020",
    "addr:postcode":"98052",
    "addr:street":"Ne 62Nd St",
    "iso:country":"US",
    "sg:address":"14020 NE 62nd St",
    "sg:city":"Redmond",
    "sg:classifiers":[
        {
            "category":"Building & Trades",
            "subcategory":"Locksmith",
            "type":"Services"
        }
    ],
    "sg:phone":"+1 425 636 1576",
    "sg:postcode":"98052",
    "sg:province":"WA",
    "sg:tags":[
        "key"
    ],
    "wof:name":"America 24 Hour Locksmith",
    "wof:placetype":"venue"
},
  "geometry": {"coordinates":[-122.15276799999999,47.662558],"type":"Point"}
}