{
  "type": "Feature",
  "properties": {
    "addr:full":"100 4th Ave N Seattle WA 98109",
    "addr:housenumber":"100",
    "addr:postcode":"98109",
    "addr:street":"4Th Ave N",
    "iso:country":"US",
    "sg:address":"100 4th Ave N",
    "sg:city":"Seattle",
    "sg:classifiers":[
        {
            "category":"Wholesale",
            "subcategory":"Books, Periodicals, & Newspapers",
            "type":"Manufacturing & Wholesale Goods"
        },
        {
            "category":"Communications",
            "subcategory":"Television Station",
            "type":"Services"
        }
    ],
    "sg:phone":"+1 206 448 3915",
    "sg:postcode":"98109",
    "sg:province":"WA",
    "sg:tags":[
        "dealers-wholesale",
        "broadcast",
        "representative",
        "news"
    ],
    "wof:name":"Khcv Tv",
    "wof:placetype":"venue"
},
  "geometry": {"coordinates":[-122.34893,47.61858],"type":"Point"}
}