{
  "type": "Feature",
  "properties": {
    "iso:country":"US",
    "sg:address":"2918 Hoyt Ave",
    "sg:city":"Everett",
    "sg:classifiers":[
        {
            "category":"Shopping",
            "subcategory":"Music",
            "type":"Retail Goods"
        }
    ],
    "sg:phone":"+1 425 339 3681",
    "sg:postcode":"98201",
    "sg:province":"WA",
    "wof:name":"Sound Music",
    "wof:placetype":"venue"
},
  "geometry": {"coordinates":[-122.210077,47.978096],"type":"Point"}
}