{
  "type": "Feature",
  "properties": {
    "addr:full":"16035 Mink Rd NE Woodinville WA 98077",
    "addr:housenumber":"16035",
    "addr:postcode":"98077",
    "addr:street":"Mink Rd Ne",
    "iso:country":"US",
    "sg:address":"16035 Mink Rd NE",
    "sg:city":"Woodinville",
    "sg:classifiers":[
        {
            "category":"Social Services",
            "subcategory":"Child Care",
            "type":"Services"
        }
    ],
    "sg:phone":"+1 425 788 2399",
    "sg:postcode":"98077",
    "sg:province":"WA",
    "sg:tags":[
        "day"
    ],
    "wof:name":"Cye Learning Center",
    "wof:placetype":"venue"
},
  "geometry": {"coordinates":[-122.067396,47.743998],"type":"Point"}
}