{
  "type": "Feature",
  "properties": {
    "addr:full":"400 Pine St Seattle WA 98101",
    "addr:housenumber":"400",
    "addr:postcode":"98101",
    "addr:street":"Pine St",
    "iso:country":"US",
    "sg:address":"400 Pine St",
    "sg:city":"Seattle",
    "sg:phone":"+1 206 393 0070",
    "sg:postcode":"98101",
    "sg:province":"WA",
    "sg:website":"http://www.pfchangs.com/",
    "wof:name":"P.F. Chang's China Bistro",
    "wof:placetype":"venue"
},
  "geometry": {"coordinates":[-122.33766199999999,47.611179],"type":"Point"}
}