{
  "type": "Feature",
  "properties": {
    "addr:full":"1815 SE Cutter Ln Vancouver WA 98661",
    "addr:housenumber":"1815",
    "addr:postcode":"98661",
    "addr:street":"Se Cutter Ln",
    "iso:country":"US",
    "sg:address":"1815 SE Cutter Ln",
    "sg:city":"Vancouver",
    "sg:classifiers":[
        {
            "category":"Professional",
            "type":"Services"
        }
    ],
    "sg:phone":"+1 360 397 4414",
    "sg:postcode":"98661",
    "sg:province":"WA",
    "wof:name":"R Litton Ej Plesko",
    "wof:placetype":"venue"
},
  "geometry": {"coordinates":[-122.652182,45.616456],"type":"Point"}
}