{
  "type": "Feature",
  "properties": {
    "addr:full":"3604 106th Avenue Ct E Edgewood WA 98372",
    "addr:housenumber":"3604",
    "addr:postcode":"98372",
    "addr:street":"106Th Avenue Ct E",
    "iso:country":"US",
    "sg:address":"3604 106th Avenue Ct E",
    "sg:city":"Edgewood",
    "sg:classifiers":[
        {
            "category":"Building & Trades",
            "subcategory":"Plumbing",
            "type":"Services"
        }
    ],
    "sg:phone":"+1 253 445 8503",
    "sg:postcode":"98372",
    "sg:province":"WA",
    "sg:tags":[
        "plumbing",
        "contractor"
    ],
    "wof:name":"Total Plumbing",
    "wof:placetype":"venue"
},
  "geometry": {"coordinates":[-122.28794499999999,47.224552],"type":"Point"}
}