{
  "type": "Feature",
  "properties": {
    "addr:full":"6006 Barr Rd Ferndale WA 98248",
    "addr:housenumber":"6006",
    "addr:postcode":"98248",
    "addr:street":"Barr Rd",
    "iso:country":"US",
    "sg:address":"6006 Barr Rd",
    "sg:city":"Ferndale",
    "sg:classifiers":[
        {
            "category":"Shopping",
            "subcategory":"Music",
            "type":"Retail Goods"
        }
    ],
    "sg:phone":"+1 360 384 4845",
    "sg:postcode":"98248",
    "sg:province":"WA",
    "wof:name":"Camelot Record Co",
    "wof:placetype":"venue"
},
  "geometry": {"coordinates":[-122.649428,48.860695],"type":"Point"}
}