{
  "type": "Feature",
  "properties": {
    "addr:full":"7900 Green Lake Dr N Seattle WA 98103",
    "addr:housenumber":"7900",
    "addr:postcode":"98103",
    "addr:street":"Green Lake Dr N",
    "iso:country":"US",
    "sg:address":"7900 Green Lake Dr N",
    "sg:city":"Seattle",
    "sg:classifiers":[
        {
            "category":"Restaurant",
            "type":"Food & Drink"
        }
    ],
    "sg:phone":"+1 206 524 3985",
    "sg:postcode":"98103",
    "sg:province":"WA",
    "wof:name":"Bluewater Greenlake",
    "wof:placetype":"venue"
},
  "geometry": {"coordinates":[-122.339015,47.686361],"type":"Point"}
}