{
  "type": "Feature",
  "properties": {
    "addr:full":"3275 State Rte 9 Sedro Woolley WA 98284",
    "addr:housenumber":"3275",
    "addr:postcode":"98284",
    "addr:street":"State Rte 9",
    "iso:country":"US",
    "sg:address":"3275 State Rte 9",
    "sg:city":"Sedro Woolley",
    "sg:classifiers":[
        {
            "category":"Personal",
            "type":"Services"
        }
    ],
    "sg:phone":"+1 360 855 0249",
    "sg:postcode":"98284",
    "sg:province":"WA",
    "wof:name":"Sunworks",
    "wof:placetype":"venue"
},
  "geometry": {"coordinates":[-122.224186,48.583687],"type":"Point"}
}