{
  "type": "Feature",
  "properties": {
    "addr:full":"315 1st Ave W Seattle WA 98119",
    "addr:housenumber":"315",
    "addr:postcode":"98119",
    "addr:street":"1St Ave W",
    "iso:country":"US",
    "sg:address":"315 1st Ave W",
    "sg:city":"Seattle",
    "sg:classifiers":[
        {
            "category":"Sports & Exercise",
            "subcategory":"Gym",
            "type":"Entertainment"
        }
    ],
    "sg:phone":"+1 206 270 9642",
    "sg:postcode":"98119",
    "sg:province":"WA",
    "sg:tags":[
        "yoga"
    ],
    "sg:website":"www.homeyogaseattle.com",
    "wof:name":"Home Yoga and Wellness Center",
    "wof:placetype":"venue"
},
  "geometry": {"coordinates":[-122.358419,47.621447],"type":"Point"}
}