{
  "type": "Feature",
  "properties": {
    "iso:country":"US",
    "sg:address":"4101 Wishkah Rd",
    "sg:city":"Aberdeen",
    "sg:classifiers":[
        {
            "category":"Building & Trades",
            "subcategory":"Landscaping Services",
            "type":"Services"
        }
    ],
    "sg:phone":"+1 360 532 8115",
    "sg:postcode":"98520",
    "sg:province":"WA",
    "sg:tags":[
        "lawn",
        "maintenance",
        "grounds"
    ],
    "wof:name":"Two Gardeners",
    "wof:placetype":"venue"
},
  "geometry": {"coordinates":[-123.768879,47.07895],"type":"Point"}
}