{
  "type": "Feature",
  "properties": {
    "addr:full":"304 NE 12th St Battle Ground WA 98604",
    "addr:housenumber":"304",
    "addr:postcode":"98604",
    "addr:street":"Ne 12Th St",
    "iso:country":"US",
    "sg:address":"304 NE 12th St",
    "sg:city":"Battle Ground",
    "sg:classifiers":[
        {
            "category":"Wholesale",
            "subcategory":"Electrical",
            "type":"Manufacturing & Wholesale Goods"
        }
    ],
    "sg:phone":"+1 360 607 6992",
    "sg:postcode":"98604",
    "sg:province":"WA",
    "sg:tags":[
        "equipment"
    ],
    "wof:name":"Columbia Signaling Systems",
    "wof:placetype":"venue"
},
  "geometry": {"coordinates":[-122.532118,45.789753],"type":"Point"}
}