{
  "type": "Feature",
  "properties": {
    "iso:country":"US",
    "sg:address":"6737 Littlerock Rd SW",
    "sg:city":"Olympia",
    "sg:classifiers":[
        {
            "category":"Professional",
            "subcategory":"Accounting & Tax Preparation",
            "type":"Services"
        }
    ],
    "sg:phone":"+1 360 754 8732",
    "sg:postcode":"98512",
    "sg:province":"WA",
    "sg:tags":[
        "return"
    ],
    "wof:name":"Cascade Tax Service Co",
    "wof:placetype":"venue"
},
  "geometry": {"coordinates":[-122.93091800000001,46.98675],"type":"Point"}
}