{
  "type": "Feature",
  "properties": {
    "addr:full":"10991 Central Valley Rd NE Poulsbo WA 98370",
    "addr:housenumber":"10991",
    "addr:postcode":"98370",
    "addr:street":"Central Valley Rd Ne",
    "iso:country":"US",
    "sg:address":"10991 Central Valley Rd NE",
    "sg:city":"Poulsbo",
    "sg:classifiers":[
        {
            "category":"Social Services",
            "subcategory":"Child Care",
            "type":"Services"
        }
    ],
    "sg:phone":"+1 360 337 2100",
    "sg:postcode":"98370",
    "sg:province":"WA",
    "sg:tags":[
        "day"
    ],
    "wof:name":"Playcare",
    "wof:placetype":"venue"
},
  "geometry": {"coordinates":[-122.65026899999999,47.66145],"type":"Point"}
}