{
  "type": "Feature",
  "properties": {
    "addr:full":"723 5th Ave S Kent WA 98032",
    "addr:housenumber":"723",
    "addr:postcode":"98032",
    "addr:street":"5Th Ave S",
    "iso:country":"US",
    "sg:address":"723 5th Ave S",
    "sg:city":"Kent",
    "sg:classifiers":[
        {
            "category":"Home & Garden",
            "subcategory":"Carpets & Floor Coverings",
            "type":"Retail Goods"
        }
    ],
    "sg:phone":"+1 206 354 6978",
    "sg:postcode":"98032",
    "sg:province":"WA",
    "wof:name":"Db Floor Covering",
    "wof:placetype":"venue"
},
  "geometry": {"coordinates":[-122.238775,47.376099],"type":"Point"}
}