{
  "type": "Feature",
  "properties": {
    "addr:full":"12188 Cloudy Peak Ln NW Silverdale WA 98383",
    "addr:postcode":"12188;98383",
    "addr:street":"Cloudy Peak Ln Nw",
    "iso:country":"US",
    "sg:address":"12188 Cloudy Peak Ln NW",
    "sg:city":"Silverdale",
    "sg:classifiers":[
        {
            "category":"Real Estate",
            "subcategory":"Real Estate Operator",
            "type":"Services"
        }
    ],
    "sg:phone":"+1 360 697 6111",
    "sg:postcode":"98383",
    "sg:province":"WA",
    "sg:tags":[
        "building",
        "apartment"
    ],
    "sg:website":"www.theoutlook.com",
    "wof:name":"Outlook Apartments The",
    "wof:placetype":"venue"
},
  "geometry": {"coordinates":[-122.67161299999999,47.671431],"type":"Point"}
}