{
  "type": "Feature",
  "properties": {
    "addr:full":"4601 E 18th St Apt 149 Vancouver WA 98661",
    "addr:housenumber":"4601;149",
    "addr:postcode":"98661",
    "addr:street":"E 18Th St Apt",
    "iso:country":"US",
    "sg:address":"4601 E 18th St Apt 149",
    "sg:city":"Vancouver",
    "sg:classifiers":[
        {
            "category":"Communications",
            "subcategory":"Film & Video Production",
            "type":"Services"
        }
    ],
    "sg:phone":"+1 360 694 1479",
    "sg:postcode":"98661",
    "sg:province":"WA",
    "sg:tags":[
        "services-commercial"
    ],
    "wof:name":"Fischer Video Productions",
    "wof:placetype":"venue"
},
  "geometry": {"coordinates":[-122.621236,45.634779],"type":"Point"}
}