{
  "type": "Feature",
  "properties": {
    "addr:full":"21901 NE 122nd St Brush Prairie WA 98606",
    "addr:housenumber":"21901",
    "addr:postcode":"98606",
    "addr:street":"Ne 122Nd St",
    "iso:country":"US",
    "sg:address":"21901 NE 122nd St",
    "sg:city":"Brush Prairie",
    "sg:classifiers":[
        {
            "category":"Manufacturing",
            "subcategory":"Tools & Machinery",
            "type":"Manufacturing & Wholesale Goods"
        }
    ],
    "sg:phone":"+1 360 892 8386",
    "sg:postcode":"98606",
    "sg:province":"WA",
    "sg:tags":[
        "bulb",
        "lamp"
    ],
    "wof:name":"Spectrum Lighting",
    "wof:placetype":"venue"
},
  "geometry": {"coordinates":[-122.44893,45.710236],"type":"Point"}
}