{
  "type": "Feature",
  "properties": {
    "addr:full":"14110 339th Ave SE Sultan WA 98294",
    "addr:housenumber":"14110",
    "addr:postcode":"98294",
    "addr:street":"339Th Ave Se Sultan",
    "iso:country":"US",
    "sg:address":"14110 339th Ave SE",
    "sg:city":"Sultan",
    "sg:classifiers":[
        {
            "category":"Autos & Motor Vehicles",
            "subcategory":"Motorcycle Sales",
            "type":"Retail Goods"
        }
    ],
    "sg:phone":"+1 360 793 2196",
    "sg:postcode":"98294",
    "sg:province":"WA",
    "sg:tags":[
        "scooter"
    ],
    "wof:name":"Flower Racing",
    "wof:placetype":"venue"
},
  "geometry": {"coordinates":[-121.777688,47.870385],"type":"Point"}
}