{
  "type": "Feature",
  "properties": {
    "addr:full":"2726 Black Lake Blvd SW Olympia WA 98512",
    "addr:housenumber":"2726",
    "addr:postcode":"98512",
    "addr:street":"Black Lake Blvd Sw",
    "iso:country":"US",
    "sg:address":"2726 Black Lake Blvd SW",
    "sg:city":"Olympia",
    "sg:classifiers":[
        {
            "category":"Retail",
            "subcategory":"Repair Shop",
            "type":"Services"
        }
    ],
    "sg:phone":"+1 360 753 4943",
    "sg:postcode":"98512",
    "sg:province":"WA",
    "sg:tags":[
        "scooter",
        "motorcycle",
        "motor"
    ],
    "wof:name":"R & R Motors Inc",
    "wof:placetype":"venue"
},
  "geometry": {"coordinates":[-122.95545,47.024065],"type":"Point"}
}