{
  "type": "Feature",
  "properties": {
    "addr:full":"5950 Conner Rd Fruitland WA 99129",
    "addr:housenumber":"5950",
    "addr:postcode":"99129",
    "addr:street":"Conner Rd",
    "iso:country":"US",
    "sg:address":"5950 Conner Rd",
    "sg:city":"Fruitland",
    "sg:classifiers":[
        {
            "category":"Retail",
            "subcategory":"Repair Shop",
            "type":"Services"
        }
    ],
    "sg:phone":"+1 509 722 5990",
    "sg:postcode":"99129",
    "sg:province":"WA",
    "wof:name":"Grizs Custom & Repair",
    "wof:placetype":"venue"
},
  "geometry": {"coordinates":[-118.128086,48.078235],"type":"Point"}
}