{
  "type": "Feature",
  "properties": {
    "addr:full":"51 E Roanoke St Seattle WA 98102",
    "addr:housenumber":"51",
    "addr:postcode":"98102",
    "addr:street":"E Roanoke St",
    "iso:country":"US",
    "sg:address":"51 E Roanoke St",
    "sg:city":"Seattle",
    "sg:classifiers":[
        {
            "category":"Professional",
            "subcategory":"Lawyer & Legal Services",
            "type":"Services"
        }
    ],
    "sg:phone":"+1 206 322 1150",
    "sg:postcode":"98102",
    "sg:province":"WA",
    "sg:tags":[
        "attorney"
    ],
    "wof:name":"Ben Hankin",
    "wof:placetype":"venue"
},
  "geometry": {"coordinates":[-122.327934,47.643116],"type":"Point"}
}