{
  "type": "Feature",
  "properties": {
    "addr:full":"959 11th Ave Longview WA 98632",
    "addr:housenumber":"959",
    "addr:postcode":"98632",
    "addr:street":"11Th Ave",
    "iso:country":"US",
    "sg:address":"959 11th Ave",
    "sg:city":"Longview",
    "sg:classifiers":[
        {
            "category":"Professional",
            "subcategory":"Accounting & Tax Preparation",
            "type":"Services"
        }
    ],
    "sg:phone":"+1 360 425 2000",
    "sg:postcode":"98632",
    "sg:province":"WA",
    "wof:name":"Lucie R Carter CPA",
    "wof:placetype":"venue"
},
  "geometry": {"coordinates":[-122.93424400000001,46.130441],"type":"Point"}
}