{
  "type": "Feature",
  "properties": {
    "addr:full":"5112 NW Taylor Rd Bremerton WA 98312",
    "addr:housenumber":"5112",
    "addr:postcode":"98312",
    "addr:street":"Nw Taylor Rd",
    "iso:country":"US",
    "sg:address":"5112 NW Taylor Rd",
    "sg:city":"Bremerton",
    "sg:classifiers":[
        {
            "category":"Professional",
            "type":"Services"
        }
    ],
    "sg:phone":"+1 360 373 2510",
    "sg:postcode":"98312",
    "sg:province":"WA",
    "sg:tags":[
        "establishment"
    ],
    "wof:name":"Growing Place",
    "wof:placetype":"venue"
},
  "geometry": {"coordinates":[-122.717274,47.586391],"type":"Point"}
}