{
  "type": "Feature",
  "properties": {
    "addr:full":"5810 W Clearwater Ave Kennewick WA 99336",
    "addr:housenumber":"5810",
    "addr:postcode":"99336",
    "addr:street":"W Clearwater Ave",
    "iso:country":"US",
    "sg:address":"5810 W Clearwater Ave",
    "sg:city":"Kennewick",
    "sg:classifiers":[
        {
            "category":"Professional",
            "subcategory":"Business Services",
            "type":"Services"
        }
    ],
    "sg:phone":"+1 509 764 9999",
    "sg:postcode":"99336",
    "sg:province":"WA",
    "wof:name":"All City Bail Bonds",
    "wof:placetype":"venue"
},
  "geometry": {"coordinates":[-119.201049,46.212513],"type":"Point"}
}