{
  "type": "Feature",
  "properties": {
    "addr:full":"18225 Dew Drop Ln NW Poulsbo WA 98370",
    "addr:housenumber":"18225",
    "addr:postcode":"98370",
    "addr:street":"Dew Drop Ln Nw",
    "iso:country":"US",
    "sg:address":"18225 Dew Drop Ln NW",
    "sg:city":"Poulsbo",
    "sg:classifiers":[
        {
            "category":"Building & Trades",
            "subcategory":"Construction",
            "type":"Services"
        }
    ],
    "sg:phone":"+1 360 697 9489",
    "sg:postcode":"98370",
    "sg:province":"WA",
    "sg:tags":[
        "hanging",
        "contractor"
    ],
    "wof:name":"Rhoades Drywall & Painting",
    "wof:placetype":"venue"
},
  "geometry": {"coordinates":[-122.680318,47.728284],"type":"Point"}
}