{
  "type": "Feature",
  "properties": {
    "iso:country":"US",
    "sg:address":"112 Basin St SW",
    "sg:city":"Ephrata",
    "sg:classifiers":[
        {
            "category":"Recreation",
            "type":"Entertainment"
        }
    ],
    "sg:phone":"+1 509 754 4426",
    "sg:postcode":"98823",
    "sg:province":"WA",
    "sg:tags":[
        "parks"
    ],
    "wof:name":"Ephrata Recreation Dept",
    "wof:placetype":"venue"
},
  "geometry": {"coordinates":[-119.552374,47.319494],"type":"Point"}
}