{
  "type": "Feature",
  "properties": {
    "iso:country":"US",
    "sg:address":"116 N Tacoma Ave",
    "sg:city":"Tacoma",
    "sg:classifiers":[
        {
            "category":"Autos & Motor Vehicles",
            "subcategory":"Fuel & Gas Station",
            "type":"Retail Goods"
        }
    ],
    "sg:phone":"+1 253 272 3562",
    "sg:postcode":"98403",
    "sg:province":"WA",
    "sg:tags":[
        "automobile",
        "station",
        "gasoline",
        "used"
    ],
    "wof:name":"Ball Auto Sales & Service Inc",
    "wof:placetype":"venue"
},
  "geometry": {"coordinates":[-122.449725,47.264911],"type":"Point"}
}