{
  "type": "Feature",
  "properties": {
    "addr:full":"223 State St Sedro Woolley WA 98284",
    "addr:housenumber":"223",
    "addr:postcode":"98284",
    "addr:street":"State St",
    "iso:country":"US",
    "sg:address":"223 State St",
    "sg:city":"Sedro Woolley",
    "sg:classifiers":[
        {
            "category":"Real Estate",
            "subcategory":"Real Estate Agent",
            "type":"Services"
        }
    ],
    "sg:phone":"+1 360 855 9437",
    "sg:postcode":"98284",
    "sg:province":"WA",
    "wof:name":"Philip A Murray",
    "wof:placetype":"venue"
},
  "geometry": {"coordinates":[-122.237447,48.503316],"type":"Point"}
}