{
  "type": "Feature",
  "properties": {
    "addr:full":"1216 50th St SE Everett WA 98203",
    "addr:housenumber":"1216",
    "addr:postcode":"98203",
    "addr:street":"50Th St Se",
    "iso:country":"US",
    "sg:address":"1216 50th St SE",
    "sg:city":"Everett",
    "sg:classifiers":[
        {
            "category":"Manufacturing",
            "subcategory":"Printing",
            "type":"Manufacturing & Wholesale Goods"
        }
    ],
    "sg:phone":"+1 425 339 1122",
    "sg:postcode":"98203",
    "sg:province":"WA",
    "sg:tags":[
        "printer",
        "commercial",
        "offset"
    ],
    "wof:name":"Evergreen Copy Service",
    "wof:placetype":"venue"
},
  "geometry": {"coordinates":[-122.211096,47.951543],"type":"Point"}
}