{
  "type": "Feature",
  "properties": {
    "iso:country":"US",
    "sg:address":"8619 Ravenna Ave NE",
    "sg:city":"Seattle",
    "sg:classifiers":[
        {
            "category":"Professional",
            "type":"Services"
        }
    ],
    "sg:phone":"+1 206 406 0987",
    "sg:postcode":"98115",
    "sg:province":"WA",
    "wof:name":"Rental Turnover Services",
    "wof:placetype":"venue"
},
  "geometry": {"coordinates":[-122.302442,47.691982],"type":"Point"}
}