{
  "type": "Feature",
  "properties": {
    "addr:full":"3217 Squalicum Pkwy Bellingham WA 98226",
    "addr:housenumber":"3217",
    "addr:postcode":"98226",
    "addr:street":"Squalicum Pkwy",
    "iso:country":"US",
    "sg:address":"3217 Squalicum Pkwy",
    "sg:city":"Bellingham",
    "sg:classifiers":[
        {
            "category":"Organizations",
            "subcategory":"Non-profit Organization",
            "type":"Services"
        }
    ],
    "sg:phone":"+1 360 738 6706",
    "sg:postcode":"98226",
    "sg:province":"WA",
    "sg:tags":[
        "social"
    ],
    "wof:name":"American Cancer Society",
    "wof:placetype":"venue"
},
  "geometry": {"coordinates":[-122.472168,48.77221],"type":"Point"}
}