{
  "type": "Feature",
  "properties": {
    "addr:full":"2339 Franklin Ave E Seattle WA 98102",
    "addr:housenumber":"2339",
    "addr:postcode":"98102",
    "addr:street":"Franklin Ave E",
    "iso:country":"US",
    "sg:address":"2339 Franklin Ave E",
    "sg:city":"Seattle",
    "sg:classifiers":[
        {
            "category":"Professional",
            "subcategory":"Business Services",
            "type":"Services"
        }
    ],
    "sg:phone":"+1 206 322 2226",
    "sg:postcode":"98102",
    "sg:province":"WA",
    "wof:name":"Zen Couriers",
    "wof:placetype":"venue"
},
  "geometry": {"coordinates":[-122.324752,47.641585],"type":"Point"}
}