{
  "type": "Feature",
  "properties": {
    "addr:full":"615 Boren Ave Apt 9 Seattle WA 98104",
    "addr:housenumber":"615;9",
    "addr:postcode":"98104",
    "addr:street":"Boren Ave Apt",
    "iso:country":"US",
    "sg:address":"615 Boren Ave Apt 9",
    "sg:city":"Seattle",
    "sg:classifiers":[
        {
            "category":"Professional",
            "subcategory":"Computer Services",
            "type":"Services"
        }
    ],
    "sg:phone":"+1 206 324 4790",
    "sg:postcode":"98104",
    "sg:province":"WA",
    "sg:tags":[
        "graphic"
    ],
    "sg:website":"http://www.atomized.ca",
    "wof:name":"Atomized Productions & Servi",
    "wof:placetype":"venue"
},
  "geometry": {"coordinates":[-122.322658,47.606571],"type":"Point"}
}