{
  "type": "Feature",
  "properties": {
    "iso:country":"US",
    "sg:address":"944 Court E",
    "sg:city":"Tacoma",
    "sg:classifiers":[
        {
            "category":"Social Services",
            "type":"Services"
        }
    ],
    "sg:phone":"+1 253 209 1999",
    "sg:postcode":"98402",
    "sg:province":"WA",
    "sg:tags":[
        "counselor",
        "marriage",
        "family"
    ],
    "wof:name":"Mitchell Counseling & Consult",
    "wof:placetype":"venue"
},
  "geometry": {"coordinates":[-122.443828,47.253289],"type":"Point"}
}