{
  "type": "Feature",
  "properties": {
    "addr:full":"1430 Pioneer Hwy Stanwood WA 98292",
    "addr:housenumber":"1430",
    "addr:postcode":"98292",
    "addr:street":"Pioneer Hwy",
    "iso:country":"US",
    "sg:address":"1430 Pioneer Hwy",
    "sg:city":"Stanwood",
    "sg:classifiers":[
        {
            "category":"Government",
            "subcategory":"Office",
            "type":"Public Place"
        }
    ],
    "sg:phone":"+1 360 652 8277",
    "sg:postcode":"98292",
    "sg:province":"WA",
    "sg:tags":[
        "executive"
    ],
    "wof:name":"Silvana Fire Dept",
    "wof:placetype":"venue"
},
  "geometry": {"coordinates":[-122.256578,48.222497],"type":"Point"}
}