{
  "type": "Feature",
  "properties": {
    "addr:full":"11912 160th Ave SE Renton WA 98059",
    "addr:housenumber":"11912",
    "addr:postcode":"98059",
    "addr:street":"160Th Ave Se",
    "iso:country":"US",
    "sg:address":"11912 160th Ave SE",
    "sg:city":"Renton",
    "sg:classifiers":[
        {
            "category":"Manufacturing",
            "subcategory":"Buildings",
            "type":"Manufacturing & Wholesale Goods"
        },
        {
            "category":"Building & Trades",
            "subcategory":"Construction",
            "type":"Services"
        }
    ],
    "sg:phone":"+1 425 255 7077",
    "sg:postcode":"98059",
    "sg:province":"WA",
    "sg:tags":[
        "home",
        "builder",
        "contractor"
    ],
    "wof:name":"Higgins, Paul & Son's Construction",
    "wof:placetype":"venue"
},
  "geometry": {"coordinates":[-122.127402,47.495824],"type":"Point"}
}