{
  "type": "Feature",
  "properties": {
    "iso:country":"US",
    "sg:address":"1800 4th St",
    "sg:city":"Marysville",
    "sg:classifiers":[
        {
            "category":"Professional",
            "subcategory":"Computer Services",
            "type":"Services"
        }
    ],
    "sg:phone":"+1 360 651 2145",
    "sg:postcode":"98270",
    "sg:province":"WA",
    "sg:tags":[
        "consultant"
    ],
    "sg:website":"www.pci-ns.com",
    "wof:name":"PCI Software",
    "wof:placetype":"venue"
},
  "geometry": {"coordinates":[-122.169656,48.051815],"type":"Point"}
}