{
  "type": "Feature",
  "properties": {
    "addr:full":"2112 Black Lake Blvd SW Olympia WA 98512",
    "addr:housenumber":"2112",
    "addr:postcode":"98512",
    "addr:street":"Black Lake Blvd Sw",
    "iso:country":"US",
    "sg:address":"2112 Black Lake Blvd SW",
    "sg:city":"Olympia",
    "sg:classifiers":[
        {
            "category":"Banks & Credit Unions",
            "subcategory":"Bank",
            "type":"Services"
        }
    ],
    "sg:phone":"+1 360 923 0870",
    "sg:postcode":"98512",
    "sg:province":"WA",
    "sg:tags":[
        "mortgage"
    ],
    "sg:website":"www.pacmo.com",
    "wof:name":"Pacific Mortgage",
    "wof:placetype":"venue"
},
  "geometry": {"coordinates":[-122.948314,47.028391],"type":"Point"}
}