{
  "type": "Feature",
  "properties": {
    "addr:full":"4402 Lone Lake Rd Langley WA 98260",
    "addr:housenumber":"4402",
    "addr:postcode":"98260",
    "addr:street":"Lone Lake Rd",
    "iso:country":"US",
    "sg:address":"4402 Lone Lake Rd",
    "sg:city":"Langley",
    "sg:classifiers":[
        {
            "category":"Building & Trades",
            "subcategory":"Construction",
            "type":"Services"
        }
    ],
    "sg:phone":"+1 360 321 6040",
    "sg:postcode":"98260",
    "sg:province":"WA",
    "sg:tags":[
        "contractor"
    ],
    "wof:name":"Aley Iron Works",
    "wof:placetype":"venue"
},
  "geometry": {"coordinates":[-122.464651,48.050865],"type":"Point"}
}