{
  "type": "Feature",
  "properties": {
    "addr:full":"1407 116th Ave NE Bellevue WA 98004",
    "addr:housenumber":"1407",
    "addr:postcode":"98004",
    "addr:street":"116Th Ave Ne",
    "iso:country":"US",
    "sg:address":"1407 116th Ave NE",
    "sg:city":"Bellevue",
    "sg:classifiers":[
        {
            "category":"Professional",
            "subcategory":"Business Services",
            "type":"Services"
        }
    ],
    "sg:phone":"+1 425 455 2544",
    "sg:postcode":"98004",
    "sg:province":"WA",
    "sg:tags":[
        "interior",
        "consultant",
        "design",
        "decorator"
    ],
    "wof:name":"Design International",
    "wof:placetype":"venue"
},
  "geometry": {"coordinates":[-122.185738,47.625867],"type":"Point"}
}