{
  "type": "Feature",
  "properties": {
    "addr:full":"417 Wildcat St SE Lacey WA 98503",
    "addr:housenumber":"417",
    "addr:postcode":"98503",
    "addr:street":"Wildcat St Se",
    "iso:country":"US",
    "sg:address":"417 Wildcat St SE",
    "sg:city":"Lacey",
    "sg:classifiers":[
        {
            "category":"Shopping",
            "subcategory":"Crafts & Fabrics",
            "type":"Retail Goods"
        }
    ],
    "sg:phone":"+1 360 456 7316",
    "sg:postcode":"98503",
    "sg:province":"WA",
    "sg:tags":[
        "sewing"
    ],
    "wof:name":"Busy Fingers",
    "wof:placetype":"venue"
},
  "geometry": {"coordinates":[-122.785462,47.049295],"type":"Point"}
}