{
  "type": "Feature",
  "properties": {
    "addr:full":"612 SW 152nd St Burien WA 98166",
    "addr:housenumber":"612",
    "addr:postcode":"98166",
    "addr:street":"Sw 152Nd St",
    "iso:country":"US",
    "sg:address":"612 SW 152nd St",
    "sg:city":"Burien",
    "sg:classifiers":[
        {
            "category":"Personal",
            "subcategory":"Massage",
            "type":"Services"
        },
        {
            "category":"Health Services",
            "subcategory":"Chiropractor",
            "type":"Services"
        }
    ],
    "sg:phone":"+1 206 244 1466",
    "sg:postcode":"98166",
    "sg:province":"WA",
    "sg:tags":[
        "therapist",
        "chiropractic"
    ],
    "wof:name":"Moss Chiropractic",
    "wof:placetype":"venue"
},
  "geometry": {"coordinates":[-122.342174,47.466805],"type":"Point"}
}