{
  "type": "Feature",
  "properties": {
    "addr:full":"11215 Saskatoon Ln SE Olympia WA 98513",
    "addr:postcode":"11215;98513",
    "addr:street":"Saskatoon Ln Se",
    "iso:country":"US",
    "sg:address":"11215 Saskatoon Ln SE",
    "sg:city":"Olympia",
    "sg:classifiers":[
        {
            "category":"Social Services",
            "type":"Services"
        }
    ],
    "sg:phone":"+1 360 923 1286",
    "sg:postcode":"98513",
    "sg:province":"WA",
    "wof:name":"Suzanne Fairbrother PHD",
    "wof:placetype":"venue"
},
  "geometry": {"coordinates":[-122.702867,47.005944],"type":"Point"}
}