{
  "type": "Feature",
  "properties": {
    "addr:full":"10720 SE Carr Rd Renton WA 98055",
    "addr:housenumber":"10720",
    "addr:postcode":"98055",
    "addr:street":"Se Carr Rd",
    "iso:country":"US",
    "sg:address":"10720 SE Carr Rd",
    "sg:city":"Renton",
    "sg:classifiers":[
        {
            "category":"Restaurant",
            "type":"Food & Drink"
        }
    ],
    "sg:phone":"+1 425 254 1599",
    "sg:postcode":"98055",
    "sg:province":"WA",
    "sg:tags":[
        "sushi",
        "bar",
        "japanese",
        "pan",
        "asian"
    ],
    "wof:name":"New Zen Japanese Restaurant",
    "wof:placetype":"venue"
},
  "geometry": {"coordinates":[-122.197748,47.445254],"type":"Point"}
}