{
  "type": "Feature",
  "properties": {
    "addr:full":"715 School Rd Eastsound WA 98245",
    "addr:housenumber":"715",
    "addr:postcode":"98245",
    "addr:street":"School Rd",
    "iso:country":"US",
    "sg:address":"715 School Rd",
    "sg:city":"Eastsound",
    "sg:classifiers":[
        {
            "category":"Education",
            "subcategory":"School",
            "type":"Public Place"
        }
    ],
    "sg:phone":"+1 360 376 2287",
    "sg:postcode":"98245",
    "sg:province":"WA",
    "sg:website":"www.orcasislandschools.org",
    "wof:name":"Orcas Island School",
    "wof:placetype":"venue"
},
  "geometry": {"coordinates":[-122.90232899999999,48.698556],"type":"Point"}
}