{
  "type": "Feature",
  "properties": {
    "addr:full":"314 Occidental Avenue S Seattle WA 98104",
    "addr:housenumber":"314",
    "addr:postcode":"98104",
    "addr:street":"Occidental Avenue S",
    "iso:country":"US",
    "sg:address":"314 Occidental Avenue S",
    "sg:city":"Seattle",
    "sg:classifiers":[
        {
            "category":"Arts & Performance",
            "subcategory":"Art Gallery",
            "type":"Entertainment"
        },
        {
            "category":"Shopping",
            "subcategory":"Antiques",
            "type":"Retail Goods"
        }
    ],
    "sg:phone":"+1 206 621 1888",
    "sg:postcode":"98104",
    "sg:province":"WA",
    "wof:name":"Staley Carolyn Fine Prints",
    "wof:placetype":"venue"
},
  "geometry": {"coordinates":[-122.33305300000001,47.599636],"type":"Point"}
}