{
  "type": "Feature",
  "properties": {
    "addr:full":"25010 SE 31st Pl Sammamish WA 98075",
    "addr:postcode":"25010;98075",
    "addr:street":"Se 31St Pl",
    "iso:country":"US",
    "sg:address":"25010 SE 31st Pl",
    "sg:city":"Sammamish",
    "sg:classifiers":[
        {
            "category":"Wholesale",
            "subcategory":"Computers",
            "type":"Manufacturing & Wholesale Goods"
        }
    ],
    "sg:phone":"+1 425 557 7740",
    "sg:postcode":"98075",
    "sg:province":"WA",
    "wof:name":"J D Consulting",
    "wof:placetype":"venue"
},
  "geometry": {"coordinates":[-122.004867,47.581384],"type":"Point"}
}