{
  "type": "Feature",
  "properties": {
    "addr:full":"19815 Yew Way Snohomish WA 98296",
    "addr:housenumber":"19815",
    "addr:postcode":"98296",
    "addr:street":"Yew Way",
    "iso:country":"US",
    "sg:address":"19815 Yew Way",
    "sg:city":"Snohomish",
    "sg:classifiers":[
        {
            "category":"Professional",
            "subcategory":"Computer Services",
            "type":"Services"
        }
    ],
    "sg:phone":"+1 425 483 7008",
    "sg:postcode":"98296",
    "sg:province":"WA",
    "sg:tags":[
        "related"
    ],
    "wof:name":"Dennis Krueger",
    "wof:placetype":"venue"
},
  "geometry": {"coordinates":[-122.092547,47.817048],"type":"Point"}
}