{
  "type": "Feature",
  "properties": {
    "addr:full":"401 Washington St Wenatchee WA 98801",
    "addr:housenumber":"401",
    "addr:postcode":"98801",
    "addr:street":"Washington St",
    "iso:country":"US",
    "sg:address":"401 Washington St",
    "sg:city":"Wenatchee",
    "sg:classifiers":[
        {
            "category":"Restaurant",
            "type":"Food & Drink"
        }
    ],
    "sg:phone":"+1 509 663 9198",
    "sg:postcode":"98801",
    "sg:province":"WA",
    "wof:name":"Tex's Courtyard Grill",
    "wof:placetype":"venue"
},
  "geometry": {"coordinates":[-120.316727,47.422581],"type":"Point"}
}