{
  "type": "Feature",
  "properties": {
    "addr:full":"6250 1st Ave NW Seattle WA 98107",
    "addr:housenumber":"6250",
    "addr:postcode":"98107",
    "addr:street":"1St Ave Nw",
    "iso:country":"US",
    "sg:address":"6250 1st Ave NW",
    "sg:city":"Seattle",
    "sg:classifiers":[
        {
            "category":"Professional",
            "subcategory":"Accounting & Tax Preparation",
            "type":"Services"
        }
    ],
    "sg:phone":"+1 206 784 2918",
    "sg:postcode":"98107",
    "sg:province":"WA",
    "sg:tags":[
        "bookkeeping",
        "general"
    ],
    "wof:name":"Christopher S Cote Management",
    "wof:placetype":"venue"
},
  "geometry": {"coordinates":[-122.357367,47.675663],"type":"Point"}
}