{
  "type": "Feature",
  "properties": {
    "iso:country":"US",
    "sg:address":"19543 Jordan St SW",
    "sg:city":"Rochester",
    "sg:classifiers":[
        {
            "category":"Farming",
            "subcategory":"Dairy Farm",
            "type":"Manufacturing & Wholesale Goods"
        }
    ],
    "sg:phone":"+1 360 273 8275",
    "sg:postcode":"98579",
    "sg:province":"WA",
    "wof:name":"Scattercreek Dairy",
    "wof:placetype":"venue"
},
  "geometry": {"coordinates":[-123.086932,46.804818],"type":"Point"}
}