{
  "type": "Feature",
  "properties": {
    "iso:country":"US",
    "sg:address":"2038 33rd Ave NE",
    "sg:city":"Olympia",
    "sg:classifiers":[
        {
            "category":"Building & Trades",
            "subcategory":"Construction",
            "type":"Services"
        }
    ],
    "sg:phone":"+1 360 705 0386",
    "sg:postcode":"98506",
    "sg:province":"WA",
    "sg:tags":[
        "house"
    ],
    "wof:name":"Schuettke Construction",
    "wof:placetype":"venue"
},
  "geometry": {"coordinates":[-122.875894,47.078951],"type":"Point"}
}