{
  "type": "Feature",
  "properties": {
    "addr:full":"1207 Bridle Dr Richland WA 99352",
    "addr:housenumber":"1207",
    "addr:postcode":"99352",
    "addr:street":"Bridle Dr",
    "iso:country":"US",
    "sg:address":"1207 Bridle Dr",
    "sg:city":"Richland",
    "sg:classifiers":[
        {
            "category":"Building & Trades",
            "subcategory":"Construction",
            "type":"Services"
        }
    ],
    "sg:phone":"+1 509 627 5952",
    "sg:postcode":"99352",
    "sg:province":"WA",
    "sg:tags":[
        "excavation",
        "contractor"
    ],
    "wof:name":"Carl Kinion Excavation",
    "wof:placetype":"venue"
},
  "geometry": {"coordinates":[-119.31559300000001,46.244638],"type":"Point"}
}