{
  "type": "Feature",
  "properties": {
    "addr:full":"8637 S 212th St Kent WA 98031",
    "addr:housenumber":"8637",
    "addr:postcode":"98031",
    "addr:street":"S 212Th St",
    "iso:country":"US",
    "sg:address":"8637 S 212th St",
    "sg:city":"Kent",
    "sg:classifiers":[
        {
            "category":"Freight",
            "type":"Transportation"
        }
    ],
    "sg:phone":"+1 253 859 8000",
    "sg:postcode":"98031",
    "sg:province":"WA",
    "sg:tags":[
        "mover"
    ],
    "wof:name":"All My Sons Moving & Storage",
    "wof:placetype":"venue"
},
  "geometry": {"coordinates":[-122.224819,47.411998],"type":"Point"}
}