{
  "type": "Feature",
  "properties": {
    "addr:full":"2906 Capitol Blvd S Olympia WA 98501",
    "addr:housenumber":"2906",
    "addr:postcode":"98501",
    "addr:street":"Capitol Blvd S",
    "iso:country":"US",
    "sg:address":"2906 Capitol Blvd S",
    "sg:city":"Olympia",
    "sg:classifiers":[
        {
            "category":"Shopping",
            "subcategory":"Used Merchandise",
            "type":"Retail Goods"
        }
    ],
    "sg:phone":"+1 360 943 9841",
    "sg:postcode":"98501",
    "sg:province":"WA",
    "sg:tags":[
        "antique"
    ],
    "wof:name":"Murray O Willard",
    "wof:placetype":"venue"
},
  "geometry": {"coordinates":[-122.89561399999999,47.022155],"type":"Point"}
}