{
  "type": "Feature",
  "properties": {
    "addr:full":"521 E Mountain View Ave Ellensburg WA 98926",
    "addr:housenumber":"521",
    "addr:postcode":"98926",
    "addr:street":"E Mountain View Ave",
    "iso:country":"US",
    "sg:address":"521 E Mountain View Ave",
    "sg:city":"Ellensburg",
    "sg:classifiers":[
        {
            "category":"Government",
            "subcategory":"Office",
            "type":"Public Place"
        }
    ],
    "sg:phone":"+1 509 925 0440",
    "sg:postcode":"98926",
    "sg:province":"WA",
    "sg:tags":[
        "state",
        "resource"
    ],
    "wof:name":"Children & Family Svc Dept",
    "wof:placetype":"venue"
},
  "geometry": {"coordinates":[-120.540916,46.98457],"type":"Point"}
}