{
  "type": "Feature",
  "properties": {
    "addr:full":"14711 NE 29th Pl Bellevue WA 98007",
    "addr:housenumber":"14711",
    "addr:postcode":"98007",
    "addr:street":"Ne 29Th Pl",
    "iso:country":"US",
    "sg:address":"14711 NE 29th Pl",
    "sg:city":"Bellevue",
    "sg:classifiers":[
        {
            "category":"Professional",
            "subcategory":"Computer Services",
            "type":"Services"
        }
    ],
    "sg:phone":"+1 425 897 3660",
    "sg:postcode":"98007",
    "sg:province":"WA",
    "wof:name":"Computer Sciences Corporation",
    "wof:placetype":"venue"
},
  "geometry": {"coordinates":[-122.143557,47.636187],"type":"Point"}
}