{
  "type": "Feature",
  "properties": {
    "addr:full":"4117 NE St Johns Rd Vancouver WA 98661",
    "addr:housenumber":"4117",
    "addr:postcode":"98661",
    "addr:street":"Ne St Johns Rd",
    "iso:country":"US",
    "sg:address":"4117 NE St Johns Rd",
    "sg:city":"Vancouver",
    "sg:classifiers":[
        {
            "category":"Real Estate",
            "subcategory":"Real Estate Operator",
            "type":"Services"
        }
    ],
    "sg:phone":"+1 360 699 7370",
    "sg:postcode":"98661",
    "sg:province":"WA",
    "sg:tags":[
        "apartment"
    ],
    "wof:name":"Summerhill Apartments",
    "wof:placetype":"venue"
},
  "geometry": {"coordinates":[-122.63596699999999,45.653208],"type":"Point"}
}