{
  "type": "Feature",
  "properties": {
    "addr:full":"11120 Walker Rd Mount Vernon WA 98273",
    "addr:housenumber":"11120",
    "addr:postcode":"98273",
    "addr:street":"Walker Rd",
    "iso:country":"US",
    "sg:address":"11120 Walker Rd",
    "sg:city":"Mount Vernon",
    "sg:classifiers":[
        {
            "category":"Manufacturing",
            "subcategory":"Jewelry",
            "type":"Manufacturing & Wholesale Goods"
        }
    ],
    "sg:phone":"+1 360 757 7745",
    "sg:postcode":"98273",
    "sg:province":"WA",
    "sg:tags":[
        "precious",
        "metal",
        "mfg"
    ],
    "wof:name":"A Majikal Image",
    "wof:placetype":"venue"
},
  "geometry": {"coordinates":[-122.466375,48.486229],"type":"Point"}
}