{
  "type": "Feature",
  "properties": {
    "addr:full":"2507 Bloor St Bellingham WA 98229",
    "addr:housenumber":"2507",
    "addr:postcode":"98229",
    "addr:street":"Bloor St",
    "iso:country":"US",
    "sg:address":"2507 Bloor St",
    "sg:city":"Bellingham",
    "sg:classifiers":[
        {
            "category":"Building & Trades",
            "subcategory":"Construction",
            "type":"Services"
        }
    ],
    "sg:phone":"+1 360 733 4595",
    "sg:postcode":"98229",
    "sg:province":"WA",
    "sg:tags":[
        "home",
        "builder",
        "house"
    ],
    "wof:name":"Catwalk Fencing & Deck",
    "wof:placetype":"venue"
},
  "geometry": {"coordinates":[-122.446229,48.73194],"type":"Point"}
}