{
  "type": "Feature",
  "properties": {
    "addr:full":"3414 137th St NW Gig Harbor WA 98332",
    "addr:housenumber":"3414",
    "addr:postcode":"98332",
    "addr:street":"137Th St Nw",
    "iso:country":"US",
    "sg:address":"3414 137th St NW",
    "sg:city":"Gig Harbor",
    "sg:classifiers":[
        {
            "category":"Building & Trades",
            "subcategory":"Construction",
            "type":"Services"
        }
    ],
    "sg:phone":"+1 253 858 8647",
    "sg:postcode":"98332",
    "sg:province":"WA",
    "sg:tags":[
        "house"
    ],
    "wof:name":"Butlers Home Maintenance",
    "wof:placetype":"venue"
},
  "geometry": {"coordinates":[-122.58466900000001,47.382591],"type":"Point"}
}