{
  "type": "Feature",
  "properties": {
    "addr:full":"681 13th Way SW Edmonds WA 98020",
    "addr:housenumber":"681",
    "addr:postcode":"98020",
    "addr:street":"13Th Way Sw",
    "iso:country":"US",
    "sg:address":"681 13th Way SW",
    "sg:city":"Edmonds",
    "sg:classifiers":[
        {
            "category":"Professional",
            "subcategory":"Management & Consulting",
            "type":"Services"
        }
    ],
    "sg:phone":"+1 425 778 9178",
    "sg:postcode":"98020",
    "sg:province":"WA",
    "sg:tags":[
        "environmental"
    ],
    "wof:name":"Scordino Envmtl Consulting",
    "wof:placetype":"venue"
},
  "geometry": {"coordinates":[-122.373802,47.7964],"type":"Point"}
}