{
  "type": "Feature",
  "properties": {
    "addr:full":"5117 NE 68th Ave Vancouver WA 98661",
    "addr:housenumber":"5117",
    "addr:postcode":"98661",
    "addr:street":"Ne 68Th Ave",
    "iso:country":"US",
    "sg:address":"5117 NE 68th Ave",
    "sg:city":"Vancouver",
    "sg:classifiers":[
        {
            "category":"Airline",
            "type":"Transportation"
        }
    ],
    "sg:phone":"+1 360 993 4262",
    "sg:postcode":"98661",
    "sg:province":"WA",
    "sg:tags":[
        "shuttle",
        "airport"
    ],
    "wof:name":"C J Business Management Inc",
    "wof:placetype":"venue"
},
  "geometry": {"coordinates":[-122.60267399999999,45.659147],"type":"Point"}
}