{
  "type": "Feature",
  "properties": {
    "addr:full":"1603 Marshall Ave Richland WA 99354",
    "addr:housenumber":"1603",
    "addr:postcode":"99354",
    "addr:street":"Marshall Ave",
    "iso:country":"US",
    "sg:address":"1603 Marshall Ave",
    "sg:city":"Richland",
    "sg:classifiers":[
        {
            "category":"Building & Trades",
            "subcategory":"Landscaping Services",
            "type":"Services"
        }
    ],
    "sg:phone":"+1 509 628 0111",
    "sg:postcode":"99354",
    "sg:province":"WA",
    "sg:tags":[
        "lawn",
        "snow",
        "maintenance",
        "removal"
    ],
    "wof:name":"Cadillac Lawn Care",
    "wof:placetype":"venue"
},
  "geometry": {"coordinates":[-119.287811,46.293095],"type":"Point"}
}