{
  "type": "Feature",
  "properties": {
    "iso:country":"US",
    "sg:address":"194 Journey Way",
    "sg:city":"Sequim",
    "sg:classifiers":[
        {
            "category":"Building & Trades",
            "subcategory":"Construction",
            "type":"Services"
        }
    ],
    "sg:phone":"+1 360 681 7012",
    "sg:postcode":"98382",
    "sg:province":"WA",
    "sg:tags":[
        "contractor"
    ],
    "wof:name":"Fusion Tile & Glass",
    "wof:placetype":"venue"
},
  "geometry": {"coordinates":[-122.98881799999999,48.04304],"type":"Point"}
}