{
  "type": "Feature",
  "properties": {
    "addr:full":"8012 W Geiger Blvd Spokane WA 99224",
    "addr:housenumber":"8012",
    "addr:postcode":"99224",
    "addr:street":"W Geiger Blvd",
    "iso:country":"US",
    "sg:address":"8012 W Geiger Blvd",
    "sg:city":"Spokane",
    "sg:classifiers":[
        {
            "category":"Manufacturing",
            "subcategory":"Tools & Machinery",
            "type":"Manufacturing & Wholesale Goods"
        }
    ],
    "sg:phone":"+1 509 747 1481",
    "sg:postcode":"99224",
    "sg:province":"WA",
    "sg:tags":[
        "machine",
        "shop",
        "repair",
        "mfg"
    ],
    "wof:name":"Specialty Machining & Mfg Co",
    "wof:placetype":"venue"
},
  "geometry": {"coordinates":[-117.52944100000001,47.607963],"type":"Point"}
}