{
  "type": "Feature",
  "properties": {
    "addr:full":"7741 2nd Ave NE Seattle WA 98115",
    "addr:housenumber":"7741",
    "addr:postcode":"98115",
    "addr:street":"2Nd Ave Ne",
    "iso:country":"US",
    "sg:address":"7741 2nd Ave NE",
    "sg:city":"Seattle",
    "sg:classifiers":[
        {
            "category":"Manufacturing",
            "subcategory":"Buildings",
            "type":"Manufacturing & Wholesale Goods"
        },
        {
            "category":"Building & Trades",
            "subcategory":"Construction",
            "type":"Services"
        }
    ],
    "sg:phone":"+1 206 522 7186",
    "sg:postcode":"98115",
    "sg:province":"WA",
    "sg:tags":[
        "home",
        "builder",
        "contractor"
    ],
    "wof:name":"Rockhold Enterprises",
    "wof:placetype":"venue"
},
  "geometry": {"coordinates":[-122.326976,47.685751],"type":"Point"}
}