{
  "type": "Feature",
  "properties": {
    "addr:full":"18634 Ridge Rd SW Vashon WA 98070",
    "addr:housenumber":"18634",
    "addr:postcode":"98070",
    "addr:street":"Ridge Rd Sw",
    "iso:country":"US",
    "sg:address":"18634 Ridge Rd SW",
    "sg:city":"Vashon",
    "sg:classifiers":[
        {
            "category":"Professional",
            "subcategory":"Engineering",
            "type":"Services"
        }
    ],
    "sg:phone":"+1 206 463 3415",
    "sg:postcode":"98070",
    "sg:province":"WA",
    "wof:name":"Carlson & Company",
    "wof:placetype":"venue"
},
  "geometry": {"coordinates":[-122.446005,47.437946],"type":"Point"}
}