{
  "type": "Feature",
  "properties": {
    "iso:country":"US",
    "sg:address":"3000 Rockefeller Ave",
    "sg:city":"Everett",
    "sg:classifiers":[
        {
            "category":"Government",
            "subcategory":"Office",
            "type":"Public Place"
        }
    ],
    "sg:phone":"+1 425 388 3331",
    "sg:postcode":"98201",
    "sg:province":"WA",
    "sg:tags":[
        "executive"
    ],
    "wof:name":"Executive Office State of WA",
    "wof:placetype":"venue"
},
  "geometry": {"coordinates":[-122.20573400000001,47.976586],"type":"Point"}
}