{
  "type": "Feature",
  "properties": {
    "addr:full":"2612 S 357th St Federal Way WA 98003",
    "addr:housenumber":"2612",
    "addr:postcode":"98003",
    "addr:street":"S 357Th St",
    "iso:country":"US",
    "sg:address":"2612 S 357th St",
    "sg:city":"Federal Way",
    "sg:classifiers":[
        {
            "category":"Personal",
            "subcategory":"Beauty Salon",
            "type":"Services"
        }
    ],
    "sg:phone":"+1 253 874 3623",
    "sg:postcode":"98003",
    "sg:province":"WA",
    "sg:tags":[
        "shop"
    ],
    "wof:name":"J D Hair Design",
    "wof:placetype":"venue"
},
  "geometry": {"coordinates":[-122.30029399999999,47.28212],"type":"Point"}
}