{
  "type": "Feature",
  "properties": {
    "addr:full":"1413 NW 70th St Seattle WA 98127",
    "addr:housenumber":"1413",
    "addr:postcode":"98127",
    "addr:street":"Nw 70Th St",
    "iso:country":"US",
    "sg:address":"1413 NW 70th St",
    "sg:city":"Seattle",
    "sg:classifiers":[
        {
            "category":"Bakery",
            "type":"Food & Drink"
        }
    ],
    "sg:phone":"+1 206 706 4035",
    "sg:postcode":"98127",
    "sg:province":"WA",
    "wof:name":"Honore Artisan Bakery",
    "wof:placetype":"venue"
},
  "geometry": {"coordinates":[-122.373991,47.679563],"type":"Point"}
}