{
  "type": "Feature",
  "properties": {
    "addr:full":"128 Washington Ave S Orting WA 98360",
    "addr:housenumber":"128",
    "addr:postcode":"98360",
    "addr:street":"Washington Ave S Orting",
    "iso:country":"US",
    "sg:address":"128 Washington Ave S",
    "sg:city":"Orting",
    "sg:classifiers":[
        {
            "category":"Banks & Credit Unions",
            "subcategory":"Investment Brokerage",
            "type":"Services"
        }
    ],
    "sg:phone":"+1 360 893 1787",
    "sg:postcode":"98360",
    "sg:province":"WA",
    "sg:tags":[
        "security"
    ],
    "sg:website":"www.edwardjones.com",
    "wof:name":"Edward Jones Co",
    "wof:placetype":"venue"
},
  "geometry": {"coordinates":[-122.20319600000001,47.097325],"type":"Point"}
}