{
  "type": "Feature",
  "properties": {
    "addr:full":"804 S 252nd St Seattle WA 98198",
    "addr:housenumber":"804",
    "addr:postcode":"98198",
    "addr:street":"S 252Nd St",
    "iso:country":"US",
    "sg:address":"804 S 252nd St",
    "sg:city":"Seattle",
    "sg:classifiers":[
        {
            "category":"Professional",
            "type":"Services"
        }
    ],
    "sg:phone":"+1 206 878 4303",
    "sg:postcode":"98198",
    "sg:province":"WA",
    "wof:name":"Lawrence A Watson",
    "wof:placetype":"venue"
},
  "geometry": {"coordinates":[-122.322198,47.376242],"type":"Point"}
}