{
  "type": "Feature",
  "properties": {
    "addr:full":"109 Washington Ave S Eatonville WA 98328",
    "addr:housenumber":"109",
    "addr:postcode":"98328",
    "addr:street":"Washington Ave S Eatonville",
    "iso:country":"US",
    "sg:address":"109 Washington Ave S",
    "sg:city":"Eatonville",
    "sg:classifiers":[
        {
            "category":"Real Estate",
            "subcategory":"Real Estate Agent",
            "type":"Services"
        }
    ],
    "sg:phone":"+1 360 832 2100",
    "sg:postcode":"98328",
    "sg:province":"WA",
    "sg:website":"www.7-24realestateinfo.com",
    "wof:name":"Real Estate Ctr",
    "wof:placetype":"venue"
},
  "geometry": {"coordinates":[-122.26534700000001,46.86669],"type":"Point"}
}