{
  "type": "Feature",
  "properties": {
    "iso:country":"US",
    "sg:address":"16249 36th Ave NE",
    "sg:city":"Seattle",
    "sg:classifiers":[
        {
            "category":"Banks & Credit Unions",
            "subcategory":"Financial Services",
            "type":"Services"
        }
    ],
    "sg:phone":"+1 206 363 4832",
    "sg:postcode":"98155",
    "sg:province":"WA",
    "sg:tags":[
        "trust",
        "management"
    ],
    "wof:name":"Hagen Family Trust",
    "wof:placetype":"venue"
},
  "geometry": {"coordinates":[-122.28854800000001,47.749319],"type":"Point"}
}