{
  "type": "Feature",
  "properties": {
    "addr:full":"735 Satsop Rd W Montesano WA 98563",
    "addr:housenumber":"735",
    "addr:postcode":"98563",
    "addr:street":"Satsop Rd W Montesano",
    "iso:country":"US",
    "sg:address":"735 Satsop Rd W",
    "sg:city":"Montesano",
    "sg:classifiers":[
        {
            "category":"Professional",
            "subcategory":"Business Services",
            "type":"Services"
        }
    ],
    "sg:phone":"+1 360 249 6727",
    "sg:postcode":"98563",
    "sg:province":"WA",
    "wof:name":"Jtc Ventures",
    "wof:placetype":"venue"
},
  "geometry": {"coordinates":[-123.545801,47.058754],"type":"Point"}
}