{
  "type": "Feature",
  "properties": {
    "addr:full":"3 Thayer Rd Oroville WA 98844",
    "addr:housenumber":"3",
    "addr:postcode":"98844",
    "addr:street":"Thayer Rd",
    "iso:country":"US",
    "sg:address":"3 Thayer Rd",
    "sg:city":"Oroville",
    "sg:classifiers":[
        {
            "category":"Farming",
            "subcategory":"Orchard",
            "type":"Manufacturing & Wholesale Goods"
        }
    ],
    "sg:phone":"+1 509 476 3810",
    "sg:postcode":"98844",
    "sg:province":"WA",
    "sg:tags":[
        "fruit",
        "tree"
    ],
    "wof:name":"Zth Enterprises",
    "wof:placetype":"venue"
},
  "geometry": {"coordinates":[-119.429312,48.834913],"type":"Point"}
}