{
  "type": "Feature",
  "properties": {
    "iso:country":"US",
    "sg:address":"202 S 348th St",
    "sg:city":"Federal Way",
    "sg:classifiers":[
        {
            "category":"Professional",
            "subcategory":"Lawyer & Legal Services",
            "type":"Services"
        }
    ],
    "sg:phone":"+1 253 815 0902",
    "sg:postcode":"98003",
    "sg:province":"WA",
    "sg:tags":[
        "naturalization",
        "immigration"
    ],
    "wof:name":"Elite Visa",
    "wof:placetype":"venue"
},
  "geometry": {"coordinates":[-122.32936599999999,47.289943],"type":"Point"}
}