{
  "type": "Feature",
  "properties": {
    "addr:full":"242 Thistledown Ln Port Angeles WA 98362",
    "addr:housenumber":"242",
    "addr:postcode":"98362",
    "addr:street":"Thistledown Ln",
    "iso:country":"US",
    "sg:address":"242 Thistledown Ln",
    "sg:city":"Port Angeles",
    "sg:classifiers":[
        {
            "category":"Social Services",
            "subcategory":"Child Care",
            "type":"Services"
        }
    ],
    "sg:phone":"+1 360 452 0933",
    "sg:postcode":"98362",
    "sg:province":"WA",
    "wof:name":"Learn & Play Child Care",
    "wof:placetype":"venue"
},
  "geometry": {"coordinates":[-123.30933899999999,48.081646],"type":"Point"}
}