{
  "type": "Feature",
  "properties": {
    "addr:full":"307 N 73rd St Seattle WA 98103",
    "addr:housenumber":"307",
    "addr:postcode":"98103",
    "addr:street":"N 73Rd St",
    "iso:country":"US",
    "sg:address":"307 N 73rd St",
    "sg:city":"Seattle",
    "sg:classifiers":[
        {
            "category":"Organizations",
            "subcategory":"Religious Organization",
            "type":"Services"
        }
    ],
    "sg:phone":"+1 206 818 8937",
    "sg:postcode":"98103",
    "sg:province":"WA",
    "wof:name":"Van Deputte Faith Lmp",
    "wof:placetype":"venue"
},
  "geometry": {"coordinates":[-122.352653,47.681727],"type":"Point"}
}