{
  "type": "Feature",
  "properties": {
    "addr:full":"2114 Burwell Pl Bremerton WA 98312",
    "addr:housenumber":"2114",
    "addr:postcode":"98312",
    "addr:street":"Burwell Pl",
    "iso:country":"US",
    "sg:address":"2114 Burwell Pl",
    "sg:city":"Bremerton",
    "sg:classifiers":[
        {
            "category":"Recreation",
            "type":"Entertainment"
        }
    ],
    "sg:phone":"+1 360 895 7819",
    "sg:postcode":"98312",
    "sg:province":"WA",
    "wof:name":"American Shaolin Martial Arts",
    "wof:placetype":"venue"
},
  "geometry": {"coordinates":[-122.64862100000001,47.565643],"type":"Point"}
}