{
  "type": "Feature",
  "properties": {
    "addr:full":"2803 NW 91st St Seattle WA 98117",
    "addr:housenumber":"2803",
    "addr:postcode":"98117",
    "addr:street":"Nw 91St St",
    "iso:country":"US",
    "sg:address":"2803 NW 91st St",
    "sg:city":"Seattle",
    "sg:classifiers":[
        {
            "category":"Social Services",
            "type":"Services"
        }
    ],
    "sg:phone":"+1 206 782 8737",
    "sg:postcode":"98117",
    "sg:province":"WA",
    "sg:tags":[
        "counselor",
        "marriage",
        "family"
    ],
    "wof:name":"Carol Hambidge",
    "wof:placetype":"venue"
},
  "geometry": {"coordinates":[-122.39413999999999,47.695243],"type":"Point"}
}