{
  "type": "Feature",
  "properties": {
    "addr:full":"911 E 1st St Cle Elum WA 98922",
    "addr:housenumber":"911",
    "addr:postcode":"98922",
    "addr:street":"E 1St St",
    "iso:country":"US",
    "sg:address":"911 E 1st St",
    "sg:city":"Cle Elum",
    "sg:classifiers":[
        {
            "category":"Restaurant",
            "type":"Food & Drink"
        }
    ],
    "sg:phone":"+1 509 674 2922",
    "sg:postcode":"98922",
    "sg:province":"WA",
    "sg:tags":[
        "american"
    ],
    "wof:name":"Cottage Cafe The",
    "wof:placetype":"venue"
},
  "geometry": {"coordinates":[-120.918882,47.192513],"type":"Point"}
}