{
  "type": "Feature",
  "properties": {
    "addr:full":"12 Pine Hill Rd Newport WA 99156",
    "addr:housenumber":"12",
    "addr:postcode":"99156",
    "addr:street":"Pine Hill Rd",
    "iso:country":"US",
    "sg:address":"12 Pine Hill Rd",
    "sg:city":"Newport",
    "sg:classifiers":[
        {
            "category":"Manufacturing",
            "subcategory":"Building Materials",
            "type":"Manufacturing & Wholesale Goods"
        }
    ],
    "sg:phone":"+1 509 447 5898",
    "sg:postcode":"99156",
    "sg:province":"WA",
    "sg:tags":[
        "mfg",
        "wood",
        "kitchen",
        "cabinet"
    ],
    "wof:name":"Custom Craft Cabinets",
    "wof:placetype":"venue"
},
  "geometry": {"coordinates":[-117.16211199999999,48.142566],"type":"Point"}
}