{
  "type": "Feature",
  "properties": {
    "addr:full":"11555 SE 8th St Bellevue WA 98004",
    "addr:housenumber":"11555",
    "addr:postcode":"98004",
    "addr:street":"Se 8Th St",
    "iso:country":"US",
    "sg:address":"11555 SE 8th St",
    "sg:city":"Bellevue",
    "sg:classifiers":[
        {
            "category":"Banks & Credit Unions",
            "subcategory":"Bank",
            "type":"Services"
        }
    ],
    "sg:phone":"+1 425 468 3330",
    "sg:postcode":"98004",
    "sg:province":"WA",
    "sg:tags":[
        "loan",
        "real estate"
    ],
    "wof:name":"Countrywide Home Loans",
    "wof:placetype":"venue"
},
  "geometry": {"coordinates":[-122.187545,47.601522],"type":"Point"}
}