{
  "type": "Feature",
  "properties": {
    "addr:full":"9804 Sales Rd S Ste A1 Lakewood WA 98499",
    "addr:housenumber":"9804",
    "addr:postcode":"98499",
    "addr:street":"Sales Rd S Ste A1",
    "iso:country":"US",
    "sg:address":"9804 Sales Rd S Ste A1",
    "sg:city":"Lakewood",
    "sg:classifiers":[
        {
            "category":"Building & Trades",
            "subcategory":"Electrical",
            "type":"Services"
        }
    ],
    "sg:phone":"+1 253 984 1611",
    "sg:postcode":"98499",
    "sg:province":"WA",
    "sg:tags":[
        "industrial",
        "electrician",
        "electric",
        "contractors-commercial"
    ],
    "wof:name":"Abacus Electric Company",
    "wof:placetype":"venue"
},
  "geometry": {"coordinates":[-122.471628,47.167986],"type":"Point"}
}