{
  "type": "Feature",
  "properties": {
    "iso:country":"US",
    "sg:address":"410 Capitol Way S",
    "sg:city":"Olympia",
    "sg:classifiers":[
        {
            "category":"Professional",
            "subcategory":"Lawyer & Legal Services",
            "type":"Services"
        }
    ],
    "sg:phone":"+1 360 786 8276",
    "sg:postcode":"98501",
    "sg:province":"WA",
    "wof:name":"Stephen Maddox",
    "wof:placetype":"venue"
},
  "geometry": {"coordinates":[-122.90148499999999,47.044161],"type":"Point"}
}