{
  "type": "Feature",
  "properties": {
    "iso:country":"US",
    "sg:address":"2707 24th St",
    "sg:city":"Bremerton",
    "sg:classifiers":[
        {
            "category":"Professional",
            "subcategory":"Advertising",
            "type":"Services"
        }
    ],
    "sg:phone":"+1 360 479 6240",
    "sg:postcode":"98312",
    "sg:province":"WA",
    "wof:name":"Worldpages Co",
    "wof:placetype":"venue"
},
  "geometry": {"coordinates":[-122.65382700000001,47.581959],"type":"Point"}
}