{
  "type": "Feature",
  "properties": {
    "addr:full":"347 W Ewing St Seattle WA 98119",
    "addr:housenumber":"347",
    "addr:postcode":"98119",
    "addr:street":"W Ewing St",
    "iso:country":"US",
    "sg:address":"347 W Ewing St",
    "sg:city":"Seattle",
    "sg:classifiers":[
        {
            "category":"Building & Trades",
            "subcategory":"Construction",
            "type":"Services"
        }
    ],
    "sg:phone":"+1 206 285 9567",
    "sg:postcode":"98119",
    "sg:province":"WA",
    "sg:tags":[
        "installs",
        "solid",
        "mfr",
        "surface"
    ],
    "wof:name":"Larsen Co",
    "wof:placetype":"venue"
},
  "geometry": {"coordinates":[-122.36370599999999,47.652305],"type":"Point"}
}