{
  "type": "Feature",
  "properties": {
    "iso:country":"US",
    "sg:address":"22721 Rose Rd",
    "sg:city":"Mt Vernon",
    "sg:classifiers":[
        {
            "category":"Building & Trades",
            "subcategory":"Construction",
            "type":"Services"
        }
    ],
    "sg:phone":"+1 360 445 4454",
    "sg:postcode":"98274",
    "sg:province":"WA",
    "sg:tags":[
        "layer",
        "carpet"
    ],
    "wof:name":"Valley Carpet Svc",
    "wof:placetype":"venue"
},
  "geometry": {"coordinates":[-122.286286,48.316146],"type":"Point"}
}