{
  "type": "Feature",
  "properties": {
    "iso:country":"US",
    "sg:address":"1609 208th St SE",
    "sg:city":"Bothell",
    "sg:classifiers":[
        {
            "category":"Professional",
            "subcategory":"Computer Services",
            "type":"Services"
        }
    ],
    "sg:phone":"+1 425 424 2294",
    "sg:postcode":"98012",
    "sg:province":"WA",
    "wof:name":"TLC Computer Care",
    "wof:placetype":"venue"
},
  "geometry": {"coordinates":[-122.211412,47.8095],"type":"Point"}
}