{
  "type": "Feature",
  "properties": {
    "addr:full":"2000 Logston Blvd Richland WA 99354",
    "addr:postcode":"99354",
    "addr:street":"Logston Blvd",
    "iso:country":"US",
    "sg:address":"2000 Logston Blvd",
    "sg:city":"Richland",
    "sg:classifiers":[
        {
            "category":"Professional",
            "subcategory":"Advertising",
            "type":"Services"
        }
    ],
    "sg:phone":"+1 509 375 1222",
    "sg:postcode":"99354",
    "sg:province":"WA",
    "sg:tags":[
        "counselor"
    ],
    "wof:name":"Information Matters",
    "wof:placetype":"venue"
},
  "geometry": {"coordinates":[-119.299986,46.320437],"type":"Point"}
}