{
  "type": "Feature",
  "properties": {
    "addr:full":"12511 State Ave Marysville WA 98271",
    "addr:housenumber":"12511",
    "addr:postcode":"98271",
    "addr:street":"State Ave",
    "iso:country":"US",
    "sg:address":"12511 State Ave",
    "sg:city":"Marysville",
    "sg:classifiers":[
        {
            "category":"Personal",
            "type":"Services"
        }
    ],
    "sg:phone":"+1 360 659 2285",
    "sg:postcode":"98271",
    "sg:province":"WA",
    "wof:name":"Leifer Manor",
    "wof:placetype":"venue"
},
  "geometry": {"coordinates":[-122.17882,48.109986],"type":"Point"}
}