{
  "type": "Feature",
  "properties": {
    "addr:full":"3443 20th St E Fife WA 98424",
    "addr:housenumber":"3443",
    "addr:postcode":"98424",
    "addr:street":"20Th St E",
    "iso:country":"US",
    "sg:address":"3443 20th St E",
    "sg:city":"Fife",
    "sg:classifiers":[
        {
            "category":"Autos & Motor Vehicles",
            "subcategory":"Automobile Sales",
            "type":"Retail Goods"
        }
    ],
    "sg:phone":"+1 253 922 7383",
    "sg:postcode":"98424",
    "sg:province":"WA",
    "sg:tags":[
        "truck"
    ],
    "wof:name":"Western Peterbilt Inc",
    "wof:placetype":"venue"
},
  "geometry": {"coordinates":[-122.384899,47.239141],"type":"Point"}
}