{
  "type": "Feature",
  "properties": {
    "addr:full":"The Training Center 3737 NE 135th Street Seattle WA 98125",
    "addr:housenumber":"3737",
    "addr:postcode":"98125",
    "addr:street":"Ne 135Th Street",
    "iso:country":"US",
    "sg:address":"The Training Center 3737 NE 135th Street",
    "sg:city":"Seattle",
    "sg:classifiers":[
        {
            "category":"Sports & Exercise",
            "subcategory":"Gym",
            "type":"Entertainment"
        }
    ],
    "sg:phone":"+1 206 605 4245",
    "sg:postcode":"98125",
    "sg:province":"WA",
    "sg:tags":[
        "trainer"
    ],
    "sg:website":"www.ontheballfitness.biz",
    "wof:name":"On The Ball Fitness",
    "wof:placetype":"venue"
},
  "geometry": {"coordinates":[-122.287064,47.726212],"type":"Point"}
}