{
  "type": "Feature",
  "properties": {
    "addr:full":"419 N 20th Ave Yakima WA 98902",
    "addr:housenumber":"419",
    "addr:postcode":"98902",
    "addr:street":"N 20Th Ave",
    "iso:country":"US",
    "sg:address":"419 N 20th Ave",
    "sg:city":"Yakima",
    "sg:classifiers":[
        {
            "category":"Shopping",
            "type":"Retail Goods"
        }
    ],
    "sg:phone":"+1 509 248 3317",
    "sg:postcode":"98902",
    "sg:province":"WA",
    "sg:tags":[
        "pool",
        "patio",
        "supply"
    ],
    "wof:name":"A-1 Pool & Patio Supply Inc",
    "wof:placetype":"venue"
},
  "geometry": {"coordinates":[-120.535686,46.604938],"type":"Point"}
}