{
  "type": "Feature",
  "properties": {
    "addr:full":"924 Lafayette St S Tacoma WA 98444",
    "addr:housenumber":"924",
    "addr:postcode":"98444",
    "addr:street":"Lafayette St S",
    "iso:country":"US",
    "sg:address":"924 Lafayette St S",
    "sg:city":"Tacoma",
    "sg:classifiers":[
        {
            "category":"Building & Trades",
            "subcategory":"Construction",
            "type":"Services"
        }
    ],
    "sg:phone":"+1 253 531 1176",
    "sg:postcode":"98444",
    "sg:province":"WA",
    "sg:tags":[
        "residential"
    ],
    "wof:name":"Mjk",
    "wof:placetype":"venue"
},
  "geometry": {"coordinates":[-122.444845,47.154778],"type":"Point"}
}