{
  "type": "Feature",
  "properties": {
    "addr:full":"10400 NE 68th St Kirkland WA 98033",
    "addr:housenumber":"10400",
    "addr:postcode":"98033",
    "addr:street":"Ne 68Th St",
    "iso:country":"US",
    "sg:address":"10400 NE 68th St",
    "sg:city":"Kirkland",
    "sg:classifiers":[
        {
            "category":"Education",
            "subcategory":"School",
            "type":"Public Place"
        }
    ],
    "sg:phone":"+1 425 822 4517",
    "sg:postcode":"98033",
    "sg:province":"WA",
    "sg:tags":[
        "high",
        "middle",
        "elementary"
    ],
    "wof:name":"Lake Washington School District No 414 Information",
    "wof:placetype":"venue"
},
  "geometry": {"coordinates":[-122.199997,47.666801],"type":"Point"}
}