{
  "type": "Feature",
  "properties": {
    "addr:full":"5509 W Lincoln Ave Yakima WA 98908",
    "addr:housenumber":"5509",
    "addr:postcode":"98908",
    "addr:street":"W Lincoln Ave",
    "iso:country":"US",
    "sg:address":"5509 W Lincoln Ave",
    "sg:city":"Yakima",
    "sg:classifiers":[
        {
            "category":"Building & Trades",
            "subcategory":"Construction",
            "type":"Services"
        }
    ],
    "sg:phone":"+1 509 966 4870",
    "sg:postcode":"98908",
    "sg:province":"WA",
    "sg:tags":[
        "excavation",
        "contractor"
    ],
    "wof:name":"Gary Krebs Excavation Inc",
    "wof:placetype":"venue"
},
  "geometry": {"coordinates":[-120.583129,46.603738],"type":"Point"}
}