{
  "type": "Feature",
  "properties": {
    "addr:full":"2806 Boulevard Rd SE Olympia WA 98501",
    "addr:housenumber":"2806",
    "addr:postcode":"olympia;98501",
    "addr:street":"Boulevard Rd Se",
    "iso:country":"US",
    "sg:address":"2806 Boulevard Rd SE",
    "sg:city":"Olympia",
    "sg:classifiers":[
        {
            "category":"Retail",
            "subcategory":"Veterinary Services",
            "type":"Services"
        }
    ],
    "sg:phone":"+1 360 943 1566",
    "sg:postcode":"98501",
    "sg:province":"WA",
    "wof:name":"Gilpin Paula S Dvm",
    "wof:placetype":"venue"
},
  "geometry": {"coordinates":[-122.865083,47.022563],"type":"Point"}
}