{
  "type": "Feature",
  "properties": {
    "addr:full":"2212 Queen Anne Ave N Seattle WA 98109",
    "addr:housenumber":"2212",
    "addr:postcode":"98109",
    "addr:street":"Queen Anne Ave N",
    "iso:country":"US",
    "sg:address":"2212 Queen Anne Ave N",
    "sg:city":"Seattle",
    "sg:classifiers":[
        {
            "category":"Shopping",
            "subcategory":"Clothing, Apparel, & Fashions",
            "type":"Retail Goods"
        }
    ],
    "sg:phone":"+1 206 286 1024",
    "sg:postcode":"98109",
    "sg:province":"WA",
    "sg:tags":[
        "clothing",
        "women's"
    ],
    "sg:website":"www.undiesandouties.com",
    "wof:name":"Undies and Outies",
    "wof:placetype":"venue"
},
  "geometry": {"coordinates":[-122.356965,47.638456],"type":"Point"}
}