{
  "type": "Feature",
  "properties": {
    "addr:full":"414 Edson St Lynden WA 98264",
    "addr:housenumber":"414",
    "addr:postcode":"98264",
    "addr:street":"Edson St",
    "iso:country":"US",
    "sg:address":"414 Edson St",
    "sg:city":"Lynden",
    "sg:classifiers":[
        {
            "category":"Building & Trades",
            "subcategory":"Construction",
            "type":"Services"
        }
    ],
    "sg:phone":"+1 360 739 2264",
    "sg:postcode":"98264",
    "sg:province":"WA",
    "sg:tags":[
        "hanging",
        "contractor"
    ],
    "wof:name":"Liquid Applications",
    "wof:placetype":"venue"
},
  "geometry": {"coordinates":[-122.45391100000001,48.94593],"type":"Point"}
}