{
  "type": "Feature",
  "properties": {
    "addr:full":"56 Union Ave Steilacoom WA 98388",
    "addr:housenumber":"56",
    "addr:postcode":"98388",
    "addr:street":"Union Ave",
    "iso:country":"US",
    "sg:address":"56 Union Ave",
    "sg:city":"Steilacoom",
    "sg:classifiers":[
        {
            "category":"Professional",
            "subcategory":"Management & Consulting",
            "type":"Services"
        }
    ],
    "sg:phone":"+1 253 588 1950",
    "sg:postcode":"98388",
    "sg:province":"WA",
    "wof:name":"Pacific Management Svcs",
    "wof:placetype":"venue"
},
  "geometry": {"coordinates":[-122.603049,47.171927],"type":"Point"}
}