{
  "type": "Feature",
  "properties": {
    "addr:full":"3516 109th Pl SE Everett WA 98208",
    "addr:housenumber":"3516",
    "addr:postcode":"98208",
    "addr:street":"109Th Pl Se",
    "iso:country":"US",
    "sg:address":"3516 109th Pl SE",
    "sg:city":"Everett",
    "sg:classifiers":[
        {
            "category":"Personal",
            "type":"Services"
        }
    ],
    "sg:phone":"+1 425 330 1733",
    "sg:postcode":"98208",
    "sg:province":"WA",
    "wof:name":"Tammy McMahan",
    "wof:placetype":"venue"
},
  "geometry": {"coordinates":[-122.18429500000001,47.898214],"type":"Point"}
}