{
  "type": "Feature",
  "properties": {
    "addr:full":"1116 S 25th St Tacoma WA 98405",
    "addr:housenumber":"1116",
    "addr:postcode":"98405",
    "addr:street":"S 25Th St",
    "iso:country":"US",
    "sg:address":"1116 S 25th St",
    "sg:city":"Tacoma",
    "sg:classifiers":[
        {
            "category":"Building & Trades",
            "subcategory":"Electrical",
            "type":"Services"
        }
    ],
    "sg:phone":"+1 253 627 4460",
    "sg:postcode":"98405",
    "sg:province":"WA",
    "sg:tags":[
        "electrician"
    ],
    "wof:name":"Electronic Webb",
    "wof:placetype":"venue"
},
  "geometry": {"coordinates":[-122.448685,47.237555],"type":"Point"}
}