{
  "type": "Feature",
  "properties": {
    "addr:full":"295142 US Hwy 101 Quilcene WA 98376",
    "addr:housenumber":"295142",
    "addr:postcode":"98376",
    "addr:street":"Us Hwy 101",
    "iso:country":"US",
    "sg:address":"295142 US Hwy 101",
    "sg:city":"Quilcene",
    "sg:classifiers":[
        {
            "category":"Manufacturing",
            "subcategory":"Lumber",
            "type":"Manufacturing & Wholesale Goods"
        }
    ],
    "sg:phone":"+1 360 765 2200",
    "sg:postcode":"98376",
    "sg:province":"WA",
    "sg:tags":[
        "government"
    ],
    "wof:name":"Us Agriculture Dept Forest Svc",
    "wof:placetype":"venue"
},
  "geometry": {"coordinates":[-122.88087299999999,47.8213],"type":"Point"}
}