{
  "type": "Feature",
  "properties": {
    "addr:full":"17014 SE 43rd St Issaquah WA 98027",
    "addr:postcode":"17014;98027",
    "addr:street":"Se 43Rd St",
    "iso:country":"US",
    "sg:address":"17014 SE 43rd St",
    "sg:city":"Issaquah",
    "sg:classifiers":[
        {
            "category":"Professional",
            "subcategory":"Computer Services",
            "type":"Services"
        }
    ],
    "sg:phone":"+1 206 618 6788",
    "sg:postcode":"98027",
    "sg:province":"WA",
    "sg:tags":[
        "related"
    ],
    "wof:name":"Toschcom",
    "wof:placetype":"venue"
},
  "geometry": {"coordinates":[-122.113705,47.568407],"type":"Point"}
}