{
  "type": "Feature",
  "properties": {
    "addr:full":"653 NW 80th St Seattle WA 98117",
    "addr:housenumber":"653",
    "addr:postcode":"98117",
    "addr:street":"Nw 80Th St",
    "iso:country":"US",
    "sg:address":"653 NW 80th St",
    "sg:city":"Seattle",
    "sg:classifiers":[
        {
            "category":"Professional",
            "subcategory":"Business Services",
            "type":"Services"
        }
    ],
    "sg:phone":"+1 206 781 6934",
    "sg:postcode":"98117",
    "sg:province":"WA",
    "wof:name":"G Schlomann",
    "wof:placetype":"venue"
},
  "geometry": {"coordinates":[-122.36555,47.686864],"type":"Point"}
}