{
  "type": "Feature",
  "properties": {
    "iso:country":"US",
    "sg:address":"3207 Vincenta Dr",
    "sg:city":"Yakima",
    "sg:classifiers":[
        {
            "category":"Shopping",
            "subcategory":"Hobbies, Toys, & Games",
            "type":"Retail Goods"
        }
    ],
    "sg:phone":"+1 509 452 6926",
    "sg:postcode":"98902",
    "sg:province":"WA",
    "wof:name":"Kathryns Kollectables",
    "wof:placetype":"venue"
},
  "geometry": {"coordinates":[-120.551526,46.584575],"type":"Point"}
}