{
  "type": "Feature",
  "properties": {
    "addr:full":"409 Viewcrest Rd Bellingham WA 98229",
    "addr:housenumber":"409",
    "addr:postcode":"98229",
    "addr:street":"Viewcrest Rd",
    "iso:country":"US",
    "sg:address":"409 Viewcrest Rd",
    "sg:city":"Bellingham",
    "sg:classifiers":[
        {
            "category":"Education",
            "subcategory":"Special Training",
            "type":"Public Place"
        }
    ],
    "sg:phone":"+1 360 671 3701",
    "sg:postcode":"98229",
    "sg:province":"WA",
    "wof:name":"First Aid Instrctn Firefightrs",
    "wof:placetype":"venue"
},
  "geometry": {"coordinates":[-122.502774,48.704399],"type":"Point"}
}