{
  "type": "Feature",
  "properties": {
    "addr:full":"10902 NE 79th Cir Vancouver WA 98662",
    "addr:housenumber":"10902",
    "addr:postcode":"98662",
    "addr:street":"Ne 79Th Cir",
    "iso:country":"US",
    "sg:address":"10902 NE 79th Cir",
    "sg:city":"Vancouver",
    "sg:classifiers":[
        {
            "category":"Professional",
            "type":"Services"
        }
    ],
    "sg:phone":"+1 360 883 0877",
    "sg:postcode":"98662",
    "sg:province":"WA",
    "sg:tags":[
        "establishment"
    ],
    "wof:name":"Latitudes",
    "wof:placetype":"venue"
},
  "geometry": {"coordinates":[-122.560816,45.679684],"type":"Point"}
}