{
  "type": "Feature",
  "properties": {
    "addr:full":"8067 170th Pl NE Redmond WA 98052",
    "addr:housenumber":"8067",
    "addr:postcode":"98052",
    "addr:street":"170Th Pl Ne",
    "iso:country":"US",
    "sg:address":"8067 170th Pl NE",
    "sg:city":"Redmond",
    "sg:classifiers":[
        {
            "category":"Professional",
            "subcategory":"Management & Consulting",
            "type":"Services"
        }
    ],
    "sg:phone":"+1 425 985 1617",
    "sg:postcode":"98052",
    "sg:province":"WA",
    "wof:name":"Newtons Laws",
    "wof:placetype":"venue"
},
  "geometry": {"coordinates":[-122.113378,47.675706],"type":"Point"}
}