{
  "type": "Feature",
  "properties": {
    "iso:country":"US",
    "sg:address":"747 St Helens Ave",
    "sg:city":"Tacoma",
    "sg:classifiers":[
        {
            "category":"Social Services",
            "type":"Services"
        }
    ],
    "sg:phone":"+1 253 272 2675",
    "sg:postcode":"98402",
    "sg:province":"WA",
    "sg:tags":[
        "home",
        "health",
        "care"
    ],
    "wof:name":"Uniserve",
    "wof:placetype":"venue"
},
  "geometry": {"coordinates":[-122.441801,47.256861],"type":"Point"}
}