{
  "type": "Feature",
  "properties": {
    "addr:full":"12300 Lake City Way NE Seattle WA 98125",
    "addr:housenumber":"12300",
    "addr:postcode":"98125",
    "addr:street":"Lake City Way Ne",
    "iso:country":"US",
    "sg:address":"12300 Lake City Way NE",
    "sg:city":"Seattle",
    "sg:classifiers":[
        {
            "category":"Retail",
            "subcategory":"Auto Repair",
            "type":"Services"
        }
    ],
    "sg:phone":"+1 206 526 5979",
    "sg:postcode":"98125",
    "sg:province":"WA",
    "sg:website":"www.cardocs.com",
    "wof:name":"Northwest Automotive",
    "wof:placetype":"venue"
},
  "geometry": {"coordinates":[-122.29563400000001,47.717662],"type":"Point"}
}