{
  "type": "Feature",
  "properties": {
    "addr:full":"260 Cascade Mall Dr Burlington WA 98233",
    "addr:housenumber":"260",
    "addr:postcode":"98233",
    "addr:street":"Cascade Mall Dr",
    "iso:country":"US",
    "sg:address":"260 Cascade Mall Dr",
    "sg:city":"Burlington",
    "sg:classifiers":[
        {
            "category":"Shopping",
            "subcategory":"Gifts & Souvenirs",
            "type":"Retail Goods"
        }
    ],
    "sg:phone":"+1 360 757 2211",
    "sg:postcode":"98233",
    "sg:province":"WA",
    "wof:name":"Carlton Cards",
    "wof:placetype":"venue"
},
  "geometry": {"coordinates":[-122.336579,48.460118],"type":"Point"}
}