{
  "type": "Feature",
  "properties": {
    "addr:full":"9333 157th Ave SE Snohomish WA 98290",
    "addr:housenumber":"9333",
    "addr:postcode":"98290",
    "addr:street":"157Th Ave Se",
    "iso:country":"US",
    "sg:address":"9333 157th Ave SE",
    "sg:city":"Snohomish",
    "sg:classifiers":[
        {
            "category":"Retail",
            "subcategory":"Repair Shop",
            "type":"Services"
        }
    ],
    "sg:phone":"+1 425 487 0897",
    "sg:postcode":"98290",
    "sg:province":"WA",
    "sg:tags":[
        "equipment",
        "as",
        "such",
        "compressor",
        "air"
    ],
    "wof:name":"Complete Equipment Maintenance",
    "wof:placetype":"venue"
},
  "geometry": {"coordinates":[-122.02233,47.913272],"type":"Point"}
}