{
  "type": "Feature",
  "properties": {
    "addr:full":"15323 N Addison Ct Spokane WA 99208",
    "addr:housenumber":"15323",
    "addr:postcode":"99208",
    "addr:street":"N Addison Ct",
    "iso:country":"US",
    "sg:address":"15323 N Addison Ct",
    "sg:city":"Spokane",
    "sg:classifiers":[
        {
            "category":"Shopping",
            "subcategory":"Used Merchandise",
            "type":"Retail Goods"
        }
    ],
    "sg:phone":"+1 509 466 5018",
    "sg:postcode":"99208",
    "sg:province":"WA",
    "wof:name":"Shelly Hoerner Antiques &",
    "wof:placetype":"venue"
},
  "geometry": {"coordinates":[-117.402534,47.797796],"type":"Point"}
}