{
  "type": "Feature",
  "properties": {
    "addr:full":"2751 70th Ave SE Mercer Island WA 98040",
    "addr:housenumber":"2751",
    "addr:postcode":"98040",
    "addr:street":"70Th Ave Se",
    "iso:country":"US",
    "sg:address":"2751 70th Ave SE",
    "sg:city":"Mercer Island",
    "sg:classifiers":[
        {
            "category":"Professional",
            "subcategory":"Business Services",
            "type":"Services"
        }
    ],
    "sg:phone":"+1 206 232 6033",
    "sg:postcode":"98040",
    "sg:province":"WA",
    "wof:name":"Judith Bedard Interiors",
    "wof:placetype":"venue"
},
  "geometry": {"coordinates":[-122.244784,47.585257],"type":"Point"}
}