{
  "type": "Feature",
  "properties": {
    "addr:full":"3236 78th Avenue SE Ste Ste 200 Seattle WA 98101",
    "addr:housenumber":"3236",
    "addr:postcode":"98101",
    "addr:street":"78Th Avenue Se Ste Ste 200",
    "iso:country":"US",
    "sg:address":"3236 78th Avenue SE Ste Ste 200",
    "sg:city":"Seattle",
    "sg:classifiers":[
        {
            "category":"Health Services",
            "subcategory":"Doctor",
            "type":"Services"
        }
    ],
    "sg:phone":"+1 206 621 4600",
    "sg:postcode":"98101",
    "sg:province":"WA",
    "wof:name":"Pacmed Clinics",
    "wof:placetype":"venue"
},
  "geometry": {"coordinates":[-122.23324100000001,47.580745],"type":"Point"}
}