{
  "type": "Feature",
  "properties": {
    "addr:full":"482 Bunker Creek Rd Chehalis WA 98532",
    "addr:housenumber":"482",
    "addr:postcode":"98532",
    "addr:street":"Bunker Creek Rd",
    "iso:country":"US",
    "sg:address":"482 Bunker Creek Rd",
    "sg:city":"Chehalis",
    "sg:classifiers":[
        {
            "category":"Farming",
            "subcategory":"Dairy Farm",
            "type":"Manufacturing & Wholesale Goods"
        }
    ],
    "sg:phone":"+1 360 740 9819",
    "sg:postcode":"98532",
    "sg:province":"WA",
    "wof:name":"Brunoff Farms Inc",
    "wof:placetype":"venue"
},
  "geometry": {"coordinates":[-123.090503,46.645633],"type":"Point"}
}