{
  "type": "Feature",
  "properties": {
    "addr:full":"37 S Hudson St Seattle WA 98134",
    "addr:housenumber":"37",
    "addr:postcode":"98134",
    "addr:street":"S Hudson St",
    "iso:country":"US",
    "sg:address":"37 S Hudson St",
    "sg:city":"Seattle",
    "sg:classifiers":[
        {
            "category":"Manufacturing",
            "subcategory":"Furniture",
            "type":"Manufacturing & Wholesale Goods"
        }
    ],
    "sg:phone":"+1 206 763 1937",
    "sg:postcode":"98134",
    "sg:province":"WA",
    "sg:tags":[
        "mfg"
    ],
    "wof:name":"Carr J H & Sons Furniture Mfg",
    "wof:placetype":"venue"
},
  "geometry": {"coordinates":[-122.3368,47.55741],"type":"Point"}
}