{
  "type": "Feature",
  "properties": {
    "addr:full":"12305 NE 103rd Ave Vancouver WA 98662",
    "addr:housenumber":"12305",
    "addr:postcode":"98662",
    "addr:street":"Ne 103Rd Ave",
    "iso:country":"US",
    "sg:address":"12305 NE 103rd Ave",
    "sg:city":"Vancouver",
    "sg:classifiers":[
        {
            "category":"Professional",
            "type":"Services"
        }
    ],
    "sg:phone":"+1 360 885 1333",
    "sg:postcode":"98662",
    "sg:province":"WA",
    "wof:name":"Visualsynergies",
    "wof:placetype":"venue"
},
  "geometry": {"coordinates":[-122.56692200000001,45.708362],"type":"Point"}
}