{
  "type": "Feature",
  "properties": {
    "addr:full":"11108 Chennault Beach Rd Mukilteo WA 98275",
    "addr:housenumber":"11108",
    "addr:postcode":"98275",
    "addr:street":"Chennault Beach Rd",
    "iso:country":"US",
    "sg:address":"11108 Chennault Beach Rd",
    "sg:city":"Mukilteo",
    "sg:classifiers":[
        {
            "category":"Real Estate",
            "subcategory":"Real Estate Operator",
            "type":"Services"
        }
    ],
    "sg:phone":"+1 425 771 5092",
    "sg:postcode":"98275",
    "sg:province":"WA",
    "sg:tags":[
        "apartment"
    ],
    "wof:name":"Manor Building",
    "wof:placetype":"venue"
},
  "geometry": {"coordinates":[-122.304267,47.897964],"type":"Point"}
}