{
  "type": "Feature",
  "properties": {
    "addr:full":"1516 N Wenatchee Ave Wenatchee WA 98801",
    "addr:housenumber":"1516",
    "addr:postcode":"98801",
    "addr:street":"N Wenatchee Ave",
    "iso:country":"US",
    "sg:address":"1516 N Wenatchee Ave",
    "sg:city":"Wenatchee",
    "sg:classifiers":[
        {
            "category":"Restaurant",
            "type":"Food & Drink"
        }
    ],
    "sg:phone":"+1 509 662 7811",
    "sg:postcode":"98801",
    "sg:province":"WA",
    "wof:name":"Shari's Of Wenatchee",
    "wof:placetype":"venue"
},
  "geometry": {"coordinates":[-120.32768799999999,47.444579],"type":"Point"}
}