{
  "type": "Feature",
  "properties": {
    "addr:full":"6522 E 1st Ave Spokane Valley WA 99212",
    "addr:housenumber":"6522",
    "addr:postcode":"99212",
    "addr:street":"E 1St Ave",
    "iso:country":"US",
    "sg:address":"6522 E 1st Ave",
    "sg:city":"Spokane Valley",
    "sg:classifiers":[
        {
            "category":"Retail",
            "subcategory":"Veterinary Services",
            "type":"Services"
        }
    ],
    "sg:phone":"+1 509 535 8743",
    "sg:postcode":"99212",
    "sg:province":"WA",
    "sg:tags":[
        "veterinarian"
    ],
    "wof:name":"Tlc Veterinary Clinic",
    "wof:placetype":"venue"
},
  "geometry": {"coordinates":[-117.316475,47.656007],"type":"Point"}
}