{
  "type": "Feature",
  "properties": {
    "addr:full":"1471 Clark Rd Pasco WA 99301",
    "addr:housenumber":"1471",
    "addr:postcode":"99301",
    "addr:street":"Clark Rd",
    "iso:country":"US",
    "sg:address":"1471 Clark Rd",
    "sg:city":"Pasco",
    "sg:classifiers":[
        {
            "category":"Shopping",
            "subcategory":"Gifts & Souvenirs",
            "type":"Retail Goods"
        }
    ],
    "sg:phone":"+1 509 547 0952",
    "sg:postcode":"99301",
    "sg:province":"WA",
    "sg:tags":[
        "windsock"
    ],
    "wof:name":"Sky's The Limit Windsocks",
    "wof:placetype":"venue"
},
  "geometry": {"coordinates":[-119.152727,46.300032],"type":"Point"}
}