{
  "type": "Feature",
  "properties": {
    "iso:country":"US",
    "sg:address":"1332 7th St",
    "sg:city":"Clarkston",
    "sg:classifiers":[
        {
            "category":"Restaurant",
            "type":"Food & Drink"
        }
    ],
    "sg:phone":"+1 509 758 6422",
    "sg:postcode":"99403",
    "sg:province":"WA",
    "sg:tags":[
        "eating"
    ],
    "wof:name":"Savannah River Coffee Company",
    "wof:placetype":"venue"
},
  "geometry": {"coordinates":[-117.046925,46.404846],"type":"Point"}
}