{
  "type": "Feature",
  "properties": {
    "addr:full":"12432 Hwy 99 Everett WA 98204",
    "addr:housenumber":"12432",
    "addr:postcode":"98204",
    "addr:street":"Hwy 99",
    "iso:country":"US",
    "sg:address":"12432 Hwy 99",
    "sg:city":"Everett",
    "sg:classifiers":[
        {
            "category":"Retail",
            "subcategory":"Auto Repair",
            "type":"Services"
        }
    ],
    "sg:phone":"+1 425 355 3369",
    "sg:postcode":"98204",
    "sg:province":"WA",
    "sg:tags":[
        "repairing",
        "automobile",
        "system"
    ],
    "wof:name":"Evergreen Carburetors",
    "wof:placetype":"venue"
},
  "geometry": {"coordinates":[-122.26271300000001,47.885183],"type":"Point"}
}