{
  "type": "Feature",
  "properties": {
    "addr:full":"327 N College Ave College Place WA 99324",
    "addr:housenumber":"327",
    "addr:postcode":"99324",
    "addr:street":"N College Ave",
    "iso:country":"US",
    "sg:address":"327 N College Ave",
    "sg:city":"College Place",
    "sg:classifiers":[
        {
            "category":"Social Services",
            "subcategory":"Adult Care",
            "type":"Services"
        }
    ],
    "sg:phone":"+1 509 526 7707",
    "sg:postcode":"99324",
    "sg:province":"WA",
    "sg:tags":[
        "residential"
    ],
    "wof:name":"Sunny Side Inn Adult Family HM",
    "wof:placetype":"venue"
},
  "geometry": {"coordinates":[-118.388552,46.054063],"type":"Point"}
}