{
  "type": "Feature",
  "properties": {
    "addr:full":"301 NE 58th St Seattle WA 98105",
    "addr:housenumber":"301",
    "addr:postcode":"98105",
    "addr:street":"Ne 58Th St",
    "iso:country":"US",
    "sg:address":"301 NE 58th St",
    "sg:city":"Seattle",
    "sg:classifiers":[
        {
            "category":"Building & Trades",
            "subcategory":"Locksmith",
            "type":"Services"
        }
    ],
    "sg:phone":"+1 206 607 0783",
    "sg:postcode":"98105",
    "sg:province":"WA",
    "sg:tags":[
        "key"
    ],
    "wof:name":"A Locksmith 0 1 24 Hour",
    "wof:placetype":"venue"
},
  "geometry": {"coordinates":[-122.324163,47.670693],"type":"Point"}
}