{
  "type": "Feature",
  "properties": {
    "addr:full":"3416 NW 72nd St Seattle WA 98117",
    "addr:housenumber":"3416",
    "addr:postcode":"98117",
    "addr:street":"Nw 72Nd St",
    "iso:country":"US",
    "sg:address":"3416 NW 72nd St",
    "sg:city":"Seattle",
    "sg:classifiers":[
        {
            "category":"Professional",
            "subcategory":"Advertising",
            "type":"Services"
        }
    ],
    "sg:phone":"+1 206 784 2529",
    "sg:postcode":"98117",
    "sg:province":"WA",
    "sg:tags":[
        "agency",
        "specialty"
    ],
    "wof:name":"John Brandon & Associates",
    "wof:placetype":"venue"
},
  "geometry": {"coordinates":[-122.40187899999999,47.680948],"type":"Point"}
}