{
  "type": "Feature",
  "properties": {
    "addr:full":"9610 24th St E Puyallup WA 98371",
    "addr:housenumber":"9610",
    "addr:postcode":"98371",
    "addr:street":"24Th St E",
    "iso:country":"US",
    "sg:address":"9610 24th St E",
    "sg:city":"Puyallup",
    "sg:classifiers":[
        {
            "category":"Building & Trades",
            "subcategory":"Construction",
            "type":"Services"
        }
    ],
    "sg:phone":"+1 253 927 3040",
    "sg:postcode":"98371",
    "sg:province":"WA",
    "sg:tags":[
        "house"
    ],
    "wof:name":"Cameo Homes Inc",
    "wof:placetype":"venue"
},
  "geometry": {"coordinates":[-122.302418,47.235479],"type":"Point"}
}