{
  "type": "Feature",
  "properties": {
    "addr:full":"3519 56th St NW Gig Harbor WA 98335",
    "addr:housenumber":"3519",
    "addr:postcode":"98335",
    "addr:street":"56Th St Nw",
    "iso:country":"US",
    "sg:address":"3519 56th St NW",
    "sg:city":"Gig Harbor",
    "sg:classifiers":[
        {
            "category":"Building & Trades",
            "subcategory":"Construction",
            "type":"Services"
        }
    ],
    "sg:phone":"+1 253 851 9952",
    "sg:postcode":"98335",
    "sg:province":"WA",
    "sg:tags":[
        "contractor"
    ],
    "wof:name":"56th Street Pro Building",
    "wof:placetype":"venue"
},
  "geometry": {"coordinates":[-122.587281,47.30901],"type":"Point"}
}