{
  "type": "Feature",
  "properties": {
    "addr:full":"721 M St NE Auburn WA 98002",
    "addr:housenumber":"721",
    "addr:postcode":"98002",
    "addr:street":"M St Ne",
    "iso:country":"US",
    "sg:address":"721 M St NE",
    "sg:city":"Auburn",
    "sg:classifiers":[
        {
            "category":"Health Services",
            "subcategory":"Chiropractor",
            "type":"Services"
        }
    ],
    "sg:phone":"+1 253 939 9599",
    "sg:postcode":"98002",
    "sg:province":"WA",
    "wof:name":"Chase Chiropractic",
    "wof:placetype":"venue"
},
  "geometry": {"coordinates":[-122.213526,47.31417],"type":"Point"}
}