{
  "type": "Feature",
  "properties": {
    "addr:full":"12629 NE 144th St Kirkland WA 98034",
    "addr:housenumber":"12629",
    "addr:postcode":"98034",
    "addr:street":"Ne 144Th St",
    "iso:country":"US",
    "sg:address":"12629 NE 144th St",
    "sg:city":"Kirkland",
    "sg:classifiers":[
        {
            "category":"Social Services",
            "subcategory":"Child Care",
            "type":"Services"
        }
    ],
    "sg:phone":"+1 425 820 1326",
    "sg:postcode":"98034",
    "sg:province":"WA",
    "sg:tags":[
        "elementary",
        "kindergarten",
        "school",
        "day",
        "preschool"
    ],
    "sg:website":"www.lilpeoplesworld.com",
    "wof:name":"Lil People's World",
    "wof:placetype":"venue"
},
  "geometry": {"coordinates":[-122.171997,47.7314],"type":"Point"}
}