{
  "type": "Feature",
  "properties": {
    "addr:full":"14336 Courtland Pl N Seattle WA 98133",
    "addr:housenumber":"14336",
    "addr:postcode":"98133",
    "addr:street":"Courtland Pl N",
    "iso:country":"US",
    "sg:address":"14336 Courtland Pl N",
    "sg:city":"Seattle",
    "sg:classifiers":[
        {
            "category":"Retail",
            "subcategory":"Auto Repair",
            "type":"Services"
        }
    ],
    "sg:phone":"+1 206 417 5363",
    "sg:postcode":"98133",
    "sg:province":"WA",
    "sg:tags":[
        "repairing",
        "automobile"
    ],
    "wof:name":"Daichi Mobil Auto Svc",
    "wof:placetype":"venue"
},
  "geometry": {"coordinates":[-122.337993,47.733801],"type":"Point"}
}