{
  "type": "Feature",
  "properties": {
    "iso:country":"US",
    "sg:address":"2808 Summitview Ave",
    "sg:city":"Yakima",
    "sg:classifiers":[
        {
            "category":"Building & Trades",
            "subcategory":"Construction",
            "type":"Services"
        }
    ],
    "sg:phone":"+1 509 961 2576",
    "sg:postcode":"98902",
    "sg:province":"WA",
    "sg:tags":[
        "house"
    ],
    "wof:name":"KMA Construction",
    "wof:placetype":"venue"
},
  "geometry": {"coordinates":[-120.54744100000001,46.599834],"type":"Point"}
}