{
  "type": "Feature",
  "properties": {
    "addr:full":"210 E Lewis Pl Pasco WA 99301",
    "addr:housenumber":"210",
    "addr:postcode":"99301",
    "addr:street":"E Lewis Pl",
    "iso:country":"US",
    "sg:address":"210 E Lewis Pl",
    "sg:city":"Pasco",
    "sg:classifiers":[
        {
            "category":"Education",
            "subcategory":"Kindergarten",
            "type":"Public Place"
        }
    ],
    "sg:phone":"+1 509 547 2441",
    "sg:postcode":"99301",
    "sg:province":"WA",
    "sg:tags":[
        "school",
        "driving"
    ],
    "wof:name":"T Enterprises",
    "wof:placetype":"venue"
},
  "geometry": {"coordinates":[-119.049004,46.2328],"type":"Point"}
}