{
  "type": "Feature",
  "properties": {
    "addr:full":"21558 1st Ct S Seattle WA 98198",
    "addr:housenumber":"21558",
    "addr:postcode":"98198",
    "addr:street":"1St Ct S",
    "iso:country":"US",
    "sg:address":"21558 1st Ct S",
    "sg:city":"Seattle",
    "sg:classifiers":[
        {
            "category":"Wholesale",
            "subcategory":"Non-durable Goods",
            "type":"Manufacturing & Wholesale Goods"
        }
    ],
    "sg:phone":"+1 206 824 1023",
    "sg:postcode":"98198",
    "sg:province":"WA",
    "wof:name":"K&S Distributors",
    "wof:placetype":"venue"
},
  "geometry": {"coordinates":[-122.33315899999999,47.40869],"type":"Point"}
}