{
  "type": "Feature",
  "properties": {
    "iso:country":"US",
    "sg:address":"7912 NE 110th St",
    "sg:city":"Vancouver",
    "sg:classifiers":[
        {
            "category":"Shopping",
            "type":"Retail Goods"
        }
    ],
    "sg:phone":"+1 360 574 7720",
    "sg:postcode":"98662",
    "sg:province":"WA",
    "sg:tags":[
        "merchandise"
    ],
    "wof:name":"Moes Aquarium",
    "wof:placetype":"venue"
},
  "geometry": {"coordinates":[-122.598348,45.701466],"type":"Point"}
}