{
  "type": "Feature",
  "properties": {
    "addr:full":"9810 S 231st St Kent WA 98031",
    "addr:housenumber":"9810",
    "addr:postcode":"98031",
    "addr:street":"S 231St St",
    "iso:country":"US",
    "sg:address":"9810 S 231st St",
    "sg:city":"Kent",
    "sg:classifiers":[
        {
            "category":"Retail",
            "subcategory":"Funeral Services",
            "type":"Services"
        }
    ],
    "sg:phone":"+1 253 854 1678",
    "sg:postcode":"98031",
    "sg:province":"WA",
    "sg:tags":[
        "home"
    ],
    "wof:name":"S E Mid-Atlantic Inc",
    "wof:placetype":"venue"
},
  "geometry": {"coordinates":[-122.207493,47.394894],"type":"Point"}
}