{
  "type": "Feature",
  "properties": {
    "addr:full":"902 E E St Tacoma WA 98421",
    "addr:housenumber":"902",
    "addr:postcode":"98421",
    "addr:street":"E E St",
    "iso:country":"US",
    "sg:address":"902 E E St",
    "sg:city":"Tacoma",
    "sg:classifiers":[
        {
            "category":"Manufacturing",
            "subcategory":"Tools & Machinery",
            "type":"Manufacturing & Wholesale Goods"
        }
    ],
    "sg:phone":"+1 253 572 9637",
    "sg:postcode":"98421",
    "sg:province":"WA",
    "sg:tags":[
        "equipment",
        "material",
        "handling"
    ],
    "sg:website":"www.globelifts.com",
    "wof:name":"Globe International",
    "wof:placetype":"venue"
},
  "geometry": {"coordinates":[-122.43041700000001,47.256079],"type":"Point"}
}