{
  "type": "Feature",
  "properties": {
    "addr:full":"25261 SE Mirrormont Way Issaquah WA 98027",
    "addr:postcode":"25261;98027",
    "addr:street":"Se Mirrormont Way",
    "iso:country":"US",
    "sg:address":"25261 SE Mirrormont Way",
    "sg:city":"Issaquah",
    "sg:classifiers":[
        {
            "category":"Professional",
            "subcategory":"Business Services",
            "type":"Services"
        }
    ],
    "sg:phone":"+1 425 837 8973",
    "sg:postcode":"98027",
    "sg:province":"WA",
    "wof:name":"Thistle Enterprises LLC",
    "wof:placetype":"venue"
},
  "geometry": {"coordinates":[-122.002065,47.467193],"type":"Point"}
}