{
  "type": "Feature",
  "properties": {
    "iso:country":"US",
    "sg:address":"14548 SE 26th St",
    "sg:city":"Bellevue",
    "sg:classifiers":[
        {
            "category":"Taxi",
            "type":"Transportation"
        }
    ],
    "sg:phone":"+1 425 351 1000",
    "sg:postcode":"98007",
    "sg:province":"WA",
    "sg:tags":[
        "taxicab"
    ],
    "wof:name":"A A Bellevue Towncar Svc",
    "wof:placetype":"venue"
},
  "geometry": {"coordinates":[-122.145453,47.587584],"type":"Point"}
}