{
  "type": "Feature",
  "properties": {
    "addr:full":"4420 14th Ave NW Seattle WA 98107",
    "addr:housenumber":"4420",
    "addr:postcode":"98107",
    "addr:street":"14Th Ave Nw",
    "iso:country":"US",
    "sg:address":"4420 14th Ave NW",
    "sg:city":"Seattle",
    "sg:classifiers":[
        {
            "category":"Manufacturing",
            "subcategory":"Tools & Machinery",
            "type":"Manufacturing & Wholesale Goods"
        }
    ],
    "sg:phone":"+1 206 789 3600",
    "sg:postcode":"98107",
    "sg:province":"WA",
    "sg:tags":[
        "for",
        "that",
        "company",
        "mfg",
        "mari",
        "holding",
        "subsidiary"
    ],
    "wof:name":"Ade Holding Inc",
    "wof:placetype":"venue"
},
  "geometry": {"coordinates":[-122.373526,47.661343],"type":"Point"}
}