{
  "type": "Feature",
  "properties": {
    "addr:full":"344 Harbor Blvd Burbank WA 99323",
    "addr:housenumber":"344",
    "addr:postcode":"99323",
    "addr:street":"Harbor Blvd",
    "iso:country":"US",
    "sg:address":"344 Harbor Blvd",
    "sg:city":"Burbank",
    "sg:classifiers":[
        {
            "category":"Professional",
            "subcategory":"Management & Consulting",
            "type":"Services"
        }
    ],
    "sg:phone":"+1 509 546 0792",
    "sg:postcode":"99323",
    "sg:province":"WA",
    "sg:tags":[
        "consultant"
    ],
    "wof:name":"Garriga Associates",
    "wof:placetype":"venue"
},
  "geometry": {"coordinates":[-118.842949,46.250301],"type":"Point"}
}