{
  "type": "Feature",
  "properties": {
    "addr:full":"111 Larch St Woodland WA 98674",
    "addr:housenumber":"111",
    "addr:postcode":"98674",
    "addr:street":"Larch St",
    "iso:country":"US",
    "sg:address":"111 Larch St",
    "sg:city":"Woodland",
    "sg:classifiers":[
        {
            "category":"Building & Trades",
            "subcategory":"Construction",
            "type":"Services"
        }
    ],
    "sg:phone":"+1 253 225 3188",
    "sg:postcode":"98674",
    "sg:province":"WA",
    "sg:tags":[
        "contractor"
    ],
    "wof:name":"Aho Construction",
    "wof:placetype":"venue"
},
  "geometry": {"coordinates":[-122.727952,45.925077],"type":"Point"}
}