{
  "type": "Feature",
  "properties": {
    "addr:full":"9804 Edmonds Way Edmonds WA 98020",
    "addr:housenumber":"9804",
    "addr:postcode":"98020",
    "addr:street":"Edmonds Way",
    "iso:country":"US",
    "sg:address":"9804 Edmonds Way",
    "sg:city":"Edmonds",
    "sg:classifiers":[
        {
            "category":"Wholesale",
            "subcategory":"Machinery & Supplies",
            "type":"Manufacturing & Wholesale Goods"
        }
    ],
    "sg:phone":"+1 425 776 0844",
    "sg:postcode":"98020",
    "sg:province":"WA",
    "sg:tags":[
        "equipment",
        "establishment"
    ],
    "wof:name":"Q-Nails",
    "wof:placetype":"venue"
},
  "geometry": {"coordinates":[-122.363513,47.79051],"type":"Point"}
}