{
  "type": "Feature",
  "properties": {
    "addr:full":"90 Lancaster Rd Selah WA 98942",
    "addr:housenumber":"90",
    "addr:postcode":"98942",
    "addr:street":"Lancaster Rd",
    "iso:country":"US",
    "sg:address":"90 Lancaster Rd",
    "sg:city":"Selah",
    "sg:classifiers":[
        {
            "category":"Social Services",
            "subcategory":"Child Care",
            "type":"Services"
        }
    ],
    "sg:phone":"+1 509 698 3440",
    "sg:postcode":"98942",
    "sg:province":"WA",
    "sg:tags":[
        "center"
    ],
    "wof:name":"Dizzy D's Day Care",
    "wof:placetype":"venue"
},
  "geometry": {"coordinates":[-120.525189,46.671109],"type":"Point"}
}