{
  "type": "Feature",
  "properties": {
    "addr:full":"3603 S 242nd St Kent WA 98032",
    "addr:housenumber":"3603",
    "addr:postcode":"98032",
    "addr:street":"S 242Nd St",
    "iso:country":"US",
    "sg:address":"3603 S 242nd St",
    "sg:city":"Kent",
    "sg:classifiers":[
        {
            "category":"Building & Trades",
            "subcategory":"Construction",
            "type":"Services"
        }
    ],
    "sg:phone":"+1 206 870 8191",
    "sg:postcode":"98032",
    "sg:province":"WA",
    "sg:tags":[
        "house"
    ],
    "wof:name":"One Bad Cat Construction LLC",
    "wof:placetype":"venue"
},
  "geometry": {"coordinates":[-122.284627,47.385355],"type":"Point"}
}