{
  "type": "Feature",
  "properties": {
    "addr:full":"511 N Saint Hilaire Rd Yakima WA 98901",
    "addr:housenumber":"511",
    "addr:postcode":"98901",
    "addr:street":"N Saint Hilaire Rd",
    "iso:country":"US",
    "sg:address":"511 N Saint Hilaire Rd",
    "sg:city":"Yakima",
    "sg:classifiers":[
        {
            "category":"Building & Trades",
            "subcategory":"Landscaping Services",
            "type":"Services"
        }
    ],
    "sg:phone":"+1 509 575 1306",
    "sg:postcode":"98901",
    "sg:province":"WA",
    "wof:name":"Corral Irrigation & Lawn Care",
    "wof:placetype":"venue"
},
  "geometry": {"coordinates":[-120.359509,46.606926],"type":"Point"}
}