{
  "type": "Feature",
  "properties": {
    "addr:full":"2806 NE Sunset Blvd, Ste B Renton WA 98056",
    "addr:housenumber":"2806",
    "addr:postcode":"98056",
    "addr:street":"Ne Sunset Blvd Ste B",
    "iso:country":"US",
    "sg:address":"2806 NE Sunset Blvd, Ste B",
    "sg:city":"Renton",
    "sg:classifiers":[
        {
            "category":"Arena",
            "subcategory":"Sports Club",
            "type":"Entertainment"
        }
    ],
    "sg:phone":"+1 425 988 3047",
    "sg:postcode":"98056",
    "sg:province":"WA",
    "sg:tags":[
        "martial art"
    ],
    "sg:website":"www.exceedma.com",
    "wof:name":"Exceed Martial Arts",
    "wof:placetype":"venue"
},
  "geometry": {"coordinates":[-122.18107000000001,47.501604],"type":"Point"}
}