{
  "type": "Feature",
  "properties": {
    "addr:full":"2601 Cherry Ave Bremerton WA 98310",
    "addr:housenumber":"2601",
    "addr:postcode":"98310",
    "addr:street":"Cherry Ave",
    "iso:country":"US",
    "sg:address":"2601 Cherry Ave",
    "sg:city":"Bremerton",
    "sg:classifiers":[
        {
            "category":"Restaurant",
            "type":"Food & Drink"
        }
    ],
    "sg:phone":"+1 360 415 9733",
    "sg:postcode":"98310",
    "sg:province":"WA",
    "sg:tags":[
        "eating"
    ],
    "wof:name":"C & C Espresso",
    "wof:placetype":"venue"
},
  "geometry": {"coordinates":[-122.62526099999999,47.585494],"type":"Point"}
}