{
  "type": "Feature",
  "properties": {
    "addr:full":"10501 Aurora Ave N #2 Seattle WA 98133",
    "addr:housenumber":"10501",
    "addr:postcode":"98133",
    "addr:street":"Aurora Ave N # 2",
    "iso:country":"US",
    "sg:address":"10501 Aurora Ave N #2",
    "sg:city":"Seattle",
    "sg:classifiers":[
        {
            "category":"Insurance",
            "subcategory":"Hazard Insurance",
            "type":"Services"
        }
    ],
    "sg:phone":"+1 206 529 0262",
    "sg:postcode":"98133",
    "sg:province":"WA",
    "sg:website":"www.autoqwote.com",
    "wof:name":"Mike Howard Insurance Solutions",
    "wof:placetype":"venue"
},
  "geometry": {"coordinates":[-122.34483899999999,47.705033],"type":"Point"}
}