{
  "type": "Feature",
  "properties": {
    "addr:full":"101 Valley Rd Brewster WA 98812",
    "addr:housenumber":"101",
    "addr:postcode":"98812",
    "addr:street":"Valley Rd",
    "iso:country":"US",
    "sg:address":"101 Valley Rd",
    "sg:city":"Brewster",
    "sg:phone":"+1 509 689 3386",
    "sg:postcode":"98812",
    "sg:province":"WA",
    "sg:tags":[
        "farm",
        "field",
        "crop"
    ],
    "wof:name":"Richard R Downey",
    "wof:placetype":"venue"
},
  "geometry": {"coordinates":[-119.755022,48.154284],"type":"Point"}
}