{
  "type": "Feature",
  "properties": {
    "addr:full":"16116 E Kahlua Ln Mica WA 99023",
    "addr:housenumber":"16116",
    "addr:postcode":"99023",
    "addr:street":"E Kahlua Ln Mica",
    "iso:country":"US",
    "sg:address":"16116 E Kahlua Ln",
    "sg:city":"Mica",
    "sg:classifiers":[
        {
            "category":"Building & Trades",
            "subcategory":"Construction",
            "type":"Services"
        }
    ],
    "sg:phone":"+1 509 922 7062",
    "sg:postcode":"99023",
    "sg:province":"WA",
    "sg:tags":[
        "house"
    ],
    "wof:name":"Roemer Construction",
    "wof:placetype":"venue"
},
  "geometry": {"coordinates":[-117.19072199999999,47.542005],"type":"Point"}
}