{
  "type": "Feature",
  "properties": {
    "addr:full":"4850 S Washington St Tacoma WA 98409",
    "addr:housenumber":"4850",
    "addr:postcode":"98409",
    "addr:street":"S Washington St",
    "iso:country":"US",
    "sg:address":"4850 S Washington St",
    "sg:city":"Tacoma",
    "sg:phone":"+1 253 272 0321",
    "sg:postcode":"98409",
    "sg:province":"WA",
    "sg:tags":[
        "equipment"
    ],
    "wof:name":"Patrick-Hart Inc",
    "wof:placetype":"venue"
},
  "geometry": {"coordinates":[-122.48508099999999,47.212103],"type":"Point"}
}