{
  "type": "Feature",
  "properties": {
    "addr:full":"2515 Main St Yakima WA 98903",
    "addr:housenumber":"2515",
    "addr:postcode":"98903",
    "addr:street":"Main St",
    "iso:country":"US",
    "sg:address":"2515 Main St",
    "sg:city":"Yakima",
    "sg:classifiers":[
        {
            "category":"Professional",
            "subcategory":"Computer Services",
            "type":"Services"
        }
    ],
    "sg:phone":"+1 509 453 9131",
    "sg:postcode":"98903",
    "sg:province":"WA",
    "sg:tags":[
        "personal",
        "related"
    ],
    "wof:name":"Remember This Computer Photos",
    "wof:placetype":"venue"
},
  "geometry": {"coordinates":[-120.480726,46.564549],"type":"Point"}
}