{
  "type": "Feature",
  "properties": {
    "addr:full":"442 Ward Creek Rd Raymond WA 98577",
    "addr:housenumber":"442",
    "addr:postcode":"98577",
    "addr:street":"Ward Creek Rd",
    "iso:country":"US",
    "sg:address":"442 Ward Creek Rd",
    "sg:city":"Raymond",
    "sg:classifiers":[
        {
            "category":"Building & Trades",
            "subcategory":"Construction",
            "type":"Services"
        }
    ],
    "sg:phone":"+1 360 942 3319",
    "sg:postcode":"98577",
    "sg:province":"WA",
    "sg:tags":[
        "residential"
    ],
    "wof:name":"Boggs Construction Co",
    "wof:placetype":"venue"
},
  "geometry": {"coordinates":[-123.651045,46.696381],"type":"Point"}
}