{
  "type": "Feature",
  "properties": {
    "addr:full":"7018 E Sprague Ave Spokane Valley WA 99212",
    "addr:housenumber":"7018",
    "addr:postcode":"99212",
    "addr:street":"E Sprague Ave",
    "iso:country":"US",
    "sg:address":"7018 E Sprague Ave",
    "sg:city":"Spokane Valley",
    "sg:classifiers":[
        {
            "category":"Food & Beverages",
            "subcategory":"Groceries & Convenience Stores",
            "type":"Retail Goods"
        }
    ],
    "sg:phone":"+1 509 928 0280",
    "sg:postcode":"99212",
    "sg:province":"WA",
    "wof:name":"Jackpot",
    "wof:placetype":"venue"
},
  "geometry": {"coordinates":[-117.309646,47.656843],"type":"Point"}
}