{
  "type": "Feature",
  "properties": {
    "addr:full":"32541 36th Ave SW Federal Way WA 98023",
    "addr:housenumber":"32541",
    "addr:postcode":"98023",
    "addr:street":"36Th Ave Sw Federal Way",
    "iso:country":"US",
    "sg:address":"32541 36th Ave SW",
    "sg:city":"Federal Way",
    "sg:classifiers":[
        {
            "category":"Building & Trades",
            "subcategory":"Construction",
            "type":"Services"
        }
    ],
    "sg:phone":"+1 253 815 0636",
    "sg:postcode":"98023",
    "sg:province":"WA",
    "sg:tags":[
        "house"
    ],
    "wof:name":"Mt Quality Remodeling",
    "wof:placetype":"venue"
},
  "geometry": {"coordinates":[-122.37805400000001,47.311021],"type":"Point"}
}