{
  "type": "Feature",
  "properties": {
    "addr:full":"357 Leonard Rd Onalaska WA 98570",
    "addr:housenumber":"357",
    "addr:postcode":"98570",
    "addr:street":"Leonard Rd",
    "iso:country":"US",
    "sg:address":"357 Leonard Rd",
    "sg:city":"Onalaska",
    "sg:classifiers":[
        {
            "category":"Organizations",
            "subcategory":"Community Association",
            "type":"Services"
        }
    ],
    "sg:phone":"+1 360 978 4325",
    "sg:postcode":"98570",
    "sg:province":"WA",
    "wof:name":"Rebeccas",
    "wof:placetype":"venue"
},
  "geometry": {"coordinates":[-122.719786,46.557453],"type":"Point"}
}