{
  "type": "Feature",
  "properties": {
    "addr:full":"736 Edgewater Ln Moses Lake WA 98837",
    "addr:housenumber":"736",
    "addr:postcode":"98837",
    "addr:street":"Edgewater Ln",
    "iso:country":"US",
    "sg:address":"736 Edgewater Ln",
    "sg:city":"Moses Lake",
    "sg:classifiers":[
        {
            "category":"Social Services",
            "type":"Services"
        }
    ],
    "sg:phone":"+1 509 765 1907",
    "sg:postcode":"98837",
    "sg:province":"WA",
    "wof:name":"Martha L Schoessler",
    "wof:placetype":"venue"
},
  "geometry": {"coordinates":[-119.29041100000001,47.130363],"type":"Point"}
}