{
  "type": "Feature",
  "properties": {
    "addr:full":"703 Grand Blvd Vancouver WA 98661",
    "addr:housenumber":"703",
    "addr:postcode":"98661",
    "addr:street":"Grand Blvd",
    "iso:country":"US",
    "sg:address":"703 Grand Blvd",
    "sg:city":"Vancouver",
    "sg:classifiers":[
        {
            "category":"Coffee & Tea",
            "type":"Food & Drink"
        }
    ],
    "sg:phone":"+1 541 400 8389",
    "sg:postcode":"98661",
    "sg:province":"WA",
    "sg:website":"www.papertigercoffee.com/",
    "wof:name":"Paper Tiger Coffee Roasters",
    "wof:placetype":"venue"
},
  "geometry": {"coordinates":[-122.640587,45.626103],"type":"Point"}
}