{
  "type": "Feature",
  "properties": {
    "addr:full":"1514 N Greenacres Rd Greenacres WA 99016",
    "addr:housenumber":"1514",
    "addr:postcode":"99016",
    "addr:street":"N Greenacres Rd",
    "iso:country":"US",
    "sg:address":"1514 N Greenacres Rd",
    "sg:city":"Greenacres",
    "sg:classifiers":[
        {
            "category":"Manufacturing",
            "subcategory":"Retail Goods",
            "type":"Manufacturing & Wholesale Goods"
        }
    ],
    "sg:phone":"+1 509 924 1451",
    "sg:postcode":"99016",
    "sg:province":"WA",
    "sg:tags":[
        "product",
        "mfg"
    ],
    "wof:name":"Mead Tool",
    "wof:placetype":"venue"
},
  "geometry": {"coordinates":[-117.158968,47.671335],"type":"Point"}
}