{
  "type": "Feature",
  "properties": {
    "addr:full":"135 S Oak St Colville WA 99114",
    "addr:housenumber":"135",
    "addr:postcode":"99114",
    "addr:street":"S Oak St",
    "iso:country":"US",
    "sg:address":"135 S Oak St",
    "sg:city":"Colville",
    "sg:classifiers":[
        {
            "category":"Wholesale",
            "subcategory":"Medical Equipment & Supplies",
            "type":"Manufacturing & Wholesale Goods"
        }
    ],
    "sg:phone":"+1 509 684 3311",
    "sg:postcode":"99114",
    "sg:province":"WA",
    "sg:tags":[
        "hospital"
    ],
    "wof:name":"Lincare",
    "wof:placetype":"venue"
},
  "geometry": {"coordinates":[-117.904259,48.54408],"type":"Point"}
}