{
  "type": "Feature",
  "properties": {
    "addr:full":"9 Koven Rd Naselle WA 98638",
    "addr:housenumber":"9",
    "addr:postcode":"98638",
    "addr:street":"Koven Rd",
    "iso:country":"US",
    "sg:address":"9 Koven Rd",
    "sg:city":"Naselle",
    "sg:classifiers":[
        {
            "category":"Professional",
            "type":"Services"
        }
    ],
    "sg:phone":"+1 360 484 3286",
    "sg:postcode":"98638",
    "sg:province":"WA",
    "sg:tags":[
        "art",
        "fine",
        "artist"
    ],
    "wof:name":"Dark Horse Designs",
    "wof:placetype":"venue"
},
  "geometry": {"coordinates":[-123.816773,46.367198],"type":"Point"}
}