{
  "type": "Feature",
  "properties": {
    "addr:full":"10707 Fruitland Ave E Puyallup WA 98373",
    "addr:housenumber":"10707",
    "addr:postcode":"98373",
    "addr:street":"Fruitland Ave E",
    "iso:country":"US",
    "sg:address":"10707 Fruitland Ave E",
    "sg:city":"Puyallup",
    "sg:classifiers":[
        {
            "category":"Personal",
            "type":"Services"
        }
    ],
    "sg:phone":"+1 253 770 4146",
    "sg:postcode":"98373",
    "sg:province":"WA",
    "wof:name":"Transcndent Orgnztion Resource",
    "wof:placetype":"venue"
},
  "geometry": {"coordinates":[-122.32804400000001,47.161733],"type":"Point"}
}