{
  "type": "Feature",
  "properties": {
    "addr:full":"3225 Cedar St Everett WA 98201",
    "addr:housenumber":"3225",
    "addr:postcode":"98201",
    "addr:street":"Cedar St",
    "iso:country":"US",
    "sg:address":"3225 Cedar St",
    "sg:city":"Everett",
    "sg:classifiers":[
        {
            "category":"Transit Center",
            "subcategory":"Passenger",
            "type":"Transportation"
        },
        {
            "category":"Local Transit",
            "type":"Transportation"
        },
        {
            "category":"Government",
            "subcategory":"Office",
            "type":"Public Place"
        }
    ],
    "sg:phone":"+1 425 257 8803",
    "sg:postcode":"98201",
    "sg:province":"WA",
    "sg:tags":[
        "line"
    ],
    "sg:website":"http://www.walterhallgolf.com",
    "wof:name":"Everett Transit System",
    "wof:placetype":"venue"
},
  "geometry": {"coordinates":[-122.193907,47.975106],"type":"Point"}
}