{
  "type": "Feature",
  "properties": {
    "addr:full":"110 W 6th Ave Ellensburg WA 98926",
    "addr:housenumber":"110",
    "addr:postcode":"98926",
    "addr:street":"W 6Th Ave",
    "iso:country":"US",
    "sg:address":"110 W 6th Ave",
    "sg:city":"Ellensburg",
    "sg:classifiers":[
        {
            "category":"Professional",
            "type":"Services"
        }
    ],
    "sg:phone":"+1 509 965 8424",
    "sg:postcode":"98926",
    "sg:province":"WA",
    "wof:name":"Wind Dancer Inc",
    "wof:placetype":"venue"
},
  "geometry": {"coordinates":[-120.54861699999999,46.997485],"type":"Point"}
}