{
  "type": "Feature",
  "properties": {
    "addr:full":"3600 Forest Dr NE Bremerton WA 98310",
    "addr:housenumber":"3600",
    "addr:postcode":"98310",
    "addr:street":"Forest Dr Ne",
    "iso:country":"US",
    "sg:address":"3600 Forest Dr NE",
    "sg:city":"Bremerton",
    "sg:classifiers":[
        {
            "category":"Personal",
            "subcategory":"Barber",
            "type":"Services"
        }
    ],
    "sg:phone":"+1 360 792 1441",
    "sg:postcode":"98310",
    "sg:province":"WA",
    "sg:tags":[
        "shop"
    ],
    "wof:name":"Carols Barber Shop Styling",
    "wof:placetype":"venue"
},
  "geometry": {"coordinates":[-122.615759,47.598575],"type":"Point"}
}