{
  "type": "Feature",
  "properties": {
    "addr:full":"5510 Sugarloaf St Anacortes WA 98221",
    "addr:housenumber":"5510",
    "addr:postcode":"98221",
    "addr:street":"Sugarloaf St",
    "iso:country":"US",
    "sg:address":"5510 Sugarloaf St",
    "sg:city":"Anacortes",
    "sg:classifiers":[
        {
            "category":"Professional",
            "subcategory":"Research",
            "type":"Services"
        }
    ],
    "sg:phone":"+1 360 421 0632",
    "sg:postcode":"98221",
    "sg:province":"WA",
    "sg:tags":[
        "energy"
    ],
    "wof:name":"Sidalgo Energy",
    "wof:placetype":"venue"
},
  "geometry": {"coordinates":[-122.68292,48.498156],"type":"Point"}
}