{
  "type": "Feature",
  "properties": {
    "addr:full":"1800 NE 47th St Seattle WA 98105",
    "addr:housenumber":"1800",
    "addr:postcode":"98105",
    "addr:street":"Ne 47Th St",
    "iso:country":"US",
    "sg:address":"1800 NE 47th St",
    "sg:city":"Seattle",
    "sg:classifiers":[
        {
            "category":"Real Estate",
            "subcategory":"Real Estate Operator",
            "type":"Services"
        }
    ],
    "sg:phone":"+1 206 526 5353",
    "sg:postcode":"98105",
    "sg:province":"WA",
    "sg:tags":[
        "boarding",
        "house"
    ],
    "wof:name":"Delta Kappa Epsilon",
    "wof:placetype":"venue"
},
  "geometry": {"coordinates":[-122.307219,47.663056],"type":"Point"}
}