{
  "type": "Feature",
  "properties": {
    "addr:full":"8210 35th Ave NE Seattle WA 98115",
    "addr:housenumber":"8210",
    "addr:postcode":"98115",
    "addr:street":"35Th Ave Ne",
    "iso:country":"US",
    "sg:address":"8210 35th Ave NE",
    "sg:city":"Seattle",
    "sg:classifiers":[
        {
            "category":"Building & Trades",
            "subcategory":"Locksmith",
            "type":"Services"
        }
    ],
    "sg:phone":"+1 206 274 2512",
    "sg:postcode":"98115",
    "sg:province":"WA",
    "sg:tags":[
        "key"
    ],
    "wof:name":"1 Emergency 1 Day Locksmith In Seattle",
    "wof:placetype":"venue"
},
  "geometry": {"coordinates":[-122.29043799999999,47.6885],"type":"Point"}
}