{
  "type": "Feature",
  "properties": {
    "addr:full":"1117 Overhulse Rd NW Olympia WA 98502",
    "addr:housenumber":"1117",
    "addr:postcode":"olympia wa 98502",
    "addr:street":"Overhulse Rd Nw",
    "iso:country":"US",
    "sg:address":"1117 Overhulse Rd NW",
    "sg:city":"Olympia",
    "sg:classifiers":[
        {
            "category":"Shopping",
            "type":"Retail Goods"
        }
    ],
    "sg:phone":"+1 360 866 1366",
    "sg:postcode":"98502",
    "sg:province":"WA",
    "sg:tags":[
        "merchandise"
    ],
    "wof:name":"Matteson Sculpture",
    "wof:placetype":"venue"
},
  "geometry": {"coordinates":[-122.97075,47.059543],"type":"Point"}
}