{
  "type": "Feature",
  "properties": {
    "addr:full":"108 Wells Ave N Renton WA 98055",
    "addr:housenumber":"108",
    "addr:postcode":"98055",
    "addr:street":"Wells Ave N",
    "iso:country":"US",
    "sg:address":"108 Wells Ave N",
    "sg:city":"Renton",
    "sg:classifiers":[
        {
            "category":"Professional",
            "subcategory":"Lawyer & Legal Services",
            "type":"Services"
        }
    ],
    "sg:phone":"+1 425 277 0977",
    "sg:postcode":"98055",
    "sg:province":"WA",
    "wof:name":"Tracy David P Atty",
    "wof:placetype":"venue"
},
  "geometry": {"coordinates":[-122.204002,47.4846],"type":"Point"}
}