{
  "type": "Feature",
  "properties": {
    "addr:full":"4310 Hoyt Ave Everett WA 98203",
    "addr:housenumber":"4310",
    "addr:postcode":"98203",
    "addr:street":"Hoyt Ave",
    "iso:country":"US",
    "sg:address":"4310 Hoyt Ave",
    "sg:city":"Everett",
    "sg:classifiers":[
        {
            "category":"Health Services",
            "subcategory":"Clinic",
            "type":"Services"
        }
    ],
    "sg:phone":"+1 425 258 2474",
    "sg:postcode":"98203",
    "sg:province":"WA",
    "sg:tags":[
        "specialty",
        "outpatient"
    ],
    "wof:name":"HealthSouth",
    "wof:placetype":"venue"
},
  "geometry": {"coordinates":[-122.209271,47.959525],"type":"Point"}
}