{
  "type": "Feature",
  "properties": {
    "addr:full":"1310 141st Pl NE Bellevue WA 98007",
    "addr:housenumber":"1310",
    "addr:postcode":"98007",
    "addr:street":"141St Pl Ne",
    "iso:country":"US",
    "sg:address":"1310 141st Pl NE",
    "sg:city":"Bellevue",
    "sg:classifiers":[
        {
            "category":"Building & Trades",
            "subcategory":"Construction",
            "type":"Services"
        }
    ],
    "sg:phone":"+1 425 747 8172",
    "sg:postcode":"98007",
    "sg:province":"WA",
    "sg:tags":[
        "hanging",
        "wallpaper",
        "contractor"
    ],
    "wof:name":"Transformations",
    "wof:placetype":"venue"
},
  "geometry": {"coordinates":[-122.15181200000001,47.622256],"type":"Point"}
}