{
  "type": "Feature",
  "properties": {
    "addr:full":"555 Goss Rd Port Townsend WA 98368",
    "addr:housenumber":"555",
    "addr:postcode":"98368",
    "addr:street":"Goss Rd",
    "iso:country":"US",
    "sg:address":"555 Goss Rd",
    "sg:city":"Port Townsend",
    "sg:classifiers":[
        {
            "category":"Building & Trades",
            "subcategory":"Construction",
            "type":"Services"
        }
    ],
    "sg:phone":"+1 360 385 9677",
    "sg:postcode":"98368",
    "sg:province":"WA",
    "sg:tags":[
        "residential"
    ],
    "wof:name":"Gregory Grupe",
    "wof:placetype":"venue"
},
  "geometry": {"coordinates":[-122.87816100000001,48.087834],"type":"Point"}
}