{
  "type": "Feature",
  "properties": {
    "addr:full":"20123 SE 353rd St Auburn WA 98092",
    "addr:postcode":"20123;98092",
    "addr:street":"Se 353Rd St",
    "iso:country":"US",
    "sg:address":"20123 SE 353rd St",
    "sg:city":"Auburn",
    "sg:classifiers":[
        {
            "category":"Retail",
            "subcategory":"Portrait Studio",
            "type":"Services"
        }
    ],
    "sg:phone":"+1 253 833 0901",
    "sg:postcode":"98092",
    "sg:province":"WA",
    "sg:tags":[
        "photo"
    ],
    "wof:name":"Dove Portraits",
    "wof:placetype":"venue"
},
  "geometry": {"coordinates":[-122.07650099999999,47.285843],"type":"Point"}
}