{
  "type": "Feature",
  "properties": {
    "addr:full":"5634 87th Ave SE Olympia WA 98513",
    "addr:housenumber":"5634",
    "addr:postcode":"98513",
    "addr:street":"87Th Ave Se",
    "iso:country":"US",
    "sg:address":"5634 87th Ave SE",
    "sg:city":"Olympia",
    "sg:classifiers":[
        {
            "category":"Professional",
            "subcategory":"Management & Consulting",
            "type":"Services"
        }
    ],
    "sg:phone":"+1 360 491 2676",
    "sg:postcode":"98513",
    "sg:province":"WA",
    "wof:name":"Go Associates",
    "wof:placetype":"venue"
},
  "geometry": {"coordinates":[-122.808466,46.961908],"type":"Point"}
}