{
  "type": "Feature",
  "properties": {
    "addr:full":"1133 164th St SW Lynnwood WA 98087",
    "addr:housenumber":"1133",
    "addr:postcode":"98087",
    "addr:street":"164Th St Sw",
    "iso:country":"US",
    "sg:address":"1133 164th St SW",
    "sg:city":"Lynnwood",
    "sg:classifiers":[
        {
            "category":"Insurance",
            "subcategory":"Insurance Agent",
            "type":"Services"
        }
    ],
    "sg:phone":"+1 425 743 3046",
    "sg:postcode":"98087",
    "sg:province":"WA",
    "sg:website":"www.rdgsons.com",
    "wof:name":"Robert D Gregg & Sons",
    "wof:placetype":"venue"
},
  "geometry": {"coordinates":[-122.248301,47.849728],"type":"Point"}
}