{
  "type": "Feature",
  "properties": {
    "addr:full":"4423 N Division St Spokane WA 99207",
    "addr:housenumber":"4423",
    "addr:postcode":"99207",
    "addr:street":"N Division St",
    "iso:country":"US",
    "sg:address":"4423 N Division St",
    "sg:city":"Spokane",
    "sg:classifiers":[
        {
            "category":"Retail",
            "subcategory":"Auto Repair",
            "type":"Services"
        }
    ],
    "sg:phone":"+1 509 489 4563",
    "sg:postcode":"99207",
    "sg:province":"WA",
    "sg:tags":[
        "repairing",
        "automobile"
    ],
    "wof:name":"Goodyear Tire Ctr-New Concepts",
    "wof:placetype":"venue"
},
  "geometry": {"coordinates":[-117.411297,47.698056],"type":"Point"}
}