{
  "type": "Feature",
  "properties": {
    "addr:full":"1833 N 105th St Ste 201 Suite 570 Seattle WA 98133",
    "addr:housenumber":"1833",
    "addr:postcode":"98133",
    "addr:street":"N 105Th St Ste 201 Suite 570",
    "iso:country":"US",
    "sg:address":"1833 N 105th St Ste 201 Suite 570",
    "sg:city":"Seattle",
    "sg:classifiers":[
        {
            "category":"Professional",
            "subcategory":"Employment Agencies",
            "type":"Services"
        },
        {
            "category":"Organizations",
            "subcategory":"Non-profit Organization",
            "type":"Services"
        }
    ],
    "sg:phone":"+1 206 938 1253",
    "sg:postcode":"98133",
    "sg:province":"WA",
    "sg:tags":[
        "service/non-profit",
        "community"
    ],
    "wof:name":"Cares of Washington",
    "wof:placetype":"venue"
},
  "geometry": {"coordinates":[-122.334439,47.704837],"type":"Point"}
}