{
  "type": "Feature",
  "properties": {
    "addr:full":"18711 35th Ave NE Seattle WA 98155",
    "addr:housenumber":"18711",
    "addr:postcode":"98155",
    "addr:street":"35Th Ave Ne",
    "iso:country":"US",
    "sg:address":"18711 35th Ave NE",
    "sg:city":"Seattle",
    "sg:classifiers":[
        {
            "category":"Building & Trades",
            "subcategory":"Construction",
            "type":"Services"
        }
    ],
    "sg:phone":"+1 206 367 0623",
    "sg:postcode":"98155",
    "sg:province":"WA",
    "sg:tags":[
        "house"
    ],
    "wof:name":"Symphonic Builders",
    "wof:placetype":"venue"
},
  "geometry": {"coordinates":[-122.291974,47.764127],"type":"Point"}
}