{
  "type": "Feature",
  "properties": {
    "addr:full":"5471 Steilacoom Blvd SW Lakewood WA 98499",
    "addr:housenumber":"5471",
    "addr:postcode":"98499",
    "addr:street":"Steilacoom Blvd Sw",
    "iso:country":"US",
    "sg:address":"5471 Steilacoom Blvd SW",
    "sg:city":"Lakewood",
    "sg:classifiers":[
        {
            "category":"Wholesale",
            "subcategory":"Electrical",
            "type":"Manufacturing & Wholesale Goods"
        }
    ],
    "sg:phone":"+1 253 581 3965",
    "sg:postcode":"98499",
    "sg:province":"WA",
    "sg:tags":[
        "supply"
    ],
    "wof:name":"Jgu Service & Supply",
    "wof:placetype":"venue"
},
  "geometry": {"coordinates":[-122.511105,47.176655],"type":"Point"}
}