{
  "type": "Feature",
  "properties": {
    "addr:full":"4724 Price Rd Clayton WA 99110",
    "addr:housenumber":"4724",
    "addr:postcode":"99110",
    "addr:street":"Price Rd",
    "iso:country":"US",
    "sg:address":"4724 Price Rd",
    "sg:city":"Clayton",
    "sg:classifiers":[
        {
            "category":"Shopping",
            "subcategory":"Bicycles & Sporting Goods",
            "type":"Retail Goods"
        }
    ],
    "sg:phone":"+1 509 276 5165",
    "sg:postcode":"99110",
    "sg:province":"WA",
    "sg:tags":[
        "gun",
        "gunsmith"
    ],
    "wof:name":"PFBT Gun Parts",
    "wof:placetype":"venue"
},
  "geometry": {"coordinates":[-117.606059,47.97562],"type":"Point"}
}