{
  "type": "Feature",
  "properties": {
    "addr:full":"8403 Greenwood Ave N Seattle WA 98103",
    "addr:housenumber":"8403",
    "addr:postcode":"98103",
    "addr:street":"Greenwood Ave N",
    "iso:country":"US",
    "sg:address":"8403 Greenwood Ave N",
    "sg:city":"Seattle",
    "sg:classifiers":[
        {
            "category":"Professional",
            "type":"Services"
        },
        {
            "category":"Restaurant",
            "type":"Food & Drink"
        }
    ],
    "sg:phone":"+1 206 448 8555",
    "sg:postcode":"98103",
    "sg:province":"WA",
    "sg:tags":[
        "greek",
        "mediterranean",
        "caterer"
    ],
    "sg:website":"www.kouzina-greco.com",
    "wof:name":"Kouzina Restaurant N Zoey Catering",
    "wof:placetype":"venue"
},
  "geometry": {"coordinates":[-122.35530799999999,47.689873],"type":"Point"}
}