{
  "type": "Feature",
  "properties": {
    "addr:full":"2135 112th Ave NE Bellevue WA 98004",
    "addr:housenumber":"2135",
    "addr:postcode":"98004",
    "addr:street":"112Th Ave Ne",
    "iso:country":"US",
    "sg:address":"2135 112th Ave NE",
    "sg:city":"Bellevue",
    "sg:classifiers":[
        {
            "category":"Professional",
            "subcategory":"Lawyer & Legal Services",
            "type":"Services"
        }
    ],
    "sg:phone":"+1 425 451 3744",
    "sg:postcode":"98004",
    "sg:province":"WA",
    "sg:tags":[
        "attorney"
    ],
    "sg:website":"www.hhattorney.com",
    "wof:name":"Holly M Holhlbein Law Offices",
    "wof:placetype":"venue"
},
  "geometry": {"coordinates":[-122.191,47.631759],"type":"Point"}
}