{
  "type": "Feature",
  "properties": {
    "addr:full":"435 NW North St Pullman WA 99163",
    "addr:housenumber":"435",
    "addr:postcode":"99163",
    "addr:street":"Nw North St",
    "iso:country":"US",
    "sg:address":"435 NW North St",
    "sg:city":"Pullman",
    "sg:classifiers":[
        {
            "category":"Building & Trades",
            "subcategory":"Electrical",
            "type":"Services"
        }
    ],
    "sg:phone":"+1 509 334 2700",
    "sg:postcode":"99163",
    "sg:province":"WA",
    "sg:tags":[
        "industrial",
        "electrician",
        "electric",
        "contractors-commercial"
    ],
    "wof:name":"Harris Electrical Contractors",
    "wof:placetype":"venue"
},
  "geometry": {"coordinates":[-117.180391,46.746149],"type":"Point"}
}