{
  "type": "Feature",
  "properties": {
    "addr:full":"1817 Queen Anne Ave N Ste 211 Seattle WA 98109",
    "addr:housenumber":"1817",
    "addr:postcode":"98109",
    "addr:street":"Queen Anne Ave N Ste 211",
    "iso:country":"US",
    "sg:address":"1817 Queen Anne Ave N Ste 211",
    "sg:city":"Seattle",
    "sg:classifiers":[
        {
            "category":"Professional",
            "subcategory":"Lawyer & Legal Services",
            "type":"Services"
        }
    ],
    "sg:phone":"+1 206 427 4456",
    "sg:postcode":"98109",
    "sg:province":"WA",
    "sg:tags":[
        "personal",
        "injury"
    ],
    "sg:website":"www.filutowskilaw.com",
    "wof:name":"The Filutowski Law Firm, PLLC",
    "wof:placetype":"venue"
},
  "geometry": {"coordinates":[-122.357358,47.635348],"type":"Point"}
}