{
  "type": "Feature",
  "properties": {
    "addr:full":"820 W Francis Ave Spokane WA 99205",
    "addr:housenumber":"820",
    "addr:postcode":"99205",
    "addr:street":"W Francis Ave",
    "iso:country":"US",
    "sg:address":"820 W Francis Ave",
    "sg:city":"Spokane",
    "sg:classifiers":[
        {
            "category":"Retail",
            "subcategory":"Repair Shop",
            "type":"Services"
        },
        {
            "category":"Shopping",
            "type":"Retail Goods"
        }
    ],
    "sg:phone":"+1 509 484 3535",
    "sg:postcode":"99205",
    "sg:province":"WA",
    "sg:tags":[
        "picture",
        "art",
        "frame",
        "custom",
        "framing",
        "gallery"
    ],
    "wof:name":"William Grant Gallery & Framng",
    "wof:placetype":"venue"
},
  "geometry": {"coordinates":[-117.424072,47.715232],"type":"Point"}
}