{
  "type": "Feature",
  "properties": {
    "addr:full":"777 108th Ave NE Bellevue WA 98004",
    "addr:housenumber":"777",
    "addr:postcode":"98004",
    "addr:street":"108Th Ave Ne",
    "iso:country":"US",
    "sg:address":"777 108th Ave NE",
    "sg:city":"Bellevue",
    "sg:classifiers":[
        {
            "category":"Professional",
            "subcategory":"Lawyer & Legal Services",
            "type":"Services"
        }
    ],
    "sg:phone":"+1 425 455 1234",
    "sg:postcode":"98004",
    "sg:province":"WA",
    "wof:name":"Wiese Brett N Atty",
    "wof:placetype":"venue"
},
  "geometry": {"coordinates":[-122.195999,47.6171],"type":"Point"}
}