{
  "type": "Feature",
  "properties": {
    "addr:full":"21010 83rd Ave W Apt 1 Edmonds WA 98026",
    "addr:housenumber":"21010;1",
    "addr:postcode":"98026",
    "addr:street":"83Rd Ave W Apt",
    "iso:country":"US",
    "sg:address":"21010 83rd Ave W Apt 1",
    "sg:city":"Edmonds",
    "sg:classifiers":[
        {
            "category":"Real Estate",
            "subcategory":"Real Estate Services",
            "type":"Services"
        },
        {
            "category":"Real Estate",
            "subcategory":"Real Estate Operator",
            "type":"Services"
        }
    ],
    "sg:phone":"+1 425 771 7209",
    "sg:postcode":"98026",
    "sg:province":"WA",
    "sg:tags":[
        "vacancy",
        "apartment",
        "rental",
        "finder",
        "listing"
    ],
    "wof:name":"Woodridge Apartments Inc",
    "wof:placetype":"venue"
},
  "geometry": {"coordinates":[-122.34500199999999,47.80881],"type":"Point"}
}