{
  "type": "Feature",
  "properties": {
    "addr:full":"1370 Stewart St Seattle WA 98109",
    "addr:housenumber":"1370",
    "addr:postcode":"98109",
    "addr:street":"Stewart St",
    "iso:country":"US",
    "sg:address":"1370 Stewart St",
    "sg:city":"Seattle",
    "sg:classifiers":[
        {
            "category":"Communications",
            "subcategory":"Film & Video Production",
            "type":"Services"
        }
    ],
    "sg:phone":"+1 206 652 5738",
    "sg:postcode":"98109",
    "sg:province":"WA",
    "sg:tags":[
        "motion",
        "picture"
    ],
    "wof:name":"Kostov & Associates",
    "wof:placetype":"venue"
},
  "geometry": {"coordinates":[-122.32978,47.619089],"type":"Point"}
}