{
  "type": "Feature",
  "properties": {
    "addr:full":"1663 S 74th St Tacoma WA 98408",
    "addr:housenumber":"1663",
    "addr:postcode":"98408",
    "addr:street":"S 74Th St",
    "iso:country":"US",
    "sg:address":"1663 S 74th St",
    "sg:city":"Tacoma",
    "sg:classifiers":[
        {
            "category":"Wholesale",
            "subcategory":"Groceries",
            "type":"Manufacturing & Wholesale Goods"
        }
    ],
    "sg:phone":"+1 253 473 4416",
    "sg:postcode":"98408",
    "sg:province":"WA",
    "wof:name":"Cool Beans",
    "wof:placetype":"venue"
},
  "geometry": {"coordinates":[-122.457606,47.190195],"type":"Point"}
}