{
  "type": "Feature",
  "properties": {
    "addr:full":"806 Officers Row Vancouver WA 98661",
    "addr:housenumber":"806",
    "addr:postcode":"98661",
    "addr:street":"Officers Row",
    "iso:country":"US",
    "sg:address":"806 Officers Row",
    "sg:city":"Vancouver",
    "sg:classifiers":[
        {
            "category":"Building & Trades",
            "subcategory":"Construction",
            "type":"Services"
        }
    ],
    "sg:phone":"+1 360 993 2275",
    "sg:postcode":"98661",
    "sg:province":"WA",
    "sg:tags":[
        "house"
    ],
    "wof:name":"Sovereign Homes",
    "wof:placetype":"venue"
},
  "geometry": {"coordinates":[-122.66478499999999,45.629774],"type":"Point"}
}