{
  "type": "Feature",
  "properties": {
    "addr:full":"570 Sauk Ave Darrington WA 98241",
    "addr:housenumber":"570",
    "addr:postcode":"98241",
    "addr:street":"Sauk Ave",
    "iso:country":"US",
    "sg:address":"570 Sauk Ave",
    "sg:city":"Darrington",
    "sg:classifiers":[
        {
            "category":"Social Services",
            "type":"Services"
        }
    ],
    "sg:phone":"+1 360 436 1833",
    "sg:postcode":"98241",
    "sg:province":"WA",
    "wof:name":"Darrington Community Svcs Ctr",
    "wof:placetype":"venue"
},
  "geometry": {"coordinates":[-121.604675,48.247714],"type":"Point"}
}