{
  "type": "Feature",
  "properties": {
    "iso:country":"US",
    "sg:address":"202 N Cedar St",
    "sg:city":"Port Angeles",
    "sg:classifiers":[
        {
            "category":"Building & Trades",
            "subcategory":"Equipment Rental",
            "type":"Services"
        }
    ],
    "sg:phone":"+1 360 808 5775",
    "sg:postcode":"98363",
    "sg:province":"WA",
    "sg:tags":[
        "heavy",
        "construction"
    ],
    "wof:name":"Baseline Cranes",
    "wof:placetype":"venue"
},
  "geometry": {"coordinates":[-123.443522,48.123224],"type":"Point"}
}