{
  "type": "Feature",
  "properties": {
    "addr:full":"16636 NE 172nd Pl Woodinville WA 98072",
    "addr:housenumber":"16636",
    "addr:postcode":"98072",
    "addr:street":"Ne 172Nd Pl",
    "iso:country":"US",
    "sg:address":"16636 NE 172nd Pl",
    "sg:city":"Woodinville",
    "sg:classifiers":[
        {
            "category":"Building & Trades",
            "subcategory":"Plumbing",
            "type":"Services"
        }
    ],
    "sg:phone":"+1 425 483 8111",
    "sg:postcode":"98072",
    "sg:province":"WA",
    "sg:tags":[
        "contractor"
    ],
    "wof:name":"Erickson & Associates",
    "wof:placetype":"venue"
},
  "geometry": {"coordinates":[-122.116366,47.752755],"type":"Point"}
}