{
  "type": "Feature",
  "properties": {
    "addr:full":"1600 E Jefferson St Seattle WA 98122",
    "addr:housenumber":"1600",
    "addr:postcode":"98122",
    "addr:street":"E Jefferson St",
    "iso:country":"US",
    "sg:address":"1600 E Jefferson St",
    "sg:city":"Seattle",
    "sg:classifiers":[
        {
            "category":"Health Services",
            "subcategory":"Doctor",
            "type":"Services"
        }
    ],
    "sg:phone":"+1 206 323 2777",
    "sg:postcode":"98122",
    "sg:province":"WA",
    "sg:tags":[
        "medicine",
        "sport",
        "orthopedist"
    ],
    "wof:name":"Kvidera Dennis J MD",
    "wof:placetype":"venue"
},
  "geometry": {"coordinates":[-122.30999799999999,47.610802],"type":"Point"}
}