{
  "type": "Feature",
  "properties": {
    "addr:full":"1045 Montague Ave Darrington WA 98241",
    "addr:housenumber":"1045",
    "addr:postcode":"98241",
    "addr:street":"Montague Ave",
    "iso:country":"US",
    "sg:address":"1045 Montague Ave",
    "sg:city":"Darrington",
    "sg:classifiers":[
        {
            "category":"Organizations",
            "subcategory":"Religious Organization",
            "type":"Services"
        }
    ],
    "sg:phone":"+1 360 436 1671",
    "sg:postcode":"98241",
    "sg:province":"WA",
    "sg:tags":[
        "clergy"
    ],
    "wof:name":"Michael De Luca",
    "wof:placetype":"venue"
},
  "geometry": {"coordinates":[-121.6006,48.256664],"type":"Point"}
}