{
  "type": "Feature",
  "properties": {
    "addr:full":"3742 S 144th St Tukwila WA 98168",
    "addr:housenumber":"3742",
    "addr:postcode":"98168",
    "addr:street":"S 144Th St",
    "iso:country":"US",
    "sg:address":"3742 S 144th St",
    "sg:city":"Tukwila",
    "sg:classifiers":[
        {
            "category":"Restaurant",
            "type":"Food & Drink"
        }
    ],
    "sg:phone":"+1 206 246 5158",
    "sg:postcode":"98168",
    "sg:province":"WA",
    "sg:tags":[
        "chicken",
        "fast"
    ],
    "sg:website":"http://www.kfc.com",
    "wof:name":"Kfc",
    "wof:placetype":"venue"
},
  "geometry": {"coordinates":[-122.285028,47.47422],"type":"Point"}
}