{
  "type": "Feature",
  "properties": {
    "iso:country":"US",
    "sg:address":"1325 82nd St NW",
    "sg:city":"Marysville",
    "sg:classifiers":[
        {
            "category":"Shopping",
            "subcategory":"Catalog Store",
            "type":"Retail Goods"
        }
    ],
    "sg:phone":"+1 360 659 9031",
    "sg:postcode":"98271",
    "sg:province":"WA",
    "sg:tags":[
        "mail",
        "house"
    ],
    "wof:name":"Gallerycraftscom",
    "wof:placetype":"venue"
},
  "geometry": {"coordinates":[-122.252819,48.070722],"type":"Point"}
}