{
  "type": "Feature",
  "properties": {
    "addr:full":"14106 55th Ave W Edmonds WA 98026",
    "addr:housenumber":"14106",
    "addr:postcode":"98026",
    "addr:street":"55Th Ave W",
    "iso:country":"US",
    "sg:address":"14106 55th Ave W",
    "sg:city":"Edmonds",
    "sg:classifiers":[
        {
            "category":"Real Estate",
            "subcategory":"Architect",
            "type":"Services"
        }
    ],
    "sg:phone":"+1 425 787 2516",
    "sg:postcode":"98026",
    "sg:province":"WA",
    "sg:tags":[
        "architectural"
    ],
    "wof:name":"Geigle Designs",
    "wof:placetype":"venue"
},
  "geometry": {"coordinates":[-122.307254,47.870236],"type":"Point"}
}