{
  "type": "Feature",
  "properties": {
    "addr:full":"1409 NW 85th St Seattle WA 98117",
    "addr:housenumber":"1409",
    "addr:postcode":"98117",
    "addr:street":"Nw 85Th St",
    "iso:country":"US",
    "sg:address":"1409 NW 85th St",
    "sg:city":"Seattle",
    "sg:classifiers":[
        {
            "category":"Health Services",
            "subcategory":"Health Practitioner",
            "type":"Services"
        }
    ],
    "sg:phone":"+1 206 781 2206",
    "sg:postcode":"98117",
    "sg:province":"WA",
    "sg:tags":[
        "naturopathic/holistic"
    ],
    "sg:website":"www.emeraldcityclinic.com",
    "wof:name":"Emerald City Clinic",
    "wof:placetype":"venue"
},
  "geometry": {"coordinates":[-122.374841,47.690605],"type":"Point"}
}