{
  "type": "Feature",
  "properties": {
    "addr:full":"717 W Yakima Ave Yakima WA 98902",
    "addr:housenumber":"717",
    "addr:postcode":"98902",
    "addr:street":"W Yakima Ave",
    "iso:country":"US",
    "sg:address":"717 W Yakima Ave",
    "sg:city":"Yakima",
    "sg:classifiers":[
        {
            "category":"Autos & Motor Vehicles",
            "subcategory":"Auto Supplies",
            "type":"Retail Goods"
        }
    ],
    "sg:phone":"+1 509 453 0299",
    "sg:postcode":"98902",
    "sg:province":"WA",
    "sg:tags":[
        "automobile",
        "parts",
        "accessory"
    ],
    "wof:name":"Auto Accessories Guadalajara",
    "wof:placetype":"venue"
},
  "geometry": {"coordinates":[-120.519899,46.599143],"type":"Point"}
}