{
  "type": "Feature",
  "properties": {
    "addr:full":"1010 Railroad Ave Bellingham WA 98225",
    "addr:housenumber":"1010",
    "addr:postcode":"98225",
    "addr:street":"Railroad",
    "iso:country":"US",
    "sg:address":"1010 Railroad Ave",
    "sg:city":"Bellingham",
    "sg:classifiers":[
        {
            "category":"Retail",
            "subcategory":"Funeral Services",
            "type":"Services"
        }
    ],
    "sg:phone":"+1 360 647 3499",
    "sg:postcode":"98225",
    "sg:province":"WA",
    "sg:tags":[
        "cemetery"
    ],
    "wof:name":"1010 Morse Square",
    "wof:placetype":"venue"
},
  "geometry": {"coordinates":[-122.482253,48.746497],"type":"Point"}
}