{
  "type": "Feature",
  "properties": {
    "addr:full":"19654 NE 133rd St Woodinville WA 98077",
    "addr:housenumber":"19654",
    "addr:postcode":"98077",
    "addr:street":"Ne 133Rd St",
    "iso:country":"US",
    "sg:address":"19654 NE 133rd St",
    "sg:city":"Woodinville",
    "sg:classifiers":[
        {
            "category":"Organizations",
            "subcategory":"Religious Organization",
            "type":"Services"
        }
    ],
    "sg:phone":"+1 425 882 0761",
    "sg:postcode":"98077",
    "sg:province":"WA",
    "sg:website":"www.impact-ministries.org",
    "wof:name":"Impact Ministries",
    "wof:placetype":"venue"
},
  "geometry": {"coordinates":[-122.075996,47.717662],"type":"Point"}
}