{
  "type": "Feature",
  "properties": {
    "addr:full":"12244 SE 25th St Bellevue WA 98005",
    "addr:postcode":"12244;98005",
    "addr:street":"Se 25Th St",
    "iso:country":"US",
    "sg:address":"12244 SE 25th St",
    "sg:city":"Bellevue",
    "sg:classifiers":[
        {
            "category":"Professional",
            "subcategory":"Business Services",
            "type":"Services"
        }
    ],
    "sg:phone":"+1 425 641 4214",
    "sg:postcode":"98005",
    "sg:province":"WA",
    "wof:name":"Barbara Kalis Interior Design",
    "wof:placetype":"venue"
},
  "geometry": {"coordinates":[-122.176423,47.588802],"type":"Point"}
}