{
  "type": "Feature",
  "properties": {
    "addr:full":"5598 Rd L NE Moses Lake WA 98837",
    "addr:housenumber":"5598",
    "addr:postcode":"98837",
    "addr:street":"Rd",
    "iso:country":"US",
    "sg:address":"5598 Rd L NE",
    "sg:city":"Moses Lake",
    "sg:classifiers":[
        {
            "category":"Building & Trades",
            "subcategory":"Construction",
            "type":"Services"
        }
    ],
    "sg:phone":"+1 509 766 6862",
    "sg:postcode":"98837",
    "sg:province":"WA",
    "sg:tags":[
        "roofing",
        "window",
        "siding",
        "contractor"
    ],
    "wof:name":"Strickland Exteriors",
    "wof:placetype":"venue"
},
  "geometry": {"coordinates":[-119.235394,47.164578],"type":"Point"}
}