{
  "type": "Feature",
  "properties": {
    "addr:full":"2420 Gilson Rd Addy WA 99101",
    "addr:housenumber":"2420",
    "addr:postcode":"99101",
    "addr:street":"Gilson Rd",
    "iso:country":"US",
    "sg:address":"2420 Gilson Rd",
    "sg:city":"Addy",
    "sg:classifiers":[
        {
            "category":"Personal",
            "type":"Services"
        }
    ],
    "sg:phone":"+1 509 935 6989",
    "sg:postcode":"99101",
    "sg:province":"WA",
    "wof:name":"Ink Expressions Tattoo",
    "wof:placetype":"venue"
},
  "geometry": {"coordinates":[-117.985455,48.273627],"type":"Point"}
}