{
  "type": "Feature",
  "properties": {
    "addr:full":"1504 W Lewis St Pasco WA 99301",
    "addr:housenumber":"1504",
    "addr:postcode":"99301",
    "addr:street":"W Lewis St",
    "iso:country":"US",
    "sg:address":"1504 W Lewis St",
    "sg:city":"Pasco",
    "sg:classifiers":[
        {
            "category":"Food & Beverages",
            "subcategory":"Meat & Fish",
            "type":"Retail Goods"
        }
    ],
    "sg:phone":"+1 509 542 1738",
    "sg:postcode":"99301",
    "sg:province":"WA",
    "sg:tags":[
        "shop"
    ],
    "wof:name":"Los Pinos",
    "wof:placetype":"venue"
},
  "geometry": {"coordinates":[-119.108002,46.227901],"type":"Point"}
}