{
  "type": "Feature",
  "properties": {
    "addr:full":"3470 Astoria Rd Mesa WA 99343",
    "addr:housenumber":"3470",
    "addr:postcode":"99343",
    "addr:street":"Astoria Rd",
    "iso:country":"US",
    "sg:address":"3470 Astoria Rd",
    "sg:city":"Mesa",
    "sg:phone":"+1 509 265 4566",
    "sg:postcode":"99343",
    "sg:province":"WA",
    "sg:tags":[
        "farm",
        "field",
        "corn",
        "crop"
    ],
    "wof:name":"Jed Crowther",
    "wof:placetype":"venue"
},
  "geometry": {"coordinates":[-119.02762,46.628131],"type":"Point"}
}