{
  "type": "Feature",
  "properties": {
    "addr:full":"1720 S 341st Pl Federal Way WA 98003",
    "addr:housenumber":"1720",
    "addr:postcode":"98003",
    "addr:street":"S 341St Pl",
    "iso:country":"US",
    "sg:address":"1720 S 341st Pl",
    "sg:city":"Federal Way",
    "sg:classifiers":[
        {
            "category":"Arts & Performance",
            "subcategory":"Theater",
            "type":"Entertainment"
        }
    ],
    "sg:phone":"+1 253 862 7141",
    "sg:postcode":"98003",
    "sg:province":"WA",
    "sg:tags":[
        "live",
        "music"
    ],
    "wof:name":"Affordable Mobile Music",
    "wof:placetype":"venue"
},
  "geometry": {"coordinates":[-122.31209699999999,47.295778],"type":"Point"}
}