{
  "type": "Feature",
  "properties": {
    "addr:full":"24 Roy St Seattle WA 98109",
    "addr:housenumber":"24",
    "addr:postcode":"98109",
    "addr:street":"Roy St",
    "iso:country":"US",
    "sg:address":"24 Roy St",
    "sg:city":"Seattle",
    "sg:classifiers":[
        {
            "category":"Manufacturing",
            "subcategory":"Furniture",
            "type":"Manufacturing & Wholesale Goods"
        }
    ],
    "sg:phone":"+1 206 384 0834",
    "sg:postcode":"98109",
    "sg:province":"WA",
    "sg:tags":[
        "building",
        "public",
        "mfg"
    ],
    "wof:name":"Two Zero Six Inc",
    "wof:placetype":"venue"
},
  "geometry": {"coordinates":[-122.35560099999999,47.625526],"type":"Point"}
}