{
  "type": "Feature",
  "properties": {
    "addr:full":"1845 NW 195th St Shoreline WA 98177",
    "addr:housenumber":"1845",
    "addr:postcode":"98177",
    "addr:street":"Nw 195Th St",
    "iso:country":"US",
    "sg:address":"1845 NW 195th St",
    "sg:city":"Shoreline",
    "sg:classifiers":[
        {
            "category":"Professional",
            "subcategory":"Lawyer & Legal Services",
            "type":"Services"
        }
    ],
    "sg:phone":"+1 206 542 7431",
    "sg:postcode":"98177",
    "sg:province":"WA",
    "sg:tags":[
        "attorney"
    ],
    "wof:name":"Sandra R Cribbs",
    "wof:placetype":"venue"
},
  "geometry": {"coordinates":[-122.380517,47.770559],"type":"Point"}
}