{
  "type": "Feature",
  "properties": {
    "addr:full":"20208 SE 26th St Sammamish WA 98075",
    "addr:postcode":"20208;98075",
    "addr:street":"Se 26Th St",
    "iso:country":"US",
    "sg:address":"20208 SE 26th St",
    "sg:city":"Sammamish",
    "sg:classifiers":[
        {
            "category":"Education",
            "subcategory":"Special Training",
            "type":"Public Place"
        }
    ],
    "sg:phone":"+1 425 746 3108",
    "sg:postcode":"98075",
    "sg:province":"WA",
    "sg:tags":[
        "school",
        "educational"
    ],
    "wof:name":"Rescue First Aid",
    "wof:placetype":"venue"
},
  "geometry": {"coordinates":[-122.067717,47.586715],"type":"Point"}
}