{
  "type": "Feature",
  "properties": {
    "addr:full":"1907 Harrison Ave NW Olympia WA 98502",
    "addr:housenumber":"1907",
    "addr:postcode":"olympia wa 98502",
    "addr:street":"Harrison Ave Nw",
    "iso:country":"US",
    "sg:address":"1907 Harrison Ave NW",
    "sg:city":"Olympia",
    "sg:classifiers":[
        {
            "category":"Shopping",
            "subcategory":"Pharmacy",
            "type":"Retail Goods"
        }
    ],
    "sg:phone":"+1 360 709 9999",
    "sg:postcode":"98502",
    "sg:province":"WA",
    "wof:name":"Degarmos Compounding Pharmacy",
    "wof:placetype":"venue"
},
  "geometry": {"coordinates":[-122.92583,47.045978],"type":"Point"}
}