{
  "type": "Feature",
  "properties": {
    "addr:full":"2572 Grandview Dr Clarkston WA 99403",
    "addr:housenumber":"2572",
    "addr:postcode":"99403",
    "addr:street":"Grandview Dr",
    "iso:country":"US",
    "sg:address":"2572 Grandview Dr",
    "sg:city":"Clarkston",
    "sg:classifiers":[
        {
            "category":"Professional",
            "subcategory":"Management & Consulting",
            "type":"Services"
        }
    ],
    "sg:phone":"+1 509 751 9566",
    "sg:postcode":"99403",
    "sg:province":"WA",
    "wof:name":"Effective Resources",
    "wof:placetype":"venue"
},
  "geometry": {"coordinates":[-117.066788,46.387151],"type":"Point"}
}