{
  "type": "Feature",
  "properties": {
    "addr:full":"2350 Main St Lynden WA 98264",
    "addr:housenumber":"2350",
    "addr:postcode":"98264",
    "addr:street":"Main St",
    "iso:country":"US",
    "sg:address":"2350 Main St",
    "sg:city":"Lynden",
    "sg:classifiers":[
        {
            "category":"Farming",
            "subcategory":"Farm & Veterinary Services",
            "type":"Manufacturing & Wholesale Goods"
        }
    ],
    "sg:phone":"+1 360 354 5266",
    "sg:postcode":"98264",
    "sg:province":"WA",
    "sg:tags":[
        "breeder",
        "livestock"
    ],
    "wof:name":"Main Stream Holsteins",
    "wof:placetype":"venue"
},
  "geometry": {"coordinates":[-122.485215,48.946027],"type":"Point"}
}