{
  "type": "Feature",
  "properties": {
    "addr:full":"4501 NE Minnehaha St Vancouver WA 98661",
    "addr:housenumber":"4501",
    "addr:postcode":"98661",
    "addr:street":"Ne Minnehaha St",
    "iso:country":"US",
    "sg:address":"4501 NE Minnehaha St",
    "sg:city":"Vancouver",
    "sg:classifiers":[
        {
            "category":"Building & Trades",
            "subcategory":"Construction",
            "type":"Services"
        }
    ],
    "sg:phone":"+1 360 694 2446",
    "sg:postcode":"98661",
    "sg:province":"WA",
    "sg:tags":[
        "home",
        "builder",
        "general",
        "contractor"
    ],
    "wof:name":"Quail Construction Inc",
    "wof:placetype":"venue"
},
  "geometry": {"coordinates":[-122.625941,45.667782],"type":"Point"}
}