{
  "type": "Feature",
  "properties": {
    "addr:full":"418 W 8th Street Vancouver WA 98660",
    "addr:housenumber":"418",
    "addr:postcode":"98660",
    "addr:street":"W 8Th Street",
    "iso:country":"US",
    "sg:address":"418 W 8th Street",
    "sg:city":"Vancouver",
    "sg:classifiers":[
        {
            "category":"Winery",
            "type":"Food & Drink"
        }
    ],
    "sg:phone":"+1 360 993 5006",
    "sg:postcode":"98660",
    "sg:province":"WA",
    "sg:website":"www.vancouvercellar.com",
    "wof:name":"Vancouver Gift & Wine Cellar",
    "wof:placetype":"venue"
},
  "geometry": {"coordinates":[-122.675383,45.62725],"type":"Point"}
}