{
  "type": "Feature",
  "properties": {
    "addr:full":"216 N I St Aberdeen WA 98520",
    "addr:housenumber":"216",
    "addr:postcode":"98520",
    "addr:street":"N I St",
    "iso:country":"US",
    "sg:address":"216 N I St",
    "sg:city":"Aberdeen",
    "sg:classifiers":[
        {
            "category":"Communications",
            "type":"Services"
        }
    ],
    "sg:phone":"+1 360 533 2405",
    "sg:postcode":"98520",
    "sg:province":"WA",
    "wof:name":"TSS Communications",
    "wof:placetype":"venue"
},
  "geometry": {"coordinates":[-123.819222,46.97721],"type":"Point"}
}