{
  "type": "Feature",
  "properties": {
    "iso:country":"US",
    "sg:address":"501 S Main St",
    "sg:city":"Coupeville",
    "sg:classifiers":[
        {
            "category":"Education",
            "subcategory":"School",
            "type":"Public Place"
        }
    ],
    "sg:phone":"+1 360 678 4409",
    "sg:postcode":"98239",
    "sg:province":"WA",
    "wof:name":"Coupeville Junior Senior High",
    "wof:placetype":"venue"
},
  "geometry": {"coordinates":[-122.68611799999999,48.207557],"type":"Point"}
}