{
  "type": "Feature",
  "properties": {
    "addr:full":"1601 E Fourth Plain Blvd A114 Vancouver WA 98661",
    "addr:housenumber":"1601",
    "addr:postcode":"98661",
    "addr:street":"E Fourth Plain Blvd",
    "iso:country":"US",
    "sg:address":"1601 E Fourth Plain Blvd A114",
    "sg:city":"Vancouver",
    "sg:classifiers":[
        {
            "category":"Professional",
            "subcategory":"Detective & Security Services",
            "type":"Services"
        }
    ],
    "sg:phone":"+1 360 397 8050",
    "sg:postcode":"98661",
    "sg:province":"WA",
    "sg:tags":[
        "buyer",
        "information"
    ],
    "sg:website":"http://www.cvab.com",
    "wof:name":"C V A B",
    "wof:placetype":"venue"
},
  "geometry": {"coordinates":[-122.65540300000001,45.639469],"type":"Point"}
}