{
  "type": "Feature",
  "properties": {
    "addr:full":"11 Dun Horse Dr Okanogan WA 98840",
    "addr:housenumber":"11",
    "addr:postcode":"98840",
    "addr:street":"Dun Horse Dr",
    "iso:country":"US",
    "sg:address":"11 Dun Horse Dr",
    "sg:city":"Okanogan",
    "sg:classifiers":[
        {
            "category":"Wholesale",
            "subcategory":"Farm Supplies",
            "type":"Manufacturing & Wholesale Goods"
        }
    ],
    "sg:phone":"+1 509 422 6388",
    "sg:postcode":"98840",
    "sg:province":"WA",
    "sg:tags":[
        "fa",
        "product",
        "material",
        "equine",
        "raw"
    ],
    "wof:name":"Western Quarter Pony Registry",
    "wof:placetype":"venue"
},
  "geometry": {"coordinates":[-119.636211,48.431614],"type":"Point"}
}