{
  "type": "Feature",
  "properties": {
    "addr:full":"123 S Pines Rd Spokane WA 99206",
    "addr:housenumber":"123",
    "addr:postcode":"99206",
    "addr:street":"S Pines Rd",
    "iso:country":"US",
    "sg:address":"123 S Pines Rd",
    "sg:city":"Spokane",
    "sg:classifiers":[
        {
            "category":"Building & Trades",
            "subcategory":"Landscaping Services",
            "type":"Services"
        }
    ],
    "sg:phone":"+1 509 921 2282",
    "sg:postcode":"99206",
    "sg:province":"WA",
    "wof:name":"Pinnacle Lawn & Tree Care",
    "wof:placetype":"venue"
},
  "geometry": {"coordinates":[-117.239727,47.65534],"type":"Point"}
}