{
  "type": "Feature",
  "properties": {
    "addr:full":"905 S 2nd Ave Walla Walla WA 99362",
    "addr:housenumber":"905",
    "addr:postcode":"99362",
    "addr:street":"S 2Nd Ave",
    "iso:country":"US",
    "sg:address":"905 S 2nd Ave",
    "sg:city":"Walla Walla",
    "sg:classifiers":[
        {
            "category":"Food & Beverages",
            "subcategory":"Groceries & Convenience Stores",
            "type":"Retail Goods"
        }
    ],
    "sg:phone":"+1 509 525 7900",
    "sg:postcode":"99362",
    "sg:province":"WA",
    "wof:name":"Loneys Superfoods",
    "wof:placetype":"venue"
},
  "geometry": {"coordinates":[-118.332559,46.055715],"type":"Point"}
}