{
  "type": "Feature",
  "properties": {
    "addr:full":"4610 Stephens Ave Carnation WA 98014",
    "addr:housenumber":"4610",
    "addr:postcode":"98014",
    "addr:street":"Stephens Ave",
    "iso:country":"US",
    "sg:address":"4610 Stephens Ave",
    "sg:city":"Carnation",
    "sg:classifiers":[
        {
            "category":"Organizations",
            "subcategory":"Religious Organization",
            "type":"Services"
        }
    ],
    "sg:phone":"+1 425 333 5922",
    "sg:postcode":"98014",
    "sg:province":"WA",
    "sg:website":"www.lwcccw.org",
    "wof:name":"Living Word Community Church",
    "wof:placetype":"venue"
},
  "geometry": {"coordinates":[-121.914776,47.648701],"type":"Point"}
}