{
  "type": "Feature",
  "properties": {
    "addr:full":"775 NW Gilman Blvd Issaquah WA 98027",
    "addr:housenumber":"775",
    "addr:postcode":"98027",
    "addr:street":"Nw Gilman Blvd",
    "iso:country":"US",
    "sg:address":"775 NW Gilman Blvd",
    "sg:city":"Issaquah",
    "sg:classifiers":[
        {
            "category":"Shopping",
            "subcategory":"Music",
            "type":"Retail Goods"
        }
    ],
    "sg:phone":"+1 425 392 6094",
    "sg:postcode":"98027",
    "sg:province":"WA",
    "wof:name":"Soundsations",
    "wof:placetype":"venue"
},
  "geometry": {"coordinates":[-122.04906,47.543687],"type":"Point"}
}