{
  "type": "Feature",
  "properties": {
    "addr:full":"15655 NE 85th St Redmond WA 98052",
    "addr:housenumber":"15655",
    "addr:postcode":"98052",
    "addr:street":"Ne 85Th St",
    "iso:country":"US",
    "sg:address":"15655 NE 85th St",
    "sg:city":"Redmond",
    "sg:classifiers":[
        {
            "category":"Banks & Credit Unions",
            "subcategory":"Investment Brokerage",
            "type":"Services"
        }
    ],
    "sg:phone":"+1 425 895 9524",
    "sg:postcode":"98052",
    "sg:province":"WA",
    "sg:tags":[
        "consultant",
        "planning",
        "financial"
    ],
    "wof:name":"Emerald Capital Preservation",
    "wof:placetype":"venue"
},
  "geometry": {"coordinates":[-122.13207199999999,47.678582],"type":"Point"}
}