{
  "type": "Feature",
  "properties": {
    "addr:full":"12244 Ravena Pl NW Silverdale WA 98383",
    "addr:postcode":"12244;98383",
    "addr:street":"Ravena Pl Nw",
    "iso:country":"US",
    "sg:address":"12244 Ravena Pl NW",
    "sg:city":"Silverdale",
    "sg:classifiers":[
        {
            "category":"Wholesale",
            "subcategory":"Seafood",
            "type":"Manufacturing & Wholesale Goods"
        }
    ],
    "sg:phone":"+1 360 697 6256",
    "sg:postcode":"98383",
    "sg:province":"WA",
    "wof:name":"B&L Seafood Express",
    "wof:placetype":"venue"
},
  "geometry": {"coordinates":[-122.666635,47.675468],"type":"Point"}
}