{
  "type": "Feature",
  "properties": {
    "addr:full":"24324 SE 400th St Enumclaw WA 98022",
    "addr:postcode":"24324;98022",
    "addr:street":"Se 400Th St",
    "iso:country":"US",
    "sg:address":"24324 SE 400th St",
    "sg:city":"Enumclaw",
    "sg:classifiers":[
        {
            "category":"Building & Trades",
            "subcategory":"Construction",
            "type":"Services"
        }
    ],
    "sg:phone":"+1 360 802 6678",
    "sg:postcode":"98022",
    "sg:province":"WA",
    "sg:tags":[
        "contractor"
    ],
    "wof:name":"Cummings Contractors Inc",
    "wof:placetype":"venue"
},
  "geometry": {"coordinates":[-122.02028199999999,47.2429],"type":"Point"}
}