{
  "type": "Feature",
  "properties": {
    "iso:country":"US",
    "sg:address":"7709 Filly Ct SE",
    "sg:city":"Olympia",
    "sg:classifiers":[
        {
            "category":"Professional",
            "type":"Services"
        }
    ],
    "sg:phone":"+1 360 352 0663",
    "sg:postcode":"98501",
    "sg:province":"WA",
    "wof:name":"Phoenix Rising 2000 Corp",
    "wof:placetype":"venue"
},
  "geometry": {"coordinates":[-122.87985399999999,46.975972],"type":"Point"}
}