{
  "type": "Feature",
  "properties": {
    "addr:full":"1618 Sylvester St SW Olympia WA 98501",
    "addr:housenumber":"1618",
    "addr:postcode":"98501",
    "addr:street":"Sylvester St Sw",
    "iso:country":"US",
    "sg:address":"1618 Sylvester St SW",
    "sg:city":"Olympia",
    "sg:classifiers":[
        {
            "category":"Wholesale",
            "subcategory":"Drugs",
            "type":"Manufacturing & Wholesale Goods"
        }
    ],
    "sg:phone":"+1 360 786 0580",
    "sg:postcode":"98501",
    "sg:province":"WA",
    "sg:tags":[
        "pharmaceutical",
        "product"
    ],
    "wof:name":"Pharmaceutical Research",
    "wof:placetype":"venue"
},
  "geometry": {"coordinates":[-122.904166,47.033198],"type":"Point"}
}