{
  "type": "Feature",
  "properties": {
    "addr:full":"4009 204th Ave NE Sammamish WA 98074",
    "addr:housenumber":"4009",
    "addr:postcode":"98074",
    "addr:street":"204Th Ave Ne",
    "iso:country":"US",
    "sg:address":"4009 204th Ave NE",
    "sg:city":"Sammamish",
    "sg:classifiers":[
        {
            "category":"Professional",
            "subcategory":"Employment Agencies",
            "type":"Services"
        }
    ],
    "sg:phone":"+1 425 898 1023",
    "sg:postcode":"98074",
    "sg:province":"WA",
    "sg:tags":[
        "travel",
        "help",
        "supply"
    ],
    "wof:name":"Crescendo Concierge",
    "wof:placetype":"venue"
},
  "geometry": {"coordinates":[-122.06742,47.645517],"type":"Point"}
}