{
  "type": "Feature",
  "properties": {
    "addr:full":"1201 Cowlitz Way Kelso WA 98626",
    "addr:housenumber":"1201",
    "addr:postcode":"98626",
    "addr:street":"Cowlitz Way",
    "iso:country":"US",
    "sg:address":"1201 Cowlitz Way",
    "sg:city":"Kelso",
    "sg:classifiers":[
        {
            "category":"Building & Trades",
            "subcategory":"Construction",
            "type":"Services"
        }
    ],
    "sg:phone":"+1 360 425 3660",
    "sg:postcode":"98626",
    "sg:province":"WA",
    "sg:tags":[
        "general",
        "contractor"
    ],
    "wof:name":"Brock Construction",
    "wof:placetype":"venue"
},
  "geometry": {"coordinates":[-122.900091,46.145777],"type":"Point"}
}