{
  "type": "Feature",
  "properties": {
    "addr:full":"24209 NE 92nd Ave Battle Ground WA 98604",
    "addr:housenumber":"24209",
    "addr:postcode":"98604",
    "addr:street":"Ne 92Nd Ave",
    "iso:country":"US",
    "sg:address":"24209 NE 92nd Ave",
    "sg:city":"Battle Ground",
    "sg:classifiers":[
        {
            "category":"Shopping",
            "type":"Retail Goods"
        }
    ],
    "sg:phone":"+1 360 666 6882",
    "sg:postcode":"98604",
    "sg:province":"WA",
    "sg:tags":[
        "binoculars",
        "telescope"
    ],
    "wof:name":"Sean's Astronomy Shop",
    "wof:placetype":"venue"
},
  "geometry": {"coordinates":[-122.578841,45.796284],"type":"Point"}
}