{
  "type": "Feature",
  "properties": {
    "addr:full":"110 Bus Park Loop Sequim WA 98382",
    "addr:housenumber":"110",
    "addr:postcode":"98382",
    "addr:street":"Bus Park Loop",
    "iso:country":"US",
    "sg:address":"110 Bus Park Loop",
    "sg:city":"Sequim",
    "sg:classifiers":[
        {
            "category":"Wholesale",
            "subcategory":"Machinery & Supplies",
            "type":"Manufacturing & Wholesale Goods"
        }
    ],
    "sg:phone":"+1 360 683 4231",
    "sg:postcode":"98382",
    "sg:province":"WA",
    "sg:tags":[
        "pump"
    ],
    "wof:name":"Sequim Valley Pump Inc",
    "wof:placetype":"venue"
},
  "geometry": {"coordinates":[-123.16931200000001,48.090637],"type":"Point"}
}