{
  "type": "Feature",
  "properties": {
    "iso:country":"US",
    "sg:address":"4410 144th Ave SE",
    "sg:city":"Bellevue",
    "sg:classifiers":[
        {
            "category":"Banks & Credit Unions",
            "subcategory":"Financial Services",
            "type":"Services"
        }
    ],
    "sg:phone":"+1 425 649 5091",
    "sg:postcode":"98006",
    "sg:province":"WA",
    "sg:tags":[
        "company",
        "holding"
    ],
    "wof:name":"Metropolitan MGT Group LLC",
    "wof:placetype":"venue"
},
  "geometry": {"coordinates":[-122.14852999999999,47.565855],"type":"Point"}
}