{
  "type": "Feature",
  "properties": {
    "addr:full":"1015 N Road 28 Pasco WA 99301",
    "addr:housenumber":"1015",
    "addr:postcode":"99301",
    "addr:street":"N Road 28",
    "iso:country":"US",
    "sg:address":"1015 N Road 28",
    "sg:city":"Pasco",
    "sg:classifiers":[
        {
            "category":"Place Of Worship",
            "subcategory":"Church",
            "type":"Public Place"
        },
        {
            "category":"Place Of Worship",
            "type":"Public Place"
        }
    ],
    "sg:phone":"+1 509 547 3466",
    "sg:postcode":"99301",
    "sg:province":"WA",
    "sg:tags":[
        "lutheran",
        "america",
        "churches-lutheran",
        "churches-lutheran-evangelical"
    ],
    "wof:name":"Trinity Lutheran Church Missouri Synod",
    "wof:placetype":"venue"
},
  "geometry": {"coordinates":[-119.12794700000001,46.237078],"type":"Point"}
}