{
  "type": "Feature",
  "properties": {
    "addr:full":"1319 2nd St Wenatchee WA 98801",
    "addr:housenumber":"1319",
    "addr:postcode":"98801",
    "addr:street":"2Nd St",
    "iso:country":"US",
    "sg:address":"1319 2nd St",
    "sg:city":"Wenatchee",
    "sg:classifiers":[
        {
            "category":"Professional",
            "subcategory":"Secretarial Services",
            "type":"Services"
        }
    ],
    "sg:phone":"+1 509 665 6938",
    "sg:postcode":"98801",
    "sg:province":"WA",
    "sg:tags":[
        "reporting"
    ],
    "wof:name":"C & S Secretarial",
    "wof:placetype":"venue"
},
  "geometry": {"coordinates":[-120.334805,47.427018],"type":"Point"}
}