{
  "type": "Feature",
  "properties": {
    "addr:full":"5707 W Lincoln Ave Yakima WA 98908",
    "addr:housenumber":"5707",
    "addr:postcode":"98908",
    "addr:street":"W Lincoln Ave",
    "iso:country":"US",
    "sg:address":"5707 W Lincoln Ave",
    "sg:city":"Yakima",
    "sg:classifiers":[
        {
            "category":"Professional",
            "subcategory":"Advertising",
            "type":"Services"
        }
    ],
    "sg:phone":"+1 509 453 5013",
    "sg:postcode":"98908",
    "sg:province":"WA",
    "sg:tags":[
        "outdoor"
    ],
    "wof:name":"Viacom Outdoor",
    "wof:placetype":"venue"
},
  "geometry": {"coordinates":[-120.585795,46.60376],"type":"Point"}
}