{
  "type": "Feature",
  "properties": {
    "iso:country":"US",
    "sg:address":"6830 88th Pl NE",
    "sg:city":"Marysville",
    "sg:classifiers":[
        {
            "category":"Retail",
            "subcategory":"Auto Repair",
            "type":"Services"
        }
    ],
    "sg:phone":"+1 360 657 1773",
    "sg:postcode":"98270",
    "sg:province":"WA",
    "sg:tags":[
        "automotive"
    ],
    "wof:name":"First Response Road",
    "wof:placetype":"venue"
},
  "geometry": {"coordinates":[-122.135649,48.074733],"type":"Point"}
}