{
  "type": "Feature",
  "properties": {
    "iso:country":"US",
    "sg:address":"11314 4th Ave W",
    "sg:city":"Everett",
    "sg:classifiers":[
        {
            "category":"Social Services",
            "subcategory":"Adult Care",
            "type":"Services"
        }
    ],
    "sg:phone":"+1 425 423 0304",
    "sg:postcode":"98204",
    "sg:province":"WA",
    "sg:tags":[
        "property",
        "management"
    ],
    "wof:name":"Legacy Management Group Inc",
    "wof:placetype":"venue"
},
  "geometry": {"coordinates":[-122.238986,47.895688],"type":"Point"}
}