{
  "type": "Feature",
  "properties": {
    "addr:full":"6119 S 296th St Auburn WA 98001",
    "addr:housenumber":"6119",
    "addr:postcode":"98001",
    "addr:street":"S 296Th St",
    "iso:country":"US",
    "sg:address":"6119 S 296th St",
    "sg:city":"Auburn",
    "sg:classifiers":[
        {
            "category":"Building & Trades",
            "subcategory":"Construction",
            "type":"Services"
        }
    ],
    "sg:phone":"+1 253 945 6689",
    "sg:postcode":"98001",
    "sg:province":"WA",
    "sg:tags":[
        "contractor"
    ],
    "wof:name":"Aquatic Designs",
    "wof:placetype":"venue"
},
  "geometry": {"coordinates":[-122.259041,47.336705],"type":"Point"}
}