{
  "type": "Feature",
  "properties": {
    "addr:full":"7526 Olympic View Dr Edmonds WA 98026",
    "addr:housenumber":"7526",
    "addr:postcode":"98026",
    "addr:street":"Olympic View Dr",
    "iso:country":"US",
    "sg:address":"7526 Olympic View Dr",
    "sg:city":"Edmonds",
    "sg:classifiers":[
        {
            "category":"Retail",
            "subcategory":"Veterinary Services",
            "type":"Services"
        }
    ],
    "sg:phone":"+1 425 775 4992",
    "sg:postcode":"98026",
    "sg:province":"WA",
    "sg:tags":[
        "hospital",
        "animal"
    ],
    "wof:name":"Perrinville Animal Hospital",
    "wof:placetype":"venue"
},
  "geometry": {"coordinates":[-122.335286,47.831066],"type":"Point"}
}