{
  "type": "Feature",
  "properties": {
    "addr:full":"2916 S Regal St Spokane WA 99223",
    "addr:housenumber":"2916",
    "addr:postcode":"99223",
    "addr:street":"S Regal St",
    "iso:country":"US",
    "sg:address":"2916 S Regal St",
    "sg:city":"Spokane",
    "sg:classifiers":[
        {
            "category":"Deli",
            "type":"Food & Drink"
        },
        {
            "category":"Restaurant",
            "type":"Food & Drink"
        }
    ],
    "sg:phone":"+1 509 535 3088",
    "sg:postcode":"99223",
    "sg:province":"WA",
    "sg:tags":[
        "delicatessen"
    ],
    "wof:name":"Mariupol European Deli",
    "wof:placetype":"venue"
},
  "geometry": {"coordinates":[-117.36859699999999,47.628029],"type":"Point"}
}