{
  "type": "Feature",
  "properties": {
    "addr:full":"400 W 1st St Warden WA 98857",
    "addr:housenumber":"400",
    "addr:postcode":"98857",
    "addr:street":"W 1St St",
    "iso:country":"US",
    "sg:address":"400 W 1st St",
    "sg:city":"Warden",
    "sg:classifiers":[
        {
            "category":"Autos & Motor Vehicles",
            "subcategory":"Auto Supplies",
            "type":"Retail Goods"
        },
        {
            "category":"Wholesale",
            "subcategory":"Electrical",
            "type":"Manufacturing & Wholesale Goods"
        }
    ],
    "sg:phone":"+1 509 349 2331",
    "sg:postcode":"98857",
    "sg:province":"WA",
    "sg:tags":[
        "battery",
        "automobile",
        "part",
        "accessory"
    ],
    "sg:website":"http://www.napaonline.com",
    "wof:name":"Napa Auto Parts",
    "wof:placetype":"venue"
},
  "geometry": {"coordinates":[-119.036118,46.969669],"type":"Point"}
}