{
  "type": "Feature",
  "properties": {
    "addr:full":"16111 Woodinville Redmond Rd NE Woodinville WA 98072",
    "addr:housenumber":"16111",
    "addr:postcode":"98072",
    "addr:street":"Woodinville Redmond Rd Ne",
    "iso:country":"US",
    "sg:address":"16111 Woodinville Redmond Rd NE",
    "sg:city":"Woodinville",
    "sg:classifiers":[
        {
            "category":"Wholesale",
            "subcategory":"Home Furnishings",
            "type":"Manufacturing & Wholesale Goods"
        }
    ],
    "sg:phone":"+1 425 485 7096",
    "sg:postcode":"98072",
    "sg:province":"WA",
    "sg:tags":[
        "warehouse",
        "location"
    ],
    "wof:name":"Warehouse",
    "wof:placetype":"venue"
},
  "geometry": {"coordinates":[-122.160946,47.744858],"type":"Point"}
}