{
  "type": "Feature",
  "properties": {
    "addr:full":"1732 5th St Wenatchee WA 98801",
    "addr:housenumber":"1732",
    "addr:postcode":"98801",
    "addr:street":"5Th St",
    "iso:country":"US",
    "sg:address":"1732 5th St",
    "sg:city":"Wenatchee",
    "sg:classifiers":[
        {
            "category":"Food & Beverages",
            "subcategory":"Groceries & Convenience Stores",
            "type":"Retail Goods"
        }
    ],
    "sg:phone":"+1 509 662 6362",
    "sg:postcode":"98801",
    "sg:province":"WA",
    "wof:name":"Western Market",
    "wof:placetype":"venue"
},
  "geometry": {"coordinates":[-120.345698,47.429886],"type":"Point"}
}