{
  "type": "Feature",
  "properties": {
    "addr:full":"Pike Place Market 1530 Post Alley Seattle WA 98101",
    "addr:housenumber":"1530",
    "addr:postcode":"98101",
    "addr:street":"Pike;Post Alley",
    "iso:country":"US",
    "sg:address":"Pike Place Market 1530 Post Alley",
    "sg:city":"Seattle",
    "sg:classifiers":[
        {
            "category":"Food & Beverages",
            "subcategory":"Bakery",
            "type":"Retail Goods"
        }
    ],
    "sg:phone":"+1 206 623 6723",
    "sg:postcode":"98101",
    "sg:province":"WA",
    "sg:tags":[
        "sandwich"
    ],
    "sg:website":"www.sisterssnacks.com",
    "wof:name":"Sisters European Snacks",
    "wof:placetype":"venue"
},
  "geometry": {"coordinates":[-122.341176,47.609234],"type":"Point"}
}