{
  "type": "Feature",
  "properties": {
    "addr:full":"1833 181st Pl SW Lynnwood WA 98037",
    "addr:housenumber":"1833",
    "addr:postcode":"98037",
    "addr:street":"181St Pl Sw",
    "iso:country":"US",
    "sg:address":"1833 181st Pl SW",
    "sg:city":"Lynnwood",
    "sg:classifiers":[
        {
            "category":"Wholesale",
            "subcategory":"Hardware",
            "type":"Manufacturing & Wholesale Goods"
        }
    ],
    "sg:phone":"+1 425 776 9631",
    "sg:postcode":"98037",
    "sg:province":"WA",
    "sg:tags":[
        "closer",
        "door",
        "check"
    ],
    "wof:name":"Norweco Co",
    "wof:placetype":"venue"
},
  "geometry": {"coordinates":[-122.256922,47.833462],"type":"Point"}
}