{
  "type": "Feature",
  "properties": {
    "addr:full":"20 N Auburn St Kennewick WA 99336",
    "addr:housenumber":"20",
    "addr:postcode":"99336",
    "addr:street":"N Auburn St",
    "iso:country":"US",
    "sg:address":"20 N Auburn St",
    "sg:city":"Kennewick",
    "sg:classifiers":[
        {
            "category":"Professional",
            "type":"Services"
        },
        {
            "category":"Restaurant",
            "type":"Food & Drink"
        },
        {
            "category":"Retail",
            "subcategory":"Event Space",
            "type":"Services"
        }
    ],
    "sg:phone":"+1 509 582 6598",
    "sg:postcode":"99336",
    "sg:province":"WA",
    "sg:tags":[
        "style",
        "family",
        "facility",
        "banquet",
        "reception",
        "caterer",
        "hall"
    ],
    "sg:website":"http://www.daleshepard.com",
    "wof:name":"Leo's Catering",
    "wof:placetype":"venue"
},
  "geometry": {"coordinates":[-119.118408,46.208887],"type":"Point"}
}