{
  "type": "Feature",
  "properties": {
    "addr:full":"19660 10th Ave NE Poulsbo WA 98370",
    "addr:housenumber":"19660",
    "addr:postcode":"98370",
    "addr:street":"10Th Ave Ne",
    "iso:country":"US",
    "sg:address":"19660 10th Ave NE",
    "sg:city":"Poulsbo",
    "sg:classifiers":[
        {
            "category":"Health Services",
            "subcategory":"Chiropractor",
            "type":"Services"
        }
    ],
    "sg:phone":"+1 360 779 7923",
    "sg:postcode":"98370",
    "sg:province":"WA",
    "wof:name":"Trish Pettapiece",
    "wof:placetype":"venue"
},
  "geometry": {"coordinates":[-122.63739700000001,47.740367],"type":"Point"}
}