{
  "type": "Feature",
  "properties": {
    "iso:country":"US",
    "sg:address":"9620 State Ave",
    "sg:city":"Marysville",
    "sg:classifiers":[
        {
            "category":"Social Services",
            "type":"Services"
        }
    ],
    "sg:phone":"+1 425 329 0357",
    "sg:postcode":"98270",
    "sg:province":"WA",
    "wof:name":"Humanitarn Org For Minors To E",
    "wof:placetype":"venue"
},
  "geometry": {"coordinates":[-122.17413999999999,48.08148],"type":"Point"}
}