{
  "type": "Feature",
  "properties": {
    "addr:full":"12901 SE 69th Pl Bellevue WA 98006",
    "addr:housenumber":"12901",
    "addr:postcode":"98006",
    "addr:street":"Se 69Th Pl",
    "iso:country":"US",
    "sg:address":"12901 SE 69th Pl",
    "sg:city":"Bellevue",
    "sg:classifiers":[
        {
            "category":"Food & Beverages",
            "subcategory":"Bakery",
            "type":"Retail Goods"
        }
    ],
    "sg:phone":"+1 425 641 7278",
    "sg:postcode":"98006",
    "sg:province":"WA",
    "wof:name":"Camelot Ctrg By McHael Knowles",
    "wof:placetype":"venue"
},
  "geometry": {"coordinates":[-122.166312,47.540504],"type":"Point"}
}