{
  "type": "Feature",
  "properties": {
    "addr:full":"4444 California Ave SW Seattle WA 98116",
    "addr:housenumber":"4444",
    "addr:postcode":"98116",
    "addr:street":"California Ave Sw",
    "iso:country":"US",
    "sg:address":"4444 California Ave SW",
    "sg:city":"Seattle",
    "sg:classifiers":[
        {
            "category":"Food & Beverages",
            "subcategory":"Candy",
            "type":"Retail Goods"
        }
    ],
    "sg:phone":"+1 206 938 0680",
    "sg:postcode":"98116",
    "sg:province":"WA",
    "sg:tags":[
        "dessert"
    ],
    "sg:website":"www.shooflypiecompany.com",
    "wof:name":"Shoofly Pie Co.",
    "wof:placetype":"venue"
},
  "geometry": {"coordinates":[-122.386765,47.563908],"type":"Point"}
}