{
  "type": "Feature",
  "properties": {
    "iso:country":"US",
    "sg:address":"159 Hamilton Rd",
    "sg:city":"Chehalis",
    "sg:classifiers":[
        {
            "category":"Wholesale",
            "subcategory":"Machinery & Supplies",
            "type":"Manufacturing & Wholesale Goods"
        }
    ],
    "sg:phone":"+1 360 748 4421",
    "sg:postcode":"98532",
    "sg:province":"WA",
    "sg:tags":[
        "equipment"
    ],
    "wof:name":"Modern Machinery Co Inc",
    "wof:placetype":"venue"
},
  "geometry": {"coordinates":[-122.91789799999999,46.612386],"type":"Point"}
}