{
  "type": "Feature",
  "properties": {
    "addr:full":"9800 Silverdale Way NW Silverdale WA 98383",
    "addr:housenumber":"9800",
    "addr:postcode":"98383",
    "addr:street":"Silverdale Way Nw",
    "iso:country":"US",
    "sg:address":"9800 Silverdale Way NW",
    "sg:city":"Silverdale",
    "sg:classifiers":[
        {
            "category":"Professional",
            "type":"Services"
        }
    ],
    "sg:phone":"+1 360 692 6522",
    "sg:postcode":"98383",
    "sg:province":"WA",
    "sg:tags":[
        "establishment"
    ],
    "wof:name":"Kitsap Cnty Cnsldt",
    "wof:placetype":"venue"
},
  "geometry": {"coordinates":[-122.690596,47.653367],"type":"Point"}
}