{
  "type": "Feature",
  "properties": {
    "addr:full":"24620 Military Rd S Kent WA 98032",
    "addr:housenumber":"24620",
    "addr:postcode":"98032",
    "addr:street":"Military Rd S",
    "iso:country":"US",
    "sg:address":"24620 Military Rd S",
    "sg:city":"Kent",
    "sg:classifiers":[
        {
            "category":"Education",
            "subcategory":"Dance Studio",
            "type":"Public Place"
        }
    ],
    "sg:phone":"+1 253 839 6771",
    "sg:postcode":"98032",
    "sg:province":"WA",
    "wof:name":"Dixies Dance Studio",
    "wof:placetype":"venue"
},
  "geometry": {"coordinates":[-122.286222,47.381443],"type":"Point"}
}