{
  "type": "Feature",
  "properties": {
    "addr:full":"6516 46th Ave S Seattle WA 98118",
    "addr:housenumber":"6516",
    "addr:postcode":"98118",
    "addr:street":"46Th Ave S",
    "iso:country":"US",
    "sg:address":"6516 46th Ave S",
    "sg:city":"Seattle",
    "sg:classifiers":[
        {
            "category":"Health Services",
            "subcategory":"Clinic",
            "type":"Services"
        }
    ],
    "sg:phone":"+1 206 725 5555",
    "sg:postcode":"98118",
    "sg:province":"WA",
    "sg:tags":[
        "welfare"
    ],
    "wof:name":"First Step Child Care Learning Center",
    "wof:placetype":"venue"
},
  "geometry": {"coordinates":[-122.275389,47.544107],"type":"Point"}
}