{
  "type": "Feature",
  "properties": {
    "addr:full":"1905 E Pacific Ave Spokane WA 99202",
    "addr:housenumber":"1905",
    "addr:postcode":"99202",
    "addr:street":"E Pacific Ave",
    "iso:country":"US",
    "sg:address":"1905 E Pacific Ave",
    "sg:city":"Spokane",
    "sg:classifiers":[
        {
            "category":"Recreation",
            "type":"Entertainment"
        }
    ],
    "sg:phone":"+1 509 535 2623",
    "sg:postcode":"99202",
    "sg:province":"WA",
    "sg:tags":[
        "amusement"
    ],
    "wof:name":"Project Spear",
    "wof:placetype":"venue"
},
  "geometry": {"coordinates":[-117.38124500000001,47.655301],"type":"Point"}
}