{
  "type": "Feature",
  "properties": {
    "addr:full":"2035 Howell Ave Richland WA 99354",
    "addr:housenumber":"2035",
    "addr:postcode":"99354",
    "addr:street":"Howell Ave",
    "iso:country":"US",
    "sg:address":"2035 Howell Ave",
    "sg:city":"Richland",
    "sg:classifiers":[
        {
            "category":"Professional",
            "subcategory":"Computer Services",
            "type":"Services"
        }
    ],
    "sg:phone":"+1 509 946 1978",
    "sg:postcode":"99354",
    "sg:province":"WA",
    "sg:tags":[
        "design",
        "system"
    ],
    "wof:name":"Blackbirds Nest",
    "wof:placetype":"venue"
},
  "geometry": {"coordinates":[-119.271201,46.303881],"type":"Point"}
}