{
  "type": "Feature",
  "properties": {
    "addr:full":"10705 Main St Bellevue WA 98004",
    "addr:housenumber":"10705",
    "addr:postcode":"98004",
    "addr:street":"Main St",
    "iso:country":"US",
    "sg:address":"10705 Main St",
    "sg:city":"Bellevue",
    "sg:classifiers":[
        {
            "category":"Restaurant",
            "type":"Food & Drink"
        },
        {
            "category":"Food & Beverages",
            "subcategory":"Ethnic Foods",
            "type":"Retail Goods"
        }
    ],
    "sg:phone":"+1 425 454 7720",
    "sg:postcode":"98004",
    "sg:province":"WA",
    "sg:tags":[
        "vietnamese"
    ],
    "wof:name":"Simply Saigon Restaurant",
    "wof:placetype":"venue"
},
  "geometry": {"coordinates":[-122.197804,47.61013],"type":"Point"}
}