{
  "type": "Feature",
  "properties": {
    "addr:full":"8404 19th St W Tacoma WA 98466",
    "addr:housenumber":"8404",
    "addr:postcode":"98466",
    "addr:street":"19Th St W",
    "iso:country":"US",
    "sg:address":"8404 19th St W",
    "sg:city":"Tacoma",
    "sg:classifiers":[
        {
            "category":"Manufacturing",
            "subcategory":"Metals",
            "type":"Manufacturing & Wholesale Goods"
        }
    ],
    "sg:phone":"+1 253 380 9421",
    "sg:postcode":"98466",
    "sg:province":"WA",
    "sg:tags":[
        "ornamental",
        "work"
    ],
    "wof:name":"Sound Iron Works",
    "wof:placetype":"venue"
},
  "geometry": {"coordinates":[-122.54990599999999,47.242607],"type":"Point"}
}