{
  "type": "Feature",
  "properties": {
    "addr:full":"2120 91st Ave W Tacoma WA 98466",
    "addr:housenumber":"2120",
    "addr:postcode":"98466",
    "addr:street":"91St Ave W",
    "iso:country":"US",
    "sg:address":"2120 91st Ave W",
    "sg:city":"Tacoma",
    "sg:classifiers":[
        {
            "category":"Professional",
            "subcategory":"Business Services",
            "type":"Services"
        }
    ],
    "sg:phone":"+1 253 565 7275",
    "sg:postcode":"98466",
    "sg:province":"WA",
    "sg:tags":[
        "consultant",
        "coach"
    ],
    "wof:name":"Pat Lamagie",
    "wof:placetype":"venue"
},
  "geometry": {"coordinates":[-122.557982,47.242508],"type":"Point"}
}