{
  "type": "Feature",
  "properties": {
    "addr:full":"382 Wyatt Way NE Bainbridge Isle WA 98110",
    "addr:housenumber":"382",
    "addr:postcode":"98110",
    "addr:street":"Wyatt Way Ne;Isle",
    "iso:country":"US",
    "sg:address":"382 Wyatt Way NE",
    "sg:city":"Bainbridge Isle",
    "sg:classifiers":[
        {
            "category":"Professional",
            "subcategory":"Engineering",
            "type":"Services"
        }
    ],
    "sg:phone":"+1 206 842 4651",
    "sg:postcode":"98110",
    "sg:province":"WA",
    "sg:tags":[
        "architect",
        "naval",
        "architectural"
    ],
    "sg:website":"www.jacksarin.com",
    "wof:name":"Jack W Sarin Naval Architects",
    "wof:placetype":"venue"
},
  "geometry": {"coordinates":[-122.517848,47.628612],"type":"Point"}
}