{
  "type": "Feature",
  "properties": {
    "addr:full":"1101 Madison St Ste 950 Seattle WA 98104",
    "addr:housenumber":"1101",
    "addr:postcode":"98104",
    "addr:street":"Madison St Ste 950",
    "iso:country":"US",
    "sg:address":"1101 Madison St Ste 950",
    "sg:city":"Seattle",
    "sg:classifiers":[
        {
            "category":"Health Services",
            "subcategory":"Doctor",
            "type":"Services"
        }
    ],
    "sg:phone":"+1 206 682 5800",
    "sg:postcode":"98104",
    "sg:province":"WA",
    "sg:tags":[
        "obstetrician",
        "gynecologist"
    ],
    "wof:name":"Daniel Anna G MD",
    "wof:placetype":"venue"
},
  "geometry": {"coordinates":[-122.324997,47.609402],"type":"Point"}
}