{
  "type": "Feature",
  "properties": {
    "addr:full":"162 S Coeur Dalene St Spokane WA 99201",
    "addr:housenumber":"162",
    "addr:postcode":"99201",
    "addr:street":"S Coeur Dalene St",
    "iso:country":"US",
    "sg:address":"162 S Coeur Dalene St",
    "sg:city":"Spokane",
    "sg:classifiers":[
        {
            "category":"Health Services",
            "subcategory":"Clinic",
            "type":"Services"
        }
    ],
    "sg:phone":"+1 509 624 1212",
    "sg:postcode":"99201",
    "sg:province":"WA",
    "sg:tags":[
        "home",
        "care"
    ],
    "wof:name":"Rhondas Compassionate Care",
    "wof:placetype":"venue"
},
  "geometry": {"coordinates":[-117.449344,47.654808],"type":"Point"}
}