{
  "type": "Feature",
  "properties": {
    "addr:full":"10210 NE Points Dr Kirkland WA 98033",
    "addr:housenumber":"10210",
    "addr:postcode":"98033",
    "addr:street":"Ne Points Dr",
    "iso:country":"US",
    "sg:address":"10210 NE Points Dr",
    "sg:city":"Kirkland",
    "sg:classifiers":[
        {
            "category":"Shopping",
            "subcategory":"Computers & Home Electronics",
            "type":"Retail Goods"
        }
    ],
    "sg:phone":"+1 425 828 4020",
    "sg:postcode":"98033",
    "sg:province":"WA",
    "wof:name":"Sun Microsystems",
    "wof:placetype":"venue"
},
  "geometry": {"coordinates":[-122.201959,47.643977],"type":"Point"}
}