{
  "type": "Feature",
  "properties": {
    "addr:full":"3405 S 229th Pl Seatac WA 98198",
    "addr:housenumber":"3405",
    "addr:postcode":"98198",
    "addr:street":"S 229Th Pl",
    "iso:country":"US",
    "sg:address":"3405 S 229th Pl",
    "sg:city":"Seatac",
    "sg:classifiers":[
        {
            "category":"Freight",
            "type":"Transportation"
        }
    ],
    "sg:phone":"+1 206 762 7373",
    "sg:postcode":"98198",
    "sg:province":"WA",
    "sg:tags":[
        "broker",
        "trucking"
    ],
    "wof:name":"Autofinders USA",
    "wof:placetype":"venue"
},
  "geometry": {"coordinates":[-122.288962,47.395824],"type":"Point"}
}