{
  "type": "Feature",
  "properties": {
    "addr:full":"1220 Maple St Wenatchee WA 98801",
    "addr:housenumber":"1220",
    "addr:postcode":"98801",
    "addr:street":"Maple St",
    "iso:country":"US",
    "sg:address":"1220 Maple St",
    "sg:city":"Wenatchee",
    "sg:classifiers":[
        {
            "category":"Bus Charters",
            "type":"Transportation"
        },
        {
            "category":"Landmark",
            "subcategory":"Tourist Information",
            "type":"Public Place"
        }
    ],
    "sg:phone":"+1 509 665 0252",
    "sg:postcode":"98801",
    "sg:province":"WA",
    "sg:tags":[
        "attraction",
        "rental",
        "tours-operators",
        "promoter",
        "buses-charter"
    ],
    "wof:name":"A & A Motorcoach Inc",
    "wof:placetype":"venue"
},
  "geometry": {"coordinates":[-120.33029999999999,47.442375],"type":"Point"}
}