{
  "type": "Feature",
  "properties": {
    "addr:full":"4410 SW Brandon St Seattle WA 98136",
    "addr:housenumber":"4410",
    "addr:postcode":"98136",
    "addr:street":"Sw;St",
    "iso:country":"US",
    "sg:address":"4410 SW Brandon St",
    "sg:city":"Seattle",
    "sg:classifiers":[
        {
            "category":"Wholesale",
            "subcategory":"Toys & Hobbies",
            "type":"Manufacturing & Wholesale Goods"
        }
    ],
    "sg:phone":"+1 206 935 3242",
    "sg:postcode":"98136",
    "sg:province":"WA",
    "wof:name":"Actiontoys4u",
    "wof:placetype":"venue"
},
  "geometry": {"coordinates":[-122.38968,47.554002],"type":"Point"}
}