{
  "type": "Feature",
  "properties": {
    "addr:full":"619 Cedar Ave Marysville WA 98270",
    "addr:housenumber":"619",
    "addr:postcode":"98270",
    "addr:street":"Cedar Ave",
    "iso:country":"US",
    "sg:address":"619 Cedar Ave",
    "sg:city":"Marysville",
    "sg:classifiers":[
        {
            "category":"Health Services",
            "subcategory":"Medical Lab",
            "type":"Services"
        }
    ],
    "sg:phone":"+1 360 659 6300",
    "sg:postcode":"98270",
    "sg:province":"WA",
    "sg:tags":[
        "laboratory",
        "dental"
    ],
    "sg:website":"www.denture.net",
    "wof:name":"Pioneer Denture Clinic",
    "wof:placetype":"venue"
},
  "geometry": {"coordinates":[-122.180576,48.054427],"type":"Point"}
}