{
  "type": "Feature",
  "properties": {
    "addr:full":"9602 Nibbelink Rd Leavenworth WA 98847",
    "addr:housenumber":"9602",
    "addr:postcode":"98847",
    "addr:street":"Nibbelink Rd",
    "iso:country":"US",
    "sg:address":"9602 Nibbelink Rd",
    "sg:city":"Leavenworth",
    "sg:classifiers":[
        {
            "category":"Farming",
            "subcategory":"Orchard",
            "type":"Manufacturing & Wholesale Goods"
        },
        {
            "category":"Farming",
            "subcategory":"Farm & Veterinary Services",
            "type":"Manufacturing & Wholesale Goods"
        }
    ],
    "sg:phone":"+1 509 548 7486",
    "sg:postcode":"98847",
    "sg:province":"WA",
    "sg:tags":[
        "grove",
        "management"
    ],
    "wof:name":"Cowan Orchards Inc",
    "wof:placetype":"venue"
},
  "geometry": {"coordinates":[-120.614392,47.594405],"type":"Point"}
}