{
  "type": "Feature",
  "properties": {
    "addr:full":"416 163rd Pl SE Bellevue WA 98008",
    "addr:housenumber":"416",
    "addr:postcode":"98008",
    "addr:street":"163Rd Pl Se",
    "iso:country":"US",
    "sg:address":"416 163rd Pl SE",
    "sg:city":"Bellevue",
    "sg:classifiers":[
        {
            "category":"Professional",
            "subcategory":"Computer Services",
            "type":"Services"
        }
    ],
    "sg:phone":"+1 425 643 4534",
    "sg:postcode":"98008",
    "sg:province":"WA",
    "sg:tags":[
        "related"
    ],
    "wof:name":"Gardner Northwest",
    "wof:placetype":"venue"
},
  "geometry": {"coordinates":[-122.12244099999999,47.60607],"type":"Point"}
}