{
  "type": "Feature",
  "properties": {
    "addr:full":"19182 Saint Andrews Dr NW Soap Lake WA 98851",
    "addr:housenumber":"19182",
    "addr:postcode":"soap;98851",
    "addr:street":"Saint Andrews Dr Nw;Lake",
    "iso:country":"US",
    "sg:address":"19182 Saint Andrews Dr NW",
    "sg:city":"Soap Lake",
    "sg:classifiers":[
        {
            "category":"Retail",
            "subcategory":"Portrait Studio",
            "type":"Services"
        }
    ],
    "sg:phone":"+1 509 246 1515",
    "sg:postcode":"98851",
    "sg:province":"WA",
    "sg:tags":[
        "photographer"
    ],
    "wof:name":"Studio 7 Photography",
    "wof:placetype":"venue"
},
  "geometry": {"coordinates":[-119.507594,47.374386],"type":"Point"}
}