{
  "type": "Feature",
  "properties": {
    "addr:full":"4411 Wallingford Ave N Seattle WA 98103",
    "addr:housenumber":"4411",
    "addr:postcode":"98103",
    "addr:street":"Wallingford Ave N",
    "iso:country":"US",
    "sg:address":"4411 Wallingford Ave N",
    "sg:city":"Seattle",
    "sg:classifiers":[
        {
            "category":"Manufacturing",
            "subcategory":"Printing",
            "type":"Manufacturing & Wholesale Goods"
        }
    ],
    "sg:phone":"+1 206 547 6462",
    "sg:postcode":"98103",
    "sg:province":"WA",
    "sg:tags":[
        "lithographic",
        "commercial"
    ],
    "wof:name":"Pro-Litho Inc",
    "wof:placetype":"venue"
},
  "geometry": {"coordinates":[-122.33626099999999,47.661275],"type":"Point"}
}