{
  "type": "Feature",
  "properties": {
    "addr:full":"20727 80th Ave S Kent WA 98032",
    "addr:housenumber":"20727",
    "addr:postcode":"98032",
    "addr:street":"80Th Ave S",
    "iso:country":"US",
    "sg:address":"20727 80th Ave S",
    "sg:city":"Kent",
    "sg:classifiers":[
        {
            "category":"Home & Garden",
            "subcategory":"Building Materials",
            "type":"Retail Goods"
        }
    ],
    "sg:phone":"+1 253 872 9510",
    "sg:postcode":"98032",
    "sg:province":"WA",
    "sg:tags":[
        "door"
    ],
    "wof:name":"Advantage Automatic Doors Inc",
    "wof:placetype":"venue"
},
  "geometry": {"coordinates":[-122.233417,47.416279],"type":"Point"}
}