{
  "type": "Feature",
  "properties": {
    "iso:country":"US",
    "sg:address":"17807 SE 38th St",
    "sg:city":"Vancouver",
    "sg:classifiers":[
        {
            "category":"Professional",
            "subcategory":"Management & Consulting",
            "type":"Services"
        }
    ],
    "sg:phone":"+1 360 256 9760",
    "sg:postcode":"98683",
    "sg:province":"WA",
    "wof:name":"K CS Consulting",
    "wof:placetype":"venue"
},
  "geometry": {"coordinates":[-122.489544,45.593404],"type":"Point"}
}