{
  "type": "Feature",
  "properties": {
    "addr:full":"300 E Pine St Seattle WA 98122",
    "addr:housenumber":"300",
    "addr:postcode":"98122",
    "addr:street":"E Pine St",
    "iso:country":"US",
    "sg:address":"300 E Pine St",
    "sg:city":"Seattle",
    "sg:phone":"+1 206 506 7080",
    "sg:postcode":"98122",
    "sg:province":"WA",
    "sg:website":"http://www.macys.com",
    "wof:name":"Macy's",
    "wof:placetype":"venue"
},
  "geometry": {"coordinates":[-122.327888,47.6152],"type":"Point"}
}