{
  "type": "Feature",
  "properties": {
    "addr:full":"11 W Sentry Ct Shelton WA 98584",
    "addr:housenumber":"11",
    "addr:postcode":"98584",
    "addr:street":"W Sentry Ct",
    "iso:country":"US",
    "sg:address":"11 W Sentry Ct",
    "sg:city":"Shelton",
    "sg:classifiers":[
        {
            "category":"Organizations",
            "subcategory":"Religious Organization",
            "type":"Services"
        }
    ],
    "sg:phone":"+1 360 426 4286",
    "sg:postcode":"98584",
    "sg:province":"WA",
    "sg:tags":[
        "church"
    ],
    "sg:website":"www.watchtower.org",
    "wof:name":"Jehovah's Witnesses",
    "wof:placetype":"venue"
},
  "geometry": {"coordinates":[-123.133495,47.206092],"type":"Point"}
}