{
  "type": "Feature",
  "properties": {
    "addr:full":"6515 W Clearwater Ave Kennewick WA 99336",
    "addr:housenumber":"6515",
    "addr:postcode":"w;99336",
    "addr:street":"Clearwater Ave",
    "iso:country":"US",
    "sg:address":"6515 W Clearwater Ave",
    "sg:city":"Kennewick",
    "sg:classifiers":[
        {
            "category":"Banks & Credit Unions",
            "subcategory":"Bank",
            "type":"Services"
        }
    ],
    "sg:phone":"+1 509 735 5553",
    "sg:postcode":"99336",
    "sg:province":"WA",
    "sg:tags":[
        "personal",
        "loan",
        "real estate",
        "institution"
    ],
    "wof:name":"Tri City Home Loans",
    "wof:placetype":"venue"
},
  "geometry": {"coordinates":[-119.20512100000001,46.212384],"type":"Point"}
}