{
  "type": "Feature",
  "properties": {
    "addr:full":"2618 Quarterhorse Way Richland WA 99352",
    "addr:postcode":"2618;99352",
    "addr:street":"Quarterhorse Way",
    "iso:country":"US",
    "sg:address":"2618 Quarterhorse Way",
    "sg:city":"Richland",
    "sg:classifiers":[
        {
            "category":"Professional",
            "subcategory":"Management & Consulting",
            "type":"Services"
        }
    ],
    "sg:phone":"+1 509 627 3000",
    "sg:postcode":"99352",
    "sg:province":"WA",
    "sg:tags":[
        "consultant",
        "business"
    ],
    "wof:name":"Allen Johnson",
    "wof:placetype":"venue"
},
  "geometry": {"coordinates":[-119.312055,46.242827],"type":"Point"}
}