{
  "type": "Feature",
  "properties": {
    "iso:country":"US",
    "sg:address":"2 Auburn Way N",
    "sg:city":"Auburn",
    "sg:classifiers":[
        {
            "category":"Real Estate",
            "subcategory":"Real Estate Agent",
            "type":"Services"
        }
    ],
    "sg:phone":"+1 360 802 2500",
    "sg:postcode":"98002",
    "sg:province":"WA",
    "wof:name":"Doug Maris Real Estate Sales &",
    "wof:placetype":"venue"
},
  "geometry": {"coordinates":[-122.225826,47.308333],"type":"Point"}
}