{
  "type": "Feature",
  "properties": {
    "addr:full":"1013 Bridge St Clarkston WA 99403",
    "addr:housenumber":"1013",
    "addr:postcode":"99403",
    "addr:street":"Bridge St",
    "iso:country":"US",
    "sg:address":"1013 Bridge St",
    "sg:city":"Clarkston",
    "sg:classifiers":[
        {
            "category":"Health Services",
            "subcategory":"Chiropractor",
            "type":"Services"
        }
    ],
    "sg:phone":"+1 509 758 9214",
    "sg:postcode":"99403",
    "sg:province":"WA",
    "wof:name":"Dwyer Charles C Chiropractic",
    "wof:placetype":"venue"
},
  "geometry": {"coordinates":[-117.050901,46.419855],"type":"Point"}
}