{
  "type": "Feature",
  "properties": {
    "addr:full":"4507 44th Ave SW Seattle WA 98116",
    "addr:housenumber":"4507",
    "addr:postcode":"98116",
    "addr:street":"44Th Ave Sw",
    "iso:country":"US",
    "sg:address":"4507 44th Ave SW",
    "sg:city":"Seattle",
    "sg:classifiers":[
        {
            "category":"Building & Trades",
            "subcategory":"Electrical",
            "type":"Services"
        }
    ],
    "sg:phone":"+1 206 937 6500",
    "sg:postcode":"98116",
    "sg:province":"WA",
    "sg:tags":[
        "electrical",
        "contractor"
    ],
    "wof:name":"Puget Sound Services Inc",
    "wof:placetype":"venue"
},
  "geometry": {"coordinates":[-122.38820800000001,47.561191],"type":"Point"}
}