{
  "type": "Feature",
  "properties": {
    "addr:full":"5616 6th Ave S Seattle WA 98108",
    "addr:housenumber":"5616",
    "addr:postcode":"98108",
    "addr:street":"6Th Ave S",
    "iso:country":"US",
    "sg:address":"5616 6th Ave S",
    "sg:city":"Seattle",
    "sg:classifiers":[
        {
            "category":"Wholesale",
            "subcategory":"Durable Goods & Equipment",
            "type":"Manufacturing & Wholesale Goods"
        }
    ],
    "sg:phone":"+1 206 767 3909",
    "sg:postcode":"98108",
    "sg:province":"WA",
    "sg:tags":[
        "importer"
    ],
    "wof:name":"Haasasian Importers LTD",
    "wof:placetype":"venue"
},
  "geometry": {"coordinates":[-122.326791,47.551986],"type":"Point"}
}