{
  "type": "Feature",
  "properties": {
    "addr:full":"621 9th St Benton City WA 99320",
    "addr:housenumber":"621",
    "addr:postcode":"99320",
    "addr:street":"9Th St",
    "iso:country":"US",
    "sg:address":"621 9th St",
    "sg:city":"Benton City",
    "sg:classifiers":[
        {
            "category":"Social Services",
            "type":"Services"
        }
    ],
    "sg:phone":"+1 509 588 5454",
    "sg:postcode":"99320",
    "sg:province":"WA",
    "wof:name":"Benton City Food Bank",
    "wof:placetype":"venue"
},
  "geometry": {"coordinates":[-119.48771000000001,46.263532],"type":"Point"}
}