{
  "type": "Feature",
  "properties": {
    "addr:full":"410 S 188th St Seattle WA 98148",
    "addr:housenumber":"410",
    "addr:postcode":"98148",
    "addr:street":"S 188Th St",
    "iso:country":"US",
    "sg:address":"410 S 188th St",
    "sg:city":"Seattle",
    "sg:classifiers":[
        {
            "category":"Communications",
            "subcategory":"Film & Video Production",
            "type":"Services"
        }
    ],
    "sg:phone":"+1 206 433 8801",
    "sg:postcode":"98148",
    "sg:province":"WA",
    "sg:tags":[
        "motion"
    ],
    "wof:name":"Fly Away Productions Inc",
    "wof:placetype":"venue"
},
  "geometry": {"coordinates":[-122.328113,47.434365],"type":"Point"}
}