{
  "type": "Feature",
  "properties": {
    "addr:full":"107 Peach Tree Ln Yakima WA 98908",
    "addr:housenumber":"107",
    "addr:postcode":"98908",
    "addr:street":"Peach Tree Ln",
    "iso:country":"US",
    "sg:address":"107 Peach Tree Ln",
    "sg:city":"Yakima",
    "sg:classifiers":[
        {
            "category":"Shopping",
            "subcategory":"Gifts & Souvenirs",
            "type":"Retail Goods"
        }
    ],
    "sg:phone":"+1 509 972 9547",
    "sg:postcode":"98908",
    "sg:province":"WA",
    "wof:name":"Twisted Sisters LLC",
    "wof:placetype":"venue"
},
  "geometry": {"coordinates":[-120.57649600000001,46.596434],"type":"Point"}
}