{
  "type": "Feature",
  "properties": {
    "addr:full":"3312 S Best Rd Veradale WA 99037",
    "addr:housenumber":"3312",
    "addr:postcode":"99037",
    "addr:street":"S Best Rd",
    "iso:country":"US",
    "sg:address":"3312 S Best Rd",
    "sg:city":"Veradale",
    "sg:classifiers":[
        {
            "category":"Building & Trades",
            "subcategory":"Landscaping Services",
            "type":"Services"
        }
    ],
    "sg:phone":"+1 509 924 9425",
    "sg:postcode":"99037",
    "sg:province":"WA",
    "sg:tags":[
        "consultant",
        "designer",
        "landscape"
    ],
    "wof:name":"Craig Zeutschel Inc",
    "wof:placetype":"venue"
},
  "geometry": {"coordinates":[-117.212845,47.627256],"type":"Point"}
}