{
  "type": "Feature",
  "properties": {
    "addr:full":"8400 Beacon Ave S Seattle WA 98118",
    "addr:housenumber":"8400",
    "addr:postcode":"98118",
    "addr:street":"Beacon Ave S",
    "iso:country":"US",
    "sg:address":"8400 Beacon Ave S",
    "sg:city":"Seattle",
    "sg:classifiers":[
        {
            "category":"Building & Trades",
            "subcategory":"Construction",
            "type":"Services"
        }
    ],
    "sg:phone":"+1 206 725 9969",
    "sg:postcode":"98118",
    "sg:province":"WA",
    "sg:tags":[
        "drywall",
        "painting",
        "contractor"
    ],
    "wof:name":"Peterson Drywall Taping",
    "wof:placetype":"venue"
},
  "geometry": {"coordinates":[-122.287943,47.526119],"type":"Point"}
}