{
  "type": "Feature",
  "properties": {
    "addr:full":"317 E Main St Pullman WA 99163",
    "addr:housenumber":"317",
    "addr:postcode":"99163",
    "addr:street":"E Main St",
    "iso:country":"US",
    "sg:address":"317 E Main St",
    "sg:city":"Pullman",
    "sg:classifiers":[
        {
            "category":"Food & Beverages",
            "subcategory":"Groceries & Convenience Stores",
            "type":"Retail Goods"
        }
    ],
    "sg:phone":"+1 509 334 3793",
    "sg:postcode":"99163",
    "sg:province":"WA",
    "wof:name":"Interntnal Store Asian Grcries",
    "wof:placetype":"venue"
},
  "geometry": {"coordinates":[-117.17897000000001,46.72951],"type":"Point"}
}