{
  "type": "Feature",
  "properties": {
    "addr:full":"5601 E Agate Rd Shelton WA 98584",
    "addr:housenumber":"5601",
    "addr:postcode":"98584",
    "addr:street":"E Agate Rd",
    "iso:country":"US",
    "sg:address":"5601 E Agate Rd",
    "sg:city":"Shelton",
    "sg:classifiers":[
        {
            "category":"Professional",
            "subcategory":"Business Services",
            "type":"Services"
        }
    ],
    "sg:phone":"+1 360 427 6618",
    "sg:postcode":"98584",
    "sg:province":"WA",
    "wof:name":"K J Enterprises Inc",
    "wof:placetype":"venue"
},
  "geometry": {"coordinates":[-122.965647,47.214283],"type":"Point"}
}