{
  "type": "Feature",
  "properties": {
    "addr:full":"2314 211th St SE Bothell WA 98021",
    "addr:housenumber":"2314",
    "addr:postcode":"98021",
    "addr:street":"211Th St Se",
    "iso:country":"US",
    "sg:address":"2314 211th St SE",
    "sg:city":"Bothell",
    "sg:classifiers":[
        {
            "category":"Shopping",
            "subcategory":"Computers & Home Electronics",
            "type":"Retail Goods"
        }
    ],
    "sg:phone":"+1 425 487 1841",
    "sg:postcode":"98021",
    "sg:province":"WA",
    "wof:name":"Stusser Computer Services",
    "wof:placetype":"venue"
},
  "geometry": {"coordinates":[-122.20035799999999,47.806388],"type":"Point"}
}