{
  "type": "Feature",
  "properties": {
    "iso:country":"US",
    "sg:address":"5614 S Chapman Rd",
    "sg:city":"Greenacres",
    "sg:classifiers":[
        {
            "category":"Professional",
            "subcategory":"Accounting & Tax Preparation",
            "type":"Services"
        }
    ],
    "sg:phone":"+1 509 921 1962",
    "sg:postcode":"99016",
    "sg:province":"WA",
    "sg:tags":[
        "bookkeeping",
        "general"
    ],
    "wof:name":"Ochoa's Bookkeeping Svc",
    "wof:placetype":"venue"
},
  "geometry": {"coordinates":[-117.174126,47.608224],"type":"Point"}
}