{
  "type": "Feature",
  "properties": {
    "addr:full":"724 E Main Ave Puyallup WA 98372",
    "addr:housenumber":"724",
    "addr:postcode":"98372",
    "addr:street":"E Main Ave",
    "iso:country":"US",
    "sg:address":"724 E Main Ave",
    "sg:city":"Puyallup",
    "sg:classifiers":[
        {
            "category":"Shopping",
            "subcategory":"Florist",
            "type":"Retail Goods"
        }
    ],
    "sg:phone":"+1 253 845 9573",
    "sg:postcode":"98372",
    "sg:province":"WA",
    "sg:website":"www.bentonstwincedarsflorist.com",
    "wof:name":"Benton's Twin Cedars Florist",
    "wof:placetype":"venue"
},
  "geometry": {"coordinates":[-122.284665,47.191906],"type":"Point"}
}