{
  "type": "Feature",
  "properties": {
    "addr:full":"237 S Washington Ave Newport WA 99156",
    "addr:housenumber":"237",
    "addr:postcode":"99156",
    "addr:street":"S Washington Ave",
    "iso:country":"US",
    "sg:address":"237 S Washington Ave",
    "sg:city":"Newport",
    "sg:classifiers":[
        {
            "category":"Restaurant",
            "type":"Food & Drink"
        }
    ],
    "sg:menulink":"http://www.allmenus.com/wa/newport/68470-pizza-factory/menu/",
    "sg:phone":"+1 509 447 5666",
    "sg:postcode":"99156",
    "sg:province":"WA",
    "sg:tags":[
        "american",
        "pizza"
    ],
    "wof:name":"Pizza Factory",
    "wof:placetype":"venue"
},
  "geometry": {"coordinates":[-117.044239,48.179668],"type":"Point"}
}