{
  "type": "Feature",
  "properties": {
    "iso:country":"US",
    "sg:address":"1703 Auburn Way S",
    "sg:city":"Auburn",
    "sg:classifiers":[
        {
            "category":"Personal",
            "subcategory":"Beauty Salon",
            "type":"Services"
        }
    ],
    "sg:phone":"+1 253 653 3479",
    "sg:postcode":"98002",
    "sg:province":"WA",
    "sg:tags":[
        "shop"
    ],
    "wof:name":"Ruths Hair",
    "wof:placetype":"venue"
},
  "geometry": {"coordinates":[-122.19760599999999,47.289288],"type":"Point"}
}