{
  "type": "Feature",
  "properties": {
    "addr:full":"301 N Bend Blvd N North Bend WA 98045",
    "addr:housenumber":"301",
    "addr:postcode":"98045",
    "addr:street":"N Bend Blvd N",
    "iso:country":"US",
    "sg:address":"301 N Bend Blvd N",
    "sg:city":"North Bend",
    "sg:classifiers":[
        {
            "category":"Personal",
            "type":"Services"
        }
    ],
    "sg:phone":"+1 425 831 5231",
    "sg:postcode":"98045",
    "sg:province":"WA",
    "sg:tags":[
        "therapist",
        "massage"
    ],
    "wof:name":"Dina Gosse",
    "wof:placetype":"venue"
},
  "geometry": {"coordinates":[-121.78674599999999,47.498827],"type":"Point"}
}