{
  "type": "Feature",
  "properties": {
    "addr:full":"19061 Road 4 SW Quincy WA 98848",
    "addr:housenumber":"19061",
    "addr:postcode":"98848",
    "addr:street":"Road 4 Sw",
    "iso:country":"US",
    "sg:address":"19061 Road 4 SW",
    "sg:city":"Quincy",
    "sg:classifiers":[
        {
            "category":"Building & Trades",
            "subcategory":"Cleaning & Sanitation",
            "type":"Services"
        },
        {
            "category":"Farming",
            "subcategory":"Orchard",
            "type":"Manufacturing & Wholesale Goods"
        }
    ],
    "sg:phone":"+1 509 785 5031",
    "sg:postcode":"98848",
    "sg:province":"WA",
    "sg:tags":[
        "drying",
        "grain"
    ],
    "wof:name":"Niderost Farms Inc",
    "wof:placetype":"venue"
},
  "geometry": {"coordinates":[-119.91643500000001,47.029419],"type":"Point"}
}