{
  "type": "Feature",
  "properties": {
    "addr:full":"15518 N Myrtle St Mead WA 99021",
    "addr:housenumber":"15518",
    "addr:postcode":"99021",
    "addr:street":"N Myrtle St",
    "iso:country":"US",
    "sg:address":"15518 N Myrtle St",
    "sg:city":"Mead",
    "sg:classifiers":[
        {
            "category":"Building & Trades",
            "subcategory":"Construction",
            "type":"Services"
        }
    ],
    "sg:phone":"+1 509 468 1494",
    "sg:postcode":"99021",
    "sg:province":"WA",
    "sg:tags":[
        "hanging",
        "contractor"
    ],
    "wof:name":"Picture Perfect Painting",
    "wof:placetype":"venue"
},
  "geometry": {"coordinates":[-117.352926,47.799352],"type":"Point"}
}