{
  "type": "Feature",
  "properties": {
    "addr:full":"18722 12th Ave NE Seattle WA 98155",
    "addr:housenumber":"18722",
    "addr:postcode":"98155",
    "addr:street":"12Th Ave Ne",
    "iso:country":"US",
    "sg:address":"18722 12th Ave NE",
    "sg:city":"Seattle",
    "sg:classifiers":[
        {
            "category":"Arts & Performance",
            "subcategory":"Theater",
            "type":"Entertainment"
        }
    ],
    "sg:phone":"+1 206 545 0402",
    "sg:postcode":"98155",
    "sg:province":"WA",
    "sg:tags":[
        "music"
    ],
    "wof:name":"Shoreline Music",
    "wof:placetype":"venue"
},
  "geometry": {"coordinates":[-122.315994,47.765275],"type":"Point"}
}