{
  "type": "Feature",
  "properties": {
    "addr:full":"1325 Aaron Dr # 103 Richland WA 99352",
    "addr:housenumber":"1325",
    "addr:postcode":"99352",
    "addr:street":"Aaron Dr # 103",
    "iso:country":"US",
    "sg:address":"1325 Aaron Dr # 103",
    "sg:city":"Richland",
    "sg:classifiers":[
        {
            "category":"Personal",
            "subcategory":"Beauty Salon",
            "type":"Services"
        }
    ],
    "sg:phone":"+1 509 943 3669",
    "sg:postcode":"99352",
    "sg:province":"WA",
    "sg:tags":[
        "hair",
        "stylist"
    ],
    "wof:name":"Monkey Dooz Salon Spa & Btq",
    "wof:placetype":"venue"
},
  "geometry": {"coordinates":[-119.268028,46.263805],"type":"Point"}
}