{
  "type": "Feature",
  "properties": {
    "addr:full":"7629 S 188th St Kent WA 98032",
    "addr:housenumber":"7629",
    "addr:postcode":"98032",
    "addr:street":"S 188Th St",
    "iso:country":"US",
    "sg:address":"7629 S 188th St",
    "sg:city":"Kent",
    "sg:classifiers":[
        {
            "category":"Retail",
            "subcategory":"Storage",
            "type":"Services"
        }
    ],
    "sg:phone":"+1 253 867 1320",
    "sg:postcode":"98032",
    "sg:province":"WA",
    "sg:tags":[
        "warehouse",
        "cold"
    ],
    "sg:website":"http://www.henningsen.com",
    "wof:name":"Henningsen Cold Storage Co.",
    "wof:placetype":"venue"
},
  "geometry": {"coordinates":[-122.238646,47.433934],"type":"Point"}
}