{
  "type": "Feature",
  "properties": {
    "addr:full":"701 Moore Rd Toutle WA 98649",
    "addr:housenumber":"701",
    "addr:postcode":"98649",
    "addr:street":"Moore Rd",
    "iso:country":"US",
    "sg:address":"701 Moore Rd",
    "sg:city":"Toutle",
    "sg:classifiers":[
        {
            "category":"Retail",
            "subcategory":"Auto Repair",
            "type":"Services"
        }
    ],
    "sg:phone":"+1 360 274 4338",
    "sg:postcode":"98649",
    "sg:province":"WA",
    "sg:tags":[
        "general"
    ],
    "wof:name":"Mobile Auto Repair & Lube",
    "wof:placetype":"venue"
},
  "geometry": {"coordinates":[-122.72158899999999,46.289274],"type":"Point"}
}