{
  "type": "Feature",
  "properties": {
    "addr:full":"15824 66th Ave NW Gig Harbor WA 98332",
    "addr:housenumber":"15824",
    "addr:postcode":"98332",
    "addr:street":"66Th Ave Nw",
    "iso:country":"US",
    "sg:address":"15824 66th Ave NW",
    "sg:city":"Gig Harbor",
    "sg:classifiers":[
        {
            "category":"Home & Garden",
            "subcategory":"Garden Supply",
            "type":"Retail Goods"
        },
        {
            "category":"Home & Garden",
            "subcategory":"Hardware",
            "type":"Retail Goods"
        }
    ],
    "sg:phone":"+1 253 851 4441",
    "sg:postcode":"98332",
    "sg:province":"WA",
    "sg:tags":[
        "nursery",
        "gardening",
        "store"
    ],
    "wof:name":"Cenex Harvest States",
    "wof:placetype":"venue"
},
  "geometry": {"coordinates":[-122.62599899999999,47.4011],"type":"Point"}
}