{
  "type": "Feature",
  "properties": {
    "addr:full":"7095 E Van Buren Ave Port Orchard WA 98366",
    "addr:housenumber":"7095",
    "addr:postcode":"98366",
    "addr:street":"E Van Buren Ave",
    "iso:country":"US",
    "sg:address":"7095 E Van Buren Ave",
    "sg:city":"Port Orchard",
    "sg:classifiers":[
        {
            "category":"Retail",
            "subcategory":"Repair Shop",
            "type":"Services"
        }
    ],
    "sg:phone":"+1 360 769 9149",
    "sg:postcode":"98366",
    "sg:province":"WA",
    "sg:tags":[
        "welding"
    ],
    "wof:name":"Advanced Welding & Steel Inc",
    "wof:placetype":"venue"
},
  "geometry": {"coordinates":[-122.55849000000001,47.544894],"type":"Point"}
}