{
  "type": "Feature",
  "properties": {
    "addr:full":"12505 100th Ave NE Kirkland WA 98034",
    "addr:housenumber":"12505",
    "addr:postcode":"98034",
    "addr:street":"100Th Ave Ne",
    "iso:country":"US",
    "sg:address":"12505 100th Ave NE",
    "sg:city":"Kirkland",
    "sg:classifiers":[
        {
            "category":"Professional",
            "type":"Services"
        }
    ],
    "sg:phone":"+1 425 820 8588",
    "sg:postcode":"98034",
    "sg:province":"WA",
    "wof:name":"Adnavseam Audio Entertain",
    "wof:placetype":"venue"
},
  "geometry": {"coordinates":[-122.207871,47.714006],"type":"Point"}
}