{
  "type": "Feature",
  "properties": {
    "addr:full":"580 N Waynes Ridge Cir Stanwood WA 98282",
    "addr:housenumber":"580",
    "addr:postcode":"98282",
    "addr:street":"N Waynes Ridge Cir",
    "iso:country":"US",
    "sg:address":"580 N Waynes Ridge Cir",
    "sg:city":"Stanwood",
    "sg:classifiers":[
        {
            "category":"Professional",
            "subcategory":"Business Services",
            "type":"Services"
        }
    ],
    "sg:phone":"+1 360 387 9937",
    "sg:postcode":"98282",
    "sg:province":"WA",
    "wof:name":"Camano Sales",
    "wof:placetype":"venue"
},
  "geometry": {"coordinates":[-122.491316,48.227592],"type":"Point"}
}