{
  "type": "Feature",
  "properties": {
    "addr:full":"2601 70th Ave W University Place WA 98466",
    "addr:housenumber":"2601",
    "addr:postcode":"98466",
    "addr:street":"70Th Ave W;Place",
    "iso:country":"US",
    "sg:address":"2601 70th Ave W",
    "sg:city":"University Place",
    "sg:classifiers":[
        {
            "category":"Professional",
            "subcategory":"Accounting & Tax Preparation",
            "type":"Services"
        }
    ],
    "sg:phone":"+1 253 565 2626",
    "sg:postcode":"98466",
    "sg:province":"WA",
    "sg:tags":[
        "accountant"
    ],
    "wof:name":"Frank J Messina Inc",
    "wof:placetype":"venue"
},
  "geometry": {"coordinates":[-122.530215,47.235692],"type":"Point"}
}