{
  "type": "Feature",
  "properties": {
    "addr:full":"120 14th Ave SE Puyallup WA 98372",
    "addr:housenumber":"120",
    "addr:postcode":"98372",
    "addr:street":"14Th Ave Se",
    "iso:country":"US",
    "sg:address":"120 14th Ave SE",
    "sg:city":"Puyallup",
    "sg:classifiers":[
        {
            "category":"Health Services",
            "subcategory":"Doctor",
            "type":"Services"
        }
    ],
    "sg:phone":"+1 253 435 5200",
    "sg:postcode":"98372",
    "sg:province":"WA",
    "sg:tags":[
        "physician",
        "surgeon"
    ],
    "wof:name":"Mt Tahoma Gynecology",
    "wof:placetype":"venue"
},
  "geometry": {"coordinates":[-122.292314,47.178712],"type":"Point"}
}