{
  "type": "Feature",
  "properties": {
    "addr:full":"206 Broadway Ave E Seattle WA 98102",
    "addr:housenumber":"206",
    "addr:postcode":"98102",
    "addr:street":"Broadway Ave E",
    "iso:country":"US",
    "sg:address":"206 Broadway Ave E",
    "sg:city":"Seattle",
    "sg:classifiers":[
        {
            "category":"Personal",
            "subcategory":"Tanning Parlor",
            "type":"Services"
        }
    ],
    "sg:phone":"+1 206 328 8267",
    "sg:postcode":"98102",
    "sg:province":"WA",
    "sg:website":"www.fastan.com",
    "wof:name":"Fastan",
    "wof:placetype":"venue"
},
  "geometry": {"coordinates":[-122.320866,47.620031],"type":"Point"}
}