{
  "type": "Feature",
  "properties": {
    "addr:full":"24839 SE 278th St Maple Valley WA 98038",
    "addr:postcode":"24839;98038",
    "addr:street":"Se 278Th St",
    "iso:country":"US",
    "sg:address":"24839 SE 278th St",
    "sg:city":"Maple Valley",
    "sg:classifiers":[
        {
            "category":"Professional",
            "subcategory":"Art Services",
            "type":"Services"
        }
    ],
    "sg:phone":"+1 425 413 8375",
    "sg:postcode":"98038",
    "sg:province":"WA",
    "sg:tags":[
        "commercial",
        "design"
    ],
    "wof:name":"Avalon Project Partners Inc",
    "wof:placetype":"venue"
},
  "geometry": {"coordinates":[-122.008905,47.351539],"type":"Point"}
}