{
  "type": "Feature",
  "properties": {
    "addr:full":"10424 SE 20th St Bellevue WA 98004",
    "addr:housenumber":"10424",
    "addr:postcode":"98004",
    "addr:street":"Se 20Th St",
    "iso:country":"US",
    "sg:address":"10424 SE 20th St",
    "sg:city":"Bellevue",
    "sg:classifiers":[
        {
            "category":"Building & Trades",
            "subcategory":"Locksmith",
            "type":"Services"
        }
    ],
    "sg:phone":"+1 206 577 5623",
    "sg:postcode":"98004",
    "sg:province":"WA",
    "sg:tags":[
        "key"
    ],
    "wof:name":"A-1 Locksmith",
    "wof:placetype":"venue"
},
  "geometry": {"coordinates":[-122.200951,47.592685],"type":"Point"}
}