{
  "type": "Feature",
  "properties": {
    "addr:full":"14900 Interurban Ave S Ste 271 Seattle WA 98168",
    "addr:housenumber":"14900",
    "addr:postcode":"98168",
    "addr:street":"Interurban Ave S Ste 271",
    "iso:country":"US",
    "sg:address":"14900 Interurban Ave S Ste 271",
    "sg:city":"Seattle",
    "sg:classifiers":[
        {
            "category":"Landmark",
            "subcategory":"Tourist Information",
            "type":"Public Place"
        }
    ],
    "sg:phone":"+1 206 587 0228",
    "sg:postcode":"98168",
    "sg:province":"WA",
    "sg:tags":[
        "tour"
    ],
    "sg:website":"www.japantourdesk.com/",
    "wof:name":"Japan Enterprises",
    "wof:placetype":"venue"
},
  "geometry": {"coordinates":[-122.25234399999999,47.468853],"type":"Point"}
}