{
  "type": "Feature",
  "properties": {
    "addr:full":"13921 N Downing Rd Mead WA 99021",
    "addr:housenumber":"13921",
    "addr:postcode":"99021",
    "addr:street":"N Downing Rd Mead",
    "iso:country":"US",
    "sg:address":"13921 N Downing Rd",
    "sg:city":"Mead",
    "sg:classifiers":[
        {
            "category":"Building & Trades",
            "subcategory":"Construction",
            "type":"Services"
        }
    ],
    "sg:phone":"+1 509 466 9367",
    "sg:postcode":"99021",
    "sg:province":"WA",
    "sg:tags":[
        "industrial",
        "supply",
        "contractor",
        "equipment",
        "contractors-commercial",
        "drywall"
    ],
    "wof:name":"Pro Bulding Systems",
    "wof:placetype":"venue"
},
  "geometry": {"coordinates":[-117.239098,47.782456],"type":"Point"}
}