{
  "type": "Feature",
  "properties": {
    "addr:full":"920 Fir St Longview WA 98632",
    "addr:housenumber":"920",
    "addr:postcode":"98632",
    "addr:street":"Fir St",
    "iso:country":"US",
    "sg:address":"920 Fir St",
    "sg:city":"Longview",
    "sg:classifiers":[
        {
            "category":"Organizations",
            "subcategory":"Non-profit Organization",
            "type":"Services"
        }
    ],
    "sg:phone":"+1 360 423 2806",
    "sg:postcode":"98632",
    "sg:province":"WA",
    "sg:tags":[
        "info",
        "addiction",
        "abuse",
        "treatment",
        "drug"
    ],
    "wof:name":"Awakenings",
    "wof:placetype":"venue"
},
  "geometry": {"coordinates":[-122.933734,46.1315],"type":"Point"}
}