{
  "type": "Feature",
  "properties": {
    "addr:full":"6018 Portal Way Ferndale WA 98248",
    "addr:housenumber":"6018",
    "addr:postcode":"98248",
    "addr:street":"Portal Way",
    "iso:country":"US",
    "sg:address":"6018 Portal Way",
    "sg:city":"Ferndale",
    "sg:classifiers":[
        {
            "category":"Tea Room",
            "subcategory":"None",
            "type":"Food & Drink"
        },
        {
            "category":"Coffee & Tea",
            "type":"Food & Drink"
        },
        {
            "category":"Restaurant",
            "type":"Food & Drink"
        }
    ],
    "sg:phone":"+1 360 384 4866",
    "sg:postcode":"98248",
    "sg:province":"WA",
    "wof:name":"Curb Shots",
    "wof:placetype":"venue"
},
  "geometry": {"coordinates":[-122.584794,48.859718],"type":"Point"}
}