{
  "type": "Feature",
  "properties": {
    "iso:country":"US",
    "sg:address":"511 5th Ave",
    "sg:city":"Forks",
    "sg:classifiers":[
        {
            "category":"Organizations",
            "subcategory":"Religious Organization",
            "type":"Services"
        }
    ],
    "sg:phone":"+1 360 374 9184",
    "sg:postcode":"98331",
    "sg:province":"WA",
    "sg:tags":[
        "church"
    ],
    "wof:name":"St Anne's Church",
    "wof:placetype":"venue"
},
  "geometry": {"coordinates":[-124.391634,47.945923],"type":"Point"}
}