{
  "type": "Feature",
  "properties": {
    "addr:full":"30676 Harker Canyon Rd N Davenport WA 99122",
    "addr:postcode":"30676;99122",
    "addr:street":"Harker Canyon Rd N",
    "iso:country":"US",
    "sg:address":"30676 Harker Canyon Rd N",
    "sg:city":"Davenport",
    "sg:classifiers":[
        {
            "category":"Professional",
            "subcategory":"Computer Services",
            "type":"Services"
        }
    ],
    "sg:phone":"+1 509 725 2882",
    "sg:postcode":"99122",
    "sg:province":"WA",
    "sg:tags":[
        "related"
    ],
    "wof:name":"Rux Electronics",
    "wof:placetype":"venue"
},
  "geometry": {"coordinates":[-118.12013899999999,47.724368],"type":"Point"}
}