{
  "type": "Feature",
  "properties": {
    "addr:full":"1104 Main St Vancouver WA 98660",
    "addr:housenumber":"1104",
    "addr:postcode":"98660",
    "addr:street":"Main St",
    "iso:country":"US",
    "sg:address":"1104 Main St",
    "sg:city":"Vancouver",
    "sg:classifiers":[
        {
            "category":"Building & Trades",
            "subcategory":"Construction",
            "type":"Services"
        }
    ],
    "sg:phone":"+1 360 693 4143",
    "sg:postcode":"98660",
    "sg:province":"WA",
    "sg:tags":[
        "contractor"
    ],
    "wof:name":"Denjoe Construction",
    "wof:placetype":"venue"
},
  "geometry": {"coordinates":[-122.671784,45.629569],"type":"Point"}
}