{
  "type": "Feature",
  "properties": {
    "addr:full":"16 N Columbia St Wenatchee WA 98801",
    "addr:housenumber":"16",
    "addr:postcode":"98801",
    "addr:street":"N Columbia St",
    "iso:country":"US",
    "sg:address":"16 N Columbia St",
    "sg:city":"Wenatchee",
    "sg:classifiers":[
        {
            "category":"Wholesale",
            "subcategory":"Groceries",
            "type":"Manufacturing & Wholesale Goods"
        }
    ],
    "sg:phone":"+1 509 662 3521",
    "sg:postcode":"98801",
    "sg:province":"WA",
    "sg:tags":[
        "drink",
        "soft"
    ],
    "wof:name":"Coca-Cola",
    "wof:placetype":"venue"
},
  "geometry": {"coordinates":[-120.31044199999999,47.425264],"type":"Point"}
}