{
  "type": "Feature",
  "properties": {
    "addr:full":"Overlake Hospital 1035 116th Ave NE Bellevue WA 98004",
    "addr:housenumber":"1035",
    "addr:postcode":"98004",
    "addr:street":"116Th Ave Ne",
    "iso:country":"US",
    "sg:address":"Overlake Hospital 1035 116th Ave NE",
    "sg:city":"Bellevue",
    "sg:classifiers":[
        {
            "category":"Restaurant",
            "type":"Food & Drink"
        }
    ],
    "sg:phone":"+1 425 688 5000",
    "sg:postcode":"98004",
    "sg:province":"WA",
    "sg:tags":[
        "traditional",
        "american"
    ],
    "wof:name":"The Atrium Cafe",
    "wof:placetype":"venue"
},
  "geometry": {"coordinates":[-122.18644399999999,47.622209],"type":"Point"}
}