{
  "type": "Feature",
  "properties": {
    "addr:full":"702 E Metler Ln Spokane WA 99218",
    "addr:housenumber":"702",
    "addr:postcode":"99218",
    "addr:street":"E Metler Ln",
    "iso:country":"US",
    "sg:address":"702 E Metler Ln",
    "sg:city":"Spokane",
    "sg:classifiers":[
        {
            "category":"Health Services",
            "subcategory":"Clinic",
            "type":"Services"
        }
    ],
    "sg:phone":"+1 509 994 9689",
    "sg:postcode":"99218",
    "sg:province":"WA",
    "sg:tags":[
        "home",
        "care"
    ],
    "wof:name":"Respiratory Connections",
    "wof:placetype":"venue"
},
  "geometry": {"coordinates":[-117.397809,47.76855],"type":"Point"}
}