{
  "type": "Feature",
  "properties": {
    "iso:country":"US",
    "sg:address":"5264 Cherry Tree Ln",
    "sg:city":"Blaine",
    "sg:classifiers":[
        {
            "category":"Shopping",
            "subcategory":"Hobbies, Toys, & Games",
            "type":"Retail Goods"
        }
    ],
    "sg:phone":"+1 360 371 3725",
    "sg:postcode":"98230",
    "sg:province":"WA",
    "wof:name":"Gina Paulene Dolls Needle Work",
    "wof:placetype":"venue"
},
  "geometry": {"coordinates":[-122.768918,48.944043],"type":"Point"}
}