{
  "type": "Feature",
  "properties": {
    "addr:full":"9015 Holman Rd NW Ste 1 Seattle WA 98117",
    "addr:housenumber":"9015",
    "addr:postcode":"98117",
    "addr:street":"Holman Rd Nw Ste 1",
    "iso:country":"US",
    "sg:address":"9015 Holman Rd NW Ste 1",
    "sg:city":"Seattle",
    "sg:classifiers":[
        {
            "category":"Health Services",
            "subcategory":"Health Practitioner",
            "type":"Services"
        }
    ],
    "sg:phone":"+1 206 782 2126",
    "sg:postcode":"98117",
    "sg:province":"WA",
    "sg:tags":[
        "acupuncture"
    ],
    "wof:name":"Acupunture and Oriental Medicine Center",
    "wof:placetype":"venue"
},
  "geometry": {"coordinates":[-122.37599899999999,47.6945],"type":"Point"}
}