{
  "type": "Feature",
  "properties": {
    "addr:full":"10510 Bridgeport Way SW Lakewood WA 98499",
    "addr:housenumber":"10510",
    "addr:postcode":"98499",
    "addr:street":"Bridgeport Way Sw",
    "iso:country":"US",
    "sg:address":"10510 Bridgeport Way SW",
    "sg:city":"Lakewood",
    "sg:classifiers":[
        {
            "category":"Professional",
            "type":"Services"
        }
    ],
    "sg:phone":"+1 253 584 6941",
    "sg:postcode":"98499",
    "sg:province":"WA",
    "wof:name":"Image Is Everything",
    "wof:placetype":"venue"
},
  "geometry": {"coordinates":[-122.504687,47.159437],"type":"Point"}
}