{
  "type": "Feature",
  "properties": {
    "addr:full":"9109 State Ave Marysville WA 98270",
    "addr:housenumber":"9109",
    "addr:postcode":"98270",
    "addr:street":"State Ave",
    "iso:country":"US",
    "sg:address":"9109 State Ave",
    "sg:city":"Marysville",
    "sg:classifiers":[
        {
            "category":"Restaurant",
            "type":"Food & Drink"
        }
    ],
    "sg:phone":"+1 360 653 8909",
    "sg:postcode":"98270",
    "sg:province":"WA",
    "sg:tags":[
        "eating"
    ],
    "wof:name":"Heaven II",
    "wof:placetype":"venue"
},
  "geometry": {"coordinates":[-122.17579600000001,48.076415],"type":"Point"}
}