{
  "type": "Feature",
  "properties": {
    "addr:full":"409 S Greene St Spokane WA 99202",
    "addr:housenumber":"409",
    "addr:postcode":"99202",
    "addr:street":"S Greene St",
    "iso:country":"US",
    "sg:address":"409 S Greene St",
    "sg:city":"Spokane",
    "sg:classifiers":[
        {
            "category":"Organizations",
            "subcategory":"Religious Organization",
            "type":"Services"
        }
    ],
    "sg:phone":"+1 509 535 1336",
    "sg:postcode":"99202",
    "sg:province":"WA",
    "wof:name":"New Hope Baptist Church",
    "wof:placetype":"venue"
},
  "geometry": {"coordinates":[-117.364295,47.651808],"type":"Point"}
}