{
  "type": "Feature",
  "properties": {
    "addr:full":"1100 Millerdale Ave Wenatchee WA 98801",
    "addr:housenumber":"1100",
    "addr:postcode":"98801",
    "addr:street":"Millerdale Ave",
    "iso:country":"US",
    "sg:address":"1100 Millerdale Ave",
    "sg:city":"Wenatchee",
    "sg:classifiers":[
        {
            "category":"Organizations",
            "subcategory":"Religious Organization",
            "type":"Services"
        }
    ],
    "sg:phone":"+1 509 662 7394",
    "sg:postcode":"98801",
    "sg:province":"WA",
    "wof:name":"Church Jsus Chrst Lttr Day STS",
    "wof:placetype":"venue"
},
  "geometry": {"coordinates":[-120.328163,47.411649],"type":"Point"}
}