{
  "type": "Feature",
  "properties": {
    "addr:full":"2938 Kindred Ave Tokeland WA 98590",
    "addr:housenumber":"2938",
    "addr:postcode":"98590",
    "addr:street":"Kindred Ave Tokeland",
    "iso:country":"US",
    "sg:address":"2938 Kindred Ave",
    "sg:city":"Tokeland",
    "sg:classifiers":[
        {
            "category":"Food & Beverages",
            "subcategory":"Specialty",
            "type":"Retail Goods"
        }
    ],
    "sg:phone":"+1 360 267 4315",
    "sg:postcode":"98590",
    "sg:province":"WA",
    "sg:tags":[
        "tea",
        "coffee"
    ],
    "wof:name":"Links Express At Tokeland Golf",
    "wof:placetype":"venue"
},
  "geometry": {"coordinates":[-123.987619,46.708818],"type":"Point"}
}