{
  "type": "Feature",
  "properties": {
    "addr:full":"11012 Canyon Rd E Puyallup WA 98373",
    "addr:housenumber":"11012",
    "addr:postcode":"98373",
    "addr:street":"Canyon Rd E",
    "iso:country":"US",
    "sg:address":"11012 Canyon Rd E",
    "sg:city":"Puyallup",
    "sg:classifiers":[
        {
            "category":"Restaurant",
            "type":"Food & Drink"
        }
    ],
    "sg:phone":"+1 253 535 9488",
    "sg:postcode":"98373",
    "sg:province":"WA",
    "sg:tags":[
        "eating"
    ],
    "wof:name":"Little Caesars",
    "wof:placetype":"venue"
},
  "geometry": {"coordinates":[-122.357269,47.15547],"type":"Point"}
}