{
  "type": "Feature",
  "properties": {
    "addr:full":"710 Sumner Ave Sumner WA 98390",
    "addr:housenumber":"710",
    "addr:postcode":"98390",
    "addr:street":"Sumner Ave",
    "iso:country":"US",
    "sg:address":"710 Sumner Ave",
    "sg:city":"Sumner",
    "sg:classifiers":[
        {
            "category":"Building & Trades",
            "subcategory":"Cleaning & Sanitation",
            "type":"Services"
        }
    ],
    "sg:phone":"+1 253 863 2578",
    "sg:postcode":"98390",
    "sg:province":"WA",
    "sg:tags":[
        "maintenance"
    ],
    "wof:name":"J & E Commercial Cleaning",
    "wof:placetype":"venue"
},
  "geometry": {"coordinates":[-122.23833,47.200905],"type":"Point"}
}