{
  "type": "Feature",
  "properties": {
    "addr:full":"220 Bethel Ave Port Orchard WA 98366",
    "addr:housenumber":"220",
    "addr:postcode":"98366",
    "addr:street":"Bethel Ave",
    "iso:country":"US",
    "sg:address":"220 Bethel Ave",
    "sg:city":"Port Orchard",
    "sg:classifiers":[
        {
            "category":"Health Services",
            "subcategory":"Health Practitioner",
            "type":"Services"
        }
    ],
    "sg:phone":"+1 360 876 0676",
    "sg:postcode":"98366",
    "sg:province":"WA",
    "wof:name":"Kris Bell",
    "wof:placetype":"venue"
},
  "geometry": {"coordinates":[-122.627032,47.540702],"type":"Point"}
}