{
  "type": "Feature",
  "properties": {
    "addr:full":"1737 N Wenatchee Ave Wenatchee WA 98801",
    "addr:housenumber":"1737",
    "addr:postcode":"98801",
    "addr:street":"N Wenatchee Ave",
    "iso:country":"US",
    "sg:address":"1737 N Wenatchee Ave",
    "sg:city":"Wenatchee",
    "sg:classifiers":[
        {
            "category":"Recreation",
            "type":"Entertainment"
        }
    ],
    "sg:phone":"+1 509 667 2466",
    "sg:postcode":"98801",
    "sg:province":"WA",
    "sg:tags":[
        "martial",
        "arts",
        "instruction"
    ],
    "wof:name":"Columbia River Soo Bank Do",
    "wof:placetype":"venue"
},
  "geometry": {"coordinates":[-120.330129,47.448089],"type":"Point"}
}