{
  "type": "Feature",
  "properties": {
    "addr:full":"1110 Marshall Ave Enumclaw WA 98022",
    "addr:housenumber":"1110",
    "addr:postcode":"98022",
    "addr:street":"Marshall Ave",
    "iso:country":"US",
    "sg:address":"1110 Marshall Ave",
    "sg:city":"Enumclaw",
    "sg:classifiers":[
        {
            "category":"Professional",
            "subcategory":"Business Services",
            "type":"Services"
        }
    ],
    "sg:phone":"+1 360 226 7490",
    "sg:postcode":"98022",
    "sg:province":"WA",
    "wof:name":"Vanderwel Enterprises Inc",
    "wof:placetype":"venue"
},
  "geometry": {"coordinates":[-121.987494,47.204526],"type":"Point"}
}