{
  "type": "Feature",
  "properties": {
    "addr:full":"14610 SE Fairwood Blvd Renton WA 98058",
    "addr:postcode":"14610;98058",
    "addr:street":"Se Fairwood Blvd",
    "iso:country":"US",
    "sg:address":"14610 SE Fairwood Blvd",
    "sg:city":"Renton",
    "sg:classifiers":[
        {
            "category":"Building & Trades",
            "subcategory":"Construction",
            "type":"Services"
        }
    ],
    "sg:phone":"+1 425 271 3170",
    "sg:postcode":"98058",
    "sg:province":"WA",
    "sg:tags":[
        "residential"
    ],
    "wof:name":"Keokis Enternational Inc",
    "wof:placetype":"venue"
},
  "geometry": {"coordinates":[-122.145594,47.452219],"type":"Point"}
}