{
  "type": "Feature",
  "properties": {
    "addr:full":"1632 W Sylvester St Pasco WA 99301",
    "addr:housenumber":"1632",
    "addr:postcode":"99301",
    "addr:street":"W Sylvester St",
    "iso:country":"US",
    "sg:address":"1632 W Sylvester St",
    "sg:city":"Pasco",
    "sg:classifiers":[
        {
            "category":"Wholesale",
            "subcategory":"Auto Parts",
            "type":"Manufacturing & Wholesale Goods"
        }
    ],
    "sg:phone":"+1 509 547 2679",
    "sg:postcode":"99301",
    "sg:province":"WA",
    "sg:tags":[
        "supply"
    ],
    "wof:name":"Harms Engineering Inc",
    "wof:placetype":"venue"
},
  "geometry": {"coordinates":[-119.110398,46.234002],"type":"Point"}
}