{
  "type": "Feature",
  "properties": {
    "addr:full":"405 W Chestnut Ave Yakima WA 98902",
    "addr:housenumber":"405",
    "addr:postcode":"98902",
    "addr:street":"W Chestnut Ave",
    "iso:country":"US",
    "sg:address":"405 W Chestnut Ave",
    "sg:city":"Yakima",
    "sg:classifiers":[
        {
            "category":"Personal",
            "type":"Services"
        },
        {
            "category":"Professional",
            "subcategory":"Accounting & Tax Preparation",
            "type":"Services"
        }
    ],
    "sg:phone":"+1 509 453 4736",
    "sg:postcode":"98902",
    "sg:province":"WA",
    "sg:tags":[
        "paying",
        "bill"
    ],
    "wof:name":"C F Enterprises",
    "wof:placetype":"venue"
},
  "geometry": {"coordinates":[-120.514968,46.598854],"type":"Point"}
}