{
  "type": "Feature",
  "properties": {
    "addr:full":"4417 102nd Ln NE Kirkland WA 98033",
    "addr:housenumber":"4417",
    "addr:postcode":"98033",
    "addr:street":"102Nd Ln Ne",
    "iso:country":"US",
    "sg:address":"4417 102nd Ln NE",
    "sg:city":"Kirkland",
    "sg:classifiers":[
        {
            "category":"Food & Beverages",
            "subcategory":"Specialty",
            "type":"Retail Goods"
        }
    ],
    "sg:phone":"+1 425 827 4730",
    "sg:postcode":"98033",
    "sg:province":"WA",
    "sg:tags":[
        "product",
        "direct",
        "sale"
    ],
    "wof:name":"Hinton & Assoc",
    "wof:placetype":"venue"
},
  "geometry": {"coordinates":[-122.201223,47.650209],"type":"Point"}
}