{
  "type": "Feature",
  "properties": {
    "addr:full":"514 Eskridge Way SE Olympia WA 98501",
    "addr:housenumber":"514",
    "addr:postcode":"98501",
    "addr:street":"Eskridge Way Se",
    "iso:country":"US",
    "sg:address":"514 Eskridge Way SE",
    "sg:city":"Olympia",
    "sg:classifiers":[
        {
            "category":"Building & Trades",
            "subcategory":"Construction",
            "type":"Services"
        }
    ],
    "sg:phone":"+1 360 753 4007",
    "sg:postcode":"98501",
    "sg:province":"WA",
    "sg:tags":[
        "hanging",
        "contractor"
    ],
    "wof:name":"Premier Pntg & Pressure Wshg",
    "wof:placetype":"venue"
},
  "geometry": {"coordinates":[-122.894884,47.023291],"type":"Point"}
}