{
  "type": "Feature",
  "properties": {
    "addr:full":"404 26th St Port Townsend WA 98368",
    "addr:housenumber":"404",
    "addr:postcode":"98368",
    "addr:street":"26Th St",
    "iso:country":"US",
    "sg:address":"404 26th St",
    "sg:city":"Port Townsend",
    "sg:classifiers":[
        {
            "category":"Retail",
            "subcategory":"Repair Shop",
            "type":"Services"
        }
    ],
    "sg:phone":"+1 360 379 5154",
    "sg:postcode":"98368",
    "sg:province":"WA",
    "wof:name":"Townsend Taxidermy",
    "wof:placetype":"venue"
},
  "geometry": {"coordinates":[-122.781907,48.118952],"type":"Point"}
}