{
  "type": "Feature",
  "properties": {
    "addr:full":"281 S Bay Way Port Ludlow WA 98365",
    "addr:housenumber":"281",
    "addr:postcode":"98365",
    "addr:street":"S Bay Way",
    "iso:country":"US",
    "sg:address":"281 S Bay Way",
    "sg:city":"Port Ludlow",
    "sg:classifiers":[
        {
            "category":"Shopping",
            "subcategory":"Computers & Home Electronics",
            "type":"Retail Goods"
        }
    ],
    "sg:phone":"+1 360 437 2786",
    "sg:postcode":"98365",
    "sg:province":"WA",
    "wof:name":"Tys Computers Inc",
    "wof:placetype":"venue"
},
  "geometry": {"coordinates":[-122.70185600000001,47.971992],"type":"Point"}
}