{
  "type": "Feature",
  "properties": {
    "addr:full":"14202 E Springfield Ave Spokane WA 99216",
    "addr:housenumber":"14202",
    "addr:postcode":"99216",
    "addr:street":"E Springfield Ave",
    "iso:country":"US",
    "sg:address":"14202 E Springfield Ave",
    "sg:city":"Spokane",
    "sg:classifiers":[
        {
            "category":"Shopping",
            "subcategory":"Hobbies, Toys, & Games",
            "type":"Retail Goods"
        }
    ],
    "sg:phone":"+1 509 928 2841",
    "sg:postcode":"99216",
    "sg:province":"WA",
    "wof:name":"Home Place Handcrafts",
    "wof:placetype":"venue"
},
  "geometry": {"coordinates":[-117.215846,47.663323],"type":"Point"}
}