{
  "type": "Feature",
  "properties": {
    "addr:full":"3206 N Division St Spokane WA 99207",
    "addr:housenumber":"3206",
    "addr:postcode":"99207",
    "addr:street":"N Division St",
    "iso:country":"US",
    "sg:address":"3206 N Division St",
    "sg:city":"Spokane",
    "sg:classifiers":[
        {
            "category":"Autos & Motor Vehicles",
            "subcategory":"Automobile Sales",
            "type":"Retail Goods"
        }
    ],
    "sg:phone":"+1 509 327 6219",
    "sg:postcode":"99207",
    "sg:province":"WA",
    "sg:tags":[
        "dealers-used",
        "car",
        "used",
        "cars-wholesale",
        "new"
    ],
    "sg:website":"http://www.alfonsomotors.com",
    "wof:name":"Alfonso Motors",
    "wof:placetype":"venue"
},
  "geometry": {"coordinates":[-117.411102,47.687797],"type":"Point"}
}