{
  "type": "Feature",
  "properties": {
    "addr:full":"First Hill Medical Bldg 515 Minor Ave Ste 140 S Seattle WA 98104",
    "addr:housenumber":"515",
    "addr:postcode":"98104",
    "addr:street":"Minor Ave Ste 140 S",
    "iso:country":"US",
    "sg:address":"First Hill Medical Bldg 515 Minor Ave Ste 140 S",
    "sg:city":"Seattle",
    "sg:classifiers":[
        {
            "category":"Health Services",
            "subcategory":"Doctor",
            "type":"Services"
        }
    ],
    "sg:phone":"+1 206 838 8345",
    "sg:postcode":"98104",
    "sg:province":"WA",
    "wof:name":"Gregory K Chan MD",
    "wof:placetype":"venue"
},
  "geometry": {"coordinates":[-122.321336,47.606596],"type":"Point"}
}