{
  "type": "Feature",
  "properties": {
    "addr:full":"7801 Rainier Ave S Seattle WA 98118",
    "addr:housenumber":"7801",
    "addr:postcode":"98118",
    "addr:street":"Rainier Ave S",
    "iso:country":"US",
    "sg:address":"7801 Rainier Ave S",
    "sg:city":"Seattle",
    "sg:classifiers":[
        {
            "category":"Building & Trades",
            "subcategory":"Landscaping Services",
            "type":"Services"
        },
        {
            "category":"Health Services",
            "subcategory":"Health Practitioner",
            "type":"Services"
        },
        {
            "category":"Social Services",
            "subcategory":"Adult Care",
            "type":"Services"
        }
    ],
    "sg:phone":"+1 206 723 6522",
    "sg:postcode":"98118",
    "sg:province":"WA",
    "sg:tags":[
        "centers-adult",
        "homes-institutional",
        "home",
        "aged",
        "day"
    ],
    "wof:name":"Luxury Adult Home Care",
    "wof:placetype":"venue"
},
  "geometry": {"coordinates":[-122.269989,47.532639],"type":"Point"}
}