{
  "type": "Feature",
  "properties": {
    "addr:full":"11204 E Sprague Ave Spokane WA 99206",
    "addr:housenumber":"11204",
    "addr:postcode":"99206",
    "addr:street":"E Sprague Ave",
    "iso:country":"US",
    "sg:address":"11204 E Sprague Ave",
    "sg:city":"Spokane",
    "sg:classifiers":[
        {
            "category":"Restaurant",
            "type":"Food & Drink"
        }
    ],
    "sg:phone":"+1 509 922 0317",
    "sg:postcode":"99206",
    "sg:province":"WA",
    "sg:tags":[
        "italian"
    ],
    "wof:name":"Spaghetti Station",
    "wof:placetype":"venue"
},
  "geometry": {"coordinates":[-117.25514099999999,47.656972],"type":"Point"}
}