{
  "type": "Feature",
  "properties": {
    "addr:full":"9412 Jackman Rd Lynden WA 98264",
    "addr:housenumber":"9412",
    "addr:postcode":"98264",
    "addr:street":"Jackman Rd",
    "iso:country":"US",
    "sg:address":"9412 Jackman Rd",
    "sg:city":"Lynden",
    "sg:classifiers":[
        {
            "category":"Professional",
            "type":"Services"
        }
    ],
    "sg:phone":"+1 360 354 2628",
    "sg:postcode":"98264",
    "sg:province":"WA",
    "wof:name":"Blankers Bertus",
    "wof:placetype":"venue"
},
  "geometry": {"coordinates":[-122.50161199999999,48.98614],"type":"Point"}
}