{
  "type": "Feature",
  "properties": {
    "addr:full":"2723 E Gordon Ave Spokane WA 99207",
    "addr:housenumber":"2723",
    "addr:postcode":"99207",
    "addr:street":"E Gordon Ave",
    "iso:country":"US",
    "sg:address":"2723 E Gordon Ave",
    "sg:city":"Spokane",
    "sg:classifiers":[
        {
            "category":"Education",
            "subcategory":"School",
            "type":"Public Place"
        }
    ],
    "sg:phone":"+1 509 483 6279",
    "sg:postcode":"99207",
    "sg:province":"WA",
    "sg:tags":[
        "catholic"
    ],
    "wof:name":"Our Lady of Rosary Academy",
    "wof:placetype":"venue"
},
  "geometry": {"coordinates":[-117.36828,47.691682],"type":"Point"}
}