{
  "type": "Feature",
  "properties": {
    "addr:full":"37225 Redwine Canyon Rd Creston WA 99117",
    "addr:postcode":"37225;99117",
    "addr:street":"Redwine Canyon Rd",
    "iso:country":"US",
    "sg:address":"37225 Redwine Canyon Rd",
    "sg:city":"Creston",
    "sg:classifiers":[
        {
            "category":"Freight",
            "type":"Transportation"
        }
    ],
    "sg:phone":"+1 509 636 2011",
    "sg:postcode":"99117",
    "sg:province":"WA",
    "sg:tags":[
        "operator",
        "local",
        "trucking"
    ],
    "wof:name":"R & K Deliveries",
    "wof:placetype":"venue"
},
  "geometry": {"coordinates":[-118.442537,47.812429],"type":"Point"}
}