{
  "type": "Feature",
  "properties": {
    "addr:full":"390 NE Midway Blvd Oak Harbor WA 98277",
    "addr:housenumber":"390",
    "addr:postcode":"98277",
    "addr:street":"Ne Midway Blvd",
    "iso:country":"US",
    "sg:address":"390 NE Midway Blvd",
    "sg:city":"Oak Harbor",
    "sg:classifiers":[
        {
            "category":"Organizations",
            "subcategory":"Religious Organization",
            "type":"Services"
        }
    ],
    "sg:phone":"+1 360 240 1377",
    "sg:postcode":"98277",
    "sg:province":"WA",
    "sg:tags":[
        "church"
    ],
    "wof:name":"Island Christian Church",
    "wof:placetype":"venue"
},
  "geometry": {"coordinates":[-122.64317699999999,48.300027],"type":"Point"}
}