{
  "type": "Feature",
  "properties": {
    "addr:full":"106 N 74th St Seattle WA 98103",
    "addr:housenumber":"106",
    "addr:postcode":"98103",
    "addr:street":"N 74Th St",
    "iso:country":"US",
    "sg:address":"106 N 74th St",
    "sg:city":"Seattle",
    "sg:classifiers":[
        {
            "category":"Retail",
            "subcategory":"Animal Services",
            "type":"Services"
        }
    ],
    "sg:phone":"+1 206 789 8138",
    "sg:postcode":"98103",
    "sg:province":"WA",
    "sg:tags":[
        "pet",
        "grooming"
    ],
    "wof:name":"Love Your Pet Products Inc",
    "wof:placetype":"venue"
},
  "geometry": {"coordinates":[-122.357816,47.682573],"type":"Point"}
}