{
  "type": "Feature",
  "properties": {
    "addr:full":"11916 NE 153rd Pl Bothell WA 98011",
    "addr:housenumber":"11916",
    "addr:postcode":"98011",
    "addr:street":"Ne 153Rd Pl",
    "iso:country":"US",
    "sg:address":"11916 NE 153rd Pl",
    "sg:city":"Bothell",
    "sg:classifiers":[
        {
            "category":"Building & Trades",
            "subcategory":"Locksmith",
            "type":"Services"
        }
    ],
    "sg:phone":"+1 425 492 1504",
    "sg:postcode":"98011",
    "sg:province":"WA",
    "sg:tags":[
        "key"
    ],
    "wof:name":"24 7 Available A Locksmith",
    "wof:placetype":"venue"
},
  "geometry": {"coordinates":[-122.18196399999999,47.739027],"type":"Point"}
}