{
  "type": "Feature",
  "properties": {
    "iso:country":"US",
    "sg:address":"328 S Stillaguamish Ave",
    "sg:city":"Arlington",
    "sg:classifiers":[
        {
            "category":"Health Services",
            "subcategory":"Hospital",
            "type":"Services"
        }
    ],
    "sg:phone":"+1 360 435 6641",
    "sg:postcode":"98223",
    "sg:province":"WA",
    "sg:tags":[
        "general"
    ],
    "wof:name":"Cascade Vly Arlngton Orthpdics",
    "wof:placetype":"venue"
},
  "geometry": {"coordinates":[-122.11761300000001,48.190503],"type":"Point"}
}