{
  "type": "Feature",
  "properties": {
    "addr:full":"24421 NE 27th Pl Redmond WA 98074",
    "addr:housenumber":"24421",
    "addr:postcode":"98074",
    "addr:street":"Ne 27Th Pl",
    "iso:country":"US",
    "sg:address":"24421 NE 27th Pl",
    "sg:city":"Redmond",
    "sg:classifiers":[
        {
            "category":"Building & Trades",
            "subcategory":"Cleaning & Sanitation",
            "type":"Services"
        }
    ],
    "sg:phone":"+1 425 836 8917",
    "sg:postcode":"98074",
    "sg:province":"WA",
    "sg:tags":[
        "janitor",
        "maintenance"
    ],
    "wof:name":"C & T Clean Sweep Janitorial",
    "wof:placetype":"venue"
},
  "geometry": {"coordinates":[-122.008374,47.633903],"type":"Point"}
}