{
  "type": "Feature",
  "properties": {
    "addr:full":"14208 21st Dr SE Bothell WA 98012",
    "addr:housenumber":"14208",
    "addr:postcode":"98012",
    "addr:street":"21St Dr Se",
    "iso:country":"US",
    "sg:address":"14208 21st Dr SE",
    "sg:city":"Bothell",
    "sg:classifiers":[
        {
            "category":"Personal",
            "subcategory":"Beauty Salon",
            "type":"Services"
        }
    ],
    "sg:phone":"+1 425 742 0202",
    "sg:postcode":"98012",
    "sg:province":"WA",
    "sg:tags":[
        "shop"
    ],
    "wof:name":"Salon Heike",
    "wof:placetype":"venue"
},
  "geometry": {"coordinates":[-122.20347599999999,47.869159],"type":"Point"}
}