{
  "type": "Feature",
  "properties": {
    "addr:full":"4430 138th Ave SE Bellevue WA 98006",
    "addr:housenumber":"4430",
    "addr:postcode":"98006",
    "addr:street":"138Th Ave Se",
    "iso:country":"US",
    "sg:address":"4430 138th Ave SE",
    "sg:city":"Bellevue",
    "sg:classifiers":[
        {
            "category":"Building & Trades",
            "subcategory":"Construction",
            "type":"Services"
        }
    ],
    "sg:phone":"+1 425 747 6791",
    "sg:postcode":"98006",
    "sg:province":"WA",
    "sg:tags":[
        "house"
    ],
    "wof:name":"Kre Investments",
    "wof:placetype":"venue"
},
  "geometry": {"coordinates":[-122.156251,47.564274],"type":"Point"}
}