{
  "type": "Feature",
  "properties": {
    "addr:full":"1401 W 1st Ave Spokane WA 99201",
    "addr:housenumber":"1401",
    "addr:postcode":"99201",
    "addr:street":"W 1St Ave",
    "iso:country":"US",
    "sg:address":"1401 W 1st Ave",
    "sg:city":"Spokane",
    "sg:classifiers":[
        {
            "category":"Restaurant",
            "type":"Food & Drink"
        }
    ],
    "sg:phone":"+1 509 363 1719",
    "sg:postcode":"99201",
    "sg:province":"WA",
    "sg:tags":[
        "eating"
    ],
    "wof:name":"Carnegies Square Bistro & Cat",
    "wof:placetype":"venue"
},
  "geometry": {"coordinates":[-117.434179,47.656477],"type":"Point"}
}