{
  "type": "Feature",
  "properties": {
    "addr:full":"2914 N Standard St Spokane WA 99207",
    "addr:housenumber":"2914",
    "addr:postcode":"99207",
    "addr:street":"N Standard St",
    "iso:country":"US",
    "sg:address":"2914 N Standard St",
    "sg:city":"Spokane",
    "sg:classifiers":[
        {
            "category":"Professional",
            "subcategory":"Secretarial Services",
            "type":"Services"
        }
    ],
    "sg:phone":"+1 509 768 8424",
    "sg:postcode":"99207",
    "sg:province":"WA",
    "sg:tags":[
        "reporting"
    ],
    "wof:name":"Accessible Solutions",
    "wof:placetype":"venue"
},
  "geometry": {"coordinates":[-117.40085500000001,47.685499],"type":"Point"}
}