{
  "type": "Feature",
  "properties": {
    "addr:full":"2148 Westlake Ave N Seattle WA 98109",
    "addr:housenumber":"2148",
    "addr:postcode":"98109",
    "addr:street":"Westlake Ave N",
    "iso:country":"US",
    "sg:address":"2148 Westlake Ave N",
    "sg:city":"Seattle",
    "sg:classifiers":[
        {
            "category":"Food & Beverages",
            "subcategory":"Meat & Fish",
            "type":"Retail Goods"
        }
    ],
    "sg:phone":"+1 206 281 7200",
    "sg:postcode":"98109",
    "sg:province":"WA",
    "sg:tags":[
        "seafood"
    ],
    "wof:name":"Da Yang Seafood Inc",
    "wof:placetype":"venue"
},
  "geometry": {"coordinates":[-122.343199,47.642038],"type":"Point"}
}