{
  "type": "Feature",
  "properties": {
    "iso:country":"US",
    "sg:address":"1942 NE Riddell Rd",
    "sg:city":"Bremerton",
    "sg:classifiers":[
        {
            "category":"Freight",
            "type":"Transportation"
        }
    ],
    "sg:phone":"+1 360 479 2880",
    "sg:postcode":"98310",
    "sg:province":"WA",
    "sg:tags":[
        "repair",
        "general"
    ],
    "wof:name":"Stor-N-Lok",
    "wof:placetype":"venue"
},
  "geometry": {"coordinates":[-122.61897500000001,47.60696],"type":"Point"}
}