{
  "type": "Feature",
  "properties": {
    "addr:full":"4200 S 176th St Seatac WA 98188",
    "addr:housenumber":"4200",
    "addr:postcode":"98188",
    "addr:street":"S 176Th St",
    "iso:country":"US",
    "sg:address":"4200 S 176th St",
    "sg:city":"Seatac",
    "sg:classifiers":[
        {
            "category":"Building & Trades",
            "subcategory":"Construction",
            "type":"Services"
        }
    ],
    "sg:phone":"+1 253 952 2740",
    "sg:postcode":"98188",
    "sg:province":"WA",
    "sg:tags":[
        "general",
        "contractor"
    ],
    "wof:name":"E & E Home Renevation & Svc",
    "wof:placetype":"venue"
},
  "geometry": {"coordinates":[-122.28179299999999,47.445269],"type":"Point"}
}