{
  "type": "Feature",
  "properties": {
    "addr:full":"1501 4th Ave Ste 2000 Seattle WA 98101",
    "addr:housenumber":"1501",
    "addr:postcode":"98101",
    "addr:street":"4Th Ave Ste 2000",
    "iso:country":"US",
    "sg:address":"1501 4th Ave Ste 2000",
    "sg:city":"Seattle",
    "sg:classifiers":[
        {
            "category":"Insurance",
            "subcategory":"Hazard Insurance",
            "type":"Services"
        }
    ],
    "sg:phone":"+1 206 623 7035",
    "sg:postcode":"98101",
    "sg:province":"WA",
    "sg:website":"http://www.sig-ins.com",
    "wof:name":"Sprague Israel Giles, Inc.",
    "wof:placetype":"venue"
},
  "geometry": {"coordinates":[-122.33681900000001,47.610246],"type":"Point"}
}