{
  "type": "Feature",
  "properties": {
    "addr:full":"19228 Duvall Monroe Rd NE Duvall WA 98019",
    "addr:housenumber":"19228",
    "addr:postcode":"98019",
    "addr:street":"Duvall Monroe Rd Ne",
    "iso:country":"US",
    "sg:address":"19228 Duvall Monroe Rd NE",
    "sg:city":"Duvall",
    "sg:classifiers":[
        {
            "category":"Recreation",
            "type":"Entertainment"
        }
    ],
    "sg:phone":"+1 425 881 7398",
    "sg:postcode":"98019",
    "sg:province":"WA",
    "wof:name":"Cherry Creek Equestrian Center",
    "wof:placetype":"venue"
},
  "geometry": {"coordinates":[-121.95738,47.766562],"type":"Point"}
}