{
  "type": "Feature",
  "properties": {
    "addr:full":"10004 Aurora Ave N Ste 10 Seattle WA 98133",
    "addr:housenumber":"10004",
    "addr:postcode":"98133",
    "addr:street":"Aurora Ave N Ste 10",
    "iso:country":"US",
    "sg:address":"10004 Aurora Ave N Ste 10",
    "sg:city":"Seattle",
    "sg:classifiers":[
        {
            "category":"Real Estate",
            "subcategory":"Real Estate Agent",
            "type":"Services"
        }
    ],
    "sg:phone":"+1 206 605 4167",
    "sg:postcode":"98133",
    "sg:province":"WA",
    "wof:name":"Debi Fortin - Windermere Real Estate",
    "wof:placetype":"venue"
},
  "geometry": {"coordinates":[-122.344058,47.702993],"type":"Point"}
}