{
  "type": "Feature",
  "properties": {
    "addr:full":"2727 Hollycroft St Gig Harbor WA 98335",
    "addr:housenumber":"2727",
    "addr:postcode":"98335",
    "addr:street":"Hollycroft St",
    "iso:country":"US",
    "sg:address":"2727 Hollycroft St",
    "sg:city":"Gig Harbor",
    "sg:classifiers":[
        {
            "category":"Real Estate",
            "subcategory":"Real Estate Agent",
            "type":"Services"
        }
    ],
    "sg:phone":"+1 253 858 1342",
    "sg:postcode":"98335",
    "sg:province":"WA",
    "wof:name":"A Team",
    "wof:placetype":"venue"
},
  "geometry": {"coordinates":[-122.574315,47.30901],"type":"Point"}
}