{
  "type": "Feature",
  "properties": {
    "addr:full":"5008 71st Dr NE Marysville WA 98270",
    "addr:housenumber":"5008",
    "addr:postcode":"98270",
    "addr:street":"71St Dr Ne",
    "iso:country":"US",
    "sg:address":"5008 71st Dr NE",
    "sg:city":"Marysville",
    "sg:classifiers":[
        {
            "category":"Building & Trades",
            "subcategory":"Cleaning & Sanitation",
            "type":"Services"
        }
    ],
    "sg:phone":"+1 425 397 7161",
    "sg:postcode":"98270",
    "sg:province":"WA",
    "sg:tags":[
        "maintenance"
    ],
    "wof:name":"On Spot Housekeeping",
    "wof:placetype":"venue"
},
  "geometry": {"coordinates":[-122.13502699999999,48.040165],"type":"Point"}
}