{
  "type": "Feature",
  "properties": {
    "addr:full":"18404 36th Ave W Lynnwood WA 98037",
    "addr:housenumber":"18404",
    "addr:postcode":"98037",
    "addr:street":"36Th Ave W",
    "iso:country":"US",
    "sg:address":"18404 36th Ave W",
    "sg:city":"Lynnwood",
    "sg:classifiers":[
        {
            "category":"Real Estate",
            "subcategory":"Real Estate Agent",
            "type":"Services"
        }
    ],
    "sg:phone":"+1 425 771 0720",
    "sg:postcode":"98037",
    "sg:province":"WA",
    "wof:name":"Alderwood Highland Townhomes",
    "wof:placetype":"venue"
},
  "geometry": {"coordinates":[-122.281837,47.831349],"type":"Point"}
}