{
  "type": "Feature",
  "properties": {
    "iso:country":"US",
    "sg:address":"3015 112th Ave NE",
    "sg:city":"Bellevue",
    "sg:classifiers":[
        {
            "category":"Manufacturing",
            "subcategory":"Furniture",
            "type":"Manufacturing & Wholesale Goods"
        }
    ],
    "sg:phone":"+1 425 576 2137",
    "sg:postcode":"98004",
    "sg:province":"WA",
    "sg:tags":[
        "mfg"
    ],
    "wof:name":"Pwi Technologies",
    "wof:placetype":"venue"
},
  "geometry": {"coordinates":[-122.193128,47.636641],"type":"Point"}
}