{
  "type": "Feature",
  "properties": {
    "addr:full":"7402 E 8th Ave Spokane WA 99212",
    "addr:housenumber":"7402",
    "addr:postcode":"99212",
    "addr:street":"E 8Th Ave",
    "iso:country":"US",
    "sg:address":"7402 E 8th Ave",
    "sg:city":"Spokane",
    "sg:classifiers":[
        {
            "category":"Food & Beverages",
            "subcategory":"Groceries & Convenience Stores",
            "type":"Retail Goods"
        }
    ],
    "sg:phone":"+1 509 482 3357",
    "sg:postcode":"99212",
    "sg:province":"WA",
    "wof:name":"Safeway",
    "wof:placetype":"venue"
},
  "geometry": {"coordinates":[-117.304328,47.649519],"type":"Point"}
}