{
  "type": "Feature",
  "properties": {
    "addr:full":"1115 NW 51st St Seattle WA 98107",
    "addr:housenumber":"1115",
    "addr:postcode":"98107",
    "addr:street":"Nw 51St St",
    "iso:country":"US",
    "sg:address":"1115 NW 51st St",
    "sg:city":"Seattle",
    "sg:classifiers":[
        {
            "category":"Building & Trades",
            "subcategory":"Construction",
            "type":"Services"
        }
    ],
    "sg:phone":"+1 206 522 0101",
    "sg:postcode":"98107",
    "sg:province":"WA",
    "sg:tags":[
        "system",
        "contractor",
        "air conditioning"
    ],
    "wof:name":"Acme Plumbing & Heating Inc",
    "wof:placetype":"venue"
},
  "geometry": {"coordinates":[-122.371162,47.66572],"type":"Point"}
}