{
  "type": "Feature",
  "properties": {
    "addr:full":"13555 SE 36th St Bellevue WA 98006",
    "addr:housenumber":"13555",
    "addr:postcode":"98006",
    "addr:street":"Se 36Th St",
    "iso:country":"US",
    "sg:address":"13555 SE 36th St",
    "sg:city":"Bellevue",
    "sg:classifiers":[
        {
            "category":"Professional",
            "subcategory":"Accounting & Tax Preparation",
            "type":"Services"
        }
    ],
    "sg:phone":"+1 425 562 6899",
    "sg:postcode":"98006",
    "sg:province":"WA",
    "sg:tags":[
        "accountant"
    ],
    "wof:name":"Shelton Donald E CPA",
    "wof:placetype":"venue"
},
  "geometry": {"coordinates":[-122.158997,47.579399],"type":"Point"}
}