{
  "type": "Feature",
  "properties": {
    "addr:full":"1200 Cooper Point Rd SW Olympia WA 98502",
    "addr:housenumber":"1200",
    "addr:postcode":"98502",
    "addr:street":"Cooper Point Rd Sw",
    "iso:country":"US",
    "sg:address":"1200 Cooper Point Rd SW",
    "sg:city":"Olympia",
    "sg:classifiers":[
        {
            "category":"Restaurant",
            "type":"Food & Drink"
        }
    ],
    "sg:menulink":"http://www.allmenus.com/wa/olympia/49788-el-sarape/menu/",
    "sg:phone":"+1 360 352 1201",
    "sg:postcode":"98502",
    "sg:province":"WA",
    "sg:tags":[
        "mexican"
    ],
    "wof:name":"El Sarape",
    "wof:placetype":"venue"
},
  "geometry": {"coordinates":[-122.94119600000001,47.055942],"type":"Point"}
}