{
  "type": "Feature",
  "properties": {
    "addr:full":"1802 36th Ave. Seattle WA 98122",
    "addr:housenumber":"1802",
    "addr:postcode":"98122",
    "addr:street":"36Th Ave.",
    "iso:country":"US",
    "sg:address":"1802 36th Ave.",
    "sg:city":"Seattle",
    "sg:classifiers":[
        {
            "category":"Education",
            "subcategory":"School",
            "type":"Public Place"
        }
    ],
    "sg:phone":"+1 206 860 5064",
    "sg:postcode":"98122",
    "sg:province":"WA",
    "sg:tags":[
        "elementary"
    ],
    "wof:name":"Epiphany School",
    "wof:placetype":"venue"
},
  "geometry": {"coordinates":[-122.287239,47.617768],"type":"Point"}
}