{
  "type": "Feature",
  "properties": {
    "iso:country":"US",
    "sg:address":"10588 NE Byron Dr",
    "sg:city":"Bainbridge Island",
    "sg:classifiers":[
        {
            "category":"Personal",
            "type":"Services"
        }
    ],
    "sg:phone":"+1 206 842 1774",
    "sg:postcode":"98110",
    "sg:province":"WA",
    "sg:tags":[
        "information"
    ],
    "wof:name":"People Centered- Dev Forum",
    "wof:placetype":"venue"
},
  "geometry": {"coordinates":[-122.506953,47.637548],"type":"Point"}
}