{
  "type": "Feature",
  "properties": {
    "addr:full":"140 S 140th Street Burien WA 98168",
    "addr:housenumber":"140",
    "addr:postcode":"98168",
    "addr:street":"S 140Th Street",
    "iso:country":"US",
    "sg:address":"140 S 140th Street",
    "sg:city":"Burien",
    "sg:classifiers":[
        {
            "category":"Building & Trades",
            "subcategory":"Locksmith",
            "type":"Services"
        }
    ],
    "sg:phone":"+1 206 774 2590",
    "sg:postcode":"98168",
    "sg:province":"WA",
    "sg:tags":[
        "key"
    ],
    "wof:name":"1 Hour All Seattle Emergency Locksmith",
    "wof:placetype":"venue"
},
  "geometry": {"coordinates":[-122.3338,47.477821],"type":"Point"}
}