{
  "type": "Feature",
  "properties": {
    "addr:full":"6002 S Wilgus Rd Prosser WA 99350",
    "addr:housenumber":"6002",
    "addr:postcode":"99350",
    "addr:street":"S Wilgus Rd",
    "iso:country":"US",
    "sg:address":"6002 S Wilgus Rd",
    "sg:city":"Prosser",
    "sg:classifiers":[
        {
            "category":"Shopping",
            "subcategory":"Florist",
            "type":"Retail Goods"
        },
        {
            "category":"Shopping",
            "subcategory":"Gifts & Souvenirs",
            "type":"Retail Goods"
        }
    ],
    "sg:phone":"+1 509 786 4440",
    "sg:postcode":"99350",
    "sg:province":"WA",
    "wof:name":"Angela's Floral's & Gifts",
    "wof:placetype":"venue"
},
  "geometry": {"coordinates":[-119.831414,46.21447],"type":"Point"}
}