{
  "type": "Feature",
  "properties": {
    "addr:full":"4418 53rd Ave SW Seattle WA 98116",
    "addr:housenumber":"4418",
    "addr:postcode":"98116",
    "addr:street":"53Rd Ave Sw",
    "iso:country":"US",
    "sg:address":"4418 53rd Ave SW",
    "sg:city":"Seattle",
    "sg:classifiers":[
        {
            "category":"Building & Trades",
            "subcategory":"Landscaping Services",
            "type":"Services"
        }
    ],
    "sg:phone":"+1 206 933 0788",
    "sg:postcode":"98116",
    "sg:province":"WA",
    "wof:name":"Vujatovich Gardeners",
    "wof:placetype":"venue"
},
  "geometry": {"coordinates":[-122.39913300000001,47.560592],"type":"Point"}
}