{
  "type": "Feature",
  "properties": {
    "addr:full":"9256 45th Ave SW Seattle WA 98136",
    "addr:housenumber":"9256",
    "addr:postcode":"98136",
    "addr:street":"45Th Ave Sw",
    "iso:country":"US",
    "sg:address":"9256 45th Ave SW",
    "sg:city":"Seattle",
    "sg:classifiers":[
        {
            "category":"Personal",
            "subcategory":"Skin Care",
            "type":"Services"
        }
    ],
    "sg:phone":"+1 206 935 4833",
    "sg:postcode":"98136",
    "sg:province":"WA",
    "sg:website":"www.inspiredhealthandbeauty.com",
    "wof:name":"Inspired Health and Beauty",
    "wof:placetype":"venue"
},
  "geometry": {"coordinates":[-122.39000799999999,47.52071],"type":"Point"}
}