{
  "type": "Feature",
  "properties": {
    "addr:full":"19231 S Choctaw Ln Cheney WA 99004",
    "addr:housenumber":"19231",
    "addr:postcode":"99004",
    "addr:street":"S Choctaw Ln",
    "iso:country":"US",
    "sg:address":"19231 S Choctaw Ln",
    "sg:city":"Cheney",
    "sg:classifiers":[
        {
            "category":"Shopping",
            "subcategory":"Hobbies, Toys, & Games",
            "type":"Retail Goods"
        },
        {
            "category":"Shopping",
            "subcategory":"Crafts & Fabrics",
            "type":"Retail Goods"
        }
    ],
    "sg:phone":"+1 509 235 2280",
    "sg:postcode":"99004",
    "sg:province":"WA",
    "sg:tags":[
        "shop",
        "hobby",
        "model",
        "supplies-wholesale",
        "manufacturer"
    ],
    "wof:name":"Pine Country Crafts",
    "wof:placetype":"venue"
},
  "geometry": {"coordinates":[-117.45473699999999,47.479958],"type":"Point"}
}