{
  "type": "Feature",
  "properties": {
    "addr:full":"23915 127th Pl SE Kent WA 98031",
    "addr:housenumber":"23915",
    "addr:postcode":"98031",
    "addr:street":"127Th Pl Se",
    "iso:country":"US",
    "sg:address":"23915 127th Pl SE",
    "sg:city":"Kent",
    "sg:classifiers":[
        {
            "category":"Shopping",
            "subcategory":"Gifts & Souvenirs",
            "type":"Retail Goods"
        }
    ],
    "sg:phone":"+1 253 630 8705",
    "sg:postcode":"98031",
    "sg:province":"WA",
    "wof:name":"Cheryls Home Decor & Gifts",
    "wof:placetype":"venue"
},
  "geometry": {"coordinates":[-122.171329,47.387949],"type":"Point"}
}