{
  "type": "Feature",
  "properties": {
    "addr:full":"7918 Green Lake Dr N Seattle WA 98103",
    "addr:housenumber":"7918",
    "addr:postcode":"98103",
    "addr:street":"Green Lake Dr N",
    "iso:country":"US",
    "sg:address":"7918 Green Lake Dr N",
    "sg:city":"Seattle",
    "sg:classifiers":[
        {
            "category":"Insurance",
            "subcategory":"Hazard Insurance",
            "type":"Services"
        }
    ],
    "sg:phone":"+1 206 985 2528",
    "sg:postcode":"98103",
    "sg:province":"WA",
    "sg:website":"statefarm.insurance-seattle.net",
    "wof:name":"Thury Foster - State Farm Insurance",
    "wof:placetype":"venue"
},
  "geometry": {"coordinates":[-122.339586,47.686505],"type":"Point"}
}