{
  "type": "Feature",
  "properties": {
    "iso:country":"US",
    "sg:address":"833 Adams St",
    "sg:city":"Port Townsend",
    "sg:classifiers":[
        {
            "category":"Home & Garden",
            "subcategory":"Carpets & Floor Coverings",
            "type":"Retail Goods"
        }
    ],
    "sg:phone":"+1 360 385 2987",
    "sg:postcode":"98368",
    "sg:province":"WA",
    "wof:name":"Ed S Carpeting & Upholstery",
    "wof:placetype":"venue"
},
  "geometry": {"coordinates":[-122.759874,48.11934],"type":"Point"}
}