{
  "type": "Feature",
  "properties": {
    "addr:full":"835 S 234th Pl Seattle WA 98198",
    "addr:housenumber":"835",
    "addr:postcode":"98198",
    "addr:street":"S 234Th Pl",
    "iso:country":"US",
    "sg:address":"835 S 234th Pl",
    "sg:city":"Seattle",
    "sg:classifiers":[
        {
            "category":"Professional",
            "subcategory":"Business Services",
            "type":"Services"
        }
    ],
    "sg:phone":"+1 206 878 7776",
    "sg:postcode":"98198",
    "sg:province":"WA",
    "wof:name":"Rgm Partnership",
    "wof:placetype":"venue"
},
  "geometry": {"coordinates":[-122.321394,47.391408],"type":"Point"}
}