{
  "type": "Feature",
  "properties": {
    "addr:full":"606 N Wilbur Ave Walla Walla WA 99362",
    "addr:housenumber":"606",
    "addr:postcode":"99362",
    "addr:street":"N Wilbur Ave",
    "iso:country":"US",
    "sg:address":"606 N Wilbur Ave",
    "sg:city":"Walla Walla",
    "sg:classifiers":[
        {
            "category":"Autos & Motor Vehicles",
            "subcategory":"Automobile Sales",
            "type":"Retail Goods"
        }
    ],
    "sg:phone":"+1 509 525 1920",
    "sg:postcode":"99362",
    "sg:province":"WA",
    "sg:tags":[
        "new",
        "used"
    ],
    "wof:name":"Lincoln-Mercury of Walla Walla",
    "wof:placetype":"venue"
},
  "geometry": {"coordinates":[-118.30451100000001,46.079494],"type":"Point"}
}