{
  "type": "Feature",
  "properties": {
    "addr:full":"1 W 2nd Ave Spokane WA 99201",
    "addr:housenumber":"1",
    "addr:postcode":"99201",
    "addr:street":"W 2Nd Ave",
    "iso:country":"US",
    "sg:address":"1 W 2nd Ave",
    "sg:city":"Spokane",
    "sg:classifiers":[
        {
            "category":"Real Estate",
            "subcategory":"Real Estate Operator",
            "type":"Services"
        }
    ],
    "sg:phone":"+1 509 838 5636",
    "sg:postcode":"99201",
    "sg:province":"WA",
    "sg:tags":[
        "apartment"
    ],
    "wof:name":"New Washington Apartments",
    "wof:placetype":"venue"
},
  "geometry": {"coordinates":[-117.412035,47.654554],"type":"Point"}
}