{
  "type": "Feature",
  "properties": {
    "addr:full":"1141 Commerce Ave Longview WA 98632",
    "addr:housenumber":"1141",
    "addr:postcode":"98632",
    "addr:street":"Commerce Ave",
    "iso:country":"US",
    "sg:address":"1141 Commerce Ave",
    "sg:city":"Longview",
    "sg:classifiers":[
        {
            "category":"Manufacturing",
            "subcategory":"Motor Vehicles & Parts",
            "type":"Manufacturing & Wholesale Goods"
        }
    ],
    "sg:phone":"+1 360 577 1534",
    "sg:postcode":"98632",
    "sg:province":"WA",
    "sg:tags":[
        "on",
        "fabric",
        "mfg",
        "screen",
        "textile",
        "printing"
    ],
    "wof:name":"Screen Print Northwest Inc",
    "wof:placetype":"venue"
},
  "geometry": {"coordinates":[-122.935349,46.134747],"type":"Point"}
}