{
  "type": "Feature",
  "properties": {
    "addr:full":"3021 36th St Everett WA 98201",
    "addr:housenumber":"3021",
    "addr:postcode":"98201",
    "addr:street":"36Th St",
    "iso:country":"US",
    "sg:address":"3021 36th St",
    "sg:city":"Everett",
    "sg:classifiers":[
        {
            "category":"Building & Trades",
            "subcategory":"Construction",
            "type":"Services"
        }
    ],
    "sg:phone":"+1 425 252 7014",
    "sg:postcode":"98201",
    "sg:province":"WA",
    "sg:tags":[
        "insulation",
        "heat",
        "contractor"
    ],
    "wof:name":"Quality Plus Insulation Inc",
    "wof:placetype":"venue"
},
  "geometry": {"coordinates":[-122.190617,47.970159],"type":"Point"}
}