{
  "type": "Feature",
  "properties": {
    "addr:full":"4020 Leary Way NW Seattle WA 98107",
    "addr:housenumber":"4020",
    "addr:postcode":"98107",
    "addr:street":"Leary Way Nw",
    "iso:country":"US",
    "sg:address":"4020 Leary Way NW",
    "sg:city":"Seattle",
    "sg:classifiers":[
        {
            "category":"Banks & Credit Unions",
            "subcategory":"Financial Services",
            "type":"Services"
        }
    ],
    "sg:phone":"+1 206 784 7892",
    "sg:postcode":"98107",
    "sg:province":"WA",
    "sg:tags":[
        "trust",
        "investment",
        "real estate"
    ],
    "wof:name":"Somerset Group",
    "wof:placetype":"venue"
},
  "geometry": {"coordinates":[-122.36259,47.656797],"type":"Point"}
}