{
  "type": "Feature",
  "properties": {
    "addr:full":"1404 S Cloverdale Rd Kalama WA 98625",
    "addr:housenumber":"1404",
    "addr:postcode":"98625",
    "addr:street":"S Cloverdale Rd",
    "iso:country":"US",
    "sg:address":"1404 S Cloverdale Rd",
    "sg:city":"Kalama",
    "sg:classifiers":[
        {
            "category":"Manufacturing",
            "subcategory":"Toys & Sporting Goods",
            "type":"Manufacturing & Wholesale Goods"
        }
    ],
    "sg:phone":"+1 360 673 2542",
    "sg:postcode":"98625",
    "sg:province":"WA",
    "sg:tags":[
        "mfg"
    ],
    "wof:name":"Kathy Tony Woodward",
    "wof:placetype":"venue"
},
  "geometry": {"coordinates":[-122.81363399999999,45.980063],"type":"Point"}
}