{
  "type": "Feature",
  "properties": {
    "addr:full":"2404 NW 112th St Vancouver WA 98685",
    "addr:housenumber":"2404",
    "addr:postcode":"98685",
    "addr:street":"Nw 112Th St",
    "iso:country":"US",
    "sg:address":"2404 NW 112th St",
    "sg:city":"Vancouver",
    "sg:classifiers":[
        {
            "category":"Retail",
            "subcategory":"Repair Shop",
            "type":"Services"
        }
    ],
    "sg:phone":"+1 360 600 1998",
    "sg:postcode":"98685",
    "sg:province":"WA",
    "sg:tags":[
        "appliance"
    ],
    "wof:name":"After Hours Home Appliance Rpr",
    "wof:placetype":"venue"
},
  "geometry": {"coordinates":[-122.69593399999999,45.702583],"type":"Point"}
}