{
  "type": "Feature",
  "properties": {
    "iso:country":"US",
    "sg:address":"212 McKenzie Ave",
    "sg:city":"Bellingham",
    "sg:classifiers":[
        {
            "category":"Manufacturing",
            "subcategory":"Tools & Machinery",
            "type":"Manufacturing & Wholesale Goods"
        }
    ],
    "sg:phone":"+1 360 738 4986",
    "sg:postcode":"98225",
    "sg:province":"WA",
    "sg:tags":[
        "metal",
        "fabrication"
    ],
    "wof:name":"Iota Metalworking Services",
    "wof:placetype":"venue"
},
  "geometry": {"coordinates":[-122.51212700000001,48.719252],"type":"Point"}
}