{
  "type": "Feature",
  "properties": {
    "addr:full":"6319 E Mill Plain Blvd Vancouver WA 98661",
    "addr:housenumber":"6319",
    "addr:postcode":"98661",
    "addr:street":"E Mill Plain Blvd",
    "iso:country":"US",
    "sg:address":"6319 E Mill Plain Blvd",
    "sg:city":"Vancouver",
    "sg:classifiers":[
        {
            "category":"Retail",
            "subcategory":"Laundry & Dry Cleaning",
            "type":"Services"
        }
    ],
    "sg:phone":"+1 360 695 8761",
    "sg:postcode":"98661",
    "sg:province":"WA",
    "sg:website":"www.customcarevalet.com",
    "wof:name":"Custom Care",
    "wof:placetype":"venue"
},
  "geometry": {"coordinates":[-122.60700199999999,45.6278],"type":"Point"}
}