{
  "type": "Feature",
  "properties": {
    "iso:country":"US",
    "sg:address":"3929 Pacific Ave SE",
    "sg:city":"Olympia",
    "sg:classifiers":[
        {
            "category":"Organizations",
            "subcategory":"Community Association",
            "type":"Services"
        }
    ],
    "sg:phone":"+1 360 491 1759",
    "sg:postcode":"98503",
    "sg:province":"WA",
    "sg:tags":[
        "fraternal"
    ],
    "wof:name":"Loyal Order Of Moose",
    "wof:placetype":"venue"
},
  "geometry": {"coordinates":[-122.83407800000001,47.039277],"type":"Point"}
}