{
  "type": "Feature",
  "properties": {
    "addr:full":"24402 N Gap Rd Prosser WA 99350",
    "addr:housenumber":"24402",
    "addr:postcode":"99350",
    "addr:street":"N Gap Rd",
    "iso:country":"US",
    "sg:address":"24402 N Gap Rd",
    "sg:city":"Prosser",
    "sg:classifiers":[
        {
            "category":"Building & Trades",
            "subcategory":"Construction",
            "type":"Services"
        }
    ],
    "sg:phone":"+1 509 788 1698",
    "sg:postcode":"99350",
    "sg:province":"WA",
    "sg:tags":[
        "house"
    ],
    "wof:name":"Easter Construction Co",
    "wof:placetype":"venue"
},
  "geometry": {"coordinates":[-119.78943099999999,46.254174],"type":"Point"}
}