{
  "type": "Feature",
  "properties": {
    "addr:full":"8084 160th Ave NE Redmond WA 98052",
    "addr:housenumber":"8084",
    "addr:postcode":"98052",
    "addr:street":"160Th Ave Ne",
    "iso:country":"US",
    "sg:address":"8084 160th Ave NE",
    "sg:city":"Redmond",
    "sg:classifiers":[
        {
            "category":"Professional",
            "type":"Services"
        }
    ],
    "sg:phone":"+1 425 883 0209",
    "sg:postcode":"98052",
    "sg:province":"WA",
    "wof:name":"Sang B MO",
    "wof:placetype":"venue"
},
  "geometry": {"coordinates":[-122.127416,47.675835],"type":"Point"}
}