{
  "type": "Feature",
  "properties": {
    "addr:full":"904 W Riverside Ave Spokane WA 99201",
    "addr:housenumber":"904",
    "addr:postcode":"99201",
    "addr:street":"W Riverside Ave",
    "iso:country":"US",
    "sg:address":"904 W Riverside Ave",
    "sg:city":"Spokane",
    "sg:classifiers":[
        {
            "category":"Government",
            "subcategory":"Office",
            "type":"Public Place"
        }
    ],
    "sg:phone":"+1 509 368 3101",
    "sg:postcode":"99201",
    "sg:province":"WA",
    "sg:tags":[
        "survey",
        "geological"
    ],
    "wof:name":"Cost Center 9935-Northwest",
    "wof:placetype":"venue"
},
  "geometry": {"coordinates":[-117.426467,47.658266],"type":"Point"}
}