{
  "type": "Feature",
  "properties": {
    "iso:country":"US",
    "sg:address":"821 E Sharp Ave",
    "sg:city":"Spokane",
    "sg:classifiers":[
        {
            "category":"Restaurant",
            "type":"Food & Drink"
        }
    ],
    "sg:phone":"+1 509 487 1630",
    "sg:postcode":"99202",
    "sg:province":"WA",
    "sg:tags":[
        "eating"
    ],
    "wof:name":"Duncan & Duncan Inc",
    "wof:placetype":"venue"
},
  "geometry": {"coordinates":[-117.39687000000001,47.669601],"type":"Point"}
}