{
  "type": "Feature",
  "properties": {
    "addr:full":"104 W Main Ave Puyallup WA 98371",
    "addr:housenumber":"104",
    "addr:postcode":"98371",
    "addr:street":"W Main Ave",
    "iso:country":"US",
    "sg:address":"104 W Main Ave",
    "sg:city":"Puyallup",
    "sg:classifiers":[
        {
            "category":"Wholesale",
            "subcategory":"Machinery & Supplies",
            "type":"Manufacturing & Wholesale Goods"
        }
    ],
    "sg:phone":"+1 253 840 1750",
    "sg:postcode":"98371",
    "sg:province":"WA",
    "sg:tags":[
        "equipment",
        "plastic"
    ],
    "sg:website":"www.shawtechsales.com",
    "wof:name":"Shaw Tech Sales Inc",
    "wof:placetype":"venue"
},
  "geometry": {"coordinates":[-122.295058,47.191721],"type":"Point"}
}