{
  "type": "Feature",
  "properties": {
    "addr:full":"1931 2nd Ave Seattle WA 98101",
    "addr:housenumber":"1931",
    "addr:postcode":"98101",
    "addr:street":"2Nd Ave",
    "iso:country":"US",
    "sg:address":"1931 2nd Ave",
    "sg:city":"Seattle",
    "sg:classifiers":[
        {
            "category":"Professional",
            "subcategory":"Business Services",
            "type":"Services"
        }
    ],
    "sg:phone":"+1 206 448 5550",
    "sg:postcode":"98101",
    "sg:province":"WA",
    "wof:name":"Jmk Industrial Design",
    "wof:placetype":"venue"
},
  "geometry": {"coordinates":[-122.34153499999999,47.611439],"type":"Point"}
}