{
  "type": "Feature",
  "properties": {
    "addr:full":"3849 Klahanie Dr SE Issaquah WA 98029",
    "addr:housenumber":"3849",
    "addr:postcode":"98029",
    "addr:street":"Klahanie Dr Se",
    "iso:country":"US",
    "sg:address":"3849 Klahanie Dr SE",
    "sg:city":"Issaquah",
    "sg:classifiers":[
        {
            "category":"Retail",
            "subcategory":"Auto Repair",
            "type":"Services"
        }
    ],
    "sg:phone":"+1 425 747 2776",
    "sg:postcode":"98029",
    "sg:province":"WA",
    "sg:tags":[
        "glass",
        "replacement"
    ],
    "wof:name":"Sterling Auto Glass",
    "wof:placetype":"venue"
},
  "geometry": {"coordinates":[-121.99902400000001,47.575104],"type":"Point"}
}