{
  "type": "Feature",
  "properties": {
    "addr:full":"9803 44th Ave NW Gig Harbor WA 98332",
    "addr:housenumber":"9803",
    "addr:postcode":"98332",
    "addr:street":"44Th Ave Nw",
    "iso:country":"US",
    "sg:address":"9803 44th Ave NW",
    "sg:city":"Gig Harbor",
    "sg:classifiers":[
        {
            "category":"Professional",
            "type":"Services"
        }
    ],
    "sg:phone":"+1 253 851 0216",
    "sg:postcode":"98332",
    "sg:province":"WA",
    "wof:name":"Burnham Inc",
    "wof:placetype":"venue"
},
  "geometry": {"coordinates":[-122.597776,47.347292],"type":"Point"}
}