{
  "type": "Feature",
  "properties": {
    "addr:full":"401 Lovell Ave SW Bainbridge Island WA 98110",
    "addr:housenumber":"401",
    "addr:postcode":"98110",
    "addr:street":"Lovell Ave Sw Bainbridge",
    "iso:country":"US",
    "sg:address":"401 Lovell Ave SW",
    "sg:city":"Bainbridge Island",
    "sg:classifiers":[
        {
            "category":"Building & Trades",
            "subcategory":"Construction",
            "type":"Services"
        }
    ],
    "sg:phone":"+1 206 842 9991",
    "sg:postcode":"98110",
    "sg:province":"WA",
    "sg:tags":[
        "residential",
        "nonresidential"
    ],
    "wof:name":"Cassella Construction LLC",
    "wof:placetype":"venue"
},
  "geometry": {"coordinates":[-122.52615400000001,47.62256],"type":"Point"}
}