{
  "type": "Feature",
  "properties": {
    "addr:full":"903 Pacific Ave Tacoma WA 98402",
    "addr:housenumber":"903",
    "addr:postcode":"98402",
    "addr:street":"Pacific Ave",
    "iso:country":"US",
    "sg:address":"903 Pacific Ave",
    "sg:city":"Tacoma",
    "sg:classifiers":[
        {
            "category":"Personal",
            "subcategory":"Barber",
            "type":"Services"
        }
    ],
    "sg:phone":"+1 253 272 2663",
    "sg:postcode":"98402",
    "sg:province":"WA",
    "wof:name":"Thee Barber Shop",
    "wof:placetype":"venue"
},
  "geometry": {"coordinates":[-122.438794,47.254437],"type":"Point"}
}