{
  "type": "Feature",
  "properties": {
    "addr:full":"1001 E Craig Ave Ellensburg WA 98926",
    "addr:housenumber":"1001",
    "addr:postcode":"98926",
    "addr:street":"E Craig Ave",
    "iso:country":"US",
    "sg:address":"1001 E Craig Ave",
    "sg:city":"Ellensburg",
    "sg:classifiers":[
        {
            "category":"Social Services",
            "type":"Services"
        },
        {
            "category":"Professional",
            "subcategory":"Employment Agencies",
            "type":"Services"
        },
        {
            "category":"Organizations",
            "subcategory":"Community Association",
            "type":"Services"
        },
        {
            "category":"Organizations",
            "subcategory":"Membership Organization",
            "type":"Services"
        }
    ],
    "sg:phone":"+1 509 925 9488",
    "sg:postcode":"98926",
    "sg:province":"WA",
    "sg:tags":[
        "workers'",
        "military",
        "veteran",
        "placement",
        "volunteer"
    ],
    "sg:website":"http://www.legion.org",
    "wof:name":"American Legion",
    "wof:placetype":"venue"
},
  "geometry": {"coordinates":[-120.533722,46.995811],"type":"Point"}
}