{
  "type": "Feature",
  "properties": {
    "addr:full":"6271 Lancaster Rd Saint John WA 99171",
    "addr:housenumber":"6271",
    "addr:postcode":"wa 99171",
    "addr:street":"Lancaster Rd",
    "iso:country":"US",
    "sg:address":"6271 Lancaster Rd",
    "sg:city":"Saint John",
    "sg:classifiers":[
        {
            "category":"Farming",
            "subcategory":"Farm",
            "type":"Manufacturing & Wholesale Goods"
        }
    ],
    "sg:phone":"+1 509 648 3473",
    "sg:postcode":"99171",
    "sg:province":"WA",
    "sg:tags":[
        "crop",
        "general"
    ],
    "wof:name":"Lisa & Tim Blumenshein",
    "wof:placetype":"venue"
},
  "geometry": {"coordinates":[-117.651399,47.053803],"type":"Point"}
}