{
  "type": "Feature",
  "properties": {
    "addr:full":"12714 Valley Ave E Sumner WA 98390",
    "addr:housenumber":"12714",
    "addr:postcode":"98390",
    "addr:street":"Valley Ave E",
    "iso:country":"US",
    "sg:address":"12714 Valley Ave E",
    "sg:city":"Sumner",
    "sg:classifiers":[
        {
            "category":"Manufacturing",
            "subcategory":"Metals",
            "type":"Manufacturing & Wholesale Goods"
        }
    ],
    "sg:phone":"+1 253 891 0389",
    "sg:postcode":"98390",
    "sg:province":"WA",
    "sg:tags":[
        "coating",
        "powder"
    ],
    "sg:website":"www.gopowder.com",
    "wof:name":"Advanced Powder Coating",
    "wof:placetype":"venue"
},
  "geometry": {"coordinates":[-122.260375,47.203953],"type":"Point"}
}