{
  "type": "Feature",
  "properties": {
    "addr:full":"2425 E Springfield Ave Spokane WA 99202",
    "addr:housenumber":"2425",
    "addr:postcode":"99202",
    "addr:street":"E Springfield Ave",
    "iso:country":"US",
    "sg:address":"2425 E Springfield Ave",
    "sg:city":"Spokane",
    "sg:classifiers":[
        {
            "category":"Shopping",
            "subcategory":"Books",
            "type":"Retail Goods"
        }
    ],
    "sg:phone":"+1 509 624 7522",
    "sg:postcode":"99202",
    "sg:province":"WA",
    "wof:name":"Best Buy Adult Entertainment",
    "wof:placetype":"venue"
},
  "geometry": {"coordinates":[-117.374044,47.663331],"type":"Point"}
}