{
  "type": "Feature",
  "properties": {
    "addr:full":"17950 Redmond Way Redmond WA 98052",
    "addr:housenumber":"17950",
    "addr:postcode":"98052",
    "addr:street":"Redmond Way",
    "iso:country":"US",
    "sg:address":"17950 Redmond Way",
    "sg:city":"Redmond",
    "sg:classifiers":[
        {
            "category":"Retail",
            "subcategory":"Repair Shop",
            "type":"Services"
        },
        {
            "category":"Building & Trades",
            "subcategory":"Equipment Rental",
            "type":"Services"
        }
    ],
    "sg:phone":"+1 800 508 4761",
    "sg:postcode":"98052",
    "sg:province":"WA",
    "sg:tags":[
        "yard",
        "supply",
        "contractor",
        "tools-renting",
        "store",
        "contractors'"
    ],
    "sg:website":"http://www-sunbeltrentals-com.netsolads.com/?utm_source=yp.com&utm_medium=tilead&utm_term=localsearch&utm_campaign=&_nsag=39093",
    "wof:name":"Sunbelt Rentals",
    "wof:placetype":"venue"
},
  "geometry": {"coordinates":[-122.101311,47.667122],"type":"Point"}
}