{
  "type": "Feature",
  "properties": {
    "addr:full":"2404 104th Street Ct S Lakewood WA 98499",
    "addr:housenumber":"2404",
    "addr:postcode":"98499",
    "addr:street":"104Th Street Ct",
    "iso:country":"US",
    "sg:address":"2404 104th Street Ct S",
    "sg:city":"Lakewood",
    "sg:classifiers":[
        {
            "category":"Banks & Credit Unions",
            "subcategory":"Financial Services",
            "type":"Services"
        }
    ],
    "sg:phone":"+1 253 584 8069",
    "sg:postcode":"98499",
    "sg:province":"WA",
    "sg:tags":[
        "international",
        "trade"
    ],
    "wof:name":"Tony's Trading",
    "wof:placetype":"venue"
},
  "geometry": {"coordinates":[-122.46685600000001,47.163242],"type":"Point"}
}