{
  "type": "Feature",
  "properties": {
    "iso:country":"US",
    "sg:address":"4001 State Hwy 3",
    "sg:city":"Bremerton",
    "sg:classifiers":[
        {
            "category":"Building & Trades",
            "subcategory":"Construction",
            "type":"Services"
        }
    ],
    "sg:phone":"+1 360 377 5678",
    "sg:postcode":"98312",
    "sg:province":"WA",
    "sg:tags":[
        "contractor"
    ],
    "wof:name":"Whittington Tile & Stone",
    "wof:placetype":"venue"
},
  "geometry": {"coordinates":[-122.703999,47.599925],"type":"Point"}
}