{
  "type": "Feature",
  "properties": {
    "addr:full":"4420 Reese Hill Rd Sumas WA 98295",
    "addr:housenumber":"4420",
    "addr:postcode":"98295",
    "addr:street":"Reese Hill Rd",
    "iso:country":"US",
    "sg:address":"4420 Reese Hill Rd",
    "sg:city":"Sumas",
    "sg:classifiers":[
        {
            "category":"Transit Center",
            "subcategory":"Freight",
            "type":"Transportation"
        },
        {
            "category":"Freight",
            "type":"Transportation"
        }
    ],
    "sg:phone":"+1 360 988 8732",
    "sg:postcode":"98295",
    "sg:province":"WA",
    "sg:tags":[
        "trucking-motor",
        "trucking"
    ],
    "wof:name":"High Valley Trucking",
    "wof:placetype":"venue"
},
  "geometry": {"coordinates":[-122.244186,48.985519],"type":"Point"}
}