{
  "type": "Feature",
  "properties": {
    "addr:full":"32818 SE 309th St Ravensdale WA 98051",
    "addr:postcode":"32818;98051",
    "addr:street":"Se 309Th St",
    "iso:country":"US",
    "sg:address":"32818 SE 309th St",
    "sg:city":"Ravensdale",
    "sg:classifiers":[
        {
            "category":"Building & Trades",
            "subcategory":"Construction",
            "type":"Services"
        }
    ],
    "sg:phone":"+1 360 886 8937",
    "sg:postcode":"98051",
    "sg:province":"WA",
    "sg:tags":[
        "excavation",
        "contractor"
    ],
    "wof:name":"Rhino Excavating & Trucking",
    "wof:placetype":"venue"
},
  "geometry": {"coordinates":[-121.902519,47.323727],"type":"Point"}
}