{
  "type": "Feature",
  "properties": {
    "iso:country":"US",
    "sg:address":"917 S 1st St",
    "sg:city":"Yakima",
    "sg:classifiers":[
        {
            "category":"Restaurant",
            "type":"Food & Drink"
        }
    ],
    "sg:phone":"+1 509 248 1848",
    "sg:postcode":"98901",
    "sg:province":"WA",
    "sg:tags":[
        "eating"
    ],
    "wof:name":"Cuppa Giddy Up Espresso",
    "wof:placetype":"venue"
},
  "geometry": {"coordinates":[-120.500356,46.591416],"type":"Point"}
}