{
  "type": "Feature",
  "properties": {
    "addr:full":"8169 NE Blakely Ct W Bainbridge Island WA 98110",
    "addr:housenumber":"8169",
    "addr:postcode":"98110",
    "addr:street":"Ne Blakely Ct W",
    "iso:country":"US",
    "sg:address":"8169 NE Blakely Ct W",
    "sg:city":"Bainbridge Island",
    "sg:classifiers":[
        {
            "category":"Real Estate",
            "subcategory":"Real Estate Agent",
            "type":"Services"
        }
    ],
    "sg:phone":"+1 206 842 7341",
    "sg:postcode":"98110",
    "sg:province":"WA",
    "wof:name":"Lynda A Blain",
    "wof:placetype":"venue"
},
  "geometry": {"coordinates":[-122.541239,47.604228],"type":"Point"}
}