{
  "type": "Feature",
  "properties": {
    "iso:country":"US",
    "sg:address":"120 E Moore St",
    "sg:city":"Port Hadlock",
    "sg:classifiers":[
        {
            "category":"Retail",
            "subcategory":"Repair Shop",
            "type":"Services"
        }
    ],
    "sg:phone":"+1 360 385 6558",
    "sg:postcode":"98339",
    "sg:province":"WA",
    "wof:name":"J & M Enterprises",
    "wof:placetype":"venue"
},
  "geometry": {"coordinates":[-122.777721,48.044506],"type":"Point"}
}