{
  "type": "Feature",
  "properties": {
    "addr:full":"2803 S D St Spokane WA 99224",
    "addr:housenumber":"2803",
    "addr:postcode":"99224",
    "addr:street":"S D St",
    "iso:country":"US",
    "sg:address":"2803 S D St",
    "sg:city":"Spokane",
    "sg:classifiers":[
        {
            "category":"Shopping",
            "subcategory":"Gifts & Souvenirs",
            "type":"Retail Goods"
        }
    ],
    "sg:phone":"+1 509 838 8274",
    "sg:postcode":"99224",
    "sg:province":"WA",
    "wof:name":"Windsor Gardens",
    "wof:placetype":"venue"
},
  "geometry": {"coordinates":[-117.459489,47.629618],"type":"Point"}
}