{
  "type": "Feature",
  "properties": {
    "addr:full":"1112 Daniels St Ste 200 Vancouver WA 98660",
    "addr:housenumber":"1112",
    "addr:postcode":"98660",
    "addr:street":"Daniels St Ste 200",
    "iso:country":"US",
    "sg:address":"1112 Daniels St Ste 200",
    "sg:city":"Vancouver",
    "sg:classifiers":[
        {
            "category":"Banks & Credit Unions",
            "subcategory":"Atm",
            "type":"Services"
        }
    ],
    "sg:phone":"+1 360 695 7909",
    "sg:postcode":"98660",
    "sg:province":"WA",
    "sg:tags":[
        "bankruptcy"
    ],
    "wof:name":"Marsh Daniel G Atty",
    "wof:placetype":"venue"
},
  "geometry": {"coordinates":[-122.675003,45.6297],"type":"Point"}
}