{
  "type": "Feature",
  "properties": {
    "addr:full":"1535 SW Dash Point Rd Federal Way WA 98023",
    "addr:housenumber":"1535",
    "addr:postcode":"98023",
    "addr:street":"Sw Dash Point Rd",
    "iso:country":"US",
    "sg:address":"1535 SW Dash Point Rd",
    "sg:city":"Federal Way",
    "sg:classifiers":[
        {
            "category":"Retail",
            "subcategory":"Funeral Services",
            "type":"Services"
        }
    ],
    "sg:phone":"+1 253 839 7317",
    "sg:postcode":"98023",
    "sg:province":"WA",
    "wof:name":"Bonney-Wtson Fnrl HM Fderal WY",
    "wof:placetype":"venue"
},
  "geometry": {"coordinates":[-122.354156,47.324166],"type":"Point"}
}