{
  "type": "Feature",
  "properties": {
    "addr:full":"6843 N Star Rd Ferndale WA 98248",
    "addr:housenumber":"6843",
    "addr:postcode":"98248",
    "addr:street":"N Star Rd",
    "iso:country":"US",
    "sg:address":"6843 N Star Rd",
    "sg:city":"Ferndale",
    "sg:classifiers":[
        {
            "category":"Professional",
            "subcategory":"Business Services",
            "type":"Services"
        }
    ],
    "sg:phone":"+1 360 366 5873",
    "sg:postcode":"98248",
    "sg:province":"WA",
    "wof:name":"Sund Enterprises",
    "wof:placetype":"venue"
},
  "geometry": {"coordinates":[-122.671978,48.891834],"type":"Point"}
}