{
  "type": "Feature",
  "properties": {
    "addr:full":"601 40th Pl Everett WA 98201",
    "addr:housenumber":"601",
    "addr:postcode":"98201",
    "addr:street":"40Th Pl",
    "iso:country":"US",
    "sg:address":"601 40th Pl",
    "sg:city":"Everett",
    "sg:classifiers":[
        {
            "category":"Manufacturing",
            "subcategory":"Tools & Machinery",
            "type":"Manufacturing & Wholesale Goods"
        }
    ],
    "sg:phone":"+1 425 259 9237",
    "sg:postcode":"98201",
    "sg:province":"WA",
    "sg:tags":[
        "control",
        "mfg"
    ],
    "wof:name":"Precision Data Technology Inc",
    "wof:placetype":"venue"
},
  "geometry": {"coordinates":[-122.22229799999999,47.965626],"type":"Point"}
}