{
  "type": "Feature",
  "properties": {
    "addr:full":"8490 E Leavenworth Rd Leavenworth WA 98826",
    "addr:housenumber":"8490",
    "addr:postcode":"98826",
    "addr:street":"E Leavenworth Rd",
    "iso:country":"US",
    "sg:address":"8490 E Leavenworth Rd",
    "sg:city":"Leavenworth",
    "sg:classifiers":[
        {
            "category":"Manufacturing",
            "subcategory":"Lumber",
            "type":"Manufacturing & Wholesale Goods"
        }
    ],
    "sg:phone":"+1 509 548 5639",
    "sg:postcode":"98826",
    "sg:province":"WA",
    "sg:tags":[
        "nursery",
        "retailer"
    ],
    "wof:name":"Aavant Gardener The",
    "wof:placetype":"venue"
},
  "geometry": {"coordinates":[-120.66175200000001,47.568068],"type":"Point"}
}