{
  "type": "Feature",
  "properties": {
    "addr:full":"12003 23rd Ave NE Seattle WA 98125",
    "addr:housenumber":"12003",
    "addr:postcode":"98125",
    "addr:street":"23Rd Ave Ne",
    "iso:country":"US",
    "sg:address":"12003 23rd Ave NE",
    "sg:city":"Seattle",
    "sg:classifiers":[
        {
            "category":"Recreation",
            "subcategory":"Boat Charter",
            "type":"Entertainment"
        }
    ],
    "sg:phone":"+1 360 378 3533",
    "sg:postcode":"98125",
    "sg:province":"WA",
    "sg:tags":[
        "boating"
    ],
    "sg:website":"www.outdoorodysseys.com",
    "wof:name":"Outdoor Odysseys Kayak Tours",
    "wof:placetype":"venue"
},
  "geometry": {"coordinates":[-122.30500000000001,47.715698],"type":"Point"}
}