{
  "type": "Feature",
  "properties": {
    "addr:full":"214 E Main St Dayton WA 99328",
    "addr:housenumber":"214",
    "addr:postcode":"99328",
    "addr:street":"E Main St",
    "iso:country":"US",
    "sg:address":"214 E Main St",
    "sg:city":"Dayton",
    "sg:classifiers":[
        {
            "category":"Bars & Pubs",
            "type":"Food & Drink"
        }
    ],
    "sg:phone":"+1 509 382 2364",
    "sg:postcode":"99328",
    "sg:province":"WA",
    "wof:name":"Cracker B's Pub",
    "wof:placetype":"venue"
},
  "geometry": {"coordinates":[-117.979221,46.320211],"type":"Point"}
}