{
  "type": "Feature",
  "properties": {
    "addr:full":"15290 Flightline Rd Burlington WA 98233",
    "addr:housenumber":"15290",
    "addr:postcode":"98233",
    "addr:street":"Flightline Rd",
    "iso:country":"US",
    "sg:address":"15290 Flightline Rd",
    "sg:city":"Burlington",
    "sg:classifiers":[
        {
            "category":"Airport",
            "type":"Transportation"
        }
    ],
    "sg:phone":"+1 360 757 4565",
    "sg:postcode":"98233",
    "sg:province":"WA",
    "sg:tags":[
        "repair",
        "aircraft",
        "maintenance",
        "rebuilding"
    ],
    "wof:name":"Sound Aircraft Repair",
    "wof:placetype":"venue"
},
  "geometry": {"coordinates":[-122.421419,48.476778],"type":"Point"}
}