{
  "type": "Feature",
  "properties": {
    "addr:full":"1323 102nd Ave NE Bellevue WA 98004",
    "addr:housenumber":"1323",
    "addr:postcode":"98004",
    "addr:street":"102Nd Ave Ne",
    "iso:country":"US",
    "sg:address":"1323 102nd Ave NE",
    "sg:city":"Bellevue",
    "sg:classifiers":[
        {
            "category":"Professional",
            "type":"Services"
        }
    ],
    "sg:phone":"+1 425 635 0447",
    "sg:postcode":"98004",
    "sg:province":"WA",
    "sg:tags":[
        "establishment"
    ],
    "sg:website":"www.eventforceinc.com",
    "wof:name":"Eventforce",
    "wof:placetype":"venue"
},
  "geometry": {"coordinates":[-122.20453999999999,47.621553],"type":"Point"}
}