{
  "type": "Feature",
  "properties": {
    "addr:full":"2251 Lancaster Rd Freeland WA 98249",
    "addr:housenumber":"2251",
    "addr:postcode":"98249",
    "addr:street":"Lancaster Rd",
    "iso:country":"US",
    "sg:address":"2251 Lancaster Rd",
    "sg:city":"Freeland",
    "sg:classifiers":[
        {
            "category":"Organizations",
            "subcategory":"Religious Organization",
            "type":"Services"
        }
    ],
    "sg:phone":"+1 360 331 4401",
    "sg:postcode":"98249",
    "sg:province":"WA",
    "sg:tags":[
        "clergy"
    ],
    "wof:name":"Lauren Burrei",
    "wof:placetype":"venue"
},
  "geometry": {"coordinates":[-122.511363,47.998913],"type":"Point"}
}