{
  "type": "Feature",
  "properties": {
    "addr:full":"3570 Sunset Dr W Tacoma WA 98466",
    "addr:housenumber":"3570",
    "addr:postcode":"98466",
    "addr:street":"Sunset Dr W",
    "iso:country":"US",
    "sg:address":"3570 Sunset Dr W",
    "sg:city":"Tacoma",
    "sg:classifiers":[
        {
            "category":"Retail",
            "subcategory":"Repair Shop",
            "type":"Services"
        }
    ],
    "sg:phone":"+1 253 565 5379",
    "sg:postcode":"98466",
    "sg:province":"WA",
    "wof:name":"M T R",
    "wof:placetype":"venue"
},
  "geometry": {"coordinates":[-122.545152,47.225754],"type":"Point"}
}