{
  "type": "Feature",
  "properties": {
    "addr:full":"16616 N Primrose Ln Nine Mile Falls WA 99026",
    "addr:housenumber":"16616",
    "addr:postcode":"99026",
    "addr:street":"N Primrose Ln",
    "iso:country":"US",
    "sg:address":"16616 N Primrose Ln",
    "sg:city":"Nine Mile Falls",
    "sg:classifiers":[
        {
            "category":"Airport",
            "type":"Transportation"
        }
    ],
    "sg:phone":"+1 509 467 9365",
    "sg:postcode":"99026",
    "sg:province":"WA",
    "wof:name":"Aviation Avionics & Instrs",
    "wof:placetype":"venue"
},
  "geometry": {"coordinates":[-117.589905,47.814584],"type":"Point"}
}