{
  "type": "Feature",
  "properties": {
    "addr:full":"10020 Main St Bellevue WA 98004",
    "addr:housenumber":"10020",
    "addr:postcode":"98004",
    "addr:street":"Main St",
    "iso:country":"US",
    "sg:address":"10020 Main St",
    "sg:city":"Bellevue",
    "sg:classifiers":[
        {
            "category":"Professional",
            "subcategory":"Lawyer & Legal Services",
            "type":"Services"
        }
    ],
    "sg:phone":"+1 425 453 0181",
    "sg:postcode":"98004",
    "sg:province":"WA",
    "sg:tags":[
        "attorney",
        "referral"
    ],
    "wof:name":"Attorney Referral Svc",
    "wof:placetype":"venue"
},
  "geometry": {"coordinates":[-122.206577,47.610262],"type":"Point"}
}