{
  "type": "Feature",
  "properties": {
    "addr:full":"6016 41st Ave NE Seattle WA 98115",
    "addr:housenumber":"6016",
    "addr:postcode":"98115",
    "addr:street":"41St Ave Ne",
    "iso:country":"US",
    "sg:address":"6016 41st Ave NE",
    "sg:city":"Seattle",
    "sg:classifiers":[
        {
            "category":"Home & Garden",
            "subcategory":"Furniture",
            "type":"Retail Goods"
        }
    ],
    "sg:phone":"+1 206 522 3369",
    "sg:postcode":"98115",
    "sg:province":"WA",
    "sg:tags":[
        "store"
    ],
    "wof:name":"Deal, Lanham Furniture",
    "wof:placetype":"venue"
},
  "geometry": {"coordinates":[-122.283511,47.672455],"type":"Point"}
}