{
  "type": "Feature",
  "properties": {
    "addr:full":"11 Logan Rd Orondo WA 98843",
    "addr:housenumber":"11",
    "addr:postcode":"98843",
    "addr:street":"Logan Rd",
    "iso:country":"US",
    "sg:address":"11 Logan Rd",
    "sg:city":"Orondo",
    "sg:classifiers":[
        {
            "category":"Government",
            "subcategory":"Fire Station",
            "type":"Public Place"
        }
    ],
    "sg:phone":"+1 509 784 2941",
    "sg:postcode":"98843",
    "sg:province":"WA",
    "sg:tags":[
        "department"
    ],
    "sg:website":"http://www.douglasfire2.org",
    "wof:name":"Douglas County Fire Dst 4",
    "wof:placetype":"venue"
},
  "geometry": {"coordinates":[-120.214119,47.73277],"type":"Point"}
}