{
  "type": "Feature",
  "properties": {
    "addr:full":"11011 SE 320th St Auburn WA 98092",
    "addr:postcode":"11011;98092",
    "addr:street":"Se 320Th St",
    "iso:country":"US",
    "sg:address":"11011 SE 320th St",
    "sg:city":"Auburn",
    "sg:classifiers":[
        {
            "category":"Manufacturing",
            "subcategory":"Motor Vehicles & Parts",
            "type":"Manufacturing & Wholesale Goods"
        }
    ],
    "sg:phone":"+1 253 351 6994",
    "sg:postcode":"98092",
    "sg:province":"WA",
    "sg:tags":[
        "mfg"
    ],
    "wof:name":"JP Enterprise",
    "wof:placetype":"venue"
},
  "geometry": {"coordinates":[-122.19378,47.315304],"type":"Point"}
}