{
  "type": "Feature",
  "properties": {
    "addr:full":"1957 Mackenzie Ln East Wenatchee WA 98802",
    "addr:housenumber":"1957",
    "addr:postcode":"98802",
    "addr:street":"Mackenzie Ln",
    "iso:country":"US",
    "sg:address":"1957 Mackenzie Ln",
    "sg:city":"East Wenatchee",
    "sg:classifiers":[
        {
            "category":"Farming",
            "subcategory":"Orchard",
            "type":"Manufacturing & Wholesale Goods"
        }
    ],
    "sg:phone":"+1 509 884 0109",
    "sg:postcode":"98802",
    "sg:province":"WA",
    "sg:tags":[
        "fruit",
        "tree"
    ],
    "wof:name":"Steven L Stuart",
    "wof:placetype":"venue"
},
  "geometry": {"coordinates":[-120.25488799999999,47.389618],"type":"Point"}
}