{
  "type": "Feature",
  "properties": {
    "addr:full":"6618 130th Ave NE Kirkland WA 98033",
    "addr:housenumber":"6618",
    "addr:postcode":"98033",
    "addr:street":"130Th Ave Ne",
    "iso:country":"US",
    "sg:address":"6618 130th Ave NE",
    "sg:city":"Kirkland",
    "sg:classifiers":[
        {
            "category":"Retail",
            "subcategory":"Auto Repair",
            "type":"Services"
        }
    ],
    "sg:phone":"+1 425 482 6383",
    "sg:postcode":"98033",
    "sg:province":"WA",
    "sg:tags":[
        "general"
    ],
    "wof:name":"BE Aerospace Inc",
    "wof:placetype":"venue"
},
  "geometry": {"coordinates":[-122.166596,47.666603],"type":"Point"}
}