{
  "type": "Feature",
  "properties": {
    "addr:full":"1803 Baker Way Kelso WA 98626",
    "addr:housenumber":"1803",
    "addr:postcode":"98626",
    "addr:street":"Baker Way",
    "iso:country":"US",
    "sg:address":"1803 Baker Way",
    "sg:city":"Kelso",
    "sg:classifiers":[
        {
            "category":"Manufacturing",
            "subcategory":"Metals",
            "type":"Manufacturing & Wholesale Goods"
        }
    ],
    "sg:phone":"+1 360 577 7213",
    "sg:postcode":"98626",
    "sg:province":"WA",
    "sg:tags":[
        "steel"
    ],
    "wof:name":"R D Olson Mfg Inc",
    "wof:placetype":"venue"
},
  "geometry": {"coordinates":[-122.89409000000001,46.120916],"type":"Point"}
}