{
  "type": "Feature",
  "properties": {
    "addr:full":"11736 SE 168th St Renton WA 98058",
    "addr:postcode":"11736;98058",
    "addr:street":"Se 168Th St",
    "iso:country":"US",
    "sg:address":"11736 SE 168th St",
    "sg:city":"Renton",
    "sg:classifiers":[
        {
            "category":"Shopping",
            "subcategory":"Catalog Store",
            "type":"Retail Goods"
        }
    ],
    "sg:phone":"+1 425 271 9964",
    "sg:postcode":"98058",
    "sg:province":"WA",
    "sg:tags":[
        "mail",
        "house"
    ],
    "wof:name":"Valdez Ray A Enterprises",
    "wof:placetype":"venue"
},
  "geometry": {"coordinates":[-122.184136,47.45253],"type":"Point"}
}