{
  "type": "Feature",
  "properties": {
    "addr:full":"2100 SE 164th Ave Vancouver WA 98683",
    "addr:housenumber":"2100",
    "addr:postcode":"98683",
    "addr:street":"Se 164Th Ave",
    "iso:country":"US",
    "sg:address":"2100 SE 164th Ave",
    "sg:city":"Vancouver",
    "sg:classifiers":[
        {
            "category":"Shopping",
            "subcategory":"Gifts & Souvenirs",
            "type":"Retail Goods"
        }
    ],
    "sg:phone":"+1 360 892 7773",
    "sg:postcode":"98683",
    "sg:province":"WA",
    "wof:name":"Hallmark 21",
    "wof:placetype":"venue"
},
  "geometry": {"coordinates":[-122.50394300000001,45.60473],"type":"Point"}
}