{
  "type": "Feature",
  "properties": {
    "iso:country":"US",
    "sg:address":"1313 W Meeker St",
    "sg:city":"Kent",
    "sg:classifiers":[
        {
            "category":"Government",
            "subcategory":"Police Station",
            "type":"Public Place"
        }
    ],
    "sg:phone":"+1 253 872 4060",
    "sg:postcode":"98032",
    "sg:province":"WA",
    "sg:tags":[
        "protection"
    ],
    "wof:name":"District 2",
    "wof:placetype":"venue"
},
  "geometry": {"coordinates":[-122.24991199999999,47.381401],"type":"Point"}
}