{
  "type": "Feature",
  "properties": {
    "addr:full":"9617 Fremont Avenue N Seattle WA 98103",
    "addr:housenumber":"9617",
    "addr:postcode":"98103",
    "addr:street":"Fremont Avenue N",
    "iso:country":"US",
    "sg:address":"9617 Fremont Avenue N",
    "sg:city":"Seattle",
    "sg:classifiers":[
        {
            "category":"Building & Trades",
            "subcategory":"Cleaning & Sanitation",
            "type":"Services"
        }
    ],
    "sg:phone":"+1 206 781 8876",
    "sg:postcode":"98103",
    "sg:province":"WA",
    "sg:tags":[
        "home"
    ],
    "wof:name":"Ladonna's Cleaning",
    "wof:placetype":"venue"
},
  "geometry": {"coordinates":[-122.35017999999999,47.69929],"type":"Point"}
}