{
  "type": "Feature",
  "properties": {
    "iso:country":"US",
    "sg:address":"3814 Steilacoom Blvd SW",
    "sg:city":"Lakewood",
    "sg:classifiers":[
        {
            "category":"Personal",
            "subcategory":"Beauty Salon",
            "type":"Services"
        }
    ],
    "sg:phone":"+1 253 983 9853",
    "sg:postcode":"98499",
    "sg:province":"WA",
    "sg:tags":[
        "shop"
    ],
    "wof:name":"Encore Hair Studio",
    "wof:placetype":"venue"
},
  "geometry": {"coordinates":[-122.48495200000001,47.176463],"type":"Point"}
}