{
  "type": "Feature",
  "properties": {
    "addr:full":"1326 5th St Marysville WA 98270",
    "addr:housenumber":"1326",
    "addr:postcode":"98270",
    "addr:street":"5Th St",
    "iso:country":"US",
    "sg:address":"1326 5th St",
    "sg:city":"Marysville",
    "sg:classifiers":[
        {
            "category":"Professional",
            "subcategory":"Employment Agencies",
            "type":"Services"
        }
    ],
    "sg:phone":"+1 360 653 8599",
    "sg:postcode":"98270",
    "sg:province":"WA",
    "sg:tags":[
        "opportunity"
    ],
    "wof:name":"Weststaff",
    "wof:placetype":"venue"
},
  "geometry": {"coordinates":[-122.178821,48.052693],"type":"Point"}
}