{
  "type": "Feature",
  "properties": {
    "addr:full":"5595 Starry Rd Bellingham WA 98226",
    "addr:housenumber":"5595",
    "addr:postcode":"98226",
    "addr:street":"Starry Rd",
    "iso:country":"US",
    "sg:address":"5595 Starry Rd",
    "sg:city":"Bellingham",
    "sg:classifiers":[
        {
            "category":"Manufacturing",
            "subcategory":"Apparel",
            "type":"Manufacturing & Wholesale Goods"
        }
    ],
    "sg:phone":"+1 360 739 7321",
    "sg:postcode":"98226",
    "sg:province":"WA",
    "sg:tags":[
        "household",
        "furnishing",
        "mfg"
    ],
    "wof:name":"Starry Night Mercantile",
    "wof:placetype":"venue"
},
  "geometry": {"coordinates":[-122.409785,48.847674],"type":"Point"}
}