{
  "type": "Feature",
  "properties": {
    "addr:full":"817 N 6th St Mt Vernon WA 98273",
    "addr:housenumber":"817",
    "addr:postcode":"98273",
    "addr:street":"N 6Th St",
    "iso:country":"US",
    "sg:address":"817 N 6th St",
    "sg:city":"Mt Vernon",
    "sg:classifiers":[
        {
            "category":"Building & Trades",
            "subcategory":"Electrical",
            "type":"Services"
        }
    ],
    "sg:phone":"+1 360 419 9378",
    "sg:postcode":"98273",
    "sg:province":"WA",
    "sg:tags":[
        "electrical",
        "electric",
        "contractor"
    ],
    "wof:name":"Electric West Inc",
    "wof:placetype":"venue"
},
  "geometry": {"coordinates":[-122.333152,48.428344],"type":"Point"}
}