{
  "type": "Feature",
  "properties": {
    "addr:full":"22313 70th Ave W Mountlake Ter WA 98043",
    "addr:housenumber":"22313",
    "addr:postcode":"98043",
    "addr:street":"70Th Ave W Mountlake Ter",
    "iso:country":"US",
    "sg:address":"22313 70th Ave W",
    "sg:city":"Mountlake Ter",
    "sg:classifiers":[
        {
            "category":"Wholesale",
            "subcategory":"Machinery & Supplies",
            "type":"Manufacturing & Wholesale Goods"
        }
    ],
    "sg:phone":"+1 425 775 4506",
    "sg:postcode":"98043",
    "sg:province":"WA",
    "sg:tags":[
        "equipment",
        "industrial"
    ],
    "wof:name":"Fastenal Co",
    "wof:placetype":"venue"
},
  "geometry": {"coordinates":[-122.32754,47.796933],"type":"Point"}
}