{
  "type": "Feature",
  "properties": {
    "addr:full":"1821 9th Ave SE Olympia WA 98501",
    "addr:housenumber":"1821",
    "addr:postcode":"98501",
    "addr:street":"9Th Ave Se",
    "iso:country":"US",
    "sg:address":"1821 9th Ave SE",
    "sg:city":"Olympia",
    "sg:classifiers":[
        {
            "category":"Professional",
            "subcategory":"Art Services",
            "type":"Services"
        }
    ],
    "sg:phone":"+1 360 951 5941",
    "sg:postcode":"98501",
    "sg:province":"WA",
    "sg:tags":[
        "photography",
        "commercial"
    ],
    "wof:name":"12 Benches Photography",
    "wof:placetype":"venue"
},
  "geometry": {"coordinates":[-122.875958,47.041717],"type":"Point"}
}