{
  "type": "Feature",
  "properties": {
    "addr:full":"13820 91st Ave NW Gig Harbor WA 98329",
    "addr:housenumber":"13820",
    "addr:postcode":"98329",
    "addr:street":"91St Ave Nw",
    "iso:country":"US",
    "sg:address":"13820 91st Ave NW",
    "sg:city":"Gig Harbor",
    "sg:classifiers":[
        {
            "category":"Social Services",
            "subcategory":"Child Care",
            "type":"Services"
        }
    ],
    "sg:phone":"+1 253 857 3836",
    "sg:postcode":"98329",
    "sg:province":"WA",
    "sg:tags":[
        "day"
    ],
    "wof:name":"Kids Kastle Daycare",
    "wof:placetype":"venue"
},
  "geometry": {"coordinates":[-122.658868,47.384572],"type":"Point"}
}