{
  "type": "Feature",
  "properties": {
    "addr:full":"17503 60th Ave W Lynnwood WA 98037",
    "addr:housenumber":"17503",
    "addr:postcode":"98037",
    "addr:street":"60Th Ave W",
    "iso:country":"US",
    "sg:address":"17503 60th Ave W",
    "sg:city":"Lynnwood",
    "sg:classifiers":[
        {
            "category":"Building & Trades",
            "subcategory":"Construction",
            "type":"Services"
        }
    ],
    "sg:phone":"+1 425 743 0204",
    "sg:postcode":"98037",
    "sg:province":"WA",
    "sg:tags":[
        "contractor"
    ],
    "wof:name":"Doonan Plastering Inc",
    "wof:placetype":"venue"
},
  "geometry": {"coordinates":[-122.314229,47.840236],"type":"Point"}
}