{
  "type": "Feature",
  "properties": {
    "addr:full":"2608 2nd Ave Seattle WA 98121",
    "addr:housenumber":"2608",
    "addr:postcode":"98121",
    "addr:street":"2Nd Ave",
    "iso:country":"US",
    "sg:address":"2608 2nd Ave",
    "sg:city":"Seattle",
    "sg:classifiers":[
        {
            "category":"Professional",
            "subcategory":"Management & Consulting",
            "type":"Services"
        }
    ],
    "sg:phone":"+1 206 683 4850",
    "sg:postcode":"98121",
    "sg:province":"WA",
    "sg:tags":[
        "business"
    ],
    "wof:name":"Wise Consulting Services",
    "wof:placetype":"venue"
},
  "geometry": {"coordinates":[-122.34965800000001,47.616476],"type":"Point"}
}