{
  "type": "Feature",
  "properties": {
    "addr:full":"4136 94th Pl SE Mercer Island WA 98040",
    "addr:housenumber":"4136",
    "addr:postcode":"98040",
    "addr:street":"94Th Pl Se",
    "iso:country":"US",
    "sg:address":"4136 94th Pl SE",
    "sg:city":"Mercer Island",
    "sg:classifiers":[
        {
            "category":"Real Estate",
            "subcategory":"Real Estate Operator",
            "type":"Services"
        }
    ],
    "sg:phone":"+1 206 236 1543",
    "sg:postcode":"98040",
    "sg:province":"WA",
    "sg:tags":[
        "building",
        "apartment"
    ],
    "wof:name":"Candlewood Apartments",
    "wof:placetype":"venue"
},
  "geometry": {"coordinates":[-122.21367499999999,47.572259],"type":"Point"}
}