{
  "type": "Feature",
  "properties": {
    "addr:full":"512 W Main St Kelso WA 98626",
    "addr:housenumber":"512",
    "addr:postcode":"98626",
    "addr:street":"W Main St",
    "iso:country":"US",
    "sg:address":"512 W Main St",
    "sg:city":"Kelso",
    "sg:classifiers":[
        {
            "category":"Shopping",
            "type":"Retail Goods"
        }
    ],
    "sg:phone":"+1 360 423 7073",
    "sg:postcode":"98626",
    "sg:province":"WA",
    "sg:tags":[
        "spa",
        "pool"
    ],
    "wof:name":"Spas N More Inc",
    "wof:placetype":"venue"
},
  "geometry": {"coordinates":[-122.921008,46.146422],"type":"Point"}
}