{
  "type": "Feature",
  "properties": {
    "addr:full":"8530 NE 128th St Kirkland WA 98034",
    "addr:housenumber":"8530",
    "addr:postcode":"98034",
    "addr:street":"Ne 128Th St",
    "iso:country":"US",
    "sg:address":"8530 NE 128th St",
    "sg:city":"Kirkland",
    "sg:classifiers":[
        {
            "category":"Health Services",
            "subcategory":"Health Practitioner",
            "type":"Services"
        }
    ],
    "sg:phone":"+1 425 820 0544",
    "sg:postcode":"98034",
    "sg:province":"WA",
    "sg:tags":[
        "acupuncture",
        "medicine",
        "alternative"
    ],
    "wof:name":"Fenoli Acupuncture Clinic",
    "wof:placetype":"venue"
},
  "geometry": {"coordinates":[-122.227639,47.714816],"type":"Point"}
}