{
  "type": "Feature",
  "properties": {
    "addr:full":"26807 SE 18th St Sammamish WA 98075",
    "addr:postcode":"26807;98075",
    "addr:street":"Se 18Th St",
    "iso:country":"US",
    "sg:address":"26807 SE 18th St",
    "sg:city":"Sammamish",
    "sg:classifiers":[
        {
            "category":"Professional",
            "subcategory":"Management & Consulting",
            "type":"Services"
        }
    ],
    "sg:phone":"+1 425 391 8148",
    "sg:postcode":"98075",
    "sg:province":"WA",
    "sg:tags":[
        "business"
    ],
    "wof:name":"Moxie Ventures Inc",
    "wof:placetype":"venue"
},
  "geometry": {"coordinates":[-121.980149,47.593278],"type":"Point"}
}