{
  "type": "Feature",
  "properties": {
    "addr:full":"590 SE Andrews St Issaquah WA 98027",
    "addr:housenumber":"590",
    "addr:postcode":"98027",
    "addr:street":"Se Andrews St",
    "iso:country":"US",
    "sg:address":"590 SE Andrews St",
    "sg:city":"Issaquah",
    "sg:classifiers":[
        {
            "category":"Wholesale",
            "subcategory":"Hardware",
            "type":"Manufacturing & Wholesale Goods"
        }
    ],
    "sg:phone":"+1 425 392 1937",
    "sg:postcode":"98027",
    "sg:province":"WA",
    "sg:tags":[
        "furnace"
    ],
    "wof:name":"Dirk's Heating",
    "wof:placetype":"venue"
},
  "geometry": {"coordinates":[-122.02816,47.529177],"type":"Point"}
}