{
  "type": "Feature",
  "properties": {
    "iso:country":"US",
    "sg:address":"13576 Bayview Edison Rd",
    "sg:city":"Mount Vernon",
    "sg:classifiers":[
        {
            "category":"Manufacturing",
            "subcategory":"Metals",
            "type":"Manufacturing & Wholesale Goods"
        }
    ],
    "sg:phone":"+1 360 466 1234",
    "sg:postcode":"98273",
    "sg:province":"WA",
    "sg:tags":[
        "mfg",
        "metalwork",
        "sheet",
        "structural"
    ],
    "wof:name":"Washington Blowpipe Inc",
    "wof:placetype":"venue"
},
  "geometry": {"coordinates":[-122.465812,48.449222],"type":"Point"}
}