{
  "type": "Feature",
  "properties": {
    "addr:full":"3100 H St Washougal WA 98671",
    "addr:housenumber":"3100",
    "addr:postcode":"98671",
    "addr:street":"H St",
    "iso:country":"US",
    "sg:address":"3100 H St",
    "sg:city":"Washougal",
    "sg:classifiers":[
        {
            "category":"Retail",
            "subcategory":"Animal Services",
            "type":"Services"
        }
    ],
    "sg:phone":"+1 360 835 5490",
    "sg:postcode":"98671",
    "sg:province":"WA",
    "sg:tags":[
        "pet",
        "grooming",
        "washing"
    ],
    "wof:name":"Joey's Dog Grooming & Pet Supl",
    "wof:placetype":"venue"
},
  "geometry": {"coordinates":[-122.338858,45.581919],"type":"Point"}
}