{
  "type": "Feature",
  "properties": {
    "addr:full":"13543 160th Ave NE Redmond WA 98052",
    "addr:housenumber":"13543",
    "addr:postcode":"98052",
    "addr:street":"160Th Ave Ne",
    "iso:country":"US",
    "sg:address":"13543 160th Ave NE",
    "sg:city":"Redmond",
    "sg:classifiers":[
        {
            "category":"Sports & Exercise",
            "subcategory":"Gym",
            "type":"Entertainment"
        }
    ],
    "sg:phone":"+1 206 612 4700",
    "sg:postcode":"98052",
    "sg:province":"WA",
    "sg:tags":[
        "trainer"
    ],
    "sg:website":"www.rusa.org",
    "wof:name":"Randonneurs USA",
    "wof:placetype":"venue"
},
  "geometry": {"coordinates":[-122.126319,47.721773],"type":"Point"}
}