{
  "type": "Feature",
  "properties": {
    "addr:full":"27 Hart Rd Oroville WA 98844",
    "addr:housenumber":"27",
    "addr:postcode":"98844",
    "addr:street":"Hart Rd",
    "iso:country":"US",
    "sg:address":"27 Hart Rd",
    "sg:city":"Oroville",
    "sg:classifiers":[
        {
            "category":"Farming",
            "subcategory":"Orchard",
            "type":"Manufacturing & Wholesale Goods"
        }
    ],
    "sg:phone":"+1 509 476 2697",
    "sg:postcode":"98844",
    "sg:province":"WA",
    "sg:tags":[
        "fruit",
        "tree"
    ],
    "wof:name":"Edwin C & Janet Lillquist",
    "wof:placetype":"venue"
},
  "geometry": {"coordinates":[-119.445487,48.931953],"type":"Point"}
}