{
  "type": "Feature",
  "properties": {
    "addr:full":"2515 112th St E Tacoma WA 98445",
    "addr:housenumber":"2515",
    "addr:postcode":"98445",
    "addr:street":"112Th St",
    "iso:country":"US",
    "sg:address":"2515 112th St E",
    "sg:city":"Tacoma",
    "sg:classifiers":[
        {
            "category":"Manufacturing",
            "subcategory":"Metals",
            "type":"Manufacturing & Wholesale Goods"
        }
    ],
    "sg:phone":"+1 253 531 1061",
    "sg:postcode":"98445",
    "sg:province":"WA",
    "sg:tags":[
        "screen"
    ],
    "wof:name":"Liberty Glass/Blinds & Shades",
    "wof:placetype":"venue"
},
  "geometry": {"coordinates":[-122.39495599999999,47.15499],"type":"Point"}
}