{
  "type": "Feature",
  "properties": {
    "addr:full":"3700 Pacific Hwy E Tacoma WA 98424",
    "addr:housenumber":"3700",
    "addr:postcode":"98424",
    "addr:street":"Pacific Hwy E",
    "iso:country":"US",
    "sg:address":"3700 Pacific Hwy E",
    "sg:city":"Tacoma",
    "sg:classifiers":[
        {
            "category":"Professional",
            "subcategory":"Employment Agencies",
            "type":"Services"
        }
    ],
    "sg:phone":"+1 253 922 7411",
    "sg:postcode":"98424",
    "sg:province":"WA",
    "sg:tags":[
        "opportunity"
    ],
    "sg:website":"www.volt.com",
    "wof:name":"Volt Services Group",
    "wof:placetype":"venue"
},
  "geometry": {"coordinates":[-122.384057,47.243081],"type":"Point"}
}