{
  "type": "Feature",
  "properties": {
    "addr:full":"219 N Bend Blvd N North Bend WA 98045",
    "addr:housenumber":"219",
    "addr:postcode":"98045",
    "addr:street":"N Bend Blvd N",
    "iso:country":"US",
    "sg:address":"219 N Bend Blvd N",
    "sg:city":"North Bend",
    "sg:classifiers":[
        {
            "category":"Building & Trades",
            "subcategory":"Construction",
            "type":"Services"
        }
    ],
    "sg:phone":"+1 425 831 7098",
    "sg:postcode":"98045",
    "sg:province":"WA",
    "sg:tags":[
        "general"
    ],
    "wof:name":"Allen Brothers Constr Co Inc",
    "wof:placetype":"venue"
},
  "geometry": {"coordinates":[-121.785776,47.496443],"type":"Point"}
}