{
  "type": "Feature",
  "properties": {
    "addr:full":"8916 Trapline Rd Everson WA 98247",
    "addr:housenumber":"8916",
    "addr:postcode":"98247",
    "addr:street":"Trapline Rd",
    "iso:country":"US",
    "sg:address":"8916 Trapline Rd",
    "sg:city":"Everson",
    "sg:classifiers":[
        {
            "category":"Building & Trades",
            "subcategory":"Construction",
            "type":"Services"
        }
    ],
    "sg:phone":"+1 360 966 2639",
    "sg:postcode":"98247",
    "sg:province":"WA",
    "sg:tags":[
        "wallcoverings-installation",
        "wallpaper",
        "painting",
        "contractor"
    ],
    "wof:name":"Chase Pro Painting",
    "wof:placetype":"venue"
},
  "geometry": {"coordinates":[-122.35220200000001,48.964569],"type":"Point"}
}