{
  "type": "Feature",
  "properties": {
    "addr:full":"22 Cole Ave Port Townsend WA 98368",
    "addr:housenumber":"22",
    "addr:postcode":"98368",
    "addr:street":"Cole Ave",
    "iso:country":"US",
    "sg:address":"22 Cole Ave",
    "sg:city":"Port Townsend",
    "sg:classifiers":[
        {
            "category":"Personal",
            "subcategory":"Barber",
            "type":"Services"
        }
    ],
    "sg:phone":"+1 360 385 6007",
    "sg:postcode":"98368",
    "sg:province":"WA",
    "sg:tags":[
        "shop"
    ],
    "wof:name":"Hello Gorgeous",
    "wof:placetype":"venue"
},
  "geometry": {"coordinates":[-122.854607,48.086652],"type":"Point"}
}