{
  "type": "Feature",
  "properties": {
    "addr:full":"109 E Forest Napavine Rd Chehalis WA 98532",
    "addr:housenumber":"109",
    "addr:postcode":"98532",
    "addr:street":"E Forest Napavine Rd",
    "iso:country":"US",
    "sg:address":"109 E Forest Napavine Rd",
    "sg:city":"Chehalis",
    "sg:classifiers":[
        {
            "category":"Government",
            "subcategory":"Office",
            "type":"Public Place"
        }
    ],
    "sg:phone":"+1 360 740 1150",
    "sg:postcode":"98532",
    "sg:province":"WA",
    "wof:name":"Lewis County Central Shop",
    "wof:placetype":"venue"
},
  "geometry": {"coordinates":[-122.854589,46.594286],"type":"Point"}
}