{
  "type": "Feature",
  "properties": {
    "addr:full":"7636 Colony Ct NE Bremerton WA 98311",
    "addr:housenumber":"7636",
    "addr:postcode":"98311",
    "addr:street":"Colony Ct Ne",
    "iso:country":"US",
    "sg:address":"7636 Colony Ct NE",
    "sg:city":"Bremerton",
    "sg:classifiers":[
        {
            "category":"Retail",
            "subcategory":"Portrait Studio",
            "type":"Services"
        }
    ],
    "sg:phone":"+1 360 337 1419",
    "sg:postcode":"98311",
    "sg:province":"WA",
    "sg:tags":[
        "photo"
    ],
    "wof:name":"Panorama Photography",
    "wof:placetype":"venue"
},
  "geometry": {"coordinates":[-122.63272499999999,47.633676],"type":"Point"}
}