{
  "type": "Feature",
  "properties": {
    "addr:full":"1100 9th Ave Seattle WA 98101",
    "addr:housenumber":"1100",
    "addr:postcode":"98101",
    "addr:street":"9Th Ave",
    "iso:country":"US",
    "sg:address":"1100 9th Ave",
    "sg:city":"Seattle",
    "sg:classifiers":[
        {
            "category":"Health Services",
            "subcategory":"Doctor",
            "type":"Services"
        }
    ],
    "sg:phone":"+1 206 223 6180",
    "sg:postcode":"98101",
    "sg:province":"WA",
    "sg:tags":[
        "physician",
        "surgeon"
    ],
    "wof:name":"Thomas R Pritchett Md",
    "wof:placetype":"venue"
},
  "geometry": {"coordinates":[-122.328011,47.6091],"type":"Point"}
}