{
  "type": "Feature",
  "properties": {
    "addr:full":"1165 N Stratford Rd Moses Lake WA 98837",
    "addr:housenumber":"1165",
    "addr:postcode":"98837",
    "addr:street":"N Stratford Rd",
    "iso:country":"US",
    "sg:address":"1165 N Stratford Rd",
    "sg:city":"Moses Lake",
    "sg:classifiers":[
        {
            "category":"Bars & Pubs",
            "type":"Food & Drink"
        }
    ],
    "sg:phone":"+1 509 765 1248",
    "sg:postcode":"98837",
    "sg:province":"WA",
    "sg:tags":[
        "lounge",
        "cocktail"
    ],
    "sg:website":"www.papas-casino.com",
    "wof:name":"Papa's Sports Lounge",
    "wof:placetype":"venue"
},
  "geometry": {"coordinates":[-119.27828100000001,47.145595],"type":"Point"}
}