{
  "type": "Feature",
  "properties": {
    "addr:full":"2016 NE 138th St Vancouver WA 98686",
    "addr:housenumber":"2016",
    "addr:postcode":"98686",
    "addr:street":"Ne 138Th St",
    "iso:country":"US",
    "sg:address":"2016 NE 138th St",
    "sg:city":"Vancouver",
    "sg:classifiers":[
        {
            "category":"Social Services",
            "subcategory":"Child Care",
            "type":"Services"
        }
    ],
    "sg:phone":"+1 360 573 1187",
    "sg:postcode":"98686",
    "sg:province":"WA",
    "sg:tags":[
        "day"
    ],
    "wof:name":"Teddy Bear Preschool",
    "wof:placetype":"venue"
},
  "geometry": {"coordinates":[-122.64997700000001,45.720987],"type":"Point"}
}