{
  "type": "Feature",
  "properties": {
    "addr:full":"15016 SE 63rd St Bellevue WA 98006",
    "addr:postcode":"15016;98006",
    "addr:street":"Se 63Rd St",
    "iso:country":"US",
    "sg:address":"15016 SE 63rd St",
    "sg:city":"Bellevue",
    "sg:classifiers":[
        {
            "category":"Professional",
            "subcategory":"Computer Services",
            "type":"Services"
        }
    ],
    "sg:phone":"+1 425 649 0459",
    "sg:postcode":"98006",
    "sg:province":"WA",
    "sg:tags":[
        "prepackaged",
        "software"
    ],
    "wof:name":"Virtual Software Corp",
    "wof:placetype":"venue"
},
  "geometry": {"coordinates":[-122.138947,47.546377],"type":"Point"}
}