{
  "type": "Feature",
  "properties": {
    "addr:full":"8502 NE 54th St Vancouver WA 98662",
    "addr:housenumber":"8502",
    "addr:postcode":"98662",
    "addr:street":"Ne 54Th St",
    "iso:country":"US",
    "sg:address":"8502 NE 54th St",
    "sg:city":"Vancouver",
    "sg:classifiers":[
        {
            "category":"Education",
            "subcategory":"Special Training",
            "type":"Public Place"
        }
    ],
    "sg:phone":"+1 360 260 9420",
    "sg:postcode":"98662",
    "sg:province":"WA",
    "wof:name":"Butterfly Rainbows",
    "wof:placetype":"venue"
},
  "geometry": {"coordinates":[-122.585143,45.661807],"type":"Point"}
}