{
  "type": "Feature",
  "properties": {
    "addr:full":"419 Confer Rd Exd Kalama WA 98625",
    "addr:housenumber":"419",
    "addr:postcode":"98625",
    "addr:street":"Confer Rd Exd Kalama",
    "iso:country":"US",
    "sg:address":"419 Confer Rd Exd",
    "sg:city":"Kalama",
    "sg:classifiers":[
        {
            "category":"Professional",
            "subcategory":"Business Services",
            "type":"Services"
        }
    ],
    "sg:phone":"+1 360 673 4476",
    "sg:postcode":"98625",
    "sg:province":"WA",
    "wof:name":"G Martin David",
    "wof:placetype":"venue"
},
  "geometry": {"coordinates":[-122.80046299999999,45.969177],"type":"Point"}
}