{
  "type": "Feature",
  "properties": {
    "addr:full":"3315 E Fourth Plain Blvd Vancouver WA 98661",
    "addr:housenumber":"3315",
    "addr:postcode":"98661",
    "addr:street":"E Fourth Plain Blvd",
    "iso:country":"US",
    "sg:address":"3315 E Fourth Plain Blvd",
    "sg:city":"Vancouver",
    "sg:classifiers":[
        {
            "category":"Retail",
            "subcategory":"Auto Rental",
            "type":"Services"
        }
    ],
    "sg:phone":"+1 360 693 0994",
    "sg:postcode":"98661",
    "sg:province":"WA",
    "sg:tags":[
        "renting",
        "truck",
        "leasing"
    ],
    "wof:name":"U-Haul Co",
    "wof:placetype":"venue"
},
  "geometry": {"coordinates":[-122.634975,45.637488],"type":"Point"}
}