{
  "type": "Feature",
  "properties": {
    "addr:full":"9500 Farwest Dr SW Lakewood WA 98498",
    "addr:postcode":"9500;98498",
    "addr:street":"Farwest Dr Sw",
    "iso:country":"US",
    "sg:address":"9500 Farwest Dr SW",
    "sg:city":"Lakewood",
    "sg:classifiers":[
        {
            "category":"Professional",
            "type":"Services"
        }
    ],
    "sg:phone":"+1 253 912 1814",
    "sg:postcode":"98498",
    "sg:province":"WA",
    "wof:name":"Rolmar Inc",
    "wof:placetype":"venue"
},
  "geometry": {"coordinates":[-122.57438399999999,47.170573],"type":"Point"}
}