{
  "type": "Feature",
  "properties": {
    "addr:full":"3849 Klahanie Dr SE Issaquah WA 98029",
    "addr:housenumber":"3849",
    "addr:postcode":"98029",
    "addr:street":"Klahanie Dr Se",
    "iso:country":"US",
    "sg:address":"3849 Klahanie Dr SE",
    "sg:city":"Issaquah",
    "sg:classifiers":[
        {
            "category":"Building & Trades",
            "subcategory":"Construction",
            "type":"Services"
        }
    ],
    "sg:phone":"+1 360 670 6490",
    "sg:postcode":"98029",
    "sg:province":"WA",
    "sg:tags":[
        "residential",
        "painting"
    ],
    "wof:name":"Northwest Painting Co",
    "wof:placetype":"venue"
},
  "geometry": {"coordinates":[-121.99902400000001,47.575104],"type":"Point"}
}