{
  "type": "Feature",
  "properties": {
    "addr:full":"1200 Westlake Ave N 406 Seattle WA 98109",
    "addr:housenumber":"1200;406",
    "addr:postcode":"98109",
    "addr:street":"Westlake Ave N",
    "iso:country":"US",
    "sg:address":"1200 Westlake Ave N 406",
    "sg:city":"Seattle",
    "sg:classifiers":[
        {
            "category":"Real Estate",
            "subcategory":"Real Estate Agent",
            "type":"Services"
        }
    ],
    "sg:phone":"+1 206 283 5200",
    "sg:postcode":"98109",
    "sg:province":"WA",
    "sg:website":"www.cbbain.com/Pages/OfficeDetai...",
    "wof:name":"Coldwell Banker Bain",
    "wof:placetype":"venue"
},
  "geometry": {"coordinates":[-122.34099500000001,47.63129],"type":"Point"}
}