{
  "type": "Feature",
  "properties": {
    "addr:full":"8613 N Hill N Dale St Spokane WA 99208",
    "addr:housenumber":"8613",
    "addr:postcode":"99208",
    "addr:street":"N Hill N Dale St",
    "iso:country":"US",
    "sg:address":"8613 N Hill N Dale St",
    "sg:city":"Spokane",
    "sg:classifiers":[
        {
            "category":"Professional",
            "subcategory":"Management & Consulting",
            "type":"Services"
        }
    ],
    "sg:phone":"+1 509 467 7546",
    "sg:postcode":"99208",
    "sg:province":"WA",
    "sg:tags":[
        "retail",
        "direct",
        "sales"
    ],
    "wof:name":"A & J Associates",
    "wof:placetype":"venue"
},
  "geometry": {"coordinates":[-117.406122,47.73663],"type":"Point"}
}