{
  "type": "Feature",
  "properties": {
    "addr:full":"1083 E Pickering Rd Shelton WA 98584",
    "addr:housenumber":"1083",
    "addr:postcode":"98584",
    "addr:street":"E Pickering Rd",
    "iso:country":"US",
    "sg:address":"1083 E Pickering Rd",
    "sg:city":"Shelton",
    "sg:classifiers":[
        {
            "category":"Food & Beverages",
            "subcategory":"Groceries & Convenience Stores",
            "type":"Retail Goods"
        }
    ],
    "sg:phone":"+1 360 426 1901",
    "sg:postcode":"98584",
    "sg:province":"WA",
    "sg:tags":[
        "station",
        "gasoline"
    ],
    "wof:name":"Spencer Lake Grocery",
    "wof:placetype":"venue"
},
  "geometry": {"coordinates":[-122.950952,47.270873],"type":"Point"}
}