{
  "type": "Feature",
  "properties": {
    "addr:full":"11412 8th St E Edgewood WA 98372",
    "addr:housenumber":"11412",
    "addr:postcode":"98372",
    "addr:street":"8Th St E",
    "iso:country":"US",
    "sg:address":"11412 8th St E",
    "sg:city":"Edgewood",
    "sg:classifiers":[
        {
            "category":"Retail",
            "subcategory":"Laundry & Dry Cleaning",
            "type":"Services"
        }
    ],
    "sg:phone":"+1 253 927 4496",
    "sg:postcode":"98372",
    "sg:province":"WA",
    "sg:tags":[
        "cleaner",
        "rug",
        "carpet"
    ],
    "wof:name":"Chem-Dry",
    "wof:placetype":"venue"
},
  "geometry": {"coordinates":[-122.27681,47.250031],"type":"Point"}
}