{
  "type": "Feature",
  "properties": {
    "addr:full":"40605 NE Dobler Hill Rd La Center WA 98629",
    "addr:housenumber":"40605",
    "addr:postcode":"98629",
    "addr:street":"Ne Dobler Hill Rd",
    "iso:country":"US",
    "sg:address":"40605 NE Dobler Hill Rd",
    "sg:city":"La Center",
    "sg:classifiers":[
        {
            "category":"Retail",
            "subcategory":"Auto Repair",
            "type":"Services"
        }
    ],
    "sg:phone":"+1 360 263 2810",
    "sg:postcode":"98629",
    "sg:province":"WA",
    "sg:tags":[
        "exhaust"
    ],
    "wof:name":"Cluch Clinic",
    "wof:placetype":"venue"
},
  "geometry": {"coordinates":[-122.62368600000001,45.914525],"type":"Point"}
}