{
  "type": "Feature",
  "properties": {
    "addr:full":"30649 52nd Ave S Auburn WA 98001",
    "addr:housenumber":"30649",
    "addr:postcode":"98001",
    "addr:street":"52Nd Ave S",
    "iso:country":"US",
    "sg:address":"30649 52nd Ave S",
    "sg:city":"Auburn",
    "sg:classifiers":[
        {
            "category":"Building & Trades",
            "subcategory":"Construction",
            "type":"Services"
        }
    ],
    "sg:phone":"+1 253 939 1255",
    "sg:postcode":"98001",
    "sg:province":"WA",
    "sg:tags":[
        "residential"
    ],
    "wof:name":"Craiger Development Inc",
    "wof:placetype":"venue"
},
  "geometry": {"coordinates":[-122.26995599999999,47.327512],"type":"Point"}
}