{
  "type": "Feature",
  "properties": {
    "addr:full":"10407 E Sprague Ave Spokane WA 99206",
    "addr:housenumber":"10407",
    "addr:postcode":"99206",
    "addr:street":"E Sprague Ave",
    "iso:country":"US",
    "sg:address":"10407 E Sprague Ave",
    "sg:city":"Spokane",
    "sg:classifiers":[
        {
            "category":"Restaurant",
            "type":"Food & Drink"
        }
    ],
    "sg:menulink":"http://www.allmenus.com/wa/spokane/165918-arbys/menu/",
    "sg:phone":"+1 509 924 3811",
    "sg:postcode":"99206",
    "sg:province":"WA",
    "sg:tags":[
        "burger",
        "american"
    ],
    "wof:name":"Arby's",
    "wof:placetype":"venue"
},
  "geometry": {"coordinates":[-117.26502600000001,47.657499],"type":"Point"}
}