{
  "type": "Feature",
  "properties": {
    "addr:full":"13730 32nd Ave NE Seattle WA 98125",
    "addr:housenumber":"13730",
    "addr:postcode":"98125",
    "addr:street":"32Nd Ave Ne",
    "iso:country":"US",
    "sg:address":"13730 32nd Ave NE",
    "sg:city":"Seattle",
    "sg:classifiers":[
        {
            "category":"Personal",
            "type":"Services"
        }
    ],
    "sg:phone":"+1 206 364 1579",
    "sg:postcode":"98125",
    "sg:province":"WA",
    "sg:tags":[
        "towing"
    ],
    "wof:name":"Bob's Crown Hill Towing",
    "wof:placetype":"venue"
},
  "geometry": {"coordinates":[-122.29299899999999,47.728401],"type":"Point"}
}