{
  "type": "Feature",
  "properties": {
    "addr:full":"609 S Main St Seattle WA 98104",
    "addr:housenumber":"609",
    "addr:postcode":"98104",
    "addr:street":"S Main St",
    "iso:country":"US",
    "sg:address":"609 S Main St",
    "sg:city":"Seattle",
    "sg:classifiers":[
        {
            "category":"Shopping",
            "subcategory":"Pharmacy",
            "type":"Retail Goods"
        }
    ],
    "sg:phone":"+1 206 624 7098",
    "sg:postcode":"98104",
    "sg:province":"WA",
    "wof:name":"Tokuda United Drug",
    "wof:placetype":"venue"
},
  "geometry": {"coordinates":[-122.32520100000001,47.599953],"type":"Point"}
}