{
  "type": "Feature",
  "properties": {
    "iso:country":"US",
    "sg:address":"22833 Bothell Way NE",
    "sg:city":"Bothell",
    "sg:classifiers":[
        {
            "category":"Personal",
            "subcategory":"Beauty Salon",
            "type":"Services"
        }
    ],
    "sg:phone":"+1 425 487 1480",
    "sg:postcode":"98011",
    "sg:province":"WA",
    "sg:tags":[
        "shop"
    ],
    "wof:name":"Paradise Bay",
    "wof:placetype":"venue"
},
  "geometry": {"coordinates":[-122.215952,47.772959],"type":"Point"}
}