{
  "type": "Feature",
  "properties": {
    "addr:full":"1100 E Columbia St Pasco WA 99301",
    "addr:housenumber":"1100",
    "addr:postcode":"99301",
    "addr:street":"E Columbia St",
    "iso:country":"US",
    "sg:address":"1100 E Columbia St",
    "sg:city":"Pasco",
    "sg:classifiers":[
        {
            "category":"Professional",
            "subcategory":"Business Services",
            "type":"Services"
        }
    ],
    "sg:phone":"+1 509 542 9349",
    "sg:postcode":"99301",
    "sg:province":"WA",
    "wof:name":"Nationwide Wholesale Brokers",
    "wof:placetype":"venue"
},
  "geometry": {"coordinates":[-119.080783,46.232067],"type":"Point"}
}