{
  "type": "Feature",
  "properties": {
    "addr:full":"15 Gossett Rd Port Angeles WA 98363",
    "addr:housenumber":"15",
    "addr:postcode":"98363",
    "addr:street":"Gossett Rd",
    "iso:country":"US",
    "sg:address":"15 Gossett Rd",
    "sg:city":"Port Angeles",
    "sg:classifiers":[
        {
            "category":"Professional",
            "type":"Services"
        }
    ],
    "sg:phone":"+1 360 928 3205",
    "sg:postcode":"98363",
    "sg:province":"WA",
    "wof:name":"Myrtle and John Gossett C",
    "wof:placetype":"venue"
},
  "geometry": {"coordinates":[-123.786154,48.13976],"type":"Point"}
}