{
  "type": "Feature",
  "properties": {
    "iso:country":"US",
    "sg:address":"2380 Bellevue Way SE",
    "sg:city":"Bellevue",
    "sg:classifiers":[
        {
            "category":"Food & Beverages",
            "subcategory":"Groceries & Convenience Stores",
            "type":"Retail Goods"
        }
    ],
    "sg:phone":"+1 425 467 0501",
    "sg:postcode":"98004",
    "sg:province":"WA",
    "sg:tags":[
        "market"
    ],
    "wof:name":"Bill Pace Fruit & Produce",
    "wof:placetype":"venue"
},
  "geometry": {"coordinates":[-122.18841399999999,47.579563],"type":"Point"}
}