{
  "type": "Feature",
  "properties": {
    "addr:full":"12003 184th Ave NE Redmond WA 98052",
    "addr:housenumber":"12003",
    "addr:postcode":"98052",
    "addr:street":"184Th Ave Ne",
    "iso:country":"US",
    "sg:address":"12003 184th Ave NE",
    "sg:city":"Redmond",
    "sg:classifiers":[
        {
            "category":"Building & Trades",
            "subcategory":"Landscaping Services",
            "type":"Services"
        }
    ],
    "sg:phone":"+1 425 556 4440",
    "sg:postcode":"98052",
    "sg:province":"WA",
    "sg:tags":[
        "consultant",
        "lawn",
        "designer",
        "landscape"
    ],
    "wof:name":"New Horizons",
    "wof:placetype":"venue"
},
  "geometry": {"coordinates":[-122.094995,47.703895],"type":"Point"}
}