{
  "type": "Feature",
  "properties": {
    "addr:full":"1808 E Union St Seattle WA 98122",
    "addr:housenumber":"1808",
    "addr:postcode":"98122",
    "addr:street":"E Union St",
    "iso:country":"US",
    "sg:address":"1808 E Union St",
    "sg:city":"Seattle",
    "sg:classifiers":[
        {
            "category":"Health Services",
            "subcategory":"Health Practitioner",
            "type":"Services"
        }
    ],
    "sg:phone":"+1 206 328 2651",
    "sg:postcode":"98122",
    "sg:province":"WA",
    "wof:name":"Patricia Moroney MA CCC",
    "wof:placetype":"venue"
},
  "geometry": {"coordinates":[-122.307581,47.612971],"type":"Point"}
}