{
  "type": "Feature",
  "properties": {
    "addr:full":"255 Ellingson Dr Pacific WA 98047",
    "addr:housenumber":"255",
    "addr:postcode":"98047",
    "addr:street":"Ellingson Dr",
    "iso:country":"US",
    "sg:address":"255 Ellingson Dr",
    "sg:city":"Pacific",
    "sg:classifiers":[
        {
            "category":"Education",
            "subcategory":"Library",
            "type":"Public Place"
        }
    ],
    "sg:phone":"+1 253 833 3554",
    "sg:postcode":"98047",
    "sg:province":"WA",
    "wof:name":"Library Systems",
    "wof:placetype":"venue"
},
  "geometry": {"coordinates":[-122.233867,47.271475],"type":"Point"}
}