{
  "type": "Feature",
  "properties": {
    "addr:full":"1300 S 359th St Federal Way WA 98003",
    "addr:housenumber":"1300",
    "addr:postcode":"98003",
    "addr:street":"S 359Th St",
    "iso:country":"US",
    "sg:address":"1300 S 359th St",
    "sg:city":"Federal Way",
    "sg:classifiers":[
        {
            "category":"Building & Trades",
            "subcategory":"Landscaping Services",
            "type":"Services"
        }
    ],
    "sg:phone":"+1 253 838 8033",
    "sg:postcode":"98003",
    "sg:province":"WA",
    "sg:tags":[
        "landscape",
        "contractor"
    ],
    "wof:name":"Anderson Landscape Svc",
    "wof:placetype":"venue"
},
  "geometry": {"coordinates":[-122.317176,47.279988],"type":"Point"}
}