{
  "type": "Feature",
  "properties": {
    "addr:full":"152 Ioka Rd Sequim WA 98382",
    "addr:housenumber":"152",
    "addr:postcode":"98382",
    "addr:street":"Ioka Rd",
    "iso:country":"US",
    "sg:address":"152 Ioka Rd",
    "sg:city":"Sequim",
    "sg:classifiers":[
        {
            "category":"Manufacturing",
            "subcategory":"Wood Products",
            "type":"Manufacturing & Wholesale Goods"
        }
    ],
    "sg:phone":"+1 360 681 0342",
    "sg:postcode":"98382",
    "sg:province":"WA",
    "sg:tags":[
        "mfg"
    ],
    "wof:name":"J & K Woodworks",
    "wof:placetype":"venue"
},
  "geometry": {"coordinates":[-123.10092400000001,48.100136],"type":"Point"}
}