{
  "type": "Feature",
  "properties": {
    "iso:country":"US",
    "sg:address":"5301 E Broadway Ave",
    "sg:city":"Spokane Valley",
    "sg:classifiers":[
        {
            "category":"Wholesale",
            "subcategory":"Motor Vehicles",
            "type":"Manufacturing & Wholesale Goods"
        }
    ],
    "sg:phone":"+1 509 535 0363",
    "sg:postcode":"99212",
    "sg:province":"WA",
    "sg:tags":[
        "body",
        "equipment",
        "truck"
    ],
    "wof:name":"Washington Auto Carriage",
    "wof:placetype":"venue"
},
  "geometry": {"coordinates":[-117.329401,47.664379],"type":"Point"}
}