{
  "type": "Feature",
  "properties": {
    "addr:full":"1200 5th Ave Ste 1900 Seattle WA 98101",
    "addr:housenumber":"1200",
    "addr:postcode":"98101",
    "addr:street":"5Th Ave Ste 1900",
    "iso:country":"US",
    "sg:address":"1200 5th Ave Ste 1900",
    "sg:city":"Seattle",
    "sg:classifiers":[
        {
            "category":"Professional",
            "subcategory":"Lawyer & Legal Services",
            "type":"Services"
        }
    ],
    "sg:phone":"+1 206 346 1750",
    "sg:postcode":"98101",
    "sg:province":"WA",
    "wof:name":"Sandler Michael D Atty",
    "wof:placetype":"venue"
},
  "geometry": {"coordinates":[-122.333,47.610401],"type":"Point"}
}