{
  "type": "Feature",
  "properties": {
    "addr:full":"5819 W Clearwater Ave Kennewick WA 99336",
    "addr:housenumber":"5819",
    "addr:postcode":"99336",
    "addr:street":"W Clearwater Ave",
    "iso:country":"US",
    "sg:address":"5819 W Clearwater Ave",
    "sg:city":"Kennewick",
    "sg:classifiers":[
        {
            "category":"Autos & Motor Vehicles",
            "subcategory":"Auto Supplies",
            "type":"Retail Goods"
        },
        {
            "category":"Wholesale",
            "subcategory":"Auto Parts",
            "type":"Manufacturing & Wholesale Goods"
        }
    ],
    "sg:phone":"+1 509 783 1892",
    "sg:postcode":"99336",
    "sg:province":"WA",
    "sg:tags":[
        "automobile"
    ],
    "wof:name":"Clearwater NAPA",
    "wof:placetype":"venue"
},
  "geometry": {"coordinates":[-119.20099,46.212363],"type":"Point"}
}