{
  "type": "Feature",
  "properties": {
    "addr:full":"1706 W Main St Battle Ground WA 98604",
    "addr:housenumber":"1706",
    "addr:postcode":"98604",
    "addr:street":"W Main St",
    "iso:country":"US",
    "sg:address":"1706 W Main St",
    "sg:city":"Battle Ground",
    "sg:classifiers":[
        {
            "category":"Personal",
            "subcategory":"Barber",
            "type":"Services"
        }
    ],
    "sg:phone":"+1 360 687 0182",
    "sg:postcode":"98604",
    "sg:province":"WA",
    "sg:tags":[
        "shop"
    ],
    "wof:name":"Melodies Salone",
    "wof:placetype":"venue"
},
  "geometry": {"coordinates":[-122.554452,45.78071],"type":"Point"}
}