{
  "type": "Feature",
  "properties": {
    "addr:full":"403 E Runnion Rd Sequim WA 98382",
    "addr:housenumber":"403",
    "addr:postcode":"98382",
    "addr:street":"E Runnion Rd",
    "iso:country":"US",
    "sg:address":"403 E Runnion Rd",
    "sg:city":"Sequim",
    "sg:classifiers":[
        {
            "category":"Shopping",
            "subcategory":"Florist",
            "type":"Retail Goods"
        }
    ],
    "sg:phone":"+1 360 683 6901",
    "sg:postcode":"98382",
    "sg:province":"WA",
    "wof:name":"Wood N Flowers",
    "wof:placetype":"venue"
},
  "geometry": {"coordinates":[-123.16240500000001,48.087071],"type":"Point"}
}