{
  "type": "Feature",
  "properties": {
    "iso:country":"US",
    "sg:address":"1420 E Fern St",
    "sg:city":"Othello",
    "sg:classifiers":[
        {
            "category":"Farming",
            "subcategory":"Farm",
            "type":"Manufacturing & Wholesale Goods"
        }
    ],
    "sg:phone":"+1 509 488 2484",
    "sg:postcode":"99344",
    "sg:province":"WA",
    "wof:name":"Oasis Trucking",
    "wof:placetype":"venue"
},
  "geometry": {"coordinates":[-119.15420899999999,46.822619],"type":"Point"}
}