{
  "type": "Feature",
  "properties": {
    "addr:full":"504 E Dayton Ave Dayton WA 99328",
    "addr:housenumber":"504",
    "addr:postcode":"99328",
    "addr:street":"E Dayton Ave",
    "iso:country":"US",
    "sg:address":"504 E Dayton Ave",
    "sg:city":"Dayton",
    "sg:classifiers":[
        {
            "category":"Retail",
            "subcategory":"Repair Shop",
            "type":"Services"
        }
    ],
    "sg:phone":"+1 509 382 2813",
    "sg:postcode":"99328",
    "sg:province":"WA",
    "wof:name":"Trails End Taxidermy",
    "wof:placetype":"venue"
},
  "geometry": {"coordinates":[-117.978371,46.32611],"type":"Point"}
}