{
  "type": "Feature",
  "properties": {
    "addr:full":"8537 15th Ave NW Seattle WA 98117",
    "addr:housenumber":"8537",
    "addr:postcode":"98117",
    "addr:street":"15Th Ave Nw",
    "iso:country":"US",
    "sg:address":"8537 15th Ave NW",
    "sg:city":"Seattle",
    "sg:classifiers":[
        {
            "category":"Food & Beverages",
            "subcategory":"Bakery",
            "type":"Retail Goods"
        }
    ],
    "sg:phone":"+1 206 784 6616",
    "sg:postcode":"98117",
    "sg:province":"WA",
    "wof:name":"Scandinavian Bakery",
    "wof:placetype":"venue"
},
  "geometry": {"coordinates":[-122.376879,47.692097],"type":"Point"}
}