{
  "type": "Feature",
  "properties": {
    "iso:country":"US",
    "sg:address":"6619 240th Way NE",
    "sg:city":"Redmond",
    "sg:classifiers":[
        {
            "category":"Professional",
            "subcategory":"Management & Consulting",
            "type":"Services"
        }
    ],
    "sg:phone":"+1 425 836 8455",
    "sg:postcode":"98053",
    "sg:province":"WA",
    "sg:tags":[
        "business"
    ],
    "wof:name":"Hc Solutions",
    "wof:placetype":"venue"
},
  "geometry": {"coordinates":[-122.016445,47.665239],"type":"Point"}
}