{
  "type": "Feature",
  "properties": {
    "addr:full":"513 S 1st St Yakima WA 98901",
    "addr:housenumber":"513",
    "addr:postcode":"98901",
    "addr:street":"S 1St St",
    "iso:country":"US",
    "sg:address":"513 S 1st St",
    "sg:city":"Yakima",
    "sg:classifiers":[
        {
            "category":"Home & Garden",
            "subcategory":"Garden Supply",
            "type":"Retail Goods"
        },
        {
            "category":"Autos & Motor Vehicles",
            "subcategory":"Motorcycle Sales",
            "type":"Retail Goods"
        }
    ],
    "sg:phone":"+1 509 452 7493",
    "sg:postcode":"98901",
    "sg:province":"WA",
    "sg:tags":[
        "lawn",
        "scooters-parts",
        "mower"
    ],
    "sg:website":"http://www.poulinsmotorcycle.hondamcdealers.com",
    "wof:name":"Poulin's Honda Motorcycle Dealership",
    "wof:placetype":"venue"
},
  "geometry": {"coordinates":[-120.503015,46.595805],"type":"Point"}
}