{
  "type": "Feature",
  "properties": {
    "addr:full":"1807 211th Pl NE Sammamish WA 98074",
    "addr:housenumber":"1807",
    "addr:postcode":"98074",
    "addr:street":"211Th Pl Ne",
    "iso:country":"US",
    "sg:address":"1807 211th Pl NE",
    "sg:city":"Sammamish",
    "sg:classifiers":[
        {
            "category":"Shopping",
            "subcategory":"Crafts & Fabrics",
            "type":"Retail Goods"
        }
    ],
    "sg:phone":"+1 425 868 7370",
    "sg:postcode":"98074",
    "sg:province":"WA",
    "sg:tags":[
        "sewing"
    ],
    "wof:name":"Simply Sew",
    "wof:placetype":"venue"
},
  "geometry": {"coordinates":[-122.058125,47.62692],"type":"Point"}
}