{
  "type": "Feature",
  "properties": {
    "addr:full":"835 Rd Q NE Moses Lake WA 98837",
    "addr:housenumber":"835",
    "addr:postcode":"98837",
    "addr:street":"Rd Q Ne",
    "iso:country":"US",
    "sg:address":"835 Rd Q NE",
    "sg:city":"Moses Lake",
    "sg:classifiers":[
        {
            "category":"Farming",
            "subcategory":"Livestock Farm",
            "type":"Manufacturing & Wholesale Goods"
        }
    ],
    "sg:phone":"+1 509 765 4084",
    "sg:postcode":"98837",
    "sg:province":"WA",
    "sg:tags":[
        "animal",
        "general"
    ],
    "wof:name":"Vincent Farms Inc",
    "wof:placetype":"venue"
},
  "geometry": {"coordinates":[-119.129299,47.103235],"type":"Point"}
}