{
  "type": "Feature",
  "properties": {
    "addr:full":"405 N 45th St Seattle WA 98103",
    "addr:housenumber":"405",
    "addr:postcode":"98103",
    "addr:street":"N 45Th St",
    "iso:country":"US",
    "sg:address":"405 N 45th St",
    "sg:city":"Seattle",
    "sg:classifiers":[
        {
            "category":"Building & Trades",
            "subcategory":"Locksmith",
            "type":"Services"
        }
    ],
    "sg:phone":"+1 206 701 8555",
    "sg:postcode":"98103",
    "sg:province":"WA",
    "sg:tags":[
        "key"
    ],
    "wof:name":"Locksmith Emergency",
    "wof:placetype":"venue"
},
  "geometry": {"coordinates":[-122.353791,47.661267],"type":"Point"}
}