{
  "type": "Feature",
  "properties": {
    "addr:full":"16528 Cleveland St Redmond WA 98052",
    "addr:housenumber":"16528",
    "addr:postcode":"98052",
    "addr:street":"Cleveland St",
    "iso:country":"US",
    "sg:address":"16528 Cleveland St",
    "sg:city":"Redmond",
    "sg:classifiers":[
        {
            "category":"Personal",
            "type":"Services"
        }
    ],
    "sg:phone":"+1 425 882 0323",
    "sg:postcode":"98052",
    "sg:province":"WA",
    "sg:tags":[
        "formal",
        "retail",
        "wear",
        "rent"
    ],
    "wof:name":"Tux Shop 106 The",
    "wof:placetype":"venue"
},
  "geometry": {"coordinates":[-122.120406,47.672637],"type":"Point"}
}