{
  "type": "Feature",
  "properties": {
    "addr:full":"3850 Meridian Ave N Seattle WA 98103",
    "addr:housenumber":"3850",
    "addr:postcode":"98103",
    "addr:street":"Meridian Ave N",
    "iso:country":"US",
    "sg:address":"3850 Meridian Ave N",
    "sg:city":"Seattle",
    "sg:classifiers":[
        {
            "category":"Retail",
            "subcategory":"Self-service Laundry",
            "type":"Services"
        }
    ],
    "sg:phone":"+1 253 848 8834",
    "sg:postcode":"98103",
    "sg:province":"WA",
    "sg:tags":[
        "coin"
    ],
    "wof:name":"Puyallup South Hill Laundromat",
    "wof:placetype":"venue"
},
  "geometry": {"coordinates":[-122.333771,47.653711],"type":"Point"}
}