{
  "type": "Feature",
  "properties": {
    "addr:full":"3231 Perry Ave Bremerton WA 98310",
    "addr:housenumber":"3231",
    "addr:postcode":"98310",
    "addr:street":"Perry Ave",
    "iso:country":"US",
    "sg:address":"3231 Perry Ave",
    "sg:city":"Bremerton",
    "sg:classifiers":[
        {
            "category":"Shopping",
            "subcategory":"Used Merchandise",
            "type":"Retail Goods"
        }
    ],
    "sg:phone":"+1 360 377 4523",
    "sg:postcode":"98310",
    "sg:province":"WA",
    "wof:name":"Perry Mall Antique",
    "wof:placetype":"venue"
},
  "geometry": {"coordinates":[-122.613461,47.5929],"type":"Point"}
}