{
  "type": "Feature",
  "properties": {
    "addr:full":"104 SE 101st Ave Vancouver WA 98664",
    "addr:housenumber":"104",
    "addr:postcode":"98664",
    "addr:street":"Se 101St Ave",
    "iso:country":"US",
    "sg:address":"104 SE 101st Ave",
    "sg:city":"Vancouver",
    "sg:classifiers":[
        {
            "category":"Professional",
            "subcategory":"Management & Consulting",
            "type":"Services"
        }
    ],
    "sg:phone":"+1 360 608 7808",
    "sg:postcode":"98664",
    "sg:province":"WA",
    "wof:name":"Metana Realty Services",
    "wof:placetype":"venue"
},
  "geometry": {"coordinates":[-122.569326,45.61818],"type":"Point"}
}