{
  "type": "Feature",
  "properties": {
    "addr:full":"33103 Pacific St Black Diamond WA 98010",
    "addr:housenumber":"33103",
    "addr:postcode":"98010",
    "addr:street":"Pacific St",
    "iso:country":"US",
    "sg:address":"33103 Pacific St",
    "sg:city":"Black Diamond",
    "sg:classifiers":[
        {
            "category":"Professional",
            "subcategory":"Computer Services",
            "type":"Services"
        }
    ],
    "sg:phone":"+1 360 886 0801",
    "sg:postcode":"98010",
    "sg:province":"WA",
    "sg:tags":[
        "design",
        "system"
    ],
    "wof:name":"Silver Eagle Treasures",
    "wof:placetype":"venue"
},
  "geometry": {"coordinates":[-121.99847800000001,47.306603],"type":"Point"}
}