{
  "type": "Feature",
  "properties": {
    "addr:full":"6448 138th Ave NE Redmond WA 98052",
    "addr:housenumber":"6448",
    "addr:postcode":"98052",
    "addr:street":"138Th Ave Ne",
    "iso:country":"US",
    "sg:address":"6448 138th Ave NE",
    "sg:city":"Redmond",
    "sg:classifiers":[
        {
            "category":"Professional",
            "subcategory":"Management & Consulting",
            "type":"Services"
        }
    ],
    "sg:phone":"+1 425 881 8998",
    "sg:postcode":"98052",
    "sg:province":"WA",
    "sg:tags":[
        "science",
        "consultant",
        "academic"
    ],
    "wof:name":"Jackson, John Scott Consultant",
    "wof:placetype":"venue"
},
  "geometry": {"coordinates":[-122.156885,47.663891],"type":"Point"}
}