{
  "type": "Feature",
  "properties": {
    "addr:full":"1701 E 44th St Tacoma WA 98404",
    "addr:housenumber":"1701",
    "addr:postcode":"98404",
    "addr:street":"E 44Th St",
    "iso:country":"US",
    "sg:address":"1701 E 44th St",
    "sg:city":"Tacoma",
    "sg:classifiers":[
        {
            "category":"Professional",
            "subcategory":"Management & Consulting",
            "type":"Services"
        }
    ],
    "sg:phone":"+1 253 475 6861",
    "sg:postcode":"98404",
    "sg:province":"WA",
    "sg:tags":[
        "planning",
        "consultant",
        "space",
        "facility"
    ],
    "wof:name":"International Place",
    "wof:placetype":"venue"
},
  "geometry": {"coordinates":[-122.406616,47.217522],"type":"Point"}
}