{
  "type": "Feature",
  "properties": {
    "addr:full":"1950 Alaskan Way Apt 327 Seattle WA 98101",
    "addr:housenumber":"1950;327",
    "addr:postcode":"98101",
    "addr:street":"Alaskan Way Apt",
    "iso:country":"US",
    "sg:address":"1950 Alaskan Way Apt 327",
    "sg:city":"Seattle",
    "sg:classifiers":[
        {
            "category":"Wholesale",
            "subcategory":"Computers",
            "type":"Manufacturing & Wholesale Goods"
        },
        {
            "category":"Professional",
            "subcategory":"Computer Services",
            "type":"Services"
        }
    ],
    "sg:phone":"+1 206 441 5165",
    "sg:postcode":"98101",
    "sg:province":"WA",
    "sg:tags":[
        "designer",
        "consultant",
        "cd-rom",
        "system",
        "equipment",
        "software"
    ],
    "wof:name":"Stepstone Technologies",
    "wof:placetype":"venue"
},
  "geometry": {"coordinates":[-122.345108,47.609291],"type":"Point"}
}