{
  "type": "Feature",
  "properties": {
    "addr:full":"400 E Evergreen Blvd Ste 224 Vancouver WA 98660",
    "addr:housenumber":"400",
    "addr:postcode":"98660",
    "addr:street":"E Evergreen Blvd Ste 224",
    "iso:country":"US",
    "sg:address":"400 E Evergreen Blvd Ste 224",
    "sg:city":"Vancouver",
    "sg:classifiers":[
        {
            "category":"Food & Beverages",
            "subcategory":"Meat & Fish",
            "type":"Retail Goods"
        }
    ],
    "sg:phone":"+1 360 693 6285",
    "sg:postcode":"98660",
    "sg:province":"WA",
    "sg:tags":[
        "seafood",
        "seafood-wholesale",
        "market"
    ],
    "sg:website":"http://www.intermec.com",
    "wof:name":"Hpn Technologies Inc",
    "wof:placetype":"venue"
},
  "geometry": {"coordinates":[-122.66836600000001,45.62874],"type":"Point"}
}