{
  "type": "Feature",
  "properties": {
    "addr:full":"3901 NE 4th Street Suite 103 Renton WA 98056",
    "addr:housenumber":"3901",
    "addr:postcode":"98056",
    "addr:street":"Ne 4Th Street Suite 103",
    "iso:country":"US",
    "sg:address":"3901 NE 4th Street Suite 103",
    "sg:city":"Renton",
    "sg:classifiers":[
        {
            "category":"Retail",
            "subcategory":"Veterinary Services",
            "type":"Services"
        }
    ],
    "sg:phone":"+1 425 255 5678",
    "sg:postcode":"98056",
    "sg:province":"WA",
    "sg:tags":[
        "veterinarian"
    ],
    "wof:name":"Value Pet Clinic Inc.",
    "wof:placetype":"venue"
},
  "geometry": {"coordinates":[-122.16686900000001,47.488591],"type":"Point"}
}