{
  "type": "Feature",
  "properties": {
    "addr:full":"404 Legion Way SE Olympia WA 98501",
    "addr:housenumber":"404",
    "addr:postcode":"98501",
    "addr:street":"Legion Way Se",
    "iso:country":"US",
    "sg:address":"404 Legion Way SE",
    "sg:city":"Olympia",
    "sg:classifiers":[
        {
            "category":"Social Services",
            "type":"Services"
        }
    ],
    "sg:phone":"+1 360 923 1884",
    "sg:postcode":"98501",
    "sg:province":"WA",
    "sg:tags":[
        "organization",
        "welfare"
    ],
    "wof:name":"Monarch Childrens Justice Ctr",
    "wof:placetype":"venue"
},
  "geometry": {"coordinates":[-122.89651600000001,47.043626],"type":"Point"}
}