{
  "type": "Feature",
  "properties": {
    "iso:country":"US",
    "sg:address":"29935 112th Ave SE",
    "sg:city":"Auburn",
    "sg:classifiers":[
        {
            "category":"Building & Trades",
            "subcategory":"Construction",
            "type":"Services"
        }
    ],
    "sg:phone":"+1 253 351 8904",
    "sg:postcode":"98092",
    "sg:province":"WA",
    "sg:tags":[
        "contractor"
    ],
    "wof:name":"Yns Roofing & Construction",
    "wof:placetype":"venue"
},
  "geometry": {"coordinates":[-122.192256,47.332609],"type":"Point"}
}