{
  "type": "Feature",
  "properties": {
    "iso:country":"US",
    "sg:address":"8900 NE St Johns Rd",
    "sg:city":"Vancouver",
    "sg:classifiers":[
        {
            "category":"Retail",
            "subcategory":"Auto Repair",
            "type":"Services"
        }
    ],
    "sg:phone":"+1 360 574 9178",
    "sg:postcode":"98665",
    "sg:province":"WA",
    "sg:tags":[
        "automotive"
    ],
    "wof:name":"Associated Divisions Services",
    "wof:placetype":"venue"
},
  "geometry": {"coordinates":[-122.620492,45.689613],"type":"Point"}
}