{
  "type": "Feature",
  "properties": {
    "addr:full":"7786 Stanley Rd NE Moses Lake WA 98837",
    "addr:housenumber":"7786",
    "addr:postcode":"98837",
    "addr:street":"Stanley Rd Ne",
    "iso:country":"US",
    "sg:address":"7786 Stanley Rd NE",
    "sg:city":"Moses Lake",
    "sg:classifiers":[
        {
            "category":"Retail",
            "subcategory":"Repair Shop",
            "type":"Services"
        }
    ],
    "sg:phone":"+1 509 765 9768",
    "sg:postcode":"98837",
    "sg:province":"WA",
    "wof:name":"J&R Cue Darts Repairs & M",
    "wof:placetype":"venue"
},
  "geometry": {"coordinates":[-119.32257300000001,47.140495],"type":"Point"}
}