{
  "type": "Feature",
  "properties": {
    "addr:full":"P.O. Box 2485, Vancouver Vancouver WA 98668",
    "addr:housenumber":"p.o. box 2485",
    "addr:postcode":"98668",
    "iso:country":"US",
    "sg:address":"P.O. Box 2485, Vancouver",
    "sg:city":"Vancouver",
    "sg:classifiers":[
        {
            "category":"Professional",
            "subcategory":"Computer Services",
            "type":"Services"
        }
    ],
    "sg:postcode":"98668",
    "sg:province":"WA",
    "sg:tags":[
        "commercial-real-estate",
        "real-estate",
        "commercial-brokers",
        "property-sales",
        "property-lease",
        "mortgage-loans",
        "brokerage-services"
    ],
    "sg:website":"http://www.cimls.com",
    "wof:name":"CIMLS.com",
    "wof:placetype":"venue"
},
  "geometry": {"coordinates":[-122.520347,45.801586],"type":"Point"}
}