{
  "type": "Feature",
  "properties": {
    "iso:country":"US",
    "sg:address":"730 1st St",
    "sg:city":"Newport",
    "sg:classifiers":[
        {
            "category":"Social Services",
            "type":"Services"
        }
    ],
    "sg:phone":"+1 509 447 2274",
    "sg:postcode":"99156",
    "sg:province":"WA",
    "sg:tags":[
        "crisis",
        "intervention"
    ],
    "wof:name":"Family Crisis Network",
    "wof:placetype":"venue"
},
  "geometry": {"coordinates":[-117.049425,48.181169],"type":"Point"}
}