{
  "type": "Feature",
  "properties": {
    "iso:country":"US",
    "sg:address":"4630 200th St SW",
    "sg:city":"Lynnwood",
    "sg:classifiers":[
        {
            "category":"Education",
            "subcategory":"Special Training",
            "type":"Public Place"
        }
    ],
    "sg:phone":"+1 425 771 5928",
    "sg:postcode":"98036",
    "sg:province":"WA",
    "sg:tags":[
        "program"
    ],
    "wof:name":"Washington Industrial Mgmt",
    "wof:placetype":"venue"
},
  "geometry": {"coordinates":[-122.29753599999999,47.817315],"type":"Point"}
}