{
  "type": "Feature",
  "properties": {
    "iso:country":"US",
    "sg:address":"1531 NW 31st Ave",
    "sg:city":"Camas",
    "sg:classifiers":[
        {
            "category":"Food & Beverages",
            "subcategory":"Groceries & Convenience Stores",
            "type":"Retail Goods"
        }
    ],
    "sg:phone":"+1 360 834 3257",
    "sg:postcode":"98607",
    "sg:province":"WA",
    "wof:name":"Market America",
    "wof:placetype":"venue"
},
  "geometry": {"coordinates":[-122.425996,45.602162],"type":"Point"}
}