{
  "type": "Feature",
  "properties": {
    "iso:country":"US",
    "sg:address":"8553 S 123rd Pl",
    "sg:city":"Seattle",
    "sg:classifiers":[
        {
            "category":"Wholesale",
            "subcategory":"Chemicals & Plastics",
            "type":"Manufacturing & Wholesale Goods"
        }
    ],
    "sg:phone":"+1 206 818 8052",
    "sg:postcode":"98178",
    "sg:province":"WA",
    "wof:name":"Marunabe Mercantile Trading Co",
    "wof:placetype":"venue"
},
  "geometry": {"coordinates":[-122.22360999999999,47.492409],"type":"Point"}
}