{
  "type": "Feature",
  "properties": {
    "addr:full":"709 W Blaine St Seattle WA 98119",
    "addr:housenumber":"709",
    "addr:postcode":"98119",
    "addr:street":"W Blaine St",
    "iso:country":"US",
    "sg:address":"709 W Blaine St",
    "sg:city":"Seattle",
    "sg:classifiers":[
        {
            "category":"Professional",
            "subcategory":"Business Services",
            "type":"Services"
        }
    ],
    "sg:phone":"+1 206 285 1708",
    "sg:postcode":"98119",
    "sg:province":"WA",
    "wof:name":"E Wulff Interior Design",
    "wof:placetype":"venue"
},
  "geometry": {"coordinates":[-122.366947,47.634727],"type":"Point"}
}