{
  "type": "Feature",
  "properties": {
    "addr:full":"1402 22nd St NE Auburn WA 98002",
    "addr:housenumber":"1402",
    "addr:postcode":"98002",
    "addr:street":"22Nd St Ne",
    "iso:country":"US",
    "sg:address":"1402 22nd St NE",
    "sg:city":"Auburn",
    "sg:classifiers":[
        {
            "category":"Real Estate",
            "subcategory":"Real Estate Operator",
            "type":"Services"
        }
    ],
    "sg:phone":"+1 253 833 7333",
    "sg:postcode":"98002",
    "sg:province":"WA",
    "sg:tags":[
        "mobile",
        "home",
        "park"
    ],
    "wof:name":"Goronkan Investments LLC",
    "wof:placetype":"venue"
},
  "geometry": {"coordinates":[-122.21232999999999,47.326376],"type":"Point"}
}