{
  "type": "Feature",
  "properties": {
    "addr:full":"5905 Evergreen Way Everett WA 98203",
    "addr:housenumber":"5905",
    "addr:postcode":"98203",
    "addr:street":"Evergreen Way",
    "iso:country":"US",
    "sg:address":"5905 Evergreen Way",
    "sg:city":"Everett",
    "sg:classifiers":[
        {
            "category":"Restaurant",
            "type":"Food & Drink"
        }
    ],
    "sg:menulink":"http://www.allmenus.com/wa/everett/164224-wienerschnitzel/menu/",
    "sg:phone":"+1 425 353 6363",
    "sg:postcode":"98203",
    "sg:province":"WA",
    "sg:tags":[
        "sandwich",
        "dog",
        "burger",
        "hot",
        "wrap",
        "american"
    ],
    "wof:name":"Wienerschnitzel",
    "wof:placetype":"venue"
},
  "geometry": {"coordinates":[-122.21622000000001,47.944276],"type":"Point"}
}