{
  "type": "Feature",
  "properties": {
    "addr:full":"503 2nd St SW Puyallup WA 98371",
    "addr:housenumber":"503",
    "addr:postcode":"98371",
    "addr:street":"2Nd St Sw",
    "iso:country":"US",
    "sg:address":"503 2nd St SW",
    "sg:city":"Puyallup",
    "sg:classifiers":[
        {
            "category":"Organizations",
            "subcategory":"Religious Organization",
            "type":"Services"
        }
    ],
    "sg:phone":"+1 253 845 5560",
    "sg:postcode":"98371",
    "sg:province":"WA",
    "sg:tags":[
        "church"
    ],
    "wof:name":"Community Of Christ",
    "wof:placetype":"venue"
},
  "geometry": {"coordinates":[-122.294968,47.187262],"type":"Point"}
}