{
  "type": "Feature",
  "properties": {
    "addr:full":"16021 NE 15th St Vancouver WA 98684",
    "addr:housenumber":"16021",
    "addr:postcode":"98684",
    "addr:street":"Ne 15Th St",
    "iso:country":"US",
    "sg:address":"16021 NE 15th St",
    "sg:city":"Vancouver",
    "sg:classifiers":[
        {
            "category":"Shopping",
            "subcategory":"Gifts & Souvenirs",
            "type":"Retail Goods"
        }
    ],
    "sg:phone":"+1 360 253 8353",
    "sg:postcode":"98684",
    "sg:province":"WA",
    "sg:tags":[
        "shop"
    ],
    "wof:name":"Hickory Farms Inc",
    "wof:placetype":"venue"
},
  "geometry": {"coordinates":[-122.508458,45.632861],"type":"Point"}
}