{
  "type": "Feature",
  "properties": {
    "addr:full":"121 Ginny Ln Ellensburg WA 98926",
    "addr:housenumber":"121",
    "addr:postcode":"98926",
    "addr:street":"Ginny Ln",
    "iso:country":"US",
    "sg:address":"121 Ginny Ln",
    "sg:city":"Ellensburg",
    "sg:classifiers":[
        {
            "category":"Professional",
            "subcategory":"Management & Consulting",
            "type":"Services"
        }
    ],
    "sg:phone":"+1 509 962 3017",
    "sg:postcode":"98926",
    "sg:province":"WA",
    "sg:tags":[
        "environmental"
    ],
    "wof:name":"Peats/Leap Consulting Services",
    "wof:placetype":"venue"
},
  "geometry": {"coordinates":[-120.59031299999999,46.9981],"type":"Point"}
}