{
  "type": "Feature",
  "properties": {
    "addr:full":"16605 Vashon Hwy SW Vashon WA 98070",
    "addr:housenumber":"16605",
    "addr:postcode":"98070",
    "addr:street":"Vashon Hwy Sw",
    "iso:country":"US",
    "sg:address":"16605 Vashon Hwy SW",
    "sg:city":"Vashon",
    "sg:classifiers":[
        {
            "category":"Professional",
            "subcategory":"Management & Consulting",
            "type":"Services"
        }
    ],
    "sg:phone":"+1 206 567 5062",
    "sg:postcode":"98070",
    "sg:province":"WA",
    "sg:tags":[
        "business"
    ],
    "wof:name":"Holly Jean Godard",
    "wof:placetype":"venue"
},
  "geometry": {"coordinates":[-122.46047299999999,47.457468],"type":"Point"}
}