{
  "type": "Feature",
  "properties": {
    "addr:full":"17885 Sam Bell Rd Bow WA 98232",
    "addr:housenumber":"17885",
    "addr:postcode":"98232",
    "addr:street":"Sam Bell Rd",
    "iso:country":"US",
    "sg:address":"17885 Sam Bell Rd",
    "sg:city":"Bow",
    "sg:classifiers":[
        {
            "category":"Building & Trades",
            "subcategory":"Electrical",
            "type":"Services"
        }
    ],
    "sg:phone":"+1 360 826 5160",
    "sg:postcode":"98232",
    "sg:province":"WA",
    "sg:tags":[
        "electric",
        "contractor"
    ],
    "wof:name":"Eagle Electric Co",
    "wof:placetype":"venue"
},
  "geometry": {"coordinates":[-122.359763,48.515435],"type":"Point"}
}