{
  "type": "Feature",
  "properties": {
    "addr:full":"422 W Main Ave Puyallup WA 98371",
    "addr:housenumber":"422",
    "addr:postcode":"98371",
    "addr:street":"W Main Ave",
    "iso:country":"US",
    "sg:address":"422 W Main Ave",
    "sg:city":"Puyallup",
    "sg:classifiers":[
        {
            "category":"Manufacturing",
            "subcategory":"Printing",
            "type":"Manufacturing & Wholesale Goods"
        }
    ],
    "sg:phone":"+1 253 848 5873",
    "sg:postcode":"98371",
    "sg:province":"WA",
    "sg:tags":[
        "book"
    ],
    "wof:name":"Fireball Publications",
    "wof:placetype":"venue"
},
  "geometry": {"coordinates":[-122.298794,47.191707],"type":"Point"}
}