{
  "type": "Feature",
  "properties": {
    "addr:full":"2821 W Northwest Blvd Spokane WA 99205",
    "addr:housenumber":"2821",
    "addr:postcode":"99205",
    "addr:street":"W Northwest Blvd",
    "iso:country":"US",
    "sg:address":"2821 W Northwest Blvd",
    "sg:city":"Spokane",
    "sg:classifiers":[
        {
            "category":"Organizations",
            "subcategory":"Religious Organization",
            "type":"Services"
        }
    ],
    "sg:phone":"+1 509 328 6001",
    "sg:postcode":"99205",
    "sg:province":"WA",
    "sg:tags":[
        "church"
    ],
    "wof:name":"Epic Life Four Square Church",
    "wof:placetype":"venue"
},
  "geometry": {"coordinates":[-117.45352,47.687153],"type":"Point"}
}