{
  "type": "Feature",
  "properties": {
    "addr:full":"1400 S Jackson St Ste 4 Seattle WA 98144",
    "addr:housenumber":"1400",
    "addr:postcode":"98144",
    "addr:street":"S Jackson St Ste 4",
    "iso:country":"US",
    "sg:address":"1400 S Jackson St Ste 4",
    "sg:city":"Seattle",
    "sg:classifiers":[
        {
            "category":"Farming",
            "subcategory":"Nursery",
            "type":"Manufacturing & Wholesale Goods"
        },
        {
            "category":"Shopping",
            "subcategory":"Florist",
            "type":"Retail Goods"
        }
    ],
    "sg:phone":"+1 206 325 6266",
    "sg:postcode":"98144",
    "sg:province":"WA",
    "sg:tags":[
        "tree",
        "nurseries-plants"
    ],
    "wof:name":"The Best Flowers On Jackson",
    "wof:placetype":"venue"
},
  "geometry": {"coordinates":[-122.31415800000001,47.599235],"type":"Point"}
}