{
  "type": "Feature",
  "properties": {
    "addr:full":"5107 NE 81st Ave Vancouver WA 98662",
    "addr:housenumber":"5107",
    "addr:postcode":"98662",
    "addr:street":"Ne 81St Ave",
    "iso:country":"US",
    "sg:address":"5107 NE 81st Ave",
    "sg:city":"Vancouver",
    "sg:classifiers":[
        {
            "category":"Banks & Credit Unions",
            "subcategory":"Bank",
            "type":"Services"
        }
    ],
    "sg:phone":"+1 360 882 7600",
    "sg:postcode":"98662",
    "sg:province":"WA",
    "sg:tags":[
        "financing"
    ],
    "wof:name":"N W Funding",
    "wof:placetype":"venue"
},
  "geometry": {"coordinates":[-122.590245,45.659698],"type":"Point"}
}