{
  "type": "Feature",
  "properties": {
    "addr:full":"411 N Havana St Spokane WA 99202",
    "addr:housenumber":"411",
    "addr:postcode":"99202",
    "addr:street":"N Havana St",
    "iso:country":"US",
    "sg:address":"411 N Havana St",
    "sg:city":"Spokane",
    "sg:phone":"+1 509 534 1581",
    "sg:postcode":"99202",
    "sg:province":"WA",
    "sg:tags":[
        "gas"
    ],
    "wof:name":"Northern Energy",
    "wof:placetype":"venue"
},
  "geometry": {"coordinates":[-117.346992,47.661614],"type":"Point"}
}