{
  "type": "Feature",
  "properties": {
    "addr:full":"22801 126th Pl SE Kent WA 98031",
    "addr:housenumber":"22801",
    "addr:postcode":"98031",
    "addr:street":"126Th Pl Se",
    "iso:country":"US",
    "sg:address":"22801 126th Pl SE",
    "sg:city":"Kent",
    "sg:classifiers":[
        {
            "category":"Home & Garden",
            "subcategory":"Home Furnishings",
            "type":"Retail Goods"
        }
    ],
    "sg:phone":"+1 253 332 4516",
    "sg:postcode":"98031",
    "sg:province":"WA",
    "wof:name":"Bill Meehan Pottery",
    "wof:placetype":"venue"
},
  "geometry": {"coordinates":[-122.17355000000001,47.396962],"type":"Point"}
}