{
  "type": "Feature",
  "properties": {
    "iso:country":"US",
    "sg:address":"1110 8th Ave",
    "sg:city":"Longview",
    "sg:classifiers":[
        {
            "category":"Building & Trades",
            "subcategory":"Construction",
            "type":"Services"
        }
    ],
    "sg:phone":"+1 360 636 3484",
    "sg:postcode":"98632",
    "sg:province":"WA",
    "sg:tags":[
        "painter"
    ],
    "wof:name":"R L Holmens",
    "wof:placetype":"venue"
},
  "geometry": {"coordinates":[-122.928552,46.133996],"type":"Point"}
}