{
  "type": "Feature",
  "properties": {
    "addr:full":"2201 NE 112th Ave Vancouver WA 98684",
    "addr:housenumber":"2201",
    "addr:postcode":"98684",
    "addr:street":"Ne 112Th Ave",
    "iso:country":"US",
    "sg:address":"2201 NE 112th Ave",
    "sg:city":"Vancouver",
    "sg:classifiers":[
        {
            "category":"Farming",
            "subcategory":"Nursery",
            "type":"Manufacturing & Wholesale Goods"
        }
    ],
    "sg:phone":"+1 360 892 9100",
    "sg:postcode":"98684",
    "sg:province":"WA",
    "sg:tags":[
        "ornamental",
        "food",
        "crop",
        "farm",
        "greenhouse",
        "covered"
    ],
    "wof:name":"R & L Greenhouses",
    "wof:placetype":"venue"
},
  "geometry": {"coordinates":[-122.557931,45.6392],"type":"Point"}
}