{
  "type": "Feature",
  "properties": {
    "addr:full":"9436 Rainier Ave S Seattle WA 98118",
    "addr:housenumber":"9436",
    "addr:postcode":"98118",
    "addr:street":"Rainier Ave S",
    "iso:country":"US",
    "sg:address":"9436 Rainier Ave S",
    "sg:city":"Seattle",
    "sg:classifiers":[
        {
            "category":"Banks & Credit Unions",
            "subcategory":"Financial Services",
            "type":"Services"
        }
    ],
    "sg:phone":"+1 206 725 7222",
    "sg:postcode":"98118",
    "sg:province":"WA",
    "sg:tags":[
        "cashing",
        "loan",
        "payday",
        "alternative",
        "check"
    ],
    "wof:name":"Quik Cash",
    "wof:placetype":"venue"
},
  "geometry": {"coordinates":[-122.264212,47.519956],"type":"Point"}
}