{
  "type": "Feature",
  "properties": {
    "addr:full":"7853 Dodson Rd N Ephrata WA 98823",
    "addr:housenumber":"7853",
    "addr:postcode":"98823",
    "addr:street":"Dodson Rd N",
    "iso:country":"US",
    "sg:address":"7853 Dodson Rd N",
    "sg:city":"Ephrata",
    "sg:phone":"+1 509 787 2852",
    "sg:postcode":"98823",
    "sg:province":"WA",
    "sg:tags":[
        "farm"
    ],
    "wof:name":"Lyndon Price",
    "wof:placetype":"venue"
},
  "geometry": {"coordinates":[-119.554224,47.198402],"type":"Point"}
}