{
  "type": "Feature",
  "properties": {
    "addr:full":"216 N Roosevelt St Walla Walla WA 99362",
    "addr:housenumber":"216",
    "addr:postcode":"99362",
    "addr:street":"N Roosevelt St",
    "iso:country":"US",
    "sg:address":"216 N Roosevelt St",
    "sg:city":"Walla Walla",
    "sg:classifiers":[
        {
            "category":"Health Services",
            "subcategory":"Chiropractor",
            "type":"Services"
        }
    ],
    "sg:phone":"+1 509 529 6200",
    "sg:postcode":"99362",
    "sg:province":"WA",
    "wof:name":"Johnston Chiropractic",
    "wof:placetype":"venue"
},
  "geometry": {"coordinates":[-118.312389,46.074776],"type":"Point"}
}