{
  "type": "Feature",
  "properties": {
    "addr:full":"416 Desert Aire Dr N Mattawa WA 99349",
    "addr:housenumber":"416",
    "addr:postcode":"99349",
    "addr:street":"Desert Aire Dr N",
    "iso:country":"US",
    "sg:address":"416 Desert Aire Dr N",
    "sg:city":"Mattawa",
    "sg:classifiers":[
        {
            "category":"Building & Trades",
            "subcategory":"Cleaning & Sanitation",
            "type":"Services"
        }
    ],
    "sg:phone":"+1 509 932 4752",
    "sg:postcode":"99349",
    "sg:province":"WA",
    "sg:tags":[
        "maintenance"
    ],
    "wof:name":"Violet Services",
    "wof:placetype":"venue"
},
  "geometry": {"coordinates":[-119.92978599999999,46.68362],"type":"Point"}
}