{
  "type": "Feature",
  "properties": {
    "addr:full":"1525 NW 59th St Seattle WA 98107",
    "addr:housenumber":"1525",
    "addr:postcode":"98107",
    "addr:street":"Nw 59Th St",
    "iso:country":"US",
    "sg:address":"1525 NW 59th St",
    "sg:city":"Seattle",
    "sg:classifiers":[
        {
            "category":"Professional",
            "subcategory":"Advertising",
            "type":"Services"
        }
    ],
    "sg:phone":"+1 206 328 5576",
    "sg:postcode":"98107",
    "sg:province":"WA",
    "sg:tags":[
        "counselor"
    ],
    "wof:name":"Duxbury-Lacey Design",
    "wof:placetype":"venue"
},
  "geometry": {"coordinates":[-122.378666,47.671556],"type":"Point"}
}