{
  "type": "Feature",
  "properties": {
    "addr:full":"8800 Imperial Way SW Port Orchard WA 98367",
    "addr:housenumber":"8800",
    "addr:postcode":"98367",
    "addr:street":"Imperial Way Sw Port Orchard",
    "iso:country":"US",
    "sg:address":"8800 Imperial Way SW",
    "sg:city":"Port Orchard",
    "sg:classifiers":[
        {
            "category":"Manufacturing",
            "subcategory":"Lumber",
            "type":"Manufacturing & Wholesale Goods"
        }
    ],
    "sg:phone":"+1 360 674 2700",
    "sg:postcode":"98367",
    "sg:province":"WA",
    "sg:tags":[
        "sawmill",
        "custom"
    ],
    "wof:name":"Pacific Western Timbers Inc",
    "wof:placetype":"venue"
},
  "geometry": {"coordinates":[-122.76653399999999,47.494653],"type":"Point"}
}