{
  "type": "Feature",
  "properties": {
    "addr:full":"22410 Benson Rd SE Kent WA 98031",
    "addr:housenumber":"22410",
    "addr:postcode":"98031",
    "addr:street":"Benson Rd Se",
    "iso:country":"US",
    "sg:address":"22410 Benson Rd SE",
    "sg:city":"Kent",
    "sg:classifiers":[
        {
            "category":"Health Services",
            "subcategory":"Nursing And Care Facility",
            "type":"Services"
        }
    ],
    "sg:phone":"+1 253 852 7755",
    "sg:postcode":"98031",
    "sg:province":"WA",
    "sg:tags":[
        "home",
        "convalescent"
    ],
    "wof:name":"Benson Heights Rehabilitation",
    "wof:placetype":"venue"
},
  "geometry": {"coordinates":[-122.200408,47.400863],"type":"Point"}
}