{
  "type": "Feature",
  "properties": {
    "addr:full":"6365 138th Pl SE Bellevue WA 98006",
    "addr:housenumber":"6365",
    "addr:postcode":"98006",
    "addr:street":"138Th Pl Se",
    "iso:country":"US",
    "sg:address":"6365 138th Pl SE",
    "sg:city":"Bellevue",
    "sg:classifiers":[
        {
            "category":"Real Estate",
            "subcategory":"Real Estate Agent",
            "type":"Services"
        }
    ],
    "sg:phone":"+1 425 746 5835",
    "sg:postcode":"98006",
    "sg:province":"WA",
    "wof:name":"L&R Management Group",
    "wof:placetype":"venue"
},
  "geometry": {"coordinates":[-122.15771700000001,47.546511],"type":"Point"}
}