{
  "type": "Feature",
  "properties": {
    "addr:full":"4140 Umptanum Rd Ellensburg WA 98926",
    "addr:housenumber":"4140",
    "addr:postcode":"98926",
    "addr:street":"Umptanum Rd",
    "iso:country":"US",
    "sg:address":"4140 Umptanum Rd",
    "sg:city":"Ellensburg",
    "sg:phone":"+1 509 925 1565",
    "sg:postcode":"98926",
    "sg:province":"WA",
    "sg:tags":[
        "farm",
        "field",
        "crop"
    ],
    "wof:name":"Kirk Riegel",
    "wof:placetype":"venue"
},
  "geometry": {"coordinates":[-120.569928,46.957293],"type":"Point"}
}