{
  "type": "Feature",
  "properties": {
    "iso:country":"US",
    "sg:address":"7512 Stanich Ln",
    "sg:city":"Gig Harbor",
    "sg:classifiers":[
        {
            "category":"Real Estate",
            "subcategory":"Real Estate Agent",
            "type":"Services"
        },
        {
            "category":"Professional",
            "subcategory":"Management & Consulting",
            "type":"Services"
        }
    ],
    "sg:phone":"+1 253 851 6060",
    "sg:postcode":"98335",
    "sg:province":"WA",
    "sg:website":"www.compasspropertymgmt.com",
    "wof:name":"Compass Property Management",
    "wof:placetype":"venue"
},
  "geometry": {"coordinates":[-122.58153299999999,47.327455],"type":"Point"}
}