{
  "type": "Feature",
  "properties": {
    "addr:full":"9312 W 10th Ave Kennewick WA 99336",
    "addr:housenumber":"9312",
    "addr:postcode":"99336",
    "addr:street":"W 10Th Ave",
    "iso:country":"US",
    "sg:address":"9312 W 10th Ave",
    "sg:city":"Kennewick",
    "sg:classifiers":[
        {
            "category":"Building & Trades",
            "subcategory":"Electrical",
            "type":"Services"
        }
    ],
    "sg:phone":"+1 509 627 5400",
    "sg:postcode":"99336",
    "sg:province":"WA",
    "sg:tags":[
        "electric",
        "contractor"
    ],
    "wof:name":"Sun River Electric Svc Inc",
    "wof:placetype":"venue"
},
  "geometry": {"coordinates":[-119.24593,46.20038],"type":"Point"}
}