{
  "type": "Feature",
  "properties": {
    "addr:full":"707 S Snoqualmie St Seattle WA 98108",
    "addr:housenumber":"707",
    "addr:postcode":"98108",
    "addr:street":"S Snoqualmie St",
    "iso:country":"US",
    "sg:address":"707 S Snoqualmie St",
    "sg:city":"Seattle",
    "sg:classifiers":[
        {
            "category":"Manufacturing",
            "subcategory":"Glass & Minerals",
            "type":"Manufacturing & Wholesale Goods"
        }
    ],
    "sg:phone":"+1 206 628 9320",
    "sg:postcode":"98108",
    "sg:province":"WA",
    "sg:tags":[
        "mfg"
    ],
    "wof:name":"Carberry Glass Works",
    "wof:placetype":"venue"
},
  "geometry": {"coordinates":[-122.323095,47.561941],"type":"Point"}
}