{
  "type": "Feature",
  "properties": {
    "iso:country":"US",
    "sg:address":"1606 SW 104th St",
    "sg:city":"Seattle",
    "sg:classifiers":[
        {
            "category":"Retail",
            "subcategory":"Auto Repair",
            "type":"Services"
        }
    ],
    "sg:phone":"+1 206 762 3443",
    "sg:postcode":"98146",
    "sg:province":"WA",
    "sg:tags":[
        "general"
    ],
    "wof:name":"Avid Auto Repair",
    "wof:placetype":"venue"
},
  "geometry": {"coordinates":[-122.35619199999999,47.510119],"type":"Point"}
}