{
  "type": "Feature",
  "properties": {
    "addr:full":"11818 NE 116th St Kirkland WA 98034",
    "addr:housenumber":"11818",
    "addr:postcode":"98034",
    "addr:street":"Ne 116Th St",
    "iso:country":"US",
    "sg:address":"11818 NE 116th St",
    "sg:city":"Kirkland",
    "sg:classifiers":[
        {
            "category":"Wholesale",
            "subcategory":"Construction Materials",
            "type":"Manufacturing & Wholesale Goods"
        }
    ],
    "sg:phone":"+1 425 820 2222",
    "sg:postcode":"98034",
    "sg:province":"WA",
    "wof:name":"American Interiors Inc",
    "wof:placetype":"venue"
},
  "geometry": {"coordinates":[-122.184217,47.704062],"type":"Point"}
}