{
  "type": "Feature",
  "properties": {
    "addr:full":"7037 132nd Ave NE Kirkland WA 98033",
    "addr:housenumber":"7037",
    "addr:postcode":"98033",
    "addr:street":"132Nd Ave Ne",
    "iso:country":"US",
    "sg:address":"7037 132nd Ave NE",
    "sg:city":"Kirkland",
    "sg:classifiers":[
        {
            "category":"Health Services",
            "subcategory":"Health Practitioner",
            "type":"Services"
        }
    ],
    "sg:phone":"+1 425 861 6688",
    "sg:postcode":"98033",
    "sg:province":"WA",
    "sg:tags":[
        "acupuncture"
    ],
    "wof:name":"Acupuncture & Chinese Herb Center",
    "wof:placetype":"venue"
},
  "geometry": {"coordinates":[-122.164001,47.666901],"type":"Point"}
}