{
  "type": "Feature",
  "properties": {
    "addr:full":"4932 NW Discovery Ridge Ct Silverdale WA 98383",
    "addr:housenumber":"4932",
    "addr:postcode":"98383",
    "addr:street":"Nw Discovery Ridge Ct",
    "iso:country":"US",
    "sg:address":"4932 NW Discovery Ridge Ct",
    "sg:city":"Silverdale",
    "sg:classifiers":[
        {
            "category":"Arts & Performance",
            "subcategory":"Theater",
            "type":"Entertainment"
        }
    ],
    "sg:phone":"+1 360 613 5161",
    "sg:postcode":"98383",
    "sg:province":"WA",
    "sg:tags":[
        "group"
    ],
    "wof:name":"Jam Production",
    "wof:placetype":"venue"
},
  "geometry": {"coordinates":[-122.71113800000001,47.650741],"type":"Point"}
}