{
  "type": "Feature",
  "properties": {
    "addr:full":"5115 NE 101st St Vancouver WA 98686",
    "addr:housenumber":"5115",
    "addr:postcode":"98686",
    "addr:street":"Ne 101St St",
    "iso:country":"US",
    "sg:address":"5115 NE 101st St",
    "sg:city":"Vancouver",
    "sg:classifiers":[
        {
            "category":"Professional",
            "subcategory":"Business Services",
            "type":"Services"
        }
    ],
    "sg:phone":"+1 360 891 0484",
    "sg:postcode":"98686",
    "sg:province":"WA",
    "sg:tags":[
        "company",
        "design",
        "mechanical"
    ],
    "wof:name":"McKune Design LLC",
    "wof:placetype":"venue"
},
  "geometry": {"coordinates":[-122.617278,45.694288],"type":"Point"}
}