{
  "type": "Feature",
  "properties": {
    "addr:full":"101 W Olympic Pl Seattle WA 98119",
    "addr:housenumber":"101",
    "addr:postcode":"98119",
    "addr:street":"W Olympic Pl",
    "iso:country":"US",
    "sg:address":"101 W Olympic Pl",
    "sg:city":"Seattle",
    "sg:classifiers":[
        {
            "category":"Retail",
            "subcategory":"Repair Shop",
            "type":"Services"
        }
    ],
    "sg:phone":"+1 206 524 3586",
    "sg:postcode":"98119",
    "sg:province":"WA",
    "sg:tags":[
        "watch",
        "jewelry"
    ],
    "wof:name":"About Time Watch & Jwly Repr",
    "wof:placetype":"venue"
},
  "geometry": {"coordinates":[-122.359308,47.626723],"type":"Point"}
}