{
  "type": "Feature",
  "properties": {
    "addr:full":"1813 NE 191st Cir Ridgefield WA 98642",
    "addr:housenumber":"1813",
    "addr:postcode":"98642",
    "addr:street":"Ne 191St Cir",
    "iso:country":"US",
    "sg:address":"1813 NE 191st Cir",
    "sg:city":"Ridgefield",
    "sg:classifiers":[
        {
            "category":"Education",
            "subcategory":"Dance Studio",
            "type":"Public Place"
        }
    ],
    "sg:phone":"+1 360 887 2141",
    "sg:postcode":"98642",
    "sg:province":"WA",
    "sg:tags":[
        "instruction",
        "dancing"
    ],
    "wof:name":"Delightful Dance",
    "wof:placetype":"venue"
},
  "geometry": {"coordinates":[-122.653137,45.759706],"type":"Point"}
}