{
  "type": "Feature",
  "properties": {
    "addr:full":"1132 N Arthur St Kennewick WA 99336",
    "addr:housenumber":"1132",
    "addr:postcode":"99336",
    "addr:street":"N Arthur St",
    "iso:country":"US",
    "sg:address":"1132 N Arthur St",
    "sg:city":"Kennewick",
    "sg:classifiers":[
        {
            "category":"Professional",
            "subcategory":"Computer Services",
            "type":"Services"
        }
    ],
    "sg:phone":"+1 509 783 4716",
    "sg:postcode":"99336",
    "sg:province":"WA",
    "sg:tags":[
        "automobile",
        "used",
        "datum"
    ],
    "wof:name":"Rognlyn Productions Inc",
    "wof:placetype":"venue"
},
  "geometry": {"coordinates":[-119.185585,46.22214],"type":"Point"}
}