{
  "type": "Feature",
  "properties": {
    "addr:full":"172 Upper Lakeview Rd Rd White Salmon WA 98651",
    "addr:housenumber":"172",
    "addr:postcode":"98651",
    "addr:street":"Upper Lakeview Rd Rd",
    "iso:country":"US",
    "sg:address":"172 Upper Lakeview Rd Rd",
    "sg:city":"White Salmon",
    "sg:classifiers":[
        {
            "category":"Retail",
            "subcategory":"Portrait Studio",
            "type":"Services"
        }
    ],
    "sg:phone":"+1 509 493 8670",
    "sg:postcode":"98651",
    "sg:province":"WA",
    "sg:tags":[
        "photo"
    ],
    "wof:name":"Laurie Black Photography",
    "wof:placetype":"venue"
},
  "geometry": {"coordinates":[-121.537824,45.775584],"type":"Point"}
}