{
  "type": "Feature",
  "properties": {
    "addr:full":"6820 Coal Creek Pkwy SE Renton WA 98059",
    "addr:housenumber":"6820",
    "addr:postcode":"98059",
    "addr:street":"Coal Creek Pkwy Se",
    "iso:country":"US",
    "sg:address":"6820 Coal Creek Pkwy SE",
    "sg:city":"Renton",
    "sg:classifiers":[
        {
            "category":"Building & Trades",
            "subcategory":"Construction",
            "type":"Services"
        }
    ],
    "sg:phone":"+1 206 919 1035",
    "sg:postcode":"98059",
    "sg:province":"WA",
    "sg:tags":[
        "ext",
        "painting",
        "contractor"
    ],
    "wof:name":"Morgan Painting Company",
    "wof:placetype":"venue"
},
  "geometry": {"coordinates":[-122.165792,47.538069],"type":"Point"}
}