{
  "type": "Feature",
  "properties": {
    "addr:full":"14710 Pacific Ave S Tacoma WA 98444",
    "addr:housenumber":"14710",
    "addr:postcode":"98444",
    "addr:street":"Pacific Ave S",
    "iso:country":"US",
    "sg:address":"14710 Pacific Ave S",
    "sg:city":"Tacoma",
    "sg:classifiers":[
        {
            "category":"Home & Garden",
            "subcategory":"Building Materials",
            "type":"Retail Goods"
        }
    ],
    "sg:phone":"+1 253 537 6400",
    "sg:postcode":"98444",
    "sg:province":"WA",
    "sg:tags":[
        "glass",
        "window",
        "plate"
    ],
    "wof:name":"Speedy Glass",
    "wof:placetype":"venue"
},
  "geometry": {"coordinates":[-122.434927,47.12339],"type":"Point"}
}