{
  "type": "Feature",
  "properties": {
    "addr:full":"3870 Bethel Rd SE Port Orchard WA 98366",
    "addr:housenumber":"3870",
    "addr:postcode":"98366",
    "addr:street":"Bethel Rd Se",
    "iso:country":"US",
    "sg:address":"3870 Bethel Rd SE",
    "sg:city":"Port Orchard",
    "sg:classifiers":[
        {
            "category":"Food & Beverages",
            "subcategory":"Meat & Fish",
            "type":"Retail Goods"
        }
    ],
    "sg:phone":"+1 360 876 3186",
    "sg:postcode":"98366",
    "sg:province":"WA",
    "wof:name":"Farmer George",
    "wof:placetype":"venue"
},
  "geometry": {"coordinates":[-122.63137,47.513436],"type":"Point"}
}