{
  "type": "Feature",
  "properties": {
    "addr:full":"3723 112th St SW Tacoma WA 98499",
    "addr:housenumber":"3723",
    "addr:postcode":"98499",
    "addr:street":"112Th St Sw",
    "iso:country":"US",
    "sg:address":"3723 112th St SW",
    "sg:city":"Tacoma",
    "sg:classifiers":[
        {
            "category":"Freight",
            "type":"Transportation"
        }
    ],
    "sg:phone":"+1 253 584 4300",
    "sg:postcode":"98499",
    "sg:province":"WA",
    "sg:tags":[
        "commercial",
        "storage"
    ],
    "wof:name":"Safe-Store Self Storage",
    "wof:placetype":"venue"
},
  "geometry": {"coordinates":[-122.48426000000001,47.155867],"type":"Point"}
}