{
  "type": "Feature",
  "properties": {
    "addr:full":"1527 Queen Anne Ave N Seattle WA 98109",
    "addr:housenumber":"1527",
    "addr:postcode":"98109",
    "addr:street":"Queen Anne Ave N",
    "iso:country":"US",
    "sg:address":"1527 Queen Anne Ave N",
    "sg:city":"Seattle",
    "sg:classifiers":[
        {
            "category":"Shopping",
            "subcategory":"Clothing, Apparel, & Fashions",
            "type":"Retail Goods"
        },
        {
            "category":"Arts & Performance",
            "subcategory":"Art Gallery",
            "type":"Entertainment"
        },
        {
            "category":"Shopping",
            "subcategory":"Jewelry",
            "type":"Retail Goods"
        },
        {
            "category":"Shopping",
            "subcategory":"Beauty & Cosmetics",
            "type":"Retail Goods"
        }
    ],
    "sg:phone":"+1 206 285 0707",
    "sg:postcode":"98109",
    "sg:province":"WA",
    "sg:tags":[
        "apparel",
        "women's",
        "clothing",
        "supply"
    ],
    "sg:website":"www.adelitastyle.com/",
    "wof:name":"Adelita",
    "wof:placetype":"venue"
},
  "geometry": {"coordinates":[-122.35696299999999,47.63266],"type":"Point"}
}