{
  "type": "Feature",
  "properties": {
    "addr:full":"2719 B St Washougal WA 98671",
    "addr:housenumber":"2719",
    "addr:postcode":"98671",
    "addr:street":"B St",
    "iso:country":"US",
    "sg:address":"2719 B St",
    "sg:city":"Washougal",
    "sg:classifiers":[
        {
            "category":"Building & Trades",
            "subcategory":"Construction",
            "type":"Services"
        }
    ],
    "sg:phone":"+1 360 835 8794",
    "sg:postcode":"98671",
    "sg:province":"WA",
    "sg:tags":[
        "excavating",
        "contractor"
    ],
    "wof:name":"Mc Donald Excavating Inc",
    "wof:placetype":"venue"
},
  "geometry": {"coordinates":[-122.34187,45.577973],"type":"Point"}
}