{
  "type": "Feature",
  "properties": {
    "addr:full":"17527 NE 67th Ct Redmond WA 98052",
    "addr:housenumber":"17527",
    "addr:postcode":"98052",
    "addr:street":"Ne 67Th Ct",
    "iso:country":"US",
    "sg:address":"17527 NE 67th Ct",
    "sg:city":"Redmond",
    "sg:classifiers":[
        {
            "category":"Building & Trades",
            "subcategory":"Construction",
            "type":"Services"
        }
    ],
    "sg:phone":"+1 425 867 9643",
    "sg:postcode":"98052",
    "sg:province":"WA",
    "sg:tags":[
        "general",
        "contractor"
    ],
    "wof:name":"A Roofing Co",
    "wof:placetype":"venue"
},
  "geometry": {"coordinates":[-122.107964,47.665187],"type":"Point"}
}