{
  "type": "Feature",
  "properties": {
    "addr:full":"19422 NE 203rd Pl Woodinville WA 98077",
    "addr:housenumber":"19422",
    "addr:postcode":"98077",
    "addr:street":"Ne 203Rd Pl",
    "iso:country":"US",
    "sg:address":"19422 NE 203rd Pl",
    "sg:city":"Woodinville",
    "sg:classifiers":[
        {
            "category":"Wholesale",
            "subcategory":"Electrical",
            "type":"Manufacturing & Wholesale Goods"
        }
    ],
    "sg:phone":"+1 425 869 1650",
    "sg:postcode":"98077",
    "sg:province":"WA",
    "sg:tags":[
        "import",
        "mfg",
        "light"
    ],
    "wof:name":"De Ruiter Co",
    "wof:placetype":"venue"
},
  "geometry": {"coordinates":[-122.07745199999999,47.775231],"type":"Point"}
}