{
  "type": "Feature",
  "properties": {
    "addr:full":"1808 Bellevue Avenue Suite 203 Seattle WA 98122",
    "addr:housenumber":"1808",
    "addr:postcode":"98122",
    "addr:street":"Bellevue Avenue Suite 203",
    "iso:country":"US",
    "sg:address":"1808 Bellevue Avenue Suite 203",
    "sg:city":"Seattle",
    "sg:classifiers":[
        {
            "category":"Real Estate",
            "subcategory":"Architect",
            "type":"Services"
        }
    ],
    "sg:phone":"+1 206 324 8619",
    "sg:postcode":"98122",
    "sg:province":"WA",
    "wof:name":"Walker Tim Aia",
    "wof:placetype":"venue"
},
  "geometry": {"coordinates":[-122.326741,47.617801],"type":"Point"}
}