{
  "type": "Feature",
  "properties": {
    "addr:full":"241 Ericksen Ave NE Bainbridge Island WA 98110",
    "addr:housenumber":"241",
    "addr:postcode":"98110",
    "addr:street":"Ericksen Ave Ne",
    "iso:country":"US",
    "sg:address":"241 Ericksen Ave NE",
    "sg:city":"Bainbridge Island",
    "sg:classifiers":[
        {
            "category":"Personal",
            "type":"Services"
        }
    ],
    "sg:phone":"+1 206 780 1720",
    "sg:postcode":"98110",
    "sg:province":"WA",
    "wof:name":"Anna Gae Johnson",
    "wof:placetype":"venue"
},
  "geometry": {"coordinates":[-122.51700599999999,47.627836],"type":"Point"}
}