{
  "type": "Feature",
  "properties": {
    "addr:full":"6430 E Royalview Ln Port Orchard WA 98366",
    "addr:housenumber":"6430",
    "addr:postcode":"98366",
    "addr:street":"E Royalview Ln",
    "iso:country":"US",
    "sg:address":"6430 E Royalview Ln",
    "sg:city":"Port Orchard",
    "sg:classifiers":[
        {
            "category":"Building & Trades",
            "subcategory":"Construction",
            "type":"Services"
        }
    ],
    "sg:phone":"+1 360 871 4943",
    "sg:postcode":"98366",
    "sg:province":"WA",
    "sg:tags":[
        "woodworker"
    ],
    "wof:name":"Poulsen Design Studio",
    "wof:placetype":"venue"
},
  "geometry": {"coordinates":[-122.550102,47.55761],"type":"Point"}
}