{
  "type": "Feature",
  "properties": {
    "addr:full":"3315 W Decatur Ave Spokane WA 99205",
    "addr:housenumber":"3315",
    "addr:postcode":"99205",
    "addr:street":"W Decatur Ave",
    "iso:country":"US",
    "sg:address":"3315 W Decatur Ave",
    "sg:city":"Spokane",
    "sg:classifiers":[
        {
            "category":"Professional",
            "subcategory":"Business Services",
            "type":"Services"
        }
    ],
    "sg:phone":"+1 509 328 8697",
    "sg:postcode":"99205",
    "sg:province":"WA",
    "wof:name":"Good Vibes Productions",
    "wof:placetype":"venue"
},
  "geometry": {"coordinates":[-117.4633,47.714505],"type":"Point"}
}