{
  "type": "Feature",
  "properties": {
    "addr:full":"153 E Rolling Hills Dr Shelton WA 98584",
    "addr:housenumber":"153",
    "addr:postcode":"98584",
    "addr:street":"E Rolling Hills Dr",
    "iso:country":"US",
    "sg:address":"153 E Rolling Hills Dr",
    "sg:city":"Shelton",
    "sg:classifiers":[
        {
            "category":"Retail",
            "subcategory":"Repair Shop",
            "type":"Services"
        }
    ],
    "sg:phone":"+1 360 426 5221",
    "sg:postcode":"98584",
    "sg:province":"WA",
    "wof:name":"Spear Services",
    "wof:placetype":"venue"
},
  "geometry": {"coordinates":[-123.145563,47.283172],"type":"Point"}
}