{
  "type": "Feature",
  "properties": {
    "addr:full":"915 Cascade Ave Shelton WA 98584",
    "addr:housenumber":"915",
    "addr:postcode":"98584",
    "addr:street":"Cascade Ave",
    "iso:country":"US",
    "sg:address":"915 Cascade Ave",
    "sg:city":"Shelton",
    "sg:classifiers":[
        {
            "category":"Retail",
            "subcategory":"Repair Shop",
            "type":"Services"
        }
    ],
    "sg:phone":"+1 360 427 9668",
    "sg:postcode":"98584",
    "sg:province":"WA",
    "wof:name":"Evergreen Ridge Cleaning",
    "wof:placetype":"venue"
},
  "geometry": {"coordinates":[-123.09026799999999,47.201381],"type":"Point"}
}