{
  "type": "Feature",
  "properties": {
    "addr:full":"743 McDowell Rd Ellensburg WA 98926",
    "addr:housenumber":"743",
    "addr:postcode":"98926",
    "addr:street":"Mcdowell Rd",
    "iso:country":"US",
    "sg:address":"743 McDowell Rd",
    "sg:city":"Ellensburg",
    "sg:classifiers":[
        {
            "category":"Farming",
            "subcategory":"Orchard",
            "type":"Manufacturing & Wholesale Goods"
        }
    ],
    "sg:phone":"+1 509 968 3823",
    "sg:postcode":"98926",
    "sg:province":"WA",
    "sg:tags":[
        "farm",
        "field",
        "fruit",
        "tree",
        "crop"
    ],
    "wof:name":"Eberhart Associates Inc-S",
    "wof:placetype":"venue"
},
  "geometry": {"coordinates":[-120.415764,46.90564],"type":"Point"}
}