{
  "type": "Feature",
  "properties": {
    "addr:full":"1904 3rd Ave Seattle WA 98101",
    "addr:housenumber":"1904",
    "addr:postcode":"98101",
    "addr:street":"3Rd Ave",
    "iso:country":"US",
    "sg:address":"1904 3rd Ave",
    "sg:city":"Seattle",
    "sg:classifiers":[
        {
            "category":"Wholesale",
            "subcategory":"Machinery & Supplies",
            "type":"Manufacturing & Wholesale Goods"
        }
    ],
    "sg:phone":"+1 206 382 1220",
    "sg:postcode":"98101",
    "sg:province":"WA",
    "sg:tags":[
        "equipment",
        "transportation"
    ],
    "wof:name":"Transportation Dept",
    "wof:placetype":"venue"
},
  "geometry": {"coordinates":[-122.340808,47.612421],"type":"Point"}
}