{
  "type": "Feature",
  "properties": {
    "addr:full":"9488 Eric Pl NE Bainbridge Isle WA 98110",
    "addr:housenumber":"9488",
    "addr:postcode":"98110",
    "addr:street":"Eric Pl Ne;Isle",
    "iso:country":"US",
    "sg:address":"9488 Eric Pl NE",
    "sg:city":"Bainbridge Isle",
    "sg:classifiers":[
        {
            "category":"Real Estate",
            "subcategory":"Real Estate Operator",
            "type":"Services"
        }
    ],
    "sg:phone":"+1 509 234 5781",
    "sg:postcode":"98110",
    "sg:province":"WA",
    "sg:tags":[
        "apartment"
    ],
    "wof:name":"Olliffe Property Holdings",
    "wof:placetype":"venue"
},
  "geometry": {"coordinates":[-122.52250600000001,47.674468],"type":"Point"}
}