{
  "type": "Feature",
  "properties": {
    "addr:full":"1015 10th Ave SE Olympia WA 98501",
    "addr:housenumber":"1015",
    "addr:postcode":"98501",
    "addr:street":"10Th Ave Se",
    "iso:country":"US",
    "sg:address":"1015 10th Ave SE",
    "sg:city":"Olympia",
    "sg:classifiers":[
        {
            "category":"Organizations",
            "subcategory":"Membership Organization",
            "type":"Services"
        }
    ],
    "sg:phone":"+1 360 586 5997",
    "sg:postcode":"98501",
    "sg:province":"WA",
    "sg:tags":[
        "environmental",
        "ecological",
        "conservation"
    ],
    "sg:website":"http://www.plia.wa.gov",
    "wof:name":"Pollution Liability Insurance Agency, Washington State",
    "wof:placetype":"venue"
},
  "geometry": {"coordinates":[-122.88809000000001,47.040734],"type":"Point"}
}