{
  "type": "Feature",
  "properties": {
    "addr:full":"10050 16th Ave SW Seattle WA 98146",
    "addr:housenumber":"10050",
    "addr:postcode":"98146",
    "addr:street":"16Th Ave Sw",
    "iso:country":"US",
    "sg:address":"10050 16th Ave SW",
    "sg:city":"Seattle",
    "sg:classifiers":[
        {
            "category":"Restaurant",
            "type":"Food & Drink"
        }
    ],
    "sg:menulink":"http://www.allmenus.com/wa/seattle/151824-aw-restaurant/menu/",
    "sg:phone":"+1 206 762 8793",
    "sg:postcode":"98146",
    "sg:province":"WA",
    "sg:tags":[
        "burger",
        "american",
        "dog",
        "pub",
        "hot"
    ],
    "wof:name":"A&W Restaurant",
    "wof:placetype":"venue"
},
  "geometry": {"coordinates":[-122.355124,47.513225],"type":"Point"}
}