{
  "type": "Feature",
  "properties": {
    "addr:full":"8216 E Big Meadows Rd Chattaroy WA 99003",
    "addr:housenumber":"8216",
    "addr:postcode":"99003",
    "addr:street":"E Big Meadows Rd",
    "iso:country":"US",
    "sg:address":"8216 E Big Meadows Rd",
    "sg:city":"Chattaroy",
    "sg:classifiers":[
        {
            "category":"Arts & Performance",
            "subcategory":"Dance",
            "type":"Entertainment"
        }
    ],
    "sg:phone":"+1 509 238 1837",
    "sg:postcode":"99003",
    "sg:province":"WA",
    "sg:tags":[
        "instruction",
        "dancing"
    ],
    "wof:name":"Kelly Irish Dancers",
    "wof:placetype":"venue"
},
  "geometry": {"coordinates":[-117.295075,47.860168],"type":"Point"}
}