{
  "type": "Feature",
  "properties": {
    "addr:full":"13243 Lake Kathleen Rd SE Renton WA 98059",
    "addr:housenumber":"13243",
    "addr:postcode":"98059",
    "addr:street":"Lake Kathleen Rd Se",
    "iso:country":"US",
    "sg:address":"13243 Lake Kathleen Rd SE",
    "sg:city":"Renton",
    "sg:classifiers":[
        {
            "category":"Building & Trades",
            "subcategory":"Construction",
            "type":"Services"
        }
    ],
    "sg:phone":"+1 425 271 9885",
    "sg:postcode":"98059",
    "sg:province":"WA",
    "sg:tags":[
        "house"
    ],
    "wof:name":"CMF Construction",
    "wof:placetype":"venue"
},
  "geometry": {"coordinates":[-122.09558199999999,47.486932],"type":"Point"}
}