{
  "type": "Feature",
  "properties": {
    "addr:full":"30 Logan Ave S Renton WA 98055",
    "addr:housenumber":"30",
    "addr:postcode":"98055",
    "addr:street":"Logan Ave S Renton",
    "iso:country":"US",
    "sg:address":"30 Logan Ave S",
    "sg:city":"Renton",
    "sg:classifiers":[
        {
            "category":"Food & Beverages",
            "subcategory":"Bakery",
            "type":"Retail Goods"
        }
    ],
    "sg:phone":"+1 425 226 5238",
    "sg:postcode":"98055",
    "sg:province":"WA",
    "sg:tags":[
        "sandwich"
    ],
    "sg:website":"www.subshop8.com",
    "wof:name":"Sub Shop #8",
    "wof:placetype":"venue"
},
  "geometry": {"coordinates":[-122.209,47.485298],"type":"Point"}
}