{
  "type": "Feature",
  "properties": {
    "addr:full":"5701 NE Bothell Way Ste 8 Kenmore WA 98028",
    "addr:housenumber":"5701",
    "addr:postcode":"98028",
    "addr:street":"Ne Bothell Way Ste 8",
    "iso:country":"US",
    "sg:address":"5701 NE Bothell Way Ste 8",
    "sg:city":"Kenmore",
    "sg:classifiers":[
        {
            "category":"Health Services",
            "subcategory":"Dentist",
            "type":"Services"
        }
    ],
    "sg:phone":"+1 425 487 2227",
    "sg:postcode":"98028",
    "sg:province":"WA",
    "sg:tags":[
        "denture",
        "dentists-prosthodontists",
        "dentistry",
        "implant",
        "dentists-implantology"
    ],
    "wof:name":"Ariel J Raigrodski Dmd P",
    "wof:placetype":"venue"
},
  "geometry": {"coordinates":[-122.269081,47.757832],"type":"Point"}
}