{
  "type": "Feature",
  "properties": {
    "addr:full":"19614 NE Finn Hill Rd Brush Prairie WA 98606",
    "addr:housenumber":"19614",
    "addr:postcode":"98606",
    "addr:street":"Ne Finn Hill Rd",
    "iso:country":"US",
    "sg:address":"19614 NE Finn Hill Rd",
    "sg:city":"Brush Prairie",
    "sg:classifiers":[
        {
            "category":"Government",
            "subcategory":"Office",
            "type":"Public Place"
        }
    ],
    "sg:phone":"+1 360 892 3687",
    "sg:postcode":"98606",
    "sg:province":"WA",
    "sg:tags":[
        "village"
    ],
    "wof:name":"Finn Hill Crusher",
    "wof:placetype":"venue"
},
  "geometry": {"coordinates":[-122.43513900000001,45.766361],"type":"Point"}
}