{
  "type": "Feature",
  "properties": {
    "addr:full":"19527 7th Ave NE Poulsbo WA 98370",
    "addr:housenumber":"19527",
    "addr:postcode":"98370",
    "addr:street":"7Th Ave Ne",
    "iso:country":"US",
    "sg:address":"19527 7th Ave NE",
    "sg:city":"Poulsbo",
    "sg:classifiers":[
        {
            "category":"Shopping",
            "type":"Retail Goods"
        }
    ],
    "sg:phone":"+1 360 697 3550",
    "sg:postcode":"98370",
    "sg:province":"WA",
    "sg:tags":[
        "pet",
        "food",
        "merchandise",
        "supply"
    ],
    "wof:name":"Superior Pet Foods",
    "wof:placetype":"venue"
},
  "geometry": {"coordinates":[-122.639939,47.739444],"type":"Point"}
}