{
  "type": "Feature",
  "properties": {
    "addr:full":"4605 S 168th St Seatac WA 98188",
    "addr:housenumber":"4605",
    "addr:postcode":"98188",
    "addr:street":"S 168Th St",
    "iso:country":"US",
    "sg:address":"4605 S 168th St",
    "sg:city":"Seatac",
    "sg:classifiers":[
        {
            "category":"Shopping",
            "subcategory":"Antiques",
            "type":"Retail Goods"
        }
    ],
    "sg:phone":"+1 206 246 9137",
    "sg:postcode":"98188",
    "sg:province":"WA",
    "sg:tags":[
        "dealers-wholesale"
    ],
    "wof:name":"Seattleusa Trading Co",
    "wof:placetype":"venue"
},
  "geometry": {"coordinates":[-122.275859,47.45285],"type":"Point"}
}