{
  "type": "Feature",
  "properties": {
    "addr:full":"1005 8th St Anacortes WA 98221",
    "addr:housenumber":"1005",
    "addr:postcode":"98221",
    "addr:street":"8Th St",
    "iso:country":"US",
    "sg:address":"1005 8th St",
    "sg:city":"Anacortes",
    "sg:classifiers":[
        {
            "category":"Insurance",
            "subcategory":"Insurance Agent",
            "type":"Services"
        }
    ],
    "sg:phone":"+1 360 424 5309",
    "sg:postcode":"98221",
    "sg:province":"WA",
    "sg:tags":[
        "auto"
    ],
    "sg:website":"http://www.farmersagent.com/lpetty",
    "wof:name":"Farmers Insurance - Leileah Petty",
    "wof:placetype":"venue"
},
  "geometry": {"coordinates":[-122.612606,48.515862],"type":"Point"}
}