{
  "type": "Feature",
  "properties": {
    "addr:full":"3907 240th Pl SE Issaquah WA 98029",
    "addr:housenumber":"3907",
    "addr:postcode":"98029",
    "addr:street":"240Th Pl Se",
    "iso:country":"US",
    "sg:address":"3907 240th Pl SE",
    "sg:city":"Issaquah",
    "sg:classifiers":[
        {
            "category":"Professional",
            "subcategory":"Computer Services",
            "type":"Services"
        }
    ],
    "sg:phone":"+1 425 313 1777",
    "sg:postcode":"98029",
    "sg:province":"WA",
    "sg:tags":[
        "related"
    ],
    "wof:name":"Ziegler Solutions",
    "wof:placetype":"venue"
},
  "geometry": {"coordinates":[-122.019149,47.574134],"type":"Point"}
}