{
  "type": "Feature",
  "properties": {
    "addr:full":"3029 46th Ave NE Olympia WA 98506",
    "addr:housenumber":"3029",
    "addr:postcode":"98506",
    "addr:street":"46Th Ave Ne",
    "iso:country":"US",
    "sg:address":"3029 46th Ave NE",
    "sg:city":"Olympia",
    "sg:classifiers":[
        {
            "category":"Professional",
            "type":"Services"
        }
    ],
    "sg:phone":"+1 360 357 5409",
    "sg:postcode":"98506",
    "sg:province":"WA",
    "wof:name":"Elder Connection",
    "wof:placetype":"venue"
},
  "geometry": {"coordinates":[-122.855035,47.097806],"type":"Point"}
}