{
  "type": "Feature",
  "properties": {
    "addr:full":"7530 W Victoria Ave Kennewick WA 99336",
    "addr:housenumber":"7530",
    "addr:postcode":"99336",
    "addr:street":"W Victoria Ave",
    "iso:country":"US",
    "sg:address":"7530 W Victoria Ave",
    "sg:city":"Kennewick",
    "sg:classifiers":[
        {
            "category":"Professional",
            "subcategory":"Employment Agencies",
            "type":"Services"
        }
    ],
    "sg:phone":"+1 509 783 0080",
    "sg:postcode":"99336",
    "sg:province":"WA",
    "sg:tags":[
        "help",
        "supply"
    ],
    "wof:name":"Ed Kathan Trucking",
    "wof:placetype":"venue"
},
  "geometry": {"coordinates":[-119.222172,46.227878],"type":"Point"}
}