{
  "type": "Feature",
  "properties": {
    "addr:full":"413 Union Ave Snohomish WA 98290",
    "addr:housenumber":"413",
    "addr:postcode":"98290",
    "addr:street":"Union Ave",
    "iso:country":"US",
    "sg:address":"413 Union Ave",
    "sg:city":"Snohomish",
    "sg:classifiers":[
        {
            "category":"Professional",
            "subcategory":"Management & Consulting",
            "type":"Services"
        }
    ],
    "sg:phone":"+1 360 563 2485",
    "sg:postcode":"98290",
    "sg:province":"WA",
    "sg:tags":[
        "tunnel",
        "building"
    ],
    "wof:name":"Roosevelt Technical Services",
    "wof:placetype":"venue"
},
  "geometry": {"coordinates":[-122.092737,47.917235],"type":"Point"}
}