{
  "type": "Feature",
  "properties": {
    "addr:full":"208 Ahtanum Rd Yakima WA 98903",
    "addr:housenumber":"208",
    "addr:postcode":"98903",
    "addr:street":"Ahtanum Rd",
    "iso:country":"US",
    "sg:address":"208 Ahtanum Rd",
    "sg:city":"Yakima",
    "sg:classifiers":[
        {
            "category":"Retail",
            "subcategory":"Animal Services",
            "type":"Services"
        }
    ],
    "sg:phone":"+1 509 457 0437",
    "sg:postcode":"98903",
    "sg:province":"WA",
    "wof:name":"Madisons Ave Racing Stables",
    "wof:placetype":"venue"
},
  "geometry": {"coordinates":[-120.511129,46.558122],"type":"Point"}
}