{
  "type": "Feature",
  "properties": {
    "iso:country":"US",
    "sg:address":"7193 129th Ln SW",
    "sg:city":"Olympia",
    "sg:classifiers":[
        {
            "category":"Building & Trades",
            "subcategory":"Construction",
            "type":"Services"
        }
    ],
    "sg:phone":"+1 360 352 4133",
    "sg:postcode":"98512",
    "sg:province":"WA",
    "sg:tags":[
        "house"
    ],
    "wof:name":"Littlerock Investment Cor",
    "wof:placetype":"venue"
},
  "geometry": {"coordinates":[-123.03366699999999,46.899603],"type":"Point"}
}