{
  "type": "Feature",
  "properties": {
    "addr:full":"8700 148th Ave NE Redmond WA 98052",
    "addr:housenumber":"8700",
    "addr:postcode":"98052",
    "addr:street":"148Th Ave Ne",
    "iso:country":"US",
    "sg:address":"8700 148th Ave NE",
    "sg:city":"Redmond",
    "sg:classifiers":[
        {
            "category":"Arts & Performance",
            "subcategory":"Art Gallery",
            "type":"Entertainment"
        },
        {
            "category":"Professional",
            "subcategory":"Art Services",
            "type":"Services"
        },
        {
            "category":"Professional",
            "subcategory":"Printing & Photocopies",
            "type":"Services"
        }
    ],
    "sg:phone":"+1 425 947 1539",
    "sg:postcode":"98052",
    "sg:province":"WA",
    "sg:tags":[
        "photographer"
    ],
    "sg:website":"www.nwfineartprinting.com",
    "wof:name":"Northwest Fine Art Printing",
    "wof:placetype":"venue"
},
  "geometry": {"coordinates":[-122.144232,47.680977],"type":"Point"}
}