{
  "type": "Feature",
  "properties": {
    "addr:full":"4215 W Clearwater Ave Kennewick WA 99336",
    "addr:housenumber":"4215",
    "addr:postcode":"99336",
    "addr:street":"W Clearwater Ave",
    "iso:country":"US",
    "sg:address":"4215 W Clearwater Ave",
    "sg:city":"Kennewick",
    "sg:classifiers":[
        {
            "category":"Shopping",
            "subcategory":"Computers & Home Electronics",
            "type":"Retail Goods"
        }
    ],
    "sg:phone":"+1 509 783 3306",
    "sg:postcode":"99336",
    "sg:province":"WA",
    "sg:tags":[
        "stereophonic",
        "residential",
        "m",
        "high",
        "construction",
        "fidelity"
    ],
    "wof:name":"Inn Toon Stereo Shop",
    "wof:placetype":"venue"
},
  "geometry": {"coordinates":[-119.17670099999999,46.212283],"type":"Point"}
}