{
  "type": "Feature",
  "properties": {
    "addr:full":"2730 Oakes Ave Everett WA 98201",
    "addr:postcode":"2730;98201",
    "addr:street":"Oakes Ave",
    "iso:country":"US",
    "sg:address":"2730 Oakes Ave",
    "sg:city":"Everett",
    "sg:classifiers":[
        {
            "category":"Government",
            "subcategory":"Office",
            "type":"Public Place"
        }
    ],
    "sg:phone":"+1 425 317 3540",
    "sg:postcode":"98201",
    "sg:province":"WA",
    "sg:tags":[
        "state",
        "security"
    ],
    "wof:name":"Army National Guard Recruiter",
    "wof:placetype":"venue"
},
  "geometry": {"coordinates":[-122.20443899999999,47.980992],"type":"Point"}
}