{
  "type": "Feature",
  "properties": {
    "addr:full":"1413 Lincoln Ave Vancouver WA 98660",
    "addr:housenumber":"1413",
    "addr:postcode":"98660",
    "addr:street":"Lincoln Ave",
    "iso:country":"US",
    "sg:address":"1413 Lincoln Ave",
    "sg:city":"Vancouver",
    "sg:classifiers":[
        {
            "category":"Manufacturing",
            "subcategory":"Tools & Machinery",
            "type":"Manufacturing & Wholesale Goods"
        }
    ],
    "sg:phone":"+1 360 693 4783",
    "sg:postcode":"98660",
    "sg:province":"WA",
    "sg:tags":[
        "machine",
        "shop"
    ],
    "wof:name":"Mellema Manufacturing Inc",
    "wof:placetype":"venue"
},
  "geometry": {"coordinates":[-122.683262,45.63267],"type":"Point"}
}