{
  "type": "Feature",
  "properties": {
    "addr:full":"3154 NE Sunset Blvd Renton WA 98056",
    "addr:housenumber":"3154",
    "addr:postcode":"98056",
    "addr:street":"Ne Sunset Blvd",
    "iso:country":"US",
    "sg:address":"3154 NE Sunset Blvd",
    "sg:city":"Renton",
    "sg:classifiers":[
        {
            "category":"Restaurant",
            "type":"Food & Drink"
        }
    ],
    "sg:phone":"+1 425 255 2233",
    "sg:postcode":"98056",
    "sg:province":"WA",
    "wof:name":"Toshi's Teriyaki",
    "wof:placetype":"venue"
},
  "geometry": {"coordinates":[-122.177002,47.503502],"type":"Point"}
}