{
  "type": "Feature",
  "properties": {
    "addr:full":"2112 NW 70th St Seattle WA 98117",
    "addr:housenumber":"2112",
    "addr:postcode":"98117",
    "addr:street":"Nw 70Th St",
    "iso:country":"US",
    "sg:address":"2112 NW 70th St",
    "sg:city":"Seattle",
    "sg:classifiers":[
        {
            "category":"Building & Trades",
            "subcategory":"Electrical",
            "type":"Services"
        }
    ],
    "sg:phone":"+1 206 781 7638",
    "sg:postcode":"98117",
    "sg:province":"WA",
    "sg:tags":[
        "electric",
        "industrial",
        "contractors-commercial",
        "contractor"
    ],
    "wof:name":"Dahlgren Electric",
    "wof:placetype":"venue"
},
  "geometry": {"coordinates":[-122.383376,47.679535],"type":"Point"}
}