{
  "type": "Feature",
  "properties": {
    "addr:full":"2999 John Stevens Way Hoquiam WA 98550",
    "addr:housenumber":"2999",
    "addr:postcode":"98550",
    "addr:street":"John Stevens Way",
    "iso:country":"US",
    "sg:address":"2999 John Stevens Way",
    "sg:city":"Hoquiam",
    "sg:classifiers":[
        {
            "category":"Manufacturing",
            "subcategory":"Wood Products",
            "type":"Manufacturing & Wholesale Goods"
        }
    ],
    "sg:phone":"+1 360 538 1480",
    "sg:postcode":"98550",
    "sg:province":"WA",
    "sg:tags":[
        "paper",
        "mfg"
    ],
    "wof:name":"Paneltech International LLC",
    "wof:placetype":"venue"
},
  "geometry": {"coordinates":[-123.85529,46.969062],"type":"Point"}
}