{
  "type": "Feature",
  "properties": {
    "addr:full":"4979 Purdue Ave NE Seattle WA 98105",
    "addr:housenumber":"4979",
    "addr:postcode":"98105",
    "addr:street":"Purdue Ave Ne",
    "iso:country":"US",
    "sg:address":"4979 Purdue Ave NE",
    "sg:city":"Seattle",
    "sg:classifiers":[
        {
            "category":"Social Services",
            "type":"Services"
        }
    ],
    "sg:phone":"+1 206 522 6151",
    "sg:postcode":"98105",
    "sg:province":"WA",
    "wof:name":"Beth Blacknall Strathy",
    "wof:placetype":"venue"
},
  "geometry": {"coordinates":[-122.27391299999999,47.670227],"type":"Point"}
}