{
  "type": "Feature",
  "properties": {
    "addr:full":"3119 S Neel Pl Kennewick WA 99337",
    "addr:housenumber":"3119",
    "addr:postcode":"99337",
    "addr:street":"S Neel Pl",
    "iso:country":"US",
    "sg:address":"3119 S Neel Pl",
    "sg:city":"Kennewick",
    "sg:classifiers":[
        {
            "category":"Shopping",
            "subcategory":"Shoes",
            "type":"Retail Goods"
        }
    ],
    "sg:phone":"+1 509 582 7410",
    "sg:postcode":"99337",
    "sg:province":"WA",
    "wof:name":"Pair Tree Corp",
    "wof:placetype":"venue"
},
  "geometry": {"coordinates":[-119.170563,46.181684],"type":"Point"}
}