{
  "type": "Feature",
  "properties": {
    "addr:full":"922 N Lake Rd Spokane WA 99212",
    "addr:housenumber":"922",
    "addr:postcode":"99212",
    "addr:street":"N Lake Rd",
    "iso:country":"US",
    "sg:address":"922 N Lake Rd",
    "sg:city":"Spokane",
    "sg:classifiers":[
        {
            "category":"Wholesale",
            "subcategory":"Auto Parts",
            "type":"Manufacturing & Wholesale Goods"
        }
    ],
    "sg:phone":"+1 509 536 9429",
    "sg:postcode":"99212",
    "sg:province":"WA",
    "wof:name":"Go/Dan Industries Inc",
    "wof:placetype":"venue"
},
  "geometry": {"coordinates":[-117.321792,47.664686],"type":"Point"}
}