{
  "type": "Feature",
  "properties": {
    "addr:full":"10801 105th St SW Lakewood WA 98498",
    "addr:housenumber":"10801",
    "addr:postcode":"98498",
    "addr:street":"105Th St Sw",
    "iso:country":"US",
    "sg:address":"10801 105th St SW",
    "sg:city":"Lakewood",
    "sg:classifiers":[
        {
            "category":"Building & Trades",
            "subcategory":"Construction",
            "type":"Services"
        }
    ],
    "sg:phone":"+1 253 581 7414",
    "sg:postcode":"98498",
    "sg:province":"WA",
    "sg:tags":[
        "house"
    ],
    "wof:name":"Steelhead Construction",
    "wof:placetype":"venue"
},
  "geometry": {"coordinates":[-122.582042,47.162734],"type":"Point"}
}