{
  "type": "Feature",
  "properties": {
    "addr:full":"1410 12th St Bremerton WA 98337",
    "addr:housenumber":"1410",
    "addr:postcode":"98337",
    "addr:street":"12Th St",
    "iso:country":"US",
    "sg:address":"1410 12th St",
    "sg:city":"Bremerton",
    "sg:classifiers":[
        {
            "category":"Building & Trades",
            "subcategory":"Landscaping Services",
            "type":"Services"
        }
    ],
    "sg:phone":"+1 360 479 6583",
    "sg:postcode":"98337",
    "sg:province":"WA",
    "wof:name":"Landscaping Lawn Maintenance",
    "wof:placetype":"venue"
},
  "geometry": {"coordinates":[-122.638738,47.571986],"type":"Point"}
}