{
  "type": "Feature",
  "properties": {
    "addr:full":"14316 SE 83rd St Renton WA 98059",
    "addr:housenumber":"14316",
    "addr:postcode":"98059",
    "addr:street":"Se 83Rd St",
    "iso:country":"US",
    "sg:address":"14316 SE 83rd St",
    "sg:city":"Renton",
    "sg:classifiers":[
        {
            "category":"Professional",
            "subcategory":"Computer Services",
            "type":"Services"
        }
    ],
    "sg:phone":"+1 425 430 7923",
    "sg:postcode":"98059",
    "sg:province":"WA",
    "sg:tags":[
        "prepackaged",
        "software"
    ],
    "wof:name":"Ilsi",
    "wof:placetype":"venue"
},
  "geometry": {"coordinates":[-122.147657,47.527446],"type":"Point"}
}