{
  "type": "Feature",
  "properties": {
    "addr:full":"14010 18th Ave S Tacoma WA 98444",
    "addr:housenumber":"14010",
    "addr:postcode":"98444",
    "addr:street":"18Th Ave S",
    "iso:country":"US",
    "sg:address":"14010 18th Ave S",
    "sg:city":"Tacoma",
    "sg:classifiers":[
        {
            "category":"Wholesale",
            "subcategory":"Drugs",
            "type":"Manufacturing & Wholesale Goods"
        }
    ],
    "sg:phone":"+1 253 537 5610",
    "sg:postcode":"98444",
    "sg:province":"WA",
    "wof:name":"Cherie Lyons Belle",
    "wof:placetype":"venue"
},
  "geometry": {"coordinates":[-122.461512,47.130299],"type":"Point"}
}