{
  "type": "Feature",
  "properties": {
    "addr:full":"10510 NE Northup Way Ste 200 Kirkland WA 98033",
    "addr:housenumber":"10510",
    "addr:postcode":"98033",
    "addr:street":"Ne Northup Way Ste 200",
    "iso:country":"US",
    "sg:address":"10510 NE Northup Way Ste 200",
    "sg:city":"Kirkland",
    "sg:classifiers":[
        {
            "category":"Personal",
            "type":"Services"
        }
    ],
    "sg:phone":"+1 425 968 0545",
    "sg:postcode":"98033",
    "sg:province":"WA",
    "sg:tags":[
        "local"
    ],
    "sg:website":"www.AAoAmerica.org/",
    "wof:name":"Affiliated Associations of America",
    "wof:placetype":"venue"
},
  "geometry": {"coordinates":[-122.20004900000001,47.64331],"type":"Point"}
}