{
  "type": "Feature",
  "properties": {
    "addr:full":"900 S Ruby St Ellensburg WA 98926",
    "addr:housenumber":"900",
    "addr:postcode":"98926",
    "addr:street":"S Ruby St",
    "iso:country":"US",
    "sg:address":"900 S Ruby St",
    "sg:city":"Ellensburg",
    "sg:classifiers":[
        {
            "category":"Banks & Credit Unions",
            "subcategory":"Investment Brokerage",
            "type":"Services"
        }
    ],
    "sg:phone":"+1 509 962 3700",
    "sg:postcode":"98926",
    "sg:province":"WA",
    "sg:tags":[
        "stock",
        "bond"
    ],
    "wof:name":"Edward Jones Co",
    "wof:placetype":"venue"
},
  "geometry": {"coordinates":[-120.544489,46.984559],"type":"Point"}
}