{
  "type": "Feature",
  "properties": {
    "addr:full":"15577 10th Ave NE Seattle WA 98155",
    "addr:housenumber":"15577",
    "addr:postcode":"98155",
    "addr:street":"10Th Ave Ne",
    "iso:country":"US",
    "sg:address":"15577 10th Ave NE",
    "sg:city":"Seattle",
    "sg:classifiers":[
        {
            "category":"Building & Trades",
            "subcategory":"Construction",
            "type":"Services"
        }
    ],
    "sg:phone":"+1 206 365 9792",
    "sg:postcode":"98155",
    "sg:province":"WA",
    "sg:tags":[
        "residential"
    ],
    "wof:name":"L T A Book Keeping Services",
    "wof:placetype":"venue"
},
  "geometry": {"coordinates":[-122.318448,47.742934],"type":"Point"}
}