{
  "type": "Feature",
  "properties": {
    "addr:full":"1818 Ferndale Ave SE Renton WA 98058",
    "addr:housenumber":"1818",
    "addr:postcode":"98058",
    "addr:street":"Ferndale Ave Se",
    "iso:country":"US",
    "sg:address":"1818 Ferndale Ave SE",
    "sg:city":"Renton",
    "sg:classifiers":[
        {
            "category":"Retail",
            "subcategory":"Repair Shop",
            "type":"Services"
        }
    ],
    "sg:phone":"+1 425 255 1838",
    "sg:postcode":"98058",
    "sg:province":"WA",
    "sg:tags":[
        "engineering",
        "business"
    ],
    "wof:name":"Regan Aircraft",
    "wof:placetype":"venue"
},
  "geometry": {"coordinates":[-122.180069,47.463487],"type":"Point"}
}