{
  "type": "Feature",
  "properties": {
    "addr:full":"196 E Kellogg Rd Bellingham WA 98226",
    "addr:housenumber":"196",
    "addr:postcode":"98226",
    "addr:street":"E Kellogg Rd",
    "iso:country":"US",
    "sg:address":"196 E Kellogg Rd",
    "sg:city":"Bellingham",
    "sg:classifiers":[
        {
            "category":"Real Estate",
            "subcategory":"Real Estate Operator",
            "type":"Services"
        }
    ],
    "sg:phone":"+1 360 734 7596",
    "sg:postcode":"98226",
    "sg:province":"WA",
    "sg:tags":[
        "building",
        "apartment"
    ],
    "wof:name":"Spring Creek Apts Inc",
    "wof:placetype":"venue"
},
  "geometry": {"coordinates":[-122.479282,48.795174],"type":"Point"}
}