{
  "type": "Feature",
  "properties": {
    "addr:full":"284 Central Way Kirkland WA 98033",
    "addr:housenumber":"284",
    "addr:postcode":"98033",
    "addr:street":"Central Way",
    "iso:country":"US",
    "sg:address":"284 Central Way",
    "sg:city":"Kirkland",
    "sg:classifiers":[
        {
            "category":"Health Services",
            "subcategory":"Chiropractor",
            "type":"Services"
        }
    ],
    "sg:phone":"+1 425 605 8508",
    "sg:postcode":"98033",
    "sg:province":"WA",
    "sg:website":"www.mccrackenchiro.com",
    "wof:name":"McCracken Chiropractic & Wellness Center",
    "wof:placetype":"venue"
},
  "geometry": {"coordinates":[-122.203621,47.677437],"type":"Point"}
}