{
  "type": "Feature",
  "properties": {
    "iso:country":"US",
    "sg:address":"640 Nelson Rd",
    "sg:city":"Granger",
    "sg:classifiers":[
        {
            "category":"Farming",
            "subcategory":"Dairy Farm",
            "type":"Manufacturing & Wholesale Goods"
        }
    ],
    "sg:phone":"+1 509 854 1025",
    "sg:postcode":"98932",
    "sg:province":"WA",
    "wof:name":"Bron Dairy",
    "wof:placetype":"venue"
},
  "geometry": {"coordinates":[-120.18588200000001,46.367961],"type":"Point"}
}