{
  "type": "Feature",
  "properties": {
    "addr:full":"1250 1st Ave S Seattle WA 98134",
    "addr:housenumber":"1250",
    "addr:postcode":"98134",
    "addr:street":"1St Ave S",
    "iso:country":"US",
    "sg:address":"1250 1st Ave S",
    "sg:city":"Seattle",
    "sg:classifiers":[
        {
            "category":"Ice Cream",
            "type":"Food & Drink"
        }
    ],
    "sg:menulink":"http://www.allmenus.com/wa/seattle/217467-ben--jerrys/menu/",
    "sg:postcode":"98134",
    "sg:province":"WA",
    "sg:tags":[
        "american"
    ],
    "wof:name":"Ben & Jerry's",
    "wof:placetype":"venue"
},
  "geometry": {"coordinates":[-122.334228,47.592053],"type":"Point"}
}