{
  "type": "Feature",
  "properties": {
    "addr:full":"1206 NW 75th St Seattle WA 98117",
    "addr:housenumber":"1206",
    "addr:postcode":"98117",
    "addr:street":"Nw 75Th St",
    "iso:country":"US",
    "sg:address":"1206 NW 75th St",
    "sg:city":"Seattle",
    "sg:classifiers":[
        {
            "category":"Professional",
            "subcategory":"Lawyer & Legal Services",
            "type":"Services"
        }
    ],
    "sg:phone":"+1 206 782 2203",
    "sg:postcode":"98117",
    "sg:province":"WA",
    "sg:tags":[
        "clinic"
    ],
    "wof:name":"Tc Legal Services",
    "wof:placetype":"venue"
},
  "geometry": {"coordinates":[-122.37188500000001,47.683267],"type":"Point"}
}