{
  "type": "Feature",
  "properties": {
    "addr:full":"4824 Rainier Ave S Seattle WA 98118",
    "addr:housenumber":"4824",
    "addr:postcode":"98118",
    "addr:street":"Rainier Ave S",
    "iso:country":"US",
    "sg:address":"4824 Rainier Ave S",
    "sg:city":"Seattle",
    "sg:classifiers":[
        {
            "category":"Coffee & Tea",
            "type":"Food & Drink"
        }
    ],
    "sg:menulink":"http://www.allmenus.com/wa/seattle/117839-starbucks-coffee/menu/",
    "sg:phone":"+1 206 721 8871",
    "sg:postcode":"98118",
    "sg:province":"WA",
    "sg:tags":[
        "american"
    ],
    "wof:name":"Starbucks Coffee",
    "wof:placetype":"venue"
},
  "geometry": {"coordinates":[-122.285689,47.559061],"type":"Point"}
}