{
  "type": "Feature",
  "properties": {
    "addr:full":"919 N 98th St Seattle WA 98103",
    "addr:housenumber":"919",
    "addr:postcode":"98103",
    "addr:street":"N 98Th St",
    "iso:country":"US",
    "sg:address":"919 N 98th St",
    "sg:city":"Seattle",
    "sg:classifiers":[
        {
            "category":"Manufacturing",
            "subcategory":"Jewelry",
            "type":"Manufacturing & Wholesale Goods"
        },
        {
            "category":"Home & Garden",
            "subcategory":"Home Furnishings",
            "type":"Retail Goods"
        }
    ],
    "sg:phone":"+1 206 522 3745",
    "sg:postcode":"98103",
    "sg:province":"WA",
    "sg:tags":[
        "cutlery"
    ],
    "wof:name":"Frye's Knives & Cutlery",
    "wof:placetype":"venue"
},
  "geometry": {"coordinates":[-122.344807,47.700449],"type":"Point"}
}