{
  "type": "Feature",
  "properties": {
    "addr:full":"16914 75th St E Sumner WA 98390",
    "addr:housenumber":"16914",
    "addr:postcode":"98390",
    "addr:street":"75Th St E",
    "iso:country":"US",
    "sg:address":"16914 75th St E",
    "sg:city":"Sumner",
    "sg:classifiers":[
        {
            "category":"Professional",
            "type":"Services"
        }
    ],
    "sg:phone":"+1 253 862 1636",
    "sg:postcode":"98390",
    "sg:province":"WA",
    "sg:tags":[
        "establishment"
    ],
    "wof:name":"Sumner Groundcovers",
    "wof:placetype":"venue"
},
  "geometry": {"coordinates":[-122.206912,47.189328],"type":"Point"}
}