{
  "type": "Feature",
  "properties": {
    "addr:full":"937 N Pine Ct Lynden WA 98264",
    "addr:housenumber":"937",
    "addr:postcode":"98264",
    "addr:street":"N Pine Ct",
    "iso:country":"US",
    "sg:address":"937 N Pine Ct",
    "sg:city":"Lynden",
    "sg:classifiers":[
        {
            "category":"Professional",
            "subcategory":"Business Services",
            "type":"Services"
        }
    ],
    "sg:phone":"+1 360 354 8142",
    "sg:postcode":"98264",
    "sg:province":"WA",
    "wof:name":"Ideal Design",
    "wof:placetype":"venue"
},
  "geometry": {"coordinates":[-122.47956499999999,48.949183],"type":"Point"}
}