{
  "type": "Feature",
  "properties": {
    "addr:full":"2490 E Ainsworth St Pasco WA 99301",
    "addr:housenumber":"2490",
    "addr:postcode":"99301",
    "addr:street":"E Ainsworth St",
    "iso:country":"US",
    "sg:address":"2490 E Ainsworth St",
    "sg:city":"Pasco",
    "sg:classifiers":[
        {
            "category":"Freight",
            "type":"Transportation"
        }
    ],
    "sg:phone":"+1 509 544 0622",
    "sg:postcode":"99301",
    "sg:province":"WA",
    "sg:tags":[
        "warehouse",
        "self",
        "storage"
    ],
    "wof:name":"KIS Intl",
    "wof:placetype":"venue"
},
  "geometry": {"coordinates":[-119.06321,46.213982],"type":"Point"}
}