{
  "type": "Feature",
  "properties": {
    "iso:country":"US",
    "sg:address":"12433 Admiralty Way",
    "sg:city":"Everett",
    "sg:classifiers":[
        {
            "category":"Education",
            "subcategory":"Special Training",
            "type":"Public Place"
        }
    ],
    "sg:phone":"+1 425 280 9336",
    "sg:postcode":"98204",
    "sg:province":"WA",
    "wof:name":"Leviticus Music Center",
    "wof:placetype":"venue"
},
  "geometry": {"coordinates":[-122.252253,47.885966],"type":"Point"}
}