{
  "type": "Feature",
  "properties": {
    "addr:full":"2611 E Sims Way Port Townsend WA 98368",
    "addr:housenumber":"2611",
    "addr:postcode":"98368",
    "addr:street":"E Sims Way",
    "iso:country":"US",
    "sg:address":"2611 E Sims Way",
    "sg:city":"Port Townsend",
    "sg:classifiers":[
        {
            "category":"Food & Beverages",
            "subcategory":"Groceries & Convenience Stores",
            "type":"Retail Goods"
        }
    ],
    "sg:phone":"+1 360 385 1175",
    "sg:postcode":"98368",
    "sg:province":"WA",
    "wof:name":"Safeway",
    "wof:placetype":"venue"
},
  "geometry": {"coordinates":[-122.77561300000001,48.108834],"type":"Point"}
}