{
  "type": "Feature",
  "properties": {
    "addr:full":"2107 Elliott Ave Seattle WA 98121",
    "addr:housenumber":"2107",
    "addr:postcode":"98121",
    "addr:street":"Elliott Ave",
    "iso:country":"US",
    "sg:address":"2107 Elliott Ave",
    "sg:city":"Seattle",
    "sg:classifiers":[
        {
            "category":"Professional",
            "subcategory":"Management & Consulting",
            "type":"Services"
        },
        {
            "category":"Organizations",
            "subcategory":"Professional Association",
            "type":"Services"
        }
    ],
    "sg:phone":"+1 206 443 8846",
    "sg:postcode":"98121",
    "sg:province":"WA",
    "sg:tags":[
        "counselor",
        "relation",
        "public",
        "relations"
    ],
    "sg:website":"www.gallatingroup.com",
    "wof:name":"Gallatin Group Inc",
    "wof:placetype":"venue"
},
  "geometry": {"coordinates":[-122.34612199999999,47.611431],"type":"Point"}
}