{
  "type": "Feature",
  "properties": {
    "addr:full":"13819 122nd Ave E Puyallup WA 98374",
    "addr:housenumber":"13819",
    "addr:postcode":"98374",
    "addr:street":"122Nd Ave E",
    "iso:country":"US",
    "sg:address":"13819 122nd Ave E",
    "sg:city":"Puyallup",
    "sg:classifiers":[
        {
            "category":"Shopping",
            "subcategory":"Gifts & Souvenirs",
            "type":"Retail Goods"
        }
    ],
    "sg:phone":"+1 253 770 0678",
    "sg:postcode":"98374",
    "sg:province":"WA",
    "wof:name":"Rebekahs Flowers & Gifts",
    "wof:placetype":"venue"
},
  "geometry": {"coordinates":[-122.266474,47.130627],"type":"Point"}
}