{
  "type": "Feature",
  "properties": {
    "addr:full":"3724 S Custer St Spokane WA 99223",
    "addr:housenumber":"3724",
    "addr:postcode":"99223",
    "addr:street":"S Custer St",
    "iso:country":"US",
    "sg:address":"3724 S Custer St",
    "sg:city":"Spokane",
    "sg:classifiers":[
        {
            "category":"Professional",
            "type":"Services"
        }
    ],
    "sg:phone":"+1 509 448 2510",
    "sg:postcode":"99223",
    "sg:province":"WA",
    "wof:name":"Robert W Rickard",
    "wof:placetype":"venue"
},
  "geometry": {"coordinates":[-117.34114099999999,47.620687],"type":"Point"}
}