{
  "type": "Feature",
  "properties": {
    "addr:full":"14650 Seabeck Hwy NW Seabeck WA 98380",
    "addr:housenumber":"14650",
    "addr:postcode":"98380",
    "addr:street":"Seabeck Hwy Nw",
    "iso:country":"US",
    "sg:address":"14650 Seabeck Hwy NW",
    "sg:city":"Seabeck",
    "sg:classifiers":[
        {
            "category":"Professional",
            "subcategory":"Management & Consulting",
            "type":"Services"
        }
    ],
    "sg:phone":"+1 360 830 4867",
    "sg:postcode":"98380",
    "sg:province":"WA",
    "sg:tags":[
        "business"
    ],
    "wof:name":"Riplinger & Associates",
    "wof:placetype":"venue"
},
  "geometry": {"coordinates":[-122.82487500000001,47.641746],"type":"Point"}
}