{
  "type": "Feature",
  "properties": {
    "addr:full":"PO Box 871573 Vancouver WA 98607",
    "addr:housenumber":"po",
    "addr:postcode":"98607",
    "addr:street":"Box 871573",
    "iso:country":"US",
    "sg:address":"PO Box 871573",
    "sg:city":"Vancouver",
    "sg:classifiers":[
        {
            "category":"Professional",
            "type":"Services"
        }
    ],
    "sg:phone":"+1 503 395 2584",
    "sg:postcode":"98607",
    "sg:province":"WA",
    "sg:website":"www.leaditconsulting.net",
    "wof:name":"Lead It Consulting",
    "wof:placetype":"venue"
},
  "geometry": {"coordinates":[-122.661486,45.638728],"type":"Point"}
}