{
  "type": "Feature",
  "properties": {
    "addr:full":"9451 Swanson Rd Sumas WA 98295",
    "addr:housenumber":"9451",
    "addr:postcode":"98295",
    "addr:street":"Swanson Rd",
    "iso:country":"US",
    "sg:address":"9451 Swanson Rd",
    "sg:city":"Sumas",
    "sg:classifiers":[
        {
            "category":"Farming",
            "subcategory":"Dairy Farm",
            "type":"Manufacturing & Wholesale Goods"
        }
    ],
    "sg:phone":"+1 360 988 5293",
    "sg:postcode":"98295",
    "sg:province":"WA",
    "wof:name":"Arlyn Visser",
    "wof:placetype":"venue"
},
  "geometry": {"coordinates":[-122.320221,48.982034],"type":"Point"}
}