{
  "type": "Feature",
  "properties": {
    "addr:full":"541 Eagle Rd Othello WA 99344",
    "addr:housenumber":"541",
    "addr:postcode":"99344",
    "addr:street":"Eagle Rd",
    "iso:country":"US",
    "sg:address":"541 Eagle Rd",
    "sg:city":"Othello",
    "sg:classifiers":[
        {
            "category":"Farming",
            "subcategory":"Orchard",
            "type":"Manufacturing & Wholesale Goods"
        },
        {
            "category":"Professional",
            "type":"Services"
        }
    ],
    "sg:phone":"+1 509 488 2523",
    "sg:postcode":"99344",
    "sg:province":"WA",
    "sg:tags":[
        "establishment",
        "fruit",
        "tree"
    ],
    "wof:name":"AB Yvo Partnership",
    "wof:placetype":"venue"
},
  "geometry": {"coordinates":[-119.175299,46.711322],"type":"Point"}
}