{
  "type": "Feature",
  "properties": {
    "addr:full":"13 Central Way Kirkland WA 98033",
    "addr:housenumber":"13",
    "addr:postcode":"98033",
    "addr:street":"Central Way",
    "iso:country":"US",
    "sg:address":"13 Central Way",
    "sg:city":"Kirkland",
    "sg:classifiers":[
        {
            "category":"Professional",
            "subcategory":"Management & Consulting",
            "type":"Services"
        }
    ],
    "sg:phone":"+1 206 790 6786",
    "sg:postcode":"98033",
    "sg:province":"WA",
    "sg:tags":[
        "business"
    ],
    "wof:name":"Deftcom Inc",
    "wof:placetype":"venue"
},
  "geometry": {"coordinates":[-122.20898800000001,47.676243],"type":"Point"}
}