{
  "type": "Feature",
  "properties": {
    "addr:full":"162 N Summit Rd Mccleary WA 98557",
    "addr:housenumber":"162",
    "addr:postcode":"98557",
    "addr:street":"N Summit Rd",
    "iso:country":"US",
    "sg:address":"162 N Summit Rd",
    "sg:city":"Mccleary",
    "sg:classifiers":[
        {
            "category":"Manufacturing",
            "subcategory":"Buildings",
            "type":"Manufacturing & Wholesale Goods"
        }
    ],
    "sg:phone":"+1 360 495 3577",
    "sg:postcode":"98557",
    "sg:province":"WA",
    "sg:tags":[
        "home",
        "log",
        "cabin"
    ],
    "sg:website":"www.singloghomes.com",
    "wof:name":"Sing Square Log Home Inc",
    "wof:placetype":"venue"
},
  "geometry": {"coordinates":[-123.267128,47.064295],"type":"Point"}
}