{
  "type": "Feature",
  "properties": {
    "addr:full":"299 Rendezvous Rd Winthrop WA 98862",
    "addr:housenumber":"299",
    "addr:postcode":"98862",
    "addr:street":"Rendezvous Rd",
    "iso:country":"US",
    "sg:address":"299 Rendezvous Rd",
    "sg:city":"Winthrop",
    "sg:classifiers":[
        {
            "category":"Recreation",
            "type":"Entertainment"
        }
    ],
    "sg:phone":"+1 509 996 3803",
    "sg:postcode":"98862",
    "sg:province":"WA",
    "sg:tags":[
        "stable"
    ],
    "wof:name":"Bob Boyce Training Stables",
    "wof:placetype":"venue"
},
  "geometry": {"coordinates":[-120.21317500000001,48.528529],"type":"Point"}
}