{
  "type": "Feature",
  "properties": {
    "addr:full":"260 Walker Rd Toledo WA 98591",
    "addr:housenumber":"260",
    "addr:postcode":"98591",
    "addr:street":"Walker Rd",
    "iso:country":"US",
    "sg:address":"260 Walker Rd",
    "sg:city":"Toledo",
    "sg:classifiers":[
        {
            "category":"Freight",
            "type":"Transportation"
        }
    ],
    "sg:phone":"+1 360 600 1339",
    "sg:postcode":"98591",
    "sg:province":"WA",
    "wof:name":"J&L Rv Transport",
    "wof:placetype":"venue"
},
  "geometry": {"coordinates":[-122.86553600000001,46.404893],"type":"Point"}
}