{
  "type": "Feature",
  "properties": {
    "addr:full":"10921 NE 85th St Vancouver WA 98662",
    "addr:housenumber":"10921",
    "addr:postcode":"98662",
    "addr:street":"Ne 85Th St",
    "iso:country":"US",
    "sg:address":"10921 NE 85th St",
    "sg:city":"Vancouver",
    "sg:classifiers":[
        {
            "category":"Building & Trades",
            "subcategory":"Construction",
            "type":"Services"
        }
    ],
    "sg:phone":"+1 360 896 6404",
    "sg:postcode":"98662",
    "sg:province":"WA",
    "sg:tags":[
        "house"
    ],
    "wof:name":"Yurax Construction",
    "wof:placetype":"venue"
},
  "geometry": {"coordinates":[-122.560396,45.68431],"type":"Point"}
}