{
  "type": "Feature",
  "properties": {
    "addr:full":"6017 W Sarazen St SE Olympia WA 98513",
    "addr:housenumber":"6017",
    "addr:postcode":"98513",
    "addr:street":"W Sarazen St Se",
    "iso:country":"US",
    "sg:address":"6017 W Sarazen St SE",
    "sg:city":"Olympia",
    "sg:classifiers":[
        {
            "category":"Wholesale",
            "subcategory":"Non-durable Goods",
            "type":"Manufacturing & Wholesale Goods"
        }
    ],
    "sg:phone":"+1 360 491 6302",
    "sg:postcode":"98513",
    "sg:province":"WA",
    "wof:name":"Soy Scent-Sations",
    "wof:placetype":"venue"
},
  "geometry": {"coordinates":[-122.821321,46.990972],"type":"Point"}
}