{
  "type": "Feature",
  "properties": {
    "addr:full":"124 W 1st Ave Kennewick WA 99336",
    "addr:housenumber":"124",
    "addr:postcode":"99336",
    "addr:street":"W 1St Ave",
    "iso:country":"US",
    "sg:address":"124 W 1st Ave",
    "sg:city":"Kennewick",
    "sg:classifiers":[
        {
            "category":"Retail",
            "subcategory":"Auto Repair",
            "type":"Services"
        }
    ],
    "sg:phone":"+1 509 582 6544",
    "sg:postcode":"99336",
    "sg:province":"WA",
    "sg:tags":[
        "general"
    ],
    "wof:name":"Genesis Auto Inc",
    "wof:placetype":"venue"
},
  "geometry": {"coordinates":[-119.119623,46.207708],"type":"Point"}
}