{
  "type": "Feature",
  "properties": {
    "addr:full":"4433 105th Pl NE Marysville WA 98271",
    "addr:housenumber":"4433",
    "addr:postcode":"98271",
    "addr:street":"105Th Pl Ne",
    "iso:country":"US",
    "sg:address":"4433 105th Pl NE",
    "sg:city":"Marysville",
    "sg:classifiers":[
        {
            "category":"Banks & Credit Unions",
            "subcategory":"Investment Brokerage",
            "type":"Services"
        }
    ],
    "sg:phone":"+1 360 659 2142",
    "sg:postcode":"98271",
    "sg:province":"WA",
    "sg:tags":[
        "advisory"
    ],
    "wof:name":"Dean Disney",
    "wof:placetype":"venue"
},
  "geometry": {"coordinates":[-122.17212000000001,48.09071],"type":"Point"}
}