{
  "type": "Feature",
  "properties": {
    "addr:full":"1700 5th St Cheney WA 99004",
    "addr:housenumber":"1700",
    "addr:postcode":"99004",
    "addr:street":"5Th St",
    "iso:country":"US",
    "sg:address":"1700 5th St",
    "sg:city":"Cheney",
    "sg:classifiers":[
        {
            "category":"Building & Trades",
            "subcategory":"Construction",
            "type":"Services"
        }
    ],
    "sg:phone":"+1 509 235 4084",
    "sg:postcode":"99004",
    "sg:province":"WA",
    "sg:tags":[
        "wallcoverings-installation",
        "wallpaper",
        "painting",
        "contractor"
    ],
    "wof:name":"Heyers Construction",
    "wof:placetype":"venue"
},
  "geometry": {"coordinates":[-117.568359,47.497978],"type":"Point"}
}