{
  "type": "Feature",
  "properties": {
    "addr:full":"22835 SE 264th Ct Maple Valley WA 98038",
    "addr:postcode":"22835;98038",
    "addr:street":"Se 264Th Ct",
    "iso:country":"US",
    "sg:address":"22835 SE 264th Ct",
    "sg:city":"Maple Valley",
    "sg:classifiers":[
        {
            "category":"Professional",
            "subcategory":"Employment Agencies",
            "type":"Services"
        }
    ],
    "sg:phone":"+1 425 432 5550",
    "sg:postcode":"98038",
    "sg:province":"WA",
    "wof:name":"Wynn Enterprises",
    "wof:placetype":"venue"
},
  "geometry": {"coordinates":[-122.03629100000001,47.364677],"type":"Point"}
}