{
  "type": "Feature",
  "properties": {
    "addr:full":"5516 Woodlawn Ave N Seattle WA 98103",
    "addr:housenumber":"5516",
    "addr:postcode":"98103",
    "addr:street":"Woodlawn Ave N",
    "iso:country":"US",
    "sg:address":"5516 Woodlawn Ave N",
    "sg:city":"Seattle",
    "sg:classifiers":[
        {
            "category":"Professional",
            "subcategory":"Business Services",
            "type":"Services"
        }
    ],
    "sg:phone":"+1 206 547 3075",
    "sg:postcode":"98103",
    "sg:province":"WA",
    "sg:tags":[
        "consultant",
        "coach"
    ],
    "wof:name":"Dot Consulting",
    "wof:placetype":"venue"
},
  "geometry": {"coordinates":[-122.33798899999999,47.668944],"type":"Point"}
}