{
  "type": "Feature",
  "properties": {
    "addr:full":"Crossroads Mall 15600 NE 8th St Bellevue WA 98008",
    "addr:housenumber":"15600",
    "addr:postcode":"98008",
    "addr:street":"Ne 8Th St",
    "iso:country":"US",
    "sg:address":"Crossroads Mall 15600 NE 8th St",
    "sg:city":"Bellevue",
    "sg:classifiers":[
        {
            "category":"Coffee & Tea",
            "type":"Food & Drink"
        }
    ],
    "sg:postcode":"98008",
    "sg:province":"WA",
    "sg:website":"www.starbucks.com",
    "wof:name":"Starbucks",
    "wof:placetype":"venue"
},
  "geometry": {"coordinates":[-122.131491,47.617504],"type":"Point"}
}