{
  "type": "Feature",
  "properties": {
    "addr:full":"614 14th Ave E Seattle WA 98112",
    "addr:housenumber":"614",
    "addr:postcode":"98112",
    "addr:street":"14Th Ave E",
    "iso:country":"US",
    "sg:address":"614 14th Ave E",
    "sg:city":"Seattle",
    "sg:classifiers":[
        {
            "category":"Communications",
            "subcategory":"Newspaper",
            "type":"Services"
        }
    ],
    "sg:phone":"+1 206 325 1672",
    "sg:postcode":"98112",
    "sg:province":"WA",
    "sg:website":"http://www.lonniedavis.net",
    "wof:name":"Lonnie Davis",
    "wof:placetype":"venue"
},
  "geometry": {"coordinates":[-122.314611,47.624393],"type":"Point"}
}