{
  "type": "Feature",
  "properties": {
    "addr:full":"8313 Aurora Ave N Seattle WA 98103",
    "addr:housenumber":"8313",
    "addr:postcode":"98103",
    "addr:street":"Aurora Ave N",
    "iso:country":"US",
    "sg:address":"8313 Aurora Ave N",
    "sg:city":"Seattle",
    "sg:classifiers":[
        {
            "category":"Health Services",
            "subcategory":"Doctor",
            "type":"Services"
        }
    ],
    "sg:phone":"+1 206 784 0737",
    "sg:postcode":"98103",
    "sg:province":"WA",
    "sg:website":"www.healthsouth.com",
    "wof:name":"Healthsouth Medical Clinic",
    "wof:placetype":"venue"
},
  "geometry": {"coordinates":[-122.345001,47.689602],"type":"Point"}
}