{
  "type": "Feature",
  "properties": {
    "addr:full":"3208 K St Vancouver WA 98663",
    "addr:housenumber":"3208",
    "addr:postcode":"98663",
    "addr:street":"K St",
    "iso:country":"US",
    "sg:address":"3208 K St",
    "sg:city":"Vancouver",
    "sg:classifiers":[
        {
            "category":"Professional",
            "subcategory":"Management & Consulting",
            "type":"Services"
        }
    ],
    "sg:phone":"+1 360 666 3206",
    "sg:postcode":"98663",
    "sg:province":"WA",
    "sg:tags":[
        "business"
    ],
    "wof:name":"Ewing Resource Consulting",
    "wof:placetype":"venue"
},
  "geometry": {"coordinates":[-122.660827,45.644976],"type":"Point"}
}