{
  "type": "Feature",
  "properties": {
    "iso:country":"US",
    "sg:address":"2327 Sandell St",
    "sg:city":"Raymond",
    "sg:classifiers":[
        {
            "category":"Professional",
            "subcategory":"Business Services",
            "type":"Services"
        }
    ],
    "sg:phone":"+1 360 942 2085",
    "sg:postcode":"98577",
    "sg:province":"WA",
    "wof:name":"American Cedar Inspection Agen",
    "wof:placetype":"venue"
},
  "geometry": {"coordinates":[-123.705504,46.674698],"type":"Point"}
}