{
  "type": "Feature",
  "properties": {
    "addr:full":"1500 E Taneum Rd Thorp WA 98946",
    "addr:housenumber":"1500",
    "addr:postcode":"98946",
    "addr:street":"E Taneum Rd",
    "iso:country":"US",
    "sg:address":"1500 E Taneum Rd",
    "sg:city":"Thorp",
    "sg:classifiers":[
        {
            "category":"Arts & Performance",
            "subcategory":"Art Gallery",
            "type":"Entertainment"
        }
    ],
    "sg:phone":"+1 509 964 2234",
    "sg:postcode":"98946",
    "sg:province":"WA",
    "sg:tags":[
        "fine",
        "artist"
    ],
    "wof:name":"Art Leather",
    "wof:placetype":"venue"
},
  "geometry": {"coordinates":[-120.725306,47.082458],"type":"Point"}
}