{
  "type": "Feature",
  "properties": {
    "addr:full":"870 Lake Rd Burbank WA 99323",
    "addr:housenumber":"870",
    "addr:postcode":"99323",
    "addr:street":"Lake Rd",
    "iso:country":"US",
    "sg:address":"870 Lake Rd",
    "sg:city":"Burbank",
    "sg:classifiers":[
        {
            "category":"Farming",
            "subcategory":"Orchard",
            "type":"Manufacturing & Wholesale Goods"
        }
    ],
    "sg:phone":"+1 509 547 2015",
    "sg:postcode":"99323",
    "sg:province":"WA",
    "sg:tags":[
        "farm",
        "fruit",
        "tree"
    ],
    "wof:name":"Applegate Nursrey",
    "wof:placetype":"venue"
},
  "geometry": {"coordinates":[-118.992221,46.20966],"type":"Point"}
}