{
  "type": "Feature",
  "properties": {
    "addr:full":"926 W Indiana Ave Spokane WA 99205",
    "addr:housenumber":"926",
    "addr:postcode":"99205",
    "addr:street":"W Indiana Ave",
    "iso:country":"US",
    "sg:address":"926 W Indiana Ave",
    "sg:city":"Spokane",
    "sg:classifiers":[
        {
            "category":"Shopping",
            "subcategory":"Tobacco",
            "type":"Retail Goods"
        }
    ],
    "sg:phone":"+1 509 327 4134",
    "sg:postcode":"99205",
    "sg:province":"WA",
    "sg:tags":[
        "cigarette",
        "product",
        "cigar",
        "dealer"
    ],
    "wof:name":"Smokers Outlet Inc",
    "wof:placetype":"venue"
},
  "geometry": {"coordinates":[-117.42630699999999,47.675013],"type":"Point"}
}