{
  "type": "Feature",
  "properties": {
    "addr:full":"2631 Evergreen Point Rd Medina WA 98039",
    "addr:housenumber":"2631",
    "addr:postcode":"98039",
    "addr:street":"Evergreen Point Rd",
    "iso:country":"US",
    "sg:address":"2631 Evergreen Point Rd",
    "sg:city":"Medina",
    "sg:classifiers":[
        {
            "category":"Banks & Credit Unions",
            "subcategory":"Financial Services",
            "type":"Services"
        }
    ],
    "sg:phone":"+1 425 454 0405",
    "sg:postcode":"98039",
    "sg:province":"WA",
    "sg:tags":[
        "company",
        "holding"
    ],
    "wof:name":"Bright Street LLC",
    "wof:placetype":"venue"
},
  "geometry": {"coordinates":[-122.23868299999999,47.63555],"type":"Point"}
}