{
  "type": "Feature",
  "properties": {
    "addr:full":"600 Stewart St Seattle WA 98101",
    "addr:housenumber":"600",
    "addr:postcode":"98101",
    "addr:street":"Stewart St",
    "iso:country":"US",
    "sg:address":"600 Stewart St",
    "sg:city":"Seattle",
    "sg:classifiers":[
        {
            "category":"Professional",
            "subcategory":"Business Services",
            "type":"Services"
        }
    ],
    "sg:phone":"+1 206 922 3620",
    "sg:postcode":"98101",
    "sg:province":"WA",
    "sg:tags":[
        "management"
    ],
    "sg:website":"http://www.rlevansco.com",
    "wof:name":"Reign Capital Management",
    "wof:placetype":"venue"
},
  "geometry": {"coordinates":[-122.337013,47.613621],"type":"Point"}
}