{
  "type": "Feature",
  "properties": {
    "addr:full":"1311 SE Cardinal Ct Vancouver WA 98683",
    "addr:housenumber":"1311",
    "addr:postcode":"98683",
    "addr:street":"Se Cardinal Ct",
    "iso:country":"US",
    "sg:address":"1311 SE Cardinal Ct",
    "sg:city":"Vancouver",
    "sg:classifiers":[
        {
            "category":"Wholesale",
            "subcategory":"Computers",
            "type":"Manufacturing & Wholesale Goods"
        }
    ],
    "sg:phone":"+1 360 896 9833",
    "sg:postcode":"98683",
    "sg:province":"WA",
    "sg:website":"www.wacom.com",
    "wof:name":"Wacom Technology",
    "wof:placetype":"venue"
},
  "geometry": {"coordinates":[-122.49539900000001,45.611399],"type":"Point"}
}