{
  "type": "Feature",
  "properties": {
    "addr:full":"11614 63rd Street Ct E Puyallup WA 98372",
    "addr:housenumber":"11614",
    "addr:postcode":"98372",
    "addr:street":"63Rd Street Ct E",
    "iso:country":"US",
    "sg:address":"11614 63rd Street Ct E",
    "sg:city":"Puyallup",
    "sg:classifiers":[
        {
            "category":"Real Estate",
            "subcategory":"Real Estate Operator",
            "type":"Services"
        }
    ],
    "sg:phone":"+1 253 864 7933",
    "sg:postcode":"98372",
    "sg:province":"WA",
    "sg:tags":[
        "apartment"
    ],
    "wof:name":"Park View Apartment",
    "wof:placetype":"venue"
},
  "geometry": {"coordinates":[-122.274879,47.199781],"type":"Point"}
}