{
  "type": "Feature",
  "properties": {
    "addr:full":"13304 Silverhill Pl NW Silverdale WA 98383",
    "addr:housenumber":"13304",
    "addr:postcode":"98383",
    "addr:street":"Silverhill Pl Nw",
    "iso:country":"US",
    "sg:address":"13304 Silverhill Pl NW",
    "sg:city":"Silverdale",
    "sg:classifiers":[
        {
            "category":"Social Services",
            "subcategory":"Child Care",
            "type":"Services"
        }
    ],
    "sg:phone":"+1 360 779 9891",
    "sg:postcode":"98383",
    "sg:province":"WA",
    "sg:tags":[
        "day"
    ],
    "wof:name":"Angel",
    "wof:placetype":"venue"
},
  "geometry": {"coordinates":[-122.669693,47.685238],"type":"Point"}
}