{
  "type": "Feature",
  "properties": {
    "addr:full":"6808 NE Fourth Plain Blvd Ste. 1 Vancouver WA 98661",
    "addr:housenumber":"6808",
    "addr:postcode":"98661",
    "addr:street":"Ne Fourth Plain Blvd Ste. 1",
    "iso:country":"US",
    "sg:address":"6808 NE Fourth Plain Blvd Ste. 1",
    "sg:city":"Vancouver",
    "sg:classifiers":[
        {
            "category":"Professional",
            "type":"Services"
        },
        {
            "category":"Restaurant",
            "type":"Food & Drink"
        },
        {
            "category":"Fast Food",
            "type":"Food & Drink"
        }
    ],
    "sg:phone":"+1 605 624 5513",
    "sg:postcode":"98661",
    "sg:province":"WA",
    "sg:tags":[
        "delivery",
        "take",
        "pizza"
    ],
    "sg:website":"http://www.pizzahut.com",
    "wof:name":"Pizza Hut",
    "wof:placetype":"venue"
},
  "geometry": {"coordinates":[-122.60225800000001,45.644542],"type":"Point"}
}