{
  "type": "Feature",
  "properties": {
    "addr:full":"17225 114th Pl NE Granite Falls WA 98252",
    "addr:housenumber":"17225",
    "addr:postcode":"98252",
    "addr:street":"114Th Pl Ne",
    "iso:country":"US",
    "sg:address":"17225 114th Pl NE",
    "sg:city":"Granite Falls",
    "sg:classifiers":[
        {
            "category":"Organizations",
            "subcategory":"Religious Organization",
            "type":"Services"
        }
    ],
    "sg:phone":"+1 360 691 5290",
    "sg:postcode":"98252",
    "sg:province":"WA",
    "sg:tags":[
        "church"
    ],
    "sg:website":"www.fathershouseag.org",
    "wof:name":"Father's House",
    "wof:placetype":"venue"
},
  "geometry": {"coordinates":[-121.99657000000001,48.100007],"type":"Point"}
}