{
  "type": "Feature",
  "properties": {
    "addr:full":"30716 40th Ave E Graham WA 98338",
    "addr:housenumber":"30716",
    "addr:postcode":"98338",
    "addr:street":"40Th Ave E",
    "iso:country":"US",
    "sg:address":"30716 40th Ave E",
    "sg:city":"Graham",
    "sg:classifiers":[
        {
            "category":"Building & Trades",
            "subcategory":"Construction",
            "type":"Services"
        }
    ],
    "sg:phone":"+1 253 847 1894",
    "sg:postcode":"98338",
    "sg:province":"WA",
    "sg:tags":[
        "hanging",
        "contractor"
    ],
    "wof:name":"First Choice Painting",
    "wof:placetype":"venue"
},
  "geometry": {"coordinates":[-122.376392,46.979139],"type":"Point"}
}