{
  "type": "Feature",
  "properties": {
    "addr:full":"9050 35th Ave SW Seattle WA 98126",
    "addr:housenumber":"9050",
    "addr:postcode":"98126",
    "addr:street":"35Th Ave Sw",
    "iso:country":"US",
    "sg:address":"9050 35th Ave SW",
    "sg:city":"Seattle",
    "sg:classifiers":[
        {
            "category":"Wholesale",
            "subcategory":"Fruits & Vegetables",
            "type":"Manufacturing & Wholesale Goods"
        }
    ],
    "sg:phone":"+1 206 937 6760",
    "sg:postcode":"98126",
    "sg:province":"WA",
    "sg:tags":[
        "veggie"
    ],
    "wof:name":"Tony's Market",
    "wof:placetype":"venue"
},
  "geometry": {"coordinates":[-122.376999,47.522202],"type":"Point"}
}