{
  "type": "Feature",
  "properties": {
    "addr:full":"245 SE Paradise St Pullman WA 99163",
    "addr:housenumber":"245",
    "addr:postcode":"99163",
    "addr:street":"Se Paradise St",
    "iso:country":"US",
    "sg:address":"245 SE Paradise St",
    "sg:city":"Pullman",
    "sg:classifiers":[
        {
            "category":"Restaurant",
            "type":"Food & Drink"
        }
    ],
    "sg:phone":"+1 509 334 1455",
    "sg:postcode":"99163",
    "sg:province":"WA",
    "sg:tags":[
        "cafe"
    ],
    "wof:name":"Belladolci Mediterranean Cafe",
    "wof:placetype":"venue"
},
  "geometry": {"coordinates":[-117.180716,46.728859],"type":"Point"}
}