{
  "type": "Feature",
  "properties": {
    "addr:full":"12100 105th Pl NE Kirkland WA 98034",
    "addr:housenumber":"12100",
    "addr:postcode":"98034",
    "addr:street":"105Th Pl Ne",
    "iso:country":"US",
    "sg:address":"12100 105th Pl NE",
    "sg:city":"Kirkland",
    "sg:classifiers":[
        {
            "category":"Professional",
            "type":"Services"
        }
    ],
    "sg:phone":"+1 425 814 6191",
    "sg:postcode":"98034",
    "sg:province":"WA",
    "wof:name":"Draftek",
    "wof:placetype":"venue"
},
  "geometry": {"coordinates":[-122.200378,47.709061],"type":"Point"}
}