{
  "type": "Feature",
  "properties": {
    "addr:full":"5616 44th Ave SW Seattle WA 98136",
    "addr:housenumber":"5616",
    "addr:postcode":"98136",
    "addr:street":"44Th Ave Sw",
    "iso:country":"US",
    "sg:address":"5616 44th Ave SW",
    "sg:city":"Seattle",
    "sg:classifiers":[
        {
            "category":"Professional",
            "subcategory":"Engineering",
            "type":"Services"
        }
    ],
    "sg:phone":"+1 206 935 8323",
    "sg:postcode":"98136",
    "sg:province":"WA",
    "sg:tags":[
        "civil",
        "land",
        "surveying"
    ],
    "wof:name":"Siegenthaler Mark C",
    "wof:placetype":"venue"
},
  "geometry": {"coordinates":[-122.388496,47.550414],"type":"Point"}
}