{
  "type": "Feature",
  "properties": {
    "addr:full":"7550 33rd Ave NE Seattle WA 98115",
    "addr:housenumber":"7550",
    "addr:postcode":"98115",
    "addr:street":"33Rd Ave Ne",
    "iso:country":"US",
    "sg:address":"7550 33rd Ave NE",
    "sg:city":"Seattle",
    "sg:classifiers":[
        {
            "category":"Building & Trades",
            "subcategory":"Locksmith",
            "type":"Services"
        }
    ],
    "sg:phone":"+1 206 494 9349",
    "sg:postcode":"98115",
    "sg:province":"WA",
    "sg:tags":[
        "key"
    ],
    "wof:name":"A B C 24 Hour Locksmith",
    "wof:placetype":"venue"
},
  "geometry": {"coordinates":[-122.292419,47.684436],"type":"Point"}
}