{
  "type": "Feature",
  "properties": {
    "addr:full":"840 SE Bishop Blvd Pullman WA 99163",
    "addr:housenumber":"840",
    "addr:postcode":"99163",
    "addr:street":"Se Bishop Blvd",
    "iso:country":"US",
    "sg:address":"840 SE Bishop Blvd",
    "sg:city":"Pullman",
    "sg:classifiers":[
        {
            "category":"Banks & Credit Unions",
            "subcategory":"Bank",
            "type":"Services"
        }
    ],
    "sg:phone":"+1 509 332 2970",
    "sg:postcode":"99163",
    "sg:province":"WA",
    "sg:tags":[
        "loan",
        "real estate"
    ],
    "wof:name":"Countrywide Home Loans",
    "wof:placetype":"venue"
},
  "geometry": {"coordinates":[-117.17188299999999,46.713768],"type":"Point"}
}