{
  "type": "Feature",
  "properties": {
    "addr:full":"9030 Mero Rd Snohomish WA 98290",
    "addr:postcode":"9030;98290",
    "addr:street":"Mero Rd",
    "iso:country":"US",
    "sg:address":"9030 Mero Rd",
    "sg:city":"Snohomish",
    "sg:classifiers":[
        {
            "category":"Health Services",
            "subcategory":"Medical Lab",
            "type":"Services"
        }
    ],
    "sg:phone":"+1 360 568 7518",
    "sg:postcode":"98290",
    "sg:province":"WA",
    "sg:tags":[
        "laboratory",
        "dental"
    ],
    "wof:name":"I D T Inc",
    "wof:placetype":"venue"
},
  "geometry": {"coordinates":[-121.94283,47.914825],"type":"Point"}
}