{
  "type": "Feature",
  "properties": {
    "addr:full":"2626 E Evergreen Blvd Vancouver WA 98661",
    "addr:housenumber":"2626",
    "addr:postcode":"98661",
    "addr:street":"E Evergreen Blvd",
    "iso:country":"US",
    "sg:address":"2626 E Evergreen Blvd",
    "sg:city":"Vancouver",
    "sg:classifiers":[
        {
            "category":"Restaurant",
            "type":"Food & Drink"
        }
    ],
    "sg:phone":"+1 360 694 1750",
    "sg:postcode":"98661",
    "sg:province":"WA",
    "wof:name":"Christine's Restaurant",
    "wof:placetype":"venue"
},
  "geometry": {"coordinates":[-122.643997,45.6259],"type":"Point"}
}