{
  "type": "Feature",
  "properties": {
    "iso:country":"US",
    "sg:address":"8401 112th St E",
    "sg:city":"Puyallup",
    "sg:classifiers":[
        {
            "category":"Organizations",
            "subcategory":"Religious Organization",
            "type":"Services"
        }
    ],
    "sg:phone":"+1 253 848 4357",
    "sg:postcode":"98373",
    "sg:province":"WA",
    "sg:tags":[
        "church"
    ],
    "sg:website":"www.shepherdofthehill.org",
    "wof:name":"Shepherd Of The Hill",
    "wof:placetype":"venue"
},
  "geometry": {"coordinates":[-122.31491699999999,47.154966],"type":"Point"}
}