{
  "type": "Feature",
  "properties": {
    "addr:full":"127 E Division St Arlington WA 98223",
    "addr:housenumber":"127",
    "addr:postcode":"98223",
    "addr:street":"E Division St",
    "iso:country":"US",
    "sg:address":"127 E Division St",
    "sg:city":"Arlington",
    "sg:classifiers":[
        {
            "category":"Restaurant",
            "type":"Food & Drink"
        }
    ],
    "sg:phone":"+1 360 435 6601",
    "sg:postcode":"98223",
    "sg:province":"WA",
    "sg:tags":[
        "eating"
    ],
    "wof:name":"Fountain Drive-In",
    "wof:placetype":"venue"
},
  "geometry": {"coordinates":[-122.126108,48.198648],"type":"Point"}
}