{
  "type": "Feature",
  "properties": {
    "addr:full":"7513 Forest Dr NE Seattle WA 98115",
    "addr:housenumber":"7513",
    "addr:postcode":"98115",
    "addr:street":"Forest Dr Ne",
    "iso:country":"US",
    "sg:address":"7513 Forest Dr NE",
    "sg:city":"Seattle",
    "sg:classifiers":[
        {
            "category":"Building & Trades",
            "subcategory":"Landscaping Services",
            "type":"Services"
        }
    ],
    "sg:phone":"+1 206 525 1486",
    "sg:postcode":"98115",
    "sg:province":"WA",
    "sg:tags":[
        "tree"
    ],
    "wof:name":"Belton Family",
    "wof:placetype":"venue"
},
  "geometry": {"coordinates":[-122.275299,47.684251],"type":"Point"}
}