{
  "type": "Feature",
  "properties": {
    "iso:country":"US",
    "sg:address":"2502 Fruitvale Blvd",
    "sg:city":"Yakima",
    "sg:classifiers":[
        {
            "category":"Real Estate",
            "subcategory":"Real Estate Operator",
            "type":"Services"
        }
    ],
    "sg:phone":"+1 509 457 1855",
    "sg:postcode":"98902",
    "sg:province":"WA",
    "sg:tags":[
        "apartment"
    ],
    "wof:name":"Columbia Apartments",
    "wof:placetype":"venue"
},
  "geometry": {"coordinates":[-120.543024,46.613765],"type":"Point"}
}