{
  "type": "Feature",
  "properties": {
    "addr:full":"23817 SE 6th St Sammamish WA 98074",
    "addr:postcode":"23817;98074",
    "addr:street":"Se 6Th St",
    "iso:country":"US",
    "sg:address":"23817 SE 6th St",
    "sg:city":"Sammamish",
    "sg:classifiers":[
        {
            "category":"Travel",
            "subcategory":"Travel Agent",
            "type":"Entertainment"
        }
    ],
    "sg:phone":"+1 425 427 2338",
    "sg:postcode":"98074",
    "sg:province":"WA",
    "sg:tags":[
        "agency"
    ],
    "wof:name":"Mutual Net International Inc",
    "wof:placetype":"venue"
},
  "geometry": {"coordinates":[-122.022012,47.603217],"type":"Point"}
}