{
  "type": "Feature",
  "properties": {
    "addr:full":"5404 E E St Tacoma WA 98404",
    "addr:housenumber":"5404",
    "addr:postcode":"98404",
    "addr:street":"E E St",
    "iso:country":"US",
    "sg:address":"5404 E E St",
    "sg:city":"Tacoma",
    "sg:classifiers":[
        {
            "category":"Professional",
            "type":"Services"
        }
    ],
    "sg:phone":"+1 253 503 2640",
    "sg:postcode":"98404",
    "sg:province":"WA",
    "wof:name":"Top Coating",
    "wof:placetype":"venue"
},
  "geometry": {"coordinates":[-122.424725,47.208224],"type":"Point"}
}