{
  "type": "Feature",
  "properties": {
    "addr:full":"7878 Birch Bay Dr Blaine WA 98230",
    "addr:housenumber":"7878",
    "addr:postcode":"98230",
    "addr:street":"Birch Bay Dr",
    "iso:country":"US",
    "sg:address":"7878 Birch Bay Dr",
    "sg:city":"Blaine",
    "sg:classifiers":[
        {
            "category":"Restaurant",
            "type":"Food & Drink"
        }
    ],
    "sg:phone":"+1 360 371 3400",
    "sg:postcode":"98230",
    "sg:province":"WA",
    "sg:tags":[
        "style",
        "family"
    ],
    "wof:name":"C J's Beach House",
    "wof:placetype":"venue"
},
  "geometry": {"coordinates":[-122.74522,48.927296],"type":"Point"}
}