{
  "type": "Feature",
  "properties": {
    "addr:full":"11834 NE 112th St Kirkland WA 98033",
    "addr:housenumber":"11834",
    "addr:postcode":"98033",
    "addr:street":"Ne 112Th St",
    "iso:country":"US",
    "sg:address":"11834 NE 112th St",
    "sg:city":"Kirkland",
    "sg:classifiers":[
        {
            "category":"Autos & Motor Vehicles",
            "subcategory":"Automobile Sales",
            "type":"Retail Goods"
        },
        {
            "category":"Autos & Motor Vehicles",
            "subcategory":"Auto Supplies",
            "type":"Retail Goods"
        },
        {
            "category":"Sports & Exercise",
            "subcategory":"Race Track",
            "type":"Entertainment"
        }
    ],
    "sg:phone":"+1 425 820 0231",
    "sg:postcode":"98033",
    "sg:province":"WA",
    "sg:tags":[
        "car",
        "equipment",
        "performance",
        "new",
        "racing"
    ],
    "wof:name":"Cantrell Motorsports Inc",
    "wof:placetype":"venue"
},
  "geometry": {"coordinates":[-122.183122,47.700378],"type":"Point"}
}