{
  "type": "Feature",
  "properties": {
    "addr:full":"2038 Asher Ln Freeland WA 98249",
    "addr:housenumber":"2038",
    "addr:postcode":"98249",
    "addr:street":"Asher Ln",
    "iso:country":"US",
    "sg:address":"2038 Asher Ln",
    "sg:city":"Freeland",
    "sg:classifiers":[
        {
            "category":"Professional",
            "subcategory":"Testing Lab",
            "type":"Services"
        },
        {
            "category":"Building & Trades",
            "subcategory":"Plumbing",
            "type":"Services"
        },
        {
            "category":"Shopping",
            "subcategory":"Party Supplies",
            "type":"Retail Goods"
        },
        {
            "category":"Utilities",
            "subcategory":"Sewage",
            "type":"Services"
        }
    ],
    "sg:phone":"+1 360 331 3160",
    "sg:postcode":"98249",
    "sg:province":"WA",
    "sg:tags":[
        "systems-cleaning",
        "tank-testing",
        "tank",
        "septic",
        "toilets-portable",
        "system",
        "sewer",
        "cleaning",
        "plumbing-drain",
        "inspection"
    ],
    "wof:name":"Gabelein Brothers Septic Tank Pumping & Portable Toilets",
    "wof:placetype":"venue"
},
  "geometry": {"coordinates":[-122.506068,48.035855],"type":"Point"}
}