{
  "type": "Feature",
  "properties": {
    "addr:full":"310 Maple Park Ave SE Olympia WA 98501",
    "addr:housenumber":"310",
    "addr:postcode":"98501",
    "addr:street":"Maple Park Ave Se",
    "iso:country":"US",
    "sg:address":"310 Maple Park Ave SE",
    "sg:city":"Olympia",
    "sg:classifiers":[
        {
            "category":"Railroad",
            "type":"Transportation"
        }
    ],
    "sg:phone":"+1 360 705 7901",
    "sg:postcode":"98501",
    "sg:province":"WA",
    "sg:tags":[
        "agency",
        "railroads-ticket"
    ],
    "wof:name":"Ken Uznanfki",
    "wof:placetype":"venue"
},
  "geometry": {"coordinates":[-122.89825999999999,47.033839],"type":"Point"}
}