{
  "type": "Feature",
  "properties": {
    "addr:full":"1620 N Mamer Rd Spokane Valley WA 99216",
    "addr:housenumber":"1620",
    "addr:postcode":"99216",
    "addr:street":"N Mamer Rd",
    "iso:country":"US",
    "sg:address":"1620 N Mamer Rd",
    "sg:city":"Spokane Valley",
    "sg:classifiers":[
        {
            "category":"Building & Trades",
            "subcategory":"Construction",
            "type":"Services"
        }
    ],
    "sg:phone":"+1 509 891 5162",
    "sg:postcode":"99216",
    "sg:province":"WA",
    "sg:tags":[
        "general",
        "indus",
        "contractor",
        "electrical",
        "nonresidential"
    ],
    "sg:website":"www.inlandconstruction.com",
    "wof:name":"Inland Construction Company",
    "wof:placetype":"venue"
},
  "geometry": {"coordinates":[-117.22025600000001,47.673771],"type":"Point"}
}