{
  "type": "Feature",
  "properties": {
    "addr:full":"38308 Lakeshore Dr Woodland WA 98674",
    "addr:housenumber":"38308",
    "addr:postcode":"98674",
    "addr:street":"Lakeshore Dr",
    "iso:country":"US",
    "sg:address":"38308 Lakeshore Dr",
    "sg:city":"Woodland",
    "sg:classifiers":[
        {
            "category":"Professional",
            "subcategory":"Computer Services",
            "type":"Services"
        }
    ],
    "sg:phone":"+1 360 225 4950",
    "sg:postcode":"98674",
    "sg:province":"WA",
    "sg:tags":[
        "programing",
        "custom"
    ],
    "wof:name":"Csi Group",
    "wof:placetype":"venue"
},
  "geometry": {"coordinates":[-122.737786,45.89655],"type":"Point"}
}