{
  "type": "Feature",
  "properties": {
    "addr:full":"37123 Hansville Rd NE Hansville WA 98340",
    "addr:housenumber":"37123",
    "addr:postcode":"98340",
    "addr:street":"Hansville Rd Ne",
    "iso:country":"US",
    "sg:address":"37123 Hansville Rd NE",
    "sg:city":"Hansville",
    "sg:classifiers":[
        {
            "category":"Manufacturing",
            "subcategory":"Watercraft",
            "type":"Manufacturing & Wholesale Goods"
        }
    ],
    "sg:phone":"+1 360 638 1416",
    "sg:postcode":"98340",
    "sg:province":"WA",
    "sg:tags":[
        "boat"
    ],
    "wof:name":"Erv's Boat Shop",
    "wof:placetype":"venue"
},
  "geometry": {"coordinates":[-122.54049999999999,47.899222],"type":"Point"}
}