{
  "type": "Feature",
  "properties": {
    "addr:full":"404 N Pacific Ave Kelso WA 98626",
    "addr:housenumber":"404",
    "addr:postcode":"98626",
    "addr:street":"N Pacific Ave",
    "iso:country":"US",
    "sg:address":"404 N Pacific Ave",
    "sg:city":"Kelso",
    "sg:classifiers":[
        {
            "category":"Retail",
            "subcategory":"Auto Repair",
            "type":"Services"
        }
    ],
    "sg:phone":"+1 360 425 6242",
    "sg:postcode":"98626",
    "sg:province":"WA",
    "sg:tags":[
        "transmission"
    ],
    "wof:name":"Lee Thomas Transmission Svc",
    "wof:placetype":"venue"
},
  "geometry": {"coordinates":[-122.910194,46.14773],"type":"Point"}
}