{
  "type": "Feature",
  "properties": {
    "addr:full":"17401 NE 195th St Woodinville WA 98072",
    "addr:housenumber":"17401",
    "addr:postcode":"98072",
    "addr:street":"Ne 195Th St",
    "iso:country":"US",
    "sg:address":"17401 NE 195th St",
    "sg:city":"Woodinville",
    "sg:classifiers":[
        {
            "category":"Building & Trades",
            "subcategory":"Construction",
            "type":"Services"
        }
    ],
    "sg:phone":"+1 425 483 8761",
    "sg:postcode":"98072",
    "sg:province":"WA",
    "sg:tags":[
        "residential",
        "nonresidential"
    ],
    "wof:name":"Demaris Construction Inc",
    "wof:placetype":"venue"
},
  "geometry": {"coordinates":[-122.107202,47.768694],"type":"Point"}
}