{
  "type": "Feature",
  "properties": {
    "iso:country":"US",
    "sg:address":"23705 91st Pl W",
    "sg:city":"Edmonds",
    "sg:classifiers":[
        {
            "category":"Professional",
            "subcategory":"Art Services",
            "type":"Services"
        }
    ],
    "sg:phone":"+1 425 774 4845",
    "sg:postcode":"98026",
    "sg:province":"WA",
    "sg:tags":[
        "commercial",
        "design"
    ],
    "wof:name":"Sharon L Robins Graphic Design",
    "wof:placetype":"venue"
},
  "geometry": {"coordinates":[-122.355362,47.783806],"type":"Point"}
}