{
  "type": "Feature",
  "properties": {
    "addr:full":"2701 E Cherry St Seattle WA 98122",
    "addr:housenumber":"2701",
    "addr:postcode":"98122",
    "addr:street":"E Cherry St",
    "iso:country":"US",
    "sg:address":"2701 E Cherry St",
    "sg:city":"Seattle",
    "sg:classifiers":[
        {
            "category":"Manufacturing",
            "subcategory":"Tools & Machinery",
            "type":"Manufacturing & Wholesale Goods"
        }
    ],
    "sg:phone":"+1 509 214 9001",
    "sg:postcode":"98122",
    "sg:province":"WA",
    "sg:tags":[
        "cutting",
        "gear"
    ],
    "wof:name":"Kutt Gear Inc",
    "wof:placetype":"venue"
},
  "geometry": {"coordinates":[-122.297539,47.60799],"type":"Point"}
}