{
  "type": "Feature",
  "properties": {
    "addr:full":"18001 Bothell Way NE Bothell WA 98011",
    "addr:housenumber":"18001",
    "addr:postcode":"98011",
    "addr:street":"Bothell Way Ne",
    "iso:country":"US",
    "sg:address":"18001 Bothell Way NE",
    "sg:city":"Bothell",
    "sg:classifiers":[
        {
            "category":"Retail",
            "subcategory":"Self-service Laundry",
            "type":"Services"
        }
    ],
    "sg:phone":"+1 425 485 1814",
    "sg:postcode":"98011",
    "sg:province":"WA",
    "sg:tags":[
        "drycleaning",
        "plant",
        "coin"
    ],
    "wof:name":"Prime Cleaners",
    "wof:placetype":"venue"
},
  "geometry": {"coordinates":[-122.21034299999999,47.758963],"type":"Point"}
}