{
  "type": "Feature",
  "properties": {
    "addr:full":"801 E 1st St Cle Elum WA 98922",
    "addr:housenumber":"801",
    "addr:postcode":"98922",
    "addr:street":"E 1St St",
    "iso:country":"US",
    "sg:address":"801 E 1st St",
    "sg:city":"Cle Elum",
    "sg:classifiers":[
        {
            "category":"Shopping",
            "subcategory":"Hobbies, Toys, & Games",
            "type":"Retail Goods"
        }
    ],
    "sg:phone":"+1 509 674 2353",
    "sg:postcode":"98922",
    "sg:province":"WA",
    "wof:name":"Interactive Toys Crafts & More",
    "wof:placetype":"venue"
},
  "geometry": {"coordinates":[-120.9222,47.192942],"type":"Point"}
}