{
  "type": "Feature",
  "properties": {
    "addr:full":"1031 116th Ave NE Bellevue WA 98004",
    "addr:housenumber":"1031",
    "addr:postcode":"98004",
    "addr:street":"116Th Ave Ne",
    "iso:country":"US",
    "sg:address":"1031 116th Ave NE",
    "sg:city":"Bellevue",
    "sg:classifiers":[
        {
            "category":"Health Services",
            "subcategory":"Medical Lab",
            "type":"Services"
        }
    ],
    "sg:phone":"+1 206 324 6622",
    "sg:postcode":"98004",
    "sg:province":"WA",
    "wof:name":"Objective Medical Assessments",
    "wof:placetype":"venue"
},
  "geometry": {"coordinates":[-122.185669,47.620049],"type":"Point"}
}