{
  "type": "Feature",
  "properties": {
    "addr:full":"12150 Greenhaven Mukilteo WA 98275",
    "addr:housenumber":"12150",
    "addr:postcode":"98275",
    "addr:street":"Greenhaven Mukilteo",
    "iso:country":"US",
    "sg:address":"12150 Greenhaven",
    "sg:city":"Mukilteo",
    "sg:classifiers":[
        {
            "category":"Health Services",
            "subcategory":"Doctor",
            "type":"Services"
        },
        {
            "category":"Personal",
            "subcategory":"Beauty Salon",
            "type":"Services"
        },
        {
            "category":"Personal",
            "subcategory":"Hair Removal",
            "type":"Services"
        }
    ],
    "sg:phone":"+1 425 608 2642",
    "sg:postcode":"98275",
    "sg:province":"WA",
    "sg:tags":[
        "wig",
        "piece",
        "weaving",
        "stylist",
        "replacement"
    ],
    "sg:website":"http://www.sandyshairexpressions.net",
    "wof:name":"Sandy's Hair Expressions",
    "wof:placetype":"venue"
},
  "geometry": {"coordinates":[-122.297157,47.88797],"type":"Point"}
}