{
  "type": "Feature",
  "properties": {
    "addr:full":"56 Ocosta 6th St Aberdeen WA 98520",
    "addr:housenumber":"56",
    "addr:postcode":"98520",
    "addr:street":"Ocosta 6Th St",
    "iso:country":"US",
    "sg:address":"56 Ocosta 6th St",
    "sg:city":"Aberdeen",
    "sg:classifiers":[
        {
            "category":"Utilities",
            "subcategory":"Telephone",
            "type":"Services"
        },
        {
            "category":"Professional",
            "subcategory":"Computer Services",
            "type":"Services"
        }
    ],
    "sg:phone":"+1 360 648 0021",
    "sg:postcode":"98520",
    "sg:province":"WA",
    "sg:tags":[
        "communications",
        "internet"
    ],
    "wof:name":"Factual Design",
    "wof:placetype":"venue"
},
  "geometry": {"coordinates":[-124.03867200000001,46.886281],"type":"Point"}
}