{
  "type": "Feature",
  "properties": {
    "addr:full":"5700 Lateral C Rd Wapato WA 98951",
    "addr:postcode":"5700;98951",
    "addr:street":"Lateral C Rd",
    "iso:country":"US",
    "sg:address":"5700 Lateral C Rd",
    "sg:city":"Wapato",
    "sg:classifiers":[
        {
            "category":"Farming",
            "subcategory":"Vineyard",
            "type":"Manufacturing & Wholesale Goods"
        }
    ],
    "sg:phone":"+1 509 848 2242",
    "sg:postcode":"98951",
    "sg:province":"WA",
    "sg:tags":[
        "grape"
    ],
    "wof:name":"David A Bouchey",
    "wof:placetype":"venue"
},
  "geometry": {"coordinates":[-120.523298,46.394494],"type":"Point"}
}