{
  "type": "Feature",
  "properties": {
    "addr:full":"25421 32nd Pl S Kent WA 98032",
    "addr:housenumber":"25421",
    "addr:postcode":"98032",
    "addr:street":"32Nd Pl S",
    "iso:country":"US",
    "sg:address":"25421 32nd Pl S",
    "sg:city":"Kent",
    "sg:classifiers":[
        {
            "category":"Professional",
            "type":"Services"
        }
    ],
    "sg:phone":"+1 206 226 9730",
    "sg:postcode":"98032",
    "sg:province":"WA",
    "wof:name":"Johns Power Washing",
    "wof:placetype":"venue"
},
  "geometry": {"coordinates":[-122.290848,47.374139],"type":"Point"}
}