{
  "type": "Feature",
  "properties": {
    "addr:full":"2319 S Tacoma Way Tacoma WA 98409",
    "addr:housenumber":"2319",
    "addr:postcode":"98409",
    "addr:street":"S Tacoma Way",
    "iso:country":"US",
    "sg:address":"2319 S Tacoma Way",
    "sg:city":"Tacoma",
    "sg:classifiers":[
        {
            "category":"Manufacturing",
            "subcategory":"Building Materials",
            "type":"Manufacturing & Wholesale Goods"
        }
    ],
    "sg:phone":"+1 253 472 5900",
    "sg:postcode":"98409",
    "sg:province":"WA",
    "sg:tags":[
        "metal",
        "mfg"
    ],
    "wof:name":"Johnson's Millwork Inc",
    "wof:placetype":"venue"
},
  "geometry": {"coordinates":[-122.468065,47.231383],"type":"Point"}
}