{
  "type": "Feature",
  "properties": {
    "addr:full":"25512 122nd Pl SE Kent WA 98030",
    "addr:housenumber":"25512",
    "addr:postcode":"98030",
    "addr:street":"122Nd Pl Se",
    "iso:country":"US",
    "sg:address":"25512 122nd Pl SE",
    "sg:city":"Kent",
    "sg:classifiers":[
        {
            "category":"Building & Trades",
            "subcategory":"Construction",
            "type":"Services"
        }
    ],
    "sg:phone":"+1 253 334 7042",
    "sg:postcode":"98030",
    "sg:province":"WA",
    "sg:tags":[
        "contractor"
    ],
    "wof:name":"J M L Construction Company",
    "wof:placetype":"venue"
},
  "geometry": {"coordinates":[-122.17849200000001,47.372511],"type":"Point"}
}