{
  "type": "Feature",
  "properties": {
    "addr:full":"722 4th Ave Seattle WA 98104",
    "addr:housenumber":"722",
    "addr:postcode":"98104",
    "addr:street":"4Th Ave",
    "iso:country":"US",
    "sg:address":"722 4th Ave",
    "sg:city":"Seattle",
    "sg:classifiers":[
        {
            "category":"Restaurant",
            "type":"Food & Drink"
        }
    ],
    "sg:menulink":"http://www.allmenus.com/wa/seattle/3503-mccormicks-fish-house/menu/",
    "sg:phone":"+1 206 682 3900",
    "sg:postcode":"98104",
    "sg:province":"WA",
    "sg:tags":[
        "seafood",
        "american"
    ],
    "wof:name":"McCormick's Fish House",
    "wof:placetype":"venue"
},
  "geometry": {"coordinates":[-122.33103,47.60416],"type":"Point"}
}