{
  "type": "Feature",
  "properties": {
    "addr:full":"581 Conklin Meadows Rd Newport WA 99156",
    "addr:housenumber":"581",
    "addr:postcode":"99156",
    "addr:street":"Conklin Meadows Rd",
    "iso:country":"US",
    "sg:address":"581 Conklin Meadows Rd",
    "sg:city":"Newport",
    "sg:classifiers":[
        {
            "category":"Home & Garden",
            "subcategory":"Hardware",
            "type":"Retail Goods"
        }
    ],
    "sg:phone":"+1 509 447 2564",
    "sg:postcode":"99156",
    "sg:province":"WA",
    "wof:name":"Locks Northwest",
    "wof:placetype":"venue"
},
  "geometry": {"coordinates":[-117.19552299999999,48.247561],"type":"Point"}
}