{
  "type": "Feature",
  "properties": {
    "addr:full":"1804 18th St Lynden WA 98264",
    "addr:housenumber":"1804",
    "addr:postcode":"98264",
    "addr:street":"18Th St",
    "iso:country":"US",
    "sg:address":"1804 18th St",
    "sg:city":"Lynden",
    "sg:classifiers":[
        {
            "category":"Restaurant",
            "type":"Food & Drink"
        }
    ],
    "sg:menulink":"http://www.allmenus.com/wa/lynden/86143-little-caesars-pizza/menu/",
    "sg:phone":"+1 360 354 8656",
    "sg:postcode":"98264",
    "sg:province":"WA",
    "sg:tags":[
        "american",
        "pizza"
    ],
    "wof:name":"Little Caesar's Pizza",
    "wof:placetype":"venue"
},
  "geometry": {"coordinates":[-122.472463,48.94089],"type":"Point"}
}