{
  "type": "Feature",
  "properties": {
    "addr:full":"460 N Market Blvd Chehalis WA 98532",
    "addr:housenumber":"460",
    "addr:postcode":"98532",
    "addr:street":"N Market Blvd",
    "iso:country":"US",
    "sg:address":"460 N Market Blvd",
    "sg:city":"Chehalis",
    "sg:classifiers":[
        {
            "category":"Retail",
            "subcategory":"Repair Shop",
            "type":"Services"
        }
    ],
    "sg:phone":"+1 360 748 1257",
    "sg:postcode":"98532",
    "sg:province":"WA",
    "sg:tags":[
        "part",
        "watch",
        "clock"
    ],
    "wof:name":"Jerry's Clock Shop",
    "wof:placetype":"venue"
},
  "geometry": {"coordinates":[-122.969174,46.664864],"type":"Point"}
}