{
  "type": "Feature",
  "properties": {
    "addr:full":"265 Hudson St Port Townsend WA 98368",
    "addr:housenumber":"265",
    "addr:postcode":"98368",
    "addr:street":"Hudson St",
    "iso:country":"US",
    "sg:address":"265 Hudson St",
    "sg:city":"Port Townsend",
    "sg:classifiers":[
        {
            "category":"Restaurant",
            "type":"Food & Drink"
        }
    ],
    "sg:phone":"+1 360 385 4810",
    "sg:postcode":"98368",
    "sg:province":"WA",
    "wof:name":"Shanghai Chinese Restaurant",
    "wof:placetype":"venue"
},
  "geometry": {"coordinates":[-122.75137700000001,48.118889],"type":"Point"}
}