{
  "type": "Feature",
  "properties": {
    "addr:full":"555 Manley Rd Bellingham WA 98229",
    "addr:housenumber":"555",
    "addr:postcode":"98229",
    "addr:street":"Manley Rd",
    "iso:country":"US",
    "sg:address":"555 Manley Rd",
    "sg:city":"Bellingham",
    "sg:classifiers":[
        {
            "category":"Building & Trades",
            "subcategory":"Electrical",
            "type":"Services"
        }
    ],
    "sg:phone":"+1 360 671 1111",
    "sg:postcode":"98229",
    "sg:province":"WA",
    "sg:tags":[
        "electrical",
        "contractor"
    ],
    "wof:name":"Arrow Electric NW",
    "wof:placetype":"venue"
},
  "geometry": {"coordinates":[-122.36972900000001,48.666031],"type":"Point"}
}