{
  "type": "Feature",
  "properties": {
    "addr:full":"6812 50th Ave E Tacoma WA 98443",
    "addr:housenumber":"6812",
    "addr:postcode":"98443",
    "addr:street":"50Th Ave E",
    "iso:country":"US",
    "sg:address":"6812 50th Ave E",
    "sg:city":"Tacoma",
    "sg:classifiers":[
        {
            "category":"Social Services",
            "subcategory":"Child Care",
            "type":"Services"
        }
    ],
    "sg:phone":"+1 253 537 6009",
    "sg:postcode":"98443",
    "sg:province":"WA",
    "sg:tags":[
        "day"
    ],
    "wof:name":"Beni Janet A Home Day Care",
    "wof:placetype":"venue"
},
  "geometry": {"coordinates":[-122.362718,47.195281],"type":"Point"}
}