{
  "type": "Feature",
  "properties": {
    "addr:full":"23830 Hwy 99 Edmonds WA 98026",
    "addr:housenumber":"23830",
    "addr:postcode":"98026",
    "addr:street":"Hwy 99",
    "iso:country":"US",
    "sg:address":"23830 Hwy 99",
    "sg:city":"Edmonds",
    "sg:classifiers":[
        {
            "category":"Personal",
            "subcategory":"Beauty Salon",
            "type":"Services"
        }
    ],
    "sg:phone":"+1 425 774 9999",
    "sg:postcode":"98026",
    "sg:province":"WA",
    "sg:tags":[
        "manicuring"
    ],
    "wof:name":"Ledo's Nails",
    "wof:placetype":"venue"
},
  "geometry": {"coordinates":[-122.344989,47.781445],"type":"Point"}
}