{
  "type": "Feature",
  "properties": {
    "addr:full":"9714 3rd Ave NE Seattle WA 98115",
    "addr:housenumber":"9714",
    "addr:postcode":"98115",
    "addr:street":"3Rd Ave Ne",
    "iso:country":"US",
    "sg:address":"9714 3rd Ave NE",
    "sg:city":"Seattle",
    "sg:classifiers":[
        {
            "category":"Health Services",
            "subcategory":"Doctor",
            "type":"Services"
        }
    ],
    "sg:phone":"+1 206 523 7600",
    "sg:postcode":"98115",
    "sg:province":"WA",
    "wof:name":"Trenor Melvyn H H DDS PS",
    "wof:placetype":"venue"
},
  "geometry": {"coordinates":[-122.325739,47.701242],"type":"Point"}
}