{
  "type": "Feature",
  "properties": {
    "addr:full":"15824 SE 47th St Bellevue WA 98006",
    "addr:postcode":"15824;98006",
    "addr:street":"Se 47Th St",
    "iso:country":"US",
    "sg:address":"15824 SE 47th St",
    "sg:city":"Bellevue",
    "sg:classifiers":[
        {
            "category":"Professional",
            "subcategory":"Business Services",
            "type":"Services"
        }
    ],
    "sg:phone":"+1 425 562 8800",
    "sg:postcode":"98006",
    "sg:province":"WA",
    "wof:name":"J Economus Designs",
    "wof:placetype":"venue"
},
  "geometry": {"coordinates":[-122.12915599999999,47.561435],"type":"Point"}
}