{
  "type": "Feature",
  "properties": {
    "addr:full":"13120 228th St E Graham WA 98338",
    "addr:housenumber":"13120",
    "addr:postcode":"98338",
    "addr:street":"228Th St E",
    "iso:country":"US",
    "sg:address":"13120 228th St E",
    "sg:city":"Graham",
    "sg:classifiers":[
        {
            "category":"Real Estate",
            "subcategory":"Real Estate Services",
            "type":"Services"
        },
        {
            "category":"Banks & Credit Unions",
            "subcategory":"Financial Services",
            "type":"Services"
        }
    ],
    "sg:phone":"+1 253 893 6300",
    "sg:postcode":"98338",
    "sg:province":"WA",
    "sg:tags":[
        "loan",
        "processing"
    ],
    "wof:name":"Wholesale Mortgage",
    "wof:placetype":"venue"
},
  "geometry": {"coordinates":[-122.25615000000001,47.049012],"type":"Point"}
}