{
  "type": "Feature",
  "properties": {
    "addr:full":"29216 NE Big Rock Rd Duvall WA 98019",
    "addr:housenumber":"29216",
    "addr:postcode":"98019",
    "addr:street":"Ne Big Rock Rd",
    "iso:country":"US",
    "sg:address":"29216 NE Big Rock Rd",
    "sg:city":"Duvall",
    "sg:classifiers":[
        {
            "category":"Building & Trades",
            "subcategory":"Landscaping Services",
            "type":"Services"
        }
    ],
    "sg:phone":"+1 425 788 2567",
    "sg:postcode":"98019",
    "sg:province":"WA",
    "sg:tags":[
        "lawn",
        "maintenance",
        "grounds"
    ],
    "sg:website":"www.jebcoservices.com",
    "wof:name":"Jebco",
    "wof:placetype":"venue"
},
  "geometry": {"coordinates":[-121.943258,47.712844],"type":"Point"}
}