{
  "type": "Feature",
  "properties": {
    "iso:country":"US",
    "sg:address":"2218 81st Ave SE",
    "sg:city":"Mercer Island",
    "sg:classifiers":[
        {
            "category":"Professional",
            "subcategory":"Engineering",
            "type":"Services"
        }
    ],
    "sg:phone":"+1 206 232 0162",
    "sg:postcode":"98040",
    "sg:province":"WA",
    "wof:name":"Ward Wilson",
    "wof:placetype":"venue"
},
  "geometry": {"coordinates":[-122.230581,47.589263],"type":"Point"}
}