{
  "type": "Feature",
  "properties": {
    "addr:full":"1133 W James St Kent WA 98032",
    "addr:housenumber":"1133",
    "addr:postcode":"98032",
    "addr:street":"W James St",
    "iso:country":"US",
    "sg:address":"1133 W James St",
    "sg:city":"Kent",
    "sg:classifiers":[
        {
            "category":"Restaurant",
            "type":"Food & Drink"
        }
    ],
    "sg:phone":"+1 253 520 7929",
    "sg:postcode":"98032",
    "sg:province":"WA",
    "sg:tags":[
        "shop",
        "coffee"
    ],
    "wof:name":"Jazzed Espresso",
    "wof:placetype":"venue"
},
  "geometry": {"coordinates":[-122.24730599999999,47.386806],"type":"Point"}
}