{
  "type": "Feature",
  "properties": {
    "addr:full":"2311 E Division St Mt Vernon WA 98274",
    "addr:housenumber":"2311",
    "addr:postcode":"98274",
    "addr:street":"E Division St",
    "iso:country":"US",
    "sg:address":"2311 E Division St",
    "sg:city":"Mt Vernon",
    "sg:classifiers":[
        {
            "category":"Social Services",
            "subcategory":"Adult Care",
            "type":"Services"
        },
        {
            "category":"Health Services",
            "subcategory":"Nursing And Care Facility",
            "type":"Services"
        }
    ],
    "sg:phone":"+1 360 428 0222",
    "sg:postcode":"98274",
    "sg:province":"WA",
    "sg:tags":[
        "residential",
        "retirement",
        "intermediate",
        "community",
        "home"
    ],
    "wof:name":"Logan Creek Retirement Ctr",
    "wof:placetype":"venue"
},
  "geometry": {"coordinates":[-122.31155699999999,48.421053],"type":"Point"}
}