{
  "type": "Feature",
  "properties": {
    "addr:full":"14911 E 17th Ct Veradale WA 99037",
    "addr:housenumber":"14911",
    "addr:postcode":"99037",
    "addr:street":"E 17Th Ct",
    "iso:country":"US",
    "sg:address":"14911 E 17th Ct",
    "sg:city":"Veradale",
    "sg:classifiers":[
        {
            "category":"Education",
            "subcategory":"School",
            "type":"Public Place"
        }
    ],
    "sg:phone":"+1 509 924 8664",
    "sg:postcode":"99037",
    "sg:province":"WA",
    "wof:name":"Odyssey",
    "wof:placetype":"venue"
},
  "geometry": {"coordinates":[-117.20369599999999,47.64161],"type":"Point"}
}