{
  "type": "Feature",
  "properties": {
    "addr:full":"8458 US Hwy 101 South Bend WA 98586",
    "addr:housenumber":"8458",
    "addr:postcode":"98586",
    "addr:street":"Us Hwy 101",
    "iso:country":"US",
    "sg:address":"8458 US Hwy 101",
    "sg:city":"South Bend",
    "sg:classifiers":[
        {
            "category":"Farming",
            "subcategory":"Livestock Farm",
            "type":"Manufacturing & Wholesale Goods"
        }
    ],
    "sg:phone":"+1 360 875 6486",
    "sg:postcode":"98586",
    "sg:province":"WA",
    "sg:tags":[
        "beef",
        "feedlot",
        "cattle"
    ],
    "wof:name":"Thomas Allen Graves",
    "wof:placetype":"venue"
},
  "geometry": {"coordinates":[-123.82279,46.678204],"type":"Point"}
}