{
  "type": "Feature",
  "properties": {
    "addr:full":"4428 176th St SW Lynnwood WA 98037",
    "addr:housenumber":"4428",
    "addr:postcode":"98037",
    "addr:street":"176Th St Sw",
    "iso:country":"US",
    "sg:address":"4428 176th St SW",
    "sg:city":"Lynnwood",
    "sg:classifiers":[
        {
            "category":"Real Estate",
            "subcategory":"Real Estate Operator",
            "type":"Services"
        }
    ],
    "sg:phone":"+1 425 745 4044",
    "sg:postcode":"98037",
    "sg:province":"WA",
    "sg:tags":[
        "building",
        "apartment"
    ],
    "wof:name":"Hidden Grove Apartments",
    "wof:placetype":"venue"
},
  "geometry": {"coordinates":[-122.293076,47.839105],"type":"Point"}
}