{
  "type": "Feature",
  "properties": {
    "addr:full":"1500 Mojonnier Rd Walla Walla WA 99362",
    "addr:housenumber":"1500",
    "addr:postcode":"99362",
    "addr:street":"Mojonnier Rd",
    "iso:country":"US",
    "sg:address":"1500 Mojonnier Rd",
    "sg:city":"Walla Walla",
    "sg:classifiers":[
        {
            "category":"Building & Trades",
            "subcategory":"Construction",
            "type":"Services"
        }
    ],
    "sg:phone":"+1 509 522 0971",
    "sg:postcode":"99362",
    "sg:province":"WA",
    "sg:tags":[
        "nonresidential"
    ],
    "wof:name":"Teds Construction",
    "wof:placetype":"venue"
},
  "geometry": {"coordinates":[-118.417322,46.027675],"type":"Point"}
}