{
  "type": "Feature",
  "properties": {
    "addr:full":"17705 State Rte 170 E Warden WA 98857",
    "addr:housenumber":"17705",
    "addr:postcode":"98857",
    "addr:street":"State Rte 170 E Warden",
    "iso:country":"US",
    "sg:address":"17705 State Rte 170 E",
    "sg:city":"Warden",
    "sg:classifiers":[
        {
            "category":"Autos & Motor Vehicles",
            "subcategory":"Fuel & Gas Station",
            "type":"Retail Goods"
        }
    ],
    "sg:phone":"+1 509 349 2514",
    "sg:postcode":"98857",
    "sg:province":"WA",
    "sg:tags":[
        "convenience",
        "station",
        "store"
    ],
    "wof:name":"Pheasant Run",
    "wof:placetype":"venue"
},
  "geometry": {"coordinates":[-119.117859,46.970087],"type":"Point"}
}