{
  "type": "Feature",
  "properties": {
    "addr:full":"15333 NE 66th Ct Redmond WA 98052",
    "addr:housenumber":"15333",
    "addr:postcode":"98052",
    "addr:street":"Ne 66Th Ct",
    "iso:country":"US",
    "sg:address":"15333 NE 66th Ct",
    "sg:city":"Redmond",
    "sg:classifiers":[
        {
            "category":"Social Services",
            "subcategory":"Child Care",
            "type":"Services"
        }
    ],
    "sg:phone":"+1 425 556 4376",
    "sg:postcode":"98052",
    "sg:province":"WA",
    "sg:tags":[
        "centers-adult",
        "day"
    ],
    "sg:website":"http://www.steppingstonesresort.com",
    "wof:name":"Stepping Stone Cottage",
    "wof:placetype":"venue"
},
  "geometry": {"coordinates":[-122.135918,47.665118],"type":"Point"}
}