{
  "type": "Feature",
  "properties": {
    "addr:full":"3426 Kromer Ave Everett WA 98201",
    "addr:housenumber":"3426",
    "addr:postcode":"98201",
    "addr:street":"Kromer Ave",
    "iso:country":"US",
    "sg:address":"3426 Kromer Ave",
    "sg:city":"Everett",
    "sg:classifiers":[
        {
            "category":"Home & Garden",
            "subcategory":"Home Furnishings",
            "type":"Retail Goods"
        }
    ],
    "sg:phone":"+1 425 303 8120",
    "sg:postcode":"98201",
    "sg:province":"WA",
    "wof:name":"Amazing Spaces",
    "wof:placetype":"venue"
},
  "geometry": {"coordinates":[-122.218812,47.971472],"type":"Point"}
}