{
  "type": "Feature",
  "properties": {
    "addr:full":"6718 Roosevelt Way NE Seattle WA 98115",
    "addr:housenumber":"6718",
    "addr:postcode":"98115",
    "addr:street":"Roosevelt Way Ne",
    "iso:country":"US",
    "sg:address":"6718 Roosevelt Way NE",
    "sg:city":"Seattle",
    "sg:classifiers":[
        {
            "category":"Retail",
            "subcategory":"Auto Repair",
            "type":"Services"
        }
    ],
    "sg:phone":"+1 206 523 6040",
    "sg:postcode":"98115",
    "sg:province":"WA",
    "sg:website":"www.seattleautoservicecenter.com",
    "wof:name":"Seattle Auto Service Center",
    "wof:placetype":"venue"
},
  "geometry": {"coordinates":[-122.31732100000001,47.677869],"type":"Point"}
}