{
  "type": "Feature",
  "properties": {
    "addr:full":"5303 Shilshole Ave NW Seattle WA 98107",
    "addr:housenumber":"5303",
    "addr:postcode":"98107",
    "addr:street":"Shilshole Ave Nw",
    "iso:country":"US",
    "sg:address":"5303 Shilshole Ave NW",
    "sg:city":"Seattle",
    "sg:classifiers":[
        {
            "category":"Manufacturing",
            "subcategory":"Food",
            "type":"Manufacturing & Wholesale Goods"
        }
    ],
    "sg:phone":"+1 206 783 3818",
    "sg:postcode":"98107",
    "sg:province":"WA",
    "sg:tags":[
        "co",
        "gear",
        "restaurant",
        "frozen",
        "seafood",
        "process",
        "fishing"
    ],
    "sg:website":"http://www.tridentseafoods.com",
    "wof:name":"Trident Seafoods Corporation",
    "wof:placetype":"venue"
},
  "geometry": {"coordinates":[-122.38404800000001,47.665932],"type":"Point"}
}