{
  "type": "Feature",
  "properties": {
    "addr:full":"6500 Ravenna Ave NE Seattle WA 98115",
    "addr:housenumber":"6500",
    "addr:postcode":"98115",
    "addr:street":"Ravenna Ave Ne",
    "iso:country":"US",
    "sg:address":"6500 Ravenna Ave NE",
    "sg:city":"Seattle",
    "sg:classifiers":[
        {
            "category":"Food & Beverages",
            "subcategory":"Liquor & Beverages",
            "type":"Retail Goods"
        }
    ],
    "sg:phone":"+1 206 524 9500",
    "sg:postcode":"98115",
    "sg:province":"WA",
    "sg:tags":[
        "beer",
        "spirit",
        "wine"
    ],
    "sg:website":"www.mccarthyandschiering.com",
    "wof:name":"McCarthy & Schiering Wine Merchants",
    "wof:placetype":"venue"
},
  "geometry": {"coordinates":[-122.30381300000001,47.67767],"type":"Point"}
}