{
  "type": "Feature",
  "properties": {
    "addr:full":"6269 19th Ave NE Seattle WA 98115",
    "addr:housenumber":"6269",
    "addr:postcode":"98115",
    "addr:street":"19Th Ave Ne",
    "iso:country":"US",
    "sg:address":"6269 19th Ave NE",
    "sg:city":"Seattle",
    "sg:classifiers":[
        {
            "category":"Professional",
            "subcategory":"Computer Services",
            "type":"Services"
        }
    ],
    "sg:phone":"+1 206 522 3256",
    "sg:postcode":"98115",
    "sg:province":"WA",
    "sg:tags":[
        "consultant",
        "designer",
        "system",
        "related"
    ],
    "wof:name":"Siebert Data Works",
    "wof:placetype":"venue"
},
  "geometry": {"coordinates":[-122.30763399999999,47.674161],"type":"Point"}
}