{
  "type": "Feature",
  "properties": {
    "addr:full":"3205 Harrison Ave NW Olympia WA 98502",
    "addr:housenumber":"3205",
    "addr:postcode":"olympia wa 98502",
    "addr:street":"Harrison Ave Nw",
    "iso:country":"US",
    "sg:address":"3205 Harrison Ave NW",
    "sg:city":"Olympia",
    "sg:classifiers":[
        {
            "category":"Utilities",
            "subcategory":"Fuel Oil & Lpg",
            "type":"Services"
        }
    ],
    "sg:phone":"+1 360 352 3498",
    "sg:postcode":"98502",
    "sg:province":"WA",
    "wof:name":"Fast Shop",
    "wof:placetype":"venue"
},
  "geometry": {"coordinates":[-122.949567,47.047039],"type":"Point"}
}