{
  "type": "Feature",
  "properties": {
    "iso:country":"US",
    "sg:address":"12805 Shorewood Dr SW",
    "sg:city":"Seattle",
    "sg:classifiers":[
        {
            "category":"Building & Trades",
            "subcategory":"Construction",
            "type":"Services"
        }
    ],
    "sg:phone":"+1 206 619 1417",
    "sg:postcode":"98146",
    "sg:province":"WA",
    "sg:tags":[
        "residential"
    ],
    "wof:name":"Jem Contractors Inc",
    "wof:placetype":"venue"
},
  "geometry": {"coordinates":[-122.35841600000001,47.487707],"type":"Point"}
}