{
  "type": "Feature",
  "properties": {
    "addr:full":"1231 Vandercook Way Longview WA 98632",
    "addr:housenumber":"1231",
    "addr:postcode":"98632",
    "addr:street":"Vandercook Way",
    "iso:country":"US",
    "sg:address":"1231 Vandercook Way",
    "sg:city":"Longview",
    "sg:classifiers":[
        {
            "category":"Organizations",
            "subcategory":"Membership Organization",
            "type":"Services"
        }
    ],
    "sg:phone":"+1 360 501 6540",
    "sg:postcode":"98632",
    "sg:province":"WA",
    "wof:name":"Longview Stageworks",
    "wof:placetype":"venue"
},
  "geometry": {"coordinates":[-122.932625,46.140915],"type":"Point"}
}