{
  "type": "Feature",
  "properties": {
    "addr:full":"18109 SE 35th St Vancouver WA 98683",
    "addr:postcode":"18109;98683",
    "addr:street":"Se 35Th St",
    "iso:country":"US",
    "sg:address":"18109 SE 35th St",
    "sg:city":"Vancouver",
    "sg:classifiers":[
        {
            "category":"Social Services",
            "type":"Services"
        }
    ],
    "sg:phone":"+1 360 885 0096",
    "sg:postcode":"98683",
    "sg:province":"WA",
    "wof:name":"A Way Through Counseling Pllc",
    "wof:placetype":"venue"
},
  "geometry": {"coordinates":[-122.484735,45.596085],"type":"Point"}
}