{
  "type": "Feature",
  "properties": {
    "addr:full":"2812 E 4th Ave Spokane WA 99202",
    "addr:housenumber":"2812",
    "addr:postcode":"99202",
    "addr:street":"E 4Th Ave",
    "iso:country":"US",
    "sg:address":"2812 E 4th Ave",
    "sg:city":"Spokane",
    "sg:classifiers":[
        {
            "category":"Freight",
            "type":"Transportation"
        }
    ],
    "sg:phone":"+1 509 535 8294",
    "sg:postcode":"99202",
    "sg:province":"WA",
    "sg:tags":[
        "trucking"
    ],
    "wof:name":"Taxi Trucks",
    "wof:placetype":"venue"
},
  "geometry": {"coordinates":[-117.368414,47.652643],"type":"Point"}
}