{
  "type": "Feature",
  "properties": {
    "addr:full":"4929 219th Ave SW Centralia WA 98531",
    "addr:housenumber":"4929",
    "addr:postcode":"98531",
    "addr:street":"219Th Ave Sw",
    "iso:country":"US",
    "sg:address":"4929 219th Ave SW",
    "sg:city":"Centralia",
    "sg:classifiers":[
        {
            "category":"Manufacturing",
            "subcategory":"Buildings",
            "type":"Manufacturing & Wholesale Goods"
        },
        {
            "category":"Building & Trades",
            "subcategory":"Construction",
            "type":"Services"
        }
    ],
    "sg:phone":"+1 360 807 6524",
    "sg:postcode":"98531",
    "sg:province":"WA",
    "sg:tags":[
        "industrial",
        "system",
        "specialty",
        "builder",
        "heating",
        "contractor",
        "contractors-commercial",
        "home",
        "air conditioning"
    ],
    "wof:name":"Hub City Homes",
    "wof:placetype":"venue"
},
  "geometry": {"coordinates":[-122.98781099999999,46.771743],"type":"Point"}
}