{
  "type": "Feature",
  "properties": {
    "addr:full":"2626 NE University Village St Seattle WA 98105",
    "addr:housenumber":"2626",
    "addr:postcode":"98105",
    "addr:street":"Ne University Village St",
    "iso:country":"US",
    "sg:address":"2626 NE University Village St",
    "sg:city":"Seattle",
    "sg:classifiers":[
        {
            "category":"Food & Beverages",
            "subcategory":"Candy",
            "type":"Retail Goods"
        },
        {
            "category":"Food & Beverages",
            "subcategory":"Chocolate",
            "type":"Retail Goods"
        }
    ],
    "sg:phone":"+1 206 528 9969",
    "sg:postcode":"98105",
    "sg:province":"WA",
    "sg:tags":[
        "shop",
        "dessert",
        "confectionery",
        "chocolatiers",
        "cocoa"
    ],
    "sg:website":"www.franschocolates.com",
    "wof:name":"Fran's Chocolates",
    "wof:placetype":"venue"
},
  "geometry": {"coordinates":[-122.299871,47.662728],"type":"Point"}
}