{
  "type": "Feature",
  "properties": {
    "addr:full":"12123 SE 44th Pl Bellevue WA 98006",
    "addr:postcode":"12123;98006",
    "addr:street":"Se 44Th Pl",
    "iso:country":"US",
    "sg:address":"12123 SE 44th Pl",
    "sg:city":"Bellevue",
    "sg:classifiers":[
        {
            "category":"Manufacturing",
            "subcategory":"Printing",
            "type":"Manufacturing & Wholesale Goods"
        }
    ],
    "sg:phone":"+1 425 746 1702",
    "sg:postcode":"98006",
    "sg:province":"WA",
    "sg:tags":[
        "lithographic",
        "commercial"
    ],
    "wof:name":"Print Art & Copy",
    "wof:placetype":"venue"
},
  "geometry": {"coordinates":[-122.177162,47.568029],"type":"Point"}
}