{
  "type": "Feature",
  "properties": {
    "addr:full":"301 Occidental Ave S Seattle WA 98104",
    "addr:housenumber":"301",
    "addr:postcode":"98104",
    "addr:street":"Occidental Ave S",
    "iso:country":"US",
    "sg:address":"301 Occidental Ave S",
    "sg:city":"Seattle",
    "sg:classifiers":[
        {
            "category":"Home & Garden",
            "subcategory":"Home Furnishings",
            "type":"Retail Goods"
        }
    ],
    "sg:phone":"+1 206 859 6492",
    "sg:postcode":"98104",
    "sg:province":"WA",
    "sg:tags":[
        "decor"
    ],
    "sg:website":"www.ornamo.com",
    "wof:name":"Ornamo",
    "wof:placetype":"venue"
},
  "geometry": {"coordinates":[-122.33289000000001,47.600022],"type":"Point"}
}