{
  "type": "Feature",
  "properties": {
    "addr:full":"1451 Pear Ln Rock Island WA 98850",
    "addr:housenumber":"1451",
    "addr:postcode":"98850",
    "addr:street":"Pear Ln",
    "iso:country":"US",
    "sg:address":"1451 Pear Ln",
    "sg:city":"Rock Island",
    "sg:classifiers":[
        {
            "category":"Professional",
            "type":"Services"
        }
    ],
    "sg:phone":"+1 509 886 1431",
    "sg:postcode":"98850",
    "sg:province":"WA",
    "wof:name":"Jalisco Orchard",
    "wof:placetype":"venue"
},
  "geometry": {"coordinates":[-120.172961,47.378515],"type":"Point"}
}