{
  "type": "Feature",
  "properties": {
    "addr:full":"8885 Shore Pl NW Silverdale WA 98383",
    "addr:housenumber":"8885",
    "addr:postcode":"98383",
    "addr:street":"Shore Pl Nw",
    "iso:country":"US",
    "sg:address":"8885 Shore Pl NW",
    "sg:city":"Silverdale",
    "sg:classifiers":[
        {
            "category":"Professional",
            "subcategory":"Engineering",
            "type":"Services"
        }
    ],
    "sg:phone":"+1 360 692 8381",
    "sg:postcode":"98383",
    "sg:province":"WA",
    "wof:name":"Wootan Group LLC",
    "wof:placetype":"venue"
},
  "geometry": {"coordinates":[-122.69841099999999,47.64385],"type":"Point"}
}