{
  "type": "Feature",
  "properties": {
    "addr:full":"1009 W Main St Monroe WA 98272",
    "addr:housenumber":"1009",
    "addr:postcode":"98272",
    "addr:street":"W Main St",
    "iso:country":"US",
    "sg:address":"1009 W Main St",
    "sg:city":"Monroe",
    "sg:classifiers":[
        {
            "category":"Education",
            "subcategory":"School",
            "type":"Public Place"
        }
    ],
    "sg:phone":"+1 360 794 8200",
    "sg:postcode":"98272",
    "sg:province":"WA",
    "wof:name":"Monroe Christian School",
    "wof:placetype":"venue"
},
  "geometry": {"coordinates":[-121.984258,47.85159],"type":"Point"}
}