{
  "type": "Feature",
  "properties": {
    "addr:full":"10330 Meridian Ave N Ste 190 Seattle WA 98133",
    "addr:housenumber":"10330",
    "addr:postcode":"98133",
    "addr:street":"Meridian Ave N Ste 190",
    "iso:country":"US",
    "sg:address":"10330 Meridian Ave N Ste 190",
    "sg:city":"Seattle",
    "sg:classifiers":[
        {
            "category":"Health Services",
            "subcategory":"Doctor",
            "type":"Services"
        }
    ],
    "sg:phone":"+1 206 389 7100",
    "sg:postcode":"98133",
    "sg:province":"WA",
    "wof:name":"Seattle Ear Nose & Throat",
    "wof:placetype":"venue"
},
  "geometry": {"coordinates":[-122.333718,47.704257],"type":"Point"}
}