{
  "type": "Feature",
  "properties": {
    "addr:full":"465 N 36th St Seattle WA 98103",
    "addr:housenumber":"465",
    "addr:postcode":"98103",
    "addr:street":"N 36Th St",
    "iso:country":"US",
    "sg:address":"465 N 36th St",
    "sg:city":"Seattle",
    "sg:classifiers":[
        {
            "category":"Organizations",
            "subcategory":"Professional Association",
            "type":"Services"
        }
    ],
    "sg:phone":"+1 206 632 1500",
    "sg:postcode":"98103",
    "sg:province":"WA",
    "sg:tags":[
        "chambers",
        "commerce"
    ],
    "sg:website":"www.fremontseattle.com",
    "wof:name":"Fremont Chamber Of Commerce",
    "wof:placetype":"venue"
},
  "geometry": {"coordinates":[-122.354477,47.652243],"type":"Point"}
}