{
  "type": "Feature",
  "properties": {
    "addr:full":"14419 Greenwood Ave N Seattle WA 98133",
    "addr:housenumber":"14419",
    "addr:postcode":"98133",
    "addr:street":"Greenwood Ave N",
    "iso:country":"US",
    "sg:address":"14419 Greenwood Ave N",
    "sg:city":"Seattle",
    "sg:classifiers":[
        {
            "category":"Professional",
            "subcategory":"Computer Services",
            "type":"Services"
        }
    ],
    "sg:phone":"+1 206 366 6606",
    "sg:postcode":"98133",
    "sg:province":"WA",
    "sg:tags":[
        "consulting"
    ],
    "wof:name":"Solution Beacon LLC",
    "wof:placetype":"venue"
},
  "geometry": {"coordinates":[-122.355647,47.733958],"type":"Point"}
}