{
  "type": "Feature",
  "properties": {
    "addr:full":"18621 16th Ave NE Seattle WA 98155",
    "addr:housenumber":"18621",
    "addr:postcode":"98155",
    "addr:street":"16Th Ave Ne",
    "iso:country":"US",
    "sg:address":"18621 16th Ave NE",
    "sg:city":"Seattle",
    "sg:classifiers":[
        {
            "category":"Retail",
            "subcategory":"Repair Shop",
            "type":"Services"
        }
    ],
    "sg:phone":"+1 206 369 4711",
    "sg:postcode":"98155",
    "sg:province":"WA",
    "wof:name":"Ruhl & Associates",
    "wof:placetype":"venue"
},
  "geometry": {"coordinates":[-122.31252000000001,47.764915],"type":"Point"}
}