{
  "type": "Feature",
  "properties": {
    "addr:full":"201 S Main St Ellensburg WA 98926",
    "addr:housenumber":"201",
    "addr:postcode":"98926",
    "addr:street":"S Main St",
    "iso:country":"US",
    "sg:address":"201 S Main St",
    "sg:city":"Ellensburg",
    "sg:classifiers":[
        {
            "category":"Shopping",
            "subcategory":"Jewelry",
            "type":"Retail Goods"
        }
    ],
    "sg:phone":"+1 509 925 4998",
    "sg:postcode":"98926",
    "sg:province":"WA",
    "sg:tags":[
        "jeweler"
    ],
    "wof:name":"Ellensburg Agate & Bead Shop",
    "wof:placetype":"venue"
},
  "geometry": {"coordinates":[-120.548404,46.991299],"type":"Point"}
}