{
  "type": "Feature",
  "properties": {
    "addr:full":"1410 119th Pl SE Everett WA 98208",
    "addr:housenumber":"1410",
    "addr:postcode":"98208",
    "addr:street":"119Th Pl Se",
    "iso:country":"US",
    "sg:address":"1410 119th Pl SE",
    "sg:city":"Everett",
    "sg:classifiers":[
        {
            "category":"Building & Trades",
            "subcategory":"Cleaning & Sanitation",
            "type":"Services"
        }
    ],
    "sg:phone":"+1 425 337 0831",
    "sg:postcode":"98208",
    "sg:province":"WA",
    "sg:tags":[
        "janitorial"
    ],
    "wof:name":"Mill Creek Maintenance Inc",
    "wof:placetype":"venue"
},
  "geometry": {"coordinates":[-122.213382,47.889418],"type":"Point"}
}