{
  "type": "Feature",
  "properties": {
    "addr:full":"5821 NE 282nd Ave Camas WA 98607",
    "addr:housenumber":"5821",
    "addr:postcode":"98607",
    "addr:street":"Ne 282Nd Ave",
    "iso:country":"US",
    "sg:address":"5821 NE 282nd Ave",
    "sg:city":"Camas",
    "sg:classifiers":[
        {
            "category":"Shopping",
            "subcategory":"Catalog Store",
            "type":"Retail Goods"
        }
    ],
    "sg:phone":"+1 360 834 6648",
    "sg:postcode":"98607",
    "sg:province":"WA",
    "sg:tags":[
        "mail",
        "house"
    ],
    "wof:name":"Wheelers",
    "wof:placetype":"venue"
},
  "geometry": {"coordinates":[-122.382891,45.665848],"type":"Point"}
}