{
  "type": "Feature",
  "properties": {
    "addr:full":"11330 NE 60th St Kirkland WA 98033",
    "addr:housenumber":"11330",
    "addr:postcode":"98033",
    "addr:street":"Ne 60Th St",
    "iso:country":"US",
    "sg:address":"11330 NE 60th St",
    "sg:city":"Kirkland",
    "sg:classifiers":[
        {
            "category":"Education",
            "subcategory":"Special Training",
            "type":"Public Place"
        }
    ],
    "sg:phone":"+1 206 290 0638",
    "sg:postcode":"98033",
    "sg:province":"WA",
    "sg:tags":[
        "school",
        "specialty"
    ],
    "sg:website":"www.sagegolfacademy.com",
    "wof:name":"Sage Golf Academy",
    "wof:placetype":"venue"
},
  "geometry": {"coordinates":[-122.188475,47.661314],"type":"Point"}
}