{
  "type": "Feature",
  "properties": {
    "addr:full":"122 Broadway E Seattle WA 98102",
    "addr:housenumber":"122",
    "addr:postcode":"98102",
    "addr:street":"Broadway",
    "iso:country":"US",
    "sg:address":"122 Broadway E",
    "sg:city":"Seattle",
    "sg:classifiers":[
        {
            "category":"Shopping",
            "subcategory":"Clothing, Apparel, & Fashions",
            "type":"Retail Goods"
        }
    ],
    "sg:phone":"+1 206 328 1313",
    "sg:postcode":"98102",
    "sg:province":"WA",
    "sg:tags":[
        "family"
    ],
    "wof:name":"Sin City",
    "wof:placetype":"venue"
},
  "geometry": {"coordinates":[-122.320797,47.619645],"type":"Point"}
}