{
  "type": "Feature",
  "properties": {
    "iso:country":"US",
    "sg:address":"7010 190th St SW",
    "sg:city":"Lynnwood",
    "sg:classifiers":[
        {
            "category":"Manufacturing",
            "subcategory":"Signs",
            "type":"Manufacturing & Wholesale Goods"
        }
    ],
    "sg:phone":"+1 425 672 7442",
    "sg:postcode":"98036",
    "sg:province":"WA",
    "sg:tags":[
        "specialty",
        "mfg"
    ],
    "wof:name":"Sound Sign Co",
    "wof:placetype":"venue"
},
  "geometry": {"coordinates":[-122.327975,47.82626],"type":"Point"}
}