{
  "type": "Feature",
  "properties": {
    "addr:full":"104 S Freya St Suite 215 Flag Spokane WA 99202",
    "addr:housenumber":"104",
    "addr:postcode":"99202",
    "addr:street":"S Freya St Suite 215 Flag",
    "iso:country":"US",
    "sg:address":"104 S Freya St Suite 215 Flag",
    "sg:city":"Spokane",
    "sg:classifiers":[
        {
            "category":"Insurance",
            "subcategory":"Insurance Agent",
            "type":"Services"
        },
        {
            "category":"Insurance",
            "subcategory":"Hazard Insurance",
            "type":"Services"
        },
        {
            "category":"Insurance",
            "subcategory":"Title Insurance",
            "type":"Services"
        },
        {
            "category":"Insurance",
            "subcategory":"Life Insurance",
            "type":"Services"
        }
    ],
    "sg:phone":"+1 509 535 5466",
    "sg:postcode":"99202",
    "sg:province":"WA",
    "sg:tags":[
        "business",
        "auto",
        "commercial",
        "homeowner",
        "motorcycle",
        "renter"
    ],
    "wof:name":"Allstate Insurance Company - Robert Fayant",
    "wof:placetype":"venue"
},
  "geometry": {"coordinates":[-117.35768899999999,47.656105],"type":"Point"}
}