{
  "type": "Feature",
  "properties": {
    "addr:full":"4037 S 128th St Tukwila WA 98168",
    "addr:housenumber":"4037",
    "addr:postcode":"98168",
    "addr:street":"S 128Th St",
    "iso:country":"US",
    "sg:address":"4037 S 128th St",
    "sg:city":"Tukwila",
    "sg:classifiers":[
        {
            "category":"Retail",
            "subcategory":"Auto Repair",
            "type":"Services"
        }
    ],
    "sg:phone":"+1 206 829 9651",
    "sg:postcode":"98168",
    "sg:province":"WA",
    "wof:name":"Dlc Executive Car Service",
    "wof:placetype":"venue"
},
  "geometry": {"coordinates":[-122.282624,47.488585],"type":"Point"}
}