{
  "type": "Feature",
  "properties": {
    "addr:full":"1850 N 180th St Seattle WA 98133",
    "addr:housenumber":"1850",
    "addr:postcode":"98133",
    "addr:street":"N 180Th St",
    "iso:country":"US",
    "sg:address":"1850 N 180th St",
    "sg:city":"Seattle",
    "sg:classifiers":[
        {
            "category":"Professional",
            "type":"Services"
        }
    ],
    "sg:phone":"+1 206 542 1509",
    "sg:postcode":"98133",
    "sg:province":"WA",
    "wof:name":"NW Home & Garden",
    "wof:placetype":"venue"
},
  "geometry": {"coordinates":[-122.334959,47.759707],"type":"Point"}
}