{
  "type": "Feature",
  "properties": {
    "addr:full":"5017 David Rd NW Bremerton WA 98312",
    "addr:housenumber":"5017",
    "addr:postcode":"98312",
    "addr:street":"David Rd Nw",
    "iso:country":"US",
    "sg:address":"5017 David Rd NW",
    "sg:city":"Bremerton",
    "sg:classifiers":[
        {
            "category":"Building & Trades",
            "subcategory":"Construction",
            "type":"Services"
        }
    ],
    "sg:phone":"+1 360 377 5760",
    "sg:postcode":"98312",
    "sg:province":"WA",
    "sg:tags":[
        "carpentry",
        "contractor"
    ],
    "wof:name":"Port Madison Woodworks",
    "wof:placetype":"venue"
},
  "geometry": {"coordinates":[-122.71955199999999,47.584407],"type":"Point"}
}