{
  "type": "Feature",
  "properties": {
    "addr:full":"1129 S 2nd Ave Walla Walla WA 99362",
    "addr:housenumber":"1129",
    "addr:postcode":"99362",
    "addr:street":"S 2Nd Ave",
    "iso:country":"US",
    "sg:address":"1129 S 2nd Ave",
    "sg:city":"Walla Walla",
    "sg:classifiers":[
        {
            "category":"Restaurant",
            "type":"Food & Drink"
        }
    ],
    "sg:phone":"+1 509 522 4777",
    "sg:postcode":"99362",
    "sg:province":"WA",
    "sg:tags":[
        "eating"
    ],
    "wof:name":"Creektown Cafe",
    "wof:placetype":"venue"
},
  "geometry": {"coordinates":[-118.330816,46.053008],"type":"Point"}
}