{
  "type": "Feature",
  "properties": {
    "addr:full":"4743 32nd Ave S Seattle WA 98118",
    "addr:housenumber":"4743",
    "addr:postcode":"98118",
    "addr:street":"32Nd Ave S",
    "iso:country":"US",
    "sg:address":"4743 32nd Ave S",
    "sg:city":"Seattle",
    "sg:classifiers":[
        {
            "category":"Building & Trades",
            "subcategory":"Landscaping Services",
            "type":"Services"
        }
    ],
    "sg:phone":"+1 206 722 4126",
    "sg:postcode":"98118",
    "sg:province":"WA",
    "sg:tags":[
        "lawn",
        "maintenance"
    ],
    "wof:name":"Dinh Gardeners",
    "wof:placetype":"venue"
},
  "geometry": {"coordinates":[-122.291481,47.560147],"type":"Point"}
}