{
  "type": "Feature",
  "properties": {
    "addr:full":"11040 Wilson Creek Rd Ellensburg WA 98926",
    "addr:housenumber":"11040",
    "addr:postcode":"98926",
    "addr:street":"Wilson Creek Rd",
    "iso:country":"US",
    "sg:address":"11040 Wilson Creek Rd",
    "sg:city":"Ellensburg",
    "sg:classifiers":[
        {
            "category":"Freight",
            "type":"Transportation"
        }
    ],
    "sg:phone":"+1 509 962 3416",
    "sg:postcode":"98926",
    "sg:province":"WA",
    "sg:tags":[
        "operator",
        "trucking"
    ],
    "wof:name":"Stuart Higginbotham Trucking",
    "wof:placetype":"venue"
},
  "geometry": {"coordinates":[-120.497288,47.093502],"type":"Point"}
}