{
  "type": "Feature",
  "properties": {
    "addr:full":"3225 S 116th Street Suite 181 Tukwila WA 98168",
    "addr:housenumber":"3225",
    "addr:postcode":"98168",
    "addr:street":"S 116Th Street Suite 181",
    "iso:country":"US",
    "sg:address":"3225 S 116th Street Suite 181",
    "sg:city":"Tukwila",
    "sg:classifiers":[
        {
            "category":"Professional",
            "subcategory":"Engineering",
            "type":"Services"
        },
        {
            "category":"Retail",
            "subcategory":"Repair Shop",
            "type":"Services"
        },
        {
            "category":"Professional",
            "subcategory":"Computer Services",
            "type":"Services"
        }
    ],
    "sg:phone":"+1 206 248 5971",
    "sg:postcode":"98168",
    "sg:province":"WA",
    "sg:tags":[
        "designer",
        "network",
        "technical",
        "repair-business",
        "assistance",
        "system",
        "integration",
        "consultant",
        "design",
        "equipment-service",
        "support",
        "engineer"
    ],
    "sg:website":"http://www.ccmaint.com",
    "wof:name":"Cascade Computer Maintenance",
    "wof:placetype":"venue"
},
  "geometry": {"coordinates":[-122.292067,47.499667],"type":"Point"}
}