{
  "type": "Feature",
  "properties": {
    "addr:full":"1600 E Olive Way Seattle WA 98102",
    "addr:housenumber":"1600",
    "addr:postcode":"98102",
    "addr:street":"E Olive Way",
    "iso:country":"US",
    "sg:address":"1600 E Olive Way",
    "sg:city":"Seattle",
    "sg:classifiers":[
        {
            "category":"Coffee & Tea",
            "type":"Food & Drink"
        }
    ],
    "sg:menulink":"http://www.allmenus.com/wa/seattle/117608-starbucks-coffee/menu/",
    "sg:phone":"+1 206 568 5185",
    "sg:postcode":"98102",
    "sg:province":"WA",
    "sg:tags":[
        "american"
    ],
    "wof:name":"Starbucks Coffee",
    "wof:placetype":"venue"
},
  "geometry": {"coordinates":[-122.325266,47.618959],"type":"Point"}
}