{
  "type": "Feature",
  "properties": {
    "addr:full":"3032 NE 140th St Seattle WA 98125",
    "addr:housenumber":"3032",
    "addr:postcode":"98125",
    "addr:street":"Ne 140Th St",
    "iso:country":"US",
    "sg:address":"3032 NE 140th St",
    "sg:city":"Seattle",
    "sg:classifiers":[
        {
            "category":"Real Estate",
            "subcategory":"Real Estate Operator",
            "type":"Services"
        }
    ],
    "sg:phone":"+1 206 363 8746",
    "sg:postcode":"98125",
    "sg:province":"WA",
    "sg:tags":[
        "building",
        "apartment"
    ],
    "wof:name":"Hidden Streams",
    "wof:placetype":"venue"
},
  "geometry": {"coordinates":[-122.29414199999999,47.730191],"type":"Point"}
}