{
  "type": "Feature",
  "properties": {
    "addr:full":"1704 J St Walla Walla WA 99362",
    "addr:housenumber":"1704",
    "addr:postcode":"99362",
    "addr:street":"J St",
    "iso:country":"US",
    "sg:address":"1704 J St",
    "sg:city":"Walla Walla",
    "sg:classifiers":[
        {
            "category":"Manufacturing",
            "subcategory":"Food",
            "type":"Manufacturing & Wholesale Goods"
        }
    ],
    "sg:phone":"+1 509 525 6502",
    "sg:postcode":"99362",
    "sg:province":"WA",
    "sg:tags":[
        "eating",
        "mfg"
    ],
    "wof:name":"Pepper Bridge Winery LLC",
    "wof:placetype":"venue"
},
  "geometry": {"coordinates":[-118.316085,46.079868],"type":"Point"}
}