{
  "type": "Feature",
  "properties": {
    "addr:full":"2902 N Carr St Apt 14 Tacoma WA 98403",
    "addr:housenumber":"2902;14",
    "addr:postcode":"98403",
    "addr:street":"N Carr St Apt",
    "iso:country":"US",
    "sg:address":"2902 N Carr St Apt 14",
    "sg:city":"Tacoma",
    "sg:classifiers":[
        {
            "category":"Organizations",
            "subcategory":"Religious Organization",
            "type":"Services"
        }
    ],
    "sg:phone":"+1 253 593 4354",
    "sg:postcode":"98403",
    "sg:province":"WA",
    "sg:website":"http://www.johnkoehler.com",
    "wof:name":"Archdioces Of Seattle",
    "wof:placetype":"venue"
},
  "geometry": {"coordinates":[-122.466904,47.273838],"type":"Point"}
}