{
  "type": "Feature",
  "properties": {
    "addr:full":"9204 Utah St NE Bremerton WA 98311",
    "addr:housenumber":"9204",
    "addr:postcode":"98311",
    "addr:street":"Utah St Ne",
    "iso:country":"US",
    "sg:address":"9204 Utah St NE",
    "sg:city":"Bremerton",
    "sg:classifiers":[
        {
            "category":"Shopping",
            "subcategory":"Crafts & Fabrics",
            "type":"Retail Goods"
        }
    ],
    "sg:phone":"+1 360 692 6887",
    "sg:postcode":"98311",
    "sg:province":"WA",
    "sg:tags":[
        "sewing"
    ],
    "wof:name":"NW Artistic Images",
    "wof:placetype":"venue"
},
  "geometry": {"coordinates":[-122.60834699999999,47.644797],"type":"Point"}
}