{
  "type": "Feature",
  "properties": {
    "addr:full":"201 W Wilson St Yacolt WA 98675",
    "addr:housenumber":"201",
    "addr:postcode":"98675",
    "addr:street":"W Wilson St",
    "iso:country":"US",
    "sg:address":"201 W Wilson St",
    "sg:city":"Yacolt",
    "sg:classifiers":[
        {
            "category":"Building & Trades",
            "subcategory":"Construction",
            "type":"Services"
        }
    ],
    "sg:phone":"+1 360 686 8498",
    "sg:postcode":"98675",
    "sg:province":"WA",
    "sg:tags":[
        "house"
    ],
    "wof:name":"Rebo Handyman Services LLC",
    "wof:placetype":"venue"
},
  "geometry": {"coordinates":[-122.409369,45.863143],"type":"Point"}
}