{
  "type": "Feature",
  "properties": {
    "addr:full":"2602 Westridge Ave W Tacoma WA 98466",
    "addr:housenumber":"2602",
    "addr:postcode":"98466",
    "addr:street":"Westridge Ave W",
    "iso:country":"US",
    "sg:address":"2602 Westridge Ave W",
    "sg:city":"Tacoma",
    "sg:classifiers":[
        {
            "category":"Wholesale",
            "subcategory":"Meat",
            "type":"Manufacturing & Wholesale Goods"
        }
    ],
    "sg:phone":"+1 253 380 0674",
    "sg:postcode":"98466",
    "sg:province":"WA",
    "wof:name":"Bison Man",
    "wof:placetype":"venue"
},
  "geometry": {"coordinates":[-122.555151,47.236302],"type":"Point"}
}