{
  "type": "Feature",
  "properties": {
    "addr:full":"4 Lake Bellevue Dr Apt 10 Bellevue WA 98005",
    "addr:housenumber":"4;10",
    "addr:postcode":"98005",
    "addr:street":"Lake Bellevue Dr Apt",
    "iso:country":"US",
    "sg:address":"4 Lake Bellevue Dr Apt 10",
    "sg:city":"Bellevue",
    "sg:classifiers":[
        {
            "category":"Building & Trades",
            "subcategory":"Equipment Rental",
            "type":"Services"
        }
    ],
    "sg:phone":"+1 425 467 0490",
    "sg:postcode":"98005",
    "sg:province":"WA",
    "sg:tags":[
        "contractors'"
    ],
    "wof:name":"P S Equipment",
    "wof:placetype":"venue"
},
  "geometry": {"coordinates":[-122.180809,47.620949],"type":"Point"}
}