{
  "type": "Feature",
  "properties": {
    "addr:full":"900 N Fancher Rd Spokane Valley WA 99212",
    "addr:housenumber":"900",
    "addr:postcode":"99212",
    "addr:street":"N Fancher Rd",
    "iso:country":"US",
    "sg:address":"900 N Fancher Rd",
    "sg:city":"Spokane Valley",
    "sg:classifiers":[
        {
            "category":"Manufacturing",
            "subcategory":"Tools & Machinery",
            "type":"Manufacturing & Wholesale Goods"
        }
    ],
    "sg:phone":"+1 509 534 6612",
    "sg:postcode":"99212",
    "sg:province":"WA",
    "sg:tags":[
        "rolling",
        "mill"
    ],
    "wof:name":"Met-Tile Inc",
    "wof:placetype":"venue"
},
  "geometry": {"coordinates":[-117.325329,47.666104],"type":"Point"}
}