{
  "type": "Feature",
  "properties": {
    "addr:full":"726 Broadway Seattle WA 98122",
    "addr:housenumber":"726",
    "addr:postcode":"98122",
    "addr:street":"Broadway",
    "iso:country":"US",
    "sg:address":"726 Broadway",
    "sg:city":"Seattle",
    "sg:classifiers":[
        {
            "category":"Health Services",
            "subcategory":"Doctor",
            "type":"Services"
        },
        {
            "category":"Professional",
            "type":"Services"
        }
    ],
    "sg:phone":"+1 206 328 1366",
    "sg:postcode":"98122",
    "sg:province":"WA",
    "sg:tags":[
        "psychiatrist"
    ],
    "wof:name":"Joan Golston, DCSW, LICSW, Therapist In Private Practice",
    "wof:placetype":"venue"
},
  "geometry": {"coordinates":[-122.32073099999999,47.608405],"type":"Point"}
}