{
  "type": "Feature",
  "properties": {
    "addr:full":"9802 48th Dr NE Marysville WA 98270",
    "addr:housenumber":"9802",
    "addr:postcode":"98270",
    "addr:street":"48Th Dr Ne",
    "iso:country":"US",
    "sg:address":"9802 48th Dr NE",
    "sg:city":"Marysville",
    "sg:classifiers":[
        {
            "category":"Health Services",
            "subcategory":"Nursing And Care Facility",
            "type":"Services"
        }
    ],
    "sg:phone":"+1 360 659 1279",
    "sg:postcode":"98270",
    "sg:province":"WA",
    "sg:tags":[
        "home",
        "retirement",
        "community"
    ],
    "wof:name":"Merrill Gardens",
    "wof:placetype":"venue"
},
  "geometry": {"coordinates":[-122.16612000000001,48.083168],"type":"Point"}
}