{
  "type": "Feature",
  "properties": {
    "addr:full":"17593 Johnson Rd NW Ephrata WA 98823",
    "addr:housenumber":"17593",
    "addr:postcode":"98823",
    "addr:street":"Johnson Rd Nw",
    "iso:country":"US",
    "sg:address":"17593 Johnson Rd NW",
    "sg:city":"Ephrata",
    "sg:classifiers":[
        {
            "category":"Home & Garden",
            "subcategory":"Furniture",
            "type":"Retail Goods"
        }
    ],
    "sg:phone":"+1 509 754 0447",
    "sg:postcode":"98823",
    "sg:province":"WA",
    "sg:tags":[
        "cabinet"
    ],
    "wof:name":"Commercial & Residential Cstm",
    "wof:placetype":"venue"
},
  "geometry": {"coordinates":[-119.60811,47.346236],"type":"Point"}
}