{
  "type": "Feature",
  "properties": {
    "addr:full":"350 Schmitt Rd Port Angeles WA 98363",
    "addr:housenumber":"350",
    "addr:postcode":"98363",
    "addr:street":"Schmitt Rd",
    "iso:country":"US",
    "sg:address":"350 Schmitt Rd",
    "sg:city":"Port Angeles",
    "sg:classifiers":[
        {
            "category":"Professional",
            "type":"Services"
        }
    ],
    "sg:phone":"+1 360 928 2053",
    "sg:postcode":"98363",
    "sg:province":"WA",
    "wof:name":"James P Criss",
    "wof:placetype":"venue"
},
  "geometry": {"coordinates":[-123.795444,48.146543],"type":"Point"}
}