{
  "type": "Feature",
  "properties": {
    "addr:full":"1923 31st Ave W Seattle WA 98199",
    "addr:housenumber":"1923",
    "addr:postcode":"98199",
    "addr:street":"31St Ave W",
    "iso:country":"US",
    "sg:address":"1923 31st Ave W",
    "sg:city":"Seattle",
    "sg:classifiers":[
        {
            "category":"Insurance",
            "subcategory":"Insurance Agent",
            "type":"Services"
        }
    ],
    "sg:phone":"+1 206 284 3608",
    "sg:postcode":"98199",
    "sg:province":"WA",
    "wof:name":"Executive Benefits Co",
    "wof:placetype":"venue"
},
  "geometry": {"coordinates":[-122.39687000000001,47.637501],"type":"Point"}
}