{
  "type": "Feature",
  "properties": {
    "addr:full":"2512 Main St Yakima WA 98903",
    "addr:housenumber":"2512",
    "addr:postcode":"98903",
    "addr:street":"Main St",
    "iso:country":"US",
    "sg:address":"2512 Main St",
    "sg:city":"Yakima",
    "sg:classifiers":[
        {
            "category":"Restaurant",
            "type":"Food & Drink"
        }
    ],
    "sg:phone":"+1 509 452 6626",
    "sg:postcode":"98903",
    "sg:province":"WA",
    "sg:tags":[
        "eating"
    ],
    "wof:name":"KFC Union Gap 304 Harma",
    "wof:placetype":"venue"
},
  "geometry": {"coordinates":[-120.47981299999999,46.563325],"type":"Point"}
}