{
  "type": "Feature",
  "properties": {
    "addr:full":"29316 52nd Ave S Auburn WA 98001",
    "addr:housenumber":"29316",
    "addr:postcode":"98001",
    "addr:street":"52Nd Ave S",
    "iso:country":"US",
    "sg:address":"29316 52nd Ave S",
    "sg:city":"Auburn",
    "sg:classifiers":[
        {
            "category":"Building & Trades",
            "subcategory":"Landscaping Services",
            "type":"Services"
        }
    ],
    "sg:phone":"+1 253 839 1270",
    "sg:postcode":"98001",
    "sg:province":"WA",
    "sg:tags":[
        "landscape"
    ],
    "wof:name":"Rollolazo Landscape Service",
    "wof:placetype":"venue"
},
  "geometry": {"coordinates":[-122.269361,47.339846],"type":"Point"}
}