{
  "type": "Feature",
  "properties": {
    "addr:full":"316 Martin Luther King Jr Way Tacoma WA 98405",
    "addr:housenumber":"316",
    "addr:postcode":"98405",
    "addr:street":"Martin Luther King Jr Way",
    "iso:country":"US",
    "sg:address":"316 Martin Luther King Jr Way",
    "sg:city":"Tacoma",
    "sg:classifiers":[
        {
            "category":"Health Services",
            "subcategory":"Doctor",
            "type":"Services"
        }
    ],
    "sg:phone":"+1 253 403 8720",
    "sg:postcode":"98405",
    "sg:province":"WA",
    "sg:tags":[
        "physician",
        "surgeon"
    ],
    "wof:name":"Majeed Al-Mateen MD",
    "wof:placetype":"venue"
},
  "geometry": {"coordinates":[-122.453221,47.258329],"type":"Point"}
}