{
  "type": "Feature",
  "properties": {
    "addr:full":"2304 SE 21st St Renton WA 98055",
    "addr:housenumber":"2304",
    "addr:postcode":"98055",
    "addr:street":"Se 21St St",
    "iso:country":"US",
    "sg:address":"2304 SE 21st St",
    "sg:city":"Renton",
    "sg:classifiers":[
        {
            "category":"Health Services",
            "subcategory":"Nursing And Care Facility",
            "type":"Services"
        }
    ],
    "sg:phone":"+1 425 228 8702",
    "sg:postcode":"98055",
    "sg:province":"WA",
    "wof:name":"Perfect Care",
    "wof:placetype":"venue"
},
  "geometry": {"coordinates":[-122.187765,47.461093],"type":"Point"}
}