{
  "type": "Feature",
  "properties": {
    "addr:full":"1619 Harbor Ave SW Seattle WA 98126",
    "addr:housenumber":"1619",
    "addr:postcode":"98126",
    "addr:street":"Harbor Ave Sw",
    "iso:country":"US",
    "sg:address":"1619 Harbor Ave SW",
    "sg:city":"Seattle",
    "sg:classifiers":[
        {
            "category":"Communications",
            "type":"Services"
        }
    ],
    "sg:phone":"+1 206 933 0608",
    "sg:postcode":"98126",
    "sg:province":"WA",
    "sg:tags":[
        "web",
        "design"
    ],
    "wof:name":"Prentice Design",
    "wof:placetype":"venue"
},
  "geometry": {"coordinates":[-122.38152100000001,47.589097],"type":"Point"}
}