{
  "type": "Feature",
  "properties": {
    "addr:full":"210 N Oak St Burlington WA 98233",
    "addr:housenumber":"210",
    "addr:postcode":"98233",
    "addr:street":"N Oak St",
    "iso:country":"US",
    "sg:address":"210 N Oak St",
    "sg:city":"Burlington",
    "sg:classifiers":[
        {
            "category":"Wholesale",
            "subcategory":"Farm Supplies",
            "type":"Manufacturing & Wholesale Goods"
        }
    ],
    "sg:phone":"+1 360 755 9011",
    "sg:postcode":"98233",
    "sg:province":"WA",
    "sg:tags":[
        "feed"
    ],
    "wof:name":"Hansen & Peterson",
    "wof:placetype":"venue"
},
  "geometry": {"coordinates":[-122.329172,48.476991],"type":"Point"}
}