{
  "type": "Feature",
  "properties": {
    "addr:full":"15231 63rd Ave W Edmonds WA 98026",
    "addr:housenumber":"15231",
    "addr:postcode":"98026",
    "addr:street":"63Rd Ave W",
    "iso:country":"US",
    "sg:address":"15231 63rd Ave W",
    "sg:city":"Edmonds",
    "sg:classifiers":[
        {
            "category":"Professional",
            "subcategory":"Business Services",
            "type":"Services"
        }
    ],
    "sg:phone":"+1 425 745 3069",
    "sg:postcode":"98026",
    "sg:province":"WA",
    "wof:name":"Dlb Interiors",
    "wof:placetype":"venue"
},
  "geometry": {"coordinates":[-122.318155,47.861113],"type":"Point"}
}