{
  "type": "Feature",
  "properties": {
    "addr:full":"13115 NE 4th St Ste 260 Vancouver WA 98684",
    "addr:housenumber":"13115",
    "addr:postcode":"98684",
    "addr:street":"Ne 4Th St Ste 260",
    "iso:country":"US",
    "sg:address":"13115 NE 4th St Ste 260",
    "sg:city":"Vancouver",
    "sg:classifiers":[
        {
            "category":"Professional",
            "subcategory":"Lawyer & Legal Services",
            "type":"Services"
        }
    ],
    "sg:phone":"+1 360 883 0636",
    "sg:postcode":"98684",
    "sg:province":"WA",
    "wof:name":"Foley Douglas Atty",
    "wof:placetype":"venue"
},
  "geometry": {"coordinates":[-122.537538,45.622394],"type":"Point"}
}