{
  "type": "Feature",
  "properties": {
    "addr:full":"413 Pine Street Suite 500 Seattle WA 98101",
    "addr:housenumber":"413",
    "addr:postcode":"98101",
    "addr:street":"Pine Street Suite 500",
    "iso:country":"US",
    "sg:address":"413 Pine Street Suite 500",
    "sg:city":"Seattle",
    "sg:classifiers":[
        {
            "category":"Professional",
            "subcategory":"Computer Services",
            "type":"Services"
        }
    ],
    "sg:postcode":"98101",
    "sg:province":"WA",
    "sg:tags":[
        "seattle"
    ],
    "sg:website":"http://www.marchex.com/",
    "wof:name":"Marchex",
    "wof:placetype":"venue"
},
  "geometry": {"coordinates":[-122.337237,47.611223],"type":"Point"}
}