{
  "type": "Feature",
  "properties": {
    "addr:full":"9711 86th Ave E Puyallup WA 98373",
    "addr:housenumber":"9711",
    "addr:postcode":"98373",
    "addr:street":"86Th Ave E",
    "iso:country":"US",
    "sg:address":"9711 86th Ave E",
    "sg:city":"Puyallup",
    "sg:classifiers":[
        {
            "category":"Building & Trades",
            "subcategory":"Construction",
            "type":"Services"
        }
    ],
    "sg:phone":"+1 253 770 0333",
    "sg:postcode":"98373",
    "sg:province":"WA",
    "sg:tags":[
        "house"
    ],
    "wof:name":"Tim Porter Const",
    "wof:placetype":"venue"
},
  "geometry": {"coordinates":[-122.31474,47.164849],"type":"Point"}
}