{
  "type": "Feature",
  "properties": {
    "addr:full":"4260 190th Ave SE Issaquah WA 98027",
    "addr:housenumber":"4260",
    "addr:postcode":"98027",
    "addr:street":"190Th Ave Se",
    "iso:country":"US",
    "sg:address":"4260 190th Ave SE",
    "sg:city":"Issaquah",
    "sg:classifiers":[
        {
            "category":"Government",
            "subcategory":"Fire Station",
            "type":"Public Place"
        }
    ],
    "sg:phone":"+1 425 643 4794",
    "sg:postcode":"98027",
    "sg:province":"WA",
    "sg:tags":[
        "protection"
    ],
    "wof:name":"United Sttes Fr/Rscue Fndation",
    "wof:placetype":"venue"
},
  "geometry": {"coordinates":[-122.086759,47.568439],"type":"Point"}
}