{
  "type": "Feature",
  "properties": {
    "addr:full":"1726 E Madison St Seattle WA 98122",
    "addr:housenumber":"1726",
    "addr:postcode":"98122",
    "addr:street":"E Madison St",
    "iso:country":"US",
    "sg:address":"1726 E Madison St",
    "sg:city":"Seattle",
    "sg:classifiers":[
        {
            "category":"Retail",
            "subcategory":"Laundry & Dry Cleaning",
            "type":"Services"
        }
    ],
    "sg:phone":"+1 206 624 1841",
    "sg:postcode":"98122",
    "sg:province":"WA",
    "wof:name":"Ding Ho Cleaners",
    "wof:placetype":"venue"
},
  "geometry": {"coordinates":[-122.30979000000001,47.61575],"type":"Point"}
}