{
  "type": "Feature",
  "properties": {
    "addr:full":"8192 NE Hidden Cove Rd Bainbridge Isle WA 98110",
    "addr:housenumber":"8192",
    "addr:postcode":"98110",
    "addr:street":"Ne Hidden Cove Rd;Isle",
    "iso:country":"US",
    "sg:address":"8192 NE Hidden Cove Rd",
    "sg:city":"Bainbridge Isle",
    "sg:classifiers":[
        {
            "category":"Real Estate",
            "subcategory":"Architect",
            "type":"Services"
        }
    ],
    "sg:phone":"+1 206 855 9391",
    "sg:postcode":"98110",
    "sg:province":"WA",
    "wof:name":"Matthews Architects AIA",
    "wof:placetype":"venue"
},
  "geometry": {"coordinates":[-122.53752,47.693835],"type":"Point"}
}