{
  "type": "Feature",
  "properties": {
    "addr:full":"524 Ave C Snohomish WA 98290",
    "addr:postcode":"98290",
    "addr:street":"524 Ave C",
    "iso:country":"US",
    "sg:address":"524 Ave C",
    "sg:city":"Snohomish",
    "sg:classifiers":[
        {
            "category":"Professional",
            "subcategory":"Art Services",
            "type":"Services"
        }
    ],
    "sg:phone":"+1 360 568 0123",
    "sg:postcode":"98290",
    "sg:province":"WA",
    "sg:tags":[
        "commercial",
        "design"
    ],
    "wof:name":"Mark C Riley",
    "wof:placetype":"venue"
},
  "geometry": {"coordinates":[-122.096898,47.918711],"type":"Point"}
}