{
  "type": "Feature",
  "properties": {
    "addr:full":"2246 Marble Valley-Basin Rd Addy WA 99101",
    "addr:housenumber":"2246",
    "addr:postcode":"99101",
    "addr:street":"Marble Valley-Basin Rd",
    "iso:country":"US",
    "sg:address":"2246 Marble Valley-Basin Rd",
    "sg:city":"Addy",
    "sg:classifiers":[
        {
            "category":"Wholesale",
            "subcategory":"Electrical",
            "type":"Manufacturing & Wholesale Goods"
        }
    ],
    "sg:phone":"+1 509 684 4557",
    "sg:postcode":"99101",
    "sg:province":"WA",
    "sg:tags":[
        "equipment"
    ],
    "wof:name":"Alternative Power Suppliers",
    "wof:placetype":"venue"
},
  "geometry": {"coordinates":[-117.951215,48.410526],"type":"Point"}
}