{
  "type": "Feature",
  "properties": {
    "addr:full":"21024 24th Ave S Seatac WA 98198",
    "addr:housenumber":"21024",
    "addr:postcode":"98198",
    "addr:street":"24Th Ave S Seatac",
    "iso:country":"US",
    "sg:address":"21024 24th Ave S",
    "sg:city":"Seatac",
    "sg:phone":"+1 206 824 8188",
    "sg:postcode":"98198",
    "sg:province":"WA",
    "wof:name":"Christian Faith Center",
    "wof:placetype":"venue"
},
  "geometry": {"coordinates":[-122.30248400000001,47.412685],"type":"Point"}
}