{
  "type": "Feature",
  "properties": {
    "addr:full":"44117 224th Ave SE Enumclaw WA 98022",
    "addr:housenumber":"44117",
    "addr:postcode":"98022",
    "addr:street":"224Th Ave Se",
    "iso:country":"US",
    "sg:address":"44117 224th Ave SE",
    "sg:city":"Enumclaw",
    "sg:classifiers":[
        {
            "category":"Education",
            "subcategory":"Music School",
            "type":"Public Place"
        }
    ],
    "sg:phone":"+1 360 825 9115",
    "sg:postcode":"98022",
    "sg:province":"WA",
    "wof:name":"Oceola Academy",
    "wof:placetype":"venue"
},
  "geometry": {"coordinates":[-122.042906,47.203351],"type":"Point"}
}