{
  "type": "Feature",
  "properties": {
    "addr:full":"601 Williams Blvd Richland WA 99354",
    "addr:housenumber":"601",
    "addr:postcode":"99354",
    "addr:street":"Williams Blvd",
    "iso:country":"US",
    "sg:address":"601 Williams Blvd",
    "sg:city":"Richland",
    "sg:classifiers":[
        {
            "category":"Professional",
            "subcategory":"Engineering",
            "type":"Services"
        }
    ],
    "sg:phone":"+1 509 946 8279",
    "sg:postcode":"99354",
    "sg:province":"WA",
    "sg:tags":[
        "consulting",
        "management",
        "engineer"
    ],
    "sg:website":"www.polestar.com",
    "wof:name":"Polestar Applied Technology",
    "wof:placetype":"venue"
},
  "geometry": {"coordinates":[-119.27947899999999,46.285717],"type":"Point"}
}