{
  "type": "Feature",
  "properties": {
    "addr:full":"721 45th St NE Auburn WA 98002",
    "addr:housenumber":"721",
    "addr:postcode":"98002",
    "addr:street":"45Th St Ne",
    "iso:country":"US",
    "sg:address":"721 45th St NE",
    "sg:city":"Auburn",
    "sg:classifiers":[
        {
            "category":"Health Services",
            "subcategory":"Clinic",
            "type":"Services"
        }
    ],
    "sg:phone":"+1 253 735 5378",
    "sg:postcode":"98002",
    "sg:province":"WA",
    "sg:tags":[
        "hospital",
        "specialty",
        "outpatient"
    ],
    "wof:name":"Lakeside-Milam Recovery Center",
    "wof:placetype":"venue"
},
  "geometry": {"coordinates":[-122.219663,47.348458],"type":"Point"}
}