{
  "type": "Feature",
  "properties": {
    "addr:full":"33607 Military Rd S Auburn WA 98001",
    "addr:housenumber":"33607",
    "addr:postcode":"98001",
    "addr:street":"Military Rd S",
    "iso:country":"US",
    "sg:address":"33607 Military Rd S",
    "sg:city":"Auburn",
    "sg:classifiers":[
        {
            "category":"Organizations",
            "subcategory":"Religious Organization",
            "type":"Services"
        }
    ],
    "sg:phone":"+1 253 661 8103",
    "sg:postcode":"98001",
    "sg:province":"WA",
    "wof:name":"Word of Truth Church",
    "wof:placetype":"venue"
},
  "geometry": {"coordinates":[-122.27419999999999,47.299577],"type":"Point"}
}