{
  "type": "Feature",
  "properties": {
    "addr:full":"4250 S Mead St Seattle WA 98118",
    "addr:housenumber":"4250",
    "addr:postcode":"98118",
    "addr:street":"S Mead St",
    "iso:country":"US",
    "sg:address":"4250 S Mead St",
    "sg:city":"Seattle",
    "sg:classifiers":[
        {
            "category":"Social Services",
            "type":"Services"
        }
    ],
    "sg:phone":"+1 206 723 0500",
    "sg:postcode":"98118",
    "sg:province":"WA",
    "wof:name":"Tenants Union",
    "wof:placetype":"venue"
},
  "geometry": {"coordinates":[-122.27770200000001,47.550501],"type":"Point"}
}