{
  "type": "Feature",
  "properties": {
    "iso:country":"US",
    "sg:address":"701 Galer St",
    "sg:city":"Seattle",
    "sg:classifiers":[
        {
            "category":"Social Services",
            "subcategory":"Child Care",
            "type":"Services"
        }
    ],
    "sg:phone":"+1 206 282 6847",
    "sg:postcode":"98109",
    "sg:province":"WA",
    "sg:tags":[
        "day"
    ],
    "wof:name":"Pacific Rim Enterprises",
    "wof:placetype":"venue"
},
  "geometry": {"coordinates":[-122.34228,47.632297],"type":"Point"}
}