{
  "type": "Feature",
  "properties": {
    "addr:full":"18302 78th Ave E Puyallup WA 98375",
    "addr:housenumber":"18302",
    "addr:postcode":"98375",
    "addr:street":"78Th Ave E",
    "iso:country":"US",
    "sg:address":"18302 78th Ave E",
    "sg:city":"Puyallup",
    "sg:classifiers":[
        {
            "category":"Retail",
            "subcategory":"Auto Repair",
            "type":"Services"
        }
    ],
    "sg:phone":"+1 253 847 6465",
    "sg:postcode":"98375",
    "sg:province":"WA",
    "wof:name":"Dales Auto Repair",
    "wof:placetype":"venue"
},
  "geometry": {"coordinates":[-122.325745,47.089878],"type":"Point"}
}