{
  "type": "Feature",
  "properties": {
    "addr:full":"2104 13th St Clarkston WA 99403",
    "addr:housenumber":"2104",
    "addr:postcode":"99403",
    "addr:street":"13Th St",
    "iso:country":"US",
    "sg:address":"2104 13th St",
    "sg:city":"Clarkston",
    "sg:classifiers":[
        {
            "category":"Freight",
            "type":"Transportation"
        }
    ],
    "sg:phone":"+1 509 758 4731",
    "sg:postcode":"99403",
    "sg:province":"WA",
    "sg:tags":[
        "local",
        "storage",
        "trucking"
    ],
    "wof:name":"A1 Moving",
    "wof:placetype":"venue"
},
  "geometry": {"coordinates":[-117.058949,46.389739],"type":"Point"}
}