{
  "type": "Feature",
  "properties": {
    "iso:country":"US",
    "sg:address":"1867 SE Cedar Rd",
    "sg:city":"Port Orchard",
    "sg:classifiers":[
        {
            "category":"Professional",
            "subcategory":"Accounting & Tax Preparation",
            "type":"Services"
        }
    ],
    "sg:phone":"+1 360 876 0380",
    "sg:postcode":"98367",
    "sg:province":"WA",
    "sg:tags":[
        "return",
        "filing"
    ],
    "wof:name":"Lewis Associates Pro Tax Svc",
    "wof:placetype":"venue"
},
  "geometry": {"coordinates":[-122.628968,47.494146],"type":"Point"}
}