{
  "type": "Feature",
  "properties": {
    "addr:full":"4026 SW 327th Pl Federal Way WA 98023",
    "addr:housenumber":"4026",
    "addr:postcode":"98023",
    "addr:street":"Sw 327Th Pl",
    "iso:country":"US",
    "sg:address":"4026 SW 327th Pl",
    "sg:city":"Federal Way",
    "sg:classifiers":[
        {
            "category":"Real Estate",
            "subcategory":"Real Estate Agent",
            "type":"Services"
        }
    ],
    "sg:phone":"+1 253 838 9118",
    "sg:postcode":"98023",
    "sg:province":"WA",
    "wof:name":"Ross Properties",
    "wof:placetype":"venue"
},
  "geometry": {"coordinates":[-122.383786,47.308657],"type":"Point"}
}