{
  "type": "Feature",
  "properties": {
    "addr:full":"900 University St Seattle WA 98101",
    "addr:housenumber":"900",
    "addr:postcode":"98101",
    "addr:street":"University St",
    "iso:country":"US",
    "sg:address":"900 University St",
    "sg:city":"Seattle",
    "sg:classifiers":[
        {
            "category":"Health Services",
            "subcategory":"Doctor",
            "type":"Services"
        }
    ],
    "sg:phone":"+1 206 922 2663",
    "sg:postcode":"98101",
    "sg:province":"WA",
    "sg:tags":[
        "physician",
        "surgeon"
    ],
    "wof:name":"William Trier Dr",
    "wof:placetype":"venue"
},
  "geometry": {"coordinates":[-122.329224,47.610458],"type":"Point"}
}