{
  "type": "Feature",
  "properties": {
    "addr:full":"10600 NE 94th Ave Vancouver WA 98662",
    "addr:housenumber":"10600",
    "addr:postcode":"98662",
    "addr:street":"Ne 94Th Ave",
    "iso:country":"US",
    "sg:address":"10600 NE 94th Ave",
    "sg:city":"Vancouver",
    "sg:classifiers":[
        {
            "category":"Building & Trades",
            "subcategory":"Construction",
            "type":"Services"
        }
    ],
    "sg:phone":"+1 360 256 3946",
    "sg:postcode":"98662",
    "sg:province":"WA",
    "sg:tags":[
        "home",
        "remodeling"
    ],
    "sg:website":"www.tsquareremodeling.com",
    "wof:name":"T Square Remodeling Inc",
    "wof:placetype":"venue"
},
  "geometry": {"coordinates":[-122.575655,45.69929],"type":"Point"}
}