{
  "type": "Feature",
  "properties": {
    "addr:full":"2515 233rd Ave SE Snohomish WA 98290",
    "addr:housenumber":"2515",
    "addr:postcode":"98290",
    "addr:street":"233Rd Ave Se",
    "iso:country":"US",
    "sg:address":"2515 233rd Ave SE",
    "sg:city":"Snohomish",
    "sg:classifiers":[
        {
            "category":"Building & Trades",
            "subcategory":"Construction",
            "type":"Services"
        }
    ],
    "sg:phone":"+1 425 334 6388",
    "sg:postcode":"98290",
    "sg:province":"WA",
    "sg:tags":[
        "woodworker"
    ],
    "wof:name":"B Z's Woodworking",
    "wof:placetype":"venue"
},
  "geometry": {"coordinates":[-121.918122,47.974781],"type":"Point"}
}