{
  "type": "Feature",
  "properties": {
    "iso:country":"US",
    "sg:address":"12511 Lakeholme Rd SW",
    "sg:city":"Tacoma",
    "sg:classifiers":[
        {
            "category":"Health Services",
            "subcategory":"Health Practitioner",
            "type":"Services"
        }
    ],
    "sg:phone":"+1 253 589 2199",
    "sg:postcode":"98498",
    "sg:province":"WA",
    "sg:tags":[
        "nurse"
    ],
    "wof:name":"Mary Kay Tomko",
    "wof:placetype":"venue"
},
  "geometry": {"coordinates":[-122.548772,47.143272],"type":"Point"}
}