{
  "type": "Feature",
  "properties": {
    "addr:full":"4005 E Rowan Ave Spokane WA 99217",
    "addr:housenumber":"4005",
    "addr:postcode":"99217",
    "addr:street":"E Rowan Ave",
    "iso:country":"US",
    "sg:address":"4005 E Rowan Ave",
    "sg:city":"Spokane",
    "sg:classifiers":[
        {
            "category":"Building & Trades",
            "subcategory":"Construction",
            "type":"Services"
        }
    ],
    "sg:phone":"+1 509 487 3008",
    "sg:postcode":"99217",
    "sg:province":"WA",
    "sg:tags":[
        "sandblasting"
    ],
    "wof:name":"Northside Sandblast & Paint",
    "wof:placetype":"venue"
},
  "geometry": {"coordinates":[-117.35202,47.707658],"type":"Point"}
}