{
  "type": "Feature",
  "properties": {
    "addr:full":"708 Main St Pomeroy WA 99347",
    "addr:housenumber":"708",
    "addr:postcode":"99347",
    "addr:street":"Main St",
    "iso:country":"US",
    "sg:address":"708 Main St",
    "sg:city":"Pomeroy",
    "sg:classifiers":[
        {
            "category":"Shopping",
            "type":"Retail Goods"
        }
    ],
    "sg:phone":"+1 509 843 5116",
    "sg:postcode":"99347",
    "sg:province":"WA",
    "sg:tags":[
        "cosmetic",
        "perfume"
    ],
    "wof:name":"A Cut Above",
    "wof:placetype":"venue"
},
  "geometry": {"coordinates":[-117.59819899999999,46.47435],"type":"Point"}
}