{
  "type": "Feature",
  "properties": {
    "iso:country":"US",
    "sg:address":"17556 10th Ave NE",
    "sg:city":"Seattle",
    "sg:classifiers":[
        {
            "category":"Building & Trades",
            "subcategory":"Construction",
            "type":"Services"
        }
    ],
    "sg:phone":"+1 206 363 9114",
    "sg:postcode":"98155",
    "sg:province":"WA",
    "sg:tags":[
        "house"
    ],
    "wof:name":"Tideman Construction",
    "wof:placetype":"venue"
},
  "geometry": {"coordinates":[-122.318789,47.757662],"type":"Point"}
}