{
  "type": "Feature",
  "properties": {
    "addr:full":"3573 Wheaton Way Bremerton WA 98310",
    "addr:housenumber":"3573",
    "addr:postcode":"98310",
    "addr:street":"Wheaton Way",
    "iso:country":"US",
    "sg:address":"3573 Wheaton Way",
    "sg:city":"Bremerton",
    "sg:classifiers":[
        {
            "category":"Restaurant",
            "type":"Food & Drink"
        }
    ],
    "sg:phone":"+1 360 792 9585",
    "sg:postcode":"98310",
    "sg:province":"WA",
    "sg:tags":[
        "eating"
    ],
    "wof:name":"Westside Pizza",
    "wof:placetype":"venue"
},
  "geometry": {"coordinates":[-122.629485,47.595954],"type":"Point"}
}