{
  "type": "Feature",
  "properties": {
    "addr:full":"6025 Portal Way Ferndale WA 98248",
    "addr:housenumber":"6025",
    "addr:postcode":"98248",
    "addr:street":"Portal Way",
    "iso:country":"US",
    "sg:address":"6025 Portal Way",
    "sg:city":"Ferndale",
    "sg:classifiers":[
        {
            "category":"Banks & Credit Unions",
            "subcategory":"Investment Brokerage",
            "type":"Services"
        }
    ],
    "sg:phone":"+1 360 312 9910",
    "sg:postcode":"98248",
    "sg:province":"WA",
    "wof:name":"Karst Investments LLC",
    "wof:placetype":"venue"
},
  "geometry": {"coordinates":[-122.584774,48.862052],"type":"Point"}
}