{
  "type": "Feature",
  "properties": {
    "addr:full":"15509 SE 326th St Auburn WA 98092",
    "addr:postcode":"15509;98092",
    "addr:street":"Se 326Th St",
    "iso:country":"US",
    "sg:address":"15509 SE 326th St",
    "sg:city":"Auburn",
    "sg:classifiers":[
        {
            "category":"Manufacturing",
            "subcategory":"Apparel",
            "type":"Manufacturing & Wholesale Goods"
        }
    ],
    "sg:phone":"+1 253 833 2071",
    "sg:postcode":"98092",
    "sg:province":"WA",
    "sg:tags":[
        "textile",
        "product",
        "fabricated",
        "mfg"
    ],
    "wof:name":"Rainbow Enterprises",
    "wof:placetype":"venue"
},
  "geometry": {"coordinates":[-122.144052,47.30975],"type":"Point"}
}