{
  "type": "Feature",
  "properties": {
    "addr:full":"147 Broadway St Tekoa WA 99033",
    "addr:housenumber":"147",
    "addr:postcode":"99033",
    "addr:street":"Broadway St",
    "iso:country":"US",
    "sg:address":"147 Broadway St",
    "sg:city":"Tekoa",
    "sg:classifiers":[
        {
            "category":"Banks & Credit Unions",
            "subcategory":"Bank",
            "type":"Services"
        }
    ],
    "sg:phone":"+1 509 284 5000",
    "sg:postcode":"99033",
    "sg:province":"WA",
    "sg:tags":[
        "loan"
    ],
    "wof:name":"American West Bank",
    "wof:placetype":"venue"
},
  "geometry": {"coordinates":[-117.071845,47.222696],"type":"Point"}
}