{
  "type": "Feature",
  "properties": {
    "addr:full":"720 Electric Ave Walla Walla WA 99362",
    "addr:housenumber":"720",
    "addr:postcode":"99362",
    "addr:street":"Electric Ave",
    "iso:country":"US",
    "sg:address":"720 Electric Ave",
    "sg:city":"Walla Walla",
    "sg:classifiers":[
        {
            "category":"Professional",
            "subcategory":"Engineering",
            "type":"Services"
        }
    ],
    "sg:phone":"+1 509 301 8923",
    "sg:postcode":"99362",
    "sg:province":"WA",
    "wof:name":"Laizure Construction",
    "wof:placetype":"venue"
},
  "geometry": {"coordinates":[-118.387187,46.061116],"type":"Point"}
}