{
  "type": "Feature",
  "properties": {
    "addr:full":"22525 50th Ave SE Bothell WA 98021",
    "addr:housenumber":"22525",
    "addr:postcode":"98021",
    "addr:street":"50Th Ave Se",
    "iso:country":"US",
    "sg:address":"22525 50th Ave SE",
    "sg:city":"Bothell",
    "sg:classifiers":[
        {
            "category":"Health Services",
            "subcategory":"Medical Lab",
            "type":"Services"
        }
    ],
    "sg:phone":"+1 425 485 7836",
    "sg:postcode":"98021",
    "sg:province":"WA",
    "sg:tags":[
        "house",
        "mail",
        "laboratory"
    ],
    "wof:name":"Madson Enterprises",
    "wof:placetype":"venue"
},
  "geometry": {"coordinates":[-122.166248,47.792588],"type":"Point"}
}