{
  "type": "Feature",
  "properties": {
    "addr:full":"4211 Alderwood Mall Blvd Ste 202 Lynnwood WA 98036",
    "addr:housenumber":"4211",
    "addr:postcode":"98036",
    "addr:street":"Alderwood Mall Blvd Ste 202",
    "iso:country":"US",
    "sg:address":"4211 Alderwood Mall Blvd Ste 202",
    "sg:city":"Lynnwood",
    "sg:classifiers":[
        {
            "category":"Professional",
            "subcategory":"Lawyer & Legal Services",
            "type":"Services"
        }
    ],
    "sg:phone":"+1 425 744 5658",
    "sg:postcode":"98036",
    "sg:province":"WA",
    "sg:tags":[
        "trust",
        "attorney",
        "planning",
        "wills",
        "estate"
    ],
    "wof:name":"Hickman & Menashe PS",
    "wof:placetype":"venue"
},
  "geometry": {"coordinates":[-122.28837900000001,47.817346],"type":"Point"}
}