{
  "type": "Feature",
  "properties": {
    "iso:country":"US",
    "sg:address":"9214 177th Pl NE",
    "sg:city":"Redmond",
    "sg:classifiers":[
        {
            "category":"Retail",
            "subcategory":"Portrait Studio",
            "type":"Services"
        }
    ],
    "sg:phone":"+1 425 829 8898",
    "sg:postcode":"98052",
    "sg:province":"WA",
    "sg:tags":[
        "photo"
    ],
    "wof:name":"James Cheng Photography",
    "wof:placetype":"venue"
},
  "geometry": {"coordinates":[-122.10338400000001,47.684075],"type":"Point"}
}