{
  "type": "Feature",
  "properties": {
    "addr:full":"928 Poplar Ave Wenatchee WA 98801",
    "addr:housenumber":"928",
    "addr:postcode":"98801",
    "addr:street":"Poplar Ave",
    "iso:country":"US",
    "sg:address":"928 Poplar Ave",
    "sg:city":"Wenatchee",
    "sg:classifiers":[
        {
            "category":"Shopping",
            "subcategory":"Bicycles & Sporting Goods",
            "type":"Retail Goods"
        }
    ],
    "sg:phone":"+1 509 663 5448",
    "sg:postcode":"98801",
    "sg:province":"WA",
    "wof:name":"Three Legs Pro Shop",
    "wof:placetype":"venue"
},
  "geometry": {"coordinates":[-120.343248,47.432728],"type":"Point"}
}