{
  "type": "Feature",
  "properties": {
    "addr:full":"7210 Sycamore Ave NW Seattle WA 98117",
    "addr:housenumber":"7210",
    "addr:postcode":"98117",
    "addr:street":"Sycamore Ave Nw",
    "iso:country":"US",
    "sg:address":"7210 Sycamore Ave NW",
    "sg:city":"Seattle",
    "sg:classifiers":[
        {
            "category":"Building & Trades",
            "subcategory":"Construction",
            "type":"Services"
        }
    ],
    "sg:phone":"+1 206 789 8461",
    "sg:postcode":"98117",
    "sg:province":"WA",
    "sg:tags":[
        "house"
    ],
    "wof:name":"JW Builders",
    "wof:placetype":"venue"
},
  "geometry": {"coordinates":[-122.358356,47.681687],"type":"Point"}
}