{
  "type": "Feature",
  "properties": {
    "iso:country":"US",
    "sg:address":"4000 Colville Rd",
    "sg:city":"Loon Lake",
    "sg:classifiers":[
        {
            "category":"Organizations",
            "subcategory":"Professional Association",
            "type":"Services"
        }
    ],
    "sg:phone":"+1 509 233 2222",
    "sg:postcode":"99148",
    "sg:province":"WA",
    "wof:name":"Loon Lake Historical Society",
    "wof:placetype":"venue"
},
  "geometry": {"coordinates":[-117.630775,48.062688],"type":"Point"}
}