{
  "type": "Feature",
  "properties": {
    "iso:country":"US",
    "sg:address":"2125 1st Ave",
    "sg:city":"Seattle",
    "sg:classifiers":[
        {
            "category":"Manufacturing",
            "subcategory":"Apparel",
            "type":"Manufacturing & Wholesale Goods"
        }
    ],
    "sg:phone":"+1 206 628 0440",
    "sg:postcode":"98121",
    "sg:province":"WA",
    "sg:tags":[
        "dress",
        "mfg"
    ],
    "wof:name":"Professional Design",
    "wof:placetype":"venue"
},
  "geometry": {"coordinates":[-122.34505,47.612359],"type":"Point"}
}