{
  "type": "Feature",
  "properties": {
    "addr:full":"812 Surry Rd Wenatchee WA 98801",
    "addr:housenumber":"812",
    "addr:postcode":"98801",
    "addr:street":"Surry Rd",
    "iso:country":"US",
    "sg:address":"812 Surry Rd",
    "sg:city":"Wenatchee",
    "sg:classifiers":[
        {
            "category":"Building & Trades",
            "subcategory":"Construction",
            "type":"Services"
        }
    ],
    "sg:phone":"+1 509 664 8040",
    "sg:postcode":"98801",
    "sg:province":"WA",
    "sg:tags":[
        "house"
    ],
    "wof:name":"Thorough-Spec",
    "wof:placetype":"venue"
},
  "geometry": {"coordinates":[-120.359188,47.43235],"type":"Point"}
}