{
  "type": "Feature",
  "properties": {
    "addr:full":"771 Tipton Rd Ellensburg WA 98926",
    "addr:housenumber":"771",
    "addr:postcode":"98926",
    "addr:street":"Tipton Rd",
    "iso:country":"US",
    "sg:address":"771 Tipton Rd",
    "sg:city":"Ellensburg",
    "sg:classifiers":[
        {
            "category":"Personal",
            "subcategory":"Beauty Salon",
            "type":"Services"
        },
        {
            "category":"Personal",
            "subcategory":"Tanning Parlor",
            "type":"Services"
        }
    ],
    "sg:phone":"+1 509 925 7726",
    "sg:postcode":"98926",
    "sg:province":"WA",
    "wof:name":"Body Tan",
    "wof:placetype":"venue"
},
  "geometry": {"coordinates":[-120.539739,47.054076],"type":"Point"}
}