{
  "type": "Feature",
  "properties": {
    "addr:full":"350 N 190th St Shoreline WA 98133",
    "addr:housenumber":"350",
    "addr:postcode":"98133",
    "addr:street":"N 190Th St",
    "iso:country":"US",
    "sg:address":"350 N 190th St",
    "sg:city":"Shoreline",
    "sg:classifiers":[
        {
            "category":"Health Services",
            "subcategory":"Nursing And Care Facility",
            "type":"Services"
        },
        {
            "category":"Social Services",
            "subcategory":"Adult Care",
            "type":"Services"
        }
    ],
    "sg:phone":"+1 206 546 7500",
    "sg:postcode":"98133",
    "sg:province":"WA",
    "sg:tags":[
        "home",
        "retirement",
        "community",
        "residential"
    ],
    "wof:name":"Cristwood",
    "wof:placetype":"venue"
},
  "geometry": {"coordinates":[-122.353888,47.766874],"type":"Point"}
}