{
  "type": "Feature",
  "properties": {
    "addr:full":"7051 S 234th St Kent WA 98032",
    "addr:housenumber":"7051",
    "addr:postcode":"98032",
    "addr:street":"S 234Th St",
    "iso:country":"US",
    "sg:address":"7051 S 234th St",
    "sg:city":"Kent",
    "sg:classifiers":[
        {
            "category":"Home & Garden",
            "subcategory":"Hardware",
            "type":"Retail Goods"
        }
    ],
    "sg:phone":"+1 253 854 3835",
    "sg:postcode":"98032",
    "sg:province":"WA",
    "sg:tags":[
        "store"
    ],
    "wof:name":"Pacific Western Agencies",
    "wof:placetype":"venue"
},
  "geometry": {"coordinates":[-122.245661,47.392082],"type":"Point"}
}