{
  "type": "Feature",
  "properties": {
    "addr:full":"243 Sherwood Rd Sequim WA 98382",
    "addr:housenumber":"243",
    "addr:postcode":"98382",
    "addr:street":"Sherwood Rd",
    "iso:country":"US",
    "sg:address":"243 Sherwood Rd",
    "sg:city":"Sequim",
    "sg:classifiers":[
        {
            "category":"Professional",
            "subcategory":"Art Services",
            "type":"Services"
        }
    ],
    "sg:phone":"+1 360 582 3845",
    "sg:postcode":"98382",
    "sg:province":"WA",
    "sg:tags":[
        "commercial",
        "design"
    ],
    "wof:name":"Vent Graphics",
    "wof:placetype":"venue"
},
  "geometry": {"coordinates":[-122.938018,48.092479],"type":"Point"}
}