{
  "type": "Feature",
  "properties": {
    "addr:full":"2914 Mitchell Rd SE Port Orchard WA 98366",
    "addr:housenumber":"2914",
    "addr:postcode":"98366",
    "addr:street":"Mitchell Rd Se",
    "iso:country":"US",
    "sg:address":"2914 Mitchell Rd SE",
    "sg:city":"Port Orchard",
    "sg:classifiers":[
        {
            "category":"Health Services",
            "subcategory":"Chiropractor",
            "type":"Services"
        }
    ],
    "sg:phone":"+1 360 876 6888",
    "sg:postcode":"98366",
    "sg:province":"WA",
    "wof:name":"Bethel-Mitchell Chiropractic",
    "wof:placetype":"venue"
},
  "geometry": {"coordinates":[-122.630728,47.522195],"type":"Point"}
}