{
  "type": "Feature",
  "properties": {
    "addr:full":"3000 W Yakima Ave Yakima WA 98902",
    "addr:housenumber":"3000",
    "addr:postcode":"98902",
    "addr:street":"W Yakima Ave",
    "iso:country":"US",
    "sg:address":"3000 W Yakima Ave",
    "sg:city":"Yakima",
    "sg:classifiers":[
        {
            "category":"Shopping",
            "subcategory":"Shoes",
            "type":"Retail Goods"
        }
    ],
    "sg:phone":"+1 509 453 8388",
    "sg:postcode":"98902",
    "sg:province":"WA",
    "sg:tags":[
        "shoe",
        "store"
    ],
    "wof:name":"Payless Shoesource",
    "wof:placetype":"venue"
},
  "geometry": {"coordinates":[-120.55139699999999,46.597238],"type":"Point"}
}