{
  "type": "Feature",
  "properties": {
    "iso:country":"US",
    "sg:address":"12600 SE 38th St",
    "sg:city":"Bellevue",
    "sg:classifiers":[
        {
            "category":"Shopping",
            "subcategory":"Computers & Home Electronics",
            "type":"Retail Goods"
        }
    ],
    "sg:phone":"+1 425 649 1121",
    "sg:postcode":"98006",
    "sg:province":"WA",
    "sg:tags":[
        "audio"
    ],
    "wof:name":"Comp View Inc",
    "wof:placetype":"venue"
},
  "geometry": {"coordinates":[-122.171239,47.576933],"type":"Point"}
}