{
  "type": "Feature",
  "properties": {
    "addr:full":"127 E Augusta Ave Ste 103 Spokane WA 99207",
    "addr:housenumber":"127",
    "addr:postcode":"99207",
    "addr:street":"E Augusta Ave Ste 103",
    "iso:country":"US",
    "sg:address":"127 E Augusta Ave Ste 103",
    "sg:city":"Spokane",
    "sg:classifiers":[
        {
            "category":"Organizations",
            "subcategory":"Labor Organization",
            "type":"Services"
        },
        {
            "category":"Building & Trades",
            "subcategory":"Construction",
            "type":"Services"
        }
    ],
    "sg:phone":"+1 509 326 0880",
    "sg:postcode":"99207",
    "sg:province":"WA",
    "sg:tags":[
        "carpenter"
    ],
    "wof:name":"Pacific Nw Distict Council Of",
    "wof:placetype":"venue"
},
  "geometry": {"coordinates":[-117.40912400000001,47.67281],"type":"Point"}
}