{
  "type": "Feature",
  "properties": {
    "addr:full":"606 E Laurel Rd Bellingham WA 98226",
    "addr:housenumber":"606",
    "addr:postcode":"98226",
    "addr:street":"E Laurel Rd",
    "iso:country":"US",
    "sg:address":"606 E Laurel Rd",
    "sg:city":"Bellingham",
    "sg:classifiers":[
        {
            "category":"Professional",
            "subcategory":"Computer Services",
            "type":"Services"
        }
    ],
    "sg:phone":"+1 360 398 1745",
    "sg:postcode":"98226",
    "sg:province":"WA",
    "sg:tags":[
        "datum"
    ],
    "wof:name":"Laurel Data Services",
    "wof:placetype":"venue"
},
  "geometry": {"coordinates":[-122.457373,48.855315],"type":"Point"}
}