{
  "type": "Feature",
  "properties": {
    "addr:full":"8117 267th Pl NW Stanwood WA 98292",
    "addr:housenumber":"8117",
    "addr:postcode":"98292",
    "addr:street":"267Th Pl Nw",
    "iso:country":"US",
    "sg:address":"8117 267th Pl NW",
    "sg:city":"Stanwood",
    "sg:classifiers":[
        {
            "category":"Government",
            "subcategory":"Office",
            "type":"Public Place"
        }
    ],
    "sg:phone":"+1 360 629 3241",
    "sg:postcode":"98292",
    "sg:province":"WA",
    "sg:tags":[
        "equipment",
        "executive"
    ],
    "wof:name":"Stanwood City of Inc",
    "wof:placetype":"venue"
},
  "geometry": {"coordinates":[-122.343338,48.239121],"type":"Point"}
}