{
  "type": "Feature",
  "properties": {
    "addr:full":"3249 Perry Ave Bremerton WA 98310",
    "addr:housenumber":"3249",
    "addr:postcode":"98310",
    "addr:street":"Perry Ave",
    "iso:country":"US",
    "sg:address":"3249 Perry Ave",
    "sg:city":"Bremerton",
    "sg:classifiers":[
        {
            "category":"Personal",
            "subcategory":"Barber",
            "type":"Services"
        }
    ],
    "sg:phone":"+1 360 792 1441",
    "sg:postcode":"98310",
    "sg:province":"WA",
    "wof:name":"C Barber Shop & Styling",
    "wof:placetype":"venue"
},
  "geometry": {"coordinates":[-122.61346399999999,47.592771],"type":"Point"}
}