{
  "type": "Feature",
  "properties": {
    "addr:full":"252 N Dale Rd Moses Lake WA 98837",
    "addr:housenumber":"252",
    "addr:postcode":"98837",
    "addr:street":"N Dale Rd",
    "iso:country":"US",
    "sg:address":"252 N Dale Rd",
    "sg:city":"Moses Lake",
    "sg:phone":"+1 509 765 5722",
    "sg:postcode":"98837",
    "sg:province":"WA",
    "sg:tags":[
        "farm",
        "field",
        "crop"
    ],
    "wof:name":"Roger Hasting Farms",
    "wof:placetype":"venue"
},
  "geometry": {"coordinates":[-119.294025,47.132969],"type":"Point"}
}