{
  "type": "Feature",
  "properties": {
    "addr:full":"6254 Harbour Heights Pkwy Mukilteo WA 98275",
    "addr:housenumber":"6254",
    "addr:postcode":"98275",
    "addr:street":"Harbour Heights Pkwy",
    "iso:country":"US",
    "sg:address":"6254 Harbour Heights Pkwy",
    "sg:city":"Mukilteo",
    "sg:classifiers":[
        {
            "category":"Real Estate",
            "subcategory":"Real Estate Operator",
            "type":"Services"
        }
    ],
    "sg:phone":"+1 425 742 4994",
    "sg:postcode":"98275",
    "sg:province":"WA",
    "sg:tags":[
        "property",
        "lessor"
    ],
    "wof:name":"Hackney Co Inc",
    "wof:placetype":"venue"
},
  "geometry": {"coordinates":[-122.314246,47.896389],"type":"Point"}
}