{
  "type": "Feature",
  "properties": {
    "addr:full":"333 11th Ave W Kirkland WA 98033",
    "addr:housenumber":"333",
    "addr:postcode":"98033",
    "addr:street":"11Th Ave W",
    "iso:country":"US",
    "sg:address":"333 11th Ave W",
    "sg:city":"Kirkland",
    "sg:classifiers":[
        {
            "category":"Health Services",
            "subcategory":"Doctor",
            "type":"Services"
        }
    ],
    "sg:phone":"+1 425 576 0726",
    "sg:postcode":"98033",
    "sg:province":"WA",
    "sg:tags":[
        "physician",
        "surgeon"
    ],
    "wof:name":"Mark B. Walker Md",
    "wof:placetype":"venue"
},
  "geometry": {"coordinates":[-122.209857,47.684151],"type":"Point"}
}