{
  "type": "Feature",
  "properties": {
    "addr:full":"1197 Bryant Ave Walla Walla WA 99362",
    "addr:housenumber":"1197",
    "addr:postcode":"99362",
    "addr:street":"Bryant Ave",
    "iso:country":"US",
    "sg:address":"1197 Bryant Ave",
    "sg:city":"Walla Walla",
    "sg:classifiers":[
        {
            "category":"Real Estate",
            "subcategory":"Real Estate Operator",
            "type":"Services"
        }
    ],
    "sg:phone":"+1 509 525 6289",
    "sg:postcode":"99362",
    "sg:province":"WA",
    "sg:tags":[
        "wheat",
        "lessor",
        "farm",
        "cash",
        "grain",
        "property"
    ],
    "wof:name":"Vernon Filan",
    "wof:placetype":"venue"
},
  "geometry": {"coordinates":[-118.309026,46.056815],"type":"Point"}
}