{
  "type": "Feature",
  "properties": {
    "addr:full":"12310 Hwy 99 Everett WA 98204",
    "addr:housenumber":"12310",
    "addr:postcode":"98204",
    "addr:street":"Hwy 99",
    "iso:country":"US",
    "sg:address":"12310 Hwy 99",
    "sg:city":"Everett",
    "sg:classifiers":[
        {
            "category":"Professional",
            "subcategory":"Advertising",
            "type":"Services"
        }
    ],
    "sg:phone":"+1 425 514 8564",
    "sg:postcode":"98204",
    "sg:province":"WA",
    "sg:tags":[
        "agency"
    ],
    "wof:name":"Rent-A-Center",
    "wof:placetype":"venue"
},
  "geometry": {"coordinates":[-122.263749,47.884114],"type":"Point"}
}