{
  "type": "Feature",
  "properties": {
    "addr:full":"414 Monroe Ave NE Renton WA 98056",
    "addr:housenumber":"414",
    "addr:postcode":"98056",
    "addr:street":"Monroe Ave Ne",
    "iso:country":"US",
    "sg:address":"414 Monroe Ave NE",
    "sg:city":"Renton",
    "sg:classifiers":[
        {
            "category":"Retail",
            "subcategory":"Auto Repair",
            "type":"Services"
        }
    ],
    "sg:phone":"+1 425 255 4966",
    "sg:postcode":"98056",
    "sg:province":"WA",
    "wof:name":"Brown's Roy Auto Service",
    "wof:placetype":"venue"
},
  "geometry": {"coordinates":[-122.175003,47.488899],"type":"Point"}
}