{
  "type": "Feature",
  "properties": {
    "addr:full":"1490 Whitehorn St Ferndale WA 98248",
    "addr:housenumber":"1490",
    "addr:postcode":"98248",
    "addr:street":"Whitehorn St",
    "iso:country":"US",
    "sg:address":"1490 Whitehorn St",
    "sg:city":"Ferndale",
    "sg:classifiers":[
        {
            "category":"Building & Trades",
            "subcategory":"Plumbing",
            "type":"Services"
        }
    ],
    "sg:phone":"+1 360 384 7667",
    "sg:postcode":"98248",
    "sg:province":"WA",
    "sg:tags":[
        "plumbing",
        "contractor"
    ],
    "wof:name":"Professional Plumbing LLC",
    "wof:placetype":"venue"
},
  "geometry": {"coordinates":[-122.55954,48.82001],"type":"Point"}
}