{
  "type": "Feature",
  "properties": {
    "addr:full":"521 NE 165th St Seattle WA 98155",
    "addr:housenumber":"521",
    "addr:postcode":"98155",
    "addr:street":"Ne 165Th St",
    "iso:country":"US",
    "sg:address":"521 NE 165th St",
    "sg:city":"Seattle",
    "sg:classifiers":[
        {
            "category":"Government",
            "subcategory":"Police Station",
            "type":"Public Place"
        }
    ],
    "sg:phone":"+1 206 363 8424",
    "sg:postcode":"98155",
    "sg:province":"WA",
    "sg:tags":[
        "protection"
    ],
    "wof:name":"Sheriffs Dept",
    "wof:placetype":"venue"
},
  "geometry": {"coordinates":[-122.32284199999999,47.748505],"type":"Point"}
}