{
  "type": "Feature",
  "properties": {
    "addr:full":"509 Valley Ave NE Puyallup WA 98372",
    "addr:housenumber":"509",
    "addr:postcode":"98372",
    "addr:street":"Valley Ave Ne",
    "iso:country":"US",
    "sg:address":"509 Valley Ave NE",
    "sg:city":"Puyallup",
    "sg:classifiers":[
        {
            "category":"Professional",
            "subcategory":"Management & Consulting",
            "type":"Services"
        }
    ],
    "sg:phone":"+1 253 223 4863",
    "sg:postcode":"98372",
    "sg:province":"WA",
    "sg:tags":[
        "consultant",
        "business"
    ],
    "wof:name":"J D Consulting Svc",
    "wof:placetype":"venue"
},
  "geometry": {"coordinates":[-122.28738,47.205692],"type":"Point"}
}