{
  "type": "Feature",
  "properties": {
    "addr:full":"801 Eastmont Ave East Wenatchee WA 98802",
    "addr:housenumber":"801",
    "addr:postcode":"98802",
    "addr:street":"Eastmont Ave",
    "iso:country":"US",
    "sg:address":"801 Eastmont Ave",
    "sg:city":"East Wenatchee",
    "sg:classifiers":[
        {
            "category":"Banks & Credit Unions",
            "subcategory":"Investment Brokerage",
            "type":"Services"
        }
    ],
    "sg:phone":"+1 509 886 4881",
    "sg:postcode":"98802",
    "sg:province":"WA",
    "sg:tags":[
        "mortgage"
    ],
    "wof:name":"A+ Mortgage Inc",
    "wof:placetype":"venue"
},
  "geometry": {"coordinates":[-120.281882,47.41757],"type":"Point"}
}