{
  "type": "Feature",
  "properties": {
    "addr:full":"1420 5th Ave. Suite 3010 Seattle WA 98101",
    "addr:housenumber":"1420",
    "addr:postcode":"98101",
    "addr:street":"5Th Ave. Suite 3010",
    "iso:country":"US",
    "sg:address":"1420 5th Ave. Suite 3010",
    "sg:city":"Seattle",
    "sg:classifiers":[
        {
            "category":"Professional",
            "subcategory":"Lawyer & Legal Services",
            "type":"Services"
        }
    ],
    "sg:phone":"+1 206 407 1524",
    "sg:postcode":"98101",
    "sg:province":"WA",
    "sg:website":"www.schwabe.com/showattorney.asp...",
    "wof:name":"Howard Christopher H Atty",
    "wof:placetype":"venue"
},
  "geometry": {"coordinates":[-122.33486600000001,47.609931],"type":"Point"}
}