{
  "type": "Feature",
  "properties": {
    "addr:full":"1133 W James St Kent WA 98032",
    "addr:housenumber":"1133",
    "addr:postcode":"98032",
    "addr:street":"W James St",
    "iso:country":"US",
    "sg:address":"1133 W James St",
    "sg:city":"Kent",
    "sg:classifiers":[
        {
            "category":"Retail",
            "subcategory":"Auto Repair",
            "type":"Services"
        }
    ],
    "sg:phone":"+1 253 856 7554",
    "sg:postcode":"98032",
    "sg:province":"WA",
    "sg:tags":[
        "repairing",
        "automobile"
    ],
    "wof:name":"Discount Automotive Svc",
    "wof:placetype":"venue"
},
  "geometry": {"coordinates":[-122.24730599999999,47.386806],"type":"Point"}
}