{
  "type": "Feature",
  "properties": {
    "iso:country":"US",
    "sg:address":"25025 SE Klahanie Blvd",
    "sg:city":"Issaquah",
    "sg:classifiers":[
        {
            "category":"Professional",
            "type":"Services"
        }
    ],
    "sg:phone":"+1 425 369 2220",
    "sg:postcode":"98029",
    "sg:province":"WA",
    "wof:name":"Home Project Resources Inc",
    "wof:placetype":"venue"
},
  "geometry": {"coordinates":[-122.00873900000001,47.575935],"type":"Point"}
}