{
  "type": "Feature",
  "properties": {
    "addr:full":"17210 Rd 10 SE Warden WA 98857",
    "addr:housenumber":"17210",
    "addr:postcode":"98857",
    "addr:street":"Rd 10 Se Warden",
    "iso:country":"US",
    "sg:address":"17210 Rd 10 SE",
    "sg:city":"Warden",
    "sg:classifiers":[
        {
            "category":"Farming",
            "subcategory":"Dairy Farm",
            "type":"Manufacturing & Wholesale Goods"
        }
    ],
    "sg:phone":"+1 509 349 2231",
    "sg:postcode":"98857",
    "sg:province":"WA",
    "wof:name":"Cole & Sons",
    "wof:placetype":"venue"
},
  "geometry": {"coordinates":[-119.120773,46.941272],"type":"Point"}
}