{
  "type": "Feature",
  "properties": {
    "iso:country":"US",
    "sg:address":"711 Tumwater Blvd",
    "sg:city":"Olympia",
    "sg:classifiers":[
        {
            "category":"Manufacturing",
            "subcategory":"Lumber",
            "type":"Manufacturing & Wholesale Goods"
        }
    ],
    "sg:phone":"+1 360 705 2431",
    "sg:postcode":"98501",
    "sg:province":"WA",
    "sg:tags":[
        "product",
        "forest",
        "gathering"
    ],
    "wof:name":"Four Seasons Greenery Industry",
    "wof:placetype":"venue"
},
  "geometry": {"coordinates":[-122.892475,46.98528],"type":"Point"}
}