{
  "type": "Feature",
  "properties": {
    "addr:full":"17145 Cook Rd Bow WA 98232",
    "addr:housenumber":"17145",
    "addr:postcode":"98232",
    "addr:street":"Cook Rd",
    "iso:country":"US",
    "sg:address":"17145 Cook Rd",
    "sg:city":"Bow",
    "sg:classifiers":[
        {
            "category":"Education",
            "subcategory":"School",
            "type":"Public Place"
        }
    ],
    "sg:phone":"+1 360 757 3352",
    "sg:postcode":"98232",
    "sg:province":"WA",
    "sg:website":"www.be.wednet.edu",
    "wof:name":"Allen Elementary School",
    "wof:placetype":"venue"
},
  "geometry": {"coordinates":[-122.368365,48.508518],"type":"Point"}
}