{
  "type": "Feature",
  "properties": {
    "addr:full":"1010 Woodworth Rd Grandview WA 98930",
    "addr:housenumber":"1010",
    "addr:postcode":"98930",
    "addr:street":"Woodworth Rd",
    "iso:country":"US",
    "sg:address":"1010 Woodworth Rd",
    "sg:city":"Grandview",
    "sg:classifiers":[
        {
            "category":"Building & Trades",
            "subcategory":"Construction",
            "type":"Services"
        }
    ],
    "sg:phone":"+1 509 882 4729",
    "sg:postcode":"98930",
    "sg:province":"WA",
    "sg:tags":[
        "remodeling"
    ],
    "wof:name":"Douglas Shelton Construction",
    "wof:placetype":"venue"
},
  "geometry": {"coordinates":[-119.92412299999999,46.287298],"type":"Point"}
}