{
  "type": "Feature",
  "properties": {
    "addr:full":"8414 47th Ave S Seattle WA 98118",
    "addr:housenumber":"8414",
    "addr:postcode":"98118",
    "addr:street":"47Th Ave S",
    "iso:country":"US",
    "sg:address":"8414 47th Ave S",
    "sg:city":"Seattle",
    "sg:classifiers":[
        {
            "category":"Professional",
            "type":"Services"
        }
    ],
    "sg:phone":"+1 206 725 3628",
    "sg:postcode":"98118",
    "sg:province":"WA",
    "wof:name":"Foster Jones",
    "wof:placetype":"venue"
},
  "geometry": {"coordinates":[-122.273346,47.526248],"type":"Point"}
}