{
  "type": "Feature",
  "properties": {
    "addr:full":"25920 NE 29th Pl Redmond WA 98053",
    "addr:housenumber":"25920",
    "addr:postcode":"98053",
    "addr:street":"Ne 29Th Pl",
    "iso:country":"US",
    "sg:address":"25920 NE 29th Pl",
    "sg:city":"Redmond",
    "sg:classifiers":[
        {
            "category":"Professional",
            "subcategory":"Art Services",
            "type":"Services"
        }
    ],
    "sg:phone":"+1 425 830 4030",
    "sg:postcode":"98053",
    "sg:province":"WA",
    "sg:tags":[
        "designer",
        "display",
        "producer"
    ],
    "wof:name":"Penny Matlick Designs",
    "wof:placetype":"venue"
},
  "geometry": {"coordinates":[-121.993561,47.634819],"type":"Point"}
}