{
  "type": "Feature",
  "properties": {
    "addr:full":"612 Malden Ave E Seattle WA 98112",
    "addr:housenumber":"612",
    "addr:postcode":"98112",
    "addr:street":"Malden Ave E",
    "iso:country":"US",
    "sg:address":"612 Malden Ave E",
    "sg:city":"Seattle",
    "sg:classifiers":[
        {
            "category":"Manufacturing",
            "subcategory":"Apparel",
            "type":"Manufacturing & Wholesale Goods"
        }
    ],
    "sg:phone":"+1 206 383 8251",
    "sg:postcode":"98112",
    "sg:province":"WA",
    "sg:tags":[
        "outerwear",
        "mfg"
    ],
    "wof:name":"Sutemi Gear",
    "wof:placetype":"venue"
},
  "geometry": {"coordinates":[-122.313523,47.625142],"type":"Point"}
}