{
  "type": "Feature",
  "properties": {
    "addr:full":"5225 S 356th St Auburn WA 98001",
    "addr:housenumber":"5225",
    "addr:postcode":"98001",
    "addr:street":"S 356Th St",
    "iso:country":"US",
    "sg:address":"5225 S 356th St",
    "sg:city":"Auburn",
    "sg:classifiers":[
        {
            "category":"Professional",
            "subcategory":"Computer Services",
            "type":"Services"
        }
    ],
    "sg:phone":"+1 253 939 5320",
    "sg:postcode":"98001",
    "sg:province":"WA",
    "sg:tags":[
        "datum"
    ],
    "wof:name":"Ss Webs",
    "wof:placetype":"venue"
},
  "geometry": {"coordinates":[-122.269102,47.282432],"type":"Point"}
}