{
  "type": "Feature",
  "properties": {
    "addr:full":"2252 NE 177th St Shoreline WA 98155",
    "addr:housenumber":"2252",
    "addr:postcode":"98155",
    "addr:street":"Ne 177Th St",
    "iso:country":"US",
    "sg:address":"2252 NE 177th St",
    "sg:city":"Shoreline",
    "sg:classifiers":[
        {
            "category":"Freight",
            "type":"Transportation"
        }
    ],
    "sg:phone":"+1 206 364 5166",
    "sg:postcode":"98155",
    "sg:province":"WA",
    "sg:tags":[
        "consultant"
    ],
    "wof:name":"A R Torrico & Sons Inc",
    "wof:placetype":"venue"
},
  "geometry": {"coordinates":[-122.30329399999999,47.755762],"type":"Point"}
}