{
  "type": "Feature",
  "properties": {
    "addr:full":"1790 Kittleson Rd Moses Lake WA 98837",
    "addr:housenumber":"1790",
    "addr:postcode":"98837",
    "addr:street":"Kittleson Rd",
    "iso:country":"US",
    "sg:address":"1790 Kittleson Rd",
    "sg:city":"Moses Lake",
    "sg:classifiers":[
        {
            "category":"Coffee & Tea",
            "type":"Food & Drink"
        }
    ],
    "sg:menulink":"http://www.allmenus.com/wa/moses-lake/117642-starbucks-coffee/menu/",
    "sg:phone":"+1 509 764 4740",
    "sg:postcode":"98837",
    "sg:province":"WA",
    "sg:tags":[
        "american"
    ],
    "wof:name":"Starbucks Coffee",
    "wof:placetype":"venue"
},
  "geometry": {"coordinates":[-119.261201,47.10182],"type":"Point"}
}