{
  "type": "Feature",
  "properties": {
    "addr:full":"3819 100th St SW Ste 19 Lakewood WA 98499",
    "addr:housenumber":"3819",
    "addr:postcode":"98499",
    "addr:street":"100Th St Sw Ste 19",
    "iso:country":"US",
    "sg:address":"3819 100th St SW Ste 19",
    "sg:city":"Lakewood",
    "sg:classifiers":[
        {
            "category":"Insurance",
            "subcategory":"Hazard Insurance",
            "type":"Services"
        }
    ],
    "sg:phone":"+1 253 582 5125",
    "sg:postcode":"98499",
    "sg:province":"WA",
    "sg:tags":[
        "commercial",
        "business"
    ],
    "wof:name":"D M S Insurance Benefits Farmers Agency",
    "wof:placetype":"venue"
},
  "geometry": {"coordinates":[-122.48641000000001,47.166846],"type":"Point"}
}