{
  "type": "Feature",
  "properties": {
    "addr:full":"1825 Howard Rd Auburn WA 98002",
    "addr:housenumber":"1825",
    "addr:postcode":"98002",
    "addr:street":"Howard Rd",
    "iso:country":"US",
    "sg:address":"1825 Howard Rd",
    "sg:city":"Auburn",
    "sg:classifiers":[
        {
            "category":"Professional",
            "subcategory":"Business Services",
            "type":"Services"
        }
    ],
    "sg:phone":"+1 253 833 3736",
    "sg:postcode":"98002",
    "sg:province":"WA",
    "wof:name":"Gustafson Enterprises Inc",
    "wof:placetype":"venue"
},
  "geometry": {"coordinates":[-122.211673,47.292866],"type":"Point"}
}