{
  "type": "Feature",
  "properties": {
    "addr:full":"606 Post Ave Seattle WA 98104",
    "addr:housenumber":"606",
    "addr:postcode":"98104",
    "addr:street":"Post Ave",
    "iso:country":"US",
    "sg:address":"606 Post Ave",
    "sg:city":"Seattle",
    "sg:classifiers":[
        {
            "category":"Communications",
            "subcategory":"Film & Video Production",
            "type":"Services"
        }
    ],
    "sg:phone":"+1 206 568 6271",
    "sg:postcode":"98104",
    "sg:province":"WA",
    "sg:tags":[
        "taping"
    ],
    "wof:name":"Global Griot Productions",
    "wof:placetype":"venue"
},
  "geometry": {"coordinates":[-122.335431,47.603016],"type":"Point"}
}