{
  "type": "Feature",
  "properties": {
    "addr:full":"203 Woodring St Cashmere WA 98815",
    "addr:housenumber":"203",
    "addr:postcode":"98815",
    "addr:street":"Woodring St",
    "iso:country":"US",
    "sg:address":"203 Woodring St",
    "sg:city":"Cashmere",
    "sg:classifiers":[
        {
            "category":"Shopping",
            "subcategory":"Gifts & Souvenirs",
            "type":"Retail Goods"
        }
    ],
    "sg:phone":"+1 509 782 0332",
    "sg:postcode":"98815",
    "sg:province":"WA",
    "sg:tags":[
        "novelty"
    ],
    "wof:name":"Gift Galore",
    "wof:placetype":"venue"
},
  "geometry": {"coordinates":[-120.467867,47.522776],"type":"Point"}
}