{
  "type": "Feature",
  "properties": {
    "addr:full":"2320 Rucker Ave Everett WA 98201",
    "addr:housenumber":"2320",
    "addr:postcode":"98201",
    "addr:street":"Rucker Ave",
    "iso:country":"US",
    "sg:address":"2320 Rucker Ave",
    "sg:city":"Everett",
    "sg:classifiers":[
        {
            "category":"Health Services",
            "subcategory":"Doctor",
            "type":"Services"
        }
    ],
    "sg:phone":"+1 425 259 5121",
    "sg:postcode":"98201",
    "sg:province":"WA",
    "sg:tags":[
        "physician",
        "surgeon",
        "neurology",
        "surgeons"
    ],
    "wof:name":"Wilhelm, Crispin Md",
    "wof:placetype":"venue"
},
  "geometry": {"coordinates":[-122.211258,47.986968],"type":"Point"}
}