{
  "type": "Feature",
  "properties": {
    "addr:full":"9401 Farwest Dr SW Lakewood WA 98498",
    "addr:housenumber":"9401",
    "addr:postcode":"98498",
    "addr:street":"Farwest Dr Sw",
    "iso:country":"US",
    "sg:address":"9401 Farwest Dr SW",
    "sg:city":"Lakewood",
    "sg:classifiers":[
        {
            "category":"Building & Trades",
            "subcategory":"Construction",
            "type":"Services"
        }
    ],
    "sg:phone":"+1 253 582 2900",
    "sg:postcode":"98498",
    "sg:province":"WA",
    "sg:tags":[
        "contractor"
    ],
    "wof:name":"Pease Construction",
    "wof:placetype":"venue"
},
  "geometry": {"coordinates":[-122.574068,47.17245],"type":"Point"}
}