{
  "type": "Feature",
  "properties": {
    "addr:full":"31255 US Hwy 97 Tonasket WA 98855",
    "addr:housenumber":"31255",
    "addr:postcode":"98855",
    "addr:street":"Us Hwy 97",
    "iso:country":"US",
    "sg:address":"31255 US Hwy 97",
    "sg:city":"Tonasket",
    "sg:classifiers":[
        {
            "category":"Farming",
            "subcategory":"Orchard",
            "type":"Manufacturing & Wholesale Goods"
        }
    ],
    "sg:phone":"+1 509 486 4983",
    "sg:postcode":"98855",
    "sg:province":"WA",
    "sg:tags":[
        "fruit",
        "tree"
    ],
    "wof:name":"Clarkson Orchards",
    "wof:placetype":"venue"
},
  "geometry": {"coordinates":[-119.469748,48.67379],"type":"Point"}
}