{
  "type": "Feature",
  "properties": {
    "addr:full":"102 Bellevue Way NE Bellevue WA 98004",
    "addr:housenumber":"102",
    "addr:postcode":"98004",
    "addr:street":"Bellevue Way Ne",
    "iso:country":"US",
    "sg:address":"102 Bellevue Way NE",
    "sg:city":"Bellevue",
    "sg:classifiers":[
        {
            "category":"Shopping",
            "subcategory":"Optician",
            "type":"Retail Goods"
        }
    ],
    "sg:phone":"+1 425 454 4611",
    "sg:postcode":"98004",
    "sg:province":"WA",
    "sg:tags":[
        "eyewear"
    ],
    "wof:name":"Western Optical Corporation",
    "wof:placetype":"venue"
},
  "geometry": {"coordinates":[-122.200996,47.611099],"type":"Point"}
}