{
  "type": "Feature",
  "properties": {
    "addr:full":"8522 382nd Ave SE Snoqualmie WA 98065",
    "addr:housenumber":"8522",
    "addr:postcode":"98065",
    "addr:street":"382Nd Ave Se",
    "iso:country":"US",
    "sg:address":"8522 382nd Ave SE",
    "sg:city":"Snoqualmie",
    "sg:classifiers":[
        {
            "category":"Retail",
            "subcategory":"Portrait Studio",
            "type":"Services"
        }
    ],
    "sg:phone":"+1 425 888 0613",
    "sg:postcode":"98065",
    "sg:province":"WA",
    "sg:tags":[
        "photo"
    ],
    "wof:name":"Frank Neef Photographer",
    "wof:placetype":"venue"
},
  "geometry": {"coordinates":[-121.83086,47.522722],"type":"Point"}
}