{
  "type": "Feature",
  "properties": {
    "addr:full":"16713 Canal Rd SE Yelm WA 98597",
    "addr:housenumber":"16713",
    "addr:postcode":"98597",
    "addr:street":"Canal Rd Se Yelm",
    "iso:country":"US",
    "sg:address":"16713 Canal Rd SE",
    "sg:city":"Yelm",
    "sg:classifiers":[
        {
            "category":"Retail",
            "subcategory":"Auto Repair",
            "type":"Services"
        }
    ],
    "sg:phone":"+1 360 458 3428",
    "sg:postcode":"98597",
    "sg:province":"WA",
    "sg:tags":[
        "shop",
        "general"
    ],
    "wof:name":"T&P Automotive Service",
    "wof:placetype":"venue"
},
  "geometry": {"coordinates":[-122.588686,46.948759],"type":"Point"}
}