{
  "type": "Feature",
  "properties": {
    "addr:full":"10630 176th Ave SW Rochester WA 98579",
    "addr:housenumber":"10630",
    "addr:postcode":"98579",
    "addr:street":"176Th Ave Sw",
    "iso:country":"US",
    "sg:address":"10630 176th Ave SW",
    "sg:city":"Rochester",
    "sg:classifiers":[
        {
            "category":"Professional",
            "subcategory":"Engineering",
            "type":"Services"
        }
    ],
    "sg:phone":"+1 360 273 8110",
    "sg:postcode":"98579",
    "sg:province":"WA",
    "sg:tags":[
        "consulting",
        "engineer"
    ],
    "wof:name":"Evergreen Wreaths",
    "wof:placetype":"venue"
},
  "geometry": {"coordinates":[-123.107578,46.832604],"type":"Point"}
}