{
  "type": "Feature",
  "properties": {
    "addr:full":"4040 23rd Ave W Seattle WA 98199",
    "addr:housenumber":"4040",
    "addr:postcode":"98199",
    "addr:street":"23Rd Ave W",
    "iso:country":"US",
    "sg:address":"4040 23rd Ave W",
    "sg:city":"Seattle",
    "sg:classifiers":[
        {
            "category":"Professional",
            "type":"Services"
        },
        {
            "category":"Personal",
            "type":"Services"
        }
    ],
    "sg:phone":"+1 206 953 2394",
    "sg:postcode":"98199",
    "sg:province":"WA",
    "sg:tags":[
        "sewing",
        "alteration"
    ],
    "sg:website":"www.1stimpressionsembroidery.com",
    "wof:name":"1st Impressions Embroidery",
    "wof:placetype":"venue"
},
  "geometry": {"coordinates":[-122.38593899999999,47.657267],"type":"Point"}
}