{
  "type": "Feature",
  "properties": {
    "addr:full":"3213 W Wheeler St Seattle WA 98199",
    "addr:housenumber":"3213",
    "addr:postcode":"98199",
    "addr:street":"W Wheeler St",
    "iso:country":"US",
    "sg:address":"3213 W Wheeler St",
    "sg:city":"Seattle",
    "sg:classifiers":[
        {
            "category":"Shopping",
            "subcategory":"Computers & Home Electronics",
            "type":"Retail Goods"
        }
    ],
    "sg:phone":"+1 206 286 7581",
    "sg:postcode":"98199",
    "sg:province":"WA",
    "sg:tags":[
        "system"
    ],
    "wof:name":"Data/Point System Inc",
    "wof:placetype":"venue"
},
  "geometry": {"coordinates":[-122.39951499999999,47.639957],"type":"Point"}
}