{
  "type": "Feature",
  "properties": {
    "iso:country":"US",
    "sg:address":"505 W Riverside Ave",
    "sg:city":"Spokane",
    "sg:classifiers":[
        {
            "category":"Restaurant",
            "type":"Food & Drink"
        }
    ],
    "sg:phone":"+1 509 624 3027",
    "sg:postcode":"99201",
    "sg:province":"WA",
    "wof:name":"Fried Circuits",
    "wof:placetype":"venue"
},
  "geometry": {"coordinates":[-117.42103400000001,47.657865],"type":"Point"}
}