{
  "type": "Feature",
  "properties": {
    "addr:full":"19119 Loganberry St SW Rochester WA 98579",
    "addr:housenumber":"19119",
    "addr:postcode":"98579",
    "addr:street":"Loganberry St Sw",
    "iso:country":"US",
    "sg:address":"19119 Loganberry St SW",
    "sg:city":"Rochester",
    "sg:classifiers":[
        {
            "category":"Manufacturing",
            "subcategory":"Glass & Minerals",
            "type":"Manufacturing & Wholesale Goods"
        }
    ],
    "sg:phone":"+1 360 561 3678",
    "sg:postcode":"98579",
    "sg:province":"WA",
    "sg:tags":[
        "glass-wholesale",
        "shape",
        "circle",
        "special",
        "manufacturer"
    ],
    "wof:name":"Blue Devil Glass",
    "wof:placetype":"venue"
},
  "geometry": {"coordinates":[-122.994433,46.811382],"type":"Point"}
}