{
  "type": "Feature",
  "properties": {
    "addr:full":"139 W Alder St Sequim WA 98382",
    "addr:housenumber":"139",
    "addr:postcode":"98382",
    "addr:street":"W Alder St",
    "iso:country":"US",
    "sg:address":"139 W Alder St",
    "sg:city":"Sequim",
    "sg:classifiers":[
        {
            "category":"Restaurant",
            "type":"Food & Drink"
        }
    ],
    "sg:menulink":"http://www.allmenus.com/wa/sequim/38924-alder-wood-bistro/menu/",
    "sg:phone":"+1 360 683 4321",
    "sg:postcode":"98382",
    "sg:province":"WA",
    "sg:tags":[
        "french"
    ],
    "wof:name":"Alder Wood Bistro",
    "wof:placetype":"venue"
},
  "geometry": {"coordinates":[-123.10333199999999,48.082353],"type":"Point"}
}