{
  "type": "Feature",
  "properties": {
    "addr:full":"14209 SE 45th St Bellevue WA 98006",
    "addr:postcode":"14209;98006",
    "addr:street":"Se 45Th St",
    "iso:country":"US",
    "sg:address":"14209 SE 45th St",
    "sg:city":"Bellevue",
    "sg:classifiers":[
        {
            "category":"Shopping",
            "subcategory":"Pharmacy",
            "type":"Retail Goods"
        }
    ],
    "sg:phone":"+1 425 641 6374",
    "sg:postcode":"98006",
    "sg:province":"WA",
    "wof:name":"Rxsales Prescriptions Sales Co",
    "wof:placetype":"venue"
},
  "geometry": {"coordinates":[-122.150036,47.565944],"type":"Point"}
}