{
  "type": "Feature",
  "properties": {
    "addr:full":"5617 111th St E Puyallup WA 98373",
    "addr:housenumber":"5617",
    "addr:postcode":"98373",
    "addr:street":"111Th St E",
    "iso:country":"US",
    "sg:address":"5617 111th St E",
    "sg:city":"Puyallup",
    "sg:classifiers":[
        {
            "category":"Real Estate",
            "subcategory":"Real Estate Operator",
            "type":"Services"
        }
    ],
    "sg:phone":"+1 253 840 5000",
    "sg:postcode":"98373",
    "sg:province":"WA",
    "sg:tags":[
        "building",
        "apartment"
    ],
    "wof:name":"Canyon Park Apartments",
    "wof:placetype":"venue"
},
  "geometry": {"coordinates":[-122.340175,47.155459],"type":"Point"}
}