{
  "type": "Feature",
  "properties": {
    "addr:full":"374 Curtis Hill Rd Chehalis WA 98532",
    "addr:housenumber":"374",
    "addr:postcode":"98532",
    "addr:street":"Curtis Hill Rd",
    "iso:country":"US",
    "sg:address":"374 Curtis Hill Rd",
    "sg:city":"Chehalis",
    "sg:classifiers":[
        {
            "category":"Building & Trades",
            "subcategory":"Construction",
            "type":"Services"
        }
    ],
    "sg:phone":"+1 360 740 6242",
    "sg:postcode":"98532",
    "sg:province":"WA",
    "sg:tags":[
        "contractor"
    ],
    "wof:name":"Stb Construction Inc",
    "wof:placetype":"venue"
},
  "geometry": {"coordinates":[-123.095674,46.612344],"type":"Point"}
}