{
  "type": "Feature",
  "properties": {
    "addr:full":"3709 S Ferdinand St Seattle WA 98118",
    "addr:housenumber":"3709",
    "addr:postcode":"98118",
    "addr:street":"S Ferdinand St",
    "iso:country":"US",
    "sg:address":"3709 S Ferdinand St",
    "sg:city":"Seattle",
    "sg:classifiers":[
        {
            "category":"Shopping",
            "subcategory":"Bicycles & Sporting Goods",
            "type":"Retail Goods"
        }
    ],
    "sg:phone":"+1 206 725 9408",
    "sg:postcode":"98118",
    "sg:province":"WA",
    "sg:tags":[
        "service/non-profit",
        "community"
    ],
    "sg:website":"www.bikeworks.org",
    "wof:name":"Bike Works",
    "wof:placetype":"venue"
},
  "geometry": {"coordinates":[-122.28600299999999,47.557701],"type":"Point"}
}