{
  "type": "Feature",
  "properties": {
    "addr:full":"780 W State Hwy 108 Shelton WA 98584",
    "addr:housenumber":"780",
    "addr:postcode":"98584",
    "addr:street":"W State Hwy 108",
    "iso:country":"US",
    "sg:address":"780 W State Hwy 108",
    "sg:city":"Shelton",
    "sg:classifiers":[
        {
            "category":"Manufacturing",
            "subcategory":"Lumber",
            "type":"Manufacturing & Wholesale Goods"
        }
    ],
    "sg:phone":"+1 360 427 8853",
    "sg:postcode":"98584",
    "sg:province":"WA",
    "sg:tags":[
        "company",
        "logging"
    ],
    "wof:name":"Gray's Harbor Scaling Bureau",
    "wof:placetype":"venue"
},
  "geometry": {"coordinates":[-123.114226,47.123988],"type":"Point"}
}