{
  "type": "Feature",
  "properties": {
    "iso:country":"US",
    "sg:address":"502 O Ave",
    "sg:city":"Anacortes",
    "sg:classifiers":[
        {
            "category":"Utilities",
            "subcategory":"Natural Gas",
            "type":"Services"
        }
    ],
    "sg:phone":"+1 360 293 5164",
    "sg:postcode":"98221",
    "sg:province":"WA",
    "sg:tags":[
        "company"
    ],
    "wof:name":"Cascade Natural Gas Corp",
    "wof:placetype":"venue"
},
  "geometry": {"coordinates":[-122.61414499999999,48.518278],"type":"Point"}
}