{
  "type": "Feature",
  "properties": {
    "addr:full":"14212 134th Dr SE Snohomish WA 98290",
    "addr:housenumber":"14212",
    "addr:postcode":"98290",
    "addr:street":"134Th Dr Se",
    "iso:country":"US",
    "sg:address":"14212 134th Dr SE",
    "sg:city":"Snohomish",
    "sg:classifiers":[
        {
            "category":"Building & Trades",
            "subcategory":"Construction",
            "type":"Services"
        }
    ],
    "sg:phone":"+1 360 568 1651",
    "sg:postcode":"98290",
    "sg:province":"WA",
    "sg:tags":[
        "house",
        "nonresidential"
    ],
    "wof:name":"Riley Construction",
    "wof:placetype":"venue"
},
  "geometry": {"coordinates":[-122.05056500000001,47.876884],"type":"Point"}
}