{
  "type": "Feature",
  "properties": {
    "addr:full":"207 SE 105th Ave Vancouver WA 98664",
    "addr:housenumber":"207",
    "addr:postcode":"98664",
    "addr:street":"Se 105Th Ave",
    "iso:country":"US",
    "sg:address":"207 SE 105th Ave",
    "sg:city":"Vancouver",
    "sg:classifiers":[
        {
            "category":"Building & Trades",
            "subcategory":"Construction",
            "type":"Services"
        }
    ],
    "sg:phone":"+1 360 256 3471",
    "sg:postcode":"98664",
    "sg:province":"WA",
    "sg:tags":[
        "nonresidential"
    ],
    "wof:name":"Cherokee Construction",
    "wof:placetype":"venue"
},
  "geometry": {"coordinates":[-122.564397,45.61955],"type":"Point"}
}