{
  "type": "Feature",
  "properties": {
    "addr:full":"6201 15th Ave NW # 542 Seattle WA 98107",
    "addr:housenumber":"6201",
    "addr:postcode":"98107",
    "addr:street":"15Th Ave Nw # 542",
    "iso:country":"US",
    "sg:address":"6201 15th Ave NW # 542",
    "sg:city":"Seattle",
    "sg:classifiers":[
        {
            "category":"Health Services",
            "subcategory":"Clinic",
            "type":"Services"
        }
    ],
    "sg:phone":"+1 206 250 5639",
    "sg:postcode":"98107",
    "sg:province":"WA",
    "sg:tags":[
        "medical"
    ],
    "sg:website":"www.theyshallwalk.org",
    "wof:name":"They Shall Walk",
    "wof:placetype":"venue"
},
  "geometry": {"coordinates":[-122.376217,47.673818],"type":"Point"}
}