{
  "type": "Feature",
  "properties": {
    "addr:full":"2035 NW Blue Ridge Dr Seattle WA 98177",
    "addr:housenumber":"2035",
    "addr:postcode":"98177",
    "addr:street":"Nw Blue Ridge Dr",
    "iso:country":"US",
    "sg:address":"2035 NW Blue Ridge Dr",
    "sg:city":"Seattle",
    "sg:classifiers":[
        {
            "category":"Professional",
            "subcategory":"Accounting & Tax Preparation",
            "type":"Services"
        }
    ],
    "sg:phone":"+1 206 605 1657",
    "sg:postcode":"98177",
    "sg:province":"WA",
    "wof:name":"Kls Enterprises",
    "wof:placetype":"venue"
},
  "geometry": {"coordinates":[-122.383251,47.703466],"type":"Point"}
}