{
  "type": "Feature",
  "properties": {
    "addr:full":"18606 NW Cervinia Ct Issaquah WA 98027",
    "addr:housenumber":"18606",
    "addr:postcode":"98027",
    "addr:street":"Nw Cervinia Ct",
    "iso:country":"US",
    "sg:address":"18606 NW Cervinia Ct",
    "sg:city":"Issaquah",
    "sg:classifiers":[
        {
            "category":"Professional",
            "subcategory":"Computer Services",
            "type":"Services"
        }
    ],
    "sg:phone":"+1 425 643 9388",
    "sg:postcode":"98027",
    "sg:province":"WA",
    "sg:tags":[
        "web",
        "medical",
        "site",
        "custom",
        "design",
        "programing"
    ],
    "sg:website":"http://www.anesoft.com",
    "wof:name":"Anesoft Corporation",
    "wof:placetype":"venue"
},
  "geometry": {"coordinates":[-122.09350000000001,47.553136],"type":"Point"}
}