{
  "type": "Feature",
  "properties": {
    "iso:country":"US",
    "sg:address":"17015 NE 32nd St",
    "sg:city":"Bellevue",
    "sg:classifiers":[
        {
            "category":"Wholesale",
            "subcategory":"Toys & Hobbies",
            "type":"Manufacturing & Wholesale Goods"
        }
    ],
    "sg:phone":"+1 425 881 8984",
    "sg:postcode":"98008",
    "sg:province":"WA",
    "sg:tags":[
        "wholesaler"
    ],
    "wof:name":"Bucket Buddy Co",
    "wof:placetype":"venue"
},
  "geometry": {"coordinates":[-122.112061,47.63916],"type":"Point"}
}