{
  "type": "Feature",
  "properties": {
    "addr:full":"6342 123rd Ave SW Olympia WA 98512",
    "addr:housenumber":"6342",
    "addr:postcode":"98512",
    "addr:street":"123Rd Ave Sw",
    "iso:country":"US",
    "sg:address":"6342 123rd Ave SW",
    "sg:city":"Olympia",
    "sg:classifiers":[
        {
            "category":"Farming",
            "subcategory":"Berry Farm",
            "type":"Manufacturing & Wholesale Goods"
        }
    ],
    "sg:phone":"+1 360 357 8370",
    "sg:postcode":"98512",
    "sg:province":"WA",
    "sg:tags":[
        "crop"
    ],
    "wof:name":"Teddies Berries",
    "wof:placetype":"venue"
},
  "geometry": {"coordinates":[-123.01855399999999,46.909174],"type":"Point"}
}