{
  "type": "Feature",
  "properties": {
    "iso:country":"US",
    "sg:address":"2406 E Trent Ave",
    "sg:city":"Spokane",
    "sg:classifiers":[
        {
            "category":"Retail",
            "subcategory":"Auto Repair",
            "type":"Services"
        }
    ],
    "sg:phone":"+1 509 534 0387",
    "sg:postcode":"99202",
    "sg:province":"WA",
    "sg:tags":[
        "automotive"
    ],
    "wof:name":"Bateman Towing",
    "wof:placetype":"venue"
},
  "geometry": {"coordinates":[-117.374538,47.662369],"type":"Point"}
}