{
  "type": "Feature",
  "properties": {
    "addr:full":"12411 16th St NE Lake Stevens WA 98258",
    "addr:housenumber":"12411",
    "addr:postcode":"98258",
    "addr:street":"16Th St Ne",
    "iso:country":"US",
    "sg:address":"12411 16th St NE",
    "sg:city":"Lake Stevens",
    "sg:classifiers":[
        {
            "category":"Social Services",
            "type":"Services"
        }
    ],
    "sg:phone":"+1 425 397 8214",
    "sg:postcode":"98258",
    "sg:province":"WA",
    "sg:tags":[
        "organization",
        "welfare"
    ],
    "wof:name":"Teen Parent Housing Council",
    "wof:placetype":"venue"
},
  "geometry": {"coordinates":[-122.063799,48.01196],"type":"Point"}
}