{
  "type": "Feature",
  "properties": {
    "addr:full":"11643 NE 155th St Bothell WA 98011",
    "addr:housenumber":"11643",
    "addr:postcode":"98011",
    "addr:street":"Ne 155Th St",
    "iso:country":"US",
    "sg:address":"11643 NE 155th St",
    "sg:city":"Bothell",
    "sg:classifiers":[
        {
            "category":"Building & Trades",
            "subcategory":"Construction",
            "type":"Services"
        }
    ],
    "sg:phone":"+1 425 488 2049",
    "sg:postcode":"98011",
    "sg:province":"WA",
    "sg:tags":[
        "contractor"
    ],
    "wof:name":"Lucas Roofing",
    "wof:placetype":"venue"
},
  "geometry": {"coordinates":[-122.184091,47.739027],"type":"Point"}
}