{
  "type": "Feature",
  "properties": {
    "addr:full":"12056 12th Ave NE Seattle WA 98125",
    "addr:housenumber":"12056",
    "addr:postcode":"98125",
    "addr:street":"12Th Ave Ne",
    "iso:country":"US",
    "sg:address":"12056 12th Ave NE",
    "sg:city":"Seattle",
    "sg:classifiers":[
        {
            "category":"Building & Trades",
            "subcategory":"Construction",
            "type":"Services"
        }
    ],
    "sg:phone":"+1 206 440 1193",
    "sg:postcode":"98125",
    "sg:province":"WA",
    "sg:tags":[
        "general",
        "contractor"
    ],
    "wof:name":"Eriks Construction Co",
    "wof:placetype":"venue"
},
  "geometry": {"coordinates":[-122.315224,47.715965],"type":"Point"}
}