{
  "type": "Feature",
  "properties": {
    "addr:full":"2735 California Ave SW Seattle WA 98116",
    "addr:housenumber":"2735",
    "addr:postcode":"98116",
    "addr:street":"California Ave Sw",
    "iso:country":"US",
    "sg:address":"2735 California Ave SW",
    "sg:city":"Seattle",
    "sg:classifiers":[
        {
            "category":"Personal",
            "subcategory":"Massage",
            "type":"Services"
        },
        {
            "category":"Health Services",
            "subcategory":"Clinic",
            "type":"Services"
        },
        {
            "category":"Health Services",
            "subcategory":"Health Practitioner",
            "type":"Services"
        }
    ],
    "sg:phone":"+1 206 937 3098",
    "sg:postcode":"98116",
    "sg:province":"WA",
    "sg:tags":[
        "therapist",
        "therapy",
        "physical"
    ],
    "sg:website":"www.painfreesolutions.com",
    "wof:name":"Pain-Free Solutions",
    "wof:placetype":"venue"
},
  "geometry": {"coordinates":[-122.38661399999999,47.579046],"type":"Point"}
}