{
  "type": "Feature",
  "properties": {
    "addr:full":"10024 SE 8th St Bellevue WA 98004",
    "addr:postcode":"10024;98004",
    "addr:street":"Se 8Th St",
    "iso:country":"US",
    "sg:address":"10024 SE 8th St",
    "sg:city":"Bellevue",
    "sg:classifiers":[
        {
            "category":"Shopping",
            "subcategory":"Hobbies, Toys, & Games",
            "type":"Retail Goods"
        }
    ],
    "sg:phone":"+1 425 454 9575",
    "sg:postcode":"98004",
    "sg:province":"WA",
    "sg:tags":[
        "arts",
        "craft"
    ],
    "wof:name":"Flower Reflection",
    "wof:placetype":"venue"
},
  "geometry": {"coordinates":[-122.205921,47.602902],"type":"Point"}
}