{
  "type": "Feature",
  "properties": {
    "addr:full":"20746 108th Ave SE Kent WA 98031",
    "addr:housenumber":"20746",
    "addr:postcode":"98031",
    "addr:street":"108Th Ave Se",
    "iso:country":"US",
    "sg:address":"20746 108th Ave SE",
    "sg:city":"Kent",
    "sg:classifiers":[
        {
            "category":"Restaurant",
            "type":"Food & Drink"
        }
    ],
    "sg:menulink":"http://www.allmenus.com/wa/seattle/177892-jack-in-the-box/menu/",
    "sg:phone":"+1 253 852 1529",
    "sg:postcode":"98031",
    "sg:province":"WA",
    "sg:tags":[
        "burger",
        "american"
    ],
    "wof:name":"Jack in the Box",
    "wof:placetype":"venue"
},
  "geometry": {"coordinates":[-122.196955,47.416236],"type":"Point"}
}