{
  "type": "Feature",
  "properties": {
    "addr:full":"9936 SW Windmill St Vashon WA 98070",
    "addr:housenumber":"9936",
    "addr:postcode":"98070",
    "addr:street":"Sw Windmill St",
    "iso:country":"US",
    "sg:address":"9936 SW Windmill St",
    "sg:city":"Vashon",
    "sg:classifiers":[
        {
            "category":"Restaurant",
            "type":"Food & Drink"
        }
    ],
    "sg:phone":"+1 206 755 6901",
    "sg:postcode":"98070",
    "sg:province":"WA",
    "sg:tags":[
        "eating"
    ],
    "wof:name":"Jenners",
    "wof:placetype":"venue"
},
  "geometry": {"coordinates":[-122.462231,47.372447],"type":"Point"}
}