{
  "type": "Feature",
  "properties": {
    "iso:country":"US",
    "sg:address":"3310 Roosevelt Dr",
    "sg:city":"Davenport",
    "sg:classifiers":[
        {
            "category":"Real Estate",
            "subcategory":"Developer",
            "type":"Services"
        }
    ],
    "sg:phone":"+1 509 725 8505",
    "sg:postcode":"99122",
    "sg:province":"WA",
    "wof:name":"Seven Bays Inc",
    "wof:placetype":"venue"
},
  "geometry": {"coordinates":[-118.348206,47.840839],"type":"Point"}
}