{
  "type": "Feature",
  "properties": {
    "addr:full":"11324 Kiptree Ln NW Silverdale WA 98383",
    "addr:housenumber":"11324",
    "addr:postcode":"98383",
    "addr:street":"Kiptree Ln Nw",
    "iso:country":"US",
    "sg:address":"11324 Kiptree Ln NW",
    "sg:city":"Silverdale",
    "sg:classifiers":[
        {
            "category":"Retail",
            "subcategory":"Auto Repair",
            "type":"Services"
        }
    ],
    "sg:phone":"+1 360 698 6610",
    "sg:postcode":"98383",
    "sg:province":"WA",
    "sg:tags":[
        "body"
    ],
    "wof:name":"Mathison Daves Rods & Customs",
    "wof:placetype":"venue"
},
  "geometry": {"coordinates":[-122.70087700000001,47.66572],"type":"Point"}
}