{
  "type": "Feature",
  "properties": {
    "addr:full":"760 CC St Woodland WA 98674",
    "addr:postcode":"98674",
    "addr:street":"760 Cc St",
    "iso:country":"US",
    "sg:address":"760 CC St",
    "sg:city":"Woodland",
    "sg:classifiers":[
        {
            "category":"Organizations",
            "subcategory":"Community Association",
            "type":"Services"
        }
    ],
    "sg:phone":"+1 360 225 5748",
    "sg:postcode":"98674",
    "sg:province":"WA",
    "wof:name":"Order of Eastern Star of",
    "wof:placetype":"venue"
},
  "geometry": {"coordinates":[-122.752162,45.906768],"type":"Point"}
}