{
  "type": "Feature",
  "properties": {
    "addr:full":"207 D St SE Auburn WA 98002",
    "addr:housenumber":"207",
    "addr:postcode":"98002",
    "addr:street":"D St Se",
    "iso:country":"US",
    "sg:address":"207 D St SE",
    "sg:city":"Auburn",
    "sg:classifiers":[
        {
            "category":"Professional",
            "type":"Services"
        }
    ],
    "sg:phone":"+1 253 333 8819",
    "sg:postcode":"98002",
    "sg:province":"WA",
    "wof:name":"A Tobin",
    "wof:placetype":"venue"
},
  "geometry": {"coordinates":[-122.224108,47.304247],"type":"Point"}
}