{
  "type": "Feature",
  "properties": {
    "addr:full":"111 W Main St Centralia WA 98531",
    "addr:housenumber":"111",
    "addr:postcode":"98531",
    "addr:street":"W Main St",
    "iso:country":"US",
    "sg:address":"111 W Main St",
    "sg:city":"Centralia",
    "sg:classifiers":[
        {
            "category":"Home & Garden",
            "subcategory":"Garden Supply",
            "type":"Retail Goods"
        },
        {
            "category":"Professional",
            "subcategory":"Management & Consulting",
            "type":"Services"
        }
    ],
    "sg:phone":"+1 360 200 1672",
    "sg:postcode":"98531",
    "sg:province":"WA",
    "sg:tags":[
        "consultant",
        "hydroponics",
        "agricultural",
        "equipment"
    ],
    "sg:website":"http://lewisindoorgardening.com",
    "wof:name":"Indoor Gardening",
    "wof:placetype":"venue"
},
  "geometry": {"coordinates":[-122.954475,46.716284],"type":"Point"}
}