{
  "type": "Feature",
  "properties": {
    "addr:full":"1420 5th Avenue Suite 450 Seattle WA 98101",
    "addr:housenumber":"1420",
    "addr:postcode":"98101",
    "addr:street":"5Th Avenue Suite 450",
    "iso:country":"US",
    "sg:address":"1420 5th Avenue Suite 450",
    "sg:city":"Seattle",
    "sg:classifiers":[
        {
            "category":"Shopping",
            "subcategory":"Department Store",
            "type":"Retail Goods"
        },
        {
            "category":"Shopping Center",
            "type":"Public Place"
        }
    ],
    "sg:phone":"+1 206 624 8800",
    "sg:postcode":"98101",
    "sg:province":"WA",
    "wof:name":"Bentall US",
    "wof:placetype":"venue"
},
  "geometry": {"coordinates":[-122.334846,47.609937],"type":"Point"}
}