{
  "type": "Feature",
  "properties": {
    "addr:full":"9209 SE 57th St Mercer Island WA 98040",
    "addr:housenumber":"9209",
    "addr:postcode":"98040",
    "addr:street":"Se 57Th St",
    "iso:country":"US",
    "sg:address":"9209 SE 57th St",
    "sg:city":"Mercer Island",
    "sg:classifiers":[
        {
            "category":"Organizations",
            "subcategory":"Professional Association",
            "type":"Services"
        }
    ],
    "sg:phone":"+1 206 232 0577",
    "sg:postcode":"98040",
    "sg:province":"WA",
    "sg:tags":[
        "business"
    ],
    "wof:name":"W&W Assococation",
    "wof:placetype":"venue"
},
  "geometry": {"coordinates":[-122.215802,47.551248],"type":"Point"}
}