{
  "type": "Feature",
  "properties": {
    "addr:full":"3703 W Kennewick Ave Kennewick WA 99336",
    "addr:housenumber":"3703",
    "addr:postcode":"99336",
    "addr:street":"W Kennewick Ave",
    "iso:country":"US",
    "sg:address":"3703 W Kennewick Ave",
    "sg:city":"Kennewick",
    "sg:classifiers":[
        {
            "category":"Professional",
            "type":"Services"
        }
    ],
    "sg:phone":"+1 509 374 2453",
    "sg:postcode":"99336",
    "sg:province":"WA",
    "wof:name":"Quarry Inc",
    "wof:placetype":"venue"
},
  "geometry": {"coordinates":[-119.172405,46.209617],"type":"Point"}
}