{
  "type": "Feature",
  "properties": {
    "iso:country":"US",
    "sg:address":"8305 134th Ave NE",
    "sg:city":"Redmond",
    "sg:classifiers":[
        {
            "category":"Professional",
            "subcategory":"Accounting & Tax Preparation",
            "type":"Services"
        }
    ],
    "sg:phone":"+1 425 881 5724",
    "sg:postcode":"98052",
    "sg:province":"WA",
    "wof:name":"Accounting Wizards",
    "wof:placetype":"venue"
},
  "geometry": {"coordinates":[-122.161362,47.677908],"type":"Point"}
}