{
  "type": "Feature",
  "properties": {
    "iso:country":"US",
    "sg:address":"2601 N Pearl St",
    "sg:city":"Tacoma",
    "sg:classifiers":[
        {
            "category":"Food & Beverages",
            "subcategory":"Specialty",
            "type":"Retail Goods"
        }
    ],
    "sg:phone":"+1 253 759 8947",
    "sg:postcode":"98407",
    "sg:province":"WA",
    "wof:name":"Espresso Stop Inc",
    "wof:placetype":"venue"
},
  "geometry": {"coordinates":[-122.515878,47.273001],"type":"Point"}
}