{
  "type": "Feature",
  "properties": {
    "addr:full":"129 N 2nd St Yakima WA 98901",
    "addr:housenumber":"129",
    "addr:postcode":"98901",
    "addr:street":"N 2Nd St",
    "iso:country":"US",
    "sg:address":"129 N 2nd St",
    "sg:city":"Yakima",
    "sg:classifiers":[
        {
            "category":"Government",
            "subcategory":"Office",
            "type":"Public Place"
        }
    ],
    "sg:phone":"+1 509 575 6113",
    "sg:postcode":"98901",
    "sg:province":"WA",
    "sg:tags":[
        "development",
        "customer",
        "councils",
        "commissions",
        "economic",
        "authorities"
    ],
    "sg:website":"http://www.co.yakima.wa.us",
    "wof:name":"Customer Srvce/Utility Billing",
    "wof:placetype":"venue"
},
  "geometry": {"coordinates":[-120.505416,46.6042],"type":"Point"}
}