{
  "type": "Feature",
  "properties": {
    "addr:full":"317 N 78th St Seattle WA 98103",
    "addr:housenumber":"317",
    "addr:postcode":"98103",
    "addr:street":"N 78Th St",
    "iso:country":"US",
    "sg:address":"317 N 78th St",
    "sg:city":"Seattle",
    "sg:classifiers":[
        {
            "category":"Professional",
            "subcategory":"Business Services",
            "type":"Services"
        }
    ],
    "sg:phone":"+1 206 675 0126",
    "sg:postcode":"98103",
    "sg:province":"WA",
    "wof:name":"Toraso Enterprises LLC",
    "wof:placetype":"venue"
},
  "geometry": {"coordinates":[-122.352582,47.685413],"type":"Point"}
}