{
  "type": "Feature",
  "properties": {
    "addr:full":"10701 Evergreen Way Everett WA 98204",
    "addr:housenumber":"10701",
    "addr:postcode":"98204",
    "addr:street":"Evergreen Way",
    "iso:country":"US",
    "sg:address":"10701 Evergreen Way",
    "sg:city":"Everett",
    "sg:classifiers":[
        {
            "category":"Retail",
            "subcategory":"Auto Repair",
            "type":"Services"
        }
    ],
    "sg:phone":"+1 425 355 3002",
    "sg:postcode":"98204",
    "sg:province":"WA",
    "sg:tags":[
        "body",
        "automobile",
        "painting"
    ],
    "wof:name":"ARA Collision Everett",
    "wof:placetype":"venue"
},
  "geometry": {"coordinates":[-122.24557299999999,47.90313],"type":"Point"}
}