{
  "type": "Feature",
  "properties": {
    "addr:full":"1227 Nevitt Rd Burlington WA 98233",
    "addr:housenumber":"1227",
    "addr:postcode":"98233",
    "addr:street":"Nevitt Rd",
    "iso:country":"US",
    "sg:address":"1227 Nevitt Rd",
    "sg:city":"Burlington",
    "sg:classifiers":[
        {
            "category":"Social Services",
            "subcategory":"Child Care",
            "type":"Services"
        }
    ],
    "sg:phone":"+1 360 757 6883",
    "sg:postcode":"98233",
    "sg:province":"WA",
    "sg:tags":[
        "day"
    ],
    "wof:name":"Kathy Deanne Barnwell",
    "wof:placetype":"venue"
},
  "geometry": {"coordinates":[-122.34419699999999,48.468719],"type":"Point"}
}