{
  "type": "Feature",
  "properties": {
    "addr:full":"2100 1st Ave Seattle WA 98121",
    "addr:housenumber":"2100",
    "addr:postcode":"98121",
    "addr:street":"1St Ave",
    "iso:country":"US",
    "sg:address":"2100 1st Ave",
    "sg:city":"Seattle",
    "sg:classifiers":[
        {
            "category":"Shopping",
            "subcategory":"Clothing, Apparel, & Fashions",
            "type":"Retail Goods"
        },
        {
            "category":"Shopping",
            "type":"Retail Goods"
        },
        {
            "category":"Recreation",
            "type":"Entertainment"
        }
    ],
    "sg:phone":"+1 206 622 9700",
    "sg:postcode":"98121",
    "sg:province":"WA",
    "sg:tags":[
        "life",
        "clothing",
        "men's",
        "sportswear",
        "women's",
        "active",
        "store",
        "apparel",
        "racing",
        "merchandise"
    ],
    "sg:website":"http://Patagonia.com",
    "wof:name":"Patagonia",
    "wof:placetype":"venue"
},
  "geometry": {"coordinates":[-122.344002,47.612099],"type":"Point"}
}