{
  "type": "Feature",
  "properties": {
    "addr:full":"24024 84th Ave W Edmonds WA 98026",
    "addr:housenumber":"24024",
    "addr:postcode":"98026",
    "addr:street":"84Th Ave W",
    "iso:country":"US",
    "sg:address":"24024 84th Ave W",
    "sg:city":"Edmonds",
    "sg:classifiers":[
        {
            "category":"Health Services",
            "subcategory":"Chiropractor",
            "type":"Services"
        }
    ],
    "sg:phone":"+1 425 776 4224",
    "sg:postcode":"98026",
    "sg:province":"WA",
    "sg:tags":[
        "medicine",
        "alternative",
        "practitioner"
    ],
    "wof:name":"Bowers Family Chiropractic",
    "wof:placetype":"venue"
},
  "geometry": {"coordinates":[-122.346181,47.780768],"type":"Point"}
}