{
  "type": "Feature",
  "properties": {
    "addr:full":"211 5th St SE Puyallup WA 98372",
    "addr:housenumber":"211",
    "addr:postcode":"98372",
    "addr:street":"5Th St Se",
    "iso:country":"US",
    "sg:address":"211 5th St SE",
    "sg:city":"Puyallup",
    "sg:classifiers":[
        {
            "category":"Home & Garden",
            "subcategory":"Building Materials",
            "type":"Retail Goods"
        }
    ],
    "sg:phone":"+1 253 848 6503",
    "sg:postcode":"98372",
    "sg:province":"WA",
    "wof:name":"Depot Art Glass",
    "wof:placetype":"venue"
},
  "geometry": {"coordinates":[-122.28808600000001,47.191162],"type":"Point"}
}