{
  "type": "Feature",
  "properties": {
    "addr:full":"6505 Perimeter Rd S Seattle WA 98108",
    "addr:housenumber":"6505",
    "addr:postcode":"98108",
    "addr:street":"Perimeter Rd S",
    "iso:country":"US",
    "sg:address":"6505 Perimeter Rd S",
    "sg:city":"Seattle",
    "sg:classifiers":[
        {
            "category":"Building & Trades",
            "subcategory":"Equipment Rental",
            "type":"Services"
        }
    ],
    "sg:phone":"+1 206 764 3861",
    "sg:postcode":"98108",
    "sg:province":"WA",
    "sg:tags":[
        "yard",
        "leasing",
        "store"
    ],
    "wof:name":"Valkyrie Aviation",
    "wof:placetype":"venue"
},
  "geometry": {"coordinates":[-122.31379800000001,47.545886],"type":"Point"}
}