{
  "type": "Feature",
  "properties": {
    "addr:full":"2800 156th Ave SE Bellevue WA 98007",
    "addr:housenumber":"2800",
    "addr:postcode":"98007",
    "addr:street":"156Th Ave Se",
    "iso:country":"US",
    "sg:address":"2800 156th Ave SE",
    "sg:city":"Bellevue",
    "sg:classifiers":[
        {
            "category":"Professional",
            "subcategory":"Computer Services",
            "type":"Services"
        }
    ],
    "sg:phone":"+1 206 284 1635",
    "sg:postcode":"98007",
    "sg:province":"WA",
    "sg:website":"www.cyberstreams.com",
    "wof:name":"Cyber Streams",
    "wof:placetype":"venue"
},
  "geometry": {"coordinates":[-122.134125,47.58215],"type":"Point"}
}