{
  "type": "Feature",
  "properties": {
    "addr:full":"223 W Kennaston Ave Montesano WA 98563",
    "addr:housenumber":"223",
    "addr:postcode":"98563",
    "addr:street":"W Kennaston Ave Montesano",
    "iso:country":"US",
    "sg:address":"223 W Kennaston Ave",
    "sg:city":"Montesano",
    "sg:classifiers":[
        {
            "category":"Social Services",
            "subcategory":"Job Training",
            "type":"Services"
        }
    ],
    "sg:phone":"+1 360 249 2683",
    "sg:postcode":"98563",
    "sg:province":"WA",
    "wof:name":"Eye Corps",
    "wof:placetype":"venue"
},
  "geometry": {"coordinates":[-123.60315300000001,46.986955],"type":"Point"}
}