{
  "type": "Feature",
  "properties": {
    "addr:full":"317 E Washington St Sequim WA 98382",
    "addr:housenumber":"317",
    "addr:postcode":"98382",
    "addr:street":"E Washington St",
    "iso:country":"US",
    "sg:address":"317 E Washington St",
    "sg:city":"Sequim",
    "sg:classifiers":[
        {
            "category":"Real Estate",
            "subcategory":"Real Estate Agent",
            "type":"Services"
        }
    ],
    "sg:phone":"+1 360 683 4160",
    "sg:postcode":"98382",
    "sg:province":"WA",
    "wof:name":"Peter Black Real Estate",
    "wof:placetype":"venue"
},
  "geometry": {"coordinates":[-123.099001,48.079567],"type":"Point"}
}