{
  "type": "Feature",
  "properties": {
    "addr:full":"625 Auburn Way S Auburn WA 98002",
    "addr:housenumber":"625",
    "addr:postcode":"98002",
    "addr:street":"Auburn Way S",
    "iso:country":"US",
    "sg:address":"625 Auburn Way S",
    "sg:city":"Auburn",
    "sg:classifiers":[
        {
            "category":"Food & Beverages",
            "subcategory":"Meat & Fish",
            "type":"Retail Goods"
        }
    ],
    "sg:phone":"+1 253 833 8871",
    "sg:postcode":"98002",
    "sg:province":"WA",
    "wof:name":"Duane's Custom Meats",
    "wof:placetype":"venue"
},
  "geometry": {"coordinates":[-122.22543,47.301729],"type":"Point"}
}