{
  "type": "Feature",
  "properties": {
    "iso:country":"US",
    "sg:address":"24310 2nd Pl W",
    "sg:city":"Bothell",
    "sg:classifiers":[
        {
            "category":"Manufacturing",
            "subcategory":"Tools & Machinery",
            "type":"Manufacturing & Wholesale Goods"
        }
    ],
    "sg:phone":"+1 425 483 6397",
    "sg:postcode":"98021",
    "sg:province":"WA",
    "sg:tags":[
        "industrial",
        "mfg"
    ],
    "wof:name":"Papa Bairs Stump Grinding",
    "wof:placetype":"venue"
},
  "geometry": {"coordinates":[-122.23642700000001,47.77871],"type":"Point"}
}