{
  "type": "Feature",
  "properties": {
    "addr:full":"102 S Stevens St Seattle WA 98144",
    "addr:housenumber":"102",
    "addr:postcode":"98144",
    "addr:street":"S Stevens St",
    "iso:country":"US",
    "sg:address":"102 S Stevens St",
    "sg:city":"Seattle",
    "sg:classifiers":[
        {
            "category":"Education",
            "subcategory":"Special Training",
            "type":"Public Place"
        },
        {
            "category":"Education",
            "subcategory":"University",
            "type":"Public Place"
        }
    ],
    "sg:phone":"+1 206 543 0970",
    "sg:postcode":"98144",
    "sg:province":"WA",
    "sg:tags":[
        "college",
        "school",
        "instruction",
        "art"
    ],
    "sg:website":"http://www.washington.edu",
    "wof:name":"School Of Art",
    "wof:placetype":"venue"
},
  "geometry": {"coordinates":[-122.29744700000001,47.576729],"type":"Point"}
}