{
  "type": "Feature",
  "properties": {
    "addr:full":"12217 W Sunridge Dr Nine Mile Falls WA 99026",
    "addr:housenumber":"12217",
    "addr:postcode":"99026",
    "addr:street":"W Sunridge Dr",
    "iso:country":"US",
    "sg:address":"12217 W Sunridge Dr",
    "sg:city":"Nine Mile Falls",
    "sg:classifiers":[
        {
            "category":"Professional",
            "type":"Services"
        }
    ],
    "sg:phone":"+1 509 468 1502",
    "sg:postcode":"99026",
    "sg:province":"WA",
    "wof:name":"Personalized Products 4u",
    "wof:placetype":"venue"
},
  "geometry": {"coordinates":[-117.58846800000001,47.803526],"type":"Point"}
}