{
  "type": "Feature",
  "properties": {
    "iso:country":"US",
    "sg:address":"2704 I St NE",
    "sg:city":"Auburn",
    "sg:classifiers":[
        {
            "category":"Health Services",
            "subcategory":"Clinic",
            "type":"Services"
        }
    ],
    "sg:phone":"+1 253 833 7444",
    "sg:postcode":"98002",
    "sg:province":"WA",
    "sg:tags":[
        "specialty",
        "outpatient"
    ],
    "wof:name":"Valley Cties Counseling Cnsltn",
    "wof:placetype":"venue"
},
  "geometry": {"coordinates":[-122.219418,47.330271],"type":"Point"}
}