{
  "type": "Feature",
  "properties": {
    "addr:full":"1206 Joy Ave NE Olympia WA 98506",
    "addr:housenumber":"1206",
    "addr:postcode":"98506",
    "addr:street":"Joy Ave Ne",
    "iso:country":"US",
    "sg:address":"1206 Joy Ave NE",
    "sg:city":"Olympia",
    "sg:classifiers":[
        {
            "category":"Recreation",
            "type":"Entertainment"
        }
    ],
    "sg:phone":"+1 360 357 6768",
    "sg:postcode":"98506",
    "sg:province":"WA",
    "wof:name":"Porter Indexing",
    "wof:placetype":"venue"
},
  "geometry": {"coordinates":[-122.887046,47.059083],"type":"Point"}
}