{
  "type": "Feature",
  "properties": {
    "addr:full":"919 124th Ave NE Ste 206 Bellevue WA 98005",
    "addr:housenumber":"919",
    "addr:postcode":"98005",
    "addr:street":"124Th Ave Ne Ste 206",
    "iso:country":"US",
    "sg:address":"919 124th Ave NE Ste 206",
    "sg:city":"Bellevue",
    "sg:classifiers":[
        {
            "category":"Professional",
            "subcategory":"Accounting & Tax Preparation",
            "type":"Services"
        }
    ],
    "sg:phone":"+1 425 462 5630",
    "sg:postcode":"98005",
    "sg:province":"WA",
    "sg:tags":[
        "accountant"
    ],
    "wof:name":"Decaro & Roberts Inc PS",
    "wof:placetype":"venue"
},
  "geometry": {"coordinates":[-122.175003,47.618401],"type":"Point"}
}