{
  "type": "Feature",
  "properties": {
    "addr:full":"4520 Lacey Blvd SE Lacey WA 98503",
    "addr:housenumber":"4520",
    "addr:postcode":"98503",
    "addr:street":"Lacey Blvd Se",
    "iso:country":"US",
    "sg:address":"4520 Lacey Blvd SE",
    "sg:city":"Lacey",
    "sg:classifiers":[
        {
            "category":"Personal",
            "subcategory":"Massage",
            "type":"Services"
        },
        {
            "category":"Personal",
            "subcategory":"Beauty Salon",
            "type":"Services"
        },
        {
            "category":"Personal",
            "subcategory":"Day Spa",
            "type":"Services"
        }
    ],
    "sg:phone":"+1 360 923 9100",
    "sg:postcode":"98503",
    "sg:province":"WA",
    "wof:name":"Ambiance",
    "wof:placetype":"venue"
},
  "geometry": {"coordinates":[-122.825874,47.036547],"type":"Point"}
}