{
  "type": "Feature",
  "properties": {
    "addr:full":"9753 Nibbelink Rd Peshastin WA 98821",
    "addr:housenumber":"9753",
    "addr:postcode":"98821",
    "addr:street":"Nibbelink Rd",
    "iso:country":"US",
    "sg:address":"9753 Nibbelink Rd",
    "sg:city":"Peshastin",
    "sg:classifiers":[
        {
            "category":"Farming",
            "subcategory":"Orchard",
            "type":"Manufacturing & Wholesale Goods"
        }
    ],
    "sg:phone":"+1 509 548 7924",
    "sg:postcode":"98821",
    "sg:province":"WA",
    "sg:tags":[
        "fruit",
        "tree"
    ],
    "wof:name":"SMC Orchards Inc",
    "wof:placetype":"venue"
},
  "geometry": {"coordinates":[-120.614317,47.594443],"type":"Point"}
}