{
  "type": "Feature",
  "properties": {
    "addr:full":"1515 Dexter Ave N Seattle WA 98109",
    "addr:housenumber":"1515",
    "addr:postcode":"98109",
    "addr:street":"Dexter Ave N",
    "iso:country":"US",
    "sg:address":"1515 Dexter Ave N",
    "sg:city":"Seattle",
    "sg:classifiers":[
        {
            "category":"Social Services",
            "type":"Services"
        }
    ],
    "sg:phone":"+1 206 461 3210",
    "sg:postcode":"98109",
    "sg:province":"WA",
    "wof:name":"Crisis Clinic",
    "wof:placetype":"venue"
},
  "geometry": {"coordinates":[-122.34235700000001,47.632367],"type":"Point"}
}