{
  "type": "Feature",
  "properties": {
    "iso:country":"US",
    "sg:address":"6848 Beach Dr E",
    "sg:city":"Port Orchard",
    "sg:classifiers":[
        {
            "category":"Shopping",
            "subcategory":"Clothing, Apparel, & Fashions",
            "type":"Retail Goods"
        }
    ],
    "sg:phone":"+1 360 871 8042",
    "sg:postcode":"98366",
    "sg:province":"WA",
    "wof:name":"Beach Drive Piano Instruction",
    "wof:placetype":"venue"
},
  "geometry": {"coordinates":[-122.561851,47.578634],"type":"Point"}
}