{
  "type": "Feature",
  "properties": {
    "addr:full":"28908 48th Ave S Roy WA 98580",
    "addr:housenumber":"28908",
    "addr:postcode":"98580",
    "addr:street":"48Th Ave S Roy",
    "iso:country":"US",
    "sg:address":"28908 48th Ave S",
    "sg:city":"Roy",
    "sg:classifiers":[
        {
            "category":"Farming",
            "subcategory":"Farm & Veterinary Services",
            "type":"Manufacturing & Wholesale Goods"
        }
    ],
    "sg:phone":"+1 253 843 2417",
    "sg:postcode":"98580",
    "sg:province":"WA",
    "sg:tags":[
        "livestock"
    ],
    "wof:name":"Lawrence Hawn",
    "wof:placetype":"venue"
},
  "geometry": {"coordinates":[-122.494697,46.995269],"type":"Point"}
}