{
  "type": "Feature",
  "properties": {
    "addr:full":"796 Wine Country Rd Prosser WA 99350",
    "addr:housenumber":"796",
    "addr:postcode":"99350",
    "addr:street":"Wine Country Rd",
    "iso:country":"US",
    "sg:address":"796 Wine Country Rd",
    "sg:city":"Prosser",
    "sg:classifiers":[
        {
            "category":"Restaurant",
            "type":"Food & Drink"
        }
    ],
    "sg:phone":"+1 509 788 0422",
    "sg:postcode":"99350",
    "sg:province":"WA",
    "sg:tags":[
        "eating"
    ],
    "wof:name":"Tummy Treats Candy & Craft",
    "wof:placetype":"venue"
},
  "geometry": {"coordinates":[-119.80000099999999,46.225179],"type":"Point"}
}