{
  "type": "Feature",
  "properties": {
    "addr:full":"13453 Marihugh Rd Mount Vernon WA 98273",
    "addr:housenumber":"13453",
    "addr:postcode":"98273",
    "addr:street":"Marihugh Rd",
    "iso:country":"US",
    "sg:address":"13453 Marihugh Rd",
    "sg:city":"Mount Vernon",
    "sg:classifiers":[
        {
            "category":"Retail",
            "subcategory":"Repair Shop",
            "type":"Services"
        }
    ],
    "sg:phone":"+1 360 757 7316",
    "sg:postcode":"98273",
    "sg:province":"WA",
    "sg:tags":[
        "electrical"
    ],
    "wof:name":"North Sound Business Systems",
    "wof:placetype":"venue"
},
  "geometry": {"coordinates":[-122.456267,48.479507],"type":"Point"}
}