{
  "type": "Feature",
  "properties": {
    "addr:full":"4416 Fremont Ave N Seattle WA 98103",
    "addr:housenumber":"4416",
    "addr:postcode":"98103",
    "addr:street":"Fremont Ave N",
    "iso:country":"US",
    "sg:address":"4416 Fremont Ave N",
    "sg:city":"Seattle",
    "sg:classifiers":[
        {
            "category":"Food & Beverages",
            "subcategory":"Groceries & Convenience Stores",
            "type":"Retail Goods"
        }
    ],
    "sg:phone":"+1 206 632 8958",
    "sg:postcode":"98103",
    "sg:province":"WA",
    "wof:name":"Marketime Foods",
    "wof:placetype":"venue"
},
  "geometry": {"coordinates":[-122.350047,47.660373],"type":"Point"}
}