{
  "type": "Feature",
  "properties": {
    "addr:full":"9124 View Ave NW Seattle WA 98117",
    "addr:housenumber":"9124",
    "addr:postcode":"98117",
    "addr:street":"View Ave Nw",
    "iso:country":"US",
    "sg:address":"9124 View Ave NW",
    "sg:city":"Seattle",
    "sg:classifiers":[
        {
            "category":"Manufacturing",
            "subcategory":"Lumber",
            "type":"Manufacturing & Wholesale Goods"
        }
    ],
    "sg:phone":"+1 206 783 0809",
    "sg:postcode":"98117",
    "sg:province":"WA",
    "sg:tags":[
        "logging"
    ],
    "sg:website":"http://www.piercefamilylaw.com",
    "wof:name":"Pierce Family",
    "wof:placetype":"venue"
},
  "geometry": {"coordinates":[-122.401482,47.695727],"type":"Point"}
}