{
  "type": "Feature",
  "properties": {
    "addr:full":"7617 160th St SE Snohomish WA 98296",
    "addr:housenumber":"7617",
    "addr:postcode":"98296",
    "addr:street":"160Th St Se",
    "iso:country":"US",
    "sg:address":"7617 160th St SE",
    "sg:city":"Snohomish",
    "sg:classifiers":[
        {
            "category":"Retail",
            "subcategory":"Auto Repair",
            "type":"Services"
        }
    ],
    "sg:phone":"+1 425 487 0763",
    "sg:postcode":"98296",
    "sg:province":"WA",
    "sg:tags":[
        "body",
        "automobile",
        "painting"
    ],
    "wof:name":"Kimbridge Enterprises Inc",
    "wof:placetype":"venue"
},
  "geometry": {"coordinates":[-122.13294,47.852345],"type":"Point"}
}