{
  "type": "Feature",
  "properties": {
    "iso:country":"US",
    "sg:address":"15239 NE 90th St",
    "sg:city":"Redmond",
    "sg:classifiers":[
        {
            "category":"Wholesale",
            "subcategory":"Electrical",
            "type":"Manufacturing & Wholesale Goods"
        }
    ],
    "sg:phone":"+1 425 881 9064",
    "sg:postcode":"98052",
    "sg:province":"WA",
    "sg:tags":[
        "electronic"
    ],
    "wof:name":"Photoloom Corporation",
    "wof:placetype":"venue"
},
  "geometry": {"coordinates":[-122.137297,47.682158],"type":"Point"}
}