{
  "type": "Feature",
  "properties": {
    "addr:full":"17811 E Alki Ave Greenacres WA 99016",
    "addr:housenumber":"17811",
    "addr:postcode":"99016",
    "addr:street":"E Alki Ave",
    "iso:country":"US",
    "sg:address":"17811 E Alki Ave",
    "sg:city":"Greenacres",
    "sg:classifiers":[
        {
            "category":"Building & Trades",
            "subcategory":"Construction",
            "type":"Services"
        }
    ],
    "sg:phone":"+1 509 701 5706",
    "sg:postcode":"99016",
    "sg:province":"WA",
    "sg:tags":[
        "carpentry",
        "contractor"
    ],
    "wof:name":"Garys Door Service",
    "wof:placetype":"venue"
},
  "geometry": {"coordinates":[-117.166845,47.662782],"type":"Point"}
}