{
  "type": "Feature",
  "properties": {
    "addr:full":"1400 N 30th St Mount Vernon WA 98273",
    "addr:housenumber":"1400",
    "addr:postcode":"98273",
    "addr:street":"N 30Th St",
    "iso:country":"US",
    "sg:address":"1400 N 30th St",
    "sg:city":"Mount Vernon",
    "sg:classifiers":[
        {
            "category":"Home & Garden",
            "subcategory":"Hardware",
            "type":"Retail Goods"
        }
    ],
    "sg:phone":"+1 360 848 7995",
    "sg:postcode":"98273",
    "sg:province":"WA",
    "wof:name":"High Value Hunter",
    "wof:placetype":"venue"
},
  "geometry": {"coordinates":[-122.302584,48.432469],"type":"Point"}
}