{
  "type": "Feature",
  "properties": {
    "addr:full":"8183 Lyman Ave Lyman WA 98284",
    "addr:housenumber":"8183",
    "addr:postcode":"98284",
    "addr:street":"Lyman Ave",
    "iso:country":"US",
    "sg:address":"8183 Lyman Ave",
    "sg:city":"Lyman",
    "sg:classifiers":[
        {
            "category":"Education",
            "subcategory":"School",
            "type":"Public Place"
        }
    ],
    "sg:phone":"+1 360 855 3535",
    "sg:postcode":"98284",
    "sg:province":"WA",
    "wof:name":"Lyman Elementary School",
    "wof:placetype":"venue"
},
  "geometry": {"coordinates":[-122.07029199999999,48.527704],"type":"Point"}
}