{
  "type": "Feature",
  "properties": {
    "addr:full":"1700 7th Ave Seattle WA 98101",
    "addr:housenumber":"1700",
    "addr:postcode":"98101",
    "addr:street":"7Th Ave",
    "iso:country":"US",
    "sg:address":"1700 7th Ave",
    "sg:city":"Seattle",
    "sg:classifiers":[
        {
            "category":"Professional",
            "subcategory":"Lawyer & Legal Services",
            "type":"Services"
        }
    ],
    "sg:phone":"+1 206 667 0235",
    "sg:postcode":"98101",
    "sg:province":"WA",
    "sg:tags":[
        "attorney"
    ],
    "wof:name":"Michael D Daudt",
    "wof:placetype":"venue"
},
  "geometry": {"coordinates":[-122.336156,47.614286],"type":"Point"}
}