{
  "type": "Feature",
  "properties": {
    "addr:full":"2210 Riverside Dr Mount Vernon WA 98273",
    "addr:housenumber":"2210",
    "addr:postcode":"98273",
    "addr:street":"Riverside Dr",
    "iso:country":"US",
    "sg:address":"2210 Riverside Dr",
    "sg:city":"Mount Vernon",
    "sg:classifiers":[
        {
            "category":"Banks & Credit Unions",
            "subcategory":"Financial Services",
            "type":"Services"
        }
    ],
    "sg:phone":"+1 360 848 7333",
    "sg:postcode":"98273",
    "sg:province":"WA",
    "sg:tags":[
        "broker",
        "mortgage"
    ],
    "sg:website":"www.countrywide.com",
    "wof:name":"Countrywide Home Loans",
    "wof:placetype":"venue"
},
  "geometry": {"coordinates":[-122.334943,48.440476],"type":"Point"}
}