{
  "type": "Feature",
  "properties": {
    "addr:full":"7452 Woodlawn Ave NE Seattle WA 98115",
    "addr:housenumber":"7452",
    "addr:postcode":"98115",
    "addr:street":"Woodlawn Ave Ne",
    "iso:country":"US",
    "sg:address":"7452 Woodlawn Ave NE",
    "sg:city":"Seattle",
    "sg:classifiers":[
        {
            "category":"Professional",
            "type":"Services"
        }
    ],
    "sg:phone":"+1 206 527 8456",
    "sg:postcode":"98115",
    "sg:province":"WA",
    "wof:name":"Erik Harada",
    "wof:placetype":"venue"
},
  "geometry": {"coordinates":[-122.328152,47.683225],"type":"Point"}
}