{
  "type": "Feature",
  "properties": {
    "addr:full":"3321 E Trent Ave Spokane WA 99212",
    "addr:housenumber":"3321",
    "addr:postcode":"99212",
    "addr:street":"E Trent Ave",
    "iso:country":"US",
    "sg:address":"3321 E Trent Ave",
    "sg:city":"Spokane",
    "sg:classifiers":[
        {
            "category":"Building & Trades",
            "subcategory":"Construction",
            "type":"Services"
        }
    ],
    "sg:phone":"+1 509 325 2572",
    "sg:postcode":"99212",
    "sg:province":"WA",
    "sg:tags":[
        "home",
        "improvement"
    ],
    "wof:name":"Greater American Construction",
    "wof:placetype":"venue"
},
  "geometry": {"coordinates":[-117.360604,47.667972],"type":"Point"}
}