{
  "type": "Feature",
  "properties": {
    "addr:full":"940 N 98th St Seattle WA 98103",
    "addr:housenumber":"940",
    "addr:postcode":"98103",
    "addr:street":"N 98Th St",
    "iso:country":"US",
    "sg:address":"940 N 98th St",
    "sg:city":"Seattle",
    "sg:classifiers":[
        {
            "category":"Real Estate",
            "subcategory":"Real Estate Operator",
            "type":"Services"
        }
    ],
    "sg:phone":"+1 206 527 7616",
    "sg:postcode":"98103",
    "sg:province":"WA",
    "sg:tags":[
        "building",
        "apartment"
    ],
    "wof:name":"Michelle Apartments",
    "wof:placetype":"venue"
},
  "geometry": {"coordinates":[-122.34500800000001,47.7006],"type":"Point"}
}