{
  "type": "Feature",
  "properties": {
    "addr:full":"1618 12th Ave SE Olympia WA 98501",
    "addr:housenumber":"1618",
    "addr:postcode":"98501",
    "addr:street":"12Th Ave Se",
    "iso:country":"US",
    "sg:address":"1618 12th Ave SE",
    "sg:city":"Olympia",
    "sg:classifiers":[
        {
            "category":"Building & Trades",
            "subcategory":"Construction",
            "type":"Services"
        }
    ],
    "sg:phone":"+1 360 352 3480",
    "sg:postcode":"98501",
    "sg:province":"WA",
    "sg:tags":[
        "installer",
        "drapery"
    ],
    "wof:name":"Installation Unique",
    "wof:placetype":"venue"
},
  "geometry": {"coordinates":[-122.879293,47.038424],"type":"Point"}
}