{
  "type": "Feature",
  "properties": {
    "addr:full":"5611 University Way NE Seattle WA 98105",
    "addr:housenumber":"5611",
    "addr:postcode":"98105",
    "addr:street":"University Way Ne",
    "iso:country":"US",
    "sg:address":"5611 University Way NE",
    "sg:city":"Seattle",
    "sg:classifiers":[
        {
            "category":"Personal",
            "subcategory":"Beauty Salon",
            "type":"Services"
        }
    ],
    "sg:phone":"+1 206 985 1010",
    "sg:postcode":"98105",
    "sg:province":"WA",
    "sg:tags":[
        "hair",
        "makeup",
        "artist"
    ],
    "sg:website":"www.tenpachi.com",
    "wof:name":"Ten Pachi Modern Salon",
    "wof:placetype":"venue"
},
  "geometry": {"coordinates":[-122.313025,47.669949],"type":"Point"}
}