{
  "type": "Feature",
  "properties": {
    "addr:full":"5312 111th St SW Lakewood WA 98499",
    "addr:housenumber":"5312",
    "addr:postcode":"98499",
    "addr:street":"111Th St Sw",
    "iso:country":"US",
    "sg:address":"5312 111th St SW",
    "sg:city":"Lakewood",
    "sg:classifiers":[
        {
            "category":"Shopping",
            "subcategory":"Bicycles & Sporting Goods",
            "type":"Retail Goods"
        }
    ],
    "sg:phone":"+1 253 589 4796",
    "sg:postcode":"98499",
    "sg:province":"WA",
    "wof:name":"Just Daves",
    "wof:placetype":"venue"
},
  "geometry": {"coordinates":[-122.505623,47.156352],"type":"Point"}
}