{
  "type": "Feature",
  "properties": {
    "iso:country":"US",
    "sg:address":"1225 Griffin Ave",
    "sg:city":"Enumclaw",
    "sg:classifiers":[
        {
            "category":"Restaurant",
            "type":"Food & Drink"
        }
    ],
    "sg:phone":"+1 360 825 6528",
    "sg:postcode":"98022",
    "sg:province":"WA",
    "sg:tags":[
        "drinking",
        "eating"
    ],
    "wof:name":"Oriental Gardens",
    "wof:placetype":"venue"
},
  "geometry": {"coordinates":[-121.989857,47.20375],"type":"Point"}
}