{
  "type": "Feature",
  "properties": {
    "iso:country":"US",
    "sg:address":"5 Front St",
    "sg:city":"St John",
    "sg:classifiers":[
        {
            "category":"Insurance",
            "subcategory":"Insurance Agent",
            "type":"Services"
        }
    ],
    "sg:phone":"+1 509 648 3670",
    "sg:postcode":"99171",
    "sg:province":"WA",
    "wof:name":"Associated Independent Agency",
    "wof:placetype":"venue"
},
  "geometry": {"coordinates":[-117.582148,47.091765],"type":"Point"}
}