{
  "type": "Feature",
  "properties": {
    "addr:full":"839 Cascade St Wenatchee WA 98801",
    "addr:housenumber":"839",
    "addr:postcode":"98801",
    "addr:street":"Cascade St",
    "iso:country":"US",
    "sg:address":"839 Cascade St",
    "sg:city":"Wenatchee",
    "sg:classifiers":[
        {
            "category":"Social Services",
            "type":"Services"
        }
    ],
    "sg:phone":"+1 509 665 8313",
    "sg:postcode":"98801",
    "sg:province":"WA",
    "wof:name":"El Tapatio IV",
    "wof:placetype":"venue"
},
  "geometry": {"coordinates":[-120.311143,47.411757],"type":"Point"}
}