{
  "type": "Feature",
  "properties": {
    "addr:full":"9951 US Hwy 12 Naches WA 98937",
    "addr:housenumber":"9951",
    "addr:postcode":"98937",
    "addr:street":"Us Hwy 12",
    "iso:country":"US",
    "sg:address":"9951 US Hwy 12",
    "sg:city":"Naches",
    "sg:classifiers":[
        {
            "category":"Food & Beverages",
            "subcategory":"Groceries & Convenience Stores",
            "type":"Retail Goods"
        }
    ],
    "sg:phone":"+1 509 653 2268",
    "sg:postcode":"98937",
    "sg:province":"WA",
    "wof:name":"Slims Market",
    "wof:placetype":"venue"
},
  "geometry": {"coordinates":[-120.699026,46.727954],"type":"Point"}
}