{
  "type": "Feature",
  "properties": {
    "iso:country":"US",
    "sg:address":"833 SW Sunset Blvd",
    "sg:city":"Renton",
    "sg:classifiers":[
        {
            "category":"Manufacturing",
            "subcategory":"Electronics",
            "type":"Manufacturing & Wholesale Goods"
        }
    ],
    "sg:phone":"+1 425 271 7486",
    "sg:postcode":"98055",
    "sg:province":"WA",
    "sg:tags":[
        "household",
        "stereo",
        "mfg"
    ],
    "wof:name":"First Sound Inc",
    "wof:placetype":"venue"
},
  "geometry": {"coordinates":[-122.228188,47.47765],"type":"Point"}
}