{
  "type": "Feature",
  "properties": {
    "addr:full":"17310 140th Ave SE Renton WA 98058",
    "addr:housenumber":"17310",
    "addr:postcode":"98058",
    "addr:street":"140Th Ave Se",
    "iso:country":"US",
    "sg:address":"17310 140th Ave SE",
    "sg:city":"Renton",
    "sg:classifiers":[
        {
            "category":"Food & Beverages",
            "subcategory":"Groceries & Convenience Stores",
            "type":"Retail Goods"
        },
        {
            "category":"Food & Beverages",
            "subcategory":"Liquor & Beverages",
            "type":"Retail Goods"
        }
    ],
    "sg:phone":"+1 425 228 8040",
    "sg:postcode":"98058",
    "sg:province":"WA",
    "sg:tags":[
        "re",
        "alcoholic"
    ],
    "wof:name":"Beverage Mart",
    "wof:placetype":"venue"
},
  "geometry": {"coordinates":[-122.15400200000001,47.448842],"type":"Point"}
}