{
  "type": "Feature",
  "properties": {
    "addr:full":"13719 SE 18th St Vancouver WA 98683",
    "addr:housenumber":"13719",
    "addr:postcode":"98683",
    "addr:street":"Se 18Th St",
    "iso:country":"US",
    "sg:address":"13719 SE 18th St",
    "sg:city":"Vancouver",
    "sg:classifiers":[
        {
            "category":"Real Estate",
            "subcategory":"Real Estate Operator",
            "type":"Services"
        }
    ],
    "sg:phone":"+1 360 254 1985",
    "sg:postcode":"98683",
    "sg:province":"WA",
    "sg:tags":[
        "apartment"
    ],
    "wof:name":"Aspenridge Apartments",
    "wof:placetype":"venue"
},
  "geometry": {"coordinates":[-122.531998,45.6082],"type":"Point"}
}