{
  "type": "Feature",
  "properties": {
    "iso:country":"US",
    "sg:address":"116 Elbe Rd",
    "sg:city":"Elbe",
    "sg:classifiers":[
        {
            "category":"Shopping",
            "subcategory":"Gifts & Souvenirs",
            "type":"Retail Goods"
        }
    ],
    "sg:phone":"+1 360 492 3530",
    "sg:postcode":"98330",
    "sg:province":"WA",
    "wof:name":"Foothilljo",
    "wof:placetype":"venue"
},
  "geometry": {"coordinates":[-122.192565,46.755277],"type":"Point"}
}