{
  "type": "Feature",
  "properties": {
    "addr:full":"4113 Eastern Ave N Seattle WA 98103",
    "addr:housenumber":"4113",
    "addr:postcode":"98103",
    "addr:street":"Eastern Ave N",
    "iso:country":"US",
    "sg:address":"4113 Eastern Ave N",
    "sg:city":"Seattle",
    "sg:classifiers":[
        {
            "category":"Health Services",
            "subcategory":"Health Practitioner",
            "type":"Services"
        }
    ],
    "sg:phone":"+1 206 634 3643",
    "sg:postcode":"98103",
    "sg:province":"WA",
    "wof:name":"Deborah P Chase Speech-L",
    "wof:placetype":"venue"
},
  "geometry": {"coordinates":[-122.329095,47.657784],"type":"Point"}
}