{
  "type": "Feature",
  "properties": {
    "addr:full":"850 Bluewater Ln Oak Harbor WA 98277",
    "addr:housenumber":"850",
    "addr:postcode":"98277",
    "addr:street":"Bluewater Ln",
    "iso:country":"US",
    "sg:address":"850 Bluewater Ln",
    "sg:city":"Oak Harbor",
    "sg:classifiers":[
        {
            "category":"Manufacturing",
            "subcategory":"Signs",
            "type":"Manufacturing & Wholesale Goods"
        }
    ],
    "sg:phone":"+1 360 675 4173",
    "sg:postcode":"98277",
    "sg:province":"WA",
    "wof:name":"Zco",
    "wof:placetype":"venue"
},
  "geometry": {"coordinates":[-122.66228700000001,48.260982],"type":"Point"}
}