{
  "type": "Feature",
  "properties": {
    "addr:full":"10829 NE 68th St Kirkland WA 98033",
    "addr:housenumber":"10829",
    "addr:postcode":"98033",
    "addr:street":"Ne 68Th St",
    "iso:country":"US",
    "sg:address":"10829 NE 68th St",
    "sg:city":"Kirkland",
    "sg:classifiers":[
        {
            "category":"Professional",
            "subcategory":"Research",
            "type":"Services"
        },
        {
            "category":"Professional",
            "subcategory":"Management & Consulting",
            "type":"Services"
        }
    ],
    "sg:phone":"+1 425 827 3188",
    "sg:postcode":"98033",
    "sg:province":"WA",
    "sg:tags":[
        "nonphysical",
        "consultant",
        "commercial",
        "marketing"
    ],
    "wof:name":"Consumer Opinion Services Inc",
    "wof:placetype":"venue"
},
  "geometry": {"coordinates":[-122.193866,47.666331],"type":"Point"}
}