{
  "type": "Feature",
  "properties": {
    "addr:full":"990 SW Rock Creek Dr Stevenson WA 98648",
    "addr:housenumber":"990",
    "addr:postcode":"98648",
    "addr:street":"Sw Rock Creek Dr",
    "iso:country":"US",
    "sg:address":"990 SW Rock Creek Dr",
    "sg:city":"Stevenson",
    "sg:classifiers":[
        {
            "category":"Landmark",
            "subcategory":"Historic",
            "type":"Public Place"
        },
        {
            "category":"Landmark",
            "subcategory":"Tourist Information",
            "type":"Public Place"
        },
        {
            "category":"Museum",
            "type":"Entertainment"
        }
    ],
    "sg:phone":"+1 509 427 8211",
    "sg:postcode":"98648",
    "sg:province":"WA",
    "sg:tags":[
        "building",
        "tour",
        "historical"
    ],
    "sg:website":"www.columbiagorge.org",
    "wof:name":"Columbia Gorge Interpretive Center Museum",
    "wof:placetype":"venue"
},
  "geometry": {"coordinates":[-121.894997,45.692501],"type":"Point"}
}