{
  "type": "Feature",
  "properties": {
    "addr:full":"1712 Young St Aberdeen WA 98520",
    "addr:housenumber":"1712",
    "addr:postcode":"98520",
    "addr:street":"Young St",
    "iso:country":"US",
    "sg:address":"1712 Young St",
    "sg:city":"Aberdeen",
    "sg:classifiers":[
        {
            "category":"Utilities",
            "subcategory":"Water",
            "type":"Services"
        }
    ],
    "sg:phone":"+1 360 532 6731",
    "sg:postcode":"98520",
    "sg:province":"WA",
    "sg:tags":[
        "cooperative"
    ],
    "wof:name":"Tokeland Water Cooperative",
    "wof:placetype":"venue"
},
  "geometry": {"coordinates":[-123.80513999999999,46.98866],"type":"Point"}
}