{
  "type": "Feature",
  "properties": {
    "addr:full":"123 N B St Aberdeen WA 98520",
    "addr:housenumber":"123",
    "addr:postcode":"98520",
    "addr:street":"N B St",
    "iso:country":"US",
    "sg:address":"123 N B St",
    "sg:city":"Aberdeen",
    "sg:classifiers":[
        {
            "category":"Professional",
            "subcategory":"Accounting & Tax Preparation",
            "type":"Services"
        }
    ],
    "sg:phone":"+1 360 533 7780",
    "sg:postcode":"98520",
    "sg:province":"WA",
    "sg:tags":[
        "return",
        "filing"
    ],
    "wof:name":"Western States Accounting Inc PS",
    "wof:placetype":"venue"
},
  "geometry": {"coordinates":[-123.809864,46.980166],"type":"Point"}
}