{
  "type": "Feature",
  "properties": {
    "iso:country":"US",
    "sg:address":"2600 N Columbia Center Blvd",
    "sg:city":"Richland",
    "sg:classifiers":[
        {
            "category":"Real Estate",
            "subcategory":"Real Estate Operator",
            "type":"Services"
        }
    ],
    "sg:phone":"+1 509 783 7332",
    "sg:postcode":"99352",
    "sg:province":"WA",
    "sg:tags":[
        "building",
        "nonresidential"
    ],
    "wof:name":"Columbia Center North MGT LLC",
    "wof:placetype":"venue"
},
  "geometry": {"coordinates":[-119.223176,46.23782],"type":"Point"}
}