{
  "type": "Feature",
  "properties": {
    "addr:full":"1816 N 185th St Seattle WA 98133",
    "addr:housenumber":"1816",
    "addr:postcode":"98133",
    "addr:street":"N 185Th St",
    "iso:country":"US",
    "sg:address":"1816 N 185th St",
    "sg:city":"Seattle",
    "sg:classifiers":[
        {
            "category":"Shopping",
            "subcategory":"Used Merchandise",
            "type":"Retail Goods"
        }
    ],
    "sg:phone":"+1 206 542 0369",
    "sg:postcode":"98133",
    "sg:province":"WA",
    "wof:name":"Atomic Lane",
    "wof:placetype":"venue"
},
  "geometry": {"coordinates":[-122.3368,47.76334],"type":"Point"}
}