{
  "type": "Feature",
  "properties": {
    "addr:full":"529 32nd St Bellingham WA 98225",
    "addr:housenumber":"529",
    "addr:postcode":"98225",
    "addr:street":"32Nd St",
    "iso:country":"US",
    "sg:address":"529 32nd St",
    "sg:city":"Bellingham",
    "sg:classifiers":[
        {
            "category":"Building & Trades",
            "subcategory":"Plumbing",
            "type":"Services"
        }
    ],
    "sg:phone":"+1 360 756 6624",
    "sg:postcode":"98225",
    "sg:province":"WA",
    "sg:tags":[
        "plumbing",
        "contractor"
    ],
    "wof:name":"Gemini Mechanical",
    "wof:placetype":"venue"
},
  "geometry": {"coordinates":[-122.47529,48.729926],"type":"Point"}
}