{
  "type": "Feature",
  "properties": {
    "addr:full":"29 N Hamilton Ave East Wenatchee WA 98802",
    "addr:housenumber":"29",
    "addr:postcode":"98802",
    "addr:street":"N Hamilton Ave",
    "iso:country":"US",
    "sg:address":"29 N Hamilton Ave",
    "sg:city":"East Wenatchee",
    "sg:classifiers":[
        {
            "category":"Building & Trades",
            "subcategory":"Construction",
            "type":"Services"
        }
    ],
    "sg:phone":"+1 509 884 1704",
    "sg:postcode":"98802",
    "sg:province":"WA",
    "sg:tags":[
        "house"
    ],
    "wof:name":"Lakes Construction",
    "wof:placetype":"venue"
},
  "geometry": {"coordinates":[-120.292153,47.41556],"type":"Point"}
}