{
  "type": "Feature",
  "properties": {
    "addr:full":"12700 124th St NE Kirkland WA 98033",
    "addr:housenumber":"12700",
    "addr:postcode":"98033",
    "addr:street":"124Th St Ne",
    "iso:country":"US",
    "sg:address":"12700 124th St NE",
    "sg:city":"Kirkland",
    "sg:classifiers":[
        {
            "category":"Coffee & Tea",
            "type":"Food & Drink"
        }
    ],
    "sg:phone":"+1 425 820 4381",
    "sg:postcode":"98033",
    "sg:province":"WA",
    "wof:name":"Kitanda Brazilian Espresso",
    "wof:placetype":"venue"
},
  "geometry": {"coordinates":[-122.171997,47.7103],"type":"Point"}
}