{
  "type": "Feature",
  "properties": {
    "addr:full":"519 Grant Rd East Wenatchee WA 98802",
    "addr:housenumber":"519",
    "addr:postcode":"98802",
    "addr:street":"Grant Rd",
    "iso:country":"US",
    "sg:address":"519 Grant Rd",
    "sg:city":"East Wenatchee",
    "sg:classifiers":[
        {
            "category":"Government",
            "subcategory":"Office",
            "type":"Public Place"
        }
    ],
    "sg:phone":"+1 509 886 6500",
    "sg:postcode":"98802",
    "sg:province":"WA",
    "sg:tags":[
        "state",
        "inspection"
    ],
    "wof:name":"Labor & Industries Dept",
    "wof:placetype":"venue"
},
  "geometry": {"coordinates":[-120.279144,47.406018],"type":"Point"}
}