{
  "type": "Feature",
  "properties": {
    "addr:full":"7961 169th Ave NE Redmond WA 98052",
    "addr:housenumber":"7961",
    "addr:postcode":"98052",
    "addr:street":"169Th Ave Ne",
    "iso:country":"US",
    "sg:address":"7961 169th Ave NE",
    "sg:city":"Redmond",
    "sg:classifiers":[
        {
            "category":"Professional",
            "subcategory":"Art Services",
            "type":"Services"
        }
    ],
    "sg:phone":"+1 425 861 0600",
    "sg:postcode":"98052",
    "sg:province":"WA",
    "sg:tags":[
        "photography",
        "commercial"
    ],
    "wof:name":"Lori Weisman MA Cmch",
    "wof:placetype":"venue"
},
  "geometry": {"coordinates":[-122.115156,47.674412],"type":"Point"}
}