{
  "type": "Feature",
  "properties": {
    "addr:full":"3027 Olympus Dr NE Bremerton WA 98310",
    "addr:housenumber":"3027",
    "addr:postcode":"98310",
    "addr:street":"Olympus Dr Ne",
    "iso:country":"US",
    "sg:address":"3027 Olympus Dr NE",
    "sg:city":"Bremerton",
    "sg:classifiers":[
        {
            "category":"Government",
            "subcategory":"Office",
            "type":"Public Place"
        }
    ],
    "sg:phone":"+1 360 478 5318",
    "sg:postcode":"98310",
    "sg:province":"WA",
    "sg:tags":[
        "govt",
        "city"
    ],
    "sg:website":"www.ci.bremerton.wa.us",
    "wof:name":"Bremerton Pblc WRKS & Utility",
    "wof:placetype":"venue"
},
  "geometry": {"coordinates":[-122.618871,47.591055],"type":"Point"}
}