{
  "type": "Feature",
  "properties": {
    "addr:full":"447 Sheridan St Tekoa WA 99033",
    "addr:housenumber":"447",
    "addr:postcode":"99033",
    "addr:street":"Sheridan St",
    "iso:country":"US",
    "sg:address":"447 Sheridan St",
    "sg:city":"Tekoa",
    "sg:classifiers":[
        {
            "category":"Manufacturing",
            "subcategory":"Retail Goods",
            "type":"Manufacturing & Wholesale Goods"
        }
    ],
    "sg:phone":"+1 509 284 3204",
    "sg:postcode":"99033",
    "sg:province":"WA",
    "sg:tags":[
        "product",
        "mfg"
    ],
    "wof:name":"Christina Birrenkotts Services",
    "wof:placetype":"venue"
},
  "geometry": {"coordinates":[-117.076413,47.22586],"type":"Point"}
}