{
  "type": "Feature",
  "properties": {
    "addr:full":"2935 Oakes Ave Everett WA 98201",
    "addr:housenumber":"2935",
    "addr:postcode":"98201",
    "addr:street":"Oakes Ave",
    "iso:country":"US",
    "sg:address":"2935 Oakes Ave",
    "sg:city":"Everett",
    "sg:classifiers":[
        {
            "category":"Organizations",
            "subcategory":"Professional Association",
            "type":"Services"
        }
    ],
    "sg:phone":"+1 425 252 9264",
    "sg:postcode":"98201",
    "sg:province":"WA",
    "sg:tags":[
        "business"
    ],
    "wof:name":"Scottish Rite Masonic Temple",
    "wof:placetype":"venue"
},
  "geometry": {"coordinates":[-122.20433,47.97839],"type":"Point"}
}