{
  "type": "Feature",
  "properties": {
    "addr:full":"30 Sanford Ln Sequim WA 98382",
    "addr:housenumber":"30",
    "addr:postcode":"98382",
    "addr:street":"Sanford Ln",
    "iso:country":"US",
    "sg:address":"30 Sanford Ln",
    "sg:city":"Sequim",
    "sg:classifiers":[
        {
            "category":"Organizations",
            "subcategory":"Religious Organization",
            "type":"Services"
        }
    ],
    "sg:phone":"+1 360 683 7373",
    "sg:postcode":"98382",
    "sg:province":"WA",
    "sg:tags":[
        "church"
    ],
    "wof:name":"Seventh Day Adventist Church",
    "wof:placetype":"venue"
},
  "geometry": {"coordinates":[-123.107084,48.100124],"type":"Point"}
}