{
  "type": "Feature",
  "properties": {
    "addr:full":"910 52nd St SE Everett WA 98203",
    "addr:housenumber":"910",
    "addr:postcode":"98203",
    "addr:street":"52Nd St Se",
    "iso:country":"US",
    "sg:address":"910 52nd St SE",
    "sg:city":"Everett",
    "sg:classifiers":[
        {
            "category":"Building & Trades",
            "subcategory":"Construction",
            "type":"Services"
        }
    ],
    "sg:phone":"+1 425 252 3489",
    "sg:postcode":"98203",
    "sg:province":"WA",
    "sg:tags":[
        "concrete",
        "contractor"
    ],
    "wof:name":"Moller Larsen & Son",
    "wof:placetype":"venue"
},
  "geometry": {"coordinates":[-122.21742500000001,47.949431],"type":"Point"}
}