{
  "type": "Feature",
  "properties": {
    "addr:full":"1500 Fairview Ave E Seattle WA 98102",
    "addr:housenumber":"1500",
    "addr:postcode":"98102",
    "addr:street":"Fairview Ave E",
    "iso:country":"US",
    "sg:address":"1500 Fairview Ave E",
    "sg:city":"Seattle",
    "sg:classifiers":[
        {
            "category":"Professional",
            "type":"Services"
        }
    ],
    "sg:phone":"+1 206 838 0320",
    "sg:postcode":"98102",
    "sg:province":"WA",
    "wof:name":"Endeavour",
    "wof:placetype":"venue"
},
  "geometry": {"coordinates":[-122.326903,47.633851],"type":"Point"}
}