{
  "type": "Feature",
  "properties": {
    "addr:full":"615 Jadwin Ave Richland WA 99352",
    "addr:housenumber":"615",
    "addr:postcode":"99352",
    "addr:street":"Jadwin Ave",
    "iso:country":"US",
    "sg:address":"615 Jadwin Ave",
    "sg:city":"Richland",
    "sg:classifiers":[
        {
            "category":"Travel",
            "subcategory":"Hotels & Motels",
            "type":"Entertainment"
        }
    ],
    "sg:phone":"+1 509 943 4611",
    "sg:postcode":"99352",
    "sg:province":"WA",
    "wof:name":"Young & Nam Inc",
    "wof:placetype":"venue"
},
  "geometry": {"coordinates":[-119.275083,46.273201],"type":"Point"}
}