{
  "type": "Feature",
  "properties": {
    "addr:full":"6418 20th Ave NW Seattle WA 98107",
    "addr:housenumber":"6418",
    "addr:postcode":"98107",
    "addr:street":"20Th Ave Nw",
    "iso:country":"US",
    "sg:address":"6418 20th Ave NW",
    "sg:city":"Seattle",
    "sg:phone":"+1 206 789 4044",
    "sg:postcode":"98107",
    "sg:province":"WA",
    "wof:name":"Laura Bee Designs",
    "wof:placetype":"venue"
},
  "geometry": {"coordinates":[-122.382133,47.675427],"type":"Point"}
}