{
  "type": "Feature",
  "properties": {
    "addr:full":"829 E 65th St Tacoma WA 98404",
    "addr:housenumber":"829",
    "addr:postcode":"98404",
    "addr:street":"E 65Th St",
    "iso:country":"US",
    "sg:address":"829 E 65th St",
    "sg:city":"Tacoma",
    "sg:classifiers":[
        {
            "category":"Manufacturing",
            "subcategory":"Retail Goods",
            "type":"Manufacturing & Wholesale Goods"
        }
    ],
    "sg:phone":"+1 253 474 7906",
    "sg:postcode":"98404",
    "sg:province":"WA",
    "sg:tags":[
        "product",
        "mfg"
    ],
    "wof:name":"R&B Mfg Inc",
    "wof:placetype":"venue"
},
  "geometry": {"coordinates":[-122.419406,47.198211],"type":"Point"}
}