{
  "type": "Feature",
  "properties": {
    "addr:full":"6441 23rd Ave S Seattle WA 98108",
    "addr:housenumber":"6441",
    "addr:postcode":"98108",
    "addr:street":"23Rd Ave S",
    "iso:country":"US",
    "sg:address":"6441 23rd Ave S",
    "sg:city":"Seattle",
    "sg:classifiers":[
        {
            "category":"Building & Trades",
            "subcategory":"Construction",
            "type":"Services"
        }
    ],
    "sg:phone":"+1 206 723 4534",
    "sg:postcode":"98108",
    "sg:province":"WA",
    "sg:tags":[
        "general",
        "contractor"
    ],
    "wof:name":"Hammerite Construction Inc",
    "wof:placetype":"venue"
},
  "geometry": {"coordinates":[-122.304204,47.544602],"type":"Point"}
}