{
  "type": "Feature",
  "properties": {
    "addr:full":"610 S 1st St Mount Vernon WA 98273",
    "addr:housenumber":"610",
    "addr:postcode":"98273",
    "addr:street":"S 1St St",
    "iso:country":"US",
    "sg:address":"610 S 1st St",
    "sg:city":"Mount Vernon",
    "sg:classifiers":[
        {
            "category":"Shopping",
            "subcategory":"Used Merchandise",
            "type":"Retail Goods"
        }
    ],
    "sg:phone":"+1 360 419 7278",
    "sg:postcode":"98273",
    "sg:province":"WA",
    "sg:tags":[
        "bookstore",
        "rare",
        "book"
    ],
    "wof:name":"The Tattered Page",
    "wof:placetype":"venue"
},
  "geometry": {"coordinates":[-122.33899700000001,48.418598],"type":"Point"}
}