{
  "type": "Feature",
  "properties": {
    "addr:full":"5503 6th Ave S Seattle WA 98108",
    "addr:housenumber":"5503",
    "addr:postcode":"98108",
    "addr:street":"6Th Ave S",
    "iso:country":"US",
    "sg:address":"5503 6th Ave S",
    "sg:city":"Seattle",
    "sg:classifiers":[
        {
            "category":"Wholesale",
            "subcategory":"Hardware",
            "type":"Manufacturing & Wholesale Goods"
        }
    ],
    "sg:phone":"+1 206 763 8800",
    "sg:postcode":"98108",
    "sg:province":"WA",
    "sg:tags":[
        "hardware-wholesale",
        "manufacturer"
    ],
    "wof:name":"Stagecraft Industries, Inc.",
    "wof:placetype":"venue"
},
  "geometry": {"coordinates":[-122.326859,47.553356],"type":"Point"}
}