{
  "type": "Feature",
  "properties": {
    "addr:full":"12111 E Main Ave Spokane Valley WA 99206",
    "addr:housenumber":"12111",
    "addr:postcode":"99206",
    "addr:street":"E Main Ave",
    "iso:country":"US",
    "sg:address":"12111 E Main Ave",
    "sg:city":"Spokane Valley",
    "sg:classifiers":[
        {
            "category":"Professional",
            "type":"Services"
        }
    ],
    "sg:phone":"+1 509 926 1753",
    "sg:postcode":"99206",
    "sg:province":"WA",
    "sg:tags":[
        "establishment"
    ],
    "wof:name":"Opportunity Manor",
    "wof:placetype":"venue"
},
  "geometry": {"coordinates":[-117.241664,47.658992],"type":"Point"}
}