{
  "type": "Feature",
  "properties": {
    "addr:full":"905 N Cedar St Colville WA 99114",
    "addr:housenumber":"905",
    "addr:postcode":"99114",
    "addr:street":"N Cedar St",
    "iso:country":"US",
    "sg:address":"905 N Cedar St",
    "sg:city":"Colville",
    "sg:classifiers":[
        {
            "category":"Building & Trades",
            "subcategory":"Construction",
            "type":"Services"
        }
    ],
    "sg:phone":"+1 509 684 3426",
    "sg:postcode":"99114",
    "sg:province":"WA",
    "sg:tags":[
        "contractor",
        "general"
    ],
    "wof:name":"Huguenin Construction",
    "wof:placetype":"venue"
},
  "geometry": {"coordinates":[-117.89882799999999,48.553917],"type":"Point"}
}