{
  "type": "Feature",
  "properties": {
    "iso:country":"US",
    "sg:address":"1008 NE 100th Ave",
    "sg:city":"Vancouver",
    "sg:classifiers":[
        {
            "category":"Building & Trades",
            "subcategory":"Construction",
            "type":"Services"
        }
    ],
    "sg:phone":"+1 360 891 8016",
    "sg:postcode":"98664",
    "sg:province":"WA",
    "sg:tags":[
        "contractor"
    ],
    "wof:name":"Advanced Contracting Inc",
    "wof:placetype":"venue"
},
  "geometry": {"coordinates":[-122.570204,45.629506],"type":"Point"}
}