{
  "type": "Feature",
  "properties": {
    "addr:full":"4540 Scott Rd NW Olympia WA 98502",
    "addr:housenumber":"4540",
    "addr:postcode":"olympia wa 98502",
    "addr:street":"Scott Rd Nw",
    "iso:country":"US",
    "sg:address":"4540 Scott Rd NW",
    "sg:city":"Olympia",
    "sg:classifiers":[
        {
            "category":"Building & Trades",
            "subcategory":"Construction",
            "type":"Services"
        }
    ],
    "sg:phone":"+1 360 866 2092",
    "sg:postcode":"98502",
    "sg:province":"WA",
    "sg:tags":[
        "excavation",
        "contractor"
    ],
    "wof:name":"Burn T L Excavating LLC",
    "wof:placetype":"venue"
},
  "geometry": {"coordinates":[-123.032758,47.101479],"type":"Point"}
}