{
  "type": "Feature",
  "properties": {
    "addr:full":"1590 Old Stage Way Yakima WA 98908",
    "addr:housenumber":"1590",
    "addr:postcode":"98908",
    "addr:street":"Old Stage Way",
    "iso:country":"US",
    "sg:address":"1590 Old Stage Way",
    "sg:city":"Yakima",
    "sg:classifiers":[
        {
            "category":"Professional",
            "subcategory":"Business Services",
            "type":"Services"
        }
    ],
    "sg:phone":"+1 509 965 9712",
    "sg:postcode":"98908",
    "sg:province":"WA",
    "sg:tags":[
        "plant",
        "design",
        "maintenance"
    ],
    "wof:name":"Exotic Green",
    "wof:placetype":"venue"
},
  "geometry": {"coordinates":[-120.586792,46.678626],"type":"Point"}
}