{
  "type": "Feature",
  "properties": {
    "addr:full":"6358 42nd Ave SW Seattle WA 98136",
    "addr:housenumber":"6358",
    "addr:postcode":"98136",
    "addr:street":"42Nd Ave Sw",
    "iso:country":"US",
    "sg:address":"6358 42nd Ave SW",
    "sg:city":"Seattle",
    "sg:classifiers":[
        {
            "category":"Banks & Credit Unions",
            "subcategory":"Financial Services",
            "type":"Services"
        }
    ],
    "sg:phone":"+1 206 932 4398",
    "sg:postcode":"98136",
    "sg:province":"WA",
    "sg:tags":[
        "escrow"
    ],
    "wof:name":"A'lora Escrow",
    "wof:placetype":"venue"
},
  "geometry": {"coordinates":[-122.385757,47.545752],"type":"Point"}
}