{
  "type": "Feature",
  "properties": {
    "addr:full":"100 State St S Kirkland WA 98033",
    "addr:housenumber":"100",
    "addr:postcode":"98033",
    "addr:street":"State St S",
    "iso:country":"US",
    "sg:address":"100 State St S",
    "sg:city":"Kirkland",
    "sg:classifiers":[
        {
            "category":"Professional",
            "subcategory":"Lawyer & Legal Services",
            "type":"Services"
        }
    ],
    "sg:phone":"+1 425 889 7461",
    "sg:postcode":"98033",
    "sg:province":"WA",
    "wof:name":"Kirkland Wills & Trusts",
    "wof:placetype":"venue"
},
  "geometry": {"coordinates":[-122.203003,47.674702],"type":"Point"}
}