{
  "type": "Feature",
  "properties": {
    "addr:full":"3241 NE Sunset Blvd Renton WA 98056",
    "addr:housenumber":"3241",
    "addr:postcode":"98056",
    "addr:street":"Ne Sunset Blvd",
    "iso:country":"US",
    "sg:address":"3241 NE Sunset Blvd",
    "sg:city":"Renton",
    "sg:classifiers":[
        {
            "category":"Retail",
            "subcategory":"Veterinary Services",
            "type":"Services"
        }
    ],
    "sg:phone":"+1 425 226 6359",
    "sg:postcode":"98056",
    "sg:province":"WA",
    "sg:tags":[
        "veterinarian"
    ],
    "wof:name":"Sunset Pet Hospital",
    "wof:placetype":"venue"
},
  "geometry": {"coordinates":[-122.175426,47.504751],"type":"Point"}
}