{
  "type": "Feature",
  "properties": {
    "addr:full":"8815 E Mill Plain Blvd Vancouver WA 98664",
    "addr:housenumber":"8815",
    "addr:postcode":"98664",
    "addr:street":"E Mill Plain Blvd",
    "iso:country":"US",
    "sg:address":"8815 E Mill Plain Blvd",
    "sg:city":"Vancouver",
    "sg:classifiers":[
        {
            "category":"Health Services",
            "subcategory":"Doctor",
            "type":"Services"
        }
    ],
    "sg:phone":"+1 360 254 1814",
    "sg:postcode":"98664",
    "sg:province":"WA",
    "sg:tags":[
        "physician",
        "surgeon",
        "surgeons",
        "psychiatry"
    ],
    "wof:name":"Wisler, Rae Md",
    "wof:placetype":"venue"
},
  "geometry": {"coordinates":[-122.582162,45.622887],"type":"Point"}
}