{
  "type": "Feature",
  "properties": {
    "addr:full":"12215 SE 60th St Bellevue WA 98006",
    "addr:housenumber":"12215",
    "addr:postcode":"98006",
    "addr:street":"Se 60Th St",
    "iso:country":"US",
    "sg:address":"12215 SE 60th St",
    "sg:city":"Bellevue",
    "sg:classifiers":[
        {
            "category":"Wholesale",
            "subcategory":"Durable Goods & Equipment",
            "type":"Manufacturing & Wholesale Goods"
        }
    ],
    "sg:phone":"+1 425 830 4697",
    "sg:postcode":"98006",
    "sg:province":"WA",
    "wof:name":"Joy Wholesale",
    "wof:placetype":"venue"
},
  "geometry": {"coordinates":[-122.1793,47.54981],"type":"Point"}
}