{
  "type": "Feature",
  "properties": {
    "addr:full":"1305 4th Ave Seattle WA 98101",
    "addr:housenumber":"1305",
    "addr:postcode":"98101",
    "addr:street":"4Th Ave",
    "iso:country":"US",
    "sg:address":"1305 4th Ave",
    "sg:city":"Seattle",
    "sg:classifiers":[
        {
            "category":"Manufacturing",
            "subcategory":"Tools & Machinery",
            "type":"Manufacturing & Wholesale Goods"
        }
    ],
    "sg:phone":"+1 206 624 2274",
    "sg:postcode":"98101",
    "sg:province":"WA",
    "sg:tags":[
        "lens",
        "mfr",
        "contact",
        "fit"
    ],
    "wof:name":"Physicians Contact Lens Inc",
    "wof:placetype":"venue"
},
  "geometry": {"coordinates":[-122.33581599999999,47.609138],"type":"Point"}
}