{
  "type": "Feature",
  "properties": {
    "addr:full":"2200 Westlake Ave, South Tower Whole Foods Village Seattle WA 98127",
    "addr:housenumber":"2200",
    "addr:postcode":"98127",
    "addr:street":"Westlake Ave South",
    "iso:country":"US",
    "sg:address":"2200 Westlake Ave, South Tower Whole Foods Village",
    "sg:city":"Seattle",
    "sg:classifiers":[
        {
            "category":"Banks & Credit Unions",
            "subcategory":"Bank",
            "type":"Services"
        }
    ],
    "sg:phone":"+1 206 262 9091",
    "sg:postcode":"98127",
    "sg:province":"WA",
    "sg:website":"www.bankofamerica.com",
    "wof:name":"Bank of America",
    "wof:placetype":"venue"
},
  "geometry": {"coordinates":[-122.338401,47.618015],"type":"Point"}
}