{
  "type": "Feature",
  "properties": {
    "addr:full":"615 W Carlisle Ave Spokane WA 99205",
    "addr:housenumber":"615",
    "addr:postcode":"99205",
    "addr:street":"W Carlisle Ave",
    "iso:country":"US",
    "sg:address":"615 W Carlisle Ave",
    "sg:city":"Spokane",
    "sg:classifiers":[
        {
            "category":"Professional",
            "subcategory":"Engineering",
            "type":"Services"
        }
    ],
    "sg:phone":"+1 509 328 6003",
    "sg:postcode":"99205",
    "sg:province":"WA",
    "wof:name":"Steve Alan Richards",
    "wof:placetype":"venue"
},
  "geometry": {"coordinates":[-117.421902,47.679291],"type":"Point"}
}