{
  "type": "Feature",
  "properties": {
    "addr:full":"6219 E Trent Ave Spokane Valley WA 99212",
    "addr:housenumber":"6219",
    "addr:postcode":"99212",
    "addr:street":"E Trent Ave",
    "iso:country":"US",
    "sg:address":"6219 E Trent Ave",
    "sg:city":"Spokane Valley",
    "sg:classifiers":[
        {
            "category":"Manufacturing",
            "subcategory":"Glass & Minerals",
            "type":"Manufacturing & Wholesale Goods"
        }
    ],
    "sg:phone":"+1 509 534 0651",
    "sg:postcode":"99212",
    "sg:province":"WA",
    "sg:tags":[
        "product",
        "mfg",
        "concrete",
        "precast",
        "brick",
        "block"
    ],
    "wof:name":"White Block Co Inc",
    "wof:placetype":"venue"
},
  "geometry": {"coordinates":[-117.321522,47.675435],"type":"Point"}
}