{
  "type": "Feature",
  "properties": {
    "addr:full":"12510 506th St E Eatonville WA 98328",
    "addr:housenumber":"12510",
    "addr:postcode":"98328",
    "addr:street":"506Th St E",
    "iso:country":"US",
    "sg:address":"12510 506th St E",
    "sg:city":"Eatonville",
    "sg:classifiers":[
        {
            "category":"Health Services",
            "subcategory":"Health Practitioner",
            "type":"Services"
        }
    ],
    "sg:phone":"+1 360 832 6809",
    "sg:postcode":"98328",
    "sg:province":"WA",
    "wof:name":"Eatonvilles Therapeutic Massa",
    "wof:placetype":"venue"
},
  "geometry": {"coordinates":[-122.267471,46.799327],"type":"Point"}
}