{
  "type": "Feature",
  "properties": {
    "addr:full":"32521 50th Pl SW Federal Way WA 98023",
    "addr:housenumber":"32521",
    "addr:postcode":"98023",
    "addr:street":"50Th Pl Sw Federal Way",
    "iso:country":"US",
    "sg:address":"32521 50th Pl SW",
    "sg:city":"Federal Way",
    "sg:classifiers":[
        {
            "category":"Retail",
            "subcategory":"Car Wash",
            "type":"Services"
        }
    ],
    "sg:phone":"+1 253 815 9253",
    "sg:postcode":"98023",
    "sg:province":"WA",
    "sg:tags":[
        "carwash"
    ],
    "wof:name":"Priceless Pressure Wash",
    "wof:placetype":"venue"
},
  "geometry": {"coordinates":[-122.39758999999999,47.310061],"type":"Point"}
}