{
  "type": "Feature",
  "properties": {
    "addr:full":"1815 Loomis-Oroville Rd Loomis WA 98827",
    "addr:housenumber":"1815",
    "addr:postcode":"98827",
    "addr:street":"Loomis-Oroville Rd",
    "iso:country":"US",
    "sg:address":"1815 Loomis-Oroville Rd",
    "sg:city":"Loomis",
    "sg:classifiers":[
        {
            "category":"Museum",
            "type":"Entertainment"
        }
    ],
    "sg:phone":"+1 509 223 3053",
    "sg:postcode":"98827",
    "sg:province":"WA",
    "sg:tags":[
        "gallery"
    ],
    "wof:name":"Rippee Collection",
    "wof:placetype":"venue"
},
  "geometry": {"coordinates":[-119.60824,48.90272],"type":"Point"}
}