{
  "type": "Feature",
  "properties": {
    "addr:full":"3519 NE 135th St Seattle WA 98125",
    "addr:housenumber":"3519",
    "addr:postcode":"98125",
    "addr:street":"Ne 135Th St",
    "iso:country":"US",
    "sg:address":"3519 NE 135th St",
    "sg:city":"Seattle",
    "sg:classifiers":[
        {
            "category":"Building & Trades",
            "subcategory":"Construction",
            "type":"Services"
        }
    ],
    "sg:phone":"+1 206 364 7240",
    "sg:postcode":"98125",
    "sg:province":"WA",
    "sg:tags":[
        "house"
    ],
    "wof:name":"Webberley Const",
    "wof:placetype":"venue"
},
  "geometry": {"coordinates":[-122.289728,47.726376],"type":"Point"}
}