{
  "type": "Feature",
  "properties": {
    "addr:full":"1736 Iowa St Bellingham WA 98229",
    "addr:housenumber":"1736",
    "addr:postcode":"98229",
    "addr:street":"Iowa St",
    "iso:country":"US",
    "sg:address":"1736 Iowa St",
    "sg:city":"Bellingham",
    "sg:classifiers":[
        {
            "category":"Personal",
            "subcategory":"Beauty Salon",
            "type":"Services"
        }
    ],
    "sg:phone":"+1 360 752 2826",
    "sg:postcode":"98229",
    "sg:province":"WA",
    "sg:tags":[
        "shop"
    ],
    "wof:name":"A True Color Salon",
    "wof:placetype":"venue"
},
  "geometry": {"coordinates":[-122.45072500000001,48.75644],"type":"Point"}
}