{
  "type": "Feature",
  "properties": {
    "iso:country":"US",
    "sg:address":"5144 Ballard Ave NW",
    "sg:city":"Seattle",
    "sg:classifiers":[
        {
            "category":"Bars & Pubs",
            "type":"Food & Drink"
        }
    ],
    "sg:phone":"+1 206 784 2251",
    "sg:postcode":"98107",
    "sg:province":"WA",
    "wof:name":"Borge's Place",
    "wof:placetype":"venue"
},
  "geometry": {"coordinates":[-122.38201100000001,47.665468],"type":"Point"}
}