{
  "type": "Feature",
  "properties": {
    "addr:full":"20510 60th Ave W Lynnwood WA 98036",
    "addr:housenumber":"20510",
    "addr:postcode":"98036",
    "addr:street":"60Th Ave W",
    "iso:country":"US",
    "sg:address":"20510 60th Ave W",
    "sg:city":"Lynnwood",
    "sg:classifiers":[
        {
            "category":"Building & Trades",
            "subcategory":"Construction",
            "type":"Services"
        }
    ],
    "sg:phone":"+1 425 672 7711",
    "sg:postcode":"98036",
    "sg:province":"WA",
    "sg:tags":[
        "masonry",
        "contractor"
    ],
    "wof:name":"American Masonry & Restoration",
    "wof:placetype":"venue"
},
  "geometry": {"coordinates":[-122.314171,47.813805],"type":"Point"}
}