{
  "type": "Feature",
  "properties": {
    "addr:full":"4830 Gravelly Beach Loop NW Olympia WA 98502",
    "addr:housenumber":"4830",
    "addr:postcode":"olympia wa 98502",
    "addr:street":"Gravelly Beach Loop Nw",
    "iso:country":"US",
    "sg:address":"4830 Gravelly Beach Loop NW",
    "sg:city":"Olympia",
    "sg:classifiers":[
        {
            "category":"Shopping",
            "subcategory":"Florist",
            "type":"Retail Goods"
        }
    ],
    "sg:phone":"+1 360 866 0812",
    "sg:postcode":"98502",
    "sg:province":"WA",
    "wof:name":"KTM",
    "wof:placetype":"venue"
},
  "geometry": {"coordinates":[-122.990753,47.107827],"type":"Point"}
}