{
  "type": "Feature",
  "properties": {
    "addr:full":"6312 N 30th St Tacoma WA 98407",
    "addr:housenumber":"6312",
    "addr:postcode":"98407",
    "addr:street":"N 30Th St",
    "iso:country":"US",
    "sg:address":"6312 N 30th St",
    "sg:city":"Tacoma",
    "sg:classifiers":[
        {
            "category":"Social Services",
            "subcategory":"Child Care",
            "type":"Services"
        }
    ],
    "sg:phone":"+1 253 752 6463",
    "sg:postcode":"98407",
    "sg:province":"WA",
    "sg:tags":[
        "day"
    ],
    "wof:name":"Arcadia Learning Center Inc",
    "wof:placetype":"venue"
},
  "geometry": {"coordinates":[-122.52167799999999,47.274303],"type":"Point"}
}