{
  "type": "Feature",
  "properties": {
    "addr:full":"10702 78th Ave NW Gig Harbor WA 98332",
    "addr:housenumber":"10702",
    "addr:postcode":"98332",
    "addr:street":"78Th Ave Nw",
    "iso:country":"US",
    "sg:address":"10702 78th Ave NW",
    "sg:city":"Gig Harbor",
    "sg:classifiers":[
        {
            "category":"Personal",
            "type":"Services"
        }
    ],
    "sg:phone":"+1 253 677 5877",
    "sg:postcode":"98332",
    "sg:province":"WA",
    "wof:name":"Invision Events",
    "wof:placetype":"venue"
},
  "geometry": {"coordinates":[-122.642647,47.358814],"type":"Point"}
}