{
  "type": "Feature",
  "properties": {
    "addr:full":"19506 Fremont Ave N Seattle WA 98133",
    "addr:housenumber":"19506",
    "addr:postcode":"98133",
    "addr:street":"Fremont Ave N",
    "iso:country":"US",
    "sg:address":"19506 Fremont Ave N",
    "sg:city":"Seattle",
    "sg:classifiers":[
        {
            "category":"Communications",
            "subcategory":"Film & Video Production",
            "type":"Services"
        }
    ],
    "sg:phone":"+1 206 789 5034",
    "sg:postcode":"98133",
    "sg:province":"WA",
    "sg:tags":[
        "motion",
        "advertising"
    ],
    "wof:name":"Eiffel Productions",
    "wof:placetype":"venue"
},
  "geometry": {"coordinates":[-122.351253,47.772269],"type":"Point"}
}