{
  "type": "Feature",
  "properties": {
    "iso:country":"US",
    "sg:address":"315 Lincoln Ave",
    "sg:city":"Mukilteo",
    "sg:classifiers":[
        {
            "category":"Professional",
            "subcategory":"Management & Consulting",
            "type":"Services"
        }
    ],
    "sg:phone":"+1 425 252 5464",
    "sg:postcode":"98275",
    "sg:province":"WA",
    "wof:name":"Scatter Brains International I",
    "wof:placetype":"venue"
},
  "geometry": {"coordinates":[-122.303455,47.945689],"type":"Point"}
}