{
  "type": "Feature",
  "properties": {
    "addr:full":"18950 Park Blvd NE Suquamish WA 98392",
    "addr:housenumber":"18950",
    "addr:postcode":"98392",
    "addr:street":"Park Blvd Ne",
    "iso:country":"US",
    "sg:address":"18950 Park Blvd NE",
    "sg:city":"Suquamish",
    "sg:classifiers":[
        {
            "category":"Education",
            "subcategory":"School",
            "type":"Public Place"
        }
    ],
    "sg:phone":"+1 360 598 4219",
    "sg:postcode":"98392",
    "sg:province":"WA",
    "sg:tags":[
        "elementary"
    ],
    "wof:name":"Suquamish Elementary School",
    "wof:placetype":"venue"
},
  "geometry": {"coordinates":[-122.55691,47.735699],"type":"Point"}
}