{
  "type": "Feature",
  "properties": {
    "addr:full":"501 Main St Vancouver WA 98660",
    "addr:housenumber":"501",
    "addr:postcode":"98660",
    "addr:street":"Main St",
    "iso:country":"US",
    "sg:address":"501 Main St",
    "sg:city":"Vancouver",
    "sg:classifiers":[
        {
            "category":"Travel",
            "subcategory":"Hotels & Motels",
            "type":"Entertainment"
        }
    ],
    "sg:phone":"+1 360 695 1133",
    "sg:postcode":"98660",
    "sg:province":"WA",
    "wof:name":"Monterey Hotel",
    "wof:placetype":"venue"
},
  "geometry": {"coordinates":[-122.671661,45.624931],"type":"Point"}
}