{
  "type": "Feature",
  "properties": {
    "addr:full":"5705 W Clearwater Ave Kennewick WA 99336",
    "addr:housenumber":"5705",
    "addr:postcode":"99336",
    "addr:street":"W Clearwater Ave",
    "iso:country":"US",
    "sg:address":"5705 W Clearwater Ave",
    "sg:city":"Kennewick",
    "sg:classifiers":[
        {
            "category":"Manufacturing",
            "subcategory":"Buildings",
            "type":"Manufacturing & Wholesale Goods"
        },
        {
            "category":"Shopping",
            "subcategory":"Mobile Phones",
            "type":"Retail Goods"
        },
        {
            "category":"Building & Trades",
            "subcategory":"Construction",
            "type":"Services"
        }
    ],
    "sg:phone":"+1 509 783 4947",
    "sg:postcode":"99336",
    "sg:province":"WA",
    "sg:tags":[
        "home",
        "builder",
        "contractor"
    ],
    "wof:name":"Western Heritage Homes",
    "wof:placetype":"venue"
},
  "geometry": {"coordinates":[-119.19719000000001,46.21244],"type":"Point"}
}