{
  "type": "Feature",
  "properties": {
    "addr:full":"11700 NE 60th Way Vancouver WA 98682",
    "addr:housenumber":"11700",
    "addr:postcode":"98682",
    "addr:street":"Ne 60Th Way",
    "iso:country":"US",
    "sg:address":"11700 NE 60th Way",
    "sg:city":"Vancouver",
    "sg:classifiers":[
        {
            "category":"Building & Trades",
            "subcategory":"Plumbing",
            "type":"Services"
        }
    ],
    "sg:phone":"+1 360 885 7641",
    "sg:postcode":"98682",
    "sg:province":"WA",
    "sg:tags":[
        "mechanical",
        "contractor"
    ],
    "wof:name":"Rohner Mechanical Inc",
    "wof:placetype":"venue"
},
  "geometry": {"coordinates":[-122.55117799999999,45.665898],"type":"Point"}
}