{
  "type": "Feature",
  "properties": {
    "addr:full":"5311 Bitteroot Way Yakima WA 98908",
    "addr:housenumber":"5311",
    "addr:postcode":"98908",
    "addr:street":"Bitteroot Way",
    "iso:country":"US",
    "sg:address":"5311 Bitteroot Way",
    "sg:city":"Yakima",
    "sg:classifiers":[
        {
            "category":"Banks & Credit Unions",
            "subcategory":"Investment Brokerage",
            "type":"Services"
        }
    ],
    "sg:phone":"+1 509 965 1015",
    "sg:postcode":"98908",
    "sg:province":"WA",
    "wof:name":"Forest Acres Inc",
    "wof:placetype":"venue"
},
  "geometry": {"coordinates":[-120.576173,46.602743],"type":"Point"}
}