{
  "type": "Feature",
  "properties": {
    "addr:full":"613 N Rd 44 Pasco WA 99301",
    "addr:housenumber":"613;44",
    "addr:postcode":"99301",
    "addr:street":"N Rd",
    "iso:country":"US",
    "sg:address":"613 N Rd 44",
    "sg:city":"Pasco",
    "sg:classifiers":[
        {
            "category":"Retail",
            "subcategory":"Portrait Studio",
            "type":"Services"
        }
    ],
    "sg:phone":"+1 509 547 7217",
    "sg:postcode":"99301",
    "sg:province":"WA",
    "sg:tags":[
        "photo"
    ],
    "wof:name":"Bill Watts Photography",
    "wof:placetype":"venue"
},
  "geometry": {"coordinates":[-119.148922,46.234106],"type":"Point"}
}