{
  "type": "Feature",
  "properties": {
    "addr:full":"1323 E Main Puyallup WA 98372",
    "addr:housenumber":"1323",
    "addr:postcode":"98372",
    "addr:street":"E Main",
    "iso:country":"US",
    "sg:address":"1323 E Main",
    "sg:city":"Puyallup",
    "sg:classifiers":[
        {
            "category":"Food & Beverages",
            "subcategory":"Specialty",
            "type":"Retail Goods"
        },
        {
            "category":"Food & Beverages",
            "subcategory":"Fruits & Vegetables",
            "type":"Retail Goods"
        },
        {
            "category":"Shopping",
            "subcategory":"Pharmacy",
            "type":"Retail Goods"
        }
    ],
    "sg:phone":"+1 253 848 3564",
    "sg:postcode":"98372",
    "sg:province":"WA",
    "sg:tags":[
        "product",
        "wellness",
        "vitamin",
        "diet",
        "supplement",
        "health",
        "herb"
    ],
    "sg:website":"http://www.gnc.com",
    "wof:name":"GNC",
    "wof:placetype":"venue"
},
  "geometry": {"coordinates":[-122.27645,47.191868],"type":"Point"}
}