{
  "type": "Feature",
  "properties": {
    "addr:full":"16068 Ambaum Blvd S Burien WA 98148",
    "addr:postcode":"16068;98148",
    "addr:street":"Ambaum Blvd S Burien",
    "iso:country":"US",
    "sg:address":"16068 Ambaum Blvd S",
    "sg:city":"Burien",
    "sg:classifiers":[
        {
            "category":"Professional",
            "subcategory":"Detective & Security Services",
            "type":"Services"
        }
    ],
    "sg:phone":"+1 206 243 3500",
    "sg:postcode":"98148",
    "sg:province":"WA",
    "sg:tags":[
        "information",
        "bureau"
    ],
    "wof:name":"Rv Service Department Inc",
    "wof:placetype":"venue"
},
  "geometry": {"coordinates":[-122.332508,47.458459],"type":"Point"}
}