{
  "type": "Feature",
  "properties": {
    "iso:country":"US",
    "sg:address":"1715 James St",
    "sg:city":"Bellingham",
    "sg:classifiers":[
        {
            "category":"Building & Trades",
            "subcategory":"Cleaning & Sanitation",
            "type":"Services"
        }
    ],
    "sg:phone":"+1 360 733 7956",
    "sg:postcode":"98225",
    "sg:province":"WA",
    "sg:tags":[
        "maintenance"
    ],
    "wof:name":"Shade Maid & Com LLC",
    "wof:placetype":"venue"
},
  "geometry": {"coordinates":[-122.46507699999999,48.753174],"type":"Point"}
}