{
  "type": "Feature",
  "properties": {
    "addr:full":"1519 NE 192nd St Shoreline WA 98155",
    "addr:housenumber":"1519",
    "addr:postcode":"98155",
    "addr:street":"Ne 192Nd St",
    "iso:country":"US",
    "sg:address":"1519 NE 192nd St",
    "sg:city":"Shoreline",
    "sg:classifiers":[
        {
            "category":"Professional",
            "subcategory":"Business Services",
            "type":"Services"
        },
        {
            "category":"Building & Trades",
            "subcategory":"Construction",
            "type":"Services"
        }
    ],
    "sg:phone":"+1 206 417 3795",
    "sg:postcode":"98155",
    "sg:province":"WA",
    "sg:tags":[
        "contractor"
    ],
    "wof:name":"Harmony Design & Build LLC",
    "wof:placetype":"venue"
},
  "geometry": {"coordinates":[-122.312713,47.768267],"type":"Point"}
}