{
  "type": "Feature",
  "properties": {
    "addr:full":"318 Montlake Blvd University of Washington Seattle WA 98195",
    "addr:housenumber":"318",
    "addr:postcode":"98195",
    "addr:street":"Montlake Blvd",
    "iso:country":"US",
    "sg:address":"318 Montlake Blvd University of Washington",
    "sg:city":"Seattle",
    "sg:classifiers":[
        {
            "category":"Arts & Performance",
            "subcategory":"Music",
            "type":"Entertainment"
        }
    ],
    "sg:postcode":"98195",
    "sg:province":"WA",
    "sg:tags":[
        "venue"
    ],
    "sg:website":"www.washington.edu/",
    "wof:name":"Hec Edmundson Pavillion",
    "wof:placetype":"venue"
},
  "geometry": {"coordinates":[-122.30245499999999,47.654421],"type":"Point"}
}