{
  "type": "Feature",
  "properties": {
    "addr:full":"16723 Larch Way Lynnwood WA 98037",
    "addr:housenumber":"16723",
    "addr:postcode":"98037",
    "addr:street":"Larch Way",
    "iso:country":"US",
    "sg:address":"16723 Larch Way",
    "sg:city":"Lynnwood",
    "sg:classifiers":[
        {
            "category":"Building & Trades",
            "subcategory":"Construction",
            "type":"Services"
        }
    ],
    "sg:phone":"+1 425 673 4614",
    "sg:postcode":"98037",
    "sg:province":"WA",
    "sg:tags":[
        "general",
        "contractor"
    ],
    "wof:name":"Brandel Family Homes",
    "wof:placetype":"venue"
},
  "geometry": {"coordinates":[-122.246618,47.847041],"type":"Point"}
}