{
  "type": "Feature",
  "properties": {
    "addr:full":"2155 E McLoughlin Blvd Vancouver WA 98661",
    "addr:housenumber":"2155",
    "addr:postcode":"98661",
    "addr:street":"E Mcloughlin Blvd",
    "iso:country":"US",
    "sg:address":"2155 E McLoughlin Blvd",
    "sg:city":"Vancouver",
    "sg:classifiers":[
        {
            "category":"Social Services",
            "subcategory":"Child Care",
            "type":"Services"
        }
    ],
    "sg:phone":"+1 360 696 4525",
    "sg:postcode":"98661",
    "sg:province":"WA",
    "sg:tags":[
        "day"
    ],
    "wof:name":"Central Park Child Care Center",
    "wof:placetype":"venue"
},
  "geometry": {"coordinates":[-122.64927299999999,45.632259],"type":"Point"}
}