{
  "type": "Feature",
  "properties": {
    "addr:full":"20609 Bothell Everett Hwy Bothell WA 98012",
    "addr:housenumber":"20609",
    "addr:postcode":"98012",
    "addr:street":"Bothell Everett Hwy",
    "iso:country":"US",
    "sg:address":"20609 Bothell Everett Hwy",
    "sg:city":"Bothell",
    "sg:classifiers":[
        {
            "category":"Retail",
            "subcategory":"Auto Repair",
            "type":"Services"
        }
    ],
    "sg:phone":"+1 425 481 8863",
    "sg:postcode":"98012",
    "sg:province":"WA",
    "sg:tags":[
        "exhaust",
        "general",
        "automotive"
    ],
    "wof:name":"Thrashers Auto Service",
    "wof:placetype":"venue"
},
  "geometry": {"coordinates":[-122.207532,47.810805],"type":"Point"}
}