{
  "type": "Feature",
  "properties": {
    "addr:full":"110 6th St Langley WA 98260",
    "addr:housenumber":"110",
    "addr:postcode":"98260",
    "addr:street":"6Th St",
    "iso:country":"US",
    "sg:address":"110 6th St",
    "sg:city":"Langley",
    "sg:classifiers":[
        {
            "category":"Building & Trades",
            "subcategory":"Landscaping Services",
            "type":"Services"
        }
    ],
    "sg:phone":"+1 360 221 3282",
    "sg:postcode":"98260",
    "sg:province":"WA",
    "sg:tags":[
        "landscape"
    ],
    "wof:name":"Abel Fran Ldscp & Grdn Design",
    "wof:placetype":"venue"
},
  "geometry": {"coordinates":[-122.406471,48.036561],"type":"Point"}
}