{
  "type": "Feature",
  "properties": {
    "addr:full":"3323 S 9th St Tacoma WA 98405",
    "addr:housenumber":"3323",
    "addr:postcode":"98405",
    "addr:street":"S 9Th St",
    "iso:country":"US",
    "sg:address":"3323 S 9th St",
    "sg:city":"Tacoma",
    "sg:classifiers":[
        {
            "category":"Professional",
            "subcategory":"Management & Consulting",
            "type":"Services"
        }
    ],
    "sg:phone":"+1 253 473 4777",
    "sg:postcode":"98405",
    "sg:province":"WA",
    "sg:tags":[
        "business"
    ],
    "wof:name":"H Weichbrodt Assoc",
    "wof:placetype":"venue"
},
  "geometry": {"coordinates":[-122.48047800000001,47.252693],"type":"Point"}
}