{
  "type": "Feature",
  "properties": {
    "iso:country":"US",
    "sg:address":"602 Bromley Ln NE",
    "sg:city":"Olympia",
    "sg:classifiers":[
        {
            "category":"Farming",
            "subcategory":"Livestock Farm",
            "type":"Manufacturing & Wholesale Goods"
        }
    ],
    "sg:phone":"+1 360 352 2535",
    "sg:postcode":"98506",
    "sg:province":"WA",
    "sg:tags":[
        "hog",
        "or",
        "feedlot"
    ],
    "wof:name":"Bill Hammer",
    "wof:placetype":"venue"
},
  "geometry": {"coordinates":[-122.899233,47.1319],"type":"Point"}
}