{
  "type": "Feature",
  "properties": {
    "iso:country":"US",
    "sg:address":"823 16th Ave",
    "sg:city":"Lewiston",
    "sg:classifiers":[
        {
            "category":"Food & Beverages",
            "subcategory":"Candy",
            "type":"Retail Goods"
        }
    ],
    "sg:phone":"+1 208 798 3236",
    "sg:postcode":"83501",
    "sg:province":"ID",
    "sg:tags":[
        "confectionery"
    ],
    "wof:name":"Choq-O-Laut",
    "wof:placetype":"venue"
},
  "geometry": {"coordinates":[-117.021224,46.404215],"type":"Point"}
}