{
  "type": "Feature",
  "properties": {
    "addr:full":"425 S Dennis St Kennewick WA 99336",
    "addr:housenumber":"425",
    "addr:postcode":"99336",
    "addr:street":"S Dennis St",
    "iso:country":"US",
    "sg:address":"425 S Dennis St",
    "sg:city":"Kennewick",
    "sg:classifiers":[
        {
            "category":"Building & Trades",
            "subcategory":"Construction",
            "type":"Services"
        }
    ],
    "sg:phone":"+1 509 585 7687",
    "sg:postcode":"99336",
    "sg:province":"WA",
    "sg:tags":[
        "general",
        "contractor"
    ],
    "wof:name":"G H Construction",
    "wof:placetype":"venue"
},
  "geometry": {"coordinates":[-119.156976,46.204796],"type":"Point"}
}