{
  "type": "Feature",
  "properties": {
    "addr:full":"809 Washington St Vancouver WA 98660",
    "addr:housenumber":"809",
    "addr:postcode":"98660",
    "addr:street":"Washington St",
    "iso:country":"US",
    "sg:address":"809 Washington St",
    "sg:city":"Vancouver",
    "sg:classifiers":[
        {
            "category":"Shopping",
            "subcategory":"Shoes",
            "type":"Retail Goods"
        }
    ],
    "sg:phone":"+1 360 694 6143",
    "sg:postcode":"98660",
    "sg:province":"WA",
    "wof:name":"Joanne's Shoe Obsession",
    "wof:placetype":"venue"
},
  "geometry": {"coordinates":[-122.67264400000001,45.627936],"type":"Point"}
}