{
  "type": "Feature",
  "properties": {
    "addr:full":"14644 SE Eastgate Way Bellevue WA 98007",
    "addr:postcode":"14644;98007",
    "addr:street":"Se Eastgate Way",
    "iso:country":"US",
    "sg:address":"14644 SE Eastgate Way",
    "sg:city":"Bellevue",
    "sg:classifiers":[
        {
            "category":"Real Estate",
            "subcategory":"Real Estate Agent",
            "type":"Services"
        }
    ],
    "sg:phone":"+1 425 641 6018",
    "sg:postcode":"98007",
    "sg:province":"WA",
    "sg:tags":[
        "investment"
    ],
    "wof:name":"Horizon Investments Inc",
    "wof:placetype":"venue"
},
  "geometry": {"coordinates":[-122.145472,47.579793],"type":"Point"}
}