{
  "type": "Feature",
  "properties": {
    "addr:full":"4526 S 301st Dr Auburn WA 98001",
    "addr:housenumber":"4526",
    "addr:postcode":"98001",
    "addr:street":"S 301St Dr",
    "iso:country":"US",
    "sg:address":"4526 S 301st Dr",
    "sg:city":"Auburn",
    "sg:classifiers":[
        {
            "category":"Professional",
            "subcategory":"Business Services",
            "type":"Services"
        }
    ],
    "sg:phone":"+1 253 221 7900",
    "sg:postcode":"98001",
    "sg:province":"WA",
    "wof:name":"Solid Surface Design",
    "wof:placetype":"venue"
},
  "geometry": {"coordinates":[-122.27834199999999,47.330963],"type":"Point"}
}