{
  "type": "Feature",
  "properties": {
    "iso:country":"US",
    "sg:address":"1115 Wheaton Way",
    "sg:city":"Bremerton",
    "sg:classifiers":[
        {
            "category":"Retail",
            "subcategory":"Laundry & Dry Cleaning",
            "type":"Services"
        }
    ],
    "sg:phone":"+1 360 621 7153",
    "sg:postcode":"98310",
    "sg:province":"WA",
    "sg:tags":[
        "cleaners",
        "rug",
        "carpet"
    ],
    "wof:name":"Doug's Carpet Cleaning Co Inc",
    "wof:placetype":"venue"
},
  "geometry": {"coordinates":[-122.61717,47.572204],"type":"Point"}
}