{
  "type": "Feature",
  "properties": {
    "addr:full":"1722 Riverside Dr Mount Vernon WA 98273",
    "addr:housenumber":"1722",
    "addr:postcode":"98273",
    "addr:street":"Riverside Dr",
    "iso:country":"US",
    "sg:address":"1722 Riverside Dr",
    "sg:city":"Mount Vernon",
    "sg:classifiers":[
        {
            "category":"Restaurant",
            "type":"Food & Drink"
        }
    ],
    "sg:phone":"+1 360 416 3977",
    "sg:postcode":"98273",
    "sg:province":"WA",
    "sg:tags":[
        "eating"
    ],
    "wof:name":"Best Teriyaki",
    "wof:placetype":"venue"
},
  "geometry": {"coordinates":[-122.335076,48.437931],"type":"Point"}
}