{
  "type": "Feature",
  "properties": {
    "addr:full":"18516 101st Ave NE Bothell WA 98011",
    "addr:housenumber":"18516",
    "addr:postcode":"98011",
    "addr:street":"101St Ave Ne",
    "iso:country":"US",
    "sg:address":"18516 101st Ave NE",
    "sg:city":"Bothell",
    "sg:classifiers":[
        {
            "category":"Personal",
            "subcategory":"Beauty Salon",
            "type":"Services"
        }
    ],
    "sg:phone":"+1 425 481 2899",
    "sg:postcode":"98011",
    "sg:province":"WA",
    "sg:tags":[
        "shop"
    ],
    "wof:name":"Update Hair Salon",
    "wof:placetype":"venue"
},
  "geometry": {"coordinates":[-122.205675,47.762061],"type":"Point"}
}