{
  "type": "Feature",
  "properties": {
    "addr:full":"10516 Silverdale Way NW Silverdale WA 98383",
    "addr:housenumber":"10516",
    "addr:postcode":"98383",
    "addr:street":"Silverdale Way Nw",
    "iso:country":"US",
    "sg:address":"10516 Silverdale Way NW",
    "sg:city":"Silverdale",
    "sg:classifiers":[
        {
            "category":"Shopping",
            "subcategory":"Hobbies, Toys, & Games",
            "type":"Retail Goods"
        },
        {
            "category":"Shopping",
            "subcategory":"Catalog Store",
            "type":"Retail Goods"
        }
    ],
    "sg:phone":"+1 360 337 2737",
    "sg:postcode":"98383",
    "sg:province":"WA",
    "sg:tags":[
        "craft",
        "art",
        "supply"
    ],
    "wof:name":"Daniel Smith Artist Materials",
    "wof:placetype":"venue"
},
  "geometry": {"coordinates":[-122.687376,47.656846],"type":"Point"}
}