{
  "type": "Feature",
  "properties": {
    "addr:full":"726 Shipmaster Ct Moses Lake WA 98837",
    "addr:housenumber":"726",
    "addr:postcode":"98837",
    "addr:street":"Shipmaster Ct",
    "iso:country":"US",
    "sg:address":"726 Shipmaster Ct",
    "sg:city":"Moses Lake",
    "sg:classifiers":[
        {
            "category":"Real Estate",
            "subcategory":"Real Estate Agent",
            "type":"Services"
        }
    ],
    "sg:phone":"+1 509 765 0740",
    "sg:postcode":"98837",
    "sg:province":"WA",
    "wof:name":"Summerhurst LLC",
    "wof:placetype":"venue"
},
  "geometry": {"coordinates":[-119.33846800000001,47.111439],"type":"Point"}
}