{
  "type": "Feature",
  "properties": {
    "addr:full":"9506 Canyon Rd E Puyallup WA 98371",
    "addr:housenumber":"9506",
    "addr:postcode":"98371",
    "addr:street":"Canyon Rd E",
    "iso:country":"US",
    "sg:address":"9506 Canyon Rd E",
    "sg:city":"Puyallup",
    "sg:classifiers":[
        {
            "category":"Professional",
            "type":"Services"
        }
    ],
    "sg:phone":"+1 253 537 2807",
    "sg:postcode":"98371",
    "sg:province":"WA",
    "wof:name":"Pine Tech Building Services",
    "wof:placetype":"venue"
},
  "geometry": {"coordinates":[-122.357164,47.170674],"type":"Point"}
}