{
  "type": "Feature",
  "properties": {
    "addr:full":"1200 Post Aly Seattle WA 98101",
    "addr:housenumber":"1200",
    "addr:postcode":"98101",
    "addr:street":"Post Aly",
    "iso:country":"US",
    "sg:address":"1200 Post Aly",
    "sg:city":"Seattle",
    "sg:classifiers":[
        {
            "category":"Professional",
            "subcategory":"Advertising",
            "type":"Services"
        }
    ],
    "sg:phone":"+1 206 467 1174",
    "sg:postcode":"98101",
    "sg:province":"WA",
    "sg:tags":[
        "counselor"
    ],
    "sg:website":"www.strikeplate.com",
    "wof:name":"Cartier Copy Writing",
    "wof:placetype":"venue"
},
  "geometry": {"coordinates":[-122.33878,47.606604],"type":"Point"}
}