{
  "type": "Feature",
  "properties": {
    "addr:full":"2019 Commercial Ave Anacortes WA 98221",
    "addr:housenumber":"2019",
    "addr:postcode":"98221",
    "addr:street":"Commercial Ave",
    "iso:country":"US",
    "sg:address":"2019 Commercial Ave",
    "sg:city":"Anacortes",
    "sg:classifiers":[
        {
            "category":"Travel",
            "subcategory":"Hotels & Motels",
            "type":"Entertainment"
        }
    ],
    "sg:phone":"+1 360 293 2655",
    "sg:postcode":"98221",
    "sg:province":"WA",
    "wof:name":"Gateway Motel",
    "wof:placetype":"venue"
},
  "geometry": {"coordinates":[-122.61260299999999,48.505956],"type":"Point"}
}