{
  "type": "Feature",
  "properties": {
    "addr:full":"3663 Pacific Ave SE Ste D Olympia WA 98501",
    "addr:housenumber":"3663",
    "addr:postcode":"98501",
    "addr:street":"Pacific Ave Se Ste D",
    "iso:country":"US",
    "sg:address":"3663 Pacific Ave SE Ste D",
    "sg:city":"Olympia",
    "sg:classifiers":[
        {
            "category":"Bars & Pubs",
            "type":"Food & Drink"
        },
        {
            "category":"Restaurant",
            "type":"Food & Drink"
        },
        {
            "category":"Bars & Pubs",
            "subcategory":"Sports Bar",
            "type":"Food & Drink"
        }
    ],
    "sg:phone":"+1 360 455 0352",
    "sg:postcode":"98501",
    "sg:province":"WA",
    "sg:tags":[
        "tavern",
        "brew",
        "hall",
        "pool"
    ],
    "wof:name":"Frankie's Sports Bar & Grill",
    "wof:placetype":"venue"
},
  "geometry": {"coordinates":[-122.84270100000001,47.041419],"type":"Point"}
}