{
  "type": "Feature",
  "properties": {
    "addr:full":"146 E Wiser Lake Rd Lynden WA 98264",
    "addr:housenumber":"146",
    "addr:postcode":"98264",
    "addr:street":"E Wiser Lake Rd",
    "iso:country":"US",
    "sg:address":"146 E Wiser Lake Rd",
    "sg:city":"Lynden",
    "sg:classifiers":[
        {
            "category":"Health Services",
            "subcategory":"Nursing And Care Facility",
            "type":"Services"
        }
    ],
    "sg:phone":"+1 360 354 4534",
    "sg:postcode":"98264",
    "sg:province":"WA",
    "wof:name":"Cdp Health Service",
    "wof:placetype":"venue"
},
  "geometry": {"coordinates":[-122.484297,48.906798],"type":"Point"}
}