{
  "type": "Feature",
  "properties": {
    "addr:full":"502 Main St Mattawa WA 99323",
    "addr:housenumber":"502",
    "addr:postcode":"99323",
    "addr:street":"Main St",
    "iso:country":"US",
    "sg:address":"502 Main St",
    "sg:city":"Mattawa",
    "sg:classifiers":[
        {
            "category":"Real Estate",
            "subcategory":"Real Estate Agent",
            "type":"Services"
        }
    ],
    "sg:phone":"+1 509 932 4101",
    "sg:postcode":"99323",
    "sg:province":"WA",
    "wof:name":"Desert Aire Sales Office",
    "wof:placetype":"venue"
},
  "geometry": {"coordinates":[-119.01402899999999,46.1991],"type":"Point"}
}