{
  "type": "Feature",
  "properties": {
    "addr:full":"108 218th Pl SE Bothell WA 98021",
    "addr:housenumber":"108",
    "addr:postcode":"98021",
    "addr:street":"218Th Pl Se",
    "iso:country":"US",
    "sg:address":"108 218th Pl SE",
    "sg:city":"Bothell",
    "sg:classifiers":[
        {
            "category":"Building & Trades",
            "subcategory":"Construction",
            "type":"Services"
        }
    ],
    "sg:phone":"+1 425 486 9308",
    "sg:postcode":"98021",
    "sg:province":"WA",
    "sg:tags":[
        "house"
    ],
    "wof:name":"Brets Handyman Services",
    "wof:placetype":"venue"
},
  "geometry": {"coordinates":[-122.232477,47.800351],"type":"Point"}
}