{
  "type": "Feature",
  "properties": {
    "addr:full":"2200 Rimland Dr Suite 220 Bellingham WA 98226",
    "addr:housenumber":"2200",
    "addr:postcode":"98226",
    "addr:street":"Rimland Dr Suite 220",
    "iso:country":"US",
    "sg:address":"2200 Rimland Dr Suite 220",
    "sg:city":"Bellingham",
    "sg:classifiers":[
        {
            "category":"Professional",
            "subcategory":"Lawyer & Legal Services",
            "type":"Services"
        }
    ],
    "sg:phone":"+1 866 972 8430",
    "sg:postcode":"98226",
    "sg:province":"WA",
    "sg:tags":[
        "attorney",
        "law",
        "business",
        "contract"
    ],
    "sg:website":"http://www.genemoses.net",
    "wof:name":"Moses Gene Law Office Of",
    "wof:placetype":"venue"
},
  "geometry": {"coordinates":[-122.44534299999999,48.773159],"type":"Point"}
}