{
  "type": "Feature",
  "properties": {
    "iso:country":"US",
    "sg:address":"6202 S 249th St",
    "sg:city":"Kent",
    "sg:classifiers":[
        {
            "category":"Social Services",
            "subcategory":"Child Care",
            "type":"Services"
        }
    ],
    "sg:phone":"+1 253 850 4343",
    "sg:postcode":"98032",
    "sg:province":"WA",
    "sg:tags":[
        "day"
    ],
    "wof:name":"Great Bginnings Child Care Ctr",
    "wof:placetype":"venue"
},
  "geometry": {"coordinates":[-122.25622199999999,47.378286],"type":"Point"}
}