{
  "type": "Feature",
  "properties": {
    "addr:full":"255983 Hwy 101 Port Angeles WA 98362",
    "addr:housenumber":"255983",
    "addr:postcode":"98362",
    "addr:street":"Hwy 101",
    "iso:country":"US",
    "sg:address":"255983 Hwy 101",
    "sg:city":"Port Angeles",
    "sg:classifiers":[
        {
            "category":"Wholesale",
            "subcategory":"Construction Materials",
            "type":"Manufacturing & Wholesale Goods"
        }
    ],
    "sg:phone":"+1 360 452 6515",
    "sg:postcode":"98362",
    "sg:province":"WA",
    "sg:tags":[
        "rock"
    ],
    "wof:name":"Lakeside Industries Blue Mtn",
    "wof:placetype":"venue"
},
  "geometry": {"coordinates":[-123.28419599999999,48.094766],"type":"Point"}
}