{
  "type": "Feature",
  "properties": {
    "addr:full":"1110 NE 143rd Ave Vancouver WA 98684",
    "addr:housenumber":"1110",
    "addr:postcode":"98684",
    "addr:street":"Ne 143Rd Ave",
    "iso:country":"US",
    "sg:address":"1110 NE 143rd Ave",
    "sg:city":"Vancouver",
    "sg:classifiers":[
        {
            "category":"Building & Trades",
            "subcategory":"Construction",
            "type":"Services"
        }
    ],
    "sg:phone":"+1 360 521 5859",
    "sg:postcode":"98684",
    "sg:province":"WA",
    "sg:tags":[
        "residential"
    ],
    "wof:name":"V Z Enterprises",
    "wof:placetype":"venue"
},
  "geometry": {"coordinates":[-122.525487,45.631212],"type":"Point"}
}