{
  "type": "Feature",
  "properties": {
    "addr:full":"33128 Sultan Basin Rd Sultan WA 98294",
    "addr:postcode":"33128;98294",
    "addr:street":"Sultan Basin Rd",
    "iso:country":"US",
    "sg:address":"33128 Sultan Basin Rd",
    "sg:city":"Sultan",
    "sg:classifiers":[
        {
            "category":"Education",
            "subcategory":"Special Training",
            "type":"Public Place"
        }
    ],
    "sg:phone":"+1 360 793 1495",
    "sg:postcode":"98294",
    "sg:province":"WA",
    "wof:name":"Rosemarys Piano",
    "wof:placetype":"venue"
},
  "geometry": {"coordinates":[-121.788129,47.897704],"type":"Point"}
}