{
  "type": "Feature",
  "properties": {
    "addr:full":"1890 Westside Hwy Kelso WA 98626",
    "addr:housenumber":"1890",
    "addr:postcode":"98626",
    "addr:street":"Westside Hwy",
    "iso:country":"US",
    "sg:address":"1890 Westside Hwy",
    "sg:city":"Kelso",
    "sg:classifiers":[
        {
            "category":"Freight",
            "type":"Transportation"
        }
    ],
    "sg:phone":"+1 360 425 9887",
    "sg:postcode":"98626",
    "sg:province":"WA",
    "sg:tags":[
        "operator",
        "local",
        "trucking"
    ],
    "wof:name":"James Gaston Trucking",
    "wof:placetype":"venue"
},
  "geometry": {"coordinates":[-122.90793499999999,46.192285],"type":"Point"}
}