{
  "type": "Feature",
  "properties": {
    "iso:country":"US",
    "sg:address":"9804 NE 15th St",
    "sg:city":"Vancouver",
    "sg:classifiers":[
        {
            "category":"Manufacturing",
            "subcategory":"Metals",
            "type":"Manufacturing & Wholesale Goods"
        }
    ],
    "sg:phone":"+1 360 256 9297",
    "sg:postcode":"98664",
    "sg:province":"WA",
    "wof:name":"Paicfic Engraving Co",
    "wof:placetype":"venue"
},
  "geometry": {"coordinates":[-122.57154300000001,45.63333],"type":"Point"}
}