{
  "type": "Feature",
  "properties": {
    "iso:country":"US",
    "sg:address":"14611 Ambaum Blvd SW",
    "sg:city":"Seattle",
    "sg:classifiers":[
        {
            "category":"Utilities",
            "subcategory":"Natural Gas",
            "type":"Services"
        }
    ],
    "sg:phone":"+1 206 244 2955",
    "sg:postcode":"98166",
    "sg:province":"WA",
    "wof:name":"Pacific Rim Oxygen Service",
    "wof:placetype":"venue"
},
  "geometry": {"coordinates":[-122.347049,47.470555],"type":"Point"}
}