{
  "type": "Feature",
  "properties": {
    "addr:full":"4504 S Caballo Rd Kennewick WA 99338",
    "addr:housenumber":"4504",
    "addr:postcode":"99338",
    "addr:street":"S Caballo Rd",
    "iso:country":"US",
    "sg:address":"4504 S Caballo Rd",
    "sg:city":"Kennewick",
    "sg:classifiers":[
        {
            "category":"Wholesale",
            "subcategory":"Vending Machines",
            "type":"Manufacturing & Wholesale Goods"
        }
    ],
    "sg:phone":"+1 509 627 4154",
    "sg:postcode":"99338",
    "sg:province":"WA",
    "sg:tags":[
        "operator"
    ],
    "wof:name":"E B Roberts Enterprises",
    "wof:placetype":"venue"
},
  "geometry": {"coordinates":[-119.29306800000001,46.206398],"type":"Point"}
}