{
  "type": "Feature",
  "properties": {
    "addr:full":"23724 SE 436th St Enumclaw WA 98022",
    "addr:housenumber":"23724",
    "addr:postcode":"98022",
    "addr:street":"Se 436Th St",
    "iso:country":"US",
    "sg:address":"23724 SE 436th St",
    "sg:city":"Enumclaw",
    "sg:classifiers":[
        {
            "category":"Professional",
            "subcategory":"Management & Consulting",
            "type":"Services"
        }
    ],
    "sg:phone":"+1 360 825 6815",
    "sg:postcode":"98022",
    "sg:province":"WA",
    "sg:tags":[
        "business"
    ],
    "wof:name":"Hopkins Larinda Inc",
    "wof:placetype":"venue"
},
  "geometry": {"coordinates":[-122.02619900000001,47.210229],"type":"Point"}
}