{
  "type": "Feature",
  "properties": {
    "addr:full":"5130 Regan Rd Cashmere WA 98815",
    "addr:housenumber":"5130",
    "addr:postcode":"98815",
    "addr:street":"Regan Rd",
    "iso:country":"US",
    "sg:address":"5130 Regan Rd",
    "sg:city":"Cashmere",
    "sg:classifiers":[
        {
            "category":"Building & Trades",
            "subcategory":"Construction",
            "type":"Services"
        }
    ],
    "sg:phone":"+1 509 782 5660",
    "sg:postcode":"98815",
    "sg:province":"WA",
    "sg:tags":[
        "stucco",
        "contractor"
    ],
    "wof:name":"Complete Plastering Number Two",
    "wof:placetype":"venue"
},
  "geometry": {"coordinates":[-120.474968,47.511343],"type":"Point"}
}