{
  "type": "Feature",
  "properties": {
    "addr:full":"193 S Market Blvd Chehalis WA 98532",
    "addr:housenumber":"193",
    "addr:postcode":"98532",
    "addr:street":"S Market Blvd",
    "iso:country":"US",
    "sg:address":"193 S Market Blvd",
    "sg:city":"Chehalis",
    "sg:classifiers":[
        {
            "category":"Health Services",
            "subcategory":"Doctor",
            "type":"Services"
        }
    ],
    "sg:phone":"+1 360 748 3366",
    "sg:postcode":"98532",
    "sg:province":"WA",
    "sg:tags":[
        "physician",
        "surgeon"
    ],
    "wof:name":"Northwest Pediatric Ctr",
    "wof:placetype":"venue"
},
  "geometry": {"coordinates":[-122.962548,46.660303],"type":"Point"}
}