{
  "type": "Feature",
  "properties": {
    "addr:full":"10436 Aqua Way S Seattle WA 98168",
    "addr:housenumber":"10436",
    "addr:postcode":"98168",
    "addr:street":"Aqua Way S",
    "iso:country":"US",
    "sg:address":"10436 Aqua Way S",
    "sg:city":"Seattle",
    "sg:classifiers":[
        {
            "category":"Building & Trades",
            "subcategory":"Locksmith",
            "type":"Services"
        }
    ],
    "sg:phone":"+1 206 701 6638",
    "sg:postcode":"98168",
    "sg:province":"WA",
    "sg:tags":[
        "key"
    ],
    "wof:name":"Locksmith 0 & 0 24 Hour",
    "wof:placetype":"venue"
},
  "geometry": {"coordinates":[-122.327551,47.51013],"type":"Point"}
}