{
  "type": "Feature",
  "properties": {
    "addr:full":"4335 Leary Way NW Seattle WA 98107",
    "addr:housenumber":"4335",
    "addr:postcode":"98107",
    "addr:street":"Leary Way Nw",
    "iso:country":"US",
    "sg:address":"4335 Leary Way NW",
    "sg:city":"Seattle",
    "sg:classifiers":[
        {
            "category":"Professional",
            "subcategory":"Business Services",
            "type":"Services"
        }
    ],
    "sg:phone":"+1 206 784 8284",
    "sg:postcode":"98107",
    "sg:province":"WA",
    "wof:name":"Nwts Inc",
    "wof:placetype":"venue"
},
  "geometry": {"coordinates":[-122.36556299999999,47.659573],"type":"Point"}
}