{
  "type": "Feature",
  "properties": {
    "addr:full":"2719 NE 93rd Ave Vancouver WA 98662",
    "addr:housenumber":"2719",
    "addr:postcode":"98662",
    "addr:street":"Ne 93Rd Ave",
    "iso:country":"US",
    "sg:address":"2719 NE 93rd Ave",
    "sg:city":"Vancouver",
    "sg:classifiers":[
        {
            "category":"Food & Beverages",
            "subcategory":"Farmers Market",
            "type":"Retail Goods"
        }
    ],
    "sg:phone":"+1 360 256 6252",
    "sg:postcode":"98662",
    "sg:province":"WA",
    "sg:tags":[
        "vegetable",
        "fruit",
        "shipper",
        "grower"
    ],
    "wof:name":"George F Schumaker",
    "wof:placetype":"venue"
},
  "geometry": {"coordinates":[-122.577237,45.641932],"type":"Point"}
}