{
  "type": "Feature",
  "properties": {
    "iso:country":"US",
    "sg:address":"31607 118th Pl SE",
    "sg:city":"Auburn",
    "sg:classifiers":[
        {
            "category":"Building & Trades",
            "subcategory":"Cleaning & Sanitation",
            "type":"Services"
        }
    ],
    "sg:phone":"+1 253 939 5645",
    "sg:postcode":"98092",
    "sg:province":"WA",
    "sg:tags":[
        "maintenance"
    ],
    "wof:name":"Ticas Cleaning",
    "wof:placetype":"venue"
},
  "geometry": {"coordinates":[-122.183891,47.317794],"type":"Point"}
}