{
  "type": "Feature",
  "properties": {
    "addr:full":"8405 NE 14th Ln Vancouver WA 98664",
    "addr:housenumber":"8405",
    "addr:postcode":"98664",
    "addr:street":"Ne 14Th Ln",
    "iso:country":"US",
    "sg:address":"8405 NE 14th Ln",
    "sg:city":"Vancouver",
    "sg:classifiers":[
        {
            "category":"Building & Trades",
            "subcategory":"Landscaping Services",
            "type":"Services"
        }
    ],
    "sg:phone":"+1 360 326 3852",
    "sg:postcode":"98664",
    "sg:province":"WA",
    "sg:tags":[
        "landscape"
    ],
    "wof:name":"Felipeslandscaping",
    "wof:placetype":"venue"
},
  "geometry": {"coordinates":[-122.587232,45.632579],"type":"Point"}
}