{
  "type": "Feature",
  "properties": {
    "addr:full":"114 E Magnolia St Bellingham WA 98225",
    "addr:housenumber":"114",
    "addr:postcode":"98225",
    "addr:street":"E Magnolia St",
    "iso:country":"US",
    "sg:address":"114 E Magnolia St",
    "sg:city":"Bellingham",
    "sg:classifiers":[
        {
            "category":"Shopping",
            "subcategory":"Gifts & Souvenirs",
            "type":"Retail Goods"
        }
    ],
    "sg:phone":"+1 360 671 1077",
    "sg:postcode":"98225",
    "sg:province":"WA",
    "wof:name":"Zephyr C Ds & Gifts",
    "wof:placetype":"venue"
},
  "geometry": {"coordinates":[-122.476872,48.750236],"type":"Point"}
}