{
  "type": "Feature",
  "properties": {
    "iso:country":"US",
    "sg:address":"2200 Division St",
    "sg:city":"Bellingham",
    "sg:classifiers":[
        {
            "category":"Organizations",
            "subcategory":"Professional Association",
            "type":"Services"
        }
    ],
    "sg:phone":"+1 360 738 4941",
    "sg:postcode":"98226",
    "sg:province":"WA",
    "sg:tags":[
        "business"
    ],
    "wof:name":"Curnic Trading Co LLC",
    "wof:placetype":"venue"
},
  "geometry": {"coordinates":[-122.445589,48.782074],"type":"Point"}
}