{
  "type": "Feature",
  "properties": {
    "addr:full":"21003 E Trent Ave Otis Orchards WA 99027",
    "addr:housenumber":"21003",
    "addr:postcode":"99027",
    "addr:street":"E Trent Ave",
    "iso:country":"US",
    "sg:address":"21003 E Trent Ave",
    "sg:city":"Otis Orchards",
    "sg:classifiers":[
        {
            "category":"Retail",
            "subcategory":"Auto Repair",
            "type":"Services"
        }
    ],
    "sg:phone":"+1 509 891 0592",
    "sg:postcode":"99027",
    "sg:province":"WA",
    "sg:tags":[
        "general"
    ],
    "wof:name":"Three C Auto",
    "wof:placetype":"venue"
},
  "geometry": {"coordinates":[-117.13179599999999,47.704905],"type":"Point"}
}