{
  "type": "Feature",
  "properties": {
    "addr:full":"4616 25th Ave NE #701 Seattle WA 98105",
    "addr:housenumber":"4616",
    "addr:postcode":"98105",
    "addr:street":"25Th Ave Ne # 701",
    "iso:country":"US",
    "sg:address":"4616 25th Ave NE #701",
    "sg:city":"Seattle",
    "sg:classifiers":[
        {
            "category":"Real Estate",
            "subcategory":"Real Estate Services",
            "type":"Services"
        }
    ],
    "sg:phone":"+1 206 985 7275",
    "sg:postcode":"98105",
    "sg:province":"WA",
    "sg:tags":[
        "management",
        "property"
    ],
    "wof:name":"Joel Erlitz",
    "wof:placetype":"venue"
},
  "geometry": {"coordinates":[-122.30086300000001,47.66274],"type":"Point"}
}