{
  "type": "Feature",
  "properties": {
    "addr:full":"1501 E Olive Way Seattle WA 98127",
    "addr:housenumber":"1501",
    "addr:postcode":"98127",
    "addr:street":"E Olive Way",
    "iso:country":"US",
    "sg:address":"1501 E Olive Way",
    "sg:city":"Seattle",
    "sg:classifiers":[
        {
            "category":"Bars & Pubs",
            "type":"Food & Drink"
        },
        {
            "category":"Restaurant",
            "type":"Food & Drink"
        }
    ],
    "sg:phone":"+1 206 709 8079",
    "sg:postcode":"98127",
    "sg:province":"WA",
    "sg:tags":[
        "irish"
    ],
    "wof:name":"Clever Dunnes Irish Pub",
    "wof:placetype":"venue"
},
  "geometry": {"coordinates":[-122.325996,47.617802],"type":"Point"}
}