{
  "type": "Feature",
  "properties": {
    "addr:full":"5313 Hillview Rd Sumas WA 98295",
    "addr:housenumber":"5313",
    "addr:postcode":"98295",
    "addr:street":"Hillview Rd",
    "iso:country":"US",
    "sg:address":"5313 Hillview Rd",
    "sg:city":"Sumas",
    "sg:classifiers":[
        {
            "category":"Farming",
            "subcategory":"Farm & Veterinary Services",
            "type":"Manufacturing & Wholesale Goods"
        }
    ],
    "sg:phone":"+1 360 988 8255",
    "sg:postcode":"98295",
    "sg:province":"WA",
    "sg:tags":[
        "livestock"
    ],
    "wof:name":"Bos Hay",
    "wof:placetype":"venue"
},
  "geometry": {"coordinates":[-122.21049600000001,48.982591],"type":"Point"}
}