{
  "type": "Feature",
  "properties": {
    "addr:full":"6274 20th Ave NE Seattle WA 98115",
    "addr:housenumber":"6274",
    "addr:postcode":"98115",
    "addr:street":"20Th Ave Ne",
    "iso:country":"US",
    "sg:address":"6274 20th Ave NE",
    "sg:city":"Seattle",
    "sg:classifiers":[
        {
            "category":"Professional",
            "subcategory":"Management & Consulting",
            "type":"Services"
        }
    ],
    "sg:phone":"+1 206 527 0222",
    "sg:postcode":"98115",
    "sg:province":"WA",
    "sg:tags":[
        "consultants-referral",
        "aerospace"
    ],
    "wof:name":"Optimal Aerospace",
    "wof:placetype":"venue"
},
  "geometry": {"coordinates":[-122.30650300000001,47.67424],"type":"Point"}
}