{
  "type": "Feature",
  "properties": {
    "addr:full":"10175 Lonerock Ln NW Seabeck WA 98380",
    "addr:housenumber":"10175",
    "addr:postcode":"98380",
    "addr:street":"Lonerock Ln Nw",
    "iso:country":"US",
    "sg:address":"10175 Lonerock Ln NW",
    "sg:city":"Seabeck",
    "sg:classifiers":[
        {
            "category":"Transit Center",
            "subcategory":"Freight",
            "type":"Transportation"
        },
        {
            "category":"Freight",
            "type":"Transportation"
        }
    ],
    "sg:phone":"+1 360 621 9188",
    "sg:postcode":"98380",
    "sg:province":"WA",
    "sg:tags":[
        "local",
        "trucking-motor",
        "trucking"
    ],
    "wof:name":"Blue Tick Trucking",
    "wof:placetype":"venue"
},
  "geometry": {"coordinates":[-122.787065,47.655172],"type":"Point"}
}