{
  "type": "Feature",
  "properties": {
    "iso:country":"US",
    "sg:address":"7901 S Hosmer St",
    "sg:city":"Tacoma",
    "sg:classifiers":[
        {
            "category":"Shopping",
            "subcategory":"Hobbies, Toys, & Games",
            "type":"Retail Goods"
        }
    ],
    "sg:phone":"+1 253 473 6223",
    "sg:postcode":"98408",
    "sg:province":"WA",
    "sg:tags":[
        "model",
        "supply"
    ],
    "sg:website":"www.fantasyworldhobbies.com",
    "wof:name":"Fantasy World Discount Hobbies",
    "wof:placetype":"venue"
},
  "geometry": {"coordinates":[-122.462677,47.187268],"type":"Point"}
}