{
  "type": "Feature",
  "properties": {
    "addr:full":"2011 E 18th Ave Spokane WA 99203",
    "addr:housenumber":"2011",
    "addr:postcode":"99203",
    "addr:street":"E 18Th Ave",
    "iso:country":"US",
    "sg:address":"2011 E 18th Ave",
    "sg:city":"Spokane",
    "sg:classifiers":[
        {
            "category":"Organizations",
            "subcategory":"Membership Organization",
            "type":"Services"
        }
    ],
    "sg:phone":"+1 509 536 7823",
    "sg:postcode":"99203",
    "sg:province":"WA",
    "sg:tags":[
        "club"
    ],
    "wof:name":"Stephen R Novak Foundat",
    "wof:placetype":"venue"
},
  "geometry": {"coordinates":[-117.381109,47.638828],"type":"Point"}
}