{
  "type": "Feature",
  "properties": {
    "addr:full":"9103 Bridgeport Way SW Lakewood WA 98499",
    "addr:housenumber":"9103",
    "addr:postcode":"98499",
    "addr:street":"Bridgeport Way Sw",
    "iso:country":"US",
    "sg:address":"9103 Bridgeport Way SW",
    "sg:city":"Lakewood",
    "sg:classifiers":[
        {
            "category":"Real Estate",
            "subcategory":"Real Estate Agent",
            "type":"Services"
        }
    ],
    "sg:phone":"+1 253 879 0202",
    "sg:postcode":"98499",
    "sg:province":"WA",
    "wof:name":"Gibson Northwest Real Estate",
    "wof:placetype":"venue"
},
  "geometry": {"coordinates":[-122.51836900000001,47.174387],"type":"Point"}
}