{
  "type": "Feature",
  "properties": {
    "iso:country":"US",
    "sg:address":"642 Thompson Dr",
    "sg:city":"Sunnyside",
    "sg:classifiers":[
        {
            "category":"Farming",
            "subcategory":"Vineyard",
            "type":"Manufacturing & Wholesale Goods"
        }
    ],
    "sg:phone":"+1 509 836 0696",
    "sg:postcode":"98944",
    "sg:province":"WA",
    "sg:tags":[
        "grape"
    ],
    "wof:name":"Kendall Farms",
    "wof:placetype":"venue"
},
  "geometry": {"coordinates":[-120.026595,46.321936],"type":"Point"}
}