{
  "type": "Feature",
  "properties": {
    "addr:full":"11511 133rd St E Puyallup WA 98374",
    "addr:housenumber":"11511",
    "addr:postcode":"98374",
    "addr:street":"133Rd St E",
    "iso:country":"US",
    "sg:address":"11511 133rd St E",
    "sg:city":"Puyallup",
    "sg:classifiers":[
        {
            "category":"Wholesale",
            "subcategory":"Stationery",
            "type":"Manufacturing & Wholesale Goods"
        }
    ],
    "sg:phone":"+1 253 841 6809",
    "sg:postcode":"98374",
    "sg:province":"WA",
    "sg:tags":[
        "supply"
    ],
    "wof:name":"J&J Ink",
    "wof:placetype":"venue"
},
  "geometry": {"coordinates":[-122.27536600000001,47.135289],"type":"Point"}
}