{
  "type": "Feature",
  "properties": {
    "addr:full":"3139 Maplewood Cir NE Tacoma WA 98422",
    "addr:housenumber":"3139",
    "addr:postcode":"98422",
    "addr:street":"Maplewood Cir Ne",
    "iso:country":"US",
    "sg:address":"3139 Maplewood Cir NE",
    "sg:city":"Tacoma",
    "sg:classifiers":[
        {
            "category":"Building & Trades",
            "subcategory":"Construction",
            "type":"Services"
        }
    ],
    "sg:phone":"+1 253 537 1753",
    "sg:postcode":"98422",
    "sg:province":"WA",
    "sg:tags":[
        "painting",
        "contractor"
    ],
    "wof:name":"Greg M Anderson",
    "wof:placetype":"venue"
},
  "geometry": {"coordinates":[-122.403037,47.304273],"type":"Point"}
}