{
  "type": "Feature",
  "properties": {
    "addr:full":"1611 E 19th Ave Spokane WA 99203",
    "addr:housenumber":"1611",
    "addr:postcode":"99203",
    "addr:street":"E 19Th Ave",
    "iso:country":"US",
    "sg:address":"1611 E 19th Ave",
    "sg:city":"Spokane",
    "sg:classifiers":[
        {
            "category":"Professional",
            "subcategory":"Business Services",
            "type":"Services"
        }
    ],
    "sg:phone":"+1 509 534 1314",
    "sg:postcode":"99203",
    "sg:province":"WA",
    "sg:tags":[
        "fund",
        "games",
        "raising",
        "merchandise",
        "supply"
    ],
    "wof:name":"Ager Consulting Company",
    "wof:placetype":"venue"
},
  "geometry": {"coordinates":[-117.387005,47.637805],"type":"Point"}
}