{
  "type": "Feature",
  "properties": {
    "addr:full":"2102 N Pearl St Tacoma WA 98406",
    "addr:housenumber":"2102",
    "addr:postcode":"98406",
    "addr:street":"N Pearl St",
    "iso:country":"US",
    "sg:address":"2102 N Pearl St",
    "sg:city":"Tacoma",
    "sg:classifiers":[
        {
            "category":"Insurance",
            "subcategory":"Insurance Agent",
            "type":"Services"
        },
        {
            "category":"Insurance",
            "subcategory":"Hazard Insurance",
            "type":"Services"
        },
        {
            "category":"Insurance",
            "subcategory":"Title Insurance",
            "type":"Services"
        },
        {
            "category":"Insurance",
            "subcategory":"Life Insurance",
            "type":"Services"
        }
    ],
    "sg:phone":"+1 253 759 9999",
    "sg:postcode":"98406",
    "sg:province":"WA",
    "sg:tags":[
        "business",
        "auto",
        "commercial",
        "homeowner",
        "motorcycle",
        "renter"
    ],
    "wof:name":"Allstate Insurance Company - Melody Williams",
    "wof:placetype":"venue"
},
  "geometry": {"coordinates":[-122.515991,47.267131],"type":"Point"}
}