{
  "type": "Feature",
  "properties": {
    "iso:country":"US",
    "sg:address":"28839 Military Rd S",
    "sg:city":"Federal Way",
    "sg:classifiers":[
        {
            "category":"Banks & Credit Unions",
            "subcategory":"Bank",
            "type":"Services"
        }
    ],
    "sg:phone":"+1 206 292 3314",
    "sg:postcode":"98003",
    "sg:province":"WA",
    "sg:tags":[
        "state"
    ],
    "wof:name":"Wells Fargo",
    "wof:placetype":"venue"
},
  "geometry": {"coordinates":[-122.301276,47.342945],"type":"Point"}
}