{
  "type": "Feature",
  "properties": {
    "addr:full":"3443 Evergreen Point Rd Medina WA 98039",
    "addr:housenumber":"3443",
    "addr:postcode":"98039",
    "addr:street":"Evergreen Point Rd",
    "iso:country":"US",
    "sg:address":"3443 Evergreen Point Rd",
    "sg:city":"Medina",
    "sg:classifiers":[
        {
            "category":"Building & Trades",
            "subcategory":"Construction",
            "type":"Services"
        }
    ],
    "sg:phone":"+1 425 637 2663",
    "sg:postcode":"98039",
    "sg:province":"WA",
    "sg:tags":[
        "contractor"
    ],
    "wof:name":"Tom Braaten Construction Inc",
    "wof:placetype":"venue"
},
  "geometry": {"coordinates":[-122.23857599999999,47.641583],"type":"Point"}
}