{
  "type": "Feature",
  "properties": {
    "addr:full":"10407 244th St E Graham WA 98338",
    "addr:housenumber":"10407",
    "addr:postcode":"98338",
    "addr:street":"244Th St E",
    "iso:country":"US",
    "sg:address":"10407 244th St E",
    "sg:city":"Graham",
    "sg:classifiers":[
        {
            "category":"Utilities",
            "subcategory":"Water",
            "type":"Services"
        }
    ],
    "sg:phone":"+1 253 847 8617",
    "sg:postcode":"98338",
    "sg:province":"WA",
    "sg:tags":[
        "company",
        "sewage"
    ],
    "wof:name":"Graham Hill Mutual Water Co",
    "wof:placetype":"venue"
},
  "geometry": {"coordinates":[-122.294158,47.034998],"type":"Point"}
}