{
  "type": "Feature",
  "properties": {
    "iso:country":"US",
    "sg:address":"207 4th Ave SE",
    "sg:city":"Puyallup",
    "sg:classifiers":[
        {
            "category":"Real Estate",
            "subcategory":"Architect",
            "type":"Services"
        }
    ],
    "sg:phone":"+1 253 840 9405",
    "sg:postcode":"98372",
    "sg:province":"WA",
    "wof:name":"Ross Deckman Architect",
    "wof:placetype":"venue"
},
  "geometry": {"coordinates":[-122.29131,47.188454],"type":"Point"}
}