{
  "type": "Feature",
  "properties": {
    "addr:full":"114 W Magnolia St Centralia WA 98531",
    "addr:housenumber":"114",
    "addr:postcode":"98531",
    "addr:street":"W Magnolia St",
    "iso:country":"US",
    "sg:address":"114 W Magnolia St",
    "sg:city":"Centralia",
    "sg:classifiers":[
        {
            "category":"Professional",
            "subcategory":"Lawyer & Legal Services",
            "type":"Services"
        }
    ],
    "sg:phone":"+1 360 736 1301",
    "sg:postcode":"98531",
    "sg:province":"WA",
    "sg:tags":[
        "attorney"
    ],
    "wof:name":"Olson Althauser Lawler",
    "wof:placetype":"venue"
},
  "geometry": {"coordinates":[-122.954615,46.718271],"type":"Point"}
}