{
  "type": "Feature",
  "properties": {
    "addr:full":"2017 S 7th Ave Yakima WA 98903",
    "addr:housenumber":"2017",
    "addr:postcode":"98903",
    "addr:street":"S 7Th Ave",
    "iso:country":"US",
    "sg:address":"2017 S 7th Ave",
    "sg:city":"Yakima",
    "sg:classifiers":[
        {
            "category":"Manufacturing",
            "subcategory":"Toys & Sporting Goods",
            "type":"Manufacturing & Wholesale Goods"
        }
    ],
    "sg:phone":"+1 509 575 7793",
    "sg:postcode":"98903",
    "sg:province":"WA",
    "sg:tags":[
        "mfg"
    ],
    "wof:name":"Skipper Stopper LLC",
    "wof:placetype":"venue"
},
  "geometry": {"coordinates":[-120.516032,46.567406],"type":"Point"}
}