{
  "type": "Feature",
  "properties": {
    "addr:full":"56 S College Ave College Place WA 99324",
    "addr:housenumber":"56",
    "addr:postcode":"99324",
    "addr:street":"S College Ave",
    "iso:country":"US",
    "sg:address":"56 S College Ave",
    "sg:city":"College Place",
    "sg:classifiers":[
        {
            "category":"Shopping",
            "subcategory":"Florist",
            "type":"Retail Goods"
        }
    ],
    "sg:phone":"+1 509 522 0583",
    "sg:postcode":"99324",
    "sg:province":"WA",
    "wof:name":"Susie's Flower Boutique",
    "wof:placetype":"venue"
},
  "geometry": {"coordinates":[-118.3886,46.048769],"type":"Point"}
}