{
  "type": "Feature",
  "properties": {
    "addr:full":"929 N State St Bellingham WA 98225",
    "addr:housenumber":"929",
    "addr:postcode":"98225",
    "addr:street":"N State St",
    "iso:country":"US",
    "sg:address":"929 N State St",
    "sg:city":"Bellingham",
    "sg:classifiers":[
        {
            "category":"Personal",
            "type":"Services"
        },
        {
            "category":"Personal",
            "subcategory":"Beauty Salon",
            "type":"Services"
        }
    ],
    "sg:phone":"+1 360 756 9330",
    "sg:postcode":"98225",
    "sg:province":"WA",
    "sg:tags":[
        "shop",
        "electrolysis"
    ],
    "wof:name":"Electrolysis Plus",
    "wof:placetype":"venue"
},
  "geometry": {"coordinates":[-122.48345999999999,48.744109],"type":"Point"}
}