{
  "type": "Feature",
  "properties": {
    "addr:full":"1000 Ahtanum Rd Union Gap WA 98903",
    "addr:housenumber":"1000",
    "addr:postcode":"98903",
    "addr:street":"Ahtanum Rd",
    "iso:country":"US",
    "sg:address":"1000 Ahtanum Rd",
    "sg:city":"Union Gap",
    "sg:classifiers":[
        {
            "category":"Recreation",
            "type":"Entertainment"
        }
    ],
    "sg:phone":"+1 509 574 2435",
    "sg:postcode":"98903",
    "sg:province":"WA",
    "sg:tags":[
        "parks"
    ],
    "sg:website":"www.co.yakima.wa.us",
    "wof:name":"Yakima County Parks",
    "wof:placetype":"venue"
},
  "geometry": {"coordinates":[-120.52070399999999,46.558038],"type":"Point"}
}