{
  "type": "Feature",
  "properties": {
    "iso:country":"US",
    "sg:address":"2210 Washington Ct",
    "sg:city":"Richland",
    "sg:classifiers":[
        {
            "category":"Home & Garden",
            "subcategory":"Hardware",
            "type":"Retail Goods"
        }
    ],
    "sg:phone":"+1 509 967 5669",
    "sg:postcode":"99353",
    "sg:province":"WA",
    "wof:name":"West Richland Hardware",
    "wof:placetype":"venue"
},
  "geometry": {"coordinates":[-119.34469900000001,46.280069],"type":"Point"}
}