{
  "type": "Feature",
  "properties": {
    "addr:full":"1503 SE 141st Ave Vancouver WA 98683",
    "addr:housenumber":"1503",
    "addr:postcode":"98683",
    "addr:street":"Se 141St Ave",
    "iso:country":"US",
    "sg:address":"1503 SE 141st Ave",
    "sg:city":"Vancouver",
    "sg:classifiers":[
        {
            "category":"Manufacturing",
            "subcategory":"Jewelry",
            "type":"Manufacturing & Wholesale Goods"
        }
    ],
    "sg:phone":"+1 360 882 9683",
    "sg:postcode":"98683",
    "sg:province":"WA",
    "sg:tags":[
        "manufacturer",
        "costume",
        "jewelers-wholesale",
        "mfg"
    ],
    "wof:name":"Gem Connection",
    "wof:placetype":"venue"
},
  "geometry": {"coordinates":[-122.52774599999999,45.610593],"type":"Point"}
}