{
  "type": "Feature",
  "properties": {
    "addr:full":"316 Sunset Dr Longview WA 98632",
    "addr:housenumber":"316",
    "addr:postcode":"98632",
    "addr:street":"Sunset Dr",
    "iso:country":"US",
    "sg:address":"316 Sunset Dr",
    "sg:city":"Longview",
    "sg:classifiers":[
        {
            "category":"Building & Trades",
            "subcategory":"Cleaning & Sanitation",
            "type":"Services"
        }
    ],
    "sg:phone":"+1 360 423 7210",
    "sg:postcode":"98632",
    "sg:province":"WA",
    "sg:tags":[
        "maintenance"
    ],
    "wof:name":"Lj Cleaning",
    "wof:placetype":"venue"
},
  "geometry": {"coordinates":[-122.97888,46.183011],"type":"Point"}
}