{
  "type": "Feature",
  "properties": {
    "addr:full":"22607 NE 19th St Sammamish WA 98074",
    "addr:housenumber":"22607",
    "addr:postcode":"98074",
    "addr:street":"Ne 19Th St",
    "iso:country":"US",
    "sg:address":"22607 NE 19th St",
    "sg:city":"Sammamish",
    "sg:classifiers":[
        {
            "category":"Professional",
            "subcategory":"Employment Agencies",
            "type":"Services"
        }
    ],
    "sg:phone":"+1 425 836 0366",
    "sg:postcode":"98074",
    "sg:province":"WA",
    "sg:tags":[
        "firm",
        "executive",
        "search",
        "management",
        "consultant"
    ],
    "wof:name":"Thomas Mangum Company",
    "wof:placetype":"venue"
},
  "geometry": {"coordinates":[-122.03766299999999,47.626111],"type":"Point"}
}