{
  "type": "Feature",
  "properties": {
    "addr:full":"300 E 17th St Vancouver WA 98663",
    "addr:housenumber":"300",
    "addr:postcode":"98663",
    "addr:street":"E 17Th St",
    "iso:country":"US",
    "sg:address":"300 E 17th St",
    "sg:city":"Vancouver",
    "sg:classifiers":[
        {
            "category":"Insurance",
            "subcategory":"Insurance Agent",
            "type":"Services"
        }
    ],
    "sg:phone":"+1 360 694 8548",
    "sg:postcode":"98663",
    "sg:province":"WA",
    "sg:website":"www.bkiins.com",
    "wof:name":"BKI Insurance Svc Inc",
    "wof:placetype":"venue"
},
  "geometry": {"coordinates":[-122.668245,45.634105],"type":"Point"}
}