{
  "type": "Feature",
  "properties": {
    "addr:full":"3520 Harts Lake Loop Rd S Roy WA 98580",
    "addr:postcode":"3520;98580",
    "addr:street":"Harts Lake Loop Rd S",
    "iso:country":"US",
    "sg:address":"3520 Harts Lake Loop Rd S",
    "sg:city":"Roy",
    "sg:classifiers":[
        {
            "category":"Retail",
            "subcategory":"Repair Shop",
            "type":"Services"
        },
        {
            "category":"Retail",
            "subcategory":"Auto Repair",
            "type":"Services"
        }
    ],
    "sg:phone":"+1 360 458 3340",
    "sg:postcode":"98580",
    "sg:province":"WA",
    "sg:tags":[
        "repairing",
        "automobile",
        "trade",
        "contractor"
    ],
    "wof:name":"Richard's Wrench",
    "wof:placetype":"venue"
},
  "geometry": {"coordinates":[-122.478623,46.905229],"type":"Point"}
}