{
  "type": "Feature",
  "properties": {
    "iso:country":"US",
    "sg:address":"3202 20th St E",
    "sg:city":"Tacoma",
    "sg:classifiers":[
        {
            "category":"Retail",
            "subcategory":"Car Wash",
            "type":"Services"
        }
    ],
    "sg:phone":"+1 253 922 5051",
    "sg:postcode":"98424",
    "sg:province":"WA",
    "sg:tags":[
        "automobile",
        "detail",
        "clean"
    ],
    "wof:name":"Bmw Northwest Detail Shop",
    "wof:placetype":"venue"
},
  "geometry": {"coordinates":[-122.38782999999999,47.239019],"type":"Point"}
}