{
  "type": "Feature",
  "properties": {
    "addr:full":"9100 Steele Creek Loop NE Bremerton WA 98311",
    "addr:housenumber":"9100",
    "addr:postcode":"98311",
    "addr:street":"Steele Creek Loop Ne",
    "iso:country":"US",
    "sg:address":"9100 Steele Creek Loop NE",
    "sg:city":"Bremerton",
    "sg:classifiers":[
        {
            "category":"Health Services",
            "subcategory":"Clinic",
            "type":"Services"
        }
    ],
    "sg:phone":"+1 360 286 2029",
    "sg:postcode":"98311",
    "sg:province":"WA",
    "sg:tags":[
        "welfare"
    ],
    "wof:name":"Health Doc Group",
    "wof:placetype":"venue"
},
  "geometry": {"coordinates":[-122.633464,47.646481],"type":"Point"}
}