{
  "type": "Feature",
  "properties": {
    "addr:full":"21821 Meridian Ave S Bothell WA 98021",
    "addr:housenumber":"21821",
    "addr:postcode":"98021",
    "addr:street":"Meridian Ave S Bothell",
    "iso:country":"US",
    "sg:address":"21821 Meridian Ave S",
    "sg:city":"Bothell",
    "sg:classifiers":[
        {
            "category":"Building & Trades",
            "subcategory":"Electrical",
            "type":"Services"
        }
    ],
    "sg:phone":"+1 425 485 0434",
    "sg:postcode":"98021",
    "sg:province":"WA",
    "sg:tags":[
        "electrical",
        "contractor"
    ],
    "wof:name":"Alternating Current Technology",
    "wof:placetype":"venue"
},
  "geometry": {"coordinates":[-122.232444,47.799443],"type":"Point"}
}