{
  "type": "Feature",
  "properties": {
    "addr:full":"3704 Mount Baker Hwy Everson WA 98247",
    "addr:housenumber":"3704",
    "addr:postcode":"98247",
    "addr:street":"Mount Baker Hwy Everson",
    "iso:country":"US",
    "sg:address":"3704 Mount Baker Hwy",
    "sg:city":"Everson",
    "sg:classifiers":[
        {
            "category":"Health Services",
            "subcategory":"Doctor",
            "type":"Services"
        }
    ],
    "sg:phone":"+1 360 592 5422",
    "sg:postcode":"98247",
    "sg:province":"WA",
    "sg:tags":[
        "dentist"
    ],
    "wof:name":"Mount Baker Dental Clinic",
    "wof:placetype":"venue"
},
  "geometry": {"coordinates":[-122.285939,48.843641],"type":"Point"}
}