{
  "type": "Feature",
  "properties": {
    "addr:full":"13782 NE 60th St Redmond WA 98052",
    "addr:housenumber":"13782",
    "addr:postcode":"98052",
    "addr:street":"Ne 60Th St",
    "iso:country":"US",
    "sg:address":"13782 NE 60th St",
    "sg:city":"Redmond",
    "sg:classifiers":[
        {
            "category":"Professional",
            "subcategory":"Business Services",
            "type":"Services"
        }
    ],
    "sg:phone":"+1 425 885 4140",
    "sg:postcode":"98052",
    "sg:province":"WA",
    "wof:name":"Saw Business Services",
    "wof:placetype":"venue"
},
  "geometry": {"coordinates":[-122.154747,47.66078],"type":"Point"}
}