{
  "type": "Feature",
  "properties": {
    "addr:full":"4160 178th Ln SE Bellevue WA 98008",
    "addr:housenumber":"4160",
    "addr:postcode":"98008",
    "addr:street":"178Th Ln Se",
    "iso:country":"US",
    "sg:address":"4160 178th Ln SE",
    "sg:city":"Bellevue",
    "sg:classifiers":[
        {
            "category":"Professional",
            "subcategory":"Computer Services",
            "type":"Services"
        }
    ],
    "sg:phone":"+1 425 444 2968",
    "sg:postcode":"98008",
    "sg:province":"WA",
    "sg:tags":[
        "related"
    ],
    "wof:name":"Rougaru",
    "wof:placetype":"venue"
},
  "geometry": {"coordinates":[-122.102081,47.570711],"type":"Point"}
}