{
  "type": "Feature",
  "properties": {
    "addr:full":"6100 4th Ave S # 210 Seattle WA 98108",
    "addr:housenumber":"6100",
    "addr:postcode":"98108",
    "addr:street":"4Th Ave S # 210",
    "iso:country":"US",
    "sg:address":"6100 4th Ave S # 210",
    "sg:city":"Seattle",
    "sg:classifiers":[
        {
            "category":"Organizations",
            "subcategory":"Professional Association",
            "type":"Services"
        }
    ],
    "sg:phone":"+1 206 767 0655",
    "sg:postcode":"98108",
    "sg:province":"WA",
    "sg:tags":[
        "representative",
        "agent",
        "manufacturers'"
    ],
    "wof:name":"Bianci Group",
    "wof:placetype":"venue"
},
  "geometry": {"coordinates":[-122.32959700000001,47.548031],"type":"Point"}
}