{
  "type": "Feature",
  "properties": {
    "iso:country":"US",
    "sg:address":"808 Aloha Pl",
    "sg:city":"Edmonds",
    "sg:classifiers":[
        {
            "category":"Shopping",
            "subcategory":"Clothing, Apparel, & Fashions",
            "type":"Retail Goods"
        }
    ],
    "sg:phone":"+1 425 771 5303",
    "sg:postcode":"98020",
    "sg:province":"WA",
    "sg:tags":[
        "family"
    ],
    "wof:name":"Joan Sims Scanlon",
    "wof:placetype":"venue"
},
  "geometry": {"coordinates":[-122.36933000000001,47.815393],"type":"Point"}
}