{
  "type": "Feature",
  "properties": {
    "addr:full":"1110 N Stanley Rd Spokane Valley WA 99212",
    "addr:housenumber":"1110",
    "addr:postcode":"99212",
    "addr:street":"N Stanley Rd",
    "iso:country":"US",
    "sg:address":"1110 N Stanley Rd",
    "sg:city":"Spokane Valley",
    "sg:classifiers":[
        {
            "category":"Retail",
            "subcategory":"Auto Repair",
            "type":"Services"
        }
    ],
    "sg:phone":"+1 509 533 9382",
    "sg:postcode":"99212",
    "sg:province":"WA",
    "sg:tags":[
        "repairing",
        "automobile"
    ],
    "wof:name":"Superior Suspension & Drive",
    "wof:placetype":"venue"
},
  "geometry": {"coordinates":[-117.33065000000001,47.667861],"type":"Point"}
}