{
  "type": "Feature",
  "properties": {
    "addr:full":"2908 41st Way SE Olympia WA 98501",
    "addr:housenumber":"2908",
    "addr:postcode":"98501",
    "addr:street":"41St Way Se",
    "iso:country":"US",
    "sg:address":"2908 41st Way SE",
    "sg:city":"Olympia",
    "sg:classifiers":[
        {
            "category":"Manufacturing",
            "subcategory":"Motor Vehicles & Parts",
            "type":"Manufacturing & Wholesale Goods"
        }
    ],
    "sg:phone":"+1 360 705 3432",
    "sg:postcode":"98501",
    "sg:province":"WA",
    "sg:tags":[
        "equipment",
        "transportation",
        "mfg"
    ],
    "wof:name":"Gmp Enterprises Inc",
    "wof:placetype":"venue"
},
  "geometry": {"coordinates":[-122.85875799999999,47.010237],"type":"Point"}
}