{
  "type": "Feature",
  "properties": {
    "addr:full":"15 Lorenz Rd Kp N Lakebay WA 98349",
    "addr:housenumber":"15",
    "addr:postcode":"98349",
    "addr:street":"Lorenz Rd Kp N Lakebay",
    "iso:country":"US",
    "sg:address":"15 Lorenz Rd Kp N",
    "sg:city":"Lakebay",
    "sg:classifiers":[
        {
            "category":"Recreation",
            "subcategory":"Marina",
            "type":"Entertainment"
        }
    ],
    "sg:phone":"+1 253 884 3350",
    "sg:postcode":"98349",
    "sg:province":"WA",
    "wof:name":"Lakebay Marina",
    "wof:placetype":"venue"
},
  "geometry": {"coordinates":[-122.75796,47.257172],"type":"Point"}
}