{
  "type": "Feature",
  "properties": {
    "addr:full":"600 University Street Suite 2250 Seattle WA 98101",
    "addr:housenumber":"600",
    "addr:postcode":"98101",
    "addr:street":"University Street Suite 2250",
    "iso:country":"US",
    "sg:address":"600 University Street Suite 2250",
    "sg:city":"Seattle",
    "sg:classifiers":[
        {
            "category":"Professional",
            "subcategory":"Lawyer & Legal Services",
            "type":"Services"
        }
    ],
    "sg:phone":"+1 206 382 1441",
    "sg:postcode":"98101",
    "sg:province":"WA",
    "wof:name":"Ross Katharine M Law Office of Pllc",
    "wof:placetype":"venue"
},
  "geometry": {"coordinates":[-122.332998,47.61039],"type":"Point"}
}