{
  "type": "Feature",
  "properties": {
    "addr:full":"1260 Blaine Ave Blaine WA 98230",
    "addr:housenumber":"1260",
    "addr:postcode":"98230",
    "addr:street":"Blaine Ave",
    "iso:country":"US",
    "sg:address":"1260 Blaine Ave",
    "sg:city":"Blaine",
    "sg:classifiers":[
        {
            "category":"Building & Trades",
            "subcategory":"Construction",
            "type":"Services"
        }
    ],
    "sg:phone":"+1 360 332 1482",
    "sg:postcode":"98230",
    "sg:province":"WA",
    "sg:tags":[
        "house"
    ],
    "wof:name":"C&B Construction LLC",
    "wof:placetype":"venue"
},
  "geometry": {"coordinates":[-122.744884,48.987901],"type":"Point"}
}