{
  "type": "Feature",
  "properties": {
    "addr:full":"21913 NE 72nd Ave Battle Ground WA 98604",
    "addr:housenumber":"21913",
    "addr:postcode":"98604",
    "addr:street":"Ne 72Nd Ave",
    "iso:country":"US",
    "sg:address":"21913 NE 72nd Ave",
    "sg:city":"Battle Ground",
    "sg:classifiers":[
        {
            "category":"Professional",
            "type":"Services"
        }
    ],
    "sg:phone":"+1 360 666 2652",
    "sg:postcode":"98604",
    "sg:province":"WA",
    "wof:name":"D Js Offroad & Mechanics",
    "wof:placetype":"venue"
},
  "geometry": {"coordinates":[-122.60007400000001,45.783079],"type":"Point"}
}