{
  "type": "Feature",
  "properties": {
    "addr:full":"2924 SE 5th St Renton WA 98058",
    "addr:housenumber":"2924",
    "addr:postcode":"98058",
    "addr:street":"Se 5Th St",
    "iso:country":"US",
    "sg:address":"2924 SE 5th St",
    "sg:city":"Renton",
    "sg:classifiers":[
        {
            "category":"Building & Trades",
            "subcategory":"Cleaning & Sanitation",
            "type":"Services"
        }
    ],
    "sg:phone":"+1 425 687 0578",
    "sg:postcode":"98058",
    "sg:province":"WA",
    "sg:tags":[
        "maintenance"
    ],
    "wof:name":"L & I Cleaning Service",
    "wof:placetype":"venue"
},
  "geometry": {"coordinates":[-122.179469,47.477154],"type":"Point"}
}