{
  "type": "Feature",
  "properties": {
    "addr:full":"10441 Bayview Edison Rd Mount Vernon WA 98273",
    "addr:housenumber":"10441",
    "addr:postcode":"98273",
    "addr:street":"Bayview Edison Rd",
    "iso:country":"US",
    "sg:address":"10441 Bayview Edison Rd",
    "sg:city":"Mount Vernon",
    "sg:classifiers":[
        {
            "category":"Organizations",
            "subcategory":"Community Association",
            "type":"Services"
        }
    ],
    "sg:phone":"+1 360 428 1084",
    "sg:postcode":"98273",
    "sg:province":"WA",
    "wof:name":"Northwest Strits Mar Fundation",
    "wof:placetype":"venue"
},
  "geometry": {"coordinates":[-122.482226,48.494579],"type":"Point"}
}