{
  "type": "Feature",
  "properties": {
    "addr:full":"10711 Main St Bellevue WA 98004",
    "addr:housenumber":"10711",
    "addr:postcode":"98004",
    "addr:street":"Main St",
    "iso:country":"US",
    "sg:address":"10711 Main St",
    "sg:city":"Bellevue",
    "sg:classifiers":[
        {
            "category":"Retail",
            "subcategory":"Laundry & Dry Cleaning",
            "type":"Services"
        }
    ],
    "sg:phone":"+1 425 451 1417",
    "sg:postcode":"98004",
    "sg:province":"WA",
    "sg:tags":[
        "pressing",
        "agent"
    ],
    "wof:name":"Michaels Fine Dry Cleaning",
    "wof:placetype":"venue"
},
  "geometry": {"coordinates":[-122.19752,47.610042],"type":"Point"}
}