{
  "type": "Feature",
  "properties": {
    "addr:full":"18807 NE 130th Cir Brush Prairie WA 98606",
    "addr:housenumber":"18807",
    "addr:postcode":"98606",
    "addr:street":"Ne 130Th Cir",
    "iso:country":"US",
    "sg:address":"18807 NE 130th Cir",
    "sg:city":"Brush Prairie",
    "sg:classifiers":[
        {
            "category":"Building & Trades",
            "subcategory":"Construction",
            "type":"Services"
        }
    ],
    "sg:phone":"+1 360 921 7129",
    "sg:postcode":"98606",
    "sg:province":"WA",
    "sg:tags":[
        "residential"
    ],
    "wof:name":"Stevens Construction Inc",
    "wof:placetype":"venue"
},
  "geometry": {"coordinates":[-122.480712,45.716514],"type":"Point"}
}