{
  "type": "Feature",
  "properties": {
    "addr:full":"49 Ponderosa Dr Oak Harbor WA 98277",
    "addr:housenumber":"49",
    "addr:postcode":"98277",
    "addr:street":"Ponderosa Dr",
    "iso:country":"US",
    "sg:address":"49 Ponderosa Dr",
    "sg:city":"Oak Harbor",
    "sg:classifiers":[
        {
            "category":"Building & Trades",
            "subcategory":"Construction",
            "type":"Services"
        }
    ],
    "sg:phone":"+1 360 279 9286",
    "sg:postcode":"98277",
    "sg:province":"WA",
    "sg:tags":[
        "contractor"
    ],
    "wof:name":"Artistic Tile & Stone Design",
    "wof:placetype":"venue"
},
  "geometry": {"coordinates":[-122.61323899999999,48.360886],"type":"Point"}
}