{
  "type": "Feature",
  "properties": {
    "addr:full":"220 NW 58th Street Seattle WA 98107",
    "addr:housenumber":"220",
    "addr:postcode":"98107",
    "addr:street":"Nw 58Th Street",
    "iso:country":"US",
    "sg:address":"220 NW 58th Street",
    "sg:city":"Seattle",
    "sg:classifiers":[
        {
            "category":"Real Estate",
            "subcategory":"Real Estate Services",
            "type":"Services"
        }
    ],
    "sg:phone":"+1 206 784 1217",
    "sg:postcode":"98107",
    "sg:province":"WA",
    "sg:tags":[
        "home",
        "inspector"
    ],
    "wof:name":"Matzen Richard C",
    "wof:placetype":"venue"
},
  "geometry": {"coordinates":[-122.35905,47.671204],"type":"Point"}
}