{
  "type": "Feature",
  "properties": {
    "addr:full":"820 Guard St Friday Harbor WA 98250",
    "addr:housenumber":"820",
    "addr:postcode":"98250",
    "addr:street":"Guard St",
    "iso:country":"US",
    "sg:address":"820 Guard St",
    "sg:city":"Friday Harbor",
    "sg:classifiers":[
        {
            "category":"Social Services",
            "type":"Services"
        }
    ],
    "sg:phone":"+1 360 376 6172",
    "sg:postcode":"98250",
    "sg:province":"WA",
    "wof:name":"Mary Nash MA",
    "wof:placetype":"venue"
},
  "geometry": {"coordinates":[-123.02822399999999,48.536314],"type":"Point"}
}