{
  "type": "Feature",
  "properties": {
    "addr:full":"1002 Aurora Ave N Seattle WA 98109",
    "addr:housenumber":"1002",
    "addr:postcode":"98109",
    "addr:street":"Aurora Ave N",
    "iso:country":"US",
    "sg:address":"1002 Aurora Ave N",
    "sg:city":"Seattle",
    "sg:classifiers":[
        {
            "category":"Professional",
            "subcategory":"Engineering",
            "type":"Services"
        }
    ],
    "sg:phone":"+1 206 789 4069",
    "sg:postcode":"98109",
    "sg:province":"WA",
    "sg:tags":[
        "consulting",
        "co"
    ],
    "wof:name":"Energy Trading Technology",
    "wof:placetype":"venue"
},
  "geometry": {"coordinates":[-122.343378,47.628859],"type":"Point"}
}