{
  "type": "Feature",
  "properties": {
    "addr:full":"737 State Rte 109 Hoquiam WA 98550",
    "addr:housenumber":"737",
    "addr:postcode":"98550",
    "addr:street":"State Rte 109",
    "iso:country":"US",
    "sg:address":"737 State Rte 109",
    "sg:city":"Hoquiam",
    "sg:classifiers":[
        {
            "category":"Manufacturing",
            "subcategory":"Wood Products",
            "type":"Manufacturing & Wholesale Goods"
        }
    ],
    "sg:phone":"+1 360 537 6850",
    "sg:postcode":"98550",
    "sg:province":"WA",
    "sg:tags":[
        "mfg"
    ],
    "wof:name":"Donald Etue Woodcarvings",
    "wof:placetype":"venue"
},
  "geometry": {"coordinates":[-123.888768,46.980954],"type":"Point"}
}