{
  "type": "Feature",
  "properties": {
    "addr:full":"20310 N Perry Rd Colbert WA 99005",
    "addr:housenumber":"20310",
    "addr:postcode":"99005",
    "addr:street":"N Perry Rd Colbert",
    "iso:country":"US",
    "sg:address":"20310 N Perry Rd",
    "sg:city":"Colbert",
    "sg:classifiers":[
        {
            "category":"Banks & Credit Unions",
            "subcategory":"Financial Services",
            "type":"Services"
        }
    ],
    "sg:phone":"+1 509 710 8043",
    "sg:postcode":"99005",
    "sg:province":"WA",
    "sg:tags":[
        "investor"
    ],
    "wof:name":"Ideal Building Solutions",
    "wof:placetype":"venue"
},
  "geometry": {"coordinates":[-117.388401,47.841704],"type":"Point"}
}