{
  "type": "Feature",
  "properties": {
    "addr:full":"815 MacArthur Blvd Ste C Vancouver WA 98661",
    "addr:housenumber":"815",
    "addr:postcode":"98661",
    "addr:street":"Macarthur Blvd Ste C",
    "iso:country":"US",
    "sg:address":"815 MacArthur Blvd Ste C",
    "sg:city":"Vancouver",
    "sg:classifiers":[
        {
            "category":"Professional",
            "subcategory":"Employment Agencies",
            "type":"Services"
        }
    ],
    "sg:phone":"+1 360 693 0203",
    "sg:postcode":"98661",
    "sg:province":"WA",
    "sg:tags":[
        "contractor"
    ],
    "sg:website":"www.laborready.com",
    "wof:name":"Labor Ready",
    "wof:placetype":"venue"
},
  "geometry": {"coordinates":[-122.617824,45.627731],"type":"Point"}
}