{
  "type": "Feature",
  "properties": {
    "addr:full":"3508 E Spangle Waverly Rd Spangle WA 99031",
    "addr:housenumber":"3508",
    "addr:postcode":"99031",
    "addr:street":"E Spangle Waverly Rd",
    "iso:country":"US",
    "sg:address":"3508 E Spangle Waverly Rd",
    "sg:city":"Spangle",
    "sg:classifiers":[
        {
            "category":"Professional",
            "subcategory":"Business Services",
            "type":"Services"
        }
    ],
    "sg:phone":"+1 509 245 3366",
    "sg:postcode":"99031",
    "sg:province":"WA",
    "sg:tags":[
        "recording",
        "studio"
    ],
    "wof:name":"Hengen Art Studio",
    "wof:placetype":"venue"
},
  "geometry": {"coordinates":[-117.358615,47.4109],"type":"Point"}
}