{
  "type": "Feature",
  "properties": {
    "addr:full":"71 Heather Heights Dr Selah WA 98942",
    "addr:housenumber":"71",
    "addr:postcode":"98942",
    "addr:street":"Heather Heights Dr",
    "iso:country":"US",
    "sg:address":"71 Heather Heights Dr",
    "sg:city":"Selah",
    "sg:classifiers":[
        {
            "category":"Shopping",
            "subcategory":"Pets & Pet Supplies",
            "type":"Retail Goods"
        }
    ],
    "sg:phone":"+1 509 698 4600",
    "sg:postcode":"98942",
    "sg:province":"WA",
    "sg:tags":[
        "product",
        "health",
        "animal"
    ],
    "wof:name":"Api",
    "wof:placetype":"venue"
},
  "geometry": {"coordinates":[-120.56295799999999,46.698105],"type":"Point"}
}