{
  "type": "Feature",
  "properties": {
    "addr:full":"1995 Division St Bellingham WA 98226",
    "addr:housenumber":"1995",
    "addr:postcode":"98226",
    "addr:street":"Division St",
    "iso:country":"US",
    "sg:address":"1995 Division St",
    "sg:city":"Bellingham",
    "sg:classifiers":[
        {
            "category":"Professional",
            "subcategory":"Business Services",
            "type":"Services"
        }
    ],
    "sg:phone":"+1 360 734 1628",
    "sg:postcode":"98226",
    "sg:province":"WA",
    "sg:tags":[
        "packaging"
    ],
    "wof:name":"Pacific Packetting Inc",
    "wof:placetype":"venue"
},
  "geometry": {"coordinates":[-122.44810200000001,48.782093],"type":"Point"}
}