{
  "type": "Feature",
  "properties": {
    "addr:full":"3400 Kitsap Way Bremerton WA 98312",
    "addr:postcode":"3400;98312",
    "addr:street":"Kitsap Way",
    "iso:country":"US",
    "sg:address":"3400 Kitsap Way",
    "sg:city":"Bremerton",
    "sg:classifiers":[
        {
            "category":"Retail",
            "subcategory":"Self-service Laundry",
            "type":"Services"
        }
    ],
    "sg:phone":"+1 360 373 9888",
    "sg:postcode":"98312",
    "sg:province":"WA",
    "wof:name":"Maytag Laundry & Cleaners",
    "wof:placetype":"venue"
},
  "geometry": {"coordinates":[-122.66109899999999,47.571623],"type":"Point"}
}