{
  "type": "Feature",
  "properties": {
    "iso:country":"US",
    "sg:address":"310 N K St",
    "sg:city":"Tacoma",
    "sg:classifiers":[
        {
            "category":"Social Services",
            "type":"Services"
        }
    ],
    "sg:phone":"+1 253 403 1837",
    "sg:postcode":"98403",
    "sg:province":"WA",
    "sg:tags":[
        "counselor",
        "marriage",
        "family"
    ],
    "wof:name":"Multicare Grief & Loss Svcs",
    "wof:placetype":"venue"
},
  "geometry": {"coordinates":[-122.455721,47.26131],"type":"Point"}
}