{
  "type": "Feature",
  "properties": {
    "addr:full":"1000 N Argonne Rd Spokane WA 99212",
    "addr:housenumber":"1000",
    "addr:postcode":"99212",
    "addr:street":"N Argonne Rd",
    "iso:country":"US",
    "sg:address":"1000 N Argonne Rd",
    "sg:city":"Spokane",
    "sg:classifiers":[
        {
            "category":"Professional",
            "type":"Services"
        }
    ],
    "sg:phone":"+1 509 353 2874",
    "sg:postcode":"99212",
    "sg:province":"WA",
    "wof:name":"Defense Contract",
    "wof:placetype":"venue"
},
  "geometry": {"coordinates":[-117.282805,47.667851],"type":"Point"}
}