{
  "type": "Feature",
  "properties": {
    "addr:full":"32 Truman Nelson Rd Oroville WA 98844",
    "addr:housenumber":"32",
    "addr:postcode":"98844",
    "addr:street":"Truman Nelson Rd",
    "iso:country":"US",
    "sg:address":"32 Truman Nelson Rd",
    "sg:city":"Oroville",
    "sg:classifiers":[
        {
            "category":"Food & Beverages",
            "subcategory":"Farmers Market",
            "type":"Retail Goods"
        }
    ],
    "sg:phone":"+1 509 476 4006",
    "sg:postcode":"98844",
    "sg:province":"WA",
    "sg:tags":[
        "beekeeper"
    ],
    "wof:name":"Stegs Apiary",
    "wof:placetype":"venue"
},
  "geometry": {"coordinates":[-119.43459300000001,48.868721],"type":"Point"}
}