{
  "type": "Feature",
  "properties": {
    "addr:full":"3600 S 344th Way Auburn WA 98001",
    "addr:housenumber":"3600",
    "addr:postcode":"98001",
    "addr:street":"S 344Th Way",
    "iso:country":"US",
    "sg:address":"3600 S 344th Way",
    "sg:city":"Auburn",
    "sg:classifiers":[
        {
            "category":"Education",
            "subcategory":"College",
            "type":"Public Place"
        }
    ],
    "sg:phone":"+1 253 943 2800",
    "sg:postcode":"98001",
    "sg:province":"WA",
    "sg:tags":[
        "junior"
    ],
    "wof:name":"Keller Graduate School MGT",
    "wof:placetype":"venue"
},
  "geometry": {"coordinates":[-122.290442,47.291862],"type":"Point"}
}