{
  "type": "Feature",
  "properties": {
    "addr:full":"2138 N 135th St Seattle WA 98133",
    "addr:housenumber":"2138",
    "addr:postcode":"98133",
    "addr:street":"N 135Th St",
    "iso:country":"US",
    "sg:address":"2138 N 135th St",
    "sg:city":"Seattle",
    "sg:classifiers":[
        {
            "category":"Professional",
            "subcategory":"Business Services",
            "type":"Services"
        }
    ],
    "sg:phone":"+1 206 363 2035",
    "sg:postcode":"98133",
    "sg:province":"WA",
    "wof:name":"Kustom Enterprises",
    "wof:placetype":"venue"
},
  "geometry": {"coordinates":[-122.331643,47.726902],"type":"Point"}
}