{
  "type": "Feature",
  "properties": {
    "addr:full":"3926 100th St SW Lakewood WA 98499",
    "addr:housenumber":"3926",
    "addr:postcode":"98499",
    "addr:street":"100Th St Sw",
    "iso:country":"US",
    "sg:address":"3926 100th St SW",
    "sg:city":"Lakewood",
    "sg:classifiers":[
        {
            "category":"Restaurant",
            "type":"Food & Drink"
        }
    ],
    "sg:phone":"+1 253 722 5310",
    "sg:postcode":"98499",
    "sg:province":"WA",
    "wof:name":"Cynthia's Coffee",
    "wof:placetype":"venue"
},
  "geometry": {"coordinates":[-122.489265,47.167141],"type":"Point"}
}