{
  "type": "Feature",
  "properties": {
    "addr:full":"8581 Hunts Point Ln Bellevue WA 98004",
    "addr:housenumber":"8581",
    "addr:postcode":"98004",
    "addr:street":"Hunts Point Ln",
    "iso:country":"US",
    "sg:address":"8581 Hunts Point Ln",
    "sg:city":"Bellevue",
    "sg:classifiers":[
        {
            "category":"Wholesale",
            "subcategory":"Groceries",
            "type":"Manufacturing & Wholesale Goods"
        }
    ],
    "sg:phone":"+1 425 462 1020",
    "sg:postcode":"98004",
    "sg:province":"WA",
    "sg:tags":[
        "general"
    ],
    "wof:name":"Sandals",
    "wof:placetype":"venue"
},
  "geometry": {"coordinates":[-122.227253,47.63795],"type":"Point"}
}