{
  "type": "Feature",
  "properties": {
    "addr:full":"301 21st Ave E Seattle WA 98112",
    "addr:housenumber":"301",
    "addr:postcode":"98112",
    "addr:street":"21St Ave E",
    "iso:country":"US",
    "sg:address":"301 21st Ave E",
    "sg:city":"Seattle",
    "sg:classifiers":[
        {
            "category":"Education",
            "subcategory":"School",
            "type":"Public Place"
        }
    ],
    "sg:phone":"+1 206 252 3500",
    "sg:postcode":"98112",
    "sg:province":"WA",
    "wof:name":"Seattle Public Schools",
    "wof:placetype":"venue"
},
  "geometry": {"coordinates":[-122.304979,47.622191],"type":"Point"}
}