{
  "type": "Feature",
  "properties": {
    "addr:full":"150 Andover Park W Seattle WA 98188",
    "addr:housenumber":"150",
    "addr:postcode":"98188",
    "addr:street":"Andover Park W",
    "iso:country":"US",
    "sg:address":"150 Andover Park W",
    "sg:city":"Seattle",
    "sg:classifiers":[
        {
            "category":"Home & Garden",
            "subcategory":"Home Furnishings",
            "type":"Retail Goods"
        }
    ],
    "sg:phone":"+1 206 243 1012",
    "sg:postcode":"98188",
    "sg:province":"WA",
    "wof:name":"Clearwater Spas & Stoves",
    "wof:placetype":"venue"
},
  "geometry": {"coordinates":[-122.254299,47.458958],"type":"Point"}
}