{
  "type": "Feature",
  "properties": {
    "addr:full":"9601 Berkshire Ct SE Olympia WA 98513",
    "addr:housenumber":"9601",
    "addr:postcode":"98513",
    "addr:street":"Berkshire Ct Se",
    "iso:country":"US",
    "sg:address":"9601 Berkshire Ct SE",
    "sg:city":"Olympia",
    "sg:classifiers":[
        {
            "category":"Home & Garden",
            "subcategory":"Building Materials",
            "type":"Retail Goods"
        }
    ],
    "sg:phone":"+1 360 455 1167",
    "sg:postcode":"98513",
    "sg:province":"WA",
    "wof:name":"Harmony Glass Designs",
    "wof:placetype":"venue"
},
  "geometry": {"coordinates":[-122.735736,47.008134],"type":"Point"}
}