{
  "type": "Feature",
  "properties": {
    "addr:full":"6409 Sandridge Rd Long Beach WA 98631",
    "addr:housenumber":"6409",
    "addr:postcode":"98631",
    "addr:street":"Sandridge Rd",
    "iso:country":"US",
    "sg:address":"6409 Sandridge Rd",
    "sg:city":"Long Beach",
    "sg:classifiers":[
        {
            "category":"Recreation",
            "type":"Entertainment"
        }
    ],
    "sg:phone":"+1 360 642 9295",
    "sg:postcode":"98631",
    "sg:province":"WA",
    "wof:name":"Red Barn Arena",
    "wof:placetype":"venue"
},
  "geometry": {"coordinates":[-124.037971,46.348849],"type":"Point"}
}