{
  "type": "Feature",
  "properties": {
    "addr:full":"231 SW 152nd St Burien WA 98166",
    "addr:housenumber":"231",
    "addr:postcode":"98166",
    "addr:street":"Sw 152Nd St",
    "iso:country":"US",
    "sg:address":"231 SW 152nd St",
    "sg:city":"Burien",
    "sg:classifiers":[
        {
            "category":"Organizations",
            "subcategory":"Religious Organization",
            "type":"Services"
        }
    ],
    "sg:phone":"+1 206 241 0664",
    "sg:postcode":"98166",
    "sg:province":"WA",
    "sg:tags":[
        "church"
    ],
    "wof:name":"Fellowship Baptist Church",
    "wof:placetype":"venue"
},
  "geometry": {"coordinates":[-122.33892299999999,47.466768],"type":"Point"}
}