{
  "type": "Feature",
  "properties": {
    "addr:full":"14740 Bethel Ln SW Vashon WA 98070",
    "addr:housenumber":"14740",
    "addr:postcode":"98070",
    "addr:street":"Bethel Ln Sw",
    "iso:country":"US",
    "sg:address":"14740 Bethel Ln SW",
    "sg:city":"Vashon",
    "sg:classifiers":[
        {
            "category":"Professional",
            "subcategory":"Business Services",
            "type":"Services"
        }
    ],
    "sg:phone":"+1 206 567 5726",
    "sg:postcode":"98070",
    "sg:province":"WA",
    "wof:name":"Shinshionstine Associates",
    "wof:placetype":"venue"
},
  "geometry": {"coordinates":[-122.486058,47.473257],"type":"Point"}
}