{
  "type": "Feature",
  "properties": {
    "addr:full":"1030 W Broadway St Goldendale WA 98620",
    "addr:housenumber":"1030",
    "addr:postcode":"98620",
    "addr:street":"W Broadway St",
    "iso:country":"US",
    "sg:address":"1030 W Broadway St",
    "sg:city":"Goldendale",
    "sg:classifiers":[
        {
            "category":"Manufacturing",
            "subcategory":"Building Materials",
            "type":"Manufacturing & Wholesale Goods"
        }
    ],
    "sg:phone":"+1 509 773 6776",
    "sg:postcode":"98620",
    "sg:province":"WA",
    "sg:tags":[
        "mfg"
    ],
    "wof:name":"Absolute Moulding & Trim",
    "wof:placetype":"venue"
},
  "geometry": {"coordinates":[-120.84207499999999,45.824398],"type":"Point"}
}