{
  "type": "Feature",
  "properties": {
    "addr:full":"3635 Thorndyke Ave W Seattle WA 98119",
    "addr:housenumber":"3635",
    "addr:postcode":"98119",
    "addr:street":"Thorndyke Ave W",
    "iso:country":"US",
    "sg:address":"3635 Thorndyke Ave W",
    "sg:city":"Seattle",
    "sg:classifiers":[
        {
            "category":"Professional",
            "type":"Services"
        },
        {
            "category":"Shopping",
            "subcategory":"Gifts & Souvenirs",
            "type":"Retail Goods"
        },
        {
            "category":"Shopping",
            "type":"Retail Goods"
        },
        {
            "category":"Manufacturing",
            "subcategory":"Paper Products",
            "type":"Manufacturing & Wholesale Goods"
        }
    ],
    "sg:phone":"+1 206 286 1000",
    "sg:postcode":"98119",
    "sg:province":"WA",
    "sg:tags":[
        "fiber",
        "materials-wholesale",
        "material",
        "wrapping",
        "packaging",
        "boxes-corrugated",
        "manufacturer"
    ],
    "sg:website":"http://www.washingtonpackaging.com",
    "wof:name":"Washington Procurement Supply",
    "wof:placetype":"venue"
},
  "geometry": {"coordinates":[-122.377537,47.65231],"type":"Point"}
}