{
  "type": "Feature",
  "properties": {
    "addr:full":"1107 S 18th St Yakima WA 98901",
    "addr:housenumber":"1107",
    "addr:postcode":"98901",
    "addr:street":"S 18Th St",
    "iso:country":"US",
    "sg:address":"1107 S 18th St",
    "sg:city":"Yakima",
    "sg:classifiers":[
        {
            "category":"Travel",
            "subcategory":"Campground",
            "type":"Entertainment"
        }
    ],
    "sg:phone":"+1 509 457 3683",
    "sg:postcode":"98901",
    "sg:province":"WA",
    "sg:tags":[
        "trailer",
        "special"
    ],
    "wof:name":"Cirlce H R V Ranch",
    "wof:placetype":"venue"
},
  "geometry": {"coordinates":[-120.477535,46.588788],"type":"Point"}
}