{
  "type": "Feature",
  "properties": {
    "addr:full":"14658 NE 16th St Bellevue WA 98007",
    "addr:housenumber":"14658",
    "addr:postcode":"98007",
    "addr:street":"Ne 16Th St",
    "iso:country":"US",
    "sg:address":"14658 NE 16th St",
    "sg:city":"Bellevue",
    "sg:classifiers":[
        {
            "category":"Real Estate",
            "subcategory":"Real Estate Services",
            "type":"Services"
        },
        {
            "category":"Home & Garden",
            "subcategory":"Home Furnishings",
            "type":"Retail Goods"
        }
    ],
    "sg:phone":"+1 425 691 9223",
    "sg:postcode":"98007",
    "sg:province":"WA",
    "sg:tags":[
        "tourists'",
        "rental",
        "sale",
        "vacation"
    ],
    "wof:name":"Italian Dream Vacation",
    "wof:placetype":"venue"
},
  "geometry": {"coordinates":[-122.144498,47.624531],"type":"Point"}
}