{
  "type": "Feature",
  "properties": {
    "iso:country":"US",
    "sg:address":"112 J St NE",
    "sg:city":"Auburn",
    "sg:classifiers":[
        {
            "category":"Building & Trades",
            "subcategory":"Construction",
            "type":"Services"
        }
    ],
    "sg:phone":"+1 253 335 8782",
    "sg:postcode":"98002",
    "sg:province":"WA",
    "sg:tags":[
        "house"
    ],
    "wof:name":"Niko Construction",
    "wof:placetype":"venue"
},
  "geometry": {"coordinates":[-122.21750400000001,47.309531],"type":"Point"}
}