{
  "type": "Feature",
  "properties": {
    "addr:full":"196 Jacobson Rd Cathlamet WA 98612",
    "addr:housenumber":"196",
    "addr:postcode":"98612",
    "addr:street":"Jacobson Rd",
    "iso:country":"US",
    "sg:address":"196 Jacobson Rd",
    "sg:city":"Cathlamet",
    "sg:classifiers":[
        {
            "category":"Real Estate",
            "subcategory":"Developer",
            "type":"Services"
        }
    ],
    "sg:phone":"+1 360 795 3459",
    "sg:postcode":"98612",
    "sg:province":"WA",
    "sg:tags":[
        "mobile",
        "home"
    ],
    "wof:name":"Indian Village Mobile Home Pk",
    "wof:placetype":"venue"
},
  "geometry": {"coordinates":[-123.371477,46.196612],"type":"Point"}
}