{
  "type": "Feature",
  "properties": {
    "addr:full":"5 N 86th Ave Yakima WA 98908",
    "addr:housenumber":"5",
    "addr:postcode":"98908",
    "addr:street":"N 86Th Ave",
    "iso:country":"US",
    "sg:address":"5 N 86th Ave",
    "sg:city":"Yakima",
    "sg:classifiers":[
        {
            "category":"Restaurant",
            "type":"Food & Drink"
        }
    ],
    "sg:phone":"+1 509 972 1372",
    "sg:postcode":"98908",
    "sg:province":"WA",
    "sg:tags":[
        "eating"
    ],
    "wof:name":"Euro Bagel LLC",
    "wof:placetype":"venue"
},
  "geometry": {"coordinates":[-120.62187900000001,46.596764],"type":"Point"}
}