{
  "type": "Feature",
  "properties": {
    "addr:full":"805 Lindy Ln Yakima WA 98901",
    "addr:housenumber":"805",
    "addr:postcode":"98901",
    "addr:street":"Lindy Ln",
    "iso:country":"US",
    "sg:address":"805 Lindy Ln",
    "sg:city":"Yakima",
    "sg:classifiers":[
        {
            "category":"Shopping",
            "subcategory":"Musical Instruments",
            "type":"Retail Goods"
        }
    ],
    "sg:phone":"+1 509 248 5364",
    "sg:postcode":"98901",
    "sg:province":"WA",
    "wof:name":"Noteworthy Music",
    "wof:placetype":"venue"
},
  "geometry": {"coordinates":[-120.488219,46.579052],"type":"Point"}
}