{
  "type": "Feature",
  "properties": {
    "addr:full":"106 E 9th St Vancouver WA 98660",
    "addr:housenumber":"106",
    "addr:postcode":"98660",
    "addr:street":"E 9Th St",
    "iso:country":"US",
    "sg:address":"106 E 9th St",
    "sg:city":"Vancouver",
    "sg:classifiers":[
        {
            "category":"Personal",
            "subcategory":"Day Spa",
            "type":"Services"
        }
    ],
    "sg:phone":"+1 360 202 2299",
    "sg:postcode":"98660",
    "sg:province":"WA",
    "wof:name":"Miley Flowers, LMP",
    "wof:placetype":"venue"
},
  "geometry": {"coordinates":[-122.671558,45.628009],"type":"Point"}
}