{
  "type": "Feature",
  "properties": {
    "addr:full":"911 N Pines Rd Spokane Valley WA 99206",
    "addr:housenumber":"911",
    "addr:postcode":"99206",
    "addr:street":"N Pines Rd",
    "iso:country":"US",
    "sg:address":"911 N Pines Rd",
    "sg:city":"Spokane Valley",
    "sg:classifiers":[
        {
            "category":"Professional",
            "subcategory":"Computer Services",
            "type":"Services"
        }
    ],
    "sg:phone":"+1 509 252 4150",
    "sg:postcode":"99206",
    "sg:province":"WA",
    "sg:tags":[
        "consultant",
        "designer",
        "datum",
        "system"
    ],
    "sg:website":"www.sssonline.com",
    "wof:name":"Spokane Software Systems Inc",
    "wof:placetype":"venue"
},
  "geometry": {"coordinates":[-117.239799,47.665176],"type":"Point"}
}