{
  "type": "Feature",
  "properties": {
    "addr:full":"2900 SW Barton St Seattle WA 98126",
    "addr:housenumber":"2900",
    "addr:postcode":"98126",
    "addr:street":"Sw Barton St",
    "iso:country":"US",
    "sg:address":"2900 SW Barton St",
    "sg:city":"Seattle",
    "sg:classifiers":[
        {
            "category":"Building & Trades",
            "subcategory":"Locksmith",
            "type":"Services"
        }
    ],
    "sg:phone":"+1 206 494 0174",
    "sg:postcode":"98126",
    "sg:province":"WA",
    "sg:tags":[
        "key"
    ],
    "wof:name":"Emergency A Locksmith",
    "wof:placetype":"venue"
},
  "geometry": {"coordinates":[-122.36995,47.521187],"type":"Point"}
}