{
  "type": "Feature",
  "properties": {
    "addr:full":"10047 NE 130th Ln Kirkland WA 98034",
    "addr:housenumber":"10047",
    "addr:postcode":"98034",
    "addr:street":"Ne 130Th Ln",
    "iso:country":"US",
    "sg:address":"10047 NE 130th Ln",
    "sg:city":"Kirkland",
    "sg:classifiers":[
        {
            "category":"Professional",
            "subcategory":"Art Services",
            "type":"Services"
        }
    ],
    "sg:phone":"+1 425 821 2992",
    "sg:postcode":"98034",
    "sg:province":"WA",
    "sg:tags":[
        "commercial",
        "design"
    ],
    "wof:name":"Alyson Ross-Markley Illu",
    "wof:placetype":"venue"
},
  "geometry": {"coordinates":[-122.207077,47.71704],"type":"Point"}
}