{
  "type": "Feature",
  "properties": {
    "addr:full":"11209 Shaw Rd E Puyallup WA 98374",
    "addr:housenumber":"11209",
    "addr:postcode":"98374",
    "addr:street":"Shaw Rd E",
    "iso:country":"US",
    "sg:address":"11209 Shaw Rd E",
    "sg:city":"Puyallup",
    "sg:classifiers":[
        {
            "category":"Shopping",
            "subcategory":"Bicycles & Sporting Goods",
            "type":"Retail Goods"
        }
    ],
    "sg:phone":"+1 253 841 0991",
    "sg:postcode":"98374",
    "sg:province":"WA",
    "sg:tags":[
        "archery",
        "fishing"
    ],
    "wof:name":"Great NW Fishing & Archery",
    "wof:placetype":"venue"
},
  "geometry": {"coordinates":[-122.25793,47.1545],"type":"Point"}
}