{
  "type": "Feature",
  "properties": {
    "addr:full":"14450 Woodinville Redmond Rd NE Ste 400 Woodinville WA 98072",
    "addr:housenumber":"14450",
    "addr:postcode":"98072",
    "addr:street":"Woodinville Redmond Rd Ne Ste 400",
    "iso:country":"US",
    "sg:address":"14450 Woodinville Redmond Rd NE Ste 400",
    "sg:city":"Woodinville",
    "sg:classifiers":[
        {
            "category":"Shopping",
            "subcategory":"Crafts & Fabrics",
            "type":"Retail Goods"
        }
    ],
    "sg:phone":"+1 425 402 9034",
    "sg:postcode":"98072",
    "sg:province":"WA",
    "sg:tags":[
        "store"
    ],
    "sg:website":"www.gatheringfabric.com",
    "wof:name":"Gathering Fabric",
    "wof:placetype":"venue"
},
  "geometry": {"coordinates":[-122.14104,47.732412],"type":"Point"}
}