{
  "type": "Feature",
  "properties": {
    "addr:full":"727 W Garland Ave Ste B Spokane WA 99205",
    "addr:housenumber":"727",
    "addr:postcode":"99205",
    "addr:street":"W Garland Ave Ste B",
    "iso:country":"US",
    "sg:address":"727 W Garland Ave Ste B",
    "sg:city":"Spokane",
    "sg:classifiers":[
        {
            "category":"Professional",
            "subcategory":"Advertising",
            "type":"Services"
        }
    ],
    "sg:phone":"+1 509 327 6688",
    "sg:postcode":"99205",
    "sg:province":"WA",
    "sg:tags":[
        "agency",
        "specialty"
    ],
    "sg:website":"http://www.quinngroup.com",
    "wof:name":"Quinn Group Advertising & Mktg",
    "wof:placetype":"venue"
},
  "geometry": {"coordinates":[-117.42227699999999,47.693481],"type":"Point"}
}