{
  "type": "Feature",
  "properties": {
    "addr:full":"1022 Summit Avenue E Seattle WA 98102",
    "addr:housenumber":"1022",
    "addr:postcode":"98102",
    "addr:street":"Summit Avenue E",
    "iso:country":"US",
    "sg:address":"1022 Summit Avenue E",
    "sg:city":"Seattle",
    "sg:classifiers":[
        {
            "category":"Real Estate",
            "subcategory":"Architect",
            "type":"Services"
        }
    ],
    "sg:phone":"+1 206 443 1011",
    "sg:postcode":"98102",
    "sg:province":"WA",
    "wof:name":"Bystrom Arne Archt",
    "wof:placetype":"venue"
},
  "geometry": {"coordinates":[-122.325236,47.627967],"type":"Point"}
}