{
  "type": "Feature",
  "properties": {
    "addr:full":"3722 27th Pl W Seattle WA 98199",
    "addr:housenumber":"3722",
    "addr:postcode":"98199",
    "addr:street":"27Th Pl W",
    "iso:country":"US",
    "sg:address":"3722 27th Pl W",
    "sg:city":"Seattle",
    "sg:classifiers":[
        {
            "category":"Shopping",
            "subcategory":"Used Merchandise",
            "type":"Retail Goods"
        },
        {
            "category":"Shopping",
            "subcategory":"Clothing, Apparel, & Fashions",
            "type":"Retail Goods"
        }
    ],
    "sg:phone":"+1 206 621 0702",
    "sg:postcode":"98199",
    "sg:province":"WA",
    "sg:tags":[
        "vintage",
        "period"
    ],
    "wof:name":"Hello Gorgeous",
    "wof:placetype":"venue"
},
  "geometry": {"coordinates":[-122.39151200000001,47.653723],"type":"Point"}
}