{
  "type": "Feature",
  "properties": {
    "addr:full":"4602 Chennault Beach Rd Mukilteo WA 98275",
    "addr:housenumber":"4602",
    "addr:postcode":"98275",
    "addr:street":"Chennault Beach Rd",
    "iso:country":"US",
    "sg:address":"4602 Chennault Beach Rd",
    "sg:city":"Mukilteo",
    "sg:classifiers":[
        {
            "category":"Shopping",
            "subcategory":"Books",
            "type":"Retail Goods"
        }
    ],
    "sg:phone":"+1 425 493 6390",
    "sg:postcode":"98275",
    "sg:province":"WA",
    "sg:tags":[
        "dealer"
    ],
    "wof:name":"Trail Stuff",
    "wof:placetype":"venue"
},
  "geometry": {"coordinates":[-122.292976,47.898471],"type":"Point"}
}