{
  "type": "Feature",
  "properties": {
    "iso:country":"US",
    "sg:address":"4002 Tacoma Mall Blvd",
    "sg:city":"Tacoma",
    "sg:classifiers":[
        {
            "category":"Professional",
            "subcategory":"Lawyer & Legal Services",
            "type":"Services"
        }
    ],
    "sg:phone":"+1 253 475 3000",
    "sg:postcode":"98409",
    "sg:province":"WA",
    "sg:tags":[
        "attorney"
    ],
    "sg:website":"www.taubfamilylawyers.com",
    "wof:name":"Robert Taub & Assoc",
    "wof:placetype":"venue"
},
  "geometry": {"coordinates":[-122.46809500000001,47.221035],"type":"Point"}
}