{
  "type": "Feature",
  "properties": {
    "iso:country":"US",
    "sg:address":"2611 N Park Dr",
    "sg:city":"Bellingham",
    "sg:classifiers":[
        {
            "category":"Shopping",
            "subcategory":"Used Merchandise",
            "type":"Retail Goods"
        }
    ],
    "sg:phone":"+1 360 733 8092",
    "sg:postcode":"98225",
    "sg:province":"WA",
    "wof:name":"Vernon Richard Hill",
    "wof:placetype":"venue"
},
  "geometry": {"coordinates":[-122.475934,48.76553],"type":"Point"}
}