{
  "type": "Feature",
  "properties": {
    "addr:full":"4314 E Portland Ave Tacoma WA 98404",
    "addr:housenumber":"4314",
    "addr:postcode":"98404",
    "addr:street":"E Portland Ave",
    "iso:country":"US",
    "sg:address":"4314 E Portland Ave",
    "sg:city":"Tacoma",
    "sg:classifiers":[
        {
            "category":"Banks & Credit Unions",
            "subcategory":"Bank",
            "type":"Services"
        }
    ],
    "sg:phone":"+1 253 472 2517",
    "sg:postcode":"98404",
    "sg:province":"WA",
    "sg:tags":[
        "depository",
        "banking",
        "check",
        "cashing"
    ],
    "wof:name":"Best Check Cashing",
    "wof:placetype":"venue"
},
  "geometry": {"coordinates":[-122.407731,47.217367],"type":"Point"}
}