{
  "type": "Feature",
  "properties": {
    "addr:full":"14809 SE 1st St Vancouver WA 98684",
    "addr:postcode":"14809;98684",
    "addr:street":"Se 1St St",
    "iso:country":"US",
    "sg:address":"14809 SE 1st St",
    "sg:city":"Vancouver",
    "sg:classifiers":[
        {
            "category":"Social Services",
            "subcategory":"Child Care",
            "type":"Services"
        }
    ],
    "sg:phone":"+1 360 256 1766",
    "sg:postcode":"98684",
    "sg:province":"WA",
    "sg:tags":[
        "day"
    ],
    "wof:name":"Anytime Child Care",
    "wof:placetype":"venue"
},
  "geometry": {"coordinates":[-122.520921,45.620883],"type":"Point"}
}