{
  "type": "Feature",
  "properties": {
    "addr:full":"1500 Vintage Rd Zillah WA 98953",
    "addr:housenumber":"1500",
    "addr:postcode":"98953",
    "addr:street":"Vintage Rd",
    "iso:country":"US",
    "sg:address":"1500 Vintage Rd",
    "sg:city":"Zillah",
    "sg:classifiers":[
        {
            "category":"Manufacturing",
            "subcategory":"Food",
            "type":"Manufacturing & Wholesale Goods"
        }
    ],
    "sg:phone":"+1 509 829 3556",
    "sg:postcode":"98953",
    "sg:province":"WA",
    "sg:tags":[
        "mfg"
    ],
    "wof:name":"Whiskey Canyon Vinyard",
    "wof:placetype":"venue"
},
  "geometry": {"coordinates":[-120.240866,46.442589],"type":"Point"}
}