{
  "type": "Feature",
  "properties": {
    "addr:full":"212 Oak St E Eatonville WA 98328",
    "addr:housenumber":"212",
    "addr:postcode":"98328",
    "addr:street":"Oak St E",
    "iso:country":"US",
    "sg:address":"212 Oak St E",
    "sg:city":"Eatonville",
    "sg:classifiers":[
        {
            "category":"Professional",
            "subcategory":"Computer Services",
            "type":"Services"
        }
    ],
    "sg:phone":"+1 360 832 8417",
    "sg:postcode":"98328",
    "sg:province":"WA",
    "sg:tags":[
        "repair"
    ],
    "wof:name":"Computer Tooter",
    "wof:placetype":"venue"
},
  "geometry": {"coordinates":[-122.264909,46.863582],"type":"Point"}
}