{
  "type": "Feature",
  "properties": {
    "addr:full":"2141 S 314th St Federal Way WA 98003",
    "addr:housenumber":"2141",
    "addr:postcode":"98003",
    "addr:street":"S 314Th St",
    "iso:country":"US",
    "sg:address":"2141 S 314th St",
    "sg:city":"Federal Way",
    "sg:classifiers":[
        {
            "category":"Shopping",
            "subcategory":"Department Store",
            "type":"Retail Goods"
        }
    ],
    "sg:phone":"+1 253 839 3399",
    "sg:postcode":"98003",
    "sg:province":"WA",
    "wof:name":"Target",
    "wof:placetype":"venue"
},
  "geometry": {"coordinates":[-122.30618200000001,47.320209],"type":"Point"}
}