{
  "type": "Feature",
  "properties": {
    "addr:full":"201 Beach Dr Sequim WA 98382",
    "addr:housenumber":"201",
    "addr:postcode":"98382",
    "addr:street":"Beach Dr",
    "iso:country":"US",
    "sg:address":"201 Beach Dr",
    "sg:city":"Sequim",
    "sg:classifiers":[
        {
            "category":"Freight",
            "type":"Transportation"
        }
    ],
    "sg:phone":"+1 360 683 8820",
    "sg:postcode":"98382",
    "sg:province":"WA",
    "sg:tags":[
        "general"
    ],
    "wof:name":"Diamond Point Storage",
    "wof:placetype":"venue"
},
  "geometry": {"coordinates":[-122.916267,48.094814],"type":"Point"}
}