{
  "type": "Feature",
  "properties": {
    "addr:full":"7101 87th St NW Gig Harbor WA 98332",
    "addr:housenumber":"7101",
    "addr:postcode":"98332",
    "addr:street":"87Th St Nw",
    "iso:country":"US",
    "sg:address":"7101 87th St NW",
    "sg:city":"Gig Harbor",
    "sg:classifiers":[
        {
            "category":"Retail",
            "subcategory":"Repair Shop",
            "type":"Services"
        }
    ],
    "sg:phone":"+1 253 853 6484",
    "sg:postcode":"98332",
    "sg:province":"WA",
    "wof:name":"Cindys Helping Hands",
    "wof:placetype":"venue"
},
  "geometry": {"coordinates":[-122.627753,47.336838],"type":"Point"}
}