{
  "type": "Feature",
  "properties": {
    "addr:full":"2701 N Lafayette Ave Bremerton WA 98312",
    "addr:housenumber":"2701",
    "addr:postcode":"98312",
    "addr:street":"N Lafayette Ave",
    "iso:country":"US",
    "sg:address":"2701 N Lafayette Ave",
    "sg:city":"Bremerton",
    "sg:classifiers":[
        {
            "category":"Professional",
            "subcategory":"Business Services",
            "type":"Services"
        }
    ],
    "sg:phone":"+1 360 478 0712",
    "sg:postcode":"98312",
    "sg:province":"WA",
    "wof:name":"Creative Endeavors",
    "wof:placetype":"venue"
},
  "geometry": {"coordinates":[-122.656121,47.5861],"type":"Point"}
}