{
  "type": "Feature",
  "properties": {
    "addr:full":"11514 15th Ave NE Seattle WA 98125",
    "addr:housenumber":"11514",
    "addr:postcode":"98125",
    "addr:street":"15Th Ave Ne",
    "iso:country":"US",
    "sg:address":"11514 15th Ave NE",
    "sg:city":"Seattle",
    "sg:classifiers":[
        {
            "category":"Professional",
            "subcategory":"Business Services",
            "type":"Services"
        }
    ],
    "sg:phone":"+1 206 362 6763",
    "sg:postcode":"98125",
    "sg:province":"WA",
    "wof:name":"Shamrock Merchant Service",
    "wof:placetype":"venue"
},
  "geometry": {"coordinates":[-122.31241799999999,47.713851],"type":"Point"}
}