{
  "type": "Feature",
  "properties": {
    "addr:full":"616 E Woodin Ave Chelan WA 98816",
    "addr:housenumber":"616",
    "addr:postcode":"98816",
    "addr:street":"E Woodin Ave",
    "iso:country":"US",
    "sg:address":"616 E Woodin Ave",
    "sg:city":"Chelan",
    "sg:classifiers":[
        {
            "category":"Retail",
            "subcategory":"Auto Repair",
            "type":"Services"
        }
    ],
    "sg:phone":"+1 509 682 9696",
    "sg:postcode":"98816",
    "sg:province":"WA",
    "sg:tags":[
        "automotive",
        "product",
        "petroleum"
    ],
    "wof:name":"Lube Town",
    "wof:placetype":"venue"
},
  "geometry": {"coordinates":[-120.008605,47.83962],"type":"Point"}
}