{
  "type": "Feature",
  "properties": {
    "addr:full":"3532 172nd St NE Arlington WA 98223",
    "addr:housenumber":"3532",
    "addr:postcode":"98223",
    "addr:street":"172Nd St Ne",
    "iso:country":"US",
    "sg:address":"3532 172nd St NE",
    "sg:city":"Arlington",
    "sg:classifiers":[
        {
            "category":"Coffee & Tea",
            "type":"Food & Drink"
        }
    ],
    "sg:menulink":"http://www.allmenus.com/wa/marysville/117788-starbucks-coffee/menu/",
    "sg:phone":"+1 360 653 4144",
    "sg:postcode":"98223",
    "sg:province":"WA",
    "sg:tags":[
        "american"
    ],
    "wof:name":"Starbucks Coffee",
    "wof:placetype":"venue"
},
  "geometry": {"coordinates":[-122.1816,48.151658],"type":"Point"}
}