{
  "type": "Feature",
  "properties": {
    "addr:full":"520 128th St SW Everett WA 98204",
    "addr:housenumber":"520",
    "addr:postcode":"98204",
    "addr:street":"128Th St Sw",
    "iso:country":"US",
    "sg:address":"520 128th St SW",
    "sg:city":"Everett",
    "sg:classifiers":[
        {
            "category":"Personal",
            "subcategory":"Beauty Salon",
            "type":"Services"
        }
    ],
    "sg:phone":"+1 425 355 4553",
    "sg:postcode":"98204",
    "sg:province":"WA",
    "sg:tags":[
        "shop"
    ],
    "wof:name":"Ishmi Salon",
    "wof:placetype":"venue"
},
  "geometry": {"coordinates":[-122.240847,47.881848],"type":"Point"}
}