{
  "type": "Feature",
  "properties": {
    "addr:full":"1521 223rd Pl NE Sammamish WA 98074",
    "addr:housenumber":"1521",
    "addr:postcode":"98074",
    "addr:street":"223Rd Pl Ne",
    "iso:country":"US",
    "sg:address":"1521 223rd Pl NE",
    "sg:city":"Sammamish",
    "sg:classifiers":[
        {
            "category":"Professional",
            "subcategory":"Computer Services",
            "type":"Services"
        }
    ],
    "sg:phone":"+1 425 868 0376",
    "sg:postcode":"98074",
    "sg:province":"WA",
    "sg:tags":[
        "software",
        "design",
        "system",
        "analysis",
        "custom"
    ],
    "wof:name":"C-Labs",
    "wof:placetype":"venue"
},
  "geometry": {"coordinates":[-122.04209400000001,47.624297],"type":"Point"}
}