{
  "type": "Feature",
  "properties": {
    "addr:full":"1704 W Wellesley Ave Spokane WA 99205",
    "addr:housenumber":"1704",
    "addr:postcode":"99205",
    "addr:street":"W Wellesley Ave",
    "iso:country":"US",
    "sg:address":"1704 W Wellesley Ave",
    "sg:city":"Spokane",
    "sg:classifiers":[
        {
            "category":"Shopping",
            "subcategory":"Music",
            "type":"Retail Goods"
        }
    ],
    "sg:phone":"+1 509 327 6008",
    "sg:postcode":"99205",
    "sg:province":"WA",
    "sg:tags":[
        "record",
        "book",
        "video",
        "cd"
    ],
    "wof:name":"Hastings Books 9831",
    "wof:placetype":"venue"
},
  "geometry": {"coordinates":[-117.43775599999999,47.7008],"type":"Point"}
}