{
  "type": "Feature",
  "properties": {
    "addr:full":"509 Olive Way Ste 833 Seattle WA 98101",
    "addr:housenumber":"509",
    "addr:postcode":"98101",
    "addr:street":"Olive Way Ste 833",
    "iso:country":"US",
    "sg:address":"509 Olive Way Ste 833",
    "sg:city":"Seattle",
    "sg:classifiers":[
        {
            "category":"Social Services",
            "type":"Services"
        }
    ],
    "sg:phone":"+1 206 522 9033",
    "sg:postcode":"98101",
    "sg:province":"WA",
    "sg:tags":[
        "worker"
    ],
    "wof:name":"Kuhlman Jane E",
    "wof:placetype":"venue"
},
  "geometry": {"coordinates":[-122.3373,47.612743],"type":"Point"}
}