{
  "type": "Feature",
  "properties": {
    "addr:full":"3210 Meridian St Bellingham WA 98225",
    "addr:housenumber":"3210",
    "addr:postcode":"98225",
    "addr:street":"Meridian St",
    "iso:country":"US",
    "sg:address":"3210 Meridian St",
    "sg:city":"Bellingham",
    "sg:classifiers":[
        {
            "category":"Organizations",
            "subcategory":"Religious Organization",
            "type":"Services"
        }
    ],
    "sg:phone":"+1 360 733 3993",
    "sg:postcode":"98225",
    "sg:province":"WA",
    "wof:name":"Abundant Life Church",
    "wof:placetype":"venue"
},
  "geometry": {"coordinates":[-122.485992,48.772334],"type":"Point"}
}