{
  "type": "Feature",
  "properties": {
    "addr:full":"9615 Levin Rd NW Silverdale WA 98383",
    "addr:housenumber":"9615",
    "addr:postcode":"98383",
    "addr:street":"Levin Rd Nw",
    "iso:country":"US",
    "sg:address":"9615 Levin Rd NW",
    "sg:city":"Silverdale",
    "sg:classifiers":[
        {
            "category":"Health Services",
            "subcategory":"Doctor",
            "type":"Services"
        }
    ],
    "sg:phone":"+1 360 613 0081",
    "sg:postcode":"98383",
    "sg:province":"WA",
    "sg:tags":[
        "medical"
    ],
    "wof:name":"Gerald G Randolph MD Inc PS",
    "wof:placetype":"venue"
},
  "geometry": {"coordinates":[-122.68462,47.653965],"type":"Point"}
}