{
  "type": "Feature",
  "properties": {
    "iso:country":"US",
    "sg:address":"10632 Tracie Ln SW",
    "sg:city":"Olympia",
    "sg:classifiers":[
        {
            "category":"Professional",
            "subcategory":"Management & Consulting",
            "type":"Services"
        }
    ],
    "sg:phone":"+1 360 753 3696",
    "sg:postcode":"98512",
    "sg:province":"WA",
    "sg:tags":[
        "consultant"
    ],
    "wof:name":"Integra Advisors LLC",
    "wof:placetype":"venue"
},
  "geometry": {"coordinates":[-123.02734,46.934272],"type":"Point"}
}