{
  "type": "Feature",
  "properties": {
    "addr:full":"2502 169th Ave NE Bellevue WA 98008",
    "addr:housenumber":"2502",
    "addr:postcode":"98008",
    "addr:street":"169Th Ave Ne",
    "iso:country":"US",
    "sg:address":"2502 169th Ave NE",
    "sg:city":"Bellevue",
    "sg:classifiers":[
        {
            "category":"Marine",
            "type":"Transportation"
        }
    ],
    "sg:phone":"+1 425 885 7605",
    "sg:postcode":"98008",
    "sg:province":"WA",
    "sg:tags":[
        "equipment",
        "supply"
    ],
    "wof:name":"American West-East Russian",
    "wof:placetype":"venue"
},
  "geometry": {"coordinates":[-122.114098,47.63261],"type":"Point"}
}