{
  "type": "Feature",
  "properties": {
    "addr:full":"29333 140th Ave SE Auburn WA 98092",
    "addr:housenumber":"29333",
    "addr:postcode":"98092",
    "addr:street":"140Th Ave Se",
    "iso:country":"US",
    "sg:address":"29333 140th Ave SE",
    "sg:city":"Auburn",
    "sg:classifiers":[
        {
            "category":"Manufacturing",
            "subcategory":"Tools & Machinery",
            "type":"Manufacturing & Wholesale Goods"
        }
    ],
    "sg:phone":"+1 253 334 6504",
    "sg:postcode":"98092",
    "sg:province":"WA",
    "sg:tags":[
        "construction",
        "mfg"
    ],
    "wof:name":"Leverage Tool",
    "wof:placetype":"venue"
},
  "geometry": {"coordinates":[-122.15495300000001,47.34187],"type":"Point"}
}