{
  "type": "Feature",
  "properties": {
    "iso:country":"US",
    "sg:address":"3520 156th St SW",
    "sg:city":"Lynnwood",
    "sg:classifiers":[
        {
            "category":"Building & Trades",
            "subcategory":"Construction",
            "type":"Services"
        }
    ],
    "sg:phone":"+1 425 742 5205",
    "sg:postcode":"98087",
    "sg:province":"WA",
    "sg:tags":[
        "general",
        "contractor"
    ],
    "wof:name":"Barr Construction Co",
    "wof:placetype":"venue"
},
  "geometry": {"coordinates":[-122.281459,47.857296],"type":"Point"}
}