{
  "type": "Feature",
  "properties": {
    "addr:full":"904 E Main St Everson WA 98247",
    "addr:housenumber":"904",
    "addr:postcode":"98247",
    "addr:street":"E Main St",
    "iso:country":"US",
    "sg:address":"904 E Main St",
    "sg:city":"Everson",
    "sg:classifiers":[
        {
            "category":"Retail",
            "subcategory":"Repair Shop",
            "type":"Services"
        }
    ],
    "sg:phone":"+1 360 966 4808",
    "sg:postcode":"98247",
    "sg:province":"WA",
    "sg:tags":[
        "electrical"
    ],
    "wof:name":"Rz Enterprises",
    "wof:placetype":"venue"
},
  "geometry": {"coordinates":[-122.33321599999999,48.920093],"type":"Point"}
}