{
  "type": "Feature",
  "properties": {
    "addr:full":"3809 S 45th St Tacoma WA 98409",
    "addr:housenumber":"3809",
    "addr:postcode":"98409",
    "addr:street":"S 45Th St",
    "iso:country":"US",
    "sg:address":"3809 S 45th St",
    "sg:city":"Tacoma",
    "sg:classifiers":[
        {
            "category":"Autos & Motor Vehicles",
            "subcategory":"Automobile Sales",
            "type":"Retail Goods"
        }
    ],
    "sg:phone":"+1 253 472 2939",
    "sg:postcode":"98409",
    "sg:province":"WA",
    "sg:tags":[
        "car",
        "dealer"
    ],
    "wof:name":"Storey's Auto Sales",
    "wof:placetype":"venue"
},
  "geometry": {"coordinates":[-122.48633700000001,47.216859],"type":"Point"}
}