{
  "type": "Feature",
  "properties": {
    "addr:full":"853 Hiawatha Pl S Seattle WA 98144",
    "addr:housenumber":"853",
    "addr:postcode":"98144",
    "addr:street":"Hiawatha Pl S",
    "iso:country":"US",
    "sg:address":"853 Hiawatha Pl S",
    "sg:city":"Seattle",
    "sg:classifiers":[
        {
            "category":"Organizations",
            "subcategory":"Non-profit Organization",
            "type":"Services"
        }
    ],
    "sg:phone":"+1 206 323 1848",
    "sg:postcode":"98144",
    "sg:province":"WA",
    "sg:tags":[
        "service/non-profit",
        "community"
    ],
    "wof:name":"Youth Venture",
    "wof:placetype":"venue"
},
  "geometry": {"coordinates":[-122.309764,47.595041],"type":"Point"}
}