{
  "type": "Feature",
  "properties": {
    "iso:country":"US",
    "sg:address":"9722 Lake Shore Blvd NE",
    "sg:city":"Seattle",
    "sg:classifiers":[
        {
            "category":"Professional",
            "subcategory":"Engineering",
            "type":"Services"
        },
        {
            "category":"Professional",
            "subcategory":"Management & Consulting",
            "type":"Services"
        }
    ],
    "sg:phone":"+1 206 529 8150",
    "sg:postcode":"98115",
    "sg:province":"WA",
    "sg:tags":[
        "consultant",
        "business"
    ],
    "wof:name":"J 2 Resources",
    "wof:placetype":"venue"
},
  "geometry": {"coordinates":[-122.27382900000001,47.701114],"type":"Point"}
}