{
  "type": "Feature",
  "properties": {
    "addr:full":"1606 4th St Marysville WA 98270",
    "addr:housenumber":"1606",
    "addr:postcode":"98270",
    "addr:street":"4Th St",
    "iso:country":"US",
    "sg:address":"1606 4th St",
    "sg:city":"Marysville",
    "sg:classifiers":[
        {
            "category":"Personal",
            "type":"Services"
        },
        {
            "category":"Health Services",
            "subcategory":"Health Practitioner",
            "type":"Services"
        }
    ],
    "sg:phone":"+1 360 657 2755",
    "sg:postcode":"98270",
    "sg:province":"WA",
    "sg:tags":[
        "therapist",
        "massage"
    ],
    "wof:name":"Breezeway Therapeutic Center",
    "wof:placetype":"venue"
},
  "geometry": {"coordinates":[-122.173237,48.051751],"type":"Point"}
}