{
  "type": "Feature",
  "properties": {
    "addr:full":"8505 Waldrick Rd SE Tenino WA 98589",
    "addr:housenumber":"8505",
    "addr:postcode":"98589",
    "addr:street":"Waldrick Rd Se Tenino",
    "iso:country":"US",
    "sg:address":"8505 Waldrick Rd SE",
    "sg:city":"Tenino",
    "sg:classifiers":[
        {
            "category":"Building & Trades",
            "subcategory":"Construction",
            "type":"Services"
        }
    ],
    "sg:phone":"+1 360 264 5649",
    "sg:postcode":"98589",
    "sg:province":"WA",
    "sg:tags":[
        "general",
        "contractor"
    ],
    "wof:name":"Pratt's Services",
    "wof:placetype":"venue"
},
  "geometry": {"coordinates":[-122.759283,46.900918],"type":"Point"}
}