{
  "type": "Feature",
  "properties": {
    "addr:full":"9508 E 24th Ave Spokane WA 99206",
    "addr:housenumber":"9508",
    "addr:postcode":"99206",
    "addr:street":"E 24Th Ave",
    "iso:country":"US",
    "sg:address":"9508 E 24th Ave",
    "sg:city":"Spokane",
    "sg:classifiers":[
        {
            "category":"Building & Trades",
            "subcategory":"Construction",
            "type":"Services"
        }
    ],
    "sg:phone":"+1 509 924 7617",
    "sg:postcode":"99206",
    "sg:province":"WA",
    "sg:tags":[
        "house",
        "nonresidential"
    ],
    "wof:name":"Tedesco Construction",
    "wof:placetype":"venue"
},
  "geometry": {"coordinates":[-117.27739,47.634959],"type":"Point"}
}