{
  "type": "Feature",
  "properties": {
    "addr:full":"1402 NW 85th St Seattle WA 98117",
    "addr:housenumber":"1402",
    "addr:postcode":"98117",
    "addr:street":"Nw 85Th St",
    "iso:country":"US",
    "sg:address":"1402 NW 85th St",
    "sg:city":"Seattle",
    "sg:classifiers":[
        {
            "category":"Coffee & Tea",
            "type":"Food & Drink"
        }
    ],
    "sg:phone":"+1 206 652 4880",
    "sg:postcode":"98117",
    "sg:province":"WA",
    "sg:website":"www.atlascoffee.com",
    "wof:name":"Atlas Coffee Importers",
    "wof:placetype":"venue"
},
  "geometry": {"coordinates":[-122.37400100000001,47.690701],"type":"Point"}
}