{
  "type": "Feature",
  "properties": {
    "addr:full":"102 Fickett Rd Onalaska WA 98570",
    "addr:housenumber":"102",
    "addr:postcode":"98570",
    "addr:street":"Fickett Rd",
    "iso:country":"US",
    "sg:address":"102 Fickett Rd",
    "sg:city":"Onalaska",
    "sg:classifiers":[
        {
            "category":"Retail",
            "subcategory":"Auto Repair",
            "type":"Services"
        }
    ],
    "sg:phone":"+1 360 978 6106",
    "sg:postcode":"98570",
    "sg:province":"WA",
    "sg:tags":[
        "general"
    ],
    "wof:name":"M & H Hotrods",
    "wof:placetype":"venue"
},
  "geometry": {"coordinates":[-122.693273,46.57728],"type":"Point"}
}