{
  "type": "Feature",
  "properties": {
    "addr:full":"9202 SW Harbor Dr Vashon WA 98070",
    "addr:housenumber":"9202",
    "addr:postcode":"98070",
    "addr:street":"Sw Harbor Dr",
    "iso:country":"US",
    "sg:address":"9202 SW Harbor Dr",
    "sg:city":"Vashon",
    "sg:classifiers":[
        {
            "category":"Professional",
            "subcategory":"Computer Services",
            "type":"Services"
        }
    ],
    "sg:phone":"+1 206 463 9015",
    "sg:postcode":"98070",
    "sg:province":"WA",
    "sg:tags":[
        "programming",
        "custom"
    ],
    "wof:name":"Symmetrics Business Intelligen",
    "wof:placetype":"venue"
},
  "geometry": {"coordinates":[-122.45036899999999,47.393095],"type":"Point"}
}