{
  "type": "Feature",
  "properties": {
    "addr:full":"6903 135th Pl SE Snohomish WA 98296",
    "addr:housenumber":"6903",
    "addr:postcode":"98296",
    "addr:street":"135Th Pl Se",
    "iso:country":"US",
    "sg:address":"6903 135th Pl SE",
    "sg:city":"Snohomish",
    "sg:classifiers":[
        {
            "category":"Professional",
            "subcategory":"Detective & Security Services",
            "type":"Services"
        }
    ],
    "sg:phone":"+1 425 357 5979",
    "sg:postcode":"98296",
    "sg:province":"WA",
    "sg:tags":[
        "car"
    ],
    "wof:name":"Sentry Systems",
    "wof:placetype":"venue"
},
  "geometry": {"coordinates":[-122.163889,47.875808],"type":"Point"}
}