{
  "type": "Feature",
  "properties": {
    "addr:full":"263 NW Chehalis Ave  Chehalis WA 98532",
    "addr:housenumber":"263",
    "addr:postcode":"98532",
    "addr:street":"Nw Chehalis Ave",
    "iso:country":"US",
    "sg:address":"263 NW Chehalis Ave ",
    "sg:city":"Chehalis",
    "sg:classifiers":[
        {
            "category":"Restaurant",
            "type":"Food & Drink"
        }
    ],
    "sg:menulink":"http://www.allmenus.com/wa/centralia-chehalis/293538-lamour-de-scotty/menu/",
    "sg:phone":"+1 360 740 9227",
    "sg:postcode":"98532",
    "sg:province":"WA",
    "sg:tags":[
        "french"
    ],
    "wof:name":"L'amour de Scotty",
    "wof:placetype":"venue"
},
  "geometry": {"coordinates":[-122.97024,46.663047],"type":"Point"}
}