{
  "type": "Feature",
  "properties": {
    "addr:full":"18621 N Yale Rd Colbert WA 99005",
    "addr:housenumber":"18621",
    "addr:postcode":"99005",
    "addr:street":"N Yale Rd Colbert",
    "iso:country":"US",
    "sg:address":"18621 N Yale Rd",
    "sg:city":"Colbert",
    "sg:classifiers":[
        {
            "category":"Government",
            "subcategory":"Post Office",
            "type":"Public Place"
        }
    ],
    "sg:phone":"+1 509 000 1111",
    "sg:postcode":"99005",
    "sg:province":"WA",
    "wof:name":"US Post Office",
    "wof:placetype":"venue"
},
  "geometry": {"coordinates":[-117.347139,47.828256],"type":"Point"}
}