{
  "type": "Feature",
  "properties": {
    "addr:full":"1531 W Sims Way Port Townsend WA 98368",
    "addr:housenumber":"1531",
    "addr:postcode":"98368",
    "addr:street":"W Sims Way",
    "iso:country":"US",
    "sg:address":"1531 W Sims Way",
    "sg:city":"Port Townsend",
    "sg:classifiers":[
        {
            "category":"Autos & Motor Vehicles",
            "subcategory":"Automobile Sales",
            "type":"Retail Goods"
        }
    ],
    "sg:phone":"+1 360 379 1335",
    "sg:postcode":"98368",
    "sg:province":"WA",
    "sg:tags":[
        "car",
        "dealer"
    ],
    "wof:name":"Houston Motors",
    "wof:placetype":"venue"
},
  "geometry": {"coordinates":[-122.794408,48.10321],"type":"Point"}
}