{
  "type": "Feature",
  "properties": {
    "addr:full":"2525 NE Park Dr Issaquah WA 98029",
    "addr:housenumber":"2525",
    "addr:postcode":"98029",
    "addr:street":"Ne Park Dr",
    "iso:country":"US",
    "sg:address":"2525 NE Park Dr",
    "sg:city":"Issaquah",
    "sg:classifiers":[
        {
            "category":"Restaurant",
            "type":"Food & Drink"
        }
    ],
    "sg:phone":"+1 425 893 8646",
    "sg:postcode":"98029",
    "sg:province":"WA",
    "wof:name":"Zeeks",
    "wof:placetype":"venue"
},
  "geometry": {"coordinates":[-121.99538099999999,47.548011],"type":"Point"}
}