{
  "type": "Feature",
  "properties": {
    "iso:country":"US",
    "sg:address":"412 N Commercial St",
    "sg:city":"Bellingham",
    "sg:classifiers":[
        {
            "category":"Professional",
            "subcategory":"Lawyer & Legal Services",
            "type":"Services"
        }
    ],
    "sg:phone":"+1 360 671 9212",
    "sg:postcode":"98225",
    "sg:province":"WA",
    "sg:tags":[
        "attorney"
    ],
    "sg:website":"www.rhf-law.com",
    "wof:name":"Resick Hansen & Follis",
    "wof:placetype":"venue"
},
  "geometry": {"coordinates":[-122.478032,48.755004],"type":"Point"}
}