{
  "type": "Feature",
  "properties": {
    "addr:full":"1940 116th Ave NE Ste 101 Bellevue WA 98004",
    "addr:housenumber":"1940",
    "addr:postcode":"98004",
    "addr:street":"116Th Ave Ne Ste 101",
    "iso:country":"US",
    "sg:address":"1940 116th Ave NE Ste 101",
    "sg:city":"Bellevue",
    "sg:classifiers":[
        {
            "category":"Health Services",
            "subcategory":"Chiropractor",
            "type":"Services"
        }
    ],
    "sg:phone":"+1 425 635 0495",
    "sg:postcode":"98004",
    "sg:province":"WA",
    "sg:website":"www.backinactionchiropractic.com",
    "wof:name":"Back In Action Chiropractic Clinic",
    "wof:placetype":"venue"
},
  "geometry": {"coordinates":[-122.185676,47.627456],"type":"Point"}
}