{
  "type": "Feature",
  "properties": {
    "addr:full":"17006 SE May Valley Rd Renton WA 98059",
    "addr:postcode":"17006;98059",
    "addr:street":"Se May Valley Rd",
    "iso:country":"US",
    "sg:address":"17006 SE May Valley Rd",
    "sg:city":"Renton",
    "sg:classifiers":[
        {
            "category":"Building & Trades",
            "subcategory":"Construction",
            "type":"Services"
        }
    ],
    "sg:phone":"+1 425 226 6436",
    "sg:postcode":"98059",
    "sg:province":"WA",
    "sg:tags":[
        "contractor"
    ],
    "wof:name":"Edwards Masonry",
    "wof:placetype":"venue"
},
  "geometry": {"coordinates":[-122.111891,47.500505],"type":"Point"}
}