{
  "type": "Feature",
  "properties": {
    "addr:full":"1123 SW 4th Ave Oak Harbor WA 98277",
    "addr:housenumber":"1123",
    "addr:postcode":"98277",
    "addr:street":"Sw 4Th Ave",
    "iso:country":"US",
    "sg:address":"1123 SW 4th Ave",
    "sg:city":"Oak Harbor",
    "sg:classifiers":[
        {
            "category":"Retail",
            "subcategory":"Laundry & Dry Cleaning",
            "type":"Services"
        }
    ],
    "sg:phone":"+1 360 679 8573",
    "sg:postcode":"98277",
    "sg:province":"WA",
    "sg:tags":[
        "carpet"
    ],
    "wof:name":"C H Beck",
    "wof:placetype":"venue"
},
  "geometry": {"coordinates":[-122.67143900000001,48.29555],"type":"Point"}
}