{
  "type": "Feature",
  "properties": {
    "addr:full":"407 14th Ave SE Puyallup WA 98372",
    "addr:housenumber":"407",
    "addr:postcode":"98372",
    "addr:street":"14Th Ave Se",
    "iso:country":"US",
    "sg:address":"407 14th Ave SE",
    "sg:city":"Puyallup",
    "sg:classifiers":[
        {
            "category":"Social Services",
            "type":"Services"
        }
    ],
    "sg:phone":"+1 253 697 3940",
    "sg:postcode":"98372",
    "sg:province":"WA",
    "sg:tags":[
        "senior",
        "citizen"
    ],
    "wof:name":"Celebrate Seniority",
    "wof:placetype":"venue"
},
  "geometry": {"coordinates":[-122.28828900000001,47.178821],"type":"Point"}
}