{
  "type": "Feature",
  "properties": {
    "addr:full":"4138 Midvale Ave N Seattle WA 98103",
    "addr:housenumber":"4138",
    "addr:postcode":"98103",
    "addr:street":"Midvale Ave N",
    "iso:country":"US",
    "sg:address":"4138 Midvale Ave N",
    "sg:city":"Seattle",
    "sg:classifiers":[
        {
            "category":"Social Services",
            "type":"Services"
        }
    ],
    "sg:phone":"+1 206 547 2590",
    "sg:postcode":"98103",
    "sg:province":"WA",
    "wof:name":"Solutions",
    "wof:placetype":"venue"
},
  "geometry": {"coordinates":[-122.343479,47.657486],"type":"Point"}
}