{
  "type": "Feature",
  "properties": {
    "iso:country":"US",
    "sg:address":"850 W Front St",
    "sg:city":"Sumas",
    "sg:classifiers":[
        {
            "category":"Manufacturing",
            "subcategory":"Petroleum Products",
            "type":"Manufacturing & Wholesale Goods"
        }
    ],
    "sg:phone":"+1 360 988 9103",
    "sg:postcode":"98295",
    "sg:province":"WA",
    "sg:tags":[
        "asphalt",
        "mfg"
    ],
    "wof:name":"Iko Pacific",
    "wof:placetype":"venue"
},
  "geometry": {"coordinates":[-122.257685,48.99281],"type":"Point"}
}