{
  "type": "Feature",
  "properties": {
    "addr:full":"17039 Bothell Way NE Seattle WA 98155",
    "addr:housenumber":"17039",
    "addr:postcode":"98155",
    "addr:street":"Bothell Way Ne",
    "iso:country":"US",
    "sg:address":"17039 Bothell Way NE",
    "sg:city":"Seattle",
    "sg:classifiers":[
        {
            "category":"Coffee & Tea",
            "type":"Food & Drink"
        }
    ],
    "sg:menulink":"http://www.allmenus.com/wa/seattle/117624-starbucks-coffee/menu/",
    "sg:phone":"+1 206 367 3811",
    "sg:postcode":"98155",
    "sg:province":"WA",
    "sg:tags":[
        "american"
    ],
    "wof:name":"Starbucks Coffee",
    "wof:placetype":"venue"
},
  "geometry": {"coordinates":[-122.28041399999999,47.752035],"type":"Point"}
}