{
  "type": "Feature",
  "properties": {
    "addr:full":"6806 N Brenda Ct Spokane WA 99208",
    "addr:housenumber":"6806",
    "addr:postcode":"99208",
    "addr:street":"N Brenda Ct",
    "iso:country":"US",
    "sg:address":"6806 N Brenda Ct",
    "sg:city":"Spokane",
    "sg:classifiers":[
        {
            "category":"Professional",
            "subcategory":"Business Services",
            "type":"Services"
        }
    ],
    "sg:phone":"+1 509 838 8200",
    "sg:postcode":"99208",
    "sg:province":"WA",
    "wof:name":"Solution Equity LLC",
    "wof:placetype":"venue"
},
  "geometry": {"coordinates":[-117.47708799999999,47.7196],"type":"Point"}
}