{
  "type": "Feature",
  "properties": {
    "addr:full":"1150 W Spruce Ct Sequim WA 98382",
    "addr:housenumber":"1150",
    "addr:postcode":"98382",
    "addr:street":"W Spruce Ct",
    "iso:country":"US",
    "sg:address":"1150 W Spruce Ct",
    "sg:city":"Sequim",
    "sg:classifiers":[
        {
            "category":"Professional",
            "type":"Services"
        }
    ],
    "sg:phone":"+1 360 683 5149",
    "sg:postcode":"98382",
    "sg:province":"WA",
    "sg:tags":[
        "information",
        "bureau"
    ],
    "wof:name":"Brooks Technical Services",
    "wof:placetype":"venue"
},
  "geometry": {"coordinates":[-123.130431,48.081606],"type":"Point"}
}