{
  "type": "Feature",
  "properties": {
    "addr:full":"12534 Rd 8 NE Moses Lake WA 98837",
    "addr:housenumber":"12534",
    "addr:postcode":"98837",
    "addr:street":"Rd 8 Ne",
    "iso:country":"US",
    "sg:address":"12534 Rd 8 NE",
    "sg:city":"Moses Lake",
    "sg:classifiers":[
        {
            "category":"Farming",
            "subcategory":"Farm & Veterinary Services",
            "type":"Manufacturing & Wholesale Goods"
        }
    ],
    "sg:phone":"+1 509 765 6720",
    "sg:postcode":"98837",
    "sg:province":"WA",
    "sg:tags":[
        "crop",
        "harvesting"
    ],
    "wof:name":"Caraway Custom Hay Stacking",
    "wof:placetype":"venue"
},
  "geometry": {"coordinates":[-119.22313699999999,47.204169],"type":"Point"}
}