{
  "type": "Feature",
  "properties": {
    "addr:full":"26527 175th Ave SE Kent WA 98042",
    "addr:housenumber":"26527",
    "addr:postcode":"98042",
    "addr:street":"175Th Ave Se",
    "iso:country":"US",
    "sg:address":"26527 175th Ave SE",
    "sg:city":"Kent",
    "sg:classifiers":[
        {
            "category":"Building & Trades",
            "subcategory":"Landscaping Services",
            "type":"Services"
        }
    ],
    "sg:phone":"+1 253 630 2016",
    "sg:postcode":"98042",
    "sg:province":"WA",
    "wof:name":"Foothills Irrigation & La",
    "wof:placetype":"venue"
},
  "geometry": {"coordinates":[-122.108052,47.363957],"type":"Point"}
}