{
  "type": "Feature",
  "properties": {
    "addr:full":"9101 NE Ward Rd Vancouver WA 98682",
    "addr:housenumber":"9101",
    "addr:postcode":"98682",
    "addr:street":"Ne Ward Rd",
    "iso:country":"US",
    "sg:address":"9101 NE Ward Rd",
    "sg:city":"Vancouver",
    "sg:classifiers":[
        {
            "category":"Retail",
            "subcategory":"Auto Repair",
            "type":"Services"
        }
    ],
    "sg:phone":"+1 360 256 3688",
    "sg:postcode":"98682",
    "sg:province":"WA",
    "sg:tags":[
        "body",
        "painting",
        "repairing",
        "automobile"
    ],
    "wof:name":"Ray's Auto Body",
    "wof:placetype":"venue"
},
  "geometry": {"coordinates":[-122.497514,45.68992],"type":"Point"}
}