{
  "type": "Feature",
  "properties": {
    "addr:full":"516 N Oregon Ave Pasco WA 99301",
    "addr:housenumber":"516",
    "addr:postcode":"99301",
    "addr:street":"N Oregon Ave",
    "iso:country":"US",
    "sg:address":"516 N Oregon Ave",
    "sg:city":"Pasco",
    "sg:classifiers":[
        {
            "category":"Home & Garden",
            "subcategory":"Hardware",
            "type":"Retail Goods"
        }
    ],
    "sg:phone":"+1 509 547 5513",
    "sg:postcode":"99301",
    "sg:province":"WA",
    "sg:tags":[
        "store"
    ],
    "wof:name":"Pasco Ranch and Home",
    "wof:placetype":"venue"
},
  "geometry": {"coordinates":[-119.08200100000001,46.237801],"type":"Point"}
}