{
  "type": "Feature",
  "properties": {
    "addr:full":"2010 Fruitvale Blvd Yakima WA 98902",
    "addr:housenumber":"2010",
    "addr:postcode":"98902",
    "addr:street":"Fruitvale Blvd",
    "iso:country":"US",
    "sg:address":"2010 Fruitvale Blvd",
    "sg:city":"Yakima",
    "sg:classifiers":[
        {
            "category":"Home & Garden",
            "subcategory":"Garden Supply",
            "type":"Retail Goods"
        }
    ],
    "sg:phone":"+1 509 453 9966",
    "sg:postcode":"98902",
    "sg:province":"WA",
    "sg:tags":[
        "repair",
        "chainsaw",
        "lawn",
        "lawnmowers",
        "mower"
    ],
    "wof:name":"Smitty's Outdoor Power Equip",
    "wof:placetype":"venue"
},
  "geometry": {"coordinates":[-120.53672400000001,46.612496],"type":"Point"}
}