{
  "type": "Feature",
  "properties": {
    "addr:full":"3932 S 293rd St Auburn WA 98001",
    "addr:housenumber":"3932",
    "addr:postcode":"98001",
    "addr:street":"S 293Rd St",
    "iso:country":"US",
    "sg:address":"3932 S 293rd St",
    "sg:city":"Auburn",
    "sg:classifiers":[
        {
            "category":"Insurance",
            "subcategory":"Insurance Agent",
            "type":"Services"
        }
    ],
    "sg:phone":"+1 253 941 1077",
    "sg:postcode":"98001",
    "sg:province":"WA",
    "sg:tags":[
        "agency"
    ],
    "wof:name":"MI Benefits",
    "wof:placetype":"venue"
},
  "geometry": {"coordinates":[-122.281612,47.339137],"type":"Point"}
}