{
  "type": "Feature",
  "properties": {
    "addr:full":"4150 Beachmont Dr Clinton WA 98236",
    "addr:housenumber":"4150",
    "addr:postcode":"98236",
    "addr:street":"Beachmont Dr",
    "iso:country":"US",
    "sg:address":"4150 Beachmont Dr",
    "sg:city":"Clinton",
    "sg:classifiers":[
        {
            "category":"Building & Trades",
            "subcategory":"Electrical",
            "type":"Services"
        }
    ],
    "sg:phone":"+1 206 789 4371",
    "sg:postcode":"98236",
    "sg:province":"WA",
    "sg:tags":[
        "electrician"
    ],
    "wof:name":"Green Lake Electric",
    "wof:placetype":"venue"
},
  "geometry": {"coordinates":[-122.38946199999999,47.971256],"type":"Point"}
}