{
  "type": "Feature",
  "properties": {
    "addr:full":"171 Carlsborg Rd Sequim WA 98382",
    "addr:housenumber":"171",
    "addr:postcode":"98382",
    "addr:street":"Carlsborg Rd",
    "iso:country":"US",
    "sg:address":"171 Carlsborg Rd",
    "sg:city":"Sequim",
    "sg:classifiers":[
        {
            "category":"Education",
            "subcategory":"School",
            "type":"Public Place"
        }
    ],
    "sg:phone":"+1 360 582 3300",
    "sg:postcode":"98382",
    "sg:province":"WA",
    "sg:tags":[
        "elementary"
    ],
    "sg:website":"http://www.sequimschools.wednet.edu",
    "wof:name":"Greywolf Elementary School",
    "wof:placetype":"venue"
},
  "geometry": {"coordinates":[-123.172949,48.081712],"type":"Point"}
}