{
  "type": "Feature",
  "properties": {
    "addr:full":"520 Pike St Ste 2700 Seattle WA 98101",
    "addr:housenumber":"520",
    "addr:postcode":"98101",
    "addr:street":"Pike St Ste 2700",
    "iso:country":"US",
    "sg:address":"520 Pike St Ste 2700",
    "sg:city":"Seattle",
    "sg:classifiers":[
        {
            "category":"Insurance",
            "subcategory":"Hazard Insurance",
            "type":"Services"
        }
    ],
    "sg:phone":"+1 206 447 0500",
    "sg:postcode":"98101",
    "sg:province":"WA",
    "sg:tags":[
        "commercial",
        "business"
    ],
    "wof:name":"Acordia Northwest Inc",
    "wof:placetype":"venue"
},
  "geometry": {"coordinates":[-122.33540499999999,47.610771],"type":"Point"}
}