{
  "type": "Feature",
  "properties": {
    "addr:full":"19420 162nd Ave NE Woodinville WA 98072",
    "addr:housenumber":"19420",
    "addr:postcode":"98072",
    "addr:street":"162Nd Ave Ne",
    "iso:country":"US",
    "sg:address":"19420 162nd Ave NE",
    "sg:city":"Woodinville",
    "sg:classifiers":[
        {
            "category":"Manufacturing",
            "subcategory":"Building Materials",
            "type":"Manufacturing & Wholesale Goods"
        }
    ],
    "sg:phone":"+1 425 482 2789",
    "sg:postcode":"98072",
    "sg:province":"WA",
    "sg:tags":[
        "mfg"
    ],
    "wof:name":"Aspen Woodworks",
    "wof:placetype":"venue"
},
  "geometry": {"coordinates":[-122.123459,47.768245],"type":"Point"}
}