{
  "type": "Feature",
  "properties": {
    "addr:full":"1619 267th St NW Stanwood WA 98292",
    "addr:housenumber":"1619",
    "addr:postcode":"98292",
    "addr:street":"267Th St Nw",
    "iso:country":"US",
    "sg:address":"1619 267th St NW",
    "sg:city":"Stanwood",
    "sg:classifiers":[
        {
            "category":"Travel",
            "subcategory":"Travel Agent",
            "type":"Entertainment"
        }
    ],
    "sg:phone":"+1 360 629 6381",
    "sg:postcode":"98292",
    "sg:province":"WA",
    "sg:tags":[
        "agency"
    ],
    "wof:name":"Anchor Travel Cruise Ctr",
    "wof:placetype":"venue"
},
  "geometry": {"coordinates":[-122.255094,48.237676],"type":"Point"}
}