{
  "type": "Feature",
  "properties": {
    "addr:full":"1503 304th St S Roy WA 98580",
    "addr:housenumber":"1503",
    "addr:postcode":"98580",
    "addr:street":"304Th St S",
    "iso:country":"US",
    "sg:address":"1503 304th St S",
    "sg:city":"Roy",
    "sg:classifiers":[
        {
            "category":"Building & Trades",
            "subcategory":"Cleaning & Sanitation",
            "type":"Services"
        }
    ],
    "sg:phone":"+1 253 843 2587",
    "sg:postcode":"98580",
    "sg:province":"WA",
    "sg:tags":[
        "maintenance"
    ],
    "wof:name":"Sally Lagergrens Cleaning Svcs",
    "wof:placetype":"venue"
},
  "geometry": {"coordinates":[-122.45291899999999,46.981034],"type":"Point"}
}