{
  "type": "Feature",
  "properties": {
    "iso:country":"US",
    "sg:address":"4411 S Grove Rd",
    "sg:city":"Spokane",
    "sg:classifiers":[
        {
            "category":"Freight",
            "type":"Transportation"
        }
    ],
    "sg:phone":"+1 509 838 7006",
    "sg:postcode":"99224",
    "sg:province":"WA",
    "sg:tags":[
        "operator",
        "local",
        "trucking"
    ],
    "wof:name":"Prudence Supply Express",
    "wof:placetype":"venue"
},
  "geometry": {"coordinates":[-117.49678900000001,47.613385],"type":"Point"}
}