{
  "type": "Feature",
  "properties": {
    "addr:full":"19101 36th Ave W Lynnwood WA 98036",
    "addr:housenumber":"19101",
    "addr:postcode":"98036",
    "addr:street":"36Th Ave W",
    "iso:country":"US",
    "sg:address":"19101 36th Ave W",
    "sg:city":"Lynnwood",
    "sg:classifiers":[
        {
            "category":"Professional",
            "subcategory":"Accounting & Tax Preparation",
            "type":"Services"
        }
    ],
    "sg:phone":"+1 425 778 1944",
    "sg:postcode":"98036",
    "sg:province":"WA",
    "sg:tags":[
        "accountant"
    ],
    "wof:name":"Bergman Group Ps",
    "wof:placetype":"venue"
},
  "geometry": {"coordinates":[-122.281766,47.828125],"type":"Point"}
}