{
  "type": "Feature",
  "properties": {
    "addr:full":"4001 SE Crown Rd Camas WA 98607",
    "addr:housenumber":"4001",
    "addr:postcode":"98607",
    "addr:street":"Se Crown Rd",
    "iso:country":"US",
    "sg:address":"4001 SE Crown Rd",
    "sg:city":"Camas",
    "sg:classifiers":[
        {
            "category":"Manufacturing",
            "subcategory":"Rubber & Plastics",
            "type":"Manufacturing & Wholesale Goods"
        }
    ],
    "sg:phone":"+1 360 834 3986",
    "sg:postcode":"98607",
    "sg:province":"WA",
    "sg:tags":[
        "product",
        "foam",
        "mfg"
    ],
    "wof:name":"Mr Ed Floats",
    "wof:placetype":"venue"
},
  "geometry": {"coordinates":[-122.389493,45.591568],"type":"Point"}
}