{
  "type": "Feature",
  "properties": {
    "iso:country":"US",
    "sg:address":"624 E Maberry Dr",
    "sg:city":"Lynden",
    "sg:classifiers":[
        {
            "category":"Health Services",
            "subcategory":"Health Practitioner",
            "type":"Services"
        }
    ],
    "sg:phone":"+1 360 354 0201",
    "sg:postcode":"98264",
    "sg:province":"WA",
    "wof:name":"Lori Fay Libolt",
    "wof:placetype":"venue"
},
  "geometry": {"coordinates":[-122.443167,48.955734],"type":"Point"}
}