{
  "type": "Feature",
  "properties": {
    "addr:full":"1003 W University Way Ellensburg WA 98926",
    "addr:housenumber":"1003",
    "addr:postcode":"98926",
    "addr:street":"W University Way",
    "iso:country":"US",
    "sg:address":"1003 W University Way",
    "sg:city":"Ellensburg",
    "sg:phone":"+1 509 925 4140",
    "sg:postcode":"98926",
    "sg:province":"WA",
    "sg:website":"http://www.chinainn.info",
    "wof:name":"China Inn",
    "wof:placetype":"venue"
},
  "geometry": {"coordinates":[-120.565445,47.004669],"type":"Point"}
}