{
  "type": "Feature",
  "properties": {
    "addr:full":"110 NE Whitman St Pullman WA 99163",
    "addr:housenumber":"110",
    "addr:postcode":"99163",
    "addr:street":"Ne Whitman St",
    "iso:country":"US",
    "sg:address":"110 NE Whitman St",
    "sg:city":"Pullman",
    "sg:classifiers":[
        {
            "category":"Freight",
            "type":"Transportation"
        }
    ],
    "sg:phone":"+1 509 332 1281",
    "sg:postcode":"99163",
    "sg:province":"WA",
    "sg:tags":[
        "commercial",
        "storage"
    ],
    "wof:name":"Grand Avenue Storage & Supply",
    "wof:placetype":"venue"
},
  "geometry": {"coordinates":[-117.178888,46.732136],"type":"Point"}
}