{
  "type": "Feature",
  "properties": {
    "addr:full":"300 Lenora St Seattle WA 98121",
    "addr:housenumber":"300",
    "addr:postcode":"98121",
    "addr:street":"Lenora St",
    "iso:country":"US",
    "sg:address":"300 Lenora St",
    "sg:city":"Seattle",
    "sg:classifiers":[
        {
            "category":"Building & Trades",
            "subcategory":"Locksmith",
            "type":"Services"
        }
    ],
    "sg:phone":"+1 206 552 7153",
    "sg:postcode":"98121",
    "sg:province":"WA",
    "sg:tags":[
        "key"
    ],
    "wof:name":"One Emergency Locksmith",
    "wof:placetype":"venue"
},
  "geometry": {"coordinates":[-122.34228,47.613316],"type":"Point"}
}