{
  "type": "Feature",
  "properties": {
    "addr:full":"601 W Hendrickson Rd Sequim WA 98382",
    "addr:housenumber":"601",
    "addr:postcode":"98382",
    "addr:street":"W Hendrickson Rd",
    "iso:country":"US",
    "sg:address":"601 W Hendrickson Rd",
    "sg:city":"Sequim",
    "sg:classifiers":[
        {
            "category":"Wholesale",
            "subcategory":"Medical Equipment & Supplies",
            "type":"Manufacturing & Wholesale Goods"
        }
    ],
    "sg:phone":"+1 360 681 4482",
    "sg:postcode":"98382",
    "sg:province":"WA",
    "sg:tags":[
        "e"
    ],
    "wof:name":"Plympic Oxygen",
    "wof:placetype":"venue"
},
  "geometry": {"coordinates":[-123.116777,48.086852],"type":"Point"}
}