{
  "type": "Feature",
  "properties": {
    "addr:full":"7601 196th Ave NE Redmond WA 98053",
    "addr:housenumber":"7601",
    "addr:postcode":"98053",
    "addr:street":"196Th Ave Ne",
    "iso:country":"US",
    "sg:address":"7601 196th Ave NE",
    "sg:city":"Redmond",
    "sg:classifiers":[
        {
            "category":"Retail",
            "subcategory":"Portrait Studio",
            "type":"Services"
        }
    ],
    "sg:phone":"+1 425 868 6137",
    "sg:postcode":"98053",
    "sg:province":"WA",
    "sg:tags":[
        "photo"
    ],
    "wof:name":"Shepards Photography",
    "wof:placetype":"venue"
},
  "geometry": {"coordinates":[-122.079069,47.67373],"type":"Point"}
}