{
  "type": "Feature",
  "properties": {
    "iso:country":"US",
    "sg:address":"9921 US Hwy 12",
    "sg:city":"Naches",
    "sg:classifiers":[
        {
            "category":"Restaurant",
            "type":"Food & Drink"
        }
    ],
    "sg:phone":"+1 509 653 2525",
    "sg:postcode":"98937",
    "sg:province":"WA",
    "wof:name":"Laredo Drive In",
    "wof:placetype":"venue"
},
  "geometry": {"coordinates":[-120.699675,46.728094],"type":"Point"}
}