{
  "type": "Feature",
  "properties": {
    "iso:country":"US",
    "sg:address":"1400 S Dearborn St",
    "sg:city":"Seattle",
    "sg:classifiers":[
        {
            "category":"Shopping",
            "subcategory":"Used Merchandise",
            "type":"Retail Goods"
        }
    ],
    "sg:phone":"+1 206 860 5791",
    "sg:postcode":"98144",
    "sg:province":"WA",
    "wof:name":"Seattle Goodwill",
    "wof:placetype":"venue"
},
  "geometry": {"coordinates":[-122.31282299999999,47.595813],"type":"Point"}
}