{
  "type": "Feature",
  "properties": {
    "addr:full":"229 St Helens Ave Tacoma WA 98402",
    "addr:housenumber":"229",
    "addr:postcode":"98402",
    "addr:street":"St Helens Ave",
    "iso:country":"US",
    "sg:address":"229 St Helens Ave",
    "sg:city":"Tacoma",
    "sg:classifiers":[
        {
            "category":"Bars & Pubs",
            "type":"Food & Drink"
        }
    ],
    "sg:phone":"+1 253 327 1015",
    "sg:postcode":"98402",
    "sg:province":"WA",
    "sg:tags":[
        "brew"
    ],
    "wof:name":"Laurco Dbalaura's Bayview Bar & Grill",
    "wof:placetype":"venue"
},
  "geometry": {"coordinates":[-122.44544500000001,47.261771],"type":"Point"}
}