{
  "type": "Feature",
  "properties": {
    "addr:full":"223 N 36th St Seattle WA 98103",
    "addr:housenumber":"223",
    "addr:postcode":"98103",
    "addr:street":"N 36Th St",
    "iso:country":"US",
    "sg:address":"223 N 36th St",
    "sg:city":"Seattle",
    "sg:classifiers":[
        {
            "category":"Restaurant",
            "type":"Food & Drink"
        },
        {
            "category":"Bars & Pubs",
            "subcategory":"Wine Bar",
            "type":"Food & Drink"
        }
    ],
    "sg:phone":"+1 206 547 1050",
    "sg:postcode":"98103",
    "sg:province":"WA",
    "sg:tags":[
        "italian"
    ],
    "sg:website":"azzurrivinobar.com/",
    "wof:name":"Azzurri Vino Bar",
    "wof:placetype":"venue"
},
  "geometry": {"coordinates":[-122.355684,47.652255],"type":"Point"}
}