{
  "type": "Feature",
  "properties": {
    "addr:full":"1421 Samish Way Bellingham WA 98229",
    "addr:housenumber":"1421",
    "addr:postcode":"98229",
    "addr:street":"Samish Way",
    "iso:country":"US",
    "sg:address":"1421 Samish Way",
    "sg:city":"Bellingham",
    "sg:classifiers":[
        {
            "category":"Real Estate",
            "subcategory":"Real Estate Services",
            "type":"Services"
        },
        {
            "category":"Real Estate",
            "subcategory":"Real Estate Agent",
            "type":"Services"
        }
    ],
    "sg:phone":"+1 360 715 3025",
    "sg:postcode":"98229",
    "sg:province":"WA",
    "sg:tags":[
        "management"
    ],
    "wof:name":"Cascade Valuation Service",
    "wof:placetype":"venue"
},
  "geometry": {"coordinates":[-122.469617,48.718856],"type":"Point"}
}