{
  "type": "Feature",
  "properties": {
    "addr:full":"22428 NE 14th Dr Sammamish WA 98074",
    "addr:housenumber":"22428",
    "addr:postcode":"98074",
    "addr:street":"Ne 14Th Dr",
    "iso:country":"US",
    "sg:address":"22428 NE 14th Dr",
    "sg:city":"Sammamish",
    "sg:classifiers":[
        {
            "category":"Professional",
            "subcategory":"Management & Consulting",
            "type":"Services"
        }
    ],
    "sg:phone":"+1 425 836 8826",
    "sg:postcode":"98074",
    "sg:province":"WA",
    "sg:tags":[
        "consultant",
        "construction"
    ],
    "wof:name":"Excalliber Home Products",
    "wof:placetype":"venue"
},
  "geometry": {"coordinates":[-122.040156,47.622041],"type":"Point"}
}