{
  "type": "Feature",
  "properties": {
    "addr:full":"402 12th Ave S Seattle WA 98144",
    "addr:housenumber":"402",
    "addr:postcode":"98144",
    "addr:street":"12Th Ave S",
    "iso:country":"US",
    "sg:address":"402 12th Ave S",
    "sg:city":"Seattle",
    "sg:classifiers":[
        {
            "category":"Personal",
            "subcategory":"Beauty Salon",
            "type":"Services"
        }
    ],
    "sg:phone":"+1 206 328 4459",
    "sg:postcode":"98144",
    "sg:province":"WA",
    "sg:tags":[
        "shop"
    ],
    "wof:name":"I House",
    "wof:placetype":"venue"
},
  "geometry": {"coordinates":[-122.317155,47.598352],"type":"Point"}
}