{
  "type": "Feature",
  "properties": {
    "addr:full":"3333 164th St SW Apt 724 Lynnwood WA 98087",
    "addr:housenumber":"3333;724",
    "addr:postcode":"98087",
    "addr:street":"164Th St Sw Apt",
    "iso:country":"US",
    "sg:address":"3333 164th St SW Apt 724",
    "sg:city":"Lynnwood",
    "sg:classifiers":[
        {
            "category":"Manufacturing",
            "subcategory":"Tools & Machinery",
            "type":"Manufacturing & Wholesale Goods"
        }
    ],
    "sg:phone":"+1 425 967 3309",
    "sg:postcode":"98087",
    "sg:province":"WA",
    "sg:tags":[
        "cutting",
        "gear"
    ],
    "wof:name":"Warrior Technology Gear",
    "wof:placetype":"venue"
},
  "geometry": {"coordinates":[-122.27793800000001,47.850019],"type":"Point"}
}