{
  "type": "Feature",
  "properties": {
    "iso:country":"US",
    "sg:address":"2201 S 78th St",
    "sg:city":"Tacoma",
    "sg:classifiers":[
        {
            "category":"Social Services",
            "subcategory":"Job Training",
            "type":"Services"
        }
    ],
    "sg:phone":"+1 253 472 2931",
    "sg:postcode":"98409",
    "sg:province":"WA",
    "sg:tags":[
        "apprenticeship",
        "program"
    ],
    "wof:name":"Carpenters Employer Training",
    "wof:placetype":"venue"
},
  "geometry": {"coordinates":[-122.465096,47.186457],"type":"Point"}
}