{
  "type": "Feature",
  "properties": {
    "addr:full":"13916 NE 119th St Brush Prairie WA 98606",
    "addr:housenumber":"13916",
    "addr:postcode":"98606",
    "addr:street":"Ne 119Th St",
    "iso:country":"US",
    "sg:address":"13916 NE 119th St",
    "sg:city":"Brush Prairie",
    "sg:classifiers":[
        {
            "category":"Manufacturing",
            "subcategory":"Glass & Minerals",
            "type":"Manufacturing & Wholesale Goods"
        }
    ],
    "sg:phone":"+1 360 892 3325",
    "sg:postcode":"98606",
    "sg:province":"WA",
    "sg:tags":[
        "mfg"
    ],
    "wof:name":"Painted Treasures",
    "wof:placetype":"venue"
},
  "geometry": {"coordinates":[-122.530188,45.708252],"type":"Point"}
}