{
  "type": "Feature",
  "properties": {
    "addr:full":"710 W Evergreen Blvd Vancouver WA 98660",
    "addr:housenumber":"710",
    "addr:postcode":"98660",
    "addr:street":"W Evergreen Blvd",
    "iso:country":"US",
    "sg:address":"710 W Evergreen Blvd",
    "sg:city":"Vancouver",
    "sg:classifiers":[
        {
            "category":"Banks & Credit Unions",
            "subcategory":"Investment Brokerage",
            "type":"Services"
        },
        {
            "category":"Insurance",
            "subcategory":"Hazard Insurance",
            "type":"Services"
        }
    ],
    "sg:phone":"+1 360 574 0737",
    "sg:postcode":"98660",
    "sg:province":"WA",
    "sg:tags":[
        "commercial",
        "agent",
        "business",
        "resume"
    ],
    "wof:name":"Anico",
    "wof:placetype":"venue"
},
  "geometry": {"coordinates":[-122.678286,45.628849],"type":"Point"}
}