{
  "type": "Feature",
  "properties": {
    "addr:full":"16725 Seminole Rd NE Poulsbo WA 98370",
    "addr:housenumber":"16725",
    "addr:postcode":"98370",
    "addr:street":"Seminole Rd Ne",
    "iso:country":"US",
    "sg:address":"16725 Seminole Rd NE",
    "sg:city":"Poulsbo",
    "sg:classifiers":[
        {
            "category":"Education",
            "subcategory":"Special Training",
            "type":"Public Place"
        }
    ],
    "sg:phone":"+1 360 697 1965",
    "sg:postcode":"98370",
    "sg:province":"WA",
    "wof:name":"Florian Piano Studio",
    "wof:placetype":"venue"
},
  "geometry": {"coordinates":[-122.607569,47.72398],"type":"Point"}
}