{
  "type": "Feature",
  "properties": {
    "addr:full":"24820 SE Mirrormont Way Issaquah WA 98027",
    "addr:postcode":"24820;98027",
    "addr:street":"Se Mirrormont Way",
    "iso:country":"US",
    "sg:address":"24820 SE Mirrormont Way",
    "sg:city":"Issaquah",
    "sg:classifiers":[
        {
            "category":"Building & Trades",
            "subcategory":"Construction",
            "type":"Services"
        }
    ],
    "sg:phone":"+1 425 392 6399",
    "sg:postcode":"98027",
    "sg:province":"WA",
    "sg:tags":[
        "house",
        "commercial",
        "light"
    ],
    "wof:name":"Dale Opp Construction Svcs",
    "wof:placetype":"venue"
},
  "geometry": {"coordinates":[-122.009142,47.470453],"type":"Point"}
}