{
  "type": "Feature",
  "properties": {
    "addr:full":"2504 N Rebecca St Spokane WA 99217",
    "addr:housenumber":"2504",
    "addr:postcode":"99217",
    "addr:street":"N Rebecca St",
    "iso:country":"US",
    "sg:address":"2504 N Rebecca St",
    "sg:city":"Spokane",
    "sg:classifiers":[
        {
            "category":"Manufacturing",
            "subcategory":"Lumber",
            "type":"Manufacturing & Wholesale Goods"
        }
    ],
    "sg:phone":"+1 509 710 4230",
    "sg:postcode":"99217",
    "sg:province":"WA",
    "sg:tags":[
        "forestry"
    ],
    "wof:name":"Edward J Miles Cnslting Frster",
    "wof:placetype":"venue"
},
  "geometry": {"coordinates":[-117.354991,47.680452],"type":"Point"}
}