{
  "type": "Feature",
  "properties": {
    "addr:full":"300 Vine St Ste 14 Seattle WA 98121",
    "addr:housenumber":"300",
    "addr:postcode":"98121",
    "addr:street":"Vine St Ste 14",
    "iso:country":"US",
    "sg:address":"300 Vine St Ste 14",
    "sg:city":"Seattle",
    "sg:classifiers":[
        {
            "category":"Professional",
            "subcategory":"Advertising",
            "type":"Services"
        },
        {
            "category":"Communications",
            "subcategory":"Film & Video Production",
            "type":"Services"
        },
        {
            "category":"Communications",
            "subcategory":"Television Station",
            "type":"Services"
        }
    ],
    "sg:phone":"+1 206 728 9995",
    "sg:postcode":"98121",
    "sg:province":"WA",
    "sg:tags":[
        "commercials-radio",
        "companies-film",
        "tv",
        "agency",
        "specialty",
        "radio"
    ],
    "wof:name":"Bob Flick Productions",
    "wof:placetype":"venue"
},
  "geometry": {"coordinates":[-122.347992,47.616581],"type":"Point"}
}