{
  "type": "Feature",
  "properties": {
    "addr:full":"6 E Yakima Ave Yakima WA 98901",
    "addr:housenumber":"6",
    "addr:postcode":"98901",
    "addr:street":"E Yakima Ave",
    "iso:country":"US",
    "sg:address":"6 E Yakima Ave",
    "sg:city":"Yakima",
    "sg:classifiers":[
        {
            "category":"Banks & Credit Unions",
            "subcategory":"Bank",
            "type":"Services"
        }
    ],
    "sg:phone":"+1 509 575 7415",
    "sg:postcode":"98901",
    "sg:province":"WA",
    "wof:name":"Wells Fargo Bank",
    "wof:placetype":"venue"
},
  "geometry": {"coordinates":[-120.50612700000001,46.60214],"type":"Point"}
}