{
  "type": "Feature",
  "properties": {
    "addr:full":"715 E Scootney St Othello WA 99344",
    "addr:housenumber":"715",
    "addr:postcode":"99344",
    "addr:street":"E Scootney St",
    "iso:country":"US",
    "sg:address":"715 E Scootney St",
    "sg:city":"Othello",
    "sg:classifiers":[
        {
            "category":"Organizations",
            "subcategory":"Religious Organization",
            "type":"Services"
        }
    ],
    "sg:phone":"+1 509 488 9957",
    "sg:postcode":"99344",
    "sg:province":"WA",
    "sg:tags":[
        "place",
        "worship",
        "church"
    ],
    "wof:name":"First Presbyterian Church",
    "wof:placetype":"venue"
},
  "geometry": {"coordinates":[-119.16418,46.816461],"type":"Point"}
}