{
  "type": "Feature",
  "properties": {
    "addr:full":"549 5th St Clarkston WA 99403",
    "addr:housenumber":"549",
    "addr:postcode":"99403",
    "addr:street":"5Th St",
    "iso:country":"US",
    "sg:address":"549 5th St",
    "sg:city":"Clarkston",
    "sg:classifiers":[
        {
            "category":"Personal",
            "subcategory":"Barber",
            "type":"Services"
        }
    ],
    "sg:phone":"+1 509 758 2879",
    "sg:postcode":"99403",
    "sg:province":"WA",
    "sg:tags":[
        "shop"
    ],
    "wof:name":"Silver Comb Barber Shop",
    "wof:placetype":"venue"
},
  "geometry": {"coordinates":[-117.04419,46.419057],"type":"Point"}
}