{
  "type": "Feature",
  "properties": {
    "addr:full":"701 Murdock St Sedro Woolley WA 98284",
    "addr:housenumber":"701",
    "addr:postcode":"98284",
    "addr:street":"Murdock St",
    "iso:country":"US",
    "sg:address":"701 Murdock St",
    "sg:city":"Sedro Woolley",
    "sg:classifiers":[
        {
            "category":"Organizations",
            "subcategory":"Community Association",
            "type":"Services"
        }
    ],
    "sg:phone":"+1 360 855 0520",
    "sg:postcode":"98284",
    "sg:province":"WA",
    "sg:tags":[
        "military"
    ],
    "wof:name":"American Legion",
    "wof:placetype":"venue"
},
  "geometry": {"coordinates":[-122.236779,48.505348],"type":"Point"}
}