{
  "type": "Feature",
  "properties": {
    "addr:full":"1820 Pine Ave Snohomish WA 98290",
    "addr:housenumber":"1820",
    "addr:postcode":"98290",
    "addr:street":"Pine Ave",
    "iso:country":"US",
    "sg:address":"1820 Pine Ave",
    "sg:city":"Snohomish",
    "sg:classifiers":[
        {
            "category":"Building & Trades",
            "subcategory":"Construction",
            "type":"Services"
        }
    ],
    "sg:phone":"+1 360 563 2601",
    "sg:postcode":"98290",
    "sg:province":"WA",
    "sg:tags":[
        "contractor"
    ],
    "wof:name":"Aaron Tuck Photography",
    "wof:placetype":"venue"
},
  "geometry": {"coordinates":[-122.0852,47.936572],"type":"Point"}
}