{
  "type": "Feature",
  "properties": {
    "addr:full":"18500 156th Ave NE Woodinville WA 98072",
    "addr:housenumber":"18500",
    "addr:postcode":"98072",
    "addr:street":"156Th Ave Ne",
    "iso:country":"US",
    "sg:address":"18500 156th Ave NE",
    "sg:city":"Woodinville",
    "sg:classifiers":[
        {
            "category":"Insurance",
            "subcategory":"Insurance Agent",
            "type":"Services"
        }
    ],
    "sg:phone":"+1 425 486 8551",
    "sg:postcode":"98072",
    "sg:province":"WA",
    "wof:name":"Barker & Assoc",
    "wof:placetype":"venue"
},
  "geometry": {"coordinates":[-122.13157699999999,47.762369],"type":"Point"}
}