{
  "type": "Feature",
  "properties": {
    "iso:country":"US",
    "sg:address":"11061 NE 2nd Pl",
    "sg:city":"Bellevue",
    "sg:classifiers":[
        {
            "category":"Real Estate",
            "subcategory":"Real Estate Agent",
            "type":"Services"
        }
    ],
    "sg:phone":"+1 425 454 5995",
    "sg:postcode":"98004",
    "sg:province":"WA",
    "sg:tags":[
        "appraiser"
    ],
    "wof:name":"Innovative Finance",
    "wof:placetype":"venue"
},
  "geometry": {"coordinates":[-122.192849,47.612325],"type":"Point"}
}