{
  "type": "Feature",
  "properties": {
    "addr:full":"13146 Campbell Ln SE Tenino WA 98589",
    "addr:housenumber":"13146",
    "addr:postcode":"98589",
    "addr:street":"Campbell Ln Se Tenino",
    "iso:country":"US",
    "sg:address":"13146 Campbell Ln SE",
    "sg:city":"Tenino",
    "sg:classifiers":[
        {
            "category":"Building & Trades",
            "subcategory":"Construction",
            "type":"Services"
        }
    ],
    "sg:phone":"+1 360 264 4350",
    "sg:postcode":"98589",
    "sg:province":"WA",
    "sg:tags":[
        "general",
        "contractor"
    ],
    "wof:name":"Leischner Construction",
    "wof:placetype":"venue"
},
  "geometry": {"coordinates":[-122.850095,46.895403],"type":"Point"}
}