{
  "type": "Feature",
  "properties": {
    "addr:full":"2590 Grimm Rd Addy WA 99101",
    "addr:postcode":"2590;99101",
    "addr:street":"Grimm Rd",
    "iso:country":"US",
    "sg:address":"2590 Grimm Rd",
    "sg:city":"Addy",
    "sg:classifiers":[
        {
            "category":"Manufacturing",
            "subcategory":"Metals",
            "type":"Manufacturing & Wholesale Goods"
        }
    ],
    "sg:phone":"+1 509 935 4367",
    "sg:postcode":"99101",
    "sg:province":"WA",
    "sg:tags":[
        "fabrication",
        "structural"
    ],
    "wof:name":"Summit Fabrications",
    "wof:placetype":"venue"
},
  "geometry": {"coordinates":[-118.014563,48.295729],"type":"Point"}
}