{
  "type": "Feature",
  "properties": {
    "addr:full":"7114 17th Ave SW Seattle WA 98106",
    "addr:housenumber":"7114",
    "addr:postcode":"98106",
    "addr:street":"17Th Ave Sw",
    "iso:country":"US",
    "sg:address":"7114 17th Ave SW",
    "sg:city":"Seattle",
    "sg:classifiers":[
        {
            "category":"Professional",
            "subcategory":"Engineering",
            "type":"Services"
        }
    ],
    "sg:phone":"+1 206 767 7262",
    "sg:postcode":"98106",
    "sg:province":"WA",
    "sg:tags":[
        "engineer"
    ],
    "sg:website":"www.tantime.com",
    "wof:name":"Electronic Programming & Dsgn",
    "wof:placetype":"venue"
},
  "geometry": {"coordinates":[-122.35606300000001,47.539026],"type":"Point"}
}