{
  "type": "Feature",
  "properties": {
    "addr:full":"19205 NE 214th St Battle Ground WA 98604",
    "addr:housenumber":"19205",
    "addr:postcode":"98604",
    "addr:street":"Ne 214Th St",
    "iso:country":"US",
    "sg:address":"19205 NE 214th St",
    "sg:city":"Battle Ground",
    "sg:classifiers":[
        {
            "category":"Building & Trades",
            "subcategory":"Landscaping Services",
            "type":"Services"
        }
    ],
    "sg:phone":"+1 360 737 9556",
    "sg:postcode":"98604",
    "sg:province":"WA",
    "sg:tags":[
        "landscape"
    ],
    "wof:name":"Lehner Landscaping",
    "wof:placetype":"venue"
},
  "geometry": {"coordinates":[-122.475934,45.777382],"type":"Point"}
}