{
  "type": "Feature",
  "properties": {
    "addr:full":"1511 167th Ave SE Snohomish WA 98290",
    "addr:housenumber":"1511",
    "addr:postcode":"98290",
    "addr:street":"167Th Ave Se",
    "iso:country":"US",
    "sg:address":"1511 167th Ave SE",
    "sg:city":"Snohomish",
    "sg:phone":"+1 425 397 0214",
    "sg:postcode":"98290",
    "sg:province":"WA",
    "sg:tags":[
        "farm",
        "field",
        "crop"
    ],
    "wof:name":"Hay 4 U",
    "wof:placetype":"venue"
},
  "geometry": {"coordinates":[-122.005227,47.982571],"type":"Point"}
}