{
  "type": "Feature",
  "properties": {
    "addr:full":"929 Water St Port Townsend WA 98368",
    "addr:housenumber":"929",
    "addr:postcode":"98368",
    "addr:street":"Water St",
    "iso:country":"US",
    "sg:address":"929 Water St",
    "sg:city":"Port Townsend",
    "sg:classifiers":[
        {
            "category":"Shopping",
            "subcategory":"Bicycles & Sporting Goods",
            "type":"Retail Goods"
        },
        {
            "category":"Shopping",
            "subcategory":"Clothing, Apparel, & Fashions",
            "type":"Retail Goods"
        }
    ],
    "sg:phone":"+1 360 379 9013",
    "sg:postcode":"98368",
    "sg:province":"WA",
    "sg:tags":[
        "equipment",
        "camping",
        "family"
    ],
    "wof:name":"Wildernest",
    "wof:placetype":"venue"
},
  "geometry": {"coordinates":[-122.756674,48.114233],"type":"Point"}
}