{
  "type": "Feature",
  "properties": {
    "addr:full":"1402 Auburn Way N Auburn WA 98002",
    "addr:housenumber":"1402",
    "addr:postcode":"98002",
    "addr:street":"Auburn Way N",
    "iso:country":"US",
    "sg:address":"1402 Auburn Way N",
    "sg:city":"Auburn",
    "sg:classifiers":[
        {
            "category":"Building & Trades",
            "subcategory":"Construction",
            "type":"Services"
        }
    ],
    "sg:phone":"+1 425 652 9187",
    "sg:postcode":"98002",
    "sg:province":"WA",
    "sg:tags":[
        "remodeling",
        "exterior"
    ],
    "wof:name":"Home America Inc",
    "wof:placetype":"venue"
},
  "geometry": {"coordinates":[-122.221445,47.32085],"type":"Point"}
}