{
  "type": "Feature",
  "properties": {
    "addr:full":"35 148th Ave SE Bellevue WA 98007",
    "addr:housenumber":"35",
    "addr:postcode":"98007",
    "addr:street":"148Th Ave Se",
    "iso:country":"US",
    "sg:address":"35 148th Ave SE",
    "sg:city":"Bellevue",
    "sg:classifiers":[
        {
            "category":"Health Services",
            "subcategory":"Doctor",
            "type":"Services"
        }
    ],
    "sg:phone":"+1 425 746 1441",
    "sg:postcode":"98007",
    "sg:province":"WA",
    "sg:tags":[
        "surgeon",
        "oral"
    ],
    "wof:name":"Jung Philip DDS",
    "wof:placetype":"venue"
},
  "geometry": {"coordinates":[-122.14342499999999,47.608491],"type":"Point"}
}