{
  "type": "Feature",
  "properties": {
    "addr:full":"25810 SE 30th St Sammamish WA 98075",
    "addr:postcode":"25810;98075",
    "addr:street":"Se 30Th St",
    "iso:country":"US",
    "sg:address":"25810 SE 30th St",
    "sg:city":"Sammamish",
    "sg:classifiers":[
        {
            "category":"Building & Trades",
            "subcategory":"Construction",
            "type":"Services"
        }
    ],
    "sg:phone":"+1 425 391 8206",
    "sg:postcode":"98075",
    "sg:province":"WA",
    "sg:tags":[
        "contractor"
    ],
    "wof:name":"Burnstead Construction",
    "wof:placetype":"venue"
},
  "geometry": {"coordinates":[-121.995593,47.582451],"type":"Point"}
}