{
  "type": "Feature",
  "properties": {
    "addr:full":"951 4th St Mukilteo WA 98275",
    "addr:housenumber":"951",
    "addr:postcode":"98275",
    "addr:street":"4Th St",
    "iso:country":"US",
    "sg:address":"951 4th St",
    "sg:city":"Mukilteo",
    "sg:classifiers":[
        {
            "category":"Education",
            "subcategory":"Special Training",
            "type":"Public Place"
        }
    ],
    "sg:phone":"+1 425 348 2209",
    "sg:postcode":"98275",
    "sg:province":"WA",
    "wof:name":"Robertsons Cpr Training",
    "wof:placetype":"venue"
},
  "geometry": {"coordinates":[-122.29772,47.946492],"type":"Point"}
}