{
  "type": "Feature",
  "properties": {
    "addr:full":"210 E 1st Ave Ritzville WA 99169",
    "addr:housenumber":"210",
    "addr:postcode":"99169",
    "addr:street":"E 1St Ave",
    "iso:country":"US",
    "sg:address":"210 E 1st Ave",
    "sg:city":"Ritzville",
    "sg:classifiers":[
        {
            "category":"Travel",
            "subcategory":"Hotels & Motels",
            "type":"Entertainment"
        }
    ],
    "sg:phone":"+1 509 659 1100",
    "sg:postcode":"99169",
    "sg:province":"WA",
    "sg:tags":[
        "operation"
    ],
    "wof:name":"Top Hat Motel",
    "wof:placetype":"venue"
},
  "geometry": {"coordinates":[-118.37615099999999,47.127511],"type":"Point"}
}