{
  "type": "Feature",
  "properties": {
    "addr:full":"7327 19th Ave NE Seattle WA 98115",
    "addr:housenumber":"7327",
    "addr:postcode":"98115",
    "addr:street":"19Th Ave Ne",
    "iso:country":"US",
    "sg:address":"7327 19th Ave NE",
    "sg:city":"Seattle",
    "sg:classifiers":[
        {
            "category":"Professional",
            "subcategory":"Management & Consulting",
            "type":"Services"
        },
        {
            "category":"Professional",
            "subcategory":"Advertising",
            "type":"Services"
        }
    ],
    "sg:phone":"+1 206 517 5663",
    "sg:postcode":"98115",
    "sg:province":"WA",
    "sg:tags":[
        "marketing",
        "program",
        "consultant"
    ],
    "wof:name":"Pch Marketing Communications",
    "wof:placetype":"venue"
},
  "geometry": {"coordinates":[-122.307766,47.681728],"type":"Point"}
}