{
  "type": "Feature",
  "properties": {
    "addr:full":"7414 S 114th St Seattle WA 98178",
    "addr:housenumber":"7414",
    "addr:postcode":"98178",
    "addr:street":"S 114Th St",
    "iso:country":"US",
    "sg:address":"7414 S 114th St",
    "sg:city":"Seattle",
    "sg:classifiers":[
        {
            "category":"Professional",
            "subcategory":"Detective & Security Services",
            "type":"Services"
        }
    ],
    "sg:phone":"+1 206 772 3483",
    "sg:postcode":"98178",
    "sg:province":"WA",
    "sg:tags":[
        "car"
    ],
    "wof:name":"Joe Gordon Investigative",
    "wof:placetype":"venue"
},
  "geometry": {"coordinates":[-122.241195,47.501549],"type":"Point"}
}