{
  "type": "Feature",
  "properties": {
    "iso:country":"US",
    "sg:address":"222 W Kalama River Rd",
    "sg:city":"Kalama",
    "sg:classifiers":[
        {
            "category":"Manufacturing",
            "subcategory":"Metals",
            "type":"Manufacturing & Wholesale Goods"
        }
    ],
    "sg:phone":"+1 360 673 8200",
    "sg:postcode":"98625",
    "sg:province":"WA",
    "sg:tags":[
        "processing"
    ],
    "wof:name":"Steelscape",
    "wof:placetype":"venue"
},
  "geometry": {"coordinates":[-122.84895,46.043273],"type":"Point"}
}