{
  "type": "Feature",
  "properties": {
    "addr:full":"1495 Harksell Rd Ferndale WA 98248",
    "addr:housenumber":"1495",
    "addr:postcode":"98248",
    "addr:street":"Harksell Rd",
    "iso:country":"US",
    "sg:address":"1495 Harksell Rd",
    "sg:city":"Ferndale",
    "sg:classifiers":[
        {
            "category":"Shopping",
            "subcategory":"Gifts & Souvenirs",
            "type":"Retail Goods"
        },
        {
            "category":"Manufacturing",
            "subcategory":"Retail Goods",
            "type":"Manufacturing & Wholesale Goods"
        }
    ],
    "sg:phone":"+1 360 384 5467",
    "sg:postcode":"98248",
    "sg:province":"WA",
    "sg:tags":[
        "shop",
        "giftware's-wholesale",
        "manufacturer"
    ],
    "wof:name":"Briarhill",
    "wof:placetype":"venue"
},
  "geometry": {"coordinates":[-122.561319,48.90607],"type":"Point"}
}