{
  "type": "Feature",
  "properties": {
    "addr:full":"17017 E Meridian Ave Puyallup WA 98375",
    "addr:housenumber":"17017",
    "addr:postcode":"98375",
    "addr:street":"E Meridian Ave",
    "iso:country":"US",
    "sg:address":"17017 E Meridian Ave",
    "sg:city":"Puyallup",
    "sg:classifiers":[
        {
            "category":"Retail",
            "subcategory":"Repair Shop",
            "type":"Services"
        }
    ],
    "sg:phone":"+1 253 840 1012",
    "sg:postcode":"98375",
    "sg:province":"WA",
    "sg:tags":[
        "aircraft",
        "maintenance"
    ],
    "wof:name":"Talon Aviation",
    "wof:placetype":"venue"
},
  "geometry": {"coordinates":[-122.293387,47.101887],"type":"Point"}
}