{
  "type": "Feature",
  "properties": {
    "addr:full":"720 Olive Way Ste 800 Seattle WA 98101",
    "addr:housenumber":"720",
    "addr:postcode":"98101",
    "addr:street":"Olive Way Ste 800",
    "iso:country":"US",
    "sg:address":"720 Olive Way Ste 800",
    "sg:city":"Seattle",
    "sg:classifiers":[
        {
            "category":"Health Services",
            "subcategory":"Dentist",
            "type":"Services"
        }
    ],
    "sg:phone":"+1 206 682 3530",
    "sg:postcode":"98101",
    "sg:province":"WA",
    "wof:name":"Dr. Bede",
    "wof:placetype":"venue"
},
  "geometry": {"coordinates":[-122.334934,47.613693],"type":"Point"}
}