{
  "type": "Feature",
  "properties": {
    "addr:full":"15 Lake St S Kirkland WA 98033",
    "addr:housenumber":"15",
    "addr:postcode":"98033",
    "addr:street":"Lake St S",
    "iso:country":"US",
    "sg:address":"15 Lake St S",
    "sg:city":"Kirkland",
    "sg:classifiers":[
        {
            "category":"Shopping",
            "subcategory":"Clothing, Apparel, & Fashions",
            "type":"Retail Goods"
        }
    ],
    "sg:phone":"+1 425 828 3191",
    "sg:postcode":"98033",
    "sg:province":"WA",
    "wof:name":"MO Love",
    "wof:placetype":"venue"
},
  "geometry": {"coordinates":[-122.20687599999999,47.676024],"type":"Point"}
}