{
  "type": "Feature",
  "properties": {
    "addr:full":"802 39th Ave SW Puyallup WA 98373",
    "addr:housenumber":"802",
    "addr:postcode":"98373",
    "addr:street":"39Th Ave Sw",
    "iso:country":"US",
    "sg:address":"802 39th Ave SW",
    "sg:city":"Puyallup",
    "sg:classifiers":[
        {
            "category":"Manufacturing",
            "subcategory":"Food",
            "type":"Manufacturing & Wholesale Goods"
        }
    ],
    "sg:phone":"+1 253 845 0333",
    "sg:postcode":"98373",
    "sg:province":"WA",
    "sg:tags":[
        "frozen"
    ],
    "wof:name":"Schwans Sales Enterprises",
    "wof:placetype":"venue"
},
  "geometry": {"coordinates":[-122.302094,47.154873],"type":"Point"}
}