{
  "type": "Feature",
  "properties": {
    "addr:full":"8611 14th Ave S Seattle WA 98108",
    "addr:housenumber":"8611",
    "addr:postcode":"98108",
    "addr:street":"14Th Ave S",
    "iso:country":"US",
    "sg:address":"8611 14th Ave S",
    "sg:city":"Seattle",
    "sg:classifiers":[
        {
            "category":"Shopping",
            "subcategory":"Hobbies, Toys, & Games",
            "type":"Retail Goods"
        }
    ],
    "sg:phone":"+1 206 762 2024",
    "sg:postcode":"98108",
    "sg:province":"WA",
    "wof:name":"Seattle Intl Toys & Etc",
    "wof:placetype":"venue"
},
  "geometry": {"coordinates":[-122.315,47.525677],"type":"Point"}
}