{
  "type": "Feature",
  "properties": {
    "addr:full":"1301 Yakima Valley Hwy Sunnyside WA 98944",
    "addr:housenumber":"1301",
    "addr:postcode":"98944",
    "addr:street":"Yakima Valley Hwy",
    "iso:country":"US",
    "sg:address":"1301 Yakima Valley Hwy",
    "sg:city":"Sunnyside",
    "sg:classifiers":[
        {
            "category":"Food & Beverages",
            "subcategory":"Groceries & Convenience Stores",
            "type":"Retail Goods"
        }
    ],
    "sg:phone":"+1 509 837 6396",
    "sg:postcode":"98944",
    "sg:province":"WA",
    "sg:tags":[
        "business"
    ],
    "wof:name":"Four Ten Market",
    "wof:placetype":"venue"
},
  "geometry": {"coordinates":[-120.003525,46.32825],"type":"Point"}
}