{
  "type": "Feature",
  "properties": {
    "addr:full":"2824 E 29th Ave Spokane WA 99223",
    "addr:housenumber":"2824",
    "addr:postcode":"99223",
    "addr:street":"E 29Th Ave",
    "iso:country":"US",
    "sg:address":"2824 E 29th Ave",
    "sg:city":"Spokane",
    "sg:classifiers":[
        {
            "category":"Professional",
            "subcategory":"Lawyer & Legal Services",
            "type":"Services"
        }
    ],
    "sg:phone":"+1 509 534 9180",
    "sg:postcode":"99223",
    "sg:province":"WA",
    "sg:tags":[
        "plan"
    ],
    "wof:name":"Dudley Matthew Attorney At Law",
    "wof:placetype":"venue"
},
  "geometry": {"coordinates":[-117.368371,47.628208],"type":"Point"}
}