{
  "type": "Feature",
  "properties": {
    "addr:full":"412 E 24th St Vancouver WA 98663",
    "addr:housenumber":"412",
    "addr:postcode":"98663",
    "addr:street":"E 24Th St",
    "iso:country":"US",
    "sg:address":"412 E 24th St",
    "sg:city":"Vancouver",
    "sg:classifiers":[
        {
            "category":"Personal",
            "type":"Services"
        }
    ],
    "sg:phone":"+1 360 607 9968",
    "sg:postcode":"98663",
    "sg:province":"WA",
    "wof:name":"Beauty & Well Being Massage",
    "wof:placetype":"venue"
},
  "geometry": {"coordinates":[-122.667146,45.638615],"type":"Point"}
}