{
  "type": "Feature",
  "properties": {
    "addr:full":"305 E Main St Battle Ground WA 98604",
    "addr:housenumber":"305",
    "addr:postcode":"98604",
    "addr:street":"E Main St",
    "iso:country":"US",
    "sg:address":"305 E Main St",
    "sg:city":"Battle Ground",
    "sg:classifiers":[
        {
            "category":"Freight",
            "type":"Transportation"
        }
    ],
    "sg:phone":"+1 360 687 7173",
    "sg:postcode":"98604",
    "sg:province":"WA",
    "sg:tags":[
        "trucking"
    ],
    "wof:name":"Green Willow Trucking Inc",
    "wof:placetype":"venue"
},
  "geometry": {"coordinates":[-122.534235,45.780824],"type":"Point"}
}