{
  "type": "Feature",
  "properties": {
    "addr:full":"16410 Smokey Point Blvd Arlington WA 98223",
    "addr:housenumber":"16410",
    "addr:postcode":"98223",
    "addr:street":"Smokey Point Blvd",
    "iso:country":"US",
    "sg:address":"16410 Smokey Point Blvd",
    "sg:city":"Arlington",
    "sg:classifiers":[
        {
            "category":"Restaurant",
            "type":"Food & Drink"
        },
        {
            "category":"Professional",
            "subcategory":"Management & Consulting",
            "type":"Services"
        }
    ],
    "sg:phone":"+1 360 653 1505",
    "sg:postcode":"98223",
    "sg:province":"WA",
    "sg:tags":[
        "shop",
        "coffee",
        "retail",
        "direct",
        "sales"
    ],
    "wof:name":"Hetta's Espresso",
    "wof:placetype":"venue"
},
  "geometry": {"coordinates":[-122.18306800000001,48.14216],"type":"Point"}
}