{
  "type": "Feature",
  "properties": {
    "addr:full":"420 N Evergreen Rd Spokane Valley WA 99216",
    "addr:housenumber":"420",
    "addr:postcode":"99216",
    "addr:street":"N Evergreen Rd",
    "iso:country":"US",
    "sg:address":"420 N Evergreen Rd",
    "sg:city":"Spokane Valley",
    "sg:classifiers":[
        {
            "category":"Health Services",
            "subcategory":"Doctor",
            "type":"Services"
        }
    ],
    "sg:phone":"+1 509 891 9011",
    "sg:postcode":"99216",
    "sg:province":"WA",
    "sg:tags":[
        "dentist"
    ],
    "wof:name":"Children's Dental Village",
    "wof:placetype":"venue"
},
  "geometry": {"coordinates":[-117.218045,47.663246],"type":"Point"}
}