{
  "type": "Feature",
  "properties": {
    "addr:full":"10119 NE Winthers Rd Bainbridge Isle WA 98110",
    "addr:housenumber":"10119",
    "addr:postcode":"98110",
    "addr:street":"Ne Winthers Rd;Isle",
    "iso:country":"US",
    "sg:address":"10119 NE Winthers Rd",
    "sg:city":"Bainbridge Isle",
    "sg:classifiers":[
        {
            "category":"Professional",
            "type":"Services"
        }
    ],
    "sg:phone":"+1 206 780 3345",
    "sg:postcode":"98110",
    "sg:province":"WA",
    "sg:tags":[
        "technical",
        "writing"
    ],
    "wof:name":"Steyer Associates Inc",
    "wof:placetype":"venue"
},
  "geometry": {"coordinates":[-122.511432,47.671873],"type":"Point"}
}