{
  "type": "Feature",
  "properties": {
    "addr:full":"16816 2nd Ave SW Seattle WA 98166",
    "addr:housenumber":"16816",
    "addr:postcode":"98166",
    "addr:street":"2Nd Ave Sw",
    "iso:country":"US",
    "sg:address":"16816 2nd Ave SW",
    "sg:city":"Seattle",
    "sg:classifiers":[
        {
            "category":"Social Services",
            "subcategory":"Child Care",
            "type":"Services"
        }
    ],
    "sg:phone":"+1 206 244 0339",
    "sg:postcode":"98166",
    "sg:province":"WA",
    "sg:tags":[
        "preschool"
    ],
    "wof:name":"L A J Books",
    "wof:placetype":"venue"
},
  "geometry": {"coordinates":[-122.336555,47.450151],"type":"Point"}
}