{
  "type": "Feature",
  "properties": {
    "addr:full":"3717 Harbour Pointe Blvd SW Mukilteo WA 98275",
    "addr:housenumber":"3717",
    "addr:postcode":"98275",
    "addr:street":"Harbour Pointe Blvd Sw",
    "iso:country":"US",
    "sg:address":"3717 Harbour Pointe Blvd SW",
    "sg:city":"Mukilteo",
    "sg:classifiers":[
        {
            "category":"Restaurant",
            "type":"Food & Drink"
        }
    ],
    "sg:menulink":"http://www.allmenus.com/wa/everett/212731-mcdonalds/menu/",
    "sg:phone":"+1 425 355 8444",
    "sg:postcode":"98275",
    "sg:province":"WA",
    "sg:tags":[
        "burger",
        "american"
    ],
    "wof:name":"McDonald's",
    "wof:placetype":"venue"
},
  "geometry": {"coordinates":[-122.284582,47.890475],"type":"Point"}
}