{
  "type": "Feature",
  "properties": {
    "addr:full":"17700 SE 272nd St Kent WA 98042",
    "addr:postcode":"17700;98042",
    "addr:street":"Se 272Nd St",
    "iso:country":"US",
    "sg:address":"17700 SE 272nd St",
    "sg:city":"Kent",
    "sg:classifiers":[
        {
            "category":"Health Services",
            "subcategory":"Doctor",
            "type":"Services"
        }
    ],
    "sg:phone":"+1 253 638 8642",
    "sg:postcode":"98042",
    "sg:province":"WA",
    "sg:tags":[
        "physician",
        "surgeon"
    ],
    "wof:name":"Cascade Orthopaedics",
    "wof:placetype":"venue"
},
  "geometry": {"coordinates":[-122.105744,47.358137],"type":"Point"}
}