{
  "type": "Feature",
  "properties": {
    "addr:full":"999 3rd Ave Ste 4100 Seattle WA 98104",
    "addr:housenumber":"999",
    "addr:postcode":"98104",
    "addr:street":"3Rd Ave Ste 4100",
    "iso:country":"US",
    "sg:address":"999 3rd Ave Ste 4100",
    "sg:city":"Seattle",
    "sg:classifiers":[
        {
            "category":"Professional",
            "subcategory":"Lawyer & Legal Services",
            "type":"Services"
        }
    ],
    "sg:phone":"+1 206 689 8510",
    "sg:postcode":"98104",
    "sg:province":"WA",
    "wof:name":"Lippek Henry E Atty",
    "wof:placetype":"venue"
},
  "geometry": {"coordinates":[-122.334,47.605499],"type":"Point"}
}