{
  "type": "Feature",
  "properties": {
    "addr:full":"7870 Dahl Rd NE Moses Lake WA 98837",
    "addr:housenumber":"7870",
    "addr:postcode":"98837",
    "addr:street":"Dahl Rd Ne",
    "iso:country":"US",
    "sg:address":"7870 Dahl Rd NE",
    "sg:city":"Moses Lake",
    "sg:classifiers":[
        {
            "category":"Building & Trades",
            "subcategory":"Cleaning & Sanitation",
            "type":"Services"
        },
        {
            "category":"Retail",
            "subcategory":"Laundry & Dry Cleaning",
            "type":"Services"
        }
    ],
    "sg:phone":"+1 509 766 7786",
    "sg:postcode":"98837",
    "sg:province":"WA",
    "sg:tags":[
        "cleaners",
        "rug",
        "maintenance",
        "carpet"
    ],
    "wof:name":"Central Washington Carpet Clg",
    "wof:placetype":"venue"
},
  "geometry": {"coordinates":[-119.322666,47.145984],"type":"Point"}
}