{
  "type": "Feature",
  "properties": {
    "addr:full":"3710 Norpoint Way NE Tacoma WA 98422",
    "addr:housenumber":"3710",
    "addr:postcode":"98422",
    "addr:street":"Norpoint Way Ne",
    "iso:country":"US",
    "sg:address":"3710 Norpoint Way NE",
    "sg:city":"Tacoma",
    "sg:classifiers":[
        {
            "category":"Building & Trades",
            "subcategory":"Construction",
            "type":"Services"
        }
    ],
    "sg:phone":"+1 253 568 7256",
    "sg:postcode":"98422",
    "sg:province":"WA",
    "sg:tags":[
        "mason",
        "masonry",
        "industrial",
        "contractors-commercial",
        "contractor"
    ],
    "wof:name":"Vk Masonry",
    "wof:placetype":"venue"
},
  "geometry": {"coordinates":[-122.406879,47.295596],"type":"Point"}
}