{
  "type": "Feature",
  "properties": {
    "addr:full":"2127 Duncan Rd N Wenatchee WA 98801",
    "addr:housenumber":"2127",
    "addr:postcode":"98801",
    "addr:street":"Duncan Rd N",
    "iso:country":"US",
    "sg:address":"2127 Duncan Rd N",
    "sg:city":"Wenatchee",
    "sg:classifiers":[
        {
            "category":"Manufacturing",
            "subcategory":"Metals",
            "type":"Manufacturing & Wholesale Goods"
        }
    ],
    "sg:phone":"+1 509 663 5923",
    "sg:postcode":"98801",
    "sg:province":"WA",
    "sg:tags":[
        "steel"
    ],
    "wof:name":"Frank Parker Mfg Co",
    "wof:placetype":"venue"
},
  "geometry": {"coordinates":[-120.335492,47.456865],"type":"Point"}
}