{
  "type": "Feature",
  "properties": {
    "iso:country":"US",
    "sg:address":"702 N Ruby St",
    "sg:city":"Ellensburg",
    "sg:classifiers":[
        {
            "category":"Professional",
            "subcategory":"Computer Services",
            "type":"Services"
        }
    ],
    "sg:phone":"+1 253 569 2444",
    "sg:postcode":"98926",
    "sg:province":"WA",
    "sg:tags":[
        "programming",
        "custom"
    ],
    "wof:name":"Unmelted Enterprises",
    "wof:placetype":"venue"
},
  "geometry": {"coordinates":[-120.54465,46.999698],"type":"Point"}
}