{
  "type": "Feature",
  "properties": {
    "addr:full":"5005 N Division St Spokane WA 99207",
    "addr:housenumber":"5005",
    "addr:postcode":"99207",
    "addr:street":"N Division St",
    "iso:country":"US",
    "sg:address":"5005 N Division St",
    "sg:city":"Spokane",
    "sg:classifiers":[
        {
            "category":"Shopping",
            "subcategory":"Clothing, Apparel, & Fashions",
            "type":"Retail Goods"
        }
    ],
    "sg:phone":"+1 509 483 4411",
    "sg:postcode":"99207",
    "sg:province":"WA",
    "sg:tags":[
        "furnishing"
    ],
    "wof:name":"Men's Wearhouse",
    "wof:placetype":"venue"
},
  "geometry": {"coordinates":[-117.411289,47.703348],"type":"Point"}
}