{
  "type": "Feature",
  "properties": {
    "addr:full":"3812 E Crown Ave Spokane WA 99217",
    "addr:housenumber":"3812",
    "addr:postcode":"99217",
    "addr:street":"E Crown Ave",
    "iso:country":"US",
    "sg:address":"3812 E Crown Ave",
    "sg:city":"Spokane",
    "sg:classifiers":[
        {
            "category":"Professional",
            "subcategory":"Accounting & Tax Preparation",
            "type":"Services"
        }
    ],
    "sg:phone":"+1 509 483 3500",
    "sg:postcode":"99217",
    "sg:province":"WA",
    "sg:tags":[
        "accountant"
    ],
    "wof:name":"G Charles Brock CPA",
    "wof:placetype":"venue"
},
  "geometry": {"coordinates":[-117.35210499999999,47.705018],"type":"Point"}
}