{
  "type": "Feature",
  "properties": {
    "addr:full":"3212 NE Royal Oaks Dr Vancouver WA 98662",
    "addr:housenumber":"3212",
    "addr:postcode":"98662",
    "addr:street":"Ne Royal Oaks Dr",
    "iso:country":"US",
    "sg:address":"3212 NE Royal Oaks Dr",
    "sg:city":"Vancouver",
    "sg:classifiers":[
        {
            "category":"Professional",
            "subcategory":"Management & Consulting",
            "type":"Services"
        },
        {
            "category":"Professional",
            "subcategory":"Business Services",
            "type":"Services"
        },
        {
            "category":"Professional",
            "subcategory":"Engineering",
            "type":"Services"
        }
    ],
    "sg:phone":"+1 360 944 9933",
    "sg:postcode":"98662",
    "sg:province":"WA",
    "sg:tags":[
        "consultant",
        "organizing",
        "services-household",
        "engineer"
    ],
    "sg:website":"http://www.paelderlaw.com",
    "wof:name":"Marshall & Assoc",
    "wof:placetype":"venue"
},
  "geometry": {"coordinates":[-122.581177,45.645679],"type":"Point"}
}