{
  "type": "Feature",
  "properties": {
    "addr:full":"1765 Kittleson Rd Moses Lake WA 98837",
    "addr:housenumber":"1765",
    "addr:postcode":"98837",
    "addr:street":"Kittleson Rd",
    "iso:country":"US",
    "sg:address":"1765 Kittleson Rd",
    "sg:city":"Moses Lake",
    "sg:classifiers":[
        {
            "category":"Restaurant",
            "type":"Food & Drink"
        }
    ],
    "sg:menulink":"http://www.allmenus.com/wa/moses-lake/6729-dennys/menu/",
    "sg:phone":"+1 509 766 7881",
    "sg:postcode":"98837",
    "sg:province":"WA",
    "sg:tags":[
        "american",
        "diner"
    ],
    "wof:name":"Denny's",
    "wof:placetype":"venue"
},
  "geometry": {"coordinates":[-119.24748200000001,47.101216],"type":"Point"}
}