{
  "type": "Feature",
  "properties": {
    "addr:full":"11605 132nd Ave NE Kirkland WA 98034",
    "addr:housenumber":"11605",
    "addr:postcode":"98034",
    "addr:street":"132Nd Ave Ne",
    "iso:country":"US",
    "sg:address":"11605 132nd Ave NE",
    "sg:city":"Kirkland",
    "sg:classifiers":[
        {
            "category":"Shopping",
            "subcategory":"Books",
            "type":"Retail Goods"
        }
    ],
    "sg:phone":"+1 425 739 8108",
    "sg:postcode":"98034",
    "sg:province":"WA",
    "sg:tags":[
        "bookstore",
        "college"
    ],
    "wof:name":"Follett Higher Education Group",
    "wof:placetype":"venue"
},
  "geometry": {"coordinates":[-122.16456100000001,47.702288],"type":"Point"}
}