{
  "type": "Feature",
  "properties": {
    "addr:full":"19620 8th Ave E Spanaway WA 98387",
    "addr:housenumber":"19620",
    "addr:postcode":"98387",
    "addr:street":"8Th Ave E",
    "iso:country":"US",
    "sg:address":"19620 8th Ave E",
    "sg:city":"Spanaway",
    "sg:classifiers":[
        {
            "category":"Health Services",
            "subcategory":"Nursing And Care Facility",
            "type":"Services"
        }
    ],
    "sg:phone":"+1 253 847 4163",
    "sg:postcode":"98387",
    "sg:province":"WA",
    "wof:name":"St Nino Adult Family Home",
    "wof:placetype":"venue"
},
  "geometry": {"coordinates":[-122.421657,47.077679],"type":"Point"}
}