{
  "type": "Feature",
  "properties": {
    "addr:full":"2711 Howard Ave Centralia WA 98531",
    "addr:housenumber":"2711",
    "addr:postcode":"98531",
    "addr:street":"Howard Ave",
    "iso:country":"US",
    "sg:address":"2711 Howard Ave",
    "sg:city":"Centralia",
    "sg:classifiers":[
        {
            "category":"Restaurant",
            "type":"Food & Drink"
        }
    ],
    "sg:phone":"+1 360 736 9758",
    "sg:postcode":"98531",
    "sg:province":"WA",
    "sg:tags":[
        "eating"
    ],
    "wof:name":"Coumbs Concessions Sausage",
    "wof:placetype":"venue"
},
  "geometry": {"coordinates":[-122.94508,46.746247],"type":"Point"}
}