{
  "type": "Feature",
  "properties": {
    "iso:country":"US",
    "sg:address":"100 W State St",
    "sg:city":"Sedro Woolley",
    "sg:classifiers":[
        {
            "category":"Personal",
            "type":"Services"
        }
    ],
    "sg:phone":"+1 360 855 9856",
    "sg:postcode":"98284",
    "sg:province":"WA",
    "sg:tags":[
        "therapist",
        "massage"
    ],
    "wof:name":"Light Touch Massage",
    "wof:placetype":"venue"
},
  "geometry": {"coordinates":[-122.24121100000001,48.503228],"type":"Point"}
}