{
  "type": "Feature",
  "properties": {
    "addr:full":"1000 W Steuben St Bingen WA 98605",
    "addr:housenumber":"1000",
    "addr:postcode":"98605",
    "addr:street":"W Steuben St",
    "iso:country":"US",
    "sg:address":"1000 W Steuben St",
    "sg:city":"Bingen",
    "sg:classifiers":[
        {
            "category":"Real Estate",
            "subcategory":"Real Estate Agent",
            "type":"Services"
        }
    ],
    "sg:phone":"+1 509 493 3440",
    "sg:postcode":"98605",
    "sg:province":"WA",
    "sg:website":"www.c21cc.com",
    "wof:name":"Century 21 Columbia Crest",
    "wof:placetype":"venue"
},
  "geometry": {"coordinates":[-121.470311,45.716402],"type":"Point"}
}