{
  "type": "Feature",
  "properties": {
    "addr:full":"22500 Port Gamble Rd NE Poulsbo WA 98370",
    "addr:housenumber":"22500",
    "addr:postcode":"98370",
    "addr:street":"Port Gamble Rd Ne",
    "iso:country":"US",
    "sg:address":"22500 Port Gamble Rd NE",
    "sg:city":"Poulsbo",
    "sg:classifiers":[
        {
            "category":"Building & Trades",
            "subcategory":"Construction",
            "type":"Services"
        }
    ],
    "sg:phone":"+1 360 779 3827",
    "sg:postcode":"98370",
    "sg:province":"WA",
    "sg:tags":[
        "house"
    ],
    "wof:name":"PDT Associates Inc",
    "wof:placetype":"venue"
},
  "geometry": {"coordinates":[-122.57999700000001,47.764346],"type":"Point"}
}