{
  "type": "Feature",
  "properties": {
    "addr:full":"209 S Broadway St Aberdeen WA 98520",
    "addr:housenumber":"209",
    "addr:postcode":"98520",
    "addr:street":"S Broadway St",
    "iso:country":"US",
    "sg:address":"209 S Broadway St",
    "sg:city":"Aberdeen",
    "sg:classifiers":[
        {
            "category":"Shopping",
            "subcategory":"Gifts & Souvenirs",
            "type":"Retail Goods"
        }
    ],
    "sg:phone":"+1 360 533 5152",
    "sg:postcode":"98520",
    "sg:province":"WA",
    "wof:name":"Country Closet",
    "wof:placetype":"venue"
},
  "geometry": {"coordinates":[-123.81795700000001,46.974123],"type":"Point"}
}