{
  "type": "Feature",
  "properties": {
    "addr:full":"910 W Holly St Bellingham WA 98225",
    "addr:housenumber":"910",
    "addr:postcode":"98225",
    "addr:street":"W Holly St",
    "iso:country":"US",
    "sg:address":"910 W Holly St",
    "sg:city":"Bellingham",
    "sg:classifiers":[
        {
            "category":"Social Services",
            "type":"Services"
        },
        {
            "category":"Real Estate",
            "subcategory":"Real Estate Services",
            "type":"Services"
        },
        {
            "category":"Place Of Worship",
            "type":"Public Place"
        },
        {
            "category":"Social Services",
            "subcategory":"Retirement Home",
            "type":"Services"
        },
        {
            "category":"Organizations",
            "subcategory":"Religious Organization",
            "type":"Services"
        },
        {
            "category":"Personal",
            "type":"Services"
        },
        {
            "category":"Health Services",
            "subcategory":"Health Practitioner",
            "type":"Services"
        }
    ],
    "sg:phone":"+1 360 733 5120",
    "sg:postcode":"98225",
    "sg:province":"WA",
    "sg:tags":[
        "boarding",
        "house",
        "mission",
        "drug",
        "rooming",
        "abuse",
        "counselors-licensed",
        "church",
        "professional",
        "addiction"
    ],
    "wof:name":"Light House Mission Association Of Whatcom County Inc",
    "wof:placetype":"venue"
},
  "geometry": {"coordinates":[-122.48688,48.754763],"type":"Point"}
}