{
  "type": "Feature",
  "properties": {
    "addr:full":"1952 1st Ave S Seattle WA 98134",
    "addr:housenumber":"1952",
    "addr:postcode":"98134",
    "addr:street":"1St Ave S",
    "iso:country":"US",
    "sg:address":"1952 1st Ave S",
    "sg:city":"Seattle",
    "sg:classifiers":[
        {
            "category":"Shopping",
            "subcategory":"Clothing, Apparel, & Fashions",
            "type":"Retail Goods"
        }
    ],
    "sg:phone":"+1 206 382 1776",
    "sg:postcode":"98134",
    "sg:province":"WA",
    "sg:tags":[
        "jean"
    ],
    "wof:name":"Debris Jeans",
    "wof:placetype":"venue"
},
  "geometry": {"coordinates":[-122.334126,47.584348],"type":"Point"}
}