{
  "type": "Feature",
  "properties": {
    "addr:full":"2114 Tacoma Ave S Tacoma WA 98402",
    "addr:housenumber":"2114",
    "addr:postcode":"98402",
    "addr:street":"Tacoma Ave S",
    "iso:country":"US",
    "sg:address":"2114 Tacoma Ave S",
    "sg:city":"Tacoma",
    "sg:classifiers":[
        {
            "category":"Retail",
            "subcategory":"Auto Repair",
            "type":"Services"
        }
    ],
    "sg:phone":"+1 253 572 0900",
    "sg:postcode":"98402",
    "sg:province":"WA",
    "sg:tags":[
        "engine",
        "shop",
        "automobile",
        "machine",
        "motorcycle",
        "automotive",
        "marine"
    ],
    "wof:name":"Jack's Custom Machine Shop",
    "wof:placetype":"venue"
},
  "geometry": {"coordinates":[-122.441834,47.240999],"type":"Point"}
}