{
  "type": "Feature",
  "properties": {
    "addr:full":"130 N Bend Blvd N North Bend WA 98045",
    "addr:housenumber":"130",
    "addr:postcode":"98045",
    "addr:street":"N Bend Blvd N",
    "iso:country":"US",
    "sg:address":"130 N Bend Blvd N",
    "sg:city":"North Bend",
    "sg:classifiers":[
        {
            "category":"Bars & Pubs",
            "type":"Food & Drink"
        }
    ],
    "sg:phone":"+1 425 888 9912",
    "sg:postcode":"98045",
    "sg:province":"WA",
    "wof:name":"Falls Tavern",
    "wof:placetype":"venue"
},
  "geometry": {"coordinates":[-121.786327,47.496026],"type":"Point"}
}