{
  "type": "Feature",
  "properties": {
    "addr:full":"2001 Western Ave Seattle WA 98121",
    "addr:housenumber":"2001",
    "addr:postcode":"98121",
    "addr:street":"Western Ave",
    "iso:country":"US",
    "sg:address":"2001 Western Ave",
    "sg:city":"Seattle",
    "sg:classifiers":[
        {
            "category":"Health Services",
            "subcategory":"Doctor",
            "type":"Services"
        },
        {
            "category":"Health Services",
            "subcategory":"Clinic",
            "type":"Services"
        }
    ],
    "sg:phone":"+1 206 443 4306",
    "sg:postcode":"98121",
    "sg:province":"WA",
    "sg:tags":[
        "information",
        "psychologist",
        "mental"
    ],
    "wof:name":"Haldeman Douglas Cphd",
    "wof:placetype":"venue"
},
  "geometry": {"coordinates":[-122.34369700000001,47.61034],"type":"Point"}
}