{
  "type": "Feature",
  "properties": {
    "addr:full":"5479 Rumac St SE Lacey WA 98513",
    "addr:housenumber":"5479",
    "addr:postcode":"98513",
    "addr:street":"Rumac St Se",
    "iso:country":"US",
    "sg:address":"5479 Rumac St SE",
    "sg:city":"Lacey",
    "sg:classifiers":[
        {
            "category":"Professional",
            "subcategory":"Management & Consulting",
            "type":"Services"
        }
    ],
    "sg:phone":"+1 360 455 0900",
    "sg:postcode":"98513",
    "sg:province":"WA",
    "sg:tags":[
        "consultant"
    ],
    "wof:name":"Executive Advisors",
    "wof:placetype":"venue"
},
  "geometry": {"coordinates":[-122.791211,46.99852],"type":"Point"}
}