{
  "type": "Feature",
  "properties": {
    "addr:full":"733 S Greene St Spokane WA 99202",
    "addr:housenumber":"733",
    "addr:postcode":"99202",
    "addr:street":"S Greene St",
    "iso:country":"US",
    "sg:address":"733 S Greene St",
    "sg:city":"Spokane",
    "sg:classifiers":[
        {
            "category":"Education",
            "subcategory":"Dance Studio",
            "type":"Public Place"
        }
    ],
    "sg:phone":"+1 509 536 1696",
    "sg:postcode":"99202",
    "sg:province":"WA",
    "wof:name":"D W A",
    "wof:placetype":"venue"
},
  "geometry": {"coordinates":[-117.364313,47.647518],"type":"Point"}
}