{
  "type": "Feature",
  "properties": {
    "addr:full":"3337 Sahalee Way NE Sammamish WA 98074",
    "addr:housenumber":"3337",
    "addr:postcode":"98074",
    "addr:street":"Sahalee Way Ne",
    "iso:country":"US",
    "sg:address":"3337 Sahalee Way NE",
    "sg:city":"Sammamish",
    "sg:classifiers":[
        {
            "category":"Professional",
            "subcategory":"Business Services",
            "type":"Services"
        }
    ],
    "sg:phone":"+1 425 868 9404",
    "sg:postcode":"98074",
    "sg:province":"WA",
    "wof:name":"Creative Design Concepts",
    "wof:placetype":"venue"
},
  "geometry": {"coordinates":[-122.042244,47.636022],"type":"Point"}
}