{
  "type": "Feature",
  "properties": {
    "addr:full":"13716 CANYON RD E PUYALLUP WA 98373",
    "addr:housenumber":"13716",
    "addr:postcode":"98373",
    "addr:street":"Canyon Rd E",
    "iso:country":"US",
    "sg:address":"13716 CANYON RD E",
    "sg:city":"PUYALLUP",
    "sg:classifiers":[
        {
            "category":"Autos & Motor Vehicles",
            "subcategory":"Fuel & Gas Station",
            "type":"Retail Goods"
        },
        {
            "category":"Autos & Motor Vehicles",
            "subcategory":"Auto Supplies",
            "type":"Retail Goods"
        },
        {
            "category":"Retail",
            "subcategory":"Auto Repair",
            "type":"Services"
        }
    ],
    "sg:phone":"+1 253 617 0023",
    "sg:postcode":"98373",
    "sg:province":"WA",
    "sg:tags":[
        "oil",
        "transmission",
        "automobile",
        "emission",
        "accessory",
        "lube",
        "truck",
        "brake",
        "repair-automobile"
    ],
    "sg:website":"http://www.kernsauto.com",
    "wof:name":"Kern's Complete Automotive Care",
    "wof:placetype":"venue"
},
  "geometry": {"coordinates":[-122.35745199999999,47.131263],"type":"Point"}
}