{
  "type": "Feature",
  "properties": {
    "addr:full":"18404 Cascade Ave S Ste 100 Seattle WA 98188",
    "addr:housenumber":"18404",
    "addr:postcode":"98188",
    "addr:street":"Cascade Ave S Ste 100",
    "iso:country":"US",
    "sg:address":"18404 Cascade Ave S Ste 100",
    "sg:city":"Seattle",
    "sg:classifiers":[
        {
            "category":"Utilities",
            "subcategory":"Water",
            "type":"Services"
        },
        {
            "category":"Home & Garden",
            "subcategory":"Hardware",
            "type":"Retail Goods"
        }
    ],
    "sg:phone":"+1 509 455 8050",
    "sg:postcode":"98188",
    "sg:province":"WA",
    "sg:tags":[
        "filtration",
        "softening",
        "companies-bottled",
        "purification",
        "bulk",
        "equipment",
        "conditioning"
    ],
    "sg:website":"http://www.culligan.com",
    "wof:name":"Culligan Water Conditioning Of Washington Inc-Tukwilla",
    "wof:placetype":"venue"
},
  "geometry": {"coordinates":[-122.249495,47.434981],"type":"Point"}
}