{
  "type": "Feature",
  "properties": {
    "addr:full":"1722 N Post St Spokane WA 99205",
    "addr:housenumber":"1722",
    "addr:postcode":"99205",
    "addr:street":"N Post St",
    "iso:country":"US",
    "sg:address":"1722 N Post St",
    "sg:city":"Spokane",
    "sg:classifiers":[
        {
            "category":"Health Services",
            "subcategory":"Medical Lab",
            "type":"Services"
        }
    ],
    "sg:phone":"+1 509 328 9538",
    "sg:postcode":"99205",
    "sg:province":"WA",
    "sg:tags":[
        "laboratory",
        "dental"
    ],
    "wof:name":"Progressive Orthodontics",
    "wof:placetype":"venue"
},
  "geometry": {"coordinates":[-117.42356599999999,47.673359],"type":"Point"}
}