{
  "type": "Feature",
  "properties": {
    "addr:full":"120 W Highland Dr Apt 225 Seattle WA 98119",
    "addr:housenumber":"120;225",
    "addr:postcode":"98119",
    "addr:street":"W Highland Dr Apt",
    "iso:country":"US",
    "sg:address":"120 W Highland Dr Apt 225",
    "sg:city":"Seattle",
    "sg:classifiers":[
        {
            "category":"Shopping",
            "subcategory":"Gifts & Souvenirs",
            "type":"Retail Goods"
        }
    ],
    "sg:phone":"+1 206 301 9715",
    "sg:postcode":"98119",
    "sg:province":"WA",
    "sg:tags":[
        "calendar"
    ],
    "wof:name":"Fuego",
    "wof:placetype":"venue"
},
  "geometry": {"coordinates":[-122.358199,47.629561],"type":"Point"}
}