{
  "type": "Feature",
  "properties": {
    "addr:full":"205 Bellevue St NW East Wenatchee WA 98802",
    "addr:housenumber":"205",
    "addr:postcode":"98802",
    "addr:street":"Bellevue St Nw",
    "iso:country":"US",
    "sg:address":"205 Bellevue St NW",
    "sg:city":"East Wenatchee",
    "sg:classifiers":[
        {
            "category":"Building & Trades",
            "subcategory":"Construction",
            "type":"Services"
        }
    ],
    "sg:phone":"+1 509 884 7305",
    "sg:postcode":"98802",
    "sg:province":"WA",
    "sg:tags":[
        "hanging",
        "painter",
        "contractor"
    ],
    "wof:name":"Crawfords Painting",
    "wof:placetype":"venue"
},
  "geometry": {"coordinates":[-120.30557,47.439613],"type":"Point"}
}