{
  "type": "Feature",
  "properties": {
    "addr:full":"210 E Sprague Ave Spokane WA 99202",
    "addr:housenumber":"210",
    "addr:postcode":"99202",
    "addr:street":"E Sprague Ave",
    "iso:country":"US",
    "sg:address":"210 E Sprague Ave",
    "sg:city":"Spokane",
    "sg:classifiers":[
        {
            "category":"Retail",
            "subcategory":"Auto Repair",
            "type":"Services"
        }
    ],
    "sg:phone":"+1 509 624 2090",
    "sg:postcode":"99202",
    "sg:province":"WA",
    "sg:tags":[
        "automobile",
        "lubrication",
        "automotive"
    ],
    "wof:name":"Curts City Center Oil & Lube",
    "wof:placetype":"venue"
},
  "geometry": {"coordinates":[-117.40680999999999,47.657207],"type":"Point"}
}