{
  "type": "Feature",
  "properties": {
    "addr:full":"1806 W Pacific Ave Spokane WA 99201",
    "addr:housenumber":"1806",
    "addr:postcode":"99201",
    "addr:street":"W Pacific Ave",
    "iso:country":"US",
    "sg:address":"1806 W Pacific Ave",
    "sg:city":"Spokane",
    "sg:classifiers":[
        {
            "category":"Health Services",
            "subcategory":"Doctor",
            "type":"Services"
        }
    ],
    "sg:phone":"+1 509 624 2188",
    "sg:postcode":"99201",
    "sg:province":"WA",
    "sg:tags":[
        "physician",
        "surgeon"
    ],
    "wof:name":"Davis Paul Grp",
    "wof:placetype":"venue"
},
  "geometry": {"coordinates":[-117.43864499999999,47.655544],"type":"Point"}
}