{
  "type": "Feature",
  "properties": {
    "addr:full":"3201 Allen Ave Bellingham WA 98225",
    "addr:housenumber":"3201",
    "addr:postcode":"98225",
    "addr:street":"Allen Ave",
    "iso:country":"US",
    "sg:address":"3201 Allen Ave",
    "sg:city":"Bellingham",
    "sg:classifiers":[
        {
            "category":"Building & Trades",
            "subcategory":"Construction",
            "type":"Services"
        }
    ],
    "sg:phone":"+1 360 715 3127",
    "sg:postcode":"98225",
    "sg:province":"WA",
    "sg:tags":[
        "general",
        "contractor"
    ],
    "wof:name":"Dmp Construction",
    "wof:placetype":"venue"
},
  "geometry": {"coordinates":[-122.474501,48.734548],"type":"Point"}
}