{
  "type": "Feature",
  "properties": {
    "iso:country":"US",
    "sg:address":"15417 SE 42nd St",
    "sg:city":"Bellevue",
    "sg:classifiers":[
        {
            "category":"Recreation",
            "type":"Entertainment"
        }
    ],
    "sg:phone":"+1 425 644 6809",
    "sg:postcode":"98006",
    "sg:province":"WA",
    "wof:name":"Portable Pro",
    "wof:placetype":"venue"
},
  "geometry": {"coordinates":[-122.13276,47.571919],"type":"Point"}
}