{
  "type": "Feature",
  "properties": {
    "addr:full":"2520 Mottman Ct SW Olympia WA 98512",
    "addr:housenumber":"2520",
    "addr:postcode":"98512",
    "addr:street":"Mottman Ct Sw",
    "iso:country":"US",
    "sg:address":"2520 Mottman Ct SW",
    "sg:city":"Olympia",
    "sg:classifiers":[
        {
            "category":"Freight",
            "type":"Transportation"
        }
    ],
    "sg:phone":"+1 360 352 2978",
    "sg:postcode":"98512",
    "sg:province":"WA",
    "sg:tags":[
        "special"
    ],
    "wof:name":"Anchor Rv Storage",
    "wof:placetype":"venue"
},
  "geometry": {"coordinates":[-122.936345,47.025514],"type":"Point"}
}