{
  "type": "Feature",
  "properties": {
    "addr:full":"735 Front St Leavenworth WA 98826",
    "addr:housenumber":"735",
    "addr:postcode":"98826",
    "addr:street":"Front St",
    "iso:country":"US",
    "sg:address":"735 Front St",
    "sg:city":"Leavenworth",
    "sg:classifiers":[
        {
            "category":"Shopping",
            "subcategory":"Clothing, Apparel, & Fashions",
            "type":"Retail Goods"
        }
    ],
    "sg:phone":"+1 509 548 2160",
    "sg:postcode":"98826",
    "sg:province":"WA",
    "sg:tags":[
        "item",
        "boutique"
    ],
    "wof:name":"Ms Arlene's Boutique & Gallery",
    "wof:placetype":"venue"
},
  "geometry": {"coordinates":[-120.663116,47.594653],"type":"Point"}
}