{
  "type": "Feature",
  "properties": {
    "addr:full":"315 2nd Ave S Seattle WA 98104",
    "addr:housenumber":"315",
    "addr:postcode":"98104",
    "addr:street":"2Nd Ave S",
    "iso:country":"US",
    "sg:address":"315 2nd Ave S",
    "sg:city":"Seattle",
    "sg:classifiers":[
        {
            "category":"Professional",
            "subcategory":"Lawyer & Legal Services",
            "type":"Services"
        }
    ],
    "sg:phone":"+1 206 624 2859",
    "sg:postcode":"98104",
    "sg:province":"WA",
    "sg:tags":[
        "attorney"
    ],
    "wof:name":"Cascade Legal Svc",
    "wof:placetype":"venue"
},
  "geometry": {"coordinates":[-122.331654,47.599319],"type":"Point"}
}