{
  "type": "Feature",
  "properties": {
    "addr:full":"3 Arrow Ct Kettle Falls WA 99141",
    "addr:housenumber":"3",
    "addr:postcode":"99141",
    "addr:street":"Arrow Ct",
    "iso:country":"US",
    "sg:address":"3 Arrow Ct",
    "sg:city":"Kettle Falls",
    "sg:classifiers":[
        {
            "category":"Building & Trades",
            "subcategory":"Construction",
            "type":"Services"
        }
    ],
    "sg:phone":"+1 509 738 2497",
    "sg:postcode":"99141",
    "sg:province":"WA",
    "sg:tags":[
        "general",
        "contractor"
    ],
    "wof:name":"J/M Construction",
    "wof:placetype":"venue"
},
  "geometry": {"coordinates":[-118.123964,48.625427],"type":"Point"}
}