{
  "type": "Feature",
  "properties": {
    "addr:full":"134 SW 153rd St Burien WA 98166",
    "addr:housenumber":"134",
    "addr:postcode":"98166",
    "addr:street":"Sw 153Rd St",
    "iso:country":"US",
    "sg:address":"134 SW 153rd St",
    "sg:city":"Burien",
    "sg:classifiers":[
        {
            "category":"Social Services",
            "type":"Services"
        }
    ],
    "sg:phone":"+1 206 723 5845",
    "sg:postcode":"98166",
    "sg:province":"WA",
    "sg:tags":[
        "organization",
        "welfare"
    ],
    "wof:name":"Acorn",
    "wof:placetype":"venue"
},
  "geometry": {"coordinates":[-122.335915,47.466052],"type":"Point"}
}