{
  "type": "Feature",
  "properties": {
    "addr:full":"10118 224th St E Graham WA 98338",
    "addr:housenumber":"10118",
    "addr:postcode":"98338",
    "addr:street":"224Th St E",
    "iso:country":"US",
    "sg:address":"10118 224th St E",
    "sg:city":"Graham",
    "sg:classifiers":[
        {
            "category":"Arena",
            "subcategory":"Sports Club",
            "type":"Entertainment"
        }
    ],
    "sg:phone":"+1 253 847 7990",
    "sg:postcode":"98338",
    "sg:province":"WA",
    "sg:tags":[
        "martial art",
        "instruction"
    ],
    "wof:name":"Carrol's Corner",
    "wof:placetype":"venue"
},
  "geometry": {"coordinates":[-122.29536299999999,47.053078],"type":"Point"}
}