{
  "type": "Feature",
  "properties": {
    "addr:full":"4979 Mount Baker Hwy Deming WA 98244",
    "addr:housenumber":"4979",
    "addr:postcode":"98244",
    "addr:street":"Mount Baker Hwy",
    "iso:country":"US",
    "sg:address":"4979 Mount Baker Hwy",
    "sg:city":"Deming",
    "sg:classifiers":[
        {
            "category":"Health Services",
            "subcategory":"Doctor",
            "type":"Services"
        }
    ],
    "sg:phone":"+1 360 592 1100",
    "sg:postcode":"98244",
    "sg:province":"WA",
    "sg:tags":[
        "dental"
    ],
    "wof:name":"Brown Jim Ernie DDS",
    "wof:placetype":"venue"
},
  "geometry": {"coordinates":[-122.214105,48.824023],"type":"Point"}
}