{
  "type": "Feature",
  "properties": {
    "iso:country":"US",
    "sg:address":"16258 River Rd",
    "sg:city":"Leavenworth",
    "sg:classifiers":[
        {
            "category":"Travel",
            "subcategory":"Hotels & Motels",
            "type":"Entertainment"
        }
    ],
    "sg:phone":"+1 509 763 3213",
    "sg:postcode":"98826",
    "sg:province":"WA",
    "sg:tags":[
        "chalet",
        "rental",
        "cabin"
    ],
    "sg:website":"www.saimons.com",
    "wof:name":"Saimons Hide-A-Way",
    "wof:placetype":"venue"
},
  "geometry": {"coordinates":[-120.67150700000001,47.710581],"type":"Point"}
}