{
  "type": "Feature",
  "properties": {
    "addr:full":"10604 NE 38th Pl Ste 212 Kirkland WA 98033",
    "addr:housenumber":"10604",
    "addr:postcode":"98033",
    "addr:street":"Ne 38Th Pl Ste 212",
    "iso:country":"US",
    "sg:address":"10604 NE 38th Pl Ste 212",
    "sg:city":"Kirkland",
    "sg:classifiers":[
        {
            "category":"Education",
            "subcategory":"School",
            "type":"Public Place"
        }
    ],
    "sg:phone":"+1 425 822 3388",
    "sg:postcode":"98033",
    "sg:province":"WA",
    "wof:name":"Lake Washington Education Assoc",
    "wof:placetype":"venue"
},
  "geometry": {"coordinates":[-122.197272,47.643125],"type":"Point"}
}