{
  "type": "Feature",
  "properties": {
    "addr:full":"24600 NE 37th Ave Ridgefield WA 98642",
    "addr:housenumber":"24600",
    "addr:postcode":"98642",
    "addr:street":"Ne 37Th Ave",
    "iso:country":"US",
    "sg:address":"24600 NE 37th Ave",
    "sg:city":"Ridgefield",
    "sg:classifiers":[
        {
            "category":"Professional",
            "type":"Services"
        }
    ],
    "sg:phone":"+1 360 887 8032",
    "sg:postcode":"98642",
    "sg:province":"WA",
    "wof:name":"Seawood Studio",
    "wof:placetype":"venue"
},
  "geometry": {"coordinates":[-122.633261,45.79505],"type":"Point"}
}