{
  "type": "Feature",
  "properties": {
    "addr:full":"2012 123rd Ave E Puyallup WA 98372",
    "addr:housenumber":"2012",
    "addr:postcode":"98372",
    "addr:street":"123Rd Ave E",
    "iso:country":"US",
    "sg:address":"2012 123rd Ave E",
    "sg:city":"Puyallup",
    "sg:classifiers":[
        {
            "category":"Communications",
            "subcategory":"Film & Video Production",
            "type":"Services"
        }
    ],
    "sg:phone":"+1 253 863 1509",
    "sg:postcode":"98372",
    "sg:province":"WA",
    "sg:tags":[
        "motion"
    ],
    "wof:name":"Olympic Video Productions",
    "wof:placetype":"venue"
},
  "geometry": {"coordinates":[-122.265255,47.238895],"type":"Point"}
}