{
  "type": "Feature",
  "properties": {
    "addr:full":"269 SW Lewis St Chehalis WA 98532",
    "addr:housenumber":"269",
    "addr:postcode":"98532",
    "addr:street":"Sw Lewis St",
    "iso:country":"US",
    "sg:address":"269 SW Lewis St",
    "sg:city":"Chehalis",
    "sg:classifiers":[
        {
            "category":"Social Services",
            "subcategory":"Child Care",
            "type":"Services"
        }
    ],
    "sg:phone":"+1 360 748 1418",
    "sg:postcode":"98532",
    "sg:province":"WA",
    "wof:name":"Best Buddies",
    "wof:placetype":"venue"
},
  "geometry": {"coordinates":[-122.967862,46.660133],"type":"Point"}
}