{
  "type": "Feature",
  "properties": {
    "addr:full":"8502 Riverside Rd E Sumner WA 98390",
    "addr:housenumber":"8502",
    "addr:postcode":"98390",
    "addr:street":"Riverside Rd E",
    "iso:country":"US",
    "sg:address":"8502 Riverside Rd E",
    "sg:city":"Sumner",
    "sg:classifiers":[
        {
            "category":"Building & Trades",
            "subcategory":"Construction",
            "type":"Services"
        }
    ],
    "sg:phone":"+1 253 833 3094",
    "sg:postcode":"98390",
    "sg:province":"WA",
    "sg:tags":[
        "family",
        "fire",
        "general",
        "water",
        "restoration",
        "home",
        "contractor",
        "wind"
    ],
    "wof:name":"Kencade Construction Company",
    "wof:placetype":"venue"
},
  "geometry": {"coordinates":[-122.21331600000001,47.180209],"type":"Point"}
}