{
  "type": "Feature",
  "properties": {
    "iso:country":"US",
    "sg:address":"4623 119th Pl SE",
    "sg:city":"Everett",
    "sg:classifiers":[
        {
            "category":"Health Services",
            "subcategory":"Nursing And Care Facility",
            "type":"Services"
        }
    ],
    "sg:phone":"+1 425 337 9793",
    "sg:postcode":"98208",
    "sg:province":"WA",
    "sg:tags":[
        "skilled"
    ],
    "wof:name":"Medical Nursing Services",
    "wof:placetype":"venue"
},
  "geometry": {"coordinates":[-122.169763,47.889311],"type":"Point"}
}