{
  "type": "Feature",
  "properties": {
    "addr:full":"918 S Monroe St Spokane WA 99204",
    "addr:housenumber":"918",
    "addr:postcode":"99204",
    "addr:street":"S Monroe St",
    "iso:country":"US",
    "sg:address":"918 S Monroe St",
    "sg:city":"Spokane",
    "sg:classifiers":[
        {
            "category":"Professional",
            "subcategory":"Management & Consulting",
            "type":"Services"
        }
    ],
    "sg:phone":"+1 509 328 7308",
    "sg:postcode":"99204",
    "sg:province":"WA",
    "sg:tags":[
        "business"
    ],
    "wof:name":"Childrens Academy For Neur",
    "wof:placetype":"venue"
},
  "geometry": {"coordinates":[-117.426125,47.646498],"type":"Point"}
}