{
  "type": "Feature",
  "properties": {
    "addr:full":"9800 NE 120th Pl Ste D Kirkland WA 98034",
    "addr:housenumber":"9800",
    "addr:postcode":"98034",
    "addr:street":"Ne 120Th Pl Ste D",
    "iso:country":"US",
    "sg:address":"9800 NE 120th Pl Ste D",
    "sg:city":"Kirkland",
    "sg:classifiers":[
        {
            "category":"Health Services",
            "subcategory":"Doctor",
            "type":"Services"
        }
    ],
    "sg:phone":"+1 425 823 8777",
    "sg:postcode":"98034",
    "sg:province":"WA",
    "sg:tags":[
        "surgeon",
        "oral"
    ],
    "wof:name":"Freeman Douglas G DDS",
    "wof:placetype":"venue"
},
  "geometry": {"coordinates":[-122.209999,47.708199],"type":"Point"}
}