{
  "type": "Feature",
  "properties": {
    "addr:full":"513 Henkle St Tekoa WA 99033",
    "addr:housenumber":"513",
    "addr:postcode":"99033",
    "addr:street":"Henkle St",
    "iso:country":"US",
    "sg:address":"513 Henkle St",
    "sg:city":"Tekoa",
    "sg:classifiers":[
        {
            "category":"Education",
            "subcategory":"School",
            "type":"Public Place"
        }
    ],
    "sg:phone":"+1 509 284 3401",
    "sg:postcode":"99033",
    "sg:province":"WA",
    "wof:name":"Tekoa High School",
    "wof:placetype":"venue"
},
  "geometry": {"coordinates":[-117.067697,47.223077],"type":"Point"}
}