{
  "type": "Feature",
  "properties": {
    "addr:full":"19005 Bothell Way NE Bothell WA 98011",
    "addr:housenumber":"19005",
    "addr:postcode":"98011",
    "addr:street":"Bothell Way Ne",
    "iso:country":"US",
    "sg:address":"19005 Bothell Way NE",
    "sg:city":"Bothell",
    "sg:classifiers":[
        {
            "category":"Autos & Motor Vehicles",
            "subcategory":"Fuel & Gas Station",
            "type":"Retail Goods"
        }
    ],
    "sg:phone":"+1 425 483 0440",
    "sg:postcode":"98011",
    "sg:province":"WA",
    "sg:tags":[
        "oil"
    ],
    "wof:name":"Bothell Service Ctr",
    "wof:placetype":"venue"
},
  "geometry": {"coordinates":[-122.209847,47.765689],"type":"Point"}
}