{
  "type": "Feature",
  "properties": {
    "addr:full":"1914 S 289th St Federal Way WA 98003",
    "addr:housenumber":"1914",
    "addr:postcode":"98003",
    "addr:street":"S 289Th St",
    "iso:country":"US",
    "sg:address":"1914 S 289th St",
    "sg:city":"Federal Way",
    "sg:classifiers":[
        {
            "category":"Professional",
            "subcategory":"Computer Services",
            "type":"Services"
        }
    ],
    "sg:phone":"+1 253 941 1299",
    "sg:postcode":"98003",
    "sg:province":"WA",
    "sg:tags":[
        "design",
        "system"
    ],
    "wof:name":"Ducthman Enterprises",
    "wof:placetype":"venue"
},
  "geometry": {"coordinates":[-122.308651,47.342644],"type":"Point"}
}