{
  "type": "Feature",
  "properties": {
    "addr:full":"159 S Lincoln St Spokane WA 99201",
    "addr:housenumber":"159",
    "addr:postcode":"99201",
    "addr:street":"S Lincoln St",
    "iso:country":"US",
    "sg:address":"159 S Lincoln St",
    "sg:city":"Spokane",
    "sg:classifiers":[
        {
            "category":"Professional",
            "subcategory":"Management & Consulting",
            "type":"Services"
        }
    ],
    "sg:phone":"+1 509 363 1500",
    "sg:postcode":"99201",
    "sg:province":"WA",
    "sg:tags":[
        "public",
        "relations"
    ],
    "wof:name":"Centricav Inc",
    "wof:placetype":"venue"
},
  "geometry": {"coordinates":[-117.424919,47.655044],"type":"Point"}
}