{
  "type": "Feature",
  "properties": {
    "addr:full":"3005 W Pearl St Pasco WA 99301",
    "addr:housenumber":"3005",
    "addr:postcode":"99301",
    "addr:street":"W Pearl St",
    "iso:country":"US",
    "sg:address":"3005 W Pearl St",
    "sg:city":"Pasco",
    "sg:classifiers":[
        {
            "category":"Professional",
            "subcategory":"Computer Services",
            "type":"Services"
        }
    ],
    "sg:phone":"+1 509 545 0482",
    "sg:postcode":"99301",
    "sg:province":"WA",
    "sg:tags":[
        "prepackaged",
        "software"
    ],
    "wof:name":"Software Consulting Service",
    "wof:placetype":"venue"
},
  "geometry": {"coordinates":[-119.13285,46.245192],"type":"Point"}
}