{
  "type": "Feature",
  "properties": {
    "addr:full":"4005 6th Ave S Seattle WA 98108",
    "addr:housenumber":"4005",
    "addr:postcode":"98108",
    "addr:street":"6Th Ave S",
    "iso:country":"US",
    "sg:address":"4005 6th Ave S",
    "sg:city":"Seattle",
    "sg:classifiers":[
        {
            "category":"Professional",
            "subcategory":"Business Services",
            "type":"Services"
        }
    ],
    "sg:phone":"+1 206 297 1780",
    "sg:postcode":"98108",
    "sg:province":"WA",
    "wof:name":"Direct Connect Group",
    "wof:placetype":"venue"
},
  "geometry": {"coordinates":[-122.326814,47.567201],"type":"Point"}
}