{
  "type": "Feature",
  "properties": {
    "addr:full":"13400 NE 20th St Bellevue WA 98005",
    "addr:housenumber":"13400",
    "addr:postcode":"98005",
    "addr:street":"Ne 20Th St",
    "iso:country":"US",
    "sg:address":"13400 NE 20th St",
    "sg:city":"Bellevue",
    "sg:classifiers":[
        {
            "category":"Shopping",
            "subcategory":"Computers & Home Electronics",
            "type":"Retail Goods"
        }
    ],
    "sg:phone":"+1 425 644 0077",
    "sg:postcode":"98005",
    "sg:province":"WA",
    "sg:tags":[
        "consulting",
        "center"
    ],
    "wof:name":"Hq NW Network & Computer",
    "wof:placetype":"venue"
},
  "geometry": {"coordinates":[-122.16003600000001,47.628088],"type":"Point"}
}