{
  "type": "Feature",
  "properties": {
    "addr:full":"116 W 2nd St Grandview WA 98930",
    "addr:housenumber":"116",
    "addr:postcode":"98930",
    "addr:street":"W 2Nd St",
    "iso:country":"US",
    "sg:address":"116 W 2nd St",
    "sg:city":"Grandview",
    "sg:classifiers":[
        {
            "category":"Food & Beverages",
            "subcategory":"Specialty",
            "type":"Retail Goods"
        }
    ],
    "sg:phone":"+1 509 882 5599",
    "sg:postcode":"98930",
    "sg:province":"WA",
    "sg:tags":[
        "health",
        "diet"
    ],
    "wof:name":"Hierveria Laesperanza Devivir",
    "wof:placetype":"venue"
},
  "geometry": {"coordinates":[-119.903268,46.254729],"type":"Point"}
}