{
  "type": "Feature",
  "properties": {
    "addr:full":"10320 NE Valley Rd Ste 107 Bainbridge Island WA 98110",
    "addr:housenumber":"10320",
    "addr:postcode":"98110",
    "addr:street":"Ne Valley Rd Ste 107",
    "iso:country":"US",
    "sg:address":"10320 NE Valley Rd Ste 107",
    "sg:city":"Bainbridge Island",
    "sg:classifiers":[
        {
            "category":"Shopping",
            "subcategory":"Clothing, Apparel, & Fashions",
            "type":"Retail Goods"
        }
    ],
    "sg:phone":"+1 206 842 8944",
    "sg:postcode":"98110",
    "sg:province":"WA",
    "sg:tags":[
        "accessory",
        "clothing",
        "women's"
    ],
    "wof:name":"Que' Sarah Boutique",
    "wof:placetype":"venue"
},
  "geometry": {"coordinates":[-122.511438,47.664934],"type":"Point"}
}