{
  "type": "Feature",
  "properties": {
    "addr:full":"6355 NE Early Dawn Ln Poulsbo WA 98370",
    "addr:housenumber":"6355",
    "addr:postcode":"98370",
    "addr:street":"Ne Early Dawn Ln",
    "iso:country":"US",
    "sg:address":"6355 NE Early Dawn Ln",
    "sg:city":"Poulsbo",
    "sg:classifiers":[
        {
            "category":"Real Estate",
            "subcategory":"Real Estate Operator",
            "type":"Services"
        }
    ],
    "sg:phone":"+1 360 598 6286",
    "sg:postcode":"98370",
    "sg:province":"WA",
    "sg:tags":[
        "building",
        "apartment"
    ],
    "wof:name":"Waki Apts",
    "wof:placetype":"venue"
},
  "geometry": {"coordinates":[-122.563228,47.751249],"type":"Point"}
}