{
  "type": "Feature",
  "properties": {
    "addr:full":"3007 S Melrose St Tacoma WA 98405",
    "addr:housenumber":"3007",
    "addr:postcode":"98405",
    "addr:street":"S Melrose St",
    "iso:country":"US",
    "sg:address":"3007 S Melrose St",
    "sg:city":"Tacoma",
    "sg:classifiers":[
        {
            "category":"Building & Trades",
            "subcategory":"Landscaping Services",
            "type":"Services"
        }
    ],
    "sg:phone":"+1 253 473 7789",
    "sg:postcode":"98405",
    "sg:province":"WA",
    "sg:tags":[
        "lawn"
    ],
    "wof:name":"Ramirez Landscape Services",
    "wof:placetype":"venue"
},
  "geometry": {"coordinates":[-122.474869,47.247398],"type":"Point"}
}