{
  "type": "Feature",
  "properties": {
    "iso:country":"US",
    "sg:address":"1140 N 94th St",
    "sg:city":"Seattle",
    "sg:classifiers":[
        {
            "category":"Building & Trades",
            "subcategory":"Plumbing",
            "type":"Services"
        }
    ],
    "sg:phone":"+1 206 575 1952",
    "sg:postcode":"98103",
    "sg:province":"WA",
    "sg:tags":[
        "mechanical",
        "contractor"
    ],
    "wof:name":"Emerald Aire Inc",
    "wof:placetype":"venue"
},
  "geometry": {"coordinates":[-122.342015,47.697147],"type":"Point"}
}