{
  "type": "Feature",
  "properties": {
    "addr:full":"1908 E Republican St Seattle WA 98112",
    "addr:housenumber":"1908",
    "addr:postcode":"98112",
    "addr:street":"E Republican St",
    "iso:country":"US",
    "sg:address":"1908 E Republican St",
    "sg:city":"Seattle",
    "sg:classifiers":[
        {
            "category":"Shopping",
            "subcategory":"Clothing, Apparel, & Fashions",
            "type":"Retail Goods"
        },
        {
            "category":"Wholesale",
            "subcategory":"Apparel",
            "type":"Manufacturing & Wholesale Goods"
        }
    ],
    "sg:phone":"+1 206 329 4494",
    "sg:postcode":"98112",
    "sg:province":"WA",
    "sg:tags":[
        "sportswear-wholesale",
        "sportswear",
        "manufacturer"
    ],
    "wof:name":"Beppa",
    "wof:placetype":"venue"
},
  "geometry": {"coordinates":[-122.307137,47.623207],"type":"Point"}
}