{
  "type": "Feature",
  "properties": {
    "addr:full":"14022 240th Ave SE Issaquah WA 98027",
    "addr:housenumber":"14022",
    "addr:postcode":"98027",
    "addr:street":"240Th Ave Se",
    "iso:country":"US",
    "sg:address":"14022 240th Ave SE",
    "sg:city":"Issaquah",
    "sg:classifiers":[
        {
            "category":"Manufacturing",
            "subcategory":"Building Materials",
            "type":"Manufacturing & Wholesale Goods"
        }
    ],
    "sg:phone":"+1 425 391 0896",
    "sg:postcode":"98027",
    "sg:province":"WA",
    "sg:tags":[
        "member",
        "mfg",
        "wood",
        "structural"
    ],
    "wof:name":"Beanko",
    "wof:placetype":"venue"
},
  "geometry": {"coordinates":[-122.020437,47.475867],"type":"Point"}
}