{
  "type": "Feature",
  "properties": {
    "addr:full":"740 Winslow Way NE Bainbridge Island WA 98110",
    "addr:housenumber":"740",
    "addr:postcode":"98110",
    "addr:street":"Winslow Way Ne",
    "iso:country":"US",
    "sg:address":"740 Winslow Way NE",
    "sg:city":"Bainbridge Island",
    "sg:classifiers":[
        {
            "category":"Shopping",
            "subcategory":"Bicycles & Sporting Goods",
            "type":"Retail Goods"
        },
        {
            "category":"Sports & Exercise",
            "subcategory":"Bicycle Rental",
            "type":"Entertainment"
        }
    ],
    "sg:phone":"+1 206 842 9191",
    "sg:postcode":"98110",
    "sg:province":"WA",
    "sg:tags":[
        "bike"
    ],
    "sg:website":"www.classiccycleus.com",
    "wof:name":"Classic Cycle",
    "wof:placetype":"venue"
},
  "geometry": {"coordinates":[-122.51022,47.624917],"type":"Point"}
}