{
  "type": "Feature",
  "properties": {
    "addr:full":"6225 Bayview Rd Clinton WA 98236",
    "addr:housenumber":"6225",
    "addr:postcode":"98236",
    "addr:street":"Bayview Rd",
    "iso:country":"US",
    "sg:address":"6225 Bayview Rd",
    "sg:city":"Clinton",
    "sg:classifiers":[
        {
            "category":"Building & Trades",
            "subcategory":"Construction",
            "type":"Services"
        }
    ],
    "sg:phone":"+1 360 321 3619",
    "sg:postcode":"98236",
    "sg:province":"WA",
    "sg:tags":[
        "contractor"
    ],
    "wof:name":"Sunlight Construction",
    "wof:placetype":"venue"
},
  "geometry": {"coordinates":[-122.46173,47.984804],"type":"Point"}
}