{
  "type": "Feature",
  "properties": {
    "addr:full":"226 Plomondon Rd Toledo WA 98591",
    "addr:housenumber":"226",
    "addr:postcode":"98591",
    "addr:street":"Plomondon Rd",
    "iso:country":"US",
    "sg:address":"226 Plomondon Rd",
    "sg:city":"Toledo",
    "sg:classifiers":[
        {
            "category":"Social Services",
            "subcategory":"Child Care",
            "type":"Services"
        }
    ],
    "sg:phone":"+1 360 864 6721",
    "sg:postcode":"98591",
    "sg:province":"WA",
    "wof:name":"Ardies Day Care & Pre School",
    "wof:placetype":"venue"
},
  "geometry": {"coordinates":[-122.85069799999999,46.452656],"type":"Point"}
}