{
  "type": "Feature",
  "properties": {
    "addr:full":"2321 S Skipworth Rd Spokane WA 99206",
    "addr:housenumber":"2321",
    "addr:postcode":"99206",
    "addr:street":"S Skipworth Rd",
    "iso:country":"US",
    "sg:address":"2321 S Skipworth Rd",
    "sg:city":"Spokane",
    "sg:classifiers":[
        {
            "category":"Professional",
            "subcategory":"Management & Consulting",
            "type":"Services"
        }
    ],
    "sg:phone":"+1 509 922 5686",
    "sg:postcode":"99206",
    "sg:province":"WA",
    "sg:tags":[
        "public",
        "relations"
    ],
    "wof:name":"Experience America",
    "wof:placetype":"venue"
},
  "geometry": {"coordinates":[-117.253265,47.635359],"type":"Point"}
}