{
  "type": "Feature",
  "properties": {
    "addr:full":"6523 California Ave SW Seattle WA 98136",
    "addr:housenumber":"6523",
    "addr:postcode":"98136",
    "addr:street":"California Ave Sw",
    "iso:country":"US",
    "sg:address":"6523 California Ave SW",
    "sg:city":"Seattle",
    "sg:classifiers":[
        {
            "category":"Building & Trades",
            "subcategory":"Locksmith",
            "type":"Services"
        }
    ],
    "sg:phone":"+1 206 212 1390",
    "sg:postcode":"98136",
    "sg:province":"WA",
    "sg:tags":[
        "key"
    ],
    "wof:name":"Locksmith Service",
    "wof:placetype":"venue"
},
  "geometry": {"coordinates":[-122.387424,47.544655],"type":"Point"}
}