{
  "type": "Feature",
  "properties": {
    "iso:country":"US",
    "sg:address":"2541 7th Ave W",
    "sg:city":"Seattle",
    "sg:classifiers":[
        {
            "category":"Retail",
            "subcategory":"Auto Repair",
            "type":"Services"
        }
    ],
    "sg:phone":"+1 206 283 4773",
    "sg:postcode":"98119",
    "sg:province":"WA",
    "sg:tags":[
        "importing",
        "automotive",
        "marine"
    ],
    "wof:name":"RPM Marine Inc",
    "wof:placetype":"venue"
},
  "geometry": {"coordinates":[-122.36633500000001,47.641586],"type":"Point"}
}