{
  "type": "Feature",
  "properties": {
    "addr:full":"22018 N Saddle Mountain Ln Colbert WA 99005",
    "addr:housenumber":"22018",
    "addr:postcode":"99005",
    "addr:street":"N Saddle Mountain Ln Colbert",
    "iso:country":"US",
    "sg:address":"22018 N Saddle Mountain Ln",
    "sg:city":"Colbert",
    "sg:classifiers":[
        {
            "category":"Home & Garden",
            "subcategory":"Building Materials",
            "type":"Retail Goods"
        },
        {
            "category":"Professional",
            "subcategory":"Printing & Photocopies",
            "type":"Services"
        }
    ],
    "sg:phone":"+1 509 467 4190",
    "sg:postcode":"99005",
    "sg:province":"WA",
    "sg:tags":[
        "garage",
        "opener",
        "door",
        "door-overhead",
        "type"
    ],
    "wof:name":"Stjern Corporation",
    "wof:placetype":"venue"
},
  "geometry": {"coordinates":[-117.400131,47.859443],"type":"Point"}
}