{
  "type": "Feature",
  "properties": {
    "addr:full":"332 Red Deer Dr Port Angeles WA 98362",
    "addr:housenumber":"332",
    "addr:postcode":"98362",
    "addr:street":"Red Deer Dr",
    "iso:country":"US",
    "sg:address":"332 Red Deer Dr",
    "sg:city":"Port Angeles",
    "sg:classifiers":[
        {
            "category":"Social Services",
            "type":"Services"
        }
    ],
    "sg:phone":"+1 360 417 0224",
    "sg:postcode":"98362",
    "sg:province":"WA",
    "wof:name":"Johnston Carolyn",
    "wof:placetype":"venue"
},
  "geometry": {"coordinates":[-123.273223,48.021647],"type":"Point"}
}