{
  "type": "Feature",
  "properties": {
    "addr:full":"924 Smith Ave Richland WA 99352",
    "addr:housenumber":"924",
    "addr:postcode":"99352",
    "addr:street":"Smith Ave",
    "iso:country":"US",
    "sg:address":"924 Smith Ave",
    "sg:city":"Richland",
    "sg:classifiers":[
        {
            "category":"Shopping",
            "type":"Retail Goods"
        }
    ],
    "sg:phone":"+1 509 947 0042",
    "sg:postcode":"99352",
    "sg:province":"WA",
    "sg:tags":[
        "merchandise"
    ],
    "wof:name":"Furrytales Pet Sitting",
    "wof:placetype":"venue"
},
  "geometry": {"coordinates":[-119.293054,46.279357],"type":"Point"}
}