{
  "type": "Feature",
  "properties": {
    "iso:country":"US",
    "sg:address":"13314 224th St E",
    "sg:city":"Graham",
    "sg:classifiers":[
        {
            "category":"Organizations",
            "subcategory":"Religious Organization",
            "type":"Services"
        }
    ],
    "sg:phone":"+1 360 893 6842",
    "sg:postcode":"98338",
    "sg:province":"WA",
    "sg:tags":[
        "church"
    ],
    "wof:name":"Cedar Springs Community Church",
    "wof:placetype":"venue"
},
  "geometry": {"coordinates":[-122.254533,47.052591],"type":"Point"}
}