{
  "type": "Feature",
  "properties": {
    "addr:full":"1105 Poplar Ave Wenatchee WA 98801",
    "addr:housenumber":"1105",
    "addr:postcode":"98801",
    "addr:street":"Poplar Ave",
    "iso:country":"US",
    "sg:address":"1105 Poplar Ave",
    "sg:city":"Wenatchee",
    "sg:classifiers":[
        {
            "category":"Building & Trades",
            "subcategory":"Plumbing",
            "type":"Services"
        }
    ],
    "sg:phone":"+1 509 548 4692",
    "sg:postcode":"98801",
    "sg:province":"WA",
    "sg:tags":[
        "contractor"
    ],
    "wof:name":"Central Washington Backflow",
    "wof:placetype":"venue"
},
  "geometry": {"coordinates":[-120.34303,47.437765],"type":"Point"}
}