{
  "type": "Feature",
  "properties": {
    "addr:full":"2201 33rd Ave SE Puyallup WA 98374",
    "addr:housenumber":"2201",
    "addr:postcode":"98374",
    "addr:street":"33Rd Ave Se",
    "iso:country":"US",
    "sg:address":"2201 33rd Ave SE",
    "sg:city":"Puyallup",
    "sg:classifiers":[
        {
            "category":"Social Services",
            "subcategory":"Adult Care",
            "type":"Services"
        }
    ],
    "sg:phone":"+1 253 841 1968",
    "sg:postcode":"98374",
    "sg:province":"WA",
    "sg:tags":[
        "residential"
    ],
    "wof:name":"Dillons Adult Family Home",
    "wof:placetype":"venue"
},
  "geometry": {"coordinates":[-122.26249900000001,47.161476],"type":"Point"}
}