{
  "type": "Feature",
  "properties": {
    "addr:full":"2424 Gravelly Beach Loop NW Olympia WA 98502",
    "addr:housenumber":"2424",
    "addr:postcode":"olympia wa 98502",
    "addr:street":"Gravelly Beach Loop Nw",
    "iso:country":"US",
    "sg:address":"2424 Gravelly Beach Loop NW",
    "sg:city":"Olympia",
    "sg:classifiers":[
        {
            "category":"Professional",
            "subcategory":"Engineering",
            "type":"Services"
        }
    ],
    "sg:phone":"+1 360 866 0164",
    "sg:postcode":"98502",
    "sg:province":"WA",
    "sg:tags":[
        "design",
        "boat",
        "mfg"
    ],
    "wof:name":"Devlin Designing Boat Builder",
    "wof:placetype":"venue"
},
  "geometry": {"coordinates":[-122.981234,47.104825],"type":"Point"}
}