{
  "type": "Feature",
  "properties": {
    "addr:full":"255796 Hwy 101 Port Angeles WA 98362",
    "addr:housenumber":"255796",
    "addr:postcode":"98362",
    "addr:street":"Hwy 101",
    "iso:country":"US",
    "sg:address":"255796 Hwy 101",
    "sg:city":"Port Angeles",
    "sg:classifiers":[
        {
            "category":"Shopping",
            "type":"Retail Goods"
        }
    ],
    "sg:phone":"+1 360 457 5561",
    "sg:postcode":"98362",
    "sg:province":"WA",
    "sg:tags":[
        "farm",
        "equine",
        "merchandise"
    ],
    "wof:name":"Justin G Peterson",
    "wof:placetype":"venue"
},
  "geometry": {"coordinates":[-123.28877,48.095064],"type":"Point"}
}