{
  "type": "Feature",
  "properties": {
    "iso:country":"US",
    "sg:address":"905 W Riverside Ave",
    "sg:city":"Spokane",
    "sg:classifiers":[
        {
            "category":"Professional",
            "subcategory":"Computer Services",
            "type":"Services"
        }
    ],
    "sg:phone":"+1 509 455 4350",
    "sg:postcode":"99201",
    "sg:province":"WA",
    "sg:tags":[
        "website",
        "design",
        "system"
    ],
    "wof:name":"Adept Web Design",
    "wof:placetype":"venue"
},
  "geometry": {"coordinates":[-117.426579,47.658167],"type":"Point"}
}