{
  "type": "Feature",
  "properties": {
    "addr:full":"10619 E Sprague Ave Spokane WA 99206",
    "addr:housenumber":"10619",
    "addr:postcode":"99206",
    "addr:street":"E Sprague Ave",
    "iso:country":"US",
    "sg:address":"10619 E Sprague Ave",
    "sg:city":"Spokane",
    "sg:classifiers":[
        {
            "category":"Home & Garden",
            "subcategory":"Furniture",
            "type":"Retail Goods"
        }
    ],
    "sg:phone":"+1 509 928 2485",
    "sg:postcode":"99206",
    "sg:province":"WA",
    "wof:name":"Walkers Furniture Inc",
    "wof:placetype":"venue"
},
  "geometry": {"coordinates":[-117.262597,47.657109],"type":"Point"}
}