{
  "type": "Feature",
  "properties": {
    "addr:full":"6645 185th Ave NE Redmond WA 98052",
    "addr:housenumber":"6645",
    "addr:postcode":"98052",
    "addr:street":"185Th Ave Ne",
    "iso:country":"US",
    "sg:address":"6645 185th Ave NE",
    "sg:city":"Redmond",
    "sg:classifiers":[
        {
            "category":"Wholesale",
            "subcategory":"Medical Equipment & Supplies",
            "type":"Manufacturing & Wholesale Goods"
        }
    ],
    "sg:phone":"+1 425 376 1300",
    "sg:postcode":"98052",
    "sg:province":"WA",
    "sg:tags":[
        "physician",
        "surgeon"
    ],
    "sg:website":"www.guidant.com",
    "wof:name":"Guidant Corp",
    "wof:placetype":"venue"
},
  "geometry": {"coordinates":[-122.093756,47.665395],"type":"Point"}
}