{
  "type": "Feature",
  "properties": {
    "addr:full":"108 E 16th Ave Spokane WA 99203",
    "addr:housenumber":"108",
    "addr:postcode":"99203",
    "addr:street":"E 16Th Ave",
    "iso:country":"US",
    "sg:address":"108 E 16th Ave",
    "sg:city":"Spokane",
    "sg:classifiers":[
        {
            "category":"Building & Trades",
            "subcategory":"Construction",
            "type":"Services"
        }
    ],
    "sg:phone":"+1 509 624 4494",
    "sg:postcode":"99203",
    "sg:province":"WA",
    "sg:tags":[
        "painter"
    ],
    "wof:name":"Dan Lynch Painting",
    "wof:placetype":"venue"
},
  "geometry": {"coordinates":[-117.40863899999999,47.641201],"type":"Point"}
}