{
  "type": "Feature",
  "properties": {
    "iso:country":"US",
    "sg:address":"921 S Monroe St",
    "sg:city":"Spokane",
    "sg:classifiers":[
        {
            "category":"Real Estate",
            "subcategory":"Real Estate Agent",
            "type":"Services"
        }
    ],
    "sg:phone":"+1 509 455 5411",
    "sg:postcode":"99204",
    "sg:province":"WA",
    "wof:name":"Robert A Gilles Inc Realty",
    "wof:placetype":"venue"
},
  "geometry": {"coordinates":[-117.426011,47.646557],"type":"Point"}
}