{
  "type": "Feature",
  "properties": {
    "addr:full":"4707 N Addison St Spokane WA 99207",
    "addr:housenumber":"4707",
    "addr:postcode":"99207",
    "addr:street":"N Addison St",
    "iso:country":"US",
    "sg:address":"4707 N Addison St",
    "sg:city":"Spokane",
    "sg:classifiers":[
        {
            "category":"Organizations",
            "subcategory":"Non-profit Organization",
            "type":"Services"
        }
    ],
    "sg:phone":"+1 509 489 2099",
    "sg:postcode":"99207",
    "sg:province":"WA",
    "sg:tags":[
        "human"
    ],
    "wof:name":"Nevada-Lidgerwood Neighborhood",
    "wof:placetype":"venue"
},
  "geometry": {"coordinates":[-117.403311,47.701014],"type":"Point"}
}