{
  "type": "Feature",
  "properties": {
    "addr:full":"641 S Pioneer Way Moses Lake WA 98837",
    "addr:housenumber":"641",
    "addr:postcode":"98837",
    "addr:street":"S Pioneer Way",
    "iso:country":"US",
    "sg:address":"641 S Pioneer Way",
    "sg:city":"Moses Lake",
    "sg:classifiers":[
        {
            "category":"Personal",
            "type":"Services"
        }
    ],
    "sg:phone":"+1 509 766 1235",
    "sg:postcode":"98837",
    "sg:province":"WA",
    "sg:tags":[
        "wear",
        "formal"
    ],
    "wof:name":"Mr Tux",
    "wof:placetype":"venue"
},
  "geometry": {"coordinates":[-119.26949999999999,47.129451],"type":"Point"}
}