{
  "type": "Feature",
  "properties": {
    "addr:full":"2806 NE 65th Ave Vancouver WA 98661",
    "addr:housenumber":"2806",
    "addr:postcode":"98661",
    "addr:street":"Ne 65Th Ave",
    "iso:country":"US",
    "sg:address":"2806 NE 65th Ave",
    "sg:city":"Vancouver",
    "sg:classifiers":[
        {
            "category":"Autos & Motor Vehicles",
            "subcategory":"Auto Supplies",
            "type":"Retail Goods"
        }
    ],
    "sg:phone":"+1 360 693 3855",
    "sg:postcode":"98661",
    "sg:province":"WA",
    "sg:tags":[
        "tire"
    ],
    "wof:name":"Interstate Tire Svc",
    "wof:placetype":"venue"
},
  "geometry": {"coordinates":[-122.60509,45.643791],"type":"Point"}
}