{
  "type": "Feature",
  "properties": {
    "addr:full":"18332 McLean Rd SW Vashon WA 98070",
    "addr:housenumber":"18332",
    "addr:postcode":"98070",
    "addr:street":"Mclean Rd Sw",
    "iso:country":"US",
    "sg:address":"18332 McLean Rd SW",
    "sg:city":"Vashon",
    "sg:classifiers":[
        {
            "category":"Shopping",
            "subcategory":"Hobbies, Toys, & Games",
            "type":"Retail Goods"
        }
    ],
    "sg:phone":"+1 206 463 2783",
    "sg:postcode":"98070",
    "sg:province":"WA",
    "wof:name":"Hobby Hut Gifts",
    "wof:placetype":"venue"
},
  "geometry": {"coordinates":[-122.448598,47.440163],"type":"Point"}
}