{
  "type": "Feature",
  "properties": {
    "addr:full":"1806 Broadway Everett WA 98201",
    "addr:housenumber":"1806",
    "addr:postcode":"98201",
    "addr:street":"Broadway",
    "iso:country":"US",
    "sg:address":"1806 Broadway",
    "sg:city":"Everett",
    "sg:classifiers":[
        {
            "category":"Food & Beverages",
            "subcategory":"Groceries & Convenience Stores",
            "type":"Retail Goods"
        }
    ],
    "sg:phone":"+1 425 252 9811",
    "sg:postcode":"98201",
    "sg:province":"WA",
    "wof:name":"Am/PM Mini Market",
    "wof:placetype":"venue"
},
  "geometry": {"coordinates":[-122.201311,47.992476],"type":"Point"}
}