{
  "type": "Feature",
  "properties": {
    "addr:full":"31011 26th Ave S Federal Way WA 98003",
    "addr:housenumber":"31011",
    "addr:postcode":"98003",
    "addr:street":"26Th Ave S Federal Way",
    "iso:country":"US",
    "sg:address":"31011 26th Ave S",
    "sg:city":"Federal Way",
    "sg:classifiers":[
        {
            "category":"Personal",
            "subcategory":"Beauty Salon",
            "type":"Services"
        }
    ],
    "sg:phone":"+1 253 941 4949",
    "sg:postcode":"98003",
    "sg:province":"WA",
    "sg:tags":[
        "shop"
    ],
    "wof:name":"Brendas Shop",
    "wof:placetype":"venue"
},
  "geometry": {"coordinates":[-122.29947799999999,47.323884],"type":"Point"}
}