{
  "type": "Feature",
  "properties": {
    "addr:full":"4922 Waschke Rd Bellingham WA 98226",
    "addr:housenumber":"4922",
    "addr:postcode":"98226",
    "addr:street":"Waschke Rd",
    "iso:country":"US",
    "sg:address":"4922 Waschke Rd",
    "sg:city":"Bellingham",
    "sg:classifiers":[
        {
            "category":"Building & Trades",
            "subcategory":"Construction",
            "type":"Services"
        }
    ],
    "sg:phone":"+1 360 671 3556",
    "sg:postcode":"98226",
    "sg:province":"WA",
    "sg:tags":[
        "contractor"
    ],
    "wof:name":"Precision Roofing",
    "wof:placetype":"venue"
},
  "geometry": {"coordinates":[-122.52981800000001,48.821697],"type":"Point"}
}