{
  "type": "Feature",
  "properties": {
    "addr:full":"4608 N Windsor Dr Spokane WA 99205",
    "addr:housenumber":"4608",
    "addr:postcode":"99205",
    "addr:street":"N Windsor Dr",
    "iso:country":"US",
    "sg:address":"4608 N Windsor Dr",
    "sg:city":"Spokane",
    "sg:classifiers":[
        {
            "category":"Sports & Exercise",
            "subcategory":"Gym",
            "type":"Entertainment"
        }
    ],
    "sg:phone":"+1 509 328 0252",
    "sg:postcode":"99205",
    "sg:province":"WA",
    "sg:tags":[
        "fitness",
        "physical",
        "facility"
    ],
    "wof:name":"Serenity Salon & Day Spa",
    "wof:placetype":"venue"
},
  "geometry": {"coordinates":[-117.489447,47.700186],"type":"Point"}
}