{
  "type": "Feature",
  "properties": {
    "iso:country":"US",
    "sg:address":"15901 23rd Ave SW",
    "sg:city":"Seattle",
    "sg:classifiers":[
        {
            "category":"Professional",
            "subcategory":"Computer Services",
            "type":"Services"
        }
    ],
    "sg:phone":"+1 206 248 1238",
    "sg:postcode":"98166",
    "sg:province":"WA",
    "sg:tags":[
        "related"
    ],
    "wof:name":"David Denmark",
    "wof:placetype":"venue"
},
  "geometry": {"coordinates":[-122.363247,47.459885],"type":"Point"}
}