{
  "type": "Feature",
  "properties": {
    "addr:full":"5700 100th St SW Tacoma WA 98499",
    "addr:housenumber":"5700",
    "addr:postcode":"98499",
    "addr:street":"100Th St Sw",
    "iso:country":"US",
    "sg:address":"5700 100th St SW",
    "sg:city":"Tacoma",
    "sg:classifiers":[
        {
            "category":"Coffee & Tea",
            "type":"Food & Drink"
        }
    ],
    "sg:menulink":"http://www.allmenus.com/wa/tacoma/117866-starbucks-coffee/menu/",
    "sg:phone":"+1 253 984 0981",
    "sg:postcode":"98499",
    "sg:province":"WA",
    "sg:tags":[
        "american"
    ],
    "wof:name":"Starbucks Coffee",
    "wof:placetype":"venue"
},
  "geometry": {"coordinates":[-122.511436,47.16665],"type":"Point"}
}