{
  "type": "Feature",
  "properties": {
    "addr:full":"4617 183rd Pl SW Lynnwood WA 98037",
    "addr:housenumber":"4617",
    "addr:postcode":"98037",
    "addr:street":"183Rd Pl Sw",
    "iso:country":"US",
    "sg:address":"4617 183rd Pl SW",
    "sg:city":"Lynnwood",
    "sg:classifiers":[
        {
            "category":"Building & Trades",
            "subcategory":"Construction",
            "type":"Services"
        }
    ],
    "sg:phone":"+1 425 776 2459",
    "sg:postcode":"98037",
    "sg:province":"WA",
    "sg:tags":[
        "contractor"
    ],
    "wof:name":"Raindrop Roofing LLC",
    "wof:placetype":"venue"
},
  "geometry": {"coordinates":[-122.29671399999999,47.832411],"type":"Point"}
}