{
  "type": "Feature",
  "properties": {
    "addr:full":"219 W Bender Rd Ellensburg WA 98926",
    "addr:housenumber":"219",
    "addr:postcode":"98926",
    "addr:street":"W Bender Rd",
    "iso:country":"US",
    "sg:address":"219 W Bender Rd",
    "sg:city":"Ellensburg",
    "sg:classifiers":[
        {
            "category":"Professional",
            "subcategory":"Management & Consulting",
            "type":"Services"
        }
    ],
    "sg:phone":"+1 509 925 4569",
    "sg:postcode":"98926",
    "sg:province":"WA",
    "sg:tags":[
        "business"
    ],
    "wof:name":"A Black Consulting",
    "wof:placetype":"venue"
},
  "geometry": {"coordinates":[-120.555539,47.021269],"type":"Point"}
}