{
  "type": "Feature",
  "properties": {
    "iso:country":"US",
    "sg:address":"115 S Pines Rd",
    "sg:city":"Spokane Valley",
    "sg:classifiers":[
        {
            "category":"Food & Beverages",
            "subcategory":"Groceries & Convenience Stores",
            "type":"Retail Goods"
        }
    ],
    "sg:phone":"+1 509 891 2525",
    "sg:postcode":"99206",
    "sg:province":"WA",
    "wof:name":"Pines Qwik Stop",
    "wof:placetype":"venue"
},
  "geometry": {"coordinates":[-117.239728,47.655283],"type":"Point"}
}