{
  "type": "Feature",
  "properties": {
    "addr:full":"2424 S 260th St Kent WA 98032",
    "addr:housenumber":"2424",
    "addr:postcode":"98032",
    "addr:street":"S 260Th St",
    "iso:country":"US",
    "sg:address":"2424 S 260th St",
    "sg:city":"Kent",
    "sg:classifiers":[
        {
            "category":"Retail",
            "subcategory":"Repair Shop",
            "type":"Services"
        }
    ],
    "sg:phone":"+1 253 839 4113",
    "sg:postcode":"98032",
    "sg:province":"WA",
    "wof:name":"Gonzalez Cleaning",
    "wof:placetype":"venue"
},
  "geometry": {"coordinates":[-122.30375600000001,47.368702],"type":"Point"}
}