{
  "type": "Feature",
  "properties": {
    "addr:full":"412 164th Pl SE Bothell WA 98012",
    "addr:housenumber":"412",
    "addr:postcode":"98012",
    "addr:street":"164Th Pl Se",
    "iso:country":"US",
    "sg:address":"412 164th Pl SE",
    "sg:city":"Bothell",
    "sg:classifiers":[
        {
            "category":"Professional",
            "type":"Services"
        }
    ],
    "sg:phone":"+1 425 232 8937",
    "sg:postcode":"98012",
    "sg:province":"WA",
    "wof:name":"Big Purple Undies",
    "wof:placetype":"venue"
},
  "geometry": {"coordinates":[-122.22579399999999,47.848681],"type":"Point"}
}