{
  "type": "Feature",
  "properties": {
    "addr:full":"195 NW Madrona Way Coupeville WA 98239",
    "addr:housenumber":"195",
    "addr:postcode":"98239",
    "addr:street":"Nw Madrona Way",
    "iso:country":"US",
    "sg:address":"195 NW Madrona Way",
    "sg:city":"Coupeville",
    "sg:classifiers":[
        {
            "category":"Manufacturing",
            "subcategory":"Tools & Machinery",
            "type":"Manufacturing & Wholesale Goods"
        }
    ],
    "sg:phone":"+1 360 678 3685",
    "sg:postcode":"98239",
    "sg:province":"WA",
    "sg:tags":[
        "industry",
        "mfg"
    ],
    "wof:name":"Aqua Pacific",
    "wof:placetype":"venue"
},
  "geometry": {"coordinates":[-122.691108,48.220135],"type":"Point"}
}