{
  "type": "Feature",
  "properties": {
    "iso:country":"US",
    "sg:address":"1826 111th Dr NE",
    "sg:city":"Lake Stevens",
    "sg:classifiers":[
        {
            "category":"Building & Trades",
            "subcategory":"Construction",
            "type":"Services"
        }
    ],
    "sg:phone":"+1 425 377 1659",
    "sg:postcode":"98258",
    "sg:province":"WA",
    "sg:tags":[
        "contractor"
    ],
    "wof:name":"Concierge Contractors",
    "wof:placetype":"venue"
},
  "geometry": {"coordinates":[-122.08135,48.014033],"type":"Point"}
}