{
  "type": "Feature",
  "properties": {
    "iso:country":"US",
    "sg:address":"11525 8th Ave NE",
    "sg:city":"Seattle",
    "sg:classifiers":[
        {
            "category":"Building & Trades",
            "subcategory":"Construction",
            "type":"Services"
        }
    ],
    "sg:phone":"+1 206 367 1114",
    "sg:postcode":"98125",
    "sg:province":"WA",
    "sg:tags":[
        "house"
    ],
    "wof:name":"Wes Pierce Construction",
    "wof:placetype":"venue"
},
  "geometry": {"coordinates":[-122.32077099999999,47.713805],"type":"Point"}
}