{
  "type": "Feature",
  "properties": {
    "addr:full":"510 Bellevue Way NE Bellevue WA 98004",
    "addr:housenumber":"510",
    "addr:postcode":"98004",
    "addr:street":"Bellevue Way Ne",
    "iso:country":"US",
    "sg:address":"510 Bellevue Way NE",
    "sg:city":"Bellevue",
    "sg:classifiers":[
        {
            "category":"Museum",
            "type":"Entertainment"
        }
    ],
    "sg:phone":"+1 425 519 0770",
    "sg:postcode":"98004",
    "sg:province":"WA",
    "sg:website":"www.bellevuearts.org",
    "wof:name":"Bellevue Arts Museum",
    "wof:placetype":"venue"
},
  "geometry": {"coordinates":[-122.201314,47.615277],"type":"Point"}
}