{
  "type": "Feature",
  "properties": {
    "addr:city":"Bellevue",
    "addr:full":"510 Bellevue Way Ne Bellevue, Wa 98004-5014",
    "addr:house_number":"510",
    "addr:housenumber":"510",
    "addr:phone":"+1 425-519-0770",
    "addr:postcode":"98004-5014",
    "addr:road":"Bellevue Way Ne",
    "addr:state":"WA",
    "addr:street":"Bellevue Way Ne",
    "iso:country":"US",
    "sg:address":"510 Bellevue Way NE",
    "sg:city":"Bellevue",
    "sg:classifiers":[
        {
            "category":"Museum",
            "type":"Entertainment"
        }
    ],
    "sg:phone":"+1 425 519 0770",
    "sg:postcode":"98004",
    "sg:province":"WA",
    "sg:website":"www.bellevuearts.org",
    "wof:airports":[
        102528147,
        102527671,
        102533269
    ],
    "wof:name":"Bellevue Art Museum",
    "wof:placetype":"venue"
},
  "geometry": {"coordinates":[-122.20156,47.6148],"type":"Point"}
}