{
  "type": "Feature",
  "properties": {
    "addr:full":"2379 Malaga Dr NE Moses Lake WA 98837",
    "addr:housenumber":"2379",
    "addr:postcode":"98837",
    "addr:street":"Malaga Dr Ne",
    "iso:country":"US",
    "sg:address":"2379 Malaga Dr NE",
    "sg:city":"Moses Lake",
    "sg:classifiers":[
        {
            "category":"Building & Trades",
            "subcategory":"Construction",
            "type":"Services"
        }
    ],
    "sg:phone":"+1 509 764 8234",
    "sg:postcode":"98837",
    "sg:province":"WA",
    "sg:tags":[
        "excavation",
        "contractor"
    ],
    "wof:name":"TM Excavation",
    "wof:placetype":"venue"
},
  "geometry": {"coordinates":[-119.352676,47.121962],"type":"Point"}
}