{
  "type": "Feature",
  "properties": {
    "addr:full":"1101 Riverside Dr Mount Vernon WA 98273",
    "addr:housenumber":"1101",
    "addr:postcode":"98273",
    "addr:street":"Riverside Dr",
    "iso:country":"US",
    "sg:address":"1101 Riverside Dr",
    "sg:city":"Mount Vernon",
    "sg:classifiers":[
        {
            "category":"Autos & Motor Vehicles",
            "subcategory":"Auto Supplies",
            "type":"Retail Goods"
        }
    ],
    "sg:phone":"+1 360 293 0589",
    "sg:postcode":"98273",
    "sg:province":"WA",
    "sg:tags":[
        "tire"
    ],
    "wof:name":"A Riteway Trailers Hitches of Mount Vernon",
    "wof:placetype":"venue"
},
  "geometry": {"coordinates":[-122.334999,48.430599],"type":"Point"}
}