{
  "type": "Feature",
  "properties": {
    "addr:full":"1243 Jewel Ln Walla Walla WA 99362",
    "addr:housenumber":"1243",
    "addr:postcode":"99362",
    "addr:street":"Jewel Ln",
    "iso:country":"US",
    "sg:address":"1243 Jewel Ln",
    "sg:city":"Walla Walla",
    "sg:classifiers":[
        {
            "category":"Building & Trades",
            "subcategory":"Construction",
            "type":"Services"
        }
    ],
    "sg:phone":"+1 509 529 7408",
    "sg:postcode":"99362",
    "sg:province":"WA",
    "sg:tags":[
        "residential"
    ],
    "wof:name":"Needham Construction",
    "wof:placetype":"venue"
},
  "geometry": {"coordinates":[-118.308099,46.051692],"type":"Point"}
}