{
  "type": "Feature",
  "properties": {
    "addr:full":"107 S Howard St Ste 205 Spokane WA 99201",
    "addr:housenumber":"107",
    "addr:postcode":"99201",
    "addr:street":"S Howard St Ste 205",
    "iso:country":"US",
    "sg:address":"107 S Howard St Ste 205",
    "sg:city":"Spokane",
    "sg:classifiers":[
        {
            "category":"Professional",
            "subcategory":"Accounting & Tax Preparation",
            "type":"Services"
        },
        {
            "category":"Professional",
            "subcategory":"Business Services",
            "type":"Services"
        }
    ],
    "sg:phone":"+1 509 624 1268",
    "sg:postcode":"99201",
    "sg:province":"WA",
    "sg:tags":[
        "consultant",
        "coach",
        "public",
        "accountants-certified"
    ],
    "sg:website":"http://www.batty-erlandsen.com",
    "wof:name":"Batty Erlandsen And Associates",
    "wof:placetype":"venue"
},
  "geometry": {"coordinates":[-117.421076,47.656083],"type":"Point"}
}