{
  "type": "Feature",
  "properties": {
    "addr:full":"915 6th St Clarkston WA 99403",
    "addr:housenumber":"915",
    "addr:postcode":"99403",
    "addr:street":"6Th St",
    "iso:country":"US",
    "sg:address":"915 6th St",
    "sg:city":"Clarkston",
    "sg:classifiers":[
        {
            "category":"Organizations",
            "subcategory":"Community Association",
            "type":"Services"
        }
    ],
    "sg:phone":"+1 509 758 7575",
    "sg:postcode":"99403",
    "sg:province":"WA",
    "wof:name":"Boy Scouts of America",
    "wof:placetype":"venue"
},
  "geometry": {"coordinates":[-117.045483,46.412431],"type":"Point"}
}