{
  "type": "Feature",
  "properties": {
    "addr:full":"4517 California Ave SW Seattle WA 98116",
    "addr:housenumber":"4517",
    "addr:postcode":"98116",
    "addr:street":"California Ave Sw",
    "iso:country":"US",
    "sg:address":"4517 California Ave SW",
    "sg:city":"Seattle",
    "sg:classifiers":[
        {
            "category":"Shopping",
            "subcategory":"Beauty & Cosmetics",
            "type":"Retail Goods"
        }
    ],
    "sg:phone":"+1 206 937 9224",
    "sg:postcode":"98116",
    "sg:province":"WA",
    "sg:tags":[
        "supply"
    ],
    "sg:website":"www.jansbeautysupply.com/",
    "wof:name":"Jan's Beauty Supply & Salon, Inc.",
    "wof:placetype":"venue"
},
  "geometry": {"coordinates":[-122.387001,47.562698],"type":"Point"}
}