{
  "type": "Feature",
  "properties": {
    "addr:full":"1140 79th Ave SE Olympia WA 98501",
    "addr:housenumber":"1140",
    "addr:postcode":"98501",
    "addr:street":"79Th Ave Se",
    "iso:country":"US",
    "sg:address":"1140 79th Ave SE",
    "sg:city":"Olympia",
    "sg:classifiers":[
        {
            "category":"Building & Trades",
            "subcategory":"Electrical",
            "type":"Services"
        },
        {
            "category":"Professional",
            "subcategory":"Computer Services",
            "type":"Services"
        }
    ],
    "sg:phone":"+1 360 786 6704",
    "sg:postcode":"98501",
    "sg:province":"WA",
    "sg:tags":[
        "wire",
        "installation",
        "cable",
        "optic",
        "communication",
        "wiring"
    ],
    "wof:name":"Netversant Solutions Northwest",
    "wof:placetype":"venue"
},
  "geometry": {"coordinates":[-122.883212,46.97212],"type":"Point"}
}