{
  "type": "Feature",
  "properties": {
    "addr:full":"21231 66th Ave W Lynnwood WA 98036",
    "addr:housenumber":"21231",
    "addr:postcode":"98036",
    "addr:street":"66Th Ave W",
    "iso:country":"US",
    "sg:address":"21231 66th Ave W",
    "sg:city":"Lynnwood",
    "sg:classifiers":[
        {
            "category":"Freight",
            "type":"Transportation"
        }
    ],
    "sg:phone":"+1 425 776 6555",
    "sg:postcode":"98036",
    "sg:province":"WA",
    "sg:tags":[
        "special"
    ],
    "wof:name":"File Box",
    "wof:placetype":"venue"
},
  "geometry": {"coordinates":[-122.321842,47.805196],"type":"Point"}
}