{
  "type": "Feature",
  "properties": {
    "iso:country":"US",
    "sg:address":"12313 35th Ave NE",
    "sg:city":"Seattle",
    "sg:classifiers":[
        {
            "category":"Government",
            "subcategory":"Office",
            "type":"Public Place"
        }
    ],
    "sg:phone":"+1 206 364 3214",
    "sg:postcode":"98125",
    "sg:province":"WA",
    "sg:tags":[
        "consulting",
        "management"
    ],
    "wof:name":"Sirealistic",
    "wof:placetype":"venue"
},
  "geometry": {"coordinates":[-122.29088,47.719147],"type":"Point"}
}