{
  "type": "Feature",
  "properties": {
    "addr:full":"375 E Main St Othello WA 99344",
    "addr:housenumber":"375",
    "addr:postcode":"99344",
    "addr:street":"E Main St",
    "iso:country":"US",
    "sg:address":"375 E Main St",
    "sg:city":"Othello",
    "sg:classifiers":[
        {
            "category":"Real Estate",
            "subcategory":"Real Estate Agent",
            "type":"Services"
        }
    ],
    "sg:phone":"+1 509 488 7737",
    "sg:postcode":"99344",
    "sg:province":"WA",
    "sg:website":"http://www.firstchoicerealty.net",
    "wof:name":"First Choice Realty Of Washington Llc",
    "wof:placetype":"venue"
},
  "geometry": {"coordinates":[-119.16996399999999,46.826172],"type":"Point"}
}