{
  "type": "Feature",
  "properties": {
    "addr:full":"9453 12th Ave SW Seattle WA 98106",
    "addr:housenumber":"9453",
    "addr:postcode":"98106",
    "addr:street":"12Th Ave Sw",
    "iso:country":"US",
    "sg:address":"9453 12th Ave SW",
    "sg:city":"Seattle",
    "sg:classifiers":[
        {
            "category":"Home & Garden",
            "subcategory":"Carpets & Floor Coverings",
            "type":"Retail Goods"
        }
    ],
    "sg:phone":"+1 206 528 8011",
    "sg:postcode":"98106",
    "sg:province":"WA",
    "wof:name":"Tc Floor Covering",
    "wof:placetype":"venue"
},
  "geometry": {"coordinates":[-122.350728,47.517814],"type":"Point"}
}