{
  "type": "Feature",
  "properties": {
    "addr:full":"10029 S Tacoma Way Ste H7 Lakewood WA 98499",
    "addr:housenumber":"10029",
    "addr:postcode":"98499",
    "addr:street":"S Tacoma Way Ste H7",
    "iso:country":"US",
    "sg:address":"10029 S Tacoma Way Ste H7",
    "sg:city":"Lakewood",
    "sg:classifiers":[
        {
            "category":"Government",
            "subcategory":"Fire Station",
            "type":"Public Place"
        },
        {
            "category":"Professional",
            "subcategory":"Detective & Security Services",
            "type":"Services"
        }
    ],
    "sg:phone":"+1 888 300 4809",
    "sg:postcode":"98499",
    "sg:province":"WA",
    "sg:tags":[
        "control",
        "television",
        "monitoring",
        "supply",
        "consultant",
        "alarm",
        "system",
        "equipment",
        "protection",
        "systems-closed",
        "circuit",
        "telecasting"
    ],
    "sg:website":"http://www.adtfastresponse.com/fastresponse/offer.aspx?ecid=bgtyp100302",
    "wof:name":"ADT Security Services",
    "wof:placetype":"venue"
},
  "geometry": {"coordinates":[-122.483644,47.165444],"type":"Point"}
}