{
  "type": "Feature",
  "properties": {
    "addr:full":"12801 Standring Ln SW Seattle WA 98146",
    "addr:housenumber":"12801",
    "addr:postcode":"98146",
    "addr:street":"Standring Ln Sw",
    "iso:country":"US",
    "sg:address":"12801 Standring Ln SW",
    "sg:city":"Seattle",
    "sg:classifiers":[
        {
            "category":"Banks & Credit Unions",
            "subcategory":"Financial Services",
            "type":"Services"
        }
    ],
    "sg:phone":"+1 206 248 3605",
    "sg:postcode":"98146",
    "sg:province":"WA",
    "sg:tags":[
        "trust",
        "investment",
        "real estate"
    ],
    "wof:name":"Carl L Hossman Family Fou",
    "wof:placetype":"venue"
},
  "geometry": {"coordinates":[-122.36332299999999,47.487985],"type":"Point"}
}