{
  "type": "Feature",
  "properties": {
    "addr:full":"117 1st Ave SW Castle Rock WA 98611",
    "addr:housenumber":"117",
    "addr:postcode":"98611",
    "addr:street":"1St Ave Sw",
    "iso:country":"US",
    "sg:address":"117 1st Ave SW",
    "sg:city":"Castle Rock",
    "sg:classifiers":[
        {
            "category":"Shopping",
            "subcategory":"Pharmacy",
            "type":"Retail Goods"
        }
    ],
    "sg:phone":"+1 360 274 8211",
    "sg:postcode":"98611",
    "sg:province":"WA",
    "wof:name":"Castle Rock Pharmacy",
    "wof:placetype":"venue"
},
  "geometry": {"coordinates":[-122.909131,46.275214],"type":"Point"}
}