{
  "type": "Feature",
  "properties": {
    "addr:full":"505 32nd St Ste 107 Bellingham WA 98225",
    "addr:housenumber":"505",
    "addr:postcode":"98225",
    "addr:street":"32Nd St Ste 107",
    "iso:country":"US",
    "sg:address":"505 32nd St Ste 107",
    "sg:city":"Bellingham",
    "sg:classifiers":[
        {
            "category":"Government",
            "subcategory":"Fire Station",
            "type":"Public Place"
        },
        {
            "category":"Home & Garden",
            "subcategory":"Hardware",
            "type":"Retail Goods"
        }
    ],
    "sg:phone":"+1 360 676 2634",
    "sg:postcode":"98225",
    "sg:province":"WA",
    "sg:tags":[
        "extinguisher",
        "sprinklers-residential",
        "industrial",
        "commercial",
        "automatic"
    ],
    "sg:website":"http://www.washingtonfire-safety.com",
    "wof:name":"Washington Fire & Safety",
    "wof:placetype":"venue"
},
  "geometry": {"coordinates":[-122.475403,48.729561],"type":"Point"}
}