{
  "type": "Feature",
  "properties": {
    "addr:full":"3230B Beacon Ave S Seattle WA 98144",
    "addr:housenumber":"3230b",
    "addr:postcode":"98144",
    "addr:street":"Beacon Ave S",
    "iso:country":"US",
    "sg:address":"3230B Beacon Ave S",
    "sg:city":"Seattle",
    "sg:classifiers":[
        {
            "category":"Health Services",
            "subcategory":"Medical Lab",
            "type":"Services"
        }
    ],
    "sg:phone":"+1 206 568 0903",
    "sg:postcode":"98144",
    "sg:province":"WA",
    "sg:tags":[
        "laboratory",
        "dental"
    ],
    "wof:name":"Broadway Denture Clinic",
    "wof:placetype":"venue"
},
  "geometry": {"coordinates":[-122.309119,47.574762],"type":"Point"}
}