{
  "type": "Feature",
  "properties": {
    "addr:full":"123 Crystal Ridge Dr Chehalis WA 98532",
    "addr:housenumber":"123",
    "addr:postcode":"98532",
    "addr:street":"Crystal Ridge Dr",
    "iso:country":"US",
    "sg:address":"123 Crystal Ridge Dr",
    "sg:city":"Chehalis",
    "sg:classifiers":[
        {
            "category":"Retail",
            "subcategory":"Repair Shop",
            "type":"Services"
        }
    ],
    "sg:phone":"+1 360 748 1656",
    "sg:postcode":"98532",
    "sg:province":"WA",
    "sg:tags":[
        "electrical"
    ],
    "wof:name":"Faunus Enterprise",
    "wof:placetype":"venue"
},
  "geometry": {"coordinates":[-122.865013,46.613983],"type":"Point"}
}