{
  "type": "Feature",
  "properties": {
    "addr:full":"1008 S 3rd St Mt Vernon WA 98273",
    "addr:housenumber":"1008",
    "addr:postcode":"98273",
    "addr:street":"S 3Rd St",
    "iso:country":"US",
    "sg:address":"1008 S 3rd St",
    "sg:city":"Mt Vernon",
    "sg:classifiers":[
        {
            "category":"Social Services",
            "type":"Services"
        }
    ],
    "sg:phone":"+1 360 336 2135",
    "sg:postcode":"98273",
    "sg:province":"WA",
    "sg:tags":[
        "organization",
        "welfare"
    ],
    "wof:name":"Friendship House",
    "wof:placetype":"venue"
},
  "geometry": {"coordinates":[-122.336578,48.415633],"type":"Point"}
}