{
  "type": "Feature",
  "properties": {
    "addr:full":"1205 Dupont St Bellingham WA 98225",
    "addr:housenumber":"1205",
    "addr:postcode":"98225",
    "addr:street":"Dupont St",
    "iso:country":"US",
    "sg:address":"1205 Dupont St",
    "sg:city":"Bellingham",
    "sg:classifiers":[
        {
            "category":"Professional",
            "subcategory":"Accounting & Tax Preparation",
            "type":"Services"
        }
    ],
    "sg:phone":"+1 360 756 0335",
    "sg:postcode":"98225",
    "sg:province":"WA",
    "sg:tags":[
        "bookkeeping",
        "general"
    ],
    "wof:name":"Jeanne M Funsch Management",
    "wof:placetype":"venue"
},
  "geometry": {"coordinates":[-122.48687099999999,48.758669],"type":"Point"}
}