{
  "type": "Feature",
  "properties": {
    "iso:country":"US",
    "sg:address":"9920 271st St NW",
    "sg:city":"Stanwood",
    "sg:classifiers":[
        {
            "category":"Professional",
            "subcategory":"Engineering",
            "type":"Services"
        }
    ],
    "sg:phone":"+1 360 629 6710",
    "sg:postcode":"98292",
    "sg:province":"WA",
    "sg:tags":[
        "engineer"
    ],
    "wof:name":"Perco Engineering PC",
    "wof:placetype":"venue"
},
  "geometry": {"coordinates":[-122.36726400000001,48.24237],"type":"Point"}
}