{
  "type": "Feature",
  "properties": {
    "addr:full":"1930 6th St Bremerton WA 98337",
    "addr:housenumber":"1930",
    "addr:postcode":"98337",
    "addr:street":"6Th St",
    "iso:country":"US",
    "sg:address":"1930 6th St",
    "sg:city":"Bremerton",
    "sg:classifiers":[
        {
            "category":"Ice Cream",
            "type":"Food & Drink"
        },
        {
            "category":"Food & Beverages",
            "subcategory":"Dairy",
            "type":"Retail Goods"
        }
    ],
    "sg:menulink":"http://www.allmenus.com/wa/bremerton/242828-baskin-robbins/menu/",
    "sg:phone":"+1 360 373 8855",
    "sg:postcode":"98337",
    "sg:province":"WA",
    "sg:tags":[
        "american",
        "ice",
        "cream"
    ],
    "wof:name":"Baskin-Robbins",
    "wof:placetype":"venue"
},
  "geometry": {"coordinates":[-122.64456300000001,47.567388],"type":"Point"}
}