{
  "type": "Feature",
  "properties": {
    "addr:full":"710 NE California St Pullman WA 99163",
    "addr:housenumber":"710",
    "addr:postcode":"99163",
    "addr:street":"Ne California St",
    "iso:country":"US",
    "sg:address":"710 NE California St",
    "sg:city":"Pullman",
    "sg:classifiers":[
        {
            "category":"Organizations",
            "subcategory":"Community Association",
            "type":"Services"
        }
    ],
    "sg:phone":"+1 509 332 6396",
    "sg:postcode":"99163",
    "sg:province":"WA",
    "sg:tags":[
        "sorority",
        "fraternity"
    ],
    "wof:name":"Pi Kappa Alpha",
    "wof:placetype":"venue"
},
  "geometry": {"coordinates":[-117.16978400000001,46.73489],"type":"Point"}
}