{
  "type": "Feature",
  "properties": {
    "addr:full":"9201 NE Sea Ray Ct Bainbridge Island WA 98110",
    "addr:housenumber":"9201",
    "addr:postcode":"98110",
    "addr:street":"Ne Sea Ray Ct",
    "iso:country":"US",
    "sg:address":"9201 NE Sea Ray Ct",
    "sg:city":"Bainbridge Island",
    "sg:classifiers":[
        {
            "category":"Government",
            "subcategory":"Office",
            "type":"Public Place"
        }
    ],
    "sg:phone":"+1 206 301 2374",
    "sg:postcode":"98110",
    "sg:province":"WA",
    "sg:tags":[
        "national",
        "security"
    ],
    "wof:name":"US Army",
    "wof:placetype":"venue"
},
  "geometry": {"coordinates":[-122.53018299999999,47.63639],"type":"Point"}
}