{
  "type": "Feature",
  "properties": {
    "addr:full":"2326 Riverwalk Dr SE Auburn WA 98002",
    "addr:housenumber":"2326",
    "addr:postcode":"98002",
    "addr:street":"Riverwalk Dr Se",
    "iso:country":"US",
    "sg:address":"2326 Riverwalk Dr SE",
    "sg:city":"Auburn",
    "sg:classifiers":[
        {
            "category":"Social Services",
            "subcategory":"Child Care",
            "type":"Services"
        }
    ],
    "sg:phone":"+1 253 288 2044",
    "sg:postcode":"98002",
    "sg:province":"WA",
    "sg:tags":[
        "day"
    ],
    "wof:name":"Muckleshoot Child Dev Ctr",
    "wof:placetype":"venue"
},
  "geometry": {"coordinates":[-122.196614,47.289038],"type":"Point"}
}