{
  "type": "Feature",
  "properties": {
    "addr:full":"225 E Lovett St Aberdeen WA 98520",
    "addr:housenumber":"225",
    "addr:postcode":"98520",
    "addr:street":"E Lovett St",
    "iso:country":"US",
    "sg:address":"225 E Lovett St",
    "sg:city":"Aberdeen",
    "sg:classifiers":[
        {
            "category":"Professional",
            "type":"Services"
        }
    ],
    "sg:phone":"+1 360 533 5880",
    "sg:postcode":"98520",
    "sg:province":"WA",
    "wof:name":"Caffalls Characters",
    "wof:placetype":"venue"
},
  "geometry": {"coordinates":[-123.788956,46.961054],"type":"Point"}
}