{
  "type": "Feature",
  "properties": {
    "addr:full":"2021 E College Way Ste 210 Mount Vernon WA 98273",
    "addr:housenumber":"2021;210",
    "addr:postcode":"98273",
    "addr:street":"E College Way Ste",
    "iso:country":"US",
    "sg:address":"2021 E College Way Ste 210",
    "sg:city":"Mount Vernon",
    "sg:classifiers":[
        {
            "category":"Building & Trades",
            "subcategory":"Construction",
            "type":"Services"
        }
    ],
    "sg:phone":"+1 360 424 6848",
    "sg:postcode":"98273",
    "sg:province":"WA",
    "sg:tags":[
        "contractor"
    ],
    "sg:website":"www.axthelmconstruction.com",
    "wof:name":"Axthelm Construction Inc",
    "wof:placetype":"venue"
},
  "geometry": {"coordinates":[-122.31543600000001,48.43679],"type":"Point"}
}