{
  "type": "Feature",
  "properties": {
    "iso:country":"US",
    "sg:address":"13805 197th Ave SE",
    "sg:city":"Renton",
    "sg:classifiers":[
        {
            "category":"Building & Trades",
            "subcategory":"Construction",
            "type":"Services"
        }
    ],
    "sg:phone":"+1 425 227 8596",
    "sg:postcode":"98059",
    "sg:province":"WA",
    "sg:tags":[
        "carpentry",
        "contractor"
    ],
    "wof:name":"Creekside Cabinets",
    "wof:placetype":"venue"
},
  "geometry": {"coordinates":[-122.078484,47.480489],"type":"Point"}
}