{
  "type": "Feature",
  "properties": {
    "addr:full":"400 W Summa St Centralia WA 98531",
    "addr:housenumber":"400",
    "addr:postcode":"98531",
    "addr:street":"W Summa St",
    "iso:country":"US",
    "sg:address":"400 W Summa St",
    "sg:city":"Centralia",
    "sg:classifiers":[
        {
            "category":"Education",
            "subcategory":"School",
            "type":"Public Place"
        }
    ],
    "sg:phone":"+1 360 330 7636",
    "sg:postcode":"98531",
    "sg:province":"WA",
    "sg:website":"www.centralia.wednet.edu",
    "wof:name":"Jefferson-Lincoln Elementary",
    "wof:placetype":"venue"
},
  "geometry": {"coordinates":[-122.964512,46.706199],"type":"Point"}
}