{
  "type": "Feature",
  "properties": {
    "addr:full":"6021 195th Ave E Sumner WA 98391",
    "addr:housenumber":"6021",
    "addr:postcode":"98391",
    "addr:street":"195Th Ave E",
    "iso:country":"US",
    "sg:address":"6021 195th Ave E",
    "sg:city":"Sumner",
    "sg:classifiers":[
        {
            "category":"Building & Trades",
            "subcategory":"Construction",
            "type":"Services"
        }
    ],
    "sg:phone":"+1 253 863 5957",
    "sg:postcode":"98391",
    "sg:province":"WA",
    "sg:tags":[
        "contractor"
    ],
    "wof:name":"Lees Bros Plastering",
    "wof:placetype":"venue"
},
  "geometry": {"coordinates":[-122.166802,47.20124],"type":"Point"}
}