{
  "type": "Feature",
  "properties": {
    "addr:full":"10541 Sirocco Cir NW Silverdale WA 98383",
    "addr:housenumber":"10541",
    "addr:postcode":"98383",
    "addr:street":"Sirocco Cir Nw",
    "iso:country":"US",
    "sg:address":"10541 Sirocco Cir NW",
    "sg:city":"Silverdale",
    "sg:classifiers":[
        {
            "category":"Professional",
            "subcategory":"Business Services",
            "type":"Services"
        }
    ],
    "sg:phone":"+1 360 337 1685",
    "sg:postcode":"98383",
    "sg:province":"WA",
    "wof:name":"UPS Stores 215",
    "wof:placetype":"venue"
},
  "geometry": {"coordinates":[-122.71024199999999,47.660341],"type":"Point"}
}