{
  "type": "Feature",
  "properties": {
    "addr:full":"1515 W Joseph Ave Spokane WA 99205",
    "addr:housenumber":"1515",
    "addr:postcode":"99205",
    "addr:street":"W Joseph Ave",
    "iso:country":"US",
    "sg:address":"1515 W Joseph Ave",
    "sg:city":"Spokane",
    "sg:classifiers":[
        {
            "category":"Education",
            "subcategory":"School",
            "type":"Public Place"
        }
    ],
    "sg:phone":"+1 509 354 3984",
    "sg:postcode":"99205",
    "sg:province":"WA",
    "wof:name":"Spokane Public Schools District",
    "wof:placetype":"venue"
},
  "geometry": {"coordinates":[-117.433747,47.709888],"type":"Point"}
}