{
  "type": "Feature",
  "properties": {
    "addr:full":"1201 C St NW Auburn WA 98001",
    "addr:housenumber":"1201",
    "addr:postcode":"98001",
    "addr:street":"C St Nw",
    "iso:country":"US",
    "sg:address":"1201 C St NW",
    "sg:city":"Auburn",
    "sg:classifiers":[
        {
            "category":"Freight",
            "type":"Transportation"
        }
    ],
    "sg:phone":"+1 253 872 4200",
    "sg:postcode":"98001",
    "sg:province":"WA",
    "sg:tags":[
        "scheduled",
        "nonscheduled",
        "air"
    ],
    "wof:name":"Fritz Air Freight",
    "wof:placetype":"venue"
},
  "geometry": {"coordinates":[-122.23281,47.315897],"type":"Point"}
}