{
  "type": "Feature",
  "properties": {
    "addr:full":"640 Mullis St Friday Harbor WA 98250",
    "addr:housenumber":"640",
    "addr:postcode":"98250",
    "addr:street":"Mullis St Friday Harbor",
    "iso:country":"US",
    "sg:address":"640 Mullis St",
    "sg:city":"Friday Harbor",
    "sg:classifiers":[
        {
            "category":"Real Estate",
            "subcategory":"Surveying",
            "type":"Services"
        }
    ],
    "sg:phone":"+1 360 378 5072",
    "sg:postcode":"98250",
    "sg:province":"WA",
    "sg:tags":[
        "surveyor"
    ],
    "wof:name":"Thomas C Starr & Assoc Inc",
    "wof:placetype":"venue"
},
  "geometry": {"coordinates":[-123.02214499999999,48.531068],"type":"Point"}
}