{
  "type": "Feature",
  "properties": {
    "addr:full":"3861 Delridge Way SW Seattle WA 98106",
    "addr:housenumber":"3861",
    "addr:postcode":"98106",
    "addr:street":"Delridge Way Sw",
    "iso:country":"US",
    "sg:address":"3861 Delridge Way SW",
    "sg:city":"Seattle",
    "sg:classifiers":[
        {
            "category":"Deli",
            "type":"Food & Drink"
        },
        {
            "category":"Food & Beverages",
            "subcategory":"Groceries & Convenience Stores",
            "type":"Retail Goods"
        }
    ],
    "sg:phone":"+1 206 932 1137",
    "sg:postcode":"98106",
    "sg:province":"WA",
    "wof:name":"Delridge Deli Mart",
    "wof:placetype":"venue"
},
  "geometry": {"coordinates":[-122.362999,47.569099],"type":"Point"}
}