{
  "type": "Feature",
  "properties": {
    "addr:full":"6702 N Van Decar Rd SE Port Orchard WA 98367",
    "addr:housenumber":"6702",
    "addr:postcode":"98367",
    "addr:street":"N Van Decar Rd Se",
    "iso:country":"US",
    "sg:address":"6702 N Van Decar Rd SE",
    "sg:city":"Port Orchard",
    "sg:classifiers":[
        {
            "category":"Recreation",
            "subcategory":"Boat Charter",
            "type":"Entertainment"
        }
    ],
    "sg:phone":"+1 360 876 4452",
    "sg:postcode":"98367",
    "sg:province":"WA",
    "sg:tags":[
        "boating"
    ],
    "sg:website":"www.mikesmarinerepair.com",
    "wof:name":"Mike's Marine Repair",
    "wof:placetype":"venue"
},
  "geometry": {"coordinates":[-122.620245,47.48671],"type":"Point"}
}