{
  "type": "Feature",
  "properties": {
    "addr:full":"1330 N Washington St Spokane WA 99205",
    "addr:housenumber":"1330",
    "addr:postcode":"99205",
    "addr:street":"N Washington St",
    "iso:country":"US",
    "sg:address":"1330 N Washington St",
    "sg:city":"Spokane",
    "sg:classifiers":[
        {
            "category":"Health Services",
            "subcategory":"Health Practitioner",
            "type":"Services"
        }
    ],
    "sg:phone":"+1 509 462 2440",
    "sg:postcode":"99205",
    "sg:province":"WA",
    "wof:name":"James E Bailey P LLC",
    "wof:placetype":"venue"
},
  "geometry": {"coordinates":[-117.417238,47.670246],"type":"Point"}
}