{
  "type": "Feature",
  "properties": {
    "addr:full":"5088 NW Taylor Rd Bremerton WA 98312",
    "addr:housenumber":"5088",
    "addr:postcode":"98312",
    "addr:street":"Nw Taylor Rd",
    "iso:country":"US",
    "sg:address":"5088 NW Taylor Rd",
    "sg:city":"Bremerton",
    "sg:classifiers":[
        {
            "category":"Education",
            "subcategory":"School",
            "type":"Public Place"
        }
    ],
    "sg:phone":"+1 360 377 4542",
    "sg:postcode":"98312",
    "sg:province":"WA",
    "wof:name":"Kipsap Adventist School",
    "wof:placetype":"venue"
},
  "geometry": {"coordinates":[-122.717401,47.586451],"type":"Point"}
}