{
  "type": "Feature",
  "properties": {
    "addr:full":"26233 Pioneer Way NW Poulsbo WA 98370",
    "addr:housenumber":"26233",
    "addr:postcode":"98370",
    "addr:street":"Pioneer Way Nw",
    "iso:country":"US",
    "sg:address":"26233 Pioneer Way NW",
    "sg:city":"Poulsbo",
    "sg:classifiers":[
        {
            "category":"Home & Garden",
            "subcategory":"Household Appliances",
            "type":"Retail Goods"
        }
    ],
    "sg:phone":"+1 360 697 5595",
    "sg:postcode":"98370",
    "sg:province":"WA",
    "wof:name":"Nilsen's Appliance Ctr",
    "wof:placetype":"venue"
},
  "geometry": {"coordinates":[-122.654713,47.801963],"type":"Point"}
}