{
  "type": "Feature",
  "properties": {
    "addr:full":"2706 S St SE Auburn WA 98002",
    "addr:housenumber":"2706",
    "addr:postcode":"98002",
    "addr:street":"S St Se",
    "iso:country":"US",
    "sg:address":"2706 S St SE",
    "sg:city":"Auburn",
    "sg:classifiers":[
        {
            "category":"Building & Trades",
            "subcategory":"Cleaning & Sanitation",
            "type":"Services"
        }
    ],
    "sg:phone":"+1 253 939 2612",
    "sg:postcode":"98002",
    "sg:province":"WA",
    "sg:tags":[
        "maintenance"
    ],
    "wof:name":"J&K Cleaning",
    "wof:placetype":"venue"
},
  "geometry": {"coordinates":[-122.207013,47.28418],"type":"Point"}
}