{
  "type": "Feature",
  "properties": {
    "addr:full":"9792 Edmonds Way 229 Edmonds WA 98020",
    "addr:housenumber":"9792;229",
    "addr:postcode":"98020",
    "addr:street":"Edmonds Way",
    "iso:country":"US",
    "sg:address":"9792 Edmonds Way 229",
    "sg:city":"Edmonds",
    "sg:classifiers":[
        {
            "category":"Organizations",
            "subcategory":"Non-profit Organization",
            "type":"Services"
        }
    ],
    "sg:phone":"+1 425 712 1804",
    "sg:postcode":"98020",
    "sg:province":"WA",
    "sg:tags":[
        "charity",
        "foundations-educational",
        "philanthropic",
        "research"
    ],
    "sg:website":"http://www.mshelp.org",
    "wof:name":"Mshh",
    "wof:placetype":"venue"
},
  "geometry": {"coordinates":[-122.364422,47.790535],"type":"Point"}
}