{
  "type": "Feature",
  "properties": {
    "addr:full":"129 N Ely St Kennewick WA 99336",
    "addr:housenumber":"129",
    "addr:postcode":"99336",
    "addr:street":"N Ely St",
    "iso:country":"US",
    "sg:address":"129 N Ely St",
    "sg:city":"Kennewick",
    "sg:classifiers":[
        {
            "category":"Shopping",
            "subcategory":"Bicycles & Sporting Goods",
            "type":"Retail Goods"
        }
    ],
    "sg:phone":"+1 509 734 8989",
    "sg:postcode":"99336",
    "sg:province":"WA",
    "sg:website":"www.rei.com",
    "wof:name":"REI-Recreational Equipment Inc",
    "wof:placetype":"venue"
},
  "geometry": {"coordinates":[-119.158897,46.21031],"type":"Point"}
}