{
  "type": "Feature",
  "properties": {
    "iso:country":"US",
    "sg:address":"208 S 60th Ave",
    "sg:city":"Yakima",
    "sg:classifiers":[
        {
            "category":"Building & Trades",
            "subcategory":"Cleaning & Sanitation",
            "type":"Services"
        }
    ],
    "sg:phone":"+1 509 966 4690",
    "sg:postcode":"98908",
    "sg:province":"WA",
    "sg:tags":[
        "maintenance"
    ],
    "wof:name":"Ivans Building Maintenance",
    "wof:placetype":"venue"
},
  "geometry": {"coordinates":[-120.588556,46.594674],"type":"Point"}
}