{
  "type": "Feature",
  "properties": {
    "addr:full":"5807 W Umatilla Ave Kennewick WA 99336",
    "addr:housenumber":"5807",
    "addr:postcode":"99336",
    "addr:street":"W Umatilla Ave",
    "iso:country":"US",
    "sg:address":"5807 W Umatilla Ave",
    "sg:city":"Kennewick",
    "sg:classifiers":[
        {
            "category":"Place Of Worship",
            "subcategory":"Church",
            "type":"Public Place"
        },
        {
            "category":"Place Of Worship",
            "type":"Public Place"
        },
        {
            "category":"Organizations",
            "subcategory":"Religious Organization",
            "type":"Services"
        }
    ],
    "sg:phone":"+1 509 783 3768",
    "sg:postcode":"99336",
    "sg:province":"WA",
    "sg:tags":[
        "churches-interdenominational",
        "churches-various",
        "denomination"
    ],
    "wof:name":"Community Bible Church",
    "wof:placetype":"venue"
},
  "geometry": {"coordinates":[-119.19894600000001,46.226905],"type":"Point"}
}