{
  "type": "Feature",
  "properties": {
    "iso:country":"US",
    "sg:address":"6119 Brooklyn Ave NE",
    "sg:city":"Seattle",
    "sg:classifiers":[
        {
            "category":"Manufacturing",
            "subcategory":"Motor Vehicles & Parts",
            "type":"Manufacturing & Wholesale Goods"
        }
    ],
    "sg:phone":"+1 206 527 5259",
    "sg:postcode":"98115",
    "sg:province":"WA",
    "sg:tags":[
        "fabricator",
        "bicycle",
        "mfg"
    ],
    "sg:website":"www.ecycletours.com",
    "wof:name":"Erickson Bicycle Tours",
    "wof:placetype":"venue"
},
  "geometry": {"coordinates":[-122.31438900000001,47.673108],"type":"Point"}
}