{
  "type": "Feature",
  "properties": {
    "addr:full":"913 Capitol Way S Olympia WA 98501",
    "addr:housenumber":"913",
    "addr:postcode":"98501",
    "addr:street":"Capitol Way S",
    "iso:country":"US",
    "sg:address":"913 Capitol Way S",
    "sg:city":"Olympia",
    "sg:classifiers":[
        {
            "category":"Professional",
            "type":"Services"
        }
    ],
    "sg:phone":"+1 360 786 6864",
    "sg:postcode":"98501",
    "sg:province":"WA",
    "wof:name":"Viva Las Latte",
    "wof:placetype":"venue"
},
  "geometry": {"coordinates":[-122.90097900000001,47.039917],"type":"Point"}
}