{
  "type": "Feature",
  "properties": {
    "addr:full":"312 Marshall St Davenport WA 99122",
    "addr:housenumber":"312",
    "addr:postcode":"99122",
    "addr:street":"Marshall St",
    "iso:country":"US",
    "sg:address":"312 Marshall St",
    "sg:city":"Davenport",
    "sg:classifiers":[
        {
            "category":"Home & Garden",
            "subcategory":"Building Materials",
            "type":"Retail Goods"
        }
    ],
    "sg:phone":"+1 509 725 3667",
    "sg:postcode":"99122",
    "sg:province":"WA",
    "sg:tags":[
        "door"
    ],
    "wof:name":"All-Star Garage Doors",
    "wof:placetype":"venue"
},
  "geometry": {"coordinates":[-118.144893,47.651695],"type":"Point"}
}