{
  "type": "Feature",
  "properties": {
    "addr:full":"200 36th St Bellingham WA 98225",
    "addr:housenumber":"200",
    "addr:postcode":"98225",
    "addr:street":"36Th St",
    "iso:country":"US",
    "sg:address":"200 36th St",
    "sg:city":"Bellingham",
    "sg:classifiers":[
        {
            "category":"Autos & Motor Vehicles",
            "subcategory":"Fuel & Gas Station",
            "type":"Retail Goods"
        }
    ],
    "sg:phone":"+1 360 671 1625",
    "sg:postcode":"98225",
    "sg:province":"WA",
    "sg:tags":[
        "station",
        "gasoline"
    ],
    "wof:name":"Unocal 76 Samish Way",
    "wof:placetype":"venue"
},
  "geometry": {"coordinates":[-122.469855,48.732659],"type":"Point"}
}