{
  "type": "Feature",
  "properties": {
    "addr:full":"33015 NE 43rd Pl Carnation WA 98014",
    "addr:housenumber":"33015",
    "addr:postcode":"98014",
    "addr:street":"Ne 43Rd Pl",
    "iso:country":"US",
    "sg:address":"33015 NE 43rd Pl",
    "sg:city":"Carnation",
    "sg:classifiers":[
        {
            "category":"Manufacturing",
            "subcategory":"Printing",
            "type":"Manufacturing & Wholesale Goods"
        }
    ],
    "sg:phone":"+1 425 333 5512",
    "sg:postcode":"98014",
    "sg:province":"WA",
    "sg:tags":[
        "publishes",
        "business",
        "periodical"
    ],
    "wof:name":"Mergent Inc",
    "wof:placetype":"venue"
},
  "geometry": {"coordinates":[-121.899697,47.646369],"type":"Point"}
}