{
  "type": "Feature",
  "properties": {
    "addr:full":"16050 Beaver Lake Rd Mount Vernon WA 98273",
    "addr:housenumber":"16050",
    "addr:postcode":"98273",
    "addr:street":"Beaver Lake Rd",
    "iso:country":"US",
    "sg:address":"16050 Beaver Lake Rd",
    "sg:city":"Mount Vernon",
    "sg:classifiers":[
        {
            "category":"Building & Trades",
            "subcategory":"Construction",
            "type":"Services"
        }
    ],
    "sg:phone":"+1 360 422 7716",
    "sg:postcode":"98273",
    "sg:province":"WA",
    "sg:tags":[
        "contractor"
    ],
    "wof:name":"E Z Masonry Inc",
    "wof:placetype":"venue"
},
  "geometry": {"coordinates":[-122.20857700000001,48.418557],"type":"Point"}
}