{
  "type": "Feature",
  "properties": {
    "addr:full":"561 Burnt Ridge Rd Onalaska WA 98570",
    "addr:housenumber":"561",
    "addr:postcode":"98570",
    "addr:street":"Burnt Ridge Rd",
    "iso:country":"US",
    "sg:address":"561 Burnt Ridge Rd",
    "sg:city":"Onalaska",
    "sg:classifiers":[
        {
            "category":"Manufacturing",
            "subcategory":"Lumber",
            "type":"Manufacturing & Wholesale Goods"
        }
    ],
    "sg:phone":"+1 360 985 0044",
    "sg:postcode":"98570",
    "sg:province":"WA",
    "sg:tags":[
        "company",
        "logging"
    ],
    "wof:name":"Pries Logging",
    "wof:placetype":"venue"
},
  "geometry": {"coordinates":[-122.630314,46.577467],"type":"Point"}
}