{
  "type": "Feature",
  "properties": {
    "addr:full":"4122 S Grove Rd Spokane WA 99224",
    "addr:housenumber":"4122",
    "addr:postcode":"99224",
    "addr:street":"S Grove Rd",
    "iso:country":"US",
    "sg:address":"4122 S Grove Rd",
    "sg:city":"Spokane",
    "sg:classifiers":[
        {
            "category":"Wholesale",
            "subcategory":"Wine & Distilled Alcoholic Beverages",
            "type":"Manufacturing & Wholesale Goods"
        }
    ],
    "sg:phone":"+1 509 535 6233",
    "sg:postcode":"99224",
    "sg:province":"WA",
    "wof:name":"Northwest Select Wine & Spirit",
    "wof:placetype":"venue"
},
  "geometry": {"coordinates":[-117.497803,47.616697],"type":"Point"}
}