{
  "type": "Feature",
  "properties": {
    "addr:full":"15100 SE 38th St Bellevue WA 98006",
    "addr:postcode":"15100;98006",
    "addr:street":"Se 38Th St",
    "iso:country":"US",
    "sg:address":"15100 SE 38th St",
    "sg:city":"Bellevue",
    "sg:classifiers":[
        {
            "category":"Professional",
            "subcategory":"Research",
            "type":"Services"
        }
    ],
    "sg:phone":"+1 425 453 6023",
    "sg:postcode":"98006",
    "sg:province":"WA",
    "sg:tags":[
        "market",
        "analysis"
    ],
    "wof:name":"Consumer Critique Mystery",
    "wof:placetype":"venue"
},
  "geometry": {"coordinates":[-122.13862899999999,47.576195],"type":"Point"}
}