{
  "type": "Feature",
  "properties": {
    "addr:full":"5506 W 1st Pl Kennewick WA 99336",
    "addr:housenumber":"5506",
    "addr:postcode":"99336",
    "addr:street":"W 1St Pl",
    "iso:country":"US",
    "sg:address":"5506 W 1st Pl",
    "sg:city":"Kennewick",
    "sg:classifiers":[
        {
            "category":"Real Estate",
            "subcategory":"Real Estate Agent",
            "type":"Services"
        }
    ],
    "sg:phone":"+1 509 948 6868",
    "sg:postcode":"99336",
    "sg:province":"WA",
    "wof:name":"Willie M Stewart",
    "wof:placetype":"venue"
},
  "geometry": {"coordinates":[-119.196326,46.209529],"type":"Point"}
}