{
  "type": "Feature",
  "properties": {
    "addr:full":"406 NE 82nd St Seattle WA 98115",
    "addr:housenumber":"406",
    "addr:postcode":"98115",
    "addr:street":"Ne 82Nd St",
    "iso:country":"US",
    "sg:address":"406 NE 82nd St",
    "sg:city":"Seattle",
    "sg:classifiers":[
        {
            "category":"Professional",
            "subcategory":"Management & Consulting",
            "type":"Services"
        }
    ],
    "sg:phone":"+1 206 985 0344",
    "sg:postcode":"98115",
    "sg:province":"WA",
    "wof:name":"Ladd Marketing Ltd",
    "wof:placetype":"venue"
},
  "geometry": {"coordinates":[-122.32302799999999,47.688306],"type":"Point"}
}