{
  "type": "Feature",
  "properties": {
    "addr:full":"203 Madison St Grandview WA 98930",
    "addr:housenumber":"203",
    "addr:postcode":"98930",
    "addr:street":"Madison St",
    "iso:country":"US",
    "sg:address":"203 Madison St",
    "sg:city":"Grandview",
    "sg:classifiers":[
        {
            "category":"Restaurant",
            "type":"Food & Drink"
        }
    ],
    "sg:phone":"+1 509 882 2374",
    "sg:postcode":"98930",
    "sg:province":"WA",
    "sg:tags":[
        "pizza"
    ],
    "wof:name":"Morries Pizza",
    "wof:placetype":"venue"
},
  "geometry": {"coordinates":[-119.900358,46.259342],"type":"Point"}
}