{
  "type": "Feature",
  "properties": {
    "addr:full":"2018 156th Ave NE Ste 304 Bellevue WA 98008",
    "addr:housenumber":"2018",
    "addr:postcode":"98008",
    "addr:street":"156Th Ave Ne Ste 304",
    "iso:country":"US",
    "sg:address":"2018 156th Ave NE Ste 304",
    "sg:city":"Bellevue",
    "sg:classifiers":[
        {
            "category":"Professional",
            "subcategory":"Advertising",
            "type":"Services"
        },
        {
            "category":"Professional",
            "subcategory":"Art Services",
            "type":"Services"
        },
        {
            "category":"Communications",
            "type":"Services"
        }
    ],
    "sg:phone":"+1 800 388 9244",
    "sg:postcode":"98008",
    "sg:province":"WA",
    "sg:tags":[
        "marketing",
        "graphic",
        "design",
        "web"
    ],
    "sg:website":"www.tigervinci.com",
    "wof:name":"Tigervinci",
    "wof:placetype":"venue"
},
  "geometry": {"coordinates":[-122.130037,47.628749],"type":"Point"}
}