{
  "type": "Feature",
  "properties": {
    "addr:full":"815 6th St W Kirkland WA 98033",
    "addr:housenumber":"815",
    "addr:postcode":"98033",
    "addr:street":"6Th St W",
    "iso:country":"US",
    "sg:address":"815 6th St W",
    "sg:city":"Kirkland",
    "sg:classifiers":[
        {
            "category":"Professional",
            "subcategory":"Computer Services",
            "type":"Services"
        }
    ],
    "sg:phone":"+1 425 827 7200",
    "sg:postcode":"98033",
    "sg:province":"WA",
    "sg:tags":[
        "prepackaged",
        "software",
        "custom"
    ],
    "wof:name":"Microquill Software Publishing",
    "wof:placetype":"venue"
},
  "geometry": {"coordinates":[-122.215309,47.686373],"type":"Point"}
}