{
  "type": "Feature",
  "properties": {
    "addr:full":"3609 S Hanford St Seattle WA 98144",
    "addr:housenumber":"3609",
    "addr:postcode":"98144",
    "addr:street":"S Hanford St",
    "iso:country":"US",
    "sg:address":"3609 S Hanford St",
    "sg:city":"Seattle",
    "sg:classifiers":[
        {
            "category":"Building & Trades",
            "subcategory":"Construction",
            "type":"Services"
        }
    ],
    "sg:phone":"+1 206 725 4038",
    "sg:postcode":"98144",
    "sg:province":"WA",
    "sg:tags":[
        "work",
        "carpentry"
    ],
    "wof:name":"Cranston Construction",
    "wof:placetype":"venue"
},
  "geometry": {"coordinates":[-122.2868,47.57516],"type":"Point"}
}