{
  "type": "Feature",
  "properties": {
    "addr:full":"108 S 44th St Bellingham WA 98229",
    "addr:housenumber":"108",
    "addr:postcode":"98229",
    "addr:street":"S 44Th St",
    "iso:country":"US",
    "sg:address":"108 S 44th St",
    "sg:city":"Bellingham",
    "sg:classifiers":[
        {
            "category":"Professional",
            "type":"Services"
        }
    ],
    "sg:phone":"+1 360 715 2020",
    "sg:postcode":"98229",
    "sg:province":"WA",
    "wof:name":"Babies Before & After",
    "wof:placetype":"venue"
},
  "geometry": {"coordinates":[-122.458906,48.735269],"type":"Point"}
}