{
  "type": "Feature",
  "properties": {
    "addr:full":"17545 Aurora Ave N Shoreline WA 98133",
    "addr:housenumber":"17545",
    "addr:postcode":"98133",
    "addr:street":"Aurora Ave N",
    "iso:country":"US",
    "sg:address":"17545 Aurora Ave N",
    "sg:city":"Shoreline",
    "sg:classifiers":[
        {
            "category":"Retail",
            "subcategory":"Auto Rental",
            "type":"Services"
        }
    ],
    "sg:phone":"+1 206 533 9159",
    "sg:postcode":"98133",
    "sg:province":"WA",
    "sg:tags":[
        "renting",
        "automobile",
        "passenger",
        "car"
    ],
    "wof:name":"Enterprise Rent-A-Car",
    "wof:placetype":"venue"
},
  "geometry": {"coordinates":[-122.345956,47.756945],"type":"Point"}
}