{
  "type": "Feature",
  "properties": {
    "addr:full":"6107 Manor Pl Everett WA 98203",
    "addr:housenumber":"6107",
    "addr:postcode":"98203",
    "addr:street":"Manor Pl",
    "iso:country":"US",
    "sg:address":"6107 Manor Pl",
    "sg:city":"Everett",
    "sg:classifiers":[
        {
            "category":"Manufacturing",
            "subcategory":"Building Materials",
            "type":"Manufacturing & Wholesale Goods"
        }
    ],
    "sg:phone":"+1 425 267 0301",
    "sg:postcode":"98203",
    "sg:province":"WA",
    "sg:tags":[
        "materials-wholesale",
        "floor",
        "manufacturer"
    ],
    "wof:name":"Trfa Associate",
    "wof:placetype":"venue"
},
  "geometry": {"coordinates":[-122.20838500000001,47.943118],"type":"Point"}
}