{
  "type": "Feature",
  "properties": {
    "addr:full":"606 S 36th Ave Yakima WA 98902",
    "addr:housenumber":"606",
    "addr:postcode":"98902",
    "addr:street":"S 36Th Ave",
    "iso:country":"US",
    "sg:address":"606 S 36th Ave",
    "sg:city":"Yakima",
    "sg:classifiers":[
        {
            "category":"Restaurant",
            "type":"Food & Drink"
        },
        {
            "category":"Food & Beverages",
            "subcategory":"Ethnic Foods",
            "type":"Retail Goods"
        }
    ],
    "sg:phone":"+1 509 453 3663",
    "sg:postcode":"98902",
    "sg:province":"WA",
    "sg:tags":[
        "asian",
        "pan",
        "vietnamese"
    ],
    "wof:name":"J 'S Asian Flaming Grill II",
    "wof:placetype":"venue"
},
  "geometry": {"coordinates":[-120.556612,46.592621],"type":"Point"}
}