{
  "type": "Feature",
  "properties": {
    "addr:full":"12535 15th Avenue NE Seattle WA 98125",
    "addr:housenumber":"12535",
    "addr:postcode":"98125",
    "addr:street":"15Th Avenue Ne",
    "iso:country":"US",
    "sg:address":"12535 15th Avenue NE",
    "sg:city":"Seattle",
    "sg:classifiers":[
        {
            "category":"Building & Trades",
            "subcategory":"Cleaning & Sanitation",
            "type":"Services"
        }
    ],
    "sg:phone":"+1 206 784 8707",
    "sg:postcode":"98125",
    "sg:province":"WA",
    "sg:tags":[
        "carpet"
    ],
    "wof:name":"G & C Carpet & Upholstery",
    "wof:placetype":"venue"
},
  "geometry": {"coordinates":[-122.312646,47.7194],"type":"Point"}
}