{
  "type": "Feature",
  "properties": {
    "addr:full":"5184 School St Acme WA 98220",
    "addr:housenumber":"5184",
    "addr:postcode":"98220",
    "addr:street":"School St",
    "iso:country":"US",
    "sg:address":"5184 School St",
    "sg:city":"Acme",
    "sg:classifiers":[
        {
            "category":"Organizations",
            "subcategory":"Labor Organization",
            "type":"Services"
        }
    ],
    "sg:phone":"+1 360 595 2296",
    "sg:postcode":"98220",
    "sg:province":"WA",
    "sg:tags":[
        "business"
    ],
    "wof:name":"Wickersham Water Assoc",
    "wof:placetype":"venue"
},
  "geometry": {"coordinates":[-122.209963,48.654545],"type":"Point"}
}