{
  "type": "Feature",
  "properties": {
    "addr:full":"1211 SW 313th St Federal Way WA 98023",
    "addr:housenumber":"1211",
    "addr:postcode":"98023",
    "addr:street":"Sw 313Th St",
    "iso:country":"US",
    "sg:address":"1211 SW 313th St",
    "sg:city":"Federal Way",
    "sg:classifiers":[
        {
            "category":"Building & Trades",
            "subcategory":"Construction",
            "type":"Services"
        }
    ],
    "sg:phone":"+1 425 226 1919",
    "sg:postcode":"98023",
    "sg:province":"WA",
    "sg:tags":[
        "home",
        "contractor",
        "remodeling",
        "family",
        "roofing"
    ],
    "wof:name":"A M Construction",
    "wof:placetype":"venue"
},
  "geometry": {"coordinates":[-122.35302799999999,47.321734],"type":"Point"}
}