{
  "type": "Feature",
  "properties": {
    "addr:full":"4202 E Hillcrest Dr Yakima WA 98901",
    "addr:housenumber":"4202",
    "addr:postcode":"98901",
    "addr:street":"E Hillcrest Dr",
    "iso:country":"US",
    "sg:address":"4202 E Hillcrest Dr",
    "sg:city":"Yakima",
    "sg:classifiers":[
        {
            "category":"Professional",
            "subcategory":"Management & Consulting",
            "type":"Services"
        }
    ],
    "sg:phone":"+1 509 453 7018",
    "sg:postcode":"98901",
    "sg:province":"WA",
    "wof:name":"J R W & Assoc",
    "wof:placetype":"venue"
},
  "geometry": {"coordinates":[-120.444374,46.611011],"type":"Point"}
}