{
  "type": "Feature",
  "properties": {
    "iso:country":"US",
    "sg:address":"4140 Bakerview Spr",
    "sg:city":"Bellingham",
    "sg:classifiers":[
        {
            "category":"Wholesale",
            "subcategory":"Construction Materials",
            "type":"Manufacturing & Wholesale Goods"
        }
    ],
    "sg:phone":"+1 360 676 2880",
    "sg:postcode":"98226",
    "sg:province":"WA",
    "sg:tags":[
        "building"
    ],
    "wof:name":"Mutual Building Materials",
    "wof:placetype":"venue"
},
  "geometry": {"coordinates":[-122.447864,48.788382],"type":"Point"}
}