{
  "type": "Feature",
  "properties": {
    "addr:full":"734 S Market Blvd Chehalis WA 98532",
    "addr:housenumber":"734",
    "addr:postcode":"98532",
    "addr:street":"S Market Blvd",
    "iso:country":"US",
    "sg:address":"734 S Market Blvd",
    "sg:city":"Chehalis",
    "sg:classifiers":[
        {
            "category":"Personal",
            "subcategory":"Beauty Salon",
            "type":"Services"
        }
    ],
    "sg:phone":"+1 360 740 7807",
    "sg:postcode":"98532",
    "sg:province":"WA",
    "wof:name":"Simple Simon",
    "wof:placetype":"venue"
},
  "geometry": {"coordinates":[-122.95778,46.657137],"type":"Point"}
}