{
  "type": "Feature",
  "properties": {
    "addr:full":"10707 Des Moines Memorial Dr Seattle WA 98168",
    "addr:housenumber":"10707",
    "addr:postcode":"98168",
    "addr:street":"Des Moines Memorial Dr",
    "iso:country":"US",
    "sg:address":"10707 Des Moines Memorial Dr",
    "sg:city":"Seattle",
    "sg:classifiers":[
        {
            "category":"Banks & Credit Unions",
            "subcategory":"Bank",
            "type":"Services"
        }
    ],
    "sg:phone":"+1 206 444 9333",
    "sg:postcode":"98168",
    "sg:province":"WA",
    "sg:tags":[
        "loan",
        "broker"
    ],
    "wof:name":"Amerifund Financial Inc",
    "wof:placetype":"venue"
},
  "geometry": {"coordinates":[-122.304164,47.50673],"type":"Point"}
}