{
  "type": "Feature",
  "properties": {
    "addr:full":"3323 169th Pl NE Arlington WA 98223",
    "addr:housenumber":"3323",
    "addr:postcode":"98223",
    "addr:street":"169Th Pl Ne",
    "iso:country":"US",
    "sg:address":"3323 169th Pl NE",
    "sg:city":"Arlington",
    "sg:classifiers":[
        {
            "category":"Home & Garden",
            "subcategory":"Carpets & Floor Coverings",
            "type":"Retail Goods"
        }
    ],
    "sg:phone":"+1 360 651 9612",
    "sg:postcode":"98223",
    "sg:province":"WA",
    "wof:name":"Virtual Floor",
    "wof:placetype":"venue"
},
  "geometry": {"coordinates":[-122.185382,48.150079],"type":"Point"}
}