{
  "type": "Feature",
  "properties": {
    "addr:full":"18020 B St E Spanaway WA 98387",
    "addr:housenumber":"18020",
    "addr:postcode":"98387",
    "addr:street":"B St E",
    "iso:country":"US",
    "sg:address":"18020 B St E",
    "sg:city":"Spanaway",
    "sg:classifiers":[
        {
            "category":"Health Services",
            "subcategory":"Health Practitioner",
            "type":"Services"
        }
    ],
    "sg:phone":"+1 253 846 8234",
    "sg:postcode":"98387",
    "sg:province":"WA",
    "sg:tags":[
        "nutritionist"
    ],
    "wof:name":"Wic-Women/Infants/Children",
    "wof:placetype":"venue"
},
  "geometry": {"coordinates":[-122.428366,47.09324],"type":"Point"}
}