{
  "type": "Feature",
  "properties": {
    "addr:full":"1240 116th Ave NE Bellevue WA 98004",
    "addr:housenumber":"1240",
    "addr:postcode":"98004",
    "addr:street":"116Th Ave Ne",
    "iso:country":"US",
    "sg:address":"1240 116th Ave NE",
    "sg:city":"Bellevue",
    "sg:classifiers":[
        {
            "category":"Health Services",
            "subcategory":"Medical Lab",
            "type":"Services"
        }
    ],
    "sg:phone":"+1 425 688 7964",
    "sg:postcode":"98004",
    "sg:province":"WA",
    "sg:tags":[
        "laboratory"
    ],
    "wof:name":"Pathology Associates Med Lab",
    "wof:placetype":"venue"
},
  "geometry": {"coordinates":[-122.18558400000001,47.626913],"type":"Point"}
}