{
  "type": "Feature",
  "properties": {
    "addr:full":"7213 NE 58th St Vancouver WA 98662",
    "addr:housenumber":"7213",
    "addr:postcode":"98662",
    "addr:street":"Ne 58Th St",
    "iso:country":"US",
    "sg:address":"7213 NE 58th St",
    "sg:city":"Vancouver",
    "sg:classifiers":[
        {
            "category":"Real Estate",
            "subcategory":"Real Estate Operator",
            "type":"Services"
        }
    ],
    "sg:phone":"+1 360 993 9503",
    "sg:postcode":"98662",
    "sg:province":"WA",
    "sg:tags":[
        "apartment"
    ],
    "wof:name":"Walnut Grove Non-Profit Housing",
    "wof:placetype":"venue"
},
  "geometry": {"coordinates":[-122.599225,45.664349],"type":"Point"}
}