{
  "type": "Feature",
  "properties": {
    "addr:full":"809 W Main St Monroe WA 98272",
    "addr:housenumber":"809",
    "addr:postcode":"98272",
    "addr:street":"W Main St",
    "iso:country":"US",
    "sg:address":"809 W Main St",
    "sg:city":"Monroe",
    "sg:classifiers":[
        {
            "category":"Health Services",
            "subcategory":"Doctor",
            "type":"Services"
        }
    ],
    "sg:phone":"+1 360 805 8448",
    "sg:postcode":"98272",
    "sg:province":"WA",
    "wof:name":"Lowell Cindy M DDS",
    "wof:placetype":"venue"
},
  "geometry": {"coordinates":[-121.980796,47.852679],"type":"Point"}
}