{
  "type": "Feature",
  "properties": {
    "addr:full":"2103 Harrison Ave NW # 2167 Olympia WA 98502",
    "addr:housenumber":"2103",
    "addr:postcode":"98502",
    "addr:street":"Harrison Ave Nw # 2167",
    "iso:country":"US",
    "sg:address":"2103 Harrison Ave NW # 2167",
    "sg:city":"Olympia",
    "sg:classifiers":[
        {
            "category":"Professional",
            "subcategory":"Printing & Photocopies",
            "type":"Services"
        }
    ],
    "sg:phone":"+1 360 956 0224",
    "sg:postcode":"98502",
    "sg:province":"WA",
    "sg:tags":[
        "photographers-commercial"
    ],
    "sg:website":"http://www.intlphoto.com",
    "wof:name":"International Photo",
    "wof:placetype":"venue"
},
  "geometry": {"coordinates":[-122.926941,47.046055],"type":"Point"}
}