{
  "type": "Feature",
  "properties": {
    "addr:full":"19812 Viking Ave NW Poulsbo WA 98370",
    "addr:housenumber":"19812",
    "addr:postcode":"98370",
    "addr:street":"Viking Ave Nw",
    "iso:country":"US",
    "sg:address":"19812 Viking Ave NW",
    "sg:city":"Poulsbo",
    "sg:classifiers":[
        {
            "category":"Autos & Motor Vehicles",
            "subcategory":"Auto Supplies",
            "type":"Retail Goods"
        }
    ],
    "sg:phone":"+1 360 779 7000",
    "sg:postcode":"98370",
    "sg:province":"WA",
    "sg:tags":[
        "automobile",
        "parts"
    ],
    "wof:name":"Parker Auto Supply",
    "wof:placetype":"venue"
},
  "geometry": {"coordinates":[-122.656597,47.743017],"type":"Point"}
}