{
  "type": "Feature",
  "properties": {
    "addr:full":"10026 Main St Bothell WA 98011",
    "addr:housenumber":"10026",
    "addr:postcode":"98011",
    "addr:street":"Main St",
    "iso:country":"US",
    "sg:address":"10026 Main St",
    "sg:city":"Bothell",
    "sg:classifiers":[
        {
            "category":"Shopping",
            "subcategory":"Used Merchandise",
            "type":"Retail Goods"
        }
    ],
    "sg:phone":"+1 425 488 2676",
    "sg:postcode":"98011",
    "sg:province":"WA",
    "wof:name":"Pawn Plus",
    "wof:placetype":"venue"
},
  "geometry": {"coordinates":[-122.205896,47.760153],"type":"Point"}
}