{
  "type": "Feature",
  "properties": {
    "iso:country":"US",
    "sg:address":"813 134th St SW",
    "sg:city":"Everett",
    "sg:classifiers":[
        {
            "category":"Wholesale",
            "subcategory":"Construction Materials",
            "type":"Manufacturing & Wholesale Goods"
        }
    ],
    "sg:phone":"+1 425 787 9633",
    "sg:postcode":"98204",
    "sg:province":"WA",
    "sg:tags":[
        "roofing"
    ],
    "wof:name":"Washington Cedar & Supply Co",
    "wof:placetype":"venue"
},
  "geometry": {"coordinates":[-122.245262,47.876953],"type":"Point"}
}