{
  "type": "Feature",
  "properties": {
    "addr:full":"747 Chandler Rd Chehalis WA 98532",
    "addr:housenumber":"747",
    "addr:postcode":"98532",
    "addr:street":"Chandler Rd",
    "iso:country":"US",
    "sg:address":"747 Chandler Rd",
    "sg:city":"Chehalis",
    "sg:classifiers":[
        {
            "category":"Wholesale",
            "subcategory":"Groceries",
            "type":"Manufacturing & Wholesale Goods"
        }
    ],
    "sg:phone":"+1 360 291 0038",
    "sg:postcode":"98532",
    "sg:province":"WA",
    "sg:tags":[
        "food",
        "product",
        "health"
    ],
    "wof:name":"Lyndas Healthcare",
    "wof:placetype":"venue"
},
  "geometry": {"coordinates":[-123.29527899999999,46.638345],"type":"Point"}
}