{
  "type": "Feature",
  "properties": {
    "addr:full":"4631 48th Ave S Seattle WA 98118",
    "addr:housenumber":"4631",
    "addr:postcode":"98118",
    "addr:street":"48Th Ave S",
    "iso:country":"US",
    "sg:address":"4631 48th Ave S",
    "sg:city":"Seattle",
    "sg:classifiers":[
        {
            "category":"Building & Trades",
            "subcategory":"Construction",
            "type":"Services"
        }
    ],
    "sg:phone":"+1 206 725 2750",
    "sg:postcode":"98118",
    "sg:province":"WA",
    "sg:tags":[
        "residential",
        "general",
        "commercial",
        "contractor"
    ],
    "wof:name":"Shadow Mountain Construction",
    "wof:placetype":"venue"
},
  "geometry": {"coordinates":[-122.273293,47.560935],"type":"Point"}
}