{
  "type": "Feature",
  "properties": {
    "addr:full":"1022 Main St Pomeroy WA 99347",
    "addr:housenumber":"1022",
    "addr:postcode":"99347",
    "addr:street":"Main St",
    "iso:country":"US",
    "sg:address":"1022 Main St",
    "sg:city":"Pomeroy",
    "sg:classifiers":[
        {
            "category":"Personal",
            "subcategory":"Tanning Parlor",
            "type":"Services"
        },
        {
            "category":"Personal",
            "subcategory":"Beauty Salon",
            "type":"Services"
        },
        {
            "category":"Personal",
            "subcategory":"Nail Salon",
            "type":"Services"
        }
    ],
    "sg:phone":"+1 509 843 3004",
    "sg:postcode":"99347",
    "sg:province":"WA",
    "wof:name":"Clippers",
    "wof:placetype":"venue"
},
  "geometry": {"coordinates":[-117.596739,46.474139],"type":"Point"}
}