{
  "type": "Feature",
  "properties": {
    "addr:full":"6790 Roche Harbor Rd Friday Harbor WA 98250",
    "addr:housenumber":"6790",
    "addr:postcode":"98250",
    "addr:street":"Roche Harbor Rd",
    "iso:country":"US",
    "sg:address":"6790 Roche Harbor Rd",
    "sg:city":"Friday Harbor",
    "sg:classifiers":[
        {
            "category":"Professional",
            "subcategory":"Business Services",
            "type":"Services"
        }
    ],
    "sg:phone":"+1 360 378 7251",
    "sg:postcode":"98250",
    "sg:province":"WA",
    "wof:name":"Lesley D Larsen",
    "wof:placetype":"venue"
},
  "geometry": {"coordinates":[-123.10531899999999,48.592782],"type":"Point"}
}