{
  "type": "Feature",
  "properties": {
    "addr:full":"18099 NW Varese Ct Issaquah WA 98027",
    "addr:housenumber":"18099",
    "addr:postcode":"98027",
    "addr:street":"Nw Varese Ct",
    "iso:country":"US",
    "sg:address":"18099 NW Varese Ct",
    "sg:city":"Issaquah",
    "sg:classifiers":[
        {
            "category":"Professional",
            "subcategory":"Management & Consulting",
            "type":"Services"
        }
    ],
    "sg:phone":"+1 425 643 1927",
    "sg:postcode":"98027",
    "sg:province":"WA",
    "sg:tags":[
        "consultant",
        "health",
        "business",
        "care"
    ],
    "wof:name":"David Hunter Associates Inc",
    "wof:placetype":"venue"
},
  "geometry": {"coordinates":[-122.099085,47.549143],"type":"Point"}
}