{
  "type": "Feature",
  "properties": {
    "addr:full":"6705 NE 117th Ave Vancouver WA 98662",
    "addr:housenumber":"6705",
    "addr:postcode":"98662",
    "addr:street":"Ne 117Th Ave",
    "iso:country":"US",
    "sg:address":"6705 NE 117th Ave",
    "sg:city":"Vancouver",
    "sg:classifiers":[
        {
            "category":"Building & Trades",
            "subcategory":"Equipment Rental",
            "type":"Services"
        }
    ],
    "sg:phone":"+1 360 260 7368",
    "sg:postcode":"98662",
    "sg:province":"WA",
    "sg:tags":[
        "heavy",
        "construction",
        "yard"
    ],
    "sg:website":"www.ur.com",
    "wof:name":"United Rentals",
    "wof:placetype":"venue"
},
  "geometry": {"coordinates":[-122.552458,45.66757],"type":"Point"}
}