{
  "type": "Feature",
  "properties": {
    "addr:full":"15206 81st Ave NE Kenmore WA 98028",
    "addr:housenumber":"15206",
    "addr:postcode":"98028",
    "addr:street":"81St Ave Ne",
    "iso:country":"US",
    "sg:address":"15206 81st Ave NE",
    "sg:city":"Kenmore",
    "sg:classifiers":[
        {
            "category":"Professional",
            "subcategory":"Management & Consulting",
            "type":"Services"
        }
    ],
    "sg:phone":"+1 206 898 8587",
    "sg:postcode":"98028",
    "sg:province":"WA",
    "wof:name":"Ryan Thomas White",
    "wof:placetype":"venue"
},
  "geometry": {"coordinates":[-122.232795,47.738454],"type":"Point"}
}