{
  "type": "Feature",
  "properties": {
    "iso:country":"US",
    "sg:address":"14405 E 32nd Ave",
    "sg:city":"Veradale",
    "sg:classifiers":[
        {
            "category":"Building & Trades",
            "subcategory":"Construction",
            "type":"Services"
        }
    ],
    "sg:phone":"+1 509 922 2427",
    "sg:postcode":"99037",
    "sg:province":"WA",
    "sg:tags":[
        "house"
    ],
    "wof:name":"Double BS Construction",
    "wof:placetype":"venue"
},
  "geometry": {"coordinates":[-117.209712,47.627925],"type":"Point"}
}