{
  "type": "Feature",
  "properties": {
    "addr:full":"444 NE Ravenna Blvd Seattle WA 98115",
    "addr:housenumber":"444",
    "addr:postcode":"98115",
    "addr:street":"Ne Ravenna Blvd",
    "iso:country":"US",
    "sg:address":"444 NE Ravenna Blvd",
    "sg:city":"Seattle",
    "sg:classifiers":[
        {
            "category":"Professional",
            "subcategory":"Accounting & Tax Preparation",
            "type":"Services"
        }
    ],
    "sg:phone":"+1 206 525 3534",
    "sg:postcode":"98115",
    "sg:province":"WA",
    "sg:tags":[
        "consulting",
        "management"
    ],
    "wof:name":"Martini & Associates Ltd",
    "wof:placetype":"venue"
},
  "geometry": {"coordinates":[-122.32378199999999,47.678212],"type":"Point"}
}