{
  "type": "Feature",
  "properties": {
    "addr:full":"939 6th St S Kirkland WA 98033",
    "addr:housenumber":"939",
    "addr:postcode":"98033",
    "addr:street":"6Th St S",
    "iso:country":"US",
    "sg:address":"939 6th St S",
    "sg:city":"Kirkland",
    "sg:classifiers":[
        {
            "category":"Retail",
            "subcategory":"Laundry & Dry Cleaning",
            "type":"Services"
        }
    ],
    "sg:phone":"+1 425 822 7074",
    "sg:postcode":"98033",
    "sg:province":"WA",
    "sg:tags":[
        "cleaner",
        "plant",
        "drycleaning"
    ],
    "wof:name":"Bakker's Fine Dry Cleaning",
    "wof:placetype":"venue"
},
  "geometry": {"coordinates":[-122.195999,47.667801],"type":"Point"}
}