{
  "type": "Feature",
  "properties": {
    "addr:full":"20351 State Rte 20 Burlington WA 98233",
    "addr:housenumber":"20351",
    "addr:postcode":"98233",
    "addr:street":"State Rte 20",
    "iso:country":"US",
    "sg:address":"20351 State Rte 20",
    "sg:city":"Burlington",
    "sg:classifiers":[
        {
            "category":"Professional",
            "subcategory":"Business Services",
            "type":"Services"
        }
    ],
    "sg:phone":"+1 360 757 6635",
    "sg:postcode":"98233",
    "sg:province":"WA",
    "wof:name":"Edson Marilyn",
    "wof:placetype":"venue"
},
  "geometry": {"coordinates":[-122.305969,48.483179],"type":"Point"}
}