{
  "type": "Feature",
  "properties": {
    "addr:full":"446 13th St Clarkston WA 99403",
    "addr:housenumber":"446",
    "addr:postcode":"99403",
    "addr:street":"13Th St",
    "iso:country":"US",
    "sg:address":"446 13th St",
    "sg:city":"Clarkston",
    "sg:classifiers":[
        {
            "category":"Home & Garden",
            "subcategory":"Home Furnishings",
            "type":"Retail Goods"
        }
    ],
    "sg:phone":"+1 509 751 1045",
    "sg:postcode":"99403",
    "sg:province":"WA",
    "sg:tags":[
        "shop",
        "pottery",
        "product",
        "gift",
        "mfg"
    ],
    "wof:name":"North Pole Ceramic & Gift Shop",
    "wof:placetype":"venue"
},
  "geometry": {"coordinates":[-117.05862999999999,46.420865],"type":"Point"}
}