{
  "type": "Feature",
  "properties": {
    "iso:country":"US",
    "sg:address":"13 S 3rd Ave",
    "sg:city":"Yakima",
    "sg:classifiers":[
        {
            "category":"Wholesale",
            "subcategory":"Scrap",
            "type":"Manufacturing & Wholesale Goods"
        }
    ],
    "sg:phone":"+1 509 457 5612",
    "sg:postcode":"98902",
    "sg:province":"WA",
    "sg:tags":[
        "material",
        "metal"
    ],
    "wof:name":"Chicago Junk & Machinery Co",
    "wof:placetype":"venue"
},
  "geometry": {"coordinates":[-120.511959,46.59964],"type":"Point"}
}