{
  "type": "Feature",
  "properties": {
    "addr:full":"439 Spooner Rd Chehalis WA 98532",
    "addr:housenumber":"439",
    "addr:postcode":"98532",
    "addr:street":"Spooner Rd",
    "iso:country":"US",
    "sg:address":"439 Spooner Rd",
    "sg:city":"Chehalis",
    "sg:classifiers":[
        {
            "category":"Farming",
            "subcategory":"Dairy Farm",
            "type":"Manufacturing & Wholesale Goods"
        }
    ],
    "sg:phone":"+1 360 740 8988",
    "sg:postcode":"98532",
    "sg:province":"WA",
    "wof:name":"Rosecrest Farm",
    "wof:placetype":"venue"
},
  "geometry": {"coordinates":[-123.097421,46.638886],"type":"Point"}
}