{
  "type": "Feature",
  "properties": {
    "addr:full":"1043 S Jackson St Ste 103 Seattle WA 98104",
    "addr:housenumber":"1043",
    "addr:postcode":"98104",
    "addr:street":"S Jackson St Ste 103",
    "iso:country":"US",
    "sg:address":"1043 S Jackson St Ste 103",
    "sg:city":"Seattle",
    "sg:classifiers":[
        {
            "category":"Shopping",
            "subcategory":"Jewelry",
            "type":"Retail Goods"
        }
    ],
    "sg:phone":"+1 206 860 1458",
    "sg:postcode":"98104",
    "sg:province":"WA",
    "wof:name":"Duc Hien",
    "wof:placetype":"venue"
},
  "geometry": {"coordinates":[-122.319,47.599098],"type":"Point"}
}