{
  "type": "Feature",
  "properties": {
    "addr:full":"209 E Casino Rd Everett WA 98208",
    "addr:housenumber":"209",
    "addr:postcode":"98208",
    "addr:street":"E Casino Rd",
    "iso:country":"US",
    "sg:address":"209 E Casino Rd",
    "sg:city":"Everett",
    "sg:classifiers":[
        {
            "category":"Personal",
            "subcategory":"Beauty Salon",
            "type":"Services"
        }
    ],
    "sg:phone":"+1 425 355 5122",
    "sg:postcode":"98208",
    "sg:province":"WA",
    "sg:tags":[
        "shop"
    ],
    "wof:name":"L A Hair",
    "wof:placetype":"venue"
},
  "geometry": {"coordinates":[-122.230378,47.921996],"type":"Point"}
}