{
  "type": "Feature",
  "properties": {
    "addr:full":"4660 Whitman Ln SE Olympia WA 98513",
    "addr:housenumber":"4660",
    "addr:postcode":"98513",
    "addr:street":"Whitman Ln Se",
    "iso:country":"US",
    "sg:address":"4660 Whitman Ln SE",
    "sg:city":"Olympia",
    "sg:classifiers":[
        {
            "category":"Coffee & Tea",
            "type":"Food & Drink"
        }
    ],
    "sg:menulink":"http://www.allmenus.com/wa/olympia/117834-starbucks-coffee/menu/",
    "sg:phone":"+1 360 491 8927",
    "sg:postcode":"98513",
    "sg:province":"WA",
    "sg:tags":[
        "american"
    ],
    "wof:name":"Starbucks Coffee",
    "wof:placetype":"venue"
},
  "geometry": {"coordinates":[-122.826713,46.99562],"type":"Point"}
}