{
  "type": "Feature",
  "properties": {
    "addr:full":"2453 Bossburg Rd Evans WA 99126",
    "addr:housenumber":"2453",
    "addr:postcode":"99126",
    "addr:street":"Bossburg Rd",
    "iso:country":"US",
    "sg:address":"2453 Bossburg Rd",
    "sg:city":"Evans",
    "sg:classifiers":[
        {
            "category":"Building & Trades",
            "subcategory":"Construction",
            "type":"Services"
        }
    ],
    "sg:phone":"+1 509 684 5583",
    "sg:postcode":"99126",
    "sg:province":"WA",
    "sg:tags":[
        "general",
        "contractor"
    ],
    "wof:name":"Short Hop Construction",
    "wof:placetype":"venue"
},
  "geometry": {"coordinates":[-118.030282,48.747119],"type":"Point"}
}