{
  "type": "Feature",
  "properties": {
    "addr:full":"13623 271st Ave SE Monroe WA 98272",
    "addr:housenumber":"13623",
    "addr:postcode":"98272",
    "addr:street":"271St Ave Se",
    "iso:country":"US",
    "sg:address":"13623 271st Ave SE",
    "sg:city":"Monroe",
    "sg:classifiers":[
        {
            "category":"Professional",
            "type":"Services"
        }
    ],
    "sg:phone":"+1 360 794 8973",
    "sg:postcode":"98272",
    "sg:province":"WA",
    "wof:name":"Melton Alfred Oneil",
    "wof:placetype":"venue"
},
  "geometry": {"coordinates":[-121.868848,47.880947],"type":"Point"}
}