{
  "type": "Feature",
  "properties": {
    "addr:full":"505 Wood Pl Everett WA 98203",
    "addr:housenumber":"505",
    "addr:postcode":"98203",
    "addr:street":"Wood Pl",
    "iso:country":"US",
    "sg:address":"505 Wood Pl",
    "sg:city":"Everett",
    "sg:classifiers":[
        {
            "category":"Professional",
            "subcategory":"Business Services",
            "type":"Services"
        }
    ],
    "sg:phone":"+1 425 259 3448",
    "sg:postcode":"98203",
    "sg:province":"WA",
    "wof:name":"George Hawkinson Inc",
    "wof:placetype":"venue"
},
  "geometry": {"coordinates":[-122.23450200000001,47.956248],"type":"Point"}
}