{
  "type": "Feature",
  "properties": {
    "iso:country":"US",
    "sg:address":"207 S 68th Ave",
    "sg:city":"Yakima",
    "sg:classifiers":[
        {
            "category":"Retail",
            "subcategory":"Laundry & Dry Cleaning",
            "type":"Services"
        }
    ],
    "sg:phone":"+1 509 966 7865",
    "sg:postcode":"98908",
    "sg:province":"WA",
    "wof:name":"Sew What",
    "wof:placetype":"venue"
},
  "geometry": {"coordinates":[-120.59966799999999,46.594585],"type":"Point"}
}