{
  "type": "Feature",
  "properties": {
    "addr:full":"10630 Lakeside Ave NE Seattle WA 98125",
    "addr:housenumber":"10630",
    "addr:postcode":"98125",
    "addr:street":"Lakeside Ave Ne",
    "iso:country":"US",
    "sg:address":"10630 Lakeside Ave NE",
    "sg:city":"Seattle",
    "sg:classifiers":[
        {
            "category":"Organizations",
            "subcategory":"Professional Association",
            "type":"Services"
        }
    ],
    "sg:phone":"+1 206 417 7846",
    "sg:postcode":"98125",
    "sg:province":"WA",
    "wof:name":"Bertil Hille",
    "wof:placetype":"venue"
},
  "geometry": {"coordinates":[-122.276073,47.706255],"type":"Point"}
}