{
  "type": "Feature",
  "properties": {
    "addr:full":"325 Wine Country Rd Prosser WA 99350",
    "addr:housenumber":"325",
    "addr:postcode":"99350",
    "addr:street":"Wine Country Rd",
    "iso:country":"US",
    "sg:address":"325 Wine Country Rd",
    "sg:city":"Prosser",
    "sg:classifiers":[
        {
            "category":"Personal",
            "subcategory":"Beauty Salon",
            "type":"Services"
        }
    ],
    "sg:phone":"+1 509 786 9915",
    "sg:postcode":"99350",
    "sg:province":"WA",
    "wof:name":"VGS Design & Tan",
    "wof:placetype":"venue"
},
  "geometry": {"coordinates":[-119.782991,46.213852],"type":"Point"}
}