{
  "type": "Feature",
  "properties": {
    "addr:full":"9601 35th Ave SW Seattle WA 98126",
    "addr:housenumber":"9601",
    "addr:postcode":"98126",
    "addr:street":"35Th Ave Sw",
    "iso:country":"US",
    "sg:address":"9601 35th Ave SW",
    "sg:city":"Seattle",
    "sg:classifiers":[
        {
            "category":"Organizations",
            "subcategory":"Religious Organization",
            "type":"Services"
        }
    ],
    "sg:phone":"+1 206 937 1417",
    "sg:postcode":"98126",
    "sg:province":"WA",
    "sg:tags":[
        "church"
    ],
    "wof:name":"Freedom Missionary Chr-Sttl",
    "wof:placetype":"venue"
},
  "geometry": {"coordinates":[-122.37675900000001,47.516545],"type":"Point"}
}