{
  "type": "Feature",
  "properties": {
    "addr:full":"11203 Benston Dr E Puyallup WA 98372",
    "addr:postcode":"11203;98372",
    "addr:street":"Benston Dr E",
    "iso:country":"US",
    "sg:address":"11203 Benston Dr E",
    "sg:city":"Puyallup",
    "sg:classifiers":[
        {
            "category":"Manufacturing",
            "subcategory":"Tools & Machinery",
            "type":"Manufacturing & Wholesale Goods"
        }
    ],
    "sg:phone":"+1 253 770 7441",
    "sg:postcode":"98372",
    "sg:province":"WA",
    "sg:tags":[
        "wiring",
        "devices",
        "mfg"
    ],
    "wof:name":"A P D Kart Racing",
    "wof:placetype":"venue"
},
  "geometry": {"coordinates":[-122.281389,47.196702],"type":"Point"}
}