{
  "type": "Feature",
  "properties": {
    "addr:full":"342 SW 16th St Chehalis WA 98532",
    "addr:housenumber":"342",
    "addr:postcode":"98532",
    "addr:street":"Sw 16Th St",
    "iso:country":"US",
    "sg:address":"342 SW 16th St",
    "sg:city":"Chehalis",
    "sg:classifiers":[
        {
            "category":"Education",
            "subcategory":"School",
            "type":"Public Place"
        }
    ],
    "sg:phone":"+1 360 807 7235",
    "sg:postcode":"98532",
    "sg:province":"WA",
    "wof:name":"W F West High School",
    "wof:placetype":"venue"
},
  "geometry": {"coordinates":[-122.950789,46.65064],"type":"Point"}
}