{
  "type": "Feature",
  "properties": {
    "addr:full":"1938 Market St Tacoma WA 98402",
    "addr:housenumber":"1938",
    "addr:postcode":"98402",
    "addr:street":"Market St",
    "iso:country":"US",
    "sg:address":"1938 Market St",
    "sg:city":"Tacoma",
    "sg:classifiers":[
        {
            "category":"Retail",
            "subcategory":"Repair Shop",
            "type":"Services"
        },
        {
            "category":"Home & Garden",
            "subcategory":"Home Furnishings",
            "type":"Retail Goods"
        }
    ],
    "sg:phone":"+1 253 572 5995",
    "sg:postcode":"98402",
    "sg:province":"WA",
    "sg:tags":[
        "refinishing",
        "furniture"
    ],
    "wof:name":"Decorator's Workshop",
    "wof:placetype":"venue"
},
  "geometry": {"coordinates":[-122.439358,47.24315],"type":"Point"}
}