{
  "type": "Feature",
  "properties": {
    "addr:full":"801 W Yelm Ave # B Yelm WA 98597",
    "addr:housenumber":"801",
    "addr:postcode":"98597",
    "addr:street":"W Yelm Ave # B",
    "iso:country":"US",
    "sg:address":"801 W Yelm Ave # B",
    "sg:city":"Yelm",
    "sg:classifiers":[
        {
            "category":"Autos & Motor Vehicles",
            "subcategory":"Auto Supplies",
            "type":"Retail Goods"
        },
        {
            "category":"Retail",
            "subcategory":"Auto Repair",
            "type":"Services"
        }
    ],
    "sg:phone":"+1 877 753 1327",
    "sg:postcode":"98597",
    "sg:province":"WA",
    "sg:tags":[
        "body",
        "undercoating-automotive",
        "automobile",
        "rustproofing",
        "removal",
        "dent",
        "painting",
        "repairing"
    ],
    "sg:website":"http://local.ingenio.com/Listings/Details.aspx?NUM=a%3a10335157%3a13%3a4859924%3a14%3a0%3a7",
    "wof:name":"Advantage collision",
    "wof:placetype":"venue"
},
  "geometry": {"coordinates":[-122.615793,46.946965],"type":"Point"}
}