{
  "type": "Feature",
  "properties": {
    "addr:full":"7735 24th Ave NW Seattle WA 98117",
    "addr:housenumber":"7735",
    "addr:postcode":"98117",
    "addr:street":"24Th Ave Nw",
    "iso:country":"US",
    "sg:address":"7735 24th Ave NW",
    "sg:city":"Seattle",
    "sg:classifiers":[
        {
            "category":"Personal",
            "subcategory":"Beauty Salon",
            "type":"Services"
        }
    ],
    "sg:phone":"+1 206 784 6737",
    "sg:postcode":"98117",
    "sg:province":"WA",
    "sg:tags":[
        "shop"
    ],
    "wof:name":"Genesis Salon",
    "wof:placetype":"venue"
},
  "geometry": {"coordinates":[-122.38766800000001,47.686591],"type":"Point"}
}