{
  "type": "Feature",
  "properties": {
    "addr:full":"5915 Airport Way S Seattle WA 98108",
    "addr:housenumber":"5915",
    "addr:postcode":"98108",
    "addr:street":"Airport Way S",
    "iso:country":"US",
    "sg:address":"5915 Airport Way S",
    "sg:city":"Seattle",
    "sg:classifiers":[
        {
            "category":"Manufacturing",
            "subcategory":"Food",
            "type":"Manufacturing & Wholesale Goods"
        }
    ],
    "sg:phone":"+1 206 762 7411",
    "sg:postcode":"98108",
    "sg:province":"WA",
    "sg:tags":[
        "bakery",
        "retail",
        "product",
        "mfg"
    ],
    "wof:name":"Savoy Truffle the",
    "wof:placetype":"venue"
},
  "geometry": {"coordinates":[-122.318001,47.550201],"type":"Point"}
}