{
  "type": "Feature",
  "properties": {
    "addr:full":"712 Martin Luther King Jr Way Tacoma WA 98405",
    "addr:housenumber":"712",
    "addr:postcode":"98405",
    "addr:street":"Martin Luther King Jr Way",
    "iso:country":"US",
    "sg:address":"712 Martin Luther King Jr Way",
    "sg:city":"Tacoma",
    "sg:classifiers":[
        {
            "category":"Social Services",
            "type":"Services"
        }
    ],
    "sg:phone":"+1 253 383 7791",
    "sg:postcode":"98405",
    "sg:province":"WA",
    "wof:name":"Phoebe House Association",
    "wof:placetype":"venue"
},
  "geometry": {"coordinates":[-122.452521,47.255204],"type":"Point"}
}