{
  "type": "Feature",
  "properties": {
    "addr:full":"2816 Wheaton Way Bremerton WA 98310",
    "addr:housenumber":"2816",
    "addr:postcode":"98310",
    "addr:street":"Wheaton Way",
    "iso:country":"US",
    "sg:address":"2816 Wheaton Way",
    "sg:city":"Bremerton",
    "sg:classifiers":[
        {
            "category":"Health Services",
            "subcategory":"Optometrist",
            "type":"Services"
        }
    ],
    "sg:phone":"+1 360 479 2020",
    "sg:postcode":"98310",
    "sg:province":"WA",
    "wof:name":"Visual Connection The",
    "wof:placetype":"venue"
},
  "geometry": {"coordinates":[-122.628939,47.587952],"type":"Point"}
}