{
  "type": "Feature",
  "properties": {
    "addr:full":"251 Hjelvicks Rd Brinnon WA 98320",
    "addr:housenumber":"251",
    "addr:postcode":"98320",
    "addr:street":"Hjelvicks Rd",
    "iso:country":"US",
    "sg:address":"251 Hjelvicks Rd",
    "sg:city":"Brinnon",
    "sg:classifiers":[
        {
            "category":"Shopping",
            "subcategory":"Discount & Variety Stores",
            "type":"Retail Goods"
        }
    ],
    "sg:phone":"+1 360 796 4720",
    "sg:postcode":"98320",
    "sg:province":"WA",
    "sg:tags":[
        "hardware",
        "merchandise",
        "general"
    ],
    "wof:name":"Hjelviks General Store",
    "wof:placetype":"venue"
},
  "geometry": {"coordinates":[-122.88070999999999,47.738164],"type":"Point"}
}