{
  "type": "Feature",
  "properties": {
    "addr:full":"5810 74th Dr NE Marysville WA 98270",
    "addr:housenumber":"5810",
    "addr:postcode":"98270",
    "addr:street":"74Th Dr Ne",
    "iso:country":"US",
    "sg:address":"5810 74th Dr NE",
    "sg:city":"Marysville",
    "sg:classifiers":[
        {
            "category":"Shopping",
            "subcategory":"Catalog Store",
            "type":"Retail Goods"
        }
    ],
    "sg:phone":"+1 425 346 6750",
    "sg:postcode":"98270",
    "sg:province":"WA",
    "sg:tags":[
        "mail",
        "house"
    ],
    "wof:name":"Kings Helper",
    "wof:placetype":"venue"
},
  "geometry": {"coordinates":[-122.13082799999999,48.048872],"type":"Point"}
}