{
  "type": "Feature",
  "properties": {
    "addr:full":"3613 N Grace Ln Bellingham WA 98226",
    "addr:housenumber":"3613",
    "addr:postcode":"98226",
    "addr:street":"N Grace Ln",
    "iso:country":"US",
    "sg:address":"3613 N Grace Ln",
    "sg:city":"Bellingham",
    "sg:classifiers":[
        {
            "category":"Professional",
            "subcategory":"Computer Services",
            "type":"Services"
        }
    ],
    "sg:phone":"+1 360 756 9630",
    "sg:postcode":"98226",
    "sg:province":"WA",
    "sg:tags":[
        "consultant",
        "designer",
        "system",
        "related"
    ],
    "wof:name":"Consultnet",
    "wof:placetype":"venue"
},
  "geometry": {"coordinates":[-122.41136400000001,48.773067],"type":"Point"}
}