{
  "type": "Feature",
  "properties": {
    "addr:full":"7031 S 196th St Kent WA 98032",
    "addr:housenumber":"7031",
    "addr:postcode":"98032",
    "addr:street":"S 196Th St",
    "iso:country":"US",
    "sg:address":"7031 S 196th St",
    "sg:city":"Kent",
    "sg:classifiers":[
        {
            "category":"Manufacturing",
            "subcategory":"Tools & Machinery",
            "type":"Manufacturing & Wholesale Goods"
        }
    ],
    "sg:phone":"+1 253 872 8195",
    "sg:postcode":"98032",
    "sg:province":"WA",
    "sg:tags":[
        "machine",
        "shop"
    ],
    "wof:name":"T&E Mfg",
    "wof:placetype":"venue"
},
  "geometry": {"coordinates":[-122.247648,47.426614],"type":"Point"}
}