{
  "type": "Feature",
  "properties": {
    "addr:full":"3339 56th Ave SW Seattle WA 98116",
    "addr:housenumber":"3339",
    "addr:postcode":"98116",
    "addr:street":"56Th Ave Sw",
    "iso:country":"US",
    "sg:address":"3339 56th Ave SW",
    "sg:city":"Seattle",
    "sg:classifiers":[
        {
            "category":"Professional",
            "subcategory":"Employment Agencies",
            "type":"Services"
        }
    ],
    "sg:phone":"+1 206 932 7693",
    "sg:postcode":"98116",
    "sg:province":"WA",
    "sg:tags":[
        "sc",
        "engineering",
        "help",
        "vocational",
        "supply"
    ],
    "wof:name":"Aero-Accords Inc",
    "wof:placetype":"venue"
},
  "geometry": {"coordinates":[-122.40372600000001,47.572529],"type":"Point"}
}