{
  "type": "Feature",
  "properties": {
    "addr:full":"2107 NW 65th St Seattle WA 98117",
    "addr:housenumber":"2107",
    "addr:postcode":"98117",
    "addr:street":"Nw 65Th St",
    "iso:country":"US",
    "sg:address":"2107 NW 65th St",
    "sg:city":"Seattle",
    "sg:classifiers":[
        {
            "category":"Building & Trades",
            "subcategory":"Construction",
            "type":"Services"
        }
    ],
    "sg:phone":"+1 206 782 0454",
    "sg:postcode":"98117",
    "sg:province":"WA",
    "sg:tags":[
        "contractor"
    ],
    "wof:name":"Woodbridge Tile",
    "wof:placetype":"venue"
},
  "geometry": {"coordinates":[-122.38472,47.67589],"type":"Point"}
}