{
  "type": "Feature",
  "properties": {
    "iso:country":"US",
    "sg:address":"4912 Lone Bear Ln SW",
    "sg:city":"Port Orchard",
    "sg:classifiers":[
        {
            "category":"Real Estate",
            "subcategory":"Real Estate Agent",
            "type":"Services"
        }
    ],
    "sg:phone":"+1 360 340 2216",
    "sg:postcode":"98367",
    "sg:province":"WA",
    "sg:tags":[
        "inspection"
    ],
    "wof:name":"Precision Inspection",
    "wof:placetype":"venue"
},
  "geometry": {"coordinates":[-122.713449,47.515732],"type":"Point"}
}