{
  "type": "Feature",
  "properties": {
    "addr:full":"111 Legion Way SW Olympia WA 98501",
    "addr:housenumber":"111",
    "addr:postcode":"98501",
    "addr:street":"Legion Way Sw",
    "iso:country":"US",
    "sg:address":"111 Legion Way SW",
    "sg:city":"Olympia",
    "sg:phone":"+1 360 357 4232",
    "sg:postcode":"98501",
    "sg:province":"WA",
    "wof:name":"Tasty Morsels",
    "wof:placetype":"venue"
},
  "geometry": {"coordinates":[-122.90158,47.043202],"type":"Point"}
}