{
  "type": "Feature",
  "properties": {
    "addr:full":"2001B N Wenatchee Ave Wenatchee WA 98801",
    "addr:housenumber":"2001b",
    "addr:postcode":"98801",
    "addr:street":"N Wenatchee Ave",
    "iso:country":"US",
    "sg:address":"2001B N Wenatchee Ave",
    "sg:city":"Wenatchee",
    "sg:classifiers":[
        {
            "category":"Autos & Motor Vehicles",
            "subcategory":"Auto Supplies",
            "type":"Retail Goods"
        },
        {
            "category":"Retail",
            "subcategory":"Auto Repair",
            "type":"Services"
        }
    ],
    "sg:phone":"+1 509 663 4131",
    "sg:postcode":"98801",
    "sg:province":"WA",
    "sg:tags":[
        "body",
        "automobile",
        "truck",
        "painting",
        "repairing"
    ],
    "sg:website":"http://www.maaco.com",
    "wof:name":"Maaco Auto Painting & Bodywork",
    "wof:placetype":"venue"
},
  "geometry": {"coordinates":[-120.3349,47.4533],"type":"Point"}
}