{
  "type": "Feature",
  "properties": {
    "addr:full":"651 S Alaska St Seattle WA 98108",
    "addr:housenumber":"651",
    "addr:postcode":"98108",
    "addr:street":"S Alaska St",
    "iso:country":"US",
    "sg:address":"651 S Alaska St",
    "sg:city":"Seattle",
    "sg:classifiers":[
        {
            "category":"Professional",
            "subcategory":"Business Services",
            "type":"Services"
        }
    ],
    "sg:postcode":"98108",
    "sg:province":"WA",
    "sg:tags":[
        "delivery",
        "courier"
    ],
    "sg:website":"www.fedex.com",
    "wof:name":"FedEx Customer Service Center",
    "wof:placetype":"venue"
},
  "geometry": {"coordinates":[-122.325793,47.561187],"type":"Point"}
}