{
  "type": "Feature",
  "properties": {
    "addr:full":"2003 Dry Creek Rd Ellensburg WA 98926",
    "addr:housenumber":"2003",
    "addr:postcode":"98926",
    "addr:street":"Dry Creek Rd",
    "iso:country":"US",
    "sg:address":"2003 Dry Creek Rd",
    "sg:city":"Ellensburg",
    "sg:classifiers":[
        {
            "category":"Professional",
            "subcategory":"Art Services",
            "type":"Services"
        }
    ],
    "sg:phone":"+1 509 925 1472",
    "sg:postcode":"98926",
    "sg:province":"WA",
    "sg:tags":[
        "designer",
        "display",
        "producer"
    ],
    "wof:name":"Ah Designs",
    "wof:placetype":"venue"
},
  "geometry": {"coordinates":[-120.578132,47.019623],"type":"Point"}
}