{
  "type": "Feature",
  "properties": {
    "addr:full":"3005 SE Spyglass Dr Vancouver WA 98683",
    "addr:housenumber":"3005",
    "addr:postcode":"98683",
    "addr:street":"Se Spyglass Dr",
    "iso:country":"US",
    "sg:address":"3005 SE Spyglass Dr",
    "sg:city":"Vancouver",
    "sg:classifiers":[
        {
            "category":"Real Estate",
            "subcategory":"Real Estate Operator",
            "type":"Services"
        }
    ],
    "sg:phone":"+1 360 944 9654",
    "sg:postcode":"98683",
    "sg:province":"WA",
    "sg:tags":[
        "building",
        "nonresidential"
    ],
    "wof:name":"Kinkade Properties LLC",
    "wof:placetype":"venue"
},
  "geometry": {"coordinates":[-122.51043,45.598955],"type":"Point"}
}