{
  "type": "Feature",
  "properties": {
    "addr:full":"5 N Walnut Rd Spokane WA 99206",
    "addr:housenumber":"5",
    "addr:postcode":"99206",
    "addr:street":"N Walnut Rd",
    "iso:country":"US",
    "sg:address":"5 N Walnut Rd",
    "sg:city":"Spokane",
    "sg:classifiers":[
        {
            "category":"Education",
            "subcategory":"Dance Studio",
            "type":"Public Place"
        }
    ],
    "sg:phone":"+1 509 747 2640",
    "sg:postcode":"99206",
    "sg:province":"WA",
    "sg:tags":[
        "school",
        "hall"
    ],
    "wof:name":"Spokane Folklore Society",
    "wof:placetype":"venue"
},
  "geometry": {"coordinates":[-117.27085,47.660625],"type":"Point"}
}