{
  "type": "Feature",
  "properties": {
    "addr:full":"1389 Ocean Beach Rd Hoquiam WA 98550",
    "addr:housenumber":"1389",
    "addr:postcode":"98550",
    "addr:street":"Ocean Beach Rd",
    "iso:country":"US",
    "sg:address":"1389 Ocean Beach Rd",
    "sg:city":"Hoquiam",
    "sg:classifiers":[
        {
            "category":"Home & Garden",
            "subcategory":"Garden Supply",
            "type":"Retail Goods"
        }
    ],
    "sg:phone":"+1 360 533 8463",
    "sg:postcode":"98550",
    "sg:province":"WA",
    "wof:name":"Burlingame Gardens",
    "wof:placetype":"venue"
},
  "geometry": {"coordinates":[-124.058729,47.091022],"type":"Point"}
}