{
  "type": "Feature",
  "properties": {
    "addr:full":"2736 18th Ave NE Olympia WA 98506",
    "addr:housenumber":"2736",
    "addr:postcode":"98506",
    "addr:street":"18Th Ave Ne",
    "iso:country":"US",
    "sg:address":"2736 18th Ave NE",
    "sg:city":"Olympia",
    "sg:classifiers":[
        {
            "category":"Retail",
            "subcategory":"Repair Shop",
            "type":"Services"
        }
    ],
    "sg:phone":"+1 360 352 0814",
    "sg:postcode":"98506",
    "sg:province":"WA",
    "wof:name":"Sir Lancelot Clk & Watch Repr",
    "wof:placetype":"venue"
},
  "geometry": {"coordinates":[-122.86093,47.060729],"type":"Point"}
}