{
  "type": "Feature",
  "properties": {
    "addr:full":"6515 66th St NE Marysville WA 98270",
    "addr:housenumber":"6515",
    "addr:postcode":"98270",
    "addr:street":"66Th St Ne",
    "iso:country":"US",
    "sg:address":"6515 66th St NE",
    "sg:city":"Marysville",
    "sg:classifiers":[
        {
            "category":"Health Services",
            "subcategory":"Nursing And Care Facility",
            "type":"Services"
        }
    ],
    "sg:phone":"+1 360 657 7612",
    "sg:postcode":"98270",
    "sg:province":"WA",
    "sg:tags":[
        "home",
        "convalescent"
    ],
    "wof:name":"Las Orquidias Adult Family",
    "wof:placetype":"venue"
},
  "geometry": {"coordinates":[-122.143004,48.056013],"type":"Point"}
}