{
  "type": "Feature",
  "properties": {
    "addr:full":"4081 Bluff Ln NE Bainbridge Island WA 98110",
    "addr:housenumber":"4081",
    "addr:postcode":"98110",
    "addr:street":"Bluff Ln Ne",
    "iso:country":"US",
    "sg:address":"4081 Bluff Ln NE",
    "sg:city":"Bainbridge Island",
    "sg:classifiers":[
        {
            "category":"Professional",
            "type":"Services"
        }
    ],
    "sg:phone":"+1 206 842 3194",
    "sg:postcode":"98110",
    "sg:province":"WA",
    "sg:tags":[
        "recording",
        "music",
        "composer"
    ],
    "wof:name":"Gistu Recording",
    "wof:placetype":"venue"
},
  "geometry": {"coordinates":[-122.543893,47.600135],"type":"Point"}
}