{
  "type": "Feature",
  "properties": {
    "addr:full":"32020 1st Ave S Federal Way WA 98003",
    "addr:housenumber":"32020",
    "addr:postcode":"98003",
    "addr:street":"1St Ave S Federal Way",
    "iso:country":"US",
    "sg:address":"32020 1st Ave S",
    "sg:city":"Federal Way",
    "sg:classifiers":[
        {
            "category":"Insurance",
            "subcategory":"Insurance Agent",
            "type":"Services"
        }
    ],
    "sg:phone":"+1 253 874 2173",
    "sg:postcode":"98003",
    "sg:province":"WA",
    "wof:name":"Allstate Insurance",
    "wof:placetype":"venue"
},
  "geometry": {"coordinates":[-122.33457799999999,47.31505],"type":"Point"}
}