{
  "type": "Feature",
  "properties": {
    "addr:full":"4235 36th Ave NE Olympia WA 98516",
    "addr:housenumber":"4235",
    "addr:postcode":"98516",
    "addr:street":"36Th Ave Ne",
    "iso:country":"US",
    "sg:address":"4235 36th Ave NE",
    "sg:city":"Olympia",
    "sg:classifiers":[
        {
            "category":"Farming",
            "subcategory":"Livestock Farm",
            "type":"Manufacturing & Wholesale Goods"
        }
    ],
    "sg:phone":"+1 360 491 5262",
    "sg:postcode":"98516",
    "sg:province":"WA",
    "sg:tags":[
        "specialty",
        "animal"
    ],
    "wof:name":"Llama Tree Ranch",
    "wof:placetype":"venue"
},
  "geometry": {"coordinates":[-122.82726,47.083344],"type":"Point"}
}