{
  "type": "Feature",
  "properties": {
    "addr:full":"207 N Tower Ave Centralia WA 98531",
    "addr:housenumber":"207",
    "addr:postcode":"98531",
    "addr:street":"N Tower Ave",
    "iso:country":"US",
    "sg:address":"207 N Tower Ave",
    "sg:city":"Centralia",
    "sg:classifiers":[
        {
            "category":"Shopping",
            "subcategory":"Party Supplies",
            "type":"Retail Goods"
        },
        {
            "category":"Shopping",
            "subcategory":"Gifts & Souvenirs",
            "type":"Retail Goods"
        },
        {
            "category":"Shopping",
            "subcategory":"Florist",
            "type":"Retail Goods"
        }
    ],
    "sg:phone":"+1 360 736 7337",
    "sg:postcode":"98531",
    "sg:province":"WA",
    "sg:tags":[
        "shop",
        "basket",
        "wedding"
    ],
    "sg:website":"http://www.chehalisflorist.com",
    "wof:name":"Centralia Flower Shop",
    "wof:placetype":"venue"
},
  "geometry": {"coordinates":[-122.953925,46.717248],"type":"Point"}
}