{
  "type": "Feature",
  "properties": {
    "addr:full":"16801 SE 1st St Vancouver WA 98684",
    "addr:postcode":"16801;98684",
    "addr:street":"Se 1St St",
    "iso:country":"US",
    "sg:address":"16801 SE 1st St",
    "sg:city":"Vancouver",
    "sg:classifiers":[
        {
            "category":"Building & Trades",
            "subcategory":"Construction",
            "type":"Services"
        }
    ],
    "sg:phone":"+1 360 907 0280",
    "sg:postcode":"98684",
    "sg:province":"WA",
    "sg:tags":[
        "contractor"
    ],
    "wof:name":"Silver Star Siding Co",
    "wof:placetype":"venue"
},
  "geometry": {"coordinates":[-122.497337,45.621179],"type":"Point"}
}