{
  "type": "Feature",
  "properties": {
    "addr:full":"102 N Fair Ave Yakima WA 98901",
    "addr:housenumber":"102",
    "addr:postcode":"98901",
    "addr:street":"N Fair Ave",
    "iso:country":"US",
    "sg:address":"102 N Fair Ave",
    "sg:city":"Yakima",
    "sg:classifiers":[
        {
            "category":"Home & Garden",
            "subcategory":"Home Furnishings",
            "type":"Retail Goods"
        }
    ],
    "sg:phone":"+1 509 574 4344",
    "sg:postcode":"98901",
    "sg:province":"WA",
    "wof:name":"Pier 1 Imports 578",
    "wof:placetype":"venue"
},
  "geometry": {"coordinates":[-120.49018700000001,46.60841],"type":"Point"}
}