{
  "type": "Feature",
  "properties": {
    "addr:full":"210 W Main St Everson WA 98247",
    "addr:housenumber":"210",
    "addr:postcode":"98247",
    "addr:street":"W Main St",
    "iso:country":"US",
    "sg:address":"210 W Main St",
    "sg:city":"Everson",
    "sg:classifiers":[
        {
            "category":"Restaurant",
            "type":"Food & Drink"
        }
    ],
    "sg:phone":"+1 360 966 7073",
    "sg:postcode":"98247",
    "sg:province":"WA",
    "wof:name":"The Farmer's Cafe",
    "wof:placetype":"venue"
},
  "geometry": {"coordinates":[-122.34491800000001,48.920099],"type":"Point"}
}