{
  "type": "Feature",
  "properties": {
    "iso:country":"US",
    "sg:address":"9724 S Tacoma Way",
    "sg:city":"Lakewood",
    "sg:classifiers":[
        {
            "category":"Retail",
            "subcategory":"Auto Repair",
            "type":"Services"
        }
    ],
    "sg:phone":"+1 253 582 4689",
    "sg:postcode":"98499",
    "sg:province":"WA",
    "sg:tags":[
        "repairing",
        "automobile",
        "general"
    ],
    "wof:name":"H K Auto Repair Shop",
    "wof:placetype":"venue"
},
  "geometry": {"coordinates":[-122.483715,47.168464],"type":"Point"}
}