{
  "type": "Feature",
  "properties": {
    "addr:full":"5112 85th Ave E Puyallup WA 98371",
    "addr:housenumber":"5112",
    "addr:postcode":"98371",
    "addr:street":"85Th Ave E",
    "iso:country":"US",
    "sg:address":"5112 85th Ave E",
    "sg:city":"Puyallup",
    "sg:classifiers":[
        {
            "category":"Professional",
            "subcategory":"Management & Consulting",
            "type":"Services"
        }
    ],
    "sg:phone":"+1 253 922 2198",
    "sg:postcode":"98371",
    "sg:province":"WA",
    "sg:tags":[
        "development",
        "industrial"
    ],
    "wof:name":"Schenk Business Park",
    "wof:placetype":"venue"
},
  "geometry": {"coordinates":[-122.31663,47.210631],"type":"Point"}
}