{
  "type": "Feature",
  "properties": {
    "addr:full":"417 Moilanen Rd Longview WA 98632",
    "addr:housenumber":"417",
    "addr:postcode":"98632",
    "addr:street":"Moilanen Rd",
    "iso:country":"US",
    "sg:address":"417 Moilanen Rd",
    "sg:city":"Longview",
    "sg:classifiers":[
        {
            "category":"Professional",
            "type":"Services"
        }
    ],
    "sg:phone":"+1 360 423 7912",
    "sg:postcode":"98632",
    "sg:province":"WA",
    "wof:name":"Fritz David",
    "wof:placetype":"venue"
},
  "geometry": {"coordinates":[-123.019328,46.185845],"type":"Point"}
}