{
  "type": "Feature",
  "properties": {
    "addr:full":"2727 NE 103rd St Seattle WA 98125",
    "addr:housenumber":"2727",
    "addr:postcode":"98125",
    "addr:street":"Ne 103Rd St",
    "iso:country":"US",
    "sg:address":"2727 NE 103rd St",
    "sg:city":"Seattle",
    "sg:classifiers":[
        {
            "category":"Social Services",
            "type":"Services"
        }
    ],
    "sg:phone":"+1 206 525 2432",
    "sg:postcode":"98125",
    "sg:province":"WA",
    "wof:name":"Jaworski Family Therapy Jay",
    "wof:placetype":"venue"
},
  "geometry": {"coordinates":[-122.29634,47.702993],"type":"Point"}
}