{
  "type": "Feature",
  "properties": {
    "iso:country":"US",
    "sg:address":"5725 Schickler Ln",
    "sg:city":"Bellingham",
    "sg:classifiers":[
        {
            "category":"Building & Trades",
            "subcategory":"Plumbing",
            "type":"Services"
        }
    ],
    "sg:phone":"+1 360 319 6948",
    "sg:postcode":"98226",
    "sg:province":"WA",
    "sg:tags":[
        "plumbing",
        "contractor"
    ],
    "wof:name":"Orca Plumbing",
    "wof:placetype":"venue"
},
  "geometry": {"coordinates":[-122.477394,48.849906],"type":"Point"}
}