{
  "type": "Feature",
  "properties": {
    "addr:full":"13913 107th Avenue Ct E Puyallup WA 98374",
    "addr:housenumber":"13913",
    "addr:postcode":"98374",
    "addr:street":"107Th Avenue Ct E",
    "iso:country":"US",
    "sg:address":"13913 107th Avenue Ct E",
    "sg:city":"Puyallup",
    "sg:classifiers":[
        {
            "category":"Personal",
            "type":"Services"
        }
    ],
    "sg:phone":"+1 253 677 7900",
    "sg:postcode":"98374",
    "sg:province":"WA",
    "wof:name":"Serendipity",
    "wof:placetype":"venue"
},
  "geometry": {"coordinates":[-122.28567,47.131725],"type":"Point"}
}