{
  "type": "Feature",
  "properties": {
    "addr:full":"47 E High Dr Spokane WA 99203",
    "addr:housenumber":"47",
    "addr:postcode":"99203",
    "addr:street":"E High Dr",
    "iso:country":"US",
    "sg:address":"47 E High Dr",
    "sg:city":"Spokane",
    "sg:classifiers":[
        {
            "category":"Health Services",
            "subcategory":"Doctor",
            "type":"Services"
        }
    ],
    "sg:phone":"+1 509 455 4100",
    "sg:postcode":"99203",
    "sg:province":"WA",
    "sg:tags":[
        "physician",
        "surgeon"
    ],
    "wof:name":"Medical Center Cardiology",
    "wof:placetype":"venue"
},
  "geometry": {"coordinates":[-117.408187,47.616789],"type":"Point"}
}