{
  "type": "Feature",
  "properties": {
    "addr:full":"415 W Main Ave Spokane WA 99201",
    "addr:housenumber":"415",
    "addr:postcode":"99201",
    "addr:street":"W Main Ave",
    "iso:country":"US",
    "sg:address":"415 W Main Ave",
    "sg:city":"Spokane",
    "sg:classifiers":[
        {
            "category":"Professional",
            "subcategory":"Art Services",
            "type":"Services"
        }
    ],
    "sg:phone":"+1 509 838 3333",
    "sg:postcode":"99201",
    "sg:province":"WA",
    "sg:tags":[
        "photo",
        "photography",
        "commercial",
        "studio",
        "portrait"
    ],
    "wof:name":"Rick Singer Photography",
    "wof:placetype":"venue"
},
  "geometry": {"coordinates":[-117.419408,47.658973],"type":"Point"}
}