{
  "type": "Feature",
  "properties": {
    "iso:country":"US",
    "sg:address":"12501 43rd Ave NE",
    "sg:city":"Marysville",
    "sg:classifiers":[
        {
            "category":"Retail",
            "subcategory":"Laundry & Dry Cleaning",
            "type":"Services"
        }
    ],
    "sg:phone":"+1 360 653 1925",
    "sg:postcode":"98271",
    "sg:province":"WA",
    "wof:name":"T R Threadworks",
    "wof:placetype":"venue"
},
  "geometry": {"coordinates":[-122.17333000000001,48.109151],"type":"Point"}
}