{
  "type": "Feature",
  "properties": {
    "addr:full":"12715 NE 124th St Kirkland WA 98034",
    "addr:housenumber":"12715",
    "addr:postcode":"98034",
    "addr:street":"Ne 124Th St",
    "iso:country":"US",
    "sg:address":"12715 NE 124th St",
    "sg:city":"Kirkland",
    "sg:classifiers":[
        {
            "category":"Bars & Pubs",
            "type":"Food & Drink"
        },
        {
            "category":"Bars & Pubs",
            "subcategory":"Sports Bar",
            "type":"Food & Drink"
        }
    ],
    "sg:phone":"+1 425 821 7717",
    "sg:postcode":"98034",
    "sg:province":"WA",
    "sg:website":"www.thelucky7.com",
    "wof:name":"Lucky 7 Saloon",
    "wof:placetype":"venue"
},
  "geometry": {"coordinates":[-122.170998,47.7104],"type":"Point"}
}