{
  "type": "Feature",
  "properties": {
    "addr:full":"22210 SE 272nd St Maple Valley WA 98038",
    "addr:postcode":"22210;98038",
    "addr:street":"Se 272Nd St",
    "iso:country":"US",
    "sg:address":"22210 SE 272nd St",
    "sg:city":"Maple Valley",
    "sg:classifiers":[
        {
            "category":"Professional",
            "type":"Services"
        },
        {
            "category":"Personal",
            "subcategory":"Beauty Salon",
            "type":"Services"
        }
    ],
    "sg:phone":"+1 425 433 1212",
    "sg:postcode":"98038",
    "sg:province":"WA",
    "sg:tags":[
        "treatment",
        "skin"
    ],
    "wof:name":"Aesthetic Imagery",
    "wof:placetype":"venue"
},
  "geometry": {"coordinates":[-122.045078,47.358038],"type":"Point"}
}