{
  "type": "Feature",
  "properties": {
    "addr:full":"7412 55th Avenue Ct NW Gig Harbor WA 98335",
    "addr:housenumber":"7412",
    "addr:postcode":"98335",
    "addr:street":"55Th Avenue Ct Nw",
    "iso:country":"US",
    "sg:address":"7412 55th Avenue Ct NW",
    "sg:city":"Gig Harbor",
    "sg:classifiers":[
        {
            "category":"Personal",
            "subcategory":"Beauty Salon",
            "type":"Services"
        }
    ],
    "sg:phone":"+1 253 851 1057",
    "sg:postcode":"98335",
    "sg:province":"WA",
    "sg:tags":[
        "shop"
    ],
    "wof:name":"Beauty Shoppe",
    "wof:placetype":"venue"
},
  "geometry": {"coordinates":[-122.612467,47.324789],"type":"Point"}
}