{
  "type": "Feature",
  "properties": {
    "addr:full":"30613 115th Ct SE Auburn WA 98092",
    "addr:housenumber":"30613",
    "addr:postcode":"98092",
    "addr:street":"115Th Ct Se",
    "iso:country":"US",
    "sg:address":"30613 115th Ct SE",
    "sg:city":"Auburn",
    "sg:classifiers":[
        {
            "category":"Professional",
            "subcategory":"Accounting & Tax Preparation",
            "type":"Services"
        }
    ],
    "sg:phone":"+1 253 804 0604",
    "sg:postcode":"98092",
    "sg:province":"WA",
    "sg:tags":[
        "billing"
    ],
    "wof:name":"Accelerated Medical Dental",
    "wof:placetype":"venue"
},
  "geometry": {"coordinates":[-122.187634,47.32744],"type":"Point"}
}