{
  "type": "Feature",
  "properties": {
    "addr:full":"93 S Jackson St ECM #6075 Seattle WA 98104",
    "addr:housenumber":"93",
    "addr:postcode":"98104",
    "addr:street":"S Jackson St Ecm # 6075",
    "iso:country":"US",
    "sg:address":"93 S Jackson St ECM #6075",
    "sg:city":"Seattle",
    "sg:classifiers":[
        {
            "category":"Professional",
            "subcategory":"Management & Consulting",
            "type":"Services"
        }
    ],
    "sg:phone":"+1 866 733 6665",
    "sg:postcode":"98104",
    "sg:province":"WA",
    "sg:website":"http://redmonk.com",
    "wof:name":"RedMonk",
    "wof:placetype":"venue"
},
  "geometry": {"coordinates":[-122.334913,47.59913],"type":"Point"}
}