{
  "type": "Feature",
  "properties": {
    "addr:full":"420 N Wilbur Ave Walla Walla WA 99362",
    "addr:housenumber":"420",
    "addr:postcode":"99362",
    "addr:street":"N Wilbur Ave",
    "iso:country":"US",
    "sg:address":"420 N Wilbur Ave",
    "sg:city":"Walla Walla",
    "sg:classifiers":[
        {
            "category":"Restaurant",
            "type":"Food & Drink"
        }
    ],
    "sg:menulink":"http://www.allmenus.com/wa/walla-walla-college-place/145355-subway/menu/",
    "sg:phone":"+1 509 525 4292",
    "sg:postcode":"99362",
    "sg:province":"WA",
    "sg:tags":[
        "american",
        "sandwich"
    ],
    "wof:name":"Subway",
    "wof:placetype":"venue"
},
  "geometry": {"coordinates":[-118.30461099999999,46.077303],"type":"Point"}
}