{
  "type": "Feature",
  "properties": {
    "addr:full":"3443 Shincke Rd NE Olympia WA 98506",
    "addr:housenumber":"3443",
    "addr:postcode":"98506",
    "addr:street":"Shincke Rd Ne",
    "iso:country":"US",
    "sg:address":"3443 Shincke Rd NE",
    "sg:city":"Olympia",
    "sg:classifiers":[
        {
            "category":"Professional",
            "subcategory":"Advertising",
            "type":"Services"
        }
    ],
    "sg:phone":"+1 360 456 0591",
    "sg:postcode":"98506",
    "sg:province":"WA",
    "sg:tags":[
        "agency",
        "specialty"
    ],
    "sg:website":"http://first-page-google.com",
    "wof:name":"First Page Google",
    "wof:placetype":"venue"
},
  "geometry": {"coordinates":[-122.846305,47.081972],"type":"Point"}
}