{
  "type": "Feature",
  "properties": {
    "addr:full":"3815 S Union Rd Spokane Valley WA 99206",
    "addr:housenumber":"3815",
    "addr:postcode":"99206",
    "addr:street":"S Union Rd",
    "iso:country":"US",
    "sg:address":"3815 S Union Rd",
    "sg:city":"Spokane Valley",
    "sg:classifiers":[
        {
            "category":"Professional",
            "subcategory":"Engineering",
            "type":"Services"
        }
    ],
    "sg:phone":"+1 509 244 3252",
    "sg:postcode":"99206",
    "sg:province":"WA",
    "sg:tags":[
        "technical",
        "consulting",
        "manufacturing",
        "engineer"
    ],
    "sg:website":"www.virtualtechnologiesltd.com",
    "wof:name":"Virtual Technologies Ltd",
    "wof:placetype":"venue"
},
  "geometry": {"coordinates":[-117.24620299999999,47.62166],"type":"Point"}
}