{
  "type": "Feature",
  "properties": {
    "addr:full":"122 S Monroe St Ste 101 Spokane WA 99201",
    "addr:housenumber":"122",
    "addr:postcode":"99201",
    "addr:street":"S Monroe St Ste 101",
    "iso:country":"US",
    "sg:address":"122 S Monroe St Ste 101",
    "sg:city":"Spokane",
    "sg:classifiers":[
        {
            "category":"Deli",
            "type":"Food & Drink"
        },
        {
            "category":"Restaurant",
            "type":"Food & Drink"
        }
    ],
    "sg:phone":"+1 509 835 4177",
    "sg:postcode":"99201",
    "sg:province":"WA",
    "sg:tags":[
        "delicatessen"
    ],
    "wof:name":"Brooklyn Deli",
    "wof:placetype":"venue"
},
  "geometry": {"coordinates":[-117.426525,47.6561],"type":"Point"}
}