{
  "type": "Feature",
  "properties": {
    "addr:full":"2950 Northrup Way Kirkland WA 98033",
    "addr:housenumber":"2950",
    "addr:postcode":"98033",
    "addr:street":"Northrup Way",
    "iso:country":"US",
    "sg:address":"2950 Northrup Way",
    "sg:city":"Kirkland",
    "sg:classifiers":[
        {
            "category":"Professional",
            "subcategory":"Accounting & Tax Preparation",
            "type":"Services"
        }
    ],
    "sg:phone":"+1 206 284 5001",
    "sg:postcode":"98033",
    "sg:province":"WA",
    "sg:tags":[
        "accountant"
    ],
    "wof:name":"Johnson & Shute Cpas",
    "wof:placetype":"venue"
},
  "geometry": {"coordinates":[-122.195999,47.676701],"type":"Point"}
}