{
  "type": "Feature",
  "properties": {
    "addr:full":"1445 NW 188th St Seattle WA 98177",
    "addr:housenumber":"1445",
    "addr:postcode":"98177",
    "addr:street":"Nw 188Th St",
    "iso:country":"US",
    "sg:address":"1445 NW 188th St",
    "sg:city":"Seattle",
    "sg:classifiers":[
        {
            "category":"Arena",
            "subcategory":"Sports Club",
            "type":"Entertainment"
        }
    ],
    "sg:phone":"+1 206 546 4139",
    "sg:postcode":"98177",
    "sg:province":"WA",
    "wof:name":"Rhino Sports NW",
    "wof:placetype":"venue"
},
  "geometry": {"coordinates":[-122.374438,47.765822],"type":"Point"}
}