{
  "type": "Feature",
  "properties": {
    "addr:full":"14 3rd Ave Zillah WA 98953",
    "addr:housenumber":"14",
    "addr:postcode":"98953",
    "addr:street":"3Rd Ave",
    "iso:country":"US",
    "sg:address":"14 3rd Ave",
    "sg:city":"Zillah",
    "sg:classifiers":[
        {
            "category":"Retail",
            "subcategory":"Repair Shop",
            "type":"Services"
        }
    ],
    "sg:phone":"+1 509 829 6116",
    "sg:postcode":"98953",
    "sg:province":"WA",
    "sg:tags":[
        "electrical"
    ],
    "wof:name":"Mocha Medics",
    "wof:placetype":"venue"
},
  "geometry": {"coordinates":[-120.267413,46.405633],"type":"Point"}
}