{
  "type": "Feature",
  "properties": {
    "addr:full":"7100 Evergreen Way Everett WA 98203",
    "addr:housenumber":"7100",
    "addr:postcode":"98203",
    "addr:street":"Evergreen Way",
    "iso:country":"US",
    "sg:address":"7100 Evergreen Way",
    "sg:city":"Everett",
    "sg:classifiers":[
        {
            "category":"Social Services",
            "type":"Services"
        }
    ],
    "sg:phone":"+1 425 513 2879",
    "sg:postcode":"98203",
    "sg:province":"WA",
    "sg:tags":[
        "information",
        "abuse",
        "domestic",
        "treatment"
    ],
    "wof:name":"Phoenix Counseling Services",
    "wof:placetype":"venue"
},
  "geometry": {"coordinates":[-122.219859,47.933609],"type":"Point"}
}