{
  "type": "Feature",
  "properties": {
    "addr:full":"111 Village Way Port Ludlow WA 98365",
    "addr:housenumber":"111",
    "addr:postcode":"98365",
    "addr:street":"Village Way",
    "iso:country":"US",
    "sg:address":"111 Village Way",
    "sg:city":"Port Ludlow",
    "sg:classifiers":[
        {
            "category":"Building & Trades",
            "subcategory":"Construction",
            "type":"Services"
        }
    ],
    "sg:phone":"+1 360 437 2501",
    "sg:postcode":"98365",
    "sg:province":"WA",
    "sg:tags":[
        "general",
        "contractor"
    ],
    "wof:name":"Lander Custom Designed Homes",
    "wof:placetype":"venue"
},
  "geometry": {"coordinates":[-122.703385,47.920243],"type":"Point"}
}