{
  "type": "Feature",
  "properties": {
    "addr:full":"23025 165th Ave SE Monroe WA 98272",
    "addr:housenumber":"23025",
    "addr:postcode":"98272",
    "addr:street":"165Th Ave Se",
    "iso:country":"US",
    "sg:address":"23025 165th Ave SE",
    "sg:city":"Monroe",
    "sg:classifiers":[
        {
            "category":"Building & Trades",
            "subcategory":"Construction",
            "type":"Services"
        }
    ],
    "sg:phone":"+1 360 863 9382",
    "sg:postcode":"98272",
    "sg:province":"WA",
    "sg:tags":[
        "installs",
        "hardware",
        "control",
        "access",
        "door"
    ],
    "wof:name":"Western Entrance Technology",
    "wof:placetype":"venue"
},
  "geometry": {"coordinates":[-122.010165,47.787986],"type":"Point"}
}