{
  "type": "Feature",
  "properties": {
    "addr:full":"3617 241st Ave SE Issaquah WA 98029",
    "addr:housenumber":"3617",
    "addr:postcode":"98029",
    "addr:street":"241St Ave Se",
    "iso:country":"US",
    "sg:address":"3617 241st Ave SE",
    "sg:city":"Issaquah",
    "sg:classifiers":[
        {
            "category":"Organizations",
            "subcategory":"Membership Organization",
            "type":"Services"
        }
    ],
    "sg:phone":"+1 425 427 9464",
    "sg:postcode":"98029",
    "sg:province":"WA",
    "wof:name":"Gfwc Eastside Womens Club",
    "wof:placetype":"venue"
},
  "geometry": {"coordinates":[-122.018462,47.579977],"type":"Point"}
}