{
  "type": "Feature",
  "properties": {
    "addr:full":"500 W Market St Aberdeen WA 98520",
    "addr:housenumber":"500",
    "addr:postcode":"98520",
    "addr:street":"W Market St",
    "iso:country":"US",
    "sg:address":"500 W Market St",
    "sg:city":"Aberdeen",
    "sg:classifiers":[
        {
            "category":"Health Services",
            "subcategory":"Optometrist",
            "type":"Services"
        }
    ],
    "sg:phone":"+1 360 532 3611",
    "sg:postcode":"98520",
    "sg:province":"WA",
    "wof:name":"Gregory G Bogdanovich OD",
    "wof:placetype":"venue"
},
  "geometry": {"coordinates":[-123.82353500000001,46.972617],"type":"Point"}
}