{
  "type": "Feature",
  "properties": {
    "addr:full":"118 E 4th Ave Ellensburg WA 98926",
    "addr:housenumber":"118",
    "addr:postcode":"98926",
    "addr:street":"E 4Th Ave",
    "iso:country":"US",
    "sg:address":"118 E 4th Ave",
    "sg:city":"Ellensburg",
    "sg:classifiers":[
        {
            "category":"Shopping",
            "subcategory":"Clothing, Apparel, & Fashions",
            "type":"Retail Goods"
        }
    ],
    "sg:phone":"+1 509 925 1272",
    "sg:postcode":"98926",
    "sg:province":"WA",
    "sg:tags":[
        "machine",
        "boy",
        "sewing"
    ],
    "wof:name":"Mosers Clothing",
    "wof:placetype":"venue"
},
  "geometry": {"coordinates":[-120.54606,46.995445],"type":"Point"}
}