{
  "type": "Feature",
  "properties": {
    "addr:full":"311 NE 103rd St Seattle WA 98125",
    "addr:housenumber":"311",
    "addr:postcode":"98125",
    "addr:street":"Ne 103Rd St",
    "iso:country":"US",
    "sg:address":"311 NE 103rd St",
    "sg:city":"Seattle",
    "sg:classifiers":[
        {
            "category":"Fast Food",
            "type":"Food & Drink"
        },
        {
            "category":"Food & Beverages",
            "subcategory":"Meat & Fish",
            "type":"Retail Goods"
        }
    ],
    "sg:phone":"+1 206 729 5028",
    "sg:postcode":"98125",
    "sg:province":"WA",
    "sg:tags":[
        "burger",
        "hot",
        "dog"
    ],
    "sg:website":"www.fiveguys.com/index.aspx",
    "wof:name":"Five Guys Burgers & Fries",
    "wof:placetype":"venue"
},
  "geometry": {"coordinates":[-122.325706,47.703149],"type":"Point"}
}