{
  "type": "Feature",
  "properties": {
    "addr:full":"208 S 4th Ave Yakima WA 98902",
    "addr:housenumber":"208",
    "addr:postcode":"98902",
    "addr:street":"S 4Th Ave",
    "iso:country":"US",
    "sg:address":"208 S 4th Ave",
    "sg:city":"Yakima",
    "sg:classifiers":[
        {
            "category":"Retail",
            "subcategory":"Auto Repair",
            "type":"Services"
        }
    ],
    "sg:phone":"+1 509 453 7714",
    "sg:postcode":"98902",
    "sg:province":"WA",
    "sg:tags":[
        "truck",
        "general"
    ],
    "wof:name":"Brand's Truck Repair",
    "wof:placetype":"venue"
},
  "geometry": {"coordinates":[-120.512381,46.596689],"type":"Point"}
}