{
  "type": "Feature",
  "properties": {
    "addr:full":"19221 SE 34th Vancouver WA 98660",
    "addr:housenumber":"19221",
    "addr:postcode":"98660",
    "addr:street":"Se 34Th",
    "iso:country":"US",
    "sg:address":"19221 SE 34th",
    "sg:city":"Vancouver",
    "sg:classifiers":[
        {
            "category":"Retail",
            "subcategory":"Laundry & Dry Cleaning",
            "type":"Services"
        }
    ],
    "sg:phone":"+1 360 883 1488",
    "sg:postcode":"98660",
    "sg:province":"WA",
    "wof:name":"Stanford Cleaners 2",
    "wof:placetype":"venue"
},
  "geometry": {"coordinates":[-122.683998,45.644699],"type":"Point"}
}