{
  "type": "Feature",
  "properties": {
    "addr:full":"2000 E 10th St Bremerton WA 98310",
    "addr:housenumber":"2000",
    "addr:postcode":"98310",
    "addr:street":"E 10Th St",
    "iso:country":"US",
    "sg:address":"2000 E 10th St",
    "sg:city":"Bremerton",
    "sg:classifiers":[
        {
            "category":"Health Services",
            "subcategory":"Medical Lab",
            "type":"Services"
        }
    ],
    "sg:phone":"+1 360 377 7997",
    "sg:postcode":"98310",
    "sg:province":"WA",
    "sg:tags":[
        "laboratory",
        "dental"
    ],
    "wof:name":"Accufit Laboratories",
    "wof:placetype":"venue"
},
  "geometry": {"coordinates":[-122.61500100000001,47.569461],"type":"Point"}
}