{
  "type": "Feature",
  "properties": {
    "addr:full":"314 Martin Luther King Jr Way Tacoma WA 98405",
    "addr:housenumber":"314",
    "addr:postcode":"98405",
    "addr:street":"Martin Luther King Jr Way",
    "iso:country":"US",
    "sg:address":"314 Martin Luther King Jr Way",
    "sg:city":"Tacoma",
    "sg:classifiers":[
        {
            "category":"Health Services",
            "subcategory":"Nursing And Care Facility",
            "type":"Services"
        }
    ],
    "sg:phone":"+1 253 272 5572",
    "sg:postcode":"98405",
    "sg:province":"WA",
    "sg:tags":[
        "nurse",
        "practice-arnp",
        "nurses-advanced"
    ],
    "wof:name":"Weatherby Shauna Arnp",
    "wof:placetype":"venue"
},
  "geometry": {"coordinates":[-122.45355600000001,47.260129],"type":"Point"}
}