{
  "type": "Feature",
  "properties": {
    "addr:full":"606 W Boeing St Pasco WA 99301",
    "addr:housenumber":"606",
    "addr:postcode":"99301",
    "addr:street":"W Boeing St",
    "iso:country":"US",
    "sg:address":"606 W Boeing St",
    "sg:city":"Pasco",
    "sg:classifiers":[
        {
            "category":"Autos & Motor Vehicles",
            "subcategory":"Auto Supplies",
            "type":"Retail Goods"
        }
    ],
    "sg:phone":"+1 509 547 6000",
    "sg:postcode":"99301",
    "sg:province":"WA",
    "wof:name":"A A W Auto Parts",
    "wof:placetype":"venue"
},
  "geometry": {"coordinates":[-119.100043,46.25961],"type":"Point"}
}