{
  "type": "Feature",
  "properties": {
    "addr:full":"9104 S Tacoma Way Lakewood WA 98499",
    "addr:housenumber":"9104",
    "addr:postcode":"98499",
    "addr:street":"S Tacoma Way",
    "iso:country":"US",
    "sg:address":"9104 S Tacoma Way",
    "sg:city":"Lakewood",
    "sg:classifiers":[
        {
            "category":"Home & Garden",
            "subcategory":"Furniture",
            "type":"Retail Goods"
        }
    ],
    "sg:phone":"+1 253 582 3111",
    "sg:postcode":"98499",
    "sg:province":"WA",
    "sg:tags":[
        "bedding"
    ],
    "wof:name":"Hefel",
    "wof:placetype":"venue"
},
  "geometry": {"coordinates":[-122.483824,47.173932],"type":"Point"}
}