{
  "type": "Feature",
  "properties": {
    "addr:full":"2313 10th Ave E Seattle WA 98102",
    "addr:housenumber":"2313",
    "addr:postcode":"98102",
    "addr:street":"10Th Ave E",
    "iso:country":"US",
    "sg:address":"2313 10th Ave E",
    "sg:city":"Seattle",
    "sg:classifiers":[
        {
            "category":"Social Services",
            "type":"Services"
        }
    ],
    "sg:phone":"+1 206 903 9195",
    "sg:postcode":"98102",
    "sg:province":"WA",
    "sg:tags":[
        "counselor",
        "marriage",
        "family"
    ],
    "wof:name":"Accessible Low Cost Therapy",
    "wof:placetype":"venue"
},
  "geometry": {"coordinates":[-122.32013499999999,47.641131],"type":"Point"}
}