{
  "type": "Feature",
  "properties": {
    "addr:full":"1618 E Aloha Street Seattle WA 98112",
    "addr:housenumber":"1618",
    "addr:postcode":"98112",
    "addr:street":"E Aloha Street",
    "iso:country":"US",
    "sg:address":"1618 E Aloha Street",
    "sg:city":"Seattle",
    "sg:classifiers":[
        {
            "category":"Health Services",
            "subcategory":"Doctor",
            "type":"Services"
        }
    ],
    "sg:phone":"+1 206 329 5439",
    "sg:postcode":"98112",
    "sg:province":"WA",
    "wof:name":"Hinton W Ladson MD III",
    "wof:placetype":"venue"
},
  "geometry": {"coordinates":[-122.311053,47.626775],"type":"Point"}
}