{
  "type": "Feature",
  "properties": {
    "addr:full":"17606 Highland View Dr Arlington WA 98223",
    "addr:housenumber":"17606",
    "addr:postcode":"98223",
    "addr:street":"Highland View Dr",
    "iso:country":"US",
    "sg:address":"17606 Highland View Dr",
    "sg:city":"Arlington",
    "sg:classifiers":[
        {
            "category":"Shopping",
            "subcategory":"Beauty & Cosmetics",
            "type":"Retail Goods"
        }
    ],
    "sg:phone":"+1 360 403 7753",
    "sg:postcode":"98223",
    "sg:province":"WA",
    "sg:tags":[
        "merchandise"
    ],
    "wof:name":"Your Image",
    "wof:placetype":"venue"
},
  "geometry": {"coordinates":[-122.136396,48.157758],"type":"Point"}
}