{
  "type": "Feature",
  "properties": {
    "addr:full":"18040 Fir Island Rd Mount Vernon WA 98273",
    "addr:housenumber":"18040",
    "addr:postcode":"98273",
    "addr:street":"Fir Island Rd",
    "iso:country":"US",
    "sg:address":"18040 Fir Island Rd",
    "sg:city":"Mount Vernon",
    "sg:classifiers":[
        {
            "category":"Shopping",
            "subcategory":"Used Merchandise",
            "type":"Retail Goods"
        }
    ],
    "sg:phone":"+1 360 445 2010",
    "sg:postcode":"98273",
    "sg:province":"WA",
    "wof:name":"Trumpeter Antiques",
    "wof:placetype":"venue"
},
  "geometry": {"coordinates":[-122.354265,48.341215],"type":"Point"}
}