{
  "type": "Feature",
  "properties": {
    "addr:full":"1405 Gulf Rd Point Roberts WA 98281",
    "addr:housenumber":"1405",
    "addr:postcode":"98281",
    "addr:street":"Gulf Rd",
    "iso:country":"US",
    "sg:address":"1405 Gulf Rd",
    "sg:city":"Point Roberts",
    "sg:classifiers":[
        {
            "category":"Food & Beverages",
            "subcategory":"Liquor & Beverages",
            "type":"Retail Goods"
        }
    ],
    "sg:phone":"+1 360 945 6311",
    "sg:postcode":"98281",
    "sg:province":"WA",
    "sg:tags":[
        "wine"
    ],
    "wof:name":"Liberty Merchant Wine Co",
    "wof:placetype":"venue"
},
  "geometry": {"coordinates":[-123.07667600000001,48.984595],"type":"Point"}
}