{
  "type": "Feature",
  "properties": {
    "addr:full":"591 E North Bay Rd Belfair WA 98528",
    "addr:housenumber":"591",
    "addr:postcode":"98528",
    "addr:street":"E North Bay Rd",
    "iso:country":"US",
    "sg:address":"591 E North Bay Rd",
    "sg:city":"Belfair",
    "sg:classifiers":[
        {
            "category":"Building & Trades",
            "subcategory":"Construction",
            "type":"Services"
        }
    ],
    "sg:phone":"+1 360 277 0912",
    "sg:postcode":"98528",
    "sg:province":"WA",
    "sg:tags":[
        "hanging",
        "contractor"
    ],
    "wof:name":"Superior Paintworks",
    "wof:placetype":"venue"
},
  "geometry": {"coordinates":[-122.824814,47.392641],"type":"Point"}
}