{
  "type": "Feature",
  "properties": {
    "addr:full":"3607 35th Ave W Seattle WA 98199",
    "addr:housenumber":"3607",
    "addr:postcode":"98199",
    "addr:street":"35Th Ave W",
    "iso:country":"US",
    "sg:address":"3607 35th Ave W",
    "sg:city":"Seattle",
    "sg:classifiers":[
        {
            "category":"Professional",
            "subcategory":"Advertising",
            "type":"Services"
        }
    ],
    "sg:phone":"+1 206 355 6919",
    "sg:postcode":"98199",
    "sg:province":"WA",
    "sg:tags":[
        "agency"
    ],
    "wof:name":"Tone Def Radio",
    "wof:placetype":"venue"
},
  "geometry": {"coordinates":[-122.40235199999999,47.653995],"type":"Point"}
}