{
  "type": "Feature",
  "properties": {
    "addr:full":"12607 NE 85th St Kirkland WA 98033",
    "addr:housenumber":"12607",
    "addr:postcode":"98033",
    "addr:street":"Ne 85Th St",
    "iso:country":"US",
    "sg:address":"12607 NE 85th St",
    "sg:city":"Kirkland",
    "sg:classifiers":[
        {
            "category":"Food & Beverages",
            "subcategory":"Groceries & Convenience Stores",
            "type":"Retail Goods"
        }
    ],
    "sg:phone":"+1 425 803 3858",
    "sg:postcode":"98033",
    "sg:province":"WA",
    "wof:name":"Bedrock Northwest Chevron",
    "wof:placetype":"venue"
},
  "geometry": {"coordinates":[-122.172997,47.679501],"type":"Point"}
}