{
  "type": "Feature",
  "properties": {
    "addr:full":"9287 NE 125th Pl Kirkland WA 98034",
    "addr:housenumber":"9287",
    "addr:postcode":"98034",
    "addr:street":"Ne 125Th Pl",
    "iso:country":"US",
    "sg:address":"9287 NE 125th Pl",
    "sg:city":"Kirkland",
    "sg:classifiers":[
        {
            "category":"Organizations",
            "subcategory":"Religious Organization",
            "type":"Services"
        }
    ],
    "sg:phone":"+1 425 820 0736",
    "sg:postcode":"98034",
    "sg:province":"WA",
    "sg:tags":[
        "clergy"
    ],
    "wof:name":"Anderson Michael J Rev S Patty Lee",
    "wof:placetype":"venue"
},
  "geometry": {"coordinates":[-122.218751,47.712776],"type":"Point"}
}