{
  "type": "Feature",
  "properties": {
    "addr:full":"4803 103rd Pl SW Mukilteo WA 98275",
    "addr:housenumber":"4803",
    "addr:postcode":"98275",
    "addr:street":"103Rd Pl Sw",
    "iso:country":"US",
    "sg:address":"4803 103rd Pl SW",
    "sg:city":"Mukilteo",
    "sg:classifiers":[
        {
            "category":"Building & Trades",
            "subcategory":"Cleaning & Sanitation",
            "type":"Services"
        }
    ],
    "sg:phone":"+1 425 349 3226",
    "sg:postcode":"98275",
    "sg:province":"WA",
    "sg:tags":[
        "maintenance"
    ],
    "wof:name":"Aceys Window Cleaning",
    "wof:placetype":"venue"
},
  "geometry": {"coordinates":[-122.29834099999999,47.905494],"type":"Point"}
}