{
  "type": "Feature",
  "properties": {
    "addr:full":"406 N 3rd St Cheney WA 99004",
    "addr:housenumber":"406",
    "addr:postcode":"99004",
    "addr:street":"N 3Rd St",
    "iso:country":"US",
    "sg:address":"406 N 3rd St",
    "sg:city":"Cheney",
    "sg:classifiers":[
        {
            "category":"Building & Trades",
            "subcategory":"Cleaning & Sanitation",
            "type":"Services"
        }
    ],
    "sg:phone":"+1 509 235 8401",
    "sg:postcode":"99004",
    "sg:province":"WA",
    "sg:tags":[
        "janitor"
    ],
    "wof:name":"LA France Enterprises",
    "wof:placetype":"venue"
},
  "geometry": {"coordinates":[-117.571549,47.497269],"type":"Point"}
}