{
  "type": "Feature",
  "properties": {
    "addr:full":"2500 E College Way Mount Vernon WA 98273",
    "addr:housenumber":"2500",
    "addr:postcode":"98273",
    "addr:street":"E College Way",
    "iso:country":"US",
    "sg:address":"2500 E College Way",
    "sg:city":"Mount Vernon",
    "sg:classifiers":[
        {
            "category":"Farming",
            "subcategory":"Farm & Veterinary Services",
            "type":"Manufacturing & Wholesale Goods"
        }
    ],
    "sg:phone":"+1 360 416 0339",
    "sg:postcode":"98273",
    "sg:province":"WA",
    "sg:tags":[
        "livestock"
    ],
    "wof:name":"Evergreen Contract Services",
    "wof:placetype":"venue"
},
  "geometry": {"coordinates":[-122.311114,48.435532],"type":"Point"}
}