{
  "type": "Feature",
  "properties": {
    "addr:full":"4444 Lacey Blvd SE Ste E Lacey WA 98503",
    "addr:housenumber":"4444",
    "addr:postcode":"98503",
    "addr:street":"Lacey Blvd Se Ste E",
    "iso:country":"US",
    "sg:address":"4444 Lacey Blvd SE Ste E",
    "sg:city":"Lacey",
    "sg:classifiers":[
        {
            "category":"Health Services",
            "subcategory":"Chiropractor",
            "type":"Services"
        }
    ],
    "sg:phone":"+1 360 438 1998",
    "sg:postcode":"98503",
    "sg:province":"WA",
    "sg:tags":[
        "chiropractic"
    ],
    "wof:name":"Friedly Howard DC",
    "wof:placetype":"venue"
},
  "geometry": {"coordinates":[-122.827923,47.037308],"type":"Point"}
}