{
  "type": "Feature",
  "properties": {
    "addr:full":"10900 NE 4th St Ste 1910 Bellevue WA 98004",
    "addr:housenumber":"10900",
    "addr:postcode":"98004",
    "addr:street":"Ne 4Th St Ste 1910",
    "iso:country":"US",
    "sg:address":"10900 NE 4th St Ste 1910",
    "sg:city":"Bellevue",
    "sg:classifiers":[
        {
            "category":"Professional",
            "subcategory":"Lawyer & Legal Services",
            "type":"Services"
        }
    ],
    "sg:phone":"+1 425 688 7620",
    "sg:postcode":"98004",
    "sg:province":"WA",
    "sg:website":"www.walterslawfirm.com",
    "wof:name":"Walters Law Firm",
    "wof:placetype":"venue"
},
  "geometry": {"coordinates":[-122.194884,47.613937],"type":"Point"}
}