{
  "type": "Feature",
  "properties": {
    "addr:full":"2222 SE 283rd Ave Camas WA 98607",
    "addr:housenumber":"2222",
    "addr:postcode":"98607",
    "addr:street":"Se 283Rd Ave",
    "iso:country":"US",
    "sg:address":"2222 SE 283rd Ave",
    "sg:city":"Camas",
    "sg:classifiers":[
        {
            "category":"Arts & Performance",
            "subcategory":"Theater",
            "type":"Entertainment"
        }
    ],
    "sg:phone":"+1 360 834 1901",
    "sg:postcode":"98607",
    "sg:province":"WA",
    "sg:tags":[
        "group"
    ],
    "wof:name":"Harp By Lena",
    "wof:placetype":"venue"
},
  "geometry": {"coordinates":[-122.382638,45.604131],"type":"Point"}
}