{
  "type": "Feature",
  "properties": {
    "addr:full":"11425 81st Ave NE Kirkland WA 98034",
    "addr:housenumber":"11425",
    "addr:postcode":"98034",
    "addr:street":"81St Ave Ne",
    "iso:country":"US",
    "sg:address":"11425 81st Ave NE",
    "sg:city":"Kirkland",
    "sg:classifiers":[
        {
            "category":"Building & Trades",
            "subcategory":"Construction",
            "type":"Services"
        }
    ],
    "sg:phone":"+1 425 821 6018",
    "sg:postcode":"98034",
    "sg:province":"WA",
    "sg:tags":[
        "hanging",
        "contractor"
    ],
    "wof:name":"Custom Hse Pntg & Wallpapering",
    "wof:placetype":"venue"
},
  "geometry": {"coordinates":[-122.232792,47.701227],"type":"Point"}
}