{
  "type": "Feature",
  "properties": {
    "addr:full":"1707 Boylston Avenue Seattle WA 98122",
    "addr:housenumber":"1707",
    "addr:postcode":"98122",
    "addr:street":"Boylston Avenue",
    "iso:country":"US",
    "sg:address":"1707 Boylston Avenue",
    "sg:city":"Seattle",
    "sg:classifiers":[
        {
            "category":"Professional",
            "type":"Services"
        },
        {
            "category":"Communications",
            "type":"Services"
        }
    ],
    "sg:phone":"+1 206 595 8816",
    "sg:postcode":"98122",
    "sg:province":"WA",
    "sg:tags":[
        "medium",
        "mass"
    ],
    "sg:website":"www.jimmypopllc.com",
    "wof:name":"JimmyPOP",
    "wof:placetype":"venue"
},
  "geometry": {"coordinates":[-122.323545,47.616655],"type":"Point"}
}