{
  "type": "Feature",
  "properties": {
    "addr:full":"101 NE 58th St Seattle WA 98105",
    "addr:housenumber":"101",
    "addr:postcode":"98105",
    "addr:street":"Ne 58Th St",
    "iso:country":"US",
    "sg:address":"101 NE 58th St",
    "sg:city":"Seattle",
    "sg:classifiers":[
        {
            "category":"Education",
            "subcategory":"School",
            "type":"Public Place"
        }
    ],
    "sg:phone":"+1 206 524 7564",
    "sg:postcode":"98105",
    "sg:province":"WA",
    "wof:name":"Rebecca Rueter Reiki",
    "wof:placetype":"venue"
},
  "geometry": {"coordinates":[-122.325532,47.670835],"type":"Point"}
}