{
  "type": "Feature",
  "properties": {
    "addr:full":"8305 25th Ave NW Seattle WA 98117",
    "addr:housenumber":"8305",
    "addr:postcode":"98117",
    "addr:street":"25Th Ave Nw",
    "iso:country":"US",
    "sg:address":"8305 25th Ave NW",
    "sg:city":"Seattle",
    "sg:classifiers":[
        {
            "category":"Autos & Motor Vehicles",
            "subcategory":"Automobile Sales",
            "type":"Retail Goods"
        }
    ],
    "sg:phone":"+1 206 497 3197",
    "sg:postcode":"98117",
    "sg:province":"WA",
    "sg:tags":[
        "automotive"
    ],
    "sg:website":"www.fsboautoadvisor.com",
    "wof:name":"FSBO Auto Advisor",
    "wof:placetype":"venue"
},
  "geometry": {"coordinates":[-122.389025,47.689246],"type":"Point"}
}