{
  "type": "Feature",
  "properties": {
    "addr:full":"6903 4th Way SE Lacey WA 98503",
    "addr:housenumber":"6903",
    "addr:postcode":"98503",
    "addr:street":"4Th Way Se",
    "iso:country":"US",
    "sg:address":"6903 4th Way SE",
    "sg:city":"Lacey",
    "sg:classifiers":[
        {
            "category":"Professional",
            "type":"Services"
        }
    ],
    "sg:phone":"+1 360 951 6714",
    "sg:postcode":"98503",
    "sg:province":"WA",
    "wof:name":"Sounds Fine",
    "wof:placetype":"venue"
},
  "geometry": {"coordinates":[-122.787862,47.048256],"type":"Point"}
}