{
  "type": "Feature",
  "properties": {
    "addr:full":"14550 NE 20th St Bellevue WA 98007",
    "addr:housenumber":"14550",
    "addr:postcode":"98007",
    "addr:street":"Ne 20Th St",
    "iso:country":"US",
    "sg:address":"14550 NE 20th St",
    "sg:city":"Bellevue",
    "sg:classifiers":[
        {
            "category":"Professional",
            "subcategory":"Management & Consulting",
            "type":"Services"
        }
    ],
    "sg:phone":"+1 425 765 5248",
    "sg:postcode":"98007",
    "sg:province":"WA",
    "wof:name":"Mk2 Inc",
    "wof:placetype":"venue"
},
  "geometry": {"coordinates":[-122.14724099999999,47.627992],"type":"Point"}
}