{
  "type": "Feature",
  "properties": {
    "addr:full":"7009 California Ave SW West Seattle WA 98136",
    "addr:housenumber":"7009",
    "addr:postcode":"98136",
    "addr:street":"California Ave Sw",
    "iso:country":"US",
    "sg:address":"7009 California Ave SW",
    "sg:city":"West Seattle",
    "sg:classifiers":[
        {
            "category":"Personal",
            "subcategory":"Beauty Salon",
            "type":"Services"
        }
    ],
    "sg:phone":"+1 206 932 1760",
    "sg:postcode":"98136",
    "sg:province":"WA",
    "sg:tags":[
        "hair"
    ],
    "sg:website":"www.christophersalonseattle.com/...",
    "wof:name":"Christopher's Salon & Massage",
    "wof:placetype":"venue"
},
  "geometry": {"coordinates":[-122.38745299999999,47.540416],"type":"Point"}
}