{
  "type": "Feature",
  "properties": {
    "addr:full":"512 E Yelm Ave Yelm WA 98597",
    "addr:housenumber":"512",
    "addr:postcode":"98597",
    "addr:street":"E Yelm Ave",
    "iso:country":"US",
    "sg:address":"512 E Yelm Ave",
    "sg:city":"Yelm",
    "sg:classifiers":[
        {
            "category":"Building & Trades",
            "subcategory":"Construction",
            "type":"Services"
        }
    ],
    "sg:phone":"+1 360 458 8744",
    "sg:postcode":"98597",
    "sg:province":"WA",
    "sg:tags":[
        "house"
    ],
    "wof:name":"Cunningham Construction",
    "wof:placetype":"venue"
},
  "geometry": {"coordinates":[-122.60123,46.938781],"type":"Point"}
}