{
  "type": "Feature",
  "properties": {
    "addr:full":"311 First Ave S Suite 306 Seattle WA 98104",
    "addr:housenumber":"311",
    "addr:postcode":"98104",
    "addr:street":"First Ave S Suite 306",
    "iso:country":"US",
    "sg:address":"311 First Ave S Suite 306",
    "sg:city":"Seattle",
    "sg:classifiers":[
        {
            "category":"Personal",
            "subcategory":"Massage",
            "type":"Services"
        }
    ],
    "sg:phone":"+1 206 381 1557",
    "sg:postcode":"98104",
    "sg:province":"WA",
    "sg:website":"www.meghanhintz.com",
    "wof:name":"Meghan Hintz Lmp",
    "wof:placetype":"venue"
},
  "geometry": {"coordinates":[-122.33458400000001,47.599664],"type":"Point"}
}