{
  "type": "Feature",
  "properties": {
    "addr:full":"1525 Clematis Ct Lynden WA 98264",
    "addr:housenumber":"1525",
    "addr:postcode":"98264",
    "addr:street":"Clematis Ct",
    "iso:country":"US",
    "sg:address":"1525 Clematis Ct",
    "sg:city":"Lynden",
    "sg:classifiers":[
        {
            "category":"Building & Trades",
            "subcategory":"Construction",
            "type":"Services"
        }
    ],
    "sg:phone":"+1 360 354 0940",
    "sg:postcode":"98264",
    "sg:province":"WA",
    "sg:tags":[
        "general",
        "contractor"
    ],
    "wof:name":"Mgh Inc",
    "wof:placetype":"venue"
},
  "geometry": {"coordinates":[-122.456693,48.956758],"type":"Point"}
}