{
  "type": "Feature",
  "properties": {
    "addr:full":"163 Nichols Rd Omak WA 98841",
    "addr:housenumber":"163",
    "addr:postcode":"98841",
    "addr:street":"Nichols Rd",
    "iso:country":"US",
    "sg:address":"163 Nichols Rd",
    "sg:city":"Omak",
    "sg:classifiers":[
        {
            "category":"Restaurant",
            "type":"Food & Drink"
        },
        {
            "category":"Retail",
            "subcategory":"Event Space",
            "type":"Services"
        }
    ],
    "sg:phone":"+1 509 826 2325",
    "sg:postcode":"98841",
    "sg:province":"WA",
    "sg:tags":[
        "style",
        "family",
        "facility",
        "hall",
        "reception",
        "banquet"
    ],
    "wof:name":"Magoo's Restaurant",
    "wof:placetype":"venue"
},
  "geometry": {"coordinates":[-119.507801,48.438549],"type":"Point"}
}