{
  "type": "Feature",
  "properties": {
    "addr:full":"19514 64th Ave W Lynnwood WA 98036",
    "addr:housenumber":"19514",
    "addr:postcode":"98036",
    "addr:street":"64Th Ave W",
    "iso:country":"US",
    "sg:address":"19514 64th Ave W",
    "sg:city":"Lynnwood",
    "sg:classifiers":[
        {
            "category":"Health Services",
            "subcategory":"Clinic",
            "type":"Services"
        },
        {
            "category":"Health Services",
            "subcategory":"Health Practitioner",
            "type":"Services"
        }
    ],
    "sg:phone":"+1 425 744 1679",
    "sg:postcode":"98036",
    "sg:province":"WA",
    "sg:tags":[
        "physician",
        "naturopathic",
        "nd",
        "medicine",
        "acupuncture",
        "alternative"
    ],
    "sg:website":"http://www.vitalishealthcenter.com",
    "wof:name":"Suzanne Way ND LAc - Vitalis Natural Health Center",
    "wof:placetype":"venue"
},
  "geometry": {"coordinates":[-122.319626,47.821722],"type":"Point"}
}