{
  "type": "Feature",
  "properties": {
    "addr:full":"420 Mount Vernon Terminal RR Mt Vernon WA 98273",
    "addr:housenumber":"420",
    "addr:postcode":"98273",
    "addr:street":"Mount;Vernon",
    "iso:country":"US",
    "sg:address":"420 Mount Vernon Terminal RR",
    "sg:city":"Mt Vernon",
    "sg:classifiers":[
        {
            "category":"Shopping",
            "subcategory":"Crafts & Fabrics",
            "type":"Retail Goods"
        }
    ],
    "sg:phone":"+1 360 424 8772",
    "sg:postcode":"98273",
    "sg:province":"WA",
    "sg:tags":[
        "shop"
    ],
    "wof:name":"Jo-Ann Fabrics & Crafts",
    "wof:placetype":"venue"
},
  "geometry": {"coordinates":[-122.33844000000001,48.420183],"type":"Point"}
}