{
  "type": "Feature",
  "properties": {
    "addr:full":"34875 Park Lake Rd NE Coulee City WA 99115",
    "addr:housenumber":"34875",
    "addr:postcode":"99115",
    "addr:street":"Park Lake Rd Ne",
    "iso:country":"US",
    "sg:address":"34875 Park Lake Rd NE",
    "sg:city":"Coulee City",
    "sg:classifiers":[
        {
            "category":"Government",
            "subcategory":"Office",
            "type":"Public Place"
        }
    ],
    "sg:phone":"+1 509 632 5583",
    "sg:postcode":"99115",
    "sg:province":"WA",
    "sg:tags":[
        "conservation",
        "trailer"
    ],
    "wof:name":"Sun Lakes State Park",
    "wof:placetype":"venue"
},
  "geometry": {"coordinates":[-119.39315000000001,47.590903],"type":"Point"}
}