{
  "type": "Feature",
  "properties": {
    "addr:full":"507 N 3rd St Tacoma WA 98403",
    "addr:housenumber":"507",
    "addr:postcode":"98403",
    "addr:street":"N 3Rd St",
    "iso:country":"US",
    "sg:address":"507 N 3rd St",
    "sg:city":"Tacoma",
    "sg:classifiers":[
        {
            "category":"Professional",
            "type":"Services"
        }
    ],
    "sg:phone":"+1 253 627 4356",
    "sg:postcode":"98403",
    "sg:province":"WA",
    "wof:name":"Richard B and Barbara B O",
    "wof:placetype":"venue"
},
  "geometry": {"coordinates":[-122.451262,47.265587],"type":"Point"}
}