{
  "type": "Feature",
  "properties": {
    "addr:full":"181 Jessica Ln Yakima WA 98908",
    "addr:housenumber":"181",
    "addr:postcode":"98908",
    "addr:street":"Jessica Ln",
    "iso:country":"US",
    "sg:address":"181 Jessica Ln",
    "sg:city":"Yakima",
    "sg:classifiers":[
        {
            "category":"Manufacturing",
            "subcategory":"Metals",
            "type":"Manufacturing & Wholesale Goods"
        }
    ],
    "sg:phone":"+1 509 969 9029",
    "sg:postcode":"98908",
    "sg:province":"WA",
    "sg:tags":[
        "ornamental",
        "structural",
        "work",
        "metalwork",
        "mfg"
    ],
    "wof:name":"A A Artistic Metal Works",
    "wof:placetype":"venue"
},
  "geometry": {"coordinates":[-120.705045,46.584513],"type":"Point"}
}