{
  "type": "Feature",
  "properties": {
    "addr:full":"21 Orchard Rite Rd Yakima WA 98908",
    "addr:housenumber":"21",
    "addr:postcode":"98908",
    "addr:street":"Orchard Rite Rd",
    "iso:country":"US",
    "sg:address":"21 Orchard Rite Rd",
    "sg:city":"Yakima",
    "sg:classifiers":[
        {
            "category":"Banks & Credit Unions",
            "subcategory":"Investment Brokerage",
            "type":"Services"
        }
    ],
    "sg:phone":"+1 509 966 7551",
    "sg:postcode":"98908",
    "sg:province":"WA",
    "sg:tags":[
        "security"
    ],
    "wof:name":"Market America",
    "wof:placetype":"venue"
},
  "geometry": {"coordinates":[-120.63137500000001,46.670957],"type":"Point"}
}