{
  "type": "Feature",
  "properties": {
    "addr:full":"501 NE Roessel Rd Belfair WA 98528",
    "addr:housenumber":"501",
    "addr:postcode":"98528",
    "addr:street":"Ne Roessel Rd",
    "iso:country":"US",
    "sg:address":"501 NE Roessel Rd",
    "sg:city":"Belfair",
    "sg:classifiers":[
        {
            "category":"Organizations",
            "subcategory":"Community Association",
            "type":"Services"
        }
    ],
    "sg:phone":"+1 360 275 0846",
    "sg:postcode":"98528",
    "sg:province":"WA",
    "sg:tags":[
        "environmental",
        "org"
    ],
    "wof:name":"Hood Canal Watershed Edu Ntwrk",
    "wof:placetype":"venue"
},
  "geometry": {"coordinates":[-122.83778,47.444937],"type":"Point"}
}