{
  "type": "Feature",
  "properties": {
    "addr:full":"1401 W Bertona St Seattle WA 98119",
    "addr:housenumber":"1401",
    "addr:postcode":"98119",
    "addr:street":"W Bertona St",
    "iso:country":"US",
    "sg:address":"1401 W Bertona St",
    "sg:city":"Seattle",
    "sg:classifiers":[
        {
            "category":"Professional",
            "type":"Services"
        }
    ],
    "sg:phone":"+1 206 282 4791",
    "sg:postcode":"98119",
    "sg:province":"WA",
    "wof:name":"Victoria Sanders Photogra",
    "wof:placetype":"venue"
},
  "geometry": {"coordinates":[-122.376127,47.650335],"type":"Point"}
}