{
  "type": "Feature",
  "properties": {
    "addr:full":"4713 California Ave SW Seattle WA 98116",
    "addr:housenumber":"4713",
    "addr:postcode":"98116",
    "addr:street":"California Ave Sw",
    "iso:country":"US",
    "sg:address":"4713 California Ave SW",
    "sg:city":"Seattle",
    "sg:classifiers":[
        {
            "category":"Autos & Motor Vehicles",
            "subcategory":"Motorcycle Sales",
            "type":"Retail Goods"
        }
    ],
    "sg:phone":"+1 206 935 4710",
    "sg:postcode":"98116",
    "sg:province":"WA",
    "sg:tags":[
        "scooter"
    ],
    "wof:name":"Dogmeats Harley-Davidson",
    "wof:placetype":"venue"
},
  "geometry": {"coordinates":[-122.386903,47.559543],"type":"Point"}
}