{
  "type": "Feature",
  "properties": {
    "addr:full":"3819 Ridge Ct Mount Vernon WA 98274",
    "addr:housenumber":"3819",
    "addr:postcode":"98274",
    "addr:street":"Ridge Ct",
    "iso:country":"US",
    "sg:address":"3819 Ridge Ct",
    "sg:city":"Mount Vernon",
    "sg:classifiers":[
        {
            "category":"Banks & Credit Unions",
            "subcategory":"Financial Services",
            "type":"Services"
        }
    ],
    "sg:phone":"+1 360 428 0136",
    "sg:postcode":"98274",
    "sg:province":"WA",
    "sg:tags":[
        "investor"
    ],
    "wof:name":"Ddd Investments LLC",
    "wof:placetype":"venue"
},
  "geometry": {"coordinates":[-122.29000000000001,48.418346],"type":"Point"}
}