{
  "type": "Feature",
  "properties": {
    "addr:full":"21813 88th Pl S Kent WA 98031",
    "addr:housenumber":"21813",
    "addr:postcode":"98031",
    "addr:street":"88Th Pl S",
    "iso:country":"US",
    "sg:address":"21813 88th Pl S",
    "sg:city":"Kent",
    "sg:classifiers":[
        {
            "category":"Professional",
            "subcategory":"Advertising",
            "type":"Services"
        }
    ],
    "sg:phone":"+1 253 395 5525",
    "sg:postcode":"98031",
    "sg:province":"WA",
    "sg:tags":[
        "mail",
        "direct"
    ],
    "wof:name":"R E V Mailing",
    "wof:placetype":"venue"
},
  "geometry": {"coordinates":[-122.222576,47.405239],"type":"Point"}
}