{
  "type": "Feature",
  "properties": {
    "addr:full":"390 E Sunset Way Issaquah WA 98027",
    "addr:housenumber":"390",
    "addr:postcode":"98027",
    "addr:street":"E Sunset Way",
    "iso:country":"US",
    "sg:address":"390 E Sunset Way",
    "sg:city":"Issaquah",
    "sg:classifiers":[
        {
            "category":"Education",
            "subcategory":"Special Training",
            "type":"Public Place"
        },
        {
            "category":"Communications",
            "type":"Services"
        }
    ],
    "sg:phone":"+1 425 369 3096",
    "sg:postcode":"98027",
    "sg:province":"WA",
    "sg:tags":[
        "translator",
        "interpreter",
        "school",
        "language"
    ],
    "sg:website":"http://www.flsincorp.net",
    "wof:name":"Foreign Language Specialists",
    "wof:placetype":"venue"
},
  "geometry": {"coordinates":[-122.03013,47.530032],"type":"Point"}
}