{
  "type": "Feature",
  "properties": {
    "addr:full":"4615 S Orchard St Seattle WA 98118",
    "addr:housenumber":"4615",
    "addr:postcode":"98118",
    "addr:street":"S Orchard St",
    "iso:country":"US",
    "sg:address":"4615 S Orchard St",
    "sg:city":"Seattle",
    "sg:classifiers":[
        {
            "category":"Professional",
            "subcategory":"Business Services",
            "type":"Services"
        }
    ],
    "sg:phone":"+1 206 722 2085",
    "sg:postcode":"98118",
    "sg:province":"WA",
    "sg:tags":[
        "school",
        "vocational"
    ],
    "wof:name":"Keith L Fukeda",
    "wof:placetype":"venue"
},
  "geometry": {"coordinates":[-122.272768,47.538223],"type":"Point"}
}