{
  "type": "Feature",
  "properties": {
    "addr:full":"23120 132nd Ave SE Kent WA 98042",
    "addr:housenumber":"23120",
    "addr:postcode":"98042",
    "addr:street":"132Nd Ave Se",
    "iso:country":"US",
    "sg:address":"23120 132nd Ave SE",
    "sg:city":"Kent",
    "sg:classifiers":[
        {
            "category":"Real Estate",
            "subcategory":"Real Estate Operator",
            "type":"Services"
        }
    ],
    "sg:phone":"+1 253 639 6266",
    "sg:postcode":"98042",
    "sg:province":"WA",
    "sg:tags":[
        "mobile",
        "home",
        "site"
    ],
    "wof:name":"Full Circle Home Inspections",
    "wof:placetype":"venue"
},
  "geometry": {"coordinates":[-122.16532599999999,47.393967],"type":"Point"}
}