{
  "type": "Feature",
  "properties": {
    "addr:full":"5036 21st Ave NE Seattle WA 98105",
    "addr:housenumber":"5036",
    "addr:postcode":"98105",
    "addr:street":"21St Ave Ne",
    "iso:country":"US",
    "sg:address":"5036 21st Ave NE",
    "sg:city":"Seattle",
    "sg:classifiers":[
        {
            "category":"Manufacturing",
            "subcategory":"Leather Goods",
            "type":"Manufacturing & Wholesale Goods"
        },
        {
            "category":"Shopping",
            "subcategory":"Luggage & Leather Goods",
            "type":"Retail Goods"
        }
    ],
    "sg:phone":"+1 206 523 8806",
    "sg:postcode":"98105",
    "sg:province":"WA",
    "wof:name":"Mikeymoto Leather",
    "wof:placetype":"venue"
},
  "geometry": {"coordinates":[-122.305542,47.66522],"type":"Point"}
}