{
  "type": "Feature",
  "properties": {
    "addr:full":"1617 W Meeker St Kent WA 98032",
    "addr:housenumber":"1617",
    "addr:postcode":"98032",
    "addr:street":"W Meeker St",
    "iso:country":"US",
    "sg:address":"1617 W Meeker St",
    "sg:city":"Kent",
    "sg:classifiers":[
        {
            "category":"Bars & Pubs",
            "type":"Food & Drink"
        }
    ],
    "sg:phone":"+1 253 852 9463",
    "sg:postcode":"98032",
    "sg:province":"WA",
    "sg:tags":[
        "tavern",
        "gambling",
        "establishment"
    ],
    "wof:name":"Monte Carlo Tavern",
    "wof:placetype":"venue"
},
  "geometry": {"coordinates":[-122.255938,47.381299],"type":"Point"}
}