{
  "type": "Feature",
  "properties": {
    "addr:full":"3511 N Normandie St Spokane WA 99205",
    "addr:housenumber":"3511",
    "addr:postcode":"99205",
    "addr:street":"N Normandie St",
    "iso:country":"US",
    "sg:address":"3511 N Normandie St",
    "sg:city":"Spokane",
    "sg:classifiers":[
        {
            "category":"Food & Beverages",
            "subcategory":"Liquor & Beverages",
            "type":"Retail Goods"
        }
    ],
    "sg:phone":"+1 509 328 4757",
    "sg:postcode":"99205",
    "sg:province":"WA",
    "sg:tags":[
        "alcoholic"
    ],
    "wof:name":"Wine Crate",
    "wof:placetype":"venue"
},
  "geometry": {"coordinates":[-117.414248,47.6907],"type":"Point"}
}