{
  "type": "Feature",
  "properties": {
    "addr:full":"13633 100th Ave NE Kirkland WA 98034",
    "addr:housenumber":"13633",
    "addr:postcode":"98034",
    "addr:street":"100Th Ave Ne",
    "iso:country":"US",
    "sg:address":"13633 100th Ave NE",
    "sg:city":"Kirkland",
    "sg:classifiers":[
        {
            "category":"Banks & Credit Unions",
            "subcategory":"Bank",
            "type":"Services"
        }
    ],
    "sg:phone":"+1 425 821 1414",
    "sg:postcode":"98034",
    "sg:province":"WA",
    "sg:tags":[
        "national",
        "commercial"
    ],
    "wof:name":"Wells Fargo",
    "wof:placetype":"venue"
},
  "geometry": {"coordinates":[-122.207853,47.722121],"type":"Point"}
}