{
  "type": "Feature",
  "properties": {
    "addr:full":"9908 NW 14th Ct Vancouver WA 98685",
    "addr:housenumber":"9908",
    "addr:postcode":"98685",
    "addr:street":"Nw 14Th Ct",
    "iso:country":"US",
    "sg:address":"9908 NW 14th Ct",
    "sg:city":"Vancouver",
    "sg:classifiers":[
        {
            "category":"Social Services",
            "subcategory":"Child Care",
            "type":"Services"
        }
    ],
    "sg:phone":"+1 360 573 1681",
    "sg:postcode":"98685",
    "sg:province":"WA",
    "sg:tags":[
        "day"
    ],
    "wof:name":"Tendercare Childrens Center",
    "wof:placetype":"venue"
},
  "geometry": {"coordinates":[-122.686053,45.693391],"type":"Point"}
}