{
  "type": "Feature",
  "properties": {
    "addr:full":"128 Mission Creek Rd Cashmere WA 98815",
    "addr:housenumber":"128",
    "addr:postcode":"98815",
    "addr:street":"Mission Creek Rd",
    "iso:country":"US",
    "sg:address":"128 Mission Creek Rd",
    "sg:city":"Cashmere",
    "sg:classifiers":[
        {
            "category":"Building & Trades",
            "subcategory":"Landscaping Services",
            "type":"Services"
        }
    ],
    "sg:phone":"+1 509 782 2006",
    "sg:postcode":"98815",
    "sg:province":"WA",
    "sg:tags":[
        "lawn",
        "maintenance"
    ],
    "wof:name":"Snip It Mowing",
    "wof:placetype":"venue"
},
  "geometry": {"coordinates":[-120.473038,47.514259],"type":"Point"}
}