{
  "type": "Feature",
  "properties": {
    "addr:full":"5802 Glacier Way Yakima WA 98908",
    "addr:housenumber":"5802",
    "addr:postcode":"98908",
    "addr:street":"Glacier Way",
    "iso:country":"US",
    "sg:address":"5802 Glacier Way",
    "sg:city":"Yakima",
    "sg:classifiers":[
        {
            "category":"Building & Trades",
            "subcategory":"Construction",
            "type":"Services"
        }
    ],
    "sg:phone":"+1 509 248 7672",
    "sg:postcode":"98908",
    "sg:province":"WA",
    "sg:tags":[
        "windows"
    ],
    "wof:name":"Buehler Windshield Repair",
    "wof:placetype":"venue"
},
  "geometry": {"coordinates":[-120.58925600000001,46.605856],"type":"Point"}
}