{
  "type": "Feature",
  "properties": {
    "addr:full":"1475 Elliott Ave W Seattle WA 98119",
    "addr:housenumber":"1475",
    "addr:postcode":"98119",
    "addr:street":"Elliott Ave W",
    "iso:country":"US",
    "sg:address":"1475 Elliott Ave W",
    "sg:city":"Seattle",
    "sg:classifiers":[
        {
            "category":"Manufacturing",
            "subcategory":"Glass & Minerals",
            "type":"Manufacturing & Wholesale Goods"
        }
    ],
    "sg:phone":"+1 206 285 0450",
    "sg:postcode":"98119",
    "sg:province":"WA",
    "sg:tags":[
        "engraver"
    ],
    "wof:name":"Dimensional Imaging Inc",
    "wof:placetype":"venue"
},
  "geometry": {"coordinates":[-122.375299,47.631788],"type":"Point"}
}