{
  "type": "Feature",
  "properties": {
    "iso:country":"US",
    "sg:address":"9220 161st St E",
    "sg:city":"Puyallup",
    "sg:classifiers":[
        {
            "category":"Professional",
            "type":"Services"
        }
    ],
    "sg:phone":"+1 253 770 3260",
    "sg:postcode":"98375",
    "sg:province":"WA",
    "wof:name":"Bjs Treasures",
    "wof:placetype":"venue"
},
  "geometry": {"coordinates":[-122.305406,47.109826],"type":"Point"}
}