{
  "type": "Feature",
  "properties": {
    "addr:full":"7601 NE Hazel Dell Ave Vancouver WA 98665",
    "addr:housenumber":"7601",
    "addr:postcode":"98665",
    "addr:street":"Ne Hazel Dell Ave",
    "iso:country":"US",
    "sg:address":"7601 NE Hazel Dell Ave",
    "sg:city":"Vancouver",
    "sg:classifiers":[
        {
            "category":"Building & Trades",
            "subcategory":"Equipment Rental",
            "type":"Services"
        },
        {
            "category":"Building & Trades",
            "subcategory":"Construction",
            "type":"Services"
        }
    ],
    "sg:phone":"+1 360 737 6576",
    "sg:postcode":"98665",
    "sg:province":"WA",
    "sg:tags":[
        "highway",
        "contractor"
    ],
    "wof:name":"Cascade Bridge Leasing LLC",
    "wof:placetype":"venue"
},
  "geometry": {"coordinates":[-122.668826,45.677704],"type":"Point"}
}