{
  "type": "Feature",
  "properties": {
    "addr:full":"303 NE Creek St Yelm WA 98597",
    "addr:housenumber":"303",
    "addr:postcode":"98597",
    "addr:street":"Ne Creek St",
    "iso:country":"US",
    "sg:address":"303 NE Creek St",
    "sg:city":"Yelm",
    "sg:classifiers":[
        {
            "category":"Building & Trades",
            "subcategory":"Plumbing",
            "type":"Services"
        }
    ],
    "sg:phone":"+1 360 458 9548",
    "sg:postcode":"98597",
    "sg:province":"WA",
    "sg:tags":[
        "contractor"
    ],
    "wof:name":"Alternative Designs",
    "wof:placetype":"venue"
},
  "geometry": {"coordinates":[-122.590096,46.936073],"type":"Point"}
}