{
  "type": "Feature",
  "properties": {
    "addr:full":"9116 Gravelly Lake Dr SW Lakewood WA 98499",
    "addr:housenumber":"9116",
    "addr:postcode":"98499",
    "addr:street":"Gravelly Lake Dr Sw",
    "iso:country":"US",
    "sg:address":"9116 Gravelly Lake Dr SW",
    "sg:city":"Lakewood",
    "sg:classifiers":[
        {
            "category":"Health Services",
            "subcategory":"Doctor",
            "type":"Services"
        }
    ],
    "sg:phone":"+1 253 581 1091",
    "sg:postcode":"98499",
    "sg:province":"WA",
    "sg:tags":[
        "physician",
        "surgeon"
    ],
    "wof:name":"Road Clinic",
    "wof:placetype":"venue"
},
  "geometry": {"coordinates":[-122.518399,47.171967],"type":"Point"}
}