{
  "type": "Feature",
  "properties": {
    "addr:full":"18129 Mountain View Rd NE Duvall WA 98019",
    "addr:housenumber":"18129",
    "addr:postcode":"98019",
    "addr:street":"Mountain View Rd Ne",
    "iso:country":"US",
    "sg:address":"18129 Mountain View Rd NE",
    "sg:city":"Duvall",
    "sg:classifiers":[
        {
            "category":"Manufacturing",
            "subcategory":"Tools & Machinery",
            "type":"Manufacturing & Wholesale Goods"
        }
    ],
    "sg:phone":"+1 425 788 7751",
    "sg:postcode":"98019",
    "sg:province":"WA",
    "sg:tags":[
        "woodworking",
        "mfg"
    ],
    "wof:name":"Knotical Arts",
    "wof:placetype":"venue"
},
  "geometry": {"coordinates":[-121.913962,47.756232],"type":"Point"}
}