{
  "type": "Feature",
  "properties": {
    "addr:full":"3209 E 57th Ave Ste B Spokane WA 99223",
    "addr:housenumber":"3209",
    "addr:postcode":"99223",
    "addr:street":"E 57Th Ave Ste B",
    "iso:country":"US",
    "sg:address":"3209 E 57th Ave Ste B",
    "sg:city":"Spokane",
    "sg:classifiers":[
        {
            "category":"Restaurant",
            "type":"Food & Drink"
        }
    ],
    "sg:phone":"+1 509 448 3834",
    "sg:postcode":"99223",
    "sg:province":"WA",
    "sg:tags":[
        "mexican"
    ],
    "sg:website":"http://www.ranchoviejo.net",
    "wof:name":"Ranch Viejo",
    "wof:placetype":"venue"
},
  "geometry": {"coordinates":[-117.363693,47.60218],"type":"Point"}
}