{
  "type": "Feature",
  "properties": {
    "addr:full":"11109 NE 84th Cir Vancouver WA 98662",
    "addr:housenumber":"11109",
    "addr:postcode":"98662",
    "addr:street":"Ne 84Th Cir",
    "iso:country":"US",
    "sg:address":"11109 NE 84th Cir",
    "sg:city":"Vancouver",
    "sg:classifiers":[
        {
            "category":"Communications",
            "subcategory":"Film & Video Production",
            "type":"Services"
        }
    ],
    "sg:phone":"+1 360 892 8259",
    "sg:postcode":"98662",
    "sg:province":"WA",
    "sg:tags":[
        "taping"
    ],
    "wof:name":"York Studios",
    "wof:placetype":"venue"
},
  "geometry": {"coordinates":[-122.557573,45.683451],"type":"Point"}
}