{
  "type": "Feature",
  "properties": {
    "addr:full":"4512 N Market St Spokane WA 99207",
    "addr:housenumber":"4512",
    "addr:postcode":"99207",
    "addr:street":"N Market St",
    "iso:country":"US",
    "sg:address":"4512 N Market St",
    "sg:city":"Spokane",
    "sg:classifiers":[
        {
            "category":"Shopping",
            "subcategory":"Discount & Variety Stores",
            "type":"Retail Goods"
        }
    ],
    "sg:phone":"+1 509 487 3987",
    "sg:postcode":"99207",
    "sg:province":"WA",
    "wof:name":"Liquidation Outlet",
    "wof:placetype":"venue"
},
  "geometry": {"coordinates":[-117.36489,47.69962],"type":"Point"}
}