{
  "type": "Feature",
  "properties": {
    "addr:full":"485 S Nevada Ave East Wenatchee WA 98802",
    "addr:housenumber":"485",
    "addr:postcode":"98802",
    "addr:street":"S Nevada Ave",
    "iso:country":"US",
    "sg:address":"485 S Nevada Ave",
    "sg:city":"East Wenatchee",
    "sg:classifiers":[
        {
            "category":"Real Estate",
            "subcategory":"Real Estate Agent",
            "type":"Services"
        }
    ],
    "sg:phone":"+1 509 884 2734",
    "sg:postcode":"98802",
    "sg:province":"WA",
    "wof:name":"Century 21",
    "wof:placetype":"venue"
},
  "geometry": {"coordinates":[-120.24486,47.396804],"type":"Point"}
}