{
  "type": "Feature",
  "properties": {
    "addr:full":"16516 NW 41st Ave Ridgefield WA 98642",
    "addr:housenumber":"16516",
    "addr:postcode":"98642",
    "addr:street":"Nw 41St Ave",
    "iso:country":"US",
    "sg:address":"16516 NW 41st Ave",
    "sg:city":"Ridgefield",
    "sg:classifiers":[
        {
            "category":"Home & Garden",
            "subcategory":"Furniture",
            "type":"Retail Goods"
        }
    ],
    "sg:phone":"+1 360 750 7875",
    "sg:postcode":"98642",
    "sg:province":"WA",
    "sg:tags":[
        "store"
    ],
    "wof:name":"Lodgepole Furniture",
    "wof:placetype":"venue"
},
  "geometry": {"coordinates":[-122.712982,45.74086],"type":"Point"}
}