{
  "type": "Feature",
  "properties": {
    "addr:full":"4121 Dayton Ave N Seattle WA 98103",
    "addr:housenumber":"4121",
    "addr:postcode":"98103",
    "addr:street":"Dayton Ave N",
    "iso:country":"US",
    "sg:address":"4121 Dayton Ave N",
    "sg:city":"Seattle",
    "sg:classifiers":[
        {
            "category":"Health Services",
            "subcategory":"Health Practitioner",
            "type":"Services"
        }
    ],
    "sg:phone":"+1 206 547 3387",
    "sg:postcode":"98103",
    "sg:province":"WA",
    "wof:name":"Jade River Healing Arts",
    "wof:placetype":"venue"
},
  "geometry": {"coordinates":[-122.35265099999999,47.657509],"type":"Point"}
}