{
  "type": "Feature",
  "properties": {
    "addr:full":"180 N Johnson Rd Selah WA 98942",
    "addr:housenumber":"180",
    "addr:postcode":"98942",
    "addr:street":"N Johnson Rd",
    "iso:country":"US",
    "sg:address":"180 N Johnson Rd",
    "sg:city":"Selah",
    "sg:classifiers":[
        {
            "category":"Professional",
            "type":"Services"
        }
    ],
    "sg:phone":"+1 509 697 4870",
    "sg:postcode":"98942",
    "sg:province":"WA",
    "wof:name":"Drew Gaskell",
    "wof:placetype":"venue"
},
  "geometry": {"coordinates":[-120.49991300000001,46.691798],"type":"Point"}
}