{
  "type": "Feature",
  "properties": {
    "addr:full":"100 S King St Seattle WA 98104",
    "addr:housenumber":"100",
    "addr:postcode":"98104",
    "addr:street":"S King St",
    "iso:country":"US",
    "sg:address":"100 S King St",
    "sg:city":"Seattle",
    "sg:classifiers":[
        {
            "category":"Professional",
            "subcategory":"Lawyer & Legal Services",
            "type":"Services"
        }
    ],
    "sg:phone":"+1 206 386 8900",
    "sg:postcode":"98104",
    "sg:province":"WA",
    "wof:name":"Droker Howard Law",
    "wof:placetype":"venue"
},
  "geometry": {"coordinates":[-122.333263,47.598288],"type":"Point"}
}