{
  "type": "Feature",
  "properties": {
    "addr:full":"1310 Tacoma Ave S Tacoma WA 98402",
    "addr:housenumber":"1310",
    "addr:postcode":"98402",
    "addr:street":"Tacoma Ave S",
    "iso:country":"US",
    "sg:address":"1310 Tacoma Ave S",
    "sg:city":"Tacoma",
    "sg:classifiers":[
        {
            "category":"Bars & Pubs",
            "type":"Food & Drink"
        }
    ],
    "sg:phone":"+1 253 272 1892",
    "sg:postcode":"98402",
    "sg:province":"WA",
    "sg:tags":[
        "tavern"
    ],
    "wof:name":"Acme Tavern",
    "wof:placetype":"venue"
},
  "geometry": {"coordinates":[-122.443826,47.249771],"type":"Point"}
}