{
  "type": "Feature",
  "properties": {
    "addr:full":"16500 SE 15th St Ste 160 Vancouver WA 98683",
    "addr:postcode":"16500;98683",
    "addr:street":"Se 15Th St Ste 160",
    "iso:country":"US",
    "sg:address":"16500 SE 15th St Ste 160",
    "sg:city":"Vancouver",
    "sg:classifiers":[
        {
            "category":"Health Services",
            "subcategory":"Health Practitioner",
            "type":"Services"
        },
        {
            "category":"Health Services",
            "subcategory":"Chiropractor",
            "type":"Services"
        }
    ],
    "sg:phone":"+1 360 718 7944",
    "sg:postcode":"98683",
    "sg:province":"WA",
    "sg:tags":[
        "acupuncture",
        "chiropractic"
    ],
    "sg:website":"www.realheadachesolutions.com",
    "wof:name":"Atlas Spinal Care",
    "wof:placetype":"venue"
},
  "geometry": {"coordinates":[-122.50218599999999,45.610336],"type":"Point"}
}