{
  "type": "Feature",
  "properties": {
    "addr:full":"17801 Pacific Hwy S Seattle WA 98188",
    "addr:housenumber":"17801",
    "addr:postcode":"98188",
    "addr:street":"Pacific Hwy S",
    "iso:country":"US",
    "sg:address":"17801 Pacific Hwy S",
    "sg:city":"Seattle",
    "sg:classifiers":[
        {
            "category":"Retail",
            "subcategory":"Repair Shop",
            "type":"Services"
        }
    ],
    "sg:phone":"+1 206 431 0844",
    "sg:postcode":"98188",
    "sg:province":"WA",
    "wof:name":"Cart Service Equipment Inc",
    "wof:placetype":"venue"
},
  "geometry": {"coordinates":[-122.296137,47.442236],"type":"Point"}
}