{
  "type": "Feature",
  "properties": {
    "addr:full":"42829 188th Ave SE Enumclaw WA 98022",
    "addr:housenumber":"42829",
    "addr:postcode":"98022",
    "addr:street":"188Th Ave Se",
    "iso:country":"US",
    "sg:address":"42829 188th Ave SE",
    "sg:city":"Enumclaw",
    "sg:classifiers":[
        {
            "category":"Farming",
            "subcategory":"Dairy Farm",
            "type":"Manufacturing & Wholesale Goods"
        }
    ],
    "sg:phone":"+1 360 825 1717",
    "sg:postcode":"98022",
    "sg:province":"WA",
    "wof:name":"Van Dam Dairy",
    "wof:placetype":"venue"
},
  "geometry": {"coordinates":[-122.090948,47.217188],"type":"Point"}
}