{
  "type": "Feature",
  "properties": {
    "addr:full":"3021 NE 4th St Renton WA 98057",
    "addr:housenumber":"3021",
    "addr:postcode":"98057",
    "addr:street":"Ne 4Th St",
    "iso:country":"US",
    "sg:address":"3021 NE 4th St",
    "sg:city":"Renton",
    "sg:classifiers":[
        {
            "category":"Local Transit",
            "type":"Transportation"
        }
    ],
    "sg:phone":"+1 206 296 4466",
    "sg:postcode":"98057",
    "sg:province":"WA",
    "sg:tags":[
        "public"
    ],
    "sg:website":"www.metrokc.gov/dnrp/swd/facilit...",
    "wof:name":"Renton Transfer Station",
    "wof:placetype":"venue"
},
  "geometry": {"coordinates":[-122.207629,47.478228],"type":"Point"}
}