{
  "type": "Feature",
  "properties": {
    "iso:country":"US",
    "sg:address":"19105 36th Ave W",
    "sg:city":"Lynnwood",
    "sg:classifiers":[
        {
            "category":"Wholesale",
            "subcategory":"Office Equipment",
            "type":"Manufacturing & Wholesale Goods"
        }
    ],
    "sg:phone":"+1 425 778 8577",
    "sg:postcode":"98036",
    "sg:province":"WA",
    "sg:tags":[
        "scanning",
        "code",
        "bar"
    ],
    "sg:website":"www.versatilemobile.com",
    "wof:name":"Versatile Mobile Systems",
    "wof:placetype":"venue"
},
  "geometry": {"coordinates":[-122.281766,47.828165],"type":"Point"}
}