{
  "type": "Feature",
  "properties": {
    "addr:full":"2301 S Jackson St Seattle WA 98144",
    "addr:housenumber":"2301",
    "addr:postcode":"98144",
    "addr:street":"S Jackson St",
    "iso:country":"US",
    "sg:address":"2301 S Jackson St",
    "sg:city":"Seattle",
    "sg:classifiers":[
        {
            "category":"Shopping",
            "subcategory":"Clothing, Apparel, & Fashions",
            "type":"Retail Goods"
        }
    ],
    "sg:phone":"+1 206 568 0900",
    "sg:postcode":"98144",
    "sg:province":"WA",
    "sg:tags":[
        "sport",
        "wear"
    ],
    "wof:name":"National Achiever Services",
    "wof:placetype":"venue"
},
  "geometry": {"coordinates":[-122.302002,47.5993],"type":"Point"}
}