{
  "type": "Feature",
  "properties": {
    "addr:full":"28520 State Rte 410 Buckley WA 98321",
    "addr:housenumber":"28520",
    "addr:postcode":"98321",
    "addr:street":"State Rte 410",
    "iso:country":"US",
    "sg:address":"28520 State Rte 410",
    "sg:city":"Buckley",
    "sg:classifiers":[
        {
            "category":"Wholesale",
            "subcategory":"Auto Parts",
            "type":"Manufacturing & Wholesale Goods"
        }
    ],
    "sg:phone":"+1 360 829 1263",
    "sg:postcode":"98321",
    "sg:province":"WA",
    "sg:tags":[
        "automobile",
        "wrecking"
    ],
    "wof:name":"Walt & Verns Pickparts Parts",
    "wof:placetype":"venue"
},
  "geometry": {"coordinates":[-122.054643,47.159678],"type":"Point"}
}