{
  "type": "Feature",
  "properties": {
    "iso:country":"US",
    "sg:address":"1225 166th Ave SE",
    "sg:city":"Bellevue",
    "sg:classifiers":[
        {
            "category":"Health Services",
            "subcategory":"Doctor",
            "type":"Services"
        }
    ],
    "sg:phone":"+1 425 747 7175",
    "sg:postcode":"98008",
    "sg:province":"WA",
    "wof:name":"Thomas R Quickstad DDS",
    "wof:placetype":"venue"
},
  "geometry": {"coordinates":[-122.118984,47.598333],"type":"Point"}
}