{
  "type": "Feature",
  "properties": {
    "addr:full":"2810 Lombard Ave Everett WA 98201",
    "addr:housenumber":"2810",
    "addr:postcode":"98201",
    "addr:street":"Lombard Ave",
    "iso:country":"US",
    "sg:address":"2810 Lombard Ave",
    "sg:city":"Everett",
    "sg:classifiers":[
        {
            "category":"Organizations",
            "subcategory":"Labor Organization",
            "type":"Services"
        }
    ],
    "sg:phone":"+1 425 252 0184",
    "sg:postcode":"98201",
    "sg:province":"WA",
    "wof:name":"National Assn Ltr Crrers U S A",
    "wof:placetype":"venue"
},
  "geometry": {"coordinates":[-122.203058,47.979946],"type":"Point"}
}