{
  "type": "Feature",
  "properties": {
    "addr:full":"1186 S Wenatchee Ave Wenatchee WA 98801",
    "addr:housenumber":"1186",
    "addr:postcode":"98801",
    "addr:street":"S Wenatchee Ave",
    "iso:country":"US",
    "sg:address":"1186 S Wenatchee Ave",
    "sg:city":"Wenatchee",
    "sg:classifiers":[
        {
            "category":"Wholesale",
            "subcategory":"Durable Goods & Equipment",
            "type":"Manufacturing & Wholesale Goods"
        }
    ],
    "sg:phone":"+1 509 662 2274",
    "sg:postcode":"98801",
    "sg:province":"WA",
    "sg:tags":[
        "fire",
        "extinguisher"
    ],
    "wof:name":"Central Washington Fire Co",
    "wof:placetype":"venue"
},
  "geometry": {"coordinates":[-120.300054,47.408978],"type":"Point"}
}