{
  "type": "Feature",
  "properties": {
    "iso:country":"US",
    "sg:address":"17505 E Indiana Ave",
    "sg:city":"Greenacres",
    "sg:classifiers":[
        {
            "category":"Wholesale",
            "subcategory":"Machinery & Supplies",
            "type":"Manufacturing & Wholesale Goods"
        }
    ],
    "sg:phone":"+1 509 926 3324",
    "sg:postcode":"99016",
    "sg:province":"WA",
    "sg:tags":[
        "equipment",
        "industrial"
    ],
    "wof:name":"Superior Fluid Power Inc",
    "wof:placetype":"venue"
},
  "geometry": {"coordinates":[-117.164444,47.675187],"type":"Point"}
}