{
  "type": "Feature",
  "properties": {
    "addr:full":"3615 Arapahoe Pl W Seattle WA 98199",
    "addr:housenumber":"3615",
    "addr:postcode":"98199",
    "addr:street":"Arapahoe Pl W",
    "iso:country":"US",
    "sg:address":"3615 Arapahoe Pl W",
    "sg:city":"Seattle",
    "sg:classifiers":[
        {
            "category":"Real Estate",
            "subcategory":"Real Estate Operator",
            "type":"Services"
        }
    ],
    "sg:phone":"+1 206 282 7340",
    "sg:postcode":"98199",
    "sg:province":"WA",
    "sg:tags":[
        "building",
        "apartment"
    ],
    "wof:name":"Rajah Apts Company",
    "wof:placetype":"venue"
},
  "geometry": {"coordinates":[-122.40902699999999,47.653831],"type":"Point"}
}