{
  "type": "Feature",
  "properties": {
    "iso:country":"US",
    "sg:address":"1028 Rd C NE",
    "sg:city":"Moses Lake",
    "sg:classifiers":[
        {
            "category":"Building & Trades",
            "subcategory":"Construction",
            "type":"Services"
        }
    ],
    "sg:phone":"+1 509 765 4985",
    "sg:postcode":"98837",
    "sg:province":"WA",
    "sg:tags":[
        "contractor"
    ],
    "wof:name":"Airway Builders",
    "wof:placetype":"venue"
},
  "geometry": {"coordinates":[-119.428085,47.106431],"type":"Point"}
}