{
  "type": "Feature",
  "properties": {
    "addr:full":"1600 Fairview Ave E Seattle WA 98102",
    "addr:housenumber":"1600",
    "addr:postcode":"98102",
    "addr:street":"Fairview Ave E",
    "iso:country":"US",
    "sg:address":"1600 Fairview Ave E",
    "sg:city":"Seattle",
    "sg:classifiers":[
        {
            "category":"Manufacturing",
            "subcategory":"Printing",
            "type":"Manufacturing & Wholesale Goods"
        }
    ],
    "sg:phone":"+1 206 336 3001",
    "sg:postcode":"98102",
    "sg:province":"WA",
    "sg:tags":[
        "publishing"
    ],
    "wof:name":"Interpblic Group Companies Inc",
    "wof:placetype":"venue"
},
  "geometry": {"coordinates":[-122.32692299999999,47.634842],"type":"Point"}
}