{
  "type": "Feature",
  "properties": {
    "addr:full":"151 Raft Island Dr NW Gig Harbor WA 98335",
    "addr:housenumber":"151",
    "addr:postcode":"98335",
    "addr:street":"Raft Island Dr Nw",
    "iso:country":"US",
    "sg:address":"151 Raft Island Dr NW",
    "sg:city":"Gig Harbor",
    "sg:classifiers":[
        {
            "category":"Professional",
            "type":"Services"
        }
    ],
    "sg:phone":"+1 253 265 6440",
    "sg:postcode":"98335",
    "sg:province":"WA",
    "sg:tags":[
        "information",
        "bureau"
    ],
    "wof:name":"Patricia T Lantz",
    "wof:placetype":"venue"
},
  "geometry": {"coordinates":[-122.66726,47.330977],"type":"Point"}
}