{
  "type": "Feature",
  "properties": {
    "addr:full":"416 NE 43rd St Seattle WA 98105",
    "addr:housenumber":"416",
    "addr:postcode":"98105",
    "addr:street":"Ne 43Rd St",
    "iso:country":"US",
    "sg:address":"416 NE 43rd St",
    "sg:city":"Seattle",
    "sg:classifiers":[
        {
            "category":"Building & Trades",
            "subcategory":"Plumbing",
            "type":"Services"
        }
    ],
    "sg:phone":"+1 206 650 0957",
    "sg:postcode":"98105",
    "sg:province":"WA",
    "sg:website":"www.wallingfordplumbing.net",
    "wof:name":"Wallingford Plumbing LLC",
    "wof:placetype":"venue"
},
  "geometry": {"coordinates":[-122.323279,47.659156],"type":"Point"}
}