{
  "type": "Feature",
  "properties": {
    "addr:full":"625 Strander Blvd Seattle WA 98188",
    "addr:housenumber":"625",
    "addr:postcode":"98188",
    "addr:street":"Strander Blvd",
    "iso:country":"US",
    "sg:address":"625 Strander Blvd",
    "sg:city":"Seattle",
    "sg:classifiers":[
        {
            "category":"Travel",
            "subcategory":"Travel Agent",
            "type":"Entertainment"
        }
    ],
    "sg:phone":"+1 206 575 8242",
    "sg:postcode":"98188",
    "sg:province":"WA",
    "sg:tags":[
        "operator",
        "tour"
    ],
    "wof:name":"Silver Wing Holidays",
    "wof:placetype":"venue"
},
  "geometry": {"coordinates":[-122.245848,47.456215],"type":"Point"}
}