{
  "type": "Feature",
  "properties": {
    "addr:full":"13329 187th Ct NE Woodinville WA 98072",
    "addr:housenumber":"13329",
    "addr:postcode":"98072",
    "addr:street":"187Th Ct Ne",
    "iso:country":"US",
    "sg:address":"13329 187th Ct NE",
    "sg:city":"Woodinville",
    "sg:classifiers":[
        {
            "category":"Building & Trades",
            "subcategory":"Construction",
            "type":"Services"
        }
    ],
    "sg:phone":"+1 425 882 1901",
    "sg:postcode":"98072",
    "sg:province":"WA",
    "sg:tags":[
        "hanging",
        "contractor"
    ],
    "wof:name":"Aj &J Quality Painting Inc",
    "wof:placetype":"venue"
},
  "geometry": {"coordinates":[-122.090096,47.719178],"type":"Point"}
}