{
  "type": "Feature",
  "properties": {
    "addr:full":"12203 NE 108th St Kirkland WA 98033",
    "addr:housenumber":"12203",
    "addr:postcode":"98033",
    "addr:street":"Ne 108Th St",
    "iso:country":"US",
    "sg:address":"12203 NE 108th St",
    "sg:city":"Kirkland",
    "sg:classifiers":[
        {
            "category":"Building & Trades",
            "subcategory":"Construction",
            "type":"Services"
        }
    ],
    "sg:phone":"+1 206 469 8705",
    "sg:postcode":"98033",
    "sg:province":"WA",
    "sg:tags":[
        "gen"
    ],
    "wof:name":"Ls Yarbro Gen Contractor",
    "wof:placetype":"venue"
},
  "geometry": {"coordinates":[-122.17576699999999,47.696744],"type":"Point"}
}