{
  "type": "Feature",
  "properties": {
    "addr:full":"623 14th St SE Puyallup WA 98372",
    "addr:housenumber":"623",
    "addr:postcode":"98372",
    "addr:street":"14Th St Se",
    "iso:country":"US",
    "sg:address":"623 14th St SE",
    "sg:city":"Puyallup",
    "sg:classifiers":[
        {
            "category":"Social Services",
            "subcategory":"Job Training",
            "type":"Services"
        }
    ],
    "sg:phone":"+1 360 832 6386",
    "sg:postcode":"98372",
    "sg:province":"WA",
    "sg:tags":[
        "rehabilitation"
    ],
    "wof:name":"Northwest Equicare Rehab Ridng",
    "wof:placetype":"venue"
},
  "geometry": {"coordinates":[-122.275997,47.18734],"type":"Point"}
}