{
  "type": "Feature",
  "properties": {
    "addr:full":"3224 SE 197th Ct Camas WA 98607",
    "addr:housenumber":"3224",
    "addr:postcode":"98607",
    "addr:street":"Se 197Th Ct",
    "iso:country":"US",
    "sg:address":"3224 SE 197th Ct",
    "sg:city":"Camas",
    "sg:classifiers":[
        {
            "category":"Building & Trades",
            "subcategory":"Construction",
            "type":"Services"
        }
    ],
    "sg:phone":"+1 360 833 1107",
    "sg:postcode":"98607",
    "sg:province":"WA",
    "sg:tags":[
        "general",
        "contractor"
    ],
    "wof:name":"Talbitzer Homes",
    "wof:placetype":"venue"
},
  "geometry": {"coordinates":[-122.47148900000001,45.597321],"type":"Point"}
}