{
  "type": "Feature",
  "properties": {
    "addr:full":"5080 W Mercer Way Mercer Island WA 98040",
    "addr:housenumber":"5080",
    "addr:postcode":"98040",
    "addr:street":"W Mercer Way",
    "iso:country":"US",
    "sg:address":"5080 W Mercer Way",
    "sg:city":"Mercer Island",
    "sg:classifiers":[
        {
            "category":"Retail",
            "subcategory":"Portrait Studio",
            "type":"Services"
        }
    ],
    "sg:phone":"+1 206 232 4570",
    "sg:postcode":"98040",
    "sg:province":"WA",
    "sg:tags":[
        "photo"
    ],
    "wof:name":"Place In Time",
    "wof:placetype":"venue"
},
  "geometry": {"coordinates":[-122.22494399999999,47.556837],"type":"Point"}
}