{
  "type": "Feature",
  "properties": {
    "addr:full":"6415 Burden Blvd Pasco WA 99301",
    "addr:housenumber":"6415",
    "addr:postcode":"99301",
    "addr:street":"Burden Blvd",
    "iso:country":"US",
    "sg:address":"6415 Burden Blvd",
    "sg:city":"Pasco",
    "sg:classifiers":[
        {
            "category":"Restaurant",
            "type":"Food & Drink"
        }
    ],
    "sg:phone":"+1 509 539 4328",
    "sg:postcode":"99301",
    "sg:province":"WA",
    "sg:tags":[
        "eating"
    ],
    "wof:name":"Lil Brick House",
    "wof:placetype":"venue"
},
  "geometry": {"coordinates":[-119.17379699999999,46.270581],"type":"Point"}
}