{
  "type": "Feature",
  "properties": {
    "addr:full":"915 W Court St Pasco WA 99301",
    "addr:housenumber":"915",
    "addr:postcode":"99301",
    "addr:street":"W Court St",
    "iso:country":"US",
    "sg:address":"915 W Court St",
    "sg:city":"Pasco",
    "sg:classifiers":[
        {
            "category":"Personal",
            "subcategory":"Beauty Salon",
            "type":"Services"
        }
    ],
    "sg:phone":"+1 509 545 4414",
    "sg:postcode":"99301",
    "sg:province":"WA",
    "wof:name":"Lupitas Beaty Salon",
    "wof:placetype":"venue"
},
  "geometry": {"coordinates":[-119.100568,46.241329],"type":"Point"}
}