{
  "type": "Feature",
  "properties": {
    "addr:full":"1721 Woodcock Rd Sequim WA 98382",
    "addr:housenumber":"1721",
    "addr:postcode":"98382",
    "addr:street":"Woodcock Rd",
    "iso:country":"US",
    "sg:address":"1721 Woodcock Rd",
    "sg:city":"Sequim",
    "sg:classifiers":[
        {
            "category":"Building & Trades",
            "subcategory":"Construction",
            "type":"Services"
        }
    ],
    "sg:phone":"+1 360 681 6866",
    "sg:postcode":"98382",
    "sg:province":"WA",
    "sg:tags":[
        "house"
    ],
    "wof:name":"Glenn Franklin Construction In",
    "wof:placetype":"venue"
},
  "geometry": {"coordinates":[-123.179181,48.116169],"type":"Point"}
}