{
  "type": "Feature",
  "properties": {
    "addr:full":"3732 York St Bellingham WA 98229",
    "addr:housenumber":"3732",
    "addr:postcode":"98229",
    "addr:street":"York St",
    "iso:country":"US",
    "sg:address":"3732 York St",
    "sg:city":"Bellingham",
    "sg:classifiers":[
        {
            "category":"Building & Trades",
            "subcategory":"Landscaping Services",
            "type":"Services"
        }
    ],
    "sg:phone":"+1 360 752 9562",
    "sg:postcode":"98229",
    "sg:province":"WA",
    "sg:tags":[
        "landscape"
    ],
    "wof:name":"New Leaf Landscapes",
    "wof:placetype":"venue"
},
  "geometry": {"coordinates":[-122.42453399999999,48.750701],"type":"Point"}
}