{
  "type": "Feature",
  "properties": {
    "addr:full":"2101 4th Ave Ste 1020 Seattle WA 98121",
    "addr:housenumber":"2101",
    "addr:postcode":"98121",
    "addr:street":"4Th Ave Ste 1020",
    "iso:country":"US",
    "sg:address":"2101 4th Ave Ste 1020",
    "sg:city":"Seattle",
    "sg:classifiers":[
        {
            "category":"Travel",
            "subcategory":"Hotels & Motels",
            "type":"Entertainment"
        }
    ],
    "sg:phone":"+1 206 443 3550",
    "sg:postcode":"98121",
    "sg:province":"WA",
    "wof:name":"Minwis Acquisition Company",
    "wof:placetype":"venue"
},
  "geometry": {"coordinates":[-122.341347,47.6138],"type":"Point"}
}