{
  "type": "Feature",
  "properties": {
    "addr:full":"451 Logger St SE Lacey WA 98503",
    "addr:housenumber":"451",
    "addr:postcode":"98503",
    "addr:street":"Logger St Se",
    "iso:country":"US",
    "sg:address":"451 Logger St SE",
    "sg:city":"Lacey",
    "sg:classifiers":[
        {
            "category":"Wholesale",
            "subcategory":"Groceries",
            "type":"Manufacturing & Wholesale Goods"
        }
    ],
    "sg:phone":"+1 360 459 1248",
    "sg:postcode":"98503",
    "sg:province":"WA",
    "wof:name":"Duchaine Distributing",
    "wof:placetype":"venue"
},
  "geometry": {"coordinates":[-122.782792,47.048646],"type":"Point"}
}