{
  "type": "Feature",
  "properties": {
    "addr:full":"15012 Main St E Sumner WA 98390",
    "addr:housenumber":"15012",
    "addr:postcode":"98390",
    "addr:street":"Main St E",
    "iso:country":"US",
    "sg:address":"15012 Main St E",
    "sg:city":"Sumner",
    "sg:classifiers":[
        {
            "category":"Restaurant",
            "type":"Food & Drink"
        }
    ],
    "sg:phone":"+1 253 891 1789",
    "sg:postcode":"98390",
    "sg:province":"WA",
    "sg:tags":[
        "eating"
    ],
    "wof:name":"Branks B B Q & Catering",
    "wof:placetype":"venue"
},
  "geometry": {"coordinates":[-122.22841699999999,47.202609],"type":"Point"}
}