{
  "type": "Feature",
  "properties": {
    "addr:full":"218 N Bernard St Spokane WA 99201",
    "addr:housenumber":"218",
    "addr:postcode":"99201",
    "addr:street":"N Bernard St",
    "iso:country":"US",
    "sg:address":"218 N Bernard St",
    "sg:city":"Spokane",
    "sg:classifiers":[
        {
            "category":"Professional",
            "subcategory":"Accounting & Tax Preparation",
            "type":"Services"
        }
    ],
    "sg:phone":"+1 509 624 9223",
    "sg:postcode":"99201",
    "sg:province":"WA",
    "sg:tags":[
        "accountant"
    ],
    "sg:website":"www.fruci.com",
    "wof:name":"Fruci & Assoc",
    "wof:placetype":"venue"
},
  "geometry": {"coordinates":[-117.415921,47.659416],"type":"Point"}
}