{
  "type": "Feature",
  "properties": {
    "addr:full":"230 Hillview Dr Richland WA 99352",
    "addr:housenumber":"230",
    "addr:postcode":"99352",
    "addr:street":"Hillview Dr",
    "iso:country":"US",
    "sg:address":"230 Hillview Dr",
    "sg:city":"Richland",
    "sg:classifiers":[
        {
            "category":"Professional",
            "subcategory":"Management & Consulting",
            "type":"Services"
        }
    ],
    "sg:phone":"+1 509 627 5811",
    "sg:postcode":"99352",
    "sg:province":"WA",
    "sg:tags":[
        "business"
    ],
    "wof:name":"William C Stahl Jr",
    "wof:placetype":"venue"
},
  "geometry": {"coordinates":[-119.271626,46.21759],"type":"Point"}
}