{
  "type": "Feature",
  "properties": {
    "addr:full":"628 W Garland Ave Spokane WA 99205",
    "addr:housenumber":"628",
    "addr:postcode":"99205",
    "addr:street":"W Garland Ave",
    "iso:country":"US",
    "sg:address":"628 W Garland Ave",
    "sg:city":"Spokane",
    "sg:classifiers":[
        {
            "category":"Recreation",
            "type":"Entertainment"
        }
    ],
    "sg:phone":"+1 509 323 9086",
    "sg:postcode":"99205",
    "sg:province":"WA",
    "sg:tags":[
        "club",
        "membership"
    ],
    "wof:name":"Nail Club",
    "wof:placetype":"venue"
},
  "geometry": {"coordinates":[-117.420982,47.693545],"type":"Point"}
}