{
  "type": "Feature",
  "properties": {
    "iso:country":"US",
    "sg:address":"17818 Aurora Ave N",
    "sg:city":"Shoreline",
    "sg:classifiers":[
        {
            "category":"Building & Trades",
            "subcategory":"Construction",
            "type":"Services"
        }
    ],
    "sg:phone":"+1 206 362 7663",
    "sg:postcode":"98133",
    "sg:province":"WA",
    "sg:tags":[
        "roofing",
        "contractor"
    ],
    "wof:name":"Hillside Roofing & Gutters",
    "wof:placetype":"venue"
},
  "geometry": {"coordinates":[-122.345986,47.758787],"type":"Point"}
}