{
  "type": "Feature",
  "properties": {
    "addr:full":"5714 Comte Dr NW Gig Harbor WA 98335",
    "addr:housenumber":"5714",
    "addr:postcode":"98335",
    "addr:street":"Comte Dr Nw",
    "iso:country":"US",
    "sg:address":"5714 Comte Dr NW",
    "sg:city":"Gig Harbor",
    "sg:classifiers":[
        {
            "category":"Professional",
            "subcategory":"Computer Services",
            "type":"Services"
        }
    ],
    "sg:phone":"+1 253 858 0801",
    "sg:postcode":"98335",
    "sg:province":"WA",
    "sg:tags":[
        "programing",
        "custom"
    ],
    "wof:name":"Workeasy Corp",
    "wof:placetype":"venue"
},
  "geometry": {"coordinates":[-122.61269,47.319363],"type":"Point"}
}