{
  "type": "Feature",
  "properties": {
    "addr:full":"4 Appelo Ln Naselle WA 98638",
    "addr:housenumber":"4",
    "addr:postcode":"98638",
    "addr:street":"Appelo Ln",
    "iso:country":"US",
    "sg:address":"4 Appelo Ln",
    "sg:city":"Naselle",
    "sg:classifiers":[
        {
            "category":"Shopping",
            "subcategory":"Florist",
            "type":"Retail Goods"
        },
        {
            "category":"Shopping",
            "subcategory":"Clothing, Apparel, & Fashions",
            "type":"Retail Goods"
        }
    ],
    "sg:phone":"+1 360 484 7181",
    "sg:postcode":"98638",
    "sg:province":"WA",
    "wof:name":"Mistie's Blessings",
    "wof:placetype":"venue"
},
  "geometry": {"coordinates":[-123.772426,46.36345],"type":"Point"}
}