{
  "type": "Feature",
  "properties": {
    "addr:full":"14513 114th Ave NE Kirkland WA 98034",
    "addr:housenumber":"14513",
    "addr:postcode":"98034",
    "addr:street":"114Th Ave Ne",
    "iso:country":"US",
    "sg:address":"14513 114th Ave NE",
    "sg:city":"Kirkland",
    "sg:classifiers":[
        {
            "category":"Education",
            "subcategory":"School",
            "type":"Public Place"
        }
    ],
    "sg:phone":"+1 425 822 1482",
    "sg:postcode":"98034",
    "sg:province":"WA",
    "wof:name":"Primary Blue Design",
    "wof:placetype":"venue"
},
  "geometry": {"coordinates":[-122.18962500000001,47.734474],"type":"Point"}
}