{
  "type": "Feature",
  "properties": {
    "addr:full":"18430 33rd Ave W Lynnwood WA 98037",
    "addr:housenumber":"18430",
    "addr:postcode":"98037",
    "addr:street":"33Rd Ave W",
    "iso:country":"US",
    "sg:address":"18430 33rd Ave W",
    "sg:city":"Lynnwood",
    "sg:classifiers":[
        {
            "category":"Restaurant",
            "type":"Food & Drink"
        }
    ],
    "sg:menulink":"http://www.allmenus.com/wa/edmonds/48082-billy-mchales/menu/",
    "sg:phone":"+1 425 775 8500",
    "sg:postcode":"98037",
    "sg:province":"WA",
    "sg:tags":[
        "american"
    ],
    "wof:name":"Billy McHale's",
    "wof:placetype":"venue"
},
  "geometry": {"coordinates":[-122.277658,47.831876],"type":"Point"}
}