{
  "type": "Feature",
  "properties": {
    "addr:full":"1018 145th Pl SE Bellevue WA 98007",
    "addr:housenumber":"1018",
    "addr:postcode":"98007",
    "addr:street":"145Th Pl Se",
    "iso:country":"US",
    "sg:address":"1018 145th Pl SE",
    "sg:city":"Bellevue",
    "sg:classifiers":[
        {
            "category":"Professional",
            "type":"Services"
        }
    ],
    "sg:phone":"+1 425 747 9876",
    "sg:postcode":"98007",
    "sg:province":"WA",
    "sg:tags":[
        "establishment"
    ],
    "wof:name":"Briggs & Riley",
    "wof:placetype":"venue"
},
  "geometry": {"coordinates":[-122.14631300000001,47.600277],"type":"Point"}
}