{
  "type": "Feature",
  "properties": {
    "addr:full":"416 State Ave NE Olympia WA 98501",
    "addr:housenumber":"416",
    "addr:postcode":"98501",
    "addr:street":"State Ave Ne",
    "iso:country":"US",
    "sg:address":"416 State Ave NE",
    "sg:city":"Olympia",
    "sg:classifiers":[
        {
            "category":"Utilities",
            "subcategory":"Fuel Oil & Lpg",
            "type":"Services"
        },
        {
            "category":"Building & Trades",
            "subcategory":"Construction",
            "type":"Services"
        }
    ],
    "sg:phone":"+1 360 339 6577",
    "sg:postcode":"98501",
    "sg:province":"WA",
    "sg:tags":[
        "system",
        "specialty",
        "heating",
        "contractor",
        "oils-fuel",
        "air conditioning"
    ],
    "sg:website":"http://www.acmefuel.com",
    "wof:name":"Acme Fuel Co",
    "wof:placetype":"venue"
},
  "geometry": {"coordinates":[-122.897837,47.046046],"type":"Point"}
}