{
  "type": "Feature",
  "properties": {
    "addr:full":"5805 18th Ave SE Lacey WA 98503",
    "addr:housenumber":"5805",
    "addr:postcode":"98503",
    "addr:street":"18Th Ave Se",
    "iso:country":"US",
    "sg:address":"5805 18th Ave SE",
    "sg:city":"Lacey",
    "sg:classifiers":[
        {
            "category":"Health Services",
            "subcategory":"Health Practitioner",
            "type":"Services"
        }
    ],
    "sg:phone":"+1 253 376 8265",
    "sg:postcode":"98503",
    "sg:province":"WA",
    "wof:name":"Fun First Therapy Services",
    "wof:placetype":"venue"
},
  "geometry": {"coordinates":[-122.807062,47.032022],"type":"Point"}
}