{
  "type": "Feature",
  "properties": {
    "addr:full":"13524 E Sprague Ave Spokane Valley WA 99216",
    "addr:housenumber":"13524",
    "addr:postcode":"99216",
    "addr:street":"E Sprague Ave",
    "iso:country":"US",
    "sg:address":"13524 E Sprague Ave",
    "sg:city":"Spokane Valley",
    "sg:classifiers":[
        {
            "category":"Retail",
            "subcategory":"Auto Repair",
            "type":"Services"
        }
    ],
    "sg:phone":"+1 509 926 2967",
    "sg:postcode":"99216",
    "sg:province":"WA",
    "sg:tags":[
        "repairing",
        "automobile"
    ],
    "wof:name":"Ray & Roy's Repair",
    "wof:placetype":"venue"
},
  "geometry": {"coordinates":[-117.221621,47.656986],"type":"Point"}
}