{
  "type": "Feature",
  "properties": {
    "addr:full":"2609 5th Ave Seattle WA 98121",
    "addr:housenumber":"2609",
    "addr:postcode":"98121",
    "addr:street":"5Th Ave",
    "iso:country":"US",
    "sg:address":"2609 5th Ave",
    "sg:city":"Seattle",
    "sg:classifiers":[
        {
            "category":"Health Services",
            "subcategory":"Doctor",
            "type":"Services"
        },
        {
            "category":"Health Services",
            "subcategory":"Clinic",
            "type":"Services"
        },
        {
            "category":"Personal",
            "subcategory":"Massage",
            "type":"Services"
        },
        {
            "category":"Health Services",
            "subcategory":"Health Practitioner",
            "type":"Services"
        },
        {
            "category":"Health Services",
            "subcategory":"Chiropractor",
            "type":"Services"
        }
    ],
    "sg:phone":"+1 206 441 7984",
    "sg:postcode":"98121",
    "sg:province":"WA",
    "sg:tags":[
        "physician",
        "chiropractic",
        "medical",
        "acupuncture",
        "therapist",
        "medicine",
        "alternative",
        "surgeon",
        "physical"
    ],
    "sg:website":"www.belltownchiro.com",
    "wof:name":"Belltown Spine & Wellness",
    "wof:placetype":"venue"
},
  "geometry": {"coordinates":[-122.34693300000001,47.61795],"type":"Point"}
}