{
  "type": "Feature",
  "properties": {
    "addr:full":"123 Rodeo Trl Okanogan WA 98840",
    "addr:housenumber":"123",
    "addr:postcode":"98840",
    "addr:street":"Rodeo Trl",
    "iso:country":"US",
    "sg:address":"123 Rodeo Trl",
    "sg:city":"Okanogan",
    "sg:classifiers":[
        {
            "category":"Coffee & Tea",
            "type":"Food & Drink"
        },
        {
            "category":"Restaurant",
            "type":"Food & Drink"
        }
    ],
    "sg:phone":"+1 509 826 1329",
    "sg:postcode":"98840",
    "sg:province":"WA",
    "sg:tags":[
        "espresso"
    ],
    "wof:name":"Livestock Cafe",
    "wof:placetype":"venue"
},
  "geometry": {"coordinates":[-119.555977,48.374336],"type":"Point"}
}