{
  "type": "Feature",
  "properties": {
    "addr:full":"14205 SE 36th St Ste 100 Bellevue WA 98006",
    "addr:postcode":"14205;98006",
    "addr:street":"Se 36Th St Ste 100",
    "iso:country":"US",
    "sg:address":"14205 SE 36th St Ste 100",
    "sg:city":"Bellevue",
    "sg:classifiers":[
        {
            "category":"Arts & Performance",
            "subcategory":"Theater",
            "type":"Entertainment"
        },
        {
            "category":"Professional",
            "subcategory":"Employment Agencies",
            "type":"Services"
        },
        {
            "category":"Organizations",
            "subcategory":"Professional Association",
            "type":"Services"
        }
    ],
    "sg:phone":"+1 425 649 1111",
    "sg:postcode":"98006",
    "sg:province":"WA",
    "sg:tags":[
        "theatrical",
        "bureau",
        "talent",
        "modeling"
    ],
    "sg:website":"http://www.verizon.com",
    "wof:name":"Verizon",
    "wof:placetype":"venue"
},
  "geometry": {"coordinates":[-122.150899,47.578517],"type":"Point"}
}