{
  "type": "Feature",
  "properties": {
    "addr:full":"701 Harrison Ave Centralia WA 98531",
    "addr:housenumber":"701",
    "addr:postcode":"98531",
    "addr:street":"Harrison Ave",
    "iso:country":"US",
    "sg:address":"701 Harrison Ave",
    "sg:city":"Centralia",
    "sg:classifiers":[
        {
            "category":"Restaurant",
            "type":"Food & Drink"
        },
        {
            "category":"Ice Cream",
            "type":"Food & Drink"
        }
    ],
    "sg:menulink":"http://www.allmenus.com/wa/centralia-chehalis/192816-dairy-queen/menu/",
    "sg:phone":"+1 360 736 0218",
    "sg:postcode":"98531",
    "sg:province":"WA",
    "sg:tags":[
        "burger",
        "american",
        "ice",
        "cream"
    ],
    "wof:name":"Dairy Queen",
    "wof:placetype":"venue"
},
  "geometry": {"coordinates":[-122.971649,46.724029],"type":"Point"}
}