{
  "type": "Feature",
  "properties": {
    "addr:full":"4420 NE St Johns Rd Ste A Vancouver WA 98661",
    "addr:housenumber":"4420",
    "addr:postcode":"98661",
    "addr:street":"Ne St Johns Rd Ste A",
    "iso:country":"US",
    "sg:address":"4420 NE St Johns Rd Ste A",
    "sg:city":"Vancouver",
    "sg:classifiers":[
        {
            "category":"Shopping",
            "subcategory":"Jewelry",
            "type":"Retail Goods"
        }
    ],
    "sg:phone":"+1 360 695 2993",
    "sg:postcode":"98661",
    "sg:province":"WA",
    "wof:name":"St Johns Jewelers Inc",
    "wof:placetype":"venue"
},
  "geometry": {"coordinates":[-122.636638,45.653986],"type":"Point"}
}