{
  "type": "Feature",
  "properties": {
    "addr:full":"12406 N Division St Spokane WA 99218",
    "addr:housenumber":"12406",
    "addr:postcode":"99218",
    "addr:street":"N Division St",
    "iso:country":"US",
    "sg:address":"12406 N Division St",
    "sg:city":"Spokane",
    "sg:classifiers":[
        {
            "category":"Personal",
            "subcategory":"Beauty Salon",
            "type":"Services"
        }
    ],
    "sg:phone":"+1 509 466 8800",
    "sg:postcode":"99218",
    "sg:province":"WA",
    "sg:tags":[
        "shop"
    ],
    "wof:name":"Nails Spa 2000",
    "wof:placetype":"venue"
},
  "geometry": {"coordinates":[-117.40311199999999,47.772724],"type":"Point"}
}