{
  "type": "Feature",
  "properties": {
    "addr:full":"226 239th Way SE Sammamish WA 98074",
    "addr:housenumber":"226",
    "addr:postcode":"98074",
    "addr:street":"239Th Way Se",
    "iso:country":"US",
    "sg:address":"226 239th Way SE",
    "sg:city":"Sammamish",
    "sg:classifiers":[
        {
            "category":"Banks & Credit Unions",
            "subcategory":"Investment Brokerage",
            "type":"Services"
        }
    ],
    "sg:phone":"+1 425 837 0795",
    "sg:postcode":"98074",
    "sg:province":"WA",
    "wof:name":"Fisher Investments",
    "wof:placetype":"venue"
},
  "geometry": {"coordinates":[-122.02067700000001,47.608335],"type":"Point"}
}