{
  "type": "Feature",
  "properties": {
    "addr:full":"4425 140th Ave SW Rochester WA 98579",
    "addr:housenumber":"4425",
    "addr:postcode":"98579",
    "addr:street":"140Th Ave Sw",
    "iso:country":"US",
    "sg:address":"4425 140th Ave SW",
    "sg:city":"Rochester",
    "sg:classifiers":[
        {
            "category":"Professional",
            "subcategory":"Business Services",
            "type":"Services"
        }
    ],
    "sg:phone":"+1 360 956 3774",
    "sg:postcode":"98579",
    "sg:province":"WA",
    "sg:tags":[
        "association"
    ],
    "wof:name":"Earthwater Stencils",
    "wof:placetype":"venue"
},
  "geometry": {"coordinates":[-122.973192,46.883652],"type":"Point"}
}