{
  "type": "Feature",
  "properties": {
    "addr:full":"5220 N Market St Spokane WA 99217",
    "addr:housenumber":"5220",
    "addr:postcode":"99217",
    "addr:street":"N Market St",
    "iso:country":"US",
    "sg:address":"5220 N Market St",
    "sg:city":"Spokane",
    "sg:classifiers":[
        {
            "category":"Professional",
            "subcategory":"Art Services",
            "type":"Services"
        }
    ],
    "sg:phone":"+1 509 484 1700",
    "sg:postcode":"99217",
    "sg:province":"WA",
    "sg:tags":[
        "commercial",
        "graphic",
        "design"
    ],
    "wof:name":"Greenburo",
    "wof:placetype":"venue"
},
  "geometry": {"coordinates":[-117.364711,47.705402],"type":"Point"}
}