{
  "type": "Feature",
  "properties": {
    "addr:full":"2034 NW Market St Seattle WA 98107",
    "addr:housenumber":"2034",
    "addr:postcode":"98107",
    "addr:street":"Nw Market St",
    "iso:country":"US",
    "sg:address":"2034 NW Market St",
    "sg:city":"Seattle",
    "sg:classifiers":[
        {
            "category":"Wholesale",
            "subcategory":"Photographic Equipment",
            "type":"Manufacturing & Wholesale Goods"
        },
        {
            "category":"Shopping",
            "subcategory":"Photographic Equipment",
            "type":"Retail Goods"
        }
    ],
    "sg:phone":"+1 206 782 2433",
    "sg:postcode":"98107",
    "sg:province":"WA",
    "sg:tags":[
        "equipment-repair",
        "manufacturer",
        "supplies-wholesale",
        "supply"
    ],
    "sg:website":"http://www.cameratechs.com",
    "wof:name":"CameraTechs",
    "wof:placetype":"venue"
},
  "geometry": {"coordinates":[-122.383246,47.668692],"type":"Point"}
}