{
  "type": "Feature",
  "properties": {
    "addr:full":"1700 Seventh Ave Ste 116, PMB 405 Seattle WA 98101",
    "addr:housenumber":"1700;405",
    "addr:postcode":"98101",
    "addr:street":"Seventh Ave Ste 116 Pmb",
    "iso:country":"US",
    "sg:address":"1700 Seventh Ave Ste 116, PMB 405",
    "sg:city":"Seattle",
    "sg:classifiers":[
        {
            "category":"Travel",
            "subcategory":"Hotels & Motels",
            "type":"Entertainment"
        },
        {
            "category":"Travel",
            "subcategory":"Travel Agent",
            "type":"Entertainment"
        }
    ],
    "sg:phone":"+1 888 813 4569",
    "sg:postcode":"98101",
    "sg:province":"WA",
    "sg:tags":[
        "house",
        "rental",
        "guest",
        "vacation"
    ],
    "sg:website":"www.vacationhousedestinations.com",
    "wof:name":"VacationHouse Destinations",
    "wof:placetype":"venue"
},
  "geometry": {"coordinates":[-122.33545100000001,47.614062],"type":"Point"}
}