{
  "type": "Feature",
  "properties": {
    "addr:full":"112 Jefferson St NE Olympia WA 98501",
    "addr:housenumber":"112",
    "addr:postcode":"98501",
    "addr:street":"Jefferson St Ne",
    "iso:country":"US",
    "sg:address":"112 Jefferson St NE",
    "sg:city":"Olympia",
    "sg:classifiers":[
        {
            "category":"Restaurant",
            "type":"Food & Drink"
        }
    ],
    "sg:menulink":"http://www.allmenus.com/wa/olympia/48357-pizza-time/menu/",
    "sg:phone":"+1 360 956 9020",
    "sg:postcode":"98501",
    "sg:province":"WA",
    "sg:tags":[
        "american",
        "pizza"
    ],
    "wof:name":"Pizza Time",
    "wof:placetype":"venue"
},
  "geometry": {"coordinates":[-122.896773,47.045433],"type":"Point"}
}