{
  "type": "Feature",
  "properties": {
    "addr:full":"14500 Juanita Dr NE Kenmore WA 98028",
    "addr:housenumber":"14500",
    "addr:postcode":"98028",
    "addr:street":"Juanita Dr Ne",
    "iso:country":"US",
    "sg:address":"14500 Juanita Dr NE",
    "sg:city":"Kenmore",
    "sg:classifiers":[
        {
            "category":"Education",
            "subcategory":"University",
            "type":"Public Place"
        }
    ],
    "sg:phone":"+1 425 602 3361",
    "sg:postcode":"98028",
    "sg:province":"WA",
    "sg:tags":[
        "college"
    ],
    "sg:website":"www.simkincenter.bastyr.edu",
    "wof:name":"Simkin Center at Bastyr University",
    "wof:placetype":"venue"
},
  "geometry": {"coordinates":[-122.257014,47.733099],"type":"Point"}
}