{
  "type": "Feature",
  "properties": {
    "addr:full":"1615 N Ashland Ave East Wenatchee WA 98802",
    "addr:housenumber":"1615",
    "addr:postcode":"98802",
    "addr:street":"N Ashland Ave",
    "iso:country":"US",
    "sg:address":"1615 N Ashland Ave",
    "sg:city":"East Wenatchee",
    "sg:classifiers":[
        {
            "category":"Social Services",
            "subcategory":"Child Care",
            "type":"Services"
        }
    ],
    "sg:phone":"+1 509 884 6108",
    "sg:postcode":"98802",
    "sg:province":"WA",
    "sg:tags":[
        "day"
    ],
    "wof:name":"Country Kiddies Daycare",
    "wof:placetype":"venue"
},
  "geometry": {"coordinates":[-120.29431700000001,47.431234],"type":"Point"}
}