{
  "type": "Feature",
  "properties": {
    "addr:full":"3906 E Beach Rd Port Angeles WA 98363",
    "addr:housenumber":"3906",
    "addr:postcode":"98363",
    "addr:street":"E Beach Rd",
    "iso:country":"US",
    "sg:address":"3906 E Beach Rd",
    "sg:city":"Port Angeles",
    "sg:classifiers":[
        {
            "category":"Organizations",
            "subcategory":"Professional Association",
            "type":"Services"
        }
    ],
    "sg:phone":"+1 360 928 9728",
    "sg:postcode":"98363",
    "sg:province":"WA",
    "wof:name":"Crescent Water Assn",
    "wof:placetype":"venue"
},
  "geometry": {"coordinates":[-123.80551,48.094269],"type":"Point"}
}