{
  "type": "Feature",
  "properties": {
    "addr:full":"301 E Schneider Rd Shelton WA 98584",
    "addr:housenumber":"301",
    "addr:postcode":"98584",
    "addr:street":"E Schneider Rd",
    "iso:country":"US",
    "sg:address":"301 E Schneider Rd",
    "sg:city":"Shelton",
    "sg:classifiers":[
        {
            "category":"Wholesale",
            "subcategory":"Durable Goods & Equipment",
            "type":"Manufacturing & Wholesale Goods"
        }
    ],
    "sg:phone":"+1 360 490 0904",
    "sg:postcode":"98584",
    "sg:province":"WA",
    "wof:name":"Production Resource Network",
    "wof:placetype":"venue"
},
  "geometry": {"coordinates":[-122.93667600000001,47.227234],"type":"Point"}
}