{
  "type": "Feature",
  "properties": {
    "addr:full":"1212 SW 349th St Federal Way WA 98023",
    "addr:housenumber":"1212",
    "addr:postcode":"98023",
    "addr:street":"Sw 349Th St",
    "iso:country":"US",
    "sg:address":"1212 SW 349th St",
    "sg:city":"Federal Way",
    "sg:classifiers":[
        {
            "category":"Health Services",
            "subcategory":"Health Practitioner",
            "type":"Services"
        }
    ],
    "sg:phone":"+1 253 255 1342",
    "sg:postcode":"98023",
    "sg:province":"WA",
    "wof:name":"Weller Dann Marie Arnp",
    "wof:placetype":"venue"
},
  "geometry": {"coordinates":[-122.35068,47.288946],"type":"Point"}
}