{
  "type": "Feature",
  "properties": {
    "addr:full":"2615 F St SE Auburn WA 98002",
    "addr:housenumber":"2615",
    "addr:postcode":"98002",
    "addr:street":"F St Se",
    "iso:country":"US",
    "sg:address":"2615 F St SE",
    "sg:city":"Auburn",
    "sg:classifiers":[
        {
            "category":"Building & Trades",
            "subcategory":"Construction",
            "type":"Services"
        }
    ],
    "sg:phone":"+1 253 735 4948",
    "sg:postcode":"98002",
    "sg:province":"WA",
    "sg:tags":[
        "floor",
        "laying",
        "contractor"
    ],
    "wof:name":"Garcias Flooring",
    "wof:placetype":"venue"
},
  "geometry": {"coordinates":[-122.22143800000001,47.284752],"type":"Point"}
}