{
  "type": "Feature",
  "properties": {
    "addr:full":"2710 McKenzie Ave Bellingham WA 98225",
    "addr:housenumber":"2710",
    "addr:postcode":"98225",
    "addr:street":"Mckenzie Ave",
    "iso:country":"US",
    "sg:address":"2710 McKenzie Ave",
    "sg:city":"Bellingham",
    "sg:classifiers":[
        {
            "category":"Education",
            "subcategory":"School",
            "type":"Public Place"
        }
    ],
    "sg:phone":"+1 360 733 1024",
    "sg:postcode":"98225",
    "sg:province":"WA",
    "sg:tags":[
        "child",
        "day",
        "care"
    ],
    "wof:name":"Bellingham Cooperative Schools",
    "wof:placetype":"venue"
},
  "geometry": {"coordinates":[-122.482833,48.719142],"type":"Point"}
}