{
  "type": "Feature",
  "properties": {
    "addr:full":"11504 SE Mill Plain Blvd Vancouver WA 98684",
    "addr:postcode":"11504;98684",
    "addr:street":"Se Mill Plain Blvd",
    "iso:country":"US",
    "sg:address":"11504 SE Mill Plain Blvd",
    "sg:city":"Vancouver",
    "sg:classifiers":[
        {
            "category":"Personal",
            "subcategory":"Tanning Parlor",
            "type":"Services"
        }
    ],
    "sg:phone":"+1 360 896 9100",
    "sg:postcode":"98684",
    "sg:province":"WA",
    "sg:tags":[
        "salon"
    ],
    "wof:name":"Tanrio",
    "wof:placetype":"venue"
},
  "geometry": {"coordinates":[-122.55278300000001,45.620877],"type":"Point"}
}