{
  "type": "Feature",
  "properties": {
    "addr:full":"5700 23rd Dr W Everett WA 98203",
    "addr:housenumber":"5700",
    "addr:postcode":"98203",
    "addr:street":"23Rd Dr W",
    "iso:country":"US",
    "sg:address":"5700 23rd Dr W",
    "sg:city":"Everett",
    "sg:classifiers":[
        {
            "category":"Place Of Worship",
            "subcategory":"Church",
            "type":"Public Place"
        },
        {
            "category":"Place Of Worship",
            "type":"Public Place"
        }
    ],
    "sg:phone":"+1 425 407 1119",
    "sg:postcode":"98203",
    "sg:province":"WA",
    "sg:tags":[
        "churches-interdenominational",
        "denomination",
        "churches-various",
        "churches-non-denominational"
    ],
    "sg:website":"http://www.northshorechristian.org",
    "wof:name":"Christian Northshore Church",
    "wof:placetype":"venue"
},
  "geometry": {"coordinates":[-122.263458,47.945332],"type":"Point"}
}