{
  "type": "Feature",
  "properties": {
    "addr:full":"112 W Montgomery Ave Spokane WA 99205",
    "addr:housenumber":"112",
    "addr:postcode":"99205",
    "addr:street":"W Montgomery Ave",
    "iso:country":"US",
    "sg:address":"112 W Montgomery Ave",
    "sg:city":"Spokane",
    "sg:classifiers":[
        {
            "category":"Shopping",
            "subcategory":"Florist",
            "type":"Retail Goods"
        }
    ],
    "sg:phone":"+1 509 216 8698",
    "sg:postcode":"99205",
    "sg:province":"WA",
    "wof:name":"Petal Impressions Floral Desig",
    "wof:placetype":"venue"
},
  "geometry": {"coordinates":[-117.414162,47.678612],"type":"Point"}
}