{
  "type": "Feature",
  "properties": {
    "addr:full":"20906 114th Pl SE Kent WA 98031",
    "addr:housenumber":"20906",
    "addr:postcode":"98031",
    "addr:street":"114Th Pl Se",
    "iso:country":"US",
    "sg:address":"20906 114th Pl SE",
    "sg:city":"Kent",
    "sg:classifiers":[
        {
            "category":"Utilities",
            "subcategory":"Telephone",
            "type":"Services"
        }
    ],
    "sg:phone":"+1 206 841 0440",
    "sg:postcode":"98031",
    "sg:province":"WA",
    "sg:tags":[
        "communications"
    ],
    "wof:name":"Mile Post 1",
    "wof:placetype":"venue"
},
  "geometry": {"coordinates":[-122.188635,47.414724],"type":"Point"}
}