{
  "type": "Feature",
  "properties": {
    "iso:country":"US",
    "sg:address":"1615 Schurman Way",
    "sg:city":"Woodland",
    "sg:classifiers":[
        {
            "category":"Manufacturing",
            "subcategory":"Lumber",
            "type":"Manufacturing & Wholesale Goods"
        }
    ],
    "sg:phone":"+1 360 225 3196",
    "sg:postcode":"98674",
    "sg:province":"WA",
    "sg:tags":[
        "product",
        "forest",
        "gathering"
    ],
    "wof:name":"Denharco USA Inc",
    "wof:placetype":"venue"
},
  "geometry": {"coordinates":[-122.762269,45.916564],"type":"Point"}
}