{
  "type": "Feature",
  "properties": {
    "addr:full":"3300 W Mc Graw St Seattle WA 98199",
    "addr:housenumber":"3300",
    "addr:postcode":"98199",
    "addr:street":"W Mc Graw St",
    "iso:country":"US",
    "sg:address":"3300 W Mc Graw St",
    "sg:city":"Seattle",
    "sg:classifiers":[
        {
            "category":"Real Estate",
            "subcategory":"Real Estate Agent",
            "type":"Services"
        }
    ],
    "sg:phone":"+1 206 283 3604",
    "sg:postcode":"98199",
    "sg:province":"WA",
    "wof:name":"Coldwell Banker",
    "wof:placetype":"venue"
},
  "geometry": {"coordinates":[-122.40100099999999,47.639554],"type":"Point"}
}