{
  "type": "Feature",
  "properties": {
    "addr:full":"7609 Steilacoom Blvd SW Lakewood WA 98498",
    "addr:housenumber":"7609",
    "addr:postcode":"98498",
    "addr:street":"Steilacoom Blvd Sw",
    "iso:country":"US",
    "sg:address":"7609 Steilacoom Blvd SW",
    "sg:city":"Lakewood",
    "sg:classifiers":[
        {
            "category":"Utilities",
            "subcategory":"Mobile Phone",
            "type":"Services"
        }
    ],
    "sg:phone":"+1 253 581 0666",
    "sg:postcode":"98498",
    "sg:province":"WA",
    "sg:tags":[
        "telephone",
        "cellular"
    ],
    "wof:name":"Area Codes",
    "wof:placetype":"venue"
},
  "geometry": {"coordinates":[-122.540277,47.179393],"type":"Point"}
}