{
  "type": "Feature",
  "properties": {
    "addr:full":"605 Boylston Ave E Seattle WA 98102",
    "addr:housenumber":"605",
    "addr:postcode":"98102",
    "addr:street":"Boylston Ave E",
    "iso:country":"US",
    "sg:address":"605 Boylston Ave E",
    "sg:city":"Seattle",
    "sg:classifiers":[
        {
            "category":"Retail",
            "subcategory":"Repair Shop",
            "type":"Services"
        }
    ],
    "sg:phone":"+1 206 324 3759",
    "sg:postcode":"98102",
    "sg:province":"WA",
    "wof:name":"My Cleaning Adventure",
    "wof:placetype":"venue"
},
  "geometry": {"coordinates":[-122.323103,47.625082],"type":"Point"}
}