{
  "type": "Feature",
  "properties": {
    "addr:full":"13336 Beacon Coal Mine Rd S Seattle WA 98178",
    "addr:housenumber":"13336",
    "addr:postcode":"98178",
    "addr:street":"Beacon Coal Mine Rd S",
    "iso:country":"US",
    "sg:address":"13336 Beacon Coal Mine Rd S",
    "sg:city":"Seattle",
    "sg:classifiers":[
        {
            "category":"Mining & Drilling",
            "type":"Manufacturing & Wholesale Goods"
        }
    ],
    "sg:phone":"+1 206 947 6345",
    "sg:postcode":"98178",
    "sg:province":"WA",
    "sg:tags":[
        "bituminous",
        "surface"
    ],
    "wof:name":"Beacon Coal Mine Trucking",
    "wof:placetype":"venue"
},
  "geometry": {"coordinates":[-122.261861,47.487765],"type":"Point"}
}