{
  "type": "Feature",
  "properties": {
    "addr:full":"506 Surry Rd Wenatchee WA 98801",
    "addr:housenumber":"506",
    "addr:postcode":"98801",
    "addr:street":"Surry Rd",
    "iso:country":"US",
    "sg:address":"506 Surry Rd",
    "sg:city":"Wenatchee",
    "sg:classifiers":[
        {
            "category":"Manufacturing",
            "subcategory":"Musical Instruments",
            "type":"Manufacturing & Wholesale Goods"
        }
    ],
    "sg:phone":"+1 509 662 7275",
    "sg:postcode":"98801",
    "sg:province":"WA",
    "sg:tags":[
        "parts"
    ],
    "wof:name":"Song Smith String Instrument",
    "wof:placetype":"venue"
},
  "geometry": {"coordinates":[-120.35929899999999,47.430591],"type":"Point"}
}