{
  "type": "Feature",
  "properties": {
    "addr:full":"26418 R St Ocean Park WA 98640",
    "addr:housenumber":"26418",
    "addr:postcode":"98640",
    "addr:street":"R St;Park",
    "iso:country":"US",
    "sg:address":"26418 R St",
    "sg:city":"Ocean Park",
    "sg:classifiers":[
        {
            "category":"Building & Trades",
            "subcategory":"Construction",
            "type":"Services"
        }
    ],
    "sg:phone":"+1 360 665 5373",
    "sg:postcode":"98640",
    "sg:province":"WA",
    "sg:tags":[
        "general",
        "contractor"
    ],
    "wof:name":"Jim Mortensen Construction",
    "wof:placetype":"venue"
},
  "geometry": {"coordinates":[-124.047264,46.49472],"type":"Point"}
}