{
  "type": "Feature",
  "properties": {
    "iso:country":"US",
    "sg:address":"224 8th St",
    "sg:city":"Leavenworth",
    "sg:classifiers":[
        {
            "category":"Wholesale",
            "subcategory":"Hardware",
            "type":"Manufacturing & Wholesale Goods"
        }
    ],
    "sg:phone":"+1 509 548 0860",
    "sg:postcode":"98826",
    "sg:province":"WA",
    "sg:tags":[
        "cutlery"
    ],
    "wof:name":"Pretty Sharp",
    "wof:placetype":"venue"
},
  "geometry": {"coordinates":[-120.662085,47.594916],"type":"Point"}
}