{
  "type": "Feature",
  "properties": {
    "addr:full":"9725 SE 43rd St Mercer Island WA 98040",
    "addr:housenumber":"9725",
    "addr:postcode":"98040",
    "addr:street":"Se 43Rd St",
    "iso:country":"US",
    "sg:address":"9725 SE 43rd St",
    "sg:city":"Mercer Island",
    "sg:classifiers":[
        {
            "category":"Shopping",
            "subcategory":"Clothing, Apparel, & Fashions",
            "type":"Retail Goods"
        }
    ],
    "sg:phone":"+1 206 232 2302",
    "sg:postcode":"98040",
    "sg:province":"WA",
    "wof:name":"Gamble Bay Outfitters",
    "wof:placetype":"venue"
},
  "geometry": {"coordinates":[-122.209444,47.569265],"type":"Point"}
}