{
  "type": "Feature",
  "properties": {
    "addr:full":"19937 NE 154th St Woodinville WA 98077",
    "addr:housenumber":"19937",
    "addr:postcode":"98077",
    "addr:street":"Ne 154Th St",
    "iso:country":"US",
    "sg:address":"19937 NE 154th St",
    "sg:city":"Woodinville",
    "sg:classifiers":[
        {
            "category":"Home & Garden",
            "subcategory":"Home Furnishings",
            "type":"Retail Goods"
        },
        {
            "category":"Professional",
            "subcategory":"Art Services",
            "type":"Services"
        }
    ],
    "sg:phone":"+1 425 885 5897",
    "sg:postcode":"98077",
    "sg:province":"WA",
    "sg:tags":[
        "draperies",
        "designer",
        "window",
        "treatment",
        "interior",
        "curtain",
        "decorator"
    ],
    "wof:name":"Emkey Designs",
    "wof:placetype":"venue"
},
  "geometry": {"coordinates":[-122.070317,47.739422],"type":"Point"}
}