{
  "type": "Feature",
  "properties": {
    "addr:full":"1414 E Liberty Ave Spokane WA 99207",
    "addr:housenumber":"1414",
    "addr:postcode":"99207",
    "addr:street":"E Liberty Ave",
    "iso:country":"US",
    "sg:address":"1414 E Liberty Ave",
    "sg:city":"Spokane",
    "sg:classifiers":[
        {
            "category":"Building & Trades",
            "subcategory":"Construction",
            "type":"Services"
        }
    ],
    "sg:phone":"+1 509 482 1206",
    "sg:postcode":"99207",
    "sg:province":"WA",
    "sg:tags":[
        "house"
    ],
    "wof:name":"A Little Bit of Everythin",
    "wof:placetype":"venue"
},
  "geometry": {"coordinates":[-117.388381,47.687542],"type":"Point"}
}