{
  "type": "Feature",
  "properties": {
    "addr:full":"12691 US Hwy 12 Naches WA 98937",
    "addr:housenumber":"12691",
    "addr:postcode":"98937",
    "addr:street":"Us Hwy 12",
    "iso:country":"US",
    "sg:address":"12691 US Hwy 12",
    "sg:city":"Naches",
    "sg:classifiers":[
        {
            "category":"Food & Beverages",
            "subcategory":"Fruits & Vegetables",
            "type":"Retail Goods"
        }
    ],
    "sg:phone":"+1 509 653 2041",
    "sg:postcode":"98937",
    "sg:province":"WA",
    "sg:tags":[
        "shop",
        "bar",
        "gift",
        "rental",
        "espresso",
        "tanning",
        "stand",
        "ski"
    ],
    "wof:name":"Little Red Schoolhouse",
    "wof:placetype":"venue"
},
  "geometry": {"coordinates":[-120.75030099999999,46.742324],"type":"Point"}
}