{
  "type": "Feature",
  "properties": {
    "addr:full":"18770 80th Pl S Kent WA 98032",
    "addr:housenumber":"18770",
    "addr:postcode":"98032",
    "addr:street":"80Th Pl S",
    "iso:country":"US",
    "sg:address":"18770 80th Pl S",
    "sg:city":"Kent",
    "sg:classifiers":[
        {
            "category":"Manufacturing",
            "subcategory":"Tools & Machinery",
            "type":"Manufacturing & Wholesale Goods"
        }
    ],
    "sg:phone":"+1 425 291 9501",
    "sg:postcode":"98032",
    "sg:province":"WA",
    "sg:tags":[
        "contractor"
    ],
    "sg:website":"www.awardmetals.com",
    "wof:name":"Award Metals Inc",
    "wof:placetype":"venue"
},
  "geometry": {"coordinates":[-122.232238,47.440207],"type":"Point"}
}