{
  "type": "Feature",
  "properties": {
    "addr:full":"418 NE Repass Rd Vancouver WA 98665",
    "addr:housenumber":"418",
    "addr:postcode":"98665",
    "addr:street":"Ne Repass Rd",
    "iso:country":"US",
    "sg:address":"418 NE Repass Rd",
    "sg:city":"Vancouver",
    "sg:classifiers":[
        {
            "category":"Manufacturing",
            "subcategory":"Tools & Machinery",
            "type":"Manufacturing & Wholesale Goods"
        }
    ],
    "sg:phone":"+1 360 619 0004",
    "sg:postcode":"98665",
    "sg:province":"WA",
    "sg:tags":[
        "machine",
        "shop"
    ],
    "wof:name":"A & L Mold & Machine",
    "wof:placetype":"venue"
},
  "geometry": {"coordinates":[-122.666971,45.675233],"type":"Point"}
}