{
  "type": "Feature",
  "properties": {
    "addr:full":"11461 Marine View Dr SW Seattle WA 98146",
    "addr:housenumber":"11461",
    "addr:postcode":"98146",
    "addr:street":"Marine View Dr Sw",
    "iso:country":"US",
    "sg:address":"11461 Marine View Dr SW",
    "sg:city":"Seattle",
    "sg:classifiers":[
        {
            "category":"Building & Trades",
            "subcategory":"Locksmith",
            "type":"Services"
        }
    ],
    "sg:phone":"+1 206 701 6698",
    "sg:postcode":"98146",
    "sg:province":"WA",
    "sg:tags":[
        "key"
    ],
    "wof:name":"Locksmith Emergency",
    "wof:placetype":"venue"
},
  "geometry": {"coordinates":[-122.378362,47.499776],"type":"Point"}
}