{
  "type": "Feature",
  "properties": {
    "addr:full":"5411 100th St SW Lakewood WA 98499",
    "addr:housenumber":"5411",
    "addr:postcode":"98499",
    "addr:street":"100Th St Sw",
    "iso:country":"US",
    "sg:address":"5411 100th St SW",
    "sg:city":"Lakewood",
    "sg:classifiers":[
        {
            "category":"Food & Beverages",
            "subcategory":"Specialty",
            "type":"Retail Goods"
        },
        {
            "category":"Restaurant",
            "type":"Food & Drink"
        }
    ],
    "sg:phone":"+1 253 582 6673",
    "sg:postcode":"98499",
    "sg:province":"WA",
    "sg:tags":[
        "shop",
        "espresso",
        "coffee",
        "eating",
        "bar"
    ],
    "wof:name":"The White House Coffee Bar",
    "wof:placetype":"venue"
},
  "geometry": {"coordinates":[-122.508912,47.166638],"type":"Point"}
}