{
  "type": "Feature",
  "properties": {
    "addr:full":"3720 6th Ave Tacoma WA 98406",
    "addr:housenumber":"3720",
    "addr:postcode":"98406",
    "addr:street":"6Th Ave",
    "iso:country":"US",
    "sg:address":"3720 6th Ave",
    "sg:city":"Tacoma",
    "sg:classifiers":[
        {
            "category":"Health Services",
            "subcategory":"Medical Lab",
            "type":"Services"
        },
        {
            "category":"Health Services",
            "subcategory":"Dentist",
            "type":"Services"
        }
    ],
    "sg:phone":"+1 253 752 1320",
    "sg:postcode":"98406",
    "sg:province":"WA",
    "sg:tags":[
        "denture",
        "laboratory",
        "dental",
        "clinic",
        "dentists-prosthodontists"
    ],
    "sg:website":"http://www.olydental.com",
    "wof:name":"Olympic Dental & Denture Center",
    "wof:placetype":"venue"
},
  "geometry": {"coordinates":[-122.48539700000001,47.255268],"type":"Point"}
}