{
  "type": "Feature",
  "properties": {
    "addr:full":"921 Bridge St Clarkston WA 99403",
    "addr:housenumber":"921",
    "addr:postcode":"99403",
    "addr:street":"Bridge St",
    "iso:country":"US",
    "sg:address":"921 Bridge St",
    "sg:city":"Clarkston",
    "sg:classifiers":[
        {
            "category":"Autos & Motor Vehicles",
            "subcategory":"Auto Supplies",
            "type":"Retail Goods"
        },
        {
            "category":"Retail",
            "subcategory":"Auto Repair",
            "type":"Services"
        },
        {
            "category":"Building & Trades",
            "subcategory":"Electrical",
            "type":"Services"
        }
    ],
    "sg:phone":"+1 509 758 6468",
    "sg:postcode":"99403",
    "sg:province":"WA",
    "sg:tags":[
        "electrician",
        "electric",
        "automobile",
        "accessory",
        "parts",
        "accessories-wholesale",
        "part",
        "manufacturer"
    ],
    "wof:name":"Wae",
    "wof:placetype":"venue"
},
  "geometry": {"coordinates":[-117.049753,46.419922],"type":"Point"}
}