{
  "type": "Feature",
  "properties": {
    "addr:full":"109 Carpenter Rd NE Lacey WA 98516",
    "addr:housenumber":"109",
    "addr:postcode":"98516",
    "addr:street":"Carpenter Rd Ne",
    "iso:country":"US",
    "sg:address":"109 Carpenter Rd NE",
    "sg:city":"Lacey",
    "sg:classifiers":[
        {
            "category":"Wholesale",
            "subcategory":"Auto Parts",
            "type":"Manufacturing & Wholesale Goods"
        }
    ],
    "sg:phone":"+1 360 413 0658",
    "sg:postcode":"98516",
    "sg:province":"WA",
    "sg:tags":[
        "automobile",
        "rebuilt"
    ],
    "wof:name":"Lacey Auto Wrecking",
    "wof:placetype":"venue"
},
  "geometry": {"coordinates":[-122.796638,47.054105],"type":"Point"}
}