{
  "type": "Feature",
  "properties": {
    "addr:full":"1326 King St Bellingham WA 98229",
    "addr:housenumber":"1326",
    "addr:postcode":"98229",
    "addr:street":"King St",
    "iso:country":"US",
    "sg:address":"1326 King St",
    "sg:city":"Bellingham",
    "sg:classifiers":[
        {
            "category":"Personal",
            "subcategory":"Beauty Salon",
            "type":"Services"
        }
    ],
    "sg:phone":"+1 360 671 9588",
    "sg:postcode":"98229",
    "sg:province":"WA",
    "wof:name":"Cindy's Salon",
    "wof:placetype":"venue"
},
  "geometry": {"coordinates":[-122.463747,48.745405],"type":"Point"}
}