{
  "type": "Feature",
  "properties": {
    "addr:full":"1527 Overhulse Rd NW Olympia WA 98502",
    "addr:housenumber":"1527",
    "addr:postcode":"olympia wa 98502",
    "addr:street":"Overhulse Rd Nw",
    "iso:country":"US",
    "sg:address":"1527 Overhulse Rd NW",
    "sg:city":"Olympia",
    "sg:classifiers":[
        {
            "category":"Professional",
            "subcategory":"Management & Consulting",
            "type":"Services"
        }
    ],
    "sg:phone":"+1 360 866 9060",
    "sg:postcode":"98502",
    "sg:province":"WA",
    "sg:tags":[
        "business"
    ],
    "wof:name":"Applied Hydrology NW LLC",
    "wof:placetype":"venue"
},
  "geometry": {"coordinates":[-122.97076300000001,47.055817],"type":"Point"}
}