{
  "type": "Feature",
  "properties": {
    "addr:full":"15408 Union Ave SW Lakewood WA 98498",
    "addr:housenumber":"15408",
    "addr:postcode":"98498",
    "addr:street":"Union Ave Sw",
    "iso:country":"US",
    "sg:address":"15408 Union Ave SW",
    "sg:city":"Lakewood",
    "sg:classifiers":[
        {
            "category":"Retail",
            "subcategory":"Auto Repair",
            "type":"Services"
        }
    ],
    "sg:phone":"+1 253 565 0915",
    "sg:postcode":"98498",
    "sg:province":"WA",
    "sg:tags":[
        "towing",
        "wrecker"
    ],
    "wof:name":"Gibbon & Sons Towing",
    "wof:placetype":"venue"
},
  "geometry": {"coordinates":[-122.557999,47.119499],"type":"Point"}
}