{
  "type": "Feature",
  "properties": {
    "addr:full":"3202 Laurel Dr Everett WA 98201",
    "addr:housenumber":"3202",
    "addr:postcode":"98201",
    "addr:street":"Laurel Dr",
    "iso:country":"US",
    "sg:address":"3202 Laurel Dr",
    "sg:city":"Everett",
    "sg:classifiers":[
        {
            "category":"Professional",
            "subcategory":"Business Services",
            "type":"Services"
        }
    ],
    "sg:phone":"+1 425 339 1184",
    "sg:postcode":"98201",
    "sg:province":"WA",
    "sg:tags":[
        "consultant",
        "coach"
    ],
    "wof:name":"Hanson & Assoc",
    "wof:placetype":"venue"
},
  "geometry": {"coordinates":[-122.221069,47.974773],"type":"Point"}
}