{
  "type": "Feature",
  "properties": {
    "addr:full":"20324 19th Ave NE Ste B Shoreline WA 98155",
    "addr:housenumber":"20324",
    "addr:postcode":"98155",
    "addr:street":"19Th Ave Ne Ste B",
    "iso:country":"US",
    "sg:address":"20324 19th Ave NE Ste B",
    "sg:city":"Shoreline",
    "sg:classifiers":[
        {
            "category":"Real Estate",
            "subcategory":"Real Estate Services",
            "type":"Services"
        },
        {
            "category":"Real Estate",
            "subcategory":"Real Estate Agent",
            "type":"Services"
        }
    ],
    "sg:phone":"+1 206 363 3921",
    "sg:postcode":"98155",
    "sg:province":"WA",
    "sg:tags":[
        "buyer",
        "broker"
    ],
    "sg:website":"http://www.ballingerrealty.net",
    "wof:name":"Ballinger Realty Inc",
    "wof:placetype":"venue"
},
  "geometry": {"coordinates":[-122.30865900000001,47.776333],"type":"Point"}
}