{
  "type": "Feature",
  "properties": {
    "addr:full":"9702 NE Burton Rd Vancouver WA 98662",
    "addr:housenumber":"9702",
    "addr:postcode":"98662",
    "addr:street":"Ne Burton Rd",
    "iso:country":"US",
    "sg:address":"9702 NE Burton Rd",
    "sg:city":"Vancouver",
    "sg:classifiers":[
        {
            "category":"Wholesale",
            "subcategory":"Electrical",
            "type":"Manufacturing & Wholesale Goods"
        }
    ],
    "sg:phone":"+1 360 260 1419",
    "sg:postcode":"98662",
    "sg:province":"WA",
    "sg:tags":[
        "assembler",
        "electronic",
        "parts"
    ],
    "wof:name":"E-Assembly",
    "wof:placetype":"venue"
},
  "geometry": {"coordinates":[-122.573178,45.640002],"type":"Point"}
}