{
  "type": "Feature",
  "properties": {
    "addr:full":"310 Peters St W Wenatchee WA 98801",
    "addr:housenumber":"310",
    "addr:postcode":"98801",
    "addr:street":"Peters St W",
    "iso:country":"US",
    "sg:address":"310 Peters St W",
    "sg:city":"Wenatchee",
    "sg:classifiers":[
        {
            "category":"Building & Trades",
            "subcategory":"Construction",
            "type":"Services"
        }
    ],
    "sg:phone":"+1 509 662 6742",
    "sg:postcode":"98801",
    "sg:province":"WA",
    "sg:tags":[
        "general",
        "contractor"
    ],
    "wof:name":"Pro Home Svc & Construction",
    "wof:placetype":"venue"
},
  "geometry": {"coordinates":[-120.34048199999999,47.472923],"type":"Point"}
}