{
  "type": "Feature",
  "properties": {
    "addr:full":"26135 SE 39th Way Issaquah WA 98029",
    "addr:postcode":"26135;98029",
    "addr:street":"Se 39Th Way",
    "iso:country":"US",
    "sg:address":"26135 SE 39th Way",
    "sg:city":"Issaquah",
    "sg:classifiers":[
        {
            "category":"Retail",
            "subcategory":"Laundry & Dry Cleaning",
            "type":"Services"
        }
    ],
    "sg:phone":"+1 425 391 3574",
    "sg:postcode":"98029",
    "sg:province":"WA",
    "sg:tags":[
        "launderer",
        "industrial"
    ],
    "wof:name":"Cintas Corp",
    "wof:placetype":"venue"
},
  "geometry": {"coordinates":[-121.99066000000001,47.574398],"type":"Point"}
}