{
  "type": "Feature",
  "properties": {
    "addr:full":"310 S 3rd St Yakima WA 98901",
    "addr:housenumber":"310",
    "addr:postcode":"98901",
    "addr:street":"S 3Rd St",
    "iso:country":"US",
    "sg:address":"310 S 3rd St",
    "sg:city":"Yakima",
    "sg:classifiers":[
        {
            "category":"Social Services",
            "subcategory":"Child Care",
            "type":"Services"
        }
    ],
    "sg:phone":"+1 509 453 1788",
    "sg:postcode":"98901",
    "sg:province":"WA",
    "wof:name":"Los Ninos",
    "wof:placetype":"venue"
},
  "geometry": {"coordinates":[-120.500767,46.598002],"type":"Point"}
}