{
  "type": "Feature",
  "properties": {
    "addr:full":"304 N 2nd St Roslyn WA 98941",
    "addr:housenumber":"304",
    "addr:postcode":"98941",
    "addr:street":"N 2Nd St",
    "iso:country":"US",
    "sg:address":"304 N 2nd St",
    "sg:city":"Roslyn",
    "sg:classifiers":[
        {
            "category":"Organizations",
            "subcategory":"Religious Organization",
            "type":"Services"
        }
    ],
    "sg:phone":"+1 509 649 2283",
    "sg:postcode":"98941",
    "sg:province":"WA",
    "sg:tags":[
        "church"
    ],
    "wof:name":"Calvary Episcopal Church",
    "wof:placetype":"venue"
},
  "geometry": {"coordinates":[-120.99609599999999,47.224545],"type":"Point"}
}