{
  "type": "Feature",
  "properties": {
    "addr:full":"4444 Woodlawn Ave N Seattle WA 98103",
    "addr:housenumber":"4444",
    "addr:postcode":"98103",
    "addr:street":"Woodlawn Ave N",
    "iso:country":"US",
    "sg:address":"4444 Woodlawn Ave N",
    "sg:city":"Seattle",
    "sg:classifiers":[
        {
            "category":"Manufacturing",
            "subcategory":"Petroleum Products",
            "type":"Manufacturing & Wholesale Goods"
        },
        {
            "category":"Utilities",
            "subcategory":"Fuel Oil & Lpg",
            "type":"Services"
        }
    ],
    "sg:phone":"+1 206 204 1670",
    "sg:postcode":"98103",
    "sg:province":"WA",
    "sg:tags":[
        "oils-fuel-wholesale",
        "oils-fuel",
        "manufacturer"
    ],
    "wof:name":"Propel Biofuels Inc.",
    "wof:placetype":"venue"
},
  "geometry": {"coordinates":[-122.338539,47.661101],"type":"Point"}
}