{
  "type": "Feature",
  "properties": {
    "iso:country":"US",
    "sg:address":"1101 E Pike St",
    "sg:city":"Seattle",
    "sg:classifiers":[
        {
            "category":"Home & Garden",
            "subcategory":"Home Furnishings",
            "type":"Retail Goods"
        }
    ],
    "sg:phone":"+1 206 322 6020",
    "sg:postcode":"98122",
    "sg:province":"WA",
    "wof:name":"Bagni Volpi Noemi USA",
    "wof:placetype":"venue"
},
  "geometry": {"coordinates":[-122.316838,47.614101],"type":"Point"}
}