{
  "type": "Feature",
  "properties": {
    "addr:full":"2207 Fairview Ave E Seattle WA 98102",
    "addr:housenumber":"2207",
    "addr:postcode":"98102",
    "addr:street":"Fairview Ave E",
    "iso:country":"US",
    "sg:address":"2207 Fairview Ave E",
    "sg:city":"Seattle",
    "sg:classifiers":[
        {
            "category":"Food & Beverages",
            "subcategory":"Bakery",
            "type":"Retail Goods"
        }
    ],
    "sg:phone":"+1 206 726 8541",
    "sg:postcode":"98102",
    "sg:province":"WA",
    "sg:tags":[
        "bakers-wholesale"
    ],
    "wof:name":"Sophie's Donuts",
    "wof:placetype":"venue"
},
  "geometry": {"coordinates":[-122.32942300000001,47.638331],"type":"Point"}
}