{
  "type": "Feature",
  "properties": {
    "addr:full":"32706 US Hwy 97 Oroville WA 98844",
    "addr:postcode":"32706;98844",
    "addr:street":"Us Hwy 97",
    "iso:country":"US",
    "sg:address":"32706 US Hwy 97",
    "sg:city":"Oroville",
    "sg:classifiers":[
        {
            "category":"Food & Beverages",
            "subcategory":"Fruits & Vegetables",
            "type":"Retail Goods"
        }
    ],
    "sg:phone":"+1 509 476 4683",
    "sg:postcode":"98844",
    "sg:province":"WA",
    "sg:tags":[
        "produce"
    ],
    "wof:name":"Don's Fruit Stand",
    "wof:placetype":"venue"
},
  "geometry": {"coordinates":[-119.414013,48.870883],"type":"Point"}
}