{
  "type": "Feature",
  "properties": {
    "addr:full":"132 Winston Creek Rd Mossyrock WA 98564",
    "addr:housenumber":"132",
    "addr:postcode":"98564",
    "addr:street":"Winston Creek Rd",
    "iso:country":"US",
    "sg:address":"132 Winston Creek Rd",
    "sg:city":"Mossyrock",
    "sg:classifiers":[
        {
            "category":"Travel",
            "subcategory":"Campground",
            "type":"Entertainment"
        }
    ],
    "sg:phone":"+1 360 985 2003",
    "sg:postcode":"98564",
    "sg:province":"WA",
    "sg:tags":[
        "trailer"
    ],
    "wof:name":"Winston Creek Rv Park",
    "wof:placetype":"venue"
},
  "geometry": {"coordinates":[-122.555091,46.52104],"type":"Point"}
}