{
  "type": "Feature",
  "properties": {
    "addr:full":"10600 NE 9th Place Bellevue WA 98004",
    "addr:housenumber":"10600",
    "addr:postcode":"98004",
    "addr:street":"Ne 9Th Place",
    "iso:country":"US",
    "sg:address":"10600 NE 9th Place",
    "sg:city":"Bellevue",
    "sg:classifiers":[
        {
            "category":"Coffee & Tea",
            "type":"Food & Drink"
        },
        {
            "category":"Donuts",
            "subcategory":"None",
            "type":"Food & Drink"
        }
    ],
    "sg:phone":"+1 425 457 7440",
    "sg:postcode":"98004",
    "sg:province":"WA",
    "sg:website":"www.toppotdoughnuts.com",
    "wof:name":"Top Pot Doughnuts",
    "wof:placetype":"venue"
},
  "geometry": {"coordinates":[-122.198104,47.619087],"type":"Point"}
}