{
  "type": "Feature",
  "properties": {
    "addr:full":"6901 E Trent Ave Spokane WA 99212",
    "addr:housenumber":"6901",
    "addr:postcode":"99212",
    "addr:street":"E Trent Ave",
    "iso:country":"US",
    "sg:address":"6901 E Trent Ave",
    "sg:city":"Spokane",
    "sg:classifiers":[
        {
            "category":"Building & Trades",
            "subcategory":"Pest Control",
            "type":"Services"
        }
    ],
    "sg:phone":"+1 509 534 9770",
    "sg:postcode":"99212",
    "sg:province":"WA",
    "wof:name":"Pest Master",
    "wof:placetype":"venue"
},
  "geometry": {"coordinates":[-117.31108399999999,47.675364],"type":"Point"}
}