{
  "type": "Feature",
  "properties": {
    "addr:full":"706 E Denny Way Seattle WA 98122",
    "addr:housenumber":"706",
    "addr:postcode":"98122",
    "addr:street":"E Denny Way",
    "iso:country":"US",
    "sg:address":"706 E Denny Way",
    "sg:city":"Seattle",
    "sg:classifiers":[
        {
            "category":"Home & Garden",
            "subcategory":"Furniture",
            "type":"Retail Goods"
        }
    ],
    "sg:phone":"+1 206 323 7392",
    "sg:postcode":"98122",
    "sg:province":"WA",
    "sg:tags":[
        "store"
    ],
    "wof:name":"Santa Monica Furniture Co",
    "wof:placetype":"venue"
},
  "geometry": {"coordinates":[-122.323393,47.618529],"type":"Point"}
}