{
  "type": "Feature",
  "properties": {
    "addr:full":"6501 East Marginal Way South Showroom/Georgetown Seattle WA 98108",
    "addr:housenumber":"6501",
    "addr:postcode":"98108",
    "addr:street":"East Marginal Way South Showroom /",
    "iso:country":"US",
    "sg:address":"6501 East Marginal Way South Showroom/Georgetown",
    "sg:city":"Seattle",
    "sg:classifiers":[
        {
            "category":"Building & Trades",
            "subcategory":"Construction",
            "type":"Services"
        }
    ],
    "sg:phone":"+1 206 909 4552",
    "sg:postcode":"98108",
    "sg:province":"WA",
    "sg:tags":[
        "interior",
        "design",
        "contractor"
    ],
    "sg:website":"www.MODernConcreteDesign.com",
    "wof:name":"MODern Concrete",
    "wof:placetype":"venue"
},
  "geometry": {"coordinates":[-122.330737,47.544596],"type":"Point"}
}