{
  "type": "Feature",
  "properties": {
    "addr:full":"1155 N Bend Blvd N North Bend WA 98045",
    "addr:housenumber":"1155",
    "addr:postcode":"98045",
    "addr:street":"N Bend Blvd N",
    "iso:country":"US",
    "sg:address":"1155 N Bend Blvd N",
    "sg:city":"North Bend",
    "sg:classifiers":[
        {
            "category":"Building & Trades",
            "subcategory":"Construction",
            "type":"Services"
        }
    ],
    "sg:phone":"+1 425 888 0486",
    "sg:postcode":"98045",
    "sg:province":"WA",
    "wof:name":"City North Bend Public Works",
    "wof:placetype":"venue"
},
  "geometry": {"coordinates":[-121.795948,47.503734],"type":"Point"}
}