{
  "type": "Feature",
  "properties": {
    "addr:full":"6014 NE 124th Ct Vancouver WA 98682",
    "addr:housenumber":"6014",
    "addr:postcode":"98682",
    "addr:street":"Ne 124Th Ct",
    "iso:country":"US",
    "sg:address":"6014 NE 124th Ct",
    "sg:city":"Vancouver",
    "sg:classifiers":[
        {
            "category":"Building & Trades",
            "subcategory":"Construction",
            "type":"Services"
        }
    ],
    "sg:phone":"+1 360 606 4134",
    "sg:postcode":"98682",
    "sg:province":"WA",
    "sg:tags":[
        "painter"
    ],
    "wof:name":"Fletcher Paint",
    "wof:placetype":"venue"
},
  "geometry": {"coordinates":[-122.544983,45.666346],"type":"Point"}
}