{
  "type": "Feature",
  "properties": {
    "addr:full":"13711 N Friendship Ln Nine Mile Falls WA 99026",
    "addr:housenumber":"13711",
    "addr:postcode":"99026",
    "addr:street":"N Friendship Ln",
    "iso:country":"US",
    "sg:address":"13711 N Friendship Ln",
    "sg:city":"Nine Mile Falls",
    "sg:classifiers":[
        {
            "category":"Banks & Credit Unions",
            "subcategory":"Bank",
            "type":"Services"
        }
    ],
    "sg:phone":"+1 509 467 2845",
    "sg:postcode":"99026",
    "sg:province":"WA",
    "sg:tags":[
        "loan",
        "real estate"
    ],
    "wof:name":"Saxon Mortgage Inc",
    "wof:placetype":"venue"
},
  "geometry": {"coordinates":[-117.636561,47.783319],"type":"Point"}
}