{
  "type": "Feature",
  "properties": {
    "addr:full":"1412 Bay Ave Ocean Park WA 98640",
    "addr:housenumber":"1412",
    "addr:postcode":"98640",
    "addr:street":"Bay Ave",
    "iso:country":"US",
    "sg:address":"1412 Bay Ave",
    "sg:city":"Ocean Park",
    "sg:classifiers":[
        {
            "category":"Professional",
            "subcategory":"Research",
            "type":"Services"
        }
    ],
    "sg:phone":"+1 360 244 0517",
    "sg:postcode":"98640",
    "sg:province":"WA",
    "sg:tags":[
        "natural",
        "consulting",
        "resource"
    ],
    "wof:name":"Roy Sampsel",
    "wof:placetype":"venue"
},
  "geometry": {"coordinates":[-124.050096,46.491423],"type":"Point"}
}