{
  "type": "Feature",
  "properties": {
    "addr:full":"1616 SW 100th Street Seattle WA 98146",
    "addr:housenumber":"1616",
    "addr:postcode":"98146",
    "addr:street":"Sw 100Th Street",
    "iso:country":"US",
    "sg:address":"1616 SW 100th Street",
    "sg:city":"Seattle",
    "sg:classifiers":[
        {
            "category":"Banks & Credit Unions",
            "subcategory":"Bank",
            "type":"Services"
        },
        {
            "category":"Banks & Credit Unions",
            "subcategory":"Financial Services",
            "type":"Services"
        }
    ],
    "sg:phone":"+1 206 461 6425",
    "sg:postcode":"98146",
    "sg:province":"WA",
    "sg:tags":[
        "broker",
        "mortgage"
    ],
    "wof:name":"Washington Mutual",
    "wof:placetype":"venue"
},
  "geometry": {"coordinates":[-122.35522400000001,47.513795],"type":"Point"}
}