{
  "type": "Feature",
  "properties": {
    "addr:full":"18210 SE 22nd St Vancouver WA 98683",
    "addr:postcode":"18210;98683",
    "addr:street":"Se 22Nd St",
    "iso:country":"US",
    "sg:address":"18210 SE 22nd St",
    "sg:city":"Vancouver",
    "sg:classifiers":[
        {
            "category":"Professional",
            "type":"Services"
        }
    ],
    "sg:phone":"+1 360 254 4120",
    "sg:postcode":"98683",
    "sg:province":"WA",
    "wof:name":"Beauticontrol Ind Unit Dir",
    "wof:placetype":"venue"
},
  "geometry": {"coordinates":[-122.48550400000001,45.605673],"type":"Point"}
}