{
  "type": "Feature",
  "properties": {
    "iso:country":"US",
    "sg:address":"950 Pacific Ave",
    "sg:city":"Tacoma",
    "sg:classifiers":[
        {
            "category":"Communications",
            "subcategory":"Radio Station",
            "type":"Services"
        }
    ],
    "sg:phone":"+1 253 682 1770",
    "sg:postcode":"98402",
    "sg:province":"WA",
    "sg:tags":[
        "company",
        "broadcasting"
    ],
    "wof:name":"Clear Channel Seattle",
    "wof:placetype":"venue"
},
  "geometry": {"coordinates":[-122.43902,47.254919],"type":"Point"}
}