{
  "type": "Feature",
  "properties": {
    "addr:full":"2135 112th Ave NE Bellevue WA 98004",
    "addr:housenumber":"2135",
    "addr:postcode":"98004",
    "addr:street":"112Th Ave Ne",
    "iso:country":"US",
    "sg:address":"2135 112th Ave NE",
    "sg:city":"Bellevue",
    "sg:classifiers":[
        {
            "category":"Professional",
            "subcategory":"Lawyer & Legal Services",
            "type":"Services"
        }
    ],
    "sg:phone":"+1 425 637 6977",
    "sg:postcode":"98004",
    "sg:province":"WA",
    "wof:name":"Kevin Jung Law Group PS",
    "wof:placetype":"venue"
},
  "geometry": {"coordinates":[-122.191002,47.629299],"type":"Point"}
}