{
  "type": "Feature",
  "properties": {
    "addr:full":"8006 240th St SW Edmonds WA 98026",
    "addr:housenumber":"8006",
    "addr:postcode":"98026",
    "addr:street":"240Th St Sw",
    "iso:country":"US",
    "sg:address":"8006 240th St SW",
    "sg:city":"Edmonds",
    "sg:classifiers":[
        {
            "category":"Manufacturing",
            "subcategory":"Toys & Sporting Goods",
            "type":"Manufacturing & Wholesale Goods"
        }
    ],
    "sg:phone":"+1 425 778 2481",
    "sg:postcode":"98026",
    "sg:province":"WA",
    "sg:tags":[
        "mfg"
    ],
    "wof:name":"Mathay Products",
    "wof:placetype":"venue"
},
  "geometry": {"coordinates":[-122.34493500000001,47.781372],"type":"Point"}
}