{
  "type": "Feature",
  "properties": {
    "addr:full":"21907 NE 4th St Sammamish WA 98074",
    "addr:housenumber":"21907",
    "addr:postcode":"98074",
    "addr:street":"Ne 4Th St",
    "iso:country":"US",
    "sg:address":"21907 NE 4th St",
    "sg:city":"Sammamish",
    "sg:classifiers":[
        {
            "category":"Organizations",
            "subcategory":"Community Association",
            "type":"Services"
        }
    ],
    "sg:phone":"+1 425 868 4502",
    "sg:postcode":"98074",
    "sg:province":"WA",
    "sg:tags":[
        "social"
    ],
    "wof:name":"Natl Rtred Crrent Fed Employee",
    "wof:placetype":"venue"
},
  "geometry": {"coordinates":[-122.045942,47.612782],"type":"Point"}
}