{
  "type": "Feature",
  "properties": {
    "addr:full":"2510 6th St Bremerton WA 98312",
    "addr:housenumber":"2510",
    "addr:postcode":"98312",
    "addr:street":"6Th St",
    "iso:country":"US",
    "sg:address":"2510 6th St",
    "sg:city":"Bremerton",
    "sg:classifiers":[
        {
            "category":"Recreation",
            "type":"Entertainment"
        }
    ],
    "sg:phone":"+1 360 782 0712",
    "sg:postcode":"98312",
    "sg:province":"WA",
    "wof:name":"Spirit Force Karate",
    "wof:placetype":"venue"
},
  "geometry": {"coordinates":[-122.652109,47.567472],"type":"Point"}
}