{
  "type": "Feature",
  "properties": {
    "addr:full":"14022 Roslyn Pl N Seattle WA 98133",
    "addr:housenumber":"14022",
    "addr:postcode":"98133",
    "addr:street":"Roslyn Pl N",
    "iso:country":"US",
    "sg:address":"14022 Roslyn Pl N",
    "sg:city":"Seattle",
    "sg:classifiers":[
        {
            "category":"Professional",
            "subcategory":"Art Services",
            "type":"Services"
        }
    ],
    "sg:phone":"+1 206 364 6082",
    "sg:postcode":"98133",
    "sg:province":"WA",
    "sg:tags":[
        "cab",
        "graphic",
        "musician",
        "driver",
        "artist"
    ],
    "wof:name":"Sidener-Lee Design Group",
    "wof:placetype":"venue"
},
  "geometry": {"coordinates":[-122.34064499999999,47.731602],"type":"Point"}
}