{
  "type": "Feature",
  "properties": {
    "addr:full":"7723 24th Ave NW Seattle WA 98107",
    "addr:housenumber":"7723",
    "addr:postcode":"98107",
    "addr:street":"24Th Ave Nw",
    "iso:country":"US",
    "sg:address":"7723 24th Ave NW",
    "sg:city":"Seattle",
    "sg:classifiers":[
        {
            "category":"Health Services",
            "subcategory":"Dentist",
            "type":"Services"
        }
    ],
    "sg:phone":"+1 206 782 3060",
    "sg:postcode":"98107",
    "sg:province":"WA",
    "wof:name":"Alan M Munk, DDS",
    "wof:placetype":"venue"
},
  "geometry": {"coordinates":[-122.38761599999999,47.685378],"type":"Point"}
}