{
  "type": "Feature",
  "properties": {
    "addr:full":"5101 E Valley Hwy E Sumner WA 98390",
    "addr:housenumber":"5101",
    "addr:postcode":"98390",
    "addr:street":"E Valley Hwy E",
    "iso:country":"US",
    "sg:address":"5101 E Valley Hwy E",
    "sg:city":"Sumner",
    "sg:classifiers":[
        {
            "category":"Food & Beverages",
            "subcategory":"Groceries & Convenience Stores",
            "type":"Retail Goods"
        }
    ],
    "sg:phone":"+1 253 863 0103",
    "sg:postcode":"98390",
    "sg:province":"WA",
    "wof:name":"City Limits Deli Mart",
    "wof:placetype":"venue"
},
  "geometry": {"coordinates":[-122.22681799999999,47.210962],"type":"Point"}
}