{
  "type": "Feature",
  "properties": {
    "addr:full":"22 Colwell St Port Hadlock WA 98339",
    "addr:housenumber":"22",
    "addr:postcode":"98339",
    "addr:street":"Colwell St",
    "iso:country":"US",
    "sg:address":"22 Colwell St",
    "sg:city":"Port Hadlock",
    "sg:classifiers":[
        {
            "category":"Personal",
            "subcategory":"Beauty Salon",
            "type":"Services"
        }
    ],
    "sg:phone":"+1 360 385 6007",
    "sg:postcode":"98339",
    "sg:province":"WA",
    "wof:name":"Hello Gorgeous Salon & Barber",
    "wof:placetype":"venue"
},
  "geometry": {"coordinates":[-122.781774,48.033129],"type":"Point"}
}