{
  "type": "Feature",
  "properties": {
    "addr:full":"10220 N Nevada St Spokane WA 99207",
    "addr:housenumber":"10220",
    "addr:postcode":"99207",
    "addr:street":"N Nevada St",
    "iso:country":"US",
    "sg:address":"10220 N Nevada St",
    "sg:city":"Spokane",
    "sg:classifiers":[
        {
            "category":"Social Services",
            "type":"Services"
        }
    ],
    "sg:phone":"+1 509 467 7913",
    "sg:postcode":"99207",
    "sg:province":"WA",
    "sg:tags":[
        "counselor",
        "marriage",
        "family"
    ],
    "sg:website":"www.genesisinstitute.org",
    "wof:name":"Genesis Institute-Counseling",
    "wof:placetype":"venue"
},
  "geometry": {"coordinates":[-117.39511299999999,47.750922],"type":"Point"}
}