{
  "type": "Feature",
  "properties": {
    "addr:full":"1336 S 1st St Yakima WA 98901",
    "addr:housenumber":"1336",
    "addr:postcode":"98901",
    "addr:street":"S 1St St",
    "iso:country":"US",
    "sg:address":"1336 S 1st St",
    "sg:city":"Yakima",
    "sg:classifiers":[
        {
            "category":"Banks & Credit Unions",
            "subcategory":"Bank",
            "type":"Services"
        }
    ],
    "sg:phone":"+1 509 452 0897",
    "sg:postcode":"98901",
    "sg:province":"WA",
    "sg:tags":[
        "cashing",
        "check"
    ],
    "wof:name":"Quick Cash",
    "wof:placetype":"venue"
},
  "geometry": {"coordinates":[-120.49668699999999,46.585309],"type":"Point"}
}