{
  "type": "Feature",
  "properties": {
    "addr:full":"12711 NE 95th St Vancouver WA 98682",
    "addr:housenumber":"12711",
    "addr:postcode":"98682",
    "addr:street":"Ne 95Th St",
    "iso:country":"US",
    "sg:address":"12711 NE 95th St",
    "sg:city":"Vancouver",
    "sg:classifiers":[
        {
            "category":"Freight",
            "type":"Transportation"
        }
    ],
    "sg:phone":"+1 360 213 2501",
    "sg:postcode":"98682",
    "sg:province":"WA",
    "wof:name":"Pacific Trail Logistics LLC",
    "wof:placetype":"venue"
},
  "geometry": {"coordinates":[-122.54296100000001,45.690452],"type":"Point"}
}