{
  "type": "Feature",
  "properties": {
    "addr:full":"10105 SE 226th Pl Kent WA 98031",
    "addr:housenumber":"10105",
    "addr:postcode":"98031",
    "addr:street":"Se 226Th Pl",
    "iso:country":"US",
    "sg:address":"10105 SE 226th Pl",
    "sg:city":"Kent",
    "sg:classifiers":[
        {
            "category":"Building & Trades",
            "subcategory":"Landscaping Services",
            "type":"Services"
        }
    ],
    "sg:phone":"+1 253 850 7709",
    "sg:postcode":"98031",
    "sg:province":"WA",
    "wof:name":"Lau Lawncare",
    "wof:placetype":"venue"
},
  "geometry": {"coordinates":[-122.20661200000001,47.399122],"type":"Point"}
}