{
  "type": "Feature",
  "properties": {
    "addr:full":"110 Harrison Ave Port Orchard WA 98366",
    "addr:housenumber":"110",
    "addr:postcode":"98366",
    "addr:street":"Harrison Ave",
    "iso:country":"US",
    "sg:address":"110 Harrison Ave",
    "sg:city":"Port Orchard",
    "sg:classifiers":[
        {
            "category":"Recreation",
            "type":"Entertainment"
        }
    ],
    "sg:phone":"+1 360 377 8924",
    "sg:postcode":"98366",
    "sg:province":"WA",
    "wof:name":"Kitsap Harbor Tours",
    "wof:placetype":"venue"
},
  "geometry": {"coordinates":[-122.634822,47.541997],"type":"Point"}
}