{
  "type": "Feature",
  "properties": {
    "addr:full":"22602 Marine View Dr S Des Moines WA 98198",
    "addr:housenumber":"22602",
    "addr:postcode":"98198",
    "addr:street":"Marine View Dr S",
    "iso:country":"US",
    "sg:address":"22602 Marine View Dr S",
    "sg:city":"Des Moines",
    "sg:classifiers":[
        {
            "category":"Personal",
            "subcategory":"Beauty Salon",
            "type":"Services"
        }
    ],
    "sg:phone":"+1 206 824 4247",
    "sg:postcode":"98198",
    "sg:province":"WA",
    "wof:name":"Bebe Nails & Spa",
    "wof:placetype":"venue"
},
  "geometry": {"coordinates":[-122.324282,47.397952],"type":"Point"}
}