{
  "type": "Feature",
  "properties": {
    "addr:full":"619 S Mission St Wenatchee WA 98801",
    "addr:housenumber":"619",
    "addr:postcode":"98801",
    "addr:street":"S;St",
    "iso:country":"US",
    "sg:address":"619 S Mission St",
    "sg:city":"Wenatchee",
    "sg:classifiers":[
        {
            "category":"Restaurant",
            "type":"Food & Drink"
        }
    ],
    "sg:phone":"+1 509 663 4594",
    "sg:postcode":"98801",
    "sg:province":"WA",
    "sg:tags":[
        "bakery",
        "retail",
        "eating"
    ],
    "wof:name":"Jeepers It's Bagels",
    "wof:placetype":"venue"
},
  "geometry": {"coordinates":[-120.306438,47.416696],"type":"Point"}
}