{
  "type": "Feature",
  "properties": {
    "addr:full":"8909 NE 144th Pl Bothell WA 98011",
    "addr:housenumber":"8909",
    "addr:postcode":"98011",
    "addr:street":"Ne 144Th Pl",
    "iso:country":"US",
    "sg:address":"8909 NE 144th Pl",
    "sg:city":"Bothell",
    "sg:classifiers":[
        {
            "category":"Professional",
            "subcategory":"Management & Consulting",
            "type":"Services"
        }
    ],
    "sg:phone":"+1 425 821 2783",
    "sg:postcode":"98011",
    "sg:province":"WA",
    "sg:tags":[
        "business"
    ],
    "wof:name":"Sandra Thompson Consultant",
    "wof:placetype":"venue"
},
  "geometry": {"coordinates":[-122.22132000000001,47.732065],"type":"Point"}
}