{
  "type": "Feature",
  "properties": {
    "addr:full":"6001 140th Ave NE Redmond WA 98052",
    "addr:housenumber":"6001",
    "addr:postcode":"98052",
    "addr:street":"140Th Ave Ne",
    "iso:country":"US",
    "sg:address":"6001 140th Ave NE",
    "sg:city":"Redmond",
    "sg:classifiers":[
        {
            "category":"Building & Trades",
            "subcategory":"Construction",
            "type":"Services"
        }
    ],
    "sg:phone":"+1 425 869 8853",
    "sg:postcode":"98052",
    "sg:province":"WA",
    "sg:tags":[
        "contractor"
    ],
    "wof:name":"Kensington Development",
    "wof:placetype":"venue"
},
  "geometry": {"coordinates":[-122.153398,47.661128],"type":"Point"}
}