{
  "type": "Feature",
  "properties": {
    "addr:full":"7609 W 13th Ave Kennewick WA 99338",
    "addr:housenumber":"7609",
    "addr:postcode":"99338",
    "addr:street":"W 13Th Ave",
    "iso:country":"US",
    "sg:address":"7609 W 13th Ave",
    "sg:city":"Kennewick",
    "sg:classifiers":[
        {
            "category":"Professional",
            "subcategory":"Business Services",
            "type":"Services"
        }
    ],
    "sg:phone":"+1 509 948 6928",
    "sg:postcode":"99338",
    "sg:province":"WA",
    "sg:tags":[
        "fire",
        "incident",
        "protection"
    ],
    "wof:name":"Lonnie E Click",
    "wof:placetype":"venue"
},
  "geometry": {"coordinates":[-119.223283,46.195822],"type":"Point"}
}