{
  "type": "Feature",
  "properties": {
    "addr:full":"22715 287th Pl SE Maple Valley WA 98038",
    "addr:housenumber":"22715",
    "addr:postcode":"98038",
    "addr:street":"287Th Pl Se;Valley",
    "iso:country":"US",
    "sg:address":"22715 287th Pl SE",
    "sg:city":"Maple Valley",
    "sg:classifiers":[
        {
            "category":"Professional",
            "type":"Services"
        }
    ],
    "sg:phone":"+1 425 432 0974",
    "sg:postcode":"98038",
    "sg:province":"WA",
    "wof:name":"Tom Beno Inc",
    "wof:placetype":"venue"
},
  "geometry": {"coordinates":[-121.96089499999999,47.398776],"type":"Point"}
}