{
  "type": "Feature",
  "properties": {
    "addr:full":"11823 NE 212th Ave Brush Prairie WA 98606",
    "addr:housenumber":"11823",
    "addr:postcode":"98606",
    "addr:street":"Ne 212Th Ave",
    "iso:country":"US",
    "sg:address":"11823 NE 212th Ave",
    "sg:city":"Brush Prairie",
    "sg:classifiers":[
        {
            "category":"Building & Trades",
            "subcategory":"Construction",
            "type":"Services"
        }
    ],
    "sg:phone":"+1 360 892 8691",
    "sg:postcode":"98606",
    "sg:province":"WA",
    "sg:tags":[
        "home",
        "family",
        "general"
    ],
    "wof:name":"Glen Stenersen Construction",
    "wof:placetype":"venue"
},
  "geometry": {"coordinates":[-122.455387,45.706076],"type":"Point"}
}