{
  "type": "Feature",
  "properties": {
    "addr:full":"326 Union Ave NE Ste 2 Renton WA 98059",
    "addr:housenumber":"326",
    "addr:postcode":"98059",
    "addr:street":"Union Ave Ne Ste 2",
    "iso:country":"US",
    "sg:address":"326 Union Ave NE Ste 2",
    "sg:city":"Renton",
    "sg:classifiers":[
        {
            "category":"Organizations",
            "subcategory":"Religious Organization",
            "type":"Services"
        }
    ],
    "sg:phone":"+1 425 793 5933",
    "sg:postcode":"98059",
    "sg:province":"WA",
    "sg:website":"www.shekinahglorytabernacle.com",
    "wof:name":"Shekinah Glory Tabernacle",
    "wof:placetype":"venue"
},
  "geometry": {"coordinates":[-122.16394200000001,47.487707],"type":"Point"}
}