{
  "type": "Feature",
  "properties": {
    "addr:full":"2147 Cloward Way Bremerton WA 98312",
    "addr:housenumber":"2147",
    "addr:postcode":"98312",
    "addr:street":"Cloward Way",
    "iso:country":"US",
    "sg:address":"2147 Cloward Way",
    "sg:city":"Bremerton",
    "sg:classifiers":[
        {
            "category":"Manufacturing",
            "subcategory":"Retail Goods",
            "type":"Manufacturing & Wholesale Goods"
        }
    ],
    "sg:phone":"+1 360 792 9297",
    "sg:postcode":"98312",
    "sg:province":"WA",
    "sg:tags":[
        "auto",
        "product",
        "mfg",
        "repair",
        "general"
    ],
    "wof:name":"B&L Enterprises Co",
    "wof:placetype":"venue"
},
  "geometry": {"coordinates":[-122.667987,47.579846],"type":"Point"}
}