{
  "type": "Feature",
  "properties": {
    "iso:country":"US",
    "sg:address":"5600 Harbour Pointe Blvd",
    "sg:city":"Mukilteo",
    "sg:classifiers":[
        {
            "category":"Personal",
            "type":"Services"
        }
    ],
    "sg:phone":"+1 206 579 7150",
    "sg:postcode":"98275",
    "sg:province":"WA",
    "wof:name":"A Something Different Weddings",
    "wof:placetype":"venue"
},
  "geometry": {"coordinates":[-122.307738,47.895682],"type":"Point"}
}