{
  "type": "Feature",
  "properties": {
    "addr:full":"790 Idylwood Dr SW Issaquah WA 98027",
    "addr:housenumber":"790",
    "addr:postcode":"98027",
    "addr:street":"Idylwood Dr Sw",
    "iso:country":"US",
    "sg:address":"790 Idylwood Dr SW",
    "sg:city":"Issaquah",
    "sg:classifiers":[
        {
            "category":"Manufacturing",
            "subcategory":"Tools & Machinery",
            "type":"Manufacturing & Wholesale Goods"
        }
    ],
    "sg:phone":"+1 425 392 9172",
    "sg:postcode":"98027",
    "sg:province":"WA",
    "sg:tags":[
        "retail",
        "parts",
        "printer"
    ],
    "wof:name":"Printerpartcom",
    "wof:placetype":"venue"
},
  "geometry": {"coordinates":[-122.052691,47.521511],"type":"Point"}
}