{
  "type": "Feature",
  "properties": {
    "iso:country":"US",
    "sg:address":"13006 37th Avenue Ct NW",
    "sg:city":"Gig Harbor",
    "sg:classifiers":[
        {
            "category":"Professional",
            "type":"Services"
        }
    ],
    "sg:phone":"+1 253 851 3301",
    "sg:postcode":"98332",
    "sg:province":"WA",
    "wof:name":"Rainshadow Reflections",
    "wof:placetype":"venue"
},
  "geometry": {"coordinates":[-122.58850099999999,47.376777],"type":"Point"}
}