{
  "type": "Feature",
  "properties": {
    "addr:full":"1408 SE 132nd Ave Vancouver WA 98683",
    "addr:housenumber":"1408",
    "addr:postcode":"98683",
    "addr:street":"Se 132Nd Ave",
    "iso:country":"US",
    "sg:address":"1408 SE 132nd Ave",
    "sg:city":"Vancouver",
    "sg:classifiers":[
        {
            "category":"Real Estate",
            "subcategory":"Real Estate Services",
            "type":"Services"
        },
        {
            "category":"Real Estate",
            "subcategory":"Real Estate Agent",
            "type":"Services"
        }
    ],
    "sg:phone":"+1 360 260 0555",
    "sg:postcode":"98683",
    "sg:province":"WA",
    "sg:tags":[
        "buyer",
        "broker"
    ],
    "wof:name":"Trendz Real Estate, Inc.",
    "wof:placetype":"venue"
},
  "geometry": {"coordinates":[-122.536507,45.611439],"type":"Point"}
}