{
  "type": "Feature",
  "properties": {
    "addr:full":"218 W Meeker St Kent WA 98032",
    "addr:housenumber":"218",
    "addr:postcode":"98032",
    "addr:street":"W Meeker St",
    "iso:country":"US",
    "sg:address":"218 W Meeker St",
    "sg:city":"Kent",
    "sg:classifiers":[
        {
            "category":"Social Services",
            "subcategory":"Child Care",
            "type":"Services"
        }
    ],
    "sg:phone":"+1 253 520 0895",
    "sg:postcode":"98032",
    "sg:province":"WA",
    "sg:tags":[
        "day"
    ],
    "wof:name":"Rainy Day Treasures & Gifts",
    "wof:placetype":"venue"
},
  "geometry": {"coordinates":[-122.23428800000001,47.3815],"type":"Point"}
}