{
  "type": "Feature",
  "properties": {
    "addr:full":"135 168th St E Spanaway WA 98387",
    "addr:housenumber":"135",
    "addr:postcode":"98387",
    "addr:street":"168Th St E",
    "iso:country":"US",
    "sg:address":"135 168th St E",
    "sg:city":"Spanaway",
    "sg:classifiers":[
        {
            "category":"Wholesale",
            "subcategory":"Groceries",
            "type":"Manufacturing & Wholesale Goods"
        }
    ],
    "sg:phone":"+1 253 537 4262",
    "sg:postcode":"98387",
    "sg:province":"WA",
    "sg:tags":[
        "food"
    ],
    "wof:name":"Airline Catering Co",
    "wof:placetype":"venue"
},
  "geometry": {"coordinates":[-122.42990899999999,47.104548],"type":"Point"}
}