{
  "type": "Feature",
  "properties": {
    "addr:full":"4603 Lacey Blvd SE Lacey WA 98503",
    "addr:housenumber":"4603",
    "addr:postcode":"98503",
    "addr:street":"Lacey Blvd Se",
    "iso:country":"US",
    "sg:address":"4603 Lacey Blvd SE",
    "sg:city":"Lacey",
    "sg:classifiers":[
        {
            "category":"Autos & Motor Vehicles",
            "subcategory":"Fuel & Gas Station",
            "type":"Retail Goods"
        }
    ],
    "sg:phone":"+1 360 923 2308",
    "sg:postcode":"98503",
    "sg:province":"WA",
    "sg:tags":[
        "oil"
    ],
    "wof:name":"Lacy Chevron",
    "wof:placetype":"venue"
},
  "geometry": {"coordinates":[-122.82149,47.035423],"type":"Point"}
}