{
  "type": "Feature",
  "properties": {
    "addr:full":"2854 SE 2nd Ave Camas WA 98607",
    "addr:housenumber":"2854",
    "addr:postcode":"98607",
    "addr:street":"Se 2Nd Ave",
    "iso:country":"US",
    "sg:address":"2854 SE 2nd Ave",
    "sg:city":"Camas",
    "sg:classifiers":[
        {
            "category":"Freight",
            "type":"Transportation"
        }
    ],
    "sg:phone":"+1 360 835 2047",
    "sg:postcode":"98607",
    "sg:province":"WA",
    "sg:tags":[
        "operator",
        "local",
        "trucking"
    ],
    "wof:name":"Affordable Trucking Inc",
    "wof:placetype":"venue"
},
  "geometry": {"coordinates":[-122.377229,45.584515],"type":"Point"}
}