{
  "type": "Feature",
  "properties": {
    "addr:full":"870 Southcenter Mall Tukwila WA 98188",
    "addr:housenumber":"870",
    "addr:postcode":"98188",
    "addr:street":"Southcenter Mall",
    "iso:country":"US",
    "sg:address":"870 Southcenter Mall",
    "sg:city":"Tukwila",
    "sg:classifiers":[
        {
            "category":"Shopping",
            "subcategory":"Jewelry",
            "type":"Retail Goods"
        },
        {
            "category":"Manufacturing",
            "subcategory":"Jewelry",
            "type":"Manufacturing & Wholesale Goods"
        }
    ],
    "sg:phone":"+1 206 901 9204",
    "sg:postcode":"98188",
    "sg:province":"WA",
    "sg:tags":[
        "stone",
        "designer",
        "semi-precious",
        "precious",
        "jeweler"
    ],
    "sg:website":"http://www.gordonsjewelers.com",
    "wof:name":"Gordon's Jewelers",
    "wof:placetype":"venue"
},
  "geometry": {"coordinates":[-122.258487,47.460668],"type":"Point"}
}