{
  "type": "Feature",
  "properties": {
    "addr:full":"4121 Springdale Hunters Rd Springdale WA 99173",
    "addr:housenumber":"4121",
    "addr:postcode":"99173",
    "addr:street":"Springdale Hunters Rd",
    "iso:country":"US",
    "sg:address":"4121 Springdale Hunters Rd",
    "sg:city":"Springdale",
    "sg:classifiers":[
        {
            "category":"Retail",
            "subcategory":"Repair Shop",
            "type":"Services"
        }
    ],
    "sg:phone":"+1 509 258 7048",
    "sg:postcode":"99173",
    "sg:province":"WA",
    "wof:name":"Camas Valley Tractor",
    "wof:placetype":"venue"
},
  "geometry": {"coordinates":[-117.76851000000001,48.053621],"type":"Point"}
}