{
  "type": "Feature",
  "properties": {
    "addr:full":"9919 Bridgeport Way SW Lakewood WA 98499",
    "addr:housenumber":"9919",
    "addr:postcode":"98499",
    "addr:street":"Bridgeport Way Sw",
    "iso:country":"US",
    "sg:address":"9919 Bridgeport Way SW",
    "sg:city":"Lakewood",
    "sg:classifiers":[
        {
            "category":"Banks & Credit Unions",
            "subcategory":"Bank",
            "type":"Services"
        }
    ],
    "sg:phone":"+1 253 589 8335",
    "sg:postcode":"98499",
    "sg:province":"WA",
    "sg:tags":[
        "federal",
        "loan",
        "saving",
        "institution"
    ],
    "sg:website":"www.washingtonfederal.com",
    "wof:name":"Washington Federal Savings",
    "wof:placetype":"venue"
},
  "geometry": {"coordinates":[-122.511002,47.167198],"type":"Point"}
}