{
  "type": "Feature",
  "properties": {
    "addr:full":"140 E Olympic Ct Allyn WA 98524",
    "addr:housenumber":"140",
    "addr:postcode":"98524",
    "addr:street":"E Olympic Ct",
    "iso:country":"US",
    "sg:address":"140 E Olympic Ct",
    "sg:city":"Allyn",
    "sg:classifiers":[
        {
            "category":"Wholesale",
            "subcategory":"Non-durable Goods",
            "type":"Manufacturing & Wholesale Goods"
        }
    ],
    "sg:phone":"+1 360 275 9495",
    "sg:postcode":"98524",
    "sg:province":"WA",
    "wof:name":"Bigfoot Trading Inc",
    "wof:placetype":"venue"
},
  "geometry": {"coordinates":[-122.83567499999999,47.391695],"type":"Point"}
}