{
  "type": "Feature",
  "properties": {
    "addr:full":"632 Davis Rd Usk WA 99180",
    "addr:housenumber":"632",
    "addr:postcode":"99180",
    "addr:street":"Davis Rd",
    "iso:country":"US",
    "sg:address":"632 Davis Rd",
    "sg:city":"Usk",
    "sg:classifiers":[
        {
            "category":"Professional",
            "subcategory":"Detective & Security Services",
            "type":"Services"
        }
    ],
    "sg:phone":"+1 509 445 1721",
    "sg:postcode":"99180",
    "sg:province":"WA",
    "sg:tags":[
        "information",
        "bureau"
    ],
    "wof:name":"Pathways Training Service",
    "wof:placetype":"venue"
},
  "geometry": {"coordinates":[-117.25685,48.271159],"type":"Point"}
}