{
  "type": "Feature",
  "properties": {
    "addr:full":"612 Omache Dr Omak WA 98841",
    "addr:housenumber":"612",
    "addr:postcode":"98841",
    "addr:street":"Omache Dr",
    "iso:country":"US",
    "sg:address":"612 Omache Dr",
    "sg:city":"Omak",
    "sg:classifiers":[
        {
            "category":"Retail",
            "subcategory":"Auto Repair",
            "type":"Services"
        }
    ],
    "sg:phone":"+1 509 826 6097",
    "sg:postcode":"98841",
    "sg:province":"WA",
    "sg:tags":[
        "automobile",
        "lubrication"
    ],
    "wof:name":"Xpress Lube & Wash",
    "wof:placetype":"venue"
},
  "geometry": {"coordinates":[-119.507514,48.420331],"type":"Point"}
}