{
  "type": "Feature",
  "properties": {
    "addr:full":"316 Bailer Hill Rd Friday Harbor WA 98250",
    "addr:housenumber":"316",
    "addr:postcode":"98250",
    "addr:street":"Bailer Hill Rd",
    "iso:country":"US",
    "sg:address":"316 Bailer Hill Rd",
    "sg:city":"Friday Harbor",
    "sg:classifiers":[
        {
            "category":"Building & Trades",
            "subcategory":"Construction",
            "type":"Services"
        }
    ],
    "sg:phone":"+1 360 378 8337",
    "sg:postcode":"98250",
    "sg:province":"WA",
    "sg:tags":[
        "general",
        "contractor"
    ],
    "wof:name":"Bailer Hill Construction",
    "wof:placetype":"venue"
},
  "geometry": {"coordinates":[-123.053473,48.500041],"type":"Point"}
}