{
  "type": "Feature",
  "properties": {
    "iso:country":"US",
    "sg:address":"2009 Walla Walla Ave",
    "sg:city":"Walla Walla",
    "sg:classifiers":[
        {
            "category":"Banks & Credit Unions",
            "subcategory":"Bank",
            "type":"Services"
        }
    ],
    "sg:phone":"+1 509 522 0061",
    "sg:postcode":"99362",
    "sg:province":"WA",
    "sg:tags":[
        "loan",
        "real estate"
    ],
    "wof:name":"Kuhlmann Mortgage Svc",
    "wof:placetype":"venue"
},
  "geometry": {"coordinates":[-118.30606400000001,46.077352],"type":"Point"}
}