{
  "type": "Feature",
  "properties": {
    "addr:full":"20013 Mountain Hwy E Spanaway WA 98387",
    "addr:housenumber":"20013",
    "addr:postcode":"98387",
    "addr:street":"Mountain Hwy E",
    "iso:country":"US",
    "sg:address":"20013 Mountain Hwy E",
    "sg:city":"Spanaway",
    "sg:classifiers":[
        {
            "category":"Personal",
            "subcategory":"Tanning Parlor",
            "type":"Services"
        }
    ],
    "sg:phone":"+1 253 847 3636",
    "sg:postcode":"98387",
    "sg:province":"WA",
    "sg:tags":[
        "salon"
    ],
    "wof:name":"Tropical Tanlines",
    "wof:placetype":"venue"
},
  "geometry": {"coordinates":[-122.425178,47.07633],"type":"Point"}
}