{
  "type": "Feature",
  "properties": {
    "addr:full":"4761 35th Ave NE Seattle WA 98105",
    "addr:housenumber":"4761",
    "addr:postcode":"98105",
    "addr:street":"35Th Ave Ne",
    "iso:country":"US",
    "sg:address":"4761 35th Ave NE",
    "sg:city":"Seattle",
    "sg:classifiers":[
        {
            "category":"Professional",
            "subcategory":"Computer Services",
            "type":"Services"
        }
    ],
    "sg:phone":"+1 206 527 1821",
    "sg:postcode":"98105",
    "sg:province":"WA",
    "sg:tags":[
        "related"
    ],
    "wof:name":"Implementation - 1",
    "wof:placetype":"venue"
},
  "geometry": {"coordinates":[-122.290239,47.664561],"type":"Point"}
}