{
  "type": "Feature",
  "properties": {
    "addr:full":"112 S 150th St Burien WA 98148",
    "addr:housenumber":"112",
    "addr:postcode":"98148",
    "addr:street":"S 150Th St",
    "iso:country":"US",
    "sg:address":"112 S 150th St",
    "sg:city":"Burien",
    "sg:classifiers":[
        {
            "category":"Retail",
            "subcategory":"Auto Repair",
            "type":"Services"
        }
    ],
    "sg:phone":"+1 206 246 9701",
    "sg:postcode":"98148",
    "sg:province":"WA",
    "sg:tags":[
        "body",
        "automobile",
        "painting"
    ],
    "sg:website":"www.burienhonda.com",
    "wof:name":"Burien Honda Body Shop",
    "wof:placetype":"venue"
},
  "geometry": {"coordinates":[-122.333848,47.468764],"type":"Point"}
}