{
  "type": "Feature",
  "properties": {
    "addr:full":"2014 E Madison St Seattle WA 98122",
    "addr:housenumber":"2014",
    "addr:postcode":"98122",
    "addr:street":"E Madison St",
    "iso:country":"US",
    "sg:address":"2014 E Madison St",
    "sg:city":"Seattle",
    "sg:classifiers":[
        {
            "category":"Professional",
            "subcategory":"Management & Consulting",
            "type":"Services"
        }
    ],
    "sg:phone":"+1 206 324 4999",
    "sg:postcode":"98122",
    "sg:province":"WA",
    "sg:tags":[
        "consultant",
        "business"
    ],
    "wof:name":"Blueprint R & D",
    "wof:placetype":"venue"
},
  "geometry": {"coordinates":[-122.304391,47.618031],"type":"Point"}
}