{
  "type": "Feature",
  "properties": {
    "addr:full":"302 S 1st St Odessa WA 99159",
    "addr:housenumber":"302",
    "addr:postcode":"99159",
    "addr:street":"S 1St St",
    "iso:country":"US",
    "sg:address":"302 S 1st St",
    "sg:city":"Odessa",
    "sg:classifiers":[
        {
            "category":"Organizations",
            "subcategory":"Religious Organization",
            "type":"Services"
        }
    ],
    "sg:phone":"+1 509 982 2951",
    "sg:postcode":"99159",
    "sg:province":"WA",
    "sg:tags":[
        "church"
    ],
    "wof:name":"Heritage Church",
    "wof:placetype":"venue"
},
  "geometry": {"coordinates":[-118.689453,47.331421],"type":"Point"}
}