{
  "type": "Feature",
  "properties": {
    "addr:full":"301 110th Pl SE Bellevue WA 98004",
    "addr:housenumber":"301",
    "addr:postcode":"98004",
    "addr:street":"110Th Pl Se",
    "iso:country":"US",
    "sg:address":"301 110th Pl SE",
    "sg:city":"Bellevue",
    "sg:classifiers":[
        {
            "category":"Building & Trades",
            "subcategory":"Construction",
            "type":"Services"
        }
    ],
    "sg:phone":"+1 425 455 1155",
    "sg:postcode":"98004",
    "sg:province":"WA",
    "sg:tags":[
        "contractor"
    ],
    "wof:name":"Mill Creek General Contractors",
    "wof:placetype":"venue"
},
  "geometry": {"coordinates":[-122.193004,47.607424],"type":"Point"}
}