{
  "type": "Feature",
  "properties": {
    "addr:full":"3600 NE 45th St Seattle WA 98105",
    "addr:housenumber":"3600",
    "addr:postcode":"98105",
    "addr:street":"Ne 45Th St",
    "iso:country":"US",
    "sg:address":"3600 NE 45th St",
    "sg:city":"Seattle",
    "sg:classifiers":[
        {
            "category":"Professional",
            "subcategory":"Management & Consulting",
            "type":"Services"
        },
        {
            "category":"Banks & Credit Unions",
            "subcategory":"Financial Services",
            "type":"Services"
        }
    ],
    "sg:phone":"+1 206 526 1151",
    "sg:postcode":"98105",
    "sg:province":"WA",
    "sg:tags":[
        "consultant",
        "financing",
        "planning"
    ],
    "wof:name":"Mallick Financial Resources",
    "wof:placetype":"venue"
},
  "geometry": {"coordinates":[-122.289207,47.661121],"type":"Point"}
}