{
  "type": "Feature",
  "properties": {
    "addr:full":"120 Nichols St Friday Harbor WA 98250",
    "addr:housenumber":"120",
    "addr:postcode":"98250",
    "addr:street":"Nichols St",
    "iso:country":"US",
    "sg:address":"120 Nichols St",
    "sg:city":"Friday Harbor",
    "sg:classifiers":[
        {
            "category":"Professional",
            "subcategory":"Research",
            "type":"Services"
        }
    ],
    "sg:phone":"+1 360 378 7292",
    "sg:postcode":"98250",
    "sg:province":"WA",
    "sg:tags":[
        "environmental",
        "ecological"
    ],
    "sg:website":"www.whitepointsystems.com",
    "wof:name":"White Point Systems Inc",
    "wof:placetype":"venue"
},
  "geometry": {"coordinates":[-123.015816,48.533513],"type":"Point"}
}