{
  "type": "Feature",
  "properties": {
    "addr:full":"2225 Riverside Dr Mount Vernon WA 98273",
    "addr:housenumber":"2225",
    "addr:postcode":"98273",
    "addr:street":"Riverside Dr",
    "iso:country":"US",
    "sg:address":"2225 Riverside Dr",
    "sg:city":"Mount Vernon",
    "sg:classifiers":[
        {
            "category":"Health Services",
            "subcategory":"Health Practitioner",
            "type":"Services"
        }
    ],
    "sg:phone":"+1 360 424 6226",
    "sg:postcode":"98273",
    "sg:province":"WA",
    "sg:tags":[
        "therapy",
        "physical"
    ],
    "wof:name":"Merit Rehab",
    "wof:placetype":"venue"
},
  "geometry": {"coordinates":[-122.33554700000001,48.441388],"type":"Point"}
}