{
  "type": "Feature",
  "properties": {
    "addr:full":"4800 Sand Point Way NE #T-0111 Seattle WA 98105",
    "addr:housenumber":"4800",
    "addr:postcode":"98105",
    "addr:street":"Sand Point Way Ne # T-0111",
    "iso:country":"US",
    "sg:address":"4800 Sand Point Way NE #T-0111",
    "sg:city":"Seattle",
    "sg:classifiers":[
        {
            "category":"Health Services",
            "subcategory":"Doctor",
            "type":"Services"
        }
    ],
    "sg:phone":"+1 206 987 2026",
    "sg:postcode":"98105",
    "sg:province":"WA",
    "sg:tags":[
        "physician",
        "surgeon"
    ],
    "wof:name":"Marcuse, Edgar, Md - Childrens Hospital",
    "wof:placetype":"venue"
},
  "geometry": {"coordinates":[-122.283394,47.664294],"type":"Point"}
}