{
  "type": "Feature",
  "properties": {
    "addr:full":"820 W 10th St Port Angeles WA 98363",
    "addr:housenumber":"820",
    "addr:postcode":"98363",
    "addr:street":"W 10Th St",
    "iso:country":"US",
    "sg:address":"820 W 10th St",
    "sg:city":"Port Angeles",
    "sg:classifiers":[
        {
            "category":"Manufacturing",
            "subcategory":"Glass & Minerals",
            "type":"Manufacturing & Wholesale Goods"
        }
    ],
    "sg:phone":"+1 360 452 7138",
    "sg:postcode":"98363",
    "sg:province":"WA",
    "sg:tags":[
        "product",
        "mfg"
    ],
    "wof:name":"Funky Dog Art",
    "wof:placetype":"venue"
},
  "geometry": {"coordinates":[-123.456225,48.117504],"type":"Point"}
}