{
  "type": "Feature",
  "properties": {
    "addr:full":"15904 SE 141st St Renton WA 98059",
    "addr:postcode":"15904;98059",
    "addr:street":"Se 141St St",
    "iso:country":"US",
    "sg:address":"15904 SE 141st St",
    "sg:city":"Renton",
    "sg:classifiers":[
        {
            "category":"Retail",
            "subcategory":"Repair Shop",
            "type":"Services"
        }
    ],
    "sg:phone":"+1 425 226 2302",
    "sg:postcode":"98059",
    "sg:province":"WA",
    "wof:name":"Neighbors Septic Tank Pump Out",
    "wof:placetype":"venue"
},
  "geometry": {"coordinates":[-122.12849,47.477163],"type":"Point"}
}