{
  "type": "Feature",
  "properties": {
    "addr:full":"1210 NW Nye St Pullman WA 99163",
    "addr:housenumber":"1210",
    "addr:postcode":"99163",
    "addr:street":"Nw Nye St",
    "iso:country":"US",
    "sg:address":"1210 NW Nye St",
    "sg:city":"Pullman",
    "sg:classifiers":[
        {
            "category":"Shopping",
            "subcategory":"Computers & Home Electronics",
            "type":"Retail Goods"
        }
    ],
    "sg:phone":"+1 509 334 2064",
    "sg:postcode":"99163",
    "sg:province":"WA",
    "wof:name":"Lobo Computer Servcies",
    "wof:placetype":"venue"
},
  "geometry": {"coordinates":[-117.174431,46.73946],"type":"Point"}
}