{
  "type": "Feature",
  "properties": {
    "addr:full":"1221 Madison St Ste 910 Seattle WA 98104",
    "addr:housenumber":"1221",
    "addr:postcode":"98104",
    "addr:street":"Madison St Ste 910",
    "iso:country":"US",
    "sg:address":"1221 Madison St Ste 910",
    "sg:city":"Seattle",
    "sg:classifiers":[
        {
            "category":"Health Services",
            "subcategory":"Doctor",
            "type":"Services"
        }
    ],
    "sg:phone":"+1 206 292 2249",
    "sg:postcode":"98104",
    "sg:province":"WA",
    "wof:name":"Zorn Sherri MD",
    "wof:placetype":"venue"
},
  "geometry": {"coordinates":[-122.329002,47.603901],"type":"Point"}
}