{
  "type": "Feature",
  "properties": {
    "addr:full":"3838 Williams Ave W Seattle WA 98199",
    "addr:housenumber":"3838",
    "addr:postcode":"98199",
    "addr:street":"Williams Ave W",
    "iso:country":"US",
    "sg:address":"3838 Williams Ave W",
    "sg:city":"Seattle",
    "sg:classifiers":[
        {
            "category":"Manufacturing",
            "subcategory":"Printing",
            "type":"Manufacturing & Wholesale Goods"
        }
    ],
    "sg:phone":"+1 206 282 8150",
    "sg:postcode":"98199",
    "sg:province":"WA",
    "sg:tags":[
        "mfg"
    ],
    "wof:name":"Sarah E Reh",
    "wof:placetype":"venue"
},
  "geometry": {"coordinates":[-122.39220299999999,47.655714],"type":"Point"}
}