{
  "type": "Feature",
  "properties": {
    "addr:full":"2208 Westlake Ave Seattle WA 98121",
    "addr:housenumber":"2208",
    "addr:postcode":"98121",
    "addr:street":"Westlake Ave",
    "iso:country":"US",
    "sg:address":"2208 Westlake Ave",
    "sg:city":"Seattle",
    "sg:classifiers":[
        {
            "category":"Building & Trades",
            "subcategory":"Locksmith",
            "type":"Services"
        }
    ],
    "sg:phone":"+1 206 238 0221",
    "sg:postcode":"98121",
    "sg:province":"WA",
    "sg:tags":[
        "key"
    ],
    "wof:name":"A Express Locksmith 24 7",
    "wof:placetype":"venue"
},
  "geometry": {"coordinates":[-122.338179,47.618014],"type":"Point"}
}