{
  "type": "Feature",
  "properties": {
    "addr:full":"1240 Lancer Dr Walla Walla WA 99362",
    "addr:housenumber":"1240",
    "addr:postcode":"99362",
    "addr:street":"Lancer Dr",
    "iso:country":"US",
    "sg:address":"1240 Lancer Dr",
    "sg:city":"Walla Walla",
    "sg:classifiers":[
        {
            "category":"Professional",
            "subcategory":"Business Services",
            "type":"Services"
        }
    ],
    "sg:phone":"+1 509 520 5541",
    "sg:postcode":"99362",
    "sg:province":"WA",
    "sg:tags":[
        "coordinate",
        "medical",
        "meeting"
    ],
    "wof:name":"World Class Radiology Seminars",
    "wof:placetype":"venue"
},
  "geometry": {"coordinates":[-118.351409,46.037776],"type":"Point"}
}