{
  "type": "Feature",
  "properties": {
    "addr:full":"4903 108th St SW Lakewood WA 98499",
    "addr:housenumber":"4903",
    "addr:postcode":"98499",
    "addr:street":"108Th St Sw",
    "iso:country":"US",
    "sg:address":"4903 108th St SW",
    "sg:city":"Lakewood",
    "sg:classifiers":[
        {
            "category":"Professional",
            "subcategory":"Management & Consulting",
            "type":"Services"
        },
        {
            "category":"Professional",
            "subcategory":"Accounting & Tax Preparation",
            "type":"Services"
        }
    ],
    "sg:phone":"+1 253 588 3101",
    "sg:postcode":"98499",
    "sg:province":"WA",
    "sg:tags":[
        "accountant"
    ],
    "wof:name":"Maurice E Laufer",
    "wof:placetype":"venue"
},
  "geometry": {"coordinates":[-122.503568,47.159526],"type":"Point"}
}