{
  "type": "Feature",
  "properties": {
    "addr:full":"177 Dubois Rd Colville WA 99114",
    "addr:housenumber":"177",
    "addr:postcode":"99114",
    "addr:street":"Dubois Rd",
    "iso:country":"US",
    "sg:address":"177 Dubois Rd",
    "sg:city":"Colville",
    "sg:classifiers":[
        {
            "category":"Manufacturing",
            "subcategory":"Lumber",
            "type":"Manufacturing & Wholesale Goods"
        }
    ],
    "sg:phone":"+1 509 684 6746",
    "sg:postcode":"99114",
    "sg:province":"WA",
    "sg:tags":[
        "logging",
        "contractor"
    ],
    "wof:name":"Stewart Logging Inc",
    "wof:placetype":"venue"
},
  "geometry": {"coordinates":[-117.882543,48.531078],"type":"Point"}
}