{
  "type": "Feature",
  "properties": {
    "addr:full":"2510 W. Bertona St. #320 Seattle WA 98199",
    "addr:housenumber":"2510",
    "addr:postcode":"98199",
    "addr:street":"W. Bertona St. # 320",
    "iso:country":"US",
    "sg:address":"2510 W. Bertona St. #320",
    "sg:city":"Seattle",
    "sg:classifiers":[
        {
            "category":"Shopping",
            "subcategory":"Pets & Pet Supplies",
            "type":"Retail Goods"
        },
        {
            "category":"Retail",
            "subcategory":"Pet Boarding",
            "type":"Services"
        }
    ],
    "sg:phone":"+1 206 450 3341",
    "sg:postcode":"98199",
    "sg:province":"WA",
    "sg:tags":[
        "walker",
        "dog",
        "boarding/pet",
        "sitting"
    ],
    "sg:website":"truecompanionspetsitting.com",
    "wof:name":"True Companions Pet Sitting",
    "wof:placetype":"venue"
},
  "geometry": {"coordinates":[-122.389309,47.650719],"type":"Point"}
}