{
  "type": "Feature",
  "properties": {
    "addr:full":"118 E Meeker Puyallup WA 98372",
    "addr:housenumber":"118",
    "addr:postcode":"98372",
    "addr:street":"E Meeker",
    "iso:country":"US",
    "sg:address":"118 E Meeker",
    "sg:city":"Puyallup",
    "sg:classifiers":[
        {
            "category":"Professional",
            "subcategory":"Accounting & Tax Preparation",
            "type":"Services"
        }
    ],
    "sg:phone":"+1 253 770 7030",
    "sg:postcode":"98372",
    "sg:province":"WA",
    "sg:tags":[
        "return",
        "filing"
    ],
    "wof:name":"Business Services",
    "wof:placetype":"venue"
},
  "geometry": {"coordinates":[-122.292654,47.190904],"type":"Point"}
}