{
  "type": "Feature",
  "properties": {
    "addr:full":"1502 N 4th Ave Pasco WA 99301",
    "addr:housenumber":"1502",
    "addr:postcode":"99301",
    "addr:street":"N 4Th Ave",
    "iso:country":"US",
    "sg:address":"1502 N 4th Ave",
    "sg:city":"Pasco",
    "sg:classifiers":[
        {
            "category":"Autos & Motor Vehicles",
            "subcategory":"Fuel & Gas Station",
            "type":"Retail Goods"
        }
    ],
    "sg:phone":"+1 509 544 9567",
    "sg:postcode":"99301",
    "sg:province":"WA",
    "wof:name":"Pik-A-Pop 7",
    "wof:placetype":"venue"
},
  "geometry": {"coordinates":[-119.09505799999999,46.241319],"type":"Point"}
}