{
  "type": "Feature",
  "properties": {
    "addr:full":"1610 Commercial Ave Anacortes WA 98221",
    "addr:housenumber":"1610",
    "addr:postcode":"98221",
    "addr:street":"Commercial Ave",
    "iso:country":"US",
    "sg:address":"1610 Commercial Ave",
    "sg:city":"Anacortes",
    "sg:classifiers":[
        {
            "category":"Professional",
            "subcategory":"Art Services",
            "type":"Services"
        }
    ],
    "sg:phone":"+1 360 293 2484",
    "sg:postcode":"98221",
    "sg:province":"WA",
    "sg:tags":[
        "graphic",
        "designer"
    ],
    "wof:name":"By Design",
    "wof:placetype":"venue"
},
  "geometry": {"coordinates":[-122.612713,48.509279],"type":"Point"}
}