{
  "type": "Feature",
  "properties": {
    "addr:full":"132 Rivers Edge Ln Yakima WA 98901",
    "addr:housenumber":"132",
    "addr:postcode":"98901",
    "addr:street":"Rivers Edge Ln",
    "iso:country":"US",
    "sg:address":"132 Rivers Edge Ln",
    "sg:city":"Yakima",
    "sg:classifiers":[
        {
            "category":"Freight",
            "type":"Transportation"
        }
    ],
    "sg:phone":"+1 509 453 8020",
    "sg:postcode":"98901",
    "sg:province":"WA",
    "sg:tags":[
        "operator",
        "local",
        "trucking"
    ],
    "wof:name":"Cruz Trucking",
    "wof:placetype":"venue"
},
  "geometry": {"coordinates":[-120.488821,46.681026],"type":"Point"}
}