{
  "type": "Feature",
  "properties": {
    "addr:full":"210 Horschel Rd Wapato WA 98951",
    "addr:housenumber":"210",
    "addr:postcode":"98951",
    "addr:street":"Horschel Rd",
    "iso:country":"US",
    "sg:address":"210 Horschel Rd",
    "sg:city":"Wapato",
    "sg:classifiers":[
        {
            "category":"Freight",
            "type":"Transportation"
        }
    ],
    "sg:phone":"+1 509 877 7926",
    "sg:postcode":"98951",
    "sg:province":"WA",
    "sg:tags":[
        "operator",
        "trucking"
    ],
    "wof:name":"Saul Valdez Trucking",
    "wof:placetype":"venue"
},
  "geometry": {"coordinates":[-120.43478,46.442459],"type":"Point"}
}