{
  "type": "Feature",
  "properties": {
    "addr:full":"330 Madison Avenue S Bainbridge Island WA 98110",
    "addr:housenumber":"330",
    "addr:postcode":"98110",
    "addr:street":"Madison Avenue S",
    "iso:country":"US",
    "sg:address":"330 Madison Avenue S",
    "sg:city":"Bainbridge Island",
    "sg:classifiers":[
        {
            "category":"Shopping",
            "subcategory":"Music",
            "type":"Retail Goods"
        }
    ],
    "sg:phone":"+1 206 780 9523",
    "sg:postcode":"98110",
    "sg:province":"WA",
    "sg:tags":[
        "dvd's"
    ],
    "wof:name":"Andreasen Enterprises",
    "wof:placetype":"venue"
},
  "geometry": {"coordinates":[-122.520996,47.622524],"type":"Point"}
}