{
  "type": "Feature",
  "properties": {
    "addr:full":"3545 Factoria Blvd SE # 400 Bellevue WA 98006",
    "addr:housenumber":"3545",
    "addr:postcode":"98006",
    "addr:street":"Factoria Blvd Se # 400",
    "iso:country":"US",
    "sg:address":"3545 Factoria Blvd SE # 400",
    "sg:city":"Bellevue",
    "sg:classifiers":[
        {
            "category":"Insurance",
            "subcategory":"Hazard Insurance",
            "type":"Services"
        },
        {
            "category":"Insurance",
            "subcategory":"Title Insurance",
            "type":"Services"
        }
    ],
    "sg:phone":"+1 425 213 5600",
    "sg:postcode":"98006",
    "sg:province":"WA",
    "sg:tags":[
        "mortgage"
    ],
    "wof:name":"Northwest Title",
    "wof:placetype":"venue"
},
  "geometry": {"coordinates":[-122.169006,47.579109],"type":"Point"}
}