{
  "type": "Feature",
  "properties": {
    "addr:full":"2411 N Pioneer Ln Spokane Valley WA 99216",
    "addr:housenumber":"2411",
    "addr:postcode":"99216",
    "addr:street":"N Pioneer Ln",
    "iso:country":"US",
    "sg:address":"2411 N Pioneer Ln",
    "sg:city":"Spokane Valley",
    "sg:classifiers":[
        {
            "category":"Government",
            "subcategory":"Office",
            "type":"Public Place"
        }
    ],
    "sg:phone":"+1 509 892 4170",
    "sg:postcode":"99216",
    "sg:province":"WA",
    "sg:website":"www.spokanevalleyfire.com",
    "wof:name":"Spokane Cnty Fire Dist 1 Trng",
    "wof:placetype":"venue"
},
  "geometry": {"coordinates":[-117.195042,47.679503],"type":"Point"}
}