{
  "type": "Feature",
  "properties": {
    "addr:full":"2546 86th Ave NE Clyde Hill WA 98004",
    "addr:housenumber":"2546",
    "addr:postcode":"98004",
    "addr:street":"86Th Ave Ne",
    "iso:country":"US",
    "sg:address":"2546 86th Ave NE",
    "sg:city":"Clyde Hill",
    "sg:classifiers":[
        {
            "category":"Professional",
            "subcategory":"Management & Consulting",
            "type":"Services"
        }
    ],
    "sg:phone":"+1 425 462 0281",
    "sg:postcode":"98004",
    "sg:province":"WA",
    "sg:tags":[
        "consultant",
        "business"
    ],
    "wof:name":"B J Hudgins Business Conslnt",
    "wof:placetype":"venue"
},
  "geometry": {"coordinates":[-122.225194,47.632993],"type":"Point"}
}