{
  "type": "Feature",
  "properties": {
    "addr:full":"4405 S Machias Rd Snohomish WA 98290",
    "addr:housenumber":"4405",
    "addr:postcode":"98290",
    "addr:street":"S Machias Rd",
    "iso:country":"US",
    "sg:address":"4405 S Machias Rd",
    "sg:city":"Snohomish",
    "sg:classifiers":[
        {
            "category":"Freight",
            "type":"Transportation"
        }
    ],
    "sg:phone":"+1 425 397 8906",
    "sg:postcode":"98290",
    "sg:province":"WA",
    "sg:tags":[
        "operator",
        "local",
        "trucking"
    ],
    "wof:name":"Crosson Trucking LLC",
    "wof:placetype":"venue"
},
  "geometry": {"coordinates":[-122.06899900000001,47.961953],"type":"Point"}
}