{
  "type": "Feature",
  "properties": {
    "addr:full":"901 Union Flat Rd Pullman WA 99163",
    "addr:housenumber":"901",
    "addr:postcode":"99163",
    "addr:street":"Union Flat Rd",
    "iso:country":"US",
    "sg:address":"901 Union Flat Rd",
    "sg:city":"Pullman",
    "sg:phone":"+1 509 334 2014",
    "sg:postcode":"99163",
    "sg:province":"WA",
    "sg:tags":[
        "wheat",
        "beef",
        "farm",
        "cash",
        "grain",
        "cattle",
        "feedlot"
    ],
    "wof:name":"Kimbles Peaceful Acres Inc",
    "wof:placetype":"venue"
},
  "geometry": {"coordinates":[-117.26924699999999,46.635244],"type":"Point"}
}