{
  "type": "Feature",
  "properties": {
    "addr:full":"3531 Oakes Ave Everett WA 98201",
    "addr:postcode":"3531;98201",
    "addr:street":"Oakes Ave",
    "iso:country":"US",
    "sg:address":"3531 Oakes Ave",
    "sg:city":"Everett",
    "sg:classifiers":[
        {
            "category":"Insurance",
            "subcategory":"Insurance Agent",
            "type":"Services"
        }
    ],
    "sg:phone":"+1 425 252 2957",
    "sg:postcode":"98201",
    "sg:province":"WA",
    "wof:name":"All About Insurance",
    "wof:placetype":"venue"
},
  "geometry": {"coordinates":[-122.203979,47.970431],"type":"Point"}
}