{
  "type": "Feature",
  "properties": {
    "addr:full":"1226 McGarigle Rd Sedro Woolley WA 98284",
    "addr:housenumber":"1226",
    "addr:postcode":"98284",
    "addr:street":"Mcgarigle Rd",
    "iso:country":"US",
    "sg:address":"1226 McGarigle Rd",
    "sg:city":"Sedro Woolley",
    "sg:classifiers":[
        {
            "category":"Professional",
            "subcategory":"Printing & Photocopies",
            "type":"Services"
        }
    ],
    "sg:phone":"+1 360 734 2262",
    "sg:postcode":"98284",
    "sg:province":"WA",
    "sg:tags":[
        "photocopying",
        "reporting"
    ],
    "wof:name":"Allen R Emerson & Associ",
    "wof:placetype":"venue"
},
  "geometry": {"coordinates":[-122.22138699999999,48.514731],"type":"Point"}
}