{
  "type": "Feature",
  "properties": {
    "addr:full":"3803 E Fairview Ave Spokane WA 99217",
    "addr:housenumber":"3803",
    "addr:postcode":"99217",
    "addr:street":"E Fairview Ave",
    "iso:country":"US",
    "sg:address":"3803 E Fairview Ave",
    "sg:city":"Spokane",
    "sg:classifiers":[
        {
            "category":"Retail",
            "subcategory":"Auto Repair",
            "type":"Services"
        }
    ],
    "sg:phone":"+1 509 489 2311",
    "sg:postcode":"99217",
    "sg:province":"WA",
    "sg:tags":[
        "recreational",
        "vehicle"
    ],
    "wof:name":"L J's Rv Svc",
    "wof:placetype":"venue"
},
  "geometry": {"coordinates":[-117.353151,47.684953],"type":"Point"}
}