{
  "type": "Feature",
  "properties": {
    "addr:full":"3220 1st Ave S Ste 100 Seattle WA 98134",
    "addr:housenumber":"3220",
    "addr:postcode":"98134",
    "addr:street":"1St Ave S Ste 100",
    "iso:country":"US",
    "sg:address":"3220 1st Ave S Ste 100",
    "sg:city":"Seattle",
    "sg:classifiers":[
        {
            "category":"Communications",
            "type":"Services"
        }
    ],
    "sg:phone":"+1 206 501 4310",
    "sg:postcode":"98134",
    "sg:province":"WA",
    "sg:tags":[
        "web",
        "design"
    ],
    "sg:website":"produxs.com",
    "wof:name":"Produxs",
    "wof:placetype":"venue"
},
  "geometry": {"coordinates":[-122.33417300000001,47.57486],"type":"Point"}
}