{
  "type": "Feature",
  "properties": {
    "addr:full":"9311 SE 36th St Mercer Island WA 98040",
    "addr:postcode":"9311;98040",
    "addr:street":"Se 36Th St",
    "iso:country":"US",
    "sg:address":"9311 SE 36th St",
    "sg:city":"Mercer Island",
    "sg:classifiers":[
        {
            "category":"Wholesale",
            "subcategory":"Seafood",
            "type":"Manufacturing & Wholesale Goods"
        }
    ],
    "sg:phone":"+1 206 236 6284",
    "sg:postcode":"98040",
    "sg:province":"WA",
    "wof:name":"Expack Deafood Northwest",
    "wof:placetype":"venue"
},
  "geometry": {"coordinates":[-122.21339,47.578076],"type":"Point"}
}