{
  "type": "Feature",
  "properties": {
    "addr:full":"1626 S 341st Pl Federal Way WA 98003",
    "addr:housenumber":"1626",
    "addr:postcode":"98003",
    "addr:street":"S 341St Pl",
    "iso:country":"US",
    "sg:address":"1626 S 341st Pl",
    "sg:city":"Federal Way",
    "sg:classifiers":[
        {
            "category":"Professional",
            "subcategory":"Business Services",
            "type":"Services"
        }
    ],
    "sg:phone":"+1 253 661 6608",
    "sg:postcode":"98003",
    "sg:province":"WA",
    "sg:tags":[
        "embroidery"
    ],
    "wof:name":"Genarus Desgnz",
    "wof:placetype":"venue"
},
  "geometry": {"coordinates":[-122.31080300000001,47.295774],"type":"Point"}
}