{
  "type": "Feature",
  "properties": {
    "addr:full":"4945 Mission Rd Bellingham WA 98226",
    "addr:housenumber":"4945",
    "addr:postcode":"98226",
    "addr:street":"Mission Rd",
    "iso:country":"US",
    "sg:address":"4945 Mission Rd",
    "sg:city":"Bellingham",
    "sg:classifiers":[
        {
            "category":"Building & Trades",
            "subcategory":"Cleaning & Sanitation",
            "type":"Services"
        }
    ],
    "sg:phone":"+1 360 592 0901",
    "sg:postcode":"98226",
    "sg:province":"WA",
    "sg:tags":[
        "maintenance"
    ],
    "wof:name":"Rain Coast",
    "wof:placetype":"venue"
},
  "geometry": {"coordinates":[-122.35484,48.823644],"type":"Point"}
}