{
  "type": "Feature",
  "properties": {
    "addr:full":"292 Highline Dr Wapato WA 98951",
    "addr:housenumber":"292",
    "addr:postcode":"98951",
    "addr:street":"Highline Dr Wapato",
    "iso:country":"US",
    "sg:address":"292 Highline Dr",
    "sg:city":"Wapato",
    "sg:classifiers":[
        {
            "category":"Farming",
            "subcategory":"Orchard",
            "type":"Manufacturing & Wholesale Goods"
        }
    ],
    "sg:phone":"+1 509 877 6246",
    "sg:postcode":"98951",
    "sg:province":"WA",
    "sg:tags":[
        "fruit",
        "tree"
    ],
    "wof:name":"Highline Orchards",
    "wof:placetype":"venue"
},
  "geometry": {"coordinates":[-120.49236000000001,46.506389],"type":"Point"}
}