{
  "type": "Feature",
  "properties": {
    "addr:full":"1104 W Sylvester St Pasco WA 99301",
    "addr:housenumber":"1104",
    "addr:postcode":"99301",
    "addr:street":"W Sylvester St",
    "iso:country":"US",
    "sg:address":"1104 W Sylvester St",
    "sg:city":"Pasco",
    "sg:classifiers":[
        {
            "category":"Personal",
            "subcategory":"Beauty Salon",
            "type":"Services"
        }
    ],
    "sg:phone":"+1 509 543 9202",
    "sg:postcode":"99301",
    "sg:province":"WA",
    "wof:name":"Gloria's Styling Zone",
    "wof:placetype":"venue"
},
  "geometry": {"coordinates":[-119.104206,46.233968],"type":"Point"}
}