{
  "type": "Feature",
  "properties": {
    "addr:full":"10828 159th Ave NE Granite Falls WA 98252",
    "addr:housenumber":"10828",
    "addr:postcode":"98252",
    "addr:street":"159Th Ave Ne",
    "iso:country":"US",
    "sg:address":"10828 159th Ave NE",
    "sg:city":"Granite Falls",
    "sg:classifiers":[
        {
            "category":"Recreation",
            "type":"Entertainment"
        }
    ],
    "sg:phone":"+1 360 691 7108",
    "sg:postcode":"98252",
    "sg:province":"WA",
    "wof:name":"S&R Fisheries Inc",
    "wof:placetype":"venue"
},
  "geometry": {"coordinates":[-122.017922,48.096532],"type":"Point"}
}