{
  "type": "Feature",
  "properties": {
    "addr:full":"300 S 1st St Mt Vernon WA 98273",
    "addr:housenumber":"300",
    "addr:postcode":"98273",
    "addr:street":"S 1St St",
    "iso:country":"US",
    "sg:address":"300 S 1st St",
    "sg:city":"Mt Vernon",
    "sg:classifiers":[
        {
            "category":"Retail",
            "subcategory":"Portrait Studio",
            "type":"Services"
        }
    ],
    "sg:phone":"+1 360 336 1507",
    "sg:postcode":"98273",
    "sg:province":"WA",
    "sg:tags":[
        "photographer",
        "photo"
    ],
    "wof:name":"Robert Wess Photography",
    "wof:placetype":"venue"
},
  "geometry": {"coordinates":[-122.33708300000001,48.420732],"type":"Point"}
}