{
  "type": "Feature",
  "properties": {
    "addr:full":"6215 S 228th St Kent WA 98032",
    "addr:housenumber":"6215",
    "addr:postcode":"98032",
    "addr:street":"S 228Th St",
    "iso:country":"US",
    "sg:address":"6215 S 228th St",
    "sg:city":"Kent",
    "sg:classifiers":[
        {
            "category":"Government",
            "subcategory":"Post Office",
            "type":"Public Place"
        }
    ],
    "sg:phone":"+1 253 856 9700",
    "sg:postcode":"98032",
    "sg:province":"WA",
    "sg:tags":[
        "delivery",
        "courier"
    ],
    "wof:name":"Wpx Courier",
    "wof:placetype":"venue"
},
  "geometry": {"coordinates":[-122.25699899999999,47.396681],"type":"Point"}
}