{
  "type": "Feature",
  "properties": {
    "addr:full":"18931 SE 133rd Pl Renton WA 98059",
    "addr:postcode":"18931;98059",
    "addr:street":"Se 133Rd Pl",
    "iso:country":"US",
    "sg:address":"18931 SE 133rd Pl",
    "sg:city":"Renton",
    "sg:classifiers":[
        {
            "category":"Building & Trades",
            "subcategory":"Construction",
            "type":"Services"
        }
    ],
    "sg:phone":"+1 425 235 0238",
    "sg:postcode":"98059",
    "sg:province":"WA",
    "sg:tags":[
        "addition",
        "dwelling",
        "remodeling",
        "repair"
    ],
    "wof:name":"Ww Construction Inc",
    "wof:placetype":"venue"
},
  "geometry": {"coordinates":[-122.087389,47.483534],"type":"Point"}
}