{
  "type": "Feature",
  "properties": {
    "addr:full":"8811 S Tacoma Way Lakewood WA 98499",
    "addr:housenumber":"8811",
    "addr:postcode":"98499",
    "addr:street":"S Tacoma Way",
    "iso:country":"US",
    "sg:address":"8811 S Tacoma Way",
    "sg:city":"Lakewood",
    "sg:classifiers":[
        {
            "category":"Government",
            "subcategory":"Office",
            "type":"Public Place"
        }
    ],
    "sg:phone":"+1 253 798 7240",
    "sg:postcode":"98499",
    "sg:province":"WA",
    "sg:tags":[
        "housing",
        "program",
        "administrative"
    ],
    "wof:name":"Pierce County Comm Act Agency",
    "wof:placetype":"venue"
},
  "geometry": {"coordinates":[-122.48372999999999,47.176745],"type":"Point"}
}