{
  "type": "Feature",
  "properties": {
    "addr:full":"625 B St Cheney WA 99004",
    "addr:housenumber":"625",
    "addr:postcode":"99004",
    "addr:street":"B St",
    "iso:country":"US",
    "sg:address":"625 B St",
    "sg:city":"Cheney",
    "sg:classifiers":[
        {
            "category":"Health Services",
            "subcategory":"Doctor",
            "type":"Services"
        }
    ],
    "sg:phone":"+1 509 747 6841",
    "sg:postcode":"99004",
    "sg:province":"WA",
    "sg:tags":[
        "dentist"
    ],
    "wof:name":"Cheney Dental Clinic",
    "wof:placetype":"venue"
},
  "geometry": {"coordinates":[-117.578012,47.492578],"type":"Point"}
}