{
  "type": "Feature",
  "properties": {
    "addr:full":"3515 Norton Ave Everett WA 98201",
    "addr:housenumber":"3515",
    "addr:postcode":"98201",
    "addr:street":"Norton Ave",
    "iso:country":"US",
    "sg:address":"3515 Norton Ave",
    "sg:city":"Everett",
    "sg:classifiers":[
        {
            "category":"Professional",
            "type":"Services"
        }
    ],
    "sg:phone":"+1 425 339 4130",
    "sg:postcode":"98201",
    "sg:province":"WA",
    "wof:name":"Mary Mc Mullen",
    "wof:placetype":"venue"
},
  "geometry": {"coordinates":[-122.213829,47.9693],"type":"Point"}
}