{
  "type": "Feature",
  "properties": {
    "iso:country":"US",
    "sg:address":"1583 Tedford St SE",
    "sg:city":"East Wenatchee",
    "sg:classifiers":[
        {
            "category":"Building & Trades",
            "subcategory":"Construction",
            "type":"Services"
        }
    ],
    "sg:phone":"+1 509 884 9206",
    "sg:postcode":"98802",
    "sg:province":"WA",
    "sg:tags":[
        "contractor",
        "special",
        "w",
        "mfg"
    ],
    "wof:name":"Cole Hurst Log Craftsman",
    "wof:placetype":"venue"
},
  "geometry": {"coordinates":[-120.261661,47.404777],"type":"Point"}
}