{
  "type": "Feature",
  "properties": {
    "addr:full":"13751 Lake City Way NE 3208 Seattle WA 98125",
    "addr:housenumber":"13751;3208",
    "addr:postcode":"98125",
    "addr:street":"Lake City Way Ne",
    "iso:country":"US",
    "sg:address":"13751 Lake City Way NE 3208",
    "sg:city":"Seattle",
    "sg:classifiers":[
        {
            "category":"Home & Garden",
            "subcategory":"Carpets & Floor Coverings",
            "type":"Retail Goods"
        }
    ],
    "sg:phone":"+1 206 362 3650",
    "sg:postcode":"98125",
    "sg:province":"WA",
    "sg:tags":[
        "distributor",
        "rug",
        "manufacturer"
    ],
    "wof:name":"Red Carpet Janitorial Services Company",
    "wof:placetype":"venue"
},
  "geometry": {"coordinates":[-122.292306,47.729204],"type":"Point"}
}