{
  "type": "Feature",
  "properties": {
    "addr:full":"8700 NE Vancouver Mall Dr Ste 133 Vancouver WA 98662",
    "addr:housenumber":"8700",
    "addr:postcode":"98662",
    "addr:street":"Ne Vancouver Mall Dr Ste 133",
    "iso:country":"US",
    "sg:address":"8700 NE Vancouver Mall Dr Ste 133",
    "sg:city":"Vancouver",
    "sg:classifiers":[
        {
            "category":"Shopping",
            "subcategory":"Clothing, Apparel, & Fashions",
            "type":"Retail Goods"
        }
    ],
    "sg:phone":"+1 360 260 0041",
    "sg:postcode":"98662",
    "sg:province":"WA",
    "sg:tags":[
        "accessory",
        "clothing",
        "women's"
    ],
    "wof:name":"Torrid",
    "wof:placetype":"venue"
},
  "geometry": {"coordinates":[-122.581833,45.66031],"type":"Point"}
}