{
  "type": "Feature",
  "properties": {
    "addr:full":"747 N Pittsburg St Kennewick WA 99336",
    "addr:housenumber":"747",
    "addr:postcode":"99336",
    "addr:street":"N Pittsburg St",
    "iso:country":"US",
    "sg:address":"747 N Pittsburg St",
    "sg:city":"Kennewick",
    "sg:classifiers":[
        {
            "category":"Freight",
            "type":"Transportation"
        }
    ],
    "sg:phone":"+1 509 783 8041",
    "sg:postcode":"99336",
    "sg:province":"WA",
    "sg:tags":[
        "arrangement"
    ],
    "wof:name":"Jmd Document Services",
    "wof:placetype":"venue"
},
  "geometry": {"coordinates":[-119.241806,46.219339],"type":"Point"}
}