{
  "type": "Feature",
  "properties": {
    "addr:full":"21107 NE 169th St Woodinville WA 98077",
    "addr:housenumber":"21107",
    "addr:postcode":"98077",
    "addr:street":"Ne 169Th St",
    "iso:country":"US",
    "sg:address":"21107 NE 169th St",
    "sg:city":"Woodinville",
    "sg:classifiers":[
        {
            "category":"Building & Trades",
            "subcategory":"Landscaping Services",
            "type":"Services"
        }
    ],
    "sg:phone":"+1 425 788 7746",
    "sg:postcode":"98077",
    "sg:province":"WA",
    "sg:tags":[
        "landscape",
        "contractor"
    ],
    "wof:name":"Always Landscaping Inc",
    "wof:placetype":"venue"
},
  "geometry": {"coordinates":[-122.05462199999999,47.750264],"type":"Point"}
}