{
  "type": "Feature",
  "properties": {
    "addr:full":"13020 Lake Kathleen Rd SE Renton WA 98059",
    "addr:housenumber":"13020",
    "addr:postcode":"98059",
    "addr:street":"Lake Kathleen Rd Se",
    "iso:country":"US",
    "sg:address":"13020 Lake Kathleen Rd SE",
    "sg:city":"Renton",
    "sg:classifiers":[
        {
            "category":"Building & Trades",
            "subcategory":"Electrical",
            "type":"Services"
        }
    ],
    "sg:phone":"+1 425 255 1441",
    "sg:postcode":"98059",
    "sg:province":"WA",
    "sg:tags":[
        "electric",
        "contractor"
    ],
    "wof:name":"Eagle Electric LLC",
    "wof:placetype":"venue"
},
  "geometry": {"coordinates":[-122.09322400000001,47.485017],"type":"Point"}
}