{
  "type": "Feature",
  "properties": {
    "addr:full":"2807 W Lewis St Pasco WA 99301",
    "addr:housenumber":"2807",
    "addr:postcode":"99301",
    "addr:street":"W Lewis St",
    "iso:country":"US",
    "sg:address":"2807 W Lewis St",
    "sg:city":"Pasco",
    "sg:classifiers":[
        {
            "category":"Communications",
            "subcategory":"Television Station",
            "type":"Services"
        }
    ],
    "sg:phone":"+1 509 547 0547",
    "sg:postcode":"99301",
    "sg:province":"WA",
    "sg:tags":[
        "broadcasting",
        "co"
    ],
    "sg:website":"www.keprtv.com",
    "wof:name":"KEPR",
    "wof:placetype":"venue"
},
  "geometry": {"coordinates":[-119.13056,46.232362],"type":"Point"}
}