{
  "type": "Feature",
  "properties": {
    "addr:full":"2114 Riverside Dr Mount Vernon WA 98273",
    "addr:housenumber":"2114",
    "addr:postcode":"98273",
    "addr:street":"Riverside Dr",
    "iso:country":"US",
    "sg:address":"2114 Riverside Dr",
    "sg:city":"Mount Vernon",
    "sg:classifiers":[
        {
            "category":"Building & Trades",
            "subcategory":"Construction",
            "type":"Services"
        }
    ],
    "sg:phone":"+1 360 424 0087",
    "sg:postcode":"98273",
    "sg:province":"WA",
    "sg:tags":[
        "contractor"
    ],
    "sg:website":"www.skagitbuilders.com",
    "wof:name":"Skagit Builders Inc",
    "wof:placetype":"venue"
},
  "geometry": {"coordinates":[-122.334999,48.437901],"type":"Point"}
}