{
  "type": "Feature",
  "properties": {
    "addr:full":"1 S Wenatchee Ave Wenatchee WA 98801",
    "addr:housenumber":"1",
    "addr:postcode":"98801",
    "addr:street":"S Wenatchee Ave",
    "iso:country":"US",
    "sg:address":"1 S Wenatchee Ave",
    "sg:city":"Wenatchee",
    "sg:classifiers":[
        {
            "category":"Shopping",
            "subcategory":"Florist",
            "type":"Retail Goods"
        }
    ],
    "sg:phone":"+1 509 664 0561",
    "sg:postcode":"98801",
    "sg:province":"WA",
    "sg:tags":[
        "re",
        "merchandise"
    ],
    "wof:name":"Bloomers Flower & Garden House",
    "wof:placetype":"venue"
},
  "geometry": {"coordinates":[-120.310441,47.423415],"type":"Point"}
}