{
  "type": "Feature",
  "properties": {
    "addr:full":"The Old Rainier Brewery 3100 Airport Way S Ste 8100 Seattle WA 98134",
    "addr:housenumber":"3100",
    "addr:postcode":"98134",
    "addr:street":"Airport Way S Ste 8100",
    "iso:country":"US",
    "sg:address":"The Old Rainier Brewery 3100 Airport Way S Ste 8100",
    "sg:city":"Seattle",
    "sg:classifiers":[
        {
            "category":"Brewery",
            "type":"Food & Drink"
        }
    ],
    "sg:phone":"+1 206 351 8250",
    "sg:postcode":"98134",
    "sg:province":"WA",
    "sg:website":"www.emeraldcitybeer.com/",
    "wof:name":"Emerald City Beer Company",
    "wof:placetype":"venue"
},
  "geometry": {"coordinates":[-122.320728,47.575541],"type":"Point"}
}