{
  "type": "Feature",
  "properties": {
    "iso:country":"US",
    "sg:address":"30556 55th Ave S",
    "sg:city":"Auburn",
    "sg:classifiers":[
        {
            "category":"Freight",
            "type":"Transportation"
        }
    ],
    "sg:phone":"+1 253 833 3239",
    "sg:postcode":"98001",
    "sg:province":"WA",
    "sg:tags":[
        "operator",
        "local",
        "trucking"
    ],
    "wof:name":"Auburn West Enterprises",
    "wof:placetype":"venue"
},
  "geometry": {"coordinates":[-122.266677,47.324714],"type":"Point"}
}