{
  "type": "Feature",
  "properties": {
    "addr:full":"401 E 25th St Tacoma WA 98421",
    "addr:housenumber":"401",
    "addr:postcode":"98421",
    "addr:street":"E 25Th St",
    "iso:country":"US",
    "sg:address":"401 E 25th St",
    "sg:city":"Tacoma",
    "sg:classifiers":[
        {
            "category":"Manufacturing",
            "subcategory":"Food",
            "type":"Manufacturing & Wholesale Goods"
        }
    ],
    "sg:phone":"+1 253 572 2557",
    "sg:postcode":"98421",
    "sg:province":"WA",
    "sg:tags":[
        "fish",
        "packaged",
        "mfg"
    ],
    "wof:name":"Y & L of Washington Inc",
    "wof:placetype":"venue"
},
  "geometry": {"coordinates":[-122.42774,47.239819],"type":"Point"}
}