{
  "type": "Feature",
  "properties": {
    "iso:country":"US",
    "sg:address":"2707 64th Ave SE",
    "sg:city":"Mercer Island",
    "sg:classifiers":[
        {
            "category":"Professional",
            "subcategory":"Management & Consulting",
            "type":"Services"
        }
    ],
    "sg:phone":"+1 206 236 3004",
    "sg:postcode":"98040",
    "sg:province":"WA",
    "sg:tags":[
        "construction"
    ],
    "wof:name":"John L Elmer & Assoc",
    "wof:placetype":"venue"
},
  "geometry": {"coordinates":[-122.24880400000001,47.586715],"type":"Point"}
}