{
  "type": "Feature",
  "properties": {
    "addr:full":"3602 37th Ave S Seattle WA 98144",
    "addr:housenumber":"3602",
    "addr:postcode":"98144",
    "addr:street":"37Th Ave S",
    "iso:country":"US",
    "sg:address":"3602 37th Ave S",
    "sg:city":"Seattle",
    "sg:classifiers":[
        {
            "category":"Building & Trades",
            "subcategory":"Construction",
            "type":"Services"
        }
    ],
    "sg:phone":"+1 206 723 4383",
    "sg:postcode":"98144",
    "sg:province":"WA",
    "sg:tags":[
        "residential"
    ],
    "wof:name":"Marten Kai Roland",
    "wof:placetype":"venue"
},
  "geometry": {"coordinates":[-122.285984,47.571063],"type":"Point"}
}