{
  "type": "Feature",
  "properties": {
    "addr:full":"3300 204th St SW Lynnwood WA 98036",
    "addr:housenumber":"3300",
    "addr:postcode":"98036",
    "addr:street":"204Th St Sw",
    "iso:country":"US",
    "sg:address":"3300 204th St SW",
    "sg:city":"Lynnwood",
    "sg:classifiers":[
        {
            "category":"Education",
            "subcategory":"School",
            "type":"Public Place"
        }
    ],
    "sg:phone":"+1 425 670 7884",
    "sg:postcode":"98036",
    "sg:province":"WA",
    "sg:tags":[
        "elementary"
    ],
    "wof:name":"Hazelwood Elementary School",
    "wof:placetype":"venue"
},
  "geometry": {"coordinates":[-122.279008,47.813604],"type":"Point"}
}