{
  "type": "Feature",
  "properties": {
    "addr:full":"1921 3rd Ave Seattle WA 98101",
    "addr:housenumber":"1921",
    "addr:postcode":"98101",
    "addr:street":"3Rd Ave",
    "iso:country":"US",
    "sg:address":"1921 3rd Ave",
    "sg:city":"Seattle",
    "sg:classifiers":[
        {
            "category":"Manufacturing",
            "subcategory":"Retail Goods",
            "type":"Manufacturing & Wholesale Goods"
        }
    ],
    "sg:phone":"+1 206 269 0868",
    "sg:postcode":"98101",
    "sg:province":"WA",
    "sg:tags":[
        "lead",
        "mfg"
    ],
    "wof:name":"Besaid Bode",
    "wof:placetype":"venue"
},
  "geometry": {"coordinates":[-122.34076399999999,47.612183],"type":"Point"}
}