{
  "type": "Feature",
  "properties": {
    "addr:full":"457 NE Eliason St Poulsbo WA 98370",
    "addr:housenumber":"457",
    "addr:postcode":"98370",
    "addr:street":"Ne Eliason St",
    "iso:country":"US",
    "sg:address":"457 NE Eliason St",
    "sg:city":"Poulsbo",
    "sg:classifiers":[
        {
            "category":"Professional",
            "subcategory":"Employment Agencies",
            "type":"Services"
        }
    ],
    "sg:phone":"+1 360 697 6850",
    "sg:postcode":"98370",
    "sg:province":"WA",
    "sg:tags":[
        "teacher"
    ],
    "wof:name":"George Epperly",
    "wof:placetype":"venue"
},
  "geometry": {"coordinates":[-122.644071,47.73264],"type":"Point"}
}