{
  "type": "Feature",
  "properties": {
    "iso:country":"US",
    "sg:address":"14424 209th Pl SE",
    "sg:city":"Renton",
    "sg:classifiers":[
        {
            "category":"Retail",
            "subcategory":"Repair Shop",
            "type":"Services"
        }
    ],
    "sg:phone":"+1 425 235 2151",
    "sg:postcode":"98059",
    "sg:province":"WA",
    "sg:tags":[
        "design",
        "hydraulic"
    ],
    "wof:name":"Evans Hydraulics",
    "wof:placetype":"venue"
},
  "geometry": {"coordinates":[-122.061189,47.472805],"type":"Point"}
}