{
  "type": "Feature",
  "properties": {
    "addr:full":"1816 10th Ave W Seattle WA 98119",
    "addr:housenumber":"1816",
    "addr:postcode":"98119",
    "addr:street":"10Th Ave W",
    "iso:country":"US",
    "sg:address":"1816 10th Ave W",
    "sg:city":"Seattle",
    "sg:classifiers":[
        {
            "category":"Real Estate",
            "subcategory":"Real Estate Agent",
            "type":"Services"
        }
    ],
    "sg:phone":"+1 206 286 6691",
    "sg:postcode":"98119",
    "sg:province":"WA",
    "wof:name":"Lake City Leasing Inc",
    "wof:placetype":"venue"
},
  "geometry": {"coordinates":[-122.370283,47.635737],"type":"Point"}
}