{
  "type": "Feature",
  "properties": {
    "addr:full":"17525 Hwy 99 Lynnwood WA 98037",
    "addr:housenumber":"17525",
    "addr:postcode":"98037",
    "addr:street":"Hwy 99",
    "iso:country":"US",
    "sg:address":"17525 Hwy 99",
    "sg:city":"Lynnwood",
    "sg:classifiers":[
        {
            "category":"Food & Beverages",
            "subcategory":"Liquor & Beverages",
            "type":"Retail Goods"
        }
    ],
    "sg:phone":"+1 425 787 3494",
    "sg:postcode":"98037",
    "sg:province":"WA",
    "wof:name":"State Liquor Store",
    "wof:placetype":"venue"
},
  "geometry": {"coordinates":[-122.298621,47.84034],"type":"Point"}
}