{
  "type": "Feature",
  "properties": {
    "addr:full":"1505 4th Ave E Olympia WA 98506",
    "addr:housenumber":"1505",
    "addr:postcode":"98506",
    "addr:street":"4Th Ave E",
    "iso:country":"US",
    "sg:address":"1505 4th Ave E",
    "sg:city":"Olympia",
    "sg:classifiers":[
        {
            "category":"Organizations",
            "subcategory":"Religious Organization",
            "type":"Services"
        }
    ],
    "sg:phone":"+1 360 754 2441",
    "sg:postcode":"98506",
    "sg:province":"WA",
    "sg:tags":[
        "church"
    ],
    "sg:website":"www.salvationarmyolympia.org",
    "wof:name":"Salvation Army",
    "wof:placetype":"venue"
},
  "geometry": {"coordinates":[-122.880499,47.045976],"type":"Point"}
}