{
  "type": "Feature",
  "properties": {
    "addr:full":"4939 N Pearl St Ruston WA 98407",
    "addr:housenumber":"4939",
    "addr:postcode":"98407",
    "addr:street":"N Pearl St",
    "iso:country":"US",
    "sg:address":"4939 N Pearl St",
    "sg:city":"Ruston",
    "sg:classifiers":[
        {
            "category":"Sports & Exercise",
            "subcategory":"Gym",
            "type":"Entertainment"
        },
        {
            "category":"Arena",
            "subcategory":"Sports Club",
            "type":"Entertainment"
        }
    ],
    "sg:phone":"+1 253 752 8599",
    "sg:postcode":"98407",
    "sg:province":"WA",
    "sg:tags":[
        "program",
        "health",
        "gymnasium",
        "physical",
        "fitness"
    ],
    "sg:website":"http://www.ladiesworkoutexpress.com",
    "wof:name":"Ladies Workout Express",
    "wof:placetype":"venue"
},
  "geometry": {"coordinates":[-122.51570100000001,47.295493],"type":"Point"}
}