{
  "type": "Feature",
  "properties": {
    "addr:full":"1705 S 93rd St Seattle WA 98108",
    "addr:housenumber":"1705",
    "addr:postcode":"98108",
    "addr:street":"S 93Rd St",
    "iso:country":"US",
    "sg:address":"1705 S 93rd St",
    "sg:city":"Seattle",
    "sg:classifiers":[
        {
            "category":"Shopping",
            "subcategory":"Gifts & Souvenirs",
            "type":"Retail Goods"
        }
    ],
    "sg:phone":"+1 206 396 3294",
    "sg:postcode":"98108",
    "sg:province":"WA",
    "wof:name":"Cards Construction",
    "wof:placetype":"venue"
},
  "geometry": {"coordinates":[-122.30923900000001,47.520188],"type":"Point"}
}