{
  "type": "Feature",
  "properties": {
    "addr:full":"16855 194th Ave SE Renton WA 98058",
    "addr:housenumber":"16855",
    "addr:postcode":"98058",
    "addr:street":"194Th Ave Se",
    "iso:country":"US",
    "sg:address":"16855 194th Ave SE",
    "sg:city":"Renton",
    "sg:classifiers":[
        {
            "category":"Government",
            "subcategory":"Fire Station",
            "type":"Public Place"
        }
    ],
    "sg:phone":"+1 425 228 6756",
    "sg:postcode":"98058",
    "sg:province":"WA",
    "sg:tags":[
        "protection"
    ],
    "wof:name":"Maple Vly Fire Lf Sfety Stn 84",
    "wof:placetype":"venue"
},
  "geometry": {"coordinates":[-122.082251,47.450496],"type":"Point"}
}