{
  "type": "Feature",
  "properties": {
    "addr:full":"13204 97th Ave NE Kirkland WA 98034",
    "addr:housenumber":"13204",
    "addr:postcode":"98034",
    "addr:street":"97Th Ave Ne",
    "iso:country":"US",
    "sg:address":"13204 97th Ave NE",
    "sg:city":"Kirkland",
    "sg:classifiers":[
        {
            "category":"Freight",
            "type":"Transportation"
        }
    ],
    "sg:phone":"+1 425 825 7231",
    "sg:postcode":"98034",
    "sg:province":"WA",
    "sg:tags":[
        "local",
        "storage",
        "trucking"
    ],
    "wof:name":"Zid",
    "wof:placetype":"venue"
},
  "geometry": {"coordinates":[-122.21158200000001,47.719192],"type":"Point"}
}