{
  "type": "Feature",
  "properties": {
    "addr:full":"20231 80th Ave S Kent WA 98032",
    "addr:housenumber":"20231",
    "addr:postcode":"98032",
    "addr:street":"80Th Ave S",
    "iso:country":"US",
    "sg:address":"20231 80th Ave S",
    "sg:city":"Kent",
    "sg:classifiers":[
        {
            "category":"Freight",
            "type":"Transportation"
        }
    ],
    "sg:phone":"+1 253 872 7255",
    "sg:postcode":"98032",
    "sg:province":"WA",
    "sg:tags":[
        "delivery"
    ],
    "wof:name":"D's Delivery",
    "wof:placetype":"venue"
},
  "geometry": {"coordinates":[-122.233367,47.422078],"type":"Point"}
}