{
  "type": "Feature",
  "properties": {
    "addr:full":"29302 40th Ave E Graham WA 98338",
    "addr:housenumber":"29302",
    "addr:postcode":"98338",
    "addr:street":"40Th Ave E",
    "iso:country":"US",
    "sg:address":"29302 40th Ave E",
    "sg:city":"Graham",
    "sg:classifiers":[
        {
            "category":"Building & Trades",
            "subcategory":"Construction",
            "type":"Services"
        }
    ],
    "sg:phone":"+1 253 847 8440",
    "sg:postcode":"98338",
    "sg:province":"WA",
    "sg:tags":[
        "house"
    ],
    "wof:name":"Veritas",
    "wof:placetype":"venue"
},
  "geometry": {"coordinates":[-122.376549,46.989603],"type":"Point"}
}