{
  "type": "Feature",
  "properties": {
    "addr:full":"9912 Donovan Ct SE Yelm WA 98597",
    "addr:housenumber":"9912",
    "addr:postcode":"98597",
    "addr:street":"Donovan Ct Se",
    "iso:country":"US",
    "sg:address":"9912 Donovan Ct SE",
    "sg:city":"Yelm",
    "sg:classifiers":[
        {
            "category":"Professional",
            "subcategory":"Lawyer & Legal Services",
            "type":"Services"
        }
    ],
    "sg:phone":"+1 360 960 8366",
    "sg:postcode":"98597",
    "sg:province":"WA",
    "sg:tags":[
        "attorney",
        "practice",
        "plan"
    ],
    "wof:name":"The Crowe Law Office",
    "wof:placetype":"venue"
},
  "geometry": {"coordinates":[-122.596993,46.944549],"type":"Point"}
}