{
  "type": "Feature",
  "properties": {
    "addr:full":"2611 Englewood Ave Yakima WA 98902",
    "addr:housenumber":"2611",
    "addr:postcode":"98902",
    "addr:street":"Englewood Ave",
    "iso:country":"US",
    "sg:address":"2611 Englewood Ave",
    "sg:city":"Yakima",
    "sg:classifiers":[
        {
            "category":"Building & Trades",
            "subcategory":"Landscaping Services",
            "type":"Services"
        }
    ],
    "sg:phone":"+1 509 248 2506",
    "sg:postcode":"98902",
    "sg:province":"WA",
    "wof:name":"Garys Lawn Service",
    "wof:placetype":"venue"
},
  "geometry": {"coordinates":[-120.545737,46.607145],"type":"Point"}
}