{
  "type": "Feature",
  "properties": {
    "addr:full":"2305 Ellington St Ellensburg WA 98926",
    "addr:housenumber":"2305",
    "addr:postcode":"98926",
    "addr:street":"Ellington St",
    "iso:country":"US",
    "sg:address":"2305 Ellington St",
    "sg:city":"Ellensburg",
    "sg:classifiers":[
        {
            "category":"Wholesale",
            "subcategory":"Machinery & Supplies",
            "type":"Manufacturing & Wholesale Goods"
        }
    ],
    "sg:phone":"+1 509 925 3492",
    "sg:postcode":"98926",
    "sg:province":"WA",
    "sg:tags":[
        "machine",
        "tool",
        "industrial"
    ],
    "wof:name":"Fordco Tools & Supply",
    "wof:placetype":"venue"
},
  "geometry": {"coordinates":[-120.54840299999999,47.017578],"type":"Point"}
}