{
  "type": "Feature",
  "properties": {
    "addr:full":"19815 NE Allworth Rd Battle Ground WA 98604",
    "addr:housenumber":"19815",
    "addr:postcode":"98604",
    "addr:street":"Ne Allworth Rd",
    "iso:country":"US",
    "sg:address":"19815 NE Allworth Rd",
    "sg:city":"Battle Ground",
    "sg:classifiers":[
        {
            "category":"Building & Trades",
            "subcategory":"Construction",
            "type":"Services"
        }
    ],
    "sg:phone":"+1 360 687 5885",
    "sg:postcode":"98604",
    "sg:province":"WA",
    "sg:tags":[
        "general",
        "contractor"
    ],
    "wof:name":"Systems II Construction",
    "wof:placetype":"venue"
},
  "geometry": {"coordinates":[-122.469447,45.799278],"type":"Point"}
}