{
  "type": "Feature",
  "properties": {
    "addr:full":"5900 NE Gunderson Rd Poulsbo WA 98370",
    "addr:housenumber":"5900",
    "addr:postcode":"98370",
    "addr:street":"Ne Gunderson Rd",
    "iso:country":"US",
    "sg:address":"5900 NE Gunderson Rd",
    "sg:city":"Poulsbo",
    "sg:classifiers":[
        {
            "category":"Organizations",
            "subcategory":"Non-profit Organization",
            "type":"Services"
        }
    ],
    "sg:phone":"+1 360 598 4060",
    "sg:postcode":"98370",
    "sg:province":"WA",
    "sg:tags":[
        "social"
    ],
    "wof:name":"Northsound Home Inspectn",
    "wof:placetype":"venue"
},
  "geometry": {"coordinates":[-122.57046200000001,47.769932],"type":"Point"}
}