{
  "type": "Feature",
  "properties": {
    "addr:full":"1205 2nd Ave Seattle WA 98101",
    "addr:housenumber":"1205",
    "addr:postcode":"98101",
    "addr:street":"2Nd Ave",
    "iso:country":"US",
    "sg:address":"1205 2nd Ave",
    "sg:city":"Seattle",
    "sg:classifiers":[
        {
            "category":"Social Services",
            "subcategory":"Job Training",
            "type":"Services"
        }
    ],
    "sg:phone":"+1 206 467 0594",
    "sg:postcode":"98101",
    "sg:province":"WA",
    "sg:tags":[
        "career",
        "counseling",
        "vocational"
    ],
    "wof:name":"International Education Netwrk",
    "wof:placetype":"venue"
},
  "geometry": {"coordinates":[-122.33713400000001,47.607227],"type":"Point"}
}