{
  "type": "Feature",
  "properties": {
    "addr:full":"3703 California Ave SW Seattle WA 98116",
    "addr:housenumber":"3703",
    "addr:postcode":"98116",
    "addr:street":"California Ave Sw",
    "iso:country":"US",
    "sg:address":"3703 California Ave SW",
    "sg:city":"Seattle",
    "sg:classifiers":[
        {
            "category":"Health Services",
            "subcategory":"Chiropractor",
            "type":"Services"
        }
    ],
    "sg:phone":"+1 206 937 3965",
    "sg:postcode":"98116",
    "sg:province":"WA",
    "wof:name":"Swanson & Seepersad Chiropractic",
    "wof:placetype":"venue"
},
  "geometry": {"coordinates":[-122.38679500000001,47.571114],"type":"Point"}
}