{
  "type": "Feature",
  "properties": {
    "addr:full":"2987 McNitt Rd Kettle Falls WA 99141",
    "addr:housenumber":"2987",
    "addr:postcode":"99141",
    "addr:street":"Mcnitt Rd",
    "iso:country":"US",
    "sg:address":"2987 McNitt Rd",
    "sg:city":"Kettle Falls",
    "sg:classifiers":[
        {
            "category":"Farming",
            "subcategory":"Livestock Farm",
            "type":"Manufacturing & Wholesale Goods"
        }
    ],
    "sg:phone":"+1 509 738 6783",
    "sg:postcode":"99141",
    "sg:province":"WA",
    "sg:tags":[
        "beef",
        "feedlot",
        "cattle"
    ],
    "wof:name":"Frank Richart",
    "wof:placetype":"venue"
},
  "geometry": {"coordinates":[-118.101479,48.782819],"type":"Point"}
}