{
  "type": "Feature",
  "properties": {
    "addr:full":"15215 NE 90th St Redmond WA 98052",
    "addr:housenumber":"15215",
    "addr:postcode":"98052",
    "addr:street":"Ne 90Th St",
    "iso:country":"US",
    "sg:address":"15215 NE 90th St",
    "sg:city":"Redmond",
    "sg:classifiers":[
        {
            "category":"Retail",
            "subcategory":"Auto Repair",
            "type":"Services"
        }
    ],
    "sg:phone":"+1 425 861 8060",
    "sg:postcode":"98052",
    "sg:province":"WA",
    "sg:website":"www.zahntechauto.com",
    "wof:name":"ZahnTech Auto",
    "wof:placetype":"venue"
},
  "geometry": {"coordinates":[-122.137283,47.682275],"type":"Point"}
}