{
  "type": "Feature",
  "properties": {
    "addr:full":"2507 S Starlight Ln Veradale WA 99037",
    "addr:housenumber":"2507",
    "addr:postcode":"99037",
    "addr:street":"S Starlight Ln",
    "iso:country":"US",
    "sg:address":"2507 S Starlight Ln",
    "sg:city":"Veradale",
    "sg:classifiers":[
        {
            "category":"Professional",
            "type":"Services"
        }
    ],
    "sg:phone":"+1 509 928 1457",
    "sg:postcode":"99037",
    "sg:province":"WA",
    "wof:name":"Richard B Jarvis",
    "wof:placetype":"venue"
},
  "geometry": {"coordinates":[-117.177952,47.633338],"type":"Point"}
}