{
  "type": "Feature",
  "properties": {
    "iso:country":"US",
    "sg:address":"5293 S Naches Rd",
    "sg:city":"Naches",
    "sg:classifiers":[
        {
            "category":"Farming",
            "subcategory":"Orchard",
            "type":"Manufacturing & Wholesale Goods"
        }
    ],
    "sg:phone":"+1 509 966 7311",
    "sg:postcode":"98937",
    "sg:province":"WA",
    "sg:tags":[
        "fruit",
        "tree"
    ],
    "wof:name":"David Daniel Riggs",
    "wof:placetype":"venue"
},
  "geometry": {"coordinates":[-120.665479,46.683312],"type":"Point"}
}