{
  "type": "Feature",
  "properties": {
    "addr:full":"3223 92nd Ave NE Bellevue WA 98004",
    "addr:housenumber":"3223",
    "addr:postcode":"98004",
    "addr:street":"92Nd Ave Ne",
    "iso:country":"US",
    "sg:address":"3223 92nd Ave NE",
    "sg:city":"Bellevue",
    "sg:classifiers":[
        {
            "category":"Professional",
            "type":"Services"
        }
    ],
    "sg:phone":"+1 425 454 4287",
    "sg:postcode":"98004",
    "sg:province":"WA",
    "wof:name":"Steven V Lundgren",
    "wof:placetype":"venue"
},
  "geometry": {"coordinates":[-122.217766,47.639862],"type":"Point"}
}