{
  "type": "Feature",
  "properties": {
    "addr:full":"7911 10th Ave S Seattle WA 98108",
    "addr:housenumber":"7911",
    "addr:postcode":"98108",
    "addr:street":"10Th Ave S",
    "iso:country":"US",
    "sg:address":"7911 10th Ave S",
    "sg:city":"Seattle",
    "sg:classifiers":[
        {
            "category":"Manufacturing",
            "subcategory":"Glass & Minerals",
            "type":"Manufacturing & Wholesale Goods"
        }
    ],
    "sg:phone":"+1 206 763 7020",
    "sg:postcode":"98108",
    "sg:province":"WA",
    "sg:tags":[
        "pottery",
        "refractory",
        "product",
        "mfg"
    ],
    "wof:name":"Pyro Media Inc",
    "wof:placetype":"venue"
},
  "geometry": {"coordinates":[-122.320251,47.530559],"type":"Point"}
}