{
  "type": "Feature",
  "properties": {
    "addr:full":"209 N Bend Blvd N North Bend WA 98045",
    "addr:housenumber":"209",
    "addr:postcode":"98045",
    "addr:street":"N Bend Blvd N",
    "iso:country":"US",
    "sg:address":"209 N Bend Blvd N",
    "sg:city":"North Bend",
    "sg:classifiers":[
        {
            "category":"Insurance",
            "subcategory":"Insurance Agent",
            "type":"Services"
        }
    ],
    "sg:phone":"+1 425 888 6288",
    "sg:postcode":"98045",
    "sg:province":"WA",
    "wof:name":"Allstate Insurance",
    "wof:placetype":"venue"
},
  "geometry": {"coordinates":[-121.787452,47.494984],"type":"Point"}
}