{
  "type": "Feature",
  "properties": {
    "addr:full":"15555 15th Ave NE Seattle WA 98155",
    "addr:housenumber":"15555",
    "addr:postcode":"98155",
    "addr:street":"15Th Ave Ne",
    "iso:country":"US",
    "sg:address":"15555 15th Ave NE",
    "sg:city":"Seattle",
    "sg:classifiers":[
        {
            "category":"Education",
            "subcategory":"Special Training",
            "type":"Public Place"
        }
    ],
    "sg:phone":"+1 206 533 2300",
    "sg:postcode":"98155",
    "sg:province":"WA",
    "wof:name":"Kumon",
    "wof:placetype":"venue"
},
  "geometry": {"coordinates":[-122.31304799999999,47.743571],"type":"Point"}
}