{
  "type": "Feature",
  "properties": {
    "iso:country":"US",
    "sg:address":"17825 NE 65th St",
    "sg:city":"Redmond",
    "sg:classifiers":[
        {
            "category":"Retail",
            "subcategory":"Auto Repair",
            "type":"Services"
        }
    ],
    "sg:phone":"+1 425 885 6609",
    "sg:postcode":"98052",
    "sg:province":"WA",
    "sg:tags":[
        "repairing",
        "automobile"
    ],
    "wof:name":"Jim's Automotive Performance",
    "wof:placetype":"venue"
},
  "geometry": {"coordinates":[-122.103325,47.66392],"type":"Point"}
}