{
  "type": "Feature",
  "properties": {
    "addr:full":"703 26th St SE Auburn WA 98002",
    "addr:housenumber":"703",
    "addr:postcode":"98002",
    "addr:street":"26Th St Se",
    "iso:country":"US",
    "sg:address":"703 26th St SE",
    "sg:city":"Auburn",
    "sg:classifiers":[
        {
            "category":"Professional",
            "subcategory":"Computer Services",
            "type":"Services"
        }
    ],
    "sg:phone":"+1 253 833 2864",
    "sg:postcode":"98002",
    "sg:province":"WA",
    "sg:tags":[
        "related"
    ],
    "wof:name":"Colorful Solutions LLC",
    "wof:placetype":"venue"
},
  "geometry": {"coordinates":[-122.219639,47.285588],"type":"Point"}
}