{
  "type": "Feature",
  "properties": {
    "addr:full":"8511 Canyon Rd E Puyallup WA 98371",
    "addr:housenumber":"8511",
    "addr:postcode":"98371",
    "addr:street":"Canyon Rd E",
    "iso:country":"US",
    "sg:address":"8511 Canyon Rd E",
    "sg:city":"Puyallup",
    "sg:classifiers":[
        {
            "category":"Health Services",
            "subcategory":"Chiropractor",
            "type":"Services"
        }
    ],
    "sg:phone":"+1 253 535 3931",
    "sg:postcode":"98371",
    "sg:province":"WA",
    "wof:name":"Summit Chiropractic Ctr",
    "wof:placetype":"venue"
},
  "geometry": {"coordinates":[-122.35709900000001,47.179132],"type":"Point"}
}