{
  "type": "Feature",
  "properties": {
    "addr:full":"73 Glessner Ln Yakima WA 98901",
    "addr:housenumber":"73",
    "addr:postcode":"98901",
    "addr:street":"Glessner Ln",
    "iso:country":"US",
    "sg:address":"73 Glessner Ln",
    "sg:city":"Yakima",
    "sg:classifiers":[
        {
            "category":"Retail",
            "subcategory":"Animal Services",
            "type":"Services"
        }
    ],
    "sg:phone":"+1 509 457 1192",
    "sg:postcode":"98901",
    "sg:province":"WA",
    "wof:name":"Yakz Stables",
    "wof:placetype":"venue"
},
  "geometry": {"coordinates":[-120.37772,46.580722],"type":"Point"}
}