{
  "type": "Feature",
  "properties": {
    "addr:full":"14355 Aurora Ave N Seattle WA 98133",
    "addr:housenumber":"14355",
    "addr:postcode":"98133",
    "addr:street":"Aurora Ave N",
    "iso:country":"US",
    "sg:address":"14355 Aurora Ave N",
    "sg:city":"Seattle",
    "sg:classifiers":[
        {
            "category":"Food & Beverages",
            "subcategory":"Specialty",
            "type":"Retail Goods"
        }
    ],
    "sg:phone":"+1 206 365 5240",
    "sg:postcode":"98133",
    "sg:province":"WA",
    "sg:tags":[
        "health",
        "market"
    ],
    "sg:website":"www.supersup.com/North-Seattle.html",
    "wof:name":"Seattle Super Supplements",
    "wof:placetype":"venue"
},
  "geometry": {"coordinates":[-122.345001,47.733299],"type":"Point"}
}