{
  "type": "Feature",
  "properties": {
    "addr:full":"280 W 3rd Ave Kettle Falls WA 99141",
    "addr:housenumber":"280",
    "addr:postcode":"99141",
    "addr:street":"W 3Rd Ave",
    "iso:country":"US",
    "sg:address":"280 W 3rd Ave",
    "sg:city":"Kettle Falls",
    "sg:classifiers":[
        {
            "category":"Shopping",
            "subcategory":"Pharmacy",
            "type":"Retail Goods"
        }
    ],
    "sg:phone":"+1 509 738 2223",
    "sg:postcode":"99141",
    "sg:province":"WA",
    "wof:name":"Kettle Falls Pharmacy",
    "wof:placetype":"venue"
},
  "geometry": {"coordinates":[-118.059575,48.610788],"type":"Point"}
}