{
  "type": "Feature",
  "properties": {
    "addr:full":"130 Churchill Ln Port Ludlow WA 98365",
    "addr:housenumber":"130",
    "addr:postcode":"98365",
    "addr:street":"Churchill Ln",
    "iso:country":"US",
    "sg:address":"130 Churchill Ln",
    "sg:city":"Port Ludlow",
    "sg:classifiers":[
        {
            "category":"Organizations",
            "subcategory":"Religious Organization",
            "type":"Services"
        }
    ],
    "sg:phone":"+1 360 385 1579",
    "sg:postcode":"98365",
    "sg:province":"WA",
    "sg:tags":[
        "church"
    ],
    "wof:name":"Community United Methodist Chr",
    "wof:placetype":"venue"
},
  "geometry": {"coordinates":[-122.678259,47.868695],"type":"Point"}
}