{
  "type": "Feature",
  "properties": {
    "addr:full":"17505 N Little Spokane Dr Colbert WA 99005",
    "addr:housenumber":"17505",
    "addr:postcode":"99005",
    "addr:street":"N;Spokane Dr Colbert",
    "iso:country":"US",
    "sg:address":"17505 N Little Spokane Dr",
    "sg:city":"Colbert",
    "sg:classifiers":[
        {
            "category":"Professional",
            "subcategory":"Business Services",
            "type":"Services"
        }
    ],
    "sg:phone":"+1 509 468 5252",
    "sg:postcode":"99005",
    "sg:province":"WA",
    "wof:name":"Creative Endeavors",
    "wof:placetype":"venue"
},
  "geometry": {"coordinates":[-117.37967399999999,47.817141],"type":"Point"}
}