{
  "type": "Feature",
  "properties": {
    "addr:full":"301 Garfield St S Tacoma WA 98444",
    "addr:housenumber":"301",
    "addr:postcode":"98444",
    "addr:street":"Garfield St S",
    "iso:country":"US",
    "sg:address":"301 Garfield St S",
    "sg:city":"Tacoma",
    "sg:classifiers":[
        {
            "category":"Retail",
            "subcategory":"Auto Repair",
            "type":"Services"
        }
    ],
    "sg:phone":"+1 253 537 7001",
    "sg:postcode":"98444",
    "sg:province":"WA",
    "sg:tags":[
        "repairing",
        "automobile"
    ],
    "wof:name":"Garfield Street Auto Parts",
    "wof:placetype":"venue"
},
  "geometry": {"coordinates":[-122.43591000000001,47.1462],"type":"Point"}
}