{
  "type": "Feature",
  "properties": {
    "addr:full":"18429 12th Ave W Lynnwood WA 98037",
    "addr:housenumber":"18429",
    "addr:postcode":"98037",
    "addr:street":"12Th Ave W",
    "iso:country":"US",
    "sg:address":"18429 12th Ave W",
    "sg:city":"Lynnwood",
    "sg:classifiers":[
        {
            "category":"Social Services",
            "type":"Services"
        }
    ],
    "sg:phone":"+1 425 280 3805",
    "sg:postcode":"98037",
    "sg:province":"WA",
    "wof:name":"Nurturing Pathways",
    "wof:placetype":"venue"
},
  "geometry": {"coordinates":[-122.25001399999999,47.831006],"type":"Point"}
}