{
  "type": "Feature",
  "properties": {
    "addr:full":"16339 NE 74th St Redmond WA 98052",
    "addr:housenumber":"16339",
    "addr:postcode":"98052",
    "addr:street":"Ne 74Th St",
    "iso:country":"US",
    "sg:address":"16339 NE 74th St",
    "sg:city":"Redmond",
    "sg:classifiers":[
        {
            "category":"Professional",
            "type":"Services"
        }
    ],
    "sg:phone":"+1 425 376 0615",
    "sg:postcode":"98052",
    "sg:province":"WA",
    "wof:name":"Maggies Christmas",
    "wof:placetype":"venue"
},
  "geometry": {"coordinates":[-122.12182199999999,47.670655],"type":"Point"}
}