{
  "type": "Feature",
  "properties": {
    "addr:full":"13023 100th Ave NE Kirkland WA 98034",
    "addr:housenumber":"13023",
    "addr:postcode":"98034",
    "addr:street":"100Th Ave Ne",
    "iso:country":"US",
    "sg:address":"13023 100th Ave NE",
    "sg:city":"Kirkland",
    "sg:classifiers":[
        {
            "category":"Shopping",
            "subcategory":"Clothing, Apparel, & Fashions",
            "type":"Retail Goods"
        }
    ],
    "sg:phone":"+1 425 814 9191",
    "sg:postcode":"98034",
    "sg:province":"WA",
    "sg:tags":[
        "personal",
        "supply",
        "dancing"
    ],
    "sg:website":"www.artsdanceshop.com",
    "wof:name":"Art's Dance Shop",
    "wof:placetype":"venue"
},
  "geometry": {"coordinates":[-122.208,47.717098],"type":"Point"}
}