{
  "type": "Feature",
  "properties": {
    "addr:full":"810 Southcenter Mall Tukwila WA 98188",
    "addr:housenumber":"810",
    "addr:postcode":"98188",
    "addr:street":"Southcenter Mall",
    "iso:country":"US",
    "sg:address":"810 Southcenter Mall",
    "sg:city":"Tukwila",
    "sg:classifiers":[
        {
            "category":"Shopping",
            "subcategory":"Clothing, Apparel, & Fashions",
            "type":"Retail Goods"
        }
    ],
    "sg:phone":"+1 206 988 0404",
    "sg:postcode":"98188",
    "sg:province":"WA",
    "sg:tags":[
        "shop",
        "cap",
        "hat",
        "sportswear"
    ],
    "sg:website":"http://www.lids.com",
    "wof:name":"Lids",
    "wof:placetype":"venue"
},
  "geometry": {"coordinates":[-122.25894599999999,47.460675],"type":"Point"}
}