{
  "type": "Feature",
  "properties": {
    "addr:full":"43726 284th Ave SE Enumclaw WA 98022",
    "addr:housenumber":"43726",
    "addr:postcode":"98022",
    "addr:street":"284Th Ave Se",
    "iso:country":"US",
    "sg:address":"43726 284th Ave SE",
    "sg:city":"Enumclaw",
    "sg:classifiers":[
        {
            "category":"Home & Garden",
            "subcategory":"Home Furnishings",
            "type":"Retail Goods"
        }
    ],
    "sg:phone":"+1 360 825 2323",
    "sg:postcode":"98022",
    "sg:province":"WA",
    "wof:name":"Opland Window Coverings",
    "wof:placetype":"venue"
},
  "geometry": {"coordinates":[-121.96319,47.209002],"type":"Point"}
}