{
  "type": "Feature",
  "properties": {
    "addr:full":"6403 N Perry St Spokane WA 99217",
    "addr:housenumber":"6403",
    "addr:postcode":"99217",
    "addr:street":"N Perry St",
    "iso:country":"US",
    "sg:address":"6403 N Perry St",
    "sg:city":"Spokane",
    "sg:classifiers":[
        {
            "category":"Autos & Motor Vehicles",
            "subcategory":"Automobile Sales",
            "type":"Retail Goods"
        }
    ],
    "sg:phone":"+1 509 483 9062",
    "sg:postcode":"99217",
    "sg:province":"WA",
    "sg:tags":[
        "wrecker"
    ],
    "sg:website":"www.inoutbackparts.com",
    "wof:name":"Outback Parts",
    "wof:placetype":"venue"
},
  "geometry": {"coordinates":[-117.39009299999999,47.716808],"type":"Point"}
}