{
  "type": "Feature",
  "properties": {
    "addr:full":"5757 Capitol Blvd S Tumwater WA 98501",
    "addr:housenumber":"5757",
    "addr:postcode":"98501",
    "addr:street":"Capitol Blvd S Tumwater",
    "iso:country":"US",
    "sg:address":"5757 Capitol Blvd S",
    "sg:city":"Tumwater",
    "sg:classifiers":[
        {
            "category":"Health Services",
            "subcategory":"Chiropractor",
            "type":"Services"
        }
    ],
    "sg:phone":"+1 360 357 5222",
    "sg:postcode":"98501",
    "sg:province":"WA",
    "wof:name":"First Choice Chiropractic",
    "wof:placetype":"venue"
},
  "geometry": {"coordinates":[-122.907641,46.996834],"type":"Point"}
}