{
  "type": "Feature",
  "properties": {
    "addr:full":"1221 SW 174th Pl Seattle WA 98166",
    "addr:housenumber":"1221",
    "addr:postcode":"98166",
    "addr:street":"Sw 174Th Pl",
    "iso:country":"US",
    "sg:address":"1221 SW 174th Pl",
    "sg:city":"Seattle",
    "sg:classifiers":[
        {
            "category":"Professional",
            "type":"Services"
        }
    ],
    "sg:phone":"+1 206 241 8802",
    "sg:postcode":"98166",
    "sg:province":"WA",
    "wof:name":"Tails of City Inc",
    "wof:placetype":"venue"
},
  "geometry": {"coordinates":[-122.34890300000001,47.44868],"type":"Point"}
}