{
  "type": "Feature",
  "properties": {
    "addr:full":"1147 Mox Chehalis Rd Mc Cleary WA 98557",
    "addr:housenumber":"1147",
    "addr:postcode":"98557",
    "addr:street":"Mox Chehalis Rd",
    "iso:country":"US",
    "sg:address":"1147 Mox Chehalis Rd",
    "sg:city":"Mc Cleary",
    "sg:classifiers":[
        {
            "category":"Building & Trades",
            "subcategory":"Landscaping Services",
            "type":"Services"
        }
    ],
    "sg:phone":"+1 360 495 7836",
    "sg:postcode":"98557",
    "sg:province":"WA",
    "wof:name":"McNealley Lawn Maintenance",
    "wof:placetype":"venue"
},
  "geometry": {"coordinates":[-123.32028200000001,46.989556],"type":"Point"}
}