{
  "type": "Feature",
  "properties": {
    "addr:full":"909 3rd St Anacortes WA 98221",
    "addr:housenumber":"909",
    "addr:postcode":"98221",
    "addr:street":"3Rd St",
    "iso:country":"US",
    "sg:address":"909 3rd St",
    "sg:city":"Anacortes",
    "sg:classifiers":[
        {
            "category":"Manufacturing",
            "subcategory":"Printing",
            "type":"Manufacturing & Wholesale Goods"
        },
        {
            "category":"Wholesale",
            "subcategory":"Books, Periodicals, & Newspapers",
            "type":"Manufacturing & Wholesale Goods"
        }
    ],
    "sg:phone":"+1 360 588 1343",
    "sg:postcode":"98221",
    "sg:province":"WA",
    "sg:tags":[
        "publisher",
        "magazines-distributors",
        "book"
    ],
    "sg:website":"http://www.lenswork.com",
    "wof:name":"Lenswork Publishing",
    "wof:placetype":"venue"
},
  "geometry": {"coordinates":[-122.611058,48.519902],"type":"Point"}
}