{
  "type": "Feature",
  "properties": {
    "addr:full":"11335 Bartlett Ave NE Seattle WA 98125",
    "addr:housenumber":"11335",
    "addr:postcode":"98125",
    "addr:street":"Bartlett Ave Ne",
    "iso:country":"US",
    "sg:address":"11335 Bartlett Ave NE",
    "sg:city":"Seattle",
    "sg:classifiers":[
        {
            "category":"Building & Trades",
            "subcategory":"Landscaping Services",
            "type":"Services"
        }
    ],
    "sg:phone":"+1 206 367 3167",
    "sg:postcode":"98125",
    "sg:province":"WA",
    "wof:name":"Dimitris A Angelou",
    "wof:placetype":"venue"
},
  "geometry": {"coordinates":[-122.283145,47.711817],"type":"Point"}
}