{
  "type": "Feature",
  "properties": {
    "addr:full":"1409 NE 45th St Seattle WA 98105",
    "addr:housenumber":"1409",
    "addr:postcode":"98105",
    "addr:street":"Ne 45Th St",
    "iso:country":"US",
    "sg:address":"1409 NE 45th St",
    "sg:city":"Seattle",
    "sg:classifiers":[
        {
            "category":"Shopping",
            "subcategory":"Clothing, Apparel, & Fashions",
            "type":"Retail Goods"
        }
    ],
    "sg:phone":"+1 206 547 8325",
    "sg:postcode":"98105",
    "sg:province":"WA",
    "sg:tags":[
        "sport"
    ],
    "wof:name":"Tequila Club Sweats",
    "wof:placetype":"venue"
},
  "geometry": {"coordinates":[-122.31204700000001,47.661187],"type":"Point"}
}