{
  "type": "Feature",
  "properties": {
    "addr:full":"1808 S Ione St Kennewick WA 99337",
    "addr:housenumber":"1808",
    "addr:postcode":"99337",
    "addr:street":"S Ione St",
    "iso:country":"US",
    "sg:address":"1808 S Ione St",
    "sg:city":"Kennewick",
    "sg:classifiers":[
        {
            "category":"Professional",
            "subcategory":"Management & Consulting",
            "type":"Services"
        }
    ],
    "sg:phone":"+1 509 586 8847",
    "sg:postcode":"99337",
    "sg:province":"WA",
    "sg:tags":[
        "consultant"
    ],
    "wof:name":"Young, S & Associates General Contractor",
    "wof:placetype":"venue"
},
  "geometry": {"coordinates":[-119.13014800000001,46.192374],"type":"Point"}
}