{
  "type": "Feature",
  "properties": {
    "iso:country":"US",
    "sg:address":"130 E Union Ridge Rd",
    "sg:city":"Union",
    "sg:classifiers":[
        {
            "category":"Building & Trades",
            "subcategory":"Construction",
            "type":"Services"
        }
    ],
    "sg:phone":"+1 360 898 2255",
    "sg:postcode":"98592",
    "sg:province":"WA",
    "sg:tags":[
        "excavating",
        "contractor"
    ],
    "wof:name":"Arrow Excavating",
    "wof:placetype":"venue"
},
  "geometry": {"coordinates":[-123.09518300000001,47.343672],"type":"Point"}
}