{
  "type": "Feature",
  "properties": {
    "addr:full":"4200 Arnie Rd Blaine WA 98230",
    "addr:housenumber":"4200",
    "addr:postcode":"98230",
    "addr:street":"Arnie Rd",
    "iso:country":"US",
    "sg:address":"4200 Arnie Rd",
    "sg:city":"Blaine",
    "sg:classifiers":[
        {
            "category":"Building & Trades",
            "subcategory":"Landscaping Services",
            "type":"Services"
        }
    ],
    "sg:phone":"+1 360 371 3191",
    "sg:postcode":"98230",
    "sg:province":"WA",
    "sg:tags":[
        "landscape",
        "contractor"
    ],
    "wof:name":"D G Lobdell",
    "wof:placetype":"venue"
},
  "geometry": {"coordinates":[-122.70997300000001,48.921143],"type":"Point"}
}