{
  "type": "Feature",
  "properties": {
    "addr:full":"29455 10th Ave SW Federal Way WA 98023",
    "addr:housenumber":"29455",
    "addr:postcode":"98023",
    "addr:street":"10Th Ave Sw Federal Way",
    "iso:country":"US",
    "sg:address":"29455 10th Ave SW",
    "sg:city":"Federal Way",
    "sg:classifiers":[
        {
            "category":"Building & Trades",
            "subcategory":"Construction",
            "type":"Services"
        }
    ],
    "sg:phone":"+1 253 941 2318",
    "sg:postcode":"98023",
    "sg:province":"WA",
    "sg:tags":[
        "house"
    ],
    "wof:name":"Spencer Construction Co I",
    "wof:placetype":"venue"
},
  "geometry": {"coordinates":[-122.347859,47.337059],"type":"Point"}
}