{
  "type": "Feature",
  "properties": {
    "addr:full":"12901 52nd Dr SE Everett WA 98208",
    "addr:housenumber":"12901",
    "addr:postcode":"98208",
    "addr:street":"52Nd Dr Se",
    "iso:country":"US",
    "sg:address":"12901 52nd Dr SE",
    "sg:city":"Everett",
    "sg:classifiers":[
        {
            "category":"Education",
            "subcategory":"Special Training",
            "type":"Public Place"
        }
    ],
    "sg:phone":"+1 800 755 7304",
    "sg:postcode":"98208",
    "sg:province":"WA",
    "sg:tags":[
        "test",
        "preparation",
        "educational",
        "tutoring"
    ],
    "wof:name":"Universal Tutors",
    "wof:placetype":"venue"
},
  "geometry": {"coordinates":[-122.160759,47.880459],"type":"Point"}
}