{
  "type": "Feature",
  "properties": {
    "addr:full":"2117 Conger Ave NW Olympia WA 98502",
    "addr:housenumber":"2117",
    "addr:postcode":"olympia wa 98502",
    "addr:street":"Conger Ave Nw",
    "iso:country":"US",
    "sg:address":"2117 Conger Ave NW",
    "sg:city":"Olympia",
    "sg:classifiers":[
        {
            "category":"Manufacturing",
            "subcategory":"Tools & Machinery",
            "type":"Manufacturing & Wholesale Goods"
        }
    ],
    "sg:phone":"+1 360 943 1305",
    "sg:postcode":"98502",
    "sg:province":"WA",
    "sg:tags":[
        "security"
    ],
    "wof:name":"Nsnwnet",
    "wof:placetype":"venue"
},
  "geometry": {"coordinates":[-122.93147399999999,47.051515],"type":"Point"}
}