{
  "type": "Feature",
  "properties": {
    "addr:full":"3766 NW Munson St Silverdale WA 98383",
    "addr:housenumber":"3766",
    "addr:postcode":"98383",
    "addr:street":"Nw Munson St",
    "iso:country":"US",
    "sg:address":"3766 NW Munson St",
    "sg:city":"Silverdale",
    "sg:classifiers":[
        {
            "category":"Arts & Performance",
            "subcategory":"Theater",
            "type":"Entertainment"
        }
    ],
    "sg:phone":"+1 360 698 3938",
    "sg:postcode":"98383",
    "sg:province":"WA",
    "sg:tags":[
        "musician"
    ],
    "wof:name":"Jane Rhodes",
    "wof:placetype":"venue"
},
  "geometry": {"coordinates":[-122.69985800000001,47.646844],"type":"Point"}
}