{
  "type": "Feature",
  "properties": {
    "iso:country":"US",
    "sg:address":"12804 E 23rd Ave",
    "sg:city":"Spokane",
    "sg:classifiers":[
        {
            "category":"Real Estate",
            "subcategory":"Real Estate Agent",
            "type":"Services"
        }
    ],
    "sg:phone":"+1 509 927 7849",
    "sg:postcode":"99216",
    "sg:province":"WA",
    "wof:name":"Teri Fisher Appraisal Service",
    "wof:placetype":"venue"
},
  "geometry": {"coordinates":[-117.23324100000001,47.63571],"type":"Point"}
}