{
  "type": "Feature",
  "properties": {
    "iso:country":"US",
    "sg:address":"15805 70th Ave NE",
    "sg:city":"Kenmore",
    "sg:classifiers":[
        {
            "category":"Building & Trades",
            "subcategory":"Landscaping Services",
            "type":"Services"
        }
    ],
    "sg:phone":"+1 425 806 3921",
    "sg:postcode":"98028",
    "sg:province":"WA",
    "sg:tags":[
        "landscape"
    ],
    "wof:name":"Berrio Landscape",
    "wof:placetype":"venue"
},
  "geometry": {"coordinates":[-122.24793699999999,47.743532],"type":"Point"}
}