{
  "type": "Feature",
  "properties": {
    "addr:full":"9741 Woodlawn Ave N Apt A Seattle WA 98103",
    "addr:housenumber":"9741",
    "addr:postcode":"98103",
    "addr:street":"Woodlawn Ave N Apt A",
    "iso:country":"US",
    "sg:address":"9741 Woodlawn Ave N Apt A",
    "sg:city":"Seattle",
    "sg:classifiers":[
        {
            "category":"Wholesale",
            "subcategory":"Construction Materials",
            "type":"Manufacturing & Wholesale Goods"
        },
        {
            "category":"Home & Garden",
            "subcategory":"Building Materials",
            "type":"Retail Goods"
        }
    ],
    "sg:phone":"+1 206 523 7333",
    "sg:postcode":"98103",
    "sg:province":"WA",
    "sg:tags":[
        "windows-wholesale",
        "window",
        "manufacturer"
    ],
    "wof:name":"Washington Window",
    "wof:placetype":"venue"
},
  "geometry": {"coordinates":[-122.33877,47.700376],"type":"Point"}
}