{
  "type": "Feature",
  "properties": {
    "addr:full":"500 108th Ave NE Ste 800 Bellevue WA 98004",
    "addr:housenumber":"500",
    "addr:postcode":"98004",
    "addr:street":"108Th Ave Ne Ste 800",
    "iso:country":"US",
    "sg:address":"500 108th Ave NE Ste 800",
    "sg:city":"Bellevue",
    "sg:classifiers":[
        {
            "category":"Banks & Credit Unions",
            "subcategory":"Financial Services",
            "type":"Services"
        }
    ],
    "sg:phone":"+1 425 452 8500",
    "sg:postcode":"98004",
    "sg:province":"WA",
    "sg:tags":[
        "broker",
        "mortgage"
    ],
    "wof:name":"Robertson Capital Corporation",
    "wof:placetype":"venue"
},
  "geometry": {"coordinates":[-122.195999,47.6147],"type":"Point"}
}