{
  "type": "Feature",
  "properties": {
    "addr:full":"2442 NW Market St Seattle WA 98107",
    "addr:housenumber":"2442",
    "addr:postcode":"98107",
    "addr:street":"Nw Market St",
    "iso:country":"US",
    "sg:address":"2442 NW Market St",
    "sg:city":"Seattle",
    "sg:classifiers":[
        {
            "category":"Professional",
            "subcategory":"Business Services",
            "type":"Services"
        }
    ],
    "sg:phone":"+1 206 789 2442",
    "sg:postcode":"98107",
    "sg:province":"WA",
    "sg:tags":[
        "packaging",
        "recycling",
        "center"
    ],
    "sg:website":"www.ballardmailbox.com",
    "wof:name":"Ballard Mailbox & Shipping Center",
    "wof:placetype":"venue"
},
  "geometry": {"coordinates":[-122.389416,47.668889],"type":"Point"}
}