{
  "type": "Feature",
  "properties": {
    "addr:full":"4109 103rd Ave SE Everett WA 98205",
    "addr:housenumber":"4109",
    "addr:postcode":"98205",
    "addr:street":"103Rd Ave Se",
    "iso:country":"US",
    "sg:address":"4109 103rd Ave SE",
    "sg:city":"Everett",
    "sg:classifiers":[
        {
            "category":"Organizations",
            "subcategory":"Religious Organization",
            "type":"Services"
        }
    ],
    "sg:phone":"+1 425 334 9422",
    "sg:postcode":"98205",
    "sg:province":"WA",
    "sg:tags":[
        "school"
    ],
    "wof:name":"Kings Way Academy",
    "wof:placetype":"venue"
},
  "geometry": {"coordinates":[-122.09320700000001,47.959419],"type":"Point"}
}