{
  "type": "Feature",
  "properties": {
    "addr:full":"732 6th St Clarkston WA 99403",
    "addr:housenumber":"732",
    "addr:postcode":"99403",
    "addr:street":"6Th St",
    "iso:country":"US",
    "sg:address":"732 6th St",
    "sg:city":"Clarkston",
    "sg:classifiers":[
        {
            "category":"Health Services",
            "subcategory":"Clinic",
            "type":"Services"
        }
    ],
    "sg:phone":"+1 509 751 9140",
    "sg:postcode":"99403",
    "sg:province":"WA",
    "sg:tags":[
        "merchandise"
    ],
    "wof:name":"Blue Mountain Hearing Services",
    "wof:placetype":"venue"
},
  "geometry": {"coordinates":[-117.04560600000001,46.415713],"type":"Point"}
}