{
  "type": "Feature",
  "properties": {
    "addr:full":"2621 N Harbor Loop Dr Bellingham WA 98225",
    "addr:housenumber":"2621",
    "addr:postcode":"98225",
    "addr:street":"N Harbor Loop Dr",
    "iso:country":"US",
    "sg:address":"2621 N Harbor Loop Dr",
    "sg:city":"Bellingham",
    "sg:classifiers":[
        {
            "category":"Autos & Motor Vehicles",
            "subcategory":"Boat Sales",
            "type":"Retail Goods"
        }
    ],
    "sg:phone":"+1 360 647 2628",
    "sg:postcode":"98225",
    "sg:province":"WA",
    "sg:tags":[
        "dealer",
        "sales"
    ],
    "wof:name":"Guyer Boatworks",
    "wof:placetype":"venue"
},
  "geometry": {"coordinates":[-122.50012,48.755298],"type":"Point"}
}