{
  "type": "Feature",
  "properties": {
    "addr:full":"5133 Lakeside Dr Langley WA 98260",
    "addr:housenumber":"5133",
    "addr:postcode":"98260",
    "addr:street":"Lakeside Dr",
    "iso:country":"US",
    "sg:address":"5133 Lakeside Dr",
    "sg:city":"Langley",
    "sg:classifiers":[
        {
            "category":"Wholesale",
            "subcategory":"Durable Goods & Equipment",
            "type":"Manufacturing & Wholesale Goods"
        }
    ],
    "sg:phone":"+1 360 659 9575",
    "sg:postcode":"98260",
    "sg:province":"WA",
    "wof:name":"Artworks Ink",
    "wof:placetype":"venue"
},
  "geometry": {"coordinates":[-122.474206,48.037794],"type":"Point"}
}