{
  "type": "Feature",
  "properties": {
    "addr:full":"34918 46th Ave S Roy WA 98580",
    "addr:housenumber":"34918",
    "addr:postcode":"98580",
    "addr:street":"46Th Ave S Roy",
    "iso:country":"US",
    "sg:address":"34918 46th Ave S",
    "sg:city":"Roy",
    "sg:classifiers":[
        {
            "category":"Wholesale",
            "subcategory":"Machinery & Supplies",
            "type":"Manufacturing & Wholesale Goods"
        }
    ],
    "sg:phone":"+1 360 458 2860",
    "sg:postcode":"98580",
    "sg:province":"WA",
    "sg:tags":[
        "logging"
    ],
    "wof:name":"J & T Farm Supplies",
    "wof:placetype":"venue"
},
  "geometry": {"coordinates":[-122.49211099999999,46.939329],"type":"Point"}
}