{
  "type": "Feature",
  "properties": {
    "addr:full":"4733 Ballard Ave NW Seattle WA 98107",
    "addr:housenumber":"4733",
    "addr:postcode":"98107",
    "addr:street":"Ballard Ave Nw",
    "iso:country":"US",
    "sg:address":"4733 Ballard Ave NW",
    "sg:city":"Seattle",
    "sg:classifiers":[
        {
            "category":"Building & Trades",
            "subcategory":"Construction",
            "type":"Services"
        }
    ],
    "sg:phone":"+1 206 783 5421",
    "sg:postcode":"98107",
    "sg:province":"WA",
    "sg:tags":[
        "general",
        "contractor"
    ],
    "wof:name":"Ed Smith Construction",
    "wof:placetype":"venue"
},
  "geometry": {"coordinates":[-122.37991,47.663328],"type":"Point"}
}