{
  "type": "Feature",
  "properties": {
    "addr:full":"2316 Maple Ln Steilacoom WA 98388",
    "addr:housenumber":"2316",
    "addr:postcode":"98388",
    "addr:street":"Maple Ln",
    "iso:country":"US",
    "sg:address":"2316 Maple Ln",
    "sg:city":"Steilacoom",
    "sg:classifiers":[
        {
            "category":"Social Services",
            "type":"Services"
        }
    ],
    "sg:phone":"+1 253 588 2591",
    "sg:postcode":"98388",
    "sg:province":"WA",
    "wof:name":"Samoan Senior Citizens Assn",
    "wof:placetype":"venue"
},
  "geometry": {"coordinates":[-122.59203100000001,47.162789],"type":"Point"}
}