{
  "type": "Feature",
  "properties": {
    "addr:full":"15511 Bandix Rd SE Olalla WA 98359",
    "addr:housenumber":"15511",
    "addr:postcode":"98359",
    "addr:street":"Bandix Rd Se Olalla",
    "iso:country":"US",
    "sg:address":"15511 Bandix Rd SE",
    "sg:city":"Olalla",
    "sg:classifiers":[
        {
            "category":"Building & Trades",
            "subcategory":"Cleaning & Sanitation",
            "type":"Services"
        }
    ],
    "sg:phone":"+1 253 857 7434",
    "sg:postcode":"98359",
    "sg:province":"WA",
    "sg:tags":[
        "maintenance"
    ],
    "wof:name":"Leann Black Cleaning",
    "wof:placetype":"venue"
},
  "geometry": {"coordinates":[-122.610439,47.407687],"type":"Point"}
}