{
  "type": "Feature",
  "properties": {
    "addr:full":"1805 W 9th Ave Spokane WA 99204",
    "addr:housenumber":"1805",
    "addr:postcode":"99204",
    "addr:street":"W 9Th Ave",
    "iso:country":"US",
    "sg:address":"1805 W 9th Ave",
    "sg:city":"Spokane",
    "sg:classifiers":[
        {
            "category":"Social Services",
            "type":"Services"
        }
    ],
    "sg:phone":"+1 509 747 9222",
    "sg:postcode":"99204",
    "sg:province":"WA",
    "wof:name":"Miryam S House",
    "wof:placetype":"venue"
},
  "geometry": {"coordinates":[-117.44014799999999,47.647307],"type":"Point"}
}