{
  "type": "Feature",
  "properties": {
    "addr:full":"3640 169th Ave NE Bellevue WA 98008",
    "addr:housenumber":"3640",
    "addr:postcode":"98008",
    "addr:street":"169Th Ave Ne",
    "iso:country":"US",
    "sg:address":"3640 169th Ave NE",
    "sg:city":"Bellevue",
    "sg:classifiers":[
        {
            "category":"Professional",
            "subcategory":"Accounting & Tax Preparation",
            "type":"Services"
        }
    ],
    "sg:phone":"+1 206 953 5159",
    "sg:postcode":"98008",
    "sg:province":"WA",
    "wof:name":"Many Happy Returns Tax Service",
    "wof:placetype":"venue"
},
  "geometry": {"coordinates":[-122.11423600000001,47.642625],"type":"Point"}
}