{
  "type": "Feature",
  "properties": {
    "addr:full":"713 NE 4th Ave Camas WA 98607",
    "addr:housenumber":"713",
    "addr:postcode":"98607",
    "addr:street":"Ne 4Th Ave",
    "iso:country":"US",
    "sg:address":"713 NE 4th Ave",
    "sg:city":"Camas",
    "sg:classifiers":[
        {
            "category":"Real Estate",
            "subcategory":"Real Estate Services",
            "type":"Services"
        }
    ],
    "sg:phone":"+1 360 834 7565",
    "sg:postcode":"98607",
    "sg:province":"WA",
    "wof:name":"Realtyworldnw Com",
    "wof:placetype":"venue"
},
  "geometry": {"coordinates":[-122.402,45.587399],"type":"Point"}
}