{
  "type": "Feature",
  "properties": {
    "addr:full":"2815 Pine Cone Dr NW Issaquah WA 98027",
    "addr:housenumber":"2815",
    "addr:postcode":"98027",
    "addr:street":"Pine Cone Dr Nw",
    "iso:country":"US",
    "sg:address":"2815 Pine Cone Dr NW",
    "sg:city":"Issaquah",
    "sg:classifiers":[
        {
            "category":"Manufacturing",
            "subcategory":"Printing",
            "type":"Manufacturing & Wholesale Goods"
        }
    ],
    "sg:phone":"+1 425 392 3514",
    "sg:postcode":"98027",
    "sg:province":"WA",
    "sg:tags":[
        "publisher",
        "book"
    ],
    "sg:website":"www.sellmorenow.com",
    "wof:name":"Denali Group Inc",
    "wof:placetype":"venue"
},
  "geometry": {"coordinates":[-122.078069,47.54987],"type":"Point"}
}