{
  "type": "Feature",
  "properties": {
    "addr:full":"122 N West Blvd Aberdeen WA 98520",
    "addr:housenumber":"122",
    "addr:postcode":"98520",
    "addr:street":"N West Blvd",
    "iso:country":"US",
    "sg:address":"122 N West Blvd",
    "sg:city":"Aberdeen",
    "sg:classifiers":[
        {
            "category":"Building & Trades",
            "subcategory":"Construction",
            "type":"Services"
        }
    ],
    "sg:phone":"+1 360 532 8248",
    "sg:postcode":"98520",
    "sg:province":"WA",
    "sg:tags":[
        "roofing",
        "industrial",
        "contractors-commercial",
        "contractor"
    ],
    "wof:name":"Nc Construction",
    "wof:placetype":"venue"
},
  "geometry": {"coordinates":[-123.789766,46.968984],"type":"Point"}
}