{
  "type": "Feature",
  "properties": {
    "addr:full":"7453 Newcastle Golf Club Rd Renton WA 98059",
    "addr:housenumber":"7453",
    "addr:postcode":"98059",
    "addr:street":"Newcastle Golf Club Rd",
    "iso:country":"US",
    "sg:address":"7453 Newcastle Golf Club Rd",
    "sg:city":"Renton",
    "sg:classifiers":[
        {
            "category":"Personal",
            "type":"Services"
        }
    ],
    "sg:phone":"+1 425 572 0049",
    "sg:postcode":"98059",
    "sg:province":"WA",
    "wof:name":"Harmony In Motion",
    "wof:placetype":"venue"
},
  "geometry": {"coordinates":[-122.163578,47.535013],"type":"Point"}
}