{
  "type": "Feature",
  "properties": {
    "addr:full":"401 S Main St Colfax WA 99111",
    "addr:housenumber":"401",
    "addr:postcode":"99111",
    "addr:street":"S Main St",
    "iso:country":"US",
    "sg:address":"401 S Main St",
    "sg:city":"Colfax",
    "sg:classifiers":[
        {
            "category":"Real Estate",
            "subcategory":"Real Estate Agent",
            "type":"Services"
        }
    ],
    "sg:phone":"+1 509 397 4434",
    "sg:postcode":"99111",
    "sg:province":"WA",
    "wof:name":"Kincaid Real Estate",
    "wof:placetype":"venue"
},
  "geometry": {"coordinates":[-117.36483,46.87799],"type":"Point"}
}