{
  "type": "Feature",
  "properties": {
    "addr:full":"22833 Bothell Everett Hwy Bothell WA 98021",
    "addr:housenumber":"22833",
    "addr:postcode":"98021",
    "addr:street":"Bothell Everett Hwy",
    "iso:country":"US",
    "sg:address":"22833 Bothell Everett Hwy",
    "sg:city":"Bothell",
    "sg:classifiers":[
        {
            "category":"Food & Beverages",
            "subcategory":"Groceries & Convenience Stores",
            "type":"Retail Goods"
        }
    ],
    "sg:phone":"+1 425 485 1991",
    "sg:postcode":"98021",
    "sg:province":"WA",
    "wof:name":"Q F C",
    "wof:placetype":"venue"
},
  "geometry": {"coordinates":[-122.216888,47.791165],"type":"Point"}
}