{
  "type": "Feature",
  "properties": {
    "iso:country":"US",
    "sg:address":"1901 E Lincoln Ave",
    "sg:city":"Sunnyside",
    "sg:classifiers":[
        {
            "category":"Professional",
            "subcategory":"Engineering",
            "type":"Services"
        }
    ],
    "sg:phone":"+1 509 837 4454",
    "sg:postcode":"98944",
    "sg:province":"WA",
    "sg:tags":[
        "engineer"
    ],
    "wof:name":"Anderson Engineering",
    "wof:placetype":"venue"
},
  "geometry": {"coordinates":[-119.992096,46.316738],"type":"Point"}
}