{
  "type": "Feature",
  "properties": {
    "addr:full":"17306 Ironwood St Arlington WA 98223",
    "addr:housenumber":"17306",
    "addr:postcode":"98223",
    "addr:street":"Ironwood St",
    "iso:country":"US",
    "sg:address":"17306 Ironwood St",
    "sg:city":"Arlington",
    "sg:classifiers":[
        {
            "category":"Restaurant",
            "type":"Food & Drink"
        }
    ],
    "sg:phone":"+1 206 622 8199",
    "sg:postcode":"98223",
    "sg:province":"WA",
    "sg:tags":[
        "caterer"
    ],
    "sg:website":"www.rent-a-chef-catering.com",
    "wof:name":"Rent-A-Chef Catering",
    "wof:placetype":"venue"
},
  "geometry": {"coordinates":[-122.128715,48.152896],"type":"Point"}
}