{
  "type": "Feature",
  "properties": {
    "addr:full":"921 S 16th St Sunnyside WA 98944",
    "addr:housenumber":"921",
    "addr:postcode":"98944",
    "addr:street":"S 16Th St",
    "iso:country":"US",
    "sg:address":"921 S 16th St",
    "sg:city":"Sunnyside",
    "sg:classifiers":[
        {
            "category":"Restaurant",
            "type":"Food & Drink"
        }
    ],
    "sg:phone":"+1 509 839 0262",
    "sg:postcode":"98944",
    "sg:province":"WA",
    "sg:tags":[
        "eating"
    ],
    "wof:name":"Ice Cream Depot",
    "wof:placetype":"venue"
},
  "geometry": {"coordinates":[-119.999365,46.318809],"type":"Point"}
}