{
  "type": "Feature",
  "properties": {
    "addr:full":"7 Stares Ln Sequim WA 98382",
    "addr:housenumber":"7",
    "addr:postcode":"98382",
    "addr:street":"Stares Ln",
    "iso:country":"US",
    "sg:address":"7 Stares Ln",
    "sg:city":"Sequim",
    "sg:classifiers":[
        {
            "category":"Shopping",
            "type":"Retail Goods"
        }
    ],
    "sg:phone":"+1 360 681 6728",
    "sg:postcode":"98382",
    "sg:province":"WA",
    "sg:tags":[
        "art",
        "gallery",
        "dealer"
    ],
    "wof:name":"Northwest Native Expressions",
    "wof:placetype":"venue"
},
  "geometry": {"coordinates":[-123.084537,48.101837],"type":"Point"}
}