{
  "type": "Feature",
  "properties": {
    "iso:country":"US",
    "sg:address":"1804 164th St S",
    "sg:city":"Spanaway",
    "sg:classifiers":[
        {
            "category":"Building & Trades",
            "subcategory":"Construction",
            "type":"Services"
        }
    ],
    "sg:phone":"+1 253 224 8873",
    "sg:postcode":"98387",
    "sg:province":"WA",
    "sg:tags":[
        "general",
        "contractor"
    ],
    "wof:name":"D L Coffey General Contractor",
    "wof:placetype":"venue"
},
  "geometry": {"coordinates":[-122.463443,47.108449],"type":"Point"}
}