{
  "type": "Feature",
  "properties": {
    "addr:full":"20622 95th Ave S Kent WA 98031",
    "addr:housenumber":"20622",
    "addr:postcode":"98031",
    "addr:street":"95Th Ave S",
    "iso:country":"US",
    "sg:address":"20622 95th Ave S",
    "sg:city":"Kent",
    "sg:classifiers":[
        {
            "category":"Wholesale",
            "subcategory":"Medical Equipment & Supplies",
            "type":"Manufacturing & Wholesale Goods"
        }
    ],
    "sg:phone":"+1 253 859 2450",
    "sg:postcode":"98031",
    "sg:province":"WA",
    "wof:name":"Cardiac Sonography Services",
    "wof:placetype":"venue"
},
  "geometry": {"coordinates":[-122.214139,47.418001],"type":"Point"}
}