{
  "type": "Feature",
  "properties": {
    "addr:full":"553 John St Seattle WA 98109",
    "addr:housenumber":"553",
    "addr:postcode":"98109",
    "addr:street":"John St",
    "iso:country":"US",
    "sg:address":"553 John St",
    "sg:city":"Seattle",
    "sg:classifiers":[
        {
            "category":"Organizations",
            "subcategory":"Labor Organization",
            "type":"Services"
        }
    ],
    "sg:phone":"+1 206 441 4860",
    "sg:postcode":"98109",
    "sg:province":"WA",
    "wof:name":"Driver Sales & Whse Local 117",
    "wof:placetype":"venue"
},
  "geometry": {"coordinates":[-122.345045,47.619652],"type":"Point"}
}