{
  "type": "Feature",
  "properties": {
    "iso:country":"US",
    "sg:address":"1420 N 5th St",
    "sg:city":"Tacoma",
    "sg:classifiers":[
        {
            "category":"Wholesale",
            "subcategory":"Groceries",
            "type":"Manufacturing & Wholesale Goods"
        }
    ],
    "sg:phone":"+1 253 572 3926",
    "sg:postcode":"98403",
    "sg:province":"WA",
    "sg:tags":[
        "general"
    ],
    "wof:name":"Pacific Rim Wholesalers",
    "wof:placetype":"venue"
},
  "geometry": {"coordinates":[-122.459509,47.258461],"type":"Point"}
}