{
  "type": "Feature",
  "properties": {
    "addr:full":"2010 Park St Enumclaw WA 98022",
    "addr:housenumber":"2010",
    "addr:postcode":"98022",
    "addr:street":"Park St",
    "iso:country":"US",
    "sg:address":"2010 Park St",
    "sg:city":"Enumclaw",
    "sg:classifiers":[
        {
            "category":"Professional",
            "subcategory":"Lawyer & Legal Services",
            "type":"Services"
        }
    ],
    "sg:phone":"+1 360 825 1289",
    "sg:postcode":"98022",
    "sg:province":"WA",
    "sg:tags":[
        "attorney"
    ],
    "wof:name":"Gail Crawford",
    "wof:placetype":"venue"
},
  "geometry": {"coordinates":[-121.99256800000001,47.208553],"type":"Point"}
}