{
  "type": "Feature",
  "properties": {
    "addr:full":"113 75th St SW Everett WA 98203",
    "addr:housenumber":"113",
    "addr:postcode":"98203",
    "addr:street":"75Th St Sw",
    "iso:country":"US",
    "sg:address":"113 75th St SW",
    "sg:city":"Everett",
    "sg:classifiers":[
        {
            "category":"Professional",
            "type":"Services"
        }
    ],
    "sg:phone":"+1 425 290 3959",
    "sg:postcode":"98203",
    "sg:province":"WA",
    "sg:tags":[
        "art",
        "fine",
        "artist"
    ],
    "wof:name":"Hyder, Lyussy Artist",
    "wof:placetype":"venue"
},
  "geometry": {"coordinates":[-122.23548700000001,47.930359],"type":"Point"}
}