{
  "type": "Feature",
  "properties": {
    "addr:full":"3715 S Grove Rd Spokane WA 99224",
    "addr:housenumber":"3715",
    "addr:postcode":"99224",
    "addr:street":"S Grove Rd",
    "iso:country":"US",
    "sg:address":"3715 S Grove Rd",
    "sg:city":"Spokane",
    "sg:classifiers":[
        {
            "category":"Organizations",
            "subcategory":"Religious Organization",
            "type":"Services"
        }
    ],
    "sg:phone":"+1 509 838 2761",
    "sg:postcode":"99224",
    "sg:province":"WA",
    "sg:tags":[
        "church"
    ],
    "wof:name":"Upper Columbia Conference",
    "wof:placetype":"venue"
},
  "geometry": {"coordinates":[-117.50427999999999,47.621169],"type":"Point"}
}