{
  "type": "Feature",
  "properties": {
    "addr:full":"20115 NW 18th Pl Ridgefield WA 98642",
    "addr:housenumber":"20115",
    "addr:postcode":"98642",
    "addr:street":"Nw 18Th Pl",
    "iso:country":"US",
    "sg:address":"20115 NW 18th Pl",
    "sg:city":"Ridgefield",
    "sg:classifiers":[
        {
            "category":"Building & Trades",
            "subcategory":"Construction",
            "type":"Services"
        },
        {
            "category":"Farming",
            "subcategory":"Farm",
            "type":"Manufacturing & Wholesale Goods"
        },
        {
            "category":"Professional",
            "subcategory":"Art Services",
            "type":"Services"
        },
        {
            "category":"Home & Garden",
            "subcategory":"Building Materials",
            "type":"Retail Goods"
        },
        {
            "category":"Building & Trades",
            "subcategory":"Landscaping Services",
            "type":"Services"
        },
        {
            "category":"Farming",
            "subcategory":"Nursery",
            "type":"Manufacturing & Wholesale Goods"
        }
    ],
    "sg:phone":"+1 360 887 8564",
    "sg:postcode":"98642",
    "sg:province":"WA",
    "sg:tags":[
        "designer",
        "nurseries-plants",
        "wall",
        "consultant",
        "tree",
        "contractor",
        "lighting",
        "hydroseeding",
        "retaining",
        "landscape"
    ],
    "sg:website":"http://www.shippbrothers.com",
    "wof:name":"Shipp Brothers Landscape Inc",
    "wof:placetype":"venue"
},
  "geometry": {"coordinates":[-122.690005,45.766818],"type":"Point"}
}