{
  "type": "Feature",
  "properties": {
    "addr:full":"The Bravern Shopping Center 700 110th Ave NE. Ste 260 Bellevue WA 98004",
    "addr:housenumber":"700",
    "addr:postcode":"98004",
    "addr:street":"110Th Ave Ne. Ste 260",
    "iso:country":"US",
    "sg:address":"The Bravern Shopping Center 700 110th Ave NE. Ste 260",
    "sg:city":"Bellevue",
    "sg:classifiers":[
        {
            "category":"Food & Beverages",
            "subcategory":"Candy",
            "type":"Retail Goods"
        },
        {
            "category":"Bakery",
            "type":"Food & Drink"
        }
    ],
    "sg:phone":"+1 425 361 0033",
    "sg:postcode":"98004",
    "sg:province":"WA",
    "sg:tags":[
        "dessert"
    ],
    "sg:website":"www.trophycupcakes.com",
    "wof:name":"Trophy Cupcakes & Party",
    "wof:placetype":"venue"
},
  "geometry": {"coordinates":[-122.19363199999999,47.616444],"type":"Point"}
}