{
  "type": "Feature",
  "properties": {
    "addr:full":"21024 24th Ave S Seatac WA 98198",
    "addr:housenumber":"21024",
    "addr:postcode":"98198",
    "addr:street":"24Th Ave S Seatac",
    "iso:country":"US",
    "sg:address":"21024 24th Ave S",
    "sg:city":"Seatac",
    "sg:classifiers":[
        {
            "category":"Social Services",
            "subcategory":"Child Care",
            "type":"Services"
        }
    ],
    "sg:phone":"+1 206 878 6036",
    "sg:postcode":"98198",
    "sg:province":"WA",
    "sg:tags":[
        "kindergarten",
        "academic",
        "school"
    ],
    "wof:name":"Christian Faith School",
    "wof:placetype":"venue"
},
  "geometry": {"coordinates":[-122.302412,47.412376],"type":"Point"}
}