{
  "type": "Feature",
  "properties": {
    "addr:full":"3611 Ryan St SE Lacey WA 98503",
    "addr:housenumber":"3611",
    "addr:postcode":"98503",
    "addr:street":"Ryan St Se",
    "iso:country":"US",
    "sg:address":"3611 Ryan St SE",
    "sg:city":"Lacey",
    "sg:classifiers":[
        {
            "category":"Shopping",
            "subcategory":"Hobbies, Toys, & Games",
            "type":"Retail Goods"
        },
        {
            "category":"Shopping",
            "subcategory":"Crafts & Fabrics",
            "type":"Retail Goods"
        }
    ],
    "sg:phone":"+1 360 459 2940",
    "sg:postcode":"98503",
    "sg:province":"WA",
    "sg:tags":[
        "shop",
        "hobby",
        "model",
        "instruction",
        "supply"
    ],
    "wof:name":"Colophon Book Arts Supply",
    "wof:placetype":"venue"
},
  "geometry": {"coordinates":[-122.806313,47.014005],"type":"Point"}
}