{
  "type": "Feature",
  "properties": {
    "addr:full":"22028 26th Ave SE Bothell WA 98021",
    "addr:housenumber":"22028",
    "addr:postcode":"98021",
    "addr:street":"26Th Ave Se",
    "iso:country":"US",
    "sg:address":"22028 26th Ave SE",
    "sg:city":"Bothell",
    "sg:classifiers":[
        {
            "category":"Shopping",
            "subcategory":"Optical Goods",
            "type":"Retail Goods"
        }
    ],
    "sg:phone":"+1 425 483 9999",
    "sg:postcode":"98021",
    "sg:province":"WA",
    "wof:name":"Fiber Optic Technologies",
    "wof:placetype":"venue"
},
  "geometry": {"coordinates":[-122.19828099999999,47.796781],"type":"Point"}
}