{
  "type": "Feature",
  "properties": {
    "addr:full":"1557 127th Pl NE Bellevue WA 98005",
    "addr:housenumber":"1557",
    "addr:postcode":"98005",
    "addr:street":"127Th Pl Ne",
    "iso:country":"US",
    "sg:address":"1557 127th Pl NE",
    "sg:city":"Bellevue",
    "sg:classifiers":[
        {
            "category":"Autos & Motor Vehicles",
            "subcategory":"Fuel & Gas Station",
            "type":"Retail Goods"
        },
        {
            "category":"Autos & Motor Vehicles",
            "subcategory":"Auto Supplies",
            "type":"Retail Goods"
        },
        {
            "category":"Retail",
            "subcategory":"Repair Shop",
            "type":"Services"
        },
        {
            "category":"Retail",
            "subcategory":"Auto Repair",
            "type":"Services"
        }
    ],
    "sg:phone":"+1 425 450 9713",
    "sg:postcode":"98005",
    "sg:province":"WA",
    "sg:tags":[
        "exhaust",
        "transmission",
        "automotive",
        "system",
        "emission",
        "truck",
        "clutch",
        "muffler",
        "brake",
        "injection",
        "diagnostic",
        "repair-automobile",
        "tune",
        "automobile"
    ],
    "sg:website":"http://www.bellevueautorepair.com",
    "wof:name":"Ali's Bellevue Auto Repair",
    "wof:placetype":"venue"
},
  "geometry": {"coordinates":[-122.17071799999999,47.623531],"type":"Point"}
}