{
  "type": "Feature",
  "properties": {
    "addr:full":"4022 SW Orchard St Seattle WA 98136",
    "addr:housenumber":"4022",
    "addr:postcode":"98136",
    "addr:street":"Sw Orchard St",
    "iso:country":"US",
    "sg:address":"4022 SW Orchard St",
    "sg:city":"Seattle",
    "sg:classifiers":[
        {
            "category":"Arts & Performance",
            "subcategory":"Theater",
            "type":"Entertainment"
        }
    ],
    "sg:phone":"+1 206 923 1598",
    "sg:postcode":"98136",
    "sg:province":"WA",
    "sg:tags":[
        "group"
    ],
    "wof:name":"Lamar Lofton",
    "wof:placetype":"venue"
},
  "geometry": {"coordinates":[-122.383956,47.538939],"type":"Point"}
}