{
  "type": "Feature",
  "properties": {
    "iso:country":"US",
    "sg:address":"33501 11th Pl SW",
    "sg:city":"Federal Way",
    "sg:classifiers":[
        {
            "category":"Professional",
            "subcategory":"Employment Agencies",
            "type":"Services"
        }
    ],
    "sg:phone":"+1 253 661 1259",
    "sg:postcode":"98023",
    "sg:province":"WA",
    "sg:tags":[
        "help",
        "supply"
    ],
    "wof:name":"Aviation Services Interna",
    "wof:placetype":"venue"
},
  "geometry": {"coordinates":[-122.34876800000001,47.300883],"type":"Point"}
}