{
  "type": "Feature",
  "properties": {
    "addr:full":"135 Union St Walla Walla WA 99362",
    "addr:housenumber":"135",
    "addr:postcode":"99362",
    "addr:street":"Union St",
    "iso:country":"US",
    "sg:address":"135 Union St",
    "sg:city":"Walla Walla",
    "sg:classifiers":[
        {
            "category":"Home & Garden",
            "subcategory":"Furniture",
            "type":"Retail Goods"
        }
    ],
    "sg:phone":"+1 509 529 6850",
    "sg:postcode":"99362",
    "sg:province":"WA",
    "sg:tags":[
        "cabinet"
    ],
    "wof:name":"Woodworking Innovations",
    "wof:placetype":"venue"
},
  "geometry": {"coordinates":[-118.299592,46.070699],"type":"Point"}
}