{
  "type": "Feature",
  "properties": {
    "addr:full":"501 8th St Lynden WA 98264",
    "addr:housenumber":"501",
    "addr:postcode":"98264",
    "addr:street":"8Th St",
    "iso:country":"US",
    "sg:address":"501 8th St",
    "sg:city":"Lynden",
    "sg:classifiers":[
        {
            "category":"Building & Trades",
            "subcategory":"Cleaning & Sanitation",
            "type":"Services"
        }
    ],
    "sg:phone":"+1 360 354 6848",
    "sg:postcode":"98264",
    "sg:province":"WA",
    "sg:tags":[
        "maintenance",
        "cleaners-interior"
    ],
    "wof:name":"Marthas Cleaning Service",
    "wof:placetype":"venue"
},
  "geometry": {"coordinates":[-122.459473,48.945431],"type":"Point"}
}