{
  "type": "Feature",
  "properties": {
    "addr:full":"7801 NE St Johns Rd Vancouver WA 98665",
    "addr:housenumber":"7801",
    "addr:postcode":"98665",
    "addr:street":"Ne St Johns Rd",
    "iso:country":"US",
    "sg:address":"7801 NE St Johns Rd",
    "sg:city":"Vancouver",
    "sg:classifiers":[
        {
            "category":"Autos & Motor Vehicles",
            "subcategory":"Fuel & Gas Station",
            "type":"Retail Goods"
        }
    ],
    "sg:phone":"+1 360 571 8647",
    "sg:postcode":"98665",
    "sg:province":"WA",
    "sg:tags":[
        "station",
        "gasoline"
    ],
    "wof:name":"Peck Petroleum",
    "wof:placetype":"venue"
},
  "geometry": {"coordinates":[-122.62554799999999,45.681344],"type":"Point"}
}