{
  "type": "Feature",
  "properties": {
    "addr:full":"3305 E Ainsworth St Pasco WA 99301",
    "addr:housenumber":"3305",
    "addr:postcode":"99301",
    "addr:street":"E Ainsworth St",
    "iso:country":"US",
    "sg:address":"3305 E Ainsworth St",
    "sg:city":"Pasco",
    "sg:classifiers":[
        {
            "category":"Wholesale",
            "subcategory":"Books, Periodicals, & Newspapers",
            "type":"Manufacturing & Wholesale Goods"
        }
    ],
    "sg:phone":"+1 509 546 0330",
    "sg:postcode":"99301",
    "sg:province":"WA",
    "sg:tags":[
        "magazine"
    ],
    "wof:name":"Anderson News LLC",
    "wof:placetype":"venue"
},
  "geometry": {"coordinates":[-119.050391,46.210137],"type":"Point"}
}