{
  "type": "Feature",
  "properties": {
    "iso:country":"US",
    "sg:address":"751 Pine St",
    "sg:city":"Medical Lake",
    "sg:classifiers":[
        {
            "category":"Government",
            "subcategory":"Office",
            "type":"Public Place"
        }
    ],
    "sg:phone":"+1 509 299 2300",
    "sg:postcode":"99022",
    "sg:province":"WA",
    "sg:website":"www.doc.wa.gov",
    "wof:name":"Pine Lodge Correction Ctr-WMEN",
    "wof:placetype":"venue"
},
  "geometry": {"coordinates":[-117.69673400000001,47.572023],"type":"Point"}
}