{
  "type": "Feature",
  "properties": {
    "iso:country":"US",
    "sg:address":"19815 44th Ave W",
    "sg:city":"Lynnwood",
    "sg:classifiers":[
        {
            "category":"Real Estate",
            "subcategory":"Developer",
            "type":"Services"
        }
    ],
    "sg:phone":"+1 425 744 2207",
    "sg:postcode":"98036",
    "sg:province":"WA",
    "wof:name":"Keith Pagnac",
    "wof:placetype":"venue"
},
  "geometry": {"coordinates":[-122.292252,47.817528],"type":"Point"}
}