{
  "type": "Feature",
  "properties": {
    "addr:full":"617 Western Ave Seattle WA 98104",
    "addr:housenumber":"617",
    "addr:postcode":"98104",
    "addr:street":"Western Ave",
    "iso:country":"US",
    "sg:address":"617 Western Ave",
    "sg:city":"Seattle",
    "sg:classifiers":[
        {
            "category":"Home & Garden",
            "subcategory":"Furniture",
            "type":"Retail Goods"
        }
    ],
    "sg:phone":"+1 206 749 0011",
    "sg:postcode":"98104",
    "sg:province":"WA",
    "wof:name":"Fine Furnishings",
    "wof:placetype":"venue"
},
  "geometry": {"coordinates":[-122.33607499999999,47.602696],"type":"Point"}
}