{
  "type": "Feature",
  "properties": {
    "iso:country":"US",
    "sg:address":"843 6th St",
    "sg:city":"Bremerton",
    "sg:classifiers":[
        {
            "category":"Professional",
            "subcategory":"Printing & Photocopies",
            "type":"Services"
        }
    ],
    "sg:phone":"+1 360 479 3024",
    "sg:postcode":"98337",
    "sg:province":"WA",
    "sg:tags":[
        "photocopying"
    ],
    "wof:name":"Rainier Properties",
    "wof:placetype":"venue"
},
  "geometry": {"coordinates":[-122.632532,47.567261],"type":"Point"}
}