{
  "type": "Feature",
  "properties": {
    "addr:full":"100 4th Ave E Olympia WA 98501",
    "addr:housenumber":"100",
    "addr:postcode":"98501",
    "addr:street":"4Th Ave E",
    "iso:country":"US",
    "sg:address":"100 4th Ave E",
    "sg:city":"Olympia",
    "sg:classifiers":[
        {
            "category":"Shopping",
            "subcategory":"Used Merchandise",
            "type":"Retail Goods"
        }
    ],
    "sg:phone":"+1 360 357 9177",
    "sg:postcode":"98501",
    "sg:province":"WA",
    "wof:name":"Sherburne Antiques & Fine Art",
    "wof:placetype":"venue"
},
  "geometry": {"coordinates":[-122.900458,47.044975],"type":"Point"}
}