{
  "type": "Feature",
  "properties": {
    "iso:country":"US",
    "sg:address":"1604 S 73rd Ave",
    "sg:city":"Yakima",
    "sg:classifiers":[
        {
            "category":"Retail",
            "subcategory":"Laundry & Dry Cleaning",
            "type":"Services"
        }
    ],
    "sg:phone":"+1 509 457 4341",
    "sg:postcode":"98908",
    "sg:province":"WA",
    "wof:name":"J&C Carpet Cleaning",
    "wof:placetype":"venue"
},
  "geometry": {"coordinates":[-120.606086,46.575531],"type":"Point"}
}