{
  "type": "Feature",
  "properties": {
    "addr:full":"6817 N Cedar Rd Spokane WA 99208",
    "addr:housenumber":"6817",
    "addr:postcode":"99208",
    "addr:street":"N Cedar Rd",
    "iso:country":"US",
    "sg:address":"6817 N Cedar Rd",
    "sg:city":"Spokane",
    "sg:classifiers":[
        {
            "category":"Health Services",
            "subcategory":"Doctor",
            "type":"Services"
        }
    ],
    "sg:phone":"+1 509 327 4469",
    "sg:postcode":"99208",
    "sg:province":"WA",
    "sg:tags":[
        "dentist"
    ],
    "wof:name":"Randy E Otterholt DDS",
    "wof:placetype":"venue"
},
  "geometry": {"coordinates":[-117.432777,47.719587],"type":"Point"}
}