{
  "type": "Feature",
  "properties": {
    "addr:full":"6608 Hilltop Ln SW Lakewood WA 98499",
    "addr:housenumber":"6608",
    "addr:postcode":"98499",
    "addr:street":"Hilltop Ln Sw",
    "iso:country":"US",
    "sg:address":"6608 Hilltop Ln SW",
    "sg:city":"Lakewood",
    "sg:classifiers":[
        {
            "category":"Professional",
            "subcategory":"Management & Consulting",
            "type":"Services"
        }
    ],
    "sg:phone":"+1 253 581 1892",
    "sg:postcode":"98499",
    "sg:province":"WA",
    "sg:tags":[
        "business"
    ],
    "wof:name":"Internet Media Strategies Inc",
    "wof:placetype":"venue"
},
  "geometry": {"coordinates":[-122.52546100000001,47.145419],"type":"Point"}
}