{
  "type": "Feature",
  "properties": {
    "addr:full":"821 Bay St Port Orchard WA 98366",
    "addr:housenumber":"821",
    "addr:postcode":"98366",
    "addr:street":"Bay St",
    "iso:country":"US",
    "sg:address":"821 Bay St",
    "sg:city":"Port Orchard",
    "sg:classifiers":[
        {
            "category":"Retail",
            "subcategory":"Portrait Studio",
            "type":"Services"
        }
    ],
    "sg:phone":"+1 360 769 2297",
    "sg:postcode":"98366",
    "sg:province":"WA",
    "sg:tags":[
        "photographer"
    ],
    "wof:name":"Capture The Moments",
    "wof:placetype":"venue"
},
  "geometry": {"coordinates":[-122.635024,47.541492],"type":"Point"}
}