{
  "type": "Feature",
  "properties": {
    "addr:full":"7011 Steilacoom Blvd SW Lakewood WA 98499",
    "addr:housenumber":"7011",
    "addr:postcode":"98499",
    "addr:street":"Steilacoom Blvd Sw",
    "iso:country":"US",
    "sg:address":"7011 Steilacoom Blvd SW",
    "sg:city":"Lakewood",
    "sg:classifiers":[
        {
            "category":"Manufacturing",
            "subcategory":"Printing",
            "type":"Manufacturing & Wholesale Goods"
        }
    ],
    "sg:phone":"+1 253 984 1840",
    "sg:postcode":"98499",
    "sg:province":"WA",
    "sg:tags":[
        "commercial"
    ],
    "wof:name":"Corning Wear",
    "wof:placetype":"venue"
},
  "geometry": {"coordinates":[-122.53249,47.177596],"type":"Point"}
}