{
  "type": "Feature",
  "properties": {
    "addr:full":"2550 Carriage Loop SW Olympia WA 98502",
    "addr:housenumber":"2550",
    "addr:postcode":"98502",
    "addr:street":"Carriage Loop Sw",
    "iso:country":"US",
    "sg:address":"2550 Carriage Loop SW",
    "sg:city":"Olympia",
    "sg:classifiers":[
        {
            "category":"Autos & Motor Vehicles",
            "subcategory":"Automobile Sales",
            "type":"Retail Goods"
        }
    ],
    "sg:phone":"+1 360 754 5550",
    "sg:postcode":"98502",
    "sg:province":"WA",
    "sg:tags":[
        "dealership"
    ],
    "sg:website":"www.rainierdodge.com",
    "wof:name":"Rainier Dodge Inc",
    "wof:placetype":"venue"
},
  "geometry": {"coordinates":[-122.93242100000001,47.031545],"type":"Point"}
}