{
  "type": "Feature",
  "properties": {
    "addr:full":"2107 Elliott Avenue Seattle WA 98121",
    "addr:housenumber":"2107",
    "addr:postcode":"98121",
    "addr:street":"Elliott Avenue",
    "iso:country":"US",
    "sg:address":"2107 Elliott Avenue",
    "sg:city":"Seattle",
    "sg:classifiers":[
        {
            "category":"Health Services",
            "subcategory":"Doctor",
            "type":"Services"
        }
    ],
    "sg:phone":"+1 206 448 7004",
    "sg:postcode":"98121",
    "sg:province":"WA",
    "wof:name":"Slater Paula L MD",
    "wof:placetype":"venue"
},
  "geometry": {"coordinates":[-122.3449,47.611189],"type":"Point"}
}