{
  "type": "Feature",
  "properties": {
    "addr:full":"11500 Meridian Ave S Everett WA 98208",
    "addr:housenumber":"11500",
    "addr:postcode":"98208",
    "addr:street":"Meridian Ave S",
    "iso:country":"US",
    "sg:address":"11500 Meridian Ave S",
    "sg:city":"Everett",
    "sg:classifiers":[
        {
            "category":"Professional",
            "subcategory":"Advertising",
            "type":"Services"
        }
    ],
    "sg:phone":"+1 425 267 9783",
    "sg:postcode":"98208",
    "sg:province":"WA",
    "sg:tags":[
        "mail",
        "direct"
    ],
    "wof:name":"Masters",
    "wof:placetype":"venue"
},
  "geometry": {"coordinates":[-122.233491,47.892786],"type":"Point"}
}