{
  "type": "Feature",
  "properties": {
    "iso:country":"US",
    "sg:address":"7701 NE Aquilla Ct",
    "sg:city":"Vancouver",
    "sg:classifiers":[
        {
            "category":"Professional",
            "subcategory":"Management & Consulting",
            "type":"Services"
        }
    ],
    "sg:phone":"+1 360 254 8845",
    "sg:postcode":"98682",
    "sg:province":"WA",
    "sg:tags":[
        "retail",
        "direct",
        "sales"
    ],
    "wof:name":"Larson Marketing",
    "wof:placetype":"venue"
},
  "geometry": {"coordinates":[-122.51859899999999,45.678414],"type":"Point"}
}