{
  "type": "Feature",
  "properties": {
    "addr:full":"18512 Sargent Rd SW Rochester WA 98579",
    "addr:postcode":"18512;98579",
    "addr:street":"Sargent Rd Sw",
    "iso:country":"US",
    "sg:address":"18512 Sargent Rd SW",
    "sg:city":"Rochester",
    "sg:classifiers":[
        {
            "category":"Building & Trades",
            "subcategory":"Construction",
            "type":"Services"
        }
    ],
    "sg:phone":"+1 360 273 3856",
    "sg:postcode":"98579",
    "sg:province":"WA",
    "sg:tags":[
        "concrete",
        "contractor"
    ],
    "wof:name":"Clarence Farmer Enterprises",
    "wof:placetype":"venue"
},
  "geometry": {"coordinates":[-123.036733,46.819345],"type":"Point"}
}