{
  "type": "Feature",
  "properties": {
    "iso:country":"US",
    "sg:address":"181 Muncie Ave",
    "sg:city":"Quilcene",
    "sg:classifiers":[
        {
            "category":"Building & Trades",
            "subcategory":"Construction",
            "type":"Services"
        }
    ],
    "sg:phone":"+1 360 765 4374",
    "sg:postcode":"98376",
    "sg:province":"WA",
    "sg:tags":[
        "general",
        "contractor"
    ],
    "wof:name":"Apex Construction",
    "wof:placetype":"venue"
},
  "geometry": {"coordinates":[-122.872676,47.818052],"type":"Point"}
}