{
  "type": "Feature",
  "properties": {
    "addr:full":"9423 N Division St Spokane WA 99218",
    "addr:housenumber":"9423",
    "addr:postcode":"99218",
    "addr:street":"N Division St",
    "iso:country":"US",
    "sg:address":"9423 N Division St",
    "sg:city":"Spokane",
    "sg:classifiers":[
        {
            "category":"Travel",
            "subcategory":"Travel Agent",
            "type":"Entertainment"
        }
    ],
    "sg:phone":"+1 509 467 6539",
    "sg:postcode":"99218",
    "sg:province":"WA",
    "sg:tags":[
        "agency",
        "bureau"
    ],
    "wof:name":"Northgate Travel",
    "wof:placetype":"venue"
},
  "geometry": {"coordinates":[-117.411541,47.743023],"type":"Point"}
}