{
  "type": "Feature",
  "properties": {
    "addr:full":"624 W Gowe St Kent WA 98032",
    "addr:housenumber":"624",
    "addr:postcode":"98032",
    "addr:street":"W Gowe St",
    "iso:country":"US",
    "sg:address":"624 W Gowe St",
    "sg:city":"Kent",
    "sg:classifiers":[
        {
            "category":"Health Services",
            "subcategory":"Clinic",
            "type":"Services"
        }
    ],
    "sg:phone":"+1 253 856 3071",
    "sg:postcode":"98032",
    "sg:province":"WA",
    "sg:tags":[
        "home",
        "care"
    ],
    "wof:name":"Chesterfield Health Services",
    "wof:placetype":"venue"
},
  "geometry": {"coordinates":[-122.239474,47.380887],"type":"Point"}
}