{
  "type": "Feature",
  "properties": {
    "addr:full":"8023 32nd Ave NW Seattle WA 98117",
    "addr:housenumber":"8023",
    "addr:postcode":"98117",
    "addr:street":"32Nd Ave Nw",
    "iso:country":"US",
    "sg:address":"8023 32nd Ave NW",
    "sg:city":"Seattle",
    "sg:classifiers":[
        {
            "category":"Manufacturing",
            "subcategory":"Chemicals & Compounds",
            "type":"Manufacturing & Wholesale Goods"
        }
    ],
    "sg:phone":"+1 206 781 5004",
    "sg:postcode":"98117",
    "sg:province":"WA",
    "sg:tags":[
        "product",
        "mfg"
    ],
    "wof:name":"Anns Frame Shop",
    "wof:placetype":"venue"
},
  "geometry": {"coordinates":[-122.398397,47.690399],"type":"Point"}
}