{
  "type": "Feature",
  "properties": {
    "addr:full":"3306 NE 49th St Vancouver WA 98663",
    "addr:housenumber":"3306",
    "addr:postcode":"98663",
    "addr:street":"Ne 49Th St",
    "iso:country":"US",
    "sg:address":"3306 NE 49th St",
    "sg:city":"Vancouver",
    "sg:classifiers":[
        {
            "category":"Professional",
            "subcategory":"Accounting & Tax Preparation",
            "type":"Services"
        }
    ],
    "sg:phone":"+1 360 693 5211",
    "sg:postcode":"98663",
    "sg:province":"WA",
    "sg:tags":[
        "accountant",
        "billing"
    ],
    "wof:name":"B L H Accounting",
    "wof:placetype":"venue"
},
  "geometry": {"coordinates":[-122.637001,45.6567],"type":"Point"}
}