{
  "type": "Feature",
  "properties": {
    "iso:country":"US",
    "sg:address":"11907 18th St E",
    "sg:city":"Puyallup",
    "sg:classifiers":[
        {
            "category":"Building & Trades",
            "subcategory":"Construction",
            "type":"Services"
        }
    ],
    "sg:phone":"+1 253 863 8441",
    "sg:postcode":"98372",
    "sg:province":"WA",
    "sg:tags":[
        "house"
    ],
    "wof:name":"Gordon Construction",
    "wof:placetype":"venue"
},
  "geometry": {"coordinates":[-122.27279,47.241098],"type":"Point"}
}