{
  "type": "Feature",
  "properties": {
    "addr:full":"15861 SE 16th St Bellevue WA 98008",
    "addr:postcode":"15861;98008",
    "addr:street":"Se 16Th St",
    "iso:country":"US",
    "sg:address":"15861 SE 16th St",
    "sg:city":"Bellevue",
    "sg:classifiers":[
        {
            "category":"Building & Trades",
            "subcategory":"Construction",
            "type":"Services"
        }
    ],
    "sg:phone":"+1 425 957 2382",
    "sg:postcode":"98008",
    "sg:province":"WA",
    "sg:tags":[
        "contractor"
    ],
    "wof:name":"Krueger Construction",
    "wof:placetype":"venue"
},
  "geometry": {"coordinates":[-122.12799800000001,47.596401],"type":"Point"}
}