{
  "type": "Feature",
  "properties": {
    "addr:full":"8704 NE Mountview St Vancouver WA 98664",
    "addr:housenumber":"8704",
    "addr:postcode":"98664",
    "addr:street":"Ne Mountview St",
    "iso:country":"US",
    "sg:address":"8704 NE Mountview St",
    "sg:city":"Vancouver",
    "sg:classifiers":[
        {
            "category":"Education",
            "subcategory":"Special Training",
            "type":"Public Place"
        }
    ],
    "sg:phone":"+1 360 256 4670",
    "sg:postcode":"98664",
    "sg:province":"WA",
    "sg:tags":[
        "instruction",
        "music"
    ],
    "wof:name":"Yamaha Music School",
    "wof:placetype":"venue"
},
  "geometry": {"coordinates":[-122.58240600000001,45.629828],"type":"Point"}
}