{
  "type": "Feature",
  "properties": {
    "addr:full":"404 Wood Ave Sumner WA 98390",
    "addr:housenumber":"404",
    "addr:postcode":"98390",
    "addr:street":"Wood Ave",
    "iso:country":"US",
    "sg:address":"404 Wood Ave",
    "sg:city":"Sumner",
    "sg:classifiers":[
        {
            "category":"Communications",
            "subcategory":"Film & Video Production",
            "type":"Services"
        }
    ],
    "sg:phone":"+1 253 863 9070",
    "sg:postcode":"98390",
    "sg:province":"WA",
    "sg:tags":[
        "taping"
    ],
    "sg:website":"www.creativevideowa.com",
    "wof:name":"Creative Video Productions",
    "wof:placetype":"venue"
},
  "geometry": {"coordinates":[-122.231994,47.19658],"type":"Point"}
}