{
  "type": "Feature",
  "properties": {
    "addr:full":"525 Valley Rd Aberdeen WA 98520",
    "addr:housenumber":"525",
    "addr:postcode":"98520",
    "addr:street":"Valley Rd",
    "iso:country":"US",
    "sg:address":"525 Valley Rd",
    "sg:city":"Aberdeen",
    "sg:classifiers":[
        {
            "category":"Professional",
            "subcategory":"Management & Consulting",
            "type":"Services"
        }
    ],
    "sg:phone":"+1 360 532 7877",
    "sg:postcode":"98520",
    "sg:province":"WA",
    "wof:name":"Seabert Associates",
    "wof:placetype":"venue"
},
  "geometry": {"coordinates":[-123.818753,46.994677],"type":"Point"}
}