{
  "type": "Feature",
  "properties": {
    "addr:full":"36005 6th Ave SW Federal Way WA 98023",
    "addr:housenumber":"36005",
    "addr:postcode":"98023",
    "addr:street":"6Th Ave Sw Federal Way",
    "iso:country":"US",
    "sg:address":"36005 6th Ave SW",
    "sg:city":"Federal Way",
    "sg:classifiers":[
        {
            "category":"Professional",
            "subcategory":"Management & Consulting",
            "type":"Services"
        }
    ],
    "sg:phone":"+1 253 838 8022",
    "sg:postcode":"98023",
    "sg:province":"WA",
    "sg:tags":[
        "business"
    ],
    "wof:name":"Alaska Catch Seafoods",
    "wof:placetype":"venue"
},
  "geometry": {"coordinates":[-122.342705,47.281707],"type":"Point"}
}