{
  "type": "Feature",
  "properties": {
    "addr:full":"25423 98th Ave S Kent WA 98030",
    "addr:housenumber":"25423",
    "addr:postcode":"98030",
    "addr:street":"98Th Ave S",
    "iso:country":"US",
    "sg:address":"25423 98th Ave S",
    "sg:city":"Kent",
    "sg:classifiers":[
        {
            "category":"Building & Trades",
            "subcategory":"Construction",
            "type":"Services"
        }
    ],
    "sg:phone":"+1 253 859 2343",
    "sg:postcode":"98030",
    "sg:province":"WA",
    "sg:tags":[
        "carpentry",
        "contractor"
    ],
    "wof:name":"J & L Construction",
    "wof:placetype":"venue"
},
  "geometry": {"coordinates":[-122.20800300000001,47.370752],"type":"Point"}
}