{
  "type": "Feature",
  "properties": {
    "addr:full":"1910 132nd Ave SE Bellevue WA 98005",
    "addr:housenumber":"1910",
    "addr:postcode":"98005",
    "addr:street":"132Nd Ave Se",
    "iso:country":"US",
    "sg:address":"1910 132nd Ave SE",
    "sg:city":"Bellevue",
    "sg:classifiers":[
        {
            "category":"Manufacturing",
            "subcategory":"Printing",
            "type":"Manufacturing & Wholesale Goods"
        }
    ],
    "sg:phone":"+1 425 562 0507",
    "sg:postcode":"98005",
    "sg:province":"WA",
    "sg:tags":[
        "lithographic",
        "commercial"
    ],
    "wof:name":"Perfect Press A",
    "wof:placetype":"venue"
},
  "geometry": {"coordinates":[-122.164862,47.593735],"type":"Point"}
}