{
  "type": "Feature",
  "properties": {
    "iso:country":"US",
    "sg:address":"14721 16th Ave NW",
    "sg:city":"Marysville",
    "sg:classifiers":[
        {
            "category":"Building & Trades",
            "subcategory":"Construction",
            "type":"Services"
        }
    ],
    "sg:phone":"+1 360 652 3824",
    "sg:postcode":"98271",
    "sg:province":"WA",
    "sg:tags":[
        "contractor"
    ],
    "wof:name":"Apollo Neon Inc",
    "wof:placetype":"venue"
},
  "geometry": {"coordinates":[-122.254687,48.130727],"type":"Point"}
}