{
  "type": "Feature",
  "properties": {
    "iso:country":"US",
    "sg:address":"1836 Westlake Ave N",
    "sg:city":"Seattle",
    "sg:classifiers":[
        {
            "category":"Social Services",
            "type":"Services"
        }
    ],
    "sg:phone":"+1 206 285 7771",
    "sg:postcode":"98109",
    "sg:province":"WA",
    "sg:tags":[
        "worker"
    ],
    "wof:name":"Steven Freng",
    "wof:placetype":"venue"
},
  "geometry": {"coordinates":[-122.340344,47.634684],"type":"Point"}
}