{
  "type": "Feature",
  "properties": {
    "addr:full":"2125 Gibson Rd Everett WA 98204",
    "addr:housenumber":"2125",
    "addr:postcode":"98204",
    "addr:street":"Gibson Rd",
    "iso:country":"US",
    "sg:address":"2125 Gibson Rd",
    "sg:city":"Everett",
    "sg:classifiers":[
        {
            "category":"Autos & Motor Vehicles",
            "subcategory":"Automobile Sales",
            "type":"Retail Goods"
        }
    ],
    "sg:phone":"+1 425 348 9826",
    "sg:postcode":"98204",
    "sg:province":"WA",
    "sg:tags":[
        "used"
    ],
    "wof:name":"A C Autohaus",
    "wof:placetype":"venue"
},
  "geometry": {"coordinates":[-122.262715,47.882854],"type":"Point"}
}