{
  "type": "Feature",
  "properties": {
    "addr:full":"6333 Seaview Ave NW Seattle WA 98107",
    "addr:housenumber":"6333",
    "addr:postcode":"98107",
    "addr:street":"Seaview Ave Nw",
    "iso:country":"US",
    "sg:address":"6333 Seaview Ave NW",
    "sg:city":"Seattle",
    "sg:classifiers":[
        {
            "category":"Building & Trades",
            "subcategory":"Cleaning & Sanitation",
            "type":"Services"
        }
    ],
    "sg:phone":"+1 206 784 8707",
    "sg:postcode":"98107",
    "sg:province":"WA",
    "sg:tags":[
        "carpet"
    ],
    "wof:name":"G & C Carpet & Upholstery Cleaners Inc",
    "wof:placetype":"venue"
},
  "geometry": {"coordinates":[-122.406998,47.6749],"type":"Point"}
}