{
  "type": "Feature",
  "properties": {
    "addr:full":"9001 Pacific Ave S Tacoma WA 98444",
    "addr:housenumber":"9001",
    "addr:postcode":"98444",
    "addr:street":"Pacific Ave S",
    "iso:country":"US",
    "sg:address":"9001 Pacific Ave S",
    "sg:city":"Tacoma",
    "sg:classifiers":[
        {
            "category":"Building & Trades",
            "subcategory":"Construction",
            "type":"Services"
        }
    ],
    "sg:phone":"+1 253 536 1161",
    "sg:postcode":"98444",
    "sg:province":"WA",
    "sg:tags":[
        "grouting",
        "drilling",
        "jet"
    ],
    "wof:name":"Layne Christensen Company",
    "wof:placetype":"venue"
},
  "geometry": {"coordinates":[-122.434004,47.170171],"type":"Point"}
}