{
  "type": "Feature",
  "properties": {
    "iso:country":"US",
    "sg:address":"3865 112th Ave NE",
    "sg:city":"Bellevue",
    "sg:classifiers":[
        {
            "category":"Professional",
            "subcategory":"Management & Consulting",
            "type":"Services"
        }
    ],
    "sg:phone":"+1 425 739 4763",
    "sg:postcode":"98004",
    "sg:province":"WA",
    "wof:name":"Dobson Group Inc",
    "wof:placetype":"venue"
},
  "geometry": {"coordinates":[-122.18977700000001,47.645148],"type":"Point"}
}