{
  "type": "Feature",
  "properties": {
    "addr:full":"1404 Commercial St Leavenworth WA 98826",
    "addr:housenumber":"1404",
    "addr:postcode":"98826",
    "addr:street":"Commercial St",
    "iso:country":"US",
    "sg:address":"1404 Commercial St",
    "sg:city":"Leavenworth",
    "sg:classifiers":[
        {
            "category":"Government",
            "subcategory":"Office",
            "type":"Public Place"
        }
    ],
    "sg:phone":"+1 509 548 5994",
    "sg:postcode":"98826",
    "sg:province":"WA",
    "sg:tags":[
        "village"
    ],
    "wof:name":"Sewer Treatment Plant",
    "wof:placetype":"venue"
},
  "geometry": {"coordinates":[-120.653994,47.597938],"type":"Point"}
}