{
  "type": "Feature",
  "properties": {
    "addr:full":"1800 NE 44th St Ste 220 Renton WA 98056",
    "addr:housenumber":"1800",
    "addr:postcode":"98056",
    "addr:street":"Ne 44Th St Ste 220",
    "iso:country":"US",
    "sg:address":"1800 NE 44th St Ste 220",
    "sg:city":"Renton",
    "sg:classifiers":[
        {
            "category":"Education",
            "subcategory":"Music School",
            "type":"Public Place"
        },
        {
            "category":"Education",
            "subcategory":"Special Training",
            "type":"Public Place"
        }
    ],
    "sg:phone":"+1 425 485 8310",
    "sg:postcode":"98056",
    "sg:province":"WA",
    "sg:tags":[
        "instrument",
        "musical",
        "specialty",
        "teacher"
    ],
    "sg:website":"www.44school.com",
    "wof:name":"4/4 School of Music",
    "wof:placetype":"venue"
},
  "geometry": {"coordinates":[-122.194303,47.532702],"type":"Point"}
}