{
  "type": "Feature",
  "properties": {
    "addr:full":"7000 Wing Point Rd NE Bainbridge Isle WA 98110",
    "addr:housenumber":"7000",
    "addr:postcode":"98110",
    "addr:street":"Wing Point Rd Ne;Isle",
    "iso:country":"US",
    "sg:address":"7000 Wing Point Rd NE",
    "sg:city":"Bainbridge Isle",
    "sg:classifiers":[
        {
            "category":"Shopping",
            "subcategory":"Computers & Home Electronics",
            "type":"Retail Goods"
        }
    ],
    "sg:phone":"+1 206 842 0174",
    "sg:postcode":"98110",
    "sg:province":"WA",
    "sg:tags":[
        "equipment",
        "electronic",
        "supply"
    ],
    "wof:name":"Data Trend Electronics",
    "wof:placetype":"venue"
},
  "geometry": {"coordinates":[-122.496044,47.626241],"type":"Point"}
}