{
  "type": "Feature",
  "properties": {
    "addr:full":"3533 172nd St NE Arlington WA 98223",
    "addr:housenumber":"3533",
    "addr:postcode":"98223",
    "addr:street":"172Nd St Ne",
    "iso:country":"US",
    "sg:address":"3533 172nd St NE",
    "sg:city":"Arlington",
    "sg:classifiers":[
        {
            "category":"Autos & Motor Vehicles",
            "subcategory":"Auto Supplies",
            "type":"Retail Goods"
        },
        {
            "category":"Wholesale",
            "subcategory":"Electrical",
            "type":"Manufacturing & Wholesale Goods"
        }
    ],
    "sg:phone":"+1 360 651 7551",
    "sg:postcode":"98223",
    "sg:province":"WA",
    "sg:tags":[
        "battery",
        "automobile",
        "part",
        "accessory"
    ],
    "sg:website":"http://www.oreillyautoparts.com",
    "wof:name":"O'Reilly Auto Parts",
    "wof:placetype":"venue"
},
  "geometry": {"coordinates":[-122.182585,48.152426],"type":"Point"}
}