{
  "type": "Feature",
  "properties": {
    "addr:full":"1205 Western Ave Seattle WA 98101",
    "addr:housenumber":"1205",
    "addr:postcode":"98101",
    "addr:street":"Western Ave",
    "iso:country":"US",
    "sg:address":"1205 Western Ave",
    "sg:city":"Seattle",
    "sg:classifiers":[
        {
            "category":"Home & Garden",
            "subcategory":"Home Furnishings",
            "type":"Retail Goods"
        },
        {
            "category":"Home & Garden",
            "subcategory":"Furniture",
            "type":"Retail Goods"
        }
    ],
    "sg:phone":"+1 206 364 0748",
    "sg:postcode":"98101",
    "sg:province":"WA",
    "sg:tags":[
        "decor",
        "store"
    ],
    "sg:website":"www.liave-home.com",
    "wof:name":"Liave",
    "wof:placetype":"venue"
},
  "geometry": {"coordinates":[-122.33871499999999,47.605699],"type":"Point"}
}