{
  "type": "Feature",
  "properties": {
    "addr:full":"531 Peach Rd Grandview WA 98930",
    "addr:housenumber":"531",
    "addr:postcode":"98930",
    "addr:street":"Peach Rd",
    "iso:country":"US",
    "sg:address":"531 Peach Rd",
    "sg:city":"Grandview",
    "sg:classifiers":[
        {
            "category":"Building & Trades",
            "subcategory":"Landscaping Services",
            "type":"Services"
        }
    ],
    "sg:phone":"+1 509 882 5100",
    "sg:postcode":"98930",
    "sg:province":"WA",
    "wof:name":"Beaulaurier Farms",
    "wof:placetype":"venue"
},
  "geometry": {"coordinates":[-119.944259,46.253245],"type":"Point"}
}