{
  "type": "Feature",
  "properties": {
    "addr:full":"2317 104th Street Ct S Lakewood WA 98499",
    "addr:housenumber":"2317",
    "addr:postcode":"98499",
    "addr:street":"104Th Street Ct",
    "iso:country":"US",
    "sg:address":"2317 104th Street Ct S",
    "sg:city":"Lakewood",
    "sg:classifiers":[
        {
            "category":"Wholesale",
            "subcategory":"Electrical",
            "type":"Manufacturing & Wholesale Goods"
        }
    ],
    "sg:phone":"+1 253 512 2381",
    "sg:postcode":"98499",
    "sg:province":"WA",
    "sg:tags":[
        "equipment"
    ],
    "wof:name":"Security One",
    "wof:placetype":"venue"
},
  "geometry": {"coordinates":[-122.46607400000001,47.163024],"type":"Point"}
}