{
  "type": "Feature",
  "properties": {
    "iso:country":"US",
    "sg:address":"11414 71st Pl S",
    "sg:city":"Seattle",
    "sg:classifiers":[
        {
            "category":"Building & Trades",
            "subcategory":"Construction",
            "type":"Services"
        }
    ],
    "sg:phone":"+1 206 478 2006",
    "sg:postcode":"98178",
    "sg:province":"WA",
    "sg:tags":[
        "residential",
        "nonresidential"
    ],
    "wof:name":"Eleven",
    "wof:placetype":"venue"
},
  "geometry": {"coordinates":[-122.24606199999999,47.501673],"type":"Point"}
}