{
  "type": "Feature",
  "properties": {
    "addr:full":"206 N 60th St Seattle WA 98103",
    "addr:housenumber":"206",
    "addr:postcode":"98103",
    "addr:street":"N 60Th St",
    "iso:country":"US",
    "sg:address":"206 N 60th St",
    "sg:city":"Seattle",
    "sg:classifiers":[
        {
            "category":"Professional",
            "subcategory":"Business Services",
            "type":"Services"
        }
    ],
    "sg:phone":"+1 206 545 0576",
    "sg:postcode":"98103",
    "sg:province":"WA",
    "wof:name":"Norm Spencer",
    "wof:placetype":"venue"
},
  "geometry": {"coordinates":[-122.355402,47.672424],"type":"Point"}
}