{
  "type": "Feature",
  "properties": {
    "addr:full":"823 State Rte 4 Naselle WA 98638",
    "addr:housenumber":"823",
    "addr:postcode":"98638",
    "addr:street":"State Rte 4 Naselle",
    "iso:country":"US",
    "sg:address":"823 State Rte 4",
    "sg:city":"Naselle",
    "sg:classifiers":[
        {
            "category":"Professional",
            "type":"Services"
        }
    ],
    "sg:phone":"+1 360 484 3455",
    "sg:postcode":"98638",
    "sg:province":"WA",
    "sg:tags":[
        "establishment"
    ],
    "wof:name":"Johnson's One Stop",
    "wof:placetype":"venue"
},
  "geometry": {"coordinates":[-123.79405300000001,46.376865],"type":"Point"}
}