{
  "type": "Feature",
  "properties": {
    "addr:full":"2104 108th Ave SE Bellevue WA 98004",
    "addr:housenumber":"2104",
    "addr:postcode":"98004",
    "addr:street":"108Th Ave Se",
    "iso:country":"US",
    "sg:address":"2104 108th Ave SE",
    "sg:city":"Bellevue",
    "sg:classifiers":[
        {
            "category":"Real Estate",
            "subcategory":"Architect",
            "type":"Services"
        }
    ],
    "sg:phone":"+1 425 454 0370",
    "sg:postcode":"98004",
    "sg:province":"WA",
    "sg:tags":[
        "architectural"
    ],
    "wof:name":"Lawrence Adolfson Inc",
    "wof:placetype":"venue"
},
  "geometry": {"coordinates":[-122.19647000000001,47.591262],"type":"Point"}
}