{
  "type": "Feature",
  "properties": {
    "addr:full":"2504 E Riverside Ave Spokane WA 99202",
    "addr:housenumber":"2504",
    "addr:postcode":"99202",
    "addr:street":"E Riverside Ave",
    "iso:country":"US",
    "sg:address":"2504 E Riverside Ave",
    "sg:city":"Spokane",
    "sg:classifiers":[
        {
            "category":"Retail",
            "subcategory":"Auto Repair",
            "type":"Services"
        }
    ],
    "sg:phone":"+1 509 535 8161",
    "sg:postcode":"99202",
    "sg:province":"WA",
    "sg:tags":[
        "body",
        "automobile",
        "painting"
    ],
    "wof:name":"Meg Automotive Refinishing",
    "wof:placetype":"venue"
},
  "geometry": {"coordinates":[-117.372288,47.658133],"type":"Point"}
}