{
  "type": "Feature",
  "properties": {
    "addr:full":"1703 32nd Ave Seattle WA 98122",
    "addr:housenumber":"1703",
    "addr:postcode":"98122",
    "addr:street":"32Nd Ave",
    "iso:country":"US",
    "sg:address":"1703 32nd Ave",
    "sg:city":"Seattle",
    "sg:classifiers":[
        {
            "category":"Professional",
            "subcategory":"Engineering",
            "type":"Services"
        }
    ],
    "sg:phone":"+1 206 325 4495",
    "sg:postcode":"98122",
    "sg:province":"WA",
    "sg:tags":[
        "aircraft",
        "maintenance"
    ],
    "wof:name":"Wright Aviation Solutions",
    "wof:placetype":"venue"
},
  "geometry": {"coordinates":[-122.291313,47.616453],"type":"Point"}
}