{
  "type": "Feature",
  "properties": {
    "addr:full":"5627 47th Ave SW Seattle WA 98136",
    "addr:housenumber":"5627",
    "addr:postcode":"98136",
    "addr:street":"47Th Ave Sw",
    "iso:country":"US",
    "sg:address":"5627 47th Ave SW",
    "sg:city":"Seattle",
    "sg:classifiers":[
        {
            "category":"Building & Trades",
            "subcategory":"Construction",
            "type":"Services"
        }
    ],
    "sg:phone":"+1 206 932 0816",
    "sg:postcode":"98136",
    "sg:province":"WA",
    "sg:tags":[
        "residential"
    ],
    "wof:name":"Green World Cnstr & Dem LLC",
    "wof:placetype":"venue"
},
  "geometry": {"coordinates":[-122.392503,47.550527],"type":"Point"}
}