{
  "type": "Feature",
  "properties": {
    "addr:full":"4002 1st St Yakima WA 98903",
    "addr:housenumber":"4002",
    "addr:postcode":"98903",
    "addr:street":"1St St",
    "iso:country":"US",
    "sg:address":"4002 1st St",
    "sg:city":"Yakima",
    "sg:classifiers":[
        {
            "category":"Retail",
            "subcategory":"Auto Repair",
            "type":"Services"
        }
    ],
    "sg:phone":"+1 509 249 5976",
    "sg:postcode":"98903",
    "sg:province":"WA",
    "sg:tags":[
        "body"
    ],
    "wof:name":"Universal Upholstery",
    "wof:placetype":"venue"
},
  "geometry": {"coordinates":[-120.476687,46.546718],"type":"Point"}
}