{
  "type": "Feature",
  "properties": {
    "addr:full":"220 E 40th St Tacoma WA 98404",
    "addr:housenumber":"220",
    "addr:postcode":"98404",
    "addr:street":"E 40Th St",
    "iso:country":"US",
    "sg:address":"220 E 40th St",
    "sg:city":"Tacoma",
    "sg:classifiers":[
        {
            "category":"Personal",
            "type":"Services"
        }
    ],
    "sg:phone":"+1 253 229 4024",
    "sg:postcode":"98404",
    "sg:province":"WA",
    "wof:name":"Always Able & Affordable",
    "wof:placetype":"venue"
},
  "geometry": {"coordinates":[-122.428363,47.2208],"type":"Point"}
}