{
  "type": "Feature",
  "properties": {
    "addr:full":"4301 Dixie Ln Malaga WA 98828",
    "addr:housenumber":"4301",
    "addr:postcode":"98828",
    "addr:street":"Dixie Ln",
    "iso:country":"US",
    "sg:address":"4301 Dixie Ln",
    "sg:city":"Malaga",
    "sg:classifiers":[
        {
            "category":"Farming",
            "subcategory":"Orchard",
            "type":"Manufacturing & Wholesale Goods"
        }
    ],
    "sg:phone":"+1 509 663 3568",
    "sg:postcode":"98828",
    "sg:province":"WA",
    "sg:tags":[
        "fruit",
        "tree"
    ],
    "wof:name":"Halvorson Orchards",
    "wof:placetype":"venue"
},
  "geometry": {"coordinates":[-120.190082,47.366087],"type":"Point"}
}