{
  "type": "Feature",
  "properties": {
    "addr:full":"12712 NE Laurin Rd Vancouver WA 98662",
    "addr:housenumber":"12712",
    "addr:postcode":"98662",
    "addr:street":"Ne Laurin Rd",
    "iso:country":"US",
    "sg:address":"12712 NE Laurin Rd",
    "sg:city":"Vancouver",
    "sg:classifiers":[
        {
            "category":"Building & Trades",
            "subcategory":"Construction",
            "type":"Services"
        }
    ],
    "sg:phone":"+1 360 892 3897",
    "sg:postcode":"98662",
    "sg:province":"WA",
    "sg:tags":[
        "wallcoverings-installation",
        "wallpaper",
        "painting",
        "contractor"
    ],
    "wof:name":"Bob's Painting Inc",
    "wof:placetype":"venue"
},
  "geometry": {"coordinates":[-122.566214,45.713999],"type":"Point"}
}