{
  "type": "Feature",
  "properties": {
    "addr:full":"445 Beaver Creek Rd Curtis WA 98538",
    "addr:housenumber":"445",
    "addr:postcode":"98538",
    "addr:street":"Beaver Creek Rd",
    "iso:country":"US",
    "sg:address":"445 Beaver Creek Rd",
    "sg:city":"Curtis",
    "sg:classifiers":[
        {
            "category":"Shopping",
            "subcategory":"Gifts & Souvenirs",
            "type":"Retail Goods"
        }
    ],
    "sg:phone":"+1 360 245 3202",
    "sg:postcode":"98538",
    "sg:province":"WA",
    "sg:tags":[
        "basket",
        "parcel"
    ],
    "wof:name":"Christmas Forest",
    "wof:placetype":"venue"
},
  "geometry": {"coordinates":[-123.12319100000001,46.574005],"type":"Point"}
}