{
  "type": "Feature",
  "properties": {
    "addr:full":"11800 148th Ave SE Renton WA 98059",
    "addr:housenumber":"11800",
    "addr:postcode":"98059",
    "addr:street":"148Th Ave Se",
    "iso:country":"US",
    "sg:address":"11800 148th Ave SE",
    "sg:city":"Renton",
    "sg:classifiers":[
        {
            "category":"Retail",
            "subcategory":"Animal Services",
            "type":"Services"
        }
    ],
    "sg:phone":"+1 425 226 0668",
    "sg:postcode":"98059",
    "sg:province":"WA",
    "wof:name":"Napoleon",
    "wof:placetype":"venue"
},
  "geometry": {"coordinates":[-122.143148,47.498897],"type":"Point"}
}