{
  "type": "Feature",
  "properties": {
    "iso:country":"US",
    "sg:address":"2519 Pacific Hwy E",
    "sg:city":"Tacoma",
    "sg:classifiers":[
        {
            "category":"Retail",
            "subcategory":"Auto Repair",
            "type":"Services"
        }
    ],
    "sg:phone":"+1 253 922 8339",
    "sg:postcode":"98424",
    "sg:province":"WA",
    "sg:tags":[
        "truck"
    ],
    "wof:name":"Big Truck Svc",
    "wof:placetype":"venue"
},
  "geometry": {"coordinates":[-122.396333,47.243278],"type":"Point"}
}