{
  "type": "Feature",
  "properties": {
    "addr:full":"132 Lake St S Kirkland WA 98033",
    "addr:housenumber":"132",
    "addr:postcode":"98033",
    "addr:street":"Lake St S",
    "iso:country":"US",
    "sg:address":"132 Lake St S",
    "sg:city":"Kirkland",
    "sg:classifiers":[
        {
            "category":"Restaurant",
            "type":"Food & Drink"
        }
    ],
    "sg:phone":"+1 425 822 7350",
    "sg:postcode":"98033",
    "sg:province":"WA",
    "sg:tags":[
        "eating"
    ],
    "sg:website":"www.calabriakirkland.com",
    "wof:name":"Calabria Restorante Italiano",
    "wof:placetype":"venue"
},
  "geometry": {"coordinates":[-122.205898,47.674333],"type":"Point"}
}