{
  "type": "Feature",
  "properties": {
    "addr:full":"3616 49th Ave SW Seattle WA 98116",
    "addr:housenumber":"3616",
    "addr:postcode":"98116",
    "addr:street":"49Th Ave Sw",
    "iso:country":"US",
    "sg:address":"3616 49th Ave SW",
    "sg:city":"Seattle",
    "sg:classifiers":[
        {
            "category":"Professional",
            "subcategory":"Management & Consulting",
            "type":"Services"
        }
    ],
    "sg:phone":"+1 206 937 6887",
    "sg:postcode":"98116",
    "sg:province":"WA",
    "sg:tags":[
        "business"
    ],
    "wof:name":"Focal Point",
    "wof:placetype":"venue"
},
  "geometry": {"coordinates":[-122.394693,47.570432],"type":"Point"}
}