{
  "type": "Feature",
  "properties": {
    "addr:full":"807 9th St Mukilteo WA 98275",
    "addr:housenumber":"807",
    "addr:postcode":"98275",
    "addr:street":"9Th St",
    "iso:country":"US",
    "sg:address":"807 9th St",
    "sg:city":"Mukilteo",
    "sg:classifiers":[
        {
            "category":"Professional",
            "type":"Services"
        }
    ],
    "sg:phone":"+1 425 348 5935",
    "sg:postcode":"98275",
    "sg:province":"WA",
    "wof:name":"Northwest Creations",
    "wof:placetype":"venue"
},
  "geometry": {"coordinates":[-122.29967499999999,47.94163],"type":"Point"}
}