{
  "type": "Feature",
  "properties": {
    "addr:full":"702 Ranger Rd Port Angeles WA 98363",
    "addr:housenumber":"702",
    "addr:postcode":"98363",
    "addr:street":"Ranger Rd",
    "iso:country":"US",
    "sg:address":"702 Ranger Rd",
    "sg:city":"Port Angeles",
    "sg:classifiers":[
        {
            "category":"Retail",
            "subcategory":"Auto Repair",
            "type":"Services"
        }
    ],
    "sg:phone":"+1 360 417 8920",
    "sg:postcode":"98363",
    "sg:province":"WA",
    "sg:tags":[
        "automotive"
    ],
    "wof:name":"Lil Petes Towing",
    "wof:placetype":"venue"
},
  "geometry": {"coordinates":[-123.57763300000001,48.126269],"type":"Point"}
}