{
  "type": "Feature",
  "properties": {
    "addr:full":"1116 N 81st St Seattle WA 98103",
    "addr:housenumber":"1116",
    "addr:postcode":"98103",
    "addr:street":"N 81St St",
    "iso:country":"US",
    "sg:address":"1116 N 81st St",
    "sg:city":"Seattle",
    "sg:classifiers":[
        {
            "category":"Personal",
            "subcategory":"Beauty Salon",
            "type":"Services"
        }
    ],
    "sg:phone":"+1 206 784 7784",
    "sg:postcode":"98103",
    "sg:province":"WA",
    "sg:tags":[
        "shop"
    ],
    "wof:name":"Susie Your Hairdresser",
    "wof:placetype":"venue"
},
  "geometry": {"coordinates":[-122.34195699999999,47.687731],"type":"Point"}
}