{
  "type": "Feature",
  "properties": {
    "addr:full":"1034 State Ave Marysville WA 98270",
    "addr:housenumber":"1034",
    "addr:postcode":"98270",
    "addr:street":"State Ave",
    "iso:country":"US",
    "sg:address":"1034 State Ave",
    "sg:city":"Marysville",
    "sg:classifiers":[
        {
            "category":"Autos & Motor Vehicles",
            "subcategory":"Fuel & Gas Station",
            "type":"Retail Goods"
        }
    ],
    "sg:phone":"+1 360 659 2215",
    "sg:postcode":"98270",
    "sg:province":"WA",
    "sg:tags":[
        "grocery",
        "station",
        "gasoline"
    ],
    "wof:name":"A R C O",
    "wof:placetype":"venue"
},
  "geometry": {"coordinates":[-122.17685,48.060758],"type":"Point"}
}