{
  "type": "Feature",
  "properties": {
    "addr:full":"18604 76th Ave W Edmonds WA 98026",
    "addr:housenumber":"18604",
    "addr:postcode":"98026",
    "addr:street":"76Th Ave W",
    "iso:country":"US",
    "sg:address":"18604 76th Ave W",
    "sg:city":"Edmonds",
    "sg:classifiers":[
        {
            "category":"Professional",
            "subcategory":"Lawyer & Legal Services",
            "type":"Services"
        }
    ],
    "sg:phone":"+1 425 776 9171",
    "sg:postcode":"98026",
    "sg:province":"WA",
    "sg:tags":[
        "attorney"
    ],
    "wof:name":"Lois A Freese",
    "wof:placetype":"venue"
},
  "geometry": {"coordinates":[-122.337757,47.83154],"type":"Point"}
}