{
  "type": "Feature",
  "properties": {
    "iso:country":"US",
    "sg:address":"26 108th St SW",
    "sg:city":"Everett",
    "sg:classifiers":[
        {
            "category":"Professional",
            "subcategory":"Art Services",
            "type":"Services"
        }
    ],
    "sg:phone":"+1 425 347 2037",
    "sg:postcode":"98204",
    "sg:province":"WA",
    "sg:tags":[
        "commercial",
        "design"
    ],
    "wof:name":"Jan Nunemaker Graphic Design",
    "wof:placetype":"venue"
},
  "geometry": {"coordinates":[-122.237241,47.899995],"type":"Point"}
}