{
  "type": "Feature",
  "properties": {
    "iso:country":"US",
    "sg:address":"524 3rd St",
    "sg:city":"Raymond",
    "sg:classifiers":[
        {
            "category":"Travel",
            "subcategory":"Hotels & Motels",
            "type":"Entertainment"
        }
    ],
    "sg:phone":"+1 360 942 5571",
    "sg:postcode":"98577",
    "sg:province":"WA",
    "wof:name":"Maunus Mountcastle Motel",
    "wof:placetype":"venue"
},
  "geometry": {"coordinates":[-123.732744,46.688618],"type":"Point"}
}