{
  "type": "Feature",
  "properties": {
    "addr:full":"1611 116th Ave NE Bellevue WA 98004",
    "addr:housenumber":"1611",
    "addr:postcode":"98004",
    "addr:street":"116Th Ave Ne",
    "iso:country":"US",
    "sg:address":"1611 116th Ave NE",
    "sg:city":"Bellevue",
    "sg:classifiers":[
        {
            "category":"Manufacturing",
            "subcategory":"Electronics",
            "type":"Manufacturing & Wholesale Goods"
        }
    ],
    "sg:phone":"+1 425 646 4918",
    "sg:postcode":"98004",
    "sg:province":"WA",
    "sg:tags":[
        "linear",
        "mfg",
        "printed",
        "circuit",
        "integrated",
        "etched"
    ],
    "sg:website":"http://www.linear-tech.com",
    "wof:name":"Linear Technology Corporation",
    "wof:placetype":"venue"
},
  "geometry": {"coordinates":[-122.185692,47.624697],"type":"Point"}
}