{
  "type": "Feature",
  "properties": {
    "addr:full":"4004 NE 134th St Vancouver WA 98686",
    "addr:housenumber":"4004",
    "addr:postcode":"98686",
    "addr:street":"Ne 134Th St",
    "iso:country":"US",
    "sg:address":"4004 NE 134th St",
    "sg:city":"Vancouver",
    "sg:classifiers":[
        {
            "category":"Professional",
            "type":"Services"
        }
    ],
    "sg:phone":"+1 360 546 2490",
    "sg:postcode":"98686",
    "sg:province":"WA",
    "wof:name":"Frohlich Consulting Servi",
    "wof:placetype":"venue"
},
  "geometry": {"coordinates":[-122.62893099999999,45.71897],"type":"Point"}
}