{
  "type": "Feature",
  "properties": {
    "addr:full":"20201 Valmore Ave NE Poulsbo WA 98370",
    "addr:housenumber":"20201",
    "addr:postcode":"98370",
    "addr:street":"Valmore Ave Ne",
    "iso:country":"US",
    "sg:address":"20201 Valmore Ave NE",
    "sg:city":"Poulsbo",
    "sg:classifiers":[
        {
            "category":"Social Services",
            "type":"Services"
        }
    ],
    "sg:phone":"+1 253 851 4888",
    "sg:postcode":"98370",
    "sg:province":"WA",
    "sg:tags":[
        "guidance",
        "child"
    ],
    "wof:name":"Ginger Bread Day Care",
    "wof:placetype":"venue"
},
  "geometry": {"coordinates":[-122.619512,47.747474],"type":"Point"}
}