{
  "type": "Feature",
  "properties": {
    "addr:full":"9122 169th Ave NE Granite Falls WA 98252",
    "addr:housenumber":"9122",
    "addr:postcode":"98252",
    "addr:street":"169Th Ave Ne",
    "iso:country":"US",
    "sg:address":"9122 169th Ave NE",
    "sg:city":"Granite Falls",
    "sg:classifiers":[
        {
            "category":"Professional",
            "subcategory":"Management & Consulting",
            "type":"Services"
        }
    ],
    "sg:phone":"+1 360 691 5910",
    "sg:postcode":"98252",
    "sg:province":"WA",
    "sg:tags":[
        "business"
    ],
    "wof:name":"Knebel Co Inc",
    "wof:placetype":"venue"
},
  "geometry": {"coordinates":[-122.004437,48.081928],"type":"Point"}
}