{
  "type": "Feature",
  "properties": {
    "addr:full":"5256 University Way NE Seattle WA 98105",
    "addr:housenumber":"5256",
    "addr:postcode":"98105",
    "addr:street":"University Way Ne",
    "iso:country":"US",
    "sg:address":"5256 University Way NE",
    "sg:city":"Seattle",
    "sg:classifiers":[
        {
            "category":"Manufacturing",
            "subcategory":"Apparel",
            "type":"Manufacturing & Wholesale Goods"
        }
    ],
    "sg:phone":"+1 206 526 1546",
    "sg:postcode":"98105",
    "sg:province":"WA",
    "sg:tags":[
        "mfg"
    ],
    "wof:name":"Faerie Fingers",
    "wof:placetype":"venue"
},
  "geometry": {"coordinates":[-122.312949,47.668124],"type":"Point"}
}