{
  "type": "Feature",
  "properties": {
    "iso:country":"US",
    "sg:address":"6 N Fair Ave",
    "sg:city":"Yakima",
    "sg:classifiers":[
        {
            "category":"Restaurant",
            "type":"Food & Drink"
        }
    ],
    "sg:phone":"+1 509 574 0642",
    "sg:postcode":"98901",
    "sg:province":"WA",
    "sg:tags":[
        "eating"
    ],
    "wof:name":"Sub Shop",
    "wof:placetype":"venue"
},
  "geometry": {"coordinates":[-120.48791900000001,46.606278],"type":"Point"}
}