{
  "type": "Feature",
  "properties": {
    "addr:full":"2819 NW Kitsap Pl Silverdale WA 98383",
    "addr:housenumber":"2819",
    "addr:postcode":"98383",
    "addr:street":"Nw Kitsap Pl",
    "iso:country":"US",
    "sg:address":"2819 NW Kitsap Pl",
    "sg:city":"Silverdale",
    "sg:classifiers":[
        {
            "category":"Education",
            "subcategory":"Special Training",
            "type":"Public Place"
        }
    ],
    "sg:phone":"+1 360 692 3661",
    "sg:postcode":"98383",
    "sg:province":"WA",
    "sg:tags":[
        "instruction",
        "driving"
    ],
    "wof:name":"Diamond Driving School",
    "wof:placetype":"venue"
},
  "geometry": {"coordinates":[-122.68648,47.656441],"type":"Point"}
}