{
  "type": "Feature",
  "properties": {
    "addr:full":"1115 E 5th St Vancouver WA 98661",
    "addr:housenumber":"1115",
    "addr:postcode":"98661",
    "addr:street":"E 5Th St",
    "iso:country":"US",
    "sg:address":"1115 E 5th St",
    "sg:city":"Vancouver",
    "sg:classifiers":[
        {
            "category":"Museum",
            "type":"Entertainment"
        }
    ],
    "sg:phone":"+1 360 694 7026",
    "sg:postcode":"98661",
    "sg:province":"WA",
    "wof:name":"Pearson Air Museum",
    "wof:placetype":"venue"
},
  "geometry": {"coordinates":[-122.66100299999999,45.624699],"type":"Point"}
}