{
  "type": "Feature",
  "properties": {
    "addr:city":"Vancouver",
    "addr:full":"1115 E 5Th St Vancouver, Wa 98661-3802",
    "addr:house_number":"1115",
    "addr:housenumber":"1115",
    "addr:phone":"+1 360-816-6232",
    "addr:postcode":"98661-3802",
    "addr:road":"E 5Th St",
    "addr:state":"WA",
    "addr:street":"E 5Th St",
    "iso:country":"US",
    "sg:address":"1115 E 5th St",
    "sg:city":"Vancouver",
    "sg:classifiers":[
        {
            "category":"Museum",
            "type":"Entertainment"
        }
    ],
    "sg:phone":"+1 360 694 7026",
    "sg:postcode":"98661",
    "sg:province":"WA",
    "wof:airports":[
        102532251
    ],
    "wof:name":"Pearson Air Museum",
    "wof:placetype":"venue"
},
  "geometry": {"coordinates":[-122.65982,45.62445],"type":"Point"}
}