{
  "type": "Feature",
  "properties": {
    "addr:full":"16420 SE Mcgillivray Blvd # 103 Vancouver WA 98683",
    "addr:postcode":"16420;98683",
    "addr:street":"Se Mcgillivray Blvd # 103",
    "iso:country":"US",
    "sg:address":"16420 SE Mcgillivray Blvd # 103",
    "sg:city":"Vancouver",
    "sg:classifiers":[
        {
            "category":"Professional",
            "subcategory":"Detective & Security Services",
            "type":"Services"
        }
    ],
    "sg:phone":"+1 360 991 0270",
    "sg:postcode":"98683",
    "sg:province":"WA",
    "sg:tags":[
        "information",
        "bureau"
    ],
    "wof:name":"Myo Services, Inc.",
    "wof:placetype":"venue"
},
  "geometry": {"coordinates":[-122.503637,45.604342],"type":"Point"}
}