{
  "type": "Feature",
  "properties": {
    "addr:full":"13833 Pacific Ave S Tacoma WA 98444",
    "addr:housenumber":"13833",
    "addr:postcode":"98444",
    "addr:street":"Pacific Ave S",
    "iso:country":"US",
    "sg:address":"13833 Pacific Ave S",
    "sg:city":"Tacoma",
    "sg:classifiers":[
        {
            "category":"Home & Garden",
            "subcategory":"Building Materials",
            "type":"Retail Goods"
        },
        {
            "category":"Retail",
            "subcategory":"Auto Repair",
            "type":"Services"
        }
    ],
    "sg:phone":"+1 253 536 0227",
    "sg:postcode":"98444",
    "sg:province":"WA",
    "sg:tags":[
        "glass",
        "window",
        "plate",
        "replacement"
    ],
    "wof:name":"16 Windshield Repair Network",
    "wof:placetype":"venue"
},
  "geometry": {"coordinates":[-122.434635,47.130516],"type":"Point"}
}