{
  "type": "Feature",
  "properties": {
    "addr:full":"9007 40th Ave E Tacoma WA 98446",
    "addr:housenumber":"9007",
    "addr:postcode":"98446",
    "addr:street":"40Th Ave E",
    "iso:country":"US",
    "sg:address":"9007 40th Ave E",
    "sg:city":"Tacoma",
    "sg:classifiers":[
        {
            "category":"Retail",
            "subcategory":"Animal Services",
            "type":"Services"
        }
    ],
    "sg:phone":"+1 253 536 6673",
    "sg:postcode":"98446",
    "sg:province":"WA",
    "wof:name":"American Eskimo Dog Assn",
    "wof:placetype":"venue"
},
  "geometry": {"coordinates":[-122.37562800000001,47.174704],"type":"Point"}
}