{
  "type": "Feature",
  "properties": {
    "iso:country":"US",
    "sg:address":"1200 Edmonds Ave NE",
    "sg:city":"Renton",
    "sg:classifiers":[
        {
            "category":"Education",
            "subcategory":"School",
            "type":"Public Place"
        }
    ],
    "sg:phone":"+1 425 204 3600",
    "sg:postcode":"98056",
    "sg:province":"WA",
    "wof:name":"McKnight Middle School",
    "wof:placetype":"venue"
},
  "geometry": {"coordinates":[-122.18552200000001,47.50149],"type":"Point"}
}