{
  "type": "Feature",
  "properties": {
    "addr:full":"318 B St NE Quincy WA 98848",
    "addr:housenumber":"318",
    "addr:postcode":"98848",
    "addr:street":"B St Ne",
    "iso:country":"US",
    "sg:address":"318 B St NE",
    "sg:city":"Quincy",
    "sg:classifiers":[
        {
            "category":"Manufacturing",
            "subcategory":"Buildings",
            "type":"Manufacturing & Wholesale Goods"
        },
        {
            "category":"Building & Trades",
            "subcategory":"Construction",
            "type":"Services"
        }
    ],
    "sg:phone":"+1 509 787 5281",
    "sg:postcode":"98848",
    "sg:province":"WA",
    "sg:tags":[
        "home",
        "builder",
        "contractor"
    ],
    "wof:name":"My Other Home .Daycare",
    "wof:placetype":"venue"
},
  "geometry": {"coordinates":[-119.847894,47.239647],"type":"Point"}
}