{
  "type": "Feature",
  "properties": {
    "addr:full":"3180 139th Ave SE Bellevue WA 98005",
    "addr:housenumber":"3180",
    "addr:postcode":"98005",
    "addr:street":"139Th Ave Se",
    "iso:country":"US",
    "sg:address":"3180 139th Ave SE",
    "sg:city":"Bellevue",
    "sg:classifiers":[
        {
            "category":"Real Estate",
            "subcategory":"Real Estate Operator",
            "type":"Services"
        }
    ],
    "sg:phone":"+1 425 641 3351",
    "sg:postcode":"98005",
    "sg:province":"WA",
    "sg:tags":[
        "building",
        "leasing",
        "agent",
        "for"
    ],
    "wof:name":"Equity Office Properties Trust",
    "wof:placetype":"venue"
},
  "geometry": {"coordinates":[-122.15536899999999,47.586766],"type":"Point"}
}