{
  "type": "Feature",
  "properties": {
    "addr:full":"416 Dutterow Rd SE Olympia WA 98513",
    "addr:housenumber":"416",
    "addr:postcode":"olympia;98513",
    "addr:street":"Dutterow Rd Se",
    "iso:country":"US",
    "sg:address":"416 Dutterow Rd SE",
    "sg:city":"Olympia",
    "sg:classifiers":[
        {
            "category":"Professional",
            "type":"Services"
        }
    ],
    "sg:phone":"+1 360 280 3711",
    "sg:postcode":"98513",
    "sg:province":"WA",
    "wof:name":"Clearview Windows",
    "wof:placetype":"venue"
},
  "geometry": {"coordinates":[-122.740223,47.055729],"type":"Point"}
}