{
  "type": "Feature",
  "properties": {
    "addr:full":"7681 NE North Shore Rd Belfair WA 98528",
    "addr:housenumber":"7681",
    "addr:postcode":"98528",
    "addr:street":"Ne North Shore Rd",
    "iso:country":"US",
    "sg:address":"7681 NE North Shore Rd",
    "sg:city":"Belfair",
    "sg:classifiers":[
        {
            "category":"Shopping",
            "subcategory":"Gifts & Souvenirs",
            "type":"Retail Goods"
        }
    ],
    "sg:phone":"+1 360 275 0629",
    "sg:postcode":"98528",
    "sg:province":"WA",
    "sg:tags":[
        "shop"
    ],
    "wof:name":"Shoreside Gardens",
    "wof:placetype":"venue"
},
  "geometry": {"coordinates":[-122.95997199999999,47.400662],"type":"Point"}
}