{
  "type": "Feature",
  "properties": {
    "addr:full":"16516 Creek Ln SE Yelm WA 98597",
    "addr:housenumber":"16516",
    "addr:postcode":"98597",
    "addr:street":"Creek Ln Se",
    "iso:country":"US",
    "sg:address":"16516 Creek Ln SE",
    "sg:city":"Yelm",
    "sg:classifiers":[
        {
            "category":"Real Estate",
            "subcategory":"Real Estate Operator",
            "type":"Services"
        }
    ],
    "sg:phone":"+1 360 458 2166",
    "sg:postcode":"98597",
    "sg:province":"WA",
    "sg:tags":[
        "building",
        "apartment"
    ],
    "wof:name":"Yelm Creek Apartments",
    "wof:placetype":"venue"
},
  "geometry": {"coordinates":[-122.589692,46.936693],"type":"Point"}
}