{
  "type": "Feature",
  "properties": {
    "addr:full":"15516 72nd Ave W Edmonds WA 98026",
    "addr:housenumber":"15516",
    "addr:postcode":"98026",
    "addr:street":"72Nd Ave W",
    "iso:country":"US",
    "sg:address":"15516 72nd Ave W",
    "sg:city":"Edmonds",
    "sg:classifiers":[
        {
            "category":"Real Estate",
            "subcategory":"Architect",
            "type":"Services"
        }
    ],
    "sg:phone":"+1 425 745 4644",
    "sg:postcode":"98026",
    "sg:province":"WA",
    "wof:name":"Namkung Development Inc",
    "wof:placetype":"venue"
},
  "geometry": {"coordinates":[-122.33083499999999,47.857489],"type":"Point"}
}