{
  "type": "Feature",
  "properties": {
    "addr:full":"28120 State Rte 410 Buckley WA 98321",
    "addr:housenumber":"28120",
    "addr:postcode":"98321",
    "addr:street":"State Rte 410",
    "iso:country":"US",
    "sg:address":"28120 State Rte 410",
    "sg:city":"Buckley",
    "sg:classifiers":[
        {
            "category":"Retail",
            "subcategory":"Auto Repair",
            "type":"Services"
        }
    ],
    "sg:phone":"+1 206 243 8751",
    "sg:postcode":"98321",
    "sg:province":"WA",
    "sg:tags":[
        "body"
    ],
    "wof:name":"T & H Auto Body Shop",
    "wof:placetype":"venue"
},
  "geometry": {"coordinates":[-122.047618,47.158964],"type":"Point"}
}