{
  "type": "Feature",
  "properties": {
    "addr:full":"5860 Balustrade Blvd SE Lacey WA 98513",
    "addr:housenumber":"5860",
    "addr:postcode":"98513",
    "addr:street":"Balustrade Blvd Se",
    "iso:country":"US",
    "sg:address":"5860 Balustrade Blvd SE",
    "sg:city":"Lacey",
    "sg:classifiers":[
        {
            "category":"Professional",
            "subcategory":"Business Services",
            "type":"Services"
        }
    ],
    "sg:phone":"+1 360 918 8078",
    "sg:postcode":"98513",
    "sg:province":"WA",
    "sg:tags":[
        "consultant",
        "coach"
    ],
    "wof:name":"Lara Consulting Group Inc",
    "wof:placetype":"venue"
},
  "geometry": {"coordinates":[-122.804564,46.987358],"type":"Point"}
}