{
  "type": "Feature",
  "properties": {
    "addr:full":"14205 SE 4th St Ofc Bellevue WA 98007",
    "addr:postcode":"14205;98007",
    "addr:street":"Se 4Th St",
    "iso:country":"US",
    "sg:address":"14205 SE 4th St Ofc",
    "sg:city":"Bellevue",
    "sg:classifiers":[
        {
            "category":"Real Estate",
            "subcategory":"Real Estate Operator",
            "type":"Services"
        }
    ],
    "sg:phone":"+1 425 747 4083",
    "sg:postcode":"98007",
    "sg:province":"WA",
    "sg:tags":[
        "apartment"
    ],
    "wof:name":"Port Apartments",
    "wof:placetype":"venue"
},
  "geometry": {"coordinates":[-122.15100099999999,47.606098],"type":"Point"}
}