{
  "type": "Feature",
  "properties": {
    "addr:full":"16313 N Pittsburg Ln Spokane WA 99208",
    "addr:housenumber":"16313",
    "addr:postcode":"99208",
    "addr:street":"N Pittsburg Ln",
    "iso:country":"US",
    "sg:address":"16313 N Pittsburg Ln",
    "sg:city":"Spokane",
    "sg:classifiers":[
        {
            "category":"Retail",
            "subcategory":"Repair Shop",
            "type":"Services"
        }
    ],
    "sg:phone":"+1 509 466 1169",
    "sg:postcode":"99208",
    "sg:province":"WA",
    "wof:name":"Legacy Collectables",
    "wof:placetype":"venue"
},
  "geometry": {"coordinates":[-117.385012,47.806397],"type":"Point"}
}