{
  "type": "Feature",
  "properties": {
    "addr:full":"27171 N US Hwy 101 Hoodsport WA 98548",
    "addr:housenumber":"27171",
    "addr:postcode":"98548",
    "addr:street":"N Us Hwy 101 Hoodsport",
    "iso:country":"US",
    "sg:address":"27171 N US Hwy 101",
    "sg:city":"Hoodsport",
    "sg:classifiers":[
        {
            "category":"Personal",
            "subcategory":"Beauty Salon",
            "type":"Services"
        }
    ],
    "sg:phone":"+1 360 877 6869",
    "sg:postcode":"98548",
    "sg:province":"WA",
    "sg:tags":[
        "shop"
    ],
    "wof:name":"Smith Connie",
    "wof:placetype":"venue"
},
  "geometry": {"coordinates":[-123.116831,47.443463],"type":"Point"}
}