{
  "type": "Feature",
  "properties": {
    "addr:full":"1406 S Dean St Seattle WA 98144",
    "addr:housenumber":"1406",
    "addr:postcode":"98144",
    "addr:street":"S Dean St",
    "iso:country":"US",
    "sg:address":"1406 S Dean St",
    "sg:city":"Seattle",
    "sg:classifiers":[
        {
            "category":"Manufacturing",
            "subcategory":"Printing",
            "type":"Manufacturing & Wholesale Goods"
        }
    ],
    "sg:phone":"+1 206 443 0392",
    "sg:postcode":"98144",
    "sg:province":"WA",
    "sg:tags":[
        "commercial"
    ],
    "wof:name":"Ultrasheen Uv For Trade",
    "wof:placetype":"venue"
},
  "geometry": {"coordinates":[-122.312563,47.595388],"type":"Point"}
}