{
  "type": "Feature",
  "properties": {
    "addr:full":"4531 Swenson Rd Clayton WA 99110",
    "addr:housenumber":"4531",
    "addr:postcode":"99110",
    "addr:street":"Swenson Rd",
    "iso:country":"US",
    "sg:address":"4531 Swenson Rd",
    "sg:city":"Clayton",
    "sg:classifiers":[
        {
            "category":"Personal",
            "type":"Services"
        }
    ],
    "sg:phone":"+1 509 276 6668",
    "sg:postcode":"99110",
    "sg:province":"WA",
    "wof:name":"Handy Clan Co",
    "wof:placetype":"venue"
},
  "geometry": {"coordinates":[-117.56621800000001,47.981013],"type":"Point"}
}