{
  "type": "Feature",
  "properties": {
    "addr:full":"16124 E Euclid Ave Spokane WA 99216",
    "addr:housenumber":"16124",
    "addr:postcode":"99216",
    "addr:street":"E Euclid Ave",
    "iso:country":"US",
    "sg:address":"16124 E Euclid Ave",
    "sg:city":"Spokane",
    "sg:classifiers":[
        {
            "category":"Manufacturing",
            "subcategory":"Signs",
            "type":"Manufacturing & Wholesale Goods"
        }
    ],
    "sg:phone":"+1 509 624 8921",
    "sg:postcode":"99216",
    "sg:province":"WA",
    "sg:tags":[
        "canvas",
        "product",
        "mfg"
    ],
    "wof:name":"F O Berg",
    "wof:placetype":"venue"
},
  "geometry": {"coordinates":[-117.188123,47.683925],"type":"Point"}
}