{
  "type": "Feature",
  "properties": {
    "addr:full":"2030 1st Ave Ste 120 Seattle WA 98121",
    "addr:housenumber":"2030",
    "addr:postcode":"98121",
    "addr:street":"1St Ave Ste 120",
    "iso:country":"US",
    "sg:address":"2030 1st Ave Ste 120",
    "sg:city":"Seattle",
    "sg:classifiers":[
        {
            "category":"Personal",
            "subcategory":"Massage",
            "type":"Services"
        },
        {
            "category":"Personal",
            "subcategory":"Beauty Salon",
            "type":"Services"
        },
        {
            "category":"Personal",
            "subcategory":"Skin Care",
            "type":"Services"
        }
    ],
    "sg:phone":"+1 206 441 5511",
    "sg:postcode":"98121",
    "sg:province":"WA",
    "sg:tags":[
        "hair"
    ],
    "sg:website":"www.milagrossalonspa.com",
    "wof:name":"Milagros SalonSpa",
    "wof:placetype":"venue"
},
  "geometry": {"coordinates":[-122.34353,47.611721],"type":"Point"}
}