{
  "type": "Feature",
  "properties": {
    "addr:full":"1107 College St SE Lacey WA 98503",
    "addr:housenumber":"1107",
    "addr:postcode":"98503",
    "addr:street":"College St Se",
    "iso:country":"US",
    "sg:address":"1107 College St SE",
    "sg:city":"Lacey",
    "sg:classifiers":[
        {
            "category":"Retail",
            "subcategory":"Laundry & Dry Cleaning",
            "type":"Services"
        }
    ],
    "sg:phone":"+1 360 456 7559",
    "sg:postcode":"98503",
    "sg:province":"WA",
    "sg:tags":[
        "drycleaning",
        "plant"
    ],
    "wof:name":"College Cleaners",
    "wof:placetype":"venue"
},
  "geometry": {"coordinates":[-122.823339,47.035996],"type":"Point"}
}