{
  "type": "Feature",
  "properties": {
    "addr:full":"348 Roosevelt Ave Enumclaw WA 98022",
    "addr:housenumber":"348",
    "addr:postcode":"98022",
    "addr:street":"Roosevelt Ave",
    "iso:country":"US",
    "sg:address":"348 Roosevelt Ave",
    "sg:city":"Enumclaw",
    "sg:classifiers":[
        {
            "category":"Restaurant",
            "type":"Food & Drink"
        }
    ],
    "sg:menulink":"http://www.allmenus.com/wa/enumclaw-plateau/218528-burger-king/menu/",
    "sg:phone":"+1 360 825 9734",
    "sg:postcode":"98022",
    "sg:province":"WA",
    "sg:tags":[
        "american"
    ],
    "wof:name":"Burger King",
    "wof:placetype":"venue"
},
  "geometry": {"coordinates":[-121.98285799999999,47.199452],"type":"Point"}
}