{
  "type": "Feature",
  "properties": {
    "addr:full":"202 5th Ave S Edmonds WA 98020",
    "addr:housenumber":"202",
    "addr:postcode":"98020",
    "addr:street":"5Th Ave S",
    "iso:country":"US",
    "sg:address":"202 5th Ave S",
    "sg:city":"Edmonds",
    "sg:classifiers":[
        {
            "category":"Food & Beverages",
            "subcategory":"Groceries & Convenience Stores",
            "type":"Retail Goods"
        }
    ],
    "sg:phone":"+1 425 775 5253",
    "sg:postcode":"98020",
    "sg:province":"WA",
    "wof:name":"Am/PM Mini Market",
    "wof:placetype":"venue"
},
  "geometry": {"coordinates":[-122.377644,47.808903],"type":"Point"}
}