{
  "type": "Feature",
  "properties": {
    "addr:full":"311 E 1st St Cle Elum WA 98922",
    "addr:housenumber":"311",
    "addr:postcode":"98922",
    "addr:street":"E 1St St",
    "iso:country":"US",
    "sg:address":"311 E 1st St",
    "sg:city":"Cle Elum",
    "sg:classifiers":[
        {
            "category":"Health Services",
            "subcategory":"Doctor",
            "type":"Services"
        }
    ],
    "sg:phone":"+1 509 674 2307",
    "sg:postcode":"98922",
    "sg:province":"WA",
    "sg:tags":[
        "dentist"
    ],
    "wof:name":"Richard R Nelson DDS",
    "wof:placetype":"venue"
},
  "geometry": {"coordinates":[-120.93349499999999,47.194331],"type":"Point"}
}