{
  "type": "Feature",
  "properties": {
    "addr:full":"3350 Monte Villa Pkwy Ste 220 Bothell WA 98021",
    "addr:housenumber":"3350",
    "addr:postcode":"98021",
    "addr:street":"Monte Villa Pkwy Ste 220",
    "iso:country":"US",
    "sg:address":"3350 Monte Villa Pkwy Ste 220",
    "sg:city":"Bothell",
    "sg:classifiers":[
        {
            "category":"Professional",
            "subcategory":"Computer Services",
            "type":"Services"
        }
    ],
    "sg:phone":"+1 425 286 9200",
    "sg:postcode":"98021",
    "sg:province":"WA",
    "sg:tags":[
        "cd-rom",
        "software"
    ],
    "sg:website":"http://www.promium.com",
    "wof:name":"Promium",
    "wof:placetype":"venue"
},
  "geometry": {"coordinates":[-122.18922600000001,47.778051],"type":"Point"}
}