{
  "type": "Feature",
  "properties": {
    "addr:full":"50 S College Ave College Place WA 99324",
    "addr:housenumber":"50",
    "addr:postcode":"99324",
    "addr:street":"S College Ave",
    "iso:country":"US",
    "sg:address":"50 S College Ave",
    "sg:city":"College Place",
    "sg:classifiers":[
        {
            "category":"Professional",
            "subcategory":"Accounting & Tax Preparation",
            "type":"Services"
        }
    ],
    "sg:phone":"+1 509 526 3898",
    "sg:postcode":"99324",
    "sg:province":"WA",
    "sg:tags":[
        "return",
        "filing"
    ],
    "wof:name":"1040 Tax Svc",
    "wof:placetype":"venue"
},
  "geometry": {"coordinates":[-118.38860099999999,46.048832],"type":"Point"}
}