{
  "type": "Feature",
  "properties": {
    "addr:full":"15814 NE 182nd Ave Brush Prairie WA 98606",
    "addr:housenumber":"15814",
    "addr:postcode":"98606",
    "addr:street":"Ne 182Nd Ave",
    "iso:country":"US",
    "sg:address":"15814 NE 182nd Ave",
    "sg:city":"Brush Prairie",
    "sg:classifiers":[
        {
            "category":"Education",
            "subcategory":"School",
            "type":"Public Place"
        }
    ],
    "sg:phone":"+1 360 883 6783",
    "sg:postcode":"98606",
    "sg:province":"WA",
    "wof:name":"Clark County School Credit",
    "wof:placetype":"venue"
},
  "geometry": {"coordinates":[-122.486819,45.737425],"type":"Point"}
}