{
  "type": "Feature",
  "properties": {
    "addr:full":"17728 State Rte 9 SE Snohomish WA 98296",
    "addr:housenumber":"17728",
    "addr:postcode":"98296",
    "addr:street":"State Rte 9",
    "iso:country":"US",
    "sg:address":"17728 State Rte 9 SE",
    "sg:city":"Snohomish",
    "sg:classifiers":[
        {
            "category":"Wholesale",
            "subcategory":"Auto Parts",
            "type":"Manufacturing & Wholesale Goods"
        }
    ],
    "sg:phone":"+1 360 668 5248",
    "sg:postcode":"98296",
    "sg:province":"WA",
    "sg:tags":[
        "automobile",
        "rebuilt"
    ],
    "wof:name":"Whiteside Auto Pick-Up-Truck",
    "wof:placetype":"venue"
},
  "geometry": {"coordinates":[-122.124787,47.836385],"type":"Point"}
}