{
  "type": "Feature",
  "properties": {
    "iso:country":"US",
    "sg:address":"7520 N Division St",
    "sg:city":"Spokane",
    "sg:classifiers":[
        {
            "category":"Home & Garden",
            "subcategory":"Furniture",
            "type":"Retail Goods"
        }
    ],
    "sg:phone":"+1 509 487 3286",
    "sg:postcode":"99208",
    "sg:province":"WA",
    "wof:name":"Bedroom Expressions",
    "wof:placetype":"venue"
},
  "geometry": {"coordinates":[-117.411241,47.725917],"type":"Point"}
}