{
  "type": "Feature",
  "properties": {
    "addr:full":"13813 93rd Ave SE Snohomish WA 98296",
    "addr:housenumber":"13813",
    "addr:postcode":"98296",
    "addr:street":"93Rd Ave Se",
    "iso:country":"US",
    "sg:address":"13813 93rd Ave SE",
    "sg:city":"Snohomish",
    "sg:classifiers":[
        {
            "category":"Building & Trades",
            "subcategory":"Construction",
            "type":"Services"
        }
    ],
    "sg:phone":"+1 360 668 5151",
    "sg:postcode":"98296",
    "sg:province":"WA",
    "sg:tags":[
        "contractor"
    ],
    "wof:name":"Craig L Morrison",
    "wof:placetype":"venue"
},
  "geometry": {"coordinates":[-122.10695200000001,47.873362],"type":"Point"}
}