{
  "type": "Feature",
  "properties": {
    "addr:full":"103 6th Ave N Auburn WA 98001",
    "addr:housenumber":"103",
    "addr:postcode":"98001",
    "addr:street":"6Th Ave N",
    "iso:country":"US",
    "sg:address":"103 6th Ave N",
    "sg:city":"Auburn",
    "sg:classifiers":[
        {
            "category":"Recreation",
            "type":"Entertainment"
        }
    ],
    "sg:phone":"+1 253 833 9839",
    "sg:postcode":"98001",
    "sg:province":"WA",
    "sg:tags":[
        "club",
        "membership"
    ],
    "wof:name":"Filipino & American Community",
    "wof:placetype":"venue"
},
  "geometry": {"coordinates":[-122.256737,47.28516],"type":"Point"}
}