{
  "type": "Feature",
  "properties": {
    "addr:full":"4402 Francis Ave N Seattle WA 98103",
    "addr:housenumber":"4402",
    "addr:postcode":"98103",
    "addr:street":"Francis Ave N",
    "iso:country":"US",
    "sg:address":"4402 Francis Ave N",
    "sg:city":"Seattle",
    "sg:classifiers":[
        {
            "category":"Manufacturing",
            "subcategory":"Printing",
            "type":"Manufacturing & Wholesale Goods"
        }
    ],
    "sg:phone":"+1 206 419 5729",
    "sg:postcode":"98103",
    "sg:province":"WA",
    "sg:tags":[
        "publishing"
    ],
    "wof:name":"Front Point Guiding",
    "wof:placetype":"venue"
},
  "geometry": {"coordinates":[-122.35324199999999,47.661374],"type":"Point"}
}