{
  "type": "Feature",
  "properties": {
    "addr:full":"1401 Danaher Rd Colfax WA 99111",
    "addr:housenumber":"1401",
    "addr:postcode":"99111",
    "addr:street":"Danaher Rd",
    "iso:country":"US",
    "sg:address":"1401 Danaher Rd",
    "sg:city":"Colfax",
    "sg:phone":"+1 509 397 3505",
    "sg:postcode":"99111",
    "sg:province":"WA",
    "sg:tags":[
        "farm",
        "wheat"
    ],
    "wof:name":"Danaher Farms",
    "wof:placetype":"venue"
},
  "geometry": {"coordinates":[-117.346762,46.951508],"type":"Point"}
}