{
  "type": "Feature",
  "properties": {
    "addr:full":"1813 O Ave Anacortes WA 98221",
    "addr:housenumber":"1813",
    "addr:postcode":"98221",
    "addr:street":"O Ave",
    "iso:country":"US",
    "sg:address":"1813 O Ave",
    "sg:city":"Anacortes",
    "sg:classifiers":[
        {
            "category":"Health Services",
            "subcategory":"Clinic",
            "type":"Services"
        },
        {
            "category":"Health Services",
            "subcategory":"Health Practitioner",
            "type":"Services"
        }
    ],
    "sg:phone":"+1 360 293 9095",
    "sg:postcode":"98221",
    "sg:province":"WA",
    "sg:tags":[
        "therapist",
        "therapy",
        "physical"
    ],
    "wof:name":"Hanson Physical Therapy",
    "wof:placetype":"venue"
},
  "geometry": {"coordinates":[-122.614243,48.50767],"type":"Point"}
}