{
  "type": "Feature",
  "properties": {
    "iso:country":"US",
    "sg:address":"110 E Woods Pl",
    "sg:city":"Belfair",
    "sg:classifiers":[
        {
            "category":"Shopping",
            "type":"Retail Goods"
        }
    ],
    "sg:phone":"+1 360 275 7482",
    "sg:postcode":"98528",
    "sg:province":"WA",
    "sg:tags":[
        "merchandise"
    ],
    "wof:name":"Dr Gabes Coins & Collectables",
    "wof:placetype":"venue"
},
  "geometry": {"coordinates":[-122.955383,47.3772],"type":"Point"}
}