{
  "type": "Feature",
  "properties": {
    "addr:full":"2130 164th St SW Lynnwood WA 98087",
    "addr:housenumber":"2130",
    "addr:postcode":"98087",
    "addr:street":"164Th St Sw",
    "iso:country":"US",
    "sg:address":"2130 164th St SW",
    "sg:city":"Lynnwood",
    "sg:classifiers":[
        {
            "category":"Restaurant",
            "type":"Food & Drink"
        }
    ],
    "sg:phone":"+1 425 741 8553",
    "sg:postcode":"98087",
    "sg:province":"WA",
    "wof:name":"Quiznos Sub",
    "wof:placetype":"venue"
},
  "geometry": {"coordinates":[-122.261805,47.84978],"type":"Point"}
}