{
  "type": "Feature",
  "properties": {
    "addr:full":"2119 SE Columbia Way # 330 Vancouver WA 98661",
    "addr:housenumber":"2119",
    "addr:postcode":"98661",
    "addr:street":"Se Columbia Way # 330",
    "iso:country":"US",
    "sg:address":"2119 SE Columbia Way # 330",
    "sg:city":"Vancouver",
    "sg:classifiers":[
        {
            "category":"Wholesale",
            "subcategory":"Office Equipment",
            "type":"Manufacturing & Wholesale Goods"
        },
        {
            "category":"Retail",
            "subcategory":"Repair Shop",
            "type":"Services"
        },
        {
            "category":"Professional",
            "subcategory":"Printing & Photocopies",
            "type":"Services"
        },
        {
            "category":"Shopping",
            "subcategory":"Computers & Home Electronics",
            "type":"Retail Goods"
        }
    ],
    "sg:phone":"+1 360 699 1231",
    "sg:postcode":"98661",
    "sg:province":"WA",
    "sg:tags":[
        "scanning",
        "printer",
        "supply",
        "equipment-wholesale",
        "duplicating",
        "machine",
        "copying",
        "furniture",
        "copy",
        "plotting",
        "manufacturer",
        "typewriter"
    ],
    "wof:name":"Action Photocopy",
    "wof:placetype":"venue"
},
  "geometry": {"coordinates":[-122.64918,45.617303],"type":"Point"}
}