{
  "type": "Feature",
  "properties": {
    "addr:full":"1533 25th Ave Seattle WA 98122",
    "addr:housenumber":"1533",
    "addr:postcode":"98122",
    "addr:street":"25Th Ave",
    "iso:country":"US",
    "sg:address":"1533 25th Ave",
    "sg:city":"Seattle",
    "sg:classifiers":[
        {
            "category":"Farming",
            "subcategory":"Nursery",
            "type":"Manufacturing & Wholesale Goods"
        }
    ],
    "sg:phone":"+1 206 325 6733",
    "sg:postcode":"98122",
    "sg:province":"WA",
    "sg:tags":[
        "ornamental"
    ],
    "wof:name":"Madison Heights Orchids",
    "wof:placetype":"venue"
},
  "geometry": {"coordinates":[-122.300164,47.614922],"type":"Point"}
}