{
  "type": "Feature",
  "properties": {
    "addr:full":"1221 Jadwin Ave Richland WA 99352",
    "addr:housenumber":"1221",
    "addr:postcode":"99352",
    "addr:street":"Jadwin Ave",
    "iso:country":"US",
    "sg:address":"1221 Jadwin Ave",
    "sg:city":"Richland",
    "sg:classifiers":[
        {
            "category":"Banks & Credit Unions",
            "subcategory":"Bank",
            "type":"Services"
        }
    ],
    "sg:phone":"+1 509 946 6191",
    "sg:postcode":"99352",
    "sg:province":"WA",
    "sg:website":"www.banrbank.com",
    "wof:name":"Banner Bank",
    "wof:placetype":"venue"
},
  "geometry": {"coordinates":[-119.275612,46.28188],"type":"Point"}
}