{
  "type": "Feature",
  "properties": {
    "addr:full":"33712 Webster Rd E Eatonville WA 98328",
    "addr:housenumber":"33712",
    "addr:postcode":"98328",
    "addr:street":"Webster Rd E",
    "iso:country":"US",
    "sg:address":"33712 Webster Rd E",
    "sg:city":"Eatonville",
    "sg:classifiers":[
        {
            "category":"Social Services",
            "type":"Services"
        },
        {
            "category":"Place Of Worship",
            "type":"Public Place"
        },
        {
            "category":"Community Center",
            "subcategory":"Youth",
            "type":"Public Place"
        },
        {
            "category":"Recreation",
            "type":"Entertainment"
        }
    ],
    "sg:phone":"+1 253 847 2511",
    "sg:postcode":"98328",
    "sg:province":"WA",
    "sg:tags":[
        "camps-recreational",
        "church"
    ],
    "sg:website":"http://www.salvationarmyusa.org",
    "wof:name":"Salvation Army Camp Arnold",
    "wof:placetype":"venue"
},
  "geometry": {"coordinates":[-122.297792,46.950822],"type":"Point"}
}