{
  "type": "Feature",
  "properties": {
    "addr:full":"3030 Center Rd Chimacum WA 98325",
    "addr:housenumber":"3030",
    "addr:postcode":"98325",
    "addr:street":"Center Rd",
    "iso:country":"US",
    "sg:address":"3030 Center Rd",
    "sg:city":"Chimacum",
    "sg:classifiers":[
        {
            "category":"Building & Trades",
            "subcategory":"Construction",
            "type":"Services"
        }
    ],
    "sg:phone":"+1 360 732 4678",
    "sg:postcode":"98325",
    "sg:province":"WA",
    "sg:tags":[
        "house",
        "nonresidential"
    ],
    "wof:name":"S & W Enterprises",
    "wof:placetype":"venue"
},
  "geometry": {"coordinates":[-122.775997,47.968],"type":"Point"}
}