{
  "type": "Feature",
  "properties": {
    "addr:full":"1606 E Horizon Pl Mukilteo WA 98275",
    "addr:housenumber":"1606",
    "addr:postcode":"98275",
    "addr:street":"E Horizon Pl",
    "iso:country":"US",
    "sg:address":"1606 E Horizon Pl",
    "sg:city":"Mukilteo",
    "sg:classifiers":[
        {
            "category":"Home & Garden",
            "subcategory":"Furniture",
            "type":"Retail Goods"
        }
    ],
    "sg:phone":"+1 425 353 5561",
    "sg:postcode":"98275",
    "sg:province":"WA",
    "wof:name":"Furniture Northwest Inc",
    "wof:placetype":"venue"
},
  "geometry": {"coordinates":[-122.30753300000001,47.936074],"type":"Point"}
}