{
  "type": "Feature",
  "properties": {
    "addr:full":"1207 S 257th Pl Seattle WA 98198",
    "addr:housenumber":"1207",
    "addr:postcode":"98198",
    "addr:street":"S 257Th Pl",
    "iso:country":"US",
    "sg:address":"1207 S 257th Pl",
    "sg:city":"Seattle",
    "sg:classifiers":[
        {
            "category":"Building & Trades",
            "subcategory":"Construction",
            "type":"Services"
        }
    ],
    "sg:phone":"+1 253 529 8531",
    "sg:postcode":"98198",
    "sg:province":"WA",
    "sg:tags":[
        "house"
    ],
    "wof:name":"Glen E Burges III",
    "wof:placetype":"venue"
},
  "geometry": {"coordinates":[-122.317144,47.371287],"type":"Point"}
}