{
  "type": "Feature",
  "properties": {
    "addr:full":"618 E Toppenish Ave Toppenish WA 98948",
    "addr:housenumber":"618",
    "addr:postcode":"98948",
    "addr:street":"E Toppenish Ave",
    "iso:country":"US",
    "sg:address":"618 E Toppenish Ave",
    "sg:city":"Toppenish",
    "sg:classifiers":[
        {
            "category":"Food & Beverages",
            "subcategory":"Groceries & Convenience Stores",
            "type":"Retail Goods"
        }
    ],
    "sg:phone":"+1 509 865 7179",
    "sg:postcode":"98948",
    "sg:province":"WA",
    "sg:tags":[
        "grocer"
    ],
    "wof:name":"Valley View Marketi",
    "wof:placetype":"venue"
},
  "geometry": {"coordinates":[-120.301704,46.377056],"type":"Point"}
}