{
  "type": "Feature",
  "properties": {
    "addr:full":"19817 SE Lacy Way Camas WA 98607",
    "addr:housenumber":"19817",
    "addr:postcode":"98607",
    "addr:street":"Se Lacy Way",
    "iso:country":"US",
    "sg:address":"19817 SE Lacy Way",
    "sg:city":"Camas",
    "sg:classifiers":[
        {
            "category":"Building & Trades",
            "subcategory":"Construction",
            "type":"Services"
        }
    ],
    "sg:phone":"+1 360 833 9520",
    "sg:postcode":"98607",
    "sg:province":"WA",
    "sg:tags":[
        "concrete",
        "contractor"
    ],
    "wof:name":"Yvs Concrete",
    "wof:placetype":"venue"
},
  "geometry": {"coordinates":[-122.469908,45.594246],"type":"Point"}
}