{
  "type": "Feature",
  "properties": {
    "addr:full":"16315 E Temple Rd Spokane WA 99217",
    "addr:housenumber":"16315",
    "addr:postcode":"99217",
    "addr:street":"E Temple Rd",
    "iso:country":"US",
    "sg:address":"16315 E Temple Rd",
    "sg:city":"Spokane",
    "sg:classifiers":[
        {
            "category":"Manufacturing",
            "subcategory":"Food",
            "type":"Manufacturing & Wholesale Goods"
        }
    ],
    "sg:phone":"+1 509 928 2788",
    "sg:postcode":"99217",
    "sg:province":"WA",
    "sg:tags":[
        "winery"
    ],
    "sg:website":"www.mountaindome.com",
    "wof:name":"Mountain Dome Winery",
    "wof:placetype":"venue"
},
  "geometry": {"coordinates":[-117.17981399999999,47.76595],"type":"Point"}
}