{
  "type": "Feature",
  "properties": {
    "addr:full":"5425 Rainier Avenue S Seattle WA 98118",
    "addr:housenumber":"5425",
    "addr:postcode":"98118",
    "addr:street":"Rainier Avenue S",
    "iso:country":"US",
    "sg:address":"5425 Rainier Avenue S",
    "sg:city":"Seattle",
    "sg:classifiers":[
        {
            "category":"Health Services",
            "subcategory":"Dentist",
            "type":"Services"
        }
    ],
    "sg:phone":"+1 206 725 3667",
    "sg:postcode":"98118",
    "sg:province":"WA",
    "wof:name":"Norvold Jan B DDS",
    "wof:placetype":"venue"
},
  "geometry": {"coordinates":[-122.27391299999999,47.538858],"type":"Point"}
}