{
  "type": "Feature",
  "properties": {
    "addr:full":"305 SE Chkalov Dr Vancouver WA 98683",
    "addr:housenumber":"305",
    "addr:postcode":"98683",
    "addr:street":"Se Chkalov Dr",
    "iso:country":"US",
    "sg:address":"305 SE Chkalov Dr",
    "sg:city":"Vancouver",
    "sg:classifiers":[
        {
            "category":"Personal",
            "subcategory":"Barber",
            "type":"Services"
        }
    ],
    "sg:phone":"+1 360 885 2522",
    "sg:postcode":"98683",
    "sg:province":"WA",
    "wof:name":"Barbers Cascade Park",
    "wof:placetype":"venue"
},
  "geometry": {"coordinates":[-122.554177,45.616032],"type":"Point"}
}