{
  "type": "Feature",
  "properties": {
    "addr:full":"34515 9th Ave S Federal Way WA 98003",
    "addr:housenumber":"34515",
    "addr:postcode":"98003",
    "addr:street":"9Th Ave S Federal Way",
    "iso:country":"US",
    "sg:address":"34515 9th Ave S",
    "sg:city":"Federal Way",
    "sg:classifiers":[
        {
            "category":"Health Services",
            "subcategory":"Hospital",
            "type":"Services"
        }
    ],
    "sg:phone":"+1 253 838 9700",
    "sg:postcode":"98003",
    "sg:province":"WA",
    "sg:tags":[
        "general"
    ],
    "wof:name":"Catholic Health Initiatives",
    "wof:placetype":"venue"
},
  "geometry": {"coordinates":[-122.32301699999999,47.292592],"type":"Point"}
}