{
  "type": "Feature",
  "properties": {
    "addr:full":"1029 W Sylvester St Pasco WA 99301",
    "addr:housenumber":"1029",
    "addr:postcode":"99301",
    "addr:street":"W Sylvester St",
    "iso:country":"US",
    "sg:address":"1029 W Sylvester St",
    "sg:city":"Pasco",
    "sg:classifiers":[
        {
            "category":"Organizations",
            "subcategory":"Community Association",
            "type":"Services"
        }
    ],
    "sg:phone":"+1 509 545 1200",
    "sg:postcode":"99301",
    "sg:province":"WA",
    "wof:name":"American Legion Post 34",
    "wof:placetype":"venue"
},
  "geometry": {"coordinates":[-119.104724,46.234121],"type":"Point"}
}