{
  "type": "Feature",
  "properties": {
    "addr:full":"5140 Ballard Ave NW Seattle WA 98107",
    "addr:housenumber":"5140",
    "addr:postcode":"98107",
    "addr:street":"Ballard Ave Nw",
    "iso:country":"US",
    "sg:address":"5140 Ballard Ave NW",
    "sg:city":"Seattle",
    "sg:classifiers":[
        {
            "category":"Real Estate",
            "subcategory":"Architect",
            "type":"Services"
        }
    ],
    "sg:phone":"+1 206 784 6355",
    "sg:postcode":"98107",
    "sg:province":"WA",
    "wof:name":"Helioprope Architechs",
    "wof:placetype":"venue"
},
  "geometry": {"coordinates":[-122.381745,47.665541],"type":"Point"}
}