{
  "type": "Feature",
  "properties": {
    "addr:full":"212 Jamestown Beach Ln Sequim WA 98382",
    "addr:housenumber":"212",
    "addr:postcode":"98382",
    "addr:street":"Jamestown Beach Ln",
    "iso:country":"US",
    "sg:address":"212 Jamestown Beach Ln",
    "sg:city":"Sequim",
    "sg:classifiers":[
        {
            "category":"Professional",
            "subcategory":"Management & Consulting",
            "type":"Services"
        }
    ],
    "sg:phone":"+1 360 681 3289",
    "sg:postcode":"98382",
    "sg:province":"WA",
    "sg:tags":[
        "business"
    ],
    "wof:name":"Springtyme Co LLC",
    "wof:placetype":"venue"
},
  "geometry": {"coordinates":[-123.092916,48.131511],"type":"Point"}
}