{
  "type": "Feature",
  "properties": {
    "addr:full":"416 111th Street Ct E Tacoma WA 98445",
    "addr:housenumber":"416",
    "addr:postcode":"98445",
    "addr:street":"111Th Street Ct E",
    "iso:country":"US",
    "sg:address":"416 111th Street Ct E",
    "sg:city":"Tacoma",
    "sg:classifiers":[
        {
            "category":"Real Estate",
            "subcategory":"Real Estate Operator",
            "type":"Services"
        }
    ],
    "sg:phone":"+1 253 536 7611",
    "sg:postcode":"98445",
    "sg:province":"WA",
    "sg:tags":[
        "apartment"
    ],
    "wof:name":"Monterra Apartment",
    "wof:placetype":"venue"
},
  "geometry": {"coordinates":[-122.425499,47.156231],"type":"Point"}
}