{
  "type": "Feature",
  "properties": {
    "addr:full":"18900 44th Ave W Lynnwood WA 98036",
    "addr:housenumber":"18900",
    "addr:postcode":"98036",
    "addr:street":"44Th Ave W",
    "iso:country":"US",
    "sg:address":"18900 44th Ave W",
    "sg:city":"Lynnwood",
    "sg:classifiers":[
        {
            "category":"Recreation",
            "type":"Entertainment"
        }
    ],
    "sg:phone":"+1 425 771 4030",
    "sg:postcode":"98036",
    "sg:province":"WA",
    "sg:tags":[
        "parks"
    ],
    "sg:website":"www.ci.lynnwood.wa.us",
    "wof:name":"Lynnwood Parks & Recreation",
    "wof:placetype":"venue"
},
  "geometry": {"coordinates":[-122.292401,47.828255],"type":"Point"}
}