{
  "type": "Feature",
  "properties": {
    "addr:full":"4404 176th St SW Lynnwood WA 98037",
    "addr:housenumber":"4404",
    "addr:postcode":"98037",
    "addr:street":"176Th St Sw",
    "iso:country":"US",
    "sg:address":"4404 176th St SW",
    "sg:city":"Lynnwood",
    "sg:classifiers":[
        {
            "category":"Shopping",
            "subcategory":"Crafts & Fabrics",
            "type":"Retail Goods"
        }
    ],
    "sg:phone":"+1 206 399 0981",
    "sg:postcode":"98037",
    "sg:province":"WA",
    "sg:tags":[
        "sewing"
    ],
    "wof:name":"Needle Werke",
    "wof:placetype":"venue"
},
  "geometry": {"coordinates":[-122.29353,47.839099],"type":"Point"}
}