{
  "type": "Feature",
  "properties": {
    "addr:full":"11225 Lakeside Ave NE Seattle WA 98125",
    "addr:housenumber":"11225",
    "addr:postcode":"98125",
    "addr:street":"Lakeside Ave Ne",
    "iso:country":"US",
    "sg:address":"11225 Lakeside Ave NE",
    "sg:city":"Seattle",
    "sg:classifiers":[
        {
            "category":"Building & Trades",
            "subcategory":"Locksmith",
            "type":"Services"
        }
    ],
    "sg:phone":"+1 206 701 6631",
    "sg:postcode":"98125",
    "sg:province":"WA",
    "sg:tags":[
        "key"
    ],
    "wof:name":"Locksmith & A 7 Day Locks",
    "wof:placetype":"venue"
},
  "geometry": {"coordinates":[-122.277568,47.71137],"type":"Point"}
}