{
  "type": "Feature",
  "properties": {
    "addr:full":"880 Valley-Westside Rd Colville WA 99114",
    "addr:housenumber":"880",
    "addr:postcode":"99114",
    "addr:street":"Valley-Westside Rd",
    "iso:country":"US",
    "sg:address":"880 Valley-Westside Rd",
    "sg:city":"Colville",
    "sg:classifiers":[
        {
            "category":"Shopping",
            "type":"Retail Goods"
        }
    ],
    "sg:phone":"+1 509 684 2177",
    "sg:postcode":"99114",
    "sg:province":"WA",
    "sg:tags":[
        "merchandise"
    ],
    "wof:name":"Agland Industries",
    "wof:placetype":"venue"
},
  "geometry": {"coordinates":[-117.926787,48.507805],"type":"Point"}
}