{
  "type": "Feature",
  "properties": {
    "addr:full":"2225 N Dollar Rd Spokane Valley WA 99212",
    "addr:housenumber":"2225",
    "addr:postcode":"99212",
    "addr:street":"N Dollar Rd",
    "iso:country":"US",
    "sg:address":"2225 N Dollar Rd",
    "sg:city":"Spokane Valley",
    "sg:classifiers":[
        {
            "category":"Shopping",
            "subcategory":"Used Merchandise",
            "type":"Retail Goods"
        },
        {
            "category":"Wholesale",
            "subcategory":"Auto Parts",
            "type":"Manufacturing & Wholesale Goods"
        }
    ],
    "sg:phone":"+1 509 535 7789",
    "sg:postcode":"99212",
    "sg:province":"WA",
    "sg:tags":[
        "automobile"
    ],
    "sg:website":"www.antiqueautoranch.com",
    "wof:name":"Antique Auto Ranch Inc",
    "wof:placetype":"venue"
},
  "geometry": {"coordinates":[-117.317376,47.680141],"type":"Point"}
}