{
  "type": "Feature",
  "properties": {
    "addr:full":"8415 SE 68th St Mercer Island WA 98040",
    "addr:housenumber":"8415",
    "addr:postcode":"98040",
    "addr:street":"Se 68Th St",
    "iso:country":"US",
    "sg:address":"8415 SE 68th St",
    "sg:city":"Mercer Island",
    "sg:classifiers":[
        {
            "category":"Building & Trades",
            "subcategory":"Locksmith",
            "type":"Services"
        }
    ],
    "sg:phone":"+1 206 774 4186",
    "sg:postcode":"98040",
    "sg:province":"WA",
    "sg:tags":[
        "key"
    ],
    "wof:name":"24 Hr Any Locksmith Service of Mercer Island",
    "wof:placetype":"venue"
},
  "geometry": {"coordinates":[-122.22680200000001,47.541895],"type":"Point"}
}