{
  "type": "Feature",
  "properties": {
    "addr:full":"3615 S Grand Blvd Spokane WA 99203",
    "addr:housenumber":"3615",
    "addr:postcode":"99203",
    "addr:street":"S Grand Blvd",
    "iso:country":"US",
    "sg:address":"3615 S Grand Blvd",
    "sg:city":"Spokane",
    "sg:classifiers":[
        {
            "category":"Health Services",
            "subcategory":"Doctor",
            "type":"Services"
        }
    ],
    "sg:phone":"+1 509 456 8676",
    "sg:postcode":"99203",
    "sg:province":"WA",
    "wof:name":"Manito Family Dentistry",
    "wof:placetype":"venue"
},
  "geometry": {"coordinates":[-117.40180100000001,47.62092],"type":"Point"}
}