{
  "type": "Feature",
  "properties": {
    "addr:full":"510 Orchard Rd Pasco WA 99301",
    "addr:housenumber":"510",
    "addr:postcode":"99301",
    "addr:street":"Orchard Rd",
    "iso:country":"US",
    "sg:address":"510 Orchard Rd",
    "sg:city":"Pasco",
    "sg:classifiers":[
        {
            "category":"Professional",
            "subcategory":"Management & Consulting",
            "type":"Services"
        }
    ],
    "sg:phone":"+1 509 545 5295",
    "sg:postcode":"99301",
    "sg:province":"WA",
    "wof:name":"Villa Management Co",
    "wof:placetype":"venue"
},
  "geometry": {"coordinates":[-119.123508,46.358496],"type":"Point"}
}