{
  "type": "Feature",
  "properties": {
    "addr:full":"29030 SE 424th St Enumclaw WA 98022",
    "addr:postcode":"29030;98022",
    "addr:street":"Se 424Th St",
    "iso:country":"US",
    "sg:address":"29030 SE 424th St",
    "sg:city":"Enumclaw",
    "sg:classifiers":[
        {
            "category":"Retail",
            "subcategory":"Repair Shop",
            "type":"Services"
        }
    ],
    "sg:phone":"+1 360 825 6965",
    "sg:postcode":"98022",
    "sg:province":"WA",
    "wof:name":"Mikes Taxidermy",
    "wof:placetype":"venue"
},
  "geometry": {"coordinates":[-121.955028,47.221006],"type":"Point"}
}