{
  "type": "Feature",
  "properties": {
    "addr:full":"15059 1st Avenue S Burien WA 98148",
    "addr:housenumber":"15059",
    "addr:postcode":"98148",
    "addr:street":"1St Avenue S",
    "iso:country":"US",
    "sg:address":"15059 1st Avenue S",
    "sg:city":"Burien",
    "sg:classifiers":[
        {
            "category":"Restaurant",
            "type":"Food & Drink"
        }
    ],
    "sg:phone":"+1 206 241 6944",
    "sg:postcode":"98148",
    "sg:province":"WA",
    "wof:name":"Taco Bell Restaurants",
    "wof:placetype":"venue"
},
  "geometry": {"coordinates":[-122.333692,47.468311],"type":"Point"}
}