{
  "type": "Feature",
  "properties": {
    "addr:full":"719 Metcalf St Sedro Woolley WA 98284",
    "addr:housenumber":"719",
    "addr:postcode":"98284",
    "addr:street":"Metcalf St",
    "iso:country":"US",
    "sg:address":"719 Metcalf St",
    "sg:city":"Sedro Woolley",
    "sg:classifiers":[
        {
            "category":"Manufacturing",
            "subcategory":"Food",
            "type":"Manufacturing & Wholesale Goods"
        }
    ],
    "sg:phone":"+1 360 855 2702",
    "sg:postcode":"98284",
    "sg:province":"WA",
    "sg:tags":[
        "frozen",
        "canned",
        "mfg",
        "p"
    ],
    "wof:name":"General Mills",
    "wof:placetype":"venue"
},
  "geometry": {"coordinates":[-122.238518,48.505205],"type":"Point"}
}