{
  "type": "Feature",
  "properties": {
    "addr:full":"1132 N 128th Street Seattle WA 98133",
    "addr:housenumber":"1132",
    "addr:postcode":"98133",
    "addr:street":"N 128Th Street",
    "iso:country":"US",
    "sg:address":"1132 N 128th Street",
    "sg:city":"Seattle",
    "sg:classifiers":[
        {
            "category":"Building & Trades",
            "subcategory":"Construction",
            "type":"Services"
        }
    ],
    "sg:phone":"+1 206 364 3562",
    "sg:postcode":"98133",
    "sg:province":"WA",
    "sg:tags":[
        "contractor"
    ],
    "wof:name":"Osberg Construction Company",
    "wof:placetype":"venue"
},
  "geometry": {"coordinates":[-122.344944,47.722155],"type":"Point"}
}