{
  "type": "Feature",
  "properties": {
    "iso:country":"US",
    "sg:address":"1600 W Clark St",
    "sg:city":"Pasco",
    "sg:classifiers":[
        {
            "category":"Personal",
            "subcategory":"Beauty Salon",
            "type":"Services"
        }
    ],
    "sg:phone":"+1 509 545 9023",
    "sg:postcode":"99301",
    "sg:province":"WA",
    "sg:tags":[
        "shop"
    ],
    "wof:name":"El Toque Magico",
    "wof:placetype":"venue"
},
  "geometry": {"coordinates":[-119.11139,46.228669],"type":"Point"}
}