{
  "type": "Feature",
  "properties": {
    "addr:full":"410 W Harrison St Ste 300 Seattle WA 98119",
    "addr:housenumber":"410",
    "addr:postcode":"98119",
    "addr:street":"W Harrison St Ste 300",
    "iso:country":"US",
    "sg:address":"410 W Harrison St Ste 300",
    "sg:city":"Seattle",
    "sg:classifiers":[
        {
            "category":"Professional",
            "subcategory":"Testing Lab",
            "type":"Services"
        }
    ],
    "sg:phone":"+1 206 805 6300",
    "sg:postcode":"98119",
    "sg:province":"WA",
    "sg:tags":[
        "biological",
        "laboratory"
    ],
    "wof:name":"Phaserx Inc.",
    "wof:placetype":"venue"
},
  "geometry": {"coordinates":[-122.36204499999999,47.62214],"type":"Point"}
}