{
  "type": "Feature",
  "properties": {
    "addr:full":"229 Riverside Ave Winthrop WA 98862",
    "addr:housenumber":"229",
    "addr:postcode":"98862",
    "addr:street":"Riverside Ave",
    "iso:country":"US",
    "sg:address":"229 Riverside Ave",
    "sg:city":"Winthrop",
    "sg:classifiers":[
        {
            "category":"Shopping",
            "subcategory":"Gifts & Souvenirs",
            "type":"Retail Goods"
        }
    ],
    "sg:phone":"+1 509 996 2018",
    "sg:postcode":"98862",
    "sg:province":"WA",
    "sg:tags":[
        "shop"
    ],
    "wof:name":"Fantasy Floral & Gifts",
    "wof:placetype":"venue"
},
  "geometry": {"coordinates":[-120.183088,48.476741],"type":"Point"}
}