{
  "type": "Feature",
  "properties": {
    "addr:full":"3330 H St Washougal WA 98671",
    "addr:housenumber":"3330",
    "addr:postcode":"98671",
    "addr:street":"H St",
    "iso:country":"US",
    "sg:address":"3330 H St",
    "sg:city":"Washougal",
    "sg:classifiers":[
        {
            "category":"Professional",
            "subcategory":"Computer Services",
            "type":"Services"
        }
    ],
    "sg:phone":"+1 503 319 2700",
    "sg:postcode":"98671",
    "sg:province":"WA",
    "sg:tags":[
        "datum"
    ],
    "wof:name":"Greaterthan Studios",
    "wof:placetype":"venue"
},
  "geometry": {"coordinates":[-122.335014,45.581891],"type":"Point"}
}