{
  "type": "Feature",
  "properties": {
    "addr:full":"2137 N 159th St Shoreline WA 98133",
    "addr:housenumber":"2137",
    "addr:postcode":"98133",
    "addr:street":"N 159Th St",
    "iso:country":"US",
    "sg:address":"2137 N 159th St",
    "sg:city":"Shoreline",
    "sg:classifiers":[
        {
            "category":"Building & Trades",
            "subcategory":"Construction",
            "type":"Services"
        }
    ],
    "sg:phone":"+1 206 367 8655",
    "sg:postcode":"98133",
    "sg:province":"WA",
    "sg:tags":[
        "painter"
    ],
    "wof:name":"City Oriental Painting Co",
    "wof:placetype":"venue"
},
  "geometry": {"coordinates":[-122.332931,47.744461],"type":"Point"}
}