{
  "type": "Feature",
  "properties": {
    "addr:full":"18518 E Maxwell Ave Greenacres WA 99016",
    "addr:housenumber":"18518",
    "addr:postcode":"99016",
    "addr:street":"E Maxwell Ave",
    "iso:country":"US",
    "sg:address":"18518 E Maxwell Ave",
    "sg:city":"Greenacres",
    "sg:classifiers":[
        {
            "category":"Professional",
            "type":"Services"
        }
    ],
    "sg:phone":"+1 509 928 0186",
    "sg:postcode":"99016",
    "sg:province":"WA",
    "wof:name":"Artistic Resumes",
    "wof:placetype":"venue"
},
  "geometry": {"coordinates":[-117.156057,47.670439],"type":"Point"}
}