{
  "type": "Feature",
  "properties": {
    "iso:country":"US",
    "sg:address":"4812 Picnic Point Rd",
    "sg:city":"Edmonds",
    "sg:classifiers":[
        {
            "category":"Professional",
            "type":"Services"
        }
    ],
    "sg:phone":"+1 425 745 0380",
    "sg:postcode":"98026",
    "sg:province":"WA",
    "wof:name":"Joseph J Vornbrock",
    "wof:placetype":"venue"
},
  "geometry": {"coordinates":[-122.29737900000001,47.871189],"type":"Point"}
}