{
  "type": "Feature",
  "properties": {
    "addr:full":"345 13th St NE East Wenatchee WA 98802",
    "addr:housenumber":"345",
    "addr:postcode":"98802",
    "addr:street":"13Th St Ne",
    "iso:country":"US",
    "sg:address":"345 13th St NE",
    "sg:city":"East Wenatchee",
    "sg:classifiers":[
        {
            "category":"Food & Beverages",
            "subcategory":"Candy",
            "type":"Retail Goods"
        }
    ],
    "sg:phone":"+1 509 886 0904",
    "sg:postcode":"98802",
    "sg:province":"WA",
    "wof:name":"Lauries Candies",
    "wof:placetype":"venue"
},
  "geometry": {"coordinates":[-120.288464,47.424082],"type":"Point"}
}