{
  "type": "Feature",
  "properties": {
    "addr:full":"12727 SE 63rd St Bellevue WA 98006",
    "addr:postcode":"12727;98006",
    "addr:street":"Se 63Rd St",
    "iso:country":"US",
    "sg:address":"12727 SE 63rd St",
    "sg:city":"Bellevue",
    "sg:classifiers":[
        {
            "category":"Building & Trades",
            "subcategory":"Construction",
            "type":"Services"
        }
    ],
    "sg:phone":"+1 425 562 4854",
    "sg:postcode":"98006",
    "sg:province":"WA",
    "sg:tags":[
        "contractor"
    ],
    "wof:name":"Properties Brandt",
    "wof:placetype":"venue"
},
  "geometry": {"coordinates":[-122.17089900000001,47.545903],"type":"Point"}
}