{
  "type": "Feature",
  "properties": {
    "addr:full":"1700 7th Ave Seattle WA 98101",
    "addr:housenumber":"1700",
    "addr:postcode":"98101",
    "addr:street":"7Th Ave",
    "iso:country":"US",
    "sg:address":"1700 7th Ave",
    "sg:city":"Seattle",
    "sg:classifiers":[
        {
            "category":"Restaurant",
            "type":"Food & Drink"
        }
    ],
    "sg:phone":"+1 206 382 0636",
    "sg:postcode":"98101",
    "sg:province":"WA",
    "sg:tags":[
        "tea",
        "coffee",
        "eating"
    ],
    "sg:website":"www.starbucks.com",
    "wof:name":"Starbucks",
    "wof:placetype":"venue"
},
  "geometry": {"coordinates":[-122.33545100000001,47.614062],"type":"Point"}
}