{
  "type": "Feature",
  "properties": {
    "addr:full":"10024 228th Pl SE Woodinville WA 98077",
    "addr:housenumber":"10024",
    "addr:postcode":"98077",
    "addr:street":"228Th Pl Se",
    "iso:country":"US",
    "sg:address":"10024 228th Pl SE",
    "sg:city":"Woodinville",
    "sg:classifiers":[
        {
            "category":"Building & Trades",
            "subcategory":"Construction",
            "type":"Services"
        }
    ],
    "sg:phone":"+1 425 485 7009",
    "sg:postcode":"98077",
    "sg:province":"WA",
    "sg:tags":[
        "roofing",
        "contractor"
    ],
    "wof:name":"L & L Roofing Plus Corporation",
    "wof:placetype":"venue"
},
  "geometry": {"coordinates":[-122.096009,47.789753],"type":"Point"}
}