{
  "type": "Feature",
  "properties": {
    "addr:full":"2804 S Needham Dr Veradale WA 99037",
    "addr:housenumber":"2804",
    "addr:postcode":"99037",
    "addr:street":"S Needham Dr",
    "iso:country":"US",
    "sg:address":"2804 S Needham Dr",
    "sg:city":"Veradale",
    "sg:classifiers":[
        {
            "category":"Manufacturing",
            "subcategory":"Retail Goods",
            "type":"Manufacturing & Wholesale Goods"
        }
    ],
    "sg:phone":"+1 509 928 5052",
    "sg:postcode":"99037",
    "sg:province":"WA",
    "sg:tags":[
        "product",
        "mfg"
    ],
    "wof:name":"Jo S Bobbi Miniatures",
    "wof:placetype":"venue"
},
  "geometry": {"coordinates":[-117.193961,47.631173],"type":"Point"}
}