{
  "type": "Feature",
  "properties": {
    "addr:full":"616 McMinn Rd Port Townsend WA 98368",
    "addr:housenumber":"616",
    "addr:postcode":"98368",
    "addr:street":"Mcminn Rd",
    "iso:country":"US",
    "sg:address":"616 McMinn Rd",
    "sg:city":"Port Townsend",
    "sg:classifiers":[
        {
            "category":"Professional",
            "type":"Services"
        }
    ],
    "sg:phone":"+1 360 385 6905",
    "sg:postcode":"98368",
    "sg:province":"WA",
    "wof:name":"AMC Enterprises",
    "wof:placetype":"venue"
},
  "geometry": {"coordinates":[-122.864577,48.115319],"type":"Point"}
}