{
  "type": "Feature",
  "properties": {
    "addr:full":"5901 N Lidgerwood St Spokane WA 99208",
    "addr:housenumber":"5901",
    "addr:postcode":"99208",
    "addr:street":"N Lidgerwood St",
    "iso:country":"US",
    "sg:address":"5901 N Lidgerwood St",
    "sg:city":"Spokane",
    "sg:classifiers":[
        {
            "category":"Health Services",
            "subcategory":"Doctor",
            "type":"Services"
        }
    ],
    "sg:phone":"+1 509 483 4060",
    "sg:postcode":"99208",
    "sg:province":"WA",
    "sg:tags":[
        "physician",
        "surgeon"
    ],
    "wof:name":"Northwest Spokane Pediatrics",
    "wof:placetype":"venue"
},
  "geometry": {"coordinates":[-117.405894,47.713302],"type":"Point"}
}