{
  "type": "Feature",
  "properties": {
    "addr:full":"1112 27th Ave Seattle WA 98122",
    "addr:housenumber":"1112",
    "addr:postcode":"98122",
    "addr:street":"27Th Ave",
    "iso:country":"US",
    "sg:address":"1112 27th Ave",
    "sg:city":"Seattle",
    "sg:classifiers":[
        {
            "category":"Real Estate",
            "subcategory":"Real Estate Agent",
            "type":"Services"
        }
    ],
    "sg:phone":"+1 206 323 6373",
    "sg:postcode":"98122",
    "sg:province":"WA",
    "wof:name":"Bob Bruneau",
    "wof:placetype":"venue"
},
  "geometry": {"coordinates":[-122.297427,47.612877],"type":"Point"}
}