{
  "type": "Feature",
  "properties": {
    "addr:full":"838 W State Rte 20 Burlington WA 98233",
    "addr:housenumber":"838",
    "addr:postcode":"98233",
    "addr:street":"W State Rte 20",
    "iso:country":"US",
    "sg:address":"838 W State Rte 20",
    "sg:city":"Burlington",
    "sg:classifiers":[
        {
            "category":"Utilities",
            "subcategory":"Cable",
            "type":"Services"
        }
    ],
    "sg:phone":"+1 360 757 8894",
    "sg:postcode":"98233",
    "sg:province":"WA",
    "sg:tags":[
        "television"
    ],
    "wof:name":"VLH Enterprises Inc",
    "wof:placetype":"venue"
},
  "geometry": {"coordinates":[-122.32372599999999,48.477228],"type":"Point"}
}