{
  "type": "Feature",
  "properties": {
    "addr:full":"2320 42nd Ave SW Seattle WA 98116",
    "addr:housenumber":"2320",
    "addr:postcode":"98116",
    "addr:street":"42Nd Ave Sw",
    "iso:country":"US",
    "sg:address":"2320 42nd Ave SW",
    "sg:city":"Seattle",
    "sg:classifiers":[
        {
            "category":"Food & Beverages",
            "subcategory":"Groceries & Convenience Stores",
            "type":"Retail Goods"
        }
    ],
    "sg:phone":"+1 206 923 3716",
    "sg:postcode":"98116",
    "sg:province":"WA",
    "wof:name":"Admiral Thriftway",
    "wof:placetype":"venue"
},
  "geometry": {"coordinates":[-122.385096,47.581303],"type":"Point"}
}