{
  "type": "Feature",
  "properties": {
    "addr:full":"13118 Lost Lake Rd Snohomish WA 98296",
    "addr:housenumber":"13118",
    "addr:postcode":"98296",
    "addr:street":"Lost Lake Rd",
    "iso:country":"US",
    "sg:address":"13118 Lost Lake Rd",
    "sg:city":"Snohomish",
    "sg:classifiers":[
        {
            "category":"Professional",
            "type":"Services"
        }
    ],
    "sg:phone":"+1 206 915 7396",
    "sg:postcode":"98296",
    "sg:province":"WA",
    "wof:name":"Finnish Touch Services LLC",
    "wof:placetype":"venue"
},
  "geometry": {"coordinates":[-122.05691899999999,47.794074],"type":"Point"}
}