{
  "type": "Feature",
  "properties": {
    "addr:full":"918 SE 164th Ave Ste 3 Vancouver WA 98683",
    "addr:housenumber":"918",
    "addr:postcode":"98683",
    "addr:street":"Se 164Th Ave Ste 3",
    "iso:country":"US",
    "sg:address":"918 SE 164th Ave Ste 3",
    "sg:city":"Vancouver",
    "sg:classifiers":[
        {
            "category":"Health Services",
            "subcategory":"Chiropractor",
            "type":"Services"
        }
    ],
    "sg:phone":"+1 503 223 9426",
    "sg:postcode":"98683",
    "sg:province":"WA",
    "sg:website":"www.fisherslandingchiropractic.com",
    "wof:name":"Fisher Landing Chiropractic",
    "wof:placetype":"venue"
},
  "geometry": {"coordinates":[-122.503998,45.615299],"type":"Point"}
}