{
  "type": "Feature",
  "properties": {
    "addr:full":"4703 S 172nd Pl Seatac WA 98188",
    "addr:housenumber":"4703",
    "addr:postcode":"98188",
    "addr:street":"S 172Nd Pl",
    "iso:country":"US",
    "sg:address":"4703 S 172nd Pl",
    "sg:city":"Seatac",
    "sg:classifiers":[
        {
            "category":"Professional",
            "subcategory":"Computer Services",
            "type":"Services"
        }
    ],
    "sg:phone":"+1 206 246 6403",
    "sg:postcode":"98188",
    "sg:province":"WA",
    "sg:tags":[
        "home",
        "consulting",
        "page",
        "dev",
        "internet"
    ],
    "wof:name":"Guy Smiley Studios",
    "wof:placetype":"venue"
},
  "geometry": {"coordinates":[-122.274946,47.448475],"type":"Point"}
}