{
  "type": "Feature",
  "properties": {
    "addr:full":"12369 SE 41st Ln Bellevue WA 98006",
    "addr:housenumber":"12369",
    "addr:postcode":"98006",
    "addr:street":"Se 41St Ln",
    "iso:country":"US",
    "sg:address":"12369 SE 41st Ln",
    "sg:city":"Bellevue",
    "sg:classifiers":[
        {
            "category":"Banks & Credit Unions",
            "subcategory":"Financial Services",
            "type":"Services"
        }
    ],
    "sg:phone":"+1 425 450 4070",
    "sg:postcode":"98006",
    "sg:province":"WA",
    "sg:tags":[
        "broker",
        "mortgage"
    ],
    "wof:name":"Northwest Lending Associates Inc",
    "wof:placetype":"venue"
},
  "geometry": {"coordinates":[-122.175757,47.571714],"type":"Point"}
}