{
  "type": "Feature",
  "properties": {
    "addr:full":"221 Edgewood Dr Richland WA 99352",
    "addr:housenumber":"221",
    "addr:postcode":"99352",
    "addr:street":"Edgewood Dr",
    "iso:country":"US",
    "sg:address":"221 Edgewood Dr",
    "sg:city":"Richland",
    "sg:classifiers":[
        {
            "category":"Building & Trades",
            "subcategory":"Construction",
            "type":"Services"
        }
    ],
    "sg:phone":"+1 509 627 6757",
    "sg:postcode":"99352",
    "sg:province":"WA",
    "sg:tags":[
        "house"
    ],
    "wof:name":"Blankenship Cnstr Systems",
    "wof:placetype":"venue"
},
  "geometry": {"coordinates":[-119.27202200000001,46.243611],"type":"Point"}
}