{
  "type": "Feature",
  "properties": {
    "addr:full":"9507 E 4th Ave Spokane Valley WA 99206",
    "addr:housenumber":"9507",
    "addr:postcode":"99206",
    "addr:street":"E 4Th Ave",
    "iso:country":"US",
    "sg:address":"9507 E 4th Ave",
    "sg:city":"Spokane Valley",
    "sg:classifiers":[
        {
            "category":"Wholesale",
            "subcategory":"Auto Parts",
            "type":"Manufacturing & Wholesale Goods"
        }
    ],
    "sg:phone":"+1 509 891 4134",
    "sg:postcode":"99206",
    "sg:province":"WA",
    "sg:tags":[
        "automobile"
    ],
    "wof:name":"Norwest Shop Equipment",
    "wof:placetype":"venue"
},
  "geometry": {"coordinates":[-117.279798,47.652993],"type":"Point"}
}