{
  "type": "Feature",
  "properties": {
    "addr:full":"5507 N Railroad Ave Pasco WA 99301",
    "addr:housenumber":"5507",
    "addr:postcode":"99301",
    "addr:street":"N Railroad Ave",
    "iso:country":"US",
    "sg:address":"5507 N Railroad Ave",
    "sg:city":"Pasco",
    "sg:classifiers":[
        {
            "category":"Wholesale",
            "subcategory":"Farm Supplies",
            "type":"Manufacturing & Wholesale Goods"
        },
        {
            "category":"Wholesale",
            "subcategory":"Hardware",
            "type":"Manufacturing & Wholesale Goods"
        },
        {
            "category":"Wholesale",
            "subcategory":"Machinery & Supplies",
            "type":"Manufacturing & Wholesale Goods"
        },
        {
            "category":"Building & Trades",
            "subcategory":"Equipment Rental",
            "type":"Services"
        },
        {
            "category":"Recreation",
            "subcategory":"Picnic Area",
            "type":"Entertainment"
        }
    ],
    "sg:phone":"+1 509 547 2888",
    "sg:postcode":"99301",
    "sg:province":"WA",
    "sg:tags":[
        "baling",
        "repair",
        "hardware-builders",
        "equipment-parts",
        "contractor"
    ],
    "wof:name":"Perkins Tractor & Equipment Inc",
    "wof:placetype":"venue"
},
  "geometry": {"coordinates":[-119.10110299999999,46.273394],"type":"Point"}
}