{
  "type": "Feature",
  "properties": {
    "addr:full":"644 Strander Blvd Ste 165 Tukwila WA 98188",
    "addr:housenumber":"644",
    "addr:postcode":"98188",
    "addr:street":"Strander Blvd Ste 165",
    "iso:country":"US",
    "sg:address":"644 Strander Blvd Ste 165",
    "sg:city":"Tukwila",
    "sg:classifiers":[
        {
            "category":"Professional",
            "subcategory":"Management & Consulting",
            "type":"Services"
        },
        {
            "category":"Professional",
            "subcategory":"Advertising",
            "type":"Services"
        },
        {
            "category":"Professional",
            "subcategory":"Business Services",
            "type":"Services"
        }
    ],
    "sg:phone":"+1 206 440 8288",
    "sg:postcode":"98188",
    "sg:province":"WA",
    "sg:tags":[
        "consultant",
        "program",
        "coach",
        "marketing"
    ],
    "wof:name":"New Trend Marketing Group",
    "wof:placetype":"venue"
},
  "geometry": {"coordinates":[-122.24518500000001,47.456551],"type":"Point"}
}