{
  "type": "Feature",
  "properties": {
    "addr:full":"625 S King Street Seattle WA 98104",
    "addr:housenumber":"625",
    "addr:postcode":"98104",
    "addr:street":"S King Street",
    "iso:country":"US",
    "sg:address":"625 S King Street",
    "sg:city":"Seattle",
    "sg:classifiers":[
        {
            "category":"Food & Beverages",
            "subcategory":"Groceries & Convenience Stores",
            "type":"Retail Goods"
        }
    ],
    "sg:phone":"+1 206 749 9689",
    "sg:postcode":"98104",
    "sg:province":"WA",
    "wof:name":"Golden Star Deli Mart",
    "wof:placetype":"venue"
},
  "geometry": {"coordinates":[-122.32568499999999,47.598478],"type":"Point"}
}