{
  "type": "Feature",
  "properties": {
    "addr:full":"648 Mobius Loop Oak Harbor WA 98277",
    "addr:housenumber":"648",
    "addr:postcode":"98277",
    "addr:street":"Mobius Loop",
    "iso:country":"US",
    "sg:address":"648 Mobius Loop",
    "sg:city":"Oak Harbor",
    "sg:classifiers":[
        {
            "category":"Wholesale",
            "subcategory":"Durable Goods & Equipment",
            "type":"Manufacturing & Wholesale Goods"
        }
    ],
    "sg:phone":"+1 360 679 3648",
    "sg:postcode":"98277",
    "sg:province":"WA",
    "sg:tags":[
        "fire",
        "safety",
        "supply"
    ],
    "wof:name":"Guardian Extinguisher Service",
    "wof:placetype":"venue"
},
  "geometry": {"coordinates":[-122.649387,48.321797],"type":"Point"}
}