{
  "type": "Feature",
  "properties": {
    "addr:full":"7637 Martin Way E Olympia WA 98516",
    "addr:housenumber":"7637",
    "addr:postcode":"98516",
    "addr:street":"Martin Way E",
    "iso:country":"US",
    "sg:address":"7637 Martin Way E",
    "sg:city":"Olympia",
    "sg:classifiers":[
        {
            "category":"Food & Beverages",
            "subcategory":"Groceries & Convenience Stores",
            "type":"Retail Goods"
        }
    ],
    "sg:phone":"+1 360 491 9626",
    "sg:postcode":"98516",
    "sg:province":"WA",
    "wof:name":"Day & Night Grocer",
    "wof:placetype":"venue"
},
  "geometry": {"coordinates":[-122.778688,47.053761],"type":"Point"}
}