{
  "type": "Feature",
  "properties": {
    "addr:full":"2314 NW 94th St Seattle WA 98117",
    "addr:housenumber":"2314",
    "addr:postcode":"98117",
    "addr:street":"Nw 94Th St",
    "iso:country":"US",
    "sg:address":"2314 NW 94th St",
    "sg:city":"Seattle",
    "sg:classifiers":[
        {
            "category":"Building & Trades",
            "subcategory":"Construction",
            "type":"Services"
        }
    ],
    "sg:phone":"+1 206 782 5138",
    "sg:postcode":"98117",
    "sg:province":"WA",
    "sg:tags":[
        "altering",
        "house",
        "contractor",
        "remodeling",
        "nonresidential"
    ],
    "wof:name":"The Janni Company",
    "wof:placetype":"venue"
},
  "geometry": {"coordinates":[-122.38601199999999,47.697544],"type":"Point"}
}