{
  "type": "Feature",
  "properties": {
    "addr:full":"2200 6th Ave Ste 535 Seattle WA 98121",
    "addr:housenumber":"2200",
    "addr:postcode":"98121",
    "addr:street":"6Th Ave Ste 535",
    "iso:country":"US",
    "sg:address":"2200 6th Ave Ste 535",
    "sg:city":"Seattle",
    "sg:classifiers":[
        {
            "category":"Banks & Credit Unions",
            "subcategory":"Investment Brokerage",
            "type":"Services"
        }
    ],
    "sg:phone":"+1 206 448 9454",
    "sg:postcode":"98121",
    "sg:province":"WA",
    "sg:tags":[
        "investing"
    ],
    "wof:name":"Marks Elizabeth K Cfp",
    "wof:placetype":"venue"
},
  "geometry": {"coordinates":[-122.341003,47.616001],"type":"Point"}
}