{
  "type": "Feature",
  "properties": {
    "addr:full":"5454 42nd Ave SW Seattle WA 98136",
    "addr:housenumber":"5454",
    "addr:postcode":"98136",
    "addr:street":"42Nd Ave Sw",
    "iso:country":"US",
    "sg:address":"5454 42nd Ave SW",
    "sg:city":"Seattle",
    "sg:classifiers":[
        {
            "category":"Real Estate",
            "subcategory":"Real Estate Agent",
            "type":"Services"
        }
    ],
    "sg:phone":"+1 206 932 2120",
    "sg:postcode":"98136",
    "sg:province":"WA",
    "sg:tags":[
        "vacancy",
        "rental",
        "listing"
    ],
    "wof:name":"Morris Rental",
    "wof:placetype":"venue"
},
  "geometry": {"coordinates":[-122.385558,47.552899],"type":"Point"}
}