{
  "type": "Feature",
  "properties": {
    "iso:country":"US",
    "sg:address":"64 Junco Rd",
    "sg:city":"Lopez Island",
    "sg:classifiers":[
        {
            "category":"Professional",
            "subcategory":"Business Services",
            "type":"Services"
        },
        {
            "category":"Professional",
            "subcategory":"Management & Consulting",
            "type":"Services"
        }
    ],
    "sg:phone":"+1 360 468 3169",
    "sg:postcode":"98261",
    "sg:province":"WA",
    "sg:tags":[
        "arbitration"
    ],
    "wof:name":"Sue Cook & Associate",
    "wof:placetype":"venue"
},
  "geometry": {"coordinates":[-122.92625,48.502002],"type":"Point"}
}