{
  "type": "Feature",
  "properties": {
    "addr:full":"308 E Republican St Seattle WA 98102",
    "addr:housenumber":"308",
    "addr:postcode":"98102",
    "addr:street":"E Republican St",
    "iso:country":"US",
    "sg:address":"308 E Republican St",
    "sg:city":"Seattle",
    "sg:classifiers":[
        {
            "category":"Real Estate",
            "subcategory":"Real Estate Services",
            "type":"Services"
        },
        {
            "category":"Real Estate",
            "subcategory":"Developer",
            "type":"Services"
        }
    ],
    "sg:phone":"+1 206 325 9630",
    "sg:postcode":"98102",
    "sg:province":"WA",
    "sg:tags":[
        "management"
    ],
    "wof:name":"Melrose Terrace Inc",
    "wof:placetype":"venue"
},
  "geometry": {"coordinates":[-122.327305,47.62312],"type":"Point"}
}