{
  "type": "Feature",
  "properties": {
    "addr:full":"36435 SE 25th St Fall City WA 98024",
    "addr:postcode":"36435;98024",
    "addr:street":"Se 25Th St",
    "iso:country":"US",
    "sg:address":"36435 SE 25th St",
    "sg:city":"Fall City",
    "sg:classifiers":[
        {
            "category":"Building & Trades",
            "subcategory":"Landscaping Services",
            "type":"Services"
        }
    ],
    "sg:phone":"+1 425 222 6226",
    "sg:postcode":"98024",
    "sg:province":"WA",
    "wof:name":"Yard Masters",
    "wof:placetype":"venue"
},
  "geometry": {"coordinates":[-121.852335,47.585564],"type":"Point"}
}