{
  "type": "Feature",
  "properties": {
    "addr:full":"1005 W 8th St Vancouver WA 98660",
    "addr:housenumber":"1005",
    "addr:postcode":"98660",
    "addr:street":"W 8Th St",
    "iso:country":"US",
    "sg:address":"1005 W 8th St",
    "sg:city":"Vancouver",
    "sg:classifiers":[
        {
            "category":"Freight",
            "type":"Transportation"
        }
    ],
    "sg:phone":"+1 360 694 9566",
    "sg:postcode":"98660",
    "sg:province":"WA",
    "sg:tags":[
        "broker",
        "trucking"
    ],
    "sg:website":"www.focusnorthamerica.com",
    "wof:name":"Focus North America",
    "wof:placetype":"venue"
},
  "geometry": {"coordinates":[-122.68256700000001,45.627241],"type":"Point"}
}