{
  "type": "Feature",
  "properties": {
    "iso:country":"US",
    "sg:address":"4911 N Florida St",
    "sg:city":"Spokane",
    "sg:classifiers":[
        {
            "category":"Real Estate",
            "subcategory":"Developer",
            "type":"Services"
        }
    ],
    "sg:phone":"+1 509 489 0768",
    "sg:postcode":"99217",
    "sg:province":"WA",
    "sg:tags":[
        "mobile",
        "home"
    ],
    "wof:name":"Wishing Well Village",
    "wof:placetype":"venue"
},
  "geometry": {"coordinates":[-117.34933700000001,47.702327],"type":"Point"}
}