{
  "type": "Feature",
  "properties": {
    "iso:country":"US",
    "sg:address":"23641 104th Ave SE",
    "sg:city":"Kent",
    "sg:classifiers":[
        {
            "category":"Restaurant",
            "type":"Food & Drink"
        }
    ],
    "sg:phone":"+1 253 854 2650",
    "sg:postcode":"98031",
    "sg:province":"WA",
    "sg:tags":[
        "eating"
    ],
    "wof:name":"Marys Fine Foods",
    "wof:placetype":"venue"
},
  "geometry": {"coordinates":[-122.202307,47.3909],"type":"Point"}
}