{
  "type": "Feature",
  "properties": {
    "addr:full":"201 E Augusta Ave Ste 204 Spokane WA 99207",
    "addr:housenumber":"201",
    "addr:postcode":"99207",
    "addr:street":"E Augusta Ave Ste 204",
    "iso:country":"US",
    "sg:address":"201 E Augusta Ave Ste 204",
    "sg:city":"Spokane",
    "sg:classifiers":[
        {
            "category":"Professional",
            "subcategory":"Engineering",
            "type":"Services"
        },
        {
            "category":"Wholesale",
            "subcategory":"Electrical",
            "type":"Manufacturing & Wholesale Goods"
        }
    ],
    "sg:phone":"+1 509 326 5859",
    "sg:postcode":"99207",
    "sg:province":"WA",
    "sg:tags":[
        "system",
        "systems-wholesale",
        "equipment",
        "air conditioning",
        "manufacturer"
    ],
    "wof:name":"Climate Control Company",
    "wof:placetype":"venue"
},
  "geometry": {"coordinates":[-117.4079,47.67281],"type":"Point"}
}