{
  "type": "Feature",
  "properties": {
    "addr:full":"815 N Bend Blvd N North Bend WA 98045",
    "addr:housenumber":"815",
    "addr:postcode":"98045",
    "addr:street":"N Bend Blvd N",
    "iso:country":"US",
    "sg:address":"815 N Bend Blvd N",
    "sg:city":"North Bend",
    "sg:classifiers":[
        {
            "category":"Professional",
            "subcategory":"Computer Services",
            "type":"Services"
        }
    ],
    "sg:phone":"+1 425 831 1523",
    "sg:postcode":"98045",
    "sg:province":"WA",
    "sg:tags":[
        "programing",
        "custom"
    ],
    "wof:name":"Brown Kelley & Assoc",
    "wof:placetype":"venue"
},
  "geometry": {"coordinates":[-121.795798,47.488756],"type":"Point"}
}