{
  "type": "Feature",
  "properties": {
    "addr:full":"3400 Wallingford Ave N Seattle WA 98103",
    "addr:housenumber":"3400",
    "addr:postcode":"98103",
    "addr:street":"Wallingford Ave N",
    "iso:country":"US",
    "sg:address":"3400 Wallingford Ave N",
    "sg:city":"Seattle",
    "sg:classifiers":[
        {
            "category":"Manufacturing",
            "subcategory":"Aerospace",
            "type":"Manufacturing & Wholesale Goods"
        }
    ],
    "sg:phone":"+1 206 634 2540",
    "sg:postcode":"98103",
    "sg:province":"WA",
    "sg:tags":[
        "aircraft",
        "mfg"
    ],
    "wof:name":"Avtech Corporation",
    "wof:placetype":"venue"
},
  "geometry": {"coordinates":[-122.33634000000001,47.649194],"type":"Point"}
}