{
  "type": "Feature",
  "properties": {
    "addr:full":"13007 SE 188th Pl Renton WA 98058",
    "addr:housenumber":"13007",
    "addr:postcode":"98058",
    "addr:street":"Se 188Th Pl",
    "iso:country":"US",
    "sg:address":"13007 SE 188th Pl",
    "sg:city":"Renton",
    "sg:classifiers":[
        {
            "category":"Building & Trades",
            "subcategory":"Landscaping Services",
            "type":"Services"
        }
    ],
    "sg:phone":"+1 425 277 6988",
    "sg:postcode":"98058",
    "sg:province":"WA",
    "sg:tags":[
        "landscape"
    ],
    "wof:name":"L & L Landscaping",
    "wof:placetype":"venue"
},
  "geometry": {"coordinates":[-122.166917,47.433341],"type":"Point"}
}