{
  "type": "Feature",
  "properties": {
    "addr:full":"5981 Turnkey Rd NE Moses Lake WA 98837",
    "addr:postcode":"5981;98837",
    "addr:street":"Turnkey Rd Ne",
    "iso:country":"US",
    "sg:address":"5981 Turnkey Rd NE",
    "sg:city":"Moses Lake",
    "sg:classifiers":[
        {
            "category":"Restaurant",
            "type":"Food & Drink"
        }
    ],
    "sg:phone":"+1 509 762 8980",
    "sg:postcode":"98837",
    "sg:province":"WA",
    "wof:name":"Buddy's At The Base",
    "wof:placetype":"venue"
},
  "geometry": {"coordinates":[-119.318991,47.175319],"type":"Point"}
}