{
  "type": "Feature",
  "properties": {
    "iso:country":"US",
    "sg:address":"16303 NE 15th St",
    "sg:city":"Vancouver",
    "sg:classifiers":[
        {
            "category":"Recreation",
            "subcategory":"Amusement Park",
            "type":"Entertainment"
        },
        {
            "category":"Recreation",
            "type":"Entertainment"
        }
    ],
    "sg:phone":"+1 360 604 0505",
    "sg:postcode":"98684",
    "sg:province":"WA",
    "wof:name":"Vancouver Speedway",
    "wof:placetype":"venue"
},
  "geometry": {"coordinates":[-122.50433099999999,45.632872],"type":"Point"}
}