{
  "type": "Feature",
  "properties": {
    "addr:full":"23937 28th Pl W Lynnwood WA 98036",
    "addr:housenumber":"23937",
    "addr:postcode":"98036",
    "addr:street":"28Th Pl W",
    "iso:country":"US",
    "sg:address":"23937 28th Pl W",
    "sg:city":"Lynnwood",
    "sg:classifiers":[
        {
            "category":"Professional",
            "subcategory":"Engineering",
            "type":"Services"
        }
    ],
    "sg:phone":"+1 425 489 2900",
    "sg:postcode":"98036",
    "sg:province":"WA",
    "wof:name":"Fred Selle P E",
    "wof:placetype":"venue"
},
  "geometry": {"coordinates":[-122.27002400000001,47.783115],"type":"Point"}
}