{
  "type": "Feature",
  "properties": {
    "addr:full":"12917 205th Ct SE Issaquah WA 98027",
    "addr:housenumber":"12917",
    "addr:postcode":"98027",
    "addr:street":"205Th Ct Se",
    "iso:country":"US",
    "sg:address":"12917 205th Ct SE",
    "sg:city":"Issaquah",
    "sg:classifiers":[
        {
            "category":"Professional",
            "subcategory":"Management & Consulting",
            "type":"Services"
        }
    ],
    "sg:phone":"+1 425 226 2500",
    "sg:postcode":"98027",
    "sg:province":"WA",
    "sg:tags":[
        "firm",
        "marketing"
    ],
    "wof:name":"International Marketing Corp",
    "wof:placetype":"venue"
},
  "geometry": {"coordinates":[-122.066939,47.487078],"type":"Point"}
}