{
  "type": "Feature",
  "properties": {
    "addr:full":"3854 S Amble Rd Langley WA 98260",
    "addr:housenumber":"3854",
    "addr:postcode":"98260",
    "addr:street":"S Amble Rd",
    "iso:country":"US",
    "sg:address":"3854 S Amble Rd",
    "sg:city":"Langley",
    "sg:classifiers":[
        {
            "category":"Manufacturing",
            "subcategory":"Metals",
            "type":"Manufacturing & Wholesale Goods"
        }
    ],
    "sg:phone":"+1 360 321 8219",
    "sg:postcode":"98260",
    "sg:province":"WA",
    "sg:tags":[
        "mfg",
        "railing"
    ],
    "wof:name":"P N W Construction",
    "wof:placetype":"venue"
},
  "geometry": {"coordinates":[-122.485117,48.070848],"type":"Point"}
}