{
  "type": "Feature",
  "properties": {
    "addr:full":"1140 State Rte 603 Chehalis WA 98532",
    "addr:housenumber":"1140",
    "addr:postcode":"98532",
    "addr:street":"State Rte 603",
    "iso:country":"US",
    "sg:address":"1140 State Rte 603",
    "sg:city":"Chehalis",
    "sg:classifiers":[
        {
            "category":"Government",
            "subcategory":"Office",
            "type":"Public Place"
        }
    ],
    "sg:phone":"+1 360 748 3241",
    "sg:postcode":"98532",
    "sg:province":"WA",
    "sg:tags":[
        "federal",
        "govt"
    ],
    "wof:name":"US Energy Dept",
    "wof:placetype":"venue"
},
  "geometry": {"coordinates":[-122.94347,46.598544],"type":"Point"}
}