{
  "type": "Feature",
  "properties": {
    "addr:full":"809 6th St Mukilteo WA 98275",
    "addr:housenumber":"809",
    "addr:postcode":"98275",
    "addr:street":"6Th St",
    "iso:country":"US",
    "sg:address":"809 6th St",
    "sg:city":"Mukilteo",
    "sg:classifiers":[
        {
            "category":"Professional",
            "subcategory":"Management & Consulting",
            "type":"Services"
        }
    ],
    "sg:phone":"+1 425 348 5567",
    "sg:postcode":"98275",
    "sg:province":"WA",
    "wof:name":"Case Moynihan Management",
    "wof:placetype":"venue"
},
  "geometry": {"coordinates":[-122.298793,47.944618],"type":"Point"}
}