{
  "type": "Feature",
  "properties": {
    "addr:full":"249 SW 153rd St Seattle WA 98166",
    "addr:housenumber":"249",
    "addr:postcode":"98166",
    "addr:street":"Sw 153Rd St",
    "iso:country":"US",
    "sg:address":"249 SW 153rd St",
    "sg:city":"Seattle",
    "sg:classifiers":[
        {
            "category":"Shopping",
            "subcategory":"Computers & Home Electronics",
            "type":"Retail Goods"
        }
    ],
    "sg:phone":"+1 206 241 5402",
    "sg:postcode":"98166",
    "sg:province":"WA",
    "wof:name":"Reed Computing",
    "wof:placetype":"venue"
},
  "geometry": {"coordinates":[-122.338756,47.465873],"type":"Point"}
}