{
  "type": "Feature",
  "properties": {
    "addr:full":"9056 N Texas Rd Anacortes WA 98221",
    "addr:housenumber":"9056",
    "addr:postcode":"98221",
    "addr:street":"N Texas Rd",
    "iso:country":"US",
    "sg:address":"9056 N Texas Rd",
    "sg:city":"Anacortes",
    "sg:classifiers":[
        {
            "category":"Wholesale",
            "subcategory":"Chemicals & Plastics",
            "type":"Manufacturing & Wholesale Goods"
        }
    ],
    "sg:phone":"+1 360 299 8478",
    "sg:postcode":"98221",
    "sg:province":"WA",
    "sg:tags":[
        "mfg"
    ],
    "wof:name":"DRT America Inc",
    "wof:placetype":"venue"
},
  "geometry": {"coordinates":[-122.546752,48.476176],"type":"Point"}
}