{
  "type": "Feature",
  "properties": {
    "addr:full":"8239 S Park Ave Tacoma WA 98408",
    "addr:housenumber":"8239",
    "addr:postcode":"98408",
    "addr:street":"S Park Ave",
    "iso:country":"US",
    "sg:address":"8239 S Park Ave",
    "sg:city":"Tacoma",
    "sg:classifiers":[
        {
            "category":"Home & Garden",
            "subcategory":"Household Appliances",
            "type":"Retail Goods"
        },
        {
            "category":"Retail",
            "subcategory":"Repair Shop",
            "type":"Services"
        }
    ],
    "sg:phone":"+1 253 474 7403",
    "sg:postcode":"98408",
    "sg:province":"WA",
    "sg:tags":[
        "electrical",
        "contractor"
    ],
    "wof:name":"Lifficks T V & Electric Shop",
    "wof:placetype":"venue"
},
  "geometry": {"coordinates":[-122.441868,47.182482],"type":"Point"}
}