{
  "type": "Feature",
  "properties": {
    "addr:full":"2631 NE University Vlg Seattle WA 98105",
    "addr:housenumber":"2631",
    "addr:postcode":"98105",
    "addr:street":"Ne University",
    "iso:country":"US",
    "sg:address":"2631 NE University Vlg",
    "sg:city":"Seattle",
    "sg:classifiers":[
        {
            "category":"Building & Trades",
            "subcategory":"Locksmith",
            "type":"Services"
        }
    ],
    "sg:phone":"+1 206 701 8499",
    "sg:postcode":"98105",
    "sg:province":"WA",
    "sg:tags":[
        "key"
    ],
    "wof:name":"Locksmith Emergency",
    "wof:placetype":"venue"
},
  "geometry": {"coordinates":[-122.299297,47.663251],"type":"Point"}
}