{
  "type": "Feature",
  "properties": {
    "addr:full":"1607 E Division St Mt Vernon WA 98274",
    "addr:housenumber":"1607",
    "addr:postcode":"98274",
    "addr:street":"E Division St",
    "iso:country":"US",
    "sg:address":"1607 E Division St",
    "sg:city":"Mt Vernon",
    "sg:classifiers":[
        {
            "category":"Organizations",
            "subcategory":"Religious Organization",
            "type":"Services"
        }
    ],
    "sg:phone":"+1 360 424 3628",
    "sg:postcode":"98274",
    "sg:province":"WA",
    "sg:tags":[
        "methodist",
        "church"
    ],
    "wof:name":"First United Methodist Church",
    "wof:placetype":"venue"
},
  "geometry": {"coordinates":[-122.321449,48.421111],"type":"Point"}
}