{
  "type": "Feature",
  "properties": {
    "addr:full":"3323 Marine Dr NE Marysville WA 98271",
    "addr:housenumber":"3323",
    "addr:postcode":"98271",
    "addr:street":"Marine Dr Ne",
    "iso:country":"US",
    "sg:address":"3323 Marine Dr NE",
    "sg:city":"Marysville",
    "sg:classifiers":[
        {
            "category":"Autos & Motor Vehicles",
            "subcategory":"Fuel & Gas Station",
            "type":"Retail Goods"
        }
    ],
    "sg:phone":"+1 360 659 3676",
    "sg:postcode":"98271",
    "sg:province":"WA",
    "sg:tags":[
        "station",
        "oil"
    ],
    "wof:name":"Easterbrook's 76",
    "wof:placetype":"venue"
},
  "geometry": {"coordinates":[-122.187282,48.052683],"type":"Point"}
}