{
  "type": "Feature",
  "properties": {
    "addr:full":"4319 N 33rd St Tacoma WA 98407",
    "addr:housenumber":"4319",
    "addr:postcode":"98407",
    "addr:street":"N 33Rd St",
    "iso:country":"US",
    "sg:address":"4319 N 33rd St",
    "sg:city":"Tacoma",
    "sg:classifiers":[
        {
            "category":"Parking",
            "type":"Transportation"
        },
        {
            "category":"Parking",
            "subcategory":"Garage",
            "type":"Transportation"
        }
    ],
    "sg:phone":"+1 253 759 4494",
    "sg:postcode":"98407",
    "sg:province":"WA",
    "sg:tags":[
        "attendant",
        "lot"
    ],
    "wof:name":"Mcdonough & Sons Parking Lot Services",
    "wof:placetype":"venue"
},
  "geometry": {"coordinates":[-122.49485799999999,47.277733],"type":"Point"}
}