{
  "type": "Feature",
  "properties": {
    "addr:full":"804 Terry Ln Selah WA 98942",
    "addr:housenumber":"804",
    "addr:postcode":"98942",
    "addr:street":"Terry Ln",
    "iso:country":"US",
    "sg:address":"804 Terry Ln",
    "sg:city":"Selah",
    "sg:classifiers":[
        {
            "category":"Building & Trades",
            "subcategory":"Construction",
            "type":"Services"
        }
    ],
    "sg:phone":"+1 509 698 6262",
    "sg:postcode":"98942",
    "sg:province":"WA",
    "sg:tags":[
        "contractor"
    ],
    "wof:name":"R W Smoot Construction",
    "wof:placetype":"venue"
},
  "geometry": {"coordinates":[-120.538344,46.66374],"type":"Point"}
}