{
  "type": "Feature",
  "properties": {
    "addr:full":"720 N 35th St Seattle WA 98103",
    "addr:housenumber":"720",
    "addr:postcode":"98103",
    "addr:street":"N 35Th St",
    "iso:country":"US",
    "sg:address":"720 N 35th St",
    "sg:city":"Seattle",
    "sg:classifiers":[
        {
            "category":"Organizations",
            "subcategory":"Non-profit Organization",
            "type":"Services"
        }
    ],
    "sg:phone":"+1 206 675 1800",
    "sg:postcode":"98103",
    "sg:province":"WA",
    "wof:name":"Investment Forum",
    "wof:placetype":"venue"
},
  "geometry": {"coordinates":[-122.347527,47.650259],"type":"Point"}
}