{
  "type": "Feature",
  "properties": {
    "addr:full":"1390 Aspen Springs Ln Yakima WA 98903",
    "addr:housenumber":"1390",
    "addr:postcode":"98903",
    "addr:street":"Aspen Springs Ln",
    "iso:country":"US",
    "sg:address":"1390 Aspen Springs Ln",
    "sg:city":"Yakima",
    "sg:classifiers":[
        {
            "category":"Food & Beverages",
            "subcategory":"Specialty",
            "type":"Retail Goods"
        }
    ],
    "sg:phone":"+1 509 966 1282",
    "sg:postcode":"98903",
    "sg:province":"WA",
    "wof:name":"Dale & Marge Cook",
    "wof:placetype":"venue"
},
  "geometry": {"coordinates":[-120.902646,46.533565],"type":"Point"}
}