{
  "type": "Feature",
  "properties": {
    "addr:full":"3440 E Marginal Way S Seattle WA 98134",
    "addr:housenumber":"3440",
    "addr:postcode":"98134",
    "addr:street":"E Marginal Way S",
    "iso:country":"US",
    "sg:address":"3440 E Marginal Way S",
    "sg:city":"Seattle",
    "sg:classifiers":[
        {
            "category":"Organizations",
            "subcategory":"Labor Organization",
            "type":"Services"
        }
    ],
    "sg:phone":"+1 206 623 7461",
    "sg:postcode":"98134",
    "sg:province":"WA",
    "wof:name":"Ilba",
    "wof:placetype":"venue"
},
  "geometry": {"coordinates":[-122.339181,47.571726],"type":"Point"}
}