{
  "type": "Feature",
  "properties": {
    "addr:full":"366 Rock Island Rd East Wenatchee WA 98802",
    "addr:housenumber":"366",
    "addr:postcode":"98802",
    "addr:street":"Rock Island Rd",
    "iso:country":"US",
    "sg:address":"366 Rock Island Rd",
    "sg:city":"East Wenatchee",
    "sg:classifiers":[
        {
            "category":"Professional",
            "type":"Services"
        }
    ],
    "sg:phone":"+1 509 884 1781",
    "sg:postcode":"98802",
    "sg:province":"WA",
    "wof:name":"Andrew W Chambers",
    "wof:placetype":"venue"
},
  "geometry": {"coordinates":[-120.28523300000001,47.399637],"type":"Point"}
}