{
  "type": "Feature",
  "properties": {
    "addr:full":"760 Gilbert Ln Friday Harbor WA 98250",
    "addr:housenumber":"760",
    "addr:postcode":"98250",
    "addr:street":"Gilbert Ln",
    "iso:country":"US",
    "sg:address":"760 Gilbert Ln",
    "sg:city":"Friday Harbor",
    "sg:classifiers":[
        {
            "category":"Building & Trades",
            "subcategory":"Construction",
            "type":"Services"
        }
    ],
    "sg:phone":"+1 360 378 2712",
    "sg:postcode":"98250",
    "sg:province":"WA",
    "sg:tags":[
        "general",
        "contractor"
    ],
    "wof:name":"C E Crist Construction",
    "wof:placetype":"venue"
},
  "geometry": {"coordinates":[-123.041934,48.524924],"type":"Point"}
}