{
  "type": "Feature",
  "properties": {
    "addr:full":"1730 Minor Ave Ste 1600 Seattle WA 98101",
    "addr:housenumber":"1730",
    "addr:postcode":"98101",
    "addr:street":"Minor Ave Ste 1600",
    "iso:country":"US",
    "sg:address":"1730 Minor Ave Ste 1600",
    "sg:city":"Seattle",
    "sg:classifiers":[
        {
            "category":"Health Services",
            "subcategory":"Doctor",
            "type":"Services"
        },
        {
            "category":"Health Services",
            "subcategory":"Hospital",
            "type":"Services"
        }
    ],
    "sg:phone":"+1 206 287 4266",
    "sg:postcode":"98101",
    "sg:province":"WA",
    "sg:tags":[
        "nursing",
        "consultant",
        "medical",
        "practice",
        "home"
    ],
    "wof:name":"Diana Miglioretti",
    "wof:placetype":"venue"
},
  "geometry": {"coordinates":[-122.329809,47.61623],"type":"Point"}
}