{
  "type": "Feature",
  "properties": {
    "addr:full":"14310 NE 20th St Ste A Bellevue WA 98007",
    "addr:housenumber":"14310",
    "addr:postcode":"98007",
    "addr:street":"Ne 20Th St Ste A",
    "iso:country":"US",
    "sg:address":"14310 NE 20th St Ste A",
    "sg:city":"Bellevue",
    "sg:classifiers":[
        {
            "category":"Shopping",
            "subcategory":"Pets & Pet Supplies",
            "type":"Retail Goods"
        }
    ],
    "sg:phone":"+1 425 746 9782",
    "sg:postcode":"98007",
    "sg:province":"WA",
    "sg:tags":[
        "store"
    ],
    "wof:name":"Pets and Things",
    "wof:placetype":"venue"
},
  "geometry": {"coordinates":[-122.152,47.627998],"type":"Point"}
}