{
  "type": "Feature",
  "properties": {
    "iso:country":"US",
    "sg:address":"1111 S 274th Pl",
    "sg:city":"Seattle",
    "sg:classifiers":[
        {
            "category":"Building & Trades",
            "subcategory":"Construction",
            "type":"Services"
        }
    ],
    "sg:phone":"+1 206 941 3711",
    "sg:postcode":"98198",
    "sg:province":"WA",
    "sg:tags":[
        "hanging",
        "contractor"
    ],
    "wof:name":"New Life Painting",
    "wof:placetype":"venue"
},
  "geometry": {"coordinates":[-122.319835,47.354816],"type":"Point"}
}