{
  "type": "Feature",
  "properties": {
    "addr:full":"2914 Yelm Hwy SE Olympia WA 98501",
    "addr:housenumber":"2914",
    "addr:postcode":"98501",
    "addr:street":"Yelm Hwy Se",
    "iso:country":"US",
    "sg:address":"2914 Yelm Hwy SE",
    "sg:city":"Olympia",
    "sg:classifiers":[
        {
            "category":"Food & Beverages",
            "subcategory":"Groceries & Convenience Stores",
            "type":"Retail Goods"
        }
    ],
    "sg:phone":"+1 360 491 6860",
    "sg:postcode":"98501",
    "sg:province":"WA",
    "wof:name":"Chambers Prairie General Store",
    "wof:placetype":"venue"
},
  "geometry": {"coordinates":[-122.856785,47.001125],"type":"Point"}
}