{
  "type": "Feature",
  "properties": {
    "addr:full":"910 Koala Ave Omak WA 98841",
    "addr:housenumber":"910",
    "addr:postcode":"98841",
    "addr:street":"Koala Ave",
    "iso:country":"US",
    "sg:address":"910 Koala Ave",
    "sg:city":"Omak",
    "sg:classifiers":[
        {
            "category":"Restaurant",
            "type":"Food & Drink"
        }
    ],
    "sg:menulink":"http://www.allmenus.com/wa/omak/145285-subway/menu/",
    "sg:phone":"+1 509 826 6145",
    "sg:postcode":"98841",
    "sg:province":"WA",
    "sg:tags":[
        "american",
        "sandwich"
    ],
    "wof:name":"Subway",
    "wof:placetype":"venue"
},
  "geometry": {"coordinates":[-119.510659,48.420432],"type":"Point"}
}