{
  "type": "Feature",
  "properties": {
    "addr:full":"23116 49th Ave SE Bothell WA 98021",
    "addr:housenumber":"23116",
    "addr:postcode":"98021",
    "addr:street":"49Th Ave Se",
    "iso:country":"US",
    "sg:address":"23116 49th Ave SE",
    "sg:city":"Bothell",
    "sg:classifiers":[
        {
            "category":"Retail",
            "subcategory":"Repair Shop",
            "type":"Services"
        }
    ],
    "sg:phone":"+1 425 485 5842",
    "sg:postcode":"98021",
    "sg:province":"WA",
    "wof:name":"Jays MBL Vinyl Lea Repr Serv",
    "wof:placetype":"venue"
},
  "geometry": {"coordinates":[-122.167569,47.787019],"type":"Point"}
}