{
  "type": "Feature",
  "properties": {
    "addr:full":"240 SW First St Stevenson WA 98648",
    "addr:housenumber":"240",
    "addr:postcode":"98648",
    "addr:street":"Sw First St",
    "iso:country":"US",
    "sg:address":"240 SW First St",
    "sg:city":"Stevenson",
    "sg:classifiers":[
        {
            "category":"Restaurant",
            "type":"Food & Drink"
        },
        {
            "category":"Food & Beverages",
            "subcategory":"Liquor & Beverages",
            "type":"Retail Goods"
        }
    ],
    "sg:phone":"+1 509 427 5520",
    "sg:postcode":"98648",
    "sg:province":"WA",
    "sg:tags":[
        "beer",
        "spirit",
        "wine"
    ],
    "sg:website":"www.walkingmanbrewing.com",
    "wof:name":"Walking Man Brewing",
    "wof:placetype":"venue"
},
  "geometry": {"coordinates":[-121.884682,45.692204],"type":"Point"}
}