{
  "type": "Feature",
  "properties": {
    "addr:full":"2508 6th Ave W Seattle WA 98119",
    "addr:housenumber":"2508",
    "addr:postcode":"98119",
    "addr:street":"6Th Ave W",
    "iso:country":"US",
    "sg:address":"2508 6th Ave W",
    "sg:city":"Seattle",
    "sg:classifiers":[
        {
            "category":"Professional",
            "subcategory":"Art Services",
            "type":"Services"
        }
    ],
    "sg:phone":"+1 206 285 5762",
    "sg:postcode":"98119",
    "sg:province":"WA",
    "sg:tags":[
        "photography",
        "commercial"
    ],
    "wof:name":"Gary Davis Photography",
    "wof:placetype":"venue"
},
  "geometry": {"coordinates":[-122.364845,47.64179],"type":"Point"}
}