{
  "type": "Feature",
  "properties": {
    "addr:full":"8611 NE Ward Rd Vancouver WA 98682",
    "addr:housenumber":"8611",
    "addr:postcode":"98682",
    "addr:street":"Ne Ward Rd",
    "iso:country":"US",
    "sg:address":"8611 NE Ward Rd",
    "sg:city":"Vancouver",
    "sg:classifiers":[
        {
            "category":"Fast Food",
            "type":"Food & Drink"
        },
        {
            "category":"Restaurant",
            "type":"Food & Drink"
        }
    ],
    "sg:phone":"+1 360 567 2661",
    "sg:postcode":"98682",
    "sg:province":"WA",
    "sg:tags":[
        "take",
        "pizza"
    ],
    "sg:website":"http://www.papamurphys.com",
    "wof:name":"Papa Murphy's",
    "wof:placetype":"venue"
},
  "geometry": {"coordinates":[-122.50614899999999,45.684953],"type":"Point"}
}