{
  "type": "Feature",
  "properties": {
    "addr:full":"466 Cresview Ln Stanwood WA 98282",
    "addr:housenumber":"466",
    "addr:postcode":"98282",
    "addr:street":"Cresview Ln",
    "iso:country":"US",
    "sg:address":"466 Cresview Ln",
    "sg:city":"Stanwood",
    "sg:classifiers":[
        {
            "category":"Insurance",
            "subcategory":"Insurance Agent",
            "type":"Services"
        }
    ],
    "sg:phone":"+1 360 629 6441",
    "sg:postcode":"98282",
    "sg:province":"WA",
    "wof:name":"Cresap Insurance",
    "wof:placetype":"venue"
},
  "geometry": {"coordinates":[-122.410679,48.228012],"type":"Point"}
}