{
  "type": "Feature",
  "properties": {
    "addr:full":"1620 Port Dr Burlington WA 98233",
    "addr:housenumber":"1620",
    "addr:postcode":"98233",
    "addr:street":"Port Dr",
    "iso:country":"US",
    "sg:address":"1620 Port Dr",
    "sg:city":"Burlington",
    "sg:classifiers":[
        {
            "category":"Freight",
            "type":"Transportation"
        }
    ],
    "sg:phone":"+1 800 222 8333",
    "sg:postcode":"98233",
    "sg:province":"WA",
    "sg:tags":[
        "courier"
    ],
    "wof:name":"United Parcel Service Ameri",
    "wof:placetype":"venue"
},
  "geometry": {"coordinates":[-122.32744,48.455221],"type":"Point"}
}