{
  "type": "Feature",
  "properties": {
    "addr:full":"551 Windy Ln Yakima WA 98903",
    "addr:housenumber":"551",
    "addr:postcode":"98903",
    "addr:street":"Windy Ln",
    "iso:country":"US",
    "sg:address":"551 Windy Ln",
    "sg:city":"Yakima",
    "sg:classifiers":[
        {
            "category":"Manufacturing",
            "subcategory":"Apparel",
            "type":"Manufacturing & Wholesale Goods"
        }
    ],
    "sg:phone":"+1 509 966 0681",
    "sg:postcode":"98903",
    "sg:province":"WA",
    "sg:tags":[
        "household",
        "furnishing",
        "mfg"
    ],
    "wof:name":"Country Quilter",
    "wof:placetype":"venue"
},
  "geometry": {"coordinates":[-120.834524,46.54832],"type":"Point"}
}