{
  "type": "Feature",
  "properties": {
    "addr:full":"5520 N Maple St Spokane WA 99205",
    "addr:housenumber":"5520",
    "addr:postcode":"99205",
    "addr:street":"N Maple St",
    "iso:country":"US",
    "sg:address":"5520 N Maple St",
    "sg:city":"Spokane",
    "sg:classifiers":[
        {
            "category":"Food & Beverages",
            "subcategory":"Specialty",
            "type":"Retail Goods"
        },
        {
            "category":"Restaurant",
            "type":"Food & Drink"
        }
    ],
    "sg:phone":"+1 509 327 9091",
    "sg:postcode":"99205",
    "sg:province":"WA",
    "sg:tags":[
        "eating",
        "bars",
        "espresso"
    ],
    "wof:name":"Field of Beans",
    "wof:placetype":"venue"
},
  "geometry": {"coordinates":[-117.43499799999999,47.708812],"type":"Point"}
}