{
  "type": "Feature",
  "properties": {
    "addr:full":"900 4th Ave Seattle WA 98164",
    "addr:housenumber":"900",
    "addr:postcode":"98164",
    "addr:street":"4Th Ave",
    "iso:country":"US",
    "sg:address":"900 4th Ave",
    "sg:city":"Seattle",
    "sg:classifiers":[
        {
            "category":"Wholesale",
            "subcategory":"Durable Goods & Equipment",
            "type":"Manufacturing & Wholesale Goods"
        }
    ],
    "sg:phone":"+1 206 623 3764",
    "sg:postcode":"98164",
    "sg:province":"WA",
    "sg:tags":[
        "exporter"
    ],
    "wof:name":"Itochu International Inc",
    "wof:placetype":"venue"
},
  "geometry": {"coordinates":[-122.332911,47.606086],"type":"Point"}
}