{
  "type": "Feature",
  "properties": {
    "addr:full":"5620 Rainier Ave Seattle WA 98118",
    "addr:housenumber":"5620",
    "addr:postcode":"98118",
    "addr:street":"Rainier Ave",
    "iso:country":"US",
    "sg:address":"5620 Rainier Ave",
    "sg:city":"Seattle",
    "sg:classifiers":[
        {
            "category":"Health Services",
            "subcategory":"Health Practitioner",
            "type":"Services"
        }
    ],
    "sg:phone":"+1 206 722 2205",
    "sg:postcode":"98118",
    "sg:province":"WA",
    "sg:tags":[
        "therapist",
        "physical"
    ],
    "wof:name":"Columbia Physical Therapy Svc",
    "wof:placetype":"venue"
},
  "geometry": {"coordinates":[-122.277652,47.551352],"type":"Point"}
}