{
  "type": "Feature",
  "properties": {
    "iso:country":"US",
    "sg:address":"5550 Tara Dr",
    "sg:city":"Freeland",
    "sg:classifiers":[
        {
            "category":"Professional",
            "subcategory":"Business Services",
            "type":"Services"
        }
    ],
    "sg:phone":"+1 360 331 0872",
    "sg:postcode":"98249",
    "sg:province":"WA",
    "wof:name":"Gail A Miller Contract Design",
    "wof:placetype":"venue"
},
  "geometry": {"coordinates":[-122.559043,48.008313],"type":"Point"}
}