{
  "type": "Feature",
  "properties": {
    "addr:full":"2054 NW 56th St Seattle WA 98107",
    "addr:housenumber":"2054",
    "addr:postcode":"98107",
    "addr:street":"Nw 56Th St",
    "iso:country":"US",
    "sg:address":"2054 NW 56th St",
    "sg:city":"Seattle",
    "sg:classifiers":[
        {
            "category":"Banks & Credit Unions",
            "subcategory":"Bank",
            "type":"Services"
        }
    ],
    "sg:phone":"+1 612 973 1111",
    "sg:postcode":"98107",
    "sg:province":"WA",
    "sg:tags":[
        "national",
        "commercial"
    ],
    "wof:name":"US Bank",
    "wof:placetype":"venue"
},
  "geometry": {"coordinates":[-122.384263,47.669526],"type":"Point"}
}