{
  "type": "Feature",
  "properties": {
    "addr:full":"1265 S Main St Seattle WA 98144",
    "addr:housenumber":"1265",
    "addr:postcode":"98144",
    "addr:street":"S Main St",
    "iso:country":"US",
    "sg:address":"1265 S Main St",
    "sg:city":"Seattle",
    "sg:classifiers":[
        {
            "category":"Personal",
            "subcategory":"Beauty Salon",
            "type":"Services"
        }
    ],
    "sg:phone":"+1 206 325 0388",
    "sg:postcode":"98144",
    "sg:province":"WA",
    "sg:tags":[
        "shop"
    ],
    "wof:name":"Nile Ladies Salon",
    "wof:placetype":"venue"
},
  "geometry": {"coordinates":[-122.315291,47.599931],"type":"Point"}
}