{
  "type": "Feature",
  "properties": {
    "addr:full":"707 N Sheridan Ave Tacoma WA 98403",
    "addr:housenumber":"707",
    "addr:postcode":"98403",
    "addr:street":"N Sheridan Ave",
    "iso:country":"US",
    "sg:address":"707 N Sheridan Ave",
    "sg:city":"Tacoma",
    "sg:classifiers":[
        {
            "category":"Social Services",
            "type":"Services"
        },
        {
            "category":"Professional",
            "subcategory":"Employment Agencies",
            "type":"Services"
        }
    ],
    "sg:phone":"+1 253 572 7700",
    "sg:postcode":"98403",
    "sg:province":"WA",
    "sg:tags":[
        "workers'",
        "placement",
        "volunteer"
    ],
    "wof:name":"Dugan Foundation",
    "wof:placetype":"venue"
},
  "geometry": {"coordinates":[-122.46189099999999,47.260104],"type":"Point"}
}