{
  "type": "Feature",
  "properties": {
    "addr:full":"12121 SE 45th Pl Bellevue WA 98006",
    "addr:postcode":"12121;98006",
    "addr:street":"Se 45Th Pl",
    "iso:country":"US",
    "sg:address":"12121 SE 45th Pl",
    "sg:city":"Bellevue",
    "sg:classifiers":[
        {
            "category":"Building & Trades",
            "subcategory":"Electrical",
            "type":"Services"
        }
    ],
    "sg:phone":"+1 425 746 1667",
    "sg:postcode":"98006",
    "sg:province":"WA",
    "sg:tags":[
        "electric",
        "contractor"
    ],
    "wof:name":"Bellevue Electric",
    "wof:placetype":"venue"
},
  "geometry": {"coordinates":[-122.176715,47.567648],"type":"Point"}
}