{
  "type": "Feature",
  "properties": {
    "addr:full":"5443 S Tacoma Way Tacoma WA 98409",
    "addr:housenumber":"5443",
    "addr:postcode":"98409",
    "addr:street":"S Tacoma Way",
    "iso:country":"US",
    "sg:address":"5443 S Tacoma Way",
    "sg:city":"Tacoma",
    "sg:classifiers":[
        {
            "category":"Bars & Pubs",
            "type":"Food & Drink"
        }
    ],
    "sg:phone":"+1 253 476 1421",
    "sg:postcode":"98409",
    "sg:province":"WA",
    "wof:name":"Dawson Tavern",
    "wof:placetype":"venue"
},
  "geometry": {"coordinates":[-122.483649,47.206608],"type":"Point"}
}