{
  "type": "Feature",
  "properties": {
    "addr:full":"2303 25th Ave E Seattle WA 98112",
    "addr:housenumber":"2303",
    "addr:postcode":"98112",
    "addr:street":"25Th Ave E",
    "iso:country":"US",
    "sg:address":"2303 25th Ave E",
    "sg:city":"Seattle",
    "sg:classifiers":[
        {
            "category":"Social Services",
            "subcategory":"Child Care",
            "type":"Services"
        }
    ],
    "sg:phone":"+1 206 322 4496",
    "sg:postcode":"98112",
    "sg:province":"WA",
    "sg:tags":[
        "center",
        "preschool",
        "day"
    ],
    "wof:name":"Cottage Preschool & Day Care",
    "wof:placetype":"venue"
},
  "geometry": {"coordinates":[-122.30042,47.640235],"type":"Point"}
}