{
  "type": "Feature",
  "properties": {
    "addr:full":"722 NE 45th St Seattle WA 98105",
    "addr:housenumber":"722",
    "addr:postcode":"98105",
    "addr:street":"Ne 45Th St",
    "iso:country":"US",
    "sg:address":"722 NE 45th St",
    "sg:city":"Seattle",
    "sg:classifiers":[
        {
            "category":"Bars & Pubs",
            "subcategory":"Lounge",
            "type":"Food & Drink"
        },
        {
            "category":"Restaurant",
            "type":"Food & Drink"
        }
    ],
    "sg:phone":"+1 206 774 9296",
    "sg:postcode":"98105",
    "sg:province":"WA",
    "sg:tags":[
        "traditional",
        "american"
    ],
    "sg:website":"www.fusionultralounge.com",
    "wof:name":"Fusion Ultra Lounge",
    "wof:placetype":"venue"
},
  "geometry": {"coordinates":[-122.319885,47.661335],"type":"Point"}
}