{
  "type": "Feature",
  "properties": {
    "addr:full":"1940 116th Ave NE Bellevue WA 98004",
    "addr:housenumber":"1940",
    "addr:postcode":"98004",
    "addr:street":"116Th Ave Ne",
    "iso:country":"US",
    "sg:address":"1940 116th Ave NE",
    "sg:city":"Bellevue",
    "sg:classifiers":[
        {
            "category":"Building & Trades",
            "subcategory":"Construction",
            "type":"Services"
        }
    ],
    "sg:phone":"+1 425 451 7321",
    "sg:postcode":"98004",
    "sg:province":"WA",
    "sg:tags":[
        "general",
        "contractor"
    ],
    "wof:name":"City View Contractors",
    "wof:placetype":"venue"
},
  "geometry": {"coordinates":[-122.18564499999999,47.628882],"type":"Point"}
}