{
  "type": "Feature",
  "properties": {
    "addr:full":"11525 State Ave Marysville WA 98271",
    "addr:housenumber":"11525",
    "addr:postcode":"98271",
    "addr:street":"State Ave",
    "iso:country":"US",
    "sg:address":"11525 State Ave",
    "sg:city":"Marysville",
    "sg:classifiers":[
        {
            "category":"Banks & Credit Unions",
            "subcategory":"Bank",
            "type":"Services"
        }
    ],
    "sg:phone":"+1 360 653 1251",
    "sg:postcode":"98271",
    "sg:province":"WA",
    "wof:name":"First Security Bank Of WA",
    "wof:placetype":"venue"
},
  "geometry": {"coordinates":[-122.174588,48.098236],"type":"Point"}
}