{
  "type": "Feature",
  "properties": {
    "addr:full":"5954 31st Avenue SW Seattle WA 98126",
    "addr:housenumber":"5954",
    "addr:postcode":"98126",
    "addr:street":"31St Avenue Sw",
    "iso:country":"US",
    "sg:address":"5954 31st Avenue SW",
    "sg:city":"Seattle",
    "sg:classifiers":[
        {
            "category":"Professional",
            "subcategory":"Art Services",
            "type":"Services"
        }
    ],
    "sg:phone":"+1 206 324 9118",
    "sg:postcode":"98126",
    "sg:province":"WA",
    "sg:tags":[
        "framing"
    ],
    "sg:website":"www.kayroodframer.com",
    "wof:name":"Kay Rood Framing",
    "wof:placetype":"venue"
},
  "geometry": {"coordinates":[-122.371538,47.548825],"type":"Point"}
}