{
  "type": "Feature",
  "properties": {
    "addr:full":"14479 Woodinville Redmond Rd NE Woodinville WA 98072",
    "addr:housenumber":"14479",
    "addr:postcode":"98072",
    "addr:street":"Woodinville Redmond Rd Ne",
    "iso:country":"US",
    "sg:address":"14479 Woodinville Redmond Rd NE",
    "sg:city":"Woodinville",
    "sg:classifiers":[
        {
            "category":"Home & Garden",
            "subcategory":"Furniture",
            "type":"Retail Goods"
        }
    ],
    "sg:phone":"+1 425 481 7081",
    "sg:postcode":"98072",
    "sg:province":"WA",
    "wof:name":"Rices Home Details",
    "wof:placetype":"venue"
},
  "geometry": {"coordinates":[-122.141476,47.731945],"type":"Point"}
}