{
  "type": "Feature",
  "properties": {
    "addr:full":"406 Yauger Way SW Olympia WA 98502",
    "addr:housenumber":"406",
    "addr:postcode":"98502",
    "addr:street":"Yauger Way Sw",
    "iso:country":"US",
    "sg:address":"406 Yauger Way SW",
    "sg:city":"Olympia",
    "sg:classifiers":[
        {
            "category":"Health Services",
            "subcategory":"Clinic",
            "type":"Services"
        }
    ],
    "sg:phone":"+1 360 357 2569",
    "sg:postcode":"98502",
    "sg:province":"WA",
    "wof:name":"Bone Density Center",
    "wof:placetype":"venue"
},
  "geometry": {"coordinates":[-122.949729,47.046755],"type":"Point"}
}