{
  "type": "Feature",
  "properties": {
    "addr:full":"10436 SE 19th St Bellevue WA 98004",
    "addr:postcode":"10436;98004",
    "addr:street":"Se 19Th St",
    "iso:country":"US",
    "sg:address":"10436 SE 19th St",
    "sg:city":"Bellevue",
    "sg:classifiers":[
        {
            "category":"Recreation",
            "subcategory":"Arcade",
            "type":"Entertainment"
        }
    ],
    "sg:phone":"+1 425 785 6834",
    "sg:postcode":"98004",
    "sg:province":"WA",
    "sg:tags":[
        "device",
        "operator",
        "amusement"
    ],
    "wof:name":"Replay Amusements Inc",
    "wof:placetype":"venue"
},
  "geometry": {"coordinates":[-122.19738700000001,47.59355],"type":"Point"}
}