{
  "type": "Feature",
  "properties": {
    "iso:country":"US",
    "sg:address":"3003 77th Ave SE",
    "sg:city":"Mercer Island",
    "sg:classifiers":[
        {
            "category":"Insurance",
            "subcategory":"Insurance Agent",
            "type":"Services"
        },
        {
            "category":"Insurance",
            "subcategory":"Life Insurance",
            "type":"Services"
        }
    ],
    "sg:phone":"+1 206 232 8400",
    "sg:postcode":"98040",
    "sg:province":"WA",
    "sg:tags":[
        "carrier"
    ],
    "sg:website":"www.farmerslife.com",
    "wof:name":"Farmers New World Life Ins Co",
    "wof:placetype":"venue"
},
  "geometry": {"coordinates":[-122.235128,47.582783],"type":"Point"}
}