{
  "type": "Feature",
  "properties": {
    "addr:full":"6346 Seward Park Ave S Seattle WA 98118",
    "addr:housenumber":"6346",
    "addr:postcode":"98118",
    "addr:street":"Seward Park Ave S",
    "iso:country":"US",
    "sg:address":"6346 Seward Park Ave S",
    "sg:city":"Seattle",
    "sg:classifiers":[
        {
            "category":"Organizations",
            "subcategory":"Membership Organization",
            "type":"Services"
        }
    ],
    "sg:phone":"+1 206 722 1653",
    "sg:postcode":"98118",
    "sg:province":"WA",
    "wof:name":"Friends of Kollel Rabbi",
    "wof:placetype":"venue"
},
  "geometry": {"coordinates":[-122.263195,47.545463],"type":"Point"}
}