{
  "type": "Feature",
  "properties": {
    "addr:full":"7601 25th Ave E Tacoma WA 98404",
    "addr:housenumber":"7601",
    "addr:postcode":"98404",
    "addr:street":"25Th Ave E",
    "iso:country":"US",
    "sg:address":"7601 25th Ave E",
    "sg:city":"Tacoma",
    "sg:classifiers":[
        {
            "category":"Professional",
            "subcategory":"Accounting & Tax Preparation",
            "type":"Services"
        }
    ],
    "sg:phone":"+1 253 537 2572",
    "sg:postcode":"98404",
    "sg:province":"WA",
    "wof:name":"Shelley R Wirkkala Inc",
    "wof:placetype":"venue"
},
  "geometry": {"coordinates":[-122.396182,47.191717],"type":"Point"}
}