{
  "type": "Feature",
  "properties": {
    "addr:full":"109 S Mission St Wenatchee WA 98801",
    "addr:housenumber":"109",
    "addr:postcode":"98801",
    "addr:street":"S;St",
    "iso:country":"US",
    "sg:address":"109 S Mission St",
    "sg:city":"Wenatchee",
    "sg:classifiers":[
        {
            "category":"Personal",
            "subcategory":"Barber",
            "type":"Services"
        }
    ],
    "sg:phone":"+1 509 668 0118",
    "sg:postcode":"98801",
    "sg:province":"WA",
    "sg:tags":[
        "shop"
    ],
    "wof:name":"Ricks Barbering Service",
    "wof:placetype":"venue"
},
  "geometry": {"coordinates":[-120.31062799999999,47.42185],"type":"Point"}
}