{
  "type": "Feature",
  "properties": {
    "addr:full":"21911 76th Ave W Ste 201 Edmonds WA 98026",
    "addr:housenumber":"21911",
    "addr:postcode":"98026",
    "addr:street":"76Th Ave W Ste 201",
    "iso:country":"US",
    "sg:address":"21911 76th Ave W Ste 201",
    "sg:city":"Edmonds",
    "sg:classifiers":[
        {
            "category":"Health Services",
            "subcategory":"Dentist",
            "type":"Services"
        }
    ],
    "sg:phone":"+1 425 744 0598",
    "sg:postcode":"98026",
    "sg:province":"WA",
    "sg:tags":[
        "implant",
        "dentistry",
        "dentists-cosmetic",
        "dentists-implantology"
    ],
    "sg:website":"http://www.dryong.com",
    "wof:name":"Custom Dental Care",
    "wof:placetype":"venue"
},
  "geometry": {"coordinates":[-122.335639,47.800486],"type":"Point"}
}