{
  "type": "Feature",
  "properties": {
    "addr:full":"40704 236th Ave SE Enumclaw WA 98022",
    "addr:housenumber":"40704",
    "addr:postcode":"98022",
    "addr:street":"236Th Ave Se",
    "iso:country":"US",
    "sg:address":"40704 236th Ave SE",
    "sg:city":"Enumclaw",
    "sg:classifiers":[
        {
            "category":"Professional",
            "subcategory":"Detective & Security Services",
            "type":"Services"
        }
    ],
    "sg:phone":"+1 360 825 7999",
    "sg:postcode":"98022",
    "sg:province":"WA",
    "sg:tags":[
        "information",
        "bureau"
    ],
    "wof:name":"Kimberly Trojcak",
    "wof:placetype":"venue"
},
  "geometry": {"coordinates":[-122.02692500000001,47.2364],"type":"Point"}
}