{
  "type": "Feature",
  "properties": {
    "addr:full":"6046 W. Lake Sammamish Parkway NE Redmond WA 98052",
    "addr:housenumber":"6046",
    "addr:postcode":"98052",
    "addr:street":"W. Lake Sammamish Parkway Ne",
    "iso:country":"US",
    "sg:address":"6046 W. Lake Sammamish Parkway NE",
    "sg:city":"Redmond",
    "sg:classifiers":[
        {
            "category":"Park",
            "type":"Public Place"
        }
    ],
    "sg:phone":"+1 206 205 3661",
    "sg:postcode":"98052",
    "sg:province":"WA",
    "sg:website":"www.metrokc.gov/parks/rentals/po...",
    "wof:name":"Marymoor Park - Off leash",
    "wof:placetype":"venue"
},
  "geometry": {"coordinates":[-122.12599899999999,47.662701],"type":"Point"}
}