{
  "type": "Feature",
  "properties": {
    "addr:full":"2298 State Rte 109 Hoquiam WA 98550",
    "addr:housenumber":"2298",
    "addr:postcode":"98550",
    "addr:street":"State Rte 109",
    "iso:country":"US",
    "sg:address":"2298 State Rte 109",
    "sg:city":"Hoquiam",
    "sg:classifiers":[
        {
            "category":"Retail",
            "subcategory":"Auto Repair",
            "type":"Services"
        }
    ],
    "sg:phone":"+1 360 289 2012",
    "sg:postcode":"98550",
    "sg:province":"WA",
    "sg:tags":[
        "wrecker"
    ],
    "wof:name":"North Beach Towing",
    "wof:placetype":"venue"
},
  "geometry": {"coordinates":[-124.155168,47.043352],"type":"Point"}
}