{
  "type": "Feature",
  "properties": {
    "addr:full":"115 W Magnolia St Bellingham WA 98225",
    "addr:housenumber":"115",
    "addr:postcode":"98225",
    "addr:street":"W Magnolia St",
    "iso:country":"US",
    "sg:address":"115 W Magnolia St",
    "sg:city":"Bellingham",
    "sg:classifiers":[
        {
            "category":"Professional",
            "type":"Services"
        }
    ],
    "sg:phone":"+1 360 738 8188",
    "sg:postcode":"98225",
    "sg:province":"WA",
    "sg:tags":[
        "attorney",
        "law",
        "malpractice"
    ],
    "wof:name":"Wlsi Of Washington",
    "wof:placetype":"venue"
},
  "geometry": {"coordinates":[-122.47781500000001,48.750855],"type":"Point"}
}