{
  "type": "Feature",
  "properties": {
    "addr:full":"12441 NE 162nd St Woodinville WA 98072",
    "addr:housenumber":"12441",
    "addr:postcode":"98072",
    "addr:street":"Ne 162Nd St",
    "iso:country":"US",
    "sg:address":"12441 NE 162nd St",
    "sg:city":"Woodinville",
    "sg:classifiers":[
        {
            "category":"Shopping",
            "subcategory":"Gifts & Souvenirs",
            "type":"Retail Goods"
        }
    ],
    "sg:phone":"+1 425 481 2217",
    "sg:postcode":"98072",
    "sg:province":"WA",
    "wof:name":"Haute Accessories",
    "wof:placetype":"venue"
},
  "geometry": {"coordinates":[-122.174814,47.745219],"type":"Point"}
}