{
  "type": "Feature",
  "properties": {
    "addr:full":"20311 52nd Ave W Lynnwood WA 98036",
    "addr:housenumber":"20311",
    "addr:postcode":"98036",
    "addr:street":"52Nd Ave W",
    "iso:country":"US",
    "sg:address":"20311 52nd Ave W",
    "sg:city":"Lynnwood",
    "sg:classifiers":[
        {
            "category":"Government",
            "subcategory":"Office",
            "type":"Public Place"
        }
    ],
    "sg:phone":"+1 425 673 3180",
    "sg:postcode":"98036",
    "sg:province":"WA",
    "sg:tags":[
        "social"
    ],
    "wof:name":"Vocational Rehabilitation",
    "wof:placetype":"venue"
},
  "geometry": {"coordinates":[-122.303122,47.814146],"type":"Point"}
}