{
  "type": "Feature",
  "properties": {
    "addr:full":"221 Park St Wenatchee WA 98801",
    "addr:housenumber":"221",
    "addr:postcode":"98801",
    "addr:street":"Park St",
    "iso:country":"US",
    "sg:address":"221 Park St",
    "sg:city":"Wenatchee",
    "sg:classifiers":[
        {
            "category":"Building & Trades",
            "subcategory":"Plumbing",
            "type":"Services"
        }
    ],
    "sg:phone":"+1 509 662 6846",
    "sg:postcode":"98801",
    "sg:province":"WA",
    "sg:tags":[
        "air",
        "heating",
        "contractor",
        "system",
        "conditioning"
    ],
    "wof:name":"Alpine Aire Inc",
    "wof:placetype":"venue"
},
  "geometry": {"coordinates":[-120.301911,47.410385],"type":"Point"}
}