{
  "type": "Feature",
  "properties": {
    "addr:full":"17909 6th Ave W Bothell WA 98012",
    "addr:housenumber":"17909",
    "addr:postcode":"98012",
    "addr:street":"6Th Ave W",
    "iso:country":"US",
    "sg:address":"17909 6th Ave W",
    "sg:city":"Bothell",
    "sg:classifiers":[
        {
            "category":"Building & Trades",
            "subcategory":"Construction",
            "type":"Services"
        }
    ],
    "sg:phone":"+1 425 745 4701",
    "sg:postcode":"98012",
    "sg:province":"WA",
    "sg:tags":[
        "house"
    ],
    "wof:name":"Forrest Dill Construction Serv",
    "wof:placetype":"venue"
},
  "geometry": {"coordinates":[-122.241716,47.83587],"type":"Point"}
}