{
  "type": "Feature",
  "properties": {
    "addr:full":"2412 7th Ave W Ste 101 Seattle WA 98119",
    "addr:housenumber":"2412",
    "addr:postcode":"98119",
    "addr:street":"7Th Ave W Ste 101",
    "iso:country":"US",
    "sg:address":"2412 7th Ave W Ste 101",
    "sg:city":"Seattle",
    "sg:classifiers":[
        {
            "category":"Personal",
            "subcategory":"Nail Salon",
            "type":"Services"
        }
    ],
    "sg:phone":"+1 206 691 9831",
    "sg:postcode":"98119",
    "sg:province":"WA",
    "sg:website":"http://www.toothandnail.com",
    "wof:name":"Tooth & Nail Record Co",
    "wof:placetype":"venue"
},
  "geometry": {"coordinates":[-122.36630599999999,47.639719],"type":"Point"}
}