{
  "type": "Feature",
  "properties": {
    "addr:full":"21007 72nd Ave S Kent WA 98032",
    "addr:housenumber":"21007",
    "addr:postcode":"98032",
    "addr:street":"72Nd Ave S",
    "iso:country":"US",
    "sg:address":"21007 72nd Ave S",
    "sg:city":"Kent",
    "sg:classifiers":[
        {
            "category":"Wholesale",
            "subcategory":"Groceries",
            "type":"Manufacturing & Wholesale Goods"
        }
    ],
    "sg:phone":"+1 253 872 6934",
    "sg:postcode":"98032",
    "sg:province":"WA",
    "sg:tags":[
        "confectionery",
        "candy"
    ],
    "sg:website":"www.consolidatedfoodsinc.com",
    "wof:name":"Consolidated Foods Inc",
    "wof:placetype":"venue"
},
  "geometry": {"coordinates":[-122.244153,47.413936],"type":"Point"}
}