{
  "type": "Feature",
  "properties": {
    "addr:full":"15715 Main St NE Suite 105 Duvall WA 98019",
    "addr:housenumber":"15715",
    "addr:postcode":"98019",
    "addr:street":"Main St Ne Suite 105",
    "iso:country":"US",
    "sg:address":"15715 Main St NE Suite 105",
    "sg:city":"Duvall",
    "sg:classifiers":[
        {
            "category":"Farming",
            "subcategory":"Fish & Marine Products",
            "type":"Manufacturing & Wholesale Goods"
        }
    ],
    "sg:phone":"+1 425 788 2590",
    "sg:postcode":"98019",
    "sg:province":"WA",
    "sg:tags":[
        "picture",
        "framing"
    ],
    "sg:website":"http://www.LaurelLeafFraming.com",
    "wof:name":"Laurel Leaf Framing",
    "wof:placetype":"venue"
},
  "geometry": {"coordinates":[-121.985979,47.741741],"type":"Point"}
}