{
  "type": "Feature",
  "properties": {
    "addr:full":"1372 W Axton Rd Ferndale WA 98248",
    "addr:housenumber":"1372",
    "addr:postcode":"98248",
    "addr:street":"W Axton Rd",
    "iso:country":"US",
    "sg:address":"1372 W Axton Rd",
    "sg:city":"Ferndale",
    "sg:classifiers":[
        {
            "category":"Retail",
            "subcategory":"Auto Repair",
            "type":"Services"
        }
    ],
    "sg:phone":"+1 360 384 5040",
    "sg:postcode":"98248",
    "sg:province":"WA",
    "sg:tags":[
        "body",
        "automobile",
        "painting"
    ],
    "wof:name":"Fayettes Country Auto Body",
    "wof:placetype":"venue"
},
  "geometry": {"coordinates":[-122.55511199999999,48.846623],"type":"Point"}
}