{
  "type": "Feature",
  "properties": {
    "addr:full":"24915 104th Ave SE Kent WA 98030",
    "addr:housenumber":"24915",
    "addr:postcode":"98030",
    "addr:street":"104Th Ave Se",
    "iso:country":"US",
    "sg:address":"24915 104th Ave SE",
    "sg:city":"Kent",
    "sg:classifiers":[
        {
            "category":"Real Estate",
            "subcategory":"Real Estate Agent",
            "type":"Services"
        }
    ],
    "sg:phone":"+1 253 854 3880",
    "sg:postcode":"98030",
    "sg:province":"WA",
    "wof:name":"Gary Wagner Real Estate",
    "wof:placetype":"venue"
},
  "geometry": {"coordinates":[-122.202434,47.379128],"type":"Point"}
}