{
  "type": "Feature",
  "properties": {
    "addr:full":"12301 NE 10th Pl Bellevue WA 98005",
    "addr:housenumber":"12301",
    "addr:postcode":"98005",
    "addr:street":"Ne 10Th Pl",
    "iso:country":"US",
    "sg:address":"12301 NE 10th Pl",
    "sg:city":"Bellevue",
    "sg:classifiers":[
        {
            "category":"Health Services",
            "subcategory":"Doctor",
            "type":"Services"
        }
    ],
    "sg:phone":"+1 425 454 2883",
    "sg:postcode":"98005",
    "sg:province":"WA",
    "wof:name":"Kim Helen MD",
    "wof:placetype":"venue"
},
  "geometry": {"coordinates":[-122.17594699999999,47.619131],"type":"Point"}
}