{
  "type": "Feature",
  "properties": {
    "iso:country":"US",
    "sg:address":"921 2nd St",
    "sg:city":"Mukilteo",
    "sg:classifiers":[
        {
            "category":"Building & Trades",
            "subcategory":"Construction",
            "type":"Services"
        }
    ],
    "sg:phone":"+1 425 347 7297",
    "sg:postcode":"98275",
    "sg:province":"WA",
    "sg:tags":[
        "hanging",
        "contractor"
    ],
    "wof:name":"Tjr Four Seasons Painting & MA",
    "wof:placetype":"venue"
},
  "geometry": {"coordinates":[-122.297389,47.948226],"type":"Point"}
}