{
  "type": "Feature",
  "properties": {
    "addr:full":"27215 76th Ave E Graham WA 98338",
    "addr:housenumber":"27215",
    "addr:postcode":"98338",
    "addr:street":"76Th Ave E",
    "iso:country":"US",
    "sg:address":"27215 76th Ave E",
    "sg:city":"Graham",
    "sg:classifiers":[
        {
            "category":"Social Services",
            "subcategory":"Adult Care",
            "type":"Services"
        }
    ],
    "sg:phone":"+1 253 846 5425",
    "sg:postcode":"98338",
    "sg:province":"WA",
    "sg:tags":[
        "home",
        "residential"
    ],
    "wof:name":"Heavenly Acres AFH",
    "wof:placetype":"venue"
},
  "geometry": {"coordinates":[-122.331093,47.009536],"type":"Point"}
}