{
  "type": "Feature",
  "properties": {
    "addr:full":"341 Meridian Dr Kelso WA 98626",
    "addr:housenumber":"341",
    "addr:postcode":"98626",
    "addr:street":"Meridian Dr",
    "iso:country":"US",
    "sg:address":"341 Meridian Dr",
    "sg:city":"Kelso",
    "sg:classifiers":[
        {
            "category":"Banks & Credit Unions",
            "subcategory":"Bank",
            "type":"Services"
        }
    ],
    "sg:phone":"+1 360 751 4528",
    "sg:postcode":"98626",
    "sg:province":"WA",
    "sg:tags":[
        "loan",
        "broker"
    ],
    "wof:name":"Washington Home Loans",
    "wof:placetype":"venue"
},
  "geometry": {"coordinates":[-122.847852,46.121489],"type":"Point"}
}