{
  "type": "Feature",
  "properties": {
    "addr:full":"26296 Twelve Trees Ln NW Poulsbo WA 98370",
    "addr:housenumber":"26296",
    "addr:postcode":"98370",
    "addr:street":"Twelve Trees Ln Nw",
    "iso:country":"US",
    "sg:address":"26296 Twelve Trees Ln NW",
    "sg:city":"Poulsbo",
    "sg:classifiers":[
        {
            "category":"Manufacturing",
            "subcategory":"Tools & Machinery",
            "type":"Manufacturing & Wholesale Goods"
        }
    ],
    "sg:phone":"+1 360 697 5656",
    "sg:postcode":"98370",
    "sg:province":"WA",
    "sg:tags":[
        "mfg",
        "surgical",
        "computer",
        "custom"
    ],
    "wof:name":"Mind",
    "wof:placetype":"venue"
},
  "geometry": {"coordinates":[-122.65465,47.799501],"type":"Point"}
}