{
  "type": "Feature",
  "properties": {
    "addr:full":"5916 Graham Ave Sumner WA 98390",
    "addr:housenumber":"5916",
    "addr:postcode":"98390",
    "addr:street":"Graham Ave",
    "iso:country":"US",
    "sg:address":"5916 Graham Ave",
    "sg:city":"Sumner",
    "sg:classifiers":[
        {
            "category":"Personal",
            "subcategory":"Beauty Salon",
            "type":"Services"
        }
    ],
    "sg:phone":"+1 253 891 2340",
    "sg:postcode":"98390",
    "sg:province":"WA",
    "sg:tags":[
        "shop",
        "tanning"
    ],
    "wof:name":"Topline Nails",
    "wof:placetype":"venue"
},
  "geometry": {"coordinates":[-122.224102,47.203507],"type":"Point"}
}