{
  "type": "Feature",
  "properties": {
    "addr:full":"15215 Military Rd S Seatac WA 98188",
    "addr:housenumber":"15215",
    "addr:postcode":"98188",
    "addr:street":"Military Rd",
    "iso:country":"US",
    "sg:address":"15215 Military Rd S",
    "sg:city":"Seatac",
    "sg:classifiers":[
        {
            "category":"Restaurant",
            "type":"Food & Drink"
        }
    ],
    "sg:phone":"+1 206 431 9411",
    "sg:postcode":"98188",
    "sg:province":"WA",
    "sg:tags":[
        "style",
        "american",
        "family"
    ],
    "wof:name":"The Pancake Chef",
    "wof:placetype":"venue"
},
  "geometry": {"coordinates":[-122.288741,47.466846],"type":"Point"}
}