{
  "type": "Feature",
  "properties": {
    "addr:full":"19 Wolf Creek Rd Winthrop WA 98862",
    "addr:housenumber":"19",
    "addr:postcode":"98862",
    "addr:street":"Wolf Creek Rd",
    "iso:country":"US",
    "sg:address":"19 Wolf Creek Rd",
    "sg:city":"Winthrop",
    "sg:phone":"+1 509 996 2518",
    "sg:postcode":"98862",
    "sg:province":"WA",
    "sg:tags":[
        "farm"
    ],
    "wof:name":"Kelly Lynn Alumbaugh",
    "wof:placetype":"venue"
},
  "geometry": {"coordinates":[-120.210159,48.475736],"type":"Point"}
}