{
  "type": "Feature",
  "properties": {
    "addr:full":"217 Airport Way S Renton WA 98055",
    "addr:housenumber":"217",
    "addr:postcode":"98055",
    "addr:street":"Airport Way S Renton",
    "iso:country":"US",
    "sg:address":"217 Airport Way S",
    "sg:city":"Renton",
    "sg:classifiers":[
        {
            "category":"Retail",
            "subcategory":"Auto Repair",
            "type":"Services"
        }
    ],
    "sg:phone":"+1 425 227 5500",
    "sg:postcode":"98055",
    "sg:province":"WA",
    "sg:tags":[
        "automotive",
        "towing"
    ],
    "wof:name":"Roscoes Towing Service",
    "wof:placetype":"venue"
},
  "geometry": {"coordinates":[-122.21384399999999,47.484942],"type":"Point"}
}