{
  "type": "Feature",
  "properties": {
    "addr:full":"531 Levey Rd Pasco WA 99301",
    "addr:housenumber":"531",
    "addr:postcode":"99301",
    "addr:street":"Levey Rd",
    "iso:country":"US",
    "sg:address":"531 Levey Rd",
    "sg:city":"Pasco",
    "sg:classifiers":[
        {
            "category":"Manufacturing",
            "subcategory":"Food",
            "type":"Manufacturing & Wholesale Goods"
        }
    ],
    "sg:phone":"+1 509 547 6224",
    "sg:postcode":"99301",
    "sg:province":"WA",
    "sg:tags":[
        "winery"
    ],
    "sg:website":"www.gordonwines.com",
    "wof:name":"Gordon Brothers Inc",
    "wof:placetype":"venue"
},
  "geometry": {"coordinates":[-118.847579,46.28041],"type":"Point"}
}