{
  "type": "Feature",
  "properties": {
    "addr:full":"12512 Lake City Way NE Seattle WA 98125",
    "addr:housenumber":"12512",
    "addr:postcode":"98125",
    "addr:street":"Lake City Way Ne",
    "iso:country":"US",
    "sg:address":"12512 Lake City Way NE",
    "sg:city":"Seattle",
    "sg:classifiers":[
        {
            "category":"Wholesale",
            "subcategory":"Computers",
            "type":"Manufacturing & Wholesale Goods"
        }
    ],
    "sg:phone":"+1 206 417 3139",
    "sg:postcode":"98125",
    "sg:province":"WA",
    "sg:website":"www.ebitspclaptop.com",
    "wof:name":"Ebits PC Laptop",
    "wof:placetype":"venue"
},
  "geometry": {"coordinates":[-122.294861,47.71931],"type":"Point"}
}