{
  "type": "Feature",
  "properties": {
    "addr:full":"3049 S 36th St Tacoma WA 98409",
    "addr:housenumber":"3049",
    "addr:postcode":"98409",
    "addr:street":"S 36Th St",
    "iso:country":"US",
    "sg:address":"3049 S 36th St",
    "sg:city":"Tacoma",
    "sg:classifiers":[
        {
            "category":"Food & Beverages",
            "subcategory":"Groceries & Convenience Stores",
            "type":"Retail Goods"
        },
        {
            "category":"Social Services",
            "type":"Services"
        }
    ],
    "sg:phone":"+1 253 475 3663",
    "sg:postcode":"98409",
    "sg:province":"WA",
    "sg:tags":[
        "product"
    ],
    "wof:name":"Tahoma Food Systems",
    "wof:placetype":"venue"
},
  "geometry": {"coordinates":[-122.475904,47.22634],"type":"Point"}
}