{
  "type": "Feature",
  "properties": {
    "addr:full":"6053 S Asotin Ct Tacoma WA 98408",
    "addr:housenumber":"6053",
    "addr:postcode":"98408",
    "addr:street":"S Asotin Ct",
    "iso:country":"US",
    "sg:address":"6053 S Asotin Ct",
    "sg:city":"Tacoma",
    "sg:classifiers":[
        {
            "category":"Wholesale",
            "subcategory":"Electrical",
            "type":"Manufacturing & Wholesale Goods"
        }
    ],
    "sg:phone":"+1 253 474 6700",
    "sg:postcode":"98408",
    "sg:province":"WA",
    "sg:tags":[
        "control",
        "security",
        "system"
    ],
    "wof:name":"Diamond Security Systems",
    "wof:placetype":"venue"
},
  "geometry": {"coordinates":[-122.458663,47.201099],"type":"Point"}
}