{
  "type": "Feature",
  "properties": {
    "addr:full":"1500 Rocky Point Rd Bremerton WA 98312",
    "addr:housenumber":"1500",
    "addr:postcode":"98312",
    "addr:street":"Rocky Point Rd",
    "iso:country":"US",
    "sg:address":"1500 Rocky Point Rd",
    "sg:city":"Bremerton",
    "sg:classifiers":[
        {
            "category":"Education",
            "subcategory":"School",
            "type":"Public Place"
        }
    ],
    "sg:phone":"+1 360 373 3454",
    "sg:postcode":"98312",
    "sg:province":"WA",
    "wof:name":"Schools Bremerton Public",
    "wof:placetype":"venue"
},
  "geometry": {"coordinates":[-122.66780900000001,47.576432],"type":"Point"}
}