{
  "type": "Feature",
  "properties": {
    "addr:full":"10924 Mukilteo Speedway Mukilteo WA 98275",
    "addr:housenumber":"10924",
    "addr:postcode":"98275",
    "addr:street":"Mukilteo Speedway",
    "iso:country":"US",
    "sg:address":"10924 Mukilteo Speedway",
    "sg:city":"Mukilteo",
    "sg:classifiers":[
        {
            "category":"Insurance",
            "subcategory":"Hazard Insurance",
            "type":"Services"
        }
    ],
    "sg:phone":"+1 425 315 1601",
    "sg:postcode":"98275",
    "sg:province":"WA",
    "sg:tags":[
        "surety"
    ],
    "wof:name":"Cascade Surety & Bonding Inc",
    "wof:placetype":"venue"
},
  "geometry": {"coordinates":[-122.291696,47.899714],"type":"Point"}
}