{
  "type": "Feature",
  "properties": {
    "addr:full":"13225 Farm To Market Rd Mount Vernon WA 98273",
    "addr:housenumber":"13225",
    "addr:postcode":"98273",
    "addr:street":"Farm To Market Rd",
    "iso:country":"US",
    "sg:address":"13225 Farm To Market Rd",
    "sg:city":"Mount Vernon",
    "sg:classifiers":[
        {
            "category":"Wholesale",
            "subcategory":"Fruits & Vegetables",
            "type":"Manufacturing & Wholesale Goods"
        }
    ],
    "sg:phone":"+1 360 428 4070",
    "sg:postcode":"98273",
    "sg:province":"WA",
    "sg:tags":[
        "a",
        "operates",
        "bro",
        "as",
        "wholesaler",
        "fresh"
    ],
    "wof:name":"Washington Lettuce Vegetable",
    "wof:placetype":"venue"
},
  "geometry": {"coordinates":[-122.443922,48.453567],"type":"Point"}
}