{
  "type": "Feature",
  "properties": {
    "addr:full":"5912 SW Point Robinson Rd Vashon WA 98070",
    "addr:housenumber":"5912",
    "addr:postcode":"98070",
    "addr:street":"Sw Point Robinson Rd",
    "iso:country":"US",
    "sg:address":"5912 SW Point Robinson Rd",
    "sg:city":"Vashon",
    "sg:classifiers":[
        {
            "category":"Utilities",
            "subcategory":"Water",
            "type":"Services"
        },
        {
            "category":"Recreation",
            "subcategory":"Water Park",
            "type":"Entertainment"
        }
    ],
    "sg:phone":"+1 206 463 6193",
    "sg:postcode":"98070",
    "sg:province":"WA",
    "sg:tags":[
        "systems-equipment",
        "industrial",
        "treatment",
        "supply-wholesale",
        "supplies-commercial"
    ],
    "wof:name":"Maury Hill Farm Enterprises",
    "wof:placetype":"venue"
},
  "geometry": {"coordinates":[-122.406098,47.3892],"type":"Point"}
}