{
  "type": "Feature",
  "properties": {
    "addr:full":"15 S Grady Way Renton WA 98057",
    "addr:housenumber":"15",
    "addr:postcode":"98057",
    "addr:street":"S Grady Way",
    "iso:country":"US",
    "sg:address":"15 S Grady Way",
    "sg:city":"Renton",
    "sg:classifiers":[
        {
            "category":"Health Services",
            "subcategory":"Doctor",
            "type":"Services"
        },
        {
            "category":"Health Services",
            "subcategory":"Clinic",
            "type":"Services"
        }
    ],
    "sg:phone":"+1 425 277 5616",
    "sg:postcode":"98057",
    "sg:province":"WA",
    "sg:tags":[
        "counseling",
        "mental"
    ],
    "wof:name":"Ladue Robin A PHD",
    "wof:placetype":"venue"
},
  "geometry": {"coordinates":[-122.215422,47.469486],"type":"Point"}
}