{
  "type": "Feature",
  "properties": {
    "addr:full":"2100 116th Ave NE Bellevue WA 98004",
    "addr:housenumber":"2100",
    "addr:postcode":"98004",
    "addr:street":"116Th Ave Ne",
    "iso:country":"US",
    "sg:address":"2100 116th Ave NE",
    "sg:city":"Bellevue",
    "sg:classifiers":[
        {
            "category":"Professional",
            "subcategory":"Lawyer & Legal Services",
            "type":"Services"
        }
    ],
    "sg:phone":"+1 425 451 1400",
    "sg:postcode":"98004",
    "sg:province":"WA",
    "sg:tags":[
        "attorney"
    ],
    "wof:name":"Herman Recor Araki Kaufman",
    "wof:placetype":"venue"
},
  "geometry": {"coordinates":[-122.185625,47.631732],"type":"Point"}
}