{
  "type": "Feature",
  "properties": {
    "addr:full":"1 Lake Bellevue Dr Ste 200 Bellevue WA 98005",
    "addr:housenumber":"1",
    "addr:postcode":"98005",
    "addr:street":"Lake Bellevue Dr Ste 200",
    "iso:country":"US",
    "sg:address":"1 Lake Bellevue Dr Ste 200",
    "sg:city":"Bellevue",
    "sg:classifiers":[
        {
            "category":"Organizations",
            "subcategory":"Non-profit Organization",
            "type":"Services"
        }
    ],
    "sg:phone":"+1 425 453 2237",
    "sg:postcode":"98005",
    "sg:province":"WA",
    "sg:tags":[
        "service/non-profit",
        "community"
    ],
    "wof:name":"American Cultural Exchange Service",
    "wof:placetype":"venue"
},
  "geometry": {"coordinates":[-122.181393,47.618998],"type":"Point"}
}