{
  "type": "Feature",
  "properties": {
    "addr:full":"16768 State Rte 536 Mount Vernon WA 98273",
    "addr:housenumber":"16768",
    "addr:postcode":"98273",
    "addr:street":"State Rte 536",
    "iso:country":"US",
    "sg:address":"16768 State Rte 536",
    "sg:city":"Mount Vernon",
    "sg:classifiers":[
        {
            "category":"Retail",
            "subcategory":"Repair Shop",
            "type":"Services"
        }
    ],
    "sg:phone":"+1 360 848 7856",
    "sg:postcode":"98273",
    "sg:province":"WA",
    "wof:name":"Hannay Forge",
    "wof:placetype":"venue"
},
  "geometry": {"coordinates":[-122.382834,48.438309],"type":"Point"}
}