{
  "type": "Feature",
  "properties": {
    "addr:full":"9 103rd Ave NE Bellevue WA 98004",
    "addr:housenumber":"9",
    "addr:postcode":"98004",
    "addr:street":"103Rd Ave Ne",
    "iso:country":"US",
    "sg:address":"9 103rd Ave NE",
    "sg:city":"Bellevue",
    "sg:classifiers":[
        {
            "category":"Real Estate",
            "subcategory":"Real Estate Services",
            "type":"Services"
        }
    ],
    "sg:phone":"+1 425 453 1655",
    "sg:postcode":"98004",
    "sg:province":"WA",
    "sg:tags":[
        "management",
        "property"
    ],
    "wof:name":"Vander Hoek Corp",
    "wof:placetype":"venue"
},
  "geometry": {"coordinates":[-122.203003,47.610199],"type":"Point"}
}