{
  "type": "Feature",
  "properties": {
    "addr:full":"422 Rd S NE Moses Lake WA 98837",
    "addr:housenumber":"422",
    "addr:postcode":"98837",
    "addr:street":"Rd",
    "iso:country":"US",
    "sg:address":"422 Rd S NE",
    "sg:city":"Moses Lake",
    "sg:classifiers":[
        {
            "category":"Farming",
            "subcategory":"Farm",
            "type":"Manufacturing & Wholesale Goods"
        }
    ],
    "sg:phone":"+1 509 765 4817",
    "sg:postcode":"98837",
    "sg:province":"WA",
    "sg:tags":[
        "crop",
        "general"
    ],
    "wof:name":"Getzinger Farms",
    "wof:placetype":"venue"
},
  "geometry": {"coordinates":[-119.08721799999999,47.102813],"type":"Point"}
}