{
  "type": "Feature",
  "properties": {
    "addr:full":"16060 Military Rd S Seatac WA 98188",
    "addr:housenumber":"16060",
    "addr:postcode":"98188",
    "addr:street":"Military Rd",
    "iso:country":"US",
    "sg:address":"16060 Military Rd S",
    "sg:city":"Seatac",
    "sg:classifiers":[
        {
            "category":"Building & Trades",
            "subcategory":"Construction",
            "type":"Services"
        }
    ],
    "sg:phone":"+1 206 243 7512",
    "sg:postcode":"98188",
    "sg:province":"WA",
    "sg:tags":[
        "repairing",
        "remodeling",
        "contractor"
    ],
    "wof:name":"Jordan's Western Woodcraft Inc",
    "wof:placetype":"venue"
},
  "geometry": {"coordinates":[-122.28522,47.45913],"type":"Point"}
}