{
  "type": "Feature",
  "properties": {
    "addr:full":"635 Highland Dr Wenatchee WA 98801",
    "addr:housenumber":"635",
    "addr:postcode":"98801",
    "addr:street":"Highland Dr",
    "iso:country":"US",
    "sg:address":"635 Highland Dr",
    "sg:city":"Wenatchee",
    "sg:classifiers":[
        {
            "category":"Building & Trades",
            "subcategory":"Construction",
            "type":"Services"
        }
    ],
    "sg:phone":"+1 509 662 8959",
    "sg:postcode":"98801",
    "sg:province":"WA",
    "sg:tags":[
        "house"
    ],
    "wof:name":"Even Stephens",
    "wof:placetype":"venue"
},
  "geometry": {"coordinates":[-120.315152,47.412446],"type":"Point"}
}