{
  "type": "Feature",
  "properties": {
    "addr:full":"12209 E Mission Ave Spokane Valley WA 99206",
    "addr:housenumber":"12209",
    "addr:postcode":"99206",
    "addr:street":"E Mission Ave",
    "iso:country":"US",
    "sg:address":"12209 E Mission Ave",
    "sg:city":"Spokane Valley",
    "sg:classifiers":[
        {
            "category":"Real Estate",
            "subcategory":"Real Estate Services",
            "type":"Services"
        }
    ],
    "sg:phone":"+1 509 242 1890",
    "sg:postcode":"99206",
    "sg:province":"WA",
    "sg:tags":[
        "company",
        "title"
    ],
    "wof:name":"First American Title Ins Co",
    "wof:placetype":"venue"
},
  "geometry": {"coordinates":[-117.242431,47.671724],"type":"Point"}
}