{
  "type": "Feature",
  "properties": {
    "iso:country":"US",
    "sg:address":"1530 Black Lake Blvd SW",
    "sg:city":"Olympia",
    "sg:classifiers":[
        {
            "category":"Shopping",
            "type":"Retail Goods"
        }
    ],
    "sg:phone":"+1 360 956 0698",
    "sg:postcode":"98502",
    "sg:province":"WA",
    "sg:tags":[
        "pet",
        "shop"
    ],
    "wof:name":"PETCO",
    "wof:placetype":"venue"
},
  "geometry": {"coordinates":[-122.939898,47.033156],"type":"Point"}
}