{
  "type": "Feature",
  "properties": {
    "addr:full":"2034 NW Swanlund St Poulsbo WA 98370",
    "addr:housenumber":"2034",
    "addr:postcode":"98370",
    "addr:street":"Nw Swanlund St",
    "iso:country":"US",
    "sg:address":"2034 NW Swanlund St",
    "sg:city":"Poulsbo",
    "sg:classifiers":[
        {
            "category":"Place Of Worship",
            "type":"Public Place"
        }
    ],
    "sg:phone":"+1 360 697 5354",
    "sg:postcode":"98370",
    "sg:province":"WA",
    "sg:tags":[
        "church"
    ],
    "wof:name":"Word Of Mouth",
    "wof:placetype":"venue"
},
  "geometry": {"coordinates":[-122.66508399999999,47.800387],"type":"Point"}
}