{
  "type": "Feature",
  "properties": {
    "addr:full":"537 14th Ave Longview WA 98632",
    "addr:housenumber":"537",
    "addr:postcode":"98632",
    "addr:street":"14Th Ave",
    "iso:country":"US",
    "sg:address":"537 14th Ave",
    "sg:city":"Longview",
    "sg:classifiers":[
        {
            "category":"Shopping",
            "type":"Retail Goods"
        }
    ],
    "sg:phone":"+1 360 578 2100",
    "sg:postcode":"98632",
    "sg:province":"WA",
    "sg:tags":[
        "supply",
        "sale",
        "machine",
        "equipment",
        "computer",
        "copy"
    ],
    "sg:website":"http://oslongview.com/",
    "wof:name":"Office Systems",
    "wof:placetype":"venue"
},
  "geometry": {"coordinates":[-122.94259099999999,46.123392],"type":"Point"}
}