{
  "type": "Feature",
  "properties": {
    "addr:full":"6416 Roosevelt Way NE Seattle WA 98115",
    "addr:housenumber":"6416",
    "addr:postcode":"98115",
    "addr:street":"Roosevelt Way Ne",
    "iso:country":"US",
    "sg:address":"6416 Roosevelt Way NE",
    "sg:city":"Seattle",
    "sg:classifiers":[
        {
            "category":"Shopping",
            "subcategory":"Stationery & Office Supplies",
            "type":"Retail Goods"
        },
        {
            "category":"Home & Garden",
            "subcategory":"Furniture",
            "type":"Retail Goods"
        }
    ],
    "sg:phone":"+1 206 524 9611",
    "sg:postcode":"98115",
    "sg:province":"WA",
    "sg:tags":[
        "equipment",
        "store"
    ],
    "sg:website":"www.daniafurniture.com",
    "wof:name":"Dania Furniture",
    "wof:placetype":"venue"
},
  "geometry": {"coordinates":[-122.317357,47.675238],"type":"Point"}
}