{
  "type": "Feature",
  "properties": {
    "addr:full":"3301 S 11th Ave Union Gap WA 98903",
    "addr:housenumber":"3301",
    "addr:postcode":"98903",
    "addr:street":"S 11Th Ave",
    "iso:country":"US",
    "sg:address":"3301 S 11th Ave",
    "sg:city":"Union Gap",
    "sg:classifiers":[
        {
            "category":"Freight",
            "type":"Transportation"
        }
    ],
    "sg:phone":"+1 509 248 3233",
    "sg:postcode":"98903",
    "sg:province":"WA",
    "sg:tags":[
        "commercial",
        "storage"
    ],
    "wof:name":"Union Gap Partnership",
    "wof:placetype":"venue"
},
  "geometry": {"coordinates":[-120.52288,46.546329],"type":"Point"}
}