{
  "type": "Feature",
  "properties": {
    "addr:full":"864 SW Winebarger Rd White Salmon WA 98672",
    "addr:housenumber":"864",
    "addr:postcode":"98672",
    "addr:street":"Sw Winebarger Rd",
    "iso:country":"US",
    "sg:address":"864 SW Winebarger Rd",
    "sg:city":"White Salmon",
    "sg:classifiers":[
        {
            "category":"Building & Trades",
            "subcategory":"Construction",
            "type":"Services"
        }
    ],
    "sg:phone":"+1 509 493 1063",
    "sg:postcode":"98672",
    "sg:province":"WA",
    "sg:tags":[
        "general",
        "contractor"
    ],
    "wof:name":"Greg Holtman Construction",
    "wof:placetype":"venue"
},
  "geometry": {"coordinates":[-121.51232299999999,45.735028],"type":"Point"}
}