{
  "type": "Feature",
  "properties": {
    "addr:full":"4724 130th St SE Everett WA 98208",
    "addr:housenumber":"4724",
    "addr:postcode":"98208",
    "addr:street":"130Th St Se",
    "iso:country":"US",
    "sg:address":"4724 130th St SE",
    "sg:city":"Everett",
    "sg:classifiers":[
        {
            "category":"Organizations",
            "subcategory":"Religious Organization",
            "type":"Services"
        }
    ],
    "sg:phone":"+1 425 338 1278",
    "sg:postcode":"98208",
    "sg:province":"WA",
    "sg:tags":[
        "clergy"
    ],
    "wof:name":"Richard E Jessup",
    "wof:placetype":"venue"
},
  "geometry": {"coordinates":[-122.168526,47.87937],"type":"Point"}
}