{
  "type": "Feature",
  "properties": {
    "iso:country":"US",
    "sg:address":"2011 W Mallon Ave",
    "sg:city":"Spokane",
    "sg:classifiers":[
        {
            "category":"Retail",
            "subcategory":"Repair Shop",
            "type":"Services"
        }
    ],
    "sg:phone":"+1 509 325 9377",
    "sg:postcode":"99201",
    "sg:province":"WA",
    "sg:tags":[
        "electrical"
    ],
    "wof:name":"Riley Appliance",
    "wof:placetype":"venue"
},
  "geometry": {"coordinates":[-117.44311999999999,47.665161],"type":"Point"}
}