{
  "type": "Feature",
  "properties": {
    "addr:full":"720 Washington St # 750 Vancouver WA 98660",
    "addr:housenumber":"720",
    "addr:postcode":"98660",
    "addr:street":"Washington St # 750",
    "iso:country":"US",
    "sg:address":"720 Washington St # 750",
    "sg:city":"Vancouver",
    "sg:classifiers":[
        {
            "category":"Professional",
            "subcategory":"Lawyer & Legal Services",
            "type":"Services"
        }
    ],
    "sg:phone":"+1 360 695 4326",
    "sg:postcode":"98660",
    "sg:province":"WA",
    "sg:website":"www.yourinjurylawyers.com",
    "wof:name":"Sam Hochberg & Associates",
    "wof:placetype":"venue"
},
  "geometry": {"coordinates":[-122.67296399999999,45.626924],"type":"Point"}
}