{
  "type": "Feature",
  "properties": {
    "addr:full":"2027 196th St SW Lynnwood WA 98036",
    "addr:housenumber":"2027",
    "addr:postcode":"98036",
    "addr:street":"196Th St Sw",
    "iso:country":"US",
    "sg:address":"2027 196th St SW",
    "sg:city":"Lynnwood",
    "sg:classifiers":[
        {
            "category":"Travel",
            "subcategory":"Campground",
            "type":"Entertainment"
        },
        {
            "category":"Arena",
            "subcategory":"Sports Club",
            "type":"Entertainment"
        }
    ],
    "sg:phone":"+1 425 640 0370",
    "sg:postcode":"98036",
    "sg:province":"WA",
    "sg:tags":[
        "camp"
    ],
    "wof:name":"Wilkinson Baseball Academy",
    "wof:placetype":"venue"
},
  "geometry": {"coordinates":[-122.259649,47.819886],"type":"Point"}
}