{
  "type": "Feature",
  "properties": {
    "iso:country":"US",
    "sg:address":"3104 W Kennewick Ave",
    "sg:city":"Kennewick",
    "sg:classifiers":[
        {
            "category":"Building & Trades",
            "subcategory":"Landscaping Services",
            "type":"Services"
        }
    ],
    "sg:phone":"+1 509 737 8040",
    "sg:postcode":"99336",
    "sg:province":"WA",
    "sg:tags":[
        "lawn",
        "maintenance",
        "grounds"
    ],
    "wof:name":"Sal's Gardening",
    "wof:placetype":"venue"
},
  "geometry": {"coordinates":[-119.163056,46.209614],"type":"Point"}
}