{
  "type": "Feature",
  "properties": {
    "addr:full":"11013 Pacific Hwy SW Lakewood WA 98499",
    "addr:housenumber":"11013",
    "addr:postcode":"98499",
    "addr:street":"Pacific Hwy Sw",
    "iso:country":"US",
    "sg:address":"11013 Pacific Hwy SW",
    "sg:city":"Lakewood",
    "sg:classifiers":[
        {
            "category":"Shopping",
            "subcategory":"Department Store",
            "type":"Retail Goods"
        },
        {
            "category":"Real Estate",
            "subcategory":"Real Estate Operator",
            "type":"Services"
        }
    ],
    "sg:phone":"+1 253 588 7566",
    "sg:postcode":"98499",
    "sg:province":"WA",
    "sg:tags":[
        "building",
        "nonresidential"
    ],
    "wof:name":"Tacoma Discount World",
    "wof:placetype":"venue"
},
  "geometry": {"coordinates":[-122.489998,47.157398],"type":"Point"}
}