{
  "type": "Feature",
  "properties": {
    "addr:full":"241 Old Hwy 97 Brewster WA 98812",
    "addr:housenumber":"241",
    "addr:postcode":"98812",
    "addr:street":"Old Hwy 97",
    "iso:country":"US",
    "sg:address":"241 Old Hwy 97",
    "sg:city":"Brewster",
    "sg:classifiers":[
        {
            "category":"Farming",
            "subcategory":"Orchard",
            "type":"Manufacturing & Wholesale Goods"
        }
    ],
    "sg:phone":"+1 509 689 3261",
    "sg:postcode":"98812",
    "sg:province":"WA",
    "sg:tags":[
        "fruit",
        "tree"
    ],
    "wof:name":"Dotty Sharable",
    "wof:placetype":"venue"
},
  "geometry": {"coordinates":[-119.7316,48.131739],"type":"Point"}
}