{
  "type": "Feature",
  "properties": {
    "addr:full":"2623 140th St NE Marysville WA 98271",
    "addr:housenumber":"2623",
    "addr:postcode":"98271",
    "addr:street":"140Th St Ne",
    "iso:country":"US",
    "sg:address":"2623 140th St NE",
    "sg:city":"Marysville",
    "sg:classifiers":[
        {
            "category":"Retail",
            "subcategory":"Auto Repair",
            "type":"Services"
        }
    ],
    "sg:phone":"+1 360 651 0534",
    "sg:postcode":"98271",
    "sg:province":"WA",
    "sg:tags":[
        "station",
        "gasoline",
        "general"
    ],
    "wof:name":"Teds Union 76",
    "wof:placetype":"venue"
},
  "geometry": {"coordinates":[-122.196437,48.123032],"type":"Point"}
}