{
  "type": "Feature",
  "properties": {
    "addr:full":"1611 116th Ave NE Ste 200 Bellevue WA 98004",
    "addr:housenumber":"1611",
    "addr:postcode":"98004",
    "addr:street":"116Th Ave Ne Ste 200",
    "iso:country":"US",
    "sg:address":"1611 116th Ave NE Ste 200",
    "sg:city":"Bellevue",
    "sg:classifiers":[
        {
            "category":"Personal",
            "subcategory":"Massage",
            "type":"Services"
        },
        {
            "category":"Health Services",
            "subcategory":"Health Practitioner",
            "type":"Services"
        }
    ],
    "sg:phone":"+1 425 455 0088",
    "sg:postcode":"98004",
    "sg:province":"WA",
    "sg:tags":[
        "therapy",
        "physical"
    ],
    "sg:website":"www.monroetherapeuticmassage.com",
    "wof:name":"Monroe Therapeutic Massage P S",
    "wof:placetype":"venue"
},
  "geometry": {"coordinates":[-122.185892,47.625357],"type":"Point"}
}