{
  "type": "Feature",
  "properties": {
    "addr:full":"4473 142nd Ave SE Bellevue WA 98006",
    "addr:housenumber":"4473",
    "addr:postcode":"98006",
    "addr:street":"142Nd Ave Se",
    "iso:country":"US",
    "sg:address":"4473 142nd Ave SE",
    "sg:city":"Bellevue",
    "sg:classifiers":[
        {
            "category":"Professional",
            "subcategory":"Engineering",
            "type":"Services"
        },
        {
            "category":"Professional",
            "subcategory":"Research",
            "type":"Services"
        }
    ],
    "sg:phone":"+1 425 643 4755",
    "sg:postcode":"98006",
    "sg:province":"WA",
    "sg:tags":[
        "consulting",
        "engineer"
    ],
    "wof:name":"Wamax, Inc.",
    "wof:placetype":"venue"
},
  "geometry": {"coordinates":[-122.151128,47.566584],"type":"Point"}
}