{
  "type": "Feature",
  "properties": {
    "addr:full":"711 9th Ave N Seattle WA 98109",
    "addr:housenumber":"711",
    "addr:postcode":"98109",
    "addr:street":"9Th Ave N",
    "iso:country":"US",
    "sg:address":"711 9th Ave N",
    "sg:city":"Seattle",
    "sg:classifiers":[
        {
            "category":"Autos & Motor Vehicles",
            "subcategory":"Motorcycle Sales",
            "type":"Retail Goods"
        }
    ],
    "sg:phone":"+1 206 298 9995",
    "sg:postcode":"98109",
    "sg:province":"WA",
    "sg:website":"www.ducatiseattle.com",
    "wof:name":"Ducati Seattle",
    "wof:placetype":"venue"
},
  "geometry": {"coordinates":[-122.339996,47.625599],"type":"Point"}
}