{
  "type": "Feature",
  "properties": {
    "addr:full":"2370 130th Ave NE Bellevue WA 98005",
    "addr:housenumber":"2370",
    "addr:postcode":"98005",
    "addr:street":"130Th Ave Ne",
    "iso:country":"US",
    "sg:address":"2370 130th Ave NE",
    "sg:city":"Bellevue",
    "sg:phone":"+1 425 883 8181",
    "sg:postcode":"98005",
    "sg:province":"WA",
    "sg:tags":[
        "equipment",
        "commercial"
    ],
    "wof:name":"Coca-Cola",
    "wof:placetype":"venue"
},
  "geometry": {"coordinates":[-122.16729599999999,47.630052],"type":"Point"}
}