{
  "type": "Feature",
  "properties": {
    "addr:full":"365 Ericksen Ave. NE Bainbridge Isladn  WA 98110",
    "addr:housenumber":"365",
    "addr:postcode":"98110",
    "addr:street":"Ericksen Ave. Ne;Isladn",
    "iso:country":"US",
    "sg:address":"365 Ericksen Ave. NE",
    "sg:city":"Bainbridge Isladn ",
    "sg:classifiers":[
        {
            "category":"Professional",
            "subcategory":"Computer Services",
            "type":"Services"
        }
    ],
    "sg:phone":"+1 206 201 3650",
    "sg:postcode":"98110",
    "sg:province":"WA",
    "sg:tags":[
        "web-video",
        "content-creators",
        "independent",
        "media",
        "publisher",
        "advertising",
        "marketing",
        "production",
        "distribution"
    ],
    "sg:website":"http://www.smallscreennetwork.com",
    "wof:name":"Small Screen Network",
    "wof:placetype":"venue"
},
  "geometry": {"coordinates":[-122.517094,47.625314],"type":"Point"}
}