{
  "type": "Feature",
  "properties": {
    "iso:country":"US",
    "sg:address":"31600 126th Ave SE",
    "sg:city":"Auburn",
    "sg:classifiers":[
        {
            "category":"Freight",
            "type":"Transportation"
        }
    ],
    "sg:phone":"+1 253 833 7408",
    "sg:postcode":"98092",
    "sg:province":"WA",
    "sg:tags":[
        "operator",
        "local",
        "trucking"
    ],
    "wof:name":"Local Valley Movers",
    "wof:placetype":"venue"
},
  "geometry": {"coordinates":[-122.17350999999999,47.318822],"type":"Point"}
}