{
  "type": "Feature",
  "properties": {
    "addr:full":"325 Donelson Ln Yakima WA 98908",
    "addr:housenumber":"325",
    "addr:postcode":"98908",
    "addr:street":"Donelson Ln",
    "iso:country":"US",
    "sg:address":"325 Donelson Ln",
    "sg:city":"Yakima",
    "sg:classifiers":[
        {
            "category":"Farming",
            "subcategory":"Orchard",
            "type":"Manufacturing & Wholesale Goods"
        }
    ],
    "sg:phone":"+1 509 966 4315",
    "sg:postcode":"98908",
    "sg:province":"WA",
    "sg:tags":[
        "fruit",
        "tree"
    ],
    "wof:name":"Apple Jack Orchards Inc",
    "wof:placetype":"venue"
},
  "geometry": {"coordinates":[-120.592124,46.6559],"type":"Point"}
}