{
  "type": "Feature",
  "properties": {
    "addr:full":"4020 SW Holly St Seattle WA 98136",
    "addr:housenumber":"4020",
    "addr:postcode":"98136",
    "addr:street":"Sw Holly St",
    "iso:country":"US",
    "sg:address":"4020 SW Holly St",
    "sg:city":"Seattle",
    "sg:classifiers":[
        {
            "category":"Professional",
            "subcategory":"Business Services",
            "type":"Services"
        }
    ],
    "sg:phone":"+1 206 938 5417",
    "sg:postcode":"98136",
    "sg:province":"WA",
    "wof:name":"Kurt Schendel Enterprises",
    "wof:placetype":"venue"
},
  "geometry": {"coordinates":[-122.38429600000001,47.543064],"type":"Point"}
}