{
  "type": "Feature",
  "properties": {
    "addr:full":"4649 Sunnyside Ave N Seattle WA 98103",
    "addr:housenumber":"4649",
    "addr:postcode":"98103",
    "addr:street":"Sunnyside Ave N",
    "iso:country":"US",
    "sg:address":"4649 Sunnyside Ave N",
    "sg:city":"Seattle",
    "sg:classifiers":[
        {
            "category":"Organizations",
            "subcategory":"Community Association",
            "type":"Services"
        }
    ],
    "sg:phone":"+1 206 781 6679",
    "sg:postcode":"98103",
    "sg:province":"WA",
    "wof:name":"Older Womens League",
    "wof:placetype":"venue"
},
  "geometry": {"coordinates":[-122.330215,47.663938],"type":"Point"}
}