{
  "type": "Feature",
  "properties": {
    "addr:full":"1510 E Spencer Lake Rd Shelton WA 98584",
    "addr:housenumber":"1510",
    "addr:postcode":"98584",
    "addr:street":"E Spencer Lake Rd",
    "iso:country":"US",
    "sg:address":"1510 E Spencer Lake Rd",
    "sg:city":"Shelton",
    "sg:classifiers":[
        {
            "category":"Shopping",
            "subcategory":"Catalog Store",
            "type":"Retail Goods"
        }
    ],
    "sg:phone":"+1 360 426 0672",
    "sg:postcode":"98584",
    "sg:province":"WA",
    "sg:tags":[
        "house",
        "mail",
        "religious",
        "organization"
    ],
    "wof:name":"Timberdoodle Company",
    "wof:placetype":"venue"
},
  "geometry": {"coordinates":[-122.976691,47.260107],"type":"Point"}
}