{
  "type": "Feature",
  "properties": {
    "addr:full":"1308 Voelker Ave Yakima WA 98902",
    "addr:housenumber":"1308",
    "addr:postcode":"98902",
    "addr:street":"Voelker Ave",
    "iso:country":"US",
    "sg:address":"1308 Voelker Ave",
    "sg:city":"Yakima",
    "sg:classifiers":[
        {
            "category":"Building & Trades",
            "subcategory":"Construction",
            "type":"Services"
        }
    ],
    "sg:phone":"+1 509 453 2988",
    "sg:postcode":"98902",
    "sg:province":"WA",
    "sg:tags":[
        "well",
        "drilling"
    ],
    "wof:name":"Larry Cassel Drilling",
    "wof:placetype":"venue"
},
  "geometry": {"coordinates":[-120.501668,46.579925],"type":"Point"}
}