{
  "type": "Feature",
  "properties": {
    "addr:full":"221 Bellevue Way NE Bellevue WA 98004",
    "addr:housenumber":"221",
    "addr:postcode":"98004",
    "addr:street":"Bellevue Way Ne",
    "iso:country":"US",
    "sg:address":"221 Bellevue Way NE",
    "sg:city":"Bellevue",
    "sg:classifiers":[
        {
            "category":"Utilities",
            "subcategory":"Mobile Phone",
            "type":"Services"
        }
    ],
    "sg:phone":"+1 425 451 3564",
    "sg:postcode":"98004",
    "sg:province":"WA",
    "sg:tags":[
        "communication",
        "radiotelephone"
    ],
    "wof:name":"Verizon",
    "wof:placetype":"venue"
},
  "geometry": {"coordinates":[-122.201661,47.612703],"type":"Point"}
}