{
  "type": "Feature",
  "properties": {
    "addr:full":"36930 SE 47th Pl Fall City WA 98024",
    "addr:postcode":"36930;98024",
    "addr:street":"Se 47Th Pl",
    "iso:country":"US",
    "sg:address":"36930 SE 47th Pl",
    "sg:city":"Fall City",
    "sg:classifiers":[
        {
            "category":"Retail",
            "subcategory":"Auto Repair",
            "type":"Services"
        }
    ],
    "sg:phone":"+1 425 222 9463",
    "sg:postcode":"98024",
    "sg:province":"WA",
    "sg:tags":[
        "body"
    ],
    "wof:name":"Silverauto Restorations",
    "wof:placetype":"venue"
},
  "geometry": {"coordinates":[-121.847852,47.558858],"type":"Point"}
}