{
  "type": "Feature",
  "properties": {
    "addr:full":"12701 247th St E Graham WA 98338",
    "addr:housenumber":"12701",
    "addr:postcode":"98338",
    "addr:street":"247Th St E",
    "iso:country":"US",
    "sg:address":"12701 247th St E",
    "sg:city":"Graham",
    "sg:classifiers":[
        {
            "category":"Building & Trades",
            "subcategory":"Construction",
            "type":"Services"
        }
    ],
    "sg:phone":"+1 253 846 8866",
    "sg:postcode":"98338",
    "sg:province":"WA",
    "sg:tags":[
        "planning",
        "remodeling",
        "kitchen"
    ],
    "wof:name":"Style Craft",
    "wof:placetype":"venue"
},
  "geometry": {"coordinates":[-122.261065,47.031771],"type":"Point"}
}