{
  "type": "Feature",
  "properties": {
    "addr:full":"9001 17th Ave SW Apt 302 Seattle WA 98106",
    "addr:housenumber":"9001;302",
    "addr:postcode":"98106",
    "addr:street":"17Th Ave Sw Apt",
    "iso:country":"US",
    "sg:address":"9001 17th Ave SW Apt 302",
    "sg:city":"Seattle",
    "sg:classifiers":[
        {
            "category":"Place Of Worship",
            "subcategory":"Church",
            "type":"Public Place"
        },
        {
            "category":"Place Of Worship",
            "type":"Public Place"
        }
    ],
    "sg:phone":"+1 206 762 0960",
    "sg:postcode":"98106",
    "sg:province":"WA",
    "sg:tags":[
        "churches-interdenominational",
        "churches-various",
        "denomination"
    ],
    "wof:name":"Myong Sun Yim",
    "wof:placetype":"venue"
},
  "geometry": {"coordinates":[-122.356483,47.522869],"type":"Point"}
}