{
  "type": "Feature",
  "properties": {
    "addr:full":"309 E Yelm Ave Yelm WA 98597",
    "addr:housenumber":"309",
    "addr:postcode":"98597",
    "addr:street":"E Yelm Ave",
    "iso:country":"US",
    "sg:address":"309 E Yelm Ave",
    "sg:city":"Yelm",
    "sg:phone":"+1 360 458 4611",
    "sg:postcode":"98597",
    "sg:province":"WA",
    "wof:name":"The Blue Bottle Espresso",
    "wof:placetype":"venue"
},
  "geometry": {"coordinates":[-122.60397399999999,46.940536],"type":"Point"}
}