{
  "type": "Feature",
  "properties": {
    "addr:full":"316 Washington Ave S Kent WA 98032",
    "addr:housenumber":"316",
    "addr:postcode":"98032",
    "addr:street":"Washington Ave S",
    "iso:country":"US",
    "sg:address":"316 Washington Ave S",
    "sg:city":"Kent",
    "sg:classifiers":[
        {
            "category":"Shopping",
            "subcategory":"Books",
            "type":"Retail Goods"
        }
    ],
    "sg:phone":"+1 253 852 3600",
    "sg:postcode":"98032",
    "sg:province":"WA",
    "sg:tags":[
        "stationery",
        "professional",
        "dealer",
        "equipment"
    ],
    "wof:name":"Christian Supply Ctr",
    "wof:placetype":"venue"
},
  "geometry": {"coordinates":[-122.247305,47.380977],"type":"Point"}
}