{
  "type": "Feature",
  "properties": {
    "addr:full":"10137 Main St Ste 5 Bothell WA 98011",
    "addr:housenumber":"10137",
    "addr:postcode":"98011",
    "addr:street":"Main St Ste 5",
    "iso:country":"US",
    "sg:address":"10137 Main St Ste 5",
    "sg:city":"Bothell",
    "sg:classifiers":[
        {
            "category":"Education",
            "subcategory":"Music School",
            "type":"Public Place"
        }
    ],
    "sg:phone":"+1 425 486 1068",
    "sg:postcode":"98011",
    "sg:province":"WA",
    "sg:tags":[
        "instruction-vocal"
    ],
    "wof:name":"J Moore Vocal Arts Studio",
    "wof:placetype":"venue"
},
  "geometry": {"coordinates":[-122.204821,47.76015],"type":"Point"}
}