{
  "type": "Feature",
  "properties": {
    "addr:full":"1005 High Ave S Renton WA 98057",
    "addr:housenumber":"1005",
    "addr:postcode":"98057",
    "addr:street":"High Ave S Renton",
    "iso:country":"US",
    "sg:address":"1005 High Ave S",
    "sg:city":"Renton",
    "sg:classifiers":[
        {
            "category":"Building & Trades",
            "subcategory":"Locksmith",
            "type":"Services"
        }
    ],
    "sg:phone":"+1 425 738 3940",
    "sg:postcode":"98057",
    "sg:province":"WA",
    "sg:tags":[
        "key"
    ],
    "wof:name":"7 Day Emergency 24 Hour Locksmith On High Av",
    "wof:placetype":"venue"
},
  "geometry": {"coordinates":[-122.19816299999999,47.471422],"type":"Point"}
}