{
  "type": "Feature",
  "properties": {
    "addr:full":"18117 36th Ave W Lynnwood WA 98037",
    "addr:housenumber":"18117",
    "addr:postcode":"98037",
    "addr:street":"36Th Ave W",
    "iso:country":"US",
    "sg:address":"18117 36th Ave W",
    "sg:city":"Lynnwood",
    "sg:classifiers":[
        {
            "category":"Professional",
            "subcategory":"Management & Consulting",
            "type":"Services"
        }
    ],
    "sg:phone":"+1 425 345 7357",
    "sg:postcode":"98037",
    "sg:province":"WA",
    "wof:name":"Rons It Service",
    "wof:placetype":"venue"
},
  "geometry": {"coordinates":[-122.281745,47.835086],"type":"Point"}
}