{
  "type": "Feature",
  "properties": {
    "iso:country":"US",
    "sg:address":"225 NW Lindvig Way",
    "sg:city":"Poulsbo",
    "sg:classifiers":[
        {
            "category":"Social Services",
            "type":"Services"
        }
    ],
    "sg:phone":"+1 360 779 9288",
    "sg:postcode":"98370",
    "sg:province":"WA",
    "sg:tags":[
        "counselor",
        "marriage",
        "family"
    ],
    "wof:name":"New Horizons Counseling",
    "wof:placetype":"venue"
},
  "geometry": {"coordinates":[-122.654099,47.747205],"type":"Point"}
}