{
  "type": "Feature",
  "properties": {
    "addr:full":"31405 49th Pl SW Federal Way WA 98023",
    "addr:housenumber":"31405",
    "addr:postcode":"98023",
    "addr:street":"49Th Pl Sw Federal Way",
    "iso:country":"US",
    "sg:address":"31405 49th Pl SW",
    "sg:city":"Federal Way",
    "sg:classifiers":[
        {
            "category":"Professional",
            "type":"Services"
        }
    ],
    "sg:phone":"+1 253 838 3608",
    "sg:postcode":"98023",
    "sg:province":"WA",
    "wof:name":"Joshua Homer",
    "wof:placetype":"venue"
},
  "geometry": {"coordinates":[-122.39600900000001,47.319397],"type":"Point"}
}