{
  "type": "Feature",
  "properties": {
    "addr:full":"20708 NE 72nd Ave Battle Ground WA 98604",
    "addr:housenumber":"20708",
    "addr:postcode":"98604",
    "addr:street":"Ne 72Nd Ave",
    "iso:country":"US",
    "sg:address":"20708 NE 72nd Ave",
    "sg:city":"Battle Ground",
    "sg:classifiers":[
        {
            "category":"Farming",
            "subcategory":"Farm",
            "type":"Manufacturing & Wholesale Goods"
        }
    ],
    "sg:phone":"+1 360 573 1287",
    "sg:postcode":"98604",
    "sg:province":"WA",
    "sg:tags":[
        "crop",
        "general"
    ],
    "wof:name":"Phillip Thomas",
    "wof:placetype":"venue"
},
  "geometry": {"coordinates":[-122.59998299999999,45.772358],"type":"Point"}
}