{
  "type": "Feature",
  "properties": {
    "addr:full":"4205 Maple St Vancouver WA 98660",
    "addr:housenumber":"4205",
    "addr:postcode":"98660",
    "addr:street":"Maple St",
    "iso:country":"US",
    "sg:address":"4205 Maple St",
    "sg:city":"Vancouver",
    "sg:classifiers":[
        {
            "category":"Professional",
            "subcategory":"Management & Consulting",
            "type":"Services"
        }
    ],
    "sg:phone":"+1 360 695 1586",
    "sg:postcode":"98660",
    "sg:province":"WA",
    "sg:tags":[
        "business"
    ],
    "sg:website":"www.competitive-insights.com",
    "wof:name":"Competitive Insights",
    "wof:placetype":"venue"
},
  "geometry": {"coordinates":[-122.68072600000001,45.652233],"type":"Point"}
}