{
  "type": "Feature",
  "properties": {
    "addr:full":"155 SE Kamiaken St Pullman WA 99163",
    "addr:housenumber":"155",
    "addr:postcode":"99163",
    "addr:street":"Se Kamiaken St",
    "iso:country":"US",
    "sg:address":"155 SE Kamiaken St",
    "sg:city":"Pullman",
    "sg:classifiers":[
        {
            "category":"Professional",
            "subcategory":"Lawyer & Legal Services",
            "type":"Services"
        }
    ],
    "sg:phone":"+1 509 332 5838",
    "sg:postcode":"99163",
    "sg:province":"WA",
    "sg:tags":[
        "attorney"
    ],
    "wof:name":"John Hart Law Office",
    "wof:placetype":"venue"
},
  "geometry": {"coordinates":[-117.179862,46.729291],"type":"Point"}
}