{
  "type": "Feature",
  "properties": {
    "iso:country":"US",
    "sg:address":"5600 Mount Baker Hwy",
    "sg:city":"Deming",
    "sg:classifiers":[
        {
            "category":"Freight",
            "type":"Transportation"
        }
    ],
    "sg:phone":"+1 360 592 2642",
    "sg:postcode":"98244",
    "sg:province":"WA",
    "sg:tags":[
        "operator",
        "local",
        "trucking"
    ],
    "wof:name":"Mountain View Trucking",
    "wof:placetype":"venue"
},
  "geometry": {"coordinates":[-122.167232,48.838021],"type":"Point"}
}