{
  "type": "Feature",
  "properties": {
    "addr:full":"310 120th Ave NE Bellevue WA 98005",
    "addr:housenumber":"310",
    "addr:postcode":"98005",
    "addr:street":"120Th Ave Ne",
    "iso:country":"US",
    "sg:address":"310 120th Ave NE",
    "sg:city":"Bellevue",
    "sg:classifiers":[
        {
            "category":"Professional",
            "subcategory":"Detective & Security Services",
            "type":"Services"
        },
        {
            "category":"Manufacturing",
            "subcategory":"Electronics",
            "type":"Manufacturing & Wholesale Goods"
        },
        {
            "category":"Shopping",
            "subcategory":"Computers & Home Electronics",
            "type":"Retail Goods"
        },
        {
            "category":"Building & Trades",
            "subcategory":"Electrical",
            "type":"Services"
        }
    ],
    "sg:phone":"+1 425 462 4250",
    "sg:postcode":"98005",
    "sg:province":"WA",
    "sg:tags":[
        "control",
        "monitoring",
        "equipment-wholesale",
        "consultant",
        "alarm",
        "system",
        "surveillance",
        "equipment",
        "smoke",
        "detector",
        "manufacturer"
    ],
    "wof:name":"Airship Industrials",
    "wof:placetype":"venue"
},
  "geometry": {"coordinates":[-122.18026,47.611987],"type":"Point"}
}