{
  "type": "Feature",
  "properties": {
    "addr:full":"410 Bellevue Way SE Ste 102 Bellevue WA 98004",
    "addr:housenumber":"410",
    "addr:postcode":"98004",
    "addr:street":"Bellevue Way Se Ste 102",
    "iso:country":"US",
    "sg:address":"410 Bellevue Way SE Ste 102",
    "sg:city":"Bellevue",
    "sg:classifiers":[
        {
            "category":"Health Services",
            "subcategory":"Dentist",
            "type":"Services"
        }
    ],
    "sg:phone":"+1 425 454 3833",
    "sg:postcode":"98004",
    "sg:province":"WA",
    "sg:website":"www.elydentist.com",
    "wof:name":"Sherman Ely DDS PS",
    "wof:placetype":"venue"
},
  "geometry": {"coordinates":[-122.201132,47.606778],"type":"Point"}
}