{
  "type": "Feature",
  "properties": {
    "addr:full":"6416 97th Dr NE Lake Stevens WA 98258",
    "addr:housenumber":"6416",
    "addr:postcode":"98258",
    "addr:street":"97Th Dr Ne",
    "iso:country":"US",
    "sg:address":"6416 97th Dr NE",
    "sg:city":"Lake Stevens",
    "sg:classifiers":[
        {
            "category":"Travel",
            "subcategory":"Hotels & Motels",
            "type":"Entertainment"
        },
        {
            "category":"Recreation",
            "type":"Entertainment"
        }
    ],
    "sg:phone":"+1 425 334 6647",
    "sg:postcode":"98258",
    "sg:province":"WA",
    "sg:tags":[
        "resort"
    ],
    "wof:name":"Lake Cassidy Resort",
    "wof:placetype":"venue"
},
  "geometry": {"coordinates":[-122.09992800000001,48.050705],"type":"Point"}
}