{
  "type": "Feature",
  "properties": {
    "addr:full":"682 Z St SE Olympia WA 98501",
    "addr:housenumber":"682 z",
    "addr:postcode":"98501",
    "addr:street":"St Se",
    "iso:country":"US",
    "sg:address":"682 Z St SE",
    "sg:city":"Olympia",
    "sg:classifiers":[
        {
            "category":"Freight",
            "type":"Transportation"
        }
    ],
    "sg:phone":"+1 360 943 8656",
    "sg:postcode":"98501",
    "sg:province":"WA",
    "sg:tags":[
        "operator",
        "local",
        "trucking"
    ],
    "wof:name":"G Knittle Trucking",
    "wof:placetype":"venue"
},
  "geometry": {"coordinates":[-122.90067000000001,46.990532],"type":"Point"}
}