{
  "type": "Feature",
  "properties": {
    "addr:full":"915 N Malvern Rd Liberty Lake WA 99019",
    "addr:housenumber":"915",
    "addr:postcode":"99019",
    "addr:street":"N Malvern Rd",
    "iso:country":"US",
    "sg:address":"915 N Malvern Rd",
    "sg:city":"Liberty Lake",
    "sg:classifiers":[
        {
            "category":"Building & Trades",
            "subcategory":"Construction",
            "type":"Services"
        }
    ],
    "sg:phone":"+1 509 891 6741",
    "sg:postcode":"99019",
    "sg:province":"WA",
    "sg:tags":[
        "house"
    ],
    "wof:name":"Thaler Construction",
    "wof:placetype":"venue"
},
  "geometry": {"coordinates":[-117.081075,47.66521],"type":"Point"}
}