{
  "type": "Feature",
  "properties": {
    "addr:full":"7515 Terminal St SW Olympia WA 98501",
    "addr:housenumber":"7515",
    "addr:postcode":"98501",
    "addr:street":"Terminal St Sw",
    "iso:country":"US",
    "sg:address":"7515 Terminal St SW",
    "sg:city":"Olympia",
    "sg:classifiers":[
        {
            "category":"Real Estate",
            "subcategory":"Real Estate Operator",
            "type":"Services"
        }
    ],
    "sg:phone":"+1 360 943 8000",
    "sg:postcode":"98501",
    "sg:province":"WA",
    "sg:tags":[
        "hotel",
        "management"
    ],
    "sg:website":"http://www.super8.com",
    "wof:name":"Super 8 Motel",
    "wof:placetype":"venue"
},
  "geometry": {"coordinates":[-122.910888,46.979838],"type":"Point"}
}