{
  "type": "Feature",
  "properties": {
    "addr:full":"11151 318th Pl NE Carnation WA 98014",
    "addr:housenumber":"11151",
    "addr:postcode":"98014",
    "addr:street":"318Th Pl Ne",
    "iso:country":"US",
    "sg:address":"11151 318th Pl NE",
    "sg:city":"Carnation",
    "sg:classifiers":[
        {
            "category":"Manufacturing",
            "subcategory":"Apparel",
            "type":"Manufacturing & Wholesale Goods"
        }
    ],
    "sg:phone":"+1 425 556 0588",
    "sg:postcode":"98014",
    "sg:province":"WA",
    "sg:tags":[
        "fur",
        "mfg"
    ],
    "wof:name":"Fur & Feahters Companion",
    "wof:placetype":"venue"
},
  "geometry": {"coordinates":[-121.913697,47.696631],"type":"Point"}
}