{
  "type": "Feature",
  "properties": {
    "addr:full":"905 24th Way SW Olympia WA 98502",
    "addr:housenumber":"905",
    "addr:postcode":"98502",
    "addr:street":"24Th Way Sw",
    "iso:country":"US",
    "sg:address":"905 24th Way SW",
    "sg:city":"Olympia",
    "sg:phone":"+1 360 534 0786",
    "sg:postcode":"98502",
    "sg:province":"WA",
    "sg:website":"http://national.citysearch.com/profile/external/10878759/olmypia_wa/manpower.html?publisher=yellowpages&reference_id=1&placement=ypwebsitemip",
    "wof:name":"Manpower",
    "wof:placetype":"venue"
},
  "geometry": {"coordinates":[-122.91337900000001,47.027869],"type":"Point"}
}