{
  "type": "Feature",
  "properties": {
    "addr:full":"3301 Gregory Ave Yakima WA 98902",
    "addr:housenumber":"3301",
    "addr:postcode":"98902",
    "addr:street":"Gregory Ave",
    "iso:country":"US",
    "sg:address":"3301 Gregory Ave",
    "sg:city":"Yakima",
    "sg:classifiers":[
        {
            "category":"Social Services",
            "subcategory":"Child Care",
            "type":"Services"
        }
    ],
    "sg:phone":"+1 509 452 5015",
    "sg:postcode":"98902",
    "sg:province":"WA",
    "wof:name":"Trish's Daycare",
    "wof:placetype":"venue"
},
  "geometry": {"coordinates":[-120.553048,46.58041],"type":"Point"}
}