{
  "type": "Feature",
  "properties": {
    "addr:full":"2651 NW 60th St Seattle WA 98107",
    "addr:housenumber":"2651",
    "addr:postcode":"98107",
    "addr:street":"Nw 60Th St",
    "iso:country":"US",
    "sg:address":"2651 NW 60th St",
    "sg:city":"Seattle",
    "sg:classifiers":[
        {
            "category":"Personal",
            "subcategory":"Massage",
            "type":"Services"
        }
    ],
    "sg:phone":"+1 206 782 6844",
    "sg:postcode":"98107",
    "sg:province":"WA",
    "wof:name":"Greenstick Enterprises",
    "wof:placetype":"venue"
},
  "geometry": {"coordinates":[-122.39284000000001,47.672309],"type":"Point"}
}