{
  "type": "Feature",
  "properties": {
    "addr:full":"3210 W Mc Graw St Seattle WA 98199",
    "addr:housenumber":"3210",
    "addr:postcode":"98199",
    "addr:street":"W Mc Graw St",
    "iso:country":"US",
    "sg:address":"3210 W Mc Graw St",
    "sg:city":"Seattle",
    "sg:classifiers":[
        {
            "category":"Insurance",
            "subcategory":"Insurance Agent",
            "type":"Services"
        }
    ],
    "sg:phone":"+1 206 282 4131",
    "sg:postcode":"98199",
    "sg:province":"WA",
    "wof:name":"Mechelsen Insurance Agency",
    "wof:placetype":"venue"
},
  "geometry": {"coordinates":[-122.39954299999999,47.639629],"type":"Point"}
}