{
  "type": "Feature",
  "properties": {
    "addr:full":"1406 NW 53rd St Seattle WA 98107",
    "addr:housenumber":"1406",
    "addr:postcode":"98107",
    "addr:street":"Nw 53Rd St",
    "iso:country":"US",
    "sg:address":"1406 NW 53rd St",
    "sg:city":"Seattle",
    "sg:classifiers":[
        {
            "category":"Education",
            "subcategory":"Special Training",
            "type":"Public Place"
        }
    ],
    "sg:phone":"+1 206 390 3122",
    "sg:postcode":"98107",
    "sg:province":"WA",
    "sg:tags":[
        "school",
        "specialty"
    ],
    "sg:website":"www.luminousworks.com/",
    "wof:name":"Luminous Works",
    "wof:placetype":"venue"
},
  "geometry": {"coordinates":[-122.374945,47.667196],"type":"Point"}
}