{
  "type": "Feature",
  "properties": {
    "addr:full":"1411 W Garland Ave Spokane WA 99205",
    "addr:housenumber":"1411",
    "addr:postcode":"99205",
    "addr:street":"W Garland Ave",
    "iso:country":"US",
    "sg:address":"1411 W Garland Ave",
    "sg:city":"Spokane",
    "sg:classifiers":[
        {
            "category":"Insurance",
            "subcategory":"Insurance Agent",
            "type":"Services"
        }
    ],
    "sg:phone":"+1 509 328 6969",
    "sg:postcode":"99205",
    "sg:province":"WA",
    "wof:name":"Cranston Insurance Agency",
    "wof:placetype":"venue"
},
  "geometry": {"coordinates":[-117.43291499999999,47.693419],"type":"Point"}
}