{
  "type": "Feature",
  "properties": {
    "addr:full":"10033 Bridgeport Way SW Lakewood WA 98499",
    "addr:housenumber":"10033",
    "addr:postcode":"98499",
    "addr:street":"Bridgeport Way Sw",
    "iso:country":"US",
    "sg:address":"10033 Bridgeport Way SW",
    "sg:city":"Lakewood",
    "sg:classifiers":[
        {
            "category":"Personal",
            "subcategory":"Tanning Parlor",
            "type":"Services"
        }
    ],
    "sg:phone":"+1 253 476 5999",
    "sg:postcode":"98499",
    "sg:province":"WA",
    "wof:name":"Pink Coconut Tanning Boutique",
    "wof:placetype":"venue"
},
  "geometry": {"coordinates":[-122.508003,47.165699],"type":"Point"}
}