{
  "type": "Feature",
  "properties": {
    "addr:full":"11322 N Guinevere Dr Spokane WA 99218",
    "addr:housenumber":"11322",
    "addr:postcode":"99218",
    "addr:street":"N Guinevere Dr",
    "iso:country":"US",
    "sg:address":"11322 N Guinevere Dr",
    "sg:city":"Spokane",
    "sg:classifiers":[
        {
            "category":"Professional",
            "subcategory":"Management & Consulting",
            "type":"Services"
        }
    ],
    "sg:phone":"+1 509 466 0510",
    "sg:postcode":"99218",
    "sg:province":"WA",
    "sg:tags":[
        "marketing",
        "consultant"
    ],
    "sg:website":"www.vision-marketing.net",
    "wof:name":"Vision Marketing & Sponsorship",
    "wof:placetype":"venue"
},
  "geometry": {"coordinates":[-117.395653,47.762038],"type":"Point"}
}