{
  "type": "Feature",
  "properties": {
    "addr:full":"711 King Ln Toppenish WA 98948",
    "addr:housenumber":"711",
    "addr:postcode":"98948",
    "addr:street":"King Ln",
    "iso:country":"US",
    "sg:address":"711 King Ln",
    "sg:city":"Toppenish",
    "sg:classifiers":[
        {
            "category":"Communications",
            "subcategory":"Radio Station",
            "type":"Services"
        }
    ],
    "sg:phone":"+1 509 865 5363",
    "sg:postcode":"98948",
    "sg:province":"WA",
    "sg:tags":[
        "company",
        "broadcasting"
    ],
    "wof:name":"Yakama Nation Radio",
    "wof:placetype":"venue"
},
  "geometry": {"coordinates":[-120.323382,46.376771],"type":"Point"}
}