{
  "type": "Feature",
  "properties": {
    "addr:full":"1311 S I St Tacoma WA 98405",
    "addr:housenumber":"1311",
    "addr:postcode":"98405",
    "addr:street":"S I St",
    "iso:country":"US",
    "sg:address":"1311 S I St",
    "sg:city":"Tacoma",
    "sg:classifiers":[
        {
            "category":"Place Of Worship",
            "subcategory":"Church",
            "type":"Public Place"
        },
        {
            "category":"Place Of Worship",
            "type":"Public Place"
        }
    ],
    "sg:phone":"+1 253 627 3569",
    "sg:postcode":"98405",
    "sg:province":"WA",
    "sg:tags":[
        "churches-baptist-general",
        "churches-baptist"
    ],
    "wof:name":"Mt Calvary Baptist Church",
    "wof:placetype":"venue"
},
  "geometry": {"coordinates":[-122.44836599999999,47.250139],"type":"Point"}
}