{
  "type": "Feature",
  "properties": {
    "addr:full":"2616 NE 55th Seattle WA 98105",
    "addr:housenumber":"2616",
    "addr:postcode":"98105",
    "addr:street":"Ne 55Th",
    "iso:country":"US",
    "sg:address":"2616 NE 55th",
    "sg:city":"Seattle",
    "sg:classifiers":[
        {
            "category":"Restaurant",
            "type":"Food & Drink"
        },
        {
            "category":"Bars & Pubs",
            "subcategory":"Champagne Bar",
            "type":"Food & Drink"
        }
    ],
    "sg:phone":"+1 206 525 0220",
    "sg:postcode":"98105",
    "sg:province":"WA",
    "sg:tags":[
        "new",
        "seafood",
        "american"
    ],
    "sg:website":"franksoysterhouse.com/",
    "wof:name":"Frank's Oyster House & Champagne Parlor",
    "wof:placetype":"venue"
},
  "geometry": {"coordinates":[-122.29933200000001,47.668519],"type":"Point"}
}