{
  "type": "Feature",
  "properties": {
    "iso:country":"US",
    "sg:address":"5211 S Orchard Ter",
    "sg:city":"Seattle",
    "sg:classifiers":[
        {
            "category":"Professional",
            "subcategory":"Business Services",
            "type":"Services"
        }
    ],
    "sg:phone":"+1 206 725 2707",
    "sg:postcode":"98118",
    "sg:province":"WA",
    "sg:tags":[
        "used",
        "merchandise"
    ],
    "wof:name":"Island Stamp Co",
    "wof:placetype":"venue"
},
  "geometry": {"coordinates":[-122.26593699999999,47.538462],"type":"Point"}
}