{
  "type": "Feature",
  "properties": {
    "addr:full":"509 Olive Way Ste 1320 Seattle WA 98101",
    "addr:housenumber":"509",
    "addr:postcode":"98101",
    "addr:street":"Olive Way Ste 1320",
    "iso:country":"US",
    "sg:address":"509 Olive Way Ste 1320",
    "sg:city":"Seattle",
    "sg:classifiers":[
        {
            "category":"Health Services",
            "subcategory":"Dentist",
            "type":"Services"
        }
    ],
    "sg:phone":"+1 206 521 9911",
    "sg:postcode":"98101",
    "sg:province":"WA",
    "sg:website":"www.emergencydentalcareusa.com",
    "wof:name":"Emergency Dental Care USA",
    "wof:placetype":"venue"
},
  "geometry": {"coordinates":[-122.33624,47.61289],"type":"Point"}
}