{
  "type": "Feature",
  "properties": {
    "iso:country":"US",
    "sg:address":"559 E Jewett Blvd",
    "sg:city":"White Salmon",
    "sg:classifiers":[
        {
            "category":"Professional",
            "subcategory":"Management & Consulting",
            "type":"Services"
        }
    ],
    "sg:phone":"+1 509 493 3221",
    "sg:postcode":"98672",
    "sg:province":"WA",
    "sg:tags":[
        "bakery"
    ],
    "wof:name":"R Bakery",
    "wof:placetype":"venue"
},
  "geometry": {"coordinates":[-121.481492,45.726573],"type":"Point"}
}