{
  "type": "Feature",
  "properties": {
    "addr:full":"508 Wellington Ave Walla Walla WA 99362",
    "addr:housenumber":"508",
    "addr:postcode":"99362",
    "addr:street":"Wellington Ave",
    "iso:country":"US",
    "sg:address":"508 Wellington Ave",
    "sg:city":"Walla Walla",
    "sg:classifiers":[
        {
            "category":"Home & Garden",
            "subcategory":"Building Materials",
            "type":"Retail Goods"
        }
    ],
    "sg:phone":"+1 509 525 4000",
    "sg:postcode":"99362",
    "sg:province":"WA",
    "sg:tags":[
        "lumber"
    ],
    "wof:name":"Lumbermen's Building Ctr",
    "wof:placetype":"venue"
},
  "geometry": {"coordinates":[-118.309629,46.078462],"type":"Point"}
}