{
  "type": "Feature",
  "properties": {
    "addr:full":"216 N Emerson St Chelan WA 98816",
    "addr:housenumber":"216",
    "addr:postcode":"98816",
    "addr:street":"N Emerson St",
    "iso:country":"US",
    "sg:address":"216 N Emerson St",
    "sg:city":"Chelan",
    "sg:classifiers":[
        {
            "category":"Education",
            "subcategory":"School",
            "type":"Public Place"
        }
    ],
    "sg:phone":"+1 509 682 2020",
    "sg:postcode":"98816",
    "sg:province":"WA",
    "wof:name":"Chelan Valley Independent Schl",
    "wof:placetype":"venue"
},
  "geometry": {"coordinates":[-120.016825,47.841564],"type":"Point"}
}