{
  "type": "Feature",
  "properties": {
    "addr:full":"617 S King St Seattle WA 98104",
    "addr:housenumber":"617",
    "addr:postcode":"98104",
    "addr:street":"S King St",
    "iso:country":"US",
    "sg:address":"617 S King St",
    "sg:city":"Seattle",
    "sg:classifiers":[
        {
            "category":"Shopping",
            "subcategory":"Florist",
            "type":"Retail Goods"
        }
    ],
    "sg:phone":"+1 206 621 1029",
    "sg:postcode":"98104",
    "sg:province":"WA",
    "wof:name":"Alice's Floral Designs",
    "wof:placetype":"venue"
},
  "geometry": {"coordinates":[-122.325947,47.598351],"type":"Point"}
}