{
  "type": "Feature",
  "properties": {
    "addr:full":"405 Castleview Pl Wenatchee WA 98801",
    "addr:housenumber":"405",
    "addr:postcode":"98801",
    "addr:street":"Castleview Pl",
    "iso:country":"US",
    "sg:address":"405 Castleview Pl",
    "sg:city":"Wenatchee",
    "sg:classifiers":[
        {
            "category":"Wholesale",
            "subcategory":"Non-durable Goods",
            "type":"Manufacturing & Wholesale Goods"
        }
    ],
    "sg:phone":"+1 509 664 9084",
    "sg:postcode":"98801",
    "sg:province":"WA",
    "wof:name":"Family Traditions",
    "wof:placetype":"venue"
},
  "geometry": {"coordinates":[-120.341722,47.418153],"type":"Point"}
}