{
  "type": "Feature",
  "properties": {
    "addr:full":"2810 Huckleberry Ln Stanwood WA 98282",
    "addr:housenumber":"2810",
    "addr:postcode":"98282",
    "addr:street":"Huckleberry Ln",
    "iso:country":"US",
    "sg:address":"2810 Huckleberry Ln",
    "sg:city":"Stanwood",
    "sg:classifiers":[
        {
            "category":"Building & Trades",
            "subcategory":"Equipment Rental",
            "type":"Services"
        }
    ],
    "sg:phone":"+1 360 387 2958",
    "sg:postcode":"98282",
    "sg:province":"WA",
    "sg:tags":[
        "party",
        "supply"
    ],
    "wof:name":"Airplay Party Rental",
    "wof:placetype":"venue"
},
  "geometry": {"coordinates":[-122.42723700000001,48.108292],"type":"Point"}
}