{
  "type": "Feature",
  "properties": {
    "iso:country":"US",
    "sg:address":"385 Court St",
    "sg:city":"Friday Harbor",
    "sg:classifiers":[
        {
            "category":"Health Services",
            "subcategory":"Doctor",
            "type":"Services"
        }
    ],
    "sg:phone":"+1 360 378 5300",
    "sg:postcode":"98250",
    "sg:province":"WA",
    "sg:tags":[
        "dentist"
    ],
    "wof:name":"Tooth Ferry Dental Office",
    "wof:placetype":"venue"
},
  "geometry": {"coordinates":[-123.018378,48.535292],"type":"Point"}
}