{
  "type": "Feature",
  "properties": {
    "iso:country":"US",
    "sg:address":"18375 Longmire St SE",
    "sg:city":"Monroe",
    "sg:classifiers":[
        {
            "category":"Banks & Credit Unions",
            "subcategory":"Financial Services",
            "type":"Services"
        }
    ],
    "sg:phone":"+1 360 805 9018",
    "sg:postcode":"98272",
    "sg:province":"WA",
    "sg:tags":[
        "investor"
    ],
    "wof:name":"Itj Investments Inc",
    "wof:placetype":"venue"
},
  "geometry": {"coordinates":[-121.984295,47.876297],"type":"Point"}
}