{
  "type": "Feature",
  "properties": {
    "addr:full":"1305 E White Creek Dr Port Angeles WA 98362",
    "addr:housenumber":"1305",
    "addr:postcode":"98362",
    "addr:street":"E White Creek Dr",
    "iso:country":"US",
    "sg:address":"1305 E White Creek Dr",
    "sg:city":"Port Angeles",
    "sg:classifiers":[
        {
            "category":"Professional",
            "subcategory":"Business Services",
            "type":"Services"
        }
    ],
    "sg:phone":"+1 360 457 9184",
    "sg:postcode":"98362",
    "sg:province":"WA",
    "sg:tags":[
        "property",
        "rental"
    ],
    "wof:name":"Patricia Roble",
    "wof:placetype":"venue"
},
  "geometry": {"coordinates":[-123.417348,48.070655],"type":"Point"}
}