{
  "type": "Feature",
  "properties": {
    "addr:full":"4103 Hillcrest Ave SW Seattle WA 98116",
    "addr:housenumber":"4103",
    "addr:postcode":"98116",
    "addr:street":"Hillcrest Ave Sw",
    "iso:country":"US",
    "sg:address":"4103 Hillcrest Ave SW",
    "sg:city":"Seattle",
    "sg:classifiers":[
        {
            "category":"Building & Trades",
            "subcategory":"Construction",
            "type":"Services"
        }
    ],
    "sg:phone":"+1 206 932 4219",
    "sg:postcode":"98116",
    "sg:province":"WA",
    "sg:tags":[
        "product",
        "floor",
        "mfg",
        "laying",
        "fabricated",
        "contractor",
        "rubber"
    ],
    "wof:name":"Southwest Recreational Inds",
    "wof:placetype":"venue"
},
  "geometry": {"coordinates":[-122.40451400000001,47.566674],"type":"Point"}
}