{
  "type": "Feature",
  "properties": {
    "addr:full":"1201 W Sprague Ave Spokane WA 99201",
    "addr:housenumber":"1201",
    "addr:postcode":"99201",
    "addr:street":"W Sprague Ave",
    "iso:country":"US",
    "sg:address":"1201 W Sprague Ave",
    "sg:city":"Spokane",
    "sg:classifiers":[
        {
            "category":"Communications",
            "subcategory":"Television Station",
            "type":"Services"
        }
    ],
    "sg:phone":"+1 509 448 4664",
    "sg:postcode":"99201",
    "sg:province":"WA",
    "sg:tags":[
        "broadcasting",
        "co"
    ],
    "sg:website":"www.khq.com",
    "wof:name":"Khqt",
    "wof:placetype":"venue"
},
  "geometry": {"coordinates":[-117.431113,47.657153],"type":"Point"}
}