{
  "type": "Feature",
  "properties": {
    "addr:full":"3201 NW Lower River Rd # 2575 Vancouver WA 98660",
    "addr:housenumber":"3201",
    "addr:postcode":"98660",
    "addr:street":"Nw Lower River Rd # 2575",
    "iso:country":"US",
    "sg:address":"3201 NW Lower River Rd # 2575",
    "sg:city":"Vancouver",
    "sg:classifiers":[
        {
            "category":"Manufacturing",
            "subcategory":"Metals",
            "type":"Manufacturing & Wholesale Goods"
        }
    ],
    "sg:phone":"+1 360 695 5949",
    "sg:postcode":"98660",
    "sg:province":"WA",
    "sg:tags":[
        "rolling",
        "forming"
    ],
    "sg:website":"http://www.seafab.com",
    "wof:name":"Seafab Metals Company",
    "wof:placetype":"venue"
},
  "geometry": {"coordinates":[-122.70374700000001,45.644215],"type":"Point"}
}