{
  "type": "Feature",
  "properties": {
    "addr:full":"615 2nd Ave Ste 402 Seattle WA 98104",
    "addr:housenumber":"615",
    "addr:postcode":"98104",
    "addr:street":"2Nd Ave Ste 402",
    "iso:country":"US",
    "sg:address":"615 2nd Ave Ste 402",
    "sg:city":"Seattle",
    "sg:phone":"+1 206 262 0363",
    "sg:postcode":"98104",
    "sg:province":"WA",
    "sg:website":"http://www.colehourcohen.com",
    "wof:name":"Envision Telephony Inc",
    "wof:placetype":"venue"
},
  "geometry": {"coordinates":[-122.332697,47.602378],"type":"Point"}
}