{
  "type": "Feature",
  "properties": {
    "addr:full":"2001 W Lincoln Ave Yakima WA 98902",
    "addr:housenumber":"2001",
    "addr:postcode":"98902",
    "addr:street":"W Lincoln Ave",
    "iso:country":"US",
    "sg:address":"2001 W Lincoln Ave",
    "sg:city":"Yakima",
    "sg:classifiers":[
        {
            "category":"Wholesale",
            "subcategory":"Medical Equipment & Supplies",
            "type":"Manufacturing & Wholesale Goods"
        },
        {
            "category":"Building & Trades",
            "subcategory":"Equipment Rental",
            "type":"Services"
        },
        {
            "category":"Shopping",
            "subcategory":"Pharmacy",
            "type":"Retail Goods"
        }
    ],
    "sg:phone":"+1 509 452 6541",
    "sg:postcode":"98902",
    "sg:province":"WA",
    "sg:tags":[
        "home",
        "care",
        "health",
        "wheelchairs-rental"
    ],
    "wof:name":"Keeler's Home Nursing Supplies",
    "wof:placetype":"venue"
},
  "geometry": {"coordinates":[-120.53574399999999,46.60347],"type":"Point"}
}