{
  "type": "Feature",
  "properties": {
    "addr:full":"635 W Ridge Dr Omak WA 98841",
    "addr:housenumber":"635",
    "addr:postcode":"98841",
    "addr:street":"W Ridge Dr",
    "iso:country":"US",
    "sg:address":"635 W Ridge Dr",
    "sg:city":"Omak",
    "sg:classifiers":[
        {
            "category":"Social Services",
            "subcategory":"Child Care",
            "type":"Services"
        }
    ],
    "sg:phone":"+1 509 826 2466",
    "sg:postcode":"98841",
    "sg:province":"WA",
    "sg:tags":[
        "kindergarten",
        "academic",
        "school"
    ],
    "wof:name":"Okanogan County Child Dev Assn",
    "wof:placetype":"venue"
},
  "geometry": {"coordinates":[-119.536823,48.401407],"type":"Point"}
}