{
  "type": "Feature",
  "properties": {
    "iso:country":"US",
    "sg:address":"15115 Bow Hill Rd",
    "sg:city":"Bow",
    "sg:classifiers":[
        {
            "category":"Farming",
            "subcategory":"Farm",
            "type":"Manufacturing & Wholesale Goods"
        }
    ],
    "sg:phone":"+1 360 766 6707",
    "sg:postcode":"98232",
    "sg:province":"WA",
    "wof:name":"Rootabaga Country Farms",
    "wof:placetype":"venue"
},
  "geometry": {"coordinates":[-122.41930499999999,48.564492],"type":"Point"}
}