{
  "type": "Feature",
  "properties": {
    "addr:full":"1327 E 54th St Tacoma WA 98404",
    "addr:housenumber":"1327",
    "addr:postcode":"98404",
    "addr:street":"E 54Th St",
    "iso:country":"US",
    "sg:address":"1327 E 54th St",
    "sg:city":"Tacoma",
    "sg:classifiers":[
        {
            "category":"Farming",
            "subcategory":"Nursery",
            "type":"Manufacturing & Wholesale Goods"
        }
    ],
    "sg:phone":"+1 253 475 1660",
    "sg:postcode":"98404",
    "sg:province":"WA",
    "sg:tags":[
        "tree",
        "grower",
        "nursery-wholesale",
        "nurseries-plants"
    ],
    "wof:name":"Hiltons Green House Inc",
    "wof:placetype":"venue"
},
  "geometry": {"coordinates":[-122.411124,47.20808],"type":"Point"}
}