{
  "type": "Feature",
  "properties": {
    "addr:full":"9240 215th Ave NE Redmond WA 98053",
    "addr:housenumber":"9240",
    "addr:postcode":"98053",
    "addr:street":"215Th Ave Ne",
    "iso:country":"US",
    "sg:address":"9240 215th Ave NE",
    "sg:city":"Redmond",
    "sg:classifiers":[
        {
            "category":"Building & Trades",
            "subcategory":"Construction",
            "type":"Services"
        }
    ],
    "sg:phone":"+1 425 868 2707",
    "sg:postcode":"98053",
    "sg:province":"WA",
    "sg:tags":[
        "foundation",
        "contractor"
    ],
    "wof:name":"J T Construction Co Inc",
    "wof:placetype":"venue"
},
  "geometry": {"coordinates":[-122.053054,47.683806],"type":"Point"}
}