{
  "type": "Feature",
  "properties": {
    "addr:full":"3620 Angel Flats Way Valley WA 99181",
    "addr:housenumber":"3620",
    "addr:postcode":"99181",
    "addr:street":"Angel Flats Way",
    "iso:country":"US",
    "sg:address":"3620 Angel Flats Way",
    "sg:city":"Valley",
    "sg:classifiers":[
        {
            "category":"Professional",
            "subcategory":"Detective & Security Services",
            "type":"Services"
        }
    ],
    "sg:phone":"+1 509 937 4204",
    "sg:postcode":"99181",
    "sg:province":"WA",
    "sg:tags":[
        "system"
    ],
    "wof:name":"Hafs Security",
    "wof:placetype":"venue"
},
  "geometry": {"coordinates":[-117.68209400000001,48.099112],"type":"Point"}
}