{
  "type": "Feature",
  "properties": {
    "addr:full":"1724 W Francis Ave Spokane WA 99205",
    "addr:housenumber":"1724",
    "addr:postcode":"99205",
    "addr:street":"W Francis Ave",
    "iso:country":"US",
    "sg:address":"1724 W Francis Ave",
    "sg:city":"Spokane",
    "sg:classifiers":[
        {
            "category":"Food & Beverages",
            "subcategory":"Groceries & Convenience Stores",
            "type":"Retail Goods"
        }
    ],
    "sg:phone":"+1 509 325 3431",
    "sg:postcode":"99205",
    "sg:province":"WA",
    "sg:tags":[
        "super",
        "supermarket"
    ],
    "sg:website":"http://www.rosauers.com",
    "wof:name":"Rosauers Pharmacy",
    "wof:placetype":"venue"
},
  "geometry": {"coordinates":[-117.43676499999999,47.715444],"type":"Point"}
}