{
  "type": "Feature",
  "properties": {
    "addr:full":"1000 SE 132nd Ave Vancouver WA 98683",
    "addr:housenumber":"1000",
    "addr:postcode":"98683",
    "addr:street":"Se 132Nd Ave",
    "iso:country":"US",
    "sg:address":"1000 SE 132nd Ave",
    "sg:city":"Vancouver",
    "sg:classifiers":[
        {
            "category":"Building & Trades",
            "subcategory":"Construction",
            "type":"Services"
        }
    ],
    "sg:phone":"+1 360 600 0522",
    "sg:postcode":"98683",
    "sg:province":"WA",
    "sg:tags":[
        "floor",
        "laying",
        "contractor"
    ],
    "wof:name":"Affordable Crpt Installations",
    "wof:placetype":"venue"
},
  "geometry": {"coordinates":[-122.537233,45.613938],"type":"Point"}
}