{
  "type": "Feature",
  "properties": {
    "addr:full":"1767 Hwy 395 S Chewelah WA 99109",
    "addr:housenumber":"1767",
    "addr:postcode":"99109",
    "addr:street":"Hwy 395 S Chewelah",
    "iso:country":"US",
    "sg:address":"1767 Hwy 395 S",
    "sg:city":"Chewelah",
    "sg:classifiers":[
        {
            "category":"Food & Beverages",
            "subcategory":"Specialty",
            "type":"Retail Goods"
        },
        {
            "category":"Professional",
            "subcategory":"Business Services",
            "type":"Services"
        }
    ],
    "sg:phone":"+1 509 935 6755",
    "sg:postcode":"99109",
    "sg:province":"WA",
    "sg:tags":[
        "water",
        "bulk",
        "company"
    ],
    "wof:name":"Lodi Water Co",
    "wof:placetype":"venue"
},
  "geometry": {"coordinates":[-117.787581,48.309811],"type":"Point"}
}