{
  "type": "Feature",
  "properties": {
    "addr:full":"4735 86th Ave SE Mercer Island WA 98040",
    "addr:housenumber":"4735",
    "addr:postcode":"98040",
    "addr:street":"86Th Ave Se",
    "iso:country":"US",
    "sg:address":"4735 86th Ave SE",
    "sg:city":"Mercer Island",
    "sg:classifiers":[
        {
            "category":"Organizations",
            "subcategory":"Membership Organization",
            "type":"Services"
        }
    ],
    "sg:phone":"+1 206 232 7339",
    "sg:postcode":"98040",
    "sg:province":"WA",
    "wof:name":"Saratoga Vista Water Assn",
    "wof:placetype":"venue"
},
  "geometry": {"coordinates":[-122.224334,47.561482],"type":"Point"}
}