{
  "type": "Feature",
  "properties": {
    "addr:full":"2608 N Alder St Tacoma WA 98407",
    "addr:housenumber":"2608",
    "addr:postcode":"98407",
    "addr:street":"N Alder St",
    "iso:country":"US",
    "sg:address":"2608 N Alder St",
    "sg:city":"Tacoma",
    "sg:classifiers":[
        {
            "category":"Personal",
            "type":"Services"
        }
    ],
    "sg:phone":"+1 253 756 5831",
    "sg:postcode":"98407",
    "sg:province":"WA",
    "sg:tags":[
        "electrolysis"
    ],
    "wof:name":"Electrolysis By Paula Haggard",
    "wof:placetype":"venue"
},
  "geometry": {"coordinates":[-122.477777,47.271914],"type":"Point"}
}