{
  "type": "Feature",
  "properties": {
    "addr:full":"309 Grandview Ave Sunnyside WA 98944",
    "addr:housenumber":"309",
    "addr:postcode":"98944",
    "addr:street":"Grandview Ave",
    "iso:country":"US",
    "sg:address":"309 Grandview Ave",
    "sg:city":"Sunnyside",
    "sg:classifiers":[
        {
            "category":"Professional",
            "subcategory":"Computer Services",
            "type":"Services"
        }
    ],
    "sg:phone":"+1 509 839 5595",
    "sg:postcode":"98944",
    "sg:province":"WA",
    "sg:tags":[
        "internet"
    ],
    "wof:name":"Axcess Internet Svc Inc",
    "wof:placetype":"venue"
},
  "geometry": {"coordinates":[-120.02269699999999,46.319927],"type":"Point"}
}