{
  "type": "Feature",
  "properties": {
    "addr:full":"1726 NW 59th St Seattle WA 98107",
    "addr:housenumber":"1726",
    "addr:postcode":"98107",
    "addr:street":"Nw 59Th St",
    "iso:country":"US",
    "sg:address":"1726 NW 59th St",
    "sg:city":"Seattle",
    "sg:classifiers":[
        {
            "category":"Utilities",
            "subcategory":"Electric",
            "type":"Services"
        }
    ],
    "sg:phone":"+1 206 782 8333",
    "sg:postcode":"98107",
    "sg:province":"WA",
    "sg:tags":[
        "equipment",
        "supplies-repair",
        "electronic",
        "equipment-repair"
    ],
    "wof:name":"Just Controls",
    "wof:placetype":"venue"
},
  "geometry": {"coordinates":[-122.37975299999999,47.671642],"type":"Point"}
}