{
  "type": "Feature",
  "properties": {
    "addr:full":"9256 45th Ave SW Seattle WA 98136",
    "addr:housenumber":"9256",
    "addr:postcode":"98136",
    "addr:street":"45Th Ave Sw",
    "iso:country":"US",
    "sg:address":"9256 45th Ave SW",
    "sg:city":"Seattle",
    "sg:classifiers":[
        {
            "category":"Professional",
            "subcategory":"Lawyer & Legal Services",
            "type":"Services"
        }
    ],
    "sg:phone":"+1 206 938 1313",
    "sg:postcode":"98136",
    "sg:province":"WA",
    "wof:name":"Ramey Mary Ellen",
    "wof:placetype":"venue"
},
  "geometry": {"coordinates":[-122.390315,47.520236],"type":"Point"}
}