{
  "type": "Feature",
  "properties": {
    "addr:full":"4309 Issaquah-Pine Lake Rd SE Sammamish WA 98075",
    "addr:housenumber":"4309",
    "addr:postcode":"98075",
    "addr:street":"Issaquah-Pine Lake Rd Se",
    "iso:country":"US",
    "sg:address":"4309 Issaquah-Pine Lake Rd SE",
    "sg:city":"Sammamish",
    "sg:classifiers":[
        {
            "category":"Real Estate",
            "subcategory":"Real Estate Operator",
            "type":"Services"
        }
    ],
    "sg:phone":"+1 425 427 9600",
    "sg:postcode":"98075",
    "sg:province":"WA",
    "sg:tags":[
        "condominium"
    ],
    "wof:name":"Jacobs Creek Condominiums",
    "wof:placetype":"venue"
},
  "geometry": {"coordinates":[-122.02418900000001,47.568889],"type":"Point"}
}