{
  "type": "Feature",
  "properties": {
    "addr:full":"20829 Hwy 99 Lynnwood WA 98036",
    "addr:housenumber":"20829",
    "addr:postcode":"98036",
    "addr:street":"Hwy 99",
    "iso:country":"US",
    "sg:address":"20829 Hwy 99",
    "sg:city":"Lynnwood",
    "sg:classifiers":[
        {
            "category":"Building & Trades",
            "subcategory":"Electrical",
            "type":"Services"
        },
        {
            "category":"Retail",
            "subcategory":"Repair Shop",
            "type":"Services"
        }
    ],
    "sg:phone":"+1 425 670 1701",
    "sg:postcode":"98036",
    "sg:province":"WA",
    "sg:tags":[
        "electrical",
        "electric",
        "contractor"
    ],
    "wof:name":"North Pacific Electronics Co",
    "wof:placetype":"venue"
},
  "geometry": {"coordinates":[-122.32441,47.809869],"type":"Point"}
}