{
  "type": "Feature",
  "properties": {
    "addr:full":"805 S Dearborn St Seattle WA 98134",
    "addr:housenumber":"805",
    "addr:postcode":"98134",
    "addr:street":"S Dearborn St",
    "iso:country":"US",
    "sg:address":"805 S Dearborn St",
    "sg:city":"Seattle",
    "sg:classifiers":[
        {
            "category":"Government",
            "subcategory":"Office",
            "type":"Public Place"
        }
    ],
    "sg:phone":"+1 206 386 1298",
    "sg:postcode":"98134",
    "sg:province":"WA",
    "sg:tags":[
        "medical",
        "executive",
        "administration",
        "business"
    ],
    "sg:website":"http://www.pioneerconstruction.com",
    "wof:name":"Weights & Measures Regulations",
    "wof:placetype":"venue"
},
  "geometry": {"coordinates":[-122.32241500000001,47.595822],"type":"Point"}
}