{
  "type": "Feature",
  "properties": {
    "addr:full":"13827 234th Ct NE Woodinville WA 98077",
    "addr:housenumber":"13827",
    "addr:postcode":"98077",
    "addr:street":"234Th Ct Ne",
    "iso:country":"US",
    "sg:address":"13827 234th Ct NE",
    "sg:city":"Woodinville",
    "sg:classifiers":[
        {
            "category":"Banks & Credit Unions",
            "subcategory":"Financial Services",
            "type":"Services"
        }
    ],
    "sg:phone":"+1 425 788 4048",
    "sg:postcode":"98077",
    "sg:province":"WA",
    "sg:tags":[
        "company",
        "holding"
    ],
    "wof:name":"Oracular Holdings",
    "wof:placetype":"venue"
},
  "geometry": {"coordinates":[-122.025364,47.72214],"type":"Point"}
}