{
  "type": "Feature",
  "properties": {
    "addr:full":"1833 Ricky Ct E Port Orchard WA 98366",
    "addr:housenumber":"1833",
    "addr:postcode":"98366",
    "addr:street":"Ricky Ct E",
    "iso:country":"US",
    "sg:address":"1833 Ricky Ct E",
    "sg:city":"Port Orchard",
    "sg:classifiers":[
        {
            "category":"Building & Trades",
            "subcategory":"Equipment Rental",
            "type":"Services"
        }
    ],
    "sg:phone":"+1 360 871 1779",
    "sg:postcode":"98366",
    "sg:province":"WA",
    "wof:name":"Tamis Touch",
    "wof:placetype":"venue"
},
  "geometry": {"coordinates":[-122.561018,47.544166],"type":"Point"}
}