{
  "type": "Feature",
  "properties": {
    "addr:full":"1851 Central Pl S Kent WA 98030",
    "addr:housenumber":"1851",
    "addr:postcode":"98030",
    "addr:street":"Central Pl S",
    "iso:country":"US",
    "sg:address":"1851 Central Pl S",
    "sg:city":"Kent",
    "sg:classifiers":[
        {
            "category":"Social Services",
            "type":"Services"
        }
    ],
    "sg:phone":"+1 253 850 1845",
    "sg:postcode":"98030",
    "sg:province":"WA",
    "wof:name":"Sound Bhavioral Hlth Solutions",
    "wof:placetype":"venue"
},
  "geometry": {"coordinates":[-122.229406,47.363354],"type":"Point"}
}