{
  "type": "Feature",
  "properties": {
    "addr:full":"6622 E Side Dr NE Tacoma WA 98422",
    "addr:housenumber":"6622",
    "addr:postcode":"98422",
    "addr:street":"E Side Dr Ne",
    "iso:country":"US",
    "sg:address":"6622 E Side Dr NE",
    "sg:city":"Tacoma",
    "sg:classifiers":[
        {
            "category":"Personal",
            "type":"Services"
        }
    ],
    "sg:phone":"+1 253 924 0874",
    "sg:postcode":"98422",
    "sg:province":"WA",
    "sg:tags":[
        "therapist",
        "massage"
    ],
    "wof:name":"Balancing Touch Therapeutic",
    "wof:placetype":"venue"
},
  "geometry": {"coordinates":[-122.43458200000001,47.300335],"type":"Point"}
}