{
  "type": "Feature",
  "properties": {
    "addr:full":"234 Wood Ave SW Bainbridge Island WA 98110",
    "addr:housenumber":"234",
    "addr:postcode":"98110",
    "addr:street":"Wood Ave Sw Bainbridge",
    "iso:country":"US",
    "sg:address":"234 Wood Ave SW",
    "sg:city":"Bainbridge Island",
    "sg:classifiers":[
        {
            "category":"Real Estate",
            "subcategory":"Real Estate Operator",
            "type":"Services"
        }
    ],
    "sg:phone":"+1 206 842 3722",
    "sg:postcode":"98110",
    "sg:province":"WA",
    "sg:tags":[
        "apartment"
    ],
    "sg:website":"www.assistedlivingnw.com",
    "wof:name":"Winslow Manor Apartments",
    "wof:placetype":"venue"
},
  "geometry": {"coordinates":[-122.524002,47.623901],"type":"Point"}
}