{
  "type": "Feature",
  "properties": {
    "addr:full":"320 E 32nd St Tacoma WA 98404",
    "addr:housenumber":"320",
    "addr:postcode":"98404",
    "addr:street":"E 32Nd St",
    "iso:country":"US",
    "sg:address":"320 E 32nd St",
    "sg:city":"Tacoma",
    "sg:classifiers":[
        {
            "category":"Wholesale",
            "subcategory":"Scrap",
            "type":"Manufacturing & Wholesale Goods"
        }
    ],
    "sg:phone":"+1 253 964 3690",
    "sg:postcode":"98404",
    "sg:province":"WA",
    "sg:tags":[
        "product",
        "metal",
        "ferrous",
        "nonferrous"
    ],
    "wof:name":"Generl Commodity Co",
    "wof:placetype":"venue"
},
  "geometry": {"coordinates":[-122.427847,47.232731],"type":"Point"}
}