{
  "type": "Feature",
  "properties": {
    "addr:full":"4505 39th Ave SW Seattle WA 98116",
    "addr:housenumber":"4505",
    "addr:postcode":"98116",
    "addr:street":"39Th Ave Sw",
    "iso:country":"US",
    "sg:address":"4505 39th Ave SW",
    "sg:city":"Seattle",
    "sg:classifiers":[
        {
            "category":"Sports & Exercise",
            "subcategory":"Bowling",
            "type":"Entertainment"
        }
    ],
    "sg:phone":"+1 206 923 3138",
    "sg:postcode":"98116",
    "sg:province":"WA",
    "wof:name":"Greater Seattle Bowling Association",
    "wof:placetype":"venue"
},
  "geometry": {"coordinates":[-122.38099699999999,47.562599],"type":"Point"}
}