{
  "type": "Feature",
  "properties": {
    "addr:full":"301 E 17th St Vancouver WA 98663",
    "addr:housenumber":"301",
    "addr:postcode":"98663",
    "addr:street":"E 17Th St",
    "iso:country":"US",
    "sg:address":"301 E 17th St",
    "sg:city":"Vancouver",
    "sg:classifiers":[
        {
            "category":"Real Estate",
            "subcategory":"Real Estate Services",
            "type":"Services"
        }
    ],
    "sg:phone":"+1 360 694 1031",
    "sg:postcode":"98663",
    "sg:province":"WA",
    "sg:tags":[
        "management",
        "property"
    ],
    "sg:website":"www.ephillipsgroup.com",
    "wof:name":"The Phillips Group, Inc",
    "wof:placetype":"venue"
},
  "geometry": {"coordinates":[-122.669026,45.633879],"type":"Point"}
}