{
  "type": "Feature",
  "properties": {
    "addr:full":"23003 60th Ave W Mountlake Ter WA 98043",
    "addr:housenumber":"23003",
    "addr:postcode":"98043",
    "addr:street":"60Th Ave W Mountlake Ter",
    "iso:country":"US",
    "sg:address":"23003 60th Ave W",
    "sg:city":"Mountlake Ter",
    "sg:classifiers":[
        {
            "category":"Professional",
            "subcategory":"Secretarial Services",
            "type":"Services"
        }
    ],
    "sg:phone":"+1 425 778 2897",
    "sg:postcode":"98043",
    "sg:province":"WA",
    "sg:tags":[
        "reporting",
        "court"
    ],
    "wof:name":"Terrace Word Processing",
    "wof:placetype":"venue"
},
  "geometry": {"coordinates":[-122.31379099999999,47.7885],"type":"Point"}
}