{
  "type": "Feature",
  "properties": {
    "addr:full":"1043 S Bay Rd NE Olympia WA 98506",
    "addr:housenumber":"1043",
    "addr:postcode":"98506",
    "addr:street":"S Bay Rd Ne",
    "iso:country":"US",
    "sg:address":"1043 S Bay Rd NE",
    "sg:city":"Olympia",
    "sg:classifiers":[
        {
            "category":"Professional",
            "subcategory":"Art Services",
            "type":"Services"
        }
    ],
    "sg:phone":"+1 360 786 9790",
    "sg:postcode":"98506",
    "sg:province":"WA",
    "sg:tags":[
        "commercial",
        "design"
    ],
    "wof:name":"Artworks",
    "wof:placetype":"venue"
},
  "geometry": {"coordinates":[-122.86303599999999,47.053027],"type":"Point"}
}