{
  "type": "Feature",
  "properties": {
    "addr:full":"2780 Old Naches Hwy Yakima WA 98908",
    "addr:housenumber":"2780",
    "addr:postcode":"98908",
    "addr:street":"Old Naches Hwy",
    "iso:country":"US",
    "sg:address":"2780 Old Naches Hwy",
    "sg:city":"Yakima",
    "sg:classifiers":[
        {
            "category":"Real Estate",
            "subcategory":"Real Estate Agent",
            "type":"Services"
        }
    ],
    "sg:phone":"+1 509 966 5818",
    "sg:postcode":"98908",
    "sg:province":"WA",
    "wof:name":"Audreys Antiques",
    "wof:placetype":"venue"
},
  "geometry": {"coordinates":[-120.608504,46.668459],"type":"Point"}
}