{
  "type": "Feature",
  "properties": {
    "addr:full":"5213 Klahanie Dr NW Olympia WA 98502",
    "addr:housenumber":"5213",
    "addr:postcode":"olympia wa 98502",
    "addr:street":"Klahanie Dr Nw",
    "iso:country":"US",
    "sg:address":"5213 Klahanie Dr NW",
    "sg:city":"Olympia",
    "sg:classifiers":[
        {
            "category":"Professional",
            "subcategory":"Management & Consulting",
            "type":"Services"
        }
    ],
    "sg:phone":"+1 360 866 6337",
    "sg:postcode":"98502",
    "sg:province":"WA",
    "wof:name":"Dorothy Benston",
    "wof:placetype":"venue"
},
  "geometry": {"coordinates":[-122.936787,47.108157],"type":"Point"}
}