{
  "type": "Feature",
  "properties": {
    "addr:full":"604 W Evergreen Blvd Vancouver WA 98660",
    "addr:housenumber":"604",
    "addr:postcode":"98660",
    "addr:street":"W Evergreen Blvd",
    "iso:country":"US",
    "sg:address":"604 W Evergreen Blvd",
    "sg:city":"Vancouver",
    "sg:classifiers":[
        {
            "category":"Professional",
            "subcategory":"Research",
            "type":"Services"
        }
    ],
    "sg:phone":"+1 360 694 3704",
    "sg:postcode":"98660",
    "sg:province":"WA",
    "sg:tags":[
        "development",
        "laboratory",
        "commercial",
        "nonphysical"
    ],
    "sg:website":"www.microet.com",
    "wof:name":"Microenergy Technologies Inc",
    "wof:placetype":"venue"
},
  "geometry": {"coordinates":[-122.67813200000001,45.628914],"type":"Point"}
}