{
  "type": "Feature",
  "properties": {
    "addr:full":"1918 3rd Ave Seattle WA 98101",
    "addr:housenumber":"1918",
    "addr:postcode":"98101",
    "addr:street":"3Rd Ave",
    "iso:country":"US",
    "sg:address":"1918 3rd Ave",
    "sg:city":"Seattle",
    "sg:classifiers":[
        {
            "category":"Health Services",
            "subcategory":"Optometrist",
            "type":"Services"
        },
        {
            "category":"Shopping",
            "subcategory":"Optician",
            "type":"Retail Goods"
        }
    ],
    "sg:phone":"+1 206 623 1758",
    "sg:postcode":"98101",
    "sg:province":"WA",
    "sg:tags":[
        "eyewear"
    ],
    "sg:website":"www.youreyesllc.com",
    "wof:name":"Your Eyes",
    "wof:placetype":"venue"
},
  "geometry": {"coordinates":[-122.34019499999999,47.612],"type":"Point"}
}