{
  "type": "Feature",
  "properties": {
    "addr:full":"242 E State St Mossyrock WA 98564",
    "addr:housenumber":"242",
    "addr:postcode":"98564",
    "addr:street":"E State St",
    "iso:country":"US",
    "sg:address":"242 E State St",
    "sg:city":"Mossyrock",
    "sg:classifiers":[
        {
            "category":"Personal",
            "subcategory":"Beauty Salon",
            "type":"Services"
        }
    ],
    "sg:phone":"+1 360 983 8939",
    "sg:postcode":"98564",
    "sg:province":"WA",
    "sg:tags":[
        "shop"
    ],
    "wof:name":"Debra's Clips Cuts & Styles",
    "wof:placetype":"venue"
},
  "geometry": {"coordinates":[-122.481865,46.528787],"type":"Point"}
}