{
  "type": "Feature",
  "properties": {
    "addr:full":"3125 Simpson Ave Hoquiam WA 98550",
    "addr:housenumber":"3125",
    "addr:postcode":"98550",
    "addr:street":"Simpson Ave",
    "iso:country":"US",
    "sg:address":"3125 Simpson Ave",
    "sg:city":"Hoquiam",
    "sg:classifiers":[
        {
            "category":"Autos & Motor Vehicles",
            "subcategory":"Auto Supplies",
            "type":"Retail Goods"
        }
    ],
    "sg:phone":"+1 360 532 4800",
    "sg:postcode":"98550",
    "sg:province":"WA",
    "sg:tags":[
        "equipment",
        "racing",
        "car",
        "automobile"
    ],
    "wof:name":"STI Racing Supplies",
    "wof:placetype":"venue"
},
  "geometry": {"coordinates":[-123.853854,46.975233],"type":"Point"}
}