{
  "type": "Feature",
  "properties": {
    "addr:full":"210 E Mcloughlin Blvd Vancouver WA 98663",
    "addr:housenumber":"210",
    "addr:postcode":"98663",
    "addr:street":"E Mcloughlin Blvd",
    "iso:country":"US",
    "sg:address":"210 E Mcloughlin Blvd",
    "sg:city":"Vancouver",
    "sg:classifiers":[
        {
            "category":"Health Services",
            "subcategory":"Chiropractor",
            "type":"Services"
        }
    ],
    "sg:phone":"+1 360 693 0400",
    "sg:postcode":"98663",
    "sg:province":"WA",
    "sg:tags":[
        "chiropractic"
    ],
    "wof:name":"Bauman Chiropractic",
    "wof:placetype":"venue"
},
  "geometry": {"coordinates":[-122.670292,45.634898],"type":"Point"}
}