{
  "type": "Feature",
  "properties": {
    "addr:full":"19000 33rd Ave W Lynnwood WA 98036",
    "addr:housenumber":"19000",
    "addr:postcode":"98036",
    "addr:street":"33Rd Ave W",
    "iso:country":"US",
    "sg:address":"19000 33rd Ave W",
    "sg:city":"Lynnwood",
    "sg:classifiers":[
        {
            "category":"Banks & Credit Unions",
            "subcategory":"Bank",
            "type":"Services"
        }
    ],
    "sg:phone":"+1 425 776 4266",
    "sg:postcode":"98036",
    "sg:province":"WA",
    "sg:tags":[
        "loan",
        "broker"
    ],
    "wof:name":"Rbc Mortgage",
    "wof:placetype":"venue"
},
  "geometry": {"coordinates":[-122.277833,47.824273],"type":"Point"}
}