{
  "type": "Feature",
  "properties": {
    "addr:full":"9612 E Sprague Ave Spokane WA 99206",
    "addr:housenumber":"9612",
    "addr:postcode":"99206",
    "addr:street":"E Sprague Ave",
    "iso:country":"US",
    "sg:address":"9612 E Sprague Ave",
    "sg:city":"Spokane",
    "sg:classifiers":[
        {
            "category":"Home & Garden",
            "subcategory":"Home Furnishings",
            "type":"Retail Goods"
        }
    ],
    "sg:phone":"+1 509 927 8367",
    "sg:postcode":"99206",
    "sg:province":"WA",
    "wof:name":"Cutco Cutlery",
    "wof:placetype":"venue"
},
  "geometry": {"coordinates":[-117.27598,47.656928],"type":"Point"}
}