{
  "type": "Feature",
  "properties": {
    "addr:full":"2346 33rd Ave S Seattle WA 98144",
    "addr:housenumber":"2346",
    "addr:postcode":"98144",
    "addr:street":"33Rd Ave S",
    "iso:country":"US",
    "sg:address":"2346 33rd Ave S",
    "sg:city":"Seattle",
    "sg:classifiers":[
        {
            "category":"Organizations",
            "subcategory":"Religious Organization",
            "type":"Services"
        }
    ],
    "sg:phone":"+1 206 760 0583",
    "sg:postcode":"98144",
    "sg:province":"WA",
    "wof:name":"Cabrini Ministry",
    "wof:placetype":"venue"
},
  "geometry": {"coordinates":[-122.290796,47.58132],"type":"Point"}
}