{
  "type": "Feature",
  "properties": {
    "addr:full":"1565 Main St Ferndale WA 98248",
    "addr:housenumber":"1565",
    "addr:postcode":"98248",
    "addr:street":"Main St",
    "iso:country":"US",
    "sg:address":"1565 Main St",
    "sg:city":"Ferndale",
    "sg:classifiers":[
        {
            "category":"Professional",
            "subcategory":"Business Services",
            "type":"Services"
        }
    ],
    "sg:phone":"+1 360 384 6887",
    "sg:postcode":"98248",
    "sg:province":"WA",
    "wof:name":"Koala T Pool and Spa Service",
    "wof:placetype":"venue"
},
  "geometry": {"coordinates":[-122.56415200000001,48.847398],"type":"Point"}
}