{
  "type": "Feature",
  "properties": {
    "addr:full":"24121 115th Ave NE Arlington WA 98223",
    "addr:housenumber":"24121",
    "addr:postcode":"98223",
    "addr:street":"115Th Ave Ne",
    "iso:country":"US",
    "sg:address":"24121 115th Ave NE",
    "sg:city":"Arlington",
    "sg:classifiers":[
        {
            "category":"Manufacturing",
            "subcategory":"Jewelry",
            "type":"Manufacturing & Wholesale Goods"
        }
    ],
    "sg:phone":"+1 360 435 5288",
    "sg:postcode":"98223",
    "sg:province":"WA",
    "sg:tags":[
        "costume",
        "mfg"
    ],
    "wof:name":"Designs By Lori Lynn",
    "wof:placetype":"venue"
},
  "geometry": {"coordinates":[-122.07438999999999,48.213694],"type":"Point"}
}