{
  "type": "Feature",
  "properties": {
    "addr:full":"2530 15th Ave W Seattle WA 98119",
    "addr:housenumber":"2530",
    "addr:postcode":"98119",
    "addr:street":"15Th Ave W",
    "iso:country":"US",
    "sg:address":"2530 15th Ave W",
    "sg:city":"Seattle",
    "sg:classifiers":[
        {
            "category":"Health Services",
            "subcategory":"Health Practitioner",
            "type":"Services"
        }
    ],
    "sg:phone":"+1 206 542 2339",
    "sg:postcode":"98119",
    "sg:province":"WA",
    "sg:tags":[
        "nutritionist"
    ],
    "wof:name":"Innovative Dietary Svc",
    "wof:placetype":"venue"
},
  "geometry": {"coordinates":[-122.376138,47.641754],"type":"Point"}
}