{
  "type": "Feature",
  "properties": {
    "addr:full":"1100 Pacific Ave Everett WA 98201",
    "addr:housenumber":"1100",
    "addr:postcode":"98201",
    "addr:street":"Pacific Ave",
    "iso:country":"US",
    "sg:address":"1100 Pacific Ave",
    "sg:city":"Everett",
    "sg:classifiers":[
        {
            "category":"Health Services",
            "subcategory":"Doctor",
            "type":"Services"
        }
    ],
    "sg:phone":"+1 425 258 3130",
    "sg:postcode":"98201",
    "sg:province":"WA",
    "sg:tags":[
        "dentist"
    ],
    "wof:name":"Gregory A Hanson DDS PS",
    "wof:placetype":"venue"
},
  "geometry": {"coordinates":[-122.21423,47.976424],"type":"Point"}
}