{
  "type": "Feature",
  "properties": {
    "addr:full":"1006 Main Street Vancouver WA 98660",
    "addr:housenumber":"1006",
    "addr:postcode":"98660",
    "addr:street":"Main Street",
    "iso:country":"US",
    "sg:address":"1006 Main Street",
    "sg:city":"Vancouver",
    "sg:classifiers":[
        {
            "category":"Shopping",
            "subcategory":"Antiques",
            "type":"Retail Goods"
        },
        {
            "category":"Shopping",
            "subcategory":"Used Merchandise",
            "type":"Retail Goods"
        }
    ],
    "sg:phone":"+1 503 206 3075",
    "sg:postcode":"98660",
    "sg:province":"WA",
    "sg:tags":[
        "vintage",
        "consignment"
    ],
    "sg:website":"www.swoonantiques.com",
    "wof:name":"Swoon Antiques Salon",
    "wof:placetype":"venue"
},
  "geometry": {"coordinates":[-122.67164699999999,45.629103],"type":"Point"}
}