{
  "type": "Feature",
  "properties": {
    "addr:full":"8716 NE 132nd St Kirkland WA 98034",
    "addr:housenumber":"8716",
    "addr:postcode":"98034",
    "addr:street":"Ne 132Nd St",
    "iso:country":"US",
    "sg:address":"8716 NE 132nd St",
    "sg:city":"Kirkland",
    "sg:classifiers":[
        {
            "category":"Building & Trades",
            "subcategory":"Cleaning & Sanitation",
            "type":"Services"
        }
    ],
    "sg:phone":"+1 425 823 2283",
    "sg:postcode":"98034",
    "sg:province":"WA",
    "sg:tags":[
        "maintenance"
    ],
    "wof:name":"ServiceMaster",
    "wof:placetype":"venue"
},
  "geometry": {"coordinates":[-122.224253,47.718719],"type":"Point"}
}