{
  "type": "Feature",
  "properties": {
    "addr:full":"9727 Lundeen Rd SW Rochester WA 98579",
    "addr:housenumber":"9727",
    "addr:postcode":"98579",
    "addr:street":"Lundeen Rd Sw",
    "iso:country":"US",
    "sg:address":"9727 Lundeen Rd SW",
    "sg:city":"Rochester",
    "sg:classifiers":[
        {
            "category":"Building & Trades",
            "subcategory":"Construction",
            "type":"Services"
        }
    ],
    "sg:phone":"+1 360 446 1709",
    "sg:postcode":"98579",
    "sg:province":"WA",
    "sg:tags":[
        "excavating",
        "contractor"
    ],
    "wof:name":"Schock Brothers Inc",
    "wof:placetype":"venue"
},
  "geometry": {"coordinates":[-123.09945,46.795716],"type":"Point"}
}