{
  "type": "Feature",
  "properties": {
    "addr:full":"10120 212th Ave NE Redmond WA 98053",
    "addr:housenumber":"10120",
    "addr:postcode":"98053",
    "addr:street":"212Th Ave Ne",
    "iso:country":"US",
    "sg:address":"10120 212th Ave NE",
    "sg:city":"Redmond",
    "sg:classifiers":[
        {
            "category":"Retail",
            "subcategory":"Repair Shop",
            "type":"Services"
        }
    ],
    "sg:phone":"+1 425 868 2815",
    "sg:postcode":"98053",
    "sg:province":"WA",
    "sg:tags":[
        "television",
        "radio"
    ],
    "wof:name":"A B C T V & Video Electronics",
    "wof:placetype":"venue"
},
  "geometry": {"coordinates":[-122.05709400000001,47.687623],"type":"Point"}
}