{
  "type": "Feature",
  "properties": {
    "addr:full":"10511 Exeter Ave NE Seattle WA 98125",
    "addr:housenumber":"10511",
    "addr:postcode":"98125",
    "addr:street":"Exeter Ave Ne",
    "iso:country":"US",
    "sg:address":"10511 Exeter Ave NE",
    "sg:city":"Seattle",
    "sg:classifiers":[
        {
            "category":"Professional",
            "subcategory":"Business Services",
            "type":"Services"
        }
    ],
    "sg:phone":"+1 206 368 3411",
    "sg:postcode":"98125",
    "sg:province":"WA",
    "wof:name":"Jeremy Mays Design",
    "wof:placetype":"venue"
},
  "geometry": {"coordinates":[-122.276088,47.705448],"type":"Point"}
}