{
  "type": "Feature",
  "properties": {
    "addr:full":"253 Camelia St Royal City WA 99357",
    "addr:housenumber":"253",
    "addr:postcode":"99357",
    "addr:street":"Camelia St",
    "iso:country":"US",
    "sg:address":"253 Camelia St",
    "sg:city":"Royal City",
    "sg:classifiers":[
        {
            "category":"Wholesale",
            "subcategory":"Farm Supplies",
            "type":"Manufacturing & Wholesale Goods"
        }
    ],
    "sg:phone":"+1 509 346 2124",
    "sg:postcode":"99357",
    "sg:province":"WA",
    "sg:tags":[
        "alfalfa",
        "hay"
    ],
    "wof:name":"Agri-Pac",
    "wof:placetype":"venue"
},
  "geometry": {"coordinates":[-119.63661,46.899887],"type":"Point"}
}