{
  "type": "Feature",
  "properties": {
    "addr:full":"1275 Westlake Ave N Seattle WA 98109",
    "addr:housenumber":"1275",
    "addr:postcode":"98109",
    "addr:street":"Westlake Ave N",
    "iso:country":"US",
    "sg:address":"1275 Westlake Ave N",
    "sg:city":"Seattle",
    "sg:classifiers":[
        {
            "category":"Sports & Exercise",
            "subcategory":"Gym",
            "type":"Entertainment"
        }
    ],
    "sg:phone":"+1 206 283 7929",
    "sg:postcode":"98109",
    "sg:province":"WA",
    "sg:tags":[
        "club",
        "health",
        "studio",
        "gymnasium"
    ],
    "wof:name":"American Health & Fitness",
    "wof:placetype":"venue"
},
  "geometry": {"coordinates":[-122.341055,47.63008],"type":"Point"}
}