{
  "type": "Feature",
  "properties": {
    "addr:full":"1396 Roma Rd Bellingham WA 98226",
    "addr:housenumber":"1396",
    "addr:postcode":"98226",
    "addr:street":"Roma Rd",
    "iso:country":"US",
    "sg:address":"1396 Roma Rd",
    "sg:city":"Bellingham",
    "sg:classifiers":[
        {
            "category":"Building & Trades",
            "subcategory":"Construction",
            "type":"Services"
        }
    ],
    "sg:phone":"+1 360 647 1319",
    "sg:postcode":"98226",
    "sg:province":"WA",
    "sg:tags":[
        "concrete",
        "contractor"
    ],
    "wof:name":"Ron Victor Concrete",
    "wof:placetype":"venue"
},
  "geometry": {"coordinates":[-122.41224699999999,48.784711],"type":"Point"}
}