{
  "type": "Feature",
  "properties": {
    "addr:full":"9805 NE 116th St Kirkland WA 98034",
    "addr:housenumber":"9805",
    "addr:postcode":"98034",
    "addr:street":"Ne 116Th St",
    "iso:country":"US",
    "sg:address":"9805 NE 116th St",
    "sg:city":"Kirkland",
    "sg:classifiers":[
        {
            "category":"Professional",
            "subcategory":"Management & Consulting",
            "type":"Services"
        },
        {
            "category":"Shopping",
            "subcategory":"Bicycles & Sporting Goods",
            "type":"Retail Goods"
        }
    ],
    "sg:phone":"+1 425 821 8372",
    "sg:postcode":"98034",
    "sg:province":"WA",
    "sg:tags":[
        "construction",
        "golf",
        "supply"
    ],
    "wof:name":"Cascade Sports",
    "wof:placetype":"venue"
},
  "geometry": {"coordinates":[-122.20935799999999,47.703943],"type":"Point"}
}