{
  "type": "Feature",
  "properties": {
    "addr:full":"34 Street & 192 Ave Vancouver WA 98660",
    "addr:postcode":"98660",
    "addr:street":"34 Street & 192 Ave",
    "iso:country":"US",
    "sg:address":"34 Street & 192 Ave",
    "sg:city":"Vancouver",
    "sg:classifiers":[
        {
            "category":"Health Services",
            "subcategory":"Dentist",
            "type":"Services"
        }
    ],
    "sg:phone":"+1 360 450 5286",
    "sg:postcode":"98660",
    "sg:province":"WA",
    "wof:name":"Wendel Family Dental Center",
    "wof:placetype":"venue"
},
  "geometry": {"coordinates":[-122.478056,45.596723],"type":"Point"}
}