{
  "type": "Feature",
  "properties": {
    "addr:full":"710 Lakeside Ave S Seattle WA 98144",
    "addr:housenumber":"710",
    "addr:postcode":"98144",
    "addr:street":"Lakeside Ave S",
    "iso:country":"US",
    "sg:address":"710 Lakeside Ave S",
    "sg:city":"Seattle",
    "sg:classifiers":[
        {
            "category":"Professional",
            "subcategory":"Management & Consulting",
            "type":"Services"
        }
    ],
    "sg:phone":"+1 206 910 4932",
    "sg:postcode":"98144",
    "sg:province":"WA",
    "wof:name":"Mosley & Associates",
    "wof:placetype":"venue"
},
  "geometry": {"coordinates":[-122.287666,47.596035],"type":"Point"}
}