{
  "type": "Feature",
  "properties": {
    "addr:full":"4560 Somerset Pl SE Bellevue WA 98006",
    "addr:housenumber":"4560",
    "addr:postcode":"98006",
    "addr:street":"Somerset Pl Se",
    "iso:country":"US",
    "sg:address":"4560 Somerset Pl SE",
    "sg:city":"Bellevue",
    "sg:classifiers":[
        {
            "category":"Professional",
            "subcategory":"Engineering",
            "type":"Services"
        }
    ],
    "sg:phone":"+1 425 562 8965",
    "sg:postcode":"98006",
    "sg:province":"WA",
    "wof:name":"Nothwest Pacific Engineering",
    "wof:placetype":"venue"
},
  "geometry": {"coordinates":[-122.158519,47.562751],"type":"Point"}
}