{
  "type": "Feature",
  "properties": {
    "addr:full":"11212 NE 53rd Ct Vancouver WA 98686",
    "addr:housenumber":"11212",
    "addr:postcode":"98686",
    "addr:street":"Ne 53Rd Ct",
    "iso:country":"US",
    "sg:address":"11212 NE 53rd Ct",
    "sg:city":"Vancouver",
    "sg:classifiers":[
        {
            "category":"Home & Garden",
            "subcategory":"Building Materials",
            "type":"Retail Goods"
        },
        {
            "category":"Building & Trades",
            "subcategory":"Construction",
            "type":"Services"
        }
    ],
    "sg:phone":"+1 360 573 8126",
    "sg:postcode":"98686",
    "sg:province":"WA",
    "sg:tags":[
        "door",
        "contractor"
    ],
    "wof:name":"Brutus Garage Door Specialists",
    "wof:placetype":"venue"
},
  "geometry": {"coordinates":[-122.61717299999999,45.703205],"type":"Point"}
}