{
  "type": "Feature",
  "properties": {
    "addr:full":"412 Lamar Ln Sequim WA 98382",
    "addr:housenumber":"412",
    "addr:postcode":"98382",
    "addr:street":"Lamar Ln",
    "iso:country":"US",
    "sg:address":"412 Lamar Ln",
    "sg:city":"Sequim",
    "sg:classifiers":[
        {
            "category":"Farming",
            "subcategory":"Farm",
            "type":"Manufacturing & Wholesale Goods"
        }
    ],
    "sg:phone":"+1 360 683 5820",
    "sg:postcode":"98382",
    "sg:province":"WA",
    "sg:tags":[
        "crop",
        "general"
    ],
    "wof:name":"Paul Lotzgesell",
    "wof:placetype":"venue"
},
  "geometry": {"coordinates":[-123.16196100000001,48.133758],"type":"Point"}
}