{
  "type": "Feature",
  "properties": {
    "addr:full":"465 N Bend Blvd N North Bend WA 98045",
    "addr:housenumber":"465",
    "addr:postcode":"98045",
    "addr:street":"N Bend Blvd N",
    "iso:country":"US",
    "sg:address":"465 N Bend Blvd N",
    "sg:city":"North Bend",
    "sg:classifiers":[
        {
            "category":"Professional",
            "subcategory":"Business Services",
            "type":"Services"
        }
    ],
    "sg:phone":"+1 425 831 5733",
    "sg:postcode":"98045",
    "sg:province":"WA",
    "wof:name":"Basics By McCallum",
    "wof:placetype":"venue"
},
  "geometry": {"coordinates":[-121.78906600000001,47.499604],"type":"Point"}
}