{
  "type": "Feature",
  "properties": {
    "addr:full":"4180 134th Ave NE Bellevue WA 98005",
    "addr:housenumber":"4180",
    "addr:postcode":"98005",
    "addr:street":"134Th Ave Ne",
    "iso:country":"US",
    "sg:address":"4180 134th Ave NE",
    "sg:city":"Bellevue",
    "sg:classifiers":[
        {
            "category":"Banks & Credit Unions",
            "subcategory":"Financial Services",
            "type":"Services"
        }
    ],
    "sg:phone":"+1 425 885 1308",
    "sg:postcode":"98005",
    "sg:province":"WA",
    "sg:tags":[
        "trust",
        "management"
    ],
    "wof:name":"Ash Gudaitis Foundation",
    "wof:placetype":"venue"
},
  "geometry": {"coordinates":[-122.161382,47.6466],"type":"Point"}
}