{
  "type": "Feature",
  "properties": {
    "addr:full":"13210 SE 253rd Pl Kent WA 98042",
    "addr:postcode":"13210;98042",
    "addr:street":"Se 253Rd Pl",
    "iso:country":"US",
    "sg:address":"13210 SE 253rd Pl",
    "sg:city":"Kent",
    "sg:classifiers":[
        {
            "category":"Personal",
            "subcategory":"Beauty Salon",
            "type":"Services"
        }
    ],
    "sg:phone":"+1 253 630 8025",
    "sg:postcode":"98042",
    "sg:province":"WA",
    "sg:tags":[
        "shop"
    ],
    "wof:name":"A Cut Above II",
    "wof:placetype":"venue"
},
  "geometry": {"coordinates":[-122.164554,47.374557],"type":"Point"}
}