{
  "type": "Feature",
  "properties": {
    "addr:full":"103 SW 5th St Battle Ground WA 98604",
    "addr:housenumber":"103",
    "addr:postcode":"98604",
    "addr:street":"Sw 5Th St",
    "iso:country":"US",
    "sg:address":"103 SW 5th St",
    "sg:city":"Battle Ground",
    "sg:classifiers":[
        {
            "category":"Building & Trades",
            "subcategory":"Construction",
            "type":"Services"
        }
    ],
    "sg:phone":"+1 360 687 4635",
    "sg:postcode":"98604",
    "sg:province":"WA",
    "sg:tags":[
        "carpentry",
        "contractor"
    ],
    "wof:name":"Brian Barney Svcs",
    "wof:placetype":"venue"
},
  "geometry": {"coordinates":[-122.538178,45.776828],"type":"Point"}
}