{
  "type": "Feature",
  "properties": {
    "iso:country":"US",
    "sg:address":"3406 N Market St",
    "sg:city":"Spokane",
    "sg:classifiers":[
        {
            "category":"Autos & Motor Vehicles",
            "subcategory":"Auto Supplies",
            "type":"Retail Goods"
        }
    ],
    "sg:phone":"+1 509 482 2955",
    "sg:postcode":"99207",
    "sg:province":"WA",
    "sg:tags":[
        "automobile",
        "parts",
        "center"
    ],
    "wof:name":"Corsmith Italian Automotive",
    "wof:placetype":"venue"
},
  "geometry": {"coordinates":[-117.365032,47.688881],"type":"Point"}
}