{
  "type": "Feature",
  "properties": {
    "addr:full":"4317 S Forest Meadow Dr Spokane WA 99206",
    "addr:housenumber":"4317",
    "addr:postcode":"99206",
    "addr:street":"S Forest Meadow Dr",
    "iso:country":"US",
    "sg:address":"4317 S Forest Meadow Dr",
    "sg:city":"Spokane",
    "sg:classifiers":[
        {
            "category":"Farming",
            "subcategory":"Farm & Veterinary Services",
            "type":"Manufacturing & Wholesale Goods"
        }
    ],
    "sg:phone":"+1 509 924 5413",
    "sg:postcode":"99206",
    "sg:province":"WA",
    "sg:tags":[
        "preparation",
        "crop",
        "for",
        "market"
    ],
    "wof:name":"John Sours & Associates",
    "wof:placetype":"venue"
},
  "geometry": {"coordinates":[-117.25802,47.613582],"type":"Point"}
}