{
  "type": "Feature",
  "properties": {
    "addr:full":"19718 144th Ave NE Woodinville WA 98072",
    "addr:housenumber":"19718",
    "addr:postcode":"98072",
    "addr:street":"144Th Ave Ne",
    "iso:country":"US",
    "sg:address":"19718 144th Ave NE",
    "sg:city":"Woodinville",
    "sg:classifiers":[
        {
            "category":"Manufacturing",
            "subcategory":"Building Materials",
            "type":"Manufacturing & Wholesale Goods"
        },
        {
            "category":"Home & Garden",
            "subcategory":"Carpets & Floor Coverings",
            "type":"Retail Goods"
        }
    ],
    "sg:phone":"+1 425 487 1129",
    "sg:postcode":"98072",
    "sg:province":"WA",
    "sg:tags":[
        "materials-wholesale",
        "manufacturer"
    ],
    "wof:name":"New Life Flooring",
    "wof:placetype":"venue"
},
  "geometry": {"coordinates":[-122.147775,47.770189],"type":"Point"}
}