{
  "type": "Feature",
  "properties": {
    "addr:full":"6250 S 228th St Kent WA 98032",
    "addr:housenumber":"6250",
    "addr:postcode":"98032",
    "addr:street":"S 228Th St",
    "iso:country":"US",
    "sg:address":"6250 S 228th St",
    "sg:city":"Kent",
    "sg:classifiers":[
        {
            "category":"Freight",
            "type":"Transportation"
        }
    ],
    "sg:phone":"+1 206 575 9575",
    "sg:postcode":"98032",
    "sg:province":"WA",
    "sg:tags":[
        "le",
        "carrier"
    ],
    "wof:name":"Overnite Transportation Co",
    "wof:placetype":"venue"
},
  "geometry": {"coordinates":[-122.255892,47.397099],"type":"Point"}
}