{
  "type": "Feature",
  "properties": {
    "addr:full":"8511 Greenwood Avenue N Seattle WA 98103",
    "addr:housenumber":"8511",
    "addr:postcode":"98103",
    "addr:street":"Greenwood Avenue N",
    "iso:country":"US",
    "sg:address":"8511 Greenwood Avenue N",
    "sg:city":"Seattle",
    "sg:classifiers":[
        {
            "category":"Health Services",
            "subcategory":"Dentist",
            "type":"Services"
        }
    ],
    "sg:phone":"+1 206 782 8223",
    "sg:postcode":"98103",
    "sg:province":"WA",
    "wof:name":"Werner Andy DDS",
    "wof:placetype":"venue"
},
  "geometry": {"coordinates":[-122.355469,47.69076],"type":"Point"}
}