{
  "type": "Feature",
  "properties": {
    "addr:full":"314 Byrd St Centralia WA 98531",
    "addr:housenumber":"314",
    "addr:postcode":"98531",
    "addr:street":"Byrd St",
    "iso:country":"US",
    "sg:address":"314 Byrd St",
    "sg:city":"Centralia",
    "sg:classifiers":[
        {
            "category":"Building & Trades",
            "subcategory":"Construction",
            "type":"Services"
        }
    ],
    "sg:phone":"+1 360 736 6497",
    "sg:postcode":"98531",
    "sg:province":"WA",
    "sg:tags":[
        "manufactured",
        "housing-communities"
    ],
    "wof:name":"Mount View Trailer Park",
    "wof:placetype":"venue"
},
  "geometry": {"coordinates":[-122.945165,46.716176],"type":"Point"}
}