{
  "type": "Feature",
  "properties": {
    "iso:country":"US",
    "sg:address":"1075 Jadwin Ave",
    "sg:city":"Richland",
    "sg:classifiers":[
        {
            "category":"Organizations",
            "subcategory":"Professional Association",
            "type":"Services"
        }
    ],
    "sg:phone":"+1 509 943 0858",
    "sg:postcode":"99352",
    "sg:province":"WA",
    "sg:tags":[
        "health"
    ],
    "wof:name":"American Diabetes Assn Themid",
    "wof:placetype":"venue"
},
  "geometry": {"coordinates":[-119.27763400000001,46.284322],"type":"Point"}
}