{
  "type": "Feature",
  "properties": {
    "addr:full":"20221 Aurora Ave N Shoreline WA 98133",
    "addr:housenumber":"20221",
    "addr:postcode":"98133",
    "addr:street":"Aurora Ave N",
    "iso:country":"US",
    "sg:address":"20221 Aurora Ave N",
    "sg:city":"Shoreline",
    "sg:classifiers":[
        {
            "category":"Restaurant",
            "type":"Food & Drink"
        }
    ],
    "sg:phone":"+1 206 546 8000",
    "sg:postcode":"98133",
    "sg:province":"WA",
    "sg:website":"http://www.taiho.com",
    "wof:name":"China Clipper",
    "wof:placetype":"venue"
},
  "geometry": {"coordinates":[-122.34607,47.775707],"type":"Point"}
}