{
  "type": "Feature",
  "properties": {
    "addr:full":"4003 Irongate Rd Bellingham WA 98226",
    "addr:housenumber":"4003",
    "addr:postcode":"98226",
    "addr:street":"Irongate Rd",
    "iso:country":"US",
    "sg:address":"4003 Irongate Rd",
    "sg:city":"Bellingham",
    "sg:classifiers":[
        {
            "category":"Shopping",
            "subcategory":"Clothing, Apparel, & Fashions",
            "type":"Retail Goods"
        },
        {
            "category":"Professional",
            "subcategory":"Art Services",
            "type":"Services"
        },
        {
            "category":"Professional",
            "subcategory":"Advertising",
            "type":"Services"
        },
        {
            "category":"Shopping",
            "subcategory":"Crafts & Fabrics",
            "type":"Retail Goods"
        },
        {
            "category":"Professional",
            "subcategory":"Printing & Photocopies",
            "type":"Services"
        }
    ],
    "sg:phone":"+1 360 676 7503",
    "sg:postcode":"98226",
    "sg:province":"WA",
    "sg:tags":[
        "shop",
        "sample",
        "product",
        "service-circular",
        "screen",
        "distributing",
        "design",
        "embroidery",
        "punching",
        "advertising-promotional",
        "clothing",
        "store"
    ],
    "sg:website":"http://www.bergenandco.com",
    "wof:name":"Bergen & Co",
    "wof:placetype":"venue"
},
  "geometry": {"coordinates":[-122.45339199999999,48.785917],"type":"Point"}
}