{
  "type": "Feature",
  "properties": {
    "addr:full":"1309 California Way Longview WA 98632",
    "addr:housenumber":"1309",
    "addr:postcode":"98632",
    "addr:street":"California Way",
    "iso:country":"US",
    "sg:address":"1309 California Way",
    "sg:city":"Longview",
    "sg:classifiers":[
        {
            "category":"Building & Trades",
            "subcategory":"Electrical",
            "type":"Services"
        }
    ],
    "sg:phone":"+1 360 636 1339",
    "sg:postcode":"98632",
    "sg:province":"WA",
    "sg:tags":[
        "electric",
        "contractor"
    ],
    "wof:name":"Fusion Electric",
    "wof:placetype":"venue"
},
  "geometry": {"coordinates":[-122.940455,46.1254],"type":"Point"}
}