{
  "type": "Feature",
  "properties": {
    "addr:full":"1115 W Bridges Rd Deer Park WA 99006",
    "addr:housenumber":"1115",
    "addr:postcode":"99006",
    "addr:street":"W Bridges Rd",
    "iso:country":"US",
    "sg:address":"1115 W Bridges Rd",
    "sg:city":"Deer Park",
    "sg:classifiers":[
        {
            "category":"Building & Trades",
            "subcategory":"Construction",
            "type":"Services"
        }
    ],
    "sg:phone":"+1 509 276 5646",
    "sg:postcode":"99006",
    "sg:province":"WA",
    "sg:tags":[
        "house"
    ],
    "wof:name":"Remington Home Remodeling",
    "wof:placetype":"venue"
},
  "geometry": {"coordinates":[-117.42412,48.017776],"type":"Point"}
}