{
  "type": "Feature",
  "properties": {
    "addr:full":"6503 S Mount Angeles Rd Port Angeles WA 98362",
    "addr:housenumber":"6503",
    "addr:postcode":"98362",
    "addr:street":"S Mount Angeles Rd",
    "iso:country":"US",
    "sg:address":"6503 S Mount Angeles Rd",
    "sg:city":"Port Angeles",
    "sg:classifiers":[
        {
            "category":"Real Estate",
            "subcategory":"Developer",
            "type":"Services"
        }
    ],
    "sg:phone":"+1 360 452 7754",
    "sg:postcode":"98362",
    "sg:province":"WA",
    "wof:name":"Triad Inc",
    "wof:placetype":"venue"
},
  "geometry": {"coordinates":[-123.423154,48.066549],"type":"Point"}
}