{
  "type": "Feature",
  "properties": {
    "addr:full":"4416 146th St NW Gig Harbor WA 98332",
    "addr:housenumber":"4416",
    "addr:postcode":"98332",
    "addr:street":"146Th St Nw",
    "iso:country":"US",
    "sg:address":"4416 146th St NW",
    "sg:city":"Gig Harbor",
    "sg:classifiers":[
        {
            "category":"Health Services",
            "subcategory":"Nursing And Care Facility",
            "type":"Services"
        }
    ],
    "sg:phone":"+1 253 857 5225",
    "sg:postcode":"98332",
    "sg:province":"WA",
    "sg:tags":[
        "home",
        "retirement",
        "community"
    ],
    "wof:name":"Lakes At Gig Harbor",
    "wof:placetype":"venue"
},
  "geometry": {"coordinates":[-122.59689299999999,47.390973],"type":"Point"}
}