{
  "type": "Feature",
  "properties": {
    "addr:full":"5100 NE 55th St Seattle WA 98105",
    "addr:housenumber":"5100",
    "addr:postcode":"98105",
    "addr:street":"Ne 55Th St",
    "iso:country":"US",
    "sg:address":"5100 NE 55th St",
    "sg:city":"Seattle",
    "sg:classifiers":[
        {
            "category":"Professional",
            "subcategory":"Management & Consulting",
            "type":"Services"
        }
    ],
    "sg:phone":"+1 206 526 9551",
    "sg:postcode":"98105",
    "sg:province":"WA",
    "wof:name":"RAO Associates Inc",
    "wof:placetype":"venue"
},
  "geometry": {"coordinates":[-122.271624,47.668504],"type":"Point"}
}