{
  "type": "Feature",
  "properties": {
    "addr:full":"3120 S Grand Blvd Spokane WA 99203",
    "addr:housenumber":"3120",
    "addr:postcode":"99203",
    "addr:street":"S Grand Blvd",
    "iso:country":"US",
    "sg:address":"3120 S Grand Blvd",
    "sg:city":"Spokane",
    "sg:classifiers":[
        {
            "category":"Government",
            "subcategory":"Post Office",
            "type":"Public Place"
        }
    ],
    "sg:phone":"+1 509 838 4092",
    "sg:postcode":"99203",
    "sg:province":"WA",
    "sg:website":"www.usps.com",
    "wof:name":"US Post Office",
    "wof:placetype":"venue"
},
  "geometry": {"coordinates":[-117.40185200000001,47.625627],"type":"Point"}
}