{
  "type": "Feature",
  "properties": {
    "iso:country":"US",
    "sg:address":"13323 224th St E",
    "sg:city":"Graham",
    "sg:classifiers":[
        {
            "category":"Food & Beverages",
            "subcategory":"Groceries & Convenience Stores",
            "type":"Retail Goods"
        }
    ],
    "sg:phone":"+1 360 893 5219",
    "sg:postcode":"98338",
    "sg:province":"WA",
    "sg:tags":[
        "grocer"
    ],
    "wof:name":"Thrift General Store Inc",
    "wof:placetype":"venue"
},
  "geometry": {"coordinates":[-122.254603,47.052742],"type":"Point"}
}