{
  "type": "Feature",
  "properties": {
    "addr:full":"525 Forsyth Ln Edmonds WA 98020",
    "addr:housenumber":"525",
    "addr:postcode":"98020",
    "addr:street":"Forsyth Ln",
    "iso:country":"US",
    "sg:address":"525 Forsyth Ln",
    "sg:city":"Edmonds",
    "sg:classifiers":[
        {
            "category":"Freight",
            "type":"Transportation"
        }
    ],
    "sg:phone":"+1 425 771 9287",
    "sg:postcode":"98020",
    "sg:province":"WA",
    "sg:tags":[
        "operator",
        "local",
        "trucking"
    ],
    "wof:name":"Frank Keeler",
    "wof:placetype":"venue"
},
  "geometry": {"coordinates":[-122.37545900000001,47.80236],"type":"Point"}
}