{
  "type": "Feature",
  "properties": {
    "addr:full":"1546 E Mesa View Ln Port Angeles WA 98362",
    "addr:housenumber":"1546",
    "addr:postcode":"98362",
    "addr:street":"E Mesa View Ln",
    "iso:country":"US",
    "sg:address":"1546 E Mesa View Ln",
    "sg:city":"Port Angeles",
    "sg:classifiers":[
        {
            "category":"Shopping",
            "subcategory":"Computers & Home Electronics",
            "type":"Retail Goods"
        },
        {
            "category":"Professional",
            "subcategory":"Computer Services",
            "type":"Services"
        }
    ],
    "sg:phone":"+1 360 417 3830",
    "sg:postcode":"98362",
    "sg:province":"WA",
    "sg:tags":[
        "equipment",
        "dealer",
        "programing",
        "custom"
    ],
    "wof:name":"Quality Computers & Svc",
    "wof:placetype":"venue"
},
  "geometry": {"coordinates":[-123.4088,48.078688],"type":"Point"}
}