{
  "type": "Feature",
  "properties": {
    "addr:full":"8244 SE 36th St Mercer Island WA 98040",
    "addr:housenumber":"8244",
    "addr:postcode":"98040",
    "addr:street":"Se 36Th St",
    "iso:country":"US",
    "sg:address":"8244 SE 36th St",
    "sg:city":"Mercer Island",
    "sg:classifiers":[
        {
            "category":"Professional",
            "subcategory":"Engineering",
            "type":"Services"
        }
    ],
    "sg:phone":"+1 206 919 9630",
    "sg:postcode":"98040",
    "sg:province":"WA",
    "wof:name":"M A Wright LLC",
    "wof:placetype":"venue"
},
  "geometry": {"coordinates":[-122.227598,47.578819],"type":"Point"}
}