{
  "type": "Feature",
  "properties": {
    "addr:full":"1824 Shamrock Dr Centralia WA 98531",
    "addr:housenumber":"1824",
    "addr:postcode":"98531",
    "addr:street":"Shamrock Dr",
    "iso:country":"US",
    "sg:address":"1824 Shamrock Dr",
    "sg:city":"Centralia",
    "sg:classifiers":[
        {
            "category":"Home & Garden",
            "subcategory":"Garden Supply",
            "type":"Retail Goods"
        }
    ],
    "sg:phone":"+1 360 330 5760",
    "sg:postcode":"98531",
    "sg:province":"WA",
    "wof:name":"L&M Christmas Tree Servic",
    "wof:placetype":"venue"
},
  "geometry": {"coordinates":[-122.983771,46.707266],"type":"Point"}
}