{
  "type": "Feature",
  "properties": {
    "addr:full":"4400 Kawecki Rd Malaga WA 98828",
    "addr:housenumber":"4400",
    "addr:postcode":"98828",
    "addr:street":"Kawecki Rd",
    "iso:country":"US",
    "sg:address":"4400 Kawecki Rd",
    "sg:city":"Malaga",
    "sg:classifiers":[
        {
            "category":"Manufacturing",
            "subcategory":"Metals",
            "type":"Manufacturing & Wholesale Goods"
        }
    ],
    "sg:phone":"+1 509 663 2165",
    "sg:postcode":"98828",
    "sg:province":"WA",
    "sg:tags":[
        "production",
        "primary",
        "aluminum"
    ],
    "wof:name":"Kb Alloys",
    "wof:placetype":"venue"
},
  "geometry": {"coordinates":[-120.187189,47.369609],"type":"Point"}
}