{
  "type": "Feature",
  "properties": {
    "iso:country":"US",
    "sg:address":"2421 Woodridge Ave",
    "sg:city":"Mount Vernon",
    "sg:classifiers":[
        {
            "category":"Professional",
            "type":"Services"
        }
    ],
    "sg:phone":"+1 360 428 4180",
    "sg:postcode":"98273",
    "sg:province":"WA",
    "wof:name":"Lynchs Links",
    "wof:placetype":"venue"
},
  "geometry": {"coordinates":[-122.320536,48.442158],"type":"Point"}
}