{
  "type": "Feature",
  "properties": {
    "addr:full":"1703 6th Ave Tacoma WA 98405",
    "addr:housenumber":"1703",
    "addr:postcode":"98405",
    "addr:street":"6Th Ave",
    "iso:country":"US",
    "sg:address":"1703 6th Ave",
    "sg:city":"Tacoma",
    "sg:classifiers":[
        {
            "category":"Restaurant",
            "type":"Food & Drink"
        }
    ],
    "sg:phone":"+1 253 272 1375",
    "sg:postcode":"98405",
    "sg:province":"WA",
    "sg:tags":[
        "greek"
    ],
    "sg:website":"http://www.itsgreektome.com",
    "wof:name":"Its Greek To Me",
    "wof:placetype":"venue"
},
  "geometry": {"coordinates":[-122.461828,47.256217],"type":"Point"}
}