{
  "type": "Feature",
  "properties": {
    "addr:full":"1309 Commercial St Bellingham WA 98225",
    "addr:housenumber":"1309",
    "addr:postcode":"98225",
    "addr:street":"Commercial St",
    "iso:country":"US",
    "sg:address":"1309 Commercial St",
    "sg:city":"Bellingham",
    "sg:classifiers":[
        {
            "category":"Restaurant",
            "type":"Food & Drink"
        }
    ],
    "sg:phone":"+1 360 714 8412",
    "sg:postcode":"98225",
    "sg:province":"WA",
    "sg:tags":[
        "eating"
    ],
    "wof:name":"Giuseppe's Italian Restaurant",
    "wof:placetype":"venue"
},
  "geometry": {"coordinates":[-122.478819,48.751402],"type":"Point"}
}