{
  "type": "Feature",
  "properties": {
    "addr:full":"6761 S 216th St Kent WA 98032",
    "addr:housenumber":"6761",
    "addr:postcode":"98032",
    "addr:street":"S 216Th St",
    "iso:country":"US",
    "sg:address":"6761 S 216th St",
    "sg:city":"Kent",
    "sg:classifiers":[
        {
            "category":"Wholesale",
            "subcategory":"Durable Goods & Equipment",
            "type":"Manufacturing & Wholesale Goods"
        }
    ],
    "sg:phone":"+1 253 395 9291",
    "sg:postcode":"98032",
    "sg:province":"WA",
    "wof:name":"Michaels Souvenirs & Gifts",
    "wof:placetype":"venue"
},
  "geometry": {"coordinates":[-122.250595,47.408465],"type":"Point"}
}