{
  "type": "Feature",
  "properties": {
    "addr:full":"17210 Tester Rd Snohomish WA 98290",
    "addr:housenumber":"17210",
    "addr:postcode":"98290",
    "addr:street":"Tester Rd",
    "iso:country":"US",
    "sg:address":"17210 Tester Rd",
    "sg:city":"Snohomish",
    "sg:classifiers":[
        {
            "category":"Shopping",
            "subcategory":"Florist",
            "type":"Retail Goods"
        }
    ],
    "sg:phone":"+1 360 794 7604",
    "sg:postcode":"98290",
    "sg:province":"WA",
    "wof:name":"Wight James & Eula Agriculture",
    "wof:placetype":"venue"
},
  "geometry": {"coordinates":[-122.01770399999999,47.834641],"type":"Point"}
}