{
  "type": "Feature",
  "properties": {
    "addr:full":"125 NW Webb St Pullman WA 99163",
    "addr:housenumber":"125",
    "addr:postcode":"99163",
    "addr:street":"Nw Webb St",
    "iso:country":"US",
    "sg:address":"125 NW Webb St",
    "sg:city":"Pullman",
    "sg:classifiers":[
        {
            "category":"Professional",
            "type":"Services"
        }
    ],
    "sg:phone":"+1 509 332 5188",
    "sg:postcode":"99163",
    "sg:province":"WA",
    "wof:name":"Jack Dollhausen",
    "wof:placetype":"venue"
},
  "geometry": {"coordinates":[-117.17550900000001,46.737753],"type":"Point"}
}