{
  "type": "Feature",
  "properties": {
    "iso:country":"US",
    "sg:address":"3622 Grandview St",
    "sg:city":"Gig Harbor",
    "sg:classifiers":[
        {
            "category":"Professional",
            "subcategory":"Business Services",
            "type":"Services"
        }
    ],
    "sg:phone":"+1 253 858 8093",
    "sg:postcode":"98335",
    "sg:province":"WA",
    "wof:name":"Alexander Design Network",
    "wof:placetype":"venue"
},
  "geometry": {"coordinates":[-122.585145,47.323203],"type":"Point"}
}