{
  "type": "Feature",
  "properties": {
    "addr:full":"3435 19th Ave S Seattle WA 98144",
    "addr:housenumber":"3435",
    "addr:postcode":"98144",
    "addr:street":"19Th Ave S",
    "iso:country":"US",
    "sg:address":"3435 19th Ave S",
    "sg:city":"Seattle",
    "sg:classifiers":[
        {
            "category":"Professional",
            "subcategory":"Art Services",
            "type":"Services"
        }
    ],
    "sg:phone":"+1 206 723 2003",
    "sg:postcode":"98144",
    "sg:province":"WA",
    "sg:tags":[
        "commercial",
        "design"
    ],
    "wof:name":"Yutaka Sasaki",
    "wof:placetype":"venue"
},
  "geometry": {"coordinates":[-122.306591,47.572107],"type":"Point"}
}