{
  "type": "Feature",
  "properties": {
    "iso:country":"US",
    "sg:address":"9900 US Hwy 12",
    "sg:city":"Rochester",
    "sg:classifiers":[
        {
            "category":"Restaurant",
            "type":"Food & Drink"
        }
    ],
    "sg:phone":"+1 360 273 6357",
    "sg:postcode":"98579",
    "sg:province":"WA",
    "wof:name":"Mason Dixon Line Restaurant",
    "wof:placetype":"venue"
},
  "geometry": {"coordinates":[-123.089141,46.821717],"type":"Point"}
}