{
  "type": "Feature",
  "properties": {
    "addr:full":"13215 SE 30th St Bellevue WA 98005",
    "addr:housenumber":"13215",
    "addr:postcode":"98005",
    "addr:street":"Se 30Th St",
    "iso:country":"US",
    "sg:address":"13215 SE 30th St",
    "sg:city":"Bellevue",
    "sg:classifiers":[
        {
            "category":"Home & Garden",
            "subcategory":"Garden Supply",
            "type":"Retail Goods"
        }
    ],
    "sg:phone":"+1 425 455 0568",
    "sg:postcode":"98005",
    "sg:province":"WA",
    "sg:tags":[
        "nursery",
        "gardening"
    ],
    "wof:name":"Garden Works",
    "wof:placetype":"venue"
},
  "geometry": {"coordinates":[-122.16300200000001,47.5839],"type":"Point"}
}