{
  "type": "Feature",
  "properties": {
    "addr:full":"9014 220th St SW Edmonds WA 98026",
    "addr:housenumber":"9014",
    "addr:postcode":"98026",
    "addr:street":"220Th St Sw",
    "iso:country":"US",
    "sg:address":"9014 220th St SW",
    "sg:city":"Edmonds",
    "sg:classifiers":[
        {
            "category":"Shopping",
            "subcategory":"Computers & Home Electronics",
            "type":"Retail Goods"
        },
        {
            "category":"Professional",
            "subcategory":"Printing & Photocopies",
            "type":"Services"
        }
    ],
    "sg:phone":"+1 425 776 2501",
    "sg:postcode":"98026",
    "sg:province":"WA",
    "sg:tags":[
        "plate",
        "medal",
        "name",
        "trophies",
        "plaque"
    ],
    "wof:name":"Star Nametag Co",
    "wof:placetype":"venue"
},
  "geometry": {"coordinates":[-122.35420999999999,47.79958],"type":"Point"}
}