{
  "type": "Feature",
  "properties": {
    "addr:full":"8824 180th St SE Snohomish WA 98296",
    "addr:housenumber":"8824",
    "addr:postcode":"98296",
    "addr:street":"180Th St Se",
    "iso:country":"US",
    "sg:address":"8824 180th St SE",
    "sg:city":"Snohomish",
    "sg:classifiers":[
        {
            "category":"Wholesale",
            "subcategory":"Chemicals & Plastics",
            "type":"Manufacturing & Wholesale Goods"
        }
    ],
    "sg:phone":"+1 360 668 6773",
    "sg:postcode":"98296",
    "sg:province":"WA",
    "wof:name":"Barkonwood Inc",
    "wof:placetype":"venue"
},
  "geometry": {"coordinates":[-122.113437,47.833772],"type":"Point"}
}