{
  "type": "Feature",
  "properties": {
    "addr:full":"10400 Sagehill Rd SE Warden WA 98857",
    "addr:housenumber":"10400",
    "addr:postcode":"98857",
    "addr:street":"Sagehill Rd Se Warden",
    "iso:country":"US",
    "sg:address":"10400 Sagehill Rd SE",
    "sg:city":"Warden",
    "sg:classifiers":[
        {
            "category":"Sports & Exercise",
            "subcategory":"Golf",
            "type":"Entertainment"
        }
    ],
    "sg:phone":"+1 509 349 2603",
    "sg:postcode":"98857",
    "sg:province":"WA",
    "sg:tags":[
        "course"
    ],
    "wof:name":"Sage Hills Golf & Rv Resort",
    "wof:placetype":"venue"
},
  "geometry": {"coordinates":[-119.130121,46.93588],"type":"Point"}
}