{
  "type": "Feature",
  "properties": {
    "addr:full":"19125 N Creek Pkwy Ste 204 Bothell WA 98011",
    "addr:housenumber":"19125",
    "addr:postcode":"98011",
    "addr:street":"N Creek Pkwy Ste 204",
    "iso:country":"US",
    "sg:address":"19125 N Creek Pkwy Ste 204",
    "sg:city":"Bothell",
    "sg:classifiers":[
        {
            "category":"Health Services",
            "subcategory":"Doctor",
            "type":"Services"
        },
        {
            "category":"Health Services",
            "subcategory":"Clinic",
            "type":"Services"
        }
    ],
    "sg:phone":"+1 425 424 2201",
    "sg:postcode":"98011",
    "sg:province":"WA",
    "sg:tags":[
        "physician",
        "family",
        "medical",
        "practice",
        "surgeons",
        "medicine"
    ],
    "sg:website":"http://www.canyoncreekclinic.com",
    "wof:name":"Canyon Creek Clinic",
    "wof:placetype":"venue"
},
  "geometry": {"coordinates":[-122.18470000000001,47.766333],"type":"Point"}
}