{
  "type": "Feature",
  "properties": {
    "iso:country":"US",
    "sg:address":"1213 Ormiston St",
    "sg:city":"Wenatchee",
    "sg:classifiers":[
        {
            "category":"Building & Trades",
            "subcategory":"Construction",
            "type":"Services"
        }
    ],
    "sg:phone":"+1 509 662 4298",
    "sg:postcode":"98801",
    "sg:province":"WA",
    "sg:tags":[
        "house"
    ],
    "wof:name":"Gabaldo Const",
    "wof:placetype":"venue"
},
  "geometry": {"coordinates":[-120.318287,47.406284],"type":"Point"}
}