{
  "type": "Feature",
  "properties": {
    "addr:full":"169 Laurelwood Ct Richland WA 99352",
    "addr:housenumber":"169",
    "addr:postcode":"99352",
    "addr:street":"Laurelwood Ct",
    "iso:country":"US",
    "sg:address":"169 Laurelwood Ct",
    "sg:city":"Richland",
    "sg:classifiers":[
        {
            "category":"Retail",
            "subcategory":"Car Wash",
            "type":"Services"
        }
    ],
    "sg:phone":"+1 509 627 4004",
    "sg:postcode":"99352",
    "sg:province":"WA",
    "wof:name":"Meadow Springs Car Wash",
    "wof:placetype":"venue"
},
  "geometry": {"coordinates":[-119.26832,46.241217],"type":"Point"}
}