{
  "type": "Feature",
  "properties": {
    "addr:full":"6215 36th Ave NW Seattle WA 98107",
    "addr:housenumber":"6215",
    "addr:postcode":"98107",
    "addr:street":"36Th Ave Nw",
    "iso:country":"US",
    "sg:address":"6215 36th Ave NW",
    "sg:city":"Seattle",
    "sg:classifiers":[
        {
            "category":"Wholesale",
            "subcategory":"Non-durable Goods",
            "type":"Manufacturing & Wholesale Goods"
        }
    ],
    "sg:phone":"+1 206 782 3494",
    "sg:postcode":"98107",
    "sg:province":"WA",
    "wof:name":"S & R Fisheries",
    "wof:placetype":"venue"
},
  "geometry": {"coordinates":[-122.403584,47.674795],"type":"Point"}
}