{
  "type": "Feature",
  "properties": {
    "addr:full":"2327 N Narrows Dr Tacoma WA 98406",
    "addr:housenumber":"2327",
    "addr:postcode":"98406",
    "addr:street":"N Narrows Dr",
    "iso:country":"US",
    "sg:address":"2327 N Narrows Dr",
    "sg:city":"Tacoma",
    "sg:classifiers":[
        {
            "category":"Professional",
            "subcategory":"Business Services",
            "type":"Services"
        }
    ],
    "sg:phone":"+1 253 752 9045",
    "sg:postcode":"98406",
    "sg:province":"WA",
    "sg:tags":[
        "consultant",
        "coach"
    ],
    "wof:name":"Rlr Consulting",
    "wof:placetype":"venue"
},
  "geometry": {"coordinates":[-122.53151099999999,47.269055],"type":"Point"}
}