{
  "type": "Feature",
  "properties": {
    "addr:full":"213 S Burke Ave Connell WA 99326",
    "addr:housenumber":"213",
    "addr:postcode":"99326",
    "addr:street":"S Burke Ave Connell",
    "iso:country":"US",
    "sg:address":"213 S Burke Ave",
    "sg:city":"Connell",
    "sg:classifiers":[
        {
            "category":"Organizations",
            "subcategory":"Religious Organization",
            "type":"Services"
        }
    ],
    "sg:phone":"+1 509 234 3191",
    "sg:postcode":"99326",
    "sg:province":"WA",
    "sg:tags":[
        "church"
    ],
    "wof:name":"Gideon Lutheran Church",
    "wof:placetype":"venue"
},
  "geometry": {"coordinates":[-118.858555,46.659467],"type":"Point"}
}