{
  "type": "Feature",
  "properties": {
    "addr:full":"328 N 77th St Seattle WA 98103",
    "addr:housenumber":"328",
    "addr:postcode":"98103",
    "addr:street":"N 77Th St",
    "iso:country":"US",
    "sg:address":"328 N 77th St",
    "sg:city":"Seattle",
    "sg:classifiers":[
        {
            "category":"Professional",
            "subcategory":"Computer Services",
            "type":"Services"
        }
    ],
    "sg:phone":"+1 206 781 6930",
    "sg:postcode":"98103",
    "sg:province":"WA",
    "sg:tags":[
        "publisher",
        "developer",
        "software"
    ],
    "wof:name":"Two Kings Media",
    "wof:placetype":"venue"
},
  "geometry": {"coordinates":[-122.354482,47.684766],"type":"Point"}
}