{
  "type": "Feature",
  "properties": {
    "addr:full":"303 N Church St Montesano WA 98563",
    "addr:housenumber":"303",
    "addr:postcode":"98563",
    "addr:street":"N Church St",
    "iso:country":"US",
    "sg:address":"303 N Church St",
    "sg:city":"Montesano",
    "sg:classifiers":[
        {
            "category":"Education",
            "subcategory":"School",
            "type":"Public Place"
        }
    ],
    "sg:phone":"+1 360 249 4041",
    "sg:postcode":"98563",
    "sg:province":"WA",
    "sg:website":"www.monte.wednet.edu",
    "wof:name":"Montesano High School",
    "wof:placetype":"venue"
},
  "geometry": {"coordinates":[-123.59708999999999,46.984471],"type":"Point"}
}