{
  "type": "Feature",
  "properties": {
    "iso:country":"US",
    "sg:address":"10826 177th Ct NE",
    "sg:city":"Redmond",
    "sg:classifiers":[
        {
            "category":"Building & Trades",
            "subcategory":"Construction",
            "type":"Services"
        }
    ],
    "sg:phone":"+1 425 869 7749",
    "sg:postcode":"98052",
    "sg:province":"WA",
    "wof:name":"Shelter Technology Corp",
    "wof:placetype":"venue"
},
  "geometry": {"coordinates":[-122.10373300000001,47.697685],"type":"Point"}
}