{
  "type": "Feature",
  "properties": {
    "addr:full":"5413 Meridian Ave N Seattle WA 98103",
    "addr:housenumber":"5413",
    "addr:postcode":"98103",
    "addr:street":"Meridian Ave N",
    "iso:country":"US",
    "sg:address":"5413 Meridian Ave N",
    "sg:city":"Seattle",
    "sg:classifiers":[
        {
            "category":"Shopping",
            "subcategory":"Musical Instruments",
            "type":"Retail Goods"
        }
    ],
    "sg:phone":"+1 206 632 8555",
    "sg:postcode":"98103",
    "sg:province":"WA",
    "sg:tags":[
        "organs"
    ],
    "wof:name":"Balcom & Vaughan Pipe Organ",
    "wof:placetype":"venue"
},
  "geometry": {"coordinates":[-122.33372199999999,47.668595],"type":"Point"}
}