{
  "type": "Feature",
  "properties": {
    "addr:full":"3527 E Sprague Ave Spokane WA 99202",
    "addr:housenumber":"3527",
    "addr:postcode":"99202",
    "addr:street":"E Sprague Ave",
    "iso:country":"US",
    "sg:address":"3527 E Sprague Ave",
    "sg:city":"Spokane",
    "sg:classifiers":[
        {
            "category":"Professional",
            "subcategory":"Business Services",
            "type":"Services"
        }
    ],
    "sg:phone":"+1 509 536 0669",
    "sg:postcode":"99202",
    "sg:province":"WA",
    "sg:tags":[
        "fund",
        "promotion",
        "raising"
    ],
    "wof:name":"Sponsor Reps Inc",
    "wof:placetype":"venue"
},
  "geometry": {"coordinates":[-117.357952,47.657398],"type":"Point"}
}