{
  "type": "Feature",
  "properties": {
    "addr:full":"5850 S 228th St Kent WA 98032",
    "addr:housenumber":"5850",
    "addr:postcode":"98032",
    "addr:street":"S 228Th St",
    "iso:country":"US",
    "sg:address":"5850 S 228th St",
    "sg:city":"Kent",
    "sg:classifiers":[
        {
            "category":"Autos & Motor Vehicles",
            "subcategory":"Fuel & Gas Station",
            "type":"Retail Goods"
        }
    ],
    "sg:phone":"+1 206 388 3869",
    "sg:postcode":"98032",
    "sg:province":"WA",
    "sg:tags":[
        "diesel"
    ],
    "wof:name":"Standard Biodiesel Usa, Inc.",
    "wof:placetype":"venue"
},
  "geometry": {"coordinates":[-122.26345999999999,47.394765],"type":"Point"}
}