{
  "type": "Feature",
  "properties": {
    "iso:country":"US",
    "sg:address":"808 W Spokane Falls Blvd",
    "sg:city":"Spokane",
    "sg:classifiers":[
        {
            "category":"Government",
            "subcategory":"Office",
            "type":"Public Place"
        }
    ],
    "sg:phone":"+1 509 625 6260",
    "sg:postcode":"99201",
    "sg:province":"WA",
    "sg:tags":[
        "village"
    ],
    "wof:name":"Spokane Contract Compliance",
    "wof:placetype":"venue"
},
  "geometry": {"coordinates":[-117.424629,47.660184],"type":"Point"}
}