{
  "type": "Feature",
  "properties": {
    "addr:full":"5013 Pacific Hwy E Fife WA 98424",
    "addr:housenumber":"5013",
    "addr:postcode":"98424",
    "addr:street":"Pacific Hwy E",
    "iso:country":"US",
    "sg:address":"5013 Pacific Hwy E",
    "sg:city":"Fife",
    "sg:classifiers":[
        {
            "category":"Recreation",
            "type":"Entertainment"
        }
    ],
    "sg:phone":"+1 253 896 4750",
    "sg:postcode":"98424",
    "sg:province":"WA",
    "sg:tags":[
        "martial",
        "arts",
        "instruction"
    ],
    "wof:name":"Bennest Karate Schools",
    "wof:placetype":"venue"
},
  "geometry": {"coordinates":[-122.35978900000001,47.243143],"type":"Point"}
}