{
  "type": "Feature",
  "properties": {
    "addr:full":"5633 17th Ave NE Olympia WA 98516",
    "addr:housenumber":"5633",
    "addr:postcode":"98516",
    "addr:street":"17Th Ave Ne",
    "iso:country":"US",
    "sg:address":"5633 17th Ave NE",
    "sg:city":"Olympia",
    "sg:classifiers":[
        {
            "category":"Structure",
            "subcategory":"Office Building",
            "type":"Public Place"
        }
    ],
    "sg:phone":"+1 360 871 2682",
    "sg:postcode":"98516",
    "sg:province":"WA",
    "sg:tags":[
        "park"
    ],
    "wof:name":"Linda Camino Properties",
    "wof:placetype":"venue"
},
  "geometry": {"coordinates":[-122.808149,47.059928],"type":"Point"}
}