{
  "type": "Feature",
  "properties": {
    "addr:full":"13434 NE 16th St Ste 230 Bellevue WA 98005",
    "addr:housenumber":"13434",
    "addr:postcode":"98005",
    "addr:street":"Ne 16Th St Ste 230",
    "iso:country":"US",
    "sg:address":"13434 NE 16th St Ste 230",
    "sg:city":"Bellevue",
    "sg:classifiers":[
        {
            "category":"Education",
            "subcategory":"School",
            "type":"Public Place"
        }
    ],
    "sg:phone":"+1 425 747 7127",
    "sg:postcode":"98005",
    "sg:province":"WA",
    "wof:name":"Aikido School of Self Defense",
    "wof:placetype":"venue"
},
  "geometry": {"coordinates":[-122.161568,47.624517],"type":"Point"}
}