{
  "type": "Feature",
  "properties": {
    "addr:full":"5804 N Freya St Spokane WA 99217",
    "addr:housenumber":"5804",
    "addr:postcode":"99217",
    "addr:street":"N Freya St",
    "iso:country":"US",
    "sg:address":"5804 N Freya St",
    "sg:city":"Spokane",
    "sg:classifiers":[
        {
            "category":"Retail",
            "subcategory":"Repair Shop",
            "type":"Services"
        }
    ],
    "sg:phone":"+1 509 487 4419",
    "sg:postcode":"99217",
    "sg:province":"WA",
    "sg:tags":[
        "glass",
        "installation"
    ],
    "wof:name":"City Glass LLC",
    "wof:placetype":"venue"
},
  "geometry": {"coordinates":[-117.35701400000001,47.711224],"type":"Point"}
}