{
  "type": "Feature",
  "properties": {
    "addr:full":"23552 State Rte 127 Lacrosse WA 99143",
    "addr:housenumber":"23552",
    "addr:postcode":"99143",
    "addr:street":"State Rte 127",
    "iso:country":"US",
    "sg:address":"23552 State Rte 127",
    "sg:city":"Lacrosse",
    "sg:classifiers":[
        {
            "category":"Organizations",
            "subcategory":"Religious Organization",
            "type":"Services"
        }
    ],
    "sg:phone":"+1 509 549 3630",
    "sg:postcode":"99143",
    "sg:province":"WA",
    "sg:tags":[
        "church"
    ],
    "wof:name":"Country Bible Church",
    "wof:placetype":"venue"
},
  "geometry": {"coordinates":[-117.705844,46.772186],"type":"Point"}
}