{
  "type": "Feature",
  "properties": {
    "addr:full":"4630 200th St SW Lynnwood WA 98036",
    "addr:housenumber":"4630",
    "addr:postcode":"98036",
    "addr:street":"200Th St Sw",
    "iso:country":"US",
    "sg:address":"4630 200th St SW",
    "sg:city":"Lynnwood",
    "sg:classifiers":[
        {
            "category":"Banks & Credit Unions",
            "subcategory":"Bank",
            "type":"Services"
        }
    ],
    "sg:phone":"+1 425 712 8709",
    "sg:postcode":"98036",
    "sg:province":"WA",
    "sg:tags":[
        "loan",
        "real estate"
    ],
    "wof:name":"Uc Lending",
    "wof:placetype":"venue"
},
  "geometry": {"coordinates":[-122.29753599999999,47.817315],"type":"Point"}
}