{
  "type": "Feature",
  "properties": {
    "addr:full":"9257 State Rte 525 Clinton WA 98236",
    "addr:housenumber":"9257",
    "addr:postcode":"98236",
    "addr:street":"State Rte 525",
    "iso:country":"US",
    "sg:address":"9257 State Rte 525",
    "sg:city":"Clinton",
    "sg:classifiers":[
        {
            "category":"Shopping",
            "subcategory":"Florist",
            "type":"Retail Goods"
        }
    ],
    "sg:phone":"+1 360 341 3016",
    "sg:postcode":"98236",
    "sg:province":"WA",
    "wof:name":"Clinton Nursery & Florist",
    "wof:placetype":"venue"
},
  "geometry": {"coordinates":[-122.367459,47.979411],"type":"Point"}
}