{
  "type": "Feature",
  "properties": {
    "addr:full":"15600 SE Mill Plain Blvd Vancouver WA 98684",
    "addr:postcode":"15600;98684",
    "addr:street":"Se Mill Plain Blvd",
    "iso:country":"US",
    "sg:address":"15600 SE Mill Plain Blvd",
    "sg:city":"Vancouver",
    "sg:classifiers":[
        {
            "category":"Retail",
            "subcategory":"Auto Repair",
            "type":"Services"
        }
    ],
    "sg:phone":"+1 360 256 1212",
    "sg:postcode":"98684",
    "sg:province":"WA",
    "sg:website":"www.gaynors.com",
    "wof:name":"Gaynor's Automotive",
    "wof:placetype":"venue"
},
  "geometry": {"coordinates":[-122.511762,45.616542],"type":"Point"}
}