{
  "type": "Feature",
  "properties": {
    "addr:full":"16031 356th Ave SE Sultan WA 98294",
    "addr:housenumber":"16031",
    "addr:postcode":"98294",
    "addr:street":"356Th Ave Se Sultan",
    "iso:country":"US",
    "sg:address":"16031 356th Ave SE",
    "sg:city":"Sultan",
    "sg:classifiers":[
        {
            "category":"Manufacturing",
            "subcategory":"Apparel",
            "type":"Manufacturing & Wholesale Goods"
        }
    ],
    "sg:phone":"+1 360 793 9107",
    "sg:postcode":"98294",
    "sg:province":"WA",
    "sg:tags":[
        "textile",
        "product",
        "fabricated",
        "mfg"
    ],
    "wof:name":"Bo Bags Inc",
    "wof:placetype":"venue"
},
  "geometry": {"coordinates":[-121.754588,47.852939],"type":"Point"}
}