{
  "type": "Feature",
  "properties": {
    "iso:country":"US",
    "sg:address":"601 W Main St",
    "sg:city":"Centralia",
    "sg:classifiers":[
        {
            "category":"Shopping",
            "subcategory":"Stationery & Office Supplies",
            "type":"Retail Goods"
        }
    ],
    "sg:phone":"+1 360 736 2826",
    "sg:postcode":"98531",
    "sg:province":"WA",
    "wof:name":"Main Business Supplies Inc",
    "wof:placetype":"venue"
},
  "geometry": {"coordinates":[-122.961491,46.717692],"type":"Point"}
}