{
  "type": "Feature",
  "properties": {
    "addr:full":"15199 Silverdale Way NW Poulsbo WA 98370",
    "addr:housenumber":"15199",
    "addr:postcode":"98370",
    "addr:street":"Silverdale Way Nw",
    "iso:country":"US",
    "sg:address":"15199 Silverdale Way NW",
    "sg:city":"Poulsbo",
    "sg:classifiers":[
        {
            "category":"Building & Trades",
            "subcategory":"Landscaping Services",
            "type":"Services"
        }
    ],
    "sg:phone":"+1 360 697 1157",
    "sg:postcode":"98370",
    "sg:province":"WA",
    "wof:name":"Azbury Gardens",
    "wof:placetype":"venue"
},
  "geometry": {"coordinates":[-122.660769,47.700514],"type":"Point"}
}