{
  "type": "Feature",
  "properties": {
    "addr:full":"3813 Rucker Ave Everett WA 98201",
    "addr:housenumber":"3813",
    "addr:postcode":"98201",
    "addr:street":"Rucker Ave",
    "iso:country":"US",
    "sg:address":"3813 Rucker Ave",
    "sg:city":"Everett",
    "sg:classifiers":[
        {
            "category":"Retail",
            "subcategory":"Auto Rental",
            "type":"Services"
        }
    ],
    "sg:phone":"+1 425 252 2123",
    "sg:postcode":"98201",
    "sg:province":"WA",
    "sg:tags":[
        "equipment",
        "truck"
    ],
    "wof:name":"Budget Rent-A-Car",
    "wof:placetype":"venue"
},
  "geometry": {"coordinates":[-122.210857,47.966444],"type":"Point"}
}