{
  "type": "Feature",
  "properties": {
    "addr:full":"113 S 2nd St Selah WA 98942",
    "addr:housenumber":"113",
    "addr:postcode":"98942",
    "addr:street":"S 2Nd St",
    "iso:country":"US",
    "sg:address":"113 S 2nd St",
    "sg:city":"Selah",
    "sg:classifiers":[
        {
            "category":"Government",
            "subcategory":"Police Station",
            "type":"Public Place"
        }
    ],
    "sg:phone":"+1 509 698 7347",
    "sg:postcode":"98942",
    "sg:province":"WA",
    "sg:tags":[
        "protection"
    ],
    "wof:name":"Selah Police Dept",
    "wof:placetype":"venue"
},
  "geometry": {"coordinates":[-120.531666,46.65253],"type":"Point"}
}