{
  "type": "Feature",
  "properties": {
    "addr:full":"6105 E Chattaroy Rd Chattaroy WA 99003",
    "addr:housenumber":"6105",
    "addr:postcode":"99003",
    "addr:street":"E Chattaroy Rd",
    "iso:country":"US",
    "sg:address":"6105 E Chattaroy Rd",
    "sg:city":"Chattaroy",
    "sg:classifiers":[
        {
            "category":"Banks & Credit Unions",
            "subcategory":"Bank",
            "type":"Services"
        }
    ],
    "sg:phone":"+1 509 220 6709",
    "sg:postcode":"99003",
    "sg:province":"WA",
    "sg:tags":[
        "financing"
    ],
    "wof:name":"American One Finance",
    "wof:placetype":"venue"
},
  "geometry": {"coordinates":[-117.3237,47.896373],"type":"Point"}
}