{
  "type": "Feature",
  "properties": {
    "addr:full":"1072 Williams Lake Rd Evans WA 99126",
    "addr:housenumber":"1072",
    "addr:postcode":"99126",
    "addr:street":"Williams Lake Rd",
    "iso:country":"US",
    "sg:address":"1072 Williams Lake Rd",
    "sg:city":"Evans",
    "sg:classifiers":[
        {
            "category":"Retail",
            "subcategory":"Veterinary Services",
            "type":"Services"
        }
    ],
    "sg:phone":"+1 509 684 8978",
    "sg:postcode":"99126",
    "sg:province":"WA",
    "sg:tags":[
        "veterinarian"
    ],
    "wof:name":"Echo Ridge Veterinary Hospital",
    "wof:placetype":"venue"
},
  "geometry": {"coordinates":[-117.95560399999999,48.68207],"type":"Point"}
}