{
  "type": "Feature",
  "properties": {
    "addr:full":"13953 127th Pl NE Kirkland WA 98034",
    "addr:housenumber":"13953",
    "addr:postcode":"98034",
    "addr:street":"127Th Pl Ne",
    "iso:country":"US",
    "sg:address":"13953 127th Pl NE",
    "sg:city":"Kirkland",
    "sg:classifiers":[
        {
            "category":"Education",
            "subcategory":"Special Training",
            "type":"Public Place"
        }
    ],
    "sg:phone":"+1 425 968 2640",
    "sg:postcode":"98034",
    "sg:province":"WA",
    "sg:tags":[
        "school",
        "language"
    ],
    "wof:name":"Mawkanuli, Talant",
    "wof:placetype":"venue"
},
  "geometry": {"coordinates":[-122.170348,47.724522],"type":"Point"}
}