{
  "type": "Feature",
  "properties": {
    "addr:full":"333 Sunset Blvd N Renton WA 98057",
    "addr:housenumber":"333",
    "addr:postcode":"98057",
    "addr:street":"Sunset Blvd N",
    "iso:country":"US",
    "sg:address":"333 Sunset Blvd N",
    "sg:city":"Renton",
    "sg:classifiers":[
        {
            "category":"Retail",
            "subcategory":"Auto Repair",
            "type":"Services"
        }
    ],
    "sg:phone":"+1 425 226 0930",
    "sg:postcode":"98057",
    "sg:province":"WA",
    "sg:website":"pacificautomachine.com/",
    "wof:name":"Pacific Auto Machine",
    "wof:placetype":"venue"
},
  "geometry": {"coordinates":[-122.195097,47.48785],"type":"Point"}
}