{
  "type": "Feature",
  "properties": {
    "addr:full":"20614 4th Ave SW Seattle WA 98166",
    "addr:housenumber":"20614",
    "addr:postcode":"98166",
    "addr:street":"4Th Ave Sw",
    "iso:country":"US",
    "sg:address":"20614 4th Ave SW",
    "sg:city":"Seattle",
    "sg:classifiers":[
        {
            "category":"Professional",
            "type":"Services"
        }
    ],
    "sg:phone":"+1 206 878 7656",
    "sg:postcode":"98166",
    "sg:province":"WA",
    "wof:name":"Gloria Marie Murtha",
    "wof:placetype":"venue"
},
  "geometry": {"coordinates":[-122.34088,47.41681],"type":"Point"}
}