{
  "type": "Feature",
  "properties": {
    "iso:country":"US",
    "sg:address":"7097 Guemes Island Rd",
    "sg:city":"Anacortes",
    "sg:classifiers":[
        {
            "category":"Professional",
            "type":"Services"
        }
    ],
    "sg:phone":"+1 360 299 2169",
    "sg:postcode":"98221",
    "sg:province":"WA",
    "wof:name":"Andy Gladish Metal Work",
    "wof:placetype":"venue"
},
  "geometry": {"coordinates":[-122.624859,48.54031],"type":"Point"}
}