{
  "type": "Feature",
  "properties": {
    "addr:full":"5508 NE 175th Cir Vancouver WA 98686",
    "addr:housenumber":"5508",
    "addr:postcode":"98686",
    "addr:street":"Ne 175Th Cir",
    "iso:country":"US",
    "sg:address":"5508 NE 175th Cir",
    "sg:city":"Vancouver",
    "sg:classifiers":[
        {
            "category":"Shopping",
            "subcategory":"Music",
            "type":"Retail Goods"
        }
    ],
    "sg:phone":"+1 360 903 3992",
    "sg:postcode":"98686",
    "sg:province":"WA",
    "wof:name":"Piledriving Records",
    "wof:placetype":"venue"
},
  "geometry": {"coordinates":[-122.612976,45.748995],"type":"Point"}
}