{
  "type": "Feature",
  "properties": {
    "addr:full":"3200 15th Ave W Seattle WA 98119",
    "addr:housenumber":"3200",
    "addr:postcode":"98119",
    "addr:street":"15Th Ave W",
    "iso:country":"US",
    "sg:address":"3200 15th Ave W",
    "sg:city":"Seattle",
    "sg:classifiers":[
        {
            "category":"Manufacturing",
            "subcategory":"Tools & Machinery",
            "type":"Manufacturing & Wholesale Goods"
        }
    ],
    "sg:phone":"+1 206 763 6417",
    "sg:postcode":"98119",
    "sg:province":"WA",
    "sg:tags":[
        "food",
        "product",
        "mfg"
    ],
    "wof:name":"That Takes Cake",
    "wof:placetype":"venue"
},
  "geometry": {"coordinates":[-122.376127,47.650335],"type":"Point"}
}