{
  "type": "Feature",
  "properties": {
    "addr:full":"818 W Riverside Ave Suite 250 Spokane WA 99201",
    "addr:housenumber":"818",
    "addr:postcode":"99201",
    "addr:street":"W Riverside Ave Suite 250",
    "iso:country":"US",
    "sg:address":"818 W Riverside Ave Suite 250",
    "sg:city":"Spokane",
    "sg:classifiers":[
        {
            "category":"Professional",
            "subcategory":"Lawyer & Legal Services",
            "type":"Services"
        }
    ],
    "sg:phone":"+1 509 455 5200",
    "sg:postcode":"99201",
    "sg:province":"WA",
    "sg:tags":[
        "personal",
        "attorney",
        "injury",
        "insurance",
        "law"
    ],
    "wof:name":"Kane , Gregory M. - Evans, Craven & Lack",
    "wof:placetype":"venue"
},
  "geometry": {"coordinates":[-117.4238,47.657938],"type":"Point"}
}