{
  "type": "Feature",
  "properties": {
    "addr:full":"2001 Main St Ferndale WA 98248",
    "addr:housenumber":"2001",
    "addr:postcode":"98248",
    "addr:street":"Main St",
    "iso:country":"US",
    "sg:address":"2001 Main St",
    "sg:city":"Ferndale",
    "sg:classifiers":[
        {
            "category":"Health Services",
            "subcategory":"Optometrist",
            "type":"Services"
        }
    ],
    "sg:phone":"+1 360 384 1463",
    "sg:postcode":"98248",
    "sg:province":"WA",
    "wof:name":"Ferndale Vision Clinic",
    "wof:placetype":"venue"
},
  "geometry": {"coordinates":[-122.591159,48.84665],"type":"Point"}
}