{
  "type": "Feature",
  "properties": {
    "addr:full":"290 Hockett Ln Pasco WA 99301",
    "addr:housenumber":"290",
    "addr:postcode":"99301",
    "addr:street":"Hockett Ln",
    "iso:country":"US",
    "sg:address":"290 Hockett Ln",
    "sg:city":"Pasco",
    "sg:phone":"+1 509 234 8491",
    "sg:postcode":"99301",
    "sg:province":"WA",
    "sg:tags":[
        "farm",
        "wheat"
    ],
    "wof:name":"D&S Ranch",
    "wof:placetype":"venue"
},
  "geometry": {"coordinates":[-118.80496100000001,46.485375],"type":"Point"}
}