{
  "type": "Feature",
  "properties": {
    "addr:full":"3849 NE 88th St Seattle WA 98115",
    "addr:housenumber":"3849",
    "addr:postcode":"98115",
    "addr:street":"Ne 88Th St",
    "iso:country":"US",
    "sg:address":"3849 NE 88th St",
    "sg:city":"Seattle",
    "sg:classifiers":[
        {
            "category":"Wholesale",
            "subcategory":"Hardware",
            "type":"Manufacturing & Wholesale Goods"
        }
    ],
    "sg:phone":"+1 206 523 7223",
    "sg:postcode":"98115",
    "sg:province":"WA",
    "sg:tags":[
        "hardware-wholesale",
        "manufacturer"
    ],
    "wof:name":"Brad Harvey",
    "wof:placetype":"venue"
},
  "geometry": {"coordinates":[-122.286671,47.692364],"type":"Point"}
}