{
  "type": "Feature",
  "properties": {
    "addr:full":"9178 State Rte 525 Clinton WA 98236",
    "addr:housenumber":"9178",
    "addr:postcode":"98236",
    "addr:street":"State Rte 525",
    "iso:country":"US",
    "sg:address":"9178 State Rte 525",
    "sg:city":"Clinton",
    "sg:classifiers":[
        {
            "category":"Personal",
            "subcategory":"Beauty Salon",
            "type":"Services"
        }
    ],
    "sg:phone":"+1 360 341 7070",
    "sg:postcode":"98236",
    "sg:province":"WA",
    "wof:name":"Darcy's",
    "wof:placetype":"venue"
},
  "geometry": {"coordinates":[-122.37009399999999,47.979265],"type":"Point"}
}