{
  "type": "Feature",
  "properties": {
    "addr:full":"8101 238th St SW Edmonds WA 98026",
    "addr:housenumber":"8101",
    "addr:postcode":"98026",
    "addr:street":"238Th St Sw",
    "iso:country":"US",
    "sg:address":"8101 238th St SW",
    "sg:city":"Edmonds",
    "sg:classifiers":[
        {
            "category":"Food & Beverages",
            "subcategory":"Groceries & Convenience Stores",
            "type":"Retail Goods"
        }
    ],
    "sg:phone":"+1 425 775 9811",
    "sg:postcode":"98026",
    "sg:province":"WA",
    "wof:name":"7-Eleven",
    "wof:placetype":"venue"
},
  "geometry": {"coordinates":[-122.34244700000001,47.783348],"type":"Point"}
}