{
  "type": "Feature",
  "properties": {
    "addr:full":"35910 N Elk Chattaroy Rd Elk WA 99009",
    "addr:housenumber":"35910",
    "addr:postcode":"99009",
    "addr:street":"N Elk Chattaroy Rd",
    "iso:country":"US",
    "sg:address":"35910 N Elk Chattaroy Rd",
    "sg:city":"Elk",
    "sg:classifiers":[
        {
            "category":"Retail",
            "subcategory":"Repair Shop",
            "type":"Services"
        }
    ],
    "sg:phone":"+1 509 292 0539",
    "sg:postcode":"99009",
    "sg:province":"WA",
    "wof:name":"Ivan D Tucker Horseshoeing",
    "wof:placetype":"venue"
},
  "geometry": {"coordinates":[-117.25189,47.979501],"type":"Point"}
}