{
  "type": "Feature",
  "properties": {
    "addr:full":"5280 Foxglove Ln Langley WA 98260",
    "addr:housenumber":"5280",
    "addr:postcode":"98260",
    "addr:street":"Foxglove Ln",
    "iso:country":"US",
    "sg:address":"5280 Foxglove Ln",
    "sg:city":"Langley",
    "sg:classifiers":[
        {
            "category":"Professional",
            "subcategory":"Engineering",
            "type":"Services"
        }
    ],
    "sg:phone":"+1 360 321 4010",
    "sg:postcode":"98260",
    "sg:province":"WA",
    "sg:tags":[
        "energy",
        "management",
        "engineer"
    ],
    "wof:name":"Empiricos",
    "wof:placetype":"venue"
},
  "geometry": {"coordinates":[-122.48253699999999,48.017994],"type":"Point"}
}