{
  "type": "Feature",
  "properties": {
    "addr:full":"825 Eastlake Ave E Seattle WA 98109",
    "addr:housenumber":"825",
    "addr:postcode":"98109",
    "addr:street":"Eastlake Ave E",
    "iso:country":"US",
    "sg:address":"825 Eastlake Ave E",
    "sg:city":"Seattle",
    "sg:classifiers":[
        {
            "category":"Professional",
            "type":"Services"
        }
    ],
    "sg:phone":"+1 206 288 2036",
    "sg:postcode":"98109",
    "sg:province":"WA",
    "wof:name":"Stethen H Tetersdorf",
    "wof:placetype":"venue"
},
  "geometry": {"coordinates":[-122.329346,47.626691],"type":"Point"}
}