{
  "type": "Feature",
  "properties": {
    "iso:country":"US",
    "sg:address":"929 S College Ave",
    "sg:city":"College Place",
    "sg:classifiers":[
        {
            "category":"Building & Trades",
            "subcategory":"Cleaning & Sanitation",
            "type":"Services"
        }
    ],
    "sg:phone":"+1 509 522 1081",
    "sg:postcode":"99324",
    "sg:province":"WA",
    "sg:tags":[
        "house"
    ],
    "wof:name":"Miracle Workers Cleaning Svc",
    "wof:placetype":"venue"
},
  "geometry": {"coordinates":[-118.388476,46.040817],"type":"Point"}
}