{
  "type": "Feature",
  "properties": {
    "addr:full":"80 Vine St Seattle WA 98121",
    "addr:housenumber":"80",
    "addr:postcode":"98121",
    "addr:street":"Vine St",
    "iso:country":"US",
    "sg:address":"80 Vine St",
    "sg:city":"Seattle",
    "sg:classifiers":[
        {
            "category":"Real Estate",
            "subcategory":"Real Estate Operator",
            "type":"Services"
        }
    ],
    "sg:phone":"+1 206 443 9861",
    "sg:postcode":"98121",
    "sg:province":"WA",
    "sg:tags":[
        "condominium"
    ],
    "wof:name":"Banner Building Sales Office",
    "wof:placetype":"venue"
},
  "geometry": {"coordinates":[-122.349947,47.615059],"type":"Point"}
}