{
  "type": "Feature",
  "properties": {
    "addr:full":"9807 28th Ave SW Seattle WA 98126",
    "addr:housenumber":"9807",
    "addr:postcode":"98126",
    "addr:street":"28Th Ave Sw",
    "iso:country":"US",
    "sg:address":"9807 28th Ave SW",
    "sg:city":"Seattle",
    "sg:classifiers":[
        {
            "category":"Travel",
            "subcategory":"Travel Agent",
            "type":"Entertainment"
        }
    ],
    "sg:phone":"+1 206 938 1212",
    "sg:postcode":"98126",
    "sg:province":"WA",
    "sg:tags":[
        "agency"
    ],
    "wof:name":"Eggy Cruises & Tours",
    "wof:placetype":"venue"
},
  "geometry": {"coordinates":[-122.36869900000001,47.516989],"type":"Point"}
}