{
  "type": "Feature",
  "properties": {
    "addr:full":"308 N 188th St Seattle WA 98133",
    "addr:housenumber":"308",
    "addr:postcode":"98133",
    "addr:street":"N 188Th St",
    "iso:country":"US",
    "sg:address":"308 N 188th St",
    "sg:city":"Seattle",
    "sg:classifiers":[
        {
            "category":"Professional",
            "subcategory":"Accounting & Tax Preparation",
            "type":"Services"
        }
    ],
    "sg:phone":"+1 206 546 3521",
    "sg:postcode":"98133",
    "sg:province":"WA",
    "wof:name":"James S & Ann M Ludwig",
    "wof:placetype":"venue"
},
  "geometry": {"coordinates":[-122.35356299999999,47.765259],"type":"Point"}
}