{
  "type": "Feature",
  "properties": {
    "addr:full":"22606 85th Pl S Kent WA 98031",
    "addr:housenumber":"22606",
    "addr:postcode":"98031",
    "addr:street":"85Th Pl S",
    "iso:country":"US",
    "sg:address":"22606 85th Pl S",
    "sg:city":"Kent",
    "sg:classifiers":[
        {
            "category":"Manufacturing",
            "subcategory":"Tools & Machinery",
            "type":"Manufacturing & Wholesale Goods"
        },
        {
            "category":"Manufacturing",
            "subcategory":"Watercraft",
            "type":"Manufacturing & Wholesale Goods"
        }
    ],
    "sg:phone":"+1 253 856 7072",
    "sg:postcode":"98031",
    "sg:province":"WA",
    "sg:tags":[
        "water",
        "cutting",
        "jet"
    ],
    "wof:name":"Advanced Water Jet & Design",
    "wof:placetype":"venue"
},
  "geometry": {"coordinates":[-122.225995,47.398703],"type":"Point"}
}