{
  "type": "Feature",
  "properties": {
    "addr:full":"5009 W Clearwater Ave C Kennewick WA 99336",
    "addr:housenumber":"5009",
    "addr:postcode":"99336",
    "addr:street":"W Clearwater Ave C",
    "iso:country":"US",
    "sg:address":"5009 W Clearwater Ave C",
    "sg:city":"Kennewick",
    "sg:classifiers":[
        {
            "category":"Personal",
            "subcategory":"Nail Salon",
            "type":"Services"
        }
    ],
    "sg:phone":"+1 509 374 1140",
    "sg:postcode":"99336",
    "sg:province":"WA",
    "wof:name":"Happy Nails",
    "wof:placetype":"venue"
},
  "geometry": {"coordinates":[-119.188407,46.212421],"type":"Point"}
}