{
  "type": "Feature",
  "properties": {
    "addr:full":"324 Salmon Creek Rd Okanogan WA 98840",
    "addr:housenumber":"324",
    "addr:postcode":"98840",
    "addr:street":"Salmon Creek Rd",
    "iso:country":"US",
    "sg:address":"324 Salmon Creek Rd",
    "sg:city":"Okanogan",
    "sg:classifiers":[
        {
            "category":"Real Estate",
            "subcategory":"Real Estate Agent",
            "type":"Services"
        }
    ],
    "sg:phone":"+1 509 422 5263",
    "sg:postcode":"98840",
    "sg:province":"WA",
    "sg:tags":[
        "appraiser"
    ],
    "wof:name":"John Whitecar Real Estate",
    "wof:placetype":"venue"
},
  "geometry": {"coordinates":[-119.60879799999999,48.395461],"type":"Point"}
}