{
  "type": "Feature",
  "properties": {
    "addr:full":"1811 W Hwy 101 Port Angeles WA 98363",
    "addr:housenumber":"1811",
    "addr:postcode":"98363",
    "addr:street":"W Hwy 101",
    "iso:country":"US",
    "sg:address":"1811 W Hwy 101",
    "sg:city":"Port Angeles",
    "sg:classifiers":[
        {
            "category":"Retail",
            "subcategory":"Veterinary Services",
            "type":"Services"
        }
    ],
    "sg:phone":"+1 360 452 4551",
    "sg:postcode":"98363",
    "sg:province":"WA",
    "sg:tags":[
        "veterinarian"
    ],
    "wof:name":"All Animal Boarding",
    "wof:placetype":"venue"
},
  "geometry": {"coordinates":[-123.48468699999999,48.104654],"type":"Point"}
}