{
  "type": "Feature",
  "properties": {
    "addr:full":"9114 NE 81st Ave Vancouver WA 98662",
    "addr:housenumber":"9114",
    "addr:postcode":"98662",
    "addr:street":"Ne 81St Ave",
    "iso:country":"US",
    "sg:address":"9114 NE 81st Ave",
    "sg:city":"Vancouver",
    "sg:classifiers":[
        {
            "category":"Professional",
            "type":"Services"
        }
    ],
    "sg:phone":"+1 360 735 1044",
    "sg:postcode":"98662",
    "sg:province":"WA",
    "wof:name":"Captured Images",
    "wof:placetype":"venue"
},
  "geometry": {"coordinates":[-122.590339,45.687755],"type":"Point"}
}