{
  "type": "Feature",
  "properties": {
    "addr:full":"21713 48th Ave W Mountlake Ter WA 98043",
    "addr:housenumber":"21713",
    "addr:postcode":"98043",
    "addr:street":"48Th Ave W Mountlake Ter",
    "iso:country":"US",
    "sg:address":"21713 48th Ave W",
    "sg:city":"Mountlake Ter",
    "sg:classifiers":[
        {
            "category":"Building & Trades",
            "subcategory":"Construction",
            "type":"Services"
        }
    ],
    "sg:phone":"+1 425 771 1738",
    "sg:postcode":"98043",
    "sg:province":"WA",
    "sg:tags":[
        "concrete",
        "contractor"
    ],
    "wof:name":"All Seasons Concrete Constr",
    "wof:placetype":"venue"
},
  "geometry": {"coordinates":[-122.29807,47.802807],"type":"Point"}
}