{
  "type": "Feature",
  "properties": {
    "addr:full":"3404 72nd Ave SE Mercer Island WA 98040",
    "addr:housenumber":"3404",
    "addr:postcode":"98040",
    "addr:street":"72Nd Ave Se",
    "iso:country":"US",
    "sg:address":"3404 72nd Ave SE",
    "sg:city":"Mercer Island",
    "sg:classifiers":[
        {
            "category":"Home & Garden",
            "subcategory":"Furniture",
            "type":"Retail Goods"
        }
    ],
    "sg:phone":"+1 206 230 5550",
    "sg:postcode":"98040",
    "sg:province":"WA",
    "wof:name":"Lori Ehrig Interior Furnishing",
    "wof:placetype":"venue"
},
  "geometry": {"coordinates":[-122.24307899999999,47.579834],"type":"Point"}
}