{
  "type": "Feature",
  "properties": {
    "addr:full":"908 S Scheuber Rd Centralia WA 98531",
    "addr:housenumber":"908",
    "addr:postcode":"98531",
    "addr:street":"S Scheuber Rd",
    "iso:country":"US",
    "sg:address":"908 S Scheuber Rd",
    "sg:city":"Centralia",
    "sg:classifiers":[
        {
            "category":"Health Services",
            "subcategory":"Doctor",
            "type":"Services"
        }
    ],
    "sg:phone":"+1 360 736 6778",
    "sg:postcode":"98531",
    "sg:province":"WA",
    "sg:tags":[
        "medical"
    ],
    "wof:name":"Jemima TSO MD",
    "wof:placetype":"venue"
},
  "geometry": {"coordinates":[-122.986903,46.712185],"type":"Point"}
}