{
  "type": "Feature",
  "properties": {
    "addr:full":"7926 SE Promenade Ln Port Orchard WA 98367",
    "addr:housenumber":"7926",
    "addr:postcode":"98367",
    "addr:street":"Se Promenade Ln",
    "iso:country":"US",
    "sg:address":"7926 SE Promenade Ln",
    "sg:city":"Port Orchard",
    "sg:classifiers":[
        {
            "category":"Building & Trades",
            "subcategory":"Landscaping Services",
            "type":"Services"
        }
    ],
    "sg:phone":"+1 360 871 2672",
    "sg:postcode":"98367",
    "sg:province":"WA",
    "sg:tags":[
        "landscape"
    ],
    "wof:name":"Abraxas Landscaping & Nur",
    "wof:placetype":"venue"
},
  "geometry": {"coordinates":[-122.54718699999999,47.492432],"type":"Point"}
}