{
  "type": "Feature",
  "properties": {
    "addr:full":"8833 Buttonwood Ln NE Olympia WA 98516",
    "addr:housenumber":"8833",
    "addr:postcode":"98516",
    "addr:street":"Buttonwood Ln Ne",
    "iso:country":"US",
    "sg:address":"8833 Buttonwood Ln NE",
    "sg:city":"Olympia",
    "sg:classifiers":[
        {
            "category":"Professional",
            "subcategory":"Accounting & Tax Preparation",
            "type":"Services"
        }
    ],
    "sg:phone":"+1 360 915 6892",
    "sg:postcode":"98516",
    "sg:province":"WA",
    "sg:tags":[
        "return",
        "preparation-business"
    ],
    "wof:name":"Susan Dean Ea",
    "wof:placetype":"venue"
},
  "geometry": {"coordinates":[-122.824245,47.161325],"type":"Point"}
}