{
  "type": "Feature",
  "properties": {
    "addr:full":"2222 Highland Ave Everett WA 98201",
    "addr:housenumber":"2222",
    "addr:postcode":"98201",
    "addr:street":"Highland Ave",
    "iso:country":"US",
    "sg:address":"2222 Highland Ave",
    "sg:city":"Everett",
    "sg:classifiers":[
        {
            "category":"Professional",
            "subcategory":"Business Services",
            "type":"Services"
        }
    ],
    "sg:phone":"+1 425 258 6819",
    "sg:postcode":"98201",
    "sg:province":"WA",
    "wof:name":"Lupe M Bustamante",
    "wof:placetype":"venue"
},
  "geometry": {"coordinates":[-122.185243,47.987235],"type":"Point"}
}