{
  "type": "Feature",
  "properties": {
    "addr:full":"270 4th Ave S Kent WA 98032",
    "addr:housenumber":"270",
    "addr:postcode":"98032",
    "addr:street":"4Th Ave S",
    "iso:country":"US",
    "sg:address":"270 4th Ave S",
    "sg:city":"Kent",
    "sg:classifiers":[
        {
            "category":"Communications",
            "subcategory":"Television Station",
            "type":"Services"
        }
    ],
    "sg:phone":"+1 206 462 3079",
    "sg:postcode":"98032",
    "sg:province":"WA",
    "sg:tags":[
        "satellite",
        "cable"
    ],
    "sg:website":"http://www.satellitetvcost.com/kent-digital-satellitetv-wa.html",
    "wof:name":"Direct Kent Satellite TV",
    "wof:placetype":"venue"
},
  "geometry": {"coordinates":[-122.237422,47.380034],"type":"Point"}
}