{
  "type": "Feature",
  "properties": {
    "addr:full":"1821 SE Solomon Loop Vancouver WA 98683",
    "addr:housenumber":"1821",
    "addr:postcode":"98683",
    "addr:street":"Se Solomon Loop",
    "iso:country":"US",
    "sg:address":"1821 SE Solomon Loop",
    "sg:city":"Vancouver",
    "sg:classifiers":[
        {
            "category":"Professional",
            "type":"Services"
        }
    ],
    "sg:phone":"+1 360 260 9002",
    "sg:postcode":"98683",
    "sg:province":"WA",
    "wof:name":"Clere Storie",
    "wof:placetype":"venue"
},
  "geometry": {"coordinates":[-122.508658,45.609238],"type":"Point"}
}