{
  "type": "Feature",
  "properties": {
    "addr:full":"17625 NE 65th St Ste 130 Redmond WA 98052",
    "addr:housenumber":"17625",
    "addr:postcode":"98052",
    "addr:street":"Ne 65Th St Ste 130",
    "iso:country":"US",
    "sg:address":"17625 NE 65th St Ste 130",
    "sg:city":"Redmond",
    "sg:classifiers":[
        {
            "category":"Retail",
            "subcategory":"Auto Repair",
            "type":"Services"
        }
    ],
    "sg:phone":"+1 425 883 1100",
    "sg:postcode":"98052",
    "sg:province":"WA",
    "sg:tags":[
        "body",
        "repairing",
        "customizing",
        "painting",
        "automobile"
    ],
    "wof:name":"Cascade Autosport",
    "wof:placetype":"venue"
},
  "geometry": {"coordinates":[-122.105081,47.663988],"type":"Point"}
}