{
  "type": "Feature",
  "properties": {
    "addr:full":"1700 Cherry St Aberdeen WA 98520",
    "addr:housenumber":"1700",
    "addr:postcode":"98520",
    "addr:street":"Cherry St",
    "iso:country":"US",
    "sg:address":"1700 Cherry St",
    "sg:city":"Aberdeen",
    "sg:classifiers":[
        {
            "category":"Education",
            "subcategory":"School",
            "type":"Public Place"
        }
    ],
    "sg:phone":"+1 360 538 2160",
    "sg:postcode":"98520",
    "sg:province":"WA",
    "sg:tags":[
        "elementary"
    ],
    "wof:name":"Alexander Young Elem School",
    "wof:placetype":"venue"
},
  "geometry": {"coordinates":[-123.836263,46.976904],"type":"Point"}
}