{
  "type": "Feature",
  "properties": {
    "addr:full":"1835 NE 177th St Seattle WA 98155",
    "addr:housenumber":"1835",
    "addr:postcode":"98155",
    "addr:street":"Ne 177Th St",
    "iso:country":"US",
    "sg:address":"1835 NE 177th St",
    "sg:city":"Seattle",
    "sg:classifiers":[
        {
            "category":"Professional",
            "subcategory":"Lawyer & Legal Services",
            "type":"Services"
        }
    ],
    "sg:phone":"+1 866 637 3652",
    "sg:postcode":"98155",
    "sg:province":"WA",
    "wof:name":"Attorney",
    "wof:placetype":"venue"
},
  "geometry": {"coordinates":[-122.31167499999999,47.757574],"type":"Point"}
}