{
  "type": "Feature",
  "properties": {
    "addr:full":"234 Otto St Port Townsend WA 98368",
    "addr:housenumber":"234",
    "addr:postcode":"98368",
    "addr:street":"Otto St",
    "iso:country":"US",
    "sg:address":"234 Otto St",
    "sg:city":"Port Townsend",
    "sg:classifiers":[
        {
            "category":"Retail",
            "subcategory":"Repair Shop",
            "type":"Services"
        }
    ],
    "sg:phone":"+1 360 385 3155",
    "sg:postcode":"98368",
    "sg:province":"WA",
    "sg:tags":[
        "repairing",
        "lawn",
        "mower"
    ],
    "wof:name":"Fen's Lawn & Garden",
    "wof:placetype":"venue"
},
  "geometry": {"coordinates":[-122.814894,48.084573],"type":"Point"}
}