{
  "type": "Feature",
  "properties": {
    "addr:full":"31519 Pacific Hwy S Federal Way WA 98003",
    "addr:housenumber":"31519",
    "addr:postcode":"98003",
    "addr:street":"Pacific Hwy S Federal Way",
    "iso:country":"US",
    "sg:address":"31519 Pacific Hwy S",
    "sg:city":"Federal Way",
    "sg:classifiers":[
        {
            "category":"Personal",
            "subcategory":"Beauty Salon",
            "type":"Services"
        }
    ],
    "sg:phone":"+1 253 946 8705",
    "sg:postcode":"98003",
    "sg:province":"WA",
    "sg:tags":[
        "shop"
    ],
    "wof:name":"Great Clips",
    "wof:placetype":"venue"
},
  "geometry": {"coordinates":[-122.31344300000001,47.321078],"type":"Point"}
}