{
  "type": "Feature",
  "properties": {
    "iso:country":"US",
    "sg:address":"22 Chicago Ave",
    "sg:city":"Yakima",
    "sg:classifiers":[
        {
            "category":"Professional",
            "type":"Services"
        }
    ],
    "sg:phone":"+1 509 452 0021",
    "sg:postcode":"98902",
    "sg:province":"WA",
    "wof:name":"Anderson Paul",
    "wof:placetype":"venue"
},
  "geometry": {"coordinates":[-120.527512,46.598921],"type":"Point"}
}