{
  "type": "Feature",
  "properties": {
    "addr:full":"1805 S Main St Seattle WA 98144",
    "addr:housenumber":"1805",
    "addr:postcode":"98144",
    "addr:street":"S Main St",
    "iso:country":"US",
    "sg:address":"1805 S Main St",
    "sg:city":"Seattle",
    "sg:classifiers":[
        {
            "category":"Banks & Credit Unions",
            "subcategory":"Bank",
            "type":"Services"
        }
    ],
    "sg:phone":"+1 206 325 7448",
    "sg:postcode":"98144",
    "sg:province":"WA",
    "wof:name":"CBC Credit Union",
    "wof:placetype":"venue"
},
  "geometry": {"coordinates":[-122.307698,47.599921],"type":"Point"}
}