{
  "type": "Feature",
  "properties": {
    "addr:full":"4400 Bullfrog Rd Cle Elum WA 98922",
    "addr:postcode":"4400;98922",
    "addr:street":"Bullfrog Rd",
    "iso:country":"US",
    "sg:address":"4400 Bullfrog Rd",
    "sg:city":"Cle Elum",
    "sg:classifiers":[
        {
            "category":"Food & Beverages",
            "subcategory":"Groceries & Convenience Stores",
            "type":"Retail Goods"
        }
    ],
    "sg:phone":"+1 509 649 2260",
    "sg:postcode":"98922",
    "sg:province":"WA",
    "wof:name":"Sportland Mini-Mart",
    "wof:placetype":"venue"
},
  "geometry": {"coordinates":[-120.981531,47.207203],"type":"Point"}
}