{
  "type": "Feature",
  "properties": {
    "addr:full":"401 E Mountain View Ave Ellensburg WA 98926",
    "addr:housenumber":"401",
    "addr:postcode":"98926",
    "addr:street":"E Mountain View Ave",
    "iso:country":"US",
    "sg:address":"401 E Mountain View Ave",
    "sg:city":"Ellensburg",
    "sg:classifiers":[
        {
            "category":"Social Services",
            "type":"Services"
        }
    ],
    "sg:phone":"+1 509 925 5311",
    "sg:postcode":"98926",
    "sg:province":"WA",
    "sg:tags":[
        "organization",
        "welfare"
    ],
    "sg:website":"www.psp.org",
    "wof:name":"People For People",
    "wof:placetype":"venue"
},
  "geometry": {"coordinates":[-120.543144,46.984638],"type":"Point"}
}