{
  "type": "Feature",
  "properties": {
    "addr:full":"4501 Mallet St Richland WA 99353",
    "addr:housenumber":"4501",
    "addr:postcode":"99353",
    "addr:street":"Mallet St",
    "iso:country":"US",
    "sg:address":"4501 Mallet St",
    "sg:city":"Richland",
    "sg:classifiers":[
        {
            "category":"Airport",
            "type":"Transportation"
        }
    ],
    "sg:phone":"+1 509 961 3032",
    "sg:postcode":"99353",
    "sg:province":"WA",
    "wof:name":"CP Aircraft Services",
    "wof:placetype":"venue"
},
  "geometry": {"coordinates":[-119.349115,46.266245],"type":"Point"}
}