{
  "type": "Feature",
  "properties": {
    "addr:full":"116 W Alder St Shelton WA 98584",
    "addr:housenumber":"116",
    "addr:postcode":"98584",
    "addr:street":"W Alder St",
    "iso:country":"US",
    "sg:address":"116 W Alder St",
    "sg:city":"Shelton",
    "sg:classifiers":[
        {
            "category":"Shopping",
            "subcategory":"Florist",
            "type":"Retail Goods"
        }
    ],
    "sg:phone":"+1 360 426 8360",
    "sg:postcode":"98584",
    "sg:province":"WA",
    "wof:name":"Kings Ransom Florist",
    "wof:placetype":"venue"
},
  "geometry": {"coordinates":[-123.09971299999999,47.21603],"type":"Point"}
}