{
  "type": "Feature",
  "properties": {
    "addr:full":"145 Logan Hill Rd Chehalis WA 98532",
    "addr:housenumber":"145",
    "addr:postcode":"98532",
    "addr:street":"Logan Hill Rd",
    "iso:country":"US",
    "sg:address":"145 Logan Hill Rd",
    "sg:city":"Chehalis",
    "sg:classifiers":[
        {
            "category":"Retail",
            "subcategory":"Repair Shop",
            "type":"Services"
        }
    ],
    "sg:phone":"+1 360 748 3294",
    "sg:postcode":"98532",
    "sg:province":"WA",
    "wof:name":"Olson Upholstery & Mfg",
    "wof:placetype":"venue"
},
  "geometry": {"coordinates":[-122.88736900000001,46.624021],"type":"Point"}
}