{
  "type": "Feature",
  "properties": {
    "addr:full":"420 Wilson Ln Sumas WA 98295",
    "addr:housenumber":"420",
    "addr:postcode":"98295",
    "addr:street":"Wilson Ln",
    "iso:country":"US",
    "sg:address":"420 Wilson Ln",
    "sg:city":"Sumas",
    "sg:classifiers":[
        {
            "category":"Building & Trades",
            "subcategory":"Construction",
            "type":"Services"
        }
    ],
    "sg:phone":"+1 360 988 3717",
    "sg:postcode":"98295",
    "sg:province":"WA",
    "sg:tags":[
        "concrete",
        "contractor"
    ],
    "wof:name":"Jim Adams Complete Asphalt",
    "wof:placetype":"venue"
},
  "geometry": {"coordinates":[-122.25305,48.999799],"type":"Point"}
}