{
  "type": "Feature",
  "properties": {
    "addr:full":"24404 48th Ln SW Vashon WA 98070",
    "addr:housenumber":"24404",
    "addr:postcode":"98070",
    "addr:street":"48Th Ln Sw",
    "iso:country":"US",
    "sg:address":"24404 48th Ln SW",
    "sg:city":"Vashon",
    "sg:classifiers":[
        {
            "category":"Health Services",
            "subcategory":"Podiatrist",
            "type":"Services"
        }
    ],
    "sg:phone":"+1 206 463 4901",
    "sg:postcode":"98070",
    "sg:province":"WA",
    "sg:tags":[
        "equipment",
        "supply"
    ],
    "wof:name":"Highland Medical Sales Inc",
    "wof:placetype":"venue"
},
  "geometry": {"coordinates":[-122.391937,47.385502],"type":"Point"}
}