{
  "type": "Feature",
  "properties": {
    "addr:full":"20304 Herron Road Kp N Lakebay WA 98349",
    "addr:postcode":"20304;98349",
    "addr:street":"Herron Road Kp N Lakebay",
    "iso:country":"US",
    "sg:address":"20304 Herron Road Kp N",
    "sg:city":"Lakebay",
    "sg:classifiers":[
        {
            "category":"Professional",
            "subcategory":"Secretarial Services",
            "type":"Services"
        }
    ],
    "sg:phone":"+1 253 884 4165",
    "sg:postcode":"98349",
    "sg:province":"WA",
    "sg:tags":[
        "reporting"
    ],
    "wof:name":"Susan M Dougherty",
    "wof:placetype":"venue"
},
  "geometry": {"coordinates":[-122.80291200000001,47.261269],"type":"Point"}
}