{
  "type": "Feature",
  "properties": {
    "iso:country":"US",
    "sg:address":"2222 N Dora Rd",
    "sg:city":"Spokane",
    "sg:classifiers":[
        {
            "category":"Professional",
            "type":"Services"
        }
    ],
    "sg:phone":"+1 509 891 9275",
    "sg:postcode":"99212",
    "sg:province":"WA",
    "wof:name":"David L Butler",
    "wof:placetype":"venue"
},
  "geometry": {"coordinates":[-117.310975,47.676163],"type":"Point"}
}