{
  "type": "Feature",
  "properties": {
    "addr:full":"9559 Sand Point Way NE Seattle WA 98115",
    "addr:housenumber":"9559",
    "addr:postcode":"98115",
    "addr:street":"Sand Point Way Ne",
    "iso:country":"US",
    "sg:address":"9559 Sand Point Way NE",
    "sg:city":"Seattle",
    "sg:classifiers":[
        {
            "category":"Museum",
            "type":"Entertainment"
        }
    ],
    "sg:phone":"+1 206 522 1187",
    "sg:postcode":"98115",
    "sg:province":"WA",
    "sg:tags":[
        "child",
        "gallery",
        "day",
        "care"
    ],
    "wof:name":"Roaring Mouse Creative AR",
    "wof:placetype":"venue"
},
  "geometry": {"coordinates":[-122.277811,47.698769],"type":"Point"}
}