{
  "type": "Feature",
  "properties": {
    "addr:full":"4277 US Hwy 12 Mossyrock WA 98564",
    "addr:housenumber":"4277",
    "addr:postcode":"98564",
    "addr:street":"Us Hwy 12 Mossyrock",
    "iso:country":"US",
    "sg:address":"4277 US Hwy 12",
    "sg:city":"Mossyrock",
    "sg:classifiers":[
        {
            "category":"Home & Garden",
            "subcategory":"Garden Supply",
            "type":"Retail Goods"
        }
    ],
    "sg:phone":"+1 360 983 3554",
    "sg:postcode":"98564",
    "sg:province":"WA",
    "sg:tags":[
        "tree",
        "christmas"
    ],
    "wof:name":"Cowlitz River Trees",
    "wof:placetype":"venue"
},
  "geometry": {"coordinates":[-122.474886,46.53634],"type":"Point"}
}