{
  "type": "Feature",
  "properties": {
    "addr:full":"4793 Stratford Rd NE Moses Lake WA 98837",
    "addr:housenumber":"4793",
    "addr:postcode":"98837",
    "addr:street":"Stratford Rd Ne",
    "iso:country":"US",
    "sg:address":"4793 Stratford Rd NE",
    "sg:city":"Moses Lake",
    "sg:classifiers":[
        {
            "category":"Professional",
            "subcategory":"Management & Consulting",
            "type":"Services"
        }
    ],
    "sg:phone":"+1 509 765 8330",
    "sg:postcode":"98837",
    "sg:province":"WA",
    "sg:tags":[
        "business"
    ],
    "wof:name":"Cs Auto Center",
    "wof:placetype":"venue"
},
  "geometry": {"coordinates":[-119.27807,47.159824],"type":"Point"}
}