{
  "type": "Feature",
  "properties": {
    "addr:full":"870 Country Haven Loop Pasco WA 99301",
    "addr:housenumber":"870",
    "addr:postcode":"99301",
    "addr:street":"Country Haven Loop",
    "iso:country":"US",
    "sg:address":"870 Country Haven Loop",
    "sg:city":"Pasco",
    "sg:classifiers":[
        {
            "category":"Restaurant",
            "type":"Food & Drink"
        }
    ],
    "sg:phone":"+1 509 266 4672",
    "sg:postcode":"99301",
    "sg:province":"WA",
    "wof:name":"Food Systems International",
    "wof:placetype":"venue"
},
  "geometry": {"coordinates":[-119.219949,46.409909],"type":"Point"}
}