{
  "type": "Feature",
  "properties": {
    "addr:full":"301 W 1st St Cle Elum WA 98922",
    "addr:housenumber":"301",
    "addr:postcode":"98922",
    "addr:street":"W 1St St",
    "iso:country":"US",
    "sg:address":"301 W 1st St",
    "sg:city":"Cle Elum",
    "sg:classifiers":[
        {
            "category":"Real Estate",
            "subcategory":"Developer",
            "type":"Services"
        },
        {
            "category":"Real Estate",
            "subcategory":"Real Estate Agent",
            "type":"Services"
        }
    ],
    "sg:phone":"+1 509 674 6828",
    "sg:postcode":"98922",
    "sg:province":"WA",
    "sg:tags":[
        "company",
        "land"
    ],
    "wof:name":"Sapphire Skies",
    "wof:placetype":"venue"
},
  "geometry": {"coordinates":[-120.941952,47.19532],"type":"Point"}
}