{
  "type": "Feature",
  "properties": {
    "addr:full":"300 E Gleed Rd Naches WA 98937",
    "addr:housenumber":"300",
    "addr:postcode":"98937",
    "addr:street":"E Gleed Rd",
    "iso:country":"US",
    "sg:address":"300 E Gleed Rd",
    "sg:city":"Naches",
    "sg:classifiers":[
        {
            "category":"Farming",
            "subcategory":"Farm",
            "type":"Manufacturing & Wholesale Goods"
        }
    ],
    "sg:phone":"+1 509 966 3101",
    "sg:postcode":"98937",
    "sg:province":"WA",
    "wof:name":"Mackenzie Farms",
    "wof:placetype":"venue"
},
  "geometry": {"coordinates":[-120.607962,46.658249],"type":"Point"}
}