{
  "type": "Feature",
  "properties": {
    "addr:full":"7450 N Division St Spokane WA 99208",
    "addr:housenumber":"7450",
    "addr:postcode":"99208",
    "addr:street":"N Division St",
    "iso:country":"US",
    "sg:address":"7450 N Division St",
    "sg:city":"Spokane",
    "sg:classifiers":[
        {
            "category":"Banks & Credit Unions",
            "subcategory":"Bank",
            "type":"Services"
        }
    ],
    "sg:phone":"+1 509 483 6451",
    "sg:postcode":"99208",
    "sg:province":"WA",
    "sg:tags":[
        "financing"
    ],
    "sg:website":"http://www.wellsfargofinancial.com",
    "wof:name":"Wells Fargo Financial",
    "wof:placetype":"venue"
},
  "geometry": {"coordinates":[-117.411222,47.725457],"type":"Point"}
}