{
  "type": "Feature",
  "properties": {
    "addr:full":"2018 Yukon Harbor Rd SE Port Orchard WA 98366",
    "addr:housenumber":"2018",
    "addr:postcode":"98366",
    "addr:street":"Yukon Harbor Rd Se",
    "iso:country":"US",
    "sg:address":"2018 Yukon Harbor Rd SE",
    "sg:city":"Port Orchard",
    "sg:classifiers":[
        {
            "category":"Wholesale",
            "subcategory":"Non-durable Goods",
            "type":"Manufacturing & Wholesale Goods"
        }
    ],
    "sg:phone":"+1 360 871 5080",
    "sg:postcode":"98366",
    "sg:province":"WA",
    "wof:name":"Dirks Fowler",
    "wof:placetype":"venue"
},
  "geometry": {"coordinates":[-122.546598,47.530358],"type":"Point"}
}