{
  "type": "Feature",
  "properties": {
    "addr:full":"18114 Westside Hwy SW Vashon WA 98070",
    "addr:housenumber":"18114",
    "addr:postcode":"98070",
    "addr:street":"Westside Hwy Sw",
    "iso:country":"US",
    "sg:address":"18114 Westside Hwy SW",
    "sg:city":"Vashon",
    "sg:classifiers":[
        {
            "category":"Shopping",
            "subcategory":"Books",
            "type":"Retail Goods"
        }
    ],
    "sg:phone":"+1 206 463 3338",
    "sg:postcode":"98070",
    "sg:province":"WA",
    "wof:name":"Big Raven Book",
    "wof:placetype":"venue"
},
  "geometry": {"coordinates":[-122.508523,47.442282],"type":"Point"}
}