{
  "type": "Feature",
  "properties": {
    "addr:full":"14041 15th Ave NE Seattle WA 98125",
    "addr:housenumber":"14041",
    "addr:postcode":"98125",
    "addr:street":"15Th Ave Ne",
    "iso:country":"US",
    "sg:address":"14041 15th Ave NE",
    "sg:city":"Seattle",
    "sg:classifiers":[
        {
            "category":"Building & Trades",
            "subcategory":"Construction",
            "type":"Services"
        }
    ],
    "sg:phone":"+1 206 363 1666",
    "sg:postcode":"98125",
    "sg:province":"WA",
    "sg:tags":[
        "house"
    ],
    "wof:name":"Steven Duarte Construction",
    "wof:placetype":"venue"
},
  "geometry": {"coordinates":[-122.312725,47.732124],"type":"Point"}
}