{
  "type": "Feature",
  "properties": {
    "addr:full":"12423 58th Dr SE Snohomish WA 98296",
    "addr:housenumber":"12423",
    "addr:postcode":"98296",
    "addr:street":"58Th Dr Se",
    "iso:country":"US",
    "sg:address":"12423 58th Dr SE",
    "sg:city":"Snohomish",
    "sg:classifiers":[
        {
            "category":"Utilities",
            "subcategory":"Water",
            "type":"Services"
        },
        {
            "category":"Building & Trades",
            "subcategory":"Cleaning & Sanitation",
            "type":"Services"
        }
    ],
    "sg:phone":"+1 888 368 7918",
    "sg:postcode":"98296",
    "sg:province":"WA",
    "sg:tags":[
        "emergency",
        "fire",
        "damage",
        "restoration",
        "remediation",
        "mold"
    ],
    "sg:website":"http://www.bennettrestoration.com",
    "wof:name":"Bennett Restoration & Cleaning",
    "wof:placetype":"venue"
},
  "geometry": {"coordinates":[-122.148123,47.883847],"type":"Point"}
}