{
  "type": "Feature",
  "properties": {
    "addr:full":"3917 S 250th St Kent WA 98032",
    "addr:housenumber":"3917",
    "addr:postcode":"98032",
    "addr:street":"S 250Th St",
    "iso:country":"US",
    "sg:address":"3917 S 250th St",
    "sg:city":"Kent",
    "sg:classifiers":[
        {
            "category":"Building & Trades",
            "subcategory":"Construction",
            "type":"Services"
        }
    ],
    "sg:phone":"+1 253 839 5160",
    "sg:postcode":"98032",
    "sg:province":"WA",
    "sg:tags":[
        "contractor",
        "painting",
        "hanging"
    ],
    "wof:name":"Steves Painting",
    "wof:placetype":"venue"
},
  "geometry": {"coordinates":[-122.282832,47.377601],"type":"Point"}
}