{
  "type": "Feature",
  "properties": {
    "addr:full":"13502 W Shore Rd Nine Mile Falls WA 99026",
    "addr:housenumber":"13502",
    "addr:postcode":"99026",
    "addr:street":"W Shore Rd",
    "iso:country":"US",
    "sg:address":"13502 W Shore Rd",
    "sg:city":"Nine Mile Falls",
    "sg:classifiers":[
        {
            "category":"Professional",
            "subcategory":"Management & Consulting",
            "type":"Services"
        }
    ],
    "sg:phone":"+1 509 466 4824",
    "sg:postcode":"99026",
    "sg:province":"WA",
    "sg:tags":[
        "retail",
        "direct",
        "sales"
    ],
    "wof:name":"Durams Diversified",
    "wof:placetype":"venue"
},
  "geometry": {"coordinates":[-117.598596,47.805976],"type":"Point"}
}