{
  "type": "Feature",
  "properties": {
    "addr:full":"6402 W Magnolia Ave Everett WA 98203",
    "addr:housenumber":"6402",
    "addr:postcode":"98203",
    "addr:street":"W Magnolia Ave",
    "iso:country":"US",
    "sg:address":"6402 W Magnolia Ave",
    "sg:city":"Everett",
    "sg:classifiers":[
        {
            "category":"Building & Trades",
            "subcategory":"Construction",
            "type":"Services"
        }
    ],
    "sg:phone":"+1 425 348 9337",
    "sg:postcode":"98203",
    "sg:province":"WA",
    "sg:tags":[
        "floor",
        "laying",
        "contractor"
    ],
    "wof:name":"Janzer Flooring",
    "wof:placetype":"venue"
},
  "geometry": {"coordinates":[-122.234562,47.941863],"type":"Point"}
}