{
  "type": "Feature",
  "properties": {
    "addr:full":"2415 Madrona Dr SE Port Orchard WA 98366",
    "addr:housenumber":"2415",
    "addr:postcode":"98366",
    "addr:street":"Madrona Dr Se",
    "iso:country":"US",
    "sg:address":"2415 Madrona Dr SE",
    "sg:city":"Port Orchard",
    "sg:classifiers":[
        {
            "category":"Social Services",
            "subcategory":"Child Care",
            "type":"Services"
        }
    ],
    "sg:phone":"+1 360 871 6249",
    "sg:postcode":"98366",
    "sg:province":"WA",
    "wof:name":"Little Lamb Day Care",
    "wof:placetype":"venue"
},
  "geometry": {"coordinates":[-122.606748,47.525364],"type":"Point"}
}