{
  "type": "Feature",
  "properties": {
    "addr:full":"2856 NE 65th Ave Vancouver WA 98661",
    "addr:housenumber":"2856",
    "addr:postcode":"98661",
    "addr:street":"Ne 65Th Ave",
    "iso:country":"US",
    "sg:address":"2856 NE 65th Ave",
    "sg:city":"Vancouver",
    "sg:classifiers":[
        {
            "category":"Autos & Motor Vehicles",
            "subcategory":"Motorcycle Sales",
            "type":"Retail Goods"
        }
    ],
    "sg:phone":"+1 360 693 4225",
    "sg:postcode":"98661",
    "sg:province":"WA",
    "wof:name":"Nash Motorcycle Co",
    "wof:placetype":"venue"
},
  "geometry": {"coordinates":[-122.605003,45.6437],"type":"Point"}
}