{
  "type": "Feature",
  "properties": {
    "addr:full":"4822 Rainier Ave S Seattle WA 98118",
    "addr:housenumber":"4822",
    "addr:postcode":"98118",
    "addr:street":"Rainier Ave S",
    "iso:country":"US",
    "sg:address":"4822 Rainier Ave S",
    "sg:city":"Seattle",
    "sg:classifiers":[
        {
            "category":"Restaurant",
            "type":"Food & Drink"
        }
    ],
    "sg:menulink":"http://www.allmenus.com/wa/seattle/144999-subway/menu/",
    "sg:phone":"+1 206 725 7777",
    "sg:postcode":"98118",
    "sg:province":"WA",
    "sg:tags":[
        "american",
        "sandwich"
    ],
    "wof:name":"Subway",
    "wof:placetype":"venue"
},
  "geometry": {"coordinates":[-122.285709,47.559093],"type":"Point"}
}