{
  "type": "Feature",
  "properties": {
    "addr:full":"3915 E Francis Ave Spokane WA 99217",
    "addr:housenumber":"3915",
    "addr:postcode":"99217",
    "addr:street":"E Francis Ave",
    "iso:country":"US",
    "sg:address":"3915 E Francis Ave",
    "sg:city":"Spokane",
    "sg:classifiers":[
        {
            "category":"Building & Trades",
            "subcategory":"Cleaning & Sanitation",
            "type":"Services"
        }
    ],
    "sg:phone":"+1 509 315 3581",
    "sg:postcode":"99217",
    "sg:province":"WA",
    "sg:tags":[
        "window",
        "contractor"
    ],
    "sg:website":"http://www.spokanecleaningservice.com/",
    "wof:name":"Spokane Cleaning Service",
    "wof:placetype":"venue"
},
  "geometry": {"coordinates":[-117.352975,47.714896],"type":"Point"}
}