{
  "type": "Feature",
  "properties": {
    "addr:full":"6400 Seaview Ave NW Seattle WA 98107",
    "addr:housenumber":"6400",
    "addr:postcode":"98107",
    "addr:street":"Seaview Ave Nw",
    "iso:country":"US",
    "sg:address":"6400 Seaview Ave NW",
    "sg:city":"Seattle",
    "sg:classifiers":[
        {
            "category":"Professional",
            "subcategory":"Computer Services",
            "type":"Services"
        }
    ],
    "sg:phone":"+1 206 783 0918",
    "sg:postcode":"98107",
    "sg:province":"WA",
    "sg:tags":[
        "publisher",
        "software",
        "developer"
    ],
    "wof:name":"Mango Park Stds",
    "wof:placetype":"venue"
},
  "geometry": {"coordinates":[-122.406357,47.675123],"type":"Point"}
}