{
  "type": "Feature",
  "properties": {
    "addr:full":"527 Sunrise Blvd Oak Harbor WA 98277",
    "addr:housenumber":"527",
    "addr:postcode":"98277",
    "addr:street":"Sunrise Blvd",
    "iso:country":"US",
    "sg:address":"527 Sunrise Blvd",
    "sg:city":"Oak Harbor",
    "sg:classifiers":[
        {
            "category":"Professional",
            "subcategory":"Management & Consulting",
            "type":"Services"
        }
    ],
    "sg:phone":"+1 360 240 0844",
    "sg:postcode":"98277",
    "sg:province":"WA",
    "sg:tags":[
        "trainer",
        "consultant",
        "speaker"
    ],
    "wof:name":"Bailey & Associates",
    "wof:placetype":"venue"
},
  "geometry": {"coordinates":[-122.585413,48.372248],"type":"Point"}
}