{
  "type": "Feature",
  "properties": {
    "addr:full":"15015 Tukwila Internationa Seattle WA 98188",
    "addr:housenumber":"15015",
    "addr:postcode":"98188",
    "addr:street":"Tukwila Internationa",
    "iso:country":"US",
    "sg:address":"15015 Tukwila Internationa",
    "sg:city":"Seattle",
    "sg:classifiers":[
        {
            "category":"Food & Beverages",
            "subcategory":"Groceries & Convenience Stores",
            "type":"Retail Goods"
        }
    ],
    "sg:phone":"+1 206 243 6446",
    "sg:postcode":"98188",
    "sg:province":"WA",
    "wof:name":"Riverton Heights",
    "wof:placetype":"venue"
},
  "geometry": {"coordinates":[-122.287128,47.468452],"type":"Point"}
}