{
  "type": "Feature",
  "properties": {
    "addr:full":"3245 146th Pl SE Bellevue WA 98007",
    "addr:housenumber":"3245",
    "addr:postcode":"98007",
    "addr:street":"146Th Pl Se",
    "iso:country":"US",
    "sg:address":"3245 146th Pl SE",
    "sg:city":"Bellevue",
    "sg:classifiers":[
        {
            "category":"Banks & Credit Unions",
            "subcategory":"Financial Services",
            "type":"Services"
        }
    ],
    "sg:phone":"+1 425 562 1181",
    "sg:postcode":"98007",
    "sg:province":"WA",
    "sg:tags":[
        "broker",
        "mortgage"
    ],
    "wof:name":"Procost",
    "wof:placetype":"venue"
},
  "geometry": {"coordinates":[-122.145903,47.580752],"type":"Point"}
}