{
  "type": "Feature",
  "properties": {
    "addr:full":"8510 Queets Dr NE Olympia WA 98516",
    "addr:housenumber":"8510",
    "addr:postcode":"98516",
    "addr:street":"Queets Dr Ne",
    "iso:country":"US",
    "sg:address":"8510 Queets Dr NE",
    "sg:city":"Olympia",
    "sg:classifiers":[
        {
            "category":"Professional",
            "subcategory":"Accounting & Tax Preparation",
            "type":"Services"
        }
    ],
    "sg:phone":"+1 360 701 9079",
    "sg:postcode":"98516",
    "sg:province":"WA",
    "wof:name":"Sheri K Hoyne",
    "wof:placetype":"venue"
},
  "geometry": {"coordinates":[-122.759061,47.062976],"type":"Point"}
}