{
  "type": "Feature",
  "properties": {
    "addr:full":"2400 11th Ave E Seattle WA 98102",
    "addr:housenumber":"2400",
    "addr:postcode":"98102",
    "addr:street":"11Th Ave E",
    "iso:country":"US",
    "sg:address":"2400 11th Ave E",
    "sg:city":"Seattle",
    "sg:classifiers":[
        {
            "category":"Education",
            "subcategory":"School",
            "type":"Public Place"
        }
    ],
    "sg:phone":"+1 206 324 7194",
    "sg:postcode":"98102",
    "sg:province":"WA",
    "sg:tags":[
        "high",
        "preparatory"
    ],
    "wof:name":"Seattle Preparatory School Development",
    "wof:placetype":"venue"
},
  "geometry": {"coordinates":[-122.318001,47.641499],"type":"Point"}
}