{
  "type": "Feature",
  "properties": {
    "addr:full":"1519 14th St NW Auburn WA 98001",
    "addr:housenumber":"1519",
    "addr:postcode":"98001",
    "addr:street":"14Th St Nw",
    "iso:country":"US",
    "sg:address":"1519 14th St NW",
    "sg:city":"Auburn",
    "sg:classifiers":[
        {
            "category":"Wholesale",
            "subcategory":"Farm Supplies",
            "type":"Manufacturing & Wholesale Goods"
        }
    ],
    "sg:phone":"+1 253 351 6591",
    "sg:postcode":"98001",
    "sg:province":"WA",
    "sg:tags":[
        "grocery",
        "electrical"
    ],
    "wof:name":"Wilbur Ellis Nthrn Div Dst 1",
    "wof:placetype":"venue"
},
  "geometry": {"coordinates":[-122.25181499999999,47.320885],"type":"Point"}
}