{
  "type": "Feature",
  "properties": {
    "addr:full":"104 W Naches Ave Selah WA 98942",
    "addr:housenumber":"104",
    "addr:postcode":"98942",
    "addr:street":"W Naches Ave",
    "iso:country":"US",
    "sg:address":"104 W Naches Ave",
    "sg:city":"Selah",
    "sg:classifiers":[
        {
            "category":"Shopping",
            "subcategory":"Books",
            "type":"Retail Goods"
        }
    ],
    "sg:phone":"+1 509 697 5688",
    "sg:postcode":"98942",
    "sg:province":"WA",
    "sg:tags":[
        "dealer"
    ],
    "wof:name":"A Little Peace Of Heaven",
    "wof:placetype":"venue"
},
  "geometry": {"coordinates":[-120.53172600000001,46.653972],"type":"Point"}
}