{
  "type": "Feature",
  "properties": {
    "addr:full":"903 W Wine Country Rd Grandview WA 98930",
    "addr:housenumber":"903",
    "addr:postcode":"98930",
    "addr:street":"W Wine Country Rd",
    "iso:country":"US",
    "sg:address":"903 W Wine Country Rd",
    "sg:city":"Grandview",
    "sg:classifiers":[
        {
            "category":"Travel",
            "subcategory":"Hotels & Motels",
            "type":"Entertainment"
        }
    ],
    "sg:phone":"+1 509 882 3003",
    "sg:postcode":"98930",
    "sg:province":"WA",
    "sg:tags":[
        "operation"
    ],
    "wof:name":"Apple Valley Motel",
    "wof:placetype":"venue"
},
  "geometry": {"coordinates":[-119.914952,46.260752],"type":"Point"}
}