{
  "type": "Feature",
  "properties": {
    "addr:full":"210 Twin Lakes Rd Winthrop WA 98862",
    "addr:housenumber":"210",
    "addr:postcode":"98862",
    "addr:street":"Twin Lakes Rd",
    "iso:country":"US",
    "sg:address":"210 Twin Lakes Rd",
    "sg:city":"Winthrop",
    "sg:classifiers":[
        {
            "category":"Travel",
            "subcategory":"Campground",
            "type":"Entertainment"
        }
    ],
    "sg:phone":"+1 509 996 2650",
    "sg:postcode":"98862",
    "sg:province":"WA",
    "wof:name":"Big Twin Lakes Campground",
    "wof:placetype":"venue"
},
  "geometry": {"coordinates":[-120.20092699999999,48.445834],"type":"Point"}
}