{
  "type": "Feature",
  "properties": {
    "addr:full":"5895 Northwest Dr Ferndale WA 98248",
    "addr:housenumber":"5895",
    "addr:postcode":"98248",
    "addr:street":"Northwest Dr",
    "iso:country":"US",
    "sg:address":"5895 Northwest Dr",
    "sg:city":"Ferndale",
    "sg:classifiers":[
        {
            "category":"Building & Trades",
            "subcategory":"Construction",
            "type":"Services"
        }
    ],
    "sg:phone":"+1 360 312 1855",
    "sg:postcode":"98248",
    "sg:province":"WA",
    "sg:tags":[
        "wallcoverings-installation",
        "wallpaper",
        "painting",
        "contractor"
    ],
    "sg:website":"http://www.pgpaintingcompany.com",
    "wof:name":"P G Painting",
    "wof:placetype":"venue"
},
  "geometry": {"coordinates":[-122.540933,48.854975],"type":"Point"}
}