{
  "type": "Feature",
  "properties": {
    "addr:full":"12920 Fast Ln SW Olympia WA 98512",
    "addr:housenumber":"12920",
    "addr:postcode":"98512",
    "addr:street":"Fast Ln Sw",
    "iso:country":"US",
    "sg:address":"12920 Fast Ln SW",
    "sg:city":"Olympia",
    "sg:classifiers":[
        {
            "category":"Building & Trades",
            "subcategory":"Construction",
            "type":"Services"
        }
    ],
    "sg:phone":"+1 360 352 0189",
    "sg:postcode":"98512",
    "sg:province":"WA",
    "sg:tags":[
        "house",
        "builder",
        "home"
    ],
    "wof:name":"Pedersen Construction Co",
    "wof:placetype":"venue"
},
  "geometry": {"coordinates":[-122.990933,46.899714],"type":"Point"}
}