{
  "type": "Feature",
  "properties": {
    "addr:full":"11000 NE 33rd Pl Ste 300 Bellevue WA 98004",
    "addr:housenumber":"11000",
    "addr:postcode":"98004",
    "addr:street":"Ne 33Rd Pl Ste 300",
    "iso:country":"US",
    "sg:address":"11000 NE 33rd Pl Ste 300",
    "sg:city":"Bellevue",
    "sg:classifiers":[
        {
            "category":"Banks & Credit Unions",
            "subcategory":"Financial Services",
            "type":"Services"
        }
    ],
    "sg:phone":"+1 425 822 0180",
    "sg:postcode":"98004",
    "sg:province":"WA",
    "sg:tags":[
        "broker",
        "mortgage"
    ],
    "wof:name":"Eagle Funding",
    "wof:placetype":"venue"
},
  "geometry": {"coordinates":[-122.191002,47.639801],"type":"Point"}
}