{
  "type": "Feature",
  "properties": {
    "addr:full":"16757 32nd Ave NE Seattle WA 98155",
    "addr:housenumber":"16757",
    "addr:postcode":"98155",
    "addr:street":"32Nd Ave Ne",
    "iso:country":"US",
    "sg:address":"16757 32nd Ave NE",
    "sg:city":"Seattle",
    "sg:classifiers":[
        {
            "category":"Building & Trades",
            "subcategory":"Electrical",
            "type":"Services"
        }
    ],
    "sg:phone":"+1 206 363 1492",
    "sg:postcode":"98155",
    "sg:province":"WA",
    "sg:tags":[
        "electrical",
        "contractor"
    ],
    "wof:name":"AK Electric Inc",
    "wof:placetype":"venue"
},
  "geometry": {"coordinates":[-122.295873,47.751303],"type":"Point"}
}