{
  "type": "Feature",
  "properties": {
    "addr:full":"6721 Regents Blvd Tacoma WA 98466",
    "addr:housenumber":"6721",
    "addr:postcode":"98466",
    "addr:street":"Regents Blvd",
    "iso:country":"US",
    "sg:address":"6721 Regents Blvd",
    "sg:city":"Tacoma",
    "sg:classifiers":[
        {
            "category":"Real Estate",
            "subcategory":"Real Estate Agent",
            "type":"Services"
        }
    ],
    "sg:phone":"+1 253 759 5282",
    "sg:postcode":"98466",
    "sg:province":"WA",
    "sg:tags":[
        "appraiser"
    ],
    "wof:name":"Allotta Real Estate Appraisal",
    "wof:placetype":"venue"
},
  "geometry": {"coordinates":[-122.52788700000001,47.235687],"type":"Point"}
}