{
  "type": "Feature",
  "properties": {
    "addr:full":"7316 101st Stct NW Gig Harbor WA 98332",
    "addr:housenumber":"7316",
    "addr:postcode":"98332",
    "addr:street":"101St Stct Nw",
    "iso:country":"US",
    "sg:address":"7316 101st Stct NW",
    "sg:city":"Gig Harbor",
    "sg:classifiers":[
        {
            "category":"Professional",
            "subcategory":"Management & Consulting",
            "type":"Services"
        }
    ],
    "sg:phone":"+1 253 853 5700",
    "sg:postcode":"98332",
    "sg:province":"WA",
    "wof:name":"Steward Prudent Consulting",
    "wof:placetype":"venue"
},
  "geometry": {"coordinates":[-122.636703,47.350454],"type":"Point"}
}