{
  "type": "Feature",
  "properties": {
    "addr:full":"15141 NE 8th Pl Bellevue WA 98007",
    "addr:housenumber":"15141",
    "addr:postcode":"98007",
    "addr:street":"Ne 8Th Pl",
    "iso:country":"US",
    "sg:address":"15141 NE 8th Pl",
    "sg:city":"Bellevue",
    "sg:classifiers":[
        {
            "category":"Shopping",
            "subcategory":"Used Merchandise",
            "type":"Retail Goods"
        }
    ],
    "sg:phone":"+1 425 641 5125",
    "sg:postcode":"98007",
    "sg:province":"WA",
    "wof:name":"Aggys Collectibles",
    "wof:placetype":"venue"
},
  "geometry": {"coordinates":[-122.13808400000001,47.617707],"type":"Point"}
}