{
  "type": "Feature",
  "properties": {
    "addr:full":"12523 Case Rd SW Olympia WA 98512",
    "addr:housenumber":"12523",
    "addr:postcode":"98512",
    "addr:street":"Case Rd Sw",
    "iso:country":"US",
    "sg:address":"12523 Case Rd SW",
    "sg:city":"Olympia",
    "sg:classifiers":[
        {
            "category":"Building & Trades",
            "subcategory":"Construction",
            "type":"Services"
        }
    ],
    "sg:phone":"+1 360 754 9646",
    "sg:postcode":"98512",
    "sg:province":"WA",
    "sg:tags":[
        "excavation",
        "contractor"
    ],
    "wof:name":"Timber Mill",
    "wof:placetype":"venue"
},
  "geometry": {"coordinates":[-122.958877,46.911889],"type":"Point"}
}