{
  "type": "Feature",
  "properties": {
    "addr:full":"18832 53rd Ave NE Seattle WA 98155",
    "addr:housenumber":"18832",
    "addr:postcode":"98155",
    "addr:street":"53Rd Ave Ne",
    "iso:country":"US",
    "sg:address":"18832 53rd Ave NE",
    "sg:city":"Seattle",
    "sg:classifiers":[
        {
            "category":"Real Estate",
            "subcategory":"Real Estate Agent",
            "type":"Services"
        }
    ],
    "sg:phone":"+1 206 368 5586",
    "sg:postcode":"98155",
    "sg:province":"WA",
    "wof:name":"Steve Hartley",
    "wof:placetype":"venue"
},
  "geometry": {"coordinates":[-122.271631,47.764357],"type":"Point"}
}