{
  "type": "Feature",
  "properties": {
    "addr:full":"2808 43rd Ave W Seattle WA 98199",
    "addr:housenumber":"2808",
    "addr:postcode":"98199",
    "addr:street":"43Rd Ave W",
    "iso:country":"US",
    "sg:address":"2808 43rd Ave W",
    "sg:city":"Seattle",
    "sg:classifiers":[
        {
            "category":"Shopping",
            "subcategory":"Jewelry",
            "type":"Retail Goods"
        }
    ],
    "sg:phone":"+1 206 283 8578",
    "sg:postcode":"98199",
    "sg:province":"WA",
    "wof:name":"Four Swans Jewelry",
    "wof:placetype":"venue"
},
  "geometry": {"coordinates":[-122.41188099999999,47.646723],"type":"Point"}
}