{
  "type": "Feature",
  "properties": {
    "addr:full":"28915 47th Ave E Graham WA 98338",
    "addr:housenumber":"28915",
    "addr:postcode":"98338",
    "addr:street":"47Th Ave E",
    "iso:country":"US",
    "sg:address":"28915 47th Ave E",
    "sg:city":"Graham",
    "sg:classifiers":[
        {
            "category":"Building & Trades",
            "subcategory":"Electrical",
            "type":"Services"
        }
    ],
    "sg:phone":"+1 253 875 1522",
    "sg:postcode":"98338",
    "sg:province":"WA",
    "sg:tags":[
        "electrical",
        "contractor"
    ],
    "wof:name":"Thompson Electrical Contr",
    "wof:placetype":"venue"
},
  "geometry": {"coordinates":[-122.36525399999999,46.993065],"type":"Point"}
}