{
  "type": "Feature",
  "properties": {
    "addr:full":"1701 2nd Ave N Seattle WA 98109",
    "addr:housenumber":"1701",
    "addr:postcode":"98109",
    "addr:street":"2Nd Ave N",
    "iso:country":"US",
    "sg:address":"1701 2nd Ave N",
    "sg:city":"Seattle",
    "sg:classifiers":[
        {
            "category":"Health Services",
            "subcategory":"Health Practitioner",
            "type":"Services"
        }
    ],
    "sg:phone":"+1 206 282 8293",
    "sg:postcode":"98109",
    "sg:province":"WA",
    "wof:name":"Healthyself Thrptic Sted Chair",
    "wof:placetype":"venue"
},
  "geometry": {"coordinates":[-122.353195,47.634861],"type":"Point"}
}