{
  "type": "Feature",
  "properties": {
    "addr:full":"1416 NW Ballard Way Seattle WA 98107",
    "addr:housenumber":"1416",
    "addr:postcode":"98107",
    "addr:street":"Nw Ballard Way",
    "iso:country":"US",
    "sg:address":"1416 NW Ballard Way",
    "sg:city":"Seattle",
    "sg:classifiers":[
        {
            "category":"Sports & Exercise",
            "subcategory":"Gym",
            "type":"Entertainment"
        }
    ],
    "sg:phone":"+1 206 508 5030",
    "sg:postcode":"98107",
    "sg:province":"WA",
    "sg:website":"lafitness.com",
    "wof:name":"LA Fitness",
    "wof:placetype":"venue"
},
  "geometry": {"coordinates":[-122.37397199999999,47.662945],"type":"Point"}
}