{
  "type": "Feature",
  "properties": {
    "iso:country":"US",
    "sg:address":"3171 E Agate Rd",
    "sg:city":"Shelton",
    "sg:classifiers":[
        {
            "category":"Retail",
            "subcategory":"Repair Shop",
            "type":"Services"
        }
    ],
    "sg:phone":"+1 360 426 4744",
    "sg:postcode":"98584",
    "sg:province":"WA",
    "sg:tags":[
        "welding"
    ],
    "wof:name":"Don Kroum Welding",
    "wof:placetype":"venue"
},
  "geometry": {"coordinates":[-123.0124,47.218106],"type":"Point"}
}