{
  "type": "Feature",
  "properties": {
    "addr:full":"2106 N Fife St Tacoma WA 98406",
    "addr:housenumber":"2106",
    "addr:postcode":"98406",
    "addr:street":"N Fife St",
    "iso:country":"US",
    "sg:address":"2106 N Fife St",
    "sg:city":"Tacoma",
    "sg:classifiers":[
        {
            "category":"Professional",
            "type":"Services"
        }
    ],
    "sg:phone":"+1 253 752 1017",
    "sg:postcode":"98406",
    "sg:province":"WA",
    "sg:tags":[
        "establishment"
    ],
    "wof:name":"Joe Johnson Enterprises",
    "wof:placetype":"venue"
},
  "geometry": {"coordinates":[-122.470432,47.268727],"type":"Point"}
}