{
  "type": "Feature",
  "properties": {
    "addr:full":"345 6th St Bremerton WA 98337",
    "addr:housenumber":"345",
    "addr:postcode":"98337",
    "addr:street":"6Th St",
    "iso:country":"US",
    "sg:address":"345 6th St",
    "sg:city":"Bremerton",
    "sg:classifiers":[
        {
            "category":"Government",
            "subcategory":"Office",
            "type":"Public Place"
        }
    ],
    "sg:phone":"+1 360 473 5290",
    "sg:postcode":"98337",
    "sg:province":"WA",
    "sg:tags":[
        "city"
    ],
    "sg:website":"www.ci.bremerton.wa.us",
    "wof:name":"Bremerton City Clerk",
    "wof:placetype":"venue"
},
  "geometry": {"coordinates":[-122.62553200000001,47.567239],"type":"Point"}
}