{
  "type": "Feature",
  "properties": {
    "addr:full":"220 Rhododendron Way NW Bremerton WA 98312",
    "addr:housenumber":"220",
    "addr:postcode":"98312",
    "addr:street":"Rhododendron Way Nw",
    "iso:country":"US",
    "sg:address":"220 Rhododendron Way NW",
    "sg:city":"Bremerton",
    "sg:classifiers":[
        {
            "category":"Real Estate",
            "subcategory":"Surveying",
            "type":"Services"
        }
    ],
    "sg:phone":"+1 360 830 4119",
    "sg:postcode":"98312",
    "sg:province":"WA",
    "wof:name":"Lakeside Land Surveying",
    "wof:placetype":"venue"
},
  "geometry": {"coordinates":[-122.842477,47.566271],"type":"Point"}
}