{
  "type": "Feature",
  "properties": {
    "addr:full":"24804 S Dague Rd Kennewick WA 99337",
    "addr:housenumber":"24804",
    "addr:postcode":"99337",
    "addr:street":"S Dague Rd",
    "iso:country":"US",
    "sg:address":"24804 S Dague Rd",
    "sg:city":"Kennewick",
    "sg:classifiers":[
        {
            "category":"Utilities",
            "subcategory":"Telephone",
            "type":"Services"
        }
    ],
    "sg:phone":"+1 509 586 4743",
    "sg:postcode":"99337",
    "sg:province":"WA",
    "sg:tags":[
        "communications"
    ],
    "wof:name":"Tim Curd Telephone Cnstr",
    "wof:placetype":"venue"
},
  "geometry": {"coordinates":[-119.07587700000001,46.175707],"type":"Point"}
}