{
  "type": "Feature",
  "properties": {
    "addr:full":"9210 N Oakland Rd Newman Lake WA 99025",
    "addr:housenumber":"9210",
    "addr:postcode":"99025",
    "addr:street":"N Oakland Rd",
    "iso:country":"US",
    "sg:address":"9210 N Oakland Rd",
    "sg:city":"Newman Lake",
    "sg:classifiers":[
        {
            "category":"Professional",
            "subcategory":"Computer Services",
            "type":"Services"
        }
    ],
    "sg:phone":"+1 509 226 1905",
    "sg:postcode":"99025",
    "sg:province":"WA",
    "sg:tags":[
        "related"
    ],
    "wof:name":"PJC Consulting",
    "wof:placetype":"venue"
},
  "geometry": {"coordinates":[-117.07632099999999,47.738651],"type":"Point"}
}