{
  "type": "Feature",
  "properties": {
    "addr:full":"9637 22nd Ave SW Seattle WA 98106",
    "addr:housenumber":"9637",
    "addr:postcode":"98106",
    "addr:street":"22Nd Ave Sw",
    "iso:country":"US",
    "sg:address":"9637 22nd Ave SW",
    "sg:city":"Seattle",
    "sg:classifiers":[
        {
            "category":"Professional",
            "type":"Services"
        }
    ],
    "sg:phone":"+1 206 762 4946",
    "sg:postcode":"98106",
    "sg:province":"WA",
    "wof:name":"American Blue World Inc",
    "wof:placetype":"venue"
},
  "geometry": {"coordinates":[-122.36194399999999,47.51586],"type":"Point"}
}