{
  "type": "Feature",
  "properties": {
    "addr:full":"6517 Sexton Dr NW Olympia WA 98502",
    "addr:housenumber":"6517",
    "addr:postcode":"olympia wa 98502",
    "addr:street":"Sexton Dr Nw",
    "iso:country":"US",
    "sg:address":"6517 Sexton Dr NW",
    "sg:city":"Olympia",
    "sg:classifiers":[
        {
            "category":"Retail",
            "subcategory":"Auto Repair",
            "type":"Services"
        }
    ],
    "sg:phone":"+1 360 867 0436",
    "sg:postcode":"98502",
    "sg:province":"WA",
    "sg:tags":[
        "general"
    ],
    "wof:name":"Kens Automotive & Electric",
    "wof:placetype":"venue"
},
  "geometry": {"coordinates":[-123.017296,47.077107],"type":"Point"}
}