{
  "type": "Feature",
  "properties": {
    "iso:country":"US",
    "sg:address":"104 N Laurel St",
    "sg:city":"Port Angeles",
    "sg:classifiers":[
        {
            "category":"Wholesale",
            "subcategory":"Durable Goods & Equipment",
            "type":"Manufacturing & Wholesale Goods"
        }
    ],
    "sg:phone":"+1 360 460 1723",
    "sg:postcode":"98362",
    "sg:province":"WA",
    "wof:name":"Munro LLC",
    "wof:placetype":"venue"
},
  "geometry": {"coordinates":[-123.432773,48.119884],"type":"Point"}
}