{
  "type": "Feature",
  "properties": {
    "addr:full":"1601 N Walnut St Ellensburg WA 98926",
    "addr:housenumber":"1601",
    "addr:postcode":"98926",
    "addr:street":"N Walnut St",
    "iso:country":"US",
    "sg:address":"1601 N Walnut St",
    "sg:city":"Ellensburg",
    "sg:classifiers":[
        {
            "category":"Professional",
            "subcategory":"Computer Services",
            "type":"Services"
        }
    ],
    "sg:phone":"+1 509 963 9060",
    "sg:postcode":"98926",
    "sg:province":"WA",
    "sg:tags":[
        "programing",
        "custom"
    ],
    "wof:name":"Mako Bay Creation",
    "wof:placetype":"venue"
},
  "geometry": {"coordinates":[-120.539579,47.007946],"type":"Point"}
}