{
  "type": "Feature",
  "properties": {
    "iso:country":"US",
    "sg:address":"8864 Utah St NE",
    "sg:city":"Bremerton",
    "sg:classifiers":[
        {
            "category":"Professional",
            "subcategory":"Computer Services",
            "type":"Services"
        }
    ],
    "sg:phone":"+1 360 698 4107",
    "sg:postcode":"98311",
    "sg:province":"WA",
    "sg:tags":[
        "related"
    ],
    "wof:name":"Infosys Network Solutions LLC",
    "wof:placetype":"venue"
},
  "geometry": {"coordinates":[-122.60509500000001,47.643581],"type":"Point"}
}