{
  "type": "Feature",
  "properties": {
    "addr:full":"205 NE Northlake Way Ste 200 Seattle WA 98105",
    "addr:housenumber":"205",
    "addr:postcode":"98105",
    "addr:street":"Ne Northlake Way Ste 200",
    "iso:country":"US",
    "sg:address":"205 NE Northlake Way Ste 200",
    "sg:city":"Seattle",
    "sg:classifiers":[
        {
            "category":"Building & Trades",
            "subcategory":"Construction",
            "type":"Services"
        }
    ],
    "sg:phone":"+1 206 633 1522",
    "sg:postcode":"98105",
    "sg:province":"WA",
    "sg:tags":[
        "interior",
        "design"
    ],
    "wof:name":"Jones William C",
    "wof:placetype":"venue"
},
  "geometry": {"coordinates":[-122.325996,47.653702],"type":"Point"}
}