{
  "type": "Feature",
  "properties": {
    "iso:country":"US",
    "sg:address":"607 W Garfield St",
    "sg:city":"Seattle",
    "sg:classifiers":[
        {
            "category":"Real Estate",
            "subcategory":"Real Estate Operator",
            "type":"Services"
        }
    ],
    "sg:phone":"+1 206 282 6157",
    "sg:postcode":"98119",
    "sg:province":"WA",
    "sg:tags":[
        "building",
        "nonresidential"
    ],
    "wof:name":"La Wilson Properties LLC",
    "wof:placetype":"venue"
},
  "geometry": {"coordinates":[-122.366321,47.63345],"type":"Point"}
}