{
  "type": "Feature",
  "properties": {
    "addr:full":"11702 E Mansfield Ave Spokane Valley WA 99206",
    "addr:housenumber":"11702",
    "addr:postcode":"99206",
    "addr:street":"E Mansfield Ave",
    "iso:country":"US",
    "sg:address":"11702 E Mansfield Ave",
    "sg:city":"Spokane Valley",
    "sg:classifiers":[
        {
            "category":"Building & Trades",
            "subcategory":"Construction",
            "type":"Services"
        }
    ],
    "sg:phone":"+1 509 539 1494",
    "sg:postcode":"99206",
    "sg:province":"WA",
    "sg:tags":[
        "product",
        "asphalt"
    ],
    "wof:name":"Early Bird Parking Lot",
    "wof:placetype":"venue"
},
  "geometry": {"coordinates":[-117.246162,47.677677],"type":"Point"}
}