{
  "type": "Feature",
  "properties": {
    "addr:full":"3717 California Ave SW Seattle WA 98116",
    "addr:housenumber":"3717",
    "addr:postcode":"98116",
    "addr:street":"California Ave Sw",
    "iso:country":"US",
    "sg:address":"3717 California Ave SW",
    "sg:city":"Seattle",
    "sg:classifiers":[
        {
            "category":"Banks & Credit Unions",
            "subcategory":"Financial Services",
            "type":"Services"
        }
    ],
    "sg:phone":"+1 206 708 7261",
    "sg:postcode":"98116",
    "sg:province":"WA",
    "sg:tags":[
        "broker",
        "mortgage"
    ],
    "sg:website":"www.alliedmtgcapital.com",
    "wof:name":"Allied Home Mortgage",
    "wof:placetype":"venue"
},
  "geometry": {"coordinates":[-122.386973,47.571084],"type":"Point"}
}