{
  "type": "Feature",
  "properties": {
    "addr:full":"101 Cottage Ave Cashmere WA 98815",
    "addr:housenumber":"101",
    "addr:postcode":"98815",
    "addr:street":"Cottage Ave",
    "iso:country":"US",
    "sg:address":"101 Cottage Ave",
    "sg:city":"Cashmere",
    "sg:classifiers":[
        {
            "category":"Shopping",
            "type":"Retail Goods"
        }
    ],
    "sg:phone":"+1 509 782 4770",
    "sg:postcode":"98815",
    "sg:province":"WA",
    "sg:tags":[
        "miscellaneous",
        "store"
    ],
    "wof:name":"Bath House",
    "wof:placetype":"venue"
},
  "geometry": {"coordinates":[-120.470006,47.522172],"type":"Point"}
}