{
  "type": "Feature",
  "properties": {
    "addr:full":"1515 Charleston Beach Rd W Bremerton WA 98312",
    "addr:housenumber":"1515",
    "addr:postcode":"98312",
    "addr:street":"Charleston Beach Rd W",
    "iso:country":"US",
    "sg:address":"1515 Charleston Beach Rd W",
    "sg:city":"Bremerton",
    "sg:classifiers":[
        {
            "category":"Autos & Motor Vehicles",
            "subcategory":"Motorcycle Sales",
            "type":"Retail Goods"
        }
    ],
    "sg:phone":"+1 360 377 5568",
    "sg:postcode":"98312",
    "sg:province":"WA",
    "sg:tags":[
        "scooter"
    ],
    "wof:name":"Cliff's Cycle & Watercraft Ctr",
    "wof:placetype":"venue"
},
  "geometry": {"coordinates":[-122.66413300000001,47.551036],"type":"Point"}
}