{
  "type": "Feature",
  "properties": {
    "addr:full":"12311 176th Ave SE Renton WA 98059",
    "addr:housenumber":"12311",
    "addr:postcode":"98059",
    "addr:street":"176Th Ave Se",
    "iso:country":"US",
    "sg:address":"12311 176th Ave SE",
    "sg:city":"Renton",
    "sg:classifiers":[
        {
            "category":"Shopping",
            "subcategory":"Gifts & Souvenirs",
            "type":"Retail Goods"
        }
    ],
    "sg:phone":"+1 425 271 8146",
    "sg:postcode":"98059",
    "sg:province":"WA",
    "wof:name":"Country Woods",
    "wof:placetype":"venue"
},
  "geometry": {"coordinates":[-122.10632099999999,47.487708],"type":"Point"}
}