{
  "type": "Feature",
  "properties": {
    "addr:full":"2304 NW 209th St Ridgefield WA 98642",
    "addr:housenumber":"2304",
    "addr:postcode":"98642",
    "addr:street":"Nw 209Th St",
    "iso:country":"US",
    "sg:address":"2304 NW 209th St",
    "sg:city":"Ridgefield",
    "sg:classifiers":[
        {
            "category":"Health Services",
            "subcategory":"Chiropractor",
            "type":"Services"
        }
    ],
    "sg:phone":"+1 360 601 8575",
    "sg:postcode":"98642",
    "sg:province":"WA",
    "wof:name":"Simply Chiropractic",
    "wof:placetype":"venue"
},
  "geometry": {"coordinates":[-122.69511900000001,45.771623],"type":"Point"}
}