{
  "type": "Feature",
  "properties": {
    "addr:full":"810 Grandridge Rd Grandview WA 98930",
    "addr:housenumber":"810",
    "addr:postcode":"98930",
    "addr:street":"Grandridge Rd",
    "iso:country":"US",
    "sg:address":"810 Grandridge Rd",
    "sg:city":"Grandview",
    "sg:classifiers":[
        {
            "category":"Real Estate",
            "subcategory":"Real Estate Operator",
            "type":"Services"
        }
    ],
    "sg:phone":"+1 509 882 2911",
    "sg:postcode":"98930",
    "sg:province":"WA",
    "sg:tags":[
        "apartment"
    ],
    "wof:name":"Vineyard II",
    "wof:placetype":"venue"
},
  "geometry": {"coordinates":[-119.905052,46.247154],"type":"Point"}
}