{
  "type": "Feature",
  "properties": {
    "iso:country":"US",
    "sg:address":"1105 Mount Vernon Terminal RR",
    "sg:city":"Mt Vernon",
    "sg:classifiers":[
        {
            "category":"Home & Garden",
            "subcategory":"Furniture",
            "type":"Retail Goods"
        }
    ],
    "sg:phone":"+1 360 424 7876",
    "sg:postcode":"98273",
    "sg:province":"WA",
    "wof:name":"Rolfson's Home Furnishings",
    "wof:placetype":"venue"
},
  "geometry": {"coordinates":[-122.34052699999999,48.414814],"type":"Point"}
}