{
  "type": "Feature",
  "properties": {
    "iso:country":"US",
    "sg:address":"223 E 4th St",
    "sg:city":"Port Angeles",
    "sg:classifiers":[
        {
            "category":"Government",
            "subcategory":"Office",
            "type":"Public Place"
        }
    ],
    "sg:phone":"+1 360 417 2303",
    "sg:postcode":"98362",
    "sg:province":"WA",
    "sg:tags":[
        "administrative",
        "program",
        "health"
    ],
    "wof:name":"Callam Cnty Dpt Hlth Humn Srvc",
    "wof:placetype":"venue"
},
  "geometry": {"coordinates":[-123.43238100000001,48.114993],"type":"Point"}
}