{
  "type": "Feature",
  "properties": {
    "addr:full":"1701 E Sprague Ave Spokane WA 99202",
    "addr:housenumber":"1701",
    "addr:postcode":"99202",
    "addr:street":"E Sprague Ave",
    "iso:country":"US",
    "sg:address":"1701 E Sprague Ave",
    "sg:city":"Spokane",
    "sg:classifiers":[
        {
            "category":"Retail",
            "subcategory":"Repair Shop",
            "type":"Services"
        }
    ],
    "sg:phone":"+1 509 534 7952",
    "sg:postcode":"99202",
    "sg:province":"WA",
    "sg:tags":[
        "lock",
        "locksmith"
    ],
    "wof:name":"ABC Locksmith",
    "wof:placetype":"venue"
},
  "geometry": {"coordinates":[-117.38422300000001,47.657244],"type":"Point"}
}