{
  "type": "Feature",
  "properties": {
    "iso:country":"US",
    "sg:address":"2622 Lilac St",
    "sg:city":"Longview",
    "sg:classifiers":[
        {
            "category":"Building & Trades",
            "subcategory":"Construction",
            "type":"Services"
        }
    ],
    "sg:phone":"+1 360 425 4143",
    "sg:postcode":"98632",
    "sg:province":"WA",
    "sg:tags":[
        "refinery",
        "oil"
    ],
    "wof:name":"Whitten Group International",
    "wof:placetype":"venue"
},
  "geometry": {"coordinates":[-122.95516000000001,46.142229],"type":"Point"}
}