{
  "type": "Feature",
  "properties": {
    "addr:full":"3212 E Terrace St Seattle WA 98122",
    "addr:housenumber":"3212",
    "addr:postcode":"98122",
    "addr:street":"E Terrace St",
    "iso:country":"US",
    "sg:address":"3212 E Terrace St",
    "sg:city":"Seattle",
    "sg:classifiers":[
        {
            "category":"Professional",
            "subcategory":"Management & Consulting",
            "type":"Services"
        }
    ],
    "sg:phone":"+1 206 428 9034",
    "sg:postcode":"98122",
    "sg:province":"WA",
    "sg:tags":[
        "business"
    ],
    "wof:name":"Stephen Brown Expriance Design",
    "wof:placetype":"venue"
},
  "geometry": {"coordinates":[-122.29059700000001,47.605229],"type":"Point"}
}