{
  "type": "Feature",
  "properties": {
    "addr:full":"1332 S 1st St Yakima WA 98901",
    "addr:housenumber":"1332",
    "addr:postcode":"98901",
    "addr:street":"S 1St St",
    "iso:country":"US",
    "sg:address":"1332 S 1st St",
    "sg:city":"Yakima",
    "sg:classifiers":[
        {
            "category":"Professional",
            "subcategory":"Business Services",
            "type":"Services"
        }
    ],
    "sg:phone":"+1 509 469 6127",
    "sg:postcode":"98901",
    "sg:province":"WA",
    "sg:tags":[
        "translator",
        "interpreter"
    ],
    "wof:name":"Castro Interpretation",
    "wof:placetype":"venue"
},
  "geometry": {"coordinates":[-120.49663700000001,46.58527],"type":"Point"}
}