{
  "type": "Feature",
  "properties": {
    "iso:country":"US",
    "sg:address":"4314 Desert St",
    "sg:city":"Pasco",
    "sg:classifiers":[
        {
            "category":"Retail",
            "subcategory":"Laundry & Dry Cleaning",
            "type":"Services"
        }
    ],
    "sg:phone":"+1 509 545 8946",
    "sg:postcode":"99301",
    "sg:province":"WA",
    "wof:name":"Professionals Choice Carpet",
    "wof:placetype":"venue"
},
  "geometry": {"coordinates":[-119.146792,46.263347],"type":"Point"}
}