{
  "type": "Feature",
  "properties": {
    "iso:country":"US",
    "sg:address":"3118 NE 165th Pl",
    "sg:city":"Vancouver",
    "sg:classifiers":[
        {
            "category":"Professional",
            "subcategory":"Management & Consulting",
            "type":"Services"
        }
    ],
    "sg:phone":"+1 503 255 5292",
    "sg:postcode":"98682",
    "sg:province":"WA",
    "sg:tags":[
        "business"
    ],
    "wof:name":"Padusa International Dev",
    "wof:placetype":"venue"
},
  "geometry": {"coordinates":[-122.50268699999999,45.644031],"type":"Point"}
}