{
  "type": "Feature",
  "properties": {
    "addr:full":"6230 Rainier Ave S Seattle WA 98118",
    "addr:housenumber":"6230",
    "addr:postcode":"98118",
    "addr:street":"Rainier Ave S",
    "iso:country":"US",
    "sg:address":"6230 Rainier Ave S",
    "sg:city":"Seattle",
    "sg:classifiers":[
        {
            "category":"Restaurant",
            "type":"Food & Drink"
        },
        {
            "category":"Food Court",
            "type":"Food & Drink"
        }
    ],
    "sg:postcode":"98118",
    "sg:province":"WA",
    "sg:tags":[
        "mexican",
        "stand"
    ],
    "wof:name":"Los Potrillos",
    "wof:placetype":"venue"
},
  "geometry": {"coordinates":[-122.276425,47.546469],"type":"Point"}
}