{
  "type": "Feature",
  "properties": {
    "addr:full":"2211 Rose St Port Townsend WA 98368",
    "addr:housenumber":"2211",
    "addr:postcode":"98368",
    "addr:street":"Rose St",
    "iso:country":"US",
    "sg:address":"2211 Rose St",
    "sg:city":"Port Townsend",
    "sg:classifiers":[
        {
            "category":"Building & Trades",
            "subcategory":"Construction",
            "type":"Services"
        }
    ],
    "sg:phone":"+1 360 531 0730",
    "sg:postcode":"98368",
    "sg:province":"WA",
    "sg:tags":[
        "residential"
    ],
    "wof:name":"Josh Call",
    "wof:placetype":"venue"
},
  "geometry": {"coordinates":[-122.768047,48.132158],"type":"Point"}
}