{
  "type": "Feature",
  "properties": {
    "iso:country":"US",
    "sg:address":"1516 S Bennett St",
    "sg:city":"Seattle",
    "sg:classifiers":[
        {
            "category":"Building & Trades",
            "subcategory":"Landscaping Services",
            "type":"Services"
        }
    ],
    "sg:phone":"+1 206 335 6215",
    "sg:postcode":"98108",
    "sg:province":"WA",
    "wof:name":"Vos Garden",
    "wof:placetype":"venue"
},
  "geometry": {"coordinates":[-122.312489,47.554826],"type":"Point"}
}