{
  "type": "Feature",
  "properties": {
    "addr:full":"23132 E Echo Lake Rd Snohomish WA 98296",
    "addr:housenumber":"23132",
    "addr:postcode":"98296",
    "addr:street":"E Echo Lake Rd",
    "iso:country":"US",
    "sg:address":"23132 E Echo Lake Rd",
    "sg:city":"Snohomish",
    "sg:classifiers":[
        {
            "category":"Wholesale",
            "subcategory":"Hardware",
            "type":"Manufacturing & Wholesale Goods"
        },
        {
            "category":"Building & Trades",
            "subcategory":"Plumbing",
            "type":"Services"
        }
    ],
    "sg:phone":"+1 206 624 1171",
    "sg:postcode":"98296",
    "sg:province":"WA",
    "sg:tags":[
        "repair",
        "boiler",
        "cleaning"
    ],
    "wof:name":"Industrial Boiler Service",
    "wof:placetype":"venue"
},
  "geometry": {"coordinates":[-122.048314,47.786874],"type":"Point"}
}