{
  "type": "Feature",
  "properties": {
    "iso:country":"US",
    "sg:address":"322 N 97th St",
    "sg:city":"Seattle",
    "sg:classifiers":[
        {
            "category":"Professional",
            "subcategory":"Management & Consulting",
            "type":"Services"
        }
    ],
    "sg:phone":"+1 206 783 6010",
    "sg:postcode":"98103",
    "sg:province":"WA",
    "wof:name":"Rene T Murry",
    "wof:placetype":"venue"
},
  "geometry": {"coordinates":[-122.35406399999999,47.699719],"type":"Point"}
}