{
  "type": "Feature",
  "properties": {
    "addr:full":"617 Eastlake Ave E Seattle WA 98109",
    "addr:housenumber":"617",
    "addr:postcode":"98109",
    "addr:street":"Eastlake Ave E",
    "iso:country":"US",
    "sg:address":"617 Eastlake Ave E",
    "sg:city":"Seattle",
    "sg:classifiers":[
        {
            "category":"Utilities",
            "subcategory":"Mobile Phone",
            "type":"Services"
        }
    ],
    "sg:phone":"+1 206 624 5700",
    "sg:postcode":"98109",
    "sg:province":"WA",
    "sg:tags":[
        "telephone",
        "cellular"
    ],
    "wof:name":"A T & T Wireless",
    "wof:placetype":"venue"
},
  "geometry": {"coordinates":[-122.329224,47.624843],"type":"Point"}
}