{
  "type": "Feature",
  "properties": {
    "iso:country":"US",
    "sg:address":"3205 Vernhardson St",
    "sg:city":"Gig Harbor",
    "sg:classifiers":[
        {
            "category":"Organizations",
            "subcategory":"Religious Organization",
            "type":"Services"
        }
    ],
    "sg:phone":"+1 253 884 5162",
    "sg:postcode":"98332",
    "sg:province":"WA",
    "sg:tags":[
        "church"
    ],
    "wof:name":"Peninsula Apostolic Church",
    "wof:placetype":"venue"
},
  "geometry": {"coordinates":[-122.58128499999999,47.345329],"type":"Point"}
}