{
  "type": "Feature",
  "properties": {
    "addr:full":"10603 1st Ave S Seattle WA 98168",
    "addr:housenumber":"10603",
    "addr:postcode":"98168",
    "addr:street":"1St Ave S",
    "iso:country":"US",
    "sg:address":"10603 1st Ave S",
    "sg:city":"Seattle",
    "sg:classifiers":[
        {
            "category":"Retail",
            "subcategory":"Repair Shop",
            "type":"Services"
        }
    ],
    "sg:phone":"+1 206 268 0551",
    "sg:postcode":"98168",
    "sg:province":"WA",
    "wof:name":"Jans Tool Repair",
    "wof:placetype":"venue"
},
  "geometry": {"coordinates":[-122.33370600000001,47.507627],"type":"Point"}
}