{
  "type": "Feature",
  "properties": {
    "addr:full":"30244 SE High Point Way Issaquah WA 98027",
    "addr:postcode":"30244;98027",
    "addr:street":"Se High Point Way",
    "iso:country":"US",
    "sg:address":"30244 SE High Point Way",
    "sg:city":"Issaquah",
    "sg:classifiers":[
        {
            "category":"Manufacturing",
            "subcategory":"Metals",
            "type":"Manufacturing & Wholesale Goods"
        }
    ],
    "sg:phone":"+1 425 222 6330",
    "sg:postcode":"98027",
    "sg:province":"WA",
    "sg:tags":[
        "steel",
        "structural"
    ],
    "wof:name":"Redmond Welders & Fabricators",
    "wof:placetype":"venue"
},
  "geometry": {"coordinates":[-121.938678,47.527801],"type":"Point"}
}