{
  "type": "Feature",
  "properties": {
    "addr:full":"30 E Sprague Ave Spokane WA 99202",
    "addr:housenumber":"30",
    "addr:postcode":"99202",
    "addr:street":"E Sprague Ave",
    "iso:country":"US",
    "sg:address":"30 E Sprague Ave",
    "sg:city":"Spokane",
    "sg:classifiers":[
        {
            "category":"Professional",
            "subcategory":"Advertising",
            "type":"Services"
        }
    ],
    "sg:phone":"+1 509 838 4080",
    "sg:postcode":"99202",
    "sg:province":"WA",
    "sg:tags":[
        "counselor"
    ],
    "wof:name":"Clark Co",
    "wof:placetype":"venue"
},
  "geometry": {"coordinates":[-117.410737,47.657187],"type":"Point"}
}