{
  "type": "Feature",
  "properties": {
    "addr:full":"415 SW 153rd St Seattle WA 98166",
    "addr:housenumber":"415",
    "addr:postcode":"98166",
    "addr:street":"Sw 153Rd St",
    "iso:country":"US",
    "sg:address":"415 SW 153rd St",
    "sg:city":"Seattle",
    "sg:classifiers":[
        {
            "category":"Utilities",
            "subcategory":"Water",
            "type":"Services"
        }
    ],
    "sg:phone":"+1 206 242 8535",
    "sg:postcode":"98166",
    "sg:province":"WA",
    "sg:tags":[
        "executive",
        "supply"
    ],
    "wof:name":"King County Water District 49",
    "wof:placetype":"venue"
},
  "geometry": {"coordinates":[-122.341722,47.465843],"type":"Point"}
}