{
  "type": "Feature",
  "properties": {
    "addr:full":"124 W Spruce St Sequim WA 98382",
    "addr:housenumber":"124",
    "addr:postcode":"98382",
    "addr:street":"W Spruce St",
    "iso:country":"US",
    "sg:address":"124 W Spruce St",
    "sg:city":"Sequim",
    "sg:classifiers":[
        {
            "category":"Health Services",
            "subcategory":"Medical Lab",
            "type":"Services"
        }
    ],
    "sg:phone":"+1 360 681 7089",
    "sg:postcode":"98382",
    "sg:province":"WA",
    "sg:tags":[
        "laboratory",
        "dental"
    ],
    "wof:name":"Gillispie Michael Dpd",
    "wof:placetype":"venue"
},
  "geometry": {"coordinates":[-123.104378,48.08156],"type":"Point"}
}