{
  "type": "Feature",
  "properties": {
    "addr:full":"3308 E 17th St Vancouver WA 98661",
    "addr:housenumber":"3308",
    "addr:postcode":"98661",
    "addr:street":"E 17Th St",
    "iso:country":"US",
    "sg:address":"3308 E 17th St",
    "sg:city":"Vancouver",
    "sg:classifiers":[
        {
            "category":"Building & Trades",
            "subcategory":"Construction",
            "type":"Services"
        }
    ],
    "sg:phone":"+1 360 258 6485",
    "sg:postcode":"98661",
    "sg:province":"WA",
    "sg:tags":[
        "house"
    ],
    "wof:name":"Holloways Contracting",
    "wof:placetype":"venue"
},
  "geometry": {"coordinates":[-122.635138,45.63389],"type":"Point"}
}