{
  "type": "Feature",
  "properties": {
    "addr:full":"15500 SE 30th Pl Bellevue WA 98007",
    "addr:postcode":"15500;98007",
    "addr:street":"Se 30Th Pl",
    "iso:country":"US",
    "sg:address":"15500 SE 30th Pl",
    "sg:city":"Bellevue",
    "sg:classifiers":[
        {
            "category":"Insurance",
            "subcategory":"Insurance Agent",
            "type":"Services"
        }
    ],
    "sg:phone":"+1 425 644 4440",
    "sg:postcode":"98007",
    "sg:province":"WA",
    "wof:name":"Farmers Insurance Group",
    "wof:placetype":"venue"
},
  "geometry": {"coordinates":[-122.134573,47.582384],"type":"Point"}
}