{
  "type": "Feature",
  "properties": {
    "addr:full":"5891 Mullen Rd SE Lacey WA 98503",
    "addr:housenumber":"5891",
    "addr:postcode":"98503",
    "addr:street":"Mullen Rd Se",
    "iso:country":"US",
    "sg:address":"5891 Mullen Rd SE",
    "sg:city":"Lacey",
    "sg:classifiers":[
        {
            "category":"Wholesale",
            "subcategory":"Non-durable Goods",
            "type":"Manufacturing & Wholesale Goods"
        }
    ],
    "sg:phone":"+1 360 493 1331",
    "sg:postcode":"98503",
    "sg:province":"WA",
    "wof:name":"Karens Statuary",
    "wof:placetype":"venue"
},
  "geometry": {"coordinates":[-122.800522,47.006245],"type":"Point"}
}