{
  "type": "Feature",
  "properties": {
    "addr:full":"818 W Riverside Ave # 320 Spokane WA 99201",
    "addr:housenumber":"818",
    "addr:postcode":"99201",
    "addr:street":"W Riverside Ave # 320",
    "iso:country":"US",
    "sg:address":"818 W Riverside Ave # 320",
    "sg:city":"Spokane",
    "sg:classifiers":[
        {
            "category":"Professional",
            "subcategory":"Employment Agencies",
            "type":"Services"
        }
    ],
    "sg:phone":"+1 509 325 7650",
    "sg:postcode":"99201",
    "sg:province":"WA",
    "wof:name":"Bernard Haldane Associates",
    "wof:placetype":"venue"
},
  "geometry": {"coordinates":[-117.4238,47.657938],"type":"Point"}
}