{
  "type": "Feature",
  "properties": {
    "addr:full":"7405 20th Ave SE Lacey WA 98503",
    "addr:housenumber":"7405",
    "addr:postcode":"98503",
    "addr:street":"20Th Ave Se",
    "iso:country":"US",
    "sg:address":"7405 20th Ave SE",
    "sg:city":"Lacey",
    "sg:classifiers":[
        {
            "category":"Professional",
            "subcategory":"Business Services",
            "type":"Services"
        }
    ],
    "sg:phone":"+1 360 438 0103",
    "sg:postcode":"98503",
    "sg:province":"WA",
    "sg:tags":[
        "consultant",
        "coach"
    ],
    "wof:name":"Reflection Pt Comm",
    "wof:placetype":"venue"
},
  "geometry": {"coordinates":[-122.78178200000001,47.027565],"type":"Point"}
}