{
  "type": "Feature",
  "properties": {
    "addr:full":"645 Keys Rd Yakima WA 98901",
    "addr:housenumber":"645",
    "addr:postcode":"98901",
    "addr:street":"Keys Rd",
    "iso:country":"US",
    "sg:address":"645 Keys Rd",
    "sg:city":"Yakima",
    "sg:classifiers":[
        {
            "category":"Airline",
            "type":"Transportation"
        }
    ],
    "sg:phone":"+1 509 453 3137",
    "sg:postcode":"98901",
    "sg:province":"WA",
    "sg:tags":[
        "cargo",
        "air"
    ],
    "wof:name":"Diamond Freight Systems Inc",
    "wof:placetype":"venue"
},
  "geometry": {"coordinates":[-120.464364,46.596037],"type":"Point"}
}