{
  "type": "Feature",
  "properties": {
    "addr:full":"6801 28th Ave NE Seattle WA 98115",
    "addr:housenumber":"6801",
    "addr:postcode":"98115",
    "addr:street":"28Th Ave Ne",
    "iso:country":"US",
    "sg:address":"6801 28th Ave NE",
    "sg:city":"Seattle",
    "sg:classifiers":[
        {
            "category":"Health Services",
            "subcategory":"Doctor",
            "type":"Services"
        }
    ],
    "sg:phone":"+1 206 323 7462",
    "sg:postcode":"98115",
    "sg:province":"WA",
    "wof:name":"Lawrence Anne MD",
    "wof:placetype":"venue"
},
  "geometry": {"coordinates":[-122.297708,47.677711],"type":"Point"}
}