{
  "type": "Feature",
  "properties": {
    "addr:full":"1833 Harvard Ave Seattle WA 98102",
    "addr:housenumber":"1833",
    "addr:postcode":"98102",
    "addr:street":"Harvard Ave",
    "iso:country":"US",
    "sg:address":"1833 Harvard Ave",
    "sg:city":"Seattle",
    "sg:classifiers":[
        {
            "category":"Shopping",
            "subcategory":"Books",
            "type":"Retail Goods"
        }
    ],
    "sg:phone":"+1 206 324 2421",
    "sg:postcode":"98102",
    "sg:province":"WA",
    "sg:tags":[
        "bookstore"
    ],
    "wof:name":"Twice Sold Tales",
    "wof:placetype":"venue"
},
  "geometry": {"coordinates":[-122.32219000000001,47.617964],"type":"Point"}
}