{
  "type": "Feature",
  "properties": {
    "addr:full":"222 Wall St #100 Seattle WA 98121",
    "addr:housenumber":"222",
    "addr:postcode":"98121",
    "addr:street":"Wall St # 100",
    "iso:country":"US",
    "sg:address":"222 Wall St #100",
    "sg:city":"Seattle",
    "sg:classifiers":[
        {
            "category":"Real Estate",
            "subcategory":"Real Estate Agent",
            "type":"Services"
        }
    ],
    "sg:phone":"+1 206 441 1850",
    "sg:postcode":"98121",
    "sg:province":"WA",
    "sg:website":"www.goseattlerealty.com",
    "wof:name":"Seattle Waterfront Real Estate Re/Max",
    "wof:placetype":"venue"
},
  "geometry": {"coordinates":[-122.347728,47.615572],"type":"Point"}
}