{
  "type": "Feature",
  "properties": {
    "addr:full":"172 Maple Crest Dr Onalaska WA 98570",
    "addr:housenumber":"172",
    "addr:postcode":"98570",
    "addr:street":"Maple Crest Dr",
    "iso:country":"US",
    "sg:address":"172 Maple Crest Dr",
    "sg:city":"Onalaska",
    "sg:classifiers":[
        {
            "category":"Manufacturing",
            "subcategory":"Lumber",
            "type":"Manufacturing & Wholesale Goods"
        }
    ],
    "sg:phone":"+1 360 985 0614",
    "sg:postcode":"98570",
    "sg:province":"WA",
    "sg:tags":[
        "thinning",
        "commercial"
    ],
    "wof:name":"Garrobos Reforestation Etc",
    "wof:placetype":"venue"
},
  "geometry": {"coordinates":[-122.607196,46.578807],"type":"Point"}
}