{
  "type": "Feature",
  "properties": {
    "addr:full":"13027 Bothell Everett Hwy Everett WA 98208",
    "addr:housenumber":"13027",
    "addr:postcode":"98208",
    "addr:street":"Bothell Everett Hwy",
    "iso:country":"US",
    "sg:address":"13027 Bothell Everett Hwy",
    "sg:city":"Everett",
    "sg:classifiers":[
        {
            "category":"Banks & Credit Unions",
            "subcategory":"Investment Brokerage",
            "type":"Services"
        }
    ],
    "sg:phone":"+1 425 379 9313",
    "sg:postcode":"98208",
    "sg:province":"WA",
    "sg:tags":[
        "stock",
        "bond"
    ],
    "wof:name":"Edward Jones Co",
    "wof:placetype":"venue"
},
  "geometry": {"coordinates":[-122.206919,47.878445],"type":"Point"}
}