{
  "type": "Feature",
  "properties": {
    "addr:full":"51927 217th Pl SE Index WA 98256",
    "addr:housenumber":"51927",
    "addr:postcode":"98256",
    "addr:street":"217Th Pl Se",
    "iso:country":"US",
    "sg:address":"51927 217th Pl SE",
    "sg:city":"Index",
    "sg:classifiers":[
        {
            "category":"Professional",
            "subcategory":"Management & Consulting",
            "type":"Services"
        }
    ],
    "sg:phone":"+1 360 793 1031",
    "sg:postcode":"98256",
    "sg:province":"WA",
    "sg:tags":[
        "consultant",
        "medical"
    ],
    "wof:name":"Swissray International",
    "wof:placetype":"venue"
},
  "geometry": {"coordinates":[-121.53555299999999,47.801836],"type":"Point"}
}