{
  "type": "Feature",
  "properties": {
    "addr:full":"15510 NE 90th St Redmond WA 98052",
    "addr:housenumber":"15510",
    "addr:postcode":"98052",
    "addr:street":"Ne 90Th St",
    "iso:country":"US",
    "sg:address":"15510 NE 90th St",
    "sg:city":"Redmond",
    "sg:classifiers":[
        {
            "category":"Manufacturing",
            "subcategory":"Printing",
            "type":"Manufacturing & Wholesale Goods"
        }
    ],
    "sg:phone":"+1 425 883 4558",
    "sg:postcode":"98052",
    "sg:province":"WA",
    "sg:tags":[
        "commercial",
        "lithographic"
    ],
    "wof:name":"The Press",
    "wof:placetype":"venue"
},
  "geometry": {"coordinates":[-122.133724,47.682277],"type":"Point"}
}