{
  "type": "Feature",
  "properties": {
    "addr:full":"3863 34th Ave SW Seattle WA 98126",
    "addr:housenumber":"3863",
    "addr:postcode":"98126",
    "addr:street":"34Th Ave Sw",
    "iso:country":"US",
    "sg:address":"3863 34th Ave SW",
    "sg:city":"Seattle",
    "sg:classifiers":[
        {
            "category":"Wholesale",
            "subcategory":"Apparel",
            "type":"Manufacturing & Wholesale Goods"
        }
    ],
    "sg:phone":"+1 206 935 2079",
    "sg:postcode":"98126",
    "sg:province":"WA",
    "sg:tags":[
        "piece"
    ],
    "wof:name":"Sin In Linen",
    "wof:placetype":"venue"
},
  "geometry": {"coordinates":[-122.37514899999999,47.568576],"type":"Point"}
}