{
  "type": "Feature",
  "properties": {
    "addr:full":"410 213th Pl SE Sammamish WA 98074",
    "addr:housenumber":"410",
    "addr:postcode":"98074",
    "addr:street":"213Th Pl Se",
    "iso:country":"US",
    "sg:address":"410 213th Pl SE",
    "sg:city":"Sammamish",
    "sg:classifiers":[
        {
            "category":"Building & Trades",
            "subcategory":"Equipment Rental",
            "type":"Services"
        }
    ],
    "sg:phone":"+1 425 392 4873",
    "sg:postcode":"98074",
    "sg:province":"WA",
    "sg:tags":[
        "leasing"
    ],
    "wof:name":"Laurent Rentals Ted",
    "wof:placetype":"venue"
},
  "geometry": {"coordinates":[-122.055277,47.604274],"type":"Point"}
}