{
  "type": "Feature",
  "properties": {
    "addr:full":"2425 E Union St Seattle WA 98122",
    "addr:housenumber":"2425",
    "addr:postcode":"98122",
    "addr:street":"E Union St",
    "iso:country":"US",
    "sg:address":"2425 E Union St",
    "sg:city":"Seattle",
    "sg:classifiers":[
        {
            "category":"Coffee & Tea",
            "type":"Food & Drink"
        }
    ],
    "sg:phone":"+1 206 327 9728",
    "sg:postcode":"98122",
    "sg:province":"WA",
    "sg:website":"www.cortonacafe.com",
    "wof:name":"Cortona Cafe",
    "wof:placetype":"venue"
},
  "geometry": {"coordinates":[-122.300282,47.612757],"type":"Point"}
}