{
  "type": "Feature",
  "properties": {
    "addr:full":"1032 S Jackson St Ste 200 Seattle WA 98104",
    "addr:housenumber":"1032",
    "addr:postcode":"98104",
    "addr:street":"S Jackson St Ste 200",
    "iso:country":"US",
    "sg:address":"1032 S Jackson St Ste 200",
    "sg:city":"Seattle",
    "sg:classifiers":[
        {
            "category":"Health Services",
            "subcategory":"Chiropractor",
            "type":"Services"
        }
    ],
    "sg:phone":"+1 206 709 4006",
    "sg:postcode":"98104",
    "sg:province":"WA",
    "wof:name":"Evergreen Chiropractic Clinic",
    "wof:placetype":"venue"
},
  "geometry": {"coordinates":[-122.319226,47.59934],"type":"Point"}
}