{
  "type": "Feature",
  "properties": {
    "iso:country":"US",
    "sg:address":"110 Manteca Dr",
    "sg:city":"Kelso",
    "sg:classifiers":[
        {
            "category":"Social Services",
            "subcategory":"Child Care",
            "type":"Services"
        }
    ],
    "sg:phone":"+1 360 577 4315",
    "sg:postcode":"98626",
    "sg:province":"WA",
    "sg:tags":[
        "day"
    ],
    "wof:name":"Play 2 Learn Daycare",
    "wof:placetype":"venue"
},
  "geometry": {"coordinates":[-122.911331,46.183477],"type":"Point"}
}