{
  "type": "Feature",
  "properties": {
    "addr:full":"2106 NE 88th St Vancouver WA 98665",
    "addr:housenumber":"2106",
    "addr:postcode":"98665",
    "addr:street":"Ne 88Th St",
    "iso:country":"US",
    "sg:address":"2106 NE 88th St",
    "sg:city":"Vancouver",
    "sg:classifiers":[
        {
            "category":"Professional",
            "subcategory":"Business Services",
            "type":"Services"
        }
    ],
    "sg:phone":"+1 360 574 8984",
    "sg:postcode":"98665",
    "sg:province":"WA",
    "sg:tags":[
        "consulting",
        "management"
    ],
    "wof:name":"Management & Personel Service",
    "wof:placetype":"venue"
},
  "geometry": {"coordinates":[-122.64758399999999,45.686042],"type":"Point"}
}