{
  "type": "Feature",
  "properties": {
    "addr:full":"15395 SE 30th Place Suite 140 Bellvue WA 98007",
    "addr:housenumber":"15395",
    "addr:postcode":"98007",
    "addr:street":"Se 30Th Place Suite 140",
    "iso:country":"US",
    "sg:address":"15395 SE 30th Place Suite 140",
    "sg:city":"Bellvue",
    "sg:classifiers":[
        {
            "category":"Professional",
            "subcategory":"Computer Services",
            "type":"Services"
        }
    ],
    "sg:phone":"+1 425 378 7887",
    "sg:postcode":"98007",
    "sg:province":"WA",
    "wof:name":"Centeris Corporation",
    "wof:placetype":"venue"
},
  "geometry": {"coordinates":[-122.13505499999999,47.582365],"type":"Point"}
}