{
  "type": "Feature",
  "properties": {
    "addr:full":"607 4th St Garfield WA 99130",
    "addr:housenumber":"607",
    "addr:postcode":"99130",
    "addr:street":"4Th St",
    "iso:country":"US",
    "sg:address":"607 4th St",
    "sg:city":"Garfield",
    "sg:classifiers":[
        {
            "category":"Manufacturing",
            "subcategory":"Printing",
            "type":"Manufacturing & Wholesale Goods"
        }
    ],
    "sg:phone":"+1 509 635 1183",
    "sg:postcode":"99130",
    "sg:province":"WA",
    "sg:tags":[
        "publisher"
    ],
    "wof:name":"Publishing EB",
    "wof:placetype":"venue"
},
  "geometry": {"coordinates":[-117.14232,47.0028],"type":"Point"}
}