{
  "type": "Feature",
  "properties": {
    "addr:full":"415 SW 15th St Olympia WA 98532",
    "addr:housenumber":"415",
    "addr:postcode":"98532",
    "addr:street":"Sw 15Th St",
    "iso:country":"US",
    "sg:address":"415 SW 15th St",
    "sg:city":"Olympia",
    "sg:classifiers":[
        {
            "category":"Restaurant",
            "type":"Food & Drink"
        }
    ],
    "sg:phone":"+1 360 534 9464",
    "sg:postcode":"98532",
    "sg:province":"WA",
    "wof:name":"Liberty Cafe",
    "wof:placetype":"venue"
},
  "geometry": {"coordinates":[-122.952442,46.649589],"type":"Point"}
}