{
  "type": "Feature",
  "properties": {
    "addr:full":"421 N 68th Ave Yakima WA 98908",
    "addr:housenumber":"421",
    "addr:postcode":"98908",
    "addr:street":"N 68Th Ave",
    "iso:country":"US",
    "sg:address":"421 N 68th Ave",
    "sg:city":"Yakima",
    "sg:classifiers":[
        {
            "category":"Wholesale",
            "subcategory":"Groceries",
            "type":"Manufacturing & Wholesale Goods"
        }
    ],
    "sg:phone":"+1 509 930 6945",
    "sg:postcode":"98908",
    "sg:province":"WA",
    "wof:name":"Daves Cooking Planks",
    "wof:placetype":"venue"
},
  "geometry": {"coordinates":[-120.59978099999999,46.605202],"type":"Point"}
}