{
  "type": "Feature",
  "properties": {
    "addr:full":"20015 Hwy 99 Lynnwood WA 98036",
    "addr:housenumber":"20015",
    "addr:postcode":"98036",
    "addr:street":"Hwy 99",
    "iso:country":"US",
    "sg:address":"20015 Hwy 99",
    "sg:city":"Lynnwood",
    "sg:classifiers":[
        {
            "category":"Personal",
            "subcategory":"Beauty Salon",
            "type":"Services"
        }
    ],
    "sg:phone":"+1 425 771 1372",
    "sg:postcode":"98036",
    "sg:province":"WA",
    "sg:tags":[
        "shop",
        "manicuring"
    ],
    "wof:name":"A Amazing Nails",
    "wof:placetype":"venue"
},
  "geometry": {"coordinates":[-122.31942100000001,47.816228],"type":"Point"}
}