{
  "type": "Feature",
  "properties": {
    "addr:full":"10509 E Dean Ave Spokane Valley WA 99206",
    "addr:housenumber":"10509",
    "addr:postcode":"99206",
    "addr:street":"E Dean Ave",
    "iso:country":"US",
    "sg:address":"10509 E Dean Ave",
    "sg:city":"Spokane Valley",
    "sg:classifiers":[
        {
            "category":"Manufacturing",
            "subcategory":"Musical Instruments",
            "type":"Manufacturing & Wholesale Goods"
        },
        {
            "category":"Shopping",
            "subcategory":"Musical Instruments",
            "type":"Retail Goods"
        }
    ],
    "sg:phone":"+1 509 927 2208",
    "sg:postcode":"99206",
    "sg:province":"WA",
    "sg:tags":[
        "mfg"
    ],
    "wof:name":"Canecrafters Oboe Reed Co",
    "wof:placetype":"venue"
},
  "geometry": {"coordinates":[-117.26291000000001,47.665795],"type":"Point"}
}