{
  "type": "Feature",
  "properties": {
    "addr:full":"1402 156th Ave NE Bellevue WA 98007",
    "addr:housenumber":"1402",
    "addr:postcode":"98007",
    "addr:street":"156Th Ave Ne",
    "iso:country":"US",
    "sg:address":"1402 156th Ave NE",
    "sg:city":"Bellevue",
    "sg:classifiers":[
        {
            "category":"Restaurant",
            "type":"Food & Drink"
        }
    ],
    "sg:phone":"+1 425 747 5731",
    "sg:postcode":"98007",
    "sg:province":"WA",
    "sg:tags":[
        "eating"
    ],
    "wof:name":"Pizza Hut",
    "wof:placetype":"venue"
},
  "geometry": {"coordinates":[-122.13233099999999,47.622377],"type":"Point"}
}