{
  "type": "Feature",
  "properties": {
    "addr:full":"4214 Pear Point Rd Friday Harbor WA 98250",
    "addr:housenumber":"4214",
    "addr:postcode":"98250",
    "addr:street":"Pear Point Rd",
    "iso:country":"US",
    "sg:address":"4214 Pear Point Rd",
    "sg:city":"Friday Harbor",
    "sg:classifiers":[
        {
            "category":"Travel",
            "subcategory":"Hotels & Motels",
            "type":"Entertainment"
        }
    ],
    "sg:phone":"+1 360 378 5604",
    "sg:postcode":"98250",
    "sg:province":"WA",
    "sg:tags":[
        "breakfast",
        "accommodation",
        "bed"
    ],
    "sg:website":"www.duffyhouse.net",
    "wof:name":"Duffy House",
    "wof:placetype":"venue"
},
  "geometry": {"coordinates":[-123.003077,48.520523],"type":"Point"}
}