{
  "type": "Feature",
  "properties": {
    "addr:full":"22141 SE 237th St Maple Valley WA 98038",
    "addr:postcode":"22141;98038",
    "addr:street":"Se 237Th St",
    "iso:country":"US",
    "sg:address":"22141 SE 237th St",
    "sg:city":"Maple Valley",
    "sg:classifiers":[
        {
            "category":"Restaurant",
            "type":"Food & Drink"
        }
    ],
    "sg:menulink":"http://www.allmenus.com/wa/tahoma-maple-valley/144870-subway/menu/",
    "sg:phone":"+1 425 413 2558",
    "sg:postcode":"98038",
    "sg:province":"WA",
    "sg:tags":[
        "american",
        "sandwich"
    ],
    "wof:name":"Subway",
    "wof:placetype":"venue"
},
  "geometry": {"coordinates":[-122.046172,47.389153],"type":"Point"}
}