{
  "type": "Feature",
  "properties": {
    "addr:full":"502 NW 14th St Battle Ground WA 98604",
    "addr:housenumber":"502",
    "addr:postcode":"98604",
    "addr:street":"Nw 14Th St",
    "iso:country":"US",
    "sg:address":"502 NW 14th St",
    "sg:city":"Battle Ground",
    "sg:classifiers":[
        {
            "category":"Retail",
            "subcategory":"Self-service Laundry",
            "type":"Services"
        }
    ],
    "sg:phone":"+1 360 666 1379",
    "sg:postcode":"98604",
    "sg:province":"WA",
    "sg:tags":[
        "coin"
    ],
    "wof:name":"Mist & Ivy Soaps",
    "wof:placetype":"venue"
},
  "geometry": {"coordinates":[-122.543796,45.791322],"type":"Point"}
}