{
  "type": "Feature",
  "properties": {
    "addr:full":"12315 N Perry St Spokane WA 99218",
    "addr:housenumber":"12315",
    "addr:postcode":"99218",
    "addr:street":"N Perry St",
    "iso:country":"US",
    "sg:address":"12315 N Perry St",
    "sg:city":"Spokane",
    "sg:classifiers":[
        {
            "category":"Manufacturing",
            "subcategory":"Retail Goods",
            "type":"Manufacturing & Wholesale Goods"
        }
    ],
    "sg:phone":"+1 509 290 1004",
    "sg:postcode":"99218",
    "sg:province":"WA",
    "sg:tags":[
        "product",
        "mfg"
    ],
    "wof:name":"Jillybeads",
    "wof:placetype":"venue"
},
  "geometry": {"coordinates":[-117.389242,47.769586],"type":"Point"}
}