{
  "type": "Feature",
  "properties": {
    "addr:full":"13116 127th Avenue Ct E Puyallup WA 98374",
    "addr:housenumber":"13116",
    "addr:postcode":"98374",
    "addr:street":"127Th Avenue Ct E",
    "iso:country":"US",
    "sg:address":"13116 127th Avenue Ct E",
    "sg:city":"Puyallup",
    "sg:classifiers":[
        {
            "category":"Building & Trades",
            "subcategory":"Landscaping Services",
            "type":"Services"
        }
    ],
    "sg:phone":"+1 253 848 4709",
    "sg:postcode":"98374",
    "sg:province":"WA",
    "sg:tags":[
        "landscape",
        "contractor"
    ],
    "wof:name":"Double D Enterprises",
    "wof:placetype":"venue"
},
  "geometry": {"coordinates":[-122.25842299999999,47.137521],"type":"Point"}
}