{
  "type": "Feature",
  "properties": {
    "addr:full":"20664 84th Ave S Kent WA 98032",
    "addr:housenumber":"20664",
    "addr:postcode":"98032",
    "addr:street":"84Th Ave S",
    "iso:country":"US",
    "sg:address":"20664 84th Ave S",
    "sg:city":"Kent",
    "sg:classifiers":[
        {
            "category":"Wholesale",
            "subcategory":"Stationery",
            "type":"Manufacturing & Wholesale Goods"
        }
    ],
    "sg:phone":"+1 425 291 9800",
    "sg:postcode":"98032",
    "sg:province":"WA",
    "sg:tags":[
        "paper"
    ],
    "wof:name":"White Paper Company",
    "wof:placetype":"venue"
},
  "geometry": {"coordinates":[-122.22787099999999,47.415777],"type":"Point"}
}