{
  "type": "Feature",
  "properties": {
    "addr:full":"2200 E Melrose St Walla Walla WA 99362",
    "addr:housenumber":"2200",
    "addr:postcode":"99362",
    "addr:street":"E Melrose St",
    "iso:country":"US",
    "sg:address":"2200 E Melrose St",
    "sg:city":"Walla Walla",
    "sg:classifiers":[
        {
            "category":"Insurance",
            "subcategory":"Insurance Agent",
            "type":"Services"
        }
    ],
    "sg:phone":"+1 509 525 4074",
    "sg:postcode":"99362",
    "sg:province":"WA",
    "wof:name":"Jim Lewis",
    "wof:placetype":"venue"
},
  "geometry": {"coordinates":[-118.30458900000001,46.078575],"type":"Point"}
}