{
  "type": "Feature",
  "properties": {
    "addr:full":"512 W Yelm Ave Yelm WA 98597",
    "addr:housenumber":"512",
    "addr:postcode":"98597",
    "addr:street":"W Yelm Ave",
    "iso:country":"US",
    "sg:address":"512 W Yelm Ave",
    "sg:city":"Yelm",
    "sg:classifiers":[
        {
            "category":"Insurance",
            "subcategory":"Insurance Agent",
            "type":"Services"
        }
    ],
    "sg:phone":"+1 360 458 4559",
    "sg:postcode":"98597",
    "sg:province":"WA",
    "wof:name":"Damitio Insurance Inc",
    "wof:placetype":"venue"
},
  "geometry": {"coordinates":[-122.612926,46.945517],"type":"Point"}
}