{
  "type": "Feature",
  "properties": {
    "addr:full":"1401 S Laventure Rd Mount Vernon WA 98274",
    "addr:housenumber":"1401",
    "addr:postcode":"98274",
    "addr:street":"S Laventure Rd",
    "iso:country":"US",
    "sg:address":"1401 S Laventure Rd",
    "sg:city":"Mount Vernon",
    "sg:classifiers":[
        {
            "category":"Health Services",
            "subcategory":"Doctor",
            "type":"Services"
        }
    ],
    "sg:phone":"+1 360 336 0759",
    "sg:postcode":"98274",
    "sg:province":"WA",
    "sg:tags":[
        "medical"
    ],
    "wof:name":"Bradley W Daniel MD",
    "wof:placetype":"venue"
},
  "geometry": {"coordinates":[-122.313458,48.410053],"type":"Point"}
}