{
  "type": "Feature",
  "properties": {
    "addr:full":"510 M St SE Auburn WA 98002",
    "addr:housenumber":"510",
    "addr:postcode":"98002",
    "addr:street":"M St Se",
    "iso:country":"US",
    "sg:address":"510 M St SE",
    "sg:city":"Auburn",
    "sg:classifiers":[
        {
            "category":"Real Estate",
            "subcategory":"Real Estate Services",
            "type":"Services"
        },
        {
            "category":"Real Estate",
            "subcategory":"Real Estate Operator",
            "type":"Services"
        }
    ],
    "sg:phone":"+1 253 735 6394",
    "sg:postcode":"98002",
    "sg:province":"WA",
    "sg:tags":[
        "vacancy",
        "apartment",
        "rental",
        "finder",
        "listing"
    ],
    "wof:name":"The Park At Auburn",
    "wof:placetype":"venue"
},
  "geometry": {"coordinates":[-122.21338799999999,47.303212],"type":"Point"}
}