{
  "type": "Feature",
  "properties": {
    "addr:full":"27 Mill St Friday Harbor WA 98250",
    "addr:housenumber":"27",
    "addr:postcode":"98250",
    "addr:street":"Mill St",
    "iso:country":"US",
    "sg:address":"27 Mill St",
    "sg:city":"Friday Harbor",
    "sg:classifiers":[
        {
            "category":"Professional",
            "subcategory":"Business Services",
            "type":"Services"
        }
    ],
    "sg:phone":"+1 360 378 2524",
    "sg:postcode":"98250",
    "sg:province":"WA",
    "wof:name":"San Juan Baseball Booster",
    "wof:placetype":"venue"
},
  "geometry": {"coordinates":[-123.022958,48.515087],"type":"Point"}
}