{
  "type": "Feature",
  "properties": {
    "addr:full":"2311 S Francis St Port Angeles WA 98362",
    "addr:housenumber":"2311",
    "addr:postcode":"98362",
    "addr:street":"S Francis St",
    "iso:country":"US",
    "sg:address":"2311 S Francis St",
    "sg:city":"Port Angeles",
    "sg:classifiers":[
        {
            "category":"Social Services",
            "subcategory":"Child Care",
            "type":"Services"
        }
    ],
    "sg:phone":"+1 360 452 8496",
    "sg:postcode":"98362",
    "sg:province":"WA",
    "sg:tags":[
        "kindergarten",
        "academic",
        "school"
    ],
    "wof:name":"Mt Angeles View Head Start Ctr",
    "wof:placetype":"venue"
},
  "geometry": {"coordinates":[-123.429304,48.104957],"type":"Point"}
}