{
  "type": "Feature",
  "properties": {
    "addr:full":"20315 Mountain Hwy E Spanaway WA 98387",
    "addr:housenumber":"20315",
    "addr:postcode":"98387",
    "addr:street":"Mountain Hwy E",
    "iso:country":"US",
    "sg:address":"20315 Mountain Hwy E",
    "sg:city":"Spanaway",
    "sg:classifiers":[
        {
            "category":"Autos & Motor Vehicles",
            "subcategory":"Fuel & Gas Station",
            "type":"Retail Goods"
        }
    ],
    "sg:phone":"+1 253 875 1151",
    "sg:postcode":"98387",
    "sg:province":"WA",
    "sg:tags":[
        "station",
        "gasoline",
        "oil"
    ],
    "wof:name":"Mountain Highway Chevron",
    "wof:placetype":"venue"
},
  "geometry": {"coordinates":[-122.41969899999999,47.072665],"type":"Point"}
}