{
  "type": "Feature",
  "properties": {
    "addr:full":"11714 N Creek Pkwy N Bothell WA 98011",
    "addr:housenumber":"11714",
    "addr:postcode":"98011",
    "addr:street":"N Creek Pkwy N",
    "iso:country":"US",
    "sg:address":"11714 N Creek Pkwy N",
    "sg:city":"Bothell",
    "sg:classifiers":[
        {
            "category":"Professional",
            "subcategory":"Engineering",
            "type":"Services"
        }
    ],
    "sg:phone":"+1 425 415 6144",
    "sg:postcode":"98011",
    "sg:province":"WA",
    "sg:tags":[
        "engineer"
    ],
    "sg:website":"www.esmcivil.com",
    "wof:name":"ESM Consulting Engineers",
    "wof:placetype":"venue"
},
  "geometry": {"coordinates":[-122.18555000000001,47.774718],"type":"Point"}
}