{
  "type": "Feature",
  "properties": {
    "addr:full":"5229 36th Ave SW Seattle WA 98126",
    "addr:housenumber":"5229",
    "addr:postcode":"98126",
    "addr:street":"36Th Ave Sw",
    "iso:country":"US",
    "sg:address":"5229 36th Ave SW",
    "sg:city":"Seattle",
    "sg:classifiers":[
        {
            "category":"Communications",
            "subcategory":"Film & Video Production",
            "type":"Services"
        }
    ],
    "sg:phone":"+1 206 935 0575",
    "sg:postcode":"98126",
    "sg:province":"WA",
    "sg:tags":[
        "tv",
        "picture",
        "radio",
        "motion",
        "companies-film"
    ],
    "wof:name":"Room In A Room 3rd",
    "wof:placetype":"venue"
},
  "geometry": {"coordinates":[-122.377611,47.555091],"type":"Point"}
}