{
  "type": "Feature",
  "properties": {
    "addr:full":"1101 D St SE Auburn WA 98002",
    "addr:housenumber":"1101",
    "addr:postcode":"98002",
    "addr:street":"D St Se",
    "iso:country":"US",
    "sg:address":"1101 D St SE",
    "sg:city":"Auburn",
    "sg:classifiers":[
        {
            "category":"Education",
            "subcategory":"School",
            "type":"Public Place"
        }
    ],
    "sg:phone":"+1 253 931 4978",
    "sg:postcode":"98002",
    "sg:province":"WA",
    "sg:tags":[
        "elementary"
    ],
    "wof:name":"Terminal Park Elem School",
    "wof:placetype":"venue"
},
  "geometry": {"coordinates":[-122.224082,47.297242],"type":"Point"}
}