{
  "type": "Feature",
  "properties": {
    "iso:country":"US",
    "sg:address":"3322 171st Pl NW",
    "sg:city":"Stanwood",
    "sg:classifiers":[
        {
            "category":"Professional",
            "subcategory":"Management & Consulting",
            "type":"Services"
        }
    ],
    "sg:phone":"+1 360 652 4198",
    "sg:postcode":"98292",
    "sg:province":"WA",
    "sg:tags":[
        "planner",
        "site"
    ],
    "wof:name":"American Mobile Home Svc",
    "wof:placetype":"venue"
},
  "geometry": {"coordinates":[-122.27884400000001,48.151044],"type":"Point"}
}