{
  "type": "Feature",
  "properties": {
    "iso:country":"US",
    "sg:address":"1931 200th St NE",
    "sg:city":"Arlington",
    "sg:classifiers":[
        {
            "category":"Professional",
            "subcategory":"Management & Consulting",
            "type":"Services"
        }
    ],
    "sg:phone":"+1 360 652 0801",
    "sg:postcode":"98223",
    "sg:province":"WA",
    "wof:name":"Lone B Construction",
    "wof:placetype":"venue"
},
  "geometry": {"coordinates":[-122.201958,48.1779],"type":"Point"}
}