{
  "type": "Feature",
  "properties": {
    "addr:full":"18899 State Hwy 21 Danville WA 99121",
    "addr:housenumber":"18899",
    "addr:postcode":"99121",
    "addr:street":"State Hwy 21",
    "iso:country":"US",
    "sg:address":"18899 State Hwy 21",
    "sg:city":"Danville",
    "sg:classifiers":[
        {
            "category":"Retail",
            "subcategory":"Repair Shop",
            "type":"Services"
        }
    ],
    "sg:phone":"+1 509 779 4526",
    "sg:postcode":"99121",
    "sg:province":"WA",
    "sg:tags":[
        "auto"
    ],
    "wof:name":"Reds Radiator & Automotive",
    "wof:placetype":"venue"
},
  "geometry": {"coordinates":[-118.535844,48.962021],"type":"Point"}
}