{
  "type": "Feature",
  "properties": {
    "addr:full":"1000 Station Dr Ste 130 Dupont WA 98327",
    "addr:housenumber":"1000",
    "addr:postcode":"98327",
    "addr:street":"Station Dr Ste 130 Dupont",
    "iso:country":"US",
    "sg:address":"1000 Station Dr Ste 130",
    "sg:city":"Dupont",
    "sg:classifiers":[
        {
            "category":"Professional",
            "subcategory":"Computer Services",
            "type":"Services"
        }
    ],
    "sg:phone":"+1 425 369 8323",
    "sg:postcode":"98327",
    "sg:province":"WA",
    "sg:tags":[
        "consultant",
        "designer",
        "system"
    ],
    "sg:website":"http://www.abntec.com",
    "wof:name":"Abn Technologies",
    "wof:placetype":"venue"
},
  "geometry": {"coordinates":[-122.624382,47.094799],"type":"Point"}
}