{
  "type": "Feature",
  "properties": {
    "addr:full":"12401 NE 60th Way # A17 Vancouver WA 98682",
    "addr:housenumber":"12401",
    "addr:postcode":"98682",
    "addr:street":"Ne 60Th Way # A17",
    "iso:country":"US",
    "sg:address":"12401 NE 60th Way # A17",
    "sg:city":"Vancouver",
    "sg:classifiers":[
        {
            "category":"Building & Trades",
            "subcategory":"Construction",
            "type":"Services"
        },
        {
            "category":"Building & Trades",
            "subcategory":"Electrical",
            "type":"Services"
        }
    ],
    "sg:phone":"+1 360 944 8616",
    "sg:postcode":"98682",
    "sg:province":"WA",
    "sg:tags":[
        "industrial",
        "electric",
        "altering",
        "consultant",
        "specialty",
        "heating",
        "contractors-commercial",
        "contractor",
        "remodeling"
    ],
    "wof:name":"Home Energy Group Inc",
    "wof:placetype":"venue"
},
  "geometry": {"coordinates":[-122.546131,45.666458],"type":"Point"}
}