{
  "type": "Feature",
  "properties": {
    "addr:full":"10824 SE 170th St Renton WA 98055",
    "addr:housenumber":"10824",
    "addr:postcode":"98055",
    "addr:street":"Se 170Th St",
    "iso:country":"US",
    "sg:address":"10824 SE 170th St",
    "sg:city":"Renton",
    "sg:classifiers":[
        {
            "category":"Restaurant",
            "type":"Food & Drink"
        }
    ],
    "sg:phone":"+1 425 687 7662",
    "sg:postcode":"98055",
    "sg:province":"WA",
    "sg:tags":[
        "eating"
    ],
    "wof:name":"Cafe Lviv",
    "wof:placetype":"venue"
},
  "geometry": {"coordinates":[-122.195252,47.450626],"type":"Point"}
}