{
  "type": "Feature",
  "properties": {
    "addr:full":"1714 Jefferson St SE Olympia WA 98501",
    "addr:housenumber":"1714",
    "addr:postcode":"98501",
    "addr:street":"Jefferson St Se",
    "iso:country":"US",
    "sg:address":"1714 Jefferson St SE",
    "sg:city":"Olympia",
    "sg:classifiers":[
        {
            "category":"Recreation",
            "type":"Entertainment"
        }
    ],
    "sg:phone":"+1 360 352 1378",
    "sg:postcode":"98501",
    "sg:province":"WA",
    "wof:name":"Astrology Works",
    "wof:placetype":"venue"
},
  "geometry": {"coordinates":[-122.895787,47.032371],"type":"Point"}
}