{
  "type": "Feature",
  "properties": {
    "addr:full":"2715 15th St Everett WA 98201",
    "addr:housenumber":"2715",
    "addr:postcode":"98201",
    "addr:street":"15Th St",
    "iso:country":"US",
    "sg:address":"2715 15th St",
    "sg:city":"Everett",
    "sg:classifiers":[
        {
            "category":"Government",
            "subcategory":"Office",
            "type":"Public Place"
        }
    ],
    "sg:phone":"+1 425 303 1170",
    "sg:postcode":"98201",
    "sg:province":"WA",
    "sg:tags":[
        "housing",
        "authority"
    ],
    "wof:name":"Housing Authority of The City",
    "wof:placetype":"venue"
},
  "geometry": {"coordinates":[-122.193917,47.997654],"type":"Point"}
}