{
  "type": "Feature",
  "properties": {
    "addr:full":"25 Dean Ln Glenwood WA 98619",
    "addr:housenumber":"25",
    "addr:postcode":"98619",
    "addr:street":"Dean Ln",
    "iso:country":"US",
    "sg:address":"25 Dean Ln",
    "sg:city":"Glenwood",
    "sg:classifiers":[
        {
            "category":"Building & Trades",
            "subcategory":"Construction",
            "type":"Services"
        }
    ],
    "sg:phone":"+1 509 364 3691",
    "sg:postcode":"98619",
    "sg:province":"WA",
    "sg:tags":[
        "general",
        "contractor"
    ],
    "wof:name":"Elk Creek Contractors Inc",
    "wof:placetype":"venue"
},
  "geometry": {"coordinates":[-121.28679200000001,46.021431],"type":"Point"}
}