{
  "type": "Feature",
  "properties": {
    "addr:full":"13129 118th Ave SE Rainier WA 98576",
    "addr:housenumber":"13129",
    "addr:postcode":"98576",
    "addr:street":"118Th Ave Se",
    "iso:country":"US",
    "sg:address":"13129 118th Ave SE",
    "sg:city":"Rainier",
    "sg:classifiers":[
        {
            "category":"Manufacturing",
            "subcategory":"Glass & Minerals",
            "type":"Manufacturing & Wholesale Goods"
        }
    ],
    "sg:phone":"+1 360 446 2990",
    "sg:postcode":"98576",
    "sg:province":"WA",
    "sg:tags":[
        "fabricator",
        "fiber"
    ],
    "wof:name":"Precision Design Plastics",
    "wof:placetype":"venue"
},
  "geometry": {"coordinates":[-122.662808,46.916002],"type":"Point"}
}