{
  "type": "Feature",
  "properties": {
    "addr:full":"7929 Lake Ballinger Way Edmonds WA 98026",
    "addr:housenumber":"7929",
    "addr:postcode":"98026",
    "addr:street":"Lake Ballinger Way",
    "iso:country":"US",
    "sg:address":"7929 Lake Ballinger Way",
    "sg:city":"Edmonds",
    "sg:classifiers":[
        {
            "category":"Restaurant",
            "type":"Food & Drink"
        }
    ],
    "sg:phone":"+1 425 771 4666",
    "sg:postcode":"98026",
    "sg:province":"WA",
    "sg:tags":[
        "eating"
    ],
    "wof:name":"Cocos",
    "wof:placetype":"venue"
},
  "geometry": {"coordinates":[-122.340602,47.777859],"type":"Point"}
}