{
  "type": "Feature",
  "properties": {
    "addr:full":"7222 NE 129th Ave Vancouver WA 98682",
    "addr:housenumber":"7222",
    "addr:postcode":"98682",
    "addr:street":"Ne 129Th Ave",
    "iso:country":"US",
    "sg:address":"7222 NE 129th Ave",
    "sg:city":"Vancouver",
    "sg:classifiers":[
        {
            "category":"Wholesale",
            "subcategory":"Durable Goods & Equipment",
            "type":"Manufacturing & Wholesale Goods"
        }
    ],
    "sg:phone":"+1 360 892 0170",
    "sg:postcode":"98682",
    "sg:province":"WA",
    "wof:name":"Mere Reflections",
    "wof:placetype":"venue"
},
  "geometry": {"coordinates":[-122.540539,45.675631],"type":"Point"}
}