{
  "type": "Feature",
  "properties": {
    "addr:full":"17620 International Blvd Seattle WA 98188",
    "addr:housenumber":"17620",
    "addr:postcode":"98188",
    "addr:street":"International Blvd",
    "iso:country":"US",
    "sg:address":"17620 International Blvd",
    "sg:city":"Seattle",
    "sg:classifiers":[
        {
            "category":"Restaurant",
            "type":"Food & Drink"
        }
    ],
    "sg:menulink":"http://www.allmenus.com/wa/seattle/5094-spencers/menu/",
    "sg:phone":"+1 206 248 7153",
    "sg:postcode":"98188",
    "sg:province":"WA",
    "sg:tags":[
        "american",
        "steakhouse"
    ],
    "wof:name":"Spencer's",
    "wof:placetype":"venue"
},
  "geometry": {"coordinates":[-122.296172,47.445108],"type":"Point"}
}