{
  "type": "Feature",
  "properties": {
    "addr:full":"142 Young Rd Randle WA 98377",
    "addr:housenumber":"142",
    "addr:postcode":"98377",
    "addr:street":"Young Rd",
    "iso:country":"US",
    "sg:address":"142 Young Rd",
    "sg:city":"Randle",
    "sg:classifiers":[
        {
            "category":"Education",
            "subcategory":"Special Training",
            "type":"Public Place"
        }
    ],
    "sg:phone":"+1 360 497 5300",
    "sg:postcode":"98377",
    "sg:province":"WA",
    "sg:tags":[
        "instruction",
        "driving"
    ],
    "wof:name":"Drive Rite Driving School LLC",
    "wof:placetype":"venue"
},
  "geometry": {"coordinates":[-121.907843,46.537355],"type":"Point"}
}