{
  "type": "Feature",
  "properties": {
    "addr:full":"7513 Aurora Ave N Seattle WA 98103",
    "addr:housenumber":"7513",
    "addr:postcode":"98103",
    "addr:street":"Aurora Ave N",
    "iso:country":"US",
    "sg:address":"7513 Aurora Ave N",
    "sg:city":"Seattle",
    "sg:classifiers":[
        {
            "category":"Autos & Motor Vehicles",
            "subcategory":"Auto Supplies",
            "type":"Retail Goods"
        }
    ],
    "sg:phone":"+1 206 769 5931",
    "sg:postcode":"98103",
    "sg:province":"WA",
    "wof:name":"U Save Auto Wholesale",
    "wof:placetype":"venue"
},
  "geometry": {"coordinates":[-122.344565,47.683946],"type":"Point"}
}