{
  "type": "Feature",
  "properties": {
    "addr:full":"1620 S Mildred St Tacoma WA 98465",
    "addr:housenumber":"1620",
    "addr:postcode":"98465",
    "addr:street":"S Mildred St",
    "iso:country":"US",
    "sg:address":"1620 S Mildred St",
    "sg:city":"Tacoma",
    "sg:classifiers":[
        {
            "category":"Restaurant",
            "type":"Food & Drink"
        }
    ],
    "sg:menulink":"http://www.allmenus.com/wa/tacoma/46636-i-love-bento/menu/",
    "sg:phone":"+1 253 460 0675",
    "sg:postcode":"98465",
    "sg:province":"WA",
    "sg:tags":[
        "japanese",
        "asian"
    ],
    "wof:name":"I Love Bento",
    "wof:placetype":"venue"
},
  "geometry": {"coordinates":[-122.526326,47.245653],"type":"Point"}
}