{
  "type": "Feature",
  "properties": {
    "addr:full":"2107 SE 160th Pl Vancouver WA 98683",
    "addr:housenumber":"2107",
    "addr:postcode":"98683",
    "addr:street":"Se 160Th Pl",
    "iso:country":"US",
    "sg:address":"2107 SE 160th Pl",
    "sg:city":"Vancouver",
    "sg:classifiers":[
        {
            "category":"Banks & Credit Unions",
            "subcategory":"Investment Brokerage",
            "type":"Services"
        }
    ],
    "sg:phone":"+1 360 896 6756",
    "sg:postcode":"98683",
    "sg:province":"WA",
    "sg:tags":[
        "advisory"
    ],
    "wof:name":"CL Ford Financial",
    "wof:placetype":"venue"
},
  "geometry": {"coordinates":[-122.507887,45.605837],"type":"Point"}
}