{
  "type": "Feature",
  "properties": {
    "addr:full":"9901 192nd St SE Snohomish WA 98296",
    "addr:housenumber":"9901",
    "addr:postcode":"98296",
    "addr:street":"192Nd St Se",
    "iso:country":"US",
    "sg:address":"9901 192nd St SE",
    "sg:city":"Snohomish",
    "sg:classifiers":[
        {
            "category":"Building & Trades",
            "subcategory":"Plumbing",
            "type":"Services"
        }
    ],
    "sg:phone":"+1 360 668 2452",
    "sg:postcode":"98296",
    "sg:province":"WA",
    "sg:tags":[
        "tank",
        "septic"
    ],
    "sg:website":"www.postema.com",
    "wof:name":"Postema Enterprises",
    "wof:placetype":"venue"
},
  "geometry": {"coordinates":[-122.10023099999999,47.822937],"type":"Point"}
}