{
  "type": "Feature",
  "properties": {
    "addr:full":"1427 Queen Ave NE Renton WA 98056",
    "addr:housenumber":"1427",
    "addr:postcode":"98056",
    "addr:street":"Queen Ave Ne",
    "iso:country":"US",
    "sg:address":"1427 Queen Ave NE",
    "sg:city":"Renton",
    "sg:classifiers":[
        {
            "category":"Building & Trades",
            "subcategory":"Construction",
            "type":"Services"
        }
    ],
    "sg:phone":"+1 425 430 5333",
    "sg:postcode":"98056",
    "sg:province":"WA",
    "sg:tags":[
        "contractor"
    ],
    "wof:name":"Selectech Services Inc",
    "wof:placetype":"venue"
},
  "geometry": {"coordinates":[-122.17089,47.505234],"type":"Point"}
}