{
  "type": "Feature",
  "properties": {
    "addr:full":"406 S 1st St Ste 300 Mount Vernon WA 98273",
    "addr:housenumber":"406",
    "addr:postcode":"98273",
    "addr:street":"S 1St St Ste 300",
    "iso:country":"US",
    "sg:address":"406 S 1st St Ste 300",
    "sg:city":"Mount Vernon",
    "sg:classifiers":[
        {
            "category":"Health Services",
            "subcategory":"Doctor",
            "type":"Services"
        },
        {
            "category":"Health Services",
            "subcategory":"Clinic",
            "type":"Services"
        }
    ],
    "sg:phone":"+1 360 336 2593",
    "sg:postcode":"98273",
    "sg:province":"WA",
    "sg:tags":[
        "counseling",
        "mental"
    ],
    "wof:name":"Clarke Jennifer F PHD",
    "wof:placetype":"venue"
},
  "geometry": {"coordinates":[-122.33899700000001,48.4203],"type":"Point"}
}