{
  "type": "Feature",
  "properties": {
    "addr:full":"9020 137th St NW Gig Harbor WA 98329",
    "addr:housenumber":"9020",
    "addr:postcode":"98329",
    "addr:street":"137Th St Nw",
    "iso:country":"US",
    "sg:address":"9020 137th St NW",
    "sg:city":"Gig Harbor",
    "sg:classifiers":[
        {
            "category":"Manufacturing",
            "subcategory":"Apparel",
            "type":"Manufacturing & Wholesale Goods"
        }
    ],
    "sg:phone":"+1 253 857 3010",
    "sg:postcode":"98329",
    "sg:province":"WA",
    "sg:tags":[
        "screen",
        "printer",
        "embroidery"
    ],
    "wof:name":"Gig Harbor Silk Screen & EMB",
    "wof:placetype":"venue"
},
  "geometry": {"coordinates":[-122.65900600000001,47.382344],"type":"Point"}
}