{
  "type": "Feature",
  "properties": {
    "iso:country":"US",
    "sg:address":"6202 NE Hwy 99",
    "sg:city":"Vancouver",
    "sg:classifiers":[
        {
            "category":"Building & Trades",
            "subcategory":"Construction",
            "type":"Services"
        }
    ],
    "sg:phone":"+1 360 737 0608",
    "sg:postcode":"98665",
    "sg:province":"WA",
    "sg:tags":[
        "housing"
    ],
    "wof:name":"Delta Structures",
    "wof:placetype":"venue"
},
  "geometry": {"coordinates":[-122.664288,45.666805],"type":"Point"}
}