{
  "type": "Feature",
  "properties": {
    "addr:full":"1313 Hays Ave NW Olympia WA 98502",
    "addr:housenumber":"1313",
    "addr:postcode":"olympia wa 98502",
    "addr:street":"Hays Ave Nw",
    "iso:country":"US",
    "sg:address":"1313 Hays Ave NW",
    "sg:city":"Olympia",
    "sg:classifiers":[
        {
            "category":"Recreation",
            "type":"Entertainment"
        }
    ],
    "sg:phone":"+1 360 754 3968",
    "sg:postcode":"98502",
    "sg:province":"WA",
    "wof:name":"Rainbow Arts",
    "wof:placetype":"venue"
},
  "geometry": {"coordinates":[-122.918325,47.056043],"type":"Point"}
}