{
  "type": "Feature",
  "properties": {
    "addr:full":"1431 Harrison Ave Blaine WA 98230",
    "addr:housenumber":"1431",
    "addr:postcode":"98230",
    "addr:street":"Harrison Ave",
    "iso:country":"US",
    "sg:address":"1431 Harrison Ave",
    "sg:city":"Blaine",
    "sg:classifiers":[
        {
            "category":"Professional",
            "subcategory":"Management & Consulting",
            "type":"Services"
        }
    ],
    "sg:phone":"+1 360 332 1576",
    "sg:postcode":"98230",
    "sg:province":"WA",
    "sg:tags":[
        "consultant"
    ],
    "wof:name":"M R Enterprises",
    "wof:placetype":"venue"
},
  "geometry": {"coordinates":[-122.746504,48.986209],"type":"Point"}
}