{
  "type": "Feature",
  "properties": {
    "addr:full":"4407 116th Ave E Puyallup WA 98372",
    "addr:housenumber":"4407",
    "addr:postcode":"98372",
    "addr:street":"116Th Ave E",
    "iso:country":"US",
    "sg:address":"4407 116th Ave E",
    "sg:city":"Puyallup",
    "sg:classifiers":[
        {
            "category":"Building & Trades",
            "subcategory":"Construction",
            "type":"Services"
        }
    ],
    "sg:phone":"+1 253 862 7349",
    "sg:postcode":"98372",
    "sg:province":"WA",
    "sg:tags":[
        "carpentry",
        "contractor"
    ],
    "wof:name":"Creekside Carpentry & Rmdlg",
    "wof:placetype":"venue"
},
  "geometry": {"coordinates":[-122.2757,47.214687],"type":"Point"}
}