{
  "type": "Feature",
  "properties": {
    "addr:full":"400 E Pioneer Ave Puyallup WA 98372",
    "addr:housenumber":"400",
    "addr:postcode":"98372",
    "addr:street":"E Pioneer Ave",
    "iso:country":"US",
    "sg:address":"400 E Pioneer Ave",
    "sg:city":"Puyallup",
    "sg:classifiers":[
        {
            "category":"Insurance",
            "subcategory":"Insurance Agent",
            "type":"Services"
        }
    ],
    "sg:phone":"+1 253 848 5566",
    "sg:postcode":"98372",
    "sg:province":"WA",
    "wof:name":"Ron S Crowe Life Insurance",
    "wof:placetype":"venue"
},
  "geometry": {"coordinates":[-122.28841799999999,47.190448],"type":"Point"}
}