{
  "type": "Feature",
  "properties": {
    "addr:full":"831 169th Pl SW Lynnwood WA 98037",
    "addr:housenumber":"831",
    "addr:postcode":"98037",
    "addr:street":"169Th Pl Sw",
    "iso:country":"US",
    "sg:address":"831 169th Pl SW",
    "sg:city":"Lynnwood",
    "sg:classifiers":[
        {
            "category":"Professional",
            "subcategory":"Computer Services",
            "type":"Services"
        }
    ],
    "sg:phone":"+1 425 742 9421",
    "sg:postcode":"98037",
    "sg:province":"WA",
    "sg:tags":[
        "related"
    ],
    "wof:name":"Grounded Heart Networking",
    "wof:placetype":"venue"
},
  "geometry": {"coordinates":[-122.244651,47.844599],"type":"Point"}
}