{
  "type": "Feature",
  "properties": {
    "addr:full":"102 National Ave S Bremerton WA 98312",
    "addr:housenumber":"102",
    "addr:postcode":"98312",
    "addr:street":"National Ave S",
    "iso:country":"US",
    "sg:address":"102 National Ave S",
    "sg:city":"Bremerton",
    "sg:classifiers":[
        {
            "category":"Professional",
            "subcategory":"Advertising",
            "type":"Services"
        }
    ],
    "sg:phone":"+1 360 373 5368",
    "sg:postcode":"98312",
    "sg:province":"WA",
    "sg:tags":[
        "distribution"
    ],
    "wof:name":"Shaklee Authorized Distr",
    "wof:placetype":"venue"
},
  "geometry": {"coordinates":[-122.667705,47.562262],"type":"Point"}
}