{
  "type": "Feature",
  "properties": {
    "addr:full":"3909 241st St NE Arlington WA 98223",
    "addr:housenumber":"3909",
    "addr:postcode":"98223",
    "addr:street":"241St St Ne",
    "iso:country":"US",
    "sg:address":"3909 241st St NE",
    "sg:city":"Arlington",
    "sg:classifiers":[
        {
            "category":"Wholesale",
            "subcategory":"Stationery",
            "type":"Manufacturing & Wholesale Goods"
        }
    ],
    "sg:phone":"+1 360 435 7663",
    "sg:postcode":"98223",
    "sg:province":"WA",
    "sg:tags":[
        "supply"
    ],
    "wof:name":"Functional Forms",
    "wof:placetype":"venue"
},
  "geometry": {"coordinates":[-122.18194,48.214496],"type":"Point"}
}