{
  "type": "Feature",
  "properties": {
    "addr:full":"168 140th St S Tacoma WA 98444",
    "addr:housenumber":"168",
    "addr:postcode":"98444",
    "addr:street":"140Th St S",
    "iso:country":"US",
    "sg:address":"168 140th St S",
    "sg:city":"Tacoma",
    "sg:classifiers":[
        {
            "category":"Autos & Motor Vehicles",
            "subcategory":"Auto Supplies",
            "type":"Retail Goods"
        }
    ],
    "sg:phone":"+1 253 531 3474",
    "sg:postcode":"98444",
    "sg:province":"WA",
    "sg:tags":[
        "automobile",
        "parts"
    ],
    "sg:website":"www.spc-napa.com",
    "wof:name":"NAPA Auto Parts",
    "wof:placetype":"venue"
},
  "geometry": {"coordinates":[-122.433283,47.130211],"type":"Point"}
}