{
  "type": "Feature",
  "properties": {
    "iso:country":"US",
    "sg:address":"6321 119th Ave E",
    "sg:city":"Puyallup",
    "sg:classifiers":[
        {
            "category":"Professional",
            "subcategory":"Business Services",
            "type":"Services"
        }
    ],
    "sg:phone":"+1 253 841 7277",
    "sg:postcode":"98372",
    "sg:province":"WA",
    "wof:name":"Berry Express",
    "wof:placetype":"venue"
},
  "geometry": {"coordinates":[-122.270861,47.199355],"type":"Point"}
}