{
  "type": "Feature",
  "properties": {
    "addr:full":"19719 SE 264th Pl Kent WA 98042",
    "addr:housenumber":"19719",
    "addr:postcode":"98042",
    "addr:street":"Se 264Th Pl",
    "iso:country":"US",
    "sg:address":"19719 SE 264th Pl",
    "sg:city":"Kent",
    "sg:classifiers":[
        {
            "category":"Building & Trades",
            "subcategory":"Construction",
            "type":"Services"
        }
    ],
    "sg:phone":"+1 206 498 9377",
    "sg:postcode":"98042",
    "sg:province":"WA",
    "sg:tags":[
        "hanging",
        "contractor"
    ],
    "wof:name":"Bob & EDS Pntg & Pressure Wshg",
    "wof:placetype":"venue"
},
  "geometry": {"coordinates":[-122.078732,47.364911],"type":"Point"}
}