{
  "type": "Feature",
  "properties": {
    "addr:full":"2450 Orcas Rd Eastsound WA 98245",
    "addr:postcode":"2450;98245",
    "addr:street":"Orcas Rd",
    "iso:country":"US",
    "sg:address":"2450 Orcas Rd",
    "sg:city":"Eastsound",
    "sg:classifiers":[
        {
            "category":"Banks & Credit Unions",
            "subcategory":"Bank",
            "type":"Services"
        }
    ],
    "sg:phone":"+1 360 376 4228",
    "sg:postcode":"98245",
    "sg:province":"WA",
    "sg:tags":[
        "personal",
        "institution"
    ],
    "wof:name":"Quick & Clean Household Servic",
    "wof:placetype":"venue"
},
  "geometry": {"coordinates":[-122.92820500000001,48.667401],"type":"Point"}
}