{
  "type": "Feature",
  "properties": {
    "addr:full":"20301 Hwy 99 Lynnwood WA 98036",
    "addr:housenumber":"20301",
    "addr:postcode":"98036",
    "addr:street":"Hwy 99",
    "iso:country":"US",
    "sg:address":"20301 Hwy 99",
    "sg:city":"Lynnwood",
    "sg:classifiers":[
        {
            "category":"Retail",
            "subcategory":"Auto Repair",
            "type":"Services"
        }
    ],
    "sg:phone":"+1 425 672 0307",
    "sg:postcode":"98036",
    "sg:province":"WA",
    "sg:tags":[
        "shop",
        "automotive",
        "automobile",
        "repairing",
        "general"
    ],
    "wof:name":"APM Auto Repair Inc",
    "wof:placetype":"venue"
},
  "geometry": {"coordinates":[-122.320573,47.814766],"type":"Point"}
}