{
  "type": "Feature",
  "properties": {
    "iso:country":"US",
    "sg:address":"2208 NW Market St",
    "sg:city":"Seattle",
    "sg:classifiers":[
        {
            "category":"Sports & Exercise",
            "subcategory":"Gym",
            "type":"Entertainment"
        }
    ],
    "sg:phone":"+1 206 706 4882",
    "sg:postcode":"98107",
    "sg:province":"WA",
    "sg:tags":[
        "club",
        "health",
        "studio",
        "gymnasium"
    ],
    "wof:name":"Ballard Health Club",
    "wof:placetype":"venue"
},
  "geometry": {"coordinates":[-122.386281,47.668753],"type":"Point"}
}