{
  "type": "Feature",
  "properties": {
    "addr:full":"316 Calistoga St E Orting WA 98360",
    "addr:housenumber":"316",
    "addr:postcode":"98360",
    "addr:street":"Calistoga St E",
    "iso:country":"US",
    "sg:address":"316 Calistoga St E",
    "sg:city":"Orting",
    "sg:classifiers":[
        {
            "category":"Banks & Credit Unions",
            "subcategory":"Bank",
            "type":"Services"
        }
    ],
    "sg:phone":"+1 360 893 6267",
    "sg:postcode":"98360",
    "sg:province":"WA",
    "sg:tags":[
        "student"
    ],
    "wof:name":"Elizabeth Jensen",
    "wof:placetype":"venue"
},
  "geometry": {"coordinates":[-122.199837,47.099702],"type":"Point"}
}