{
  "type": "Feature",
  "properties": {
    "addr:full":"14045 24th Ave NE Seattle WA 98125",
    "addr:housenumber":"14045",
    "addr:postcode":"98125",
    "addr:street":"24Th Ave Ne",
    "iso:country":"US",
    "sg:address":"14045 24th Ave NE",
    "sg:city":"Seattle",
    "sg:classifiers":[
        {
            "category":"Wholesale",
            "subcategory":"Music Publishers",
            "type":"Manufacturing & Wholesale Goods"
        }
    ],
    "sg:phone":"+1 206 365 6249",
    "sg:postcode":"98125",
    "sg:province":"WA",
    "sg:tags":[
        "distribution"
    ],
    "wof:name":"Lets Play Stella",
    "wof:placetype":"venue"
},
  "geometry": {"coordinates":[-122.30307000000001,47.731043],"type":"Point"}
}