{
  "type": "Feature",
  "properties": {
    "addr:full":"29805 NE 107th St Carnation WA 98014",
    "addr:housenumber":"29805",
    "addr:postcode":"98014",
    "addr:street":"Ne 107Th St",
    "iso:country":"US",
    "sg:address":"29805 NE 107th St",
    "sg:city":"Carnation",
    "sg:classifiers":[
        {
            "category":"Building & Trades",
            "subcategory":"Construction",
            "type":"Services"
        }
    ],
    "sg:phone":"+1 425 788 3273",
    "sg:postcode":"98014",
    "sg:province":"WA",
    "sg:tags":[
        "excavation",
        "contractor"
    ],
    "wof:name":"Blackcreek Excavation And Grading",
    "wof:placetype":"venue"
},
  "geometry": {"coordinates":[-121.940817,47.69297],"type":"Point"}
}