{
  "type": "Feature",
  "properties": {
    "iso:country":"US",
    "sg:address":"2225 Crestline Blvd NW",
    "sg:city":"Olympia",
    "sg:classifiers":[
        {
            "category":"Professional",
            "subcategory":"Business Services",
            "type":"Services"
        }
    ],
    "sg:phone":"+1 360 709 0600",
    "sg:postcode":"98502",
    "sg:province":"WA",
    "wof:name":"Kingfisher Design",
    "wof:placetype":"venue"
},
  "geometry": {"coordinates":[-122.921466,47.066774],"type":"Point"}
}