{
  "type": "Feature",
  "properties": {
    "addr:full":"451 Ransom Rd Walla Walla WA 99362",
    "addr:housenumber":"451",
    "addr:postcode":"99362",
    "addr:street":"Ransom Rd",
    "iso:country":"US",
    "sg:address":"451 Ransom Rd",
    "sg:city":"Walla Walla",
    "sg:classifiers":[
        {
            "category":"Insurance",
            "subcategory":"Insurance Agent",
            "type":"Services"
        }
    ],
    "sg:phone":"+1 509 529 2112",
    "sg:postcode":"99362",
    "sg:province":"WA",
    "wof:name":"American Hardware Mutual Ins",
    "wof:placetype":"venue"
},
  "geometry": {"coordinates":[-118.326025,46.039113],"type":"Point"}
}