{
  "type": "Feature",
  "properties": {
    "iso:country":"US",
    "sg:address":"27102 Meadow Cir NE",
    "sg:city":"Kingston",
    "sg:classifiers":[
        {
            "category":"Building & Trades",
            "subcategory":"Cleaning & Sanitation",
            "type":"Services"
        }
    ],
    "sg:phone":"+1 360 297 2961",
    "sg:postcode":"98346",
    "sg:province":"WA",
    "sg:tags":[
        "maintenance"
    ],
    "wof:name":"C J S Mobile Enterprises",
    "wof:placetype":"venue"
},
  "geometry": {"coordinates":[-122.573267,47.809788],"type":"Point"}
}