{
  "type": "Feature",
  "properties": {
    "addr:full":"1100 9th Ave Seattle WA 98101",
    "addr:housenumber":"1100",
    "addr:postcode":"98101",
    "addr:street":"9Th Ave",
    "iso:country":"US",
    "sg:address":"1100 9th Ave",
    "sg:city":"Seattle",
    "sg:classifiers":[
        {
            "category":"Health Services",
            "subcategory":"Doctor",
            "type":"Services"
        }
    ],
    "sg:phone":"+1 206 223 6191",
    "sg:postcode":"98101",
    "sg:province":"WA",
    "wof:name":"Tipton Nancy MD",
    "wof:placetype":"venue"
},
  "geometry": {"coordinates":[-122.327831,47.609223],"type":"Point"}
}