{
  "type": "Feature",
  "properties": {
    "addr:full":"550 Kirkland Way Ste 402 Kirkland WA 98033",
    "addr:housenumber":"550",
    "addr:postcode":"98033",
    "addr:street":"Kirkland Way Ste 402",
    "iso:country":"US",
    "sg:address":"550 Kirkland Way Ste 402",
    "sg:city":"Kirkland",
    "sg:classifiers":[
        {
            "category":"Professional",
            "subcategory":"Accounting & Tax Preparation",
            "type":"Services"
        }
    ],
    "sg:phone":"+1 425 828 8252",
    "sg:postcode":"98033",
    "sg:province":"WA",
    "sg:tags":[
        "accountant"
    ],
    "wof:name":"Martin PC",
    "wof:placetype":"venue"
},
  "geometry": {"coordinates":[-122.197981,47.676835],"type":"Point"}
}