{
  "type": "Feature",
  "properties": {
    "addr:full":"16403 NE 28th Ave Ridgefield WA 98642",
    "addr:housenumber":"16403",
    "addr:postcode":"98642",
    "addr:street":"Ne 28Th Ave",
    "iso:country":"US",
    "sg:address":"16403 NE 28th Ave",
    "sg:city":"Ridgefield",
    "sg:classifiers":[
        {
            "category":"Professional",
            "subcategory":"Business Services",
            "type":"Services"
        }
    ],
    "sg:phone":"+1 360 574 3114",
    "sg:postcode":"98642",
    "sg:province":"WA",
    "sg:tags":[
        "language",
        "for",
        "freelance",
        "deaf",
        "sign",
        "interpreter"
    ],
    "wof:name":"Carol Doty Enterprises",
    "wof:placetype":"venue"
},
  "geometry": {"coordinates":[-122.641623,45.741669],"type":"Point"}
}