{
  "type": "Feature",
  "properties": {
    "iso:country":"US",
    "sg:address":"1901 Freeway Dr",
    "sg:city":"Mt Vernon",
    "sg:classifiers":[
        {
            "category":"Autos & Motor Vehicles",
            "subcategory":"Automobile Sales",
            "type":"Retail Goods"
        }
    ],
    "sg:phone":"+1 360 424 5400",
    "sg:postcode":"98273",
    "sg:province":"WA",
    "sg:tags":[
        "car",
        "dealer"
    ],
    "sg:website":"www.auto-gate.com",
    "wof:name":"Gateway Auto Ctr",
    "wof:placetype":"venue"
},
  "geometry": {"coordinates":[-122.343191,48.437552],"type":"Point"}
}