{
  "type": "Feature",
  "properties": {
    "addr:full":"5321 Evergreen Way Everett WA 98203",
    "addr:housenumber":"5321",
    "addr:postcode":"98203",
    "addr:street":"Evergreen Way",
    "iso:country":"US",
    "sg:address":"5321 Evergreen Way",
    "sg:city":"Everett",
    "sg:classifiers":[
        {
            "category":"Shopping",
            "subcategory":"Hobbies, Toys, & Games",
            "type":"Retail Goods"
        },
        {
            "category":"Shopping",
            "type":"Retail Goods"
        }
    ],
    "sg:phone":"+1 425 353 3084",
    "sg:postcode":"98203",
    "sg:province":"WA",
    "sg:tags":[
        "picture",
        "frame"
    ],
    "sg:website":"www.artsupply-nw.com",
    "wof:name":"Art Supply Northwest Inc",
    "wof:placetype":"venue"
},
  "geometry": {"coordinates":[-122.215306,47.947641],"type":"Point"}
}