{
  "type": "Feature",
  "properties": {
    "addr:full":"2108 S 279th Pl Federal Way WA 98003",
    "addr:housenumber":"2108",
    "addr:postcode":"98003",
    "addr:street":"S 279Th Pl",
    "iso:country":"US",
    "sg:address":"2108 S 279th Pl",
    "sg:city":"Federal Way",
    "sg:classifiers":[
        {
            "category":"Building & Trades",
            "subcategory":"Cleaning & Sanitation",
            "type":"Services"
        }
    ],
    "sg:phone":"+1 253 839 2070",
    "sg:postcode":"98003",
    "sg:province":"WA",
    "sg:tags":[
        "repair",
        "maintenance"
    ],
    "wof:name":"Englehart Enterprises",
    "wof:placetype":"venue"
},
  "geometry": {"coordinates":[-122.304877,47.352644],"type":"Point"}
}