{
  "type": "Feature",
  "properties": {
    "addr:full":"2512 N Proctor St Tacoma WA 98406",
    "addr:housenumber":"2512",
    "addr:postcode":"98406",
    "addr:street":"N Proctor St",
    "iso:country":"US",
    "sg:address":"2512 N Proctor St",
    "sg:city":"Tacoma",
    "sg:classifiers":[
        {
            "category":"Shopping",
            "subcategory":"Discount & Variety Stores",
            "type":"Retail Goods"
        }
    ],
    "sg:phone":"+1 253 759 2823",
    "sg:postcode":"98406",
    "sg:province":"WA",
    "sg:tags":[
        "merchandise",
        "general"
    ],
    "wof:name":"ACS Discovery Shop",
    "wof:placetype":"venue"
},
  "geometry": {"coordinates":[-122.488944,47.270952],"type":"Point"}
}