{
  "type": "Feature",
  "properties": {
    "addr:full":"5324 84th St E Tacoma WA 98446",
    "addr:housenumber":"5324",
    "addr:postcode":"98446",
    "addr:street":"84Th St",
    "iso:country":"US",
    "sg:address":"5324 84th St E",
    "sg:city":"Tacoma",
    "sg:classifiers":[
        {
            "category":"Personal",
            "subcategory":"Beauty Salon",
            "type":"Services"
        }
    ],
    "sg:phone":"+1 253 536 2501",
    "sg:postcode":"98446",
    "sg:province":"WA",
    "sg:tags":[
        "manicuring"
    ],
    "wof:name":"L D Nails & Body Wax",
    "wof:placetype":"venue"
},
  "geometry": {"coordinates":[-122.358799,47.180822],"type":"Point"}
}