{
  "type": "Feature",
  "properties": {
    "addr:full":"2804 Happy Valley Rd Sequim WA 98382",
    "addr:housenumber":"2804",
    "addr:postcode":"98382",
    "addr:street":"Happy Valley Rd",
    "iso:country":"US",
    "sg:address":"2804 Happy Valley Rd",
    "sg:city":"Sequim",
    "sg:classifiers":[
        {
            "category":"Building & Trades",
            "subcategory":"Construction",
            "type":"Services"
        }
    ],
    "sg:phone":"+1 360 681 7800",
    "sg:postcode":"98382",
    "sg:province":"WA",
    "sg:tags":[
        "house"
    ],
    "wof:name":"Sound Construction",
    "wof:placetype":"venue"
},
  "geometry": {"coordinates":[-123.098688,48.043334],"type":"Point"}
}