{
  "type": "Feature",
  "properties": {
    "addr:full":"13885 S Keyport Rd NE Poulsbo WA 98370",
    "addr:housenumber":"13885",
    "addr:postcode":"98370",
    "addr:street":"S Keyport Rd Ne",
    "iso:country":"US",
    "sg:address":"13885 S Keyport Rd NE",
    "sg:city":"Poulsbo",
    "sg:classifiers":[
        {
            "category":"Manufacturing",
            "subcategory":"Buildings",
            "type":"Manufacturing & Wholesale Goods"
        },
        {
            "category":"Building & Trades",
            "subcategory":"Construction",
            "type":"Services"
        }
    ],
    "sg:phone":"+1 360 697 1541",
    "sg:postcode":"98370",
    "sg:province":"WA",
    "sg:tags":[
        "home",
        "builder",
        "industrial",
        "contractors-commercial",
        "contractor"
    ],
    "wof:name":"Bernier Contracting",
    "wof:placetype":"venue"
},
  "geometry": {"coordinates":[-122.624234,47.688498],"type":"Point"}
}