{
  "type": "Feature",
  "properties": {
    "addr:full":"721 E Pike Street Seattle WA 98122",
    "addr:housenumber":"721",
    "addr:postcode":"98122",
    "addr:street":"E Pike Street",
    "iso:country":"US",
    "sg:address":"721 E Pike Street",
    "sg:city":"Seattle",
    "sg:classifiers":[
        {
            "category":"Arts & Performance",
            "subcategory":"Art Gallery",
            "type":"Entertainment"
        }
    ],
    "sg:phone":"+1 206 726 9509",
    "sg:postcode":"98122",
    "sg:province":"WA",
    "wof:name":"Martin-Zambito Fine Art",
    "wof:placetype":"venue"
},
  "geometry": {"coordinates":[-122.322396,47.61418],"type":"Point"}
}