{
  "type": "Feature",
  "properties": {
    "addr:full":"1900 116th Ave NE Ste 200 Bellevue WA 98004",
    "addr:housenumber":"1900",
    "addr:postcode":"98004",
    "addr:street":"116Th Ave Ne Ste 200",
    "iso:country":"US",
    "sg:address":"1900 116th Ave NE Ste 200",
    "sg:city":"Bellevue",
    "sg:classifiers":[
        {
            "category":"Health Services",
            "subcategory":"Clinic",
            "type":"Services"
        },
        {
            "category":"Health Services",
            "subcategory":"Health Practitioner",
            "type":"Services"
        }
    ],
    "sg:phone":"+1 425 577 8074",
    "sg:postcode":"98004",
    "sg:province":"WA",
    "sg:tags":[
        "acupuncture",
        "spa",
        "medical"
    ],
    "sg:website":"www.artofasiaacu.com/",
    "wof:name":"Art of Asia Healing Medicine",
    "wof:placetype":"venue"
},
  "geometry": {"coordinates":[-122.185036,47.627191],"type":"Point"}
}