{
  "type": "Feature",
  "properties": {
    "addr:full":"9007 Allen Point Dr NW Gig Harbor WA 98332",
    "addr:housenumber":"9007",
    "addr:postcode":"98332",
    "addr:street":"Allen Point Dr Nw",
    "iso:country":"US",
    "sg:address":"9007 Allen Point Dr NW",
    "sg:city":"Gig Harbor",
    "sg:classifiers":[
        {
            "category":"Freight",
            "type":"Transportation"
        }
    ],
    "sg:phone":"+1 253 851 5987",
    "sg:postcode":"98332",
    "sg:province":"WA",
    "sg:tags":[
        "broker",
        "customs"
    ],
    "sg:website":"www.al-tokin.com",
    "wof:name":"A L TOKIN Co LLC",
    "wof:placetype":"venue"
},
  "geometry": {"coordinates":[-122.65801999999999,47.340991],"type":"Point"}
}