{
  "type": "Feature",
  "properties": {
    "addr:full":"6317 California Ave SW Seattle WA 98136",
    "addr:housenumber":"6317",
    "addr:postcode":"98136",
    "addr:street":"California Ave Sw",
    "iso:country":"US",
    "sg:address":"6317 California Ave SW",
    "sg:city":"Seattle",
    "sg:classifiers":[
        {
            "category":"Retail",
            "subcategory":"Laundry & Dry Cleaning",
            "type":"Services"
        }
    ],
    "sg:phone":"+1 206 935 9211",
    "sg:postcode":"98136",
    "sg:province":"WA",
    "wof:name":"Shortstop Cleaners",
    "wof:placetype":"venue"
},
  "geometry": {"coordinates":[-122.387001,47.5462],"type":"Point"}
}