{
  "type": "Feature",
  "properties": {
    "addr:full":"3733 221st Pl SE Sammamish WA 98075",
    "addr:housenumber":"3733",
    "addr:postcode":"98075",
    "addr:street":"221St Pl Se",
    "iso:country":"US",
    "sg:address":"3733 221st Pl SE",
    "sg:city":"Sammamish",
    "sg:classifiers":[
        {
            "category":"Health Services",
            "subcategory":"Clinic",
            "type":"Services"
        }
    ],
    "sg:phone":"+1 425 392 2701",
    "sg:postcode":"98075",
    "sg:province":"WA",
    "sg:tags":[
        "home",
        "care"
    ],
    "wof:name":"M&M Adult Family Home Care",
    "wof:placetype":"venue"
},
  "geometry": {"coordinates":[-122.044455,47.576632],"type":"Point"}
}