{
  "type": "Feature",
  "properties": {
    "addr:full":"2000 SW Dash Point Rd Federal Way WA 98023",
    "addr:housenumber":"2000",
    "addr:postcode":"98023",
    "addr:street":"Sw Dash Point Rd",
    "iso:country":"US",
    "sg:address":"2000 SW Dash Point Rd",
    "sg:city":"Federal Way",
    "sg:classifiers":[
        {
            "category":"Organizations",
            "subcategory":"Religious Organization",
            "type":"Services"
        }
    ],
    "sg:phone":"+1 253 838 0915",
    "sg:postcode":"98023",
    "sg:province":"WA",
    "wof:name":"Wayside United Church Christ",
    "wof:placetype":"venue"
},
  "geometry": {"coordinates":[-122.35675500000001,47.322035],"type":"Point"}
}