{
  "type": "Feature",
  "properties": {
    "addr:full":"926 Prospect Ave NE Olympia WA 98506",
    "addr:housenumber":"926",
    "addr:postcode":"98506",
    "addr:street":"Prospect Ave Ne",
    "iso:country":"US",
    "sg:address":"926 Prospect Ave NE",
    "sg:city":"Olympia",
    "sg:classifiers":[
        {
            "category":"Personal",
            "subcategory":"Beauty Salon",
            "type":"Services"
        }
    ],
    "sg:phone":"+1 360 705 8920",
    "sg:postcode":"98506",
    "sg:province":"WA",
    "sg:tags":[
        "shop"
    ],
    "wof:name":"Salon Intrigue LLC",
    "wof:placetype":"venue"
},
  "geometry": {"coordinates":[-122.890908,47.048924],"type":"Point"}
}