{
  "type": "Feature",
  "properties": {
    "addr:full":"2701 Eastlake Ave E Seattle WA 98102",
    "addr:housenumber":"2701",
    "addr:postcode":"98102",
    "addr:street":"Eastlake Ave E",
    "iso:country":"US",
    "sg:address":"2701 Eastlake Ave E",
    "sg:city":"Seattle",
    "sg:classifiers":[
        {
            "category":"Personal",
            "subcategory":"Beauty Salon",
            "type":"Services"
        }
    ],
    "sg:phone":"+1 206 329 9007",
    "sg:postcode":"98102",
    "sg:province":"WA",
    "wof:name":"Beautyworks",
    "wof:placetype":"venue"
},
  "geometry": {"coordinates":[-122.325881,47.645621],"type":"Point"}
}