{
  "type": "Feature",
  "properties": {
    "iso:country":"US",
    "sg:address":"4 S 1st Ave",
    "sg:city":"Walla Walla",
    "sg:classifiers":[
        {
            "category":"Restaurant",
            "type":"Food & Drink"
        }
    ],
    "sg:phone":"+1 509 526 0636",
    "sg:postcode":"99362",
    "sg:province":"WA",
    "sg:tags":[
        "eating"
    ],
    "wof:name":"Coffee Perk",
    "wof:placetype":"venue"
},
  "geometry": {"coordinates":[-118.338142,46.067154],"type":"Point"}
}