{
  "type": "Feature",
  "properties": {
    "addr:full":"526 S Main St Colville WA 99114",
    "addr:housenumber":"526",
    "addr:postcode":"99114",
    "addr:street":"S Main St",
    "iso:country":"US",
    "sg:address":"526 S Main St",
    "sg:city":"Colville",
    "sg:classifiers":[
        {
            "category":"Professional",
            "subcategory":"Lawyer & Legal Services",
            "type":"Services"
        }
    ],
    "sg:phone":"+1 509 684 1965",
    "sg:postcode":"99114",
    "sg:province":"WA",
    "sg:tags":[
        "attorney"
    ],
    "wof:name":"Skok & Monasmith-Colville",
    "wof:placetype":"venue"
},
  "geometry": {"coordinates":[-117.90577999999999,48.539832],"type":"Point"}
}