{
  "type": "Feature",
  "properties": {
    "addr:full":"610 NW 65th St Seattle WA 98117",
    "addr:housenumber":"610",
    "addr:postcode":"98117",
    "addr:street":"Nw 65Th St",
    "iso:country":"US",
    "sg:address":"610 NW 65th St",
    "sg:city":"Seattle",
    "sg:classifiers":[
        {
            "category":"Bars & Pubs",
            "type":"Food & Drink"
        },
        {
            "category":"Restaurant",
            "type":"Food & Drink"
        }
    ],
    "sg:phone":"+1 206 789 9643",
    "sg:postcode":"98117",
    "sg:province":"WA",
    "sg:tags":[
        "irish"
    ],
    "sg:website":"www.mollyson65th.com",
    "wof:name":"Molly Maguires",
    "wof:placetype":"venue"
},
  "geometry": {"coordinates":[-122.363998,47.676102],"type":"Point"}
}