{
  "type": "Feature",
  "properties": {
    "addr:full":"8610 169th Ct NE Redmond WA 98052",
    "addr:housenumber":"8610",
    "addr:postcode":"98052",
    "addr:street":"169Th Ct Ne",
    "iso:country":"US",
    "sg:address":"8610 169th Ct NE",
    "sg:city":"Redmond",
    "sg:classifiers":[
        {
            "category":"Health Services",
            "subcategory":"Clinic",
            "type":"Services"
        }
    ],
    "sg:phone":"+1 425 556 4379",
    "sg:postcode":"98052",
    "sg:province":"WA",
    "sg:tags":[
        "specialty",
        "outpatient"
    ],
    "wof:name":"Lite For Life Inc",
    "wof:placetype":"venue"
},
  "geometry": {"coordinates":[-122.11533799999999,47.679507],"type":"Point"}
}