{
  "type": "Feature",
  "properties": {
    "addr:full":"309 Puyallup Ave Tacoma WA 98421",
    "addr:housenumber":"309",
    "addr:postcode":"98421",
    "addr:street":"Puyallup Ave",
    "iso:country":"US",
    "sg:address":"309 Puyallup Ave",
    "sg:city":"Tacoma",
    "sg:classifiers":[
        {
            "category":"Professional",
            "subcategory":"Art Services",
            "type":"Services"
        }
    ],
    "sg:phone":"+1 253 779 5800",
    "sg:postcode":"98421",
    "sg:province":"WA",
    "sg:tags":[
        "graphic",
        "designer"
    ],
    "wof:name":"Hemisphere Design",
    "wof:placetype":"venue"
},
  "geometry": {"coordinates":[-122.429576,47.240698],"type":"Point"}
}