{
  "type": "Feature",
  "properties": {
    "addr:full":"117 Camp Creek Rd Montesano WA 98563",
    "addr:housenumber":"117",
    "addr:postcode":"98563",
    "addr:street":"Camp Creek Rd",
    "iso:country":"US",
    "sg:address":"117 Camp Creek Rd",
    "sg:city":"Montesano",
    "sg:classifiers":[
        {
            "category":"Professional",
            "subcategory":"Computer Services",
            "type":"Services"
        }
    ],
    "sg:phone":"+1 360 249 2849",
    "sg:postcode":"98563",
    "sg:province":"WA",
    "sg:tags":[
        "related"
    ],
    "wof:name":"Polrcom",
    "wof:placetype":"venue"
},
  "geometry": {"coordinates":[-123.573111,46.991811],"type":"Point"}
}