{
  "type": "Feature",
  "properties": {
    "addr:full":"13 Belbrook Ln Port Angeles WA 98362",
    "addr:housenumber":"13",
    "addr:postcode":"98362",
    "addr:street":"Belbrook Ln",
    "iso:country":"US",
    "sg:address":"13 Belbrook Ln",
    "sg:city":"Port Angeles",
    "sg:classifiers":[
        {
            "category":"Retail",
            "subcategory":"Auto Repair",
            "type":"Services"
        }
    ],
    "sg:phone":"+1 360 457 7013",
    "sg:postcode":"98362",
    "sg:province":"WA",
    "sg:tags":[
        "general"
    ],
    "wof:name":"Hot Wheels Automotive",
    "wof:placetype":"venue"
},
  "geometry": {"coordinates":[-123.284361,48.102558],"type":"Point"}
}