{
  "type": "Feature",
  "properties": {
    "addr:full":"2412 E 13th St Vancouver WA 98661",
    "addr:housenumber":"2412",
    "addr:postcode":"98661",
    "addr:street":"E 13Th St",
    "iso:country":"US",
    "sg:address":"2412 E 13th St",
    "sg:city":"Vancouver",
    "sg:classifiers":[
        {
            "category":"Building & Trades",
            "subcategory":"Construction",
            "type":"Services"
        }
    ],
    "sg:phone":"+1 360 513 6719",
    "sg:postcode":"98661",
    "sg:province":"WA",
    "sg:tags":[
        "repairing",
        "remodeling",
        "contractor"
    ],
    "wof:name":"Allphase Contracting",
    "wof:placetype":"venue"
},
  "geometry": {"coordinates":[-122.645325,45.630294],"type":"Point"}
}