{
  "type": "Feature",
  "properties": {
    "iso:country":"US",
    "sg:address":"161 Hanson Rd",
    "sg:city":"Touchet",
    "sg:classifiers":[
        {
            "category":"Education",
            "subcategory":"Library",
            "type":"Public Place"
        }
    ],
    "sg:phone":"+1 509 394 2329",
    "sg:postcode":"99360",
    "sg:province":"WA",
    "wof:name":"Touchet Community Library",
    "wof:placetype":"venue"
},
  "geometry": {"coordinates":[-118.67447199999999,46.046478],"type":"Point"}
}