{
  "type": "Feature",
  "properties": {
    "addr:full":"675 NW Columbia Dr Oak Harbor WA 98277",
    "addr:housenumber":"675",
    "addr:postcode":"98277",
    "addr:street":"Nw Columbia Dr",
    "iso:country":"US",
    "sg:address":"675 NW Columbia Dr",
    "sg:city":"Oak Harbor",
    "sg:classifiers":[
        {
            "category":"Building & Trades",
            "subcategory":"Construction",
            "type":"Services"
        }
    ],
    "sg:phone":"+1 360 675 3731",
    "sg:postcode":"98277",
    "sg:province":"WA",
    "sg:tags":[
        "hanging",
        "contractor"
    ],
    "wof:name":"Cline Painting",
    "wof:placetype":"venue"
},
  "geometry": {"coordinates":[-122.66562399999999,48.302822],"type":"Point"}
}