{
  "type": "Feature",
  "properties": {
    "addr:full":"2501 Warner Ave Enumclaw WA 98022",
    "addr:housenumber":"2501",
    "addr:postcode":"98022",
    "addr:street":"Warner Ave",
    "iso:country":"US",
    "sg:address":"2501 Warner Ave",
    "sg:city":"Enumclaw",
    "sg:classifiers":[
        {
            "category":"Organizations",
            "subcategory":"Religious Organization",
            "type":"Services"
        }
    ],
    "sg:phone":"+1 360 825 5578",
    "sg:postcode":"98022",
    "sg:province":"WA",
    "sg:tags":[
        "church"
    ],
    "wof:name":"Church Of The Nazarene",
    "wof:placetype":"venue"
},
  "geometry": {"coordinates":[-122.00022199999999,47.192066],"type":"Point"}
}