{
  "type": "Feature",
  "properties": {
    "addr:full":"10688 NE 10th St Bellevue WA 98004",
    "addr:housenumber":"10688",
    "addr:postcode":"98004",
    "addr:street":"Ne 10Th St",
    "iso:country":"US",
    "sg:address":"10688 NE 10th St",
    "sg:city":"Bellevue",
    "sg:classifiers":[
        {
            "category":"Real Estate",
            "subcategory":"Real Estate Operator",
            "type":"Services"
        }
    ],
    "sg:phone":"+1 425 454 5300",
    "sg:postcode":"98004",
    "sg:province":"WA",
    "sg:tags":[
        "apartment"
    ],
    "wof:name":"Belcarra",
    "wof:placetype":"venue"
},
  "geometry": {"coordinates":[-122.191115,47.619517],"type":"Point"}
}