{
  "type": "Feature",
  "properties": {
    "addr:full":"2551 Cole St Enumclaw WA 98022",
    "addr:housenumber":"2551",
    "addr:postcode":"98022",
    "addr:street":"Cole St",
    "iso:country":"US",
    "sg:address":"2551 Cole St",
    "sg:city":"Enumclaw",
    "sg:classifiers":[
        {
            "category":"Professional",
            "type":"Services"
        }
    ],
    "sg:phone":"+1 360 802 2716",
    "sg:postcode":"98022",
    "sg:province":"WA",
    "sg:tags":[
        "establishment"
    ],
    "wof:name":"A Better Concept Inc",
    "wof:placetype":"venue"
},
  "geometry": {"coordinates":[-121.985826,47.207321],"type":"Point"}
}