{
  "type": "Feature",
  "properties": {
    "addr:full":"1111 Griffith Point Rd Nordland WA 98358",
    "addr:housenumber":"1111",
    "addr:postcode":"98358",
    "addr:street":"Griffith Point Rd",
    "iso:country":"US",
    "sg:address":"1111 Griffith Point Rd",
    "sg:city":"Nordland",
    "sg:classifiers":[
        {
            "category":"Building & Trades",
            "subcategory":"Construction",
            "type":"Services"
        }
    ],
    "sg:phone":"+1 360 379 0544",
    "sg:postcode":"98358",
    "sg:province":"WA",
    "sg:tags":[
        "repairing",
        "remodeling",
        "contractor"
    ],
    "wof:name":"Mystery Bay Woodworks",
    "wof:placetype":"venue"
},
  "geometry": {"coordinates":[-122.700497,48.052925],"type":"Point"}
}