{
  "type": "Feature",
  "properties": {
    "addr:full":"5300 Lacey Blvd SE Lacey WA 98503",
    "addr:housenumber":"5300",
    "addr:postcode":"98503",
    "addr:street":"Lacey Blvd Se",
    "iso:country":"US",
    "sg:address":"5300 Lacey Blvd SE",
    "sg:city":"Lacey",
    "sg:classifiers":[
        {
            "category":"Wholesale",
            "subcategory":"Hardware",
            "type":"Manufacturing & Wholesale Goods"
        },
        {
            "category":"Wholesale",
            "subcategory":"Metals & Minerals",
            "type":"Manufacturing & Wholesale Goods"
        }
    ],
    "sg:phone":"+1 360 491 0996",
    "sg:postcode":"98503",
    "sg:province":"WA",
    "sg:tags":[
        "plumbing",
        "fixture",
        "center",
        "supply"
    ],
    "wof:name":"Rosen Supply Company Inc",
    "wof:placetype":"venue"
},
  "geometry": {"coordinates":[-122.812138,47.035688],"type":"Point"}
}