{
  "type": "Feature",
  "properties": {
    "addr:full":"4429 95th St SW Lakewood WA 98499",
    "addr:housenumber":"4429",
    "addr:postcode":"98499",
    "addr:street":"95Th St Sw",
    "iso:country":"US",
    "sg:address":"4429 95th St SW",
    "sg:city":"Lakewood",
    "sg:classifiers":[
        {
            "category":"Wholesale",
            "subcategory":"Construction Materials",
            "type":"Manufacturing & Wholesale Goods"
        }
    ],
    "sg:phone":"+1 253 474 5356",
    "sg:postcode":"98499",
    "sg:province":"WA",
    "sg:tags":[
        "frame",
        "door"
    ],
    "wof:name":"Benson Industries Inc LLC",
    "wof:placetype":"venue"
},
  "geometry": {"coordinates":[-122.496177,47.17109],"type":"Point"}
}