{
  "type": "Feature",
  "properties": {
    "addr:full":"1009 SE 130th Ave Vancouver WA 98683",
    "addr:housenumber":"1009",
    "addr:postcode":"98683",
    "addr:street":"Se 130Th Ave",
    "iso:country":"US",
    "sg:address":"1009 SE 130th Ave",
    "sg:city":"Vancouver",
    "sg:classifiers":[
        {
            "category":"Professional",
            "subcategory":"Accounting & Tax Preparation",
            "type":"Services"
        }
    ],
    "sg:phone":"+1 360 260 4854",
    "sg:postcode":"98683",
    "sg:province":"WA",
    "wof:name":"Virtual Business Assoc",
    "wof:placetype":"venue"
},
  "geometry": {"coordinates":[-122.539237,45.613641],"type":"Point"}
}