{
  "type": "Feature",
  "properties": {
    "addr:full":"10309 Lakeview Ave SW Tacoma WA 98499",
    "addr:housenumber":"10309",
    "addr:postcode":"98499",
    "addr:street":"Lakeview Ave Sw",
    "iso:country":"US",
    "sg:address":"10309 Lakeview Ave SW",
    "sg:city":"Tacoma",
    "sg:classifiers":[
        {
            "category":"Shopping",
            "subcategory":"Discount & Variety Stores",
            "type":"Retail Goods"
        }
    ],
    "sg:phone":"+1 253 983 1233",
    "sg:postcode":"98499",
    "sg:province":"WA",
    "sg:tags":[
        "post",
        "trading"
    ],
    "wof:name":"Lee's Trading",
    "wof:placetype":"venue"
},
  "geometry": {"coordinates":[-122.494552,47.163317],"type":"Point"}
}