{
  "type": "Feature",
  "properties": {
    "addr:full":"551 W Washington St Sequim WA 98382",
    "addr:housenumber":"551",
    "addr:postcode":"98382",
    "addr:street":"W Washington St",
    "iso:country":"US",
    "sg:address":"551 W Washington St",
    "sg:city":"Sequim",
    "sg:classifiers":[
        {
            "category":"Professional",
            "subcategory":"Printing & Photocopies",
            "type":"Services"
        }
    ],
    "sg:phone":"+1 360 681 0000",
    "sg:postcode":"98382",
    "sg:province":"WA",
    "sg:tags":[
        "photocopying",
        "business",
        "copying",
        "duplicating"
    ],
    "wof:name":"Spacecopies",
    "wof:placetype":"venue"
},
  "geometry": {"coordinates":[-123.115199,48.079637],"type":"Point"}
}