{
  "type": "Feature",
  "properties": {
    "addr:full":"529 4th Ave W Olympia WA 98501",
    "addr:housenumber":"529",
    "addr:postcode":"98501",
    "addr:street":"4Th Ave W",
    "iso:country":"US",
    "sg:address":"529 4th Ave W",
    "sg:city":"Olympia",
    "sg:classifiers":[
        {
            "category":"Government",
            "subcategory":"Office",
            "type":"Public Place"
        }
    ],
    "sg:phone":"+1 360 786 5581",
    "sg:postcode":"98501",
    "sg:province":"WA",
    "sg:tags":[
        "administrative",
        "program",
        "health"
    ],
    "wof:name":"Public Hlth & Social Svc Dept",
    "wof:placetype":"venue"
},
  "geometry": {"coordinates":[-122.907961,47.044341],"type":"Point"}
}