{
  "type": "Feature",
  "properties": {
    "addr:full":"555 NE Northgate Way Seattle WA 98125",
    "addr:housenumber":"555",
    "addr:postcode":"98125",
    "addr:street":"Ne Northgate Way",
    "iso:country":"US",
    "sg:address":"555 NE Northgate Way",
    "sg:city":"Seattle",
    "sg:classifiers":[
        {
            "category":"Fast Food",
            "type":"Food & Drink"
        },
        {
            "category":"Restaurant",
            "type":"Food & Drink"
        }
    ],
    "sg:phone":"+1 206 367 8696",
    "sg:postcode":"98125",
    "sg:province":"WA",
    "sg:tags":[
        "chinese"
    ],
    "sg:website":"www.pandaexpress.com",
    "wof:name":"Panda Express",
    "wof:placetype":"venue"
},
  "geometry": {"coordinates":[-122.32086700000001,47.708517],"type":"Point"}
}