{
  "type": "Feature",
  "properties": {
    "iso:country":"US",
    "sg:address":"10244 19th Ave SW",
    "sg:city":"Seattle",
    "sg:classifiers":[
        {
            "category":"Building & Trades",
            "subcategory":"Construction",
            "type":"Services"
        }
    ],
    "sg:phone":"+1 206 768 0484",
    "sg:postcode":"98146",
    "sg:province":"WA",
    "sg:tags":[
        "gen"
    ],
    "wof:name":"Reidt Construction",
    "wof:placetype":"venue"
},
  "geometry": {"coordinates":[-122.358369,47.510444],"type":"Point"}
}