{
  "type": "Feature",
  "properties": {
    "addr:full":"31421 76th Ave NW Stanwood WA 98292",
    "addr:housenumber":"31421",
    "addr:postcode":"98292",
    "addr:street":"76Th Ave Nw",
    "iso:country":"US",
    "sg:address":"31421 76th Ave NW",
    "sg:city":"Stanwood",
    "sg:classifiers":[
        {
            "category":"Retail",
            "subcategory":"Repair Shop",
            "type":"Services"
        }
    ],
    "sg:phone":"+1 360 629 2068",
    "sg:postcode":"98292",
    "sg:province":"WA",
    "sg:tags":[
        "bathtub",
        "sink",
        "refinishing"
    ],
    "wof:name":"A Classic Finish",
    "wof:placetype":"venue"
},
  "geometry": {"coordinates":[-122.336392,48.280567],"type":"Point"}
}