{
  "type": "Feature",
  "properties": {
    "addr:full":"2701 2nd Ave Seattle WA 98121",
    "addr:housenumber":"2701",
    "addr:postcode":"98121",
    "addr:street":"2Nd Ave",
    "iso:country":"US",
    "sg:address":"2701 2nd Ave",
    "sg:city":"Seattle",
    "sg:classifiers":[
        {
            "category":"Manufacturing",
            "subcategory":"Jewelry",
            "type":"Manufacturing & Wholesale Goods"
        }
    ],
    "sg:phone":"+1 206 448 4466",
    "sg:postcode":"98121",
    "sg:province":"WA",
    "sg:tags":[
        "precious",
        "mfg"
    ],
    "wof:name":"Eastern Merchandise Co Inc",
    "wof:placetype":"venue"
},
  "geometry": {"coordinates":[-122.349998,47.616501],"type":"Point"}
}