{
  "type": "Feature",
  "properties": {
    "addr:full":"1600 116th Ave NE Bellevue WA 98004",
    "addr:housenumber":"1600",
    "addr:postcode":"98004",
    "addr:street":"116Th Ave Ne",
    "iso:country":"US",
    "sg:address":"1600 116th Ave NE",
    "sg:city":"Bellevue",
    "sg:classifiers":[
        {
            "category":"Health Services",
            "subcategory":"Health Practitioner",
            "type":"Services"
        }
    ],
    "sg:phone":"+1 425 440 3886",
    "sg:postcode":"98004",
    "sg:province":"WA",
    "sg:tags":[
        "control",
        "reducing",
        "weight"
    ],
    "sg:website":"http://laparoscopynw.reachlocal.com/?scid=1877438",
    "wof:name":"Weight Loss Surgery",
    "wof:placetype":"venue"
},
  "geometry": {"coordinates":[-122.185692,47.624576],"type":"Point"}
}