{
  "type": "Feature",
  "properties": {
    "iso:country":"US",
    "sg:address":"500 Lilly Rd NE",
    "sg:city":"Olympia",
    "sg:classifiers":[
        {
            "category":"Health Services",
            "subcategory":"Doctor",
            "type":"Services"
        }
    ],
    "sg:phone":"+1 360 413 8292",
    "sg:postcode":"98506",
    "sg:province":"WA",
    "sg:tags":[
        "medical"
    ],
    "wof:name":"Mark J Bauer MD",
    "wof:placetype":"venue"
},
  "geometry": {"coordinates":[-122.84433900000001,47.054026],"type":"Point"}
}