{
  "type": "Feature",
  "properties": {
    "addr:full":"221 S 10th Ave Pasco WA 99301",
    "addr:housenumber":"221",
    "addr:postcode":"99301",
    "addr:street":"S 10Th Ave",
    "iso:country":"US",
    "sg:address":"221 S 10th Ave",
    "sg:city":"Pasco",
    "sg:classifiers":[
        {
            "category":"Food & Beverages",
            "subcategory":"Groceries & Convenience Stores",
            "type":"Retail Goods"
        }
    ],
    "sg:phone":"+1 509 545 2119",
    "sg:postcode":"99301",
    "sg:province":"WA",
    "wof:name":"Stop and Go",
    "wof:placetype":"venue"
},
  "geometry": {"coordinates":[-119.100998,46.227402],"type":"Point"}
}