{
  "type": "Feature",
  "properties": {
    "addr:full":"115 N 4th Ave Yakima WA 98902",
    "addr:housenumber":"115",
    "addr:postcode":"98902",
    "addr:street":"N 4Th Ave",
    "iso:country":"US",
    "sg:address":"115 N 4th Ave",
    "sg:city":"Yakima",
    "sg:classifiers":[
        {
            "category":"Professional",
            "subcategory":"Engineering",
            "type":"Services"
        },
        {
            "category":"Home & Garden",
            "subcategory":"Building Materials",
            "type":"Retail Goods"
        },
        {
            "category":"Building & Trades",
            "subcategory":"Construction",
            "type":"Services"
        }
    ],
    "sg:phone":"+1 509 654 9537",
    "sg:postcode":"98902",
    "sg:province":"WA",
    "sg:tags":[
        "system",
        "specialty",
        "heating",
        "equipment",
        "ventilating",
        "contractor",
        "air conditioning"
    ],
    "sg:website":"http://heat-cool-fireplace.com/",
    "wof:name":"Allard Heating Cooling & Gas Fireplace",
    "wof:placetype":"venue"
},
  "geometry": {"coordinates":[-120.514786,46.601813],"type":"Point"}
}