{
  "type": "Feature",
  "properties": {
    "addr:full":"1825 Leslie Rd Richland WA 99352",
    "addr:housenumber":"1825",
    "addr:postcode":"99352",
    "addr:street":"Leslie Rd",
    "iso:country":"US",
    "sg:address":"1825 Leslie Rd",
    "sg:city":"Richland",
    "sg:classifiers":[
        {
            "category":"Professional",
            "subcategory":"Detective & Security Services",
            "type":"Services"
        }
    ],
    "sg:phone":"+1 509 366 1942",
    "sg:postcode":"99352",
    "sg:province":"WA",
    "sg:tags":[
        "car"
    ],
    "wof:name":"Agency Northwest Investigation",
    "wof:placetype":"venue"
},
  "geometry": {"coordinates":[-119.264893,46.226736],"type":"Point"}
}