{
  "type": "Feature",
  "properties": {
    "addr:full":"1213 Hemlock St Milton WA 98354",
    "addr:housenumber":"1213",
    "addr:postcode":"98354",
    "addr:street":"Hemlock St",
    "iso:country":"US",
    "sg:address":"1213 Hemlock St",
    "sg:city":"Milton",
    "sg:classifiers":[
        {
            "category":"Travel",
            "subcategory":"Travel Agent",
            "type":"Entertainment"
        }
    ],
    "sg:phone":"+1 253 517 8651",
    "sg:postcode":"98354",
    "sg:province":"WA",
    "sg:tags":[
        "agency",
        "services-commercial"
    ],
    "wof:name":"San Pierre Travel",
    "wof:placetype":"venue"
},
  "geometry": {"coordinates":[-122.318006,47.251301],"type":"Point"}
}