{
  "type": "Feature",
  "properties": {
    "addr:full":"7312 Meridian Rd SE Olympia WA 98513",
    "addr:housenumber":"7312",
    "addr:postcode":"olympia;98513",
    "addr:street":"Meridian Rd Se",
    "iso:country":"US",
    "sg:address":"7312 Meridian Rd SE",
    "sg:city":"Olympia",
    "sg:classifiers":[
        {
            "category":"Real Estate",
            "subcategory":"Real Estate Services",
            "type":"Services"
        },
        {
            "category":"Professional",
            "subcategory":"Business Services",
            "type":"Services"
        },
        {
            "category":"Real Estate",
            "subcategory":"Surveying",
            "type":"Services"
        }
    ],
    "sg:phone":"+1 360 459 8203",
    "sg:postcode":"98513",
    "sg:province":"WA",
    "sg:tags":[
        "commercial",
        "appraisers-business",
        "industrial",
        "appraisers-commercial",
        "appraiser"
    ],
    "wof:name":"The Granger Co",
    "wof:placetype":"venue"
},
  "geometry": {"coordinates":[-122.738511,46.981842],"type":"Point"}
}