{
  "type": "Feature",
  "properties": {
    "addr:full":"1150 W Chestnut St Walla Walla WA 99362",
    "addr:housenumber":"1150",
    "addr:postcode":"99362",
    "addr:street":"W Chestnut St",
    "iso:country":"US",
    "sg:address":"1150 W Chestnut St",
    "sg:city":"Walla Walla",
    "sg:classifiers":[
        {
            "category":"Education",
            "subcategory":"School",
            "type":"Public Place"
        }
    ],
    "sg:phone":"+1 509 527 3066",
    "sg:postcode":"99362",
    "sg:province":"WA",
    "wof:name":"Blue Ridge Elementary School",
    "wof:placetype":"venue"
},
  "geometry": {"coordinates":[-118.35242100000001,46.055003],"type":"Point"}
}