{
  "type": "Feature",
  "properties": {
    "addr:full":"7202 6th Ave Tacoma WA 98406",
    "addr:housenumber":"7202",
    "addr:postcode":"98406",
    "addr:street":"6Th Ave",
    "iso:country":"US",
    "sg:address":"7202 6th Ave",
    "sg:city":"Tacoma",
    "sg:classifiers":[
        {
            "category":"Restaurant",
            "type":"Food & Drink"
        }
    ],
    "sg:phone":"+1 253 564 4588",
    "sg:postcode":"98406",
    "sg:province":"WA",
    "sg:tags":[
        "shop",
        "coffee",
        "eating"
    ],
    "wof:name":"Amy's Espresso",
    "wof:placetype":"venue"
},
  "geometry": {"coordinates":[-122.534059,47.255449],"type":"Point"}
}