{
  "type": "Feature",
  "properties": {
    "addr:full":"15421 Des Moines Memorial Dr Ofc Burien WA 98148",
    "addr:housenumber":"15421",
    "addr:postcode":"98148",
    "addr:street":"Des Moines Memorial Dr",
    "iso:country":"US",
    "sg:address":"15421 Des Moines Memorial Dr Ofc",
    "sg:city":"Burien",
    "sg:classifiers":[
        {
            "category":"Real Estate",
            "subcategory":"Real Estate Operator",
            "type":"Services"
        }
    ],
    "sg:phone":"+1 206 241 0310",
    "sg:postcode":"98148",
    "sg:province":"WA",
    "sg:tags":[
        "apartment"
    ],
    "wof:name":"Lapaloma Apts",
    "wof:placetype":"venue"
},
  "geometry": {"coordinates":[-122.323441,47.464751],"type":"Point"}
}