{
  "type": "Feature",
  "properties": {
    "addr:full":"702 Kentucky St 531 Bellingham WA 98225",
    "addr:housenumber":"702;531",
    "addr:postcode":"98225",
    "addr:street":"Kentucky St",
    "iso:country":"US",
    "sg:address":"702 Kentucky St 531",
    "sg:city":"Bellingham",
    "sg:classifiers":[
        {
            "category":"Manufacturing",
            "subcategory":"Pet Food",
            "type":"Manufacturing & Wholesale Goods"
        },
        {
            "category":"Shopping",
            "subcategory":"Pets & Pet Supplies",
            "type":"Retail Goods"
        }
    ],
    "sg:phone":"+1 360 715 8787",
    "sg:postcode":"98225",
    "sg:province":"WA",
    "sg:tags":[
        "manufacturer",
        "store",
        "foods-wholesale"
    ],
    "wof:name":"Furhaven Pet Products, Inc.",
    "wof:placetype":"venue"
},
  "geometry": {"coordinates":[-122.466348,48.75777],"type":"Point"}
}