{
  "type": "Feature",
  "properties": {
    "addr:full":"715 Fern St Walla Walla WA 99362",
    "addr:housenumber":"715",
    "addr:postcode":"99362",
    "addr:street":"Fern St",
    "iso:country":"US",
    "sg:address":"715 Fern St",
    "sg:city":"Walla Walla",
    "sg:classifiers":[
        {
            "category":"Professional",
            "type":"Services"
        }
    ],
    "sg:phone":"+1 509 526 7696",
    "sg:postcode":"99362",
    "sg:province":"WA",
    "wof:name":"Turning Point Motor Sports",
    "wof:placetype":"venue"
},
  "geometry": {"coordinates":[-118.314536,46.062066],"type":"Point"}
}