{
  "type": "Feature",
  "properties": {
    "addr:full":"652 E 11th St Tacoma WA 98421",
    "addr:housenumber":"652",
    "addr:postcode":"98421",
    "addr:street":"E 11Th St",
    "iso:country":"US",
    "sg:address":"652 E 11th St",
    "sg:city":"Tacoma",
    "sg:classifiers":[
        {
            "category":"Wholesale",
            "subcategory":"Durable Goods & Equipment",
            "type":"Manufacturing & Wholesale Goods"
        }
    ],
    "sg:phone":"+1 253 779 8166",
    "sg:postcode":"98421",
    "sg:province":"WA",
    "wof:name":"Turco Engineering",
    "wof:placetype":"venue"
},
  "geometry": {"coordinates":[-122.427024,47.25494],"type":"Point"}
}