{
  "type": "Feature",
  "properties": {
    "addr:full":"8 N Argonne Rd Spokane WA 99212",
    "addr:housenumber":"8",
    "addr:postcode":"99212",
    "addr:street":"N Argonne Rd",
    "iso:country":"US",
    "sg:address":"8 N Argonne Rd",
    "sg:city":"Spokane",
    "sg:classifiers":[
        {
            "category":"Organizations",
            "subcategory":"Community Association",
            "type":"Services"
        }
    ],
    "sg:phone":"+1 509 927 0648",
    "sg:postcode":"99212",
    "sg:province":"WA",
    "wof:name":"Mountain View Homeowners Assoc",
    "wof:placetype":"venue"
},
  "geometry": {"coordinates":[-117.28277199999999,47.657281],"type":"Point"}
}