{
  "type": "Feature",
  "properties": {
    "iso:country":"US",
    "sg:address":"710 S Anderson St",
    "sg:city":"Tacoma",
    "sg:classifiers":[
        {
            "category":"Organizations",
            "subcategory":"Religious Organization",
            "type":"Services"
        }
    ],
    "sg:phone":"+1 253 627 0700",
    "sg:postcode":"98405",
    "sg:province":"WA",
    "wof:name":"Epworth Lesourd United Method",
    "wof:placetype":"venue"
},
  "geometry": {"coordinates":[-122.472561,47.253743],"type":"Point"}
}