{
  "type": "Feature",
  "properties": {
    "addr:full":"4909 Rainier Ave S Seattle WA 98118",
    "addr:housenumber":"4909",
    "addr:postcode":"98118",
    "addr:street":"Rainier Ave S",
    "iso:country":"US",
    "sg:address":"4909 Rainier Ave S",
    "sg:city":"Seattle",
    "sg:classifiers":[
        {
            "category":"Restaurant",
            "type":"Food & Drink"
        }
    ],
    "sg:phone":"+1 206 721 0212",
    "sg:postcode":"98118",
    "sg:province":"WA",
    "sg:tags":[
        "fusion",
        "sushi",
        "bar",
        "asian",
        "japanese"
    ],
    "sg:website":"www.wabisabicolumbiacity.com",
    "wof:name":"Wabi Sabi",
    "wof:placetype":"venue"
},
  "geometry": {"coordinates":[-122.28519900000001,47.557541],"type":"Point"}
}