{
  "type": "Feature",
  "properties": {
    "addr:full":"2428 S Irving St Seattle WA 98144",
    "addr:housenumber":"2428",
    "addr:postcode":"98144",
    "addr:street":"S Irving St",
    "iso:country":"US",
    "sg:address":"2428 S Irving St",
    "sg:city":"Seattle",
    "sg:classifiers":[
        {
            "category":"Banks & Credit Unions",
            "subcategory":"Bank",
            "type":"Services"
        }
    ],
    "sg:phone":"+1 206 571 6802",
    "sg:postcode":"98144",
    "sg:province":"WA",
    "sg:tags":[
        "loan",
        "broker"
    ],
    "wof:name":"Martin Gaelyn Ind Contracts",
    "wof:placetype":"venue"
},
  "geometry": {"coordinates":[-122.29884,47.591278],"type":"Point"}
}