{
  "type": "Feature",
  "properties": {
    "addr:full":"98503 E Michelle Dr Kennewick WA 99338",
    "addr:housenumber":"98503",
    "addr:postcode":"99338",
    "addr:street":"E Michelle Dr",
    "iso:country":"US",
    "sg:address":"98503 E Michelle Dr",
    "sg:city":"Kennewick",
    "sg:classifiers":[
        {
            "category":"Building & Trades",
            "subcategory":"Plumbing",
            "type":"Services"
        }
    ],
    "sg:phone":"+1 509 628 8703",
    "sg:postcode":"99338",
    "sg:province":"WA",
    "sg:tags":[
        "contractor"
    ],
    "wof:name":"Prettyman Construction",
    "wof:placetype":"venue"
},
  "geometry": {"coordinates":[-119.29236,46.199161],"type":"Point"}
}