{
  "type": "Feature",
  "properties": {
    "addr:full":"222 NE Pk Plaza Dr Vancouver WA 98660",
    "addr:housenumber":"222",
    "addr:postcode":"98660",
    "addr:street":"Ne Pk Plaza Dr",
    "iso:country":"US",
    "sg:address":"222 NE Pk Plaza Dr",
    "sg:city":"Vancouver",
    "sg:classifiers":[
        {
            "category":"Health Services",
            "subcategory":"Health Practitioner",
            "type":"Services"
        }
    ],
    "sg:phone":"+1 360 253 8285",
    "sg:postcode":"98660",
    "sg:province":"WA",
    "sg:tags":[
        "therapy",
        "physical"
    ],
    "sg:website":"www.pteliteinc.com",
    "wof:name":"Pt Elite Inc",
    "wof:placetype":"venue"
},
  "geometry": {"coordinates":[-122.540938,45.621601],"type":"Point"}
}