{
  "type": "Feature",
  "properties": {
    "addr:full":"550 106th Ave NE Bellevue WA 98004",
    "addr:housenumber":"550",
    "addr:postcode":"98004",
    "addr:street":"106Th Ave Ne",
    "iso:country":"US",
    "sg:address":"550 106th Ave NE",
    "sg:city":"Bellevue",
    "sg:classifiers":[
        {
            "category":"Restaurant",
            "type":"Food & Drink"
        }
    ],
    "sg:menulink":"http://www.allmenus.com/wa/east-seattle/268699-yama-at-the-galleria/menu/",
    "sg:phone":"+1 425 453 4007",
    "sg:postcode":"98004",
    "sg:province":"WA",
    "wof:name":"Yama at the Galleria",
    "wof:placetype":"venue"
},
  "geometry": {"coordinates":[-122.198914,47.61514],"type":"Point"}
}