{
  "type": "Feature",
  "properties": {
    "addr:full":"6313 75th St W Tacoma WA 98499",
    "addr:housenumber":"6313",
    "addr:postcode":"98499",
    "addr:street":"75Th St W",
    "iso:country":"US",
    "sg:address":"6313 75th St W",
    "sg:city":"Tacoma",
    "sg:classifiers":[
        {
            "category":"Organizations",
            "subcategory":"Community Association",
            "type":"Services"
        }
    ],
    "sg:phone":"+1 253 588 2388",
    "sg:postcode":"98499",
    "sg:province":"WA",
    "sg:tags":[
        "fraternal"
    ],
    "wof:name":"Elks Lodge",
    "wof:placetype":"venue"
},
  "geometry": {"coordinates":[-122.523717,47.189849],"type":"Point"}
}