{
  "type": "Feature",
  "properties": {
    "addr:full":"10945 SE 223rd St Kent WA 98031",
    "addr:housenumber":"10945",
    "addr:postcode":"98031",
    "addr:street":"Se 223Rd St",
    "iso:country":"US",
    "sg:address":"10945 SE 223rd St",
    "sg:city":"Kent",
    "sg:classifiers":[
        {
            "category":"Real Estate",
            "subcategory":"Real Estate Operator",
            "type":"Services"
        }
    ],
    "sg:phone":"+1 253 852 0834",
    "sg:postcode":"98031",
    "sg:province":"WA",
    "sg:tags":[
        "building",
        "apartment"
    ],
    "sg:website":"http://www.reedermgt.com",
    "wof:name":"Benson East",
    "wof:placetype":"venue"
},
  "geometry": {"coordinates":[-122.194523,47.402356],"type":"Point"}
}