{
  "type": "Feature",
  "properties": {
    "iso:country":"US",
    "sg:address":"14733 247th Pl SE",
    "sg:city":"Issaquah",
    "sg:classifiers":[
        {
            "category":"Wholesale",
            "subcategory":"Medical Equipment & Supplies",
            "type":"Manufacturing & Wholesale Goods"
        }
    ],
    "sg:phone":"+1 425 392 7402",
    "sg:postcode":"98027",
    "sg:province":"WA",
    "sg:tags":[
        "hospital"
    ],
    "wof:name":"Mac Farland Associates",
    "wof:placetype":"venue"
},
  "geometry": {"coordinates":[-122.01135600000001,47.470548],"type":"Point"}
}