{
  "type": "Feature",
  "properties": {
    "addr:full":"19612 70th Ave S Kent WA 98032",
    "addr:housenumber":"19612",
    "addr:postcode":"98032",
    "addr:street":"70Th Ave S",
    "iso:country":"US",
    "sg:address":"19612 70th Ave S",
    "sg:city":"Kent",
    "sg:classifiers":[
        {
            "category":"Wholesale",
            "subcategory":"Electrical",
            "type":"Manufacturing & Wholesale Goods"
        }
    ],
    "sg:phone":"+1 253 872 1880",
    "sg:postcode":"98032",
    "sg:province":"WA",
    "sg:tags":[
        "equipment"
    ],
    "wof:name":"Windy City Wire",
    "wof:placetype":"venue"
},
  "geometry": {"coordinates":[-122.24559000000001,47.42433],"type":"Point"}
}