{
  "type": "Feature",
  "properties": {
    "addr:full":"4211 W Olympic Ave Spokane WA 99205",
    "addr:housenumber":"4211",
    "addr:postcode":"99205",
    "addr:street":"W Olympic Ave",
    "iso:country":"US",
    "sg:address":"4211 W Olympic Ave",
    "sg:city":"Spokane",
    "sg:classifiers":[
        {
            "category":"Shopping",
            "subcategory":"Gifts & Souvenirs",
            "type":"Retail Goods"
        }
    ],
    "sg:phone":"+1 509 328 6881",
    "sg:postcode":"99205",
    "sg:province":"WA",
    "wof:name":"Gifts & More",
    "wof:placetype":"venue"
},
  "geometry": {"coordinates":[-117.47546199999999,47.70296],"type":"Point"}
}