{
  "type": "Feature",
  "properties": {
    "addr:full":"43 SW Cascade Ave Chehalis WA 98532",
    "addr:housenumber":"43",
    "addr:postcode":"98532",
    "addr:street":"Sw Cascade Ave",
    "iso:country":"US",
    "sg:address":"43 SW Cascade Ave",
    "sg:city":"Chehalis",
    "sg:classifiers":[
        {
            "category":"Organizations",
            "subcategory":"Professional Association",
            "type":"Services"
        }
    ],
    "sg:phone":"+1 360 748 9193",
    "sg:postcode":"98532",
    "sg:province":"WA",
    "sg:tags":[
        "insurance",
        "business"
    ],
    "wof:name":"Nase",
    "wof:placetype":"venue"
},
  "geometry": {"coordinates":[-122.9669,46.66022],"type":"Point"}
}