{
  "type": "Feature",
  "properties": {
    "addr:full":"302 Bellevue Way NE Bellevue WA 98004",
    "addr:housenumber":"302",
    "addr:postcode":"98004",
    "addr:street":"Bellevue Way Ne",
    "iso:country":"US",
    "sg:address":"302 Bellevue Way NE",
    "sg:city":"Bellevue",
    "sg:classifiers":[
        {
            "category":"Restaurant",
            "type":"Food & Drink"
        }
    ],
    "sg:phone":"+1 425 451 1144",
    "sg:postcode":"98004",
    "sg:province":"WA",
    "sg:tags":[
        "italian"
    ],
    "wof:name":"Sbarro",
    "wof:placetype":"venue"
},
  "geometry": {"coordinates":[-122.201531,47.613787],"type":"Point"}
}