{
  "type": "Feature",
  "properties": {
    "addr:full":"1411 36th St Everett WA 98201",
    "addr:housenumber":"1411",
    "addr:postcode":"98201",
    "addr:street":"36Th St",
    "iso:country":"US",
    "sg:address":"1411 36th St",
    "sg:city":"Everett",
    "sg:classifiers":[
        {
            "category":"Building & Trades",
            "subcategory":"Construction",
            "type":"Services"
        }
    ],
    "sg:phone":"+1 425 339 3110",
    "sg:postcode":"98201",
    "sg:province":"WA",
    "sg:tags":[
        "painter"
    ],
    "wof:name":"Sanora Painting",
    "wof:placetype":"venue"
},
  "geometry": {"coordinates":[-122.20974699999999,47.969991],"type":"Point"}
}