{
  "type": "Feature",
  "properties": {
    "addr:full":"4634 E Marginal Way S Ste C150 Seattle WA 98134",
    "addr:housenumber":"4634",
    "addr:postcode":"98134",
    "addr:street":"E Marginal Way S Ste C150",
    "iso:country":"US",
    "sg:address":"4634 E Marginal Way S Ste C150",
    "sg:city":"Seattle",
    "sg:classifiers":[
        {
            "category":"Utilities",
            "type":"Services"
        }
    ],
    "sg:phone":"+1 206 694 1800",
    "sg:postcode":"98134",
    "sg:province":"WA",
    "sg:tags":[
        "provider",
        "internet"
    ],
    "wof:name":"E-Net China Inc",
    "wof:placetype":"venue"
},
  "geometry": {"coordinates":[-122.33905900000001,47.561671],"type":"Point"}
}