{
  "type": "Feature",
  "properties": {
    "addr:full":"4027 N Post St Spokane WA 99205",
    "addr:housenumber":"4027",
    "addr:postcode":"99205",
    "addr:street":"N Post St",
    "iso:country":"US",
    "sg:address":"4027 N Post St",
    "sg:city":"Spokane",
    "sg:classifiers":[
        {
            "category":"Shopping",
            "subcategory":"Bicycles & Sporting Goods",
            "type":"Retail Goods"
        }
    ],
    "sg:phone":"+1 509 868 1228",
    "sg:postcode":"99205",
    "sg:province":"WA",
    "sg:tags":[
        "whole",
        "sale"
    ],
    "wof:name":"Seabreeze Ventures",
    "wof:placetype":"venue"
},
  "geometry": {"coordinates":[-117.423314,47.695188],"type":"Point"}
}