{
  "type": "Feature",
  "properties": {
    "addr:full":"12407 127th St E Puyallup WA 98374",
    "addr:housenumber":"12407",
    "addr:postcode":"98374",
    "addr:street":"127Th St E",
    "iso:country":"US",
    "sg:address":"12407 127th St E",
    "sg:city":"Puyallup",
    "sg:classifiers":[
        {
            "category":"Home & Garden",
            "subcategory":"Furniture",
            "type":"Retail Goods"
        }
    ],
    "sg:phone":"+1 253 848 2940",
    "sg:postcode":"98374",
    "sg:province":"WA",
    "wof:name":"J Boyd Designs",
    "wof:placetype":"venue"
},
  "geometry": {"coordinates":[-122.26320699999999,47.140474],"type":"Point"}
}