{
  "type": "Feature",
  "properties": {
    "addr:full":"23106 N Crescent Rd Chattaroy WA 99003",
    "addr:housenumber":"23106",
    "addr:postcode":"99003",
    "addr:street":"N Crescent Rd",
    "iso:country":"US",
    "sg:address":"23106 N Crescent Rd",
    "sg:city":"Chattaroy",
    "sg:classifiers":[
        {
            "category":"Building & Trades",
            "subcategory":"Construction",
            "type":"Services"
        }
    ],
    "sg:phone":"+1 509 466 1460",
    "sg:postcode":"99003",
    "sg:province":"WA",
    "sg:tags":[
        "electrical",
        "contractor"
    ],
    "wof:name":"Robertson & Co Electrical",
    "wof:placetype":"venue"
},
  "geometry": {"coordinates":[-117.37622399999999,47.868322],"type":"Point"}
}