{
  "type": "Feature",
  "properties": {
    "addr:full":"1820 N 48th St Seattle WA 98103",
    "addr:housenumber":"1820",
    "addr:postcode":"98103",
    "addr:street":"N 48Th St",
    "iso:country":"US",
    "sg:address":"1820 N 48th St",
    "sg:city":"Seattle",
    "sg:classifiers":[
        {
            "category":"Building & Trades",
            "subcategory":"Plumbing",
            "type":"Services"
        }
    ],
    "sg:phone":"+1 206 632 8069",
    "sg:postcode":"98103",
    "sg:province":"WA",
    "sg:website":"www.seattledrainservice.com/",
    "wof:name":"Seattle Drain Service",
    "wof:placetype":"venue"
},
  "geometry": {"coordinates":[-122.33548500000001,47.663797],"type":"Point"}
}