{
  "type": "Feature",
  "properties": {
    "addr:full":"13204 Country Club Dr SW Lakewood WA 98498",
    "addr:housenumber":"13204",
    "addr:postcode":"98498",
    "addr:street":"Country Club Dr Sw",
    "iso:country":"US",
    "sg:address":"13204 Country Club Dr SW",
    "sg:city":"Lakewood",
    "sg:classifiers":[
        {
            "category":"Sports & Exercise",
            "subcategory":"Golf",
            "type":"Entertainment"
        }
    ],
    "sg:phone":"+1 253 588 2161",
    "sg:postcode":"98498",
    "sg:province":"WA",
    "wof:name":"Tacoma Country & Golf Club",
    "wof:placetype":"venue"
},
  "geometry": {"coordinates":[-122.53330699999999,47.137546],"type":"Point"}
}