{
  "type": "Feature",
  "properties": {
    "addr:full":"1420 N Pines Rd Spokane Valley WA 99206",
    "addr:housenumber":"1420",
    "addr:postcode":"99206",
    "addr:street":"N Pines Rd",
    "iso:country":"US",
    "sg:address":"1420 N Pines Rd",
    "sg:city":"Spokane Valley",
    "sg:classifiers":[
        {
            "category":"Wholesale",
            "subcategory":"Electrical",
            "type":"Manufacturing & Wholesale Goods"
        },
        {
            "category":"Shopping",
            "subcategory":"Computers & Home Electronics",
            "type":"Retail Goods"
        }
    ],
    "sg:phone":"+1 208 772 3348",
    "sg:postcode":"99206",
    "sg:province":"WA",
    "sg:tags":[
        "sound",
        "control",
        "automotive",
        "system",
        "security",
        "consumer"
    ],
    "sg:website":"www.certified-security.com",
    "wof:name":"Certified Security Systems",
    "wof:placetype":"venue"
},
  "geometry": {"coordinates":[-117.239741,47.670572],"type":"Point"}
}