{
  "type": "Feature",
  "properties": {
    "addr:full":"1624 Overlook Dr Wenatchee WA 98801",
    "addr:housenumber":"1624",
    "addr:postcode":"98801",
    "addr:street":"Overlook Dr",
    "iso:country":"US",
    "sg:address":"1624 Overlook Dr",
    "sg:city":"Wenatchee",
    "sg:classifiers":[
        {
            "category":"Manufacturing",
            "subcategory":"Lumber",
            "type":"Manufacturing & Wholesale Goods"
        }
    ],
    "sg:phone":"+1 509 662 3035",
    "sg:postcode":"98801",
    "sg:province":"WA",
    "sg:tags":[
        "forester"
    ],
    "wof:name":"Cascade Woodlands",
    "wof:placetype":"venue"
},
  "geometry": {"coordinates":[-120.343335,47.454205],"type":"Point"}
}