{
  "type": "Feature",
  "properties": {
    "addr:full":"965 54th Ave E Tacoma WA 98424",
    "addr:housenumber":"965",
    "addr:postcode":"98424",
    "addr:street":"54Th Ave E",
    "iso:country":"US",
    "sg:address":"965 54th Ave E",
    "sg:city":"Tacoma",
    "sg:classifiers":[
        {
            "category":"Manufacturing",
            "subcategory":"Metals",
            "type":"Manufacturing & Wholesale Goods"
        }
    ],
    "sg:phone":"+1 253 922 6030",
    "sg:postcode":"98424",
    "sg:province":"WA",
    "sg:tags":[
        "windows"
    ],
    "wof:name":"Milgard Manufacturing",
    "wof:placetype":"venue"
},
  "geometry": {"coordinates":[-122.35674400000001,47.249882],"type":"Point"}
}