{
  "type": "Feature",
  "properties": {
    "addr:full":"9202 Dibble Ave NW Seattle WA 98117",
    "addr:housenumber":"9202",
    "addr:postcode":"98117",
    "addr:street":"Dibble Ave Nw",
    "iso:country":"US",
    "sg:address":"9202 Dibble Ave NW",
    "sg:city":"Seattle",
    "sg:classifiers":[
        {
            "category":"Government",
            "subcategory":"Post Office",
            "type":"Public Place"
        }
    ],
    "sg:phone":"+1 206 240 2642",
    "sg:postcode":"98117",
    "sg:province":"WA",
    "sg:tags":[
        "delivery",
        "courier"
    ],
    "wof:name":"Knr Couriers",
    "wof:placetype":"venue"
},
  "geometry": {"coordinates":[-122.367363,47.696116],"type":"Point"}
}