{
  "type": "Feature",
  "properties": {
    "addr:full":"1108 Creekwood Ct SE Olympia WA 98501",
    "addr:housenumber":"1108",
    "addr:postcode":"98501",
    "addr:street":"Creekwood Ct Se",
    "iso:country":"US",
    "sg:address":"1108 Creekwood Ct SE",
    "sg:city":"Olympia",
    "sg:classifiers":[
        {
            "category":"Organizations",
            "subcategory":"Professional Association",
            "type":"Services"
        }
    ],
    "sg:phone":"+1 360 753 8672",
    "sg:postcode":"98501",
    "sg:province":"WA",
    "sg:tags":[
        "business"
    ],
    "wof:name":"Gq International Merchandising",
    "wof:placetype":"venue"
},
  "geometry": {"coordinates":[-122.866998,47.038731],"type":"Point"}
}