{
  "type": "Feature",
  "properties": {
    "iso:country":"US",
    "sg:address":"460 N 5th St",
    "sg:city":"Cheney",
    "sg:classifiers":[
        {
            "category":"Organizations",
            "subcategory":"Religious Organization",
            "type":"Services"
        }
    ],
    "sg:phone":"+1 509 235 6229",
    "sg:postcode":"99004",
    "sg:province":"WA",
    "sg:tags":[
        "church"
    ],
    "wof:name":"St Rose-Lima Church",
    "wof:placetype":"venue"
},
  "geometry": {"coordinates":[-117.57419400000001,47.496584],"type":"Point"}
}