{
  "type": "Feature",
  "properties": {
    "addr:full":"1619 21st Ave Seattle WA 98122",
    "addr:housenumber":"1619",
    "addr:postcode":"98122",
    "addr:street":"21St Ave",
    "iso:country":"US",
    "sg:address":"1619 21st Ave",
    "sg:city":"Seattle",
    "sg:classifiers":[
        {
            "category":"Recreation",
            "type":"Entertainment"
        }
    ],
    "sg:phone":"+1 206 852 4078",
    "sg:postcode":"98122",
    "sg:province":"WA",
    "wof:name":"Holly Yoga",
    "wof:placetype":"venue"
},
  "geometry": {"coordinates":[-122.304928,47.616778],"type":"Point"}
}