{
  "type": "Feature",
  "properties": {
    "addr:full":"5727 N 21st St Tacoma WA 98406",
    "addr:housenumber":"5727",
    "addr:postcode":"98406",
    "addr:street":"N 21St St",
    "iso:country":"US",
    "sg:address":"5727 N 21st St",
    "sg:city":"Tacoma",
    "sg:classifiers":[
        {
            "category":"Banks & Credit Unions",
            "subcategory":"Bank",
            "type":"Services"
        }
    ],
    "sg:phone":"+1 253 761 8170",
    "sg:postcode":"98406",
    "sg:province":"WA",
    "sg:tags":[
        "commercial"
    ],
    "sg:website":"www.columbiabank.com",
    "wof:name":"Columbia Bank",
    "wof:placetype":"venue"
},
  "geometry": {"coordinates":[-122.515685,47.267256],"type":"Point"}
}