{
  "type": "Feature",
  "properties": {
    "addr:full":"7700 NE 72nd Ave Vancouver WA 98661",
    "addr:housenumber":"7700",
    "addr:postcode":"98661",
    "addr:street":"Ne 72Nd Ave",
    "iso:country":"US",
    "sg:address":"7700 NE 72nd Ave",
    "sg:city":"Vancouver",
    "sg:classifiers":[
        {
            "category":"Professional",
            "subcategory":"Lawyer & Legal Services",
            "type":"Services"
        }
    ],
    "sg:phone":"+1 360 896 3467",
    "sg:postcode":"98661",
    "sg:province":"WA",
    "wof:name":"West Link Legal Services",
    "wof:placetype":"venue"
},
  "geometry": {"coordinates":[-122.599453,45.677378],"type":"Point"}
}