{
  "type": "Feature",
  "properties": {
    "addr:full":"2556 Burwell St Bremerton WA 98312",
    "addr:housenumber":"2556",
    "addr:postcode":"98312",
    "addr:street":"Burwell St",
    "iso:country":"US",
    "sg:address":"2556 Burwell St",
    "sg:city":"Bremerton",
    "sg:classifiers":[
        {
            "category":"Retail",
            "subcategory":"Car Wash",
            "type":"Services"
        }
    ],
    "sg:phone":"+1 360 373 5020",
    "sg:postcode":"98312",
    "sg:province":"WA",
    "sg:tags":[
        "polishing",
        "washing"
    ],
    "wof:name":"Burwell Landing",
    "wof:placetype":"venue"
},
  "geometry": {"coordinates":[-122.651624,47.565632],"type":"Point"}
}