{
  "type": "Feature",
  "properties": {
    "addr:full":"12222 Bear Track Ln SW Port Orchard WA 98367",
    "addr:housenumber":"12222",
    "addr:postcode":"98367",
    "addr:street":"Bear Track Ln Sw Port Orchard",
    "iso:country":"US",
    "sg:address":"12222 Bear Track Ln SW",
    "sg:city":"Port Orchard",
    "sg:classifiers":[
        {
            "category":"Manufacturing",
            "subcategory":"Tools & Machinery",
            "type":"Manufacturing & Wholesale Goods"
        }
    ],
    "sg:phone":"+1 360 275 0879",
    "sg:postcode":"98367",
    "sg:province":"WA",
    "sg:tags":[
        "computer",
        "electronic",
        "mfg"
    ],
    "wof:name":"Peanut Computers",
    "wof:placetype":"venue"
},
  "geometry": {"coordinates":[-122.73434899999999,47.43548],"type":"Point"}
}