{
  "type": "Feature",
  "properties": {
    "addr:full":"5815 4th Ave S Seattle WA 98108",
    "addr:housenumber":"5815",
    "addr:postcode":"98108",
    "addr:street":"4Th Ave S",
    "iso:country":"US",
    "sg:address":"5815 4th Ave S",
    "sg:city":"Seattle",
    "sg:classifiers":[
        {
            "category":"Wholesale",
            "subcategory":"Groceries",
            "type":"Manufacturing & Wholesale Goods"
        }
    ],
    "sg:phone":"+1 206 768 8812",
    "sg:postcode":"98108",
    "sg:province":"WA",
    "sg:tags":[
        "food",
        "broker",
        "general"
    ],
    "sg:website":"www.c-cbrokers.com",
    "wof:name":"C & C Quality Brokers",
    "wof:placetype":"venue"
},
  "geometry": {"coordinates":[-122.329654,47.550534],"type":"Point"}
}