{
  "type": "Feature",
  "properties": {
    "addr:full":"1426 SW 304th St Federal Way WA 98023",
    "addr:housenumber":"1426",
    "addr:postcode":"98023",
    "addr:street":"Sw 304Th St",
    "iso:country":"US",
    "sg:address":"1426 SW 304th St",
    "sg:city":"Federal Way",
    "sg:classifiers":[
        {
            "category":"Building & Trades",
            "subcategory":"Construction",
            "type":"Services"
        }
    ],
    "sg:phone":"+1 253 839 7573",
    "sg:postcode":"98023",
    "sg:province":"WA",
    "sg:tags":[
        "general",
        "contractor"
    ],
    "wof:name":"A & A Construction",
    "wof:placetype":"venue"
},
  "geometry": {"coordinates":[-122.353639,47.329682],"type":"Point"}
}