{
  "type": "Feature",
  "properties": {
    "addr:full":"2320 W Sylvester St Pasco WA 99301",
    "addr:housenumber":"2320",
    "addr:postcode":"99301",
    "addr:street":"W Sylvester St",
    "iso:country":"US",
    "sg:address":"2320 W Sylvester St",
    "sg:city":"Pasco",
    "sg:classifiers":[
        {
            "category":"Real Estate",
            "subcategory":"Real Estate Operator",
            "type":"Services"
        }
    ],
    "sg:phone":"+1 509 547 0879",
    "sg:postcode":"99301",
    "sg:province":"WA",
    "sg:tags":[
        "building",
        "apartment"
    ],
    "wof:name":"Sun Gardens West",
    "wof:placetype":"venue"
},
  "geometry": {"coordinates":[-119.12241,46.234072],"type":"Point"}
}