{
  "type": "Feature",
  "properties": {
    "addr:full":"3120 W Connaught Dr Spokane WA 99208",
    "addr:housenumber":"3120",
    "addr:postcode":"99208",
    "addr:street":"W Connaught Dr",
    "iso:country":"US",
    "sg:address":"3120 W Connaught Dr",
    "sg:city":"Spokane",
    "sg:classifiers":[
        {
            "category":"Professional",
            "subcategory":"Advertising",
            "type":"Services"
        }
    ],
    "sg:phone":"+1 509 464 4444",
    "sg:postcode":"99208",
    "sg:province":"WA",
    "sg:tags":[
        "agency",
        "specialty"
    ],
    "wof:name":"Partnering Marketing Solutions",
    "wof:placetype":"venue"
},
  "geometry": {"coordinates":[-117.453836,47.75515],"type":"Point"}
}