{
  "type": "Feature",
  "properties": {
    "addr:full":"12951 Bel Red Rd Ste 120 Bellevue WA 98005",
    "addr:housenumber":"12951",
    "addr:postcode":"98005",
    "addr:street":"Bel Red Rd Ste 120",
    "iso:country":"US",
    "sg:address":"12951 Bel Red Rd Ste 120",
    "sg:city":"Bellevue",
    "sg:classifiers":[
        {
            "category":"Health Services",
            "subcategory":"Chiropractor",
            "type":"Services"
        }
    ],
    "sg:phone":"+1 425 455 3636",
    "sg:postcode":"98005",
    "sg:province":"WA",
    "wof:name":"Lockwood Chiropractic DC",
    "wof:placetype":"venue"
},
  "geometry": {"coordinates":[-122.167579,47.621303],"type":"Point"}
}