{
  "type": "Feature",
  "properties": {
    "addr:full":"290 Colman Dr Port Townsend WA 98368",
    "addr:housenumber":"290",
    "addr:postcode":"98368",
    "addr:street":"Colman Dr",
    "iso:country":"US",
    "sg:address":"290 Colman Dr",
    "sg:city":"Port Townsend",
    "sg:classifiers":[
        {
            "category":"Manufacturing",
            "subcategory":"Printing",
            "type":"Manufacturing & Wholesale Goods"
        }
    ],
    "sg:phone":"+1 360 379 5330",
    "sg:postcode":"98368",
    "sg:province":"WA",
    "sg:tags":[
        "publishing"
    ],
    "wof:name":"GKS Consultant Services Inc",
    "wof:placetype":"venue"
},
  "geometry": {"coordinates":[-122.87733,48.092706],"type":"Point"}
}