{
  "type": "Feature",
  "properties": {
    "addr:full":"2271 E White Fir Pl Freeland WA 98249",
    "addr:housenumber":"2271",
    "addr:postcode":"98249",
    "addr:street":"E White Fir Pl",
    "iso:country":"US",
    "sg:address":"2271 E White Fir Pl",
    "sg:city":"Freeland",
    "sg:classifiers":[
        {
            "category":"Communications",
            "subcategory":"Film & Video Production",
            "type":"Services"
        }
    ],
    "sg:phone":"+1 360 331 5056",
    "sg:postcode":"98249",
    "sg:province":"WA",
    "sg:tags":[
        "motion"
    ],
    "wof:name":"Firedancer Productions",
    "wof:placetype":"venue"
},
  "geometry": {"coordinates":[-122.492895,48.031299],"type":"Point"}
}