{
  "type": "Feature",
  "properties": {
    "addr:full":"5 W Poplar St Walla Walla WA 99362",
    "addr:housenumber":"5",
    "addr:postcode":"99362",
    "addr:street":"W Poplar St",
    "iso:country":"US",
    "sg:address":"5 W Poplar St",
    "sg:city":"Walla Walla",
    "sg:classifiers":[
        {
            "category":"Home & Garden",
            "subcategory":"Building Materials",
            "type":"Retail Goods"
        }
    ],
    "sg:phone":"+1 509 529 1290",
    "sg:postcode":"99362",
    "sg:province":"WA",
    "sg:tags":[
        "plate",
        "window",
        "repair",
        "auto",
        "glass"
    ],
    "wof:name":"Jim's Glass Shop",
    "wof:placetype":"venue"
},
  "geometry": {"coordinates":[-118.337958,46.064915],"type":"Point"}
}