{
  "type": "Feature",
  "properties": {
    "addr:full":"1380 112th Ave SE Bellevue WA 98004",
    "addr:housenumber":"1380",
    "addr:postcode":"98004",
    "addr:street":"112Th Ave Se",
    "iso:country":"US",
    "sg:address":"1380 112th Ave SE",
    "sg:city":"Bellevue",
    "sg:classifiers":[
        {
            "category":"Professional",
            "subcategory":"Engineering",
            "type":"Services"
        }
    ],
    "sg:phone":"+1 425 454 7137",
    "sg:postcode":"98004",
    "sg:province":"WA",
    "wof:name":"Johnson Consulting Engineers",
    "wof:placetype":"venue"
},
  "geometry": {"coordinates":[-122.190577,47.600515],"type":"Point"}
}