{
  "type": "Feature",
  "properties": {
    "addr:full":"200 W Thomas St Seattle WA 98119",
    "addr:housenumber":"200",
    "addr:postcode":"98119",
    "addr:street":"W Thomas St",
    "iso:country":"US",
    "sg:address":"200 W Thomas St",
    "sg:city":"Seattle",
    "sg:classifiers":[
        {
            "category":"Wholesale",
            "subcategory":"Construction Materials",
            "type":"Manufacturing & Wholesale Goods"
        }
    ],
    "sg:phone":"+1 206 284 1559",
    "sg:postcode":"98119",
    "sg:province":"WA",
    "sg:tags":[
        "mixed",
        "concrete-ready"
    ],
    "wof:name":"Case Mix Analysis Inc",
    "wof:placetype":"venue"
},
  "geometry": {"coordinates":[-122.359398,47.620972],"type":"Point"}
}