{
  "type": "Feature",
  "properties": {
    "addr:full":"14083 22nd Ave NE Seattle WA 98125",
    "addr:housenumber":"14083",
    "addr:postcode":"98125",
    "addr:street":"22Nd Ave Ne",
    "iso:country":"US",
    "sg:address":"14083 22nd Ave NE",
    "sg:city":"Seattle",
    "sg:classifiers":[
        {
            "category":"Professional",
            "type":"Services"
        }
    ],
    "sg:phone":"+1 206 362 0084",
    "sg:postcode":"98125",
    "sg:province":"WA",
    "wof:name":"Lyle T Abrahamson Co",
    "wof:placetype":"venue"
},
  "geometry": {"coordinates":[-122.305869,47.73186],"type":"Point"}
}