{
  "type": "Feature",
  "properties": {
    "addr:full":"206 Dubois Ct Vancouver WA 98661",
    "addr:housenumber":"206",
    "addr:postcode":"98661",
    "addr:street":"Dubois Ct",
    "iso:country":"US",
    "sg:address":"206 Dubois Ct",
    "sg:city":"Vancouver",
    "sg:classifiers":[
        {
            "category":"Professional",
            "type":"Services"
        }
    ],
    "sg:phone":"+1 360 696 2363",
    "sg:postcode":"98661",
    "sg:province":"WA",
    "wof:name":"Dorothy M Jackson",
    "wof:placetype":"venue"
},
  "geometry": {"coordinates":[-122.61645799999999,45.620585],"type":"Point"}
}