{
  "type": "Feature",
  "properties": {
    "addr:full":"437 Knapp Rd Colville WA 99114",
    "addr:housenumber":"437",
    "addr:postcode":"99114",
    "addr:street":"Knapp Rd",
    "iso:country":"US",
    "sg:address":"437 Knapp Rd",
    "sg:city":"Colville",
    "sg:classifiers":[
        {
            "category":"Wholesale",
            "subcategory":"Machinery & Supplies",
            "type":"Manufacturing & Wholesale Goods"
        }
    ],
    "sg:phone":"+1 509 684 4994",
    "sg:postcode":"99114",
    "sg:province":"WA",
    "sg:tags":[
        "equipment",
        "industrial"
    ],
    "wof:name":"Galli Woodcraft",
    "wof:placetype":"venue"
},
  "geometry": {"coordinates":[-117.846728,48.558287],"type":"Point"}
}