{
  "type": "Feature",
  "properties": {
    "addr:full":"9751 Fort Rd Wapato WA 98951",
    "addr:housenumber":"9751",
    "addr:postcode":"98951",
    "addr:street":"Fort Rd",
    "iso:country":"US",
    "sg:address":"9751 Fort Rd",
    "sg:city":"Wapato",
    "sg:classifiers":[
        {
            "category":"Education",
            "subcategory":"Special Training",
            "type":"Public Place"
        }
    ],
    "sg:phone":"+1 509 848 2081",
    "sg:postcode":"98951",
    "sg:province":"WA",
    "sg:tags":[
        "center"
    ],
    "wof:name":"Discovery Depot Learning Ctr",
    "wof:placetype":"venue"
},
  "geometry": {"coordinates":[-120.533057,46.375284],"type":"Point"}
}