{
  "type": "Feature",
  "properties": {
    "addr:full":"9015 Mount Hood Ave Vancouver WA 98664",
    "addr:housenumber":"9015",
    "addr:postcode":"98664",
    "addr:street":"Mount Hood Ave",
    "iso:country":"US",
    "sg:address":"9015 Mount Hood Ave",
    "sg:city":"Vancouver",
    "sg:classifiers":[
        {
            "category":"Home & Garden",
            "subcategory":"Garden Supply",
            "type":"Retail Goods"
        },
        {
            "category":"Building & Trades",
            "subcategory":"Landscaping Services",
            "type":"Services"
        }
    ],
    "sg:phone":"+1 360 695 1863",
    "sg:postcode":"98664",
    "sg:province":"WA",
    "sg:tags":[
        "sprinkler",
        "landscape"
    ],
    "wof:name":"Schaeffer's Sprinkler Systems",
    "wof:placetype":"venue"
},
  "geometry": {"coordinates":[-122.579448,45.610534],"type":"Point"}
}