{
  "type": "Feature",
  "properties": {
    "addr:full":"4926 26th Ave S Seattle WA 98108",
    "addr:housenumber":"4926",
    "addr:postcode":"98108",
    "addr:street":"26Th Ave S",
    "iso:country":"US",
    "sg:address":"4926 26th Ave S",
    "sg:city":"Seattle",
    "sg:classifiers":[
        {
            "category":"Professional",
            "subcategory":"Management & Consulting",
            "type":"Services"
        }
    ],
    "sg:phone":"+1 206 725 7648",
    "sg:postcode":"98108",
    "sg:province":"WA",
    "sg:tags":[
        "environmental",
        "consultant"
    ],
    "wof:name":"Trotter Fishery Science Conslt",
    "wof:placetype":"venue"
},
  "geometry": {"coordinates":[-122.299114,47.557628],"type":"Point"}
}