{
  "type": "Feature",
  "properties": {
    "addr:full":"6145 Steilacoom Blvd SW Ste F Lakewood WA 98499",
    "addr:housenumber":"6145",
    "addr:postcode":"98499",
    "addr:street":"Steilacoom Blvd Sw Ste F",
    "iso:country":"US",
    "sg:address":"6145 Steilacoom Blvd SW Ste F",
    "sg:city":"Lakewood",
    "sg:classifiers":[
        {
            "category":"Social Services",
            "subcategory":"Child Care",
            "type":"Services"
        },
        {
            "category":"Education",
            "subcategory":"Preschool",
            "type":"Public Place"
        }
    ],
    "sg:phone":"+1 253 589 3697",
    "sg:postcode":"98499",
    "sg:province":"WA",
    "sg:tags":[
        "day"
    ],
    "wof:name":"New Jerusalem Child Care Center",
    "wof:placetype":"venue"
},
  "geometry": {"coordinates":[-122.520661,47.176643],"type":"Point"}
}