{
  "type": "Feature",
  "properties": {
    "addr:full":"29224 52nd Ave S Auburn WA 98001",
    "addr:housenumber":"29224",
    "addr:postcode":"98001",
    "addr:street":"52Nd Ave S",
    "iso:country":"US",
    "sg:address":"29224 52nd Ave S",
    "sg:city":"Auburn",
    "sg:classifiers":[
        {
            "category":"Building & Trades",
            "subcategory":"Construction",
            "type":"Services"
        }
    ],
    "sg:phone":"+1 253 839 9007",
    "sg:postcode":"98001",
    "sg:province":"WA",
    "sg:tags":[
        "house",
        "nonresidential"
    ],
    "wof:name":"Advance Cnstr Gen Contrs",
    "wof:placetype":"venue"
},
  "geometry": {"coordinates":[-122.269355,47.339296],"type":"Point"}
}