{
  "type": "Feature",
  "properties": {
    "addr:full":"932 E Maple St Kent WA 98030",
    "addr:housenumber":"932",
    "addr:postcode":"98030",
    "addr:street":"E Maple St",
    "iso:country":"US",
    "sg:address":"932 E Maple St",
    "sg:city":"Kent",
    "sg:classifiers":[
        {
            "category":"Building & Trades",
            "subcategory":"Construction",
            "type":"Services"
        }
    ],
    "sg:phone":"+1 253 854 3012",
    "sg:postcode":"98030",
    "sg:province":"WA",
    "sg:tags":[
        "house",
        "contractor",
        "nonresidential"
    ],
    "wof:name":"Torr Construction Company",
    "wof:placetype":"venue"
},
  "geometry": {"coordinates":[-122.221362,47.371566],"type":"Point"}
}