{
  "type": "Feature",
  "properties": {
    "addr:full":"817 Pleasant St Walla Walla WA 99362",
    "addr:housenumber":"817",
    "addr:postcode":"99362",
    "addr:street":"Pleasant St",
    "iso:country":"US",
    "sg:address":"817 Pleasant St",
    "sg:city":"Walla Walla",
    "sg:classifiers":[
        {
            "category":"Food & Beverages",
            "subcategory":"Bakery",
            "type":"Retail Goods"
        }
    ],
    "sg:phone":"+1 509 527 3693",
    "sg:postcode":"99362",
    "sg:province":"WA",
    "wof:name":"Popular Donuts",
    "wof:placetype":"venue"
},
  "geometry": {"coordinates":[-118.317325,46.062149],"type":"Point"}
}