{
  "type": "Feature",
  "properties": {
    "addr:full":"1111 Northcliff Rd Shelton WA 98584",
    "addr:housenumber":"1111",
    "addr:postcode":"98584",
    "addr:street":"Northcliff Rd",
    "iso:country":"US",
    "sg:address":"1111 Northcliff Rd",
    "sg:city":"Shelton",
    "sg:classifiers":[
        {
            "category":"Health Services",
            "subcategory":"Chiropractor",
            "type":"Services"
        }
    ],
    "sg:phone":"+1 360 427 9013",
    "sg:postcode":"98584",
    "sg:province":"WA",
    "wof:name":"Soundview Chiropractic Inc",
    "wof:placetype":"venue"
},
  "geometry": {"coordinates":[-123.105763,47.22112],"type":"Point"}
}