{
  "type": "Feature",
  "properties": {
    "addr:full":"3625 E B St Tacoma WA 98404",
    "addr:housenumber":"3625",
    "addr:postcode":"98404",
    "addr:street":"E B St",
    "iso:country":"US",
    "sg:address":"3625 E B St",
    "sg:city":"Tacoma",
    "sg:classifiers":[
        {
            "category":"Social Services",
            "subcategory":"Job Training",
            "type":"Services"
        }
    ],
    "sg:phone":"+1 253 475 2507",
    "sg:postcode":"98404",
    "sg:province":"WA",
    "sg:tags":[
        "rehabilitation"
    ],
    "sg:website":"www.avamere.com",
    "wof:name":"Tacoma Rehab & Specialty Care",
    "wof:placetype":"venue"
},
  "geometry": {"coordinates":[-122.42965700000001,47.225953],"type":"Point"}
}