{
  "type": "Feature",
  "properties": {
    "addr:full":"215 SW 41st St Renton WA 98057",
    "addr:housenumber":"215",
    "addr:postcode":"98057",
    "addr:street":"Sw 41St St",
    "iso:country":"US",
    "sg:address":"215 SW 41st St",
    "sg:city":"Renton",
    "sg:classifiers":[
        {
            "category":"Wholesale",
            "subcategory":"Machinery & Supplies",
            "type":"Manufacturing & Wholesale Goods"
        }
    ],
    "sg:phone":"+1 425 251 5479",
    "sg:postcode":"98057",
    "sg:province":"WA",
    "sg:tags":[
        "equipment",
        "industrial"
    ],
    "wof:name":"Chandler and Associates",
    "wof:placetype":"venue"
},
  "geometry": {"coordinates":[-122.219936,47.443774],"type":"Point"}
}