{
  "type": "Feature",
  "properties": {
    "addr:full":"198 Kowntee St Stanwood WA 98282",
    "addr:housenumber":"198",
    "addr:postcode":"98282",
    "addr:street":"Kowntee St",
    "iso:country":"US",
    "sg:address":"198 Kowntee St",
    "sg:city":"Stanwood",
    "sg:classifiers":[
        {
            "category":"Shopping",
            "type":"Retail Goods"
        }
    ],
    "sg:phone":"+1 360 387 9994",
    "sg:postcode":"98282",
    "sg:province":"WA",
    "sg:tags":[
        "merchandise"
    ],
    "wof:name":"Proline Sign & Banner",
    "wof:placetype":"venue"
},
  "geometry": {"coordinates":[-122.474279,48.210924],"type":"Point"}
}