{
  "type": "Feature",
  "properties": {
    "addr:full":"6997 Patton Blvd NE Moses Lake WA 98837",
    "addr:housenumber":"6997",
    "addr:postcode":"98837",
    "addr:street":"Patton Blvd Ne",
    "iso:country":"US",
    "sg:address":"6997 Patton Blvd NE",
    "sg:city":"Moses Lake",
    "sg:classifiers":[
        {
            "category":"Government",
            "subcategory":"Office",
            "type":"Public Place"
        }
    ],
    "sg:phone":"+1 509 762 5304",
    "sg:postcode":"98837",
    "sg:province":"WA",
    "sg:tags":[
        "state",
        "program"
    ],
    "wof:name":"Port-Moses Lake Public Safety",
    "wof:placetype":"venue"
},
  "geometry": {"coordinates":[-119.322552,47.188327],"type":"Point"}
}