{
  "type": "Feature",
  "properties": {
    "addr:full":"10113 NE 379th St La Center WA 98629",
    "addr:housenumber":"10113",
    "addr:postcode":"98629",
    "addr:street":"Ne 379Th St",
    "iso:country":"US",
    "sg:address":"10113 NE 379th St",
    "sg:city":"La Center",
    "sg:classifiers":[
        {
            "category":"Farming",
            "subcategory":"Dairy Farm",
            "type":"Manufacturing & Wholesale Goods"
        }
    ],
    "sg:phone":"+1 360 263 3499",
    "sg:postcode":"98629",
    "sg:province":"WA",
    "wof:name":"Van Tol Dairy",
    "wof:placetype":"venue"
},
  "geometry": {"coordinates":[-122.56813200000001,45.895395],"type":"Point"}
}