{
  "type": "Feature",
  "properties": {
    "addr:full":"315 1st Avenue S Floor 3 Seattle WA 98104",
    "addr:housenumber":"315;3",
    "addr:postcode":"98104",
    "addr:street":"1St Avenue S Floor",
    "iso:country":"US",
    "sg:address":"315 1st Avenue S Floor 3",
    "sg:city":"Seattle",
    "sg:classifiers":[
        {
            "category":"Professional",
            "subcategory":"Computer Services",
            "type":"Services"
        }
    ],
    "sg:postcode":"98104",
    "sg:province":"WA",
    "sg:tags":[
        "travel",
        "airfare",
        "airline"
    ],
    "sg:website":"http://www.yapta.com",
    "wof:name":"Yapta",
    "wof:placetype":"venue"
},
  "geometry": {"coordinates":[-122.334265,47.599322],"type":"Point"}
}