{
  "type": "Feature",
  "properties": {
    "addr:full":"12292 Sidney Rd SW Port Orchard WA 98367",
    "addr:housenumber":"12292",
    "addr:postcode":"98367",
    "addr:street":"Sidney Rd Sw Port Orchard",
    "iso:country":"US",
    "sg:address":"12292 Sidney Rd SW",
    "sg:city":"Port Orchard",
    "sg:classifiers":[
        {
            "category":"Restaurant",
            "type":"Food & Drink"
        }
    ],
    "sg:phone":"+1 360 874 8336",
    "sg:postcode":"98367",
    "sg:province":"WA",
    "sg:tags":[
        "pizza"
    ],
    "wof:name":"Empire Pizza",
    "wof:placetype":"venue"
},
  "geometry": {"coordinates":[-122.66100299999999,47.437401],"type":"Point"}
}