{
  "type": "Feature",
  "properties": {
    "addr:full":"207 Washington St NE Olympia WA 98501",
    "addr:housenumber":"207",
    "addr:postcode":"98501",
    "addr:street":"Washington St Ne",
    "iso:country":"US",
    "sg:address":"207 Washington St NE",
    "sg:city":"Olympia",
    "sg:classifiers":[
        {
            "category":"Food & Beverages",
            "subcategory":"Specialty",
            "type":"Retail Goods"
        }
    ],
    "sg:phone":"+1 360 705 1867",
    "sg:postcode":"98501",
    "sg:province":"WA",
    "sg:tags":[
        "bars",
        "espresso"
    ],
    "wof:name":"Java Flow",
    "wof:placetype":"venue"
},
  "geometry": {"coordinates":[-122.900763,47.046625],"type":"Point"}
}