{
  "type": "Feature",
  "properties": {
    "addr:full":"206 Kirkland Ave Kirkland WA 98033",
    "addr:housenumber":"206",
    "addr:postcode":"98033",
    "addr:street":"Kirkland Ave",
    "iso:country":"US",
    "sg:address":"206 Kirkland Ave",
    "sg:city":"Kirkland",
    "sg:classifiers":[
        {
            "category":"Utilities",
            "subcategory":"Telephone",
            "type":"Services"
        }
    ],
    "sg:phone":"+1 425 803 3200",
    "sg:postcode":"98033",
    "sg:province":"WA",
    "sg:tags":[
        "communications"
    ],
    "wof:name":"Neptunecom Inc",
    "wof:placetype":"venue"
},
  "geometry": {"coordinates":[-122.20454599999999,47.675608],"type":"Point"}
}