{
  "type": "Feature",
  "properties": {
    "addr:full":"4962 Lower Crab Creek Rd SW Royal City WA 99357",
    "addr:housenumber":"4962",
    "addr:postcode":"99357",
    "addr:street":"Lower Crab Creek Rd Sw",
    "iso:country":"US",
    "sg:address":"4962 Lower Crab Creek Rd SW",
    "sg:city":"Royal City",
    "sg:classifiers":[
        {
            "category":"Building & Trades",
            "subcategory":"Construction",
            "type":"Services"
        }
    ],
    "sg:phone":"+1 509 346 2594",
    "sg:postcode":"99357",
    "sg:province":"WA",
    "sg:tags":[
        "excavation",
        "contractor"
    ],
    "wof:name":"Wyle Excavating",
    "wof:placetype":"venue"
},
  "geometry": {"coordinates":[-119.601096,46.840148],"type":"Point"}
}