{
  "type": "Feature",
  "properties": {
    "addr:full":"310 Blossom Way Yakima WA 98908",
    "addr:housenumber":"310",
    "addr:postcode":"98908",
    "addr:street":"Blossom Way",
    "iso:country":"US",
    "sg:address":"310 Blossom Way",
    "sg:city":"Yakima",
    "sg:classifiers":[
        {
            "category":"Health Services",
            "subcategory":"Medical Lab",
            "type":"Services"
        }
    ],
    "sg:phone":"+1 509 972 3102",
    "sg:postcode":"98908",
    "sg:province":"WA",
    "sg:tags":[
        "laboratory"
    ],
    "wof:name":"Mills Dental Laboratory",
    "wof:placetype":"venue"
},
  "geometry": {"coordinates":[-120.577866,46.642214],"type":"Point"}
}