{
  "type": "Feature",
  "properties": {
    "addr:full":"23217 NE 10th Pl Sammamish WA 98074",
    "addr:housenumber":"23217",
    "addr:postcode":"98074",
    "addr:street":"Ne 10Th Pl",
    "iso:country":"US",
    "sg:address":"23217 NE 10th Pl",
    "sg:city":"Sammamish",
    "sg:classifiers":[
        {
            "category":"Building & Trades",
            "subcategory":"Construction",
            "type":"Services"
        }
    ],
    "sg:phone":"+1 425 868 0950",
    "sg:postcode":"98074",
    "sg:province":"WA",
    "wof:name":"Plateau Fix-It",
    "wof:placetype":"venue"
},
  "geometry": {"coordinates":[-122.02972800000001,47.619507],"type":"Point"}
}