{
  "type": "Feature",
  "properties": {
    "iso:country":"US",
    "sg:address":"4404 230th Pl SW",
    "sg:city":"Mountlake Terrace",
    "sg:classifiers":[
        {
            "category":"Professional",
            "subcategory":"Business Services",
            "type":"Services"
        }
    ],
    "sg:phone":"+1 425 774 7335",
    "sg:postcode":"98043",
    "sg:province":"WA",
    "wof:name":"Jerry E Smith",
    "wof:placetype":"venue"
},
  "geometry": {"coordinates":[-122.294605,47.789671],"type":"Point"}
}