{
  "type": "Feature",
  "properties": {
    "addr:full":"14404 NE 84th St Vancouver WA 98682",
    "addr:housenumber":"14404",
    "addr:postcode":"98682",
    "addr:street":"Ne 84Th St",
    "iso:country":"US",
    "sg:address":"14404 NE 84th St",
    "sg:city":"Vancouver",
    "sg:classifiers":[
        {
            "category":"Manufacturing",
            "subcategory":"Textiles",
            "type":"Manufacturing & Wholesale Goods"
        }
    ],
    "sg:phone":"+1 360 892 2465",
    "sg:postcode":"98682",
    "sg:province":"WA",
    "sg:tags":[
        "knitting",
        "mills"
    ],
    "wof:name":"Nancy's Workshop",
    "wof:placetype":"venue"
},
  "geometry": {"coordinates":[-122.523346,45.683912],"type":"Point"}
}