{
  "type": "Feature",
  "properties": {
    "addr:full":"318 Glover St Twisp WA 98856",
    "addr:housenumber":"318",
    "addr:postcode":"98856",
    "addr:street":"Glover St",
    "iso:country":"US",
    "sg:address":"318 Glover St",
    "sg:city":"Twisp",
    "sg:classifiers":[
        {
            "category":"Real Estate",
            "subcategory":"Real Estate Agent",
            "type":"Services"
        }
    ],
    "sg:phone":"+1 509 997 9433",
    "sg:postcode":"98856",
    "sg:province":"WA",
    "wof:name":"Valleywide Real Estate",
    "wof:placetype":"venue"
},
  "geometry": {"coordinates":[-120.12120400000001,48.362786],"type":"Point"}
}