{
  "type": "Feature",
  "properties": {
    "addr:full":"14103 177th Ave NE Redmond WA 98052",
    "addr:housenumber":"14103",
    "addr:postcode":"98052",
    "addr:street":"177Th Ave Ne",
    "iso:country":"US",
    "sg:address":"14103 177th Ave NE",
    "sg:city":"Redmond",
    "sg:classifiers":[
        {
            "category":"Professional",
            "subcategory":"Management & Consulting",
            "type":"Services"
        }
    ],
    "sg:phone":"+1 425 814 0362",
    "sg:postcode":"98052",
    "sg:province":"WA",
    "sg:tags":[
        "business"
    ],
    "wof:name":"P&S Consulting",
    "wof:placetype":"venue"
},
  "geometry": {"coordinates":[-122.10255100000001,47.726655],"type":"Point"}
}