{
  "type": "Feature",
  "properties": {
    "addr:full":"2508 S Anderson St Kennewick WA 99337",
    "addr:housenumber":"2508",
    "addr:postcode":"99337",
    "addr:street":"S Anderson St",
    "iso:country":"US",
    "sg:address":"2508 S Anderson St",
    "sg:city":"Kennewick",
    "sg:classifiers":[
        {
            "category":"Building & Trades",
            "subcategory":"Equipment Rental",
            "type":"Services"
        }
    ],
    "sg:phone":"+1 509 582 4012",
    "sg:postcode":"99337",
    "sg:province":"WA",
    "wof:name":"Kit N Caboodle Homecare",
    "wof:placetype":"venue"
},
  "geometry": {"coordinates":[-119.15334,46.185143],"type":"Point"}
}