{
  "type": "Feature",
  "properties": {
    "addr:full":"11544 Whistle Lake Rd Anacortes WA 98221",
    "addr:housenumber":"11544",
    "addr:postcode":"98221",
    "addr:street":"Whistle Lake Rd",
    "iso:country":"US",
    "sg:address":"11544 Whistle Lake Rd",
    "sg:city":"Anacortes",
    "sg:classifiers":[
        {
            "category":"Building & Trades",
            "subcategory":"Construction",
            "type":"Services"
        }
    ],
    "sg:phone":"+1 360 293 4340",
    "sg:postcode":"98221",
    "sg:province":"WA",
    "sg:tags":[
        "contractor"
    ],
    "wof:name":"Schwabe Construction",
    "wof:placetype":"venue"
},
  "geometry": {"coordinates":[-122.603846,48.476298],"type":"Point"}
}