{
  "type": "Feature",
  "properties": {
    "addr:full":"2210 Port Industrial Rd Aberdeen WA 98520",
    "addr:housenumber":"2210",
    "addr:postcode":"98520",
    "addr:street":"Port Industrial Rd",
    "iso:country":"US",
    "sg:address":"2210 Port Industrial Rd",
    "sg:city":"Aberdeen",
    "sg:classifiers":[
        {
            "category":"Wholesale",
            "subcategory":"Beer",
            "type":"Manufacturing & Wholesale Goods"
        }
    ],
    "sg:phone":"+1 360 533 3960",
    "sg:postcode":"98520",
    "sg:province":"WA",
    "sg:tags":[
        "ale"
    ],
    "wof:name":"Independent Distributors Inc",
    "wof:placetype":"venue"
},
  "geometry": {"coordinates":[-123.84317900000001,46.966573],"type":"Point"}
}