{
  "type": "Feature",
  "properties": {
    "addr:full":"2715 Evening Glory Ct Clinton WA 98236",
    "addr:housenumber":"2715",
    "addr:postcode":"98236",
    "addr:street":"Evening Glory Ct",
    "iso:country":"US",
    "sg:address":"2715 Evening Glory Ct",
    "sg:city":"Clinton",
    "sg:classifiers":[
        {
            "category":"Manufacturing",
            "subcategory":"Furniture",
            "type":"Manufacturing & Wholesale Goods"
        }
    ],
    "sg:phone":"+1 360 321 8221",
    "sg:postcode":"98236",
    "sg:province":"WA",
    "sg:tags":[
        "household",
        "wood",
        "mfg"
    ],
    "wof:name":"Whidbey Design Works",
    "wof:placetype":"venue"
},
  "geometry": {"coordinates":[-122.465844,47.985485],"type":"Point"}
}