{
  "type": "Feature",
  "properties": {
    "iso:country":"US",
    "sg:address":"19612 Hwy 99",
    "sg:city":"Lynnwood",
    "sg:classifiers":[
        {
            "category":"Retail",
            "subcategory":"Auto Repair",
            "type":"Services"
        }
    ],
    "sg:phone":"+1 425 776 9039",
    "sg:postcode":"98036",
    "sg:province":"WA",
    "sg:tags":[
        "repairing",
        "automobile"
    ],
    "wof:name":"J C Auto Repair",
    "wof:placetype":"venue"
},
  "geometry": {"coordinates":[-122.316,47.820417],"type":"Point"}
}