{
  "type": "Feature",
  "properties": {
    "addr:full":"Gould Hall University of Washington Seattle WA 98105",
    "addr:postcode":"98105",
    "iso:country":"US",
    "sg:address":"Gould Hall University of Washington",
    "sg:city":"Seattle",
    "sg:classifiers":[
        {
            "category":"Coffee & Tea",
            "type":"Food & Drink"
        }
    ],
    "sg:postcode":"98105",
    "sg:province":"WA",
    "sg:website":"depts.washington.edu/archdept/fa...",
    "wof:name":"Design Coffee",
    "wof:placetype":"venue"
},
  "geometry": {"coordinates":[-122.31277,47.654911],"type":"Point"}
}