{
  "type": "Feature",
  "properties": {
    "addr:full":"635 SW 152nd St Burien WA 98166",
    "addr:housenumber":"635",
    "addr:postcode":"98166",
    "addr:street":"Sw 152Nd St",
    "iso:country":"US",
    "sg:address":"635 SW 152nd St",
    "sg:city":"Burien",
    "sg:classifiers":[
        {
            "category":"Restaurant",
            "type":"Food & Drink"
        }
    ],
    "sg:phone":"+1 206 243 6810",
    "sg:postcode":"98166",
    "sg:province":"WA",
    "sg:tags":[
        "drinking",
        "eating"
    ],
    "wof:name":"Ding How Restaurant Inc",
    "wof:placetype":"venue"
},
  "geometry": {"coordinates":[-122.343951,47.466718],"type":"Point"}
}