{
  "type": "Feature",
  "properties": {
    "addr:full":"10024 41st Ave NE Seattle WA 98125",
    "addr:housenumber":"10024",
    "addr:postcode":"98125",
    "addr:street":"41St Ave Ne",
    "iso:country":"US",
    "sg:address":"10024 41st Ave NE",
    "sg:city":"Seattle",
    "sg:classifiers":[
        {
            "category":"Health Services",
            "subcategory":"Medical Lab",
            "type":"Services"
        }
    ],
    "sg:phone":"+1 206 525 0386",
    "sg:postcode":"98125",
    "sg:province":"WA",
    "sg:tags":[
        "laboratory",
        "dental"
    ],
    "wof:name":"Allan Pinch Dental Lab",
    "wof:placetype":"venue"
},
  "geometry": {"coordinates":[-122.284262,47.701238],"type":"Point"}
}