{
  "type": "Feature",
  "properties": {
    "addr:full":"2849 NW 67th St Seattle WA 98117",
    "addr:housenumber":"2849",
    "addr:postcode":"98117",
    "addr:street":"Nw 67Th St",
    "iso:country":"US",
    "sg:address":"2849 NW 67th St",
    "sg:city":"Seattle",
    "sg:classifiers":[
        {
            "category":"Professional",
            "subcategory":"Computer Services",
            "type":"Services"
        }
    ],
    "sg:phone":"+1 206 781 2582",
    "sg:postcode":"98117",
    "sg:province":"WA",
    "sg:tags":[
        "related"
    ],
    "wof:name":"Cde Consulting LLC",
    "wof:placetype":"venue"
},
  "geometry": {"coordinates":[-122.39524,47.67724],"type":"Point"}
}