{
  "type": "Feature",
  "properties": {
    "addr:full":"2202 N 45th St Seattle WA 98103",
    "addr:housenumber":"2202",
    "addr:postcode":"98103",
    "addr:street":"N 45Th St",
    "iso:country":"US",
    "sg:address":"2202 N 45th St",
    "sg:city":"Seattle",
    "sg:classifiers":[
        {
            "category":"Arts & Performance",
            "subcategory":"Music",
            "type":"Entertainment"
        },
        {
            "category":"Bars & Pubs",
            "type":"Food & Drink"
        },
        {
            "category":"Arts & Performance",
            "subcategory":"Jazz & Blues",
            "type":"Entertainment"
        },
        {
            "category":"Bars & Pubs",
            "subcategory":"Lounge",
            "type":"Food & Drink"
        }
    ],
    "sg:phone":"+1 206 992 1120",
    "sg:postcode":"98103",
    "sg:province":"WA",
    "sg:tags":[
        "tapa",
        "venue"
    ],
    "sg:website":"seamonsterlounge.com/",
    "wof:name":"Seamonster Lounge",
    "wof:placetype":"venue"
},
  "geometry": {"coordinates":[-122.33235500000001,47.661394],"type":"Point"}
}