{
  "type": "Feature",
  "properties": {
    "iso:country":"US",
    "sg:address":"7001 162nd Pl NE",
    "sg:city":"Arlington",
    "sg:classifiers":[
        {
            "category":"Freight",
            "type":"Transportation"
        }
    ],
    "sg:phone":"+1 360 657 2462",
    "sg:postcode":"98223",
    "sg:province":"WA",
    "sg:tags":[
        "general"
    ],
    "wof:name":"Papas Lockers Self Storage",
    "wof:placetype":"venue"
},
  "geometry": {"coordinates":[-122.13559600000001,48.143692],"type":"Point"}
}