{
  "type": "Feature",
  "properties": {
    "addr:full":"3502 Little Alkali Rd Lacrosse WA 99143",
    "addr:housenumber":"3502",
    "addr:postcode":"99143",
    "addr:street":"Little Alkali Rd",
    "iso:country":"US",
    "sg:address":"3502 Little Alkali Rd",
    "sg:city":"Lacrosse",
    "sg:classifiers":[
        {
            "category":"Farming",
            "subcategory":"Farm",
            "type":"Manufacturing & Wholesale Goods"
        }
    ],
    "sg:phone":"+1 509 549 3398",
    "sg:postcode":"99143",
    "sg:province":"WA",
    "wof:name":"B&E Farms Inc",
    "wof:placetype":"venue"
},
  "geometry": {"coordinates":[-117.63566400000001,46.791204],"type":"Point"}
}