{
  "type": "Feature",
  "properties": {
    "addr:full":"401 S 1st St Mount Vernon WA 98273",
    "addr:housenumber":"401",
    "addr:postcode":"98273",
    "addr:street":"S 1St St",
    "iso:country":"US",
    "sg:address":"401 S 1st St",
    "sg:city":"Mount Vernon",
    "sg:classifiers":[
        {
            "category":"Manufacturing",
            "subcategory":"Jewelry",
            "type":"Manufacturing & Wholesale Goods"
        }
    ],
    "sg:phone":"+1 360 336 5234",
    "sg:postcode":"98273",
    "sg:province":"WA",
    "sg:website":"www.aucornerstone.com",
    "wof:name":"Au Cornerstone",
    "wof:placetype":"venue"
},
  "geometry": {"coordinates":[-122.337997,48.4202],"type":"Point"}
}