{
  "type": "Feature",
  "properties": {
    "addr:full":"18129 Fjord Dr NE Poulsbo WA 98370",
    "addr:postcode":"18129;98370",
    "addr:street":"Fjord Dr Ne",
    "iso:country":"US",
    "sg:address":"18129 Fjord Dr NE",
    "sg:city":"Poulsbo",
    "sg:classifiers":[
        {
            "category":"Recreation",
            "type":"Entertainment"
        },
        {
            "category":"Organizations",
            "subcategory":"Community Association",
            "type":"Services"
        }
    ],
    "sg:phone":"+1 360 779 9936",
    "sg:postcode":"98370",
    "sg:province":"WA",
    "sg:tags":[
        "club",
        "yacht"
    ],
    "sg:website":"www.poulsboyc.org",
    "wof:name":"Poulsbo Yacht Club",
    "wof:placetype":"venue"
},
  "geometry": {"coordinates":[-122.643663,47.72856],"type":"Point"}
}