{
  "type": "Feature",
  "properties": {
    "addr:full":"543 Main St Edmonds WA 98020",
    "addr:housenumber":"543",
    "addr:postcode":"98020",
    "addr:street":"Main St",
    "iso:country":"US",
    "sg:address":"543 Main St",
    "sg:city":"Edmonds",
    "sg:classifiers":[
        {
            "category":"Health Services",
            "subcategory":"Clinic",
            "type":"Services"
        }
    ],
    "sg:phone":"+1 206 286 7761",
    "sg:postcode":"98020",
    "sg:province":"WA",
    "wof:name":"Beverly Rogers Lmp",
    "wof:placetype":"venue"
},
  "geometry": {"coordinates":[-122.375798,47.810598],"type":"Point"}
}