{
  "type": "Feature",
  "properties": {
    "addr:full":"12616 NE 180th St Bothell WA 98011",
    "addr:housenumber":"12616",
    "addr:postcode":"98011",
    "addr:street":"Ne 180Th St",
    "iso:country":"US",
    "sg:address":"12616 NE 180th St",
    "sg:city":"Bothell",
    "sg:classifiers":[
        {
            "category":"Professional",
            "type":"Services"
        }
    ],
    "sg:phone":"+1 425 486 9627",
    "sg:postcode":"98011",
    "sg:province":"WA",
    "wof:name":"Resendiz",
    "wof:placetype":"venue"
},
  "geometry": {"coordinates":[-122.17040900000001,47.757929],"type":"Point"}
}