{
  "type": "Feature",
  "properties": {
    "addr:full":"Crossroads Mall 15600 NE 8th St Bellevue WA 98008",
    "addr:housenumber":"15600",
    "addr:postcode":"98008",
    "addr:street":"Ne 8Th St",
    "iso:country":"US",
    "sg:address":"Crossroads Mall 15600 NE 8th St",
    "sg:city":"Bellevue",
    "sg:classifiers":[
        {
            "category":"Ice Cream",
            "type":"Food & Drink"
        }
    ],
    "sg:phone":"+1 425 957 0333",
    "sg:postcode":"98008",
    "sg:province":"WA",
    "sg:tags":[
        "frozen",
        "yogurt"
    ],
    "sg:website":"www.coldstonecreamery.com",
    "wof:name":"Cold Stone Creamery",
    "wof:placetype":"venue"
},
  "geometry": {"coordinates":[-122.13242099999999,47.617033],"type":"Point"}
}