{
  "type": "Feature",
  "properties": {
    "addr:full":"7925 Ellison Loop NW Olympia WA 98502",
    "addr:housenumber":"7925",
    "addr:postcode":"olympia wa 98502",
    "addr:street":"Ellison Loop Nw",
    "iso:country":"US",
    "sg:address":"7925 Ellison Loop NW",
    "sg:city":"Olympia",
    "sg:classifiers":[
        {
            "category":"Professional",
            "type":"Services"
        }
    ],
    "sg:phone":"+1 360 866 9654",
    "sg:postcode":"98502",
    "sg:province":"WA",
    "wof:name":"Symbolicity",
    "wof:placetype":"venue"
},
  "geometry": {"coordinates":[-123.04751899999999,47.10733],"type":"Point"}
}