{
  "type": "Feature",
  "properties": {
    "addr:full":"204 Quince St NE Olympia WA 98506",
    "addr:housenumber":"204",
    "addr:postcode":"98506",
    "addr:street":"Quince St Ne",
    "iso:country":"US",
    "sg:address":"204 Quince St NE",
    "sg:city":"Olympia",
    "sg:classifiers":[
        {
            "category":"Health Services",
            "subcategory":"Clinic",
            "type":"Services"
        }
    ],
    "sg:phone":"+1 360 459 4281",
    "sg:postcode":"98506",
    "sg:province":"WA",
    "sg:tags":[
        "specialty",
        "outpatient"
    ],
    "wof:name":"Behavioral Science Institute",
    "wof:placetype":"venue"
},
  "geometry": {"coordinates":[-122.89014299999999,47.047361],"type":"Point"}
}