{
  "type": "Feature",
  "properties": {
    "iso:country":"US",
    "sg:address":"17330 117th Ave SE",
    "sg:city":"Renton",
    "sg:classifiers":[
        {
            "category":"Personal",
            "type":"Services"
        }
    ],
    "sg:phone":"+1 425 306 0852",
    "sg:postcode":"98058",
    "sg:province":"WA",
    "wof:name":"NW Auto Scene",
    "wof:placetype":"venue"
},
  "geometry": {"coordinates":[-122.184731,47.447817],"type":"Point"}
}