{
  "type": "Feature",
  "properties": {
    "addr:full":"4638 B St NW Auburn WA 98001",
    "addr:housenumber":"4638",
    "addr:postcode":"98001",
    "addr:street":"B St Nw",
    "iso:country":"US",
    "sg:address":"4638 B St NW",
    "sg:city":"Auburn",
    "sg:classifiers":[
        {
            "category":"Professional",
            "subcategory":"Computer Services",
            "type":"Services"
        }
    ],
    "sg:phone":"+1 253 334 8677",
    "sg:postcode":"98001",
    "sg:province":"WA",
    "sg:tags":[
        "related"
    ],
    "wof:name":"Quality Concepts",
    "wof:placetype":"venue"
},
  "geometry": {"coordinates":[-122.23230599999999,47.348761],"type":"Point"}
}