{
  "type": "Feature",
  "properties": {
    "addr:full":"1004 Ridgeway Dr Oak Harbor WA 98277",
    "addr:housenumber":"1004",
    "addr:postcode":"98277",
    "addr:street":"Ridgeway Dr",
    "iso:country":"US",
    "sg:address":"1004 Ridgeway Dr",
    "sg:city":"Oak Harbor",
    "sg:classifiers":[
        {
            "category":"Arts & Performance",
            "subcategory":"Theater",
            "type":"Entertainment"
        }
    ],
    "sg:phone":"+1 360 240 0252",
    "sg:postcode":"98277",
    "sg:province":"WA",
    "sg:tags":[
        "group"
    ],
    "wof:name":"Double A Azul Amor Productions",
    "wof:placetype":"venue"
},
  "geometry": {"coordinates":[-122.674144,48.279996],"type":"Point"}
}