{
  "type": "Feature",
  "properties": {
    "addr:full":"1014 S Scheuber Rd Centralia WA 98531",
    "addr:housenumber":"1014",
    "addr:postcode":"98531",
    "addr:street":"S Scheuber Rd",
    "iso:country":"US",
    "sg:address":"1014 S Scheuber Rd",
    "sg:city":"Centralia",
    "sg:classifiers":[
        {
            "category":"Travel",
            "subcategory":"Bed & Breakfast",
            "type":"Entertainment"
        }
    ],
    "sg:phone":"+1 360 736 8610",
    "sg:postcode":"98531",
    "sg:province":"WA",
    "sg:tags":[
        "rooming",
        "boarding",
        "house"
    ],
    "wof:name":"Jacobson Property Management",
    "wof:placetype":"venue"
},
  "geometry": {"coordinates":[-122.98689299999999,46.710984],"type":"Point"}
}