{
  "type": "Feature",
  "properties": {
    "addr:full":"2700 W Commodore Way # 202 Seattle WA 98199",
    "addr:housenumber":"2700",
    "addr:postcode":"98199",
    "addr:street":"W Commodore Way # 202",
    "iso:country":"US",
    "sg:address":"2700 W Commodore Way # 202",
    "sg:city":"Seattle",
    "sg:classifiers":[
        {
            "category":"Restaurant",
            "type":"Food & Drink"
        },
        {
            "category":"Food & Beverages",
            "subcategory":"Meat & Fish",
            "type":"Retail Goods"
        }
    ],
    "sg:phone":"+1 206 407 3499",
    "sg:postcode":"98199",
    "sg:province":"WA",
    "sg:tags":[
        "seafood",
        "seafood-wholesale",
        "market"
    ],
    "wof:name":"Pacifica Fish & Seafoods, Inc.",
    "wof:placetype":"venue"
},
  "geometry": {"coordinates":[-122.391052,47.662251],"type":"Point"}
}