{
  "type": "Feature",
  "properties": {
    "addr:full":"14230 160th Ave SE Renton WA 98059",
    "addr:housenumber":"14230",
    "addr:postcode":"98059",
    "addr:street":"160Th Ave Se",
    "iso:country":"US",
    "sg:address":"14230 160th Ave SE",
    "sg:city":"Renton",
    "sg:classifiers":[
        {
            "category":"Professional",
            "subcategory":"Computer Services",
            "type":"Services"
        }
    ],
    "sg:phone":"+1 425 235 7043",
    "sg:postcode":"98059",
    "sg:province":"WA",
    "sg:tags":[
        "programing",
        "custom"
    ],
    "wof:name":"Paynter Computer Consulting",
    "wof:placetype":"venue"
},
  "geometry": {"coordinates":[-122.126865,47.475567],"type":"Point"}
}