{
  "type": "Feature",
  "properties": {
    "addr:full":"2143 SW 305th St Federal Way WA 98023",
    "addr:housenumber":"2143",
    "addr:postcode":"98023",
    "addr:street":"Sw 305Th St",
    "iso:country":"US",
    "sg:address":"2143 SW 305th St",
    "sg:city":"Federal Way",
    "sg:classifiers":[
        {
            "category":"Building & Trades",
            "subcategory":"Cleaning & Sanitation",
            "type":"Services"
        }
    ],
    "sg:phone":"+1 253 874 3072",
    "sg:postcode":"98023",
    "sg:province":"WA",
    "sg:tags":[
        "maintenance"
    ],
    "wof:name":"Bolox Corp",
    "wof:placetype":"venue"
},
  "geometry": {"coordinates":[-122.362273,47.328263],"type":"Point"}
}