{
  "type": "Feature",
  "properties": {
    "addr:full":"3101 NE 145th St Apt E101 Seattle WA 98155",
    "addr:housenumber":"3101",
    "addr:postcode":"98155",
    "addr:street":"Ne 145Th St Apt E101",
    "iso:country":"US",
    "sg:address":"3101 NE 145th St Apt E101",
    "sg:city":"Seattle",
    "sg:classifiers":[
        {
            "category":"Communications",
            "subcategory":"Film & Video Production",
            "type":"Services"
        }
    ],
    "sg:phone":"+1 206 695 2174",
    "sg:postcode":"98155",
    "sg:province":"WA",
    "sg:tags":[
        "tv",
        "radio",
        "services-commercial",
        "companies-film"
    ],
    "wof:name":"Good Dan Evil Dan Productions",
    "wof:placetype":"venue"
},
  "geometry": {"coordinates":[-122.295151,47.733761],"type":"Point"}
}