{
  "type": "Feature",
  "properties": {
    "addr:full":"5400 Meeker Dr Unit 115 Kalama WA 98625",
    "addr:housenumber":"115",
    "addr:postcode":"5400;98625",
    "addr:street":"Meeker Dr Unit;Kalama",
    "iso:country":"US",
    "sg:address":"5400 Meeker Dr Unit 115",
    "sg:city":"Kalama",
    "sg:classifiers":[
        {
            "category":"Education",
            "subcategory":"Special Training",
            "type":"Public Place"
        }
    ],
    "sg:phone":"+1 360 673 4555",
    "sg:postcode":"98625",
    "sg:province":"WA",
    "sg:tags":[
        "aid",
        "instruction",
        "safety",
        "first"
    ],
    "wof:name":"Pro Training",
    "wof:placetype":"venue"
},
  "geometry": {"coordinates":[-122.850067,46.02684],"type":"Point"}
}