{
  "type": "Feature",
  "properties": {
    "addr:full":"217 Yale Ave Seattle WA 98109",
    "addr:housenumber":"217",
    "addr:postcode":"98109",
    "addr:street":"Yale Ave",
    "iso:country":"US",
    "sg:address":"217 Yale Ave",
    "sg:city":"Seattle",
    "sg:classifiers":[
        {
            "category":"Education",
            "subcategory":"Vocational School",
            "type":"Public Place"
        }
    ],
    "sg:postcode":"98109",
    "sg:province":"WA",
    "sg:tags":[
        "cooking"
    ],
    "wof:name":"Hipcooks",
    "wof:placetype":"venue"
},
  "geometry": {"coordinates":[-122.33051500000001,47.620069],"type":"Point"}
}