{
  "type": "Feature",
  "properties": {
    "addr:full":"5247 California Ave SW Seattle WA 98136",
    "addr:housenumber":"5247",
    "addr:postcode":"98136",
    "addr:street":"California Ave Sw",
    "iso:country":"US",
    "sg:address":"5247 California Ave SW",
    "sg:city":"Seattle",
    "sg:classifiers":[
        {
            "category":"Shopping",
            "subcategory":"Gifts & Souvenirs",
            "type":"Retail Goods"
        }
    ],
    "sg:phone":"+1 206 937 9609",
    "sg:postcode":"98136",
    "sg:province":"WA",
    "sg:tags":[
        "shop"
    ],
    "wof:name":"Cavvy's Market Place",
    "wof:placetype":"venue"
},
  "geometry": {"coordinates":[-122.38699800000001,47.556394],"type":"Point"}
}