{
  "type": "Feature",
  "properties": {
    "addr:full":"1425 S 32nd Ave Yakima WA 98902",
    "addr:housenumber":"1425",
    "addr:postcode":"98902",
    "addr:street":"S 32Nd Ave",
    "iso:country":"US",
    "sg:address":"1425 S 32nd Ave",
    "sg:city":"Yakima",
    "sg:classifiers":[
        {
            "category":"Shopping",
            "type":"Retail Goods"
        }
    ],
    "sg:phone":"+1 509 457 4775",
    "sg:postcode":"98902",
    "sg:province":"WA",
    "sg:tags":[
        "merchandise"
    ],
    "wof:name":"DWG Of Yakima",
    "wof:placetype":"venue"
},
  "geometry": {"coordinates":[-120.551508,46.57966],"type":"Point"}
}