{
  "type": "Feature",
  "properties": {
    "addr:full":"11265 57th Ave S Seattle WA 98178",
    "addr:housenumber":"11265",
    "addr:postcode":"98178",
    "addr:street":"57Th Ave S",
    "iso:country":"US",
    "sg:address":"11265 57th Ave S",
    "sg:city":"Seattle",
    "sg:classifiers":[
        {
            "category":"Organizations",
            "subcategory":"Membership Organization",
            "type":"Services"
        }
    ],
    "sg:phone":"+1 206 722 2868",
    "sg:postcode":"98178",
    "sg:province":"WA",
    "wof:name":"Sisters of Unconditional Love",
    "wof:placetype":"venue"
},
  "geometry": {"coordinates":[-122.261099,47.499333],"type":"Point"}
}