{
  "type": "Feature",
  "properties": {
    "addr:full":"41419 NE Bald Mountain Rd La Center WA 98629",
    "addr:housenumber":"41419",
    "addr:postcode":"98629",
    "addr:street":"Ne Bald Mountain Rd",
    "iso:country":"US",
    "sg:address":"41419 NE Bald Mountain Rd",
    "sg:city":"La Center",
    "sg:classifiers":[
        {
            "category":"Building & Trades",
            "subcategory":"Construction",
            "type":"Services"
        }
    ],
    "sg:phone":"+1 360 263 4183",
    "sg:postcode":"98629",
    "sg:province":"WA",
    "sg:tags":[
        "house"
    ],
    "wof:name":"Mountain View Construction",
    "wof:placetype":"venue"
},
  "geometry": {"coordinates":[-122.56703899999999,45.920871],"type":"Point"}
}