{
  "type": "Feature",
  "properties": {
    "addr:full":"420 Grove St Walla Walla WA 99362",
    "addr:housenumber":"420",
    "addr:postcode":"99362",
    "addr:street":"Grove St",
    "iso:country":"US",
    "sg:address":"420 Grove St",
    "sg:city":"Walla Walla",
    "sg:classifiers":[
        {
            "category":"Wholesale",
            "subcategory":"Toys & Hobbies",
            "type":"Manufacturing & Wholesale Goods"
        }
    ],
    "sg:phone":"+1 509 529 2337",
    "sg:postcode":"99362",
    "sg:province":"WA",
    "wof:name":"Fixcraft",
    "wof:placetype":"venue"
},
  "geometry": {"coordinates":[-118.32704200000001,46.065753],"type":"Point"}
}