{
  "type": "Feature",
  "properties": {
    "iso:country":"US",
    "sg:address":"2802 Wetmore Ave",
    "sg:city":"Everett",
    "sg:classifiers":[
        {
            "category":"Health Services",
            "subcategory":"Health Practitioner",
            "type":"Services"
        }
    ],
    "sg:phone":"+1 425 745 8856",
    "sg:postcode":"98201",
    "sg:province":"WA",
    "sg:tags":[
        "nurse",
        "registry"
    ],
    "sg:website":"www.vnsnw.com",
    "wof:name":"Visiting Nurse Svc",
    "wof:placetype":"venue"
},
  "geometry": {"coordinates":[-122.207279,47.979809],"type":"Point"}
}