{
  "type": "Feature",
  "properties": {
    "addr:full":"27932 123rd Pl SE Kent WA 98030",
    "addr:housenumber":"27932",
    "addr:postcode":"98030",
    "addr:street":"123Rd Pl Se",
    "iso:country":"US",
    "sg:address":"27932 123rd Pl SE",
    "sg:city":"Kent",
    "sg:classifiers":[
        {
            "category":"Shopping",
            "type":"Retail Goods"
        }
    ],
    "sg:phone":"+1 253 981 3460",
    "sg:postcode":"98030",
    "sg:province":"WA",
    "sg:tags":[
        "merchandise"
    ],
    "wof:name":"Sam S Bargains",
    "wof:placetype":"venue"
},
  "geometry": {"coordinates":[-122.17675800000001,47.351458],"type":"Point"}
}