{
  "type": "Feature",
  "properties": {
    "addr:full":"1451 Sandy Ln NE Lacey WA 98516",
    "addr:housenumber":"1451",
    "addr:postcode":"98516",
    "addr:street":"Sandy Ln Ne",
    "iso:country":"US",
    "sg:address":"1451 Sandy Ln NE",
    "sg:city":"Lacey",
    "sg:classifiers":[
        {
            "category":"Shopping",
            "subcategory":"Gifts & Souvenirs",
            "type":"Retail Goods"
        },
        {
            "category":"Manufacturing",
            "subcategory":"Retail Goods",
            "type":"Manufacturing & Wholesale Goods"
        }
    ],
    "sg:phone":"+1 360 456 2380",
    "sg:postcode":"98516",
    "sg:province":"WA",
    "sg:tags":[
        "shop",
        "giftware's-wholesale",
        "manufacturer"
    ],
    "wof:name":"A L B O E - Dutch Treats",
    "wof:placetype":"venue"
},
  "geometry": {"coordinates":[-122.797393,47.06111],"type":"Point"}
}