{
  "type": "Feature",
  "properties": {
    "addr:full":"1011 Western Ave Seattle WA 98104",
    "addr:housenumber":"1011",
    "addr:postcode":"98104",
    "addr:street":"Western Ave",
    "iso:country":"US",
    "sg:address":"1011 Western Ave",
    "sg:city":"Seattle",
    "sg:classifiers":[
        {
            "category":"Professional",
            "subcategory":"Research",
            "type":"Services"
        }
    ],
    "sg:phone":"+1 206 623 2744",
    "sg:postcode":"98104",
    "sg:province":"WA",
    "sg:tags":[
        "economic",
        "analysis"
    ],
    "wof:name":"Central Puget Sound Ecnmc Dev",
    "wof:placetype":"venue"
},
  "geometry": {"coordinates":[-122.338022,47.60483],"type":"Point"}
}