{
  "type": "Feature",
  "properties": {
    "addr:full":"9929 Kinder Rd NE Moses Lake WA 98837",
    "addr:housenumber":"9929",
    "addr:postcode":"98837",
    "addr:street":"Kinder Rd Ne",
    "iso:country":"US",
    "sg:address":"9929 Kinder Rd NE",
    "sg:city":"Moses Lake",
    "sg:classifiers":[
        {
            "category":"Freight",
            "type":"Transportation"
        }
    ],
    "sg:phone":"+1 509 765 7886",
    "sg:postcode":"98837",
    "sg:province":"WA",
    "sg:tags":[
        "commercial",
        "storage"
    ],
    "wof:name":"Hall's Self Storage",
    "wof:placetype":"venue"
},
  "geometry": {"coordinates":[-119.28010999999999,47.145715],"type":"Point"}
}