{
  "type": "Feature",
  "properties": {
    "iso:country":"US",
    "sg:address":"2730 NW Bliss Rd",
    "sg:city":"Vancouver",
    "sg:classifiers":[
        {
            "category":"Banks & Credit Unions",
            "subcategory":"Financial Services",
            "type":"Services"
        }
    ],
    "sg:phone":"+1 360 546 3633",
    "sg:postcode":"98685",
    "sg:province":"WA",
    "sg:tags":[
        "investor"
    ],
    "wof:name":"Ross Property Investments LLC",
    "wof:placetype":"venue"
},
  "geometry": {"coordinates":[-122.700078,45.726082],"type":"Point"}
}