{
  "type": "Feature",
  "properties": {
    "addr:full":"1080 W Ewing St Seattle WA 98119",
    "addr:housenumber":"1080",
    "addr:postcode":"98119",
    "addr:street":"W Ewing St",
    "iso:country":"US",
    "sg:address":"1080 W Ewing St",
    "sg:city":"Seattle",
    "sg:classifiers":[
        {
            "category":"Shopping",
            "subcategory":"Computers & Home Electronics",
            "type":"Retail Goods"
        }
    ],
    "sg:phone":"+1 206 352 3055",
    "sg:postcode":"98119",
    "sg:province":"WA",
    "sg:tags":[
        "software"
    ],
    "sg:website":"www.callvision.com",
    "wof:name":"CALLVISION.COM",
    "wof:placetype":"venue"
},
  "geometry": {"coordinates":[-122.368937,47.654388],"type":"Point"}
}