{
  "type": "Feature",
  "properties": {
    "addr:full":"1004 NE 72nd St Vancouver WA 98665",
    "addr:housenumber":"1004",
    "addr:postcode":"98665",
    "addr:street":"Ne 72Nd St",
    "iso:country":"US",
    "sg:address":"1004 NE 72nd St",
    "sg:city":"Vancouver",
    "sg:classifiers":[
        {
            "category":"Real Estate",
            "subcategory":"Developer",
            "type":"Services"
        }
    ],
    "sg:phone":"+1 360 993 2070",
    "sg:postcode":"98665",
    "sg:province":"WA",
    "sg:tags":[
        "mobile",
        "home"
    ],
    "wof:name":"Lazy Z Mobile Homes",
    "wof:placetype":"venue"
},
  "geometry": {"coordinates":[-122.661464,45.674159],"type":"Point"}
}