{
  "type": "Feature",
  "properties": {
    "addr:full":"8037 Incline Dr SE Olympia WA 98513",
    "addr:postcode":"8037;98513",
    "addr:street":"Incline Dr Se",
    "iso:country":"US",
    "sg:address":"8037 Incline Dr SE",
    "sg:city":"Olympia",
    "sg:classifiers":[
        {
            "category":"Professional",
            "subcategory":"Management & Consulting",
            "type":"Services"
        }
    ],
    "sg:phone":"+1 360 923 5899",
    "sg:postcode":"98513",
    "sg:province":"WA",
    "sg:tags":[
        "training"
    ],
    "wof:name":"Quest",
    "wof:placetype":"venue"
},
  "geometry": {"coordinates":[-122.77081800000001,46.9652],"type":"Point"}
}