{
  "type": "Feature",
  "properties": {
    "addr:full":"12547 Lake City Way Seattle WA 98125",
    "addr:housenumber":"12547",
    "addr:postcode":"98125",
    "addr:street":"Lake City Way",
    "iso:country":"US",
    "sg:address":"12547 Lake City Way",
    "sg:city":"Seattle",
    "sg:classifiers":[
        {
            "category":"Coffee & Tea",
            "type":"Food & Drink"
        },
        {
            "category":"Restaurant",
            "type":"Food & Drink"
        }
    ],
    "sg:phone":"+1 206 650 6621",
    "sg:postcode":"98125",
    "sg:province":"WA",
    "sg:tags":[
        "brunch",
        "breakfast"
    ],
    "sg:website":"Beancitycoffeeco.com",
    "wof:name":"BeanCity Coffee Co",
    "wof:placetype":"venue"
},
  "geometry": {"coordinates":[-122.295119,47.720681],"type":"Point"}
}