{
  "type": "Feature",
  "properties": {
    "addr:full":"2720 W Washington Ave Yakima WA 98903",
    "addr:housenumber":"2720",
    "addr:postcode":"98903",
    "addr:street":"W Washington Ave",
    "iso:country":"US",
    "sg:address":"2720 W Washington Ave",
    "sg:city":"Yakima",
    "sg:classifiers":[
        {
            "category":"Travel",
            "subcategory":"Travel Agent",
            "type":"Entertainment"
        }
    ],
    "sg:phone":"+1 509 248 5000",
    "sg:postcode":"98903",
    "sg:province":"WA",
    "sg:tags":[
        "agency"
    ],
    "wof:name":"American Express",
    "wof:placetype":"venue"
},
  "geometry": {"coordinates":[-120.542023,46.571798],"type":"Point"}
}