{
  "type": "Feature",
  "properties": {
    "addr:full":"2299 140th Ave NE Ste C Bellevue WA 98005",
    "addr:housenumber":"2299",
    "addr:postcode":"98005",
    "addr:street":"140Th Ave Ne Ste C",
    "iso:country":"US",
    "sg:address":"2299 140th Ave NE Ste C",
    "sg:city":"Bellevue",
    "sg:classifiers":[
        {
            "category":"Autos & Motor Vehicles",
            "subcategory":"Auto Supplies",
            "type":"Retail Goods"
        }
    ],
    "sg:phone":"+1 425 643 1446",
    "sg:postcode":"98005",
    "sg:province":"WA",
    "sg:tags":[
        "tire"
    ],
    "sg:website":"www.firestone.com",
    "wof:name":"Firestone Market Office",
    "wof:placetype":"venue"
},
  "geometry": {"coordinates":[-122.16999800000001,47.615002],"type":"Point"}
}