{
  "type": "Feature",
  "properties": {
    "addr:full":"915 S Laventure Rd Mount Vernon WA 98274",
    "addr:housenumber":"915",
    "addr:postcode":"98274",
    "addr:street":"S Laventure Rd",
    "iso:country":"US",
    "sg:address":"915 S Laventure Rd",
    "sg:city":"Mount Vernon",
    "sg:classifiers":[
        {
            "category":"Social Services",
            "subcategory":"Child Care",
            "type":"Services"
        }
    ],
    "sg:phone":"+1 360 424 5000",
    "sg:postcode":"98274",
    "sg:province":"WA",
    "sg:tags":[
        "center"
    ],
    "wof:name":"Wee Care Early Lrng & Day Care",
    "wof:placetype":"venue"
},
  "geometry": {"coordinates":[-122.313399,48.416286],"type":"Point"}
}