{
  "type": "Feature",
  "properties": {
    "addr:full":"11516 Lake City Way NE Seattle WA 98125",
    "addr:housenumber":"11516",
    "addr:postcode":"98125",
    "addr:street":"Lake City Way Ne",
    "iso:country":"US",
    "sg:address":"11516 Lake City Way NE",
    "sg:city":"Seattle",
    "sg:classifiers":[
        {
            "category":"Autos & Motor Vehicles",
            "subcategory":"Auto Supplies",
            "type":"Retail Goods"
        }
    ],
    "sg:phone":"+1 206 957 0777",
    "sg:postcode":"98125",
    "sg:province":"WA",
    "sg:tags":[
        "equipment",
        "racing",
        "car",
        "automobile"
    ],
    "wof:name":"Howe Automotive Technologies",
    "wof:placetype":"venue"
},
  "geometry": {"coordinates":[-122.298845,47.712883],"type":"Point"}
}