{
  "type": "Feature",
  "properties": {
    "addr:full":"7407 25th Ave NE Seattle WA 98115",
    "addr:housenumber":"7407",
    "addr:postcode":"98115",
    "addr:street":"25Th Ave Ne",
    "iso:country":"US",
    "sg:address":"7407 25th Ave NE",
    "sg:city":"Seattle",
    "sg:classifiers":[
        {
            "category":"Health Services",
            "subcategory":"Health Practitioner",
            "type":"Services"
        }
    ],
    "sg:phone":"+1 206 523 8642",
    "sg:postcode":"98115",
    "sg:province":"WA",
    "sg:tags":[
        "hypnotherapy",
        "hypnotist"
    ],
    "wof:name":"Steiner Bradley J",
    "wof:placetype":"venue"
},
  "geometry": {"coordinates":[-122.30076099999999,47.682085],"type":"Point"}
}