{
  "type": "Feature",
  "properties": {
    "addr:full":"6301 NE 124th St Vancouver WA 98686",
    "addr:housenumber":"6301",
    "addr:postcode":"98686",
    "addr:street":"Ne 124Th St",
    "iso:country":"US",
    "sg:address":"6301 NE 124th St",
    "sg:city":"Vancouver",
    "sg:classifiers":[
        {
            "category":"Manufacturing",
            "subcategory":"Signs",
            "type":"Manufacturing & Wholesale Goods"
        }
    ],
    "sg:phone":"+1 360 571 5885",
    "sg:postcode":"98686",
    "sg:province":"WA",
    "sg:website":"www.oldneonsigns.com",
    "wof:name":"Rocket City Neon",
    "wof:placetype":"venue"
},
  "geometry": {"coordinates":[-122.608035,45.711274],"type":"Point"}
}