{
  "type": "Feature",
  "properties": {
    "addr:full":"444 NE Ravenna Blvd Ste 400 Seattle WA 98115",
    "addr:housenumber":"444",
    "addr:postcode":"98115",
    "addr:street":"Ne Ravenna Blvd Ste 400",
    "iso:country":"US",
    "sg:address":"444 NE Ravenna Blvd Ste 400",
    "sg:city":"Seattle",
    "sg:classifiers":[
        {
            "category":"Real Estate",
            "subcategory":"Real Estate Services",
            "type":"Services"
        }
    ],
    "sg:phone":"+1 206 285 0664",
    "sg:postcode":"98115",
    "sg:province":"WA",
    "sg:tags":[
        "management",
        "property"
    ],
    "wof:name":"Uhlman Wes & Associates Inc",
    "wof:placetype":"venue"
},
  "geometry": {"coordinates":[-122.323334,47.678136],"type":"Point"}
}