{
  "type": "Feature",
  "properties": {
    "addr:full":"3725 40th Ave SW Seattle WA 98116",
    "addr:housenumber":"3725",
    "addr:postcode":"98116",
    "addr:street":"40Th Ave Sw",
    "iso:country":"US",
    "sg:address":"3725 40th Ave SW",
    "sg:city":"Seattle",
    "sg:classifiers":[
        {
            "category":"Retail",
            "subcategory":"Portrait Studio",
            "type":"Services"
        }
    ],
    "sg:phone":"+1 206 938 1766",
    "sg:postcode":"98116",
    "sg:province":"WA",
    "sg:tags":[
        "photo",
        "photography",
        "videography",
        "wedding"
    ],
    "wof:name":"Janet Sherwood Photography",
    "wof:placetype":"venue"
},
  "geometry": {"coordinates":[-122.382561,47.570963],"type":"Point"}
}