{
  "type": "Feature",
  "properties": {
    "addr:full":"1515 116th Ave NE Bellevue WA 98004",
    "addr:housenumber":"1515",
    "addr:postcode":"98004",
    "addr:street":"116Th Ave Ne",
    "iso:country":"US",
    "sg:address":"1515 116th Ave NE",
    "sg:city":"Bellevue",
    "sg:classifiers":[
        {
            "category":"Health Services",
            "subcategory":"Doctor",
            "type":"Services"
        }
    ],
    "sg:phone":"+1 425 454 6868",
    "sg:postcode":"98004",
    "sg:province":"WA",
    "sg:tags":[
        "clinic"
    ],
    "wof:name":"Bellevue Family Clinic",
    "wof:placetype":"venue"
},
  "geometry": {"coordinates":[-122.18574,47.625186],"type":"Point"}
}