{
  "type": "Feature",
  "properties": {
    "addr:full":"4977 Harbor Hills Dr Freeland WA 98249",
    "addr:housenumber":"4977",
    "addr:postcode":"98249",
    "addr:street":"Harbor Hills Dr",
    "iso:country":"US",
    "sg:address":"4977 Harbor Hills Dr",
    "sg:city":"Freeland",
    "sg:classifiers":[
        {
            "category":"Building & Trades",
            "subcategory":"Construction",
            "type":"Services"
        }
    ],
    "sg:phone":"+1 360 331 3690",
    "sg:postcode":"98249",
    "sg:province":"WA",
    "sg:tags":[
        "house"
    ],
    "wof:name":"Gerald A Wood Construction",
    "wof:placetype":"venue"
},
  "geometry": {"coordinates":[-122.53912200000001,48.031171],"type":"Point"}
}