{
  "type": "Feature",
  "properties": {
    "addr:full":"8222 NE 203rd St Kenmore WA 98028",
    "addr:housenumber":"8222",
    "addr:postcode":"98028",
    "addr:street":"Ne 203Rd St",
    "iso:country":"US",
    "sg:address":"8222 NE 203rd St",
    "sg:city":"Kenmore",
    "sg:classifiers":[
        {
            "category":"Manufacturing",
            "subcategory":"Toys & Sporting Goods",
            "type":"Manufacturing & Wholesale Goods"
        }
    ],
    "sg:phone":"+1 425 483 5016",
    "sg:postcode":"98028",
    "sg:province":"WA",
    "sg:tags":[
        "mfg"
    ],
    "wof:name":"Wachlin Folk Art",
    "wof:placetype":"venue"
},
  "geometry": {"coordinates":[-122.233064,47.775003],"type":"Point"}
}