{
  "type": "Feature",
  "properties": {
    "addr:full":"7411 144th St E Puyallup WA 98375",
    "addr:housenumber":"7411",
    "addr:postcode":"98375",
    "addr:street":"144Th St E",
    "iso:country":"US",
    "sg:address":"7411 144th St E",
    "sg:city":"Puyallup",
    "sg:classifiers":[
        {
            "category":"Organizations",
            "subcategory":"Religious Organization",
            "type":"Services"
        }
    ],
    "sg:phone":"+1 253 535 8919",
    "sg:postcode":"98375",
    "sg:province":"WA",
    "wof:name":"New Church Consulting",
    "wof:placetype":"venue"
},
  "geometry": {"coordinates":[-122.328813,47.125849],"type":"Point"}
}