{
  "type": "Feature",
  "properties": {
    "addr:full":"7742 32nd Ave NW Seattle WA 98117",
    "addr:housenumber":"7742",
    "addr:postcode":"98117",
    "addr:street":"32Nd Ave Nw",
    "iso:country":"US",
    "sg:address":"7742 32nd Ave NW",
    "sg:city":"Seattle",
    "sg:classifiers":[
        {
            "category":"Banks & Credit Unions",
            "subcategory":"Investment Brokerage",
            "type":"Services"
        }
    ],
    "sg:phone":"+1 206 782 5680",
    "sg:postcode":"98117",
    "sg:province":"WA",
    "sg:tags":[
        "trust"
    ],
    "wof:name":"Larry Clovis Trust",
    "wof:placetype":"venue"
},
  "geometry": {"coordinates":[-122.398303,47.685683],"type":"Point"}
}