{
  "type": "Feature",
  "properties": {
    "addr:full":"94 Lee Blvd Richland WA 99352",
    "addr:housenumber":"94",
    "addr:postcode":"99352",
    "addr:street":"Lee Blvd",
    "iso:country":"US",
    "sg:address":"94 Lee Blvd",
    "sg:city":"Richland",
    "sg:classifiers":[
        {
            "category":"Restaurant",
            "type":"Food & Drink"
        }
    ],
    "sg:phone":"+1 509 942 1914",
    "sg:postcode":"99352",
    "sg:province":"WA",
    "wof:name":"Aioli's",
    "wof:placetype":"venue"
},
  "geometry": {"coordinates":[-119.27322599999999,46.274901],"type":"Point"}
}