{
  "type": "Feature",
  "properties": {
    "addr:full":"3020 Conarty Rd Malaga WA 98828",
    "addr:housenumber":"3020",
    "addr:postcode":"98828",
    "addr:street":"Conarty Rd",
    "iso:country":"US",
    "sg:address":"3020 Conarty Rd",
    "sg:city":"Malaga",
    "sg:classifiers":[
        {
            "category":"Professional",
            "subcategory":"Engineering",
            "type":"Services"
        }
    ],
    "sg:phone":"+1 509 663 8148",
    "sg:postcode":"98828",
    "sg:province":"WA",
    "wof:name":"Chic Worthing Custom",
    "wof:placetype":"venue"
},
  "geometry": {"coordinates":[-120.224558,47.369491],"type":"Point"}
}