{
  "type": "Feature",
  "properties": {
    "addr:full":"3010 177th Ave NE Redmond WA 98052",
    "addr:housenumber":"3010",
    "addr:postcode":"98052",
    "addr:street":"177Th Ave Ne",
    "iso:country":"US",
    "sg:address":"3010 177th Ave NE",
    "sg:city":"Redmond",
    "sg:classifiers":[
        {
            "category":"Professional",
            "subcategory":"Employment Agencies",
            "type":"Services"
        }
    ],
    "sg:phone":"+1 425 885 7710",
    "sg:postcode":"98052",
    "sg:province":"WA",
    "sg:tags":[
        "employee",
        "benefit",
        "consulting"
    ],
    "wof:name":"David Nitsch",
    "wof:placetype":"venue"
},
  "geometry": {"coordinates":[-122.10362600000001,47.637189],"type":"Point"}
}