{
  "type": "Feature",
  "properties": {
    "addr:full":"13716 Lake City Way NE Seattle WA 98125",
    "addr:housenumber":"13716",
    "addr:postcode":"98125",
    "addr:street":"Lake City Way Ne",
    "iso:country":"US",
    "sg:address":"13716 Lake City Way NE",
    "sg:city":"Seattle",
    "sg:classifiers":[
        {
            "category":"Autos & Motor Vehicles",
            "subcategory":"Auto Supplies",
            "type":"Retail Goods"
        }
    ],
    "sg:phone":"+1 206 363 3122",
    "sg:postcode":"98125",
    "sg:province":"WA",
    "wof:name":"1st Tire & Wheel Center",
    "wof:placetype":"venue"
},
  "geometry": {"coordinates":[-122.292236,47.730016],"type":"Point"}
}