{
  "type": "Feature",
  "properties": {
    "addr:full":"915 Alvarado Ter Walla Walla WA 99362",
    "addr:housenumber":"915",
    "addr:postcode":"99362",
    "addr:street":"Alvarado Ter",
    "iso:country":"US",
    "sg:address":"915 Alvarado Ter",
    "sg:city":"Walla Walla",
    "sg:classifiers":[
        {
            "category":"Shopping",
            "type":"Retail Goods"
        }
    ],
    "sg:phone":"+1 509 525 1061",
    "sg:postcode":"99362",
    "sg:province":"WA",
    "sg:tags":[
        "merchandise"
    ],
    "wof:name":"Gonnamakeit (gmi)",
    "wof:placetype":"venue"
},
  "geometry": {"coordinates":[-118.327805,46.074833],"type":"Point"}
}