{
  "type": "Feature",
  "properties": {
    "addr:full":"14731 Aurora Avenue N Shoreline WA 98133",
    "addr:housenumber":"14731",
    "addr:postcode":"98133",
    "addr:street":"Aurora Avenue N",
    "iso:country":"US",
    "sg:address":"14731 Aurora Avenue N",
    "sg:city":"Shoreline",
    "sg:classifiers":[
        {
            "category":"Health Services",
            "subcategory":"Doctor",
            "type":"Services"
        }
    ],
    "sg:phone":"+1 206 365 0220",
    "sg:postcode":"98133",
    "sg:province":"WA",
    "wof:name":"Careplus Medical Centers",
    "wof:placetype":"venue"
},
  "geometry": {"coordinates":[-122.345321,47.73607],"type":"Point"}
}