{
  "type": "Feature",
  "properties": {
    "addr:full":"2300 SW 4th St Battle Ground WA 98604",
    "addr:housenumber":"2300",
    "addr:postcode":"98604",
    "addr:street":"Sw 4Th St",
    "iso:country":"US",
    "sg:address":"2300 SW 4th St",
    "sg:city":"Battle Ground",
    "sg:classifiers":[
        {
            "category":"Professional",
            "subcategory":"Computer Services",
            "type":"Services"
        }
    ],
    "sg:phone":"+1 360 666 4856",
    "sg:postcode":"98604",
    "sg:province":"WA",
    "sg:tags":[
        "datum"
    ],
    "wof:name":"Firefly Computer Graphics",
    "wof:placetype":"venue"
},
  "geometry": {"coordinates":[-122.561725,45.778215],"type":"Point"}
}