{
  "type": "Feature",
  "properties": {
    "addr:full":"685 Ocean Shores Blvd NW Ocean Shores WA 98569",
    "addr:housenumber":"685",
    "addr:postcode":"98569",
    "addr:street":"Ocean Shores Blvd Nw",
    "iso:country":"US",
    "sg:address":"685 Ocean Shores Blvd NW",
    "sg:city":"Ocean Shores",
    "sg:classifiers":[
        {
            "category":"Travel",
            "subcategory":"Hotels & Motels",
            "type":"Entertainment"
        }
    ],
    "sg:phone":"+1 360 289 4900",
    "sg:postcode":"98569",
    "sg:province":"WA",
    "sg:tags":[
        "operation"
    ],
    "wof:name":"Holiday Inn",
    "wof:placetype":"venue"
},
  "geometry": {"coordinates":[-124.166151,47.001512],"type":"Point"}
}