{
  "type": "Feature",
  "properties": {
    "addr:full":"8014 NE 13th Ave Vancouver WA 98665",
    "addr:housenumber":"8014",
    "addr:postcode":"98665",
    "addr:street":"Ne 13Th Ave",
    "iso:country":"US",
    "sg:address":"8014 NE 13th Ave",
    "sg:city":"Vancouver",
    "sg:classifiers":[
        {
            "category":"Banks & Credit Unions",
            "subcategory":"Bank",
            "type":"Services"
        }
    ],
    "sg:phone":"+1 360 699 4264",
    "sg:postcode":"98665",
    "sg:province":"WA",
    "sg:website":"www.firstindy.com",
    "wof:name":"First Independent Bank",
    "wof:placetype":"venue"
},
  "geometry": {"coordinates":[-122.6592,45.685791],"type":"Point"}
}