{
  "type": "Feature",
  "properties": {
    "addr:full":"2111 140th Ave NE Bellevue WA 98005",
    "addr:housenumber":"2111",
    "addr:postcode":"98005",
    "addr:street":"140Th Ave Ne",
    "iso:country":"US",
    "sg:address":"2111 140th Ave NE",
    "sg:city":"Bellevue",
    "sg:classifiers":[
        {
            "category":"Retail",
            "subcategory":"Auto Repair",
            "type":"Services"
        }
    ],
    "sg:phone":"+1 425 747 6044",
    "sg:postcode":"98005",
    "sg:province":"WA",
    "wof:name":"Strictly Bmw Independent Service",
    "wof:placetype":"venue"
},
  "geometry": {"coordinates":[-122.153999,47.629299],"type":"Point"}
}