{
  "type": "Feature",
  "properties": {
    "addr:full":"8031 16th Ave NW Seattle WA 98117",
    "addr:housenumber":"8031",
    "addr:postcode":"98117",
    "addr:street":"16Th Ave Nw",
    "iso:country":"US",
    "sg:address":"8031 16th Ave NW",
    "sg:city":"Seattle",
    "sg:classifiers":[
        {
            "category":"Professional",
            "subcategory":"Management & Consulting",
            "type":"Services"
        }
    ],
    "sg:phone":"+1 206 789 3751",
    "sg:postcode":"98117",
    "sg:province":"WA",
    "sg:tags":[
        "consultant",
        "restaurant"
    ],
    "sg:website":"http://www.wildginger.net",
    "wof:name":"Mann Building",
    "wof:placetype":"venue"
},
  "geometry": {"coordinates":[-122.377881,47.687452],"type":"Point"}
}