{
  "type": "Feature",
  "properties": {
    "addr:full":"11201 Whitcomb Pl Edmonds WA 98020",
    "addr:housenumber":"11201",
    "addr:postcode":"98020",
    "addr:street":"Whitcomb Pl",
    "iso:country":"US",
    "sg:address":"11201 Whitcomb Pl",
    "sg:city":"Edmonds",
    "sg:classifiers":[
        {
            "category":"Professional",
            "subcategory":"Computer Services",
            "type":"Services"
        }
    ],
    "sg:phone":"+1 425 712 9015",
    "sg:postcode":"98020",
    "sg:province":"WA",
    "sg:tags":[
        "consultant"
    ],
    "wof:name":"Pareto Corp",
    "wof:placetype":"venue"
},
  "geometry": {"coordinates":[-122.38297,47.798912],"type":"Point"}
}