{
  "type": "Feature",
  "properties": {
    "addr:full":"14923 Pacific Ave S Tacoma WA 98444",
    "addr:housenumber":"14923",
    "addr:postcode":"98444",
    "addr:street":"Pacific Ave S",
    "iso:country":"US",
    "sg:address":"14923 Pacific Ave S",
    "sg:city":"Tacoma",
    "sg:classifiers":[
        {
            "category":"Restaurant",
            "type":"Food & Drink"
        }
    ],
    "sg:menulink":"http://www.allmenus.com/wa/tacoma/78858-pizza-hut/menu/",
    "sg:phone":"+1 253 531 3800",
    "sg:postcode":"98444",
    "sg:province":"WA",
    "sg:tags":[
        "american",
        "pizza"
    ],
    "wof:name":"PIZZA HUT",
    "wof:placetype":"venue"
},
  "geometry": {"coordinates":[-122.434477,47.121159],"type":"Point"}
}