{
  "type": "Feature",
  "properties": {
    "addr:full":"8350 6th Ave Tacoma WA 98465",
    "addr:housenumber":"8350",
    "addr:postcode":"98465",
    "addr:street":"6Th Ave",
    "iso:country":"US",
    "sg:address":"8350 6th Ave",
    "sg:city":"Tacoma",
    "sg:classifiers":[
        {
            "category":"Freight",
            "type":"Transportation"
        }
    ],
    "sg:phone":"+1 253 460 0181",
    "sg:postcode":"98465",
    "sg:province":"WA",
    "sg:tags":[
        "operator",
        "local",
        "trucking"
    ],
    "wof:name":"Freeman Trucking",
    "wof:placetype":"venue"
},
  "geometry": {"coordinates":[-122.54846499999999,47.249533],"type":"Point"}
}