{
  "type": "Feature",
  "properties": {
    "addr:full":"1177 Andover Park W Seattle WA 98188",
    "addr:housenumber":"1177",
    "addr:postcode":"98188",
    "addr:street":"Andover Park W",
    "iso:country":"US",
    "sg:address":"1177 Andover Park W",
    "sg:city":"Seattle",
    "sg:classifiers":[
        {
            "category":"Wholesale",
            "subcategory":"Machinery & Supplies",
            "type":"Manufacturing & Wholesale Goods"
        },
        {
            "category":"Autos & Motor Vehicles",
            "subcategory":"Boat Sales",
            "type":"Retail Goods"
        }
    ],
    "sg:phone":"+1 206 575 0700",
    "sg:postcode":"98188",
    "sg:province":"WA",
    "sg:tags":[
        "ship",
        "marine",
        "chandler"
    ],
    "wof:name":"Harbor Ship Supply San Pedro",
    "wof:placetype":"venue"
},
  "geometry": {"coordinates":[-122.25460099999999,47.44354],"type":"Point"}
}