{
  "type": "Feature",
  "properties": {
    "addr:full":"430 91st Ave SE Everett WA 98205",
    "addr:housenumber":"430",
    "addr:postcode":"98205",
    "addr:street":"91St Ave Se",
    "iso:country":"US",
    "sg:address":"430 91st Ave SE",
    "sg:city":"Everett",
    "sg:classifiers":[
        {
            "category":"Manufacturing",
            "subcategory":"Printing",
            "type":"Manufacturing & Wholesale Goods"
        }
    ],
    "sg:phone":"+1 425 334 9317",
    "sg:postcode":"98205",
    "sg:province":"WA",
    "sg:tags":[
        "commercial",
        "typesetting"
    ],
    "wof:name":"Foster Press",
    "wof:placetype":"venue"
},
  "geometry": {"coordinates":[-122.108818,47.992356],"type":"Point"}
}