{
  "type": "Feature",
  "properties": {
    "addr:full":"253 Winslow Way W Bainbridge Isle WA 98110",
    "addr:housenumber":"253",
    "addr:postcode":"98110",
    "addr:street":"Winslow Way W;Isle",
    "iso:country":"US",
    "sg:address":"253 Winslow Way W",
    "sg:city":"Bainbridge Isle",
    "sg:classifiers":[
        {
            "category":"Professional",
            "subcategory":"Engineering",
            "type":"Services"
        }
    ],
    "sg:phone":"+1 206 842 7656",
    "sg:postcode":"98110",
    "sg:province":"WA",
    "sg:tags":[
        "engineer"
    ],
    "wof:name":"Dli Engineering",
    "wof:placetype":"venue"
},
  "geometry": {"coordinates":[-122.52269099999999,47.624834],"type":"Point"}
}