{
  "type": "Feature",
  "properties": {
    "addr:full":"7959 Berry Ridge Rd NW Bremerton WA 98383",
    "addr:housenumber":"7959",
    "addr:postcode":"98383",
    "addr:street":"Berry Ridge Rd Nw",
    "iso:country":"US",
    "sg:address":"7959 Berry Ridge Rd NW",
    "sg:city":"Bremerton",
    "sg:classifiers":[
        {
            "category":"Building & Trades",
            "subcategory":"Construction",
            "type":"Services"
        }
    ],
    "sg:phone":"+1 360 613 2443",
    "sg:postcode":"98383",
    "sg:province":"WA",
    "sg:tags":[
        "contractor"
    ],
    "wof:name":"Lighthouse Gutters",
    "wof:placetype":"venue"
},
  "geometry": {"coordinates":[-122.730035,47.634382],"type":"Point"}
}