{
  "type": "Feature",
  "properties": {
    "addr:full":"116 Warren Ave N Seattle WA 98109",
    "addr:housenumber":"116",
    "addr:postcode":"98109",
    "addr:street":"Warren Ave N",
    "iso:country":"US",
    "sg:address":"116 Warren Ave N",
    "sg:city":"Seattle",
    "sg:classifiers":[
        {
            "category":"Real Estate",
            "subcategory":"Real Estate Operator",
            "type":"Services"
        }
    ],
    "sg:phone":"+1 206 441 5867",
    "sg:postcode":"98109",
    "sg:province":"WA",
    "sg:tags":[
        "building",
        "apartment"
    ],
    "wof:name":"Hillyard Plaza Apartmts",
    "wof:placetype":"venue"
},
  "geometry": {"coordinates":[-122.354066,47.61957],"type":"Point"}
}