{
  "type": "Feature",
  "properties": {
    "addr:full":"4824 126th Pl SE Everett WA 98208",
    "addr:housenumber":"4824",
    "addr:postcode":"98208",
    "addr:street":"126Th Pl Se",
    "iso:country":"US",
    "sg:address":"4824 126th Pl SE",
    "sg:city":"Everett",
    "sg:classifiers":[
        {
            "category":"Wholesale",
            "subcategory":"Machinery & Supplies",
            "type":"Manufacturing & Wholesale Goods"
        }
    ],
    "sg:phone":"+1 425 385 3125",
    "sg:postcode":"98208",
    "sg:province":"WA",
    "sg:tags":[
        "equipment"
    ],
    "wof:name":"Gosch & Konishi General Co",
    "wof:placetype":"venue"
},
  "geometry": {"coordinates":[-122.166118,47.882671],"type":"Point"}
}