{
  "type": "Feature",
  "properties": {
    "addr:full":"3206 6th Ave Tacoma WA 98406",
    "addr:housenumber":"3206",
    "addr:postcode":"98406",
    "addr:street":"6Th Ave",
    "iso:country":"US",
    "sg:address":"3206 6th Ave",
    "sg:city":"Tacoma",
    "sg:classifiers":[
        {
            "category":"Retail",
            "subcategory":"Laundry & Dry Cleaning",
            "type":"Services"
        }
    ],
    "sg:phone":"+1 253 759 3319",
    "sg:postcode":"98406",
    "sg:province":"WA",
    "wof:name":"John Stokley",
    "wof:placetype":"venue"
},
  "geometry": {"coordinates":[-122.479163,47.255194],"type":"Point"}
}