{
  "type": "Feature",
  "properties": {
    "addr:full":"106 S Mill St Colfax WA 99111",
    "addr:housenumber":"106",
    "addr:postcode":"99111",
    "addr:street":"S Mill St",
    "iso:country":"US",
    "sg:address":"106 S Mill St",
    "sg:city":"Colfax",
    "sg:classifiers":[
        {
            "category":"Shopping",
            "type":"Retail Goods"
        }
    ],
    "sg:phone":"+1 509 397 2052",
    "sg:postcode":"99111",
    "sg:province":"WA",
    "sg:tags":[
        "merchandise",
        "monument"
    ],
    "wof:name":"Colfax Monument",
    "wof:placetype":"venue"
},
  "geometry": {"coordinates":[-117.363606,46.88081],"type":"Point"}
}