{
  "type": "Feature",
  "properties": {
    "addr:full":"7480 W Shelton Matlock Rd Shelton WA 98584",
    "addr:housenumber":"7480",
    "addr:postcode":"98584",
    "addr:street":"W;Matlock Rd",
    "iso:country":"US",
    "sg:address":"7480 W Shelton Matlock Rd",
    "sg:city":"Shelton",
    "sg:classifiers":[
        {
            "category":"Food & Beverages",
            "subcategory":"Groceries & Convenience Stores",
            "type":"Retail Goods"
        }
    ],
    "sg:phone":"+1 360 427 5527",
    "sg:postcode":"98584",
    "sg:province":"WA",
    "wof:name":"Dayton Grocery",
    "wof:placetype":"venue"
},
  "geometry": {"coordinates":[-123.233445,47.226757],"type":"Point"}
}