{
  "type": "Feature",
  "properties": {
    "addr:full":"2616 NE Kresky Ave Chehalis WA 98532",
    "addr:housenumber":"2616",
    "addr:postcode":"98532",
    "addr:street":"Ne Kresky Ave",
    "iso:country":"US",
    "sg:address":"2616 NE Kresky Ave",
    "sg:city":"Chehalis",
    "sg:classifiers":[
        {
            "category":"Social Services",
            "type":"Services"
        }
    ],
    "sg:phone":"+1 360 807 6187",
    "sg:postcode":"98532",
    "sg:province":"WA",
    "sg:tags":[
        "worker"
    ],
    "wof:name":"Families In Crisis",
    "wof:placetype":"venue"
},
  "geometry": {"coordinates":[-122.955386,46.692498],"type":"Point"}
}