{
  "type": "Feature",
  "properties": {
    "addr:full":"345 Factory Pl N Renton WA 98055",
    "addr:housenumber":"345",
    "addr:postcode":"98055",
    "addr:street":"Factory Pl N",
    "iso:country":"US",
    "sg:address":"345 Factory Pl N",
    "sg:city":"Renton",
    "sg:classifiers":[
        {
            "category":"Retail",
            "subcategory":"Auto Repair",
            "type":"Services"
        }
    ],
    "sg:phone":"+1 425 228 4262",
    "sg:postcode":"98055",
    "sg:province":"WA",
    "wof:name":"Friedel's Service Inc",
    "wof:placetype":"venue"
},
  "geometry": {"coordinates":[-122.197998,47.488499],"type":"Point"}
}