{
  "type": "Feature",
  "properties": {
    "addr:full":"9479 Bayshore Dr NW Silverdale WA 98383",
    "addr:housenumber":"9479",
    "addr:postcode":"98383",
    "addr:street":"Bayshore Dr Nw",
    "iso:country":"US",
    "sg:address":"9479 Bayshore Dr NW",
    "sg:city":"Silverdale",
    "sg:classifiers":[
        {
            "category":"Organizations",
            "subcategory":"Labor Organization",
            "type":"Services"
        }
    ],
    "sg:phone":"+1 360 692 2322",
    "sg:postcode":"98383",
    "sg:province":"WA",
    "wof:name":"Central Kitsap Education Assn",
    "wof:placetype":"venue"
},
  "geometry": {"coordinates":[-122.69393100000001,47.647241],"type":"Point"}
}