{
  "type": "Feature",
  "properties": {
    "addr:full":"10 N Post St Spokane WA 99201",
    "addr:housenumber":"10",
    "addr:postcode":"99201",
    "addr:street":"St",
    "iso:country":"US",
    "sg:address":"10 N Post St",
    "sg:city":"Spokane",
    "sg:classifiers":[
        {
            "category":"Professional",
            "subcategory":"Management & Consulting",
            "type":"Services"
        }
    ],
    "sg:phone":"+1 509 747 8031",
    "sg:postcode":"99201",
    "sg:province":"WA",
    "sg:tags":[
        "construction"
    ],
    "wof:name":"KJM & Assoc",
    "wof:placetype":"venue"
},
  "geometry": {"coordinates":[-117.42343099999999,47.657868],"type":"Point"}
}