{
  "type": "Feature",
  "properties": {
    "iso:country":"US",
    "sg:address":"1660 S Columbian Way",
    "sg:city":"Seattle",
    "sg:classifiers":[
        {
            "category":"Professional",
            "subcategory":"Management & Consulting",
            "type":"Services"
        }
    ],
    "sg:phone":"+1 206 764 2730",
    "sg:postcode":"98108",
    "sg:province":"WA",
    "sg:tags":[
        "physical",
        "commercial",
        "research"
    ],
    "wof:name":"Seattle Institute For Bio Rsrc",
    "wof:placetype":"venue"
},
  "geometry": {"coordinates":[-122.311781,47.562289],"type":"Point"}
}