{
  "type": "Feature",
  "properties": {
    "addr:full":"3183 E Beach Rd Port Angeles WA 98363",
    "addr:housenumber":"3183",
    "addr:postcode":"98363",
    "addr:street":"E Beach Rd",
    "iso:country":"US",
    "sg:address":"3183 E Beach Rd",
    "sg:city":"Port Angeles",
    "sg:classifiers":[
        {
            "category":"Travel",
            "subcategory":"Hotels & Motels",
            "type":"Entertainment"
        }
    ],
    "sg:phone":"+1 360 928 3325",
    "sg:postcode":"98363",
    "sg:province":"WA",
    "sg:tags":[
        "resort",
        "gift"
    ],
    "wof:name":"Log Cabin Resort Inc",
    "wof:placetype":"venue"
},
  "geometry": {"coordinates":[-123.79086599999999,48.095493],"type":"Point"}
}