{
  "type": "Feature",
  "properties": {
    "addr:full":"152 SW 153rd St Burien WA 98166",
    "addr:housenumber":"152",
    "addr:postcode":"98166",
    "addr:street":"Sw 153Rd St",
    "iso:country":"US",
    "sg:address":"152 SW 153rd St",
    "sg:city":"Burien",
    "sg:classifiers":[
        {
            "category":"Shopping",
            "subcategory":"Used Merchandise",
            "type":"Retail Goods"
        }
    ],
    "sg:phone":"+1 206 838 3734",
    "sg:postcode":"98166",
    "sg:province":"WA",
    "sg:tags":[
        "shop",
        "thrift"
    ],
    "wof:name":"Frenzi Inc",
    "wof:placetype":"venue"
},
  "geometry": {"coordinates":[-122.33558499999999,47.466056],"type":"Point"}
}