{
  "type": "Feature",
  "properties": {
    "addr:full":"10209 Bridgeport Way SW Lakewood WA 98499",
    "addr:housenumber":"10209",
    "addr:postcode":"98499",
    "addr:street":"Bridgeport Way Sw",
    "iso:country":"US",
    "sg:address":"10209 Bridgeport Way SW",
    "sg:city":"Lakewood",
    "sg:classifiers":[
        {
            "category":"Real Estate",
            "subcategory":"Architect",
            "type":"Services"
        }
    ],
    "sg:phone":"+1 253 581 7239",
    "sg:postcode":"98499",
    "sg:province":"WA",
    "wof:name":"Guerrero James Archt",
    "wof:placetype":"venue"
},
  "geometry": {"coordinates":[-122.507846,47.165364],"type":"Point"}
}