{
  "type": "Feature",
  "properties": {
    "addr:full":"4213 Rural Ave Bellingham WA 98226",
    "addr:housenumber":"4213",
    "addr:postcode":"98226",
    "addr:street":"Rural Ave",
    "iso:country":"US",
    "sg:address":"4213 Rural Ave",
    "sg:city":"Bellingham",
    "sg:classifiers":[
        {
            "category":"Health Services",
            "subcategory":"Clinic",
            "type":"Services"
        }
    ],
    "sg:phone":"+1 360 671 8388",
    "sg:postcode":"98226",
    "sg:province":"WA",
    "sg:tags":[
        "home",
        "care"
    ],
    "wof:name":"Visiting Angels Living Assista",
    "wof:placetype":"venue"
},
  "geometry": {"coordinates":[-122.579238,48.791519],"type":"Point"}
}