{
  "type": "Feature",
  "properties": {
    "iso:country":"US",
    "sg:address":"1348 Lake Whatcom Blvd",
    "sg:city":"Bellingham",
    "sg:classifiers":[
        {
            "category":"Communications",
            "subcategory":"Radio Station",
            "type":"Services"
        }
    ],
    "sg:phone":"+1 360 595 9606",
    "sg:postcode":"98229",
    "sg:province":"WA",
    "sg:tags":[
        "broadcast"
    ],
    "wof:name":"Mji Broadcasting Inc",
    "wof:placetype":"venue"
},
  "geometry": {"coordinates":[-122.396835,48.74755],"type":"Point"}
}