{
  "type": "Feature",
  "properties": {
    "addr:full":"766 Garfield Street #304 Seattle WA 98109",
    "addr:housenumber":"766",
    "addr:postcode":"98109",
    "addr:street":"Garfield Street # 304",
    "iso:country":"US",
    "sg:address":"766 Garfield Street #304",
    "sg:city":"Seattle",
    "sg:classifiers":[
        {
            "category":"Professional",
            "type":"Services"
        }
    ],
    "sg:phone":"+1 206 551 5595",
    "sg:postcode":"98109",
    "sg:province":"WA",
    "sg:website":"www.killorn.com",
    "wof:name":"koMEDIA Graphic Design",
    "wof:placetype":"venue"
},
  "geometry": {"coordinates":[-122.341846,47.633004],"type":"Point"}
}