{
  "type": "Feature",
  "properties": {
    "addr:full":"97 Pike Street Seattle WA 98101",
    "addr:housenumber":"97",
    "addr:postcode":"98101",
    "addr:street":"Pike Street",
    "iso:country":"US",
    "sg:address":"97 Pike Street",
    "sg:city":"Seattle",
    "sg:classifiers":[
        {
            "category":"Arts & Performance",
            "subcategory":"Art Gallery",
            "type":"Entertainment"
        }
    ],
    "sg:phone":"+1 206 623 7538",
    "sg:postcode":"98101",
    "sg:province":"WA",
    "sg:website":"www.artstallgallery.com",
    "wof:name":"Art Stall Gallery",
    "wof:placetype":"venue"
},
  "geometry": {"coordinates":[-122.34009399999999,47.608862],"type":"Point"}
}