{
  "type": "Feature",
  "properties": {
    "addr:full":"1325 SE Tech Center Dr Vancouver WA 98683",
    "addr:housenumber":"1325",
    "addr:postcode":"98683",
    "addr:street":"Se Tech Center Dr",
    "iso:country":"US",
    "sg:address":"1325 SE Tech Center Dr",
    "sg:city":"Vancouver",
    "sg:classifiers":[
        {
            "category":"Banks & Credit Unions",
            "subcategory":"Bank",
            "type":"Services"
        }
    ],
    "sg:phone":"+1 360 604 8470",
    "sg:postcode":"98683",
    "sg:province":"WA",
    "sg:tags":[
        "loan",
        "broker"
    ],
    "sg:website":"www.ameriquest.com",
    "wof:name":"Ameriquest Mortgage Company",
    "wof:placetype":"venue"
},
  "geometry": {"coordinates":[-122.499881,45.611916],"type":"Point"}
}