{
  "type": "Feature",
  "properties": {
    "addr:full":"1523 W Indiana Ave Spokane WA 99205",
    "addr:housenumber":"1523",
    "addr:postcode":"99205",
    "addr:street":"W Indiana Ave",
    "iso:country":"US",
    "sg:address":"1523 W Indiana Ave",
    "sg:city":"Spokane",
    "sg:classifiers":[
        {
            "category":"Organizations",
            "subcategory":"Religious Organization",
            "type":"Services"
        }
    ],
    "sg:phone":"+1 509 324 1706",
    "sg:postcode":"99205",
    "sg:province":"WA",
    "sg:tags":[
        "church"
    ],
    "sg:website":"www.johnglake.com",
    "wof:name":"John G Lake Healing Ministries",
    "wof:placetype":"venue"
},
  "geometry": {"coordinates":[-117.435231,47.674859],"type":"Point"}
}