{
  "type": "Feature",
  "properties": {
    "addr:full":"321 E 25th St Tacoma WA 98421",
    "addr:housenumber":"321",
    "addr:postcode":"98421",
    "addr:street":"E 25Th St",
    "iso:country":"US",
    "sg:address":"321 E 25th St",
    "sg:city":"Tacoma",
    "sg:classifiers":[
        {
            "category":"Building & Trades",
            "subcategory":"Construction",
            "type":"Services"
        }
    ],
    "sg:phone":"+1 253 939 0355",
    "sg:postcode":"98421",
    "sg:province":"WA",
    "sg:tags":[
        "contractor"
    ],
    "wof:name":"Bathcrest",
    "wof:placetype":"venue"
},
  "geometry": {"coordinates":[-122.42948199999999,47.239703],"type":"Point"}
}