{
  "type": "Feature",
  "properties": {
    "addr:full":"323 Queen Anne Ave N Seattle WA 98109",
    "addr:housenumber":"323",
    "addr:postcode":"98109",
    "addr:street":"Queen Anne Ave N",
    "iso:country":"US",
    "sg:address":"323 Queen Anne Ave N",
    "sg:city":"Seattle",
    "sg:classifiers":[
        {
            "category":"Building & Trades",
            "subcategory":"Construction",
            "type":"Services"
        }
    ],
    "sg:phone":"+1 206 352 7028",
    "sg:postcode":"98109",
    "sg:province":"WA",
    "sg:tags":[
        "hanging",
        "contractor"
    ],
    "wof:name":"Ransoms Pro Painters",
    "wof:placetype":"venue"
},
  "geometry": {"coordinates":[-122.356807,47.621845],"type":"Point"}
}