{
  "type": "Feature",
  "properties": {
    "addr:full":"16505 4th Ave S Seattle WA 98148",
    "addr:housenumber":"16505",
    "addr:postcode":"98148",
    "addr:street":"4Th Ave S",
    "iso:country":"US",
    "sg:address":"16505 4th Ave S",
    "sg:city":"Seattle",
    "sg:classifiers":[
        {
            "category":"Insurance",
            "subcategory":"Insurance Agent",
            "type":"Services"
        }
    ],
    "sg:phone":"+1 206 246 7045",
    "sg:postcode":"98148",
    "sg:province":"WA",
    "sg:tags":[
        "medical"
    ],
    "wof:name":"Advisory Svc Hlth Plan Cmprson",
    "wof:placetype":"venue"
},
  "geometry": {"coordinates":[-122.328802,47.452475],"type":"Point"}
}