{
  "type": "Feature",
  "properties": {
    "addr:full":"11541 26th Ave NE Seattle WA 98125",
    "addr:housenumber":"11541",
    "addr:postcode":"98125",
    "addr:street":"26Th Ave Ne",
    "iso:country":"US",
    "sg:address":"11541 26th Ave NE",
    "sg:city":"Seattle",
    "sg:classifiers":[
        {
            "category":"Retail",
            "subcategory":"Car Wash",
            "type":"Services"
        }
    ],
    "sg:phone":"+1 206 417 3703",
    "sg:postcode":"98125",
    "sg:province":"WA",
    "sg:tags":[
        "automobile",
        "detail",
        "clean"
    ],
    "wof:name":"Detail Building & Design Inc",
    "wof:placetype":"venue"
},
  "geometry": {"coordinates":[-122.300397,47.713719],"type":"Point"}
}