{
  "type": "Feature",
  "properties": {
    "addr:full":"5700 34th Ave NW Seattle WA 98107",
    "addr:housenumber":"5700",
    "addr:postcode":"98107",
    "addr:street":"34Th Ave Nw",
    "iso:country":"US",
    "sg:address":"5700 34th Ave NW",
    "sg:city":"Seattle",
    "sg:classifiers":[
        {
            "category":"Shopping",
            "subcategory":"Crafts & Fabrics",
            "type":"Retail Goods"
        }
    ],
    "sg:phone":"+1 206 783 0405",
    "sg:postcode":"98107",
    "sg:province":"WA",
    "sg:tags":[
        "sewing"
    ],
    "wof:name":"Mickeys Knits",
    "wof:placetype":"venue"
},
  "geometry": {"coordinates":[-122.40111,47.671299],"type":"Point"}
}