{
  "type": "Feature",
  "properties": {
    "addr:full":"6523 Latona Ave NE Seattle WA 98115",
    "addr:housenumber":"6523",
    "addr:postcode":"98115",
    "addr:street":"Latona Ave Ne",
    "iso:country":"US",
    "sg:address":"6523 Latona Ave NE",
    "sg:city":"Seattle",
    "sg:classifiers":[
        {
            "category":"Professional",
            "subcategory":"Management & Consulting",
            "type":"Services"
        }
    ],
    "sg:phone":"+1 206 525 1641",
    "sg:postcode":"98115",
    "sg:province":"WA",
    "sg:tags":[
        "business"
    ],
    "wof:name":"Russell Hanbey Consulting",
    "wof:placetype":"venue"
},
  "geometry": {"coordinates":[-122.327062,47.677152],"type":"Point"}
}