{
  "type": "Feature",
  "properties": {
    "addr:full":"1241 Bridle Dr SE Olympia WA 98501",
    "addr:housenumber":"1241",
    "addr:postcode":"98501",
    "addr:street":"Bridle Dr Se",
    "iso:country":"US",
    "sg:address":"1241 Bridle Dr SE",
    "sg:city":"Olympia",
    "sg:classifiers":[
        {
            "category":"Building & Trades",
            "subcategory":"Construction",
            "type":"Services"
        }
    ],
    "sg:phone":"+1 360 352 2664",
    "sg:postcode":"98501",
    "sg:province":"WA",
    "sg:tags":[
        "residential"
    ],
    "wof:name":"Copeland Construction",
    "wof:placetype":"venue"
},
  "geometry": {"coordinates":[-122.885783,46.977599],"type":"Point"}
}