{
  "type": "Feature",
  "properties": {
    "addr:full":"5009 196th St SW Lynnwood WA 98036",
    "addr:housenumber":"5009",
    "addr:postcode":"98036",
    "addr:street":"196Th St Sw",
    "iso:country":"US",
    "sg:address":"5009 196th St SW",
    "sg:city":"Lynnwood",
    "sg:classifiers":[
        {
            "category":"Home & Garden",
            "subcategory":"Building Materials",
            "type":"Retail Goods"
        },
        {
            "category":"Wholesale",
            "subcategory":"Painting Supplies",
            "type":"Manufacturing & Wholesale Goods"
        }
    ],
    "sg:phone":"+1 425 672 2551",
    "sg:postcode":"98036",
    "sg:province":"WA",
    "sg:tags":[
        "paint"
    ],
    "wof:name":"Kelly-Moore Paint Co",
    "wof:placetype":"venue"
},
  "geometry": {"coordinates":[-122.300982,47.821182],"type":"Point"}
}