{
  "type": "Feature",
  "properties": {
    "addr:full":"515 Wilderness Way Oak Harbor WA 98277",
    "addr:housenumber":"515",
    "addr:postcode":"98277",
    "addr:street":"Wilderness Way",
    "iso:country":"US",
    "sg:address":"515 Wilderness Way",
    "sg:city":"Oak Harbor",
    "sg:classifiers":[
        {
            "category":"Retail",
            "subcategory":"Repair Shop",
            "type":"Services"
        }
    ],
    "sg:phone":"+1 360 678 6814",
    "sg:postcode":"98277",
    "sg:province":"WA",
    "wof:name":"Red Cat Crafts",
    "wof:placetype":"venue"
},
  "geometry": {"coordinates":[-122.586395,48.342579],"type":"Point"}
}