{
  "type": "Feature",
  "properties": {
    "iso:country":"US",
    "sg:address":"1546 State Rte 6",
    "sg:city":"Raymond",
    "sg:classifiers":[
        {
            "category":"Farming",
            "subcategory":"Dairy Farm",
            "type":"Manufacturing & Wholesale Goods"
        }
    ],
    "sg:phone":"+1 360 942 5950",
    "sg:postcode":"98577",
    "sg:province":"WA",
    "wof:name":"Oxbow Dairy",
    "wof:placetype":"venue"
},
  "geometry": {"coordinates":[-123.718029,46.677988],"type":"Point"}
}