{
  "type": "Feature",
  "properties": {
    "addr:full":"12044 Slater Ave NE Kirkland WA 98034",
    "addr:housenumber":"12044",
    "addr:postcode":"98034",
    "addr:street":"Slater Ave Ne",
    "iso:country":"US",
    "sg:address":"12044 Slater Ave NE",
    "sg:city":"Kirkland",
    "sg:classifiers":[
        {
            "category":"Building & Trades",
            "subcategory":"Construction",
            "type":"Services"
        }
    ],
    "sg:phone":"+1 425 823 7454",
    "sg:postcode":"98034",
    "sg:province":"WA",
    "sg:tags":[
        "nonresidential"
    ],
    "wof:name":"Maintenance Plus",
    "wof:placetype":"venue"
},
  "geometry": {"coordinates":[-122.170436,47.709518],"type":"Point"}
}