{
  "type": "Feature",
  "properties": {
    "addr:full":"3815 E Trent Ave Spokane WA 99212",
    "addr:housenumber":"3815",
    "addr:postcode":"99212",
    "addr:street":"E Trent Ave",
    "iso:country":"US",
    "sg:address":"3815 E Trent Ave",
    "sg:city":"Spokane",
    "sg:classifiers":[
        {
            "category":"Building & Trades",
            "subcategory":"Equipment Rental",
            "type":"Services"
        }
    ],
    "sg:phone":"+1 509 535 1300",
    "sg:postcode":"99212",
    "sg:province":"WA",
    "wof:name":"Nbi-Usa LLC",
    "wof:placetype":"venue"
},
  "geometry": {"coordinates":[-117.353233,47.670835],"type":"Point"}
}