{
  "type": "Feature",
  "properties": {
    "iso:country":"US",
    "sg:address":"513 Anthes Ave",
    "sg:city":"Langley",
    "sg:classifiers":[
        {
            "category":"Travel",
            "subcategory":"Hotels & Motels",
            "type":"Entertainment"
        }
    ],
    "sg:phone":"+1 360 221 9121",
    "sg:postcode":"98260",
    "sg:province":"WA",
    "sg:tags":[
        "breakfast",
        "accommodation",
        "bed"
    ],
    "wof:name":"Heron Haven Bed & Breakfast",
    "wof:placetype":"venue"
},
  "geometry": {"coordinates":[-122.409622,48.036528],"type":"Point"}
}