{
  "type": "Feature",
  "properties": {
    "addr:full":"13622 Whites Rd Arlington WA 98223",
    "addr:housenumber":"13622",
    "addr:postcode":"98223",
    "addr:street":"Whites Rd",
    "iso:country":"US",
    "sg:address":"13622 Whites Rd",
    "sg:city":"Arlington",
    "sg:classifiers":[
        {
            "category":"Professional",
            "subcategory":"Business Services",
            "type":"Services"
        }
    ],
    "sg:phone":"+1 360 435 9208",
    "sg:postcode":"98223",
    "sg:province":"WA",
    "wof:name":"Fries Design",
    "wof:placetype":"venue"
},
  "geometry": {"coordinates":[-122.039862,48.179186],"type":"Point"}
}