{
  "type": "Feature",
  "properties": {
    "addr:full":"7517 166th Ave NE Redmond WA 98052",
    "addr:housenumber":"7517",
    "addr:postcode":"98052",
    "addr:street":"166Th Ave Ne",
    "iso:country":"US",
    "sg:address":"7517 166th Ave NE",
    "sg:city":"Redmond",
    "sg:classifiers":[
        {
            "category":"Shopping",
            "subcategory":"Shoes",
            "type":"Retail Goods"
        }
    ],
    "sg:phone":"+1 425 556 0383",
    "sg:postcode":"98052",
    "sg:province":"WA",
    "sg:website":"www.footzone.com",
    "wof:name":"Foot Zone",
    "wof:placetype":"venue"
},
  "geometry": {"coordinates":[-122.118921,47.670925],"type":"Point"}
}