{
  "type": "Feature",
  "properties": {
    "addr:full":"7724 13th Avenue NW Seattle WA 98117",
    "addr:housenumber":"7724",
    "addr:postcode":"98117",
    "addr:street":"13Th Avenue Nw",
    "iso:country":"US",
    "sg:address":"7724 13th Avenue NW",
    "sg:city":"Seattle",
    "sg:classifiers":[
        {
            "category":"Real Estate",
            "subcategory":"Real Estate Services",
            "type":"Services"
        },
        {
            "category":"Professional",
            "subcategory":"Business Services",
            "type":"Services"
        }
    ],
    "sg:phone":"+1 206 784 4964",
    "sg:postcode":"98117",
    "sg:province":"WA",
    "sg:tags":[
        "home",
        "inspector",
        "inspection"
    ],
    "wof:name":"Erickson David W Inspections",
    "wof:placetype":"venue"
},
  "geometry": {"coordinates":[-122.37257,47.686309],"type":"Point"}
}