{
  "type": "Feature",
  "properties": {
    "addr:full":"3411 169th Pl NE Arlington WA 98223",
    "addr:housenumber":"3411",
    "addr:postcode":"98223",
    "addr:street":"169Th Pl Ne",
    "iso:country":"US",
    "sg:address":"3411 169th Pl NE",
    "sg:city":"Arlington",
    "sg:classifiers":[
        {
            "category":"Restaurant",
            "type":"Food & Drink"
        }
    ],
    "sg:menulink":"http://www.allmenus.com/wa/marysville/78032-papa-murphys/menu/",
    "sg:phone":"+1 360 651 1969",
    "sg:postcode":"98223",
    "sg:province":"WA",
    "sg:tags":[
        "american",
        "pizza"
    ],
    "wof:name":"Papa Murphy's",
    "wof:placetype":"venue"
},
  "geometry": {"coordinates":[-122.184164,48.150361],"type":"Point"}
}