{
  "type": "Feature",
  "properties": {
    "addr:full":"884 Quail Ln Oak Harbor WA 98277",
    "addr:housenumber":"884",
    "addr:postcode":"98277",
    "addr:street":"Quail Ln",
    "iso:country":"US",
    "sg:address":"884 Quail Ln",
    "sg:city":"Oak Harbor",
    "sg:classifiers":[
        {
            "category":"Personal",
            "type":"Services"
        }
    ],
    "sg:phone":"+1 360 675 5624",
    "sg:postcode":"98277",
    "sg:province":"WA",
    "wof:name":"Kneaing Theraputic Massage",
    "wof:placetype":"venue"
},
  "geometry": {"coordinates":[-122.661528,48.312336],"type":"Point"}
}