{
  "type": "Feature",
  "properties": {
    "addr:full":"4009 E Meridian Ave Puyallup WA 98373",
    "addr:housenumber":"4009",
    "addr:postcode":"98373",
    "addr:street":"E Meridian Ave",
    "iso:country":"US",
    "sg:address":"4009 E Meridian Ave",
    "sg:city":"Puyallup",
    "sg:classifiers":[
        {
            "category":"Professional",
            "type":"Services"
        }
    ],
    "sg:phone":"+1 253 841 0765",
    "sg:postcode":"98373",
    "sg:province":"WA",
    "wof:name":"Paper Zone",
    "wof:placetype":"venue"
},
  "geometry": {"coordinates":[-122.292963,47.153461],"type":"Point"}
}