{
  "type": "Feature",
  "properties": {
    "addr:full":"441 W Sharp Ave Spokane WA 99201",
    "addr:housenumber":"441",
    "addr:postcode":"99201",
    "addr:street":"W Sharp Ave",
    "iso:country":"US",
    "sg:address":"441 W Sharp Ave",
    "sg:city":"Spokane",
    "sg:classifiers":[
        {
            "category":"Professional",
            "subcategory":"Business Services",
            "type":"Services"
        }
    ],
    "sg:phone":"+1 509 326 9128",
    "sg:postcode":"99201",
    "sg:province":"WA",
    "sg:tags":[
        "equipment",
        "microfilming"
    ],
    "wof:name":"NORTHWEST Microfilm Inc",
    "wof:placetype":"venue"
},
  "geometry": {"coordinates":[-117.420283,47.669159],"type":"Point"}
}