{
  "type": "Feature",
  "properties": {
    "iso:country":"US",
    "sg:address":"2 Union St",
    "sg:city":"Seattle",
    "sg:classifiers":[
        {
            "category":"Professional",
            "subcategory":"Management & Consulting",
            "type":"Services"
        }
    ],
    "sg:phone":"+1 206 720 1000",
    "sg:postcode":"98101",
    "sg:province":"WA",
    "wof:name":"Mavirex Corporation",
    "wof:placetype":"venue"
},
  "geometry": {"coordinates":[-122.340935,47.607065],"type":"Point"}
}