{
  "type": "Feature",
  "properties": {
    "addr:full":"2457 Kamber Rd Bellevue WA 98007",
    "addr:housenumber":"2457",
    "addr:postcode":"98007",
    "addr:street":"Kamber Rd",
    "iso:country":"US",
    "sg:address":"2457 Kamber Rd",
    "sg:city":"Bellevue",
    "sg:classifiers":[
        {
            "category":"Retail",
            "subcategory":"Auto Repair",
            "type":"Services"
        }
    ],
    "sg:phone":"+1 425 746 4373",
    "sg:postcode":"98007",
    "sg:province":"WA",
    "sg:tags":[
        "automotive",
        "wrecker",
        "towing"
    ],
    "sg:website":"www.crossroadstowing.com",
    "wof:name":"Crossroads Towing",
    "wof:placetype":"venue"
},
  "geometry": {"coordinates":[-122.154201,47.587943],"type":"Point"}
}