{
  "type": "Feature",
  "properties": {
    "addr:full":"450 W Enterprise Rd Shelton WA 98584",
    "addr:housenumber":"450",
    "addr:postcode":"98584",
    "addr:street":"W Enterprise Rd",
    "iso:country":"US",
    "sg:address":"450 W Enterprise Rd",
    "sg:city":"Shelton",
    "sg:classifiers":[
        {
            "category":"Manufacturing",
            "subcategory":"Tools & Machinery",
            "type":"Manufacturing & Wholesale Goods"
        }
    ],
    "sg:phone":"+1 360 427 1418",
    "sg:postcode":"98584",
    "sg:province":"WA",
    "sg:tags":[
        "control"
    ],
    "sg:website":"www.compudas.com",
    "wof:name":"Compu Das Corp",
    "wof:placetype":"venue"
},
  "geometry": {"coordinates":[-123.139646,47.237649],"type":"Point"}
}