{
  "type": "Feature",
  "properties": {
    "iso:country":"US",
    "sg:address":"11335 Durland Pl NE",
    "sg:city":"Seattle",
    "sg:classifiers":[
        {
            "category":"Building & Trades",
            "subcategory":"Landscaping Services",
            "type":"Services"
        }
    ],
    "sg:phone":"+1 206 365 4378",
    "sg:postcode":"98125",
    "sg:province":"WA",
    "sg:tags":[
        "architect",
        "landscape",
        "maintenance"
    ],
    "wof:name":"Shamrock Landscaping & Nursery",
    "wof:placetype":"venue"
},
  "geometry": {"coordinates":[-122.279685,47.712008],"type":"Point"}
}