{
  "type": "Feature",
  "properties": {
    "addr:full":"410 S 12th Ave Yakima WA 98902",
    "addr:housenumber":"410",
    "addr:postcode":"98902",
    "addr:street":"S 12Th Ave",
    "iso:country":"US",
    "sg:address":"410 S 12th Ave",
    "sg:city":"Yakima",
    "sg:classifiers":[
        {
            "category":"Health Services",
            "subcategory":"Dentist",
            "type":"Services"
        }
    ],
    "sg:phone":"+1 509 452 7115",
    "sg:postcode":"98902",
    "sg:province":"WA",
    "wof:name":"Iasella John M DDS MS",
    "wof:placetype":"venue"
},
  "geometry": {"coordinates":[-120.525032,46.59385],"type":"Point"}
}