{
  "type": "Feature",
  "properties": {
    "addr:full":"12303 NE 130th Ln Ste 450 Kirkland WA 98034",
    "addr:housenumber":"12303",
    "addr:postcode":"98034",
    "addr:street":"Ne 130Th Ln Ste 450",
    "iso:country":"US",
    "sg:address":"12303 NE 130th Ln Ste 450",
    "sg:city":"Kirkland",
    "sg:classifiers":[
        {
            "category":"Manufacturing",
            "subcategory":"Chemicals & Compounds",
            "type":"Manufacturing & Wholesale Goods"
        }
    ],
    "sg:phone":"+1 425 899 5000",
    "sg:postcode":"98034",
    "sg:province":"WA",
    "sg:tags":[
        "electrolysis"
    ],
    "wof:name":"Aesthetic Litetouch Inc",
    "wof:placetype":"venue"
},
  "geometry": {"coordinates":[-122.177059,47.716721],"type":"Point"}
}