{
  "type": "Feature",
  "properties": {
    "addr:full":"14224 146th Pl SE Renton WA 98059",
    "addr:housenumber":"14224",
    "addr:postcode":"98059",
    "addr:street":"146Th Pl Se",
    "iso:country":"US",
    "sg:address":"14224 146th Pl SE",
    "sg:city":"Renton",
    "sg:classifiers":[
        {
            "category":"Government",
            "subcategory":"Office",
            "type":"Public Place"
        }
    ],
    "sg:phone":"+1 425 455 5404",
    "sg:postcode":"98059",
    "sg:province":"WA",
    "sg:tags":[
        "sector",
        "regulation",
        "commercial"
    ],
    "wof:name":"Retail System Designs",
    "wof:placetype":"venue"
},
  "geometry": {"coordinates":[-122.14474300000001,47.474147],"type":"Point"}
}