{
  "type": "Feature",
  "properties": {
    "addr:full":"178 Sunset Ave N Edmonds WA 98020",
    "addr:housenumber":"178",
    "addr:postcode":"98020",
    "addr:street":"Sunset Ave N",
    "iso:country":"US",
    "sg:address":"178 Sunset Ave N",
    "sg:city":"Edmonds",
    "sg:classifiers":[
        {
            "category":"Restaurant",
            "type":"Food & Drink"
        }
    ],
    "sg:phone":"+1 425 673 9000",
    "sg:postcode":"98020",
    "sg:province":"WA",
    "wof:name":"Pizza Port",
    "wof:placetype":"venue"
},
  "geometry": {"coordinates":[-122.38157699999999,47.812408],"type":"Point"}
}