{
  "type": "Feature",
  "properties": {
    "addr:full":"1116 Key St Bellingham WA 98225",
    "addr:housenumber":"1116",
    "addr:postcode":"98225",
    "addr:street":"Key St",
    "iso:country":"US",
    "sg:address":"1116 Key St",
    "sg:city":"Bellingham",
    "sg:classifiers":[
        {
            "category":"Health Services",
            "subcategory":"Health Practitioner",
            "type":"Services"
        }
    ],
    "sg:phone":"+1 360 647 8295",
    "sg:postcode":"98225",
    "sg:province":"WA",
    "wof:name":"Elizabeth Nyblade PHD",
    "wof:placetype":"venue"
},
  "geometry": {"coordinates":[-122.473241,48.742402],"type":"Point"}
}