{
  "type": "Feature",
  "properties": {
    "addr:full":"2907 N Hogan St Spokane WA 99207",
    "addr:housenumber":"2907",
    "addr:postcode":"99207",
    "addr:street":"N Hogan St",
    "iso:country":"US",
    "sg:address":"2907 N Hogan St",
    "sg:city":"Spokane",
    "sg:classifiers":[
        {
            "category":"Building & Trades",
            "subcategory":"Landscaping Services",
            "type":"Services"
        }
    ],
    "sg:phone":"+1 509 487 3479",
    "sg:postcode":"99207",
    "sg:province":"WA",
    "wof:name":"Extreme Lawn Care",
    "wof:placetype":"venue"
},
  "geometry": {"coordinates":[-117.387719,47.685468],"type":"Point"}
}