{
  "type": "Feature",
  "properties": {
    "addr:full":"2137 3rd Ave Clarkston WA 99403",
    "addr:housenumber":"2137",
    "addr:postcode":"99403",
    "addr:street":"3Rd Ave",
    "iso:country":"US",
    "sg:address":"2137 3rd Ave",
    "sg:city":"Clarkston",
    "sg:classifiers":[
        {
            "category":"Building & Trades",
            "subcategory":"Construction",
            "type":"Services"
        }
    ],
    "sg:phone":"+1 509 758 3967",
    "sg:postcode":"99403",
    "sg:province":"WA",
    "sg:tags":[
        "concrete",
        "contractor",
        "general"
    ],
    "wof:name":"Mc Keehan Construction",
    "wof:placetype":"venue"
},
  "geometry": {"coordinates":[-117.08372199999999,46.396095],"type":"Point"}
}