{
  "type": "Feature",
  "properties": {
    "addr:full":"151 S Cedar St Buckley WA 98321",
    "addr:housenumber":"151",
    "addr:postcode":"98321",
    "addr:street":"S Cedar St",
    "iso:country":"US",
    "sg:address":"151 S Cedar St",
    "sg:city":"Buckley",
    "sg:classifiers":[
        {
            "category":"Government",
            "subcategory":"Fire Station",
            "type":"Public Place"
        }
    ],
    "sg:phone":"+1 360 829 1441",
    "sg:postcode":"98321",
    "sg:province":"WA",
    "sg:tags":[
        "department"
    ],
    "sg:website":"www.cityofbuckley.com",
    "wof:name":"Buckley City Fire Dept",
    "wof:placetype":"venue"
},
  "geometry": {"coordinates":[-122.028267,47.162811],"type":"Point"}
}