{
  "type": "Feature",
  "properties": {
    "addr:full":"16821 Smokey Point Blvd Arlington WA 98223",
    "addr:housenumber":"16821",
    "addr:postcode":"98223",
    "addr:street":"Smokey Point Blvd",
    "iso:country":"US",
    "sg:address":"16821 Smokey Point Blvd",
    "sg:city":"Arlington",
    "sg:classifiers":[
        {
            "category":"Manufacturing",
            "subcategory":"Petroleum Products",
            "type":"Manufacturing & Wholesale Goods"
        }
    ],
    "sg:phone":"+1 360 969 3966",
    "sg:postcode":"98223",
    "sg:province":"WA",
    "sg:tags":[
        "contract"
    ],
    "wof:name":"Prime Biodiesel",
    "wof:placetype":"venue"
},
  "geometry": {"coordinates":[-122.18293,48.148868],"type":"Point"}
}