{
  "type": "Feature",
  "properties": {
    "addr:full":"660 Swift Blvd Richland WA 99352",
    "addr:housenumber":"660",
    "addr:postcode":"99352",
    "addr:street":"Swift Blvd",
    "iso:country":"US",
    "sg:address":"660 Swift Blvd",
    "sg:city":"Richland",
    "sg:classifiers":[
        {
            "category":"Manufacturing",
            "subcategory":"Tools & Machinery",
            "type":"Manufacturing & Wholesale Goods"
        }
    ],
    "sg:phone":"+1 509 943 8561",
    "sg:postcode":"99352",
    "sg:province":"WA",
    "sg:tags":[
        "orthopedic"
    ],
    "wof:name":"Tri-Cities Orthotics Prsthtcs",
    "wof:placetype":"venue"
},
  "geometry": {"coordinates":[-119.276053,46.280503],"type":"Point"}
}