{
  "type": "Feature",
  "properties": {
    "addr:full":"2324 106th Pl SE Everett WA 98208",
    "addr:housenumber":"2324",
    "addr:postcode":"98208",
    "addr:street":"106Th Pl Se",
    "iso:country":"US",
    "sg:address":"2324 106th Pl SE",
    "sg:city":"Everett",
    "sg:classifiers":[
        {
            "category":"Professional",
            "subcategory":"Business Services",
            "type":"Services"
        }
    ],
    "sg:phone":"+1 425 337 7519",
    "sg:postcode":"98208",
    "sg:province":"WA",
    "wof:name":"Water Doctors Pool Service",
    "wof:placetype":"venue"
},
  "geometry": {"coordinates":[-122.19991,47.901104],"type":"Point"}
}