{
  "type": "Feature",
  "properties": {
    "iso:country":"US",
    "sg:address":"6942 16th Ave SW",
    "sg:city":"Seattle",
    "sg:classifiers":[
        {
            "category":"Restaurant",
            "type":"Food & Drink"
        }
    ],
    "sg:phone":"+1 206 763 8765",
    "sg:postcode":"98106",
    "sg:province":"WA",
    "sg:tags":[
        "eating"
    ],
    "wof:name":"Pho-White Center",
    "wof:placetype":"venue"
},
  "geometry": {"coordinates":[-122.35486899999999,47.542755],"type":"Point"}
}