{
  "type": "Feature",
  "properties": {
    "addr:full":"3701 Broadway Everett WA 98201",
    "addr:housenumber":"3701",
    "addr:postcode":"98201",
    "addr:street":"Broadway",
    "iso:country":"US",
    "sg:address":"3701 Broadway",
    "sg:city":"Everett",
    "sg:classifiers":[
        {
            "category":"Organizations",
            "subcategory":"Membership Organization",
            "type":"Services"
        }
    ],
    "sg:phone":"+1 425 259 9899",
    "sg:postcode":"98201",
    "sg:province":"WA",
    "wof:name":"Positive Women's Network",
    "wof:placetype":"venue"
},
  "geometry": {"coordinates":[-122.201075,47.967452],"type":"Point"}
}