{
  "type": "Feature",
  "properties": {
    "addr:full":"6585 123rd Ave SE Bellevue WA 98006",
    "addr:housenumber":"6585",
    "addr:postcode":"98006",
    "addr:street":"123Rd Ave Se",
    "iso:country":"US",
    "sg:address":"6585 123rd Ave SE",
    "sg:city":"Bellevue",
    "sg:classifiers":[
        {
            "category":"Real Estate",
            "subcategory":"Real Estate Agent",
            "type":"Services"
        }
    ],
    "sg:phone":"+1 425 562 0088",
    "sg:postcode":"98006",
    "sg:province":"WA",
    "wof:name":"Continental Group Realty Inc",
    "wof:placetype":"venue"
},
  "geometry": {"coordinates":[-122.17586900000001,47.544485],"type":"Point"}
}