{
  "type": "Feature",
  "properties": {
    "addr:full":"1810 12th Ave NW Issaquah WA 98027",
    "addr:housenumber":"1810",
    "addr:postcode":"98027",
    "addr:street":"12Th Ave Nw",
    "iso:country":"US",
    "sg:address":"1810 12th Ave NW",
    "sg:city":"Issaquah",
    "sg:phone":"+1 425 369 1222",
    "sg:postcode":"98027",
    "sg:province":"WA",
    "sg:website":"http://www.pccnaturalmarkets.com",
    "wof:name":"Pcc Natural Markets",
    "wof:placetype":"venue"
},
  "geometry": {"coordinates":[-122.057256,47.550084],"type":"Point"}
}