{
  "type": "Feature",
  "properties": {
    "iso:country":"US",
    "sg:address":"100 River Rd",
    "sg:city":"Puyallup",
    "sg:classifiers":[
        {
            "category":"Autos & Motor Vehicles",
            "subcategory":"Automobile Sales",
            "type":"Retail Goods"
        }
    ],
    "sg:phone":"+1 253 841 7607",
    "sg:postcode":"98371",
    "sg:province":"WA",
    "sg:tags":[
        "car",
        "dealer"
    ],
    "sg:website":"www.korum.net",
    "wof:name":"Korum Mitsubishi",
    "wof:placetype":"venue"
},
  "geometry": {"coordinates":[-122.295661,47.199203],"type":"Point"}
}