{
  "type": "Feature",
  "properties": {
    "addr:full":"1606 Lafayette St Steilacoom WA 98388",
    "addr:housenumber":"1606",
    "addr:postcode":"98388",
    "addr:street":"Lafayette St",
    "iso:country":"US",
    "sg:address":"1606 Lafayette St",
    "sg:city":"Steilacoom",
    "sg:classifiers":[
        {
            "category":"Shopping",
            "subcategory":"Gifts & Souvenirs",
            "type":"Retail Goods"
        }
    ],
    "sg:phone":"+1 253 581 8599",
    "sg:postcode":"98388",
    "sg:province":"WA",
    "sg:tags":[
        "shop"
    ],
    "wof:name":"Robyn's Nest",
    "wof:placetype":"venue"
},
  "geometry": {"coordinates":[-122.598495,47.172692],"type":"Point"}
}