{
  "type": "Feature",
  "properties": {
    "addr:full":"210 NW 101 St Seattle WA 98177",
    "addr:housenumber":"210",
    "addr:postcode":"98177",
    "addr:street":"Nw 101 St",
    "iso:country":"US",
    "sg:address":"210 NW 101 St",
    "sg:city":"Seattle",
    "sg:classifiers":[
        {
            "category":"Home & Garden",
            "subcategory":"Garden Supply",
            "type":"Retail Goods"
        }
    ],
    "sg:phone":"+1 206 297 1978",
    "sg:postcode":"98177",
    "sg:province":"WA",
    "sg:tags":[
        "nursery",
        "gardening"
    ],
    "sg:website":"www.piperscreeknursery.com",
    "wof:name":"Pipers Creek Nursery",
    "wof:placetype":"venue"
},
  "geometry": {"coordinates":[-122.360049,47.702224],"type":"Point"}
}