{
  "type": "Feature",
  "properties": {
    "iso:country":"US",
    "sg:address":"20231 85th Pl W",
    "sg:city":"Edmonds",
    "sg:classifiers":[
        {
            "category":"Wholesale",
            "subcategory":"Durable Goods & Equipment",
            "type":"Manufacturing & Wholesale Goods"
        }
    ],
    "sg:phone":"+1 425 776 0293",
    "sg:postcode":"98026",
    "sg:province":"WA",
    "wof:name":"C & Gs Collectibles",
    "wof:placetype":"venue"
},
  "geometry": {"coordinates":[-122.348591,47.815473],"type":"Point"}
}