{
  "type": "Feature",
  "properties": {
    "addr:full":"910 6th St S Kirkland WA 98033",
    "addr:housenumber":"910",
    "addr:postcode":"98033",
    "addr:street":"6Th St S",
    "iso:country":"US",
    "sg:address":"910 6th St S",
    "sg:city":"Kirkland",
    "sg:classifiers":[
        {
            "category":"Health Services",
            "subcategory":"Doctor",
            "type":"Services"
        }
    ],
    "sg:phone":"+1 425 889 9999",
    "sg:postcode":"98033",
    "sg:province":"WA",
    "wof:name":"Allen Dennis R PHD",
    "wof:placetype":"venue"
},
  "geometry": {"coordinates":[-122.195999,47.668098],"type":"Point"}
}