{
  "type": "Feature",
  "properties": {
    "addr:full":"302 W Francis Ave Spokane WA 99205",
    "addr:housenumber":"302",
    "addr:postcode":"99205",
    "addr:street":"W Francis Ave",
    "iso:country":"US",
    "sg:address":"302 W Francis Ave",
    "sg:city":"Spokane",
    "sg:classifiers":[
        {
            "category":"Food & Beverages",
            "subcategory":"Fruits & Vegetables",
            "type":"Retail Goods"
        }
    ],
    "sg:phone":"+1 509 467 3957",
    "sg:postcode":"99205",
    "sg:province":"WA",
    "sg:tags":[
        "produce"
    ],
    "wof:name":"Rusty's Prouduce",
    "wof:placetype":"venue"
},
  "geometry": {"coordinates":[-117.415851,47.715172],"type":"Point"}
}