{
  "type": "Feature",
  "properties": {
    "addr:full":"1930 N 13th St Shelton WA 98584",
    "addr:housenumber":"1930",
    "addr:postcode":"98584",
    "addr:street":"N 13Th St",
    "iso:country":"US",
    "sg:address":"1930 N 13th St",
    "sg:city":"Shelton",
    "sg:classifiers":[
        {
            "category":"Health Services",
            "subcategory":"Doctor",
            "type":"Services"
        }
    ],
    "sg:phone":"+1 360 427 8940",
    "sg:postcode":"98584",
    "sg:province":"WA",
    "sg:tags":[
        "physician",
        "surgeon"
    ],
    "wof:name":"Chandar Bhimani MD",
    "wof:placetype":"venue"
},
  "geometry": {"coordinates":[-123.112503,47.227653],"type":"Point"}
}