{
  "type": "Feature",
  "properties": {
    "iso:country":"US",
    "sg:address":"7718 NE 192nd St",
    "sg:city":"Kenmore",
    "sg:classifiers":[
        {
            "category":"Building & Trades",
            "subcategory":"Construction",
            "type":"Services"
        }
    ],
    "sg:phone":"+1 425 486 3859",
    "sg:postcode":"98028",
    "sg:province":"WA",
    "sg:tags":[
        "residential"
    ],
    "wof:name":"J D Bannister Construction",
    "wof:placetype":"venue"
},
  "geometry": {"coordinates":[-122.233406,47.767212],"type":"Point"}
}