{
  "type": "Feature",
  "properties": {
    "addr:full":"2900 Washington St Port Townsend WA 98368",
    "addr:housenumber":"2900",
    "addr:postcode":"98368",
    "addr:street":"Washington St",
    "iso:country":"US",
    "sg:address":"2900 Washington St",
    "sg:city":"Port Townsend",
    "sg:classifiers":[
        {
            "category":"Shopping",
            "subcategory":"Bicycles & Sporting Goods",
            "type":"Retail Goods"
        }
    ],
    "sg:phone":"+1 360 379 3635",
    "sg:postcode":"98368",
    "sg:province":"WA",
    "wof:name":"Port Townsend Dive Shop",
    "wof:placetype":"venue"
},
  "geometry": {"coordinates":[-122.77730699999999,48.106815],"type":"Point"}
}