{
  "type": "Feature",
  "properties": {
    "addr:full":"278 Winslow Way E Ste 1 Bainbridge Island WA 98110",
    "addr:housenumber":"278",
    "addr:postcode":"98110",
    "addr:street":"Winslow Way E Ste 1",
    "iso:country":"US",
    "sg:address":"278 Winslow Way E Ste 1",
    "sg:city":"Bainbridge Island",
    "sg:classifiers":[
        {
            "category":"Restaurant",
            "type":"Food & Drink"
        }
    ],
    "sg:phone":"+1 206 855 1200",
    "sg:postcode":"98110",
    "sg:province":"WA",
    "sg:tags":[
        "japanese"
    ],
    "wof:name":"Teriyaki Town",
    "wof:placetype":"venue"
},
  "geometry": {"coordinates":[-122.518997,47.625],"type":"Point"}
}