{
  "type": "Feature",
  "properties": {
    "addr:full":"3010 W Peninsula Dr Moses Lake WA 98837",
    "addr:housenumber":"3010",
    "addr:postcode":"98837",
    "addr:street":"W Peninsula Dr",
    "iso:country":"US",
    "sg:address":"3010 W Peninsula Dr",
    "sg:city":"Moses Lake",
    "sg:classifiers":[
        {
            "category":"Farming",
            "subcategory":"Farm",
            "type":"Manufacturing & Wholesale Goods"
        }
    ],
    "sg:phone":"+1 509 765 0343",
    "sg:postcode":"98837",
    "sg:province":"WA",
    "sg:tags":[
        "crop",
        "general"
    ],
    "wof:name":"Circle West Farms Inc",
    "wof:placetype":"venue"
},
  "geometry": {"coordinates":[-119.307616,47.09944],"type":"Point"}
}