{
  "type": "Feature",
  "properties": {
    "addr:full":"703 N 33rd St Yakima WA 98901",
    "addr:housenumber":"703",
    "addr:postcode":"98901",
    "addr:street":"N 33Rd St",
    "iso:country":"US",
    "sg:address":"703 N 33rd St",
    "sg:city":"Yakima",
    "sg:classifiers":[
        {
            "category":"Real Estate",
            "subcategory":"Real Estate Agent",
            "type":"Services"
        }
    ],
    "sg:phone":"+1 509 453 5743",
    "sg:postcode":"98901",
    "sg:province":"WA",
    "wof:name":"Laroca Investments",
    "wof:placetype":"venue"
},
  "geometry": {"coordinates":[-120.456354,46.612555],"type":"Point"}
}