{
  "type": "Feature",
  "properties": {
    "addr:full":"1203 Lum Rd Centralia WA 98531",
    "addr:housenumber":"1203",
    "addr:postcode":"98531",
    "addr:street":"Lum Rd",
    "iso:country":"US",
    "sg:address":"1203 Lum Rd",
    "sg:city":"Centralia",
    "sg:classifiers":[
        {
            "category":"Shopping",
            "subcategory":"Clothing, Apparel, & Fashions",
            "type":"Retail Goods"
        }
    ],
    "sg:phone":"+1 360 736 0348",
    "sg:postcode":"98531",
    "sg:province":"WA",
    "sg:tags":[
        "infant",
        "wear"
    ],
    "wof:name":"Carter's Childrenswear",
    "wof:placetype":"venue"
},
  "geometry": {"coordinates":[-122.977689,46.732045],"type":"Point"}
}