{
  "type": "Feature",
  "properties": {
    "addr:full":"13624 Dana Ln E Puyallup WA 98373",
    "addr:housenumber":"13624",
    "addr:postcode":"98373",
    "addr:street":"Dana Ln E",
    "iso:country":"US",
    "sg:address":"13624 Dana Ln E",
    "sg:city":"Puyallup",
    "sg:classifiers":[
        {
            "category":"Professional",
            "type":"Services"
        }
    ],
    "sg:phone":"+1 253 537 3455",
    "sg:postcode":"98373",
    "sg:province":"WA",
    "wof:name":"B A Hill",
    "wof:placetype":"venue"
},
  "geometry": {"coordinates":[-122.32979899999999,47.132049],"type":"Point"}
}