{
  "type": "Feature",
  "properties": {
    "addr:full":"801 Broadway Ste 611 Seattle WA 98122",
    "addr:housenumber":"801",
    "addr:postcode":"98122",
    "addr:street":"Broadway Ste 611",
    "iso:country":"US",
    "sg:address":"801 Broadway Ste 611",
    "sg:city":"Seattle",
    "sg:classifiers":[
        {
            "category":"Health Services",
            "subcategory":"Doctor",
            "type":"Services"
        }
    ],
    "sg:phone":"+1 206 215 2525",
    "sg:postcode":"98122",
    "sg:province":"WA",
    "sg:tags":[
        "medicine",
        "physician",
        "surgeon",
        "internal",
        "surgeons"
    ],
    "wof:name":"Center For Medical Weight Mgmt",
    "wof:placetype":"venue"
},
  "geometry": {"coordinates":[-122.32077,47.60923],"type":"Point"}
}