{
  "type": "Feature",
  "properties": {
    "addr:full":"417 S 6th St Sunnyside WA 98944",
    "addr:housenumber":"417",
    "addr:postcode":"98944",
    "addr:street":"S 6Th St",
    "iso:country":"US",
    "sg:address":"417 S 6th St",
    "sg:city":"Sunnyside",
    "sg:classifiers":[
        {
            "category":"Shopping",
            "subcategory":"Musical Instruments",
            "type":"Retail Goods"
        }
    ],
    "sg:phone":"+1 509 839 8448",
    "sg:postcode":"98944",
    "sg:province":"WA",
    "wof:name":"Sunnyside Music Store",
    "wof:placetype":"venue"
},
  "geometry": {"coordinates":[-120.013012,46.324328],"type":"Point"}
}