{
  "type": "Feature",
  "properties": {
    "addr:full":"2801 Alaskan Way Ste 200 Seattle WA 98121",
    "addr:housenumber":"2801",
    "addr:postcode":"98121",
    "addr:street":"Alaskan Way Ste 200",
    "iso:country":"US",
    "sg:address":"2801 Alaskan Way Ste 200",
    "sg:city":"Seattle",
    "sg:classifiers":[
        {
            "category":"Real Estate",
            "subcategory":"Real Estate Services",
            "type":"Services"
        },
        {
            "category":"Real Estate",
            "subcategory":"Real Estate Agent",
            "type":"Services"
        }
    ],
    "sg:phone":"+1 206 215 9820",
    "sg:postcode":"98121",
    "sg:province":"WA",
    "sg:tags":[
        "management"
    ],
    "wof:name":"Berkeley Heights Apartments",
    "wof:placetype":"venue"
},
  "geometry": {"coordinates":[-122.354012,47.614429],"type":"Point"}
}