{
  "type": "Feature",
  "properties": {
    "addr:full":"438 Overlake Dr E Medina WA 98039",
    "addr:housenumber":"438",
    "addr:postcode":"98039",
    "addr:street":"Overlake Dr E Medina",
    "iso:country":"US",
    "sg:address":"438 Overlake Dr E",
    "sg:city":"Medina",
    "sg:classifiers":[
        {
            "category":"Health Services",
            "subcategory":"Doctor",
            "type":"Services"
        }
    ],
    "sg:phone":"+1 425 462 5122",
    "sg:postcode":"98039",
    "sg:province":"WA",
    "sg:tags":[
        "medical"
    ],
    "wof:name":"Pyfers Dr Wellness Center Inc",
    "wof:placetype":"venue"
},
  "geometry": {"coordinates":[-122.223913,47.612444],"type":"Point"}
}