{
  "type": "Feature",
  "properties": {
    "addr:full":"20639 Old Hwy 99 SW Centralia WA 98531",
    "addr:housenumber":"20639",
    "addr:postcode":"98531",
    "addr:street":"Old Hwy 99 Sw",
    "iso:country":"US",
    "sg:address":"20639 Old Hwy 99 SW",
    "sg:city":"Centralia",
    "sg:classifiers":[
        {
            "category":"Shopping",
            "subcategory":"Used Merchandise",
            "type":"Retail Goods"
        }
    ],
    "sg:phone":"+1 360 273 0825",
    "sg:postcode":"98531",
    "sg:province":"WA",
    "sg:tags":[
        "hardware"
    ],
    "wof:name":"Star Exchange Ln Co Pawn Brks",
    "wof:placetype":"venue"
},
  "geometry": {"coordinates":[-123.01164300000001,46.788284],"type":"Point"}
}