{
  "type": "Feature",
  "properties": {
    "addr:full":"114 E Main Ave Ritzville WA 99169",
    "addr:housenumber":"114",
    "addr:postcode":"99169",
    "addr:street":"E Main Ave",
    "iso:country":"US",
    "sg:address":"114 E Main Ave",
    "sg:city":"Ritzville",
    "sg:classifiers":[
        {
            "category":"Social Services",
            "type":"Services"
        }
    ],
    "sg:phone":"+1 509 659 4225",
    "sg:postcode":"99169",
    "sg:province":"WA",
    "sg:tags":[
        "crisis",
        "intervention"
    ],
    "wof:name":"Adams County Resource Ctr",
    "wof:placetype":"venue"
},
  "geometry": {"coordinates":[-118.379845,47.127578],"type":"Point"}
}