{
  "type": "Feature",
  "properties": {
    "addr:full":"1904 3rd Ave Seattle WA 98101",
    "addr:housenumber":"1904",
    "addr:postcode":"98101",
    "addr:street":"3Rd Ave",
    "iso:country":"US",
    "sg:address":"1904 3rd Ave",
    "sg:city":"Seattle",
    "sg:classifiers":[
        {
            "category":"Real Estate",
            "subcategory":"Architect",
            "type":"Services"
        }
    ],
    "sg:phone":"+1 206 682 5000",
    "sg:postcode":"98101",
    "sg:province":"WA",
    "sg:tags":[
        "architectural"
    ],
    "sg:website":"www.cornerstonearch.com",
    "wof:name":"Cornerstone Architectural Grp",
    "wof:placetype":"venue"
},
  "geometry": {"coordinates":[-122.340808,47.612421],"type":"Point"}
}