{
  "type": "Feature",
  "properties": {
    "addr:full":"541 Industry Dr Tukwila WA 98188",
    "addr:housenumber":"541",
    "addr:postcode":"98188",
    "addr:street":"Industry Dr",
    "iso:country":"US",
    "sg:address":"541 Industry Dr",
    "sg:city":"Tukwila",
    "sg:classifiers":[
        {
            "category":"Professional",
            "subcategory":"Advertising",
            "type":"Services"
        }
    ],
    "sg:phone":"+1 206 236 7539",
    "sg:postcode":"98188",
    "sg:province":"WA",
    "sg:tags":[
        "designer",
        "display",
        "producer"
    ],
    "wof:name":"All Display Co",
    "wof:placetype":"venue"
},
  "geometry": {"coordinates":[-122.248137,47.453509],"type":"Point"}
}