{
  "type": "Feature",
  "properties": {
    "addr:full":"38 E Main St Walla Walla WA 99362",
    "addr:housenumber":"38",
    "addr:postcode":"99362",
    "addr:street":"E Main St",
    "iso:country":"US",
    "sg:address":"38 E Main St",
    "sg:city":"Walla Walla",
    "sg:classifiers":[
        {
            "category":"Home & Garden",
            "subcategory":"Building Materials",
            "type":"Retail Goods"
        }
    ],
    "sg:phone":"+1 509 529 7056",
    "sg:postcode":"99362",
    "sg:province":"WA",
    "sg:tags":[
        "auto",
        "glass"
    ],
    "wof:name":"89 Glass",
    "wof:placetype":"venue"
},
  "geometry": {"coordinates":[-118.337856,46.067455],"type":"Point"}
}