{
  "type": "Feature",
  "properties": {
    "addr:full":"6100 NE Highway 99 Vancouver WA 98665",
    "addr:housenumber":"6100",
    "addr:postcode":"98665",
    "addr:street":"Ne Highway 99",
    "iso:country":"US",
    "sg:address":"6100 NE Highway 99",
    "sg:city":"Vancouver",
    "sg:classifiers":[
        {
            "category":"Real Estate",
            "subcategory":"Real Estate Services",
            "type":"Services"
        },
        {
            "category":"Real Estate",
            "subcategory":"Real Estate Agent",
            "type":"Services"
        }
    ],
    "sg:phone":"+1 360 696 4571",
    "sg:postcode":"98665",
    "sg:province":"WA",
    "sg:tags":[
        "buyer",
        "broker"
    ],
    "wof:name":"Fbr Realty Inc",
    "wof:placetype":"venue"
},
  "geometry": {"coordinates":[-122.664418,45.666047],"type":"Point"}
}