{
  "type": "Feature",
  "properties": {
    "addr:full":"2913a S 38th St Tacoma WA 98409",
    "addr:housenumber":"2913a",
    "addr:postcode":"98409",
    "addr:street":"S 38Th St",
    "iso:country":"US",
    "sg:address":"2913a S 38th St",
    "sg:city":"Tacoma",
    "sg:classifiers":[
        {
            "category":"Cafe",
            "type":"Food & Drink"
        }
    ],
    "sg:menulink":"http://www.allmenus.com/wa/tacoma/106138-the-honey-baked-ham-co-and-cafe/menu/",
    "sg:phone":"+1 253 472 4260",
    "sg:postcode":"98409",
    "sg:province":"WA",
    "sg:tags":[
        "american"
    ],
    "wof:name":"The Honey Baked Ham Co. And Cafe",
    "wof:placetype":"venue"
},
  "geometry": {"coordinates":[-122.474594,47.222551],"type":"Point"}
}