{
  "type": "Feature",
  "properties": {
    "addr:full":"16207 177th Ave SE Monroe WA 98272",
    "addr:housenumber":"16207",
    "addr:postcode":"98272",
    "addr:street":"177Th Ave Se",
    "iso:country":"US",
    "sg:address":"16207 177th Ave SE",
    "sg:city":"Monroe",
    "sg:classifiers":[
        {
            "category":"Social Services",
            "type":"Services"
        }
    ],
    "sg:phone":"+1 360 794 8720",
    "sg:postcode":"98272",
    "sg:province":"WA",
    "sg:tags":[
        "organization",
        "welfare"
    ],
    "wof:name":"Matthew House",
    "wof:placetype":"venue"
},
  "geometry": {"coordinates":[-121.993076,47.849723],"type":"Point"}
}