{
  "type": "Feature",
  "properties": {
    "addr:full":"2615 4th Ave Seattle WA 98121",
    "addr:housenumber":"2615",
    "addr:postcode":"98121",
    "addr:street":"4Th Ave",
    "iso:country":"US",
    "sg:address":"2615 4th Ave",
    "sg:city":"Seattle",
    "sg:classifiers":[
        {
            "category":"Professional",
            "subcategory":"Engineering",
            "type":"Services"
        }
    ],
    "sg:phone":"+1 206 443 0949",
    "sg:postcode":"98121",
    "sg:province":"WA",
    "sg:tags":[
        "engineer"
    ],
    "wof:name":"Cedtech",
    "wof:placetype":"venue"
},
  "geometry": {"coordinates":[-122.348001,47.617659],"type":"Point"}
}