{
  "type": "Feature",
  "properties": {
    "addr:full":"2630 NW 63rd St Seattle WA 98107",
    "addr:housenumber":"2630",
    "addr:postcode":"98107",
    "addr:street":"Nw 63Rd St",
    "iso:country":"US",
    "sg:address":"2630 NW 63rd St",
    "sg:city":"Seattle",
    "sg:classifiers":[
        {
            "category":"Banks & Credit Unions",
            "subcategory":"Financial Services",
            "type":"Services"
        }
    ],
    "sg:phone":"+1 206 783 4722",
    "sg:postcode":"98107",
    "sg:province":"WA",
    "sg:tags":[
        "trust",
        "management"
    ],
    "wof:name":"Fred Liljenberg Trust",
    "wof:placetype":"venue"
},
  "geometry": {"coordinates":[-122.392695,47.674562],"type":"Point"}
}