{
  "type": "Feature",
  "properties": {
    "addr:full":"6529 77th Ave SE Snohomish WA 98290",
    "addr:housenumber":"6529",
    "addr:postcode":"98290",
    "addr:street":"77Th Ave Se",
    "iso:country":"US",
    "sg:address":"6529 77th Ave SE",
    "sg:city":"Snohomish",
    "sg:classifiers":[
        {
            "category":"Real Estate",
            "subcategory":"Architect",
            "type":"Services"
        }
    ],
    "sg:phone":"+1 425 334 1255",
    "sg:postcode":"98290",
    "sg:province":"WA",
    "sg:tags":[
        "architectural"
    ],
    "wof:name":"Van G Tormohlen Architect",
    "wof:placetype":"venue"
},
  "geometry": {"coordinates":[-122.12817,47.93132],"type":"Point"}
}