{
  "type": "Feature",
  "properties": {
    "addr:full":"270 S Main St Colville WA 99114",
    "addr:housenumber":"270",
    "addr:postcode":"99114",
    "addr:street":"S Main St",
    "iso:country":"US",
    "sg:address":"270 S Main St",
    "sg:city":"Colville",
    "sg:classifiers":[
        {
            "category":"Manufacturing",
            "subcategory":"Lumber",
            "type":"Manufacturing & Wholesale Goods"
        }
    ],
    "sg:phone":"+1 509 684 8550",
    "sg:postcode":"99114",
    "sg:province":"WA",
    "sg:tags":[
        "forestry",
        "consulting",
        "business"
    ],
    "sg:website":"www.williamsonconsulting.net",
    "wof:name":"WILLIAMSON Consulting",
    "wof:placetype":"venue"
},
  "geometry": {"coordinates":[-117.905828,48.542585],"type":"Point"}
}