{
  "type": "Feature",
  "properties": {
    "addr:full":"1000 Dexter Avenue N. Suite 502 Seattle WA 98109",
    "addr:housenumber":"1000",
    "addr:postcode":"98109",
    "addr:street":"Dexter Avenue N. Suite 502",
    "iso:country":"US",
    "sg:address":"1000 Dexter Avenue N. Suite 502",
    "sg:city":"Seattle",
    "sg:classifiers":[
        {
            "category":"Professional",
            "type":"Services"
        }
    ],
    "sg:phone":"+1 206 623 2090",
    "sg:postcode":"98109",
    "sg:province":"WA",
    "sg:tags":[
        "planning",
        "event"
    ],
    "sg:website":"www.shworldwide.com",
    "wof:name":"SH Worldwide",
    "wof:placetype":"venue"
},
  "geometry": {"coordinates":[-122.341909,47.628533],"type":"Point"}
}