{
  "type": "Feature",
  "properties": {
    "addr:full":"12817 E Broadway Ave Spokane Valley WA 99216",
    "addr:housenumber":"12817",
    "addr:postcode":"99216",
    "addr:street":"E Broadway Ave",
    "iso:country":"US",
    "sg:address":"12817 E Broadway Ave",
    "sg:city":"Spokane Valley",
    "sg:classifiers":[
        {
            "category":"Organizations",
            "subcategory":"Religious Organization",
            "type":"Services"
        }
    ],
    "sg:phone":"+1 509 921 1543",
    "sg:postcode":"99216",
    "sg:province":"WA",
    "sg:tags":[
        "church"
    ],
    "wof:name":"Cornerstone",
    "wof:placetype":"venue"
},
  "geometry": {"coordinates":[-117.233209,47.664436],"type":"Point"}
}