{
  "type": "Feature",
  "properties": {
    "addr:full":"1710 N Calispel St Spokane WA 99205",
    "addr:housenumber":"1710",
    "addr:postcode":"99205",
    "addr:street":"N Calispel St",
    "iso:country":"US",
    "sg:address":"1710 N Calispel St",
    "sg:city":"Spokane",
    "sg:classifiers":[
        {
            "category":"Organizations",
            "subcategory":"Labor Organization",
            "type":"Services"
        }
    ],
    "sg:phone":"+1 509 328 5812",
    "sg:postcode":"99205",
    "sg:province":"WA",
    "wof:name":"Local 1001 Ufcw",
    "wof:placetype":"venue"
},
  "geometry": {"coordinates":[-117.415762,47.67293],"type":"Point"}
}