{
  "type": "Feature",
  "properties": {
    "addr:full":"69 Jadwin Ave Richland WA 99352",
    "addr:housenumber":"69",
    "addr:postcode":"99352",
    "addr:street":"Jadwin Ave",
    "iso:country":"US",
    "sg:address":"69 Jadwin Ave",
    "sg:city":"Richland",
    "sg:classifiers":[
        {
            "category":"Real Estate",
            "subcategory":"Real Estate Operator",
            "type":"Services"
        }
    ],
    "sg:phone":"+1 509 946 5658",
    "sg:postcode":"99352",
    "sg:province":"WA",
    "sg:tags":[
        "apartment",
        "complex"
    ],
    "wof:name":"Quarry House",
    "wof:placetype":"venue"
},
  "geometry": {"coordinates":[-119.27517,46.26109],"type":"Point"}
}