{
  "type": "Feature",
  "properties": {
    "addr:full":"107 S Main St Coupeville WA 98239",
    "addr:housenumber":"107",
    "addr:postcode":"98239",
    "addr:street":"S Main St",
    "iso:country":"US",
    "sg:address":"107 S Main St",
    "sg:city":"Coupeville",
    "sg:classifiers":[
        {
            "category":"Food & Beverages",
            "subcategory":"Bakery",
            "type":"Retail Goods"
        }
    ],
    "sg:phone":"+1 360 221 3525",
    "sg:postcode":"98239",
    "sg:province":"WA",
    "wof:name":"Langley Village Bakery",
    "wof:placetype":"venue"
},
  "geometry": {"coordinates":[-122.68607,48.211268],"type":"Point"}
}