{
  "type": "Feature",
  "properties": {
    "addr:full":"11750 Lake City Way NE Seattle WA 98125",
    "addr:housenumber":"11750",
    "addr:postcode":"98125",
    "addr:street":"Lake City Way Ne",
    "iso:country":"US",
    "sg:address":"11750 Lake City Way NE",
    "sg:city":"Seattle",
    "sg:classifiers":[
        {
            "category":"Autos & Motor Vehicles",
            "subcategory":"Fuel & Gas Station",
            "type":"Retail Goods"
        },
        {
            "category":"Retail",
            "subcategory":"Auto Repair",
            "type":"Services"
        }
    ],
    "sg:phone":"+1 206 364 4684",
    "sg:postcode":"98125",
    "sg:province":"WA",
    "wof:name":"Hand Ron Chevron",
    "wof:placetype":"venue"
},
  "geometry": {"coordinates":[-122.29723,47.715508],"type":"Point"}
}