{
  "type": "Feature",
  "properties": {
    "addr:full":"3407 241st Pl SE Issaquah WA 98029",
    "addr:housenumber":"3407",
    "addr:postcode":"98029",
    "addr:street":"241St Pl Se",
    "iso:country":"US",
    "sg:address":"3407 241st Pl SE",
    "sg:city":"Issaquah",
    "sg:classifiers":[
        {
            "category":"Building & Trades",
            "subcategory":"Landscaping Services",
            "type":"Services"
        }
    ],
    "sg:phone":"+1 425 391 6946",
    "sg:postcode":"98029",
    "sg:province":"WA",
    "sg:tags":[
        "designer",
        "landscape"
    ],
    "wof:name":"Darwin WEBB Landscape Arch",
    "wof:placetype":"venue"
},
  "geometry": {"coordinates":[-122.01759300000001,47.576617],"type":"Point"}
}