{
  "type": "Feature",
  "properties": {
    "addr:full":"12664 SE 306th Ct Auburn WA 98092",
    "addr:housenumber":"12664",
    "addr:postcode":"98092",
    "addr:street":"Se 306Th Ct",
    "iso:country":"US",
    "sg:address":"12664 SE 306th Ct",
    "sg:city":"Auburn",
    "sg:classifiers":[
        {
            "category":"Recreation",
            "type":"Entertainment"
        }
    ],
    "sg:phone":"+1 253 735 9603",
    "sg:postcode":"98092",
    "sg:province":"WA",
    "wof:name":"Yoga With Tracey",
    "wof:placetype":"venue"
},
  "geometry": {"coordinates":[-122.17246799999999,47.327543],"type":"Point"}
}