{
  "type": "Feature",
  "properties": {
    "addr:full":"134 S Deadman Rd Pomeroy WA 99347",
    "addr:housenumber":"134",
    "addr:postcode":"99347",
    "addr:street":"S Deadman Rd",
    "iso:country":"US",
    "sg:address":"134 S Deadman Rd",
    "sg:city":"Pomeroy",
    "sg:classifiers":[
        {
            "category":"Building & Trades",
            "subcategory":"Construction",
            "type":"Services"
        }
    ],
    "sg:phone":"+1 509 843 1774",
    "sg:postcode":"99347",
    "sg:province":"WA",
    "sg:tags":[
        "contractor"
    ],
    "wof:name":"Anderson Contracting",
    "wof:placetype":"venue"
},
  "geometry": {"coordinates":[-117.534801,46.562242],"type":"Point"}
}