{
  "type": "Feature",
  "properties": {
    "addr:full":"1308 E Union St Seattle WA 98122",
    "addr:housenumber":"1308",
    "addr:postcode":"98122",
    "addr:street":"E Union St",
    "iso:country":"US",
    "sg:address":"1308 E Union St",
    "sg:city":"Seattle",
    "sg:phone":"+1 206 322 1602",
    "sg:postcode":"98122",
    "sg:province":"WA",
    "sg:website":"http://www.fleurish.com",
    "wof:name":"Fleurish",
    "wof:placetype":"venue"
},
  "geometry": {"coordinates":[-122.315231,47.6129],"type":"Point"}
}