{
  "type": "Feature",
  "properties": {
    "addr:full":"4345 Lakeview Dr NW Bremerton WA 98312",
    "addr:housenumber":"4345",
    "addr:postcode":"98312",
    "addr:street":"Lakeview Dr Nw",
    "iso:country":"US",
    "sg:address":"4345 Lakeview Dr NW",
    "sg:city":"Bremerton",
    "sg:classifiers":[
        {
            "category":"Home & Garden",
            "subcategory":"Garden Supply",
            "type":"Retail Goods"
        }
    ],
    "sg:phone":"+1 360 373 8015",
    "sg:postcode":"98312",
    "sg:province":"WA",
    "sg:tags":[
        "nurseryman"
    ],
    "wof:name":"Carter's Nursery",
    "wof:placetype":"venue"
},
  "geometry": {"coordinates":[-122.708072,47.582728],"type":"Point"}
}