{
  "type": "Feature",
  "properties": {
    "addr:full":"2802 Simpson Ave Hoquiam WA 98550",
    "addr:housenumber":"2802",
    "addr:postcode":"98550",
    "addr:street":"Simpson Ave",
    "iso:country":"US",
    "sg:address":"2802 Simpson Ave",
    "sg:city":"Hoquiam",
    "sg:classifiers":[
        {
            "category":"Wholesale",
            "subcategory":"Electrical",
            "type":"Manufacturing & Wholesale Goods"
        }
    ],
    "sg:phone":"+1 360 538 1130",
    "sg:postcode":"98550",
    "sg:province":"WA",
    "sg:tags":[
        "telecommunication"
    ],
    "wof:name":"Rey-Com",
    "wof:placetype":"venue"
},
  "geometry": {"coordinates":[-123.86041400000001,46.975106],"type":"Point"}
}