{
  "type": "Feature",
  "properties": {
    "addr:full":"5212 22nd Ave. NE Seattle WA 98105",
    "addr:housenumber":"5212",
    "addr:postcode":"98105",
    "addr:street":"22Nd Ave. Ne",
    "iso:country":"US",
    "sg:address":"5212 22nd Ave. NE",
    "sg:city":"Seattle",
    "sg:classifiers":[
        {
            "category":"Building & Trades",
            "subcategory":"Cleaning & Sanitation",
            "type":"Services"
        }
    ],
    "sg:phone":"+1 206 528 6146",
    "sg:postcode":"98105",
    "sg:province":"WA",
    "sg:tags":[
        "home",
        "window",
        "washing"
    ],
    "sg:website":"www.simplejoys.info",
    "wof:name":"Simple Joys",
    "wof:placetype":"venue"
},
  "geometry": {"coordinates":[-122.30409899999999,47.666932],"type":"Point"}
}