{
  "type": "Feature",
  "properties": {
    "addr:full":"8512 Evergreen Way Everett WA 98208",
    "addr:housenumber":"8512",
    "addr:postcode":"98208",
    "addr:street":"Evergreen Way",
    "iso:country":"US",
    "sg:address":"8512 Evergreen Way",
    "sg:city":"Everett",
    "sg:phone":"+1 425 267 9393",
    "sg:postcode":"98208",
    "sg:province":"WA",
    "wof:name":"Lovely Nails",
    "wof:placetype":"venue"
},
  "geometry": {"coordinates":[-122.228887,47.921009],"type":"Point"}
}