{
  "type": "Feature",
  "properties": {
    "addr:full":"3927 Lakemont Rd Bellingham WA 98226",
    "addr:housenumber":"3927",
    "addr:postcode":"98226",
    "addr:street":"Lakemont Rd",
    "iso:country":"US",
    "sg:address":"3927 Lakemont Rd",
    "sg:city":"Bellingham",
    "sg:classifiers":[
        {
            "category":"Travel",
            "subcategory":"Travel Agent",
            "type":"Entertainment"
        }
    ],
    "sg:phone":"+1 360 527 3262",
    "sg:postcode":"98226",
    "sg:province":"WA",
    "sg:tags":[
        "passenger",
        "transportation",
        "arrangement"
    ],
    "wof:name":"Transmarine Navigation Corpora",
    "wof:placetype":"venue"
},
  "geometry": {"coordinates":[-122.41212299999999,48.783476],"type":"Point"}
}