{
  "type": "Feature",
  "properties": {
    "addr:full":"1418 1/2 3rd Avenue Seattle WA 98101",
    "addr:housenumber":"1418 1 / 2",
    "addr:postcode":"98101",
    "addr:street":"3Rd Avenue",
    "iso:country":"US",
    "sg:address":"1418 1/2 3rd Avenue",
    "sg:city":"Seattle",
    "sg:classifiers":[
        {
            "category":"Shopping",
            "subcategory":"Department Store",
            "type":"Retail Goods"
        },
        {
            "category":"Shopping",
            "subcategory":"Clothing, Apparel, & Fashions",
            "type":"Retail Goods"
        },
        {
            "category":"Shopping",
            "subcategory":"Discount & Variety Stores",
            "type":"Retail Goods"
        }
    ],
    "sg:phone":"+1 206 623 6781",
    "sg:postcode":"98101",
    "sg:province":"WA",
    "sg:tags":[
        "clothing"
    ],
    "sg:website":"http://www.rossstores.com",
    "wof:name":"Ross Dress For Less",
    "wof:placetype":"venue"
},
  "geometry": {"coordinates":[-122.337458,47.609586],"type":"Point"}
}