{
  "type": "Feature",
  "properties": {
    "addr:full":"110 N Washington St Kennewick WA 99336",
    "addr:housenumber":"110",
    "addr:postcode":"99336",
    "addr:street":"N Washington St",
    "iso:country":"US",
    "sg:address":"110 N Washington St",
    "sg:city":"Kennewick",
    "sg:classifiers":[
        {
            "category":"Wholesale",
            "subcategory":"Machinery & Supplies",
            "type":"Manufacturing & Wholesale Goods"
        }
    ],
    "sg:phone":"+1 509 586 0551",
    "sg:postcode":"99336",
    "sg:province":"WA",
    "sg:tags":[
        "equipment",
        "mater",
        "construction",
        "rent"
    ],
    "wof:name":"Seco Construction Equipment",
    "wof:placetype":"venue"
},
  "geometry": {"coordinates":[-119.11691999999999,46.210688],"type":"Point"}
}