{
  "type": "Feature",
  "properties": {
    "addr:full":"10905 164th Pl NE Redmond WA 98052",
    "addr:housenumber":"10905",
    "addr:postcode":"98052",
    "addr:street":"164Th Pl Ne",
    "iso:country":"US",
    "sg:address":"10905 164th Pl NE",
    "sg:city":"Redmond",
    "sg:classifiers":[
        {
            "category":"Real Estate",
            "subcategory":"Real Estate Operator",
            "type":"Services"
        }
    ],
    "sg:phone":"+1 425 556 9606",
    "sg:postcode":"98052",
    "sg:province":"WA",
    "sg:tags":[
        "building",
        "apartment"
    ],
    "wof:name":"Pearson Juvrud Properties",
    "wof:placetype":"venue"
},
  "geometry": {"coordinates":[-122.120907,47.697724],"type":"Point"}
}