{
  "type": "Feature",
  "properties": {
    "addr:full":"5605 100th St SW Lakewood WA 98499",
    "addr:housenumber":"5605",
    "addr:postcode":"98499",
    "addr:street":"100Th St Sw",
    "iso:country":"US",
    "sg:address":"5605 100th St SW",
    "sg:city":"Lakewood",
    "sg:classifiers":[
        {
            "category":"Health Services",
            "subcategory":"Health Practitioner",
            "type":"Services"
        }
    ],
    "sg:phone":"+1 253 284 9800",
    "sg:postcode":"98499",
    "sg:province":"WA",
    "sg:tags":[
        "therapist",
        "physical"
    ],
    "wof:name":"Apple Physical Thrpy Lakewood",
    "wof:placetype":"venue"
},
  "geometry": {"coordinates":[-122.514235,47.166773],"type":"Point"}
}