{
  "type": "Feature",
  "properties": {
    "addr:full":"10013 NE Hwy 99 Vancouver WA 98686",
    "addr:housenumber":"10013",
    "addr:postcode":"98686",
    "addr:street":"Ne Hwy 99",
    "iso:country":"US",
    "sg:address":"10013 NE Hwy 99",
    "sg:city":"Vancouver",
    "sg:classifiers":[
        {
            "category":"Autos & Motor Vehicles",
            "subcategory":"Automobile Sales",
            "type":"Retail Goods"
        }
    ],
    "sg:phone":"+1 360 574 6916",
    "sg:postcode":"98686",
    "sg:province":"WA",
    "sg:tags":[
        "car",
        "dealer"
    ],
    "wof:name":"Susie's Auto Sales",
    "wof:placetype":"venue"
},
  "geometry": {"coordinates":[-122.655807,45.694265],"type":"Point"}
}