{
  "type": "Feature",
  "properties": {
    "addr:full":"5309 Spruce Ln NW Gig Harbor WA 98335",
    "addr:housenumber":"5309",
    "addr:postcode":"98335",
    "addr:street":"Spruce Ln Nw",
    "iso:country":"US",
    "sg:address":"5309 Spruce Ln NW",
    "sg:city":"Gig Harbor",
    "sg:classifiers":[
        {
            "category":"Professional",
            "type":"Services"
        }
    ],
    "sg:phone":"+1 253 851 2840",
    "sg:postcode":"98335",
    "sg:province":"WA",
    "wof:name":"Glacier Seal",
    "wof:placetype":"venue"
},
  "geometry": {"coordinates":[-122.60986699999999,47.305555],"type":"Point"}
}