{
  "type": "Feature",
  "properties": {
    "addr:full":"7320 W Quinault Ave Kennewick WA 99336",
    "addr:housenumber":"7320",
    "addr:postcode":"99336",
    "addr:street":"W Quinault Ave",
    "iso:country":"US",
    "sg:address":"7320 W Quinault Ave",
    "sg:city":"Kennewick",
    "sg:classifiers":[
        {
            "category":"Government",
            "subcategory":"Police Station",
            "type":"Public Place"
        }
    ],
    "sg:phone":"+1 509 735 6555",
    "sg:postcode":"99336",
    "sg:province":"WA",
    "sg:tags":[
        "protection"
    ],
    "wof:name":"Benton County Sheriff",
    "wof:placetype":"venue"
},
  "geometry": {"coordinates":[-119.22030700000001,46.221374],"type":"Point"}
}