{
  "type": "Feature",
  "properties": {
    "addr:full":"4983 Bayview Rd Langley WA 98260",
    "addr:housenumber":"4983",
    "addr:postcode":"98260",
    "addr:street":"Bayview Rd",
    "iso:country":"US",
    "sg:address":"4983 Bayview Rd",
    "sg:city":"Langley",
    "sg:classifiers":[
        {
            "category":"Manufacturing",
            "subcategory":"Building Materials",
            "type":"Manufacturing & Wholesale Goods"
        }
    ],
    "sg:phone":"+1 360 221 2147",
    "sg:postcode":"98260",
    "sg:province":"WA",
    "sg:tags":[
        "mfg"
    ],
    "wof:name":"Baca Woods",
    "wof:placetype":"venue"
},
  "geometry": {"coordinates":[-122.447293,48.029035],"type":"Point"}
}