{
  "type": "Feature",
  "properties": {
    "addr:full":"784 N Dewald Rd Ritzville WA 99169",
    "addr:housenumber":"784",
    "addr:postcode":"99169",
    "addr:street":"N Dewald Rd",
    "iso:country":"US",
    "sg:address":"784 N Dewald Rd",
    "sg:city":"Ritzville",
    "sg:classifiers":[
        {
            "category":"Retail",
            "subcategory":"Auto Repair",
            "type":"Services"
        }
    ],
    "sg:phone":"+1 509 659 1676",
    "sg:postcode":"99169",
    "sg:province":"WA",
    "sg:tags":[
        "body"
    ],
    "wof:name":"Borth Restoration",
    "wof:placetype":"venue"
},
  "geometry": {"coordinates":[-118.47246,47.03632],"type":"Point"}
}