{
  "type": "Feature",
  "properties": {
    "addr:full":"6632 119th Pl SE Bellevue WA 98006",
    "addr:housenumber":"6632",
    "addr:postcode":"98006",
    "addr:street":"119Th Pl Se",
    "iso:country":"US",
    "sg:address":"6632 119th Pl SE",
    "sg:city":"Bellevue",
    "sg:classifiers":[
        {
            "category":"Professional",
            "subcategory":"Business Services",
            "type":"Services"
        }
    ],
    "sg:phone":"+1 425 277 8550",
    "sg:postcode":"98006",
    "sg:province":"WA",
    "wof:name":"Creative Solutions By Design L",
    "wof:placetype":"venue"
},
  "geometry": {"coordinates":[-122.180982,47.542925],"type":"Point"}
}