{
  "type": "Feature",
  "properties": {
    "addr:full":"11208 NE Fourth Plain Rd Vancouver WA 98662",
    "addr:housenumber":"11208",
    "addr:postcode":"98662",
    "addr:street":"Ne Fourth Plain Rd",
    "iso:country":"US",
    "sg:address":"11208 NE Fourth Plain Rd",
    "sg:city":"Vancouver",
    "sg:classifiers":[
        {
            "category":"Restaurant",
            "type":"Food & Drink"
        }
    ],
    "sg:phone":"+1 360 936 2972",
    "sg:postcode":"98662",
    "sg:province":"WA",
    "sg:tags":[
        "caterer"
    ],
    "wof:name":"Haole Bob's Hawaiian Barbeque",
    "wof:placetype":"venue"
},
  "geometry": {"coordinates":[-122.557862,45.666046],"type":"Point"}
}