{
  "type": "Feature",
  "properties": {
    "addr:full":"4812 130th Ave SE Bellevue WA 98006",
    "addr:housenumber":"4812",
    "addr:postcode":"98006",
    "addr:street":"130Th Ave Se",
    "iso:country":"US",
    "sg:address":"4812 130th Ave SE",
    "sg:city":"Bellevue",
    "sg:classifiers":[
        {
            "category":"Building & Trades",
            "subcategory":"Locksmith",
            "type":"Services"
        }
    ],
    "sg:phone":"+1 425 749 3381",
    "sg:postcode":"98006",
    "sg:province":"WA",
    "sg:tags":[
        "key"
    ],
    "wof:name":"Locksmith A 24 Hour",
    "wof:placetype":"venue"
},
  "geometry": {"coordinates":[-122.166647,47.559685],"type":"Point"}
}