{
  "type": "Feature",
  "properties": {
    "addr:full":"130 SE Kodiak Ridge Rd Shelton WA 98584",
    "addr:housenumber":"130",
    "addr:postcode":"98584",
    "addr:street":"Se Kodiak Ridge Rd",
    "iso:country":"US",
    "sg:address":"130 SE Kodiak Ridge Rd",
    "sg:city":"Shelton",
    "sg:classifiers":[
        {
            "category":"Wholesale",
            "subcategory":"Sporting Goods",
            "type":"Manufacturing & Wholesale Goods"
        },
        {
            "category":"Professional",
            "subcategory":"Research",
            "type":"Services"
        }
    ],
    "sg:phone":"+1 360 432 2339",
    "sg:postcode":"98584",
    "sg:province":"WA",
    "sg:tags":[
        "target",
        "hunting",
        "commercial",
        "d",
        "fishing",
        "military",
        "shooting",
        "physical"
    ],
    "wof:name":"Eagle View Research Center LLC",
    "wof:placetype":"venue"
},
  "geometry": {"coordinates":[-123.010214,47.18503],"type":"Point"}
}