{
  "type": "Feature",
  "properties": {
    "iso:country":"US",
    "sg:address":"12925 NE Rockwell Dr",
    "sg:city":"Vancouver",
    "sg:classifiers":[
        {
            "category":"Professional",
            "type":"Services"
        }
    ],
    "sg:phone":"+1 360 546 3288",
    "sg:postcode":"98686",
    "sg:province":"WA",
    "wof:name":"Perfect Last Word",
    "wof:placetype":"venue"
},
  "geometry": {"coordinates":[-122.64403,45.715212],"type":"Point"}
}