{
  "type": "Feature",
  "properties": {
    "addr:full":"205 NE 78th St Vancouver WA 98665",
    "addr:housenumber":"205",
    "addr:postcode":"98665",
    "addr:street":"Ne 78Th St",
    "iso:country":"US",
    "sg:address":"205 NE 78th St",
    "sg:city":"Vancouver",
    "sg:classifiers":[
        {
            "category":"Personal",
            "type":"Services"
        },
        {
            "category":"Retail",
            "subcategory":"Auto Rental",
            "type":"Services"
        }
    ],
    "sg:phone":"+1 800 468 4285",
    "sg:postcode":"98665",
    "sg:province":"WA",
    "sg:tags":[
        "car",
        "mover",
        "truck"
    ],
    "wof:name":"U-Haul Co.",
    "wof:placetype":"venue"
},
  "geometry": {"coordinates":[-122.669541,45.678585],"type":"Point"}
}