{
  "type": "Feature",
  "properties": {
    "addr:full":"11255 Fairview Blvd SW Port Orchard WA 98367",
    "addr:housenumber":"11255",
    "addr:postcode":"98367",
    "addr:street":"Fairview Blvd Sw Port Orchard",
    "iso:country":"US",
    "sg:address":"11255 Fairview Blvd SW",
    "sg:city":"Port Orchard",
    "sg:classifiers":[
        {
            "category":"Professional",
            "type":"Services"
        }
    ],
    "sg:phone":"+1 360 876 2105",
    "sg:postcode":"98367",
    "sg:province":"WA",
    "wof:name":"Diversified Ind",
    "wof:placetype":"venue"
},
  "geometry": {"coordinates":[-122.64971,47.446335],"type":"Point"}
}