{
  "type": "Feature",
  "properties": {
    "addr:full":"17535 NE 104th St Redmond WA 98052",
    "addr:housenumber":"17535",
    "addr:postcode":"98052",
    "addr:street":"Ne 104Th St",
    "iso:country":"US",
    "sg:address":"17535 NE 104th St",
    "sg:city":"Redmond",
    "sg:classifiers":[
        {
            "category":"Recreation",
            "type":"Entertainment"
        }
    ],
    "sg:phone":"+1 425 296 2961",
    "sg:postcode":"98052",
    "sg:province":"WA",
    "sg:tags":[
        "executive"
    ],
    "wof:name":"Redmond Pool",
    "wof:placetype":"venue"
},
  "geometry": {"coordinates":[-122.10789200000001,47.692964],"type":"Point"}
}