{
  "type": "Feature",
  "properties": {
    "addr:full":"15238 SE 272nd St Kent WA 98042",
    "addr:postcode":"15238;98042",
    "addr:street":"Se 272Nd St",
    "iso:country":"US",
    "sg:address":"15238 SE 272nd St",
    "sg:city":"Kent",
    "sg:classifiers":[
        {
            "category":"Real Estate",
            "subcategory":"Real Estate Operator",
            "type":"Services"
        }
    ],
    "sg:phone":"+1 253 631 2906",
    "sg:postcode":"98042",
    "sg:province":"WA",
    "sg:tags":[
        "mobile",
        "manufactured",
        "housing-communities",
        "site",
        "home"
    ],
    "wof:name":"Martel's Trailer Park",
    "wof:placetype":"venue"
},
  "geometry": {"coordinates":[-122.138092,47.357998],"type":"Point"}
}