{
  "type": "Feature",
  "properties": {
    "iso:country":"US",
    "sg:address":"830 Township St",
    "sg:city":"Sedro Woolley",
    "sg:classifiers":[
        {
            "category":"Real Estate",
            "subcategory":"Real Estate Agent",
            "type":"Services"
        }
    ],
    "sg:phone":"+1 360 855 0404",
    "sg:postcode":"98284",
    "sg:province":"WA",
    "sg:tags":[
        "authorities",
        "housing"
    ],
    "wof:name":"Sedro Woolley Housing Auth",
    "wof:placetype":"venue"
},
  "geometry": {"coordinates":[-122.225965,48.503967],"type":"Point"}
}