{
  "type": "Feature",
  "properties": {
    "addr:full":"477 S 28th St Washougal WA 98671",
    "addr:housenumber":"477",
    "addr:postcode":"98671",
    "addr:street":"S 28Th St",
    "iso:country":"US",
    "sg:address":"477 S 28th St",
    "sg:city":"Washougal",
    "sg:classifiers":[
        {
            "category":"Wholesale",
            "subcategory":"Machinery & Supplies",
            "type":"Manufacturing & Wholesale Goods"
        }
    ],
    "sg:phone":"+1 360 835 2067",
    "sg:postcode":"98671",
    "sg:province":"WA",
    "sg:tags":[
        "ladder"
    ],
    "wof:name":"N W Ladder Svc",
    "wof:placetype":"venue"
},
  "geometry": {"coordinates":[-122.341466,45.573093],"type":"Point"}
}