{
  "type": "Feature",
  "properties": {
    "addr:full":"23700 104th Ave W Edmonds WA 98020",
    "addr:housenumber":"23700",
    "addr:postcode":"98020",
    "addr:street":"104Th Ave W",
    "iso:country":"US",
    "sg:address":"23700 104th Ave W",
    "sg:city":"Edmonds",
    "sg:classifiers":[
        {
            "category":"Education",
            "subcategory":"School",
            "type":"Public Place"
        }
    ],
    "sg:phone":"+1 206 546 6670",
    "sg:postcode":"98020",
    "sg:province":"WA",
    "wof:name":"Pacific Montessori Learning",
    "wof:placetype":"venue"
},
  "geometry": {"coordinates":[-122.372193,47.784272],"type":"Point"}
}