{
  "type": "Feature",
  "properties": {
    "addr:full":"613 N K St Aberdeen WA 98520",
    "addr:housenumber":"613",
    "addr:postcode":"98520",
    "addr:street":"N K St",
    "iso:country":"US",
    "sg:address":"613 N K St",
    "sg:city":"Aberdeen",
    "sg:classifiers":[
        {
            "category":"Real Estate",
            "subcategory":"Real Estate Agent",
            "type":"Services"
        }
    ],
    "sg:phone":"+1 360 482 4440",
    "sg:postcode":"98520",
    "sg:province":"WA",
    "sg:tags":[
        "appraiser"
    ],
    "wof:name":"Approved Appraisals",
    "wof:placetype":"venue"
},
  "geometry": {"coordinates":[-123.825262,46.979031],"type":"Point"}
}