{
  "type": "Feature",
  "properties": {
    "addr:full":"107 W Washington Ave Dayton WA 99328",
    "addr:housenumber":"107",
    "addr:postcode":"99328",
    "addr:street":"W Washington Ave",
    "iso:country":"US",
    "sg:address":"107 W Washington Ave",
    "sg:city":"Dayton",
    "sg:classifiers":[
        {
            "category":"Health Services",
            "subcategory":"Health Practitioner",
            "type":"Services"
        }
    ],
    "sg:phone":"+1 509 382 4402",
    "sg:postcode":"99328",
    "sg:province":"WA",
    "sg:tags":[
        "dietitian"
    ],
    "wof:name":"Nutrition Care Made Simple",
    "wof:placetype":"venue"
},
  "geometry": {"coordinates":[-117.98553200000001,46.320029],"type":"Point"}
}