{
  "type": "Feature",
  "properties": {
    "iso:country":"US",
    "sg:address":"3221 Cottonwood Creek Rd",
    "sg:city":"Chewelah",
    "sg:classifiers":[
        {
            "category":"Freight",
            "type":"Transportation"
        }
    ],
    "sg:phone":"+1 509 935 6340",
    "sg:postcode":"99109",
    "sg:province":"WA",
    "sg:tags":[
        "operator",
        "local",
        "trucking"
    ],
    "wof:name":"Chris Smith Trucking",
    "wof:placetype":"venue"
},
  "geometry": {"coordinates":[-117.629041,48.201204],"type":"Point"}
}