{
  "type": "Feature",
  "properties": {
    "addr:full":"409 W Hastings Rd Spokane WA 99218",
    "addr:housenumber":"409",
    "addr:postcode":"99218",
    "addr:street":"W Hastings Rd",
    "iso:country":"US",
    "sg:address":"409 W Hastings Rd",
    "sg:city":"Spokane",
    "sg:classifiers":[
        {
            "category":"Sports & Exercise",
            "subcategory":"Gym",
            "type":"Entertainment"
        }
    ],
    "sg:phone":"+1 509 464 4545",
    "sg:postcode":"99218",
    "sg:province":"WA",
    "sg:tags":[
        "facility",
        "club",
        "gymnasium",
        "health",
        "fitness",
        "studio",
        "physical"
    ],
    "wof:name":"Neighborhood Fitness For Women",
    "wof:placetype":"venue"
},
  "geometry": {"coordinates":[-117.421812,47.76821],"type":"Point"}
}