{
  "type": "Feature",
  "properties": {
    "addr:full":"301 12th Ave Seattle WA 98122",
    "addr:housenumber":"301",
    "addr:postcode":"98122",
    "addr:street":"12Th Ave",
    "iso:country":"US",
    "sg:address":"301 12th Ave",
    "sg:city":"Seattle",
    "sg:classifiers":[
        {
            "category":"Education",
            "subcategory":"Special Training",
            "type":"Public Place"
        },
        {
            "category":"Sports & Exercise",
            "subcategory":"Playing Field",
            "type":"Entertainment"
        }
    ],
    "sg:phone":"+1 206 734 0046",
    "sg:postcode":"98122",
    "sg:province":"WA",
    "sg:tags":[
        "school",
        "instruction",
        "specialty",
        "fitness"
    ],
    "sg:website":"www.accelerateyourgame.webs.com/",
    "wof:name":"ACCELERATE Softball Instruction",
    "wof:placetype":"venue"
},
  "geometry": {"coordinates":[-122.31711300000001,47.604514],"type":"Point"}
}