{
  "type": "Feature",
  "properties": {
    "addr:full":"8518 Vickery Ave E Tacoma WA 98446",
    "addr:housenumber":"8518",
    "addr:postcode":"98446",
    "addr:street":"Vickery Ave E",
    "iso:country":"US",
    "sg:address":"8518 Vickery Ave E",
    "sg:city":"Tacoma",
    "sg:classifiers":[
        {
            "category":"Building & Trades",
            "subcategory":"Construction",
            "type":"Services"
        }
    ],
    "sg:phone":"+1 253 538 9647",
    "sg:postcode":"98446",
    "sg:province":"WA",
    "sg:tags":[
        "downspouts",
        "gutter",
        "contractor"
    ],
    "wof:name":"Allen's Custom Gutters",
    "wof:placetype":"venue"
},
  "geometry": {"coordinates":[-122.37845799999999,47.179647],"type":"Point"}
}