{
  "type": "Feature",
  "properties": {
    "addr:full":"20406 Little Bear Creek Rd Woodinville WA 98072",
    "addr:housenumber":"20406",
    "addr:postcode":"98072",
    "addr:street":"Little Bear Creek Rd",
    "iso:country":"US",
    "sg:address":"20406 Little Bear Creek Rd",
    "sg:city":"Woodinville",
    "sg:classifiers":[
        {
            "category":"Professional",
            "subcategory":"Management & Consulting",
            "type":"Services"
        }
    ],
    "sg:phone":"+1 425 483 7021",
    "sg:postcode":"98072",
    "sg:province":"WA",
    "sg:tags":[
        "business"
    ],
    "wof:name":"S J Mudie Enterprises",
    "wof:placetype":"venue"
},
  "geometry": {"coordinates":[-122.162297,47.811975],"type":"Point"}
}