{
  "type": "Feature",
  "properties": {
    "addr:full":"14349 Old Hwy 99 SE Tenino WA 98589",
    "addr:housenumber":"14349",
    "addr:postcode":"98589",
    "addr:street":"Old Hwy 99 Se Tenino",
    "iso:country":"US",
    "sg:address":"14349 Old Hwy 99 SE",
    "sg:city":"Tenino",
    "sg:classifiers":[
        {
            "category":"Building & Trades",
            "subcategory":"Construction",
            "type":"Services"
        }
    ],
    "sg:phone":"+1 360 264 6130",
    "sg:postcode":"98589",
    "sg:province":"WA",
    "sg:tags":[
        "contractor"
    ],
    "wof:name":"Stewart Brothers Construction",
    "wof:placetype":"venue"
},
  "geometry": {"coordinates":[-122.845764,46.878331],"type":"Point"}
}