{
  "type": "Feature",
  "properties": {
    "addr:full":"9623 32nd St SE Everett WA 98205",
    "addr:housenumber":"9623",
    "addr:postcode":"98205",
    "addr:street":"32Nd St Se",
    "iso:country":"US",
    "sg:address":"9623 32nd St SE",
    "sg:city":"Everett",
    "sg:classifiers":[
        {
            "category":"Insurance",
            "subcategory":"Insurance Agent",
            "type":"Services"
        },
        {
            "category":"Insurance",
            "subcategory":"Hazard Insurance",
            "type":"Services"
        },
        {
            "category":"Insurance",
            "subcategory":"Title Insurance",
            "type":"Services"
        },
        {
            "category":"Insurance",
            "subcategory":"Life Insurance",
            "type":"Services"
        }
    ],
    "sg:phone":"+1 425 212 9008",
    "sg:postcode":"98205",
    "sg:province":"WA",
    "sg:tags":[
        "business",
        "auto",
        "commercial",
        "homeowner",
        "motorcycle",
        "renter"
    ],
    "wof:name":"Allstate Insurance Company - Verla Calderon",
    "wof:placetype":"venue"
},
  "geometry": {"coordinates":[-122.101844,47.967306],"type":"Point"}
}