{
  "type": "Feature",
  "properties": {
    "addr:full":"1722 127th Pl SE Everett WA 98208",
    "addr:housenumber":"1722",
    "addr:postcode":"98208",
    "addr:street":"127Th Pl Se",
    "iso:country":"US",
    "sg:address":"1722 127th Pl SE",
    "sg:city":"Everett",
    "sg:classifiers":[
        {
            "category":"Building & Trades",
            "subcategory":"Construction",
            "type":"Services"
        }
    ],
    "sg:phone":"+1 425 486 7257",
    "sg:postcode":"98208",
    "sg:province":"WA",
    "sg:tags":[
        "house"
    ],
    "wof:name":"D N Construction",
    "wof:placetype":"venue"
},
  "geometry": {"coordinates":[-122.20972500000001,47.88223],"type":"Point"}
}