{
  "type": "Feature",
  "properties": {
    "addr:full":"18424 92nd Ave W Edmonds WA 98020",
    "addr:housenumber":"18424",
    "addr:postcode":"98020",
    "addr:street":"92Nd Ave W",
    "iso:country":"US",
    "sg:address":"18424 92nd Ave W",
    "sg:city":"Edmonds",
    "sg:classifiers":[
        {
            "category":"Real Estate",
            "subcategory":"Real Estate Operator",
            "type":"Services"
        }
    ],
    "sg:phone":"+1 425 697 5459",
    "sg:postcode":"98020",
    "sg:province":"WA",
    "sg:tags":[
        "apartment"
    ],
    "wof:name":"Bodine Property Management",
    "wof:placetype":"venue"
},
  "geometry": {"coordinates":[-122.356426,47.831248],"type":"Point"}
}