{
  "type": "Feature",
  "properties": {
    "addr:full":"17123 Vashon Hwy SW Vashon WA 98070",
    "addr:postcode":"17123;98070",
    "addr:street":"Vashon Hwy Sw",
    "iso:country":"US",
    "sg:address":"17123 Vashon Hwy SW",
    "sg:city":"Vashon",
    "sg:classifiers":[
        {
            "category":"Shopping",
            "subcategory":"Used Merchandise",
            "type":"Retail Goods"
        }
    ],
    "sg:phone":"+1 206 463 5963",
    "sg:postcode":"98070",
    "sg:province":"WA",
    "wof:name":"Old Dreams",
    "wof:placetype":"venue"
},
  "geometry": {"coordinates":[-122.460521,47.452075],"type":"Point"}
}