{
  "type": "Feature",
  "properties": {
    "addr:full":"6557 Sycamore Ave NW Seattle WA 98117",
    "addr:housenumber":"6557",
    "addr:postcode":"98117",
    "addr:street":"Sycamore Ave Nw",
    "iso:country":"US",
    "sg:address":"6557 Sycamore Ave NW",
    "sg:city":"Seattle",
    "sg:classifiers":[
        {
            "category":"Wholesale",
            "subcategory":"Non-durable Goods",
            "type":"Manufacturing & Wholesale Goods"
        }
    ],
    "sg:phone":"+1 206 783 1963",
    "sg:postcode":"98117",
    "sg:province":"WA",
    "sg:tags":[
        "dry",
        "goods-wholesale"
    ],
    "wof:name":"Randi K Starup Wholesalers",
    "wof:placetype":"venue"
},
  "geometry": {"coordinates":[-122.358446,47.677032],"type":"Point"}
}