{
  "type": "Feature",
  "properties": {
    "addr:full":"1221 S Main Street Seattle WA 98144",
    "addr:housenumber":"1221",
    "addr:postcode":"98144",
    "addr:street":"S Main Street",
    "iso:country":"US",
    "sg:address":"1221 S Main Street",
    "sg:city":"Seattle",
    "sg:classifiers":[
        {
            "category":"Shopping",
            "subcategory":"Pharmacy",
            "type":"Retail Goods"
        }
    ],
    "sg:phone":"+1 206 323 6003",
    "sg:postcode":"98144",
    "sg:province":"WA",
    "sg:tags":[
        "drugstore"
    ],
    "wof:name":"Nguyen's Pharmacy and Gifts",
    "wof:placetype":"venue"
},
  "geometry": {"coordinates":[-122.316321,47.600003],"type":"Point"}
}