{
  "type": "Feature",
  "properties": {
    "addr:full":"410 E King Ave Chewelah WA 99109",
    "addr:housenumber":"410",
    "addr:postcode":"99109",
    "addr:street":"E King Ave",
    "iso:country":"US",
    "sg:address":"410 E King Ave",
    "sg:city":"Chewelah",
    "sg:classifiers":[
        {
            "category":"Health Services",
            "subcategory":"Doctor",
            "type":"Services"
        }
    ],
    "sg:phone":"+1 509 935 8711",
    "sg:postcode":"99109",
    "sg:province":"WA",
    "sg:tags":[
        "physician",
        "family",
        "practice",
        "surgeons",
        "medicine"
    ],
    "wof:name":"Chewelah Associated Physicians",
    "wof:placetype":"venue"
},
  "geometry": {"coordinates":[-117.712459,48.275249],"type":"Point"}
}