{
  "type": "Feature",
  "properties": {
    "addr:full":"10245 NE Casey St Bainbridge Island WA 98110",
    "addr:housenumber":"10245",
    "addr:postcode":"98110",
    "addr:street":"Ne Casey St",
    "iso:country":"US",
    "sg:address":"10245 NE Casey St",
    "sg:city":"Bainbridge Island",
    "sg:classifiers":[
        {
            "category":"Retail",
            "subcategory":"Repair Shop",
            "type":"Services"
        }
    ],
    "sg:phone":"+1 206 842 8574",
    "sg:postcode":"98110",
    "sg:province":"WA",
    "wof:name":"Narimatsu Small Repair",
    "wof:placetype":"venue"
},
  "geometry": {"coordinates":[-122.510892,47.642987],"type":"Point"}
}