{
  "type": "Feature",
  "properties": {
    "addr:full":"305 N Ruby St Ellensburg WA 98926",
    "addr:housenumber":"305",
    "addr:postcode":"98926",
    "addr:street":"N Ruby St",
    "iso:country":"US",
    "sg:address":"305 N Ruby St",
    "sg:city":"Ellensburg",
    "sg:classifiers":[
        {
            "category":"Utilities",
            "subcategory":"Telephone",
            "type":"Services"
        },
        {
            "category":"Professional",
            "subcategory":"Computer Services",
            "type":"Services"
        }
    ],
    "sg:phone":"+1 509 697 9876",
    "sg:postcode":"98926",
    "sg:province":"WA",
    "sg:tags":[
        "distance",
        "long",
        "internet"
    ],
    "wof:name":"Ell Tel Long Distance",
    "wof:placetype":"venue"
},
  "geometry": {"coordinates":[-120.544606,46.995511],"type":"Point"}
}