{
  "type": "Feature",
  "properties": {
    "addr:full":"3020 E 12th Ave Spokane WA 99202",
    "addr:housenumber":"3020",
    "addr:postcode":"99202",
    "addr:street":"E 12Th Ave",
    "iso:country":"US",
    "sg:address":"3020 E 12th Ave",
    "sg:city":"Spokane",
    "sg:classifiers":[
        {
            "category":"Building & Trades",
            "subcategory":"Landscaping Services",
            "type":"Services"
        }
    ],
    "sg:phone":"+1 509 535 3583",
    "sg:postcode":"99202",
    "sg:province":"WA",
    "sg:tags":[
        "lawn",
        "maintenance",
        "grounds"
    ],
    "wof:name":"Elite Lawn & Tree Svc",
    "wof:placetype":"venue"
},
  "geometry": {"coordinates":[-117.36703300000001,47.643994],"type":"Point"}
}