{
  "type": "Feature",
  "properties": {
    "addr:full":"421 E Railroad Ave Cle Elum WA 98922",
    "addr:housenumber":"421",
    "addr:postcode":"98922",
    "addr:street":"E Railroad Ave",
    "iso:country":"US",
    "sg:address":"421 E Railroad Ave",
    "sg:city":"Cle Elum",
    "sg:classifiers":[
        {
            "category":"Retail",
            "subcategory":"Auto Repair",
            "type":"Services"
        }
    ],
    "sg:phone":"+1 509 674 7001",
    "sg:postcode":"98922",
    "sg:province":"WA",
    "sg:tags":[
        "automotive",
        "wrecker"
    ],
    "wof:name":"Cle Elum Towing",
    "wof:placetype":"venue"
},
  "geometry": {"coordinates":[-120.93189599999999,47.193193],"type":"Point"}
}