{
  "type": "Feature",
  "properties": {
    "addr:full":"411 N 90th St Seattle WA 98103",
    "addr:housenumber":"411",
    "addr:postcode":"98103",
    "addr:street":"N 90Th St",
    "iso:country":"US",
    "sg:address":"411 N 90th St",
    "sg:city":"Seattle",
    "sg:classifiers":[
        {
            "category":"Professional",
            "type":"Services"
        }
    ],
    "sg:phone":"+1 206 498 6900",
    "sg:postcode":"98103",
    "sg:province":"WA",
    "wof:name":"Eilers Residential Apprai",
    "wof:placetype":"venue"
},
  "geometry": {"coordinates":[-122.352732,47.694132],"type":"Point"}
}