{
  "type": "Feature",
  "properties": {
    "addr:full":"718 Kirkland Cir Kirkland WA 98033",
    "addr:housenumber":"718",
    "addr:postcode":"98033",
    "addr:street":"Kirkland Cir",
    "iso:country":"US",
    "sg:address":"718 Kirkland Cir",
    "sg:city":"Kirkland",
    "sg:classifiers":[
        {
            "category":"Real Estate",
            "subcategory":"Real Estate Agent",
            "type":"Services"
        }
    ],
    "sg:phone":"+1 425 614 2905",
    "sg:postcode":"98033",
    "sg:province":"WA",
    "wof:name":"AK Appraisal",
    "wof:placetype":"venue"
},
  "geometry": {"coordinates":[-122.194339,47.677687],"type":"Point"}
}