{
  "type": "Feature",
  "properties": {
    "addr:full":"12902 Wide Hollow Rd Yakima WA 98908",
    "addr:housenumber":"12902",
    "addr:postcode":"98908",
    "addr:street":"Wide Hollow Rd",
    "iso:country":"US",
    "sg:address":"12902 Wide Hollow Rd",
    "sg:city":"Yakima",
    "sg:classifiers":[
        {
            "category":"Freight",
            "type":"Transportation"
        }
    ],
    "sg:phone":"+1 509 972 0326",
    "sg:postcode":"98908",
    "sg:province":"WA",
    "sg:tags":[
        "operator",
        "trucking"
    ],
    "wof:name":"Ronald James Kerr",
    "wof:placetype":"venue"
},
  "geometry": {"coordinates":[-120.68279200000001,46.585714],"type":"Point"}
}