{
  "type": "Feature",
  "properties": {
    "addr:full":"6908 S Mason Ave Tacoma WA 98409",
    "addr:housenumber":"6908",
    "addr:postcode":"98409",
    "addr:street":"S Mason Ave",
    "iso:country":"US",
    "sg:address":"6908 S Mason Ave",
    "sg:city":"Tacoma",
    "sg:classifiers":[
        {
            "category":"Building & Trades",
            "subcategory":"Construction",
            "type":"Services"
        }
    ],
    "sg:phone":"+1 253 474 7544",
    "sg:postcode":"98409",
    "sg:province":"WA",
    "sg:tags":[
        "contractor"
    ],
    "wof:name":"Michaels Roof Service",
    "wof:placetype":"venue"
},
  "geometry": {"coordinates":[-122.494038,47.193587],"type":"Point"}
}