{
  "type": "Feature",
  "properties": {
    "addr:full":"15722 4th Ave SW Seattle WA 98166",
    "addr:housenumber":"15722",
    "addr:postcode":"98166",
    "addr:street":"4Th Ave Sw",
    "iso:country":"US",
    "sg:address":"15722 4th Ave SW",
    "sg:city":"Seattle",
    "sg:classifiers":[
        {
            "category":"Professional",
            "type":"Services"
        }
    ],
    "sg:phone":"+1 206 242 8185",
    "sg:postcode":"98166",
    "sg:province":"WA",
    "wof:name":"You Otter Be In Pictures",
    "wof:placetype":"venue"
},
  "geometry": {"coordinates":[-122.339142,47.462566],"type":"Point"}
}