{
  "type": "Feature",
  "properties": {
    "addr:full":"9103 Evergreen Way Everett WA 98204",
    "addr:housenumber":"9103",
    "addr:postcode":"98204",
    "addr:street":"Evergreen Way",
    "iso:country":"US",
    "sg:address":"9103 Evergreen Way",
    "sg:city":"Everett",
    "sg:classifiers":[
        {
            "category":"Personal",
            "subcategory":"Beauty Salon",
            "type":"Services"
        }
    ],
    "sg:phone":"+1 425 355 8330",
    "sg:postcode":"98204",
    "sg:province":"WA",
    "sg:tags":[
        "shop"
    ],
    "wof:name":"A Nu Image",
    "wof:placetype":"venue"
},
  "geometry": {"coordinates":[-122.23426600000001,47.915467],"type":"Point"}
}