{
  "type": "Feature",
  "properties": {
    "addr:full":"196 Springwater Ln Sequim WA 98382",
    "addr:housenumber":"196",
    "addr:postcode":"98382",
    "addr:street":"Springwater Ln",
    "iso:country":"US",
    "sg:address":"196 Springwater Ln",
    "sg:city":"Sequim",
    "sg:classifiers":[
        {
            "category":"Manufacturing",
            "subcategory":"Printing",
            "type":"Manufacturing & Wholesale Goods"
        }
    ],
    "sg:phone":"+1 360 683 7084",
    "sg:postcode":"98382",
    "sg:province":"WA",
    "sg:tags":[
        "publisher"
    ],
    "sg:website":"www.sellyourhouse.net",
    "wof:name":"Ideaworks Publishing Inc",
    "wof:placetype":"venue"
},
  "geometry": {"coordinates":[-123.102289,48.056604],"type":"Point"}
}