{
  "type": "Feature",
  "properties": {
    "addr:full":"6908 Ford Dr NW Gig Harbor WA 98335",
    "addr:housenumber":"6908",
    "addr:postcode":"98335",
    "addr:street":"Ford Dr Nw",
    "iso:country":"US",
    "sg:address":"6908 Ford Dr NW",
    "sg:city":"Gig Harbor",
    "sg:classifiers":[
        {
            "category":"Building & Trades",
            "subcategory":"Construction",
            "type":"Services"
        }
    ],
    "sg:phone":"+1 253 265 3726",
    "sg:postcode":"98335",
    "sg:province":"WA",
    "sg:tags":[
        "carpentry",
        "contractor"
    ],
    "wof:name":"Watts Construction",
    "wof:placetype":"venue"
},
  "geometry": {"coordinates":[-122.628927,47.280321],"type":"Point"}
}