{
  "type": "Feature",
  "properties": {
    "addr:full":"3300 NE 3rd Ave Camas WA 98607",
    "addr:housenumber":"3300",
    "addr:postcode":"98607",
    "addr:street":"Ne 3Rd Ave",
    "iso:country":"US",
    "sg:address":"3300 NE 3rd Ave",
    "sg:city":"Camas",
    "sg:classifiers":[
        {
            "category":"Food & Beverages",
            "subcategory":"Groceries & Convenience Stores",
            "type":"Retail Goods"
        }
    ],
    "sg:phone":"+1 360 835 7675",
    "sg:postcode":"98607",
    "sg:province":"WA",
    "sg:tags":[
        "super",
        "supermarket"
    ],
    "wof:name":"Camas Thriftway",
    "wof:placetype":"venue"
},
  "geometry": {"coordinates":[-122.36981299999999,45.585101],"type":"Point"}
}