{
  "type": "Feature",
  "properties": {
    "addr:full":"9533 Mose Rd Arlington WA 98223",
    "addr:housenumber":"9533",
    "addr:postcode":"98223",
    "addr:street":"Mose Rd",
    "iso:country":"US",
    "sg:address":"9533 Mose Rd",
    "sg:city":"Arlington",
    "sg:classifiers":[
        {
            "category":"Home & Garden",
            "subcategory":"Garden Supply",
            "type":"Retail Goods"
        }
    ],
    "sg:phone":"+1 360 435 9799",
    "sg:postcode":"98223",
    "sg:province":"WA",
    "sg:tags":[
        "tree",
        "christmas"
    ],
    "wof:name":"Pilchuck Secret Vly Christmas",
    "wof:placetype":"venue"
},
  "geometry": {"coordinates":[-122.10904600000001,48.223177],"type":"Point"}
}