{
  "type": "Feature",
  "properties": {
    "addr:full":"475 N Bend Blvd N North Bend WA 98045",
    "addr:housenumber":"475",
    "addr:postcode":"98045",
    "addr:street":"N Bend Blvd N",
    "iso:country":"US",
    "sg:address":"475 N Bend Blvd N",
    "sg:city":"North Bend",
    "sg:classifiers":[
        {
            "category":"Building & Trades",
            "subcategory":"Cleaning & Sanitation",
            "type":"Services"
        }
    ],
    "sg:phone":"+1 425 831 6916",
    "sg:postcode":"98045",
    "sg:province":"WA",
    "sg:tags":[
        "maintenance"
    ],
    "wof:name":"All Purpose Cleaning Serv",
    "wof:placetype":"venue"
},
  "geometry": {"coordinates":[-121.788928,47.499519],"type":"Point"}
}