{
  "type": "Feature",
  "properties": {
    "addr:full":"23711 N Wagon Rd Colbert WA 99005",
    "addr:housenumber":"23711",
    "addr:postcode":"99005",
    "addr:street":"N Wagon Rd Colbert",
    "iso:country":"US",
    "sg:address":"23711 N Wagon Rd",
    "sg:city":"Colbert",
    "sg:classifiers":[
        {
            "category":"Wholesale",
            "subcategory":"Farm Supplies",
            "type":"Manufacturing & Wholesale Goods"
        }
    ],
    "sg:phone":"+1 509 238 4464",
    "sg:postcode":"99005",
    "sg:province":"WA",
    "sg:tags":[
        "chemical",
        "agricultural"
    ],
    "wof:name":"Monsanto Co",
    "wof:placetype":"venue"
},
  "geometry": {"coordinates":[-117.338938,47.874414],"type":"Point"}
}