{
  "type": "Feature",
  "properties": {
    "addr:full":"13029 Northup Way NE Bellevue WA 98005",
    "addr:housenumber":"13029",
    "addr:postcode":"98005",
    "addr:street":"Northup Way Ne",
    "iso:country":"US",
    "sg:address":"13029 Northup Way NE",
    "sg:city":"Bellevue",
    "sg:classifiers":[
        {
            "category":"Communications",
            "subcategory":"Film & Video Production",
            "type":"Services"
        }
    ],
    "sg:phone":"+1 206 236 3133",
    "sg:postcode":"98005",
    "sg:province":"WA",
    "sg:tags":[
        "motion"
    ],
    "wof:name":"Marlowe Productions",
    "wof:placetype":"venue"
},
  "geometry": {"coordinates":[-122.16523100000001,47.627976],"type":"Point"}
}