{
  "type": "Feature",
  "properties": {
    "addr:full":"25518 174th St SE Monroe WA 98272",
    "addr:housenumber":"25518",
    "addr:postcode":"98272",
    "addr:street":"174Th St Se",
    "iso:country":"US",
    "sg:address":"25518 174th St SE",
    "sg:city":"Monroe",
    "sg:classifiers":[
        {
            "category":"Social Services",
            "subcategory":"Child Care",
            "type":"Services"
        }
    ],
    "sg:phone":"+1 360 794 9501",
    "sg:postcode":"98272",
    "sg:province":"WA",
    "sg:tags":[
        "day"
    ],
    "wof:name":"O Kay Korral",
    "wof:placetype":"venue"
},
  "geometry": {"coordinates":[-121.88929400000001,47.839611],"type":"Point"}
}