{
  "type": "Feature",
  "properties": {
    "addr:full":"10650 SE 180th Pl Renton WA 98055",
    "addr:housenumber":"10650",
    "addr:postcode":"98055",
    "addr:street":"Se 180Th Pl",
    "iso:country":"US",
    "sg:address":"10650 SE 180th Pl",
    "sg:city":"Renton",
    "sg:classifiers":[
        {
            "category":"Wholesale",
            "subcategory":"Auto Parts",
            "type":"Manufacturing & Wholesale Goods"
        }
    ],
    "sg:phone":"+1 425 228 5315",
    "sg:postcode":"98055",
    "sg:province":"WA",
    "sg:tags":[
        "muffler",
        "repair",
        "radiator",
        "brakes"
    ],
    "wof:name":"Walts Radiator & Muffler Inc",
    "wof:placetype":"venue"
},
  "geometry": {"coordinates":[-122.198442,47.440914],"type":"Point"}
}