{
  "type": "Feature",
  "properties": {
    "addr:full":"1333 Corona St Port Townsend WA 98368",
    "addr:housenumber":"1333",
    "addr:postcode":"98368",
    "addr:street":"Corona St",
    "iso:country":"US",
    "sg:address":"1333 Corona St",
    "sg:city":"Port Townsend",
    "sg:classifiers":[
        {
            "category":"Retail",
            "subcategory":"Portrait Studio",
            "type":"Services"
        }
    ],
    "sg:phone":"+1 360 379 9045",
    "sg:postcode":"98368",
    "sg:province":"WA",
    "sg:tags":[
        "photographer",
        "photo"
    ],
    "wof:name":"Manning's Photo Co",
    "wof:placetype":"venue"
},
  "geometry": {"coordinates":[-122.79368100000001,48.125158],"type":"Point"}
}