{
  "type": "Feature",
  "properties": {
    "addr:full":"1635 Grove St Marysville WA 98270",
    "addr:housenumber":"1635",
    "addr:postcode":"98270",
    "addr:street":"Grove St",
    "iso:country":"US",
    "sg:address":"1635 Grove St",
    "sg:city":"Marysville",
    "sg:classifiers":[
        {
            "category":"Professional",
            "subcategory":"Management & Consulting",
            "type":"Services"
        }
    ],
    "sg:phone":"+1 360 659 5674",
    "sg:postcode":"98270",
    "sg:province":"WA",
    "sg:tags":[
        "business"
    ],
    "wof:name":"Natron Consulting",
    "wof:placetype":"venue"
},
  "geometry": {"coordinates":[-122.173682,48.061334],"type":"Point"}
}