{
  "type": "Feature",
  "properties": {
    "addr:full":"13043 NE 1st St Bellevue WA 98005",
    "addr:housenumber":"13043",
    "addr:postcode":"98005",
    "addr:street":"Ne 1St St",
    "iso:country":"US",
    "sg:address":"13043 NE 1st St",
    "sg:city":"Bellevue",
    "sg:classifiers":[
        {
            "category":"Building & Trades",
            "subcategory":"Construction",
            "type":"Services"
        }
    ],
    "sg:phone":"+1 206 953 9606",
    "sg:postcode":"98005",
    "sg:province":"WA",
    "sg:tags":[
        "general",
        "contractor"
    ],
    "wof:name":"Jergens Construction Company",
    "wof:placetype":"venue"
},
  "geometry": {"coordinates":[-122.165407,47.610365],"type":"Point"}
}