{
  "type": "Feature",
  "properties": {
    "addr:full":"1695 S 13th Ave Kelso WA 98626",
    "addr:housenumber":"1695",
    "addr:postcode":"98626",
    "addr:street":"S 13Th Ave",
    "iso:country":"US",
    "sg:address":"1695 S 13th Ave",
    "sg:city":"Kelso",
    "sg:classifiers":[
        {
            "category":"Manufacturing",
            "subcategory":"Tools & Machinery",
            "type":"Manufacturing & Wholesale Goods"
        }
    ],
    "sg:phone":"+1 360 423 9071",
    "sg:postcode":"98626",
    "sg:province":"WA",
    "sg:tags":[
        "machine",
        "shop"
    ],
    "wof:name":"Williams Precision Machine",
    "wof:placetype":"venue"
},
  "geometry": {"coordinates":[-122.90074199999999,46.127953],"type":"Point"}
}