{
  "type": "Feature",
  "properties": {
    "addr:full":"19709 Bothell Everett Hwy Bothell WA 98012",
    "addr:housenumber":"19709",
    "addr:postcode":"98012",
    "addr:street":"Bothell Everett Hwy",
    "iso:country":"US",
    "sg:address":"19709 Bothell Everett Hwy",
    "sg:city":"Bothell",
    "sg:classifiers":[
        {
            "category":"Professional",
            "subcategory":"Business Services",
            "type":"Services"
        }
    ],
    "sg:phone":"+1 425 485 2069",
    "sg:postcode":"98012",
    "sg:province":"WA",
    "wof:name":"Scolan Enterprises",
    "wof:placetype":"venue"
},
  "geometry": {"coordinates":[-122.207399,47.81899],"type":"Point"}
}