{
  "type": "Feature",
  "properties": {
    "addr:full":"10021 Olalla Valley Rd SE Olalla WA 98359",
    "addr:postcode":"10021;98359",
    "addr:street":"Valley Rd Se Olalla",
    "iso:country":"US",
    "sg:address":"10021 Olalla Valley Rd SE",
    "sg:city":"Olalla",
    "sg:classifiers":[
        {
            "category":"Professional",
            "type":"Services"
        }
    ],
    "sg:phone":"+1 253 857 6462",
    "sg:postcode":"98359",
    "sg:province":"WA",
    "wof:name":"Kerr Systems",
    "wof:placetype":"venue"
},
  "geometry": {"coordinates":[-122.572855,47.461399],"type":"Point"}
}