{
  "type": "Feature",
  "properties": {
    "iso:country":"US",
    "sg:address":"1012 Dolfay Ln",
    "sg:city":"East Wenatchee",
    "sg:classifiers":[
        {
            "category":"Building & Trades",
            "subcategory":"Electrical",
            "type":"Services"
        }
    ],
    "sg:phone":"+1 509 884 4434",
    "sg:postcode":"98802",
    "sg:province":"WA",
    "sg:tags":[
        "electric",
        "contractor"
    ],
    "wof:name":"Rivercity Electric",
    "wof:placetype":"venue"
},
  "geometry": {"coordinates":[-120.285427,47.420383],"type":"Point"}
}