{
  "type": "Feature",
  "properties": {
    "addr:full":"7799 Nahahum Canyon Rd Cashmere WA 98815",
    "addr:housenumber":"7799",
    "addr:postcode":"98815",
    "addr:street":"Nahahum Canyon Rd",
    "iso:country":"US",
    "sg:address":"7799 Nahahum Canyon Rd",
    "sg:city":"Cashmere",
    "sg:classifiers":[
        {
            "category":"Organizations",
            "subcategory":"Religious Organization",
            "type":"Services"
        },
        {
            "category":"Education",
            "subcategory":"School",
            "type":"Public Place"
        }
    ],
    "sg:phone":"+1 509 782 1499",
    "sg:postcode":"98815",
    "sg:province":"WA",
    "wof:name":"Mountain View Adventist School",
    "wof:placetype":"venue"
},
  "geometry": {"coordinates":[-120.43480700000001,47.557254],"type":"Point"}
}