{
  "type": "Feature",
  "properties": {
    "addr:full":"1112 N Nelson St Spokane WA 99202",
    "addr:housenumber":"1112",
    "addr:postcode":"99202",
    "addr:street":"N Nelson St",
    "iso:country":"US",
    "sg:address":"1112 N Nelson St",
    "sg:city":"Spokane",
    "sg:classifiers":[
        {
            "category":"Building & Trades",
            "subcategory":"Plumbing",
            "type":"Services"
        }
    ],
    "sg:phone":"+1 509 325 4505",
    "sg:postcode":"99202",
    "sg:province":"WA",
    "sg:tags":[
        "system",
        "heating",
        "contractor",
        "air conditioning"
    ],
    "sg:website":"http://find.trane.com/tcs-dealer-411381?utm_source=YP&utm_medium=banner&utm_campaign=TL",
    "wof:name":"Sturm Heating, Inc.",
    "wof:placetype":"venue"
},
  "geometry": {"coordinates":[-117.36921,47.667656],"type":"Point"}
}