{
  "type": "Feature",
  "properties": {
    "addr:full":"2705 W Sylvester St Pasco WA 99301",
    "addr:housenumber":"2705",
    "addr:postcode":"99301",
    "addr:street":"W Sylvester St",
    "iso:country":"US",
    "sg:address":"2705 W Sylvester St",
    "sg:city":"Pasco",
    "sg:classifiers":[
        {
            "category":"Wholesale",
            "subcategory":"Durable Goods & Equipment",
            "type":"Manufacturing & Wholesale Goods"
        }
    ],
    "sg:phone":"+1 509 544 9394",
    "sg:postcode":"99301",
    "sg:province":"WA",
    "wof:name":"Thrifty Supply",
    "wof:placetype":"venue"
},
  "geometry": {"coordinates":[-119.127954,46.234243],"type":"Point"}
}