{
  "type": "Feature",
  "properties": {
    "addr:full":"12320 SW Cemetery Rd Vashon WA 98070",
    "addr:housenumber":"12320",
    "addr:postcode":"98070",
    "addr:street":"Sw Cemetery Rd",
    "iso:country":"US",
    "sg:address":"12320 SW Cemetery Rd",
    "sg:city":"Vashon",
    "sg:classifiers":[
        {
            "category":"Building & Trades",
            "subcategory":"Construction",
            "type":"Services"
        }
    ],
    "sg:phone":"+1 206 463 3508",
    "sg:postcode":"98070",
    "sg:province":"WA",
    "sg:tags":[
        "roofing",
        "contractor"
    ],
    "wof:name":"Alumbaugh Roofing",
    "wof:placetype":"venue"
},
  "geometry": {"coordinates":[-122.492707,47.429218],"type":"Point"}
}