{
  "type": "Feature",
  "properties": {
    "addr:full":"3048 Issaquah Pine Lake Rd SE R Sammamish WA 98075",
    "addr:postcode":"3048;98075",
    "addr:street":"Pine Lake Rd Se R",
    "iso:country":"US",
    "sg:address":"3048 Issaquah Pine Lake Rd SE R",
    "sg:city":"Sammamish",
    "sg:classifiers":[
        {
            "category":"Retail",
            "subcategory":"Laundry & Dry Cleaning",
            "type":"Services"
        }
    ],
    "sg:phone":"+1 425 392 7252",
    "sg:postcode":"98075",
    "sg:province":"WA",
    "sg:tags":[
        "cleaner",
        "commercial"
    ],
    "sg:website":"http://www.drycleanusa.com",
    "wof:name":"S A Dryclean-U",
    "wof:placetype":"venue"
},
  "geometry": {"coordinates":[-122.033755,47.581973],"type":"Point"}
}