{
  "type": "Feature",
  "properties": {
    "addr:full":"465 Sauk Ave Darrington WA 98241",
    "addr:housenumber":"465",
    "addr:postcode":"98241",
    "addr:street":"Sauk Ave",
    "iso:country":"US",
    "sg:address":"465 Sauk Ave",
    "sg:city":"Darrington",
    "sg:classifiers":[
        {
            "category":"Communications",
            "subcategory":"Film & Video Production",
            "type":"Services"
        }
    ],
    "sg:phone":"+1 360 436 1065",
    "sg:postcode":"98241",
    "sg:province":"WA",
    "sg:tags":[
        "taping"
    ],
    "wof:name":"Master's Touch Video Svc",
    "wof:placetype":"venue"
},
  "geometry": {"coordinates":[-121.60466099999999,48.245105],"type":"Point"}
}