{
  "type": "Feature",
  "properties": {
    "addr:full":"11310 Farm To Market Rd Mount Vernon WA 98273",
    "addr:housenumber":"11310",
    "addr:postcode":"98273",
    "addr:street":"Farm To Market Rd",
    "iso:country":"US",
    "sg:address":"11310 Farm To Market Rd",
    "sg:city":"Mount Vernon",
    "sg:classifiers":[
        {
            "category":"Building & Trades",
            "subcategory":"Construction",
            "type":"Services"
        }
    ],
    "sg:phone":"+1 360 707 0336",
    "sg:postcode":"98273",
    "sg:province":"WA",
    "sg:tags":[
        "commercial"
    ],
    "wof:name":"North Left Coast Ltd",
    "wof:placetype":"venue"
},
  "geometry": {"coordinates":[-122.44411700000001,48.482247],"type":"Point"}
}