{
  "type": "Feature",
  "properties": {
    "addr:full":"4901 Center St Tacoma WA 98409",
    "addr:housenumber":"4901",
    "addr:postcode":"98409",
    "addr:street":"Center St",
    "iso:country":"US",
    "sg:address":"4901 Center St",
    "sg:city":"Tacoma",
    "sg:classifiers":[
        {
            "category":"Manufacturing",
            "subcategory":"Printing",
            "type":"Manufacturing & Wholesale Goods"
        }
    ],
    "sg:phone":"+1 253 564 4600",
    "sg:postcode":"98409",
    "sg:province":"WA",
    "sg:tags":[
        "commercial",
        "lithographic"
    ],
    "wof:name":"Pumpskins",
    "wof:placetype":"venue"
},
  "geometry": {"coordinates":[-122.501964,47.234469],"type":"Point"}
}