{
  "type": "Feature",
  "properties": {
    "addr:full":"7879 S Superior Ave Concrete WA 98237",
    "addr:housenumber":"7879",
    "addr:postcode":"98237",
    "addr:street":"S Superior Ave",
    "iso:country":"US",
    "sg:address":"7879 S Superior Ave",
    "sg:city":"Concrete",
    "sg:classifiers":[
        {
            "category":"Manufacturing",
            "subcategory":"Printing",
            "type":"Manufacturing & Wholesale Goods"
        }
    ],
    "sg:phone":"+1 360 853 7935",
    "sg:postcode":"98237",
    "sg:province":"WA",
    "sg:tags":[
        "book"
    ],
    "wof:name":"D&K Enterprises",
    "wof:placetype":"venue"
},
  "geometry": {"coordinates":[-121.759,48.531195],"type":"Point"}
}