{
  "type": "Feature",
  "properties": {
    "addr:full":"2020 Orchard Rd Ellensburg WA 98926",
    "addr:housenumber":"2020",
    "addr:postcode":"98926",
    "addr:street":"Orchard Rd",
    "iso:country":"US",
    "sg:address":"2020 Orchard Rd",
    "sg:city":"Ellensburg",
    "sg:classifiers":[
        {
            "category":"Farming",
            "subcategory":"Orchard",
            "type":"Manufacturing & Wholesale Goods"
        }
    ],
    "sg:phone":"+1 509 925 6642",
    "sg:postcode":"98926",
    "sg:province":"WA",
    "wof:name":"Sundance Orchards",
    "wof:placetype":"venue"
},
  "geometry": {"coordinates":[-120.45554199999999,46.922798],"type":"Point"}
}