{
  "type": "Feature",
  "properties": {
    "addr:full":"16576 NE 97th Pl Redmond WA 98052",
    "addr:housenumber":"16576",
    "addr:postcode":"98052",
    "addr:street":"Ne 97Th Pl",
    "iso:country":"US",
    "sg:address":"16576 NE 97th Pl",
    "sg:city":"Redmond",
    "sg:classifiers":[
        {
            "category":"Building & Trades",
            "subcategory":"Landscaping Services",
            "type":"Services"
        }
    ],
    "sg:phone":"+1 425 885 6821",
    "sg:postcode":"98052",
    "sg:province":"WA",
    "wof:name":"Stevens Landscaping",
    "wof:placetype":"venue"
},
  "geometry": {"coordinates":[-122.11839000000001,47.687048],"type":"Point"}
}