{
  "type": "Feature",
  "properties": {
    "addr:full":"611 SE Kaiser Ave Vancouver WA 98661",
    "addr:housenumber":"611",
    "addr:postcode":"98661",
    "addr:street":"Se Kaiser Ave",
    "iso:country":"US",
    "sg:address":"611 SE Kaiser Ave",
    "sg:city":"Vancouver",
    "sg:classifiers":[
        {
            "category":"Manufacturing",
            "subcategory":"Signs",
            "type":"Manufacturing & Wholesale Goods"
        }
    ],
    "sg:phone":"+1 360 750 6810",
    "sg:postcode":"98661",
    "sg:province":"WA",
    "wof:name":"L A Graphics",
    "wof:placetype":"venue"
},
  "geometry": {"coordinates":[-122.64303,45.615877],"type":"Point"}
}