{
  "type": "Feature",
  "properties": {
    "addr:full":"3405 Lincoln Ave Tacoma WA 98421",
    "addr:housenumber":"3405",
    "addr:postcode":"98421",
    "addr:street":"Lincoln Ave",
    "iso:country":"US",
    "sg:address":"3405 Lincoln Ave",
    "sg:city":"Tacoma",
    "sg:classifiers":[
        {
            "category":"Professional",
            "subcategory":"Business Services",
            "type":"Services"
        }
    ],
    "sg:phone":"+1 253 272 4682",
    "sg:postcode":"98421",
    "sg:province":"WA",
    "sg:tags":[
        "packaging"
    ],
    "wof:name":"Glacier Packaging Inc",
    "wof:placetype":"venue"
},
  "geometry": {"coordinates":[-122.386083,47.269382],"type":"Point"}
}