{
  "type": "Feature",
  "properties": {
    "iso:country":"US",
    "sg:address":"14714 Pacific Ave S",
    "sg:city":"Tacoma",
    "sg:classifiers":[
        {
            "category":"Retail",
            "subcategory":"Auto Repair",
            "type":"Services"
        }
    ],
    "sg:phone":"+1 253 535 1500",
    "sg:postcode":"98444",
    "sg:province":"WA",
    "sg:tags":[
        "muffler",
        "exhaust",
        "system"
    ],
    "wof:name":"Midas Auto Svc Experts",
    "wof:placetype":"venue"
},
  "geometry": {"coordinates":[-122.434927,47.123357],"type":"Point"}
}