{
  "type": "Feature",
  "properties": {
    "addr:full":"218 N Oak St Colville WA 99114",
    "addr:housenumber":"218",
    "addr:postcode":"99114",
    "addr:street":"N Oak St",
    "iso:country":"US",
    "sg:address":"218 N Oak St",
    "sg:city":"Colville",
    "sg:classifiers":[
        {
            "category":"Personal",
            "type":"Services"
        },
        {
            "category":"Personal",
            "subcategory":"Beauty Salon",
            "type":"Services"
        }
    ],
    "sg:phone":"+1 509 685 9344",
    "sg:postcode":"99114",
    "sg:province":"WA",
    "sg:tags":[
        "shop",
        "electrolysis"
    ],
    "wof:name":"Robinson Electrolysis Clinic",
    "wof:placetype":"venue"
},
  "geometry": {"coordinates":[-117.904295,48.546369],"type":"Point"}
}