{
  "type": "Feature",
  "properties": {
    "addr:full":"1600 S 13th Ave Kelso WA 98626",
    "addr:housenumber":"1600",
    "addr:postcode":"98626",
    "addr:street":"S 13Th Ave",
    "iso:country":"US",
    "sg:address":"1600 S 13th Ave",
    "sg:city":"Kelso",
    "sg:classifiers":[
        {
            "category":"Professional",
            "subcategory":"Management & Consulting",
            "type":"Services"
        }
    ],
    "sg:phone":"+1 360 578 3817",
    "sg:postcode":"98626",
    "sg:province":"WA",
    "sg:tags":[
        "forestry",
        "building",
        "road"
    ],
    "wof:name":"Niemi Forestry",
    "wof:placetype":"venue"
},
  "geometry": {"coordinates":[-122.90075299999999,46.128949],"type":"Point"}
}