{
  "type": "Feature",
  "properties": {
    "addr:full":"1800 Cooks Hill Rd Centralia WA 98531",
    "addr:housenumber":"1800",
    "addr:postcode":"98531",
    "addr:street":"Cooks Hill Rd",
    "iso:country":"US",
    "sg:address":"1800 Cooks Hill Rd",
    "sg:city":"Centralia",
    "sg:classifiers":[
        {
            "category":"Health Services",
            "subcategory":"Doctor",
            "type":"Services"
        }
    ],
    "sg:phone":"+1 360 330 2634",
    "sg:postcode":"98531",
    "sg:province":"WA",
    "sg:tags":[
        "physician",
        "surgeon"
    ],
    "wof:name":"Hogg, Katherine M Md",
    "wof:placetype":"venue"
},
  "geometry": {"coordinates":[-122.98333700000001,46.71373],"type":"Point"}
}