{
  "type": "Feature",
  "properties": {
    "addr:full":"1270 E Spencer Ct La Center WA 98629",
    "addr:housenumber":"1270",
    "addr:postcode":"98629",
    "addr:street":"E Spencer Ct",
    "iso:country":"US",
    "sg:address":"1270 E Spencer Ct",
    "sg:city":"La Center",
    "sg:classifiers":[
        {
            "category":"Professional",
            "subcategory":"Secretarial Services",
            "type":"Services"
        }
    ],
    "sg:phone":"+1 360 600 3781",
    "sg:postcode":"98629",
    "sg:province":"WA",
    "sg:tags":[
        "reporting"
    ],
    "wof:name":"Transcriptions Unlimited",
    "wof:placetype":"venue"
},
  "geometry": {"coordinates":[-122.66337900000001,45.866757],"type":"Point"}
}