{
  "type": "Feature",
  "properties": {
    "addr:full":"11605 Bridgeport Way SW Lakewood WA 98499",
    "addr:housenumber":"11605",
    "addr:postcode":"98499",
    "addr:street":"Bridgeport Way Sw",
    "iso:country":"US",
    "sg:address":"11605 Bridgeport Way SW",
    "sg:city":"Lakewood",
    "sg:classifiers":[
        {
            "category":"Home & Garden",
            "subcategory":"Furniture",
            "type":"Retail Goods"
        }
    ],
    "sg:phone":"+1 253 581 2454",
    "sg:postcode":"98499",
    "sg:province":"WA",
    "sg:tags":[
        "store"
    ],
    "sg:website":"www.jsktreasurechest.com",
    "wof:name":"Treasure Chest",
    "wof:placetype":"venue"
},
  "geometry": {"coordinates":[-122.503998,47.151699],"type":"Point"}
}