{
  "type": "Feature",
  "properties": {
    "iso:country":"US",
    "sg:address":"702 S 48th Ave",
    "sg:city":"Yakima",
    "sg:classifiers":[
        {
            "category":"Building & Trades",
            "subcategory":"Landscaping Services",
            "type":"Services"
        }
    ],
    "sg:phone":"+1 509 965 4521",
    "sg:postcode":"98908",
    "sg:province":"WA",
    "sg:tags":[
        "horticulture"
    ],
    "wof:name":"Everclear Systems LLC",
    "wof:placetype":"venue"
},
  "geometry": {"coordinates":[-120.572382,46.590386],"type":"Point"}
}