{
  "type": "Feature",
  "properties": {
    "addr:full":"9020 S Hosmer St Tacoma WA 98444",
    "addr:housenumber":"9020",
    "addr:postcode":"98444",
    "addr:street":"S Hosmer St",
    "iso:country":"US",
    "sg:address":"9020 S Hosmer St",
    "sg:city":"Tacoma",
    "sg:classifiers":[
        {
            "category":"Personal",
            "subcategory":"Beauty Salon",
            "type":"Services"
        }
    ],
    "sg:phone":"+1 253 537 2727",
    "sg:postcode":"98444",
    "sg:province":"WA",
    "wof:name":"Camelot Styling Salon",
    "wof:placetype":"venue"
},
  "geometry": {"coordinates":[-122.46319699999999,47.17503],"type":"Point"}
}