{
  "type": "Feature",
  "properties": {
    "addr:full":"8210 64th Street Ct W Tacoma WA 98467",
    "addr:housenumber":"8210",
    "addr:postcode":"98467",
    "addr:street":"64Th Street Ct W",
    "iso:country":"US",
    "sg:address":"8210 64th Street Ct W",
    "sg:city":"Tacoma",
    "sg:classifiers":[
        {
            "category":"Travel",
            "subcategory":"Travel Agent",
            "type":"Entertainment"
        }
    ],
    "sg:phone":"+1 253 564 2260",
    "sg:postcode":"98467",
    "sg:province":"WA",
    "sg:tags":[
        "agency"
    ],
    "wof:name":"Tjhung Kayak Journeys",
    "wof:placetype":"venue"
},
  "geometry": {"coordinates":[-122.544709,47.198416],"type":"Point"}
}