{
  "type": "Feature",
  "properties": {
    "addr:full":"433 E Trevor Rd Colbert WA 99005",
    "addr:housenumber":"433",
    "addr:postcode":"99005",
    "addr:street":"E Trevor Rd Colbert",
    "iso:country":"US",
    "sg:address":"433 E Trevor Rd",
    "sg:city":"Colbert",
    "sg:classifiers":[
        {
            "category":"Building & Trades",
            "subcategory":"Construction",
            "type":"Services"
        }
    ],
    "sg:phone":"+1 509 464 1610",
    "sg:postcode":"99005",
    "sg:province":"WA",
    "sg:tags":[
        "contractor"
    ],
    "sg:website":"www.greathousedesign.net",
    "wof:name":"Great House Design",
    "wof:placetype":"venue"
},
  "geometry": {"coordinates":[-117.341335,47.823741],"type":"Point"}
}