{
  "type": "Feature",
  "properties": {
    "addr:full":"191 Birch Bay Lynden Rd Lynden WA 98264",
    "addr:housenumber":"191",
    "addr:postcode":"98264",
    "addr:street":"Birch Bay Lynden Rd",
    "iso:country":"US",
    "sg:address":"191 Birch Bay Lynden Rd",
    "sg:city":"Lynden",
    "sg:classifiers":[
        {
            "category":"Retail",
            "subcategory":"Laundry & Dry Cleaning",
            "type":"Services"
        }
    ],
    "sg:phone":"+1 360 354 4145",
    "sg:postcode":"98264",
    "sg:province":"WA",
    "sg:tags":[
        "re",
        "upholstery",
        "janitorial",
        "carpet"
    ],
    "wof:name":"Northwest Cleaning Supply",
    "wof:placetype":"venue"
},
  "geometry": {"coordinates":[-122.489018,48.935132],"type":"Point"}
}