{
  "type": "Feature",
  "properties": {
    "addr:full":"16220 NE 169th Pl Woodinville WA 98072",
    "addr:housenumber":"16220",
    "addr:postcode":"98072",
    "addr:street":"Ne 169Th Pl",
    "iso:country":"US",
    "sg:address":"16220 NE 169th Pl",
    "sg:city":"Woodinville",
    "sg:classifiers":[
        {
            "category":"Building & Trades",
            "subcategory":"Landscaping Services",
            "type":"Services"
        }
    ],
    "sg:phone":"+1 425 483 9264",
    "sg:postcode":"98072",
    "sg:province":"WA",
    "wof:name":"Dahlstrom Landscaping",
    "wof:placetype":"venue"
},
  "geometry": {"coordinates":[-122.12209900000001,47.750376],"type":"Point"}
}