{
  "type": "Feature",
  "properties": {
    "addr:full":"1804 NW Lutes Rd Poulsbo WA 98370",
    "addr:housenumber":"1804",
    "addr:postcode":"98370",
    "addr:street":"Nw Lutes Rd",
    "iso:country":"US",
    "sg:address":"1804 NW Lutes Rd",
    "sg:city":"Poulsbo",
    "sg:classifiers":[
        {
            "category":"Professional",
            "subcategory":"Engineering",
            "type":"Services"
        }
    ],
    "sg:phone":"+1 360 779 4244",
    "sg:postcode":"98370",
    "sg:province":"WA",
    "sg:tags":[
        "engineer"
    ],
    "wof:name":"R L Morrison Engineering Co",
    "wof:placetype":"venue"
},
  "geometry": {"coordinates":[-122.675355,47.800405],"type":"Point"}
}