{
  "type": "Feature",
  "properties": {
    "addr:full":"2147 Lummi Shore Rd Bellingham WA 98226",
    "addr:housenumber":"2147",
    "addr:postcode":"98226",
    "addr:street":"Lummi Shore Rd",
    "iso:country":"US",
    "sg:address":"2147 Lummi Shore Rd",
    "sg:city":"Bellingham",
    "sg:classifiers":[
        {
            "category":"Wholesale",
            "subcategory":"Jewelry",
            "type":"Manufacturing & Wholesale Goods"
        }
    ],
    "sg:phone":"+1 360 758 2430",
    "sg:postcode":"98226",
    "sg:province":"WA",
    "sg:tags":[
        "stone"
    ],
    "wof:name":"Hand Beading By Dee",
    "wof:placetype":"venue"
},
  "geometry": {"coordinates":[-122.64663,48.721395],"type":"Point"}
}