{
  "type": "Feature",
  "properties": {
    "addr:full":"18015 NE 13th St Bellevue WA 98008",
    "addr:housenumber":"18015",
    "addr:postcode":"98008",
    "addr:street":"Ne 13Th St",
    "iso:country":"US",
    "sg:address":"18015 NE 13th St",
    "sg:city":"Bellevue",
    "sg:classifiers":[
        {
            "category":"Professional",
            "type":"Services"
        }
    ],
    "sg:phone":"+1 425 747 3890",
    "sg:postcode":"98008",
    "sg:province":"WA",
    "wof:name":"Milt Smith & Assoc",
    "wof:placetype":"venue"
},
  "geometry": {"coordinates":[-122.09922,47.621395],"type":"Point"}
}