{
  "type": "Feature",
  "properties": {
    "addr:full":"12814 NE Hwy 99 Vancouver WA 98686",
    "addr:housenumber":"12814",
    "addr:postcode":"98686",
    "addr:street":"Ne Hwy 99",
    "iso:country":"US",
    "sg:address":"12814 NE Hwy 99",
    "sg:city":"Vancouver",
    "sg:classifiers":[
        {
            "category":"Manufacturing",
            "subcategory":"Tools & Machinery",
            "type":"Manufacturing & Wholesale Goods"
        }
    ],
    "sg:phone":"+1 360 573 9443",
    "sg:postcode":"98686",
    "sg:province":"WA",
    "sg:tags":[
        "pressure",
        "mfg",
        "sprayer",
        "paint",
        "spraying"
    ],
    "wof:name":"G T Marketing",
    "wof:placetype":"venue"
},
  "geometry": {"coordinates":[-122.651284,45.714325],"type":"Point"}
}