{
  "type": "Feature",
  "properties": {
    "addr:full":"9301 Linder Way NW Silverdale WA 98383",
    "addr:housenumber":"9301",
    "addr:postcode":"98383",
    "addr:street":"Linder Way Nw",
    "iso:country":"US",
    "sg:address":"9301 Linder Way NW",
    "sg:city":"Silverdale",
    "sg:classifiers":[
        {
            "category":"Professional",
            "subcategory":"Lawyer & Legal Services",
            "type":"Services"
        }
    ],
    "sg:phone":"+1 360 692 1320",
    "sg:postcode":"98383",
    "sg:province":"WA",
    "wof:name":"Robert J Spader",
    "wof:placetype":"venue"
},
  "geometry": {"coordinates":[-122.69539399999999,47.647752],"type":"Point"}
}