{
  "type": "Feature",
  "properties": {
    "addr:full":"10711 Meridian Avenue N Seattle WA 98133",
    "addr:housenumber":"10711",
    "addr:postcode":"98133",
    "addr:street":"Meridian Avenue N",
    "iso:country":"US",
    "sg:address":"10711 Meridian Avenue N",
    "sg:city":"Seattle",
    "sg:classifiers":[
        {
            "category":"Real Estate",
            "subcategory":"Real Estate Operator",
            "type":"Services"
        }
    ],
    "sg:phone":"+1 206 417 1340",
    "sg:postcode":"98133",
    "sg:province":"WA",
    "sg:tags":[
        "apartment"
    ],
    "wof:name":"Meridian Place Apartments",
    "wof:placetype":"venue"
},
  "geometry": {"coordinates":[-122.333991,47.706888],"type":"Point"}
}