{
  "type": "Feature",
  "properties": {
    "addr:full":"1250 Denny Way Seattle WA 98109",
    "addr:housenumber":"1250",
    "addr:postcode":"98109",
    "addr:street":"Denny Way",
    "iso:country":"US",
    "sg:address":"1250 Denny Way",
    "sg:city":"Seattle",
    "sg:classifiers":[
        {
            "category":"Professional",
            "type":"Services"
        }
    ],
    "sg:phone":"+1 206 682 8037",
    "sg:postcode":"98109",
    "sg:province":"WA",
    "wof:name":"Air Mart",
    "wof:placetype":"venue"
},
  "geometry": {"coordinates":[-122.331397,47.618506],"type":"Point"}
}