{
  "type": "Feature",
  "properties": {
    "addr:full":"109 State Rte 4 Cathlamet WA 98612",
    "addr:housenumber":"109",
    "addr:postcode":"98612",
    "addr:street":"State Rte 4",
    "iso:country":"US",
    "sg:address":"109 State Rte 4",
    "sg:city":"Cathlamet",
    "sg:classifiers":[
        {
            "category":"Manufacturing",
            "subcategory":"Lumber",
            "type":"Manufacturing & Wholesale Goods"
        }
    ],
    "sg:phone":"+1 360 795 3616",
    "sg:postcode":"98612",
    "sg:province":"WA",
    "sg:tags":[
        "logging"
    ],
    "wof:name":"Heagy Inc",
    "wof:placetype":"venue"
},
  "geometry": {"coordinates":[-123.38200000000001,46.204724],"type":"Point"}
}