{
  "type": "Feature",
  "properties": {
    "addr:full":"16319 NE 182nd Ave Brush Prairie WA 98606",
    "addr:housenumber":"16319",
    "addr:postcode":"98606",
    "addr:street":"Ne 182Nd Ave",
    "iso:country":"US",
    "sg:address":"16319 NE 182nd Ave",
    "sg:city":"Brush Prairie",
    "sg:classifiers":[
        {
            "category":"Organizations",
            "subcategory":"Religious Organization",
            "type":"Services"
        }
    ],
    "sg:phone":"+1 360 254 1144",
    "sg:postcode":"98606",
    "sg:province":"WA",
    "sg:tags":[
        "church"
    ],
    "sg:website":"www.wellspringfoursquare.com",
    "wof:name":"Wellspring Foursquare Church",
    "wof:placetype":"venue"
},
  "geometry": {"coordinates":[-122.486666,45.738191],"type":"Point"}
}