{
  "type": "Feature",
  "properties": {
    "addr:full":"1617 Sixth Avenue Suite 500 Seattle WA 98101",
    "addr:housenumber":"1617",
    "addr:postcode":"98101",
    "addr:street":"Sixth Avenue Suite 500",
    "iso:country":"US",
    "sg:address":"1617 Sixth Avenue Suite 500",
    "sg:city":"Seattle",
    "sg:classifiers":[
        {
            "category":"Professional",
            "subcategory":"Computer Services",
            "type":"Services"
        }
    ],
    "sg:phone":"+1 206 628 2111",
    "sg:postcode":"98101",
    "sg:province":"WA",
    "sg:website":"http://www.nordstrom.com",
    "wof:name":"Nordstrom",
    "wof:placetype":"venue"
},
  "geometry": {"coordinates":[-122.521006,47.630694],"type":"Point"}
}