{
  "type": "Feature",
  "properties": {
    "addr:full":"32038 23rd Ave S Federal Way WA 98003",
    "addr:housenumber":"32038",
    "addr:postcode":"98003",
    "addr:street":"23Rd Ave S Federal Way",
    "iso:country":"US",
    "sg:address":"32038 23rd Ave S",
    "sg:city":"Federal Way",
    "sg:classifiers":[
        {
            "category":"Professional",
            "subcategory":"Business Services",
            "type":"Services"
        }
    ],
    "sg:phone":"+1 253 946 0505",
    "sg:postcode":"98003",
    "sg:province":"WA",
    "wof:name":"Safari Mail Express",
    "wof:placetype":"venue"
},
  "geometry": {"coordinates":[-122.30355,47.314645],"type":"Point"}
}