{
  "type": "Feature",
  "properties": {
    "addr:full":"4111 E Ferry Ave Spokane WA 99202",
    "addr:housenumber":"4111",
    "addr:postcode":"99202",
    "addr:street":"E Ferry Ave",
    "iso:country":"US",
    "sg:address":"4111 E Ferry Ave",
    "sg:city":"Spokane",
    "sg:classifiers":[
        {
            "category":"Manufacturing",
            "subcategory":"Building Materials",
            "type":"Manufacturing & Wholesale Goods"
        }
    ],
    "sg:phone":"+1 509 535 0600",
    "sg:postcode":"99202",
    "sg:province":"WA",
    "sg:website":"www.ascprofiles.com",
    "wof:name":"BHP Steel Building Products",
    "wof:placetype":"venue"
},
  "geometry": {"coordinates":[-117.34952,47.660951],"type":"Point"}
}