{
  "type": "Feature",
  "properties": {
    "addr:full":"720 Bent Arrow Ln SW Olympia WA 98512",
    "addr:housenumber":"720",
    "addr:postcode":"98512",
    "addr:street":"Bent Arrow Ln Sw",
    "iso:country":"US",
    "sg:address":"720 Bent Arrow Ln SW",
    "sg:city":"Olympia",
    "sg:classifiers":[
        {
            "category":"Retail",
            "subcategory":"Animal Services",
            "type":"Services"
        }
    ],
    "sg:phone":"+1 360 956 7412",
    "sg:postcode":"98512",
    "sg:province":"WA",
    "wof:name":"Cross Heart Arena",
    "wof:placetype":"venue"
},
  "geometry": {"coordinates":[-122.915238,46.946798],"type":"Point"}
}