{
  "type": "Feature",
  "properties": {
    "addr:full":"1400 N B St Aberdeen WA 98520",
    "addr:housenumber":"1400",
    "addr:postcode":"98520",
    "addr:street":"N B St",
    "iso:country":"US",
    "sg:address":"1400 N B St",
    "sg:city":"Aberdeen",
    "sg:classifiers":[
        {
            "category":"Professional",
            "subcategory":"Advertising",
            "type":"Services"
        }
    ],
    "sg:phone":"+1 360 532 7818",
    "sg:postcode":"98520",
    "sg:province":"WA",
    "wof:name":"Barta Sibrechta Scott",
    "wof:placetype":"venue"
},
  "geometry": {"coordinates":[-123.814289,46.985535],"type":"Point"}
}