{
  "type": "Feature",
  "properties": {
    "addr:full":"19915 Hwy 99 Lynnwood WA 98036",
    "addr:housenumber":"19915",
    "addr:postcode":"98036",
    "addr:street":"Hwy 99",
    "iso:country":"US",
    "sg:address":"19915 Hwy 99",
    "sg:city":"Lynnwood",
    "sg:classifiers":[
        {
            "category":"Autos & Motor Vehicles",
            "subcategory":"Auto Supplies",
            "type":"Retail Goods"
        }
    ],
    "sg:phone":"+1 425 775 1551",
    "sg:postcode":"98036",
    "sg:province":"WA",
    "wof:name":"Schucks Auto Supply 4303",
    "wof:placetype":"venue"
},
  "geometry": {"coordinates":[-122.317902,47.818044],"type":"Point"}
}