{
  "type": "Feature",
  "properties": {
    "addr:full":"4156 Guide Meridian Rd Bellingham WA 98226",
    "addr:housenumber":"4156",
    "addr:postcode":"98226",
    "addr:street":"Guide Meridian Rd",
    "iso:country":"US",
    "sg:address":"4156 Guide Meridian Rd",
    "sg:city":"Bellingham",
    "sg:classifiers":[
        {
            "category":"Restaurant",
            "type":"Food & Drink"
        }
    ],
    "sg:phone":"+1 360 647 1060",
    "sg:postcode":"98226",
    "sg:province":"WA",
    "sg:tags":[
        "eating"
    ],
    "wof:name":"Bistecca Italian Steakhouse",
    "wof:placetype":"venue"
},
  "geometry": {"coordinates":[-122.48595899999999,48.791718],"type":"Point"}
}