{
  "type": "Feature",
  "properties": {
    "addr:full":"6002 98th St E Puyallup WA 98373",
    "addr:housenumber":"6002",
    "addr:postcode":"98373",
    "addr:street":"98Th St E",
    "iso:country":"US",
    "sg:address":"6002 98th St E",
    "sg:city":"Puyallup",
    "sg:classifiers":[
        {
            "category":"Wholesale",
            "subcategory":"Durable Goods & Equipment",
            "type":"Manufacturing & Wholesale Goods"
        }
    ],
    "sg:phone":"+1 253 840 9110",
    "sg:postcode":"98373",
    "sg:province":"WA",
    "wof:name":"Morecollectables",
    "wof:placetype":"venue"
},
  "geometry": {"coordinates":[-122.34854300000001,47.168145],"type":"Point"}
}