{
  "type": "Feature",
  "properties": {
    "addr:full":"989 112th Ave NE #207 Bellevue WA 98004",
    "addr:housenumber":"989",
    "addr:postcode":"98004",
    "addr:street":"112Th Ave Ne # 207",
    "iso:country":"US",
    "sg:address":"989 112th Ave NE #207",
    "sg:city":"Bellevue",
    "sg:classifiers":[
        {
            "category":"Personal",
            "subcategory":"Day Spa",
            "type":"Services"
        }
    ],
    "sg:phone":"+1 425 709 6900",
    "sg:postcode":"98004",
    "sg:province":"WA",
    "sg:website":"www.deyss.com/",
    "wof:name":"Deyss Salon & Spa",
    "wof:placetype":"venue"
},
  "geometry": {"coordinates":[-122.19093700000001,47.619286],"type":"Point"}
}