{
  "type": "Feature",
  "properties": {
    "addr:full":"5 N Colville St Walla Walla WA 99362",
    "addr:housenumber":"5",
    "addr:postcode":"99362",
    "addr:street":"N Colville St",
    "iso:country":"US",
    "sg:address":"5 N Colville St",
    "sg:city":"Walla Walla",
    "sg:classifiers":[
        {
            "category":"Real Estate",
            "subcategory":"Surveying",
            "type":"Services"
        }
    ],
    "sg:phone":"+1 509 522 4843",
    "sg:postcode":"99362",
    "sg:province":"WA",
    "sg:tags":[
        "surveyor"
    ],
    "wof:name":"Paul WP Tompkins Land Survey",
    "wof:placetype":"venue"
},
  "geometry": {"coordinates":[-118.33843,46.068499],"type":"Point"}
}