{
  "type": "Feature",
  "properties": {
    "addr:full":"6 E Alder St Walla Walla WA 99362",
    "addr:housenumber":"6",
    "addr:postcode":"99362",
    "addr:street":"E Alder St",
    "iso:country":"US",
    "sg:address":"6 E Alder St",
    "sg:city":"Walla Walla",
    "sg:classifiers":[
        {
            "category":"Professional",
            "type":"Services"
        }
    ],
    "sg:phone":"+1 509 526 4340",
    "sg:postcode":"99362",
    "sg:province":"WA",
    "sg:tags":[
        "establishment"
    ],
    "wof:name":"Denny Bulding Partnership",
    "wof:placetype":"venue"
},
  "geometry": {"coordinates":[-118.33736500000001,46.066289],"type":"Point"}
}