{
  "type": "Feature",
  "properties": {
    "addr:full":"3931 1st Ave S Seattle WA 98134",
    "addr:housenumber":"3931",
    "addr:postcode":"98134",
    "addr:street":"1St Ave S",
    "iso:country":"US",
    "sg:address":"3931 1st Ave S",
    "sg:city":"Seattle",
    "sg:classifiers":[
        {
            "category":"Manufacturing",
            "subcategory":"Rubber & Plastics",
            "type":"Manufacturing & Wholesale Goods"
        }
    ],
    "sg:phone":"+1 206 682 4467",
    "sg:postcode":"98134",
    "sg:province":"WA",
    "wof:name":"Image Fabricating & Graphics",
    "wof:placetype":"venue"
},
  "geometry": {"coordinates":[-122.334283,47.569122],"type":"Point"}
}