{
  "type": "Feature",
  "properties": {
    "addr:full":"3650 State Hwy 16 SW Port Orchard WA 98367",
    "addr:housenumber":"3650",
    "addr:postcode":"98367",
    "addr:street":"State Hwy 16 Sw",
    "iso:country":"US",
    "sg:address":"3650 State Hwy 16 SW",
    "sg:city":"Port Orchard",
    "sg:classifiers":[
        {
            "category":"Building & Trades",
            "subcategory":"Plumbing",
            "type":"Services"
        }
    ],
    "sg:phone":"+1 360 377 4050",
    "sg:postcode":"98367",
    "sg:province":"WA",
    "sg:tags":[
        "tank",
        "septic"
    ],
    "wof:name":"Pacific Specialty Contracting",
    "wof:placetype":"venue"
},
  "geometry": {"coordinates":[-122.650998,47.509519],"type":"Point"}
}