{
  "type": "Feature",
  "properties": {
    "addr:full":"4032 SW 327th Pl Federal Way WA 98023",
    "addr:housenumber":"4032",
    "addr:postcode":"98023",
    "addr:street":"Sw 327Th Pl",
    "iso:country":"US",
    "sg:address":"4032 SW 327th Pl",
    "sg:city":"Federal Way",
    "sg:classifiers":[
        {
            "category":"Real Estate",
            "subcategory":"Real Estate Agent",
            "type":"Services"
        }
    ],
    "sg:phone":"+1 253 838 1473",
    "sg:postcode":"98023",
    "sg:province":"WA",
    "wof:name":"Pacific American Capital Inc",
    "wof:placetype":"venue"
},
  "geometry": {"coordinates":[-122.383893,47.308675],"type":"Point"}
}