{
  "type": "Feature",
  "properties": {
    "iso:country":"US",
    "sg:address":"4938 Hillview Rd",
    "sg:city":"Sumas",
    "sg:classifiers":[
        {
            "category":"Farming",
            "subcategory":"Farm & Veterinary Services",
            "type":"Manufacturing & Wholesale Goods"
        }
    ],
    "sg:phone":"+1 360 988 7117",
    "sg:postcode":"98295",
    "sg:province":"WA",
    "sg:tags":[
        "crop",
        "harvesting"
    ],
    "wof:name":"Marvin Vreugdenhill Partne",
    "wof:placetype":"venue"
},
  "geometry": {"coordinates":[-122.194996,48.989906],"type":"Point"}
}