{
  "type": "Feature",
  "properties": {
    "addr:full":"1103 E Main St Auburn WA 98002",
    "addr:housenumber":"1103",
    "addr:postcode":"98002",
    "addr:street":"E Main St",
    "iso:country":"US",
    "sg:address":"1103 E Main St",
    "sg:city":"Auburn",
    "sg:classifiers":[
        {
            "category":"Retail",
            "subcategory":"Self-service Laundry",
            "type":"Services"
        }
    ],
    "sg:phone":"+1 253 939 6394",
    "sg:postcode":"98002",
    "sg:province":"WA",
    "sg:tags":[
        "coin"
    ],
    "wof:name":"Thrifty Wash",
    "wof:placetype":"venue"
},
  "geometry": {"coordinates":[-122.215214,47.308017],"type":"Point"}
}