{
  "type": "Feature",
  "properties": {
    "addr:full":"7534 NE 175th St Kenmore WA 98028",
    "addr:housenumber":"7534",
    "addr:postcode":"98028",
    "addr:street":"Ne 175Th St",
    "iso:country":"US",
    "sg:address":"7534 NE 175th St",
    "sg:city":"Kenmore",
    "sg:classifiers":[
        {
            "category":"Building & Trades",
            "subcategory":"Electrical",
            "type":"Services"
        }
    ],
    "sg:phone":"+1 425 485 1233",
    "sg:postcode":"98028",
    "sg:province":"WA",
    "sg:tags":[
        "electric",
        "contractor"
    ],
    "wof:name":"Evergreen Electric Inc",
    "wof:placetype":"venue"
},
  "geometry": {"coordinates":[-122.235902,47.755849],"type":"Point"}
}