{
  "type": "Feature",
  "properties": {
    "addr:full":"4542 Island Ave NE Bainbridge Island WA 98110",
    "addr:housenumber":"4542",
    "addr:postcode":"98110",
    "addr:street":"Island Ave Ne",
    "iso:country":"US",
    "sg:address":"4542 Island Ave NE",
    "sg:city":"Bainbridge Island",
    "sg:classifiers":[
        {
            "category":"Shopping",
            "subcategory":"Books",
            "type":"Retail Goods"
        }
    ],
    "sg:phone":"+1 206 780 0962",
    "sg:postcode":"98110",
    "sg:province":"WA",
    "wof:name":"Cedar Ridge Books",
    "wof:placetype":"venue"
},
  "geometry": {"coordinates":[-122.56037499999999,47.606359],"type":"Point"}
}