{
  "type": "Feature",
  "properties": {
    "addr:full":"9781 NE Harris Ave Indianola WA 98342",
    "addr:housenumber":"9781",
    "addr:postcode":"98342",
    "addr:street":"Ne Harris Ave",
    "iso:country":"US",
    "sg:address":"9781 NE Harris Ave",
    "sg:city":"Indianola",
    "sg:classifiers":[
        {
            "category":"Building & Trades",
            "subcategory":"Landscaping Services",
            "type":"Services"
        }
    ],
    "sg:phone":"+1 360 297 8790",
    "sg:postcode":"98342",
    "sg:province":"WA",
    "wof:name":"Breen Thumb Hydroseeding",
    "wof:placetype":"venue"
},
  "geometry": {"coordinates":[-122.51693,47.747893],"type":"Point"}
}