{
  "type": "Feature",
  "properties": {
    "addr:full":"700 Broadway E Unit 119 Seattle WA 98102",
    "addr:housenumber":"700;e unit 119",
    "addr:postcode":"98102",
    "addr:street":"Broadway",
    "iso:country":"US",
    "sg:address":"700 Broadway E Unit 119",
    "sg:city":"Seattle",
    "sg:classifiers":[
        {
            "category":"Professional",
            "subcategory":"Research",
            "type":"Services"
        }
    ],
    "sg:phone":"+1 206 659 8175",
    "sg:postcode":"98102",
    "sg:province":"WA",
    "sg:tags":[
        "analysis",
        "market"
    ],
    "wof:name":"Northwest Social Research Group",
    "wof:placetype":"venue"
},
  "geometry": {"coordinates":[-122.32131200000001,47.625149],"type":"Point"}
}