{
  "type": "Feature",
  "properties": {
    "addr:full":"3724 E 28th Ave Spokane WA 99223",
    "addr:housenumber":"3724",
    "addr:postcode":"99223",
    "addr:street":"E 28Th Ave",
    "iso:country":"US",
    "sg:address":"3724 E 28th Ave",
    "sg:city":"Spokane",
    "sg:classifiers":[
        {
            "category":"Building & Trades",
            "subcategory":"Construction",
            "type":"Services"
        }
    ],
    "sg:phone":"+1 509 534 4647",
    "sg:postcode":"99223",
    "sg:province":"WA",
    "sg:tags":[
        "metal",
        "work",
        "sheet",
        "contractor"
    ],
    "wof:name":"Integrity Roofing & Cleaning",
    "wof:placetype":"venue"
},
  "geometry": {"coordinates":[-117.35615900000001,47.629311],"type":"Point"}
}