{
  "type": "Feature",
  "properties": {
    "addr:full":"1800 Continental Pl Mount Vernon WA 98273",
    "addr:housenumber":"1800",
    "addr:postcode":"98273",
    "addr:street":"Continental Pl",
    "iso:country":"US",
    "sg:address":"1800 Continental Pl",
    "sg:city":"Mount Vernon",
    "sg:classifiers":[
        {
            "category":"Government",
            "subcategory":"Office",
            "type":"Public Place"
        }
    ],
    "sg:phone":"+1 360 336 9400",
    "sg:postcode":"98273",
    "sg:province":"WA",
    "sg:tags":[
        "payable",
        "account"
    ],
    "wof:name":"County of Skagit",
    "wof:placetype":"venue"
},
  "geometry": {"coordinates":[-122.325703,48.436738],"type":"Point"}
}