{
  "type": "Feature",
  "properties": {
    "addr:full":"8301 161st Ave NE Redmond WA 98052",
    "addr:housenumber":"8301",
    "addr:postcode":"98052",
    "addr:street":"161St Ave Ne",
    "iso:country":"US",
    "sg:address":"8301 161st Ave NE",
    "sg:city":"Redmond",
    "sg:classifiers":[
        {
            "category":"Health Services",
            "subcategory":"Clinic",
            "type":"Services"
        },
        {
            "category":"Health Services",
            "subcategory":"Health Practitioner",
            "type":"Services"
        }
    ],
    "sg:phone":"+1 425 881 3114",
    "sg:postcode":"98052",
    "sg:province":"WA",
    "sg:tags":[
        "therapist",
        "physical",
        "center",
        "rehabilitation"
    ],
    "wof:name":"HealthSouth",
    "wof:placetype":"venue"
},
  "geometry": {"coordinates":[-122.12555399999999,47.67852],"type":"Point"}
}