{
  "type": "Feature",
  "properties": {
    "addr:full":"7209 NE 83rd Ave Vancouver WA 98662",
    "addr:housenumber":"7209",
    "addr:postcode":"98662",
    "addr:street":"Ne 83Rd Ave",
    "iso:country":"US",
    "sg:address":"7209 NE 83rd Ave",
    "sg:city":"Vancouver",
    "sg:classifiers":[
        {
            "category":"Banks & Credit Unions",
            "subcategory":"Financial Services",
            "type":"Services"
        }
    ],
    "sg:phone":"+1 360 254 9141",
    "sg:postcode":"98662",
    "sg:province":"WA",
    "sg:tags":[
        "investor"
    ],
    "wof:name":"Gerry M Coppedge",
    "wof:placetype":"venue"
},
  "geometry": {"coordinates":[-122.58847900000001,45.674423],"type":"Point"}
}