{
  "type": "Feature",
  "properties": {
    "addr:full":"1716 E Washington Ave Union Gap WA 98903",
    "addr:housenumber":"1716",
    "addr:postcode":"98903",
    "addr:street":"E Washington Ave",
    "iso:country":"US",
    "sg:address":"1716 E Washington Ave",
    "sg:city":"Union Gap",
    "sg:classifiers":[
        {
            "category":"Shopping",
            "subcategory":"Clothing, Apparel, & Fashions",
            "type":"Retail Goods"
        }
    ],
    "sg:phone":"+1 509 453 5105",
    "sg:postcode":"98903",
    "sg:province":"WA",
    "sg:website":"www.oldnavy.com",
    "wof:name":"Old Navy",
    "wof:placetype":"venue"
},
  "geometry": {"coordinates":[-120.48133900000001,46.570466],"type":"Point"}
}