{
  "type": "Feature",
  "properties": {
    "addr:full":"9925 Nunn Rd SW Olympia WA 98512",
    "addr:housenumber":"9925",
    "addr:postcode":"98512",
    "addr:street":"Nunn Rd Sw",
    "iso:country":"US",
    "sg:address":"9925 Nunn Rd SW",
    "sg:city":"Olympia",
    "sg:classifiers":[
        {
            "category":"Farming",
            "subcategory":"Livestock Farm",
            "type":"Manufacturing & Wholesale Goods"
        }
    ],
    "sg:phone":"+1 360 943 2016",
    "sg:postcode":"98512",
    "sg:province":"WA",
    "sg:tags":[
        "beef",
        "feedlot",
        "cattle"
    ],
    "wof:name":"Gayle McLain",
    "wof:placetype":"venue"
},
  "geometry": {"coordinates":[-122.93450799999999,46.943604],"type":"Point"}
}