{
  "type": "Feature",
  "properties": {
    "addr:full":"4040 W Belfair Valley Rd Bremerton WA 98312",
    "addr:housenumber":"4040",
    "addr:postcode":"98312",
    "addr:street":"W Belfair Valley Rd",
    "iso:country":"US",
    "sg:address":"4040 W Belfair Valley Rd",
    "sg:city":"Bremerton",
    "sg:classifiers":[
        {
            "category":"Professional",
            "subcategory":"Computer Services",
            "type":"Services"
        }
    ],
    "sg:phone":"+1 360 616 8928",
    "sg:postcode":"98312",
    "sg:province":"WA",
    "sg:tags":[
        "network",
        "digital",
        "solution",
        "signage"
    ],
    "wof:name":"Jmp Interact",
    "wof:placetype":"venue"
},
  "geometry": {"coordinates":[-122.70397199999999,47.529179],"type":"Point"}
}