{
  "type": "Feature",
  "properties": {
    "addr:full":"14686 NW Seaview Dr Seabeck WA 98380",
    "addr:housenumber":"14686",
    "addr:postcode":"98380",
    "addr:street":"Nw Seaview Dr",
    "iso:country":"US",
    "sg:address":"14686 NW Seaview Dr",
    "sg:city":"Seabeck",
    "sg:classifiers":[
        {
            "category":"Building & Trades",
            "subcategory":"Construction",
            "type":"Services"
        }
    ],
    "sg:phone":"+1 360 830 5509",
    "sg:postcode":"98380",
    "sg:province":"WA",
    "sg:tags":[
        "welder"
    ],
    "wof:name":"Christie Machine Welding",
    "wof:placetype":"venue"
},
  "geometry": {"coordinates":[-122.84674099999999,47.63049],"type":"Point"}
}