{
  "type": "Feature",
  "properties": {
    "addr:full":"10915 Willows Rd NE Redmond WA 98052",
    "addr:housenumber":"10915",
    "addr:postcode":"98052",
    "addr:street":"Willows Rd Ne",
    "iso:country":"US",
    "sg:address":"10915 Willows Rd NE",
    "sg:city":"Redmond",
    "sg:classifiers":[
        {
            "category":"Insurance",
            "subcategory":"Hazard Insurance",
            "type":"Services"
        }
    ],
    "sg:phone":"+1 425 881 4500",
    "sg:postcode":"98052",
    "sg:province":"WA",
    "sg:tags":[
        "carrier"
    ],
    "wof:name":"Safeco",
    "wof:placetype":"venue"
},
  "geometry": {"coordinates":[-122.152726,47.701046],"type":"Point"}
}