{
  "type": "Feature",
  "properties": {
    "addr:full":"715 100th St SE Everett WA 98208",
    "addr:housenumber":"715",
    "addr:postcode":"98208",
    "addr:street":"100Th St Se",
    "iso:country":"US",
    "sg:address":"715 100th St SE",
    "sg:city":"Everett",
    "sg:classifiers":[
        {
            "category":"Wholesale",
            "subcategory":"Wine & Distilled Alcoholic Beverages",
            "type":"Manufacturing & Wholesale Goods"
        }
    ],
    "sg:phone":"+1 425 267 0937",
    "sg:postcode":"98208",
    "sg:province":"WA",
    "sg:tags":[
        "liquor"
    ],
    "wof:name":"Koryo Brewery",
    "wof:placetype":"venue"
},
  "geometry": {"coordinates":[-122.217867,47.907497],"type":"Point"}
}