{
  "type": "Feature",
  "properties": {
    "addr:full":"10315 E Marginal Way S Tukwila WA 98168",
    "addr:housenumber":"10315",
    "addr:postcode":"98168",
    "addr:street":"E Marginal Way S",
    "iso:country":"US",
    "sg:address":"10315 E Marginal Way S",
    "sg:city":"Tukwila",
    "sg:classifiers":[
        {
            "category":"Real Estate",
            "subcategory":"Real Estate Services",
            "type":"Services"
        }
    ],
    "sg:phone":"+1 206 767 4024",
    "sg:postcode":"98168",
    "sg:province":"WA",
    "sg:tags":[
        "management",
        "property"
    ],
    "wof:name":"Chase Property Management",
    "wof:placetype":"venue"
},
  "geometry": {"coordinates":[-122.293074,47.510676],"type":"Point"}
}