{
  "type": "Feature",
  "properties": {
    "addr:full":"4218 227th Avenue Ct E Buckley WA 98321",
    "addr:housenumber":"4218",
    "addr:postcode":"98321",
    "addr:street":"227Th Avenue Ct E",
    "iso:country":"US",
    "sg:address":"4218 227th Avenue Ct E",
    "sg:city":"Buckley",
    "sg:classifiers":[
        {
            "category":"Restaurant",
            "type":"Food & Drink"
        }
    ],
    "sg:phone":"+1 253 862 5411",
    "sg:postcode":"98321",
    "sg:province":"WA",
    "sg:tags":[
        "eating"
    ],
    "wof:name":"Terri DS Catering",
    "wof:placetype":"venue"
},
  "geometry": {"coordinates":[-122.12630299999999,47.219688],"type":"Point"}
}