{
  "type": "Feature",
  "properties": {
    "iso:country":"US",
    "sg:address":"4503 Peyote Dr",
    "sg:city":"Pasco",
    "sg:classifiers":[
        {
            "category":"Health Services",
            "subcategory":"Clinic",
            "type":"Services"
        }
    ],
    "sg:phone":"+1 509 547 7965",
    "sg:postcode":"99301",
    "sg:province":"WA",
    "wof:name":"Kerry Schafer Mental Health Co",
    "wof:placetype":"venue"
},
  "geometry": {"coordinates":[-119.149681,46.267527],"type":"Point"}
}