{
  "type": "Feature",
  "properties": {
    "addr:full":"12420 E Indiana Ave Spokane Valley WA 99216",
    "addr:housenumber":"12420",
    "addr:postcode":"99216",
    "addr:street":"E Indiana Ave",
    "iso:country":"US",
    "sg:address":"12420 E Indiana Ave",
    "sg:city":"Spokane Valley",
    "sg:classifiers":[
        {
            "category":"Retail",
            "subcategory":"Auto Rental",
            "type":"Services"
        }
    ],
    "sg:phone":"+1 509 922 3334",
    "sg:postcode":"99216",
    "sg:province":"WA",
    "sg:tags":[
        "renting",
        "truck",
        "leasing"
    ],
    "wof:name":"U-Haul Co",
    "wof:placetype":"venue"
},
  "geometry": {"coordinates":[-117.239193,47.675436],"type":"Point"}
}