{
  "type": "Feature",
  "properties": {
    "addr:full":"1045 State Rte 4 Naselle WA 98638",
    "addr:housenumber":"1045",
    "addr:postcode":"98638",
    "addr:street":"State Rte 4 Naselle",
    "iso:country":"US",
    "sg:address":"1045 State Rte 4",
    "sg:city":"Naselle",
    "sg:classifiers":[
        {
            "category":"Restaurant",
            "type":"Food & Drink"
        }
    ],
    "sg:phone":"+1 360 484 3777",
    "sg:postcode":"98638",
    "sg:province":"WA",
    "wof:name":"Comets Cafe",
    "wof:placetype":"venue"
},
  "geometry": {"coordinates":[-123.773866,46.365258],"type":"Point"}
}