{
  "type": "Feature",
  "properties": {
    "addr:full":"14532 180th Pl SE Snohomish WA 98290",
    "addr:housenumber":"14532",
    "addr:postcode":"98290",
    "addr:street":"180Th Pl Se",
    "iso:country":"US",
    "sg:address":"14532 180th Pl SE",
    "sg:city":"Snohomish",
    "sg:classifiers":[
        {
            "category":"Building & Trades",
            "subcategory":"Construction",
            "type":"Services"
        }
    ],
    "sg:phone":"+1 425 338 5334",
    "sg:postcode":"98290",
    "sg:province":"WA",
    "sg:tags":[
        "road",
        "contractor"
    ],
    "wof:name":"R J Lampers Construction Co Inc",
    "wof:placetype":"venue"
},
  "geometry": {"coordinates":[-122.03613199999999,47.832385],"type":"Point"}
}