{
  "type": "Feature",
  "properties": {
    "addr:full":"2225 4th Ave Seattle WA 98121",
    "addr:housenumber":"2225",
    "addr:postcode":"98121",
    "addr:street":"4Th Ave",
    "iso:country":"US",
    "sg:address":"2225 4th Ave",
    "sg:city":"Seattle",
    "sg:classifiers":[
        {
            "category":"Professional",
            "subcategory":"Lawyer & Legal Services",
            "type":"Services"
        }
    ],
    "sg:phone":"+1 206 622 2655",
    "sg:postcode":"98121",
    "sg:province":"WA",
    "sg:tags":[
        "law"
    ],
    "wof:name":"Murray Dunham & Murray",
    "wof:placetype":"venue"
},
  "geometry": {"coordinates":[-122.343771,47.615123],"type":"Point"}
}