{
  "type": "Feature",
  "properties": {
    "addr:full":"15015 Main St Bellevue WA 98007",
    "addr:housenumber":"15015",
    "addr:postcode":"98007",
    "addr:street":"Main St",
    "iso:country":"US",
    "sg:address":"15015 Main St",
    "sg:city":"Bellevue",
    "sg:classifiers":[
        {
            "category":"Professional",
            "subcategory":"Lawyer & Legal Services",
            "type":"Services"
        }
    ],
    "sg:phone":"+1 425 586 1900",
    "sg:postcode":"98007",
    "sg:province":"WA",
    "sg:tags":[
        "a",
        "as",
        "law",
        "operates"
    ],
    "wof:name":"Routh Crabtree Fennell PS",
    "wof:placetype":"venue"
},
  "geometry": {"coordinates":[-122.13976599999999,47.609771],"type":"Point"}
}