{
  "type": "Feature",
  "properties": {
    "addr:full":"1101 Pacific Ave Tacoma WA 98402",
    "addr:housenumber":"1101",
    "addr:postcode":"98402",
    "addr:street":"Pacific Ave",
    "iso:country":"US",
    "sg:address":"1101 Pacific Ave",
    "sg:city":"Tacoma",
    "sg:classifiers":[
        {
            "category":"Banks & Credit Unions",
            "subcategory":"Financial Services",
            "type":"Services"
        }
    ],
    "sg:phone":"+1 253 305 2723",
    "sg:postcode":"98402",
    "sg:province":"WA",
    "sg:tags":[
        "investor"
    ],
    "wof:name":"Property Management",
    "wof:placetype":"venue"
},
  "geometry": {"coordinates":[-122.438395,47.25235],"type":"Point"}
}