{
  "type": "Feature",
  "properties": {
    "addr:full":"21844 76th Ave S Kent WA 98032",
    "addr:housenumber":"21844",
    "addr:postcode":"98032",
    "addr:street":"76Th Ave S",
    "iso:country":"US",
    "sg:address":"21844 76th Ave S",
    "sg:city":"Kent",
    "sg:classifiers":[
        {
            "category":"Farming",
            "subcategory":"Fish & Marine Products",
            "type":"Manufacturing & Wholesale Goods"
        },
        {
            "category":"Retail",
            "subcategory":"Storage",
            "type":"Services"
        }
    ],
    "sg:phone":"+1 206 575 6443",
    "sg:postcode":"98032",
    "sg:province":"WA",
    "sg:tags":[
        "box",
        "boxes-used"
    ],
    "wof:name":"Cascae Container Corp",
    "wof:placetype":"venue"
},
  "geometry": {"coordinates":[-122.238671,47.405082],"type":"Point"}
}