{
  "type": "Feature",
  "properties": {
    "addr:full":"1320 174th St E Spanaway WA 98387",
    "addr:housenumber":"1320",
    "addr:postcode":"98387",
    "addr:street":"174Th St E",
    "iso:country":"US",
    "sg:address":"1320 174th St E",
    "sg:city":"Spanaway",
    "sg:classifiers":[
        {
            "category":"Real Estate",
            "subcategory":"Real Estate Agent",
            "type":"Services"
        }
    ],
    "sg:phone":"+1 253 988 5580",
    "sg:postcode":"98387",
    "sg:province":"WA",
    "sg:tags":[
        "inspection"
    ],
    "wof:name":"Northwest Home Specialists",
    "wof:placetype":"venue"
},
  "geometry": {"coordinates":[-122.411457,47.098899],"type":"Point"}
}