{
  "type": "Feature",
  "properties": {
    "iso:country":"US",
    "sg:address":"710 S Sheridan Ave",
    "sg:city":"Tacoma",
    "sg:classifiers":[
        {
            "category":"Building & Trades",
            "subcategory":"Landscaping Services",
            "type":"Services"
        }
    ],
    "sg:phone":"+1 253 383 5504",
    "sg:postcode":"98405",
    "sg:province":"WA",
    "wof:name":"Lys Ground Maintenance",
    "wof:placetype":"venue"
},
  "geometry": {"coordinates":[-122.456812,47.25473],"type":"Point"}
}