{
  "type": "Feature",
  "properties": {
    "addr:full":"1717 S J St Tacoma WA 98405",
    "addr:housenumber":"1717",
    "addr:postcode":"98405",
    "addr:street":"S J St",
    "iso:country":"US",
    "sg:address":"1717 S J St",
    "sg:city":"Tacoma",
    "sg:classifiers":[
        {
            "category":"Health Services",
            "subcategory":"Doctor",
            "type":"Services"
        }
    ],
    "sg:phone":"+1 253 426 6625",
    "sg:postcode":"98405",
    "sg:province":"WA",
    "sg:tags":[
        "physician",
        "surgeon"
    ],
    "wof:name":"Pacific Anesthesia",
    "wof:placetype":"venue"
},
  "geometry": {"coordinates":[-122.448601,47.245124],"type":"Point"}
}