{
  "type": "Feature",
  "properties": {
    "addr:full":"12902 Bothell Everett Hwy Everett WA 98208",
    "addr:housenumber":"12902",
    "addr:postcode":"98208",
    "addr:street":"Bothell Everett Hwy",
    "iso:country":"US",
    "sg:address":"12902 Bothell Everett Hwy",
    "sg:city":"Everett",
    "sg:classifiers":[
        {
            "category":"Personal",
            "subcategory":"Beauty Salon",
            "type":"Services"
        }
    ],
    "sg:phone":"+1 425 338 0349",
    "sg:postcode":"98208",
    "sg:province":"WA",
    "sg:tags":[
        "shop"
    ],
    "wof:name":"Crystale Nails",
    "wof:placetype":"venue"
},
  "geometry": {"coordinates":[-122.206846,47.882666],"type":"Point"}
}