{
  "type": "Feature",
  "properties": {
    "iso:country":"US",
    "sg:address":"1164 E Front St",
    "sg:city":"Lynden",
    "sg:classifiers":[
        {
            "category":"Real Estate",
            "subcategory":"Real Estate Agent",
            "type":"Services"
        }
    ],
    "sg:phone":"+1 360 354 6000",
    "sg:postcode":"98264",
    "sg:province":"WA",
    "sg:tags":[
        "motion",
        "picture"
    ],
    "wof:name":"Brennick Rentals",
    "wof:placetype":"venue"
},
  "geometry": {"coordinates":[-122.434304,48.947985],"type":"Point"}
}