{
  "type": "Feature",
  "properties": {
    "addr:full":"10208 NE 186th St Bothell WA 98011",
    "addr:housenumber":"10208",
    "addr:postcode":"98011",
    "addr:street":"Ne 186Th St",
    "iso:country":"US",
    "sg:address":"10208 NE 186th St",
    "sg:city":"Bothell",
    "sg:classifiers":[
        {
            "category":"Manufacturing",
            "subcategory":"Apparel",
            "type":"Manufacturing & Wholesale Goods"
        }
    ],
    "sg:phone":"+1 425 402 3736",
    "sg:postcode":"98011",
    "sg:province":"WA",
    "sg:tags":[
        "gown",
        "mfg"
    ],
    "wof:name":"Robe Shop The",
    "wof:placetype":"venue"
},
  "geometry": {"coordinates":[-122.20424,47.76269],"type":"Point"}
}