{
  "type": "Feature",
  "properties": {
    "addr:full":"17228 17th Ave W Lynnwood WA 98037",
    "addr:housenumber":"17228",
    "addr:postcode":"98037",
    "addr:street":"17Th Ave W",
    "iso:country":"US",
    "sg:address":"17228 17th Ave W",
    "sg:city":"Lynnwood",
    "sg:classifiers":[
        {
            "category":"Building & Trades",
            "subcategory":"Construction",
            "type":"Services"
        }
    ],
    "sg:phone":"+1 425 745 8848",
    "sg:postcode":"98037",
    "sg:province":"WA",
    "sg:tags":[
        "contractor"
    ],
    "wof:name":"Fick & Company Roofing",
    "wof:placetype":"venue"
},
  "geometry": {"coordinates":[-122.25588999999999,47.842112],"type":"Point"}
}