{
  "type": "Feature",
  "properties": {
    "addr:full":"828 SW 304th St Federal Way WA 98023",
    "addr:housenumber":"828",
    "addr:postcode":"98023",
    "addr:street":"Sw 304Th St",
    "iso:country":"US",
    "sg:address":"828 SW 304th St",
    "sg:city":"Federal Way",
    "sg:classifiers":[
        {
            "category":"Social Services",
            "subcategory":"Child Care",
            "type":"Services"
        }
    ],
    "sg:phone":"+1 253 839 0355",
    "sg:postcode":"98023",
    "sg:province":"WA",
    "sg:tags":[
        "day"
    ],
    "wof:name":"Silly Goose Daycare",
    "wof:placetype":"venue"
},
  "geometry": {"coordinates":[-122.347759,47.329298],"type":"Point"}
}