{
  "type": "Feature",
  "properties": {
    "addr:full":"4500 9th Ave NE 3rd Fl Ste 19 Seattle WA 98105",
    "addr:housenumber":"4500;3rd fl ste 19",
    "addr:postcode":"98105",
    "addr:street":"9Th Ave Ne",
    "iso:country":"US",
    "sg:address":"4500 9th Ave NE 3rd Fl Ste 19",
    "sg:city":"Seattle",
    "sg:classifiers":[
        {
            "category":"Personal",
            "subcategory":"Massage",
            "type":"Services"
        },
        {
            "category":"Health Services",
            "subcategory":"Clinic",
            "type":"Services"
        }
    ],
    "sg:phone":"+1 206 250 0550",
    "sg:postcode":"98105",
    "sg:province":"WA",
    "sg:tags":[
        "medical"
    ],
    "sg:website":"www.fullbodybalancing.com",
    "wof:name":"Full Body Balancing - Alis Brown, LMP",
    "wof:placetype":"venue"
},
  "geometry": {"coordinates":[-122.31833899999999,47.661682],"type":"Point"}
}