{
  "type": "Feature",
  "properties": {
    "addr:full":"7031 NE 175th St Kenmore WA 98028",
    "addr:housenumber":"7031",
    "addr:postcode":"98028",
    "addr:street":"Ne 175Th St",
    "iso:country":"US",
    "sg:address":"7031 NE 175th St",
    "sg:city":"Kenmore",
    "sg:classifiers":[
        {
            "category":"Home & Garden",
            "subcategory":"Mobile Homes",
            "type":"Retail Goods"
        }
    ],
    "sg:phone":"+1 425 482 0909",
    "sg:postcode":"98028",
    "sg:province":"WA",
    "wof:name":"Mobil/Mnfctured Homes In Parks",
    "wof:placetype":"venue"
},
  "geometry": {"coordinates":[-122.247649,47.757026],"type":"Point"}
}