{
  "type": "Feature",
  "properties": {
    "addr:full":"224 192nd St SW Bothell WA 98012",
    "addr:housenumber":"224",
    "addr:postcode":"98012",
    "addr:street":"192Nd St Sw",
    "iso:country":"US",
    "sg:address":"224 192nd St SW",
    "sg:city":"Bothell",
    "sg:classifiers":[
        {
            "category":"Freight",
            "type":"Transportation"
        }
    ],
    "sg:phone":"+1 425 771 6522",
    "sg:postcode":"98012",
    "sg:province":"WA",
    "sg:tags":[
        "forwarders"
    ],
    "wof:name":"Alpine Forwarders Inc",
    "wof:placetype":"venue"
},
  "geometry": {"coordinates":[-122.237241,47.824182],"type":"Point"}
}