{
  "type": "Feature",
  "properties": {
    "addr:full":"4809 Airport Way S Seattle WA 98108",
    "addr:housenumber":"4809",
    "addr:postcode":"98108",
    "addr:street":"Airport Way S",
    "iso:country":"US",
    "sg:address":"4809 Airport Way S",
    "sg:city":"Seattle",
    "sg:classifiers":[
        {
            "category":"Manufacturing",
            "subcategory":"Printing",
            "type":"Manufacturing & Wholesale Goods"
        }
    ],
    "sg:phone":"+1 206 628 3756",
    "sg:postcode":"98108",
    "sg:province":"WA",
    "sg:tags":[
        "bookbinder"
    ],
    "wof:name":"Emerald City Bindery",
    "wof:placetype":"venue"
},
  "geometry": {"coordinates":[-122.32311300000001,47.558325],"type":"Point"}
}