{
  "type": "Feature",
  "properties": {
    "addr:full":"9610 Des Moines Memorial Seattle WA 98108",
    "addr:housenumber":"9610",
    "addr:postcode":"98108",
    "addr:street":"Des Moines",
    "iso:country":"US",
    "sg:address":"9610 Des Moines Memorial",
    "sg:city":"Seattle",
    "sg:classifiers":[
        {
            "category":"Restaurant",
            "type":"Food & Drink"
        }
    ],
    "sg:phone":"+1 206 762 9445",
    "sg:postcode":"98108",
    "sg:province":"WA",
    "sg:website":"www.mcdonalds.com",
    "wof:name":"McDonald's Restaurants",
    "wof:placetype":"venue"
},
  "geometry": {"coordinates":[-122.315423,47.516831],"type":"Point"}
}