{
  "type": "Feature",
  "properties": {
    "addr:full":"18316 58th Pl W Lynnwood WA 98037",
    "addr:housenumber":"18316",
    "addr:postcode":"98037",
    "addr:street":"58Th Pl W",
    "iso:country":"US",
    "sg:address":"18316 58th Pl W",
    "sg:city":"Lynnwood",
    "sg:classifiers":[
        {
            "category":"Wholesale",
            "subcategory":"Non-durable Goods",
            "type":"Manufacturing & Wholesale Goods"
        },
        {
            "category":"Personal",
            "subcategory":"Barber",
            "type":"Services"
        }
    ],
    "sg:phone":"+1 425 775 5705",
    "sg:postcode":"98037",
    "sg:province":"WA",
    "sg:tags":[
        "beauty",
        "supply",
        "equipment",
        "salons-equipment",
        "supplies-wholesale",
        "manufacturer"
    ],
    "wof:name":"Home Stylin'",
    "wof:placetype":"venue"
},
  "geometry": {"coordinates":[-122.311921,47.832269],"type":"Point"}
}