{
  "type": "Feature",
  "properties": {
    "addr:full":"36227 Hood Canal Dr NE Hansville WA 98340",
    "addr:housenumber":"36227",
    "addr:postcode":"98340",
    "addr:street":"Hood Canal Dr Ne",
    "iso:country":"US",
    "sg:address":"36227 Hood Canal Dr NE",
    "sg:city":"Hansville",
    "sg:classifiers":[
        {
            "category":"Building & Trades",
            "subcategory":"Construction",
            "type":"Services"
        }
    ],
    "sg:phone":"+1 360 638 1166",
    "sg:postcode":"98340",
    "sg:province":"WA",
    "sg:tags":[
        "new",
        "design",
        "commercial",
        "home"
    ],
    "wof:name":"Arborview Construction Inc",
    "wof:placetype":"venue"
},
  "geometry": {"coordinates":[-122.578301,47.889432],"type":"Point"}
}