{
  "type": "Feature",
  "properties": {
    "addr:full":"711 5th St Hoquiam WA 98550",
    "addr:housenumber":"711",
    "addr:postcode":"98550",
    "addr:street":"5Th St",
    "iso:country":"US",
    "sg:address":"711 5th St",
    "sg:city":"Hoquiam",
    "sg:classifiers":[
        {
            "category":"Manufacturing",
            "subcategory":"Chemicals & Compounds",
            "type":"Manufacturing & Wholesale Goods"
        }
    ],
    "sg:phone":"+1 360 580 1100",
    "sg:postcode":"98550",
    "sg:province":"WA",
    "sg:tags":[
        "preparation",
        "toilet",
        "mfg"
    ],
    "wof:name":"Green Earth Essentials",
    "wof:placetype":"venue"
},
  "geometry": {"coordinates":[-123.89143199999999,46.976662],"type":"Point"}
}