{
  "type": "Feature",
  "properties": {
    "addr:full":"20311 12th Dr SE Bothell WA 98012",
    "addr:housenumber":"20311",
    "addr:postcode":"98012",
    "addr:street":"12Th Dr Se",
    "iso:country":"US",
    "sg:address":"20311 12th Dr SE",
    "sg:city":"Bothell",
    "sg:classifiers":[
        {
            "category":"Banks & Credit Unions",
            "subcategory":"Bank",
            "type":"Services"
        }
    ],
    "sg:phone":"+1 206 992 0398",
    "sg:postcode":"98012",
    "sg:province":"WA",
    "sg:tags":[
        "federal",
        "agency"
    ],
    "wof:name":"Pacifica International LLC",
    "wof:placetype":"venue"
},
  "geometry": {"coordinates":[-122.215673,47.812754],"type":"Point"}
}