{
  "type": "Feature",
  "properties": {
    "addr:full":"9 Lake Bellevue Dr Ste 103 Bellevue WA 98005",
    "addr:housenumber":"9",
    "addr:postcode":"98005",
    "addr:street":"Lake Bellevue Dr Ste 103",
    "iso:country":"US",
    "sg:address":"9 Lake Bellevue Dr Ste 103",
    "sg:city":"Bellevue",
    "sg:classifiers":[
        {
            "category":"Professional",
            "subcategory":"Lawyer & Legal Services",
            "type":"Services"
        }
    ],
    "sg:phone":"+1 425 462 6580",
    "sg:postcode":"98005",
    "sg:province":"WA",
    "wof:name":"De Maar Natalie Law & Mediation Services",
    "wof:placetype":"venue"
},
  "geometry": {"coordinates":[-122.180746,47.619245],"type":"Point"}
}