{
  "type": "Feature",
  "properties": {
    "iso:country":"US",
    "sg:address":"4045 262nd Ave SE",
    "sg:city":"Issaquah",
    "sg:classifiers":[
        {
            "category":"Professional",
            "subcategory":"Lawyer & Legal Services",
            "type":"Services"
        }
    ],
    "sg:phone":"+1 425 392 7118",
    "sg:postcode":"98029",
    "sg:province":"WA",
    "sg:tags":[
        "attorney"
    ],
    "wof:name":"Houck Law Firm PS",
    "wof:placetype":"venue"
},
  "geometry": {"coordinates":[-121.993146,47.570551],"type":"Point"}
}