{
  "type": "Feature",
  "properties": {
    "addr:full":"2328 Alpine Pl Enumclaw WA 98022",
    "addr:housenumber":"2328",
    "addr:postcode":"98022",
    "addr:street":"Alpine Pl",
    "iso:country":"US",
    "sg:address":"2328 Alpine Pl",
    "sg:city":"Enumclaw",
    "sg:classifiers":[
        {
            "category":"Building & Trades",
            "subcategory":"Construction",
            "type":"Services"
        }
    ],
    "sg:phone":"+1 360 825 8338",
    "sg:postcode":"98022",
    "sg:province":"WA",
    "sg:tags":[
        "contractor"
    ],
    "wof:name":"Shades of Rainier",
    "wof:placetype":"venue"
},
  "geometry": {"coordinates":[-121.96473899999999,47.204412],"type":"Point"}
}