{
  "type": "Feature",
  "properties": {
    "addr:full":"18211 NE Fourth Plain Rd Vancouver WA 98682",
    "addr:housenumber":"18211",
    "addr:postcode":"98682",
    "addr:street":"Ne Fourth Plain Rd",
    "iso:country":"US",
    "sg:address":"18211 NE Fourth Plain Rd",
    "sg:city":"Vancouver",
    "sg:classifiers":[
        {
            "category":"Building & Trades",
            "subcategory":"Construction",
            "type":"Services"
        }
    ],
    "sg:phone":"+1 360 254 7056",
    "sg:postcode":"98682",
    "sg:province":"WA",
    "sg:tags":[
        "excavation",
        "contractor"
    ],
    "wof:name":"Thompson Bros Excavating Inc",
    "wof:placetype":"venue"
},
  "geometry": {"coordinates":[-122.48572,45.670527],"type":"Point"}
}