{
  "type": "Feature",
  "properties": {
    "addr:full":"4 99th Ave NE Lake Stevens WA 98258",
    "addr:housenumber":"4",
    "addr:postcode":"98258",
    "addr:street":"99Th Ave Ne",
    "iso:country":"US",
    "sg:address":"4 99th Ave NE",
    "sg:city":"Lake Stevens",
    "sg:classifiers":[
        {
            "category":"Government",
            "subcategory":"Fire Station",
            "type":"Public Place"
        }
    ],
    "sg:phone":"+1 425 334 3034",
    "sg:postcode":"98258",
    "sg:province":"WA",
    "sg:tags":[
        "department"
    ],
    "wof:name":"Lake Stevens Fire Dept",
    "wof:placetype":"venue"
},
  "geometry": {"coordinates":[-122.09829499999999,47.996141],"type":"Point"}
}