{
  "type": "Feature",
  "properties": {
    "addr:full":"7319 Dayton Ave N Seattle WA 98103",
    "addr:housenumber":"7319",
    "addr:postcode":"98103",
    "addr:street":"Dayton Ave N",
    "iso:country":"US",
    "sg:address":"7319 Dayton Ave N",
    "sg:city":"Seattle",
    "sg:classifiers":[
        {
            "category":"Building & Trades",
            "subcategory":"Landscaping Services",
            "type":"Services"
        }
    ],
    "sg:phone":"+1 206 368 8935",
    "sg:postcode":"98103",
    "sg:province":"WA",
    "sg:tags":[
        "landscape",
        "contractor"
    ],
    "wof:name":"Greenfield Landscape",
    "wof:placetype":"venue"
},
  "geometry": {"coordinates":[-122.352676,47.682418],"type":"Point"}
}