{
  "type": "Feature",
  "properties": {
    "addr:full":"417 N Jefferson St Kennewick WA 99336",
    "addr:housenumber":"417",
    "addr:postcode":"99336",
    "addr:street":"N Jefferson St",
    "iso:country":"US",
    "sg:address":"417 N Jefferson St",
    "sg:city":"Kennewick",
    "sg:classifiers":[
        {
            "category":"Professional",
            "subcategory":"Detective & Security Services",
            "type":"Services"
        }
    ],
    "sg:phone":"+1 509 727 0459",
    "sg:postcode":"99336",
    "sg:province":"WA",
    "sg:tags":[
        "system"
    ],
    "wof:name":"See More Surveillance",
    "wof:placetype":"venue"
},
  "geometry": {"coordinates":[-119.199082,46.214624],"type":"Point"}
}