{
  "type": "Feature",
  "properties": {
    "addr:full":"6543 Greenwood Ave N Seattle WA 98103",
    "addr:housenumber":"6543",
    "addr:postcode":"98103",
    "addr:street":"Greenwood Ave N",
    "iso:country":"US",
    "sg:address":"6543 Greenwood Ave N",
    "sg:city":"Seattle",
    "sg:classifiers":[
        {
            "category":"Shopping",
            "subcategory":"Jewelry",
            "type":"Retail Goods"
        }
    ],
    "sg:phone":"+1 206 789 5151",
    "sg:postcode":"98103",
    "sg:province":"WA",
    "sg:tags":[
        "precious",
        "semi-precious",
        "stone"
    ],
    "wof:name":"Divine Adornments Jewelry",
    "wof:placetype":"venue"
},
  "geometry": {"coordinates":[-122.355305,47.676771],"type":"Point"}
}