{
  "type": "Feature",
  "properties": {
    "addr:full":"608 S 152nd St Burien WA 98148",
    "addr:housenumber":"608",
    "addr:postcode":"98148",
    "addr:street":"S 152Nd St",
    "iso:country":"US",
    "sg:address":"608 S 152nd St",
    "sg:city":"Burien",
    "sg:classifiers":[
        {
            "category":"Real Estate",
            "subcategory":"Real Estate Operator",
            "type":"Services"
        }
    ],
    "sg:phone":"+1 206 246 4591",
    "sg:postcode":"98148",
    "sg:province":"WA",
    "sg:tags":[
        "building",
        "apartment"
    ],
    "wof:name":"Cierra Commons Apartments",
    "wof:placetype":"venue"
},
  "geometry": {"coordinates":[-122.327656,47.466976],"type":"Point"}
}