{
  "type": "Feature",
  "properties": {
    "addr:full":"4480 W Frone Dr Bremerton WA 98312",
    "addr:housenumber":"4480",
    "addr:postcode":"98312",
    "addr:street":"W Frone Dr",
    "iso:country":"US",
    "sg:address":"4480 W Frone Dr",
    "sg:city":"Bremerton",
    "sg:classifiers":[
        {
            "category":"Banks & Credit Unions",
            "subcategory":"Financial Services",
            "type":"Services"
        }
    ],
    "sg:phone":"+1 360 373 9003",
    "sg:postcode":"98312",
    "sg:province":"WA",
    "sg:tags":[
        "trust",
        "management"
    ],
    "wof:name":"Jerryann Huff Trust",
    "wof:placetype":"venue"
},
  "geometry": {"coordinates":[-122.710842,47.525453],"type":"Point"}
}