{
  "type": "Feature",
  "properties": {
    "addr:full":"627 Lewis St Walla Walla WA 99362",
    "addr:housenumber":"627",
    "addr:postcode":"99362",
    "addr:street":"Lewis St",
    "iso:country":"US",
    "sg:address":"627 Lewis St",
    "sg:city":"Walla Walla",
    "sg:classifiers":[
        {
            "category":"Building & Trades",
            "subcategory":"Construction",
            "type":"Services"
        },
        {
            "category":"Home & Garden",
            "subcategory":"Garden Supply",
            "type":"Retail Goods"
        }
    ],
    "sg:phone":"+1 509 544 8995",
    "sg:postcode":"99362",
    "sg:province":"WA",
    "sg:tags":[
        "heavy",
        "sprinkler"
    ],
    "wof:name":"Northwest Irrigation & Ldscpg",
    "wof:placetype":"venue"
},
  "geometry": {"coordinates":[-118.314986,46.079597],"type":"Point"}
}