{
  "type": "Feature",
  "properties": {
    "iso:country":"US",
    "sg:address":"18631 Alderwood Mall Pkwy",
    "sg:city":"Lynnwood",
    "sg:classifiers":[
        {
            "category":"Manufacturing",
            "subcategory":"Tools & Machinery",
            "type":"Manufacturing & Wholesale Goods"
        }
    ],
    "sg:phone":"+1 425 771 4408",
    "sg:postcode":"98037",
    "sg:province":"WA",
    "sg:tags":[
        "optical",
        "mfg"
    ],
    "wof:name":"Lens Association LLP",
    "wof:placetype":"venue"
},
  "geometry": {"coordinates":[-122.268496,47.829395],"type":"Point"}
}