{
  "type": "Feature",
  "properties": {
    "addr:full":"32209 State Rte 20 Oak Harbor WA 98277",
    "addr:housenumber":"32209",
    "addr:postcode":"98277",
    "addr:street":"State Rte 20",
    "iso:country":"US",
    "sg:address":"32209 State Rte 20",
    "sg:city":"Oak Harbor",
    "sg:classifiers":[
        {
            "category":"Wholesale",
            "subcategory":"Non-durable Goods",
            "type":"Manufacturing & Wholesale Goods"
        }
    ],
    "sg:phone":"+1 360 279 1195",
    "sg:postcode":"98277",
    "sg:province":"WA",
    "wof:name":"Dollar Power Stores Inc",
    "wof:placetype":"venue"
},
  "geometry": {"coordinates":[-122.652185,48.299085],"type":"Point"}
}