{
  "type": "Feature",
  "properties": {
    "addr:full":"4680 95th St SW Lakewood WA 98499",
    "addr:housenumber":"4680",
    "addr:postcode":"98499",
    "addr:street":"95Th St Sw",
    "iso:country":"US",
    "sg:address":"4680 95th St SW",
    "sg:city":"Lakewood",
    "sg:classifiers":[
        {
            "category":"Manufacturing",
            "subcategory":"Printing",
            "type":"Manufacturing & Wholesale Goods"
        }
    ],
    "sg:phone":"+1 253 983 1040",
    "sg:postcode":"98499",
    "sg:province":"WA",
    "sg:tags":[
        "label"
    ],
    "wof:name":"Relm West Labels",
    "wof:placetype":"venue"
},
  "geometry": {"coordinates":[-122.498474,47.17094],"type":"Point"}
}