{
  "type": "Feature",
  "properties": {
    "addr:full":"4820 Avalanche Ave Yakima WA 98908",
    "addr:postcode":"4820;98908",
    "addr:street":"Avalanche Ave",
    "iso:country":"US",
    "sg:address":"4820 Avalanche Ave",
    "sg:city":"Yakima",
    "sg:classifiers":[
        {
            "category":"Insurance",
            "subcategory":"Insurance Agent",
            "type":"Services"
        }
    ],
    "sg:phone":"+1 509 966 1337",
    "sg:postcode":"98908",
    "sg:province":"WA",
    "wof:name":"Maher Insurance Services",
    "wof:placetype":"venue"
},
  "geometry": {"coordinates":[-120.571782,46.602316],"type":"Point"}
}