{
  "type": "Feature",
  "properties": {
    "addr:full":"23002 63rd Ave W Mountlake Ter WA 98043",
    "addr:housenumber":"23002",
    "addr:postcode":"98043",
    "addr:street":"63Rd Ave W Mountlake Ter",
    "iso:country":"US",
    "sg:address":"23002 63rd Ave W",
    "sg:city":"Mountlake Ter",
    "sg:classifiers":[
        {
            "category":"Social Services",
            "subcategory":"Child Care",
            "type":"Services"
        }
    ],
    "sg:phone":"+1 425 775 6508",
    "sg:postcode":"98043",
    "sg:province":"WA",
    "sg:tags":[
        "day"
    ],
    "wof:name":"Ollie & Friends Day Care",
    "wof:placetype":"venue"
},
  "geometry": {"coordinates":[-122.318268,47.790983],"type":"Point"}
}