{
  "type": "Feature",
  "properties": {
    "addr:full":"2301 58th Ave E Tacoma WA 98424",
    "addr:housenumber":"2301",
    "addr:postcode":"98424",
    "addr:street":"58Th Ave E",
    "iso:country":"US",
    "sg:address":"2301 58th Ave E",
    "sg:city":"Tacoma",
    "sg:classifiers":[
        {
            "category":"Real Estate",
            "subcategory":"Real Estate Operator",
            "type":"Services"
        }
    ],
    "sg:phone":"+1 253 922 0352",
    "sg:postcode":"98424",
    "sg:province":"WA",
    "sg:tags":[
        "apartment"
    ],
    "wof:name":"Lakes At Fife",
    "wof:placetype":"venue"
},
  "geometry": {"coordinates":[-122.352155,47.236312],"type":"Point"}
}