{
  "type": "Feature",
  "properties": {
    "addr:full":"2667 SW 172nd St Seattle WA 98166",
    "addr:housenumber":"2667",
    "addr:postcode":"98166",
    "addr:street":"Sw 172Nd St",
    "iso:country":"US",
    "sg:address":"2667 SW 172nd St",
    "sg:city":"Seattle",
    "sg:classifiers":[
        {
            "category":"Professional",
            "subcategory":"Engineering",
            "type":"Services"
        }
    ],
    "sg:phone":"+1 206 242 3851",
    "sg:postcode":"98166",
    "sg:province":"WA",
    "wof:name":"Pulley Point Enterprise",
    "wof:placetype":"venue"
},
  "geometry": {"coordinates":[-122.36609199999999,47.448164],"type":"Point"}
}