{
  "type": "Feature",
  "properties": {
    "addr:full":"1610 S Gold St Centralia WA 98531",
    "addr:housenumber":"1610",
    "addr:postcode":"98531",
    "addr:street":"S Gold St",
    "iso:country":"US",
    "sg:address":"1610 S Gold St",
    "sg:city":"Centralia",
    "sg:classifiers":[
        {
            "category":"Home & Garden",
            "subcategory":"Hardware",
            "type":"Retail Goods"
        }
    ],
    "sg:phone":"+1 360 736 3203",
    "sg:postcode":"98531",
    "sg:province":"WA",
    "wof:name":"Westcoast Tool Supply",
    "wof:placetype":"venue"
},
  "geometry": {"coordinates":[-122.957341,46.697341],"type":"Point"}
}