{
  "type": "Feature",
  "properties": {
    "addr:full":"13621 103rd Ave NE Arlington WA 98223",
    "addr:housenumber":"13621",
    "addr:postcode":"98223",
    "addr:street":"103Rd Ave Ne",
    "iso:country":"US",
    "sg:address":"13621 103rd Ave NE",
    "sg:city":"Arlington",
    "sg:classifiers":[
        {
            "category":"Manufacturing",
            "subcategory":"Tools & Machinery",
            "type":"Manufacturing & Wholesale Goods"
        }
    ],
    "sg:phone":"+1 360 651 1962",
    "sg:postcode":"98223",
    "sg:province":"WA",
    "sg:tags":[
        "surgical",
        "mfg"
    ],
    "sg:website":"www.touchturner.com",
    "wof:name":"Touch Turner",
    "wof:placetype":"venue"
},
  "geometry": {"coordinates":[-122.09208599999999,48.116871],"type":"Point"}
}