{
  "type": "Feature",
  "properties": {
    "iso:country":"US",
    "sg:address":"701 16th St",
    "sg:city":"Bellingham",
    "sg:classifiers":[
        {
            "category":"Professional",
            "type":"Services"
        }
    ],
    "sg:phone":"+1 360 733 2470",
    "sg:postcode":"98225",
    "sg:province":"WA",
    "wof:name":"Three Roses",
    "wof:placetype":"venue"
},
  "geometry": {"coordinates":[-122.49716600000001,48.726417],"type":"Point"}
}