{
  "type": "Feature",
  "properties": {
    "addr:full":"12920 SE 38th St Bellevue WA 98006",
    "addr:housenumber":"12920",
    "addr:postcode":"98006",
    "addr:street":"Se 38Th St",
    "iso:country":"US",
    "sg:address":"12920 SE 38th St",
    "sg:city":"Bellevue",
    "sg:classifiers":[
        {
            "category":"Shopping",
            "subcategory":"Mobile Phones",
            "type":"Retail Goods"
        }
    ],
    "sg:phone":"+1 800 318 9270",
    "sg:postcode":"98006",
    "sg:province":"WA",
    "sg:website":"www.t-mobile.com",
    "wof:name":"T-Mobile",
    "wof:placetype":"venue"
},
  "geometry": {"coordinates":[-122.167886,47.576056],"type":"Point"}
}