{
  "type": "Feature",
  "properties": {
    "addr:full":"913 Dundee Rd NW Olympia WA 98502",
    "addr:housenumber":"913",
    "addr:postcode":"olympia wa 98502",
    "addr:street":"Dundee Rd Nw",
    "iso:country":"US",
    "sg:address":"913 Dundee Rd NW",
    "sg:city":"Olympia",
    "sg:classifiers":[
        {
            "category":"Education",
            "subcategory":"Dance Studio",
            "type":"Public Place"
        }
    ],
    "sg:phone":"+1 360 786 8567",
    "sg:postcode":"98502",
    "sg:province":"WA",
    "wof:name":"Ballet Folklorico Ollin",
    "wof:placetype":"venue"
},
  "geometry": {"coordinates":[-122.93419799999999,47.051587],"type":"Point"}
}