{
  "type": "Feature",
  "properties": {
    "addr:full":"641 W University Way Ellensburg WA 98926",
    "addr:housenumber":"641",
    "addr:postcode":"98926",
    "addr:street":"W University Way",
    "iso:country":"US",
    "sg:address":"641 W University Way",
    "sg:city":"Ellensburg",
    "sg:classifiers":[
        {
            "category":"Retail",
            "subcategory":"Auto Repair",
            "type":"Services"
        }
    ],
    "sg:phone":"+1 509 925 5680",
    "sg:postcode":"98926",
    "sg:province":"WA",
    "sg:tags":[
        "body",
        "automobile",
        "painting"
    ],
    "wof:name":"R & R Auto Body",
    "wof:placetype":"venue"
},
  "geometry": {"coordinates":[-120.55605199999999,46.99974],"type":"Point"}
}