{
  "type": "Feature",
  "properties": {
    "iso:country":"US",
    "sg:address":"215 S K St",
    "sg:city":"Aberdeen",
    "sg:classifiers":[
        {
            "category":"Travel",
            "subcategory":"Hotels & Motels",
            "type":"Entertainment"
        }
    ],
    "sg:phone":"+1 360 533 1013",
    "sg:postcode":"98520",
    "sg:province":"WA",
    "sg:tags":[
        "building",
        "operator",
        "operation",
        "apartment"
    ],
    "wof:name":"Morck Apartments Inc",
    "wof:placetype":"venue"
},
  "geometry": {"coordinates":[-123.81914500000001,46.973443],"type":"Point"}
}