{
  "type": "Feature",
  "properties": {
    "addr:full":"210 Oak Meadows Rd Oakville WA 98568",
    "addr:housenumber":"210",
    "addr:postcode":"98568",
    "addr:street":"Oak Meadows Rd",
    "iso:country":"US",
    "sg:address":"210 Oak Meadows Rd",
    "sg:city":"Oakville",
    "sg:classifiers":[
        {
            "category":"Building & Trades",
            "subcategory":"Construction",
            "type":"Services"
        }
    ],
    "sg:phone":"+1 360 273 9641",
    "sg:postcode":"98568",
    "sg:province":"WA",
    "sg:tags":[
        "house",
        "general",
        "remodeling",
        "contractor"
    ],
    "wof:name":"Dotson Electric & Construction",
    "wof:placetype":"venue"
},
  "geometry": {"coordinates":[-123.2881,46.855543],"type":"Point"}
}