{
  "type": "Feature",
  "properties": {
    "addr:full":"6725 W Clearwater Ave Kennewick WA 99336",
    "addr:housenumber":"6725",
    "addr:postcode":"99336",
    "addr:street":"W Clearwater Ave",
    "iso:country":"US",
    "sg:address":"6725 W Clearwater Ave",
    "sg:city":"Kennewick",
    "sg:classifiers":[
        {
            "category":"Professional",
            "subcategory":"Lawyer & Legal Services",
            "type":"Services"
        }
    ],
    "sg:phone":"+1 509 783 6154",
    "sg:postcode":"99336",
    "sg:province":"WA",
    "sg:tags":[
        "attorney",
        "law",
        "estate",
        "planning",
        "plan",
        "criminal"
    ],
    "wof:name":"Raekes, John - Rettig Osborne & Forgette",
    "wof:placetype":"venue"
},
  "geometry": {"coordinates":[-119.20934099999999,46.21127],"type":"Point"}
}