{
  "type": "Feature",
  "properties": {
    "iso:country":"US",
    "sg:address":"5446 Black Lake Blvd SW",
    "sg:city":"Olympia",
    "sg:classifiers":[
        {
            "category":"Travel",
            "subcategory":"Campground",
            "type":"Entertainment"
        }
    ],
    "sg:phone":"+1 360 357 8618",
    "sg:postcode":"98512",
    "sg:province":"WA",
    "sg:tags":[
        "trailer"
    ],
    "wof:name":"Salmon Shres Rv Pk On Black Lk",
    "wof:placetype":"venue"
},
  "geometry": {"coordinates":[-122.982822,46.998668],"type":"Point"}
}