{
  "type": "Feature",
  "properties": {
    "addr:full":"1148 22nd Ave Longview WA 98632",
    "addr:housenumber":"1148",
    "addr:postcode":"98632",
    "addr:street":"22Nd Ave",
    "iso:country":"US",
    "sg:address":"1148 22nd Ave",
    "sg:city":"Longview",
    "sg:classifiers":[
        {
            "category":"Professional",
            "subcategory":"Business Services",
            "type":"Services"
        }
    ],
    "sg:phone":"+1 360 693 7114",
    "sg:postcode":"98632",
    "sg:province":"WA",
    "wof:name":"Bishops Bail Bonds",
    "wof:placetype":"venue"
},
  "geometry": {"coordinates":[-122.94746000000001,46.136468],"type":"Point"}
}