{
  "type": "Feature",
  "properties": {
    "addr:full":"1511 14th Ave Seattle WA 98122",
    "addr:housenumber":"1511",
    "addr:postcode":"98122",
    "addr:street":"14Th Ave",
    "iso:country":"US",
    "sg:address":"1511 14th Ave",
    "sg:city":"Seattle",
    "sg:classifiers":[
        {
            "category":"Shopping",
            "subcategory":"Jewelry",
            "type":"Retail Goods"
        }
    ],
    "sg:phone":"+1 206 726 8551",
    "sg:postcode":"98122",
    "sg:province":"WA",
    "sg:tags":[
        "repair",
        "clocks",
        "watch"
    ],
    "wof:name":"Tiempo Timepiece & Jewelry",
    "wof:placetype":"venue"
},
  "geometry": {"coordinates":[-122.314318,47.615161],"type":"Point"}
}