{
  "type": "Feature",
  "properties": {
    "addr:full":"5211 146th St E Tacoma WA 98446",
    "addr:housenumber":"5211",
    "addr:postcode":"98446",
    "addr:street":"146Th St",
    "iso:country":"US",
    "sg:address":"5211 146th St E",
    "sg:city":"Tacoma",
    "sg:classifiers":[
        {
            "category":"Building & Trades",
            "subcategory":"Cleaning & Sanitation",
            "type":"Services"
        }
    ],
    "sg:phone":"+1 253 548 0761",
    "sg:postcode":"98446",
    "sg:province":"WA",
    "sg:tags":[
        "maintenance"
    ],
    "wof:name":"Ceiling Cleaning Specialist",
    "wof:placetype":"venue"
},
  "geometry": {"coordinates":[-122.361952,47.123686],"type":"Point"}
}