{
  "type": "Feature",
  "properties": {
    "iso:country":"US",
    "sg:address":"28029 197th Ave SE",
    "sg:city":"Kent",
    "sg:classifiers":[
        {
            "category":"Organizations",
            "subcategory":"Membership Organization",
            "type":"Services"
        }
    ],
    "sg:phone":"+1 253 631 0894",
    "sg:postcode":"98042",
    "sg:province":"WA",
    "wof:name":"Computer Bank Charity",
    "wof:placetype":"venue"
},
  "geometry": {"coordinates":[-122.07950599999999,47.350637],"type":"Point"}
}