{
  "type": "Feature",
  "properties": {
    "addr:full":"14808 NW 4th Ct Vancouver WA 98685",
    "addr:housenumber":"14808",
    "addr:postcode":"98685",
    "addr:street":"Nw 4Th Ct",
    "iso:country":"US",
    "sg:address":"14808 NW 4th Ct",
    "sg:city":"Vancouver",
    "sg:classifiers":[
        {
            "category":"Arts & Performance",
            "subcategory":"Theater",
            "type":"Entertainment"
        }
    ],
    "sg:phone":"+1 360 546 2172",
    "sg:postcode":"98685",
    "sg:province":"WA",
    "sg:tags":[
        "live",
        "music"
    ],
    "wof:name":"Prime Time Music",
    "wof:placetype":"venue"
},
  "geometry": {"coordinates":[-122.673765,45.728435],"type":"Point"}
}