{
  "type": "Feature",
  "properties": {
    "addr:full":"105 S 18th St Ste 227 Yakima WA 98901",
    "addr:housenumber":"105",
    "addr:postcode":"98901",
    "addr:street":"S 18Th St Ste 227",
    "iso:country":"US",
    "sg:address":"105 S 18th St Ste 227",
    "sg:city":"Yakima",
    "sg:classifiers":[
        {
            "category":"Sports & Exercise",
            "subcategory":"Playing Field",
            "type":"Entertainment"
        }
    ],
    "sg:phone":"+1 509 576 8004",
    "sg:postcode":"98901",
    "sg:province":"WA",
    "sg:tags":[
        "vegetable",
        "packer",
        "fruit"
    ],
    "sg:website":"http://www.goodfruit.com",
    "wof:name":"Northwest Fruit Exporters",
    "wof:placetype":"venue"
},
  "geometry": {"coordinates":[-120.47770300000001,46.603241],"type":"Point"}
}