{
  "type": "Feature",
  "properties": {
    "addr:full":"600 5th Ave S Seattle WA 98104",
    "addr:housenumber":"600",
    "addr:postcode":"98104",
    "addr:street":"5Th Ave S",
    "iso:country":"US",
    "sg:address":"600 5th Ave S",
    "sg:city":"Seattle",
    "sg:classifiers":[
        {
            "category":"Shopping",
            "subcategory":"Optician",
            "type":"Retail Goods"
        }
    ],
    "sg:phone":"+1 206 652 8436",
    "sg:postcode":"98104",
    "sg:province":"WA",
    "sg:tags":[
        "eyewear"
    ],
    "sg:website":"parismikiusa.com",
    "wof:name":"Paris Miki",
    "wof:placetype":"venue"
},
  "geometry": {"coordinates":[-122.328003,47.5975],"type":"Point"}
}