{
  "type": "Feature",
  "properties": {
    "addr:full":"9545 Yelm Hwy SE Olympia WA 98513",
    "addr:housenumber":"9545",
    "addr:postcode":"98513",
    "addr:street":"Yelm Hwy Se",
    "iso:country":"US",
    "sg:address":"9545 Yelm Hwy SE",
    "sg:city":"Olympia",
    "sg:classifiers":[
        {
            "category":"Manufacturing",
            "subcategory":"Lumber",
            "type":"Manufacturing & Wholesale Goods"
        }
    ],
    "sg:phone":"+1 360 459 5743",
    "sg:postcode":"98513",
    "sg:province":"WA",
    "sg:tags":[
        "logging"
    ],
    "wof:name":"Carol & Dennis Akehurst",
    "wof:placetype":"venue"
},
  "geometry": {"coordinates":[-122.738218,46.985512],"type":"Point"}
}