{
  "type": "Feature",
  "properties": {
    "addr:full":"908 Narnia Ln NW Olympia WA 98502",
    "addr:housenumber":"908",
    "addr:postcode":"olympia wa 98502",
    "addr:street":"Narnia Ln Nw",
    "iso:country":"US",
    "sg:address":"908 Narnia Ln NW",
    "sg:city":"Olympia",
    "sg:classifiers":[
        {
            "category":"Personal",
            "type":"Services"
        }
    ],
    "sg:phone":"+1 360 866 0800",
    "sg:postcode":"98502",
    "sg:province":"WA",
    "wof:name":"Bubbling Well Healing Art",
    "wof:placetype":"venue"
},
  "geometry": {"coordinates":[-122.967648,47.053407],"type":"Point"}
}