{
  "type": "Feature",
  "properties": {
    "addr:full":"4197 Georgia Ct Silverdale WA 98315",
    "addr:housenumber":"4197",
    "addr:postcode":"98315",
    "addr:street":"Georgia Ct",
    "iso:country":"US",
    "sg:address":"4197 Georgia Ct",
    "sg:city":"Silverdale",
    "sg:classifiers":[
        {
            "category":"Retail",
            "subcategory":"Driving School",
            "type":"Services"
        }
    ],
    "sg:phone":"+1 360 535 7884",
    "sg:postcode":"98315",
    "sg:province":"WA",
    "sg:tags":[
        "instruction",
        "traffic"
    ],
    "wof:name":"Cdc Driving Improvement",
    "wof:placetype":"venue"
},
  "geometry": {"coordinates":[-122.731565,47.689904],"type":"Point"}
}