{
  "type": "Feature",
  "properties": {
    "addr:full":"1211 E Princeton Ave Spokane WA 99207",
    "addr:housenumber":"1211",
    "addr:postcode":"99207",
    "addr:street":"E Princeton Ave",
    "iso:country":"US",
    "sg:address":"1211 E Princeton Ave",
    "sg:city":"Spokane",
    "sg:classifiers":[
        {
            "category":"Professional",
            "type":"Services"
        }
    ],
    "sg:phone":"+1 509 370 1721",
    "sg:postcode":"99207",
    "sg:province":"WA",
    "wof:name":"Bruce Herrmann",
    "wof:placetype":"venue"
},
  "geometry": {"coordinates":[-117.38976700000001,47.699254],"type":"Point"}
}