{
  "type": "Feature",
  "properties": {
    "addr:full":"8916 5th Ave NE Seattle WA 98115",
    "addr:housenumber":"8916",
    "addr:postcode":"98115",
    "addr:street":"5Th Ave Ne",
    "iso:country":"US",
    "sg:address":"8916 5th Ave NE",
    "sg:city":"Seattle",
    "sg:classifiers":[
        {
            "category":"Social Services",
            "subcategory":"Child Care",
            "type":"Services"
        }
    ],
    "sg:phone":"+1 206 522 7646",
    "sg:postcode":"98115",
    "sg:province":"WA",
    "sg:tags":[
        "day"
    ],
    "wof:name":"Ce Ces Playhouse",
    "wof:placetype":"venue"
},
  "geometry": {"coordinates":[-122.322959,47.693282],"type":"Point"}
}