{
  "type": "Feature",
  "properties": {
    "addr:full":"7235 NE James St Suquamish WA 98392",
    "addr:housenumber":"7235",
    "addr:postcode":"98392",
    "addr:street":"Ne James St",
    "iso:country":"US",
    "sg:address":"7235 NE James St",
    "sg:city":"Suquamish",
    "sg:classifiers":[
        {
            "category":"Professional",
            "subcategory":"Accounting & Tax Preparation",
            "type":"Services"
        }
    ],
    "sg:phone":"+1 360 598 6775",
    "sg:postcode":"98392",
    "sg:province":"WA",
    "wof:name":"Northwestern Medical Billing",
    "wof:placetype":"venue"
},
  "geometry": {"coordinates":[-122.551914,47.735207],"type":"Point"}
}