{
  "type": "Feature",
  "properties": {
    "addr:full":"813 Avenue D Snohomish WA 98290",
    "addr:housenumber":"813",
    "addr:postcode":"98290",
    "addr:street":"Avenue D",
    "iso:country":"US",
    "sg:address":"813 Avenue D",
    "sg:city":"Snohomish",
    "sg:classifiers":[
        {
            "category":"Personal",
            "subcategory":"Nail Salon",
            "type":"Services"
        }
    ],
    "sg:phone":"+1 360 568 4701",
    "sg:postcode":"98290",
    "sg:province":"WA",
    "wof:name":"Awesome Nail & Hair",
    "wof:placetype":"venue"
},
  "geometry": {"coordinates":[-122.098012,47.921806],"type":"Point"}
}