{
  "type": "Feature",
  "properties": {
    "addr:full":"1800 NE Lincoln Rd # 45 Poulsbo WA 98370",
    "addr:housenumber":"1800",
    "addr:postcode":"98370",
    "addr:street":"Ne Lincoln Rd # 45",
    "iso:country":"US",
    "sg:address":"1800 NE Lincoln Rd # 45",
    "sg:city":"Poulsbo",
    "sg:classifiers":[
        {
            "category":"Shopping",
            "subcategory":"Catalog Store",
            "type":"Retail Goods"
        }
    ],
    "sg:phone":"+1 360 697 1637",
    "sg:postcode":"98370",
    "sg:province":"WA",
    "sg:tags":[
        "mail",
        "order",
        "online"
    ],
    "wof:name":"Quick Star",
    "wof:placetype":"venue"
},
  "geometry": {"coordinates":[-122.62487,47.740059],"type":"Point"}
}