{
  "type": "Feature",
  "properties": {
    "addr:full":"655 Lynnwood Loop Richland WA 99354",
    "addr:housenumber":"655",
    "addr:postcode":"99354",
    "addr:street":"Lynnwood Loop",
    "iso:country":"US",
    "sg:address":"655 Lynnwood Loop",
    "sg:city":"Richland",
    "sg:classifiers":[
        {
            "category":"Professional",
            "subcategory":"Computer Services",
            "type":"Services"
        }
    ],
    "sg:phone":"+1 509 375 0475",
    "sg:postcode":"99354",
    "sg:province":"WA",
    "sg:tags":[
        "datum"
    ],
    "wof:name":"Opertunities LLC",
    "wof:placetype":"venue"
},
  "geometry": {"coordinates":[-119.27883,46.312003],"type":"Point"}
}