{
  "type": "Feature",
  "properties": {
    "iso:country":"US",
    "sg:address":"2401 S 35th St",
    "sg:city":"Tacoma",
    "sg:classifiers":[
        {
            "category":"Government",
            "subcategory":"Office",
            "type":"Public Place"
        }
    ],
    "sg:phone":"+1 253 798 3649",
    "sg:postcode":"98409",
    "sg:province":"WA",
    "sg:tags":[
        "county",
        "taxation"
    ],
    "sg:website":"www.co.pierce.wa.us/auditor",
    "wof:name":"Auditor Office",
    "wof:placetype":"venue"
},
  "geometry": {"coordinates":[-122.473535,47.228293],"type":"Point"}
}