{
  "type": "Feature",
  "properties": {
    "addr:full":"5450 US Hwy 97 Peshastin WA 98847",
    "addr:housenumber":"5450",
    "addr:postcode":"98847",
    "addr:street":"Us Hwy 97 Peshastin",
    "iso:country":"US",
    "sg:address":"5450 US Hwy 97",
    "sg:city":"Peshastin",
    "sg:classifiers":[
        {
            "category":"Manufacturing",
            "subcategory":"Lumber",
            "type":"Manufacturing & Wholesale Goods"
        }
    ],
    "sg:phone":"+1 509 548 1154",
    "sg:postcode":"98847",
    "sg:province":"WA",
    "sg:tags":[
        "logging",
        "contractor"
    ],
    "wof:name":"Marcon Timber Co Inc",
    "wof:placetype":"venue"
},
  "geometry": {"coordinates":[-120.628259,47.51552],"type":"Point"}
}