{
  "type": "Feature",
  "properties": {
    "addr:full":"1827 E Maryland St Bellingham WA 98226",
    "addr:housenumber":"1827",
    "addr:postcode":"98226",
    "addr:street":"E Maryland St",
    "iso:country":"US",
    "sg:address":"1827 E Maryland St",
    "sg:city":"Bellingham",
    "sg:classifiers":[
        {
            "category":"Building & Trades",
            "subcategory":"Landscaping Services",
            "type":"Services"
        }
    ],
    "sg:phone":"+1 360 714 8525",
    "sg:postcode":"98226",
    "sg:province":"WA",
    "wof:name":"Done Right Cleaning & Yar",
    "wof:placetype":"venue"
},
  "geometry": {"coordinates":[-122.451278,48.766902],"type":"Point"}
}