{
  "type": "Feature",
  "properties": {
    "addr:full":"5246 Patton Blvd NE Moses Lake WA 98837",
    "addr:housenumber":"5246",
    "addr:postcode":"98837",
    "addr:street":"Patton Blvd Ne",
    "iso:country":"US",
    "sg:address":"5246 Patton Blvd NE",
    "sg:city":"Moses Lake",
    "sg:classifiers":[
        {
            "category":"Government",
            "subcategory":"Office",
            "type":"Public Place"
        }
    ],
    "sg:phone":"+1 509 762 3062",
    "sg:postcode":"98837",
    "sg:province":"WA",
    "wof:name":"Grant County Office",
    "wof:placetype":"venue"
},
  "geometry": {"coordinates":[-119.312963,47.161623],"type":"Point"}
}