{
  "type": "Feature",
  "properties": {
    "addr:full":"1233 6th Avenue Seattle WA 98101",
    "addr:housenumber":"1233",
    "addr:postcode":"98101",
    "addr:street":"6Th Avenue",
    "iso:country":"US",
    "sg:address":"1233 6th Avenue",
    "sg:city":"Seattle",
    "sg:classifiers":[
        {
            "category":"Shopping",
            "subcategory":"Clothing, Apparel, & Fashions",
            "type":"Retail Goods"
        }
    ],
    "sg:phone":"+1 206 447 1881",
    "sg:postcode":"98101",
    "sg:province":"WA",
    "sg:tags":[
        "clothing",
        "women's"
    ],
    "wof:name":"Image Concepts",
    "wof:placetype":"venue"
},
  "geometry": {"coordinates":[-122.332313,47.608632],"type":"Point"}
}