{
  "type": "Feature",
  "properties": {
    "addr:full":"11013 NE 39th St Ste A Vancouver WA 98682",
    "addr:housenumber":"11013",
    "addr:postcode":"wa 98682",
    "addr:street":"Ne 39Th St Ste A",
    "iso:country":"US",
    "sg:address":"11013 NE 39th St Ste A",
    "sg:city":"Vancouver",
    "sg:classifiers":[
        {
            "category":"Professional",
            "subcategory":"Lawyer & Legal Services",
            "type":"Services"
        }
    ],
    "sg:phone":"+1 360 253 1500",
    "sg:postcode":"98682",
    "sg:province":"WA",
    "sg:tags":[
        "case"
    ],
    "wof:name":"Bauer Cases",
    "wof:placetype":"venue"
},
  "geometry": {"coordinates":[-122.560231,45.6507],"type":"Point"}
}