{
  "type": "Feature",
  "properties": {
    "addr:full":"32885 State Rte 20 Oak Harbor WA 98277",
    "addr:housenumber":"32885",
    "addr:postcode":"98277",
    "addr:street":"State Rte 20",
    "iso:country":"US",
    "sg:address":"32885 State Rte 20",
    "sg:city":"Oak Harbor",
    "sg:classifiers":[
        {
            "category":"Real Estate",
            "subcategory":"Real Estate Agent",
            "type":"Services"
        }
    ],
    "sg:phone":"+1 360 675 9094",
    "sg:postcode":"98277",
    "sg:province":"WA",
    "sg:tags":[
        "sales"
    ],
    "wof:name":"Panorama Properties",
    "wof:placetype":"venue"
},
  "geometry": {"coordinates":[-122.64464,48.305191],"type":"Point"}
}