{
  "type": "Feature",
  "properties": {
    "addr:full":"701 5th Ave Seattle WA 98104",
    "addr:housenumber":"701",
    "addr:postcode":"98104",
    "addr:street":"5Th Ave",
    "iso:country":"US",
    "sg:address":"701 5th Ave",
    "sg:city":"Seattle",
    "sg:classifiers":[
        {
            "category":"Autos & Motor Vehicles",
            "subcategory":"Automobile Sales",
            "type":"Retail Goods"
        }
    ],
    "sg:phone":"+1 206 271 8844",
    "sg:postcode":"98104",
    "sg:province":"WA",
    "sg:tags":[
        "limo"
    ],
    "sg:website":"www.northwestlimousineinc.com",
    "wof:name":"Northwest Limousine",
    "wof:placetype":"venue"
},
  "geometry": {"coordinates":[-122.33077900000001,47.604828],"type":"Point"}
}