{
  "type": "Feature",
  "properties": {
    "addr:full":"2360 62nd Ave E Tacoma WA 98424",
    "addr:housenumber":"2360",
    "addr:postcode":"98424",
    "addr:street":"62Nd Ave E",
    "iso:country":"US",
    "sg:address":"2360 62nd Ave E",
    "sg:city":"Tacoma",
    "sg:classifiers":[
        {
            "category":"Real Estate",
            "subcategory":"Real Estate Operator",
            "type":"Services"
        }
    ],
    "sg:phone":"+1 253 922 8850",
    "sg:postcode":"98424",
    "sg:province":"WA",
    "sg:tags":[
        "apartment"
    ],
    "wof:name":"Sherwood Park Apartments",
    "wof:placetype":"venue"
},
  "geometry": {"coordinates":[-122.34721,47.236098],"type":"Point"}
}