{
  "type": "Feature",
  "properties": {
    "iso:country":"US",
    "sg:address":"84 Bayview Park Ln",
    "sg:city":"Port Angeles",
    "sg:classifiers":[
        {
            "category":"Building & Trades",
            "subcategory":"Cleaning & Sanitation",
            "type":"Services"
        }
    ],
    "sg:phone":"+1 360 452 0780",
    "sg:postcode":"98362",
    "sg:province":"WA",
    "sg:tags":[
        "house"
    ],
    "wof:name":"Housekeeping & Window Washing",
    "wof:placetype":"venue"
},
  "geometry": {"coordinates":[-123.369095,48.102178],"type":"Point"}
}