{
  "type": "Feature",
  "properties": {
    "addr:full":"375 118th Ave SE Ste 210 Bellevue WA 98005",
    "addr:housenumber":"375",
    "addr:postcode":"98005",
    "addr:street":"118Th Ave Se Ste 210",
    "iso:country":"US",
    "sg:address":"375 118th Ave SE Ste 210",
    "sg:city":"Bellevue",
    "sg:classifiers":[
        {
            "category":"Banks & Credit Unions",
            "subcategory":"Financial Services",
            "type":"Services"
        }
    ],
    "sg:phone":"+1 425 641 4800",
    "sg:postcode":"98005",
    "sg:province":"WA",
    "sg:tags":[
        "broker",
        "mortgage"
    ],
    "wof:name":"First Mark Mortgage",
    "wof:placetype":"venue"
},
  "geometry": {"coordinates":[-122.182999,47.606701],"type":"Point"}
}