{
  "type": "Feature",
  "properties": {
    "addr:full":"5701 6th Ave South Suite 479 Seattle WA 98108",
    "addr:housenumber":"5701",
    "addr:postcode":"98108",
    "addr:street":"6Th Ave South Suite 479",
    "iso:country":"US",
    "sg:address":"5701 6th Ave South Suite 479",
    "sg:city":"Seattle",
    "sg:classifiers":[
        {
            "category":"Shopping",
            "subcategory":"Computers & Home Electronics",
            "type":"Retail Goods"
        }
    ],
    "sg:phone":"+1 206 264 9386",
    "sg:postcode":"98108",
    "sg:province":"WA",
    "sg:website":"www.pacificproaudio.com",
    "wof:name":"Pacific Pro Audio",
    "wof:placetype":"venue"
},
  "geometry": {"coordinates":[-122.326909,47.551807],"type":"Point"}
}