{
  "type": "Feature",
  "properties": {
    "addr:full":"1900 W Nickerson Street Suite 112 Seattle WA 98119",
    "addr:housenumber":"1900",
    "addr:postcode":"98119",
    "addr:street":"W Nickerson Street Suite 112",
    "iso:country":"US",
    "sg:address":"1900 W Nickerson Street Suite 112",
    "sg:city":"Seattle",
    "sg:classifiers":[
        {
            "category":"Shopping",
            "subcategory":"Tobacco",
            "type":"Retail Goods"
        }
    ],
    "sg:phone":"+1 206 286 0851",
    "sg:postcode":"98119",
    "sg:province":"WA",
    "sg:tags":[
        "shop"
    ],
    "wof:name":"Kirsten F K Ltd",
    "wof:placetype":"venue"
},
  "geometry": {"coordinates":[-122.381418,47.654873],"type":"Point"}
}