{
  "type": "Feature",
  "properties": {
    "iso:country":"US",
    "sg:address":"7500 Detroit Ave SW",
    "sg:city":"Seattle",
    "sg:classifiers":[
        {
            "category":"Manufacturing",
            "subcategory":"Tools & Machinery",
            "type":"Manufacturing & Wholesale Goods"
        }
    ],
    "sg:phone":"+1 206 767 8253",
    "sg:postcode":"98106",
    "sg:province":"WA",
    "sg:tags":[
        "undercarriage",
        "tractor"
    ],
    "wof:name":"Intertractor America Corp",
    "wof:placetype":"venue"
},
  "geometry": {"coordinates":[-122.34084300000001,47.538196],"type":"Point"}
}