{
  "type": "Feature",
  "properties": {
    "iso:country":"US",
    "sg:address":"916 Pacific Ave",
    "sg:city":"Everett",
    "sg:classifiers":[
        {
            "category":"Health Services",
            "subcategory":"Medical Lab",
            "type":"Services"
        }
    ],
    "sg:phone":"+1 425 258 7255",
    "sg:postcode":"98201",
    "sg:province":"WA",
    "sg:tags":[
        "radiotherapy"
    ],
    "wof:name":"Flynn Radiation Therapy Svc",
    "wof:placetype":"venue"
},
  "geometry": {"coordinates":[-122.218237,47.976406],"type":"Point"}
}