{
  "type": "Feature",
  "properties": {
    "iso:country":"US",
    "sg:address":"1913 W Maxwell Ave",
    "sg:city":"Spokane",
    "sg:classifiers":[
        {
            "category":"Building & Trades",
            "subcategory":"Construction",
            "type":"Services"
        }
    ],
    "sg:phone":"+1 509 328 2218",
    "sg:postcode":"99201",
    "sg:province":"WA",
    "sg:tags":[
        "general",
        "contractor"
    ],
    "wof:name":"Lill Construction Co",
    "wof:placetype":"venue"
},
  "geometry": {"coordinates":[-117.441256,47.670741],"type":"Point"}
}