{
  "type": "Feature",
  "properties": {
    "addr:full":"2546 P Rd NE Mansfield WA 98830",
    "addr:housenumber":"2546",
    "addr:postcode":"98830",
    "addr:street":"P Rd Ne",
    "iso:country":"US",
    "sg:address":"2546 P Rd NE",
    "sg:city":"Mansfield",
    "sg:classifiers":[
        {
            "category":"Manufacturing",
            "subcategory":"Lumber",
            "type":"Manufacturing & Wholesale Goods"
        }
    ],
    "sg:phone":"+1 509 686 8583",
    "sg:postcode":"98830",
    "sg:province":"WA",
    "sg:tags":[
        "fire",
        "forest",
        "fighting"
    ],
    "wof:name":"Crossfire Wild Land Frfighters",
    "wof:placetype":"venue"
},
  "geometry": {"coordinates":[-119.408467,47.991266],"type":"Point"}
}