{
  "type": "Feature",
  "properties": {
    "iso:country":"US",
    "sg:address":"7815 Bobcat Dr SE",
    "sg:city":"Lacey",
    "sg:classifiers":[
        {
            "category":"Home & Garden",
            "subcategory":"Carpets & Floor Coverings",
            "type":"Retail Goods"
        }
    ],
    "sg:phone":"+1 360 459 0108",
    "sg:postcode":"98503",
    "sg:province":"WA",
    "sg:tags":[
        "installs"
    ],
    "wof:name":"Got It Covered Flooring",
    "wof:placetype":"venue"
},
  "geometry": {"coordinates":[-122.773117,47.048865],"type":"Point"}
}