{
  "type": "Feature",
  "properties": {
    "addr:full":"6917 Coal Creek Pkwy SE Newcastle WA 98059",
    "addr:housenumber":"6917",
    "addr:postcode":"98059",
    "addr:street":"Coal Creek Pkwy Se",
    "iso:country":"US",
    "sg:address":"6917 Coal Creek Pkwy SE",
    "sg:city":"Newcastle",
    "sg:classifiers":[
        {
            "category":"Cinema",
            "subcategory":"Movie Rental",
            "type":"Entertainment"
        }
    ],
    "sg:phone":"+1 425 746 8050",
    "sg:postcode":"98059",
    "sg:province":"WA",
    "sg:tags":[
        "leasing",
        "video",
        "disc",
        "tape"
    ],
    "wof:name":"Blockbuster Video",
    "wof:placetype":"venue"
},
  "geometry": {"coordinates":[-122.166078,47.538243],"type":"Point"}
}