{
  "type": "Feature",
  "properties": {
    "addr:full":"3971 N Coulee Rd Eltopia WA 99330",
    "addr:housenumber":"3971",
    "addr:postcode":"99330",
    "addr:street":"N Coulee Rd",
    "iso:country":"US",
    "sg:address":"3971 N Coulee Rd",
    "sg:city":"Eltopia",
    "sg:classifiers":[
        {
            "category":"Farming",
            "subcategory":"Farm",
            "type":"Manufacturing & Wholesale Goods"
        }
    ],
    "sg:phone":"+1 509 266 4335",
    "sg:postcode":"99330",
    "sg:province":"WA",
    "wof:name":"Mcgary Farms",
    "wof:placetype":"venue"
},
  "geometry": {"coordinates":[-119.163898,46.505273],"type":"Point"}
}