{
  "type": "Feature",
  "properties": {
    "addr:full":"718 S College Ave College Place WA 99324",
    "addr:housenumber":"718",
    "addr:postcode":"99324",
    "addr:street":"S College Ave",
    "iso:country":"US",
    "sg:address":"718 S College Ave",
    "sg:city":"College Place",
    "sg:classifiers":[
        {
            "category":"Social Services",
            "type":"Services"
        }
    ],
    "sg:phone":"+1 509 529 5906",
    "sg:postcode":"99324",
    "sg:province":"WA",
    "wof:name":"Habitat For Humanity Blue Mt P",
    "wof:placetype":"venue"
},
  "geometry": {"coordinates":[-118.388616,46.042776],"type":"Point"}
}