{
  "type": "Feature",
  "properties": {
    "iso:country":"US",
    "sg:address":"11816 NE 160th St",
    "sg:city":"Brush Prairie",
    "sg:classifiers":[
        {
            "category":"Building & Trades",
            "subcategory":"Construction",
            "type":"Services"
        }
    ],
    "sg:phone":"+1 360 921 7991",
    "sg:postcode":"98606",
    "sg:province":"WA",
    "sg:tags":[
        "contractor"
    ],
    "wof:name":"Northern Fireplaces",
    "wof:placetype":"venue"
},
  "geometry": {"coordinates":[-122.549696,45.738089],"type":"Point"}
}