{
  "type": "Feature",
  "properties": {
    "addr:full":"18523 N Water St Colbert WA 99005",
    "addr:housenumber":"18523",
    "addr:postcode":"99005",
    "addr:street":"N Water St Colbert",
    "iso:country":"US",
    "sg:address":"18523 N Water St",
    "sg:city":"Colbert",
    "sg:classifiers":[
        {
            "category":"Freight",
            "type":"Transportation"
        }
    ],
    "sg:phone":"+1 509 238 6513",
    "sg:postcode":"99005",
    "sg:province":"WA",
    "sg:tags":[
        "operator",
        "local",
        "trucking"
    ],
    "wof:name":"John H Aiken",
    "wof:placetype":"venue"
},
  "geometry": {"coordinates":[-117.34514900000001,47.826182],"type":"Point"}
}