{
  "type": "Feature",
  "properties": {
    "addr:full":"4601 Mason St Port Townsend WA 98368",
    "addr:housenumber":"4601",
    "addr:postcode":"98368",
    "addr:street":"Mason St",
    "iso:country":"US",
    "sg:address":"4601 Mason St",
    "sg:city":"Port Townsend",
    "sg:classifiers":[
        {
            "category":"Real Estate",
            "subcategory":"Architect",
            "type":"Services"
        }
    ],
    "sg:phone":"+1 360 385 6140",
    "sg:postcode":"98368",
    "sg:province":"WA",
    "wof:name":"KIRK Boike Architects",
    "wof:placetype":"venue"
},
  "geometry": {"coordinates":[-122.80072699999999,48.133361],"type":"Point"}
}