{
  "type": "Feature",
  "properties": {
    "addr:full":"204 W Simpson Ave Mccleary WA 98557",
    "addr:housenumber":"204",
    "addr:postcode":"98557",
    "addr:street":"W Simpson Ave",
    "iso:country":"US",
    "sg:address":"204 W Simpson Ave",
    "sg:city":"Mccleary",
    "sg:classifiers":[
        {
            "category":"Food & Beverages",
            "subcategory":"Groceries & Convenience Stores",
            "type":"Retail Goods"
        },
        {
            "category":"Autos & Motor Vehicles",
            "subcategory":"Fuel & Gas Station",
            "type":"Retail Goods"
        }
    ],
    "sg:phone":"+1 360 495 4157",
    "sg:postcode":"98557",
    "sg:province":"WA",
    "sg:tags":[
        "station",
        "gasoline"
    ],
    "wof:name":"Mike's Market",
    "wof:placetype":"venue"
},
  "geometry": {"coordinates":[-123.267262,47.055693],"type":"Point"}
}