{
  "type": "Feature",
  "properties": {
    "addr:full":"16820 E Meridian Ave Puyallup WA 98375",
    "addr:housenumber":"16820",
    "addr:postcode":"98375",
    "addr:street":"E Meridian Ave",
    "iso:country":"US",
    "sg:address":"16820 E Meridian Ave",
    "sg:city":"Puyallup",
    "sg:classifiers":[
        {
            "category":"Freight",
            "type":"Transportation"
        }
    ],
    "sg:phone":"+1 253 841 1400",
    "sg:postcode":"98375",
    "sg:province":"WA",
    "sg:tags":[
        "recreational",
        "special",
        "vehicle"
    ],
    "wof:name":"Firgrove Self Storage",
    "wof:placetype":"venue"
},
  "geometry": {"coordinates":[-122.293526,47.10279],"type":"Point"}
}