{
  "type": "Feature",
  "properties": {
    "addr:full":"205 S British Columbia Ave Lynden WA 98264",
    "addr:housenumber":"205",
    "addr:postcode":"98264",
    "addr:street":"S British Columbia Ave",
    "iso:country":"US",
    "sg:address":"205 S British Columbia Ave",
    "sg:city":"Lynden",
    "sg:classifiers":[
        {
            "category":"Social Services",
            "type":"Services"
        }
    ],
    "sg:phone":"+1 360 354 1501",
    "sg:postcode":"98264",
    "sg:province":"WA",
    "sg:tags":[
        "organization",
        "individual",
        "family",
        "welfare"
    ],
    "wof:name":"One To One",
    "wof:placetype":"venue"
},
  "geometry": {"coordinates":[-122.463526,48.938747],"type":"Point"}
}