{
  "type": "Feature",
  "properties": {
    "addr:full":"7749 15th Ave NW Seattle WA 98117",
    "addr:housenumber":"7749",
    "addr:postcode":"98117",
    "addr:street":"15Th Ave Nw",
    "iso:country":"US",
    "sg:address":"7749 15th Ave NW",
    "sg:city":"Seattle",
    "sg:classifiers":[
        {
            "category":"Shopping",
            "subcategory":"Gifts & Souvenirs",
            "type":"Retail Goods"
        }
    ],
    "sg:phone":"+1 206 297 9800",
    "sg:postcode":"98117",
    "sg:province":"WA",
    "wof:name":"Romanza Gifts Web Store",
    "wof:placetype":"venue"
},
  "geometry": {"coordinates":[-122.376868,47.686583],"type":"Point"}
}