{
  "type": "Feature",
  "properties": {
    "addr:full":"112 1st St Cosmopolis WA 98537",
    "addr:housenumber":"112",
    "addr:postcode":"98537",
    "addr:street":"1St St",
    "iso:country":"US",
    "sg:address":"112 1st St",
    "sg:city":"Cosmopolis",
    "sg:classifiers":[
        {
            "category":"Manufacturing",
            "subcategory":"Lumber",
            "type":"Manufacturing & Wholesale Goods"
        }
    ],
    "sg:phone":"+1 360 532 9565",
    "sg:postcode":"98537",
    "sg:province":"WA",
    "wof:name":"Premier Forest Products",
    "wof:placetype":"venue"
},
  "geometry": {"coordinates":[-123.778482,46.961394],"type":"Point"}
}