{
  "type": "Feature",
  "properties": {
    "addr:full":"1100 E Sunset Dr Bellingham WA 98226",
    "addr:housenumber":"1100",
    "addr:postcode":"98226",
    "addr:street":"E Sunset Dr",
    "iso:country":"US",
    "sg:address":"1100 E Sunset Dr",
    "sg:city":"Bellingham",
    "sg:classifiers":[
        {
            "category":"Coffee & Tea",
            "type":"Food & Drink"
        },
        {
            "category":"Food & Beverages",
            "subcategory":"Groceries & Convenience Stores",
            "type":"Retail Goods"
        }
    ],
    "sg:phone":"+1 360 734 3013",
    "sg:postcode":"98226",
    "sg:province":"WA",
    "sg:tags":[
        "espresso",
        "restaurant"
    ],
    "sg:website":"http://bigfootjava.com",
    "wof:name":"Sunset Way Bigfoot Java",
    "wof:placetype":"venue"
},
  "geometry": {"coordinates":[-122.46151999999999,48.771769],"type":"Point"}
}