{
  "type": "Feature",
  "properties": {
    "addr:full":"15 S Grady Way Ste 120 Renton WA 98057",
    "addr:housenumber":"15",
    "addr:postcode":"98057",
    "addr:street":"S Grady Way Ste 120",
    "iso:country":"US",
    "sg:address":"15 S Grady Way Ste 120",
    "sg:city":"Renton",
    "sg:classifiers":[
        {
            "category":"Banks & Credit Unions",
            "subcategory":"Financial Services",
            "type":"Services"
        }
    ],
    "sg:phone":"+1 425 254 8010",
    "sg:postcode":"98057",
    "sg:province":"WA",
    "sg:tags":[
        "broker",
        "mortgage"
    ],
    "wof:name":"Bank of America",
    "wof:placetype":"venue"
},
  "geometry": {"coordinates":[-122.216954,47.470749],"type":"Point"}
}