{
  "type": "Feature",
  "properties": {
    "addr:full":"2381 Nelson Siding Rd Cle Elum WA 98922",
    "addr:housenumber":"2381",
    "addr:postcode":"98922",
    "addr:street":"Nelson Siding Rd",
    "iso:country":"US",
    "sg:address":"2381 Nelson Siding Rd",
    "sg:city":"Cle Elum",
    "sg:classifiers":[
        {
            "category":"Shopping",
            "type":"Retail Goods"
        }
    ],
    "sg:phone":"+1 509 674 2591",
    "sg:postcode":"98922",
    "sg:province":"WA",
    "sg:tags":[
        "merchandise"
    ],
    "wof:name":"Anitas Mgcal Touch All Natural",
    "wof:placetype":"venue"
},
  "geometry": {"coordinates":[-121.08716200000001,47.197271],"type":"Point"}
}