{
  "type": "Feature",
  "properties": {
    "addr:full":"1616 S 223rd St Seattle WA 98198",
    "addr:housenumber":"1616",
    "addr:postcode":"98198",
    "addr:street":"S 223Rd St",
    "iso:country":"US",
    "sg:address":"1616 S 223rd St",
    "sg:city":"Seattle",
    "sg:classifiers":[
        {
            "category":"Building & Trades",
            "subcategory":"Construction",
            "type":"Services"
        }
    ],
    "sg:phone":"+1 206 824 5520",
    "sg:postcode":"98198",
    "sg:province":"WA",
    "sg:tags":[
        "contractor"
    ],
    "wof:name":"Industriap",
    "wof:placetype":"venue"
},
  "geometry": {"coordinates":[-122.309878,47.402218],"type":"Point"}
}