{
  "type": "Feature",
  "properties": {
    "addr:full":"17417 55th Pl W Lynnwood WA 98037",
    "addr:housenumber":"17417",
    "addr:postcode":"98037",
    "addr:street":"55Th Pl W",
    "iso:country":"US",
    "sg:address":"17417 55th Pl W",
    "sg:city":"Lynnwood",
    "sg:classifiers":[
        {
            "category":"Building & Trades",
            "subcategory":"Construction",
            "type":"Services"
        }
    ],
    "sg:phone":"+1 206 390 6963",
    "sg:postcode":"98037",
    "sg:province":"WA",
    "sg:tags":[
        "house"
    ],
    "wof:name":"Thom Lee Construction Inc",
    "wof:placetype":"venue"
},
  "geometry": {"coordinates":[-122.308358,47.840371],"type":"Point"}
}