{
  "type": "Feature",
  "properties": {
    "addr:full":"999 Lake Dr Issaquah WA 98027",
    "addr:housenumber":"999",
    "addr:postcode":"98027",
    "addr:street":"Lake Dr",
    "iso:country":"US",
    "sg:address":"999 Lake Dr",
    "sg:city":"Issaquah",
    "sg:classifiers":[
        {
            "category":"Food & Beverages",
            "subcategory":"Liquor & Beverages",
            "type":"Retail Goods"
        }
    ],
    "sg:phone":"+1 425 313 8091",
    "sg:postcode":"98027",
    "sg:province":"WA",
    "sg:tags":[
        "beverages-distributors",
        "bottler",
        "wine"
    ],
    "wof:name":"National Distributors",
    "wof:placetype":"venue"
},
  "geometry": {"coordinates":[-122.050308,47.54974],"type":"Point"}
}