{
  "type": "Feature",
  "properties": {
    "addr:full":"82 Stewart St Seattle WA 98101",
    "addr:housenumber":"82",
    "addr:postcode":"98101",
    "addr:street":"Stewart St",
    "iso:country":"US",
    "sg:address":"82 Stewart St",
    "sg:city":"Seattle",
    "sg:classifiers":[
        {
            "category":"Restaurant",
            "type":"Food & Drink"
        }
    ],
    "sg:phone":"+1 206 728 6204",
    "sg:postcode":"98101",
    "sg:province":"WA",
    "sg:tags":[
        "sushi",
        "bar",
        "japanese"
    ],
    "sg:website":"jpgourmet.com",
    "wof:name":"Japanese Gourmet Restaurant",
    "wof:placetype":"venue"
},
  "geometry": {"coordinates":[-122.341003,47.6101],"type":"Point"}
}