{
  "type": "Feature",
  "properties": {
    "addr:full":"41025 N Grove Rd Deer Park WA 99006",
    "addr:housenumber":"41025",
    "addr:postcode":"99006",
    "addr:street":"N Grove Rd",
    "iso:country":"US",
    "sg:address":"41025 N Grove Rd",
    "sg:city":"Deer Park",
    "sg:classifiers":[
        {
            "category":"Farming",
            "subcategory":"Farm & Veterinary Services",
            "type":"Manufacturing & Wholesale Goods"
        }
    ],
    "sg:phone":"+1 509 276 2282",
    "sg:postcode":"99006",
    "sg:province":"WA",
    "sg:tags":[
        "livestock"
    ],
    "wof:name":"Dara Park Peruvains",
    "wof:placetype":"venue"
},
  "geometry": {"coordinates":[-117.50192699999999,48.027964],"type":"Point"}
}