{
  "type": "Feature",
  "properties": {
    "addr:full":"520 SW 128th St Seattle WA 98146",
    "addr:housenumber":"520",
    "addr:postcode":"98146",
    "addr:street":"Sw 128Th St",
    "iso:country":"US",
    "sg:address":"520 SW 128th St",
    "sg:city":"Seattle",
    "sg:classifiers":[
        {
            "category":"Banks & Credit Unions",
            "subcategory":"Investment Brokerage",
            "type":"Services"
        }
    ],
    "sg:phone":"+1 425 513 9222",
    "sg:postcode":"98146",
    "sg:province":"WA",
    "sg:tags":[
        "security"
    ],
    "wof:name":"Edward Jones 18585",
    "wof:placetype":"venue"
},
  "geometry": {"coordinates":[-122.34075,47.488579],"type":"Point"}
}