{
  "type": "Feature",
  "properties": {
    "addr:full":"1041 S King St Seattle WA 98104",
    "addr:housenumber":"1041",
    "addr:postcode":"98104",
    "addr:street":"S King St",
    "iso:country":"US",
    "sg:address":"1041 S King St",
    "sg:city":"Seattle",
    "sg:classifiers":[
        {
            "category":"Manufacturing",
            "subcategory":"Food",
            "type":"Manufacturing & Wholesale Goods"
        },
        {
            "category":"Food & Beverages",
            "subcategory":"Specialty",
            "type":"Retail Goods"
        },
        {
            "category":"Food & Beverages",
            "subcategory":"Fruits & Vegetables",
            "type":"Retail Goods"
        }
    ],
    "sg:phone":"+1 206 323 2528",
    "sg:postcode":"98104",
    "sg:province":"WA",
    "sg:tags":[
        "product",
        "herb",
        "diet",
        "spices-wholesale",
        "health",
        "spice",
        "manufacturer"
    ],
    "wof:name":"Lucky An Dong Inc",
    "wof:placetype":"venue"
},
  "geometry": {"coordinates":[-122.319153,47.598339],"type":"Point"}
}