{
  "type": "Feature",
  "properties": {
    "addr:full":"12514 SE 7th St Apt 17 Vancouver WA 98683",
    "addr:housenumber":"17",
    "addr:postcode":"12514;98683",
    "addr:street":"Se 7Th St Apt",
    "iso:country":"US",
    "sg:address":"12514 SE 7th St Apt 17",
    "sg:city":"Vancouver",
    "sg:classifiers":[
        {
            "category":"Real Estate",
            "subcategory":"Real Estate Operator",
            "type":"Services"
        }
    ],
    "sg:phone":"+1 360 260 3951",
    "sg:postcode":"98683",
    "sg:province":"WA",
    "sg:tags":[
        "apartment"
    ],
    "wof:name":"Cascadian East Apartment",
    "wof:placetype":"venue"
},
  "geometry": {"coordinates":[-122.543999,45.6161],"type":"Point"}
}