{
  "type": "Feature",
  "properties": {
    "addr:full":"222 E Wapato Way Manson WA 98831",
    "addr:housenumber":"222",
    "addr:postcode":"98831",
    "addr:street":"E Wapato Way",
    "iso:country":"US",
    "sg:address":"222 E Wapato Way",
    "sg:city":"Manson",
    "sg:classifiers":[
        {
            "category":"Manufacturing",
            "subcategory":"Tools & Machinery",
            "type":"Manufacturing & Wholesale Goods"
        }
    ],
    "sg:phone":"+1 509 687 1302",
    "sg:postcode":"98831",
    "sg:province":"WA",
    "sg:tags":[
        "lift",
        "boat"
    ],
    "wof:name":"Reed's Marine",
    "wof:placetype":"venue"
},
  "geometry": {"coordinates":[-120.155866,47.884353],"type":"Point"}
}