{
  "type": "Feature",
  "properties": {
    "addr:full":"600 106th Ave NE Ste 210 Bellevue WA 98004",
    "addr:housenumber":"600",
    "addr:postcode":"98004",
    "addr:street":"106Th Ave Ne Ste 210",
    "iso:country":"US",
    "sg:address":"600 106th Ave NE Ste 210",
    "sg:city":"Bellevue",
    "sg:classifiers":[
        {
            "category":"Professional",
            "subcategory":"Computer Services",
            "type":"Services"
        }
    ],
    "sg:phone":"+1 425 990 8180",
    "sg:postcode":"98004",
    "sg:province":"WA",
    "sg:tags":[
        "design",
        "system",
        "network"
    ],
    "wof:name":"Symatrix Technolgy Inc",
    "wof:placetype":"venue"
},
  "geometry": {"coordinates":[-122.198936,47.615528],"type":"Point"}
}