{
  "type": "Feature",
  "properties": {
    "addr:full":"100 Main St Kittitas WA 98934",
    "addr:housenumber":"100",
    "addr:postcode":"98934",
    "addr:street":"Main St",
    "iso:country":"US",
    "sg:address":"100 Main St",
    "sg:city":"Kittitas",
    "sg:classifiers":[
        {
            "category":"Food & Beverages",
            "subcategory":"Groceries & Convenience Stores",
            "type":"Retail Goods"
        }
    ],
    "sg:phone":"+1 509 968 3318",
    "sg:postcode":"98934",
    "sg:province":"WA",
    "sg:tags":[
        "grocer"
    ],
    "wof:name":"Johnny's Serv-U",
    "wof:placetype":"venue"
},
  "geometry": {"coordinates":[-120.41754,46.984248],"type":"Point"}
}