{
  "type": "Feature",
  "properties": {
    "addr:full":"10619 16th Ave SW Seattle WA 98146",
    "addr:housenumber":"10619",
    "addr:postcode":"98146",
    "addr:street":"16Th Ave Sw",
    "iso:country":"US",
    "sg:address":"10619 16th Ave SW",
    "sg:city":"Seattle",
    "sg:classifiers":[
        {
            "category":"Personal",
            "subcategory":"Beauty Salon",
            "type":"Services"
        }
    ],
    "sg:phone":"+1 206 433 9056",
    "sg:postcode":"98146",
    "sg:province":"WA",
    "wof:name":"Rosies Hair Design",
    "wof:placetype":"venue"
},
  "geometry": {"coordinates":[-122.355182,47.507378],"type":"Point"}
}