{
  "type": "Feature",
  "properties": {
    "addr:full":"413 N Main St Ellensburg WA 98926",
    "addr:housenumber":"413",
    "addr:postcode":"98926",
    "addr:street":"N Main St",
    "iso:country":"US",
    "sg:address":"413 N Main St",
    "sg:city":"Ellensburg",
    "sg:classifiers":[
        {
            "category":"Professional",
            "subcategory":"Lawyer & Legal Services",
            "type":"Services"
        }
    ],
    "sg:phone":"+1 509 925 6434",
    "sg:postcode":"98926",
    "sg:province":"WA",
    "sg:tags":[
        "clinic"
    ],
    "wof:name":"Kittitas County Legal Svc",
    "wof:placetype":"venue"
},
  "geometry": {"coordinates":[-120.548725,46.996379],"type":"Point"}
}