{
  "type": "Feature",
  "properties": {
    "addr:full":"565 Bay St Port Orchard WA 98366",
    "addr:housenumber":"565",
    "addr:postcode":"98366",
    "addr:street":"Bay St",
    "iso:country":"US",
    "sg:address":"565 Bay St",
    "sg:city":"Port Orchard",
    "sg:classifiers":[
        {
            "category":"Insurance",
            "subcategory":"Hazard Insurance",
            "type":"Services"
        }
    ],
    "sg:phone":"+1 360 895 0434",
    "sg:postcode":"98366",
    "sg:province":"WA",
    "sg:tags":[
        "bond"
    ],
    "wof:name":"Casey Bail Co",
    "wof:placetype":"venue"
},
  "geometry": {"coordinates":[-122.63924799999999,47.541609],"type":"Point"}
}