{
  "type": "Feature",
  "properties": {
    "addr:full":"500 NW Market St Seattle WA 98107",
    "addr:housenumber":"500",
    "addr:postcode":"98107",
    "addr:street":"Nw Market St",
    "iso:country":"US",
    "sg:address":"500 NW Market St",
    "sg:city":"Seattle",
    "sg:classifiers":[
        {
            "category":"Building & Trades",
            "subcategory":"Locksmith",
            "type":"Services"
        }
    ],
    "sg:phone":"+1 206 905 6150",
    "sg:postcode":"98107",
    "sg:province":"WA",
    "sg:tags":[
        "key"
    ],
    "wof:name":"Locksmith",
    "wof:placetype":"venue"
},
  "geometry": {"coordinates":[-122.36294599999999,47.668847],"type":"Point"}
}