{
  "type": "Feature",
  "properties": {
    "addr:full":"2640 W Reynolds Ave Centralia WA 98531",
    "addr:housenumber":"2640",
    "addr:postcode":"98531",
    "addr:street":"W Reynolds Ave",
    "iso:country":"US",
    "sg:address":"2640 W Reynolds Ave",
    "sg:city":"Centralia",
    "sg:classifiers":[
        {
            "category":"Organizations",
            "subcategory":"Religious Organization",
            "type":"Services"
        }
    ],
    "sg:phone":"+1 360 736 5898",
    "sg:postcode":"98531",
    "sg:province":"WA",
    "wof:name":"Life Center",
    "wof:placetype":"venue"
},
  "geometry": {"coordinates":[-122.98317,46.735248],"type":"Point"}
}