{
  "type": "Feature",
  "properties": {
    "addr:full":"20241 84th Ave S Kent WA 98032",
    "addr:housenumber":"20241",
    "addr:postcode":"98032",
    "addr:street":"84Th Ave S",
    "iso:country":"US",
    "sg:address":"20241 84th Ave S",
    "sg:city":"Kent",
    "sg:classifiers":[
        {
            "category":"Restaurant",
            "type":"Food & Drink"
        },
        {
            "category":"Coffee & Tea",
            "type":"Food & Drink"
        },
        {
            "category":"Food & Beverages",
            "subcategory":"Liquor & Beverages",
            "type":"Retail Goods"
        }
    ],
    "sg:phone":"+1 253 395 0664",
    "sg:postcode":"98032",
    "sg:province":"WA",
    "sg:tags":[
        "shop",
        "espresso"
    ],
    "wof:name":"Associated Espresso",
    "wof:placetype":"venue"
},
  "geometry": {"coordinates":[-122.22798,47.419947],"type":"Point"}
}