{
  "type": "Feature",
  "properties": {
    "iso:country":"US",
    "sg:address":"1403 N Greene St",
    "sg:city":"Spokane",
    "sg:classifiers":[
        {
            "category":"Manufacturing",
            "subcategory":"Signs",
            "type":"Manufacturing & Wholesale Goods"
        },
        {
            "category":"Professional",
            "subcategory":"Business Services",
            "type":"Services"
        }
    ],
    "sg:phone":"+1 509 536 9452",
    "sg:postcode":"99202",
    "sg:province":"WA",
    "sg:tags":[
        "specialty",
        "painter",
        "mfg"
    ],
    "wof:name":"Metro Quick Signs & Banners",
    "wof:placetype":"venue"
},
  "geometry": {"coordinates":[-117.363781,47.671851],"type":"Point"}
}