{
  "type": "Feature",
  "properties": {
    "iso:country":"US",
    "sg:address":"603 Stewart St",
    "sg:city":"Seattle",
    "sg:classifiers":[
        {
            "category":"Arts & Performance",
            "subcategory":"Theater",
            "type":"Entertainment"
        }
    ],
    "sg:phone":"+1 206 521 9551",
    "sg:postcode":"98101",
    "sg:province":"WA",
    "sg:tags":[
        "group"
    ],
    "wof:name":"C Major Entertainment Marketin",
    "wof:placetype":"venue"
},
  "geometry": {"coordinates":[-122.336111,47.614223],"type":"Point"}
}