{
  "type": "Feature",
  "properties": {
    "addr:full":"4545 Ocean Beach Hwy Longview WA 98632",
    "addr:housenumber":"4545",
    "addr:postcode":"98632",
    "addr:street":"Ocean Beach Hwy",
    "iso:country":"US",
    "sg:address":"4545 Ocean Beach Hwy",
    "sg:city":"Longview",
    "sg:classifiers":[
        {
            "category":"Restaurant",
            "type":"Food & Drink"
        },
        {
            "category":"Retail",
            "subcategory":"Event Space",
            "type":"Services"
        }
    ],
    "sg:phone":"+1 360 425 7970",
    "sg:postcode":"98632",
    "sg:province":"WA",
    "sg:tags":[
        "seafood",
        "banquet",
        "hall",
        "reception",
        "facility"
    ],
    "wof:name":"Henri's Restaurant",
    "wof:placetype":"venue"
},
  "geometry": {"coordinates":[-122.996995,46.162249],"type":"Point"}
}