{
  "type": "Feature",
  "properties": {
    "addr:full":"15118 E Sprague Ave Spokane Valley WA 99037",
    "addr:housenumber":"15118",
    "addr:postcode":"99037",
    "addr:street":"E Sprague Ave",
    "iso:country":"US",
    "sg:address":"15118 E Sprague Ave",
    "sg:city":"Spokane Valley",
    "sg:classifiers":[
        {
            "category":"Retail",
            "subcategory":"Repair Shop",
            "type":"Services"
        }
    ],
    "sg:phone":"+1 509 926 5004",
    "sg:postcode":"99037",
    "sg:province":"WA",
    "sg:tags":[
        "lock",
        "locksmith"
    ],
    "wof:name":"Affordable Lock Express",
    "wof:placetype":"venue"
},
  "geometry": {"coordinates":[-117.196758,47.656951],"type":"Point"}
}