{
  "type": "Feature",
  "properties": {
    "addr:full":"800 C St Vancouver WA 98660",
    "addr:housenumber":"800",
    "addr:postcode":"98660",
    "addr:street":"C St",
    "iso:country":"US",
    "sg:address":"800 C St",
    "sg:city":"Vancouver",
    "sg:classifiers":[
        {
            "category":"Professional",
            "subcategory":"Accounting & Tax Preparation",
            "type":"Services"
        }
    ],
    "sg:phone":"+1 360 690 4535",
    "sg:postcode":"98660",
    "sg:province":"WA",
    "sg:tags":[
        "accountant"
    ],
    "wof:name":"Phillips Craig J CPA",
    "wof:placetype":"venue"
},
  "geometry": {"coordinates":[-122.66947999999999,45.627182],"type":"Point"}
}