{
  "type": "Feature",
  "properties": {
    "addr:full":"4520 200th St SW Lynnwood WA 98036",
    "addr:housenumber":"4520",
    "addr:postcode":"98036",
    "addr:street":"200Th St Sw",
    "iso:country":"US",
    "sg:address":"4520 200th St SW",
    "sg:city":"Lynnwood",
    "sg:classifiers":[
        {
            "category":"Restaurant",
            "type":"Food & Drink"
        }
    ],
    "sg:menulink":"http://www.allmenus.com/wa/edmonds/46477-kalia-indian-cuisine/menu/",
    "sg:phone":"+1 425 771 6422",
    "sg:postcode":"98036",
    "sg:province":"WA",
    "sg:tags":[
        "indian",
        "asian"
    ],
    "wof:name":"Kalia Indian Cuisine",
    "wof:placetype":"venue"
},
  "geometry": {"coordinates":[-122.294023,47.817018],"type":"Point"}
}