{
  "type": "Feature",
  "properties": {
    "addr:full":"3027 Broadway Everett WA 98201",
    "addr:housenumber":"3027",
    "addr:postcode":"98201",
    "addr:street":"Broadway",
    "iso:country":"US",
    "sg:address":"3027 Broadway",
    "sg:city":"Everett",
    "sg:classifiers":[
        {
            "category":"Professional",
            "subcategory":"Business Services",
            "type":"Services"
        }
    ],
    "sg:phone":"+1 310 694 5100",
    "sg:postcode":"98201",
    "sg:province":"WA",
    "sg:tags":[
        "holding"
    ],
    "wof:name":"Suncor Holdings",
    "wof:placetype":"venue"
},
  "geometry": {"coordinates":[-122.201522,47.977647],"type":"Point"}
}