{
  "type": "Feature",
  "properties": {
    "addr:full":"9757 NE Juanita Dr Kirkland WA 98034",
    "addr:housenumber":"9757",
    "addr:postcode":"98034",
    "addr:street":"Ne Juanita Dr",
    "iso:country":"US",
    "sg:address":"9757 NE Juanita Dr",
    "sg:city":"Kirkland",
    "sg:classifiers":[
        {
            "category":"Professional",
            "subcategory":"Computer Services",
            "type":"Services"
        },
        {
            "category":"Shopping",
            "subcategory":"Computers & Home Electronics",
            "type":"Retail Goods"
        }
    ],
    "sg:phone":"+1 425 820 0828",
    "sg:postcode":"98034",
    "sg:province":"WA",
    "sg:tags":[
        "prepackaged",
        "software"
    ],
    "wof:name":"HMS Software Inc",
    "wof:placetype":"venue"
},
  "geometry": {"coordinates":[-122.215452,47.705306],"type":"Point"}
}