{
  "type": "Feature",
  "properties": {
    "addr:full":"1313 S Mica Park Dr Spokane WA 99206",
    "addr:housenumber":"1313",
    "addr:postcode":"99206",
    "addr:street":"S Mica Park Dr",
    "iso:country":"US",
    "sg:address":"1313 S Mica Park Dr",
    "sg:city":"Spokane",
    "sg:classifiers":[
        {
            "category":"Professional",
            "subcategory":"Business Services",
            "type":"Services"
        }
    ],
    "sg:phone":"+1 509 926 7348",
    "sg:postcode":"99206",
    "sg:province":"WA",
    "wof:name":"Nostrafides Interpreter Svc",
    "wof:placetype":"venue"
},
  "geometry": {"coordinates":[-117.276878,47.645773],"type":"Point"}
}