{
  "type": "Feature",
  "properties": {
    "addr:full":"600 4th Ave Fl 6 Seattle WA 98104",
    "addr:housenumber":"600;6",
    "addr:postcode":"98104",
    "addr:street":"4Th Ave Fl",
    "iso:country":"US",
    "sg:address":"600 4th Ave Fl 6",
    "sg:city":"Seattle",
    "sg:classifiers":[
        {
            "category":"Government",
            "subcategory":"Office",
            "type":"Public Place"
        }
    ],
    "sg:phone":"+1 206 684 8041",
    "sg:postcode":"98104",
    "sg:province":"WA",
    "sg:tags":[
        "parish",
        "government-county"
    ],
    "sg:website":"http://www.seattlemonorail.com",
    "wof:name":"Policy & Management",
    "wof:placetype":"venue"
},
  "geometry": {"coordinates":[-122.33026099999999,47.60323],"type":"Point"}
}