{
  "type": "Feature",
  "properties": {
    "addr:full":"9310 E Montgomery Ave Spokane WA 99206",
    "addr:housenumber":"9310",
    "addr:postcode":"99206",
    "addr:street":"E Montgomery Ave",
    "iso:country":"US",
    "sg:address":"9310 E Montgomery Ave",
    "sg:city":"Spokane",
    "sg:classifiers":[
        {
            "category":"Home & Garden",
            "subcategory":"Carpets & Floor Coverings",
            "type":"Retail Goods"
        }
    ],
    "sg:phone":"+1 509 626 9532",
    "sg:postcode":"99206",
    "sg:province":"WA",
    "wof:name":"Guys Tough Carpet & Floo",
    "wof:placetype":"venue"
},
  "geometry": {"coordinates":[-117.277383,47.678676],"type":"Point"}
}