{
  "type": "Feature",
  "properties": {
    "addr:full":"2092 Van Dyk Rd Everson WA 98247",
    "addr:housenumber":"2092",
    "addr:postcode":"98247",
    "addr:street":"Van Dyk Rd",
    "iso:country":"US",
    "sg:address":"2092 Van Dyk Rd",
    "sg:city":"Everson",
    "sg:classifiers":[
        {
            "category":"Farming",
            "subcategory":"Orchard",
            "type":"Manufacturing & Wholesale Goods"
        }
    ],
    "sg:phone":"+1 360 966 3919",
    "sg:postcode":"98247",
    "sg:province":"WA",
    "sg:tags":[
        "farm",
        "fruit",
        "tree"
    ],
    "wof:name":"Stoney Ridge Farm",
    "wof:placetype":"venue"
},
  "geometry": {"coordinates":[-122.37669200000001,48.906116],"type":"Point"}
}