{
  "type": "Feature",
  "properties": {
    "addr:full":"1200 6th Ave Seattle WA 98101",
    "addr:housenumber":"1200",
    "addr:postcode":"98101",
    "addr:street":"6Th Ave",
    "iso:country":"US",
    "sg:address":"1200 6th Ave",
    "sg:city":"Seattle",
    "sg:classifiers":[
        {
            "category":"Professional",
            "subcategory":"Advertising",
            "type":"Services"
        }
    ],
    "sg:phone":"+1 206 382 5523",
    "sg:postcode":"98101",
    "sg:province":"WA",
    "sg:tags":[
        "mailing",
        "shipping"
    ],
    "wof:name":"Fed Ex Kinko's Ofc & Print Ctr",
    "wof:placetype":"venue"
},
  "geometry": {"coordinates":[-122.33264200000001,47.609158],"type":"Point"}
}