{
  "type": "Feature",
  "properties": {
    "addr:full":"3842 N Deer Lake Rd Loon Lake WA 99148",
    "addr:housenumber":"3842",
    "addr:postcode":"99148",
    "addr:street":"N Deer Lake Rd",
    "iso:country":"US",
    "sg:address":"3842 N Deer Lake Rd",
    "sg:city":"Loon Lake",
    "sg:classifiers":[
        {
            "category":"Shopping",
            "subcategory":"Computers & Home Electronics",
            "type":"Retail Goods"
        }
    ],
    "sg:phone":"+1 509 233 9321",
    "sg:postcode":"99148",
    "sg:province":"WA",
    "wof:name":"Lantz Enterprises",
    "wof:placetype":"venue"
},
  "geometry": {"coordinates":[-117.60320299999999,48.111627],"type":"Point"}
}