{
  "type": "Feature",
  "properties": {
    "addr:full":"400 Highland Dr Okanogan WA 98840",
    "addr:housenumber":"400",
    "addr:postcode":"98840",
    "addr:street":"Highland Dr Okanogan",
    "iso:country":"US",
    "sg:address":"400 Highland Dr",
    "sg:city":"Okanogan",
    "sg:classifiers":[
        {
            "category":"Shopping",
            "subcategory":"Used Merchandise",
            "type":"Retail Goods"
        }
    ],
    "sg:phone":"+1 509 422 0443",
    "sg:postcode":"98840",
    "sg:province":"WA",
    "wof:name":"Holly Hock Antq & Collectables",
    "wof:placetype":"venue"
},
  "geometry": {"coordinates":[-119.580962,48.369595],"type":"Point"}
}