{
  "type": "Feature",
  "properties": {
    "addr:full":"14524 Main St NE Suite 203 Duvall WA 98019",
    "addr:housenumber":"14524",
    "addr:postcode":"98019",
    "addr:street":"Main St Ne Suite 203",
    "iso:country":"US",
    "sg:address":"14524 Main St NE Suite 203",
    "sg:city":"Duvall",
    "sg:classifiers":[
        {
            "category":"Banks & Credit Unions",
            "subcategory":"Investment Brokerage",
            "type":"Services"
        },
        {
            "category":"Banks & Credit Unions",
            "subcategory":"Bank",
            "type":"Services"
        },
        {
            "category":"Banks & Credit Unions",
            "subcategory":"Financial Services",
            "type":"Services"
        }
    ],
    "sg:phone":"+1 425 844 9769",
    "sg:postcode":"98019",
    "sg:province":"WA",
    "sg:tags":[
        "mutual",
        "retirement",
        "broker",
        "fund",
        "planning",
        "security",
        "bond",
        "stock"
    ],
    "sg:website":"http://www.edwardjones.com/en_US/fa/index.html&CIRN=410948",
    "wof:name":"Edward Jones - Financial Advisor: DANNY L EDWARDS",
    "wof:placetype":"venue"
},
  "geometry": {"coordinates":[-121.987436,47.732568],"type":"Point"}
}