{
  "type": "Feature",
  "properties": {
    "iso:country":"US",
    "sg:address":"1688 10th St W",
    "sg:city":"Kirkland",
    "sg:classifiers":[
        {
            "category":"Professional",
            "type":"Services"
        }
    ],
    "sg:phone":"+1 425 830 6630",
    "sg:postcode":"98033",
    "sg:province":"WA",
    "wof:name":"Contract Corporate Crews",
    "wof:placetype":"venue"
},
  "geometry": {"coordinates":[-122.21574699999999,47.693904],"type":"Point"}
}