{
  "type": "Feature",
  "properties": {
    "addr:full":"15914 State Hwy 305 Poulsbo WA 98370",
    "addr:housenumber":"15914",
    "addr:postcode":"98370",
    "addr:street":"State Hwy 305",
    "iso:country":"US",
    "sg:address":"15914 State Hwy 305",
    "sg:city":"Poulsbo",
    "sg:classifiers":[
        {
            "category":"Food & Beverages",
            "subcategory":"Groceries & Convenience Stores",
            "type":"Retail Goods"
        }
    ],
    "sg:phone":"+1 360 598 3333",
    "sg:postcode":"98370",
    "sg:province":"WA",
    "wof:name":"Evergreen Mini Mart",
    "wof:placetype":"venue"
},
  "geometry": {"coordinates":[-122.578205,47.711384],"type":"Point"}
}