{
  "type": "Feature",
  "properties": {
    "addr:full":"3701 S Norfolk St Seattle WA 98118",
    "addr:housenumber":"3701",
    "addr:postcode":"98118",
    "addr:street":"S Norfolk St",
    "iso:country":"US",
    "sg:address":"3701 S Norfolk St",
    "sg:city":"Seattle",
    "sg:classifiers":[
        {
            "category":"Home & Garden",
            "subcategory":"Furniture",
            "type":"Retail Goods"
        }
    ],
    "sg:phone":"+1 206 760 0252",
    "sg:postcode":"98118",
    "sg:province":"WA",
    "wof:name":"Masins Furniture",
    "wof:placetype":"venue"
},
  "geometry": {"coordinates":[-122.28423100000001,47.513413],"type":"Point"}
}