{
  "type": "Feature",
  "properties": {
    "addr:full":"8003 5th Avenue NE Seattle WA 98115",
    "addr:housenumber":"8003",
    "addr:postcode":"98115",
    "addr:street":"5Th Avenue Ne",
    "iso:country":"US",
    "sg:address":"8003 5th Avenue NE",
    "sg:city":"Seattle",
    "sg:classifiers":[
        {
            "category":"Professional",
            "subcategory":"Art Services",
            "type":"Services"
        },
        {
            "category":"Communications",
            "type":"Services"
        }
    ],
    "sg:phone":"+1 206 633 3883",
    "sg:postcode":"98115",
    "sg:province":"WA",
    "sg:tags":[
        "web",
        "graphic",
        "design"
    ],
    "sg:website":"www.martinidesign.com",
    "wof:name":"Martini Design :: An Integrated Marketing Agency",
    "wof:placetype":"venue"
},
  "geometry": {"coordinates":[-122.323233,47.686943],"type":"Point"}
}