{
  "type": "Feature",
  "properties": {
    "addr:full":"18836 102nd Ave SE Renton WA 98055",
    "addr:housenumber":"18836",
    "addr:postcode":"98055",
    "addr:street":"102Nd Ave Se",
    "iso:country":"US",
    "sg:address":"18836 102nd Ave SE",
    "sg:city":"Renton",
    "sg:classifiers":[
        {
            "category":"Building & Trades",
            "subcategory":"Construction",
            "type":"Services"
        }
    ],
    "sg:phone":"+1 425 243 7512",
    "sg:postcode":"98055",
    "sg:province":"WA",
    "sg:tags":[
        "residential"
    ],
    "wof:name":"Jordan S Western Woodcraft",
    "wof:placetype":"venue"
},
  "geometry": {"coordinates":[-122.20493500000001,47.431923],"type":"Point"}
}