{
  "type": "Feature",
  "properties": {
    "addr:full":"354 W Cedar St Sequim WA 98382",
    "addr:housenumber":"354",
    "addr:postcode":"98382",
    "addr:street":"W Cedar St",
    "iso:country":"US",
    "sg:address":"354 W Cedar St",
    "sg:city":"Sequim",
    "sg:classifiers":[
        {
            "category":"Social Services",
            "subcategory":"Child Care",
            "type":"Services"
        }
    ],
    "sg:phone":"+1 360 681 7126",
    "sg:postcode":"98382",
    "sg:province":"WA",
    "sg:tags":[
        "kindergarten",
        "academic",
        "school"
    ],
    "wof:name":"Faith Lutheran Preschool",
    "wof:placetype":"venue"
},
  "geometry": {"coordinates":[-123.10926000000001,48.080647],"type":"Point"}
}