{
  "type": "Feature",
  "properties": {
    "addr:full":"11924 SE 217th St Kent WA 98031",
    "addr:housenumber":"11924",
    "addr:postcode":"98031",
    "addr:street":"Se 217Th St",
    "iso:country":"US",
    "sg:address":"11924 SE 217th St",
    "sg:city":"Kent",
    "sg:classifiers":[
        {
            "category":"Professional",
            "subcategory":"Computer Services",
            "type":"Services"
        }
    ],
    "sg:phone":"+1 253 630 1896",
    "sg:postcode":"98031",
    "sg:province":"WA",
    "wof:name":"Computer Repair Zone",
    "wof:placetype":"venue"
},
  "geometry": {"coordinates":[-122.181738,47.407769],"type":"Point"}
}