{
  "type": "Feature",
  "properties": {
    "addr:full":"1802 S 3rd Ave Yakima WA 98902",
    "addr:housenumber":"1802",
    "addr:postcode":"98902",
    "addr:street":"S 3Rd Ave",
    "iso:country":"US",
    "sg:address":"1802 S 3rd Ave",
    "sg:city":"Yakima",
    "sg:classifiers":[
        {
            "category":"Shopping",
            "type":"Retail Goods"
        }
    ],
    "sg:phone":"+1 509 249 2825",
    "sg:postcode":"98902",
    "sg:province":"WA",
    "sg:tags":[
        "merchandise"
    ],
    "wof:name":"Angels Outer Shop",
    "wof:placetype":"venue"
},
  "geometry": {"coordinates":[-120.509502,46.570727],"type":"Point"}
}