{
  "type": "Feature",
  "properties": {
    "addr:full":"511 W 10th Ave Ellensburg WA 98926",
    "addr:housenumber":"511",
    "addr:postcode":"98926",
    "addr:street":"W 10Th Ave",
    "iso:country":"US",
    "sg:address":"511 W 10th Ave",
    "sg:city":"Ellensburg",
    "sg:classifiers":[
        {
            "category":"Education",
            "subcategory":"Special Training",
            "type":"Public Place"
        }
    ],
    "sg:phone":"+1 509 925 3457",
    "sg:postcode":"98926",
    "sg:province":"WA",
    "wof:name":"Acoustic/Electric Guitar Lesso",
    "wof:placetype":"venue"
},
  "geometry": {"coordinates":[-120.55427299999999,47.001649],"type":"Point"}
}