{
  "type": "Feature",
  "properties": {
    "addr:full":"228 Albatross St NE Ocean Shores WA 98569",
    "addr:housenumber":"228",
    "addr:postcode":"98569",
    "addr:street":"Albatross St Ne",
    "iso:country":"US",
    "sg:address":"228 Albatross St NE",
    "sg:city":"Ocean Shores",
    "sg:classifiers":[
        {
            "category":"Organizations",
            "subcategory":"Religious Organization",
            "type":"Services"
        }
    ],
    "sg:phone":"+1 360 289 2037",
    "sg:postcode":"98569",
    "sg:province":"WA",
    "sg:tags":[
        "church"
    ],
    "wof:name":"Church Of Jesus Christ Of Lds",
    "wof:placetype":"venue"
},
  "geometry": {"coordinates":[-124.15301100000001,46.998104],"type":"Point"}
}