{
  "type": "Feature",
  "properties": {
    "addr:full":"32000 Pacific Hwy S Federal Way WA 98003",
    "addr:housenumber":"32000",
    "addr:postcode":"98003",
    "addr:street":"Pacific Hwy S Federal Way",
    "iso:country":"US",
    "sg:address":"32000 Pacific Hwy S",
    "sg:city":"Federal Way",
    "sg:classifiers":[
        {
            "category":"Banks & Credit Unions",
            "subcategory":"Investment Brokerage",
            "type":"Services"
        }
    ],
    "sg:phone":"+1 253 927 7272",
    "sg:postcode":"98003",
    "sg:province":"WA",
    "wof:name":"Wm Fund Services Inc",
    "wof:placetype":"venue"
},
  "geometry": {"coordinates":[-122.31339199999999,47.314335],"type":"Point"}
}