{
  "type": "Feature",
  "properties": {
    "addr:full":"5711 W Payette Ave Kennewick WA 99336",
    "addr:housenumber":"5711",
    "addr:postcode":"99336",
    "addr:street":"W Payette Ave",
    "iso:country":"US",
    "sg:address":"5711 W Payette Ave",
    "sg:city":"Kennewick",
    "sg:classifiers":[
        {
            "category":"Professional",
            "subcategory":"Secretarial Services",
            "type":"Services"
        }
    ],
    "sg:phone":"+1 509 783 3727",
    "sg:postcode":"99336",
    "sg:province":"WA",
    "sg:tags":[
        "reporting"
    ],
    "wof:name":"Price Seminars",
    "wof:placetype":"venue"
},
  "geometry": {"coordinates":[-119.19891800000001,46.22179],"type":"Point"}
}