{
  "type": "Feature",
  "properties": {
    "addr:full":"8833 Pacific Ave S Tacoma WA 98444",
    "addr:housenumber":"8833",
    "addr:postcode":"98444",
    "addr:street":"Pacific Ave S",
    "iso:country":"US",
    "sg:address":"8833 Pacific Ave S",
    "sg:city":"Tacoma",
    "sg:classifiers":[
        {
            "category":"Organizations",
            "subcategory":"Non-profit Organization",
            "type":"Services"
        }
    ],
    "sg:phone":"+1 253 536 2881",
    "sg:postcode":"98444",
    "sg:province":"WA",
    "sg:tags":[
        "info",
        "addiction",
        "abuse",
        "treatment",
        "drug"
    ],
    "wof:name":"Casteele Williams & Assoc",
    "wof:placetype":"venue"
},
  "geometry": {"coordinates":[-122.434006,47.17614],"type":"Point"}
}