{
  "type": "Feature",
  "properties": {
    "addr:full":"220 SW Main St Washtucna WA 99371",
    "addr:housenumber":"220",
    "addr:postcode":"99371",
    "addr:street":"Sw Main St",
    "iso:country":"US",
    "sg:address":"220 SW Main St",
    "sg:city":"Washtucna",
    "sg:classifiers":[
        {
            "category":"Government",
            "subcategory":"Post Office",
            "type":"Public Place"
        }
    ],
    "sg:phone":"+1 509 646 3376",
    "sg:postcode":"99371",
    "sg:province":"WA",
    "sg:website":"http://www.usps.gov",
    "wof:name":"Us Post Office",
    "wof:placetype":"venue"
},
  "geometry": {"coordinates":[-118.314977,46.751749],"type":"Point"}
}