{
  "type": "Feature",
  "properties": {
    "addr:full":"2003 9th Ave Milton WA 98354",
    "addr:housenumber":"2003",
    "addr:postcode":"98354",
    "addr:street":"9Th Ave",
    "iso:country":"US",
    "sg:address":"2003 9th Ave",
    "sg:city":"Milton",
    "sg:classifiers":[
        {
            "category":"Professional",
            "type":"Services"
        }
    ],
    "sg:phone":"+1 253 922 7561",
    "sg:postcode":"98354",
    "sg:province":"WA",
    "wof:name":"James Stanley Jack",
    "wof:placetype":"venue"
},
  "geometry": {"coordinates":[-122.32294899999999,47.241601],"type":"Point"}
}