{
  "type": "Feature",
  "properties": {
    "addr:full":"615 2nd Ave Seattle WA 98104",
    "addr:housenumber":"615",
    "addr:postcode":"98104",
    "addr:street":"2Nd Ave",
    "iso:country":"US",
    "sg:address":"615 2nd Ave",
    "sg:city":"Seattle",
    "sg:classifiers":[
        {
            "category":"Professional",
            "subcategory":"Computer Services",
            "type":"Services"
        }
    ],
    "sg:phone":"+1 206 623 1965",
    "sg:postcode":"98104",
    "sg:province":"WA",
    "sg:tags":[
        "web",
        "design",
        "site",
        "software"
    ],
    "wof:name":"Vmware, Inc.",
    "wof:placetype":"venue"
},
  "geometry": {"coordinates":[-122.332697,47.602378],"type":"Point"}
}