{
  "type": "Feature",
  "properties": {
    "addr:full":"9960 Silverdale Way NW Silverdale WA 98383",
    "addr:housenumber":"9960",
    "addr:postcode":"98383",
    "addr:street":"Silverdale Way Nw",
    "iso:country":"US",
    "sg:address":"9960 Silverdale Way NW",
    "sg:city":"Silverdale",
    "sg:classifiers":[
        {
            "category":"Shopping",
            "subcategory":"Gifts & Souvenirs",
            "type":"Retail Goods"
        }
    ],
    "sg:phone":"+1 360 373 3594",
    "sg:postcode":"98383",
    "sg:province":"WA",
    "sg:tags":[
        "collectible"
    ],
    "wof:name":"D K Enterprises",
    "wof:placetype":"venue"
},
  "geometry": {"coordinates":[-122.691534,47.65208],"type":"Point"}
}