{
  "type": "Feature",
  "properties": {
    "addr:full":"10235 Tilley Rd S Olympia WA 98512",
    "addr:housenumber":"10235",
    "addr:postcode":"98512",
    "addr:street":"Tilley Rd",
    "iso:country":"US",
    "sg:address":"10235 Tilley Rd S",
    "sg:city":"Olympia",
    "sg:classifiers":[
        {
            "category":"Building & Trades",
            "subcategory":"Landscaping Services",
            "type":"Services"
        }
    ],
    "sg:phone":"+1 360 352 9405",
    "sg:postcode":"98512",
    "sg:province":"WA",
    "wof:name":"Duffers Landscaping",
    "wof:placetype":"venue"
},
  "geometry": {"coordinates":[-122.909812,46.896295],"type":"Point"}
}