{
  "type": "Feature",
  "properties": {
    "iso:country":"US",
    "sg:address":"25927 NW Vuemor Ct",
    "sg:city":"Poulsbo",
    "sg:classifiers":[
        {
            "category":"Professional",
            "subcategory":"Computer Services",
            "type":"Services"
        }
    ],
    "sg:phone":"+1 360 779 7098",
    "sg:postcode":"98370",
    "sg:province":"WA",
    "sg:tags":[
        "related"
    ],
    "wof:name":"Erics Creative Computing",
    "wof:placetype":"venue"
},
  "geometry": {"coordinates":[-122.663618,47.79954],"type":"Point"}
}