{
  "type": "Feature",
  "properties": {
    "iso:country":"US",
    "sg:address":"5907 18th Ave S",
    "sg:city":"Seattle",
    "sg:classifiers":[
        {
            "category":"Building & Trades",
            "subcategory":"Construction",
            "type":"Services"
        }
    ],
    "sg:phone":"+1 206 763 8002",
    "sg:postcode":"98108",
    "sg:province":"WA",
    "sg:tags":[
        "house"
    ],
    "wof:name":"Ming Fat Construction",
    "wof:placetype":"venue"
},
  "geometry": {"coordinates":[-122.309991,47.548839],"type":"Point"}
}