{
  "type": "Feature",
  "properties": {
    "addr:full":"610 Second Ave Seattle WA 98104",
    "addr:housenumber":"610",
    "addr:postcode":"98104",
    "addr:street":"Second Ave",
    "iso:country":"US",
    "sg:address":"610 Second Ave",
    "sg:city":"Seattle",
    "sg:classifiers":[
        {
            "category":"Shopping",
            "subcategory":"Gifts & Souvenirs",
            "type":"Retail Goods"
        }
    ],
    "sg:phone":"+1 206 624 9338",
    "sg:postcode":"98104",
    "sg:province":"WA",
    "sg:tags":[
        "flower"
    ],
    "wof:name":"Green Garden Cards & Gifts",
    "wof:placetype":"venue"
},
  "geometry": {"coordinates":[-122.333,47.602501],"type":"Point"}
}