{
  "type": "Feature",
  "properties": {
    "iso:country":"US",
    "sg:address":"1317 54th Ave E",
    "sg:city":"Fife",
    "sg:classifiers":[
        {
            "category":"Building & Trades",
            "subcategory":"Construction",
            "type":"Services"
        },
        {
            "category":"Mining & Drilling",
            "type":"Manufacturing & Wholesale Goods"
        }
    ],
    "sg:phone":"+1 253 922 6815",
    "sg:postcode":"98424",
    "sg:province":"WA",
    "sg:tags":[
        "station",
        "gas",
        "producer",
        "oil",
        "contractor"
    ],
    "sg:website":"www.joehall.com",
    "wof:name":"Joe Hall Construction Inc",
    "wof:placetype":"venue"
},
  "geometry": {"coordinates":[-122.356876,47.244167],"type":"Point"}
}