{
  "type": "Feature",
  "properties": {
    "addr:full":"419 NE Cedar St Camas WA 98607",
    "addr:housenumber":"419",
    "addr:postcode":"98607",
    "addr:street":"Ne Cedar St",
    "iso:country":"US",
    "sg:address":"419 NE Cedar St",
    "sg:city":"Camas",
    "sg:classifiers":[
        {
            "category":"Restaurant",
            "type":"Food & Drink"
        }
    ],
    "sg:phone":"+1 360 834 5393",
    "sg:postcode":"98607",
    "sg:province":"WA",
    "sg:tags":[
        "style",
        "chinese",
        "family",
        "asian",
        "pan"
    ],
    "wof:name":"Happy Island Restaurant",
    "wof:placetype":"venue"
},
  "geometry": {"coordinates":[-122.404358,45.585866],"type":"Point"}
}