{
  "type": "Feature",
  "properties": {
    "addr:full":"6523 5th Ave NE Seattle WA 98115",
    "addr:housenumber":"6523",
    "addr:postcode":"98115",
    "addr:street":"5Th Ave Ne",
    "iso:country":"US",
    "sg:address":"6523 5th Ave NE",
    "sg:city":"Seattle",
    "sg:classifiers":[
        {
            "category":"Professional",
            "subcategory":"Art Services",
            "type":"Services"
        }
    ],
    "sg:phone":"+1 206 729 2471",
    "sg:postcode":"98115",
    "sg:province":"WA",
    "sg:tags":[
        "commercial",
        "consulting",
        "management",
        "design"
    ],
    "wof:name":"Moulton Creative",
    "wof:placetype":"venue"
},
  "geometry": {"coordinates":[-122.325097,47.677733],"type":"Point"}
}