{
  "type": "Feature",
  "properties": {
    "addr:full":"147 Carswell Dr Moses Lake WA 98837",
    "addr:housenumber":"147",
    "addr:postcode":"98837",
    "addr:street":"Carswell Dr",
    "iso:country":"US",
    "sg:address":"147 Carswell Dr",
    "sg:city":"Moses Lake",
    "sg:classifiers":[
        {
            "category":"Retail",
            "subcategory":"Laundry & Dry Cleaning",
            "type":"Services"
        }
    ],
    "sg:phone":"+1 509 762 5061",
    "sg:postcode":"98837",
    "sg:province":"WA",
    "sg:tags":[
        "cleaners",
        "rug",
        "carpet"
    ],
    "wof:name":"First Choice Carpet Cleaning",
    "wof:placetype":"venue"
},
  "geometry": {"coordinates":[-119.324592,47.164333],"type":"Point"}
}