{
  "type": "Feature",
  "properties": {
    "addr:full":"34503 SE Osprey Ct Snoqualmie WA 98065",
    "addr:housenumber":"34503",
    "addr:postcode":"98065",
    "addr:street":"Se Osprey Ct",
    "iso:country":"US",
    "sg:address":"34503 SE Osprey Ct",
    "sg:city":"Snoqualmie",
    "sg:classifiers":[
        {
            "category":"Real Estate",
            "subcategory":"Real Estate Services",
            "type":"Services"
        },
        {
            "category":"Real Estate",
            "subcategory":"Real Estate Agent",
            "type":"Services"
        }
    ],
    "sg:phone":"+1 425 281 8860",
    "sg:postcode":"98065",
    "sg:province":"WA",
    "sg:tags":[
        "buyer",
        "broker"
    ],
    "wof:name":"The Force Realty",
    "wof:placetype":"venue"
},
  "geometry": {"coordinates":[-121.880021,47.528418],"type":"Point"}
}