{
  "type": "Feature",
  "properties": {
    "addr:full":"920 Pine St Lynden WA 98264",
    "addr:housenumber":"920",
    "addr:postcode":"98264",
    "addr:street":"Pine St",
    "iso:country":"US",
    "sg:address":"920 Pine St",
    "sg:city":"Lynden",
    "sg:classifiers":[
        {
            "category":"Professional",
            "subcategory":"Art Services",
            "type":"Services"
        }
    ],
    "sg:phone":"+1 360 354 4777",
    "sg:postcode":"98264",
    "sg:province":"WA",
    "sg:tags":[
        "commercial",
        "design"
    ],
    "wof:name":"Bh Design",
    "wof:placetype":"venue"
},
  "geometry": {"coordinates":[-122.463216,48.947668],"type":"Point"}
}