{
  "type": "Feature",
  "properties": {
    "addr:full":"2324 1st Ave Seattle WA 98121",
    "addr:housenumber":"2324",
    "addr:postcode":"98121",
    "addr:street":"1St Ave",
    "iso:country":"US",
    "sg:address":"2324 1st Ave",
    "sg:city":"Seattle",
    "sg:classifiers":[
        {
            "category":"Real Estate",
            "subcategory":"Architect",
            "type":"Services"
        }
    ],
    "sg:phone":"+1 206 441 2989",
    "sg:postcode":"98121",
    "sg:province":"WA",
    "sg:tags":[
        "architectural"
    ],
    "wof:name":"Snell Partnership",
    "wof:placetype":"venue"
},
  "geometry": {"coordinates":[-122.34725400000001,47.61378],"type":"Point"}
}