{
  "type": "Feature",
  "properties": {
    "addr:full":"17030 106th Ave SE Renton WA 98055",
    "addr:housenumber":"17030",
    "addr:postcode":"98055",
    "addr:street":"106Th Ave Se",
    "iso:country":"US",
    "sg:address":"17030 106th Ave SE",
    "sg:city":"Renton",
    "sg:classifiers":[
        {
            "category":"Building & Trades",
            "subcategory":"Construction",
            "type":"Services"
        }
    ],
    "sg:phone":"+1 425 917 1852",
    "sg:postcode":"98055",
    "sg:province":"WA",
    "sg:tags":[
        "carpentry",
        "contractor"
    ],
    "wof:name":"Sound Carpentry",
    "wof:placetype":"venue"
},
  "geometry": {"coordinates":[-122.199421,47.452382],"type":"Point"}
}