{
  "type": "Feature",
  "properties": {
    "addr:full":"23226 Kingsbury Rd SW Vashon WA 98070",
    "addr:housenumber":"23226",
    "addr:postcode":"98070",
    "addr:street":"Kingsbury Rd Sw",
    "iso:country":"US",
    "sg:address":"23226 Kingsbury Rd SW",
    "sg:city":"Vashon",
    "sg:classifiers":[
        {
            "category":"Professional",
            "type":"Services"
        }
    ],
    "sg:phone":"+1 206 463 1631",
    "sg:postcode":"98070",
    "sg:province":"WA",
    "wof:name":"Richard Kremer",
    "wof:placetype":"venue"
},
  "geometry": {"coordinates":[-122.436795,47.396568],"type":"Point"}
}