{
  "type": "Feature",
  "properties": {
    "addr:full":"3253 62nd Ave SW Seattle WA 98116",
    "addr:housenumber":"3253",
    "addr:postcode":"98116",
    "addr:street":"62Nd Ave Sw",
    "iso:country":"US",
    "sg:address":"3253 62nd Ave SW",
    "sg:city":"Seattle",
    "sg:classifiers":[
        {
            "category":"Retail",
            "subcategory":"Repair Shop",
            "type":"Services"
        }
    ],
    "sg:phone":"+1 206 525 2009",
    "sg:postcode":"98116",
    "sg:province":"WA",
    "wof:name":"British Tradition Upholstery",
    "wof:placetype":"venue"
},
  "geometry": {"coordinates":[-122.412166,47.574593],"type":"Point"}
}