{
  "type": "Feature",
  "properties": {
    "addr:full":"19611 Alderwood Mall Pkwy Lynnwood WA 98036",
    "addr:housenumber":"19611",
    "addr:postcode":"98036",
    "addr:street":"Alderwood Mall Pkwy",
    "iso:country":"US",
    "sg:address":"19611 Alderwood Mall Pkwy",
    "sg:city":"Lynnwood",
    "sg:classifiers":[
        {
            "category":"Retail",
            "subcategory":"Car Wash",
            "type":"Services"
        },
        {
            "category":"Autos & Motor Vehicles",
            "subcategory":"Fuel & Gas Station",
            "type":"Retail Goods"
        }
    ],
    "sg:phone":"+1 425 774 8200",
    "sg:postcode":"98036",
    "sg:province":"WA",
    "sg:tags":[
        "grocery",
        "washing",
        "gasoline",
        "polishing",
        "station",
        "carwash"
    ],
    "wof:name":"76 Mr Kleen Car Wash",
    "wof:placetype":"venue"
},
  "geometry": {"coordinates":[-122.271004,47.820563],"type":"Point"}
}