{
  "type": "Feature",
  "properties": {
    "addr:full":"14730 NE 8th St Bellevue WA 98007",
    "addr:housenumber":"14730",
    "addr:postcode":"98007",
    "addr:street":"Ne 8Th St",
    "iso:country":"US",
    "sg:address":"14730 NE 8th St",
    "sg:city":"Bellevue",
    "sg:classifiers":[
        {
            "category":"Health Services",
            "subcategory":"Chiropractor",
            "type":"Services"
        }
    ],
    "sg:phone":"+1 425 373 4673",
    "sg:postcode":"98007",
    "sg:province":"WA",
    "wof:name":"Scott John Dr",
    "wof:placetype":"venue"
},
  "geometry": {"coordinates":[-122.144102,47.617208],"type":"Point"}
}