{
  "type": "Feature",
  "properties": {
    "addr:full":"9 S Alder St Toppenish WA 98948",
    "addr:housenumber":"9",
    "addr:postcode":"98948",
    "addr:street":"S Alder St",
    "iso:country":"US",
    "sg:address":"9 S Alder St",
    "sg:city":"Toppenish",
    "sg:classifiers":[
        {
            "category":"Personal",
            "subcategory":"Beauty Salon",
            "type":"Services"
        }
    ],
    "sg:phone":"+1 509 865 4430",
    "sg:postcode":"98948",
    "sg:province":"WA",
    "sg:tags":[
        "shop"
    ],
    "wof:name":"Lovely You Hair Affair",
    "wof:placetype":"venue"
},
  "geometry": {"coordinates":[-120.311644,46.376339],"type":"Point"}
}