{
  "type": "Feature",
  "properties": {
    "addr:full":"11418 NE 72nd Ave Vancouver WA 98686",
    "addr:housenumber":"11418",
    "addr:postcode":"98686",
    "addr:street":"Ne 72Nd Ave",
    "iso:country":"US",
    "sg:address":"11418 NE 72nd Ave",
    "sg:city":"Vancouver",
    "sg:classifiers":[
        {
            "category":"Tea Room",
            "subcategory":"None",
            "type":"Food & Drink"
        },
        {
            "category":"Coffee & Tea",
            "type":"Food & Drink"
        },
        {
            "category":"Manufacturing",
            "subcategory":"Food",
            "type":"Manufacturing & Wholesale Goods"
        }
    ],
    "sg:phone":"+1 360 546 3217",
    "sg:postcode":"98686",
    "sg:province":"WA",
    "sg:tags":[
        "tea-wholesale",
        "manufacturer"
    ],
    "wof:name":"Legends' Coffee Company",
    "wof:placetype":"venue"
},
  "geometry": {"coordinates":[-122.59940400000001,45.704107],"type":"Point"}
}