{
  "type": "Feature",
  "properties": {
    "addr:full":"2720 E 57th Ave Spokane WA 99223",
    "addr:housenumber":"2720",
    "addr:postcode":"99223",
    "addr:street":"E 57Th Ave",
    "iso:country":"US",
    "sg:address":"2720 E 57th Ave",
    "sg:city":"Spokane",
    "sg:classifiers":[
        {
            "category":"Government",
            "subcategory":"Post Office",
            "type":"Public Place"
        }
    ],
    "sg:phone":"+1 509 000 1111",
    "sg:postcode":"99223",
    "sg:province":"WA",
    "wof:name":"US Post Office",
    "wof:placetype":"venue"
},
  "geometry": {"coordinates":[-117.368685,47.602133],"type":"Point"}
}