{
  "type": "Feature",
  "properties": {
    "addr:full":"951 Pe Ell McDonald Rd Chehalis WA 98532",
    "addr:housenumber":"951",
    "addr:postcode":"98532",
    "addr:street":"Pe;Mcdonald Rd",
    "iso:country":"US",
    "sg:address":"951 Pe Ell McDonald Rd",
    "sg:city":"Chehalis",
    "sg:classifiers":[
        {
            "category":"Professional",
            "subcategory":"Management & Consulting",
            "type":"Services"
        }
    ],
    "sg:phone":"+1 360 291 3655",
    "sg:postcode":"98532",
    "sg:province":"WA",
    "sg:tags":[
        "business"
    ],
    "wof:name":"Sbm Consulting Services",
    "wof:placetype":"venue"
},
  "geometry": {"coordinates":[-123.29047799999999,46.573409],"type":"Point"}
}