{
  "type": "Feature",
  "properties": {
    "addr:full":"1215 S C St Port Angeles WA 98363",
    "addr:housenumber":"1215",
    "addr:postcode":"98363",
    "addr:street":"S C St",
    "iso:country":"US",
    "sg:address":"1215 S C St",
    "sg:city":"Port Angeles",
    "sg:classifiers":[
        {
            "category":"Professional",
            "subcategory":"Business Services",
            "type":"Services"
        }
    ],
    "sg:phone":"+1 360 417 1005",
    "sg:postcode":"98363",
    "sg:province":"WA",
    "wof:name":"Hoch Agency",
    "wof:placetype":"venue"
},
  "geometry": {"coordinates":[-123.46016299999999,48.116657],"type":"Point"}
}