{
  "type": "Feature",
  "properties": {
    "addr:full":"4141 42nd Ave NE Seattle WA 98105",
    "addr:housenumber":"4141",
    "addr:postcode":"98105",
    "addr:street":"42Nd Ave Ne",
    "iso:country":"US",
    "sg:address":"4141 42nd Ave NE",
    "sg:city":"Seattle",
    "sg:classifiers":[
        {
            "category":"Building & Trades",
            "subcategory":"Construction",
            "type":"Services"
        }
    ],
    "sg:phone":"+1 206 526 9350",
    "sg:postcode":"98105",
    "sg:province":"WA",
    "sg:tags":[
        "industrial"
    ],
    "wof:name":"Bryan Em Co",
    "wof:placetype":"venue"
},
  "geometry": {"coordinates":[-122.282821,47.660986],"type":"Point"}
}