{
  "type": "Feature",
  "properties": {
    "addr:full":"270 SW Captain Cook Rd White Salmon WA 98672",
    "addr:housenumber":"270",
    "addr:postcode":"98672",
    "addr:street":"Sw Captain Cook Rd",
    "iso:country":"US",
    "sg:address":"270 SW Captain Cook Rd",
    "sg:city":"White Salmon",
    "sg:classifiers":[
        {
            "category":"Professional",
            "type":"Services"
        }
    ],
    "sg:phone":"+1 509 493 3017",
    "sg:postcode":"98672",
    "sg:province":"WA",
    "wof:name":"Windy Ridge Studios",
    "wof:placetype":"venue"
},
  "geometry": {"coordinates":[-121.51669699999999,45.73438],"type":"Point"}
}