{
  "type": "Feature",
  "properties": {
    "addr:full":"205 Mountain View Rd SE Yelm WA 98597",
    "addr:housenumber":"205",
    "addr:postcode":"98597",
    "addr:street":"Mountain View Rd Se Yelm",
    "iso:country":"US",
    "sg:address":"205 Mountain View Rd SE",
    "sg:city":"Yelm",
    "sg:classifiers":[
        {
            "category":"Real Estate",
            "subcategory":"Real Estate Operator",
            "type":"Services"
        }
    ],
    "sg:phone":"+1 360 400 0567",
    "sg:postcode":"98597",
    "sg:province":"WA",
    "sg:tags":[
        "building",
        "apartment"
    ],
    "wof:name":"Prairie Run Apartments",
    "wof:placetype":"venue"
},
  "geometry": {"coordinates":[-122.622248,46.961595],"type":"Point"}
}