{
  "type": "Feature",
  "properties": {
    "addr:full":"7715 61st Ave E Puyallup WA 98371",
    "addr:housenumber":"7715",
    "addr:postcode":"98371",
    "addr:street":"61St Ave E",
    "iso:country":"US",
    "sg:address":"7715 61st Ave E",
    "sg:city":"Puyallup",
    "sg:classifiers":[
        {
            "category":"Marine",
            "type":"Transportation"
        }
    ],
    "sg:phone":"+1 253 840 4476",
    "sg:postcode":"98371",
    "sg:province":"WA",
    "sg:tags":[
        "water",
        "surveyor",
        "transport"
    ],
    "wof:name":"Donald Goodell Marine Sur",
    "wof:placetype":"venue"
},
  "geometry": {"coordinates":[-122.347679,47.186223],"type":"Point"}
}