{
  "type": "Feature",
  "properties": {
    "addr:full":"3328 Smith Ave Everett WA 98201",
    "addr:housenumber":"3328",
    "addr:postcode":"98201",
    "addr:street":"Smith Ave",
    "iso:country":"US",
    "sg:address":"3328 Smith Ave",
    "sg:city":"Everett",
    "sg:classifiers":[
        {
            "category":"Wholesale",
            "subcategory":"Motor Vehicles",
            "type":"Manufacturing & Wholesale Goods"
        },
        {
            "category":"Personal",
            "type":"Services"
        },
        {
            "category":"Retail",
            "subcategory":"Auto Repair",
            "type":"Services"
        },
        {
            "category":"Utilities",
            "type":"Services"
        }
    ],
    "sg:phone":"+1 425 355 7212",
    "sg:postcode":"98201",
    "sg:province":"WA",
    "sg:tags":[
        "automobile",
        "equipment",
        "towing",
        "transporter",
        "referral",
        "road",
        "service-automotive"
    ],
    "sg:website":"http://www.americantowingeverett.com",
    "wof:name":"American Towing",
    "wof:placetype":"venue"
},
  "geometry": {"coordinates":[-122.19734699999999,47.973376],"type":"Point"}
}