{
  "type": "Feature",
  "properties": {
    "addr:full":"430 SE 192nd Ave Vancouver WA 98683",
    "addr:housenumber":"430",
    "addr:postcode":"98683",
    "addr:street":"Se 192Nd Ave",
    "iso:country":"US",
    "sg:address":"430 SE 192nd Ave",
    "sg:city":"Vancouver",
    "sg:classifiers":[
        {
            "category":"Personal",
            "subcategory":"Nail Salon",
            "type":"Services"
        }
    ],
    "sg:phone":"+1 360 256 2661",
    "sg:postcode":"98683",
    "sg:province":"WA",
    "wof:name":"Regal Nails",
    "wof:placetype":"venue"
},
  "geometry": {"coordinates":[-122.47625600000001,45.617567],"type":"Point"}
}