{
  "type": "Feature",
  "properties": {
    "addr:full":"116 N 3rd St Dayton WA 99328",
    "addr:housenumber":"116",
    "addr:postcode":"99328",
    "addr:street":"N 3Rd St",
    "iso:country":"US",
    "sg:address":"116 N 3rd St",
    "sg:city":"Dayton",
    "sg:classifiers":[
        {
            "category":"Government",
            "subcategory":"Court House",
            "type":"Public Place"
        }
    ],
    "sg:phone":"+1 509 382 1197",
    "sg:postcode":"99328",
    "sg:province":"WA",
    "sg:tags":[
        "county",
        "counsel"
    ],
    "wof:name":"Columbia Cnty Prosecuting Atty",
    "wof:placetype":"venue"
},
  "geometry": {"coordinates":[-117.97823699999999,46.321712],"type":"Point"}
}