{
  "type": "Feature",
  "properties": {
    "addr:full":"281 NE Tee Lake Rd Tahuya WA 98588",
    "addr:housenumber":"281",
    "addr:postcode":"98588",
    "addr:street":"Ne Tee Lake Rd",
    "iso:country":"US",
    "sg:address":"281 NE Tee Lake Rd",
    "sg:city":"Tahuya",
    "sg:classifiers":[
        {
            "category":"Restaurant",
            "type":"Food & Drink"
        }
    ],
    "sg:phone":"+1 360 275 2302",
    "sg:postcode":"98588",
    "sg:province":"WA",
    "sg:tags":[
        "style",
        "family"
    ],
    "wof:name":"The Rice Bowl",
    "wof:placetype":"venue"
},
  "geometry": {"coordinates":[-123.020584,47.431202],"type":"Point"}
}