{
  "type": "Feature",
  "properties": {
    "addr:full":"600 Pine Street Space 136 Seattle WA 98101",
    "addr:housenumber":"600;136",
    "addr:postcode":"98101",
    "addr:street":"Pine Street",
    "iso:country":"US",
    "sg:address":"600 Pine Street Space 136",
    "sg:city":"Seattle",
    "sg:classifiers":[
        {
            "category":"Shopping",
            "subcategory":"Beauty & Cosmetics",
            "type":"Retail Goods"
        }
    ],
    "sg:phone":"+1 206 624 2450",
    "sg:postcode":"98101",
    "sg:province":"WA",
    "sg:tags":[
        "supply"
    ],
    "sg:website":"www.aveda.com/templates/door/fac...",
    "wof:name":"Aveda",
    "wof:placetype":"venue"
},
  "geometry": {"coordinates":[-122.335297,47.612167],"type":"Point"}
}