{
  "type": "Feature",
  "properties": {
    "iso:country":"US",
    "sg:address":"612 S Fife St",
    "sg:city":"Tacoma",
    "sg:classifiers":[
        {
            "category":"Professional",
            "type":"Services"
        }
    ],
    "sg:phone":"+1 253 232 7790",
    "sg:postcode":"98405",
    "sg:province":"WA",
    "wof:name":"Hidden Dragon",
    "wof:placetype":"venue"
},
  "geometry": {"coordinates":[-122.470299,47.254439],"type":"Point"}
}