{
  "type": "Feature",
  "properties": {
    "addr:full":"12801 Aurora Ave N Seattle WA 98133",
    "addr:housenumber":"12801",
    "addr:postcode":"98133",
    "addr:street":"Aurora Ave N",
    "iso:country":"US",
    "sg:address":"12801 Aurora Ave N",
    "sg:city":"Seattle",
    "sg:classifiers":[
        {
            "category":"Autos & Motor Vehicles",
            "subcategory":"Automobile Sales",
            "type":"Retail Goods"
        }
    ],
    "sg:phone":"+1 206 361 2155",
    "sg:postcode":"98133",
    "sg:province":"WA",
    "wof:name":"Warren Westlund Buick GMC Trck",
    "wof:placetype":"venue"
},
  "geometry": {"coordinates":[-122.344978,47.723237],"type":"Point"}
}