{
  "type": "Feature",
  "properties": {
    "addr:full":"29911 48th Ave S Roy WA 98580",
    "addr:housenumber":"29911",
    "addr:postcode":"98580",
    "addr:street":"48Th Ave S Roy",
    "iso:country":"US",
    "sg:address":"29911 48th Ave S",
    "sg:city":"Roy",
    "sg:classifiers":[
        {
            "category":"Utilities",
            "subcategory":"Telephone",
            "type":"Services"
        }
    ],
    "sg:phone":"+1 253 843 0568",
    "sg:postcode":"98580",
    "sg:province":"WA",
    "sg:tags":[
        "communications"
    ],
    "wof:name":"Peart Products",
    "wof:placetype":"venue"
},
  "geometry": {"coordinates":[-122.494366,46.986259],"type":"Point"}
}