{
  "type": "Feature",
  "properties": {
    "addr:full":"32232 12th Pl SW Federal Way WA 98023",
    "addr:housenumber":"32232",
    "addr:postcode":"98023",
    "addr:street":"12Th Pl Sw Federal Way",
    "iso:country":"US",
    "sg:address":"32232 12th Pl SW",
    "sg:city":"Federal Way",
    "sg:classifiers":[
        {
            "category":"Restaurant",
            "type":"Food & Drink"
        }
    ],
    "sg:phone":"+1 253 874 6204",
    "sg:postcode":"98023",
    "sg:province":"WA",
    "sg:tags":[
        "eating"
    ],
    "wof:name":"Classic Deli",
    "wof:placetype":"venue"
},
  "geometry": {"coordinates":[-122.350988,47.313077],"type":"Point"}
}