{
  "type": "Feature",
  "properties": {
    "iso:country":"US",
    "sg:address":"911 E Pike St",
    "sg:city":"Seattle",
    "sg:classifiers":[
        {
            "category":"Professional",
            "type":"Services"
        }
    ],
    "sg:phone":"+1 206 501 5517",
    "sg:postcode":"98122",
    "sg:province":"WA",
    "wof:name":"Milk Bone Art",
    "wof:placetype":"venue"
},
  "geometry": {"coordinates":[-122.31953900000001,47.614007],"type":"Point"}
}