{
  "type": "Feature",
  "properties": {
    "addr:full":"205 S Meridian Puyallup WA 98371",
    "addr:housenumber":"205",
    "addr:postcode":"98371",
    "addr:street":"S Meridian",
    "iso:country":"US",
    "sg:address":"205 S Meridian",
    "sg:city":"Puyallup",
    "sg:classifiers":[
        {
            "category":"Professional",
            "subcategory":"Accounting & Tax Preparation",
            "type":"Services"
        }
    ],
    "sg:phone":"+1 253 845 6611",
    "sg:postcode":"98371",
    "sg:province":"WA",
    "sg:tags":[
        "accountant"
    ],
    "wof:name":"Robert G Murray",
    "wof:placetype":"venue"
},
  "geometry": {"coordinates":[-122.293631,47.190463],"type":"Point"}
}