{
  "type": "Feature",
  "properties": {
    "addr:full":"7837 Custer School Rd Custer WA 98240",
    "addr:housenumber":"7837",
    "addr:postcode":"98240",
    "addr:street":"Custer School Rd",
    "iso:country":"US",
    "sg:address":"7837 Custer School Rd",
    "sg:city":"Custer",
    "sg:classifiers":[
        {
            "category":"Manufacturing",
            "subcategory":"Rubber & Plastics",
            "type":"Manufacturing & Wholesale Goods"
        }
    ],
    "sg:phone":"+1 360 366 5044",
    "sg:postcode":"98240",
    "sg:province":"WA",
    "sg:tags":[
        "component",
        "mfg"
    ],
    "wof:name":"Signature Plastics LLC",
    "wof:placetype":"venue"
},
  "geometry": {"coordinates":[-122.638993,48.924436],"type":"Point"}
}