{
  "type": "Feature",
  "properties": {
    "addr:full":"12001 Lake City Way NE Seattle WA 98125",
    "addr:housenumber":"12001",
    "addr:postcode":"98125",
    "addr:street":"Lake City Way Ne",
    "iso:country":"US",
    "sg:address":"12001 Lake City Way NE",
    "sg:city":"Seattle",
    "sg:phone":"+1 206 364 2490",
    "sg:postcode":"98125",
    "sg:province":"WA",
    "sg:website":"http://www.starbuckscoffee.com",
    "wof:name":"Starbucks Coffee",
    "wof:placetype":"venue"
},
  "geometry": {"coordinates":[-122.297363,47.715611],"type":"Point"}
}