{
  "type": "Feature",
  "properties": {
    "addr:full":"4571 Burpee Hill Rd Concrete WA 98237",
    "addr:postcode":"4571;98237",
    "addr:street":"Burpee Hill Rd",
    "iso:country":"US",
    "sg:address":"4571 Burpee Hill Rd",
    "sg:city":"Concrete",
    "sg:classifiers":[
        {
            "category":"Recreation",
            "subcategory":"Campground",
            "type":"Entertainment"
        }
    ],
    "sg:phone":"+1 360 853 7020",
    "sg:postcode":"98237",
    "sg:province":"WA",
    "sg:tags":[
        "recreational",
        "park",
        "vehicle"
    ],
    "wof:name":"Lake Tyee",
    "wof:placetype":"venue"
},
  "geometry": {"coordinates":[-121.77407100000001,48.578838],"type":"Point"}
}