{
  "type": "Feature",
  "properties": {
    "addr:full":"702 Main St Pomeroy WA 99347",
    "addr:housenumber":"702",
    "addr:postcode":"99347",
    "addr:street":"Main St",
    "iso:country":"US",
    "sg:address":"702 Main St",
    "sg:city":"Pomeroy",
    "sg:classifiers":[
        {
            "category":"Sports & Exercise",
            "subcategory":"Gym",
            "type":"Entertainment"
        }
    ],
    "sg:phone":"+1 509 843 5060",
    "sg:postcode":"99347",
    "sg:province":"WA",
    "sg:tags":[
        "club",
        "health",
        "studio",
        "gymnasium"
    ],
    "wof:name":"Fun Fitness",
    "wof:placetype":"venue"
},
  "geometry": {"coordinates":[-117.598305,46.474353],"type":"Point"}
}