{
  "type": "Feature",
  "properties": {
    "addr:full":"1905 SE 114th Ct Vancouver WA 98664",
    "addr:housenumber":"1905",
    "addr:postcode":"98664",
    "addr:street":"Se 114Th Ct",
    "iso:country":"US",
    "sg:address":"1905 SE 114th Ct",
    "sg:city":"Vancouver",
    "sg:classifiers":[
        {
            "category":"Food & Beverages",
            "subcategory":"Groceries & Convenience Stores",
            "type":"Retail Goods"
        }
    ],
    "sg:phone":"+1 360 882 6076",
    "sg:postcode":"98664",
    "sg:province":"WA",
    "wof:name":"Custom Market System",
    "wof:placetype":"venue"
},
  "geometry": {"coordinates":[-122.55591200000001,45.606291],"type":"Point"}
}