{
  "type": "Feature",
  "properties": {
    "addr:full":"5100 SW 316th Pl Federal Way WA 98023",
    "addr:housenumber":"5100",
    "addr:postcode":"98023",
    "addr:street":"Sw 316Th Pl",
    "iso:country":"US",
    "sg:address":"5100 SW 316th Pl",
    "sg:city":"Federal Way",
    "sg:classifiers":[
        {
            "category":"Health Services",
            "subcategory":"Doctor",
            "type":"Services"
        }
    ],
    "sg:phone":"+1 253 952 4268",
    "sg:postcode":"98023",
    "sg:province":"WA",
    "sg:tags":[
        "medical"
    ],
    "wof:name":"Eleanor I Sutherland MD",
    "wof:placetype":"venue"
},
  "geometry": {"coordinates":[-122.39841199999999,47.319765],"type":"Point"}
}