{
  "type": "Feature",
  "properties": {
    "addr:full":"38579 River St Snoqualmie WA 98065",
    "addr:housenumber":"38579",
    "addr:postcode":"98065",
    "addr:street":"River St",
    "iso:country":"US",
    "sg:address":"38579 River St",
    "sg:city":"Snoqualmie",
    "sg:classifiers":[
        {
            "category":"Health Services",
            "subcategory":"Chiropractor",
            "type":"Services"
        }
    ],
    "sg:phone":"+1 425 888 1780",
    "sg:postcode":"98065",
    "sg:province":"WA",
    "wof:name":"Chiropractic Today",
    "wof:placetype":"venue"
},
  "geometry": {"coordinates":[-121.82692400000001,47.526913],"type":"Point"}
}