{
  "type": "Feature",
  "properties": {
    "addr:full":"409 Stevens Ave Sultan WA 98294",
    "addr:housenumber":"409",
    "addr:postcode":"98294",
    "addr:street":"Stevens Ave",
    "iso:country":"US",
    "sg:address":"409 Stevens Ave",
    "sg:city":"Sultan",
    "sg:classifiers":[
        {
            "category":"Personal",
            "subcategory":"Beauty Salon",
            "type":"Services"
        }
    ],
    "sg:phone":"+1 360 793 8700",
    "sg:postcode":"98294",
    "sg:province":"WA",
    "sg:tags":[
        "manicuring"
    ],
    "wof:name":"Pac's Nail Express",
    "wof:placetype":"venue"
},
  "geometry": {"coordinates":[-121.815091,47.861892],"type":"Point"}
}