{
  "type": "Feature",
  "properties": {
    "addr:full":"113 S 6th St Lynden WA 98264",
    "addr:housenumber":"113",
    "addr:postcode":"98264",
    "addr:street":"S 6Th St",
    "iso:country":"US",
    "sg:address":"113 S 6th St",
    "sg:city":"Lynden",
    "sg:classifiers":[
        {
            "category":"Manufacturing",
            "subcategory":"Printing",
            "type":"Manufacturing & Wholesale Goods"
        }
    ],
    "sg:phone":"+1 360 354 4444",
    "sg:postcode":"98264",
    "sg:province":"WA",
    "sg:tags":[
        "newspaper"
    ],
    "sg:website":"www.lyndentrib.com",
    "wof:name":"Lynden Tribune",
    "wof:placetype":"venue"
},
  "geometry": {"coordinates":[-122.454477,48.941678],"type":"Point"}
}