{
  "type": "Feature",
  "properties": {
    "addr:full":"328 W Pine St Sequim WA 98382",
    "addr:housenumber":"328",
    "addr:postcode":"98382",
    "addr:street":"W Pine St",
    "iso:country":"US",
    "sg:address":"328 W Pine St",
    "sg:city":"Sequim",
    "sg:classifiers":[
        {
            "category":"Building & Trades",
            "subcategory":"Construction",
            "type":"Services"
        }
    ],
    "sg:phone":"+1 360 683 2857",
    "sg:postcode":"98382",
    "sg:province":"WA",
    "sg:tags":[
        "hanging",
        "co",
        "contractor"
    ],
    "wof:name":"John Kinsella Painting",
    "wof:placetype":"venue"
},
  "geometry": {"coordinates":[-123.112925,48.074283],"type":"Point"}
}