{
  "type": "Feature",
  "properties": {
    "addr:full":"27435 SE 150th St Issaquah WA 98027",
    "addr:postcode":"27435;98027",
    "addr:street":"Se 150Th St",
    "iso:country":"US",
    "sg:address":"27435 SE 150th St",
    "sg:city":"Issaquah",
    "sg:classifiers":[
        {
            "category":"Shopping",
            "type":"Retail Goods"
        }
    ],
    "sg:phone":"+1 425 837 1316",
    "sg:postcode":"98027",
    "sg:province":"WA",
    "sg:tags":[
        "merchandise"
    ],
    "wof:name":"Tiger Mountain Gear Inc",
    "wof:placetype":"venue"
},
  "geometry": {"coordinates":[-121.975393,47.466593],"type":"Point"}
}