{
  "type": "Feature",
  "properties": {
    "addr:full":"2525 E Girard Pl Spokane WA 99223",
    "addr:housenumber":"2525",
    "addr:postcode":"99223",
    "addr:street":"E Girard Pl",
    "iso:country":"US",
    "sg:address":"2525 E Girard Pl",
    "sg:city":"Spokane",
    "sg:classifiers":[
        {
            "category":"Building & Trades",
            "subcategory":"Landscaping Services",
            "type":"Services"
        }
    ],
    "sg:phone":"+1 509 701 6100",
    "sg:postcode":"99223",
    "sg:province":"WA",
    "wof:name":"Creative Landscaping Design",
    "wof:placetype":"venue"
},
  "geometry": {"coordinates":[-117.372827,47.641401],"type":"Point"}
}