{
  "type": "Feature",
  "properties": {
    "addr:full":"19611 International Blvd Seattle WA 98188",
    "addr:housenumber":"19611",
    "addr:postcode":"98188",
    "addr:street":"International Blvd",
    "iso:country":"US",
    "sg:address":"19611 International Blvd",
    "sg:city":"Seattle",
    "sg:classifiers":[
        {
            "category":"Retail",
            "subcategory":"Auto Repair",
            "type":"Services"
        }
    ],
    "sg:phone":"+1 206 878 1481",
    "sg:postcode":"98188",
    "sg:province":"WA",
    "sg:tags":[
        "general"
    ],
    "wof:name":"Volkswagen Repair",
    "wof:placetype":"venue"
},
  "geometry": {"coordinates":[-122.295917,47.426631],"type":"Point"}
}