{
  "type": "Feature",
  "properties": {
    "addr:full":"12608 NE 16th St Vancouver WA 98684",
    "addr:housenumber":"12608",
    "addr:postcode":"98684",
    "addr:street":"Ne 16Th St",
    "iso:country":"US",
    "sg:address":"12608 NE 16th St",
    "sg:city":"Vancouver",
    "sg:classifiers":[
        {
            "category":"Building & Trades",
            "subcategory":"Construction",
            "type":"Services"
        }
    ],
    "sg:phone":"+1 360 521 3719",
    "sg:postcode":"98684",
    "sg:province":"WA",
    "sg:tags":[
        "house"
    ],
    "wof:name":"N L S Construction",
    "wof:placetype":"venue"
},
  "geometry": {"coordinates":[-122.542447,45.633614],"type":"Point"}
}