{
  "type": "Feature",
  "properties": {
    "addr:full":"707 N Emerson Ave Wenatchee WA 98801",
    "addr:housenumber":"707",
    "addr:postcode":"98801",
    "addr:street":"N Emerson Ave",
    "iso:country":"US",
    "sg:address":"707 N Emerson Ave",
    "sg:city":"Wenatchee",
    "sg:classifiers":[
        {
            "category":"Shopping",
            "type":"Retail Goods"
        },
        {
            "category":"Health Services",
            "subcategory":"Doctor",
            "type":"Services"
        }
    ],
    "sg:phone":"+1 509 663 8711",
    "sg:postcode":"98801",
    "sg:province":"WA",
    "sg:tags":[
        "injury",
        "supply",
        "hearing",
        "equipment",
        "medicine",
        "impaired",
        "sport"
    ],
    "wof:name":"Wenatchee Valley Clinic",
    "wof:placetype":"venue"
},
  "geometry": {"coordinates":[-120.322355,47.431831],"type":"Point"}
}