{
  "type": "Feature",
  "properties": {
    "addr:full":"12058 Lake City Way NE Seattle WA 98125",
    "addr:housenumber":"12058",
    "addr:postcode":"98125",
    "addr:street":"Lake City Way Ne",
    "iso:country":"US",
    "sg:address":"12058 Lake City Way NE",
    "sg:city":"Seattle",
    "sg:classifiers":[
        {
            "category":"Manufacturing",
            "subcategory":"Electronics",
            "type":"Manufacturing & Wholesale Goods"
        },
        {
            "category":"Shopping",
            "subcategory":"Computers & Home Electronics",
            "type":"Retail Goods"
        }
    ],
    "sg:phone":"+1 206 363 9200",
    "sg:postcode":"98125",
    "sg:province":"WA",
    "sg:tags":[
        "radio-wholesale",
        "television",
        "radio",
        "store",
        "manufacturer"
    ],
    "sg:website":"http://www.tjcsm.com",
    "wof:name":"Joncas, The",
    "wof:placetype":"venue"
},
  "geometry": {"coordinates":[-122.29662,47.716903],"type":"Point"}
}