{
  "type": "Feature",
  "properties": {
    "addr:full":"5100 25th Ave NE Seattle WA 98105",
    "addr:housenumber":"5100",
    "addr:postcode":"98105",
    "addr:street":"25Th Ave Ne",
    "iso:country":"US",
    "sg:address":"5100 25th Ave NE",
    "sg:city":"Seattle",
    "sg:phone":"+1 206 526 5979",
    "sg:postcode":"98105",
    "sg:province":"WA",
    "sg:website":"http://clickserve.dartsearch.net/link/click?lid=43000000313867648&ds_s_kwgid=58000000006820725&ds_e_matchtype={MatchType}&ds_e_kwdid={OrderItemId}&ds_e_adid={AdId}&ds_url_v=2",
    "wof:name":"Northwest Automotive Inc",
    "wof:placetype":"venue"
},
  "geometry": {"coordinates":[-122.300629,47.666309],"type":"Point"}
}