{
  "type": "Feature",
  "properties": {
    "addr:full":"1014 E HEMMI RD EVERSON WA 98247",
    "addr:housenumber":"1014",
    "addr:postcode":"98247",
    "addr:street":"E Hemmi Rd",
    "iso:country":"US",
    "sg:address":"1014 E HEMMI RD",
    "sg:city":"EVERSON",
    "sg:phone":"+1 360 398 0174",
    "sg:postcode":"98247",
    "sg:province":"WA",
    "sg:website":"http://www.hylinehotel.com/Default.htm",
    "wof:name":"Hyline Hotel And Training For Dogs, LLC",
    "wof:placetype":"venue"
},
  "geometry": {"coordinates":[-122.420834,48.862556],"type":"Point"}
}