{
  "type": "Feature",
  "properties": {
    "iso:country":"US",
    "sg:address":"430 S 16th Ave",
    "sg:city":"Othello",
    "sg:classifiers":[
        {
            "category":"Manufacturing",
            "subcategory":"Signs",
            "type":"Manufacturing & Wholesale Goods"
        }
    ],
    "sg:phone":"+1 509 488 5081",
    "sg:postcode":"99344",
    "sg:province":"WA",
    "wof:name":"Signs Of Grace",
    "wof:placetype":"venue"
},
  "geometry": {"coordinates":[-119.151869,46.821572],"type":"Point"}
}