{
  "type": "Feature",
  "properties": {
    "addr:full":"2916 Mission Beach Rd Marysville WA 98271",
    "addr:housenumber":"2916",
    "addr:postcode":"98271",
    "addr:street":"Mission Beach Rd",
    "iso:country":"US",
    "sg:address":"2916 Mission Beach Rd",
    "sg:city":"Marysville",
    "sg:classifiers":[
        {
            "category":"Manufacturing",
            "subcategory":"Jewelry",
            "type":"Manufacturing & Wholesale Goods"
        }
    ],
    "sg:phone":"+1 360 653 5287",
    "sg:postcode":"98271",
    "sg:province":"WA",
    "sg:tags":[
        "ware",
        "mfg"
    ],
    "wof:name":"Susan Large",
    "wof:placetype":"venue"
},
  "geometry": {"coordinates":[-122.274507,48.048759],"type":"Point"}
}