{
  "type": "Feature",
  "properties": {
    "addr:full":"308 118th Ave SE Bellevue WA 98005",
    "addr:housenumber":"308",
    "addr:postcode":"98005",
    "addr:street":"118Th Ave Se",
    "iso:country":"US",
    "sg:address":"308 118th Ave SE",
    "sg:city":"Bellevue",
    "sg:classifiers":[
        {
            "category":"Social Services",
            "subcategory":"Child Care",
            "type":"Services"
        }
    ],
    "sg:phone":"+1 425 453 6077",
    "sg:postcode":"98005",
    "sg:province":"WA",
    "sg:tags":[
        "kindergarten",
        "academic",
        "school"
    ],
    "wof:name":"Bright Horizons Family Solutns",
    "wof:placetype":"venue"
},
  "geometry": {"coordinates":[-122.18270200000001,47.608062],"type":"Point"}
}