{
  "type": "Feature",
  "properties": {
    "addr:full":"400 Pine Street Suite 328 Seattle WA 98101",
    "addr:housenumber":"400",
    "addr:postcode":"98101",
    "addr:street":"Pine Street Suite 328",
    "iso:country":"US",
    "sg:address":"400 Pine Street Suite 328",
    "sg:city":"Seattle",
    "sg:classifiers":[
        {
            "category":"Restaurant",
            "type":"Food & Drink"
        }
    ],
    "sg:phone":"+1 206 623 9090",
    "sg:postcode":"98101",
    "sg:province":"WA",
    "sg:tags":[
        "indian"
    ],
    "sg:website":"http://www.bombaywala.com",
    "wof:name":"Bombay Wala Cuisine of India",
    "wof:placetype":"venue"
},
  "geometry": {"coordinates":[-122.337997,47.611401],"type":"Point"}
}