{
  "type": "Feature",
  "properties": {
    "addr:full":"11061 NE 2nd St Bellevue WA 98004",
    "addr:housenumber":"11061",
    "addr:postcode":"98004",
    "addr:street":"Ne 2Nd St",
    "iso:country":"US",
    "sg:address":"11061 NE 2nd St",
    "sg:city":"Bellevue",
    "sg:classifiers":[
        {
            "category":"Professional",
            "subcategory":"Lawyer & Legal Services",
            "type":"Services"
        }
    ],
    "sg:phone":"+1 425 455 2332",
    "sg:postcode":"98004",
    "sg:province":"WA",
    "sg:tags":[
        "attorney"
    ],
    "wof:name":"Lawrence & Finkelstein Pllc",
    "wof:placetype":"venue"
},
  "geometry": {"coordinates":[-122.192854,47.61192],"type":"Point"}
}