{
  "type": "Feature",
  "properties": {
    "addr:full":"1231 230th Ave NE Sammamish WA 98074",
    "addr:housenumber":"1231",
    "addr:postcode":"98074",
    "addr:street":"230Th Ave Ne",
    "iso:country":"US",
    "sg:address":"1231 230th Ave NE",
    "sg:city":"Sammamish",
    "sg:classifiers":[
        {
            "category":"Professional",
            "type":"Services"
        }
    ],
    "sg:phone":"+1 425 868 0964",
    "sg:postcode":"98074",
    "sg:province":"WA",
    "sg:tags":[
        "establishment"
    ],
    "wof:name":"Crompe Jeffrey-CANON USA",
    "wof:placetype":"venue"
},
  "geometry": {"coordinates":[-122.032224,47.620816],"type":"Point"}
}