{
  "type": "Feature",
  "properties": {
    "addr:full":"4804 Center St Tacoma WA 98409",
    "addr:housenumber":"4804",
    "addr:postcode":"98409",
    "addr:street":"Center St",
    "iso:country":"US",
    "sg:address":"4804 Center St",
    "sg:city":"Tacoma",
    "sg:classifiers":[
        {
            "category":"Professional",
            "subcategory":"Accounting & Tax Preparation",
            "type":"Services"
        }
    ],
    "sg:phone":"+1 253 565 2734",
    "sg:postcode":"98409",
    "sg:province":"WA",
    "sg:tags":[
        "bookkeeping",
        "general"
    ],
    "wof:name":"Professional Bookkeeping",
    "wof:placetype":"venue"
},
  "geometry": {"coordinates":[-122.503688,47.234352],"type":"Point"}
}