{
  "type": "Feature",
  "properties": {
    "iso:country":"US",
    "sg:address":"770 Mullis St",
    "sg:city":"Friday Harbor",
    "sg:classifiers":[
        {
            "category":"Travel",
            "subcategory":"Hotels & Motels",
            "type":"Entertainment"
        }
    ],
    "sg:phone":"+1 360 378 2724",
    "sg:postcode":"98250",
    "sg:province":"WA",
    "sg:website":"www.theorcainn.org",
    "wof:name":"Orca Inn",
    "wof:placetype":"venue"
},
  "geometry": {"coordinates":[-123.023186,48.528527],"type":"Point"}
}