{
  "type": "Feature",
  "properties": {
    "addr:full":"111 NW 184th St Ridgefield WA 98642",
    "addr:housenumber":"111",
    "addr:postcode":"98642",
    "addr:street":"Nw 184Th St",
    "iso:country":"US",
    "sg:address":"111 NW 184th St",
    "sg:city":"Ridgefield",
    "sg:classifiers":[
        {
            "category":"Freight",
            "type":"Transportation"
        }
    ],
    "sg:phone":"+1 360 887 8731",
    "sg:postcode":"98642",
    "sg:province":"WA",
    "sg:tags":[
        "operator",
        "local",
        "trucking"
    ],
    "wof:name":"Barry Ralph Reed",
    "wof:placetype":"venue"
},
  "geometry": {"coordinates":[-122.669276,45.75419],"type":"Point"}
}