{
  "type": "Feature",
  "properties": {
    "addr:full":"2220 Monica Dr Mount Vernon WA 98273",
    "addr:housenumber":"2220",
    "addr:postcode":"98273",
    "addr:street":"Monica Dr",
    "iso:country":"US",
    "sg:address":"2220 Monica Dr",
    "sg:city":"Mount Vernon",
    "sg:classifiers":[
        {
            "category":"Arts & Performance",
            "subcategory":"Theater",
            "type":"Entertainment"
        }
    ],
    "sg:phone":"+1 360 424 3886",
    "sg:postcode":"98273",
    "sg:province":"WA",
    "sg:tags":[
        "group"
    ],
    "wof:name":"Michael R Tolf",
    "wof:placetype":"venue"
},
  "geometry": {"coordinates":[-122.310293,48.443666],"type":"Point"}
}