{
  "type": "Feature",
  "properties": {
    "addr:full":"1026 164th St SE Mill Creek WA 98012",
    "addr:housenumber":"1026",
    "addr:postcode":"98012",
    "addr:street":"164Th St Se",
    "iso:country":"US",
    "sg:address":"1026 164th St SE",
    "sg:city":"Mill Creek",
    "sg:classifiers":[
        {
            "category":"Food & Beverages",
            "subcategory":"Groceries & Convenience Stores",
            "type":"Retail Goods"
        }
    ],
    "sg:phone":"+1 425 742 1511",
    "sg:postcode":"98012",
    "sg:province":"WA",
    "wof:name":"AVS Gas & Go",
    "wof:placetype":"venue"
},
  "geometry": {"coordinates":[-122.21922499999999,47.84939],"type":"Point"}
}