{
  "type": "Feature",
  "properties": {
    "addr:full":"1836 156th Ave NE Bellevue WA 98007",
    "addr:housenumber":"1836",
    "addr:postcode":"98007",
    "addr:street":"156Th Ave Ne",
    "iso:country":"US",
    "sg:address":"1836 156th Ave NE",
    "sg:city":"Bellevue",
    "sg:classifiers":[
        {
            "category":"Sports & Exercise",
            "subcategory":"Gym",
            "type":"Entertainment"
        }
    ],
    "sg:phone":"+1 425 894 4111",
    "sg:postcode":"98007",
    "sg:province":"WA",
    "sg:tags":[
        "club",
        "health",
        "studio",
        "gymnasium"
    ],
    "wof:name":"Jazzercise Of Bellevue",
    "wof:placetype":"venue"
},
  "geometry": {"coordinates":[-122.132312,47.625835],"type":"Point"}
}