{
  "type": "Feature",
  "properties": {
    "addr:full":"8002 W Imnaha Ave Kennewick WA 99336",
    "addr:housenumber":"8002",
    "addr:postcode":"99336",
    "addr:street":"W Imnaha Ave",
    "iso:country":"US",
    "sg:address":"8002 W Imnaha Ave",
    "sg:city":"Kennewick",
    "sg:classifiers":[
        {
            "category":"Wholesale",
            "subcategory":"Machinery & Supplies",
            "type":"Manufacturing & Wholesale Goods"
        }
    ],
    "sg:phone":"+1 509 521 0991",
    "sg:postcode":"99336",
    "sg:province":"WA",
    "sg:tags":[
        "industrial",
        "for",
        "provide",
        "coating",
        "liner",
        "sundries"
    ],
    "wof:name":"Sabana Sales",
    "wof:placetype":"venue"
},
  "geometry": {"coordinates":[-119.23230100000001,46.217771],"type":"Point"}
}