{
  "type": "Feature",
  "properties": {
    "iso:country":"US",
    "sg:address":"12 Karen Ct",
    "sg:city":"Sequim",
    "sg:classifiers":[
        {
            "category":"Retail",
            "subcategory":"Repair Shop",
            "type":"Services"
        }
    ],
    "sg:phone":"+1 360 683 1786",
    "sg:postcode":"98382",
    "sg:province":"WA",
    "wof:name":"Henning Mindi Marie",
    "wof:placetype":"venue"
},
  "geometry": {"coordinates":[-123.11761,48.096936],"type":"Point"}
}