{
  "type": "Feature",
  "properties": {
    "iso:country":"US",
    "sg:address":"27611 42nd Ave S",
    "sg:city":"Auburn",
    "sg:classifiers":[
        {
            "category":"Autos & Motor Vehicles",
            "subcategory":"Automobile Sales",
            "type":"Retail Goods"
        }
    ],
    "sg:phone":"+1 253 941 3454",
    "sg:postcode":"98001",
    "sg:province":"WA",
    "sg:tags":[
        "used"
    ],
    "wof:name":"Classic Cars",
    "wof:placetype":"venue"
},
  "geometry": {"coordinates":[-122.281288,47.352768],"type":"Point"}
}