{
  "type": "Feature",
  "properties": {
    "addr:full":"6527 20th Dr NE Marysville WA 98271",
    "addr:housenumber":"6527",
    "addr:postcode":"98271",
    "addr:street":"20Th Dr Ne",
    "iso:country":"US",
    "sg:address":"6527 20th Dr NE",
    "sg:city":"Marysville",
    "sg:classifiers":[
        {
            "category":"Retail",
            "subcategory":"Repair Shop",
            "type":"Services"
        }
    ],
    "sg:phone":"+1 360 653 9186",
    "sg:postcode":"98271",
    "sg:province":"WA",
    "sg:tags":[
        "welding"
    ],
    "wof:name":"Bcp Welding Fabrication",
    "wof:placetype":"venue"
},
  "geometry": {"coordinates":[-122.203807,48.055573],"type":"Point"}
}