{
  "type": "Feature",
  "properties": {
    "addr:full":"7505 Zircon Dr SW Lakewood WA 98498",
    "addr:housenumber":"7505",
    "addr:postcode":"98498",
    "addr:street":"Zircon Dr Sw",
    "iso:country":"US",
    "sg:address":"7505 Zircon Dr SW",
    "sg:city":"Lakewood",
    "sg:classifiers":[
        {
            "category":"Professional",
            "subcategory":"Management & Consulting",
            "type":"Services"
        }
    ],
    "sg:phone":"+1 253 584 5237",
    "sg:postcode":"98498",
    "sg:province":"WA",
    "wof:name":"Elizabeth Allen Willis",
    "wof:placetype":"venue"
},
  "geometry": {"coordinates":[-122.542518,47.194903],"type":"Point"}
}