{
  "type": "Feature",
  "properties": {
    "addr:full":"41st And 15th at the Henry Art Gallery Seattle WA 98195",
    "addr:postcode":"98195",
    "iso:country":"US",
    "sg:address":"41st And 15th at the Henry Art Gallery",
    "sg:city":"Seattle",
    "sg:classifiers":[
        {
            "category":"Coffee & Tea",
            "type":"Food & Drink"
        }
    ],
    "sg:phone":"+1 206 221 6267",
    "sg:postcode":"98195",
    "sg:province":"WA",
    "wof:name":"Baci Cafe",
    "wof:placetype":"venue"
},
  "geometry": {"coordinates":[-122.31210299999999,47.656799],"type":"Point"}
}