{
  "type": "Feature",
  "properties": {
    "addr:full":"5834 S 196th St Kent WA 98032",
    "addr:housenumber":"5834",
    "addr:postcode":"98032",
    "addr:street":"S 196Th St",
    "iso:country":"US",
    "sg:address":"5834 S 196th St",
    "sg:city":"Kent",
    "sg:classifiers":[
        {
            "category":"Utilities",
            "subcategory":"Mobile Phone",
            "type":"Services"
        },
        {
            "category":"Communications",
            "type":"Services"
        }
    ],
    "sg:phone":"+1 253 437 5144",
    "sg:postcode":"98032",
    "sg:province":"WA",
    "sg:tags":[
        "telephone",
        "cellular"
    ],
    "wof:name":"At&T Store",
    "wof:placetype":"venue"
},
  "geometry": {"coordinates":[-122.260577,47.426642],"type":"Point"}
}