{
  "type": "Feature",
  "properties": {
    "iso:country":"US",
    "sg:address":"904 6th St",
    "sg:city":"Anacortes",
    "sg:classifiers":[
        {
            "category":"Government",
            "subcategory":"Office",
            "type":"Public Place"
        }
    ],
    "sg:phone":"+1 360 293 1909",
    "sg:postcode":"98221",
    "sg:province":"WA",
    "sg:tags":[
        "govt",
        "city"
    ],
    "wof:name":"Utility Billing",
    "wof:placetype":"venue"
},
  "geometry": {"coordinates":[-122.61247,48.517548],"type":"Point"}
}