{
  "type": "Feature",
  "properties": {
    "addr:full":"708 Mount Vernon Terminal RR Mt Vernon WA 98273",
    "addr:housenumber":"708",
    "addr:postcode":"98273",
    "addr:street":"Mount;Vernon",
    "iso:country":"US",
    "sg:address":"708 Mount Vernon Terminal RR",
    "sg:city":"Mt Vernon",
    "sg:classifiers":[
        {
            "category":"Personal",
            "subcategory":"Tattoo Parlor",
            "type":"Services"
        }
    ],
    "sg:phone":"+1 360 336 2609",
    "sg:postcode":"98273",
    "sg:province":"WA",
    "sg:tags":[
        "tattooing"
    ],
    "wof:name":"K & S Fineline Tattoo",
    "wof:placetype":"venue"
},
  "geometry": {"coordinates":[-122.33922800000001,48.41822],"type":"Point"}
}