{
  "type": "Feature",
  "properties": {
    "addr:full":"109 E Houghton Ave Spokane WA 99208",
    "addr:housenumber":"109",
    "addr:postcode":"99208",
    "addr:street":"E Houghton Ave",
    "iso:country":"US",
    "sg:address":"109 E Houghton Ave",
    "sg:city":"Spokane",
    "sg:classifiers":[
        {
            "category":"Banks & Credit Unions",
            "subcategory":"Investment Brokerage",
            "type":"Services"
        }
    ],
    "sg:phone":"+1 509 362 2224",
    "sg:postcode":"99208",
    "sg:province":"WA",
    "wof:name":"Weekley & Lymon Investment",
    "wof:placetype":"venue"
},
  "geometry": {"coordinates":[-117.407861,47.726915],"type":"Point"}
}