{
  "type": "Feature",
  "properties": {
    "addr:full":"1716 N 20th Ave Pasco WA 99301",
    "addr:housenumber":"1716",
    "addr:postcode":"99301",
    "addr:street":"N 20Th Ave",
    "iso:country":"US",
    "sg:address":"1716 N 20th Ave",
    "sg:city":"Pasco",
    "sg:classifiers":[
        {
            "category":"Retail",
            "subcategory":"Veterinary Services",
            "type":"Services"
        }
    ],
    "sg:phone":"+1 509 544 2899",
    "sg:postcode":"99301",
    "sg:province":"WA",
    "wof:name":"Achord T John Dvm",
    "wof:placetype":"venue"
},
  "geometry": {"coordinates":[-119.117334,46.24411],"type":"Point"}
}