{
  "type": "Feature",
  "properties": {
    "addr:full":"2005 Lakewood Rd Arlington WA 98223",
    "addr:housenumber":"2005",
    "addr:postcode":"98223",
    "addr:street":"Lakewood Rd",
    "iso:country":"US",
    "sg:address":"2005 Lakewood Rd",
    "sg:city":"Arlington",
    "sg:classifiers":[
        {
            "category":"Wholesale",
            "subcategory":"Non-durable Goods",
            "type":"Manufacturing & Wholesale Goods"
        }
    ],
    "sg:phone":"+1 360 652 8986",
    "sg:postcode":"98223",
    "sg:province":"WA",
    "wof:name":"Basket KASE",
    "wof:placetype":"venue"
},
  "geometry": {"coordinates":[-122.262266,48.156851],"type":"Point"}
}