{
  "type": "Feature",
  "properties": {
    "addr:full":"403 N Welcome Slough Rd Cathlamet WA 98612",
    "addr:housenumber":"403",
    "addr:postcode":"98612",
    "addr:street":"N Welcome Slough Rd",
    "iso:country":"US",
    "sg:address":"403 N Welcome Slough Rd",
    "sg:city":"Cathlamet",
    "sg:classifiers":[
        {
            "category":"Farming",
            "subcategory":"Dairy Farm",
            "type":"Manufacturing & Wholesale Goods"
        }
    ],
    "sg:phone":"+1 360 849 4146",
    "sg:postcode":"98612",
    "sg:province":"WA",
    "wof:name":"Aegerter Dairy Farm",
    "wof:placetype":"venue"
},
  "geometry": {"coordinates":[-123.425055,46.182277],"type":"Point"}
}