{
  "type": "Feature",
  "properties": {
    "addr:full":"4008 R Ave Anacortes WA 98221",
    "addr:housenumber":"4008",
    "addr:postcode":"98221",
    "addr:street":"R Ave",
    "iso:country":"US",
    "sg:address":"4008 R Ave",
    "sg:city":"Anacortes",
    "sg:classifiers":[
        {
            "category":"Freight",
            "type":"Transportation"
        }
    ],
    "sg:phone":"+1 360 293 5321",
    "sg:postcode":"98221",
    "sg:province":"WA",
    "sg:tags":[
        "operator",
        "local",
        "trucking"
    ],
    "wof:name":"EDS",
    "wof:placetype":"venue"
},
  "geometry": {"coordinates":[-122.610489,48.488877],"type":"Point"}
}