{
  "type": "Feature",
  "properties": {
    "addr:full":"2915 NE 53rd St Vancouver WA 98663",
    "addr:housenumber":"2915",
    "addr:postcode":"98663",
    "addr:street":"Ne 53Rd St",
    "iso:country":"US",
    "sg:address":"2915 NE 53rd St",
    "sg:city":"Vancouver",
    "sg:classifiers":[
        {
            "category":"Professional",
            "subcategory":"Business Services",
            "type":"Services"
        }
    ],
    "sg:phone":"+1 360 737 8078",
    "sg:postcode":"98663",
    "sg:province":"WA",
    "wof:name":"Edwards Interiors",
    "wof:placetype":"venue"
},
  "geometry": {"coordinates":[-122.64484,45.660119],"type":"Point"}
}