{
  "type": "Feature",
  "properties": {
    "addr:full":"14201 42nd Ave S Seattle WA 98168",
    "addr:housenumber":"14201",
    "addr:postcode":"98168",
    "addr:street":"42Nd Ave S",
    "iso:country":"US",
    "sg:address":"14201 42nd Ave S",
    "sg:city":"Seattle",
    "sg:classifiers":[
        {
            "category":"Real Estate",
            "subcategory":"Real Estate Agent",
            "type":"Services"
        }
    ],
    "sg:phone":"+1 206 241 9322",
    "sg:postcode":"98168",
    "sg:province":"WA",
    "sg:tags":[
        "building",
        "operator",
        "apartment"
    ],
    "wof:name":"Samara Apartments Inc",
    "wof:placetype":"venue"
},
  "geometry": {"coordinates":[-122.28128,47.476619],"type":"Point"}
}