{
  "type": "Feature",
  "properties": {
    "addr:full":"11106 S Pinecroft Rd Medical Lake WA 99022",
    "addr:housenumber":"11106",
    "addr:postcode":"99022",
    "addr:street":"S Pinecroft Rd",
    "iso:country":"US",
    "sg:address":"11106 S Pinecroft Rd",
    "sg:city":"Medical Lake",
    "sg:classifiers":[
        {
            "category":"Retail",
            "subcategory":"Photofinishing",
            "type":"Services"
        }
    ],
    "sg:phone":"+1 509 299 4107",
    "sg:postcode":"99022",
    "sg:province":"WA",
    "sg:tags":[
        "laboratory"
    ],
    "wof:name":"WA 1 Hr Photo",
    "wof:placetype":"venue"
},
  "geometry": {"coordinates":[-117.647851,47.553057],"type":"Point"}
}