{
  "type": "Feature",
  "properties": {
    "addr:full":"2614 4th Ave Apt 101 Seattle WA 98121",
    "addr:housenumber":"2614;101",
    "addr:postcode":"98121",
    "addr:street":"4Th Ave Apt",
    "iso:country":"US",
    "sg:address":"2614 4th Ave Apt 101",
    "sg:city":"Seattle",
    "sg:classifiers":[
        {
            "category":"Real Estate",
            "subcategory":"Developer",
            "type":"Services"
        }
    ],
    "sg:phone":"+1 206 285 7867",
    "sg:postcode":"98121",
    "sg:province":"WA",
    "wof:name":"Cascade Crest Development",
    "wof:placetype":"venue"
},
  "geometry": {"coordinates":[-122.347256,47.617328],"type":"Point"}
}