{
  "type": "Feature",
  "properties": {
    "addr:full":"6032 California Ave SW Seattle WA 98136",
    "addr:housenumber":"6032",
    "addr:postcode":"98136",
    "addr:street":"California Ave Sw",
    "iso:country":"US",
    "sg:address":"6032 California Ave SW",
    "sg:city":"Seattle",
    "sg:classifiers":[
        {
            "category":"Restaurant",
            "type":"Food & Drink"
        }
    ],
    "sg:phone":"+1 206 932 9840",
    "sg:postcode":"98136",
    "sg:province":"WA",
    "sg:tags":[
        "eating"
    ],
    "wof:name":"Jade West Cafe",
    "wof:placetype":"venue"
},
  "geometry": {"coordinates":[-122.387118,47.546874],"type":"Point"}
}