{
  "type": "Feature",
  "properties": {
    "addr:full":"525 19th Ave E Seattle WA 98112",
    "addr:housenumber":"525",
    "addr:postcode":"98112",
    "addr:street":"19Th Ave E",
    "iso:country":"US",
    "sg:address":"525 19th Ave E",
    "sg:city":"Seattle",
    "sg:classifiers":[
        {
            "category":"Professional",
            "subcategory":"Computer Services",
            "type":"Services"
        }
    ],
    "sg:phone":"+1 206 323 0052",
    "sg:postcode":"98112",
    "sg:province":"WA",
    "sg:tags":[
        "programing",
        "custom"
    ],
    "wof:name":"Eileen K Gunn",
    "wof:placetype":"venue"
},
  "geometry": {"coordinates":[-122.307365,47.624122],"type":"Point"}
}