{
  "type": "Feature",
  "properties": {
    "addr:full":"2227 Evergreen Point Rd Medina WA 98039",
    "addr:housenumber":"2227",
    "addr:postcode":"98039",
    "addr:street":"Evergreen Point Rd",
    "iso:country":"US",
    "sg:address":"2227 Evergreen Point Rd",
    "sg:city":"Medina",
    "sg:classifiers":[
        {
            "category":"Professional",
            "type":"Services"
        }
    ],
    "sg:phone":"+1 425 453 0883",
    "sg:postcode":"98039",
    "sg:province":"WA",
    "wof:name":"Karen Handaly",
    "wof:placetype":"venue"
},
  "geometry": {"coordinates":[-122.238716,47.630856],"type":"Point"}
}