{
  "type": "Feature",
  "properties": {
    "addr:full":"120 W Front St Sumas WA 98295",
    "addr:housenumber":"120",
    "addr:postcode":"98295",
    "addr:street":"W Front St",
    "iso:country":"US",
    "sg:address":"120 W Front St",
    "sg:city":"Sumas",
    "sg:classifiers":[
        {
            "category":"Restaurant",
            "type":"Food & Drink"
        }
    ],
    "sg:phone":"+1 360 988 6400",
    "sg:postcode":"98295",
    "sg:province":"WA",
    "sg:tags":[
        "eating"
    ],
    "wof:name":"Warnies Family Restaurant",
    "wof:placetype":"venue"
},
  "geometry": {"coordinates":[-122.264653,48.99278],"type":"Point"}
}