{
  "type": "Feature",
  "properties": {
    "iso:country":"US",
    "sg:address":"7633 140th Pl NE",
    "sg:city":"Redmond",
    "sg:classifiers":[
        {
            "category":"Manufacturing",
            "subcategory":"Signs",
            "type":"Manufacturing & Wholesale Goods"
        }
    ],
    "sg:phone":"+1 425 885 5665",
    "sg:postcode":"98052",
    "sg:province":"WA",
    "sg:tags":[
        "specialty",
        "mfg"
    ],
    "wof:name":"New Designs",
    "wof:placetype":"venue"
},
  "geometry": {"coordinates":[-122.152574,47.673251],"type":"Point"}
}