{
  "type": "Feature",
  "properties": {
    "addr:full":"1920 SE Larch Ln Port Orchard WA 98366",
    "addr:housenumber":"1920",
    "addr:postcode":"98366",
    "addr:street":"Se Larch Ln",
    "iso:country":"US",
    "sg:address":"1920 SE Larch Ln",
    "sg:city":"Port Orchard",
    "sg:classifiers":[
        {
            "category":"Real Estate",
            "subcategory":"Real Estate Operator",
            "type":"Services"
        }
    ],
    "sg:phone":"+1 360 871 2040",
    "sg:postcode":"98366",
    "sg:province":"WA",
    "sg:tags":[
        "building",
        "apartment"
    ],
    "wof:name":"Village Lane Apts",
    "wof:placetype":"venue"
},
  "geometry": {"coordinates":[-122.596535,47.531449],"type":"Point"}
}