{
  "type": "Feature",
  "properties": {
    "addr:full":"4525 Martin Luther King Jr Way S Seattle WA 98108",
    "addr:housenumber":"4525",
    "addr:postcode":"98108",
    "addr:street":"Martin Luther King Jr Way S",
    "iso:country":"US",
    "sg:address":"4525 Martin Luther King Jr Way S",
    "sg:city":"Seattle",
    "sg:classifiers":[
        {
            "category":"Bars & Pubs",
            "type":"Food & Drink"
        },
        {
            "category":"Restaurant",
            "type":"Food & Drink"
        }
    ],
    "sg:phone":"+1 206 725 8879",
    "sg:postcode":"98108",
    "sg:province":"WA",
    "sg:tags":[
        "vegetarian",
        "gastropubs",
        "brunch",
        "breakfast"
    ],
    "sg:website":"www.stdames.com",
    "wof:name":"St. Dames",
    "wof:placetype":"venue"
},
  "geometry": {"coordinates":[-122.29441300000001,47.562257],"type":"Point"}
}