{
  "type": "Feature",
  "properties": {
    "addr:full":"1 N Division St Grandview WA 98930",
    "addr:housenumber":"1",
    "addr:postcode":"98930",
    "addr:street":"N Division St",
    "iso:country":"US",
    "sg:address":"1 N Division St",
    "sg:city":"Grandview",
    "sg:classifiers":[
        {
            "category":"Restaurant",
            "type":"Food & Drink"
        }
    ],
    "sg:phone":"+1 509 882 1551",
    "sg:postcode":"98930",
    "sg:province":"WA",
    "wof:name":"El Guerrero Restaurante",
    "wof:placetype":"venue"
},
  "geometry": {"coordinates":[-119.901961,46.256537],"type":"Point"}
}