{
  "type": "Feature",
  "properties": {
    "addr:full":"2205 51st Ave E Ste 300 Fife WA 98424",
    "addr:housenumber":"2205",
    "addr:postcode":"98424",
    "addr:street":"51St Ave E Ste 300",
    "iso:country":"US",
    "sg:address":"2205 51st Ave E Ste 300",
    "sg:city":"Fife",
    "sg:classifiers":[
        {
            "category":"Transit Center",
            "subcategory":"Freight",
            "type":"Transportation"
        },
        {
            "category":"Freight",
            "type":"Transportation"
        }
    ],
    "sg:phone":"+1 253 922 9100",
    "sg:postcode":"98424",
    "sg:province":"WA",
    "sg:tags":[
        "trucking-motor",
        "trucking"
    ],
    "sg:website":"http://www.washingtonarchives.net",
    "wof:name":"Washington Archives Management",
    "wof:placetype":"venue"
},
  "geometry": {"coordinates":[-122.361251,47.23762],"type":"Point"}
}