{
  "type": "Feature",
  "properties": {
    "addr:full":"239 Zandecki Rd Chehalis WA 98532",
    "addr:housenumber":"239",
    "addr:postcode":"98532",
    "addr:street":"Zandecki Rd",
    "iso:country":"US",
    "sg:address":"239 Zandecki Rd",
    "sg:city":"Chehalis",
    "sg:classifiers":[
        {
            "category":"Utilities",
            "subcategory":"Electric",
            "type":"Services"
        }
    ],
    "sg:phone":"+1 360 262 3365",
    "sg:postcode":"98532",
    "sg:province":"WA",
    "sg:tags":[
        "transmission",
        "natural",
        "gas"
    ],
    "wof:name":"Puget Sound Energy",
    "wof:placetype":"venue"
},
  "geometry": {"coordinates":[-122.831155,46.535861],"type":"Point"}
}