{
  "type": "Feature",
  "properties": {
    "addr:full":"3411 Capitol Blvd S Olympia WA 98501",
    "addr:housenumber":"3411",
    "addr:postcode":"98501",
    "addr:street":"Capitol Blvd S",
    "iso:country":"US",
    "sg:address":"3411 Capitol Blvd S",
    "sg:city":"Olympia",
    "sg:classifiers":[
        {
            "category":"Social Services",
            "subcategory":"Job Training",
            "type":"Services"
        }
    ],
    "sg:phone":"+1 360 754 7544",
    "sg:postcode":"98501",
    "sg:province":"WA",
    "wof:name":"Turner Jeff",
    "wof:placetype":"venue"
},
  "geometry": {"coordinates":[-122.90066899999999,47.017428],"type":"Point"}
}