{
  "type": "Feature",
  "properties": {
    "addr:full":"4402 N Wall St Spokane WA 99205",
    "addr:housenumber":"4402",
    "addr:postcode":"99205",
    "addr:street":"N Wall St",
    "iso:country":"US",
    "sg:address":"4402 N Wall St",
    "sg:city":"Spokane",
    "sg:classifiers":[
        {
            "category":"Personal",
            "subcategory":"Beauty Salon",
            "type":"Services"
        }
    ],
    "sg:phone":"+1 509 487 4418",
    "sg:postcode":"99205",
    "sg:province":"WA",
    "wof:name":"Style & The City",
    "wof:placetype":"venue"
},
  "geometry": {"coordinates":[-117.421952,47.698442],"type":"Point"}
}