{
  "type": "Feature",
  "properties": {
    "iso:country":"US",
    "sg:address":"1722 NW 63rd St",
    "sg:city":"Seattle",
    "sg:classifiers":[
        {
            "category":"Building & Trades",
            "subcategory":"Construction",
            "type":"Services"
        }
    ],
    "sg:phone":"+1 206 706 9219",
    "sg:postcode":"98107",
    "sg:province":"WA",
    "sg:tags":[
        "house",
        "general",
        "contractor"
    ],
    "wof:name":"Ashley Remodeling & Constructi",
    "wof:placetype":"venue"
},
  "geometry": {"coordinates":[-122.381963,47.674629],"type":"Point"}
}