{
  "type": "Feature",
  "properties": {
    "addr:full":"6208 NE 17th Ave Vancouver WA 98665",
    "addr:housenumber":"6208",
    "addr:postcode":"98665",
    "addr:street":"Ne 17Th Ave",
    "iso:country":"US",
    "sg:address":"6208 NE 17th Ave",
    "sg:city":"Vancouver",
    "sg:classifiers":[
        {
            "category":"Real Estate",
            "subcategory":"Real Estate Operator",
            "type":"Services"
        }
    ],
    "sg:phone":"+1 360 695 9781",
    "sg:postcode":"98665",
    "sg:province":"WA",
    "sg:tags":[
        "apartment"
    ],
    "wof:name":"Evergreen Ridge",
    "wof:placetype":"venue"
},
  "geometry": {"coordinates":[-122.654276,45.666914],"type":"Point"}
}