{
  "type": "Feature",
  "properties": {
    "addr:full":"18408 Angeline Ave NE Suquamish WA 98392",
    "addr:housenumber":"18408",
    "addr:postcode":"98392",
    "addr:street":"Angeline Ave Ne",
    "iso:country":"US",
    "sg:address":"18408 Angeline Ave NE",
    "sg:city":"Suquamish",
    "sg:classifiers":[
        {
            "category":"Restaurant",
            "type":"Food & Drink"
        }
    ],
    "sg:phone":"+1 360 598 5398",
    "sg:postcode":"98392",
    "sg:province":"WA",
    "sg:tags":[
        "italian",
        "pizza"
    ],
    "wof:name":"Bella Luna Pizzeria",
    "wof:placetype":"venue"
},
  "geometry": {"coordinates":[-122.551773,47.729853],"type":"Point"}
}