{
  "type": "Feature",
  "properties": {
    "addr:full":"25 Stillson Rd Mc Cleary WA 98557",
    "addr:housenumber":"25",
    "addr:postcode":"98557",
    "addr:street":"Stillson Rd",
    "iso:country":"US",
    "sg:address":"25 Stillson Rd",
    "sg:city":"Mc Cleary",
    "sg:classifiers":[
        {
            "category":"Retail",
            "subcategory":"Auto Repair",
            "type":"Services"
        }
    ],
    "sg:phone":"+1 360 495 3763",
    "sg:postcode":"98557",
    "sg:province":"WA",
    "sg:tags":[
        "automotive"
    ],
    "wof:name":"Darrins Automotive & Smal",
    "wof:placetype":"venue"
},
  "geometry": {"coordinates":[-123.308013,47.05146],"type":"Point"}
}