{
  "type": "Feature",
  "properties": {
    "addr:full":"6641 Flora Ave S Seattle WA 98108",
    "addr:housenumber":"6641",
    "addr:postcode":"98108",
    "addr:street":"Flora Ave S",
    "iso:country":"US",
    "sg:address":"6641 Flora Ave S",
    "sg:city":"Seattle",
    "sg:classifiers":[
        {
            "category":"Utilities",
            "subcategory":"Telephone",
            "type":"Services"
        }
    ],
    "sg:phone":"+1 206 764 5037",
    "sg:postcode":"98108",
    "sg:province":"WA",
    "sg:tags":[
        "communications"
    ],
    "wof:name":"R Citinet Inc",
    "wof:placetype":"venue"
},
  "geometry": {"coordinates":[-122.321003,47.541491],"type":"Point"}
}