{
  "type": "Feature",
  "properties": {
    "addr:full":"305 SE 252nd Ave Camas WA 98607",
    "addr:housenumber":"305",
    "addr:postcode":"98607",
    "addr:street":"Se 252Nd Ave",
    "iso:country":"US",
    "sg:address":"305 SE 252nd Ave",
    "sg:city":"Camas",
    "sg:phone":"+1 360 834 2028",
    "sg:postcode":"98607",
    "sg:province":"WA",
    "sg:tags":[
        "farm",
        "field",
        "crop"
    ],
    "wof:name":"Cisneyland LLC",
    "wof:placetype":"venue"
},
  "geometry": {"coordinates":[-122.41374399999999,45.61909],"type":"Point"}
}