{
  "type": "Feature",
  "properties": {
    "iso:country":"US",
    "sg:address":"1477 State Rte 6",
    "sg:city":"Chehalis",
    "sg:classifiers":[
        {
            "category":"Building & Trades",
            "subcategory":"Landscaping Services",
            "type":"Services"
        }
    ],
    "sg:phone":"+1 360 748 3754",
    "sg:postcode":"98532",
    "sg:province":"WA",
    "wof:name":"Stricklands Blcbry & Brsh REM",
    "wof:placetype":"venue"
},
  "geometry": {"coordinates":[-123.03860400000001,46.634155],"type":"Point"}
}