{
  "type": "Feature",
  "properties": {
    "addr:full":"17110 140th Ave NE Woodinville WA 98072",
    "addr:housenumber":"17110",
    "addr:postcode":"98072",
    "addr:street":"140Th Ave Ne",
    "iso:country":"US",
    "sg:address":"17110 140th Ave NE",
    "sg:city":"Woodinville",
    "sg:classifiers":[
        {
            "category":"Social Services",
            "subcategory":"Child Care",
            "type":"Services"
        }
    ],
    "sg:phone":"+1 425 483 1672",
    "sg:postcode":"98072",
    "sg:province":"WA",
    "sg:tags":[
        "kindergarten",
        "academic",
        "school"
    ],
    "sg:website":"www.bellevuechristian.org",
    "wof:name":"Bellevue Christian Preschool",
    "wof:placetype":"venue"
},
  "geometry": {"coordinates":[-122.152653,47.752807],"type":"Point"}
}