{
  "type": "Feature",
  "properties": {
    "iso:country":"US",
    "sg:address":"10407 324th Pl SE",
    "sg:city":"Issaquah",
    "sg:classifiers":[
        {
            "category":"Recreation",
            "type":"Entertainment"
        }
    ],
    "sg:phone":"+1 425 222 5598",
    "sg:postcode":"98027",
    "sg:province":"WA",
    "sg:tags":[
        "amusement"
    ],
    "wof:name":"Mountain To Sound Motorcycle",
    "wof:placetype":"venue"
},
  "geometry": {"coordinates":[-121.9093,47.507199],"type":"Point"}
}