{
  "type": "Feature",
  "properties": {
    "iso:country":"US",
    "sg:address":"1846 Main St",
    "sg:city":"Ferndale",
    "sg:classifiers":[
        {
            "category":"Food & Beverages",
            "subcategory":"Groceries & Convenience Stores",
            "type":"Retail Goods"
        }
    ],
    "sg:phone":"+1 360 384 5490",
    "sg:postcode":"98248",
    "sg:province":"WA",
    "wof:name":"Express Lane",
    "wof:placetype":"venue"
},
  "geometry": {"coordinates":[-122.585618,48.844723],"type":"Point"}
}