{
  "type": "Feature",
  "properties": {
    "addr:full":"2571 Elmway St Okanogan WA 98840",
    "addr:housenumber":"2571",
    "addr:postcode":"98840",
    "addr:street":"Elmway St",
    "iso:country":"US",
    "sg:address":"2571 Elmway St",
    "sg:city":"Okanogan",
    "sg:classifiers":[
        {
            "category":"Social Services",
            "subcategory":"Child Care",
            "type":"Services"
        }
    ],
    "sg:phone":"+1 509 422 5728",
    "sg:postcode":"98840",
    "sg:province":"WA",
    "sg:tags":[
        "day"
    ],
    "wof:name":"Willow Tree Child Care Ctr",
    "wof:placetype":"venue"
},
  "geometry": {"coordinates":[-119.551356,48.389574],"type":"Point"}
}