{
  "type": "Feature",
  "properties": {
    "addr:full":"495 SE Evans Ln Issaquah WA 98027",
    "addr:housenumber":"495",
    "addr:postcode":"98027",
    "addr:street":"Se Evans Ln",
    "iso:country":"US",
    "sg:address":"495 SE Evans Ln",
    "sg:city":"Issaquah",
    "sg:classifiers":[
        {
            "category":"Building & Trades",
            "subcategory":"Cleaning & Sanitation",
            "type":"Services"
        }
    ],
    "sg:phone":"+1 425 837 0216",
    "sg:postcode":"98027",
    "sg:province":"WA",
    "sg:tags":[
        "maintenance"
    ],
    "wof:name":"Michaelsoft Window Cleaning",
    "wof:placetype":"venue"
},
  "geometry": {"coordinates":[-122.029661,47.525857],"type":"Point"}
}