{
  "type": "Feature",
  "properties": {
    "addr:full":"40418 NE 5th Ave Woodland WA 98674",
    "addr:housenumber":"40418",
    "addr:postcode":"98674",
    "addr:street":"Ne 5Th Ave",
    "iso:country":"US",
    "sg:address":"40418 NE 5th Ave",
    "sg:city":"Woodland",
    "sg:classifiers":[
        {
            "category":"Professional",
            "subcategory":"Computer Services",
            "type":"Services"
        }
    ],
    "sg:phone":"+1 360 263 4897",
    "sg:postcode":"98674",
    "sg:province":"WA",
    "sg:tags":[
        "technical",
        "assistance",
        "support"
    ],
    "sg:website":"http://www.greenpastures-e.com",
    "wof:name":"Green Pastures Enterprise",
    "wof:placetype":"venue"
},
  "geometry": {"coordinates":[-122.66713900000001,45.913214],"type":"Point"}
}