{
  "type": "Feature",
  "properties": {
    "addr:full":"10622 Bridgeport Way SW Lakewood WA 98499",
    "addr:housenumber":"10622",
    "addr:postcode":"98499",
    "addr:street":"Bridgeport Way Sw",
    "iso:country":"US",
    "sg:address":"10622 Bridgeport Way SW",
    "sg:city":"Lakewood",
    "sg:classifiers":[
        {
            "category":"Personal",
            "subcategory":"Beauty Salon",
            "type":"Services"
        }
    ],
    "sg:phone":"+1 253 582 8304",
    "sg:postcode":"98499",
    "sg:province":"WA",
    "sg:website":"http://www.saloninfinity.com",
    "wof:name":"Salon Infinity",
    "wof:placetype":"venue"
},
  "geometry": {"coordinates":[-122.504811,47.160495],"type":"Point"}
}