{
  "type": "Feature",
  "properties": {
    "addr:full":"415 Alder Ave Sumner WA 98390",
    "addr:housenumber":"415",
    "addr:postcode":"98390",
    "addr:street":"Alder Ave",
    "iso:country":"US",
    "sg:address":"415 Alder Ave",
    "sg:city":"Sumner",
    "sg:classifiers":[
        {
            "category":"Health Services",
            "subcategory":"Clinic",
            "type":"Services"
        },
        {
            "category":"Health Services",
            "subcategory":"Health Practitioner",
            "type":"Services"
        }
    ],
    "sg:phone":"+1 253 862 2575",
    "sg:postcode":"98390",
    "sg:province":"WA",
    "sg:tags":[
        "therapist",
        "therapy",
        "physical"
    ],
    "wof:name":"Airport Physical Therapy, Inc.",
    "wof:placetype":"venue"
},
  "geometry": {"coordinates":[-122.240587,47.196868],"type":"Point"}
}