{
  "type": "Feature",
  "properties": {
    "addr:full":"701 Pike Street Suite 1500 Seattle WA 98101",
    "addr:housenumber":"701",
    "addr:postcode":"98101",
    "addr:street":"Pike Street Suite 1500",
    "iso:country":"US",
    "sg:address":"701 Pike Street Suite 1500",
    "sg:city":"Seattle",
    "sg:classifiers":[
        {
            "category":"Professional",
            "subcategory":"Accounting & Tax Preparation",
            "type":"Services"
        }
    ],
    "sg:phone":"+1 206 623 1121",
    "sg:postcode":"98101",
    "sg:province":"WA",
    "sg:tags":[
        "accountant"
    ],
    "wof:name":"Grant Thornton Llp",
    "wof:placetype":"venue"
},
  "geometry": {"coordinates":[-122.333353,47.611626],"type":"Point"}
}