{
  "type": "Feature",
  "properties": {
    "addr:full":"222 S Wenatchee Ave Wenatchee WA 98801",
    "addr:housenumber":"222",
    "addr:postcode":"98801",
    "addr:street":"S Wenatchee Ave",
    "iso:country":"US",
    "sg:address":"222 S Wenatchee Ave",
    "sg:city":"Wenatchee",
    "sg:classifiers":[
        {
            "category":"Shopping",
            "subcategory":"Used Merchandise",
            "type":"Retail Goods"
        }
    ],
    "sg:phone":"+1 509 662 9713",
    "sg:postcode":"98801",
    "sg:province":"WA",
    "sg:tags":[
        "sport",
        "music"
    ],
    "wof:name":"Valley Pawnshop",
    "wof:placetype":"venue"
},
  "geometry": {"coordinates":[-120.30868599999999,47.421179],"type":"Point"}
}