{
  "type": "Feature",
  "properties": {
    "addr:full":"2755 Northup Way Bellevue WA 98004",
    "addr:housenumber":"2755",
    "addr:postcode":"98004",
    "addr:street":"Northup Way",
    "iso:country":"US",
    "sg:address":"2755 Northup Way",
    "sg:city":"Bellevue",
    "sg:classifiers":[
        {
            "category":"Manufacturing",
            "subcategory":"Tools & Machinery",
            "type":"Manufacturing & Wholesale Goods"
        }
    ],
    "sg:phone":"+1 425 260 4678",
    "sg:postcode":"98004",
    "sg:province":"WA",
    "sg:tags":[
        "mfg",
        "laser",
        "system",
        "custom"
    ],
    "wof:name":"Laservision",
    "wof:placetype":"venue"
},
  "geometry": {"coordinates":[-122.190119,47.63642],"type":"Point"}
}