{
  "type": "Feature",
  "properties": {
    "addr:full":"409 7th Avenue S Seattle WA 98104",
    "addr:housenumber":"409",
    "addr:postcode":"98104",
    "addr:street":"7Th Avenue S",
    "iso:country":"US",
    "sg:address":"409 7th Avenue S",
    "sg:city":"Seattle",
    "sg:classifiers":[
        {
            "category":"Arts & Performance",
            "subcategory":"Arts Center",
            "type":"Entertainment"
        }
    ],
    "sg:phone":"+1 206 340 1445",
    "sg:postcode":"98104",
    "sg:province":"WA",
    "sg:tags":[
        "performing"
    ],
    "wof:name":"Northwest Asian American Theatre",
    "wof:placetype":"venue"
},
  "geometry": {"coordinates":[-122.32358499999999,47.598883],"type":"Point"}
}