{
  "type": "Feature",
  "properties": {
    "iso:country":"US",
    "sg:address":"3803 NE 199th St",
    "sg:city":"Ridgefield",
    "sg:classifiers":[
        {
            "category":"Farming",
            "subcategory":"Farm",
            "type":"Manufacturing & Wholesale Goods"
        }
    ],
    "sg:phone":"+1 360 887 4359",
    "sg:postcode":"98642",
    "sg:province":"WA",
    "sg:tags":[
        "crop",
        "general"
    ],
    "wof:name":"Pioneer Grange 901",
    "wof:placetype":"venue"
},
  "geometry": {"coordinates":[-122.632637,45.765224],"type":"Point"}
}