{
  "type": "Feature",
  "properties": {
    "addr:full":"205 S Columbus Ave Goldendale WA 98620",
    "addr:housenumber":"205",
    "addr:postcode":"98620",
    "addr:street":"S Columbus Ave",
    "iso:country":"US",
    "sg:address":"205 S Columbus Ave",
    "sg:city":"Goldendale",
    "sg:classifiers":[
        {
            "category":"Government",
            "subcategory":"Office",
            "type":"Public Place"
        }
    ],
    "sg:phone":"+1 509 773 5011",
    "sg:postcode":"98620",
    "sg:province":"WA",
    "wof:name":"Courthouse Custodian",
    "wof:placetype":"venue"
},
  "geometry": {"coordinates":[-120.822683,45.821398],"type":"Point"}
}