{
  "type": "Feature",
  "properties": {
    "addr:full":"4870 Yelm Hwy SE Lacey WA 98503",
    "addr:housenumber":"4870",
    "addr:postcode":"98503",
    "addr:street":"Yelm Hwy Se",
    "iso:country":"US",
    "sg:address":"4870 Yelm Hwy SE",
    "sg:city":"Lacey",
    "sg:classifiers":[
        {
            "category":"Restaurant",
            "type":"Food & Drink"
        }
    ],
    "sg:phone":"+1 360 493 2090",
    "sg:postcode":"98503",
    "sg:province":"WA",
    "sg:tags":[
        "pizza"
    ],
    "wof:name":"Farrelli's Pizza & Pool",
    "wof:placetype":"venue"
},
  "geometry": {"coordinates":[-122.819104,46.9962],"type":"Point"}
}