{
  "type": "Feature",
  "properties": {
    "addr:full":"16209 SE McGillivray Blvd Vancouver WA 98683",
    "addr:housenumber":"16209",
    "addr:postcode":"98683",
    "addr:street":"Se Mcgillivray Blvd",
    "iso:country":"US",
    "sg:address":"16209 SE McGillivray Blvd",
    "sg:city":"Vancouver",
    "sg:classifiers":[
        {
            "category":"Professional",
            "type":"Services"
        }
    ],
    "sg:phone":"+1 360 254 0801",
    "sg:postcode":"98683",
    "sg:province":"WA",
    "sg:tags":[
        "establishment"
    ],
    "wof:name":"Bean Bobby",
    "wof:placetype":"venue"
},
  "geometry": {"coordinates":[-122.5047,45.604274],"type":"Point"}
}