{
  "type": "Feature",
  "properties": {
    "addr:full":"1014 S 16th Ave Yakima WA 98902",
    "addr:housenumber":"1014",
    "addr:postcode":"98902",
    "addr:street":"S 16Th Ave",
    "iso:country":"US",
    "sg:address":"1014 S 16th Ave",
    "sg:city":"Yakima",
    "sg:classifiers":[
        {
            "category":"Real Estate",
            "subcategory":"Real Estate Agent",
            "type":"Services"
        },
        {
            "category":"Building & Trades",
            "subcategory":"Construction",
            "type":"Services"
        }
    ],
    "sg:phone":"+1 509 453 5566",
    "sg:postcode":"98902",
    "sg:province":"WA",
    "sg:tags":[
        "home",
        "speculative"
    ],
    "wof:name":"Emhoff Group Inc",
    "wof:placetype":"venue"
},
  "geometry": {"coordinates":[-120.530415,46.5855],"type":"Point"}
}