{
  "type": "Feature",
  "properties": {
    "addr:full":"2310 NE 45th Cir Vancouver WA 98663",
    "addr:housenumber":"2310",
    "addr:postcode":"98663",
    "addr:street":"Ne 45Th Cir",
    "iso:country":"US",
    "sg:address":"2310 NE 45th Cir",
    "sg:city":"Vancouver",
    "sg:classifiers":[
        {
            "category":"Health Services",
            "subcategory":"Nursing And Care Facility",
            "type":"Services"
        }
    ],
    "sg:phone":"+1 360 696 0825",
    "sg:postcode":"98663",
    "sg:province":"WA",
    "wof:name":"Garden View Lafh",
    "wof:placetype":"venue"
},
  "geometry": {"coordinates":[-122.646576,45.653672],"type":"Point"}
}