{
  "type": "Feature",
  "properties": {
    "addr:full":"5613 4th Ave S Seattle WA 98108",
    "addr:housenumber":"5613",
    "addr:postcode":"98108",
    "addr:street":"4Th Ave S",
    "iso:country":"US",
    "sg:address":"5613 4th Ave S",
    "sg:city":"Seattle",
    "sg:classifiers":[
        {
            "category":"Bars & Pubs",
            "subcategory":"Lounge",
            "type":"Food & Drink"
        },
        {
            "category":"Bars & Pubs",
            "subcategory":"Dive Bar",
            "type":"Food & Drink"
        }
    ],
    "sg:phone":"+1 206 762 3964",
    "sg:postcode":"98108",
    "sg:province":"WA",
    "sg:tags":[
        "karaoke"
    ],
    "wof:name":"Marco Polo Bar & Grill",
    "wof:placetype":"venue"
},
  "geometry": {"coordinates":[-122.32986699999999,47.552124],"type":"Point"}
}