{
  "type": "Feature",
  "properties": {
    "addr:full":"3544 Bay Rd Ferndale WA 98248",
    "addr:housenumber":"3544",
    "addr:postcode":"98248",
    "addr:street":"Bay Rd",
    "iso:country":"US",
    "sg:address":"3544 Bay Rd",
    "sg:city":"Ferndale",
    "sg:phone":"+1 360 366 3611",
    "sg:postcode":"98248",
    "sg:province":"WA",
    "sg:tags":[
        "oil"
    ],
    "wof:name":"Lind Fuel Co",
    "wof:placetype":"venue"
},
  "geometry": {"coordinates":[-122.67684199999999,48.906537],"type":"Point"}
}