{
  "type": "Feature",
  "properties": {
    "addr:full":"17600 Talbot Rd S Renton WA 98055",
    "addr:housenumber":"17600",
    "addr:postcode":"98055",
    "addr:street":"Talbot Rd S",
    "iso:country":"US",
    "sg:address":"17600 Talbot Rd S",
    "sg:city":"Renton",
    "sg:classifiers":[
        {
            "category":"Health Services",
            "subcategory":"Doctor",
            "type":"Services"
        }
    ],
    "sg:phone":"+1 425 226 9636",
    "sg:postcode":"98055",
    "sg:province":"WA",
    "sg:tags":[
        "medical"
    ],
    "wof:name":"Andy J Sands MD",
    "wof:placetype":"venue"
},
  "geometry": {"coordinates":[-122.211516,47.443909],"type":"Point"}
}