{
  "type": "Feature",
  "properties": {
    "addr:full":"5612 Ocean Beach Hwy Longview WA 98632",
    "addr:housenumber":"5612",
    "addr:postcode":"98632",
    "addr:street":"Ocean Beach Hwy",
    "iso:country":"US",
    "sg:address":"5612 Ocean Beach Hwy",
    "sg:city":"Longview",
    "sg:classifiers":[
        {
            "category":"Social Services",
            "subcategory":"Child Care",
            "type":"Services"
        }
    ],
    "sg:phone":"+1 360 423 9466",
    "sg:postcode":"98632",
    "sg:province":"WA",
    "wof:name":"Winners Learning Ctr West",
    "wof:placetype":"venue"
},
  "geometry": {"coordinates":[-123.016434,46.171936],"type":"Point"}
}