{
  "type": "Feature",
  "properties": {
    "addr:full":"3003 146th Ave E Sumner WA 98390",
    "addr:housenumber":"3003",
    "addr:postcode":"98390",
    "addr:street":"146Th Ave E",
    "iso:country":"US",
    "sg:address":"3003 146th Ave E",
    "sg:city":"Sumner",
    "sg:classifiers":[
        {
            "category":"Manufacturing",
            "subcategory":"Tools & Machinery",
            "type":"Manufacturing & Wholesale Goods"
        }
    ],
    "sg:phone":"+1 253 862 7980",
    "sg:postcode":"98390",
    "sg:province":"WA",
    "wof:name":"Comm Tools Inc",
    "wof:placetype":"venue"
},
  "geometry": {"coordinates":[-122.234628,47.229611],"type":"Point"}
}