{
  "type": "Feature",
  "properties": {
    "addr:full":"9165 Willows Rd NE Redmond WA 98052",
    "addr:housenumber":"9165",
    "addr:postcode":"98052",
    "addr:street":"Willows Rd Ne",
    "iso:country":"US",
    "sg:address":"9165 Willows Rd NE",
    "sg:city":"Redmond",
    "sg:classifiers":[
        {
            "category":"Retail",
            "subcategory":"Auto Repair",
            "type":"Services"
        }
    ],
    "sg:phone":"+1 425 885 4165",
    "sg:postcode":"98052",
    "sg:province":"WA",
    "sg:tags":[
        "automotive"
    ],
    "wof:name":"A A A Radiator",
    "wof:placetype":"venue"
},
  "geometry": {"coordinates":[-122.145408,47.685204],"type":"Point"}
}