{
  "type": "Feature",
  "properties": {
    "iso:country":"US",
    "sg:address":"13525 51st Ave NE",
    "sg:city":"Marysville",
    "sg:classifiers":[
        {
            "category":"Education",
            "subcategory":"School",
            "type":"Public Place"
        }
    ],
    "sg:phone":"+1 360 653 0640",
    "sg:postcode":"98271",
    "sg:province":"WA",
    "wof:name":"Shoultes Elementary School",
    "wof:placetype":"venue"
},
  "geometry": {"coordinates":[-122.162408,48.118444],"type":"Point"}
}