{
  "type": "Feature",
  "properties": {
    "addr:full":"1594 Mukilteo Speedway Mukilteo WA 98275",
    "addr:housenumber":"1594",
    "addr:postcode":"98275",
    "addr:street":"Mukilteo Speedway",
    "iso:country":"US",
    "sg:address":"1594 Mukilteo Speedway",
    "sg:city":"Mukilteo",
    "sg:classifiers":[
        {
            "category":"Building & Trades",
            "subcategory":"Construction",
            "type":"Services"
        }
    ],
    "sg:phone":"+1 425 327 8215",
    "sg:postcode":"98275",
    "sg:province":"WA",
    "sg:tags":[
        "tile-contractors"
    ],
    "wof:name":"Alexs Distinctive Tile Inc",
    "wof:placetype":"venue"
},
  "geometry": {"coordinates":[-122.306147,47.936658],"type":"Point"}
}