{
  "type": "Feature",
  "properties": {
    "addr:full":"1201 Division Ave Tacoma WA 98403",
    "addr:housenumber":"1201",
    "addr:postcode":"98403",
    "addr:street":"Division Ave",
    "iso:country":"US",
    "sg:address":"1201 Division Ave",
    "sg:city":"Tacoma",
    "sg:classifiers":[
        {
            "category":"Restaurant",
            "type":"Food & Drink"
        }
    ],
    "sg:phone":"+1 253 272 4800",
    "sg:postcode":"98403",
    "sg:province":"WA",
    "sg:tags":[
        "eating"
    ],
    "wof:name":"Frisko Freeze Inc",
    "wof:placetype":"venue"
},
  "geometry": {"coordinates":[-122.456349,47.259418],"type":"Point"}
}