{
  "type": "Feature",
  "properties": {
    "iso:country":"US",
    "sg:address":"415 W Republican St",
    "sg:city":"Seattle",
    "sg:classifiers":[
        {
            "category":"Real Estate",
            "subcategory":"Real Estate Agent",
            "type":"Services"
        }
    ],
    "sg:phone":"+1 206 284 3356",
    "sg:postcode":"98119",
    "sg:province":"WA",
    "wof:name":"Balfour Co",
    "wof:placetype":"venue"
},
  "geometry": {"coordinates":[-122.36312700000001,47.623222],"type":"Point"}
}