{
  "type": "Feature",
  "properties": {
    "addr:full":"1108 Cole St Enumclaw WA 98022",
    "addr:housenumber":"1108",
    "addr:postcode":"98022",
    "addr:street":"Cole St",
    "iso:country":"US",
    "sg:address":"1108 Cole St",
    "sg:city":"Enumclaw",
    "sg:classifiers":[
        {
            "category":"Insurance",
            "subcategory":"Hazard Insurance",
            "type":"Services"
        }
    ],
    "sg:phone":"+1 360 825 2031",
    "sg:postcode":"98022",
    "sg:province":"WA",
    "sg:website":"http://statefarm.mqgroup.com/url.asp?usr=472763",
    "wof:name":"State Farm Insurance Agent-Tony Truax Insurance Agency Inc",
    "wof:placetype":"venue"
},
  "geometry": {"coordinates":[-121.993309,47.200116],"type":"Point"}
}