{
  "type": "Feature",
  "properties": {
    "addr:full":"808 Ave A Snohomish WA 98290",
    "addr:housenumber":"808",
    "addr:postcode":"98290",
    "addr:street":"Ave A Snohomish",
    "iso:country":"US",
    "sg:address":"808 Ave A",
    "sg:city":"Snohomish",
    "sg:classifiers":[
        {
            "category":"Retail",
            "subcategory":"Laundry & Dry Cleaning",
            "type":"Services"
        }
    ],
    "sg:phone":"+1 360 563 2809",
    "sg:postcode":"98290",
    "sg:province":"WA",
    "sg:tags":[
        "drycleaning",
        "plant"
    ],
    "wof:name":"Quality Cleaners",
    "wof:placetype":"venue"
},
  "geometry": {"coordinates":[-122.093098,47.922686],"type":"Point"}
}