{
  "type": "Feature",
  "properties": {
    "addr:full":"125 112th St SE Everett WA 98208",
    "addr:housenumber":"125",
    "addr:postcode":"98208",
    "addr:street":"112Th St Se",
    "iso:country":"US",
    "sg:address":"125 112th St SE",
    "sg:city":"Everett",
    "sg:classifiers":[
        {
            "category":"Building & Trades",
            "subcategory":"Construction",
            "type":"Services"
        }
    ],
    "sg:phone":"+1 425 355 1125",
    "sg:postcode":"98208",
    "sg:province":"WA",
    "sg:tags":[
        "concrete",
        "contractor"
    ],
    "wof:name":"Leducs Concrete Co",
    "wof:placetype":"venue"
},
  "geometry": {"coordinates":[-122.23127599999999,47.89656],"type":"Point"}
}