{
  "type": "Feature",
  "properties": {
    "addr:full":"4473 Tolt River Rd NE Carnation WA 98014",
    "addr:housenumber":"4473",
    "addr:postcode":"98014",
    "addr:street":"Tolt River Rd Ne",
    "iso:country":"US",
    "sg:address":"4473 Tolt River Rd NE",
    "sg:city":"Carnation",
    "sg:classifiers":[
        {
            "category":"Personal",
            "subcategory":"Barber",
            "type":"Services"
        }
    ],
    "sg:phone":"+1 425 333 6678",
    "sg:postcode":"98014",
    "sg:province":"WA",
    "wof:name":"Luda's Barber Shop",
    "wof:placetype":"venue"
},
  "geometry": {"coordinates":[-121.88065899999999,47.648719],"type":"Point"}
}