{
  "type": "Feature",
  "properties": {
    "addr:full":"8817 E Mission Ave Spokane Valley WA 99212",
    "addr:housenumber":"8817",
    "addr:postcode":"99212",
    "addr:street":"E Mission Ave",
    "iso:country":"US",
    "sg:address":"8817 E Mission Ave",
    "sg:city":"Spokane Valley",
    "sg:classifiers":[
        {
            "category":"Banks & Credit Unions",
            "subcategory":"Bank",
            "type":"Services"
        }
    ],
    "sg:phone":"+1 509 924 8000",
    "sg:postcode":"99212",
    "sg:province":"WA",
    "sg:tags":[
        "loan",
        "real estate"
    ],
    "wof:name":"Major Mortgage",
    "wof:placetype":"venue"
},
  "geometry": {"coordinates":[-117.282836,47.67156],"type":"Point"}
}