{
  "type": "Feature",
  "properties": {
    "addr:full":"21616 SE 269th St Maple Valley WA 98038",
    "addr:housenumber":"21616",
    "addr:postcode":"98038",
    "addr:street":"Se 269Th St",
    "iso:country":"US",
    "sg:address":"21616 SE 269th St",
    "sg:city":"Maple Valley",
    "sg:classifiers":[
        {
            "category":"Professional",
            "subcategory":"Computer Services",
            "type":"Services"
        }
    ],
    "sg:phone":"+1 425 413 9105",
    "sg:postcode":"98038",
    "sg:province":"WA",
    "sg:tags":[
        "programing",
        "custom"
    ],
    "wof:name":"Exclusive Touch",
    "wof:placetype":"venue"
},
  "geometry": {"coordinates":[-122.051164,47.36078],"type":"Point"}
}