{
  "type": "Feature",
  "properties": {
    "addr:full":"1214 S Jefferson Ave Moses Lake WA 98837",
    "addr:housenumber":"1214",
    "addr:postcode":"98837",
    "addr:street":"S Jefferson Ave",
    "iso:country":"US",
    "sg:address":"1214 S Jefferson Ave",
    "sg:city":"Moses Lake",
    "sg:classifiers":[
        {
            "category":"Building & Trades",
            "subcategory":"Cleaning & Sanitation",
            "type":"Services"
        }
    ],
    "sg:phone":"+1 509 766 8921",
    "sg:postcode":"98837",
    "sg:province":"WA",
    "sg:tags":[
        "janitor"
    ],
    "wof:name":"Nature's Best Janitorial",
    "wof:placetype":"venue"
},
  "geometry": {"coordinates":[-119.27091900000001,47.11795],"type":"Point"}
}