{
  "type": "Feature",
  "properties": {
    "addr:full":"1507 Willowbrook Pl Bellingham WA 98229",
    "addr:housenumber":"1507",
    "addr:postcode":"98229",
    "addr:street":"Willowbrook Pl",
    "iso:country":"US",
    "sg:address":"1507 Willowbrook Pl",
    "sg:city":"Bellingham",
    "sg:classifiers":[
        {
            "category":"Home & Garden",
            "subcategory":"Home Furnishings",
            "type":"Retail Goods"
        }
    ],
    "sg:phone":"+1 360 671 5335",
    "sg:postcode":"98229",
    "sg:province":"WA",
    "sg:tags":[
        "curtain",
        "made",
        "drapery"
    ],
    "wof:name":"Lyn's Draperies",
    "wof:placetype":"venue"
},
  "geometry": {"coordinates":[-122.416134,48.750315],"type":"Point"}
}