{
  "type": "Feature",
  "properties": {
    "addr:full":"23006 13th Dr SE Bothell WA 98021",
    "addr:housenumber":"23006",
    "addr:postcode":"98021",
    "addr:street":"13Th Dr Se",
    "iso:country":"US",
    "sg:address":"23006 13th Dr SE",
    "sg:city":"Bothell",
    "sg:classifiers":[
        {
            "category":"Education",
            "subcategory":"Music School",
            "type":"Public Place"
        }
    ],
    "sg:phone":"+1 425 939 0723",
    "sg:postcode":"98021",
    "sg:province":"WA",
    "sg:tags":[
        "instruction-instrumental"
    ],
    "wof:name":"A Free Lesson",
    "wof:placetype":"venue"
},
  "geometry": {"coordinates":[-122.214972,47.788992],"type":"Point"}
}