{
  "type": "Feature",
  "properties": {
    "addr:full":"1115 S 84th St Tacoma WA 98444",
    "addr:housenumber":"1115",
    "addr:postcode":"98444",
    "addr:street":"S 84Th St",
    "iso:country":"US",
    "sg:address":"1115 S 84th St",
    "sg:city":"Tacoma",
    "sg:classifiers":[
        {
            "category":"Wholesale",
            "subcategory":"Medical Equipment & Supplies",
            "type":"Manufacturing & Wholesale Goods"
        }
    ],
    "sg:phone":"+1 253 537 3933",
    "sg:postcode":"98444",
    "sg:province":"WA",
    "sg:tags":[
        "orthopedic",
        "braces"
    ],
    "wof:name":"Orthopedic Specialties",
    "wof:placetype":"venue"
},
  "geometry": {"coordinates":[-122.449817,47.181081],"type":"Point"}
}