{
  "type": "Feature",
  "properties": {
    "iso:country":"US",
    "sg:address":"140 NW True St",
    "sg:city":"Pullman",
    "sg:classifiers":[
        {
            "category":"Manufacturing",
            "subcategory":"Glass & Minerals",
            "type":"Manufacturing & Wholesale Goods"
        }
    ],
    "sg:phone":"+1 509 432 9413",
    "sg:postcode":"99163",
    "sg:province":"WA",
    "sg:tags":[
        "product",
        "mfg"
    ],
    "wof:name":"Rooneys Beads",
    "wof:placetype":"venue"
},
  "geometry": {"coordinates":[-117.17544700000001,46.738637],"type":"Point"}
}