{
  "type": "Feature",
  "properties": {
    "addr:full":"6300 9th Ave NE Ste 353 Seattle WA 98115",
    "addr:housenumber":"6300",
    "addr:postcode":"98115",
    "addr:street":"9Th Ave Ne Ste 353",
    "iso:country":"US",
    "sg:address":"6300 9th Ave NE Ste 353",
    "sg:city":"Seattle",
    "sg:classifiers":[
        {
            "category":"Health Services",
            "subcategory":"Doctor",
            "type":"Services"
        }
    ],
    "sg:phone":"+1 206 527 6289",
    "sg:postcode":"98115",
    "sg:province":"WA",
    "sg:tags":[
        "physician",
        "surgeon"
    ],
    "wof:name":"Neppe Vernon M MD Ph.D.",
    "wof:placetype":"venue"
},
  "geometry": {"coordinates":[-122.318687,47.67416],"type":"Point"}
}