{
  "type": "Feature",
  "properties": {
    "addr:full":"4204 S Sunderland Dr Spokane WA 99206",
    "addr:housenumber":"4204",
    "addr:postcode":"99206",
    "addr:street":"S Sunderland Dr",
    "iso:country":"US",
    "sg:address":"4204 S Sunderland Dr",
    "sg:city":"Spokane",
    "sg:classifiers":[
        {
            "category":"Professional",
            "subcategory":"Management & Consulting",
            "type":"Services"
        }
    ],
    "sg:phone":"+1 509 924 8829",
    "sg:postcode":"99206",
    "sg:province":"WA",
    "sg:tags":[
        "business"
    ],
    "wof:name":"Bernice A Kulm",
    "wof:placetype":"venue"
},
  "geometry": {"coordinates":[-117.27398700000001,47.615723],"type":"Point"}
}