{
  "type": "Feature",
  "properties": {
    "addr:full":"7624 67th Ave NE Marysville WA 98270",
    "addr:housenumber":"7624",
    "addr:postcode":"98270",
    "addr:street":"67Th Ave Ne",
    "iso:country":"US",
    "sg:address":"7624 67th Ave NE",
    "sg:city":"Marysville",
    "sg:classifiers":[
        {
            "category":"Professional",
            "subcategory":"Management & Consulting",
            "type":"Services"
        }
    ],
    "sg:phone":"+1 360 658 1721",
    "sg:postcode":"98270",
    "sg:province":"WA",
    "wof:name":"Hatcher Jr W W",
    "wof:placetype":"venue"
},
  "geometry": {"coordinates":[-122.14087000000001,48.064458],"type":"Point"}
}