{
  "type": "Feature",
  "properties": {
    "addr:full":"908 NW 49th St Seattle WA 98107",
    "addr:housenumber":"908",
    "addr:postcode":"98107",
    "addr:street":"Nw 49Th St",
    "iso:country":"US",
    "sg:address":"908 NW 49th St",
    "sg:city":"Seattle",
    "sg:classifiers":[
        {
            "category":"Museum",
            "type":"Entertainment"
        }
    ],
    "sg:phone":"+1 206 706 2700",
    "sg:postcode":"98107",
    "sg:province":"WA",
    "sg:tags":[
        "organization",
        "arts",
        "information"
    ],
    "wof:name":"Chihuly Inc",
    "wof:placetype":"venue"
},
  "geometry": {"coordinates":[-122.37070799999999,47.664459],"type":"Point"}
}