{
  "type": "Feature",
  "properties": {
    "addr:full":"17929 SE May Valley Rd Renton WA 98059",
    "addr:postcode":"17929;98059",
    "addr:street":"Se May Valley Rd",
    "iso:country":"US",
    "sg:address":"17929 SE May Valley Rd",
    "sg:city":"Renton",
    "sg:classifiers":[
        {
            "category":"Social Services",
            "subcategory":"Child Care",
            "type":"Services"
        }
    ],
    "sg:phone":"+1 425 255 0384",
    "sg:postcode":"98059",
    "sg:province":"WA",
    "sg:tags":[
        "day"
    ],
    "wof:name":"Preschool Connection",
    "wof:placetype":"venue"
},
  "geometry": {"coordinates":[-122.101613,47.499992],"type":"Point"}
}