{
  "type": "Feature",
  "properties": {
    "addr:full":"1980 W Hampton Rd Othello WA 99344",
    "addr:housenumber":"1980",
    "addr:postcode":"99344",
    "addr:street":"W Hampton Rd",
    "iso:country":"US",
    "sg:address":"1980 W Hampton Rd",
    "sg:city":"Othello",
    "sg:classifiers":[
        {
            "category":"Professional",
            "type":"Services"
        }
    ],
    "sg:phone":"+1 509 488 9215",
    "sg:postcode":"99344",
    "sg:province":"WA",
    "sg:tags":[
        "establishment"
    ],
    "wof:name":"Alf Christianson Seen Co Inc",
    "wof:placetype":"venue"
},
  "geometry": {"coordinates":[-119.15211499999999,46.782547],"type":"Point"}
}