{
  "type": "Feature",
  "properties": {
    "addr:full":"4122 B Pl NW Auburn WA 98001",
    "addr:housenumber":"4122",
    "addr:postcode":"98001",
    "addr:street":"B Pl Nw",
    "iso:country":"US",
    "sg:address":"4122 B Pl NW",
    "sg:city":"Auburn",
    "sg:classifiers":[
        {
            "category":"Manufacturing",
            "subcategory":"Electronics",
            "type":"Manufacturing & Wholesale Goods"
        }
    ],
    "sg:phone":"+1 253 288 8020",
    "sg:postcode":"98001",
    "sg:province":"WA",
    "sg:tags":[
        "printed",
        "circuit",
        "etched"
    ],
    "wof:name":"Popular Networks",
    "wof:placetype":"venue"
},
  "geometry": {"coordinates":[-122.23230700000001,47.343694],"type":"Point"}
}