{
  "type": "Feature",
  "properties": {
    "addr:full":"5729 93rd Pl NE Marysville WA 98270",
    "addr:housenumber":"5729",
    "addr:postcode":"98270",
    "addr:street":"93Rd Pl Ne",
    "iso:country":"US",
    "sg:address":"5729 93rd Pl NE",
    "sg:city":"Marysville",
    "sg:classifiers":[
        {
            "category":"Building & Trades",
            "subcategory":"Construction",
            "type":"Services"
        }
    ],
    "sg:phone":"+1 360 658 7212",
    "sg:postcode":"98270",
    "sg:province":"WA",
    "sg:tags":[
        "hanging",
        "contractor"
    ],
    "wof:name":"Try Painting",
    "wof:placetype":"venue"
},
  "geometry": {"coordinates":[-122.154973,48.079738],"type":"Point"}
}