{
  "type": "Feature",
  "properties": {
    "addr:full":"2109 S Skipworth Rd Spokane Valley WA 99206",
    "addr:housenumber":"2109",
    "addr:postcode":"99206",
    "addr:street":"S Skipworth Rd",
    "iso:country":"US",
    "sg:address":"2109 S Skipworth Rd",
    "sg:city":"Spokane Valley",
    "sg:classifiers":[
        {
            "category":"Education",
            "subcategory":"School",
            "type":"Public Place"
        }
    ],
    "sg:phone":"+1 509 228 4700",
    "sg:postcode":"99206",
    "sg:province":"WA",
    "sg:website":"www.cvsd.org",
    "wof:name":"Bowdish Junior High School",
    "wof:placetype":"venue"
},
  "geometry": {"coordinates":[-117.253264,47.637058],"type":"Point"}
}