{
  "type": "Feature",
  "properties": {
    "addr:full":"2414 31st Ave W Seattle WA 98199",
    "addr:housenumber":"2414",
    "addr:postcode":"98199",
    "addr:street":"31St Ave W",
    "iso:country":"US",
    "sg:address":"2414 31st Ave W",
    "sg:city":"Seattle",
    "sg:classifiers":[
        {
            "category":"Place Of Worship",
            "subcategory":"Church",
            "type":"Public Place"
        },
        {
            "category":"Place Of Worship",
            "type":"Public Place"
        }
    ],
    "sg:phone":"+1 206 284 0155",
    "sg:postcode":"98199",
    "sg:province":"WA",
    "sg:tags":[
        "lutheran",
        "america",
        "churches-lutheran",
        "churches-lutheran-evangelical"
    ],
    "wof:name":"Magnolia Lutheran Church",
    "wof:placetype":"venue"
},
  "geometry": {"coordinates":[-122.396984,47.639774],"type":"Point"}
}