{
  "type": "Feature",
  "properties": {
    "addr:full":"12807 Country Club Pl Burlington WA 98233",
    "addr:housenumber":"12807",
    "addr:postcode":"98233",
    "addr:street":"Country Club Pl",
    "iso:country":"US",
    "sg:address":"12807 Country Club Pl",
    "sg:city":"Burlington",
    "sg:classifiers":[
        {
            "category":"Professional",
            "subcategory":"Lawyer & Legal Services",
            "type":"Services"
        }
    ],
    "sg:phone":"+1 360 757 0376",
    "sg:postcode":"98233",
    "sg:province":"WA",
    "wof:name":"Yamashita David Atty",
    "wof:placetype":"venue"
},
  "geometry": {"coordinates":[-122.387001,48.461498],"type":"Point"}
}