{
  "type": "Feature",
  "properties": {
    "addr:full":"15605 Hwy 99 Lynnwood WA 98087",
    "addr:housenumber":"15605",
    "addr:postcode":"98087",
    "addr:street":"Hwy 99",
    "iso:country":"US",
    "sg:address":"15605 Hwy 99",
    "sg:city":"Lynnwood",
    "sg:classifiers":[
        {
            "category":"Shopping",
            "subcategory":"Jewelry",
            "type":"Retail Goods"
        }
    ],
    "sg:phone":"+1 425 743 0033",
    "sg:postcode":"98087",
    "sg:province":"WA",
    "sg:tags":[
        "repair",
        "clocks"
    ],
    "wof:name":"A House of Clocks",
    "wof:placetype":"venue"
},
  "geometry": {"coordinates":[-122.290413,47.855012],"type":"Point"}
}