{
  "type": "Feature",
  "properties": {
    "addr:full":"101 116th Ave SE Bellevue WA 98004",
    "addr:housenumber":"101",
    "addr:postcode":"98004",
    "addr:street":"116Th Ave Se",
    "iso:country":"US",
    "sg:address":"101 116th Ave SE",
    "sg:city":"Bellevue",
    "sg:classifiers":[
        {
            "category":"Autos & Motor Vehicles",
            "subcategory":"Automobile Sales",
            "type":"Retail Goods"
        },
        {
            "category":"Autos & Motor Vehicles",
            "subcategory":"Auto Supplies",
            "type":"Retail Goods"
        },
        {
            "category":"Retail",
            "subcategory":"Auto Repair",
            "type":"Services"
        }
    ],
    "sg:phone":"+1 425 455 9995",
    "sg:postcode":"98004",
    "sg:province":"WA",
    "sg:tags":[
        "used",
        "car",
        "accessory",
        "part",
        "new"
    ],
    "sg:website":"www.lexusofbellevue.com",
    "wof:name":"Lexus of Bellevue",
    "wof:placetype":"venue"
},
  "geometry": {"coordinates":[-122.185507,47.609199],"type":"Point"}
}