{
  "type": "Feature",
  "properties": {
    "addr:full":"1250 Garfield St Enumclaw WA 98022",
    "addr:housenumber":"1250",
    "addr:postcode":"98022",
    "addr:street":"Garfield St",
    "iso:country":"US",
    "sg:address":"1250 Garfield St",
    "sg:city":"Enumclaw",
    "sg:classifiers":[
        {
            "category":"Professional",
            "subcategory":"Accounting & Tax Preparation",
            "type":"Services"
        }
    ],
    "sg:phone":"+1 360 825 1915",
    "sg:postcode":"98022",
    "sg:province":"WA",
    "wof:name":"Cjs Bottomline Bookkeeping",
    "wof:placetype":"venue"
},
  "geometry": {"coordinates":[-122.00025599999999,47.201225],"type":"Point"}
}