{
  "type": "Feature",
  "properties": {
    "iso:country":"US",
    "sg:address":"1275 Chimacum Rd",
    "sg:city":"Port Hadlock",
    "sg:classifiers":[
        {
            "category":"Home & Garden",
            "subcategory":"Garden Supply",
            "type":"Retail Goods"
        }
    ],
    "sg:phone":"+1 360 732 4677",
    "sg:postcode":"98325",
    "sg:province":"WA",
    "wof:name":"Gladys Garden Nursery",
    "wof:placetype":"venue"
},
  "geometry": {"coordinates":[-122.768846,48.013977],"type":"Point"}
}