{
  "type": "Feature",
  "properties": {
    "addr:full":"2517 NE Andresen Rd Vancouver WA 98661",
    "addr:housenumber":"2517",
    "addr:postcode":"98661",
    "addr:street":"Ne Andresen Rd",
    "iso:country":"US",
    "sg:address":"2517 NE Andresen Rd",
    "sg:city":"Vancouver",
    "sg:classifiers":[
        {
            "category":"Professional",
            "subcategory":"Management & Consulting",
            "type":"Services"
        }
    ],
    "sg:phone":"+1 360 892 9720",
    "sg:postcode":"98661",
    "sg:province":"WA",
    "wof:name":"Amity Market",
    "wof:placetype":"venue"
},
  "geometry": {"coordinates":[-122.60068800000001,45.643447],"type":"Point"}
}