{
  "type": "Feature",
  "properties": {
    "addr:full":"549 Kinwood St SE Lacey WA 98503",
    "addr:housenumber":"549",
    "addr:postcode":"98503",
    "addr:street":"Kinwood St Se",
    "iso:country":"US",
    "sg:address":"549 Kinwood St SE",
    "sg:city":"Lacey",
    "sg:classifiers":[
        {
            "category":"Retail",
            "subcategory":"Auto Repair",
            "type":"Services"
        }
    ],
    "sg:phone":"+1 360 491 6876",
    "sg:postcode":"98503",
    "sg:province":"WA",
    "sg:tags":[
        "general"
    ],
    "wof:name":"IDM Auto Repairs",
    "wof:placetype":"venue"
},
  "geometry": {"coordinates":[-122.791357,47.04252],"type":"Point"}
}