{
  "type": "Feature",
  "properties": {
    "addr:full":"14500 NE 137th Ave Brush Prairie WA 98606",
    "addr:housenumber":"14500",
    "addr:postcode":"98606",
    "addr:street":"Ne 137Th Ave",
    "iso:country":"US",
    "sg:address":"14500 NE 137th Ave",
    "sg:city":"Brush Prairie",
    "sg:classifiers":[
        {
            "category":"Recreation",
            "type":"Entertainment"
        }
    ],
    "sg:phone":"+1 360 254 4263",
    "sg:postcode":"98606",
    "sg:province":"WA",
    "sg:tags":[
        "center"
    ],
    "wof:name":"Prairie Fields",
    "wof:placetype":"venue"
},
  "geometry": {"coordinates":[-122.53195100000001,45.727154],"type":"Point"}
}