{
  "type": "Feature",
  "properties": {
    "iso:country":"US",
    "sg:address":"407 S Tower Ave",
    "sg:city":"Centralia",
    "sg:classifiers":[
        {
            "category":"Health Services",
            "subcategory":"Doctor",
            "type":"Services"
        }
    ],
    "sg:phone":"+1 360 736 6283",
    "sg:postcode":"98531",
    "sg:province":"WA",
    "sg:tags":[
        "clinic"
    ],
    "wof:name":"Avada Audiology Hearing",
    "wof:placetype":"venue"
},
  "geometry": {"coordinates":[-122.955671,46.713273],"type":"Point"}
}