{
  "type": "Feature",
  "properties": {
    "addr:full":"21108 67th Ave NE Arlington WA 98223",
    "addr:housenumber":"21108",
    "addr:postcode":"98223",
    "addr:street":"67Th Ave Ne",
    "iso:country":"US",
    "sg:address":"21108 67th Ave NE",
    "sg:city":"Arlington",
    "sg:classifiers":[
        {
            "category":"Food & Beverages",
            "subcategory":"Groceries & Convenience Stores",
            "type":"Retail Goods"
        }
    ],
    "sg:phone":"+1 360 403 9373",
    "sg:postcode":"98223",
    "sg:province":"WA",
    "wof:name":"Super Mini Mart",
    "wof:placetype":"venue"
},
  "geometry": {"coordinates":[-122.133638,48.187701],"type":"Point"}
}