{
  "type": "Feature",
  "properties": {
    "addr:full":"1014 Walla Walla Ave Wenatchee WA 98801",
    "addr:housenumber":"1014",
    "addr:postcode":"98801",
    "addr:street":"Walla Walla Ave",
    "iso:country":"US",
    "sg:address":"1014 Walla Walla Ave",
    "sg:city":"Wenatchee",
    "sg:classifiers":[
        {
            "category":"Food & Beverages",
            "subcategory":"Groceries & Convenience Stores",
            "type":"Retail Goods"
        }
    ],
    "sg:phone":"+1 509 662 6502",
    "sg:postcode":"98801",
    "sg:province":"WA",
    "wof:name":"Safeway Training & Develo",
    "wof:placetype":"venue"
},
  "geometry": {"coordinates":[-120.316581,47.437772],"type":"Point"}
}