{
  "type": "Feature",
  "properties": {
    "addr:full":"11031 159th Ave NE Granite Falls WA 98252",
    "addr:housenumber":"11031",
    "addr:postcode":"98252",
    "addr:street":"159Th Ave Ne",
    "iso:country":"US",
    "sg:address":"11031 159th Ave NE",
    "sg:city":"Granite Falls",
    "sg:classifiers":[
        {
            "category":"Airport",
            "type":"Transportation"
        }
    ],
    "sg:phone":"+1 425 334 3030",
    "sg:postcode":"98252",
    "sg:province":"WA",
    "sg:tags":[
        "aircraft",
        "maintenance"
    ],
    "wof:name":"Air Mods Northwest",
    "wof:placetype":"venue"
},
  "geometry": {"coordinates":[-122.017719,48.094693],"type":"Point"}
}