{
  "type": "Feature",
  "properties": {
    "addr:full":"24561 River Rd Sedro Woolley WA 98284",
    "addr:housenumber":"24561",
    "addr:postcode":"98284",
    "addr:street":"River Rd",
    "iso:country":"US",
    "sg:address":"24561 River Rd",
    "sg:city":"Sedro Woolley",
    "sg:classifiers":[
        {
            "category":"Farming",
            "subcategory":"Dairy Farm",
            "type":"Manufacturing & Wholesale Goods"
        }
    ],
    "sg:phone":"+1 360 856 1713",
    "sg:postcode":"98284",
    "sg:province":"WA",
    "wof:name":"Sid Top",
    "wof:placetype":"venue"
},
  "geometry": {"coordinates":[-122.209801,48.490414],"type":"Point"}
}