{
  "type": "Feature",
  "properties": {
    "iso:country":"US",
    "sg:address":"3217 204th St SW",
    "sg:city":"Lynnwood",
    "sg:classifiers":[
        {
            "category":"Social Services",
            "subcategory":"Adult Care",
            "type":"Services"
        }
    ],
    "sg:phone":"+1 425 774 5487",
    "sg:postcode":"98036",
    "sg:province":"WA",
    "sg:tags":[
        "home",
        "residential"
    ],
    "wof:name":"American Adult Assisted Living",
    "wof:placetype":"venue"
},
  "geometry": {"coordinates":[-122.276027,47.813694],"type":"Point"}
}