{
  "type": "Feature",
  "properties": {
    "addr:full":"805 E Main St Battle Ground WA 98604",
    "addr:housenumber":"805",
    "addr:postcode":"98604",
    "addr:street":"E Main St",
    "iso:country":"US",
    "sg:address":"805 E Main St",
    "sg:city":"Battle Ground",
    "sg:classifiers":[
        {
            "category":"Manufacturing",
            "subcategory":"Printing",
            "type":"Manufacturing & Wholesale Goods"
        },
        {
            "category":"Shopping",
            "subcategory":"Clothing, Apparel, & Fashions",
            "type":"Retail Goods"
        }
    ],
    "sg:phone":"+1 360 687 0301",
    "sg:postcode":"98604",
    "sg:province":"WA",
    "sg:tags":[
        "screen"
    ],
    "wof:name":"Screen Grafx Custom Shirts & G",
    "wof:placetype":"venue"
},
  "geometry": {"coordinates":[-122.52842,45.780903],"type":"Point"}
}