{
  "type": "Feature",
  "properties": {
    "addr:full":"17250 N Wenas Rd Selah WA 98942",
    "addr:housenumber":"17250",
    "addr:postcode":"98942",
    "addr:street":"N Wenas Rd",
    "iso:country":"US",
    "sg:address":"17250 N Wenas Rd",
    "sg:city":"Selah",
    "sg:phone":"+1 509 697 3564",
    "sg:postcode":"98942",
    "sg:province":"WA",
    "sg:tags":[
        "farm",
        "field",
        "dog",
        "crop",
        "kennel"
    ],
    "wof:name":"Hoover Farm",
    "wof:placetype":"venue"
},
  "geometry": {"coordinates":[-120.71017000000001,46.832688],"type":"Point"}
}