{
  "type": "Feature",
  "properties": {
    "addr:full":"45 N 9th Ave Walla Walla WA 99362",
    "addr:housenumber":"45",
    "addr:postcode":"99362",
    "addr:street":"N 9Th Ave",
    "iso:country":"US",
    "sg:address":"45 N 9th Ave",
    "sg:city":"Walla Walla",
    "sg:classifiers":[
        {
            "category":"Retail",
            "subcategory":"Auto Rental",
            "type":"Services"
        }
    ],
    "sg:phone":"+1 509 522 3321",
    "sg:postcode":"99362",
    "sg:province":"WA",
    "sg:tags":[
        "passenger",
        "car"
    ],
    "wof:name":"Hertz",
    "wof:placetype":"venue"
},
  "geometry": {"coordinates":[-118.349085,46.063727],"type":"Point"}
}