{
  "type": "Feature",
  "properties": {
    "addr:full":"3602 Fruitvale Blvd Yakima WA 98902",
    "addr:housenumber":"3602",
    "addr:postcode":"98902",
    "addr:street":"Fruitvale Blvd",
    "iso:country":"US",
    "sg:address":"3602 Fruitvale Blvd",
    "sg:city":"Yakima",
    "sg:classifiers":[
        {
            "category":"Wholesale",
            "subcategory":"Office Equipment",
            "type":"Manufacturing & Wholesale Goods"
        }
    ],
    "sg:phone":"+1 509 574 5675",
    "sg:postcode":"98902",
    "sg:province":"WA",
    "sg:tags":[
        "vault",
        "safe"
    ],
    "wof:name":"Grizzley Enterprises",
    "wof:placetype":"venue"
},
  "geometry": {"coordinates":[-120.555066,46.618548],"type":"Point"}
}