{
  "type": "Feature",
  "properties": {
    "addr:full":"3729 156th St SW Lynnwood WA 98087",
    "addr:housenumber":"3729",
    "addr:postcode":"98087",
    "addr:street":"156Th St Sw",
    "iso:country":"US",
    "sg:address":"3729 156th St SW",
    "sg:city":"Lynnwood",
    "sg:classifiers":[
        {
            "category":"Manufacturing",
            "subcategory":"Signs",
            "type":"Manufacturing & Wholesale Goods"
        }
    ],
    "sg:phone":"+1 425 742 2378",
    "sg:postcode":"98087",
    "sg:province":"WA",
    "sg:tags":[
        "specialty",
        "mfg"
    ],
    "wof:name":"CN Sign",
    "wof:placetype":"venue"
},
  "geometry": {"coordinates":[-122.28444500000001,47.857323],"type":"Point"}
}