{
  "type": "Feature",
  "properties": {
    "addr:full":"11549 16th Ave NE Seattle WA 98125",
    "addr:housenumber":"11549",
    "addr:postcode":"98125",
    "addr:street":"16Th Ave Ne",
    "iso:country":"US",
    "sg:address":"11549 16th Ave NE",
    "sg:city":"Seattle",
    "sg:classifiers":[
        {
            "category":"Health Services",
            "subcategory":"Clinic",
            "type":"Services"
        }
    ],
    "sg:phone":"+1 206 363 9773",
    "sg:postcode":"98125",
    "sg:province":"WA",
    "sg:tags":[
        "information",
        "center",
        "outpatient",
        "specialty",
        "treatment",
        "alcoholism"
    ],
    "wof:name":"Lowell Independent Living Services",
    "wof:placetype":"venue"
},
  "geometry": {"coordinates":[-122.31111900000001,47.71304],"type":"Point"}
}