{
  "type": "Feature",
  "properties": {
    "addr:full":"11414 8th Ave NW Seattle WA 98177",
    "addr:housenumber":"11414",
    "addr:postcode":"98177",
    "addr:street":"8Th Ave Nw",
    "iso:country":"US",
    "sg:address":"11414 8th Ave NW",
    "sg:city":"Seattle",
    "sg:classifiers":[
        {
            "category":"Professional",
            "subcategory":"Advertising",
            "type":"Services"
        }
    ],
    "sg:phone":"+1 206 298 4945",
    "sg:postcode":"98177",
    "sg:province":"WA",
    "sg:tags":[
        "advertising-broadcast",
        "representative",
        "film"
    ],
    "sg:website":"http://www.greaterradio.com",
    "wof:name":"Hoyts Greater Radio",
    "wof:placetype":"venue"
},
  "geometry": {"coordinates":[-122.366088,47.711761],"type":"Point"}
}