{
  "type": "Feature",
  "properties": {
    "addr:full":"2501 Washington St Port Townsend WA 98368",
    "addr:housenumber":"2501",
    "addr:postcode":"98368",
    "addr:street":"Washington St",
    "iso:country":"US",
    "sg:address":"2501 Washington St",
    "sg:city":"Port Townsend",
    "sg:classifiers":[
        {
            "category":"Restaurant",
            "type":"Food & Drink"
        }
    ],
    "sg:phone":"+1 360 385 6312",
    "sg:postcode":"98368",
    "sg:province":"WA",
    "wof:name":"Sea J's Cafe",
    "wof:placetype":"venue"
},
  "geometry": {"coordinates":[-122.77310199999999,48.108183],"type":"Point"}
}