{
  "type": "Feature",
  "properties": {
    "addr:full":"2300 E Cherry St Seattle WA 98122",
    "addr:housenumber":"2300",
    "addr:postcode":"98122",
    "addr:street":"E Cherry St",
    "iso:country":"US",
    "sg:address":"2300 E Cherry St",
    "sg:city":"Seattle",
    "sg:classifiers":[
        {
            "category":"Manufacturing",
            "subcategory":"Food",
            "type":"Manufacturing & Wholesale Goods"
        }
    ],
    "sg:phone":"+1 206 328 1955",
    "sg:postcode":"98122",
    "sg:province":"WA",
    "sg:tags":[
        "confectionery",
        "candy"
    ],
    "wof:name":"Dilettante Chocolates",
    "wof:placetype":"venue"
},
  "geometry": {"coordinates":[-122.301478,47.608004],"type":"Point"}
}