{
  "type": "Feature",
  "properties": {
    "addr:full":"3819 S Meridian Puyallup WA 98373",
    "addr:housenumber":"3819",
    "addr:postcode":"98373",
    "addr:street":"S Meridian",
    "iso:country":"US",
    "sg:address":"3819 S Meridian",
    "sg:city":"Puyallup",
    "sg:classifiers":[
        {
            "category":"Personal",
            "subcategory":"Beauty Salon",
            "type":"Services"
        }
    ],
    "sg:phone":"+1 253 864 6798",
    "sg:postcode":"98373",
    "sg:province":"WA",
    "sg:tags":[
        "shop"
    ],
    "wof:name":"Pro Nails",
    "wof:placetype":"venue"
},
  "geometry": {"coordinates":[-122.293254,47.164317],"type":"Point"}
}