{
  "type": "Feature",
  "properties": {
    "addr:full":"1620 4th Ave Seattle WA 98101",
    "addr:housenumber":"1620",
    "addr:postcode":"98101",
    "addr:street":"4Th Ave",
    "iso:country":"US",
    "sg:address":"1620 4th Ave",
    "sg:city":"Seattle",
    "sg:classifiers":[
        {
            "category":"Banks & Credit Unions",
            "subcategory":"Bank",
            "type":"Services"
        }
    ],
    "sg:phone":"+1 206 287 0039",
    "sg:postcode":"98101",
    "sg:province":"WA",
    "wof:name":"Wells Fargo",
    "wof:placetype":"venue"
},
  "geometry": {"coordinates":[-122.337997,47.611198],"type":"Point"}
}