{
  "type": "Feature",
  "properties": {
    "addr:full":"1686 Brooks Rd Evans WA 99126",
    "addr:housenumber":"1686",
    "addr:postcode":"99126",
    "addr:street":"Brooks Rd",
    "iso:country":"US",
    "sg:address":"1686 Brooks Rd",
    "sg:city":"Evans",
    "sg:classifiers":[
        {
            "category":"Manufacturing",
            "subcategory":"Lumber",
            "type":"Manufacturing & Wholesale Goods"
        }
    ],
    "sg:phone":"+1 509 684 3949",
    "sg:postcode":"99126",
    "sg:province":"WA",
    "sg:tags":[
        "logging"
    ],
    "wof:name":"Hydra Cut",
    "wof:placetype":"venue"
},
  "geometry": {"coordinates":[-117.967309,48.737641],"type":"Point"}
}