{
  "type": "Feature",
  "properties": {
    "addr:full":"19405 NE 20th Ave Ridgefield WA 98642",
    "addr:housenumber":"19405",
    "addr:postcode":"98642",
    "addr:street":"Ne 20Th Ave",
    "iso:country":"US",
    "sg:address":"19405 NE 20th Ave",
    "sg:city":"Ridgefield",
    "sg:classifiers":[
        {
            "category":"Farming",
            "subcategory":"Farm & Veterinary Services",
            "type":"Manufacturing & Wholesale Goods"
        }
    ],
    "sg:phone":"+1 360 921 2953",
    "sg:postcode":"98642",
    "sg:province":"WA",
    "sg:tags":[
        "preparation",
        "soil"
    ],
    "wof:name":"T & T Shavings",
    "wof:placetype":"venue"
},
  "geometry": {"coordinates":[-122.65114,45.763455],"type":"Point"}
}