{
  "type": "Feature",
  "properties": {
    "addr:full":"600 N 36th St Seattle WA 98103",
    "addr:housenumber":"600",
    "addr:postcode":"98103",
    "addr:street":"N 36Th St",
    "iso:country":"US",
    "sg:address":"600 N 36th St",
    "sg:city":"Seattle",
    "sg:classifiers":[
        {
            "category":"Professional",
            "subcategory":"Lawyer & Legal Services",
            "type":"Services"
        }
    ],
    "sg:phone":"+1 206 547 7800",
    "sg:postcode":"98103",
    "sg:province":"WA",
    "sg:tags":[
        "divorce",
        "law",
        "family"
    ],
    "sg:website":"www.familylawfolks.com",
    "wof:name":"Family Law Folks",
    "wof:placetype":"venue"
},
  "geometry": {"coordinates":[-122.35136900000001,47.651573],"type":"Point"}
}