{
  "type": "Feature",
  "properties": {
    "addr:full":"2150 N 107th St Seattle WA 98133",
    "addr:housenumber":"2150",
    "addr:postcode":"98133",
    "addr:street":"N 107Th St",
    "iso:country":"US",
    "sg:address":"2150 N 107th St",
    "sg:city":"Seattle",
    "sg:classifiers":[
        {
            "category":"Organizations",
            "subcategory":"Professional Association",
            "type":"Services"
        }
    ],
    "sg:phone":"+1 206 363 9188",
    "sg:postcode":"98133",
    "sg:province":"WA",
    "sg:tags":[
        "business"
    ],
    "wof:name":"Greater Seattle Business Assn",
    "wof:placetype":"venue"
},
  "geometry": {"coordinates":[-122.331278,47.70683],"type":"Point"}
}