{
  "type": "Feature",
  "properties": {
    "addr:full":"9234 3rd Ave NW Seattle WA 98117",
    "addr:housenumber":"9234",
    "addr:postcode":"98117",
    "addr:street":"3Rd Ave Nw",
    "iso:country":"US",
    "sg:address":"9234 3rd Ave NW",
    "sg:city":"Seattle",
    "sg:classifiers":[
        {
            "category":"Professional",
            "subcategory":"Business Services",
            "type":"Services"
        }
    ],
    "sg:phone":"+1 206 297 1227",
    "sg:postcode":"98117",
    "sg:province":"WA",
    "wof:name":"Sunmark Design Inc",
    "wof:placetype":"venue"
},
  "geometry": {"coordinates":[-122.36063,47.697643],"type":"Point"}
}