{
  "type": "Feature",
  "properties": {
    "addr:full":"520 S Pines Rd Spokane Valley WA 99206",
    "addr:housenumber":"520",
    "addr:postcode":"99206",
    "addr:street":"S Pines Rd",
    "iso:country":"US",
    "sg:address":"520 S Pines Rd",
    "sg:city":"Spokane Valley",
    "sg:classifiers":[
        {
            "category":"Food & Beverages",
            "subcategory":"Groceries & Convenience Stores",
            "type":"Retail Goods"
        }
    ],
    "sg:phone":"+1 509 891 5200",
    "sg:postcode":"99206",
    "sg:province":"WA",
    "wof:name":"Pronto Plus Deli-Mart",
    "wof:placetype":"venue"
},
  "geometry": {"coordinates":[-117.239906,47.652722],"type":"Point"}
}