{
  "type": "Feature",
  "properties": {
    "iso:country":"US",
    "sg:address":"12737 Bel Red Rd",
    "sg:city":"Bellevue",
    "sg:classifiers":[
        {
            "category":"Building & Trades",
            "subcategory":"Construction",
            "type":"Services"
        }
    ],
    "sg:phone":"+1 425 889 8890",
    "sg:postcode":"98005",
    "sg:province":"WA",
    "sg:tags":[
        "family",
        "contractor",
        "new",
        "home",
        "improvement",
        "tenant"
    ],
    "wof:name":"Ticon Inc",
    "wof:placetype":"venue"
},
  "geometry": {"coordinates":[-122.17262599999999,47.620081],"type":"Point"}
}