{
  "type": "Feature",
  "properties": {
    "addr:full":"10003 N Division St Spokane WA 99218",
    "addr:housenumber":"10003",
    "addr:postcode":"99218",
    "addr:street":"N Division St",
    "iso:country":"US",
    "sg:address":"10003 N Division St",
    "sg:city":"Spokane",
    "sg:classifiers":[
        {
            "category":"Health Services",
            "subcategory":"Chiropractor",
            "type":"Services"
        }
    ],
    "sg:phone":"+1 509 468 2102",
    "sg:postcode":"99218",
    "sg:province":"WA",
    "sg:tags":[
        "chiropractic"
    ],
    "wof:name":"Williams Michael DC",
    "wof:placetype":"venue"
},
  "geometry": {"coordinates":[-117.41134099999999,47.7488],"type":"Point"}
}