{
  "type": "Feature",
  "properties": {
    "addr:full":"9019 112th St SW Tacoma WA 98498",
    "addr:housenumber":"9019",
    "addr:postcode":"98498",
    "addr:street":"112Th St Sw",
    "iso:country":"US",
    "sg:address":"9019 112th St SW",
    "sg:city":"Tacoma",
    "sg:classifiers":[
        {
            "category":"Building & Trades",
            "subcategory":"Cleaning & Sanitation",
            "type":"Services"
        }
    ],
    "sg:phone":"+1 253 589 9664",
    "sg:postcode":"98498",
    "sg:province":"WA",
    "sg:tags":[
        "janitor"
    ],
    "wof:name":"D-S Enterprises",
    "wof:placetype":"venue"
},
  "geometry": {"coordinates":[-122.55726799999999,47.155944],"type":"Point"}
}