{
  "type": "Feature",
  "properties": {
    "addr:full":"520 Lilly Rd NE Ste A Olympia WA 98506",
    "addr:housenumber":"520",
    "addr:postcode":"98506",
    "addr:street":"Lilly Rd Ne Ste A",
    "iso:country":"US",
    "sg:address":"520 Lilly Rd NE Ste A",
    "sg:city":"Olympia",
    "sg:classifiers":[
        {
            "category":"Health Services",
            "subcategory":"Doctor",
            "type":"Services"
        }
    ],
    "sg:phone":"+1 360 438 2727",
    "sg:postcode":"98506",
    "sg:province":"WA",
    "sg:tags":[
        "physician",
        "family",
        "practice",
        "surgeons",
        "medicine",
        "surgeon"
    ],
    "wof:name":"Kevin F Connolly Md",
    "wof:placetype":"venue"
},
  "geometry": {"coordinates":[-122.84440600000001,47.053271],"type":"Point"}
}