{
  "type": "Feature",
  "properties": {
    "addr:full":"3145 Hogum Bay Rd NE Lacey WA 98516",
    "addr:housenumber":"3145",
    "addr:postcode":"98516",
    "addr:street":"Hogum Bay Rd Ne",
    "iso:country":"US",
    "sg:address":"3145 Hogum Bay Rd NE",
    "sg:city":"Lacey",
    "sg:classifiers":[
        {
            "category":"Wholesale",
            "subcategory":"Farm Supplies",
            "type":"Manufacturing & Wholesale Goods"
        },
        {
            "category":"Wholesale",
            "subcategory":"Groceries",
            "type":"Manufacturing & Wholesale Goods"
        }
    ],
    "sg:phone":"+1 360 413 7269",
    "sg:postcode":"98516",
    "sg:province":"WA",
    "sg:tags":[
        "food",
        "feed",
        "animal"
    ],
    "wof:name":"Nutriom LLC",
    "wof:placetype":"venue"
},
  "geometry": {"coordinates":[-122.765006,47.078373],"type":"Point"}
}