{
  "type": "Feature",
  "properties": {
    "addr:full":"17010 Sandridge Rd Long Beach WA 98631",
    "addr:housenumber":"17010",
    "addr:postcode":"98631",
    "addr:street":"Sandridge Rd",
    "iso:country":"US",
    "sg:address":"17010 Sandridge Rd",
    "sg:city":"Long Beach",
    "sg:classifiers":[
        {
            "category":"Autos & Motor Vehicles",
            "subcategory":"Automobile Sales",
            "type":"Retail Goods"
        }
    ],
    "sg:phone":"+1 360 642 2069",
    "sg:postcode":"98631",
    "sg:province":"WA",
    "sg:tags":[
        "used"
    ],
    "wof:name":"OConnor Used Equipment Sales",
    "wof:placetype":"venue"
},
  "geometry": {"coordinates":[-124.020951,46.424584],"type":"Point"}
}