{
  "type": "Feature",
  "properties": {
    "addr:full":"3231 NW 62nd Street Seattle WA 98107",
    "addr:housenumber":"3231",
    "addr:postcode":"98107",
    "addr:street":"Nw 62Nd Street",
    "iso:country":"US",
    "sg:address":"3231 NW 62nd Street",
    "sg:city":"Seattle",
    "sg:classifiers":[
        {
            "category":"Building & Trades",
            "subcategory":"Cleaning & Sanitation",
            "type":"Services"
        }
    ],
    "sg:phone":"+1 415 425 8373",
    "sg:postcode":"98107",
    "sg:province":"WA",
    "sg:tags":[
        "home"
    ],
    "sg:website":"www.organizetomove.com",
    "wof:name":"Organize to Move",
    "wof:placetype":"venue"
},
  "geometry": {"coordinates":[-122.39982000000001,47.673629],"type":"Point"}
}