{
  "type": "Feature",
  "properties": {
    "addr:full":"516 Broadway E Seattle WA 98102",
    "addr:housenumber":"516",
    "addr:postcode":"98102",
    "addr:street":"Broadway",
    "iso:country":"US",
    "sg:address":"516 Broadway E",
    "sg:city":"Seattle",
    "sg:classifiers":[
        {
            "category":"Restaurant",
            "type":"Food & Drink"
        }
    ],
    "sg:phone":"+1 206 568 7218",
    "sg:postcode":"98102",
    "sg:province":"WA",
    "sg:tags":[
        "vietnamese"
    ],
    "sg:website":"www.thanbrothers.com",
    "wof:name":"Pho Than Brothers",
    "wof:placetype":"venue"
},
  "geometry": {"coordinates":[-122.320583,47.623637],"type":"Point"}
}