{
  "type": "Feature",
  "properties": {
    "addr:full":"3301 46th Ave NE Olympia WA 98506",
    "addr:housenumber":"3301",
    "addr:postcode":"98506",
    "addr:street":"46Th Ave Ne",
    "iso:country":"US",
    "sg:address":"3301 46th Ave NE",
    "sg:city":"Olympia",
    "sg:classifiers":[
        {
            "category":"Building & Trades",
            "subcategory":"Plumbing",
            "type":"Services"
        }
    ],
    "sg:phone":"+1 360 357 3262",
    "sg:postcode":"98506",
    "sg:province":"WA",
    "sg:tags":[
        "plumbing",
        "contractor"
    ],
    "wof:name":"Pratt's Plumbing",
    "wof:placetype":"venue"
},
  "geometry": {"coordinates":[-122.853393,47.097797],"type":"Point"}
}