{
  "type": "Feature",
  "properties": {
    "addr:full":"3106 SW 169th St Seattle WA 98166",
    "addr:housenumber":"3106",
    "addr:postcode":"98166",
    "addr:street":"Sw 169Th St",
    "iso:country":"US",
    "sg:address":"3106 SW 169th St",
    "sg:city":"Seattle",
    "sg:classifiers":[
        {
            "category":"Professional",
            "subcategory":"Management & Consulting",
            "type":"Services"
        }
    ],
    "sg:phone":"+1 206 246 5021",
    "sg:postcode":"98166",
    "sg:province":"WA",
    "sg:tags":[
        "selling",
        "establishment",
        "direct"
    ],
    "wof:name":"Colleen Ikeda",
    "wof:placetype":"venue"
},
  "geometry": {"coordinates":[-122.37291,47.452051],"type":"Point"}
}