{
  "type": "Feature",
  "properties": {
    "addr:full":"520 Hoag Rd Mt Vernon WA 98273",
    "addr:housenumber":"520",
    "addr:postcode":"98273",
    "addr:street":"Hoag Rd",
    "iso:country":"US",
    "sg:address":"520 Hoag Rd",
    "sg:city":"Mt Vernon",
    "sg:classifiers":[
        {
            "category":"Organizations",
            "subcategory":"Religious Organization",
            "type":"Services"
        }
    ],
    "sg:phone":"+1 360 421 4577",
    "sg:postcode":"98273",
    "sg:province":"WA",
    "sg:tags":[
        "church"
    ],
    "wof:name":"All Nations Christian Ctr",
    "wof:placetype":"venue"
},
  "geometry": {"coordinates":[-122.33349800000001,48.443015],"type":"Point"}
}