{
  "type": "Feature",
  "properties": {
    "addr:full":"2707 76th Ave SE Mercer Island WA 98040",
    "addr:housenumber":"2707",
    "addr:postcode":"98040",
    "addr:street":"76Th Ave Se",
    "iso:country":"US",
    "sg:address":"2707 76th Ave SE",
    "sg:city":"Mercer Island",
    "sg:classifiers":[
        {
            "category":"Retail",
            "subcategory":"Veterinary Services",
            "type":"Services"
        }
    ],
    "sg:phone":"+1 206 232 3128",
    "sg:postcode":"98040",
    "sg:province":"WA",
    "sg:tags":[
        "veterinarian"
    ],
    "wof:name":"Mercy Vet",
    "wof:placetype":"venue"
},
  "geometry": {"coordinates":[-122.237999,47.585999],"type":"Point"}
}