{
  "type": "Feature",
  "properties": {
    "addr:full":"2030 Broadway Everett WA 98201",
    "addr:housenumber":"2030",
    "addr:postcode":"98201",
    "addr:street":"Broadway",
    "iso:country":"US",
    "sg:address":"2030 Broadway",
    "sg:city":"Everett",
    "sg:classifiers":[
        {
            "category":"Restaurant",
            "type":"Food & Drink"
        }
    ],
    "sg:phone":"+1 425 259 2205",
    "sg:postcode":"98201",
    "sg:province":"WA",
    "wof:name":"Oishi Teriyaki",
    "wof:placetype":"venue"
},
  "geometry": {"coordinates":[-122.201376,47.990166],"type":"Point"}
}