{
  "type": "Feature",
  "properties": {
    "addr:full":"1936 18th St Bellingham WA 98225",
    "addr:housenumber":"1936",
    "addr:postcode":"98225",
    "addr:street":"18Th St",
    "iso:country":"US",
    "sg:address":"1936 18th St",
    "sg:city":"Bellingham",
    "sg:classifiers":[
        {
            "category":"Building & Trades",
            "subcategory":"Cleaning & Sanitation",
            "type":"Services"
        }
    ],
    "sg:phone":"+1 360 714 1687",
    "sg:postcode":"98225",
    "sg:province":"WA",
    "sg:tags":[
        "maintenance"
    ],
    "wof:name":"Christine Cleaning Service",
    "wof:placetype":"venue"
},
  "geometry": {"coordinates":[-122.494094,48.714126],"type":"Point"}
}