{
  "type": "Feature",
  "properties": {
    "addr:full":"186 Buena Vista Dr Colville WA 99114",
    "addr:housenumber":"186",
    "addr:postcode":"99114",
    "addr:street":"Buena Vista Dr",
    "iso:country":"US",
    "sg:address":"186 Buena Vista Dr",
    "sg:city":"Colville",
    "sg:classifiers":[
        {
            "category":"Personal",
            "subcategory":"Shoe Repair & Shine",
            "type":"Services"
        }
    ],
    "sg:phone":"+1 509 684 2481",
    "sg:postcode":"99114",
    "sg:province":"WA",
    "sg:tags":[
        "repairing",
        "boot"
    ],
    "wof:name":"Uptown Shoe Repair",
    "wof:placetype":"venue"
},
  "geometry": {"coordinates":[-117.91791000000001,48.561347],"type":"Point"}
}