{
  "type": "Feature",
  "properties": {
    "addr:full":"7410 Onyx Dr SW Lakewood WA 98498",
    "addr:housenumber":"7410",
    "addr:postcode":"98498",
    "addr:street":"Onyx Dr Sw",
    "iso:country":"US",
    "sg:address":"7410 Onyx Dr SW",
    "sg:city":"Lakewood",
    "sg:classifiers":[
        {
            "category":"Real Estate",
            "subcategory":"Real Estate Agent",
            "type":"Services"
        }
    ],
    "sg:phone":"+1 253 512 1223",
    "sg:postcode":"98498",
    "sg:province":"WA",
    "wof:name":"Rancho Rojo Apartments",
    "wof:placetype":"venue"
},
  "geometry": {"coordinates":[-122.536981,47.190196],"type":"Point"}
}