{
  "type": "Feature",
  "properties": {
    "addr:full":"140 Rainier Ave Renton WA 98055",
    "addr:housenumber":"140",
    "addr:postcode":"98055",
    "addr:street":"Rainier Ave",
    "iso:country":"US",
    "sg:address":"140 Rainier Ave",
    "sg:city":"Renton",
    "sg:classifiers":[
        {
            "category":"Real Estate",
            "subcategory":"Real Estate Agent",
            "type":"Services"
        }
    ],
    "sg:phone":"+1 425 277 5727",
    "sg:postcode":"98055",
    "sg:province":"WA",
    "wof:name":"Broome Appraisal",
    "wof:placetype":"venue"
},
  "geometry": {"coordinates":[-122.217085,47.481912],"type":"Point"}
}