{
  "type": "Feature",
  "properties": {
    "iso:country":"US",
    "sg:address":"50788 State Hwy 112",
    "sg:city":"Port Angeles",
    "sg:classifiers":[
        {
            "category":"Freight",
            "type":"Transportation"
        }
    ],
    "sg:phone":"+1 360 928 2105",
    "sg:postcode":"98363",
    "sg:province":"WA",
    "sg:tags":[
        "operator",
        "local",
        "trucking"
    ],
    "wof:name":"Thomas Rogers Trucking",
    "wof:placetype":"venue"
},
  "geometry": {"coordinates":[-123.735867,48.136075],"type":"Point"}
}