{
  "type": "Feature",
  "properties": {
    "addr:full":"490 N 3rd Pl Kalama WA 98625",
    "addr:housenumber":"490",
    "addr:postcode":"98625",
    "addr:street":"N 3Rd Pl Kalama",
    "iso:country":"US",
    "sg:address":"490 N 3rd Pl",
    "sg:city":"Kalama",
    "sg:classifiers":[
        {
            "category":"Personal",
            "subcategory":"Beauty Salon",
            "type":"Services"
        }
    ],
    "sg:phone":"+1 360 673 4130",
    "sg:postcode":"98625",
    "sg:province":"WA",
    "wof:name":"Shear Maddness",
    "wof:placetype":"venue"
},
  "geometry": {"coordinates":[-122.841807,46.01129],"type":"Point"}
}