{
  "type": "Feature",
  "properties": {
    "addr:full":"4526 California Ave SW Seattle WA 98116",
    "addr:housenumber":"4526",
    "addr:postcode":"98116",
    "addr:street":"California Ave Sw",
    "iso:country":"US",
    "sg:address":"4526 California Ave SW",
    "sg:city":"Seattle",
    "sg:classifiers":[
        {
            "category":"Real Estate",
            "subcategory":"Real Estate Agent",
            "type":"Services"
        }
    ],
    "sg:phone":"+1 206 683 1737",
    "sg:postcode":"98116",
    "sg:province":"WA",
    "sg:website":"www.brittspicks.com",
    "wof:name":"Britt Salaverry",
    "wof:placetype":"venue"
},
  "geometry": {"coordinates":[-122.38675000000001,47.562005],"type":"Point"}
}