{
  "type": "Feature",
  "properties": {
    "addr:full":"5908 Athens Beach Rd NW Olympia WA 98502",
    "addr:housenumber":"5908",
    "addr:postcode":"olympia wa 98502",
    "addr:street":"Athens Beach Rd Nw",
    "iso:country":"US",
    "sg:address":"5908 Athens Beach Rd NW",
    "sg:city":"Olympia",
    "sg:classifiers":[
        {
            "category":"Professional",
            "subcategory":"Management & Consulting",
            "type":"Services"
        }
    ],
    "sg:phone":"+1 360 866 2716",
    "sg:postcode":"98502",
    "sg:province":"WA",
    "sg:tags":[
        "business"
    ],
    "wof:name":"John A Hill Enterprises LLC",
    "wof:placetype":"venue"
},
  "geometry": {"coordinates":[-122.924948,47.116539],"type":"Point"}
}