{
  "type": "Feature",
  "properties": {
    "addr:full":"26020 NE Hinness Rd Brush Prairie WA 98606",
    "addr:housenumber":"26020",
    "addr:postcode":"98606",
    "addr:street":"Ne Hinness Rd",
    "iso:country":"US",
    "sg:address":"26020 NE Hinness Rd",
    "sg:city":"Brush Prairie",
    "sg:classifiers":[
        {
            "category":"Building & Trades",
            "subcategory":"Landscaping Services",
            "type":"Services"
        }
    ],
    "sg:phone":"+1 360 891 2144",
    "sg:postcode":"98606",
    "sg:province":"WA",
    "sg:tags":[
        "landscape",
        "contractor"
    ],
    "wof:name":"Green Haven Inc",
    "wof:placetype":"venue"
},
  "geometry": {"coordinates":[-122.40373599999999,45.724453],"type":"Point"}
}