{
  "type": "Feature",
  "properties": {
    "iso:country":"US",
    "sg:address":"1123 Meade Ave",
    "sg:city":"Prosser",
    "sg:classifiers":[
        {
            "category":"Personal",
            "type":"Services"
        }
    ],
    "sg:phone":"+1 509 786 3419",
    "sg:postcode":"99350",
    "sg:province":"WA",
    "wof:name":"Electra Life Technologies",
    "wof:placetype":"venue"
},
  "geometry": {"coordinates":[-119.769809,46.204875],"type":"Point"}
}