{
  "type": "Feature",
  "properties": {
    "addr:full":"53 Ginny Ln Elma WA 98541",
    "addr:housenumber":"53",
    "addr:postcode":"98541",
    "addr:street":"Ginny Ln",
    "iso:country":"US",
    "sg:address":"53 Ginny Ln",
    "sg:city":"Elma",
    "sg:classifiers":[
        {
            "category":"Shopping",
            "type":"Retail Goods"
        }
    ],
    "sg:phone":"+1 360 482 4704",
    "sg:postcode":"98541",
    "sg:province":"WA",
    "sg:tags":[
        "merchandise"
    ],
    "wof:name":"M&L Ice Co",
    "wof:placetype":"venue"
},
  "geometry": {"coordinates":[-123.37214899999999,47.013425],"type":"Point"}
}