{
  "type": "Feature",
  "properties": {
    "addr:full":"8204 NE 96th St Vancouver WA 98662",
    "addr:housenumber":"8204",
    "addr:postcode":"98662",
    "addr:street":"Ne 96Th St",
    "iso:country":"US",
    "sg:address":"8204 NE 96th St",
    "sg:city":"Vancouver",
    "sg:classifiers":[
        {
            "category":"Manufacturing",
            "subcategory":"Retail Goods",
            "type":"Manufacturing & Wholesale Goods"
        }
    ],
    "sg:phone":"+1 360 896 3553",
    "sg:postcode":"98662",
    "sg:province":"WA",
    "sg:tags":[
        "lead",
        "mfg"
    ],
    "wof:name":"Evalyn I Baker",
    "wof:placetype":"venue"
},
  "geometry": {"coordinates":[-122.588138,45.691723],"type":"Point"}
}