{
  "type": "Feature",
  "properties": {
    "addr:full":"4882 Swenson Rd Deer Park WA 99006",
    "addr:housenumber":"4882",
    "addr:postcode":"99006",
    "addr:street":"Swenson Rd",
    "iso:country":"US",
    "sg:address":"4882 Swenson Rd",
    "sg:city":"Deer Park",
    "sg:classifiers":[
        {
            "category":"Travel",
            "subcategory":"Travel Agent",
            "type":"Entertainment"
        }
    ],
    "sg:phone":"+1 509 276 1133",
    "sg:postcode":"99006",
    "sg:province":"WA",
    "sg:tags":[
        "agency",
        "bureau"
    ],
    "wof:name":"Globe Trekkers Travel",
    "wof:placetype":"venue"
},
  "geometry": {"coordinates":[-117.563453,47.933765],"type":"Point"}
}