{
  "type": "Feature",
  "properties": {
    "iso:country":"US",
    "sg:address":"11075 Gunderson Ln",
    "sg:city":"Burlington",
    "sg:classifiers":[
        {
            "category":"Home & Garden",
            "subcategory":"Mobile Homes",
            "type":"Retail Goods"
        },
        {
            "category":"Manufacturing",
            "subcategory":"Buildings",
            "type":"Manufacturing & Wholesale Goods"
        }
    ],
    "sg:phone":"+1 360 757 8178",
    "sg:postcode":"98233",
    "sg:province":"WA",
    "sg:tags":[
        "prefab"
    ],
    "wof:name":"North Cascade Mobile Home Sls",
    "wof:placetype":"venue"
},
  "geometry": {"coordinates":[-122.301716,48.485016],"type":"Point"}
}