{
  "type": "Feature",
  "properties": {
    "addr:full":"611 Cowlitz Way Kelso WA 98626",
    "addr:housenumber":"611",
    "addr:postcode":"98626",
    "addr:street":"Cowlitz Way",
    "iso:country":"US",
    "sg:address":"611 Cowlitz Way",
    "sg:city":"Kelso",
    "sg:classifiers":[
        {
            "category":"Banks & Credit Unions",
            "subcategory":"Bank",
            "type":"Services"
        }
    ],
    "sg:phone":"+1 360 423 1190",
    "sg:postcode":"98626",
    "sg:province":"WA",
    "sg:tags":[
        "cashing",
        "check"
    ],
    "wof:name":"Cash Store",
    "wof:placetype":"venue"
},
  "geometry": {"coordinates":[-122.90560000000001,46.146277],"type":"Point"}
}