{
  "type": "Feature",
  "properties": {
    "addr:full":"NE 47th St. and 11th Ave. NE Seattle WA 98127",
    "addr:postcode":"98127",
    "addr:street":"Ne 47Th St. And 11Th Ave. Ne",
    "iso:country":"US",
    "sg:address":"NE 47th St. and 11th Ave. NE",
    "sg:city":"Seattle",
    "sg:classifiers":[
        {
            "category":"Local Transit",
            "type":"Transportation"
        }
    ],
    "sg:phone":"+1 206 553 3000",
    "sg:postcode":"98127",
    "sg:province":"WA",
    "sg:tags":[
        "public"
    ],
    "sg:website":"transit.metrokc.gov/tops/bus/sch...",
    "wof:name":"Metro Bus Route 271",
    "wof:placetype":"venue"
},
  "geometry": {"coordinates":[-122.31636,47.663128],"type":"Point"}
}