{
  "type": "Feature",
  "properties": {
    "addr:full":"4805 Bosworth Dr Snohomish WA 98290",
    "addr:housenumber":"4805",
    "addr:postcode":"98290",
    "addr:street":"Bosworth Dr",
    "iso:country":"US",
    "sg:address":"4805 Bosworth Dr",
    "sg:city":"Snohomish",
    "sg:classifiers":[
        {
            "category":"Retail",
            "subcategory":"Auto Repair",
            "type":"Services"
        }
    ],
    "sg:phone":"+1 360 691 6169",
    "sg:postcode":"98290",
    "sg:province":"WA",
    "sg:tags":[
        "truck"
    ],
    "wof:name":"Vic's Diesel Svc",
    "wof:placetype":"venue"
},
  "geometry": {"coordinates":[-121.95791,48.046469],"type":"Point"}
}