{
  "type": "Feature",
  "properties": {
    "iso:country":"US",
    "sg:address":"67 W Canal Dr",
    "sg:city":"Camano Island",
    "sg:classifiers":[
        {
            "category":"Professional",
            "type":"Services"
        }
    ],
    "sg:phone":"+1 360 387 8978",
    "sg:postcode":"99336",
    "sg:province":"WA",
    "sg:tags":[
        "establishment"
    ],
    "wof:name":"Watts Fluid Air",
    "wof:placetype":"venue"
},
  "geometry": {"coordinates":[-119.117676,46.209557],"type":"Point"}
}