{
  "type": "Feature",
  "properties": {
    "addr:full":"17853 E Lake Desire Dr SE Renton WA 98058",
    "addr:housenumber":"17853",
    "addr:postcode":"98058",
    "addr:street":"E Lake Desire Dr Se",
    "iso:country":"US",
    "sg:address":"17853 E Lake Desire Dr SE",
    "sg:city":"Renton",
    "sg:classifiers":[
        {
            "category":"Professional",
            "subcategory":"Accounting & Tax Preparation",
            "type":"Services"
        }
    ],
    "sg:phone":"+1 425 351 3112",
    "sg:postcode":"98058",
    "sg:province":"WA",
    "wof:name":"Kraght Snell PS",
    "wof:placetype":"venue"
},
  "geometry": {"coordinates":[-122.103706,47.444309],"type":"Point"}
}