{
  "type": "Feature",
  "properties": {
    "addr:full":"419 N Long Rd Spokane Valley WA 99016",
    "addr:housenumber":"419",
    "addr:postcode":"99016",
    "addr:street":"N Long Rd",
    "iso:country":"US",
    "sg:address":"419 N Long Rd",
    "sg:city":"Spokane Valley",
    "sg:classifiers":[
        {
            "category":"Wholesale",
            "subcategory":"Motor Vehicles",
            "type":"Manufacturing & Wholesale Goods"
        }
    ],
    "sg:phone":"+1 509 927 8897",
    "sg:postcode":"99016",
    "sg:province":"WA",
    "sg:tags":[
        "camper",
        "pick"
    ],
    "wof:name":"Roamin' Chariot Industries",
    "wof:placetype":"venue"
},
  "geometry": {"coordinates":[-117.164484,47.660404],"type":"Point"}
}