{
  "type": "Feature",
  "properties": {
    "addr:full":"6807 211th Ave SE Snohomish WA 98290",
    "addr:housenumber":"6807",
    "addr:postcode":"98290",
    "addr:street":"211Th Ave Se",
    "iso:country":"US",
    "sg:address":"6807 211th Ave SE",
    "sg:city":"Snohomish",
    "sg:classifiers":[
        {
            "category":"Arts & Performance",
            "subcategory":"Theater",
            "type":"Entertainment"
        }
    ],
    "sg:phone":"+1 425 335 5088",
    "sg:postcode":"98290",
    "sg:province":"WA",
    "sg:tags":[
        "entertainer",
        "business"
    ],
    "wof:name":"Noah Time Productions",
    "wof:placetype":"venue"
},
  "geometry": {"coordinates":[-121.94465099999999,47.944293],"type":"Point"}
}