{
  "type": "Feature",
  "properties": {
    "addr:full":"1015 State Ave Marysville WA 98270",
    "addr:housenumber":"1015",
    "addr:postcode":"98270",
    "addr:street":"State Ave",
    "iso:country":"US",
    "sg:address":"1015 State Ave",
    "sg:city":"Marysville",
    "sg:classifiers":[
        {
            "category":"Insurance",
            "subcategory":"Insurance Agent",
            "type":"Services"
        }
    ],
    "sg:phone":"+1 425 388 4100",
    "sg:postcode":"98270",
    "sg:province":"WA",
    "sg:website":"www.statefarm.com",
    "wof:name":"State Farm Insurance",
    "wof:placetype":"venue"
},
  "geometry": {"coordinates":[-122.176999,48.061074],"type":"Point"}
}