{
  "type": "Feature",
  "properties": {
    "addr:full":"7 N Herald Rd Spokane Valley WA 99206",
    "addr:housenumber":"7",
    "addr:postcode":"99206",
    "addr:street":"N Herald Rd",
    "iso:country":"US",
    "sg:address":"7 N Herald Rd",
    "sg:city":"Spokane Valley",
    "sg:classifiers":[
        {
            "category":"Sports & Exercise",
            "subcategory":"Gym",
            "type":"Entertainment"
        }
    ],
    "sg:phone":"+1 509 927 0909",
    "sg:postcode":"99206",
    "sg:province":"WA",
    "sg:tags":[
        "club",
        "health",
        "studio",
        "gymnasium"
    ],
    "wof:name":"Valley Fitness",
    "wof:placetype":"venue"
},
  "geometry": {"coordinates":[-117.26947800000001,47.658784],"type":"Point"}
}