{
  "type": "Feature",
  "properties": {
    "addr:full":"1491 Moon Rd Connell WA 99326",
    "addr:housenumber":"1491",
    "addr:postcode":"99326",
    "addr:street":"Moon Rd",
    "iso:country":"US",
    "sg:address":"1491 Moon Rd",
    "sg:city":"Connell",
    "sg:classifiers":[
        {
            "category":"Farming",
            "subcategory":"Farm",
            "type":"Manufacturing & Wholesale Goods"
        }
    ],
    "sg:phone":"+1 509 234 2042",
    "sg:postcode":"99326",
    "sg:province":"WA",
    "sg:tags":[
        "general"
    ],
    "wof:name":"Circle P",
    "wof:placetype":"venue"
},
  "geometry": {"coordinates":[-118.89973000000001,46.673431],"type":"Point"}
}