{
  "type": "Feature",
  "properties": {
    "addr:full":"1019 21st St Anacortes WA 98221",
    "addr:housenumber":"1019",
    "addr:postcode":"98221",
    "addr:street":"21St St",
    "iso:country":"US",
    "sg:address":"1019 21st St",
    "sg:city":"Anacortes",
    "sg:classifiers":[
        {
            "category":"Health Services",
            "subcategory":"Doctor",
            "type":"Services"
        }
    ],
    "sg:phone":"+1 360 299 0965",
    "sg:postcode":"98221",
    "sg:province":"WA",
    "sg:tags":[
        "physician",
        "surgeon"
    ],
    "wof:name":"Gina R. Thompson Md P",
    "wof:placetype":"venue"
},
  "geometry": {"coordinates":[-122.612994,48.505323],"type":"Point"}
}