{
  "type": "Feature",
  "properties": {
    "addr:full":"211 Shore Dr Grapeview WA 98546",
    "addr:housenumber":"211",
    "addr:postcode":"98546",
    "addr:street":"Shore Dr Grapeview",
    "iso:country":"US",
    "sg:address":"211 Shore Dr",
    "sg:city":"Grapeview",
    "sg:classifiers":[
        {
            "category":"Personal",
            "subcategory":"Beauty Salon",
            "type":"Services"
        }
    ],
    "sg:phone":"+1 360 426 6864",
    "sg:postcode":"98546",
    "sg:province":"WA",
    "wof:name":"Friends & Co Hair Pros",
    "wof:placetype":"venue"
},
  "geometry": {"coordinates":[-122.954322,47.32787],"type":"Point"}
}