{
  "type": "Feature",
  "properties": {
    "addr:full":"125 Mulford Rd Toledo WA 98591",
    "addr:housenumber":"125",
    "addr:postcode":"98591",
    "addr:street":"Mulford Rd",
    "iso:country":"US",
    "sg:address":"125 Mulford Rd",
    "sg:city":"Toledo",
    "sg:classifiers":[
        {
            "category":"Retail",
            "subcategory":"Auto Repair",
            "type":"Services"
        }
    ],
    "sg:phone":"+1 360 864 4040",
    "sg:postcode":"98591",
    "sg:province":"WA",
    "sg:tags":[
        "shop",
        "truck"
    ],
    "sg:website":"www.washingtontruckrebuilders.com",
    "wof:name":"Washington Truck Rebuilders",
    "wof:placetype":"venue"
},
  "geometry": {"coordinates":[-122.888441,46.419812],"type":"Point"}
}