{
  "type": "Feature",
  "properties": {
    "addr:full":"570 E Strong Rd Shelton WA 98584",
    "addr:housenumber":"570",
    "addr:postcode":"98584",
    "addr:street":"E Strong Rd",
    "iso:country":"US",
    "sg:address":"570 E Strong Rd",
    "sg:city":"Shelton",
    "sg:classifiers":[
        {
            "category":"Real Estate",
            "subcategory":"Surveying",
            "type":"Services"
        }
    ],
    "sg:phone":"+1 360 426 9118",
    "sg:postcode":"98584",
    "sg:province":"WA",
    "wof:name":"Nor Pac Marine Surveyors LLC",
    "wof:placetype":"venue"
},
  "geometry": {"coordinates":[-122.93509400000001,47.272338],"type":"Point"}
}