{
  "type": "Feature",
  "properties": {
    "addr:full":"1722 S J St Tacoma WA 98405",
    "addr:housenumber":"1722",
    "addr:postcode":"98405",
    "addr:street":"S J St",
    "iso:country":"US",
    "sg:address":"1722 S J St",
    "sg:city":"Tacoma",
    "sg:classifiers":[
        {
            "category":"Organizations",
            "subcategory":"Non-profit Organization",
            "type":"Services"
        }
    ],
    "sg:phone":"+1 253 272 5134",
    "sg:postcode":"98405",
    "sg:province":"WA",
    "wof:name":"Diabetes Association-Pierce",
    "wof:placetype":"venue"
},
  "geometry": {"coordinates":[-122.448759,47.245165],"type":"Point"}
}