{
  "type": "Feature",
  "properties": {
    "addr:full":"9408 N Davies Rd Lake Stevens WA 98258",
    "addr:housenumber":"9408",
    "addr:postcode":"98258",
    "addr:street":"N Davies Rd",
    "iso:country":"US",
    "sg:address":"9408 N Davies Rd",
    "sg:city":"Lake Stevens",
    "sg:classifiers":[
        {
            "category":"Health Services",
            "subcategory":"Doctor",
            "type":"Services"
        }
    ],
    "sg:phone":"+1 425 334 8555",
    "sg:postcode":"98258",
    "sg:province":"WA",
    "sg:tags":[
        "medical"
    ],
    "wof:name":"Lake Stevens Clinic",
    "wof:placetype":"venue"
},
  "geometry": {"coordinates":[-122.104528,48.004662],"type":"Point"}
}