{
  "type": "Feature",
  "properties": {
    "addr:full":"9501 Van Buren Rd Lynden WA 98264",
    "addr:housenumber":"9501",
    "addr:postcode":"98264",
    "addr:street":"Van Buren Rd",
    "iso:country":"US",
    "sg:address":"9501 Van Buren Rd",
    "sg:city":"Lynden",
    "sg:classifiers":[
        {
            "category":"Farming",
            "subcategory":"Dairy Farm",
            "type":"Manufacturing & Wholesale Goods"
        }
    ],
    "sg:phone":"+1 360 988 5924",
    "sg:postcode":"98264",
    "sg:province":"WA",
    "wof:name":"Tj Veenacre Farms Inc",
    "wof:placetype":"venue"
},
  "geometry": {"coordinates":[-122.329804,48.993153],"type":"Point"}
}