{
  "type": "Feature",
  "properties": {
    "addr:full":"6512 23rd Ave NW Seattle WA 98117",
    "addr:housenumber":"6512",
    "addr:postcode":"98117",
    "addr:street":"23Rd Ave Nw",
    "iso:country":"US",
    "sg:address":"6512 23rd Ave NW",
    "sg:city":"Seattle",
    "sg:classifiers":[
        {
            "category":"Education",
            "subcategory":"Preschool",
            "type":"Public Place"
        },
        {
            "category":"Education",
            "subcategory":"School",
            "type":"Public Place"
        }
    ],
    "sg:phone":"+1 206 789 2341",
    "sg:postcode":"98117",
    "sg:province":"WA",
    "sg:tags":[
        "elementary"
    ],
    "wof:name":"65th Street Preschool Co-Op",
    "wof:placetype":"venue"
},
  "geometry": {"coordinates":[-122.385002,47.676102],"type":"Point"}
}