{
  "type": "Feature",
  "properties": {
    "addr:full":"26055 222nd Ct SE Maple Valley WA 98038",
    "addr:housenumber":"26055",
    "addr:postcode":"98038",
    "addr:street":"222Nd Ct Se;Valley",
    "iso:country":"US",
    "sg:address":"26055 222nd Ct SE",
    "sg:city":"Maple Valley",
    "sg:classifiers":[
        {
            "category":"Shopping",
            "subcategory":"Computers & Home Electronics",
            "type":"Retail Goods"
        }
    ],
    "sg:phone":"+1 425 432 1211",
    "sg:postcode":"98038",
    "sg:province":"WA",
    "sg:tags":[
        "sound",
        "software"
    ],
    "wof:name":"Audioamigocom",
    "wof:placetype":"venue"
},
  "geometry": {"coordinates":[-122.04494099999999,47.366769],"type":"Point"}
}