{
  "type": "Feature",
  "properties": {
    "addr:full":"9812 N Wall St Spokane WA 99218",
    "addr:housenumber":"9812",
    "addr:postcode":"99218",
    "addr:street":"N Wall St",
    "iso:country":"US",
    "sg:address":"9812 N Wall St",
    "sg:city":"Spokane",
    "sg:classifiers":[
        {
            "category":"Shopping",
            "type":"Retail Goods"
        }
    ],
    "sg:phone":"+1 509 465 1538",
    "sg:postcode":"99218",
    "sg:province":"WA",
    "sg:tags":[
        "merchandise"
    ],
    "wof:name":"Court of Gentiles",
    "wof:placetype":"venue"
},
  "geometry": {"coordinates":[-117.421667,47.746663],"type":"Point"}
}