{
  "type": "Feature",
  "properties": {
    "addr:full":"31509 Pacific Hwy S Federal Way WA 98003",
    "addr:housenumber":"31509",
    "addr:postcode":"98003",
    "addr:street":"Pacific Hwy S Federal Way",
    "iso:country":"US",
    "sg:address":"31509 Pacific Hwy S",
    "sg:city":"Federal Way",
    "sg:classifiers":[
        {
            "category":"Restaurant",
            "type":"Food & Drink"
        }
    ],
    "sg:phone":"+1 253 946 8833",
    "sg:postcode":"98003",
    "sg:province":"WA",
    "wof:name":"Bangkok Garden Thai Restaurant",
    "wof:placetype":"venue"
},
  "geometry": {"coordinates":[-122.31344199999999,47.321003],"type":"Point"}
}