{
  "type": "Feature",
  "properties": {
    "addr:full":"1933 S 72nd St Tacoma WA 98408",
    "addr:housenumber":"1933",
    "addr:postcode":"98408",
    "addr:street":"S 72Nd St",
    "iso:country":"US",
    "sg:address":"1933 S 72nd St",
    "sg:city":"Tacoma",
    "sg:classifiers":[
        {
            "category":"Restaurant",
            "type":"Food & Drink"
        }
    ],
    "sg:phone":"+1 253 473 5925",
    "sg:postcode":"98408",
    "sg:province":"WA",
    "sg:tags":[
        "style",
        "american",
        "family"
    ],
    "wof:name":"Shari's Restaurants",
    "wof:placetype":"venue"
},
  "geometry": {"coordinates":[-122.459765,47.191837],"type":"Point"}
}