{
  "type": "Feature",
  "properties": {
    "addr:full":"1601 Bethany Rd Grandview WA 98930",
    "addr:housenumber":"1601",
    "addr:postcode":"98930",
    "addr:street":"Bethany Rd",
    "iso:country":"US",
    "sg:address":"1601 Bethany Rd",
    "sg:city":"Grandview",
    "sg:classifiers":[
        {
            "category":"Food & Beverages",
            "subcategory":"Fruits & Vegetables",
            "type":"Retail Goods"
        }
    ],
    "sg:phone":"+1 509 882 4514",
    "sg:postcode":"98930",
    "sg:province":"WA",
    "sg:tags":[
        "produce"
    ],
    "wof:name":"Washington Fruit Adm Svc",
    "wof:placetype":"venue"
},
  "geometry": {"coordinates":[-119.925968,46.295325],"type":"Point"}
}