{
  "type": "Feature",
  "properties": {
    "addr:full":"2000 NE Perkins Way Seattle WA 98155",
    "addr:housenumber":"2000",
    "addr:postcode":"98155",
    "addr:street":"Ne Perkins Way",
    "iso:country":"US",
    "sg:address":"2000 NE Perkins Way",
    "sg:city":"Seattle",
    "sg:classifiers":[
        {
            "category":"Education",
            "subcategory":"School",
            "type":"Public Place"
        }
    ],
    "sg:phone":"+1 206 365 2720",
    "sg:postcode":"98155",
    "sg:province":"WA",
    "sg:tags":[
        "grade",
        "to",
        "eight"
    ],
    "wof:name":"Norht Seattle",
    "wof:placetype":"venue"
},
  "geometry": {"coordinates":[-122.307478,47.76452],"type":"Point"}
}