{
  "type": "Feature",
  "properties": {
    "addr:full":"2011 99th Ave SE Everett WA 98205",
    "addr:housenumber":"2011",
    "addr:postcode":"98205",
    "addr:street":"99Th Ave Se",
    "iso:country":"US",
    "sg:address":"2011 99th Ave SE",
    "sg:city":"Everett",
    "sg:classifiers":[
        {
            "category":"Professional",
            "subcategory":"Art Services",
            "type":"Services"
        }
    ],
    "sg:phone":"+1 425 334 6000",
    "sg:postcode":"98205",
    "sg:province":"WA",
    "sg:tags":[
        "commercial",
        "design"
    ],
    "wof:name":"Quick Sign Inc",
    "wof:placetype":"venue"
},
  "geometry": {"coordinates":[-122.09839700000001,47.978035],"type":"Point"}
}