{
  "type": "Feature",
  "properties": {
    "addr:full":"113 Ave C Snohomish WA 98290",
    "addr:housenumber":"113",
    "addr:postcode":"98290",
    "addr:street":"Ave C",
    "iso:country":"US",
    "sg:address":"113 Ave C",
    "sg:city":"Snohomish",
    "sg:classifiers":[
        {
            "category":"Home & Garden",
            "subcategory":"Furniture",
            "type":"Retail Goods"
        }
    ],
    "sg:phone":"+1 360 568 5344",
    "sg:postcode":"98290",
    "sg:province":"WA",
    "sg:tags":[
        "builder",
        "custom"
    ],
    "wof:name":"Faded Glory LTD",
    "wof:placetype":"venue"
},
  "geometry": {"coordinates":[-122.097105,47.912767],"type":"Point"}
}