{
  "type": "Feature",
  "properties": {
    "iso:country":"US",
    "sg:address":"2919 Rainier Ave",
    "sg:city":"Seattle",
    "sg:classifiers":[
        {
            "category":"Restaurant",
            "type":"Food & Drink"
        }
    ],
    "sg:phone":"+1 206 725 5336",
    "sg:postcode":"98144",
    "sg:province":"WA",
    "wof:name":"Hong Kong Barbeque",
    "wof:placetype":"venue"
},
  "geometry": {"coordinates":[-122.29714800000001,47.576944],"type":"Point"}
}