{
  "type": "Feature",
  "properties": {
    "addr:full":"5300 SW Charlestown St Seattle WA 98116",
    "addr:housenumber":"5300",
    "addr:postcode":"98116",
    "addr:street":"Sw Charlestown St",
    "iso:country":"US",
    "sg:address":"5300 SW Charlestown St",
    "sg:city":"Seattle",
    "sg:classifiers":[
        {
            "category":"Building & Trades",
            "subcategory":"Locksmith",
            "type":"Services"
        }
    ],
    "sg:phone":"+1 206 238 0209",
    "sg:postcode":"98116",
    "sg:province":"WA",
    "sg:tags":[
        "lock",
        "key"
    ],
    "wof:name":"0 Metro Locksmith Seattle WA",
    "wof:placetype":"venue"
},
  "geometry": {"coordinates":[-122.400182,47.570366],"type":"Point"}
}