{
  "type": "Feature",
  "properties": {
    "addr:full":"3815 Fruit Valley Rd Vancouver WA 98660",
    "addr:housenumber":"3815",
    "addr:postcode":"98660",
    "addr:street":"Fruit Valley Rd",
    "iso:country":"US",
    "sg:address":"3815 Fruit Valley Rd",
    "sg:city":"Vancouver",
    "sg:classifiers":[
        {
            "category":"Food & Beverages",
            "subcategory":"Groceries & Convenience Stores",
            "type":"Retail Goods"
        }
    ],
    "sg:phone":"+1 360 693 5244",
    "sg:postcode":"98660",
    "sg:province":"WA",
    "sg:website":"www.chevron.com",
    "wof:name":"Fruit Valley Chevron",
    "wof:placetype":"venue"
},
  "geometry": {"coordinates":[-122.692001,45.649269],"type":"Point"}
}