{
  "type": "Feature",
  "properties": {
    "addr:full":"1156 SE Polk St Camas WA 98607",
    "addr:housenumber":"1156",
    "addr:postcode":"98607",
    "addr:street":"Se Polk St",
    "iso:country":"US",
    "sg:address":"1156 SE Polk St",
    "sg:city":"Camas",
    "sg:classifiers":[
        {
            "category":"Building & Trades",
            "subcategory":"Construction",
            "type":"Services"
        }
    ],
    "sg:phone":"+1 360 833 2681",
    "sg:postcode":"98607",
    "sg:province":"WA",
    "sg:tags":[
        "residential"
    ],
    "wof:name":"Aaron Angelo Development",
    "wof:placetype":"venue"
},
  "geometry": {"coordinates":[-122.39180899999999,45.578661],"type":"Point"}
}