{
  "type": "Feature",
  "properties": {
    "addr:full":"220 Rogers Rd Kalama WA 98625",
    "addr:housenumber":"220",
    "addr:postcode":"98625",
    "addr:street":"Rogers Rd",
    "iso:country":"US",
    "sg:address":"220 Rogers Rd",
    "sg:city":"Kalama",
    "sg:classifiers":[
        {
            "category":"Retail",
            "subcategory":"Animal Services",
            "type":"Services"
        }
    ],
    "sg:phone":"+1 360 673 2657",
    "sg:postcode":"98625",
    "sg:province":"WA",
    "wof:name":"Double H Paints",
    "wof:placetype":"venue"
},
  "geometry": {"coordinates":[-122.804014,46.012377],"type":"Point"}
}