{
  "type": "Feature",
  "properties": {
    "addr:full":"115 E Crawford St Deer Park WA 99006",
    "addr:housenumber":"115",
    "addr:postcode":"99006",
    "addr:street":"E Crawford St",
    "iso:country":"US",
    "sg:address":"115 E Crawford St",
    "sg:city":"Deer Park",
    "sg:classifiers":[
        {
            "category":"Food & Beverages",
            "subcategory":"Groceries & Convenience Stores",
            "type":"Retail Goods"
        }
    ],
    "sg:phone":"+1 509 276 5190",
    "sg:postcode":"99006",
    "sg:province":"WA",
    "wof:name":"Express Way",
    "wof:placetype":"venue"
},
  "geometry": {"coordinates":[-117.47417900000001,47.954373],"type":"Point"}
}