{
  "type": "Feature",
  "properties": {
    "addr:full":"1483 N 20th St Washougal WA 98671",
    "addr:housenumber":"1483",
    "addr:postcode":"98671",
    "addr:street":"N 20Th St",
    "iso:country":"US",
    "sg:address":"1483 N 20th St",
    "sg:city":"Washougal",
    "sg:classifiers":[
        {
            "category":"Manufacturing",
            "subcategory":"Chemicals & Compounds",
            "type":"Manufacturing & Wholesale Goods"
        }
    ],
    "sg:phone":"+1 360 835 3874",
    "sg:postcode":"98671",
    "sg:province":"WA",
    "sg:tags":[
        "manufacture",
        "ink"
    ],
    "wof:name":"Ken Louie and Associates",
    "wof:placetype":"venue"
},
  "geometry": {"coordinates":[-122.351032,45.586771],"type":"Point"}
}