{
  "type": "Feature",
  "properties": {
    "addr:full":"6315 15th Ave NW Seattle WA 98107",
    "addr:housenumber":"6315",
    "addr:postcode":"98107",
    "addr:street":"15Th Ave Nw",
    "iso:country":"US",
    "sg:address":"6315 15th Ave NW",
    "sg:city":"Seattle",
    "sg:classifiers":[
        {
            "category":"Restaurant",
            "type":"Food & Drink"
        }
    ],
    "sg:menulink":"http://www.allmenus.com/wa/seattle/114087-tony-teriyaki--pho-2/menu/",
    "sg:phone":"+1 206 706 4711",
    "sg:postcode":"98107",
    "sg:province":"WA",
    "sg:tags":[
        "asian",
        "vietnamese"
    ],
    "wof:name":"Tony Teriyaki & Pho #2",
    "wof:placetype":"venue"
},
  "geometry": {"coordinates":[-122.37621799999999,47.674726],"type":"Point"}
}