{
  "type": "Feature",
  "properties": {
    "addr:full":"9625 E Big Meadows Rd Chattaroy WA 99003",
    "addr:housenumber":"9625",
    "addr:postcode":"99003",
    "addr:street":"E Big Meadows Rd",
    "iso:country":"US",
    "sg:address":"9625 E Big Meadows Rd",
    "sg:city":"Chattaroy",
    "sg:classifiers":[
        {
            "category":"Personal",
            "type":"Services"
        }
    ],
    "sg:phone":"+1 509 238 6832",
    "sg:postcode":"99003",
    "sg:province":"WA",
    "wof:name":"Inch",
    "wof:placetype":"venue"
},
  "geometry": {"coordinates":[-117.26674,47.865713],"type":"Point"}
}