{
  "type": "Feature",
  "properties": {
    "addr:full":"1912 64th Ave W Fircrest WA 98466",
    "addr:housenumber":"1912",
    "addr:postcode":"98466",
    "addr:street":"64Th Ave W",
    "iso:country":"US",
    "sg:address":"1912 64th Ave W",
    "sg:city":"Fircrest",
    "sg:classifiers":[
        {
            "category":"Organizations",
            "subcategory":"Religious Organization",
            "type":"Services"
        }
    ],
    "sg:phone":"+1 253 272 0330",
    "sg:postcode":"98466",
    "sg:province":"WA",
    "sg:tags":[
        "church"
    ],
    "wof:name":"Church Of Christ Tacoma-Narrow",
    "wof:placetype":"venue"
},
  "geometry": {"coordinates":[-122.52278800000001,47.242556],"type":"Point"}
}