{
  "type": "Feature",
  "properties": {
    "addr:full":"71 Hoquiam Trl Elma WA 98541",
    "addr:housenumber":"71",
    "addr:postcode":"98541",
    "addr:street":"Hoquiam Trl",
    "iso:country":"US",
    "sg:address":"71 Hoquiam Trl",
    "sg:city":"Elma",
    "sg:classifiers":[
        {
            "category":"Professional",
            "subcategory":"Research",
            "type":"Services"
        }
    ],
    "sg:phone":"+1 360 229 0887",
    "sg:postcode":"98541",
    "sg:province":"WA",
    "sg:tags":[
        "organization",
        "noncommercial"
    ],
    "wof:name":"Ypsilon Enterprise",
    "wof:placetype":"venue"
},
  "geometry": {"coordinates":[-123.341978,47.135577],"type":"Point"}
}