{
  "type": "Feature",
  "properties": {
    "addr:full":"16303 25th Ave SE Bothell WA 98012",
    "addr:housenumber":"16303",
    "addr:postcode":"98012",
    "addr:street":"25Th Ave Se",
    "iso:country":"US",
    "sg:address":"16303 25th Ave SE",
    "sg:city":"Bothell",
    "sg:classifiers":[
        {
            "category":"Shopping",
            "subcategory":"Florist",
            "type":"Retail Goods"
        }
    ],
    "sg:phone":"+1 425 503 3526",
    "sg:postcode":"98012",
    "sg:province":"WA",
    "wof:name":"Occasionally Yours",
    "wof:placetype":"venue"
},
  "geometry": {"coordinates":[-122.19917,47.850824],"type":"Point"}
}