{
  "type": "Feature",
  "properties": {
    "addr:full":"24817 52nd Ave E Graham WA 98338",
    "addr:housenumber":"24817",
    "addr:postcode":"98338",
    "addr:street":"52Nd Ave E",
    "iso:country":"US",
    "sg:address":"24817 52nd Ave E",
    "sg:city":"Graham",
    "sg:classifiers":[
        {
            "category":"Professional",
            "type":"Services"
        }
    ],
    "sg:phone":"+1 253 847 3903",
    "sg:postcode":"98338",
    "sg:province":"WA",
    "wof:name":"Ace Railroad Special",
    "wof:placetype":"venue"
},
  "geometry": {"coordinates":[-122.360401,47.030257],"type":"Point"}
}