{
  "type": "Feature",
  "properties": {
    "addr:full":"456 26th Ave Longview WA 98632",
    "addr:housenumber":"456",
    "addr:postcode":"98632",
    "addr:street":"26Th Ave",
    "iso:country":"US",
    "sg:address":"456 26th Ave",
    "sg:city":"Longview",
    "sg:classifiers":[
        {
            "category":"Personal",
            "subcategory":"Beauty Salon",
            "type":"Services"
        }
    ],
    "sg:phone":"+1 360 577 4905",
    "sg:postcode":"98632",
    "sg:province":"WA",
    "sg:tags":[
        "shop"
    ],
    "wof:name":"Tip & Toes",
    "wof:placetype":"venue"
},
  "geometry": {"coordinates":[-122.957888,46.12758],"type":"Point"}
}