{
  "type": "Feature",
  "properties": {
    "addr:full":"41901 196th Ave SE Enumclaw WA 98022",
    "addr:housenumber":"41901",
    "addr:postcode":"98022",
    "addr:street":"196Th Ave Se",
    "iso:country":"US",
    "sg:address":"41901 196th Ave SE",
    "sg:city":"Enumclaw",
    "sg:classifiers":[
        {
            "category":"Manufacturing",
            "subcategory":"Tools & Machinery",
            "type":"Manufacturing & Wholesale Goods"
        }
    ],
    "sg:phone":"+1 360 825 2367",
    "sg:postcode":"98022",
    "sg:province":"WA",
    "sg:tags":[
        "machine",
        "vending",
        "mfg"
    ],
    "wof:name":"Jennings Marketing Enterp",
    "wof:placetype":"venue"
},
  "geometry": {"coordinates":[-122.080324,47.225477],"type":"Point"}
}