{
  "type": "Feature",
  "properties": {
    "iso:country":"US",
    "sg:address":"50 Comstock St",
    "sg:city":"Richland",
    "sg:classifiers":[
        {
            "category":"Travel",
            "subcategory":"Hotels & Motels",
            "type":"Entertainment"
        }
    ],
    "sg:phone":"+1 509 946 4661",
    "sg:postcode":"99352",
    "sg:province":"WA",
    "sg:tags":[
        "operation",
        "eating"
    ],
    "wof:name":"Shilo Inn Rivershore Motel",
    "wof:placetype":"venue"
},
  "geometry": {"coordinates":[-119.268997,46.268129],"type":"Point"}
}