{
  "type": "Feature",
  "properties": {
    "addr:full":"4364 Birch Bay Lynden Rd Blaine WA 98230",
    "addr:housenumber":"4364",
    "addr:postcode":"98230",
    "addr:street":"Birch Bay Lynden Rd",
    "iso:country":"US",
    "sg:address":"4364 Birch Bay Lynden Rd",
    "sg:city":"Blaine",
    "sg:classifiers":[
        {
            "category":"Wholesale",
            "subcategory":"Vending Machines",
            "type":"Manufacturing & Wholesale Goods"
        }
    ],
    "sg:phone":"+1 360 371 7676",
    "sg:postcode":"98230",
    "sg:province":"WA",
    "sg:tags":[
        "operator"
    ],
    "wof:name":"A&K Enterprises",
    "wof:placetype":"venue"
},
  "geometry": {"coordinates":[-122.71242100000001,48.935748],"type":"Point"}
}