{
  "type": "Feature",
  "properties": {
    "addr:full":"911 Western Ave Ste 306A Seattle WA 98104",
    "addr:housenumber":"911",
    "addr:postcode":"98104",
    "addr:street":"Western Ave Ste 306A",
    "iso:country":"US",
    "sg:address":"911 Western Ave Ste 306A",
    "sg:city":"Seattle",
    "sg:classifiers":[
        {
            "category":"Sports & Exercise",
            "subcategory":"Gym",
            "type":"Entertainment"
        }
    ],
    "sg:phone":"+1 206 730 7768",
    "sg:postcode":"98104",
    "sg:province":"WA",
    "sg:tags":[
        "pilate"
    ],
    "sg:website":"www.studiojacks.com",
    "wof:name":"Studio Jacks Pilates Studio",
    "wof:placetype":"venue"
},
  "geometry": {"coordinates":[-122.33712,47.60379],"type":"Point"}
}