{
  "type": "Feature",
  "properties": {
    "addr:full":"11621 E Trent Ave Spokane Valley WA 99206",
    "addr:housenumber":"11621",
    "addr:postcode":"99206",
    "addr:street":"E Trent Ave",
    "iso:country":"US",
    "sg:address":"11621 E Trent Ave",
    "sg:city":"Spokane Valley",
    "sg:classifiers":[
        {
            "category":"Home & Garden",
            "subcategory":"Garden Supply",
            "type":"Retail Goods"
        }
    ],
    "sg:phone":"+1 509 893 1843",
    "sg:postcode":"99206",
    "sg:province":"WA",
    "sg:tags":[
        "landscaping",
        "equipment"
    ],
    "wof:name":"D M Layman Inc",
    "wof:placetype":"venue"
},
  "geometry": {"coordinates":[-117.249323,47.687801],"type":"Point"}
}