{
  "type": "Feature",
  "properties": {
    "addr:full":"303 Division St Grandview WA 98930",
    "addr:housenumber":"303",
    "addr:postcode":"98930",
    "addr:street":"Division St",
    "iso:country":"US",
    "sg:address":"303 Division St",
    "sg:city":"Grandview",
    "sg:classifiers":[
        {
            "category":"Wholesale",
            "subcategory":"Electrical",
            "type":"Manufacturing & Wholesale Goods"
        }
    ],
    "sg:phone":"+1 509 882 3000",
    "sg:postcode":"98930",
    "sg:province":"WA",
    "sg:tags":[
        "control",
        "security",
        "system"
    ],
    "wof:name":"American Protection",
    "wof:placetype":"venue"
},
  "geometry": {"coordinates":[-119.901869,46.253499],"type":"Point"}
}