{
  "type": "Feature",
  "properties": {
    "addr:full":"2402 Fruitvale Blvd Yakima WA 98902",
    "addr:housenumber":"2402",
    "addr:postcode":"98902",
    "addr:street":"Fruitvale Blvd",
    "iso:country":"US",
    "sg:address":"2402 Fruitvale Blvd",
    "sg:city":"Yakima",
    "sg:classifiers":[
        {
            "category":"Shopping",
            "subcategory":"Gifts & Souvenirs",
            "type":"Retail Goods"
        }
    ],
    "sg:phone":"+1 509 574 5281",
    "sg:postcode":"98902",
    "sg:province":"WA",
    "wof:name":"Village Shoppe",
    "wof:placetype":"venue"
},
  "geometry": {"coordinates":[-120.54219000000001,46.613461],"type":"Point"}
}