{
  "type": "Feature",
  "properties": {
    "addr:full":"16306 W Lake Goodwin Rd Stanwood WA 98292",
    "addr:housenumber":"16306",
    "addr:postcode":"98292",
    "addr:street":"W Lake Goodwin Rd",
    "iso:country":"US",
    "sg:address":"16306 W Lake Goodwin Rd",
    "sg:city":"Stanwood",
    "sg:classifiers":[
        {
            "category":"Building & Trades",
            "subcategory":"Construction",
            "type":"Services"
        }
    ],
    "sg:phone":"+1 360 654 0904",
    "sg:postcode":"98292",
    "sg:province":"WA",
    "sg:tags":[
        "repairing",
        "residential",
        "remodeling",
        "contractor"
    ],
    "wof:name":"3 D Construction Inc",
    "wof:placetype":"venue"
},
  "geometry": {"coordinates":[-122.303321,48.144927],"type":"Point"}
}