{
  "type": "Feature",
  "properties": {
    "addr:full":"1702 S 6th Ave Tacoma WA 98405",
    "addr:housenumber":"1702",
    "addr:postcode":"98405",
    "addr:street":"S 6Th Ave",
    "iso:country":"US",
    "sg:address":"1702 S 6th Ave",
    "sg:city":"Tacoma",
    "sg:classifiers":[
        {
            "category":"Professional",
            "subcategory":"Lawyer & Legal Services",
            "type":"Services"
        }
    ],
    "sg:phone":"+1 253 593 4190",
    "sg:postcode":"98405",
    "sg:province":"WA",
    "sg:tags":[
        "attorney"
    ],
    "wof:name":"Stan Bonner Law Office",
    "wof:placetype":"venue"
},
  "geometry": {"coordinates":[-122.462903,47.256021],"type":"Point"}
}