{
  "type": "Feature",
  "properties": {
    "addr:full":"359 Wetherbee Ln Enumclaw WA 98022",
    "addr:housenumber":"359",
    "addr:postcode":"98022",
    "addr:street":"Wetherbee Ln",
    "iso:country":"US",
    "sg:address":"359 Wetherbee Ln",
    "sg:city":"Enumclaw",
    "sg:classifiers":[
        {
            "category":"Building & Trades",
            "subcategory":"Construction",
            "type":"Services"
        }
    ],
    "sg:phone":"+1 360 825 8469",
    "sg:postcode":"98022",
    "sg:province":"WA",
    "sg:tags":[
        "carpentry",
        "contractor"
    ],
    "wof:name":"Advanced Concepts Business",
    "wof:placetype":"venue"
},
  "geometry": {"coordinates":[-122.01329699999999,47.194236],"type":"Point"}
}