{
  "type": "Feature",
  "properties": {
    "addr:full":"1500 S Taft St Kennewick WA 99338",
    "addr:housenumber":"1500",
    "addr:postcode":"99338",
    "addr:street":"S Taft St",
    "iso:country":"US",
    "sg:address":"1500 S Taft St",
    "sg:city":"Kennewick",
    "sg:classifiers":[
        {
            "category":"Building & Trades",
            "subcategory":"Construction",
            "type":"Services"
        }
    ],
    "sg:phone":"+1 509 735 1824",
    "sg:postcode":"99338",
    "sg:province":"WA",
    "sg:tags":[
        "wallcoverings-installation",
        "wallpaper",
        "painting",
        "contractor"
    ],
    "wof:name":"Sam Hopwood Enterprises",
    "wof:placetype":"venue"
},
  "geometry": {"coordinates":[-119.213638,46.19556],"type":"Point"}
}