{
  "type": "Feature",
  "properties": {
    "addr:full":"15 N Grant St Spokane WA 99202",
    "addr:housenumber":"15",
    "addr:postcode":"99202",
    "addr:street":"N Grant St",
    "iso:country":"US",
    "sg:address":"15 N Grant St",
    "sg:city":"Spokane",
    "sg:classifiers":[
        {
            "category":"Freight",
            "type":"Transportation"
        }
    ],
    "sg:phone":"+1 509 747 3174",
    "sg:postcode":"99202",
    "sg:province":"WA",
    "sg:tags":[
        "trucking"
    ],
    "wof:name":"C J Trucking",
    "wof:placetype":"venue"
},
  "geometry": {"coordinates":[-117.40531300000001,47.657961],"type":"Point"}
}