{
  "type": "Feature",
  "properties": {
    "addr:full":"623 9th Ave SW Puyallup WA 98371",
    "addr:housenumber":"623",
    "addr:postcode":"98371",
    "addr:street":"9Th Ave Sw",
    "iso:country":"US",
    "sg:address":"623 9th Ave SW",
    "sg:city":"Puyallup",
    "sg:classifiers":[
        {
            "category":"Organizations",
            "subcategory":"Religious Organization",
            "type":"Services"
        }
    ],
    "sg:phone":"+1 253 845 6232",
    "sg:postcode":"98371",
    "sg:province":"WA",
    "sg:tags":[
        "place",
        "worship",
        "church"
    ],
    "sg:website":"http://www.fccpuyallup.com",
    "wof:name":"First Christian Church",
    "wof:placetype":"venue"
},
  "geometry": {"coordinates":[-122.301237,47.18446],"type":"Point"}
}