{
  "type": "Feature",
  "properties": {
    "addr:full":"1299 Grow Ave NW Bainbridge Island WA 98110",
    "addr:housenumber":"1299",
    "addr:postcode":"98110",
    "addr:street":"Grow Ave Nw",
    "iso:country":"US",
    "sg:address":"1299 Grow Ave NW",
    "sg:city":"Bainbridge Island",
    "sg:classifiers":[
        {
            "category":"Retail",
            "subcategory":"Event Space",
            "type":"Services"
        }
    ],
    "sg:phone":"+1 206 842 8846",
    "sg:postcode":"98110",
    "sg:province":"WA",
    "sg:tags":[
        "venue"
    ],
    "wof:name":"Masonic Temple",
    "wof:placetype":"venue"
},
  "geometry": {"coordinates":[-122.525002,47.635601],"type":"Point"}
}