{
  "type": "Feature",
  "properties": {
    "addr:full":"4933 Pine Rd NE Bremerton WA 98311",
    "addr:housenumber":"4933",
    "addr:postcode":"98311",
    "addr:street":"Pine Rd Ne",
    "iso:country":"US",
    "sg:address":"4933 Pine Rd NE",
    "sg:city":"Bremerton",
    "sg:classifiers":[
        {
            "category":"Organizations",
            "subcategory":"Community Association",
            "type":"Services"
        }
    ],
    "sg:phone":"+1 360 373 8029",
    "sg:postcode":"98311",
    "sg:province":"WA",
    "wof:name":"American Ex Prisoners of War",
    "wof:placetype":"venue"
},
  "geometry": {"coordinates":[-122.63936699999999,47.607935],"type":"Point"}
}