{
  "type": "Feature",
  "properties": {
    "addr:full":"112 N Wenatchee Ave Wenatchee WA 98801",
    "addr:housenumber":"112",
    "addr:postcode":"98801",
    "addr:street":"N Wenatchee Ave",
    "iso:country":"US",
    "sg:address":"112 N Wenatchee Ave",
    "sg:city":"Wenatchee",
    "sg:classifiers":[
        {
            "category":"Shopping",
            "subcategory":"Used Merchandise",
            "type":"Retail Goods"
        }
    ],
    "sg:phone":"+1 509 665 8444",
    "sg:postcode":"98801",
    "sg:province":"WA",
    "sg:tags":[
        "shop",
        "consignment"
    ],
    "wof:name":"Willow Creek Consignments",
    "wof:placetype":"venue"
},
  "geometry": {"coordinates":[-120.312618,47.426043],"type":"Point"}
}