{
  "type": "Feature",
  "properties": {
    "addr:full":"28712 SE 440th St Enumclaw WA 98022",
    "addr:postcode":"28712;98022",
    "addr:street":"Se 440Th St",
    "iso:country":"US",
    "sg:address":"28712 SE 440th St",
    "sg:city":"Enumclaw",
    "sg:classifiers":[
        {
            "category":"Manufacturing",
            "subcategory":"Lumber",
            "type":"Manufacturing & Wholesale Goods"
        }
    ],
    "sg:phone":"+1 360 825 3478",
    "sg:postcode":"98022",
    "sg:province":"WA",
    "sg:tags":[
        "burl",
        "wood"
    ],
    "wof:name":"C&C Logging",
    "wof:placetype":"venue"
},
  "geometry": {"coordinates":[-121.95302700000001,47.209759],"type":"Point"}
}