{
  "type": "Feature",
  "properties": {
    "iso:country":"US",
    "sg:address":"140 Mill Rd",
    "sg:city":"Sequim",
    "sg:classifiers":[
        {
            "category":"Retail",
            "subcategory":"Photofinishing",
            "type":"Services"
        }
    ],
    "sg:phone":"+1 360 683 9672",
    "sg:postcode":"98382",
    "sg:province":"WA",
    "sg:tags":[
        "photo",
        "studio",
        "portrait"
    ],
    "wof:name":"Custom Photo",
    "wof:placetype":"venue"
},
  "geometry": {"coordinates":[-123.167393,48.080462],"type":"Point"}
}