{
  "type": "Feature",
  "properties": {
    "addr:full":"23200 100th Ave W Edmonds WA 98020",
    "addr:housenumber":"23200",
    "addr:postcode":"98020",
    "addr:street":"100Th Ave W",
    "iso:country":"US",
    "sg:address":"23200 100th Ave W",
    "sg:city":"Edmonds",
    "sg:classifiers":[
        {
            "category":"Education",
            "subcategory":"School",
            "type":"Public Place"
        }
    ],
    "sg:phone":"+1 425 670 7495",
    "sg:postcode":"98020",
    "sg:province":"WA",
    "sg:tags":[
        "elementary"
    ],
    "wof:name":"Chase Lake Elementary School",
    "wof:placetype":"venue"
},
  "geometry": {"coordinates":[-122.366725,47.788731],"type":"Point"}
}