{
  "type": "Feature",
  "properties": {
    "addr:full":"11401 3rd Ave SE Apt Z12 Everett WA 98208",
    "addr:housenumber":"11401",
    "addr:postcode":"98208",
    "addr:street":"3Rd Ave Se Apt Z12",
    "iso:country":"US",
    "sg:address":"11401 3rd Ave SE Apt Z12",
    "sg:city":"Everett",
    "sg:classifiers":[
        {
            "category":"Professional",
            "subcategory":"Advertising",
            "type":"Services"
        }
    ],
    "sg:phone":"+1 425 355 0146",
    "sg:postcode":"98208",
    "sg:province":"WA",
    "sg:tags":[
        "product",
        "advertising-promotional",
        "specialty"
    ],
    "wof:name":"Globalink Direct",
    "wof:placetype":"venue"
},
  "geometry": {"coordinates":[-122.22793,47.894623],"type":"Point"}
}