{
  "type": "Feature",
  "properties": {
    "addr:full":"2253 Gilman Dr W Seattle WA 98119",
    "addr:housenumber":"2253",
    "addr:postcode":"98119",
    "addr:street":"Gilman Dr W",
    "iso:country":"US",
    "sg:address":"2253 Gilman Dr W",
    "sg:city":"Seattle",
    "sg:classifiers":[
        {
            "category":"Health Services",
            "subcategory":"Health Practitioner",
            "type":"Services"
        }
    ],
    "sg:phone":"+1 206 281 7777",
    "sg:postcode":"98119",
    "sg:province":"WA",
    "sg:tags":[
        "hypnotherapy",
        "hypnotist"
    ],
    "wof:name":"Bev Baker Hypnotherapist",
    "wof:placetype":"venue"
},
  "geometry": {"coordinates":[-122.373983,47.639798],"type":"Point"}
}