{
  "type": "Feature",
  "properties": {
    "addr:full":"19711 64th Ave W Lynnwood WA 98036",
    "addr:housenumber":"19711",
    "addr:postcode":"98036",
    "addr:street":"64Th Ave W",
    "iso:country":"US",
    "sg:address":"19711 64th Ave W",
    "sg:city":"Lynnwood",
    "sg:classifiers":[
        {
            "category":"Manufacturing",
            "subcategory":"Tools & Machinery",
            "type":"Manufacturing & Wholesale Goods"
        }
    ],
    "sg:phone":"+1 425 712 9223",
    "sg:postcode":"98036",
    "sg:province":"WA",
    "sg:tags":[
        "mfg",
        "set",
        "commercial",
        "physical"
    ],
    "wof:name":"Synergy Power (usa) Corp",
    "wof:placetype":"venue"
},
  "geometry": {"coordinates":[-122.319557,47.818338],"type":"Point"}
}