{
  "type": "Feature",
  "properties": {
    "iso:country":"US",
    "sg:address":"6502 146th St SE",
    "sg:city":"Snohomish",
    "sg:classifiers":[
        {
            "category":"Professional",
            "subcategory":"Management & Consulting",
            "type":"Services"
        }
    ],
    "sg:phone":"+1 425 337 0853",
    "sg:postcode":"98296",
    "sg:province":"WA",
    "sg:tags":[
        "consultant"
    ],
    "wof:name":"Stu Schell Consulting & Design",
    "wof:placetype":"venue"
},
  "geometry": {"coordinates":[-122.144756,47.864978],"type":"Point"}
}