{
  "type": "Feature",
  "properties": {
    "addr:full":"819 Bay St Port Orchard WA 98366",
    "addr:housenumber":"819",
    "addr:postcode":"98366",
    "addr:street":"Bay St",
    "iso:country":"US",
    "sg:address":"819 Bay St",
    "sg:city":"Port Orchard",
    "sg:classifiers":[
        {
            "category":"Shopping",
            "type":"Retail Goods"
        }
    ],
    "sg:phone":"+1 360 895 1201",
    "sg:postcode":"98366",
    "sg:province":"WA",
    "sg:tags":[
        "merchandise"
    ],
    "wof:name":"All Games Great & Small",
    "wof:placetype":"venue"
},
  "geometry": {"coordinates":[-122.63504500000001,47.54148],"type":"Point"}
}