{
  "type": "Feature",
  "properties": {
    "addr:full":"4318 Murphy Dr NW Gig Harbor WA 98335",
    "addr:housenumber":"4318",
    "addr:postcode":"98335",
    "addr:street":"Murphy Dr Nw",
    "iso:country":"US",
    "sg:address":"4318 Murphy Dr NW",
    "sg:city":"Gig Harbor",
    "sg:classifiers":[
        {
            "category":"Professional",
            "subcategory":"Business Services",
            "type":"Services"
        }
    ],
    "sg:phone":"+1 253 851 9636",
    "sg:postcode":"98335",
    "sg:province":"WA",
    "wof:name":"Mojacom",
    "wof:placetype":"venue"
},
  "geometry": {"coordinates":[-122.59895299999999,47.30021],"type":"Point"}
}