{
  "type": "Feature",
  "properties": {
    "addr:full":"1111 S 344th St Federal Way WA 98003",
    "addr:housenumber":"1111",
    "addr:postcode":"98003",
    "addr:street":"S 344Th St",
    "iso:country":"US",
    "sg:address":"1111 S 344th St",
    "sg:city":"Federal Way",
    "sg:classifiers":[
        {
            "category":"Airline",
            "type":"Transportation"
        }
    ],
    "sg:phone":"+1 253 838 3902",
    "sg:postcode":"98003",
    "sg:province":"WA",
    "sg:tags":[
        "cargo",
        "air"
    ],
    "wof:name":"Hawaiian Distribution System",
    "wof:placetype":"venue"
},
  "geometry": {"coordinates":[-122.31625,47.293437],"type":"Point"}
}