{
  "type": "Feature",
  "properties": {
    "addr:full":"441 E Columbia Dr Kennewick WA 99336",
    "addr:housenumber":"441",
    "addr:postcode":"99336",
    "addr:street":"E Columbia Dr",
    "iso:country":"US",
    "sg:address":"441 E Columbia Dr",
    "sg:city":"Kennewick",
    "sg:classifiers":[
        {
            "category":"Shopping",
            "subcategory":"Hobbies, Toys, & Games",
            "type":"Retail Goods"
        }
    ],
    "sg:phone":"+1 509 783 6204",
    "sg:postcode":"99336",
    "sg:province":"WA",
    "sg:tags":[
        "item"
    ],
    "wof:name":"Kb Toys",
    "wof:placetype":"venue"
},
  "geometry": {"coordinates":[-119.110123,46.212109],"type":"Point"}
}