{
  "type": "Feature",
  "properties": {
    "addr:full":"11424 238th St E Graham WA 98338",
    "addr:housenumber":"11424",
    "addr:postcode":"98338",
    "addr:street":"238Th St E",
    "iso:country":"US",
    "sg:address":"11424 238th St E",
    "sg:city":"Graham",
    "sg:classifiers":[
        {
            "category":"Home & Garden",
            "subcategory":"Carpets & Floor Coverings",
            "type":"Retail Goods"
        }
    ],
    "sg:phone":"+1 253 847 5690",
    "sg:postcode":"98338",
    "sg:province":"WA",
    "sg:tags":[
        "construction",
        "nonresidential",
        "la"
    ],
    "wof:name":"Metcalf Carpet Supply Inc",
    "wof:placetype":"venue"
},
  "geometry": {"coordinates":[-122.27932300000001,47.040045],"type":"Point"}
}