{
  "type": "Feature",
  "properties": {
    "addr:full":"4248 Van Horn Ln Bellingham WA 98226",
    "addr:housenumber":"4248",
    "addr:postcode":"98226",
    "addr:street":"Van Horn Ln",
    "iso:country":"US",
    "sg:address":"4248 Van Horn Ln",
    "sg:city":"Bellingham",
    "sg:classifiers":[
        {
            "category":"Farming",
            "subcategory":"Nursery",
            "type":"Manufacturing & Wholesale Goods"
        }
    ],
    "sg:phone":"+1 360 671 9153",
    "sg:postcode":"98226",
    "sg:province":"WA",
    "sg:tags":[
        "grower",
        "nursery-wholesale"
    ],
    "wof:name":"Green Frog Nursery",
    "wof:placetype":"venue"
},
  "geometry": {"coordinates":[-122.575844,48.79513],"type":"Point"}
}