{
  "type": "Feature",
  "properties": {
    "addr:full":"14 Rock Island Rd East Wenatchee WA 98802",
    "addr:housenumber":"14",
    "addr:postcode":"98802",
    "addr:street":"Rock Island Rd",
    "iso:country":"US",
    "sg:address":"14 Rock Island Rd",
    "sg:city":"East Wenatchee",
    "sg:classifiers":[
        {
            "category":"Food & Beverages",
            "subcategory":"Groceries & Convenience Stores",
            "type":"Retail Goods"
        }
    ],
    "sg:phone":"+1 509 886 5230",
    "sg:postcode":"98802",
    "sg:province":"WA",
    "wof:name":"E-Z Mart East",
    "wof:placetype":"venue"
},
  "geometry": {"coordinates":[-120.28854,47.405191],"type":"Point"}
}