{
  "type": "Feature",
  "properties": {
    "addr:full":"410 4th Ave N Edmonds WA 98020",
    "addr:housenumber":"410",
    "addr:postcode":"98020",
    "addr:street":"4Th Ave N",
    "iso:country":"US",
    "sg:address":"410 4th Ave N",
    "sg:city":"Edmonds",
    "sg:classifiers":[
        {
            "category":"Education",
            "subcategory":"Dance Studio",
            "type":"Public Place"
        }
    ],
    "sg:phone":"+1 425 778 5784",
    "sg:postcode":"98020",
    "sg:province":"WA",
    "sg:tags":[
        "instruction",
        "dancing"
    ],
    "wof:name":"Academy Gymnastics Of Edmonds",
    "wof:placetype":"venue"
},
  "geometry": {"coordinates":[-122.376435,47.815006],"type":"Point"}
}