{
  "type": "Feature",
  "properties": {
    "addr:full":"11323 Hwy 99 Everett WA 98204",
    "addr:housenumber":"11323",
    "addr:postcode":"98204",
    "addr:street":"Hwy 99",
    "iso:country":"US",
    "sg:address":"11323 Hwy 99",
    "sg:city":"Everett",
    "sg:classifiers":[
        {
            "category":"Retail",
            "subcategory":"Auto Repair",
            "type":"Services"
        }
    ],
    "sg:phone":"+1 425 347 8721",
    "sg:postcode":"98204",
    "sg:province":"WA",
    "sg:tags":[
        "body",
        "automotive"
    ],
    "wof:name":"Collision Connection Inc",
    "wof:placetype":"venue"
},
  "geometry": {"coordinates":[-122.25254700000001,47.89555],"type":"Point"}
}