{
  "type": "Feature",
  "properties": {
    "addr:full":"3422 161st Ct SE Bellevue WA 98008",
    "addr:housenumber":"3422",
    "addr:postcode":"98008",
    "addr:street":"161St Ct Se",
    "iso:country":"US",
    "sg:address":"3422 161st Ct SE",
    "sg:city":"Bellevue",
    "sg:classifiers":[
        {
            "category":"Personal",
            "subcategory":"Beauty Salon",
            "type":"Services"
        }
    ],
    "sg:phone":"+1 425 641 4515",
    "sg:postcode":"98008",
    "sg:province":"WA",
    "sg:tags":[
        "shop"
    ],
    "wof:name":"Losan Inc",
    "wof:placetype":"venue"
},
  "geometry": {"coordinates":[-122.125255,47.578934],"type":"Point"}
}