{
  "type": "Feature",
  "properties": {
    "addr:full":"903 5th Ave Seattle WA 98164",
    "addr:housenumber":"903",
    "addr:postcode":"98164",
    "addr:street":"5Th Ave",
    "iso:country":"US",
    "sg:address":"903 5th Ave",
    "sg:city":"Seattle",
    "sg:classifiers":[
        {
            "category":"Building & Trades",
            "subcategory":"Locksmith",
            "type":"Services"
        }
    ],
    "sg:phone":"+1 206 237 0812",
    "sg:postcode":"98164",
    "sg:province":"WA",
    "sg:tags":[
        "key"
    ],
    "wof:name":"All Seattle Locksmith",
    "wof:placetype":"venue"
},
  "geometry": {"coordinates":[-122.331288,47.605746],"type":"Point"}
}