{
  "type": "Feature",
  "properties": {
    "addr:full":"212 Sawmill Rd Sequim WA 98382",
    "addr:housenumber":"212",
    "addr:postcode":"98382",
    "addr:street":"Sawmill Rd",
    "iso:country":"US",
    "sg:address":"212 Sawmill Rd",
    "sg:city":"Sequim",
    "sg:classifiers":[
        {
            "category":"Building & Trades",
            "subcategory":"Landscaping Services",
            "type":"Services"
        }
    ],
    "sg:phone":"+1 360 582 1176",
    "sg:postcode":"98382",
    "sg:province":"WA",
    "sg:tags":[
        "lawn",
        "maintenance",
        "grounds"
    ],
    "wof:name":"Brad's Lawn Aerating",
    "wof:placetype":"venue"
},
  "geometry": {"coordinates":[-123.160712,48.088627],"type":"Point"}
}