{
  "type": "Feature",
  "properties": {
    "iso:country":"US",
    "sg:address":"615 S 9th St",
    "sg:city":"Tacoma",
    "sg:classifiers":[
        {
            "category":"Personal",
            "type":"Services"
        }
    ],
    "sg:phone":"+1 253 798 7285",
    "sg:postcode":"98405",
    "sg:province":"WA",
    "sg:tags":[
        "executive"
    ],
    "wof:name":"Pierce County Information Svcs",
    "wof:placetype":"venue"
},
  "geometry": {"coordinates":[-122.445542,47.254836],"type":"Point"}
}