{
  "type": "Feature",
  "properties": {
    "addr:full":"316 5th St Wenatchee WA 98801",
    "addr:housenumber":"316",
    "addr:postcode":"98801",
    "addr:street":"5Th St",
    "iso:country":"US",
    "sg:address":"316 5th St",
    "sg:city":"Wenatchee",
    "sg:classifiers":[
        {
            "category":"Insurance",
            "subcategory":"Insurance Agent",
            "type":"Services"
        }
    ],
    "sg:phone":"+1 509 665 0505",
    "sg:postcode":"98801",
    "sg:province":"WA",
    "wof:name":"Valley Insurance Corp",
    "wof:placetype":"venue"
},
  "geometry": {"coordinates":[-120.31974,47.42988],"type":"Point"}
}