{
  "type": "Feature",
  "properties": {
    "addr:full":"1010 Atlantic Ave Woodland WA 98674",
    "addr:housenumber":"1010",
    "addr:postcode":"98674",
    "addr:street":"Atlantic Ave",
    "iso:country":"US",
    "sg:address":"1010 Atlantic Ave",
    "sg:city":"Woodland",
    "sg:classifiers":[
        {
            "category":"Autos & Motor Vehicles",
            "subcategory":"Fuel & Gas Station",
            "type":"Retail Goods"
        }
    ],
    "sg:phone":"+1 360 225 8475",
    "sg:postcode":"98674",
    "sg:province":"WA",
    "sg:tags":[
        "oil"
    ],
    "wof:name":"Woodland Chevron",
    "wof:placetype":"venue"
},
  "geometry": {"coordinates":[-122.742605,45.906978],"type":"Point"}
}