{
  "type": "Feature",
  "properties": {
    "addr:full":"1770 State Rte 508 Onalaska WA 98570",
    "addr:housenumber":"1770",
    "addr:postcode":"98570",
    "addr:street":"State Rte 508",
    "iso:country":"US",
    "sg:address":"1770 State Rte 508",
    "sg:city":"Onalaska",
    "sg:classifiers":[
        {
            "category":"Personal",
            "subcategory":"Shoe Repair & Shine",
            "type":"Services"
        }
    ],
    "sg:phone":"+1 360 978 6969",
    "sg:postcode":"98570",
    "sg:province":"WA",
    "sg:tags":[
        "repairing",
        "boot"
    ],
    "wof:name":"Country Shoe Repair",
    "wof:placetype":"venue"
},
  "geometry": {"coordinates":[-122.71951799999999,46.575631],"type":"Point"}
}