{
  "type": "Feature",
  "properties": {
    "addr:full":"1203 W Yakima Ave Selah WA 98942",
    "addr:housenumber":"1203",
    "addr:postcode":"98942",
    "addr:street":"W Yakima Ave",
    "iso:country":"US",
    "sg:address":"1203 W Yakima Ave",
    "sg:city":"Selah",
    "sg:classifiers":[
        {
            "category":"Professional",
            "subcategory":"Accounting & Tax Preparation",
            "type":"Services"
        }
    ],
    "sg:phone":"+1 509 697 5497",
    "sg:postcode":"98942",
    "sg:province":"WA",
    "wof:name":"Laurel K Stewart",
    "wof:placetype":"venue"
},
  "geometry": {"coordinates":[-120.544932,46.65276],"type":"Point"}
}