{
  "type": "Feature",
  "properties": {
    "addr:full":"510 SE 157th Ave Vancouver WA 98684",
    "addr:housenumber":"510",
    "addr:postcode":"98684",
    "addr:street":"Se 157Th Ave",
    "iso:country":"US",
    "sg:address":"510 SE 157th Ave",
    "sg:city":"Vancouver",
    "sg:classifiers":[
        {
            "category":"Real Estate",
            "subcategory":"Real Estate Operator",
            "type":"Services"
        }
    ],
    "sg:phone":"+1 360 254 8366",
    "sg:postcode":"98684",
    "sg:province":"WA",
    "sg:tags":[
        "apartment"
    ],
    "wof:name":"Ironwood Luxury Apartments",
    "wof:placetype":"venue"
},
  "geometry": {"coordinates":[-122.511107,45.617847],"type":"Point"}
}