{
  "type": "Feature",
  "properties": {
    "addr:full":"246 2 School House Rd Friday Harbor WA 98250",
    "addr:housenumber":"246 2",
    "addr:postcode":"98250",
    "addr:street":"School House Rd",
    "iso:country":"US",
    "sg:address":"246 2 School House Rd",
    "sg:city":"Friday Harbor",
    "sg:classifiers":[
        {
            "category":"Building & Trades",
            "subcategory":"Electrical",
            "type":"Services"
        }
    ],
    "sg:phone":"+1 360 378 6640",
    "sg:postcode":"98250",
    "sg:province":"WA",
    "sg:tags":[
        "electrical",
        "contractor"
    ],
    "wof:name":"Guard Electric Inc",
    "wof:placetype":"venue"
},
  "geometry": {"coordinates":[-122.899097,48.492473],"type":"Point"}
}