{
  "type": "Feature",
  "properties": {
    "addr:full":"2610 Kauffman Ave Vancouver WA 98660",
    "addr:postcode":"2610;98660",
    "addr:street":"Kauffman Ave",
    "iso:country":"US",
    "sg:address":"2610 Kauffman Ave",
    "sg:city":"Vancouver",
    "sg:classifiers":[
        {
            "category":"Wholesale",
            "subcategory":"Construction Materials",
            "type":"Manufacturing & Wholesale Goods"
        }
    ],
    "sg:phone":"+1 360 696 4421",
    "sg:postcode":"98660",
    "sg:province":"WA",
    "sg:tags":[
        "brick"
    ],
    "wof:name":"Hidden Brick Co",
    "wof:placetype":"venue"
},
  "geometry": {"coordinates":[-122.681017,45.641262],"type":"Point"}
}