{
  "type": "Feature",
  "properties": {
    "addr:full":"3002 NE 112th Ave Vancouver WA 98682",
    "addr:housenumber":"3002",
    "addr:postcode":"98682",
    "addr:street":"Ne 112Th Ave",
    "iso:country":"US",
    "sg:address":"3002 NE 112th Ave",
    "sg:city":"Vancouver",
    "sg:classifiers":[
        {
            "category":"Manufacturing",
            "subcategory":"Tools & Machinery",
            "type":"Manufacturing & Wholesale Goods"
        }
    ],
    "sg:phone":"+1 360 896 8779",
    "sg:postcode":"98682",
    "sg:province":"WA",
    "sg:tags":[
        "residential",
        "lighting",
        "fixture",
        "mfg"
    ],
    "wof:name":"Builders Lighting Store",
    "wof:placetype":"venue"
},
  "geometry": {"coordinates":[-122.55803299999999,45.644037],"type":"Point"}
}