{
  "type": "Feature",
  "properties": {
    "addr:full":"2830 Sunset Ln NE Renton WA 98056",
    "addr:housenumber":"2830",
    "addr:postcode":"98056",
    "addr:street":"Sunset Ln Ne",
    "iso:country":"US",
    "sg:address":"2830 Sunset Ln NE",
    "sg:city":"Renton",
    "sg:classifiers":[
        {
            "category":"Bakery",
            "type":"Food & Drink"
        }
    ],
    "sg:phone":"+1 425 277 8600",
    "sg:postcode":"98056",
    "sg:province":"WA",
    "wof:name":"Simply Fresh Bakery",
    "wof:placetype":"venue"
},
  "geometry": {"coordinates":[-122.1811,47.500966],"type":"Point"}
}