{
  "type": "Feature",
  "properties": {
    "addr:full":"116 Aumick Rd Vader WA 98593",
    "addr:housenumber":"116",
    "addr:postcode":"98593",
    "addr:street":"Aumick Rd",
    "iso:country":"US",
    "sg:address":"116 Aumick Rd",
    "sg:city":"Vader",
    "sg:classifiers":[
        {
            "category":"Professional",
            "type":"Services"
        }
    ],
    "sg:phone":"+1 360 295 3778",
    "sg:postcode":"98593",
    "sg:province":"WA",
    "wof:name":"Darla A Anderson",
    "wof:placetype":"venue"
},
  "geometry": {"coordinates":[-122.993168,46.422376],"type":"Point"}
}