{
  "type": "Feature",
  "properties": {
    "addr:full":"516 W Pine St Centralia WA 98531",
    "addr:housenumber":"516",
    "addr:postcode":"98531",
    "addr:street":"W Pine St",
    "iso:country":"US",
    "sg:address":"516 W Pine St",
    "sg:city":"Centralia",
    "sg:classifiers":[
        {
            "category":"Personal",
            "subcategory":"Barber",
            "type":"Services"
        }
    ],
    "sg:phone":"+1 360 330 2838",
    "sg:postcode":"98531",
    "sg:province":"WA",
    "sg:tags":[
        "shop"
    ],
    "wof:name":"Joz Barbershop",
    "wof:placetype":"venue"
},
  "geometry": {"coordinates":[-122.95966300000001,46.718262],"type":"Point"}
}