{
  "type": "Feature",
  "properties": {
    "addr:full":"1818 226th Pl NE Sammamish WA 98074",
    "addr:housenumber":"1818",
    "addr:postcode":"98074",
    "addr:street":"226Th Pl Ne",
    "iso:country":"US",
    "sg:address":"1818 226th Pl NE",
    "sg:city":"Sammamish",
    "sg:classifiers":[
        {
            "category":"Food & Beverages",
            "subcategory":"Candy",
            "type":"Retail Goods"
        }
    ],
    "sg:phone":"+1 425 868 1437",
    "sg:postcode":"98074",
    "sg:province":"WA",
    "sg:tags":[
        "confectionery"
    ],
    "wof:name":"Candy Magic",
    "wof:placetype":"venue"
},
  "geometry": {"coordinates":[-122.03752299999999,47.624716],"type":"Point"}
}