{
  "type": "Feature",
  "properties": {
    "addr:full":"910 Riverview Blvd Clarkston WA 99403",
    "addr:housenumber":"910",
    "addr:postcode":"99403",
    "addr:street":"Riverview Blvd",
    "iso:country":"US",
    "sg:address":"910 Riverview Blvd",
    "sg:city":"Clarkston",
    "sg:classifiers":[
        {
            "category":"Building & Trades",
            "subcategory":"Construction",
            "type":"Services"
        }
    ],
    "sg:phone":"+1 509 758 2206",
    "sg:postcode":"99403",
    "sg:province":"WA",
    "sg:tags":[
        "house"
    ],
    "wof:name":"Anderson Construction",
    "wof:placetype":"venue"
},
  "geometry": {"coordinates":[-117.039354,46.412296],"type":"Point"}
}