{
  "type": "Feature",
  "properties": {
    "addr:full":"5311 Fern Ave NE Bremerton WA 98311",
    "addr:housenumber":"5311",
    "addr:postcode":"98311",
    "addr:street":"Fern Ave Ne",
    "iso:country":"US",
    "sg:address":"5311 Fern Ave NE",
    "sg:city":"Bremerton",
    "sg:classifiers":[
        {
            "category":"Wholesale",
            "subcategory":"Electrical",
            "type":"Manufacturing & Wholesale Goods"
        }
    ],
    "sg:phone":"+1 360 373 8195",
    "sg:postcode":"98311",
    "sg:province":"WA",
    "sg:tags":[
        "burglar",
        "alarm",
        "monitoring",
        "system"
    ],
    "wof:name":"Viking Security Services Inc",
    "wof:placetype":"venue"
},
  "geometry": {"coordinates":[-122.599975,47.610552],"type":"Point"}
}