{
  "type": "Feature",
  "properties": {
    "addr:full":"7100 E Green Lake Dr N Seattle WA 98115",
    "addr:housenumber":"7100",
    "addr:postcode":"98115",
    "addr:street":"E Green Lake Dr N",
    "iso:country":"US",
    "sg:address":"7100 E Green Lake Dr N",
    "sg:city":"Seattle",
    "sg:classifiers":[
        {
            "category":"Restaurant",
            "type":"Food & Drink"
        }
    ],
    "sg:phone":"+1 206 523 9594",
    "sg:postcode":"98115",
    "sg:province":"WA",
    "sg:tags":[
        "tea",
        "coffee",
        "eating"
    ],
    "sg:website":"www.starbucks.com",
    "wof:name":"Starbucks",
    "wof:placetype":"venue"
},
  "geometry": {"coordinates":[-122.32539199999999,47.679989],"type":"Point"}
}