{
  "type": "Feature",
  "properties": {
    "addr:full":"1810 Kauffman Ave Vancouver WA 98660",
    "addr:housenumber":"1810",
    "addr:postcode":"98660",
    "addr:street":"Kauffman Ave",
    "iso:country":"US",
    "sg:address":"1810 Kauffman Ave",
    "sg:city":"Vancouver",
    "sg:classifiers":[
        {
            "category":"Organizations",
            "subcategory":"Religious Organization",
            "type":"Services"
        }
    ],
    "sg:phone":"+1 360 258 8703",
    "sg:postcode":"98660",
    "sg:province":"WA",
    "sg:tags":[
        "churches-non-denominational"
    ],
    "wof:name":"Renewed Hope Ministries",
    "wof:placetype":"venue"
},
  "geometry": {"coordinates":[-122.681254,45.634817],"type":"Point"}
}