{
  "type": "Feature",
  "properties": {
    "addr:full":"19117 85th Avenue Ct E Puyallup WA 98375",
    "addr:housenumber":"19117",
    "addr:postcode":"98375",
    "addr:street":"85Th Avenue Ct E",
    "iso:country":"US",
    "sg:address":"19117 85th Avenue Ct E",
    "sg:city":"Puyallup",
    "sg:classifiers":[
        {
            "category":"Building & Trades",
            "subcategory":"Cleaning & Sanitation",
            "type":"Services"
        }
    ],
    "sg:phone":"+1 253 589 0907",
    "sg:postcode":"98375",
    "sg:province":"WA",
    "sg:tags":[
        "maintenance"
    ],
    "wof:name":"EE Enterprises",
    "wof:placetype":"venue"
},
  "geometry": {"coordinates":[-122.315819,47.082429],"type":"Point"}
}