{
  "type": "Feature",
  "properties": {
    "addr:full":"2012 Broadway St Vancouver WA 98663",
    "addr:housenumber":"2012",
    "addr:postcode":"98663",
    "addr:street":"Broadway St",
    "iso:country":"US",
    "sg:address":"2012 Broadway St",
    "sg:city":"Vancouver",
    "sg:classifiers":[
        {
            "category":"Professional",
            "type":"Services"
        }
    ],
    "sg:phone":"+1 360 695 1704",
    "sg:postcode":"98663",
    "sg:province":"WA",
    "sg:website":"www.kidstoadopt.org/",
    "wof:name":"Kids To Adopt",
    "wof:placetype":"venue"
},
  "geometry": {"coordinates":[-122.67067900000001,45.637293],"type":"Point"}
}