{
  "type": "Feature",
  "properties": {
    "addr:full":"12744 Bel Red Rd Bellevue WA 98005",
    "addr:housenumber":"12744",
    "addr:postcode":"98005",
    "addr:street":"Bel Red Rd",
    "iso:country":"US",
    "sg:address":"12744 Bel Red Rd",
    "sg:city":"Bellevue",
    "sg:classifiers":[
        {
            "category":"Retail",
            "subcategory":"Repair Shop",
            "type":"Services"
        }
    ],
    "sg:phone":"+1 425 787 5884",
    "sg:postcode":"98005",
    "sg:province":"WA",
    "sg:tags":[
        "bathtub",
        "sink",
        "refinishing"
    ],
    "wof:name":"Emerald City Refinishing Spec",
    "wof:placetype":"venue"
},
  "geometry": {"coordinates":[-122.171227,47.620666],"type":"Point"}
}