{
  "type": "Feature",
  "properties": {
    "addr:full":"17 Lentz Dr Aberdeen WA 98520",
    "addr:housenumber":"17",
    "addr:postcode":"98520",
    "addr:street":"Lentz Dr",
    "iso:country":"US",
    "sg:address":"17 Lentz Dr",
    "sg:city":"Aberdeen",
    "sg:classifiers":[
        {
            "category":"Manufacturing",
            "subcategory":"Lumber",
            "type":"Manufacturing & Wholesale Goods"
        }
    ],
    "sg:phone":"+1 360 533 4375",
    "sg:postcode":"98520",
    "sg:province":"WA",
    "sg:tags":[
        "logging"
    ],
    "wof:name":"Peter Raich Logging Co",
    "wof:placetype":"venue"
},
  "geometry": {"coordinates":[-123.772443,47.059544],"type":"Point"}
}