{
  "type": "Feature",
  "properties": {
    "addr:full":"10139 US Hwy 12 Rochester WA 98579",
    "addr:housenumber":"10139",
    "addr:postcode":"98579",
    "addr:street":"Us Hwy 12",
    "iso:country":"US",
    "sg:address":"10139 US Hwy 12",
    "sg:city":"Rochester",
    "sg:classifiers":[
        {
            "category":"Shopping",
            "subcategory":"Bicycles & Sporting Goods",
            "type":"Retail Goods"
        }
    ],
    "sg:phone":"+1 360 273 0565",
    "sg:postcode":"98579",
    "sg:province":"WA",
    "wof:name":"Chieftain Handymen Inc",
    "wof:placetype":"venue"
},
  "geometry": {"coordinates":[-123.09683099999999,46.821741],"type":"Point"}
}