{
  "type": "Feature",
  "properties": {
    "addr:full":"1227 26th St SE Auburn WA 98002",
    "addr:housenumber":"1227",
    "addr:postcode":"98002",
    "addr:street":"26Th St Se",
    "iso:country":"US",
    "sg:address":"1227 26th St SE",
    "sg:city":"Auburn",
    "sg:classifiers":[
        {
            "category":"Shopping",
            "type":"Retail Goods"
        }
    ],
    "sg:phone":"+1 253 833 6829",
    "sg:postcode":"98002",
    "sg:province":"WA",
    "sg:tags":[
        "merchandise"
    ],
    "wof:name":"Bill S Jackie Collectibles",
    "wof:placetype":"venue"
},
  "geometry": {"coordinates":[-122.213076,47.285538],"type":"Point"}
}