{
  "type": "Feature",
  "properties": {
    "addr:full":"9 Marshall St Davenport WA 99122",
    "addr:housenumber":"9",
    "addr:postcode":"99122",
    "addr:street":"Marshall St",
    "iso:country":"US",
    "sg:address":"9 Marshall St",
    "sg:city":"Davenport",
    "sg:classifiers":[
        {
            "category":"Social Services",
            "subcategory":"Adult Care",
            "type":"Services"
        }
    ],
    "sg:phone":"+1 509 725 1155",
    "sg:postcode":"99122",
    "sg:province":"WA",
    "sg:tags":[
        "home"
    ],
    "wof:name":"Serene Meadows",
    "wof:placetype":"venue"
},
  "geometry": {"coordinates":[-118.14207399999999,47.651527],"type":"Point"}
}