{
  "type": "Feature",
  "properties": {
    "addr:full":"10216 SE 256th St 321 Kent WA 98030",
    "addr:housenumber":"10216;321",
    "addr:postcode":"98030",
    "addr:street":"Se 256Th St",
    "iso:country":"US",
    "sg:address":"10216 SE 256th St 321",
    "sg:city":"Kent",
    "sg:classifiers":[
        {
            "category":"Professional",
            "subcategory":"Computer Services",
            "type":"Services"
        },
        {
            "category":"Internet Cafe",
            "subcategory":"None",
            "type":"Food & Drink"
        }
    ],
    "sg:phone":"+1 253 850 2457",
    "sg:postcode":"98030",
    "sg:province":"WA",
    "sg:tags":[
        "product",
        "software"
    ],
    "sg:website":"http://www.organizedexpressions.com",
    "wof:name":"Lns Software Solutions",
    "wof:placetype":"venue"
},
  "geometry": {"coordinates":[-122.20410200000001,47.372556],"type":"Point"}
}