{
  "type": "Feature",
  "properties": {
    "addr:full":"803 Columbia Park Trl Richland WA 99352",
    "addr:housenumber":"803",
    "addr:postcode":"99352",
    "addr:street":"Columbia Park Trl",
    "iso:country":"US",
    "sg:address":"803 Columbia Park Trl",
    "sg:city":"Richland",
    "sg:classifiers":[
        {
            "category":"Real Estate",
            "subcategory":"Surveying",
            "type":"Services"
        }
    ],
    "sg:phone":"+1 509 627 5656",
    "sg:postcode":"99352",
    "sg:province":"WA",
    "sg:tags":[
        "professional",
        "land"
    ],
    "wof:name":"Rogers Surveying Inc",
    "wof:placetype":"venue"
},
  "geometry": {"coordinates":[-119.24637199999999,46.239066],"type":"Point"}
}