{
  "type": "Feature",
  "properties": {
    "addr:full":"100 N Park St Aberdeen WA 98520",
    "addr:housenumber":"100",
    "addr:postcode":"98520",
    "addr:street":"N Park St",
    "iso:country":"US",
    "sg:address":"100 N Park St",
    "sg:city":"Aberdeen",
    "sg:classifiers":[
        {
            "category":"Autos & Motor Vehicles",
            "subcategory":"Automobile Sales",
            "type":"Retail Goods"
        },
        {
            "category":"Retail",
            "subcategory":"Auto Rental",
            "type":"Services"
        },
        {
            "category":"Building & Trades",
            "subcategory":"Equipment Rental",
            "type":"Services"
        }
    ],
    "sg:phone":"+1 360 533 3852",
    "sg:postcode":"98520",
    "sg:province":"WA",
    "sg:tags":[
        "truck",
        "used",
        "moving"
    ],
    "sg:website":"http://budgettruck.com/IYP_tl",
    "wof:name":"The Dog House DBA/Budget Truck Rental",
    "wof:placetype":"venue"
},
  "geometry": {"coordinates":[-123.826965,46.970886],"type":"Point"}
}