{
  "type": "Feature",
  "properties": {
    "addr:full":"1107 Olympic Way W Seattle WA 98119",
    "addr:housenumber":"1107",
    "addr:postcode":"98119",
    "addr:street":"Olympic Way W",
    "iso:country":"US",
    "sg:address":"1107 Olympic Way W",
    "sg:city":"Seattle",
    "sg:classifiers":[
        {
            "category":"Professional",
            "subcategory":"Business Services",
            "type":"Services"
        }
    ],
    "sg:phone":"+1 206 282 0311",
    "sg:postcode":"98119",
    "sg:province":"WA",
    "sg:tags":[
        "financial"
    ],
    "wof:name":"Gary Stevens & Co",
    "wof:placetype":"venue"
},
  "geometry": {"coordinates":[-122.368881,47.629707],"type":"Point"}
}