{
  "type": "Feature",
  "properties": {
    "addr:full":"131 Lummi Cir La Conner WA 98257",
    "addr:housenumber":"131",
    "addr:postcode":"98257",
    "addr:street":"Lummi Cir",
    "iso:country":"US",
    "sg:address":"131 Lummi Cir",
    "sg:city":"La Conner",
    "sg:classifiers":[
        {
            "category":"Autos & Motor Vehicles",
            "subcategory":"Boat Sales",
            "type":"Retail Goods"
        }
    ],
    "sg:phone":"+1 360 466 2419",
    "sg:postcode":"98257",
    "sg:province":"WA",
    "wof:name":"Sun Valley Marine",
    "wof:placetype":"venue"
},
  "geometry": {"coordinates":[-122.50889599999999,48.383341],"type":"Point"}
}