{
  "type": "Feature",
  "properties": {
    "addr:full":"3148 Michigan St Longview WA 98632",
    "addr:housenumber":"3148",
    "addr:postcode":"98632",
    "addr:street":"Michigan St",
    "iso:country":"US",
    "sg:address":"3148 Michigan St",
    "sg:city":"Longview",
    "sg:classifiers":[
        {
            "category":"Personal",
            "subcategory":"Barber",
            "type":"Services"
        }
    ],
    "sg:phone":"+1 360 425 0360",
    "sg:postcode":"98632",
    "sg:province":"WA",
    "wof:name":"Darrel's Barber Stylist",
    "wof:placetype":"venue"
},
  "geometry": {"coordinates":[-122.965305,46.147181],"type":"Point"}
}