{
  "type": "Feature",
  "properties": {
    "addr:full":"478 N Market Blvd Chehalis WA 98532",
    "addr:housenumber":"478",
    "addr:postcode":"98532",
    "addr:street":"N Market Blvd",
    "iso:country":"US",
    "sg:address":"478 N Market Blvd",
    "sg:city":"Chehalis",
    "sg:classifiers":[
        {
            "category":"Professional",
            "subcategory":"Lawyer & Legal Services",
            "type":"Services"
        }
    ],
    "sg:phone":"+1 360 740 0733",
    "sg:postcode":"98532",
    "sg:province":"WA",
    "sg:tags":[
        "attorney"
    ],
    "wof:name":"Robert L Schroeter",
    "wof:placetype":"venue"
},
  "geometry": {"coordinates":[-122.96884300000001,46.664487],"type":"Point"}
}