{
  "type": "Feature",
  "properties": {
    "addr:full":"5700 100th St SW Ste 390 Lakewood WA 98499",
    "addr:housenumber":"5700",
    "addr:postcode":"98499",
    "addr:street":"100Th St Sw Ste 390",
    "iso:country":"US",
    "sg:address":"5700 100th St SW Ste 390",
    "sg:city":"Lakewood",
    "sg:classifiers":[
        {
            "category":"Home & Garden",
            "subcategory":"Carpets & Floor Coverings",
            "type":"Retail Goods"
        }
    ],
    "sg:phone":"+1 253 588 7703",
    "sg:postcode":"98499",
    "sg:province":"WA",
    "sg:tags":[
        "mattress"
    ],
    "sg:website":"www.sleepcountry.com",
    "wof:name":"Sleep Country USA",
    "wof:placetype":"venue"
},
  "geometry": {"coordinates":[-122.51300000000001,47.166698],"type":"Point"}
}