{
  "type": "Feature",
  "properties": {
    "addr:full":"2506 SW Portland Ct Seattle WA 98106",
    "addr:housenumber":"2506",
    "addr:postcode":"98106",
    "addr:street":"Sw Portland Ct",
    "iso:country":"US",
    "sg:address":"2506 SW Portland Ct",
    "sg:city":"Seattle",
    "sg:classifiers":[
        {
            "category":"Professional",
            "subcategory":"Management & Consulting",
            "type":"Services"
        },
        {
            "category":"Professional",
            "subcategory":"Advertising",
            "type":"Services"
        },
        {
            "category":"Professional",
            "subcategory":"Computer Services",
            "type":"Services"
        }
    ],
    "sg:phone":"+1 206 354 9272",
    "sg:postcode":"98106",
    "sg:province":"WA",
    "sg:tags":[
        "web",
        "marketing",
        "site",
        "program",
        "design",
        "internet",
        "consultant"
    ],
    "sg:website":"http://www.seattleweb.net",
    "wof:name":"Seattle Web Services",
    "wof:placetype":"venue"
},
  "geometry": {"coordinates":[-122.36524799999999,47.533211],"type":"Point"}
}