{
  "type": "Feature",
  "properties": {
    "addr:full":"101 N Tacoma Ave Tacoma WA 98403",
    "addr:housenumber":"101",
    "addr:postcode":"98403",
    "addr:street":"N Tacoma Ave",
    "iso:country":"US",
    "sg:address":"101 N Tacoma Ave",
    "sg:city":"Tacoma",
    "sg:classifiers":[
        {
            "category":"Bars & Pubs",
            "type":"Food & Drink"
        }
    ],
    "sg:phone":"+1 253 627 9014",
    "sg:postcode":"98403",
    "sg:province":"WA",
    "wof:name":"Pub Tel",
    "wof:placetype":"venue"
},
  "geometry": {"coordinates":[-122.44984700000001,47.265052],"type":"Point"}
}