{
  "type": "Feature",
  "properties": {
    "addr:full":"12702 NE Proctor Rd Woodland WA 98674",
    "addr:housenumber":"12702",
    "addr:postcode":"98674",
    "addr:street":"Ne Proctor Rd",
    "iso:country":"US",
    "sg:address":"12702 NE Proctor Rd",
    "sg:city":"Woodland",
    "sg:classifiers":[
        {
            "category":"Building & Trades",
            "subcategory":"Construction",
            "type":"Services"
        }
    ],
    "sg:phone":"+1 425 263 4779",
    "sg:postcode":"98674",
    "sg:province":"WA",
    "sg:tags":[
        "contractor"
    ],
    "wof:name":"Clark Cnty Deck Rail Orna Wldg",
    "wof:placetype":"venue"
},
  "geometry": {"coordinates":[-122.53921200000001,45.934864],"type":"Point"}
}