{
  "type": "Feature",
  "properties": {
    "addr:full":"1507 N Cedar St Tacoma WA 98406",
    "addr:housenumber":"1507",
    "addr:postcode":"98406",
    "addr:street":"N Cedar St",
    "iso:country":"US",
    "sg:address":"1507 N Cedar St",
    "sg:city":"Tacoma",
    "sg:classifiers":[
        {
            "category":"Professional",
            "subcategory":"Art Services",
            "type":"Services"
        }
    ],
    "sg:phone":"+1 253 761 8105",
    "sg:postcode":"98406",
    "sg:province":"WA",
    "sg:tags":[
        "commercial",
        "design"
    ],
    "wof:name":"Hanks Design",
    "wof:placetype":"venue"
},
  "geometry": {"coordinates":[-122.476254,47.264518],"type":"Point"}
}