{
  "type": "Feature",
  "properties": {
    "addr:full":"2110 Coral Sea Ave Oak Harbor WA 98277",
    "addr:housenumber":"2110",
    "addr:postcode":"98277",
    "addr:street":"Coral Sea Ave",
    "iso:country":"US",
    "sg:address":"2110 Coral Sea Ave",
    "sg:city":"Oak Harbor",
    "sg:classifiers":[
        {
            "category":"Shopping",
            "subcategory":"Clothing, Apparel, & Fashions",
            "type":"Retail Goods"
        }
    ],
    "sg:phone":"+1 360 257 0555",
    "sg:postcode":"98277",
    "sg:province":"WA",
    "sg:tags":[
        "family"
    ],
    "wof:name":"Usn Exchange",
    "wof:placetype":"venue"
},
  "geometry": {"coordinates":[-122.628139,48.284151],"type":"Point"}
}