{
  "type": "Feature",
  "properties": {
    "addr:full":"701 9th St Benton City WA 99320",
    "addr:housenumber":"701",
    "addr:postcode":"99320",
    "addr:street":"9Th St",
    "iso:country":"US",
    "sg:address":"701 9th St",
    "sg:city":"Benton City",
    "sg:classifiers":[
        {
            "category":"Manufacturing",
            "subcategory":"Printing",
            "type":"Manufacturing & Wholesale Goods"
        }
    ],
    "sg:phone":"+1 509 588 4417",
    "sg:postcode":"99320",
    "sg:province":"WA",
    "sg:tags":[
        "commercial"
    ],
    "wof:name":"Big Print Shop",
    "wof:placetype":"venue"
},
  "geometry": {"coordinates":[-119.487543,46.265913],"type":"Point"}
}