{
  "type": "Feature",
  "properties": {
    "addr:full":"2424 Mildred St W Tacoma WA 98466",
    "addr:housenumber":"2424",
    "addr:postcode":"98466",
    "addr:street":"Mildred St W",
    "iso:country":"US",
    "sg:address":"2424 Mildred St W",
    "sg:city":"Tacoma",
    "sg:classifiers":[
        {
            "category":"Banks & Credit Unions",
            "subcategory":"Bank",
            "type":"Services"
        },
        {
            "category":"Banks & Credit Unions",
            "subcategory":"Financial Services",
            "type":"Services"
        }
    ],
    "sg:phone":"+1 253 593 3810",
    "sg:postcode":"98466",
    "sg:province":"WA",
    "sg:tags":[
        "saving",
        "loan",
        "commercial"
    ],
    "sg:website":"http://www.key.com",
    "wof:name":"Keybank National Association",
    "wof:placetype":"venue"
},
  "geometry": {"coordinates":[-122.526371,47.238602],"type":"Point"}
}