{
  "type": "Feature",
  "properties": {
    "addr:full":"5209 36th Ave SW Seattle WA 98126",
    "addr:housenumber":"5209",
    "addr:postcode":"98126",
    "addr:street":"36Th Ave Sw",
    "iso:country":"US",
    "sg:address":"5209 36th Ave SW",
    "sg:city":"Seattle",
    "sg:classifiers":[
        {
            "category":"Organizations",
            "subcategory":"Political Organization",
            "type":"Services"
        }
    ],
    "sg:phone":"+1 206 935 9176",
    "sg:postcode":"98126",
    "sg:province":"WA",
    "wof:name":"Committee To Elect Eileen Cody",
    "wof:placetype":"venue"
},
  "geometry": {"coordinates":[-122.37761,47.555462],"type":"Point"}
}