{
  "type": "Feature",
  "properties": {
    "addr:full":"1615 N 145th St Seattle WA 98133",
    "addr:housenumber":"1615",
    "addr:postcode":"98133",
    "addr:street":"N 145Th St",
    "iso:country":"US",
    "sg:address":"1615 N 145th St",
    "sg:city":"Seattle",
    "sg:classifiers":[
        {
            "category":"Retail",
            "subcategory":"Repair Shop",
            "type":"Services"
        }
    ],
    "sg:phone":"+1 206 365 9199",
    "sg:postcode":"98133",
    "sg:province":"WA",
    "wof:name":"JP Custom Upholstery Inc",
    "wof:placetype":"venue"
},
  "geometry": {"coordinates":[-122.33898600000001,47.734056],"type":"Point"}
}