{
  "type": "Feature",
  "properties": {
    "addr:full":"17325 Alder Way Lynnwood WA 98037",
    "addr:housenumber":"17325",
    "addr:postcode":"98037",
    "addr:street":"Alder Way",
    "iso:country":"US",
    "sg:address":"17325 Alder Way",
    "sg:city":"Lynnwood",
    "sg:classifiers":[
        {
            "category":"Building & Trades",
            "subcategory":"Construction",
            "type":"Services"
        }
    ],
    "sg:phone":"+1 425 742 1520",
    "sg:postcode":"98037",
    "sg:province":"WA",
    "sg:tags":[
        "excavation",
        "contractor"
    ],
    "wof:name":"Micro Excavation",
    "wof:placetype":"venue"
},
  "geometry": {"coordinates":[-122.260949,47.839782],"type":"Point"}
}