{
  "type": "Feature",
  "properties": {
    "iso:country":"US",
    "sg:address":"17406 NE 13th Pl",
    "sg:city":"Bellevue",
    "sg:classifiers":[
        {
            "category":"Professional",
            "type":"Services"
        },
        {
            "category":"Health Services",
            "subcategory":"Medical Lab",
            "type":"Services"
        }
    ],
    "sg:phone":"+1 425 957 0426",
    "sg:postcode":"98008",
    "sg:province":"WA",
    "sg:tags":[
        "laboratory"
    ],
    "wof:name":"Art and Function Dental",
    "wof:placetype":"venue"
},
  "geometry": {"coordinates":[-122.107303,47.621855],"type":"Point"}
}