{
  "type": "Feature",
  "properties": {
    "addr:full":"3394 Bell Rd NE Moses Lake WA 98837",
    "addr:housenumber":"3394",
    "addr:postcode":"98837",
    "addr:street":"Bell Rd Ne",
    "iso:country":"US",
    "sg:address":"3394 Bell Rd NE",
    "sg:city":"Moses Lake",
    "sg:classifiers":[
        {
            "category":"Professional",
            "subcategory":"Testing Lab",
            "type":"Services"
        },
        {
            "category":"Farming",
            "subcategory":"Farm & Veterinary Services",
            "type":"Manufacturing & Wholesale Goods"
        }
    ],
    "sg:phone":"+1 509 766 7701",
    "sg:postcode":"98837",
    "sg:province":"WA",
    "sg:tags":[
        "soil",
        "laboratory"
    ],
    "wof:name":"Best-Test Analytical Services",
    "wof:placetype":"venue"
},
  "geometry": {"coordinates":[-119.23831199999999,47.137135],"type":"Point"}
}