{
  "type": "Feature",
  "properties": {
    "iso:country":"US",
    "sg:address":"3321 6th Ave",
    "sg:city":"Tacoma",
    "sg:classifiers":[
        {
            "category":"Real Estate",
            "subcategory":"Real Estate Operator",
            "type":"Services"
        }
    ],
    "sg:phone":"+1 253 475 6610",
    "sg:postcode":"98406",
    "sg:province":"WA",
    "sg:tags":[
        "apartment"
    ],
    "wof:name":"Dowling Court",
    "wof:placetype":"venue"
},
  "geometry": {"coordinates":[-122.48049,47.255346],"type":"Point"}
}