{
  "type": "Feature",
  "properties": {
    "addr:full":"9122 E Sprague Ave Spokane WA 99206",
    "addr:housenumber":"9122",
    "addr:postcode":"99206",
    "addr:street":"E Sprague Ave",
    "iso:country":"US",
    "sg:address":"9122 E Sprague Ave",
    "sg:city":"Spokane",
    "sg:classifiers":[
        {
            "category":"Restaurant",
            "type":"Food & Drink"
        }
    ],
    "sg:menulink":"http://www.allmenus.com/wa/spokane/78114-papa-murphys/menu/",
    "sg:phone":"+1 509 922 3222",
    "sg:postcode":"99206",
    "sg:province":"WA",
    "sg:tags":[
        "american",
        "pizza"
    ],
    "wof:name":"Papa Murphy's",
    "wof:placetype":"venue"
},
  "geometry": {"coordinates":[-117.281909,47.657007],"type":"Point"}
}