{
  "type": "Feature",
  "properties": {
    "addr:full":"2132 2nd Avenue Seattle WA 98121",
    "addr:housenumber":"2132",
    "addr:postcode":"98121",
    "addr:street":"2Nd Avenue",
    "iso:country":"US",
    "sg:address":"2132 2nd Avenue",
    "sg:city":"Seattle",
    "sg:classifiers":[
        {
            "category":"Real Estate",
            "subcategory":"Real Estate Services",
            "type":"Services"
        },
        {
            "category":"Real Estate",
            "subcategory":"Real Estate Operator",
            "type":"Services"
        }
    ],
    "sg:phone":"+1 206 956 3592",
    "sg:postcode":"98121",
    "sg:province":"WA",
    "sg:tags":[
        "apartment",
        "vacancy",
        "listing",
        "rental",
        "finder"
    ],
    "wof:name":"Castle",
    "wof:placetype":"venue"
},
  "geometry": {"coordinates":[-122.343492,47.612791],"type":"Point"}
}