{
  "type": "Feature",
  "properties": {
    "addr:full":"832 Georgiana St Port Angeles WA 98362",
    "addr:housenumber":"832",
    "addr:postcode":"98362",
    "addr:street":"Georgiana St",
    "iso:country":"US",
    "sg:address":"832 Georgiana St",
    "sg:city":"Port Angeles",
    "sg:classifiers":[
        {
            "category":"Health Services",
            "subcategory":"Doctor",
            "type":"Services"
        }
    ],
    "sg:phone":"+1 360 457 7003",
    "sg:postcode":"98362",
    "sg:province":"WA",
    "sg:tags":[
        "physician",
        "surgeon",
        "medical"
    ],
    "wof:name":"Center For Bone Joint Surgery",
    "wof:placetype":"venue"
},
  "geometry": {"coordinates":[-123.41865900000001,48.115206],"type":"Point"}
}