{
  "type": "Feature",
  "properties": {
    "addr:full":"3510 NW Anderson Hill Rd Silverdale WA 98383",
    "addr:housenumber":"3510",
    "addr:postcode":"98383",
    "addr:street":"Nw Anderson Hill Rd",
    "iso:country":"US",
    "sg:address":"3510 NW Anderson Hill Rd",
    "sg:city":"Silverdale",
    "sg:classifiers":[
        {
            "category":"Building & Trades",
            "subcategory":"Construction",
            "type":"Services"
        }
    ],
    "sg:phone":"+1 360 698 8649",
    "sg:postcode":"98383",
    "sg:province":"WA",
    "sg:tags":[
        "hanging",
        "painter",
        "contractor"
    ],
    "wof:name":"Northsound Maintenance Service",
    "wof:placetype":"venue"
},
  "geometry": {"coordinates":[-122.69919400000001,47.650271],"type":"Point"}
}