{
  "type": "Feature",
  "properties": {
    "addr:full":"2801 S Jackson St Seattle WA 98144",
    "addr:housenumber":"2801",
    "addr:postcode":"98144",
    "addr:street":"S Jackson St",
    "iso:country":"US",
    "sg:address":"2801 S Jackson St",
    "sg:city":"Seattle",
    "sg:classifiers":[
        {
            "category":"Organizations",
            "subcategory":"Religious Organization",
            "type":"Services"
        }
    ],
    "sg:phone":"+1 206 329 9794",
    "sg:postcode":"98144",
    "sg:province":"WA",
    "wof:name":"Taberncle Mssnary Bptst Church",
    "wof:placetype":"venue"
},
  "geometry": {"coordinates":[-122.29501999999999,47.599201],"type":"Point"}
}