{
  "type": "Feature",
  "properties": {
    "addr:full":"7703 NE 72nd Ave Vancouver WA 98661",
    "addr:housenumber":"7703",
    "addr:postcode":"98661",
    "addr:street":"Ne 72Nd Ave",
    "iso:country":"US",
    "sg:address":"7703 NE 72nd Ave",
    "sg:city":"Vancouver",
    "sg:classifiers":[
        {
            "category":"Restaurant",
            "type":"Food & Drink"
        }
    ],
    "sg:phone":"+1 360 253 6341",
    "sg:postcode":"98661",
    "sg:province":"WA",
    "wof:name":"Cameo Cafe Of Washington",
    "wof:placetype":"venue"
},
  "geometry": {"coordinates":[-122.59930300000001,45.677364],"type":"Point"}
}