{
  "type": "Feature",
  "properties": {
    "addr:full":"23805 Hwy 99 Edmonds WA 98026",
    "addr:housenumber":"23805",
    "addr:postcode":"98026",
    "addr:street":"Hwy 99",
    "iso:country":"US",
    "sg:address":"23805 Hwy 99",
    "sg:city":"Edmonds",
    "sg:classifiers":[
        {
            "category":"Professional",
            "subcategory":"Accounting & Tax Preparation",
            "type":"Services"
        }
    ],
    "sg:phone":"+1 425 771 8239",
    "sg:postcode":"98026",
    "sg:province":"WA",
    "sg:tags":[
        "return",
        "filing"
    ],
    "wof:name":"Giarde Tax Svc",
    "wof:placetype":"venue"
},
  "geometry": {"coordinates":[-122.34369599999999,47.782975],"type":"Point"}
}