{
  "type": "Feature",
  "properties": {
    "addr:full":"20828 SE 132nd St Issaquah WA 98027",
    "addr:postcode":"20828;98027",
    "addr:street":"Se 132Nd St",
    "iso:country":"US",
    "sg:address":"20828 SE 132nd St",
    "sg:city":"Issaquah",
    "sg:classifiers":[
        {
            "category":"Travel",
            "subcategory":"Travel Agent",
            "type":"Entertainment"
        }
    ],
    "sg:phone":"+1 425 572 5800",
    "sg:postcode":"98027",
    "sg:province":"WA",
    "sg:tags":[
        "agency",
        "services-commercial"
    ],
    "wof:name":"Smore Travel",
    "wof:placetype":"venue"
},
  "geometry": {"coordinates":[-122.06462999999999,47.484311],"type":"Point"}
}