{
  "type": "Feature",
  "properties": {
    "addr:full":"14832 SE Fairwood Blvd Renton WA 98058",
    "addr:housenumber":"14832",
    "addr:postcode":"98058",
    "addr:street":"Se Fairwood Blvd",
    "iso:country":"US",
    "sg:address":"14832 SE Fairwood Blvd",
    "sg:city":"Renton",
    "sg:classifiers":[
        {
            "category":"Personal",
            "subcategory":"Beauty Salon",
            "type":"Services"
        }
    ],
    "sg:phone":"+1 425 255 0549",
    "sg:postcode":"98058",
    "sg:province":"WA",
    "sg:tags":[
        "shop"
    ],
    "wof:name":"Sally Ann Comp",
    "wof:placetype":"venue"
},
  "geometry": {"coordinates":[-122.140809,47.451915],"type":"Point"}
}