{
  "type": "Feature",
  "properties": {
    "addr:full":"400 Front St Lynden WA 98264",
    "addr:housenumber":"400",
    "addr:postcode":"98264",
    "addr:street":"Front St",
    "iso:country":"US",
    "sg:address":"400 Front St",
    "sg:city":"Lynden",
    "sg:classifiers":[
        {
            "category":"Shopping",
            "subcategory":"Used Merchandise",
            "type":"Retail Goods"
        },
        {
            "category":"Professional",
            "subcategory":"Business Services",
            "type":"Services"
        }
    ],
    "sg:phone":"+1 360 354 7576",
    "sg:postcode":"98264",
    "sg:province":"WA",
    "sg:tags":[
        "antique"
    ],
    "wof:name":"F M I More Than Antiques",
    "wof:placetype":"venue"
},
  "geometry": {"coordinates":[-122.451814,48.943151],"type":"Point"}
}