{
  "type": "Feature",
  "properties": {
    "addr:full":"7303 Ridgemont Dr SE Olympia WA 98513",
    "addr:housenumber":"7303",
    "addr:postcode":"98513",
    "addr:street":"Ridgemont Dr Se",
    "iso:country":"US",
    "sg:address":"7303 Ridgemont Dr SE",
    "sg:city":"Olympia",
    "sg:classifiers":[
        {
            "category":"Social Services",
            "type":"Services"
        }
    ],
    "sg:phone":"+1 360 491 7151",
    "sg:postcode":"98513",
    "sg:province":"WA",
    "wof:name":"Harriet J Wehnes",
    "wof:placetype":"venue"
},
  "geometry": {"coordinates":[-122.781813,47.003737],"type":"Point"}
}