{
  "type": "Feature",
  "properties": {
    "addr:full":"1620 E Holyoke Ave Spokane WA 99217",
    "addr:housenumber":"1620",
    "addr:postcode":"99217",
    "addr:street":"E Holyoke Ave",
    "iso:country":"US",
    "sg:address":"1620 E Holyoke Ave",
    "sg:city":"Spokane",
    "sg:classifiers":[
        {
            "category":"Retail",
            "subcategory":"Auto Rental",
            "type":"Services"
        }
    ],
    "sg:phone":"+1 509 483 2912",
    "sg:postcode":"99217",
    "sg:province":"WA",
    "sg:tags":[
        "automobile",
        "leasing"
    ],
    "wof:name":"Oasis Leasing",
    "wof:placetype":"venue"
},
  "geometry": {"coordinates":[-117.385155,47.717609],"type":"Point"}
}