{
  "type": "Feature",
  "properties": {
    "addr:full":"420 Schut Rd Moxee WA 98936",
    "addr:housenumber":"420",
    "addr:postcode":"98936",
    "addr:street":"Schut Rd",
    "iso:country":"US",
    "sg:address":"420 Schut Rd",
    "sg:city":"Moxee",
    "sg:classifiers":[
        {
            "category":"Food & Beverages",
            "subcategory":"Fruits & Vegetables",
            "type":"Retail Goods"
        }
    ],
    "sg:phone":"+1 509 453 7905",
    "sg:postcode":"98936",
    "sg:province":"WA",
    "wof:name":"Olson Fruit & Berries",
    "wof:placetype":"venue"
},
  "geometry": {"coordinates":[-120.324164,46.561729],"type":"Point"}
}