{
  "type": "Feature",
  "properties": {
    "iso:country":"US",
    "sg:address":"801 Alaskan Way",
    "sg:city":"Seattle",
    "sg:classifiers":[
        {
            "category":"Restaurant",
            "type":"Food & Drink"
        }
    ],
    "sg:phone":"+1 206 264 2500",
    "sg:postcode":"98104",
    "sg:province":"WA",
    "sg:tags":[
        "cafe"
    ],
    "wof:name":"Caffe Appassionato",
    "wof:placetype":"venue"
},
  "geometry": {"coordinates":[-122.337717,47.602981],"type":"Point"}
}