{
  "type": "Feature",
  "properties": {
    "addr:full":"606 N State St Tacoma WA 98403",
    "addr:housenumber":"606",
    "addr:postcode":"98403",
    "addr:street":"N State St",
    "iso:country":"US",
    "sg:address":"606 N State St",
    "sg:city":"Tacoma",
    "sg:classifiers":[
        {
            "category":"Personal",
            "subcategory":"Beauty Salon",
            "type":"Services"
        }
    ],
    "sg:phone":"+1 253 383 3855",
    "sg:postcode":"98403",
    "sg:province":"WA",
    "wof:name":"Salon Baroque",
    "wof:placetype":"venue"
},
  "geometry": {"coordinates":[-122.466077,47.257166],"type":"Point"}
}