{
  "type": "Feature",
  "properties": {
    "addr:full":"6309 1st St E Tacoma WA 98422",
    "addr:housenumber":"6309",
    "addr:postcode":"98422",
    "addr:street":"1St St",
    "iso:country":"US",
    "sg:address":"6309 1st St E",
    "sg:city":"Tacoma",
    "sg:classifiers":[
        {
            "category":"Manufacturing",
            "subcategory":"Metals",
            "type":"Manufacturing & Wholesale Goods"
        }
    ],
    "sg:phone":"+1 253 820 9147",
    "sg:postcode":"98422",
    "sg:province":"WA",
    "sg:tags":[
        "engraver"
    ],
    "wof:name":"Impact Laser Svc",
    "wof:placetype":"venue"
},
  "geometry": {"coordinates":[-122.343209,47.258612],"type":"Point"}
}