{
  "type": "Feature",
  "properties": {
    "addr:full":"427 E Main St Dayton WA 99328",
    "addr:housenumber":"427",
    "addr:postcode":"99328",
    "addr:street":"E Main St",
    "iso:country":"US",
    "sg:address":"427 E Main St",
    "sg:city":"Dayton",
    "sg:classifiers":[
        {
            "category":"Banks & Credit Unions",
            "subcategory":"Bank",
            "type":"Services"
        }
    ],
    "sg:phone":"+1 509 382 2800",
    "sg:postcode":"99328",
    "sg:province":"WA",
    "wof:name":"American West Bank",
    "wof:placetype":"venue"
},
  "geometry": {"coordinates":[-117.976629,46.321585],"type":"Point"}
}