{
  "type": "Feature",
  "properties": {
    "addr:full":"10819 Airport Rd Everett WA 98204",
    "addr:housenumber":"10819",
    "addr:postcode":"98204",
    "addr:street":"Airport Rd",
    "iso:country":"US",
    "sg:address":"10819 Airport Rd",
    "sg:city":"Everett",
    "sg:classifiers":[
        {
            "category":"Utilities",
            "type":"Services"
        },
        {
            "category":"Utilities",
            "subcategory":"Cable",
            "type":"Services"
        }
    ],
    "sg:phone":"+1 425 348 8028",
    "sg:postcode":"98204",
    "sg:province":"WA",
    "sg:tags":[
        "pipe",
        "underground",
        "wire",
        "locating",
        "contractor"
    ],
    "wof:name":"Contractors Pioneer Cable",
    "wof:placetype":"venue"
},
  "geometry": {"coordinates":[-122.265659,47.899464],"type":"Point"}
}