{
  "type": "Feature",
  "properties": {
    "addr:full":"20924 Pugh Rd NE Poulsbo WA 98370",
    "addr:postcode":"20924;98370",
    "addr:street":"Pugh Rd Ne",
    "iso:country":"US",
    "sg:address":"20924 Pugh Rd NE",
    "sg:city":"Poulsbo",
    "sg:classifiers":[
        {
            "category":"Professional",
            "subcategory":"Management & Consulting",
            "type":"Services"
        }
    ],
    "sg:phone":"+1 360 697 3262",
    "sg:postcode":"98370",
    "sg:province":"WA",
    "sg:tags":[
        "business"
    ],
    "wof:name":"Stark Enterprizes",
    "wof:placetype":"venue"
},
  "geometry": {"coordinates":[-122.61953699999999,47.753662],"type":"Point"}
}