{
  "type": "Feature",
  "properties": {
    "iso:country":"US",
    "sg:address":"1201 4th St",
    "sg:city":"Anacortes",
    "sg:classifiers":[
        {
            "category":"Banks & Credit Unions",
            "subcategory":"Financial Services",
            "type":"Services"
        }
    ],
    "sg:phone":"+1 360 293 5338",
    "sg:postcode":"98221",
    "sg:province":"WA",
    "sg:tags":[
        "investor"
    ],
    "wof:name":"Smrq Investments Inc",
    "wof:placetype":"venue"
},
  "geometry": {"coordinates":[-122.617193,48.519127],"type":"Point"}
}