{
  "type": "Feature",
  "properties": {
    "addr:full":"538 Hyacinth Rd Manson WA 98831",
    "addr:housenumber":"538",
    "addr:postcode":"98831",
    "addr:street":"Hyacinth Rd",
    "iso:country":"US",
    "sg:address":"538 Hyacinth Rd",
    "sg:city":"Manson",
    "sg:classifiers":[
        {
            "category":"Farming",
            "subcategory":"Farm & Veterinary Services",
            "type":"Manufacturing & Wholesale Goods"
        }
    ],
    "sg:phone":"+1 509 687 3306",
    "sg:postcode":"98831",
    "sg:province":"WA",
    "sg:tags":[
        "preparation",
        "crop",
        "for",
        "market"
    ],
    "wof:name":"Chapman Road Orchard",
    "wof:placetype":"venue"
},
  "geometry": {"coordinates":[-120.140101,47.877518],"type":"Point"}
}