{
  "type": "Feature",
  "properties": {
    "addr:full":"14337 20th Ave NE Seattle WA 98125",
    "addr:housenumber":"14337",
    "addr:postcode":"98125",
    "addr:street":"20Th Ave Ne",
    "iso:country":"US",
    "sg:address":"14337 20th Ave NE",
    "sg:city":"Seattle",
    "sg:classifiers":[
        {
            "category":"Professional",
            "subcategory":"Business Services",
            "type":"Services"
        }
    ],
    "sg:phone":"+1 206 523 6459",
    "sg:postcode":"98125",
    "sg:province":"WA",
    "wof:name":"Cyberspeed Technologies LLC",
    "wof:placetype":"venue"
},
  "geometry": {"coordinates":[-122.307394,47.733558],"type":"Point"}
}