{
  "type": "Feature",
  "properties": {
    "addr:full":"12216 138th Ave E Puyallup WA 98374",
    "addr:housenumber":"12216",
    "addr:postcode":"98374",
    "addr:street":"138Th Ave E",
    "iso:country":"US",
    "sg:address":"12216 138th Ave E",
    "sg:city":"Puyallup",
    "sg:classifiers":[
        {
            "category":"Building & Trades",
            "subcategory":"Construction",
            "type":"Services"
        }
    ],
    "sg:phone":"+1 253 770 0100",
    "sg:postcode":"98374",
    "sg:province":"WA",
    "sg:tags":[
        "residential",
        "work",
        "concrete"
    ],
    "wof:name":"R C Concrete",
    "wof:placetype":"venue"
},
  "geometry": {"coordinates":[-122.246803,47.14373],"type":"Point"}
}