{
  "type": "Feature",
  "properties": {
    "addr:full":"3527 Holiday Dr SE Olympia WA 98501",
    "addr:housenumber":"3527",
    "addr:postcode":"98501",
    "addr:street":"Holiday Dr Se",
    "iso:country":"US",
    "sg:address":"3527 Holiday Dr SE",
    "sg:city":"Olympia",
    "sg:classifiers":[
        {
            "category":"Wholesale",
            "subcategory":"Sporting Goods",
            "type":"Manufacturing & Wholesale Goods"
        }
    ],
    "sg:phone":"+1 360 705 8872",
    "sg:postcode":"98501",
    "sg:province":"WA",
    "wof:name":"Visualizer Golf LLC",
    "wof:placetype":"venue"
},
  "geometry": {"coordinates":[-122.87600999999999,47.016483],"type":"Point"}
}