{
  "type": "Feature",
  "properties": {
    "addr:full":"9465 Provost Rd NW Silverdale WA 98383",
    "addr:housenumber":"9465",
    "addr:postcode":"98383",
    "addr:street":"Provost Rd Nw",
    "iso:country":"US",
    "sg:address":"9465 Provost Rd NW",
    "sg:city":"Silverdale",
    "sg:classifiers":[
        {
            "category":"Professional",
            "subcategory":"Business Services",
            "type":"Services"
        }
    ],
    "sg:phone":"+1 360 692 5505",
    "sg:postcode":"98383",
    "sg:province":"WA",
    "sg:tags":[
        "appraiser"
    ],
    "wof:name":"Spier Appraisal Svc",
    "wof:placetype":"venue"
},
  "geometry": {"coordinates":[-122.707309,47.650559],"type":"Point"}
}