{
  "type": "Feature",
  "properties": {
    "addr:full":"1986 S Market Blvd Chehalis WA 98532",
    "addr:housenumber":"1986",
    "addr:postcode":"98532",
    "addr:street":"S Market Blvd",
    "iso:country":"US",
    "sg:address":"1986 S Market Blvd",
    "sg:city":"Chehalis",
    "sg:classifiers":[
        {
            "category":"Professional",
            "subcategory":"Business Services",
            "type":"Services"
        }
    ],
    "sg:phone":"+1 360 748 4037",
    "sg:postcode":"98532",
    "sg:province":"WA",
    "sg:tags":[
        "grocery"
    ],
    "wof:name":"Time Oil Co",
    "wof:placetype":"venue"
},
  "geometry": {"coordinates":[-122.942604,46.648804],"type":"Point"}
}