{
  "type": "Feature",
  "properties": {
    "addr:full":"20013 Aurora Ave N Seattle WA 98133",
    "addr:housenumber":"20013",
    "addr:postcode":"98133",
    "addr:street":"Aurora Ave N",
    "iso:country":"US",
    "sg:address":"20013 Aurora Ave N",
    "sg:city":"Seattle",
    "sg:classifiers":[
        {
            "category":"Retail",
            "subcategory":"Repair Shop",
            "type":"Services"
        }
    ],
    "sg:phone":"+1 206 546 0891",
    "sg:postcode":"98133",
    "sg:province":"WA",
    "sg:tags":[
        "locksmith"
    ],
    "wof:name":"Aa Abco Locksmiths",
    "wof:placetype":"venue"
},
  "geometry": {"coordinates":[-122.34629099999999,47.777699],"type":"Point"}
}