{
  "type": "Feature",
  "properties": {
    "addr:full":"25725 101st Ave SE Kent WA 98030",
    "addr:housenumber":"25725",
    "addr:postcode":"98030",
    "addr:street":"101St Ave Se",
    "iso:country":"US",
    "sg:address":"25725 101st Ave SE",
    "sg:city":"Kent",
    "sg:classifiers":[
        {
            "category":"Personal",
            "subcategory":"Beauty Salon",
            "type":"Services"
        }
    ],
    "sg:phone":"+1 253 852 1255",
    "sg:postcode":"98030",
    "sg:province":"WA",
    "sg:tags":[
        "wig",
        "hair",
        "piece"
    ],
    "wof:name":"Otrenez",
    "wof:placetype":"venue"
},
  "geometry": {"coordinates":[-122.205951,47.370906],"type":"Point"}
}