{
  "type": "Feature",
  "properties": {
    "addr:full":"5215 Wollochet Dr NW Gig Harbor WA 98335",
    "addr:housenumber":"5215",
    "addr:postcode":"98335",
    "addr:street":"Wollochet Dr Nw",
    "iso:country":"US",
    "sg:address":"5215 Wollochet Dr NW",
    "sg:city":"Gig Harbor",
    "sg:classifiers":[
        {
            "category":"Social Services",
            "subcategory":"Child Care",
            "type":"Services"
        }
    ],
    "sg:phone":"+1 253 851 0401",
    "sg:postcode":"98335",
    "sg:province":"WA",
    "sg:tags":[
        "day"
    ],
    "wof:name":"Safe Harbor Child Development",
    "wof:placetype":"venue"
},
  "geometry": {"coordinates":[-122.611608,47.30179],"type":"Point"}
}