{
  "type": "Feature",
  "properties": {
    "addr:full":"6006 S Palouse Hwy Spokane WA 99223",
    "addr:housenumber":"6006",
    "addr:postcode":"99223",
    "addr:street":"S Palouse Hwy",
    "iso:country":"US",
    "sg:address":"6006 S Palouse Hwy",
    "sg:city":"Spokane",
    "sg:classifiers":[
        {
            "category":"Organizations",
            "subcategory":"Religious Organization",
            "type":"Services"
        }
    ],
    "sg:phone":"+1 509 329 0314",
    "sg:postcode":"99223",
    "sg:province":"WA",
    "sg:tags":[
        "church"
    ],
    "sg:website":"www.christkirk.org",
    "wof:name":"Christ Church Spokane",
    "wof:placetype":"venue"
},
  "geometry": {"coordinates":[-117.352127,47.599864],"type":"Point"}
}