{
  "type": "Feature",
  "properties": {
    "addr:full":"5462 E Mercer Way Mercer Island WA 98040",
    "addr:housenumber":"5462",
    "addr:postcode":"98040",
    "addr:street":"E Mercer Way",
    "iso:country":"US",
    "sg:address":"5462 E Mercer Way",
    "sg:city":"Mercer Island",
    "sg:classifiers":[
        {
            "category":"Professional",
            "subcategory":"Management & Consulting",
            "type":"Services"
        }
    ],
    "sg:phone":"+1 206 236 1537",
    "sg:postcode":"98040",
    "sg:province":"WA",
    "wof:name":"Premiere Financial Services",
    "wof:placetype":"venue"
},
  "geometry": {"coordinates":[-122.212429,47.552772],"type":"Point"}
}