{
  "type": "Feature",
  "properties": {
    "addr:full":"2905 C St SW Auburn WA 98001",
    "addr:housenumber":"2905",
    "addr:postcode":"98001",
    "addr:street":"C St Sw",
    "iso:country":"US",
    "sg:address":"2905 C St SW",
    "sg:city":"Auburn",
    "sg:classifiers":[
        {
            "category":"Building & Trades",
            "subcategory":"Cleaning & Sanitation",
            "type":"Services"
        }
    ],
    "sg:phone":"+1 253 931 0223",
    "sg:postcode":"98001",
    "sg:province":"WA",
    "sg:tags":[
        "maintenance"
    ],
    "wof:name":"One Source Energy",
    "wof:placetype":"venue"
},
  "geometry": {"coordinates":[-122.230835,47.273581],"type":"Point"}
}