{
  "type": "Feature",
  "properties": {
    "addr:full":"92 Pike St Seattle WA 98101",
    "addr:housenumber":"92",
    "addr:postcode":"98101",
    "addr:street":"Pike St",
    "iso:country":"US",
    "sg:address":"92 Pike St",
    "sg:city":"Seattle",
    "sg:classifiers":[
        {
            "category":"Food & Beverages",
            "subcategory":"Groceries & Convenience Stores",
            "type":"Retail Goods"
        }
    ],
    "sg:phone":"+1 206 622 0195",
    "sg:postcode":"98101",
    "sg:province":"WA",
    "wof:name":"Pike Place Market",
    "wof:placetype":"venue"
},
  "geometry": {"coordinates":[-122.340174,47.608986],"type":"Point"}
}