{
  "type": "Feature",
  "properties": {
    "addr:full":"6930 6th Ave SW Tumwater WA 98501",
    "addr:housenumber":"6930",
    "addr:postcode":"98501",
    "addr:street":"6Th Ave Sw",
    "iso:country":"US",
    "sg:address":"6930 6th Ave SW",
    "sg:city":"Tumwater",
    "sg:classifiers":[
        {
            "category":"Retail",
            "subcategory":"Laundry & Dry Cleaning",
            "type":"Services"
        }
    ],
    "sg:phone":"+1 360 786 0535",
    "sg:postcode":"98501",
    "sg:province":"WA",
    "sg:tags":[
        "cleaners",
        "rug",
        "carpet"
    ],
    "wof:name":"Precision Carpet Cleaning",
    "wof:placetype":"venue"
},
  "geometry": {"coordinates":[-122.911568,46.988878],"type":"Point"}
}