{
  "type": "Feature",
  "properties": {
    "addr:full":"2920 Colby Ave Everett WA 98201",
    "addr:housenumber":"2920",
    "addr:postcode":"98201",
    "addr:street":"Colby Ave",
    "iso:country":"US",
    "sg:address":"2920 Colby Ave",
    "sg:city":"Everett",
    "sg:classifiers":[
        {
            "category":"Restaurant",
            "type":"Food & Drink"
        }
    ],
    "sg:phone":"+1 425 258 2168",
    "sg:postcode":"98201",
    "sg:province":"WA",
    "sg:tags":[
        "american"
    ],
    "wof:name":"Damon H Canfield",
    "wof:placetype":"venue"
},
  "geometry": {"coordinates":[-122.208618,47.978912],"type":"Point"}
}