{
  "type": "Feature",
  "properties": {
    "addr:full":"25 Central Way Ste 230 Kirkland WA 98033",
    "addr:housenumber":"25",
    "addr:postcode":"98033",
    "addr:street":"Central Way Ste 230",
    "iso:country":"US",
    "sg:address":"25 Central Way Ste 230",
    "sg:city":"Kirkland",
    "sg:classifiers":[
        {
            "category":"Personal",
            "subcategory":"Nail Salon",
            "type":"Services"
        }
    ],
    "sg:phone":"+1 425 889 1117",
    "sg:postcode":"98033",
    "sg:province":"WA",
    "wof:name":"Jana Nail Salon",
    "wof:placetype":"venue"
},
  "geometry": {"coordinates":[-122.209,47.6763],"type":"Point"}
}