{
  "type": "Feature",
  "properties": {
    "addr:full":"818 W Riverside Ave Spokane WA 99201",
    "addr:housenumber":"818",
    "addr:postcode":"99201",
    "addr:street":"W Riverside Ave",
    "iso:country":"US",
    "sg:address":"818 W Riverside Ave",
    "sg:city":"Spokane",
    "sg:classifiers":[
        {
            "category":"Banks & Credit Unions",
            "subcategory":"Investment Brokerage",
            "type":"Services"
        }
    ],
    "sg:phone":"+1 509 328 0111",
    "sg:postcode":"99201",
    "sg:province":"WA",
    "sg:tags":[
        "security"
    ],
    "wof:name":"AIG Sunamerica",
    "wof:placetype":"venue"
},
  "geometry": {"coordinates":[-117.42484,47.657995],"type":"Point"}
}