{
  "type": "Feature",
  "properties": {
    "addr:full":"27520 94th Ave SW Vashon WA 98070",
    "addr:housenumber":"27520",
    "addr:postcode":"98070",
    "addr:street":"94Th Ave Sw",
    "iso:country":"US",
    "sg:address":"27520 94th Ave SW",
    "sg:city":"Vashon",
    "sg:classifiers":[
        {
            "category":"Professional",
            "subcategory":"Management & Consulting",
            "type":"Services"
        }
    ],
    "sg:phone":"+1 206 463 3043",
    "sg:postcode":"98070",
    "sg:province":"WA",
    "sg:tags":[
        "business"
    ],
    "wof:name":"Nancy Wing Soho",
    "wof:placetype":"venue"
},
  "geometry": {"coordinates":[-122.454165,47.357139],"type":"Point"}
}