{
  "type": "Feature",
  "properties": {
    "addr:full":"580 C St Blaine WA 98230",
    "addr:housenumber":"580",
    "addr:postcode":"98230",
    "addr:street":"C St",
    "iso:country":"US",
    "sg:address":"580 C St",
    "sg:city":"Blaine",
    "sg:classifiers":[
        {
            "category":"Place Of Worship",
            "subcategory":"Church",
            "type":"Public Place"
        },
        {
            "category":"Place Of Worship",
            "type":"Public Place"
        }
    ],
    "sg:phone":"+1 360 332 8610",
    "sg:postcode":"98230",
    "sg:province":"WA",
    "sg:tags":[
        "churches-interdenominational",
        "churches-various",
        "denomination"
    ],
    "wof:name":"Northwood Alliance Church",
    "wof:placetype":"venue"
},
  "geometry": {"coordinates":[-122.744034,48.999121],"type":"Point"}
}