{
  "type": "Feature",
  "properties": {
    "addr:full":"2918 N Nevada St Spokane WA 99207",
    "addr:housenumber":"2918",
    "addr:postcode":"99207",
    "addr:street":"N Nevada St",
    "iso:country":"US",
    "sg:address":"2918 N Nevada St",
    "sg:city":"Spokane",
    "sg:classifiers":[
        {
            "category":"Retail",
            "subcategory":"Auto Repair",
            "type":"Services"
        }
    ],
    "sg:phone":"+1 509 487 2984",
    "sg:postcode":"99207",
    "sg:province":"WA",
    "sg:tags":[
        "repairing",
        "automobile",
        "general"
    ],
    "wof:name":"Auto Masters",
    "wof:placetype":"venue"
},
  "geometry": {"coordinates":[-117.395133,47.684918],"type":"Point"}
}