{
  "type": "Feature",
  "properties": {
    "addr:full":"1207 13th St Snohomish WA 98290",
    "addr:housenumber":"1207",
    "addr:postcode":"98290",
    "addr:street":"13Th St",
    "iso:country":"US",
    "sg:address":"1207 13th St",
    "sg:city":"Snohomish",
    "sg:classifiers":[
        {
            "category":"Shopping",
            "type":"Retail Goods"
        }
    ],
    "sg:phone":"+1 360 568 1607",
    "sg:postcode":"98290",
    "sg:province":"WA",
    "sg:tags":[
        "pet",
        "food",
        "supply"
    ],
    "wof:name":"Pet Pros",
    "wof:placetype":"venue"
},
  "geometry": {"coordinates":[-122.096422,47.927041],"type":"Point"}
}