{
  "type": "Feature",
  "properties": {
    "iso:country":"US",
    "sg:address":"4028 26th Ave W",
    "sg:city":"Seattle",
    "sg:classifiers":[
        {
            "category":"Banks & Credit Unions",
            "subcategory":"Financial Services",
            "type":"Services"
        }
    ],
    "sg:phone":"+1 206 281 8983",
    "sg:postcode":"98199",
    "sg:province":"WA",
    "sg:tags":[
        "investor"
    ],
    "wof:name":"Mika Investments LLC",
    "wof:placetype":"venue"
},
  "geometry": {"coordinates":[-122.389822,47.657221],"type":"Point"}
}