{
  "type": "Feature",
  "properties": {
    "addr:full":"9925 NE 190th St Bothell WA 98011",
    "addr:housenumber":"9925",
    "addr:postcode":"98011",
    "addr:street":"Ne 190Th St",
    "iso:country":"US",
    "sg:address":"9925 NE 190th St",
    "sg:city":"Bothell",
    "sg:classifiers":[
        {
            "category":"Farming",
            "subcategory":"Poultry Farm",
            "type":"Manufacturing & Wholesale Goods"
        }
    ],
    "sg:phone":"+1 425 481 1641",
    "sg:postcode":"98011",
    "sg:province":"WA",
    "sg:tags":[
        "poultry-wholesale"
    ],
    "wof:name":"Stecher",
    "wof:placetype":"venue"
},
  "geometry": {"coordinates":[-122.20910600000001,47.765701],"type":"Point"}
}