{
  "type": "Feature",
  "properties": {
    "addr:full":"324 15th Ave E Seattle WA 98112",
    "addr:housenumber":"324",
    "addr:postcode":"98112",
    "addr:street":"15Th Ave E",
    "iso:country":"US",
    "sg:address":"324 15th Ave E",
    "sg:city":"Seattle",
    "sg:classifiers":[
        {
            "category":"Professional",
            "type":"Services"
        }
    ],
    "sg:phone":"+1 206 524 3144",
    "sg:postcode":"98112",
    "sg:province":"WA",
    "sg:tags":[
        "establishment"
    ],
    "wof:name":"Hola Spanish Language Ctr",
    "wof:placetype":"venue"
},
  "geometry": {"coordinates":[-122.312611,47.620838],"type":"Point"}
}