{
  "type": "Feature",
  "properties": {
    "addr:full":"16312 SE 12th St Vancouver WA 98683",
    "addr:postcode":"16312;98683",
    "addr:street":"Se 12Th St",
    "iso:country":"US",
    "sg:address":"16312 SE 12th St",
    "sg:city":"Vancouver",
    "sg:classifiers":[
        {
            "category":"Fast Food",
            "type":"Food & Drink"
        }
    ],
    "sg:phone":"+1 360 260 2666",
    "sg:postcode":"98683",
    "sg:province":"WA",
    "sg:tags":[
        "burger"
    ],
    "sg:website":"www.jackinthebox.com",
    "wof:name":"Jack In The Box",
    "wof:placetype":"venue"
},
  "geometry": {"coordinates":[-122.504977,45.612138],"type":"Point"}
}