{
  "type": "Feature",
  "properties": {
    "addr:full":"13500 NE 124th St Kirkland WA 98034",
    "addr:housenumber":"13500",
    "addr:postcode":"98034",
    "addr:street":"Ne 124Th St",
    "iso:country":"US",
    "sg:address":"13500 NE 124th St",
    "sg:city":"Kirkland",
    "sg:classifiers":[
        {
            "category":"Wholesale",
            "subcategory":"Hardware",
            "type":"Manufacturing & Wholesale Goods"
        }
    ],
    "sg:phone":"+1 425 821 8494",
    "sg:postcode":"98034",
    "sg:province":"WA",
    "sg:tags":[
        "plumbing",
        "merchandise"
    ],
    "wof:name":"Rosen Plumbing Supply",
    "wof:placetype":"venue"
},
  "geometry": {"coordinates":[-122.15808,47.71181],"type":"Point"}
}