{
  "type": "Feature",
  "properties": {
    "addr:full":"21926 49th Ave SE Bothell WA 98021",
    "addr:housenumber":"21926",
    "addr:postcode":"98021",
    "addr:street":"49Th Ave Se",
    "iso:country":"US",
    "sg:address":"21926 49th Ave SE",
    "sg:city":"Bothell",
    "sg:classifiers":[
        {
            "category":"Shopping",
            "subcategory":"Bicycles & Sporting Goods",
            "type":"Retail Goods"
        }
    ],
    "sg:phone":"+1 425 486 6741",
    "sg:postcode":"98021",
    "sg:province":"WA",
    "sg:tags":[
        "equipment",
        "basketball",
        "mfg"
    ],
    "wof:name":"Basketball Systems Inc",
    "wof:placetype":"venue"
},
  "geometry": {"coordinates":[-122.167618,47.798414],"type":"Point"}
}