{
  "type": "Feature",
  "properties": {
    "addr:full":"2517 Elmway Okanogan WA 98840",
    "addr:housenumber":"2517",
    "addr:postcode":"98840",
    "addr:street":"Elmway Okanogan",
    "iso:country":"US",
    "sg:address":"2517 Elmway",
    "sg:city":"Okanogan",
    "sg:classifiers":[
        {
            "category":"Retail",
            "subcategory":"Funeral Services",
            "type":"Services"
        }
    ],
    "sg:phone":"+1 509 422 2645",
    "sg:postcode":"98840",
    "sg:province":"WA",
    "sg:tags":[
        "cemetery"
    ],
    "wof:name":"Omak Memorial Cemetery",
    "wof:placetype":"venue"
},
  "geometry": {"coordinates":[-119.55294000000001,48.388179],"type":"Point"}
}