{
  "type": "Feature",
  "properties": {
    "addr:full":"2001 N 35th Pl Mount Vernon WA 98273",
    "addr:housenumber":"2001",
    "addr:postcode":"98273",
    "addr:street":"N 35Th Pl",
    "iso:country":"US",
    "sg:address":"2001 N 35th Pl",
    "sg:city":"Mount Vernon",
    "sg:classifiers":[
        {
            "category":"Building & Trades",
            "subcategory":"Construction",
            "type":"Services"
        }
    ],
    "sg:phone":"+1 360 424 5879",
    "sg:postcode":"98273",
    "sg:province":"WA",
    "sg:tags":[
        "contractor"
    ],
    "wof:name":"Classical Glass",
    "wof:placetype":"venue"
},
  "geometry": {"coordinates":[-122.296628,48.438689],"type":"Point"}
}