{
  "type": "Feature",
  "properties": {
    "addr:full":"8580 W Cloquallum Rd Shelton WA 98584",
    "addr:housenumber":"8580",
    "addr:postcode":"98584",
    "addr:street":"W Cloquallum Rd",
    "iso:country":"US",
    "sg:address":"8580 W Cloquallum Rd",
    "sg:city":"Shelton",
    "sg:classifiers":[
        {
            "category":"Manufacturing",
            "subcategory":"Chemicals & Compounds",
            "type":"Manufacturing & Wholesale Goods"
        }
    ],
    "sg:phone":"+1 360 426 3955",
    "sg:postcode":"98584",
    "sg:province":"WA",
    "sg:tags":[
        "fertilizer",
        "nitrogenous",
        "mfg"
    ],
    "wof:name":"Frog Belly Organics",
    "wof:placetype":"venue"
},
  "geometry": {"coordinates":[-123.214282,47.161421],"type":"Point"}
}