{
  "type": "Feature",
  "properties": {
    "addr:full":"1210 N Wenatchee Ave Wenatchee WA 98801",
    "addr:housenumber":"1210",
    "addr:postcode":"98801",
    "addr:street":"N Wenatchee Ave",
    "iso:country":"US",
    "sg:address":"1210 N Wenatchee Ave",
    "sg:city":"Wenatchee",
    "sg:classifiers":[
        {
            "category":"Food & Beverages",
            "subcategory":"Bakery",
            "type":"Retail Goods"
        }
    ],
    "sg:phone":"+1 509 667 9969",
    "sg:postcode":"98801",
    "sg:province":"WA",
    "sg:tags":[
        "baker"
    ],
    "wof:name":"White's Bakery",
    "wof:placetype":"venue"
},
  "geometry": {"coordinates":[-120.323292,47.439117],"type":"Point"}
}