{
  "type": "Feature",
  "properties": {
    "iso:country":"US",
    "sg:address":"1203 E D St",
    "sg:city":"Tacoma",
    "sg:classifiers":[
        {
            "category":"Freight",
            "type":"Transportation"
        }
    ],
    "sg:phone":"+1 253 272 7205",
    "sg:postcode":"98421",
    "sg:province":"WA",
    "sg:tags":[
        "warehouse",
        "self",
        "storage"
    ],
    "wof:name":"Wattles Co",
    "wof:placetype":"venue"
},
  "geometry": {"coordinates":[-122.43168900000001,47.256863],"type":"Point"}
}