{
  "type": "Feature",
  "properties": {
    "addr:full":"3516 Paine Ave Everett WA 98201",
    "addr:housenumber":"3516",
    "addr:postcode":"98201",
    "addr:street":"Paine Ave",
    "iso:country":"US",
    "sg:address":"3516 Paine Ave",
    "sg:city":"Everett",
    "sg:classifiers":[
        {
            "category":"Retail",
            "subcategory":"Auto Repair",
            "type":"Services"
        }
    ],
    "sg:phone":"+1 425 252 4004",
    "sg:postcode":"98201",
    "sg:province":"WA",
    "sg:tags":[
        "towing"
    ],
    "wof:name":"Dicks Towing Inc",
    "wof:placetype":"venue"
},
  "geometry": {"coordinates":[-122.198556,47.970139],"type":"Point"}
}