{
  "type": "Feature",
  "properties": {
    "addr:full":"2611 241st Pl SW Lynnwood WA 98036",
    "addr:housenumber":"2611",
    "addr:postcode":"98036",
    "addr:street":"241St Pl Sw",
    "iso:country":"US",
    "sg:address":"2611 241st Pl SW",
    "sg:city":"Lynnwood",
    "sg:classifiers":[
        {
            "category":"Retail",
            "subcategory":"Repair Shop",
            "type":"Services"
        }
    ],
    "sg:phone":"+1 425 487 1123",
    "sg:postcode":"98036",
    "sg:province":"WA",
    "sg:tags":[
        "engine",
        "marine",
        "diesel"
    ],
    "wof:name":"Tobys Marine Diesl Repr & Svc",
    "wof:placetype":"venue"
},
  "geometry": {"coordinates":[-122.270636,47.779399],"type":"Point"}
}