{
  "type": "Feature",
  "properties": {
    "addr:full":"803 E Main Puyallup WA 98372",
    "addr:housenumber":"803",
    "addr:postcode":"98372",
    "addr:street":"E Main",
    "iso:country":"US",
    "sg:address":"803 E Main",
    "sg:city":"Puyallup",
    "sg:classifiers":[
        {
            "category":"Professional",
            "subcategory":"Detective & Security Services",
            "type":"Services"
        }
    ],
    "sg:phone":"+1 253 881 1337",
    "sg:postcode":"98372",
    "sg:province":"WA",
    "sg:tags":[
        "information",
        "bureau"
    ],
    "wof:name":"Puyallup Respiratory Services",
    "wof:placetype":"venue"
},
  "geometry": {"coordinates":[-122.284351,47.191841],"type":"Point"}
}