{
  "type": "Feature",
  "properties": {
    "addr:full":"14603 104th Ave NE Bothell WA 98011",
    "addr:housenumber":"14603",
    "addr:postcode":"98011",
    "addr:street":"104Th Ave Ne",
    "iso:country":"US",
    "sg:address":"14603 104th Ave NE",
    "sg:city":"Bothell",
    "sg:classifiers":[
        {
            "category":"Insurance",
            "subcategory":"Insurance Agent",
            "type":"Services"
        }
    ],
    "sg:phone":"+1 425 398 9375",
    "sg:postcode":"98011",
    "sg:province":"WA",
    "wof:name":"Sirius Billing",
    "wof:placetype":"venue"
},
  "geometry": {"coordinates":[-122.201651,47.73515],"type":"Point"}
}