{
  "type": "Feature",
  "properties": {
    "addr:full":"13317 Ash Way Everett WA 98204",
    "addr:housenumber":"13317",
    "addr:postcode":"98204",
    "addr:street":"Ash Way",
    "iso:country":"US",
    "sg:address":"13317 Ash Way",
    "sg:city":"Everett",
    "sg:classifiers":[
        {
            "category":"Wholesale",
            "subcategory":"Durable Goods & Equipment",
            "type":"Manufacturing & Wholesale Goods"
        }
    ],
    "sg:phone":"+1 425 918 1433",
    "sg:postcode":"98204",
    "sg:province":"WA",
    "sg:tags":[
        "importer"
    ],
    "wof:name":"Heart Side Collection",
    "wof:placetype":"venue"
},
  "geometry": {"coordinates":[-122.248492,47.877733],"type":"Point"}
}