{
  "type": "Feature",
  "properties": {
    "addr:full":"1016 Mingo Mountain Rd Kettle Falls WA 99141",
    "addr:housenumber":"1016",
    "addr:postcode":"99141",
    "addr:street":"Mingo Mountain Rd",
    "iso:country":"US",
    "sg:address":"1016 Mingo Mountain Rd",
    "sg:city":"Kettle Falls",
    "sg:classifiers":[
        {
            "category":"Professional",
            "type":"Services"
        }
    ],
    "sg:phone":"+1 509 738 2519",
    "sg:postcode":"99141",
    "sg:province":"WA",
    "wof:name":"Cherry Blossoms",
    "wof:placetype":"venue"
},
  "geometry": {"coordinates":[-118.06605999999999,48.57105],"type":"Point"}
}