{
  "type": "Feature",
  "properties": {
    "addr:full":"2657 20th Ave W Seattle WA 98199",
    "addr:housenumber":"2657",
    "addr:postcode":"98199",
    "addr:street":"20Th Ave W",
    "iso:country":"US",
    "sg:address":"2657 20th Ave W",
    "sg:city":"Seattle",
    "sg:classifiers":[
        {
            "category":"Building & Trades",
            "subcategory":"Construction",
            "type":"Services"
        }
    ],
    "sg:phone":"+1 206 282 4288",
    "sg:postcode":"98199",
    "sg:province":"WA",
    "sg:tags":[
        "acoustical",
        "plastering",
        "drywall",
        "contractor"
    ],
    "sg:website":"http://www.mehrer.com",
    "wof:name":"Mehrer Drywall Inc",
    "wof:placetype":"venue"
},
  "geometry": {"coordinates":[-122.381981,47.645555],"type":"Point"}
}