{
  "type": "Feature",
  "properties": {
    "addr:full":"692 Bakken Rd Greenbank WA 98253",
    "addr:housenumber":"692",
    "addr:postcode":"98253",
    "addr:street":"Bakken Rd",
    "iso:country":"US",
    "sg:address":"692 Bakken Rd",
    "sg:city":"Greenbank",
    "sg:classifiers":[
        {
            "category":"Building & Trades",
            "subcategory":"Construction",
            "type":"Services"
        }
    ],
    "sg:phone":"+1 360 678 4315",
    "sg:postcode":"98253",
    "sg:province":"WA",
    "sg:tags":[
        "carpentry",
        "contractor"
    ],
    "wof:name":"Petry Overhead Doors & Custom",
    "wof:placetype":"venue"
},
  "geometry": {"coordinates":[-122.579133,48.098257],"type":"Point"}
}