{
  "type": "Feature",
  "properties": {
    "addr:full":"2848 S Othello St Seattle WA 98108",
    "addr:housenumber":"2848",
    "addr:postcode":"98108",
    "addr:street":"S Othello St",
    "iso:country":"US",
    "sg:address":"2848 S Othello St",
    "sg:city":"Seattle",
    "sg:classifiers":[
        {
            "category":"Wholesale",
            "subcategory":"Meat",
            "type":"Manufacturing & Wholesale Goods"
        }
    ],
    "sg:phone":"+1 206 683 5508",
    "sg:postcode":"98108",
    "sg:province":"WA",
    "wof:name":"Che Enterprise",
    "wof:placetype":"venue"
},
  "geometry": {"coordinates":[-122.293221,47.536761],"type":"Point"}
}