{
  "type": "Feature",
  "properties": {
    "addr:full":"217 Lake St S Kirkland WA 98033",
    "addr:housenumber":"217",
    "addr:postcode":"98033",
    "addr:street":"Lake St S",
    "iso:country":"US",
    "sg:address":"217 Lake St S",
    "sg:city":"Kirkland",
    "sg:classifiers":[
        {
            "category":"Shopping",
            "subcategory":"Antiques",
            "type":"Retail Goods"
        }
    ],
    "sg:phone":"+1 425 827 6593",
    "sg:postcode":"98033",
    "sg:province":"WA",
    "wof:name":"Lisa's Fine Antiques & Wonderful Things",
    "wof:placetype":"venue"
},
  "geometry": {"coordinates":[-122.206001,47.673599],"type":"Point"}
}