{
  "type": "Feature",
  "properties": {
    "addr:full":"1410 218th St SW Lynnwood WA 98036",
    "addr:housenumber":"1410",
    "addr:postcode":"98036",
    "addr:street":"218Th St Sw",
    "iso:country":"US",
    "sg:address":"1410 218th St SW",
    "sg:city":"Lynnwood",
    "sg:classifiers":[
        {
            "category":"Building & Trades",
            "subcategory":"Construction",
            "type":"Services"
        }
    ],
    "sg:phone":"+1 425 744 9705",
    "sg:postcode":"98036",
    "sg:province":"WA",
    "sg:tags":[
        "residential",
        "contractor"
    ],
    "wof:name":"New Millennium Construction",
    "wof:placetype":"venue"
},
  "geometry": {"coordinates":[-122.252753,47.800724],"type":"Point"}
}