{
  "type": "Feature",
  "properties": {
    "addr:full":"12506 89th Ct NE Kirkland WA 98034",
    "addr:housenumber":"12506",
    "addr:postcode":"98034",
    "addr:street":"89Th Ct Ne",
    "iso:country":"US",
    "sg:address":"12506 89th Ct NE",
    "sg:city":"Kirkland",
    "sg:classifiers":[
        {
            "category":"Professional",
            "subcategory":"Accounting & Tax Preparation",
            "type":"Services"
        }
    ],
    "sg:phone":"+1 425 820 8952",
    "sg:postcode":"98034",
    "sg:province":"WA",
    "wof:name":"Ronald L Haworth CPA",
    "wof:placetype":"venue"
},
  "geometry": {"coordinates":[-122.222728,47.713048],"type":"Point"}
}