{
  "type": "Feature",
  "properties": {
    "addr:full":"25 N Worthen St Wenatchee WA 98801",
    "addr:housenumber":"25",
    "addr:postcode":"98801",
    "addr:street":"N Worthen St",
    "iso:country":"US",
    "sg:address":"25 N Worthen St",
    "sg:city":"Wenatchee",
    "sg:classifiers":[
        {
            "category":"Government",
            "subcategory":"Office",
            "type":"Public Place"
        }
    ],
    "sg:phone":"+1 509 664 3368",
    "sg:postcode":"98801",
    "sg:province":"WA",
    "sg:tags":[
        "village"
    ],
    "wof:name":"City Engineer",
    "wof:placetype":"venue"
},
  "geometry": {"coordinates":[-120.313338,47.431853],"type":"Point"}
}