{
  "type": "Feature",
  "properties": {
    "addr:full":"512 S Lake St Colfax WA 99111",
    "addr:housenumber":"512",
    "addr:postcode":"99111",
    "addr:street":"S Lake St",
    "iso:country":"US",
    "sg:address":"512 S Lake St",
    "sg:city":"Colfax",
    "sg:classifiers":[
        {
            "category":"Retail",
            "subcategory":"Repair Shop",
            "type":"Services"
        }
    ],
    "sg:phone":"+1 509 397 4232",
    "sg:postcode":"99111",
    "sg:province":"WA",
    "wof:name":"J & J Upholstery",
    "wof:placetype":"venue"
},
  "geometry": {"coordinates":[-117.366669,46.877523],"type":"Point"}
}