{
  "type": "Feature",
  "properties": {
    "addr:full":"8332 196th Ave NE Redmond WA 98053",
    "addr:housenumber":"8332",
    "addr:postcode":"98053",
    "addr:street":"196Th Ave Ne",
    "iso:country":"US",
    "sg:address":"8332 196th Ave NE",
    "sg:city":"Redmond",
    "sg:classifiers":[
        {
            "category":"Building & Trades",
            "subcategory":"Landscaping Services",
            "type":"Services"
        }
    ],
    "sg:phone":"+1 425 868 5885",
    "sg:postcode":"98053",
    "sg:province":"WA",
    "sg:tags":[
        "lawn",
        "maintenance",
        "garden",
        "landscape",
        "contractor"
    ],
    "wof:name":"Signature Landscape Services",
    "wof:placetype":"venue"
},
  "geometry": {"coordinates":[-122.079003,47.681903],"type":"Point"}
}