{
  "type": "Feature",
  "properties": {
    "addr:full":"102 Sinlahekin Rd Conconully WA 98840",
    "addr:housenumber":"102",
    "addr:postcode":"98840",
    "addr:street":"Sinlahekin Rd",
    "iso:country":"US",
    "sg:address":"102 Sinlahekin Rd",
    "sg:city":"Conconully",
    "sg:classifiers":[
        {
            "category":"Travel",
            "subcategory":"Hotels & Motels",
            "type":"Entertainment"
        }
    ],
    "sg:phone":"+1 509 826 0813",
    "sg:postcode":"98840",
    "sg:province":"WA",
    "sg:tags":[
        "resort"
    ],
    "wof:name":"Conconully Lake Resort",
    "wof:placetype":"venue"
},
  "geometry": {"coordinates":[-119.722773,48.564686],"type":"Point"}
}