{
  "type": "Feature",
  "properties": {
    "addr:full":"17836 108th Ave SE Renton WA 98055",
    "addr:housenumber":"17836",
    "addr:postcode":"98055",
    "addr:street":"108Th Ave Se",
    "iso:country":"US",
    "sg:address":"17836 108th Ave SE",
    "sg:city":"Renton",
    "sg:classifiers":[
        {
            "category":"Health Services",
            "subcategory":"Chiropractor",
            "type":"Services"
        }
    ],
    "sg:phone":"+1 425 271 6271",
    "sg:postcode":"98055",
    "sg:province":"WA",
    "wof:name":"Marsh Chiropractic",
    "wof:placetype":"venue"
},
  "geometry": {"coordinates":[-122.196894,47.441675],"type":"Point"}
}