{
  "type": "Feature",
  "properties": {
    "addr:full":"6538 4th Ave S Seattle WA 98108",
    "addr:housenumber":"6538",
    "addr:postcode":"98108",
    "addr:street":"4Th Ave S",
    "iso:country":"US",
    "sg:address":"6538 4th Ave S",
    "sg:city":"Seattle",
    "sg:classifiers":[
        {
            "category":"Restaurant",
            "type":"Food & Drink"
        }
    ],
    "sg:phone":"+1 206 932 7200",
    "sg:postcode":"98108",
    "sg:province":"WA",
    "sg:tags":[
        "barbeque"
    ],
    "sg:website":"www.piggspenbbq.com",
    "wof:name":"Pigg's Pen BBQ",
    "wof:placetype":"venue"
},
  "geometry": {"coordinates":[-122.32916,47.544052],"type":"Point"}
}