{
  "type": "Feature",
  "properties": {
    "addr:full":"904 Dwight St Port Orchard WA 98366",
    "addr:housenumber":"904",
    "addr:postcode":"98366",
    "addr:street":"Dwight St",
    "iso:country":"US",
    "sg:address":"904 Dwight St",
    "sg:city":"Port Orchard",
    "sg:classifiers":[
        {
            "category":"Professional",
            "subcategory":"Lawyer & Legal Services",
            "type":"Services"
        }
    ],
    "sg:phone":"+1 360 876 5567",
    "sg:postcode":"98366",
    "sg:province":"WA",
    "wof:name":"Case and Hemstreet",
    "wof:placetype":"venue"
},
  "geometry": {"coordinates":[-122.632751,47.538792],"type":"Point"}
}