{
  "type": "Feature",
  "properties": {
    "addr:full":"5110 NE 184th St Seattle WA 98155",
    "addr:housenumber":"5110",
    "addr:postcode":"98155",
    "addr:street":"Ne 184Th St",
    "iso:country":"US",
    "sg:address":"5110 NE 184th St",
    "sg:city":"Seattle",
    "sg:classifiers":[
        {
            "category":"Building & Trades",
            "subcategory":"Construction",
            "type":"Services"
        }
    ],
    "sg:phone":"+1 206 417 4550",
    "sg:postcode":"98155",
    "sg:province":"WA",
    "sg:tags":[
        "contractor"
    ],
    "wof:name":"Solarium Skylighting Inc",
    "wof:placetype":"venue"
},
  "geometry": {"coordinates":[-122.27564099999999,47.761235],"type":"Point"}
}