{
  "type": "Feature",
  "properties": {
    "iso:country":"US",
    "sg:address":"1081 Hildebrand Ln NE",
    "sg:city":"Bainbridge Isle",
    "sg:classifiers":[
        {
            "category":"Banks & Credit Unions",
            "subcategory":"Bank",
            "type":"Services"
        }
    ],
    "sg:phone":"+1 206 842 1444",
    "sg:postcode":"98110",
    "sg:province":"WA",
    "sg:tags":[
        "loan"
    ],
    "wof:name":"Bainbridge Lending Group",
    "wof:placetype":"venue"
},
  "geometry": {"coordinates":[-122.517079,47.633751],"type":"Point"}
}