{
  "type": "Feature",
  "properties": {
    "addr:full":"256861 Hwy 101 Port Angeles WA 98362",
    "addr:housenumber":"256861",
    "addr:postcode":"98362",
    "addr:street":"Hwy 101",
    "iso:country":"US",
    "sg:address":"256861 Hwy 101",
    "sg:city":"Port Angeles",
    "sg:classifiers":[
        {
            "category":"Food & Beverages",
            "subcategory":"Bakery",
            "type":"Retail Goods"
        }
    ],
    "sg:phone":"+1 360 452 6360",
    "sg:postcode":"98362",
    "sg:province":"WA",
    "sg:tags":[
        "baker"
    ],
    "wof:name":"Rain Drop Desserts",
    "wof:placetype":"venue"
},
  "geometry": {"coordinates":[-123.266217,48.092693],"type":"Point"}
}