{
  "type": "Feature",
  "properties": {
    "addr:full":"620 W Main St Centralia WA 98531",
    "addr:housenumber":"620",
    "addr:postcode":"98531",
    "addr:street":"W Main St",
    "iso:country":"US",
    "sg:address":"620 W Main St",
    "sg:city":"Centralia",
    "sg:classifiers":[
        {
            "category":"Banks & Credit Unions",
            "subcategory":"Investment Brokerage",
            "type":"Services"
        }
    ],
    "sg:phone":"+1 360 736 8200",
    "sg:postcode":"98531",
    "sg:province":"WA",
    "sg:tags":[
        "stock",
        "bond"
    ],
    "wof:name":"Ragen Mackenzie Investments",
    "wof:placetype":"venue"
},
  "geometry": {"coordinates":[-122.961331,46.717567],"type":"Point"}
}