{
  "type": "Feature",
  "properties": {
    "addr:full":"16401 84th St NE Lake Stevens WA 98252",
    "addr:housenumber":"16401",
    "addr:postcode":"98252",
    "addr:street":"84Th St Ne",
    "iso:country":"US",
    "sg:address":"16401 84th St NE",
    "sg:city":"Lake Stevens",
    "sg:classifiers":[
        {
            "category":"Restaurant",
            "type":"Food & Drink"
        }
    ],
    "sg:phone":"+1 360 691 1561",
    "sg:postcode":"98252",
    "sg:province":"WA",
    "wof:name":"Sahara's Pizza",
    "wof:placetype":"venue"
},
  "geometry": {"coordinates":[-122.011464,48.07207],"type":"Point"}
}