{
  "type": "Feature",
  "properties": {
    "addr:full":"3221 Eastlake Ave E Ste 120 Seattle WA 98102",
    "addr:housenumber":"3221",
    "addr:postcode":"98102",
    "addr:street":"Eastlake Ave E Ste 120",
    "iso:country":"US",
    "sg:address":"3221 Eastlake Ave E Ste 120",
    "sg:city":"Seattle",
    "sg:classifiers":[
        {
            "category":"Health Services",
            "subcategory":"Health Practitioner",
            "type":"Services"
        },
        {
            "category":"Health Services",
            "subcategory":"Chiropractor",
            "type":"Services"
        }
    ],
    "sg:phone":"+1 206 957 4550",
    "sg:postcode":"98102",
    "sg:province":"WA",
    "sg:tags":[
        "acupuncture"
    ],
    "wof:name":"Lewis Michael DC",
    "wof:placetype":"venue"
},
  "geometry": {"coordinates":[-122.322062,47.650607],"type":"Point"}
}