{
  "type": "Feature",
  "properties": {
    "addr:full":"22017 100th Ct SE Kent WA 98031",
    "addr:housenumber":"22017",
    "addr:postcode":"98031",
    "addr:street":"100Th Ct Se",
    "iso:country":"US",
    "sg:address":"22017 100th Ct SE",
    "sg:city":"Kent",
    "sg:classifiers":[
        {
            "category":"Shopping",
            "subcategory":"Department Store",
            "type":"Retail Goods"
        }
    ],
    "sg:phone":"+1 253 850 1325",
    "sg:postcode":"98031",
    "sg:province":"WA",
    "sg:tags":[
        "variety"
    ],
    "wof:name":"Take 99 Studios",
    "wof:placetype":"venue"
},
  "geometry": {"coordinates":[-122.20661800000001,47.404981],"type":"Point"}
}