{
  "type": "Feature",
  "properties": {
    "addr:full":"3828 4th Ave S Seattle WA 98134",
    "addr:housenumber":"3828",
    "addr:postcode":"98134",
    "addr:street":"4Th Ave S",
    "iso:country":"US",
    "sg:address":"3828 4th Ave S",
    "sg:city":"Seattle",
    "sg:classifiers":[
        {
            "category":"Real Estate",
            "subcategory":"Architect",
            "type":"Services"
        }
    ],
    "sg:phone":"+1 206 282 7582",
    "sg:postcode":"98134",
    "sg:province":"WA",
    "sg:tags":[
        "architectural"
    ],
    "wof:name":"Und",
    "wof:placetype":"venue"
},
  "geometry": {"coordinates":[-122.328975,47.569978],"type":"Point"}
}