{
  "type": "Feature",
  "properties": {
    "addr:full":"508 108th Ave SE Bellevue WA 98004",
    "addr:housenumber":"508",
    "addr:postcode":"98004",
    "addr:street":"108Th Ave Se",
    "iso:country":"US",
    "sg:address":"508 108th Ave SE",
    "sg:city":"Bellevue",
    "sg:classifiers":[
        {
            "category":"Professional",
            "subcategory":"Management & Consulting",
            "type":"Services"
        }
    ],
    "sg:phone":"+1 425 453 1544",
    "sg:postcode":"98004",
    "sg:province":"WA",
    "wof:name":"Westrum Janice J Kms Fincl Svc",
    "wof:placetype":"venue"
},
  "geometry": {"coordinates":[-122.19591800000001,47.604092],"type":"Point"}
}