{
  "type": "Feature",
  "properties": {
    "addr:full":"17500 Beach Dr NE Seattle WA 98155",
    "addr:housenumber":"17500",
    "addr:postcode":"98155",
    "addr:street":"Beach Dr Ne",
    "iso:country":"US",
    "sg:address":"17500 Beach Dr NE",
    "sg:city":"Seattle",
    "sg:classifiers":[
        {
            "category":"Marine",
            "type":"Transportation"
        }
    ],
    "sg:phone":"+1 206 362 7860",
    "sg:postcode":"98155",
    "sg:province":"WA",
    "sg:tags":[
        "water",
        "transport"
    ],
    "wof:name":"George M Poor Inc",
    "wof:placetype":"venue"
},
  "geometry": {"coordinates":[-122.27611,47.75333],"type":"Point"}
}