{
  "type": "Feature",
  "properties": {
    "addr:full":"511 164th St SW Lynnwood WA 98087",
    "addr:housenumber":"511",
    "addr:postcode":"98087",
    "addr:street":"164Th St Sw",
    "iso:country":"US",
    "sg:address":"511 164th St SW",
    "sg:city":"Lynnwood",
    "sg:classifiers":[
        {
            "category":"Food & Beverages",
            "subcategory":"Groceries & Convenience Stores",
            "type":"Retail Goods"
        }
    ],
    "sg:phone":"+1 425 745 3777",
    "sg:postcode":"98087",
    "sg:province":"WA",
    "wof:name":"Sam's Mini Market",
    "wof:placetype":"venue"
},
  "geometry": {"coordinates":[-122.239721,47.849593],"type":"Point"}
}