{
  "type": "Feature",
  "properties": {
    "addr:full":"8407 Rainier Ave Seattle WA 98118",
    "addr:housenumber":"8407",
    "addr:postcode":"98118",
    "addr:street":"Rainier Ave",
    "iso:country":"US",
    "sg:address":"8407 Rainier Ave",
    "sg:city":"Seattle",
    "sg:classifiers":[
        {
            "category":"Personal",
            "subcategory":"Barber",
            "type":"Services"
        }
    ],
    "sg:phone":"+1 206 242 7575",
    "sg:postcode":"98118",
    "sg:province":"WA",
    "sg:tags":[
        "shop"
    ],
    "wof:name":"Crosby Berry Barber Shop",
    "wof:placetype":"venue"
},
  "geometry": {"coordinates":[-122.270059,47.526221],"type":"Point"}
}