{
  "type": "Feature",
  "properties": {
    "addr:full":"15316 NE 44th St Vancouver WA 98682",
    "addr:housenumber":"15316",
    "addr:postcode":"98682",
    "addr:street":"Ne 44Th St",
    "iso:country":"US",
    "sg:address":"15316 NE 44th St",
    "sg:city":"Vancouver",
    "sg:classifiers":[
        {
            "category":"Building & Trades",
            "subcategory":"Construction",
            "type":"Services"
        }
    ],
    "sg:phone":"+1 360 882 5003",
    "sg:postcode":"98682",
    "sg:province":"WA",
    "sg:tags":[
        "contractor"
    ],
    "wof:name":"Pro West Roofing",
    "wof:placetype":"venue"
},
  "geometry": {"coordinates":[-122.515103,45.654377],"type":"Point"}
}