{
  "type": "Feature",
  "properties": {
    "iso:country":"US",
    "sg:address":"608 Pioneer Ln",
    "sg:city":"Yakima",
    "sg:classifiers":[
        {
            "category":"Professional",
            "subcategory":"Computer Services",
            "type":"Services"
        }
    ],
    "sg:phone":"+1 509 248 5936",
    "sg:postcode":"98903",
    "sg:province":"WA",
    "sg:tags":[
        "software",
        "developer"
    ],
    "wof:name":"Tiburon Inc",
    "wof:placetype":"venue"
},
  "geometry": {"coordinates":[-120.513504,46.563494],"type":"Point"}
}