{
  "type": "Feature",
  "properties": {
    "addr:full":"2102 E Sprague Ave Spokane WA 99202",
    "addr:housenumber":"2102",
    "addr:postcode":"99202",
    "addr:street":"E Sprague Ave",
    "iso:country":"US",
    "sg:address":"2102 E Sprague Ave",
    "sg:city":"Spokane",
    "sg:classifiers":[
        {
            "category":"Health Services",
            "subcategory":"Clinic",
            "type":"Services"
        }
    ],
    "sg:phone":"+1 509 458 7454",
    "sg:postcode":"99202",
    "sg:province":"WA",
    "sg:tags":[
        "specialty",
        "outpatient"
    ],
    "wof:name":"Evergreen Club",
    "wof:placetype":"venue"
},
  "geometry": {"coordinates":[-117.378247,47.657196],"type":"Point"}
}