{
  "type": "Feature",
  "properties": {
    "addr:full":"725 6th St Ste 108 Clarkston WA 99403",
    "addr:housenumber":"725",
    "addr:postcode":"99403",
    "addr:street":"6Th St Ste 108",
    "iso:country":"US",
    "sg:address":"725 6th St Ste 108",
    "sg:city":"Clarkston",
    "sg:classifiers":[
        {
            "category":"Real Estate",
            "subcategory":"Real Estate Services",
            "type":"Services"
        },
        {
            "category":"Real Estate",
            "subcategory":"Real Estate Agent",
            "type":"Services"
        }
    ],
    "sg:phone":"+1 509 758 2600",
    "sg:postcode":"99403",
    "sg:province":"WA",
    "sg:tags":[
        "buyer",
        "broker"
    ],
    "wof:name":"Ausman Realty",
    "wof:placetype":"venue"
},
  "geometry": {"coordinates":[-117.045592,46.415845],"type":"Point"}
}