{
  "type": "Feature",
  "properties": {
    "addr:full":"3822 N Simpson Rd Otis Orchards WA 99027",
    "addr:housenumber":"3822",
    "addr:postcode":"99027",
    "addr:street":"N Simpson Rd",
    "iso:country":"US",
    "sg:address":"3822 N Simpson Rd",
    "sg:city":"Otis Orchards",
    "sg:classifiers":[
        {
            "category":"Professional",
            "subcategory":"Computer Services",
            "type":"Services"
        }
    ],
    "sg:phone":"+1 509 226 1973",
    "sg:postcode":"99027",
    "sg:province":"WA",
    "sg:tags":[
        "prepackaged",
        "software"
    ],
    "wof:name":"Team Management Software Inc",
    "wof:placetype":"venue"
},
  "geometry": {"coordinates":[-117.07932599999999,47.692886],"type":"Point"}
}