{
  "type": "Feature",
  "properties": {
    "addr:full":"1313 Jadwin Ave Richland WA 99354",
    "addr:housenumber":"1313",
    "addr:postcode":"99354",
    "addr:street":"Jadwin Ave",
    "iso:country":"US",
    "sg:address":"1313 Jadwin Ave",
    "sg:city":"Richland",
    "sg:phone":"+1 509 946 9011",
    "sg:postcode":"99354",
    "sg:province":"WA",
    "sg:website":"http://www.dairyqueen.com",
    "wof:name":"Dairy Queen",
    "wof:placetype":"venue"
},
  "geometry": {"coordinates":[-119.27739,46.2878],"type":"Point"}
}