{
  "type": "Feature",
  "properties": {
    "addr:full":"19707 130th Pl NE Woodinville WA 98072",
    "addr:housenumber":"19707",
    "addr:postcode":"98072",
    "addr:street":"130Th Pl Ne",
    "iso:country":"US",
    "sg:address":"19707 130th Pl NE",
    "sg:city":"Woodinville",
    "sg:classifiers":[
        {
            "category":"Wholesale",
            "subcategory":"Vending Machines",
            "type":"Manufacturing & Wholesale Goods"
        }
    ],
    "sg:phone":"+1 425 481 4746",
    "sg:postcode":"98072",
    "sg:province":"WA",
    "sg:tags":[
        "operator"
    ],
    "wof:name":"Gumball Gourmet",
    "wof:placetype":"venue"
},
  "geometry": {"coordinates":[-122.16601199999999,47.770398],"type":"Point"}
}