{
  "type": "Feature",
  "properties": {
    "iso:country":"US",
    "sg:address":"414 3rd Ave W",
    "sg:city":"Seattle",
    "sg:classifiers":[
        {
            "category":"Banks & Credit Unions",
            "subcategory":"Bank",
            "type":"Services"
        }
    ],
    "sg:phone":"+1 206 281 8842",
    "sg:postcode":"98119",
    "sg:province":"WA",
    "sg:tags":[
        "lender",
        "commercial"
    ],
    "wof:name":"Northwest Capitol Partners Inc",
    "wof:placetype":"venue"
},
  "geometry": {"coordinates":[-122.36056600000001,47.62312],"type":"Point"}
}