{
  "type": "Feature",
  "properties": {
    "addr:full":"1412 E Union Seattle WA 98122",
    "addr:housenumber":"1412",
    "addr:postcode":"98122",
    "addr:street":"E Union",
    "iso:country":"US",
    "sg:address":"1412 E Union",
    "sg:city":"Seattle",
    "sg:classifiers":[
        {
            "category":"Restaurant",
            "type":"Food & Drink"
        }
    ],
    "sg:phone":"+1 206 441 9842",
    "sg:postcode":"98122",
    "sg:province":"WA",
    "sg:tags":[
        "new",
        "american"
    ],
    "sg:website":"www.marjorierestaurant.com/",
    "wof:name":"Marjorie",
    "wof:placetype":"venue"
},
  "geometry": {"coordinates":[-122.313509,47.613289],"type":"Point"}
}