{
  "type": "Feature",
  "properties": {
    "addr:full":"26910 Barber Cut Off Rd NE Kingston WA 98346",
    "addr:housenumber":"26910",
    "addr:postcode":"98346",
    "addr:street":"Barber Cut Off Rd Ne",
    "iso:country":"US",
    "sg:address":"26910 Barber Cut Off Rd NE",
    "sg:city":"Kingston",
    "sg:classifiers":[
        {
            "category":"Restaurant",
            "type":"Food & Drink"
        }
    ],
    "sg:phone":"+1 360 297 2676",
    "sg:postcode":"98346",
    "sg:province":"WA",
    "sg:tags":[
        "eating"
    ],
    "wof:name":"Beaver Hill Cafe",
    "wof:placetype":"venue"
},
  "geometry": {"coordinates":[-122.518169,47.807851],"type":"Point"}
}