{
  "type": "Feature",
  "properties": {
    "addr:full":"1801 Ellis St Bellingham WA 98225",
    "addr:housenumber":"1801",
    "addr:postcode":"98225",
    "addr:street":"Ellis St",
    "iso:country":"US",
    "sg:address":"1801 Ellis St",
    "sg:city":"Bellingham",
    "sg:classifiers":[
        {
            "category":"Professional",
            "type":"Services"
        },
        {
            "category":"Personal",
            "type":"Services"
        },
        {
            "category":"Freight",
            "type":"Transportation"
        },
        {
            "category":"Retail",
            "subcategory":"Storage",
            "type":"Services"
        }
    ],
    "sg:phone":"+1 360 733 7800",
    "sg:postcode":"98225",
    "sg:province":"WA",
    "sg:tags":[
        "full",
        "household",
        "material",
        "commercial",
        "trucking",
        "moving",
        "services-labor",
        "mover",
        "local"
    ],
    "wof:name":"K & E Moving & Storage",
    "wof:placetype":"venue"
},
  "geometry": {"coordinates":[-122.472191,48.753811],"type":"Point"}
}