{
  "type": "Feature",
  "properties": {
    "addr:full":"3602 Fairbanks Ave Yakima WA 98902",
    "addr:housenumber":"3602",
    "addr:postcode":"98902",
    "addr:street":"Fairbanks Ave",
    "iso:country":"US",
    "sg:address":"3602 Fairbanks Ave",
    "sg:city":"Yakima",
    "sg:classifiers":[
        {
            "category":"Utilities",
            "subcategory":"Telephone",
            "type":"Services"
        }
    ],
    "sg:phone":"+1 509 469 1417",
    "sg:postcode":"98902",
    "sg:province":"WA",
    "sg:tags":[
        "communications"
    ],
    "wof:name":"JM Traders",
    "wof:placetype":"venue"
},
  "geometry": {"coordinates":[-120.554428,46.607934],"type":"Point"}
}