{
  "type": "Feature",
  "properties": {
    "addr:full":"2112 N 30th St Tacoma WA 98403",
    "addr:housenumber":"2112",
    "addr:postcode":"98403",
    "addr:street":"N 30Th St",
    "iso:country":"US",
    "sg:address":"2112 N 30th St",
    "sg:city":"Tacoma",
    "sg:classifiers":[
        {
            "category":"Coffee & Tea",
            "type":"Food & Drink"
        }
    ],
    "sg:menulink":"http://www.allmenus.com/wa/tacoma/117689-starbucks-coffee/menu/",
    "sg:phone":"+1 253 573 1901",
    "sg:postcode":"98403",
    "sg:province":"WA",
    "sg:tags":[
        "american"
    ],
    "wof:name":"Starbucks Coffee",
    "wof:placetype":"venue"
},
  "geometry": {"coordinates":[-122.46446299999999,47.274769],"type":"Point"}
}