{
  "type": "Feature",
  "properties": {
    "addr:full":"16807 25th Ave SE Bothell WA 98012",
    "addr:housenumber":"16807",
    "addr:postcode":"98012",
    "addr:street":"25Th Ave Se",
    "iso:country":"US",
    "sg:address":"16807 25th Ave SE",
    "sg:city":"Bothell",
    "sg:classifiers":[
        {
            "category":"Building & Trades",
            "subcategory":"Cleaning & Sanitation",
            "type":"Services"
        }
    ],
    "sg:phone":"+1 425 766 0254",
    "sg:postcode":"98012",
    "sg:province":"WA",
    "sg:tags":[
        "maintenance"
    ],
    "wof:name":"P & E Janitorials",
    "wof:placetype":"venue"
},
  "geometry": {"coordinates":[-122.198547,47.844931],"type":"Point"}
}