{
  "type": "Feature",
  "properties": {
    "addr:full":"6319 Soundview Dr Gig Harbor WA 98335",
    "addr:housenumber":"6319",
    "addr:postcode":"98335",
    "addr:street":"Soundview Dr",
    "iso:country":"US",
    "sg:address":"6319 Soundview Dr",
    "sg:city":"Gig Harbor",
    "sg:classifiers":[
        {
            "category":"Personal",
            "subcategory":"Beauty Salon",
            "type":"Services"
        }
    ],
    "sg:phone":"+1 253 858 5118",
    "sg:postcode":"98335",
    "sg:province":"WA",
    "sg:tags":[
        "shop"
    ],
    "wof:name":"Northwest Hair Care",
    "wof:placetype":"venue"
},
  "geometry": {"coordinates":[-122.578935,47.315901],"type":"Point"}
}