{
  "type": "Feature",
  "properties": {
    "addr:full":"1305 Tacoma Ave S Tacoma WA 98402",
    "addr:housenumber":"1305",
    "addr:postcode":"98402",
    "addr:street":"Tacoma Ave S",
    "iso:country":"US",
    "sg:address":"1305 Tacoma Ave S",
    "sg:city":"Tacoma",
    "sg:classifiers":[
        {
            "category":"Organizations",
            "subcategory":"Membership Organization",
            "type":"Services"
        }
    ],
    "sg:phone":"+1 253 627 6674",
    "sg:postcode":"98402",
    "sg:province":"WA",
    "wof:name":"Public Service Building",
    "wof:placetype":"venue"
},
  "geometry": {"coordinates":[-122.443668,47.24973],"type":"Point"}
}