{
  "type": "Feature",
  "properties": {
    "addr:full":"1515 NW 53rd St Seattle WA 98107",
    "addr:housenumber":"1515",
    "addr:postcode":"98107",
    "addr:street":"Nw 53Rd St",
    "iso:country":"US",
    "sg:address":"1515 NW 53rd St",
    "sg:city":"Seattle",
    "sg:classifiers":[
        {
            "category":"Wholesale",
            "subcategory":"Electrical",
            "type":"Manufacturing & Wholesale Goods"
        }
    ],
    "sg:phone":"+1 206 227 5700",
    "sg:postcode":"98107",
    "sg:province":"WA",
    "sg:tags":[
        "equipment"
    ],
    "wof:name":"Vilmar Lighting Sales",
    "wof:placetype":"venue"
},
  "geometry": {"coordinates":[-122.378759,47.66709],"type":"Point"}
}