{
  "type": "Feature",
  "properties": {
    "addr:full":"813 Alabama St Bellingham WA 98225",
    "addr:housenumber":"813",
    "addr:postcode":"98225",
    "addr:street":"Alabama St",
    "iso:country":"US",
    "sg:address":"813 Alabama St",
    "sg:city":"Bellingham",
    "sg:classifiers":[
        {
            "category":"Manufacturing",
            "subcategory":"Furniture",
            "type":"Manufacturing & Wholesale Goods"
        }
    ],
    "sg:phone":"+1 360 734 7459",
    "sg:postcode":"98225",
    "sg:province":"WA",
    "sg:tags":[
        "household",
        "wood",
        "mfg"
    ],
    "wof:name":"Wood Creations",
    "wof:placetype":"venue"
},
  "geometry": {"coordinates":[-122.463583,48.7631],"type":"Point"}
}