{
  "type": "Feature",
  "properties": {
    "addr:full":"3596 Mount Pleasant Rd Kelso WA 98626",
    "addr:housenumber":"3596",
    "addr:postcode":"98626",
    "addr:street":"Mount Pleasant Rd",
    "iso:country":"US",
    "sg:address":"3596 Mount Pleasant Rd",
    "sg:city":"Kelso",
    "sg:classifiers":[
        {
            "category":"Manufacturing",
            "subcategory":"Toys & Sporting Goods",
            "type":"Manufacturing & Wholesale Goods"
        },
        {
            "category":"Shopping",
            "subcategory":"Bicycles & Sporting Goods",
            "type":"Retail Goods"
        }
    ],
    "sg:phone":"+1 360 636 5021",
    "sg:postcode":"98626",
    "sg:province":"WA",
    "sg:tags":[
        "goods-wholesale",
        "manufacturer"
    ],
    "wof:name":"Bernie's Big Boys' Toys",
    "wof:placetype":"venue"
},
  "geometry": {"coordinates":[-122.767872,46.083932],"type":"Point"}
}