{
  "type": "Feature",
  "properties": {
    "addr:full":"2412 N Road 68 Pasco WA 99301",
    "addr:housenumber":"2412",
    "addr:postcode":"99301",
    "addr:street":"N Road 68",
    "iso:country":"US",
    "sg:address":"2412 N Road 68",
    "sg:city":"Pasco",
    "sg:classifiers":[
        {
            "category":"Place Of Worship",
            "subcategory":"Church",
            "type":"Public Place"
        },
        {
            "category":"Place Of Worship",
            "type":"Public Place"
        }
    ],
    "sg:phone":"+1 509 547 0091",
    "sg:postcode":"99301",
    "sg:province":"WA",
    "sg:tags":[
        "testament",
        "christ-new",
        "churches-church",
        "christ"
    ],
    "wof:name":"Church Of Christ",
    "wof:placetype":"venue"
},
  "geometry": {"coordinates":[-119.180046,46.249923],"type":"Point"}
}