{
  "type": "Feature",
  "properties": {
    "addr:full":"219 1st Ave S Ste 310 Seattle WA 98104",
    "addr:housenumber":"219",
    "addr:postcode":"98104",
    "addr:street":"1St Ave S Ste 310",
    "iso:country":"US",
    "sg:address":"219 1st Ave S Ste 310",
    "sg:city":"Seattle",
    "sg:classifiers":[
        {
            "category":"Food & Beverages",
            "subcategory":"Meat & Fish",
            "type":"Retail Goods"
        }
    ],
    "sg:phone":"+1 206 587 0005",
    "sg:postcode":"98104",
    "sg:province":"WA",
    "sg:tags":[
        "seafood",
        "market"
    ],
    "wof:name":"Tatoosh Seafood Llc",
    "wof:placetype":"venue"
},
  "geometry": {"coordinates":[-122.334343,47.600215],"type":"Point"}
}