{
  "type": "Feature",
  "properties": {
    "addr:full":"8214 S 192nd St Kent WA 98032",
    "addr:housenumber":"8214",
    "addr:postcode":"98032",
    "addr:street":"S 192Nd St",
    "iso:country":"US",
    "sg:address":"8214 S 192nd St",
    "sg:city":"Kent",
    "sg:classifiers":[
        {
            "category":"Wholesale",
            "subcategory":"Auto Parts",
            "type":"Manufacturing & Wholesale Goods"
        }
    ],
    "sg:phone":"+1 425 251 9388",
    "sg:postcode":"98032",
    "sg:province":"WA",
    "wof:name":"Pacific Rim & Tire",
    "wof:placetype":"venue"
},
  "geometry": {"coordinates":[-122.228131,47.430282],"type":"Point"}
}