{
  "type": "Feature",
  "properties": {
    "addr:full":"719 W Wheeler St Seattle WA 98119",
    "addr:housenumber":"719",
    "addr:postcode":"98119",
    "addr:street":"W Wheeler St",
    "iso:country":"US",
    "sg:address":"719 W Wheeler St",
    "sg:city":"Seattle",
    "sg:classifiers":[
        {
            "category":"Building & Trades",
            "subcategory":"Construction",
            "type":"Services"
        }
    ],
    "sg:phone":"+1 206 285 5957",
    "sg:postcode":"98119",
    "sg:province":"WA",
    "sg:tags":[
        "house"
    ],
    "wof:name":"Gladstone Construction",
    "wof:placetype":"venue"
},
  "geometry": {"coordinates":[-122.36676900000001,47.64063],"type":"Point"}
}