{
  "type": "Feature",
  "properties": {
    "addr:full":"4459 26th Ave SW Seattle WA 98106",
    "addr:housenumber":"4459",
    "addr:postcode":"98106",
    "addr:street":"26Th Ave Sw",
    "iso:country":"US",
    "sg:address":"4459 26th Ave SW",
    "sg:city":"Seattle",
    "sg:classifiers":[
        {
            "category":"Building & Trades",
            "subcategory":"Landscaping Services",
            "type":"Services"
        }
    ],
    "sg:phone":"+1 206 933 8575",
    "sg:postcode":"98106",
    "sg:province":"WA",
    "sg:tags":[
        "landscape"
    ],
    "wof:name":"G & K Landscaping & Yard Maint",
    "wof:placetype":"venue"
},
  "geometry": {"coordinates":[-122.36554700000001,47.563682],"type":"Point"}
}