{
  "type": "Feature",
  "properties": {
    "addr:full":"115 26th Ave Seattle WA 98122",
    "addr:housenumber":"115",
    "addr:postcode":"98122",
    "addr:street":"26Th Ave",
    "iso:country":"US",
    "sg:address":"115 26th Ave",
    "sg:city":"Seattle",
    "sg:classifiers":[
        {
            "category":"Shopping",
            "subcategory":"Music",
            "type":"Retail Goods"
        }
    ],
    "sg:phone":"+1 206 568 2485",
    "sg:postcode":"98122",
    "sg:province":"WA",
    "wof:name":"Tribes Projects",
    "wof:placetype":"venue"
},
  "geometry": {"coordinates":[-122.29899,47.602367],"type":"Point"}
}