{
  "type": "Feature",
  "properties": {
    "addr:full":"7301 Bainbridge Pl SW Seattle WA 98136",
    "addr:housenumber":"7301",
    "addr:postcode":"98136",
    "addr:street":"Bainbridge Pl Sw",
    "iso:country":"US",
    "sg:address":"7301 Bainbridge Pl SW",
    "sg:city":"Seattle",
    "sg:classifiers":[
        {
            "category":"Restaurant",
            "type":"Food & Drink"
        }
    ],
    "sg:phone":"+1 206 935 2229",
    "sg:postcode":"98136",
    "sg:province":"WA",
    "sg:tags":[
        "eating"
    ],
    "wof:name":"Cat's Eye Cafe",
    "wof:placetype":"venue"
},
  "geometry": {"coordinates":[-122.391794,47.537305],"type":"Point"}
}