{
  "type": "Feature",
  "properties": {
    "iso:country":"US",
    "sg:address":"456 Manley Rd",
    "sg:city":"Bellingham",
    "sg:classifiers":[
        {
            "category":"Farming",
            "subcategory":"Livestock Farm",
            "type":"Manufacturing & Wholesale Goods"
        }
    ],
    "sg:phone":"+1 360 671 1735",
    "sg:postcode":"98229",
    "sg:province":"WA",
    "wof:name":"Sweetbrier Farm",
    "wof:placetype":"venue"
},
  "geometry": {"coordinates":[-122.368891,48.663116],"type":"Point"}
}