{
  "type": "Feature",
  "properties": {
    "addr:full":"625 S 4th St Renton WA 98057",
    "addr:housenumber":"625",
    "addr:postcode":"98057",
    "addr:street":"S 4Th St",
    "iso:country":"US",
    "sg:address":"625 S 4th St",
    "sg:city":"Renton",
    "sg:classifiers":[
        {
            "category":"Building & Trades",
            "subcategory":"Locksmith",
            "type":"Services"
        }
    ],
    "sg:phone":"+1 425 873 1914",
    "sg:postcode":"98057",
    "sg:province":"WA",
    "sg:tags":[
        "key"
    ],
    "wof:name":"Locksmith",
    "wof:placetype":"venue"
},
  "geometry": {"coordinates":[-122.209046,47.478087],"type":"Point"}
}