{
  "type": "Feature",
  "properties": {
    "addr:full":"23615 74th Ave W Edmonds WA 98026",
    "addr:housenumber":"23615",
    "addr:postcode":"98026",
    "addr:street":"74Th Ave W",
    "iso:country":"US",
    "sg:address":"23615 74th Ave W",
    "sg:city":"Edmonds",
    "sg:classifiers":[
        {
            "category":"Professional",
            "subcategory":"Business Services",
            "type":"Services"
        }
    ],
    "sg:phone":"+1 425 672 8888",
    "sg:postcode":"98026",
    "sg:province":"WA",
    "wof:name":"Meyerson & Assoc Telemark",
    "wof:placetype":"venue"
},
  "geometry": {"coordinates":[-122.333405,47.784513],"type":"Point"}
}