{
  "type": "Feature",
  "properties": {
    "iso:country":"US",
    "sg:address":"609 S 48th Ave",
    "sg:city":"Yakima",
    "sg:classifiers":[
        {
            "category":"Professional",
            "type":"Services"
        },
        {
            "category":"Health Services",
            "subcategory":"Clinic",
            "type":"Services"
        }
    ],
    "sg:phone":"+1 509 965 3131",
    "sg:postcode":"98908",
    "sg:province":"WA",
    "sg:tags":[
        "colonic",
        "irrigation"
    ],
    "wof:name":"Colon Hyrdro Therapy",
    "wof:placetype":"venue"
},
  "geometry": {"coordinates":[-120.572261,46.591866],"type":"Point"}
}