{
  "type": "Feature",
  "properties": {
    "addr:full":"4605 E Woodglen Rd Mead WA 99021",
    "addr:housenumber":"4605",
    "addr:postcode":"99021",
    "addr:street":"E Woodglen Rd Mead",
    "iso:country":"US",
    "sg:address":"4605 E Woodglen Rd",
    "sg:city":"Mead",
    "sg:classifiers":[
        {
            "category":"Building & Trades",
            "subcategory":"Construction",
            "type":"Services"
        }
    ],
    "sg:phone":"+1 509 951 4231",
    "sg:postcode":"99021",
    "sg:province":"WA",
    "sg:tags":[
        "equipment",
        "material",
        "installation",
        "handling"
    ],
    "wof:name":"Ryco Services Inc",
    "wof:placetype":"venue"
},
  "geometry": {"coordinates":[-117.339641,47.79935],"type":"Point"}
}