{
  "type": "Feature",
  "properties": {
    "addr:full":"4601 Shilshole Ave NW Seattle WA 98107",
    "addr:housenumber":"4601",
    "addr:postcode":"98107",
    "addr:street":"Shilshole Ave Nw",
    "iso:country":"US",
    "sg:address":"4601 Shilshole Ave NW",
    "sg:city":"Seattle",
    "sg:classifiers":[
        {
            "category":"Food & Beverages",
            "subcategory":"Groceries & Convenience Stores",
            "type":"Retail Goods"
        }
    ],
    "sg:phone":"+1 206 789 1930",
    "sg:postcode":"98107",
    "sg:province":"WA",
    "sg:website":"http://www.alaskashipsupply.com",
    "wof:name":"Alaska Ship Supply",
    "wof:placetype":"venue"
},
  "geometry": {"coordinates":[-122.378113,47.66217],"type":"Point"}
}