{
  "type": "Feature",
  "properties": {
    "addr:full":"885 E Broadway St Goldendale WA 98620",
    "addr:housenumber":"885",
    "addr:postcode":"98620",
    "addr:street":"E Broadway St",
    "iso:country":"US",
    "sg:address":"885 E Broadway St",
    "sg:city":"Goldendale",
    "sg:classifiers":[
        {
            "category":"Autos & Motor Vehicles",
            "subcategory":"Automobile Sales",
            "type":"Retail Goods"
        }
    ],
    "sg:phone":"+1 509 773 5644",
    "sg:postcode":"98620",
    "sg:province":"WA",
    "sg:tags":[
        "used"
    ],
    "wof:name":"M & J Autoworks",
    "wof:placetype":"venue"
},
  "geometry": {"coordinates":[-120.80880399999999,45.824024],"type":"Point"}
}