{
  "type": "Feature",
  "properties": {
    "addr:full":"16706 86th Pl SW Vashon WA 98070",
    "addr:housenumber":"16706",
    "addr:postcode":"98070",
    "addr:street":"86Th Pl Sw",
    "iso:country":"US",
    "sg:address":"16706 86th Pl SW",
    "sg:city":"Vashon",
    "sg:classifiers":[
        {
            "category":"Professional",
            "type":"Services"
        }
    ],
    "sg:phone":"+1 206 349 5909",
    "sg:postcode":"98070",
    "sg:province":"WA",
    "wof:name":"Ah Life Inc",
    "wof:placetype":"venue"
},
  "geometry": {"coordinates":[-122.442881,47.456135],"type":"Point"}
}