{
  "type": "Feature",
  "properties": {
    "addr:full":"123 W Cascade Way Spokane WA 99208",
    "addr:housenumber":"123",
    "addr:postcode":"99208",
    "addr:street":"W Cascade Way",
    "iso:country":"US",
    "sg:address":"123 W Cascade Way",
    "sg:city":"Spokane",
    "sg:classifiers":[
        {
            "category":"Banks & Credit Unions",
            "subcategory":"Bank",
            "type":"Services"
        }
    ],
    "sg:phone":"+1 509 465 2160",
    "sg:postcode":"99208",
    "sg:province":"WA",
    "sg:tags":[
        "financing"
    ],
    "wof:name":"Transouth Financial Svc",
    "wof:placetype":"venue"
},
  "geometry": {"coordinates":[-117.412721,47.729417],"type":"Point"}
}