{
  "type": "Feature",
  "properties": {
    "addr:full":"2611 NE 125th St Seattle WA 98125",
    "addr:housenumber":"2611",
    "addr:postcode":"98125",
    "addr:street":"Ne 125Th St",
    "iso:country":"US",
    "sg:address":"2611 NE 125th St",
    "sg:city":"Seattle",
    "sg:classifiers":[
        {
            "category":"Social Services",
            "type":"Services"
        }
    ],
    "sg:phone":"+1 206 729 9233",
    "sg:postcode":"98125",
    "sg:province":"WA",
    "sg:tags":[
        "counselor",
        "marriage",
        "family"
    ],
    "wof:name":"Polly Amkraut",
    "wof:placetype":"venue"
},
  "geometry": {"coordinates":[-122.29917399999999,47.719225],"type":"Point"}
}