{
  "type": "Feature",
  "properties": {
    "addr:full":"1200 Cornwall Ave Bellingham WA 98225",
    "addr:housenumber":"1200",
    "addr:postcode":"98225",
    "addr:street":"Cornwall Ave",
    "iso:country":"US",
    "sg:address":"1200 Cornwall Ave",
    "sg:city":"Bellingham",
    "sg:classifiers":[
        {
            "category":"Restaurant",
            "type":"Food & Drink"
        }
    ],
    "sg:phone":"+1 360 752 9100",
    "sg:postcode":"98225",
    "sg:province":"WA",
    "wof:name":"Shrimp Shack",
    "wof:placetype":"venue"
},
  "geometry": {"coordinates":[-122.479944,48.748848],"type":"Point"}
}