{
  "type": "Feature",
  "properties": {
    "addr:full":"6710 80th St SW Lakewood WA 98499",
    "addr:housenumber":"6710",
    "addr:postcode":"98499",
    "addr:street":"80Th St Sw",
    "iso:country":"US",
    "sg:address":"6710 80th St SW",
    "sg:city":"Lakewood",
    "sg:classifiers":[
        {
            "category":"Utilities",
            "subcategory":"Refuse",
            "type":"Services"
        }
    ],
    "sg:phone":"+1 206 915 8043",
    "sg:postcode":"98499",
    "sg:province":"WA",
    "sg:tags":[
        "system"
    ],
    "wof:name":"Waste Management",
    "wof:placetype":"venue"
},
  "geometry": {"coordinates":[-122.52596699999999,47.184791],"type":"Point"}
}