{
  "type": "Feature",
  "properties": {
    "addr:full":"7501 49th Dr NE Marysville WA 98270",
    "addr:housenumber":"7501",
    "addr:postcode":"98270",
    "addr:street":"49Th Dr Ne",
    "iso:country":"US",
    "sg:address":"7501 49th Dr NE",
    "sg:city":"Marysville",
    "sg:classifiers":[
        {
            "category":"Home & Garden",
            "subcategory":"Building Materials",
            "type":"Retail Goods"
        }
    ],
    "sg:phone":"+1 360 651 9553",
    "sg:postcode":"98270",
    "sg:province":"WA",
    "sg:tags":[
        "downspouts",
        "gutter"
    ],
    "wof:name":"Marks Gutters",
    "wof:placetype":"venue"
},
  "geometry": {"coordinates":[-122.164146,48.064152],"type":"Point"}
}