{
  "type": "Feature",
  "properties": {
    "iso:country":"US",
    "sg:address":"17655 122nd Pl SE",
    "sg:city":"Renton",
    "sg:classifiers":[
        {
            "category":"Organizations",
            "subcategory":"Membership Organization",
            "type":"Services"
        }
    ],
    "sg:phone":"+1 206 794 4663",
    "sg:postcode":"98058",
    "sg:province":"WA",
    "wof:name":"Heartlinq",
    "wof:placetype":"venue"
},
  "geometry": {"coordinates":[-122.17750100000001,47.444684],"type":"Point"}
}