{
  "type": "Feature",
  "properties": {
    "addr:full":"24202 104th Ave SE Kent WA 98030",
    "addr:housenumber":"24202",
    "addr:postcode":"98030",
    "addr:street":"104Th Ave Se",
    "iso:country":"US",
    "sg:address":"24202 104th Ave SE",
    "sg:city":"Kent",
    "sg:classifiers":[
        {
            "category":"Personal",
            "subcategory":"Beauty Salon",
            "type":"Services"
        }
    ],
    "sg:phone":"+1 206 696 4700",
    "sg:postcode":"98030",
    "sg:province":"WA",
    "sg:tags":[
        "shop"
    ],
    "wof:name":"Lisa Rozzini",
    "wof:placetype":"venue"
},
  "geometry": {"coordinates":[-122.202213,47.384377],"type":"Point"}
}