{
  "type": "Feature",
  "properties": {
    "addr:full":"7700 Earling St NE Olympia WA 98506",
    "addr:postcode":"7700;98506",
    "addr:street":"Earling St Ne",
    "iso:country":"US",
    "sg:address":"7700 Earling St NE",
    "sg:city":"Olympia",
    "sg:classifiers":[
        {
            "category":"Shopping",
            "subcategory":"Computers & Home Electronics",
            "type":"Retail Goods"
        }
    ],
    "sg:phone":"+1 360 943 9092",
    "sg:postcode":"98506",
    "sg:province":"WA",
    "wof:name":"Software For Artists",
    "wof:placetype":"venue"
},
  "geometry": {"coordinates":[-122.894272,47.142941],"type":"Point"}
}