{
  "type": "Feature",
  "properties": {
    "addr:full":"8009 Lake City Way NE Seattle WA 98115",
    "addr:housenumber":"8009",
    "addr:postcode":"98115",
    "addr:street":"Lake City Way Ne",
    "iso:country":"US",
    "sg:address":"8009 Lake City Way NE",
    "sg:city":"Seattle",
    "sg:classifiers":[
        {
            "category":"Building & Trades",
            "subcategory":"Locksmith",
            "type":"Services"
        }
    ],
    "sg:phone":"+1 206 701 8635",
    "sg:postcode":"98115",
    "sg:province":"WA",
    "sg:tags":[
        "key"
    ],
    "wof:name":"Locksmith Emergency",
    "wof:placetype":"venue"
},
  "geometry": {"coordinates":[-122.313123,47.687022],"type":"Point"}
}