{
  "type": "Feature",
  "properties": {
    "addr:full":"1302 Puyallup St Sumner WA 98390",
    "addr:housenumber":"1302",
    "addr:postcode":"98390",
    "addr:street":"Puyallup St",
    "iso:country":"US",
    "sg:address":"1302 Puyallup St",
    "sg:city":"Sumner",
    "sg:classifiers":[
        {
            "category":"Real Estate",
            "subcategory":"Real Estate Agent",
            "type":"Services"
        },
        {
            "category":"Professional",
            "subcategory":"Management & Consulting",
            "type":"Services"
        }
    ],
    "sg:phone":"+1 253 863 6200",
    "sg:postcode":"98390",
    "sg:province":"WA",
    "sg:tags":[
        "open",
        "investment",
        "subdivider"
    ],
    "sg:website":"www.newhomesatlakeland.com",
    "wof:name":"Investco Financial Corporation",
    "wof:placetype":"venue"
},
  "geometry": {"coordinates":[-122.240914,47.212881],"type":"Point"}
}