{
  "type": "Feature",
  "properties": {
    "addr:full":"10412 NE 19th Ave Vancouver WA 98686",
    "addr:housenumber":"10412",
    "addr:postcode":"98686",
    "addr:street":"Ne 19Th Ave",
    "iso:country":"US",
    "sg:address":"10412 NE 19th Ave",
    "sg:city":"Vancouver",
    "sg:classifiers":[
        {
            "category":"Wholesale",
            "subcategory":"Groceries",
            "type":"Manufacturing & Wholesale Goods"
        }
    ],
    "sg:phone":"+1 360 573 0616",
    "sg:postcode":"98686",
    "sg:province":"WA",
    "sg:tags":[
        "confectionery"
    ],
    "wof:name":"Woodys Buy More",
    "wof:placetype":"venue"
},
  "geometry": {"coordinates":[-122.65195900000001,45.698925],"type":"Point"}
}