{
  "type": "Feature",
  "properties": {
    "addr:full":"514 S Washington St Port Angeles WA 98362",
    "addr:housenumber":"514",
    "addr:postcode":"98362",
    "addr:street":"S Washington St",
    "iso:country":"US",
    "sg:address":"514 S Washington St",
    "sg:city":"Port Angeles",
    "sg:classifiers":[
        {
            "category":"Professional",
            "subcategory":"Computer Services",
            "type":"Services"
        }
    ],
    "sg:phone":"+1 360 452 9996",
    "sg:postcode":"98362",
    "sg:province":"WA",
    "sg:tags":[
        "related"
    ],
    "wof:name":"Sanders Network Consultants",
    "wof:placetype":"venue"
},
  "geometry": {"coordinates":[-123.42066,48.108432],"type":"Point"}
}