{
  "type": "Feature",
  "properties": {
    "addr:full":"14215 Pacific Ave S Tacoma WA 98444",
    "addr:housenumber":"14215",
    "addr:postcode":"98444",
    "addr:street":"Pacific Ave S",
    "iso:country":"US",
    "sg:address":"14215 Pacific Ave S",
    "sg:city":"Tacoma",
    "sg:classifiers":[
        {
            "category":"Social Services",
            "subcategory":"Child Care",
            "type":"Services"
        }
    ],
    "sg:phone":"+1 253 536 4744",
    "sg:postcode":"98444",
    "sg:province":"WA",
    "wof:name":"Kreative Kidz Child Care",
    "wof:placetype":"venue"
},
  "geometry": {"coordinates":[-122.434697,47.127683],"type":"Point"}
}