{
  "type": "Feature",
  "properties": {
    "addr:full":"10 N Nancy Ave Hoodsport WA 98548",
    "addr:housenumber":"10",
    "addr:postcode":"98548",
    "addr:street":"N Nancy Ave",
    "iso:country":"US",
    "sg:address":"10 N Nancy Ave",
    "sg:city":"Hoodsport",
    "sg:classifiers":[
        {
            "category":"Professional",
            "subcategory":"Management & Consulting",
            "type":"Services"
        }
    ],
    "sg:phone":"+1 360 877 5676",
    "sg:postcode":"98548",
    "sg:province":"WA",
    "wof:name":"Synergy Financial Management C",
    "wof:placetype":"venue"
},
  "geometry": {"coordinates":[-123.125925,47.430433],"type":"Point"}
}