{
  "type": "Feature",
  "properties": {
    "addr:full":"743 N 72nd St Seattle WA 98103",
    "addr:housenumber":"743",
    "addr:postcode":"98103",
    "addr:street":"N 72Nd St",
    "iso:country":"US",
    "sg:address":"743 N 72nd St",
    "sg:city":"Seattle",
    "sg:classifiers":[
        {
            "category":"Building & Trades",
            "subcategory":"Construction",
            "type":"Services"
        }
    ],
    "sg:phone":"+1 206 789 5612",
    "sg:postcode":"98103",
    "sg:province":"WA",
    "sg:tags":[
        "contractor"
    ],
    "wof:name":"Gray Wolf Inc",
    "wof:placetype":"venue"
},
  "geometry": {"coordinates":[-122.34899900000001,47.681198],"type":"Point"}
}