{
  "type": "Feature",
  "properties": {
    "addr:full":"3012 Gs Center Rd Wenatchee WA 98801",
    "addr:postcode":"3012;98801",
    "addr:street":"Center Rd",
    "iso:country":"US",
    "sg:address":"3012 Gs Center Rd",
    "sg:city":"Wenatchee",
    "sg:classifiers":[
        {
            "category":"Wholesale",
            "subcategory":"Machinery & Supplies",
            "type":"Manufacturing & Wholesale Goods"
        }
    ],
    "sg:phone":"+1 509 547 1661",
    "sg:postcode":"98801",
    "sg:province":"WA",
    "sg:tags":[
        "equipment",
        "industrial",
        "bearing"
    ],
    "wof:name":"Washington Belt & Drv Systems",
    "wof:placetype":"venue"
},
  "geometry": {"coordinates":[-120.33130800000001,47.47192],"type":"Point"}
}