{
  "type": "Feature",
  "properties": {
    "addr:full":"14422 E Meridian Ave Puyallup WA 98375",
    "addr:housenumber":"14422",
    "addr:postcode":"98375",
    "addr:street":"E Meridian Ave",
    "iso:country":"US",
    "sg:address":"14422 E Meridian Ave",
    "sg:city":"Puyallup",
    "sg:classifiers":[
        {
            "category":"Arts & Performance",
            "subcategory":"Theater",
            "type":"Entertainment"
        }
    ],
    "sg:phone":"+1 253 848 3411",
    "sg:postcode":"98375",
    "sg:province":"WA",
    "wof:name":"Amphitheater",
    "wof:placetype":"venue"
},
  "geometry": {"coordinates":[-122.29318600000001,47.124123],"type":"Point"}
}