{
  "type": "Feature",
  "properties": {
    "addr:full":"2930 S Manito Blvd Spokane WA 99203",
    "addr:housenumber":"2930",
    "addr:postcode":"99203",
    "addr:street":"S Manito Blvd",
    "iso:country":"US",
    "sg:address":"2930 S Manito Blvd",
    "sg:city":"Spokane",
    "sg:classifiers":[
        {
            "category":"Building & Trades",
            "subcategory":"Plumbing",
            "type":"Services"
        }
    ],
    "sg:phone":"+1 509 624 0686",
    "sg:postcode":"99203",
    "sg:province":"WA",
    "sg:tags":[
        "plumbing",
        "contractor"
    ],
    "wof:name":"Roe's Plumbing",
    "wof:placetype":"venue"
},
  "geometry": {"coordinates":[-117.40782299999999,47.626632],"type":"Point"}
}