{
  "type": "Feature",
  "properties": {
    "addr:full":"12737 SE 298th Pl Auburn WA 98092",
    "addr:postcode":"12737;98092",
    "addr:street":"Se 298Th Pl",
    "iso:country":"US",
    "sg:address":"12737 SE 298th Pl",
    "sg:city":"Auburn",
    "sg:classifiers":[
        {
            "category":"Professional",
            "subcategory":"Management & Consulting",
            "type":"Services"
        }
    ],
    "sg:phone":"+1 253 833 5229",
    "sg:postcode":"98092",
    "sg:province":"WA",
    "sg:tags":[
        "business"
    ],
    "wof:name":"Tdk Consulting Inc",
    "wof:placetype":"venue"
},
  "geometry": {"coordinates":[-122.171019,47.334673],"type":"Point"}
}