{
  "type": "Feature",
  "properties": {
    "addr:full":"6849 50th Ave NE Seattle WA 98115",
    "addr:housenumber":"6849",
    "addr:postcode":"98115",
    "addr:street":"50Th Ave Ne",
    "iso:country":"US",
    "sg:address":"6849 50th Ave NE",
    "sg:city":"Seattle",
    "sg:classifiers":[
        {
            "category":"Building & Trades",
            "subcategory":"Landscaping Services",
            "type":"Services"
        }
    ],
    "sg:phone":"+1 206 524 2747",
    "sg:postcode":"98115",
    "sg:province":"WA",
    "sg:tags":[
        "landscape"
    ],
    "wof:name":"Martha Keck Design Inc",
    "wof:placetype":"venue"
},
  "geometry": {"coordinates":[-122.27437,47.678957],"type":"Point"}
}