{
  "type": "Feature",
  "properties": {
    "addr:full":"2610 SW Barton St Seattle WA 98126",
    "addr:housenumber":"2610",
    "addr:postcode":"98126",
    "addr:street":"Sw Barton St",
    "iso:country":"US",
    "sg:address":"2610 SW Barton St",
    "sg:city":"Seattle",
    "sg:classifiers":[
        {
            "category":"Building & Trades",
            "subcategory":"Locksmith",
            "type":"Services"
        }
    ],
    "sg:phone":"+1 206 238 0296",
    "sg:postcode":"98126",
    "sg:province":"WA",
    "sg:tags":[
        "key"
    ],
    "wof:name":"A&j Locksmith 24 7",
    "wof:placetype":"venue"
},
  "geometry": {"coordinates":[-122.365981,47.521177],"type":"Point"}
}