{
  "type": "Feature",
  "properties": {
    "addr:full":"2515 E Cherry Seattle WA 98122",
    "addr:housenumber":"2515",
    "addr:postcode":"98122",
    "addr:street":"E Cherry",
    "iso:country":"US",
    "sg:address":"2515 E Cherry",
    "sg:city":"Seattle",
    "sg:classifiers":[
        {
            "category":"Restaurant",
            "type":"Food & Drink"
        }
    ],
    "sg:phone":"+1 206 250 3525",
    "sg:postcode":"98122",
    "sg:province":"WA",
    "sg:tags":[
        "barbeque"
    ],
    "wof:name":"The Barbecue Pit",
    "wof:placetype":"venue"
},
  "geometry": {"coordinates":[-122.299531,47.607978],"type":"Point"}
}