{
  "type": "Feature",
  "properties": {
    "iso:country":"US",
    "sg:address":"12931 SE 26th Pl",
    "sg:city":"Bellevue",
    "sg:classifiers":[
        {
            "category":"Professional",
            "type":"Services"
        }
    ],
    "sg:phone":"+1 425 746 4379",
    "sg:postcode":"98005",
    "sg:province":"WA",
    "wof:name":"Bijoux World Inc",
    "wof:placetype":"venue"
},
  "geometry": {"coordinates":[-122.166787,47.587174],"type":"Point"}
}