{
  "type": "Feature",
  "properties": {
    "addr:full":"201 E Fairhaven Ave Burlington WA 98233",
    "addr:housenumber":"201",
    "addr:postcode":"98233",
    "addr:street":"E Fairhaven Ave",
    "iso:country":"US",
    "sg:address":"201 E Fairhaven Ave",
    "sg:city":"Burlington",
    "sg:classifiers":[
        {
            "category":"Banks & Credit Unions",
            "subcategory":"Bank",
            "type":"Services"
        }
    ],
    "sg:phone":"+1 360 755 9045",
    "sg:postcode":"98233",
    "sg:province":"WA",
    "wof:name":"Keybank",
    "wof:placetype":"venue"
},
  "geometry": {"coordinates":[-122.333,48.475601],"type":"Point"}
}