{
  "type": "Feature",
  "properties": {
    "addr:full":"23122 52nd Pl S Kent WA 98032",
    "addr:housenumber":"23122",
    "addr:postcode":"98032",
    "addr:street":"52Nd Pl S",
    "iso:country":"US",
    "sg:address":"23122 52nd Pl S",
    "sg:city":"Kent",
    "sg:classifiers":[
        {
            "category":"Professional",
            "subcategory":"Business Services",
            "type":"Services"
        }
    ],
    "sg:phone":"+1 253 520 3130",
    "sg:postcode":"98032",
    "sg:province":"WA",
    "wof:name":"Indo American Business Pages",
    "wof:placetype":"venue"
},
  "geometry": {"coordinates":[-122.26966299999999,47.39382],"type":"Point"}
}