{
  "type": "Feature",
  "properties": {
    "addr:full":"206 5th Ave S Seattle WA 98104",
    "addr:housenumber":"206",
    "addr:postcode":"98104",
    "addr:street":"5Th Ave S",
    "iso:country":"US",
    "sg:address":"206 5th Ave S",
    "sg:city":"Seattle",
    "sg:classifiers":[
        {
            "category":"Manufacturing",
            "subcategory":"Tools & Machinery",
            "type":"Manufacturing & Wholesale Goods"
        }
    ],
    "sg:phone":"+1 206 583 2333",
    "sg:postcode":"98104",
    "sg:province":"WA",
    "sg:tags":[
        "machine",
        "supplier"
    ],
    "wof:name":"North Western Machinery",
    "wof:placetype":"venue"
},
  "geometry": {"coordinates":[-122.32759,47.600083],"type":"Point"}
}