{
  "type": "Feature",
  "properties": {
    "iso:country":"US",
    "sg:address":"2321 173rd Ave NE",
    "sg:city":"Redmond",
    "sg:classifiers":[
        {
            "category":"Organizations",
            "subcategory":"Religious Organization",
            "type":"Services"
        }
    ],
    "sg:phone":"+1 425 644 1267",
    "sg:postcode":"98052",
    "sg:province":"WA",
    "wof:name":"Grace Church",
    "wof:placetype":"venue"
},
  "geometry": {"coordinates":[-122.10985700000001,47.631229],"type":"Point"}
}