{
  "type": "Feature",
  "properties": {
    "addr:full":"2829 Lynn St Bellingham WA 98225",
    "addr:housenumber":"2829",
    "addr:postcode":"98225",
    "addr:street":"Lynn St",
    "iso:country":"US",
    "sg:address":"2829 Lynn St",
    "sg:city":"Bellingham",
    "sg:classifiers":[
        {
            "category":"Social Services",
            "subcategory":"Child Care",
            "type":"Services"
        }
    ],
    "sg:phone":"+1 360 671 7921",
    "sg:postcode":"98225",
    "sg:province":"WA",
    "sg:tags":[
        "day"
    ],
    "wof:name":"Happy Campers Daycare",
    "wof:placetype":"venue"
},
  "geometry": {"coordinates":[-122.496968,48.766599],"type":"Point"}
}