{
  "type": "Feature",
  "properties": {
    "addr:full":"17002 Aurora Ave N Shoreline WA 98133",
    "addr:housenumber":"17002",
    "addr:postcode":"98133",
    "addr:street":"Aurora Ave N",
    "iso:country":"US",
    "sg:address":"17002 Aurora Ave N",
    "sg:city":"Shoreline",
    "sg:classifiers":[
        {
            "category":"Food & Beverages",
            "subcategory":"Groceries & Convenience Stores",
            "type":"Retail Goods"
        }
    ],
    "sg:phone":"+1 206 542 2879",
    "sg:postcode":"98133",
    "sg:province":"WA",
    "sg:tags":[
        "grocer"
    ],
    "wof:name":"Baro Grocery & Deli",
    "wof:placetype":"venue"
},
  "geometry": {"coordinates":[-122.34555899999999,47.754316],"type":"Point"}
}