{
  "type": "Feature",
  "properties": {
    "addr:full":"2408 NE 9th St Renton WA 98056",
    "addr:housenumber":"2408",
    "addr:postcode":"98056",
    "addr:street":"Ne 9Th St",
    "iso:country":"US",
    "sg:address":"2408 NE 9th St",
    "sg:city":"Renton",
    "sg:classifiers":[
        {
            "category":"Professional",
            "type":"Services"
        }
    ],
    "sg:phone":"+1 425 255 6290",
    "sg:postcode":"98056",
    "sg:province":"WA",
    "wof:name":"Merton Conn",
    "wof:placetype":"venue"
},
  "geometry": {"coordinates":[-122.186091,47.497356],"type":"Point"}
}