{
  "type": "Feature",
  "properties": {
    "addr:full":"13221 42nd Ave NE Seattle WA 98125",
    "addr:housenumber":"13221",
    "addr:postcode":"98125",
    "addr:street":"42Nd Ave Ne",
    "iso:country":"US",
    "sg:address":"13221 42nd Ave NE",
    "sg:city":"Seattle",
    "sg:classifiers":[
        {
            "category":"Building & Trades",
            "subcategory":"Locksmith",
            "type":"Services"
        }
    ],
    "sg:phone":"+1 206 494 0171",
    "sg:postcode":"98125",
    "sg:province":"WA",
    "sg:tags":[
        "key"
    ],
    "wof:name":"1 7 A 24 A Locksmith",
    "wof:placetype":"venue"
},
  "geometry": {"coordinates":[-122.282652,47.725664],"type":"Point"}
}