{
  "type": "Feature",
  "properties": {
    "addr:full":"3323 Northwest Ave Bellingham WA 98225",
    "addr:housenumber":"3323",
    "addr:postcode":"98225",
    "addr:street":"Northwest Ave",
    "iso:country":"US",
    "sg:address":"3323 Northwest Ave",
    "sg:city":"Bellingham",
    "sg:classifiers":[
        {
            "category":"Fast Food",
            "type":"Food & Drink"
        },
        {
            "category":"Restaurant",
            "type":"Food & Drink"
        }
    ],
    "sg:phone":"+1 360 733 8830",
    "sg:postcode":"98225",
    "sg:province":"WA",
    "sg:tags":[
        "hamburger",
        "hot",
        "dog",
        "american",
        "take",
        "chicken"
    ],
    "wof:name":"Mcdonald's",
    "wof:placetype":"venue"
},
  "geometry": {"coordinates":[-122.497998,48.776695],"type":"Point"}
}