{
  "type": "Feature",
  "properties": {
    "iso:country":"US",
    "sg:address":"2840 E Melrose St",
    "sg:city":"Walla Walla",
    "sg:classifiers":[
        {
            "category":"Manufacturing",
            "subcategory":"Metals",
            "type":"Manufacturing & Wholesale Goods"
        }
    ],
    "sg:phone":"+1 509 526 7171",
    "sg:postcode":"99362",
    "sg:province":"WA",
    "sg:tags":[
        "coating"
    ],
    "wof:name":"Walla Walla Super Liner",
    "wof:placetype":"venue"
},
  "geometry": {"coordinates":[-118.286514,46.080432],"type":"Point"}
}