{
  "type": "Feature",
  "properties": {
    "iso:country":"US",
    "sg:address":"303 Jones Rd",
    "sg:city":"Sedro Woolley",
    "sg:classifiers":[
        {
            "category":"Building & Trades",
            "subcategory":"Cleaning & Sanitation",
            "type":"Services"
        }
    ],
    "sg:phone":"+1 360 675 8343",
    "sg:postcode":"98284",
    "sg:province":"WA",
    "sg:tags":[
        "downspout",
        "gutter"
    ],
    "wof:name":"Mt Vernon-Oak Harbor Gutter",
    "wof:placetype":"venue"
},
  "geometry": {"coordinates":[-122.24163,48.514574],"type":"Point"}
}