{
  "type": "Feature",
  "properties": {
    "addr:full":"238 171st Pl NE Bellevue WA 98008",
    "addr:housenumber":"238",
    "addr:postcode":"98008",
    "addr:street":"171St Pl Ne",
    "iso:country":"US",
    "sg:address":"238 171st Pl NE",
    "sg:city":"Bellevue",
    "sg:classifiers":[
        {
            "category":"Shopping",
            "subcategory":"Computers & Home Electronics",
            "type":"Retail Goods"
        }
    ],
    "sg:phone":"+1 425 746 0236",
    "sg:postcode":"98008",
    "sg:province":"WA",
    "wof:name":"Media A-Plus",
    "wof:placetype":"venue"
},
  "geometry": {"coordinates":[-122.11300900000001,47.612096],"type":"Point"}
}