{
  "type": "Feature",
  "properties": {
    "addr:full":"1039 Byerly Rd Touchet WA 99360",
    "addr:housenumber":"1039",
    "addr:postcode":"99360",
    "addr:street":"Byerly Rd",
    "iso:country":"US",
    "sg:address":"1039 Byerly Rd",
    "sg:city":"Touchet",
    "sg:phone":"+1 509 394 2616",
    "sg:postcode":"99360",
    "sg:province":"WA",
    "sg:tags":[
        "farm",
        "field",
        "wheat",
        "crop"
    ],
    "wof:name":"Byerley Farms Inc",
    "wof:placetype":"venue"
},
  "geometry": {"coordinates":[-118.761977,46.03619],"type":"Point"}
}