{
  "type": "Feature",
  "properties": {
    "addr:full":"16330 Cleveland St Redmond WA 98052",
    "addr:housenumber":"16330",
    "addr:postcode":"98052",
    "addr:street":"Cleveland St",
    "iso:country":"US",
    "sg:address":"16330 Cleveland St",
    "sg:city":"Redmond",
    "sg:classifiers":[
        {
            "category":"Restaurant",
            "type":"Food & Drink"
        }
    ],
    "sg:phone":"+1 425 497 9673",
    "sg:postcode":"98052",
    "sg:province":"WA",
    "sg:tags":[
        "eating"
    ],
    "wof:name":"Fresh Four Inc",
    "wof:placetype":"venue"
},
  "geometry": {"coordinates":[-122.12268899999999,47.673424],"type":"Point"}
}