{
  "type": "Feature",
  "properties": {
    "addr:full":"827 State Rte 4 Naselle WA 98638",
    "addr:housenumber":"827",
    "addr:postcode":"98638",
    "addr:street":"State Rte 4 Naselle",
    "iso:country":"US",
    "sg:address":"827 State Rte 4",
    "sg:city":"Naselle",
    "sg:classifiers":[
        {
            "category":"Restaurant",
            "type":"Food & Drink"
        }
    ],
    "sg:phone":"+1 360 484 9777",
    "sg:postcode":"98638",
    "sg:province":"WA",
    "wof:name":"Oh Carol's Restaurant",
    "wof:placetype":"venue"
},
  "geometry": {"coordinates":[-123.79298900000001,46.376579],"type":"Point"}
}