{
  "type": "Feature",
  "properties": {
    "addr:full":"7916 N Graycoat Ct Spokane WA 99208",
    "addr:housenumber":"7916",
    "addr:postcode":"99208",
    "addr:street":"N Graycoat Ct",
    "iso:country":"US",
    "sg:address":"7916 N Graycoat Ct",
    "sg:city":"Spokane",
    "sg:classifiers":[
        {
            "category":"Food & Beverages",
            "subcategory":"Specialty",
            "type":"Retail Goods"
        }
    ],
    "sg:phone":"+1 509 468 4315",
    "sg:postcode":"99208",
    "sg:province":"WA",
    "wof:name":"Gingers Health Products",
    "wof:placetype":"venue"
},
  "geometry": {"coordinates":[-117.399305,47.729609],"type":"Point"}
}