{
  "type": "Feature",
  "properties": {
    "addr:full":"2316 Olympic Hwy N Shelton WA 98584",
    "addr:housenumber":"2316",
    "addr:postcode":"98584",
    "addr:street":"Olympic Hwy N",
    "iso:country":"US",
    "sg:address":"2316 Olympic Hwy N",
    "sg:city":"Shelton",
    "sg:classifiers":[
        {
            "category":"Retail",
            "subcategory":"Auto Repair",
            "type":"Services"
        }
    ],
    "sg:phone":"+1 360 427 3581",
    "sg:postcode":"98584",
    "sg:province":"WA",
    "sg:tags":[
        "exhaust"
    ],
    "wof:name":"R JS Mufflers & More",
    "wof:placetype":"venue"
},
  "geometry": {"coordinates":[-123.12290400000001,47.225323],"type":"Point"}
}