{
  "type": "Feature",
  "properties": {
    "addr:full":"14842 Densmore Ave N Shoreline WA 98133",
    "addr:housenumber":"14842",
    "addr:postcode":"98133",
    "addr:street":"Densmore Ave N",
    "iso:country":"US",
    "sg:address":"14842 Densmore Ave N",
    "sg:city":"Shoreline",
    "sg:classifiers":[
        {
            "category":"Manufacturing",
            "subcategory":"Tools & Machinery",
            "type":"Manufacturing & Wholesale Goods"
        },
        {
            "category":"Retail",
            "subcategory":"Repair Shop",
            "type":"Services"
        }
    ],
    "sg:phone":"+1 206 365 5563",
    "sg:postcode":"98133",
    "sg:province":"WA",
    "sg:tags":[
        "industrial",
        "electrical",
        "electric",
        "generator",
        "contractors-commercial"
    ],
    "sg:website":"http://www.uptime.org",
    "wof:name":"Expert Auto Electric",
    "wof:placetype":"venue"
},
  "geometry": {"coordinates":[-122.338358,47.736847],"type":"Point"}
}