{
  "type": "Feature",
  "properties": {
    "addr:full":"7530 Roosevelt Way NE Seattle WA 98115",
    "addr:housenumber":"7530",
    "addr:postcode":"98115",
    "addr:street":"Roosevelt Way Ne",
    "iso:country":"US",
    "sg:address":"7530 Roosevelt Way NE",
    "sg:city":"Seattle",
    "sg:classifiers":[
        {
            "category":"Professional",
            "subcategory":"Engineering",
            "type":"Services"
        }
    ],
    "sg:phone":"+1 206 523 9796",
    "sg:postcode":"98115",
    "sg:province":"WA",
    "sg:tags":[
        "civil",
        "consulting",
        "engineer"
    ],
    "sg:website":"http://www.pavementconsultants.com",
    "wof:name":"Pavement Consultants Inc.",
    "wof:placetype":"venue"
},
  "geometry": {"coordinates":[-122.31753500000001,47.683984],"type":"Point"}
}