{
  "type": "Feature",
  "properties": {
    "addr:full":"24009 NE 26th Ave Ridgefield WA 98642",
    "addr:housenumber":"24009",
    "addr:postcode":"98642",
    "addr:street":"Ne 26Th Ave",
    "iso:country":"US",
    "sg:address":"24009 NE 26th Ave",
    "sg:city":"Ridgefield",
    "sg:classifiers":[
        {
            "category":"Building & Trades",
            "subcategory":"Construction",
            "type":"Services"
        }
    ],
    "sg:phone":"+1 360 887 3296",
    "sg:postcode":"98642",
    "sg:province":"WA",
    "sg:tags":[
        "house"
    ],
    "wof:name":"Allais Remodel",
    "wof:placetype":"venue"
},
  "geometry": {"coordinates":[-122.644702,45.795661],"type":"Point"}
}