{
  "type": "Feature",
  "properties": {
    "addr:full":"444 11th St Clarkston WA 99403",
    "addr:housenumber":"444",
    "addr:postcode":"99403",
    "addr:street":"11Th St",
    "iso:country":"US",
    "sg:address":"444 11th St",
    "sg:city":"Clarkston",
    "sg:classifiers":[
        {
            "category":"Retail",
            "subcategory":"Auto Repair",
            "type":"Services"
        }
    ],
    "sg:phone":"+1 509 758 3211",
    "sg:postcode":"99403",
    "sg:province":"WA",
    "sg:tags":[
        "general"
    ],
    "wof:name":"Bridge Street Auto Center",
    "wof:placetype":"venue"
},
  "geometry": {"coordinates":[-117.05217500000001,46.420922],"type":"Point"}
}