{
  "type": "Feature",
  "properties": {
    "addr:full":"11915 Lakeside Pl NE Seattle WA 98125",
    "addr:housenumber":"11915",
    "addr:postcode":"98125",
    "addr:street":"Lakeside Pl Ne",
    "iso:country":"US",
    "sg:address":"11915 Lakeside Pl NE",
    "sg:city":"Seattle",
    "sg:classifiers":[
        {
            "category":"Professional",
            "subcategory":"Business Services",
            "type":"Services"
        }
    ],
    "sg:phone":"+1 206 362 2463",
    "sg:postcode":"98125",
    "sg:province":"WA",
    "wof:name":"Seabloom Enterprises Inc",
    "wof:placetype":"venue"
},
  "geometry": {"coordinates":[-122.279467,47.716877],"type":"Point"}
}