{
  "type": "Feature",
  "properties": {
    "addr:full":"1109 S Homestead Ct Veradale WA 99037",
    "addr:housenumber":"1109",
    "addr:postcode":"99037",
    "addr:street":"S Homestead Ct",
    "iso:country":"US",
    "sg:address":"1109 S Homestead Ct",
    "sg:city":"Veradale",
    "sg:classifiers":[
        {
            "category":"Manufacturing",
            "subcategory":"Apparel",
            "type":"Manufacturing & Wholesale Goods"
        }
    ],
    "sg:phone":"+1 509 891 5922",
    "sg:postcode":"99037",
    "sg:province":"WA",
    "sg:tags":[
        "baby",
        "blanket",
        "mfg"
    ],
    "wof:name":"Chilly Pepper Studios",
    "wof:placetype":"venue"
},
  "geometry": {"coordinates":[-117.190819,47.645817],"type":"Point"}
}