{
  "type": "Feature",
  "properties": {
    "addr:full":"528 E 9th St Port Angeles WA 98362",
    "addr:housenumber":"528",
    "addr:postcode":"98362",
    "addr:street":"E 9Th St",
    "iso:country":"US",
    "sg:address":"528 E 9th St",
    "sg:city":"Port Angeles",
    "sg:classifiers":[
        {
            "category":"Freight",
            "type":"Transportation"
        }
    ],
    "sg:phone":"+1 360 461 1720",
    "sg:postcode":"98362",
    "sg:province":"WA",
    "sg:tags":[
        "operator",
        "local",
        "trucking"
    ],
    "wof:name":"Griels Trucking",
    "wof:placetype":"venue"
},
  "geometry": {"coordinates":[-123.432078,48.108809],"type":"Point"}
}