{
  "type": "Feature",
  "properties": {
    "addr:full":"10106 SW Bank Rd Vashon WA 98070",
    "addr:housenumber":"10106",
    "addr:postcode":"98070",
    "addr:street":"Sw Bank Rd",
    "iso:country":"US",
    "sg:address":"10106 SW Bank Rd",
    "sg:city":"Vashon",
    "sg:classifiers":[
        {
            "category":"Wholesale",
            "subcategory":"Non-durable Goods",
            "type":"Manufacturing & Wholesale Goods"
        }
    ],
    "sg:phone":"+1 206 463 4604",
    "sg:postcode":"98070",
    "sg:province":"WA",
    "wof:name":"Naomi Shipley Imports",
    "wof:placetype":"venue"
},
  "geometry": {"coordinates":[-122.46307,47.447468],"type":"Point"}
}