{
  "type": "Feature",
  "properties": {
    "iso:country":"US",
    "sg:address":"19711 1st Ave S",
    "sg:city":"Seattle",
    "sg:classifiers":[
        {
            "category":"Health Services",
            "subcategory":"Doctor",
            "type":"Services"
        }
    ],
    "sg:phone":"+1 206 824 2183",
    "sg:postcode":"98148",
    "sg:province":"WA",
    "sg:tags":[
        "medical"
    ],
    "wof:name":"Max M Lee MD",
    "wof:placetype":"venue"
},
  "geometry": {"coordinates":[-122.33547,47.425659],"type":"Point"}
}