{
  "type": "Feature",
  "properties": {
    "addr:full":"201 Birch Ave Grandview WA 98930",
    "addr:housenumber":"201",
    "addr:postcode":"98930",
    "addr:street":"Birch Ave",
    "iso:country":"US",
    "sg:address":"201 Birch Ave",
    "sg:city":"Grandview",
    "sg:classifiers":[
        {
            "category":"Organizations",
            "subcategory":"Religious Organization",
            "type":"Services"
        }
    ],
    "sg:phone":"+1 509 882 3576",
    "sg:postcode":"98930",
    "sg:province":"WA",
    "sg:tags":[
        "church"
    ],
    "wof:name":"Presbyterian Church Bethany",
    "wof:placetype":"venue"
},
  "geometry": {"coordinates":[-119.899023,46.254811],"type":"Point"}
}