{
  "type": "Feature",
  "properties": {
    "addr:full":"11240 12th Ave NE Seattle WA 98125",
    "addr:housenumber":"11240",
    "addr:postcode":"98125",
    "addr:street":"12Th Ave Ne",
    "iso:country":"US",
    "sg:address":"11240 12th Ave NE",
    "sg:city":"Seattle",
    "sg:classifiers":[
        {
            "category":"Social Services",
            "type":"Services"
        }
    ],
    "sg:phone":"+1 206 367 5492",
    "sg:postcode":"98125",
    "sg:province":"WA",
    "wof:name":"Northwest Geriatric Care",
    "wof:placetype":"venue"
},
  "geometry": {"coordinates":[-122.315119,47.710247],"type":"Point"}
}