{
  "type": "Feature",
  "properties": {
    "addr:full":"1215 2nd St Snohomish WA 98290",
    "addr:housenumber":"1215",
    "addr:postcode":"98290",
    "addr:street":"2Nd St",
    "iso:country":"US",
    "sg:address":"1215 2nd St",
    "sg:city":"Snohomish",
    "sg:classifiers":[
        {
            "category":"Food & Beverages",
            "subcategory":"Groceries & Convenience Stores",
            "type":"Retail Goods"
        }
    ],
    "sg:phone":"+1 360 568 8086",
    "sg:postcode":"98290",
    "sg:province":"WA",
    "wof:name":"7-Eleven",
    "wof:placetype":"venue"
},
  "geometry": {"coordinates":[-122.098411,47.912921],"type":"Point"}
}