{
  "type": "Feature",
  "properties": {
    "addr:full":"111 W 29th St Vancouver WA 98660",
    "addr:housenumber":"111",
    "addr:postcode":"98660",
    "addr:street":"W 29Th St",
    "iso:country":"US",
    "sg:address":"111 W 29th St",
    "sg:city":"Vancouver",
    "sg:classifiers":[
        {
            "category":"Home & Garden",
            "subcategory":"Carpets & Floor Coverings",
            "type":"Retail Goods"
        }
    ],
    "sg:phone":"+1 360 571 5647",
    "sg:postcode":"98660",
    "sg:province":"WA",
    "wof:name":"Londons Custom Floors Inc",
    "wof:placetype":"venue"
},
  "geometry": {"coordinates":[-122.67203000000001,45.642372],"type":"Point"}
}