{
  "type": "Feature",
  "properties": {
    "iso:country":"US",
    "sg:address":"712 N Williams St",
    "sg:city":"Aberdeen",
    "sg:classifiers":[
        {
            "category":"Arts & Performance",
            "subcategory":"Theater",
            "type":"Entertainment"
        }
    ],
    "sg:phone":"+1 360 533 2816",
    "sg:postcode":"98520",
    "sg:province":"WA",
    "sg:tags":[
        "group"
    ],
    "wof:name":"Portaparty Sound and Lighting",
    "wof:placetype":"venue"
},
  "geometry": {"coordinates":[-123.83227599999999,46.97755],"type":"Point"}
}