{
  "type": "Feature",
  "properties": {
    "addr:full":"967 Thomas St Seattle WA 98109",
    "addr:housenumber":"967",
    "addr:postcode":"98109",
    "addr:street":"Thomas St",
    "iso:country":"US",
    "sg:address":"967 Thomas St",
    "sg:city":"Seattle",
    "sg:classifiers":[
        {
            "category":"Shopping",
            "type":"Retail Goods"
        }
    ],
    "sg:phone":"+1 206 223 4907",
    "sg:postcode":"98109",
    "sg:province":"WA",
    "sg:tags":[
        "durable",
        "merchandise"
    ],
    "wof:name":"Alpha Omega Sign Co Inc",
    "wof:placetype":"venue"
},
  "geometry": {"coordinates":[-122.337456,47.620794],"type":"Point"}
}