{
  "type": "Feature",
  "properties": {
    "addr:full":"210 W Galer St Seattle WA 98119",
    "addr:housenumber":"210",
    "addr:postcode":"98119",
    "addr:street":"W Galer St",
    "iso:country":"US",
    "sg:address":"210 W Galer St",
    "sg:city":"Seattle",
    "sg:classifiers":[
        {
            "category":"Social Services",
            "type":"Services"
        }
    ],
    "sg:phone":"+1 206 284 1435",
    "sg:postcode":"98119",
    "sg:province":"WA",
    "sg:tags":[
        "counselor",
        "marriage",
        "family"
    ],
    "wof:name":"Victoria Coen",
    "wof:placetype":"venue"
},
  "geometry": {"coordinates":[-122.360041,47.632393],"type":"Point"}
}