{
  "type": "Feature",
  "properties": {
    "addr:full":"7809 NE Vancouver Plaza Dr Ste 110 Vancouver WA 98662",
    "addr:housenumber":"7809",
    "addr:postcode":"98662",
    "addr:street":"Ne Vancouver Plaza Dr Ste 110",
    "iso:country":"US",
    "sg:address":"7809 NE Vancouver Plaza Dr Ste 110",
    "sg:city":"Vancouver",
    "sg:classifiers":[
        {
            "category":"Restaurant",
            "type":"Food & Drink"
        }
    ],
    "sg:phone":"+1 360 883 4900",
    "sg:postcode":"98662",
    "sg:province":"WA",
    "sg:tags":[
        "traditional",
        "american"
    ],
    "wof:name":"Boppin Bo's Malt Shop & Grill",
    "wof:placetype":"venue"
},
  "geometry": {"coordinates":[-122.593227,45.648777],"type":"Point"}
}