{
  "type": "Feature",
  "properties": {
    "addr:full":"68 Island Blvd Fi Fox Island WA 98333",
    "addr:housenumber":"68",
    "addr:postcode":"98333",
    "addr:street":"Island Blvd Fi",
    "iso:country":"US",
    "sg:address":"68 Island Blvd Fi",
    "sg:city":"Fox Island",
    "sg:classifiers":[
        {
            "category":"Personal",
            "subcategory":"Beauty Salon",
            "type":"Services"
        }
    ],
    "sg:phone":"+1 253 549 2332",
    "sg:postcode":"98333",
    "sg:province":"WA",
    "sg:tags":[
        "shop"
    ],
    "wof:name":"Island Wave Hair Design",
    "wof:placetype":"venue"
},
  "geometry": {"coordinates":[-122.665673,47.274754],"type":"Point"}
}