{
  "type": "Feature",
  "properties": {
    "addr:full":"61 Hutchens Hill Rd Pomeroy WA 99347",
    "addr:housenumber":"61",
    "addr:postcode":"99347",
    "addr:street":"Hutchens Hill Rd",
    "iso:country":"US",
    "sg:address":"61 Hutchens Hill Rd",
    "sg:city":"Pomeroy",
    "sg:classifiers":[
        {
            "category":"Manufacturing",
            "subcategory":"Soap",
            "type":"Manufacturing & Wholesale Goods"
        }
    ],
    "sg:phone":"+1 509 843 3677",
    "sg:postcode":"99347",
    "sg:province":"WA",
    "sg:tags":[
        "detergent"
    ],
    "wof:name":"K And D Asso",
    "wof:placetype":"venue"
},
  "geometry": {"coordinates":[-117.54171700000001,46.472073],"type":"Point"}
}