{
  "type": "Feature",
  "properties": {
    "addr:full":"401 Lewis Ave Gold Bar WA 98251",
    "addr:housenumber":"401",
    "addr:postcode":"98251",
    "addr:street":"Lewis Ave",
    "iso:country":"US",
    "sg:address":"401 Lewis Ave",
    "sg:city":"Gold Bar",
    "sg:classifiers":[
        {
            "category":"Education",
            "subcategory":"School",
            "type":"Public Place"
        }
    ],
    "sg:phone":"+1 360 793 9840",
    "sg:postcode":"98251",
    "sg:province":"WA",
    "sg:website":"www.sultan.k12.wa.us",
    "wof:name":"Goldbar Elementary School",
    "wof:placetype":"venue"
},
  "geometry": {"coordinates":[-121.697626,47.856995],"type":"Point"}
}