{
  "type": "Feature",
  "properties": {
    "addr:full":"2305 Bay Ave Hoquiam WA 98550",
    "addr:housenumber":"2305",
    "addr:postcode":"98550",
    "addr:street":"Bay Ave",
    "iso:country":"US",
    "sg:address":"2305 Bay Ave",
    "sg:city":"Hoquiam",
    "sg:classifiers":[
        {
            "category":"Autos & Motor Vehicles",
            "subcategory":"Boat Sales",
            "type":"Retail Goods"
        },
        {
            "category":"Professional",
            "type":"Services"
        }
    ],
    "sg:phone":"+1 360 553 5355",
    "sg:postcode":"98550",
    "sg:province":"WA",
    "sg:tags":[
        "top",
        "upholstery",
        "cover"
    ],
    "wof:name":"Bottom Siders Custom All Wthr",
    "wof:placetype":"venue"
},
  "geometry": {"coordinates":[-123.869739,46.972593],"type":"Point"}
}