{
  "type": "Feature",
  "properties": {
    "addr:full":"101 Auburn Way S Auburn WA 98002",
    "addr:housenumber":"101",
    "addr:postcode":"98002",
    "addr:street":"Auburn Way S",
    "iso:country":"US",
    "sg:address":"101 Auburn Way S",
    "sg:city":"Auburn",
    "sg:classifiers":[
        {
            "category":"Coffee & Tea",
            "type":"Food & Drink"
        }
    ],
    "sg:phone":"+1 253 804 0138",
    "sg:postcode":"98002",
    "sg:province":"WA",
    "sg:tags":[
        "espresso",
        "restaurant"
    ],
    "sg:website":"http://www.starbuckscoffee.com",
    "wof:name":"Starbucks Coffee",
    "wof:placetype":"venue"
},
  "geometry": {"coordinates":[-122.225737,47.306211],"type":"Point"}
}