{
  "type": "Feature",
  "properties": {
    "addr:full":"14 Lopez Ky Bellevue WA 98006",
    "addr:housenumber":"14",
    "addr:postcode":"98006",
    "addr:street":"Lopez Ky",
    "iso:country":"US",
    "sg:address":"14 Lopez Ky",
    "sg:city":"Bellevue",
    "sg:classifiers":[
        {
            "category":"Professional",
            "subcategory":"Employment Agencies",
            "type":"Services"
        }
    ],
    "sg:phone":"+1 425 453 5318",
    "sg:postcode":"98006",
    "sg:province":"WA",
    "sg:tags":[
        "consultants-referral"
    ],
    "sg:website":"http://www.tqsinc.com",
    "wof:name":"Top Quality Services Bellvue O",
    "wof:placetype":"venue"
},
  "geometry": {"coordinates":[-122.18271799999999,47.572979],"type":"Point"}
}