{
  "type": "Feature",
  "properties": {
    "addr:full":"32 Airport Way Chelan WA 98816",
    "addr:housenumber":"32",
    "addr:postcode":"98816",
    "addr:street":"Airport Way",
    "iso:country":"US",
    "sg:address":"32 Airport Way",
    "sg:city":"Chelan",
    "sg:classifiers":[
        {
            "category":"Airport",
            "type":"Transportation"
        }
    ],
    "sg:phone":"+1 509 682 5976",
    "sg:postcode":"98816",
    "sg:province":"WA",
    "wof:name":"Lake Chelan Airport",
    "wof:placetype":"venue"
},
  "geometry": {"coordinates":[-119.938802,47.870333],"type":"Point"}
}