{
  "type": "Feature",
  "properties": {
    "addr:full":"1308 12th St Davenport WA 99122",
    "addr:housenumber":"1308",
    "addr:postcode":"99122",
    "addr:street":"12Th St",
    "iso:country":"US",
    "sg:address":"1308 12th St",
    "sg:city":"Davenport",
    "sg:classifiers":[
        {
            "category":"Building & Trades",
            "subcategory":"Construction",
            "type":"Services"
        }
    ],
    "sg:phone":"+1 509 725 1860",
    "sg:postcode":"99122",
    "sg:province":"WA",
    "sg:tags":[
        "altering",
        "remodeling",
        "contractor"
    ],
    "wof:name":"Rudolph Construction",
    "wof:placetype":"venue"
},
  "geometry": {"coordinates":[-118.15767700000001,47.647217],"type":"Point"}
}