{
  "type": "Feature",
  "properties": {
    "addr:full":"1350 Marvin Rd NE Olympia WA 98516",
    "addr:housenumber":"1350",
    "addr:postcode":"98516",
    "addr:street":"Marvin Rd Ne",
    "iso:country":"US",
    "sg:address":"1350 Marvin Rd NE",
    "sg:city":"Olympia",
    "sg:classifiers":[
        {
            "category":"Restaurant",
            "type":"Food & Drink"
        }
    ],
    "sg:menulink":"http://www.allmenus.com/wa/olympia/6403-taco-del-mar/menu/",
    "sg:phone":"+1 360 456 8120",
    "sg:postcode":"98516",
    "sg:province":"WA",
    "sg:tags":[
        "mexican"
    ],
    "wof:name":"Taco Del Mar",
    "wof:placetype":"venue"
},
  "geometry": {"coordinates":[-122.764713,47.059406],"type":"Point"}
}