{
  "type": "Feature",
  "properties": {
    "addr:full":"9308 Merrick Dr Pasco WA 99301",
    "addr:housenumber":"9308",
    "addr:postcode":"99301",
    "addr:street":"Merrick Dr",
    "iso:country":"US",
    "sg:address":"9308 Merrick Dr",
    "sg:city":"Pasco",
    "sg:classifiers":[
        {
            "category":"Restaurant",
            "type":"Food & Drink"
        }
    ],
    "sg:phone":"+1 509 545 1800",
    "sg:postcode":"99301",
    "sg:province":"WA",
    "sg:tags":[
        "eating"
    ],
    "wof:name":"Black Tie Catering",
    "wof:placetype":"venue"
},
  "geometry": {"coordinates":[-119.21225800000001,46.248465],"type":"Point"}
}