{
  "type": "Feature",
  "properties": {
    "addr:full":"911 E 10th St Port Angeles WA 98362",
    "addr:housenumber":"911",
    "addr:postcode":"98362",
    "addr:street":"E 10Th St",
    "iso:country":"US",
    "sg:address":"911 E 10th St",
    "sg:city":"Port Angeles",
    "sg:classifiers":[
        {
            "category":"Education",
            "subcategory":"Vocational School",
            "type":"Public Place"
        }
    ],
    "sg:phone":"+1 360 457 8443",
    "sg:postcode":"98362",
    "sg:province":"WA",
    "wof:name":"School Of Mortgage Lending",
    "wof:placetype":"venue"
},
  "geometry": {"coordinates":[-123.425652,48.105145],"type":"Point"}
}