{
  "type": "Feature",
  "properties": {
    "addr:full":"812 Columbia St Vancouver WA 98660",
    "addr:housenumber":"812",
    "addr:postcode":"98660",
    "addr:street":"Columbia St",
    "iso:country":"US",
    "sg:address":"812 Columbia St",
    "sg:city":"Vancouver",
    "sg:classifiers":[
        {
            "category":"Shopping",
            "subcategory":"Shoes",
            "type":"Retail Goods"
        }
    ],
    "sg:phone":"+1 360 993 5996",
    "sg:postcode":"98660",
    "sg:province":"WA",
    "sg:tags":[
        "store"
    ],
    "wof:name":"Contessa",
    "wof:placetype":"venue"
},
  "geometry": {"coordinates":[-122.674004,45.628399],"type":"Point"}
}