{
  "type": "Feature",
  "properties": {
    "addr:full":"5303 Bristol Way Ct Yakima WA 98908",
    "addr:housenumber":"5303",
    "addr:postcode":"98908",
    "addr:street":"Bristol Way Ct",
    "iso:country":"US",
    "sg:address":"5303 Bristol Way Ct",
    "sg:city":"Yakima",
    "sg:classifiers":[
        {
            "category":"Professional",
            "type":"Services"
        }
    ],
    "sg:phone":"+1 509 972 4583",
    "sg:postcode":"98908",
    "sg:province":"WA",
    "wof:name":"Knucklehead Sports",
    "wof:placetype":"venue"
},
  "geometry": {"coordinates":[-120.57980499999999,46.589824],"type":"Point"}
}