{
  "type": "Feature",
  "properties": {
    "addr:full":"10564 5th Ave NE Ste 205/304 Seattle WA 98125",
    "addr:housenumber":"10564;/ 304",
    "addr:postcode":"98125",
    "addr:street":"5Th Ave Ne Ste 205",
    "iso:country":"US",
    "sg:address":"10564 5th Ave NE Ste 205/304",
    "sg:city":"Seattle",
    "sg:classifiers":[
        {
            "category":"Health Services",
            "subcategory":"Doctor",
            "type":"Services"
        }
    ],
    "sg:phone":"+1 206 367 2556",
    "sg:postcode":"98125",
    "sg:province":"WA",
    "sg:website":"www.soundsleephealth.com",
    "wof:name":"Sound Sleep Health",
    "wof:placetype":"venue"
},
  "geometry": {"coordinates":[-122.32317,47.705385],"type":"Point"}
}