{
  "type": "Feature",
  "properties": {
    "addr:full":"271 E Balmoral Way Shelton WA 98584",
    "addr:housenumber":"271",
    "addr:postcode":"98584",
    "addr:street":"E Balmoral Way",
    "iso:country":"US",
    "sg:address":"271 E Balmoral Way",
    "sg:city":"Shelton",
    "sg:classifiers":[
        {
            "category":"Building & Trades",
            "subcategory":"Construction",
            "type":"Services"
        }
    ],
    "sg:phone":"+1 360 427 6652",
    "sg:postcode":"98584",
    "sg:province":"WA",
    "sg:tags":[
        "house"
    ],
    "wof:name":"Danford Const",
    "wof:placetype":"venue"
},
  "geometry": {"coordinates":[-123.056506,47.290618],"type":"Point"}
}