{
  "type": "Feature",
  "properties": {
    "addr:full":"4811 NE 139th Ave Vancouver WA 98682",
    "addr:housenumber":"4811",
    "addr:postcode":"98682",
    "addr:street":"Ne 139Th Ave",
    "iso:country":"US",
    "sg:address":"4811 NE 139th Ave",
    "sg:city":"Vancouver",
    "sg:classifiers":[
        {
            "category":"Freight",
            "type":"Transportation"
        }
    ],
    "sg:phone":"+1 360 608 7999",
    "sg:postcode":"98682",
    "sg:province":"WA",
    "sg:tags":[
        "operator",
        "trucking"
    ],
    "wof:name":"Good Old American Trucking",
    "wof:placetype":"venue"
},
  "geometry": {"coordinates":[-122.528946,45.656784],"type":"Point"}
}