{
  "type": "Feature",
  "properties": {
    "addr:full":"5112 NE 145th Ave Vancouver WA 98682",
    "addr:housenumber":"5112",
    "addr:postcode":"98682",
    "addr:street":"Ne 145Th Ave",
    "iso:country":"US",
    "sg:address":"5112 NE 145th Ave",
    "sg:city":"Vancouver",
    "sg:classifiers":[
        {
            "category":"Building & Trades",
            "subcategory":"Construction",
            "type":"Services"
        }
    ],
    "sg:phone":"+1 360 882 1249",
    "sg:postcode":"98682",
    "sg:province":"WA",
    "sg:tags":[
        "contractor"
    ],
    "wof:name":"Reliant Contracting",
    "wof:placetype":"venue"
},
  "geometry": {"coordinates":[-122.523782,45.660216],"type":"Point"}
}