{
  "type": "Feature",
  "properties": {
    "addr:full":"17215 7th Avenue Kp N Lakebay WA 98349",
    "addr:housenumber":"17215",
    "addr:postcode":"98349",
    "addr:street":"7Th Avenue Kp N Lakebay",
    "iso:country":"US",
    "sg:address":"17215 7th Avenue Kp N",
    "sg:city":"Lakebay",
    "sg:classifiers":[
        {
            "category":"Farming",
            "subcategory":"Farm",
            "type":"Manufacturing & Wholesale Goods"
        }
    ],
    "sg:phone":"+1 253 884 4412",
    "sg:postcode":"98349",
    "sg:province":"WA",
    "wof:name":"Boll Heritage Farm",
    "wof:placetype":"venue"
},
  "geometry": {"coordinates":[-122.766813,47.276301],"type":"Point"}
}