{
  "type": "Feature",
  "properties": {
    "addr:full":"7525 NE 202nd Pl Kenmore WA 98028",
    "addr:housenumber":"7525",
    "addr:postcode":"98028",
    "addr:street":"Ne 202Nd Pl",
    "iso:country":"US",
    "sg:address":"7525 NE 202nd Pl",
    "sg:city":"Kenmore",
    "sg:classifiers":[
        {
            "category":"Professional",
            "subcategory":"Business Services",
            "type":"Services"
        }
    ],
    "sg:phone":"+1 425 402 7047",
    "sg:postcode":"98028",
    "sg:province":"WA",
    "wof:name":"Olsen Enterprises",
    "wof:placetype":"venue"
},
  "geometry": {"coordinates":[-122.24009100000001,47.774647],"type":"Point"}
}