{
  "type": "Feature",
  "properties": {
    "iso:country":"US",
    "sg:address":"15320 NE 40th St",
    "sg:city":"Redmond",
    "sg:classifiers":[
        {
            "category":"Insurance",
            "subcategory":"Insurance Agent",
            "type":"Services"
        }
    ],
    "sg:phone":"+1 425 882 5500",
    "sg:postcode":"98052",
    "sg:province":"WA",
    "wof:name":"State Farm Insurance",
    "wof:placetype":"venue"
},
  "geometry": {"coordinates":[-122.135847,47.646085],"type":"Point"}
}