{
  "type": "Feature",
  "properties": {
    "iso:country":"US",
    "sg:address":"1742 NE 147th St",
    "sg:city":"Seattle",
    "sg:classifiers":[
        {
            "category":"Shopping",
            "subcategory":"Musical Instruments",
            "type":"Retail Goods"
        }
    ],
    "sg:phone":"+1 206 365 4851",
    "sg:postcode":"98155",
    "sg:province":"WA",
    "wof:name":"Luna Percussion",
    "wof:placetype":"venue"
},
  "geometry": {"coordinates":[-122.307641,47.735779],"type":"Point"}
}