{
  "type": "Feature",
  "properties": {
    "addr:full":"21310 NE 60th Pl Redmond WA 98053",
    "addr:housenumber":"21310",
    "addr:postcode":"98053",
    "addr:street":"Ne 60Th Pl",
    "iso:country":"US",
    "sg:address":"21310 NE 60th Pl",
    "sg:city":"Redmond",
    "sg:classifiers":[
        {
            "category":"Professional",
            "subcategory":"Business Services",
            "type":"Services"
        }
    ],
    "sg:phone":"+1 206 335 4261",
    "sg:postcode":"98053",
    "sg:province":"WA",
    "wof:name":"Lei",
    "wof:placetype":"venue"
},
  "geometry": {"coordinates":[-122.056297,47.660866],"type":"Point"}
}