{
  "type": "Feature",
  "properties": {
    "addr:full":"6409 6th Ave Tacoma WA 98406",
    "addr:housenumber":"6409",
    "addr:postcode":"98406",
    "addr:street":"6Th Ave",
    "iso:country":"US",
    "sg:address":"6409 6th Ave",
    "sg:city":"Tacoma",
    "sg:classifiers":[
        {
            "category":"Shopping",
            "subcategory":"Tobacco",
            "type":"Retail Goods"
        }
    ],
    "sg:phone":"+1 253 566 6436",
    "sg:postcode":"98406",
    "sg:province":"WA",
    "sg:tags":[
        "cigarette",
        "cigar",
        "dealer"
    ],
    "wof:name":"Greenroom",
    "wof:placetype":"venue"
},
  "geometry": {"coordinates":[-122.521862,47.255526],"type":"Point"}
}