{
  "type": "Feature",
  "properties": {
    "iso:country":"US",
    "sg:address":"917 Wall St",
    "sg:city":"Everett",
    "sg:classifiers":[
        {
            "category":"Manufacturing",
            "subcategory":"Printing",
            "type":"Manufacturing & Wholesale Goods"
        }
    ],
    "sg:phone":"+1 425 339 2221",
    "sg:postcode":"98201",
    "sg:province":"WA",
    "sg:tags":[
        "lithographic",
        "commercial"
    ],
    "wof:name":"Olsen Lithographics",
    "wof:placetype":"venue"
},
  "geometry": {"coordinates":[-122.217167,47.97776],"type":"Point"}
}