{
  "type": "Feature",
  "properties": {
    "addr:full":"3201 Hunter Blvd S Seattle WA 98144",
    "addr:housenumber":"3201",
    "addr:postcode":"98144",
    "addr:street":"Hunter Blvd S",
    "iso:country":"US",
    "sg:address":"3201 Hunter Blvd S",
    "sg:city":"Seattle",
    "sg:classifiers":[
        {
            "category":"Organizations",
            "subcategory":"Religious Organization",
            "type":"Services"
        }
    ],
    "sg:phone":"+1 206 722 5884",
    "sg:postcode":"98144",
    "sg:province":"WA",
    "wof:name":"Mt Baker Park Presbyterian Church",
    "wof:placetype":"venue"
},
  "geometry": {"coordinates":[-122.285004,47.5751],"type":"Point"}
}