{
  "type": "Feature",
  "properties": {
    "addr:full":"810 Twisp-Winthrop East Rd Winthrop WA 98862",
    "addr:housenumber":"810",
    "addr:postcode":"98862",
    "addr:street":"Twisp-Winthrop East Rd",
    "iso:country":"US",
    "sg:address":"810 Twisp-Winthrop East Rd",
    "sg:city":"Winthrop",
    "sg:classifiers":[
        {
            "category":"Building & Trades",
            "subcategory":"Construction",
            "type":"Services"
        }
    ],
    "sg:phone":"+1 509 996 2161",
    "sg:postcode":"98862",
    "sg:province":"WA",
    "sg:tags":[
        "residential",
        "designer"
    ],
    "wof:name":"D E Potter Co",
    "wof:placetype":"venue"
},
  "geometry": {"coordinates":[-120.168161,48.468492],"type":"Point"}
}