{
  "type": "Feature",
  "properties": {
    "addr:full":"8103 Bachelorview Dr Yakima WA 98903",
    "addr:housenumber":"8103",
    "addr:postcode":"98903",
    "addr:street":"Bachelorview Dr",
    "iso:country":"US",
    "sg:address":"8103 Bachelorview Dr",
    "sg:city":"Yakima",
    "sg:classifiers":[
        {
            "category":"Freight",
            "type":"Transportation"
        }
    ],
    "sg:phone":"+1 509 972 2246",
    "sg:postcode":"98903",
    "sg:province":"WA",
    "sg:tags":[
        "arrangement"
    ],
    "wof:name":"Alpine Freight Brokers Inc",
    "wof:placetype":"venue"
},
  "geometry": {"coordinates":[-120.616005,46.553619],"type":"Point"}
}