{
  "type": "Feature",
  "properties": {
    "iso:country":"US",
    "sg:address":"4902 12th Ave S",
    "sg:city":"Seattle",
    "sg:classifiers":[
        {
            "category":"Wholesale",
            "subcategory":"Machinery & Supplies",
            "type":"Manufacturing & Wholesale Goods"
        }
    ],
    "sg:phone":"+1 206 650 6489",
    "sg:postcode":"98108",
    "sg:province":"WA",
    "sg:tags":[
        "equipment",
        "establishment"
    ],
    "wof:name":"Jaj Seafood Co",
    "wof:placetype":"venue"
},
  "geometry": {"coordinates":[-122.317078,47.558191],"type":"Point"}
}