{
  "type": "Feature",
  "properties": {
    "addr:full":"650 Duvall Ave NE Renton WA 98059",
    "addr:housenumber":"650",
    "addr:postcode":"98059",
    "addr:street":"Duvall Ave Ne",
    "iso:country":"US",
    "sg:address":"650 Duvall Ave NE",
    "sg:city":"Renton",
    "sg:classifiers":[
        {
            "category":"Real Estate",
            "subcategory":"Real Estate Operator",
            "type":"Services"
        }
    ],
    "sg:phone":"+1 425 255 7800",
    "sg:postcode":"98059",
    "sg:province":"WA",
    "sg:tags":[
        "building",
        "apartment"
    ],
    "wof:name":"Forestview",
    "wof:placetype":"venue"
},
  "geometry": {"coordinates":[-122.15634,47.492688],"type":"Point"}
}