{
  "type": "Feature",
  "properties": {
    "addr:full":"10848 E Marginal Way S Seattle WA 98168",
    "addr:housenumber":"10848",
    "addr:postcode":"98168",
    "addr:street":"E Marginal Way S",
    "iso:country":"US",
    "sg:address":"10848 E Marginal Way S",
    "sg:city":"Seattle",
    "sg:classifiers":[
        {
            "category":"Wholesale",
            "subcategory":"Chemicals & Plastics",
            "type":"Manufacturing & Wholesale Goods"
        }
    ],
    "sg:phone":"+1 206 763 1340",
    "sg:postcode":"98168",
    "sg:province":"WA",
    "wof:name":"Savolite Inc",
    "wof:placetype":"venue"
},
  "geometry": {"coordinates":[-122.290975,47.507051],"type":"Point"}
}