{
  "type": "Feature",
  "properties": {
    "addr:full":"201 W Shelton Valley Rd Shelton WA 98584",
    "addr:housenumber":"201",
    "addr:postcode":"98584",
    "addr:street":"W Shelton Valley Rd",
    "iso:country":"US",
    "sg:address":"201 W Shelton Valley Rd",
    "sg:city":"Shelton",
    "sg:classifiers":[
        {
            "category":"Place Of Worship",
            "type":"Public Place"
        },
        {
            "category":"Education",
            "subcategory":"School",
            "type":"Public Place"
        }
    ],
    "sg:phone":"+1 360 426 4198",
    "sg:postcode":"98584",
    "sg:province":"WA",
    "sg:tags":[
        "interest",
        "religious",
        "private",
        "k-",
        "church"
    ],
    "wof:name":"Shelton Valley Christian Sch",
    "wof:placetype":"venue"
},
  "geometry": {"coordinates":[-123.13657499999999,47.203026],"type":"Point"}
}