{
  "type": "Feature",
  "properties": {
    "addr:full":"208 E Naches Ave Selah WA 98942",
    "addr:housenumber":"208",
    "addr:postcode":"98942",
    "addr:street":"E Naches Ave",
    "iso:country":"US",
    "sg:address":"208 E Naches Ave",
    "sg:city":"Selah",
    "sg:classifiers":[
        {
            "category":"Retail",
            "subcategory":"Auto Repair",
            "type":"Services"
        }
    ],
    "sg:phone":"+1 509 698 5833",
    "sg:postcode":"98942",
    "sg:province":"WA",
    "sg:tags":[
        "transmission"
    ],
    "wof:name":"AAA Transmission & Auto",
    "wof:placetype":"venue"
},
  "geometry": {"coordinates":[-120.525818,46.653985],"type":"Point"}
}