{
  "type": "Feature",
  "properties": {
    "addr:full":"511 N Argonne Rd Spokane WA 99212",
    "addr:housenumber":"511",
    "addr:postcode":"99212",
    "addr:street":"N Argonne Rd",
    "iso:country":"US",
    "sg:address":"511 N Argonne Rd",
    "sg:city":"Spokane",
    "sg:classifiers":[
        {
            "category":"Social Services",
            "type":"Services"
        }
    ],
    "sg:phone":"+1 509 921 0585",
    "sg:postcode":"99212",
    "sg:province":"WA",
    "wof:name":"Walsh and Associates Inc",
    "wof:placetype":"venue"
},
  "geometry": {"coordinates":[-117.282915,47.661292],"type":"Point"}
}