{
  "type": "Feature",
  "properties": {
    "addr:full":"508 S 3rd St Renton WA 98055",
    "addr:housenumber":"508",
    "addr:postcode":"98055",
    "addr:street":"S 3Rd St",
    "iso:country":"US",
    "sg:address":"508 S 3rd St",
    "sg:city":"Renton",
    "sg:classifiers":[
        {
            "category":"Shopping",
            "subcategory":"Bicycles & Sporting Goods",
            "type":"Retail Goods"
        }
    ],
    "sg:phone":"+1 425 271 6900",
    "sg:postcode":"98055",
    "sg:province":"WA",
    "sg:website":"www.big5sportinggoods.com",
    "wof:name":"Big 5 Sporting Goods",
    "wof:placetype":"venue"
},
  "geometry": {"coordinates":[-122.209999,47.479599],"type":"Point"}
}