{
  "type": "Feature",
  "properties": {
    "addr:full":"1921 Lakewood Dr SE Olympia WA 98501",
    "addr:housenumber":"1921",
    "addr:postcode":"98501",
    "addr:street":"Lakewood Dr Se",
    "iso:country":"US",
    "sg:address":"1921 Lakewood Dr SE",
    "sg:city":"Olympia",
    "sg:classifiers":[
        {
            "category":"Organizations",
            "subcategory":"Religious Organization",
            "type":"Services"
        }
    ],
    "sg:phone":"+1 360 236 0439",
    "sg:postcode":"98501",
    "sg:province":"WA",
    "wof:name":"Foursquare Olympia 2",
    "wof:placetype":"venue"
},
  "geometry": {"coordinates":[-122.87445099999999,47.012575],"type":"Point"}
}