{
  "type": "Feature",
  "properties": {
    "addr:full":"911 N 15th Ave Yakima WA 98902",
    "addr:housenumber":"911",
    "addr:postcode":"98902",
    "addr:street":"N 15Th Ave",
    "iso:country":"US",
    "sg:address":"911 N 15th Ave",
    "sg:city":"Yakima",
    "sg:classifiers":[
        {
            "category":"Organizations",
            "subcategory":"Professional Association",
            "type":"Services"
        },
        {
            "category":"Organizations",
            "subcategory":"Community Association",
            "type":"Services"
        }
    ],
    "sg:phone":"+1 509 575 4748",
    "sg:postcode":"98902",
    "sg:province":"WA",
    "wof:name":"Disabled American Veterans 8",
    "wof:placetype":"venue"
},
  "geometry": {"coordinates":[-120.528998,46.61295],"type":"Point"}
}