{
  "type": "Feature",
  "properties": {
    "addr:full":"1008 Western Ave Ste 307 Seattle WA 98104",
    "addr:housenumber":"1008",
    "addr:postcode":"98104",
    "addr:street":"Western Ave Ste 307",
    "iso:country":"US",
    "sg:address":"1008 Western Ave Ste 307",
    "sg:city":"Seattle",
    "sg:classifiers":[
        {
            "category":"Professional",
            "subcategory":"Engineering",
            "type":"Services"
        }
    ],
    "sg:phone":"+1 206 462 3600",
    "sg:postcode":"98104",
    "sg:province":"WA",
    "sg:tags":[
        "industrial",
        "engineer"
    ],
    "wof:name":"E3 Energy Partners",
    "wof:placetype":"venue"
},
  "geometry": {"coordinates":[-122.337428,47.604299],"type":"Point"}
}