{
  "type": "Feature",
  "properties": {
    "addr:full":"425 NE 95th St Seattle WA 98115",
    "addr:housenumber":"425",
    "addr:postcode":"98115",
    "addr:street":"Ne 95Th St",
    "iso:country":"US",
    "sg:address":"425 NE 95th St",
    "sg:city":"Seattle",
    "sg:classifiers":[
        {
            "category":"Organizations",
            "subcategory":"Religious Organization",
            "type":"Services"
        }
    ],
    "sg:phone":"+1 206 525 8900",
    "sg:postcode":"98115",
    "sg:province":"WA",
    "sg:tags":[
        "churches-community",
        "church"
    ],
    "sg:website":"http://www.olympicchurch.org",
    "wof:name":"Olympic View Community Church",
    "wof:placetype":"venue"
},
  "geometry": {"coordinates":[-122.323713,47.697708],"type":"Point"}
}