{
  "type": "Feature",
  "properties": {
    "addr:full":"403 Madison Ave N Bainbridge Island WA 98110",
    "addr:housenumber":"403",
    "addr:postcode":"98110",
    "addr:street":"Madison Ave N",
    "iso:country":"US",
    "sg:address":"403 Madison Ave N",
    "sg:city":"Bainbridge Island",
    "sg:classifiers":[
        {
            "category":"Cinema",
            "subcategory":"Movie Theater",
            "type":"Entertainment"
        }
    ],
    "sg:phone":"+1 206 855 8169",
    "sg:postcode":"98110",
    "sg:province":"WA",
    "wof:name":"Bainbridge Cinemas",
    "wof:placetype":"venue"
},
  "geometry": {"coordinates":[-122.521004,47.627899],"type":"Point"}
}