{
  "type": "Feature",
  "properties": {
    "addr:full":"18718 NE 161st Pl Woodinville WA 98072",
    "addr:housenumber":"18718",
    "addr:postcode":"98072",
    "addr:street":"Ne 161St Pl",
    "iso:country":"US",
    "sg:address":"18718 NE 161st Pl",
    "sg:city":"Woodinville",
    "sg:classifiers":[
        {
            "category":"Organizations",
            "subcategory":"Community Association",
            "type":"Services"
        }
    ],
    "sg:phone":"+1 425 788 5841",
    "sg:postcode":"98072",
    "sg:province":"WA",
    "wof:name":"Upper Bear Creek Community Cou",
    "wof:placetype":"venue"
},
  "geometry": {"coordinates":[-122.089001,47.74414],"type":"Point"}
}