{
  "type": "Feature",
  "properties": {
    "addr:full":"1928 E 12th Ave Spokane WA 99202",
    "addr:housenumber":"1928",
    "addr:postcode":"99202",
    "addr:street":"E 12Th Ave",
    "iso:country":"US",
    "sg:address":"1928 E 12th Ave",
    "sg:city":"Spokane",
    "sg:classifiers":[
        {
            "category":"Real Estate",
            "subcategory":"Real Estate Operator",
            "type":"Services"
        }
    ],
    "sg:phone":"+1 509 534 2118",
    "sg:postcode":"99202",
    "sg:province":"WA",
    "sg:tags":[
        "building",
        "dwelling",
        "nonresidential"
    ],
    "wof:name":"Norm C Balzer",
    "wof:placetype":"venue"
},
  "geometry": {"coordinates":[-117.379487,47.644489],"type":"Point"}
}