{
  "type": "Feature",
  "properties": {
    "addr:full":"3110 E 12th St Vancouver WA 98661",
    "addr:housenumber":"3110",
    "addr:postcode":"98661",
    "addr:street":"E 12Th St",
    "iso:country":"US",
    "sg:address":"3110 E 12th St",
    "sg:city":"Vancouver",
    "sg:classifiers":[
        {
            "category":"Building & Trades",
            "subcategory":"Construction",
            "type":"Services"
        }
    ],
    "sg:phone":"+1 360 699 6688",
    "sg:postcode":"98661",
    "sg:province":"WA",
    "sg:tags":[
        "restoration",
        "preservation"
    ],
    "wof:name":"Restorations Unlimited",
    "wof:placetype":"venue"
},
  "geometry": {"coordinates":[-122.638198,45.629354],"type":"Point"}
}