{
  "type": "Feature",
  "properties": {
    "iso:country":"US",
    "sg:address":"900 N Maple St",
    "sg:city":"Spokane",
    "sg:classifiers":[
        {
            "category":"Professional",
            "subcategory":"Lawyer & Legal Services",
            "type":"Services"
        }
    ],
    "sg:phone":"+1 509 326 5160",
    "sg:postcode":"99201",
    "sg:province":"WA",
    "sg:tags":[
        "attorney"
    ],
    "wof:name":"Jason B Couey",
    "wof:placetype":"venue"
},
  "geometry": {"coordinates":[-117.435472,47.66576],"type":"Point"}
}