{
  "type": "Feature",
  "properties": {
    "addr:full":"2217 NE 170th St Shoreline WA 98155",
    "addr:housenumber":"2217",
    "addr:postcode":"98155",
    "addr:street":"Ne 170Th St",
    "iso:country":"US",
    "sg:address":"2217 NE 170th St",
    "sg:city":"Shoreline",
    "sg:classifiers":[
        {
            "category":"Building & Trades",
            "subcategory":"Construction",
            "type":"Services"
        },
        {
            "category":"Building & Trades",
            "subcategory":"Landscaping Services",
            "type":"Services"
        }
    ],
    "sg:phone":"+1 206 362 6495",
    "sg:postcode":"98155",
    "sg:province":"WA",
    "sg:tags":[
        "heavy",
        "landscape",
        "contractor"
    ],
    "wof:name":"Green Thumb Landscape",
    "wof:placetype":"venue"
},
  "geometry": {"coordinates":[-122.302708,47.751905],"type":"Point"}
}