{
  "type": "Feature",
  "properties": {
    "addr:full":"705 W 1st Ave Spokane WA 99201",
    "addr:housenumber":"705",
    "addr:postcode":"99201",
    "addr:street":"W 1St Ave",
    "iso:country":"US",
    "sg:address":"705 W 1st Ave",
    "sg:city":"Spokane",
    "sg:classifiers":[
        {
            "category":"Education",
            "subcategory":"College",
            "type":"Public Place"
        }
    ],
    "sg:phone":"+1 509 623 4200",
    "sg:postcode":"99201",
    "sg:province":"WA",
    "sg:website":"www.ewu.edu",
    "wof:name":"Eastern Washington University",
    "wof:placetype":"venue"
},
  "geometry": {"coordinates":[-117.423452,47.656488],"type":"Point"}
}