{
  "type": "Feature",
  "properties": {
    "addr:full":"232 Stretch Island Rd S Grapeview WA 98546",
    "addr:housenumber":"232",
    "addr:postcode":"98546",
    "addr:street":"Stretch Island Rd;Grapeview",
    "iso:country":"US",
    "sg:address":"232 Stretch Island Rd S",
    "sg:city":"Grapeview",
    "sg:classifiers":[
        {
            "category":"Shopping",
            "subcategory":"Florist",
            "type":"Retail Goods"
        }
    ],
    "sg:phone":"+1 360 275 6343",
    "sg:postcode":"98546",
    "sg:province":"WA",
    "wof:name":"Petunia Patch",
    "wof:placetype":"venue"
},
  "geometry": {"coordinates":[-122.82738500000001,47.322874],"type":"Point"}
}