{
  "type": "Feature",
  "properties": {
    "addr:full":"341 E Main St Othello WA 99344",
    "addr:housenumber":"341",
    "addr:postcode":"99344",
    "addr:street":"E Main St",
    "iso:country":"US",
    "sg:address":"341 E Main St",
    "sg:city":"Othello",
    "sg:classifiers":[
        {
            "category":"Autos & Motor Vehicles",
            "subcategory":"Auto Supplies",
            "type":"Retail Goods"
        }
    ],
    "sg:phone":"+1 509 488 9686",
    "sg:postcode":"99344",
    "sg:province":"WA",
    "sg:tags":[
        "tire"
    ],
    "wof:name":"Commercial Tire Inc",
    "wof:placetype":"venue"
},
  "geometry": {"coordinates":[-119.170545,46.826252],"type":"Point"}
}