{
  "type": "Feature",
  "properties": {
    "addr:full":"12913 46th Dr SE Everett WA 98208",
    "addr:housenumber":"12913",
    "addr:postcode":"98208",
    "addr:street":"46Th Dr Se",
    "iso:country":"US",
    "sg:address":"12913 46th Dr SE",
    "sg:city":"Everett",
    "sg:classifiers":[
        {
            "category":"Shopping",
            "type":"Retail Goods"
        }
    ],
    "sg:phone":"+1 425 338 2539",
    "sg:postcode":"98208",
    "sg:province":"WA",
    "sg:tags":[
        "cosmetic",
        "perfume"
    ],
    "wof:name":"Jafra Cosmetics",
    "wof:placetype":"venue"
},
  "geometry": {"coordinates":[-122.169616,47.880842],"type":"Point"}
}