{
  "type": "Feature",
  "properties": {
    "addr:full":"7531 34th Ave NW Seattle WA 98107",
    "addr:housenumber":"7531",
    "addr:postcode":"98107",
    "addr:street":"34Th Ave Nw",
    "iso:country":"US",
    "sg:address":"7531 34th Ave NW",
    "sg:city":"Seattle",
    "sg:classifiers":[
        {
            "category":"Park",
            "type":"Public Place"
        }
    ],
    "sg:postcode":"98107",
    "sg:province":"WA",
    "sg:website":"www.ci.seattle.wa.us/parks/parks...",
    "wof:name":"Sunset Hill Park",
    "wof:placetype":"venue"
},
  "geometry": {"coordinates":[-122.40100099999999,47.683701],"type":"Point"}
}