{
  "type": "Feature",
  "properties": {
    "addr:full":"816 N 38th St Seattle WA 98103",
    "addr:housenumber":"816",
    "addr:postcode":"98103",
    "addr:street":"N 38Th St",
    "iso:country":"US",
    "sg:address":"816 N 38th St",
    "sg:city":"Seattle",
    "sg:classifiers":[
        {
            "category":"Organizations",
            "subcategory":"Non-profit Organization",
            "type":"Services"
        }
    ],
    "sg:phone":"+1 206 547 2171",
    "sg:postcode":"98103",
    "sg:province":"WA",
    "sg:tags":[
        "information",
        "alcoholism",
        "treatment"
    ],
    "wof:name":"Chrysalis Recovery Inc",
    "wof:placetype":"venue"
},
  "geometry": {"coordinates":[-122.348591,47.652726],"type":"Point"}
}