{
  "type": "Feature",
  "properties": {
    "addr:full":"230 N Georgia Ave East Wenatchee WA 98802",
    "addr:housenumber":"230",
    "addr:postcode":"98802",
    "addr:street":"N Georgia Ave",
    "iso:country":"US",
    "sg:address":"230 N Georgia Ave",
    "sg:city":"East Wenatchee",
    "sg:classifiers":[
        {
            "category":"Organizations",
            "subcategory":"Religious Organization",
            "type":"Services"
        }
    ],
    "sg:phone":"+1 509 886 9410",
    "sg:postcode":"98802",
    "sg:province":"WA",
    "sg:tags":[
        "church"
    ],
    "wof:name":"Wenatchee Valley Praise Ctr",
    "wof:placetype":"venue"
},
  "geometry": {"coordinates":[-120.27715999999999,47.408379],"type":"Point"}
}