{
  "type": "Feature",
  "properties": {
    "addr:full":"7801 Hay Lacrosse Rd Lacrosse WA 99143",
    "addr:housenumber":"7801",
    "addr:postcode":"99143",
    "addr:street":"Hay Lacrosse Rd",
    "iso:country":"US",
    "sg:address":"7801 Hay Lacrosse Rd",
    "sg:city":"Lacrosse",
    "sg:classifiers":[
        {
            "category":"Farming",
            "subcategory":"Farm",
            "type":"Manufacturing & Wholesale Goods"
        }
    ],
    "sg:phone":"+1 509 549 3328",
    "sg:postcode":"99143",
    "sg:province":"WA",
    "wof:name":"Durand A Cox",
    "wof:placetype":"venue"
},
  "geometry": {"coordinates":[-117.883781,46.698856],"type":"Point"}
}