{
  "type": "Feature",
  "properties": {
    "addr:full":"315 2nd Ave N Auburn WA 98001",
    "addr:housenumber":"315",
    "addr:postcode":"98001",
    "addr:street":"2Nd Ave N",
    "iso:country":"US",
    "sg:address":"315 2nd Ave N",
    "sg:city":"Auburn",
    "sg:classifiers":[
        {
            "category":"Building & Trades",
            "subcategory":"Construction",
            "type":"Services"
        }
    ],
    "sg:phone":"+1 253 939 4265",
    "sg:postcode":"98001",
    "sg:province":"WA",
    "sg:tags":[
        "house"
    ],
    "wof:name":"Hoffner Construction",
    "wof:placetype":"venue"
},
  "geometry": {"coordinates":[-122.249522,47.281166],"type":"Point"}
}