{
  "type": "Feature",
  "properties": {
    "addr:full":"515 S Dishman Mica Rd Spokane Valley WA 99206",
    "addr:housenumber":"515",
    "addr:postcode":"99206",
    "addr:street":"S Dishman Mica Rd",
    "iso:country":"US",
    "sg:address":"515 S Dishman Mica Rd",
    "sg:city":"Spokane Valley",
    "sg:classifiers":[
        {
            "category":"Building & Trades",
            "subcategory":"Plumbing",
            "type":"Services"
        }
    ],
    "sg:phone":"+1 509 891 5110",
    "sg:postcode":"99206",
    "sg:province":"WA",
    "sg:tags":[
        "air",
        "heating",
        "conditioning",
        "contractor"
    ],
    "sg:website":"www.hurlimanheating.com",
    "wof:name":"Hurliman Heating & Air Cond",
    "wof:placetype":"venue"
},
  "geometry": {"coordinates":[-117.278887,47.651423],"type":"Point"}
}