{
  "type": "Feature",
  "properties": {
    "addr:full":"841 6th St Clarkston WA 99403",
    "addr:housenumber":"841",
    "addr:postcode":"99403",
    "addr:street":"6Th St",
    "iso:country":"US",
    "sg:address":"841 6th St",
    "sg:city":"Clarkston",
    "sg:classifiers":[
        {
            "category":"Bars & Pubs",
            "type":"Food & Drink"
        }
    ],
    "sg:phone":"+1 509 751 9331",
    "sg:postcode":"99403",
    "sg:province":"WA",
    "sg:tags":[
        "drinking"
    ],
    "wof:name":"Vesuvius Lounge",
    "wof:placetype":"venue"
},
  "geometry": {"coordinates":[-117.045495,46.413761],"type":"Point"}
}