{
  "type": "Feature",
  "properties": {
    "addr:full":"7115 NE Hazel Dell Ave Vancouver WA 98665",
    "addr:housenumber":"7115",
    "addr:postcode":"98665",
    "addr:street":"Ne Hazel Dell Ave",
    "iso:country":"US",
    "sg:address":"7115 NE Hazel Dell Ave",
    "sg:city":"Vancouver",
    "sg:classifiers":[
        {
            "category":"Bars & Pubs",
            "type":"Food & Drink"
        }
    ],
    "sg:phone":"+1 360 694 3114",
    "sg:postcode":"98665",
    "sg:province":"WA",
    "sg:tags":[
        "drinking",
        "eating"
    ],
    "wof:name":"Halftime Bar & Grill",
    "wof:placetype":"venue"
},
  "geometry": {"coordinates":[-122.667951,45.672964],"type":"Point"}
}