{
  "type": "Feature",
  "properties": {
    "addr:full":"9915 NE 53rd Ave Vancouver WA 98686",
    "addr:housenumber":"9915",
    "addr:postcode":"98686",
    "addr:street":"Ne 53Rd Ave",
    "iso:country":"US",
    "sg:address":"9915 NE 53rd Ave",
    "sg:city":"Vancouver",
    "sg:classifiers":[
        {
            "category":"Wholesale",
            "subcategory":"Medical Equipment & Supplies",
            "type":"Manufacturing & Wholesale Goods"
        }
    ],
    "sg:phone":"+1 360 576 5559",
    "sg:postcode":"98686",
    "sg:province":"WA",
    "wof:name":"Tanner & Assoc",
    "wof:placetype":"venue"
},
  "geometry": {"coordinates":[-122.617114,45.693389],"type":"Point"}
}