{
  "type": "Feature",
  "properties": {
    "addr:full":"9529 244th St SW Edmonds WA 98020",
    "addr:housenumber":"9529",
    "addr:postcode":"98020",
    "addr:street":"244Th St Sw",
    "iso:country":"US",
    "sg:address":"9529 244th St SW",
    "sg:city":"Edmonds",
    "sg:classifiers":[
        {
            "category":"Health Services",
            "subcategory":"Doctor",
            "type":"Services"
        }
    ],
    "sg:phone":"+1 206 542 7557",
    "sg:postcode":"98020",
    "sg:province":"WA",
    "sg:tags":[
        "dentist"
    ],
    "wof:name":"Firdale Dental Clinic",
    "wof:placetype":"venue"
},
  "geometry": {"coordinates":[-122.359534,47.777841],"type":"Point"}
}