{
  "type": "Feature",
  "properties": {
    "addr:full":"901 Boren Avenue, Suite 900 Seattle WA 98104",
    "addr:housenumber":"901",
    "addr:postcode":"98104",
    "addr:street":"Boren Avenue Suite 900",
    "iso:country":"US",
    "sg:address":"901 Boren Avenue, Suite 900",
    "sg:city":"Seattle",
    "sg:classifiers":[
        {
            "category":"Health Services",
            "subcategory":"Doctor",
            "type":"Services"
        }
    ],
    "sg:phone":"+1 206 323 1900",
    "sg:postcode":"98104",
    "sg:province":"WA",
    "sg:tags":[
        "orthopedist"
    ],
    "sg:website":"www.orthopedics-intl.net",
    "wof:name":"Orthopedics International Ltd PS",
    "wof:placetype":"venue"
},
  "geometry": {"coordinates":[-122.325242,47.608607],"type":"Point"}
}