{
  "type": "Feature",
  "properties": {
    "addr:full":"3600 Admiral Way SW Seattle WA 98126",
    "addr:housenumber":"3600",
    "addr:postcode":"98126",
    "addr:street":"Admiral Way Sw",
    "iso:country":"US",
    "sg:address":"3600 Admiral Way SW",
    "sg:city":"Seattle",
    "sg:classifiers":[
        {
            "category":"Park",
            "type":"Public Place"
        }
    ],
    "sg:phone":"+1 206 684 4075",
    "sg:postcode":"98126",
    "sg:province":"WA",
    "sg:website":"www.ci.seattle.wa.us/parks/parks...",
    "wof:name":"Belvedere Viewpoint",
    "wof:placetype":"venue"
},
  "geometry": {"coordinates":[-122.376688,47.580354],"type":"Point"}
}