{
  "type": "Feature",
  "properties": {
    "addr:full":"6500 26th St E Fife WA 98424",
    "addr:housenumber":"6500",
    "addr:postcode":"98424",
    "addr:street":"26Th St E",
    "iso:country":"US",
    "sg:address":"6500 26th St E",
    "sg:city":"Fife",
    "sg:classifiers":[
        {
            "category":"Shopping",
            "subcategory":"Catalog Store",
            "type":"Retail Goods"
        }
    ],
    "sg:phone":"+1 253 922 3198",
    "sg:postcode":"98424",
    "sg:province":"WA",
    "sg:tags":[
        "mail",
        "order",
        "online"
    ],
    "wof:name":"Mezco Toys",
    "wof:placetype":"venue"
},
  "geometry": {"coordinates":[-122.341469,47.233459],"type":"Point"}
}