{
  "type": "Feature",
  "properties": {
    "addr:full":"119 Prefontaine Pl S Seattle WA 98104",
    "addr:housenumber":"119",
    "addr:postcode":"98104",
    "addr:street":"Prefontaine Pl S",
    "iso:country":"US",
    "sg:address":"119 Prefontaine Pl S",
    "sg:city":"Seattle",
    "sg:classifiers":[
        {
            "category":"Arts & Performance",
            "subcategory":"Art Gallery",
            "type":"Entertainment"
        }
    ],
    "sg:phone":"+1 206 621 1945",
    "sg:postcode":"98104",
    "sg:province":"WA",
    "sg:website":"www.punchgallery.com",
    "wof:name":"Punch Gallery",
    "wof:placetype":"venue"
},
  "geometry": {"coordinates":[-122.33009,47.601471],"type":"Point"}
}