{
  "type": "Feature",
  "properties": {
    "addr:full":"520 112th Ave NE Ste 220 Bellevue WA 98004",
    "addr:housenumber":"520",
    "addr:postcode":"98004",
    "addr:street":"112Th Ave Ne Ste 220",
    "iso:country":"US",
    "sg:address":"520 112th Ave NE Ste 220",
    "sg:city":"Bellevue",
    "sg:classifiers":[
        {
            "category":"Manufacturing",
            "subcategory":"Rubber & Plastics",
            "type":"Manufacturing & Wholesale Goods"
        },
        {
            "category":"Manufacturing",
            "subcategory":"Chemicals & Compounds",
            "type":"Manufacturing & Wholesale Goods"
        }
    ],
    "sg:phone":"+1 425 455 4400",
    "sg:postcode":"98004",
    "sg:province":"WA",
    "sg:tags":[
        "product",
        "compounds",
        "materials-colorants",
        "resin",
        "powders",
        "plastics-raw",
        "resins",
        "liquids"
    ],
    "sg:website":"http://www.hexion.com",
    "wof:name":"Borden",
    "wof:placetype":"venue"
},
  "geometry": {"coordinates":[-122.190944,47.61476],"type":"Point"}
}