{
  "type": "Feature",
  "properties": {
    "iso:country":"US",
    "sg:address":"8415 8th Pl SE",
    "sg:city":"Everett",
    "sg:classifiers":[
        {
            "category":"Personal",
            "subcategory":"Beauty Salon",
            "type":"Services"
        }
    ],
    "sg:phone":"+1 425 353 3859",
    "sg:postcode":"98208",
    "sg:province":"WA",
    "sg:tags":[
        "shop"
    ],
    "wof:name":"Style Wise",
    "wof:placetype":"venue"
},
  "geometry": {"coordinates":[-122.221334,47.92107],"type":"Point"}
}