{
  "type": "Feature",
  "properties": {
    "addr:full":"24803 42nd Ave S Kent WA 98032",
    "addr:housenumber":"24803",
    "addr:postcode":"98032",
    "addr:street":"42Nd Ave S",
    "iso:country":"US",
    "sg:address":"24803 42nd Ave S",
    "sg:city":"Kent",
    "sg:classifiers":[
        {
            "category":"Building & Trades",
            "subcategory":"Pest Control",
            "type":"Services"
        }
    ],
    "sg:phone":"+1 253 854 7117",
    "sg:postcode":"98032",
    "sg:province":"WA",
    "wof:name":"Aggressive Pest Control",
    "wof:placetype":"venue"
},
  "geometry": {"coordinates":[-122.281301,47.378521],"type":"Point"}
}