{
  "type": "Feature",
  "properties": {
    "iso:country":"US",
    "sg:address":"6849 51st Ave NE",
    "sg:city":"Seattle",
    "sg:classifiers":[
        {
            "category":"Professional",
            "subcategory":"Management & Consulting",
            "type":"Services"
        }
    ],
    "sg:phone":"+1 206 527 4327",
    "sg:postcode":"98115",
    "sg:province":"WA",
    "sg:tags":[
        "consultant"
    ],
    "wof:name":"Cullen Administration",
    "wof:placetype":"venue"
},
  "geometry": {"coordinates":[-122.27303499999999,47.678953],"type":"Point"}
}