{
  "type": "Feature",
  "properties": {
    "addr:full":"2018 Blaine Ave NE Renton WA 98056",
    "addr:housenumber":"2018",
    "addr:postcode":"98056",
    "addr:street":"Blaine Ave Ne",
    "iso:country":"US",
    "sg:address":"2018 Blaine Ave NE",
    "sg:city":"Renton",
    "sg:classifiers":[
        {
            "category":"Professional",
            "subcategory":"Engineering",
            "type":"Services"
        },
        {
            "category":"Building & Trades",
            "subcategory":"Electrical",
            "type":"Services"
        }
    ],
    "sg:phone":"+1 425 207 8866",
    "sg:postcode":"98056",
    "sg:province":"WA",
    "sg:tags":[
        "industrial",
        "electrician",
        "electric",
        "contractors-commercial",
        "engineer"
    ],
    "wof:name":"Quality Electrical Contractors",
    "wof:placetype":"venue"
},
  "geometry": {"coordinates":[-122.189376,47.50984],"type":"Point"}
}