{
  "type": "Feature",
  "properties": {
    "addr:full":"1128 N Dennis Ct East Wenatchee WA 98802",
    "addr:housenumber":"1128",
    "addr:postcode":"98802",
    "addr:street":"N Dennis Ct",
    "iso:country":"US",
    "sg:address":"1128 N Dennis Ct",
    "sg:city":"East Wenatchee",
    "sg:classifiers":[
        {
            "category":"Real Estate",
            "subcategory":"Real Estate Operator",
            "type":"Services"
        }
    ],
    "sg:phone":"+1 509 884 4077",
    "sg:postcode":"98802",
    "sg:province":"WA",
    "sg:tags":[
        "building",
        "apartment"
    ],
    "wof:name":"Rio Avista Apartment",
    "wof:placetype":"venue"
},
  "geometry": {"coordinates":[-120.285504,47.423484],"type":"Point"}
}