{
  "type": "Feature",
  "properties": {
    "addr:full":"13109 NE 175th St Woodinville WA 98072",
    "addr:housenumber":"13109",
    "addr:postcode":"98072",
    "addr:street":"Ne 175Th St",
    "iso:country":"US",
    "sg:address":"13109 NE 175th St",
    "sg:city":"Woodinville",
    "sg:classifiers":[
        {
            "category":"Manufacturing",
            "subcategory":"Printing",
            "type":"Manufacturing & Wholesale Goods"
        }
    ],
    "sg:phone":"+1 425 481 2188",
    "sg:postcode":"98072",
    "sg:province":"WA",
    "sg:tags":[
        "photocopying",
        "printer",
        "commercial"
    ],
    "wof:name":"Jiffy Prints & Copy",
    "wof:placetype":"venue"
},
  "geometry": {"coordinates":[-122.163347,47.754397],"type":"Point"}
}