{
  "type": "Feature",
  "properties": {
    "addr:full":"2612 NW 98th St Seattle WA 98117",
    "addr:housenumber":"2612",
    "addr:postcode":"98117",
    "addr:street":"Nw 98Th St",
    "iso:country":"US",
    "sg:address":"2612 NW 98th St",
    "sg:city":"Seattle",
    "sg:classifiers":[
        {
            "category":"Professional",
            "subcategory":"Business Services",
            "type":"Services"
        }
    ],
    "sg:phone":"+1 206 784 7598",
    "sg:postcode":"98117",
    "sg:province":"WA",
    "wof:name":"Habitat Construction Cod",
    "wof:placetype":"venue"
},
  "geometry": {"coordinates":[-122.392134,47.70017],"type":"Point"}
}