{
  "type": "Feature",
  "properties": {
    "addr:full":"17427 SE Covington Sawyer Rd Kent WA 98042",
    "addr:housenumber":"17427",
    "addr:postcode":"98042",
    "addr:street":"Se;Sawyer Rd",
    "iso:country":"US",
    "sg:address":"17427 SE Covington Sawyer Rd",
    "sg:city":"Kent",
    "sg:classifiers":[
        {
            "category":"Building & Trades",
            "subcategory":"Construction",
            "type":"Services"
        }
    ],
    "sg:phone":"+1 206 228 2470",
    "sg:postcode":"98042",
    "sg:province":"WA",
    "sg:tags":[
        "painting",
        "contractor"
    ],
    "wof:name":"Decorative Finishes",
    "wof:placetype":"venue"
},
  "geometry": {"coordinates":[-122.108541,47.347543],"type":"Point"}
}