{
  "type": "Feature",
  "properties": {
    "addr:full":"15559 Washington Ave NE Bainbridge Island WA 98110",
    "addr:housenumber":"15559",
    "addr:postcode":"98110",
    "addr:street":"Washington Ave Ne",
    "iso:country":"US",
    "sg:address":"15559 Washington Ave NE",
    "sg:city":"Bainbridge Island",
    "sg:classifiers":[
        {
            "category":"Professional",
            "type":"Services"
        }
    ],
    "sg:phone":"+1 206 842 7298",
    "sg:postcode":"98110",
    "sg:province":"WA",
    "wof:name":"Hilary Hilscher",
    "wof:placetype":"venue"
},
  "geometry": {"coordinates":[-122.524112,47.703572],"type":"Point"}
}