{
  "type": "Feature",
  "properties": {
    "iso:country":"US",
    "sg:address":"3692 Deer Creek Rd",
    "sg:city":"Valley",
    "sg:classifiers":[
        {
            "category":"Building & Trades",
            "subcategory":"Construction",
            "type":"Services"
        },
        {
            "category":"Manufacturing",
            "subcategory":"Lumber",
            "type":"Manufacturing & Wholesale Goods"
        }
    ],
    "sg:phone":"+1 509 937 4466",
    "sg:postcode":"99181",
    "sg:province":"WA",
    "sg:tags":[
        "excavation",
        "forester",
        "contractor"
    ],
    "wof:name":"Nelson's Silviculture Inc",
    "wof:placetype":"venue"
},
  "geometry": {"coordinates":[-117.77726,48.114573],"type":"Point"}
}