{
  "type": "Feature",
  "properties": {
    "addr:full":"1700 Gilman St Ste 210 Redmond WA 98052",
    "addr:housenumber":"1700",
    "addr:postcode":"98052",
    "addr:street":"Gilman St Ste 210",
    "iso:country":"US",
    "sg:address":"1700 Gilman St Ste 210",
    "sg:city":"Redmond",
    "sg:classifiers":[
        {
            "category":"Shopping",
            "subcategory":"Clothing, Apparel, & Fashions",
            "type":"Retail Goods"
        }
    ],
    "sg:phone":"+1 425 558 4433",
    "sg:postcode":"98052",
    "sg:province":"WA",
    "sg:tags":[
        "work",
        "uniform",
        "clothes"
    ],
    "sg:website":"http://www.cintas-corp.com",
    "wof:name":"Cintas",
    "wof:placetype":"venue"
},
  "geometry": {"coordinates":[-122.121685,47.674486],"type":"Point"}
}