{
  "type": "Feature",
  "properties": {
    "addr:full":"15525 15th Ave NE Shoreline WA 98155",
    "addr:housenumber":"15525",
    "addr:postcode":"98155",
    "addr:street":"15Th Ave Ne",
    "iso:country":"US",
    "sg:address":"15525 15th Ave NE",
    "sg:city":"Shoreline",
    "sg:classifiers":[
        {
            "category":"Professional",
            "subcategory":"Business Services",
            "type":"Services"
        }
    ],
    "sg:phone":"+1 206 417 0766",
    "sg:postcode":"98155",
    "sg:province":"WA",
    "sg:tags":[
        "music",
        "producer"
    ],
    "sg:website":"http://www.undercaste.com",
    "wof:name":"Undercaste Studios",
    "wof:placetype":"venue"
},
  "geometry": {"coordinates":[-122.312962,47.74179],"type":"Point"}
}