{
  "type": "Feature",
  "properties": {
    "addr:full":"26715 Old Owen Rd Monroe WA 98272",
    "addr:housenumber":"26715",
    "addr:postcode":"98272",
    "addr:street":"Old Owen Rd",
    "iso:country":"US",
    "sg:address":"26715 Old Owen Rd",
    "sg:city":"Monroe",
    "sg:classifiers":[
        {
            "category":"Professional",
            "subcategory":"Art Services",
            "type":"Services"
        }
    ],
    "sg:phone":"+1 360 863 8345",
    "sg:postcode":"98272",
    "sg:province":"WA",
    "sg:tags":[
        "graphic",
        "designer"
    ],
    "wof:name":"Apex Graffix",
    "wof:placetype":"venue"
},
  "geometry": {"coordinates":[-121.872586,47.861488],"type":"Point"}
}