{
  "type": "Feature",
  "properties": {
    "addr:full":"4234 Southcenter Blvd Seattle WA 98188",
    "addr:housenumber":"4234",
    "addr:postcode":"98188",
    "addr:street":"Southcenter Blvd",
    "iso:country":"US",
    "sg:address":"4234 Southcenter Blvd",
    "sg:city":"Seattle",
    "sg:classifiers":[
        {
            "category":"Wholesale",
            "subcategory":"Machinery & Supplies",
            "type":"Manufacturing & Wholesale Goods"
        }
    ],
    "sg:phone":"+1 206 277 8945",
    "sg:postcode":"98188",
    "sg:province":"WA",
    "sg:tags":[
        "distributor",
        "aircraft"
    ],
    "wof:name":"Jet Link International Inc",
    "wof:placetype":"venue"
},
  "geometry": {"coordinates":[-122.27860099999999,47.466004],"type":"Point"}
}