{
  "type": "Feature",
  "properties": {
    "addr:full":"14022 SE Petrovitsky Rd Renton WA 98058",
    "addr:postcode":"14022;98058",
    "addr:street":"Se Petrovitsky Rd",
    "iso:country":"US",
    "sg:address":"14022 SE Petrovitsky Rd",
    "sg:city":"Renton",
    "sg:classifiers":[
        {
            "category":"Restaurant",
            "type":"Food & Drink"
        }
    ],
    "sg:phone":"+1 425 430 9134",
    "sg:postcode":"98058",
    "sg:province":"WA",
    "sg:tags":[
        "eating"
    ],
    "wof:name":"Seattles Best Coffee",
    "wof:placetype":"venue"
},
  "geometry": {"coordinates":[-122.15062500000001,47.444769],"type":"Point"}
}