{
  "type": "Feature",
  "properties": {
    "addr:full":"18407 228th Ave NE Woodinville WA 98077",
    "addr:housenumber":"18407",
    "addr:postcode":"98077",
    "addr:street":"228Th Ave Ne",
    "iso:country":"US",
    "sg:address":"18407 228th Ave NE",
    "sg:city":"Woodinville",
    "sg:classifiers":[
        {
            "category":"Manufacturing",
            "subcategory":"Metals",
            "type":"Manufacturing & Wholesale Goods"
        }
    ],
    "sg:phone":"+1 425 844 1412",
    "sg:postcode":"98077",
    "sg:province":"WA",
    "wof:name":"Classic Metal Design Gates",
    "wof:placetype":"venue"
},
  "geometry": {"coordinates":[-122.03461299999999,47.761822],"type":"Point"}
}