{
  "type": "Feature",
  "properties": {
    "addr:full":"2125 Western Avenue Seattle WA 98121",
    "addr:housenumber":"2125",
    "addr:postcode":"98121",
    "addr:street":"Western Avenue",
    "iso:country":"US",
    "sg:address":"2125 Western Avenue",
    "sg:city":"Seattle",
    "sg:classifiers":[
        {
            "category":"Communications",
            "subcategory":"Newspaper",
            "type":"Services"
        }
    ],
    "sg:phone":"+1 206 728 7200",
    "sg:postcode":"98121",
    "sg:province":"WA",
    "sg:tags":[
        "print",
        "medium"
    ],
    "wof:name":"Citadel Management Partners",
    "wof:placetype":"venue"
},
  "geometry": {"coordinates":[-122.34502999999999,47.611308],"type":"Point"}
}