{
  "type": "Feature",
  "properties": {
    "addr:full":"811 S Auburn St Kennewick WA 99336",
    "addr:housenumber":"811",
    "addr:postcode":"99336",
    "addr:street":"S Auburn St",
    "iso:country":"US",
    "sg:address":"811 S Auburn St",
    "sg:city":"Kennewick",
    "sg:classifiers":[
        {
            "category":"Health Services",
            "subcategory":"Doctor",
            "type":"Services"
        }
    ],
    "sg:phone":"+1 509 586 9187",
    "sg:postcode":"99336",
    "sg:province":"WA",
    "sg:tags":[
        "internist",
        "surgeon",
        "physician"
    ],
    "wof:name":"Coler Roderick S MD",
    "wof:placetype":"venue"
},
  "geometry": {"coordinates":[-119.118476,46.19849],"type":"Point"}
}