{
  "type": "Feature",
  "properties": {
    "addr:full":"1213 Euclid Ave Bellingham WA 98229",
    "addr:housenumber":"1213",
    "addr:postcode":"98229",
    "addr:street":"Euclid Ave",
    "iso:country":"US",
    "sg:address":"1213 Euclid Ave",
    "sg:city":"Bellingham",
    "sg:classifiers":[
        {
            "category":"Shopping",
            "subcategory":"Clothing, Apparel, & Fashions",
            "type":"Retail Goods"
        }
    ],
    "sg:phone":"+1 360 733 1381",
    "sg:postcode":"98229",
    "sg:province":"WA",
    "wof:name":"Willow Tree Audio Works",
    "wof:placetype":"venue"
},
  "geometry": {"coordinates":[-122.40989999999999,48.74153],"type":"Point"}
}