{
  "type": "Feature",
  "properties": {
    "addr:full":"3705 Taylor Ave Bellingham WA 98229",
    "addr:housenumber":"3705",
    "addr:postcode":"98229",
    "addr:street":"Taylor Ave",
    "iso:country":"US",
    "sg:address":"3705 Taylor Ave",
    "sg:city":"Bellingham",
    "sg:classifiers":[
        {
            "category":"Professional",
            "subcategory":"Secretarial Services",
            "type":"Services"
        }
    ],
    "sg:phone":"+1 360 733 3077",
    "sg:postcode":"98229",
    "sg:province":"WA",
    "sg:tags":[
        "reporting"
    ],
    "wof:name":"Priority Business Support",
    "wof:placetype":"venue"
},
  "geometry": {"coordinates":[-122.467856,48.724975],"type":"Point"}
}