{
  "type": "Feature",
  "properties": {
    "addr:full":"11066 5th Ave NE Seattle WA 98125",
    "addr:housenumber":"11066",
    "addr:postcode":"98125",
    "addr:street":"5Th Ave Ne",
    "iso:country":"US",
    "sg:address":"11066 5th Ave NE",
    "sg:city":"Seattle",
    "sg:classifiers":[
        {
            "category":"Health Services",
            "subcategory":"Doctor",
            "type":"Services"
        }
    ],
    "sg:phone":"+1 206 363 1464",
    "sg:postcode":"98125",
    "sg:province":"WA",
    "wof:name":"Ralph A Nord DDS PS",
    "wof:placetype":"venue"
},
  "geometry": {"coordinates":[-122.32322499999999,47.70929],"type":"Point"}
}