{
  "type": "Feature",
  "properties": {
    "addr:full":"5407 NE 47th St Vancouver WA 98661",
    "addr:housenumber":"5407",
    "addr:postcode":"98661",
    "addr:street":"Ne 47Th St",
    "iso:country":"US",
    "sg:address":"5407 NE 47th St",
    "sg:city":"Vancouver",
    "sg:classifiers":[
        {
            "category":"Professional",
            "type":"Services"
        }
    ],
    "sg:phone":"+1 360 608 3472",
    "sg:postcode":"98661",
    "sg:province":"WA",
    "wof:name":"Daicom Pacific",
    "wof:placetype":"venue"
},
  "geometry": {"coordinates":[-122.615358,45.656345],"type":"Point"}
}