{
  "type": "Feature",
  "properties": {
    "addr:full":"3105 W Jennings Rd Cheney WA 99004",
    "addr:housenumber":"3105",
    "addr:postcode":"99004",
    "addr:street":"W Jennings Rd",
    "iso:country":"US",
    "sg:address":"3105 W Jennings Rd",
    "sg:city":"Cheney",
    "sg:classifiers":[
        {
            "category":"Manufacturing",
            "subcategory":"Chemicals & Compounds",
            "type":"Manufacturing & Wholesale Goods"
        }
    ],
    "sg:phone":"+1 509 235 2216",
    "sg:postcode":"99004",
    "sg:province":"WA",
    "sg:tags":[
        "product",
        "mfg"
    ],
    "wof:name":"Young Health",
    "wof:placetype":"venue"
},
  "geometry": {"coordinates":[-117.45895299999999,47.43453],"type":"Point"}
}