{
  "type": "Feature",
  "properties": {
    "addr:full":"4009 Bridgeport Way W University Place WA 98466",
    "addr:housenumber":"4009",
    "addr:postcode":"98466",
    "addr:street":"Bridgeport Way W;Place",
    "iso:country":"US",
    "sg:address":"4009 Bridgeport Way W",
    "sg:city":"University Place",
    "sg:classifiers":[
        {
            "category":"Organizations",
            "subcategory":"Non-profit Organization",
            "type":"Services"
        }
    ],
    "sg:phone":"+1 253 564 3377",
    "sg:postcode":"98466",
    "sg:province":"WA",
    "sg:tags":[
        "info",
        "addiction",
        "abuse",
        "treatment",
        "drug"
    ],
    "wof:name":"Horizon Treatment Svc",
    "wof:placetype":"venue"
},
  "geometry": {"coordinates":[-122.53704,47.219604],"type":"Point"}
}