{
  "type": "Feature",
  "properties": {
    "addr:full":"1110 Capitol Way SE Olympia WA 98501",
    "addr:housenumber":"1110",
    "addr:postcode":"98501",
    "addr:street":"Capitol Way Se",
    "iso:country":"US",
    "sg:address":"1110 Capitol Way SE",
    "sg:city":"Olympia",
    "sg:classifiers":[
        {
            "category":"Professional",
            "subcategory":"Lawyer & Legal Services",
            "type":"Services"
        }
    ],
    "sg:phone":"+1 360 943 3300",
    "sg:postcode":"98501",
    "sg:province":"WA",
    "sg:tags":[
        "attorney"
    ],
    "wof:name":"Mentor Law Group",
    "wof:placetype":"venue"
},
  "geometry": {"coordinates":[-122.900727,47.037787],"type":"Point"}
}