{
  "type": "Feature",
  "properties": {
    "iso:country":"US",
    "sg:address":"25431 213th Ave SE",
    "sg:city":"Maple Valley",
    "sg:classifiers":[
        {
            "category":"Professional",
            "subcategory":"Accounting & Tax Preparation",
            "type":"Services"
        }
    ],
    "sg:phone":"+1 425 433 1700",
    "sg:postcode":"98038",
    "sg:province":"WA",
    "wof:name":"Northwest Billing Systems",
    "wof:placetype":"venue"
},
  "geometry": {"coordinates":[-122.056477,47.373371],"type":"Point"}
}