{
  "type": "Feature",
  "properties": {
    "addr:full":"215 Melody Ln Wenatchee WA 98801",
    "addr:housenumber":"215",
    "addr:postcode":"98801",
    "addr:street":"Melody Ln",
    "iso:country":"US",
    "sg:address":"215 Melody Ln",
    "sg:city":"Wenatchee",
    "sg:classifiers":[
        {
            "category":"Manufacturing",
            "subcategory":"Lumber",
            "type":"Manufacturing & Wholesale Goods"
        }
    ],
    "sg:phone":"+1 509 662 4335",
    "sg:postcode":"98801",
    "sg:province":"WA",
    "sg:tags":[
        "government"
    ],
    "wof:name":"US Forestry Dept",
    "wof:placetype":"venue"
},
  "geometry": {"coordinates":[-120.338719,47.469493],"type":"Point"}
}