{
  "type": "Feature",
  "properties": {
    "addr:full":"1806 169th St S Spanaway WA 98387",
    "addr:housenumber":"1806",
    "addr:postcode":"98387",
    "addr:street":"169Th St S",
    "iso:country":"US",
    "sg:address":"1806 169th St S",
    "sg:city":"Spanaway",
    "sg:classifiers":[
        {
            "category":"Building & Trades",
            "subcategory":"Construction",
            "type":"Services"
        }
    ],
    "sg:phone":"+1 253 531 1183",
    "sg:postcode":"98387",
    "sg:province":"WA",
    "sg:tags":[
        "contractor"
    ],
    "wof:name":"RMC Siding",
    "wof:placetype":"venue"
},
  "geometry": {"coordinates":[-122.45746699999999,47.103557],"type":"Point"}
}