{
  "type": "Feature",
  "properties": {
    "addr:full":"1507 S Grand Blvd Spokane WA 99203",
    "addr:housenumber":"1507",
    "addr:postcode":"99203",
    "addr:street":"S Grand Blvd",
    "iso:country":"US",
    "sg:address":"1507 S Grand Blvd",
    "sg:city":"Spokane",
    "sg:classifiers":[
        {
            "category":"Insurance",
            "subcategory":"Hazard Insurance",
            "type":"Services"
        }
    ],
    "sg:phone":"+1 509 624 7073",
    "sg:postcode":"99203",
    "sg:province":"WA",
    "sg:website":"http://statefarm.mqgroup.com/url.asp?usr=4794B3",
    "wof:name":"State Farm Insurance Agent-J Praxel Insurance Agency Inc",
    "wof:placetype":"venue"
},
  "geometry": {"coordinates":[-117.408187,47.641861],"type":"Point"}
}