{
  "type": "Feature",
  "properties": {
    "addr:full":"1500 112th Ave NE Bellevue WA 98004",
    "addr:housenumber":"1500",
    "addr:postcode":"98004",
    "addr:street":"112Th Ave Ne",
    "iso:country":"US",
    "sg:address":"1500 112th Ave NE",
    "sg:city":"Bellevue",
    "sg:classifiers":[
        {
            "category":"Real Estate",
            "subcategory":"Real Estate Agent",
            "type":"Services"
        }
    ],
    "sg:phone":"+1 425 454 7700",
    "sg:postcode":"98004",
    "sg:province":"WA",
    "sg:tags":[
        "appraiser"
    ],
    "wof:name":"Boldrey Valuation Advisors Inc",
    "wof:placetype":"venue"
},
  "geometry": {"coordinates":[-122.190943,47.629301],"type":"Point"}
}