{
  "type": "Feature",
  "properties": {
    "addr:full":"6623 S 228th St Kent WA 98032",
    "addr:housenumber":"6623",
    "addr:postcode":"98032",
    "addr:street":"S 228Th St",
    "iso:country":"US",
    "sg:address":"6623 S 228th St",
    "sg:city":"Kent",
    "sg:classifiers":[
        {
            "category":"Wholesale",
            "subcategory":"Home Furnishings",
            "type":"Manufacturing & Wholesale Goods"
        }
    ],
    "sg:phone":"+1 253 872 4909",
    "sg:postcode":"98032",
    "sg:province":"WA",
    "sg:tags":[
        "housewares",
        "item",
        "tableware",
        "ceramic"
    ],
    "wof:name":"Inspirado Designs Corp",
    "wof:placetype":"venue"
},
  "geometry": {"coordinates":[-122.250214,47.397529],"type":"Point"}
}