{
  "type": "Feature",
  "properties": {
    "addr:full":"15465 179th Ave SE Monroe WA 98272",
    "addr:housenumber":"15465",
    "addr:postcode":"98272",
    "addr:street":"179Th Ave Se",
    "iso:country":"US",
    "sg:address":"15465 179th Ave SE",
    "sg:city":"Monroe",
    "sg:classifiers":[
        {
            "category":"Real Estate",
            "subcategory":"Real Estate Operator",
            "type":"Services"
        }
    ],
    "sg:phone":"+1 360 794 4284",
    "sg:postcode":"98272",
    "sg:province":"WA",
    "sg:tags":[
        "building",
        "apartment",
        "skilled",
        "nursing",
        "care"
    ],
    "wof:name":"Merrill Gardens At Monroe",
    "wof:placetype":"venue"
},
  "geometry": {"coordinates":[-121.990574,47.856887],"type":"Point"}
}