{
  "type": "Feature",
  "properties": {
    "addr:full":"7402 E Sprague Ave Spokane Valley WA 99212",
    "addr:housenumber":"7402",
    "addr:postcode":"99212",
    "addr:street":"E Sprague Ave",
    "iso:country":"US",
    "sg:address":"7402 E Sprague Ave",
    "sg:city":"Spokane Valley",
    "sg:classifiers":[
        {
            "category":"Retail",
            "subcategory":"Repair Shop",
            "type":"Services"
        }
    ],
    "sg:phone":"+1 509 928 0701",
    "sg:postcode":"99212",
    "sg:province":"WA",
    "sg:tags":[
        "welding"
    ],
    "wof:name":"J & B Welding",
    "wof:placetype":"venue"
},
  "geometry": {"coordinates":[-117.30522000000001,47.6568],"type":"Point"}
}