{
  "type": "Feature",
  "properties": {
    "addr:full":"2708 McDougall Ave Everett WA 98201",
    "addr:housenumber":"2708",
    "addr:postcode":"98201",
    "addr:street":"Mcdougall Ave",
    "iso:country":"US",
    "sg:address":"2708 McDougall Ave",
    "sg:city":"Everett",
    "sg:classifiers":[
        {
            "category":"Retail",
            "subcategory":"Auto Repair",
            "type":"Services"
        }
    ],
    "sg:phone":"+1 425 252 8091",
    "sg:postcode":"98201",
    "sg:province":"WA",
    "sg:tags":[
        "repairing",
        "automobile"
    ],
    "wof:name":"Iver's Auto Clinic",
    "wof:placetype":"venue"
},
  "geometry": {"coordinates":[-122.200149,47.98064],"type":"Point"}
}