{
  "type": "Feature",
  "properties": {
    "addr:full":"673 Arden Hill Rd Colville WA 99114",
    "addr:housenumber":"673",
    "addr:postcode":"99114",
    "addr:street":"Arden Hill Rd",
    "iso:country":"US",
    "sg:address":"673 Arden Hill Rd",
    "sg:city":"Colville",
    "sg:classifiers":[
        {
            "category":"Organizations",
            "subcategory":"Religious Organization",
            "type":"Services"
        }
    ],
    "sg:phone":"+1 509 684 3983",
    "sg:postcode":"99114",
    "sg:province":"WA",
    "sg:tags":[
        "church"
    ],
    "wof:name":"Arden Faith Baptist Church",
    "wof:placetype":"venue"
},
  "geometry": {"coordinates":[-117.89083100000001,48.455562],"type":"Point"}
}