{
  "type": "Feature",
  "properties": {
    "addr:full":"901 W Bertona St Ste 702 Seattle WA 98119",
    "addr:housenumber":"901",
    "addr:postcode":"98119",
    "addr:street":"W Bertona St Ste 702",
    "iso:country":"US",
    "sg:address":"901 W Bertona St Ste 702",
    "sg:city":"Seattle",
    "sg:classifiers":[
        {
            "category":"Health Services",
            "subcategory":"Doctor",
            "type":"Services"
        }
    ],
    "sg:phone":"+1 206 623 7445",
    "sg:postcode":"98119",
    "sg:province":"WA",
    "wof:name":"Ovenstein Herbert MD PS",
    "wof:placetype":"venue"
},
  "geometry": {"coordinates":[-122.368905,47.650459],"type":"Point"}
}