{
  "type": "Feature",
  "properties": {
    "addr:full":"5901 N Lidgerwood St Spokane WA 99208",
    "addr:housenumber":"5901",
    "addr:postcode":"99208",
    "addr:street":"N Lidgerwood St",
    "iso:country":"US",
    "sg:address":"5901 N Lidgerwood St",
    "sg:city":"Spokane",
    "sg:classifiers":[
        {
            "category":"Health Services",
            "subcategory":"Hospital",
            "type":"Services"
        }
    ],
    "sg:phone":"+1 509 489 5019",
    "sg:postcode":"99208",
    "sg:province":"WA",
    "sg:website":"http://www.mscenter.us",
    "wof:name":"Holy Family Hospital - Multiple Sclerosis Center",
    "wof:placetype":"venue"
},
  "geometry": {"coordinates":[-117.405907,47.711498],"type":"Point"}
}