{
  "type": "Feature",
  "properties": {
    "addr:full":"4437 California Ave SW Seattle WA 98116",
    "addr:housenumber":"4437",
    "addr:postcode":"98116",
    "addr:street":"California Ave Sw",
    "iso:country":"US",
    "sg:address":"4437 California Ave SW",
    "sg:city":"Seattle",
    "sg:classifiers":[
        {
            "category":"Building & Trades",
            "subcategory":"Landscaping Services",
            "type":"Services"
        }
    ],
    "sg:phone":"+1 206 932 2588",
    "sg:postcode":"98116",
    "sg:province":"WA",
    "sg:tags":[
        "lawn",
        "maintenance",
        "grounds"
    ],
    "wof:name":"In Bloom",
    "wof:placetype":"venue"
},
  "geometry": {"coordinates":[-122.38685099999999,47.563571],"type":"Point"}
}