{
  "type": "Feature",
  "properties": {
    "addr:full":"405 S 1st St Mt Vernon WA 98273",
    "addr:housenumber":"405",
    "addr:postcode":"98273",
    "addr:street":"S 1St St",
    "iso:country":"US",
    "sg:address":"405 S 1st St",
    "sg:city":"Mt Vernon",
    "sg:classifiers":[
        {
            "category":"Shopping",
            "type":"Retail Goods"
        }
    ],
    "sg:phone":"+1 360 336 9717",
    "sg:postcode":"98273",
    "sg:province":"WA",
    "sg:tags":[
        "jewelry",
        "supply",
        "re",
        "coin",
        "dealer",
        "merchandise"
    ],
    "wof:name":"Stamp and Coin Place",
    "wof:placetype":"venue"
},
  "geometry": {"coordinates":[-122.337525,48.420102],"type":"Point"}
}