{
  "type": "Feature",
  "properties": {
    "addr:full":"205 N Conant Dr Eatonville WA 98328",
    "addr:housenumber":"205",
    "addr:postcode":"98328",
    "addr:street":"N Conant Dr",
    "iso:country":"US",
    "sg:address":"205 N Conant Dr",
    "sg:city":"Eatonville",
    "sg:classifiers":[
        {
            "category":"Shopping",
            "subcategory":"Clothing, Apparel, & Fashions",
            "type":"Retail Goods"
        }
    ],
    "sg:phone":"+1 253 381 4721",
    "sg:postcode":"98328",
    "sg:province":"WA",
    "wof:name":"Ready To Golf",
    "wof:placetype":"venue"
},
  "geometry": {"coordinates":[-122.277205,46.86974],"type":"Point"}
}