{
  "type": "Feature",
  "properties": {
    "addr:full":"13406 S Echo Lake Rd Snohomish WA 98296",
    "addr:housenumber":"13406",
    "addr:postcode":"98296",
    "addr:street":"S Echo Lake Rd",
    "iso:country":"US",
    "sg:address":"13406 S Echo Lake Rd",
    "sg:city":"Snohomish",
    "sg:classifiers":[
        {
            "category":"Shopping",
            "type":"Retail Goods"
        }
    ],
    "sg:phone":"+1 360 668 2494",
    "sg:postcode":"98296",
    "sg:province":"WA",
    "sg:tags":[
        "billing",
        "merchandise"
    ],
    "wof:name":"Word Shop",
    "wof:placetype":"venue"
},
  "geometry": {"coordinates":[-122.050127,47.783637],"type":"Point"}
}