{
  "type": "Feature",
  "properties": {
    "addr:full":"102 N Main St Bainbridge Island WA 98110",
    "addr:housenumber":"102",
    "addr:postcode":"98110",
    "addr:street":"N Main St",
    "iso:country":"US",
    "sg:address":"102 N Main St",
    "sg:city":"Bainbridge Island",
    "sg:classifiers":[
        {
            "category":"Communications",
            "subcategory":"Newspaper",
            "type":"Services"
        }
    ],
    "sg:phone":"+1 260 347 0400",
    "sg:postcode":"98110",
    "sg:province":"WA",
    "sg:tags":[
        "print",
        "medium"
    ],
    "sg:website":"www.thenewssunonline.com",
    "wof:name":"News-Sun the",
    "wof:placetype":"venue"
},
  "geometry": {"coordinates":[-122.334057,47.600176],"type":"Point"}
}