{
  "type": "Feature",
  "properties": {
    "addr:full":"19520 NE 159th St Woodinville WA 98077",
    "addr:housenumber":"19520",
    "addr:postcode":"98077",
    "addr:street":"Ne 159Th St",
    "iso:country":"US",
    "sg:address":"19520 NE 159th St",
    "sg:city":"Woodinville",
    "sg:classifiers":[
        {
            "category":"Banks & Credit Unions",
            "subcategory":"Investment Brokerage",
            "type":"Services"
        }
    ],
    "sg:phone":"+1 425 788 3547",
    "sg:postcode":"98077",
    "sg:province":"WA",
    "sg:tags":[
        "advisory"
    ],
    "wof:name":"KS Investments",
    "wof:placetype":"venue"
},
  "geometry": {"coordinates":[-122.076283,47.742701],"type":"Point"}
}