{
  "type": "Feature",
  "properties": {
    "iso:country":"US",
    "sg:address":"640 Jadwin Ave",
    "sg:city":"Richland",
    "sg:classifiers":[
        {
            "category":"Professional",
            "subcategory":"Management & Consulting",
            "type":"Services"
        }
    ],
    "sg:phone":"+1 509 946 0334",
    "sg:postcode":"99352",
    "sg:province":"WA",
    "wof:name":"Gem Technology International",
    "wof:placetype":"venue"
},
  "geometry": {"coordinates":[-119.275147,46.274325],"type":"Point"}
}