{
  "type": "Feature",
  "properties": {
    "addr:full":"134 E 7th St Port Angeles WA 98362",
    "addr:housenumber":"134",
    "addr:postcode":"98362",
    "addr:street":"E 7Th St",
    "iso:country":"US",
    "sg:address":"134 E 7th St",
    "sg:city":"Port Angeles",
    "sg:classifiers":[
        {
            "category":"Banks & Credit Unions",
            "subcategory":"Bank",
            "type":"Services"
        }
    ],
    "sg:phone":"+1 360 457 8571",
    "sg:postcode":"98362",
    "sg:province":"WA",
    "sg:tags":[
        "national",
        "commercial"
    ],
    "wof:name":"US Bank",
    "wof:placetype":"venue"
},
  "geometry": {"coordinates":[-123.43772199999999,48.113495],"type":"Point"}
}