{
  "type": "Feature",
  "properties": {
    "addr:full":"2290 Robertson Ave Richland WA 99354",
    "addr:housenumber":"2290",
    "addr:postcode":"99354",
    "addr:street":"Robertson Ave",
    "iso:country":"US",
    "sg:address":"2290 Robertson Ave",
    "sg:city":"Richland",
    "sg:classifiers":[
        {
            "category":"Shopping",
            "subcategory":"Computers & Home Electronics",
            "type":"Retail Goods"
        }
    ],
    "sg:phone":"+1 509 371 0600",
    "sg:postcode":"99354",
    "sg:province":"WA",
    "sg:tags":[
        "software"
    ],
    "wof:name":"Positive Software Co",
    "wof:placetype":"venue"
},
  "geometry": {"coordinates":[-119.292925,46.315608],"type":"Point"}
}