{
  "type": "Feature",
  "properties": {
    "addr:full":"1611 Ragan Rd Wapato WA 98951",
    "addr:housenumber":"1611",
    "addr:postcode":"98951",
    "addr:street":"Ragan Rd",
    "iso:country":"US",
    "sg:address":"1611 Ragan Rd",
    "sg:city":"Wapato",
    "sg:classifiers":[
        {
            "category":"Farming",
            "subcategory":"Orchard",
            "type":"Manufacturing & Wholesale Goods"
        }
    ],
    "sg:phone":"+1 509 877 4366",
    "sg:postcode":"98951",
    "sg:province":"WA",
    "sg:tags":[
        "fruit",
        "tree"
    ],
    "wof:name":"Carnevali Orchards",
    "wof:placetype":"venue"
},
  "geometry": {"coordinates":[-120.50232099999999,46.496042],"type":"Point"}
}