{
  "type": "Feature",
  "properties": {
    "addr:full":"3939 Old Olympic Hwy Port Angeles WA 98362",
    "addr:housenumber":"3939",
    "addr:postcode":"98362",
    "addr:street":"Old Olympic Hwy",
    "iso:country":"US",
    "sg:address":"3939 Old Olympic Hwy",
    "sg:city":"Port Angeles",
    "sg:classifiers":[
        {
            "category":"Building & Trades",
            "subcategory":"Construction",
            "type":"Services"
        }
    ],
    "sg:phone":"+1 360 457 6697",
    "sg:postcode":"98362",
    "sg:province":"WA",
    "sg:tags":[
        "general",
        "contractor"
    ],
    "wof:name":"Seaview Construction",
    "wof:placetype":"venue"
},
  "geometry": {"coordinates":[-123.223186,48.105255],"type":"Point"}
}