{
  "type": "Feature",
  "properties": {
    "addr:full":"11211 NW 6th Ave Vancouver WA 98685",
    "addr:housenumber":"11211",
    "addr:postcode":"98685",
    "addr:street":"Nw 6Th Ave",
    "iso:country":"US",
    "sg:address":"11211 NW 6th Ave",
    "sg:city":"Vancouver",
    "sg:classifiers":[
        {
            "category":"Real Estate",
            "subcategory":"Real Estate Agent",
            "type":"Services"
        }
    ],
    "sg:phone":"+1 360 574 6506",
    "sg:postcode":"98685",
    "sg:province":"WA",
    "wof:name":"Northwest Century Services",
    "wof:placetype":"venue"
},
  "geometry": {"coordinates":[-122.67606000000001,45.70237],"type":"Point"}
}