{
  "type": "Feature",
  "properties": {
    "addr:full":"6513 NE St Johns Rd Vancouver WA 98661",
    "addr:housenumber":"6513",
    "addr:postcode":"98661",
    "addr:street":"Ne St Johns Rd",
    "iso:country":"US",
    "sg:address":"6513 NE St Johns Rd",
    "sg:city":"Vancouver",
    "sg:classifiers":[
        {
            "category":"Retail",
            "subcategory":"Repair Shop",
            "type":"Services"
        }
    ],
    "sg:phone":"+1 360 693 9111",
    "sg:postcode":"98661",
    "sg:province":"WA",
    "sg:tags":[
        "body",
        "auto",
        "electrical"
    ],
    "wof:name":"Rogers Auto Body",
    "wof:placetype":"venue"
},
  "geometry": {"coordinates":[-122.636518,45.668855],"type":"Point"}
}