{
  "type": "Feature",
  "properties": {
    "addr:full":"2259 Jericho Rd Richland WA 99352",
    "addr:housenumber":"2259",
    "addr:postcode":"99352",
    "addr:street":"Jericho Rd",
    "iso:country":"US",
    "sg:address":"2259 Jericho Rd",
    "sg:city":"Richland",
    "sg:classifiers":[
        {
            "category":"Retail",
            "subcategory":"Auto Repair",
            "type":"Services"
        }
    ],
    "sg:phone":"+1 509 628 1500",
    "sg:postcode":"99352",
    "sg:province":"WA",
    "sg:tags":[
        "transmission"
    ],
    "wof:name":"American Transmission Inc",
    "wof:placetype":"venue"
},
  "geometry": {"coordinates":[-119.30358200000001,46.250353],"type":"Point"}
}