{
  "type": "Feature",
  "properties": {
    "addr:full":"865 Carlsborg Rd Sequim WA 98382",
    "addr:housenumber":"865",
    "addr:postcode":"98382",
    "addr:street":"Carlsborg Rd",
    "iso:country":"US",
    "sg:address":"865 Carlsborg Rd",
    "sg:city":"Sequim",
    "sg:classifiers":[
        {
            "category":"Professional",
            "subcategory":"Computer Services",
            "type":"Services"
        }
    ],
    "sg:phone":"+1 360 683 5760",
    "sg:postcode":"98382",
    "sg:province":"WA",
    "sg:tags":[
        "consultant",
        "designer"
    ],
    "sg:website":"www.sysconsrv.com",
    "wof:name":"Greywolf Networking Svc",
    "wof:placetype":"venue"
},
  "geometry": {"coordinates":[-123.172945,48.093421],"type":"Point"}
}