{
  "type": "Feature",
  "properties": {
    "addr:full":"1600 Currier St Ellensburg WA 98926",
    "addr:housenumber":"1600",
    "addr:postcode":"98926",
    "addr:street":"Currier St",
    "iso:country":"US",
    "sg:address":"1600 Currier St",
    "sg:city":"Ellensburg",
    "sg:classifiers":[
        {
            "category":"Recreation",
            "subcategory":"Arcade",
            "type":"Entertainment"
        }
    ],
    "sg:phone":"+1 509 925 5825",
    "sg:postcode":"98926",
    "sg:province":"WA",
    "sg:tags":[
        "casino"
    ],
    "wof:name":"Wild Goose Casino",
    "wof:placetype":"venue"
},
  "geometry": {"coordinates":[-120.58363799999999,47.010145],"type":"Point"}
}