{
  "type": "Feature",
  "properties": {
    "addr:full":"701 N 34th St Seattle WA 98103",
    "addr:housenumber":"701",
    "addr:postcode":"98103",
    "addr:street":"N 34Th St",
    "iso:country":"US",
    "sg:address":"701 N 34th St",
    "sg:city":"Seattle",
    "sg:classifiers":[
        {
            "category":"Restaurant",
            "type":"Food & Drink"
        }
    ],
    "sg:menulink":"http://www.allmenus.com/wa/seattle/139184-quiznos-sub/menu/",
    "sg:phone":"+1 206 632 2015",
    "sg:postcode":"98103",
    "sg:province":"WA",
    "sg:tags":[
        "wrap",
        "american",
        "sandwich"
    ],
    "wof:name":"Quiznos Sub",
    "wof:placetype":"venue"
},
  "geometry": {"coordinates":[-122.34868400000001,47.649392],"type":"Point"}
}