{
  "type": "Feature",
  "properties": {
    "addr:full":"186 Buena Vista Dr Colville WA 99114",
    "addr:housenumber":"186",
    "addr:postcode":"99114",
    "addr:street":"Buena Vista Dr",
    "iso:country":"US",
    "sg:address":"186 Buena Vista Dr",
    "sg:city":"Colville",
    "sg:classifiers":[
        {
            "category":"Retail",
            "subcategory":"Repair Shop",
            "type":"Services"
        },
        {
            "category":"Home & Garden",
            "subcategory":"Garden Supply",
            "type":"Retail Goods"
        }
    ],
    "sg:phone":"+1 509 684 2272",
    "sg:postcode":"99114",
    "sg:province":"WA",
    "sg:tags":[
        "lawn",
        "mower"
    ],
    "wof:name":"Colville Small Engine Service",
    "wof:placetype":"venue"
},
  "geometry": {"coordinates":[-117.91791000000001,48.561347],"type":"Point"}
}