{
  "type": "Feature",
  "properties": {
    "addr:full":"1022W W 7th Ave Spokane WA 99204",
    "addr:postcode":"99204",
    "addr:street":"W 7Th Ave",
    "iso:country":"US",
    "sg:address":"1022W W 7th Ave",
    "sg:city":"Spokane",
    "sg:classifiers":[
        {
            "category":"Professional",
            "subcategory":"Engineering",
            "type":"Services"
        },
        {
            "category":"Real Estate",
            "subcategory":"Architect",
            "type":"Services"
        }
    ],
    "sg:phone":"+1 509 624 5755",
    "sg:postcode":"99204",
    "sg:province":"WA",
    "sg:tags":[
        "architects'",
        "consulting",
        "specification",
        "builders'",
        "construction",
        "architectural",
        "engineer"
    ],
    "wof:name":"T Ac 1 Architects & Planning",
    "wof:placetype":"venue"
},
  "geometry": {"coordinates":[-117.426804,47.649339],"type":"Point"}
}