{
  "type": "Feature",
  "properties": {
    "addr:full":"4533 Rainier Ave S Seattle WA 98118",
    "addr:housenumber":"4533",
    "addr:postcode":"98118",
    "addr:street":"Rainier Ave S",
    "iso:country":"US",
    "sg:address":"4533 Rainier Ave S",
    "sg:city":"Seattle",
    "sg:classifiers":[
        {
            "category":"Building & Trades",
            "subcategory":"Cleaning & Sanitation",
            "type":"Services"
        }
    ],
    "sg:phone":"+1 206 721 4910",
    "sg:postcode":"98118",
    "sg:province":"WA",
    "sg:tags":[
        "cleaners-interior",
        "cleaning-industrial",
        "janitorial",
        "contractor"
    ],
    "wof:name":"Emerald City Janitorial Inc",
    "wof:placetype":"venue"
},
  "geometry": {"coordinates":[-122.28746599999999,47.561454],"type":"Point"}
}