{
  "type": "Feature",
  "properties": {
    "addr:full":"2933 East Hwy 101 Port Angeles WA 98362",
    "addr:housenumber":"2933",
    "addr:postcode":"98362",
    "addr:street":"East Hwy 101",
    "iso:country":"US",
    "sg:address":"2933 East Hwy 101",
    "sg:city":"Port Angeles",
    "sg:classifiers":[
        {
            "category":"Restaurant",
            "type":"Food & Drink"
        }
    ],
    "sg:menulink":"http://www.allmenus.com/wa/port-angeles/38782-sams-chinese-restaraunt--teriyaki/menu/",
    "sg:phone":"+1 360 565 8476",
    "sg:postcode":"98362",
    "sg:province":"WA",
    "sg:tags":[
        "asian",
        "chinese"
    ],
    "wof:name":"Sam's Chinese Restaraunt & Teriyaki",
    "wof:placetype":"venue"
},
  "geometry": {"coordinates":[-123.36882900000001,48.105857],"type":"Point"}
}