{
  "type": "Feature",
  "properties": {
    "addr:full":"8418 Renton Ave S Seattle WA 98118",
    "addr:housenumber":"8418",
    "addr:postcode":"98118",
    "addr:street":"Renton Ave S",
    "iso:country":"US",
    "sg:address":"8418 Renton Ave S",
    "sg:city":"Seattle",
    "sg:classifiers":[
        {
            "category":"Building & Trades",
            "subcategory":"Construction",
            "type":"Services"
        }
    ],
    "sg:phone":"+1 206 721 1312",
    "sg:postcode":"98118",
    "sg:province":"WA",
    "sg:tags":[
        "general",
        "contractor"
    ],
    "wof:name":"All Phaze Construction Inc",
    "wof:placetype":"venue"
},
  "geometry": {"coordinates":[-122.27687299999999,47.526148],"type":"Point"}
}