{
  "type": "Feature",
  "properties": {
    "addr:full":"13711 34th Ave S Seattle WA 98168",
    "addr:housenumber":"13711",
    "addr:postcode":"98168",
    "addr:street":"34Th Ave S",
    "iso:country":"US",
    "sg:address":"13711 34th Ave S",
    "sg:city":"Seattle",
    "sg:classifiers":[
        {
            "category":"Building & Trades",
            "subcategory":"Construction",
            "type":"Services"
        }
    ],
    "sg:phone":"+1 206 433 8520",
    "sg:postcode":"98168",
    "sg:province":"WA",
    "sg:tags":[
        "house"
    ],
    "wof:name":"Ian Construction Co",
    "wof:placetype":"venue"
},
  "geometry": {"coordinates":[-122.288279,47.479988],"type":"Point"}
}