{
  "type": "Feature",
  "properties": {
    "addr:full":"2203 Elm St Bellingham WA 98225",
    "addr:housenumber":"2203",
    "addr:postcode":"98225",
    "addr:street":"Elm St",
    "iso:country":"US",
    "sg:address":"2203 Elm St",
    "sg:city":"Bellingham",
    "sg:classifiers":[
        {
            "category":"Banks & Credit Unions",
            "subcategory":"Investment Brokerage",
            "type":"Services"
        }
    ],
    "sg:phone":"+1 360 756 1511",
    "sg:postcode":"98225",
    "sg:province":"WA",
    "sg:tags":[
        "advisory"
    ],
    "wof:name":"Roberts Financial Services",
    "wof:placetype":"venue"
},
  "geometry": {"coordinates":[-122.488471,48.760599],"type":"Point"}
}