{
  "type": "Feature",
  "properties": {
    "addr:full":"17471 Bow Hill Rd Bow WA 98232",
    "addr:housenumber":"17471",
    "addr:postcode":"98232",
    "addr:street":"Bow Hill Rd",
    "iso:country":"US",
    "sg:address":"17471 Bow Hill Rd",
    "sg:city":"Bow",
    "sg:classifiers":[
        {
            "category":"Freight",
            "type":"Transportation"
        }
    ],
    "sg:phone":"+1 360 766 7050",
    "sg:postcode":"98232",
    "sg:province":"WA",
    "sg:tags":[
        "operator",
        "local",
        "trucking"
    ],
    "wof:name":"Jay R Harvey Enterprises Inc",
    "wof:placetype":"venue"
},
  "geometry": {"coordinates":[-122.367971,48.559132],"type":"Point"}
}