{
  "type": "Feature",
  "properties": {
    "addr:full":"2802 Rainier Ave Seattle WA 98144",
    "addr:housenumber":"2802",
    "addr:postcode":"98144",
    "addr:street":"Rainier Ave",
    "iso:country":"US",
    "sg:address":"2802 Rainier Ave",
    "sg:city":"Seattle",
    "sg:classifiers":[
        {
            "category":"Autos & Motor Vehicles",
            "subcategory":"Fuel & Gas Station",
            "type":"Retail Goods"
        }
    ],
    "sg:phone":"+1 206 722 6805",
    "sg:postcode":"98144",
    "sg:province":"WA",
    "sg:tags":[
        "oil"
    ],
    "wof:name":"Chevron",
    "wof:placetype":"venue"
},
  "geometry": {"coordinates":[-122.297466,47.577575],"type":"Point"}
}