{
  "type": "Feature",
  "properties": {
    "iso:country":"US",
    "sg:address":"519 W Gordon Ave",
    "sg:city":"Spokane",
    "sg:classifiers":[
        {
            "category":"Professional",
            "type":"Services"
        }
    ],
    "sg:phone":"+1 509 326 2005",
    "sg:postcode":"99205",
    "sg:province":"WA",
    "wof:name":"Wendy Acosta",
    "wof:placetype":"venue"
},
  "geometry": {"coordinates":[-117.418712,47.690748],"type":"Point"}
}