{
  "type": "Feature",
  "properties": {
    "addr:full":"125 Boren Ave N Seattle WA 98109",
    "addr:housenumber":"125",
    "addr:postcode":"98109",
    "addr:street":"Boren Ave N",
    "iso:country":"US",
    "sg:address":"125 Boren Ave N",
    "sg:city":"Seattle",
    "sg:classifiers":[
        {
            "category":"Restaurant",
            "type":"Food & Drink"
        }
    ],
    "sg:menulink":"http://www.allmenus.com/wa/seattle/3426-13-coins-restaurant/menu/",
    "sg:phone":"+1 206 682 2513",
    "sg:postcode":"98109",
    "sg:province":"WA",
    "sg:tags":[
        "american"
    ],
    "wof:name":"13 Coins Restaurant",
    "wof:placetype":"venue"
},
  "geometry": {"coordinates":[-122.33592400000001,47.618826],"type":"Point"}
}