{
  "type": "Feature",
  "properties": {
    "addr:full":"16112 Lindsay Rd SE Yelm WA 98597",
    "addr:housenumber":"16112",
    "addr:postcode":"98597",
    "addr:street":"Lindsay Rd Se Yelm",
    "iso:country":"US",
    "sg:address":"16112 Lindsay Rd SE",
    "sg:city":"Yelm",
    "sg:classifiers":[
        {
            "category":"Shopping",
            "subcategory":"Hobbies, Toys, & Games",
            "type":"Retail Goods"
        }
    ],
    "sg:phone":"+1 360 894 7513",
    "sg:postcode":"98597",
    "sg:province":"WA",
    "sg:tags":[
        "craft"
    ],
    "wof:name":"Sassy's Stuff",
    "wof:placetype":"venue"
},
  "geometry": {"coordinates":[-122.581299,46.853093],"type":"Point"}
}