{
  "type": "Feature",
  "properties": {
    "addr:full":"9264 57th Ave S Seattle WA 98118",
    "addr:housenumber":"9264",
    "addr:postcode":"98118",
    "addr:street":"57Th Ave S",
    "iso:country":"US",
    "sg:address":"9264 57th Ave S",
    "sg:city":"Seattle",
    "sg:classifiers":[
        {
            "category":"Education",
            "subcategory":"Dance Studio",
            "type":"Public Place"
        }
    ],
    "sg:phone":"+1 206 721 3133",
    "sg:postcode":"98118",
    "sg:province":"WA",
    "sg:tags":[
        "instruction",
        "dancing"
    ],
    "wof:name":"Rainier Dance Center",
    "wof:placetype":"venue"
},
  "geometry": {"coordinates":[-122.261518,47.519952],"type":"Point"}
}