{
  "type": "Feature",
  "properties": {
    "addr:full":"1355 Elm St Clarkston WA 99403",
    "addr:housenumber":"1355",
    "addr:postcode":"99403",
    "addr:street":"Elm St",
    "iso:country":"US",
    "sg:address":"1355 Elm St",
    "sg:city":"Clarkston",
    "sg:classifiers":[
        {
            "category":"Organizations",
            "subcategory":"Religious Organization",
            "type":"Services"
        }
    ],
    "sg:phone":"+1 509 758 2637",
    "sg:postcode":"99403",
    "sg:province":"WA",
    "sg:tags":[
        "place",
        "worship",
        "church"
    ],
    "sg:website":"http://www.pcg.org",
    "wof:name":"Pentacostal Church Of God",
    "wof:placetype":"venue"
},
  "geometry": {"coordinates":[-117.061736,46.414483],"type":"Point"}
}