{
  "type": "Feature",
  "properties": {
    "addr:full":"8246 S 194th St Kent WA 98032",
    "addr:housenumber":"8246",
    "addr:postcode":"98032",
    "addr:street":"S 194Th St",
    "iso:country":"US",
    "sg:address":"8246 S 194th St",
    "sg:city":"Kent",
    "sg:classifiers":[
        {
            "category":"Manufacturing",
            "subcategory":"Buildings",
            "type":"Manufacturing & Wholesale Goods"
        },
        {
            "category":"Home & Garden",
            "subcategory":"Building Materials",
            "type":"Retail Goods"
        },
        {
            "category":"Building & Trades",
            "subcategory":"Construction",
            "type":"Services"
        }
    ],
    "sg:phone":"+1 253 395 1211",
    "sg:postcode":"98032",
    "sg:province":"WA",
    "sg:tags":[
        "insulation",
        "builder",
        "lumber-used",
        "contractor"
    ],
    "sg:website":"http://www.uresco.com",
    "wof:name":"Uresco Construction Mils, Inc.",
    "wof:placetype":"venue"
},
  "geometry": {"coordinates":[-122.22896299999999,47.428227],"type":"Point"}
}