{
  "type": "Feature",
  "properties": {
    "addr:full":"800 W Columbia Dr Kennewick WA 99336",
    "addr:housenumber":"800",
    "addr:postcode":"99336",
    "addr:street":"W Columbia Dr",
    "iso:country":"US",
    "sg:address":"800 W Columbia Dr",
    "sg:city":"Kennewick",
    "sg:classifiers":[
        {
            "category":"Autos & Motor Vehicles",
            "subcategory":"Automobile Sales",
            "type":"Retail Goods"
        }
    ],
    "sg:phone":"+1 509 585 5021",
    "sg:postcode":"99336",
    "sg:province":"WA",
    "sg:tags":[
        "car",
        "dealer"
    ],
    "wof:name":"Paradise Auto Sales",
    "wof:placetype":"venue"
},
  "geometry": {"coordinates":[-119.130906,46.216848],"type":"Point"}
}