{
  "type": "Feature",
  "properties": {
    "addr:full":"3601 Colby Ave Everett WA 98201",
    "addr:housenumber":"3601",
    "addr:postcode":"98201",
    "addr:street":"Colby Ave",
    "iso:country":"US",
    "sg:address":"3601 Colby Ave",
    "sg:city":"Everett",
    "sg:classifiers":[
        {
            "category":"Professional",
            "subcategory":"Lawyer & Legal Services",
            "type":"Services"
        }
    ],
    "sg:phone":"+1 425 259 9000",
    "sg:postcode":"98201",
    "sg:province":"WA",
    "wof:name":"Robinett Martin H PS",
    "wof:placetype":"venue"
},
  "geometry": {"coordinates":[-122.208185,47.968627],"type":"Point"}
}