{
  "type": "Feature",
  "properties": {
    "addr:full":"813 Academy St Sumner WA 98390",
    "addr:housenumber":"813",
    "addr:postcode":"98390",
    "addr:street":"Academy St",
    "iso:country":"US",
    "sg:address":"813 Academy St",
    "sg:city":"Sumner",
    "sg:classifiers":[
        {
            "category":"Restaurant",
            "type":"Food & Drink"
        }
    ],
    "sg:phone":"+1 253 826 4681",
    "sg:postcode":"98390",
    "sg:province":"WA",
    "sg:tags":[
        "shop",
        "coffee"
    ],
    "wof:name":"Midtown Station Espresso",
    "wof:placetype":"venue"
},
  "geometry": {"coordinates":[-122.243118,47.201116],"type":"Point"}
}