{
  "type": "Feature",
  "properties": {
    "addr:full":"26050 129th Ave SE Kent WA 98030",
    "addr:housenumber":"26050",
    "addr:postcode":"98030",
    "addr:street":"129Th Ave Se",
    "iso:country":"US",
    "sg:address":"26050 129th Ave SE",
    "sg:city":"Kent",
    "sg:classifiers":[
        {
            "category":"Professional",
            "subcategory":"Art Services",
            "type":"Services"
        }
    ],
    "sg:phone":"+1 253 639 4365",
    "sg:postcode":"98030",
    "sg:province":"WA",
    "sg:tags":[
        "commercial",
        "design"
    ],
    "wof:name":"Red Blaze Art",
    "wof:placetype":"venue"
},
  "geometry": {"coordinates":[-122.16965999999999,47.368238],"type":"Point"}
}