{
  "type": "Feature",
  "properties": {
    "addr:full":"5920 100th St SW Ste 11 Lakewood WA 98499",
    "addr:housenumber":"5920",
    "addr:postcode":"98499",
    "addr:street":"100Th St Sw Ste 11",
    "iso:country":"US",
    "sg:address":"5920 100th St SW Ste 11",
    "sg:city":"Lakewood",
    "sg:classifiers":[
        {
            "category":"Health Services",
            "subcategory":"Doctor",
            "type":"Services"
        }
    ],
    "sg:phone":"+1 253 584 7240",
    "sg:postcode":"98499",
    "sg:province":"WA",
    "sg:tags":[
        "podiatrist"
    ],
    "wof:name":"Alenick Mark A DPM",
    "wof:placetype":"venue"
},
  "geometry": {"coordinates":[-122.51599899999999,47.166698],"type":"Point"}
}