{
  "type": "Feature",
  "properties": {
    "addr:full":"44118 State Rte 161 Eatonville WA 98328",
    "addr:housenumber":"44118",
    "addr:postcode":"98328",
    "addr:street":"State Rte 161",
    "iso:country":"US",
    "sg:address":"44118 State Rte 161",
    "sg:city":"Eatonville",
    "sg:classifiers":[
        {
            "category":"Banks & Credit Unions",
            "subcategory":"Investment Brokerage",
            "type":"Services"
        }
    ],
    "sg:phone":"+1 360 832 3902",
    "sg:postcode":"98328",
    "sg:province":"WA",
    "sg:tags":[
        "security"
    ],
    "wof:name":"F V Antquera Associates",
    "wof:placetype":"venue"
},
  "geometry": {"coordinates":[-122.28615499999999,46.854778],"type":"Point"}
}