{
  "type": "Feature",
  "properties": {
    "addr:full":"5007 NE St Johns Rd Vancouver WA 98661",
    "addr:housenumber":"5007",
    "addr:postcode":"98661",
    "addr:street":"Ne St Johns Rd",
    "iso:country":"US",
    "sg:address":"5007 NE St Johns Rd",
    "sg:city":"Vancouver",
    "sg:classifiers":[
        {
            "category":"Home & Garden",
            "subcategory":"Building Materials",
            "type":"Retail Goods"
        },
        {
            "category":"Building & Trades",
            "subcategory":"Construction",
            "type":"Services"
        },
        {
            "category":"Manufacturing",
            "subcategory":"Building Materials",
            "type":"Manufacturing & Wholesale Goods"
        }
    ],
    "sg:phone":"+1 360 694 7333",
    "sg:postcode":"98661",
    "sg:province":"WA",
    "sg:tags":[
        "altering",
        "accessory",
        "window",
        "doors",
        "frames",
        "contractor",
        "remodeling"
    ],
    "wof:name":"L & L Design & Remodeling",
    "wof:placetype":"venue"
},
  "geometry": {"coordinates":[-122.636009,45.65811],"type":"Point"}
}