{
  "type": "Feature",
  "properties": {
    "addr:full":"3711 NE 45th St Seattle WA 98105",
    "addr:housenumber":"3711",
    "addr:postcode":"98105",
    "addr:street":"Ne 45Th St",
    "iso:country":"US",
    "sg:address":"3711 NE 45th St",
    "sg:city":"Seattle",
    "sg:classifiers":[
        {
            "category":"Food & Beverages",
            "subcategory":"Liquor & Beverages",
            "type":"Retail Goods"
        }
    ],
    "sg:phone":"+1 206 708 1537",
    "sg:postcode":"98105",
    "sg:province":"WA",
    "sg:tags":[
        "beer",
        "spirit",
        "wine"
    ],
    "wof:name":"Laurelhurst Wine Merchants",
    "wof:placetype":"venue"
},
  "geometry": {"coordinates":[-122.287691,47.660847],"type":"Point"}
}