{
  "type": "Feature",
  "properties": {
    "iso:country":"US",
    "sg:address":"5011 S Dawson St",
    "sg:city":"Seattle",
    "sg:classifiers":[
        {
            "category":"Restaurant",
            "type":"Food & Drink"
        }
    ],
    "sg:phone":"+1 206 723 0445",
    "sg:postcode":"98118",
    "sg:province":"WA",
    "sg:tags":[
        "eating"
    ],
    "wof:name":"Pizza Rio",
    "wof:placetype":"venue"
},
  "geometry": {"coordinates":[-122.269918,47.554773],"type":"Point"}
}