{
  "type": "Feature",
  "properties": {
    "addr:full":"815 National Ave S Bremerton WA 98312",
    "addr:housenumber":"815",
    "addr:postcode":"98312",
    "addr:street":"National Ave S",
    "iso:country":"US",
    "sg:address":"815 National Ave S",
    "sg:city":"Bremerton",
    "sg:classifiers":[
        {
            "category":"Retail",
            "subcategory":"Auto Repair",
            "type":"Services"
        }
    ],
    "sg:phone":"+1 360 373 3210",
    "sg:postcode":"98312",
    "sg:province":"WA",
    "sg:tags":[
        "body",
        "automobile",
        "painting"
    ],
    "wof:name":"Long's Auto Rebuild Inc",
    "wof:placetype":"venue"
},
  "geometry": {"coordinates":[-122.66789799999999,47.554201],"type":"Point"}
}