{
  "type": "Feature",
  "properties": {
    "iso:country":"US",
    "sg:address":"15031 Military Rd S",
    "sg:city":"Seattle",
    "sg:classifiers":[
        {
            "category":"Freight",
            "type":"Transportation"
        }
    ],
    "sg:phone":"+1 206 618 0494",
    "sg:postcode":"98188",
    "sg:province":"WA",
    "sg:tags":[
        "operator",
        "local",
        "trucking"
    ],
    "wof:name":"Roble Musse Trucking",
    "wof:placetype":"venue"
},
  "geometry": {"coordinates":[-122.288935,47.467217],"type":"Point"}
}