{
  "type": "Feature",
  "properties": {
    "addr:full":"7522 N Division St Spokane WA 99208",
    "addr:housenumber":"7522",
    "addr:postcode":"99208",
    "addr:street":"N Division St",
    "iso:country":"US",
    "sg:address":"7522 N Division St",
    "sg:city":"Spokane",
    "sg:classifiers":[
        {
            "category":"Restaurant",
            "type":"Food & Drink"
        }
    ],
    "sg:phone":"+1 509 482 6100",
    "sg:postcode":"99208",
    "sg:province":"WA",
    "sg:tags":[
        "lounge",
        "cocktail"
    ],
    "wof:name":"Onion The",
    "wof:placetype":"venue"
},
  "geometry": {"coordinates":[-117.41124000000001,47.725879],"type":"Point"}
}