{
  "type": "Feature",
  "properties": {
    "addr:full":"23824 3rd Ave SE Bothell WA 98021",
    "addr:housenumber":"23824",
    "addr:postcode":"98021",
    "addr:street":"3Rd Ave Se",
    "iso:country":"US",
    "sg:address":"23824 3rd Ave SE",
    "sg:city":"Bothell",
    "sg:classifiers":[
        {
            "category":"Communications",
            "subcategory":"Film & Video Production",
            "type":"Services"
        }
    ],
    "sg:phone":"+1 425 483 0500",
    "sg:postcode":"98021",
    "sg:province":"WA",
    "sg:tags":[
        "motion"
    ],
    "wof:name":"Heck Yes Productions",
    "wof:placetype":"venue"
},
  "geometry": {"coordinates":[-122.227732,47.781934],"type":"Point"}
}