{
  "type": "Feature",
  "properties": {
    "addr:full":"7704 Saddle Ct SE Olympia WA 98501",
    "addr:housenumber":"7704",
    "addr:postcode":"98501",
    "addr:street":"Saddle Ct Se",
    "iso:country":"US",
    "sg:address":"7704 Saddle Ct SE",
    "sg:city":"Olympia",
    "sg:classifiers":[
        {
            "category":"Professional",
            "subcategory":"Management & Consulting",
            "type":"Services"
        }
    ],
    "sg:phone":"+1 360 357 4435",
    "sg:postcode":"98501",
    "sg:province":"WA",
    "sg:tags":[
        "business"
    ],
    "wof:name":"Judith L Hartman",
    "wof:placetype":"venue"
},
  "geometry": {"coordinates":[-122.876745,46.977412],"type":"Point"}
}