{
  "type": "Feature",
  "properties": {
    "addr:full":"808 W Holbeck Dr Stanwood WA 98282",
    "addr:housenumber":"808",
    "addr:postcode":"98282",
    "addr:street":"W Holbeck Dr",
    "iso:country":"US",
    "sg:address":"808 W Holbeck Dr",
    "sg:city":"Stanwood",
    "sg:classifiers":[
        {
            "category":"Professional",
            "type":"Services"
        }
    ],
    "sg:phone":"+1 360 387 0536",
    "sg:postcode":"98282",
    "sg:province":"WA",
    "sg:tags":[
        "gallery"
    ],
    "wof:name":"John Ebner Watercolors",
    "wof:placetype":"venue"
},
  "geometry": {"coordinates":[-122.52776,48.237399],"type":"Point"}
}