{
  "type": "Feature",
  "properties": {
    "iso:country":"US",
    "sg:address":"1148 NW Leary Way",
    "sg:city":"Seattle",
    "sg:classifiers":[
        {
            "category":"Professional",
            "subcategory":"Art Services",
            "type":"Services"
        }
    ],
    "sg:phone":"+1 206 781 3261",
    "sg:postcode":"98107",
    "sg:province":"WA",
    "sg:tags":[
        "artist"
    ],
    "wof:name":"Mary Iverson",
    "wof:placetype":"venue"
},
  "geometry": {"coordinates":[-122.37156400000001,47.66373],"type":"Point"}
}