{
  "type": "Feature",
  "properties": {
    "addr:full":"8611 312th St S Roy WA 98580",
    "addr:housenumber":"8611",
    "addr:postcode":"98580",
    "addr:street":"312Th St S",
    "iso:country":"US",
    "sg:address":"8611 312th St S",
    "sg:city":"Roy",
    "sg:classifiers":[
        {
            "category":"Retail",
            "subcategory":"Auto Repair",
            "type":"Services"
        }
    ],
    "sg:phone":"+1 360 456 0344",
    "sg:postcode":"98580",
    "sg:province":"WA",
    "sg:tags":[
        "general"
    ],
    "wof:name":"High Times Rv",
    "wof:placetype":"venue"
},
  "geometry": {"coordinates":[-122.54385600000001,46.974098],"type":"Point"}
}