{
  "type": "Feature",
  "properties": {
    "addr:full":"1225 Narcisse Creek Rd Colville WA 99114",
    "addr:housenumber":"1225",
    "addr:postcode":"99114",
    "addr:street":"Narcisse Creek Rd",
    "iso:country":"US",
    "sg:address":"1225 Narcisse Creek Rd",
    "sg:city":"Colville",
    "sg:classifiers":[
        {
            "category":"Manufacturing",
            "subcategory":"Lumber",
            "type":"Manufacturing & Wholesale Goods"
        }
    ],
    "sg:phone":"+1 509 684 3906",
    "sg:postcode":"99114",
    "sg:province":"WA",
    "sg:tags":[
        "logging"
    ],
    "wof:name":"Bear Creek Tree Farms",
    "wof:placetype":"venue"
},
  "geometry": {"coordinates":[-117.732246,48.484796],"type":"Point"}
}