{
  "type": "Feature",
  "properties": {
    "addr:full":"1102 W Broadway Ave Moses Lake WA 98837",
    "addr:housenumber":"1102",
    "addr:postcode":"98837",
    "addr:street":"W Broadway Ave",
    "iso:country":"US",
    "sg:address":"1102 W Broadway Ave",
    "sg:city":"Moses Lake",
    "sg:classifiers":[
        {
            "category":"Shopping",
            "type":"Retail Goods"
        }
    ],
    "sg:phone":"+1 509 766 6728",
    "sg:postcode":"98837",
    "sg:province":"WA",
    "sg:tags":[
        "ice"
    ],
    "wof:name":"Artic-Land Ice",
    "wof:placetype":"venue"
},
  "geometry": {"coordinates":[-119.292107,47.122452],"type":"Point"}
}