{
  "type": "Feature",
  "properties": {
    "addr:full":"21424 4th Ave W Bothell WA 98021",
    "addr:housenumber":"21424",
    "addr:postcode":"98021",
    "addr:street":"4Th Ave W",
    "iso:country":"US",
    "sg:address":"21424 4th Ave W",
    "sg:city":"Bothell",
    "sg:classifiers":[
        {
            "category":"Building & Trades",
            "subcategory":"Construction",
            "type":"Services"
        }
    ],
    "sg:phone":"+1 425 766 4104",
    "sg:postcode":"98021",
    "sg:province":"WA",
    "sg:tags":[
        "concrete",
        "contractor"
    ],
    "wof:name":"Precision Wall Systems LLC",
    "wof:placetype":"venue"
},
  "geometry": {"coordinates":[-122.238314,47.803662],"type":"Point"}
}