{
  "type": "Feature",
  "properties": {
    "addr:full":"2414 Milton Way Milton WA 98354",
    "addr:housenumber":"2414",
    "addr:postcode":"98354",
    "addr:street":"Milton Way",
    "iso:country":"US",
    "sg:address":"2414 Milton Way",
    "sg:city":"Milton",
    "sg:classifiers":[
        {
            "category":"Social Services",
            "subcategory":"Child Care",
            "type":"Services"
        }
    ],
    "sg:phone":"+1 253 943 3576",
    "sg:postcode":"98354",
    "sg:province":"WA",
    "wof:name":"Children's Character Club",
    "wof:placetype":"venue"
},
  "geometry": {"coordinates":[-122.303945,47.250178],"type":"Point"}
}