{
  "type": "Feature",
  "properties": {
    "addr:full":"1515 NW Leary Way Seattle WA 98107",
    "addr:housenumber":"1515",
    "addr:postcode":"98107",
    "addr:street":"Nw Leary Way",
    "iso:country":"US",
    "sg:address":"1515 NW Leary Way",
    "sg:city":"Seattle",
    "sg:classifiers":[
        {
            "category":"Manufacturing",
            "subcategory":"Food",
            "type":"Manufacturing & Wholesale Goods"
        }
    ],
    "sg:phone":"+1 206 783 1533",
    "sg:postcode":"98107",
    "sg:province":"WA",
    "sg:tags":[
        "brewer"
    ],
    "wof:name":"Beaver Brew",
    "wof:placetype":"venue"
},
  "geometry": {"coordinates":[-122.378497,47.663697],"type":"Point"}
}