{
  "type": "Feature",
  "properties": {
    "addr:full":"20200 10th Pl SW Seattle WA 98166",
    "addr:housenumber":"20200",
    "addr:postcode":"98166",
    "addr:street":"10Th Pl Sw",
    "iso:country":"US",
    "sg:address":"20200 10th Pl SW",
    "sg:city":"Seattle",
    "sg:classifiers":[
        {
            "category":"Banks & Credit Unions",
            "subcategory":"Investment Brokerage",
            "type":"Services"
        }
    ],
    "sg:phone":"+1 206 870 2286",
    "sg:postcode":"98166",
    "sg:province":"WA",
    "sg:tags":[
        "advisory"
    ],
    "wof:name":"Investco Financial Corp",
    "wof:placetype":"venue"
},
  "geometry": {"coordinates":[-122.347813,47.419531],"type":"Point"}
}