{
  "type": "Feature",
  "properties": {
    "addr:full":"20527 76th Ave SE Snohomish WA 98296",
    "addr:housenumber":"20527",
    "addr:postcode":"98296",
    "addr:street":"76Th Ave Se",
    "iso:country":"US",
    "sg:address":"20527 76th Ave SE",
    "sg:city":"Snohomish",
    "sg:classifiers":[
        {
            "category":"Home & Garden",
            "subcategory":"Furniture",
            "type":"Retail Goods"
        }
    ],
    "sg:phone":"+1 360 652 2721",
    "sg:postcode":"98296",
    "sg:province":"WA",
    "sg:tags":[
        "maker",
        "cabinet"
    ],
    "wof:name":"Kens Kustom Kabinets Inc",
    "wof:placetype":"venue"
},
  "geometry": {"coordinates":[-122.13062600000001,47.811321],"type":"Point"}
}