{
  "type": "Feature",
  "properties": {
    "addr:full":"2212 92nd Ave NE Clyde Hill WA 98004",
    "addr:housenumber":"2212",
    "addr:postcode":"98004",
    "addr:street":"92Nd Ave Ne",
    "iso:country":"US",
    "sg:address":"2212 92nd Ave NE",
    "sg:city":"Clyde Hill",
    "sg:classifiers":[
        {
            "category":"Home & Garden",
            "subcategory":"Garden Supply",
            "type":"Retail Goods"
        }
    ],
    "sg:phone":"+1 425 454 0125",
    "sg:postcode":"98004",
    "sg:province":"WA",
    "sg:tags":[
        "lawn"
    ],
    "wof:name":"Diggit Garden Tools",
    "wof:placetype":"venue"
},
  "geometry": {"coordinates":[-122.217765,47.631819],"type":"Point"}
}