{
  "type": "Feature",
  "properties": {
    "addr:full":"1423 N Monroe St Spokane WA 99201",
    "addr:housenumber":"1423",
    "addr:postcode":"99201",
    "addr:street":"N Monroe St",
    "iso:country":"US",
    "sg:address":"1423 N Monroe St",
    "sg:city":"Spokane",
    "sg:classifiers":[
        {
            "category":"Real Estate",
            "subcategory":"Real Estate Agent",
            "type":"Services"
        }
    ],
    "sg:phone":"+1 509 325 5070",
    "sg:postcode":"99201",
    "sg:province":"WA",
    "wof:name":"Simpson Realty Inc",
    "wof:placetype":"venue"
},
  "geometry": {"coordinates":[-117.42675699999999,47.671019],"type":"Point"}
}