{
  "type": "Feature",
  "properties": {
    "addr:full":"426 S College Ave College Place WA 99324",
    "addr:housenumber":"426",
    "addr:postcode":"99324",
    "addr:street":"S College Ave",
    "iso:country":"US",
    "sg:address":"426 S College Ave",
    "sg:city":"College Place",
    "sg:classifiers":[
        {
            "category":"Organizations",
            "subcategory":"Religious Organization",
            "type":"Services"
        }
    ],
    "sg:phone":"+1 509 522 4890",
    "sg:postcode":"99324",
    "sg:province":"WA",
    "wof:name":"Foundation of Our Faith",
    "wof:placetype":"venue"
},
  "geometry": {"coordinates":[-118.388608,46.04546],"type":"Point"}
}