{
  "type": "Feature",
  "properties": {
    "addr:full":"51 Ellis St Raymond WA 98577",
    "addr:housenumber":"51",
    "addr:postcode":"98577",
    "addr:street":"Ellis St Raymond",
    "iso:country":"US",
    "sg:address":"51 Ellis St",
    "sg:city":"Raymond",
    "sg:classifiers":[
        {
            "category":"Manufacturing",
            "subcategory":"Lumber",
            "type":"Manufacturing & Wholesale Goods"
        }
    ],
    "sg:phone":"+1 360 942 2442",
    "sg:postcode":"98577",
    "sg:province":"WA",
    "sg:tags":[
        "mill"
    ],
    "sg:website":"www.weyerhaeuser.com",
    "wof:name":"Weyerhaeuser Company",
    "wof:placetype":"venue"
},
  "geometry": {"coordinates":[-123.736887,46.687896],"type":"Point"}
}