{
  "type": "Feature",
  "properties": {
    "addr:full":"12126 SE 280th St Kent WA 98030",
    "addr:postcode":"12126;98030",
    "addr:street":"Se 280Th St",
    "iso:country":"US",
    "sg:address":"12126 SE 280th St",
    "sg:city":"Kent",
    "sg:classifiers":[
        {
            "category":"Shopping",
            "type":"Retail Goods"
        }
    ],
    "sg:phone":"+1 253 630 5685",
    "sg:postcode":"98030",
    "sg:province":"WA",
    "sg:tags":[
        "trophy",
        "medal",
        "award"
    ],
    "wof:name":"Bernard's Awards & High Tech",
    "wof:placetype":"venue"
},
  "geometry": {"coordinates":[-122.177859,47.351116],"type":"Point"}
}