{
  "type": "Feature",
  "properties": {
    "addr:full":"16401 10th Ave SW Seattle WA 98166",
    "addr:housenumber":"16401",
    "addr:postcode":"98166",
    "addr:street":"10Th Ave Sw",
    "iso:country":"US",
    "sg:address":"16401 10th Ave SW",
    "sg:city":"Seattle",
    "sg:classifiers":[
        {
            "category":"Building & Trades",
            "subcategory":"Cleaning & Sanitation",
            "type":"Services"
        }
    ],
    "sg:phone":"+1 206 246 2951",
    "sg:postcode":"98166",
    "sg:province":"WA",
    "sg:tags":[
        "maintenance"
    ],
    "wof:name":"Clean As A Whistle",
    "wof:placetype":"venue"
},
  "geometry": {"coordinates":[-122.347324,47.454177],"type":"Point"}
}