{
  "type": "Feature",
  "properties": {
    "addr:full":"19 Coulee Blvd Electric City WA 99123",
    "addr:housenumber":"19",
    "addr:postcode":"99123",
    "addr:street":"Coulee Blvd Electric",
    "iso:country":"US",
    "sg:address":"19 Coulee Blvd",
    "sg:city":"Electric City",
    "sg:classifiers":[
        {
            "category":"Building & Trades",
            "subcategory":"Construction",
            "type":"Services"
        }
    ],
    "sg:phone":"+1 509 633 1664",
    "sg:postcode":"99123",
    "sg:province":"WA",
    "sg:tags":[
        "general",
        "contractor"
    ],
    "wof:name":"A J Gerard Building Co",
    "wof:placetype":"venue"
},
  "geometry": {"coordinates":[-119.03916,47.931911],"type":"Point"}
}