{
  "type": "Feature",
  "properties": {
    "addr:full":"4028 Tacoma Mall Blvd Tacoma WA 98409",
    "addr:housenumber":"4028",
    "addr:postcode":"98409",
    "addr:street":"Tacoma Mall Blvd",
    "iso:country":"US",
    "sg:address":"4028 Tacoma Mall Blvd",
    "sg:city":"Tacoma",
    "sg:classifiers":[
        {
            "category":"Professional",
            "subcategory":"Computer Services",
            "type":"Services"
        }
    ],
    "sg:phone":"+1 253 476 5804",
    "sg:postcode":"98409",
    "sg:province":"WA",
    "wof:name":"Comp USA",
    "wof:placetype":"venue"
},
  "geometry": {"coordinates":[-122.46790799999999,47.220949],"type":"Point"}
}