{
  "type": "Feature",
  "properties": {
    "addr:full":"18707 139th Ave NE Woodinville WA 98072",
    "addr:housenumber":"18707",
    "addr:postcode":"98072",
    "addr:street":"139Th Ave Ne",
    "iso:country":"US",
    "sg:address":"18707 139th Ave NE",
    "sg:city":"Woodinville",
    "sg:classifiers":[
        {
            "category":"Freight",
            "type":"Transportation"
        }
    ],
    "sg:phone":"+1 425 482 4432",
    "sg:postcode":"98072",
    "sg:province":"WA",
    "wof:name":"Central Transport Intl",
    "wof:placetype":"venue"
},
  "geometry": {"coordinates":[-122.156451,47.759377],"type":"Point"}
}