{
  "type": "Feature",
  "properties": {
    "addr:full":"11030 8th Ave NE Seattle WA 98125",
    "addr:housenumber":"11030",
    "addr:postcode":"98125",
    "addr:street":"8Th Ave Ne",
    "iso:country":"US",
    "sg:address":"11030 8th Ave NE",
    "sg:city":"Seattle",
    "sg:classifiers":[
        {
            "category":"Personal",
            "type":"Services"
        },
        {
            "category":"Sports & Exercise",
            "subcategory":"Gym",
            "type":"Entertainment"
        },
        {
            "category":"Arena",
            "subcategory":"Sports Club",
            "type":"Entertainment"
        }
    ],
    "sg:phone":"+1 206 368 2431",
    "sg:postcode":"98125",
    "sg:province":"WA",
    "sg:tags":[
        "trainer",
        "consultant",
        "program",
        "health",
        "fitness",
        "physical"
    ],
    "sg:website":"www.24hourfitness.com",
    "wof:name":"24 Hour Fitness",
    "wof:placetype":"venue"
},
  "geometry": {"coordinates":[-122.32055699999999,47.709646],"type":"Point"}
}