{
  "type": "Feature",
  "properties": {
    "addr:full":"13075 Gateway Dr Seattle WA 98168",
    "addr:housenumber":"13075",
    "addr:postcode":"98168",
    "addr:street":"Gateway Dr",
    "iso:country":"US",
    "sg:address":"13075 Gateway Dr",
    "sg:city":"Seattle",
    "sg:classifiers":[
        {
            "category":"Local Transit",
            "type":"Transportation"
        }
    ],
    "sg:phone":"+1 206 322 0330",
    "sg:postcode":"98168",
    "sg:province":"WA",
    "sg:tags":[
        "ambulance"
    ],
    "wof:name":"Shepard Lifefleet",
    "wof:placetype":"venue"
},
  "geometry": {"coordinates":[-122.27442600000001,47.486383],"type":"Point"}
}