{
  "type": "Feature",
  "properties": {
    "addr:full":"205 S Pioneer Way Moses Lake WA 98837",
    "addr:housenumber":"205",
    "addr:postcode":"98837",
    "addr:street":"S Pioneer Way",
    "iso:country":"US",
    "sg:address":"205 S Pioneer Way",
    "sg:city":"Moses Lake",
    "sg:classifiers":[
        {
            "category":"Bars & Pubs",
            "type":"Food & Drink"
        }
    ],
    "sg:phone":"+1 509 765 7502",
    "sg:postcode":"98837",
    "sg:province":"WA",
    "sg:tags":[
        "tavern"
    ],
    "wof:name":"Shagg Tavern Inc",
    "wof:placetype":"venue"
},
  "geometry": {"coordinates":[-119.275172,47.132566],"type":"Point"}
}