{
  "type": "Feature",
  "properties": {
    "addr:full":"11308 47th Ave SE Everett WA 98208",
    "addr:housenumber":"11308",
    "addr:postcode":"98208",
    "addr:street":"47Th Ave Se",
    "iso:country":"US",
    "sg:address":"11308 47th Ave SE",
    "sg:city":"Everett",
    "sg:classifiers":[
        {
            "category":"Professional",
            "subcategory":"Lawyer & Legal Services",
            "type":"Services"
        }
    ],
    "sg:phone":"+1 425 422 7064",
    "sg:postcode":"98208",
    "sg:province":"WA",
    "wof:name":"Scott Santoro",
    "wof:placetype":"venue"
},
  "geometry": {"coordinates":[-122.169023,47.894847],"type":"Point"}
}