{
  "type": "Feature",
  "properties": {
    "addr:full":"4815 S 216th St Kent WA 98032",
    "addr:housenumber":"4815",
    "addr:postcode":"98032",
    "addr:street":"S 216Th St",
    "iso:country":"US",
    "sg:address":"4815 S 216th St",
    "sg:city":"Kent",
    "sg:classifiers":[
        {
            "category":"Professional",
            "subcategory":"Management & Consulting",
            "type":"Services"
        }
    ],
    "sg:phone":"+1 253 395 8001",
    "sg:postcode":"98032",
    "sg:province":"WA",
    "sg:tags":[
        "consultant",
        "educational"
    ],
    "wof:name":"Jacque Davis Educational Consultant",
    "wof:placetype":"venue"
},
  "geometry": {"coordinates":[-122.274164,47.408623],"type":"Point"}
}