{
  "type": "Feature",
  "properties": {
    "addr:full":"8101 Willows Rd NE Apt 14 Redmond WA 98052",
    "addr:housenumber":"8101;14",
    "addr:postcode":"98052",
    "addr:street":"Willows Rd Ne Apt",
    "iso:country":"US",
    "sg:address":"8101 Willows Rd NE Apt 14",
    "sg:city":"Redmond",
    "sg:classifiers":[
        {
            "category":"Sports & Exercise",
            "subcategory":"Stables",
            "type":"Entertainment"
        }
    ],
    "sg:phone":"+1 425 788 5391",
    "sg:postcode":"98052",
    "sg:province":"WA",
    "sg:tags":[
        "riding",
        "academy"
    ],
    "wof:name":"Broken Arrow Therapeutic Riding",
    "wof:placetype":"venue"
},
  "geometry": {"coordinates":[-122.136893,47.675813],"type":"Point"}
}