{
  "type": "Feature",
  "properties": {
    "addr:full":"2111 N Northgate Way Ste 100 Seattle WA 98133",
    "addr:housenumber":"2111",
    "addr:postcode":"98133",
    "addr:street":"N Northgate Way Ste 100",
    "iso:country":"US",
    "sg:address":"2111 N Northgate Way Ste 100",
    "sg:city":"Seattle",
    "sg:classifiers":[
        {
            "category":"Health Services",
            "subcategory":"Dentist",
            "type":"Services"
        }
    ],
    "sg:phone":"+1 800 359 6019",
    "sg:postcode":"98133",
    "sg:province":"WA",
    "sg:website":"www.willamettedental.com",
    "wof:name":"Willamette Dental",
    "wof:placetype":"venue"
},
  "geometry": {"coordinates":[-122.333696,47.708605],"type":"Point"}
}