{
  "type": "Feature",
  "properties": {
    "addr:full":"1011 E Ermina Ave Spokane WA 99207",
    "addr:housenumber":"1011",
    "addr:postcode":"99207",
    "addr:street":"E Ermina Ave",
    "iso:country":"US",
    "sg:address":"1011 E Ermina Ave",
    "sg:city":"Spokane",
    "sg:classifiers":[
        {
            "category":"Shopping",
            "subcategory":"Books",
            "type":"Retail Goods"
        }
    ],
    "sg:phone":"+1 509 484 3653",
    "sg:postcode":"99207",
    "sg:province":"WA",
    "wof:name":"Next Day Books",
    "wof:placetype":"venue"
},
  "geometry": {"coordinates":[-117.392059,47.676791],"type":"Point"}
}