{
  "type": "Feature",
  "properties": {
    "addr:full":"408 Yakima Valley Hwy Sunnyside WA 98944",
    "addr:housenumber":"408",
    "addr:postcode":"98944",
    "addr:street":"Yakima Valley Hwy",
    "iso:country":"US",
    "sg:address":"408 Yakima Valley Hwy",
    "sg:city":"Sunnyside",
    "sg:classifiers":[
        {
            "category":"Travel",
            "subcategory":"Hotels & Motels",
            "type":"Entertainment"
        }
    ],
    "sg:phone":"+1 509 837 7878",
    "sg:postcode":"98944",
    "sg:province":"WA",
    "wof:name":"Sunnyside Country Inn Suites",
    "wof:placetype":"venue"
},
  "geometry": {"coordinates":[-120.01549,46.329869],"type":"Point"}
}