{
  "type": "Feature",
  "properties": {
    "addr:full":"3314 17th Street Pl SE Puyallup WA 98374",
    "addr:housenumber":"3314",
    "addr:postcode":"98374",
    "addr:street":"17Th Street Pl Se",
    "iso:country":"US",
    "sg:address":"3314 17th Street Pl SE",
    "sg:city":"Puyallup",
    "sg:classifiers":[
        {
            "category":"Professional",
            "subcategory":"Business Services",
            "type":"Services"
        }
    ],
    "sg:phone":"+1 253 770 8681",
    "sg:postcode":"98374",
    "sg:province":"WA",
    "wof:name":"Wildwood Manor Interior Design",
    "wof:placetype":"venue"
},
  "geometry": {"coordinates":[-122.272391,47.161632],"type":"Point"}
}