{
  "type": "Feature",
  "properties": {
    "addr:full":"19017 120th Ave NE Bothell WA 98011",
    "addr:housenumber":"19017",
    "addr:postcode":"98011",
    "addr:street":"120Th Ave Ne",
    "iso:country":"US",
    "sg:address":"19017 120th Ave NE",
    "sg:city":"Bothell",
    "sg:classifiers":[
        {
            "category":"Professional",
            "subcategory":"Computer Services",
            "type":"Services"
        }
    ],
    "sg:phone":"+1 425 483 3875",
    "sg:postcode":"98011",
    "sg:province":"WA",
    "sg:tags":[
        "programing",
        "custom"
    ],
    "wof:name":"Landmark Graphics Corporation",
    "wof:placetype":"venue"
},
  "geometry": {"coordinates":[-122.179091,47.765862],"type":"Point"}
}