{
  "type": "Feature",
  "properties": {
    "addr:full":"304 Lynn St Seattle WA 98109",
    "addr:housenumber":"304",
    "addr:postcode":"98109",
    "addr:street":"Lynn St",
    "iso:country":"US",
    "sg:address":"304 Lynn St",
    "sg:city":"Seattle",
    "sg:classifiers":[
        {
            "category":"Health Services",
            "subcategory":"Health Practitioner",
            "type":"Services"
        }
    ],
    "sg:phone":"+1 206 283 5250",
    "sg:postcode":"98109",
    "sg:province":"WA",
    "wof:name":"Dana Harmon PHD",
    "wof:placetype":"venue"
},
  "geometry": {"coordinates":[-122.35077699999999,47.639183],"type":"Point"}
}