{
  "type": "Feature",
  "properties": {
    "addr:full":"200 W Mercer St Ste 208 Seattle WA 98119",
    "addr:housenumber":"200",
    "addr:postcode":"98119",
    "addr:street":"W Mercer St Ste 208",
    "iso:country":"US",
    "sg:address":"200 W Mercer St Ste 208",
    "sg:city":"Seattle",
    "sg:classifiers":[
        {
            "category":"Shopping",
            "subcategory":"Mobile Phones",
            "type":"Retail Goods"
        }
    ],
    "sg:phone":"+1 206 550 4996",
    "sg:postcode":"98119",
    "sg:province":"WA",
    "sg:website":"www.nexusmobility.com",
    "wof:name":"Nexus Mobility",
    "wof:placetype":"venue"
},
  "geometry": {"coordinates":[-122.35994100000001,47.624962],"type":"Point"}
}