{
  "type": "Feature",
  "properties": {
    "addr:full":"3108 29th Ave SW Tumwater WA 98512",
    "addr:housenumber":"3108",
    "addr:postcode":"98512",
    "addr:street":"29Th Ave Sw",
    "iso:country":"US",
    "sg:address":"3108 29th Ave SW",
    "sg:city":"Tumwater",
    "sg:classifiers":[
        {
            "category":"Wholesale",
            "subcategory":"Durable Goods & Equipment",
            "type":"Manufacturing & Wholesale Goods"
        }
    ],
    "sg:phone":"+1 360 705 2431",
    "sg:postcode":"98512",
    "sg:province":"WA",
    "sg:tags":[
        "exporter"
    ],
    "wof:name":"Four Seasons Greenery",
    "wof:placetype":"venue"
},
  "geometry": {"coordinates":[-122.94807299999999,47.021828],"type":"Point"}
}