{
  "type": "Feature",
  "properties": {
    "addr:full":"15006 NE 79th Cir Vancouver WA 98682",
    "addr:housenumber":"15006",
    "addr:postcode":"98682",
    "addr:street":"Ne 79Th Cir",
    "iso:country":"US",
    "sg:address":"15006 NE 79th Cir",
    "sg:city":"Vancouver",
    "sg:classifiers":[
        {
            "category":"Building & Trades",
            "subcategory":"Construction",
            "type":"Services"
        }
    ],
    "sg:phone":"+1 360 944 7549",
    "sg:postcode":"98682",
    "sg:province":"WA",
    "sg:tags":[
        "contractor"
    ],
    "wof:name":"Tact Industries Inc",
    "wof:placetype":"venue"
},
  "geometry": {"coordinates":[-122.51777,45.679846],"type":"Point"}
}