{
  "type": "Feature",
  "properties": {
    "addr:full":"106 4th Ave N Kelso WA 98626",
    "addr:housenumber":"106",
    "addr:postcode":"98626",
    "addr:street":"4Th Ave N",
    "iso:country":"US",
    "sg:address":"106 4th Ave N",
    "sg:city":"Kelso",
    "sg:classifiers":[
        {
            "category":"Taxi",
            "type":"Transportation"
        }
    ],
    "sg:phone":"+1 360 577 6777",
    "sg:postcode":"98626",
    "sg:province":"WA",
    "sg:tags":[
        "taxicab"
    ],
    "wof:name":"Owl Taxi",
    "wof:placetype":"venue"
},
  "geometry": {"coordinates":[-122.90898300000001,46.145242],"type":"Point"}
}