{
  "type": "Feature",
  "properties": {
    "addr:full":"227 Bellevue Way NE # 483 Bellevue WA 98004",
    "addr:housenumber":"227",
    "addr:postcode":"98004",
    "addr:street":"Bellevue Way Ne # 483",
    "iso:country":"US",
    "sg:address":"227 Bellevue Way NE # 483",
    "sg:city":"Bellevue",
    "sg:classifiers":[
        {
            "category":"Building & Trades",
            "subcategory":"Cleaning & Sanitation",
            "type":"Services"
        },
        {
            "category":"Personal",
            "type":"Services"
        }
    ],
    "sg:phone":"+1 888 969 4779",
    "sg:postcode":"98004",
    "sg:province":"WA",
    "sg:tags":[
        "home",
        "local"
    ],
    "sg:website":"www.zippydump.com",
    "wof:name":"Zippy Dump",
    "wof:placetype":"venue"
},
  "geometry": {"coordinates":[-122.20153999999999,47.611903],"type":"Point"}
}