{
  "type": "Feature",
  "properties": {
    "addr:full":"3505 S High Dr Spokane WA 99203",
    "addr:housenumber":"3505",
    "addr:postcode":"99203",
    "addr:street":"S High Dr",
    "iso:country":"US",
    "sg:address":"3505 S High Dr",
    "sg:city":"Spokane",
    "sg:classifiers":[
        {
            "category":"Shopping",
            "subcategory":"Florist",
            "type":"Retail Goods"
        }
    ],
    "sg:phone":"+1 509 838 3477",
    "sg:postcode":"99203",
    "sg:province":"WA",
    "wof:name":"Moffitt, Janet A Flowers",
    "wof:placetype":"venue"
},
  "geometry": {"coordinates":[-117.424691,47.620317],"type":"Point"}
}