{
  "type": "Feature",
  "properties": {
    "addr:full":"7816 NE 100th Ave Vancouver WA 98662",
    "addr:housenumber":"7816",
    "addr:postcode":"98662",
    "addr:street":"Ne 100Th Ave",
    "iso:country":"US",
    "sg:address":"7816 NE 100th Ave",
    "sg:city":"Vancouver",
    "sg:classifiers":[
        {
            "category":"Personal",
            "subcategory":"Beauty Salon",
            "type":"Services"
        }
    ],
    "sg:phone":"+1 360 254 9152",
    "sg:postcode":"98662",
    "sg:province":"WA",
    "wof:name":"Elaine Gray Beauty Salon",
    "wof:placetype":"venue"
},
  "geometry": {"coordinates":[-122.57075399999999,45.680035],"type":"Point"}
}