{
  "type": "Feature",
  "properties": {
    "addr:full":"18628 NE 189th St Woodinville WA 98077",
    "addr:housenumber":"18628",
    "addr:postcode":"98077",
    "addr:street":"Ne 189Th St",
    "iso:country":"US",
    "sg:address":"18628 NE 189th St",
    "sg:city":"Woodinville",
    "sg:classifiers":[
        {
            "category":"Professional",
            "subcategory":"Advertising",
            "type":"Services"
        }
    ],
    "sg:phone":"+1 425 844 3000",
    "sg:postcode":"98077",
    "sg:province":"WA",
    "sg:tags":[
        "mail",
        "direct"
    ],
    "wof:name":"Buyers' Choice Direct Mail",
    "wof:placetype":"venue"
},
  "geometry": {"coordinates":[-122.08885100000001,47.764378],"type":"Point"}
}