{
  "type": "Feature",
  "properties": {
    "addr:full":"13520 SE 163rd St Renton WA 98058",
    "addr:housenumber":"13520",
    "addr:postcode":"98058",
    "addr:street":"Se 163Rd St",
    "iso:country":"US",
    "sg:address":"13520 SE 163rd St",
    "sg:city":"Renton",
    "sg:classifiers":[
        {
            "category":"Retail",
            "subcategory":"Repair Shop",
            "type":"Services"
        }
    ],
    "sg:phone":"+1 425 235 7180",
    "sg:postcode":"98058",
    "sg:province":"WA",
    "wof:name":"Michael Judge Cleaning",
    "wof:placetype":"venue"
},
  "geometry": {"coordinates":[-122.15847599999999,47.456894],"type":"Point"}
}