{
  "type": "Feature",
  "properties": {
    "addr:full":"1865 SW Fawn Ln Port Orchard WA 98367",
    "addr:housenumber":"1865",
    "addr:postcode":"98367",
    "addr:street":"Sw Fawn Ln",
    "iso:country":"US",
    "sg:address":"1865 SW Fawn Ln",
    "sg:city":"Port Orchard",
    "sg:classifiers":[
        {
            "category":"Personal",
            "subcategory":"Beauty Salon",
            "type":"Services"
        }
    ],
    "sg:phone":"+1 360 876 0945",
    "sg:postcode":"98367",
    "sg:province":"WA",
    "sg:tags":[
        "shop"
    ],
    "wof:name":"Angelas Artistry",
    "wof:placetype":"venue"
},
  "geometry": {"coordinates":[-122.677953,47.462632],"type":"Point"}
}