{
  "type": "Feature",
  "properties": {
    "addr:full":"244 NW Market St Seattle WA 98107",
    "addr:housenumber":"244",
    "addr:postcode":"98107",
    "addr:street":"Nw Market St",
    "iso:country":"US",
    "sg:address":"244 NW Market St",
    "sg:city":"Seattle",
    "sg:classifiers":[
        {
            "category":"Professional",
            "subcategory":"Art Services",
            "type":"Services"
        }
    ],
    "sg:phone":"+1 206 783 4322",
    "sg:postcode":"98107",
    "sg:province":"WA",
    "sg:tags":[
        "commercial",
        "design"
    ],
    "wof:name":"Lynn E Pasley",
    "wof:placetype":"venue"
},
  "geometry": {"coordinates":[-122.360803,47.666919],"type":"Point"}
}