{
  "type": "Feature",
  "properties": {
    "addr:full":"11717 NE 143rd St Kirkland WA 98034",
    "addr:housenumber":"11717",
    "addr:postcode":"98034",
    "addr:street":"Ne 143Rd St",
    "iso:country":"US",
    "sg:address":"11717 NE 143rd St",
    "sg:city":"Kirkland",
    "sg:classifiers":[
        {
            "category":"Professional",
            "subcategory":"Management & Consulting",
            "type":"Services"
        }
    ],
    "sg:phone":"+1 425 821 9578",
    "sg:postcode":"98034",
    "sg:province":"WA",
    "wof:name":"Hays Co",
    "wof:placetype":"venue"
},
  "geometry": {"coordinates":[-122.183212,47.729902],"type":"Point"}
}