{
  "type": "Feature",
  "properties": {
    "iso:country":"US",
    "sg:address":"41947 Challenger Rd",
    "sg:city":"Concrete",
    "sg:classifiers":[
        {
            "category":"Personal",
            "subcategory":"Beauty Salon",
            "type":"Services"
        }
    ],
    "sg:phone":"+1 360 826 3231",
    "sg:postcode":"98237",
    "sg:province":"WA",
    "sg:tags":[
        "shop"
    ],
    "wof:name":"Beverlys Hill",
    "wof:placetype":"venue"
},
  "geometry": {"coordinates":[-121.838447,48.541648],"type":"Point"}
}