{
  "type": "Feature",
  "properties": {
    "addr:full":"10904 Peacock Ln Burlington WA 98233",
    "addr:housenumber":"10904",
    "addr:postcode":"98233",
    "addr:street":"Peacock Ln",
    "iso:country":"US",
    "sg:address":"10904 Peacock Ln",
    "sg:city":"Burlington",
    "sg:classifiers":[
        {
            "category":"Professional",
            "subcategory":"Accounting & Tax Preparation",
            "type":"Services"
        }
    ],
    "sg:phone":"+1 360 757 4844",
    "sg:postcode":"98233",
    "sg:province":"WA",
    "sg:tags":[
        "bookkeeping",
        "general"
    ],
    "wof:name":"Terrie's Bookkeeping Svc",
    "wof:placetype":"venue"
},
  "geometry": {"coordinates":[-122.313576,48.487484],"type":"Point"}
}