{
  "type": "Feature",
  "properties": {
    "addr:full":"27120 92nd Ave NW Stanwood WA 98292",
    "addr:housenumber":"27120",
    "addr:postcode":"98292",
    "addr:street":"92Nd Ave Nw",
    "iso:country":"US",
    "sg:address":"27120 92nd Ave NW",
    "sg:city":"Stanwood",
    "sg:classifiers":[
        {
            "category":"Sports & Exercise",
            "subcategory":"Bowling",
            "type":"Entertainment"
        }
    ],
    "sg:phone":"+1 360 629 3001",
    "sg:postcode":"98292",
    "sg:province":"WA",
    "sg:tags":[
        "center"
    ],
    "wof:name":"Twin City Lanes",
    "wof:placetype":"venue"
},
  "geometry": {"coordinates":[-122.35746399999999,48.242969],"type":"Point"}
}