{
  "type": "Feature",
  "properties": {
    "addr:full":"6027 Manchester Ln SE Olympia WA 98513",
    "addr:housenumber":"6027",
    "addr:postcode":"98513",
    "addr:street":"Manchester Ln Se",
    "iso:country":"US",
    "sg:address":"6027 Manchester Ln SE",
    "sg:city":"Olympia",
    "sg:classifiers":[
        {
            "category":"Manufacturing",
            "subcategory":"Leather Goods",
            "type":"Manufacturing & Wholesale Goods"
        }
    ],
    "sg:phone":"+1 360 459 2881",
    "sg:postcode":"98513",
    "sg:province":"WA",
    "sg:tags":[
        "mfg"
    ],
    "wof:name":"Woodys World",
    "wof:placetype":"venue"
},
  "geometry": {"coordinates":[-122.82655099999999,46.99283],"type":"Point"}
}