{
  "type": "Feature",
  "properties": {
    "addr:full":"1601 E Fourth Plain Blvd Vancouver WA 98661",
    "addr:housenumber":"1601",
    "addr:postcode":"98661",
    "addr:street":"E Fourth Plain Blvd",
    "iso:country":"US",
    "sg:address":"1601 E Fourth Plain Blvd",
    "sg:city":"Vancouver",
    "sg:classifiers":[
        {
            "category":"Government",
            "subcategory":"Office",
            "type":"Public Place"
        }
    ],
    "sg:phone":"+1 360 696 4061",
    "sg:postcode":"98661",
    "sg:province":"WA",
    "sg:tags":[
        "federal",
        "affairs",
        "govt",
        "admin"
    ],
    "wof:name":"US Veterans Affairs Dept",
    "wof:placetype":"venue"
},
  "geometry": {"coordinates":[-122.65488499999999,45.639354],"type":"Point"}
}