{
  "type": "Feature",
  "properties": {
    "addr:full":"1812 Odegard Rd SW Olympia WA 98512",
    "addr:housenumber":"1812",
    "addr:postcode":"98512",
    "addr:street":"Odegard Rd Sw",
    "iso:country":"US",
    "sg:address":"1812 Odegard Rd SW",
    "sg:city":"Olympia",
    "sg:classifiers":[
        {
            "category":"Retail",
            "subcategory":"Auto Repair",
            "type":"Services"
        }
    ],
    "sg:phone":"+1 360 709 0509",
    "sg:postcode":"98512",
    "sg:province":"WA",
    "sg:tags":[
        "automotive"
    ],
    "wof:name":"Doorstep Rv Generator Rep",
    "wof:placetype":"venue"
},
  "geometry": {"coordinates":[-122.925645,46.989713],"type":"Point"}
}