{
  "type": "Feature",
  "properties": {
    "addr:full":"7107 W Ridgeway Rd Deer Park WA 99006",
    "addr:housenumber":"7107",
    "addr:postcode":"99006",
    "addr:street":"W Ridgeway Rd",
    "iso:country":"US",
    "sg:address":"7107 W Ridgeway Rd",
    "sg:city":"Deer Park",
    "sg:classifiers":[
        {
            "category":"Building & Trades",
            "subcategory":"Construction",
            "type":"Services"
        }
    ],
    "sg:phone":"+1 509 276 7475",
    "sg:postcode":"99006",
    "sg:province":"WA",
    "sg:tags":[
        "repairing",
        "remodeling",
        "contractor"
    ],
    "wof:name":"Panagos Construction",
    "wof:placetype":"venue"
},
  "geometry": {"coordinates":[-117.512542,47.860033],"type":"Point"}
}