{
  "type": "Feature",
  "properties": {
    "addr:full":"122 S Columbia St Wenatchee WA 98801",
    "addr:housenumber":"122",
    "addr:postcode":"98801",
    "addr:street":"S Columbia St",
    "iso:country":"US",
    "sg:address":"122 S Columbia St",
    "sg:city":"Wenatchee",
    "sg:classifiers":[
        {
            "category":"Home & Garden",
            "subcategory":"Household Appliances",
            "type":"Retail Goods"
        }
    ],
    "sg:phone":"+1 509 663 2923",
    "sg:postcode":"98801",
    "sg:province":"WA",
    "sg:tags":[
        "cleaners",
        "vacuum"
    ],
    "wof:name":"Kirby Service Ctr",
    "wof:placetype":"venue"
},
  "geometry": {"coordinates":[-120.30885600000001,47.423246],"type":"Point"}
}