{
  "type": "Feature",
  "properties": {
    "addr:full":"1045 Rd 3 NW Waterville WA 98858",
    "addr:housenumber":"1045",
    "addr:postcode":"98858",
    "addr:street":"Rd 3 Nw",
    "iso:country":"US",
    "sg:address":"1045 Rd 3 NW",
    "sg:city":"Waterville",
    "sg:classifiers":[
        {
            "category":"Farming",
            "subcategory":"Livestock Farm",
            "type":"Manufacturing & Wholesale Goods"
        }
    ],
    "sg:phone":"+1 509 745 8984",
    "sg:postcode":"98858",
    "sg:province":"WA",
    "sg:tags":[
        "equine"
    ],
    "wof:name":"Circle DOT",
    "wof:placetype":"venue"
},
  "geometry": {"coordinates":[-119.984748,47.6563],"type":"Point"}
}