{
  "type": "Feature",
  "properties": {
    "addr:full":"100 Peavine Rd Ellensburg WA 98926",
    "addr:housenumber":"100",
    "addr:postcode":"98926",
    "addr:street":"Peavine Rd",
    "iso:country":"US",
    "sg:address":"100 Peavine Rd",
    "sg:city":"Ellensburg",
    "sg:classifiers":[
        {
            "category":"Real Estate",
            "subcategory":"Real Estate Agent",
            "type":"Services"
        }
    ],
    "sg:phone":"+1 509 962 5910",
    "sg:postcode":"98926",
    "sg:province":"WA",
    "wof:name":"Caylx Property Management",
    "wof:placetype":"venue"
},
  "geometry": {"coordinates":[-120.587853,46.995809],"type":"Point"}
}