{
  "type": "Feature",
  "properties": {
    "addr:full":"900 1st Ave S Ste 104 Seattle WA 98134",
    "addr:housenumber":"900",
    "addr:postcode":"98134",
    "addr:street":"1St Ave S Ste 104",
    "iso:country":"US",
    "sg:address":"900 1st Ave S Ste 104",
    "sg:city":"Seattle",
    "sg:classifiers":[
        {
            "category":"Professional",
            "subcategory":"Lawyer & Legal Services",
            "type":"Services"
        }
    ],
    "sg:phone":"+1 206 749 0228",
    "sg:postcode":"98134",
    "sg:province":"WA",
    "wof:name":"Weber & Marks Pllc",
    "wof:placetype":"venue"
},
  "geometry": {"coordinates":[-122.333686,47.594855],"type":"Point"}
}