{
  "type": "Feature",
  "properties": {
    "addr:full":"1216 10th Ave Seattle WA 98122",
    "addr:housenumber":"1216",
    "addr:postcode":"98122",
    "addr:street":"10Th Ave",
    "iso:country":"US",
    "sg:address":"1216 10th Ave",
    "sg:city":"Seattle",
    "sg:classifiers":[
        {
            "category":"Communications",
            "subcategory":"Film & Video Production",
            "type":"Services"
        }
    ],
    "sg:phone":"+1 206 323 0557",
    "sg:postcode":"98122",
    "sg:province":"WA",
    "sg:tags":[
        "picture",
        "services-commercial",
        "motion"
    ],
    "wof:name":"Pound Gallery",
    "wof:placetype":"venue"
},
  "geometry": {"coordinates":[-122.31936,47.612208],"type":"Point"}
}