{
  "type": "Feature",
  "properties": {
    "addr:full":"1019 W 7th Ave Spokane WA 99204",
    "addr:housenumber":"1019",
    "addr:postcode":"99204",
    "addr:street":"W 7Th Ave",
    "iso:country":"US",
    "sg:address":"1019 W 7th Ave",
    "sg:city":"Spokane",
    "sg:classifiers":[
        {
            "category":"Museum",
            "type":"Entertainment"
        }
    ],
    "sg:phone":"+1 509 879 7858",
    "sg:postcode":"99204",
    "sg:province":"WA",
    "sg:tags":[
        "gallery"
    ],
    "wof:name":"Potters Hand Pottery",
    "wof:placetype":"venue"
},
  "geometry": {"coordinates":[-117.429305,47.649239],"type":"Point"}
}