{
  "type": "Feature",
  "properties": {
    "addr:full":"200 15th Ave E Seattle WA 98112",
    "addr:housenumber":"200",
    "addr:postcode":"98112",
    "addr:street":"15Th Ave E",
    "iso:country":"US",
    "sg:address":"200 15th Ave E",
    "sg:city":"Seattle",
    "sg:classifiers":[
        {
            "category":"Health Services",
            "subcategory":"Hospital",
            "type":"Services"
        }
    ],
    "sg:phone":"+1 206 326 3000",
    "sg:postcode":"98112",
    "sg:province":"WA",
    "sg:tags":[
        "physician",
        "surgeon"
    ],
    "sg:website":"http://www.ghc.org",
    "wof:name":"Group Health Cooperative",
    "wof:placetype":"venue"
},
  "geometry": {"coordinates":[-122.312752,47.619942],"type":"Point"}
}