{
  "type": "Feature",
  "properties": {
    "addr:full":"23880 NE State Rte 3 Belfair WA 98528",
    "addr:housenumber":"23880",
    "addr:postcode":"98528",
    "addr:street":"Ne State Rte 3",
    "iso:country":"US",
    "sg:address":"23880 NE State Rte 3",
    "sg:city":"Belfair",
    "sg:classifiers":[
        {
            "category":"Autos & Motor Vehicles",
            "subcategory":"Fuel & Gas Station",
            "type":"Retail Goods"
        }
    ],
    "sg:phone":"+1 360 275 2754",
    "sg:postcode":"98528",
    "sg:province":"WA",
    "sg:tags":[
        "oil"
    ],
    "wof:name":"Chevron",
    "wof:placetype":"venue"
},
  "geometry": {"coordinates":[-122.82107999999999,47.453747],"type":"Point"}
}