{
  "type": "Feature",
  "properties": {
    "addr:full":"357 S 76th Ave Yakima WA 98908",
    "addr:housenumber":"357",
    "addr:postcode":"98908",
    "addr:street":"S 76Th Ave",
    "iso:country":"US",
    "sg:address":"357 S 76th Ave",
    "sg:city":"Yakima",
    "sg:classifiers":[
        {
            "category":"Manufacturing",
            "subcategory":"Glass & Minerals",
            "type":"Manufacturing & Wholesale Goods"
        }
    ],
    "sg:phone":"+1 509 965 5288",
    "sg:postcode":"98908",
    "sg:province":"WA",
    "sg:tags":[
        "mfg"
    ],
    "wof:name":"Silicate Creations",
    "wof:placetype":"venue"
},
  "geometry": {"coordinates":[-120.609497,46.594217],"type":"Point"}
}