{
  "type": "Feature",
  "properties": {
    "iso:country":"US",
    "sg:address":"5 W Alder St",
    "sg:city":"Walla Walla",
    "sg:classifiers":[
        {
            "category":"Social Services",
            "type":"Services"
        }
    ],
    "sg:phone":"+1 509 525 4290",
    "sg:postcode":"99362",
    "sg:province":"WA",
    "sg:tags":[
        "organization",
        "welfare"
    ],
    "wof:name":"Payee Service Carol Brown",
    "wof:placetype":"venue"
},
  "geometry": {"coordinates":[-118.338663,46.065772],"type":"Point"}
}