{
  "type": "Feature",
  "properties": {
    "addr:full":"4300 Talbot Rd S Renton WA 98055",
    "addr:housenumber":"4300",
    "addr:postcode":"98055",
    "addr:street":"Talbot Rd S",
    "iso:country":"US",
    "sg:address":"4300 Talbot Rd S",
    "sg:city":"Renton",
    "sg:classifiers":[
        {
            "category":"Wholesale",
            "subcategory":"Medical Equipment & Supplies",
            "type":"Manufacturing & Wholesale Goods"
        },
        {
            "category":"Communications",
            "type":"Services"
        }
    ],
    "sg:phone":"+1 425 277 9521",
    "sg:postcode":"98055",
    "sg:province":"WA",
    "sg:tags":[
        "speech-language",
        "hearing",
        "pathologist",
        "device",
        "assistive",
        "aid"
    ],
    "sg:website":"http://www.keyhearing.com",
    "wof:name":"Key Hearing",
    "wof:placetype":"venue"
},
  "geometry": {"coordinates":[-122.212852,47.441109],"type":"Point"}
}