{
  "type": "Feature",
  "properties": {
    "addr:full":"2320 139th Ave SE Snohomish WA 98290",
    "addr:housenumber":"2320",
    "addr:postcode":"98290",
    "addr:street":"139Th Ave Se",
    "iso:country":"US",
    "sg:address":"2320 139th Ave SE",
    "sg:city":"Snohomish",
    "sg:classifiers":[
        {
            "category":"Shopping",
            "subcategory":"Gifts & Souvenirs",
            "type":"Retail Goods"
        }
    ],
    "sg:phone":"+1 425 359 6620",
    "sg:postcode":"98290",
    "sg:province":"WA",
    "wof:name":"Victorianrosecottagecom",
    "wof:placetype":"venue"
},
  "geometry": {"coordinates":[-122.043644,47.974481],"type":"Point"}
}