{
  "type": "Feature",
  "properties": {
    "addr:full":"6010 Seaview Ave NW Seattle WA 98107",
    "addr:housenumber":"6010",
    "addr:postcode":"98107",
    "addr:street":"Seaview Ave Nw",
    "iso:country":"US",
    "sg:address":"6010 Seaview Ave NW",
    "sg:city":"Seattle",
    "sg:classifiers":[
        {
            "category":"Manufacturing",
            "subcategory":"Apparel",
            "type":"Manufacturing & Wholesale Goods"
        }
    ],
    "sg:phone":"+1 206 783 2400",
    "sg:postcode":"98107",
    "sg:province":"WA",
    "sg:tags":[
        "product",
        "boat",
        "mfg"
    ],
    "wof:name":"Schattauer Sails Inc",
    "wof:placetype":"venue"
},
  "geometry": {"coordinates":[-122.40558299999999,47.672214],"type":"Point"}
}