{
  "type": "Feature",
  "properties": {
    "addr:full":"11313 127th Pl NE Kirkland WA 98033",
    "addr:housenumber":"11313",
    "addr:postcode":"98033",
    "addr:street":"127Th Pl Ne",
    "iso:country":"US",
    "sg:address":"11313 127th Pl NE",
    "sg:city":"Kirkland",
    "sg:classifiers":[
        {
            "category":"Professional",
            "type":"Services"
        }
    ],
    "sg:phone":"+1 425 882 6044",
    "sg:postcode":"98033",
    "sg:province":"WA",
    "wof:name":"3 Sisters",
    "wof:placetype":"venue"
},
  "geometry": {"coordinates":[-122.170738,47.70248],"type":"Point"}
}