{
  "type": "Feature",
  "properties": {
    "addr:full":"10186 Merlin Ln NW Bremerton WA 98312",
    "addr:housenumber":"10186",
    "addr:postcode":"98312",
    "addr:street":"Merlin Ln Nw",
    "iso:country":"US",
    "sg:address":"10186 Merlin Ln NW",
    "sg:city":"Bremerton",
    "sg:classifiers":[
        {
            "category":"Professional",
            "subcategory":"Business Services",
            "type":"Services"
        }
    ],
    "sg:phone":"+1 360 692 1925",
    "sg:postcode":"98312",
    "sg:province":"WA",
    "wof:name":"Judys Enterprises",
    "wof:placetype":"venue"
},
  "geometry": {"coordinates":[-122.784648,47.630723],"type":"Point"}
}