{
  "type": "Feature",
  "properties": {
    "addr:full":"108 SE 124th Ave Vancouver WA 98684",
    "addr:housenumber":"108",
    "addr:postcode":"98684",
    "addr:street":"Se 124Th Ave",
    "iso:country":"US",
    "sg:address":"108 SE 124th Ave",
    "sg:city":"Vancouver",
    "sg:classifiers":[
        {
            "category":"Banks & Credit Unions",
            "subcategory":"Investment Brokerage",
            "type":"Services"
        }
    ],
    "sg:phone":"+1 360 896 8020",
    "sg:postcode":"98684",
    "sg:province":"WA",
    "sg:tags":[
        "security"
    ],
    "wof:name":"Rod Whitesmith",
    "wof:placetype":"venue"
},
  "geometry": {"coordinates":[-122.54505399999999,45.620059],"type":"Point"}
}