{
  "type": "Feature",
  "properties": {
    "addr:full":"9728 Dayton Ave N Seattle WA 98103",
    "addr:housenumber":"9728",
    "addr:postcode":"98103",
    "addr:street":"Dayton Ave N",
    "iso:country":"US",
    "sg:address":"9728 Dayton Ave N",
    "sg:city":"Seattle",
    "sg:classifiers":[
        {
            "category":"Professional",
            "subcategory":"Management & Consulting",
            "type":"Services"
        }
    ],
    "sg:phone":"+1 206 297 6265",
    "sg:postcode":"98103",
    "sg:province":"WA",
    "sg:tags":[
        "business"
    ],
    "wof:name":"Sound Progression",
    "wof:placetype":"venue"
},
  "geometry": {"coordinates":[-122.352653,47.701281],"type":"Point"}
}