{
  "type": "Feature",
  "properties": {
    "addr:full":"311 E Balbriggan Rd Shelton WA 98584",
    "addr:housenumber":"311",
    "addr:postcode":"98584",
    "addr:street":"E Balbriggan Rd",
    "iso:country":"US",
    "sg:address":"311 E Balbriggan Rd",
    "sg:city":"Shelton",
    "sg:classifiers":[
        {
            "category":"Building & Trades",
            "subcategory":"Construction",
            "type":"Services"
        }
    ],
    "sg:phone":"+1 360 427 1988",
    "sg:postcode":"98584",
    "sg:province":"WA",
    "sg:tags":[
        "contractor"
    ],
    "wof:name":"Braggs Quality Drywall",
    "wof:placetype":"venue"
},
  "geometry": {"coordinates":[-123.048503,47.276741],"type":"Point"}
}