{
  "type": "Feature",
  "properties": {
    "addr:full":"9706 N Newport Hwy Spokane WA 99218",
    "addr:housenumber":"9706",
    "addr:postcode":"99218",
    "addr:street":"N Newport Hwy",
    "iso:country":"US",
    "sg:address":"9706 N Newport Hwy",
    "sg:city":"Spokane",
    "sg:classifiers":[
        {
            "category":"Personal",
            "subcategory":"Beauty Salon",
            "type":"Services"
        }
    ],
    "sg:phone":"+1 509 468 7242",
    "sg:postcode":"99218",
    "sg:province":"WA",
    "sg:tags":[
        "nail"
    ],
    "wof:name":"Foxy Nails",
    "wof:placetype":"venue"
},
  "geometry": {"coordinates":[-117.405028,47.746266],"type":"Point"}
}