{
  "type": "Feature",
  "properties": {
    "addr:full":"1206 N Dolarway Rd Ellensburg WA 98926",
    "addr:housenumber":"1206",
    "addr:postcode":"98926",
    "addr:street":"N Dolarway Rd",
    "iso:country":"US",
    "sg:address":"1206 N Dolarway Rd",
    "sg:city":"Ellensburg",
    "sg:classifiers":[
        {
            "category":"Real Estate",
            "subcategory":"Real Estate Agent",
            "type":"Services"
        }
    ],
    "sg:phone":"+1 509 925 7000",
    "sg:postcode":"98926",
    "sg:province":"WA",
    "wof:name":"Northwest Lending Associates I",
    "wof:placetype":"venue"
},
  "geometry": {"coordinates":[-120.58543899999999,47.004144],"type":"Point"}
}