{
  "type": "Feature",
  "properties": {
    "addr:full":"101 4th Ave S Seattle WA 98104",
    "addr:housenumber":"101",
    "addr:postcode":"98104",
    "addr:street":"4Th Ave S",
    "iso:country":"US",
    "sg:address":"101 4th Ave S",
    "sg:city":"Seattle",
    "sg:classifiers":[
        {
            "category":"Wholesale",
            "subcategory":"Machinery & Supplies",
            "type":"Manufacturing & Wholesale Goods"
        }
    ],
    "sg:phone":"+1 206 624 1636",
    "sg:postcode":"98104",
    "sg:province":"WA",
    "sg:tags":[
        "equipment",
        "establishment"
    ],
    "wof:name":"Windows 101",
    "wof:placetype":"venue"
},
  "geometry": {"coordinates":[-122.328986,47.600873],"type":"Point"}
}