{
  "type": "Feature",
  "properties": {
    "iso:country":"US",
    "sg:address":"372 H St",
    "sg:city":"Blaine",
    "sg:classifiers":[
        {
            "category":"Manufacturing",
            "subcategory":"Printing",
            "type":"Manufacturing & Wholesale Goods"
        }
    ],
    "sg:phone":"+1 360 332 5454",
    "sg:postcode":"98230",
    "sg:province":"WA",
    "sg:tags":[
        "commercial"
    ],
    "wof:name":"Pelican Press",
    "wof:placetype":"venue"
},
  "geometry": {"coordinates":[-122.74891,48.994095],"type":"Point"}
}