{
  "type": "Feature",
  "properties": {
    "iso:country":"US",
    "sg:address":"117 E 3rd Ave",
    "sg:city":"Selah",
    "sg:classifiers":[
        {
            "category":"Food & Beverages",
            "subcategory":"Bakery",
            "type":"Retail Goods"
        }
    ],
    "sg:phone":"+1 509 697 5858",
    "sg:postcode":"98942",
    "sg:province":"WA",
    "wof:name":"Royal Bavarian Bakery Inc",
    "wof:placetype":"venue"
},
  "geometry": {"coordinates":[-120.526779,46.651089],"type":"Point"}
}