{
  "type": "Feature",
  "properties": {
    "addr:full":"1139 23rd Ave E Seattle WA 98112",
    "addr:housenumber":"1139",
    "addr:postcode":"98112",
    "addr:street":"23Rd Ave E",
    "iso:country":"US",
    "sg:address":"1139 23rd Ave E",
    "sg:city":"Seattle",
    "sg:classifiers":[
        {
            "category":"Real Estate",
            "subcategory":"Developer",
            "type":"Services"
        }
    ],
    "sg:phone":"+1 206 324 3221",
    "sg:postcode":"98112",
    "sg:province":"WA",
    "wof:name":"Howe Capital Investments",
    "wof:placetype":"venue"
},
  "geometry": {"coordinates":[-122.30233800000001,47.629879],"type":"Point"}
}