{
  "type": "Feature",
  "properties": {
    "addr:full":"3512 Summitview Ave Yakima WA 98902",
    "addr:housenumber":"3512",
    "addr:postcode":"98902",
    "addr:street":"Summitview Ave",
    "iso:country":"US",
    "sg:address":"3512 Summitview Ave",
    "sg:city":"Yakima",
    "sg:classifiers":[
        {
            "category":"Restaurant",
            "type":"Food & Drink"
        }
    ],
    "sg:phone":"+1 509 452 0485",
    "sg:postcode":"98902",
    "sg:province":"WA",
    "sg:tags":[
        "mexican"
    ],
    "wof:name":"Antojitos Mexicano Restaurant",
    "wof:placetype":"venue"
},
  "geometry": {"coordinates":[-120.55570899999999,46.59993],"type":"Point"}
}