{
  "type": "Feature",
  "properties": {
    "addr:full":"1019 Ironwood St Oroville WA 98844",
    "addr:housenumber":"1019",
    "addr:postcode":"98844",
    "addr:street":"Ironwood St",
    "iso:country":"US",
    "sg:address":"1019 Ironwood St",
    "sg:city":"Oroville",
    "sg:classifiers":[
        {
            "category":"Place Of Worship",
            "subcategory":"Church",
            "type":"Public Place"
        },
        {
            "category":"Place Of Worship",
            "type":"Public Place"
        },
        {
            "category":"Organizations",
            "subcategory":"Religious Organization",
            "type":"Services"
        }
    ],
    "sg:phone":"+1 509 476 2426",
    "sg:postcode":"98844",
    "sg:province":"WA",
    "sg:tags":[
        "lutheran",
        "america",
        "churches-lutheran",
        "clergy",
        "churches-lutheran-evangelical"
    ],
    "wof:name":"Faith Luthern Church",
    "wof:placetype":"venue"
},
  "geometry": {"coordinates":[-119.43825099999999,48.93427],"type":"Point"}
}