{
  "type": "Feature",
  "properties": {
    "iso:country":"US",
    "sg:address":"1720 W Marine View Dr",
    "sg:city":"Everett",
    "sg:classifiers":[
        {
            "category":"Building & Trades",
            "subcategory":"Construction",
            "type":"Services"
        }
    ],
    "sg:phone":"+1 425 259 9008",
    "sg:postcode":"98201",
    "sg:province":"WA",
    "sg:tags":[
        "contractor"
    ],
    "wof:name":"Westwind Builders",
    "wof:placetype":"venue"
},
  "geometry": {"coordinates":[-122.21387799999999,47.998449],"type":"Point"}
}