{
  "type": "Feature",
  "properties": {
    "addr:full":"1420 NW Gilman Blvd Ste 2 Issaquah WA 98027",
    "addr:housenumber":"1420",
    "addr:postcode":"98027",
    "addr:street":"Nw Gilman Blvd Ste 2",
    "iso:country":"US",
    "sg:address":"1420 NW Gilman Blvd Ste 2",
    "sg:city":"Issaquah",
    "sg:classifiers":[
        {
            "category":"Building & Trades",
            "subcategory":"Landscaping Services",
            "type":"Services"
        }
    ],
    "sg:phone":"+1 425 228 1458",
    "sg:postcode":"98027",
    "sg:province":"WA",
    "sg:tags":[
        "lawn"
    ],
    "wof:name":"May Creek Landscape Inc",
    "wof:placetype":"venue"
},
  "geometry": {"coordinates":[-122.059009,47.545712],"type":"Point"}
}