{
  "type": "Feature",
  "properties": {
    "addr:full":"20102 Cedar Valley Rd Ste 105 Lynnwood WA 98036",
    "addr:housenumber":"20102",
    "addr:postcode":"98036",
    "addr:street":"Cedar Valley Rd Ste 105",
    "iso:country":"US",
    "sg:address":"20102 Cedar Valley Rd Ste 105",
    "sg:city":"Lynnwood",
    "sg:classifiers":[
        {
            "category":"Health Services",
            "subcategory":"Dentist",
            "type":"Services"
        }
    ],
    "sg:phone":"+1 425 954 8085",
    "sg:postcode":"98036",
    "sg:province":"WA",
    "sg:tags":[
        "dentists-orthodontists",
        "dentists-pediatric",
        "dentistry"
    ],
    "sg:website":"http://www.kidsdentist.com",
    "wof:name":"Lynnwood Children?s Dentistry",
    "wof:placetype":"venue"
},
  "geometry": {"coordinates":[-122.301453,47.816268],"type":"Point"}
}