{
  "type": "Feature",
  "properties": {
    "addr:full":"5503 N Wall St Spokane WA 99205",
    "addr:housenumber":"5503",
    "addr:postcode":"99205",
    "addr:street":"N Wall St",
    "iso:country":"US",
    "sg:address":"5503 N Wall St",
    "sg:city":"Spokane",
    "sg:classifiers":[
        {
            "category":"Professional",
            "subcategory":"Management & Consulting",
            "type":"Services"
        },
        {
            "category":"Professional",
            "subcategory":"Accounting & Tax Preparation",
            "type":"Services"
        }
    ],
    "sg:phone":"+1 509 324 3313",
    "sg:postcode":"99205",
    "sg:province":"WA",
    "sg:tags":[
        "accountant"
    ],
    "wof:name":"Niccum & Associates",
    "wof:placetype":"venue"
},
  "geometry": {"coordinates":[-117.422059,47.708852],"type":"Point"}
}