{
  "type": "Feature",
  "properties": {
    "addr:full":"7521 Ridge Dr NE Seattle WA 98115",
    "addr:housenumber":"7521",
    "addr:postcode":"98115",
    "addr:street":"Ridge Dr Ne",
    "iso:country":"US",
    "sg:address":"7521 Ridge Dr NE",
    "sg:city":"Seattle",
    "sg:classifiers":[
        {
            "category":"Wholesale",
            "subcategory":"Electrical",
            "type":"Manufacturing & Wholesale Goods"
        }
    ],
    "sg:phone":"+1 206 789 8808",
    "sg:postcode":"98115",
    "sg:province":"WA",
    "sg:tags":[
        "industrial",
        "electronic"
    ],
    "wof:name":"N L Barnes Timesaver",
    "wof:placetype":"venue"
},
  "geometry": {"coordinates":[-122.275324,47.684163],"type":"Point"}
}