{
  "type": "Feature",
  "properties": {
    "iso:country":"US",
    "sg:address":"1201 M St SE",
    "sg:city":"Auburn",
    "sg:classifiers":[
        {
            "category":"Retail",
            "subcategory":"Auto Repair",
            "type":"Services"
        }
    ],
    "sg:phone":"+1 253 906 0810",
    "sg:postcode":"98002",
    "sg:province":"WA",
    "sg:tags":[
        "recycling",
        "tire"
    ],
    "wof:name":"Tire Disposal Recycling Inc",
    "wof:placetype":"venue"
},
  "geometry": {"coordinates":[-122.213396,47.295981],"type":"Point"}
}