{
  "type": "Feature",
  "properties": {
    "addr:full":"2721 W Montgomery Rd Deer Park WA 99006",
    "addr:housenumber":"2721",
    "addr:postcode":"99006",
    "addr:street":"W Montgomery Rd",
    "iso:country":"US",
    "sg:address":"2721 W Montgomery Rd",
    "sg:city":"Deer Park",
    "sg:phone":"+1 509 276 2994",
    "sg:postcode":"99006",
    "sg:province":"WA",
    "sg:tags":[
        "leather"
    ],
    "wof:name":"Rocky Mountain Leather Smith",
    "wof:placetype":"venue"
},
  "geometry": {"coordinates":[-117.455185,47.989274],"type":"Point"}
}