{
  "type": "Feature",
  "properties": {
    "addr:full":"1590 SE Woodridge Dr Port Orchard WA 98366",
    "addr:housenumber":"1590",
    "addr:postcode":"98366",
    "addr:street":"Se Woodridge Dr",
    "iso:country":"US",
    "sg:address":"1590 SE Woodridge Dr",
    "sg:city":"Port Orchard",
    "sg:classifiers":[
        {
            "category":"Health Services",
            "subcategory":"Medical Lab",
            "type":"Services"
        }
    ],
    "sg:phone":"+1 360 871 9705",
    "sg:postcode":"98366",
    "sg:province":"WA",
    "sg:tags":[
        "laboratory",
        "dental"
    ],
    "wof:name":"Empire Crown & Bridge",
    "wof:placetype":"venue"
},
  "geometry": {"coordinates":[-122.58156099999999,47.534775],"type":"Point"}
}