{
  "type": "Feature",
  "properties": {
    "addr:full":"38602 NW 9th Ave La Center WA 98629",
    "addr:housenumber":"38602",
    "addr:postcode":"98629",
    "addr:street":"Nw 9Th Ave",
    "iso:country":"US",
    "sg:address":"38602 NW 9th Ave",
    "sg:city":"La Center",
    "sg:classifiers":[
        {
            "category":"Farming",
            "subcategory":"Nursery",
            "type":"Manufacturing & Wholesale Goods"
        }
    ],
    "sg:phone":"+1 360 263 2282",
    "sg:postcode":"98629",
    "sg:province":"WA",
    "sg:tags":[
        "ornamental"
    ],
    "wof:name":"Schaers Greenhouse",
    "wof:placetype":"venue"
},
  "geometry": {"coordinates":[-122.68069199999999,45.901048],"type":"Point"}
}