{
  "type": "Feature",
  "properties": {
    "addr:full":"16217 95th Ave SE Snohomish WA 98296",
    "addr:housenumber":"16217",
    "addr:postcode":"98296",
    "addr:street":"95Th Ave Se",
    "iso:country":"US",
    "sg:address":"16217 95th Ave SE",
    "sg:city":"Snohomish",
    "sg:classifiers":[
        {
            "category":"Building & Trades",
            "subcategory":"Construction",
            "type":"Services"
        }
    ],
    "sg:phone":"+1 360 668 4163",
    "sg:postcode":"98296",
    "sg:province":"WA",
    "sg:tags":[
        "house"
    ],
    "wof:name":"Fisk Enterprises",
    "wof:placetype":"venue"
},
  "geometry": {"coordinates":[-122.104484,47.849894],"type":"Point"}
}