{
  "type": "Feature",
  "properties": {
    "addr:full":"1541 Campbell Rd Wapato WA 98951",
    "addr:housenumber":"1541",
    "addr:postcode":"98951",
    "addr:street":"Campbell Rd",
    "iso:country":"US",
    "sg:address":"1541 Campbell Rd",
    "sg:city":"Wapato",
    "sg:classifiers":[
        {
            "category":"Organizations",
            "subcategory":"Religious Organization",
            "type":"Services"
        }
    ],
    "sg:phone":"+1 509 877 3315",
    "sg:postcode":"98951",
    "sg:province":"WA",
    "wof:name":"Wapato Bible Baptist Church",
    "wof:placetype":"venue"
},
  "geometry": {"coordinates":[-120.438041,46.440458],"type":"Point"}
}