{
  "type": "Feature",
  "properties": {
    "iso:country":"US",
    "sg:address":"201 S Washington Ave",
    "sg:city":"Newport",
    "sg:classifiers":[
        {
            "category":"Health Services",
            "subcategory":"Clinic",
            "type":"Services"
        }
    ],
    "sg:phone":"+1 509 447 2301",
    "sg:postcode":"99156",
    "sg:province":"WA",
    "wof:name":"Advanced Wellness Clinic",
    "wof:placetype":"venue"
},
  "geometry": {"coordinates":[-117.044051,48.180068],"type":"Point"}
}