{
  "type": "Feature",
  "properties": {
    "iso:country":"US",
    "sg:address":"23000 Edmonds Way",
    "sg:city":"Edmonds",
    "sg:classifiers":[
        {
            "category":"Real Estate",
            "subcategory":"Real Estate Operator",
            "type":"Services"
        }
    ],
    "sg:phone":"+1 425 771 5030",
    "sg:postcode":"98020",
    "sg:province":"WA",
    "sg:tags":[
        "building",
        "apartment"
    ],
    "wof:name":"Woodway Estates Inc",
    "wof:placetype":"venue"
},
  "geometry": {"coordinates":[-122.355711,47.789274],"type":"Point"}
}