{
  "type": "Feature",
  "properties": {
    "iso:country":"US",
    "sg:address":"811 N Deep Creek Rd",
    "sg:city":"Medical Lake",
    "sg:classifiers":[
        {
            "category":"Farming",
            "subcategory":"Livestock Farm",
            "type":"Manufacturing & Wholesale Goods"
        }
    ],
    "sg:phone":"+1 509 244 9415",
    "sg:postcode":"99022",
    "sg:province":"WA",
    "sg:tags":[
        "me",
        "feedlot",
        "equine",
        "beef",
        "cattle"
    ],
    "wof:name":"Deep Creek Farm",
    "wof:placetype":"venue"
},
  "geometry": {"coordinates":[-117.68804900000001,47.660107],"type":"Point"}
}