{
  "type": "Feature",
  "properties": {
    "addr:full":"1802 Perry St Yakima WA 98902",
    "addr:housenumber":"1802",
    "addr:postcode":"98902",
    "addr:street":"Perry St",
    "iso:country":"US",
    "sg:address":"1802 Perry St",
    "sg:city":"Yakima",
    "sg:classifiers":[
        {
            "category":"School Buses",
            "type":"Transportation"
        }
    ],
    "sg:phone":"+1 509 453 2645",
    "sg:postcode":"98902",
    "sg:province":"WA",
    "wof:name":"Central Washington Co Op",
    "wof:placetype":"venue"
},
  "geometry": {"coordinates":[-120.531229,46.573475],"type":"Point"}
}