{
  "type": "Feature",
  "properties": {
    "addr:full":"353 Pleasant Valley Rd Mineral WA 98355",
    "addr:housenumber":"353",
    "addr:postcode":"98355",
    "addr:street":"Pleasant Valley Rd",
    "iso:country":"US",
    "sg:address":"353 Pleasant Valley Rd",
    "sg:city":"Mineral",
    "sg:classifiers":[
        {
            "category":"Freight",
            "type":"Transportation"
        }
    ],
    "sg:phone":"+1 360 492 3601",
    "sg:postcode":"98355",
    "sg:province":"WA",
    "sg:tags":[
        "trucking"
    ],
    "wof:name":"Robertson Robert Trucking",
    "wof:placetype":"venue"
},
  "geometry": {"coordinates":[-122.225323,46.733843],"type":"Point"}
}