{
  "type": "Feature",
  "properties": {
    "addr:full":"532 NE 3rd Ave Ste 100 Camas WA 98607",
    "addr:housenumber":"532",
    "addr:postcode":"98607",
    "addr:street":"Ne 3Rd Ave Ste 100",
    "iso:country":"US",
    "sg:address":"532 NE 3rd Ave Ste 100",
    "sg:city":"Camas",
    "sg:classifiers":[
        {
            "category":"Health Services",
            "subcategory":"Clinic",
            "type":"Services"
        },
        {
            "category":"Health Services",
            "subcategory":"Health Practitioner",
            "type":"Services"
        },
        {
            "category":"Health Services",
            "subcategory":"Chiropractor",
            "type":"Services"
        }
    ],
    "sg:phone":"+1 360 834 6964",
    "sg:postcode":"98607",
    "sg:province":"WA",
    "sg:tags":[
        "acupuncture",
        "medical",
        "chiropractic"
    ],
    "sg:website":"www.fearnnaturalhealth.com",
    "wof:name":"Fearn Natural Health",
    "wof:placetype":"venue"
},
  "geometry": {"coordinates":[-122.402207,45.585885],"type":"Point"}
}