{
  "type": "Feature",
  "properties": {
    "addr:full":"7029 Falcon Ct Arlington WA 98223",
    "addr:housenumber":"7029",
    "addr:postcode":"98223",
    "addr:street":"Falcon Ct",
    "iso:country":"US",
    "sg:address":"7029 Falcon Ct",
    "sg:city":"Arlington",
    "sg:classifiers":[
        {
            "category":"Home & Garden",
            "subcategory":"Carpets & Floor Coverings",
            "type":"Retail Goods"
        },
        {
            "category":"Professional",
            "subcategory":"Computer Services",
            "type":"Services"
        }
    ],
    "sg:phone":"+1 360 435 0348",
    "sg:postcode":"98223",
    "sg:province":"WA",
    "sg:tags":[
        "dealer",
        "related",
        "rug"
    ],
    "wof:name":"Emerald City Carpeting",
    "wof:placetype":"venue"
},
  "geometry": {"coordinates":[-122.134343,48.166001],"type":"Point"}
}