{
  "type": "Feature",
  "properties": {
    "iso:country":"US",
    "sg:address":"3002 S Meridian",
    "sg:city":"Puyallup",
    "sg:classifiers":[
        {
            "category":"Retail",
            "subcategory":"Auto Repair",
            "type":"Services"
        }
    ],
    "sg:phone":"+1 253 845 4505",
    "sg:postcode":"98373",
    "sg:province":"WA",
    "sg:tags":[
        "repairing",
        "automobile"
    ],
    "wof:name":"Hilltop Service",
    "wof:placetype":"venue"
},
  "geometry": {"coordinates":[-122.293324,47.165217],"type":"Point"}
}