{
  "type": "Feature",
  "properties": {
    "addr:full":"4302 Fremont Ave N Seattle WA 98103",
    "addr:housenumber":"4302",
    "addr:postcode":"98103",
    "addr:street":"Fremont Ave N",
    "iso:country":"US",
    "sg:address":"4302 Fremont Ave N",
    "sg:city":"Seattle",
    "sg:classifiers":[
        {
            "category":"Fast Food",
            "type":"Food & Drink"
        },
        {
            "category":"Food & Beverages",
            "subcategory":"Bakery",
            "type":"Retail Goods"
        }
    ],
    "sg:phone":"+1 206 547 2600",
    "sg:postcode":"98103",
    "sg:province":"WA",
    "sg:tags":[
        "burger",
        "sandwich"
    ],
    "wof:name":"Uneeda Burger",
    "wof:placetype":"venue"
},
  "geometry": {"coordinates":[-122.34991100000001,47.659551],"type":"Point"}
}