{
  "type": "Feature",
  "properties": {
    "addr:full":"12570 Ranger Rd Leavenworth WA 98826",
    "addr:housenumber":"12570",
    "addr:postcode":"98826",
    "addr:street":"Ranger Rd",
    "iso:country":"US",
    "sg:address":"12570 Ranger Rd",
    "sg:city":"Leavenworth",
    "sg:classifiers":[
        {
            "category":"Building & Trades",
            "subcategory":"Construction",
            "type":"Services"
        }
    ],
    "sg:phone":"+1 509 433 1390",
    "sg:postcode":"98826",
    "sg:province":"WA",
    "sg:tags":[
        "general",
        "contractor"
    ],
    "wof:name":"Paragon Construction",
    "wof:placetype":"venue"
},
  "geometry": {"coordinates":[-120.668982,47.602601],"type":"Point"}
}