{
  "type": "Feature",
  "properties": {
    "iso:country":"US",
    "sg:address":"8016 N Division St",
    "sg:city":"Spokane",
    "sg:classifiers":[
        {
            "category":"Shopping",
            "subcategory":"Computers & Home Electronics",
            "type":"Retail Goods"
        }
    ],
    "sg:phone":"+1 509 467 4434",
    "sg:postcode":"99208",
    "sg:province":"WA",
    "sg:tags":[
        "high",
        "fidelity",
        "stereophonic"
    ],
    "sg:website":"www.magnoliahifi.com",
    "wof:name":"Magnolia Audio Video",
    "wof:placetype":"venue"
},
  "geometry": {"coordinates":[-117.411298,47.731727],"type":"Point"}
}