{
  "type": "Feature",
  "properties": {
    "addr:full":"6135 Seaview Ave NW Ste 2E Seattle WA 98107",
    "addr:housenumber":"6135",
    "addr:postcode":"98107",
    "addr:street":"Seaview Ave Nw Ste 2E",
    "iso:country":"US",
    "sg:address":"6135 Seaview Ave NW Ste 2E",
    "sg:city":"Seattle",
    "sg:classifiers":[
        {
            "category":"Health Services",
            "subcategory":"Doctor",
            "type":"Services"
        },
        {
            "category":"Health Services",
            "subcategory":"Dentist",
            "type":"Services"
        }
    ],
    "sg:phone":"+1 206 782 9183",
    "sg:postcode":"98107",
    "sg:province":"WA",
    "wof:name":"Swaid Albaraa Mhd DDS",
    "wof:placetype":"venue"
},
  "geometry": {"coordinates":[-122.40655700000001,47.673002],"type":"Point"}
}