{
  "type": "Feature",
  "properties": {
    "addr:full":"2712 Eastlake Ave E Seattle WA 98102",
    "addr:housenumber":"2712",
    "addr:postcode":"98102",
    "addr:street":"Eastlake Ave E",
    "iso:country":"US",
    "sg:address":"2712 Eastlake Ave E",
    "sg:city":"Seattle",
    "sg:classifiers":[
        {
            "category":"Professional",
            "subcategory":"Art Services",
            "type":"Services"
        }
    ],
    "sg:phone":"+1 206 545 1010",
    "sg:postcode":"98102",
    "sg:province":"WA",
    "sg:tags":[
        "commercial",
        "graphic",
        "design"
    ],
    "wof:name":"Z Lane Enterprises Inc",
    "wof:placetype":"venue"
},
  "geometry": {"coordinates":[-122.325806,47.645482],"type":"Point"}
}