{
  "type": "Feature",
  "properties": {
    "addr:full":"23308 NE 148th St Brush Prairie WA 98606",
    "addr:housenumber":"23308",
    "addr:postcode":"98606",
    "addr:street":"Ne 148Th St",
    "iso:country":"US",
    "sg:address":"23308 NE 148th St",
    "sg:city":"Brush Prairie",
    "sg:classifiers":[
        {
            "category":"Retail",
            "subcategory":"Repair Shop",
            "type":"Services"
        }
    ],
    "sg:phone":"+1 360 254 3442",
    "sg:postcode":"98606",
    "sg:province":"WA",
    "wof:name":"Quilting Battz",
    "wof:placetype":"venue"
},
  "geometry": {"coordinates":[-122.432541,45.729161],"type":"Point"}
}