{
  "type": "Feature",
  "properties": {
    "addr:full":"207 W Boone Ave Spokane WA 99201",
    "addr:housenumber":"207",
    "addr:postcode":"99201",
    "addr:street":"W Boone Ave",
    "iso:country":"US",
    "sg:address":"207 W Boone Ave",
    "sg:city":"Spokane",
    "sg:classifiers":[
        {
            "category":"Real Estate",
            "subcategory":"Real Estate Services",
            "type":"Services"
        },
        {
            "category":"Building & Trades",
            "subcategory":"Cleaning & Sanitation",
            "type":"Services"
        },
        {
            "category":"Professional",
            "subcategory":"Management & Consulting",
            "type":"Services"
        },
        {
            "category":"Professional",
            "subcategory":"Business Services",
            "type":"Services"
        },
        {
            "category":"Professional",
            "subcategory":"Engineering",
            "type":"Services"
        }
    ],
    "sg:phone":"+1 509 459 9220",
    "sg:postcode":"99201",
    "sg:province":"WA",
    "sg:tags":[
        "consultant",
        "environmental",
        "ecological",
        "maintenance",
        "cleaners-interior",
        "inspection",
        "engineer"
    ],
    "sg:website":"http://www.efulcrum.net",
    "wof:name":"Fulcrum Environmental Consulting Inc",
    "wof:placetype":"venue"
},
  "geometry": {"coordinates":[-117.414424,47.668091],"type":"Point"}
}