{
  "type": "Feature",
  "properties": {
    "addr:full":"11135 NE 33rd Pl Bellevue WA 98004",
    "addr:housenumber":"11135",
    "addr:postcode":"98004",
    "addr:street":"Ne 33Rd Pl",
    "iso:country":"US",
    "sg:address":"11135 NE 33rd Pl",
    "sg:city":"Bellevue",
    "sg:classifiers":[
        {
            "category":"Wholesale",
            "subcategory":"Machinery & Supplies",
            "type":"Manufacturing & Wholesale Goods"
        }
    ],
    "sg:phone":"+1 425 828 6390",
    "sg:postcode":"98004",
    "sg:province":"WA",
    "sg:tags":[
        "equipment",
        "irrigation",
        "system"
    ],
    "sg:website":"www.horizononline.com",
    "wof:name":"Horizon Irrigation & Turf",
    "wof:placetype":"venue"
},
  "geometry": {"coordinates":[-122.19201,47.640259],"type":"Point"}
}