{
  "type": "Feature",
  "properties": {
    "addr:full":"425 N 1st St Montesano WA 98563",
    "addr:housenumber":"425",
    "addr:postcode":"98563",
    "addr:street":"N 1St St",
    "iso:country":"US",
    "sg:address":"425 N 1st St",
    "sg:city":"Montesano",
    "sg:classifiers":[
        {
            "category":"Wholesale",
            "subcategory":"Groceries",
            "type":"Manufacturing & Wholesale Goods"
        }
    ],
    "sg:phone":"+1 360 249 3388",
    "sg:postcode":"98563",
    "sg:province":"WA",
    "sg:tags":[
        "snack"
    ],
    "wof:name":"Harr Distributing",
    "wof:placetype":"venue"
},
  "geometry": {"coordinates":[-123.602121,46.985006],"type":"Point"}
}