{
  "type": "Feature",
  "properties": {
    "addr:full":"10706 Pioneer Dr Anderson Island WA 98303",
    "addr:housenumber":"10706",
    "addr:postcode":"98303",
    "addr:street":"Pioneer Dr Anderson Island",
    "iso:country":"US",
    "sg:address":"10706 Pioneer Dr",
    "sg:city":"Anderson Island",
    "sg:classifiers":[
        {
            "category":"Utilities",
            "subcategory":"Electric",
            "type":"Services"
        }
    ],
    "sg:phone":"+1 253 884 6297",
    "sg:postcode":"98303",
    "sg:province":"WA",
    "wof:name":"Tanner Electric Cooperative",
    "wof:placetype":"venue"
},
  "geometry": {"coordinates":[-122.693237,47.159019],"type":"Point"}
}