{
  "type": "Feature",
  "properties": {
    "addr:full":"4927 SW 324th Pl Federal Way WA 98023",
    "addr:housenumber":"4927",
    "addr:postcode":"98023",
    "addr:street":"Sw 324Th Pl",
    "iso:country":"US",
    "sg:address":"4927 SW 324th Pl",
    "sg:city":"Federal Way",
    "sg:classifiers":[
        {
            "category":"Utilities",
            "subcategory":"Refuse",
            "type":"Services"
        }
    ],
    "sg:phone":"+1 253 661 1653",
    "sg:postcode":"98023",
    "sg:province":"WA",
    "sg:tags":[
        "system"
    ],
    "wof:name":"Dlc Recycling LLC",
    "wof:placetype":"venue"
},
  "geometry": {"coordinates":[-122.39584000000001,47.311182],"type":"Point"}
}