{
  "type": "Feature",
  "properties": {
    "addr:full":"4828 192nd St NW Stanwood WA 98292",
    "addr:housenumber":"4828",
    "addr:postcode":"98292",
    "addr:street":"192Nd St Nw",
    "iso:country":"US",
    "sg:address":"4828 192nd St NW",
    "sg:city":"Stanwood",
    "sg:classifiers":[
        {
            "category":"Shopping",
            "subcategory":"Hobbies, Toys, & Games",
            "type":"Retail Goods"
        },
        {
            "category":"Shopping",
            "subcategory":"Crafts & Fabrics",
            "type":"Retail Goods"
        }
    ],
    "sg:phone":"+1 360 652 9751",
    "sg:postcode":"98292",
    "sg:province":"WA",
    "sg:tags":[
        "shop",
        "hobby",
        "model",
        "supplies-wholesale",
        "manufacturer"
    ],
    "wof:name":"Karen Anns Kreations",
    "wof:placetype":"venue"
},
  "geometry": {"coordinates":[-122.297574,48.170225],"type":"Point"}
}