{
  "type": "Feature",
  "properties": {
    "addr:full":"116 Vine St Seattle WA 98121",
    "addr:housenumber":"116",
    "addr:postcode":"98121",
    "addr:street":"Vine St",
    "iso:country":"US",
    "sg:address":"116 Vine St",
    "sg:city":"Seattle",
    "sg:classifiers":[
        {
            "category":"Building & Trades",
            "subcategory":"Construction",
            "type":"Services"
        }
    ],
    "sg:phone":"+1 206 322 2152",
    "sg:postcode":"98121",
    "sg:province":"WA",
    "sg:tags":[
        "interior",
        "design"
    ],
    "wof:name":"J Qb Ltd",
    "wof:placetype":"venue"
},
  "geometry": {"coordinates":[-122.34899900000001,47.6157],"type":"Point"}
}