{
  "type": "Feature",
  "properties": {
    "addr:full":"5202 S Proctor St Tacoma WA 98409",
    "addr:housenumber":"5202",
    "addr:postcode":"98409",
    "addr:street":"S Proctor St",
    "iso:country":"US",
    "sg:address":"5202 S Proctor St",
    "sg:city":"Tacoma",
    "sg:classifiers":[
        {
            "category":"Professional",
            "subcategory":"Business Services",
            "type":"Services"
        }
    ],
    "sg:phone":"+1 253 474 7109",
    "sg:postcode":"98409",
    "sg:province":"WA",
    "wof:name":"Airspace Recording",
    "wof:placetype":"venue"
},
  "geometry": {"coordinates":[-122.48922899999999,47.207801],"type":"Point"}
}