{
  "type": "Feature",
  "properties": {
    "addr:full":"825 S 3rd St Renton WA 98057",
    "addr:housenumber":"825",
    "addr:postcode":"98057",
    "addr:street":"S 3Rd St",
    "iso:country":"US",
    "sg:address":"825 S 3rd St",
    "sg:city":"Renton",
    "sg:classifiers":[
        {
            "category":"Building & Trades",
            "subcategory":"Locksmith",
            "type":"Services"
        }
    ],
    "sg:phone":"+1 425 738 4025",
    "sg:postcode":"98057",
    "sg:province":"WA",
    "sg:tags":[
        "key"
    ],
    "wof:name":"Renton 24 Hour 7 Days Locksmith",
    "wof:placetype":"venue"
},
  "geometry": {"coordinates":[-122.20631400000001,47.479563],"type":"Point"}
}