{
  "type": "Feature",
  "properties": {
    "iso:country":"US",
    "sg:address":"25905 NE Hinness Rd",
    "sg:city":"Brush Prairie",
    "sg:classifiers":[
        {
            "category":"Education",
            "subcategory":"Special Training",
            "type":"Public Place"
        }
    ],
    "sg:phone":"+1 360 892 4343",
    "sg:postcode":"98606",
    "sg:province":"WA",
    "wof:name":"Patricia L Bartlett",
    "wof:placetype":"venue"
},
  "geometry": {"coordinates":[-122.403139,45.724281],"type":"Point"}
}