{
  "type": "Feature",
  "properties": {
    "addr:full":"22131 17th Pl W Bothell WA 98021",
    "addr:housenumber":"22131",
    "addr:postcode":"98021",
    "addr:street":"17Th Pl W",
    "iso:country":"US",
    "sg:address":"22131 17th Pl W",
    "sg:city":"Bothell",
    "sg:classifiers":[
        {
            "category":"Building & Trades",
            "subcategory":"Construction",
            "type":"Services"
        }
    ],
    "sg:phone":"+1 425 485 2312",
    "sg:postcode":"98021",
    "sg:province":"WA",
    "sg:tags":[
        "hanging",
        "contractor"
    ],
    "wof:name":"Pearl Painting Services",
    "wof:placetype":"venue"
},
  "geometry": {"coordinates":[-122.25672400000001,47.795796],"type":"Point"}
}