{
  "type": "Feature",
  "properties": {
    "addr:full":"2863 Verlane St Langley WA 98260",
    "addr:housenumber":"2863",
    "addr:postcode":"98260",
    "addr:street":"Verlane St",
    "iso:country":"US",
    "sg:address":"2863 Verlane St",
    "sg:city":"Langley",
    "sg:classifiers":[
        {
            "category":"Home & Garden",
            "subcategory":"Building Materials",
            "type":"Retail Goods"
        }
    ],
    "sg:phone":"+1 360 321 6424",
    "sg:postcode":"98260",
    "sg:province":"WA",
    "sg:tags":[
        "lumber"
    ],
    "wof:name":"Hanson's Building Supply Inc",
    "wof:placetype":"venue"
},
  "geometry": {"coordinates":[-122.45707400000001,47.998934],"type":"Point"}
}