{
  "type": "Feature",
  "properties": {
    "addr:full":"829 Israel Rd SW Olympia WA 98501",
    "addr:housenumber":"829",
    "addr:postcode":"98501",
    "addr:street":"Israel Rd Sw",
    "iso:country":"US",
    "sg:address":"829 Israel Rd SW",
    "sg:city":"Olympia",
    "sg:classifiers":[
        {
            "category":"Retail",
            "subcategory":"Portrait Studio",
            "type":"Services"
        }
    ],
    "sg:phone":"+1 360 709 0766",
    "sg:postcode":"98501",
    "sg:province":"WA",
    "sg:tags":[
        "photo"
    ],
    "wof:name":"C&C Photography",
    "wof:placetype":"venue"
},
  "geometry": {"coordinates":[-122.91795500000001,46.985339],"type":"Point"}
}