{
  "type": "Feature",
  "properties": {
    "addr:full":"5103 Mosquito Lake Rd Deming WA 98244",
    "addr:housenumber":"5103",
    "addr:postcode":"98244",
    "addr:street":"Mosquito Lake Rd",
    "iso:country":"US",
    "sg:address":"5103 Mosquito Lake Rd",
    "sg:city":"Deming",
    "sg:classifiers":[
        {
            "category":"Social Services",
            "type":"Services"
        }
    ],
    "sg:phone":"+1 360 592 5403",
    "sg:postcode":"98244",
    "sg:province":"WA",
    "sg:tags":[
        "executive"
    ],
    "wof:name":"Welcome Senior Center",
    "wof:placetype":"venue"
},
  "geometry": {"coordinates":[-122.13032,48.826734],"type":"Point"}
}