{
  "type": "Feature",
  "properties": {
    "addr:full":"420 N Regent St Burlington WA 98233",
    "addr:housenumber":"420",
    "addr:postcode":"98233",
    "addr:street":"N Regent St",
    "iso:country":"US",
    "sg:address":"420 N Regent St",
    "sg:city":"Burlington",
    "sg:classifiers":[
        {
            "category":"Social Services",
            "subcategory":"Child Care",
            "type":"Services"
        }
    ],
    "sg:phone":"+1 360 755 0583",
    "sg:postcode":"98233",
    "sg:province":"WA",
    "sg:tags":[
        "nursery",
        "center",
        "day"
    ],
    "wof:name":"Sunny Smiles Daycare",
    "wof:placetype":"venue"
},
  "geometry": {"coordinates":[-122.321777,48.478164],"type":"Point"}
}