{
  "type": "Feature",
  "properties": {
    "iso:country":"US",
    "sg:address":"28866 156th Ave SE",
    "sg:city":"Kent",
    "sg:classifiers":[
        {
            "category":"Professional",
            "type":"Services"
        }
    ],
    "sg:phone":"+1 253 630 3060",
    "sg:postcode":"98042",
    "sg:province":"WA",
    "wof:name":"Jetcom Inc",
    "wof:placetype":"venue"
},
  "geometry": {"coordinates":[-122.13359800000001,47.34205],"type":"Point"}
}