{
  "type": "Feature",
  "properties": {
    "addr:full":"2410 W Manor Pl Seattle WA 98199",
    "addr:housenumber":"2410",
    "addr:postcode":"98199",
    "addr:street":"W Manor Pl",
    "iso:country":"US",
    "sg:address":"2410 W Manor Pl",
    "sg:city":"Seattle",
    "sg:classifiers":[
        {
            "category":"Manufacturing",
            "subcategory":"Food",
            "type":"Manufacturing & Wholesale Goods"
        }
    ],
    "sg:phone":"+1 206 283 2722",
    "sg:postcode":"98199",
    "sg:province":"WA",
    "sg:tags":[
        "packer",
        "fish"
    ],
    "wof:name":"Crab King Seafood Specialties",
    "wof:placetype":"venue"
},
  "geometry": {"coordinates":[-122.388685,47.653609],"type":"Point"}
}