{
  "type": "Feature",
  "properties": {
    "iso:country":"US",
    "sg:address":"3436 14th Ave S",
    "sg:city":"Seattle",
    "sg:classifiers":[
        {
            "category":"Home & Garden",
            "subcategory":"Furniture",
            "type":"Retail Goods"
        }
    ],
    "sg:phone":"+1 206 328 6597",
    "sg:postcode":"98144",
    "sg:province":"WA",
    "wof:name":"Withycombe Furniture Stud",
    "wof:placetype":"venue"
},
  "geometry": {"coordinates":[-122.31473200000001,47.572813],"type":"Point"}
}