{
  "type": "Feature",
  "properties": {
    "addr:full":"57 Kinkaid Dr Coupeville WA 98239",
    "addr:housenumber":"57",
    "addr:postcode":"98239",
    "addr:street":"Kinkaid Dr",
    "iso:country":"US",
    "sg:address":"57 Kinkaid Dr",
    "sg:city":"Coupeville",
    "sg:classifiers":[
        {
            "category":"Professional",
            "subcategory":"Business Services",
            "type":"Services"
        }
    ],
    "sg:phone":"+1 360 678 5799",
    "sg:postcode":"98239",
    "sg:province":"WA",
    "sg:tags":[
        "consultant",
        "coach"
    ],
    "wof:name":"Ballard Consulting",
    "wof:placetype":"venue"
},
  "geometry": {"coordinates":[-122.616906,48.168909],"type":"Point"}
}