{
  "type": "Feature",
  "properties": {
    "addr:full":"22611 NE 142nd Pl Woodinville WA 98077",
    "addr:housenumber":"22611",
    "addr:postcode":"98077",
    "addr:street":"Ne 142Nd Pl",
    "iso:country":"US",
    "sg:address":"22611 NE 142nd Pl",
    "sg:city":"Woodinville",
    "sg:classifiers":[
        {
            "category":"Manufacturing",
            "subcategory":"Building Materials",
            "type":"Manufacturing & Wholesale Goods"
        }
    ],
    "sg:phone":"+1 425 556 9802",
    "sg:postcode":"98077",
    "sg:province":"WA",
    "sg:tags":[
        "mfg"
    ],
    "wof:name":"Edward Gordon Byrd",
    "wof:placetype":"venue"
},
  "geometry": {"coordinates":[-122.03644300000001,47.729103],"type":"Point"}
}