{
  "type": "Feature",
  "properties": {
    "addr:full":"220 N Main St Colfax WA 99111",
    "addr:housenumber":"220",
    "addr:postcode":"99111",
    "addr:street":"N Main St",
    "iso:country":"US",
    "sg:address":"220 N Main St",
    "sg:city":"Colfax",
    "sg:classifiers":[
        {
            "category":"Home & Garden",
            "subcategory":"Furniture",
            "type":"Retail Goods"
        }
    ],
    "sg:phone":"+1 509 397 6827",
    "sg:postcode":"99111",
    "sg:province":"WA",
    "sg:tags":[
        "floor",
        "covering"
    ],
    "wof:name":"Hunter's Furniture",
    "wof:placetype":"venue"
},
  "geometry": {"coordinates":[-117.364515,46.882599],"type":"Point"}
}