{
  "type": "Feature",
  "properties": {
    "addr:full":"5202 Jones Rd Sumas WA 98295",
    "addr:housenumber":"5202",
    "addr:postcode":"98295",
    "addr:street":"Jones Rd",
    "iso:country":"US",
    "sg:address":"5202 Jones Rd",
    "sg:city":"Sumas",
    "sg:classifiers":[
        {
            "category":"Farming",
            "subcategory":"Dairy Farm",
            "type":"Manufacturing & Wholesale Goods"
        }
    ],
    "sg:phone":"+1 360 961 0777",
    "sg:postcode":"98295",
    "sg:province":"WA",
    "wof:name":"Vreugdenhil Farms Inc",
    "wof:placetype":"venue"
},
  "geometry": {"coordinates":[-122.21392400000001,48.999983],"type":"Point"}
}