{
  "type": "Feature",
  "properties": {
    "addr:full":"2621 Trevue Ave SW Olympia WA 98512",
    "addr:housenumber":"2621",
    "addr:postcode":"98512",
    "addr:street":"Trevue Ave Sw",
    "iso:country":"US",
    "sg:address":"2621 Trevue Ave SW",
    "sg:city":"Olympia",
    "sg:classifiers":[
        {
            "category":"Retail",
            "subcategory":"Auto Repair",
            "type":"Services"
        }
    ],
    "sg:phone":"+1 360 402 7866",
    "sg:postcode":"98512",
    "sg:province":"WA",
    "sg:tags":[
        "general"
    ],
    "wof:name":"McKinneys Auto Detail Inc",
    "wof:placetype":"venue"
},
  "geometry": {"coordinates":[-122.93831900000001,46.91991],"type":"Point"}
}