{
  "type": "Feature",
  "properties": {
    "addr:full":"3231 Hillside Rd Deming WA 98244",
    "addr:housenumber":"3231",
    "addr:postcode":"98244",
    "addr:street":"Hillside Rd",
    "iso:country":"US",
    "sg:address":"3231 Hillside Rd",
    "sg:city":"Deming",
    "sg:classifiers":[
        {
            "category":"Manufacturing",
            "subcategory":"Apparel",
            "type":"Manufacturing & Wholesale Goods"
        }
    ],
    "sg:phone":"+1 360 592 9018",
    "sg:postcode":"98244",
    "sg:province":"WA",
    "sg:tags":[
        "outerwear",
        "mfg"
    ],
    "wof:name":"Cetus",
    "wof:placetype":"venue"
},
  "geometry": {"coordinates":[-122.223555,48.76351],"type":"Point"}
}