{
  "type": "Feature",
  "properties": {
    "addr:full":"2808 Hoyt Ave Everett WA 98201",
    "addr:housenumber":"2808",
    "addr:postcode":"98201",
    "addr:street":"Hoyt Ave",
    "iso:country":"US",
    "sg:address":"2808 Hoyt Ave",
    "sg:city":"Everett",
    "sg:classifiers":[
        {
            "category":"Wholesale",
            "subcategory":"Medical Equipment & Supplies",
            "type":"Manufacturing & Wholesale Goods"
        }
    ],
    "sg:phone":"+1 425 303 8797",
    "sg:postcode":"98201",
    "sg:province":"WA",
    "sg:tags":[
        "oxygen"
    ],
    "wof:name":"Lincare",
    "wof:placetype":"venue"
},
  "geometry": {"coordinates":[-122.21008500000001,47.979928],"type":"Point"}
}