{
  "type": "Feature",
  "properties": {
    "addr:full":"4719 W Garden Springs Rd Spokane WA 99224",
    "addr:housenumber":"4719",
    "addr:postcode":"99224",
    "addr:street":"W Garden Springs Rd",
    "iso:country":"US",
    "sg:address":"4719 W Garden Springs Rd",
    "sg:city":"Spokane",
    "sg:classifiers":[
        {
            "category":"Professional",
            "subcategory":"Art Services",
            "type":"Services"
        }
    ],
    "sg:phone":"+1 509 455 9769",
    "sg:postcode":"99224",
    "sg:province":"WA",
    "sg:tags":[
        "commercial",
        "design"
    ],
    "wof:name":"D&L Graphics Inc",
    "wof:placetype":"venue"
},
  "geometry": {"coordinates":[-117.476894,47.632601],"type":"Point"}
}