{
  "type": "Feature",
  "properties": {
    "iso:country":"US",
    "sg:address":"1 5th St",
    "sg:city":"Wenatchee",
    "sg:classifiers":[
        {
            "category":"Professional",
            "subcategory":"Lawyer & Legal Services",
            "type":"Services"
        }
    ],
    "sg:phone":"+1 509 662 1954",
    "sg:postcode":"98801",
    "sg:province":"WA",
    "sg:tags":[
        "attorney"
    ],
    "sg:website":"www.omwlaw.com",
    "wof:name":"Ogden Murphy Wallace",
    "wof:placetype":"venue"
},
  "geometry": {"coordinates":[-120.314567,47.43137],"type":"Point"}
}