{
  "type": "Feature",
  "properties": {
    "addr:full":"415 Index Pl NE Renton WA 98056",
    "addr:housenumber":"415",
    "addr:postcode":"98056",
    "addr:street":"Index Pl Ne",
    "iso:country":"US",
    "sg:address":"415 Index Pl NE",
    "sg:city":"Renton",
    "sg:classifiers":[
        {
            "category":"Building & Trades",
            "subcategory":"Plumbing",
            "type":"Services"
        },
        {
            "category":"Building & Trades",
            "subcategory":"Cleaning & Sanitation",
            "type":"Services"
        }
    ],
    "sg:phone":"+1 425 228 1150",
    "sg:postcode":"98056",
    "sg:province":"WA",
    "sg:tags":[
        "tanks-treatment",
        "tank",
        "system",
        "septic",
        "supply"
    ],
    "wof:name":"Scotts Septic Service",
    "wof:placetype":"venue"
},
  "geometry": {"coordinates":[-122.180347,47.488728],"type":"Point"}
}