{
  "type": "Feature",
  "properties": {
    "addr:full":"709 37th St Anacortes WA 98221",
    "addr:housenumber":"709",
    "addr:postcode":"98221",
    "addr:street":"37Th St",
    "iso:country":"US",
    "sg:address":"709 37th St",
    "sg:city":"Anacortes",
    "sg:classifiers":[
        {
            "category":"Insurance",
            "subcategory":"Insurance Agent",
            "type":"Services"
        }
    ],
    "sg:phone":"+1 360 588 8302",
    "sg:postcode":"98221",
    "sg:province":"WA",
    "wof:name":"ADB Insurance",
    "wof:placetype":"venue"
},
  "geometry": {"coordinates":[-122.609583,48.492266],"type":"Point"}
}