{
  "type": "Feature",
  "properties": {
    "addr:full":"3246 23rd Ave W Seattle WA 98199",
    "addr:housenumber":"3246",
    "addr:postcode":"98199",
    "addr:street":"23Rd Ave W",
    "iso:country":"US",
    "sg:address":"3246 23rd Ave W",
    "sg:city":"Seattle",
    "sg:classifiers":[
        {
            "category":"Real Estate",
            "subcategory":"Architect",
            "type":"Services"
        }
    ],
    "sg:phone":"+1 206 286 8546",
    "sg:postcode":"98199",
    "sg:province":"WA",
    "sg:tags":[
        "building",
        "construction"
    ],
    "wof:name":"Home Builders Consulting",
    "wof:placetype":"venue"
},
  "geometry": {"coordinates":[-122.385902,47.649887],"type":"Point"}
}