{
  "type": "Feature",
  "properties": {
    "addr:full":"14524 SE 46th St Bellevue WA 98006",
    "addr:housenumber":"14524",
    "addr:postcode":"98006",
    "addr:street":"Se 46Th St",
    "iso:country":"US",
    "sg:address":"14524 SE 46th St",
    "sg:city":"Bellevue",
    "sg:classifiers":[
        {
            "category":"Personal",
            "subcategory":"Beauty Salon",
            "type":"Services"
        }
    ],
    "sg:phone":"+1 425 746 1580",
    "sg:postcode":"98006",
    "sg:province":"WA",
    "sg:tags":[
        "shop"
    ],
    "wof:name":"Alternative Salon Concepts",
    "wof:placetype":"venue"
},
  "geometry": {"coordinates":[-122.14445000000001,47.563572],"type":"Point"}
}