{
  "type": "Feature",
  "properties": {
    "addr:full":"3820 NE 92nd St Seattle WA 98115",
    "addr:housenumber":"3820",
    "addr:postcode":"98115",
    "addr:street":"Ne 92Nd St",
    "iso:country":"US",
    "sg:address":"3820 NE 92nd St",
    "sg:city":"Seattle",
    "sg:classifiers":[
        {
            "category":"Professional",
            "subcategory":"Management & Consulting",
            "type":"Services"
        }
    ],
    "sg:phone":"+1 206 525 7497",
    "sg:postcode":"98115",
    "sg:province":"WA",
    "sg:tags":[
        "business"
    ],
    "wof:name":"Sharon Glein Consulting Servic",
    "wof:placetype":"venue"
},
  "geometry": {"coordinates":[-122.28579000000001,47.695324],"type":"Point"}
}