{
  "type": "Feature",
  "properties": {
    "addr:full":"191 Deweese Ln Yakima WA 98901",
    "addr:housenumber":"191",
    "addr:postcode":"98901",
    "addr:street":"Deweese Ln",
    "iso:country":"US",
    "sg:address":"191 Deweese Ln",
    "sg:city":"Yakima",
    "sg:classifiers":[
        {
            "category":"Real Estate",
            "subcategory":"Surveying",
            "type":"Services"
        }
    ],
    "sg:phone":"+1 509 576 0441",
    "sg:postcode":"98901",
    "sg:province":"WA",
    "sg:tags":[
        "surveyor"
    ],
    "wof:name":"Thomas F Upton Surveying",
    "wof:placetype":"venue"
},
  "geometry": {"coordinates":[-120.45656,46.69112],"type":"Point"}
}