{
  "type": "Feature",
  "properties": {
    "addr:full":"29910 Webster Rd E Graham WA 98338",
    "addr:housenumber":"29910",
    "addr:postcode":"98338",
    "addr:street":"Webster Rd E",
    "iso:country":"US",
    "sg:address":"29910 Webster Rd E",
    "sg:city":"Graham",
    "sg:classifiers":[
        {
            "category":"Manufacturing",
            "subcategory":"Lumber",
            "type":"Manufacturing & Wholesale Goods"
        }
    ],
    "sg:phone":"+1 253 847 7695",
    "sg:postcode":"98338",
    "sg:province":"WA",
    "sg:tags":[
        "company",
        "logging"
    ],
    "wof:name":"Mc Fadden Logging Co",
    "wof:placetype":"venue"
},
  "geometry": {"coordinates":[-122.31652099999999,46.9845],"type":"Point"}
}