{
  "type": "Feature",
  "properties": {
    "addr:full":"8730 S Tacoma Way Lakewood WA 98499",
    "addr:housenumber":"8730",
    "addr:postcode":"98499",
    "addr:street":"S Tacoma Way",
    "iso:country":"US",
    "sg:address":"8730 S Tacoma Way",
    "sg:city":"Lakewood",
    "sg:classifiers":[
        {
            "category":"Restaurant",
            "type":"Food & Drink"
        }
    ],
    "sg:phone":"+1 253 984 7879",
    "sg:postcode":"98499",
    "sg:province":"WA",
    "sg:tags":[
        "eating"
    ],
    "wof:name":"Beul Mee Restaurant",
    "wof:placetype":"venue"
},
  "geometry": {"coordinates":[-122.483901,47.178748],"type":"Point"}
}