{
  "type": "Feature",
  "properties": {
    "addr:full":"6227 139th Ave SE Snohomish WA 98290",
    "addr:housenumber":"6227",
    "addr:postcode":"98290",
    "addr:street":"139Th Ave Se",
    "iso:country":"US",
    "sg:address":"6227 139th Ave SE",
    "sg:city":"Snohomish",
    "sg:classifiers":[
        {
            "category":"Retail",
            "subcategory":"Repair Shop",
            "type":"Services"
        }
    ],
    "sg:phone":"+1 360 563 0130",
    "sg:postcode":"98290",
    "sg:province":"WA",
    "wof:name":"Odoms Inc",
    "wof:placetype":"venue"
},
  "geometry": {"coordinates":[-122.04477799999999,47.940408],"type":"Point"}
}