{
  "type": "Feature",
  "properties": {
    "addr:full":"1044 B St Woodland WA 98674",
    "addr:housenumber":"1044",
    "addr:postcode":"98674",
    "addr:street":"B St",
    "iso:country":"US",
    "sg:address":"1044 B St",
    "sg:city":"Woodland",
    "sg:classifiers":[
        {
            "category":"Health Services",
            "subcategory":"Chiropractor",
            "type":"Services"
        }
    ],
    "sg:phone":"+1 253 225 8314",
    "sg:postcode":"98674",
    "sg:province":"WA",
    "wof:name":"Ronald S Gerne DC PS",
    "wof:placetype":"venue"
},
  "geometry": {"coordinates":[-122.740996,45.906845],"type":"Point"}
}