{
  "type": "Feature",
  "properties": {
    "addr:full":"510 W 1st Ave Kennewick WA 99336",
    "addr:housenumber":"510",
    "addr:postcode":"99336",
    "addr:street":"W 1St Ave",
    "iso:country":"US",
    "sg:address":"510 W 1st Ave",
    "sg:city":"Kennewick",
    "sg:classifiers":[
        {
            "category":"Shopping",
            "type":"Retail Goods"
        }
    ],
    "sg:phone":"+1 509 586 0681",
    "sg:postcode":"99336",
    "sg:province":"WA",
    "sg:tags":[
        "coin",
        "dealer",
        "supply"
    ],
    "wof:name":"R & D Coins & Jewelry",
    "wof:placetype":"venue"
},
  "geometry": {"coordinates":[-119.126108,46.207733],"type":"Point"}
}