{
  "type": "Feature",
  "properties": {
    "addr:full":"122 SW 10th St College Place WA 99324",
    "addr:housenumber":"122",
    "addr:postcode":"99324",
    "addr:street":"Sw 10Th St",
    "iso:country":"US",
    "sg:address":"122 SW 10th St",
    "sg:city":"College Place",
    "sg:classifiers":[
        {
            "category":"Real Estate",
            "subcategory":"Real Estate Agent",
            "type":"Services"
        }
    ],
    "sg:phone":"+1 509 522 9897",
    "sg:postcode":"99324",
    "sg:province":"WA",
    "wof:name":"Desmond Property Management",
    "wof:placetype":"venue"
},
  "geometry": {"coordinates":[-118.390225,46.040311],"type":"Point"}
}