{
  "type": "Feature",
  "properties": {
    "addr:full":"11523 Avondale Rd Ne Woodinville WA 98052",
    "addr:housenumber":"11523",
    "addr:postcode":"98052",
    "addr:street":"Avondale Rd Ne",
    "iso:country":"US",
    "sg:address":"11523 Avondale Rd Ne",
    "sg:city":"Woodinville",
    "sg:classifiers":[
        {
            "category":"Retail",
            "subcategory":"Laundry & Dry Cleaning",
            "type":"Services"
        }
    ],
    "sg:phone":"+1 425 881 4210",
    "sg:postcode":"98052",
    "sg:province":"WA",
    "wof:name":"Avondale Cleaners",
    "wof:placetype":"venue"
},
  "geometry": {"coordinates":[-122.131967,47.703798],"type":"Point"}
}