{
  "type": "Feature",
  "properties": {
    "addr:full":"1502 N Shore Dr Bellingham WA 98226",
    "addr:housenumber":"1502",
    "addr:postcode":"98226",
    "addr:street":"N Shore Dr",
    "iso:country":"US",
    "sg:address":"1502 N Shore Dr",
    "sg:city":"Bellingham",
    "sg:classifiers":[
        {
            "category":"Professional",
            "subcategory":"Advertising",
            "type":"Services"
        },
        {
            "category":"Professional",
            "subcategory":"Printing & Photocopies",
            "type":"Services"
        },
        {
            "category":"Manufacturing",
            "subcategory":"Signs",
            "type":"Manufacturing & Wholesale Goods"
        }
    ],
    "sg:phone":"+1 360 756 9990",
    "sg:postcode":"98226",
    "sg:province":"WA",
    "sg:tags":[
        "banners",
        "flag",
        "specialty",
        "pennant"
    ],
    "sg:website":"http://www.blazingbanners.com",
    "wof:name":"Blazing Banners",
    "wof:placetype":"venue"
},
  "geometry": {"coordinates":[-122.35518999999999,48.756369],"type":"Point"}
}