{
  "type": "Feature",
  "properties": {
    "addr:full":"312 W Hastings Rd Spokane WA 99218",
    "addr:housenumber":"312",
    "addr:postcode":"99218",
    "addr:street":"W Hastings Rd",
    "iso:country":"US",
    "sg:address":"312 W Hastings Rd",
    "sg:city":"Spokane",
    "sg:classifiers":[
        {
            "category":"Social Services",
            "subcategory":"Adult Care",
            "type":"Services"
        }
    ],
    "sg:phone":"+1 509 468 0457",
    "sg:postcode":"99218",
    "sg:province":"WA",
    "sg:tags":[
        "home",
        "residential"
    ],
    "wof:name":"Fairwood Village Assisted Lvng",
    "wof:placetype":"venue"
},
  "geometry": {"coordinates":[-117.42282,47.768142],"type":"Point"}
}