{
  "type": "Feature",
  "properties": {
    "addr:full":"2913 S C St Tacoma WA 98402",
    "addr:housenumber":"2913",
    "addr:postcode":"98402",
    "addr:street":"S C St",
    "iso:country":"US",
    "sg:address":"2913 S C St",
    "sg:city":"Tacoma",
    "sg:classifiers":[
        {
            "category":"Manufacturing",
            "subcategory":"Furniture",
            "type":"Manufacturing & Wholesale Goods"
        }
    ],
    "sg:phone":"+1 253 531 5370",
    "sg:postcode":"98402",
    "sg:province":"WA",
    "sg:tags":[
        "building",
        "public",
        "mfg"
    ],
    "wof:name":"Preferred Services",
    "wof:placetype":"venue"
},
  "geometry": {"coordinates":[-122.435896,47.234555],"type":"Point"}
}