{
  "type": "Feature",
  "properties": {
    "addr:full":"18449 Cascade Ave S Seattle WA 98188",
    "addr:housenumber":"18449",
    "addr:postcode":"98188",
    "addr:street":"Cascade Ave S",
    "iso:country":"US",
    "sg:address":"18449 Cascade Ave S",
    "sg:city":"Seattle",
    "sg:classifiers":[
        {
            "category":"Arena",
            "subcategory":"Bull Ring",
            "type":"Entertainment"
        }
    ],
    "sg:phone":"+1 206 285 2819",
    "sg:postcode":"98188",
    "sg:province":"WA",
    "sg:tags":[
        "tarp"
    ],
    "sg:website":"http://www.seattletarp.com",
    "wof:name":"Seattle Tarp Inc",
    "wof:placetype":"venue"
},
  "geometry": {"coordinates":[-122.249653,47.434434],"type":"Point"}
}