{
  "type": "Feature",
  "properties": {
    "addr:full":"8107 Steilacoom Blvd SW Lakewood WA 98498",
    "addr:housenumber":"8107",
    "addr:postcode":"98498",
    "addr:street":"Steilacoom Blvd Sw",
    "iso:country":"US",
    "sg:address":"8107 Steilacoom Blvd SW",
    "sg:city":"Lakewood",
    "sg:classifiers":[
        {
            "category":"Sports & Exercise",
            "subcategory":"Gym",
            "type":"Entertainment"
        }
    ],
    "sg:phone":"+1 253 584 6809",
    "sg:postcode":"98498",
    "sg:province":"WA",
    "sg:tags":[
        "fitness",
        "physical",
        "facility"
    ],
    "wof:name":"Physio Fitness",
    "wof:placetype":"venue"
},
  "geometry": {"coordinates":[-122.544449,47.180002],"type":"Point"}
}