{
  "type": "Feature",
  "properties": {
    "addr:full":"8829 Roosevelt Way NE Seattle WA 98115",
    "addr:housenumber":"8829",
    "addr:postcode":"98115",
    "addr:street":"Roosevelt Way Ne",
    "iso:country":"US",
    "sg:address":"8829 Roosevelt Way NE",
    "sg:city":"Seattle",
    "sg:classifiers":[
        {
            "category":"Retail",
            "subcategory":"Auto Repair",
            "type":"Services"
        }
    ],
    "sg:phone":"+1 206 525 0045",
    "sg:postcode":"98115",
    "sg:province":"WA",
    "wof:name":"Northgate Auto Care Center",
    "wof:placetype":"venue"
},
  "geometry": {"coordinates":[-122.318001,47.693001],"type":"Point"}
}