{
  "type": "Feature",
  "properties": {
    "addr:full":"1475 Silver Run Ln Bellingham WA 98229",
    "addr:housenumber":"1475",
    "addr:postcode":"98229",
    "addr:street":"Silver Run Ln",
    "iso:country":"US",
    "sg:address":"1475 Silver Run Ln",
    "sg:city":"Bellingham",
    "sg:classifiers":[
        {
            "category":"Organizations",
            "subcategory":"Religious Organization",
            "type":"Services"
        }
    ],
    "sg:phone":"+1 360 724 5211",
    "sg:postcode":"98229",
    "sg:province":"WA",
    "wof:name":"Alger Community Church",
    "wof:placetype":"venue"
},
  "geometry": {"coordinates":[-122.34371,48.623265],"type":"Point"}
}