{
  "type": "Feature",
  "properties": {
    "addr:full":"4425 S 3rd Ave Everett WA 98203",
    "addr:housenumber":"4425",
    "addr:postcode":"98203",
    "addr:street":"S 3Rd Ave",
    "iso:country":"US",
    "sg:address":"4425 S 3rd Ave",
    "sg:city":"Everett",
    "sg:classifiers":[
        {
            "category":"Manufacturing",
            "subcategory":"Tools & Machinery",
            "type":"Manufacturing & Wholesale Goods"
        }
    ],
    "sg:phone":"+1 425 258 3555",
    "sg:postcode":"98203",
    "sg:province":"WA",
    "sg:tags":[
        "mill",
        "paper"
    ],
    "sg:website":"www.acrowood.com",
    "wof:name":"Acrowood Corp",
    "wof:placetype":"venue"
},
  "geometry": {"coordinates":[-122.196995,47.958698],"type":"Point"}
}