{
  "type": "Feature",
  "properties": {
    "addr:full":"9326 Bridgeport Way SW Lakewood WA 98499",
    "addr:housenumber":"9326",
    "addr:postcode":"98499",
    "addr:street":"Bridgeport Way Sw",
    "iso:country":"US",
    "sg:address":"9326 Bridgeport Way SW",
    "sg:city":"Lakewood",
    "sg:classifiers":[
        {
            "category":"Professional",
            "type":"Services"
        },
        {
            "category":"Bakery",
            "type":"Food & Drink"
        }
    ],
    "sg:phone":"+1 253 582 2755",
    "sg:postcode":"98499",
    "sg:province":"WA",
    "sg:tags":[
        "caterer"
    ],
    "sg:website":"www.legacy-catering.com",
    "wof:name":"Legacy Bakery & Catering",
    "wof:placetype":"venue"
},
  "geometry": {"coordinates":[-122.51846500000001,47.173143],"type":"Point"}
}