{
  "type": "Feature",
  "properties": {
    "addr:full":"17115 NE 163rd Pl Woodinville WA 98072",
    "addr:housenumber":"17115",
    "addr:postcode":"98072",
    "addr:street":"Ne 163Rd Pl",
    "iso:country":"US",
    "sg:address":"17115 NE 163rd Pl",
    "sg:city":"Woodinville",
    "sg:classifiers":[
        {
            "category":"Professional",
            "subcategory":"Business Services",
            "type":"Services"
        }
    ],
    "sg:phone":"+1 425 481 1305",
    "sg:postcode":"98072",
    "sg:province":"WA",
    "wof:name":"Portage Bay Solutions Inc",
    "wof:placetype":"venue"
},
  "geometry": {"coordinates":[-122.109695,47.746013],"type":"Point"}
}