{
  "type": "Feature",
  "properties": {
    "iso:country":"US",
    "sg:address":"8119 Lopez Dr",
    "sg:city":"Clinton",
    "sg:classifiers":[
        {
            "category":"Retail",
            "subcategory":"Laundry & Dry Cleaning",
            "type":"Services"
        }
    ],
    "sg:phone":"+1 360 579 2035",
    "sg:postcode":"98236",
    "sg:province":"WA",
    "sg:tags":[
        "cleaners",
        "rug",
        "carpet"
    ],
    "wof:name":"Dana's Mobile Carpet Steam",
    "wof:placetype":"venue"
},
  "geometry": {"coordinates":[-122.419511,47.915994],"type":"Point"}
}