{
  "type": "Feature",
  "properties": {
    "addr:full":"1331 W Nebraska Ave Spokane WA 99205",
    "addr:housenumber":"1331",
    "addr:postcode":"99205",
    "addr:street":"W Nebraska Ave",
    "iso:country":"US",
    "sg:address":"1331 W Nebraska Ave",
    "sg:city":"Spokane",
    "sg:classifiers":[
        {
            "category":"Building & Trades",
            "subcategory":"Construction",
            "type":"Services"
        }
    ],
    "sg:phone":"+1 509 327 5624",
    "sg:postcode":"99205",
    "sg:province":"WA",
    "sg:tags":[
        "house"
    ],
    "wof:name":"Sam Cozza Construction",
    "wof:placetype":"venue"
},
  "geometry": {"coordinates":[-117.431802,47.708922],"type":"Point"}
}