{
  "type": "Feature",
  "properties": {
    "addr:full":"8082 Quinault Rd Blaine WA 98230",
    "addr:postcode":"8082;98230",
    "addr:street":"Quinault Rd",
    "iso:country":"US",
    "sg:address":"8082 Quinault Rd",
    "sg:city":"Blaine",
    "sg:classifiers":[
        {
            "category":"Shopping",
            "subcategory":"Catalog Store",
            "type":"Retail Goods"
        }
    ],
    "sg:phone":"+1 360 392 8570",
    "sg:postcode":"98230",
    "sg:province":"WA",
    "sg:tags":[
        "mail",
        "house"
    ],
    "wof:name":"Cleveland Bay",
    "wof:placetype":"venue"
},
  "geometry": {"coordinates":[-122.79616900000001,48.938198],"type":"Point"}
}