{
  "type": "Feature",
  "properties": {
    "addr:full":"4325 Graler Pl Lummi Island WA 98262",
    "addr:housenumber":"4325",
    "addr:postcode":"98262",
    "addr:street":"Graler Pl Lummi Island",
    "iso:country":"US",
    "sg:address":"4325 Graler Pl",
    "sg:city":"Lummi Island",
    "sg:classifiers":[
        {
            "category":"Building & Trades",
            "subcategory":"Cleaning & Sanitation",
            "type":"Services"
        }
    ],
    "sg:phone":"+1 360 758 7620",
    "sg:postcode":"98262",
    "sg:province":"WA",
    "sg:tags":[
        "maintenance"
    ],
    "wof:name":"Allen Duct Services",
    "wof:placetype":"venue"
},
  "geometry": {"coordinates":[-122.71695099999999,48.734421],"type":"Point"}
}