{
  "type": "Feature",
  "properties": {
    "addr:full":"2334 S Holgate St Tacoma WA 98402",
    "addr:housenumber":"2334",
    "addr:postcode":"98402",
    "addr:street":"S Holgate St",
    "iso:country":"US",
    "sg:address":"2334 S Holgate St",
    "sg:city":"Tacoma",
    "sg:classifiers":[
        {
            "category":"Shopping",
            "subcategory":"Discount & Variety Stores",
            "type":"Retail Goods"
        }
    ],
    "sg:phone":"+1 253 272 7544",
    "sg:postcode":"98402",
    "sg:province":"WA",
    "sg:tags":[
        "merchandise",
        "general"
    ],
    "wof:name":"Stand-Out Products Inc",
    "wof:placetype":"venue"
},
  "geometry": {"coordinates":[-122.43769500000001,47.240139],"type":"Point"}
}