{
  "type": "Feature",
  "properties": {
    "addr:full":"4609 Bryce Dr Anacortes WA 98221",
    "addr:housenumber":"4609",
    "addr:postcode":"98221",
    "addr:street":"Bryce Dr",
    "iso:country":"US",
    "sg:address":"4609 Bryce Dr",
    "sg:city":"Anacortes",
    "sg:classifiers":[
        {
            "category":"Real Estate",
            "subcategory":"Real Estate Agent",
            "type":"Services"
        }
    ],
    "sg:phone":"+1 360 202 0580",
    "sg:postcode":"98221",
    "sg:province":"WA",
    "wof:name":"Bryan Real Estate",
    "wof:placetype":"venue"
},
  "geometry": {"coordinates":[-122.667275,48.488241],"type":"Point"}
}