{
  "type": "Feature",
  "properties": {
    "addr:full":"15 Lakeview Dr Burbank WA 99323",
    "addr:housenumber":"15",
    "addr:postcode":"99323",
    "addr:street":"Lakeview Dr",
    "iso:country":"US",
    "sg:address":"15 Lakeview Dr",
    "sg:city":"Burbank",
    "sg:classifiers":[
        {
            "category":"Real Estate",
            "subcategory":"Real Estate Agent",
            "type":"Services"
        }
    ],
    "sg:phone":"+1 509 547 4527",
    "sg:postcode":"99323",
    "sg:province":"WA",
    "wof:name":"Frank G Mull",
    "wof:placetype":"venue"
},
  "geometry": {"coordinates":[-118.84228,46.2523],"type":"Point"}
}