{
  "type": "Feature",
  "properties": {
    "addr:full":"3900 Industry Dr E Tacoma WA 98424",
    "addr:housenumber":"3900",
    "addr:postcode":"98424",
    "addr:street":"Industry Dr E",
    "iso:country":"US",
    "sg:address":"3900 Industry Dr E",
    "sg:city":"Tacoma",
    "sg:classifiers":[
        {
            "category":"Wholesale",
            "subcategory":"Wine & Distilled Alcoholic Beverages",
            "type":"Manufacturing & Wholesale Goods"
        }
    ],
    "sg:phone":"+1 253 896 2100",
    "sg:postcode":"98424",
    "sg:province":"WA",
    "wof:name":"Northwest Wines Company Inc",
    "wof:placetype":"venue"
},
  "geometry": {"coordinates":[-122.375333,47.236503],"type":"Point"}
}