{
  "type": "Feature",
  "properties": {
    "addr:full":"402 Black Hills Ln SW D Olympia WA 98502",
    "addr:housenumber":"402",
    "addr:postcode":"98502",
    "addr:street":"Black Hills Ln Sw D",
    "iso:country":"US",
    "sg:address":"402 Black Hills Ln SW D",
    "sg:city":"Olympia",
    "sg:classifiers":[
        {
            "category":"Health Services",
            "subcategory":"Doctor",
            "type":"Services"
        }
    ],
    "sg:phone":"+1 360 754 7881",
    "sg:postcode":"98502",
    "sg:province":"WA",
    "sg:tags":[
        "physician",
        "rheumatology",
        "arthritis",
        "surgeons",
        "surgeon"
    ],
    "wof:name":"Frederick A Jensen Md",
    "wof:placetype":"venue"
},
  "geometry": {"coordinates":[-122.95046600000001,47.046501],"type":"Point"}
}