{
  "type": "Feature",
  "properties": {
    "addr:full":"15217 58th St E Sumner WA 98390",
    "addr:housenumber":"15217",
    "addr:postcode":"98390",
    "addr:street":"58Th St E",
    "iso:country":"US",
    "sg:address":"15217 58th St E",
    "sg:city":"Sumner",
    "sg:classifiers":[
        {
            "category":"Personal",
            "subcategory":"Beauty Salon",
            "type":"Services"
        }
    ],
    "sg:phone":"+1 253 447 7645",
    "sg:postcode":"98390",
    "sg:province":"WA",
    "wof:name":"Manestage Theatre",
    "wof:placetype":"venue"
},
  "geometry": {"coordinates":[-122.22548500000001,47.204521],"type":"Point"}
}