{
  "type": "Feature",
  "properties": {
    "addr:full":"801 Broadway Seattle WA 98122",
    "addr:housenumber":"801",
    "addr:postcode":"98122",
    "addr:street":"Broadway",
    "iso:country":"US",
    "sg:address":"801 Broadway",
    "sg:city":"Seattle",
    "sg:classifiers":[
        {
            "category":"Health Services",
            "subcategory":"Hospital",
            "type":"Services"
        }
    ],
    "sg:phone":"+1 206 215 6050",
    "sg:postcode":"98122",
    "sg:province":"WA",
    "wof:name":"Vlcek Brien W MD",
    "wof:placetype":"venue"
},
  "geometry": {"coordinates":[-122.32077,47.609187],"type":"Point"}
}