{
  "type": "Feature",
  "properties": {
    "addr:full":"500 13th Ave E Seattle WA 98102",
    "addr:housenumber":"500",
    "addr:postcode":"98102",
    "addr:street":"13Th Ave E",
    "iso:country":"US",
    "sg:address":"500 13th Ave E",
    "sg:city":"Seattle",
    "sg:classifiers":[
        {
            "category":"Real Estate",
            "subcategory":"Real Estate Operator",
            "type":"Services"
        }
    ],
    "sg:phone":"+1 206 323 4732",
    "sg:postcode":"98102",
    "sg:province":"WA",
    "sg:tags":[
        "apartment"
    ],
    "wof:name":"Somerset House",
    "wof:placetype":"venue"
},
  "geometry": {"coordinates":[-122.316002,47.6231],"type":"Point"}
}