{
  "type": "Feature",
  "properties": {
    "addr:full":"8225 84th St NE Marysville WA 98270",
    "addr:housenumber":"8225",
    "addr:postcode":"98270",
    "addr:street":"84Th St Ne",
    "iso:country":"US",
    "sg:address":"8225 84th St NE",
    "sg:city":"Marysville",
    "sg:classifiers":[
        {
            "category":"Food & Beverages",
            "subcategory":"Groceries & Convenience Stores",
            "type":"Retail Goods"
        }
    ],
    "sg:phone":"+1 360 659 2592",
    "sg:postcode":"98270",
    "sg:province":"WA",
    "wof:name":"Hunters Corner Svc",
    "wof:placetype":"venue"
},
  "geometry": {"coordinates":[-122.117512,48.072082],"type":"Point"}
}