{
  "type": "Feature",
  "properties": {
    "addr:full":"4716 N Baltimore St Tacoma WA 98407",
    "addr:housenumber":"4716",
    "addr:postcode":"98407",
    "addr:street":"N Baltimore St",
    "iso:country":"US",
    "sg:address":"4716 N Baltimore St",
    "sg:city":"Tacoma",
    "sg:classifiers":[
        {
            "category":"Organizations",
            "subcategory":"Community Association",
            "type":"Services"
        }
    ],
    "sg:phone":"+1 253 756 0601",
    "sg:postcode":"98407",
    "sg:province":"WA",
    "wof:name":"Point Dfance Ruston Senior Ctr",
    "wof:placetype":"venue"
},
  "geometry": {"coordinates":[-122.50779900000001,47.292093],"type":"Point"}
}