{
  "type": "Feature",
  "properties": {
    "addr:full":"135 S Brandon St Seattle WA 98108",
    "addr:housenumber":"135",
    "addr:postcode":"98108",
    "addr:street":"S Brandon St",
    "iso:country":"US",
    "sg:address":"135 S Brandon St",
    "sg:city":"Seattle",
    "sg:classifiers":[
        {
            "category":"Professional",
            "subcategory":"Management & Consulting",
            "type":"Services"
        }
    ],
    "sg:phone":"+1 206 402 6172",
    "sg:postcode":"98108",
    "sg:province":"WA",
    "sg:tags":[
        "consultant",
        "restaurant"
    ],
    "wof:name":"Grande Cappo",
    "wof:placetype":"venue"
},
  "geometry": {"coordinates":[-122.333578,47.554158],"type":"Point"}
}