{
  "type": "Feature",
  "properties": {
    "addr:full":"16730 Larch Way Lynnwood WA 98037",
    "addr:housenumber":"16730",
    "addr:postcode":"98037",
    "addr:street":"Larch Way",
    "iso:country":"US",
    "sg:address":"16730 Larch Way",
    "sg:city":"Lynnwood",
    "sg:classifiers":[
        {
            "category":"Building & Trades",
            "subcategory":"Construction",
            "type":"Services"
        }
    ],
    "sg:phone":"+1 425 745 0795",
    "sg:postcode":"98037",
    "sg:province":"WA",
    "sg:tags":[
        "excavation",
        "excavating",
        "contractor"
    ],
    "wof:name":"Kraft Excavation",
    "wof:placetype":"venue"
},
  "geometry": {"coordinates":[-122.24676599999999,47.846956],"type":"Point"}
}