{
  "type": "Feature",
  "properties": {
    "addr:full":"3309 W Lincoln Ave Yakima WA 98902",
    "addr:housenumber":"3309",
    "addr:postcode":"98902",
    "addr:street":"W Lincoln Ave",
    "iso:country":"US",
    "sg:address":"3309 W Lincoln Ave",
    "sg:city":"Yakima",
    "sg:classifiers":[
        {
            "category":"Professional",
            "subcategory":"Business Services",
            "type":"Services"
        }
    ],
    "sg:phone":"+1 509 452 0198",
    "sg:postcode":"98902",
    "sg:province":"WA",
    "wof:name":"Muriel Watts",
    "wof:placetype":"venue"
},
  "geometry": {"coordinates":[-120.55297,46.603598],"type":"Point"}
}