{
  "type": "Feature",
  "properties": {
    "addr:full":"606 Cedar Ave Marysville WA 98270",
    "addr:housenumber":"606",
    "addr:postcode":"98270",
    "addr:street":"Cedar Ave",
    "iso:country":"US",
    "sg:address":"606 Cedar Ave",
    "sg:city":"Marysville",
    "sg:classifiers":[
        {
            "category":"Home & Garden",
            "subcategory":"Building Materials",
            "type":"Retail Goods"
        }
    ],
    "sg:phone":"+1 425 334 8619",
    "sg:postcode":"98270",
    "sg:province":"WA",
    "wof:name":"Brian Hathaway",
    "wof:placetype":"venue"
},
  "geometry": {"coordinates":[-122.180425,48.054539],"type":"Point"}
}