{
  "type": "Feature",
  "properties": {
    "addr:full":"8730 Sand Point Way NE Seattle WA 98115",
    "addr:housenumber":"8730",
    "addr:postcode":"98115",
    "addr:street":"Sand Point Way Ne",
    "iso:country":"US",
    "sg:address":"8730 Sand Point Way NE",
    "sg:city":"Seattle",
    "sg:classifiers":[
        {
            "category":"Building & Trades",
            "subcategory":"Construction",
            "type":"Services"
        }
    ],
    "sg:phone":"+1 206 522 5809",
    "sg:postcode":"98115",
    "sg:province":"WA",
    "sg:tags":[
        "builder",
        "operative"
    ],
    "wof:name":"Mumm Construction",
    "wof:placetype":"venue"
},
  "geometry": {"coordinates":[-122.26830200000001,47.691146],"type":"Point"}
}