{
  "type": "Feature",
  "properties": {
    "addr:full":"6620 E Side Dr NE Tacoma WA 98422",
    "addr:housenumber":"6620",
    "addr:postcode":"98422",
    "addr:street":"E Side Dr Ne",
    "iso:country":"US",
    "sg:address":"6620 E Side Dr NE",
    "sg:city":"Tacoma",
    "sg:classifiers":[
        {
            "category":"Banks & Credit Unions",
            "subcategory":"Investment Brokerage",
            "type":"Services"
        }
    ],
    "sg:phone":"+1 253 942 8222",
    "sg:postcode":"98422",
    "sg:province":"WA",
    "sg:tags":[
        "security"
    ],
    "wof:name":"Sound Reliance Inc",
    "wof:placetype":"venue"
},
  "geometry": {"coordinates":[-122.434586,47.300364],"type":"Point"}
}