{
  "type": "Feature",
  "properties": {
    "addr:full":"1902 E Aloha St Seattle WA 98112",
    "addr:housenumber":"1902",
    "addr:postcode":"98112",
    "addr:street":"E Aloha St",
    "iso:country":"US",
    "sg:address":"1902 E Aloha St",
    "sg:city":"Seattle",
    "sg:classifiers":[
        {
            "category":"Recreation",
            "type":"Entertainment"
        }
    ],
    "sg:phone":"+1 206 726 0950",
    "sg:postcode":"98112",
    "sg:province":"WA",
    "wof:name":"Ellen Finn",
    "wof:placetype":"venue"
},
  "geometry": {"coordinates":[-122.306071,47.626916],"type":"Point"}
}