{
  "type": "Feature",
  "properties": {
    "addr:full":"405 S Chelan Ave Wenatchee WA 98801",
    "addr:housenumber":"405",
    "addr:postcode":"98801",
    "addr:street":"S Chelan Ave",
    "iso:country":"US",
    "sg:address":"405 S Chelan Ave",
    "sg:city":"Wenatchee",
    "sg:classifiers":[
        {
            "category":"Professional",
            "subcategory":"Detective & Security Services",
            "type":"Services"
        }
    ],
    "sg:phone":"+1 509 662 6465",
    "sg:postcode":"98801",
    "sg:province":"WA",
    "sg:tags":[
        "system"
    ],
    "wof:name":"Surveillance & Custom Security",
    "wof:placetype":"venue"
},
  "geometry": {"coordinates":[-120.309557,47.418907],"type":"Point"}
}