{
  "type": "Feature",
  "properties": {
    "addr:full":"830 106th Ave NE Bellevue WA 98004",
    "addr:housenumber":"830",
    "addr:postcode":"98004",
    "addr:street":"106Th Ave Ne",
    "iso:country":"US",
    "sg:address":"830 106th Ave NE",
    "sg:city":"Bellevue",
    "sg:classifiers":[
        {
            "category":"Shopping",
            "subcategory":"Bicycles & Sporting Goods",
            "type":"Retail Goods"
        },
        {
            "category":"Sports & Exercise",
            "subcategory":"Bicycle Rental",
            "type":"Entertainment"
        }
    ],
    "sg:phone":"+1 425 637 8958",
    "sg:postcode":"98004",
    "sg:province":"WA",
    "sg:tags":[
        "outdoor",
        "gear",
        "wear"
    ],
    "sg:website":"www.sturtevants.com",
    "wof:name":"Ski Mart",
    "wof:placetype":"venue"
},
  "geometry": {"coordinates":[-122.19899700000001,47.617599],"type":"Point"}
}