{
  "type": "Feature",
  "properties": {
    "addr:full":"352 NE Tiger Way W Belfair WA 98528",
    "addr:housenumber":"352",
    "addr:postcode":"98528",
    "addr:street":"Ne Tiger Way W",
    "iso:country":"US",
    "sg:address":"352 NE Tiger Way W",
    "sg:city":"Belfair",
    "sg:classifiers":[
        {
            "category":"Building & Trades",
            "subcategory":"Construction",
            "type":"Services"
        }
    ],
    "sg:phone":"+1 360 275 0352",
    "sg:postcode":"98528",
    "sg:province":"WA",
    "sg:tags":[
        "contractor"
    ],
    "wof:name":"Artisan Tile & Mosaic",
    "wof:placetype":"venue"
},
  "geometry": {"coordinates":[-122.83684,47.512893],"type":"Point"}
}