{
  "type": "Feature",
  "properties": {
    "addr:full":"4448 160th Ave SE Issaquah WA 98027",
    "addr:housenumber":"4448",
    "addr:postcode":"98027",
    "addr:street":"160Th Ave Se",
    "iso:country":"US",
    "sg:address":"4448 160th Ave SE",
    "sg:city":"Issaquah",
    "sg:classifiers":[
        {
            "category":"Building & Trades",
            "subcategory":"Construction",
            "type":"Services"
        }
    ],
    "sg:phone":"+1 206 683 6628",
    "sg:postcode":"98027",
    "sg:province":"WA",
    "sg:tags":[
        "house"
    ],
    "wof:name":"Best View Inc",
    "wof:placetype":"venue"
},
  "geometry": {"coordinates":[-122.127561,47.566016],"type":"Point"}
}