{
  "type": "Feature",
  "properties": {
    "addr:full":"621 W Mallon Ave Spokane WA 99201",
    "addr:housenumber":"621",
    "addr:postcode":"99201",
    "addr:street":"W Mallon Ave",
    "iso:country":"US",
    "sg:address":"621 W Mallon Ave",
    "sg:city":"Spokane",
    "sg:classifiers":[
        {
            "category":"Banks & Credit Unions",
            "subcategory":"Investment Brokerage",
            "type":"Services"
        }
    ],
    "sg:phone":"+1 509 328 5627",
    "sg:postcode":"99201",
    "sg:province":"WA",
    "sg:tags":[
        "consulting",
        "management",
        "p",
        "security",
        "stock",
        "bond"
    ],
    "wof:name":"Linsco Private Ledger",
    "wof:placetype":"venue"
},
  "geometry": {"coordinates":[-117.423399,47.665257],"type":"Point"}
}