{
  "type": "Feature",
  "properties": {
    "addr:full":"6799 Old Guide Rd Lynden WA 98264",
    "addr:housenumber":"6799",
    "addr:postcode":"98264",
    "addr:street":"Old Guide Rd",
    "iso:country":"US",
    "sg:address":"6799 Old Guide Rd",
    "sg:city":"Lynden",
    "sg:classifiers":[
        {
            "category":"Building & Trades",
            "subcategory":"Construction",
            "type":"Services"
        }
    ],
    "sg:phone":"+1 360 398 2289",
    "sg:postcode":"98264",
    "sg:province":"WA",
    "sg:tags":[
        "vinyl"
    ],
    "wof:name":"Bakerview Construction Inc",
    "wof:placetype":"venue"
},
  "geometry": {"coordinates":[-122.49687900000001,48.888588],"type":"Point"}
}