{
  "type": "Feature",
  "properties": {
    "addr:full":"3423 Best Ln Bellingham WA 98226",
    "addr:housenumber":"3423",
    "addr:postcode":"98226",
    "addr:street":"Best Ln",
    "iso:country":"US",
    "sg:address":"3423 Best Ln",
    "sg:city":"Bellingham",
    "sg:classifiers":[
        {
            "category":"Professional",
            "subcategory":"Business Services",
            "type":"Services"
        }
    ],
    "sg:phone":"+1 360 592 1370",
    "sg:postcode":"98226",
    "sg:province":"WA",
    "wof:name":"Bendure Fishing Enterprises",
    "wof:placetype":"venue"
},
  "geometry": {"coordinates":[-122.308644,48.823053],"type":"Point"}
}