{
  "type": "Feature",
  "properties": {
    "addr:full":"1806 Roberdeau St Richland WA 99354",
    "addr:housenumber":"1806",
    "addr:postcode":"99354",
    "addr:street":"Roberdeau St",
    "iso:country":"US",
    "sg:address":"1806 Roberdeau St",
    "sg:city":"Richland",
    "sg:classifiers":[
        {
            "category":"Building & Trades",
            "subcategory":"Electrical",
            "type":"Services"
        }
    ],
    "sg:phone":"+1 509 946 1536",
    "sg:postcode":"99354",
    "sg:province":"WA",
    "sg:tags":[
        "electrical",
        "contractor"
    ],
    "wof:name":"Rightwire Electric Co",
    "wof:placetype":"venue"
},
  "geometry": {"coordinates":[-119.295608,46.284144],"type":"Point"}
}