{
  "type": "Feature",
  "properties": {
    "addr:full":"Redmond Athletic Club 8709 161st Ave Redmond WA 98052",
    "addr:housenumber":"8709",
    "addr:postcode":"98052",
    "addr:street":"161St Ave",
    "iso:country":"US",
    "sg:address":"Redmond Athletic Club 8709 161st Ave",
    "sg:city":"Redmond",
    "sg:classifiers":[
        {
            "category":"Education",
            "subcategory":"Dance Studio",
            "type":"Public Place"
        }
    ],
    "sg:phone":"+1 425 881 6245",
    "sg:postcode":"98052",
    "sg:province":"WA",
    "sg:website":"www.iteachbellydance.com",
    "wof:name":"Learn to Belly Dance with Alexandra",
    "wof:placetype":"venue"
},
  "geometry": {"coordinates":[-122.12632000000001,47.680057],"type":"Point"}
}