{
  "type": "Feature",
  "properties": {
    "addr:full":"8221 NE Hazel Dell Ave Vancouver WA 98665",
    "addr:housenumber":"8221",
    "addr:postcode":"98665",
    "addr:street":"Ne Hazel Dell Ave",
    "iso:country":"US",
    "sg:address":"8221 NE Hazel Dell Ave",
    "sg:city":"Vancouver",
    "sg:classifiers":[
        {
            "category":"Professional",
            "subcategory":"Accounting & Tax Preparation",
            "type":"Services"
        }
    ],
    "sg:phone":"+1 360 573 9800",
    "sg:postcode":"98665",
    "sg:province":"WA",
    "sg:tags":[
        "accountant"
    ],
    "wof:name":"Golden & Co Cpa's PC",
    "wof:placetype":"venue"
},
  "geometry": {"coordinates":[-122.66928,45.682327],"type":"Point"}
}