{
  "type": "Feature",
  "properties": {
    "addr:full":"755 Winslow Way E Suite 206 Bainbridge Island WA 98110",
    "addr:housenumber":"755",
    "addr:postcode":"98110",
    "addr:street":"Winslow Way E Suite 206",
    "iso:country":"US",
    "sg:address":"755 Winslow Way E Suite 206",
    "sg:city":"Bainbridge Island",
    "sg:classifiers":[
        {
            "category":"Professional",
            "subcategory":"Lawyer & Legal Services",
            "type":"Services"
        }
    ],
    "sg:phone":"+1 206 855 1025",
    "sg:postcode":"98110",
    "sg:province":"WA",
    "wof:name":"Muenster John R PS",
    "wof:placetype":"venue"
},
  "geometry": {"coordinates":[-122.511742,47.624893],"type":"Point"}
}