{
  "type": "Feature",
  "properties": {
    "addr:full":"22811 NE 14th ST Sammamish WA 98074 ",
    "addr:housenumber":"22811",
    "addr:postcode":"98074",
    "addr:street":"Ne 14Th St",
    "iso:country":"US",
    "sg:address":"22811 NE 14th ST",
    "sg:city":"Sammamish",
    "sg:classifiers":[
        {
            "category":"Professional",
            "subcategory":"Computer Services",
            "type":"Services"
        }
    ],
    "sg:phone":"+1 425 836 8722",
    "sg:postcode":"98074 ",
    "sg:province":"WA",
    "sg:website":"http://www.data-applied.com",
    "wof:name":"Data Applied",
    "wof:placetype":"venue"
},
  "geometry": {"coordinates":[-122.034569,47.622174],"type":"Point"}
}