{
  "type": "Feature",
  "properties": {
    "iso:country":"US",
    "sg:address":"10 N Madison St",
    "sg:city":"Walla Walla",
    "sg:classifiers":[
        {
            "category":"Farming",
            "subcategory":"Vineyard",
            "type":"Manufacturing & Wholesale Goods"
        }
    ],
    "sg:phone":"+1 509 526 7643",
    "sg:postcode":"99362",
    "sg:province":"WA",
    "sg:tags":[
        "grape"
    ],
    "wof:name":"VA Piano Vineyards",
    "wof:placetype":"venue"
},
  "geometry": {"coordinates":[-118.321459,46.071784],"type":"Point"}
}