{
  "type": "Feature",
  "properties": {
    "addr:full":"5414 Edgewood Dr E Edgewood WA 98372",
    "addr:housenumber":"5414",
    "addr:postcode":"98372",
    "addr:street":"Edgewood Dr E",
    "iso:country":"US",
    "sg:address":"5414 Edgewood Dr E",
    "sg:city":"Edgewood",
    "sg:classifiers":[
        {
            "category":"Retail",
            "subcategory":"Repair Shop",
            "type":"Services"
        }
    ],
    "sg:phone":"+1 253 863 5008",
    "sg:postcode":"98372",
    "sg:province":"WA",
    "sg:tags":[
        "equipment",
        "hydraulic"
    ],
    "wof:name":"Puget Sound Compressor & Heavy",
    "wof:placetype":"venue"
},
  "geometry": {"coordinates":[-122.252422,47.20825],"type":"Point"}
}