{
  "type": "Feature",
  "properties": {
    "addr:full":"14306 E Sprague Ave Spokane WA 99216",
    "addr:housenumber":"14306",
    "addr:postcode":"99216",
    "addr:street":"E Sprague Ave",
    "iso:country":"US",
    "sg:address":"14306 E Sprague Ave",
    "sg:city":"Spokane",
    "sg:classifiers":[
        {
            "category":"Retail",
            "subcategory":"Veterinary Services",
            "type":"Services"
        }
    ],
    "sg:phone":"+1 509 926 1062",
    "sg:postcode":"99216",
    "sg:province":"WA",
    "wof:name":"Blumenstein Sheryl Dvm",
    "wof:placetype":"venue"
},
  "geometry": {"coordinates":[-117.21330500000001,47.656988],"type":"Point"}
}