{
  "type": "Feature",
  "properties": {
    "addr:full":"2000 2nd Ave Seattle WA 98121",
    "addr:housenumber":"2000",
    "addr:postcode":"98121",
    "addr:street":"2Nd Ave",
    "iso:country":"US",
    "sg:address":"2000 2nd Ave",
    "sg:city":"Seattle",
    "sg:classifiers":[
        {
            "category":"Manufacturing",
            "subcategory":"Printing",
            "type":"Manufacturing & Wholesale Goods"
        }
    ],
    "sg:phone":"+1 206 706 3339",
    "sg:postcode":"98121",
    "sg:province":"WA",
    "sg:tags":[
        "book"
    ],
    "wof:name":"Scala House Publishers LLC",
    "wof:placetype":"venue"
},
  "geometry": {"coordinates":[-122.343054,47.6125],"type":"Point"}
}