{
  "type": "Feature",
  "properties": {
    "addr:full":"10200 Edmonds Ave SE Renton WA 98058",
    "addr:housenumber":"10200",
    "addr:postcode":"98058",
    "addr:street":"Edmonds Ave Se",
    "iso:country":"US",
    "sg:address":"10200 Edmonds Ave SE",
    "sg:city":"Renton",
    "sg:classifiers":[
        {
            "category":"Restaurant",
            "type":"Food & Drink"
        }
    ],
    "sg:menulink":"http://www.allmenus.com/wa/east-seattle/20598-pagliacci/menu/",
    "sg:phone":"+1 206 726 1717",
    "sg:postcode":"98058",
    "sg:province":"WA",
    "sg:tags":[
        "american",
        "pizza"
    ],
    "wof:name":"Pagliacci",
    "wof:placetype":"venue"
},
  "geometry": {"coordinates":[-122.185901,47.459551],"type":"Point"}
}