{
  "type": "Feature",
  "properties": {
    "addr:full":"502 E Main St Battle Ground WA 98604",
    "addr:housenumber":"502",
    "addr:postcode":"98604",
    "addr:street":"E Main St",
    "iso:country":"US",
    "sg:address":"502 E Main St",
    "sg:city":"Battle Ground",
    "sg:classifiers":[
        {
            "category":"Building & Trades",
            "subcategory":"Equipment Rental",
            "type":"Services"
        }
    ],
    "sg:phone":"+1 360 687 1768",
    "sg:postcode":"98604",
    "sg:province":"WA",
    "sg:tags":[
        "instrument",
        "musical"
    ],
    "wof:name":"Music World",
    "wof:placetype":"venue"
},
  "geometry": {"coordinates":[-122.53022199999999,45.781036],"type":"Point"}
}