{
  "type": "Feature",
  "properties": {
    "addr:full":"904 7th Ave Seattle WA 98104",
    "addr:housenumber":"904",
    "addr:postcode":"98104",
    "addr:street":"7Th Ave",
    "iso:country":"US",
    "sg:address":"904 7th Ave",
    "sg:city":"Seattle",
    "sg:classifiers":[
        {
            "category":"Health Services",
            "subcategory":"Podiatrist",
            "type":"Services"
        }
    ],
    "sg:phone":"+1 206 223 7527",
    "sg:postcode":"98104",
    "sg:province":"WA",
    "wof:name":"Richard T Bouche DPM",
    "wof:placetype":"venue"
},
  "geometry": {"coordinates":[-122.32901699999999,47.60695],"type":"Point"}
}