{
  "type": "Feature",
  "properties": {
    "addr:full":"6906 N F St Spokane WA 99208",
    "addr:housenumber":"6906",
    "addr:postcode":"99208",
    "addr:street":"N F St",
    "iso:country":"US",
    "sg:address":"6906 N F St",
    "sg:city":"Spokane",
    "sg:classifiers":[
        {
            "category":"Manufacturing",
            "subcategory":"Lumber",
            "type":"Manufacturing & Wholesale Goods"
        }
    ],
    "sg:phone":"+1 509 326 4981",
    "sg:postcode":"99208",
    "sg:province":"WA",
    "sg:tags":[
        "consulting",
        "management",
        "logging"
    ],
    "wof:name":"Empire Forests",
    "wof:placetype":"venue"
},
  "geometry": {"coordinates":[-117.45865999999999,47.720834],"type":"Point"}
}