{
  "type": "Feature",
  "properties": {
    "addr:full":"9322 271st St NW Stanwood WA 98292",
    "addr:housenumber":"9322",
    "addr:postcode":"98292",
    "addr:street":"271St St Nw",
    "iso:country":"US",
    "sg:address":"9322 271st St NW",
    "sg:city":"Stanwood",
    "sg:classifiers":[
        {
            "category":"Banks & Credit Unions",
            "subcategory":"Bank",
            "type":"Services"
        }
    ],
    "sg:phone":"+1 360 939 0009",
    "sg:postcode":"98292",
    "sg:province":"WA",
    "sg:tags":[
        "cashing",
        "check"
    ],
    "wof:name":"Advance America",
    "wof:placetype":"venue"
},
  "geometry": {"coordinates":[-122.35959,48.242059],"type":"Point"}
}