{
  "type": "Feature",
  "properties": {
    "addr:full":"12528 SW 158th St Vashon WA 98070",
    "addr:housenumber":"12528",
    "addr:postcode":"98070",
    "addr:street":"Sw 158Th St",
    "iso:country":"US",
    "sg:address":"12528 SW 158th St",
    "sg:city":"Vashon",
    "sg:classifiers":[
        {
            "category":"Professional",
            "subcategory":"Management & Consulting",
            "type":"Services"
        }
    ],
    "sg:phone":"+1 206 567 4229",
    "sg:postcode":"98070",
    "sg:province":"WA",
    "sg:tags":[
        "business"
    ],
    "wof:name":"Wendell P Clark",
    "wof:placetype":"venue"
},
  "geometry": {"coordinates":[-122.493272,47.463718],"type":"Point"}
}