{
  "type": "Feature",
  "properties": {
    "addr:full":"340 15th Ave E Bsmt Seattle WA 98112",
    "addr:housenumber":"340",
    "addr:postcode":"98112",
    "addr:street":"15Th Ave E",
    "iso:country":"US",
    "sg:address":"340 15th Ave E Bsmt",
    "sg:city":"Seattle",
    "sg:classifiers":[
        {
            "category":"Sports & Exercise",
            "subcategory":"Playing Field",
            "type":"Entertainment"
        }
    ],
    "sg:phone":"+1 206 328 1500",
    "sg:postcode":"98112",
    "sg:province":"WA",
    "sg:tags":[
        "instruction",
        "fitness"
    ],
    "sg:website":"www.dance-underground.com/",
    "wof:name":"Dance Underground",
    "wof:placetype":"venue"
},
  "geometry": {"coordinates":[-122.31300400000001,47.621799],"type":"Point"}
}