{
  "type": "Feature",
  "properties": {
    "iso:country":"US",
    "sg:address":"22010 5th Ave W",
    "sg:city":"Bothell",
    "sg:classifiers":[
        {
            "category":"Building & Trades",
            "subcategory":"Construction",
            "type":"Services"
        }
    ],
    "sg:phone":"+1 425 486 2627",
    "sg:postcode":"98021",
    "sg:province":"WA",
    "sg:tags":[
        "concrete",
        "contractor"
    ],
    "wof:name":"Chriss Concrete Finishing",
    "wof:placetype":"venue"
},
  "geometry": {"coordinates":[-122.240252,47.798068],"type":"Point"}
}