{
  "type": "Feature",
  "properties": {
    "iso:country":"US",
    "sg:address":"23725 101st Pl SE",
    "sg:city":"Kent",
    "sg:classifiers":[
        {
            "category":"Organizations",
            "subcategory":"Religious Organization",
            "type":"Services"
        }
    ],
    "sg:phone":"+1 253 859 7977",
    "sg:postcode":"98031",
    "sg:province":"WA",
    "wof:name":"Islamic Educational Institute",
    "wof:placetype":"venue"
},
  "geometry": {"coordinates":[-122.205213,47.389878],"type":"Point"}
}