{
  "type": "Feature",
  "properties": {
    "addr:full":"14257 Lake Hills Blvd Bellevue WA 98007",
    "addr:housenumber":"14257",
    "addr:postcode":"98007",
    "addr:street":"Lake Hills Blvd",
    "iso:country":"US",
    "sg:address":"14257 Lake Hills Blvd",
    "sg:city":"Bellevue",
    "sg:classifiers":[
        {
            "category":"Professional",
            "subcategory":"Art Services",
            "type":"Services"
        }
    ],
    "sg:phone":"+1 425 644 4687",
    "sg:postcode":"98007",
    "sg:province":"WA",
    "sg:tags":[
        "commercial",
        "design"
    ],
    "wof:name":"Flying Koala Brothers Graphics",
    "wof:placetype":"venue"
},
  "geometry": {"coordinates":[-122.14887299999999,47.597627],"type":"Point"}
}