{
  "type": "Feature",
  "properties": {
    "addr:full":"1114 S 35th St Renton WA 98055",
    "addr:housenumber":"1114",
    "addr:postcode":"98055",
    "addr:street":"S 35Th St",
    "iso:country":"US",
    "sg:address":"1114 S 35th St",
    "sg:city":"Renton",
    "sg:classifiers":[
        {
            "category":"Taxi",
            "type":"Transportation"
        }
    ],
    "sg:phone":"+1 425 277 8717",
    "sg:postcode":"98055",
    "sg:province":"WA",
    "sg:tags":[
        "taxicab"
    ],
    "wof:name":"Bxm Cab Holding",
    "wof:placetype":"venue"
},
  "geometry": {"coordinates":[-122.20429,47.448848],"type":"Point"}
}