{
  "type": "Feature",
  "properties": {
    "addr:full":"16020 E Kahlua Ln Mica WA 99023",
    "addr:housenumber":"16020",
    "addr:postcode":"99023",
    "addr:street":"E Kahlua Ln Mica",
    "iso:country":"US",
    "sg:address":"16020 E Kahlua Ln",
    "sg:city":"Mica",
    "sg:classifiers":[
        {
            "category":"Real Estate",
            "subcategory":"Real Estate Agent",
            "type":"Services"
        }
    ],
    "sg:phone":"+1 509 922 0005",
    "sg:postcode":"99023",
    "sg:province":"WA",
    "wof:name":"M&R Properties",
    "wof:placetype":"venue"
},
  "geometry": {"coordinates":[-117.189606,47.542006],"type":"Point"}
}