{
  "type": "Feature",
  "properties": {
    "addr:full":"1169 Harrington Pl Du Pont WA 98327",
    "addr:housenumber":"1169",
    "addr:postcode":"98327",
    "addr:street":"Harrington Pl Du Pont",
    "iso:country":"US",
    "sg:address":"1169 Harrington Pl",
    "sg:city":"Du Pont",
    "sg:classifiers":[
        {
            "category":"Personal",
            "type":"Services"
        }
    ],
    "sg:phone":"+1 253 884 3647",
    "sg:postcode":"98327",
    "sg:province":"WA",
    "wof:name":"Brigittes Healing Haven",
    "wof:placetype":"venue"
},
  "geometry": {"coordinates":[-122.63773500000001,47.099087],"type":"Point"}
}