{
  "type": "Feature",
  "properties": {
    "addr:full":"1750 112th Ave NE Bellevue WA 98004",
    "addr:housenumber":"1750",
    "addr:postcode":"98004",
    "addr:street":"112Th Ave Ne",
    "iso:country":"US",
    "sg:address":"1750 112th Ave NE",
    "sg:city":"Bellevue",
    "sg:classifiers":[
        {
            "category":"Health Services",
            "subcategory":"Chiropractor",
            "type":"Services"
        }
    ],
    "sg:phone":"+1 425 455 5390",
    "sg:postcode":"98004",
    "sg:province":"WA",
    "wof:name":"Matthewson Steven DC",
    "wof:placetype":"venue"
},
  "geometry": {"coordinates":[-122.190877,47.627251],"type":"Point"}
}