{
  "type": "Feature",
  "properties": {
    "addr:full":"3492 NW Byron St Silverdale WA 98383",
    "addr:housenumber":"3492",
    "addr:postcode":"98383",
    "addr:street":"Nw Byron St",
    "iso:country":"US",
    "sg:address":"3492 NW Byron St",
    "sg:city":"Silverdale",
    "sg:classifiers":[
        {
            "category":"Shopping",
            "subcategory":"Used Merchandise",
            "type":"Retail Goods"
        }
    ],
    "sg:phone":"+1 360 662 0272",
    "sg:postcode":"98383",
    "sg:province":"WA",
    "sg:tags":[
        "shop",
        "consignment"
    ],
    "wof:name":"Inner Winds",
    "wof:placetype":"venue"
},
  "geometry": {"coordinates":[-122.697968,47.644596],"type":"Point"}
}