{
  "type": "Feature",
  "properties": {
    "addr:full":"101 NE Coast Pine Ave Vancouver WA 98684",
    "addr:housenumber":"101",
    "addr:postcode":"98684",
    "addr:street":"Ne Coast Pine Ave",
    "iso:country":"US",
    "sg:address":"101 NE Coast Pine Ave",
    "sg:city":"Vancouver",
    "sg:classifiers":[
        {
            "category":"Home & Garden",
            "subcategory":"Building Materials",
            "type":"Retail Goods"
        }
    ],
    "sg:phone":"+1 360 882 4689",
    "sg:postcode":"98684",
    "sg:province":"WA",
    "sg:tags":[
        "door",
        "gate",
        "operating",
        "devices"
    ],
    "wof:name":"Active Garage Door Repair",
    "wof:placetype":"venue"
},
  "geometry": {"coordinates":[-122.52319199999999,45.621549],"type":"Point"}
}