{
  "type": "Feature",
  "properties": {
    "addr:full":"3361 Porcupine Ln Valley WA 99181",
    "addr:housenumber":"3361",
    "addr:postcode":"99181",
    "addr:street":"Porcupine Ln",
    "iso:country":"US",
    "sg:address":"3361 Porcupine Ln",
    "sg:city":"Valley",
    "sg:classifiers":[
        {
            "category":"Wholesale",
            "subcategory":"Stationery",
            "type":"Manufacturing & Wholesale Goods"
        }
    ],
    "sg:phone":"+1 509 937 2417",
    "sg:postcode":"99181",
    "sg:province":"WA",
    "sg:tags":[
        "mapping"
    ],
    "wof:name":"Straightline Topo & Reclaimtn",
    "wof:placetype":"venue"
},
  "geometry": {"coordinates":[-117.789249,48.192931],"type":"Point"}
}