{
  "type": "Feature",
  "properties": {
    "iso:country":"US",
    "sg:address":"5705 S Mohawk Dr",
    "sg:city":"Spokane",
    "sg:classifiers":[
        {
            "category":"Building & Trades",
            "subcategory":"Electrical",
            "type":"Services"
        }
    ],
    "sg:phone":"+1 509 892 7644",
    "sg:postcode":"99206",
    "sg:province":"WA",
    "sg:tags":[
        "electrical",
        "contractor"
    ],
    "wof:name":"Lakeside Electrical Contg",
    "wof:placetype":"venue"
},
  "geometry": {"coordinates":[-117.245902,47.601911],"type":"Point"}
}