{
  "type": "Feature",
  "properties": {
    "addr:full":"401 N Young St Kennewick WA 99336",
    "addr:housenumber":"401",
    "addr:postcode":"99336",
    "addr:street":"N Young St",
    "iso:country":"US",
    "sg:address":"401 N Young St",
    "sg:city":"Kennewick",
    "sg:classifiers":[
        {
            "category":"Organizations",
            "subcategory":"Non-profit Organization",
            "type":"Services"
        }
    ],
    "sg:phone":"+1 509 783 4102",
    "sg:postcode":"99336",
    "sg:province":"WA",
    "sg:tags":[
        "social"
    ],
    "sg:website":"www.unitedway-bfco.com",
    "wof:name":"United Way",
    "wof:placetype":"venue"
},
  "geometry": {"coordinates":[-119.21869599999999,46.212554],"type":"Point"}
}