{
  "type": "Feature",
  "properties": {
    "addr:full":"118 E 8th St Port Angeles WA 98362",
    "addr:housenumber":"118",
    "addr:postcode":"98362",
    "addr:street":"E 8Th St",
    "iso:country":"US",
    "sg:address":"118 E 8th St",
    "sg:city":"Port Angeles",
    "sg:classifiers":[
        {
            "category":"Health Services",
            "subcategory":"Hospital",
            "type":"Services"
        }
    ],
    "sg:phone":"+1 360 457 0431",
    "sg:postcode":"98362",
    "sg:province":"WA",
    "sg:tags":[
        "mental"
    ],
    "sg:website":"www.pcmhc.org",
    "wof:name":"Peninsula Community Mental",
    "wof:placetype":"venue"
},
  "geometry": {"coordinates":[-123.438828,48.112743],"type":"Point"}
}