{
  "type": "Feature",
  "properties": {
    "addr:full":"8911 186th St NE Arlington WA 98223",
    "addr:housenumber":"8911",
    "addr:postcode":"98223",
    "addr:street":"186Th St Ne",
    "iso:country":"US",
    "sg:address":"8911 186th St NE",
    "sg:city":"Arlington",
    "sg:classifiers":[
        {
            "category":"Manufacturing",
            "subcategory":"Retail Goods",
            "type":"Manufacturing & Wholesale Goods"
        }
    ],
    "sg:phone":"+1 360 435 3376",
    "sg:postcode":"98223",
    "sg:province":"WA",
    "sg:tags":[
        "product",
        "mfg"
    ],
    "wof:name":"Avl Machine Works",
    "wof:placetype":"venue"
},
  "geometry": {"coordinates":[-122.11219699999999,48.164503],"type":"Point"}
}