{
  "type": "Feature",
  "properties": {
    "addr:full":"18133 NE 68th St Redmond WA 98052",
    "addr:housenumber":"18133",
    "addr:postcode":"98052",
    "addr:street":"Ne 68Th St",
    "iso:country":"US",
    "sg:address":"18133 NE 68th St",
    "sg:city":"Redmond",
    "sg:classifiers":[
        {
            "category":"Wholesale",
            "subcategory":"Electrical",
            "type":"Manufacturing & Wholesale Goods"
        }
    ],
    "sg:phone":"+1 425 398 0613",
    "sg:postcode":"98052",
    "sg:province":"WA",
    "sg:tags":[
        "wholesaler",
        "computer",
        "cable"
    ],
    "wof:name":"Wwwcableconnectioncom",
    "wof:placetype":"venue"
},
  "geometry": {"coordinates":[-122.09728200000001,47.666972],"type":"Point"}
}