{
  "type": "Feature",
  "properties": {
    "addr:full":"3410 N 9th St Tacoma WA 98406",
    "addr:housenumber":"3410",
    "addr:postcode":"98406",
    "addr:street":"N 9Th St",
    "iso:country":"US",
    "sg:address":"3410 N 9th St",
    "sg:city":"Tacoma",
    "sg:classifiers":[
        {
            "category":"Personal",
            "type":"Services"
        }
    ],
    "sg:phone":"+1 253 756 8993",
    "sg:postcode":"98406",
    "sg:province":"WA",
    "wof:name":"Sofe Silverman Lmp",
    "wof:placetype":"venue"
},
  "geometry": {"coordinates":[-122.48179500000001,47.257867],"type":"Point"}
}