{
  "type": "Feature",
  "properties": {
    "addr:full":"14804 NE 31st St Vancouver WA 98682",
    "addr:housenumber":"14804",
    "addr:postcode":"98682",
    "addr:street":"Ne 31St St",
    "iso:country":"US",
    "sg:address":"14804 NE 31st St",
    "sg:city":"Vancouver",
    "sg:classifiers":[
        {
            "category":"Social Services",
            "subcategory":"Adult Care",
            "type":"Services"
        }
    ],
    "sg:phone":"+1 360 260 7328",
    "sg:postcode":"98682",
    "sg:province":"WA",
    "sg:tags":[
        "residential"
    ],
    "wof:name":"Generous Care Giving",
    "wof:placetype":"venue"
},
  "geometry": {"coordinates":[-122.51978200000001,45.644407],"type":"Point"}
}