{
  "type": "Feature",
  "properties": {
    "addr:full":"1105 Bellevue Way NE Bellevue WA 98004",
    "addr:housenumber":"1105",
    "addr:postcode":"98004",
    "addr:street":"Bellevue Way Ne",
    "iso:country":"US",
    "sg:address":"1105 Bellevue Way NE",
    "sg:city":"Bellevue",
    "sg:classifiers":[
        {
            "category":"Retail",
            "subcategory":"Veterinary Services",
            "type":"Services"
        }
    ],
    "sg:phone":"+1 425 455 2273",
    "sg:postcode":"98004",
    "sg:province":"WA",
    "sg:tags":[
        "veterinarian"
    ],
    "wof:name":"Hodges Thomas Gil DVM",
    "wof:placetype":"venue"
},
  "geometry": {"coordinates":[-122.202003,47.620201],"type":"Point"}
}