{
  "type": "Feature",
  "properties": {
    "addr:full":"2401 14th Ave S Seattle WA 98144",
    "addr:housenumber":"2401",
    "addr:postcode":"98144",
    "addr:street":"14Th Ave S",
    "iso:country":"US",
    "sg:address":"2401 14th Ave S",
    "sg:city":"Seattle",
    "sg:classifiers":[
        {
            "category":"Shopping",
            "type":"Retail Goods"
        }
    ],
    "sg:phone":"+1 206 860 7615",
    "sg:postcode":"98144",
    "sg:province":"WA",
    "sg:tags":[
        "merchandise"
    ],
    "wof:name":"Kathleen McHugh",
    "wof:placetype":"venue"
},
  "geometry": {"coordinates":[-122.314714,47.581019],"type":"Point"}
}