{
  "type": "Feature",
  "properties": {
    "addr:full":"801 N 3rd St Yakima WA 98901",
    "addr:housenumber":"801",
    "addr:postcode":"98901",
    "addr:street":"N 3Rd St",
    "iso:country":"US",
    "sg:address":"801 N 3rd St",
    "sg:city":"Yakima",
    "sg:classifiers":[
        {
            "category":"Social Services",
            "subcategory":"Child Care",
            "type":"Services"
        }
    ],
    "sg:phone":"+1 509 573 3315",
    "sg:postcode":"98901",
    "sg:province":"WA",
    "sg:tags":[
        "day"
    ],
    "wof:name":"Rachels Day Care",
    "wof:placetype":"venue"
},
  "geometry": {"coordinates":[-120.50860900000001,46.614338],"type":"Point"}
}