{
  "type": "Feature",
  "properties": {
    "addr:full":"3501 Illinois Ln Bellingham WA 98226",
    "addr:housenumber":"3501",
    "addr:postcode":"98226",
    "addr:street":"Illinois Ln",
    "iso:country":"US",
    "sg:address":"3501 Illinois Ln",
    "sg:city":"Bellingham",
    "sg:classifiers":[
        {
            "category":"Professional",
            "subcategory":"Management & Consulting",
            "type":"Services"
        }
    ],
    "sg:phone":"+1 360 671 2298",
    "sg:postcode":"98226",
    "sg:province":"WA",
    "wof:name":"CJ Transportation",
    "wof:placetype":"venue"
},
  "geometry": {"coordinates":[-122.428635,48.768106],"type":"Point"}
}