{
  "type": "Feature",
  "properties": {
    "addr:full":"10221 152nd St E Puyallup WA 98374",
    "addr:housenumber":"10221",
    "addr:postcode":"98374",
    "addr:street":"152Nd St E",
    "iso:country":"US",
    "sg:address":"10221 152nd St E",
    "sg:city":"Puyallup",
    "sg:classifiers":[
        {
            "category":"Social Services",
            "subcategory":"Child Care",
            "type":"Services"
        }
    ],
    "sg:phone":"+1 253 840 5686",
    "sg:postcode":"98374",
    "sg:province":"WA",
    "sg:tags":[
        "day"
    ],
    "wof:name":"Kindercare Child Care Network",
    "wof:placetype":"venue"
},
  "geometry": {"coordinates":[-122.291571,47.118454],"type":"Point"}
}