{
  "type": "Feature",
  "properties": {
    "addr:full":"593 Industry Dr Seattle WA 98188",
    "addr:housenumber":"593",
    "addr:postcode":"98188",
    "addr:street":"Industry Dr",
    "iso:country":"US",
    "sg:address":"593 Industry Dr",
    "sg:city":"Seattle",
    "sg:classifiers":[
        {
            "category":"Professional",
            "subcategory":"Lawyer & Legal Services",
            "type":"Services"
        },
        {
            "category":"Professional",
            "subcategory":"Business Services",
            "type":"Services"
        }
    ],
    "sg:phone":"+1 206 575 8733",
    "sg:postcode":"98188",
    "sg:province":"WA",
    "sg:tags":[
        "bus",
        "naturalization",
        "immigration"
    ],
    "wof:name":"Alpha International Inc",
    "wof:placetype":"venue"
},
  "geometry": {"coordinates":[-122.24872499999999,47.453735],"type":"Point"}
}