{
  "type": "Feature",
  "properties": {
    "addr:full":"1518 Main St Sumner WA 98390",
    "addr:housenumber":"1518",
    "addr:postcode":"98390",
    "addr:street":"Main St",
    "iso:country":"US",
    "sg:address":"1518 Main St",
    "sg:city":"Sumner",
    "sg:classifiers":[
        {
            "category":"Health Services",
            "subcategory":"Doctor",
            "type":"Services"
        }
    ],
    "sg:phone":"+1 253 863 6338",
    "sg:postcode":"98390",
    "sg:province":"WA",
    "sg:tags":[
        "medical",
        "clinic"
    ],
    "wof:name":"Sumner Family Medicine",
    "wof:placetype":"venue"
},
  "geometry": {"coordinates":[-122.23487,47.203098],"type":"Point"}
}