{
  "type": "Feature",
  "properties": {
    "addr:full":"1026 7th Ave SW Puyallup WA 98371",
    "addr:housenumber":"1026",
    "addr:postcode":"98371",
    "addr:street":"7Th Ave Sw",
    "iso:country":"US",
    "sg:address":"1026 7th Ave SW",
    "sg:city":"Puyallup",
    "sg:classifiers":[
        {
            "category":"Organizations",
            "subcategory":"Religious Organization",
            "type":"Services"
        }
    ],
    "sg:phone":"+1 253 845 7508",
    "sg:postcode":"98371",
    "sg:province":"WA",
    "sg:tags":[
        "church"
    ],
    "sg:website":"www.puyallupnazarene.org",
    "wof:name":"Puyallup Church of Nazarene",
    "wof:placetype":"venue"
},
  "geometry": {"coordinates":[-122.30717199999999,47.186172],"type":"Point"}
}