{
  "type": "Feature",
  "properties": {
    "addr:full":"19325 66th Ave W Lynnwood WA 98036",
    "addr:housenumber":"19325",
    "addr:postcode":"98036",
    "addr:street":"66Th Ave W",
    "iso:country":"US",
    "sg:address":"19325 66th Ave W",
    "sg:city":"Lynnwood",
    "sg:classifiers":[
        {
            "category":"Building & Trades",
            "subcategory":"Construction",
            "type":"Services"
        }
    ],
    "sg:phone":"+1 425 776 1397",
    "sg:postcode":"98036",
    "sg:province":"WA",
    "sg:tags":[
        "house"
    ],
    "wof:name":"Boswell Construction",
    "wof:placetype":"venue"
},
  "geometry": {"coordinates":[-122.322791,47.821493],"type":"Point"}
}