{
  "type": "Feature",
  "properties": {
    "addr:full":"5042 15th Ave NE Seattle WA 98105",
    "addr:housenumber":"5042",
    "addr:postcode":"98105",
    "addr:street":"15Th Ave Ne",
    "iso:country":"US",
    "sg:address":"5042 15th Ave NE",
    "sg:city":"Seattle",
    "sg:classifiers":[
        {
            "category":"Building & Trades",
            "subcategory":"Locksmith",
            "type":"Services"
        }
    ],
    "sg:phone":"+1 206 701 8466",
    "sg:postcode":"98105",
    "sg:province":"WA",
    "sg:tags":[
        "key"
    ],
    "wof:name":"Locksmith Express",
    "wof:placetype":"venue"
},
  "geometry": {"coordinates":[-122.311708,47.665211],"type":"Point"}
}