{
  "type": "Feature",
  "properties": {
    "addr:full":"10302 66th Ave E Puyallup WA 98373",
    "addr:housenumber":"10302",
    "addr:postcode":"98373",
    "addr:street":"66Th Ave E",
    "iso:country":"US",
    "sg:address":"10302 66th Ave E",
    "sg:city":"Puyallup",
    "sg:classifiers":[
        {
            "category":"Building & Trades",
            "subcategory":"Landscaping Services",
            "type":"Services"
        }
    ],
    "sg:phone":"+1 253 445 4139",
    "sg:postcode":"98373",
    "sg:province":"WA",
    "sg:tags":[
        "lawn",
        "maintenance",
        "grounds"
    ],
    "wof:name":"Kelly's Lawn Salon",
    "wof:placetype":"venue"
},
  "geometry": {"coordinates":[-122.341538,47.162613],"type":"Point"}
}