{
  "type": "Feature",
  "properties": {
    "addr:full":"4619 E Sorrel Ave Spokane WA 99217",
    "addr:housenumber":"4619",
    "addr:postcode":"99217",
    "addr:street":"E Sorrel Ave",
    "iso:country":"US",
    "sg:address":"4619 E Sorrel Ave",
    "sg:city":"Spokane",
    "sg:classifiers":[
        {
            "category":"Professional",
            "subcategory":"Accounting & Tax Preparation",
            "type":"Services"
        }
    ],
    "sg:phone":"+1 509 467 8753",
    "sg:postcode":"99217",
    "sg:province":"WA",
    "wof:name":"Kay A Meracle",
    "wof:placetype":"venue"
},
  "geometry": {"coordinates":[-117.34282,47.757446],"type":"Point"}
}