{
  "type": "Feature",
  "properties": {
    "addr:full":"4195 Kitsap Way Bremerton WA 98312",
    "addr:housenumber":"4195",
    "addr:postcode":"98312",
    "addr:street":"Kitsap Way",
    "iso:country":"US",
    "sg:address":"4195 Kitsap Way",
    "sg:city":"Bremerton",
    "sg:classifiers":[
        {
            "category":"Banks & Credit Unions",
            "subcategory":"Investment Brokerage",
            "type":"Services"
        },
        {
            "category":"Shopping",
            "subcategory":"Computers & Home Electronics",
            "type":"Retail Goods"
        }
    ],
    "sg:phone":"+1 360 373 7300",
    "sg:postcode":"98312",
    "sg:province":"WA",
    "sg:tags":[
        "dvd",
        "video",
        "tape",
        "sale",
        "dvds-rental"
    ],
    "sg:website":"http://www.blockbuster.com",
    "wof:name":"Blockbuster",
    "wof:placetype":"venue"
},
  "geometry": {"coordinates":[-122.669776,47.568286],"type":"Point"}
}