{
  "type": "Feature",
  "properties": {
    "addr:full":"2315 W Casino Rd Everett WA 98204",
    "addr:housenumber":"2315",
    "addr:postcode":"98204",
    "addr:street":"W Casino Rd",
    "iso:country":"US",
    "sg:address":"2315 W Casino Rd",
    "sg:city":"Everett",
    "sg:classifiers":[
        {
            "category":"Wholesale",
            "subcategory":"Construction Materials",
            "type":"Manufacturing & Wholesale Goods"
        }
    ],
    "sg:phone":"+1 425 290 9556",
    "sg:postcode":"98204",
    "sg:province":"WA",
    "sg:tags":[
        "windows",
        "roofing",
        "siding"
    ],
    "wof:name":"ABC Supply Co",
    "wof:placetype":"venue"
},
  "geometry": {"coordinates":[-122.26431100000001,47.920112],"type":"Point"}
}