{
  "type": "Feature",
  "properties": {
    "addr:full":"1420 5th Ave Ste 2400 Seattle WA 98101",
    "addr:housenumber":"1420",
    "addr:postcode":"98101",
    "addr:street":"5Th Ave Ste 2400",
    "iso:country":"US",
    "sg:address":"1420 5th Ave Ste 2400",
    "sg:city":"Seattle",
    "sg:classifiers":[
        {
            "category":"Home & Garden",
            "subcategory":"Home Furnishings",
            "type":"Retail Goods"
        }
    ],
    "sg:phone":"+1 206 623 4646",
    "sg:postcode":"98101",
    "sg:province":"WA",
    "sg:tags":[
        "house"
    ],
    "sg:website":"http://www.callison.com",
    "wof:name":"T C P Sources Inc",
    "wof:placetype":"venue"
},
  "geometry": {"coordinates":[-122.33486600000001,47.609869],"type":"Point"}
}