{
  "type": "Feature",
  "properties": {
    "addr:full":"2030 N Hamilton St Spokane WA 99207",
    "addr:housenumber":"2030",
    "addr:postcode":"99207",
    "addr:street":"N Hamilton St",
    "iso:country":"US",
    "sg:address":"2030 N Hamilton St",
    "sg:city":"Spokane",
    "sg:classifiers":[
        {
            "category":"Shopping",
            "subcategory":"Clothing, Apparel, & Fashions",
            "type":"Retail Goods"
        }
    ],
    "sg:phone":"+1 509 489 1364",
    "sg:postcode":"99207",
    "sg:province":"WA",
    "sg:tags":[
        "dance",
        "square"
    ],
    "wof:name":"Circle 8 Squaredance Shop",
    "wof:placetype":"venue"
},
  "geometry": {"coordinates":[-117.39648,47.675908],"type":"Point"}
}