{
  "type": "Feature",
  "properties": {
    "addr:full":"13334 3rd Ave NE Seattle WA 98125",
    "addr:housenumber":"13334",
    "addr:postcode":"98125",
    "addr:street":"3Rd Ave Ne",
    "iso:country":"US",
    "sg:address":"13334 3rd Ave NE",
    "sg:city":"Seattle",
    "sg:classifiers":[
        {
            "category":"Building & Trades",
            "subcategory":"Locksmith",
            "type":"Services"
        }
    ],
    "sg:phone":"+1 206 494 0209",
    "sg:postcode":"98125",
    "sg:province":"WA",
    "sg:tags":[
        "key"
    ],
    "wof:name":"Emergency All Day Locksmith",
    "wof:placetype":"venue"
},
  "geometry": {"coordinates":[-122.325982,47.725922],"type":"Point"}
}