{
  "type": "Feature",
  "properties": {
    "addr:full":"1933 NE 125th St Seattle WA 98125",
    "addr:housenumber":"1933",
    "addr:postcode":"98125",
    "addr:street":"Ne 125Th St",
    "iso:country":"US",
    "sg:address":"1933 NE 125th St",
    "sg:city":"Seattle",
    "sg:classifiers":[
        {
            "category":"Organizations",
            "subcategory":"Religious Organization",
            "type":"Services"
        }
    ],
    "sg:phone":"+1 206 363 1438",
    "sg:postcode":"98125",
    "sg:province":"WA",
    "wof:name":"Lake City Chrstn Church",
    "wof:placetype":"venue"
},
  "geometry": {"coordinates":[-122.30813000000001,47.7193],"type":"Point"}
}