{
  "type": "Feature",
  "properties": {
    "addr:full":"4754 University Way NE Seattle WA 98105",
    "addr:housenumber":"4754",
    "addr:postcode":"98105",
    "addr:street":"University Way Ne",
    "iso:country":"US",
    "sg:address":"4754 University Way NE",
    "sg:city":"Seattle",
    "sg:classifiers":[
        {
            "category":"Food & Beverages",
            "subcategory":"Bakery",
            "type":"Retail Goods"
        }
    ],
    "sg:phone":"+1 206 527 2040",
    "sg:postcode":"98105",
    "sg:province":"WA",
    "sg:tags":[
        "sandwich"
    ],
    "wof:name":"Subs Sandwiches",
    "wof:placetype":"venue"
},
  "geometry": {"coordinates":[-122.31300400000001,47.6633],"type":"Point"}
}