{
  "type": "Feature",
  "properties": {
    "addr:full":"17839 NE 224th Ct Brush Prairie WA 98606",
    "addr:housenumber":"17839",
    "addr:postcode":"98606",
    "addr:street":"Ne 224Th Ct",
    "iso:country":"US",
    "sg:address":"17839 NE 224th Ct",
    "sg:city":"Brush Prairie",
    "sg:classifiers":[
        {
            "category":"Recreation",
            "type":"Entertainment"
        }
    ],
    "sg:phone":"+1 360 254 3194",
    "sg:postcode":"98606",
    "sg:province":"WA",
    "wof:name":"Rainbow Pony Rides",
    "wof:placetype":"venue"
},
  "geometry": {"coordinates":[-122.440691,45.748161],"type":"Point"}
}