{
  "type": "Feature",
  "properties": {
    "addr:full":"12800 Hwy 99 Everett WA 98204",
    "addr:housenumber":"12800",
    "addr:postcode":"98204",
    "addr:street":"Hwy 99",
    "iso:country":"US",
    "sg:address":"12800 Hwy 99",
    "sg:city":"Everett",
    "sg:classifiers":[
        {
            "category":"Autos & Motor Vehicles",
            "subcategory":"Automobile Sales",
            "type":"Retail Goods"
        }
    ],
    "sg:phone":"+1 425 514 3040",
    "sg:postcode":"98204",
    "sg:province":"WA",
    "sg:tags":[
        "used"
    ],
    "wof:name":"Whataway To Go Autos LLC",
    "wof:placetype":"venue"
},
  "geometry": {"coordinates":[-122.264965,47.88233],"type":"Point"}
}