{
  "type": "Feature",
  "properties": {
    "iso:country":"US",
    "sg:address":"441 W Washington St",
    "sg:city":"Sequim",
    "sg:classifiers":[
        {
            "category":"Professional",
            "subcategory":"Accounting & Tax Preparation",
            "type":"Services"
        }
    ],
    "sg:phone":"+1 360 683 3229",
    "sg:postcode":"98382",
    "sg:province":"WA",
    "sg:tags":[
        "accountant"
    ],
    "wof:name":"Lewis W Kastner CPA",
    "wof:placetype":"venue"
},
  "geometry": {"coordinates":[-123.11221500000001,48.079748],"type":"Point"}
}