{
  "type": "Feature",
  "properties": {
    "addr:full":"9988 N Newport Hwy Spokane WA 99218",
    "addr:housenumber":"9988",
    "addr:postcode":"99218",
    "addr:street":"N Newport Hwy",
    "iso:country":"US",
    "sg:address":"9988 N Newport Hwy",
    "sg:city":"Spokane",
    "sg:classifiers":[
        {
            "category":"Personal",
            "subcategory":"Beauty Salon",
            "type":"Services"
        },
        {
            "category":"Personal",
            "subcategory":"Barber",
            "type":"Services"
        }
    ],
    "sg:phone":"+1 509 466 8379",
    "sg:postcode":"99218",
    "sg:province":"WA",
    "sg:tags":[
        "hair",
        "accessory",
        "stylist",
        "supply"
    ],
    "sg:website":"http://www.greatclips.com/",
    "wof:name":"Great Clips",
    "wof:placetype":"venue"
},
  "geometry": {"coordinates":[-117.404163,47.747332],"type":"Point"}
}