{
  "type": "Feature",
  "properties": {
    "addr:full":"2806 S Dearborn St Seattle WA 98144",
    "addr:housenumber":"2806",
    "addr:postcode":"98144",
    "addr:street":"S Dearborn St",
    "iso:country":"US",
    "sg:address":"2806 S Dearborn St",
    "sg:city":"Seattle",
    "sg:classifiers":[
        {
            "category":"Building & Trades",
            "subcategory":"Cleaning & Sanitation",
            "type":"Services"
        }
    ],
    "sg:phone":"+1 206 323 7051",
    "sg:postcode":"98144",
    "sg:province":"WA",
    "sg:tags":[
        "cleaning-industrial",
        "contractor"
    ],
    "wof:name":"Cwl Cleaning Services",
    "wof:placetype":"venue"
},
  "geometry": {"coordinates":[-122.296283,47.59579],"type":"Point"}
}