{
  "type": "Feature",
  "properties": {
    "addr:full":"401 2nd Avenue Seattle WA 98101",
    "addr:housenumber":"401",
    "addr:postcode":"98101",
    "addr:street":"2Nd Avenue",
    "iso:country":"US",
    "sg:address":"401 2nd Avenue",
    "sg:city":"Seattle",
    "sg:classifiers":[
        {
            "category":"Shopping",
            "subcategory":"Jewelry",
            "type":"Retail Goods"
        },
        {
            "category":"Shopping",
            "subcategory":"Pawn Shop",
            "type":"Retail Goods"
        }
    ],
    "sg:phone":"+1 206 623 6654",
    "sg:postcode":"98101",
    "sg:province":"WA",
    "wof:name":"Barney's Jewelry and Loan",
    "wof:placetype":"venue"
},
  "geometry": {"coordinates":[-122.332998,47.61039],"type":"Point"}
}