{
  "type": "Feature",
  "properties": {
    "addr:full":"8635 SE 68th St Mercer Island WA 98040",
    "addr:housenumber":"8635",
    "addr:postcode":"98040",
    "addr:street":"Se 68Th St",
    "iso:country":"US",
    "sg:address":"8635 SE 68th St",
    "sg:city":"Mercer Island",
    "sg:classifiers":[
        {
            "category":"Education",
            "subcategory":"Preschool",
            "type":"Public Place"
        },
        {
            "category":"Education",
            "subcategory":"School",
            "type":"Public Place"
        }
    ],
    "sg:phone":"+1 206 232 5776",
    "sg:postcode":"98040",
    "sg:province":"WA",
    "sg:tags":[
        "elementary"
    ],
    "wof:name":"Sunnybeam School",
    "wof:placetype":"venue"
},
  "geometry": {"coordinates":[-122.22399900000001,47.542198],"type":"Point"}
}