{
  "type": "Feature",
  "properties": {
    "addr:full":"4621 Bellview St W University Place WA 98466",
    "addr:housenumber":"4621",
    "addr:postcode":"98466",
    "addr:street":"Bellview St W;Place",
    "iso:country":"US",
    "sg:address":"4621 Bellview St W",
    "sg:city":"University Place",
    "sg:classifiers":[
        {
            "category":"Professional",
            "subcategory":"Accounting & Tax Preparation",
            "type":"Services"
        }
    ],
    "sg:phone":"+1 253 565 2309",
    "sg:postcode":"98466",
    "sg:province":"WA",
    "sg:tags":[
        "accountant"
    ],
    "wof:name":"Marilyn M Sheasley CPA",
    "wof:placetype":"venue"
},
  "geometry": {"coordinates":[-122.570198,47.213991],"type":"Point"}
}