{
  "type": "Feature",
  "properties": {
    "addr:full":"1109 W Yakima Ave Yakima WA 98902",
    "addr:housenumber":"1109",
    "addr:postcode":"98902",
    "addr:street":"W Yakima Ave",
    "iso:country":"US",
    "sg:address":"1109 W Yakima Ave",
    "sg:city":"Yakima",
    "sg:classifiers":[
        {
            "category":"Retail",
            "subcategory":"Portrait Studio",
            "type":"Services"
        },
        {
            "category":"Professional",
            "subcategory":"Art Services",
            "type":"Services"
        }
    ],
    "sg:phone":"+1 509 452 0432",
    "sg:postcode":"98902",
    "sg:province":"WA",
    "sg:tags":[
        "photographer",
        "photo"
    ],
    "wof:name":"Image West Photography",
    "wof:placetype":"venue"
},
  "geometry": {"coordinates":[-120.524334,46.598037],"type":"Point"}
}