{
  "type": "Feature",
  "properties": {
    "addr:full":"437 25th Ave E Seattle WA 98112",
    "addr:housenumber":"437",
    "addr:postcode":"98112",
    "addr:street":"25Th Ave E",
    "iso:country":"US",
    "sg:address":"437 25th Ave E",
    "sg:city":"Seattle",
    "sg:classifiers":[
        {
            "category":"Education",
            "subcategory":"Special Training",
            "type":"Public Place"
        }
    ],
    "sg:phone":"+1 206 323 2762",
    "sg:postcode":"98112",
    "sg:province":"WA",
    "wof:name":"Cellular Wisdom",
    "wof:placetype":"venue"
},
  "geometry": {"coordinates":[-122.29984899999999,47.624376],"type":"Point"}
}