{
  "type": "Feature",
  "properties": {
    "addr:full":"20312 15th Ave NW Seattle WA 98177",
    "addr:housenumber":"20312",
    "addr:postcode":"98177",
    "addr:street":"15Th Ave Nw",
    "iso:country":"US",
    "sg:address":"20312 15th Ave NW",
    "sg:city":"Seattle",
    "sg:classifiers":[
        {
            "category":"Home & Garden",
            "subcategory":"Garden Supply",
            "type":"Retail Goods"
        }
    ],
    "sg:phone":"+1 206 546 1281",
    "sg:postcode":"98177",
    "sg:province":"WA",
    "wof:name":"Msk Rare Plant Nursery",
    "wof:placetype":"venue"
},
  "geometry": {"coordinates":[-122.37738299999999,47.777004],"type":"Point"}
}