{
  "type": "Feature",
  "properties": {
    "addr:full":"706 Butterfield Rd Yakima WA 98901",
    "addr:housenumber":"706",
    "addr:postcode":"98901",
    "addr:street":"Butterfield Rd",
    "iso:country":"US",
    "sg:address":"706 Butterfield Rd",
    "sg:city":"Yakima",
    "sg:classifiers":[
        {
            "category":"Communications",
            "subcategory":"Radio Station",
            "type":"Services"
        }
    ],
    "sg:phone":"+1 509 452 5925",
    "sg:postcode":"98901",
    "sg:province":"WA",
    "sg:tags":[
        "company",
        "broadcasting"
    ],
    "wof:name":"KYAK",
    "wof:placetype":"venue"
},
  "geometry": {"coordinates":[-120.47239,46.60981],"type":"Point"}
}