{
  "type": "Feature",
  "properties": {
    "iso:country":"US",
    "sg:address":"2200 N 77th St",
    "sg:city":"Seattle",
    "sg:classifiers":[
        {
            "category":"Professional",
            "subcategory":"Management & Consulting",
            "type":"Services"
        }
    ],
    "sg:phone":"+1 206 524 8555",
    "sg:postcode":"98103",
    "sg:province":"WA",
    "sg:website":"www.consensustech.com",
    "wof:name":"Consensus Technology",
    "wof:placetype":"venue"
},
  "geometry": {"coordinates":[-122.332548,47.685174],"type":"Point"}
}