{
  "type": "Feature",
  "properties": {
    "addr:full":"301 N 1st St Sunnyside WA 98944",
    "addr:housenumber":"301",
    "addr:postcode":"98944",
    "addr:street":"N 1St St",
    "iso:country":"US",
    "sg:address":"301 N 1st St",
    "sg:city":"Sunnyside",
    "sg:classifiers":[
        {
            "category":"Banks & Credit Unions",
            "subcategory":"Investment Brokerage",
            "type":"Services"
        }
    ],
    "sg:phone":"+1 509 837 8464",
    "sg:postcode":"98944",
    "sg:province":"WA",
    "sg:tags":[
        "security"
    ],
    "wof:name":"AIG Royal Alliance",
    "wof:placetype":"venue"
},
  "geometry": {"coordinates":[-120.020089,46.331523],"type":"Point"}
}