{
  "type": "Feature",
  "properties": {
    "addr:full":"7200 W Nob Hill Blvd Yakima WA 98908",
    "addr:housenumber":"7200",
    "addr:postcode":"98908",
    "addr:street":"W Nob Hill Blvd",
    "iso:country":"US",
    "sg:address":"7200 W Nob Hill Blvd",
    "sg:city":"Yakima",
    "sg:classifiers":[
        {
            "category":"Food & Beverages",
            "subcategory":"Groceries & Convenience Stores",
            "type":"Retail Goods"
        }
    ],
    "sg:phone":"+1 509 966 7320",
    "sg:postcode":"98908",
    "sg:province":"WA",
    "wof:name":"Shell",
    "wof:placetype":"venue"
},
  "geometry": {"coordinates":[-120.60767199999999,46.585767],"type":"Point"}
}