{
  "type": "Feature",
  "properties": {
    "addr:full":"10 Front St Friday Harbor WA 98250",
    "addr:housenumber":"10",
    "addr:postcode":"98250",
    "addr:street":"Front St",
    "iso:country":"US",
    "sg:address":"10 Front St",
    "sg:city":"Friday Harbor",
    "sg:classifiers":[
        {
            "category":"Restaurant",
            "type":"Food & Drink"
        }
    ],
    "sg:phone":"+1 360 378 2700",
    "sg:postcode":"98250",
    "sg:province":"WA",
    "wof:name":"Downriggers",
    "wof:placetype":"venue"
},
  "geometry": {"coordinates":[-123.016111,48.535868],"type":"Point"}
}