{
  "type": "Feature",
  "properties": {
    "addr:full":"208 Cedarcreek Ter Ione WA 99139",
    "addr:housenumber":"208",
    "addr:postcode":"99139",
    "addr:street":"Cedarcreek Ter Ione",
    "iso:country":"US",
    "sg:address":"208 Cedarcreek Ter",
    "sg:city":"Ione",
    "sg:classifiers":[
        {
            "category":"Health Services",
            "subcategory":"Doctor",
            "type":"Services"
        }
    ],
    "sg:phone":"+1 509 442 3514",
    "sg:postcode":"99139",
    "sg:province":"WA",
    "sg:tags":[
        "physician",
        "surgeon"
    ],
    "wof:name":"Selkirk Community Health Ctr",
    "wof:placetype":"venue"
},
  "geometry": {"coordinates":[-117.417917,48.744348],"type":"Point"}
}