{
  "type": "Feature",
  "properties": {
    "addr:full":"33319 N Conklin Rd Elk WA 99009",
    "addr:housenumber":"33319",
    "addr:postcode":"99009",
    "addr:street":"N Conklin Rd",
    "iso:country":"US",
    "sg:address":"33319 N Conklin Rd",
    "sg:city":"Elk",
    "sg:classifiers":[
        {
            "category":"Building & Trades",
            "subcategory":"Plumbing",
            "type":"Services"
        }
    ],
    "sg:phone":"+1 509 292 8817",
    "sg:postcode":"99009",
    "sg:province":"WA",
    "sg:tags":[
        "plumbing",
        "contractor"
    ],
    "wof:name":"Alpha Plumbing & Heating",
    "wof:placetype":"venue"
},
  "geometry": {"coordinates":[-117.21043,47.952627],"type":"Point"}
}