{
  "type": "Feature",
  "properties": {
    "iso:country":"US",
    "sg:address":"29633 1st Ave S",
    "sg:city":"Federal Way",
    "sg:classifiers":[
        {
            "category":"Building & Trades",
            "subcategory":"Landscaping Services",
            "type":"Services"
        }
    ],
    "sg:phone":"+1 253 941 7500",
    "sg:postcode":"98003",
    "sg:province":"WA",
    "sg:tags":[
        "landscape",
        "contractor"
    ],
    "wof:name":"Fulford Ken Landscaping Svc",
    "wof:placetype":"venue"
},
  "geometry": {"coordinates":[-122.334523,47.335401],"type":"Point"}
}