{
  "type": "Feature",
  "properties": {
    "addr:full":"8753 Honeycomb Ct NW Seabeck WA 98380",
    "addr:postcode":"8753;98380",
    "addr:street":"Honeycomb Ct Nw",
    "iso:country":"US",
    "sg:address":"8753 Honeycomb Ct NW",
    "sg:city":"Seabeck",
    "sg:classifiers":[
        {
            "category":"Shopping",
            "subcategory":"Discount & Variety Stores",
            "type":"Retail Goods"
        }
    ],
    "sg:phone":"+1 360 830 3525",
    "sg:postcode":"98380",
    "sg:province":"WA",
    "sg:tags":[
        "merchandise",
        "general"
    ],
    "wof:name":"Caldwell Enterprises",
    "wof:placetype":"venue"
},
  "geometry": {"coordinates":[-122.846323,47.642292],"type":"Point"}
}