{
  "type": "Feature",
  "properties": {
    "addr:full":"408 N K St Tacoma WA 98403",
    "addr:housenumber":"408",
    "addr:postcode":"98403",
    "addr:street":"N K St",
    "iso:country":"US",
    "sg:address":"408 N K St",
    "sg:city":"Tacoma",
    "sg:classifiers":[
        {
            "category":"Professional",
            "type":"Services"
        }
    ],
    "sg:phone":"+1 253 627 2107",
    "sg:postcode":"98403",
    "sg:province":"WA",
    "wof:name":"Philip G Masenheimer",
    "wof:placetype":"venue"
},
  "geometry": {"coordinates":[-122.457121,47.261771],"type":"Point"}
}