{
  "type": "Feature",
  "properties": {
    "addr:full":"707 W Spruce St Yakima WA 98902",
    "addr:housenumber":"707",
    "addr:postcode":"98902",
    "addr:street":"W Spruce St",
    "iso:country":"US",
    "sg:address":"707 W Spruce St",
    "sg:city":"Yakima",
    "sg:classifiers":[
        {
            "category":"Organizations",
            "subcategory":"Religious Organization",
            "type":"Services"
        }
    ],
    "sg:phone":"+1 509 453 6727",
    "sg:postcode":"98902",
    "sg:province":"WA",
    "wof:name":"Community of Christ",
    "wof:placetype":"venue"
},
  "geometry": {"coordinates":[-120.518158,46.595336],"type":"Point"}
}