{
  "type": "Feature",
  "properties": {
    "addr:full":"3600 E Marginal Way S Seattle WA 98134",
    "addr:housenumber":"3600",
    "addr:postcode":"98134",
    "addr:street":"E Marginal Way S",
    "iso:country":"US",
    "sg:address":"3600 E Marginal Way S",
    "sg:city":"Seattle",
    "sg:classifiers":[
        {
            "category":"Manufacturing",
            "subcategory":"Metals",
            "type":"Manufacturing & Wholesale Goods"
        }
    ],
    "sg:phone":"+1 206 794 4074",
    "sg:postcode":"98134",
    "sg:province":"WA",
    "sg:tags":[
        "fabrication",
        "structural"
    ],
    "wof:name":"Alki Foundry",
    "wof:placetype":"venue"
},
  "geometry": {"coordinates":[-122.339821,47.571383],"type":"Point"}
}