{
  "type": "Feature",
  "properties": {
    "addr:full":"8721 15th Ave NW Seattle WA 98117",
    "addr:housenumber":"8721",
    "addr:postcode":"98117",
    "addr:street":"15Th Ave Nw",
    "iso:country":"US",
    "sg:address":"8721 15th Ave NW",
    "sg:city":"Seattle",
    "sg:classifiers":[
        {
            "category":"Retail",
            "subcategory":"Laundry & Dry Cleaning",
            "type":"Services"
        }
    ],
    "sg:phone":"+1 206 789 2170",
    "sg:postcode":"98117",
    "sg:province":"WA",
    "sg:tags":[
        "drycleaning",
        "plant",
        "cleaners"
    ],
    "wof:name":"Crown Cleaners Inc",
    "wof:placetype":"venue"
},
  "geometry": {"coordinates":[-122.376876,47.694131],"type":"Point"}
}