{
  "type": "Feature",
  "properties": {
    "addr:full":"9531 225th Way NE Redmond WA 98053",
    "addr:housenumber":"9531",
    "addr:postcode":"98053",
    "addr:street":"225Th Way Ne",
    "iso:country":"US",
    "sg:address":"9531 225th Way NE",
    "sg:city":"Redmond",
    "sg:classifiers":[
        {
            "category":"Organizations",
            "subcategory":"Religious Organization",
            "type":"Services"
        }
    ],
    "sg:phone":"+1 425 898 7244",
    "sg:postcode":"98053",
    "sg:province":"WA",
    "wof:name":"One New Man Ministry",
    "wof:placetype":"venue"
},
  "geometry": {"coordinates":[-122.040792,47.684471],"type":"Point"}
}