{
  "type": "Feature",
  "properties": {
    "addr:full":"5101 NE 82nd Ave Vancouver WA 98662",
    "addr:housenumber":"5101",
    "addr:postcode":"98662",
    "addr:street":"Ne 82Nd Ave",
    "iso:country":"US",
    "sg:address":"5101 NE 82nd Ave",
    "sg:city":"Vancouver",
    "sg:classifiers":[
        {
            "category":"Insurance",
            "subcategory":"Insurance Agent",
            "type":"Services"
        },
        {
            "category":"Insurance",
            "subcategory":"Hazard Insurance",
            "type":"Services"
        },
        {
            "category":"Insurance",
            "subcategory":"Title Insurance",
            "type":"Services"
        },
        {
            "category":"Insurance",
            "subcategory":"Health Insurance",
            "type":"Services"
        },
        {
            "category":"Insurance",
            "subcategory":"Life Insurance",
            "type":"Services"
        }
    ],
    "sg:phone":"+1 360 892 1888",
    "sg:postcode":"98662",
    "sg:province":"WA",
    "sg:tags":[
        "business",
        "auto",
        "commercial",
        "homeowner",
        "casualty",
        "motorcycle",
        "renter",
        "property",
        "marine",
        "boat"
    ],
    "sg:website":"http://www.amfam.com/agentlocator/RHOWES?sourceid=yp9",
    "wof:name":"American Family Insurance- Ryan Howes Agency",
    "wof:placetype":"venue"
},
  "geometry": {"coordinates":[-122.588814,45.659088],"type":"Point"}
}