{
  "type": "Feature",
  "properties": {
    "addr:full":"823 5th Avenue N Seattle WA 98109",
    "addr:housenumber":"823",
    "addr:postcode":"98109",
    "addr:street":"5Th Avenue N",
    "iso:country":"US",
    "sg:address":"823 5th Avenue N",
    "sg:city":"Seattle",
    "sg:classifiers":[
        {
            "category":"Restaurant",
            "type":"Food & Drink"
        }
    ],
    "sg:phone":"+1 206 283 8800",
    "sg:postcode":"98109",
    "sg:province":"WA",
    "wof:name":"Crow Restaurant & Bar",
    "wof:placetype":"venue"
},
  "geometry": {"coordinates":[-122.347703,47.626996],"type":"Point"}
}