{
  "type": "Feature",
  "properties": {
    "addr:full":"8808 Quinault Loop NE Olympia WA 98516",
    "addr:postcode":"8808;98516",
    "addr:street":"Quinault Loop Ne",
    "iso:country":"US",
    "sg:address":"8808 Quinault Loop NE",
    "sg:city":"Olympia",
    "sg:classifiers":[
        {
            "category":"Building & Trades",
            "subcategory":"Cleaning & Sanitation",
            "type":"Services"
        }
    ],
    "sg:phone":"+1 360 459 2038",
    "sg:postcode":"98516",
    "sg:province":"WA",
    "sg:tags":[
        "maintenance"
    ],
    "wof:name":"Dependable Services/House Clg",
    "wof:placetype":"venue"
},
  "geometry": {"coordinates":[-122.749713,47.064292],"type":"Point"}
}