{
  "type": "Feature",
  "properties": {
    "addr:full":"2927 36th Avenue S Seattle WA 98144",
    "addr:housenumber":"2927",
    "addr:postcode":"98144",
    "addr:street":"36Th Avenue S",
    "iso:country":"US",
    "sg:address":"2927 36th Avenue S",
    "sg:city":"Seattle",
    "sg:classifiers":[
        {
            "category":"Professional",
            "subcategory":"Lawyer & Legal Services",
            "type":"Services"
        }
    ],
    "sg:phone":"+1 206 723 5874",
    "sg:postcode":"98144",
    "sg:province":"WA",
    "sg:tags":[
        "divorce",
        "law",
        "family"
    ],
    "wof:name":"Wechsler Barbara J",
    "wof:placetype":"venue"
},
  "geometry": {"coordinates":[-122.28756799999999,47.576241],"type":"Point"}
}