{
  "type": "Feature",
  "properties": {
    "addr:full":"8 S 2nd Ave Walla Walla WA 99362",
    "addr:housenumber":"8",
    "addr:postcode":"99362",
    "addr:street":"S 2Nd Ave",
    "iso:country":"US",
    "sg:address":"8 S 2nd Ave",
    "sg:city":"Walla Walla",
    "sg:classifiers":[
        {
            "category":"Manufacturing",
            "subcategory":"Tools & Machinery",
            "type":"Manufacturing & Wholesale Goods"
        }
    ],
    "sg:phone":"+1 509 529 2646",
    "sg:postcode":"99362",
    "sg:province":"WA",
    "sg:tags":[
        "equipment",
        "irrigation",
        "system"
    ],
    "wof:name":"Fountainhead",
    "wof:placetype":"venue"
},
  "geometry": {"coordinates":[-118.33940200000001,46.066624],"type":"Point"}
}