{
  "type": "Feature",
  "properties": {
    "addr:full":"21900 Highway 99 Edmonds WA 98026",
    "addr:housenumber":"21900",
    "addr:postcode":"98026",
    "addr:street":"Highway 99",
    "iso:country":"US",
    "sg:address":"21900 Highway 99",
    "sg:city":"Edmonds",
    "sg:classifiers":[
        {
            "category":"Personal",
            "type":"Services"
        },
        {
            "category":"Wholesale",
            "subcategory":"Scrap",
            "type":"Manufacturing & Wholesale Goods"
        }
    ],
    "sg:phone":"+1 425 467 5610",
    "sg:postcode":"98026",
    "sg:province":"WA",
    "sg:tags":[
        "truck",
        "towing",
        "wrecking"
    ],
    "wof:name":"Able Towing & Wrecker",
    "wof:placetype":"venue"
},
  "geometry": {"coordinates":[-122.33095899999999,47.800712],"type":"Point"}
}