{
  "type": "Feature",
  "properties": {
    "iso:country":"US",
    "sg:address":"4031 Vantage Hwy",
    "sg:city":"Ellensburg",
    "sg:classifiers":[
        {
            "category":"Shopping",
            "subcategory":"Bicycles & Sporting Goods",
            "type":"Retail Goods"
        }
    ],
    "sg:phone":"+1 509 925 2648",
    "sg:postcode":"98926",
    "sg:province":"WA",
    "sg:tags":[
        "saddlery",
        "harness"
    ],
    "wof:name":"Panattoni's Leather Shop",
    "wof:placetype":"venue"
},
  "geometry": {"coordinates":[-120.47800100000001,46.999916],"type":"Point"}
}