{
  "type": "Feature",
  "properties": {
    "addr:full":"4743 NW Quartz Ct Camas WA 98607",
    "addr:housenumber":"4743",
    "addr:postcode":"98607",
    "addr:street":"Nw Quartz Ct",
    "iso:country":"US",
    "sg:address":"4743 NW Quartz Ct",
    "sg:city":"Camas",
    "sg:classifiers":[
        {
            "category":"Professional",
            "type":"Services"
        }
    ],
    "sg:phone":"+1 360 696 9040",
    "sg:postcode":"98607",
    "sg:province":"WA",
    "wof:name":"Denjoe LLC",
    "wof:placetype":"venue"
},
  "geometry": {"coordinates":[-122.428929,45.614296],"type":"Point"}
}