{
  "type": "Feature",
  "properties": {
    "addr:full":"3504 S Inland Empire Way Spokane WA 99224",
    "addr:housenumber":"3504",
    "addr:postcode":"99224",
    "addr:street":"S Inland Empire Way",
    "iso:country":"US",
    "sg:address":"3504 S Inland Empire Way",
    "sg:city":"Spokane",
    "sg:classifiers":[
        {
            "category":"Autos & Motor Vehicles",
            "subcategory":"Auto Supplies",
            "type":"Retail Goods"
        }
    ],
    "sg:phone":"+1 509 456 4367",
    "sg:postcode":"99224",
    "sg:province":"WA",
    "sg:tags":[
        "used",
        "parts"
    ],
    "wof:name":"A & A Auto Spangle",
    "wof:placetype":"venue"
},
  "geometry": {"coordinates":[-117.439125,47.624193],"type":"Point"}
}