{
  "type": "Feature",
  "properties": {
    "addr:full":"3708 Airport Way S Seattle WA 98134",
    "addr:housenumber":"3708",
    "addr:postcode":"98134",
    "addr:street":"Airport Way S",
    "iso:country":"US",
    "sg:address":"3708 Airport Way S",
    "sg:city":"Seattle",
    "sg:classifiers":[
        {
            "category":"Retail",
            "subcategory":"Portrait Studio",
            "type":"Services"
        }
    ],
    "sg:phone":"+1 206 343 9900",
    "sg:postcode":"98134",
    "sg:province":"WA",
    "sg:tags":[
        "photography",
        "store"
    ],
    "sg:website":"www.optechsdigital.com",
    "wof:name":"Optechs Digital",
    "wof:placetype":"venue"
},
  "geometry": {"coordinates":[-122.322699,47.570378],"type":"Point"}
}