{
  "type": "Feature",
  "properties": {
    "addr:full":"1301 6th Ave Seattle WA 98101",
    "addr:housenumber":"1301",
    "addr:postcode":"98101",
    "addr:street":"6Th Ave",
    "iso:country":"US",
    "sg:address":"1301 6th Ave",
    "sg:city":"Seattle",
    "sg:classifiers":[
        {
            "category":"Shopping",
            "subcategory":"Gifts & Souvenirs",
            "type":"Retail Goods"
        }
    ],
    "sg:phone":"+1 206 292 7110",
    "sg:postcode":"98101",
    "sg:province":"WA",
    "wof:name":"Juns Gift Shop",
    "wof:placetype":"venue"
},
  "geometry": {"coordinates":[-122.333558,47.610147],"type":"Point"}
}