{
  "type": "Feature",
  "properties": {
    "iso:country":"US",
    "sg:address":"15814 33rd Ave NE",
    "sg:city":"Seattle",
    "sg:classifiers":[
        {
            "category":"Building & Trades",
            "subcategory":"Construction",
            "type":"Services"
        }
    ],
    "sg:phone":"+1 206 932 7663",
    "sg:postcode":"98155",
    "sg:province":"WA",
    "sg:tags":[
        "contractor"
    ],
    "wof:name":"Righteous Roofing",
    "wof:placetype":"venue"
},
  "geometry": {"coordinates":[-122.29400200000001,47.744486],"type":"Point"}
}