{
  "type": "Feature",
  "properties": {
    "addr:full":"7207 265th St NW Stanwood WA 98292",
    "addr:housenumber":"7207",
    "addr:postcode":"98292",
    "addr:street":"265Th St Nw",
    "iso:country":"US",
    "sg:address":"7207 265th St NW",
    "sg:city":"Stanwood",
    "sg:classifiers":[
        {
            "category":"Health Services",
            "subcategory":"Doctor",
            "type":"Services"
        }
    ],
    "sg:phone":"+1 360 629 6544",
    "sg:postcode":"98292",
    "sg:province":"WA",
    "sg:tags":[
        "medical"
    ],
    "wof:name":"Scott W Harris Dr",
    "wof:placetype":"venue"
},
  "geometry": {"coordinates":[-122.33183699999999,48.237152],"type":"Point"}
}