{
  "type": "Feature",
  "properties": {
    "addr:full":"7300 E Green Lake Drive N Seattle WA 98115",
    "addr:housenumber":"7300",
    "addr:postcode":"98115",
    "addr:street":"E Green Lake Drive N",
    "iso:country":"US",
    "sg:address":"7300 E Green Lake Drive N",
    "sg:city":"Seattle",
    "sg:classifiers":[
        {
            "category":"Building & Trades",
            "subcategory":"Construction",
            "type":"Services"
        }
    ],
    "sg:phone":"+1 206 527 6291",
    "sg:postcode":"98115",
    "sg:province":"WA",
    "sg:tags":[
        "contractor"
    ],
    "wof:name":"Classic City Homes",
    "wof:placetype":"venue"
},
  "geometry": {"coordinates":[-122.326115,47.680682],"type":"Point"}
}