{
  "type": "Feature",
  "properties": {
    "addr:full":"5612 104th Pl SW Mukilteo WA 98275",
    "addr:housenumber":"5612",
    "addr:postcode":"98275",
    "addr:street":"104Th Pl Sw",
    "iso:country":"US",
    "sg:address":"5612 104th Pl SW",
    "sg:city":"Mukilteo",
    "sg:classifiers":[
        {
            "category":"Insurance",
            "subcategory":"Insurance Agent",
            "type":"Services"
        }
    ],
    "sg:phone":"+1 425 315 8565",
    "sg:postcode":"98275",
    "sg:province":"WA",
    "wof:name":"Farmers Insurance Group",
    "wof:placetype":"venue"
},
  "geometry": {"coordinates":[-122.307829,47.903624],"type":"Point"}
}