{
  "type": "Feature",
  "properties": {
    "addr:full":"618 174th Pl NE Bellevue WA 98008",
    "addr:housenumber":"618",
    "addr:postcode":"98008",
    "addr:street":"174Th Pl Ne",
    "iso:country":"US",
    "sg:address":"618 174th Pl NE",
    "sg:city":"Bellevue",
    "sg:classifiers":[
        {
            "category":"Professional",
            "subcategory":"Art Services",
            "type":"Services"
        }
    ],
    "sg:phone":"+1 425 747 6170",
    "sg:postcode":"98008",
    "sg:province":"WA",
    "sg:tags":[
        "interior",
        "designer",
        "decorator"
    ],
    "wof:name":"Forever Flowers",
    "wof:placetype":"venue"
},
  "geometry": {"coordinates":[-122.10825800000001,47.615353],"type":"Point"}
}