{
  "type": "Feature",
  "properties": {
    "addr:full":"732 Firglade Dr NW Bremerton WA 98311",
    "addr:housenumber":"732",
    "addr:postcode":"98311",
    "addr:street":"Firglade Dr Nw",
    "iso:country":"US",
    "sg:address":"732 Firglade Dr NW",
    "sg:city":"Bremerton",
    "sg:classifiers":[
        {
            "category":"Social Services",
            "subcategory":"Child Care",
            "type":"Services"
        }
    ],
    "sg:phone":"+1 360 692 9501",
    "sg:postcode":"98311",
    "sg:province":"WA",
    "sg:tags":[
        "day"
    ],
    "wof:name":"Q-T Day Care",
    "wof:placetype":"venue"
},
  "geometry": {"coordinates":[-122.66081800000001,47.626802],"type":"Point"}
}