{
  "type": "Feature",
  "properties": {
    "addr:full":"7110 NW 25th Ave Vancouver WA 98665",
    "addr:housenumber":"7110",
    "addr:postcode":"98665",
    "addr:street":"Nw 25Th Ave",
    "iso:country":"US",
    "sg:address":"7110 NW 25th Ave",
    "sg:city":"Vancouver",
    "sg:classifiers":[
        {
            "category":"Organizations",
            "subcategory":"Community Association",
            "type":"Services"
        }
    ],
    "sg:phone":"+1 360 693 9752",
    "sg:postcode":"98665",
    "sg:province":"WA",
    "sg:tags":[
        "club"
    ],
    "wof:name":"Vancouver Lake Sailing",
    "wof:placetype":"venue"
},
  "geometry": {"coordinates":[-122.696882,45.673852],"type":"Point"}
}