{
  "type": "Feature",
  "properties": {
    "addr:full":"720 Olive Way Ste 300 Seattle WA 98101",
    "addr:housenumber":"720",
    "addr:postcode":"98101",
    "addr:street":"Olive Way Ste 300",
    "iso:country":"US",
    "sg:address":"720 Olive Way Ste 300",
    "sg:city":"Seattle",
    "sg:classifiers":[
        {
            "category":"Health Services",
            "subcategory":"Clinic",
            "type":"Services"
        },
        {
            "category":"Insurance",
            "subcategory":"Hazard Insurance",
            "type":"Services"
        },
        {
            "category":"Insurance",
            "subcategory":"Health Insurance",
            "type":"Services"
        }
    ],
    "sg:phone":"+1 206 521 8833",
    "sg:postcode":"98101",
    "sg:province":"WA",
    "sg:tags":[
        "employee",
        "medical",
        "benefit",
        "maintenance"
    ],
    "wof:name":"Community Health Plan Of Washington",
    "wof:placetype":"venue"
},
  "geometry": {"coordinates":[-122.334941,47.613675],"type":"Point"}
}