{
  "type": "Feature",
  "properties": {
    "addr:full":"16625 NE 26th St Bellevue WA 98008",
    "addr:housenumber":"16625",
    "addr:postcode":"98008",
    "addr:street":"Ne 26Th St",
    "iso:country":"US",
    "sg:address":"16625 NE 26th St",
    "sg:city":"Bellevue",
    "sg:classifiers":[
        {
            "category":"Wholesale",
            "subcategory":"Jewelry",
            "type":"Manufacturing & Wholesale Goods"
        },
        {
            "category":"Shopping",
            "subcategory":"Crafts & Fabrics",
            "type":"Retail Goods"
        }
    ],
    "sg:phone":"+1 425 885 2991",
    "sg:postcode":"98008",
    "sg:province":"WA",
    "sg:tags":[
        "bead",
        "beads-wholesale",
        "manufacturer"
    ],
    "wof:name":"Happy Bead",
    "wof:placetype":"venue"
},
  "geometry": {"coordinates":[-122.118995,47.632779],"type":"Point"}
}