{
  "type": "Feature",
  "properties": {
    "addr:full":"1849 Loraine St Enumclaw WA 98022",
    "addr:housenumber":"1849",
    "addr:postcode":"98022",
    "addr:street":"Loraine St",
    "iso:country":"US",
    "sg:address":"1849 Loraine St",
    "sg:city":"Enumclaw",
    "sg:classifiers":[
        {
            "category":"Manufacturing",
            "subcategory":"Buildings",
            "type":"Manufacturing & Wholesale Goods"
        },
        {
            "category":"Building & Trades",
            "subcategory":"Construction",
            "type":"Services"
        }
    ],
    "sg:phone":"+1 360 825 5802",
    "sg:postcode":"98022",
    "sg:province":"WA",
    "sg:tags":[
        "home",
        "builder",
        "industrial",
        "contractors-commercial",
        "contractor"
    ],
    "wof:name":"Okeson Construction",
    "wof:placetype":"venue"
},
  "geometry": {"coordinates":[-122.00156800000001,47.208347],"type":"Point"}
}