{
  "type": "Feature",
  "properties": {
    "iso:country":"US",
    "sg:address":"1000 Alexander Ct",
    "sg:city":"Prosser",
    "sg:classifiers":[
        {
            "category":"Wholesale",
            "subcategory":"Vending Machines",
            "type":"Manufacturing & Wholesale Goods"
        }
    ],
    "sg:phone":"+1 509 786 0272",
    "sg:postcode":"99350",
    "sg:province":"WA",
    "sg:tags":[
        "operator"
    ],
    "wof:name":"Munchies Vending",
    "wof:placetype":"venue"
},
  "geometry": {"coordinates":[-119.751822,46.205568],"type":"Point"}
}