{
  "type": "Feature",
  "properties": {
    "addr:full":"4908 208th St SE Bothell WA 98012",
    "addr:housenumber":"4908",
    "addr:postcode":"98012",
    "addr:street":"208Th St Se",
    "iso:country":"US",
    "sg:address":"4908 208th St SE",
    "sg:city":"Bothell",
    "sg:classifiers":[
        {
            "category":"Professional",
            "subcategory":"Art Services",
            "type":"Services"
        }
    ],
    "sg:phone":"+1 425 402 3879",
    "sg:postcode":"98012",
    "sg:province":"WA",
    "sg:tags":[
        "commercial",
        "design"
    ],
    "wof:name":"Brownlee Design Works",
    "wof:placetype":"venue"
},
  "geometry": {"coordinates":[-122.166759,47.808925],"type":"Point"}
}