{
  "type": "Feature",
  "properties": {
    "addr:full":"11109 66th Ave E Puyallup WA 98373",
    "addr:housenumber":"11109",
    "addr:postcode":"98373",
    "addr:street":"66Th Ave E",
    "iso:country":"US",
    "sg:address":"11109 66th Ave E",
    "sg:city":"Puyallup",
    "sg:classifiers":[
        {
            "category":"Building & Trades",
            "subcategory":"Electrical",
            "type":"Services"
        }
    ],
    "sg:phone":"+1 253 848 5595",
    "sg:postcode":"98373",
    "sg:province":"WA",
    "sg:tags":[
        "electric",
        "contractor"
    ],
    "sg:website":"www.mcelectric.com",
    "wof:name":"Meridian Center Electric",
    "wof:placetype":"venue"
},
  "geometry": {"coordinates":[-122.341295,47.155336],"type":"Point"}
}