{
  "type": "Feature",
  "properties": {
    "addr:full":"606 N Prospect St Tacoma WA 98406",
    "addr:housenumber":"606",
    "addr:postcode":"98406",
    "addr:street":"N Prospect St",
    "iso:country":"US",
    "sg:address":"606 N Prospect St",
    "sg:city":"Tacoma",
    "sg:classifiers":[
        {
            "category":"Food & Beverages",
            "subcategory":"Liquor & Beverages",
            "type":"Retail Goods"
        }
    ],
    "sg:phone":"+1 253 318 1113",
    "sg:postcode":"98406",
    "sg:province":"WA",
    "sg:tags":[
        "alcoholic"
    ],
    "wof:name":"Bacchante Wine & Essentials",
    "wof:placetype":"venue"
},
  "geometry": {"coordinates":[-122.469172,47.257167],"type":"Point"}
}