{
  "type": "Feature",
  "properties": {
    "addr:full":"3047 78th Ave SE Mercer Island WA 98040",
    "addr:housenumber":"3047",
    "addr:postcode":"98040",
    "addr:street":"78Th Ave Se",
    "iso:country":"US",
    "sg:address":"3047 78th Ave SE",
    "sg:city":"Mercer Island",
    "sg:classifiers":[
        {
            "category":"Professional",
            "subcategory":"Management & Consulting",
            "type":"Services"
        }
    ],
    "sg:phone":"+1 206 236 6231",
    "sg:postcode":"98040",
    "sg:province":"WA",
    "sg:tags":[
        "consultant",
        "business"
    ],
    "wof:name":"Boateng & Assoc",
    "wof:placetype":"venue"
},
  "geometry": {"coordinates":[-122.233724,47.582027],"type":"Point"}
}