{
  "type": "Feature",
  "properties": {
    "addr:full":"4310 NE 179th St Vancouver WA 98686",
    "addr:housenumber":"4310",
    "addr:postcode":"98686",
    "addr:street":"Ne 179Th St",
    "iso:country":"US",
    "sg:address":"4310 NE 179th St",
    "sg:city":"Vancouver",
    "sg:classifiers":[
        {
            "category":"Professional",
            "type":"Services"
        }
    ],
    "sg:phone":"+1 360 573 6036",
    "sg:postcode":"98686",
    "sg:province":"WA",
    "wof:name":"Wilfred N Zilke",
    "wof:placetype":"venue"
},
  "geometry": {"coordinates":[-122.631086,45.750926],"type":"Point"}
}