{
  "type": "Feature",
  "properties": {
    "addr:full":"2300 W Washington Ave Yakima WA 98903",
    "addr:housenumber":"2300",
    "addr:postcode":"98903",
    "addr:street":"W Washington Ave",
    "iso:country":"US",
    "sg:address":"2300 W Washington Ave",
    "sg:city":"Yakima",
    "sg:classifiers":[
        {
            "category":"Travel",
            "subcategory":"Travel Agent",
            "type":"Entertainment"
        }
    ],
    "sg:phone":"+1 509 575 0292",
    "sg:postcode":"98903",
    "sg:province":"WA",
    "sg:tags":[
        "agency"
    ],
    "wof:name":"Carlson Wagonlit Travel",
    "wof:placetype":"venue"
},
  "geometry": {"coordinates":[-120.533204,46.570872],"type":"Point"}
}