{
  "type": "Feature",
  "properties": {
    "addr:full":"13129 N Echo Lake Rd Snohomish WA 98296",
    "addr:housenumber":"13129",
    "addr:postcode":"98296",
    "addr:street":"N Echo Lake Rd",
    "iso:country":"US",
    "sg:address":"13129 N Echo Lake Rd",
    "sg:city":"Snohomish",
    "sg:classifiers":[
        {
            "category":"Social Services",
            "subcategory":"Child Care",
            "type":"Services"
        }
    ],
    "sg:phone":"+1 360 668 2185",
    "sg:postcode":"98296",
    "sg:province":"WA",
    "sg:tags":[
        "day"
    ],
    "wof:name":"Echo Kids Day Care",
    "wof:placetype":"venue"
},
  "geometry": {"coordinates":[-122.053079,47.789549],"type":"Point"}
}