{
  "type": "Feature",
  "properties": {
    "addr:full":"11104 221st Ave E Buckley WA 98321",
    "addr:housenumber":"11104",
    "addr:postcode":"98321",
    "addr:street":"221St Ave E",
    "iso:country":"US",
    "sg:address":"11104 221st Ave E",
    "sg:city":"Buckley",
    "sg:classifiers":[
        {
            "category":"Retail",
            "subcategory":"Repair Shop",
            "type":"Services"
        }
    ],
    "sg:phone":"+1 253 863 8400",
    "sg:postcode":"98321",
    "sg:province":"WA",
    "sg:tags":[
        "scooter",
        "motorcycle",
        "motor"
    ],
    "wof:name":"American Custom Cycle",
    "wof:placetype":"venue"
},
  "geometry": {"coordinates":[-122.134872,47.155349],"type":"Point"}
}