{
  "type": "Feature",
  "properties": {
    "addr:full":"353 Malaga Alcoa Hwy Wenatchee WA 98801",
    "addr:housenumber":"353",
    "addr:postcode":"98801",
    "addr:street":"Malaga Alcoa Hwy",
    "iso:country":"US",
    "sg:address":"353 Malaga Alcoa Hwy",
    "sg:city":"Wenatchee",
    "sg:classifiers":[
        {
            "category":"Professional",
            "type":"Services"
        }
    ],
    "sg:phone":"+1 509 665 8205",
    "sg:postcode":"98801",
    "sg:province":"WA",
    "wof:name":"Wenatchee Valley Kirby",
    "wof:placetype":"venue"
},
  "geometry": {"coordinates":[-120.275453,47.385559],"type":"Point"}
}