{
  "type": "Feature",
  "properties": {
    "addr:full":"20807 NE 68th St Vancouver WA 98682",
    "addr:housenumber":"20807",
    "addr:postcode":"98682",
    "addr:street":"Ne 68Th St",
    "iso:country":"US",
    "sg:address":"20807 NE 68th St",
    "sg:city":"Vancouver",
    "sg:classifiers":[
        {
            "category":"Wholesale",
            "subcategory":"Construction Materials",
            "type":"Manufacturing & Wholesale Goods"
        }
    ],
    "sg:phone":"+1 360 896 3662",
    "sg:postcode":"98682",
    "sg:province":"WA",
    "sg:tags":[
        "wholesaler",
        "building",
        "representative",
        "manufacturer"
    ],
    "wof:name":"Innovative Panel Tech Inc",
    "wof:placetype":"venue"
},
  "geometry": {"coordinates":[-122.457511,45.67207],"type":"Point"}
}