{
  "type": "Feature",
  "properties": {
    "addr:full":"3720 Meridian St Bellingham WA 98225",
    "addr:housenumber":"3720",
    "addr:postcode":"98225",
    "addr:street":"Meridian St",
    "iso:country":"US",
    "sg:address":"3720 Meridian St",
    "sg:city":"Bellingham",
    "sg:classifiers":[
        {
            "category":"Restaurant",
            "type":"Food & Drink"
        }
    ],
    "sg:phone":"+1 360 676 5555",
    "sg:postcode":"98225",
    "sg:province":"WA",
    "wof:name":"Eleni's Family Restaurant",
    "wof:placetype":"venue"
},
  "geometry": {"coordinates":[-122.486025,48.782206],"type":"Point"}
}