{
  "type": "Feature",
  "properties": {
    "addr:full":"20702 NE 101st Ct Battle Ground WA 98604",
    "addr:housenumber":"20702",
    "addr:postcode":"98604",
    "addr:street":"Ne 101St Ct",
    "iso:country":"US",
    "sg:address":"20702 NE 101st Ct",
    "sg:city":"Battle Ground",
    "sg:classifiers":[
        {
            "category":"Wholesale",
            "subcategory":"Computers",
            "type":"Manufacturing & Wholesale Goods"
        }
    ],
    "sg:phone":"+1 360 546 1934",
    "sg:postcode":"98604",
    "sg:province":"WA",
    "sg:tags":[
        "communications",
        "datum"
    ],
    "wof:name":"Adc Kentrox",
    "wof:placetype":"venue"
},
  "geometry": {"coordinates":[-122.57028,45.770837],"type":"Point"}
}