{
  "type": "Feature",
  "properties": {
    "addr:full":"18021 SE 254th St Kent WA 98042",
    "addr:postcode":"18021;98042",
    "addr:street":"Se 254Th St",
    "iso:country":"US",
    "sg:address":"18021 SE 254th St",
    "sg:city":"Kent",
    "sg:classifiers":[
        {
            "category":"Building & Trades",
            "subcategory":"Cleaning & Sanitation",
            "type":"Services"
        }
    ],
    "sg:phone":"+1 253 630 7493",
    "sg:postcode":"98042",
    "sg:province":"WA",
    "sg:tags":[
        "maintenance"
    ],
    "wof:name":"Rhondas Homecleaning Service",
    "wof:placetype":"venue"
},
  "geometry": {"coordinates":[-122.09955100000001,47.374788],"type":"Point"}
}