{
  "type": "Feature",
  "properties": {
    "addr:full":"24716 142nd Ave SE Kent WA 98042",
    "addr:housenumber":"24716",
    "addr:postcode":"98042",
    "addr:street":"142Nd Ave Se",
    "iso:country":"US",
    "sg:address":"24716 142nd Ave SE",
    "sg:city":"Kent",
    "sg:classifiers":[
        {
            "category":"Insurance",
            "subcategory":"Life Insurance",
            "type":"Services"
        }
    ],
    "sg:phone":"+1 253 661 0400",
    "sg:postcode":"98042",
    "sg:province":"WA",
    "sg:tags":[
        "carrier"
    ],
    "wof:name":"Joel Roy & Assoc Inc",
    "wof:placetype":"venue"
},
  "geometry": {"coordinates":[-122.153942,47.379974],"type":"Point"}
}