{
  "type": "Feature",
  "properties": {
    "addr:full":"4361 Talbot Rd S Ste 112 Renton WA 98055",
    "addr:housenumber":"4361",
    "addr:postcode":"98055",
    "addr:street":"Talbot Rd S Ste 112",
    "iso:country":"US",
    "sg:address":"4361 Talbot Rd S Ste 112",
    "sg:city":"Renton",
    "sg:classifiers":[
        {
            "category":"Health Services",
            "subcategory":"Doctor",
            "type":"Services"
        },
        {
            "category":"Health Services",
            "subcategory":"Clinic",
            "type":"Services"
        }
    ],
    "sg:phone":"+1 425 255 5111",
    "sg:postcode":"98055",
    "sg:province":"WA",
    "sg:tags":[
        "physician",
        "family",
        "gynecology",
        "practice",
        "surgeons",
        "osteopathic",
        "obstetrics",
        "medicine",
        "surgeon"
    ],
    "wof:name":"Associated Valley Providers",
    "wof:placetype":"venue"
},
  "geometry": {"coordinates":[-122.213015,47.439683],"type":"Point"}
}