{
  "type": "Feature",
  "properties": {
    "addr:full":"143 Columbia St Sumas WA 98295",
    "addr:housenumber":"143",
    "addr:postcode":"98295",
    "addr:street":"Columbia St",
    "iso:country":"US",
    "sg:address":"143 Columbia St",
    "sg:city":"Sumas",
    "sg:classifiers":[
        {
            "category":"Government",
            "subcategory":"Fire Station",
            "type":"Public Place"
        }
    ],
    "sg:phone":"+1 360 599 2823",
    "sg:postcode":"98295",
    "sg:province":"WA",
    "sg:tags":[
        "department"
    ],
    "sg:website":"http://www.wcfd14.org",
    "wof:name":"Whatcom County Fire District 14",
    "wof:placetype":"venue"
},
  "geometry": {"coordinates":[-122.26408000000001,48.996345],"type":"Point"}
}