{
  "type": "Feature",
  "properties": {
    "addr:full":"8827 NE 138th St Kirkland WA 98034",
    "addr:housenumber":"8827",
    "addr:postcode":"98034",
    "addr:street":"Ne 138Th St",
    "iso:country":"US",
    "sg:address":"8827 NE 138th St",
    "sg:city":"Kirkland",
    "sg:classifiers":[
        {
            "category":"Building & Trades",
            "subcategory":"Construction",
            "type":"Services"
        }
    ],
    "sg:phone":"+1 425 825 8773",
    "sg:postcode":"98034",
    "sg:province":"WA",
    "sg:tags":[
        "residential"
    ],
    "wof:name":"Graham Drake Construction",
    "wof:placetype":"venue"
},
  "geometry": {"coordinates":[-122.22124599999999,47.724512],"type":"Point"}
}