{
  "type": "Feature",
  "properties": {
    "addr:full":"2110 3rd Ave W Seattle WA 98119",
    "addr:housenumber":"2110",
    "addr:postcode":"98119",
    "addr:street":"3Rd Ave W",
    "iso:country":"US",
    "sg:address":"2110 3rd Ave W",
    "sg:city":"Seattle",
    "sg:classifiers":[
        {
            "category":"Recreation",
            "type":"Entertainment"
        }
    ],
    "sg:phone":"+1 206 285 9653",
    "sg:postcode":"98119",
    "sg:province":"WA",
    "sg:tags":[
        "club",
        "membership"
    ],
    "wof:name":"Edelweis Ski Club Inc",
    "wof:placetype":"venue"
},
  "geometry": {"coordinates":[-122.360884,47.637335],"type":"Point"}
}