{
  "type": "Feature",
  "properties": {
    "addr:full":"1212 NE 65th St Seattle WA 98115",
    "addr:housenumber":"1212",
    "addr:postcode":"98115",
    "addr:street":"Ne 65Th St",
    "iso:country":"US",
    "sg:address":"1212 NE 65th St",
    "sg:city":"Seattle",
    "sg:classifiers":[
        {
            "category":"Real Estate",
            "subcategory":"Architect",
            "type":"Services"
        }
    ],
    "sg:phone":"+1 206 523 1618",
    "sg:postcode":"98115",
    "sg:province":"WA",
    "sg:tags":[
        "planning",
        "architectural"
    ],
    "wof:name":"Johnson Partnership the",
    "wof:placetype":"venue"
},
  "geometry": {"coordinates":[-122.31500200000001,47.675701],"type":"Point"}
}