{
  "type": "Feature",
  "properties": {
    "addr:full":"1420 E Marine View Dr Everett WA 98201",
    "addr:housenumber":"1420",
    "addr:postcode":"98201",
    "addr:street":"E Marine View Dr",
    "iso:country":"US",
    "sg:address":"1420 E Marine View Dr",
    "sg:city":"Everett",
    "sg:classifiers":[
        {
            "category":"Food & Beverages",
            "subcategory":"Fruits & Vegetables",
            "type":"Retail Goods"
        }
    ],
    "sg:phone":"+1 425 303 0153",
    "sg:postcode":"98201",
    "sg:province":"WA",
    "sg:tags":[
        "produce"
    ],
    "wof:name":"Triangle Fruit Market",
    "wof:placetype":"venue"
},
  "geometry": {"coordinates":[-122.189179,47.998626],"type":"Point"}
}