{
  "type": "Feature",
  "properties": {
    "addr:full":"12305 99th Ave NE Arlington WA 98223",
    "addr:housenumber":"12305",
    "addr:postcode":"98223",
    "addr:street":"99Th Ave Ne",
    "iso:country":"US",
    "sg:address":"12305 99th Ave NE",
    "sg:city":"Arlington",
    "sg:classifiers":[
        {
            "category":"Building & Trades",
            "subcategory":"Landscaping Services",
            "type":"Services"
        }
    ],
    "sg:phone":"+1 360 653 6949",
    "sg:postcode":"98223",
    "sg:province":"WA",
    "wof:name":"J R Landscaping Inc",
    "wof:placetype":"venue"
},
  "geometry": {"coordinates":[-122.097865,48.103795],"type":"Point"}
}