{
  "type": "Feature",
  "properties": {
    "iso:country":"US",
    "sg:address":"235 E Rowan Ave",
    "sg:city":"Spokane",
    "sg:classifiers":[
        {
            "category":"Health Services",
            "subcategory":"Doctor",
            "type":"Services"
        }
    ],
    "sg:phone":"+1 509 482 3565",
    "sg:postcode":"99207",
    "sg:province":"WA",
    "sg:tags":[
        "physician",
        "medical",
        "surgeon"
    ],
    "wof:name":"Norman J James MD PS",
    "wof:placetype":"venue"
},
  "geometry": {"coordinates":[-117.40724899999999,47.707978],"type":"Point"}
}