{
  "type": "Feature",
  "properties": {
    "addr:full":"115 Cleveland Ave SE Olympia WA 98501",
    "addr:housenumber":"115",
    "addr:postcode":"98501",
    "addr:street":"Cleveland Ave Se",
    "iso:country":"US",
    "sg:address":"115 Cleveland Ave SE",
    "sg:city":"Olympia",
    "sg:classifiers":[
        {
            "category":"Social Services",
            "type":"Services"
        }
    ],
    "sg:phone":"+1 360 789 6676",
    "sg:postcode":"98501",
    "sg:province":"WA",
    "sg:tags":[
        "youth",
        "organization",
        "center"
    ],
    "wof:name":"Greater Olympia Young Life",
    "wof:placetype":"venue"
},
  "geometry": {"coordinates":[-122.898634,47.014166],"type":"Point"}
}