{
  "type": "Feature",
  "properties": {
    "addr:full":"1119 Foxtrot Ln Richland WA 99352",
    "addr:housenumber":"1119",
    "addr:postcode":"99352",
    "addr:street":"Foxtrot Ln",
    "iso:country":"US",
    "sg:address":"1119 Foxtrot Ln",
    "sg:city":"Richland",
    "sg:classifiers":[
        {
            "category":"Restaurant",
            "type":"Food & Drink"
        }
    ],
    "sg:phone":"+1 509 627 2333",
    "sg:postcode":"99352",
    "sg:province":"WA",
    "wof:name":"Liu, Chung-King",
    "wof:placetype":"venue"
},
  "geometry": {"coordinates":[-119.31302599999999,46.250198],"type":"Point"}
}