{
  "type": "Feature",
  "properties": {
    "addr:full":"2939 Lombard Ave Everett WA 98201",
    "addr:housenumber":"2939",
    "addr:postcode":"98201",
    "addr:street":"Lombard Ave",
    "iso:country":"US",
    "sg:address":"2939 Lombard Ave",
    "sg:city":"Everett",
    "sg:classifiers":[
        {
            "category":"Retail",
            "subcategory":"Laundry & Dry Cleaning",
            "type":"Services"
        }
    ],
    "sg:phone":"+1 425 281 1994",
    "sg:postcode":"98201",
    "sg:province":"WA",
    "wof:name":"American Linen",
    "wof:placetype":"venue"
},
  "geometry": {"coordinates":[-122.202916,47.978454],"type":"Point"}
}