{
  "type": "Feature",
  "properties": {
    "addr:full":"445 SW 41st St Renton WA 98057",
    "addr:housenumber":"445",
    "addr:postcode":"98057",
    "addr:street":"Sw 41St St",
    "iso:country":"US",
    "sg:address":"445 SW 41st St",
    "sg:city":"Renton",
    "sg:classifiers":[
        {
            "category":"Insurance",
            "subcategory":"Health Insurance",
            "type":"Services"
        }
    ],
    "sg:phone":"+1 425 251 5446",
    "sg:postcode":"98057",
    "sg:province":"WA",
    "sg:tags":[
        "carrier"
    ],
    "wof:name":"Balboa Life & Casualty",
    "wof:placetype":"venue"
},
  "geometry": {"coordinates":[-122.222641,47.443779],"type":"Point"}
}