{
  "type": "Feature",
  "properties": {
    "iso:country":"US",
    "sg:address":"37 Dixon Rd",
    "sg:city":"Omak",
    "sg:classifiers":[
        {
            "category":"Farming",
            "subcategory":"Orchard",
            "type":"Manufacturing & Wholesale Goods"
        }
    ],
    "sg:phone":"+1 509 826 2232",
    "sg:postcode":"98841",
    "sg:province":"WA",
    "sg:tags":[
        "fruit",
        "tree",
        "crop"
    ],
    "wof:name":"M&W Orchards",
    "wof:placetype":"venue"
},
  "geometry": {"coordinates":[-119.552108,48.420643],"type":"Point"}
}