{
  "type": "Feature",
  "properties": {
    "addr:full":"520 Birchwood Ave Bellingham WA 98225",
    "addr:housenumber":"520",
    "addr:postcode":"98225",
    "addr:street":"Birchwood Ave",
    "iso:country":"US",
    "sg:address":"520 Birchwood Ave",
    "sg:city":"Bellingham",
    "sg:classifiers":[
        {
            "category":"Health Services",
            "subcategory":"Doctor",
            "type":"Services"
        }
    ],
    "sg:phone":"+1 360 671 6303",
    "sg:postcode":"98225",
    "sg:province":"WA",
    "wof:name":"Family Dentistry",
    "wof:placetype":"venue"
},
  "geometry": {"coordinates":[-122.480739,48.777048],"type":"Point"}
}