{
  "type": "Feature",
  "properties": {
    "addr:full":"10525 State Ave Marysville WA 98271",
    "addr:housenumber":"10525",
    "addr:postcode":"98271",
    "addr:street":"State Ave",
    "iso:country":"US",
    "sg:address":"10525 State Ave",
    "sg:city":"Marysville",
    "sg:classifiers":[
        {
            "category":"Personal",
            "subcategory":"Beauty Salon",
            "type":"Services"
        }
    ],
    "sg:phone":"+1 360 659 3223",
    "sg:postcode":"98271",
    "sg:province":"WA",
    "wof:name":"Positive Reflections",
    "wof:placetype":"venue"
},
  "geometry": {"coordinates":[-122.173497,48.090766],"type":"Point"}
}