{
  "type": "Feature",
  "properties": {
    "iso:country":"US",
    "sg:address":"9610 Kimmie St SW",
    "sg:city":"Olympia",
    "sg:classifiers":[
        {
            "category":"Travel",
            "subcategory":"Campground",
            "type":"Entertainment"
        }
    ],
    "sg:phone":"+1 360 943 8778",
    "sg:postcode":"98512",
    "sg:province":"WA",
    "wof:name":"Olympia Amrcn Hritg Campground",
    "wof:placetype":"venue"
},
  "geometry": {"coordinates":[-122.928995,46.950391],"type":"Point"}
}