{
  "type": "Feature",
  "properties": {
    "addr:full":"7603 149th Ave NE Redmond WA 98052",
    "addr:housenumber":"7603",
    "addr:postcode":"98052",
    "addr:street":"149Th Ave Ne",
    "iso:country":"US",
    "sg:address":"7603 149th Ave NE",
    "sg:city":"Redmond",
    "sg:classifiers":[
        {
            "category":"Professional",
            "subcategory":"Computer Services",
            "type":"Services"
        }
    ],
    "sg:phone":"+1 425 881 2674",
    "sg:postcode":"98052",
    "sg:province":"WA",
    "sg:tags":[
        "information",
        "recovery",
        "processing",
        "system",
        "equipment",
        "data",
        "retrieval"
    ],
    "wof:name":"Subscription Connection",
    "wof:placetype":"venue"
},
  "geometry": {"coordinates":[-122.141689,47.672251],"type":"Point"}
}