{
  "type": "Feature",
  "properties": {
    "addr:full":"147 C St Blaine WA 98230",
    "addr:housenumber":"147",
    "addr:postcode":"98230",
    "addr:street":"C St",
    "iso:country":"US",
    "sg:address":"147 C St",
    "sg:city":"Blaine",
    "sg:classifiers":[
        {
            "category":"Building & Trades",
            "subcategory":"Construction",
            "type":"Services"
        }
    ],
    "sg:phone":"+1 360 332 3921",
    "sg:postcode":"98230",
    "sg:province":"WA",
    "sg:tags":[
        "boring",
        "drilling",
        "contractor"
    ],
    "wof:name":"Foundex Pacific Inc",
    "wof:placetype":"venue"
},
  "geometry": {"coordinates":[-122.751881,48.999067],"type":"Point"}
}