{
  "type": "Feature",
  "properties": {
    "addr:full":"560 Naches Ave SW Renton WA 98057",
    "addr:housenumber":"560",
    "addr:postcode":"98057",
    "addr:street":"Naches Ave Sw",
    "iso:country":"US",
    "sg:address":"560 Naches Ave SW",
    "sg:city":"Renton",
    "sg:classifiers":[
        {
            "category":"Manufacturing",
            "subcategory":"Retail Goods",
            "type":"Manufacturing & Wholesale Goods"
        }
    ],
    "sg:phone":"+1 425 277 2503",
    "sg:postcode":"98057",
    "sg:province":"WA",
    "sg:tags":[
        "hardware",
        "mfg"
    ],
    "wof:name":"YKK USA Inc",
    "wof:placetype":"venue"
},
  "geometry": {"coordinates":[-122.232512,47.473772],"type":"Point"}
}