{
  "type": "Feature",
  "properties": {
    "addr:full":"4981 E 26th Dr Bellingham WA 98226",
    "addr:housenumber":"4981",
    "addr:postcode":"98226",
    "addr:street":"E 26Th Dr",
    "iso:country":"US",
    "sg:address":"4981 E 26th Dr",
    "sg:city":"Bellingham",
    "sg:classifiers":[
        {
            "category":"Retail",
            "subcategory":"Repair Shop",
            "type":"Services"
        }
    ],
    "sg:phone":"+1 360 592 1106",
    "sg:postcode":"98226",
    "sg:province":"WA",
    "wof:name":"Winter Creek Piano Works",
    "wof:placetype":"venue"
},
  "geometry": {"coordinates":[-122.346019,48.819166],"type":"Point"}
}