{
  "type": "Feature",
  "properties": {
    "addr:full":"503 Lilly Rd SE Olympia WA 98501",
    "addr:housenumber":"503",
    "addr:postcode":"olympia;98501",
    "addr:street":"Lilly Rd Se",
    "iso:country":"US",
    "sg:address":"503 Lilly Rd SE",
    "sg:city":"Olympia",
    "sg:classifiers":[
        {
            "category":"Building & Trades",
            "subcategory":"Construction",
            "type":"Services"
        }
    ],
    "sg:phone":"+1 360 459 9305",
    "sg:postcode":"98501",
    "sg:province":"WA",
    "sg:tags":[
        "carpentry",
        "finish",
        "remodeling",
        "general"
    ],
    "wof:name":"Thompsons Finish Carpentry",
    "wof:placetype":"venue"
},
  "geometry": {"coordinates":[-122.844398,47.044411],"type":"Point"}
}