{
  "type": "Feature",
  "properties": {
    "addr:full":"1506 Franklin Ave E Seattle WA 98102",
    "addr:housenumber":"1506",
    "addr:postcode":"98102",
    "addr:street":"Franklin Ave E",
    "iso:country":"US",
    "sg:address":"1506 Franklin Ave E",
    "sg:city":"Seattle",
    "sg:classifiers":[
        {
            "category":"Professional",
            "type":"Services"
        }
    ],
    "sg:phone":"+1 206 328 4758",
    "sg:postcode":"98102",
    "sg:province":"WA",
    "sg:tags":[
        "gallery"
    ],
    "wof:name":"Hengst Studio",
    "wof:placetype":"venue"
},
  "geometry": {"coordinates":[-122.324434,47.633768],"type":"Point"}
}