{
  "type": "Feature",
  "properties": {
    "addr:full":"8802 Bridgeport Way SW Lakewood WA 98499",
    "addr:housenumber":"8802",
    "addr:postcode":"98499",
    "addr:street":"Bridgeport Way Sw",
    "iso:country":"US",
    "sg:address":"8802 Bridgeport Way SW",
    "sg:city":"Lakewood",
    "sg:classifiers":[
        {
            "category":"Organizations",
            "subcategory":"Religious Organization",
            "type":"Services"
        }
    ],
    "sg:phone":"+1 253 584 2084",
    "sg:postcode":"98499",
    "sg:province":"WA",
    "sg:tags":[
        "church"
    ],
    "wof:name":"Refreshing Springs Church",
    "wof:placetype":"venue"
},
  "geometry": {"coordinates":[-122.51816700000001,47.176506],"type":"Point"}
}