{
  "type": "Feature",
  "properties": {
    "addr:full":"29416 18th Ave S Federal Way WA 98003",
    "addr:housenumber":"29416",
    "addr:postcode":"98003",
    "addr:street":"18Th Ave S Federal Way",
    "iso:country":"US",
    "sg:address":"29416 18th Ave S",
    "sg:city":"Federal Way",
    "sg:classifiers":[
        {
            "category":"Restaurant",
            "type":"Food & Drink"
        }
    ],
    "sg:phone":"+1 253 529 2881",
    "sg:postcode":"98003",
    "sg:province":"WA",
    "sg:tags":[
        "eating"
    ],
    "wof:name":"Northwest Bath & Kitchen",
    "wof:placetype":"venue"
},
  "geometry": {"coordinates":[-122.31058400000001,47.337905],"type":"Point"}
}