{
  "type": "Feature",
  "properties": {
    "addr:full":"11661 Fay Rd NE Carnation WA 98014",
    "addr:housenumber":"11661",
    "addr:postcode":"98014",
    "addr:street":"Fay Rd Ne",
    "iso:country":"US",
    "sg:address":"11661 Fay Rd NE",
    "sg:city":"Carnation",
    "sg:classifiers":[
        {
            "category":"Building & Trades",
            "subcategory":"Landscaping Services",
            "type":"Services"
        }
    ],
    "sg:phone":"+1 425 788 4915",
    "sg:postcode":"98014",
    "sg:province":"WA",
    "sg:tags":[
        "landscape",
        "contractor"
    ],
    "wof:name":"Coast Landscaping",
    "wof:placetype":"venue"
},
  "geometry": {"coordinates":[-121.921851,47.701702],"type":"Point"}
}