{
  "type": "Feature",
  "properties": {
    "addr:full":"219 James St Seattle WA 98104",
    "addr:housenumber":"219",
    "addr:postcode":"98104",
    "addr:street":"James St",
    "iso:country":"US",
    "sg:address":"219 James St",
    "sg:city":"Seattle",
    "sg:classifiers":[
        {
            "category":"Personal",
            "subcategory":"Beauty Salon",
            "type":"Services"
        }
    ],
    "sg:phone":"+1 206 381 3699",
    "sg:postcode":"98104",
    "sg:province":"WA",
    "sg:tags":[
        "hair"
    ],
    "sg:website":"www.foxycut.com",
    "wof:name":"FoxyCut Salon",
    "wof:placetype":"venue"
},
  "geometry": {"coordinates":[-122.332302,47.602411],"type":"Point"}
}