{
  "type": "Feature",
  "properties": {
    "iso:country":"US",
    "sg:address":"5611 195th Ave E",
    "sg:city":"Sumner",
    "sg:classifiers":[
        {
            "category":"Building & Trades",
            "subcategory":"Construction",
            "type":"Services"
        }
    ],
    "sg:phone":"+1 253 862 2196",
    "sg:postcode":"98391",
    "sg:province":"WA",
    "sg:tags":[
        "heavy"
    ],
    "wof:name":"D&A Construction",
    "wof:placetype":"venue"
},
  "geometry": {"coordinates":[-122.166974,47.203233],"type":"Point"}
}