{
  "type": "Feature",
  "properties": {
    "addr:full":"16541 Redmond Way, #414-C Redmond WA 98052",
    "addr:housenumber":"16541",
    "addr:postcode":"98052",
    "addr:street":"Redmond Way # 414-C",
    "iso:country":"US",
    "sg:address":"16541 Redmond Way, #414-C",
    "sg:city":"Redmond",
    "sg:classifiers":[
        {
            "category":"Building & Trades",
            "subcategory":"Landscaping Services",
            "type":"Services"
        }
    ],
    "sg:phone":"+1 425 605 4640",
    "sg:postcode":"98052",
    "sg:province":"WA",
    "sg:tags":[
        "tree"
    ],
    "sg:website":"http://agtree.com",
    "wof:name":"AG Tree Service",
    "wof:placetype":"venue"
},
  "geometry": {"coordinates":[-122.11979599999999,47.673421],"type":"Point"}
}