{
  "type": "Feature",
  "properties": {
    "addr:full":"6505 233rd Pl SE Woodinville WA 98072",
    "addr:housenumber":"6505",
    "addr:postcode":"98072",
    "addr:street":"233Rd Pl Se",
    "iso:country":"US",
    "sg:address":"6505 233rd Pl SE",
    "sg:city":"Woodinville",
    "sg:classifiers":[
        {
            "category":"Retail",
            "subcategory":"Auto Repair",
            "type":"Services"
        }
    ],
    "sg:phone":"+1 425 402 1634",
    "sg:postcode":"98072",
    "sg:province":"WA",
    "sg:tags":[
        "repairing",
        "automobile",
        "general"
    ],
    "wof:name":"Euro and Exotic Garage Inc",
    "wof:placetype":"venue"
},
  "geometry": {"coordinates":[-122.143424,47.785593],"type":"Point"}
}