{
  "type": "Feature",
  "properties": {
    "addr:full":"28608 SE 224th St Maple Valley WA 98038",
    "addr:postcode":"28608;98038",
    "addr:street":"Se 224Th St",
    "iso:country":"US",
    "sg:address":"28608 SE 224th St",
    "sg:city":"Maple Valley",
    "sg:classifiers":[
        {
            "category":"Building & Trades",
            "subcategory":"Landscaping Services",
            "type":"Services"
        }
    ],
    "sg:phone":"+1 425 432 4678",
    "sg:postcode":"98038",
    "sg:province":"WA",
    "sg:tags":[
        "motion",
        "picture",
        "distribution"
    ],
    "wof:name":"Owens Outdoor Services",
    "wof:placetype":"venue"
},
  "geometry": {"coordinates":[-121.960403,47.401479],"type":"Point"}
}