{
  "type": "Feature",
  "properties": {
    "iso:country":"US",
    "sg:address":"661 Pays Rd",
    "sg:city":"Cle Elum",
    "sg:classifiers":[
        {
            "category":"Building & Trades",
            "subcategory":"Landscaping Services",
            "type":"Services"
        }
    ],
    "sg:phone":"+1 509 674 7692",
    "sg:postcode":"98922",
    "sg:province":"WA",
    "wof:name":"Mikes Brush Cutting Servi",
    "wof:placetype":"venue"
},
  "geometry": {"coordinates":[-120.927049,47.175251],"type":"Point"}
}