{
  "type": "Feature",
  "properties": {
    "addr:full":"4024 22nd Ave W Seattle WA 98199",
    "addr:housenumber":"4024",
    "addr:postcode":"98199",
    "addr:street":"22Nd Ave W",
    "iso:country":"US",
    "sg:address":"4024 22nd Ave W",
    "sg:city":"Seattle",
    "sg:classifiers":[
        {
            "category":"Building & Trades",
            "subcategory":"Construction",
            "type":"Services"
        }
    ],
    "sg:phone":"+1 206 352 8800",
    "sg:postcode":"98199",
    "sg:province":"WA",
    "sg:tags":[
        "testing",
        "hydraulic",
        "maintenance"
    ],
    "wof:name":"Hydraulic Testing & Maint",
    "wof:placetype":"venue"
},
  "geometry": {"coordinates":[-122.384614,47.656229],"type":"Point"}
}