{
  "type": "Feature",
  "properties": {
    "addr:full":"7800 NE 99th St Vancouver WA 98662",
    "addr:housenumber":"7800",
    "addr:postcode":"98662",
    "addr:street":"Ne 99Th St",
    "iso:country":"US",
    "sg:address":"7800 NE 99th St",
    "sg:city":"Vancouver",
    "sg:classifiers":[
        {
            "category":"Building & Trades",
            "subcategory":"Landscaping Services",
            "type":"Services"
        }
    ],
    "sg:phone":"+1 360 573 3909",
    "sg:postcode":"98662",
    "sg:province":"WA",
    "sg:tags":[
        "landscape",
        "contractor"
    ],
    "sg:website":"www.dallaslandscapesinc.com",
    "wof:name":"Dallas Landscapes Inc",
    "wof:placetype":"venue"
},
  "geometry": {"coordinates":[-122.59686000000001,45.69326],"type":"Point"}
}