{
  "type": "Feature",
  "properties": {
    "addr:full":"4700 NE St Johns Rd Vancouver WA 98661",
    "addr:housenumber":"4700",
    "addr:postcode":"98661",
    "addr:street":"Ne St Johns Rd",
    "iso:country":"US",
    "sg:address":"4700 NE St Johns Rd",
    "sg:city":"Vancouver",
    "sg:classifiers":[
        {
            "category":"Retail",
            "subcategory":"Funeral Services",
            "type":"Services"
        }
    ],
    "sg:phone":"+1 360 693 3649",
    "sg:postcode":"98661",
    "sg:province":"WA",
    "sg:tags":[
        "crematory",
        "mortuary"
    ],
    "sg:website":"http://www.stricklinsnivelymortuary.com",
    "wof:name":"Evergreen Staples Funeral Chapel",
    "wof:placetype":"venue"
},
  "geometry": {"coordinates":[-122.636009,45.65617],"type":"Point"}
}