{
  "type": "Feature",
  "properties": {
    "addr:full":"12003 NE 12th St Bellevue WA 98005",
    "addr:housenumber":"12003",
    "addr:postcode":"98005",
    "addr:street":"Ne 12Th St",
    "iso:country":"US",
    "sg:address":"12003 NE 12th St",
    "sg:city":"Bellevue",
    "sg:classifiers":[
        {
            "category":"Wholesale",
            "subcategory":"Sporting Goods",
            "type":"Manufacturing & Wholesale Goods"
        }
    ],
    "sg:phone":"+1 425 454 6766",
    "sg:postcode":"98005",
    "sg:province":"WA",
    "sg:tags":[
        "equipment",
        "golf",
        "supplies-wholesale",
        "manufacturer"
    ],
    "wof:name":"Studio Fore Golf",
    "wof:placetype":"venue"
},
  "geometry": {"coordinates":[-122.179405,47.620608],"type":"Point"}
}