{
  "type": "Feature",
  "properties": {
    "addr:full":"416 W 3rd Ave Moses Lake WA 98837",
    "addr:housenumber":"416",
    "addr:postcode":"98837",
    "addr:street":"W 3Rd Ave",
    "iso:country":"US",
    "sg:address":"416 W 3rd Ave",
    "sg:city":"Moses Lake",
    "sg:classifiers":[
        {
            "category":"Personal",
            "subcategory":"Beauty Salon",
            "type":"Services"
        }
    ],
    "sg:phone":"+1 509 765 2245",
    "sg:postcode":"98837",
    "sg:province":"WA",
    "wof:name":"Brand New Day Salon & Beauty",
    "wof:placetype":"venue"
},
  "geometry": {"coordinates":[-119.281959,47.128285],"type":"Point"}
}