{
  "type": "Feature",
  "properties": {
    "iso:country":"US",
    "sg:address":"1117 S Woodlawn St",
    "sg:city":"Tacoma",
    "sg:classifiers":[
        {
            "category":"Building & Trades",
            "subcategory":"Cleaning & Sanitation",
            "type":"Services"
        }
    ],
    "sg:phone":"+1 253 460 2645",
    "sg:postcode":"98465",
    "sg:province":"WA",
    "sg:tags":[
        "janitor"
    ],
    "wof:name":"D Jack Janitorial Svc",
    "wof:placetype":"venue"
},
  "geometry": {"coordinates":[-122.51437,47.25024],"type":"Point"}
}