{
  "type": "Feature",
  "properties": {
    "addr:full":"5520 Sidney Rd SW Port Orchard WA 98367",
    "addr:housenumber":"5520",
    "addr:postcode":"98367",
    "addr:street":"Sidney Rd Sw Port Orchard",
    "iso:country":"US",
    "sg:address":"5520 Sidney Rd SW",
    "sg:city":"Port Orchard",
    "sg:classifiers":[
        {
            "category":"Coffee & Tea",
            "type":"Food & Drink"
        }
    ],
    "sg:menulink":"http://www.allmenus.com/wa/port-orchard/117863-starbucks-coffee/menu/",
    "sg:phone":"+1 360 692 8088",
    "sg:postcode":"98367",
    "sg:province":"WA",
    "sg:tags":[
        "american"
    ],
    "wof:name":"Starbucks Coffee",
    "wof:placetype":"venue"
},
  "geometry": {"coordinates":[-122.653778,47.497336],"type":"Point"}
}