{
  "type": "Feature",
  "properties": {
    "addr:full":"2027 NE Northgate Way Seattle WA 98125",
    "addr:housenumber":"2027",
    "addr:postcode":"98125",
    "addr:street":"Ne Northgate Way",
    "iso:country":"US",
    "sg:address":"2027 NE Northgate Way",
    "sg:city":"Seattle",
    "sg:classifiers":[
        {
            "category":"Professional",
            "subcategory":"Management & Consulting",
            "type":"Services"
        },
        {
            "category":"Banks & Credit Unions",
            "subcategory":"Financial Services",
            "type":"Services"
        }
    ],
    "sg:phone":"+1 206 363 9197",
    "sg:postcode":"98125",
    "sg:province":"WA",
    "sg:tags":[
        "consultant",
        "financing",
        "planning"
    ],
    "wof:name":"Kern A Kenrud",
    "wof:placetype":"venue"
},
  "geometry": {"coordinates":[-122.305814,47.708471],"type":"Point"}
}