{
  "type": "Feature",
  "properties": {
    "addr:full":"8825 34th Ave NE Tulalip WA 98271",
    "addr:housenumber":"8825",
    "addr:postcode":"98271",
    "addr:street":"34Th Ave Ne",
    "iso:country":"US",
    "sg:address":"8825 34th Ave NE",
    "sg:city":"Tulalip",
    "sg:classifiers":[
        {
            "category":"Fast Food",
            "type":"Food & Drink"
        },
        {
            "category":"Restaurant",
            "type":"Food & Drink"
        },
        {
            "category":"Food & Beverages",
            "subcategory":"Groceries & Convenience Stores",
            "type":"Retail Goods"
        }
    ],
    "sg:phone":"+1 360 716 2950",
    "sg:postcode":"98271",
    "sg:province":"WA",
    "sg:tags":[
        "shop",
        "american",
        "sandwich",
        "take"
    ],
    "sg:website":"http://www.portofsubs.com/",
    "wof:name":"Port of Subs",
    "wof:placetype":"venue"
},
  "geometry": {"coordinates":[-122.187782,48.076809],"type":"Point"}
}