{
  "type": "Feature",
  "properties": {
    "addr:full":"6141 115th Pl SE Bellevue WA 98006",
    "addr:housenumber":"6141",
    "addr:postcode":"98006",
    "addr:street":"115Th Pl Se",
    "iso:country":"US",
    "sg:address":"6141 115th Pl SE",
    "sg:city":"Bellevue",
    "sg:classifiers":[
        {
            "category":"Real Estate",
            "subcategory":"Real Estate Operator",
            "type":"Services"
        }
    ],
    "sg:phone":"+1 425 747 3158",
    "sg:postcode":"98006",
    "sg:province":"WA",
    "sg:tags":[
        "building",
        "nonresidential"
    ],
    "wof:name":"Shepherd Properties LLC",
    "wof:placetype":"venue"
},
  "geometry": {"coordinates":[-122.18609600000001,47.548665],"type":"Point"}
}