{
  "type": "Feature",
  "properties": {
    "addr:full":"4604 San Juan Ave Anacortes WA 98221",
    "addr:housenumber":"4604",
    "addr:postcode":"98221",
    "addr:street":"San Juan Ave",
    "iso:country":"US",
    "sg:address":"4604 San Juan Ave",
    "sg:city":"Anacortes",
    "sg:classifiers":[
        {
            "category":"Social Services",
            "type":"Services"
        }
    ],
    "sg:phone":"+1 360 293 2853",
    "sg:postcode":"98221",
    "sg:province":"WA",
    "wof:name":"Petrinovich Toni PHD Rmt Ch",
    "wof:placetype":"venue"
},
  "geometry": {"coordinates":[-122.66655799999999,48.497525],"type":"Point"}
}