{
  "type": "Feature",
  "properties": {
    "addr:full":"710 W 1st Ave Toppenish WA 98948",
    "addr:housenumber":"710",
    "addr:postcode":"98948",
    "addr:street":"W 1St Ave",
    "iso:country":"US",
    "sg:address":"710 W 1st Ave",
    "sg:city":"Toppenish",
    "sg:classifiers":[
        {
            "category":"Retail",
            "subcategory":"Auto Rental",
            "type":"Services"
        }
    ],
    "sg:phone":"+1 509 865 2703",
    "sg:postcode":"98948",
    "sg:province":"WA",
    "sg:tags":[
        "renting",
        "truck",
        "leasing"
    ],
    "wof:name":"U-Haul Co",
    "wof:placetype":"venue"
},
  "geometry": {"coordinates":[-120.320103,46.374987],"type":"Point"}
}