{
  "type": "Feature",
  "properties": {
    "addr:full":"1807 Howard Rd Ellensburg WA 98926",
    "addr:housenumber":"1807",
    "addr:postcode":"98926",
    "addr:street":"Howard Rd",
    "iso:country":"US",
    "sg:address":"1807 Howard Rd",
    "sg:city":"Ellensburg",
    "sg:classifiers":[
        {
            "category":"Building & Trades",
            "subcategory":"Construction",
            "type":"Services"
        }
    ],
    "sg:phone":"+1 509 925 5400",
    "sg:postcode":"98926",
    "sg:province":"WA",
    "sg:tags":[
        "residential"
    ],
    "wof:name":"Kyllo Construction Co Inc",
    "wof:placetype":"venue"
},
  "geometry": {"coordinates":[-120.624455,47.09005],"type":"Point"}
}