{
  "type": "Feature",
  "properties": {
    "iso:country":"US",
    "sg:address":"1495 E Village Ln",
    "sg:city":"Bellingham",
    "sg:classifiers":[
        {
            "category":"Shopping",
            "subcategory":"Computers & Home Electronics",
            "type":"Retail Goods"
        }
    ],
    "sg:phone":"+1 360 715 1329",
    "sg:postcode":"98226",
    "sg:province":"WA",
    "sg:tags":[
        "equipment",
        "dealer"
    ],
    "wof:name":"Great Lakes Computers",
    "wof:placetype":"venue"
},
  "geometry": {"coordinates":[-122.49937300000001,48.794124],"type":"Point"}
}