{
  "type": "Feature",
  "properties": {
    "addr:full":"1161 Beffa Rd Tieton WA 98947",
    "addr:housenumber":"1161",
    "addr:postcode":"98947",
    "addr:street":"Beffa Rd",
    "iso:country":"US",
    "sg:address":"1161 Beffa Rd",
    "sg:city":"Tieton",
    "sg:classifiers":[
        {
            "category":"Building & Trades",
            "subcategory":"Construction",
            "type":"Services"
        }
    ],
    "sg:phone":"+1 509 673 3077",
    "sg:postcode":"98947",
    "sg:province":"WA",
    "sg:tags":[
        "steel",
        "erection",
        "structural"
    ],
    "wof:name":"Whipline Steel Erectors",
    "wof:placetype":"venue"
},
  "geometry": {"coordinates":[-120.742105,46.723503],"type":"Point"}
}