{
  "type": "Feature",
  "properties": {
    "addr:full":"13320 SE McGillivray Blvd Vancouver WA 98683",
    "addr:postcode":"13320;98683",
    "addr:street":"Se Mcgillivray Blvd",
    "iso:country":"US",
    "sg:address":"13320 SE McGillivray Blvd",
    "sg:city":"Vancouver",
    "sg:classifiers":[
        {
            "category":"Freight",
            "type":"Transportation"
        }
    ],
    "sg:phone":"+1 360 260 2523",
    "sg:postcode":"98683",
    "sg:province":"WA",
    "sg:tags":[
        "arrangement"
    ],
    "wof:name":"Pro Pack & Ship",
    "wof:placetype":"venue"
},
  "geometry": {"coordinates":[-122.53387600000001,45.609904],"type":"Point"}
}