{
  "type": "Feature",
  "properties": {
    "addr:full":"5911 NE 88th St Vancouver WA 98665",
    "addr:housenumber":"5911",
    "addr:postcode":"98665",
    "addr:street":"Ne 88Th St",
    "iso:country":"US",
    "sg:address":"5911 NE 88th St",
    "sg:city":"Vancouver",
    "sg:classifiers":[
        {
            "category":"Wholesale",
            "subcategory":"Electrical",
            "type":"Manufacturing & Wholesale Goods"
        }
    ],
    "sg:phone":"+1 360 573 8220",
    "sg:postcode":"98665",
    "sg:province":"WA",
    "sg:tags":[
        "equipment",
        "electric",
        "supply"
    ],
    "wof:name":"EOFF Electric Co",
    "wof:placetype":"venue"
},
  "geometry": {"coordinates":[-122.606115,45.68596],"type":"Point"}
}