{
  "type": "Feature",
  "properties": {
    "addr:full":"341 E Pickering Rd Shelton WA 98584",
    "addr:housenumber":"341",
    "addr:postcode":"98584",
    "addr:street":"E Pickering Rd",
    "iso:country":"US",
    "sg:address":"341 E Pickering Rd",
    "sg:city":"Shelton",
    "sg:classifiers":[
        {
            "category":"Freight",
            "type":"Transportation"
        }
    ],
    "sg:phone":"+1 360 427 6278",
    "sg:postcode":"98584",
    "sg:province":"WA",
    "sg:tags":[
        "general"
    ],
    "wof:name":"Pickering Storage",
    "wof:placetype":"venue"
},
  "geometry": {"coordinates":[-122.96625,47.276664],"type":"Point"}
}