{
  "type": "Feature",
  "properties": {
    "addr:full":"9911 129th Pl NE Kirkland WA 98033",
    "addr:housenumber":"9911",
    "addr:postcode":"98033",
    "addr:street":"129Th Pl Ne",
    "iso:country":"US",
    "sg:address":"9911 129th Pl NE",
    "sg:city":"Kirkland",
    "sg:classifiers":[
        {
            "category":"Professional",
            "type":"Services"
        }
    ],
    "sg:phone":"+1 425 822 3935",
    "sg:postcode":"98033",
    "sg:province":"WA",
    "wof:name":"Ta Kang MA",
    "wof:placetype":"venue"
},
  "geometry": {"coordinates":[-122.168869,47.689065],"type":"Point"}
}