{
  "type": "Feature",
  "properties": {
    "addr:full":"107 W Stewart Ave Puyallup WA 98371",
    "addr:housenumber":"107",
    "addr:postcode":"98371",
    "addr:street":"W Stewart Ave",
    "iso:country":"US",
    "sg:address":"107 W Stewart Ave",
    "sg:city":"Puyallup",
    "sg:classifiers":[
        {
            "category":"Personal",
            "subcategory":"Beauty Salon",
            "type":"Services"
        }
    ],
    "sg:phone":"+1 253 770 6000",
    "sg:postcode":"98371",
    "sg:province":"WA",
    "sg:tags":[
        "shop"
    ],
    "wof:name":"Face It Inc",
    "wof:placetype":"venue"
},
  "geometry": {"coordinates":[-122.295117,47.193157],"type":"Point"}
}