{
  "type": "Feature",
  "properties": {
    "addr:full":"2217 73rd St SE Ste B Everett WA 98203",
    "addr:housenumber":"2217",
    "addr:postcode":"98203",
    "addr:street":"73Rd St Se Ste B",
    "iso:country":"US",
    "sg:address":"2217 73rd St SE Ste B",
    "sg:city":"Everett",
    "sg:classifiers":[
        {
            "category":"Arts & Performance",
            "subcategory":"Music",
            "type":"Entertainment"
        }
    ],
    "sg:phone":"+1 425 353 6196",
    "sg:postcode":"98203",
    "sg:province":"WA",
    "sg:tags":[
        "jockey",
        "disc"
    ],
    "wof:name":"Donny Does Music",
    "wof:placetype":"venue"
},
  "geometry": {"coordinates":[-122.20290799999999,47.932241],"type":"Point"}
}