{
  "type": "Feature",
  "properties": {
    "iso:country":"US",
    "sg:address":"80 Nichols St",
    "sg:city":"Friday Harbor",
    "sg:classifiers":[
        {
            "category":"Building & Trades",
            "subcategory":"Construction",
            "type":"Services"
        }
    ],
    "sg:phone":"+1 360 378 6725",
    "sg:postcode":"98250",
    "sg:province":"WA",
    "sg:tags":[
        "general",
        "contractor"
    ],
    "wof:name":"Mancuso Design & Construction",
    "wof:placetype":"venue"
},
  "geometry": {"coordinates":[-123.01598,48.533511],"type":"Point"}
}