{
  "type": "Feature",
  "properties": {
    "addr:full":"3540 Factoria Blvd SE Bellevue WA 98006",
    "addr:housenumber":"3540",
    "addr:postcode":"98006",
    "addr:street":"Factoria Blvd Se",
    "iso:country":"US",
    "sg:address":"3540 Factoria Blvd SE",
    "sg:city":"Bellevue",
    "sg:classifiers":[
        {
            "category":"Professional",
            "type":"Services"
        }
    ],
    "sg:phone":"+1 425 643 2112",
    "sg:postcode":"98006",
    "sg:province":"WA",
    "wof:name":"Micro Options",
    "wof:placetype":"venue"
},
  "geometry": {"coordinates":[-122.16925500000001,47.578547],"type":"Point"}
}