{
  "type": "Feature",
  "properties": {
    "addr:full":"18981 State Highway 305 NE Poulsbo WA 98370",
    "addr:housenumber":"18981",
    "addr:postcode":"98370",
    "addr:street":"State Highway 305 Ne",
    "iso:country":"US",
    "sg:address":"18981 State Highway 305 NE",
    "sg:city":"Poulsbo",
    "sg:classifiers":[
        {
            "category":"Retail",
            "subcategory":"Veterinary Services",
            "type":"Services"
        }
    ],
    "sg:phone":"+1 360 779 3414",
    "sg:postcode":"98370",
    "sg:province":"WA",
    "sg:tags":[
        "clinic",
        "hospital",
        "veterinarian",
        "specialty"
    ],
    "wof:name":"Jeffrey Harrison Dvm",
    "wof:placetype":"venue"
},
  "geometry": {"coordinates":[-122.637377,47.735508],"type":"Point"}
}