{
  "type": "Feature",
  "properties": {
    "iso:country":"US",
    "sg:address":"19510 144th Ave NE",
    "sg:city":"Woodinville",
    "sg:classifiers":[
        {
            "category":"Building & Trades",
            "subcategory":"Construction",
            "type":"Services"
        }
    ],
    "sg:phone":"+1 425 485 0726",
    "sg:postcode":"98072",
    "sg:province":"WA",
    "sg:tags":[
        "floor",
        "laying",
        "contractor"
    ],
    "wof:name":"Washington Floor & Tile Co",
    "wof:placetype":"venue"
},
  "geometry": {"coordinates":[-122.14769200000001,47.769047],"type":"Point"}
}