{
  "type": "Feature",
  "properties": {
    "addr:full":"11890 US Hwy 12 Randle WA 98377",
    "addr:housenumber":"11890",
    "addr:postcode":"98377",
    "addr:street":"Us Hwy 12",
    "iso:country":"US",
    "sg:address":"11890 US Hwy 12",
    "sg:city":"Randle",
    "sg:classifiers":[
        {
            "category":"Travel",
            "subcategory":"Hotels & Motels",
            "type":"Entertainment"
        }
    ],
    "sg:phone":"+1 360 494 6766",
    "sg:postcode":"98377",
    "sg:province":"WA",
    "wof:name":"Woodland Motel",
    "wof:placetype":"venue"
},
  "geometry": {"coordinates":[-121.743233,46.547806],"type":"Point"}
}