{
  "type": "Feature",
  "properties": {
    "addr:full":"220 8th St SE Auburn WA 98002",
    "addr:housenumber":"220",
    "addr:postcode":"98002",
    "addr:street":"8Th St Se",
    "iso:country":"US",
    "sg:address":"220 8th St SE",
    "sg:city":"Auburn",
    "sg:classifiers":[
        {
            "category":"Taxi",
            "type":"Transportation"
        }
    ],
    "sg:phone":"+1 253 569 5729",
    "sg:postcode":"98002",
    "sg:province":"WA",
    "sg:tags":[
        "taxicab"
    ],
    "wof:name":"Cuddy's Taxi Svc",
    "wof:placetype":"venue"
},
  "geometry": {"coordinates":[-122.225193,47.300342],"type":"Point"}
}