{
  "type": "Feature",
  "properties": {
    "addr:full":"1400 NW 56th Street Seattle WA 98107",
    "addr:housenumber":"1400",
    "addr:postcode":"98107",
    "addr:street":"Nw 56Th Street",
    "iso:country":"US",
    "sg:address":"1400 NW 56th Street",
    "sg:city":"Seattle",
    "sg:classifiers":[
        {
            "category":"Food & Beverages",
            "subcategory":"Liquor & Beverages",
            "type":"Retail Goods"
        },
        {
            "category":"Food & Beverages",
            "subcategory":"Groceries & Convenience Stores",
            "type":"Retail Goods"
        }
    ],
    "sg:phone":"+1 206 783 7922",
    "sg:postcode":"98107",
    "sg:province":"WA",
    "sg:tags":[
        "beer",
        "spirit",
        "wine"
    ],
    "sg:website":"www.townandcountrymarkets.com/ba...",
    "wof:name":"Ballard Town & Country Market",
    "wof:placetype":"venue"
},
  "geometry": {"coordinates":[-122.37400100000001,47.669601],"type":"Point"}
}