{
  "type": "Feature",
  "properties": {
    "addr:full":"7214 Woodlawn Ave NE Seattle WA 98115",
    "addr:housenumber":"7214",
    "addr:postcode":"98115",
    "addr:street":"Woodlawn Ave Ne",
    "iso:country":"US",
    "sg:address":"7214 Woodlawn Ave NE",
    "sg:city":"Seattle",
    "sg:classifiers":[
        {
            "category":"Retail",
            "subcategory":"Laundry & Dry Cleaning",
            "type":"Services"
        }
    ],
    "sg:phone":"+1 206 525 9886",
    "sg:postcode":"98115",
    "sg:province":"WA",
    "sg:tags":[
        "garment",
        "agent"
    ],
    "wof:name":"Greenlake Cleaners",
    "wof:placetype":"venue"
},
  "geometry": {"coordinates":[-122.32503800000001,47.681111],"type":"Point"}
}