{
  "type": "Feature",
  "properties": {
    "addr:full":"11757 Lakeside Avenue NE Seattle WA 98125",
    "addr:housenumber":"11757",
    "addr:postcode":"98125",
    "addr:street":"Lakeside Avenue Ne",
    "iso:country":"US",
    "sg:address":"11757 Lakeside Avenue NE",
    "sg:city":"Seattle",
    "sg:classifiers":[
        {
            "category":"Building & Trades",
            "subcategory":"Construction",
            "type":"Services"
        }
    ],
    "sg:phone":"+1 206 365 0319",
    "sg:postcode":"98125",
    "sg:province":"WA",
    "sg:tags":[
        "contractor"
    ],
    "wof:name":"Berger Built",
    "wof:placetype":"venue"
},
  "geometry": {"coordinates":[-122.280509,47.715816],"type":"Point"}
}