{
  "type": "Feature",
  "properties": {
    "addr:full":"212 S Pearl St Centralia WA 98531",
    "addr:housenumber":"212",
    "addr:postcode":"98531",
    "addr:street":"S Pearl St",
    "iso:country":"US",
    "sg:address":"212 S Pearl St",
    "sg:city":"Centralia",
    "sg:classifiers":[
        {
            "category":"Autos & Motor Vehicles",
            "subcategory":"Auto Supplies",
            "type":"Retail Goods"
        },
        {
            "category":"Wholesale",
            "subcategory":"Auto Parts",
            "type":"Manufacturing & Wholesale Goods"
        }
    ],
    "sg:phone":"+1 360 736 9335",
    "sg:postcode":"98531",
    "sg:province":"WA",
    "sg:tags":[
        "body",
        "automobile",
        "truck",
        "equipment",
        "accessory"
    ],
    "sg:website":"http://www.oreillyauto.com?utm_source=yellowpages&utm_medium=iyp&utm_campaign=2531",
    "wof:name":"Schuck's O'Reilly Auto Parts",
    "wof:placetype":"venue"
},
  "geometry": {"coordinates":[-122.95601499999999,46.715414],"type":"Point"}
}