{
  "type": "Feature",
  "properties": {
    "addr:full":"10728 16th Avenue SW Seattle WA 98146",
    "addr:housenumber":"10728",
    "addr:postcode":"98146",
    "addr:street":"16Th Avenue Sw",
    "iso:country":"US",
    "sg:address":"10728 16th Avenue SW",
    "sg:city":"Seattle",
    "sg:classifiers":[
        {
            "category":"Professional",
            "type":"Services"
        },
        {
            "category":"Shopping",
            "subcategory":"Florist",
            "type":"Retail Goods"
        }
    ],
    "sg:phone":"+1 206 246 5000",
    "sg:postcode":"98146",
    "sg:province":"WA",
    "sg:tags":[
        "caterer"
    ],
    "wof:name":"White Center Florist",
    "wof:placetype":"venue"
},
  "geometry": {"coordinates":[-122.35528100000001,47.506305],"type":"Point"}
}