{
  "type": "Feature",
  "properties": {
    "addr:full":"2614 NE 86th St Seattle WA 98115",
    "addr:housenumber":"2614",
    "addr:postcode":"98115",
    "addr:street":"Ne 86Th St",
    "iso:country":"US",
    "sg:address":"2614 NE 86th St",
    "sg:city":"Seattle",
    "sg:classifiers":[
        {
            "category":"Wholesale",
            "subcategory":"Durable Goods & Equipment",
            "type":"Manufacturing & Wholesale Goods"
        }
    ],
    "sg:phone":"+1 206 524 4595",
    "sg:postcode":"98115",
    "sg:province":"WA",
    "sg:tags":[
        "professional"
    ],
    "wof:name":"Northwest Scientific Co",
    "wof:placetype":"venue"
},
  "geometry": {"coordinates":[-122.299336,47.691056],"type":"Point"}
}