{
  "type": "Feature",
  "properties": {
    "addr:full":"18506 NE 100th Ct Redmond WA 98052",
    "addr:housenumber":"18506",
    "addr:postcode":"98052",
    "addr:street":"Ne 100Th Ct",
    "iso:country":"US",
    "sg:address":"18506 NE 100th Ct",
    "sg:city":"Redmond",
    "sg:classifiers":[
        {
            "category":"Professional",
            "subcategory":"Computer Services",
            "type":"Services"
        }
    ],
    "sg:phone":"+1 425 869 1118",
    "sg:postcode":"98052",
    "sg:province":"WA",
    "sg:tags":[
        "related"
    ],
    "wof:name":"Feditc LLC",
    "wof:placetype":"venue"
},
  "geometry": {"coordinates":[-122.093254,47.690139],"type":"Point"}
}