{
  "type": "Feature",
  "properties": {
    "addr:full":"292 Corbett Creek Rd Colville WA 99114",
    "addr:housenumber":"292",
    "addr:postcode":"99114",
    "addr:street":"Corbett Creek Rd",
    "iso:country":"US",
    "sg:address":"292 Corbett Creek Rd",
    "sg:city":"Colville",
    "sg:classifiers":[
        {
            "category":"Shopping",
            "subcategory":"Hobbies, Toys, & Games",
            "type":"Retail Goods"
        }
    ],
    "sg:phone":"+1 509 684 8854",
    "sg:postcode":"99114",
    "sg:province":"WA",
    "wof:name":"Hofman Doll Works",
    "wof:placetype":"venue"
},
  "geometry": {"coordinates":[-117.96196399999999,48.53789],"type":"Point"}
}