{
  "type": "Feature",
  "properties": {
    "addr:full":"2718 Kateenah Way Union Gap WA 98903",
    "addr:housenumber":"2718",
    "addr:postcode":"98903",
    "addr:street":"Kateenah Way",
    "iso:country":"US",
    "sg:address":"2718 Kateenah Way",
    "sg:city":"Union Gap",
    "sg:classifiers":[
        {
            "category":"Professional",
            "subcategory":"Detective & Security Services",
            "type":"Services"
        }
    ],
    "sg:phone":"+1 509 453 6900",
    "sg:postcode":"98903",
    "sg:province":"WA",
    "sg:tags":[
        "investigator"
    ],
    "wof:name":"Walmsley Investigations",
    "wof:placetype":"venue"
},
  "geometry": {"coordinates":[-120.48146699999999,46.560356],"type":"Point"}
}