{
  "type": "Feature",
  "properties": {
    "addr:full":"1051 4th St Washougal WA 98671",
    "addr:housenumber":"1051",
    "addr:postcode":"98671",
    "addr:street":"4Th St",
    "iso:country":"US",
    "sg:address":"1051 4th St",
    "sg:city":"Washougal",
    "sg:classifiers":[
        {
            "category":"Restaurant",
            "type":"Food & Drink"
        }
    ],
    "sg:phone":"+1 360 835 5623",
    "sg:postcode":"98671",
    "sg:province":"WA",
    "wof:name":"Round Up Cafe",
    "wof:placetype":"venue"
},
  "geometry": {"coordinates":[-122.370502,45.58729],"type":"Point"}
}