{
  "type": "Feature",
  "properties": {
    "addr:full":"1121 N 92nd St Seattle WA 98103",
    "addr:housenumber":"1121",
    "addr:postcode":"98103",
    "addr:street":"N 92Nd St",
    "iso:country":"US",
    "sg:address":"1121 N 92nd St",
    "sg:city":"Seattle",
    "sg:classifiers":[
        {
            "category":"Recreation",
            "type":"Entertainment"
        }
    ],
    "sg:phone":"+1 206 795 6275",
    "sg:postcode":"98103",
    "sg:province":"WA",
    "sg:tags":[
        "aquarium"
    ],
    "wof:name":"Artisan Aquarium Svc",
    "wof:placetype":"venue"
},
  "geometry": {"coordinates":[-122.342072,47.695543],"type":"Point"}
}