{
  "type": "Feature",
  "properties": {
    "addr:full":"5192 Aldrich Rd Bellingham WA 98226",
    "addr:housenumber":"5192",
    "addr:postcode":"98226",
    "addr:street":"Aldrich Rd",
    "iso:country":"US",
    "sg:address":"5192 Aldrich Rd",
    "sg:city":"Bellingham",
    "sg:classifiers":[
        {
            "category":"Wholesale",
            "subcategory":"Plants",
            "type":"Manufacturing & Wholesale Goods"
        }
    ],
    "sg:phone":"+1 360 384 3763",
    "sg:postcode":"98226",
    "sg:province":"WA",
    "sg:tags":[
        "supply"
    ],
    "wof:name":"Sunbreak Nursery Company",
    "wof:placetype":"venue"
},
  "geometry": {"coordinates":[-122.51872299999999,48.8263],"type":"Point"}
}