{
  "type": "Feature",
  "properties": {
    "addr:full":"703 E Cedar St Sequim WA 98382",
    "addr:housenumber":"703",
    "addr:postcode":"98382",
    "addr:street":"E Cedar St",
    "iso:country":"US",
    "sg:address":"703 E Cedar St",
    "sg:city":"Sequim",
    "sg:classifiers":[
        {
            "category":"Retail",
            "subcategory":"Repair Shop",
            "type":"Services"
        }
    ],
    "sg:phone":"+1 360 681 4354",
    "sg:postcode":"98382",
    "sg:province":"WA",
    "wof:name":"Home Exterior Cleaning",
    "wof:placetype":"venue"
},
  "geometry": {"coordinates":[-123.093479,48.080245],"type":"Point"}
}