{
  "type": "Feature",
  "properties": {
    "iso:country":"US",
    "sg:address":"6223 Nugget Ct SW",
    "sg:city":"Olympia",
    "sg:classifiers":[
        {
            "category":"Wholesale",
            "subcategory":"Toys & Hobbies",
            "type":"Manufacturing & Wholesale Goods"
        },
        {
            "category":"Social Services",
            "type":"Services"
        }
    ],
    "sg:phone":"+1 360 352 8546",
    "sg:postcode":"98512",
    "sg:province":"WA",
    "sg:tags":[
        "wholesaler"
    ],
    "wof:name":"FCI Of Western Washington",
    "wof:placetype":"venue"
},
  "geometry": {"coordinates":[-122.933897,46.993152],"type":"Point"}
}