{
  "type": "Feature",
  "properties": {
    "addr:full":"7103 W Grandridge Blvd Kennewick WA 99336",
    "addr:housenumber":"7103",
    "addr:postcode":"99336",
    "addr:street":"W Grandridge Blvd",
    "iso:country":"US",
    "sg:address":"7103 W Grandridge Blvd",
    "sg:city":"Kennewick",
    "sg:classifiers":[
        {
            "category":"Health Services",
            "subcategory":"Doctor",
            "type":"Services"
        }
    ],
    "sg:phone":"+1 509 735 9001",
    "sg:postcode":"99336",
    "sg:province":"WA",
    "sg:tags":[
        "physician",
        "surgeons",
        "disease",
        "internal",
        "medicine",
        "surgeon",
        "pulmonary"
    ],
    "wof:name":"Tan Thomas Dr Md",
    "wof:placetype":"venue"
},
  "geometry": {"coordinates":[-119.217321,46.217056],"type":"Point"}
}