{
  "type": "Feature",
  "properties": {
    "addr:full":"21701 NE 159th St Brush Prairie WA 98606",
    "addr:housenumber":"21701",
    "addr:postcode":"98606",
    "addr:street":"Ne 159Th St",
    "iso:country":"US",
    "sg:address":"21701 NE 159th St",
    "sg:city":"Brush Prairie",
    "sg:classifiers":[
        {
            "category":"Professional",
            "type":"Services"
        }
    ],
    "sg:phone":"+1 360 254 5707",
    "sg:postcode":"98606",
    "sg:province":"WA",
    "wof:name":"Customer Care Inc",
    "wof:placetype":"venue"
},
  "geometry": {"coordinates":[-122.44770699999999,45.737141],"type":"Point"}
}