{
  "type": "Feature",
  "properties": {
    "addr:full":"822 Queen Anne Ave N Seattle WA 98109",
    "addr:housenumber":"822",
    "addr:postcode":"98109",
    "addr:street":"Queen Anne Ave N",
    "iso:country":"US",
    "sg:address":"822 Queen Anne Ave N",
    "sg:city":"Seattle",
    "sg:classifiers":[
        {
            "category":"Professional",
            "subcategory":"Management & Consulting",
            "type":"Services"
        }
    ],
    "sg:phone":"+1 206 691 3879",
    "sg:postcode":"98109",
    "sg:province":"WA",
    "sg:tags":[
        "fuel"
    ],
    "wof:name":"CAC Management",
    "wof:placetype":"venue"
},
  "geometry": {"coordinates":[-122.356617,47.626994],"type":"Point"}
}