{
  "type": "Feature",
  "properties": {
    "addr:full":"2606 N Alder St Tacoma WA 98407",
    "addr:housenumber":"2606",
    "addr:postcode":"98407",
    "addr:street":"N Alder St",
    "iso:country":"US",
    "sg:address":"2606 N Alder St",
    "sg:city":"Tacoma",
    "sg:classifiers":[
        {
            "category":"Professional",
            "subcategory":"Lawyer & Legal Services",
            "type":"Services"
        }
    ],
    "sg:phone":"+1 253 859 8067",
    "sg:postcode":"98407",
    "sg:province":"WA",
    "sg:tags":[
        "attorney"
    ],
    "wof:name":"Margullis Luedtke & Ray Attys",
    "wof:placetype":"venue"
},
  "geometry": {"coordinates":[-122.477778,47.271933],"type":"Point"}
}