{
  "type": "Feature",
  "properties": {
    "addr:full":"3626 NE 45th St Seattle WA 98105",
    "addr:housenumber":"3626",
    "addr:postcode":"98105",
    "addr:street":"Ne 45Th St",
    "iso:country":"US",
    "sg:address":"3626 NE 45th St",
    "sg:city":"Seattle",
    "sg:classifiers":[
        {
            "category":"Health Services",
            "subcategory":"Health Practitioner",
            "type":"Services"
        }
    ],
    "sg:phone":"+1 206 523 1325",
    "sg:postcode":"98105",
    "sg:province":"WA",
    "sg:tags":[
        "therapist",
        "physical"
    ],
    "wof:name":"Physio Therapy Associates",
    "wof:placetype":"venue"
},
  "geometry": {"coordinates":[-122.288399,47.661214],"type":"Point"}
}