{
  "type": "Feature",
  "properties": {
    "addr:full":"2406 S Ledbetter St Kennewick WA 99337",
    "addr:housenumber":"2406",
    "addr:postcode":"99337",
    "addr:street":"S Ledbetter St",
    "iso:country":"US",
    "sg:address":"2406 S Ledbetter St",
    "sg:city":"Kennewick",
    "sg:classifiers":[
        {
            "category":"Building & Trades",
            "subcategory":"Construction",
            "type":"Services"
        }
    ],
    "sg:phone":"+1 509 586 1542",
    "sg:postcode":"99337",
    "sg:province":"WA",
    "sg:tags":[
        "concrete",
        "contractor"
    ],
    "wof:name":"Maydole Concrete",
    "wof:placetype":"venue"
},
  "geometry": {"coordinates":[-119.16863499999999,46.184349],"type":"Point"}
}