{
  "type": "Feature",
  "properties": {
    "addr:full":"1717 136th Pl NE Bellevue WA 98005",
    "addr:housenumber":"1717",
    "addr:postcode":"98005",
    "addr:street":"136Th Pl Ne",
    "iso:country":"US",
    "sg:address":"1717 136th Pl NE",
    "sg:city":"Bellevue",
    "sg:classifiers":[
        {
            "category":"Manufacturing",
            "subcategory":"Rubber & Plastics",
            "type":"Manufacturing & Wholesale Goods"
        }
    ],
    "sg:phone":"+1 425 646 0670",
    "sg:postcode":"98005",
    "sg:province":"WA",
    "sg:tags":[
        "auto",
        "mfg",
        "accessory"
    ],
    "wof:name":"Stongard Inc",
    "wof:placetype":"venue"
},
  "geometry": {"coordinates":[-122.157617,47.626956],"type":"Point"}
}