{
  "type": "Feature",
  "properties": {
    "addr:full":"5738 N 26th St Tacoma WA 98407",
    "addr:housenumber":"5738",
    "addr:postcode":"98407",
    "addr:street":"N 26Th St",
    "iso:country":"US",
    "sg:address":"5738 N 26th St",
    "sg:city":"Tacoma",
    "sg:classifiers":[
        {
            "category":"Retail",
            "subcategory":"Self-service Laundry",
            "type":"Services"
        }
    ],
    "sg:phone":"+1 253 297 8632",
    "sg:postcode":"98407",
    "sg:province":"WA",
    "wof:name":"Lighthouse Laundry",
    "wof:placetype":"venue"
},
  "geometry": {"coordinates":[-122.51553,47.271015],"type":"Point"}
}