{
  "type": "Feature",
  "properties": {
    "addr:full":"1999 30th St Bellingham WA 98225",
    "addr:housenumber":"1999",
    "addr:postcode":"98225",
    "addr:street":"30Th St",
    "iso:country":"US",
    "sg:address":"1999 30th St",
    "sg:city":"Bellingham",
    "sg:classifiers":[
        {
            "category":"Professional",
            "subcategory":"Business Services",
            "type":"Services"
        }
    ],
    "sg:phone":"+1 360 676 9857",
    "sg:postcode":"98225",
    "sg:province":"WA",
    "wof:name":"Word Wide Grman To Englh Trans",
    "wof:placetype":"venue"
},
  "geometry": {"coordinates":[-122.478191,48.714596],"type":"Point"}
}