{
  "type": "Feature",
  "properties": {
    "addr:full":"6802 96th Ave SE Mercer Island WA 98040",
    "addr:housenumber":"6802",
    "addr:postcode":"98040",
    "addr:street":"96Th Ave Se",
    "iso:country":"US",
    "sg:address":"6802 96th Ave SE",
    "sg:city":"Mercer Island",
    "sg:classifiers":[
        {
            "category":"Health Services",
            "subcategory":"Clinic",
            "type":"Services"
        }
    ],
    "sg:phone":"+1 206 953 6089",
    "sg:postcode":"98040",
    "sg:province":"WA",
    "wof:name":"Catalyst Health & Medical Svcs",
    "wof:placetype":"venue"
},
  "geometry": {"coordinates":[-122.210981,47.540749],"type":"Point"}
}