{
  "type": "Feature",
  "properties": {
    "addr:full":"1114 NW 22nd Ave Battle Ground WA 98604",
    "addr:housenumber":"1114",
    "addr:postcode":"98604",
    "addr:street":"Nw 22Nd Ave",
    "iso:country":"US",
    "sg:address":"1114 NW 22nd Ave",
    "sg:city":"Battle Ground",
    "sg:classifiers":[
        {
            "category":"Real Estate",
            "subcategory":"Developer",
            "type":"Services"
        }
    ],
    "sg:phone":"+1 360 666 2552",
    "sg:postcode":"98604",
    "sg:province":"WA",
    "wof:name":"Rockford Homes Inc",
    "wof:placetype":"venue"
},
  "geometry": {"coordinates":[-122.560582,45.789295],"type":"Point"}
}