{
  "type": "Feature",
  "properties": {
    "addr:full":"23714 222nd Pl SE Maple Valley WA 98038",
    "addr:housenumber":"23714",
    "addr:postcode":"98038",
    "addr:street":"222Nd Pl Se;Valley",
    "iso:country":"US",
    "sg:address":"23714 222nd Pl SE",
    "sg:city":"Maple Valley",
    "sg:classifiers":[
        {
            "category":"Restaurant",
            "type":"Food & Drink"
        }
    ],
    "sg:phone":"+1 425 432 5027",
    "sg:postcode":"98038",
    "sg:province":"WA",
    "sg:tags":[
        "eating"
    ],
    "wof:name":"China Light",
    "wof:placetype":"venue"
},
  "geometry": {"coordinates":[-122.044332,47.387735],"type":"Point"}
}