{
  "type": "Feature",
  "properties": {
    "addr:full":"4126 4th St NW Gig Harbor WA 98335",
    "addr:housenumber":"4126",
    "addr:postcode":"98335",
    "addr:street":"4Th St Nw",
    "iso:country":"US",
    "sg:address":"4126 4th St NW",
    "sg:city":"Gig Harbor",
    "sg:classifiers":[
        {
            "category":"Professional",
            "subcategory":"Computer Services",
            "type":"Services"
        }
    ],
    "sg:phone":"+1 253 851 3200",
    "sg:postcode":"98335",
    "sg:province":"WA",
    "sg:tags":[
        "programing",
        "custom"
    ],
    "wof:name":"Measurement Research Corp",
    "wof:placetype":"venue"
},
  "geometry": {"coordinates":[-122.59425899999999,47.261554],"type":"Point"}
}