{
  "type": "Feature",
  "properties": {
    "addr:full":"2235 Main St Ferndale WA 98248",
    "addr:housenumber":"2235",
    "addr:postcode":"98248",
    "addr:street":"Main St",
    "iso:country":"US",
    "sg:address":"2235 Main St",
    "sg:city":"Ferndale",
    "sg:classifiers":[
        {
            "category":"Utilities",
            "subcategory":"Telephone",
            "type":"Services"
        }
    ],
    "sg:phone":"+1 360 384 2422",
    "sg:postcode":"98248",
    "sg:province":"WA",
    "sg:tags":[
        "communications"
    ],
    "wof:name":"Mount View High Tech",
    "wof:placetype":"venue"
},
  "geometry": {"coordinates":[-122.60318100000001,48.848273],"type":"Point"}
}