{
  "type": "Feature",
  "properties": {
    "addr:full":"1601 R Ave Anacortes WA 98221",
    "addr:housenumber":"1601",
    "addr:postcode":"98221",
    "addr:street":"R Ave",
    "iso:country":"US",
    "sg:address":"1601 R Ave",
    "sg:city":"Anacortes",
    "sg:classifiers":[
        {
            "category":"Professional",
            "subcategory":"Computer Services",
            "type":"Services"
        }
    ],
    "sg:phone":"+1 360 299 8558",
    "sg:postcode":"98221",
    "sg:province":"WA",
    "sg:tags":[
        "prepackaged",
        "custom",
        "programing",
        "software"
    ],
    "wof:name":"Shs",
    "wof:placetype":"venue"
},
  "geometry": {"coordinates":[-122.608908,48.510604],"type":"Point"}
}