{
  "type": "Feature",
  "properties": {
    "addr:full":"1105 Main St Oroville WA 98844",
    "addr:housenumber":"1105",
    "addr:postcode":"98844",
    "addr:street":"Main St",
    "iso:country":"US",
    "sg:address":"1105 Main St",
    "sg:city":"Oroville",
    "sg:classifiers":[
        {
            "category":"Government",
            "subcategory":"Office",
            "type":"Public Place"
        }
    ],
    "sg:phone":"+1 509 476 3622",
    "sg:postcode":"98844",
    "sg:province":"WA",
    "sg:tags":[
        "federal",
        "affairs"
    ],
    "wof:name":"US Border Patrol",
    "wof:placetype":"venue"
},
  "geometry": {"coordinates":[-119.43702999999999,48.935921],"type":"Point"}
}