{
  "type": "Feature",
  "properties": {
    "addr:full":"14424 NE 14th Pl Bellevue WA 98007",
    "addr:housenumber":"14424",
    "addr:postcode":"98007",
    "addr:street":"Ne 14Th Pl",
    "iso:country":"US",
    "sg:address":"14424 NE 14th Pl",
    "sg:city":"Bellevue",
    "sg:classifiers":[
        {
            "category":"Shopping",
            "subcategory":"Clothing, Apparel, & Fashions",
            "type":"Retail Goods"
        }
    ],
    "sg:phone":"+1 425 885 9892",
    "sg:postcode":"98007",
    "sg:province":"WA",
    "wof:name":"Classy Oak",
    "wof:placetype":"venue"
},
  "geometry": {"coordinates":[-122.14742699999999,47.6221],"type":"Point"}
}