{
  "type": "Feature",
  "properties": {
    "addr:full":"201 W Prospect Ave Hoquiam WA 98550",
    "addr:housenumber":"201",
    "addr:postcode":"98550",
    "addr:street":"W Prospect Ave",
    "iso:country":"US",
    "sg:address":"201 W Prospect Ave",
    "sg:city":"Hoquiam",
    "sg:classifiers":[
        {
            "category":"Professional",
            "subcategory":"Management & Consulting",
            "type":"Services"
        }
    ],
    "sg:phone":"+1 360 533 4331",
    "sg:postcode":"98550",
    "sg:province":"WA",
    "sg:tags":[
        "business"
    ],
    "wof:name":"Mlc Associates",
    "wof:placetype":"venue"
},
  "geometry": {"coordinates":[-123.903954,46.984624],"type":"Point"}
}