{
  "type": "Feature",
  "properties": {
    "addr:full":"700 E Manitoba Ave # 109 Ellensburg WA 98926",
    "addr:housenumber":"700",
    "addr:postcode":"98926",
    "addr:street":"E Manitoba Ave # 109",
    "iso:country":"US",
    "sg:address":"700 E Manitoba Ave # 109",
    "sg:city":"Ellensburg",
    "sg:classifiers":[
        {
            "category":"Health Services",
            "subcategory":"Doctor",
            "type":"Services"
        }
    ],
    "sg:phone":"+1 509 925 6947",
    "sg:postcode":"98926",
    "sg:province":"WA",
    "sg:tags":[
        "physician",
        "family",
        "practice",
        "surgeons",
        "medicine",
        "surgeon",
        "surgery-general"
    ],
    "wof:name":"O'brien, Timothy J Md",
    "wof:placetype":"venue"
},
  "geometry": {"coordinates":[-120.538712,46.98843],"type":"Point"}
}