{
  "type": "Feature",
  "properties": {
    "addr:full":"10019 NE 29th Pl Bellevue WA 98004",
    "addr:housenumber":"10019",
    "addr:postcode":"98004",
    "addr:street":"Ne 29Th Pl",
    "iso:country":"US",
    "sg:address":"10019 NE 29th Pl",
    "sg:city":"Bellevue",
    "sg:classifiers":[
        {
            "category":"Professional",
            "subcategory":"Management & Consulting",
            "type":"Services"
        }
    ],
    "sg:phone":"+1 425 241 4639",
    "sg:postcode":"98004",
    "sg:province":"WA",
    "sg:tags":[
        "business"
    ],
    "wof:name":"Blasko Consulting",
    "wof:placetype":"venue"
},
  "geometry": {"coordinates":[-122.203487,47.636878],"type":"Point"}
}