{
  "type": "Feature",
  "properties": {
    "addr:full":"8102 NE 91st Pl Vancouver WA 98662",
    "addr:housenumber":"8102",
    "addr:postcode":"98662",
    "addr:street":"Ne 91St Pl",
    "iso:country":"US",
    "sg:address":"8102 NE 91st Pl",
    "sg:city":"Vancouver",
    "sg:classifiers":[
        {
            "category":"Real Estate",
            "subcategory":"Real Estate Operator",
            "type":"Services"
        }
    ],
    "sg:phone":"+1 360 260 7292",
    "sg:postcode":"98662",
    "sg:province":"WA",
    "sg:tags":[
        "building",
        "apartment",
        "shoes"
    ],
    "wof:name":"4 KS Properties LLC",
    "wof:placetype":"venue"
},
  "geometry": {"coordinates":[-122.579324,45.681258],"type":"Point"}
}