{
  "type": "Feature",
  "properties": {
    "addr:full":"16832 Bradley Rd Bow WA 98232",
    "addr:housenumber":"16832",
    "addr:postcode":"98232",
    "addr:street":"Bradley Rd",
    "iso:country":"US",
    "sg:address":"16832 Bradley Rd",
    "sg:city":"Bow",
    "sg:classifiers":[
        {
            "category":"Health Services",
            "subcategory":"Nursing And Care Facility",
            "type":"Services"
        }
    ],
    "sg:phone":"+1 360 707 2767",
    "sg:postcode":"98232",
    "sg:province":"WA",
    "wof:name":"L BS Adult Family Home",
    "wof:placetype":"venue"
},
  "geometry": {"coordinates":[-122.38151999999999,48.508633],"type":"Point"}
}