{
  "type": "Feature",
  "properties": {
    "addr:full":"14325 Lake City Way NE Seattle WA 98125",
    "addr:housenumber":"14325",
    "addr:postcode":"98125",
    "addr:street":"Lake City Way Ne",
    "iso:country":"US",
    "sg:address":"14325 Lake City Way NE",
    "sg:city":"Seattle",
    "sg:classifiers":[
        {
            "category":"Building & Trades",
            "subcategory":"Construction",
            "type":"Services"
        }
    ],
    "sg:phone":"+1 206 367 8405",
    "sg:postcode":"98125",
    "sg:province":"WA",
    "sg:tags":[
        "hardwood",
        "floor",
        "contractor"
    ],
    "wof:name":"Sterling Hardwood Floors Inc",
    "wof:placetype":"venue"
},
  "geometry": {"coordinates":[-122.29250500000001,47.73353],"type":"Point"}
}