{
  "type": "Feature",
  "properties": {
    "addr:full":"8608 W Clearwater Ave Kennewick WA 99336",
    "addr:housenumber":"8608",
    "addr:postcode":"99336",
    "addr:street":"W Clearwater Ave",
    "iso:country":"US",
    "sg:address":"8608 W Clearwater Ave",
    "sg:city":"Kennewick",
    "sg:classifiers":[
        {
            "category":"Real Estate",
            "subcategory":"Developer",
            "type":"Services"
        }
    ],
    "sg:phone":"+1 509 627 0743",
    "sg:postcode":"99336",
    "sg:province":"WA",
    "wof:name":"TMT Homes Inc",
    "wof:placetype":"venue"
},
  "geometry": {"coordinates":[-119.23307800000001,46.209653],"type":"Point"}
}