{
  "type": "Feature",
  "properties": {
    "addr:full":"2820 164th St SW Lynnwood WA 98087",
    "addr:housenumber":"2820",
    "addr:postcode":"98087",
    "addr:street":"164Th St Sw",
    "iso:country":"US",
    "sg:address":"2820 164th St SW",
    "sg:city":"Lynnwood",
    "sg:classifiers":[
        {
            "category":"Real Estate",
            "subcategory":"Developer",
            "type":"Services"
        }
    ],
    "sg:phone":"+1 425 741 3535",
    "sg:postcode":"98087",
    "sg:province":"WA",
    "sg:website":"www.echelbarger.com",
    "wof:name":"Echelbarger Properties Inc",
    "wof:placetype":"venue"
},
  "geometry": {"coordinates":[-122.274236,47.849999],"type":"Point"}
}