{
  "type": "Feature",
  "properties": {
    "addr:full":"811 1st Ave Seattle WA 98104",
    "addr:housenumber":"811",
    "addr:postcode":"98104",
    "addr:street":"1St Ave",
    "iso:country":"US",
    "sg:address":"811 1st Ave",
    "sg:city":"Seattle",
    "sg:classifiers":[
        {
            "category":"Professional",
            "subcategory":"Lawyer & Legal Services",
            "type":"Services"
        }
    ],
    "sg:phone":"+1 206 322 1845",
    "sg:postcode":"98104",
    "sg:province":"WA",
    "wof:name":"Stephenson John C Atty",
    "wof:placetype":"venue"
},
  "geometry": {"coordinates":[-122.334999,47.603401],"type":"Point"}
}