{
  "type": "Feature",
  "properties": {
    "iso:country":"US",
    "sg:address":"500 Boren Ave N",
    "sg:city":"Seattle",
    "sg:classifiers":[
        {
            "category":"Museum",
            "type":"Entertainment"
        }
    ],
    "sg:phone":"+1 206 381 3218",
    "sg:postcode":"98109",
    "sg:province":"WA",
    "sg:tags":[
        "organization",
        "arts",
        "information"
    ],
    "sg:website":"www.conworks.org",
    "wof:name":"Consolidated Works",
    "wof:placetype":"venue"
},
  "geometry": {"coordinates":[-122.335829,47.624541],"type":"Point"}
}