{
  "type": "Feature",
  "properties": {
    "addr:full":"10918 E 20th Ave Spokane WA 99206",
    "addr:housenumber":"10918",
    "addr:postcode":"99206",
    "addr:street":"E 20Th Ave",
    "iso:country":"US",
    "sg:address":"10918 E 20th Ave",
    "sg:city":"Spokane",
    "sg:classifiers":[
        {
            "category":"Manufacturing",
            "subcategory":"Retail Goods",
            "type":"Manufacturing & Wholesale Goods"
        }
    ],
    "sg:phone":"+1 509 924 4780",
    "sg:postcode":"99206",
    "sg:province":"WA",
    "sg:tags":[
        "product",
        "mfg"
    ],
    "wof:name":"She Kat",
    "wof:placetype":"venue"
},
  "geometry": {"coordinates":[-117.25618900000001,47.638716],"type":"Point"}
}