{
  "type": "Feature",
  "properties": {
    "addr:full":"12502 E Sprague Ave Spokane Valley WA 99216",
    "addr:housenumber":"12502",
    "addr:postcode":"99216",
    "addr:street":"E Sprague Ave",
    "iso:country":"US",
    "sg:address":"12502 E Sprague Ave",
    "sg:city":"Spokane Valley",
    "sg:classifiers":[
        {
            "category":"Restaurant",
            "type":"Food & Drink"
        }
    ],
    "sg:phone":"+1 509 924 4660",
    "sg:postcode":"99216",
    "sg:province":"WA",
    "wof:name":"Ron's Drive-In",
    "wof:placetype":"venue"
},
  "geometry": {"coordinates":[-117.237128,47.656988],"type":"Point"}
}