{
  "type": "Feature",
  "properties": {
    "addr:full":"10222 E Mission Ave Spokane WA 99206",
    "addr:housenumber":"10222",
    "addr:postcode":"99206",
    "addr:street":"E Mission Ave",
    "iso:country":"US",
    "sg:address":"10222 E Mission Ave",
    "sg:city":"Spokane",
    "sg:classifiers":[
        {
            "category":"Education",
            "subcategory":"Special Training",
            "type":"Public Place"
        }
    ],
    "sg:phone":"+1 509 922 5791",
    "sg:postcode":"99206",
    "sg:province":"WA",
    "wof:name":"Horizon Quest Tutoring Ce",
    "wof:placetype":"venue"
},
  "geometry": {"coordinates":[-117.26794099999999,47.671473],"type":"Point"}
}