{
  "type": "Feature",
  "properties": {
    "iso:country":"US",
    "sg:address":"431 Ambaum Blvd SW",
    "sg:city":"Seattle",
    "sg:classifiers":[
        {
            "category":"Utilities",
            "subcategory":"Sewage",
            "type":"Services"
        }
    ],
    "sg:phone":"+1 206 244 9575",
    "sg:postcode":"98166",
    "sg:province":"WA",
    "sg:tags":[
        "sewer",
        "district"
    ],
    "wof:name":"Southwest Suburban Sewer Dst",
    "wof:placetype":"venue"
},
  "geometry": {"coordinates":[-122.33955899999999,47.463018],"type":"Point"}
}