{
  "type": "Feature",
  "properties": {
    "addr:full":"6545 5th Pl S Seattle WA 98108",
    "addr:housenumber":"6545",
    "addr:postcode":"98108",
    "addr:street":"5Th Pl S",
    "iso:country":"US",
    "sg:address":"6545 5th Pl S",
    "sg:city":"Seattle",
    "sg:classifiers":[
        {
            "category":"Shopping",
            "subcategory":"Books",
            "type":"Retail Goods"
        }
    ],
    "sg:phone":"+1 206 763 4840",
    "sg:postcode":"98108",
    "sg:province":"WA",
    "sg:tags":[
        "comic"
    ],
    "wof:name":"Capital City Distribution Inc",
    "wof:placetype":"venue"
},
  "geometry": {"coordinates":[-122.32735,47.544798],"type":"Point"}
}