{
  "type": "Feature",
  "properties": {
    "addr:full":"118 S Lincoln St Spokane WA 99201",
    "addr:housenumber":"118",
    "addr:postcode":"99201",
    "addr:street":"S Lincoln St",
    "iso:country":"US",
    "sg:address":"118 S Lincoln St",
    "sg:city":"Spokane",
    "sg:classifiers":[
        {
            "category":"Manufacturing",
            "subcategory":"Printing",
            "type":"Manufacturing & Wholesale Goods"
        }
    ],
    "sg:phone":"+1 509 838 3646",
    "sg:postcode":"99201",
    "sg:province":"WA",
    "sg:tags":[
        "commercial"
    ],
    "sg:website":"www.lithoartprinters.com",
    "wof:name":"Litho-Art Printers Inc",
    "wof:placetype":"venue"
},
  "geometry": {"coordinates":[-117.425085,47.656356],"type":"Point"}
}