{
  "type": "Feature",
  "properties": {
    "iso:country":"US",
    "sg:address":"2106 N Flora Rd",
    "sg:city":"Greenacres",
    "sg:classifiers":[
        {
            "category":"Building & Trades",
            "subcategory":"Construction",
            "type":"Services"
        }
    ],
    "sg:phone":"+1 509 928 3189",
    "sg:postcode":"99016",
    "sg:province":"WA",
    "sg:tags":[
        "carpentry",
        "contractor"
    ],
    "wof:name":"J&K Custom Cabinets",
    "wof:placetype":"venue"
},
  "geometry": {"coordinates":[-117.17503000000001,47.676376],"type":"Point"}
}