{
  "type": "Feature",
  "properties": {
    "addr:full":"27635 Covington Way SE Kent WA 98042",
    "addr:housenumber":"27635",
    "addr:postcode":"98042",
    "addr:street":"Covington Way Se",
    "iso:country":"US",
    "sg:address":"27635 Covington Way SE",
    "sg:city":"Kent",
    "sg:classifiers":[
        {
            "category":"Building & Trades",
            "subcategory":"Electrical",
            "type":"Services"
        }
    ],
    "sg:phone":"+1 253 630 5712",
    "sg:postcode":"98042",
    "sg:province":"WA",
    "sg:tags":[
        "electrical",
        "contractor"
    ],
    "wof:name":"Rec Residentual Electric Co",
    "wof:placetype":"venue"
},
  "geometry": {"coordinates":[-122.122995,47.354613],"type":"Point"}
}