{
  "type": "Feature",
  "properties": {
    "addr:full":"418 Old Pottery Rd Eastsound WA 98245",
    "addr:housenumber":"418",
    "addr:postcode":"98245",
    "addr:street":"Old Pottery Rd",
    "iso:country":"US",
    "sg:address":"418 Old Pottery Rd",
    "sg:city":"Eastsound",
    "sg:classifiers":[
        {
            "category":"Organizations",
            "subcategory":"Religious Organization",
            "type":"Services"
        }
    ],
    "sg:phone":"+1 360 376 2191",
    "sg:postcode":"98245",
    "sg:province":"WA",
    "wof:name":"Covenant Capital LLC",
    "wof:placetype":"venue"
},
  "geometry": {"coordinates":[-122.962678,48.682223],"type":"Point"}
}