{
  "type": "Feature",
  "properties": {
    "addr:full":"2224 N Locust Rd Spokane WA 99206",
    "addr:housenumber":"2224",
    "addr:postcode":"99206",
    "addr:street":"N Locust Rd",
    "iso:country":"US",
    "sg:address":"2224 N Locust Rd",
    "sg:city":"Spokane",
    "sg:classifiers":[
        {
            "category":"Manufacturing",
            "subcategory":"Wood Products",
            "type":"Manufacturing & Wholesale Goods"
        }
    ],
    "sg:phone":"+1 509 255 5355",
    "sg:postcode":"99206",
    "sg:province":"WA",
    "sg:tags":[
        "mfg"
    ],
    "wof:name":"Design Factory",
    "wof:placetype":"venue"
},
  "geometry": {"coordinates":[-117.277293,47.67765],"type":"Point"}
}