{
  "type": "Feature",
  "properties": {
    "addr:full":"17850 Military Rd S Seattle WA 98188",
    "addr:housenumber":"17850",
    "addr:postcode":"98188",
    "addr:street":"Military Rd S",
    "iso:country":"US",
    "sg:address":"17850 Military Rd S",
    "sg:city":"Seattle",
    "sg:classifiers":[
        {
            "category":"Education",
            "subcategory":"Library",
            "type":"Public Place"
        }
    ],
    "sg:phone":"+1 206 242 6044",
    "sg:postcode":"98188",
    "sg:province":"WA",
    "sg:tags":[
        "executive"
    ],
    "wof:name":"Library Systems",
    "wof:placetype":"venue"
},
  "geometry": {"coordinates":[-122.273943,47.442986],"type":"Point"}
}