{
  "type": "Feature",
  "properties": {
    "addr:full":"704 S Ralph St Spokane WA 99202",
    "addr:housenumber":"704",
    "addr:postcode":"99202",
    "addr:street":"S Ralph St",
    "iso:country":"US",
    "sg:address":"704 S Ralph St",
    "sg:city":"Spokane",
    "sg:classifiers":[
        {
            "category":"Building & Trades",
            "subcategory":"Cleaning & Sanitation",
            "type":"Services"
        }
    ],
    "sg:phone":"+1 509 535 8476",
    "sg:postcode":"99202",
    "sg:province":"WA",
    "sg:tags":[
        "butler",
        "maid"
    ],
    "wof:name":"NPCS",
    "wof:placetype":"venue"
},
  "geometry": {"coordinates":[-117.36178099999999,47.649177],"type":"Point"}
}