{
  "type": "Feature",
  "properties": {
    "addr:full":"1422 S 31st Ave Yakima WA 98902",
    "addr:housenumber":"1422",
    "addr:postcode":"98902",
    "addr:street":"S 31St Ave",
    "iso:country":"US",
    "sg:address":"1422 S 31st Ave",
    "sg:city":"Yakima",
    "sg:classifiers":[
        {
            "category":"Wholesale",
            "subcategory":"Auto Parts",
            "type":"Manufacturing & Wholesale Goods"
        }
    ],
    "sg:phone":"+1 509 969 4753",
    "sg:postcode":"98902",
    "sg:province":"WA",
    "wof:name":"Xtreme Body Modifications",
    "wof:placetype":"venue"
},
  "geometry": {"coordinates":[-120.550622,46.578283],"type":"Point"}
}