{
  "type": "Feature",
  "properties": {
    "addr:full":"27280 188th Ave SE Kent WA 98042",
    "addr:housenumber":"27280",
    "addr:postcode":"98042",
    "addr:street":"188Th Ave Se",
    "iso:country":"US",
    "sg:address":"27280 188th Ave SE",
    "sg:city":"Kent",
    "sg:classifiers":[
        {
            "category":"Local Transit",
            "type":"Transportation"
        }
    ],
    "sg:phone":"+1 206 601 3261",
    "sg:postcode":"98042",
    "sg:province":"WA",
    "sg:tags":[
        "passenger"
    ],
    "wof:name":"Pin Point Town Car Service",
    "wof:placetype":"venue"
},
  "geometry": {"coordinates":[-122.090175,47.357821],"type":"Point"}
}