{
  "type": "Feature",
  "properties": {
    "iso:country":"US",
    "sg:address":"391 Hoctor Rd",
    "sg:city":"Goldendale",
    "sg:classifiers":[
        {
            "category":"Freight",
            "type":"Transportation"
        }
    ],
    "sg:phone":"+1 509 773 4625",
    "sg:postcode":"98620",
    "sg:province":"WA",
    "sg:tags":[
        "operator",
        "local",
        "trucking"
    ],
    "wof:name":"C&K Trucking",
    "wof:placetype":"venue"
},
  "geometry": {"coordinates":[-120.74231399999999,45.780707],"type":"Point"}
}