{
  "type": "Feature",
  "properties": {
    "addr:full":"21334 191st Ave SE Renton WA 98058",
    "addr:housenumber":"21334",
    "addr:postcode":"98058",
    "addr:street":"191St Ave Se",
    "iso:country":"US",
    "sg:address":"21334 191st Ave SE",
    "sg:city":"Renton",
    "sg:classifiers":[
        {
            "category":"Professional",
            "subcategory":"Management & Consulting",
            "type":"Services"
        }
    ],
    "sg:phone":"+1 425 432 1913",
    "sg:postcode":"98058",
    "sg:province":"WA",
    "sg:tags":[
        "business"
    ],
    "wof:name":"Fred McAry Consultant",
    "wof:placetype":"venue"
},
  "geometry": {"coordinates":[-122.087812,47.411007],"type":"Point"}
}