{
  "type": "Feature",
  "properties": {
    "addr:full":"8023 Greenlake Dr NE Seattle WA 98103",
    "addr:housenumber":"8023",
    "addr:postcode":"98103",
    "addr:street":"Greenlake Dr Ne",
    "iso:country":"US",
    "sg:address":"8023 Greenlake Dr NE",
    "sg:city":"Seattle",
    "sg:classifiers":[
        {
            "category":"Sports & Exercise",
            "subcategory":"Gym",
            "type":"Entertainment"
        },
        {
            "category":"Arena",
            "subcategory":"Sports Club",
            "type":"Entertainment"
        }
    ],
    "sg:phone":"+1 206 260 0491",
    "sg:postcode":"98103",
    "sg:province":"WA",
    "sg:tags":[
        "trainer"
    ],
    "sg:website":"www.seattlefit.com",
    "wof:name":"USA Fit Seattle",
    "wof:placetype":"venue"
},
  "geometry": {"coordinates":[-122.342119,47.687175],"type":"Point"}
}