{
  "type": "Feature",
  "properties": {
    "addr:full":"413 N Pine St Ellensburg WA 98926",
    "addr:housenumber":"413",
    "addr:postcode":"98926",
    "addr:street":"N Pine St",
    "iso:country":"US",
    "sg:address":"413 N Pine St",
    "sg:city":"Ellensburg",
    "sg:classifiers":[
        {
            "category":"Shopping",
            "type":"Retail Goods"
        }
    ],
    "sg:phone":"+1 509 925 5511",
    "sg:postcode":"98926",
    "sg:province":"WA",
    "sg:tags":[
        "merchandise"
    ],
    "sg:website":"www.stayhomeandplay.com",
    "wof:name":"Stay Home & Play Inc",
    "wof:placetype":"venue"
},
  "geometry": {"coordinates":[-120.54600499999999,46.996439],"type":"Point"}
}