{
  "type": "Feature",
  "properties": {
    "addr:full":"917 W Montgomery Ave Spokane WA 99205",
    "addr:housenumber":"917",
    "addr:postcode":"99205",
    "addr:street":"W Montgomery Ave",
    "iso:country":"US",
    "sg:address":"917 W Montgomery Ave",
    "sg:city":"Spokane",
    "sg:classifiers":[
        {
            "category":"Building & Trades",
            "subcategory":"Construction",
            "type":"Services"
        }
    ],
    "sg:phone":"+1 509 328 4931",
    "sg:postcode":"99205",
    "sg:province":"WA",
    "sg:tags":[
        "contractor"
    ],
    "wof:name":"Bb Creek Corp",
    "wof:placetype":"venue"
},
  "geometry": {"coordinates":[-117.426495,47.678491],"type":"Point"}
}