{
  "type": "Feature",
  "properties": {
    "addr:full":"13892 Carney Lake Rd SW Port Orchard WA 98367",
    "addr:housenumber":"13892",
    "addr:postcode":"98367",
    "addr:street":"Carney Lake Rd Sw Port Orchard",
    "iso:country":"US",
    "sg:address":"13892 Carney Lake Rd SW",
    "sg:city":"Port Orchard",
    "sg:classifiers":[
        {
            "category":"Freight",
            "type":"Transportation"
        }
    ],
    "sg:phone":"+1 360 876 1365",
    "sg:postcode":"98367",
    "sg:province":"WA",
    "sg:tags":[
        "operator",
        "local",
        "trucking"
    ],
    "wof:name":"Hare Express",
    "wof:placetype":"venue"
},
  "geometry": {"coordinates":[-122.75432000000001,47.422509],"type":"Point"}
}