{
  "type": "Feature",
  "properties": {
    "addr:full":"1839 N 53rd St Seattle WA 98103",
    "addr:housenumber":"1839",
    "addr:postcode":"98103",
    "addr:street":"N 53Rd St",
    "iso:country":"US",
    "sg:address":"1839 N 53rd St",
    "sg:city":"Seattle",
    "sg:classifiers":[
        {
            "category":"Professional",
            "subcategory":"Management & Consulting",
            "type":"Services"
        }
    ],
    "sg:phone":"+1 206 547 4954",
    "sg:postcode":"98103",
    "sg:province":"WA",
    "sg:tags":[
        "business"
    ],
    "wof:name":"Right Foot Consulting",
    "wof:placetype":"venue"
},
  "geometry": {"coordinates":[-122.33393100000001,47.667143],"type":"Point"}
}