{
  "type": "Feature",
  "properties": {
    "addr:full":"4412 155th Ave SE Bellevue WA 98006",
    "addr:housenumber":"4412",
    "addr:postcode":"98006",
    "addr:street":"155Th Ave Se",
    "iso:country":"US",
    "sg:address":"4412 155th Ave SE",
    "sg:city":"Bellevue",
    "sg:classifiers":[
        {
            "category":"Manufacturing",
            "subcategory":"Paper Products",
            "type":"Manufacturing & Wholesale Goods"
        }
    ],
    "sg:phone":"+1 425 746 7057",
    "sg:postcode":"98006",
    "sg:province":"WA",
    "sg:tags":[
        "mill"
    ],
    "wof:name":"Card-Stock",
    "wof:placetype":"venue"
},
  "geometry": {"coordinates":[-122.13289,47.566678],"type":"Point"}
}