{
  "type": "Feature",
  "properties": {
    "addr:full":"721 Ave D Snohomish WA 98290",
    "addr:housenumber":"721",
    "addr:postcode":"98290",
    "addr:street":"Ave D",
    "iso:country":"US",
    "sg:address":"721 Ave D",
    "sg:city":"Snohomish",
    "sg:classifiers":[
        {
            "category":"Shopping",
            "subcategory":"Computers & Home Electronics",
            "type":"Retail Goods"
        }
    ],
    "sg:phone":"+1 360 862 1450",
    "sg:postcode":"98290",
    "sg:province":"WA",
    "sg:tags":[
        "audio"
    ],
    "wof:name":"MBF Audiovisual",
    "wof:placetype":"venue"
},
  "geometry": {"coordinates":[-122.097897,47.922763],"type":"Point"}
}