{
  "type": "Feature",
  "properties": {
    "addr:full":"1136 NW 50th St Seattle WA 98107",
    "addr:housenumber":"1136",
    "addr:postcode":"98107",
    "addr:street":"Nw 50Th St",
    "iso:country":"US",
    "sg:address":"1136 NW 50th St",
    "sg:city":"Seattle",
    "sg:classifiers":[
        {
            "category":"Retail",
            "subcategory":"Auto Repair",
            "type":"Services"
        }
    ],
    "sg:phone":"+1 206 783 6303",
    "sg:postcode":"98107",
    "sg:province":"WA",
    "sg:tags":[
        "repairing",
        "automobile"
    ],
    "sg:website":"www.doctordonsautomotive.com",
    "wof:name":"Doctor Don's Automotive",
    "wof:placetype":"venue"
},
  "geometry": {"coordinates":[-122.372421,47.665252],"type":"Point"}
}