{
  "type": "Feature",
  "properties": {
    "addr:full":"1805 Bellevue Ave Seattle WA 98122",
    "addr:housenumber":"1805",
    "addr:postcode":"98122",
    "addr:street":"Bellevue Ave",
    "iso:country":"US",
    "sg:address":"1805 Bellevue Ave",
    "sg:city":"Seattle",
    "sg:classifiers":[
        {
            "category":"Building & Trades",
            "subcategory":"Locksmith",
            "type":"Services"
        }
    ],
    "sg:phone":"+1 206 552 7798",
    "sg:postcode":"98122",
    "sg:province":"WA",
    "sg:tags":[
        "key"
    ],
    "wof:name":"Locksmith Auto Home and Office Seattle",
    "wof:placetype":"venue"
},
  "geometry": {"coordinates":[-122.326953,47.617775],"type":"Point"}
}