{
  "type": "Feature",
  "properties": {
    "addr:full":"220 4th Ave S Seattle WA 98104",
    "addr:housenumber":"220",
    "addr:postcode":"98104",
    "addr:street":"4Th Ave S",
    "iso:country":"US",
    "sg:address":"220 4th Ave S",
    "sg:city":"Seattle",
    "sg:classifiers":[
        {
            "category":"Organizations",
            "subcategory":"Community Association",
            "type":"Services"
        }
    ],
    "sg:phone":"+1 206 748 9779",
    "sg:postcode":"98104",
    "sg:province":"WA",
    "sg:tags":[
        "club",
        "nightlife"
    ],
    "wof:name":"Aristocrat's Club Bar & Grill",
    "wof:placetype":"venue"
},
  "geometry": {"coordinates":[-122.329002,47.6003],"type":"Point"}
}