{
  "type": "Feature",
  "properties": {
    "addr:full":"7720 NE Vancouver Mall Dr Vancouver WA 98662",
    "addr:housenumber":"7720",
    "addr:postcode":"98662",
    "addr:street":"Ne Vancouver Mall Dr",
    "iso:country":"US",
    "sg:address":"7720 NE Vancouver Mall Dr",
    "sg:city":"Vancouver",
    "sg:classifiers":[
        {
            "category":"Real Estate",
            "subcategory":"Real Estate Services",
            "type":"Services"
        },
        {
            "category":"Banks & Credit Unions",
            "subcategory":"Bank",
            "type":"Services"
        },
        {
            "category":"Banks & Credit Unions",
            "subcategory":"Financial Services",
            "type":"Services"
        }
    ],
    "sg:phone":"+1 360 449 8010",
    "sg:postcode":"98662",
    "sg:province":"WA",
    "sg:tags":[
        "loan",
        "mortgage"
    ],
    "wof:name":"Golf Savings Bank",
    "wof:placetype":"venue"
},
  "geometry": {"coordinates":[-122.594021,45.657883],"type":"Point"}
}