{
  "type": "Feature",
  "properties": {
    "addr:full":"17711 Spruce Way Lynnwood WA 98037",
    "addr:housenumber":"17711",
    "addr:postcode":"98037",
    "addr:street":"Spruce Way",
    "iso:country":"US",
    "sg:address":"17711 Spruce Way",
    "sg:city":"Lynnwood",
    "sg:classifiers":[
        {
            "category":"Education",
            "subcategory":"College",
            "type":"Public Place"
        }
    ],
    "sg:phone":"+1 425 787 5144",
    "sg:postcode":"98037",
    "sg:province":"WA",
    "sg:tags":[
        "academic",
        "school"
    ],
    "wof:name":"Northwest Theol Seminary",
    "wof:placetype":"venue"
},
  "geometry": {"coordinates":[-122.28872800000001,47.837295],"type":"Point"}
}