{
  "type": "Feature",
  "properties": {
    "iso:country":"US",
    "sg:address":"9024 McConnell Dr",
    "sg:city":"Moses Lake",
    "sg:classifiers":[
        {
            "category":"Building & Trades",
            "subcategory":"Cleaning & Sanitation",
            "type":"Services"
        }
    ],
    "sg:phone":"+1 509 762 9431",
    "sg:postcode":"98837",
    "sg:province":"WA",
    "sg:tags":[
        "maintenance"
    ],
    "wof:name":"Karen Ann Chapman",
    "wof:placetype":"venue"
},
  "geometry": {"coordinates":[-119.322416,47.163312],"type":"Point"}
}