{
  "type": "Feature",
  "properties": {
    "addr:full":"31225 Pioneer Hwy Stanwood WA 98292",
    "addr:housenumber":"31225",
    "addr:postcode":"98292",
    "addr:street":"Pioneer Hwy",
    "iso:country":"US",
    "sg:address":"31225 Pioneer Hwy",
    "sg:city":"Stanwood",
    "sg:classifiers":[
        {
            "category":"Building & Trades",
            "subcategory":"Construction",
            "type":"Services"
        }
    ],
    "sg:phone":"+1 360 629 3157",
    "sg:postcode":"98292",
    "sg:province":"WA",
    "sg:tags":[
        "heavy",
        "equipment",
        "rental"
    ],
    "wof:name":"Larry Sande Dragline Service",
    "wof:placetype":"venue"
},
  "geometry": {"coordinates":[-122.360968,48.279865],"type":"Point"}
}