{
  "type": "Feature",
  "properties": {
    "iso:country":"US",
    "sg:address":"18505 31st Ave SE",
    "sg:city":"Bothell",
    "sg:classifiers":[
        {
            "category":"Real Estate",
            "subcategory":"Developer",
            "type":"Services"
        }
    ],
    "sg:phone":"+1 425 486 9132",
    "sg:postcode":"98012",
    "sg:province":"WA",
    "wof:name":"R & R Properties WA LLC",
    "wof:placetype":"venue"
},
  "geometry": {"coordinates":[-122.19083000000001,47.82942],"type":"Point"}
}