{
  "type": "Feature",
  "properties": {
    "addr:full":"4610 Furzee Rd Clayton WA 99110",
    "addr:housenumber":"4610",
    "addr:postcode":"99110",
    "addr:street":"Furzee Rd",
    "iso:country":"US",
    "sg:address":"4610 Furzee Rd",
    "sg:city":"Clayton",
    "sg:classifiers":[
        {
            "category":"Freight",
            "type":"Transportation"
        }
    ],
    "sg:phone":"+1 509 276 2043",
    "sg:postcode":"99110",
    "sg:province":"WA",
    "sg:tags":[
        "commercial",
        "storage"
    ],
    "wof:name":"Clayton Mini Storage",
    "wof:placetype":"venue"
},
  "geometry": {"coordinates":[-117.54507099999999,48.003122],"type":"Point"}
}