{
  "type": "Feature",
  "properties": {
    "addr:full":"4816 Cypress Dr Anacortes WA 98221",
    "addr:housenumber":"4816",
    "addr:postcode":"98221",
    "addr:street":"Cypress Dr",
    "iso:country":"US",
    "sg:address":"4816 Cypress Dr",
    "sg:city":"Anacortes",
    "sg:classifiers":[
        {
            "category":"Manufacturing",
            "subcategory":"Retail Goods",
            "type":"Manufacturing & Wholesale Goods"
        }
    ],
    "sg:phone":"+1 360 299 8929",
    "sg:postcode":"98221",
    "sg:province":"WA",
    "sg:tags":[
        "fastener",
        "needle",
        "pin"
    ],
    "wof:name":"Fidalgo Fasteners",
    "wof:placetype":"venue"
},
  "geometry": {"coordinates":[-122.66804,48.496826],"type":"Point"}
}