{
  "type": "Feature",
  "properties": {
    "addr:full":"3401 C St NE Suite 14 Auburn WA 98002",
    "addr:housenumber":"3401;14",
    "addr:postcode":"98002",
    "addr:street":"C St Ne Suite",
    "iso:country":"US",
    "sg:address":"3401 C St NE Suite 14",
    "sg:city":"Auburn",
    "sg:classifiers":[
        {
            "category":"Home & Garden",
            "subcategory":"Hardware",
            "type":"Retail Goods"
        }
    ],
    "sg:phone":"+1 877 854 5822",
    "sg:postcode":"98002",
    "sg:province":"WA",
    "sg:tags":[
        "water",
        "equipment",
        "filtration",
        "purification"
    ],
    "sg:website":"http://local.ingenio.com/Listings/Details.aspx?NUM=a%3a10294314%3a13%3a4859924%3a14%3a0%3a7",
    "wof:name":"Drain Away Plumbing Inc",
    "wof:placetype":"venue"
},
  "geometry": {"coordinates":[-122.226562,47.337316],"type":"Point"}
}