{
  "type": "Feature",
  "properties": {
    "iso:country":"US",
    "sg:address":"3834 175th Ave NE",
    "sg:city":"Redmond",
    "sg:classifiers":[
        {
            "category":"Retail",
            "subcategory":"Portrait Studio",
            "type":"Services"
        }
    ],
    "sg:phone":"+1 425 497 9093",
    "sg:postcode":"98052",
    "sg:province":"WA",
    "sg:tags":[
        "photo"
    ],
    "wof:name":"Longshot Photography",
    "wof:placetype":"venue"
},
  "geometry": {"coordinates":[-122.10567500000001,47.643826],"type":"Point"}
}