{
  "type": "Feature",
  "properties": {
    "addr:full":"4127 SW 327th Pl Federal Way WA 98023",
    "addr:housenumber":"4127",
    "addr:postcode":"98023",
    "addr:street":"Sw 327Th Pl",
    "iso:country":"US",
    "sg:address":"4127 SW 327th Pl",
    "sg:city":"Federal Way",
    "sg:classifiers":[
        {
            "category":"Wholesale",
            "subcategory":"Stationery",
            "type":"Manufacturing & Wholesale Goods"
        }
    ],
    "sg:phone":"+1 253 838 3251",
    "sg:postcode":"98023",
    "sg:province":"WA",
    "sg:tags":[
        "supply"
    ],
    "wof:name":"Creative Memories",
    "wof:placetype":"venue"
},
  "geometry": {"coordinates":[-122.38505600000001,47.308989],"type":"Point"}
}