{
  "type": "Feature",
  "properties": {
    "addr:full":"1084 Monroe Landing Rd Oak Harbor WA 98277",
    "addr:housenumber":"1084",
    "addr:postcode":"98277",
    "addr:street":"Monroe Landing Rd",
    "iso:country":"US",
    "sg:address":"1084 Monroe Landing Rd",
    "sg:city":"Oak Harbor",
    "sg:classifiers":[
        {
            "category":"Professional",
            "subcategory":"Management & Consulting",
            "type":"Services"
        }
    ],
    "sg:phone":"+1 360 675 3163",
    "sg:postcode":"98277",
    "sg:province":"WA",
    "sg:tags":[
        "business"
    ],
    "wof:name":"Just Facts",
    "wof:placetype":"venue"
},
  "geometry": {"coordinates":[-122.68056900000001,48.251267],"type":"Point"}
}