{
  "type": "Feature",
  "properties": {
    "addr:full":"15608 NE Noble St Vancouver WA 98665",
    "addr:housenumber":"15608",
    "addr:postcode":"98665",
    "addr:street":"Ne Noble St",
    "iso:country":"US",
    "sg:address":"15608 NE Noble St",
    "sg:city":"Vancouver",
    "sg:classifiers":[
        {
            "category":"Social Services",
            "subcategory":"Retirement Home",
            "type":"Services"
        }
    ],
    "sg:phone":"+1 360 254 3278",
    "sg:postcode":"98665",
    "sg:province":"WA",
    "sg:website":"www.assurety.org",
    "wof:name":"Assurety Senior Center",
    "wof:placetype":"venue"
},
  "geometry": {"coordinates":[-122.510462,45.65609],"type":"Point"}
}