{
  "type": "Feature",
  "properties": {
    "addr:full":"1381 Linwood Ave SW Olympia WA 98512",
    "addr:housenumber":"1381",
    "addr:postcode":"98512",
    "addr:street":"Linwood Ave Sw",
    "iso:country":"US",
    "sg:address":"1381 Linwood Ave SW",
    "sg:city":"Olympia",
    "sg:classifiers":[
        {
            "category":"Manufacturing",
            "subcategory":"Signs",
            "type":"Manufacturing & Wholesale Goods"
        }
    ],
    "sg:phone":"+1 360 352 5926",
    "sg:postcode":"98512",
    "sg:province":"WA",
    "sg:tags":[
        "specialty",
        "mfg"
    ],
    "wof:name":"Sign Shop",
    "wof:placetype":"venue"
},
  "geometry": {"coordinates":[-122.92283399999999,47.007287],"type":"Point"}
}