{
  "type": "Feature",
  "properties": {
    "iso:country":"US",
    "sg:address":"182 Deer Hollow Cir",
    "sg:city":"Port Ludlow",
    "sg:classifiers":[
        {
            "category":"Banks & Credit Unions",
            "subcategory":"Financial Services",
            "type":"Services"
        }
    ],
    "sg:phone":"+1 360 437 2299",
    "sg:postcode":"98365",
    "sg:province":"WA",
    "sg:tags":[
        "trust",
        "management"
    ],
    "wof:name":"Kerr Family Trust 07 20 8",
    "wof:placetype":"venue"
},
  "geometry": {"coordinates":[-122.694208,47.907179],"type":"Point"}
}