{
  "type": "Feature",
  "properties": {
    "addr:full":"2916 S Division St Spokane WA 99203",
    "addr:housenumber":"2916",
    "addr:postcode":"99203",
    "addr:street":"S Division St",
    "iso:country":"US",
    "sg:address":"2916 S Division St",
    "sg:city":"Spokane",
    "sg:classifiers":[
        {
            "category":"Building & Trades",
            "subcategory":"Construction",
            "type":"Services"
        }
    ],
    "sg:phone":"+1 509 838 3940",
    "sg:postcode":"99203",
    "sg:province":"WA",
    "sg:tags":[
        "contractor"
    ],
    "wof:name":"Dan Johnston Masonry",
    "wof:placetype":"venue"
},
  "geometry": {"coordinates":[-117.41149799999999,47.627414],"type":"Point"}
}