{
  "type": "Feature",
  "properties": {
    "addr:full":"3832 S G St Tacoma WA 98418",
    "addr:housenumber":"3832",
    "addr:postcode":"98418",
    "addr:street":"S G St",
    "iso:country":"US",
    "sg:address":"3832 S G St",
    "sg:city":"Tacoma",
    "sg:classifiers":[
        {
            "category":"Organizations",
            "subcategory":"Religious Organization",
            "type":"Services"
        }
    ],
    "sg:phone":"+1 253 474 5127",
    "sg:postcode":"98418",
    "sg:province":"WA",
    "wof:name":"Lincoln Park Christian Church",
    "wof:placetype":"venue"
},
  "geometry": {"coordinates":[-122.440704,47.221235],"type":"Point"}
}