{
  "type": "Feature",
  "properties": {
    "addr:full":"151 S Hamilton Rd Moses Lake WA 98837",
    "addr:housenumber":"151",
    "addr:postcode":"98837",
    "addr:street":"S Hamilton Rd",
    "iso:country":"US",
    "sg:address":"151 S Hamilton Rd",
    "sg:city":"Moses Lake",
    "sg:classifiers":[
        {
            "category":"Wholesale",
            "subcategory":"Beer",
            "type":"Manufacturing & Wholesale Goods"
        }
    ],
    "sg:phone":"+1 509 765 9161",
    "sg:postcode":"98837",
    "sg:province":"WA",
    "sg:tags":[
        "beverage"
    ],
    "wof:name":"Pistoresi Distributing Inc",
    "wof:placetype":"venue"
},
  "geometry": {"coordinates":[-119.247992,47.130832],"type":"Point"}
}