{
  "type": "Feature",
  "properties": {
    "addr:full":"10305 E Buckeye Ave Spokane Valley WA 99206",
    "addr:housenumber":"10305",
    "addr:postcode":"99206",
    "addr:street":"E Buckeye Ave",
    "iso:country":"US",
    "sg:address":"10305 E Buckeye Ave",
    "sg:city":"Spokane Valley",
    "sg:classifiers":[
        {
            "category":"Wholesale",
            "subcategory":"Construction Materials",
            "type":"Manufacturing & Wholesale Goods"
        }
    ],
    "sg:phone":"+1 509 926 2118",
    "sg:postcode":"99206",
    "sg:province":"WA",
    "sg:tags":[
        "stucco"
    ],
    "wof:name":"Spokane Wall Systems",
    "wof:placetype":"venue"
},
  "geometry": {"coordinates":[-117.268552,47.682231],"type":"Point"}
}