{
  "type": "Feature",
  "properties": {
    "addr:full":"661 N Bend Blvd N North Bend WA 98045",
    "addr:housenumber":"661",
    "addr:postcode":"98045",
    "addr:street":"N Bend Blvd N",
    "iso:country":"US",
    "sg:address":"661 N Bend Blvd N",
    "sg:city":"North Bend",
    "sg:classifiers":[
        {
            "category":"Shopping",
            "subcategory":"Department Store",
            "type":"Retail Goods"
        }
    ],
    "sg:phone":"+1 425 831 3113",
    "sg:postcode":"98045",
    "sg:province":"WA",
    "wof:name":"Eddie Bauer",
    "wof:placetype":"venue"
},
  "geometry": {"coordinates":[-121.79301700000001,47.490296],"type":"Point"}
}