{
  "type": "Feature",
  "properties": {
    "addr:full":"17216 SE 272nd St Covington WA 98042",
    "addr:housenumber":"17216",
    "addr:postcode":"98042",
    "addr:street":"Se 272Nd St",
    "iso:country":"US",
    "sg:address":"17216 SE 272nd St",
    "sg:city":"Covington",
    "sg:classifiers":[
        {
            "category":"Personal",
            "type":"Services"
        },
        {
            "category":"Health Services",
            "subcategory":"Health Practitioner",
            "type":"Services"
        }
    ],
    "sg:phone":"+1 253 631 2406",
    "sg:postcode":"98042",
    "sg:province":"WA",
    "sg:tags":[
        "therapist",
        "massage"
    ],
    "wof:name":"Blue Skies Therapeutic Massage",
    "wof:placetype":"venue"
},
  "geometry": {"coordinates":[-122.111007,47.358248],"type":"Point"}
}