{
  "type": "Feature",
  "properties": {
    "addr:full":"801 E Main St Elma WA 98541",
    "addr:housenumber":"801",
    "addr:postcode":"98541",
    "addr:street":"E Main St",
    "iso:country":"US",
    "sg:address":"801 E Main St",
    "sg:city":"Elma",
    "sg:classifiers":[
        {
            "category":"Travel",
            "subcategory":"Campground",
            "type":"Entertainment"
        }
    ],
    "sg:phone":"+1 360 482 3877",
    "sg:postcode":"98541",
    "sg:province":"WA",
    "sg:tags":[
        "trailer"
    ],
    "wof:name":"Travel Inn Resort",
    "wof:placetype":"venue"
},
  "geometry": {"coordinates":[-123.38741400000001,47.008947],"type":"Point"}
}