{
  "type": "Feature",
  "properties": {
    "addr:full":"12321 NE Fourth Plain Rd Vancouver WA 98682",
    "addr:housenumber":"12321",
    "addr:postcode":"98682",
    "addr:street":"Ne Fourth Plain Rd",
    "iso:country":"US",
    "sg:address":"12321 NE Fourth Plain Rd",
    "sg:city":"Vancouver",
    "sg:classifiers":[
        {
            "category":"Food & Beverages",
            "subcategory":"Bakery",
            "type":"Retail Goods"
        }
    ],
    "sg:phone":"+1 360 260 0878",
    "sg:postcode":"98682",
    "sg:province":"WA",
    "sg:tags":[
        "doughnut"
    ],
    "wof:name":"Donut Plus",
    "wof:placetype":"venue"
},
  "geometry": {"coordinates":[-122.547374,45.668451],"type":"Point"}
}