{
  "type": "Feature",
  "properties": {
    "addr:full":"3377 Bethel Rd SE Port Orchard WA 98366",
    "addr:housenumber":"3377",
    "addr:postcode":"98366",
    "addr:street":"Bethel Rd Se",
    "iso:country":"US",
    "sg:address":"3377 Bethel Rd SE",
    "sg:city":"Port Orchard",
    "sg:classifiers":[
        {
            "category":"Building & Trades",
            "subcategory":"Construction",
            "type":"Services"
        }
    ],
    "sg:phone":"+1 360 981 5996",
    "sg:postcode":"98366",
    "sg:province":"WA",
    "sg:tags":[
        "contractor"
    ],
    "wof:name":"Olympiclean",
    "wof:placetype":"venue"
},
  "geometry": {"coordinates":[-122.63109300000001,47.517622],"type":"Point"}
}