{
  "type": "Feature",
  "properties": {
    "addr:full":"5132 6th Ave Tacoma WA 98406",
    "addr:housenumber":"5132",
    "addr:postcode":"98406",
    "addr:street":"6Th Ave",
    "iso:country":"US",
    "sg:address":"5132 6th Ave",
    "sg:city":"Tacoma",
    "sg:classifiers":[
        {
            "category":"Retail",
            "subcategory":"Portrait Studio",
            "type":"Services"
        }
    ],
    "sg:phone":"+1 253 756 1812",
    "sg:postcode":"98406",
    "sg:province":"WA",
    "sg:tags":[
        "photo"
    ],
    "wof:name":"Olan Mills Studios",
    "wof:placetype":"venue"
},
  "geometry": {"coordinates":[-122.50999400000001,47.255319],"type":"Point"}
}