{
  "type": "Feature",
  "properties": {
    "addr:full":"4301 E Marginal Way S Seattle WA 98134",
    "addr:housenumber":"4301",
    "addr:postcode":"98134",
    "addr:street":"E Marginal Way S",
    "iso:country":"US",
    "sg:address":"4301 E Marginal Way S",
    "sg:city":"Seattle",
    "sg:classifiers":[
        {
            "category":"Building & Trades",
            "subcategory":"Locksmith",
            "type":"Services"
        }
    ],
    "sg:phone":"+1 206 494 9177",
    "sg:postcode":"98134",
    "sg:province":"WA",
    "sg:tags":[
        "key"
    ],
    "wof:name":"0 1 24 Hour A Locksmith",
    "wof:placetype":"venue"
},
  "geometry": {"coordinates":[-122.33963300000001,47.563285],"type":"Point"}
}