{
  "type": "Feature",
  "properties": {
    "addr:full":"5630 138th Pl NE Marysville WA 98271",
    "addr:housenumber":"5630",
    "addr:postcode":"98271",
    "addr:street":"138Th Pl Ne",
    "iso:country":"US",
    "sg:address":"5630 138th Pl NE",
    "sg:city":"Marysville",
    "sg:classifiers":[
        {
            "category":"Building & Trades",
            "subcategory":"Construction",
            "type":"Services"
        }
    ],
    "sg:phone":"+1 360 653 1853",
    "sg:postcode":"98271",
    "sg:province":"WA",
    "sg:tags":[
        "house"
    ],
    "wof:name":"24 7 Construction Co",
    "wof:placetype":"venue"
},
  "geometry": {"coordinates":[-122.15544300000001,48.121322],"type":"Point"}
}