{
  "type": "Feature",
  "properties": {
    "addr:full":"1903 Dry Creek Rd Ellensburg WA 98926",
    "addr:housenumber":"1903",
    "addr:postcode":"98926",
    "addr:street":"Dry Creek Rd",
    "iso:country":"US",
    "sg:address":"1903 Dry Creek Rd",
    "sg:city":"Ellensburg",
    "sg:classifiers":[
        {
            "category":"Building & Trades",
            "subcategory":"Construction",
            "type":"Services"
        }
    ],
    "sg:phone":"+1 509 925 1925",
    "sg:postcode":"98926",
    "sg:province":"WA",
    "sg:tags":[
        "contractor"
    ],
    "wof:name":"Pool Solutions",
    "wof:placetype":"venue"
},
  "geometry": {"coordinates":[-120.579089,47.02056],"type":"Point"}
}