{
  "type": "Feature",
  "properties": {
    "addr:full":"14407 SE 47th Pl Bellevue WA 98006",
    "addr:housenumber":"14407",
    "addr:postcode":"98006",
    "addr:street":"Se 47Th Pl",
    "iso:country":"US",
    "sg:address":"14407 SE 47th Pl",
    "sg:city":"Bellevue",
    "sg:classifiers":[
        {
            "category":"Professional",
            "subcategory":"Business Services",
            "type":"Services"
        }
    ],
    "sg:phone":"+1 425 746 1641",
    "sg:postcode":"98006",
    "sg:province":"WA",
    "sg:tags":[
        "interior",
        "designer",
        "design",
        "decorator"
    ],
    "wof:name":"Sharon Westin Interior Design",
    "wof:placetype":"venue"
},
  "geometry": {"coordinates":[-122.147659,47.560109],"type":"Point"}
}