{
  "type": "Feature",
  "properties": {
    "addr:full":"2332 2nd Ave Seattle WA 98121",
    "addr:housenumber":"2332",
    "addr:postcode":"98121",
    "addr:street":"2Nd Ave",
    "iso:country":"US",
    "sg:address":"2332 2nd Ave",
    "sg:city":"Seattle",
    "sg:classifiers":[
        {
            "category":"Bars & Pubs",
            "subcategory":"Lounge",
            "type":"Food & Drink"
        }
    ],
    "sg:phone":"+1 206 956 8423",
    "sg:postcode":"98121",
    "sg:province":"WA",
    "sg:website":"www.robroyseattle.com/",
    "wof:name":"The Rob Roy",
    "wof:placetype":"venue"
},
  "geometry": {"coordinates":[-122.346537,47.614544],"type":"Point"}
}