{
  "type": "Feature",
  "properties": {
    "addr:full":"40 NE View Ct Belfair WA 98528",
    "addr:housenumber":"40",
    "addr:postcode":"98528",
    "addr:street":"Ne View Ct",
    "iso:country":"US",
    "sg:address":"40 NE View Ct",
    "sg:city":"Belfair",
    "sg:classifiers":[
        {
            "category":"Retail",
            "subcategory":"Auto Repair",
            "type":"Services"
        }
    ],
    "sg:phone":"+1 360 275 5370",
    "sg:postcode":"98528",
    "sg:province":"WA",
    "sg:tags":[
        "repairing",
        "automobile"
    ],
    "wof:name":"DJP Auto Repair",
    "wof:placetype":"venue"
},
  "geometry": {"coordinates":[-122.888604,47.43034],"type":"Point"}
}