{
  "type": "Feature",
  "properties": {
    "addr:full":"9029 Icicle Rd Leavenworth WA 98826",
    "addr:housenumber":"9029",
    "addr:postcode":"98826",
    "addr:street":"Icicle Rd",
    "iso:country":"US",
    "sg:address":"9029 Icicle Rd",
    "sg:city":"Leavenworth",
    "sg:classifiers":[
        {
            "category":"Organizations",
            "subcategory":"Religious Organization",
            "type":"Services"
        }
    ],
    "sg:phone":"+1 509 548 4645",
    "sg:postcode":"98826",
    "sg:province":"WA",
    "wof:name":"Leavenworth Church Of God",
    "wof:placetype":"venue"
},
  "geometry": {"coordinates":[-120.67282299999999,47.580991],"type":"Point"}
}