{
  "type": "Feature",
  "properties": {
    "addr:full":"11724 Lake City Way NE Seattle WA 98125",
    "addr:housenumber":"11724",
    "addr:postcode":"98125",
    "addr:street":"Lake City Way Ne",
    "iso:country":"US",
    "sg:address":"11724 Lake City Way NE",
    "sg:city":"Seattle",
    "sg:classifiers":[
        {
            "category":"Home & Garden",
            "subcategory":"Carpets & Floor Coverings",
            "type":"Retail Goods"
        }
    ],
    "sg:phone":"+1 206 440 8609",
    "sg:postcode":"98125",
    "sg:province":"WA",
    "sg:tags":[
        "flooring"
    ],
    "wof:name":"Pacific Northwest Flooring, LLC",
    "wof:placetype":"venue"
},
  "geometry": {"coordinates":[-122.297487,47.714725],"type":"Point"}
}