{
  "type": "Feature",
  "properties": {
    "addr:full":"2045 S 216th St Des Moines WA 98198",
    "addr:housenumber":"2045",
    "addr:postcode":"98198",
    "addr:street":"S 216Th St",
    "iso:country":"US",
    "sg:address":"2045 S 216th St",
    "sg:city":"Des Moines",
    "sg:classifiers":[
        {
            "category":"Local Transit",
            "type":"Transportation"
        }
    ],
    "sg:phone":"+1 206 878 2066",
    "sg:postcode":"98198",
    "sg:province":"WA",
    "wof:name":"Des Moines Senior Shuttle",
    "wof:placetype":"venue"
},
  "geometry": {"coordinates":[-122.30725200000001,47.408221],"type":"Point"}
}