{
  "type": "Feature",
  "properties": {
    "addr:full":"18804 NE 121st St Brush Prairie WA 98606",
    "addr:housenumber":"18804",
    "addr:postcode":"98606",
    "addr:street":"Ne 121St St",
    "iso:country":"US",
    "sg:address":"18804 NE 121st St",
    "sg:city":"Brush Prairie",
    "sg:classifiers":[
        {
            "category":"Manufacturing",
            "subcategory":"Metals",
            "type":"Manufacturing & Wholesale Goods"
        },
        {
            "category":"Professional",
            "type":"Services"
        }
    ],
    "sg:phone":"+1 360 892 9727",
    "sg:postcode":"98606",
    "sg:province":"WA",
    "sg:tags":[
        "weather",
        "application",
        "industrial",
        "coating",
        "forecast"
    ],
    "wof:name":"Weather Proof Company",
    "wof:placetype":"venue"
},
  "geometry": {"coordinates":[-122.48017400000001,45.710418],"type":"Point"}
}