{
  "type": "Feature",
  "properties": {
    "addr:full":"1780 Kennedy Pl Dupont WA 98327",
    "addr:housenumber":"1780",
    "addr:postcode":"98327",
    "addr:street":"Kennedy Pl Dupont",
    "iso:country":"US",
    "sg:address":"1780 Kennedy Pl",
    "sg:city":"Dupont",
    "sg:classifiers":[
        {
            "category":"Professional",
            "subcategory":"Accounting & Tax Preparation",
            "type":"Services"
        }
    ],
    "sg:phone":"+1 360 491 5999",
    "sg:postcode":"98327",
    "sg:province":"WA",
    "sg:tags":[
        "bookkeeping",
        "billing"
    ],
    "wof:name":"Slm Billing Services",
    "wof:placetype":"venue"
},
  "geometry": {"coordinates":[-122.643743,47.097338],"type":"Point"}
}