{
  "type": "Feature",
  "properties": {
    "addr:full":"8909 61st Ave Ct E Puyallup WA 98371",
    "addr:housenumber":"8909",
    "addr:postcode":"98371",
    "addr:street":"61St Ave Ct E",
    "iso:country":"US",
    "sg:address":"8909 61st Ave Ct E",
    "sg:city":"Puyallup",
    "sg:classifiers":[
        {
            "category":"Organizations",
            "subcategory":"Membership Organization",
            "type":"Services"
        }
    ],
    "sg:phone":"+1 253 848 5724",
    "sg:postcode":"98371",
    "sg:province":"WA",
    "wof:name":"Sons of American Revolution",
    "wof:placetype":"venue"
},
  "geometry": {"coordinates":[-122.34750200000001,47.175875],"type":"Point"}
}