{
  "type": "Feature",
  "properties": {
    "addr:full":"9403 39th Avenue Ct SW Lakewood WA 98499",
    "addr:housenumber":"9403",
    "addr:postcode":"98499",
    "addr:street":"39Th Avenue Ct Sw",
    "iso:country":"US",
    "sg:address":"9403 39th Avenue Ct SW",
    "sg:city":"Lakewood",
    "sg:classifiers":[
        {
            "category":"Professional",
            "type":"Services"
        }
    ],
    "sg:phone":"+1 253 584 9548",
    "sg:postcode":"98499",
    "sg:province":"WA",
    "wof:name":"Peggs Company Inc",
    "wof:placetype":"venue"
},
  "geometry": {"coordinates":[-122.48962,47.172085],"type":"Point"}
}