{
  "type": "Feature",
  "properties": {
    "addr:full":"8115 Broadway Everett WA 98203",
    "addr:housenumber":"8115",
    "addr:postcode":"98203",
    "addr:street":"Broadway",
    "iso:country":"US",
    "sg:address":"8115 Broadway",
    "sg:city":"Everett",
    "sg:classifiers":[
        {
            "category":"Professional",
            "subcategory":"Management & Consulting",
            "type":"Services"
        }
    ],
    "sg:phone":"+1 425 347 0594",
    "sg:postcode":"98203",
    "sg:province":"WA",
    "wof:name":"Murray Property Management",
    "wof:placetype":"venue"
},
  "geometry": {"coordinates":[-122.202918,47.929917],"type":"Point"}
}