{
  "type": "Feature",
  "properties": {
    "addr:full":"625 Black Lake Blvd SW Olympia WA 98502",
    "addr:housenumber":"625",
    "addr:postcode":"98502",
    "addr:street":"Black Lake Blvd Sw",
    "iso:country":"US",
    "sg:address":"625 Black Lake Blvd SW",
    "sg:city":"Olympia",
    "sg:classifiers":[
        {
            "category":"Shopping",
            "subcategory":"Clothing, Apparel, & Fashions",
            "type":"Retail Goods"
        }
    ],
    "sg:phone":"+1 909 605 5016",
    "sg:postcode":"98502",
    "sg:province":"WA",
    "sg:tags":[
        "family"
    ],
    "wof:name":"Millers Outpost 172",
    "wof:placetype":"venue"
},
  "geometry": {"coordinates":[-122.928786,47.04239],"type":"Point"}
}