{
  "type": "Feature",
  "properties": {
    "addr:full":"7814 Fir Tree Ln Lake Stevens WA 98258",
    "addr:housenumber":"7814",
    "addr:postcode":"98258",
    "addr:street":"Fir Tree Ln",
    "iso:country":"US",
    "sg:address":"7814 Fir Tree Ln",
    "sg:city":"Lake Stevens",
    "sg:classifiers":[
        {
            "category":"Professional",
            "type":"Services"
        }
    ],
    "sg:phone":"+1 360 691 5641",
    "sg:postcode":"98258",
    "sg:province":"WA",
    "wof:name":"Exelens Service",
    "wof:placetype":"venue"
},
  "geometry": {"coordinates":[-122.030371,48.067558],"type":"Point"}
}