{
  "type": "Feature",
  "properties": {
    "addr:full":"625 Aloha Way Edmonds WA 98020",
    "addr:housenumber":"625",
    "addr:postcode":"98020",
    "addr:street":"Aloha Way",
    "iso:country":"US",
    "sg:address":"625 Aloha Way",
    "sg:city":"Edmonds",
    "sg:classifiers":[
        {
            "category":"Banks & Credit Unions",
            "subcategory":"Financial Services",
            "type":"Services"
        }
    ],
    "sg:phone":"+1 425 775 0594",
    "sg:postcode":"98020",
    "sg:province":"WA",
    "sg:tags":[
        "investor"
    ],
    "wof:name":"Hutchins Investments",
    "wof:placetype":"venue"
},
  "geometry": {"coordinates":[-122.374043,47.816165],"type":"Point"}
}