{
  "type": "Feature",
  "properties": {
    "addr:full":"27412 NE 29th Ave Ridgefield WA 98642",
    "addr:housenumber":"27412",
    "addr:postcode":"98642",
    "addr:street":"Ne 29Th Ave",
    "iso:country":"US",
    "sg:address":"27412 NE 29th Ave",
    "sg:city":"Ridgefield",
    "sg:classifiers":[
        {
            "category":"Real Estate",
            "subcategory":"Real Estate Operator",
            "type":"Services"
        }
    ],
    "sg:phone":"+1 360 887 4775",
    "sg:postcode":"98642",
    "sg:province":"WA",
    "sg:tags":[
        "apartment"
    ],
    "wof:name":"Walter Wenthin",
    "wof:placetype":"venue"
},
  "geometry": {"coordinates":[-122.640869,45.819456],"type":"Point"}
}