{
  "type": "Feature",
  "properties": {
    "addr:full":"5406 22nd Ave NW Seattle WA 98107",
    "addr:housenumber":"5406",
    "addr:postcode":"98107",
    "addr:street":"22Nd Ave Nw",
    "iso:country":"US",
    "sg:address":"5406 22nd Ave NW",
    "sg:city":"Seattle",
    "sg:classifiers":[
        {
            "category":"Manufacturing",
            "subcategory":"Glass & Minerals",
            "type":"Manufacturing & Wholesale Goods"
        },
        {
            "category":"Manufacturing",
            "subcategory":"Building Materials",
            "type":"Manufacturing & Wholesale Goods"
        }
    ],
    "sg:phone":"+1 206 706 7117",
    "sg:postcode":"98107",
    "sg:province":"WA",
    "sg:tags":[
        "plate",
        "repair",
        "glazier",
        "window",
        "replacement"
    ],
    "wof:name":"Coldworks",
    "wof:placetype":"venue"
},
  "geometry": {"coordinates":[-122.384801,47.667723],"type":"Point"}
}