{
  "type": "Feature",
  "properties": {
    "addr:full":"165 Ocean Lake Way SW Ocean Shores WA 98569",
    "addr:housenumber":"165",
    "addr:postcode":"98569",
    "addr:street":"Ocean Lake Way Sw",
    "iso:country":"US",
    "sg:address":"165 Ocean Lake Way SW",
    "sg:city":"Ocean Shores",
    "sg:classifiers":[
        {
            "category":"Government",
            "subcategory":"Office",
            "type":"Public Place"
        }
    ],
    "sg:phone":"+1 360 289 4210",
    "sg:postcode":"98569",
    "sg:province":"WA",
    "sg:tags":[
        "govt",
        "city"
    ],
    "wof:name":"Ocean Shores Water Treatment",
    "wof:placetype":"venue"
},
  "geometry": {"coordinates":[-124.163673,46.983751],"type":"Point"}
}