{
  "type": "Feature",
  "properties": {
    "addr:full":"3526 132nd St SW Lynnwood WA 98087",
    "addr:housenumber":"3526",
    "addr:postcode":"98087",
    "addr:street":"132Nd St Sw",
    "iso:country":"US",
    "sg:address":"3526 132nd St SW",
    "sg:city":"Lynnwood",
    "sg:classifiers":[
        {
            "category":"Real Estate",
            "subcategory":"Developer",
            "type":"Services"
        }
    ],
    "sg:phone":"+1 206 229 2693",
    "sg:postcode":"98087",
    "sg:province":"WA",
    "wof:name":"Harris Land Development",
    "wof:placetype":"venue"
},
  "geometry": {"coordinates":[-122.281177,47.879139],"type":"Point"}
}