{
  "type": "Feature",
  "properties": {
    "addr:full":"914 Washington St Port Townsend WA 98368",
    "addr:housenumber":"914",
    "addr:postcode":"98368",
    "addr:street":"Washington St",
    "iso:country":"US",
    "sg:address":"914 Washington St",
    "sg:city":"Port Townsend",
    "sg:classifiers":[
        {
            "category":"Professional",
            "subcategory":"Lawyer & Legal Services",
            "type":"Services"
        }
    ],
    "sg:phone":"+1 360 385 4399",
    "sg:postcode":"98368",
    "sg:province":"WA",
    "sg:tags":[
        "attorney"
    ],
    "wof:name":"Platt Irwin Taylor Law Firm",
    "wof:placetype":"venue"
},
  "geometry": {"coordinates":[-122.757295,48.11509],"type":"Point"}
}