{
  "type": "Feature",
  "properties": {
    "addr:full":"6114 Bock Ave Sumner WA 98390",
    "addr:postcode":"6114;98390",
    "addr:street":"Bock Ave",
    "iso:country":"US",
    "sg:address":"6114 Bock Ave",
    "sg:city":"Sumner",
    "sg:classifiers":[
        {
            "category":"Professional",
            "subcategory":"Advertising",
            "type":"Services"
        }
    ],
    "sg:phone":"+1 253 863 8397",
    "sg:postcode":"98390",
    "sg:province":"WA",
    "wof:name":"Sticky Situation",
    "wof:placetype":"venue"
},
  "geometry": {"coordinates":[-122.228403,47.201622],"type":"Point"}
}