{
  "type": "Feature",
  "properties": {
    "addr:full":"15118 Ok Mill Rd Snohomish WA 98290",
    "addr:housenumber":"15118",
    "addr:postcode":"98290",
    "addr:street":"Ok Mill Rd",
    "iso:country":"US",
    "sg:address":"15118 Ok Mill Rd",
    "sg:city":"Snohomish",
    "sg:classifiers":[
        {
            "category":"Wholesale",
            "subcategory":"Machinery & Supplies",
            "type":"Manufacturing & Wholesale Goods"
        }
    ],
    "sg:phone":"+1 425 334 5331",
    "sg:postcode":"98290",
    "sg:province":"WA",
    "sg:tags":[
        "pressure",
        "washing",
        "equipment"
    ],
    "wof:name":"F & P Svc",
    "wof:placetype":"venue"
},
  "geometry": {"coordinates":[-122.023565,47.993458],"type":"Point"}
}