{
  "type": "Feature",
  "properties": {
    "iso:country":"US",
    "sg:address":"755 Winslow Way E",
    "sg:city":"Bainbridge Isle",
    "sg:classifiers":[
        {
            "category":"Professional",
            "subcategory":"Lawyer & Legal Services",
            "type":"Services"
        }
    ],
    "sg:phone":"+1 206 855 4148",
    "sg:postcode":"98110",
    "sg:province":"WA",
    "sg:tags":[
        "attorney"
    ],
    "wof:name":"Michael L Jacob",
    "wof:placetype":"venue"
},
  "geometry": {"coordinates":[-122.510882,47.624786],"type":"Point"}
}