{
  "type": "Feature",
  "properties": {
    "addr:full":"10457 1st Ave S Seattle WA 98168",
    "addr:housenumber":"10457",
    "addr:postcode":"98168",
    "addr:street":"1St Ave S",
    "iso:country":"US",
    "sg:address":"10457 1st Ave S",
    "sg:city":"Seattle",
    "sg:classifiers":[
        {
            "category":"Building & Trades",
            "subcategory":"Construction",
            "type":"Services"
        }
    ],
    "sg:phone":"+1 206 241 7069",
    "sg:postcode":"98168",
    "sg:province":"WA",
    "sg:tags":[
        "contractor"
    ],
    "wof:name":"Executive Roofing & Cnstr",
    "wof:placetype":"venue"
},
  "geometry": {"coordinates":[-122.333702,47.509072],"type":"Point"}
}