{
  "type": "Feature",
  "properties": {
    "addr:full":"7304 259th Pl NE Redmond WA 98053",
    "addr:housenumber":"7304",
    "addr:postcode":"98053",
    "addr:street":"259Th Pl Ne",
    "iso:country":"US",
    "sg:address":"7304 259th Pl NE",
    "sg:city":"Redmond",
    "sg:classifiers":[
        {
            "category":"Building & Trades",
            "subcategory":"Construction",
            "type":"Services"
        }
    ],
    "sg:phone":"+1 425 898 0940",
    "sg:postcode":"98053",
    "sg:province":"WA",
    "sg:tags":[
        "general",
        "contractor"
    ],
    "wof:name":"Eastmont Homes Inc",
    "wof:placetype":"venue"
},
  "geometry": {"coordinates":[-121.99318,47.668616],"type":"Point"}
}