{
  "type": "Feature",
  "properties": {
    "addr:full":"1801 Center St Tacoma WA 98409",
    "addr:housenumber":"1801",
    "addr:postcode":"98409",
    "addr:street":"Center St",
    "iso:country":"US",
    "sg:address":"1801 Center St",
    "sg:city":"Tacoma",
    "sg:classifiers":[
        {
            "category":"Wholesale",
            "subcategory":"Machinery & Supplies",
            "type":"Manufacturing & Wholesale Goods"
        }
    ],
    "sg:phone":"+1 253 272 4203",
    "sg:postcode":"98409",
    "sg:province":"WA",
    "sg:tags":[
        "casket"
    ],
    "wof:name":"Puget Sound Casket Company",
    "wof:placetype":"venue"
},
  "geometry": {"coordinates":[-122.46157599999999,47.233854],"type":"Point"}
}