{
  "type": "Feature",
  "properties": {
    "iso:country":"US",
    "sg:address":"15709 Hwy 99",
    "sg:city":"Lynnwood",
    "sg:classifiers":[
        {
            "category":"Autos & Motor Vehicles",
            "subcategory":"Automobile Sales",
            "type":"Retail Goods"
        }
    ],
    "sg:phone":"+1 425 754 7675",
    "sg:postcode":"98087",
    "sg:province":"WA",
    "wof:name":"Kc Motors Inc",
    "wof:placetype":"venue"
},
  "geometry": {"coordinates":[-122.289717,47.856056],"type":"Point"}
}