{
  "type": "Feature",
  "properties": {
    "addr:full":"6116 211th St SW Lynnwood WA 98036",
    "addr:housenumber":"6116",
    "addr:postcode":"98036",
    "addr:street":"211Th St Sw",
    "iso:country":"US",
    "sg:address":"6116 211th St SW",
    "sg:city":"Lynnwood",
    "sg:classifiers":[
        {
            "category":"Manufacturing",
            "subcategory":"Tools & Machinery",
            "type":"Manufacturing & Wholesale Goods"
        }
    ],
    "sg:phone":"+1 425 672 1170",
    "sg:postcode":"98036",
    "sg:province":"WA",
    "sg:tags":[
        "equipment",
        "printing"
    ],
    "sg:website":"www.mgmgraphics.com",
    "wof:name":"MGM Graphics",
    "wof:placetype":"venue"
},
  "geometry": {"coordinates":[-122.317723,47.807605],"type":"Point"}
}