{
  "type": "Feature",
  "properties": {
    "addr:full":"16924 Juanita Dr NE Kenmore WA 98028",
    "addr:housenumber":"16924",
    "addr:postcode":"98028",
    "addr:street":"Juanita Dr Ne",
    "iso:country":"US",
    "sg:address":"16924 Juanita Dr NE",
    "sg:city":"Kenmore",
    "sg:classifiers":[
        {
            "category":"Cinema",
            "subcategory":"Movie Rental",
            "type":"Entertainment"
        }
    ],
    "sg:phone":"+1 425 483 6665",
    "sg:postcode":"98028",
    "sg:province":"WA",
    "sg:tags":[
        "video",
        "game",
        "leasing"
    ],
    "sg:website":"www.rocketdeals.com",
    "wof:name":"Famcom",
    "wof:placetype":"venue"
},
  "geometry": {"coordinates":[-122.249937,47.751458],"type":"Point"}
}