{
  "type": "Feature",
  "properties": {
    "addr:full":"1301 E 26th St Tacoma WA 98421",
    "addr:housenumber":"1301",
    "addr:postcode":"98421",
    "addr:street":"E 26Th St",
    "iso:country":"US",
    "sg:address":"1301 E 26th St",
    "sg:city":"Tacoma",
    "sg:classifiers":[
        {
            "category":"Wholesale",
            "subcategory":"Electrical",
            "type":"Manufacturing & Wholesale Goods"
        }
    ],
    "sg:phone":"+1 253 383 1606",
    "sg:postcode":"98421",
    "sg:province":"WA",
    "sg:tags":[
        "equipment",
        "electric",
        "supply"
    ],
    "sg:website":"www.northcoastelectric.com",
    "wof:name":"North Coast Electric Company",
    "wof:placetype":"venue"
},
  "geometry": {"coordinates":[-122.41085699999999,47.240587],"type":"Point"}
}