{
  "type": "Feature",
  "properties": {
    "addr:full":"2714 Grand Blvd Vancouver WA 98661",
    "addr:housenumber":"2714",
    "addr:postcode":"98661",
    "addr:street":"Grand Blvd",
    "iso:country":"US",
    "sg:address":"2714 Grand Blvd",
    "sg:city":"Vancouver",
    "sg:classifiers":[
        {
            "category":"Health Services",
            "subcategory":"Doctor",
            "type":"Services"
        }
    ],
    "sg:phone":"+1 360 694 9801",
    "sg:postcode":"98661",
    "sg:province":"WA",
    "sg:tags":[
        "surgeon",
        "oral"
    ],
    "wof:name":"John A Griffith DDS",
    "wof:placetype":"venue"
},
  "geometry": {"coordinates":[-122.641998,45.641201],"type":"Point"}
}