{
  "type": "Feature",
  "properties": {
    "addr:full":"5821 NE Fox Glove Ln Poulsbo WA 98370",
    "addr:housenumber":"5821",
    "addr:postcode":"98370",
    "addr:street":"Ne Fox Glove Ln",
    "iso:country":"US",
    "sg:address":"5821 NE Fox Glove Ln",
    "sg:city":"Poulsbo",
    "sg:classifiers":[
        {
            "category":"Building & Trades",
            "subcategory":"Construction",
            "type":"Services"
        }
    ],
    "sg:phone":"+1 360 697 1771",
    "sg:postcode":"98370",
    "sg:province":"WA",
    "sg:tags":[
        "contractor"
    ],
    "wof:name":"W I S Welding and Insptn Svcs",
    "wof:placetype":"venue"
},
  "geometry": {"coordinates":[-122.574213,47.777613],"type":"Point"}
}