{
  "type": "Feature",
  "properties": {
    "iso:country":"US",
    "sg:address":"7503 214th Ave E",
    "sg:city":"Sumner",
    "sg:classifiers":[
        {
            "category":"Restaurant",
            "type":"Food & Drink"
        }
    ],
    "sg:phone":"+1 253 826 7718",
    "sg:postcode":"98391",
    "sg:province":"WA",
    "sg:tags":[
        "eating"
    ],
    "wof:name":"Cubby Hole",
    "wof:placetype":"venue"
},
  "geometry": {"coordinates":[-122.14407,47.191348],"type":"Point"}
}