{
  "type": "Feature",
  "properties": {
    "addr:full":"101 W Galbreath Way Ritzville WA 99169",
    "addr:housenumber":"101",
    "addr:postcode":"99169",
    "addr:street":"W Galbreath Way",
    "iso:country":"US",
    "sg:address":"101 W Galbreath Way",
    "sg:city":"Ritzville",
    "sg:classifiers":[
        {
            "category":"Autos & Motor Vehicles",
            "subcategory":"Fuel & Gas Station",
            "type":"Retail Goods"
        },
        {
            "category":"Food & Beverages",
            "subcategory":"Groceries & Convenience Stores",
            "type":"Retail Goods"
        }
    ],
    "sg:phone":"+1 509 659 0530",
    "sg:postcode":"99169",
    "sg:province":"WA",
    "sg:website":"http://www.chevron.com/products/",
    "wof:name":"Chevron",
    "wof:placetype":"venue"
},
  "geometry": {"coordinates":[-118.368202,47.118172],"type":"Point"}
}