{
  "type": "Feature",
  "properties": {
    "addr:full":"620 Park Ave Bremerton WA 98337",
    "addr:housenumber":"620",
    "addr:postcode":"98337",
    "addr:street":"Park Ave",
    "iso:country":"US",
    "sg:address":"620 Park Ave",
    "sg:city":"Bremerton",
    "sg:classifiers":[
        {
            "category":"Banks & Credit Unions",
            "subcategory":"Bank",
            "type":"Services"
        }
    ],
    "sg:phone":"+1 360 405 5000",
    "sg:postcode":"98337",
    "sg:province":"WA",
    "sg:tags":[
        "loan",
        "real estate"
    ],
    "sg:website":"www.countrywide.com",
    "wof:name":"Countrywide Home Loans",
    "wof:placetype":"venue"
},
  "geometry": {"coordinates":[-122.630144,47.567872],"type":"Point"}
}