{
  "type": "Feature",
  "properties": {
    "addr:full":"514 Auburn Way N No Auburn WA 98002",
    "addr:housenumber":"514",
    "addr:postcode":"98002",
    "addr:street":"Auburn Way N No",
    "iso:country":"US",
    "sg:address":"514 Auburn Way N No",
    "sg:city":"Auburn",
    "sg:classifiers":[
        {
            "category":"Insurance",
            "subcategory":"Insurance Agent",
            "type":"Services"
        },
        {
            "category":"Insurance",
            "subcategory":"Hazard Insurance",
            "type":"Services"
        }
    ],
    "sg:phone":"+1 253 735 6747",
    "sg:postcode":"98002",
    "sg:province":"WA",
    "sg:tags":[
        "agriculture",
        "business",
        "auto",
        "recreational",
        "commercial",
        "casualty",
        "motorcycle",
        "vehicle",
        "property",
        "marine",
        "boat"
    ],
    "sg:website":"http://www.southsoundinsurance.com",
    "wof:name":"South Sound Insurance Inc",
    "wof:placetype":"venue"
},
  "geometry": {"coordinates":[-122.22599,47.312248],"type":"Point"}
}