{
  "type": "Feature",
  "properties": {
    "addr:full":"3209 S Howard St Spokane WA 99203",
    "addr:housenumber":"3209",
    "addr:postcode":"99203",
    "addr:street":"S Howard St",
    "iso:country":"US",
    "sg:address":"3209 S Howard St",
    "sg:city":"Spokane",
    "sg:classifiers":[
        {
            "category":"Wholesale",
            "subcategory":"Jewelry",
            "type":"Manufacturing & Wholesale Goods"
        }
    ],
    "sg:phone":"+1 509 456 8997",
    "sg:postcode":"99203",
    "sg:province":"WA",
    "sg:tags":[
        "stone",
        "general"
    ],
    "wof:name":"Jade Tree Importers",
    "wof:placetype":"venue"
},
  "geometry": {"coordinates":[-117.420136,47.625875],"type":"Point"}
}