{
  "type": "Feature",
  "properties": {
    "addr:full":"819 Sunnyside Blvd Everett WA 98205",
    "addr:housenumber":"819",
    "addr:postcode":"98205",
    "addr:street":"Sunnyside Blvd",
    "iso:country":"US",
    "sg:address":"819 Sunnyside Blvd",
    "sg:city":"Everett",
    "sg:classifiers":[
        {
            "category":"Wholesale",
            "subcategory":"Durable Goods & Equipment",
            "type":"Manufacturing & Wholesale Goods"
        }
    ],
    "sg:phone":"+1 425 335 7404",
    "sg:postcode":"98205",
    "sg:province":"WA",
    "wof:name":"Hidden Hill Antiques",
    "wof:placetype":"venue"
},
  "geometry": {"coordinates":[-122.12712500000001,47.997743],"type":"Point"}
}