{
  "type": "Feature",
  "properties": {
    "addr:full":"4822 Fowler Ave Everett WA 98203",
    "addr:housenumber":"4822",
    "addr:postcode":"98203",
    "addr:street":"Fowler Ave",
    "iso:country":"US",
    "sg:address":"4822 Fowler Ave",
    "sg:city":"Everett",
    "sg:classifiers":[
        {
            "category":"Food & Beverages",
            "subcategory":"Liquor & Beverages",
            "type":"Retail Goods"
        }
    ],
    "sg:phone":"+1 425 258 3117",
    "sg:postcode":"98203",
    "sg:province":"WA",
    "sg:tags":[
        "alcoholic"
    ],
    "wof:name":"Wicked Cellars",
    "wof:placetype":"venue"
},
  "geometry": {"coordinates":[-122.219542,47.953452],"type":"Point"}
}