{
  "type": "Feature",
  "properties": {
    "addr:full":"6710 124th Pl SE Snohomish WA 98296",
    "addr:housenumber":"6710",
    "addr:postcode":"98296",
    "addr:street":"124Th Pl Se",
    "iso:country":"US",
    "sg:address":"6710 124th Pl SE",
    "sg:city":"Snohomish",
    "sg:classifiers":[
        {
            "category":"Health Services",
            "subcategory":"Optometrist",
            "type":"Services"
        }
    ],
    "sg:phone":"+1 425 338 9426",
    "sg:postcode":"98296",
    "sg:province":"WA",
    "wof:name":"Maryjane T. Healey, Od, Ps",
    "wof:placetype":"venue"
},
  "geometry": {"coordinates":[-122.14259699999999,47.884348],"type":"Point"}
}