{
  "type": "Feature",
  "properties": {
    "addr:full":"10829 31st Ave SW Seattle WA 98146",
    "addr:housenumber":"10829",
    "addr:postcode":"98146",
    "addr:street":"31St Ave Sw",
    "iso:country":"US",
    "sg:address":"10829 31st Ave SW",
    "sg:city":"Seattle",
    "sg:classifiers":[
        {
            "category":"Building & Trades",
            "subcategory":"Construction",
            "type":"Services"
        }
    ],
    "sg:phone":"+1 206 244 5444",
    "sg:postcode":"98146",
    "sg:province":"WA",
    "sg:tags":[
        "residential",
        "contractor"
    ],
    "wof:name":"Kutz Construction Inc",
    "wof:placetype":"venue"
},
  "geometry": {"coordinates":[-122.372193,47.505542],"type":"Point"}
}