{
  "type": "Feature",
  "properties": {
    "addr:full":"12121 Northup Way Ste 205 Bellevue WA 98005",
    "addr:housenumber":"12121",
    "addr:postcode":"98005",
    "addr:street":"Northup Way Ste 205",
    "iso:country":"US",
    "sg:address":"12121 Northup Way Ste 205",
    "sg:city":"Bellevue",
    "sg:classifiers":[
        {
            "category":"Restaurant",
            "type":"Food & Drink"
        },
        {
            "category":"Bakery",
            "type":"Food & Drink"
        }
    ],
    "sg:phone":"+1 425 895 8899",
    "sg:postcode":"98005",
    "sg:province":"WA",
    "sg:tags":[
        "taiwanese",
        "chinese"
    ],
    "sg:website":"www.101yess.com",
    "wof:name":"101Yess",
    "wof:placetype":"venue"
},
  "geometry": {"coordinates":[-122.17876,47.630298],"type":"Point"}
}