{
  "type": "Feature",
  "properties": {
    "addr:full":"28004 S 887 Pr SE Kennewick WA 99338",
    "addr:housenumber":"28004",
    "addr:postcode":"99338",
    "addr:street":"S 887;Se",
    "iso:country":"US",
    "sg:address":"28004 S 887 Pr SE",
    "sg:city":"Kennewick",
    "sg:classifiers":[
        {
            "category":"Professional",
            "subcategory":"Management & Consulting",
            "type":"Services"
        }
    ],
    "sg:phone":"+1 509 627 1808",
    "sg:postcode":"99338",
    "sg:province":"WA",
    "sg:tags":[
        "consultant"
    ],
    "wof:name":"Northwest Construction Svcs",
    "wof:placetype":"venue"
},
  "geometry": {"coordinates":[-119.312589,46.168581],"type":"Point"}
}