{
  "type": "Feature",
  "properties": {
    "addr:full":"1104 Diagonal St Clarkston WA 99403",
    "addr:housenumber":"1104",
    "addr:postcode":"99403",
    "addr:street":"Diagonal St",
    "iso:country":"US",
    "sg:address":"1104 Diagonal St",
    "sg:city":"Clarkston",
    "sg:classifiers":[
        {
            "category":"Organizations",
            "subcategory":"Religious Organization",
            "type":"Services"
        }
    ],
    "sg:phone":"+1 509 758 0223",
    "sg:postcode":"99403",
    "sg:province":"WA",
    "sg:tags":[
        "churches-reformed"
    ],
    "wof:name":"Grace Reformed Church",
    "wof:placetype":"venue"
},
  "geometry": {"coordinates":[-117.052116,46.411752],"type":"Point"}
}