{
  "type": "Feature",
  "properties": {
    "iso:country":"US",
    "sg:address":"4338 Evanston Ave N",
    "sg:city":"Seattle",
    "sg:classifiers":[
        {
            "category":"Museum",
            "type":"Entertainment"
        }
    ],
    "sg:phone":"+1 206 527 0315",
    "sg:postcode":"98103",
    "sg:province":"WA",
    "sg:tags":[
        "gallery"
    ],
    "wof:name":"Bladegallery Co",
    "wof:placetype":"venue"
},
  "geometry": {"coordinates":[-122.350937,47.659726],"type":"Point"}
}