{
  "type": "Feature",
  "properties": {
    "addr:full":"250 W Dominion Ave Colville WA 99114",
    "addr:housenumber":"250",
    "addr:postcode":"99114",
    "addr:street":"W Dominion Ave",
    "iso:country":"US",
    "sg:address":"250 W Dominion Ave",
    "sg:city":"Colville",
    "sg:classifiers":[
        {
            "category":"Freight",
            "type":"Transportation"
        }
    ],
    "sg:phone":"+1 509 684 3401",
    "sg:postcode":"99114",
    "sg:province":"WA",
    "sg:tags":[
        "special"
    ],
    "wof:name":"Colville Custom Storage",
    "wof:placetype":"venue"
},
  "geometry": {"coordinates":[-117.907764,48.540361],"type":"Point"}
}