{
  "type": "Feature",
  "properties": {
    "addr:full":"13005 Camus Rd Anderson Island WA 98303",
    "addr:postcode":"13005;98303",
    "addr:street":"Camus Rd",
    "iso:country":"US",
    "sg:address":"13005 Camus Rd",
    "sg:city":"Anderson Island",
    "sg:classifiers":[
        {
            "category":"Education",
            "subcategory":"School",
            "type":"Public Place"
        }
    ],
    "sg:phone":"+1 253 884 4901",
    "sg:postcode":"98303",
    "sg:province":"WA",
    "wof:name":"Anderson Island Elem School",
    "wof:placetype":"venue"
},
  "geometry": {"coordinates":[-122.713291,47.16272],"type":"Point"}
}