{
  "type": "Feature",
  "properties": {
    "addr:full":"11840 194th Ave NE Redmond WA 98053",
    "addr:housenumber":"11840",
    "addr:postcode":"98053",
    "addr:street":"194Th Ave Ne",
    "iso:country":"US",
    "sg:address":"11840 194th Ave NE",
    "sg:city":"Redmond",
    "sg:classifiers":[
        {
            "category":"Building & Trades",
            "subcategory":"Construction",
            "type":"Services"
        }
    ],
    "sg:phone":"+1 425 885 4230",
    "sg:postcode":"98053",
    "sg:province":"WA",
    "sg:tags":[
        "house"
    ],
    "wof:name":"Natural Concepts Construction",
    "wof:placetype":"venue"
},
  "geometry": {"coordinates":[-122.081388,47.70395],"type":"Point"}
}