{
  "type": "Feature",
  "properties": {
    "iso:country":"US",
    "sg:address":"223 174th St S",
    "sg:city":"Spanaway",
    "sg:classifiers":[
        {
            "category":"Building & Trades",
            "subcategory":"Construction",
            "type":"Services"
        }
    ],
    "sg:phone":"+1 253 843 1562",
    "sg:postcode":"98387",
    "sg:province":"WA",
    "sg:tags":[
        "general",
        "contractor"
    ],
    "wof:name":"Grace Enterprises",
    "wof:placetype":"venue"
},
  "geometry": {"coordinates":[-122.435256,47.099381],"type":"Point"}
}