{
  "type": "Feature",
  "properties": {
    "iso:country":"US",
    "sg:address":"1456 Olney Ave E",
    "sg:city":"Port Orchard",
    "sg:classifiers":[
        {
            "category":"Food & Beverages",
            "subcategory":"Specialty",
            "type":"Retail Goods"
        }
    ],
    "sg:phone":"+1 360 874 9628",
    "sg:postcode":"98366",
    "sg:province":"WA",
    "sg:tags":[
        "health",
        "diet"
    ],
    "wof:name":"GNC",
    "wof:placetype":"venue"
},
  "geometry": {"coordinates":[-122.61243899999999,47.546653],"type":"Point"}
}