{
  "type": "Feature",
  "properties": {
    "addr:full":"13420 NE 16th St Bellevue WA 98005",
    "addr:housenumber":"13420",
    "addr:postcode":"98005",
    "addr:street":"Ne 16Th St",
    "iso:country":"US",
    "sg:address":"13420 NE 16th St",
    "sg:city":"Bellevue",
    "sg:classifiers":[
        {
            "category":"Autos & Motor Vehicles",
            "subcategory":"Automobile Sales",
            "type":"Retail Goods"
        }
    ],
    "sg:phone":"+1 425 643 0097",
    "sg:postcode":"98005",
    "sg:province":"WA",
    "sg:tags":[
        "car",
        "dealer"
    ],
    "wof:name":"Car Co Sales & Leasing",
    "wof:placetype":"venue"
},
  "geometry": {"coordinates":[-122.162097,47.624454],"type":"Point"}
}