{
  "type": "Feature",
  "properties": {
    "addr:full":"9758 NE 119th Way Kirkland WA 98034",
    "addr:housenumber":"9758",
    "addr:postcode":"98034",
    "addr:street":"Ne 119Th Way",
    "iso:country":"US",
    "sg:address":"9758 NE 119th Way",
    "sg:city":"Kirkland",
    "sg:classifiers":[
        {
            "category":"Restaurant",
            "type":"Food & Drink"
        }
    ],
    "sg:postcode":"98034",
    "sg:province":"WA",
    "sg:tags":[
        "pizza"
    ],
    "sg:website":"www.garlicjims.com",
    "wof:name":"Garlic Jim's",
    "wof:placetype":"venue"
},
  "geometry": {"coordinates":[-122.21132799999999,47.707043],"type":"Point"}
}