{
  "type": "Feature",
  "properties": {
    "addr:full":"2100 196th St SW Lynnwood WA 98036",
    "addr:housenumber":"2100",
    "addr:postcode":"98036",
    "addr:street":"196Th St Sw",
    "iso:country":"US",
    "sg:address":"2100 196th St SW",
    "sg:city":"Lynnwood",
    "sg:classifiers":[
        {
            "category":"Professional",
            "type":"Services"
        }
    ],
    "sg:phone":"+1 425 774 6969",
    "sg:postcode":"98036",
    "sg:province":"WA",
    "sg:tags":[
        "establishment"
    ],
    "wof:name":"ADEI",
    "wof:placetype":"venue"
},
  "geometry": {"coordinates":[-122.26183899999999,47.820545],"type":"Point"}
}