{
  "type": "Feature",
  "properties": {
    "addr:full":"3029 W Lake Sammamish Pkwy NE Redmond WA 98052",
    "addr:housenumber":"3029",
    "addr:postcode":"98052",
    "addr:street":"W Lake Sammamish Pkwy Ne",
    "iso:country":"US",
    "sg:address":"3029 W Lake Sammamish Pkwy NE",
    "sg:city":"Redmond",
    "sg:classifiers":[
        {
            "category":"Professional",
            "subcategory":"Art Services",
            "type":"Services"
        }
    ],
    "sg:phone":"+1 425 885 2249",
    "sg:postcode":"98052",
    "sg:province":"WA",
    "sg:tags":[
        "designer",
        "display",
        "producer"
    ],
    "wof:name":"Thor Lawson Design",
    "wof:placetype":"venue"
},
  "geometry": {"coordinates":[-122.093897,47.636564],"type":"Point"}
}