{
  "type": "Feature",
  "properties": {
    "addr:full":"757 Rainier Ave South Suite 5 Renton WA 98055",
    "addr:housenumber":"757",
    "addr:postcode":"98055",
    "addr:street":"Rainier Ave South Suite 5",
    "iso:country":"US",
    "sg:address":"757 Rainier Ave South Suite 5",
    "sg:city":"Renton",
    "sg:classifiers":[
        {
            "category":"Personal",
            "subcategory":"Beauty Salon",
            "type":"Services"
        },
        {
            "category":"Personal",
            "subcategory":"Tanning Parlor",
            "type":"Services"
        }
    ],
    "sg:phone":"+1 425 226 8988",
    "sg:postcode":"98055",
    "sg:province":"WA",
    "sg:tags":[
        "hair"
    ],
    "wof:name":"The Clipping Company & Tanning Salon",
    "wof:placetype":"venue"
},
  "geometry": {"coordinates":[-122.217365,47.472845],"type":"Point"}
}