{
  "type": "Feature",
  "properties": {
    "addr:full":"6108 NE Hwy 99 Vancouver WA 98665",
    "addr:housenumber":"6108",
    "addr:postcode":"98665",
    "addr:street":"Ne Hwy 99",
    "iso:country":"US",
    "sg:address":"6108 NE Hwy 99",
    "sg:city":"Vancouver",
    "sg:classifiers":[
        {
            "category":"Education",
            "subcategory":"Vocational School",
            "type":"Public Place"
        }
    ],
    "sg:phone":"+1 360 737 8022",
    "sg:postcode":"98665",
    "sg:province":"WA",
    "wof:name":"Fryar's Maritime Svc",
    "wof:placetype":"venue"
},
  "geometry": {"coordinates":[-122.664225,45.667278],"type":"Point"}
}