{
  "type": "Feature",
  "properties": {
    "addr:full":"8254 Hansen Rd NE Bainbridge Island WA 98110",
    "addr:housenumber":"8254",
    "addr:postcode":"98110",
    "addr:street":"Hansen Rd Ne",
    "iso:country":"US",
    "sg:address":"8254 Hansen Rd NE",
    "sg:city":"Bainbridge Island",
    "sg:classifiers":[
        {
            "category":"Shopping",
            "subcategory":"Used Merchandise",
            "type":"Retail Goods"
        }
    ],
    "sg:phone":"+1 206 842 2349",
    "sg:postcode":"98110",
    "sg:province":"WA",
    "wof:name":"Skybird Enterprises",
    "wof:placetype":"venue"
},
  "geometry": {"coordinates":[-122.574518,47.634451],"type":"Point"}
}