{
  "type": "Feature",
  "properties": {
    "addr:full":"106 N 101st St Seattle WA 98133",
    "addr:housenumber":"106",
    "addr:postcode":"98133",
    "addr:street":"N 101St St",
    "iso:country":"US",
    "sg:address":"106 N 101st St",
    "sg:city":"Seattle",
    "sg:classifiers":[
        {
            "category":"Marine",
            "type":"Transportation"
        }
    ],
    "sg:phone":"+1 206 283 0593",
    "sg:postcode":"98133",
    "sg:province":"WA",
    "sg:tags":[
        "haul",
        "boat",
        "out"
    ],
    "wof:name":"Salmon Bay Boatyard Inc",
    "wof:placetype":"venue"
},
  "geometry": {"coordinates":[-122.35547800000001,47.702258],"type":"Point"}
}