{
  "type": "Feature",
  "properties": {
    "addr:full":"2 Brim Rd Onalaska WA 98570",
    "addr:housenumber":"2",
    "addr:postcode":"98570",
    "addr:street":"Brim Rd",
    "iso:country":"US",
    "sg:address":"2 Brim Rd",
    "sg:city":"Onalaska",
    "sg:classifiers":[
        {
            "category":"Freight",
            "type":"Transportation"
        }
    ],
    "sg:phone":"+1 360 978 4015",
    "sg:postcode":"98570",
    "sg:province":"WA",
    "sg:tags":[
        "operator",
        "local",
        "trucking"
    ],
    "wof:name":"Woods Hauling",
    "wof:placetype":"venue"
},
  "geometry": {"coordinates":[-122.709734,46.503026],"type":"Point"}
}