{
  "type": "Feature",
  "properties": {
    "addr:full":"4814 N Walnut St Spokane WA 99205",
    "addr:housenumber":"4814",
    "addr:postcode":"99205",
    "addr:street":"N Walnut St",
    "iso:country":"US",
    "sg:address":"4814 N Walnut St",
    "sg:city":"Spokane",
    "sg:classifiers":[
        {
            "category":"Retail",
            "subcategory":"Auto Repair",
            "type":"Services"
        }
    ],
    "sg:phone":"+1 509 324 8136",
    "sg:postcode":"99205",
    "sg:province":"WA",
    "sg:tags":[
        "general"
    ],
    "wof:name":"C&M Mobile Auto Repair",
    "wof:placetype":"venue"
},
  "geometry": {"coordinates":[-117.433545,47.701514],"type":"Point"}
}