{
  "type": "Feature",
  "properties": {
    "addr:full":"820 Stanley Dr College Place WA 99324",
    "addr:housenumber":"820",
    "addr:postcode":"99324",
    "addr:street":"Stanley Dr",
    "iso:country":"US",
    "sg:address":"820 Stanley Dr",
    "sg:city":"College Place",
    "sg:classifiers":[
        {
            "category":"Building & Trades",
            "subcategory":"Construction",
            "type":"Services"
        }
    ],
    "sg:phone":"+1 509 525 2115",
    "sg:postcode":"99324",
    "sg:province":"WA",
    "sg:tags":[
        "residential"
    ],
    "wof:name":"Loomer Construction",
    "wof:placetype":"venue"
},
  "geometry": {"coordinates":[-118.40518,46.041543],"type":"Point"}
}