{
  "type": "Feature",
  "properties": {
    "iso:country":"US",
    "sg:address":"1401 SE Catalina Dr",
    "sg:city":"Oak Harbor",
    "sg:classifiers":[
        {
            "category":"Building & Trades",
            "subcategory":"Construction",
            "type":"Services"
        }
    ],
    "sg:phone":"+1 360 202 6543",
    "sg:postcode":"98277",
    "sg:province":"WA",
    "sg:tags":[
        "designer",
        "marine",
        "contractor"
    ],
    "wof:name":"On Board Marine",
    "wof:placetype":"venue"
},
  "geometry": {"coordinates":[-122.631916,48.287249],"type":"Point"}
}