{
  "type": "Feature",
  "properties": {
    "addr:full":"9122 S Tacoma Way Lakewood WA 98499",
    "addr:housenumber":"9122",
    "addr:postcode":"98499",
    "addr:street":"S Tacoma Way",
    "iso:country":"US",
    "sg:address":"9122 S Tacoma Way",
    "sg:city":"Lakewood",
    "sg:classifiers":[
        {
            "category":"Real Estate",
            "subcategory":"Real Estate Agent",
            "type":"Services"
        }
    ],
    "sg:phone":"+1 253 512 1004",
    "sg:postcode":"98499",
    "sg:province":"WA",
    "wof:name":"Sk Realty",
    "wof:placetype":"venue"
},
  "geometry": {"coordinates":[-122.483825,47.174096],"type":"Point"}
}