{
  "type": "Feature",
  "properties": {
    "addr:full":"9114 NE 106th St Vancouver WA 98662",
    "addr:housenumber":"9114",
    "addr:postcode":"98662",
    "addr:street":"Ne 106Th St",
    "iso:country":"US",
    "sg:address":"9114 NE 106th St",
    "sg:city":"Vancouver",
    "sg:classifiers":[
        {
            "category":"Wholesale",
            "subcategory":"Chemicals & Plastics",
            "type":"Manufacturing & Wholesale Goods"
        }
    ],
    "sg:phone":"+1 360 567 0404",
    "sg:postcode":"98662",
    "sg:province":"WA",
    "sg:tags":[
        "product",
        "polyurethane"
    ],
    "wof:name":"Polyfoam Solutions",
    "wof:placetype":"venue"
},
  "geometry": {"coordinates":[-122.57932700000001,45.698836],"type":"Point"}
}