{
  "type": "Feature",
  "properties": {
    "addr:full":"511 Washington St SE Olympia WA 98501",
    "addr:housenumber":"511",
    "addr:postcode":"98501",
    "addr:street":"Washington St Se",
    "iso:country":"US",
    "sg:address":"511 Washington St SE",
    "sg:city":"Olympia",
    "sg:classifiers":[
        {
            "category":"Personal",
            "subcategory":"Beauty Salon",
            "type":"Services"
        }
    ],
    "sg:phone":"+1 360 705 3111",
    "sg:postcode":"98501",
    "sg:province":"WA",
    "sg:tags":[
        "hair",
        "stylist"
    ],
    "wof:name":"Envy Hair Studio",
    "wof:placetype":"venue"
},
  "geometry": {"coordinates":[-122.900293,47.044077],"type":"Point"}
}