{
  "type": "Feature",
  "properties": {
    "addr:full":"18204 Bothell Everett Hwy Seunit C Bothell WA 98012",
    "addr:housenumber":"18204",
    "addr:postcode":"98012",
    "addr:street":"Bothell Everett Hwy Seunit C",
    "iso:country":"US",
    "sg:address":"18204 Bothell Everett Hwy Seunit C",
    "sg:city":"Bothell",
    "sg:phone":"+1 425 481 5101",
    "sg:postcode":"98012",
    "sg:province":"WA",
    "sg:website":"http://www.napaautoparts.com",
    "wof:name":"North Creek Auto Parts",
    "wof:placetype":"venue"
},
  "geometry": {"coordinates":[-122.209236,47.83245],"type":"Point"}
}