{
  "type": "Feature",
  "properties": {
    "addr:full":"4756 155th Pl SE Bellevue WA 98006",
    "addr:housenumber":"4756",
    "addr:postcode":"98006",
    "addr:street":"155Th Pl Se",
    "iso:country":"US",
    "sg:address":"4756 155th Pl SE",
    "sg:city":"Bellevue",
    "sg:classifiers":[
        {
            "category":"Organizations",
            "subcategory":"Community Association",
            "type":"Services"
        }
    ],
    "sg:phone":"+1 425 643 9354",
    "sg:postcode":"98006",
    "sg:province":"WA",
    "wof:name":"Westlake Shores Homeowner",
    "wof:placetype":"venue"
},
  "geometry": {"coordinates":[-122.132454,47.561062],"type":"Point"}
}