{
  "type": "Feature",
  "properties": {
    "addr:full":"33915 53rd Ave S Auburn WA 98001",
    "addr:housenumber":"33915",
    "addr:postcode":"98001",
    "addr:street":"53Rd Ave S",
    "iso:country":"US",
    "sg:address":"33915 53rd Ave S",
    "sg:city":"Auburn",
    "sg:classifiers":[
        {
            "category":"Professional",
            "subcategory":"Art Services",
            "type":"Services"
        }
    ],
    "sg:phone":"+1 253 653 4442",
    "sg:postcode":"98001",
    "sg:province":"WA",
    "sg:tags":[
        "photographer"
    ],
    "sg:website":"www.constructionsitephotos.com",
    "wof:name":"CONSTRUCTIONSITEPHOTOS.COM",
    "wof:placetype":"venue"
},
  "geometry": {"coordinates":[-122.268653,47.298278],"type":"Point"}
}