{
  "type": "Feature",
  "properties": {
    "addr:full":"601 W State St Aberdeen WA 98520",
    "addr:housenumber":"601",
    "addr:postcode":"98520",
    "addr:street":"W State St",
    "iso:country":"US",
    "sg:address":"601 W State St",
    "sg:city":"Aberdeen",
    "sg:classifiers":[
        {
            "category":"Building & Trades",
            "subcategory":"Construction",
            "type":"Services"
        }
    ],
    "sg:phone":"+1 360 533 6141",
    "sg:postcode":"98520",
    "sg:province":"WA",
    "sg:tags":[
        "general",
        "contractor"
    ],
    "wof:name":"Evergreen Environmental Inc",
    "wof:placetype":"venue"
},
  "geometry": {"coordinates":[-123.822097,46.969656],"type":"Point"}
}