{
  "type": "Feature",
  "properties": {
    "addr:full":"5134 S Willow St Seattle WA 98118",
    "addr:housenumber":"5134",
    "addr:postcode":"98118",
    "addr:street":"S Willow St",
    "iso:country":"US",
    "sg:address":"5134 S Willow St",
    "sg:city":"Seattle",
    "sg:classifiers":[
        {
            "category":"Professional",
            "subcategory":"Business Services",
            "type":"Services"
        }
    ],
    "sg:phone":"+1 206 725 6926",
    "sg:postcode":"98118",
    "sg:province":"WA",
    "wof:name":"Elizabeth C Walker Business",
    "wof:placetype":"venue"
},
  "geometry": {"coordinates":[-122.267813,47.540766],"type":"Point"}
}