{
  "type": "Feature",
  "properties": {
    "iso:country":"US",
    "sg:address":"1308 14th St",
    "sg:city":"Port Townsend",
    "sg:classifiers":[
        {
            "category":"Professional",
            "subcategory":"Computer Services",
            "type":"Services"
        }
    ],
    "sg:phone":"+1 360 385 4234",
    "sg:postcode":"98368",
    "sg:province":"WA",
    "sg:tags":[
        "repair"
    ],
    "wof:name":"Computer Coaching Solutions",
    "wof:placetype":"venue"
},
  "geometry": {"coordinates":[-122.792524,48.110107],"type":"Point"}
}