{
  "type": "Feature",
  "properties": {
    "addr:full":"4006 Black Diamond Rd Port Angeles WA 98363",
    "addr:housenumber":"4006",
    "addr:postcode":"98363",
    "addr:street":"Black Diamond Rd",
    "iso:country":"US",
    "sg:address":"4006 Black Diamond Rd",
    "sg:city":"Port Angeles",
    "sg:classifiers":[
        {
            "category":"Manufacturing",
            "subcategory":"Lumber",
            "type":"Manufacturing & Wholesale Goods"
        }
    ],
    "sg:phone":"+1 360 452 2661",
    "sg:postcode":"98363",
    "sg:province":"WA",
    "sg:tags":[
        "operation",
        "timber",
        "tract"
    ],
    "wof:name":"Dennis Shore",
    "wof:placetype":"venue"
},
  "geometry": {"coordinates":[-123.49895600000001,48.058513],"type":"Point"}
}