{
  "type": "Feature",
  "properties": {
    "addr:full":"25171 State Rte 525 Greenbank WA 98253",
    "addr:housenumber":"25171",
    "addr:postcode":"98253",
    "addr:street":"State Rte 525 Greenbank",
    "iso:country":"US",
    "sg:address":"25171 State Rte 525",
    "sg:city":"Greenbank",
    "sg:classifiers":[
        {
            "category":"Real Estate",
            "subcategory":"Real Estate Agent",
            "type":"Services"
        }
    ],
    "sg:phone":"+1 360 678 5690",
    "sg:postcode":"98253",
    "sg:province":"WA",
    "wof:name":"Loganberry Hill Realty",
    "wof:placetype":"venue"
},
  "geometry": {"coordinates":[-122.573978,48.099757],"type":"Point"}
}