{
  "type": "Feature",
  "properties": {
    "addr:full":"2100 Western Ave Apt 46 Seattle WA 98121",
    "addr:housenumber":"2100;46",
    "addr:postcode":"98121",
    "addr:street":"Western Ave Apt",
    "iso:country":"US",
    "sg:address":"2100 Western Ave Apt 46",
    "sg:city":"Seattle",
    "sg:classifiers":[
        {
            "category":"Real Estate",
            "subcategory":"Real Estate Operator",
            "type":"Services"
        }
    ],
    "sg:phone":"+1 206 441 9191",
    "sg:postcode":"98121",
    "sg:province":"WA",
    "sg:tags":[
        "apartment"
    ],
    "wof:name":"Ventana At The Market",
    "wof:placetype":"venue"
},
  "geometry": {"coordinates":[-122.34478799999999,47.611179],"type":"Point"}
}