{
  "type": "Feature",
  "properties": {
    "addr:full":"30601 NE 172nd Ave Yacolt WA 98675",
    "addr:housenumber":"30601",
    "addr:postcode":"98675",
    "addr:street":"Ne 172Nd Ave",
    "iso:country":"US",
    "sg:address":"30601 NE 172nd Ave",
    "sg:city":"Yacolt",
    "sg:classifiers":[
        {
            "category":"Organizations",
            "subcategory":"Religious Organization",
            "type":"Services"
        }
    ],
    "sg:phone":"+1 360 687 1354",
    "sg:postcode":"98675",
    "sg:province":"WA",
    "wof:name":"North Country Church",
    "wof:placetype":"venue"
},
  "geometry": {"coordinates":[-122.495476,45.840661],"type":"Point"}
}