{
  "type": "Feature",
  "properties": {
    "addr:full":"5320 Roosevelt Way NE Seattle WA 98105",
    "addr:housenumber":"5320",
    "addr:postcode":"98105",
    "addr:street":"Roosevelt Way Ne",
    "iso:country":"US",
    "sg:address":"5320 Roosevelt Way NE",
    "sg:city":"Seattle",
    "sg:classifiers":[
        {
            "category":"Arts & Performance",
            "subcategory":"Art Gallery",
            "type":"Entertainment"
        },
        {
            "category":"Shopping",
            "subcategory":"Crafts & Fabrics",
            "type":"Retail Goods"
        },
        {
            "category":"Professional",
            "subcategory":"Art Services",
            "type":"Services"
        }
    ],
    "sg:phone":"+1 206 522 2011",
    "sg:postcode":"98105",
    "sg:province":"WA",
    "sg:tags":[
        "picture",
        "instruction",
        "consultant",
        "frame",
        "galleries"
    ],
    "sg:website":"www.kirstengallery.com/index.htm",
    "wof:name":"Kirsten Gallery",
    "wof:placetype":"venue"
},
  "geometry": {"coordinates":[-122.317001,47.6675],"type":"Point"}
}