{
  "type": "Feature",
  "properties": {
    "addr:full":"551 S Michigan St Seattle WA 98108",
    "addr:housenumber":"551",
    "addr:postcode":"98108",
    "addr:street":"S Michigan St",
    "iso:country":"US",
    "sg:address":"551 S Michigan St",
    "sg:city":"Seattle",
    "sg:classifiers":[
        {
            "category":"Retail",
            "subcategory":"Car Wash",
            "type":"Services"
        }
    ],
    "sg:phone":"+1 206 762 9492",
    "sg:postcode":"98108",
    "sg:province":"WA",
    "sg:tags":[
        "polishing",
        "washing"
    ],
    "wof:name":"Akaal Investors",
    "wof:placetype":"venue"
},
  "geometry": {"coordinates":[-122.327003,47.5462],"type":"Point"}
}