{
  "type": "Feature",
  "properties": {
    "addr:full":"18512 Ballinger Way NE Seattle WA 98155",
    "addr:housenumber":"18512",
    "addr:postcode":"98155",
    "addr:street":"Ballinger Way Ne",
    "iso:country":"US",
    "sg:address":"18512 Ballinger Way NE",
    "sg:city":"Seattle",
    "sg:classifiers":[
        {
            "category":"Social Services",
            "subcategory":"Child Care",
            "type":"Services"
        }
    ],
    "sg:phone":"+1 206 362 6519",
    "sg:postcode":"98155",
    "sg:province":"WA",
    "sg:tags":[
        "day"
    ],
    "wof:name":"Lake Frest Pk Wiz Kids Academy",
    "wof:placetype":"venue"
},
  "geometry": {"coordinates":[-122.292678,47.763378],"type":"Point"}
}