{
  "type": "Feature",
  "properties": {
    "addr:full":"922 Peace Portal Dr Blaine WA 98230",
    "addr:housenumber":"922",
    "addr:postcode":"98230",
    "addr:street":"Peace Portal Dr",
    "iso:country":"US",
    "sg:address":"922 Peace Portal Dr",
    "sg:city":"Blaine",
    "sg:classifiers":[
        {
            "category":"Travel",
            "subcategory":"Hotels & Motels",
            "type":"Entertainment"
        }
    ],
    "sg:phone":"+1 360 332 8400",
    "sg:postcode":"98230",
    "sg:province":"WA",
    "sg:tags":[
        "operation"
    ],
    "wof:name":"Pendergrast Beach House",
    "wof:placetype":"venue"
},
  "geometry": {"coordinates":[-122.751513,48.990986],"type":"Point"}
}