{
  "type": "Feature",
  "properties": {
    "iso:country":"US",
    "sg:address":"15001 NE 181st St",
    "sg:city":"Brush Prairie",
    "sg:classifiers":[
        {
            "category":"Sports & Exercise",
            "subcategory":"Golf",
            "type":"Entertainment"
        }
    ],
    "sg:phone":"+1 360 687 4233",
    "sg:postcode":"98606",
    "sg:province":"WA",
    "sg:tags":[
        "course"
    ],
    "wof:name":"Cedars On Salmon Creek",
    "wof:placetype":"venue"
},
  "geometry": {"coordinates":[-122.518863,45.753326],"type":"Point"}
}