{
  "type": "Feature",
  "properties": {
    "addr:full":"12707 182nd Ave SE Snohomish WA 98290",
    "addr:housenumber":"12707",
    "addr:postcode":"98290",
    "addr:street":"182Nd Ave Se",
    "iso:country":"US",
    "sg:address":"12707 182nd Ave SE",
    "sg:city":"Snohomish",
    "sg:classifiers":[
        {
            "category":"Personal",
            "subcategory":"Beauty Salon",
            "type":"Services"
        }
    ],
    "sg:phone":"+1 360 794 9472",
    "sg:postcode":"98290",
    "sg:province":"WA",
    "sg:tags":[
        "shop"
    ],
    "wof:name":"Greater Lengths",
    "wof:placetype":"venue"
},
  "geometry": {"coordinates":[-121.986946,47.883067],"type":"Point"}
}