{
  "type": "Feature",
  "properties": {
    "addr:full":"1814 Hewitt Ave Everett WA 98201",
    "addr:housenumber":"1814",
    "addr:postcode":"98201",
    "addr:street":"Hewitt Ave",
    "iso:country":"US",
    "sg:address":"1814 Hewitt Ave",
    "sg:city":"Everett",
    "sg:classifiers":[
        {
            "category":"Professional",
            "subcategory":"Computer Services",
            "type":"Services"
        }
    ],
    "sg:phone":"+1 425 257 1054",
    "sg:postcode":"98201",
    "sg:province":"WA",
    "sg:tags":[
        "datum"
    ],
    "wof:name":"Image Master",
    "wof:placetype":"venue"
},
  "geometry": {"coordinates":[-122.20454700000001,47.979162],"type":"Point"}
}