{
  "type": "Feature",
  "properties": {
    "addr:full":"14651 NE 179th St Woodinville WA 98072",
    "addr:housenumber":"14651",
    "addr:postcode":"98072",
    "addr:street":"Ne 179Th St",
    "iso:country":"US",
    "sg:address":"14651 NE 179th St",
    "sg:city":"Woodinville",
    "sg:classifiers":[
        {
            "category":"Real Estate",
            "subcategory":"Real Estate Agent",
            "type":"Services"
        }
    ],
    "sg:phone":"+1 425 483 1891",
    "sg:postcode":"98072",
    "sg:province":"WA",
    "wof:name":"Roskind Appraisal Service",
    "wof:placetype":"venue"
},
  "geometry": {"coordinates":[-122.144676,47.757419],"type":"Point"}
}