{
  "type": "Feature",
  "properties": {
    "addr:full":"17009 Alpine Dr E Enumclaw WA 98022",
    "addr:housenumber":"17009",
    "addr:postcode":"98022",
    "addr:street":"Alpine Dr E",
    "iso:country":"US",
    "sg:address":"17009 Alpine Dr E",
    "sg:city":"Enumclaw",
    "sg:classifiers":[
        {
            "category":"Professional",
            "subcategory":"Accounting & Tax Preparation",
            "type":"Services"
        }
    ],
    "sg:phone":"+1 360 663 2626",
    "sg:postcode":"98022",
    "sg:province":"WA",
    "sg:tags":[
        "return"
    ],
    "wof:name":"Business Svc/Taxes",
    "wof:placetype":"venue"
},
  "geometry": {"coordinates":[-121.601724,47.103304],"type":"Point"}
}