{
  "type": "Feature",
  "properties": {
    "addr:full":"5105 Idaho St Vancouver WA 98661",
    "addr:housenumber":"5105",
    "addr:postcode":"98661",
    "addr:street":"Idaho St",
    "iso:country":"US",
    "sg:address":"5105 Idaho St",
    "sg:city":"Vancouver",
    "sg:classifiers":[
        {
            "category":"Retail",
            "subcategory":"Repair Shop",
            "type":"Services"
        }
    ],
    "sg:phone":"+1 360 573 2527",
    "sg:postcode":"98661",
    "sg:province":"WA",
    "wof:name":"Homepoate Heroes",
    "wof:placetype":"venue"
},
  "geometry": {"coordinates":[-122.616936,45.630766],"type":"Point"}
}