{
  "type": "Feature",
  "properties": {
    "addr:full":"1805 NE 86th St Vancouver WA 98665",
    "addr:housenumber":"1805",
    "addr:postcode":"98665",
    "addr:street":"Ne 86Th St",
    "iso:country":"US",
    "sg:address":"1805 NE 86th St",
    "sg:city":"Vancouver",
    "sg:classifiers":[
        {
            "category":"Professional",
            "type":"Services"
        }
    ],
    "sg:phone":"+1 360 574 3916",
    "sg:postcode":"98665",
    "sg:province":"WA",
    "wof:name":"Keith M Spain",
    "wof:placetype":"venue"
},
  "geometry": {"coordinates":[-122.653054,45.684387],"type":"Point"}
}