{
  "type": "Feature",
  "properties": {
    "addr:full":"4122 Factoria Blvd Suite 401 Bellevue WA 98006",
    "addr:housenumber":"4122",
    "addr:postcode":"98006",
    "addr:street":"Factoria Blvd Suite 401",
    "iso:country":"US",
    "sg:address":"4122 Factoria Blvd Suite 401",
    "sg:city":"Bellevue",
    "sg:classifiers":[
        {
            "category":"Health Services",
            "subcategory":"Doctor",
            "type":"Services"
        }
    ],
    "sg:phone":"+1 425 562 1920",
    "sg:postcode":"98006",
    "sg:province":"WA",
    "sg:website":"myphysiobellevue.com",
    "wof:name":"Physiotherapy Associates",
    "wof:placetype":"venue"
},
  "geometry": {"coordinates":[-122.169296,47.571629],"type":"Point"}
}