{
  "type": "Feature",
  "properties": {
    "addr:full":"1200 W Fourth Plain Blvd Vancouver WA 98660",
    "addr:housenumber":"1200",
    "addr:postcode":"98660",
    "addr:street":"W Fourth Plain Blvd",
    "iso:country":"US",
    "sg:address":"1200 W Fourth Plain Blvd",
    "sg:city":"Vancouver",
    "sg:classifiers":[
        {
            "category":"Professional",
            "type":"Services"
        },
        {
            "category":"Retail",
            "subcategory":"Auto Rental",
            "type":"Services"
        },
        {
            "category":"Building & Trades",
            "subcategory":"Equipment Rental",
            "type":"Services"
        },
        {
            "category":"Retail",
            "subcategory":"Storage",
            "type":"Services"
        }
    ],
    "sg:phone":"+1 866 205 7339",
    "sg:postcode":"98660",
    "sg:province":"WA",
    "sg:tags":[
        "renting",
        "moving-self",
        "leasing",
        "material",
        "moving",
        "services-labor",
        "truck",
        "trailer"
    ],
    "sg:website":"http://www.pensketruckrental.com/personal_rental/?cid=Yptmlist",
    "wof:name":"Penske Truck Rental",
    "wof:placetype":"venue"
},
  "geometry": {"coordinates":[-122.683189,45.640259],"type":"Point"}
}