{
  "type": "Feature",
  "properties": {
    "addr:full":"378 Malott Eastside Rd Malott WA 98829",
    "addr:housenumber":"378",
    "addr:postcode":"98829",
    "addr:street":"Malott Eastside Rd",
    "iso:country":"US",
    "sg:address":"378 Malott Eastside Rd",
    "sg:city":"Malott",
    "sg:classifiers":[
        {
            "category":"Building & Trades",
            "subcategory":"Electrical",
            "type":"Services"
        }
    ],
    "sg:phone":"+1 509 422 5644",
    "sg:postcode":"98829",
    "sg:province":"WA",
    "sg:tags":[
        "electric",
        "contractor"
    ],
    "wof:name":"Ideal Electric Co",
    "wof:placetype":"venue"
},
  "geometry": {"coordinates":[-119.725543,48.231021],"type":"Point"}
}