{
  "type": "Feature",
  "properties": {
    "addr:full":"1140 Monroe Landing Rd Oak Harbor WA 98277",
    "addr:housenumber":"1140",
    "addr:postcode":"98277",
    "addr:street":"Monroe Landing Rd",
    "iso:country":"US",
    "sg:address":"1140 Monroe Landing Rd",
    "sg:city":"Oak Harbor",
    "sg:classifiers":[
        {
            "category":"Professional",
            "type":"Services"
        }
    ],
    "sg:phone":"+1 360 679 1065",
    "sg:postcode":"98277",
    "sg:province":"WA",
    "wof:name":"Air International LLC",
    "wof:placetype":"venue"
},
  "geometry": {"coordinates":[-122.680581,48.249294],"type":"Point"}
}