{
  "type": "Feature",
  "properties": {
    "iso:country":"US",
    "sg:address":"1109 N 36th St",
    "sg:city":"Seattle",
    "sg:classifiers":[
        {
            "category":"Manufacturing",
            "subcategory":"Textiles",
            "type":"Manufacturing & Wholesale Goods"
        }
    ],
    "sg:phone":"+1 206 632 9037",
    "sg:postcode":"98103",
    "sg:province":"WA",
    "sg:tags":[
        "sweater",
        "mfg"
    ],
    "wof:name":"Norris Knitting Company Inc",
    "wof:placetype":"venue"
},
  "geometry": {"coordinates":[-122.34354399999999,47.650464],"type":"Point"}
}