{
  "type": "Feature",
  "properties": {
    "addr:full":"4010 Woodbrook Dr SW Lakewood WA 98439",
    "addr:housenumber":"4010",
    "addr:postcode":"98439",
    "addr:street":"Woodbrook Dr Sw",
    "iso:country":"US",
    "sg:address":"4010 Woodbrook Dr SW",
    "sg:city":"Lakewood",
    "sg:classifiers":[
        {
            "category":"Education",
            "subcategory":"School",
            "type":"Public Place"
        }
    ],
    "sg:phone":"+1 253 583 5270",
    "sg:postcode":"98439",
    "sg:province":"WA",
    "sg:tags":[
        "high",
        "middle",
        "elementary"
    ],
    "wof:name":"Clover Park School District 400",
    "wof:placetype":"venue"
},
  "geometry": {"coordinates":[-122.52800000000001,47.127399],"type":"Point"}
}