{
  "type": "Feature",
  "properties": {
    "addr:full":"4612 182nd Pl SW Lynnwood WA 98037",
    "addr:housenumber":"4612",
    "addr:postcode":"98037",
    "addr:street":"182Nd Pl Sw",
    "iso:country":"US",
    "sg:address":"4612 182nd Pl SW",
    "sg:city":"Lynnwood",
    "sg:classifiers":[
        {
            "category":"Professional",
            "type":"Services"
        }
    ],
    "sg:phone":"+1 425 771 3303",
    "sg:postcode":"98037",
    "sg:province":"WA",
    "wof:name":"Araki Takaharu",
    "wof:placetype":"venue"
},
  "geometry": {"coordinates":[-122.29515000000001,47.8331],"type":"Point"}
}