{
  "type": "Feature",
  "properties": {
    "addr:full":"536 E Wellesley Ave Spokane WA 99207",
    "addr:housenumber":"536",
    "addr:postcode":"99207",
    "addr:street":"E Wellesley Ave",
    "iso:country":"US",
    "sg:address":"536 E Wellesley Ave",
    "sg:city":"Spokane",
    "sg:classifiers":[
        {
            "category":"Professional",
            "type":"Services"
        }
    ],
    "sg:phone":"+1 509 484 9445",
    "sg:postcode":"99207",
    "sg:province":"WA",
    "wof:name":"Executive PC Services",
    "wof:placetype":"venue"
},
  "geometry": {"coordinates":[-117.401371,47.700592],"type":"Point"}
}