{
  "type": "Feature",
  "properties": {
    "addr:full":"3012 NE 127th St Seattle WA 98125",
    "addr:housenumber":"3012",
    "addr:postcode":"98125",
    "addr:street":"Ne 127Th St",
    "iso:country":"US",
    "sg:address":"3012 NE 127th St",
    "sg:city":"Seattle",
    "sg:classifiers":[
        {
            "category":"Shopping",
            "subcategory":"Discount & Variety Stores",
            "type":"Retail Goods"
        }
    ],
    "sg:phone":"+1 206 368 3937",
    "sg:postcode":"98125",
    "sg:province":"WA",
    "wof:name":"Ninety Nine Cents Etc",
    "wof:placetype":"venue"
},
  "geometry": {"coordinates":[-122.295216,47.721084],"type":"Point"}
}