{
  "type": "Feature",
  "properties": {
    "iso:country":"US",
    "sg:address":"486 Alamo Way",
    "sg:city":"Oak Harbor",
    "sg:classifiers":[
        {
            "category":"Organizations",
            "subcategory":"Membership Organization",
            "type":"Services"
        }
    ],
    "sg:phone":"+1 360 679 6962",
    "sg:postcode":"98277",
    "sg:province":"WA",
    "wof:name":"Camp Hacienda Water Assn",
    "wof:placetype":"venue"
},
  "geometry": {"coordinates":[-122.618634,48.375879],"type":"Point"}
}