{
  "type": "Feature",
  "properties": {
    "addr:full":"1517 12th Ave Seattle WA 98122",
    "addr:housenumber":"1517",
    "addr:postcode":"98122",
    "addr:street":"12Th Ave",
    "iso:country":"US",
    "sg:address":"1517 12th Ave",
    "sg:city":"Seattle",
    "sg:classifiers":[
        {
            "category":"Arts & Performance",
            "subcategory":"Music",
            "type":"Entertainment"
        }
    ],
    "sg:phone":"+1 206 860 5185",
    "sg:postcode":"98122",
    "sg:province":"WA",
    "sg:tags":[
        "musician"
    ],
    "sg:website":"http://www.moscozzi.com",
    "wof:name":"Moscozzi Music",
    "wof:placetype":"venue"
},
  "geometry": {"coordinates":[-122.316836,47.614295],"type":"Point"}
}