{
  "type": "Feature",
  "properties": {
    "addr:full":"17607 32nd Ave E Tacoma WA 98446",
    "addr:housenumber":"17607",
    "addr:postcode":"98446",
    "addr:street":"32Nd Ave E",
    "iso:country":"US",
    "sg:address":"17607 32nd Ave E",
    "sg:city":"Tacoma",
    "sg:classifiers":[
        {
            "category":"Professional",
            "subcategory":"Lawyer & Legal Services",
            "type":"Services"
        }
    ],
    "sg:phone":"+1 253 847 3631",
    "sg:postcode":"98446",
    "sg:province":"WA",
    "wof:name":"Richard C Brawley Attorney",
    "wof:placetype":"venue"
},
  "geometry": {"coordinates":[-122.386228,47.096659],"type":"Point"}
}