{
  "type": "Feature",
  "properties": {
    "addr:full":"1611 116th Ave NE Bellevue WA 98004",
    "addr:housenumber":"1611",
    "addr:postcode":"98004",
    "addr:street":"116Th Ave Ne",
    "iso:country":"US",
    "sg:address":"1611 116th Ave NE",
    "sg:city":"Bellevue",
    "sg:classifiers":[
        {
            "category":"Shopping",
            "subcategory":"Computers & Home Electronics",
            "type":"Retail Goods"
        }
    ],
    "sg:phone":"+1 425 646 4960",
    "sg:postcode":"98004",
    "sg:province":"WA",
    "sg:tags":[
        "software"
    ],
    "wof:name":"Ddim Inc",
    "wof:placetype":"venue"
},
  "geometry": {"coordinates":[-122.185742,47.624581],"type":"Point"}
}