{
  "type": "Feature",
  "properties": {
    "addr:full":"125 3rd St NE Auburn WA 98002",
    "addr:housenumber":"125",
    "addr:postcode":"98002",
    "addr:street":"3Rd St Ne",
    "iso:country":"US",
    "sg:address":"125 3rd St NE",
    "sg:city":"Auburn",
    "sg:classifiers":[
        {
            "category":"Health Services",
            "subcategory":"Doctor",
            "type":"Services"
        }
    ],
    "sg:phone":"+1 253 735 1400",
    "sg:postcode":"98002",
    "sg:province":"WA",
    "sg:tags":[
        "medical"
    ],
    "wof:name":"Sports Medicine and Hand Ctr",
    "wof:placetype":"venue"
},
  "geometry": {"coordinates":[-122.227986,47.310239],"type":"Point"}
}