{
  "type": "Feature",
  "properties": {
    "addr:full":"18333 85th Pl W Edmonds WA 98026",
    "addr:housenumber":"18333",
    "addr:postcode":"98026",
    "addr:street":"85Th Pl W",
    "iso:country":"US",
    "sg:address":"18333 85th Pl W",
    "sg:city":"Edmonds",
    "sg:classifiers":[
        {
            "category":"Building & Trades",
            "subcategory":"Construction",
            "type":"Services"
        }
    ],
    "sg:phone":"+1 425 670 3669",
    "sg:postcode":"98026",
    "sg:province":"WA",
    "sg:tags":[
        "house"
    ],
    "wof:name":"Eric Thuesen Custom Homes LLC",
    "wof:placetype":"venue"
},
  "geometry": {"coordinates":[-122.348848,47.832685],"type":"Point"}
}