{
  "type": "Feature",
  "properties": {
    "iso:country":"US",
    "sg:address":"124 W Main St",
    "sg:city":"Auburn",
    "sg:classifiers":[
        {
            "category":"Building & Trades",
            "subcategory":"Plumbing",
            "type":"Services"
        }
    ],
    "sg:phone":"+1 253 833 2330",
    "sg:postcode":"98001",
    "sg:province":"WA",
    "sg:tags":[
        "plumbing",
        "contractor"
    ],
    "wof:name":"Harold's Plumbing Co",
    "wof:placetype":"venue"
},
  "geometry": {"coordinates":[-122.23182799999999,47.307342],"type":"Point"}
}