{
  "type": "Feature",
  "properties": {
    "addr:full":"10023 128th St E Puyallup WA 98373",
    "addr:housenumber":"10023",
    "addr:postcode":"98373",
    "addr:street":"128Th St E",
    "iso:country":"US",
    "sg:address":"10023 128th St E",
    "sg:city":"Puyallup",
    "sg:classifiers":[
        {
            "category":"Autos & Motor Vehicles",
            "subcategory":"Auto Supplies",
            "type":"Retail Goods"
        }
    ],
    "sg:phone":"+1 253 286 2344",
    "sg:postcode":"98373",
    "sg:province":"WA",
    "sg:tags":[
        "automobile",
        "parts"
    ],
    "wof:name":"Billy Bob's Off Road & Truck",
    "wof:placetype":"venue"
},
  "geometry": {"coordinates":[-122.29467099999999,47.140307],"type":"Point"}
}