{
  "type": "Feature",
  "properties": {
    "addr:full":"201 Eberle Ln Sequim WA 98382",
    "addr:housenumber":"201",
    "addr:postcode":"98382",
    "addr:street":"Eberle Ln",
    "iso:country":"US",
    "sg:address":"201 Eberle Ln",
    "sg:city":"Sequim",
    "sg:classifiers":[
        {
            "category":"Building & Trades",
            "subcategory":"Construction",
            "type":"Services"
        }
    ],
    "sg:phone":"+1 360 681 5113",
    "sg:postcode":"98382",
    "sg:province":"WA",
    "sg:tags":[
        "contractor"
    ],
    "wof:name":"Tims Construction Clean Up",
    "wof:placetype":"venue"
},
  "geometry": {"coordinates":[-123.11991999999999,48.131216],"type":"Point"}
}