{
  "type": "Feature",
  "properties": {
    "addr:full":"2535 Jefferson Ave Tacoma WA 98402",
    "addr:housenumber":"2535",
    "addr:postcode":"98402",
    "addr:street":"Jefferson Ave",
    "iso:country":"US",
    "sg:address":"2535 Jefferson Ave",
    "sg:city":"Tacoma",
    "sg:classifiers":[
        {
            "category":"Professional",
            "subcategory":"Research",
            "type":"Services"
        }
    ],
    "sg:phone":"+1 253 203 0054",
    "sg:postcode":"98402",
    "sg:province":"WA",
    "sg:tags":[
        "commercial",
        "physical"
    ],
    "wof:name":"Processing Technology Inc",
    "wof:placetype":"venue"
},
  "geometry": {"coordinates":[-122.43904999999999,47.237467],"type":"Point"}
}