{
  "type": "Feature",
  "properties": {
    "addr:full":"2335 NW Turner Dr Pullman WA 99163",
    "addr:housenumber":"2335",
    "addr:postcode":"99163",
    "addr:street":"Nw Turner Dr",
    "iso:country":"US",
    "sg:address":"2335 NW Turner Dr",
    "sg:city":"Pullman",
    "sg:classifiers":[
        {
            "category":"Building & Trades",
            "subcategory":"Landscaping Services",
            "type":"Services"
        }
    ],
    "sg:phone":"+1 509 334 6289",
    "sg:postcode":"99163",
    "sg:province":"WA",
    "sg:tags":[
        "hydroseeding"
    ],
    "wof:name":"Yardquick Hydroseeding Ltd",
    "wof:placetype":"venue"
},
  "geometry": {"coordinates":[-117.179992,46.749985],"type":"Point"}
}