{
  "type": "Feature",
  "properties": {
    "addr:full":"5115 Capitol Blvd S Olympia WA 98501",
    "addr:housenumber":"5115",
    "addr:postcode":"98501",
    "addr:street":"Capitol Blvd S",
    "iso:country":"US",
    "sg:address":"5115 Capitol Blvd S",
    "sg:city":"Olympia",
    "sg:classifiers":[
        {
            "category":"Autos & Motor Vehicles",
            "subcategory":"Auto Supplies",
            "type":"Retail Goods"
        }
    ],
    "sg:phone":"+1 360 352 8680",
    "sg:postcode":"98501",
    "sg:province":"WA",
    "wof:name":"Schucks Auto Supply 4235",
    "wof:placetype":"venue"
},
  "geometry": {"coordinates":[-122.908857,46.999938],"type":"Point"}
}