{
  "type": "Feature",
  "properties": {
    "addr:full":"2700 NE Andresen Rd Vancouver WA 98661",
    "addr:housenumber":"2700",
    "addr:postcode":"98661",
    "addr:street":"Ne Andresen Rd",
    "iso:country":"US",
    "sg:address":"2700 NE Andresen Rd",
    "sg:city":"Vancouver",
    "sg:classifiers":[
        {
            "category":"Health Services",
            "subcategory":"Clinic",
            "type":"Services"
        }
    ],
    "sg:phone":"+1 360 694 8558",
    "sg:postcode":"98661",
    "sg:province":"WA",
    "sg:tags":[
        "counseling",
        "mental"
    ],
    "wof:name":"Morganstern Kenneth P Psychologist",
    "wof:placetype":"venue"
},
  "geometry": {"coordinates":[-122.601997,45.654701],"type":"Point"}
}