{
  "type": "Feature",
  "properties": {
    "addr:full":"842 Washington St Port Townsend WA 98368",
    "addr:housenumber":"842",
    "addr:postcode":"98368",
    "addr:street":"Washington St",
    "iso:country":"US",
    "sg:address":"842 Washington St",
    "sg:city":"Port Townsend",
    "sg:classifiers":[
        {
            "category":"Shopping",
            "type":"Retail Goods"
        }
    ],
    "sg:phone":"+1 360 385 2969",
    "sg:postcode":"98368",
    "sg:province":"WA",
    "sg:tags":[
        "art",
        "gallery",
        "dealer"
    ],
    "wof:name":"Dolce LA Belle",
    "wof:placetype":"venue"
},
  "geometry": {"coordinates":[-122.756456,48.115393],"type":"Point"}
}