{
  "type": "Feature",
  "properties": {
    "addr:full":"1605 SW 5th St Battle Ground WA 98604",
    "addr:housenumber":"1605",
    "addr:postcode":"98604",
    "addr:street":"Sw 5Th St",
    "iso:country":"US",
    "sg:address":"1605 SW 5th St",
    "sg:city":"Battle Ground",
    "sg:classifiers":[
        {
            "category":"Shopping",
            "subcategory":"Computers & Home Electronics",
            "type":"Retail Goods"
        }
    ],
    "sg:phone":"+1 360 666 0340",
    "sg:postcode":"98604",
    "sg:province":"WA",
    "sg:tags":[
        "equipment",
        "dealer"
    ],
    "wof:name":"A To Z Computer Liquidations",
    "wof:placetype":"venue"
},
  "geometry": {"coordinates":[-122.55415000000001,45.776652],"type":"Point"}
}