{
  "type": "Feature",
  "properties": {
    "addr:full":"2319 S Ferdinand St Seattle WA 98108",
    "addr:housenumber":"2319",
    "addr:postcode":"98108",
    "addr:street":"S Ferdinand St",
    "iso:country":"US",
    "sg:address":"2319 S Ferdinand St",
    "sg:city":"Seattle",
    "sg:classifiers":[
        {
            "category":"Building & Trades",
            "subcategory":"Landscaping Services",
            "type":"Services"
        }
    ],
    "sg:phone":"+1 206 250 6848",
    "sg:postcode":"98108",
    "sg:province":"WA",
    "sg:tags":[
        "landscape"
    ],
    "wof:name":"Natori Landscaping Service",
    "wof:placetype":"venue"
},
  "geometry": {"coordinates":[-122.302623,47.55824],"type":"Point"}
}