{
  "type": "Feature",
  "properties": {
    "addr:full":"4710 229th Pl NE Redmond WA 98053",
    "addr:housenumber":"4710",
    "addr:postcode":"98053",
    "addr:street":"229Th Pl Ne",
    "iso:country":"US",
    "sg:address":"4710 229th Pl NE",
    "sg:city":"Redmond",
    "sg:classifiers":[
        {
            "category":"Building & Trades",
            "subcategory":"Equipment Rental",
            "type":"Services"
        }
    ],
    "sg:phone":"+1 425 836 9777",
    "sg:postcode":"98053",
    "sg:province":"WA",
    "sg:tags":[
        "yard",
        "leasing",
        "store"
    ],
    "wof:name":"Emergency Phone Systems",
    "wof:placetype":"venue"
},
  "geometry": {"coordinates":[-122.033749,47.65158],"type":"Point"}
}