{
  "type": "Feature",
  "properties": {
    "addr:full":"2910 E 57th Ave Spokane WA 99223",
    "addr:housenumber":"2910",
    "addr:postcode":"99223",
    "addr:street":"E 57Th Ave",
    "iso:country":"US",
    "sg:address":"2910 E 57th Ave",
    "sg:city":"Spokane",
    "sg:classifiers":[
        {
            "category":"Cinema",
            "subcategory":"Movie Rental",
            "type":"Entertainment"
        }
    ],
    "sg:phone":"+1 509 443 8117",
    "sg:postcode":"99223",
    "sg:province":"WA",
    "sg:tags":[
        "video",
        "tape"
    ],
    "wof:name":"Hollywood Video",
    "wof:placetype":"venue"
},
  "geometry": {"coordinates":[-117.36380200000001,47.602099],"type":"Point"}
}