{
  "type": "Feature",
  "properties": {
    "addr:full":"2956 152nd Ave NE Redmond WA 98052",
    "addr:housenumber":"2956",
    "addr:postcode":"98052",
    "addr:street":"152Nd Ave Ne",
    "iso:country":"US",
    "sg:address":"2956 152nd Ave NE",
    "sg:city":"Redmond",
    "sg:classifiers":[
        {
            "category":"Health Services",
            "subcategory":"Clinic",
            "type":"Services"
        }
    ],
    "sg:phone":"+1 425 883 3236",
    "sg:postcode":"98052",
    "sg:province":"WA",
    "sg:tags":[
        "specialty",
        "outpatient"
    ],
    "wof:name":"Weston Group Inc",
    "wof:placetype":"venue"
},
  "geometry": {"coordinates":[-122.13632200000001,47.637749],"type":"Point"}
}