{
  "type": "Feature",
  "properties": {
    "addr:full":"12024 Juanita Dr NE Kirkland WA 98034",
    "addr:housenumber":"12024",
    "addr:postcode":"98034",
    "addr:street":"Juanita Dr Ne",
    "iso:country":"US",
    "sg:address":"12024 Juanita Dr NE",
    "sg:city":"Kirkland",
    "sg:classifiers":[
        {
            "category":"Real Estate",
            "subcategory":"Real Estate Services",
            "type":"Services"
        },
        {
            "category":"Real Estate",
            "subcategory":"Real Estate Agent",
            "type":"Services"
        }
    ],
    "sg:phone":"+1 425 629 3345",
    "sg:postcode":"98034",
    "sg:province":"WA",
    "sg:tags":[
        "buyer",
        "management",
        "broker"
    ],
    "wof:name":"Washington State Homes/Coldwell Banker",
    "wof:placetype":"venue"
},
  "geometry": {"coordinates":[-122.237109,47.708079],"type":"Point"}
}