{
  "type": "Feature",
  "properties": {
    "addr:full":"3850 Klahanie Dr SE Issaquah WA 98029",
    "addr:postcode":"3850;98029",
    "addr:street":"Klahanie Dr Se",
    "iso:country":"US",
    "sg:address":"3850 Klahanie Dr SE",
    "sg:city":"Issaquah",
    "sg:classifiers":[
        {
            "category":"Professional",
            "type":"Services"
        }
    ],
    "sg:phone":"+1 425 391 5989",
    "sg:postcode":"98029",
    "sg:province":"WA",
    "wof:name":"Soaring Solo",
    "wof:placetype":"venue"
},
  "geometry": {"coordinates":[-121.998909,47.575201],"type":"Point"}
}