{
  "type": "Feature",
  "properties": {
    "addr:full":"15103 NE 80th St Vancouver WA 98682",
    "addr:housenumber":"15103",
    "addr:postcode":"98682",
    "addr:street":"Ne 80Th St",
    "iso:country":"US",
    "sg:address":"15103 NE 80th St",
    "sg:city":"Vancouver",
    "sg:classifiers":[
        {
            "category":"Home & Garden",
            "subcategory":"Hardware",
            "type":"Retail Goods"
        }
    ],
    "sg:phone":"+1 360 609 3332",
    "sg:postcode":"98682",
    "sg:province":"WA",
    "wof:name":"Phil Kronebusch",
    "wof:placetype":"venue"
},
  "geometry": {"coordinates":[-122.516318,45.680514],"type":"Point"}
}