{
  "type": "Feature",
  "properties": {
    "addr:full":"1230 S College Ave College Place WA 99324",
    "addr:housenumber":"1230",
    "addr:postcode":"99324",
    "addr:street":"S College Ave",
    "iso:country":"US",
    "sg:address":"1230 S College Ave",
    "sg:city":"College Place",
    "sg:classifiers":[
        {
            "category":"Professional",
            "subcategory":"Business Services",
            "type":"Services"
        }
    ],
    "sg:phone":"+1 509 522 1983",
    "sg:postcode":"99324",
    "sg:province":"WA",
    "wof:name":"Two Hearts Communications Llc",
    "wof:placetype":"venue"
},
  "geometry": {"coordinates":[-118.38864100000001,46.038141],"type":"Point"}
}