{
  "type": "Feature",
  "properties": {
    "addr:full":"17926 NE 101st Ct Redmond WA 98052",
    "addr:housenumber":"17926",
    "addr:postcode":"98052",
    "addr:street":"Ne 101St Ct",
    "iso:country":"US",
    "sg:address":"17926 NE 101st Ct",
    "sg:city":"Redmond",
    "sg:classifiers":[
        {
            "category":"Professional",
            "subcategory":"Business Services",
            "type":"Services"
        }
    ],
    "sg:phone":"+1 425 497 8533",
    "sg:postcode":"98052",
    "sg:province":"WA",
    "wof:name":"Reindal Ventures Ltd",
    "wof:placetype":"venue"
},
  "geometry": {"coordinates":[-122.099301,47.691261],"type":"Point"}
}