{
  "type": "Feature",
  "properties": {
    "addr:full":"572 Pine St Omak WA 98841",
    "addr:housenumber":"572",
    "addr:postcode":"98841",
    "addr:street":"Pine St",
    "iso:country":"US",
    "sg:address":"572 Pine St",
    "sg:city":"Omak",
    "sg:classifiers":[
        {
            "category":"Real Estate",
            "subcategory":"Real Estate Operator",
            "type":"Services"
        }
    ],
    "sg:phone":"+1 509 826 0424",
    "sg:postcode":"98841",
    "sg:province":"WA",
    "sg:tags":[
        "building",
        "apartment"
    ],
    "wof:name":"North Valley Apartments",
    "wof:placetype":"venue"
},
  "geometry": {"coordinates":[-119.513913,48.416345],"type":"Point"}
}