{
  "type": "Feature",
  "properties": {
    "addr:full":"4400 S Graham S Seattle WA 98118",
    "addr:housenumber":"4400",
    "addr:postcode":"98118",
    "addr:street":"S Graham S",
    "iso:country":"US",
    "sg:address":"4400 S Graham S",
    "sg:city":"Seattle",
    "sg:classifiers":[
        {
            "category":"Building & Trades",
            "subcategory":"Locksmith",
            "type":"Services"
        }
    ],
    "sg:phone":"+1 206 238 0215",
    "sg:postcode":"98118",
    "sg:province":"WA",
    "sg:tags":[
        "key"
    ],
    "wof:name":"Run Locksmith Seattle WA",
    "wof:placetype":"venue"
},
  "geometry": {"coordinates":[-122.27812900000001,47.546024],"type":"Point"}
}