{
  "type": "Feature",
  "properties": {
    "addr:full":"14021 162nd Pl NE Arlington WA 98223",
    "addr:housenumber":"14021",
    "addr:postcode":"98223",
    "addr:street":"162Nd Pl Ne",
    "iso:country":"US",
    "sg:address":"14021 162nd Pl NE",
    "sg:city":"Arlington",
    "sg:classifiers":[
        {
            "category":"Building & Trades",
            "subcategory":"Construction",
            "type":"Services"
        }
    ],
    "sg:phone":"+1 360 435 4130",
    "sg:postcode":"98223",
    "sg:province":"WA",
    "sg:tags":[
        "concrete",
        "contractor"
    ],
    "wof:name":"John Olson Concrete Const",
    "wof:placetype":"venue"
},
  "geometry": {"coordinates":[-122.04061299999999,48.14393],"type":"Point"}
}