{
  "type": "Feature",
  "properties": {
    "addr:full":"80 Boundary Point Rd Oroville WA 98844",
    "addr:housenumber":"80",
    "addr:postcode":"98844",
    "addr:street":"Boundary Point Rd",
    "iso:country":"US",
    "sg:address":"80 Boundary Point Rd",
    "sg:city":"Oroville",
    "sg:classifiers":[
        {
            "category":"Building & Trades",
            "subcategory":"Construction",
            "type":"Services"
        }
    ],
    "sg:phone":"+1 509 476 3145",
    "sg:postcode":"98844",
    "sg:province":"WA",
    "sg:tags":[
        "system",
        "specialty",
        "heating",
        "contractor",
        "air conditioning"
    ],
    "wof:name":"Thermal Air",
    "wof:placetype":"venue"
},
  "geometry": {"coordinates":[-119.454781,48.996059],"type":"Point"}
}