{
  "type": "Feature",
  "properties": {
    "addr:full":"325 S 3rd St Renton WA 98055",
    "addr:housenumber":"325",
    "addr:postcode":"98055",
    "addr:street":"S 3Rd St",
    "iso:country":"US",
    "sg:address":"325 S 3rd St",
    "sg:city":"Renton",
    "sg:classifiers":[
        {
            "category":"Organizations",
            "subcategory":"Religious Organization",
            "type":"Services"
        }
    ],
    "sg:phone":"+1 206 527 5464",
    "sg:postcode":"98055",
    "sg:province":"WA",
    "sg:tags":[
        "church"
    ],
    "wof:name":"Church Universal & Triumphant",
    "wof:placetype":"venue"
},
  "geometry": {"coordinates":[-122.212221,47.479652],"type":"Point"}
}