{
  "type": "Feature",
  "properties": {
    "addr:full":"15th Ave W and Dravus Seattle WA 98119",
    "addr:postcode":"98119",
    "addr:street":"15Th Ave W And Dravus",
    "iso:country":"US",
    "sg:address":"15th Ave W and Dravus",
    "sg:city":"Seattle",
    "sg:classifiers":[
        {
            "category":"Professional",
            "subcategory":"Computer Services",
            "type":"Services"
        }
    ],
    "sg:phone":"+1 206 286 8438",
    "sg:postcode":"98119",
    "sg:province":"WA",
    "sg:tags":[
        "repair"
    ],
    "sg:website":"davidanders.wordpress.com",
    "wof:name":"The Computer Guy",
    "wof:placetype":"venue"
},
  "geometry": {"coordinates":[-122.37551499999999,47.648495],"type":"Point"}
}