{
  "type": "Feature",
  "properties": {
    "addr:full":"31919 1st Ave S Federal Way WA 98003",
    "addr:housenumber":"31919",
    "addr:postcode":"98003",
    "addr:street":"1St Ave S Federal Way",
    "iso:country":"US",
    "sg:address":"31919 1st Ave S",
    "sg:city":"Federal Way",
    "sg:classifiers":[
        {
            "category":"Professional",
            "subcategory":"Engineering",
            "type":"Services"
        }
    ],
    "sg:phone":"+1 253 946 5138",
    "sg:postcode":"98003",
    "sg:province":"WA",
    "sg:tags":[
        "surveying"
    ],
    "wof:name":"Hallin & Assoc",
    "wof:placetype":"venue"
},
  "geometry": {"coordinates":[-122.334732,47.316884],"type":"Point"}
}