{
  "type": "Feature",
  "properties": {
    "addr:full":"42312 252nd Ave SE Enumclaw WA 98022",
    "addr:housenumber":"42312",
    "addr:postcode":"98022",
    "addr:street":"252Nd Ave Se",
    "iso:country":"US",
    "sg:address":"42312 252nd Ave SE",
    "sg:city":"Enumclaw",
    "sg:classifiers":[
        {
            "category":"Home & Garden",
            "subcategory":"Building Materials",
            "type":"Retail Goods"
        }
    ],
    "sg:phone":"+1 360 825 2455",
    "sg:postcode":"98022",
    "sg:province":"WA",
    "wof:name":"Sasek Cement Finishing",
    "wof:placetype":"venue"
},
  "geometry": {"coordinates":[-122.007548,47.221869],"type":"Point"}
}