{
  "type": "Feature",
  "properties": {
    "iso:country":"US",
    "sg:address":"3320 S 23rd St",
    "sg:city":"Tacoma",
    "sg:classifiers":[
        {
            "category":"Retail",
            "subcategory":"Photofinishing",
            "type":"Services"
        }
    ],
    "sg:phone":"+1 253 572 5766",
    "sg:postcode":"98405",
    "sg:province":"WA",
    "sg:tags":[
        "laboratory",
        "finishing",
        "photo"
    ],
    "wof:name":"One Hour Photo Lab",
    "wof:placetype":"venue"
},
  "geometry": {"coordinates":[-122.479231,47.238114],"type":"Point"}
}