{
  "type": "Feature",
  "properties": {
    "addr:full":"116 W 3rd St Wapato WA 98951",
    "addr:housenumber":"116",
    "addr:postcode":"98951",
    "addr:street":"W 3Rd St",
    "iso:country":"US",
    "sg:address":"116 W 3rd St",
    "sg:city":"Wapato",
    "sg:classifiers":[
        {
            "category":"Shopping",
            "subcategory":"Music",
            "type":"Retail Goods"
        }
    ],
    "sg:phone":"+1 509 877 3518",
    "sg:postcode":"98951",
    "sg:province":"WA",
    "sg:tags":[
        "compact",
        "record",
        "disc",
        "tape"
    ],
    "wof:name":"Casa Musical",
    "wof:placetype":"venue"
},
  "geometry": {"coordinates":[-120.421064,46.446089],"type":"Point"}
}