{
  "type": "Feature",
  "properties": {
    "addr:full":"101 S Meridian Puyallup WA 98371",
    "addr:housenumber":"101",
    "addr:postcode":"98371",
    "addr:street":"S Meridian",
    "iso:country":"US",
    "sg:address":"101 S Meridian",
    "sg:city":"Puyallup",
    "sg:classifiers":[
        {
            "category":"Real Estate",
            "subcategory":"Architect",
            "type":"Services"
        }
    ],
    "sg:phone":"+1 253 840 5100",
    "sg:postcode":"98371",
    "sg:province":"WA",
    "wof:name":"JBM Designs",
    "wof:placetype":"venue"
},
  "geometry": {"coordinates":[-122.29370900000001,47.190978],"type":"Point"}
}