{
  "type": "Feature",
  "properties": {
    "addr:full":"14355 Fremont Ave N Seattle WA 98133",
    "addr:housenumber":"14355",
    "addr:postcode":"98133",
    "addr:street":"Fremont Ave N",
    "iso:country":"US",
    "sg:address":"14355 Fremont Ave N",
    "sg:city":"Seattle",
    "sg:classifiers":[
        {
            "category":"Professional",
            "subcategory":"Computer Services",
            "type":"Services"
        }
    ],
    "sg:phone":"+1 206 365 3578",
    "sg:postcode":"98133",
    "sg:province":"WA",
    "sg:tags":[
        "datum"
    ],
    "wof:name":"Sage Studio",
    "wof:placetype":"venue"
},
  "geometry": {"coordinates":[-122.350571,47.733273],"type":"Point"}
}