{
  "type": "Feature",
  "properties": {
    "addr:full":"16820 1st Ave SE Bothell WA 98012",
    "addr:housenumber":"16820",
    "addr:postcode":"98012",
    "addr:street":"1St Ave Se",
    "iso:country":"US",
    "sg:address":"16820 1st Ave SE",
    "sg:city":"Bothell",
    "sg:classifiers":[
        {
            "category":"Health Services",
            "subcategory":"Nursing And Care Facility",
            "type":"Services"
        }
    ],
    "sg:phone":"+1 425 750 5803",
    "sg:postcode":"98012",
    "sg:province":"WA",
    "wof:name":"Mill Creek Adult Family Home",
    "wof:placetype":"venue"
},
  "geometry": {"coordinates":[-122.231827,47.845417],"type":"Point"}
}