{
  "type": "Feature",
  "properties": {
    "addr:full":"18707 Pacific Ave S Spanaway WA 98387",
    "addr:housenumber":"18707",
    "addr:postcode":"98387",
    "addr:street":"Pacific Ave S Spanaway",
    "iso:country":"US",
    "sg:address":"18707 Pacific Ave S",
    "sg:city":"Spanaway",
    "sg:classifiers":[
        {
            "category":"Home & Garden",
            "subcategory":"Hardware",
            "type":"Retail Goods"
        }
    ],
    "sg:phone":"+1 253 847 7211",
    "sg:postcode":"98387",
    "sg:province":"WA",
    "wof:name":"South End Ace Hardware",
    "wof:placetype":"venue"
},
  "geometry": {"coordinates":[-122.43499199999999,47.087334],"type":"Point"}
}