{
  "type": "Feature",
  "properties": {
    "addr:full":"5215 Ronnona Ln Bellingham WA 98226",
    "addr:housenumber":"5215",
    "addr:postcode":"98226",
    "addr:street":"Ronnona Ln",
    "iso:country":"US",
    "sg:address":"5215 Ronnona Ln",
    "sg:city":"Bellingham",
    "sg:classifiers":[
        {
            "category":"Retail",
            "subcategory":"Portrait Studio",
            "type":"Services"
        }
    ],
    "sg:phone":"+1 360 592 0917",
    "sg:postcode":"98226",
    "sg:province":"WA",
    "sg:tags":[
        "photo"
    ],
    "wof:name":"Northern Lights Photography",
    "wof:placetype":"venue"
},
  "geometry": {"coordinates":[-122.302081,48.831666],"type":"Point"}
}