{
  "type": "Feature",
  "properties": {
    "addr:full":"3187 Ocean Beach Hwy Longview WA 98632",
    "addr:housenumber":"3187",
    "addr:postcode":"98632",
    "addr:street":"Ocean Beach Hwy",
    "iso:country":"US",
    "sg:address":"3187 Ocean Beach Hwy",
    "sg:city":"Longview",
    "sg:classifiers":[
        {
            "category":"Retail",
            "subcategory":"Photofinishing",
            "type":"Services"
        }
    ],
    "sg:phone":"+1 360 425 1922",
    "sg:postcode":"98632",
    "sg:province":"WA",
    "sg:tags":[
        "photo",
        "finishing"
    ],
    "wof:name":"Camera Shop",
    "wof:placetype":"venue"
},
  "geometry": {"coordinates":[-122.964378,46.147665],"type":"Point"}
}