{
  "type": "Feature",
  "properties": {
    "addr:full":"548 NE 98th St Seattle WA 98115",
    "addr:housenumber":"548",
    "addr:postcode":"98115",
    "addr:street":"Ne 98Th St",
    "iso:country":"US",
    "sg:address":"548 NE 98th St",
    "sg:city":"Seattle",
    "sg:classifiers":[
        {
            "category":"Health Services",
            "subcategory":"Clinic",
            "type":"Services"
        }
    ],
    "sg:phone":"+1 206 528 5888",
    "sg:postcode":"98115",
    "sg:province":"WA",
    "sg:tags":[
        "welfare"
    ],
    "wof:name":"Forever Health Co",
    "wof:placetype":"venue"
},
  "geometry": {"coordinates":[-122.321794,47.7004],"type":"Point"}
}