{
  "type": "Feature",
  "properties": {
    "addr:full":"15919 85th Ave E Puyallup WA 98375",
    "addr:housenumber":"15919",
    "addr:postcode":"98375",
    "addr:street":"85Th Ave E",
    "iso:country":"US",
    "sg:address":"15919 85th Ave E",
    "sg:city":"Puyallup",
    "sg:classifiers":[
        {
            "category":"Building & Trades",
            "subcategory":"Construction",
            "type":"Services"
        }
    ],
    "sg:phone":"+1 253 841 2051",
    "sg:postcode":"98375",
    "sg:province":"WA",
    "sg:tags":[
        "house"
    ],
    "wof:name":"Sandy Handy",
    "wof:placetype":"venue"
},
  "geometry": {"coordinates":[-122.316034,47.11369],"type":"Point"}
}