{
  "type": "Feature",
  "properties": {
    "addr:full":"649 Larson Rd Greenbank WA 98253",
    "addr:housenumber":"649",
    "addr:postcode":"98253",
    "addr:street":"Larson Rd",
    "iso:country":"US",
    "sg:address":"649 Larson Rd",
    "sg:city":"Greenbank",
    "sg:classifiers":[
        {
            "category":"Building & Trades",
            "subcategory":"Electrical",
            "type":"Services"
        }
    ],
    "sg:phone":"+1 360 222 3099",
    "sg:postcode":"98253",
    "sg:province":"WA",
    "sg:tags":[
        "electrician"
    ],
    "wof:name":"Homeowner's Electric",
    "wof:placetype":"venue"
},
  "geometry": {"coordinates":[-122.577297,48.078341],"type":"Point"}
}