{
  "type": "Feature",
  "properties": {
    "addr:full":"331 W Bell St Sequim WA 98382",
    "addr:housenumber":"331",
    "addr:postcode":"98382",
    "addr:street":"W Bell St",
    "iso:country":"US",
    "sg:address":"331 W Bell St",
    "sg:city":"Sequim",
    "sg:classifiers":[
        {
            "category":"Education",
            "subcategory":"Special Training",
            "type":"Public Place"
        }
    ],
    "sg:phone":"+1 360 681 0232",
    "sg:postcode":"98382",
    "sg:province":"WA",
    "sg:tags":[
        "instruction",
        "music"
    ],
    "wof:name":"Olympic Music School",
    "wof:placetype":"venue"
},
  "geometry": {"coordinates":[-123.109703,48.078679],"type":"Point"}
}