{
  "type": "Feature",
  "properties": {
    "addr:full":"212 5th St Wenatchee WA 98801",
    "addr:housenumber":"212",
    "addr:postcode":"98801",
    "addr:street":"5Th St",
    "iso:country":"US",
    "sg:address":"212 5th St",
    "sg:city":"Wenatchee",
    "sg:classifiers":[
        {
            "category":"Banks & Credit Unions",
            "subcategory":"Bank",
            "type":"Services"
        }
    ],
    "sg:phone":"+1 509 667 5046",
    "sg:postcode":"98801",
    "sg:province":"WA",
    "sg:tags":[
        "cashing",
        "check"
    ],
    "wof:name":"Check Into Cash",
    "wof:placetype":"venue"
},
  "geometry": {"coordinates":[-120.318771,47.429906],"type":"Point"}
}