{
  "type": "Feature",
  "properties": {
    "addr:full":"800 4th Ave Seattle WA 98185",
    "addr:housenumber":"800",
    "addr:postcode":"98185",
    "addr:street":"4Th Ave",
    "iso:country":"US",
    "sg:address":"800 4th Ave",
    "sg:city":"Seattle",
    "sg:classifiers":[
        {
            "category":"Social Services",
            "subcategory":"Retirement Home",
            "type":"Services"
        }
    ],
    "sg:phone":"+1 206 734 3653",
    "sg:postcode":"98185",
    "sg:province":"WA",
    "sg:website":"www.merrillgardens.com/assisted_...",
    "wof:name":"Merrill Gardens Queen Anne",
    "wof:placetype":"venue"
},
  "geometry": {"coordinates":[-122.331593,47.604675],"type":"Point"}
}