{
  "type": "Feature",
  "properties": {
    "addr:full":"15124 Main St E Sumner WA 98390",
    "addr:housenumber":"15124",
    "addr:postcode":"98390",
    "addr:street":"Main St E",
    "iso:country":"US",
    "sg:address":"15124 Main St E",
    "sg:city":"Sumner",
    "sg:classifiers":[
        {
            "category":"Retail",
            "subcategory":"Funeral Services",
            "type":"Services"
        }
    ],
    "sg:phone":"+1 253 863 1443",
    "sg:postcode":"98390",
    "sg:province":"WA",
    "sg:tags":[
        "home"
    ],
    "wof:name":"Powers Sumner Voiles Fnrl HM",
    "wof:placetype":"venue"
},
  "geometry": {"coordinates":[-122.225972,47.202597],"type":"Point"}
}