{
  "type": "Feature",
  "properties": {
    "addr:full":"15 S 6th Ave Yakima WA 98902",
    "addr:housenumber":"15",
    "addr:postcode":"98902",
    "addr:street":"S 6Th Ave",
    "iso:country":"US",
    "sg:address":"15 S 6th Ave",
    "sg:city":"Yakima",
    "sg:classifiers":[
        {
            "category":"Professional",
            "subcategory":"Accounting & Tax Preparation",
            "type":"Services"
        }
    ],
    "sg:phone":"+1 509 453 9195",
    "sg:postcode":"98902",
    "sg:province":"WA",
    "sg:tags":[
        "bookkeeping"
    ],
    "wof:name":"Langley, Terry & Assoc",
    "wof:placetype":"venue"
},
  "geometry": {"coordinates":[-120.517021,46.599489],"type":"Point"}
}