{
  "type": "Feature",
  "properties": {
    "addr:full":"2900 Westlake Ave N Seattle WA 98109",
    "addr:housenumber":"2900",
    "addr:postcode":"98109",
    "addr:street":"Westlake Ave N",
    "iso:country":"US",
    "sg:address":"2900 Westlake Ave N",
    "sg:city":"Seattle",
    "sg:classifiers":[
        {
            "category":"Recreation",
            "subcategory":"Marina",
            "type":"Entertainment"
        }
    ],
    "sg:phone":"+1 206 285 6040",
    "sg:postcode":"98109",
    "sg:province":"WA",
    "wof:name":"Pacific Intercoastal Company",
    "wof:placetype":"venue"
},
  "geometry": {"coordinates":[-122.347373,47.645015],"type":"Point"}
}