{
  "type": "Feature",
  "properties": {
    "addr:full":"5415 220th Ave SE Issaquah WA 98029",
    "addr:housenumber":"5415",
    "addr:postcode":"98029",
    "addr:street":"220Th Ave Se",
    "iso:country":"US",
    "sg:address":"5415 220th Ave SE",
    "sg:city":"Issaquah",
    "sg:classifiers":[
        {
            "category":"Government",
            "subcategory":"Court House",
            "type":"Public Place"
        }
    ],
    "sg:phone":"+1 206 296 7688",
    "sg:postcode":"98029",
    "sg:province":"WA",
    "sg:tags":[
        "state",
        "system"
    ],
    "wof:name":"King County Dst Crt Issaquah",
    "wof:placetype":"venue"
},
  "geometry": {"coordinates":[-122.047715,47.554412],"type":"Point"}
}