{
  "type": "Feature",
  "properties": {
    "addr:full":"2314 S 16th St Tacoma WA 98405",
    "addr:housenumber":"2314",
    "addr:postcode":"98405",
    "addr:street":"S 16Th St",
    "iso:country":"US",
    "sg:address":"2314 S 16th St",
    "sg:city":"Tacoma",
    "sg:classifiers":[
        {
            "category":"Shopping",
            "subcategory":"Jewelry",
            "type":"Retail Goods"
        },
        {
            "category":"Manufacturing",
            "subcategory":"Jewelry",
            "type":"Manufacturing & Wholesale Goods"
        }
    ],
    "sg:phone":"+1 253 272 3877",
    "sg:postcode":"98405",
    "sg:province":"WA",
    "sg:tags":[
        "designer",
        "jeweler"
    ],
    "wof:name":"Bradley Jewelry & Repair",
    "wof:placetype":"venue"
},
  "geometry": {"coordinates":[-122.467102,47.245838],"type":"Point"}
}