{
  "type": "Feature",
  "properties": {
    "addr:full":"1615 Index Ct SE Renton WA 98058",
    "addr:housenumber":"1615",
    "addr:postcode":"98058",
    "addr:street":"Index Ct Se",
    "iso:country":"US",
    "sg:address":"1615 Index Ct SE",
    "sg:city":"Renton",
    "sg:classifiers":[
        {
            "category":"Taxi",
            "type":"Transportation"
        }
    ],
    "sg:phone":"+1 425 226 9776",
    "sg:postcode":"98058",
    "sg:province":"WA",
    "sg:tags":[
        "taxicab"
    ],
    "wof:name":"Site Taxi",
    "wof:placetype":"venue"
},
  "geometry": {"coordinates":[-122.18084500000001,47.466065],"type":"Point"}
}