{
  "type": "Feature",
  "properties": {
    "iso:country":"US",
    "sg:address":"102 Pacific Ave",
    "sg:city":"Bremerton",
    "sg:classifiers":[
        {
            "category":"Shopping",
            "subcategory":"Florist",
            "type":"Retail Goods"
        }
    ],
    "sg:phone":"+1 360 377 8888",
    "sg:postcode":"98337",
    "sg:province":"WA",
    "wof:name":"Flowers D'Amour",
    "wof:placetype":"venue"
},
  "geometry": {"coordinates":[-122.626825,47.564228],"type":"Point"}
}