{
  "type": "Feature",
  "properties": {
    "iso:country":"US",
    "sg:address":"1708 Rainier St",
    "sg:city":"Sumner",
    "sg:classifiers":[
        {
            "category":"Professional",
            "subcategory":"Business Services",
            "type":"Services"
        }
    ],
    "sg:phone":"+1 253 863 4017",
    "sg:postcode":"98390",
    "sg:province":"WA",
    "wof:name":"Pyfer Enterprises",
    "wof:placetype":"venue"
},
  "geometry": {"coordinates":[-122.23197500000001,47.196449],"type":"Point"}
}