{
  "type": "Feature",
  "properties": {
    "addr:full":"3124 Valley Hwy Deming WA 98244",
    "addr:housenumber":"3124",
    "addr:postcode":"98244",
    "addr:street":"Valley Hwy",
    "iso:country":"US",
    "sg:address":"3124 Valley Hwy",
    "sg:city":"Deming",
    "sg:classifiers":[
        {
            "category":"Shopping",
            "subcategory":"Bicycles & Sporting Goods",
            "type":"Retail Goods"
        }
    ],
    "sg:phone":"+1 360 595 2964",
    "sg:postcode":"98244",
    "sg:province":"WA",
    "wof:name":"Dairy Farm",
    "wof:placetype":"venue"
},
  "geometry": {"coordinates":[-122.201865,48.755816],"type":"Point"}
}