{
  "type": "Feature",
  "properties": {
    "addr:full":"5018 Highland Dr SE Auburn WA 98092",
    "addr:housenumber":"5018",
    "addr:postcode":"98092",
    "addr:street":"Highland Dr Se",
    "iso:country":"US",
    "sg:address":"5018 Highland Dr SE",
    "sg:city":"Auburn",
    "sg:classifiers":[
        {
            "category":"Professional",
            "subcategory":"Art Services",
            "type":"Services"
        }
    ],
    "sg:phone":"+1 253 833 8022",
    "sg:postcode":"98092",
    "sg:province":"WA",
    "sg:tags":[
        "photography",
        "commercial"
    ],
    "wof:name":"Ccw Prtrait Wdding Photography",
    "wof:placetype":"venue"
},
  "geometry": {"coordinates":[-122.21194,47.264022],"type":"Point"}
}