{
  "type": "Feature",
  "properties": {
    "addr:full":"454 Monroe Ave NE Renton WA 98056",
    "addr:housenumber":"454",
    "addr:postcode":"98056",
    "addr:street":"Monroe Ave Ne",
    "iso:country":"US",
    "sg:address":"454 Monroe Ave NE",
    "sg:city":"Renton",
    "sg:classifiers":[
        {
            "category":"Wholesale",
            "subcategory":"Durable Goods & Equipment",
            "type":"Manufacturing & Wholesale Goods"
        }
    ],
    "sg:phone":"+1 425 917 5395",
    "sg:postcode":"98056",
    "sg:province":"WA",
    "wof:name":"North Pole Wholesale",
    "wof:placetype":"venue"
},
  "geometry": {"coordinates":[-122.17481100000001,47.48864],"type":"Point"}
}