{
  "type": "Feature",
  "properties": {
    "iso:country":"US",
    "sg:address":"2226 116th St SE",
    "sg:city":"Everett",
    "sg:classifiers":[
        {
            "category":"Building & Trades",
            "subcategory":"Construction",
            "type":"Services"
        }
    ],
    "sg:phone":"+1 425 501 2707",
    "sg:postcode":"98208",
    "sg:province":"WA",
    "sg:tags":[
        "contractor"
    ],
    "wof:name":"Daves Window & Gutter Cleanin",
    "wof:placetype":"venue"
},
  "geometry": {"coordinates":[-122.202113,47.892636],"type":"Point"}
}