{
  "type": "Feature",
  "properties": {
    "addr:full":"3190 Kindred Ave Tokeland WA 98590",
    "addr:housenumber":"3190",
    "addr:postcode":"98590",
    "addr:street":"Kindred Ave Tokeland",
    "iso:country":"US",
    "sg:address":"3190 Kindred Ave",
    "sg:city":"Tokeland",
    "sg:classifiers":[
        {
            "category":"Utilities",
            "subcategory":"Water",
            "type":"Services"
        }
    ],
    "sg:phone":"+1 360 267 2722",
    "sg:postcode":"98590",
    "sg:province":"WA",
    "sg:tags":[
        "fishermen-commercial"
    ],
    "wof:name":"F V Willapa",
    "wof:placetype":"venue"
},
  "geometry": {"coordinates":[-123.97163500000001,46.704801],"type":"Point"}
}