{
  "type": "Feature",
  "properties": {
    "addr:full":"7479 Enterprise Rd Ferndale WA 98248",
    "addr:housenumber":"7479",
    "addr:postcode":"98248",
    "addr:street":"Enterprise Rd",
    "iso:country":"US",
    "sg:address":"7479 Enterprise Rd",
    "sg:city":"Ferndale",
    "sg:classifiers":[
        {
            "category":"Building & Trades",
            "subcategory":"Cleaning & Sanitation",
            "type":"Services"
        }
    ],
    "sg:phone":"+1 360 380 2827",
    "sg:postcode":"98248",
    "sg:province":"WA",
    "sg:tags":[
        "maintenance"
    ],
    "wof:name":"Management Services NW Inc",
    "wof:placetype":"venue"
},
  "geometry": {"coordinates":[-122.574595,48.907314],"type":"Point"}
}