{
  "type": "Feature",
  "properties": {
    "addr:full":"9351 Jeske Rd Peshastin WA 98847",
    "addr:housenumber":"9351",
    "addr:postcode":"98847",
    "addr:street":"Jeske Rd",
    "iso:country":"US",
    "sg:address":"9351 Jeske Rd",
    "sg:city":"Peshastin",
    "sg:classifiers":[
        {
            "category":"Retail",
            "subcategory":"Repair Shop",
            "type":"Services"
        }
    ],
    "sg:phone":"+1 509 548 6282",
    "sg:postcode":"98847",
    "sg:province":"WA",
    "sg:tags":[
        "trade",
        "logging",
        "contractor"
    ],
    "wof:name":"G&V General Contractors",
    "wof:placetype":"venue"
},
  "geometry": {"coordinates":[-120.584332,47.558605],"type":"Point"}
}