{
  "type": "Feature",
  "properties": {
    "addr:full":"4918 196th St SW Lynnwood WA 98036",
    "addr:housenumber":"4918",
    "addr:postcode":"98036",
    "addr:street":"196Th St Sw",
    "iso:country":"US",
    "sg:address":"4918 196th St SW",
    "sg:city":"Lynnwood",
    "sg:classifiers":[
        {
            "category":"Shopping",
            "subcategory":"Musical Instruments",
            "type":"Retail Goods"
        },
        {
            "category":"Manufacturing",
            "subcategory":"Musical Instruments",
            "type":"Manufacturing & Wholesale Goods"
        }
    ],
    "sg:phone":"+1 425 775 4226",
    "sg:postcode":"98036",
    "sg:province":"WA",
    "sg:tags":[
        "guitar",
        "instruments-rental",
        "amplifier"
    ],
    "wof:name":"Roys Place Rehearsal Studios",
    "wof:placetype":"venue"
},
  "geometry": {"coordinates":[-122.29939899999999,47.82109],"type":"Point"}
}