{
  "type": "Feature",
  "properties": {
    "addr:full":"13062 NE 113th St Kirkland WA 98033",
    "addr:housenumber":"13062",
    "addr:postcode":"98033",
    "addr:street":"Ne 113Th St",
    "iso:country":"US",
    "sg:address":"13062 NE 113th St",
    "sg:city":"Kirkland",
    "sg:classifiers":[
        {
            "category":"Retail",
            "subcategory":"Repair Shop",
            "type":"Services"
        }
    ],
    "sg:phone":"+1 425 822 0690",
    "sg:postcode":"98033",
    "sg:province":"WA",
    "sg:tags":[
        "maintenance",
        "boat"
    ],
    "wof:name":"Mauldin Marine Services",
    "wof:placetype":"venue"
},
  "geometry": {"coordinates":[-122.16746500000001,47.701913],"type":"Point"}
}