{
  "type": "Feature",
  "properties": {
    "addr:full":"291 N Beach Rd Eastsound WA 98245",
    "addr:housenumber":"291",
    "addr:postcode":"98245",
    "addr:street":"N Beach Rd",
    "iso:country":"US",
    "sg:address":"291 N Beach Rd",
    "sg:city":"Eastsound",
    "sg:classifiers":[
        {
            "category":"Professional",
            "subcategory":"Computer Services",
            "type":"Services"
        }
    ],
    "sg:phone":"+1 360 376 3306",
    "sg:postcode":"98245",
    "sg:province":"WA",
    "sg:tags":[
        "datum"
    ],
    "wof:name":"Stark Images",
    "wof:placetype":"venue"
},
  "geometry": {"coordinates":[-122.906426,48.69473],"type":"Point"}
}