{
  "type": "Feature",
  "properties": {
    "addr:full":"14505 E 18th Ave Veradale WA 99037",
    "addr:housenumber":"14505",
    "addr:postcode":"99037",
    "addr:street":"E 18Th Ave",
    "iso:country":"US",
    "sg:address":"14505 E 18th Ave",
    "sg:city":"Veradale",
    "sg:classifiers":[
        {
            "category":"Wholesale",
            "subcategory":"Office Equipment",
            "type":"Manufacturing & Wholesale Goods"
        }
    ],
    "sg:phone":"+1 509 928 2019",
    "sg:postcode":"99037",
    "sg:province":"WA",
    "wof:name":"Document Technologies",
    "wof:placetype":"venue"
},
  "geometry": {"coordinates":[-117.208422,47.640725],"type":"Point"}
}