{
  "type": "Feature",
  "properties": {
    "addr:full":"4 E Main St Walla Walla WA 99362",
    "addr:housenumber":"4",
    "addr:postcode":"99362",
    "addr:street":"E Main St",
    "iso:country":"US",
    "sg:address":"4 E Main St",
    "sg:city":"Walla Walla",
    "sg:classifiers":[
        {
            "category":"Food & Beverages",
            "subcategory":"Liquor & Beverages",
            "type":"Retail Goods"
        }
    ],
    "sg:phone":"+1 509 522 3993",
    "sg:postcode":"99362",
    "sg:province":"WA",
    "sg:tags":[
        "wine"
    ],
    "wof:name":"Grapefields",
    "wof:placetype":"venue"
},
  "geometry": {"coordinates":[-118.338109,46.06712],"type":"Point"}
}