{
  "type": "Feature",
  "properties": {
    "addr:full":"10434 NE 16th Pl Bellevue WA 98004",
    "addr:housenumber":"10434",
    "addr:postcode":"98004",
    "addr:street":"Ne 16Th Pl",
    "iso:country":"US",
    "sg:address":"10434 NE 16th Pl",
    "sg:city":"Bellevue",
    "sg:classifiers":[
        {
            "category":"Manufacturing",
            "subcategory":"Printing",
            "type":"Manufacturing & Wholesale Goods"
        }
    ],
    "sg:phone":"+1 425 453 9860",
    "sg:postcode":"98004",
    "sg:province":"WA",
    "sg:tags":[
        "lithographic",
        "commercial"
    ],
    "wof:name":"Flamingo Design",
    "wof:placetype":"venue"
},
  "geometry": {"coordinates":[-122.200243,47.624441],"type":"Point"}
}