{
  "type": "Feature",
  "properties": {
    "addr:full":"1725 Westlake Ave N Ste 210 Seattle WA 98109",
    "addr:housenumber":"1725",
    "addr:postcode":"98109",
    "addr:street":"Westlake Ave N Ste 210",
    "iso:country":"US",
    "sg:address":"1725 Westlake Ave N Ste 210",
    "sg:city":"Seattle",
    "sg:classifiers":[
        {
            "category":"Shopping",
            "type":"Retail Goods"
        }
    ],
    "sg:phone":"+1 206 464 0600",
    "sg:postcode":"98109",
    "sg:province":"WA",
    "wof:name":"Real Retail",
    "wof:placetype":"venue"
},
  "geometry": {"coordinates":[-122.340777,47.634379],"type":"Point"}
}