{
  "type": "Feature",
  "properties": {
    "addr:full":"21615 SE 270th St Maple Valley WA 98038",
    "addr:housenumber":"21615",
    "addr:postcode":"98038",
    "addr:street":"Se 270Th St",
    "iso:country":"US",
    "sg:address":"21615 SE 270th St",
    "sg:city":"Maple Valley",
    "sg:classifiers":[
        {
            "category":"Professional",
            "subcategory":"Engineering",
            "type":"Services"
        }
    ],
    "sg:phone":"+1 425 432 6875",
    "sg:postcode":"98038",
    "sg:province":"WA",
    "wof:name":"Medchill Consulting Servi",
    "wof:placetype":"venue"
},
  "geometry": {"coordinates":[-122.051147,47.359879],"type":"Point"}
}