{
  "type": "Feature",
  "properties": {
    "addr:full":"7200 W Nob Hill Blvd Yakima WA 98908",
    "addr:housenumber":"7200",
    "addr:postcode":"98908",
    "addr:street":"W Nob Hill Blvd",
    "iso:country":"US",
    "sg:address":"7200 W Nob Hill Blvd",
    "sg:city":"Yakima",
    "sg:classifiers":[
        {
            "category":"Government",
            "subcategory":"Office",
            "type":"Public Place"
        },
        {
            "category":"Social Services",
            "type":"Services"
        }
    ],
    "sg:phone":"+1 509 574 1060",
    "sg:postcode":"98908",
    "sg:province":"WA",
    "sg:tags":[
        "county",
        "executive",
        "resource"
    ],
    "sg:website":"www.altcwashington.com",
    "wof:name":"Aging and Long Term Care",
    "wof:placetype":"venue"
},
  "geometry": {"coordinates":[-120.60767199999999,46.585767],"type":"Point"}
}