{
  "type": "Feature",
  "properties": {
    "addr:full":"1101 Madison St Ste 200 Seattle WA 98104",
    "addr:housenumber":"1101",
    "addr:postcode":"98104",
    "addr:street":"Madison St Ste 200",
    "iso:country":"US",
    "sg:address":"1101 Madison St Ste 200",
    "sg:city":"Seattle",
    "sg:classifiers":[
        {
            "category":"Arts & Performance",
            "subcategory":"Music",
            "type":"Entertainment"
        },
        {
            "category":"Health Services",
            "subcategory":"Health Practitioner",
            "type":"Services"
        }
    ],
    "sg:phone":"+1 206 386 2035",
    "sg:postcode":"98104",
    "sg:province":"WA",
    "sg:tags":[
        "speech",
        "therapist",
        "therapy",
        "physical"
    ],
    "sg:website":"www.swedish.org/rehabilitation",
    "wof:name":"Swedish Rehabilitation Services First Hill",
    "wof:placetype":"venue"
},
  "geometry": {"coordinates":[-122.32426,47.609212],"type":"Point"}
}