{
  "type": "Feature",
  "properties": {
    "addr:full":"8134 Guide Meridian Rd Lynden WA 98264",
    "addr:housenumber":"8134",
    "addr:postcode":"98264",
    "addr:street":"Guide Meridian Rd",
    "iso:country":"US",
    "sg:address":"8134 Guide Meridian Rd",
    "sg:city":"Lynden",
    "sg:classifiers":[
        {
            "category":"Restaurant",
            "type":"Food & Drink"
        },
        {
            "category":"Food & Beverages",
            "subcategory":"Ethnic Foods",
            "type":"Retail Goods"
        }
    ],
    "sg:phone":"+1 360 318 9878",
    "sg:postcode":"98264",
    "sg:province":"WA",
    "sg:tags":[
        "dining",
        "fine",
        "asian",
        "pan",
        "vietnamese"
    ],
    "wof:name":"Pho & Teriyaki",
    "wof:placetype":"venue"
},
  "geometry": {"coordinates":[-122.485407,48.93578],"type":"Point"}
}