{
  "type": "Feature",
  "properties": {
    "addr:full":"311 N 50th St Seattle WA 98103",
    "addr:housenumber":"311",
    "addr:postcode":"98103",
    "addr:street":"N 50Th St",
    "iso:country":"US",
    "sg:address":"311 N 50th St",
    "sg:city":"Seattle",
    "sg:classifiers":[
        {
            "category":"Professional",
            "subcategory":"Management & Consulting",
            "type":"Services"
        }
    ],
    "sg:phone":"+1 206 782 8956",
    "sg:postcode":"98103",
    "sg:province":"WA",
    "wof:name":"Paradigm Consulting Assoc",
    "wof:placetype":"venue"
},
  "geometry": {"coordinates":[-122.35460500000001,47.664921],"type":"Point"}
}