{
  "type": "Feature",
  "properties": {
    "iso:country":"US",
    "sg:address":"1422 N Mamer Rd",
    "sg:city":"Spokane",
    "sg:classifiers":[
        {
            "category":"Building & Trades",
            "subcategory":"Landscaping Services",
            "type":"Services"
        }
    ],
    "sg:phone":"+1 509 891 5942",
    "sg:postcode":"99216",
    "sg:province":"WA",
    "wof:name":"Days Lawn Service",
    "wof:placetype":"venue"
},
  "geometry": {"coordinates":[-117.220753,47.66813],"type":"Point"}
}