{
  "type": "Feature",
  "properties": {
    "addr:full":"2003 Western Avenue Suite 360 Seattle WA 98121",
    "addr:housenumber":"2003",
    "addr:postcode":"98121",
    "addr:street":"Western Avenue Suite 360",
    "iso:country":"US",
    "sg:address":"2003 Western Avenue Suite 360",
    "sg:city":"Seattle",
    "sg:classifiers":[
        {
            "category":"Shopping",
            "subcategory":"Bicycles & Sporting Goods",
            "type":"Retail Goods"
        }
    ],
    "sg:phone":"+1 206 374 0575",
    "sg:postcode":"98121",
    "sg:province":"WA",
    "wof:name":"Winds",
    "wof:placetype":"venue"
},
  "geometry": {"coordinates":[-122.34369599999999,47.610326],"type":"Point"}
}