{
  "type": "Feature",
  "properties": {
    "addr:full":"6521 127th Ave SE Bellevue WA 98006",
    "addr:housenumber":"6521",
    "addr:postcode":"98006",
    "addr:street":"127Th Ave Se",
    "iso:country":"US",
    "sg:address":"6521 127th Ave SE",
    "sg:city":"Bellevue",
    "sg:classifiers":[
        {
            "category":"Utilities",
            "subcategory":"Telephone",
            "type":"Services"
        }
    ],
    "sg:phone":"+1 425 260 4218",
    "sg:postcode":"98006",
    "sg:province":"WA",
    "sg:tags":[
        "communications"
    ],
    "wof:name":"Avaya",
    "wof:placetype":"venue"
},
  "geometry": {"coordinates":[-122.172259,47.544448],"type":"Point"}
}