{
  "type": "Feature",
  "properties": {
    "addr:full":"1720 SW 359th St Federal Way WA 98023",
    "addr:housenumber":"1720",
    "addr:postcode":"98023",
    "addr:street":"Sw 359Th St",
    "iso:country":"US",
    "sg:address":"1720 SW 359th St",
    "sg:city":"Federal Way",
    "sg:classifiers":[
        {
            "category":"Building & Trades",
            "subcategory":"Cleaning & Sanitation",
            "type":"Services"
        }
    ],
    "sg:phone":"+1 253 334 3347",
    "sg:postcode":"98023",
    "sg:province":"WA",
    "sg:tags":[
        "maintenance"
    ],
    "wof:name":"Spirit Journey",
    "wof:placetype":"venue"
},
  "geometry": {"coordinates":[-122.35671499999999,47.280149],"type":"Point"}
}