{
  "type": "Feature",
  "properties": {
    "addr:full":"10002 Aurora Ave N Seattle WA 98133",
    "addr:housenumber":"10002",
    "addr:postcode":"98133",
    "addr:street":"Aurora Ave N",
    "iso:country":"US",
    "sg:address":"10002 Aurora Ave N",
    "sg:city":"Seattle",
    "sg:classifiers":[
        {
            "category":"Restaurant",
            "type":"Food & Drink"
        }
    ],
    "sg:phone":"+1 206 517 4467",
    "sg:postcode":"98133",
    "sg:province":"WA",
    "wof:name":"International House of Pancakes",
    "wof:placetype":"venue"
},
  "geometry": {"coordinates":[-122.34699999999999,47.7341],"type":"Point"}
}