{
  "type": "Feature",
  "properties": {
    "addr:full":"435 N 34th Street Seattle WA 98103",
    "addr:housenumber":"435",
    "addr:postcode":"98103",
    "addr:street":"N 34Th Street",
    "iso:country":"US",
    "sg:address":"435 N 34th Street",
    "sg:city":"Seattle",
    "sg:classifiers":[
        {
            "category":"Health Services",
            "subcategory":"Health Practitioner",
            "type":"Services"
        }
    ],
    "sg:phone":"+1 206 548 1522",
    "sg:postcode":"98103",
    "sg:province":"WA",
    "sg:tags":[
        "therapy",
        "physical"
    ],
    "wof:name":"Olympic Rehabilitation Specialties",
    "wof:placetype":"venue"
},
  "geometry": {"coordinates":[-122.354163,47.650476],"type":"Point"}
}