{
  "type": "Feature",
  "properties": {
    "addr:full":"26015 104th Ave SE Kent WA 98030",
    "addr:housenumber":"26015",
    "addr:postcode":"98030",
    "addr:street":"104Th Ave Se",
    "iso:country":"US",
    "sg:address":"26015 104th Ave SE",
    "sg:city":"Kent",
    "sg:classifiers":[
        {
            "category":"Coffee & Tea",
            "type":"Food & Drink"
        }
    ],
    "sg:menulink":"http://www.allmenus.com/wa/seattle/117732-starbucks-coffee/menu/",
    "sg:phone":"+1 253 856 1440",
    "sg:postcode":"98030",
    "sg:province":"WA",
    "sg:tags":[
        "american"
    ],
    "wof:name":"Starbucks Coffee",
    "wof:placetype":"venue"
},
  "geometry": {"coordinates":[-122.202347,47.3688],"type":"Point"}
}