{
  "type": "Feature",
  "properties": {
    "addr:full":"330 King St Ste 6 Wenatchee WA 98801",
    "addr:housenumber":"330",
    "addr:postcode":"98801",
    "addr:street":"King St Ste 6",
    "iso:country":"US",
    "sg:address":"330 King St Ste 6",
    "sg:city":"Wenatchee",
    "sg:classifiers":[
        {
            "category":"Professional",
            "subcategory":"Management & Consulting",
            "type":"Services"
        },
        {
            "category":"Banks & Credit Unions",
            "subcategory":"Investment Brokerage",
            "type":"Services"
        },
        {
            "category":"Banks & Credit Unions",
            "subcategory":"Bank",
            "type":"Services"
        },
        {
            "category":"Banks & Credit Unions",
            "subcategory":"Financial Services",
            "type":"Services"
        }
    ],
    "sg:phone":"+1 509 664 3700",
    "sg:postcode":"98801",
    "sg:province":"WA",
    "sg:tags":[
        "advisory",
        "financing",
        "planner",
        "consultant",
        "broker",
        "agent",
        "planning",
        "transfer",
        "security",
        "bond",
        "stock"
    ],
    "wof:name":"Bliggenstorfer Financial",
    "wof:placetype":"venue"
},
  "geometry": {"coordinates":[-120.316199,47.423098],"type":"Point"}
}