{
  "type": "Feature",
  "properties": {
    "addr:full":"900 Thomas St Ste 200 Seattle WA 98109",
    "addr:housenumber":"900",
    "addr:postcode":"98109",
    "addr:street":"Thomas St Ste 200",
    "iso:country":"US",
    "sg:address":"900 Thomas St Ste 200",
    "sg:city":"Seattle",
    "sg:classifiers":[
        {
            "category":"Personal",
            "subcategory":"Massage",
            "type":"Services"
        }
    ],
    "sg:phone":"+1 206 292 8055",
    "sg:postcode":"98109",
    "sg:province":"WA",
    "sg:website":"www.cortiva.com/locations/seattle",
    "wof:name":"Brian Utting School of Massage",
    "wof:placetype":"venue"
},
  "geometry": {"coordinates":[-122.33976199999999,47.62089],"type":"Point"}
}