{
  "type": "Feature",
  "properties": {
    "addr:full":"3803 Summitview Ave Yakima WA 98902",
    "addr:housenumber":"3803",
    "addr:postcode":"98902",
    "addr:street":"Summitview Ave",
    "iso:country":"US",
    "sg:address":"3803 Summitview Ave",
    "sg:city":"Yakima",
    "sg:classifiers":[
        {
            "category":"Social Services",
            "subcategory":"Adult Care",
            "type":"Services"
        }
    ],
    "sg:phone":"+1 509 965 5269",
    "sg:postcode":"98902",
    "sg:province":"WA",
    "sg:tags":[
        "home",
        "residential"
    ],
    "wof:name":"Living Care Retirement Cmmty",
    "wof:placetype":"venue"
},
  "geometry": {"coordinates":[-120.559742,46.599994],"type":"Point"}
}