{
  "type": "Feature",
  "properties": {
    "addr:full":"2124 NE 155th St Vancouver WA 98686",
    "addr:housenumber":"2124",
    "addr:postcode":"98686",
    "addr:street":"Ne 155Th St",
    "iso:country":"US",
    "sg:address":"2124 NE 155th St",
    "sg:city":"Vancouver",
    "sg:classifiers":[
        {
            "category":"Banks & Credit Unions",
            "subcategory":"Financial Services",
            "type":"Services"
        }
    ],
    "sg:phone":"+1 360 571 8500",
    "sg:postcode":"98686",
    "sg:province":"WA",
    "sg:tags":[
        "other",
        "investment",
        "holding"
    ],
    "wof:name":"Savings Plus",
    "wof:placetype":"venue"
},
  "geometry": {"coordinates":[-122.650479,45.733038],"type":"Point"}
}