{
  "type": "Feature",
  "properties": {
    "addr:full":"32501 NE 50th St Carnation WA 98014",
    "addr:housenumber":"32501",
    "addr:postcode":"98014",
    "addr:street":"Ne 50Th St",
    "iso:country":"US",
    "sg:address":"32501 NE 50th St",
    "sg:city":"Carnation",
    "sg:classifiers":[
        {
            "category":"Building & Trades",
            "subcategory":"Cleaning & Sanitation",
            "type":"Services"
        }
    ],
    "sg:phone":"+1 425 333 4821",
    "sg:postcode":"98014",
    "sg:province":"WA",
    "sg:tags":[
        "maintenance"
    ],
    "wof:name":"Dunn Janitorial",
    "wof:placetype":"venue"
},
  "geometry": {"coordinates":[-121.904511,47.651527],"type":"Point"}
}