{
  "type": "Feature",
  "properties": {
    "addr:full":"17237 148th Ave SE Yelm WA 98597",
    "addr:housenumber":"17237",
    "addr:postcode":"98597",
    "addr:street":"148Th Ave Se",
    "iso:country":"US",
    "sg:address":"17237 148th Ave SE",
    "sg:city":"Yelm",
    "sg:classifiers":[
        {
            "category":"Professional",
            "type":"Services"
        }
    ],
    "sg:phone":"+1 360 894 3368",
    "sg:postcode":"98597",
    "sg:province":"WA",
    "wof:name":"Rodney D Mercier",
    "wof:placetype":"venue"
},
  "geometry": {"coordinates":[-122.58135900000001,46.872216],"type":"Point"}
}