{
  "type": "Feature",
  "properties": {
    "addr:full":"1311 Lum Rd Centralia WA 98531",
    "addr:housenumber":"1311",
    "addr:postcode":"98531",
    "addr:street":"Lum Rd",
    "iso:country":"US",
    "sg:address":"1311 Lum Rd",
    "sg:city":"Centralia",
    "sg:classifiers":[
        {
            "category":"Home & Garden",
            "subcategory":"Home Furnishings",
            "type":"Retail Goods"
        }
    ],
    "sg:phone":"+1 360 330 5053",
    "sg:postcode":"98531",
    "sg:province":"WA",
    "sg:tags":[
        "dinnerware"
    ],
    "wof:name":"Pfaltzgraff Factory Store",
    "wof:placetype":"venue"
},
  "geometry": {"coordinates":[-122.977694,46.730703],"type":"Point"}
}