{
  "type": "Feature",
  "properties": {
    "addr:full":"53 S Dawson St Seattle WA 98134",
    "addr:housenumber":"53",
    "addr:postcode":"98134",
    "addr:street":"S Dawson St",
    "iso:country":"US",
    "sg:address":"53 S Dawson St",
    "sg:city":"Seattle",
    "sg:classifiers":[
        {
            "category":"Transit Center",
            "subcategory":"Freight",
            "type":"Transportation"
        },
        {
            "category":"Freight",
            "type":"Transportation"
        }
    ],
    "sg:phone":"+1 206 768 1801",
    "sg:postcode":"98134",
    "sg:province":"WA",
    "sg:tags":[
        "trucking-motor",
        "trucking"
    ],
    "sg:website":"http://www.vashonuu.org",
    "wof:name":"Dispatch Office",
    "wof:placetype":"venue"
},
  "geometry": {"coordinates":[-122.336663,47.555719],"type":"Point"}
}