{
  "type": "Feature",
  "properties": {
    "iso:country":"US",
    "sg:address":"22912 Hwy 99",
    "sg:city":"Edmonds",
    "sg:classifiers":[
        {
            "category":"Autos & Motor Vehicles",
            "subcategory":"Auto Supplies",
            "type":"Retail Goods"
        }
    ],
    "sg:phone":"+1 425 775 1995",
    "sg:postcode":"98026",
    "sg:province":"WA",
    "sg:tags":[
        "automobile",
        "parts"
    ],
    "sg:website":"www.natlap.com",
    "wof:name":"National Auto Parts",
    "wof:placetype":"venue"
},
  "geometry": {"coordinates":[-122.33762,47.791603],"type":"Point"}
}