{
  "type": "Feature",
  "properties": {
    "addr:full":"6717 Seabeck Holly Rd NW Seabeck WA 98380",
    "addr:housenumber":"6717",
    "addr:postcode":"98380",
    "addr:street":"Seabeck Holly Rd Nw",
    "iso:country":"US",
    "sg:address":"6717 Seabeck Holly Rd NW",
    "sg:city":"Seabeck",
    "sg:classifiers":[
        {
            "category":"Wholesale",
            "subcategory":"Construction Materials",
            "type":"Manufacturing & Wholesale Goods"
        }
    ],
    "sg:phone":"+1 360 830 4271",
    "sg:postcode":"98380",
    "sg:province":"WA",
    "sg:tags":[
        "fence"
    ],
    "wof:name":"Pick-It Fence",
    "wof:placetype":"venue"
},
  "geometry": {"coordinates":[-122.837923,47.627242],"type":"Point"}
}