{
  "type": "Feature",
  "properties": {
    "addr:full":"121 1st Ave S Seattle WA 98104",
    "addr:housenumber":"121",
    "addr:postcode":"98104",
    "addr:street":"1St Ave S",
    "iso:country":"US",
    "sg:address":"121 1st Ave S",
    "sg:city":"Seattle",
    "sg:classifiers":[
        {
            "category":"Home & Garden",
            "subcategory":"Carpets & Floor Coverings",
            "type":"Retail Goods"
        }
    ],
    "sg:phone":"+1 206 622 2439",
    "sg:postcode":"98104",
    "sg:province":"WA",
    "sg:tags":[
        "carpeting"
    ],
    "sg:website":"yamorientalrugs.com",
    "wof:name":"Yam Oriental Rugs",
    "wof:placetype":"venue"
},
  "geometry": {"coordinates":[-122.33426799999999,47.601053],"type":"Point"}
}