{
  "type": "Feature",
  "properties": {
    "addr:full":"227 Williams Ave S Renton WA 98057",
    "addr:housenumber":"227",
    "addr:postcode":"98057",
    "addr:street":"Williams Ave S Renton",
    "iso:country":"US",
    "sg:address":"227 Williams Ave S",
    "sg:city":"Renton",
    "sg:classifiers":[
        {
            "category":"Professional",
            "subcategory":"Art Services",
            "type":"Services"
        }
    ],
    "sg:phone":"+1 425 738 4505",
    "sg:postcode":"98057",
    "sg:province":"WA",
    "sg:tags":[
        "graphic",
        "design"
    ],
    "sg:website":"www.4worddesign.com",
    "wof:name":"4Word Design",
    "wof:placetype":"venue"
},
  "geometry": {"coordinates":[-122.20702300000001,47.480104],"type":"Point"}
}