{
  "type": "Feature",
  "properties": {
    "addr:full":"3903 Southlake Dr Richland WA 99353",
    "addr:housenumber":"3903",
    "addr:postcode":"99353",
    "addr:street":"Southlake Dr",
    "iso:country":"US",
    "sg:address":"3903 Southlake Dr",
    "sg:city":"Richland",
    "sg:classifiers":[
        {
            "category":"Manufacturing",
            "subcategory":"Tools & Machinery",
            "type":"Manufacturing & Wholesale Goods"
        }
    ],
    "sg:phone":"+1 509 539 6514",
    "sg:postcode":"99353",
    "sg:province":"WA",
    "sg:tags":[
        "conductive",
        "wiring",
        "devices",
        "mfg"
    ],
    "wof:name":"Manthei Industries LLC",
    "wof:placetype":"venue"
},
  "geometry": {"coordinates":[-119.33958,46.267668],"type":"Point"}
}