{
  "type": "Feature",
  "properties": {
    "addr:full":"8107 195th St E Spanaway WA 98387",
    "addr:housenumber":"8107",
    "addr:postcode":"98387",
    "addr:street":"195Th St E",
    "iso:country":"US",
    "sg:address":"8107 195th St E",
    "sg:city":"Spanaway",
    "sg:classifiers":[
        {
            "category":"Professional",
            "subcategory":"Management & Consulting",
            "type":"Services"
        }
    ],
    "sg:phone":"+1 253 846 8503",
    "sg:postcode":"98387",
    "sg:province":"WA",
    "sg:tags":[
        "business"
    ],
    "wof:name":"Masters Own",
    "wof:placetype":"venue"
},
  "geometry": {"coordinates":[-122.321682,47.079382],"type":"Point"}
}