{
  "type": "Feature",
  "properties": {
    "addr:full":"424 Billy Smith Rd Port Angeles WA 98362",
    "addr:housenumber":"424",
    "addr:postcode":"98362",
    "addr:street":"Billy Smith Rd",
    "iso:country":"US",
    "sg:address":"424 Billy Smith Rd",
    "sg:city":"Port Angeles",
    "sg:classifiers":[
        {
            "category":"Shopping",
            "subcategory":"Clothing, Apparel, & Fashions",
            "type":"Retail Goods"
        }
    ],
    "sg:phone":"+1 360 457 8114",
    "sg:postcode":"98362",
    "sg:province":"WA",
    "sg:tags":[
        "mfg"
    ],
    "wof:name":"DVine Inspirations",
    "wof:placetype":"venue"
},
  "geometry": {"coordinates":[-123.387011,48.083276],"type":"Point"}
}