{
  "type": "Feature",
  "properties": {
    "addr:full":"9907 19th Ave SE Everett WA 98208",
    "addr:housenumber":"9907",
    "addr:postcode":"98208",
    "addr:street":"19Th Ave Se",
    "iso:country":"US",
    "sg:address":"9907 19th Ave SE",
    "sg:city":"Everett",
    "sg:classifiers":[
        {
            "category":"Organizations",
            "subcategory":"Religious Organization",
            "type":"Services"
        }
    ],
    "sg:phone":"+1 425 337 8586",
    "sg:postcode":"98208",
    "sg:province":"WA",
    "wof:name":"Church of Christ",
    "wof:placetype":"venue"
},
  "geometry": {"coordinates":[-122.206964,47.90835],"type":"Point"}
}