{
  "type": "Feature",
  "properties": {
    "addr:full":"1056 Walnut St Bremerton WA 98310",
    "addr:housenumber":"1056",
    "addr:postcode":"98310",
    "addr:street":"Walnut St",
    "iso:country":"US",
    "sg:address":"1056 Walnut St",
    "sg:city":"Bremerton",
    "sg:classifiers":[
        {
            "category":"Building & Trades",
            "subcategory":"Construction",
            "type":"Services"
        }
    ],
    "sg:phone":"+1 360 479 2364",
    "sg:postcode":"98310",
    "sg:province":"WA",
    "sg:tags":[
        "general",
        "contractor"
    ],
    "wof:name":"R G Construction",
    "wof:placetype":"venue"
},
  "geometry": {"coordinates":[-122.621008,47.587405],"type":"Point"}
}