{
  "type": "Feature",
  "properties": {
    "addr:full":"15045 Bellevue Redmond Rd Bellevue WA 98007",
    "addr:housenumber":"15045",
    "addr:postcode":"98007",
    "addr:street":"Bellevue Redmond Rd",
    "iso:country":"US",
    "sg:address":"15045 Bellevue Redmond Rd",
    "sg:city":"Bellevue",
    "sg:classifiers":[
        {
            "category":"Restaurant",
            "type":"Food & Drink"
        }
    ],
    "sg:phone":"+1 425 401 0823",
    "sg:postcode":"98007",
    "sg:province":"WA",
    "sg:tags":[
        "eating"
    ],
    "wof:name":"Saigon City",
    "wof:placetype":"venue"
},
  "geometry": {"coordinates":[-122.140469,47.626823],"type":"Point"}
}