{
  "type": "Feature",
  "properties": {
    "iso:country":"US",
    "sg:address":"26275 103rd St SE",
    "sg:city":"Monroe",
    "sg:classifiers":[
        {
            "category":"Professional",
            "type":"Services"
        }
    ],
    "sg:phone":"+1 360 794 5629",
    "sg:postcode":"98272",
    "sg:province":"WA",
    "wof:name":"Jason Bronson",
    "wof:placetype":"venue"
},
  "geometry": {"coordinates":[-121.881328,47.904288],"type":"Point"}
}