{
  "type": "Feature",
  "properties": {
    "addr:full":"22516 SE 64th Pl Issaquah WA 98027",
    "addr:postcode":"22516;98027",
    "addr:street":"Se 64Th Pl",
    "iso:country":"US",
    "sg:address":"22516 SE 64th Pl",
    "sg:city":"Issaquah",
    "sg:classifiers":[
        {
            "category":"Insurance",
            "subcategory":"Insurance Agent",
            "type":"Services"
        }
    ],
    "sg:phone":"+1 425 391 8731",
    "sg:postcode":"98027",
    "sg:province":"WA",
    "wof:name":"Cox Insurance",
    "wof:placetype":"venue"
},
  "geometry": {"coordinates":[-122.03983700000001,47.544181],"type":"Point"}
}