{
  "type": "Feature",
  "properties": {
    "iso:country":"US",
    "sg:address":"6707 W Clearwater Ave",
    "sg:city":"Kennewick",
    "sg:classifiers":[
        {
            "category":"Retail",
            "subcategory":"Car Wash",
            "type":"Services"
        }
    ],
    "sg:phone":"+1 509 735 2622",
    "sg:postcode":"99336",
    "sg:province":"WA",
    "wof:name":"Hura Clean Car Wash",
    "wof:placetype":"venue"
},
  "geometry": {"coordinates":[-119.210751,46.210766],"type":"Point"}
}