{
  "type": "Feature",
  "properties": {
    "addr:full":"115 Prefontaine Pl S Seattle WA 98104",
    "addr:housenumber":"115",
    "addr:postcode":"98104",
    "addr:street":"Prefontaine Pl S",
    "iso:country":"US",
    "sg:address":"115 Prefontaine Pl S",
    "sg:city":"Seattle",
    "sg:classifiers":[
        {
            "category":"Health Services",
            "subcategory":"Clinic",
            "type":"Services"
        }
    ],
    "sg:phone":"+1 206 682 3181",
    "sg:postcode":"98104",
    "sg:province":"WA",
    "sg:tags":[
        "banks",
        "blood",
        "center"
    ],
    "wof:name":"Alpha Therapeutic Corp",
    "wof:placetype":"venue"
},
  "geometry": {"coordinates":[-122.329132,47.600955],"type":"Point"}
}