{
  "type": "Feature",
  "properties": {
    "addr:full":"409 N Ruby St Ellensburg WA 98926",
    "addr:housenumber":"409",
    "addr:postcode":"98926",
    "addr:street":"N Ruby St",
    "iso:country":"US",
    "sg:address":"409 N Ruby St",
    "sg:city":"Ellensburg",
    "sg:classifiers":[
        {
            "category":"Restaurant",
            "type":"Food & Drink"
        }
    ],
    "sg:phone":"+1 509 933 3001",
    "sg:postcode":"98926",
    "sg:province":"WA",
    "wof:name":"Valley Espresso & Burgers",
    "wof:placetype":"venue"
},
  "geometry": {"coordinates":[-120.544653,46.99651],"type":"Point"}
}