{
  "type": "Feature",
  "properties": {
    "addr:full":"1724 3rd St Marysville WA 98270",
    "addr:housenumber":"1724",
    "addr:postcode":"98270",
    "addr:street":"3Rd St",
    "iso:country":"US",
    "sg:address":"1724 3rd St",
    "sg:city":"Marysville",
    "sg:classifiers":[
        {
            "category":"Retail",
            "subcategory":"Laundry & Dry Cleaning",
            "type":"Services"
        }
    ],
    "sg:phone":"+1 360 653 4625",
    "sg:postcode":"98270",
    "sg:province":"WA",
    "sg:tags":[
        "alterations-clothing"
    ],
    "wof:name":"Altered Images",
    "wof:placetype":"venue"
},
  "geometry": {"coordinates":[-122.172618,48.050898],"type":"Point"}
}