{
  "type": "Feature",
  "properties": {
    "addr:full":"414 Boren Ave N Seattle WA 98109",
    "addr:housenumber":"414",
    "addr:postcode":"98109",
    "addr:street":"Boren Ave N",
    "iso:country":"US",
    "sg:address":"414 Boren Ave N",
    "sg:city":"Seattle",
    "sg:classifiers":[
        {
            "category":"Shopping",
            "subcategory":"Florist",
            "type":"Retail Goods"
        }
    ],
    "sg:phone":"+1 206 344 3966",
    "sg:postcode":"98109",
    "sg:province":"WA",
    "wof:name":"Floral Indotsmant",
    "wof:placetype":"venue"
},
  "geometry": {"coordinates":[-122.335837,47.622205],"type":"Point"}
}