{
  "type": "Feature",
  "properties": {
    "addr:full":"32715 NE 9th St Washougal WA 98671",
    "addr:housenumber":"32715",
    "addr:postcode":"98671",
    "addr:street":"Ne 9Th St",
    "iso:country":"US",
    "sg:address":"32715 NE 9th St",
    "sg:city":"Washougal",
    "sg:classifiers":[
        {
            "category":"Professional",
            "type":"Services"
        }
    ],
    "sg:phone":"+1 360 835 0430",
    "sg:postcode":"98671",
    "sg:province":"WA",
    "wof:name":"Fariha",
    "wof:placetype":"venue"
},
  "geometry": {"coordinates":[-122.33793,45.628866],"type":"Point"}
}