{
  "type": "Feature",
  "properties": {
    "addr:full":"12560 Corliss Ave N Seattle WA 98133",
    "addr:housenumber":"12560",
    "addr:postcode":"98133",
    "addr:street":"Corliss Ave N",
    "iso:country":"US",
    "sg:address":"12560 Corliss Ave N",
    "sg:city":"Seattle",
    "sg:classifiers":[
        {
            "category":"Building & Trades",
            "subcategory":"Construction",
            "type":"Services"
        }
    ],
    "sg:phone":"+1 206 363 9757",
    "sg:postcode":"98133",
    "sg:province":"WA",
    "sg:tags":[
        "house"
    ],
    "wof:name":"Wsw Custom Homes LLC",
    "wof:placetype":"venue"
},
  "geometry": {"coordinates":[-122.331002,47.721986],"type":"Point"}
}