{
  "type": "Feature",
  "properties": {
    "addr:full":"4407 144th Ave SE Bellevue WA 98006",
    "addr:housenumber":"4407",
    "addr:postcode":"98006",
    "addr:street":"144Th Ave Se",
    "iso:country":"US",
    "sg:address":"4407 144th Ave SE",
    "sg:city":"Bellevue",
    "sg:classifiers":[
        {
            "category":"Professional",
            "subcategory":"Business Services",
            "type":"Services"
        }
    ],
    "sg:phone":"+1 425 865 9802",
    "sg:postcode":"98006",
    "sg:province":"WA",
    "wof:name":"Pearsall William E",
    "wof:placetype":"venue"
},
  "geometry": {"coordinates":[-122.148627,47.565697],"type":"Point"}
}