{
  "type": "Feature",
  "properties": {
    "addr:full":"770 Hoffman St Woodland WA 98674",
    "addr:housenumber":"770",
    "addr:postcode":"98674",
    "addr:street":"Hoffman St",
    "iso:country":"US",
    "sg:address":"770 Hoffman St",
    "sg:city":"Woodland",
    "sg:classifiers":[
        {
            "category":"Wholesale",
            "subcategory":"Vending Machines",
            "type":"Manufacturing & Wholesale Goods"
        }
    ],
    "sg:phone":"+1 253 225 7573",
    "sg:postcode":"98674",
    "sg:province":"WA",
    "sg:tags":[
        "operator"
    ],
    "wof:name":"Snackn Good",
    "wof:placetype":"venue"
},
  "geometry": {"coordinates":[-122.74632200000001,45.904052],"type":"Point"}
}