{
  "type": "Feature",
  "properties": {
    "addr:full":"2926 E Bay Dr NW Gig Harbor WA 98335",
    "addr:housenumber":"2926",
    "addr:postcode":"98335",
    "addr:street":"E Bay Dr Nw",
    "iso:country":"US",
    "sg:address":"2926 E Bay Dr NW",
    "sg:city":"Gig Harbor",
    "sg:classifiers":[
        {
            "category":"Retail",
            "subcategory":"Laundry & Dry Cleaning",
            "type":"Services"
        }
    ],
    "sg:phone":"+1 253 759 4100",
    "sg:postcode":"98335",
    "sg:province":"WA",
    "wof:name":"Carbo Clean",
    "wof:placetype":"venue"
},
  "geometry": {"coordinates":[-122.600505,47.286349],"type":"Point"}
}