{
  "type": "Feature",
  "properties": {
    "addr:full":"4903 108th St SW Tacoma WA 98499",
    "addr:housenumber":"4903",
    "addr:postcode":"98499",
    "addr:street":"108Th St Sw",
    "iso:country":"US",
    "sg:address":"4903 108th St SW",
    "sg:city":"Tacoma",
    "sg:classifiers":[
        {
            "category":"Health Services",
            "subcategory":"Doctor",
            "type":"Services"
        }
    ],
    "sg:phone":"+1 253 984 7247",
    "sg:postcode":"98499",
    "sg:province":"WA",
    "sg:tags":[
        "physician",
        "surgeon"
    ],
    "wof:name":"Home Doctor",
    "wof:placetype":"venue"
},
  "geometry": {"coordinates":[-122.503568,47.159526],"type":"Point"}
}