{
  "type": "Feature",
  "properties": {
    "addr:full":"9419 16th Pl NE Lake Stevens WA 98258",
    "addr:housenumber":"9419",
    "addr:postcode":"98258",
    "addr:street":"16Th Pl Ne",
    "iso:country":"US",
    "sg:address":"9419 16th Pl NE",
    "sg:city":"Lake Stevens",
    "sg:classifiers":[
        {
            "category":"Professional",
            "type":"Services"
        }
    ],
    "sg:phone":"+1 425 418 6787",
    "sg:postcode":"98258",
    "sg:province":"WA",
    "wof:name":"Sun Pros",
    "wof:placetype":"venue"
},
  "geometry": {"coordinates":[-122.105357,48.010692],"type":"Point"}
}