{
  "type": "Feature",
  "properties": {
    "addr:full":"250 Pleasant Hills Dr Yakima WA 98908",
    "addr:housenumber":"250",
    "addr:postcode":"98908",
    "addr:street":"Pleasant Hills Dr",
    "iso:country":"US",
    "sg:address":"250 Pleasant Hills Dr",
    "sg:city":"Yakima",
    "sg:classifiers":[
        {
            "category":"Farming",
            "subcategory":"Nursery",
            "type":"Manufacturing & Wholesale Goods"
        }
    ],
    "sg:phone":"+1 509 966 2363",
    "sg:postcode":"98908",
    "sg:province":"WA",
    "sg:tags":[
        "ornamental"
    ],
    "wof:name":"Monsanto",
    "wof:placetype":"venue"
},
  "geometry": {"coordinates":[-120.60162099999999,46.666822],"type":"Point"}
}