{
  "type": "Feature",
  "properties": {
    "addr:full":"13715 310th Ave SE Sultan WA 98294",
    "addr:housenumber":"13715",
    "addr:postcode":"98294",
    "addr:street":"310Th Ave Se Sultan",
    "iso:country":"US",
    "sg:address":"13715 310th Ave SE",
    "sg:city":"Sultan",
    "sg:classifiers":[
        {
            "category":"Education",
            "subcategory":"School",
            "type":"Public Place"
        }
    ],
    "sg:phone":"+1 360 793 9860",
    "sg:postcode":"98294",
    "sg:province":"WA",
    "sg:website":"www.sultan.k12.wa.us",
    "wof:name":"Sultan High School",
    "wof:placetype":"venue"
},
  "geometry": {"coordinates":[-121.815141,47.873299],"type":"Point"}
}