{
  "type": "Feature",
  "properties": {
    "addr:full":"2707 Colby Ave Everett WA 98201",
    "addr:housenumber":"2707",
    "addr:postcode":"98201",
    "addr:street":"Colby Ave",
    "iso:country":"US",
    "sg:address":"2707 Colby Ave",
    "sg:city":"Everett",
    "sg:classifiers":[
        {
            "category":"Professional",
            "subcategory":"Accounting & Tax Preparation",
            "type":"Services"
        }
    ],
    "sg:phone":"+1 425 261 2272",
    "sg:postcode":"98201",
    "sg:province":"WA",
    "sg:tags":[
        "accountant"
    ],
    "wof:name":"Moss Adams LLC",
    "wof:placetype":"venue"
},
  "geometry": {"coordinates":[-122.208502,47.980712],"type":"Point"}
}