{
  "type": "Feature",
  "properties": {
    "addr:full":"1800 Index Ave NE Renton WA 98056",
    "addr:housenumber":"1800",
    "addr:postcode":"98056",
    "addr:street":"Index Ave Ne",
    "iso:country":"US",
    "sg:address":"1800 Index Ave NE",
    "sg:city":"Renton",
    "sg:classifiers":[
        {
            "category":"Education",
            "subcategory":"School",
            "type":"Public Place"
        }
    ],
    "sg:phone":"+1 425 204 2200",
    "sg:postcode":"98056",
    "sg:province":"WA",
    "wof:name":"Hillcrest Schl Spcial Svcs Ctr",
    "wof:placetype":"venue"
},
  "geometry": {"coordinates":[-122.18221,47.507922],"type":"Point"}
}