{
  "type": "Feature",
  "properties": {
    "addr:full":"104 N 92nd Ave Yakima WA 98908",
    "addr:housenumber":"104",
    "addr:postcode":"98908",
    "addr:street":"N 92Nd Ave",
    "iso:country":"US",
    "sg:address":"104 N 92nd Ave",
    "sg:city":"Yakima",
    "sg:classifiers":[
        {
            "category":"Shopping",
            "subcategory":"Gifts & Souvenirs",
            "type":"Retail Goods"
        }
    ],
    "sg:phone":"+1 509 965 7235",
    "sg:postcode":"98908",
    "sg:province":"WA",
    "wof:name":"Simply Unique Gift Baskets",
    "wof:placetype":"venue"
},
  "geometry": {"coordinates":[-120.631367,46.598539],"type":"Point"}
}