{
  "type": "Feature",
  "properties": {
    "addr:full":"1810 15th Pl NW Issaquah WA 98027",
    "addr:housenumber":"1810",
    "addr:postcode":"98027",
    "addr:street":"15Th Pl Nw",
    "iso:country":"US",
    "sg:address":"1810 15th Pl NW",
    "sg:city":"Issaquah",
    "sg:classifiers":[
        {
            "category":"Health Services",
            "subcategory":"Doctor",
            "type":"Services"
        }
    ],
    "sg:phone":"+1 425 392 4600",
    "sg:postcode":"98027",
    "sg:province":"WA",
    "wof:name":"Schmedding Troy A DDS PS",
    "wof:placetype":"venue"
},
  "geometry": {"coordinates":[-122.060329,47.551537],"type":"Point"}
}