{
  "type": "Feature",
  "properties": {
    "addr:full":"8623 216th St SE Woodinville WA 98072",
    "addr:housenumber":"8623",
    "addr:postcode":"98072",
    "addr:street":"216Th St Se",
    "iso:country":"US",
    "sg:address":"8623 216th St SE",
    "sg:city":"Woodinville",
    "sg:classifiers":[
        {
            "category":"Building & Trades",
            "subcategory":"Construction",
            "type":"Services"
        }
    ],
    "sg:phone":"+1 425 806 9735",
    "sg:postcode":"98072",
    "sg:province":"WA",
    "sg:tags":[
        "general",
        "contractor"
    ],
    "wof:name":"Howard S Wright Construction",
    "wof:placetype":"venue"
},
  "geometry": {"coordinates":[-122.11709,47.801497],"type":"Point"}
}