{
  "type": "Feature",
  "properties": {
    "addr:full":"815 E 35th Ave Spokane WA 99203",
    "addr:housenumber":"815",
    "addr:postcode":"99203",
    "addr:street":"E 35Th Ave",
    "iso:country":"US",
    "sg:address":"815 E 35th Ave",
    "sg:city":"Spokane",
    "sg:classifiers":[
        {
            "category":"Professional",
            "subcategory":"Secretarial Services",
            "type":"Services"
        }
    ],
    "sg:phone":"+1 509 624 4520",
    "sg:postcode":"99203",
    "sg:province":"WA",
    "sg:tags":[
        "reporting"
    ],
    "wof:name":"Spokane Interview Specialists",
    "wof:placetype":"venue"
},
  "geometry": {"coordinates":[-117.398106,47.622601],"type":"Point"}
}