{
  "type": "Feature",
  "properties": {
    "addr:full":"11650 102nd Pl NE Kirkland WA 98034",
    "addr:housenumber":"11650",
    "addr:postcode":"98034",
    "addr:street":"102Nd Pl Ne",
    "iso:country":"US",
    "sg:address":"11650 102nd Pl NE",
    "sg:city":"Kirkland",
    "sg:classifiers":[
        {
            "category":"Shopping",
            "subcategory":"Department Store",
            "type":"Retail Goods"
        }
    ],
    "sg:phone":"+1 425 821 7211",
    "sg:postcode":"98034",
    "sg:province":"WA",
    "wof:name":"As Seen On TV Store The",
    "wof:placetype":"venue"
},
  "geometry": {"coordinates":[-122.20492400000001,47.705184],"type":"Point"}
}