{
  "type": "Feature",
  "properties": {
    "addr:full":"510 W Lewis St Pasco WA 99301",
    "addr:housenumber":"510",
    "addr:postcode":"99301",
    "addr:street":"W Lewis St",
    "iso:country":"US",
    "sg:address":"510 W Lewis St",
    "sg:city":"Pasco",
    "sg:classifiers":[
        {
            "category":"Restaurant",
            "type":"Food & Drink"
        }
    ],
    "sg:phone":"+1 509 543 6884",
    "sg:postcode":"99301",
    "sg:province":"WA",
    "sg:tags":[
        "mexican"
    ],
    "wof:name":"Fiesta Mexican Restaurant",
    "wof:placetype":"venue"
},
  "geometry": {"coordinates":[-119.093002,46.230499],"type":"Point"}
}