{
  "type": "Feature",
  "properties": {
    "addr:full":"43910 N Demoss Rd Benton City WA 99320",
    "addr:housenumber":"43910",
    "addr:postcode":"99320",
    "addr:street":"N Demoss Rd",
    "iso:country":"US",
    "sg:address":"43910 N Demoss Rd",
    "sg:city":"Benton City",
    "sg:classifiers":[
        {
            "category":"Building & Trades",
            "subcategory":"Plumbing",
            "type":"Services"
        }
    ],
    "sg:phone":"+1 509 588 4849",
    "sg:postcode":"99320",
    "sg:province":"WA",
    "sg:tags":[
        "excavation",
        "contractor"
    ],
    "wof:name":"Emmons General Contractors",
    "wof:placetype":"venue"
},
  "geometry": {"coordinates":[-119.470668,46.285444],"type":"Point"}
}