{
  "type": "Feature",
  "properties": {
    "addr:full":"806 112th St E Tacoma WA 98445",
    "addr:housenumber":"806",
    "addr:postcode":"98445",
    "addr:street":"112Th St",
    "iso:country":"US",
    "sg:address":"806 112th St E",
    "sg:city":"Tacoma",
    "sg:classifiers":[
        {
            "category":"Real Estate",
            "subcategory":"Real Estate Operator",
            "type":"Services"
        }
    ],
    "sg:phone":"+1 253 537 0303",
    "sg:postcode":"98445",
    "sg:province":"WA",
    "sg:tags":[
        "apartment"
    ],
    "wof:name":"Autumn Woods Apts Clubhouse",
    "wof:placetype":"venue"
},
  "geometry": {"coordinates":[-122.41704,47.155108],"type":"Point"}
}