{
  "type": "Feature",
  "properties": {
    "addr:full":"19819 136th Ave NE Woodinville WA 98072",
    "addr:housenumber":"19819",
    "addr:postcode":"98072",
    "addr:street":"136Th Ave Ne",
    "iso:country":"US",
    "sg:address":"19819 136th Ave NE",
    "sg:city":"Woodinville",
    "sg:classifiers":[
        {
            "category":"Education",
            "subcategory":"School",
            "type":"Public Place"
        }
    ],
    "sg:phone":"+1 425 489 6700",
    "sg:postcode":"98072",
    "sg:province":"WA",
    "wof:name":"Woodinville Senior High School",
    "wof:placetype":"venue"
},
  "geometry": {"coordinates":[-122.15859,47.769254],"type":"Point"}
}