{
  "type": "Feature",
  "properties": {
    "addr:full":"327 W Lewis St Pasco WA 99301",
    "addr:housenumber":"327",
    "addr:postcode":"99301",
    "addr:street":"W Lewis St",
    "iso:country":"US",
    "sg:address":"327 W Lewis St",
    "sg:city":"Pasco",
    "sg:classifiers":[
        {
            "category":"Restaurant",
            "type":"Food & Drink"
        }
    ],
    "sg:phone":"+1 509 543 3796",
    "sg:postcode":"99301",
    "sg:province":"WA",
    "sg:tags":[
        "eating",
        "nightlife"
    ],
    "wof:name":"Out And About",
    "wof:placetype":"venue"
},
  "geometry": {"coordinates":[-119.089996,46.230999],"type":"Point"}
}