{
  "type": "Feature",
  "properties": {
    "addr:full":"6182 Apollo Dr Ferndale WA 98248",
    "addr:housenumber":"6182",
    "addr:postcode":"98248",
    "addr:street":"Apollo Dr",
    "iso:country":"US",
    "sg:address":"6182 Apollo Dr",
    "sg:city":"Ferndale",
    "sg:classifiers":[
        {
            "category":"Shopping",
            "subcategory":"Computers & Home Electronics",
            "type":"Retail Goods"
        }
    ],
    "sg:phone":"+1 360 380 2403",
    "sg:postcode":"98248",
    "sg:province":"WA",
    "wof:name":"Hansen Computer Service",
    "wof:placetype":"venue"
},
  "geometry": {"coordinates":[-122.60740800000001,48.86593],"type":"Point"}
}