{
  "type": "Feature",
  "properties": {
    "iso:country":"US",
    "sg:address":"23837 108th Ave SE",
    "sg:city":"Kent",
    "sg:classifiers":[
        {
            "category":"Banks & Credit Unions",
            "subcategory":"Financial Services",
            "type":"Services"
        }
    ],
    "sg:phone":"+1 206 369 7288",
    "sg:postcode":"98031",
    "sg:province":"WA",
    "sg:tags":[
        "contracting",
        "work",
        "charity"
    ],
    "wof:name":"Outreach Foundation",
    "wof:placetype":"venue"
},
  "geometry": {"coordinates":[-122.19701999999999,47.388315],"type":"Point"}
}