{
  "type": "Feature",
  "properties": {
    "addr:full":"129 173rd Pl SE Bothell WA 98012",
    "addr:housenumber":"129",
    "addr:postcode":"98012",
    "addr:street":"173Rd Pl Se",
    "iso:country":"US",
    "sg:address":"129 173rd Pl SE",
    "sg:city":"Bothell",
    "sg:classifiers":[
        {
            "category":"Professional",
            "subcategory":"Business Services",
            "type":"Services"
        }
    ],
    "sg:phone":"+1 425 787 5827",
    "sg:postcode":"98012",
    "sg:province":"WA",
    "wof:name":"Richard Pilskog",
    "wof:placetype":"venue"
},
  "geometry": {"coordinates":[-122.22927,47.840792],"type":"Point"}
}