{
  "type": "Feature",
  "properties": {
    "addr:full":"16218 46th Ave S Tukwila WA 98188",
    "addr:housenumber":"16218",
    "addr:postcode":"98188",
    "addr:street":"46Th Ave S",
    "iso:country":"US",
    "sg:address":"16218 46th Ave S",
    "sg:city":"Tukwila",
    "sg:classifiers":[
        {
            "category":"Shopping",
            "subcategory":"Used Merchandise",
            "type":"Retail Goods"
        }
    ],
    "sg:phone":"+1 206 433 7777",
    "sg:postcode":"98188",
    "sg:province":"WA",
    "sg:tags":[
        "shop",
        "consignment"
    ],
    "wof:name":"Internet Auction Svc",
    "wof:placetype":"venue"
},
  "geometry": {"coordinates":[-122.275526,47.45764],"type":"Point"}
}