{
  "type": "Feature",
  "properties": {
    "addr:full":"6524 E Fourth Plain Blvd Vancouver WA 98661",
    "addr:housenumber":"6524",
    "addr:postcode":"98661",
    "addr:street":"E Fourth Plain Blvd",
    "iso:country":"US",
    "sg:address":"6524 E Fourth Plain Blvd",
    "sg:city":"Vancouver",
    "sg:classifiers":[
        {
            "category":"Banks & Credit Unions",
            "subcategory":"Bank",
            "type":"Services"
        }
    ],
    "sg:phone":"+1 360 737 2897",
    "sg:postcode":"98661",
    "sg:province":"WA",
    "sg:tags":[
        "financing"
    ],
    "wof:name":"United Finance Co",
    "wof:placetype":"venue"
},
  "geometry": {"coordinates":[-122.604668,45.644222],"type":"Point"}
}