{
  "type": "Feature",
  "properties": {
    "iso:country":"US",
    "sg:address":"25744 135th Pl SE",
    "sg:city":"Kent",
    "sg:classifiers":[
        {
            "category":"Professional",
            "subcategory":"Testing Lab",
            "type":"Services"
        }
    ],
    "sg:phone":"+1 253 630 3996",
    "sg:postcode":"98042",
    "sg:province":"WA",
    "sg:tags":[
        "asbestos"
    ],
    "wof:name":"Certified Ahera Asbestos",
    "wof:placetype":"venue"
},
  "geometry": {"coordinates":[-122.160715,47.371628],"type":"Point"}
}