{
  "type": "Feature",
  "properties": {
    "addr:full":"11905 Hwy 99 Everett WA 98204",
    "addr:housenumber":"11905",
    "addr:postcode":"98204",
    "addr:street":"Hwy 99",
    "iso:country":"US",
    "sg:address":"11905 Hwy 99",
    "sg:city":"Everett",
    "sg:classifiers":[
        {
            "category":"Restaurant",
            "type":"Food & Drink"
        }
    ],
    "sg:phone":"+1 425 513 1255",
    "sg:postcode":"98204",
    "sg:province":"WA",
    "sg:tags":[
        "eating"
    ],
    "wof:name":"Wendys",
    "wof:placetype":"venue"
},
  "geometry": {"coordinates":[-122.257857,47.890049],"type":"Point"}
}