{
  "type": "Feature",
  "properties": {
    "addr:full":"104 Morrison Heights Rd Woodland WA 98674",
    "addr:housenumber":"104",
    "addr:postcode":"98674",
    "addr:street":"Morrison Heights Rd",
    "iso:country":"US",
    "sg:address":"104 Morrison Heights Rd",
    "sg:city":"Woodland",
    "sg:classifiers":[
        {
            "category":"Shopping",
            "subcategory":"Gifts & Souvenirs",
            "type":"Retail Goods"
        }
    ],
    "sg:phone":"+1 360 225 1763",
    "sg:postcode":"98674",
    "sg:province":"WA",
    "wof:name":"Columbia Mist Alpacas Delgh Tr",
    "wof:placetype":"venue"
},
  "geometry": {"coordinates":[-122.764321,45.95863],"type":"Point"}
}