{
  "type": "Feature",
  "properties": {
    "addr:full":"1155 N State St Ste 426 Bellingham WA 98225",
    "addr:housenumber":"1155",
    "addr:postcode":"98225",
    "addr:street":"N State St Ste 426",
    "iso:country":"US",
    "sg:address":"1155 N State St Ste 426",
    "sg:city":"Bellingham",
    "sg:classifiers":[
        {
            "category":"Utilities",
            "subcategory":"Electric",
            "type":"Services"
        },
        {
            "category":"Manufacturing",
            "subcategory":"Electronics",
            "type":"Manufacturing & Wholesale Goods"
        }
    ],
    "sg:phone":"+1 360 306 5331",
    "sg:postcode":"98225",
    "sg:province":"WA",
    "sg:tags":[
        "equipment-testing"
    ],
    "wof:name":"Adams 1",
    "wof:placetype":"venue"
},
  "geometry": {"coordinates":[-122.479274,48.746932],"type":"Point"}
}