{
  "type": "Feature",
  "properties": {
    "addr:full":"8411 N Forest Ct Spokane WA 99208",
    "addr:housenumber":"8411",
    "addr:postcode":"99208",
    "addr:street":"N Forest Ct",
    "iso:country":"US",
    "sg:address":"8411 N Forest Ct",
    "sg:city":"Spokane",
    "sg:classifiers":[
        {
            "category":"Building & Trades",
            "subcategory":"Construction",
            "type":"Services"
        }
    ],
    "sg:phone":"+1 509 466 1392",
    "sg:postcode":"99208",
    "sg:province":"WA",
    "sg:tags":[
        "contractor"
    ],
    "wof:name":"Marx Construction",
    "wof:placetype":"venue"
},
  "geometry": {"coordinates":[-117.49557900000001,47.7342],"type":"Point"}
}