{
  "type": "Feature",
  "properties": {
    "addr:full":"1424 4th Ave Ste 702 Seattle WA 98101",
    "addr:housenumber":"1424",
    "addr:postcode":"98101",
    "addr:street":"4Th Ave Ste 702",
    "iso:country":"US",
    "sg:address":"1424 4th Ave Ste 702",
    "sg:city":"Seattle",
    "sg:classifiers":[
        {
            "category":"Shopping",
            "subcategory":"Jewelry",
            "type":"Retail Goods"
        }
    ],
    "sg:phone":"+1 206 223 2305",
    "sg:postcode":"98101",
    "sg:province":"WA",
    "sg:tags":[
        "watch",
        "jeweler"
    ],
    "wof:name":"Won's Jewelry",
    "wof:placetype":"venue"
},
  "geometry": {"coordinates":[-122.33600300000001,47.609435],"type":"Point"}
}