{
  "type": "Feature",
  "properties": {
    "iso:country":"US",
    "sg:address":"3400 Beacon Ave S",
    "sg:city":"Seattle",
    "sg:classifiers":[
        {
            "category":"Professional",
            "subcategory":"Business Services",
            "type":"Services"
        }
    ],
    "sg:phone":"+1 206 624 9465",
    "sg:postcode":"98144",
    "sg:province":"WA",
    "sg:website":"www.theactorsgroup.com",
    "wof:name":"Actors Group",
    "wof:placetype":"venue"
},
  "geometry": {"coordinates":[-122.30824699999999,47.571901],"type":"Point"}
}