{
  "type": "Feature",
  "properties": {
    "addr:full":"16014 NW 6th Ave Ridgefield WA 98642",
    "addr:housenumber":"16014",
    "addr:postcode":"98642",
    "addr:street":"Nw 6Th Ave",
    "iso:country":"US",
    "sg:address":"16014 NW 6th Ave",
    "sg:city":"Ridgefield",
    "sg:classifiers":[
        {
            "category":"Manufacturing",
            "subcategory":"Tools & Machinery",
            "type":"Manufacturing & Wholesale Goods"
        }
    ],
    "sg:phone":"+1 360 576 8007",
    "sg:postcode":"98642",
    "sg:province":"WA",
    "sg:tags":[
        "lighting"
    ],
    "wof:name":"Government Supply Source LLC",
    "wof:placetype":"venue"
},
  "geometry": {"coordinates":[-122.67574999999999,45.738092],"type":"Point"}
}