{
  "type": "Feature",
  "properties": {
    "addr:full":"1035 Beach Ave Marysville WA 98270",
    "addr:housenumber":"1035",
    "addr:postcode":"98270",
    "addr:street":"Beach Ave",
    "iso:country":"US",
    "sg:address":"1035 Beach Ave",
    "sg:city":"Marysville",
    "sg:classifiers":[
        {
            "category":"Banks & Credit Unions",
            "subcategory":"Investment Brokerage",
            "type":"Services"
        }
    ],
    "sg:phone":"+1 425 252 6641",
    "sg:postcode":"98270",
    "sg:province":"WA",
    "sg:website":"http://www.lienresearch.com",
    "wof:name":"Lien Research Corp",
    "wof:placetype":"venue"
},
  "geometry": {"coordinates":[-122.182135,48.057301],"type":"Point"}
}