{
  "type": "Feature",
  "properties": {
    "addr:full":"1126 N 198th St Seattle WA 98133",
    "addr:housenumber":"1126",
    "addr:postcode":"98133",
    "addr:street":"N 198Th St",
    "iso:country":"US",
    "sg:address":"1126 N 198th St",
    "sg:city":"Seattle",
    "sg:classifiers":[
        {
            "category":"Real Estate",
            "subcategory":"Real Estate Operator",
            "type":"Services"
        }
    ],
    "sg:phone":"+1 206 542 0620",
    "sg:postcode":"98133",
    "sg:province":"WA",
    "sg:tags":[
        "building",
        "apartment"
    ],
    "wof:name":"Echo Lk Waterfront Apartments",
    "wof:placetype":"venue"
},
  "geometry": {"coordinates":[-122.345406,47.772405],"type":"Point"}
}