{
  "type": "Feature",
  "properties": {
    "addr:full":"703 S Pekin Rd Woodland WA 98674",
    "addr:housenumber":"703",
    "addr:postcode":"98674",
    "addr:street":"S Pekin Rd",
    "iso:country":"US",
    "sg:address":"703 S Pekin Rd",
    "sg:city":"Woodland",
    "sg:classifiers":[
        {
            "category":"Retail",
            "subcategory":"Repair Shop",
            "type":"Services"
        }
    ],
    "sg:phone":"+1 360 225 6202",
    "sg:postcode":"98674",
    "sg:province":"WA",
    "wof:name":"South Pekin Taxidermy",
    "wof:placetype":"venue"
},
  "geometry": {"coordinates":[-122.736064,45.884281],"type":"Point"}
}