{
  "type": "Feature",
  "properties": {
    "addr:full":"1037 Central Ave S Kent WA 98032",
    "addr:housenumber":"1037",
    "addr:postcode":"98032",
    "addr:street":"Central Ave S",
    "iso:country":"US",
    "sg:address":"1037 Central Ave S",
    "sg:city":"Kent",
    "sg:classifiers":[
        {
            "category":"Autos & Motor Vehicles",
            "subcategory":"Automobile Sales",
            "type":"Retail Goods"
        }
    ],
    "sg:phone":"+1 206 234 5277",
    "sg:postcode":"98032",
    "sg:province":"WA",
    "wof:name":"Reliable Imports Intl LLC",
    "wof:placetype":"venue"
},
  "geometry": {"coordinates":[-122.23037100000001,47.374033],"type":"Point"}
}