{
  "type": "Feature",
  "properties": {
    "addr:full":"1108 E Farwell Rd Spokane WA 99208",
    "addr:housenumber":"1108",
    "addr:postcode":"99208",
    "addr:street":"E Farwell Rd",
    "iso:country":"US",
    "sg:address":"1108 E Farwell Rd",
    "sg:city":"Spokane",
    "sg:classifiers":[
        {
            "category":"Building & Trades",
            "subcategory":"Plumbing",
            "type":"Services"
        }
    ],
    "sg:phone":"+1 509 466 9399",
    "sg:postcode":"99208",
    "sg:province":"WA",
    "sg:tags":[
        "plumbing",
        "contractor"
    ],
    "wof:name":"Summit Mechanical Inc",
    "wof:placetype":"venue"
},
  "geometry": {"coordinates":[-117.394813,47.772802],"type":"Point"}
}