{
  "type": "Feature",
  "properties": {
    "addr:full":"2017 NE 172nd Ave Vancouver WA 98684",
    "addr:housenumber":"2017",
    "addr:postcode":"98684",
    "addr:street":"Ne 172Nd Ave",
    "iso:country":"US",
    "sg:address":"2017 NE 172nd Ave",
    "sg:city":"Vancouver",
    "sg:classifiers":[
        {
            "category":"Education",
            "subcategory":"School",
            "type":"Public Place"
        }
    ],
    "sg:phone":"+1 360 604 6500",
    "sg:postcode":"98684",
    "sg:province":"WA",
    "sg:website":"www.egreen.wednet.edu",
    "wof:name":"Schools Public",
    "wof:placetype":"venue"
},
  "geometry": {"coordinates":[-122.495486,45.637665],"type":"Point"}
}