{
  "type": "Feature",
  "properties": {
    "addr:full":"9832 NE 30th St Bellevue WA 98004",
    "addr:housenumber":"9832",
    "addr:postcode":"98004",
    "addr:street":"Ne 30Th St",
    "iso:country":"US",
    "sg:address":"9832 NE 30th St",
    "sg:city":"Bellevue",
    "sg:classifiers":[
        {
            "category":"Personal",
            "type":"Services"
        }
    ],
    "sg:phone":"+1 425 453 9847",
    "sg:postcode":"98004",
    "sg:province":"WA",
    "sg:tags":[
        "butlers'",
        "maids'"
    ],
    "wof:name":"Judith L Green",
    "wof:placetype":"venue"
},
  "geometry": {"coordinates":[-122.20883499999999,47.637443],"type":"Point"}
}