{
  "type": "Feature",
  "properties": {
    "addr:full":"1416 E Main Ave Puyallup WA 98372",
    "addr:housenumber":"1416",
    "addr:postcode":"98372",
    "addr:street":"E Main Ave",
    "iso:country":"US",
    "sg:address":"1416 E Main Ave",
    "sg:city":"Puyallup",
    "sg:classifiers":[
        {
            "category":"Sports & Exercise",
            "subcategory":"Gym",
            "type":"Entertainment"
        }
    ],
    "sg:phone":"+1 253 446 0166",
    "sg:postcode":"98372",
    "sg:province":"WA",
    "sg:tags":[
        "club",
        "health",
        "studio",
        "gymnasium"
    ],
    "wof:name":"Curves For Women",
    "wof:placetype":"venue"
},
  "geometry": {"coordinates":[-122.27384000000001,47.191912],"type":"Point"}
}