{
  "type": "Feature",
  "properties": {
    "addr:full":"3719 168th St NE Arlington WA 98223",
    "addr:housenumber":"3719",
    "addr:postcode":"98223",
    "addr:street":"168Th St Ne",
    "iso:country":"US",
    "sg:address":"3719 168th St NE",
    "sg:city":"Arlington",
    "sg:classifiers":[
        {
            "category":"Banks & Credit Unions",
            "subcategory":"Investment Brokerage",
            "type":"Services"
        }
    ],
    "sg:phone":"+1 360 653 8807",
    "sg:postcode":"98223",
    "sg:province":"WA",
    "sg:tags":[
        "security"
    ],
    "wof:name":"Edward Jones Co",
    "wof:placetype":"venue"
},
  "geometry": {"coordinates":[-122.17961099999999,48.148622],"type":"Point"}
}