{
  "type": "Feature",
  "properties": {
    "addr:full":"1201 S Miller St Wenatchee WA 98801",
    "addr:housenumber":"1201",
    "addr:postcode":"98801",
    "addr:street":"S Miller St",
    "iso:country":"US",
    "sg:address":"1201 S Miller St",
    "sg:city":"Wenatchee",
    "sg:classifiers":[
        {
            "category":"Organizations",
            "subcategory":"Non-profit Organization",
            "type":"Services"
        }
    ],
    "sg:phone":"+1 509 665 6254",
    "sg:postcode":"98801",
    "sg:province":"WA",
    "wof:name":"Mobile Meals",
    "wof:placetype":"venue"
},
  "geometry": {"coordinates":[-120.324544,47.406364],"type":"Point"}
}