{
  "type": "Feature",
  "properties": {
    "addr:full":"12666 Des Moines Memorial Dr Seattle WA 98168",
    "addr:housenumber":"12666",
    "addr:postcode":"98168",
    "addr:street":"Des Moines Memorial Dr",
    "iso:country":"US",
    "sg:address":"12666 Des Moines Memorial Dr",
    "sg:city":"Seattle",
    "sg:classifiers":[
        {
            "category":"Coffee & Tea",
            "type":"Food & Drink"
        },
        {
            "category":"Restaurant",
            "type":"Food & Drink"
        }
    ],
    "sg:phone":"+1 206 242 2152",
    "sg:postcode":"98168",
    "sg:province":"WA",
    "sg:tags":[
        "shop",
        "espresso"
    ],
    "wof:name":"Sisters Expresso Inc",
    "wof:placetype":"venue"
},
  "geometry": {"coordinates":[-122.311009,47.489635],"type":"Point"}
}