{
  "type": "Feature",
  "properties": {
    "addr:full":"828 Gilmore Way NE Bainbridge Island WA 98110",
    "addr:housenumber":"828",
    "addr:postcode":"98110",
    "addr:street":"Gilmore Way Ne",
    "iso:country":"US",
    "sg:address":"828 Gilmore Way NE",
    "sg:city":"Bainbridge Island",
    "sg:classifiers":[
        {
            "category":"Real Estate",
            "subcategory":"Real Estate Operator",
            "type":"Services"
        }
    ],
    "sg:phone":"+1 206 842 7273",
    "sg:postcode":"98110",
    "sg:province":"WA",
    "sg:tags":[
        "building",
        "nonresidential"
    ],
    "wof:name":"J&M Island Properties LLC",
    "wof:placetype":"venue"
},
  "geometry": {"coordinates":[-122.510651,47.626606],"type":"Point"}
}