{
  "type": "Feature",
  "properties": {
    "addr:full":"225 108th Ave Civica Office Commons Lobby Bellevue WA 98004",
    "addr:housenumber":"225",
    "addr:postcode":"98004",
    "addr:street":"108Th Ave",
    "iso:country":"US",
    "sg:address":"225 108th Ave Civica Office Commons Lobby",
    "sg:city":"Bellevue",
    "sg:classifiers":[
        {
            "category":"Food & Beverages",
            "subcategory":"Groceries & Convenience Stores",
            "type":"Retail Goods"
        }
    ],
    "sg:postcode":"98004",
    "sg:province":"WA",
    "wof:name":"Sam's at Civica",
    "wof:placetype":"venue"
},
  "geometry": {"coordinates":[-122.195999,47.612598],"type":"Point"}
}