{
  "type": "Feature",
  "properties": {
    "iso:country":"US",
    "sg:address":"4344 Memory Ln W",
    "sg:city":"Tacoma",
    "sg:classifiers":[
        {
            "category":"Professional",
            "subcategory":"Secretarial Services",
            "type":"Services"
        }
    ],
    "sg:phone":"+1 253 564 8494",
    "sg:postcode":"98466",
    "sg:province":"WA",
    "sg:tags":[
        "reporting"
    ],
    "wof:name":"Sandra Baker & Associates",
    "wof:placetype":"venue"
},
  "geometry": {"coordinates":[-122.56903,47.219114],"type":"Point"}
}