{
  "type": "Feature",
  "properties": {
    "addr:full":"1912 C St Vancouver WA 98663",
    "addr:housenumber":"1912",
    "addr:postcode":"98663",
    "addr:street":"C St",
    "iso:country":"US",
    "sg:address":"1912 C St",
    "sg:city":"Vancouver",
    "sg:classifiers":[
        {
            "category":"Professional",
            "subcategory":"Art Services",
            "type":"Services"
        }
    ],
    "sg:phone":"+1 360 693 2391",
    "sg:postcode":"98663",
    "sg:province":"WA",
    "sg:tags":[
        "photo",
        "photography",
        "commercial",
        "studio",
        "portrait"
    ],
    "sg:website":"www.barboursphotography.com",
    "wof:name":"Barbours Photography",
    "wof:placetype":"venue"
},
  "geometry": {"coordinates":[-122.66934999999999,45.636628],"type":"Point"}
}