{
  "type": "Feature",
  "properties": {
    "addr:full":"1908 W Francis Ave Spokane WA 99205",
    "addr:housenumber":"1908",
    "addr:postcode":"99205",
    "addr:street":"W Francis Ave",
    "iso:country":"US",
    "sg:address":"1908 W Francis Ave",
    "sg:city":"Spokane",
    "sg:classifiers":[
        {
            "category":"Restaurant",
            "type":"Food & Drink"
        }
    ],
    "sg:menulink":"http://www.allmenus.com/wa/spokane/75677-round-table-pizza/menu/",
    "sg:phone":"+1 509 324 2414",
    "sg:postcode":"99205",
    "sg:province":"WA",
    "sg:tags":[
        "american",
        "pizza"
    ],
    "wof:name":"Round Table Pizza",
    "wof:placetype":"venue"
},
  "geometry": {"coordinates":[-117.44001299999999,47.716277],"type":"Point"}
}