{
  "type": "Feature",
  "properties": {
    "addr:full":"10058 13th Ave NW Seattle WA 98177",
    "addr:housenumber":"10058",
    "addr:postcode":"98177",
    "addr:street":"13Th Ave Nw",
    "iso:country":"US",
    "sg:address":"10058 13th Ave NW",
    "sg:city":"Seattle",
    "sg:classifiers":[
        {
            "category":"Retail",
            "subcategory":"Repair Shop",
            "type":"Services"
        }
    ],
    "sg:phone":"+1 206 782 9545",
    "sg:postcode":"98177",
    "sg:province":"WA",
    "sg:tags":[
        "spa",
        "hot",
        "tub"
    ],
    "wof:name":"Bill's Spa & Pellet Stoves Svc",
    "wof:placetype":"venue"
},
  "geometry": {"coordinates":[-122.372676,47.702999],"type":"Point"}
}