{
  "type": "Feature",
  "properties": {
    "iso:country":"US",
    "sg:address":"1021 S 40th Ave",
    "sg:city":"Yakima",
    "sg:classifiers":[
        {
            "category":"Shopping",
            "subcategory":"Pharmacy",
            "type":"Retail Goods"
        }
    ],
    "sg:phone":"+1 509 965 2497",
    "sg:postcode":"98908",
    "sg:province":"WA",
    "sg:tags":[
        "drug",
        "store"
    ],
    "wof:name":"Fortieth Avenue Pharmacy",
    "wof:placetype":"venue"
},
  "geometry": {"coordinates":[-120.561818,46.587622],"type":"Point"}
}