{
  "type": "Feature",
  "properties": {
    "addr:full":"3526 278th Pl NE Redmond WA 98053",
    "addr:housenumber":"3526",
    "addr:postcode":"98053",
    "addr:street":"278Th Pl Ne",
    "iso:country":"US",
    "sg:address":"3526 278th Pl NE",
    "sg:city":"Redmond",
    "sg:classifiers":[
        {
            "category":"Building & Trades",
            "subcategory":"Construction",
            "type":"Services"
        }
    ],
    "sg:phone":"+1 425 880 4672",
    "sg:postcode":"98053",
    "sg:province":"WA",
    "sg:tags":[
        "mason",
        "masonry",
        "industrial",
        "contractors-commercial",
        "contractor"
    ],
    "wof:name":"Milestone Masonry",
    "wof:placetype":"venue"
},
  "geometry": {"coordinates":[-121.96704200000001,47.639797],"type":"Point"}
}