{
  "type": "Feature",
  "properties": {
    "addr:full":"2043 Bridgeman Rd Sunnyside WA 98944",
    "addr:housenumber":"2043",
    "addr:postcode":"98944",
    "addr:street":"Bridgeman Rd",
    "iso:country":"US",
    "sg:address":"2043 Bridgeman Rd",
    "sg:city":"Sunnyside",
    "sg:classifiers":[
        {
            "category":"Building & Trades",
            "subcategory":"Construction",
            "type":"Services"
        }
    ],
    "sg:phone":"+1 509 837 6523",
    "sg:postcode":"98944",
    "sg:province":"WA",
    "sg:tags":[
        "heavy"
    ],
    "wof:name":"P D S Construction",
    "wof:placetype":"venue"
},
  "geometry": {"coordinates":[-119.93701299999999,46.352791],"type":"Point"}
}