{
  "type": "Feature",
  "properties": {
    "addr:full":"618 W 1st St Wapato WA 98951",
    "addr:housenumber":"618",
    "addr:postcode":"98951",
    "addr:street":"W 1St St",
    "iso:country":"US",
    "sg:address":"618 W 1st St",
    "sg:city":"Wapato",
    "sg:classifiers":[
        {
            "category":"Insurance",
            "subcategory":"Insurance Agent",
            "type":"Services"
        }
    ],
    "sg:phone":"+1 509 877 3601",
    "sg:postcode":"98951",
    "sg:province":"WA",
    "wof:name":"Farmers Insurance",
    "wof:placetype":"venue"
},
  "geometry": {"coordinates":[-120.42863699999999,46.44794],"type":"Point"}
}