{
  "type": "Feature",
  "properties": {
    "addr:full":"210 Polk St Port Townsend WA 98368",
    "addr:housenumber":"210",
    "addr:postcode":"98368",
    "addr:street":"Polk St",
    "iso:country":"US",
    "sg:address":"210 Polk St",
    "sg:city":"Port Townsend",
    "sg:classifiers":[
        {
            "category":"Organizations",
            "subcategory":"Political Organization",
            "type":"Services"
        }
    ],
    "sg:phone":"+1 360 379 5655",
    "sg:postcode":"98368",
    "sg:province":"WA",
    "wof:name":"Democratic Party Of Jefferson",
    "wof:placetype":"venue"
},
  "geometry": {"coordinates":[-122.758978,48.114011],"type":"Point"}
}