{
  "type": "Feature",
  "properties": {
    "addr:full":"3501 Pacific Ave SE Olympia WA 98501",
    "addr:housenumber":"3501",
    "addr:postcode":"98501",
    "addr:street":"Pacific Ave Se",
    "iso:country":"US",
    "sg:address":"3501 Pacific Ave SE",
    "sg:city":"Olympia",
    "sg:classifiers":[
        {
            "category":"Restaurant",
            "type":"Food & Drink"
        }
    ],
    "sg:menulink":"http://www.allmenus.com/wa/olympia/235514-taco-time/menu/",
    "sg:phone":"+1 360 438 9511",
    "sg:postcode":"98501",
    "sg:province":"WA",
    "sg:tags":[
        "american",
        "mexican",
        "tex-mex"
    ],
    "wof:name":"Taco Time",
    "wof:placetype":"venue"
},
  "geometry": {"coordinates":[-122.846568,47.04151],"type":"Point"}
}