{
  "type": "Feature",
  "properties": {
    "addr:full":"2003 Todd Rd Apt D49 Vancouver WA 98661",
    "addr:housenumber":"2003",
    "addr:postcode":"98661",
    "addr:street":"Todd Rd Apt D49",
    "iso:country":"US",
    "sg:address":"2003 Todd Rd Apt D49",
    "sg:city":"Vancouver",
    "sg:classifiers":[
        {
            "category":"Real Estate",
            "subcategory":"Real Estate Operator",
            "type":"Services"
        }
    ],
    "sg:phone":"+1 360 694 1024",
    "sg:postcode":"98661",
    "sg:province":"WA",
    "sg:tags":[
        "apartment"
    ],
    "wof:name":"Senior Estates II Apartments",
    "wof:placetype":"venue"
},
  "geometry": {"coordinates":[-122.63153,45.636488],"type":"Point"}
}