{
  "type": "Feature",
  "properties": {
    "addr:full":"1215 NW Haven Cir Pullman WA 99163",
    "addr:housenumber":"1215",
    "addr:postcode":"99163",
    "addr:street":"Nw Haven Cir",
    "iso:country":"US",
    "sg:address":"1215 NW Haven Cir",
    "sg:city":"Pullman",
    "sg:classifiers":[
        {
            "category":"Personal",
            "subcategory":"Beauty Salon",
            "type":"Services"
        }
    ],
    "sg:phone":"+1 509 332 1062",
    "sg:postcode":"99163",
    "sg:province":"WA",
    "wof:name":"Color By Nancy",
    "wof:placetype":"venue"
},
  "geometry": {"coordinates":[-117.184382,46.739904],"type":"Point"}
}