{
  "type": "Feature",
  "properties": {
    "addr:full":"14929 SE Allen Rd Bellevue WA 98006",
    "addr:postcode":"14929;98006",
    "addr:street":"Se Allen Rd",
    "iso:country":"US",
    "sg:address":"14929 SE Allen Rd",
    "sg:city":"Bellevue",
    "sg:classifiers":[
        {
            "category":"Health Services",
            "subcategory":"Doctor",
            "type":"Services"
        }
    ],
    "sg:phone":"+1 425 746 2124",
    "sg:postcode":"98006",
    "sg:province":"WA",
    "wof:name":"Ballard Clark MD",
    "wof:placetype":"venue"
},
  "geometry": {"coordinates":[-122.14148900000001,47.575148],"type":"Point"}
}