{
  "type": "Feature",
  "properties": {
    "addr:full":"3011 S Huson St Suite A Tacoma WA 98409",
    "addr:housenumber":"3011",
    "addr:postcode":"98409",
    "addr:street":"S Huson St Suite A",
    "iso:country":"US",
    "sg:address":"3011 S Huson St Suite A",
    "sg:city":"Tacoma",
    "sg:classifiers":[
        {
            "category":"Professional",
            "subcategory":"Engineering",
            "type":"Services"
        }
    ],
    "sg:phone":"+1 877 432 0709",
    "sg:postcode":"98409",
    "sg:province":"WA",
    "sg:tags":[
        "environmental",
        "engineer"
    ],
    "sg:website":"http://www.robinson-noble.com",
    "wof:name":"Robinson Noble, Inc.",
    "wof:placetype":"venue"
},
  "geometry": {"coordinates":[-122.503867,47.233214],"type":"Point"}
}