{
  "type": "Feature",
  "properties": {
    "addr:full":"4011 238th St NE Arlington WA 98223",
    "addr:housenumber":"4011",
    "addr:postcode":"98223",
    "addr:street":"238Th St Ne",
    "iso:country":"US",
    "sg:address":"4011 238th St NE",
    "sg:city":"Arlington",
    "sg:classifiers":[
        {
            "category":"Building & Trades",
            "subcategory":"Construction",
            "type":"Services"
        }
    ],
    "sg:phone":"+1 360 435 4562",
    "sg:postcode":"98223",
    "sg:province":"WA",
    "sg:tags":[
        "house"
    ],
    "wof:name":"Mark Webb Construction",
    "wof:placetype":"venue"
},
  "geometry": {"coordinates":[-122.175377,48.211896],"type":"Point"}
}