{
  "type": "Feature",
  "properties": {
    "addr:full":"3524 SW 325th St Federal Way WA 98023",
    "addr:housenumber":"3524",
    "addr:postcode":"98023",
    "addr:street":"Sw 325Th St",
    "iso:country":"US",
    "sg:address":"3524 SW 325th St",
    "sg:city":"Federal Way",
    "sg:classifiers":[
        {
            "category":"Professional",
            "subcategory":"Engineering",
            "type":"Services"
        }
    ],
    "sg:phone":"+1 253 838 0660",
    "sg:postcode":"98023",
    "sg:province":"WA",
    "wof:name":"Jack Lyon Professional Engr",
    "wof:placetype":"venue"
},
  "geometry": {"coordinates":[-122.37778400000001,47.312029],"type":"Point"}
}