{
  "type": "Feature",
  "properties": {
    "addr:full":"2828 13th Ave W Seattle WA 98119",
    "addr:housenumber":"2828",
    "addr:postcode":"98119",
    "addr:street":"13Th Ave W",
    "iso:country":"US",
    "sg:address":"2828 13th Ave W",
    "sg:city":"Seattle",
    "sg:classifiers":[
        {
            "category":"Real Estate",
            "subcategory":"Real Estate Operator",
            "type":"Services"
        }
    ],
    "sg:phone":"+1 206 283 4839",
    "sg:postcode":"98119",
    "sg:province":"WA",
    "sg:tags":[
        "property",
        "management",
        "investment"
    ],
    "wof:name":"Ascolier APT",
    "wof:placetype":"venue"
},
  "geometry": {"coordinates":[-122.373487,47.646333],"type":"Point"}
}