{
  "type": "Feature",
  "properties": {
    "addr:full":"118 Lake St S Kirkland WA 98033",
    "addr:housenumber":"118",
    "addr:postcode":"98033",
    "addr:street":"Lake St S",
    "iso:country":"US",
    "sg:address":"118 Lake St S",
    "sg:city":"Kirkland",
    "sg:classifiers":[
        {
            "category":"Building & Trades",
            "subcategory":"Construction",
            "type":"Services"
        }
    ],
    "sg:phone":"+1 425 803 6959",
    "sg:postcode":"98033",
    "sg:province":"WA",
    "sg:tags":[
        "installation"
    ],
    "wof:name":"Interior Services Inc",
    "wof:placetype":"venue"
},
  "geometry": {"coordinates":[-122.206773,47.675958],"type":"Point"}
}