{
  "type": "Feature",
  "properties": {
    "addr:full":"26310 Ridge Ave Ocean Park WA 98640",
    "addr:housenumber":"26310",
    "addr:postcode":"98640",
    "addr:street":"Ridge Ave",
    "iso:country":"US",
    "sg:address":"26310 Ridge Ave",
    "sg:city":"Ocean Park",
    "sg:classifiers":[
        {
            "category":"Organizations",
            "subcategory":"Religious Organization",
            "type":"Services"
        }
    ],
    "sg:phone":"+1 360 665 6340",
    "sg:postcode":"98640",
    "sg:province":"WA",
    "sg:tags":[
        "church"
    ],
    "sg:website":"www.peninsulaag.com",
    "wof:name":"Peninsula Assembly Of God",
    "wof:placetype":"venue"
},
  "geometry": {"coordinates":[-124.048851,46.493027],"type":"Point"}
}