{
  "type": "Feature",
  "properties": {
    "addr:full":"10821 47th Ave W Mukilteo WA 98275",
    "addr:housenumber":"10821",
    "addr:postcode":"98275",
    "addr:street":"47Th Ave W",
    "iso:country":"US",
    "sg:address":"10821 47th Ave W",
    "sg:city":"Mukilteo",
    "sg:classifiers":[
        {
            "category":"Manufacturing",
            "subcategory":"Metals",
            "type":"Manufacturing & Wholesale Goods"
        }
    ],
    "sg:phone":"+1 425 745 5110",
    "sg:postcode":"98275",
    "sg:province":"WA",
    "sg:tags":[
        "sheet",
        "fabrication"
    ],
    "wof:name":"Western Fabricators Inc",
    "wof:placetype":"venue"
},
  "geometry": {"coordinates":[-122.29475600000001,47.8998],"type":"Point"}
}