{
  "type": "Feature",
  "properties": {
    "iso:country":"US",
    "sg:address":"10526 N Park Ave N",
    "sg:city":"Seattle",
    "sg:classifiers":[
        {
            "category":"Professional",
            "subcategory":"Management & Consulting",
            "type":"Services"
        }
    ],
    "sg:phone":"+1 206 362 1587",
    "sg:postcode":"98133",
    "sg:province":"WA",
    "sg:tags":[
        "consultant",
        "business"
    ],
    "wof:name":"Valerie Noack",
    "wof:placetype":"venue"
},
  "geometry": {"coordinates":[-122.348664,47.706324],"type":"Point"}
}