{
  "type": "Feature",
  "properties": {
    "addr:full":"8412 W Gage Blvd Kennewick WA 99336",
    "addr:housenumber":"8412",
    "addr:postcode":"99336",
    "addr:street":"W Gage Blvd",
    "iso:country":"US",
    "sg:address":"8412 W Gage Blvd",
    "sg:city":"Kennewick",
    "sg:classifiers":[
        {
            "category":"Professional",
            "subcategory":"Management & Consulting",
            "type":"Services"
        }
    ],
    "sg:phone":"+1 509 735 0364",
    "sg:postcode":"99336",
    "sg:province":"WA",
    "sg:tags":[
        "business"
    ],
    "wof:name":"Columbia Basin Tech",
    "wof:placetype":"venue"
},
  "geometry": {"coordinates":[-119.23767100000001,46.227229],"type":"Point"}
}