{
  "type": "Feature",
  "properties": {
    "addr:full":"1961 Conifer Dr Ferndale WA 98248",
    "addr:housenumber":"1961",
    "addr:postcode":"98248",
    "addr:street":"Conifer Dr",
    "iso:country":"US",
    "sg:address":"1961 Conifer Dr",
    "sg:city":"Ferndale",
    "sg:classifiers":[
        {
            "category":"Professional",
            "type":"Services"
        }
    ],
    "sg:phone":"+1 360 380 0508",
    "sg:postcode":"98248",
    "sg:province":"WA",
    "wof:name":"Bobs Tractor Service",
    "wof:placetype":"venue"
},
  "geometry": {"coordinates":[-122.586,48.900309],"type":"Point"}
}