{
  "type": "Feature",
  "properties": {
    "addr:full":"3205 B West Lynn St Seattle WA 98199",
    "addr:housenumber":"3205 b",
    "addr:postcode":"98199",
    "addr:street":"West Lynn St",
    "iso:country":"US",
    "sg:address":"3205 B West Lynn St",
    "sg:city":"Seattle",
    "sg:classifiers":[
        {
            "category":"Personal",
            "subcategory":"Hair Removal",
            "type":"Services"
        }
    ],
    "sg:phone":"+1 206 335 7411",
    "sg:postcode":"98199",
    "sg:province":"WA",
    "sg:website":"sugarmemagnolia.com",
    "wof:name":"Sugar Me",
    "wof:placetype":"venue"
},
  "geometry": {"coordinates":[-122.398403,47.63912],"type":"Point"}
}