{
  "type": "Feature",
  "properties": {
    "addr:full":"2600 2nd Ave N Seattle WA 98109",
    "addr:housenumber":"2600",
    "addr:postcode":"98109",
    "addr:street":"2Nd Ave N",
    "iso:country":"US",
    "sg:address":"2600 2nd Ave N",
    "sg:city":"Seattle",
    "sg:classifiers":[
        {
            "category":"Park",
            "type":"Public Place"
        }
    ],
    "sg:postcode":"98109",
    "sg:province":"WA",
    "wof:name":"Mayfair Park",
    "wof:placetype":"venue"
},
  "geometry": {"coordinates":[-122.353882,47.643247],"type":"Point"}
}