{
  "type": "Feature",
  "properties": {
    "addr:full":"1035 Lakeview Dr Kettle Falls WA 99141",
    "addr:housenumber":"1035",
    "addr:postcode":"99141",
    "addr:street":"Lakeview Dr",
    "iso:country":"US",
    "sg:address":"1035 Lakeview Dr",
    "sg:city":"Kettle Falls",
    "sg:classifiers":[
        {
            "category":"Manufacturing",
            "subcategory":"Motor Vehicles & Parts",
            "type":"Manufacturing & Wholesale Goods"
        }
    ],
    "sg:phone":"+1 509 738 6815",
    "sg:postcode":"99141",
    "sg:province":"WA",
    "sg:tags":[
        "mfg"
    ],
    "wof:name":"Lakeview Products",
    "wof:placetype":"venue"
},
  "geometry": {"coordinates":[-118.073149,48.615228],"type":"Point"}
}