{
  "type": "Feature",
  "properties": {
    "addr:full":"1915 California St Everett WA 98201",
    "addr:housenumber":"1915",
    "addr:postcode":"98201",
    "addr:street":"California St",
    "iso:country":"US",
    "sg:address":"1915 California St",
    "sg:city":"Everett",
    "sg:classifiers":[
        {
            "category":"Restaurant",
            "type":"Food & Drink"
        }
    ],
    "sg:phone":"+1 425 257 0457",
    "sg:postcode":"98201",
    "sg:province":"WA",
    "sg:tags":[
        "eating"
    ],
    "wof:name":"Lemay's Early Bird Cafe",
    "wof:placetype":"venue"
},
  "geometry": {"coordinates":[-122.203102,47.980638],"type":"Point"}
}