{
  "type": "Feature",
  "properties": {
    "addr:full":"10020 Main St Ste A PMB 113 Bellevue WA 98004",
    "addr:housenumber":"10020;113",
    "addr:postcode":"98004",
    "addr:street":"Main St Ste A Pmb",
    "iso:country":"US",
    "sg:address":"10020 Main St Ste A PMB 113",
    "sg:city":"Bellevue",
    "sg:classifiers":[
        {
            "category":"Marine",
            "type":"Transportation"
        }
    ],
    "sg:phone":"+1 425 641 7771",
    "sg:postcode":"98004",
    "sg:province":"WA",
    "sg:tags":[
        "cruise"
    ],
    "wof:name":"Cruisemax Cruises Inc",
    "wof:placetype":"venue"
},
  "geometry": {"coordinates":[-122.206444,47.61021],"type":"Point"}
}