{
  "type": "Feature",
  "properties": {
    "iso:country":"US",
    "sg:address":"10208 N Division St",
    "sg:city":"Spokane",
    "sg:classifiers":[
        {
            "category":"Banks & Credit Unions",
            "subcategory":"Investment Brokerage",
            "type":"Services"
        }
    ],
    "sg:phone":"+1 509 467 0682",
    "sg:postcode":"99218",
    "sg:province":"WA",
    "wof:name":"Lakeshore Investment Corp",
    "wof:placetype":"venue"
},
  "geometry": {"coordinates":[-117.411287,47.747656],"type":"Point"}
}