{
  "type": "Feature",
  "properties": {
    "addr:full":"895 Monroe Landing Rd Oak Harbor WA 98277",
    "addr:housenumber":"895",
    "addr:postcode":"98277",
    "addr:street":"Monroe Landing Rd",
    "iso:country":"US",
    "sg:address":"895 Monroe Landing Rd",
    "sg:city":"Oak Harbor",
    "sg:classifiers":[
        {
            "category":"Professional",
            "subcategory":"Business Services",
            "type":"Services"
        }
    ],
    "sg:phone":"+1 360 675 7450",
    "sg:postcode":"98277",
    "sg:province":"WA",
    "sg:tags":[
        "fencing"
    ],
    "wof:name":"Whidbey Fencing",
    "wof:placetype":"venue"
},
  "geometry": {"coordinates":[-122.68072600000001,48.242644],"type":"Point"}
}