{
  "type": "Feature",
  "properties": {
    "addr:full":"1419 E 55th St Tacoma WA 98404",
    "addr:housenumber":"1419",
    "addr:postcode":"98404",
    "addr:street":"E 55Th St",
    "iso:country":"US",
    "sg:address":"1419 E 55th St",
    "sg:city":"Tacoma",
    "sg:classifiers":[
        {
            "category":"Recreation",
            "type":"Entertainment"
        }
    ],
    "sg:phone":"+1 253 284 9284",
    "sg:postcode":"98404",
    "sg:province":"WA",
    "sg:tags":[
        "sporting"
    ],
    "wof:name":"A Action Rentals",
    "wof:placetype":"venue"
},
  "geometry": {"coordinates":[-122.408171,47.207229],"type":"Point"}
}