{
  "type": "Feature",
  "properties": {
    "addr:full":"509 N West Ave Arlington WA 98223",
    "addr:housenumber":"509",
    "addr:postcode":"98223",
    "addr:street":"N West Ave",
    "iso:country":"US",
    "sg:address":"509 N West Ave",
    "sg:city":"Arlington",
    "sg:classifiers":[
        {
            "category":"Shopping",
            "type":"Retail Goods"
        }
    ],
    "sg:phone":"+1 360 403 8485",
    "sg:postcode":"98223",
    "sg:province":"WA",
    "sg:tags":[
        "merchandise"
    ],
    "wof:name":"Pet Country",
    "wof:placetype":"venue"
},
  "geometry": {"coordinates":[-122.128063,48.198654],"type":"Point"}
}