{
  "type": "Feature",
  "properties": {
    "addr:full":"5031 University Way Northeast Seattle WA 98105",
    "addr:housenumber":"5031",
    "addr:postcode":"98105",
    "addr:street":"University Way Northeast",
    "iso:country":"US",
    "sg:address":"5031 University Way Northeast",
    "sg:city":"Seattle",
    "sg:classifiers":[
        {
            "category":"Professional",
            "subcategory":"Management & Consulting",
            "type":"Services"
        },
        {
            "category":"Education",
            "subcategory":"Special Training",
            "type":"Public Place"
        }
    ],
    "sg:phone":"+1 480 440 2401",
    "sg:postcode":"98105",
    "sg:province":"WA",
    "sg:tags":[
        "school",
        "coach",
        "life",
        "specialty"
    ],
    "sg:website":"www.seattlelifecoachtraining.com",
    "wof:name":"Seattle Life Coach Training",
    "wof:placetype":"venue"
},
  "geometry": {"coordinates":[-122.312894,47.665705],"type":"Point"}
}