{
  "type": "Feature",
  "properties": {
    "addr:full":"3405 172nd St NE Ste 4 Arlington WA 98223",
    "addr:housenumber":"3405",
    "addr:postcode":"98223",
    "addr:street":"172Nd St Ne Ste 4",
    "iso:country":"US",
    "sg:address":"3405 172nd St NE Ste 4",
    "sg:city":"Arlington",
    "sg:classifiers":[
        {
            "category":"Personal",
            "subcategory":"Tanning Parlor",
            "type":"Services"
        },
        {
            "category":"Personal",
            "subcategory":"Nail Salon",
            "type":"Services"
        }
    ],
    "sg:phone":"+1 360 658 1657",
    "sg:postcode":"98223",
    "sg:province":"WA",
    "wof:name":"Hi Tek Nails",
    "wof:placetype":"venue"
},
  "geometry": {"coordinates":[-122.184445,48.152418],"type":"Point"}
}