{
  "type": "Feature",
  "properties": {
    "addr:full":"19725 7th Ave NE Poulsbo WA 98370",
    "addr:housenumber":"19725",
    "addr:postcode":"98370",
    "addr:street":"7Th Ave Ne",
    "iso:country":"US",
    "sg:address":"19725 7th Ave NE",
    "sg:city":"Poulsbo",
    "sg:classifiers":[
        {
            "category":"Banks & Credit Unions",
            "subcategory":"Bank",
            "type":"Services"
        }
    ],
    "sg:phone":"+1 360 779 7799",
    "sg:postcode":"98370",
    "sg:province":"WA",
    "sg:website":"www.kitsapbank.com",
    "wof:name":"Kitsap Bank",
    "wof:placetype":"venue"
},
  "geometry": {"coordinates":[-122.640108,47.744252],"type":"Point"}
}