{
  "type": "Feature",
  "properties": {
    "addr:full":"1901 Park Ave Raymond WA 98577",
    "addr:housenumber":"1901",
    "addr:postcode":"98577",
    "addr:street":"Park Ave Raymond",
    "iso:country":"US",
    "sg:address":"1901 Park Ave",
    "sg:city":"Raymond",
    "sg:classifiers":[
        {
            "category":"Food & Beverages",
            "subcategory":"Groceries & Convenience Stores",
            "type":"Retail Goods"
        }
    ],
    "sg:phone":"+1 360 942 5066",
    "sg:postcode":"98577",
    "sg:province":"WA",
    "sg:tags":[
        "independent"
    ],
    "wof:name":"Riverdale Grocery",
    "wof:placetype":"venue"
},
  "geometry": {"coordinates":[-123.738865,46.693757],"type":"Point"}
}