{
  "type": "Feature",
  "properties": {
    "addr:full":"1128 SW Spokane St Seattle WA 98134",
    "addr:housenumber":"1128",
    "addr:postcode":"98134",
    "addr:street":"Sw Spokane St",
    "iso:country":"US",
    "sg:address":"1128 SW Spokane St",
    "sg:city":"Seattle",
    "sg:classifiers":[
        {
            "category":"Personal",
            "type":"Services"
        },
        {
            "category":"Building & Trades",
            "subcategory":"Construction",
            "type":"Services"
        }
    ],
    "sg:phone":"+1 206 682 5354",
    "sg:postcode":"98134",
    "sg:province":"WA",
    "sg:tags":[
        "roofing",
        "local"
    ],
    "sg:website":"pacificsheetmetal.com",
    "wof:name":"Pacific Sheet Metal & Roofing",
    "wof:placetype":"venue"
},
  "geometry": {"coordinates":[-122.35144699999999,47.572041],"type":"Point"}
}