{
  "type": "Feature",
  "properties": {
    "addr:full":"5225 W Clearwater Ave Kennewick WA 99336",
    "addr:housenumber":"5225",
    "addr:postcode":"99336",
    "addr:street":"W Clearwater Ave",
    "iso:country":"US",
    "sg:address":"5225 W Clearwater Ave",
    "sg:city":"Kennewick",
    "sg:classifiers":[
        {
            "category":"Real Estate",
            "subcategory":"Real Estate Services",
            "type":"Services"
        },
        {
            "category":"Real Estate",
            "subcategory":"Real Estate Operator",
            "type":"Services"
        }
    ],
    "sg:phone":"+1 509 783 4293",
    "sg:postcode":"99336",
    "sg:province":"WA",
    "sg:tags":[
        "vacancy",
        "apartment",
        "rental",
        "finder",
        "listing"
    ],
    "wof:name":"Clearwater Bay Apt",
    "wof:placetype":"venue"
},
  "geometry": {"coordinates":[-119.195001,46.21244],"type":"Point"}
}