{
  "type": "Feature",
  "properties": {
    "addr:full":"11201 SE 8th St Bellevue WA 98004",
    "addr:postcode":"11201;98004",
    "addr:street":"Se 8Th St",
    "iso:country":"US",
    "sg:address":"11201 SE 8th St",
    "sg:city":"Bellevue",
    "sg:classifiers":[
        {
            "category":"Insurance",
            "subcategory":"Insurance Agent",
            "type":"Services"
        }
    ],
    "sg:phone":"+1 425 462 7443",
    "sg:postcode":"98004",
    "sg:province":"WA",
    "sg:website":"www.bell-anderson.com",
    "wof:name":"Bell Anderson Insurance",
    "wof:placetype":"venue"
},
  "geometry": {"coordinates":[-122.187794,47.601568],"type":"Point"}
}