{
  "type": "Feature",
  "properties": {
    "addr:full":"411 Stewart St Seattle WA 98101",
    "addr:housenumber":"411",
    "addr:postcode":"98101",
    "addr:street":"Stewart St",
    "iso:country":"US",
    "sg:address":"411 Stewart St",
    "sg:city":"Seattle",
    "sg:classifiers":[
        {
            "category":"Real Estate",
            "subcategory":"Developer",
            "type":"Services"
        }
    ],
    "sg:phone":"+1 206 499 7169",
    "sg:postcode":"98101",
    "sg:province":"WA",
    "wof:name":"Watkins & Choi Holdings Inc",
    "wof:placetype":"venue"
},
  "geometry": {"coordinates":[-122.337851,47.612861],"type":"Point"}
}