{
  "type": "Feature",
  "properties": {
    "addr:full":"20219 87th Ave S Kent WA 98031",
    "addr:housenumber":"20219",
    "addr:postcode":"98031",
    "addr:street":"87Th Ave S",
    "iso:country":"US",
    "sg:address":"20219 87th Ave S",
    "sg:city":"Kent",
    "sg:classifiers":[
        {
            "category":"Food & Beverages",
            "subcategory":"Liquor & Beverages",
            "type":"Retail Goods"
        }
    ],
    "sg:phone":"+1 253 395 5233",
    "sg:postcode":"98031",
    "sg:province":"WA",
    "sg:tags":[
        "alcoholic"
    ],
    "wof:name":"Bottles Of Grapes Inc",
    "wof:placetype":"venue"
},
  "geometry": {"coordinates":[-122.224068,47.415729],"type":"Point"}
}