{
  "type": "Feature",
  "properties": {
    "addr:full":"615 174th Pl NE Bellevue WA 98008",
    "addr:housenumber":"615",
    "addr:postcode":"98008",
    "addr:street":"174Th Pl Ne",
    "iso:country":"US",
    "sg:address":"615 174th Pl NE",
    "sg:city":"Bellevue",
    "sg:classifiers":[
        {
            "category":"Retail",
            "subcategory":"Auto Repair",
            "type":"Services"
        }
    ],
    "sg:phone":"+1 425 644 7484",
    "sg:postcode":"98008",
    "sg:province":"WA",
    "sg:tags":[
        "automotive"
    ],
    "wof:name":"Comp U Tune",
    "wof:placetype":"venue"
},
  "geometry": {"coordinates":[-122.108063,47.616055],"type":"Point"}
}