{
  "type": "Feature",
  "properties": {
    "addr:full":"10007 Main St Bothell WA 98011",
    "addr:housenumber":"10007",
    "addr:postcode":"98011",
    "addr:street":"Main St",
    "iso:country":"US",
    "sg:address":"10007 Main St",
    "sg:city":"Bothell",
    "sg:classifiers":[
        {
            "category":"Ice Cream",
            "type":"Food & Drink"
        }
    ],
    "sg:menulink":"http://www.allmenus.com/wa/east-seattle/242826-baskin-robbins/menu/",
    "sg:phone":"+1 425 486 3131",
    "sg:postcode":"98011",
    "sg:province":"WA",
    "sg:tags":[
        "american"
    ],
    "wof:name":"Baskin-Robbins",
    "wof:placetype":"venue"
},
  "geometry": {"coordinates":[-122.207296,47.759982],"type":"Point"}
}