{
  "type": "Feature",
  "properties": {
    "addr:full":"2108 NW 98th St Seattle WA 98117",
    "addr:housenumber":"2108",
    "addr:postcode":"98117",
    "addr:street":"Nw 98Th St",
    "iso:country":"US",
    "sg:address":"2108 NW 98th St",
    "sg:city":"Seattle",
    "sg:classifiers":[
        {
            "category":"Health Services",
            "subcategory":"Nursing And Care Facility",
            "type":"Services"
        }
    ],
    "sg:phone":"+1 206 706 0755",
    "sg:postcode":"98117",
    "sg:province":"WA",
    "wof:name":"Sarausad Home Incorporated",
    "wof:placetype":"venue"
},
  "geometry": {"coordinates":[-122.385234,47.700519],"type":"Point"}
}