{
  "type": "Feature",
  "properties": {
    "addr:full":"1340 Van Wyck Rd Bellingham WA 98226",
    "addr:housenumber":"1340",
    "addr:postcode":"98226",
    "addr:street":"Van Wyck Rd",
    "iso:country":"US",
    "sg:address":"1340 Van Wyck Rd",
    "sg:city":"Bellingham",
    "sg:classifiers":[
        {
            "category":"Retail",
            "subcategory":"Repair Shop",
            "type":"Services"
        },
        {
            "category":"Utilities",
            "type":"Services"
        }
    ],
    "sg:phone":"+1 360 738 1009",
    "sg:postcode":"98226",
    "sg:province":"WA",
    "sg:tags":[
        "cover",
        "slip",
        "upholsterer"
    ],
    "sg:website":"http://www.aasestudios.com",
    "wof:name":"Aase Studios",
    "wof:placetype":"venue"
},
  "geometry": {"coordinates":[-122.418646,48.804081],"type":"Point"}
}