{
  "type": "Feature",
  "properties": {
    "addr:full":"6510 141st St SW Edmonds WA 98026",
    "addr:housenumber":"6510",
    "addr:postcode":"98026",
    "addr:street":"141St St Sw",
    "iso:country":"US",
    "sg:address":"6510 141st St SW",
    "sg:city":"Edmonds",
    "sg:classifiers":[
        {
            "category":"Professional",
            "subcategory":"Business Services",
            "type":"Services"
        }
    ],
    "sg:phone":"+1 425 745 6221",
    "sg:postcode":"98026",
    "sg:province":"WA",
    "wof:name":"Nystrom & Assoc",
    "wof:placetype":"venue"
},
  "geometry": {"coordinates":[-122.322405,47.870778],"type":"Point"}
}