{
  "type": "Feature",
  "properties": {
    "addr:full":"5233 Auto Center Way Bremerton WA 98312",
    "addr:housenumber":"5233",
    "addr:postcode":"98312",
    "addr:street":"Auto Center Way",
    "iso:country":"US",
    "sg:address":"5233 Auto Center Way",
    "sg:city":"Bremerton",
    "sg:classifiers":[
        {
            "category":"Wholesale",
            "subcategory":"Electrical",
            "type":"Manufacturing & Wholesale Goods"
        }
    ],
    "sg:phone":"+1 360 377 3877",
    "sg:postcode":"98312",
    "sg:province":"WA",
    "sg:tags":[
        "equipment",
        "electric",
        "supply"
    ],
    "sg:website":"http://www.platt.com",
    "wof:name":"Platt Electric Supply, Inc.",
    "wof:placetype":"venue"
},
  "geometry": {"coordinates":[-122.68218,47.566309],"type":"Point"}
}