{
  "type": "Feature",
  "properties": {
    "addr:full":"210 N Fairway Dr W Hoodsport WA 98548",
    "addr:housenumber":"210",
    "addr:postcode":"98548",
    "addr:street":"N Fairway Dr W Hoodsport",
    "iso:country":"US",
    "sg:address":"210 N Fairway Dr W",
    "sg:city":"Hoodsport",
    "sg:classifiers":[
        {
            "category":"Sports & Exercise",
            "subcategory":"Golf",
            "type":"Entertainment"
        }
    ],
    "sg:phone":"+1 360 877 5505",
    "sg:postcode":"98548",
    "sg:province":"WA",
    "sg:tags":[
        "course"
    ],
    "wof:name":"Lake Cushman Golf Course",
    "wof:placetype":"venue"
},
  "geometry": {"coordinates":[-123.19811199999999,47.412991],"type":"Point"}
}