{
  "type": "Feature",
  "properties": {
    "addr:full":"22037 129th Pl SE Kent WA 98031",
    "addr:housenumber":"22037",
    "addr:postcode":"98031",
    "addr:street":"129Th Pl Se",
    "iso:country":"US",
    "sg:address":"22037 129th Pl SE",
    "sg:city":"Kent",
    "sg:classifiers":[
        {
            "category":"Professional",
            "subcategory":"Research",
            "type":"Services"
        }
    ],
    "sg:phone":"+1 253 631 3843",
    "sg:postcode":"98031",
    "sg:province":"WA",
    "sg:tags":[
        "commercial",
        "physical"
    ],
    "wof:name":"Applied Evolution",
    "wof:placetype":"venue"
},
  "geometry": {"coordinates":[-122.169026,47.404281],"type":"Point"}
}