{
  "type": "Feature",
  "properties": {
    "addr:full":"123 Park Ln Kirkland WA 98033",
    "addr:housenumber":"123",
    "addr:postcode":"98033",
    "addr:street":"Park Ln",
    "iso:country":"US",
    "sg:address":"123 Park Ln",
    "sg:city":"Kirkland",
    "sg:classifiers":[
        {
            "category":"Home & Garden",
            "subcategory":"Home Furnishings",
            "type":"Retail Goods"
        }
    ],
    "sg:phone":"+1 425 822 2730",
    "sg:postcode":"98033",
    "sg:province":"WA",
    "sg:tags":[
        "decor"
    ],
    "sg:website":"www.haleyscottage.com",
    "wof:name":"Haleys Cottage",
    "wof:placetype":"venue"
},
  "geometry": {"coordinates":[-122.206138,47.676055],"type":"Point"}
}