{
  "type": "Feature",
  "properties": {
    "addr:full":"4033 Ottmar Rd NE Moses Lake WA 98837",
    "addr:postcode":"4033;98837",
    "addr:street":"Ottmar Rd Ne",
    "iso:country":"US",
    "sg:address":"4033 Ottmar Rd NE",
    "sg:city":"Moses Lake",
    "sg:classifiers":[
        {
            "category":"Manufacturing",
            "subcategory":"Printing",
            "type":"Manufacturing & Wholesale Goods"
        },
        {
            "category":"Manufacturing",
            "subcategory":"Motor Vehicles & Parts",
            "type":"Manufacturing & Wholesale Goods"
        }
    ],
    "sg:phone":"+1 509 765 3885",
    "sg:postcode":"98837",
    "sg:province":"WA",
    "sg:tags":[
        "screen",
        "custom"
    ],
    "wof:name":"Shirt Builders Inc",
    "wof:placetype":"venue"
},
  "geometry": {"coordinates":[-119.320615,47.146798],"type":"Point"}
}