{
  "type": "Feature",
  "properties": {
    "addr:full":"5813 S Tacoma Way Tacoma WA 98409",
    "addr:housenumber":"5813",
    "addr:postcode":"98409",
    "addr:street":"S Tacoma Way",
    "iso:country":"US",
    "sg:address":"5813 S Tacoma Way",
    "sg:city":"Tacoma",
    "sg:classifiers":[
        {
            "category":"Banks & Credit Unions",
            "subcategory":"Bank",
            "type":"Services"
        }
    ],
    "sg:phone":"+1 253 593 3375",
    "sg:postcode":"98409",
    "sg:province":"WA",
    "sg:tags":[
        "national"
    ],
    "sg:website":"www.bankofamerica.com",
    "wof:name":"Bank Of America",
    "wof:placetype":"venue"
},
  "geometry": {"coordinates":[-122.483609,47.20291],"type":"Point"}
}