{
  "type": "Feature",
  "properties": {
    "addr:full":"5119 47th Ave NW Gig Harbor WA 98335",
    "addr:housenumber":"5119",
    "addr:postcode":"98335",
    "addr:street":"47Th Ave Nw",
    "iso:country":"US",
    "sg:address":"5119 47th Ave NW",
    "sg:city":"Gig Harbor",
    "sg:classifiers":[
        {
            "category":"Professional",
            "subcategory":"Art Services",
            "type":"Services"
        }
    ],
    "sg:phone":"+1 253 851 7997",
    "sg:postcode":"98335",
    "sg:province":"WA",
    "sg:tags":[
        "graphic",
        "designer"
    ],
    "wof:name":"Harbor Effects",
    "wof:placetype":"venue"
},
  "geometry": {"coordinates":[-122.60196500000001,47.305066],"type":"Point"}
}