{
  "type": "Feature",
  "properties": {
    "addr:full":"3735 S Pine St Ste E Tacoma WA 98409",
    "addr:housenumber":"3735",
    "addr:postcode":"98409",
    "addr:street":"S Pine St Ste E",
    "iso:country":"US",
    "sg:address":"3735 S Pine St Ste E",
    "sg:city":"Tacoma",
    "sg:phone":"+1 253 473 5797",
    "sg:postcode":"98409",
    "sg:province":"WA",
    "sg:website":"http://www.olympicoffroad.com",
    "wof:name":"Olympic Off Road",
    "wof:placetype":"venue"
},
  "geometry": {"coordinates":[-122.473608,47.223675],"type":"Point"}
}