{
  "type": "Feature",
  "properties": {
    "addr:full":"18021 22nd Ave E Tacoma WA 98445",
    "addr:housenumber":"18021",
    "addr:postcode":"98445",
    "addr:street":"22Nd Ave E",
    "iso:country":"US",
    "sg:address":"18021 22nd Ave E",
    "sg:city":"Tacoma",
    "sg:classifiers":[
        {
            "category":"Building & Trades",
            "subcategory":"Construction",
            "type":"Services"
        }
    ],
    "sg:phone":"+1 253 847 1354",
    "sg:postcode":"98445",
    "sg:province":"WA",
    "sg:tags":[
        "carpentry",
        "contractor"
    ],
    "wof:name":"Dye General Contractors",
    "wof:placetype":"venue"
},
  "geometry": {"coordinates":[-122.400102,47.092701],"type":"Point"}
}