{
  "type": "Feature",
  "properties": {
    "addr:full":"3604 Grandview Dr W Tacoma WA 98466",
    "addr:housenumber":"3604",
    "addr:postcode":"98466",
    "addr:street":"Grandview Dr W",
    "iso:country":"US",
    "sg:address":"3604 Grandview Dr W",
    "sg:city":"Tacoma",
    "sg:classifiers":[
        {
            "category":"Personal",
            "subcategory":"Beauty Salon",
            "type":"Services"
        }
    ],
    "sg:phone":"+1 253 566 0354",
    "sg:postcode":"98466",
    "sg:province":"WA",
    "sg:tags":[
        "shop",
        "barber"
    ],
    "wof:name":"Gayle's Styling Salon",
    "wof:placetype":"venue"
},
  "geometry": {"coordinates":[-122.55212,47.225319],"type":"Point"}
}