{
  "type": "Feature",
  "properties": {
    "iso:country":"US",
    "sg:address":"19124 Jensen Way NE",
    "sg:city":"Poulsbo",
    "sg:classifiers":[
        {
            "category":"Manufacturing",
            "subcategory":"Printing",
            "type":"Manufacturing & Wholesale Goods"
        }
    ],
    "sg:phone":"+1 360 697 2286",
    "sg:postcode":"98370",
    "sg:province":"WA",
    "sg:tags":[
        "printer"
    ],
    "wof:name":"Kitsap Printing",
    "wof:placetype":"venue"
},
  "geometry": {"coordinates":[-122.646728,47.736551],"type":"Point"}
}