{
  "type": "Feature",
  "properties": {
    "addr:full":"18418 NE 207th Ave Brush Prairie WA 98606",
    "addr:housenumber":"18418",
    "addr:postcode":"98606",
    "addr:street":"Ne 207Th Ave",
    "iso:country":"US",
    "sg:address":"18418 NE 207th Ave",
    "sg:city":"Brush Prairie",
    "sg:classifiers":[
        {
            "category":"Shopping",
            "subcategory":"Beauty & Cosmetics",
            "type":"Retail Goods"
        }
    ],
    "sg:phone":"+1 360 892 1190",
    "sg:postcode":"98606",
    "sg:province":"WA",
    "sg:tags":[
        "merchandise"
    ],
    "wof:name":"Lucille Sarvela",
    "wof:placetype":"venue"
},
  "geometry": {"coordinates":[-122.460627,45.753245],"type":"Point"}
}