{
  "type": "Feature",
  "properties": {
    "addr:full":"700 5th Avenue Seattle WA 98104",
    "addr:housenumber":"700",
    "addr:postcode":"98104",
    "addr:street":"5Th Avenue",
    "iso:country":"US",
    "sg:address":"700 5th Avenue",
    "sg:city":"Seattle",
    "sg:classifiers":[
        {
            "category":"Utilities",
            "type":"Services"
        }
    ],
    "sg:phone":"+1 206 607 2700",
    "sg:postcode":"98104",
    "sg:province":"WA",
    "sg:tags":[
        "provider",
        "internet"
    ],
    "wof:name":"Tenzing Communications",
    "wof:placetype":"venue"
},
  "geometry": {"coordinates":[-122.32942,47.603871],"type":"Point"}
}