{
  "type": "Feature",
  "properties": {
    "addr:full":"5991 State Rte 270 Pullman WA 99163",
    "addr:housenumber":"5991",
    "addr:postcode":"99163",
    "addr:street":"State Rte 270",
    "iso:country":"US",
    "sg:address":"5991 State Rte 270",
    "sg:city":"Pullman",
    "sg:classifiers":[
        {
            "category":"Manufacturing",
            "subcategory":"Petroleum Products",
            "type":"Manufacturing & Wholesale Goods"
        }
    ],
    "sg:phone":"+1 509 334 6400",
    "sg:postcode":"99163",
    "sg:province":"WA",
    "sg:tags":[
        "asphalt"
    ],
    "sg:website":"www.poeasphalt.com",
    "wof:name":"Poe Asphalt Paving Inc",
    "wof:placetype":"venue"
},
  "geometry": {"coordinates":[-117.08772999999999,46.73176],"type":"Point"}
}