{
  "type": "Feature",
  "properties": {
    "addr:full":"4015 SE Sunrise Dr Camas WA 98607",
    "addr:housenumber":"4015",
    "addr:postcode":"98607",
    "addr:street":"Se Sunrise Dr",
    "iso:country":"US",
    "sg:address":"4015 SE Sunrise Dr",
    "sg:city":"Camas",
    "sg:classifiers":[
        {
            "category":"Home & Garden",
            "subcategory":"Garden Supply",
            "type":"Retail Goods"
        }
    ],
    "sg:phone":"+1 360 834 0270",
    "sg:postcode":"98607",
    "sg:province":"WA",
    "sg:tags":[
        "nurseryman"
    ],
    "wof:name":"Hilltop Nursery",
    "wof:placetype":"venue"
},
  "geometry": {"coordinates":[-122.46727,45.592561],"type":"Point"}
}