{
  "type": "Feature",
  "properties": {
    "addr:full":"1251 Lewis River Rd Woodland WA 98674",
    "addr:housenumber":"1251",
    "addr:postcode":"98674",
    "addr:street":"Lewis River Rd",
    "iso:country":"US",
    "sg:address":"1251 Lewis River Rd",
    "sg:city":"Woodland",
    "sg:classifiers":[
        {
            "category":"Health Services",
            "subcategory":"Doctor",
            "type":"Services"
        }
    ],
    "sg:phone":"+1 360 226 4310",
    "sg:postcode":"98674",
    "sg:province":"WA",
    "sg:tags":[
        "urgent",
        "center",
        "care"
    ],
    "wof:name":"Urgent Care Woodland",
    "wof:placetype":"venue"
},
  "geometry": {"coordinates":[-122.740441,45.909772],"type":"Point"}
}