{
  "type": "Feature",
  "properties": {
    "addr:full":"26930 104th Dr NW Stanwood WA 98292",
    "addr:housenumber":"26930",
    "addr:postcode":"98292",
    "addr:street":"104Th Dr Nw",
    "iso:country":"US",
    "sg:address":"26930 104th Dr NW",
    "sg:city":"Stanwood",
    "sg:classifiers":[
        {
            "category":"Food & Beverages",
            "subcategory":"Groceries & Convenience Stores",
            "type":"Retail Goods"
        }
    ],
    "sg:phone":"+1 360 629 5186",
    "sg:postcode":"98292",
    "sg:province":"WA",
    "wof:name":"Stanwood Ampm",
    "wof:placetype":"venue"
},
  "geometry": {"coordinates":[-122.374278,48.24183],"type":"Point"}
}