{
  "type": "Feature",
  "properties": {
    "addr:full":"1105 Spring St Apt 201 Seattle WA 98104",
    "addr:housenumber":"1105;201",
    "addr:postcode":"98104",
    "addr:street":"Spring St Apt",
    "iso:country":"US",
    "sg:address":"1105 Spring St Apt 201",
    "sg:city":"Seattle",
    "sg:classifiers":[
        {
            "category":"Bakery",
            "type":"Food & Drink"
        }
    ],
    "sg:phone":"+1 206 420 8504",
    "sg:postcode":"98104",
    "sg:province":"WA",
    "sg:tags":[
        "cake",
        "pastry",
        "wedding"
    ],
    "wof:name":"Bride Cake",
    "wof:placetype":"venue"
},
  "geometry": {"coordinates":[-122.32575199999999,47.610069],"type":"Point"}
}