{
  "type": "Feature",
  "properties": {
    "addr:full":"19401 40th Ave W Lynnwood WA 98036",
    "addr:housenumber":"19401",
    "addr:postcode":"98036",
    "addr:street":"40Th Ave W",
    "iso:country":"US",
    "sg:address":"19401 40th Ave W",
    "sg:city":"Lynnwood",
    "sg:classifiers":[
        {
            "category":"Health Services",
            "subcategory":"Doctor",
            "type":"Services"
        }
    ],
    "sg:phone":"+1 425 771 8161",
    "sg:postcode":"98036",
    "sg:province":"WA",
    "sg:tags":[
        "physician",
        "surgeon"
    ],
    "wof:name":"Advanced Open Imaging",
    "wof:placetype":"venue"
},
  "geometry": {"coordinates":[-122.28700000000001,47.821392],"type":"Point"}
}