{
  "type": "Feature",
  "properties": {
    "addr:full":"370 River Rd Sequim WA 98382",
    "addr:housenumber":"370",
    "addr:postcode":"98382",
    "addr:street":"River Rd",
    "iso:country":"US",
    "sg:address":"370 River Rd",
    "sg:city":"Sequim",
    "sg:classifiers":[
        {
            "category":"Personal",
            "subcategory":"Beauty Salon",
            "type":"Services"
        }
    ],
    "sg:phone":"+1 360 683 2055",
    "sg:postcode":"98382",
    "sg:province":"WA",
    "sg:tags":[
        "hair",
        "stylist"
    ],
    "wof:name":"Beauty Salon Priddy Fabul",
    "wof:placetype":"venue"
},
  "geometry": {"coordinates":[-123.13494900000001,48.07198],"type":"Point"}
}