{
  "type": "Feature",
  "properties": {
    "addr:full":"202 5th St NW Puyallup WA 98371",
    "addr:housenumber":"202",
    "addr:postcode":"98371",
    "addr:street":"5Th St Nw",
    "iso:country":"US",
    "sg:address":"202 5th St NW",
    "sg:city":"Puyallup",
    "sg:classifiers":[
        {
            "category":"Organizations",
            "subcategory":"Community Association",
            "type":"Services"
        }
    ],
    "sg:phone":"+1 253 845 5021",
    "sg:postcode":"98371",
    "sg:province":"WA",
    "sg:tags":[
        "fraternal"
    ],
    "wof:name":"Fraternal Order Of Eagles",
    "wof:placetype":"venue"
},
  "geometry": {"coordinates":[-122.29909600000001,47.192832],"type":"Point"}
}