{
  "type": "Feature",
  "properties": {
    "addr:full":"3157 Fisherman Bay Rd Lopez Island WA 98261",
    "addr:housenumber":"3157",
    "addr:postcode":"98261",
    "addr:street":"Fisherman Bay Rd Lopez Island",
    "iso:country":"US",
    "sg:address":"3157 Fisherman Bay Rd",
    "sg:city":"Lopez Island",
    "sg:classifiers":[
        {
            "category":"Organizations",
            "subcategory":"Non-profit Organization",
            "type":"Services"
        }
    ],
    "sg:phone":"+1 360 468 3202",
    "sg:postcode":"98261",
    "sg:province":"WA",
    "wof:name":"San Juan Preservation Trust",
    "wof:placetype":"venue"
},
  "geometry": {"coordinates":[-122.914265,48.509166],"type":"Point"}
}