{
  "type": "Feature",
  "properties": {
    "addr:full":"12314 Meridian E Ste A5 Puyallup WA 98373",
    "addr:housenumber":"12314",
    "addr:postcode":"98373",
    "addr:street":"Meridian E Ste A5",
    "iso:country":"US",
    "sg:address":"12314 Meridian E Ste A5",
    "sg:city":"Puyallup",
    "sg:classifiers":[
        {
            "category":"Retail",
            "subcategory":"Veterinary Services",
            "type":"Services"
        }
    ],
    "sg:phone":"+1 253 445 0808",
    "sg:postcode":"98373",
    "sg:province":"WA",
    "sg:tags":[
        "veterinarian",
        "specialty"
    ],
    "wof:name":"Vets For Less Animal Clinic",
    "wof:placetype":"venue"
},
  "geometry": {"coordinates":[-122.292957,47.143754],"type":"Point"}
}