{
  "type": "Feature",
  "properties": {
    "addr:full":"2015 S 96th St Tacoma WA 98444",
    "addr:housenumber":"2015",
    "addr:postcode":"98444",
    "addr:street":"S 96Th St",
    "iso:country":"US",
    "sg:address":"2015 S 96th St",
    "sg:city":"Tacoma",
    "sg:classifiers":[
        {
            "category":"Food & Beverages",
            "subcategory":"Groceries & Convenience Stores",
            "type":"Retail Goods"
        }
    ],
    "sg:phone":"+1 253 538 0632",
    "sg:postcode":"98444",
    "sg:province":"WA",
    "sg:tags":[
        "market"
    ],
    "wof:name":"First Market",
    "wof:placetype":"venue"
},
  "geometry": {"coordinates":[-122.462962,47.170251],"type":"Point"}
}