{
  "type": "Feature",
  "properties": {
    "iso:country":"US",
    "sg:address":"14212 SE 38th St",
    "sg:city":"Bellevue",
    "sg:classifiers":[
        {
            "category":"Building & Trades",
            "subcategory":"Construction",
            "type":"Services"
        }
    ],
    "sg:phone":"+1 425 643 2589",
    "sg:postcode":"98006",
    "sg:province":"WA",
    "sg:tags":[
        "concrete",
        "contractor"
    ],
    "wof:name":"Lihona Concrete & Masonar",
    "wof:placetype":"venue"
},
  "geometry": {"coordinates":[-122.14937399999999,47.576808],"type":"Point"}
}