{
  "type": "Feature",
  "properties": {
    "addr:full":"4900 Rainier Ave Seattle WA 98118",
    "addr:housenumber":"4900",
    "addr:postcode":"98118",
    "addr:street":"Rainier Ave",
    "iso:country":"US",
    "sg:address":"4900 Rainier Ave",
    "sg:city":"Seattle",
    "sg:classifiers":[
        {
            "category":"Personal",
            "subcategory":"Massage",
            "type":"Services"
        }
    ],
    "sg:phone":"+1 206 760 7661",
    "sg:postcode":"98118",
    "sg:province":"WA",
    "sg:website":"bodygoodmassage.com",
    "wof:name":"BodyGood Massage Therapy",
    "wof:placetype":"venue"
},
  "geometry": {"coordinates":[-122.285009,47.557855],"type":"Point"}
}