{
  "type": "Feature",
  "properties": {
    "addr:full":"9919 NE St Johns Rd Vancouver WA 98686",
    "addr:housenumber":"9919",
    "addr:postcode":"98686",
    "addr:street":"Ne St Johns Rd",
    "iso:country":"US",
    "sg:address":"9919 NE St Johns Rd",
    "sg:city":"Vancouver",
    "sg:classifiers":[
        {
            "category":"Wholesale",
            "subcategory":"Construction Materials",
            "type":"Manufacturing & Wholesale Goods"
        }
    ],
    "sg:phone":"+1 360 573 6655",
    "sg:postcode":"98686",
    "sg:province":"WA",
    "sg:tags":[
        "fence"
    ],
    "wof:name":"D J Fence Svc",
    "wof:placetype":"venue"
},
  "geometry": {"coordinates":[-122.612664,45.694959],"type":"Point"}
}