{
  "type": "Feature",
  "properties": {
    "addr:full":"4625 45th Ave SE Ofc Lacey WA 98503",
    "addr:housenumber":"4625",
    "addr:postcode":"98503",
    "addr:street":"45Th Ave Se",
    "iso:country":"US",
    "sg:address":"4625 45th Ave SE Ofc",
    "sg:city":"Lacey",
    "sg:classifiers":[
        {
            "category":"Real Estate",
            "subcategory":"Real Estate Services",
            "type":"Services"
        },
        {
            "category":"Real Estate",
            "subcategory":"Real Estate Operator",
            "type":"Services"
        }
    ],
    "sg:phone":"+1 360 438 6659",
    "sg:postcode":"98503",
    "sg:province":"WA",
    "sg:tags":[
        "vacancy",
        "apartment",
        "rental",
        "finder",
        "listing"
    ],
    "wof:name":"College Point Apts",
    "wof:placetype":"venue"
},
  "geometry": {"coordinates":[-122.82208300000001,47.007109],"type":"Point"}
}