{
  "type": "Feature",
  "properties": {
    "addr:full":"8014 NW 12th Ave Vancouver WA 98665",
    "addr:housenumber":"8014",
    "addr:postcode":"98665",
    "addr:street":"Nw 12Th Ave",
    "iso:country":"US",
    "sg:address":"8014 NW 12th Ave",
    "sg:city":"Vancouver",
    "sg:classifiers":[
        {
            "category":"Shopping",
            "subcategory":"Bicycles & Sporting Goods",
            "type":"Retail Goods"
        }
    ],
    "sg:phone":"+1 360 798 2812",
    "sg:postcode":"98665",
    "sg:province":"WA",
    "wof:name":"Bike Cellar",
    "wof:placetype":"venue"
},
  "geometry": {"coordinates":[-122.683955,45.680285],"type":"Point"}
}