{
  "type": "Feature",
  "properties": {
    "addr:full":"2916 W Bismark Ave Spokane WA 99205",
    "addr:housenumber":"2916",
    "addr:postcode":"99205",
    "addr:street":"W Bismark Ave",
    "iso:country":"US",
    "sg:address":"2916 W Bismark Ave",
    "sg:city":"Spokane",
    "sg:classifiers":[
        {
            "category":"Autos & Motor Vehicles",
            "subcategory":"Automobile Sales",
            "type":"Retail Goods"
        }
    ],
    "sg:phone":"+1 509 323 1707",
    "sg:postcode":"99205",
    "sg:province":"WA",
    "wof:name":"Limo Lane",
    "wof:placetype":"venue"
},
  "geometry": {"coordinates":[-117.45442799999999,47.713064],"type":"Point"}
}