{
  "type": "Feature",
  "properties": {
    "addr:full":"4 S South Lander Seattle WA 98134",
    "addr:housenumber":"4",
    "addr:postcode":"98134",
    "addr:street":"S South",
    "iso:country":"US",
    "sg:address":"4 S South Lander",
    "sg:city":"Seattle",
    "sg:classifiers":[
        {
            "category":"Autos & Motor Vehicles",
            "subcategory":"Auto Supplies",
            "type":"Retail Goods"
        }
    ],
    "sg:phone":"+1 206 628 4812",
    "sg:postcode":"98134",
    "sg:province":"WA",
    "sg:tags":[
        "tire"
    ],
    "wof:name":"Tires 4 Less",
    "wof:placetype":"venue"
},
  "geometry": {"coordinates":[-122.34005500000001,47.5797],"type":"Point"}
}