{
  "type": "Feature",
  "properties": {
    "addr:full":"16005 193rd Ave SE Renton WA 98058",
    "addr:housenumber":"16005",
    "addr:postcode":"98058",
    "addr:street":"193Rd Ave Se",
    "iso:country":"US",
    "sg:address":"16005 193rd Ave SE",
    "sg:city":"Renton",
    "sg:classifiers":[
        {
            "category":"Building & Trades",
            "subcategory":"Construction",
            "type":"Services"
        }
    ],
    "sg:phone":"+1 425 226 5112",
    "sg:postcode":"98058",
    "sg:province":"WA",
    "sg:tags":[
        "contractor"
    ],
    "wof:name":"Hockenson Tile",
    "wof:placetype":"venue"
},
  "geometry": {"coordinates":[-122.083358,47.458151],"type":"Point"}
}