{
  "type": "Feature",
  "properties": {
    "addr:full":"144 Bellevue Sq Bellevue WA 98004",
    "addr:housenumber":"144",
    "addr:postcode":"98004",
    "addr:street":"Bellevue Sq",
    "iso:country":"US",
    "sg:address":"144 Bellevue Sq",
    "sg:city":"Bellevue",
    "sg:classifiers":[
        {
            "category":"Shopping",
            "subcategory":"Hobbies, Toys, & Games",
            "type":"Retail Goods"
        }
    ],
    "sg:phone":"+1 425 467 5944",
    "sg:postcode":"98004",
    "sg:province":"WA",
    "sg:tags":[
        "toy",
        "store"
    ],
    "wof:name":"Build A Bear Workshop",
    "wof:placetype":"venue"
},
  "geometry": {"coordinates":[-122.19899700000001,47.614799],"type":"Point"}
}