{
  "type": "Feature",
  "properties": {
    "addr:full":"2892 State Hwy 211 Newport WA 99156",
    "addr:housenumber":"2892",
    "addr:postcode":"99156",
    "addr:street":"State Hwy 211",
    "iso:country":"US",
    "sg:address":"2892 State Hwy 211",
    "sg:city":"Newport",
    "sg:classifiers":[
        {
            "category":"Organizations",
            "subcategory":"Religious Organization",
            "type":"Services"
        }
    ],
    "sg:phone":"+1 509 292 0978",
    "sg:postcode":"99156",
    "sg:province":"WA",
    "wof:name":"Carmelite Sisters of Mary",
    "wof:placetype":"venue"
},
  "geometry": {"coordinates":[-117.27953100000001,48.131148],"type":"Point"}
}