{
  "type": "Feature",
  "properties": {
    "iso:country":"US",
    "sg:address":"253 D St NE",
    "sg:city":"Ephrata",
    "sg:classifiers":[
        {
            "category":"Farming",
            "subcategory":"Farm",
            "type":"Manufacturing & Wholesale Goods"
        }
    ],
    "sg:phone":"+1 509 754 4152",
    "sg:postcode":"98823",
    "sg:province":"WA",
    "sg:tags":[
        "crop",
        "general"
    ],
    "wof:name":"Barry Schmidt",
    "wof:placetype":"venue"
},
  "geometry": {"coordinates":[-119.544256,47.323531],"type":"Point"}
}