{
  "type": "Feature",
  "properties": {
    "addr:full":"3610 104th St E Tacoma WA 98446",
    "addr:housenumber":"3610",
    "addr:postcode":"98446",
    "addr:street":"104Th St",
    "iso:country":"US",
    "sg:address":"3610 104th St E",
    "sg:city":"Tacoma",
    "sg:classifiers":[
        {
            "category":"Manufacturing",
            "subcategory":"Tools & Machinery",
            "type":"Manufacturing & Wholesale Goods"
        }
    ],
    "sg:phone":"+1 253 535 0408",
    "sg:postcode":"98446",
    "sg:province":"WA",
    "sg:tags":[
        "engine",
        "equipment",
        "electrical",
        "mfg"
    ],
    "wof:name":"Electra Start Inc",
    "wof:placetype":"venue"
},
  "geometry": {"coordinates":[-122.380425,47.162109],"type":"Point"}
}