{
  "type": "Feature",
  "properties": {
    "addr:full":"11700 Mukilteo Speedway Mukilteo WA 98275",
    "addr:housenumber":"11700",
    "addr:postcode":"98275",
    "addr:street":"Mukilteo Speedway",
    "iso:country":"US",
    "sg:address":"11700 Mukilteo Speedway",
    "sg:city":"Mukilteo",
    "sg:classifiers":[
        {
            "category":"Shopping",
            "type":"Retail Goods"
        },
        {
            "category":"Shopping",
            "subcategory":"Computers & Home Electronics",
            "type":"Retail Goods"
        }
    ],
    "sg:phone":"+1 425 353 2131",
    "sg:postcode":"98275",
    "sg:province":"WA",
    "sg:tags":[
        "telephone",
        "cellular"
    ],
    "wof:name":"Radio Shack",
    "wof:placetype":"venue"
},
  "geometry": {"coordinates":[-122.28770299999999,47.893922],"type":"Point"}
}