{
  "type": "Feature",
  "properties": {
    "addr:full":"353 W Bell St Sequim WA 98382",
    "addr:housenumber":"353",
    "addr:postcode":"98382",
    "addr:street":"W Bell St",
    "iso:country":"US",
    "sg:address":"353 W Bell St",
    "sg:city":"Sequim",
    "sg:classifiers":[
        {
            "category":"Shopping",
            "subcategory":"Books",
            "type":"Retail Goods"
        }
    ],
    "sg:phone":"+1 360 683 9004",
    "sg:postcode":"98382",
    "sg:province":"WA",
    "sg:tags":[
        "dealer"
    ],
    "wof:name":"Healing Heart Ctr",
    "wof:placetype":"venue"
},
  "geometry": {"coordinates":[-123.109295,48.078678],"type":"Point"}
}