{
  "type": "Feature",
  "properties": {
    "addr:full":"115 W Yakima Ave Yakima WA 98902",
    "addr:housenumber":"115",
    "addr:postcode":"98902",
    "addr:street":"W Yakima Ave",
    "iso:country":"US",
    "sg:address":"115 W Yakima Ave",
    "sg:city":"Yakima",
    "sg:classifiers":[
        {
            "category":"Banks & Credit Unions",
            "subcategory":"Financial Services",
            "type":"Services"
        }
    ],
    "sg:phone":"+1 509 771 6887",
    "sg:postcode":"98902",
    "sg:province":"WA",
    "sg:tags":[
        "company",
        "holding"
    ],
    "wof:name":"Antique World On Line",
    "wof:placetype":"venue"
},
  "geometry": {"coordinates":[-120.511078,46.601153],"type":"Point"}
}