{
  "type": "Feature",
  "properties": {
    "addr:full":"16508 154th Street Kp N Gig Harbor WA 98329",
    "addr:housenumber":"16508",
    "addr:postcode":"98329",
    "addr:street":"154Th Street Kp N",
    "iso:country":"US",
    "sg:address":"16508 154th Street Kp N",
    "sg:city":"Gig Harbor",
    "sg:classifiers":[
        {
            "category":"Building & Trades",
            "subcategory":"Construction",
            "type":"Services"
        }
    ],
    "sg:phone":"+1 253 884 5451",
    "sg:postcode":"98329",
    "sg:province":"WA",
    "sg:tags":[
        "house"
    ],
    "wof:name":"J & K Construcion",
    "wof:placetype":"venue"
},
  "geometry": {"coordinates":[-122.757994,47.397885],"type":"Point"}
}