{
  "type": "Feature",
  "properties": {
    "iso:country":"US",
    "sg:address":"18260 Segale Park Dr D",
    "sg:city":"Seattle",
    "sg:classifiers":[
        {
            "category":"Autos & Motor Vehicles",
            "subcategory":"Auto Supplies",
            "type":"Retail Goods"
        }
    ],
    "sg:phone":"+1 206 575 4681",
    "sg:postcode":"98188",
    "sg:province":"WA",
    "wof:name":"Big A Auto Parts",
    "wof:placetype":"venue"
},
  "geometry": {"coordinates":[-122.25595300000001,47.440119],"type":"Point"}
}