{
  "type": "Feature",
  "properties": {
    "addr:full":"929 N 130th St Ste 8 Seattle WA 98133",
    "addr:housenumber":"929",
    "addr:postcode":"98133",
    "addr:street":"N 130Th St Ste 8",
    "iso:country":"US",
    "sg:address":"929 N 130th St Ste 8",
    "sg:city":"Seattle",
    "sg:classifiers":[
        {
            "category":"Personal",
            "type":"Services"
        },
        {
            "category":"Shopping",
            "subcategory":"Bridal",
            "type":"Retail Goods"
        }
    ],
    "sg:phone":"+1 206 367 2392",
    "sg:postcode":"98133",
    "sg:province":"WA",
    "sg:tags":[
        "sewing",
        "alteration"
    ],
    "sg:website":"www.vcustomdesign.com",
    "wof:name":"V Custom Design",
    "wof:placetype":"venue"
},
  "geometry": {"coordinates":[-122.34774899999999,47.723203],"type":"Point"}
}