{
  "type": "Feature",
  "properties": {
    "addr:full":"1104 University St Clarkston WA 99403",
    "addr:housenumber":"1104",
    "addr:postcode":"99403",
    "addr:street":"University St",
    "iso:country":"US",
    "sg:address":"1104 University St",
    "sg:city":"Clarkston",
    "sg:classifiers":[
        {
            "category":"Manufacturing",
            "subcategory":"Buildings",
            "type":"Manufacturing & Wholesale Goods"
        },
        {
            "category":"Building & Trades",
            "subcategory":"Construction",
            "type":"Services"
        }
    ],
    "sg:phone":"+1 509 758 4631",
    "sg:postcode":"99403",
    "sg:province":"WA",
    "sg:tags":[
        "home",
        "builder",
        "contractor"
    ],
    "wof:name":"Kaufman Construction",
    "wof:placetype":"venue"
},
  "geometry": {"coordinates":[-117.054688,46.408657],"type":"Point"}
}