{
  "type": "Feature",
  "properties": {
    "addr:full":"204 SE Park Plaza Dr Ste 103 Vancouver WA 98684",
    "addr:housenumber":"204",
    "addr:postcode":"98684",
    "addr:street":"Se Park Plaza Dr Ste 103",
    "iso:country":"US",
    "sg:address":"204 SE Park Plaza Dr Ste 103",
    "sg:city":"Vancouver",
    "sg:classifiers":[
        {
            "category":"Restaurant",
            "type":"Food & Drink"
        }
    ],
    "sg:phone":"+1 360 883 1325",
    "sg:postcode":"98684",
    "sg:province":"WA",
    "wof:name":"Little Italy's Trattoria",
    "wof:placetype":"venue"
},
  "geometry": {"coordinates":[-122.53800200000001,45.619301],"type":"Point"}
}