{
  "type": "Feature",
  "properties": {
    "addr:full":"3889 Harborview Dr Gig Harbor WA 98332",
    "addr:housenumber":"3889",
    "addr:postcode":"98332",
    "addr:street":"Harborview Dr",
    "iso:country":"US",
    "sg:address":"3889 Harborview Dr",
    "sg:city":"Gig Harbor",
    "sg:classifiers":[
        {
            "category":"Professional",
            "subcategory":"Business Services",
            "type":"Services"
        }
    ],
    "sg:phone":"+1 253 858 9859",
    "sg:postcode":"98332",
    "sg:province":"WA",
    "wof:name":"Abode Design",
    "wof:placetype":"venue"
},
  "geometry": {"coordinates":[-122.594132,47.337123],"type":"Point"}
}