{
  "type": "Feature",
  "properties": {
    "addr:full":"3518 Fremont Ave N Ste 274 Seattle WA 98103",
    "addr:housenumber":"3518",
    "addr:postcode":"98103",
    "addr:street":"Fremont Ave N Ste 274",
    "iso:country":"US",
    "sg:address":"3518 Fremont Ave N Ste 274",
    "sg:city":"Seattle",
    "sg:classifiers":[
        {
            "category":"Building & Trades",
            "subcategory":"Plumbing",
            "type":"Services"
        }
    ],
    "sg:phone":"+1 206 786 4414",
    "sg:postcode":"98103",
    "sg:province":"WA",
    "sg:website":"www.paradiseplumbing.net",
    "wof:name":"Paradise Plumbing",
    "wof:placetype":"venue"
},
  "geometry": {"coordinates":[-122.349852,47.650793],"type":"Point"}
}