{
  "type": "Feature",
  "properties": {
    "addr:full":"8909 W Gage Blvd Kennewick WA 99336",
    "addr:housenumber":"8909",
    "addr:postcode":"99336",
    "addr:street":"W Gage Blvd",
    "iso:country":"US",
    "sg:address":"8909 W Gage Blvd",
    "sg:city":"Kennewick",
    "sg:classifiers":[
        {
            "category":"Banks & Credit Unions",
            "subcategory":"Bank",
            "type":"Services"
        }
    ],
    "sg:phone":"+1 509 735 6696",
    "sg:postcode":"99336",
    "sg:province":"WA",
    "wof:name":"Yakima Federal Savings & Loan",
    "wof:placetype":"venue"
},
  "geometry": {"coordinates":[-119.24059099999999,46.227163],"type":"Point"}
}