{
  "type": "Feature",
  "properties": {
    "addr:full":"21616 76th Ave W Ste 109 Edmonds WA 98026",
    "addr:housenumber":"21616",
    "addr:postcode":"98026",
    "addr:street":"76Th Ave W Ste 109",
    "iso:country":"US",
    "sg:address":"21616 76th Ave W Ste 109",
    "sg:city":"Edmonds",
    "sg:classifiers":[
        {
            "category":"Health Services",
            "subcategory":"Doctor",
            "type":"Services"
        }
    ],
    "sg:phone":"+1 425 670 6788",
    "sg:postcode":"98026",
    "sg:province":"WA",
    "sg:tags":[
        "physician",
        "family",
        "practice",
        "surgeons",
        "medicine",
        "surgeon"
    ],
    "wof:name":"Ronald M Waltz Md Inc",
    "wof:placetype":"venue"
},
  "geometry": {"coordinates":[-122.33567499999999,47.803154],"type":"Point"}
}