{
  "type": "Feature",
  "properties": {
    "addr:full":"750 17th Ave NW Issaquah WA 98027",
    "addr:housenumber":"750",
    "addr:postcode":"98027",
    "addr:street":"17Th Ave Nw",
    "iso:country":"US",
    "sg:address":"750 17th Ave NW",
    "sg:city":"Issaquah",
    "sg:classifiers":[
        {
            "category":"Retail",
            "subcategory":"Event Space",
            "type":"Services"
        },
        {
            "category":"Community Center",
            "type":"Public Place"
        },
        {
            "category":"Government",
            "subcategory":"Office",
            "type":"Public Place"
        }
    ],
    "sg:phone":"+1 425 837 3366",
    "sg:postcode":"98027",
    "sg:province":"WA",
    "sg:tags":[
        "recreation",
        "facility",
        "hall",
        "reception",
        "village",
        "township",
        "government-city",
        "banquet"
    ],
    "wof:name":"Tibbetts Creek Manor",
    "wof:placetype":"venue"
},
  "geometry": {"coordinates":[-122.063142,47.539066],"type":"Point"}
}