{
  "type": "Feature",
  "properties": {
    "addr:full":"110 12 7TH ST Vader WA 98593",
    "addr:housenumber":"110 12",
    "addr:postcode":"98593",
    "addr:street":"7Th St",
    "iso:country":"US",
    "sg:address":"110 12 7TH ST",
    "sg:city":"Vader",
    "sg:classifiers":[
        {
            "category":"Retail",
            "subcategory":"Storage",
            "type":"Services"
        }
    ],
    "sg:phone":"+1 360 295 3716",
    "sg:postcode":"98593",
    "sg:province":"WA",
    "sg:tags":[
        "self",
        "commercial",
        "household"
    ],
    "wof:name":"Daileys Mini Storage",
    "wof:placetype":"venue"
},
  "geometry": {"coordinates":[-123.019409,46.41169],"type":"Point"}
}