{
  "type": "Feature",
  "properties": {
    "addr:full":"136 102nd Ave SE Bellevue WA 98004",
    "addr:housenumber":"136",
    "addr:postcode":"98004",
    "addr:street":"102Nd Ave Se",
    "iso:country":"US",
    "sg:address":"136 102nd Ave SE",
    "sg:city":"Bellevue",
    "sg:classifiers":[
        {
            "category":"Sports & Exercise",
            "subcategory":"Gym",
            "type":"Entertainment"
        }
    ],
    "sg:phone":"+1 425 451 3444",
    "sg:postcode":"98004",
    "sg:province":"WA",
    "sg:tags":[
        "club",
        "health",
        "studio",
        "gymnasium"
    ],
    "wof:name":"Innovative Fitness Consultants",
    "wof:placetype":"venue"
},
  "geometry": {"coordinates":[-122.204054,47.608966],"type":"Point"}
}