{
  "type": "Feature",
  "properties": {
    "iso:country":"US",
    "sg:address":"9401 Lupine Cir W",
    "sg:city":"Tacoma",
    "sg:classifiers":[
        {
            "category":"Building & Trades",
            "subcategory":"Construction",
            "type":"Services"
        }
    ],
    "sg:phone":"+1 253 566 3317",
    "sg:postcode":"98467",
    "sg:province":"WA",
    "sg:tags":[
        "hanging",
        "contractor"
    ],
    "wof:name":"Painting By George",
    "wof:placetype":"venue"
},
  "geometry": {"coordinates":[-122.563079,47.208518],"type":"Point"}
}