{
  "type": "Feature",
  "properties": {
    "addr:full":"3714 14th Ave S Seattle WA 98144",
    "addr:housenumber":"3714",
    "addr:postcode":"98144",
    "addr:street":"14Th Ave S",
    "iso:country":"US",
    "sg:address":"3714 14th Ave S",
    "sg:city":"Seattle",
    "sg:classifiers":[
        {
            "category":"Social Services",
            "subcategory":"Child Care",
            "type":"Services"
        }
    ],
    "sg:phone":"+1 206 764 1066",
    "sg:postcode":"98144",
    "sg:province":"WA",
    "wof:name":"Amana Family Child Care",
    "wof:placetype":"venue"
},
  "geometry": {"coordinates":[-122.31467000000001,47.569869],"type":"Point"}
}