{
  "type": "Feature",
  "properties": {
    "addr:full":"5606 1st Ave S Seattle WA 98108",
    "addr:housenumber":"5606",
    "addr:postcode":"98108",
    "addr:street":"1St Ave S",
    "iso:country":"US",
    "sg:address":"5606 1st Ave S",
    "sg:city":"Seattle",
    "sg:phone":"+1 206 762 7900",
    "sg:postcode":"98108",
    "sg:province":"WA",
    "sg:website":"http://www.slimslastchance.com",
    "wof:name":"Slim's Last Chance",
    "wof:placetype":"venue"
},
  "geometry": {"coordinates":[-122.33421300000001,47.552642],"type":"Point"}
}