{
  "type": "Feature",
  "properties": {
    "addr:full":"2707 NE 125th Street Seattle WA 98125",
    "addr:housenumber":"2707",
    "addr:postcode":"98125",
    "addr:street":"Ne 125Th Street",
    "iso:country":"US",
    "sg:address":"2707 NE 125th Street",
    "sg:city":"Seattle",
    "sg:classifiers":[
        {
            "category":"Banks & Credit Unions",
            "subcategory":"Bank",
            "type":"Services"
        }
    ],
    "sg:phone":"+1 206 362 2660",
    "sg:postcode":"98125",
    "sg:province":"WA",
    "wof:name":"Kobs Juliann",
    "wof:placetype":"venue"
},
  "geometry": {"coordinates":[-122.298445,47.719391],"type":"Point"}
}