{
  "type": "Feature",
  "properties": {
    "addr:full":"4725 36th St NE Tacoma WA 98422",
    "addr:housenumber":"4725",
    "addr:postcode":"98422",
    "addr:street":"36Th St Ne",
    "iso:country":"US",
    "sg:address":"4725 36th St NE",
    "sg:city":"Tacoma",
    "sg:classifiers":[
        {
            "category":"Professional",
            "subcategory":"Computer Services",
            "type":"Services"
        }
    ],
    "sg:phone":"+1 253 927 8703",
    "sg:postcode":"98422",
    "sg:province":"WA",
    "sg:tags":[
        "consultant",
        "designer",
        "system"
    ],
    "sg:website":"http://www.fison.net",
    "wof:name":"Fison Services",
    "wof:placetype":"venue"
},
  "geometry": {"coordinates":[-122.384882,47.289704],"type":"Point"}
}