{
  "type": "Feature",
  "properties": {
    "addr:full":"945 6th St Mukilteo WA 98275",
    "addr:housenumber":"945",
    "addr:postcode":"98275",
    "addr:street":"6Th St",
    "iso:country":"US",
    "sg:address":"945 6th St",
    "sg:city":"Mukilteo",
    "sg:classifiers":[
        {
            "category":"Personal",
            "type":"Services"
        }
    ],
    "sg:phone":"+1 425 348 5149",
    "sg:postcode":"98275",
    "sg:province":"WA",
    "wof:name":"M & M Embroidery",
    "wof:placetype":"venue"
},
  "geometry": {"coordinates":[-122.298124,47.944734],"type":"Point"}
}