{
  "type": "Feature",
  "properties": {
    "addr:full":"3513 NE 45th Street Seattle WA 98105",
    "addr:housenumber":"3513",
    "addr:postcode":"98105",
    "addr:street":"Ne 45Th Street",
    "iso:country":"US",
    "sg:address":"3513 NE 45th Street",
    "sg:city":"Seattle",
    "sg:classifiers":[
        {
            "category":"Home & Garden",
            "subcategory":"Home Furnishings",
            "type":"Retail Goods"
        },
        {
            "category":"Professional",
            "subcategory":"Art Services",
            "type":"Services"
        },
        {
            "category":"Building & Trades",
            "subcategory":"Construction",
            "type":"Services"
        },
        {
            "category":"Home & Garden",
            "subcategory":"Furniture",
            "type":"Retail Goods"
        }
    ],
    "sg:phone":"+1 206 517 4424",
    "sg:postcode":"98105",
    "sg:province":"WA",
    "sg:tags":[
        "designer",
        "altering",
        "contractor",
        "planning",
        "design",
        "decorator",
        "interior",
        "remodeling",
        "store"
    ],
    "sg:website":"http://www.christinesuzuki.com",
    "wof:name":"Christine Suzuki & Associates",
    "wof:placetype":"venue"
},
  "geometry": {"coordinates":[-122.289886,47.661145],"type":"Point"}
}