{
  "type": "Feature",
  "properties": {
    "addr:full":"1428 Judson Ave Richland WA 99354",
    "addr:housenumber":"1428",
    "addr:postcode":"99354",
    "addr:street":"Judson Ave",
    "iso:country":"US",
    "sg:address":"1428 Judson Ave",
    "sg:city":"Richland",
    "sg:classifiers":[
        {
            "category":"Social Services",
            "subcategory":"Child Care",
            "type":"Services"
        }
    ],
    "sg:phone":"+1 509 943 2628",
    "sg:postcode":"99354",
    "sg:province":"WA",
    "sg:tags":[
        "nursery",
        "day"
    ],
    "wof:name":"Conrads Daycare",
    "wof:placetype":"venue"
},
  "geometry": {"coordinates":[-119.279734,46.290094],"type":"Point"}
}