{
  "type": "Feature",
  "properties": {
    "addr:full":"4610 Hickory Dr Anacortes WA 98221",
    "addr:housenumber":"4610",
    "addr:postcode":"98221",
    "addr:street":"Hickory Dr",
    "iso:country":"US",
    "sg:address":"4610 Hickory Dr",
    "sg:city":"Anacortes",
    "sg:classifiers":[
        {
            "category":"Building & Trades",
            "subcategory":"Construction",
            "type":"Services"
        }
    ],
    "sg:phone":"+1 360 588 8018",
    "sg:postcode":"98221",
    "sg:province":"WA",
    "sg:tags":[
        "house"
    ],
    "wof:name":"Island Design Works",
    "wof:placetype":"venue"
},
  "geometry": {"coordinates":[-122.634745,48.483306],"type":"Point"}
}