{
  "type": "Feature",
  "properties": {
    "addr:full":"5687 S 6th Way Ridgefield WA 98642",
    "addr:housenumber":"5687",
    "addr:postcode":"98642",
    "addr:street":"S 6Th Way",
    "iso:country":"US",
    "sg:address":"5687 S 6th Way",
    "sg:city":"Ridgefield",
    "sg:classifiers":[
        {
            "category":"Banks & Credit Unions",
            "subcategory":"Bank",
            "type":"Services"
        }
    ],
    "sg:phone":"+1 360 887 3319",
    "sg:postcode":"98642",
    "sg:province":"WA",
    "wof:name":"People Community Credit Union",
    "wof:placetype":"venue"
},
  "geometry": {"coordinates":[-122.68778500000001,45.810701],"type":"Point"}
}