{
  "type": "Feature",
  "properties": {
    "addr:full":"1660 Heritage Way Woodland WA 98674",
    "addr:housenumber":"1660",
    "addr:postcode":"98674",
    "addr:street":"Heritage Way",
    "iso:country":"US",
    "sg:address":"1660 Heritage Way",
    "sg:city":"Woodland",
    "sg:classifiers":[
        {
            "category":"Manufacturing",
            "subcategory":"Paper Products",
            "type":"Manufacturing & Wholesale Goods"
        }
    ],
    "sg:phone":"+1 360 225 0488",
    "sg:postcode":"98674",
    "sg:province":"WA",
    "sg:tags":[
        "converted",
        "mfg"
    ],
    "wof:name":"American Paper Converting",
    "wof:placetype":"venue"
},
  "geometry": {"coordinates":[-122.761404,45.924701],"type":"Point"}
}