{
  "type": "Feature",
  "properties": {
    "addr:full":"31610 NE 40th St Carnation WA 98014",
    "addr:housenumber":"31610",
    "addr:postcode":"98014",
    "addr:street":"Ne 40Th St",
    "iso:country":"US",
    "sg:address":"31610 NE 40th St",
    "sg:city":"Carnation",
    "sg:classifiers":[
        {
            "category":"Manufacturing",
            "subcategory":"Tools & Machinery",
            "type":"Manufacturing & Wholesale Goods"
        }
    ],
    "sg:phone":"+1 425 883 1991",
    "sg:postcode":"98014",
    "sg:province":"WA",
    "sg:tags":[
        "mold"
    ],
    "wof:name":"Eldorado Stone LLC",
    "wof:placetype":"venue"
},
  "geometry": {"coordinates":[-121.916554,47.644349],"type":"Point"}
}