{
  "type": "Feature",
  "properties": {
    "addr:full":"1000 13th Ave SW Quincy WA 98848",
    "addr:housenumber":"1000",
    "addr:postcode":"98848",
    "addr:street":"13Th Ave Sw",
    "iso:country":"US",
    "sg:address":"1000 13th Ave SW",
    "sg:city":"Quincy",
    "sg:classifiers":[
        {
            "category":"Building & Trades",
            "subcategory":"Construction",
            "type":"Services"
        }
    ],
    "sg:phone":"+1 509 787 4123",
    "sg:postcode":"98848",
    "sg:province":"WA",
    "sg:tags":[
        "general",
        "contractor"
    ],
    "wof:name":"Valley Construction",
    "wof:placetype":"venue"
},
  "geometry": {"coordinates":[-119.87508099999999,47.2331],"type":"Point"}
}