{
  "type": "Feature",
  "properties": {
    "addr:full":"3315 S 116th St Ste 115 Tukwila WA 98168",
    "addr:housenumber":"3315",
    "addr:postcode":"98168",
    "addr:street":"S 116Th St Ste 115",
    "iso:country":"US",
    "sg:address":"3315 S 116th St Ste 115",
    "sg:city":"Tukwila",
    "sg:classifiers":[
        {
            "category":"Personal",
            "type":"Services"
        },
        {
            "category":"Professional",
            "subcategory":"Detective & Security Services",
            "type":"Services"
        },
        {
            "category":"Manufacturing",
            "subcategory":"Building Materials",
            "type":"Manufacturing & Wholesale Goods"
        }
    ],
    "sg:phone":"+1 206 772 7502",
    "sg:postcode":"98168",
    "sg:province":"WA",
    "sg:tags":[
        "control",
        "monitoring",
        "fire",
        "alarm",
        "system",
        "systems-wholesale",
        "medical",
        "manufacturer"
    ],
    "wof:name":"Northwest Fire Systems",
    "wof:placetype":"venue"
},
  "geometry": {"coordinates":[-122.291147,47.499442],"type":"Point"}
}