{
  "type": "Feature",
  "properties": {
    "addr:full":"8514 26th Ave NW Seattle WA 98117",
    "addr:housenumber":"8514",
    "addr:postcode":"98117",
    "addr:street":"26Th Ave Nw",
    "iso:country":"US",
    "sg:address":"8514 26th Ave NW",
    "sg:city":"Seattle",
    "sg:classifiers":[
        {
            "category":"Restaurant",
            "type":"Food & Drink"
        }
    ],
    "sg:phone":"+1 206 782 5615",
    "sg:postcode":"98117",
    "sg:province":"WA",
    "sg:tags":[
        "eating"
    ],
    "wof:name":"Blue Plate Innovations LLC",
    "wof:placetype":"venue"
},
  "geometry": {"coordinates":[-122.39022799999999,47.691202],"type":"Point"}
}