{
  "type": "Feature",
  "properties": {
    "addr:full":"734 S Market Blvd Chehalis WA 98532",
    "addr:housenumber":"734",
    "addr:postcode":"98532",
    "addr:street":"S Market Blvd",
    "iso:country":"US",
    "sg:address":"734 S Market Blvd",
    "sg:city":"Chehalis",
    "sg:classifiers":[
        {
            "category":"Social Services",
            "type":"Services"
        }
    ],
    "sg:phone":"+1 360 748 4607",
    "sg:postcode":"98532",
    "sg:province":"WA",
    "sg:tags":[
        "organization",
        "welfare"
    ],
    "wof:name":"American Red Cross",
    "wof:placetype":"venue"
},
  "geometry": {"coordinates":[-122.957848,46.657179],"type":"Point"}
}