{
  "type": "Feature",
  "properties": {
    "addr:full":"318 6th Ave S Seattle WA 98104",
    "addr:housenumber":"318",
    "addr:postcode":"98104",
    "addr:street":"6Th Ave S",
    "iso:country":"US",
    "sg:address":"318 6th Ave S",
    "sg:city":"Seattle",
    "sg:classifiers":[
        {
            "category":"Professional",
            "subcategory":"Lawyer & Legal Services",
            "type":"Services"
        }
    ],
    "sg:phone":"+1 206 405 4520",
    "sg:postcode":"98104",
    "sg:province":"WA",
    "wof:name":"Berger Alex",
    "wof:placetype":"venue"
},
  "geometry": {"coordinates":[-122.32628699999999,47.599345],"type":"Point"}
}