{
  "type": "Feature",
  "properties": {
    "addr:full":"401 NE Northgate Way, Suite 880 Seattle WA 98125",
    "addr:housenumber":"401",
    "addr:postcode":"98125",
    "addr:street":"Ne Northgate Way Suite 880",
    "iso:country":"US",
    "sg:address":"401 NE Northgate Way, Suite 880",
    "sg:city":"Seattle",
    "sg:classifiers":[
        {
            "category":"Shopping",
            "subcategory":"Jewelry",
            "type":"Retail Goods"
        }
    ],
    "sg:phone":"+1 206 363 7227",
    "sg:postcode":"98125",
    "sg:province":"WA",
    "sg:website":"www.BenBridge.com",
    "wof:name":"Ben Bridge Jeweler",
    "wof:placetype":"venue"
},
  "geometry": {"coordinates":[-122.32397899999999,47.708597],"type":"Point"}
}