{
  "type": "Feature",
  "properties": {
    "addr:full":"10720 Pacific Ave S Tacoma WA 98444",
    "addr:housenumber":"10720",
    "addr:postcode":"98444",
    "addr:street":"Pacific Ave S",
    "iso:country":"US",
    "sg:address":"10720 Pacific Ave S",
    "sg:city":"Tacoma",
    "sg:classifiers":[
        {
            "category":"Travel",
            "subcategory":"Hotels & Motels",
            "type":"Entertainment"
        }
    ],
    "sg:phone":"+1 877 226 3539",
    "sg:postcode":"98444",
    "sg:province":"WA",
    "wof:name":"Sunnyside Hospitality",
    "wof:placetype":"venue"
},
  "geometry": {"coordinates":[-122.43423,47.159816],"type":"Point"}
}