{
  "type": "Feature",
  "properties": {
    "addr:full":"830 N Columbia Center Blvd Kennewick WA 99336",
    "addr:housenumber":"830",
    "addr:postcode":"99336",
    "addr:street":"N Columbia Center Blvd",
    "iso:country":"US",
    "sg:address":"830 N Columbia Center Blvd",
    "sg:city":"Kennewick",
    "sg:classifiers":[
        {
            "category":"Social Services",
            "type":"Services"
        }
    ],
    "sg:phone":"+1 509 374 5391",
    "sg:postcode":"99336",
    "sg:province":"WA",
    "sg:tags":[
        "crisis",
        "intervention"
    ],
    "wof:name":"Sexual Assault Response Center",
    "wof:placetype":"venue"
},
  "geometry": {"coordinates":[-119.22458899999999,46.216903],"type":"Point"}
}