{
  "type": "Feature",
  "properties": {
    "addr:full":"13300 SE 30th St Bellevue WA 98005",
    "addr:postcode":"13300;98005",
    "addr:street":"Se 30Th St",
    "iso:country":"US",
    "sg:address":"13300 SE 30th St",
    "sg:city":"Bellevue",
    "sg:classifiers":[
        {
            "category":"Building & Trades",
            "subcategory":"Electrical",
            "type":"Services"
        },
        {
            "category":"Retail",
            "subcategory":"Repair Shop",
            "type":"Services"
        }
    ],
    "sg:phone":"+1 425 653 4085",
    "sg:postcode":"98005",
    "sg:province":"WA",
    "sg:tags":[
        "electrical",
        "electric",
        "contractor"
    ],
    "wof:name":"Electro Serve LLC",
    "wof:placetype":"venue"
},
  "geometry": {"coordinates":[-122.164095,47.583844],"type":"Point"}
}