{
  "type": "Feature",
  "properties": {
    "addr:full":"1513 Pacific Ave N Long Beach WA 98631",
    "addr:housenumber":"1513",
    "addr:postcode":"98631",
    "addr:street":"Pacific Ave N",
    "iso:country":"US",
    "sg:address":"1513 Pacific Ave N",
    "sg:city":"Long Beach",
    "sg:classifiers":[
        {
            "category":"Restaurant",
            "type":"Food & Drink"
        }
    ],
    "sg:phone":"+1 360 642 1355",
    "sg:postcode":"98631",
    "sg:province":"WA",
    "wof:name":"Sunset Taco Express",
    "wof:placetype":"venue"
},
  "geometry": {"coordinates":[-124.05388499999999,46.3621],"type":"Point"}
}