{
  "type": "Feature",
  "properties": {
    "addr:full":"9224 Ridgetop Blvd NW Silverdale WA 98383",
    "addr:housenumber":"9224",
    "addr:postcode":"98383",
    "addr:street":"Ridgetop Blvd Nw",
    "iso:country":"US",
    "sg:address":"9224 Ridgetop Blvd NW",
    "sg:city":"Silverdale",
    "sg:classifiers":[
        {
            "category":"Professional",
            "subcategory":"Business Services",
            "type":"Services"
        }
    ],
    "sg:phone":"+1 360 698 6081",
    "sg:postcode":"98383",
    "sg:province":"WA",
    "sg:tags":[
        "organizing",
        "services-household"
    ],
    "wof:name":"Details Property Managment",
    "wof:placetype":"venue"
},
  "geometry": {"coordinates":[-122.685647,47.654081],"type":"Point"}
}