{
  "type": "Feature",
  "properties": {
    "addr:full":"29010 64th Ave NW Stanwood WA 98292",
    "addr:housenumber":"29010",
    "addr:postcode":"98292",
    "addr:street":"64Th Ave Nw",
    "iso:country":"US",
    "sg:address":"29010 64th Ave NW",
    "sg:city":"Stanwood",
    "sg:classifiers":[
        {
            "category":"Building & Trades",
            "subcategory":"Construction",
            "type":"Services"
        }
    ],
    "sg:phone":"+1 360 629 2861",
    "sg:postcode":"98292",
    "sg:province":"WA",
    "sg:tags":[
        "general",
        "contractor"
    ],
    "wof:name":"L L Construction",
    "wof:placetype":"venue"
},
  "geometry": {"coordinates":[-122.319255,48.26],"type":"Point"}
}