{
  "type": "Feature",
  "properties": {
    "addr:full":"8506 14th Ave S Seattle WA 98108",
    "addr:housenumber":"8506",
    "addr:postcode":"98108",
    "addr:street":"14Th Ave S",
    "iso:country":"US",
    "sg:address":"8506 14th Ave S",
    "sg:city":"Seattle",
    "sg:classifiers":[
        {
            "category":"Retail",
            "subcategory":"Laundry & Dry Cleaning",
            "type":"Services"
        }
    ],
    "sg:phone":"+1 206 768 9200",
    "sg:postcode":"98108",
    "sg:province":"WA",
    "sg:tags":[
        "drycleaning",
        "plant"
    ],
    "wof:name":"Regency 2 Cleaners",
    "wof:placetype":"venue"
},
  "geometry": {"coordinates":[-122.314814,47.528147],"type":"Point"}
}