{
  "type": "Feature",
  "properties": {
    "addr:full":"2501 S C St Tacoma WA 98402",
    "addr:housenumber":"2501",
    "addr:postcode":"98402",
    "addr:street":"S C St",
    "iso:country":"US",
    "sg:address":"2501 S C St",
    "sg:city":"Tacoma",
    "sg:classifiers":[
        {
            "category":"Building & Trades",
            "subcategory":"Electrical",
            "type":"Services"
        }
    ],
    "sg:phone":"+1 253 473 5636",
    "sg:postcode":"98402",
    "sg:province":"WA",
    "sg:tags":[
        "electrical"
    ],
    "wof:name":"Spirit Electric LLC",
    "wof:placetype":"venue"
},
  "geometry": {"coordinates":[-122.436425,47.237136],"type":"Point"}
}