{
  "type": "Feature",
  "properties": {
    "addr:full":"1815 E D St Tacoma WA 98421",
    "addr:housenumber":"1815",
    "addr:postcode":"98421",
    "addr:street":"E D St",
    "iso:country":"US",
    "sg:address":"1815 E D St",
    "sg:city":"Tacoma",
    "sg:classifiers":[
        {
            "category":"Building & Trades",
            "subcategory":"Construction",
            "type":"Services"
        }
    ],
    "sg:phone":"+1 206 583 0172",
    "sg:postcode":"98421",
    "sg:province":"WA",
    "sg:tags":[
        "mfg",
        "kitchen",
        "cabinet",
        "wood",
        "contractor",
        "carpentry"
    ],
    "sg:website":"www.tacomafixture.com",
    "wof:name":"Tacoma Cabinet & Fixture Co",
    "wof:placetype":"venue"
},
  "geometry": {"coordinates":[-122.430448,47.245738],"type":"Point"}
}