{
  "type": "Feature",
  "properties": {
    "addr:full":"3804 N Regal St Spokane WA 99207",
    "addr:housenumber":"3804",
    "addr:postcode":"99207",
    "addr:street":"N Regal St",
    "iso:country":"US",
    "sg:address":"3804 N Regal St",
    "sg:city":"Spokane",
    "sg:classifiers":[
        {
            "category":"Building & Trades",
            "subcategory":"Construction",
            "type":"Services"
        }
    ],
    "sg:phone":"+1 509 483 2222",
    "sg:postcode":"99207",
    "sg:province":"WA",
    "sg:tags":[
        "installation",
        "terrazzo",
        "floor",
        "ceramic",
        "contract",
        "tile"
    ],
    "wof:name":"Associated Terrazzo & Ceramics",
    "wof:placetype":"venue"
},
  "geometry": {"coordinates":[-117.367992,47.69346],"type":"Point"}
}