{
  "type": "Feature",
  "properties": {
    "addr:full":"23803 29th Ave W Brier WA 98036",
    "addr:housenumber":"23803",
    "addr:postcode":"98036",
    "addr:street":"29Th Ave W Brier",
    "iso:country":"US",
    "sg:address":"23803 29th Ave W",
    "sg:city":"Brier",
    "sg:classifiers":[
        {
            "category":"Manufacturing",
            "subcategory":"Printing",
            "type":"Manufacturing & Wholesale Goods"
        }
    ],
    "sg:phone":"+1 425 488 9155",
    "sg:postcode":"98036",
    "sg:province":"WA",
    "sg:tags":[
        "printer"
    ],
    "wof:name":"Print Masters",
    "wof:placetype":"venue"
},
  "geometry": {"coordinates":[-122.27188700000001,47.781179],"type":"Point"}
}