{
  "type": "Feature",
  "properties": {
    "addr:full":"1950 130th Ave NE Bellevue WA 98005",
    "addr:housenumber":"1950",
    "addr:postcode":"98005",
    "addr:street":"130Th Ave Ne",
    "iso:country":"US",
    "sg:address":"1950 130th Ave NE",
    "sg:city":"Bellevue",
    "sg:classifiers":[
        {
            "category":"Arena",
            "subcategory":"Sports Club",
            "type":"Entertainment"
        }
    ],
    "sg:phone":"+1 425 881 1550",
    "sg:postcode":"98005",
    "sg:province":"WA",
    "sg:tags":[
        "martial art"
    ],
    "wof:name":"A K M A Washington Llc",
    "wof:placetype":"venue"
},
  "geometry": {"coordinates":[-122.166894,47.627669],"type":"Point"}
}