{
  "type": "Feature",
  "properties": {
    "addr:full":"7420 Ford Dr NW Gig Harbor WA 98335",
    "addr:housenumber":"7420",
    "addr:postcode":"98335",
    "addr:street":"Ford Dr Nw",
    "iso:country":"US",
    "sg:address":"7420 Ford Dr NW",
    "sg:city":"Gig Harbor",
    "sg:classifiers":[
        {
            "category":"Shopping",
            "subcategory":"Clothing, Apparel, & Fashions",
            "type":"Retail Goods"
        }
    ],
    "sg:phone":"+1 253 858 7800",
    "sg:postcode":"98335",
    "sg:province":"WA",
    "wof:name":"A Little Accent",
    "wof:placetype":"venue"
},
  "geometry": {"coordinates":[-122.640255,47.279954],"type":"Point"}
}