{
  "type": "Feature",
  "properties": {
    "addr:full":"31711 Pacific Hwy S Federal Way WA 98003",
    "addr:housenumber":"31711",
    "addr:postcode":"98003",
    "addr:street":"Pacific Hwy S Federal Way",
    "iso:country":"US",
    "sg:address":"31711 Pacific Hwy S",
    "sg:city":"Federal Way",
    "sg:classifiers":[
        {
            "category":"Restaurant",
            "type":"Food & Drink"
        }
    ],
    "sg:menulink":"http://www.allmenus.com/wa/auburn/109463-village-inn/menu/",
    "sg:phone":"+1 253 941 9860",
    "sg:postcode":"98003",
    "sg:province":"WA",
    "sg:tags":[
        "new",
        "american"
    ],
    "wof:name":"Village Inn",
    "wof:placetype":"venue"
},
  "geometry": {"coordinates":[-122.313479,47.317756],"type":"Point"}
}