{
  "type": "Feature",
  "properties": {
    "addr:full":"4807 50th Ave S Seattle WA 98118",
    "addr:housenumber":"4807",
    "addr:postcode":"98118",
    "addr:street":"50Th Ave S",
    "iso:country":"US",
    "sg:address":"4807 50th Ave S",
    "sg:city":"Seattle",
    "sg:classifiers":[
        {
            "category":"Government",
            "subcategory":"Office",
            "type":"Public Place"
        }
    ],
    "sg:phone":"+1 206 722 9263",
    "sg:postcode":"98118",
    "sg:province":"WA",
    "sg:tags":[
        "executive"
    ],
    "wof:name":"Water Works",
    "wof:placetype":"venue"
},
  "geometry": {"coordinates":[-122.270762,47.558309],"type":"Point"}
}