{
  "type": "Feature",
  "properties": {
    "addr:full":"2612 E Sanson Ave Spokane WA 99217",
    "addr:housenumber":"2612",
    "addr:postcode":"99217",
    "addr:street":"E Sanson Ave",
    "iso:country":"US",
    "sg:address":"2612 E Sanson Ave",
    "sg:city":"Spokane",
    "sg:classifiers":[
        {
            "category":"Professional",
            "subcategory":"Computer Services",
            "type":"Services"
        }
    ],
    "sg:phone":"+1 509 487 6548",
    "sg:postcode":"99217",
    "sg:province":"WA",
    "sg:tags":[
        "consultant",
        "designer",
        "system",
        "related"
    ],
    "wof:name":"Now Services",
    "wof:placetype":"venue"
},
  "geometry": {"coordinates":[-117.371887,47.706817],"type":"Point"}
}