{
  "type": "Feature",
  "properties": {
    "addr:full":"20225 20th Ave NW Seattle WA 98177",
    "addr:housenumber":"20225",
    "addr:postcode":"98177",
    "addr:street":"20Th Ave Nw",
    "iso:country":"US",
    "sg:address":"20225 20th Ave NW",
    "sg:city":"Seattle",
    "sg:classifiers":[
        {
            "category":"Personal",
            "subcategory":"Beauty Salon",
            "type":"Services"
        }
    ],
    "sg:phone":"+1 206 546 5773",
    "sg:postcode":"98177",
    "sg:province":"WA",
    "sg:tags":[
        "shop"
    ],
    "wof:name":"Trintiy Salon Spa & Boutique",
    "wof:placetype":"venue"
},
  "geometry": {"coordinates":[-122.382921,47.776859],"type":"Point"}
}