{
  "type": "Feature",
  "properties": {
    "addr:full":"505 Basin St SW Ephrata WA 98823",
    "addr:housenumber":"505",
    "addr:postcode":"98823",
    "addr:street":"Basin St Sw",
    "iso:country":"US",
    "sg:address":"505 Basin St SW",
    "sg:city":"Ephrata",
    "sg:classifiers":[
        {
            "category":"Retail",
            "subcategory":"Auto Repair",
            "type":"Services"
        }
    ],
    "sg:phone":"+1 509 754 3677",
    "sg:postcode":"98823",
    "sg:province":"WA",
    "sg:tags":[
        "repairing",
        "automobile"
    ],
    "wof:name":"Denny's Pit Stop",
    "wof:placetype":"venue"
},
  "geometry": {"coordinates":[-119.55534900000001,47.315621],"type":"Point"}
}