{
  "type": "Feature",
  "properties": {
    "iso:country":"US",
    "sg:address":"22419 NE 30th Ct",
    "sg:city":"Sammamish",
    "sg:classifiers":[
        {
            "category":"Professional",
            "subcategory":"Management & Consulting",
            "type":"Services"
        }
    ],
    "sg:phone":"+1 425 836 8479",
    "sg:postcode":"98074",
    "sg:province":"WA",
    "sg:tags":[
        "business"
    ],
    "wof:name":"Wenzinger Consulting",
    "wof:placetype":"venue"
},
  "geometry": {"coordinates":[-122.040099,47.636044],"type":"Point"}
}