{
  "type": "Feature",
  "properties": {
    "addr:full":"22203 State Hwy 203 Monroe WA 98272",
    "addr:housenumber":"22203",
    "addr:postcode":"98272",
    "addr:street":"State Hwy 203",
    "iso:country":"US",
    "sg:address":"22203 State Hwy 203",
    "sg:city":"Monroe",
    "sg:classifiers":[
        {
            "category":"Organizations",
            "subcategory":"Professional Association",
            "type":"Services"
        }
    ],
    "sg:phone":"+1 360 794 4469",
    "sg:postcode":"98272",
    "sg:province":"WA",
    "sg:tags":[
        "business"
    ],
    "wof:name":"Log Home Builders Assoc",
    "wof:placetype":"venue"
},
  "geometry": {"coordinates":[-121.97789400000001,47.798225],"type":"Point"}
}