{
  "type": "Feature",
  "properties": {
    "addr:full":"7476 Valley View Rd Ferndale WA 98248",
    "addr:housenumber":"7476",
    "addr:postcode":"98248",
    "addr:street":"Valley View Rd",
    "iso:country":"US",
    "sg:address":"7476 Valley View Rd",
    "sg:city":"Ferndale",
    "sg:classifiers":[
        {
            "category":"Professional",
            "subcategory":"Printing & Photocopies",
            "type":"Services"
        }
    ],
    "sg:phone":"+1 360 366 3410",
    "sg:postcode":"98248",
    "sg:province":"WA",
    "sg:tags":[
        "engraving"
    ],
    "wof:name":"Tlc Custom Engraving",
    "wof:placetype":"venue"
},
  "geometry": {"coordinates":[-122.660388,48.912779],"type":"Point"}
}