{
  "type": "Feature",
  "properties": {
    "iso:country":"US",
    "sg:address":"18814 72nd Ave S",
    "sg:city":"Kent",
    "sg:classifiers":[
        {
            "category":"Wholesale",
            "subcategory":"Auto Parts",
            "type":"Manufacturing & Wholesale Goods"
        }
    ],
    "sg:phone":"+1 425 251 9092",
    "sg:postcode":"98032",
    "sg:province":"WA",
    "sg:tags":[
        "mfg",
        "motor",
        "vehicle"
    ],
    "wof:name":"Instrument Sales and Service",
    "wof:placetype":"venue"
},
  "geometry": {"coordinates":[-122.24394599999999,47.433432],"type":"Point"}
}