{
  "type": "Feature",
  "properties": {
    "addr:full":"400 Warren Ave Suite 412 Bremerton WA 98337",
    "addr:housenumber":"400",
    "addr:postcode":"98337",
    "addr:street":"Warren Ave Suite 412",
    "iso:country":"US",
    "sg:address":"400 Warren Ave Suite 412",
    "sg:city":"Bremerton",
    "sg:classifiers":[
        {
            "category":"Professional",
            "subcategory":"Accounting & Tax Preparation",
            "type":"Services"
        }
    ],
    "sg:phone":"+1 360 479 8846",
    "sg:postcode":"98337",
    "sg:province":"WA",
    "sg:tags":[
        "public",
        "representative",
        "accountants-certified",
        "taxes-consultants"
    ],
    "sg:website":"http://www.frycpa.com",
    "wof:name":"Darrell W Fry CPA Inc PS",
    "wof:placetype":"venue"
},
  "geometry": {"coordinates":[-122.632927,47.565781],"type":"Point"}
}