{
  "type": "Feature",
  "properties": {
    "addr:full":"1420 5th Ave Seattle WA 98101",
    "addr:housenumber":"1420",
    "addr:postcode":"98101",
    "addr:street":"5Th Ave",
    "iso:country":"US",
    "sg:address":"1420 5th Ave",
    "sg:city":"Seattle",
    "sg:classifiers":[
        {
            "category":"Restaurant",
            "type":"Food & Drink"
        }
    ],
    "sg:menulink":"http://www.allmenus.com/wa/seattle/3519-palomino/menu/",
    "sg:phone":"+1 206 623 1300",
    "sg:postcode":"98101",
    "sg:province":"WA",
    "sg:tags":[
        "american"
    ],
    "wof:name":"Palomino",
    "wof:placetype":"venue"
},
  "geometry": {"coordinates":[-122.33475799999999,47.610005],"type":"Point"}
}