{
  "type": "Feature",
  "properties": {
    "addr:full":"3707 College St SE Lacey WA 98503",
    "addr:housenumber":"3707",
    "addr:postcode":"98503",
    "addr:street":"College St Se",
    "iso:country":"US",
    "sg:address":"3707 College St SE",
    "sg:city":"Lacey",
    "sg:classifiers":[
        {
            "category":"Restaurant",
            "type":"Food & Drink"
        }
    ],
    "sg:phone":"+1 360 438 3787",
    "sg:postcode":"98503",
    "sg:province":"WA",
    "sg:tags":[
        "eating"
    ],
    "wof:name":"Kings Pizza & Sub Shop",
    "wof:placetype":"venue"
},
  "geometry": {"coordinates":[-122.82316299999999,47.010973],"type":"Point"}
}