{
  "type": "Feature",
  "properties": {
    "addr:full":"1101 4th Ave Seattle WA 98101",
    "addr:housenumber":"1101",
    "addr:postcode":"98101",
    "addr:street":"4Th Ave",
    "iso:country":"US",
    "sg:address":"1101 4th Ave",
    "sg:city":"Seattle",
    "sg:classifiers":[
        {
            "category":"Restaurant",
            "type":"Food & Drink"
        }
    ],
    "sg:menulink":"http://www.allmenus.com/wa/seattle/3537-sazerac-restautrant/menu/",
    "sg:phone":"+1 206 624 7755",
    "sg:postcode":"98101",
    "sg:province":"WA",
    "sg:tags":[
        "american",
        "southern"
    ],
    "wof:name":"Sazerac Restautrant",
    "wof:placetype":"venue"
},
  "geometry": {"coordinates":[-122.333484,47.606839],"type":"Point"}
}