{
  "type": "Feature",
  "properties": {
    "addr:full":"508 N Main St Ellensburg WA 98926",
    "addr:housenumber":"508",
    "addr:postcode":"98926",
    "addr:street":"N Main St",
    "iso:country":"US",
    "sg:address":"508 N Main St",
    "sg:city":"Ellensburg",
    "sg:classifiers":[
        {
            "category":"Real Estate",
            "subcategory":"Real Estate Services",
            "type":"Services"
        },
        {
            "category":"Real Estate",
            "subcategory":"Real Estate Agent",
            "type":"Services"
        }
    ],
    "sg:phone":"+1 509 925 8939",
    "sg:postcode":"98926",
    "sg:province":"WA",
    "sg:tags":[
        "management"
    ],
    "wof:name":"Jerry E Anderson Real Estate",
    "wof:placetype":"venue"
},
  "geometry": {"coordinates":[-120.54870200000001,46.996606],"type":"Point"}
}