{
  "type": "Feature",
  "properties": {
    "addr:full":"212 W Railroad Ave Kennewick WA 99336",
    "addr:housenumber":"212",
    "addr:postcode":"99336",
    "addr:street":"W Railroad Ave",
    "iso:country":"US",
    "sg:address":"212 W Railroad Ave",
    "sg:city":"Kennewick",
    "sg:classifiers":[
        {
            "category":"Wholesale",
            "subcategory":"Fruits & Vegetables",
            "type":"Manufacturing & Wholesale Goods"
        }
    ],
    "sg:phone":"+1 509 586 6174",
    "sg:postcode":"99336",
    "sg:province":"WA",
    "sg:website":"www.bakerproduce.com",
    "wof:name":"Baker Produce",
    "wof:placetype":"venue"
},
  "geometry": {"coordinates":[-119.12207100000001,46.211733],"type":"Point"}
}