{
  "type": "Feature",
  "properties": {
    "addr:full":"4002 287th Ave SE Fall City WA 98024",
    "addr:housenumber":"4002",
    "addr:postcode":"98024",
    "addr:street":"287Th Ave Se",
    "iso:country":"US",
    "sg:address":"4002 287th Ave SE",
    "sg:city":"Fall City",
    "sg:classifiers":[
        {
            "category":"Home & Garden",
            "subcategory":"Garden Supply",
            "type":"Retail Goods"
        }
    ],
    "sg:phone":"+1 425 392 0201",
    "sg:postcode":"98024",
    "sg:province":"WA",
    "sg:tags":[
        "gallery"
    ],
    "wof:name":"Namm Fountains",
    "wof:placetype":"venue"
},
  "geometry": {"coordinates":[-121.958631,47.572653],"type":"Point"}
}