{
  "type": "Feature",
  "properties": {
    "addr:full":"35861 N US Hwy 101 Lilliwaup WA 98555",
    "addr:housenumber":"35861",
    "addr:postcode":"98555",
    "addr:street":"N Us Hwy 101 Lilliwaup",
    "iso:country":"US",
    "sg:address":"35861 N US Hwy 101",
    "sg:city":"Lilliwaup",
    "sg:classifiers":[
        {
            "category":"Farming",
            "subcategory":"Fish & Marine Products",
            "type":"Manufacturing & Wholesale Goods"
        }
    ],
    "sg:phone":"+1 360 877 5811",
    "sg:postcode":"98555",
    "sg:province":"WA",
    "sg:tags":[
        "oyster"
    ],
    "wof:name":"Hama Hama Co Store",
    "wof:placetype":"venue"
},
  "geometry": {"coordinates":[-123.046205,47.532265],"type":"Point"}
}