{
  "type": "Feature",
  "properties": {
    "addr:full":"1500 4th Avenue Seattle WA 98101",
    "addr:housenumber":"1500",
    "addr:postcode":"98101",
    "addr:street":"4Th Avenue",
    "iso:country":"US",
    "sg:address":"1500 4th Avenue",
    "sg:city":"Seattle",
    "sg:classifiers":[
        {
            "category":"Real Estate",
            "subcategory":"Architect",
            "type":"Services"
        }
    ],
    "sg:phone":"+1 206 467 0613",
    "sg:postcode":"98101",
    "sg:province":"WA",
    "wof:name":"Pacific Architects PS Aia",
    "wof:placetype":"venue"
},
  "geometry": {"coordinates":[-122.336675,47.610267],"type":"Point"}
}