{
  "type": "Feature",
  "properties": {
    "addr:full":"112 10th Ave E Seattle WA 98102",
    "addr:housenumber":"112",
    "addr:postcode":"98102",
    "addr:street":"10Th Ave E",
    "iso:country":"US",
    "sg:address":"112 10th Ave E",
    "sg:city":"Seattle",
    "sg:classifiers":[
        {
            "category":"Social Services",
            "subcategory":"Child Care",
            "type":"Services"
        }
    ],
    "sg:phone":"+1 206 328 6103",
    "sg:postcode":"98102",
    "sg:province":"WA",
    "wof:name":"Building Blocks Children's Ctr",
    "wof:placetype":"venue"
},
  "geometry": {"coordinates":[-122.319464,47.619773],"type":"Point"}
}