{
  "type": "Feature",
  "properties": {
    "addr:full":"1300 W 12th St Vancouver WA 98660",
    "addr:housenumber":"1300",
    "addr:postcode":"98660",
    "addr:street":"W 12Th St",
    "iso:country":"US",
    "sg:address":"1300 W 12th St",
    "sg:city":"Vancouver",
    "sg:classifiers":[
        {
            "category":"Building & Trades",
            "subcategory":"Cleaning & Sanitation",
            "type":"Services"
        }
    ],
    "sg:phone":"+1 866 965 9768",
    "sg:postcode":"98660",
    "sg:province":"WA",
    "sg:tags":[
        "contractor"
    ],
    "sg:website":"http://www.emeraldnw.com",
    "wof:name":"Emerald Services Inc",
    "wof:placetype":"venue"
},
  "geometry": {"coordinates":[-122.683271,45.630407],"type":"Point"}
}