{
  "type": "Feature",
  "properties": {
    "addr:full":"502 E Haskel Hill Rd Shelton WA 98584",
    "addr:housenumber":"502",
    "addr:postcode":"98584",
    "addr:street":"E Haskel Hill Rd",
    "iso:country":"US",
    "sg:address":"502 E Haskel Hill Rd",
    "sg:city":"Shelton",
    "sg:classifiers":[
        {
            "category":"Home & Garden",
            "subcategory":"Garden Supply",
            "type":"Retail Goods"
        }
    ],
    "sg:phone":"+1 360 427 5318",
    "sg:postcode":"98584",
    "sg:province":"WA",
    "sg:tags":[
        "bamboo",
        "product"
    ],
    "wof:name":"Heaths & Heathers",
    "wof:placetype":"venue"
},
  "geometry": {"coordinates":[-122.895973,47.279694],"type":"Point"}
}