{
  "type": "Feature",
  "properties": {
    "addr:full":"10300 Des Moines Memorial Dr Seattle WA 98168",
    "addr:housenumber":"10300",
    "addr:postcode":"98168",
    "addr:street":"Des Moines Memorial Dr",
    "iso:country":"US",
    "sg:address":"10300 Des Moines Memorial Dr",
    "sg:city":"Seattle",
    "sg:classifiers":[
        {
            "category":"Real Estate",
            "subcategory":"Real Estate Operator",
            "type":"Services"
        }
    ],
    "sg:phone":"+1 206 762 3396",
    "sg:postcode":"98168",
    "sg:province":"WA",
    "sg:tags":[
        "apartment"
    ],
    "wof:name":"Riverside West Apartments",
    "wof:placetype":"venue"
},
  "geometry": {"coordinates":[-122.306602,47.5113],"type":"Point"}
}