{
  "type": "Feature",
  "properties": {
    "iso:country":"US",
    "sg:address":"465 SE Bush St",
    "sg:city":"Issaquah",
    "sg:classifiers":[
        {
            "category":"Professional",
            "subcategory":"Computer Services",
            "type":"Services"
        }
    ],
    "sg:phone":"+1 425 391 0391",
    "sg:postcode":"98027",
    "sg:province":"WA",
    "sg:tags":[
        "related"
    ],
    "wof:name":"Cintras Inc",
    "wof:placetype":"venue"
},
  "geometry": {"coordinates":[-122.029505,47.528179],"type":"Point"}
}