{
  "type": "Feature",
  "properties": {
    "addr:full":"735 Front St Leavenworth WA 98826",
    "addr:housenumber":"735",
    "addr:postcode":"98826",
    "addr:street":"Front St",
    "iso:country":"US",
    "sg:address":"735 Front St",
    "sg:city":"Leavenworth",
    "sg:classifiers":[
        {
            "category":"Shopping",
            "subcategory":"Gifts & Souvenirs",
            "type":"Retail Goods"
        }
    ],
    "sg:phone":"+1 509 548 4708",
    "sg:postcode":"98826",
    "sg:province":"WA",
    "sg:tags":[
        "shop"
    ],
    "sg:website":"http://www.nussknackerhaus.com",
    "wof:name":"Nussknacker Haus",
    "wof:placetype":"venue"
},
  "geometry": {"coordinates":[-120.663501,47.594691],"type":"Point"}
}