{
  "type": "Feature",
  "properties": {
    "addr:full":"796 Columbia St Pomeroy WA 99347",
    "addr:housenumber":"796",
    "addr:postcode":"99347",
    "addr:street":"Columbia St",
    "iso:country":"US",
    "sg:address":"796 Columbia St",
    "sg:city":"Pomeroy",
    "sg:classifiers":[
        {
            "category":"Organizations",
            "subcategory":"Religious Organization",
            "type":"Services"
        }
    ],
    "sg:phone":"+1 509 843 3821",
    "sg:postcode":"99347",
    "sg:province":"WA",
    "sg:tags":[
        "church"
    ],
    "wof:name":"Methodist Church United",
    "wof:placetype":"venue"
},
  "geometry": {"coordinates":[-117.6003,46.473449],"type":"Point"}
}