{
  "type": "Feature",
  "properties": {
    "addr:full":"837 Jameson St Sedro Woolley WA 98284",
    "addr:housenumber":"837",
    "addr:postcode":"98284",
    "addr:street":"Jameson St",
    "iso:country":"US",
    "sg:address":"837 Jameson St",
    "sg:city":"Sedro Woolley",
    "sg:classifiers":[
        {
            "category":"Shopping",
            "subcategory":"Catalog Store",
            "type":"Retail Goods"
        }
    ],
    "sg:phone":"+1 360 855 1549",
    "sg:postcode":"98284",
    "sg:province":"WA",
    "sg:tags":[
        "order"
    ],
    "wof:name":"Beckys Gifts Collectibles Etc",
    "wof:placetype":"venue"
},
  "geometry": {"coordinates":[-122.22654199999999,48.498766],"type":"Point"}
}