{
  "type": "Feature",
  "properties": {
    "addr:full":"410 Broadway Seattle WA 98122",
    "addr:housenumber":"410",
    "addr:postcode":"98122",
    "addr:street":"Broadway",
    "iso:country":"US",
    "sg:address":"410 Broadway",
    "sg:city":"Seattle",
    "sg:classifiers":[
        {
            "category":"Building & Trades",
            "subcategory":"Locksmith",
            "type":"Services"
        }
    ],
    "sg:phone":"+1 206 552 7173",
    "sg:postcode":"98122",
    "sg:province":"WA",
    "sg:tags":[
        "key"
    ],
    "wof:name":"One Emergency Locksmith",
    "wof:placetype":"venue"
},
  "geometry": {"coordinates":[-122.320537,47.605259],"type":"Point"}
}