{
  "type": "Feature",
  "properties": {
    "addr:full":"118 N Lewis St Monroe WA 98272",
    "addr:housenumber":"118",
    "addr:postcode":"98272",
    "addr:street":"N Lewis St",
    "iso:country":"US",
    "sg:address":"118 N Lewis St",
    "sg:city":"Monroe",
    "sg:classifiers":[
        {
            "category":"Health Services",
            "subcategory":"Health Practitioner",
            "type":"Services"
        }
    ],
    "sg:phone":"+1 360 794 8183",
    "sg:postcode":"98272",
    "sg:province":"WA",
    "wof:name":"Olympic Ntrpathic Wellness Ctr",
    "wof:placetype":"venue"
},
  "geometry": {"coordinates":[-121.970838,47.856083],"type":"Point"}
}