{
  "type": "Feature",
  "properties": {
    "addr:full":"20415 Bothell Everett Hwy Bothell WA 98012",
    "addr:housenumber":"20415",
    "addr:postcode":"98012",
    "addr:street":"Bothell Everett Hwy",
    "iso:country":"US",
    "sg:address":"20415 Bothell Everett Hwy",
    "sg:city":"Bothell",
    "sg:classifiers":[
        {
            "category":"Professional",
            "subcategory":"Computer Services",
            "type":"Services"
        }
    ],
    "sg:phone":"+1 425 486 1622",
    "sg:postcode":"98012",
    "sg:province":"WA",
    "sg:tags":[
        "prepackaged",
        "software"
    ],
    "wof:name":"Eternity Software",
    "wof:placetype":"venue"
},
  "geometry": {"coordinates":[-122.207533,47.811926],"type":"Point"}
}