{
  "type": "Feature",
  "properties": {
    "addr:full":"10804 NE Hwy 99 Vancouver WA 98686",
    "addr:housenumber":"10804",
    "addr:postcode":"98686",
    "addr:street":"Ne Hwy 99",
    "iso:country":"US",
    "sg:address":"10804 NE Hwy 99",
    "sg:city":"Vancouver",
    "sg:classifiers":[
        {
            "category":"Building & Trades",
            "subcategory":"Landscaping Services",
            "type":"Services"
        }
    ],
    "sg:phone":"+1 360 735 5835",
    "sg:postcode":"98686",
    "sg:province":"WA",
    "sg:tags":[
        "landscape",
        "contractor"
    ],
    "wof:name":"Fresh Expression Landscaping",
    "wof:placetype":"venue"
},
  "geometry": {"coordinates":[-122.65244800000001,45.700731],"type":"Point"}
}