{
  "type": "Feature",
  "properties": {
    "addr:full":"101 Nickerson St Ste 340 Seattle WA 98109",
    "addr:housenumber":"101",
    "addr:postcode":"98109",
    "addr:street":"Nickerson St Ste 340",
    "iso:country":"US",
    "sg:address":"101 Nickerson St Ste 340",
    "sg:city":"Seattle",
    "sg:classifiers":[
        {
            "category":"Farming",
            "subcategory":"Fish & Marine Products",
            "type":"Manufacturing & Wholesale Goods"
        },
        {
            "category":"Recreation",
            "subcategory":"Fishing",
            "type":"Entertainment"
        }
    ],
    "sg:phone":"+1 206 282 6996",
    "sg:postcode":"98109",
    "sg:province":"WA",
    "sg:tags":[
        "pond",
        "pier",
        "lake"
    ],
    "wof:name":"Harvester Enterprises",
    "wof:placetype":"venue"
},
  "geometry": {"coordinates":[-122.35449199999999,47.6483],"type":"Point"}
}