{
  "type": "Feature",
  "properties": {
    "addr:full":"4701 SW Admiral Way Ste 1 Seattle WA 98116",
    "addr:housenumber":"4701",
    "addr:postcode":"98116",
    "addr:street":"Sw Admiral Way Ste 1",
    "iso:country":"US",
    "sg:address":"4701 SW Admiral Way Ste 1",
    "sg:city":"Seattle",
    "sg:classifiers":[
        {
            "category":"Utilities",
            "subcategory":"Electric",
            "type":"Services"
        },
        {
            "category":"Manufacturing",
            "subcategory":"Electronics",
            "type":"Manufacturing & Wholesale Goods"
        }
    ],
    "sg:phone":"+1 206 203 3135",
    "sg:postcode":"98116",
    "sg:province":"WA",
    "sg:tags":[
        "equipment-testing"
    ],
    "wof:name":"Prodigy Power",
    "wof:placetype":"venue"
},
  "geometry": {"coordinates":[-122.391899,47.58115],"type":"Point"}
}