{
  "type": "Feature",
  "properties": {
    "iso:country":"US",
    "sg:address":"202809 E 10th Ave",
    "sg:city":"Kennewick",
    "sg:classifiers":[
        {
            "category":"Communications",
            "type":"Services"
        }
    ],
    "sg:phone":"+1 509 585 2606",
    "sg:postcode":"99337",
    "sg:province":"WA",
    "sg:tags":[
        "communication"
    ],
    "wof:name":"Dailey Communications",
    "wof:placetype":"venue"
},
  "geometry": {"coordinates":[-119.075433,46.19804],"type":"Point"}
}