{
  "type": "Feature",
  "properties": {
    "addr:full":"118 W 3rd St Wapato WA 98951",
    "addr:housenumber":"118",
    "addr:postcode":"98951",
    "addr:street":"W 3Rd St",
    "iso:country":"US",
    "sg:address":"118 W 3rd St",
    "sg:city":"Wapato",
    "sg:phone":"+1 509 877 6380",
    "sg:postcode":"98951",
    "sg:province":"WA",
    "wof:name":"Bennett's Lower Valley Collision Center, Inc",
    "wof:placetype":"venue"
},
  "geometry": {"coordinates":[-120.42012099999999,46.446018],"type":"Point"}
}