{
  "type": "Feature",
  "properties": {
    "addr:full":"23513 NE 229th St Battle Ground WA 98604",
    "addr:housenumber":"23513",
    "addr:postcode":"98604",
    "addr:street":"Ne 229Th St",
    "iso:country":"US",
    "sg:address":"23513 NE 229th St",
    "sg:city":"Battle Ground",
    "sg:classifiers":[
        {
            "category":"Home & Garden",
            "subcategory":"Home Furnishings",
            "type":"Retail Goods"
        }
    ],
    "sg:phone":"+1 360 687 9393",
    "sg:postcode":"98604",
    "sg:province":"WA",
    "sg:tags":[
        "quilting"
    ],
    "wof:name":"Quilted Memories",
    "wof:placetype":"venue"
},
  "geometry": {"coordinates":[-122.43192000000001,45.788185],"type":"Point"}
}