{
  "type": "Feature",
  "properties": {
    "addr:full":"8903 W Gage Blvd Kennewick WA 99336",
    "addr:housenumber":"8903",
    "addr:postcode":"99336",
    "addr:street":"W Gage Blvd",
    "iso:country":"US",
    "sg:address":"8903 W Gage Blvd",
    "sg:city":"Kennewick",
    "sg:classifiers":[
        {
            "category":"Restaurant",
            "type":"Food & Drink"
        }
    ],
    "sg:menulink":"http://www.allmenus.com/wa/richland-kennewick/80522-papa-johns-pizza/menu/",
    "sg:phone":"+1 509 736 1500",
    "sg:postcode":"99336",
    "sg:province":"WA",
    "sg:tags":[
        "american",
        "pizza"
    ],
    "wof:name":"Papa John's Pizza",
    "wof:placetype":"venue"
},
  "geometry": {"coordinates":[-119.24029,46.227208],"type":"Point"}
}