{
  "type": "Feature",
  "properties": {
    "addr:full":"2824 Grand Ave Everett WA 98201",
    "addr:housenumber":"2824",
    "addr:postcode":"98201",
    "addr:street":"Grand Ave",
    "iso:country":"US",
    "sg:address":"2824 Grand Ave",
    "sg:city":"Everett",
    "sg:classifiers":[
        {
            "category":"Real Estate",
            "subcategory":"Real Estate Operator",
            "type":"Services"
        }
    ],
    "sg:phone":"+1 425 339 1331",
    "sg:postcode":"98201",
    "sg:province":"WA",
    "sg:tags":[
        "building",
        "apartment"
    ],
    "wof:name":"Nautica Apartments",
    "wof:placetype":"venue"
},
  "geometry": {"coordinates":[-122.212957,47.98026],"type":"Point"}
}