{
  "type": "Feature",
  "properties": {
    "iso:country":"US",
    "sg:address":"5535 Lake Washington Blvd NE",
    "sg:city":"Kirkland",
    "sg:classifiers":[
        {
            "category":"Government",
            "subcategory":"Office",
            "type":"Public Place"
        }
    ],
    "sg:phone":"+1 425 828 6013",
    "sg:postcode":"98033",
    "sg:province":"WA",
    "sg:tags":[
        "development"
    ],
    "wof:name":"Womens Enterprises Intl",
    "wof:placetype":"venue"
},
  "geometry": {"coordinates":[-122.20596999999999,47.658112],"type":"Point"}
}