{
  "type": "Feature",
  "properties": {
    "addr:full":"208 James St Seattle WA 98104",
    "addr:housenumber":"208",
    "addr:postcode":"98104",
    "addr:street":"James St",
    "iso:country":"US",
    "sg:address":"208 James St",
    "sg:city":"Seattle",
    "sg:classifiers":[
        {
            "category":"Shopping",
            "subcategory":"Stationery & Office Supplies",
            "type":"Retail Goods"
        }
    ],
    "sg:phone":"+1 206 628 3787",
    "sg:postcode":"98104",
    "sg:province":"WA",
    "sg:tags":[
        "carrier",
        "surety",
        "insurance"
    ],
    "wof:name":"V Spino Bonding",
    "wof:placetype":"venue"
},
  "geometry": {"coordinates":[-122.331512,47.602632],"type":"Point"}
}