{
  "type": "Feature",
  "properties": {
    "addr:full":"217 S Barr Rd Port Angeles WA 98362",
    "addr:housenumber":"217",
    "addr:postcode":"98362",
    "addr:street":"S Barr Rd",
    "iso:country":"US",
    "sg:address":"217 S Barr Rd",
    "sg:city":"Port Angeles",
    "sg:classifiers":[
        {
            "category":"Manufacturing",
            "subcategory":"Toys & Sporting Goods",
            "type":"Manufacturing & Wholesale Goods"
        }
    ],
    "sg:phone":"+1 360 452 8858",
    "sg:postcode":"98362",
    "sg:province":"WA",
    "sg:tags":[
        "mfg"
    ],
    "wof:name":"Boynton Bodies",
    "wof:placetype":"venue"
},
  "geometry": {"coordinates":[-123.237891,48.087502],"type":"Point"}
}