{
  "type": "Feature",
  "properties": {
    "addr:full":"511 N 103rd St Seattle WA 98133",
    "addr:housenumber":"511",
    "addr:postcode":"98133",
    "addr:street":"N 103Rd St",
    "iso:country":"US",
    "sg:address":"511 N 103rd St",
    "sg:city":"Seattle",
    "sg:classifiers":[
        {
            "category":"Restaurant",
            "type":"Food & Drink"
        }
    ],
    "sg:phone":"+1 206 781 8736",
    "sg:postcode":"98133",
    "sg:province":"WA",
    "sg:tags":[
        "asian",
        "chinese",
        "pan"
    ],
    "wof:name":"Highline International Corp",
    "wof:placetype":"venue"
},
  "geometry": {"coordinates":[-122.352564,47.703621],"type":"Point"}
}