{
  "type": "Feature",
  "properties": {
    "addr:full":"10 S 1st Ave Yakima WA 98902",
    "addr:housenumber":"10",
    "addr:postcode":"98902",
    "addr:street":"S 1St Ave",
    "iso:country":"US",
    "sg:address":"10 S 1st Ave",
    "sg:city":"Yakima",
    "sg:classifiers":[
        {
            "category":"Freight",
            "type":"Transportation"
        }
    ],
    "sg:phone":"+1 509 457 6185",
    "sg:postcode":"98902",
    "sg:province":"WA",
    "sg:tags":[
        "trucking"
    ],
    "wof:name":"SAIA Motor Freight Line Inc",
    "wof:placetype":"venue"
},
  "geometry": {"coordinates":[-120.508498,46.598979],"type":"Point"}
}