{
  "type": "Feature",
  "properties": {
    "addr:full":"12725 Wilson St Leavenworth WA 98826",
    "addr:housenumber":"12725",
    "addr:postcode":"98826",
    "addr:street":"Wilson St",
    "iso:country":"US",
    "sg:address":"12725 Wilson St",
    "sg:city":"Leavenworth",
    "sg:classifiers":[
        {
            "category":"Manufacturing",
            "subcategory":"Printing",
            "type":"Manufacturing & Wholesale Goods"
        }
    ],
    "sg:phone":"+1 509 548 7849",
    "sg:postcode":"98826",
    "sg:province":"WA",
    "sg:tags":[
        "commercial"
    ],
    "wof:name":"Maynard H Johnson Printers",
    "wof:placetype":"venue"
},
  "geometry": {"coordinates":[-120.674375,47.573436],"type":"Point"}
}