{
  "type": "Feature",
  "properties": {
    "addr:full":"3926 Commercial Ave Anacortes WA 98221",
    "addr:housenumber":"3926",
    "addr:postcode":"98221",
    "addr:street":"Commercial Ave",
    "iso:country":"US",
    "sg:address":"3926 Commercial Ave",
    "sg:city":"Anacortes",
    "sg:classifiers":[
        {
            "category":"Education",
            "subcategory":"Special Training",
            "type":"Public Place"
        }
    ],
    "sg:phone":"+1 360 293 6268",
    "sg:postcode":"98221",
    "sg:province":"WA",
    "sg:tags":[
        "reading",
        "instruction",
        "improvement"
    ],
    "wof:name":"Reading Skill Center",
    "wof:placetype":"venue"
},
  "geometry": {"coordinates":[-122.61292400000001,48.490083],"type":"Point"}
}