{
  "type": "Feature",
  "properties": {
    "addr:full":"919 Mount Vernon Terminal RR Mt Vernon WA 98273",
    "addr:housenumber":"919",
    "addr:postcode":"98273",
    "addr:street":"Mount;Vernon",
    "iso:country":"US",
    "sg:address":"919 Mount Vernon Terminal RR",
    "sg:city":"Mt Vernon",
    "sg:classifiers":[
        {
            "category":"Food & Beverages",
            "subcategory":"Bakery",
            "type":"Retail Goods"
        }
    ],
    "sg:phone":"+1 360 428 4831",
    "sg:postcode":"98273",
    "sg:province":"WA",
    "sg:tags":[
        "baker"
    ],
    "sg:website":"www.xtraspecialcakes.com",
    "wof:name":"Xtra Special Cakes",
    "wof:placetype":"venue"
},
  "geometry": {"coordinates":[-122.339551,48.416501],"type":"Point"}
}