{
  "type": "Feature",
  "properties": {
    "addr:full":"205 7th St Hoquiam WA 98550",
    "addr:housenumber":"205",
    "addr:postcode":"98550",
    "addr:street":"7Th St",
    "iso:country":"US",
    "sg:address":"205 7th St",
    "sg:city":"Hoquiam",
    "sg:classifiers":[
        {
            "category":"Personal",
            "subcategory":"Beauty Salon",
            "type":"Services"
        }
    ],
    "sg:phone":"+1 360 533 3093",
    "sg:postcode":"98550",
    "sg:province":"WA",
    "sg:tags":[
        "shop"
    ],
    "wof:name":"Creative Attitudes",
    "wof:placetype":"venue"
},
  "geometry": {"coordinates":[-123.884387,46.978456],"type":"Point"}
}