{
  "type": "Feature",
  "properties": {
    "addr:full":"8006 26th Ave NW Seattle WA 98117",
    "addr:housenumber":"8006",
    "addr:postcode":"98117",
    "addr:street":"26Th Ave Nw",
    "iso:country":"US",
    "sg:address":"8006 26th Ave NW",
    "sg:city":"Seattle",
    "sg:classifiers":[
        {
            "category":"Professional",
            "subcategory":"Management & Consulting",
            "type":"Services"
        }
    ],
    "sg:phone":"+1 206 297 8036",
    "sg:postcode":"98117",
    "sg:province":"WA",
    "sg:tags":[
        "business"
    ],
    "wof:name":"Vermilion",
    "wof:placetype":"venue"
},
  "geometry": {"coordinates":[-122.389718,47.688957],"type":"Point"}
}