{
  "type": "Feature",
  "properties": {
    "addr:full":"115 NE 100th St 325 Seattle Wa Seattle WA 98125",
    "addr:housenumber":"115;325",
    "addr:postcode":"98125",
    "addr:street":"Ne 100Th St",
    "iso:country":"US",
    "sg:address":"115 NE 100th St 325 Seattle Wa",
    "sg:city":"Seattle",
    "sg:classifiers":[
        {
            "category":"Health Services",
            "subcategory":"Nursing And Care Facility",
            "type":"Services"
        },
        {
            "category":"Health Services",
            "subcategory":"Health Practitioner",
            "type":"Services"
        },
        {
            "category":"Health Services",
            "subcategory":"Hospice",
            "type":"Services"
        },
        {
            "category":"Social Services",
            "subcategory":"Adult Care",
            "type":"Services"
        }
    ],
    "sg:phone":"+1 206 417 7700",
    "sg:postcode":"98125",
    "sg:province":"WA",
    "sg:tags":[
        "nurses-home",
        "therapist",
        "home",
        "nurse",
        "physical"
    ],
    "sg:website":"http://www.heartlandhomehealth.com/Seattle",
    "wof:name":"Heartland Home Care",
    "wof:placetype":"venue"
},
  "geometry": {"coordinates":[-122.32775599999999,47.70137],"type":"Point"}
}