{
  "type": "Feature",
  "properties": {
    "addr:full":"3305 Powerhouse Rd Yakima WA 98902",
    "addr:housenumber":"3305",
    "addr:postcode":"98902",
    "addr:street":"Powerhouse Rd",
    "iso:country":"US",
    "sg:address":"3305 Powerhouse Rd",
    "sg:city":"Yakima",
    "sg:classifiers":[
        {
            "category":"Wholesale",
            "subcategory":"Machinery & Supplies",
            "type":"Manufacturing & Wholesale Goods"
        }
    ],
    "sg:phone":"+1 509 457 6214",
    "sg:postcode":"98902",
    "sg:province":"WA",
    "sg:tags":[
        "water",
        "equipment",
        "distribution",
        "irrigation",
        "system"
    ],
    "wof:name":"Naches & Cowiche Canal Company",
    "wof:placetype":"venue"
},
  "geometry": {"coordinates":[-120.551794,46.609481],"type":"Point"}
}