{
  "type": "Feature",
  "properties": {
    "addr:full":"320 S Sullivan Rd Spokane Valley WA 99037",
    "addr:housenumber":"320",
    "addr:postcode":"99037",
    "addr:street":"S Sullivan Rd",
    "iso:country":"US",
    "sg:address":"320 S Sullivan Rd",
    "sg:city":"Spokane Valley",
    "sg:classifiers":[
        {
            "category":"Building & Trades",
            "subcategory":"Construction",
            "type":"Services"
        }
    ],
    "sg:phone":"+1 509 927 1190",
    "sg:postcode":"99037",
    "sg:province":"WA",
    "sg:tags":[
        "repairing",
        "remodeling",
        "contractor"
    ],
    "wof:name":"Wright Brothers Sunrooms LLC",
    "wof:placetype":"venue"
},
  "geometry": {"coordinates":[-117.19668299999999,47.653996],"type":"Point"}
}