{
  "type": "Feature",
  "properties": {
    "addr:full":"1601 223rd Ave SE Sammamish WA 98075",
    "addr:housenumber":"1601",
    "addr:postcode":"98075",
    "addr:street":"223Rd Ave Se",
    "iso:country":"US",
    "sg:address":"1601 223rd Ave SE",
    "sg:city":"Sammamish",
    "sg:classifiers":[
        {
            "category":"Manufacturing",
            "subcategory":"Rubber & Plastics",
            "type":"Manufacturing & Wholesale Goods"
        }
    ],
    "sg:phone":"+1 425 392 6080",
    "sg:postcode":"98075",
    "sg:province":"WA",
    "sg:tags":[
        "material",
        "construction",
        "product",
        "mfg"
    ],
    "wof:name":"Crescent Vinyl Fence",
    "wof:placetype":"venue"
},
  "geometry": {"coordinates":[-122.041439,47.598365],"type":"Point"}
}