{
  "type": "Feature",
  "properties": {
    "addr:full":"2211 112th St S Tacoma WA 98444",
    "addr:housenumber":"2211",
    "addr:postcode":"98444",
    "addr:street":"112Th St S",
    "iso:country":"US",
    "sg:address":"2211 112th St S",
    "sg:city":"Tacoma",
    "sg:classifiers":[
        {
            "category":"Retail",
            "subcategory":"Storage",
            "type":"Services"
        }
    ],
    "sg:phone":"+1 253 582 7797",
    "sg:postcode":"98444",
    "sg:province":"WA",
    "sg:tags":[
        "self"
    ],
    "sg:website":"www.tacoma-selfstorage.com",
    "wof:name":"Evergreen Self Storage",
    "wof:placetype":"venue"
},
  "geometry": {"coordinates":[-122.466607,47.156644],"type":"Point"}
}