{
  "type": "Feature",
  "properties": {
    "addr:full":"800 NE Tenney Rd Vancouver WA 98685",
    "addr:housenumber":"800",
    "addr:postcode":"98685",
    "addr:street":"Ne Tenney Rd",
    "iso:country":"US",
    "sg:address":"800 NE Tenney Rd",
    "sg:city":"Vancouver",
    "sg:classifiers":[
        {
            "category":"Banks & Credit Unions",
            "subcategory":"Bank",
            "type":"Services"
        }
    ],
    "sg:phone":"+1 360 992 5710",
    "sg:postcode":"98685",
    "sg:province":"WA",
    "sg:tags":[
        "federal",
        "savings",
        "institution"
    ],
    "wof:name":"Washington Mutual Bank",
    "wof:placetype":"venue"
},
  "geometry": {"coordinates":[-122.66687400000001,45.721759],"type":"Point"}
}