{
  "type": "Feature",
  "properties": {
    "addr:full":"230 Williams Lake Rd Colville WA 99114",
    "addr:housenumber":"230",
    "addr:postcode":"99114",
    "addr:street":"Williams Lake Rd",
    "iso:country":"US",
    "sg:address":"230 Williams Lake Rd",
    "sg:city":"Colville",
    "sg:classifiers":[
        {
            "category":"Government",
            "subcategory":"Office",
            "type":"Public Place"
        }
    ],
    "sg:phone":"+1 509 684 7590",
    "sg:postcode":"99114",
    "sg:province":"WA",
    "sg:tags":[
        "county",
        "program"
    ],
    "wof:name":"Stevens County Weed Board",
    "wof:placetype":"venue"
},
  "geometry": {"coordinates":[-117.93608399999999,48.568788],"type":"Point"}
}