{
  "type": "Feature",
  "properties": {
    "addr:full":"13333 Bel Red Rd Ste 200 Bellevue WA 98005",
    "addr:housenumber":"13333",
    "addr:postcode":"98005",
    "addr:street":"Bel Red Rd Ste 200",
    "iso:country":"US",
    "sg:address":"13333 Bel Red Rd Ste 200",
    "sg:city":"Bellevue",
    "sg:classifiers":[
        {
            "category":"Banks & Credit Unions",
            "subcategory":"Financial Services",
            "type":"Services"
        }
    ],
    "sg:phone":"+1 425 462 0566",
    "sg:postcode":"98005",
    "sg:province":"WA",
    "sg:tags":[
        "broker",
        "mortgage"
    ],
    "wof:name":"Shelter Mortgage",
    "wof:placetype":"venue"
},
  "geometry": {"coordinates":[-122.16300200000001,47.622501],"type":"Point"}
}