{
  "type": "Feature",
  "properties": {
    "addr:full":"8970 Blaine Rd Blaine WA 98230",
    "addr:housenumber":"8970",
    "addr:postcode":"98230",
    "addr:street":"Blaine Rd",
    "iso:country":"US",
    "sg:address":"8970 Blaine Rd",
    "sg:city":"Blaine",
    "sg:classifiers":[
        {
            "category":"Farming",
            "subcategory":"Livestock Farm",
            "type":"Manufacturing & Wholesale Goods"
        }
    ],
    "sg:phone":"+1 360 332 6123",
    "sg:postcode":"98230",
    "sg:province":"WA",
    "sg:tags":[
        "beef",
        "feedlot",
        "cattle"
    ],
    "wof:name":"Don Hrutfiord",
    "wof:placetype":"venue"
},
  "geometry": {"coordinates":[-122.729829,48.967349],"type":"Point"}
}