{
  "type": "Feature",
  "properties": {
    "addr:full":"3701 SW Alaska St Seattle WA 98126",
    "addr:housenumber":"3701",
    "addr:postcode":"98126",
    "addr:street":"Sw;St",
    "iso:country":"US",
    "sg:address":"3701 SW Alaska St",
    "sg:city":"Seattle",
    "sg:classifiers":[
        {
            "category":"Travel",
            "subcategory":"Travel Agent",
            "type":"Entertainment"
        }
    ],
    "sg:phone":"+1 206 937 7464",
    "sg:postcode":"98126",
    "sg:province":"WA",
    "sg:tags":[
        "agency"
    ],
    "sg:website":"www.marynorth.com",
    "wof:name":"Mary North Travel Service Inc",
    "wof:placetype":"venue"
},
  "geometry": {"coordinates":[-122.378998,47.560902],"type":"Point"}
}