{
  "type": "Feature",
  "properties": {
    "addr:full":"5492 Rd 3 NE Moses Lake WA 98837",
    "addr:postcode":"5492;98837",
    "addr:street":"Rd 3 Ne",
    "iso:country":"US",
    "sg:address":"5492 Rd 3 NE",
    "sg:city":"Moses Lake",
    "sg:classifiers":[
        {
            "category":"Building & Trades",
            "subcategory":"Pest Control",
            "type":"Services"
        }
    ],
    "sg:phone":"+1 509 765 8299",
    "sg:postcode":"98837",
    "sg:province":"WA",
    "sg:tags":[
        "spraying"
    ],
    "wof:name":"Double R Spraying Svc Inc",
    "wof:placetype":"venue"
},
  "geometry": {"coordinates":[-119.37469299999999,47.131667],"type":"Point"}
}