{
  "type": "Feature",
  "properties": {
    "addr:full":"2086 Jeffcott Pl Ferndale WA 98248",
    "addr:housenumber":"2086",
    "addr:postcode":"98248",
    "addr:street":"Jeffcott Pl",
    "iso:country":"US",
    "sg:address":"2086 Jeffcott Pl",
    "sg:city":"Ferndale",
    "sg:classifiers":[
        {
            "category":"Professional",
            "subcategory":"Business Services",
            "type":"Services"
        }
    ],
    "sg:phone":"+1 360 384 6652",
    "sg:postcode":"98248",
    "sg:province":"WA",
    "wof:name":"Storms Music Services",
    "wof:placetype":"venue"
},
  "geometry": {"coordinates":[-122.59495099999999,48.858244],"type":"Point"}
}