{
  "type": "Feature",
  "properties": {
    "addr:full":"4535 NE 41st St Seattle WA 98105",
    "addr:housenumber":"4535",
    "addr:postcode":"98105",
    "addr:street":"Ne 41St St",
    "iso:country":"US",
    "sg:address":"4535 NE 41st St",
    "sg:city":"Seattle",
    "sg:classifiers":[
        {
            "category":"Health Services",
            "subcategory":"Dentist",
            "type":"Services"
        }
    ],
    "sg:phone":"+1 206 522 5225",
    "sg:postcode":"98105",
    "sg:province":"WA",
    "wof:name":"Morton Thomas S DDS",
    "wof:placetype":"venue"
},
  "geometry": {"coordinates":[-122.27845499999999,47.658261],"type":"Point"}
}