{
  "type": "Feature",
  "properties": {
    "addr:full":"10114 Taylor St Puyallup WA 98371",
    "addr:housenumber":"10114",
    "addr:postcode":"98371",
    "addr:street":"Taylor St",
    "iso:country":"US",
    "sg:address":"10114 Taylor St",
    "sg:city":"Puyallup",
    "sg:classifiers":[
        {
            "category":"Manufacturing",
            "subcategory":"Lumber",
            "type":"Manufacturing & Wholesale Goods"
        }
    ],
    "sg:phone":"+1 253 952 4310",
    "sg:postcode":"98371",
    "sg:province":"WA",
    "sg:tags":[
        "mill"
    ],
    "wof:name":"Sitka Spruce Sales",
    "wof:placetype":"venue"
},
  "geometry": {"coordinates":[-122.294267,47.24267],"type":"Point"}
}