{
  "type": "Feature",
  "properties": {
    "addr:full":"7719 12th Ave E Tacoma WA 98404",
    "addr:housenumber":"7719",
    "addr:postcode":"98404",
    "addr:street":"12Th Ave E",
    "iso:country":"US",
    "sg:address":"7719 12th Ave E",
    "sg:city":"Tacoma",
    "sg:classifiers":[
        {
            "category":"Professional",
            "type":"Services"
        }
    ],
    "sg:phone":"+1 253 606 4053",
    "sg:postcode":"98404",
    "sg:province":"WA",
    "wof:name":"Murals By Angie",
    "wof:placetype":"venue"
},
  "geometry": {"coordinates":[-122.412926,47.187986],"type":"Point"}
}