{
  "type": "Feature",
  "properties": {
    "addr:full":"702 101st Ave SW Olympia WA 98512",
    "addr:housenumber":"702",
    "addr:postcode":"98512",
    "addr:street":"101St Ave Sw",
    "iso:country":"US",
    "sg:address":"702 101st Ave SW",
    "sg:city":"Olympia",
    "sg:classifiers":[
        {
            "category":"Professional",
            "subcategory":"Management & Consulting",
            "type":"Services"
        }
    ],
    "sg:phone":"+1 360 352 3415",
    "sg:postcode":"98512",
    "sg:province":"WA",
    "sg:tags":[
        "construction"
    ],
    "wof:name":"Kneeland Co",
    "wof:placetype":"venue"
},
  "geometry": {"coordinates":[-122.915437,46.941963],"type":"Point"}
}