{
  "type": "Feature",
  "properties": {
    "addr:full":"1107W W 2nd St Grandview WA 98930",
    "addr:postcode":"98930",
    "addr:street":"W 2Nd St",
    "iso:country":"US",
    "sg:address":"1107W W 2nd St",
    "sg:city":"Grandview",
    "sg:classifiers":[
        {
            "category":"Building & Trades",
            "subcategory":"Cleaning & Sanitation",
            "type":"Services"
        }
    ],
    "sg:phone":"+1 509 882 3104",
    "sg:postcode":"98930",
    "sg:province":"WA",
    "sg:tags":[
        "janitorial"
    ],
    "wof:name":"Building Maintenance",
    "wof:placetype":"venue"
},
  "geometry": {"coordinates":[-119.91698100000001,46.254755],"type":"Point"}
}