{
  "type": "Feature",
  "properties": {
    "addr:full":"506 NE Blair Rd Washougal WA 98671",
    "addr:housenumber":"506",
    "addr:postcode":"98671",
    "addr:street":"Ne Blair Rd",
    "iso:country":"US",
    "sg:address":"506 NE Blair Rd",
    "sg:city":"Washougal",
    "sg:classifiers":[
        {
            "category":"Professional",
            "subcategory":"Research",
            "type":"Services"
        }
    ],
    "sg:phone":"+1 360 834 2576",
    "sg:postcode":"98671",
    "sg:province":"WA",
    "sg:tags":[
        "information",
        "medical",
        "noncommercial"
    ],
    "wof:name":"P S Transcription",
    "wof:placetype":"venue"
},
  "geometry": {"coordinates":[-122.378123,45.623854],"type":"Point"}
}