{
  "type": "Feature",
  "properties": {
    "addr:full":"829 W Broadway Ave Spokane WA 99201",
    "addr:housenumber":"829",
    "addr:postcode":"99201",
    "addr:street":"W Broadway Ave",
    "iso:country":"US",
    "sg:address":"829 W Broadway Ave",
    "sg:city":"Spokane",
    "sg:classifiers":[
        {
            "category":"Health Services",
            "subcategory":"Doctor",
            "type":"Services"
        }
    ],
    "sg:phone":"+1 509 325 9439",
    "sg:postcode":"99201",
    "sg:province":"WA",
    "sg:tags":[
        "physician",
        "surgeon"
    ],
    "wof:name":"Pathology Assoicates",
    "wof:placetype":"venue"
},
  "geometry": {"coordinates":[-117.424699,47.66432],"type":"Point"}
}