{
  "type": "Feature",
  "properties": {
    "addr:full":"5403 NE 59th Cir Vancouver WA 98661",
    "addr:housenumber":"5403",
    "addr:postcode":"98661",
    "addr:street":"Ne 59Th Cir",
    "iso:country":"US",
    "sg:address":"5403 NE 59th Cir",
    "sg:city":"Vancouver",
    "sg:classifiers":[
        {
            "category":"Professional",
            "type":"Services"
        }
    ],
    "sg:phone":"+1 360 750 4775",
    "sg:postcode":"98661",
    "sg:province":"WA",
    "sg:tags":[
        "establishment"
    ],
    "wof:name":"Stark & Stark",
    "wof:placetype":"venue"
},
  "geometry": {"coordinates":[-122.616679,45.664872],"type":"Point"}
}