{
  "type": "Feature",
  "properties": {
    "addr:full":"9939 Mickelberry Rd NW Silverdale WA 98383",
    "addr:housenumber":"9939",
    "addr:postcode":"98383",
    "addr:street":"Mickelberry Rd Nw",
    "iso:country":"US",
    "sg:address":"9939 Mickelberry Rd NW",
    "sg:city":"Silverdale",
    "sg:classifiers":[
        {
            "category":"Banks & Credit Unions",
            "subcategory":"Bank",
            "type":"Services"
        }
    ],
    "sg:phone":"+1 360 613 0156",
    "sg:postcode":"98383",
    "sg:province":"WA",
    "sg:tags":[
        "mortgage",
        "real estate"
    ],
    "wof:name":"Windermere Mortgage Services",
    "wof:placetype":"venue"
},
  "geometry": {"coordinates":[-122.68235799999999,47.654122],"type":"Point"}
}