{
  "type": "Feature",
  "properties": {
    "addr:full":"1304 Main St Vancouver WA 98660",
    "addr:housenumber":"1304",
    "addr:postcode":"98660",
    "addr:street":"Main St",
    "iso:country":"US",
    "sg:address":"1304 Main St",
    "sg:city":"Vancouver",
    "sg:classifiers":[
        {
            "category":"Real Estate",
            "subcategory":"Real Estate Operator",
            "type":"Services"
        }
    ],
    "sg:phone":"+1 360 256 3841",
    "sg:postcode":"98660",
    "sg:province":"WA",
    "sg:tags":[
        "building",
        "apartment"
    ],
    "wof:name":"Realvest Corporation",
    "wof:placetype":"venue"
},
  "geometry": {"coordinates":[-122.67163499999999,45.631838],"type":"Point"}
}