{
  "type": "Feature",
  "properties": {
    "addr:full":"5009 W Clearwater Ave Kennewick WA 99336",
    "addr:housenumber":"5009",
    "addr:postcode":"99336",
    "addr:street":"W Clearwater Ave",
    "iso:country":"US",
    "sg:address":"5009 W Clearwater Ave",
    "sg:city":"Kennewick",
    "sg:classifiers":[
        {
            "category":"Insurance",
            "subcategory":"Insurance Agent",
            "type":"Services"
        }
    ],
    "sg:phone":"+1 509 734 5304",
    "sg:postcode":"99336",
    "sg:province":"WA",
    "wof:name":"AFLAC",
    "wof:placetype":"venue"
},
  "geometry": {"coordinates":[-119.18960300000001,46.212344],"type":"Point"}
}