{
  "type": "Feature",
  "properties": {
    "addr:full":"38104 NE 85th Ave La Center WA 98629",
    "addr:housenumber":"38104",
    "addr:postcode":"98629",
    "addr:street":"Ne 85Th Ave",
    "iso:country":"US",
    "sg:address":"38104 NE 85th Ave",
    "sg:city":"La Center",
    "sg:classifiers":[
        {
            "category":"Building & Trades",
            "subcategory":"Construction",
            "type":"Services"
        }
    ],
    "sg:phone":"+1 360 608 5085",
    "sg:postcode":"98629",
    "sg:province":"WA",
    "sg:tags":[
        "masonry",
        "contractor"
    ],
    "wof:name":"Evergreen Masonry",
    "wof:placetype":"venue"
},
  "geometry": {"coordinates":[-122.586146,45.895931],"type":"Point"}
}