{
  "type": "Feature",
  "properties": {
    "addr:full":"917 10th St Bellingham WA 98225",
    "addr:housenumber":"917",
    "addr:postcode":"98225",
    "addr:street":"10Th St",
    "iso:country":"US",
    "sg:address":"917 10th St",
    "sg:city":"Bellingham",
    "sg:classifiers":[
        {
            "category":"Building & Trades",
            "subcategory":"Equipment Rental",
            "type":"Services"
        }
    ],
    "sg:phone":"+1 360 676 7476",
    "sg:postcode":"98225",
    "sg:province":"WA",
    "wof:name":"Befort Rentals LLC",
    "wof:placetype":"venue"
},
  "geometry": {"coordinates":[-122.504952,48.724975],"type":"Point"}
}