{
  "type": "Feature",
  "properties": {
    "addr:full":"1615 Bayon Rd Bellingham WA 98225",
    "addr:housenumber":"1615",
    "addr:postcode":"98225",
    "addr:street":"Bayon Rd",
    "iso:country":"US",
    "sg:address":"1615 Bayon Rd",
    "sg:city":"Bellingham",
    "sg:classifiers":[
        {
            "category":"Government",
            "subcategory":"Office",
            "type":"Public Place"
        }
    ],
    "sg:phone":"+1 360 733 5770",
    "sg:postcode":"98225",
    "sg:province":"WA",
    "sg:tags":[
        "management"
    ],
    "wof:name":"Whatcom County Water Dst 2",
    "wof:placetype":"venue"
},
  "geometry": {"coordinates":[-122.570941,48.787424],"type":"Point"}
}