{
  "type": "Feature",
  "properties": {
    "addr:full":"411 McCormick St SE Olympia WA 98501",
    "addr:housenumber":"411",
    "addr:postcode":"98501",
    "addr:street":"Mccormick St Se",
    "iso:country":"US",
    "sg:address":"411 McCormick St SE",
    "sg:city":"Olympia",
    "sg:classifiers":[
        {
            "category":"Utilities",
            "subcategory":"Telephone",
            "type":"Services"
        }
    ],
    "sg:phone":"+1 360 352 1144",
    "sg:postcode":"98501",
    "sg:province":"WA",
    "sg:tags":[
        "communications"
    ],
    "wof:name":"Layne Huber",
    "wof:placetype":"venue"
},
  "geometry": {"coordinates":[-122.879186,47.045283],"type":"Point"}
}