{
  "type": "Feature",
  "properties": {
    "addr:full":"1200 12th Ave S Seattle WA 98107",
    "addr:housenumber":"1200",
    "addr:postcode":"98107",
    "addr:street":"12Th Ave S",
    "iso:country":"US",
    "sg:address":"1200 12th Ave S",
    "sg:city":"Seattle",
    "sg:classifiers":[
        {
            "category":"Taxi",
            "type":"Transportation"
        }
    ],
    "sg:phone":"+1 206 788 7722",
    "sg:postcode":"98107",
    "sg:province":"WA",
    "wof:name":"Seattle Airport Taxi Service",
    "wof:placetype":"venue"
},
  "geometry": {"coordinates":[-122.317251,47.593793],"type":"Point"}
}