{
  "type": "Feature",
  "properties": {
    "addr:full":"436 168th Ave SE Bellevue WA 98008",
    "addr:housenumber":"436",
    "addr:postcode":"98008",
    "addr:street":"168Th Ave Se",
    "iso:country":"US",
    "sg:address":"436 168th Ave SE",
    "sg:city":"Bellevue",
    "sg:classifiers":[
        {
            "category":"Real Estate",
            "subcategory":"Real Estate Agent",
            "type":"Services"
        }
    ],
    "sg:phone":"+1 425 562 3087",
    "sg:postcode":"98008",
    "sg:province":"WA",
    "wof:name":"Stappcorp Inc",
    "wof:placetype":"venue"
},
  "geometry": {"coordinates":[-122.117637,47.606565],"type":"Point"}
}