{
  "type": "Feature",
  "properties": {
    "addr:full":"1526 Springwater Ave Wenatchee WA 98801",
    "addr:housenumber":"1526",
    "addr:postcode":"98801",
    "addr:street":"Springwater Ave",
    "iso:country":"US",
    "sg:address":"1526 Springwater Ave",
    "sg:city":"Wenatchee",
    "sg:classifiers":[
        {
            "category":"Retail",
            "subcategory":"Auto Repair",
            "type":"Services"
        }
    ],
    "sg:phone":"+1 509 664 2996",
    "sg:postcode":"98801",
    "sg:province":"WA",
    "sg:tags":[
        "automotive",
        "general"
    ],
    "wof:name":"Fordable Auto Repair",
    "wof:placetype":"venue"
},
  "geometry": {"coordinates":[-120.33936300000001,47.437053],"type":"Point"}
}