{
  "type": "Feature",
  "properties": {
    "addr:full":"621 172nd St NE Arlington WA 98223",
    "addr:housenumber":"621",
    "addr:postcode":"98223",
    "addr:street":"172Nd St Ne",
    "iso:country":"US",
    "sg:address":"621 172nd St NE",
    "sg:city":"Arlington",
    "sg:classifiers":[
        {
            "category":"Wholesale",
            "subcategory":"Machinery & Supplies",
            "type":"Manufacturing & Wholesale Goods"
        }
    ],
    "sg:phone":"+1 360 652 4200",
    "sg:postcode":"98223",
    "sg:province":"WA",
    "sg:tags":[
        "equipment",
        "industrial"
    ],
    "wof:name":"Evans Manufacturing Company",
    "wof:placetype":"venue"
},
  "geometry": {"coordinates":[-122.215693,48.151911],"type":"Point"}
}