{
  "type": "Feature",
  "properties": {
    "addr:full":"5720 S Cheyenne St Tacoma WA 98409",
    "addr:housenumber":"5720",
    "addr:postcode":"98409",
    "addr:street":"S Cheyenne St",
    "iso:country":"US",
    "sg:address":"5720 S Cheyenne St",
    "sg:city":"Tacoma",
    "sg:classifiers":[
        {
            "category":"Wholesale",
            "subcategory":"Groceries",
            "type":"Manufacturing & Wholesale Goods"
        }
    ],
    "sg:phone":"+1 253 227 1400",
    "sg:postcode":"98409",
    "sg:province":"WA",
    "sg:tags":[
        "general"
    ],
    "wof:name":"Meridian Vap Corp",
    "wof:placetype":"venue"
},
  "geometry": {"coordinates":[-122.498351,47.205118],"type":"Point"}
}