{
  "type": "Feature",
  "properties": {
    "addr:full":"22203 84th Ave S Kent WA 98032",
    "addr:housenumber":"22203",
    "addr:postcode":"98032",
    "addr:street":"84Th Ave S",
    "iso:country":"US",
    "sg:address":"22203 84th Ave S",
    "sg:city":"Kent",
    "sg:classifiers":[
        {
            "category":"Travel",
            "subcategory":"Hotels & Motels",
            "type":"Entertainment"
        }
    ],
    "sg:phone":"+1 253 872 8382",
    "sg:postcode":"98032",
    "sg:province":"WA",
    "wof:name":"Orgady",
    "wof:placetype":"venue"
},
  "geometry": {"coordinates":[-122.228022,47.40209],"type":"Point"}
}