{
  "type": "Feature",
  "properties": {
    "addr:full":"2424 E 2nd St Vancouver WA 98661",
    "addr:housenumber":"2424",
    "addr:postcode":"98661",
    "addr:street":"E 2Nd St",
    "iso:country":"US",
    "sg:address":"2424 E 2nd St",
    "sg:city":"Vancouver",
    "sg:classifiers":[
        {
            "category":"Manufacturing",
            "subcategory":"Metals",
            "type":"Manufacturing & Wholesale Goods"
        }
    ],
    "sg:phone":"+1 360 737 8235",
    "sg:postcode":"98661",
    "sg:province":"WA",
    "sg:tags":[
        "steel"
    ],
    "wof:name":"Instafab",
    "wof:placetype":"venue"
},
  "geometry": {"coordinates":[-122.645945,45.622443],"type":"Point"}
}