{
  "type": "Feature",
  "properties": {
    "addr:full":"1518 11th Ave Seattle WA 98122",
    "addr:housenumber":"1518",
    "addr:postcode":"98122",
    "addr:street":"11Th Ave",
    "iso:country":"US",
    "sg:address":"1518 11th Ave",
    "sg:city":"Seattle",
    "sg:classifiers":[
        {
            "category":"Bars & Pubs",
            "type":"Food & Drink"
        },
        {
            "category":"Restaurant",
            "type":"Food & Drink"
        },
        {
            "category":"Bars & Pubs",
            "subcategory":"Lounge",
            "type":"Food & Drink"
        }
    ],
    "sg:phone":"+1 206 325 3112",
    "sg:postcode":"98122",
    "sg:province":"WA",
    "sg:tags":[
        "grill",
        "cocktail"
    ],
    "wof:name":"Purr",
    "wof:placetype":"venue"
},
  "geometry": {"coordinates":[-122.31813200000001,47.614303],"type":"Point"}
}