{
  "type": "Feature",
  "properties": {
    "addr:full":"3403 S Tekoa St Spokane WA 99203",
    "addr:housenumber":"3403",
    "addr:postcode":"99203",
    "addr:street":"S Tekoa St",
    "iso:country":"US",
    "sg:address":"3403 S Tekoa St",
    "sg:city":"Spokane",
    "sg:classifiers":[
        {
            "category":"Government",
            "subcategory":"Office",
            "type":"Public Place"
        }
    ],
    "sg:phone":"+1 509 455 7944",
    "sg:postcode":"99203",
    "sg:province":"WA",
    "sg:tags":[
        "program",
        "administrative"
    ],
    "wof:name":"Personnel Solutions",
    "wof:placetype":"venue"
},
  "geometry": {"coordinates":[-117.409175,47.622649],"type":"Point"}
}