{
  "type": "Feature",
  "properties": {
    "addr:full":"2233 1st Ave S Seattle WA 98134",
    "addr:housenumber":"2233",
    "addr:postcode":"98134",
    "addr:street":"1St Ave S",
    "iso:country":"US",
    "sg:address":"2233 1st Ave S",
    "sg:city":"Seattle",
    "sg:classifiers":[
        {
            "category":"Home & Garden",
            "subcategory":"Home Furnishings",
            "type":"Retail Goods"
        },
        {
            "category":"Wholesale",
            "subcategory":"Electrical",
            "type":"Manufacturing & Wholesale Goods"
        }
    ],
    "sg:phone":"+1 206 682 6385",
    "sg:postcode":"98134",
    "sg:province":"WA",
    "sg:tags":[
        "fluorescent",
        "lighting",
        "fixture"
    ],
    "wof:name":"Commercial Lighting Co Inc",
    "wof:placetype":"venue"
},
  "geometry": {"coordinates":[-122.334277,47.58223],"type":"Point"}
}