{
  "type": "Feature",
  "properties": {
    "addr:full":"6 W Falcon Ave Spokane WA 99218",
    "addr:housenumber":"6",
    "addr:postcode":"99218",
    "addr:street":"W Falcon Ave",
    "iso:country":"US",
    "sg:address":"6 W Falcon Ave",
    "sg:city":"Spokane",
    "sg:classifiers":[
        {
            "category":"Recreation",
            "type":"Entertainment"
        }
    ],
    "sg:phone":"+1 509 467 2122",
    "sg:postcode":"99218",
    "sg:province":"WA",
    "sg:tags":[
        "clinic",
        "training",
        "sport",
        "instruction",
        "skill"
    ],
    "wof:name":"Glenn Bishop",
    "wof:placetype":"venue"
},
  "geometry": {"coordinates":[-117.41123899999999,47.761612],"type":"Point"}
}