{
  "type": "Feature",
  "properties": {
    "addr:full":"802 172nd St E Spanaway WA 98387",
    "addr:housenumber":"802",
    "addr:postcode":"98387",
    "addr:street":"172Nd St E",
    "iso:country":"US",
    "sg:address":"802 172nd St E",
    "sg:city":"Spanaway",
    "sg:classifiers":[
        {
            "category":"Manufacturing",
            "subcategory":"Lumber",
            "type":"Manufacturing & Wholesale Goods"
        }
    ],
    "sg:phone":"+1 253 531 8728",
    "sg:postcode":"98387",
    "sg:province":"WA",
    "sg:tags":[
        "logging"
    ],
    "wof:name":"Lee Hughes Logging",
    "wof:placetype":"venue"
},
  "geometry": {"coordinates":[-122.419979,47.10071],"type":"Point"}
}