{
  "type": "Feature",
  "properties": {
    "addr:full":"11600 SE Mill Plain Blvd Ste P Vancouver WA 98684",
    "addr:postcode":"11600;98684",
    "addr:street":"Se Mill Plain Blvd Ste P",
    "iso:country":"US",
    "sg:address":"11600 SE Mill Plain Blvd Ste P",
    "sg:city":"Vancouver",
    "sg:classifiers":[
        {
            "category":"Professional",
            "subcategory":"Computer Services",
            "type":"Services"
        }
    ],
    "sg:phone":"+1 360 699 4010",
    "sg:postcode":"98684",
    "sg:province":"WA",
    "sg:tags":[
        "repair"
    ],
    "wof:name":"Cutting Edge Technologies Inc",
    "wof:placetype":"venue"
},
  "geometry": {"coordinates":[-122.55300099999999,45.620899],"type":"Point"}
}