{
  "type": "Feature",
  "properties": {
    "addr:full":"1353 Yukon Harbor Rd SE Port Orchard WA 98366",
    "addr:housenumber":"1353",
    "addr:postcode":"98366",
    "addr:street":"Yukon Harbor Rd Se",
    "iso:country":"US",
    "sg:address":"1353 Yukon Harbor Rd SE",
    "sg:city":"Port Orchard",
    "sg:classifiers":[
        {
            "category":"Social Services",
            "type":"Services"
        }
    ],
    "sg:phone":"+1 360 871 5494",
    "sg:postcode":"98366",
    "sg:province":"WA",
    "sg:tags":[
        "counselor",
        "marriage",
        "family"
    ],
    "wof:name":"Phillips & Assoc",
    "wof:placetype":"venue"
},
  "geometry": {"coordinates":[-122.545284,47.536295],"type":"Point"}
}