{
  "type": "Feature",
  "properties": {
    "addr:full":"3028 Wetmore Ave Everett WA 98201",
    "addr:housenumber":"3028",
    "addr:postcode":"98201",
    "addr:street":"Wetmore Ave",
    "iso:country":"US",
    "sg:address":"3028 Wetmore Ave",
    "sg:city":"Everett",
    "sg:classifiers":[
        {
            "category":"Government",
            "subcategory":"Court House",
            "type":"Public Place"
        }
    ],
    "sg:phone":"+1 425 257 8778",
    "sg:postcode":"98201",
    "sg:province":"WA",
    "sg:tags":[
        "city"
    ],
    "wof:name":"Everett Municipal Court",
    "wof:placetype":"venue"
},
  "geometry": {"coordinates":[-122.207216,47.976933],"type":"Point"}
}