{
  "type": "Feature",
  "properties": {
    "addr:full":"5818 24th Ave NW Seattle WA 98107",
    "addr:housenumber":"5818",
    "addr:postcode":"98107",
    "addr:street":"24Th Ave Nw",
    "iso:country":"US",
    "sg:address":"5818 24th Ave NW",
    "sg:city":"Seattle",
    "sg:classifiers":[
        {
            "category":"Real Estate",
            "subcategory":"Architect",
            "type":"Services"
        }
    ],
    "sg:phone":"+1 206 784 0887",
    "sg:postcode":"98107",
    "sg:province":"WA",
    "wof:name":"Carsten Stinn Architecture",
    "wof:placetype":"venue"
},
  "geometry": {"coordinates":[-122.387513,47.67151],"type":"Point"}
}