{
  "type": "Feature",
  "properties": {
    "addr:full":"117 W Magnolia St Bellingham WA 98225",
    "addr:housenumber":"117",
    "addr:postcode":"98225",
    "addr:street":"W Magnolia St",
    "iso:country":"US",
    "sg:address":"117 W Magnolia St",
    "sg:city":"Bellingham",
    "sg:phone":"+1 360 756 0711",
    "sg:postcode":"98225",
    "sg:province":"WA",
    "wof:name":"Taco Lobo",
    "wof:placetype":"venue"
},
  "geometry": {"coordinates":[-122.477836,48.750869],"type":"Point"}
}