{
  "type": "Feature",
  "properties": {
    "addr:full":"4519 Sahalee Way NE Sammamish WA 98074",
    "addr:postcode":"4519;98074",
    "addr:street":"Sahalee Way Ne",
    "iso:country":"US",
    "sg:address":"4519 Sahalee Way NE",
    "sg:city":"Sammamish",
    "sg:classifiers":[
        {
            "category":"Retail",
            "subcategory":"Auto Repair",
            "type":"Services"
        }
    ],
    "sg:phone":"+1 425 868 8631",
    "sg:postcode":"98074",
    "sg:province":"WA",
    "sg:tags":[
        "automotive",
        "general"
    ],
    "wof:name":"Preston Automotive Ltd",
    "wof:placetype":"venue"
},
  "geometry": {"coordinates":[-122.05578199999999,47.649173],"type":"Point"}
}