{
  "type": "Feature",
  "properties": {
    "addr:full":"15690 SE 227th St Kent WA 98042",
    "addr:postcode":"15690;98042",
    "addr:street":"Se 227Th St",
    "iso:country":"US",
    "sg:address":"15690 SE 227th St",
    "sg:city":"Kent",
    "sg:classifiers":[
        {
            "category":"Building & Trades",
            "subcategory":"Construction",
            "type":"Services"
        }
    ],
    "sg:phone":"+1 253 638 2213",
    "sg:postcode":"98042",
    "sg:province":"WA",
    "sg:tags":[
        "house"
    ],
    "wof:name":"Reeder Const Inc",
    "wof:placetype":"venue"
},
  "geometry": {"coordinates":[-122.132379,47.398785],"type":"Point"}
}