{
  "type": "Feature",
  "properties": {
    "addr:full":"2516 Montavista Pl W Seattle WA 98199",
    "addr:housenumber":"2516",
    "addr:postcode":"98199",
    "addr:street":"Montavista Pl W",
    "iso:country":"US",
    "sg:address":"2516 Montavista Pl W",
    "sg:city":"Seattle",
    "sg:classifiers":[
        {
            "category":"Social Services",
            "subcategory":"Child Care",
            "type":"Services"
        }
    ],
    "sg:phone":"+1 206 285 5593",
    "sg:postcode":"98199",
    "sg:province":"WA",
    "sg:tags":[
        "day"
    ],
    "wof:name":"B & JS Child Care",
    "wof:placetype":"venue"
},
  "geometry": {"coordinates":[-122.405113,47.641876],"type":"Point"}
}