{
  "type": "Feature",
  "properties": {
    "addr:full":"5105 200th St SW Lynnwood WA 98036",
    "addr:housenumber":"5105",
    "addr:postcode":"98036",
    "addr:street":"200Th St Sw",
    "iso:country":"US",
    "sg:address":"5105 200th St SW",
    "sg:city":"Lynnwood",
    "sg:classifiers":[
        {
            "category":"Communications",
            "type":"Services"
        }
    ],
    "sg:phone":"+1 425 762 5858",
    "sg:postcode":"98036",
    "sg:province":"WA",
    "sg:tags":[
        "communication"
    ],
    "wof:name":"Westower Communications",
    "wof:placetype":"venue"
},
  "geometry": {"coordinates":[-122.30197099999999,47.817532],"type":"Point"}
}