{
  "type": "Feature",
  "properties": {
    "iso:country":"US",
    "sg:address":"30408 N Mill Rd",
    "sg:city":"Deer Park",
    "sg:classifiers":[
        {
            "category":"Manufacturing",
            "subcategory":"Wood Products",
            "type":"Manufacturing & Wholesale Goods"
        }
    ],
    "sg:phone":"+1 509 276 2464",
    "sg:postcode":"99006",
    "sg:province":"WA",
    "sg:tags":[
        "mfg"
    ],
    "wof:name":"Sinnsational Enterprises",
    "wof:placetype":"venue"
},
  "geometry": {"coordinates":[-117.422877,47.937611],"type":"Point"}
}