{
  "type": "Feature",
  "properties": {
    "addr:full":"1112 Daniels St Ste 110 Vancouver WA 98660",
    "addr:housenumber":"1112",
    "addr:postcode":"98660",
    "addr:street":"Daniels St Ste 110",
    "iso:country":"US",
    "sg:address":"1112 Daniels St Ste 110",
    "sg:city":"Vancouver",
    "sg:classifiers":[
        {
            "category":"Professional",
            "subcategory":"Accounting & Tax Preparation",
            "type":"Services"
        }
    ],
    "sg:phone":"+1 360 695 0068",
    "sg:postcode":"98660",
    "sg:province":"WA",
    "sg:tags":[
        "accountant"
    ],
    "wof:name":"Plymale Michael J Inc PS",
    "wof:placetype":"venue"
},
  "geometry": {"coordinates":[-122.675003,45.6297],"type":"Point"}
}