{
  "type": "Feature",
  "properties": {
    "addr:full":"31001 N Staghorn Rd Deer Park WA 99006",
    "addr:housenumber":"31001",
    "addr:postcode":"99006",
    "addr:street":"N Staghorn Rd",
    "iso:country":"US",
    "sg:address":"31001 N Staghorn Rd",
    "sg:city":"Deer Park",
    "sg:classifiers":[
        {
            "category":"Professional",
            "subcategory":"Business Services",
            "type":"Services"
        }
    ],
    "sg:phone":"+1 509 276 3437",
    "sg:postcode":"99006",
    "sg:province":"WA",
    "wof:name":"Lens Sales & Service",
    "wof:placetype":"venue"
},
  "geometry": {"coordinates":[-117.440833,47.934431],"type":"Point"}
}