{
  "type": "Feature",
  "properties": {
    "addr:full":"314 S Monroe St Aberdeen WA 98520",
    "addr:housenumber":"314",
    "addr:postcode":"98520",
    "addr:street":"S Monroe St",
    "iso:country":"US",
    "sg:address":"314 S Monroe St",
    "sg:city":"Aberdeen",
    "sg:classifiers":[
        {
            "category":"Building & Trades",
            "subcategory":"Plumbing",
            "type":"Services"
        }
    ],
    "sg:phone":"+1 360 537 1249",
    "sg:postcode":"98520",
    "sg:province":"WA",
    "sg:tags":[
        "contractor"
    ],
    "wof:name":"Patriot Heating & Air",
    "wof:placetype":"venue"
},
  "geometry": {"coordinates":[-123.82854500000001,46.967439],"type":"Point"}
}