{
  "type": "Feature",
  "properties": {
    "iso:country":"US",
    "sg:address":"3389 Ward Ct",
    "sg:city":"Enumclaw",
    "sg:classifiers":[
        {
            "category":"Home & Garden",
            "subcategory":"Garden Supply",
            "type":"Retail Goods"
        }
    ],
    "sg:phone":"+1 360 802 0168",
    "sg:postcode":"98022",
    "sg:province":"WA",
    "wof:name":"Weeping Garden",
    "wof:placetype":"venue"
},
  "geometry": {"coordinates":[-122.01323600000001,47.195634],"type":"Point"}
}