{
  "type": "Feature",
  "properties": {
    "addr:full":"14925 171st Ave SE Monroe WA 98272",
    "addr:housenumber":"14925",
    "addr:postcode":"98272",
    "addr:street":"171St Ave Se",
    "iso:country":"US",
    "sg:address":"14925 171st Ave SE",
    "sg:city":"Monroe",
    "sg:classifiers":[
        {
            "category":"Real Estate",
            "subcategory":"Developer",
            "type":"Services"
        }
    ],
    "sg:phone":"+1 425 487 9663",
    "sg:postcode":"98272",
    "sg:province":"WA",
    "sg:tags":[
        "subdivider"
    ],
    "wof:name":"Monroe Land & Development Co",
    "wof:placetype":"venue"
},
  "geometry": {"coordinates":[-122.001464,47.862384],"type":"Point"}
}