{
  "type": "Feature",
  "properties": {
    "addr:full":"1729 W Railroad Ave Shelton WA 98584",
    "addr:housenumber":"1729",
    "addr:postcode":"98584",
    "addr:street":"W Railroad Ave",
    "iso:country":"US",
    "sg:address":"1729 W Railroad Ave",
    "sg:city":"Shelton",
    "sg:classifiers":[
        {
            "category":"Real Estate",
            "subcategory":"Real Estate Agent",
            "type":"Services"
        }
    ],
    "sg:phone":"+1 360 426 3567",
    "sg:postcode":"98584",
    "sg:province":"WA",
    "wof:name":"Invest Realty LLC",
    "wof:placetype":"venue"
},
  "geometry": {"coordinates":[-123.121424,47.213435],"type":"Point"}
}