{
  "type": "Feature",
  "properties": {
    "addr:full":"8220 96th St NW Gig Harbor WA 98332",
    "addr:housenumber":"8220",
    "addr:postcode":"98332",
    "addr:street":"96Th St Nw",
    "iso:country":"US",
    "sg:address":"8220 96th St NW",
    "sg:city":"Gig Harbor",
    "sg:classifiers":[
        {
            "category":"Building & Trades",
            "subcategory":"Construction",
            "type":"Services"
        }
    ],
    "sg:phone":"+1 253 851 9266",
    "sg:postcode":"98332",
    "sg:province":"WA",
    "sg:tags":[
        "contractor"
    ],
    "wof:name":"Beals Drywall",
    "wof:placetype":"venue"
},
  "geometry": {"coordinates":[-122.648432,47.345673],"type":"Point"}
}