{
  "type": "Feature",
  "properties": {
    "addr:full":"12601 Eagle Dr Burlington WA 98233",
    "addr:postcode":"12601;98233",
    "addr:street":"Eagle Dr",
    "iso:country":"US",
    "sg:address":"12601 Eagle Dr",
    "sg:city":"Burlington",
    "sg:classifiers":[
        {
            "category":"Building & Trades",
            "subcategory":"Equipment Rental",
            "type":"Services"
        }
    ],
    "sg:phone":"+1 360 757 1743",
    "sg:postcode":"98233",
    "sg:province":"WA",
    "wof:name":"P & H Leasing",
    "wof:placetype":"venue"
},
  "geometry": {"coordinates":[-122.390074,48.46406],"type":"Point"}
}