{
  "type": "Feature",
  "properties": {
    "addr:full":"17118 SE 328th St Auburn WA 98092",
    "addr:postcode":"17118;98092",
    "addr:street":"Se 328Th St",
    "iso:country":"US",
    "sg:address":"17118 SE 328th St",
    "sg:city":"Auburn",
    "sg:classifiers":[
        {
            "category":"Building & Trades",
            "subcategory":"Construction",
            "type":"Services"
        }
    ],
    "sg:phone":"+1 253 931 1278",
    "sg:postcode":"98092",
    "sg:province":"WA",
    "sg:tags":[
        "residential",
        "general",
        "commercial",
        "contractor"
    ],
    "wof:name":"Mto Construction Inc",
    "wof:placetype":"venue"
},
  "geometry": {"coordinates":[-122.113451,47.307783],"type":"Point"}
}