{
  "type": "Feature",
  "properties": {
    "addr:full":"17009 NE 105th St Redmond WA 98052",
    "addr:housenumber":"17009",
    "addr:postcode":"98052",
    "addr:street":"Ne 105Th St",
    "iso:country":"US",
    "sg:address":"17009 NE 105th St",
    "sg:city":"Redmond",
    "sg:classifiers":[
        {
            "category":"Professional",
            "subcategory":"Employment Agencies",
            "type":"Services"
        }
    ],
    "sg:phone":"+1 425 605 4751",
    "sg:postcode":"98052",
    "sg:province":"WA",
    "sg:tags":[
        "opportunity"
    ],
    "wof:name":"Mcintire Ventures",
    "wof:placetype":"venue"
},
  "geometry": {"coordinates":[-122.113168,47.694345],"type":"Point"}
}