{
  "type": "Feature",
  "properties": {
    "addr:full":"10011 E Montgomery Dr Spokane Valley WA 99206",
    "addr:housenumber":"10011",
    "addr:postcode":"99206",
    "addr:street":"E Montgomery Dr",
    "iso:country":"US",
    "sg:address":"10011 E Montgomery Dr",
    "sg:city":"Spokane Valley",
    "sg:classifiers":[
        {
            "category":"Manufacturing",
            "subcategory":"Tools & Machinery",
            "type":"Manufacturing & Wholesale Goods"
        }
    ],
    "sg:phone":"+1 509 922 7742",
    "sg:postcode":"99206",
    "sg:province":"WA",
    "sg:tags":[
        "machine",
        "shop"
    ],
    "sg:website":"www.mackaymfg.com",
    "wof:name":"Mac Kay Mfg",
    "wof:placetype":"venue"
},
  "geometry": {"coordinates":[-117.268868,47.679924],"type":"Point"}
}