{
  "type": "Feature",
  "properties": {
    "addr:full":"26805 165th Pl SE Kent WA 98042",
    "addr:housenumber":"26805",
    "addr:postcode":"98042",
    "addr:street":"165Th Pl Se",
    "iso:country":"US",
    "sg:address":"26805 165th Pl SE",
    "sg:city":"Kent",
    "sg:classifiers":[
        {
            "category":"Building & Trades",
            "subcategory":"Construction",
            "type":"Services"
        }
    ],
    "sg:phone":"+1 253 630 9405",
    "sg:postcode":"98042",
    "sg:province":"WA",
    "sg:tags":[
        "excavation",
        "contractor"
    ],
    "wof:name":"Penello & Sons",
    "wof:placetype":"venue"
},
  "geometry": {"coordinates":[-122.120931,47.361586],"type":"Point"}
}