{
  "type": "Feature",
  "properties": {
    "addr:full":"3520 S Pine St Tacoma WA 98409",
    "addr:housenumber":"3520",
    "addr:postcode":"98409",
    "addr:street":"S Pine St",
    "iso:country":"US",
    "sg:address":"3520 S Pine St",
    "sg:city":"Tacoma",
    "sg:classifiers":[
        {
            "category":"Manufacturing",
            "subcategory":"Printing",
            "type":"Manufacturing & Wholesale Goods"
        }
    ],
    "sg:phone":"+1 253 472 5500",
    "sg:postcode":"98409",
    "sg:province":"WA",
    "sg:tags":[
        "printer"
    ],
    "wof:name":"Cascade Print Media",
    "wof:placetype":"venue"
},
  "geometry": {"coordinates":[-122.47365000000001,47.226671],"type":"Point"}
}