{
  "type": "Feature",
  "properties": {
    "addr:full":"3803 NE 4th St Renton WA 98056",
    "addr:housenumber":"3803",
    "addr:postcode":"98056",
    "addr:street":"Ne 4Th St",
    "iso:country":"US",
    "sg:address":"3803 NE 4th St",
    "sg:city":"Renton",
    "sg:classifiers":[
        {
            "category":"Shopping",
            "subcategory":"Clothing, Apparel, & Fashions",
            "type":"Retail Goods"
        }
    ],
    "sg:phone":"+1 425 235 5494",
    "sg:postcode":"98056",
    "sg:province":"WA",
    "sg:tags":[
        "accessory",
        "clothing",
        "women's"
    ],
    "sg:website":"www.mjcfashion.com",
    "wof:name":"Mjc Fashion",
    "wof:placetype":"venue"
},
  "geometry": {"coordinates":[-122.168147,47.488453],"type":"Point"}
}