{
  "type": "Feature",
  "properties": {
    "addr:full":"6506 57th Dr NE Marysville WA 98270",
    "addr:housenumber":"6506",
    "addr:postcode":"98270",
    "addr:street":"57Th Dr Ne",
    "iso:country":"US",
    "sg:address":"6506 57th Dr NE",
    "sg:city":"Marysville",
    "sg:classifiers":[
        {
            "category":"Professional",
            "subcategory":"Computer Services",
            "type":"Services"
        }
    ],
    "sg:phone":"+1 425 343 3799",
    "sg:postcode":"98270",
    "sg:province":"WA",
    "sg:tags":[
        "related"
    ],
    "wof:name":"Kevin Beegle",
    "wof:placetype":"venue"
},
  "geometry": {"coordinates":[-122.155269,48.054529],"type":"Point"}
}