{
  "type": "Feature",
  "properties": {
    "addr:full":"23444 30th Ave S Kent WA 98032",
    "addr:housenumber":"23444",
    "addr:postcode":"98032",
    "addr:street":"30Th Ave S",
    "iso:country":"US",
    "sg:address":"23444 30th Ave S",
    "sg:city":"Kent",
    "sg:classifiers":[
        {
            "category":"Retail",
            "subcategory":"Repair Shop",
            "type":"Services"
        }
    ],
    "sg:phone":"+1 206 878 3750",
    "sg:postcode":"98032",
    "sg:province":"WA",
    "sg:tags":[
        "merchandise"
    ],
    "sg:website":"www.daywireless.com",
    "wof:name":"Day Wireless Systems",
    "wof:placetype":"venue"
},
  "geometry": {"coordinates":[-122.29327600000001,47.392341],"type":"Point"}
}