{
  "type": "Feature",
  "properties": {
    "addr:full":"200 W Mercer St Seattle WA 98119",
    "addr:housenumber":"200",
    "addr:postcode":"98119",
    "addr:street":"W Mercer St",
    "iso:country":"US",
    "sg:address":"200 W Mercer St",
    "sg:city":"Seattle",
    "sg:classifiers":[
        {
            "category":"Insurance",
            "subcategory":"Insurance Agent",
            "type":"Services"
        }
    ],
    "sg:phone":"+1 206 623 0856",
    "sg:postcode":"98119",
    "sg:province":"WA",
    "wof:name":"Reliance Standard Lf Insur Co",
    "wof:placetype":"venue"
},
  "geometry": {"coordinates":[-122.36063,47.624596],"type":"Point"}
}