{
  "type": "Feature",
  "properties": {
    "addr:full":"14150 NE 20th St Bellevue WA 98007",
    "addr:housenumber":"14150",
    "addr:postcode":"98007",
    "addr:street":"Ne 20Th St",
    "iso:country":"US",
    "sg:address":"14150 NE 20th St",
    "sg:city":"Bellevue",
    "sg:classifiers":[
        {
            "category":"Personal",
            "type":"Services"
        }
    ],
    "sg:phone":"+1 425 562 3060",
    "sg:postcode":"98007",
    "sg:province":"WA",
    "sg:tags":[
        "control",
        "weight"
    ],
    "wof:name":"Jenny Craig Weight Loss Ctr",
    "wof:placetype":"venue"
},
  "geometry": {"coordinates":[-122.143553,47.627944],"type":"Point"}
}