{
  "type": "Feature",
  "properties": {
    "addr:full":"13833 W Snoqualmie Valley Rd NE Duvall WA 98019",
    "addr:housenumber":"13833",
    "addr:postcode":"98019",
    "addr:street":"W Snoqualmie Valley Rd Ne",
    "iso:country":"US",
    "sg:address":"13833 W Snoqualmie Valley Rd NE",
    "sg:city":"Duvall",
    "sg:classifiers":[
        {
            "category":"Building & Trades",
            "subcategory":"Construction",
            "type":"Services"
        }
    ],
    "sg:phone":"+1 425 844 2120",
    "sg:postcode":"98019",
    "sg:province":"WA",
    "sg:tags":[
        "demolition",
        "contractor"
    ],
    "wof:name":"J & B Demolition",
    "wof:placetype":"venue"
},
  "geometry": {"coordinates":[-122.00908800000001,47.721799],"type":"Point"}
}