{
  "type": "Feature",
  "properties": {
    "addr:full":"12812 Ridge Cir E Sumner WA 98391",
    "addr:housenumber":"12812",
    "addr:postcode":"98391",
    "addr:street":"Ridge Cir E",
    "iso:country":"US",
    "sg:address":"12812 Ridge Cir E",
    "sg:city":"Sumner",
    "sg:classifiers":[
        {
            "category":"Professional",
            "type":"Services"
        }
    ],
    "sg:phone":"+1 360 897 8041",
    "sg:postcode":"98391",
    "sg:province":"WA",
    "wof:name":"Jacob V Hendrickson",
    "wof:placetype":"venue"
},
  "geometry": {"coordinates":[-122.14121,47.138039],"type":"Point"}
}