{
  "type": "Feature",
  "properties": {
    "addr:full":"10823 206th St SE Snohomish WA 98296",
    "addr:housenumber":"10823",
    "addr:postcode":"98296",
    "addr:street":"206Th St Se",
    "iso:country":"US",
    "sg:address":"10823 206th St SE",
    "sg:city":"Snohomish",
    "sg:classifiers":[
        {
            "category":"Professional",
            "subcategory":"Business Services",
            "type":"Services"
        }
    ],
    "sg:phone":"+1 425 876 8075",
    "sg:postcode":"98296",
    "sg:province":"WA",
    "sg:tags":[
        "pharmaceutical",
        "broker"
    ],
    "wof:name":"Millenium Pharmaceuticals LLC",
    "wof:placetype":"venue"
},
  "geometry": {"coordinates":[-122.085207,47.81015],"type":"Point"}
}