{
  "type": "Feature",
  "properties": {
    "addr:full":"1523 Willeys Lake Rd Ferndale WA 98248",
    "addr:housenumber":"1523",
    "addr:postcode":"98248",
    "addr:street":"Willeys Lake Rd",
    "iso:country":"US",
    "sg:address":"1523 Willeys Lake Rd",
    "sg:city":"Ferndale",
    "sg:classifiers":[
        {
            "category":"Manufacturing",
            "subcategory":"Tools & Machinery",
            "type":"Manufacturing & Wholesale Goods"
        }
    ],
    "sg:phone":"+1 360 380 1074",
    "sg:postcode":"98248",
    "sg:province":"WA",
    "sg:tags":[
        "industrial",
        "mfg"
    ],
    "wof:name":"Van Fleet Precision",
    "wof:placetype":"venue"
},
  "geometry": {"coordinates":[-122.572712,48.920593],"type":"Point"}
}