{
  "type": "Feature",
  "properties": {
    "addr:full":"250 N Mission St Wenatchee WA 98801",
    "addr:housenumber":"250",
    "addr:postcode":"98801",
    "addr:street":"N Mission St",
    "iso:country":"US",
    "sg:address":"250 N Mission St",
    "sg:city":"Wenatchee",
    "sg:classifiers":[
        {
            "category":"Banks & Credit Unions",
            "subcategory":"Investment Brokerage",
            "type":"Services"
        }
    ],
    "sg:phone":"+1 509 663 3565",
    "sg:postcode":"98801",
    "sg:province":"WA",
    "sg:tags":[
        "advisory",
        "consulting",
        "management"
    ],
    "wof:name":"American Express",
    "wof:placetype":"venue"
},
  "geometry": {"coordinates":[-120.31552600000001,47.427537],"type":"Point"}
}