{
  "type": "Feature",
  "properties": {
    "addr:full":"601 106th Ave NE Bellevue WA 98004",
    "addr:housenumber":"601",
    "addr:postcode":"98004",
    "addr:street":"106Th Ave Ne",
    "iso:country":"US",
    "sg:address":"601 106th Ave NE",
    "sg:city":"Bellevue",
    "sg:classifiers":[
        {
            "category":"Shopping",
            "subcategory":"Computers & Home Electronics",
            "type":"Retail Goods"
        }
    ],
    "sg:phone":"+1 425 688 0029",
    "sg:postcode":"98004",
    "sg:province":"WA",
    "sg:tags":[
        "equipment",
        "electronic",
        "supply"
    ],
    "wof:name":"Good Guys",
    "wof:placetype":"venue"
},
  "geometry": {"coordinates":[-122.198995,47.617416],"type":"Point"}
}