{
  "type": "Feature",
  "properties": {
    "addr:full":"405 W Walnut St Newport WA 99156",
    "addr:housenumber":"405",
    "addr:postcode":"99156",
    "addr:street":"W Walnut St",
    "iso:country":"US",
    "sg:address":"405 W Walnut St",
    "sg:city":"Newport",
    "sg:classifiers":[
        {
            "category":"Social Services",
            "type":"Services"
        }
    ],
    "sg:phone":"+1 509 447 5607",
    "sg:postcode":"99156",
    "sg:province":"WA",
    "sg:tags":[
        "counseling"
    ],
    "wof:name":"Counseling Associates",
    "wof:placetype":"venue"
},
  "geometry": {"coordinates":[-117.045377,48.183942],"type":"Point"}
}