{
  "type": "Feature",
  "properties": {
    "addr:full":"2470 Westlake Ave N Suite A Seattle WA 98109",
    "addr:housenumber":"2470",
    "addr:postcode":"98109",
    "addr:street":"Westlake Ave N Suite A",
    "iso:country":"US",
    "sg:address":"2470 Westlake Ave N Suite A",
    "sg:city":"Seattle",
    "sg:classifiers":[
        {
            "category":"Building & Trades",
            "subcategory":"Construction",
            "type":"Services"
        },
        {
            "category":"Real Estate",
            "subcategory":"Architect",
            "type":"Services"
        }
    ],
    "sg:phone":"+1 206 352 9248",
    "sg:postcode":"98109",
    "sg:province":"WA",
    "sg:tags":[
        "contractor"
    ],
    "sg:website":"www.planone.biz",
    "wof:name":"Plan One",
    "wof:placetype":"venue"
},
  "geometry": {"coordinates":[-122.343895,47.64288],"type":"Point"}
}