{
  "type": "Feature",
  "properties": {
    "addr:full":"302 E 3rd St Arlington WA 98223",
    "addr:housenumber":"302",
    "addr:postcode":"98223",
    "addr:street":"E 3Rd St",
    "iso:country":"US",
    "sg:address":"302 E 3rd St",
    "sg:city":"Arlington",
    "sg:classifiers":[
        {
            "category":"Health Services",
            "subcategory":"Doctor",
            "type":"Services"
        }
    ],
    "sg:phone":"+1 360 435 2764",
    "sg:postcode":"98223",
    "sg:province":"WA",
    "sg:tags":[
        "dentist"
    ],
    "wof:name":"Paul E Kulits DDS",
    "wof:placetype":"venue"
},
  "geometry": {"coordinates":[-122.12390600000001,48.194771],"type":"Point"}
}