{
  "type": "Feature",
  "properties": {
    "addr:full":"5025 Issaquah-Pine Lake Rd SE Issaquah WA 98029",
    "addr:housenumber":"5025",
    "addr:postcode":"98029",
    "addr:street":"Issaquah-Pine Lake Rd Se",
    "iso:country":"US",
    "sg:address":"5025 Issaquah-Pine Lake Rd SE",
    "sg:city":"Issaquah",
    "sg:classifiers":[
        {
            "category":"Travel",
            "subcategory":"Campground",
            "type":"Entertainment"
        }
    ],
    "sg:phone":"+1 425 427 0740",
    "sg:postcode":"98029",
    "sg:province":"WA",
    "sg:tags":[
        "camp"
    ],
    "wof:name":"Royal Fmly Kids Camp Issaquah",
    "wof:placetype":"venue"
},
  "geometry": {"coordinates":[-122.02245499999999,47.556337],"type":"Point"}
}