{
  "type": "Feature",
  "properties": {
    "addr:full":"3708 E Central Ave Spokane WA 99217",
    "addr:housenumber":"3708",
    "addr:postcode":"99217",
    "addr:street":"E Central Ave",
    "iso:country":"US",
    "sg:address":"3708 E Central Ave",
    "sg:city":"Spokane",
    "sg:classifiers":[
        {
            "category":"Retail",
            "subcategory":"Auto Repair",
            "type":"Services"
        }
    ],
    "sg:phone":"+1 509 489 9372",
    "sg:postcode":"99217",
    "sg:province":"WA",
    "sg:tags":[
        "body",
        "automobile",
        "painting"
    ],
    "wof:name":"Stromberg's Body & Paint",
    "wof:placetype":"venue"
},
  "geometry": {"coordinates":[-117.354122,47.711138],"type":"Point"}
}