{
  "type": "Feature",
  "properties": {
    "addr:full":"5326 Roosevelt Way NE Seattle WA 98105",
    "addr:housenumber":"5326",
    "addr:postcode":"98105",
    "addr:street":"Roosevelt Way Ne",
    "iso:country":"US",
    "sg:address":"5326 Roosevelt Way NE",
    "sg:city":"Seattle",
    "sg:classifiers":[
        {
            "category":"Retail",
            "subcategory":"Auto Rental",
            "type":"Services"
        }
    ],
    "sg:phone":"+1 206 729 4580",
    "sg:postcode":"98105",
    "sg:province":"WA",
    "sg:tags":[
        "car"
    ],
    "sg:website":"www.enterprise.com",
    "wof:name":"Enterprise Rent-A-Car",
    "wof:placetype":"venue"
},
  "geometry": {"coordinates":[-122.31737200000001,47.66734],"type":"Point"}
}