{
  "type": "Feature",
  "properties": {
    "addr:full":"14012 SE 20th St Bellevue WA 98007",
    "addr:postcode":"14012;98007",
    "addr:street":"Se 20Th St",
    "iso:country":"US",
    "sg:address":"14012 SE 20th St",
    "sg:city":"Bellevue",
    "sg:classifiers":[
        {
            "category":"Professional",
            "subcategory":"Advertising",
            "type":"Services"
        }
    ],
    "sg:phone":"+1 425 644 6776",
    "sg:postcode":"98007",
    "sg:province":"WA",
    "sg:tags":[
        "coupon"
    ],
    "wof:name":"Coupon Deal Usa",
    "wof:placetype":"venue"
},
  "geometry": {"coordinates":[-122.152637,47.592382],"type":"Point"}
}