{
  "type": "Feature",
  "properties": {
    "addr:full":"13055 Corliss Ave N Seattle WA 98133",
    "addr:housenumber":"13055",
    "addr:postcode":"98133",
    "addr:street":"Corliss Ave N",
    "iso:country":"US",
    "sg:address":"13055 Corliss Ave N",
    "sg:city":"Seattle",
    "sg:classifiers":[
        {
            "category":"Building & Trades",
            "subcategory":"Construction",
            "type":"Services"
        }
    ],
    "sg:phone":"+1 206 364 7895",
    "sg:postcode":"98133",
    "sg:province":"WA",
    "sg:tags":[
        "hanging",
        "contractor"
    ],
    "wof:name":"Popeye Painting Co",
    "wof:placetype":"venue"
},
  "geometry": {"coordinates":[-122.331621,47.724675],"type":"Point"}
}