{
  "type": "Feature",
  "properties": {
    "iso:country":"US",
    "sg:address":"7410 147th Ave SE",
    "sg:city":"Snohomish",
    "sg:classifiers":[
        {
            "category":"Building & Trades",
            "subcategory":"Construction",
            "type":"Services"
        }
    ],
    "sg:phone":"+1 360 568 7792",
    "sg:postcode":"98290",
    "sg:province":"WA",
    "sg:tags":[
        "excavation",
        "contractor"
    ],
    "wof:name":"A1 Bulldozing",
    "wof:placetype":"venue"
},
  "geometry": {"coordinates":[-122.034221,47.929197],"type":"Point"}
}