{
  "type": "Feature",
  "properties": {
    "addr:full":"29716 28th Ave S Roy WA 98580",
    "addr:housenumber":"29716",
    "addr:postcode":"98580",
    "addr:street":"28Th Ave S Roy",
    "iso:country":"US",
    "sg:address":"29716 28th Ave S",
    "sg:city":"Roy",
    "sg:classifiers":[
        {
            "category":"Restaurant",
            "type":"Food & Drink"
        }
    ],
    "sg:phone":"+1 253 843 1353",
    "sg:postcode":"98580",
    "sg:province":"WA",
    "sg:tags":[
        "eating"
    ],
    "wof:name":"Maple Tree Farm",
    "wof:placetype":"venue"
},
  "geometry": {"coordinates":[-122.469306,46.984888],"type":"Point"}
}