{
  "type": "Feature",
  "properties": {
    "addr:full":"14635 9th Ave SW Burien WA 98166",
    "addr:housenumber":"14635",
    "addr:postcode":"98166",
    "addr:street":"9Th Ave Sw",
    "iso:country":"US",
    "sg:address":"14635 9th Ave SW",
    "sg:city":"Burien",
    "sg:classifiers":[
        {
            "category":"Sports & Exercise",
            "subcategory":"Gym",
            "type":"Entertainment"
        }
    ],
    "sg:phone":"+1 206 248 3800",
    "sg:postcode":"98166",
    "sg:province":"WA",
    "sg:website":"profitnessclubs.com/",
    "wof:name":"Pro Fitness",
    "wof:placetype":"venue"
},
  "geometry": {"coordinates":[-122.34614500000001,47.471268],"type":"Point"}
}