{
  "type": "Feature",
  "properties": {
    "addr:full":"9920 State Ave Marysville WA 98270",
    "addr:housenumber":"9920",
    "addr:postcode":"98270",
    "addr:street":"State Ave",
    "iso:country":"US",
    "sg:address":"9920 State Ave",
    "sg:city":"Marysville",
    "sg:classifiers":[
        {
            "category":"Banks & Credit Unions",
            "subcategory":"Bank",
            "type":"Services"
        }
    ],
    "sg:phone":"+1 360 651 0103",
    "sg:postcode":"98270",
    "sg:province":"WA",
    "sg:tags":[
        "loan",
        "real estate"
    ],
    "wof:name":"Guaranty Mortgage",
    "wof:placetype":"venue"
},
  "geometry": {"coordinates":[-122.172353,48.085168],"type":"Point"}
}