{
  "type": "Feature",
  "properties": {
    "addr:full":"430 E 25th St Ste 17 Tacoma WA 98421",
    "addr:housenumber":"430;17",
    "addr:postcode":"98421",
    "addr:street":"E 25Th St Ste",
    "iso:country":"US",
    "sg:address":"430 E 25th St Ste 17",
    "sg:city":"Tacoma",
    "sg:classifiers":[
        {
            "category":"Restaurant",
            "type":"Food & Drink"
        }
    ],
    "sg:phone":"+1 253 383 0911",
    "sg:postcode":"98421",
    "sg:province":"WA",
    "sg:tags":[
        "mexican"
    ],
    "wof:name":"Santa Fe Mexican Restaurant",
    "wof:placetype":"venue"
},
  "geometry": {"coordinates":[-122.428951,47.239698],"type":"Point"}
}