{
  "type": "Feature",
  "properties": {
    "addr:full":"10138 NE 64th St Kirkland WA 98033",
    "addr:housenumber":"10138",
    "addr:postcode":"98033",
    "addr:street":"Ne 64Th St",
    "iso:country":"US",
    "sg:address":"10138 NE 64th St",
    "sg:city":"Kirkland",
    "sg:classifiers":[
        {
            "category":"Real Estate",
            "subcategory":"Real Estate Operator",
            "type":"Services"
        }
    ],
    "sg:phone":"+1 425 827 7727",
    "sg:postcode":"98033",
    "sg:province":"WA",
    "sg:tags":[
        "building",
        "apartment"
    ],
    "wof:name":"Sunset Shores Apartments",
    "wof:placetype":"venue"
},
  "geometry": {"coordinates":[-122.205071,47.663859],"type":"Point"}
}