{
  "type": "Feature",
  "properties": {
    "addr:full":"10 NE Brookdale Ln Bremerton WA 98311",
    "addr:housenumber":"10",
    "addr:postcode":"98311",
    "addr:street":"Ne Brookdale Ln",
    "iso:country":"US",
    "sg:address":"10 NE Brookdale Ln",
    "sg:city":"Bremerton",
    "sg:classifiers":[
        {
            "category":"Communications",
            "subcategory":"Radio Station",
            "type":"Services"
        }
    ],
    "sg:phone":"+1 360 698 6647",
    "sg:postcode":"98311",
    "sg:province":"WA",
    "sg:tags":[
        "broadcast"
    ],
    "wof:name":"A Teachable Moment",
    "wof:placetype":"venue"
},
  "geometry": {"coordinates":[-122.649134,47.630758],"type":"Point"}
}