{
  "type": "Feature",
  "properties": {
    "addr:full":"2004 Wintler Dr Vancouver WA 98661",
    "addr:housenumber":"2004",
    "addr:postcode":"98661",
    "addr:street":"Wintler Dr",
    "iso:country":"US",
    "sg:address":"2004 Wintler Dr",
    "sg:city":"Vancouver",
    "sg:classifiers":[
        {
            "category":"Shopping",
            "subcategory":"Gifts & Souvenirs",
            "type":"Retail Goods"
        }
    ],
    "sg:phone":"+1 360 694 8030",
    "sg:postcode":"98661",
    "sg:province":"WA",
    "sg:tags":[
        "cards",
        "baseball"
    ],
    "wof:name":"Michael R Whisman",
    "wof:placetype":"venue"
},
  "geometry": {"coordinates":[-122.62305600000001,45.638795],"type":"Point"}
}