{
  "type": "Feature",
  "properties": {
    "addr:full":"1420 156th Ave NE, Suite S Bellevue WA 98008",
    "addr:housenumber":"1420",
    "addr:postcode":"98008",
    "addr:street":"156Th Ave Ne Suite S Bellevue",
    "iso:country":"US",
    "sg:address":"1420 156th Ave NE, Suite S",
    "sg:city":"Bellevue",
    "sg:classifiers":[
        {
            "category":"Insurance",
            "subcategory":"Hazard Insurance",
            "type":"Services"
        }
    ],
    "sg:phone":"+1 425 440 3993",
    "sg:postcode":"98008",
    "sg:province":"WA",
    "sg:website":"www.haykinsurance.com",
    "wof:name":"Hayk Tadevosyan State Farm Insurance Agency",
    "wof:placetype":"venue"
},
  "geometry": {"coordinates":[-122.131705,47.62276],"type":"Point"}
}