{
  "type": "Feature",
  "properties": {
    "addr:full":"5355 Homesteader Rd Deming WA 98244",
    "addr:postcode":"5355;98244",
    "addr:street":"Homesteader Rd",
    "iso:country":"US",
    "sg:address":"5355 Homesteader Rd",
    "sg:city":"Deming",
    "sg:classifiers":[
        {
            "category":"Retail",
            "subcategory":"Animal Services",
            "type":"Services"
        }
    ],
    "sg:phone":"+1 360 595 0114",
    "sg:postcode":"98244",
    "sg:province":"WA",
    "wof:name":"Boultons South Fork Kennels",
    "wof:placetype":"venue"
},
  "geometry": {"coordinates":[-122.199141,48.745953],"type":"Point"}
}