{
  "type": "Feature",
  "properties": {
    "addr:full":"712 Clark Rd Sequim WA 98382",
    "addr:housenumber":"712",
    "addr:postcode":"98382",
    "addr:street":"Clark Rd",
    "iso:country":"US",
    "sg:address":"712 Clark Rd",
    "sg:city":"Sequim",
    "sg:classifiers":[
        {
            "category":"Building & Trades",
            "subcategory":"Construction",
            "type":"Services"
        }
    ],
    "sg:phone":"+1 360 683 0623",
    "sg:postcode":"98382",
    "sg:province":"WA",
    "sg:tags":[
        "carpentry",
        "contractor"
    ],
    "wof:name":"Wolfe Woodworks",
    "wof:placetype":"venue"
},
  "geometry": {"coordinates":[-123.151331,48.147339],"type":"Point"}
}