{
  "type": "Feature",
  "properties": {
    "addr:full":"6110 145th Pl SE Bellevue WA 98006",
    "addr:housenumber":"6110",
    "addr:postcode":"98006",
    "addr:street":"145Th Pl Se",
    "iso:country":"US",
    "sg:address":"6110 145th Pl SE",
    "sg:city":"Bellevue",
    "sg:classifiers":[
        {
            "category":"Professional",
            "subcategory":"Management & Consulting",
            "type":"Services"
        }
    ],
    "sg:phone":"+1 425 562 0756",
    "sg:postcode":"98006",
    "sg:province":"WA",
    "sg:tags":[
        "business"
    ],
    "wof:name":"Decision Risk Management Inc",
    "wof:placetype":"venue"
},
  "geometry": {"coordinates":[-122.147036,47.54801],"type":"Point"}
}