{
  "type": "Feature",
  "properties": {
    "addr:full":"204 111th Ave NE Bellevue WA 98004",
    "addr:housenumber":"204",
    "addr:postcode":"98004",
    "addr:street":"111Th Ave Ne",
    "iso:country":"US",
    "sg:address":"204 111th Ave NE",
    "sg:city":"Bellevue",
    "sg:classifiers":[
        {
            "category":"Building & Trades",
            "subcategory":"Landscaping Services",
            "type":"Services"
        }
    ],
    "sg:phone":"+1 425 454 5723",
    "sg:postcode":"98004",
    "sg:province":"WA",
    "sg:tags":[
        "designer",
        "landscape"
    ],
    "sg:website":"www.jgm-inc.com",
    "wof:name":"JGM/Jongejan/Gerrand/Mc Neal",
    "wof:placetype":"venue"
},
  "geometry": {"coordinates":[-122.19223700000001,47.612362],"type":"Point"}
}