{
  "type": "Feature",
  "properties": {
    "addr:full":"19112 Pioneer Way E Orting WA 98360",
    "addr:housenumber":"19112",
    "addr:postcode":"98360",
    "addr:street":"Pioneer Way E",
    "iso:country":"US",
    "sg:address":"19112 Pioneer Way E",
    "sg:city":"Orting",
    "sg:classifiers":[
        {
            "category":"Farming",
            "subcategory":"Fish & Marine Products",
            "type":"Manufacturing & Wholesale Goods"
        }
    ],
    "sg:phone":"+1 360 893 6440",
    "sg:postcode":"98360",
    "sg:province":"WA",
    "sg:tags":[
        "hatchery"
    ],
    "wof:name":"Voights Creek Hatchery",
    "wof:placetype":"venue"
},
  "geometry": {"coordinates":[-122.176011,47.082729],"type":"Point"}
}