{
  "type": "Feature",
  "properties": {
    "addr:full":"423 E 31st St Bremerton WA 98310",
    "addr:housenumber":"423",
    "addr:postcode":"98310",
    "addr:street":"E 31St St",
    "iso:country":"US",
    "sg:address":"423 E 31st St",
    "sg:city":"Bremerton",
    "sg:classifiers":[
        {
            "category":"Professional",
            "subcategory":"Computer Services",
            "type":"Services"
        }
    ],
    "sg:phone":"+1 360 649 4596",
    "sg:postcode":"98310",
    "sg:province":"WA",
    "sg:tags":[
        "datum"
    ],
    "wof:name":"Timber Wolf Developers",
    "wof:placetype":"venue"
},
  "geometry": {"coordinates":[-122.64143799999999,47.591422],"type":"Point"}
}