{
  "type": "Feature",
  "properties": {
    "addr:full":"2838 Lyle St Bellingham WA 98225",
    "addr:housenumber":"2838",
    "addr:postcode":"98225",
    "addr:street":"Lyle St",
    "iso:country":"US",
    "sg:address":"2838 Lyle St",
    "sg:city":"Bellingham",
    "sg:classifiers":[
        {
            "category":"Building & Trades",
            "subcategory":"Cleaning & Sanitation",
            "type":"Services"
        }
    ],
    "sg:phone":"+1 360 671 6758",
    "sg:postcode":"98225",
    "sg:province":"WA",
    "sg:tags":[
        "maintenance"
    ],
    "wof:name":"Sound Cleaning Services",
    "wof:placetype":"venue"
},
  "geometry": {"coordinates":[-122.473263,48.767514],"type":"Point"}
}