{
  "type": "Feature",
  "properties": {
    "addr:full":"15716 1st Ave S Seattle WA 98148",
    "addr:housenumber":"15716",
    "addr:postcode":"98148",
    "addr:street":"1St Ave S",
    "iso:country":"US",
    "sg:address":"15716 1st Ave S",
    "sg:city":"Seattle",
    "sg:classifiers":[
        {
            "category":"Shopping",
            "subcategory":"Pharmacy",
            "type":"Retail Goods"
        }
    ],
    "sg:phone":"+1 206 243 1500",
    "sg:postcode":"98148",
    "sg:province":"WA",
    "sg:tags":[
        "mai",
        "photofinishing",
        "direct",
        "laboratory"
    ],
    "wof:name":"Longs Drug Store",
    "wof:placetype":"venue"
},
  "geometry": {"coordinates":[-122.333844,47.462852],"type":"Point"}
}