{
  "type": "Feature",
  "properties": {
    "addr:full":"2125 1st Avenue Seattle WA 98121",
    "addr:housenumber":"2125",
    "addr:postcode":"98121",
    "addr:street":"1St Avenue",
    "iso:country":"US",
    "sg:address":"2125 1st Avenue",
    "sg:city":"Seattle",
    "sg:classifiers":[
        {
            "category":"Retail",
            "subcategory":"Event Space",
            "type":"Services"
        }
    ],
    "sg:phone":"+1 206 403 0754",
    "sg:postcode":"98121",
    "sg:province":"WA",
    "sg:tags":[
        "venue"
    ],
    "sg:website":"www.eVenues.com",
    "wof:name":"eVenues",
    "wof:placetype":"venue"
},
  "geometry": {"coordinates":[-122.344273,47.612045],"type":"Point"}
}