{
  "type": "Feature",
  "properties": {
    "addr:full":"2461 S Maiers Rd Moses Lake WA 98837",
    "addr:housenumber":"2461",
    "addr:postcode":"98837",
    "addr:street":"S Maiers Rd",
    "iso:country":"US",
    "sg:address":"2461 S Maiers Rd",
    "sg:city":"Moses Lake",
    "sg:classifiers":[
        {
            "category":"Restaurant",
            "type":"Food & Drink"
        }
    ],
    "sg:menulink":"http://www.allmenus.com/wa/moses-lake/218559-burger-king/menu/",
    "sg:phone":"+1 509 764 5183",
    "sg:postcode":"98837",
    "sg:province":"WA",
    "sg:tags":[
        "american"
    ],
    "wof:name":"Burger King",
    "wof:placetype":"venue"
},
  "geometry": {"coordinates":[-119.249674,47.102742],"type":"Point"}
}