{
  "type": "Feature",
  "properties": {
    "iso:country":"US",
    "sg:address":"15843 International Blvd",
    "sg:city":"Seatac",
    "sg:classifiers":[
        {
            "category":"Restaurant",
            "type":"Food & Drink"
        }
    ],
    "sg:phone":"+1 206 444 5000",
    "sg:postcode":"98188",
    "sg:province":"WA",
    "wof:name":"A Pizza Mart",
    "wof:placetype":"venue"
},
  "geometry": {"coordinates":[-122.29105800000001,47.461261],"type":"Point"}
}