{
  "type": "Feature",
  "properties": {
    "addr:full":"SE Mill Plain Blvd and 164th Ave Vancouver WA 98684",
    "addr:postcode":"98684",
    "addr:street":"Se Mill Plain Blvd And 164Th Ave",
    "iso:country":"US",
    "sg:address":"SE Mill Plain Blvd and 164th Ave",
    "sg:city":"Vancouver",
    "sg:classifiers":[
        {
            "category":"Food Court",
            "type":"Food & Drink"
        }
    ],
    "sg:postcode":"98684",
    "sg:province":"WA",
    "sg:tags":[
        "stand"
    ],
    "wof:name":"Vipayan",
    "wof:placetype":"venue"
},
  "geometry": {"coordinates":[-122.50439799999999,45.615557],"type":"Point"}
}