{
  "type": "Feature",
  "properties": {
    "addr:full":"13028 53rd Dr SE Everett WA 98208",
    "addr:housenumber":"13028",
    "addr:postcode":"98208",
    "addr:street":"53Rd Dr Se",
    "iso:country":"US",
    "sg:address":"13028 53rd Dr SE",
    "sg:city":"Everett",
    "sg:classifiers":[
        {
            "category":"Building & Trades",
            "subcategory":"Landscaping Services",
            "type":"Services"
        }
    ],
    "sg:phone":"+1 425 483 4698",
    "sg:postcode":"98208",
    "sg:province":"WA",
    "sg:tags":[
        "excavation",
        "utility",
        "contractor"
    ],
    "wof:name":"J W Trucking and Excavating",
    "wof:placetype":"venue"
},
  "geometry": {"coordinates":[-122.16004700000001,47.879157],"type":"Point"}
}