{
  "type": "Feature",
  "properties": {
    "addr:full":"8681 154th Ave NE Redmond WA 98052",
    "addr:housenumber":"8681",
    "addr:postcode":"98052",
    "addr:street":"154Th Ave Ne",
    "iso:country":"US",
    "sg:address":"8681 154th Ave NE",
    "sg:city":"Redmond",
    "sg:classifiers":[
        {
            "category":"Building & Trades",
            "subcategory":"Construction",
            "type":"Services"
        },
        {
            "category":"Home & Garden",
            "subcategory":"Household Appliances",
            "type":"Retail Goods"
        },
        {
            "category":"Retail",
            "subcategory":"Laundry & Dry Cleaning",
            "type":"Services"
        },
        {
            "category":"Home & Garden",
            "subcategory":"Carpets & Floor Coverings",
            "type":"Retail Goods"
        },
        {
            "category":"Manufacturing",
            "subcategory":"Tools & Machinery",
            "type":"Manufacturing & Wholesale Goods"
        },
        {
            "category":"Utilities",
            "subcategory":"Water",
            "type":"Services"
        },
        {
            "category":"Personal",
            "type":"Services"
        },
        {
            "category":"Building & Trades",
            "subcategory":"Cleaning & Sanitation",
            "type":"Services"
        }
    ],
    "sg:phone":"+1 425 867 5035",
    "sg:postcode":"98052",
    "sg:province":"WA",
    "sg:tags":[
        "control",
        "cleaner",
        "duct",
        "house",
        "mold",
        "janitorial",
        "site-clean-up",
        "equipment",
        "damage",
        "contractor",
        "extraction",
        "window",
        "cleaning-industrial",
        "curtain",
        "drapery",
        "counteracting",
        "emergency",
        "fire",
        "cleaners-water",
        "odor",
        "rug",
        "restoration",
        "vacuum",
        "remediation",
        "upholstery",
        "flood",
        "air",
        "waxing",
        "ventilation",
        "smoke",
        "polishing"
    ],
    "sg:website":"http://www.servicemasterclean.com/reslf/smclean_leadform.asp?url=http://www.servicemasterclean.com/reslf/smclean_leadform.asp&partnerName=YellowPages.com&adName=yptl&HGProp=SMClean",
    "wof:name":"ServiceMaster Clean",
    "wof:placetype":"venue"
},
  "geometry": {"coordinates":[-122.13468899999999,47.679895],"type":"Point"}
}