{
  "type": "Feature",
  "properties": {
    "addr:full":"360 W Bell St Sequim WA 98382",
    "addr:housenumber":"360",
    "addr:postcode":"98382",
    "addr:street":"W Bell St",
    "iso:country":"US",
    "sg:address":"360 W Bell St",
    "sg:city":"Sequim",
    "sg:classifiers":[
        {
            "category":"Health Services",
            "subcategory":"Health Practitioner",
            "type":"Services"
        }
    ],
    "sg:phone":"+1 360 683 8288",
    "sg:postcode":"98382",
    "sg:province":"WA",
    "sg:tags":[
        "psychologist"
    ],
    "wof:name":"Katherine Loveland",
    "wof:placetype":"venue"
},
  "geometry": {"coordinates":[-123.109146,48.078827],"type":"Point"}
}