{
  "type": "Feature",
  "properties": {
    "addr:full":"11835 184th Ave NE Redmond WA 98052",
    "addr:housenumber":"11835",
    "addr:postcode":"98052",
    "addr:street":"184Th Ave Ne",
    "iso:country":"US",
    "sg:address":"11835 184th Ave NE",
    "sg:city":"Redmond",
    "sg:classifiers":[
        {
            "category":"Manufacturing",
            "subcategory":"Signs",
            "type":"Manufacturing & Wholesale Goods"
        }
    ],
    "sg:phone":"+1 425 883 3093",
    "sg:postcode":"98052",
    "sg:province":"WA",
    "sg:tags":[
        "specialty",
        "mfg"
    ],
    "wof:name":"Fleetmark",
    "wof:placetype":"venue"
},
  "geometry": {"coordinates":[-122.094892,47.707517],"type":"Point"}
}