{
  "type": "Feature",
  "properties": {
    "addr:full":"4310 Colby Ave Everett WA 98203",
    "addr:housenumber":"4310",
    "addr:postcode":"98203",
    "addr:street":"Colby Ave",
    "iso:country":"US",
    "sg:address":"4310 Colby Ave",
    "sg:city":"Everett",
    "sg:classifiers":[
        {
            "category":"Health Services",
            "subcategory":"Doctor",
            "type":"Services"
        }
    ],
    "sg:phone":"+1 425 259 9111",
    "sg:postcode":"98203",
    "sg:province":"WA",
    "sg:tags":[
        "medical"
    ],
    "wof:name":"Stack Gary M MD Facs",
    "wof:placetype":"venue"
},
  "geometry": {"coordinates":[-122.207863,47.959554],"type":"Point"}
}