{
  "type": "Feature",
  "properties": {
    "addr:full":"22321 100th St SE Monroe WA 98272",
    "addr:housenumber":"22321",
    "addr:postcode":"98272",
    "addr:street":"100Th St Se",
    "iso:country":"US",
    "sg:address":"22321 100th St SE",
    "sg:city":"Monroe",
    "sg:classifiers":[
        {
            "category":"Wholesale",
            "subcategory":"Non-durable Goods",
            "type":"Manufacturing & Wholesale Goods"
        }
    ],
    "sg:phone":"+1 360 794 7177",
    "sg:postcode":"98272",
    "sg:province":"WA",
    "sg:tags":[
        "engineering"
    ],
    "wof:name":"Foster Enterprises",
    "wof:placetype":"venue"
},
  "geometry": {"coordinates":[-121.930004,47.90567],"type":"Point"}
}