{
  "type": "Feature",
  "properties": {
    "addr:full":"7040 38th Ave NE Seattle WA 98115",
    "addr:housenumber":"7040",
    "addr:postcode":"98115",
    "addr:street":"38Th Ave Ne",
    "iso:country":"US",
    "sg:address":"7040 38th Ave NE",
    "sg:city":"Seattle",
    "sg:classifiers":[
        {
            "category":"Education",
            "subcategory":"Special Training",
            "type":"Public Place"
        }
    ],
    "sg:phone":"+1 425 237 2332",
    "sg:postcode":"98115",
    "sg:province":"WA",
    "wof:name":"Robert L Guthrie CFI",
    "wof:placetype":"venue"
},
  "geometry": {"coordinates":[-122.287109,47.681003],"type":"Point"}
}