{
  "type": "Feature",
  "properties": {
    "addr:full":"701 Main St Vancouver WA 98660",
    "addr:housenumber":"701",
    "addr:postcode":"98660",
    "addr:street":"Main St",
    "iso:country":"US",
    "sg:address":"701 Main St",
    "sg:city":"Vancouver",
    "sg:classifiers":[
        {
            "category":"Coffee & Tea",
            "type":"Food & Drink"
        }
    ],
    "sg:phone":"+1 360 859 3133",
    "sg:postcode":"98660",
    "sg:province":"WA",
    "sg:website":"rivermaidencoffee.com/index.html",
    "wof:name":"River Maiden Coffee Bar",
    "wof:placetype":"venue"
},
  "geometry": {"coordinates":[-122.671423,45.626694],"type":"Point"}
}