{
  "type": "Feature",
  "properties": {
    "iso:country":"US",
    "sg:address":"8630 Evergreen Way",
    "sg:city":"Everett",
    "sg:classifiers":[
        {
            "category":"Shopping",
            "subcategory":"Gifts & Souvenirs",
            "type":"Retail Goods"
        }
    ],
    "sg:phone":"+1 425 348 9031",
    "sg:postcode":"98203",
    "sg:province":"WA",
    "sg:tags":[
        "party",
        "supply"
    ],
    "wof:name":"Party City",
    "wof:placetype":"venue"
},
  "geometry": {"coordinates":[-122.23088,47.919412],"type":"Point"}
}