{
  "type": "Feature",
  "properties": {
    "addr:full":"3050 SW Graham St Seattle WA 98126",
    "addr:housenumber":"3050",
    "addr:postcode":"98126",
    "addr:street":"Sw Graham St",
    "iso:country":"US",
    "sg:address":"3050 SW Graham St",
    "sg:city":"Seattle",
    "sg:classifiers":[
        {
            "category":"Wholesale",
            "subcategory":"Construction Materials",
            "type":"Manufacturing & Wholesale Goods"
        }
    ],
    "sg:phone":"+1 206 933 1395",
    "sg:postcode":"98126",
    "sg:province":"WA",
    "wof:name":"Finishers Drywall",
    "wof:placetype":"venue"
},
  "geometry": {"coordinates":[-122.371949,47.545569],"type":"Point"}
}