{
  "type": "Feature",
  "properties": {
    "addr:full":"410 Morrison St Clarkston WA 99403",
    "addr:housenumber":"410",
    "addr:postcode":"99403",
    "addr:street":"Morrison St",
    "iso:country":"US",
    "sg:address":"410 Morrison St",
    "sg:city":"Clarkston",
    "sg:classifiers":[
        {
            "category":"Retail",
            "subcategory":"Portrait Studio",
            "type":"Services"
        }
    ],
    "sg:phone":"+1 509 751 1527",
    "sg:postcode":"99403",
    "sg:province":"WA",
    "sg:tags":[
        "photo"
    ],
    "wof:name":"Indepndent Grphics Photography",
    "wof:placetype":"venue"
},
  "geometry": {"coordinates":[-117.057405,46.421554],"type":"Point"}
}