{
  "type": "Feature",
  "properties": {
    "addr:full":"17430 102nd Ave NE Bothell WA 98011",
    "addr:housenumber":"17430",
    "addr:postcode":"98011",
    "addr:street":"102Nd Ave Ne",
    "iso:country":"US",
    "sg:address":"17430 102nd Ave NE",
    "sg:city":"Bothell",
    "sg:classifiers":[
        {
            "category":"Health Services",
            "subcategory":"Chiropractor",
            "type":"Services"
        }
    ],
    "sg:phone":"+1 425 488 6647",
    "sg:postcode":"98011",
    "sg:province":"WA",
    "wof:name":"Gary G Bruner DC",
    "wof:placetype":"venue"
},
  "geometry": {"coordinates":[-122.204655,47.752791],"type":"Point"}
}