{
  "type": "Feature",
  "properties": {
    "iso:country":"US",
    "sg:address":"26012 95th Ave NW",
    "sg:city":"Stanwood",
    "sg:classifiers":[
        {
            "category":"Building & Trades",
            "subcategory":"Landscaping Services",
            "type":"Services"
        }
    ],
    "sg:phone":"+1 360 629 3218",
    "sg:postcode":"98292",
    "sg:province":"WA",
    "sg:tags":[
        "lawn",
        "mowing"
    ],
    "wof:name":"Cedar Home Lawn & Garden Svc",
    "wof:placetype":"venue"
},
  "geometry": {"coordinates":[-122.36162,48.234291],"type":"Point"}
}