{
  "type": "Feature",
  "properties": {
    "addr:full":"615 Lower Hogeye Rd Waitsburg WA 99361",
    "addr:housenumber":"615",
    "addr:postcode":"99361",
    "addr:street":"Lower Hogeye Rd",
    "iso:country":"US",
    "sg:address":"615 Lower Hogeye Rd",
    "sg:city":"Waitsburg",
    "sg:classifiers":[
        {
            "category":"Farming",
            "subcategory":"Farm",
            "type":"Manufacturing & Wholesale Goods"
        }
    ],
    "sg:phone":"+1 509 337 6469",
    "sg:postcode":"99361",
    "sg:province":"WA",
    "sg:tags":[
        "crop",
        "general"
    ],
    "wof:name":"R Ketcherside",
    "wof:placetype":"venue"
},
  "geometry": {"coordinates":[-118.096621,46.269307],"type":"Point"}
}