{
  "type": "Feature",
  "properties": {
    "addr:full":"16121 SE 42nd Pl Bellevue WA 98006",
    "addr:postcode":"16121;98006",
    "addr:street":"Se 42Nd Pl",
    "iso:country":"US",
    "sg:address":"16121 SE 42nd Pl",
    "sg:city":"Bellevue",
    "sg:classifiers":[
        {
            "category":"Home & Garden",
            "subcategory":"Building Materials",
            "type":"Retail Goods"
        },
        {
            "category":"Building & Trades",
            "subcategory":"Construction",
            "type":"Services"
        }
    ],
    "sg:phone":"+1 425 747 4662",
    "sg:postcode":"98006",
    "sg:province":"WA",
    "sg:tags":[
        "concrete",
        "staining",
        "contractor"
    ],
    "wof:name":"Eastside Construction And Conc",
    "wof:placetype":"venue"
},
  "geometry": {"coordinates":[-122.12473799999999,47.570263],"type":"Point"}
}