{
  "type": "Feature",
  "properties": {
    "addr:full":"7714 185th Ave E Sumner WA 98391",
    "addr:housenumber":"7714",
    "addr:postcode":"98391",
    "addr:street":"185Th Ave E",
    "iso:country":"US",
    "sg:address":"7714 185th Ave E",
    "sg:city":"Sumner",
    "sg:classifiers":[
        {
            "category":"Shopping",
            "subcategory":"Gifts & Souvenirs",
            "type":"Retail Goods"
        }
    ],
    "sg:phone":"+1 253 862 9019",
    "sg:postcode":"98391",
    "sg:province":"WA",
    "wof:name":"Handmade By Holly",
    "wof:placetype":"venue"
},
  "geometry": {"coordinates":[-122.182951,47.18794],"type":"Point"}
}