{
  "type": "Feature",
  "properties": {
    "addr:full":"310 S Mission St Wenatchee WA 98801",
    "addr:housenumber":"310",
    "addr:postcode":"98801",
    "addr:street":"S;St",
    "iso:country":"US",
    "sg:address":"310 S Mission St",
    "sg:city":"Wenatchee",
    "sg:classifiers":[
        {
            "category":"Health Services",
            "subcategory":"Health Practitioner",
            "type":"Services"
        }
    ],
    "sg:phone":"+1 509 663 2770",
    "sg:postcode":"98801",
    "sg:province":"WA",
    "sg:tags":[
        "midwife"
    ],
    "wof:name":"Wenatchee Midwife Svc & Ctr",
    "wof:placetype":"venue"
},
  "geometry": {"coordinates":[-120.308745,47.419331],"type":"Point"}
}