{
  "type": "Feature",
  "properties": {
    "iso:country":"US",
    "sg:address":"12907 74th Ave E",
    "sg:city":"Puyallup",
    "sg:classifiers":[
        {
            "category":"Manufacturing",
            "subcategory":"Tools & Machinery",
            "type":"Manufacturing & Wholesale Goods"
        }
    ],
    "sg:phone":"+1 253 535 0311",
    "sg:postcode":"98373",
    "sg:province":"WA",
    "sg:tags":[
        "equipment",
        "peripheral",
        "computer",
        "mfg"
    ],
    "wof:name":"Fox Innovations",
    "wof:placetype":"venue"
},
  "geometry": {"coordinates":[-122.33077400000001,47.140108],"type":"Point"}
}