{
  "type": "Feature",
  "properties": {
    "addr:full":"14916 Old Manor Way Lynnwood WA 98087",
    "addr:housenumber":"14916",
    "addr:postcode":"98087",
    "addr:street":"Old Manor Way",
    "iso:country":"US",
    "sg:address":"14916 Old Manor Way",
    "sg:city":"Lynnwood",
    "sg:classifiers":[
        {
            "category":"Personal",
            "subcategory":"Beauty Salon",
            "type":"Services"
        }
    ],
    "sg:phone":"+1 425 787 0824",
    "sg:postcode":"98087",
    "sg:province":"WA",
    "wof:name":"Leanne's Salon",
    "wof:placetype":"venue"
},
  "geometry": {"coordinates":[-122.269473,47.862559],"type":"Point"}
}