{
  "type": "Feature",
  "properties": {
    "addr:full":"600 University St # 2800 Seattle WA 98101",
    "addr:housenumber":"600",
    "addr:postcode":"98101",
    "addr:street":"University St # 2800",
    "iso:country":"US",
    "sg:address":"600 University St # 2800",
    "sg:city":"Seattle",
    "sg:classifiers":[
        {
            "category":"Banks & Credit Unions",
            "subcategory":"Investment Brokerage",
            "type":"Services"
        },
        {
            "category":"Banks & Credit Unions",
            "subcategory":"Financial Services",
            "type":"Services"
        }
    ],
    "sg:phone":"+1 206 623 1200",
    "sg:postcode":"98101",
    "sg:province":"WA",
    "sg:tags":[
        "advisory",
        "security"
    ],
    "sg:website":"http://www.broadmark.com",
    "wof:name":"Broadmark Capital Corp",
    "wof:placetype":"venue"
},
  "geometry": {"coordinates":[-122.332649,47.609138],"type":"Point"}
}