{
  "type": "Feature",
  "properties": {
    "addr:full":"11312 Fieldstone Ln NE Bainbridge Island WA 98110",
    "addr:housenumber":"11312",
    "addr:postcode":"98110",
    "addr:street":"Fieldstone Ln Ne",
    "iso:country":"US",
    "sg:address":"11312 Fieldstone Ln NE",
    "sg:city":"Bainbridge Island",
    "sg:classifiers":[
        {
            "category":"Professional",
            "subcategory":"Management & Consulting",
            "type":"Services"
        }
    ],
    "sg:phone":"+1 206 842 2452",
    "sg:postcode":"98110",
    "sg:province":"WA",
    "sg:tags":[
        "business"
    ],
    "wof:name":"Patricia M Ostenson Consultant",
    "wof:placetype":"venue"
},
  "geometry": {"coordinates":[-122.545193,47.666555],"type":"Point"}
}