{
  "type": "Feature",
  "properties": {
    "addr:full":"101 Pershing Ave Carbonado WA 98321",
    "addr:housenumber":"101",
    "addr:postcode":"98321",
    "addr:street":"Pershing Ave",
    "iso:country":"US",
    "sg:address":"101 Pershing Ave",
    "sg:city":"Carbonado",
    "sg:classifiers":[
        {
            "category":"Bars & Pubs",
            "type":"Food & Drink"
        }
    ],
    "sg:phone":"+1 360 829 9417",
    "sg:postcode":"98321",
    "sg:province":"WA",
    "wof:name":"Carbonado Tavern",
    "wof:placetype":"venue"
},
  "geometry": {"coordinates":[-122.054732,47.077341],"type":"Point"}
}