{
  "type": "Feature",
  "properties": {
    "addr:full":"11223 Bunk Foss Rd Snohomish WA 98290",
    "addr:postcode":"11223;98290",
    "addr:street":"Bunk Foss Rd",
    "iso:country":"US",
    "sg:address":"11223 Bunk Foss Rd",
    "sg:city":"Snohomish",
    "sg:classifiers":[
        {
            "category":"Shopping",
            "type":"Retail Goods"
        }
    ],
    "sg:phone":"+1 360 568 3245",
    "sg:postcode":"98290",
    "sg:province":"WA",
    "sg:tags":[
        "miscellaneous",
        "store"
    ],
    "wof:name":"Jennings Racing",
    "wof:placetype":"venue"
},
  "geometry": {"coordinates":[-122.081059,47.948832],"type":"Point"}
}