{
  "type": "Feature",
  "properties": {
    "addr:full":"619 E Pine St Seattle WA 98122",
    "addr:housenumber":"619",
    "addr:postcode":"98122",
    "addr:street":"E Pine St",
    "iso:country":"US",
    "sg:address":"619 E Pine St",
    "sg:city":"Seattle",
    "sg:classifiers":[
        {
            "category":"Recreation",
            "subcategory":"Dance Hall",
            "type":"Entertainment"
        }
    ],
    "sg:phone":"+1 206 322 8828",
    "sg:postcode":"98122",
    "sg:province":"WA",
    "sg:tags":[
        "club"
    ],
    "sg:website":"www.rplaceseattle.com/index.cfm",
    "wof:name":"R Place Bar & Grill",
    "wof:placetype":"venue"
},
  "geometry": {"coordinates":[-122.323567,47.615105],"type":"Point"}
}