{
  "type": "Feature",
  "properties": {
    "iso:country":"US",
    "sg:address":"7216 NE 109th Ave",
    "sg:city":"Vancouver",
    "sg:classifiers":[
        {
            "category":"Professional",
            "subcategory":"Management & Consulting",
            "type":"Services"
        }
    ],
    "sg:phone":"+1 360 944 1750",
    "sg:postcode":"98662",
    "sg:province":"WA",
    "sg:tags":[
        "engineering",
        "construction"
    ],
    "wof:name":"Skyline Engineering",
    "wof:placetype":"venue"
},
  "geometry": {"coordinates":[-122.56152299999999,45.675123],"type":"Point"}
}