{
  "type": "Feature",
  "properties": {
    "addr:full":"58 Union Ave Steilacoom WA 98388",
    "addr:housenumber":"58",
    "addr:postcode":"98388",
    "addr:street":"Union Ave",
    "iso:country":"US",
    "sg:address":"58 Union Ave",
    "sg:city":"Steilacoom",
    "sg:classifiers":[
        {
            "category":"Professional",
            "subcategory":"Engineering",
            "type":"Services"
        }
    ],
    "sg:phone":"+1 253 588 5290",
    "sg:postcode":"98388",
    "sg:province":"WA",
    "sg:tags":[
        "operations",
        "marine"
    ],
    "wof:name":"Pacific Navigation Co",
    "wof:placetype":"venue"
},
  "geometry": {"coordinates":[-122.60305099999999,47.171938],"type":"Point"}
}