{
  "type": "Feature",
  "properties": {
    "addr:full":"13503 SE Mill Plain Blvd Ste 108 Vancouver WA 98684",
    "addr:postcode":"13503;98684",
    "addr:street":"Se Mill Plain Blvd Ste 108",
    "iso:country":"US",
    "sg:address":"13503 SE Mill Plain Blvd Ste 108",
    "sg:city":"Vancouver",
    "sg:phone":"+1 360 883 1188",
    "sg:postcode":"98684",
    "sg:province":"WA",
    "sg:website":"http://www.baxterautoparts.com",
    "wof:name":"Baxter Auto Parts Inc",
    "wof:placetype":"venue"
},
  "geometry": {"coordinates":[-122.53360000000001,45.618737],"type":"Point"}
}