{
  "type": "Feature",
  "properties": {
    "addr:full":"209 NE 158th Ave Vancouver WA 98684",
    "addr:housenumber":"209",
    "addr:postcode":"98684",
    "addr:street":"Ne 158Th Ave",
    "iso:country":"US",
    "sg:address":"209 NE 158th Ave",
    "sg:city":"Vancouver",
    "sg:classifiers":[
        {
            "category":"Sports & Exercise",
            "subcategory":"Gym",
            "type":"Entertainment"
        }
    ],
    "sg:phone":"+1 360 566 5268",
    "sg:postcode":"98684",
    "sg:province":"WA",
    "sg:tags":[
        "trainer"
    ],
    "sg:website":"www.h2-fitness.com",
    "wof:name":"H2 Fitness",
    "wof:placetype":"venue"
},
  "geometry": {"coordinates":[-122.51042200000001,45.622576],"type":"Point"}
}