{
  "type": "Feature",
  "properties": {
    "addr:full":"363 101st Ave SE Bellevue WA 98004",
    "addr:housenumber":"363",
    "addr:postcode":"98004",
    "addr:street":"101St Ave Se",
    "iso:country":"US",
    "sg:address":"363 101st Ave SE",
    "sg:city":"Bellevue",
    "sg:classifiers":[
        {
            "category":"Professional",
            "type":"Services"
        }
    ],
    "sg:phone":"+1 425 453 9229",
    "sg:postcode":"98004",
    "sg:province":"WA",
    "wof:name":"62878",
    "wof:placetype":"venue"
},
  "geometry": {"coordinates":[-122.205564,47.606722],"type":"Point"}
}