{
  "type": "Feature",
  "properties": {
    "addr:full":"23109 NE 189th Ct Battle Ground WA 98604",
    "addr:housenumber":"23109",
    "addr:postcode":"98604",
    "addr:street":"Ne 189Th Ct",
    "iso:country":"US",
    "sg:address":"23109 NE 189th Ct",
    "sg:city":"Battle Ground",
    "sg:classifiers":[
        {
            "category":"Professional",
            "subcategory":"Lawyer & Legal Services",
            "type":"Services"
        }
    ],
    "sg:phone":"+1 360 687 6000",
    "sg:postcode":"98604",
    "sg:province":"WA",
    "wof:name":"Associated Insurance Cons",
    "wof:placetype":"venue"
},
  "geometry": {"coordinates":[-122.478663,45.792052],"type":"Point"}
}