{
  "type": "Feature",
  "properties": {
    "addr:full":"504 E Denny Way Seattle WA 98122",
    "addr:housenumber":"504",
    "addr:postcode":"98122",
    "addr:street":"E Denny Way",
    "iso:country":"US",
    "sg:address":"504 E Denny Way",
    "sg:city":"Seattle",
    "sg:classifiers":[
        {
            "category":"Professional",
            "type":"Services"
        }
    ],
    "sg:phone":"+1 206 323 3777",
    "sg:postcode":"98122",
    "sg:province":"WA",
    "wof:name":"Muck",
    "wof:placetype":"venue"
},
  "geometry": {"coordinates":[-122.32404699999999,47.618581],"type":"Point"}
}