{
  "type": "Feature",
  "properties": {
    "addr:full":"3238 Capitol Blvd S Olympia WA 98501",
    "addr:housenumber":"3238",
    "addr:postcode":"98501",
    "addr:street":"Capitol Blvd S",
    "iso:country":"US",
    "sg:address":"3238 Capitol Blvd S",
    "sg:city":"Olympia",
    "sg:classifiers":[
        {
            "category":"Restaurant",
            "type":"Food & Drink"
        }
    ],
    "sg:phone":"+1 360 943 5555",
    "sg:postcode":"98501",
    "sg:province":"WA",
    "sg:tags":[
        "delicatessen",
        "catering"
    ],
    "wof:name":"Urban Onion",
    "wof:placetype":"venue"
},
  "geometry": {"coordinates":[-122.89873299999999,47.019291],"type":"Point"}
}