{
  "type": "Feature",
  "properties": {
    "addr:full":"2735 California Ave SW Ste 120 Seattle WA 98116",
    "addr:housenumber":"2735",
    "addr:postcode":"98116",
    "addr:street":"California Ave Sw Ste 120",
    "iso:country":"US",
    "sg:address":"2735 California Ave SW Ste 120",
    "sg:city":"Seattle",
    "sg:classifiers":[
        {
            "category":"Coffee & Tea",
            "type":"Food & Drink"
        }
    ],
    "sg:phone":"+1 206 937 4316",
    "sg:postcode":"98116",
    "sg:province":"WA",
    "sg:website":"www.freshyscoffee.com",
    "wof:name":"Freshy's",
    "wof:placetype":"venue"
},
  "geometry": {"coordinates":[-122.38667599999999,47.578288],"type":"Point"}
}