{
  "type": "Feature",
  "properties": {
    "addr:full":"6737 Corson Ave S Seattle WA 98108",
    "addr:housenumber":"6737",
    "addr:postcode":"98108",
    "addr:street":"Corson Ave S",
    "iso:country":"US",
    "sg:address":"6737 Corson Ave S",
    "sg:city":"Seattle",
    "sg:classifiers":[
        {
            "category":"Building & Trades",
            "subcategory":"Locksmith",
            "type":"Services"
        }
    ],
    "sg:phone":"+1 206 607 0760",
    "sg:postcode":"98108",
    "sg:province":"WA",
    "sg:tags":[
        "key"
    ],
    "wof:name":"Abbe Locks 24 Locksmith",
    "wof:placetype":"venue"
},
  "geometry": {"coordinates":[-122.32328200000001,47.542388],"type":"Point"}
}