{
  "type": "Feature",
  "properties": {
    "addr:full":"2308 N Rd 44 Pasco WA 99301",
    "addr:housenumber":"2308;44",
    "addr:postcode":"99301",
    "addr:street":"N Rd",
    "iso:country":"US",
    "sg:address":"2308 N Rd 44",
    "sg:city":"Pasco",
    "sg:classifiers":[
        {
            "category":"Shopping",
            "subcategory":"Gifts & Souvenirs",
            "type":"Retail Goods"
        }
    ],
    "sg:phone":"+1 509 543 9051",
    "sg:postcode":"99301",
    "sg:province":"WA",
    "sg:tags":[
        "farm",
        "field",
        "crop"
    ],
    "wof:name":"Country Garden Farm",
    "wof:placetype":"venue"
},
  "geometry": {"coordinates":[-119.14840100000001,46.252354],"type":"Point"}
}