{
  "type": "Feature",
  "properties": {
    "addr:full":"101 S Parkway Ave Battle Ground WA 98604",
    "addr:housenumber":"101",
    "addr:postcode":"98604",
    "addr:street":"S Parkway Ave",
    "iso:country":"US",
    "sg:address":"101 S Parkway Ave",
    "sg:city":"Battle Ground",
    "sg:classifiers":[
        {
            "category":"Health Services",
            "subcategory":"Chiropractor",
            "type":"Services"
        }
    ],
    "sg:phone":"+1 360 687 8787",
    "sg:postcode":"98604",
    "sg:province":"WA",
    "wof:name":"Parkway Chiropractic & Massage",
    "wof:placetype":"venue"
},
  "geometry": {"coordinates":[-122.537323,45.780146],"type":"Point"}
}