{
  "type": "Feature",
  "properties": {
    "addr:full":"1130 Barnhart Rd Lynden WA 98264",
    "addr:housenumber":"1130",
    "addr:postcode":"98264",
    "addr:street":"Barnhart Rd",
    "iso:country":"US",
    "sg:address":"1130 Barnhart Rd",
    "sg:city":"Lynden",
    "sg:classifiers":[
        {
            "category":"Farming",
            "subcategory":"Farm",
            "type":"Manufacturing & Wholesale Goods"
        }
    ],
    "sg:phone":"+1 360 354 3077",
    "sg:postcode":"98264",
    "sg:province":"WA",
    "sg:tags":[
        "crop",
        "general"
    ],
    "wof:name":"Swede Hill Farm",
    "wof:placetype":"venue"
},
  "geometry": {"coordinates":[-122.544169,48.983248],"type":"Point"}
}