{
  "type": "Feature",
  "properties": {
    "addr:full":"730 Lateral 1 Rd Wapato WA 98951",
    "addr:housenumber":"730;1",
    "addr:postcode":"98951",
    "addr:street":"Lateral;Rd Wapato",
    "iso:country":"US",
    "sg:address":"730 Lateral 1 Rd",
    "sg:city":"Wapato",
    "sg:classifiers":[
        {
            "category":"Farming",
            "subcategory":"Orchard",
            "type":"Manufacturing & Wholesale Goods"
        }
    ],
    "sg:phone":"+1 509 877 4324",
    "sg:postcode":"98951",
    "sg:province":"WA",
    "sg:tags":[
        "grove",
        "management"
    ],
    "wof:name":"J & C Schibig Orchard",
    "wof:placetype":"venue"
},
  "geometry": {"coordinates":[-120.46098000000001,46.477306],"type":"Point"}
}