{
  "type": "Feature",
  "properties": {
    "addr:full":"22219 Mountain Hwy E Spanaway WA 98387",
    "addr:housenumber":"22219",
    "addr:postcode":"98387",
    "addr:street":"Mountain Hwy E",
    "iso:country":"US",
    "sg:address":"22219 Mountain Hwy E",
    "sg:city":"Spanaway",
    "sg:classifiers":[
        {
            "category":"Banks & Credit Unions",
            "subcategory":"Bank",
            "type":"Services"
        }
    ],
    "sg:phone":"+1 253 875 2811",
    "sg:postcode":"98387",
    "sg:province":"WA",
    "sg:tags":[
        "cashing",
        "check"
    ],
    "wof:name":"Allied Cash Advance",
    "wof:placetype":"venue"
},
  "geometry": {"coordinates":[-122.397974,47.053446],"type":"Point"}
}