{
  "type": "Feature",
  "properties": {
    "addr:full":"2801 Commercial Ave Anacortes WA 98221",
    "addr:housenumber":"2801",
    "addr:postcode":"98221",
    "addr:street":"Commercial Ave",
    "iso:country":"US",
    "sg:address":"2801 Commercial Ave",
    "sg:city":"Anacortes",
    "sg:classifiers":[
        {
            "category":"Banks & Credit Unions",
            "subcategory":"Bank",
            "type":"Services"
        }
    ],
    "sg:phone":"+1 360 299 0564",
    "sg:postcode":"98221",
    "sg:province":"WA",
    "sg:tags":[
        "loan",
        "real estate"
    ],
    "wof:name":"Alderwood Mortgage North",
    "wof:placetype":"venue"
},
  "geometry": {"coordinates":[-122.612784,48.499646],"type":"Point"}
}