{
  "type": "Feature",
  "properties": {
    "addr:full":"610 NE Colorado St Pullman WA 99163",
    "addr:housenumber":"610",
    "addr:postcode":"99163",
    "addr:street":"Ne Colorado St",
    "iso:country":"US",
    "sg:address":"610 NE Colorado St",
    "sg:city":"Pullman",
    "sg:classifiers":[
        {
            "category":"Organizations",
            "subcategory":"Community Association",
            "type":"Services"
        }
    ],
    "sg:phone":"+1 509 332 3261",
    "sg:postcode":"99163",
    "sg:province":"WA",
    "wof:name":"Sigma PHI Epsilon",
    "wof:placetype":"venue"
},
  "geometry": {"coordinates":[-117.17003699999999,46.733662],"type":"Point"}
}