{
  "type": "Feature",
  "properties": {
    "addr:full":"4201 SW Morgan St Seattle WA 98136",
    "addr:housenumber":"4201",
    "addr:postcode":"98136",
    "addr:street":"Sw Morgan St",
    "iso:country":"US",
    "sg:address":"4201 SW Morgan St",
    "sg:city":"Seattle",
    "sg:classifiers":[
        {
            "category":"Food & Beverages",
            "subcategory":"Groceries & Convenience Stores",
            "type":"Retail Goods"
        }
    ],
    "sg:phone":"+1 206 937 0245",
    "sg:postcode":"98136",
    "sg:province":"WA",
    "sg:website":"westseattlethriftway.com",
    "wof:name":"Thriftway",
    "wof:placetype":"venue"
},
  "geometry": {"coordinates":[-122.385801,47.544816],"type":"Point"}
}