{
  "type": "Feature",
  "properties": {
    "addr:full":"192 Nickerson St Seattle WA 98109",
    "addr:housenumber":"192",
    "addr:postcode":"98109",
    "addr:street":"Nickerson St",
    "iso:country":"US",
    "sg:address":"192 Nickerson St",
    "sg:city":"Seattle",
    "sg:classifiers":[
        {
            "category":"Wholesale",
            "subcategory":"Seafood",
            "type":"Manufacturing & Wholesale Goods"
        }
    ],
    "sg:phone":"+1 206 281 9040",
    "sg:postcode":"98109",
    "sg:province":"WA",
    "wof:name":"Talbot Seafood",
    "wof:placetype":"venue"
},
  "geometry": {"coordinates":[-122.353972,47.648302],"type":"Point"}
}