{
  "type": "Feature",
  "properties": {
    "addr:full":"9316 Clover Dr SE Olympia WA 98513",
    "addr:housenumber":"9316",
    "addr:postcode":"98513",
    "addr:street":"Clover Dr Se",
    "iso:country":"US",
    "sg:address":"9316 Clover Dr SE",
    "sg:city":"Olympia",
    "sg:classifiers":[
        {
            "category":"Manufacturing",
            "subcategory":"Textiles",
            "type":"Manufacturing & Wholesale Goods"
        }
    ],
    "sg:phone":"+1 360 491 9435",
    "sg:postcode":"98513",
    "sg:province":"WA",
    "sg:tags":[
        "mill",
        "fabric",
        "cotton"
    ],
    "wof:name":"Work Room",
    "wof:placetype":"venue"
},
  "geometry": {"coordinates":[-122.742029,47.04086],"type":"Point"}
}