{
  "type": "Feature",
  "properties": {
    "addr:full":"502 NE 134th St Vancouver WA 98685",
    "addr:housenumber":"502",
    "addr:postcode":"98685",
    "addr:street":"Ne 134Th St",
    "iso:country":"US",
    "sg:address":"502 NE 134th St",
    "sg:city":"Vancouver",
    "sg:classifiers":[
        {
            "category":"Wholesale",
            "subcategory":"Machinery & Supplies",
            "type":"Manufacturing & Wholesale Goods"
        }
    ],
    "sg:phone":"+1 360 546 0562",
    "sg:postcode":"98685",
    "sg:province":"WA",
    "sg:tags":[
        "equipment",
        "industrial"
    ],
    "wof:name":"Emerson Electric Co",
    "wof:placetype":"venue"
},
  "geometry": {"coordinates":[-122.666284,45.717925],"type":"Point"}
}