{
  "type": "Feature",
  "properties": {
    "addr:full":"104 E J St Shelton WA 98584",
    "addr:housenumber":"104",
    "addr:postcode":"98584",
    "addr:street":"E J St",
    "iso:country":"US",
    "sg:address":"104 E J St",
    "sg:city":"Shelton",
    "sg:classifiers":[
        {
            "category":"Retail",
            "subcategory":"Veterinary Services",
            "type":"Services"
        }
    ],
    "sg:phone":"+1 360 426 2616",
    "sg:postcode":"98584",
    "sg:province":"WA",
    "sg:tags":[
        "for",
        "animal",
        "specialty"
    ],
    "wof:name":"Shelton Veterinary Hospital",
    "wof:placetype":"venue"
},
  "geometry": {"coordinates":[-123.12140599999999,47.224967],"type":"Point"}
}