{
  "type": "Feature",
  "properties": {
    "addr:full":"12423 89th Ave E Puyallup WA 98373",
    "addr:housenumber":"12423",
    "addr:postcode":"98373",
    "addr:street":"89Th Ave E",
    "iso:country":"US",
    "sg:address":"12423 89th Ave E",
    "sg:city":"Puyallup",
    "sg:classifiers":[
        {
            "category":"Personal",
            "subcategory":"Beauty Salon",
            "type":"Services"
        }
    ],
    "sg:phone":"+1 253 841 8994",
    "sg:postcode":"98373",
    "sg:province":"WA",
    "sg:tags":[
        "shop"
    ],
    "wof:name":"Happy Hair Today Gone Tomorrow",
    "wof:placetype":"venue"
},
  "geometry": {"coordinates":[-122.310777,47.14405],"type":"Point"}
}