{
  "type": "Feature",
  "properties": {
    "addr:full":"95 B and O Rd Malott WA 98840",
    "addr:housenumber":"95",
    "addr:postcode":"98840",
    "addr:street":"B And O Rd",
    "iso:country":"US",
    "sg:address":"95 B and O Rd",
    "sg:city":"Malott",
    "sg:classifiers":[
        {
            "category":"Manufacturing",
            "subcategory":"Lumber",
            "type":"Manufacturing & Wholesale Goods"
        }
    ],
    "sg:phone":"+1 509 422 5054",
    "sg:postcode":"98840",
    "sg:province":"WA",
    "sg:tags":[
        "forestry"
    ],
    "wof:name":"Martin A Fudge",
    "wof:placetype":"venue"
},
  "geometry": {"coordinates":[-119.707272,48.293237],"type":"Point"}
}