{
  "type": "Feature",
  "properties": {
    "addr:full":"4613 Shincke Rd NE Olympia WA 98506",
    "addr:housenumber":"4613",
    "addr:postcode":"98506",
    "addr:street":"Shincke Rd Ne",
    "iso:country":"US",
    "sg:address":"4613 Shincke Rd NE",
    "sg:city":"Olympia",
    "sg:classifiers":[
        {
            "category":"Social Services",
            "type":"Services"
        }
    ],
    "sg:phone":"+1 360 456 6310",
    "sg:postcode":"98506",
    "sg:province":"WA",
    "wof:name":"Counseling Resources",
    "wof:placetype":"venue"
},
  "geometry": {"coordinates":[-122.84439500000001,47.110216],"type":"Point"}
}