{
  "type": "Feature",
  "properties": {
    "iso:country":"US",
    "sg:address":"4914 Blue Heron Blvd",
    "sg:city":"Richland",
    "sg:classifiers":[
        {
            "category":"Building & Trades",
            "subcategory":"Cleaning & Sanitation",
            "type":"Services"
        }
    ],
    "sg:phone":"+1 509 366 3966",
    "sg:postcode":"99353",
    "sg:province":"WA",
    "sg:tags":[
        "maintenance"
    ],
    "wof:name":"Thomas Janitorial",
    "wof:placetype":"venue"
},
  "geometry": {"coordinates":[-119.352541,46.279823],"type":"Point"}
}