{
  "type": "Feature",
  "properties": {
    "addr:full":"1333 5th Avenue Seattle WA 98101",
    "addr:housenumber":"1333",
    "addr:postcode":"98101",
    "addr:street":"5Th Avenue",
    "iso:country":"US",
    "sg:address":"1333 5th Avenue",
    "sg:city":"Seattle",
    "sg:classifiers":[
        {
            "category":"Arts & Performance",
            "subcategory":"Art Gallery",
            "type":"Entertainment"
        }
    ],
    "sg:phone":"+1 206 467 6951",
    "sg:postcode":"98101",
    "sg:province":"WA",
    "wof:name":"Jeffrey Moose Gallery",
    "wof:placetype":"venue"
},
  "geometry": {"coordinates":[-122.334081,47.609028],"type":"Point"}
}