{
  "type": "Feature",
  "properties": {
    "addr:full":"8340 132nd Ave NE Redmond WA 98052",
    "addr:housenumber":"8340",
    "addr:postcode":"98052",
    "addr:street":"132Nd Ave Ne",
    "iso:country":"US",
    "sg:address":"8340 132nd Ave NE",
    "sg:city":"Redmond",
    "sg:classifiers":[
        {
            "category":"Professional",
            "subcategory":"Management & Consulting",
            "type":"Services"
        }
    ],
    "sg:phone":"+1 425 881 5299",
    "sg:postcode":"98052",
    "sg:province":"WA",
    "wof:name":"Al Gugeler Financial Services",
    "wof:placetype":"venue"
},
  "geometry": {"coordinates":[-122.16399199999999,47.678788],"type":"Point"}
}