{
  "type": "Feature",
  "properties": {
    "addr:full":"154 E Wiser Lake Rd Lynden WA 98264",
    "addr:housenumber":"154",
    "addr:postcode":"98264",
    "addr:street":"E Wiser Lake Rd",
    "iso:country":"US",
    "sg:address":"154 E Wiser Lake Rd",
    "sg:city":"Lynden",
    "sg:classifiers":[
        {
            "category":"Shopping",
            "type":"Retail Goods"
        }
    ],
    "sg:phone":"+1 360 354 0807",
    "sg:postcode":"98264",
    "sg:province":"WA",
    "sg:tags":[
        "merchandise"
    ],
    "wof:name":"Candles By Taan",
    "wof:placetype":"venue"
},
  "geometry": {"coordinates":[-122.483963,48.906793],"type":"Point"}
}