{
  "type": "Feature",
  "properties": {
    "addr:full":"5306 Ballard Ave NW Seattle WA 98107",
    "addr:housenumber":"5306",
    "addr:postcode":"98107",
    "addr:street":"Ballard Ave Nw",
    "iso:country":"US",
    "sg:address":"5306 Ballard Ave NW",
    "sg:city":"Seattle",
    "sg:classifiers":[
        {
            "category":"Coffee & Tea",
            "type":"Food & Drink"
        }
    ],
    "sg:phone":"+1 206 784 2576",
    "sg:postcode":"98107",
    "sg:province":"WA",
    "wof:name":"Cugini Cafe",
    "wof:placetype":"venue"
},
  "geometry": {"coordinates":[-122.383259,47.666514],"type":"Point"}
}