{
  "type": "Feature",
  "properties": {
    "addr:full":"8620 180th Way SW Rochester WA 98579",
    "addr:housenumber":"8620",
    "addr:postcode":"98579",
    "addr:street":"180Th Way Sw",
    "iso:country":"US",
    "sg:address":"8620 180th Way SW",
    "sg:city":"Rochester",
    "sg:classifiers":[
        {
            "category":"Farming",
            "subcategory":"Farm",
            "type":"Manufacturing & Wholesale Goods"
        }
    ],
    "sg:phone":"+1 360 273 8788",
    "sg:postcode":"98579",
    "sg:province":"WA",
    "sg:tags":[
        "ornamental",
        "nursery",
        "crop",
        "general"
    ],
    "wof:name":"Happy Hen Farm Inc",
    "wof:placetype":"venue"
},
  "geometry": {"coordinates":[-123.063035,46.825753],"type":"Point"}
}