{
  "type": "Feature",
  "properties": {
    "addr:full":"5601 20th St E Tacoma WA 98424",
    "addr:housenumber":"5601",
    "addr:postcode":"98424",
    "addr:street":"20Th St",
    "iso:country":"US",
    "sg:address":"5601 20th St E",
    "sg:city":"Tacoma",
    "sg:classifiers":[
        {
            "category":"Freight",
            "type":"Transportation"
        }
    ],
    "sg:phone":"+1 253 922 8030",
    "sg:postcode":"98424",
    "sg:province":"WA",
    "sg:website":"www.fifeschools.com",
    "wof:name":"Fife Public Schls Trnsprtn",
    "wof:placetype":"venue"
},
  "geometry": {"coordinates":[-122.35351900000001,47.239023],"type":"Point"}
}