{
  "type": "Feature",
  "properties": {
    "addr:full":"3408 Rd N NE Moses Lake WA 98837",
    "addr:postcode":"3408;98837",
    "addr:street":"Rd N Ne",
    "iso:country":"US",
    "sg:address":"3408 Rd N NE",
    "sg:city":"Moses Lake",
    "sg:classifiers":[
        {
            "category":"Manufacturing",
            "subcategory":"Chemicals & Compounds",
            "type":"Manufacturing & Wholesale Goods"
        }
    ],
    "sg:phone":"+1 509 764 0923",
    "sg:postcode":"98837",
    "sg:province":"WA",
    "sg:tags":[
        "gas"
    ],
    "wof:name":"Air Products & Chemicals Inc",
    "wof:placetype":"venue"
},
  "geometry": {"coordinates":[-119.193096,47.143531],"type":"Point"}
}