{
  "type": "Feature",
  "properties": {
    "addr:full":"20015 120th Ave E Graham WA 98338",
    "addr:housenumber":"20015",
    "addr:postcode":"98338",
    "addr:street":"120Th Ave E",
    "iso:country":"US",
    "sg:address":"20015 120th Ave E",
    "sg:city":"Graham",
    "sg:classifiers":[
        {
            "category":"Professional",
            "subcategory":"Art Services",
            "type":"Services"
        }
    ],
    "sg:phone":"+1 253 210 4446",
    "sg:postcode":"98338",
    "sg:province":"WA",
    "sg:tags":[
        "designer",
        "display",
        "producer"
    ],
    "wof:name":"Aggressive Designs",
    "wof:placetype":"venue"
},
  "geometry": {"coordinates":[-122.27043,47.074419],"type":"Point"}
}