{
  "type": "Feature",
  "properties": {
    "addr:full":"2851 134th Ave NE Bellevue WA 98005",
    "addr:housenumber":"2851",
    "addr:postcode":"98005",
    "addr:street":"134Th Ave Ne",
    "iso:country":"US",
    "sg:address":"2851 134th Ave NE",
    "sg:city":"Bellevue",
    "sg:classifiers":[
        {
            "category":"Health Services",
            "subcategory":"Doctor",
            "type":"Services"
        }
    ],
    "sg:phone":"+1 425 883 0513",
    "sg:postcode":"98005",
    "sg:province":"WA",
    "wof:name":"Dunn John E MD",
    "wof:placetype":"venue"
},
  "geometry": {"coordinates":[-122.162003,47.636299],"type":"Point"}
}