{
  "type": "Feature",
  "properties": {
    "addr:full":"8545 Fletcher Bay Rd NE Bainbridge Isle WA 98110",
    "addr:housenumber":"8545",
    "addr:postcode":"98110",
    "addr:street":"Fletcher Bay Rd Ne;Isle",
    "iso:country":"US",
    "sg:address":"8545 Fletcher Bay Rd NE",
    "sg:city":"Bainbridge Isle",
    "sg:classifiers":[
        {
            "category":"Recreation",
            "type":"Entertainment"
        }
    ],
    "sg:phone":"+1 206 842 2235",
    "sg:postcode":"98110",
    "sg:province":"WA",
    "sg:tags":[
        "stable"
    ],
    "wof:name":"Immigrant Farms",
    "wof:placetype":"venue"
},
  "geometry": {"coordinates":[-122.564418,47.64217],"type":"Point"}
}