{
  "type": "Feature",
  "properties": {
    "addr:full":"228 Limestone Point Rd Friday Harbor WA 98250",
    "addr:housenumber":"228",
    "addr:postcode":"98250",
    "addr:street":"Limestone Point Rd",
    "iso:country":"US",
    "sg:address":"228 Limestone Point Rd",
    "sg:city":"Friday Harbor",
    "sg:classifiers":[
        {
            "category":"Building & Trades",
            "subcategory":"Construction",
            "type":"Services"
        }
    ],
    "sg:phone":"+1 360 378 5637",
    "sg:postcode":"98250",
    "sg:province":"WA",
    "sg:tags":[
        "woodworker"
    ],
    "wof:name":"FENLEYCO.COM",
    "wof:placetype":"venue"
},
  "geometry": {"coordinates":[-123.117271,48.61389],"type":"Point"}
}