{
  "type": "Feature",
  "properties": {
    "addr:full":"19924 97th Ave SE Snohomish WA 98296",
    "addr:housenumber":"19924",
    "addr:postcode":"98296",
    "addr:street":"97Th Ave Se",
    "iso:country":"US",
    "sg:address":"19924 97th Ave SE",
    "sg:city":"Snohomish",
    "sg:classifiers":[
        {
            "category":"Professional",
            "subcategory":"Management & Consulting",
            "type":"Services"
        }
    ],
    "sg:phone":"+1 425 486 6737",
    "sg:postcode":"98296",
    "sg:province":"WA",
    "sg:tags":[
        "public",
        "relations"
    ],
    "wof:name":"Cyclops Group",
    "wof:placetype":"venue"
},
  "geometry": {"coordinates":[-122.102509,47.816433],"type":"Point"}
}