{
  "type": "Feature",
  "properties": {
    "addr:full":"7424A Evergreen Way Everett WA 98203",
    "addr:housenumber":"7424a",
    "addr:postcode":"98203",
    "addr:street":"Evergreen Way",
    "iso:country":"US",
    "sg:address":"7424A Evergreen Way",
    "sg:city":"Everett",
    "sg:classifiers":[
        {
            "category":"Utilities",
            "subcategory":"Telephone",
            "type":"Services"
        },
        {
            "category":"Shopping",
            "subcategory":"Mobile Phones",
            "type":"Retail Goods"
        },
        {
            "category":"Manufacturing",
            "subcategory":"Electronics",
            "type":"Manufacturing & Wholesale Goods"
        },
        {
            "category":"Shopping",
            "subcategory":"Computers & Home Electronics",
            "type":"Retail Goods"
        },
        {
            "category":"Communications",
            "type":"Services"
        }
    ],
    "sg:phone":"+1 425 353 0020",
    "sg:postcode":"98203",
    "sg:province":"WA",
    "sg:tags":[
        "sound",
        "television",
        "theater",
        "supply",
        "system",
        "equipment",
        "radio",
        "cellular",
        "telecommunications-equipment",
        "consumer",
        "store"
    ],
    "sg:website":"http://www.radioshack.com",
    "wof:name":"RadioShack",
    "wof:placetype":"venue"
},
  "geometry": {"coordinates":[-122.22078399999999,47.930254],"type":"Point"}
}