{
  "type": "Feature",
  "properties": {
    "addr:full":"2822 Martin Luther King Jr Way Ste J Seattle WA 98144",
    "addr:housenumber":"2822",
    "addr:postcode":"98144",
    "addr:street":"Martin Luther King Jr Way Ste J",
    "iso:country":"US",
    "sg:address":"2822 Martin Luther King Jr Way Ste J",
    "sg:city":"Seattle",
    "sg:classifiers":[
        {
            "category":"Restaurant",
            "type":"Food & Drink"
        }
    ],
    "sg:phone":"+1 206 760 5775",
    "sg:postcode":"98144",
    "sg:province":"WA",
    "wof:name":"Pho Nuong",
    "wof:placetype":"venue"
},
  "geometry": {"coordinates":[-122.296221,47.578093],"type":"Point"}
}