{
  "type": "Feature",
  "properties": {
    "addr:full":"6824 NE 175th St Kenmore WA 98028",
    "addr:housenumber":"6824",
    "addr:postcode":"98028",
    "addr:street":"Ne 175Th St",
    "iso:country":"US",
    "sg:address":"6824 NE 175th St",
    "sg:city":"Kenmore",
    "sg:classifiers":[
        {
            "category":"Autos & Motor Vehicles",
            "subcategory":"Auto Supplies",
            "type":"Retail Goods"
        }
    ],
    "sg:phone":"+1 425 483 2071",
    "sg:postcode":"98028",
    "sg:province":"WA",
    "wof:name":"Skips American Car Care Ctr",
    "wof:placetype":"venue"
},
  "geometry": {"coordinates":[-122.24951299999999,47.757586],"type":"Point"}
}