{
  "type": "Feature",
  "properties": {
    "addr:full":"8621 Martin Way E Olympia WA 98516",
    "addr:housenumber":"8621",
    "addr:postcode":"98516",
    "addr:street":"Martin Way E",
    "iso:country":"US",
    "sg:address":"8621 Martin Way E",
    "sg:city":"Olympia",
    "sg:classifiers":[
        {
            "category":"Shopping",
            "subcategory":"Computers & Home Electronics",
            "type":"Retail Goods"
        }
    ],
    "sg:phone":"+1 360 413 7955",
    "sg:postcode":"98516",
    "sg:province":"WA",
    "sg:tags":[
        "sales"
    ],
    "wof:name":"Lcw",
    "wof:placetype":"venue"
},
  "geometry": {"coordinates":[-122.75509,47.058715],"type":"Point"}
}