{
  "type": "Feature",
  "properties": {
    "addr:full":"10518 NE Rosewood Ave Vancouver WA 98662",
    "addr:housenumber":"10518",
    "addr:postcode":"98662",
    "addr:street":"Ne Rosewood Ave",
    "iso:country":"US",
    "sg:address":"10518 NE Rosewood Ave",
    "sg:city":"Vancouver",
    "sg:classifiers":[
        {
            "category":"Shopping",
            "subcategory":"Jewelry",
            "type":"Retail Goods"
        }
    ],
    "sg:phone":"+1 360 944 7472",
    "sg:postcode":"98662",
    "sg:province":"WA",
    "wof:name":"Place In Time",
    "wof:placetype":"venue"
},
  "geometry": {"coordinates":[-122.563712,45.66605],"type":"Point"}
}