{
  "type": "Feature",
  "properties": {
    "addr:full":"9105 13th Pl SE Everett WA 98205",
    "addr:housenumber":"9105",
    "addr:postcode":"98205",
    "addr:street":"13Th Pl Se",
    "iso:country":"US",
    "sg:address":"9105 13th Pl SE",
    "sg:city":"Everett",
    "sg:classifiers":[
        {
            "category":"Organizations",
            "subcategory":"Religious Organization",
            "type":"Services"
        }
    ],
    "sg:phone":"+1 425 353 6960",
    "sg:postcode":"98205",
    "sg:province":"WA",
    "sg:tags":[
        "church"
    ],
    "wof:name":"Evergreen Christian Church",
    "wof:placetype":"venue"
},
  "geometry": {"coordinates":[-122.106841,47.983934],"type":"Point"}
}