{
  "type": "Feature",
  "properties": {
    "addr:full":"2604 W 18th St Port Angeles WA 98363",
    "addr:housenumber":"2604",
    "addr:postcode":"98363",
    "addr:street":"W 18Th St",
    "iso:country":"US",
    "sg:address":"2604 W 18th St",
    "sg:city":"Port Angeles",
    "sg:classifiers":[
        {
            "category":"Manufacturing",
            "subcategory":"Lumber",
            "type":"Manufacturing & Wholesale Goods"
        }
    ],
    "sg:phone":"+1 360 460 2833",
    "sg:postcode":"98363",
    "sg:province":"WA",
    "sg:tags":[
        "logging"
    ],
    "wof:name":"Logging",
    "wof:placetype":"venue"
},
  "geometry": {"coordinates":[-123.49887200000001,48.125337],"type":"Point"}
}