{
  "type": "Feature",
  "properties": {
    "addr:full":"6549 Fauntleroy Way SW Seattle WA 98136",
    "addr:housenumber":"6549",
    "addr:postcode":"98136",
    "addr:street":"Fauntleroy Way Sw",
    "iso:country":"US",
    "sg:address":"6549 Fauntleroy Way SW",
    "sg:city":"Seattle",
    "sg:classifiers":[
        {
            "category":"Personal",
            "type":"Services"
        },
        {
            "category":"Shopping",
            "subcategory":"Florist",
            "type":"Retail Goods"
        }
    ],
    "sg:phone":"+1 253 225 2152",
    "sg:postcode":"98136",
    "sg:province":"WA",
    "sg:tags":[
        "party",
        "planning",
        "event"
    ],
    "sg:website":"www.finchandthistleevents.com",
    "wof:name":"Finch and Thistle Event Design",
    "wof:placetype":"venue"
},
  "geometry": {"coordinates":[-122.38943399999999,47.544749],"type":"Point"}
}