{
  "type": "Feature",
  "properties": {
    "addr:full":"17110 NE 202nd Pl Woodinville WA 98072",
    "addr:housenumber":"17110",
    "addr:postcode":"98072",
    "addr:street":"Ne 202Nd Pl",
    "iso:country":"US",
    "sg:address":"17110 NE 202nd Pl",
    "sg:city":"Woodinville",
    "sg:classifiers":[
        {
            "category":"Professional",
            "subcategory":"Management & Consulting",
            "type":"Services"
        }
    ],
    "sg:phone":"+1 206 778 5358",
    "sg:postcode":"98072",
    "sg:province":"WA",
    "sg:tags":[
        "business"
    ],
    "wof:name":"Madden Mac Consulting LLC",
    "wof:placetype":"venue"
},
  "geometry": {"coordinates":[-122.11149,47.774353],"type":"Point"}
}