{
  "type": "Feature",
  "properties": {
    "iso:country":"US",
    "sg:address":"1704 Amber Blvd SE",
    "sg:city":"Puyallup",
    "sg:classifiers":[
        {
            "category":"Restaurant",
            "type":"Food & Drink"
        }
    ],
    "sg:phone":"+1 253 840 2713",
    "sg:postcode":"98372",
    "sg:province":"WA",
    "sg:tags":[
        "eating"
    ],
    "wof:name":"G&K Ice Creams",
    "wof:placetype":"venue"
},
  "geometry": {"coordinates":[-122.247866,47.17484],"type":"Point"}
}