{
  "type": "Feature",
  "properties": {
    "addr:full":"807 2nd Ave SW Quincy WA 98848",
    "addr:housenumber":"807",
    "addr:postcode":"98848",
    "addr:street":"2Nd Ave Sw",
    "iso:country":"US",
    "sg:address":"807 2nd Ave SW",
    "sg:city":"Quincy",
    "sg:classifiers":[
        {
            "category":"Food & Beverages",
            "subcategory":"Groceries & Convenience Stores",
            "type":"Retail Goods"
        }
    ],
    "sg:phone":"+1 509 787 4567",
    "sg:postcode":"98848",
    "sg:province":"WA",
    "wof:name":"Quincy Market",
    "wof:placetype":"venue"
},
  "geometry": {"coordinates":[-119.856557,47.232005],"type":"Point"}
}