{
  "type": "Feature",
  "properties": {
    "addr:full":"701 5th Ave Ste 4640 Seattle WA 98104",
    "addr:housenumber":"701",
    "addr:postcode":"98104",
    "addr:street":"5Th Ave Ste 4640",
    "iso:country":"US",
    "sg:address":"701 5th Ave Ste 4640",
    "sg:city":"Seattle",
    "sg:classifiers":[
        {
            "category":"Professional",
            "subcategory":"Management & Consulting",
            "type":"Services"
        },
        {
            "category":"Banks & Credit Unions",
            "subcategory":"Financial Services",
            "type":"Services"
        }
    ],
    "sg:phone":"+1 206 264 2610",
    "sg:postcode":"98104",
    "sg:province":"WA",
    "sg:tags":[
        "consultant",
        "financing",
        "planning"
    ],
    "wof:name":"Duff & Phelps",
    "wof:placetype":"venue"
},
  "geometry": {"coordinates":[-122.329826,47.604431],"type":"Point"}
}