{
  "type": "Feature",
  "properties": {
    "iso:country":"US",
    "sg:address":"635 Chapman Rd",
    "sg:city":"Castle Rock",
    "sg:classifiers":[
        {
            "category":"Professional",
            "subcategory":"Art Services",
            "type":"Services"
        }
    ],
    "sg:phone":"+1 360 274 4001",
    "sg:postcode":"98611",
    "sg:province":"WA",
    "sg:tags":[
        "photographer"
    ],
    "wof:name":"Sethers Outdoor Photography",
    "wof:placetype":"venue"
},
  "geometry": {"coordinates":[-122.924358,46.312773],"type":"Point"}
}