{
  "type": "Feature",
  "properties": {
    "addr:full":"2121 1st Ave Seattle WA 98121",
    "addr:housenumber":"2121",
    "addr:postcode":"98121",
    "addr:street":"1St Ave",
    "iso:country":"US",
    "sg:address":"2121 1st Ave",
    "sg:city":"Seattle",
    "sg:classifiers":[
        {
            "category":"Real Estate",
            "subcategory":"Architect",
            "type":"Services"
        }
    ],
    "sg:phone":"+1 206 441 5943",
    "sg:postcode":"98121",
    "sg:province":"WA",
    "sg:tags":[
        "building",
        "designer"
    ],
    "wof:name":"Bain Construction-Design Build",
    "wof:placetype":"venue"
},
  "geometry": {"coordinates":[-122.345085,47.612391],"type":"Point"}
}