{
  "type": "Feature",
  "properties": {
    "addr:full":"13746 23rd Pl NE Seattle WA 98125",
    "addr:housenumber":"13746",
    "addr:postcode":"98125",
    "addr:street":"23Rd Pl Ne",
    "iso:country":"US",
    "sg:address":"13746 23rd Pl NE",
    "sg:city":"Seattle",
    "sg:classifiers":[
        {
            "category":"Recreation",
            "type":"Entertainment"
        }
    ],
    "sg:phone":"+1 206 361 6314",
    "sg:postcode":"98125",
    "sg:province":"WA",
    "wof:name":"Amma Yoga",
    "wof:placetype":"venue"
},
  "geometry": {"coordinates":[-122.30358,47.729558],"type":"Point"}
}