{
  "type": "Feature",
  "properties": {
    "addr:full":"9991 Beecher Hill Rd Peshastin WA 98847",
    "addr:housenumber":"9991",
    "addr:postcode":"98847",
    "addr:street":"Beecher Hill Rd",
    "iso:country":"US",
    "sg:address":"9991 Beecher Hill Rd",
    "sg:city":"Peshastin",
    "sg:classifiers":[
        {
            "category":"Travel",
            "subcategory":"Hotels & Motels",
            "type":"Entertainment"
        }
    ],
    "sg:phone":"+1 509 548 0559",
    "sg:postcode":"98847",
    "sg:province":"WA",
    "sg:tags":[
        "operation",
        "lodging"
    ],
    "sg:website":"http://www.beecherhill.com",
    "wof:name":"Beecher Hill House",
    "wof:placetype":"venue"
},
  "geometry": {"coordinates":[-120.60060300000001,47.560636],"type":"Point"}
}