{
  "type": "Feature",
  "properties": {
    "addr:full":"10109 Aurora Avenue N Seattle WA 98133",
    "addr:housenumber":"10109",
    "addr:postcode":"98133",
    "addr:street":"Aurora Avenue N",
    "iso:country":"US",
    "sg:address":"10109 Aurora Avenue N",
    "sg:city":"Seattle",
    "sg:classifiers":[
        {
            "category":"Professional",
            "subcategory":"Employment Agencies",
            "type":"Services"
        }
    ],
    "sg:phone":"+1 206 522 0581",
    "sg:postcode":"98133",
    "sg:province":"WA",
    "sg:website":"www.laborready.com",
    "wof:name":"Labor Ready",
    "wof:placetype":"venue"
},
  "geometry": {"coordinates":[-122.344813,47.702356],"type":"Point"}
}