{
  "type": "Feature",
  "properties": {
    "addr:full":"12124 29th St E Puyallup WA 98372",
    "addr:housenumber":"12124",
    "addr:postcode":"98372",
    "addr:street":"29Th St E",
    "iso:country":"US",
    "sg:address":"12124 29th St E",
    "sg:city":"Puyallup",
    "sg:classifiers":[
        {
            "category":"Building & Trades",
            "subcategory":"Construction",
            "type":"Services"
        }
    ],
    "sg:phone":"+1 253 863 6441",
    "sg:postcode":"98372",
    "sg:province":"WA",
    "sg:tags":[
        "house"
    ],
    "wof:name":"Precisely Right",
    "wof:placetype":"venue"
},
  "geometry": {"coordinates":[-122.26808,47.231126],"type":"Point"}
}