{
  "type": "Feature",
  "properties": {
    "addr:full":"6509 E 18th Ave Spokane WA 99212",
    "addr:housenumber":"6509",
    "addr:postcode":"99212",
    "addr:street":"E 18Th Ave",
    "iso:country":"US",
    "sg:address":"6509 E 18th Ave",
    "sg:city":"Spokane",
    "sg:classifiers":[
        {
            "category":"Building & Trades",
            "subcategory":"Cleaning & Sanitation",
            "type":"Services"
        }
    ],
    "sg:phone":"+1 509 536 0245",
    "sg:postcode":"99212",
    "sg:province":"WA",
    "sg:tags":[
        "maintenance"
    ],
    "wof:name":"A Snowwhite Cleaning Service",
    "wof:placetype":"venue"
},
  "geometry": {"coordinates":[-117.318135,47.641251],"type":"Point"}
}