{
  "type": "Feature",
  "properties": {
    "addr:full":"6 N 6th St Yakima WA 98901",
    "addr:housenumber":"6",
    "addr:postcode":"98901",
    "addr:street":"N 6Th St",
    "iso:country":"US",
    "sg:address":"6 N 6th St",
    "sg:city":"Yakima",
    "sg:classifiers":[
        {
            "category":"Health Services",
            "subcategory":"Nursing And Care Facility",
            "type":"Services"
        },
        {
            "category":"Real Estate",
            "subcategory":"Real Estate Operator",
            "type":"Services"
        }
    ],
    "sg:phone":"+1 509 248 3191",
    "sg:postcode":"98901",
    "sg:province":"WA",
    "sg:tags":[
        "home",
        "retirement",
        "community"
    ],
    "sg:website":"www.suntower.org",
    "wof:name":"Sun Tower",
    "wof:placetype":"venue"
},
  "geometry": {"coordinates":[-120.49907,46.605199],"type":"Point"}
}