{
  "type": "Feature",
  "properties": {
    "addr:full":"3536 NE 3rd Ave Camas WA 98607",
    "addr:housenumber":"3536",
    "addr:postcode":"98607",
    "addr:street":"Ne 3Rd Ave",
    "iso:country":"US",
    "sg:address":"3536 NE 3rd Ave",
    "sg:city":"Camas",
    "sg:classifiers":[
        {
            "category":"Shopping",
            "subcategory":"Music",
            "type":"Retail Goods"
        }
    ],
    "sg:phone":"+1 360 835 7310",
    "sg:postcode":"98607",
    "sg:province":"WA",
    "wof:name":"American Family Video",
    "wof:placetype":"venue"
},
  "geometry": {"coordinates":[-122.368606,45.584009],"type":"Point"}
}