{
  "type": "Feature",
  "properties": {
    "addr:full":"1520 268th Ave NE Redmond WA 98053",
    "addr:housenumber":"1520",
    "addr:postcode":"98053",
    "addr:street":"268Th Ave Ne",
    "iso:country":"US",
    "sg:address":"1520 268th Ave NE",
    "sg:city":"Redmond",
    "sg:classifiers":[
        {
            "category":"Building & Trades",
            "subcategory":"Construction",
            "type":"Services"
        }
    ],
    "sg:phone":"+1 425 868 3230",
    "sg:postcode":"98053",
    "sg:province":"WA",
    "sg:tags":[
        "contractor"
    ],
    "wof:name":"John A. Nelson Construction Company",
    "wof:placetype":"venue"
},
  "geometry": {"coordinates":[-121.98123,47.624139],"type":"Point"}
}