{
  "type": "Feature",
  "properties": {
    "addr:full":"6472 129th Pl SE Bellevue WA 98006",
    "addr:housenumber":"6472",
    "addr:postcode":"98006",
    "addr:street":"129Th Pl Se",
    "iso:country":"US",
    "sg:address":"6472 129th Pl SE",
    "sg:city":"Bellevue",
    "sg:classifiers":[
        {
            "category":"Building & Trades",
            "subcategory":"Construction",
            "type":"Services"
        }
    ],
    "sg:phone":"+1 425 644 6803",
    "sg:postcode":"98006",
    "sg:province":"WA",
    "sg:tags":[
        "house",
        "real estate"
    ],
    "wof:name":"Lowell Appraisal Service",
    "wof:placetype":"venue"
},
  "geometry": {"coordinates":[-122.167618,47.546183],"type":"Point"}
}