{
  "type": "Feature",
  "properties": {
    "addr:full":"724 101st Ave SW Olympia WA 98512",
    "addr:housenumber":"724",
    "addr:postcode":"98512",
    "addr:street":"101St Ave Sw",
    "iso:country":"US",
    "sg:address":"724 101st Ave SW",
    "sg:city":"Olympia",
    "sg:classifiers":[
        {
            "category":"Sports & Exercise",
            "subcategory":"Bowling",
            "type":"Entertainment"
        }
    ],
    "sg:phone":"+1 360 754 2021",
    "sg:postcode":"98512",
    "sg:province":"WA",
    "sg:tags":[
        "center",
        "landscape"
    ],
    "wof:name":"Blue Ribbon Turf",
    "wof:placetype":"venue"
},
  "geometry": {"coordinates":[-122.915632,46.941963],"type":"Point"}
}