{
  "type": "Feature",
  "properties": {
    "addr:full":"960 Rice St Aberdeen WA 98520",
    "addr:housenumber":"960",
    "addr:postcode":"98520",
    "addr:street":"Rice St",
    "iso:country":"US",
    "sg:address":"960 Rice St",
    "sg:city":"Aberdeen",
    "sg:classifiers":[
        {
            "category":"Manufacturing",
            "subcategory":"Lumber",
            "type":"Manufacturing & Wholesale Goods"
        }
    ],
    "sg:phone":"+1 360 532 2285",
    "sg:postcode":"98520",
    "sg:province":"WA",
    "sg:tags":[
        "logger",
        "contract"
    ],
    "wof:name":"McKay & Son",
    "wof:placetype":"venue"
},
  "geometry": {"coordinates":[-123.840114,46.980286],"type":"Point"}
}