{
  "type": "Feature",
  "properties": {
    "addr:full":"3515 Grandview Dr W Tacoma WA 98466",
    "addr:housenumber":"3515",
    "addr:postcode":"98466",
    "addr:street":"Grandview Dr W",
    "iso:country":"US",
    "sg:address":"3515 Grandview Dr W",
    "sg:city":"Tacoma",
    "sg:classifiers":[
        {
            "category":"Organizations",
            "subcategory":"Professional Association",
            "type":"Services"
        }
    ],
    "sg:phone":"+1 253 566 8475",
    "sg:postcode":"98466",
    "sg:province":"WA",
    "sg:tags":[
        "hospital",
        "group",
        "membership",
        "pharmacy"
    ],
    "wof:name":"Wsshp",
    "wof:placetype":"venue"
},
  "geometry": {"coordinates":[-122.550471,47.226728],"type":"Point"}
}