{
  "type": "Feature",
  "properties": {
    "addr:full":"1425 Broadway #533 Seattle WA 98122",
    "addr:housenumber":"1425;#",
    "addr:postcode":"98122",
    "addr:street":"Broadway",
    "iso:country":"US",
    "sg:address":"1425 Broadway #533",
    "sg:city":"Seattle",
    "sg:classifiers":[
        {
            "category":"Professional",
            "type":"Services"
        }
    ],
    "sg:phone":"+1 206 328 6138",
    "sg:postcode":"98122",
    "sg:province":"WA",
    "wof:name":"OrgTheory",
    "wof:placetype":"venue"
},
  "geometry": {"coordinates":[-122.320791,47.613244],"type":"Point"}
}