{
  "type": "Feature",
  "properties": {
    "addr:full":"774 Water St Chinook WA 98614",
    "addr:housenumber":"774",
    "addr:postcode":"98614",
    "addr:street":"Water St",
    "iso:country":"US",
    "sg:address":"774 Water St",
    "sg:city":"Chinook",
    "sg:classifiers":[
        {
            "category":"Travel",
            "subcategory":"Campground",
            "type":"Entertainment"
        }
    ],
    "sg:phone":"+1 360 777 8247",
    "sg:postcode":"98614",
    "sg:province":"WA",
    "wof:name":"Safe Harbor Rv Park",
    "wof:placetype":"venue"
},
  "geometry": {"coordinates":[-123.948071,46.272466],"type":"Point"}
}