{
  "type": "Feature",
  "properties": {
    "addr:full":"4003 Mc Kinley Ave E Tacoma WA 98404",
    "addr:housenumber":"4003",
    "addr:postcode":"98404",
    "addr:street":"Mc Kinley Ave E",
    "iso:country":"US",
    "sg:address":"4003 Mc Kinley Ave E",
    "sg:city":"Tacoma",
    "sg:classifiers":[
        {
            "category":"Retail",
            "subcategory":"Auto Repair",
            "type":"Services"
        }
    ],
    "sg:phone":"+1 253 474 5022",
    "sg:postcode":"98404",
    "sg:province":"WA",
    "sg:tags":[
        "muffler",
        "exhaust",
        "system"
    ],
    "wof:name":"Carrillo's Super Svc Inc",
    "wof:placetype":"venue"
},
  "geometry": {"coordinates":[-122.42079099999999,47.218423],"type":"Point"}
}