{
  "type": "Feature",
  "properties": {
    "addr:full":"8815 S Tacoma Way Ste 118 Lakewood WA 98499",
    "addr:housenumber":"8815",
    "addr:postcode":"98499",
    "addr:street":"S Tacoma Way Ste 118",
    "iso:country":"US",
    "sg:address":"8815 S Tacoma Way Ste 118",
    "sg:city":"Lakewood",
    "sg:classifiers":[
        {
            "category":"Education",
            "subcategory":"Kindergarten",
            "type":"Public Place"
        }
    ],
    "sg:phone":"+1 253 581 1420",
    "sg:postcode":"98499",
    "sg:province":"WA",
    "sg:tags":[
        "school",
        "driving"
    ],
    "wof:name":"Ninnis Driving School",
    "wof:placetype":"venue"
},
  "geometry": {"coordinates":[-122.48400100000001,47.176601],"type":"Point"}
}