{
  "type": "Feature",
  "properties": {
    "addr:full":"1310 Minor Ave Apt 610 Seattle WA 98101",
    "addr:housenumber":"1310;610",
    "addr:postcode":"98101",
    "addr:street":"Minor Ave Apt",
    "iso:country":"US",
    "sg:address":"1310 Minor Ave Apt 610",
    "sg:city":"Seattle",
    "sg:classifiers":[
        {
            "category":"Manufacturing",
            "subcategory":"Buildings",
            "type":"Manufacturing & Wholesale Goods"
        },
        {
            "category":"Building & Trades",
            "subcategory":"Construction",
            "type":"Services"
        }
    ],
    "sg:phone":"+1 206 623 8130",
    "sg:postcode":"98101",
    "sg:province":"WA",
    "sg:tags":[
        "home",
        "builder",
        "contractor"
    ],
    "wof:name":"Straits Area Construction",
    "wof:placetype":"venue"
},
  "geometry": {"coordinates":[-122.326081,47.61205],"type":"Point"}
}