{
  "type": "Feature",
  "properties": {
    "addr:full":"601 Auburn Way S Auburn WA 98002",
    "addr:housenumber":"601",
    "addr:postcode":"98002",
    "addr:street":"Auburn Way S",
    "iso:country":"US",
    "sg:address":"601 Auburn Way S",
    "sg:city":"Auburn",
    "sg:classifiers":[
        {
            "category":"Autos & Motor Vehicles",
            "subcategory":"Fuel & Gas Station",
            "type":"Retail Goods"
        }
    ],
    "sg:phone":"+1 253 288 0418",
    "sg:postcode":"98002",
    "sg:province":"WA",
    "sg:tags":[
        "station",
        "gasoline"
    ],
    "wof:name":"Circle K Store",
    "wof:placetype":"venue"
},
  "geometry": {"coordinates":[-122.225263,47.301562],"type":"Point"}
}