{
  "type": "Feature",
  "properties": {
    "addr:full":"2964 SW Avalon Way Seattle WA 98126",
    "addr:housenumber":"2964",
    "addr:postcode":"98126",
    "addr:street":"Sw Avalon Way",
    "iso:country":"US",
    "sg:address":"2964 SW Avalon Way",
    "sg:city":"Seattle",
    "sg:classifiers":[
        {
            "category":"Retail",
            "subcategory":"Auto Rental",
            "type":"Services"
        }
    ],
    "sg:phone":"+1 206 932 3274",
    "sg:postcode":"98126",
    "sg:province":"WA",
    "sg:tags":[
        "truck",
        "leasing"
    ],
    "wof:name":"Ryder",
    "wof:placetype":"venue"
},
  "geometry": {"coordinates":[-122.37084299999999,47.567776],"type":"Point"}
}