{
  "type": "Feature",
  "properties": {
    "addr:full":"1612 8th Ave W Seattle WA 98119",
    "addr:housenumber":"1612",
    "addr:postcode":"98119",
    "addr:street":"8Th Ave W",
    "iso:country":"US",
    "sg:address":"1612 8th Ave W",
    "sg:city":"Seattle",
    "sg:classifiers":[
        {
            "category":"Health Services",
            "subcategory":"Doctor",
            "type":"Services"
        }
    ],
    "sg:phone":"+1 206 284 9012",
    "sg:postcode":"98119",
    "sg:province":"WA",
    "wof:name":"Mensher John H MD",
    "wof:placetype":"venue"
},
  "geometry": {"coordinates":[-122.367445,47.63418],"type":"Point"}
}