{
  "type": "Feature",
  "properties": {
    "addr:full":"140 105th Ave NE Bellevue WA 98004",
    "addr:housenumber":"140",
    "addr:postcode":"98004",
    "addr:street":"105Th Ave Ne",
    "iso:country":"US",
    "sg:address":"140 105th Ave NE",
    "sg:city":"Bellevue",
    "sg:classifiers":[
        {
            "category":"Personal",
            "type":"Services"
        }
    ],
    "sg:phone":"+1 425 455 4554",
    "sg:postcode":"98004",
    "sg:province":"WA",
    "sg:tags":[
        "formal",
        "rental",
        "wear",
        "costume"
    ],
    "wof:name":"Brocklind's Formal Wear",
    "wof:placetype":"venue"
},
  "geometry": {"coordinates":[-122.20007200000001,47.611642],"type":"Point"}
}