{
  "type": "Feature",
  "properties": {
    "addr:full":"6336 Leprechaun Ln NW Olympia WA 98502",
    "addr:postcode":"6336;olympia wa 98502",
    "addr:street":"Leprechaun Ln Nw",
    "iso:country":"US",
    "sg:address":"6336 Leprechaun Ln NW",
    "sg:city":"Olympia",
    "sg:classifiers":[
        {
            "category":"Organizations",
            "subcategory":"Labor Organization",
            "type":"Services"
        }
    ],
    "sg:phone":"+1 360 866 0483",
    "sg:postcode":"98502",
    "sg:province":"WA",
    "wof:name":"Hall Investments Lc",
    "wof:placetype":"venue"
},
  "geometry": {"coordinates":[-122.92652,47.124271],"type":"Point"}
}