{
  "type": "Feature",
  "properties": {
    "addr:full":"17106 SE 18th St Vancouver WA 98683",
    "addr:postcode":"17106;98683",
    "addr:street":"Se 18Th St",
    "iso:country":"US",
    "sg:address":"17106 SE 18th St",
    "sg:city":"Vancouver",
    "sg:classifiers":[
        {
            "category":"Professional",
            "type":"Services"
        }
    ],
    "sg:phone":"+1 360 883 1213",
    "sg:postcode":"98683",
    "sg:province":"WA",
    "sg:tags":[
        "transportation"
    ],
    "wof:name":"Rolly Aydarski Transportation",
    "wof:placetype":"venue"
},
  "geometry": {"coordinates":[-122.49575,45.608028],"type":"Point"}
}