{
  "type": "Feature",
  "properties": {
    "addr:full":"420 S College Ave College Place WA 99324",
    "addr:housenumber":"420",
    "addr:postcode":"99324",
    "addr:street":"S College Ave",
    "iso:country":"US",
    "sg:address":"420 S College Ave",
    "sg:city":"College Place",
    "sg:classifiers":[
        {
            "category":"Health Services",
            "subcategory":"Nursing And Care Facility",
            "type":"Services"
        }
    ],
    "sg:phone":"+1 509 529 4480",
    "sg:postcode":"99324",
    "sg:province":"WA",
    "sg:tags":[
        "skilled"
    ],
    "wof:name":"Regency",
    "wof:placetype":"venue"
},
  "geometry": {"coordinates":[-118.388608,46.045516],"type":"Point"}
}