{
  "type": "Feature",
  "properties": {
    "iso:country":"US",
    "sg:address":"11125 NE 123rd Ln",
    "sg:city":"Kirkland",
    "sg:classifiers":[
        {
            "category":"Professional",
            "type":"Services"
        }
    ],
    "sg:phone":"+1 425 891 7636",
    "sg:postcode":"98034",
    "sg:province":"WA",
    "wof:name":"Platinum Wheels",
    "wof:placetype":"venue"
},
  "geometry": {"coordinates":[-122.193881,47.710891],"type":"Point"}
}