{
  "type": "Feature",
  "properties": {
    "iso:country":"US",
    "sg:address":"34935 SE Douglas St",
    "sg:city":"Snoqualmie",
    "sg:classifiers":[
        {
            "category":"Professional",
            "subcategory":"Management & Consulting",
            "type":"Services"
        }
    ],
    "sg:phone":"+1 425 396 5860",
    "sg:postcode":"98065",
    "sg:province":"WA",
    "wof:name":"Snoqualmie Adminstrative Svc",
    "wof:placetype":"venue"
},
  "geometry": {"coordinates":[-121.87379199999999,47.526789],"type":"Point"}
}