{
  "type": "Feature",
  "properties": {
    "addr:full":"5788 Lenea Dr NW Bremerton WA 98312",
    "addr:housenumber":"5788",
    "addr:postcode":"98312",
    "addr:street":"Lenea Dr Nw",
    "iso:country":"US",
    "sg:address":"5788 Lenea Dr NW",
    "sg:city":"Bremerton",
    "sg:classifiers":[
        {
            "category":"Building & Trades",
            "subcategory":"Landscaping Services",
            "type":"Services"
        }
    ],
    "sg:phone":"+1 360 613 5075",
    "sg:postcode":"98312",
    "sg:province":"WA",
    "sg:tags":[
        "lawn",
        "landscape",
        "contractor"
    ],
    "wof:name":"Donald Haviland",
    "wof:placetype":"venue"
},
  "geometry": {"coordinates":[-122.720985,47.615977],"type":"Point"}
}