{
  "type": "Feature",
  "properties": {
    "addr:full":"4721 Rainier Ave S Seattle WA 98118",
    "addr:housenumber":"4721",
    "addr:postcode":"98118",
    "addr:street":"Rainier Ave S",
    "iso:country":"US",
    "sg:address":"4721 Rainier Ave S",
    "sg:city":"Seattle",
    "sg:classifiers":[
        {
            "category":"Education",
            "subcategory":"Library",
            "type":"Public Place"
        }
    ],
    "sg:phone":"+1 206 386 1908",
    "sg:postcode":"98118",
    "sg:province":"WA",
    "sg:website":"www.seattle.gov",
    "wof:name":"Columbia City Library",
    "wof:placetype":"venue"
},
  "geometry": {"coordinates":[-122.286776,47.560443],"type":"Point"}
}