{
  "type": "Feature",
  "properties": {
    "addr:full":"5405 Mount Aix Way Yakima WA 98901",
    "addr:housenumber":"5405",
    "addr:postcode":"98901",
    "addr:street":"Mount Aix Way",
    "iso:country":"US",
    "sg:address":"5405 Mount Aix Way",
    "sg:city":"Yakima",
    "sg:classifiers":[
        {
            "category":"Building & Trades",
            "subcategory":"Construction",
            "type":"Services"
        }
    ],
    "sg:phone":"+1 509 952 2170",
    "sg:postcode":"98901",
    "sg:province":"WA",
    "sg:tags":[
        "house"
    ],
    "wof:name":"Rogers Construction",
    "wof:placetype":"venue"
},
  "geometry": {"coordinates":[-120.427161,46.609841],"type":"Point"}
}