{
  "type": "Feature",
  "properties": {
    "addr:full":"4505 39th Ave SW Seattle WA 98116",
    "addr:housenumber":"4505",
    "addr:postcode":"98116",
    "addr:street":"39Th Ave Sw",
    "iso:country":"US",
    "sg:address":"4505 39th Ave SW",
    "sg:city":"Seattle",
    "sg:classifiers":[
        {
            "category":"Restaurant",
            "type":"Food & Drink"
        }
    ],
    "sg:phone":"+1 206 937 4050",
    "sg:postcode":"98116",
    "sg:province":"WA",
    "sg:tags":[
        "traditional",
        "american"
    ],
    "sg:website":"www.highstrikegrill.com/",
    "wof:name":"Highstrike Grill",
    "wof:placetype":"venue"
},
  "geometry": {"coordinates":[-122.381654,47.562481],"type":"Point"}
}