{
  "type": "Feature",
  "properties": {
    "addr:full":"3338 SE Baker Rd Port Orchard WA 98367",
    "addr:housenumber":"3338",
    "addr:postcode":"98367",
    "addr:street":"Se Baker Rd",
    "iso:country":"US",
    "sg:address":"3338 SE Baker Rd",
    "sg:city":"Port Orchard",
    "sg:classifiers":[
        {
            "category":"Recreation",
            "subcategory":"Marina",
            "type":"Entertainment"
        }
    ],
    "sg:phone":"+1 360 876 2122",
    "sg:postcode":"98367",
    "sg:province":"WA",
    "sg:tags":[
        "operation"
    ],
    "wof:name":"Simmons Marine Maint & Repr",
    "wof:placetype":"venue"
},
  "geometry": {"coordinates":[-122.60937300000001,47.490264],"type":"Point"}
}