{
  "type": "Feature",
  "properties": {
    "addr:full":"8019 NE 71st Loop Vancouver WA 98662",
    "addr:housenumber":"8019",
    "addr:postcode":"98662",
    "addr:street":"Ne 71St Loop",
    "iso:country":"US",
    "sg:address":"8019 NE 71st Loop",
    "sg:city":"Vancouver",
    "sg:classifiers":[
        {
            "category":"Professional",
            "subcategory":"Management & Consulting",
            "type":"Services"
        }
    ],
    "sg:phone":"+1 360 892 7565",
    "sg:postcode":"98662",
    "sg:province":"WA",
    "sg:tags":[
        "business"
    ],
    "wof:name":"Leave Your Legacy Inc",
    "wof:placetype":"venue"
},
  "geometry": {"coordinates":[-122.589127,45.673507],"type":"Point"}
}