{
  "type": "Feature",
  "properties": {
    "addr:full":"423 E Pike St Seattle WA 98122",
    "addr:housenumber":"423",
    "addr:postcode":"98122",
    "addr:street":"E Pike St",
    "iso:country":"US",
    "sg:address":"423 E Pike St",
    "sg:city":"Seattle",
    "sg:classifiers":[
        {
            "category":"Restaurant",
            "type":"Food & Drink"
        }
    ],
    "sg:phone":"+1 206 652 0877",
    "sg:postcode":"98122",
    "sg:province":"WA",
    "wof:name":"Pagliacci Corporate Offices",
    "wof:placetype":"venue"
},
  "geometry": {"coordinates":[-122.325996,47.614201],"type":"Point"}
}