{
  "type": "Feature",
  "properties": {
    "addr:full":"2505 Olympic Hwy N Shelton WA 98584",
    "addr:housenumber":"2505",
    "addr:postcode":"98584",
    "addr:street":"Olympic Hwy N",
    "iso:country":"US",
    "sg:address":"2505 Olympic Hwy N",
    "sg:city":"Shelton",
    "sg:classifiers":[
        {
            "category":"Social Services",
            "type":"Services"
        }
    ],
    "sg:phone":"+1 360 432 0240",
    "sg:postcode":"98584",
    "sg:province":"WA",
    "wof:name":"Mason House",
    "wof:placetype":"venue"
},
  "geometry": {"coordinates":[-123.12447899999999,47.226933],"type":"Point"}
}