{
  "type": "Feature",
  "properties": {
    "addr:full":"197 Similkameen Rd Loomis WA 98827",
    "addr:housenumber":"197",
    "addr:postcode":"98827",
    "addr:street":"Similkameen Rd",
    "iso:country":"US",
    "sg:address":"197 Similkameen Rd",
    "sg:city":"Loomis",
    "sg:classifiers":[
        {
            "category":"Government",
            "subcategory":"Office",
            "type":"Public Place"
        }
    ],
    "sg:phone":"+1 509 476 2125",
    "sg:postcode":"98827",
    "sg:province":"WA",
    "sg:tags":[
        "entry",
        "port"
    ],
    "wof:name":"Port of Entry",
    "wof:placetype":"venue"
},
  "geometry": {"coordinates":[-119.66330600000001,48.999962],"type":"Point"}
}