{
  "type": "Feature",
  "properties": {
    "addr:full":"210 240th St SE Bothell WA 98021",
    "addr:housenumber":"210",
    "addr:postcode":"98021",
    "addr:street":"240Th St Se",
    "iso:country":"US",
    "sg:address":"210 240th St SE",
    "sg:city":"Bothell",
    "sg:classifiers":[
        {
            "category":"Shopping",
            "subcategory":"Bicycles & Sporting Goods",
            "type":"Retail Goods"
        }
    ],
    "sg:phone":"+1 425 483 1594",
    "sg:postcode":"98021",
    "sg:province":"WA",
    "wof:name":"Gavins Tack",
    "wof:placetype":"venue"
},
  "geometry": {"coordinates":[-122.229491,47.780283],"type":"Point"}
}