{
  "type": "Feature",
  "properties": {
    "iso:country":"US",
    "sg:address":"1756 268th Pl SE",
    "sg:city":"Sammamish",
    "sg:classifiers":[
        {
            "category":"Shopping",
            "subcategory":"Catalog Store",
            "type":"Retail Goods"
        },
        {
            "category":"Shopping",
            "subcategory":"Computers & Home Electronics",
            "type":"Retail Goods"
        }
    ],
    "sg:phone":"+1 425 830 1088",
    "sg:postcode":"98075",
    "sg:province":"WA",
    "sg:tags":[
        "house",
        "supply",
        "electronic",
        "mail",
        "equipment"
    ],
    "wof:name":"Cool Gadgets 4 U",
    "wof:placetype":"venue"
},
  "geometry": {"coordinates":[-121.980572,47.593884],"type":"Point"}
}