{
  "type": "Feature",
  "properties": {
    "addr:full":"365 Carter Ave Friday Harbor WA 98250",
    "addr:housenumber":"365",
    "addr:postcode":"98250",
    "addr:street":"Carter Ave",
    "iso:country":"US",
    "sg:address":"365 Carter Ave",
    "sg:city":"Friday Harbor",
    "sg:classifiers":[
        {
            "category":"Travel",
            "subcategory":"Hotels & Motels",
            "type":"Entertainment"
        }
    ],
    "sg:phone":"+1 360 378 4730",
    "sg:postcode":"98250",
    "sg:province":"WA",
    "sg:tags":[
        "breakfast",
        "inn",
        "bed"
    ],
    "wof:name":"Hillside House Bed & Breakfast",
    "wof:placetype":"venue"
},
  "geometry": {"coordinates":[-123.028615,48.537068],"type":"Point"}
}