{
  "type": "Feature",
  "properties": {
    "addr:full":"2310 E Madison St Seattle WA 98112",
    "addr:housenumber":"2310",
    "addr:postcode":"98112",
    "addr:street":"E Madison St",
    "iso:country":"US",
    "sg:address":"2310 E Madison St",
    "sg:city":"Seattle",
    "sg:classifiers":[
        {
            "category":"Personal",
            "subcategory":"Tattoo Parlor",
            "type":"Services"
        },
        {
            "category":"Personal",
            "subcategory":"Piercing",
            "type":"Services"
        }
    ],
    "sg:phone":"+1 206 325 5110",
    "sg:postcode":"98112",
    "sg:province":"WA",
    "sg:tags":[
        "body"
    ],
    "wof:name":"Jack Black Tattoo",
    "wof:placetype":"venue"
},
  "geometry": {"coordinates":[-122.30238300000001,47.619282],"type":"Point"}
}