{
  "type": "Feature",
  "properties": {
    "iso:country":"US",
    "sg:address":"620 23rd Ave E",
    "sg:city":"Seattle",
    "sg:classifiers":[
        {
            "category":"Building & Trades",
            "subcategory":"Construction",
            "type":"Services"
        }
    ],
    "sg:phone":"+1 206 365 0402",
    "sg:postcode":"98112",
    "sg:province":"WA",
    "sg:tags":[
        "contractor"
    ],
    "wof:name":"Duran Construction Inc",
    "wof:placetype":"venue"
},
  "geometry": {"coordinates":[-122.30234799999999,47.625032],"type":"Point"}
}