{
  "type": "Feature",
  "properties": {
    "addr:full":"1220 4th Ave E Olympia WA 98506",
    "addr:housenumber":"1220",
    "addr:postcode":"98506",
    "addr:street":"4Th Ave E",
    "iso:country":"US",
    "sg:address":"1220 4th Ave E",
    "sg:city":"Olympia",
    "sg:classifiers":[
        {
            "category":"Professional",
            "subcategory":"Management & Consulting",
            "type":"Services"
        }
    ],
    "sg:phone":"+1 360 754 1344",
    "sg:postcode":"98506",
    "sg:province":"WA",
    "sg:tags":[
        "business"
    ],
    "wof:name":"Envirovision Corp",
    "wof:placetype":"venue"
},
  "geometry": {"coordinates":[-122.887085,47.045888],"type":"Point"}
}