{
  "type": "Feature",
  "properties": {
    "addr:full":"11319 1st Avenue NE Seattle WA 98125",
    "addr:housenumber":"11319",
    "addr:postcode":"98125",
    "addr:street":"1St Avenue Ne",
    "iso:country":"US",
    "sg:address":"11319 1st Avenue NE",
    "sg:city":"Seattle",
    "sg:classifiers":[
        {
            "category":"Professional",
            "type":"Services"
        },
        {
            "category":"Recreation",
            "type":"Entertainment"
        },
        {
            "category":"Health Services",
            "subcategory":"Clinic",
            "type":"Services"
        }
    ],
    "sg:phone":"+1 206 365 3121",
    "sg:postcode":"98125",
    "sg:province":"WA",
    "sg:tags":[
        "active",
        "life",
        "medical"
    ],
    "wof:name":"Wheelchair Taxicabulance of Puget Sound",
    "wof:placetype":"venue"
},
  "geometry": {"coordinates":[-122.32865200000001,47.711055],"type":"Point"}
}