{
  "type": "Feature",
  "properties": {
    "addr:full":"150 Park Ave N Renton WA 98057",
    "addr:housenumber":"150",
    "addr:postcode":"98057",
    "addr:street":"Park Ave N",
    "iso:country":"US",
    "sg:address":"150 Park Ave N",
    "sg:city":"Renton",
    "sg:classifiers":[
        {
            "category":"Health Services",
            "subcategory":"Dentist",
            "type":"Services"
        }
    ],
    "sg:phone":"+1 425 227 7788",
    "sg:postcode":"98057",
    "sg:province":"WA",
    "wof:name":"Babin Scott A",
    "wof:placetype":"venue"
},
  "geometry": {"coordinates":[-122.201998,47.483485],"type":"Point"}
}