{
  "type": "Feature",
  "properties": {
    "addr:full":"2012 Longfiber Ave Union Gap WA 98903",
    "addr:housenumber":"2012",
    "addr:postcode":"98903",
    "addr:street":"Longfiber Ave",
    "iso:country":"US",
    "sg:address":"2012 Longfiber Ave",
    "sg:city":"Union Gap",
    "sg:classifiers":[
        {
            "category":"Building & Trades",
            "subcategory":"Construction",
            "type":"Services"
        }
    ],
    "sg:phone":"+1 509 577 8888",
    "sg:postcode":"98903",
    "sg:province":"WA",
    "sg:tags":[
        "masonry",
        "contractor"
    ],
    "wof:name":"Johnson Enterprises Inc",
    "wof:placetype":"venue"
},
  "geometry": {"coordinates":[-120.492992,46.564947],"type":"Point"}
}