{
  "type": "Feature",
  "properties": {
    "addr:full":"360 E Cedar St Belfair WA 98528",
    "addr:housenumber":"360",
    "addr:postcode":"98528",
    "addr:street":"E Cedar St",
    "iso:country":"US",
    "sg:address":"360 E Cedar St",
    "sg:city":"Belfair",
    "sg:classifiers":[
        {
            "category":"Building & Trades",
            "subcategory":"Landscaping Services",
            "type":"Services"
        }
    ],
    "sg:phone":"+1 360 275 8807",
    "sg:postcode":"98528",
    "sg:province":"WA",
    "sg:tags":[
        "landscape"
    ],
    "wof:name":"Gunters Landscape Maintenance",
    "wof:placetype":"venue"
},
  "geometry": {"coordinates":[-122.876131,47.409989],"type":"Point"}
}