{
  "type": "Feature",
  "properties": {
    "addr:full":"619 Broadway E Seattle WA 98102",
    "addr:housenumber":"619",
    "addr:postcode":"98102",
    "addr:street":"Broadway",
    "iso:country":"US",
    "sg:address":"619 Broadway E",
    "sg:city":"Seattle",
    "sg:classifiers":[
        {
            "category":"Manufacturing",
            "subcategory":"Retail Goods",
            "type":"Manufacturing & Wholesale Goods"
        }
    ],
    "sg:phone":"+1 206 624 4880",
    "sg:postcode":"98102",
    "sg:province":"WA",
    "sg:tags":[
        "manufacturer"
    ],
    "wof:name":"Frequency-8",
    "wof:placetype":"venue"
},
  "geometry": {"coordinates":[-122.32101,47.624908],"type":"Point"}
}