{
  "type": "Feature",
  "properties": {
    "addr:full":"4443 S 134th Place Tukwila WA 98168",
    "addr:housenumber":"4443",
    "addr:postcode":"98168",
    "addr:street":"S 134Th Place",
    "iso:country":"US",
    "sg:address":"4443 S 134th Place",
    "sg:city":"Tukwila",
    "sg:classifiers":[
        {
            "category":"Personal",
            "type":"Services"
        }
    ],
    "sg:phone":"+1 206 433 6260",
    "sg:postcode":"98168",
    "sg:province":"WA",
    "sg:tags":[
        "mover"
    ],
    "sg:website":"www.alaskaairforwarding.com",
    "wof:name":"Alaska Air Forwarding",
    "wof:placetype":"venue"
},
  "geometry": {"coordinates":[-122.27658,47.484708],"type":"Point"}
}