{
  "type": "Feature",
  "properties": {
    "addr:full":"303 E 16th St Vancouver WA 98663",
    "addr:housenumber":"303",
    "addr:postcode":"98663",
    "addr:street":"E 16Th St",
    "iso:country":"US",
    "sg:address":"303 E 16th St",
    "sg:city":"Vancouver",
    "sg:classifiers":[
        {
            "category":"Social Services",
            "type":"Services"
        }
    ],
    "sg:phone":"+1 360 699 8668",
    "sg:postcode":"98663",
    "sg:province":"WA",
    "wof:name":"Marsha Sork Counselor",
    "wof:placetype":"venue"
},
  "geometry": {"coordinates":[-122.668267,45.633259],"type":"Point"}
}