{
  "type": "Feature",
  "properties": {
    "addr:full":"12951 Bel Red Rd Bellevue WA 98005",
    "addr:housenumber":"12951",
    "addr:postcode":"98005",
    "addr:street":"Bel Red Rd",
    "iso:country":"US",
    "sg:address":"12951 Bel Red Rd",
    "sg:city":"Bellevue",
    "sg:classifiers":[
        {
            "category":"Professional",
            "subcategory":"Computer Services",
            "type":"Services"
        }
    ],
    "sg:phone":"+1 425 643 7117",
    "sg:postcode":"98005",
    "sg:province":"WA",
    "sg:tags":[
        "programming",
        "custom"
    ],
    "wof:name":"Verus",
    "wof:placetype":"venue"
},
  "geometry": {"coordinates":[-122.16503,47.621833],"type":"Point"}
}