{
  "type": "Feature",
  "properties": {
    "addr:full":"18313 127th Ave NE Bothell WA 98011",
    "addr:housenumber":"18313",
    "addr:postcode":"98011",
    "addr:street":"127Th Ave Ne",
    "iso:country":"US",
    "sg:address":"18313 127th Ave NE",
    "sg:city":"Bothell",
    "sg:classifiers":[
        {
            "category":"Manufacturing",
            "subcategory":"Jewelry",
            "type":"Manufacturing & Wholesale Goods"
        }
    ],
    "sg:phone":"+1 425 486 8436",
    "sg:postcode":"98011",
    "sg:province":"WA",
    "sg:tags":[
        "precious",
        "metal",
        "mfg"
    ],
    "wof:name":"CJ Designs",
    "wof:placetype":"venue"
},
  "geometry": {"coordinates":[-122.171429,47.761277],"type":"Point"}
}