{
  "type": "Feature",
  "properties": {
    "addr:full":"2200 Industry Ln Yakima WA 98901",
    "addr:housenumber":"2200",
    "addr:postcode":"98901",
    "addr:street":"Industry Ln",
    "iso:country":"US",
    "sg:address":"2200 Industry Ln",
    "sg:city":"Yakima",
    "sg:classifiers":[
        {
            "category":"Manufacturing",
            "subcategory":"Lumber",
            "type":"Manufacturing & Wholesale Goods"
        }
    ],
    "sg:phone":"+1 509 452 5893",
    "sg:postcode":"98901",
    "sg:province":"WA",
    "sg:tags":[
        "company",
        "logging"
    ],
    "wof:name":"C Wyss & Son",
    "wof:placetype":"venue"
},
  "geometry": {"coordinates":[-120.469525,46.604627],"type":"Point"}
}