{
  "type": "Feature",
  "properties": {
    "addr:full":"206 Rosebrook Rd Chehalis WA 98532",
    "addr:housenumber":"206",
    "addr:postcode":"98532",
    "addr:street":"Rosebrook Rd",
    "iso:country":"US",
    "sg:address":"206 Rosebrook Rd",
    "sg:city":"Chehalis",
    "sg:classifiers":[
        {
            "category":"Professional",
            "type":"Services"
        }
    ],
    "sg:phone":"+1 360 262 3111",
    "sg:postcode":"98532",
    "sg:province":"WA",
    "wof:name":"Wimos Inc",
    "wof:placetype":"venue"
},
  "geometry": {"coordinates":[-122.84693900000001,46.603917],"type":"Point"}
}