{
  "type": "Feature",
  "properties": {
    "addr:full":"35910 N River Estates Ln Chattaroy WA 99003",
    "addr:housenumber":"35910",
    "addr:postcode":"99003",
    "addr:street":"N River Estates Ln",
    "iso:country":"US",
    "sg:address":"35910 N River Estates Ln",
    "sg:city":"Chattaroy",
    "sg:classifiers":[
        {
            "category":"Health Services",
            "subcategory":"Nursing And Care Facility",
            "type":"Services"
        }
    ],
    "sg:phone":"+1 509 292 8103",
    "sg:postcode":"99003",
    "sg:province":"WA",
    "sg:tags":[
        "home",
        "convalescent"
    ],
    "wof:name":"Rimrock Estates",
    "wof:placetype":"venue"
},
  "geometry": {"coordinates":[-117.338803,47.970186],"type":"Point"}
}