{
  "type": "Feature",
  "properties": {
    "addr:full":"608 Robert Bush Dr South Bend WA 98586",
    "addr:housenumber":"608",
    "addr:postcode":"98586",
    "addr:street":"Robert Bush Dr",
    "iso:country":"US",
    "sg:address":"608 Robert Bush Dr",
    "sg:city":"South Bend",
    "sg:classifiers":[
        {
            "category":"Shopping",
            "subcategory":"Gifts & Souvenirs",
            "type":"Retail Goods"
        }
    ],
    "sg:phone":"+1 360 875 6604",
    "sg:postcode":"98586",
    "sg:province":"WA",
    "sg:tags":[
        "shop"
    ],
    "wof:name":"Something Special Gift Shop",
    "wof:placetype":"venue"
},
  "geometry": {"coordinates":[-123.806952,46.664387],"type":"Point"}
}