{
  "type": "Feature",
  "properties": {
    "addr:full":"7720 32nd Ave NW Seattle WA 98117",
    "addr:housenumber":"7720",
    "addr:postcode":"98117",
    "addr:street":"32Nd Ave Nw",
    "iso:country":"US",
    "sg:address":"7720 32nd Ave NW",
    "sg:city":"Seattle",
    "sg:classifiers":[
        {
            "category":"Professional",
            "subcategory":"Management & Consulting",
            "type":"Services"
        }
    ],
    "sg:phone":"+1 206 789 7113",
    "sg:postcode":"98117",
    "sg:province":"WA",
    "sg:tags":[
        "counselor",
        "public",
        "relations"
    ],
    "wof:name":"Abuzz Communications",
    "wof:placetype":"venue"
},
  "geometry": {"coordinates":[-122.39823699999999,47.684974],"type":"Point"}
}