{
  "type": "Feature",
  "properties": {
    "addr:full":"204 W Clark St Pasco WA 99301",
    "addr:housenumber":"204",
    "addr:postcode":"99301",
    "addr:street":"W Clark St",
    "iso:country":"US",
    "sg:address":"204 W Clark St",
    "sg:city":"Pasco",
    "sg:classifiers":[
        {
            "category":"Organizations",
            "subcategory":"Professional Association",
            "type":"Services"
        }
    ],
    "sg:phone":"+1 509 547 2253",
    "sg:postcode":"99301",
    "sg:province":"WA",
    "wof:name":"Laborers Nw Regl Organizers",
    "wof:placetype":"venue"
},
  "geometry": {"coordinates":[-119.089068,46.232284],"type":"Point"}
}