{
  "type": "Feature",
  "properties": {
    "iso:country":"US",
    "sg:address":"19919 68th Ave W",
    "sg:city":"Lynnwood",
    "sg:classifiers":[
        {
            "category":"Travel",
            "subcategory":"Travel Agent",
            "type":"Entertainment"
        }
    ],
    "sg:phone":"+1 425 778 2086",
    "sg:postcode":"98036",
    "sg:province":"WA",
    "sg:tags":[
        "operator",
        "tour"
    ],
    "wof:name":"Trajal Hsptlity Turism College",
    "wof:placetype":"venue"
},
  "geometry": {"coordinates":[-122.32485699999999,47.817852],"type":"Point"}
}