{
  "type": "Feature",
  "properties": {
    "addr:full":"2417 E Evergreen Blvd Vancouver WA 98661",
    "addr:housenumber":"2417",
    "addr:postcode":"98661",
    "addr:street":"E Evergreen Blvd",
    "iso:country":"US",
    "sg:address":"2417 E Evergreen Blvd",
    "sg:city":"Vancouver",
    "sg:classifiers":[
        {
            "category":"Health Services",
            "subcategory":"Chiropractor",
            "type":"Services"
        }
    ],
    "sg:phone":"+1 360 694 3021",
    "sg:postcode":"98661",
    "sg:province":"WA",
    "wof:name":"Puariea E E DC",
    "wof:placetype":"venue"
},
  "geometry": {"coordinates":[-122.646004,45.625999],"type":"Point"}
}