{
  "type": "Feature",
  "properties": {
    "addr:full":"516 Market St Kirkland WA 98033",
    "addr:housenumber":"516",
    "addr:postcode":"98033",
    "addr:street":"Market St",
    "iso:country":"US",
    "sg:address":"516 Market St",
    "sg:city":"Kirkland",
    "sg:classifiers":[
        {
            "category":"Professional",
            "type":"Services"
        }
    ],
    "sg:phone":"+1 425 576 8503",
    "sg:postcode":"98033",
    "sg:province":"WA",
    "wof:name":"Capturescom",
    "wof:placetype":"venue"
},
  "geometry": {"coordinates":[-122.209614,47.679553],"type":"Point"}
}