{
  "type": "Feature",
  "properties": {
    "addr:full":"4204 Clearwater Dr SE Lacey WA 98503",
    "addr:housenumber":"4204",
    "addr:postcode":"98503",
    "addr:street":"Clearwater Dr Se",
    "iso:country":"US",
    "sg:address":"4204 Clearwater Dr SE",
    "sg:city":"Lacey",
    "sg:classifiers":[
        {
            "category":"Professional",
            "subcategory":"Management & Consulting",
            "type":"Services"
        }
    ],
    "sg:phone":"+1 360 459 0862",
    "sg:postcode":"98503",
    "sg:province":"WA",
    "sg:tags":[
        "consultant"
    ],
    "wof:name":"Christie Oloughlin & Associates",
    "wof:placetype":"venue"
},
  "geometry": {"coordinates":[-122.781353,47.008444],"type":"Point"}
}