{
  "type": "Feature",
  "properties": {
    "iso:country":"US",
    "sg:address":"15900 NE 47th St",
    "sg:city":"Vancouver",
    "sg:classifiers":[
        {
            "category":"Building & Trades",
            "subcategory":"Construction",
            "type":"Services"
        }
    ],
    "sg:phone":"+1 360 281 3178",
    "sg:postcode":"98682",
    "sg:province":"WA",
    "sg:tags":[
        "floor",
        "laying",
        "contractor"
    ],
    "wof:name":"Douglas R Hall Flooring",
    "wof:placetype":"venue"
},
  "geometry": {"coordinates":[-122.508993,45.656446],"type":"Point"}
}