{
  "type": "Feature",
  "properties": {
    "addr:full":"915 Lawton Rd Lynnwood WA 98036",
    "addr:housenumber":"915",
    "addr:postcode":"98036",
    "addr:street":"Lawton Rd",
    "iso:country":"US",
    "sg:address":"915 Lawton Rd",
    "sg:city":"Lynnwood",
    "sg:classifiers":[
        {
            "category":"Wholesale",
            "subcategory":"Durable Goods & Equipment",
            "type":"Manufacturing & Wholesale Goods"
        }
    ],
    "sg:phone":"+1 425 672 0197",
    "sg:postcode":"98036",
    "sg:province":"WA",
    "sg:tags":[
        "representative",
        "manufacturer"
    ],
    "wof:name":"Pacific Resource Group",
    "wof:placetype":"venue"
},
  "geometry": {"coordinates":[-122.246745,47.814821],"type":"Point"}
}