{
  "type": "Feature",
  "properties": {
    "addr:full":"550 N Lake Surf Dr Lilliwaup WA 98555",
    "addr:housenumber":"550",
    "addr:postcode":"98555",
    "addr:street":"N Lake Surf Dr Lilliwaup",
    "iso:country":"US",
    "sg:address":"550 N Lake Surf Dr",
    "sg:city":"Lilliwaup",
    "sg:classifiers":[
        {
            "category":"Manufacturing",
            "subcategory":"Paper Products",
            "type":"Manufacturing & Wholesale Goods"
        }
    ],
    "sg:phone":"+1 360 877 6754",
    "sg:postcode":"98555",
    "sg:province":"WA",
    "sg:tags":[
        "die",
        "mfg"
    ],
    "wof:name":"Korian Kreations",
    "wof:placetype":"venue"
},
  "geometry": {"coordinates":[-123.068262,47.505626],"type":"Point"}
}