{
  "type": "Feature",
  "properties": {
    "addr:full":"423 E Main St Auburn WA 98002",
    "addr:housenumber":"423",
    "addr:postcode":"98002",
    "addr:street":"E Main St",
    "iso:country":"US",
    "sg:address":"423 E Main St",
    "sg:city":"Auburn",
    "sg:classifiers":[
        {
            "category":"Personal",
            "type":"Services"
        },
        {
            "category":"Sports & Exercise",
            "subcategory":"Gym",
            "type":"Entertainment"
        },
        {
            "category":"Health Services",
            "subcategory":"Health Practitioner",
            "type":"Services"
        },
        {
            "category":"Arena",
            "subcategory":"Sports Club",
            "type":"Entertainment"
        }
    ],
    "sg:phone":"+1 253 887 8959",
    "sg:postcode":"98002",
    "sg:province":"WA",
    "sg:tags":[
        "control",
        "weight",
        "consultant",
        "program",
        "fitness",
        "physical"
    ],
    "sg:website":"http://www.curves.com",
    "wof:name":"Curves",
    "wof:placetype":"venue"
},
  "geometry": {"coordinates":[-122.22380800000001,47.30761],"type":"Point"}
}