{
  "type": "Feature",
  "properties": {
    "addr:full":"318 Westlake Ave N Seattle WA 98109",
    "addr:housenumber":"318",
    "addr:postcode":"98109",
    "addr:street":"Westlake Ave N",
    "iso:country":"US",
    "sg:address":"318 Westlake Ave N",
    "sg:city":"Seattle",
    "sg:classifiers":[
        {
            "category":"Sports & Exercise",
            "subcategory":"Gym",
            "type":"Entertainment"
        }
    ],
    "sg:phone":"+1 206 621 8333",
    "sg:postcode":"98109",
    "sg:province":"WA",
    "sg:tags":[
        "sporting",
        "fitness",
        "physical",
        "facility"
    ],
    "wof:name":"E E C Fitness Superstore",
    "wof:placetype":"venue"
},
  "geometry": {"coordinates":[-122.33838299999999,47.621824],"type":"Point"}
}