{
  "type": "Feature",
  "properties": {
    "addr:full":"301 114th St S Tacoma WA 98444",
    "addr:housenumber":"301",
    "addr:postcode":"98444",
    "addr:street":"114Th St S",
    "iso:country":"US",
    "sg:address":"301 114th St S",
    "sg:city":"Tacoma",
    "sg:classifiers":[
        {
            "category":"Freight",
            "type":"Transportation"
        }
    ],
    "sg:phone":"+1 253 537 3508",
    "sg:postcode":"98444",
    "sg:province":"WA",
    "sg:tags":[
        "operator",
        "local",
        "trucking"
    ],
    "wof:name":"Overland Excavating",
    "wof:placetype":"venue"
},
  "geometry": {"coordinates":[-122.436323,47.153346],"type":"Point"}
}