{
  "type": "Feature",
  "properties": {
    "addr:full":"120 Park Ln Kirkland WA 98033",
    "addr:housenumber":"120",
    "addr:postcode":"98033",
    "addr:street":"Park Ln",
    "iso:country":"US",
    "sg:address":"120 Park Ln",
    "sg:city":"Kirkland",
    "sg:classifiers":[
        {
            "category":"Building & Trades",
            "subcategory":"Locksmith",
            "type":"Services"
        }
    ],
    "sg:phone":"+1 425 996 4406",
    "sg:postcode":"98033",
    "sg:province":"WA",
    "sg:tags":[
        "key"
    ],
    "wof:name":"24 Hour A Day Locksmith Service In Kirkland",
    "wof:placetype":"venue"
},
  "geometry": {"coordinates":[-122.206284,47.676149],"type":"Point"}
}