{
  "type": "Feature",
  "properties": {
    "addr:full":"4521 188th St SW Lynnwood WA 98037",
    "addr:housenumber":"4521",
    "addr:postcode":"98037",
    "addr:street":"188Th St Sw",
    "iso:country":"US",
    "sg:address":"4521 188th St SW",
    "sg:city":"Lynnwood",
    "sg:classifiers":[
        {
            "category":"Organizations",
            "subcategory":"Religious Organization",
            "type":"Services"
        }
    ],
    "sg:phone":"+1 425 774 4521",
    "sg:postcode":"98037",
    "sg:province":"WA",
    "wof:name":"Filipino Amrcn Chrstn Fllwship",
    "wof:placetype":"venue"
},
  "geometry": {"coordinates":[-122.294657,47.828336],"type":"Point"}
}