{
  "type": "Feature",
  "properties": {
    "addr:full":"14506 N Columbus St Spokane WA 99208",
    "addr:housenumber":"14506",
    "addr:postcode":"99208",
    "addr:street":"N Columbus St",
    "iso:country":"US",
    "sg:address":"14506 N Columbus St",
    "sg:city":"Spokane",
    "sg:classifiers":[
        {
            "category":"Professional",
            "type":"Services"
        }
    ],
    "sg:phone":"+1 509 467 4465",
    "sg:postcode":"99208",
    "sg:province":"WA",
    "wof:name":"Kim M Hopkins Business Svc",
    "wof:placetype":"venue"
},
  "geometry": {"coordinates":[-117.39349,47.789597],"type":"Point"}
}