{
  "type": "Feature",
  "properties": {
    "addr:full":"615 Monahan Rd Castle Rock WA 98611",
    "addr:housenumber":"615",
    "addr:postcode":"98611",
    "addr:street":"Monahan Rd",
    "iso:country":"US",
    "sg:address":"615 Monahan Rd",
    "sg:city":"Castle Rock",
    "sg:classifiers":[
        {
            "category":"Farming",
            "subcategory":"Poultry Farm",
            "type":"Manufacturing & Wholesale Goods"
        }
    ],
    "sg:phone":"+1 360 274 6277",
    "sg:postcode":"98611",
    "sg:province":"WA",
    "sg:tags":[
        "chicken",
        "logging"
    ],
    "wof:name":"Kayser Melvin L",
    "wof:placetype":"venue"
},
  "geometry": {"coordinates":[-122.99022100000001,46.272142],"type":"Point"}
}