{
  "type": "Feature",
  "properties": {
    "addr:full":"11315 NE 65th St Kirkland WA 98033",
    "addr:housenumber":"11315",
    "addr:postcode":"98033",
    "addr:street":"Ne 65Th St",
    "iso:country":"US",
    "sg:address":"11315 NE 65th St",
    "sg:city":"Kirkland",
    "sg:classifiers":[
        {
            "category":"Building & Trades",
            "subcategory":"Landscaping Services",
            "type":"Services"
        }
    ],
    "sg:phone":"+1 425 827 7244",
    "sg:postcode":"98033",
    "sg:province":"WA",
    "sg:tags":[
        "lawn",
        "landscape",
        "contractor"
    ],
    "wof:name":"Cedergreens, Inc.",
    "wof:placetype":"venue"
},
  "geometry": {"coordinates":[-122.188953,47.664672],"type":"Point"}
}