{
  "type": "Feature",
  "properties": {
    "addr:full":"820 Commercial St Leavenworth WA 98826",
    "addr:housenumber":"820",
    "addr:postcode":"98826",
    "addr:street":"Commercial St",
    "iso:country":"US",
    "sg:address":"820 Commercial St",
    "sg:city":"Leavenworth",
    "sg:classifiers":[
        {
            "category":"Building & Trades",
            "subcategory":"Construction",
            "type":"Services"
        }
    ],
    "sg:phone":"+1 509 548 2158",
    "sg:postcode":"98826",
    "sg:province":"WA",
    "sg:tags":[
        "wallpaper"
    ],
    "wof:name":"Schnickelfritz Paper Co",
    "wof:placetype":"venue"
},
  "geometry": {"coordinates":[-120.656463,47.596397],"type":"Point"}
}