{
  "type": "Feature",
  "properties": {
    "addr:full":"3903 E Olympic Ave Spokane WA 99217",
    "addr:housenumber":"3903",
    "addr:postcode":"99217",
    "addr:street":"E Olympic Ave",
    "iso:country":"US",
    "sg:address":"3903 E Olympic Ave",
    "sg:city":"Spokane",
    "sg:classifiers":[
        {
            "category":"Building & Trades",
            "subcategory":"Construction",
            "type":"Services"
        }
    ],
    "sg:phone":"+1 509 484 6877",
    "sg:postcode":"99217",
    "sg:province":"WA",
    "sg:tags":[
        "masonry",
        "contractor"
    ],
    "wof:name":"Great Northern Masonry",
    "wof:placetype":"venue"
},
  "geometry": {"coordinates":[-117.353104,47.703147],"type":"Point"}
}