{
  "type": "Feature",
  "properties": {
    "addr:full":"4310 B St NW Auburn WA 98001",
    "addr:housenumber":"4310",
    "addr:postcode":"98001",
    "addr:street":"B St Nw",
    "iso:country":"US",
    "sg:address":"4310 B St NW",
    "sg:city":"Auburn",
    "sg:classifiers":[
        {
            "category":"Professional",
            "subcategory":"Management & Consulting",
            "type":"Services"
        },
        {
            "category":"Professional",
            "subcategory":"Advertising",
            "type":"Services"
        }
    ],
    "sg:phone":"+1 253 859 9568",
    "sg:postcode":"98001",
    "sg:province":"WA",
    "sg:tags":[
        "marketing",
        "program",
        "consultant"
    ],
    "wof:name":"Oliver Marketing",
    "wof:placetype":"venue"
},
  "geometry": {"coordinates":[-122.23233500000001,47.345287],"type":"Point"}
}