{
  "type": "Feature",
  "properties": {
    "iso:country":"US",
    "sg:address":"640 Frontier St",
    "sg:city":"Clallam Bay",
    "sg:classifiers":[
        {
            "category":"Travel",
            "subcategory":"Campground",
            "type":"Entertainment"
        }
    ],
    "sg:phone":"+1 360 963 2890",
    "sg:postcode":"98326",
    "sg:province":"WA",
    "wof:name":"Fish On Rv Park & Dry Storage",
    "wof:placetype":"venue"
},
  "geometry": {"coordinates":[-124.25117899999999,48.259408],"type":"Point"}
}