{
  "type": "Feature",
  "properties": {
    "iso:country":"US",
    "sg:address":"714 N 28th Ave",
    "sg:city":"Yakima",
    "sg:classifiers":[
        {
            "category":"Manufacturing",
            "subcategory":"Tools & Machinery",
            "type":"Manufacturing & Wholesale Goods"
        }
    ],
    "sg:phone":"+1 509 248 8957",
    "sg:postcode":"98902",
    "sg:province":"WA",
    "sg:tags":[
        "transmission",
        "equipment",
        "power",
        "mfg"
    ],
    "wof:name":"PR Fabrications",
    "wof:placetype":"venue"
},
  "geometry": {"coordinates":[-120.54619700000001,46.610715],"type":"Point"}
}