{
  "type": "Feature",
  "properties": {
    "addr:full":"6400 15th Avenue NW Seattle WA 98107",
    "addr:housenumber":"6400",
    "addr:postcode":"98107",
    "addr:street":"15Th Avenue Nw",
    "iso:country":"US",
    "sg:address":"6400 15th Avenue NW",
    "sg:city":"Seattle",
    "sg:classifiers":[
        {
            "category":"Retail",
            "subcategory":"Laundry & Dry Cleaning",
            "type":"Services"
        }
    ],
    "sg:phone":"+1 206 789 5770",
    "sg:postcode":"98107",
    "sg:province":"WA",
    "wof:name":"Corry's Fine Dry Cleaning",
    "wof:placetype":"venue"
},
  "geometry": {"coordinates":[-122.376041,47.675337],"type":"Point"}
}