{
  "type": "Feature",
  "properties": {
    "addr:full":"534 Rainier Ave S Renton WA 98055",
    "addr:housenumber":"534",
    "addr:postcode":"98055",
    "addr:street":"Rainier Ave S Renton",
    "iso:country":"US",
    "sg:address":"534 Rainier Ave S",
    "sg:city":"Renton",
    "sg:classifiers":[
        {
            "category":"Personal",
            "subcategory":"Nail Salon",
            "type":"Services"
        }
    ],
    "sg:phone":"+1 425 235 8656",
    "sg:postcode":"98055",
    "sg:province":"WA",
    "wof:name":"Perfect Nail Salon",
    "wof:placetype":"venue"
},
  "geometry": {"coordinates":[-122.214996,47.4753],"type":"Point"}
}