{
  "type": "Feature",
  "properties": {
    "addr:full":"8515 NE 25th St Bellevue WA 98004",
    "addr:housenumber":"8515",
    "addr:postcode":"98004",
    "addr:street":"Ne 25Th St",
    "iso:country":"US",
    "sg:address":"8515 NE 25th St",
    "sg:city":"Bellevue",
    "sg:classifiers":[
        {
            "category":"Restaurant",
            "type":"Food & Drink"
        }
    ],
    "sg:phone":"+1 425 454 7085",
    "sg:postcode":"98004",
    "sg:province":"WA",
    "sg:tags":[
        "eating"
    ],
    "wof:name":"Shays Catering",
    "wof:placetype":"venue"
},
  "geometry": {"coordinates":[-122.22563100000001,47.632454],"type":"Point"}
}