{
  "type": "Feature",
  "properties": {
    "addr:full":"1511 NE 166th St Shoreline WA 98155",
    "addr:housenumber":"1511",
    "addr:postcode":"98155",
    "addr:street":"Ne 166Th St",
    "iso:country":"US",
    "sg:address":"1511 NE 166th St",
    "sg:city":"Shoreline",
    "sg:classifiers":[
        {
            "category":"Retail",
            "subcategory":"Pet Boarding",
            "type":"Services"
        },
        {
            "category":"Retail",
            "subcategory":"Animal Services",
            "type":"Services"
        }
    ],
    "sg:phone":"+1 206 367 3325",
    "sg:postcode":"98155",
    "sg:province":"WA",
    "sg:tags":[
        "kennel"
    ],
    "sg:website":"http://www.purrfectcatboarding.com",
    "wof:name":"Purrfect Cat Boarding/Vacation Solutions",
    "wof:placetype":"venue"
},
  "geometry": {"coordinates":[-122.312926,47.749358],"type":"Point"}
}