{
  "type": "Feature",
  "properties": {
    "addr:full":"1322 N Wenatchee Ave Wenatchee WA 98801",
    "addr:housenumber":"1322",
    "addr:postcode":"98801",
    "addr:street":"N Wenatchee Ave",
    "iso:country":"US",
    "sg:address":"1322 N Wenatchee Ave",
    "sg:city":"Wenatchee",
    "sg:classifiers":[
        {
            "category":"Retail",
            "subcategory":"Auto Repair",
            "type":"Services"
        }
    ],
    "sg:phone":"+1 509 663 4947",
    "sg:postcode":"98801",
    "sg:province":"WA",
    "sg:tags":[
        "repairing",
        "automobile"
    ],
    "wof:name":"Quality Import Repair & Sales",
    "wof:placetype":"venue"
},
  "geometry": {"coordinates":[-120.32487999999999,47.441036],"type":"Point"}
}