{
  "type": "Feature",
  "properties": {
    "addr:full":"7409 NE Hazel Dell Ave Vancouver WA 98665",
    "addr:housenumber":"7409",
    "addr:postcode":"98665",
    "addr:street":"Ne Hazel Dell Ave",
    "iso:country":"US",
    "sg:address":"7409 NE Hazel Dell Ave",
    "sg:city":"Vancouver",
    "sg:classifiers":[
        {
            "category":"Health Services",
            "subcategory":"Hospital",
            "type":"Services"
        }
    ],
    "sg:phone":"+1 360 750 7026",
    "sg:postcode":"98665",
    "sg:province":"WA",
    "sg:tags":[
        "mental"
    ],
    "wof:name":"Columbia River Adult Day Hlth",
    "wof:placetype":"venue"
},
  "geometry": {"coordinates":[-122.668582,45.676495],"type":"Point"}
}