{
  "type": "Feature",
  "properties": {
    "addr:full":"556 S 330th Pl Federal Way WA 98003",
    "addr:housenumber":"556",
    "addr:postcode":"98003",
    "addr:street":"S 330Th Pl",
    "iso:country":"US",
    "sg:address":"556 S 330th Pl",
    "sg:city":"Federal Way",
    "sg:classifiers":[
        {
            "category":"Shopping",
            "subcategory":"Pharmacy",
            "type":"Retail Goods"
        }
    ],
    "sg:phone":"+1 253 835 9727",
    "sg:postcode":"98003",
    "sg:province":"WA",
    "wof:name":"Asaave International",
    "wof:placetype":"venue"
},
  "geometry": {"coordinates":[-122.327091,47.309474],"type":"Point"}
}