{
  "type": "Feature",
  "properties": {
    "addr:full":"903 W Broadway Ave Spokane WA 99201",
    "addr:housenumber":"903",
    "addr:postcode":"99201",
    "addr:street":"W Broadway Ave",
    "iso:country":"US",
    "sg:address":"903 W Broadway Ave",
    "sg:city":"Spokane",
    "sg:classifiers":[
        {
            "category":"Communications",
            "subcategory":"Film & Video Production",
            "type":"Services"
        }
    ],
    "sg:phone":"+1 509 324 2949",
    "sg:postcode":"99201",
    "sg:province":"WA",
    "sg:tags":[
        "tape"
    ],
    "sg:website":"www.nxnw.net",
    "wof:name":"North By Northwest Productions",
    "wof:placetype":"venue"
},
  "geometry": {"coordinates":[-117.42659500000001,47.664312],"type":"Point"}
}