{
  "type": "Feature",
  "properties": {
    "addr:full":"2813 N Rd 92 Pasco WA 99301",
    "addr:housenumber":"2813;92",
    "addr:postcode":"99301",
    "addr:street":"N Rd",
    "iso:country":"US",
    "sg:address":"2813 N Rd 92",
    "sg:city":"Pasco",
    "sg:classifiers":[
        {
            "category":"Retail",
            "subcategory":"Animal Services",
            "type":"Services"
        }
    ],
    "sg:phone":"+1 509 544 9350",
    "sg:postcode":"99301",
    "sg:province":"WA",
    "wof:name":"Legacy-Miniature Schnauzers",
    "wof:placetype":"venue"
},
  "geometry": {"coordinates":[-119.21155299999999,46.256369],"type":"Point"}
}