{
  "type": "Feature",
  "properties": {
    "addr:full":"2619 1st Ave Seattle WA 98121",
    "addr:housenumber":"2619",
    "addr:postcode":"98121",
    "addr:street":"1St Ave",
    "iso:country":"US",
    "sg:address":"2619 1st Ave",
    "sg:city":"Seattle",
    "sg:classifiers":[
        {
            "category":"Restaurant",
            "type":"Food & Drink"
        }
    ],
    "sg:phone":"+1 206 728 1648",
    "sg:postcode":"98121",
    "sg:province":"WA",
    "wof:name":"C J's Restaurant",
    "wof:placetype":"venue"
},
  "geometry": {"coordinates":[-122.35055199999999,47.615642],"type":"Point"}
}