{
  "type": "Feature",
  "properties": {
    "addr:full":"5920 100th St SW Lakewood WA 98499",
    "addr:housenumber":"5920",
    "addr:postcode":"98499",
    "addr:street":"100Th St Sw",
    "iso:country":"US",
    "sg:address":"5920 100th St SW",
    "sg:city":"Lakewood",
    "sg:classifiers":[
        {
            "category":"Health Services",
            "subcategory":"Doctor",
            "type":"Services"
        }
    ],
    "sg:phone":"+1 253 581 6303",
    "sg:postcode":"98499",
    "sg:province":"WA",
    "sg:tags":[
        "medical"
    ],
    "wof:name":"Manuel Bautista",
    "wof:placetype":"venue"
},
  "geometry": {"coordinates":[-122.51770500000001,47.166638],"type":"Point"}
}