{
  "type": "Feature",
  "properties": {
    "addr:full":"6703 Bethel Rd SE Port Orchard WA 98367",
    "addr:housenumber":"6703",
    "addr:postcode":"98367",
    "addr:street":"Bethel Rd Se",
    "iso:country":"US",
    "sg:address":"6703 Bethel Rd SE",
    "sg:city":"Port Orchard",
    "sg:classifiers":[
        {
            "category":"Organizations",
            "subcategory":"Religious Organization",
            "type":"Services"
        }
    ],
    "sg:phone":"+1 360 876 0602",
    "sg:postcode":"98367",
    "sg:province":"WA",
    "sg:tags":[
        "church"
    ],
    "sg:website":"www.biblebaptistportorchard.com",
    "wof:name":"Bible Baptist Church Inc",
    "wof:placetype":"venue"
},
  "geometry": {"coordinates":[-122.631906,47.488542],"type":"Point"}
}