{
  "type": "Feature",
  "properties": {
    "addr:full":"902 2nd St Snohomish WA 98290",
    "addr:housenumber":"902",
    "addr:postcode":"98290",
    "addr:street":"2Nd St",
    "iso:country":"US",
    "sg:address":"902 2nd St",
    "sg:city":"Snohomish",
    "sg:classifiers":[
        {
            "category":"Banks & Credit Unions",
            "subcategory":"Bank",
            "type":"Services"
        }
    ],
    "sg:phone":"+1 360 568 2151",
    "sg:postcode":"98290",
    "sg:province":"WA",
    "sg:website":"www.wamu.com",
    "wof:name":"Washington Mutual",
    "wof:placetype":"venue"
},
  "geometry": {"coordinates":[-122.094403,47.912972],"type":"Point"}
}