{
  "type": "Feature",
  "properties": {
    "addr:full":"454 E Smith Rd Bellingham WA 98226",
    "addr:housenumber":"454",
    "addr:postcode":"98226",
    "addr:street":"E Smith Rd",
    "iso:country":"US",
    "sg:address":"454 E Smith Rd",
    "sg:city":"Bellingham",
    "sg:classifiers":[
        {
            "category":"Manufacturing",
            "subcategory":"Retail Goods",
            "type":"Manufacturing & Wholesale Goods"
        }
    ],
    "sg:phone":"+1 360 398 0289",
    "sg:postcode":"98226",
    "sg:province":"WA",
    "sg:tags":[
        "product",
        "mfg"
    ],
    "wof:name":"Nbs Industries",
    "wof:placetype":"venue"
},
  "geometry": {"coordinates":[-122.4678,48.833379],"type":"Point"}
}