{
  "type": "Feature",
  "properties": {
    "addr:full":"8605 E Trent Ave Spokane Valley WA 99212",
    "addr:housenumber":"8605",
    "addr:postcode":"99212",
    "addr:street":"E Trent Ave",
    "iso:country":"US",
    "sg:address":"8605 E Trent Ave",
    "sg:city":"Spokane Valley",
    "sg:classifiers":[
        {
            "category":"Shopping",
            "subcategory":"Florist",
            "type":"Retail Goods"
        }
    ],
    "sg:phone":"+1 509 928 0950",
    "sg:postcode":"99212",
    "sg:province":"WA",
    "sg:tags":[
        "plant",
        "flower",
        "gift"
    ],
    "wof:name":"Riverpark Flowers & Gifts",
    "wof:placetype":"venue"
},
  "geometry": {"coordinates":[-117.28910999999999,47.679831],"type":"Point"}
}