{
  "type": "Feature",
  "properties": {
    "addr:full":"Evergreen Way Everett WA 98203",
    "addr:postcode":"98203",
    "addr:street":"Evergreen Way",
    "iso:country":"US",
    "sg:address":"Evergreen Way",
    "sg:city":"Everett",
    "sg:classifiers":[
        {
            "category":"Organizations",
            "subcategory":"Professional Association",
            "type":"Services"
        }
    ],
    "sg:phone":"+1 206 931 9361",
    "sg:postcode":"98203",
    "sg:province":"WA",
    "sg:tags":[
        "agency",
        "bureau",
        "entertainment"
    ],
    "sg:website":"http://www.bugsieproductions.com",
    "wof:name":"Bugsie Productions",
    "wof:placetype":"venue"
},
  "geometry": {"coordinates":[-122.22778700000001,47.922199],"type":"Point"}
}