{
  "type": "Feature",
  "properties": {
    "addr:full":"10876 NW Myhre Pl Ste 108 Silverdale WA 98383",
    "addr:housenumber":"10876;108",
    "addr:postcode":"98383",
    "addr:street":"Nw Myhre Pl Ste",
    "iso:country":"US",
    "sg:address":"10876 NW Myhre Pl Ste 108",
    "sg:city":"Silverdale",
    "sg:classifiers":[
        {
            "category":"Restaurant",
            "type":"Food & Drink"
        }
    ],
    "sg:phone":"+1 360 698 0929",
    "sg:postcode":"98383",
    "sg:province":"WA",
    "sg:tags":[
        "style",
        "pan",
        "japanese",
        "family",
        "asian"
    ],
    "wof:name":"Hakata Japanese Restaurant",
    "wof:placetype":"venue"
},
  "geometry": {"coordinates":[-122.687686,47.661704],"type":"Point"}
}