{
  "type": "Feature",
  "properties": {
    "addr:full":"601 N Fork Rd Chehalis WA 98532",
    "addr:housenumber":"601",
    "addr:postcode":"98532",
    "addr:street":"N Fork Rd",
    "iso:country":"US",
    "sg:address":"601 N Fork Rd",
    "sg:city":"Chehalis",
    "sg:classifiers":[
        {
            "category":"Manufacturing",
            "subcategory":"Lumber",
            "type":"Manufacturing & Wholesale Goods"
        }
    ],
    "sg:phone":"+1 360 262 0314",
    "sg:postcode":"98532",
    "sg:province":"WA",
    "sg:tags":[
        "reforestation"
    ],
    "wof:name":"Martinez Honorio",
    "wof:placetype":"venue"
},
  "geometry": {"coordinates":[-122.814263,46.616009],"type":"Point"}
}