{
  "type": "Feature",
  "properties": {
    "addr:full":"3128 E Evergreen Blvd Vancouver WA 98661",
    "addr:housenumber":"3128",
    "addr:postcode":"98661",
    "addr:street":"E Evergreen Blvd",
    "iso:country":"US",
    "sg:address":"3128 E Evergreen Blvd",
    "sg:city":"Vancouver",
    "sg:classifiers":[
        {
            "category":"Restaurant",
            "type":"Food & Drink"
        }
    ],
    "sg:phone":"+1 360 690 0803",
    "sg:postcode":"98661",
    "sg:province":"WA",
    "sg:tags":[
        "burger"
    ],
    "wof:name":"The Igloo Restaurant",
    "wof:placetype":"venue"
},
  "geometry": {"coordinates":[-122.63821299999999,45.626207],"type":"Point"}
}