{
  "type": "Feature",
  "properties": {
    "addr:full":"1561 Number 6 Rd Ellensburg WA 98926",
    "addr:housenumber":"1561",
    "addr:postcode":"98926",
    "addr:street":"Number 6 Rd",
    "iso:country":"US",
    "sg:address":"1561 Number 6 Rd",
    "sg:city":"Ellensburg",
    "sg:classifiers":[
        {
            "category":"Building & Trades",
            "subcategory":"Construction",
            "type":"Services"
        }
    ],
    "sg:phone":"+1 509 925 4030",
    "sg:postcode":"98926",
    "sg:province":"WA",
    "sg:tags":[
        "excavation",
        "operator",
        "contractor",
        "local",
        "trucking"
    ],
    "wof:name":"Elbow Backhoe & Hauling",
    "wof:placetype":"venue"
},
  "geometry": {"coordinates":[-120.498079,46.985139],"type":"Point"}
}