{
  "type": "Feature",
  "properties": {
    "addr:full":"2238 Birch Bay Lynden Rd Custer WA 98240",
    "addr:housenumber":"2238",
    "addr:postcode":"98240",
    "addr:street":"Birch Bay Lynden Rd",
    "iso:country":"US",
    "sg:address":"2238 Birch Bay Lynden Rd",
    "sg:city":"Custer",
    "sg:classifiers":[
        {
            "category":"Building & Trades",
            "subcategory":"Construction",
            "type":"Services"
        }
    ],
    "sg:phone":"+1 360 366 9397",
    "sg:postcode":"98240",
    "sg:province":"WA",
    "sg:tags":[
        "residential",
        "general",
        "contractor"
    ],
    "wof:name":"Comfort Builders Inc",
    "wof:placetype":"venue"
},
  "geometry": {"coordinates":[-122.603196,48.935533],"type":"Point"}
}