{
  "type": "Feature",
  "properties": {
    "addr:full":"615 NW Guy St Pullman WA 99163",
    "addr:housenumber":"615",
    "addr:postcode":"99163",
    "addr:street":"Nw Guy St",
    "iso:country":"US",
    "sg:address":"615 NW Guy St",
    "sg:city":"Pullman",
    "sg:classifiers":[
        {
            "category":"Freight",
            "type":"Transportation"
        }
    ],
    "sg:phone":"+1 509 332 4865",
    "sg:postcode":"99163",
    "sg:province":"WA",
    "sg:tags":[
        "commercial",
        "storage"
    ],
    "wof:name":"Morgan Rent-A-Space",
    "wof:placetype":"venue"
},
  "geometry": {"coordinates":[-117.188671,46.734727],"type":"Point"}
}