{
  "type": "Feature",
  "properties": {
    "addr:full":"23632 Highway 99 Ste F-347 Edmonds WA 98026",
    "addr:housenumber":"23632",
    "addr:postcode":"98026",
    "addr:street":"Highway 99 Ste",
    "iso:country":"US",
    "sg:address":"23632 Highway 99 Ste F-347",
    "sg:city":"Edmonds",
    "sg:classifiers":[
        {
            "category":"Professional",
            "subcategory":"Management & Consulting",
            "type":"Services"
        }
    ],
    "sg:phone":"+1 206 546 4017",
    "sg:postcode":"98026",
    "sg:province":"WA",
    "sg:tags":[
        "consultant"
    ],
    "wof:name":"Richings And Associates",
    "wof:placetype":"venue"
},
  "geometry": {"coordinates":[-122.34246400000001,47.784764],"type":"Point"}
}