{
  "type": "Feature",
  "properties": {
    "addr:full":"4216 6th Avenue NW Seattle WA 98107",
    "addr:housenumber":"4216",
    "addr:postcode":"98107",
    "addr:street":"6Th Avenue Nw",
    "iso:country":"US",
    "sg:address":"4216 6th Avenue NW",
    "sg:city":"Seattle",
    "sg:classifiers":[
        {
            "category":"Professional",
            "type":"Services"
        }
    ],
    "sg:phone":"+1 206 781 8149",
    "sg:postcode":"98107",
    "sg:province":"WA",
    "sg:tags":[
        "caterer"
    ],
    "sg:website":"www.cameroncatering.com",
    "wof:name":"Cameron Catering",
    "wof:placetype":"venue"
},
  "geometry": {"coordinates":[-122.363781,47.658254],"type":"Point"}
}