{
  "type": "Feature",
  "properties": {
    "addr:full":"38500 N Grove Rd Deer Park WA 99006",
    "addr:housenumber":"38500",
    "addr:postcode":"99006",
    "addr:street":"N Grove Rd",
    "iso:country":"US",
    "sg:address":"38500 N Grove Rd",
    "sg:city":"Deer Park",
    "sg:classifiers":[
        {
            "category":"Wholesale",
            "subcategory":"Drugs",
            "type":"Manufacturing & Wholesale Goods"
        }
    ],
    "sg:phone":"+1 509 276 7555",
    "sg:postcode":"99006",
    "sg:province":"WA",
    "sg:tags":[
        "cosmetic"
    ],
    "wof:name":"L Q Enterprises",
    "wof:placetype":"venue"
},
  "geometry": {"coordinates":[-117.50165200000001,48.015019],"type":"Point"}
}