{
  "type": "Feature",
  "properties": {
    "iso:country":"US",
    "sg:address":"6649 S 216th St",
    "sg:city":"Kent",
    "sg:classifiers":[
        {
            "category":"Retail",
            "subcategory":"Repair Shop",
            "type":"Services"
        }
    ],
    "sg:phone":"+1 253 872 3695",
    "sg:postcode":"98032",
    "sg:province":"WA",
    "wof:name":"Diamond Power Speciality Co",
    "wof:placetype":"venue"
},
  "geometry": {"coordinates":[-122.25160700000001,47.408459],"type":"Point"}
}