{
  "type": "Feature",
  "properties": {
    "addr:full":"5305 N McKinzie Rd Otis Orchards WA 99027",
    "addr:housenumber":"5305",
    "addr:postcode":"99027",
    "addr:street":"N Mckinzie Rd",
    "iso:country":"US",
    "sg:address":"5305 N McKinzie Rd",
    "sg:city":"Otis Orchards",
    "sg:classifiers":[
        {
            "category":"Retail",
            "subcategory":"Repair Shop",
            "type":"Services"
        }
    ],
    "sg:phone":"+1 509 893 1533",
    "sg:postcode":"99027",
    "sg:province":"WA",
    "sg:tags":[
        "welding"
    ],
    "wof:name":"Steve Carter Welding",
    "wof:placetype":"venue"
},
  "geometry": {"coordinates":[-117.09863,47.702045],"type":"Point"}
}