{
  "type": "Feature",
  "properties": {
    "addr:full":"24090 NE State Rte 3 Belfair WA 98528",
    "addr:housenumber":"24090",
    "addr:postcode":"98528",
    "addr:street":"Ne State Rte 3",
    "iso:country":"US",
    "sg:address":"24090 NE State Rte 3",
    "sg:city":"Belfair",
    "sg:classifiers":[
        {
            "category":"Insurance",
            "subcategory":"Insurance Agent",
            "type":"Services"
        }
    ],
    "sg:phone":"+1 360 275 9636",
    "sg:postcode":"98528",
    "sg:province":"WA",
    "wof:name":"Allstate Insurance",
    "wof:placetype":"venue"
},
  "geometry": {"coordinates":[-122.819384,47.455345],"type":"Point"}
}