{
  "type": "Feature",
  "properties": {
    "iso:country":"US",
    "sg:address":"8601 Canyon Rd E",
    "sg:city":"Puyallup",
    "sg:classifiers":[
        {
            "category":"Building & Trades",
            "subcategory":"Plumbing",
            "type":"Services"
        }
    ],
    "sg:phone":"+1 253 845 1213",
    "sg:postcode":"98371",
    "sg:province":"WA",
    "sg:tags":[
        "contractor"
    ],
    "wof:name":"Dicks Heating & AC",
    "wof:placetype":"venue"
},
  "geometry": {"coordinates":[-122.357153,47.177718],"type":"Point"}
}