{
  "type": "Feature",
  "properties": {
    "iso:country":"US",
    "sg:address":"117 E Main St",
    "sg:city":"Goldendale",
    "sg:classifiers":[
        {
            "category":"Professional",
            "subcategory":"Lawyer & Legal Services",
            "type":"Services"
        }
    ],
    "sg:phone":"+1 509 773 4988",
    "sg:postcode":"98620",
    "sg:province":"WA",
    "wof:name":"Norris Construction Inc",
    "wof:placetype":"venue"
},
  "geometry": {"coordinates":[-120.82241999999999,45.822292],"type":"Point"}
}