{
  "type": "Feature",
  "properties": {
    "addr:full":"21416 NE 10th Ave Ridgefield WA 98642",
    "addr:housenumber":"21416",
    "addr:postcode":"98642",
    "addr:street":"Ne 10Th Ave",
    "iso:country":"US",
    "sg:address":"21416 NE 10th Ave",
    "sg:city":"Ridgefield",
    "sg:classifiers":[
        {
            "category":"Retail",
            "subcategory":"Veterinary Services",
            "type":"Services"
        }
    ],
    "sg:phone":"+1 360 887 0714",
    "sg:postcode":"98642",
    "sg:province":"WA",
    "sg:tags":[
        "veterinarian"
    ],
    "wof:name":"Healing Star Veterinary & Anim",
    "wof:placetype":"venue"
},
  "geometry": {"coordinates":[-122.661728,45.773917],"type":"Point"}
}