{
  "type": "Feature",
  "properties": {
    "iso:country":"US",
    "sg:address":"3125 E Francis Ave",
    "sg:city":"Spokane",
    "sg:classifiers":[
        {
            "category":"Retail",
            "subcategory":"Auto Repair",
            "type":"Services"
        }
    ],
    "sg:phone":"+1 509 466 2086",
    "sg:postcode":"99208",
    "sg:province":"WA",
    "sg:tags":[
        "exchanging",
        "engine"
    ],
    "wof:name":"Schuck's Auto Supply",
    "wof:placetype":"venue"
},
  "geometry": {"coordinates":[-117.36326099999999,47.714998],"type":"Point"}
}