{
  "type": "Feature",
  "properties": {
    "addr:full":"30102 NE 108th Ave Battle Ground WA 98604",
    "addr:housenumber":"30102",
    "addr:postcode":"98604",
    "addr:street":"Ne 108Th Ave",
    "iso:country":"US",
    "sg:address":"30102 NE 108th Ave",
    "sg:city":"Battle Ground",
    "sg:classifiers":[
        {
            "category":"Professional",
            "subcategory":"Management & Consulting",
            "type":"Services"
        }
    ],
    "sg:phone":"+1 360 687 0823",
    "sg:postcode":"98604",
    "sg:province":"WA",
    "wof:name":"Okawa Enterprises",
    "wof:placetype":"venue"
},
  "geometry": {"coordinates":[-122.562449,45.839456],"type":"Point"}
}