{
  "type": "Feature",
  "properties": {
    "iso:country":"US",
    "sg:address":"8395 NE Grizdale Ln",
    "sg:city":"Bainbridge Island",
    "sg:classifiers":[
        {
            "category":"Professional",
            "subcategory":"Management & Consulting",
            "type":"Services"
        }
    ],
    "sg:phone":"+1 206 780 9942",
    "sg:postcode":"98110",
    "sg:province":"WA",
    "sg:tags":[
        "business"
    ],
    "wof:name":"Cummings Consulting L L C",
    "wof:placetype":"venue"
},
  "geometry": {"coordinates":[-122.537936,47.644786],"type":"Point"}
}