{
  "type": "Feature",
  "properties": {
    "addr:full":"7209 NE 152nd Pl Kenmore WA 98028",
    "addr:housenumber":"7209",
    "addr:postcode":"98028",
    "addr:street":"Ne 152Nd Pl",
    "iso:country":"US",
    "sg:address":"7209 NE 152nd Pl",
    "sg:city":"Kenmore",
    "sg:classifiers":[
        {
            "category":"Health Services",
            "subcategory":"Health Practitioner",
            "type":"Services"
        },
        {
            "category":"Social Services",
            "subcategory":"Retirement Home",
            "type":"Services"
        }
    ],
    "sg:phone":"+1 425 877 1440",
    "sg:postcode":"98028",
    "sg:province":"WA",
    "sg:tags":[
        "care"
    ],
    "sg:website":"www.shariezhaven.com",
    "wof:name":"Shari's LakeHaven Adult Family Home",
    "wof:placetype":"venue"
},
  "geometry": {"coordinates":[-122.24345700000001,47.738559],"type":"Point"}
}