{
  "type": "Feature",
  "properties": {
    "addr:full":"13427 E 32nd Ave Spokane Valley WA 99216",
    "addr:housenumber":"13427",
    "addr:postcode":"99216",
    "addr:street":"E 32Nd Ave",
    "iso:country":"US",
    "sg:address":"13427 E 32nd Ave",
    "sg:city":"Spokane Valley",
    "sg:classifiers":[
        {
            "category":"Personal",
            "subcategory":"Beauty Salon",
            "type":"Services"
        }
    ],
    "sg:phone":"+1 509 891 7562",
    "sg:postcode":"99216",
    "sg:province":"WA",
    "sg:tags":[
        "shop"
    ],
    "wof:name":"Creative Cuts",
    "wof:placetype":"venue"
},
  "geometry": {"coordinates":[-117.225916,47.627959],"type":"Point"}
}