{
  "type": "Feature",
  "properties": {
    "addr:full":"223 Hudon Rd Sequim WA 98382",
    "addr:housenumber":"223",
    "addr:postcode":"98382",
    "addr:street":"Hudon Rd",
    "iso:country":"US",
    "sg:address":"223 Hudon Rd",
    "sg:city":"Sequim",
    "sg:classifiers":[
        {
            "category":"Restaurant",
            "type":"Food & Drink"
        }
    ],
    "sg:phone":"+1 360 681 7523",
    "sg:postcode":"98382",
    "sg:province":"WA",
    "wof:name":"Nicks Antique Car Restorat",
    "wof:placetype":"venue"
},
  "geometry": {"coordinates":[-123.13381800000001,48.094229],"type":"Point"}
}