{
  "type": "Feature",
  "properties": {
    "addr:full":"10220 S Sharon Rd Spokane WA 99223",
    "addr:housenumber":"10220",
    "addr:postcode":"99223",
    "addr:street":"S Sharon Rd",
    "iso:country":"US",
    "sg:address":"10220 S Sharon Rd",
    "sg:city":"Spokane",
    "sg:classifiers":[
        {
            "category":"Building & Trades",
            "subcategory":"Landscaping Services",
            "type":"Services"
        }
    ],
    "sg:phone":"+1 509 448 1639",
    "sg:postcode":"99223",
    "sg:province":"WA",
    "sg:tags":[
        "tree"
    ],
    "sg:website":"www.inlandtreeservice.com",
    "wof:name":"Inland Tree Svc Inc",
    "wof:placetype":"venue"
},
  "geometry": {"coordinates":[-117.29995099999999,47.560146],"type":"Point"}
}