{
  "type": "Feature",
  "properties": {
    "addr:full":"17715 162nd Ave SE Renton WA 98058",
    "addr:housenumber":"17715",
    "addr:postcode":"98058",
    "addr:street":"162Nd Ave Se",
    "iso:country":"US",
    "sg:address":"17715 162nd Ave SE",
    "sg:city":"Renton",
    "sg:classifiers":[
        {
            "category":"Wholesale",
            "subcategory":"Non-durable Goods",
            "type":"Manufacturing & Wholesale Goods"
        }
    ],
    "sg:phone":"+1 425 271 6496",
    "sg:postcode":"98058",
    "sg:province":"WA",
    "wof:name":"Inspirations",
    "wof:placetype":"venue"
},
  "geometry": {"coordinates":[-122.125514,47.443063],"type":"Point"}
}