{
  "type": "Feature",
  "properties": {
    "addr:full":"5812 Banner Rd SE Port Orchard WA 98367",
    "addr:housenumber":"5812",
    "addr:postcode":"98367",
    "addr:street":"Banner Rd Se",
    "iso:country":"US",
    "sg:address":"5812 Banner Rd SE",
    "sg:city":"Port Orchard",
    "sg:classifiers":[
        {
            "category":"Personal",
            "type":"Services"
        }
    ],
    "sg:phone":"+1 360 871 3904",
    "sg:postcode":"98367",
    "sg:province":"WA",
    "wof:name":"Mango Bay Tanning Co",
    "wof:placetype":"venue"
},
  "geometry": {"coordinates":[-122.545779,47.495934],"type":"Point"}
}