{
  "type": "Feature",
  "properties": {
    "iso:country":"US",
    "sg:address":"1417 116th Ave NE",
    "sg:city":"Bellevue",
    "sg:classifiers":[
        {
            "category":"Insurance",
            "subcategory":"Insurance Agent",
            "type":"Services"
        }
    ],
    "sg:phone":"+1 425 635 2900",
    "sg:postcode":"98004",
    "sg:province":"WA",
    "wof:name":"Farmers Insurance Group",
    "wof:placetype":"venue"
},
  "geometry": {"coordinates":[-122.185738,47.625804],"type":"Point"}
}