{
  "type": "Feature",
  "properties": {
    "addr:full":"1218 3rd Avenue Suite 1500 Seattle WA 98101",
    "addr:housenumber":"1218",
    "addr:postcode":"98101",
    "addr:street":"3Rd Avenue Suite 1500",
    "iso:country":"US",
    "sg:address":"1218 3rd Avenue Suite 1500",
    "sg:city":"Seattle",
    "sg:classifiers":[
        {
            "category":"Professional",
            "subcategory":"Lawyer & Legal Services",
            "type":"Services"
        }
    ],
    "sg:phone":"+1 206 447 9186",
    "sg:postcode":"98101",
    "sg:province":"WA",
    "wof:name":"Reed Richard D",
    "wof:placetype":"venue"
},
  "geometry": {"coordinates":[-122.335392,47.60711],"type":"Point"}
}