{
  "type": "Feature",
  "properties": {
    "addr:full":"13751 Lake City Way NE Seattle WA 98125",
    "addr:housenumber":"13751",
    "addr:postcode":"98125",
    "addr:street":"Lake City Way Ne",
    "iso:country":"US",
    "sg:address":"13751 Lake City Way NE",
    "sg:city":"Seattle",
    "sg:classifiers":[
        {
            "category":"Manufacturing",
            "subcategory":"Printing",
            "type":"Manufacturing & Wholesale Goods"
        }
    ],
    "sg:phone":"+1 206 362 0336",
    "sg:postcode":"98125",
    "sg:province":"WA",
    "sg:tags":[
        "house",
        "periodical",
        "con"
    ],
    "wof:name":"Cultural Diversity At Work Onl",
    "wof:placetype":"venue"
},
  "geometry": {"coordinates":[-122.29238100000001,47.729804],"type":"Point"}
}