{
  "type": "Feature",
  "properties": {
    "addr:full":"1620 E Kincaid St Mount Vernon WA 98274",
    "addr:housenumber":"1620",
    "addr:postcode":"98274",
    "addr:street":"E Kincaid St",
    "iso:country":"US",
    "sg:address":"1620 E Kincaid St",
    "sg:city":"Mount Vernon",
    "sg:classifiers":[
        {
            "category":"Real Estate",
            "subcategory":"Real Estate Agent",
            "type":"Services"
        }
    ],
    "sg:phone":"+1 360 424 1281",
    "sg:postcode":"98274",
    "sg:province":"WA",
    "sg:tags":[
        "manager"
    ],
    "wof:name":"Sidney J Beeman",
    "wof:placetype":"venue"
},
  "geometry": {"coordinates":[-122.32083900000001,48.417359],"type":"Point"}
}