{
  "type": "Feature",
  "properties": {
    "iso:country":"US",
    "sg:address":"120 132nd St S",
    "sg:city":"Tacoma",
    "sg:classifiers":[
        {
            "category":"Utilities",
            "subcategory":"Electric",
            "type":"Services"
        }
    ],
    "sg:phone":"+1 253 531 4646",
    "sg:postcode":"98444",
    "sg:province":"WA",
    "sg:tags":[
        "distributor",
        "company",
        "power"
    ],
    "sg:website":"www.elmhurstmutual.org",
    "wof:name":"Elmhurst Mutual Pwr & Light Co",
    "wof:placetype":"venue"
},
  "geometry": {"coordinates":[-122.43423900000001,47.137325],"type":"Point"}
}