{
  "type": "Feature",
  "properties": {
    "addr:full":"217 S 201st St Seattle WA 98198",
    "addr:housenumber":"217",
    "addr:postcode":"98198",
    "addr:street":"S 201St St",
    "iso:country":"US",
    "sg:address":"217 S 201st St",
    "sg:city":"Seattle",
    "sg:classifiers":[
        {
            "category":"Restaurant",
            "type":"Food & Drink"
        }
    ],
    "sg:phone":"+1 206 878 9090",
    "sg:postcode":"98198",
    "sg:province":"WA",
    "sg:tags":[
        "eating"
    ],
    "wof:name":"Als Lunch Box",
    "wof:placetype":"venue"
},
  "geometry": {"coordinates":[-122.332008,47.422268],"type":"Point"}
}