{
  "type": "Feature",
  "properties": {
    "addr:full":"2313 Sleater Kinney Rd SE Lacey WA 98503",
    "addr:housenumber":"2313",
    "addr:postcode":"98503",
    "addr:street":"Sleater Kinney Rd Se",
    "iso:country":"US",
    "sg:address":"2313 Sleater Kinney Rd SE",
    "sg:city":"Lacey",
    "sg:classifiers":[
        {
            "category":"Professional",
            "subcategory":"Detective & Security Services",
            "type":"Services"
        }
    ],
    "sg:phone":"+1 360 456 8470",
    "sg:postcode":"98503",
    "sg:province":"WA",
    "sg:tags":[
        "car"
    ],
    "wof:name":"Washington State Senior G",
    "wof:placetype":"venue"
},
  "geometry": {"coordinates":[-122.833719,47.02501],"type":"Point"}
}