{
  "type": "Feature",
  "properties": {
    "iso:country":"US",
    "sg:address":"12305 120th Ave NE",
    "sg:city":"Kirkland",
    "sg:classifiers":[
        {
            "category":"Home & Garden",
            "subcategory":"Building Materials",
            "type":"Retail Goods"
        }
    ],
    "sg:phone":"+1 425 820 4400",
    "sg:postcode":"98034",
    "sg:province":"WA",
    "sg:tags":[
        "tile",
        "ceramic"
    ],
    "wof:name":"Tile For Less Inc",
    "wof:placetype":"venue"
},
  "geometry": {"coordinates":[-122.186133,47.710203],"type":"Point"}
}