{
  "type": "Feature",
  "properties": {
    "addr:full":"8036 S 194th St Kent WA 98032",
    "addr:housenumber":"8036",
    "addr:postcode":"98032",
    "addr:street":"S 194Th St",
    "iso:country":"US",
    "sg:address":"8036 S 194th St",
    "sg:city":"Kent",
    "sg:classifiers":[
        {
            "category":"Wholesale",
            "subcategory":"Metals & Minerals",
            "type":"Manufacturing & Wholesale Goods"
        }
    ],
    "sg:phone":"+1 253 395 9228",
    "sg:postcode":"98032",
    "sg:province":"WA",
    "sg:tags":[
        "tubing",
        "copper"
    ],
    "wof:name":"Cerro Copper",
    "wof:placetype":"venue"
},
  "geometry": {"coordinates":[-122.228374,47.428274],"type":"Point"}
}