{
  "type": "Feature",
  "properties": {
    "iso:country":"US",
    "sg:address":"408 Park Pl",
    "sg:city":"Everett",
    "sg:classifiers":[
        {
            "category":"Building & Trades",
            "subcategory":"Pest Control",
            "type":"Services"
        }
    ],
    "sg:phone":"+1 425 258 1575",
    "sg:postcode":"98203",
    "sg:province":"WA",
    "wof:name":"Harns Protect Pest Management",
    "wof:placetype":"venue"
},
  "geometry": {"coordinates":[-122.234532,47.962982],"type":"Point"}
}