{
  "type": "Feature",
  "properties": {
    "addr:full":"748 SE Fairwinds Loop Vancouver WA 98661",
    "addr:housenumber":"748",
    "addr:postcode":"98661",
    "addr:street":"Se Fairwinds Loop",
    "iso:country":"US",
    "sg:address":"748 SE Fairwinds Loop",
    "sg:city":"Vancouver",
    "sg:classifiers":[
        {
            "category":"Health Services",
            "subcategory":"Doctor",
            "type":"Services"
        }
    ],
    "sg:phone":"+1 360 695 8476",
    "sg:postcode":"98661",
    "sg:province":"WA",
    "sg:tags":[
        "psychiatrist"
    ],
    "wof:name":"Johnson Bruce C MD",
    "wof:placetype":"venue"
},
  "geometry": {"coordinates":[-122.65303,45.616546],"type":"Point"}
}