{
  "type": "Feature",
  "properties": {
    "addr:full":"15024 Densmore Ave N Seattle WA 98133",
    "addr:housenumber":"15024",
    "addr:postcode":"98133",
    "addr:street":"Densmore Ave N",
    "iso:country":"US",
    "sg:address":"15024 Densmore Ave N",
    "sg:city":"Seattle",
    "sg:classifiers":[
        {
            "category":"Shopping",
            "subcategory":"Gifts & Souvenirs",
            "type":"Retail Goods"
        }
    ],
    "sg:phone":"+1 206 364 4015",
    "sg:postcode":"98133",
    "sg:province":"WA",
    "wof:name":"Perfect Gift",
    "wof:placetype":"venue"
},
  "geometry": {"coordinates":[-122.338455,47.741249],"type":"Point"}
}