{
  "type": "Feature",
  "properties": {
    "addr:full":"2430 Stangroom Rd Bellingham WA 98229",
    "addr:housenumber":"2430",
    "addr:postcode":"98229",
    "addr:street":"Stangroom Rd",
    "iso:country":"US",
    "sg:address":"2430 Stangroom Rd",
    "sg:city":"Bellingham",
    "sg:classifiers":[
        {
            "category":"Professional",
            "subcategory":"Management & Consulting",
            "type":"Services"
        }
    ],
    "sg:phone":"+1 360 671 7486",
    "sg:postcode":"98229",
    "sg:province":"WA",
    "wof:name":"Waters Consulting",
    "wof:placetype":"venue"
},
  "geometry": {"coordinates":[-122.446055,48.728566],"type":"Point"}
}