{
  "type": "Feature",
  "properties": {
    "addr:full":"105 W Pennsylvania Ave Roslyn WA 98941",
    "addr:housenumber":"105",
    "addr:postcode":"98941",
    "addr:street":"W Pennsylvania Ave",
    "iso:country":"US",
    "sg:address":"105 W Pennsylvania Ave",
    "sg:city":"Roslyn",
    "sg:phone":"+1 509 649 2992",
    "sg:postcode":"98941",
    "sg:province":"WA",
    "wof:name":"Village Pizza",
    "wof:placetype":"venue"
},
  "geometry": {"coordinates":[-120.995203,47.2222],"type":"Point"}
}