{
  "type": "Feature",
  "properties": {
    "addr:full":"20020 50th St SE Snohomish WA 98290",
    "addr:housenumber":"20020",
    "addr:postcode":"98290",
    "addr:street":"50Th St Se",
    "iso:country":"US",
    "sg:address":"20020 50th St SE",
    "sg:city":"Snohomish",
    "sg:classifiers":[
        {
            "category":"Manufacturing",
            "subcategory":"Textiles",
            "type":"Manufacturing & Wholesale Goods"
        }
    ],
    "sg:phone":"+1 360 568 2488",
    "sg:postcode":"98290",
    "sg:province":"WA",
    "sg:tags":[
        "mill",
        "wool",
        "fabric"
    ],
    "wof:name":"Slug Ranch Fibers",
    "wof:placetype":"venue"
},
  "geometry": {"coordinates":[-121.960842,47.951826],"type":"Point"}
}