{
  "type": "Feature",
  "properties": {
    "addr:full":"454 N 34th St Seattle WA 98103",
    "addr:housenumber":"454",
    "addr:postcode":"98103",
    "addr:street":"N 34Th St",
    "iso:country":"US",
    "sg:address":"454 N 34th St",
    "sg:city":"Seattle",
    "sg:classifiers":[
        {
            "category":"Professional",
            "subcategory":"Research",
            "type":"Services"
        }
    ],
    "sg:phone":"+1 206 812 1530",
    "sg:postcode":"98103",
    "sg:province":"WA",
    "sg:website":"http://www.phaserx.com",
    "wof:name":"PhaseRx",
    "wof:placetype":"venue"
},
  "geometry": {"coordinates":[-122.351884,47.65003],"type":"Point"}
}