{
  "type": "Feature",
  "properties": {
    "addr:full":"600 1st Avenue Seattle WA 98104",
    "addr:housenumber":"600",
    "addr:postcode":"98104",
    "addr:street":"1St Avenue",
    "iso:country":"US",
    "sg:address":"600 1st Avenue",
    "sg:city":"Seattle",
    "sg:classifiers":[
        {
            "category":"Professional",
            "subcategory":"Lawyer & Legal Services",
            "type":"Services"
        }
    ],
    "sg:phone":"+1 206 267 0234",
    "sg:postcode":"98104",
    "sg:province":"WA",
    "wof:name":"Higuera Marie Attorney At Law",
    "wof:placetype":"venue"
},
  "geometry": {"coordinates":[-122.334102,47.601761],"type":"Point"}
}