{
  "type": "Feature",
  "properties": {
    "addr:full":"29223 Pacific Hwy S Federal Way WA 98003",
    "addr:housenumber":"29223",
    "addr:postcode":"98003",
    "addr:street":"Pacific Hwy S Federal Way",
    "iso:country":"US",
    "sg:address":"29223 Pacific Hwy S",
    "sg:city":"Federal Way",
    "sg:classifiers":[
        {
            "category":"Shopping",
            "type":"Retail Goods"
        }
    ],
    "sg:phone":"+1 800 832 8131",
    "sg:postcode":"98003",
    "sg:province":"WA",
    "sg:tags":[
        "merchandise"
    ],
    "wof:name":"Awardsbywilsoncom",
    "wof:placetype":"venue"
},
  "geometry": {"coordinates":[-122.31235100000001,47.342524],"type":"Point"}
}