{
  "type": "Feature",
  "properties": {
    "addr:full":"1023 Capitol Way S Olympia WA 98501",
    "addr:housenumber":"1023",
    "addr:postcode":"98501",
    "addr:street":"Capitol Way S",
    "iso:country":"US",
    "sg:address":"1023 Capitol Way S",
    "sg:city":"Olympia",
    "sg:classifiers":[
        {
            "category":"Restaurant",
            "type":"Food & Drink"
        }
    ],
    "sg:menulink":"http://www.allmenus.com/wa/olympia/145205-subway/menu/",
    "sg:phone":"+1 360 352 5305",
    "sg:postcode":"98501",
    "sg:province":"WA",
    "sg:tags":[
        "american",
        "sandwich"
    ],
    "wof:name":"Subway",
    "wof:placetype":"venue"
},
  "geometry": {"coordinates":[-122.901116,47.039162],"type":"Point"}
}