{
  "type": "Feature",
  "properties": {
    "addr:full":"111 S Oak St Colville WA 99114",
    "addr:housenumber":"111",
    "addr:postcode":"99114",
    "addr:street":"S Oak St",
    "iso:country":"US",
    "sg:address":"111 S Oak St",
    "sg:city":"Colville",
    "sg:classifiers":[
        {
            "category":"Home & Garden",
            "subcategory":"Building Materials",
            "type":"Retail Goods"
        }
    ],
    "sg:phone":"+1 509 684 6501",
    "sg:postcode":"99114",
    "sg:province":"WA",
    "sg:tags":[
        "glass",
        "window",
        "plate"
    ],
    "wof:name":"Colville Glass",
    "wof:placetype":"venue"
},
  "geometry": {"coordinates":[-117.904263,48.544342],"type":"Point"}
}