{
  "type": "Feature",
  "properties": {
    "addr:full":"1816 NE 3rd Ave Camas WA 98607",
    "addr:housenumber":"1816",
    "addr:postcode":"98607",
    "addr:street":"Ne 3Rd Ave",
    "iso:country":"US",
    "sg:address":"1816 NE 3rd Ave",
    "sg:city":"Camas",
    "sg:classifiers":[
        {
            "category":"Restaurant",
            "type":"Food & Drink"
        }
    ],
    "sg:phone":"+1 360 834 4257",
    "sg:postcode":"98607",
    "sg:province":"WA",
    "wof:name":"Smitty's Restaurant",
    "wof:placetype":"venue"
},
  "geometry": {"coordinates":[-122.389,45.588699],"type":"Point"}
}