{
  "type": "Feature",
  "properties": {
    "addr:full":"2200 Broadway St Vancouver WA 98663",
    "addr:housenumber":"2200",
    "addr:postcode":"98663",
    "addr:street":"Broadway St",
    "iso:country":"US",
    "sg:address":"2200 Broadway St",
    "sg:city":"Vancouver",
    "sg:classifiers":[
        {
            "category":"Utilities",
            "subcategory":"Refuse",
            "type":"Services"
        }
    ],
    "sg:phone":"+1 360 737 2425",
    "sg:postcode":"98663",
    "sg:province":"WA",
    "sg:tags":[
        "disposal",
        "waste"
    ],
    "wof:name":"Waste Management",
    "wof:placetype":"venue"
},
  "geometry": {"coordinates":[-122.670354,45.638549],"type":"Point"}
}