{
  "type": "Feature",
  "properties": {
    "addr:full":"1304 Olympic View Dr Edmonds WA 98020",
    "addr:housenumber":"1304",
    "addr:postcode":"98020",
    "addr:street":"Olympic View Dr",
    "iso:country":"US",
    "sg:address":"1304 Olympic View Dr",
    "sg:city":"Edmonds",
    "sg:classifiers":[
        {
            "category":"Personal",
            "subcategory":"Beauty Salon",
            "type":"Services"
        }
    ],
    "sg:phone":"+1 425 775 4528",
    "sg:postcode":"98020",
    "sg:province":"WA",
    "wof:name":"London Pride Hair Styling",
    "wof:placetype":"venue"
},
  "geometry": {"coordinates":[-122.364026,47.821626],"type":"Point"}
}