{
  "type": "Feature",
  "properties": {
    "addr:full":"21609 84th Ave S Kent WA 98032",
    "addr:housenumber":"21609",
    "addr:postcode":"98032",
    "addr:street":"84Th Ave S",
    "iso:country":"US",
    "sg:address":"21609 84th Ave S",
    "sg:city":"Kent",
    "sg:classifiers":[
        {
            "category":"Bars & Pubs",
            "type":"Food & Drink"
        }
    ],
    "sg:phone":"+1 253 437 0362",
    "sg:postcode":"98032",
    "sg:province":"WA",
    "wof:name":"Gators Sports Bar & Grill",
    "wof:placetype":"venue"
},
  "geometry": {"coordinates":[-122.228054,47.408391],"type":"Point"}
}