{
  "type": "Feature",
  "properties": {
    "addr:full":"18927 33rd Ave W Lynnwood WA 98036",
    "addr:housenumber":"18927",
    "addr:postcode":"98036",
    "addr:street":"33Rd Ave W",
    "iso:country":"US",
    "sg:address":"18927 33rd Ave W",
    "sg:city":"Lynnwood",
    "sg:classifiers":[
        {
            "category":"Insurance",
            "subcategory":"Insurance Agent",
            "type":"Services"
        }
    ],
    "sg:phone":"+1 425 744 0911",
    "sg:postcode":"98036",
    "sg:province":"WA",
    "wof:name":"GNP",
    "wof:placetype":"venue"
},
  "geometry": {"coordinates":[-122.277686,47.823691],"type":"Point"}
}