{
  "type": "Feature",
  "properties": {
    "addr:full":"10600 8th Ave S Seattle WA 98168",
    "addr:housenumber":"10600",
    "addr:postcode":"98168",
    "addr:street":"8Th Ave S",
    "iso:country":"US",
    "sg:address":"10600 8th Ave S",
    "sg:city":"Seattle",
    "sg:classifiers":[
        {
            "category":"Manufacturing",
            "subcategory":"Metals",
            "type":"Manufacturing & Wholesale Goods"
        }
    ],
    "sg:phone":"+1 206 932 8433",
    "sg:postcode":"98168",
    "sg:province":"WA",
    "sg:tags":[
        "steel",
        "detailers",
        "repair",
        "mobile",
        "ship",
        "structural"
    ],
    "wof:name":"Froland Marine Fab",
    "wof:placetype":"venue"
},
  "geometry": {"coordinates":[-122.32325,47.508419],"type":"Point"}
}