{
  "type": "Feature",
  "properties": {
    "addr:full":"1223 Broadway Everett WA 98201",
    "addr:housenumber":"1223",
    "addr:postcode":"98201",
    "addr:street":"Broadway",
    "iso:country":"US",
    "sg:address":"1223 Broadway",
    "sg:city":"Everett",
    "sg:classifiers":[
        {
            "category":"Professional",
            "subcategory":"Lawyer & Legal Services",
            "type":"Services"
        }
    ],
    "sg:phone":"+1 425 774 8954",
    "sg:postcode":"98201",
    "sg:province":"WA",
    "wof:name":"Farley & Dimmock LLC",
    "wof:placetype":"venue"
},
  "geometry": {"coordinates":[-122.20095499999999,48.000579],"type":"Point"}
}