{
  "type": "Feature",
  "properties": {
    "iso:country":"US",
    "sg:address":"391 Wine Country Rd",
    "sg:city":"Prosser",
    "sg:classifiers":[
        {
            "category":"Building & Trades",
            "subcategory":"Equipment Rental",
            "type":"Services"
        }
    ],
    "sg:phone":"+1 509 786 3004",
    "sg:postcode":"99350",
    "sg:province":"WA",
    "sg:tags":[
        "yard"
    ],
    "wof:name":"Prosser Rental & Sales",
    "wof:placetype":"venue"
},
  "geometry": {"coordinates":[-119.78015600000001,46.211958],"type":"Point"}
}