{
  "type": "Feature",
  "properties": {
    "addr:full":"624 6th St Prosser WA 99350",
    "addr:housenumber":"624",
    "addr:postcode":"99350",
    "addr:street":"6Th St",
    "iso:country":"US",
    "sg:address":"624 6th St",
    "sg:city":"Prosser",
    "sg:classifiers":[
        {
            "category":"Fast Food",
            "type":"Food & Drink"
        },
        {
            "category":"Restaurant",
            "type":"Food & Drink"
        }
    ],
    "sg:phone":"+1 509 786 4910",
    "sg:postcode":"99350",
    "sg:province":"WA",
    "sg:tags":[
        "dining",
        "mexican",
        "take",
        "fine"
    ],
    "wof:name":"El Caporal",
    "wof:placetype":"venue"
},
  "geometry": {"coordinates":[-119.77033,46.205645],"type":"Point"}
}