{
  "type": "Feature",
  "properties": {
    "addr:full":"17922 Bothell Way NE Bothell WA 98011",
    "addr:housenumber":"17922",
    "addr:postcode":"98011",
    "addr:street":"Bothell Way Ne",
    "iso:country":"US",
    "sg:address":"17922 Bothell Way NE",
    "sg:city":"Bothell",
    "sg:classifiers":[
        {
            "category":"Food & Beverages",
            "subcategory":"Groceries & Convenience Stores",
            "type":"Retail Goods"
        }
    ],
    "sg:phone":"+1 425 481 7296",
    "sg:postcode":"98011",
    "sg:province":"WA",
    "wof:name":"7-Eleven",
    "wof:placetype":"venue"
},
  "geometry": {"coordinates":[-122.20990399999999,47.759124],"type":"Point"}
}