{
  "type": "Feature",
  "properties": {
    "addr:full":"701 E Heron St Aberdeen WA 98520",
    "addr:housenumber":"701",
    "addr:postcode":"98520",
    "addr:street":"E Heron St",
    "iso:country":"US",
    "sg:address":"701 E Heron St",
    "sg:city":"Aberdeen",
    "sg:classifiers":[
        {
            "category":"Travel",
            "subcategory":"Hotels & Motels",
            "type":"Entertainment"
        }
    ],
    "sg:phone":"+1 360 537 7460",
    "sg:postcode":"98520",
    "sg:province":"WA",
    "wof:name":"Guest House Inn & Suites",
    "wof:placetype":"venue"
},
  "geometry": {"coordinates":[-123.80878800000001,46.976262],"type":"Point"}
}