{
  "type": "Feature",
  "properties": {
    "addr:full":"6611 Millstone Ln SE Olympia WA 98513",
    "addr:housenumber":"6611",
    "addr:postcode":"98513",
    "addr:street":"Millstone Ln Se",
    "iso:country":"US",
    "sg:address":"6611 Millstone Ln SE",
    "sg:city":"Olympia",
    "sg:classifiers":[
        {
            "category":"Wholesale",
            "subcategory":"Non-durable Goods",
            "type":"Manufacturing & Wholesale Goods"
        }
    ],
    "sg:phone":"+1 360 438 0138",
    "sg:postcode":"98513",
    "sg:province":"WA",
    "wof:name":"Asian Eight Treasures",
    "wof:placetype":"venue"
},
  "geometry": {"coordinates":[-122.823673,46.988187],"type":"Point"}
}