{
  "type": "Feature",
  "properties": {
    "addr:full":"10018 NE 13th Ave Vancouver WA 98686",
    "addr:housenumber":"10018",
    "addr:postcode":"98686",
    "addr:street":"Ne 13Th Ave",
    "iso:country":"US",
    "sg:address":"10018 NE 13th Ave",
    "sg:city":"Vancouver",
    "sg:classifiers":[
        {
            "category":"Retail",
            "subcategory":"Auto Repair",
            "type":"Services"
        }
    ],
    "sg:phone":"+1 360 695 9195",
    "sg:postcode":"98686",
    "sg:province":"WA",
    "sg:tags":[
        "repairing",
        "automobile",
        "automotive",
        "general"
    ],
    "wof:name":"Matt's Alignment & Brake Inc",
    "wof:placetype":"venue"
},
  "geometry": {"coordinates":[-122.658519,45.693971],"type":"Point"}
}