{
  "type": "Feature",
  "properties": {
    "addr:full":"11314 9th Pl W Everett WA 98204",
    "addr:housenumber":"11314",
    "addr:postcode":"98204",
    "addr:street":"9Th Pl W",
    "iso:country":"US",
    "sg:address":"11314 9th Pl W",
    "sg:city":"Everett",
    "sg:classifiers":[
        {
            "category":"Professional",
            "subcategory":"Accounting & Tax Preparation",
            "type":"Services"
        }
    ],
    "sg:phone":"+1 425 290 8056",
    "sg:postcode":"98204",
    "sg:province":"WA",
    "sg:tags":[
        "bookkeeping",
        "general"
    ],
    "wof:name":"Rosa Fawn Briggs Accounting",
    "wof:placetype":"venue"
},
  "geometry": {"coordinates":[-122.247,47.89542],"type":"Point"}
}