{
  "type": "Feature",
  "properties": {
    "addr:full":"905 Vintage Valley Pkwy Zillah WA 98953",
    "addr:housenumber":"905",
    "addr:postcode":"98953",
    "addr:street":"Vintage Valley Pkwy Zillah",
    "iso:country":"US",
    "sg:address":"905 Vintage Valley Pkwy",
    "sg:city":"Zillah",
    "sg:classifiers":[
        {
            "category":"Personal",
            "subcategory":"Barber",
            "type":"Services"
        }
    ],
    "sg:phone":"+1 509 829 3888",
    "sg:postcode":"98953",
    "sg:province":"WA",
    "sg:tags":[
        "shop"
    ],
    "wof:name":"Country Gentleman Barber Shop",
    "wof:placetype":"venue"
},
  "geometry": {"coordinates":[-120.27909099999999,46.406062],"type":"Point"}
}