{
  "type": "Feature",
  "properties": {
    "addr:full":"4107 NW Fruit Valley Rd Ste S Vancouver WA 98660",
    "addr:housenumber":"4107",
    "addr:postcode":"98660",
    "addr:street":"Nw Fruit Valley Rd Ste S",
    "iso:country":"US",
    "sg:address":"4107 NW Fruit Valley Rd Ste S",
    "sg:city":"Vancouver",
    "sg:classifiers":[
        {
            "category":"Retail",
            "subcategory":"Repair Shop",
            "type":"Services"
        }
    ],
    "sg:phone":"+1 360 695 1188",
    "sg:postcode":"98660",
    "sg:province":"WA",
    "sg:tags":[
        "reupholstery",
        "furniture"
    ],
    "wof:name":"Quality First Upholstery",
    "wof:placetype":"venue"
},
  "geometry": {"coordinates":[-122.691559,45.652482],"type":"Point"}
}