{
  "type": "Feature",
  "properties": {
    "addr:full":"19557 Aurora Ave N Shoreline WA 98133",
    "addr:housenumber":"19557",
    "addr:postcode":"98133",
    "addr:street":"Aurora Ave N",
    "iso:country":"US",
    "sg:address":"19557 Aurora Ave N",
    "sg:city":"Shoreline",
    "sg:phone":"+1 206 542 0302",
    "sg:postcode":"98133",
    "sg:province":"WA",
    "wof:name":"Taqueria Guaymas",
    "wof:placetype":"venue"
},
  "geometry": {"coordinates":[-122.346002,47.77145],"type":"Point"}
}