{
  "type": "Feature",
  "properties": {
    "addr:full":"2705 N Pearl St Centralia WA 98531",
    "addr:housenumber":"2705",
    "addr:postcode":"98531",
    "addr:street":"N Pearl St",
    "iso:country":"US",
    "sg:address":"2705 N Pearl St",
    "sg:city":"Centralia",
    "sg:classifiers":[
        {
            "category":"Wholesale",
            "subcategory":"Scrap",
            "type":"Manufacturing & Wholesale Goods"
        }
    ],
    "sg:phone":"+1 360 736 5467",
    "sg:postcode":"98531",
    "sg:province":"WA",
    "sg:tags":[
        "automobile",
        "material",
        "used"
    ],
    "wof:name":"Grasser Auto Wreckers",
    "wof:placetype":"venue"
},
  "geometry": {"coordinates":[-122.950885,46.752479],"type":"Point"}
}