{
  "type": "Feature",
  "properties": {
    "addr:full":"2415 2nd Ave Seattle WA 98121",
    "addr:housenumber":"2415",
    "addr:postcode":"98121",
    "addr:street":"2Nd Ave",
    "iso:country":"US",
    "sg:address":"2415 2nd Ave",
    "sg:city":"Seattle",
    "sg:classifiers":[
        {
            "category":"Real Estate",
            "subcategory":"Real Estate Services",
            "type":"Services"
        },
        {
            "category":"Travel",
            "subcategory":"Hotels & Motels",
            "type":"Entertainment"
        }
    ],
    "sg:phone":"+1 206 856 9100",
    "sg:postcode":"98121",
    "sg:province":"WA",
    "sg:tags":[
        "home",
        "rental",
        "sale",
        "vacation"
    ],
    "sg:website":"http://www.emeraldcitysuites.com",
    "wof:name":"Emerald City Suites",
    "wof:placetype":"venue"
},
  "geometry": {"coordinates":[-122.34787,47.614734],"type":"Point"}
}