{
  "type": "Feature",
  "properties": {
    "addr:full":"330 Rainier Ave S Renton WA 98055",
    "addr:housenumber":"330",
    "addr:postcode":"98055",
    "addr:street":"Rainier Ave S Renton",
    "iso:country":"US",
    "sg:address":"330 Rainier Ave S",
    "sg:city":"Renton",
    "sg:classifiers":[
        {
            "category":"Bakery",
            "type":"Food & Drink"
        },
        {
            "category":"Donuts",
            "subcategory":"None",
            "type":"Food & Drink"
        }
    ],
    "sg:phone":"+1 425 235 1555",
    "sg:postcode":"98055",
    "sg:province":"WA",
    "wof:name":"Mrs. Johnson's Donuts",
    "wof:placetype":"venue"
},
  "geometry": {"coordinates":[-122.21700300000001,47.4786],"type":"Point"}
}