{
  "type": "Feature",
  "properties": {
    "addr:full":"159 Western Ave W Ste 484 Seattle WA 98119",
    "addr:housenumber":"159",
    "addr:postcode":"98119",
    "addr:street":"Western Ave W Ste 484",
    "iso:country":"US",
    "sg:address":"159 Western Ave W Ste 484",
    "sg:city":"Seattle",
    "sg:classifiers":[
        {
            "category":"Health Services",
            "subcategory":"Medical Lab",
            "type":"Services"
        }
    ],
    "sg:phone":"+1 206 464 5182",
    "sg:postcode":"98119",
    "sg:province":"WA",
    "wof:name":"Autism Speaks",
    "wof:placetype":"venue"
},
  "geometry": {"coordinates":[-122.358975,47.619551],"type":"Point"}
}