{
  "type": "Feature",
  "properties": {
    "addr:full":"10430 Creek St SE Yelm WA 98597",
    "addr:housenumber":"10430",
    "addr:postcode":"98597",
    "addr:street":"Creek St Se",
    "iso:country":"US",
    "sg:address":"10430 Creek St SE",
    "sg:city":"Yelm",
    "sg:classifiers":[
        {
            "category":"Home & Garden",
            "subcategory":"Building Materials",
            "type":"Retail Goods"
        }
    ],
    "sg:phone":"+1 360 458 5101",
    "sg:postcode":"98597",
    "sg:province":"WA",
    "sg:tags":[
        "hardware"
    ],
    "wof:name":"Mountain Lumber & Hardware",
    "wof:placetype":"venue"
},
  "geometry": {"coordinates":[-122.590019,46.937442],"type":"Point"}
}