{
  "type": "Feature",
  "properties": {
    "addr:full":"11451 109th Ave NE Kirkland WA 98033",
    "addr:housenumber":"11451",
    "addr:postcode":"98033",
    "addr:street":"109Th Ave Ne",
    "iso:country":"US",
    "sg:address":"11451 109th Ave NE",
    "sg:city":"Kirkland",
    "sg:classifiers":[
        {
            "category":"Real Estate",
            "subcategory":"Architect",
            "type":"Services"
        }
    ],
    "sg:phone":"+1 425 820 2096",
    "sg:postcode":"98033",
    "sg:province":"WA",
    "sg:tags":[
        "architects'",
        "specification",
        "construction",
        "builders'",
        "architectural"
    ],
    "wof:name":"Hill Archtects Planners Cons A",
    "wof:placetype":"venue"
},
  "geometry": {"coordinates":[-122.195976,47.703503],"type":"Point"}
}