{
  "type": "Feature",
  "properties": {
    "addr:full":"5531 Airport Way South Seattle WA 98108",
    "addr:housenumber":"5531",
    "addr:postcode":"98108",
    "addr:street":"Airport Way South",
    "iso:country":"US",
    "sg:address":"5531 Airport Way South",
    "sg:city":"Seattle",
    "sg:classifiers":[
        {
            "category":"Building & Trades",
            "subcategory":"Construction",
            "type":"Services"
        }
    ],
    "sg:phone":"+1 206 658 8189",
    "sg:postcode":"98108",
    "sg:province":"WA",
    "sg:tags":[
        "installation",
        "solar",
        "contractor"
    ],
    "sg:website":"www.mitchell-mechanical.com",
    "wof:name":"Mitchell Mechanical, Inc.",
    "wof:placetype":"venue"
},
  "geometry": {"coordinates":[-122.320487,47.552368],"type":"Point"}
}