{
  "type": "Feature",
  "properties": {
    "addr:full":"220 N Church St Montesano WA 98563",
    "addr:housenumber":"220",
    "addr:postcode":"98563",
    "addr:street":"N Church St",
    "iso:country":"US",
    "sg:address":"220 N Church St",
    "sg:city":"Montesano",
    "sg:classifiers":[
        {
            "category":"Retail",
            "subcategory":"Repair Shop",
            "type":"Services"
        }
    ],
    "sg:phone":"+1 360 249 2716",
    "sg:postcode":"98563",
    "sg:province":"WA",
    "sg:tags":[
        "lower",
        "resell",
        "for",
        "furniture"
    ],
    "wof:name":"Loose Cnon Antiq Furn Rstrtion",
    "wof:placetype":"venue"
},
  "geometry": {"coordinates":[-123.59693300000001,46.985228],"type":"Point"}
}