{
  "type": "Feature",
  "properties": {
    "addr:full":"731 Broadway Ave E Seattle WA 98102",
    "addr:housenumber":"731",
    "addr:postcode":"98102",
    "addr:street":"Broadway Ave E",
    "iso:country":"US",
    "sg:address":"731 Broadway Ave E",
    "sg:city":"Seattle",
    "sg:classifiers":[
        {
            "category":"Retail",
            "subcategory":"Repair Shop",
            "type":"Services"
        }
    ],
    "sg:phone":"+1 206 328 2379",
    "sg:postcode":"98102",
    "sg:province":"WA",
    "wof:name":"J W Quick & Clean",
    "wof:placetype":"venue"
},
  "geometry": {"coordinates":[-122.32105799999999,47.625188],"type":"Point"}
}