{
  "type": "Feature",
  "properties": {
    "addr:full":"1921 2nd Ave Seattle WA 98101",
    "addr:housenumber":"1921",
    "addr:postcode":"98101",
    "addr:street":"2Nd Ave",
    "iso:country":"US",
    "sg:address":"1921 2nd Ave",
    "sg:city":"Seattle",
    "sg:classifiers":[
        {
            "category":"Shopping",
            "subcategory":"Used Merchandise",
            "type":"Retail Goods"
        }
    ],
    "sg:phone":"+1 206 448 9405",
    "sg:postcode":"98101",
    "sg:province":"WA",
    "sg:tags":[
        "interior",
        "antique",
        "design"
    ],
    "wof:name":"Great Jones Home",
    "wof:placetype":"venue"
},
  "geometry": {"coordinates":[-122.34200300000001,47.6115],"type":"Point"}
}