{
  "type": "Feature",
  "properties": {
    "iso:country":"US",
    "sg:address":"3233 NE 12th St",
    "sg:city":"Renton",
    "sg:classifiers":[
        {
            "category":"Wholesale",
            "subcategory":"Apparel",
            "type":"Manufacturing & Wholesale Goods"
        }
    ],
    "sg:phone":"+1 425 271 2450",
    "sg:postcode":"98056",
    "sg:province":"WA",
    "sg:tags":[
        "clothing"
    ],
    "wof:name":"My World Sports Wear",
    "wof:placetype":"venue"
},
  "geometry": {"coordinates":[-122.175526,47.503016],"type":"Point"}
}