{
  "type": "Feature",
  "properties": {
    "addr:full":"10518 Dayton Ave N Seattle WA 98133",
    "addr:housenumber":"10518",
    "addr:postcode":"98133",
    "addr:street":"Dayton Ave N",
    "iso:country":"US",
    "sg:address":"10518 Dayton Ave N",
    "sg:city":"Seattle",
    "sg:classifiers":[
        {
            "category":"Wholesale",
            "subcategory":"Non-durable Goods",
            "type":"Manufacturing & Wholesale Goods"
        }
    ],
    "sg:phone":"+1 206 368 9035",
    "sg:postcode":"98133",
    "sg:province":"WA",
    "wof:name":"Ad Man Resources",
    "wof:placetype":"venue"
},
  "geometry": {"coordinates":[-122.35271299999999,47.706725],"type":"Point"}
}