{
  "type": "Feature",
  "properties": {
    "addr:full":"1144 W Jewett Blvd White Salmon WA 98672",
    "addr:housenumber":"1144",
    "addr:postcode":"98672",
    "addr:street":"W Jewett Blvd",
    "iso:country":"US",
    "sg:address":"1144 W Jewett Blvd",
    "sg:city":"White Salmon",
    "sg:classifiers":[
        {
            "category":"Building & Trades",
            "subcategory":"Landscaping Services",
            "type":"Services"
        }
    ],
    "sg:phone":"+1 509 493 4614",
    "sg:postcode":"98672",
    "sg:province":"WA",
    "sg:tags":[
        "landscape"
    ],
    "wof:name":"Landmarks Ldscpg & Maint Svc",
    "wof:placetype":"venue"
},
  "geometry": {"coordinates":[-121.51249799999999,45.736784],"type":"Point"}
}