{
  "type": "Feature",
  "properties": {
    "addr:full":"2241 N Shore Rd Bellingham WA 98226",
    "addr:housenumber":"2241",
    "addr:postcode":"98226",
    "addr:street":"N Shore Rd",
    "iso:country":"US",
    "sg:address":"2241 N Shore Rd",
    "sg:city":"Bellingham",
    "sg:classifiers":[
        {
            "category":"Real Estate",
            "subcategory":"Real Estate Operator",
            "type":"Services"
        }
    ],
    "sg:phone":"+1 360 715 8244",
    "sg:postcode":"98226",
    "sg:province":"WA",
    "sg:tags":[
        "building",
        "apartment",
        "commercial"
    ],
    "wof:name":"Romarr Properties",
    "wof:placetype":"venue"
},
  "geometry": {"coordinates":[-122.371471,48.752127],"type":"Point"}
}