{
  "type": "Feature",
  "properties": {
    "addr:full":"10 Echo Ct Yakima WA 98908",
    "addr:housenumber":"10",
    "addr:postcode":"98908",
    "addr:street":"Echo Ct",
    "iso:country":"US",
    "sg:address":"10 Echo Ct",
    "sg:city":"Yakima",
    "sg:classifiers":[
        {
            "category":"Food & Beverages",
            "subcategory":"Bakery",
            "type":"Retail Goods"
        }
    ],
    "sg:phone":"+1 509 966 4082",
    "sg:postcode":"98908",
    "sg:province":"WA",
    "sg:tags":[
        "baker"
    ],
    "wof:name":"Shirley's Cakes",
    "wof:placetype":"venue"
},
  "geometry": {"coordinates":[-120.62876199999999,46.6513],"type":"Point"}
}