{
  "type": "Feature",
  "properties": {
    "iso:country":"US",
    "sg:address":"10611 Canyon Rd E",
    "sg:city":"Puyallup",
    "sg:classifiers":[
        {
            "category":"Retail",
            "subcategory":"Car Wash",
            "type":"Services"
        }
    ],
    "sg:phone":"+1 253 535 6401",
    "sg:postcode":"98373",
    "sg:province":"WA",
    "sg:tags":[
        "automobile",
        "detail",
        "clean"
    ],
    "wof:name":"Speedway Auto Detail",
    "wof:placetype":"venue"
},
  "geometry": {"coordinates":[-122.35715999999999,47.158837],"type":"Point"}
}