{
  "type": "Feature",
  "properties": {
    "iso:country":"US",
    "sg:address":"19109 63rd Ave NE",
    "sg:city":"Arlington",
    "sg:classifiers":[
        {
            "category":"Education",
            "subcategory":"School",
            "type":"Public Place"
        }
    ],
    "sg:phone":"+1 360 435 3806",
    "sg:postcode":"98223",
    "sg:province":"WA",
    "wof:name":"North Snohomish Discovery Prgm",
    "wof:placetype":"venue"
},
  "geometry": {"coordinates":[-122.14590800000001,48.167779],"type":"Point"}
}