{
  "type": "Feature",
  "properties": {
    "addr:full":"7910 Diagonal Rd SE Olympia WA 98501",
    "addr:housenumber":"7910",
    "addr:postcode":"olympia;98501",
    "addr:street":"Diagonal Rd Se",
    "iso:country":"US",
    "sg:address":"7910 Diagonal Rd SE",
    "sg:city":"Olympia",
    "sg:classifiers":[
        {
            "category":"Wholesale",
            "subcategory":"Apparel",
            "type":"Manufacturing & Wholesale Goods"
        }
    ],
    "sg:phone":"+1 360 870 1121",
    "sg:postcode":"98501",
    "sg:province":"WA",
    "sg:tags":[
        "clothing"
    ],
    "wof:name":"Stolen Apparel",
    "wof:placetype":"venue"
},
  "geometry": {"coordinates":[-122.8288,46.972262],"type":"Point"}
}