{
  "type": "Feature",
  "properties": {
    "addr:full":"7614 Aurora Ave N Seattle WA 98103",
    "addr:housenumber":"7614",
    "addr:postcode":"98103",
    "addr:street":"Aurora Ave N",
    "iso:country":"US",
    "sg:address":"7614 Aurora Ave N",
    "sg:city":"Seattle",
    "sg:classifiers":[
        {
            "category":"Shopping",
            "subcategory":"Computers & Home Electronics",
            "type":"Retail Goods"
        }
    ],
    "sg:phone":"+1 206 728 0369",
    "sg:postcode":"98103",
    "sg:province":"WA",
    "wof:name":"Northwest Audio Service",
    "wof:placetype":"venue"
},
  "geometry": {"coordinates":[-122.344238,47.684443],"type":"Point"}
}