{
  "type": "Feature",
  "properties": {
    "addr:full":"8015 28th Ave NW Seattle WA 98117",
    "addr:housenumber":"8015",
    "addr:postcode":"98117",
    "addr:street":"28Th Ave Nw",
    "iso:country":"US",
    "sg:address":"8015 28th Ave NW",
    "sg:city":"Seattle",
    "sg:classifiers":[
        {
            "category":"Professional",
            "subcategory":"Computer Services",
            "type":"Services"
        }
    ],
    "sg:phone":"+1 206 297 9575",
    "sg:postcode":"98117",
    "sg:province":"WA",
    "sg:tags":[
        "programing",
        "custom"
    ],
    "wof:name":"Mobile Geographics Llc",
    "wof:placetype":"venue"
},
  "geometry": {"coordinates":[-122.39310999999999,47.687129],"type":"Point"}
}