{
  "type": "Feature",
  "properties": {
    "addr:full":"402 N 26th Ave Yakima WA 98902",
    "addr:housenumber":"402",
    "addr:postcode":"98902",
    "addr:street":"N 26Th Ave",
    "iso:country":"US",
    "sg:address":"402 N 26th Ave",
    "sg:city":"Yakima",
    "sg:classifiers":[
        {
            "category":"Shopping",
            "subcategory":"Used Merchandise",
            "type":"Retail Goods"
        }
    ],
    "sg:phone":"+1 509 452 2796",
    "sg:postcode":"98902",
    "sg:province":"WA",
    "wof:name":"Wild West Antiques",
    "wof:placetype":"venue"
},
  "geometry": {"coordinates":[-120.543741,46.605924],"type":"Point"}
}