{
  "type": "Feature",
  "properties": {
    "addr:full":"3120 Harborview Dr Gig Harbor WA 98335",
    "addr:housenumber":"3120",
    "addr:postcode":"98335",
    "addr:street":"Harborview Dr",
    "iso:country":"US",
    "sg:address":"3120 Harborview Dr",
    "sg:city":"Gig Harbor",
    "sg:classifiers":[
        {
            "category":"Shopping",
            "subcategory":"Clothing, Apparel, & Fashions",
            "type":"Retail Goods"
        }
    ],
    "sg:phone":"+1 253 851 5525",
    "sg:postcode":"98335",
    "sg:province":"WA",
    "sg:tags":[
        "gift"
    ],
    "wof:name":"Mc Becklands II",
    "wof:placetype":"venue"
},
  "geometry": {"coordinates":[-122.581993,47.330462],"type":"Point"}
}