{
  "type": "Feature",
  "properties": {
    "addr:full":"1620 26th Ave NW Gig Harbor WA 98335",
    "addr:housenumber":"1620",
    "addr:postcode":"98335",
    "addr:street":"26Th Ave Nw",
    "iso:country":"US",
    "sg:address":"1620 26th Ave NW",
    "sg:city":"Gig Harbor",
    "sg:classifiers":[
        {
            "category":"Travel",
            "subcategory":"Travel Agent",
            "type":"Entertainment"
        }
    ],
    "sg:phone":"+1 253 857 4760",
    "sg:postcode":"98335",
    "sg:province":"WA",
    "sg:tags":[
        "passenger",
        "transportation",
        "arrangement"
    ],
    "wof:name":"Airline Trnspt Professionals",
    "wof:placetype":"venue"
},
  "geometry": {"coordinates":[-122.57320900000001,47.270987],"type":"Point"}
}