{
  "type": "Feature",
  "properties": {
    "addr:full":"21603 121st Pl SE Kent WA 98031",
    "addr:housenumber":"21603",
    "addr:postcode":"98031",
    "addr:street":"121St Pl Se",
    "iso:country":"US",
    "sg:address":"21603 121st Pl SE",
    "sg:city":"Kent",
    "sg:classifiers":[
        {
            "category":"Social Services",
            "subcategory":"Child Care",
            "type":"Services"
        }
    ],
    "sg:phone":"+1 253 630 9298",
    "sg:postcode":"98031",
    "sg:province":"WA",
    "sg:tags":[
        "day"
    ],
    "wof:name":"Beverly Chahanovich",
    "wof:placetype":"venue"
},
  "geometry": {"coordinates":[-122.179357,47.408591],"type":"Point"}
}