{
  "type": "Feature",
  "properties": {
    "addr:full":"1433 NW Louisiana Ave Chehalis WA 98532",
    "addr:housenumber":"1433",
    "addr:postcode":"98532",
    "addr:street":"Nw Louisiana Ave",
    "iso:country":"US",
    "sg:address":"1433 NW Louisiana Ave",
    "sg:city":"Chehalis",
    "sg:classifiers":[
        {
            "category":"Professional",
            "subcategory":"Accounting & Tax Preparation",
            "type":"Services"
        }
    ],
    "sg:phone":"+1 866 871 1040",
    "sg:postcode":"98532",
    "sg:province":"WA",
    "sg:tags":[
        "return",
        "preparation-business"
    ],
    "sg:website":"http://www.libertytax.com/",
    "wof:name":"Liberty Tax Service",
    "wof:placetype":"venue"
},
  "geometry": {"coordinates":[-122.97821,46.675515],"type":"Point"}
}