{
  "type": "Feature",
  "properties": {
    "addr:full":"6332 31st Ave NE Tulalip WA 98271",
    "addr:housenumber":"6332",
    "addr:postcode":"98271",
    "addr:street":"31St Ave Ne",
    "iso:country":"US",
    "sg:address":"6332 31st Ave NE",
    "sg:city":"Tulalip",
    "sg:classifiers":[
        {
            "category":"Education",
            "subcategory":"School",
            "type":"Public Place"
        }
    ],
    "sg:phone":"+1 360 653 0664",
    "sg:postcode":"98271",
    "sg:province":"WA",
    "sg:tags":[
        "high"
    ],
    "sg:website":"http://www.msvl.wednet.edu",
    "wof:name":"Marysville Arts And Technology High School",
    "wof:placetype":"venue"
},
  "geometry": {"coordinates":[-122.18952299999999,48.052923],"type":"Point"}
}