{
  "type": "Feature",
  "properties": {
    "addr:full":"658 Strander Blvd Tukwila WA 98188",
    "addr:housenumber":"658",
    "addr:postcode":"98188",
    "addr:street":"Strander Blvd",
    "iso:country":"US",
    "sg:address":"658 Strander Blvd",
    "sg:city":"Tukwila",
    "sg:classifiers":[
        {
            "category":"Personal",
            "subcategory":"Beauty Salon",
            "type":"Services"
        }
    ],
    "sg:phone":"+1 425 793 6303",
    "sg:postcode":"98188",
    "sg:province":"WA",
    "wof:name":"Clipper Cuts",
    "wof:placetype":"venue"
},
  "geometry": {"coordinates":[-122.24596,47.456227],"type":"Point"}
}