{
  "type": "Feature",
  "properties": {
    "addr:full":"136 102nd Ave SE Ste 101 Bellevue WA 98004",
    "addr:housenumber":"136",
    "addr:postcode":"98004",
    "addr:street":"102Nd Ave Se Ste 101",
    "iso:country":"US",
    "sg:address":"136 102nd Ave SE Ste 101",
    "sg:city":"Bellevue",
    "sg:classifiers":[
        {
            "category":"Sports & Exercise",
            "subcategory":"Gym",
            "type":"Entertainment"
        }
    ],
    "sg:phone":"+1 425 451 3444",
    "sg:postcode":"98004",
    "sg:province":"WA",
    "sg:tags":[
        "trainer"
    ],
    "sg:website":"www.elitefitnessbellevue.com",
    "wof:name":"Elite Fitness Training",
    "wof:placetype":"venue"
},
  "geometry": {"coordinates":[-122.20329599999999,47.609231],"type":"Point"}
}