{
  "type": "Feature",
  "properties": {
    "addr:full":"1003 N 34th St Renton WA 98056",
    "addr:housenumber":"1003",
    "addr:postcode":"98056",
    "addr:street":"N 34Th St",
    "iso:country":"US",
    "sg:address":"1003 N 34th St",
    "sg:city":"Renton",
    "sg:classifiers":[
        {
            "category":"Building & Trades",
            "subcategory":"Plumbing",
            "type":"Services"
        }
    ],
    "sg:phone":"+1 425 227 9333",
    "sg:postcode":"98056",
    "sg:province":"WA",
    "sg:tags":[
        "contractor"
    ],
    "wof:name":"Stac Strength Toning & Cond",
    "wof:placetype":"venue"
},
  "geometry": {"coordinates":[-122.20267200000001,47.522005],"type":"Point"}
}