{
  "type": "Feature",
  "properties": {
    "addr:full":"4904 93rd Ave W Tacoma WA 98467",
    "addr:housenumber":"4904",
    "addr:postcode":"98467",
    "addr:street":"93Rd Ave W",
    "iso:country":"US",
    "sg:address":"4904 93rd Ave W",
    "sg:city":"Tacoma",
    "sg:classifiers":[
        {
            "category":"Professional",
            "subcategory":"Accounting & Tax Preparation",
            "type":"Services"
        }
    ],
    "sg:phone":"+1 253 565 7250",
    "sg:postcode":"98467",
    "sg:province":"WA",
    "wof:name":"Cheryl Hill CPA",
    "wof:placetype":"venue"
},
  "geometry": {"coordinates":[-122.560755,47.212552],"type":"Point"}
}