{
  "type": "Feature",
  "properties": {
    "addr:full":"4352 36th Ave W Seattle WA 98199",
    "addr:housenumber":"4352",
    "addr:postcode":"98199",
    "addr:street":"36Th Ave W",
    "iso:country":"US",
    "sg:address":"4352 36th Ave W",
    "sg:city":"Seattle",
    "sg:classifiers":[
        {
            "category":"Professional",
            "subcategory":"Management & Consulting",
            "type":"Services"
        }
    ],
    "sg:phone":"+1 206 216 3936",
    "sg:postcode":"98199",
    "sg:province":"WA",
    "wof:name":"Fusion Marketing",
    "wof:placetype":"venue"
},
  "geometry": {"coordinates":[-122.403502,47.659253],"type":"Point"}
}