{
  "type": "Feature",
  "properties": {
    "addr:full":"1800 E Trent Ave Spokane WA 99202",
    "addr:housenumber":"1800",
    "addr:postcode":"99202",
    "addr:street":"E Trent Ave",
    "iso:country":"US",
    "sg:address":"1800 E Trent Ave",
    "sg:city":"Spokane",
    "sg:classifiers":[
        {
            "category":"Manufacturing",
            "subcategory":"Buildings",
            "type":"Manufacturing & Wholesale Goods"
        },
        {
            "category":"Building & Trades",
            "subcategory":"Construction",
            "type":"Services"
        }
    ],
    "sg:phone":"+1 509 535 8877",
    "sg:postcode":"99202",
    "sg:province":"WA",
    "sg:tags":[
        "industrial",
        "system",
        "specialty",
        "builder",
        "heating",
        "contractor",
        "contractors-commercial",
        "home",
        "air conditioning"
    ],
    "wof:name":"Robert B. Goebel, General Contractor, Inc.",
    "wof:placetype":"venue"
},
  "geometry": {"coordinates":[-117.384393,47.661921],"type":"Point"}
}