{
  "type": "Feature",
  "properties": {
    "addr:full":"1334 King St Ste 3 Bellingham WA 98229",
    "addr:housenumber":"1334",
    "addr:postcode":"98229",
    "addr:street":"King St Ste 3",
    "iso:country":"US",
    "sg:address":"1334 King St Ste 3",
    "sg:city":"Bellingham",
    "sg:classifiers":[
        {
            "category":"Insurance",
            "subcategory":"Hazard Insurance",
            "type":"Services"
        }
    ],
    "sg:phone":"+1 360 733 0206",
    "sg:postcode":"98229",
    "sg:province":"WA",
    "sg:tags":[
        "commercial",
        "business"
    ],
    "sg:website":"http://www.hartins.com",
    "wof:name":"Mutual Of Enumclaw Insurance Co",
    "wof:placetype":"venue"
},
  "geometry": {"coordinates":[-122.46375399999999,48.745548],"type":"Point"}
}