{
  "type": "Feature",
  "properties": {
    "addr:full":"16515 NE 74th St Redmond WA 98052",
    "addr:housenumber":"16515",
    "addr:postcode":"98052",
    "addr:street":"Ne 74Th St",
    "iso:country":"US",
    "sg:address":"16515 NE 74th St",
    "sg:city":"Redmond",
    "sg:classifiers":[
        {
            "category":"Shopping",
            "subcategory":"Gifts & Souvenirs",
            "type":"Retail Goods"
        }
    ],
    "sg:phone":"+1 425 883 1233",
    "sg:postcode":"98052",
    "sg:province":"WA",
    "sg:tags":[
        "shop"
    ],
    "sg:website":"www.countryclutter.com",
    "wof:name":"Country Clutter Of Redmond",
    "wof:placetype":"venue"
},
  "geometry": {"coordinates":[-122.119895,47.670351],"type":"Point"}
}