{
  "type": "Feature",
  "properties": {
    "addr:full":"4726 N Park Acres Dr Oak Harbor WA 98277",
    "addr:housenumber":"4726",
    "addr:postcode":"98277",
    "addr:street":"N Park Acres Dr",
    "iso:country":"US",
    "sg:address":"4726 N Park Acres Dr",
    "sg:city":"Oak Harbor",
    "sg:classifiers":[
        {
            "category":"Retail",
            "subcategory":"Auto Repair",
            "type":"Services"
        }
    ],
    "sg:phone":"+1 360 679 1354",
    "sg:postcode":"98277",
    "sg:province":"WA",
    "sg:tags":[
        "general"
    ],
    "wof:name":"Carls Auto Repair Mobile",
    "wof:placetype":"venue"
},
  "geometry": {"coordinates":[-122.62081499999999,48.379171],"type":"Point"}
}