{
  "type": "Feature",
  "properties": {
    "addr:full":"5455 NE Fox Glove Ln Poulsbo WA 98370",
    "addr:housenumber":"5455",
    "addr:postcode":"98370",
    "addr:street":"Ne Fox Glove Ln",
    "iso:country":"US",
    "sg:address":"5455 NE Fox Glove Ln",
    "sg:city":"Poulsbo",
    "sg:classifiers":[
        {
            "category":"Farming",
            "subcategory":"Livestock Farm",
            "type":"Manufacturing & Wholesale Goods"
        }
    ],
    "sg:phone":"+1 360 871 2171",
    "sg:postcode":"98370",
    "sg:province":"WA",
    "sg:tags":[
        "equine"
    ],
    "wof:name":"Day Dreamin Farm",
    "wof:placetype":"venue"
},
  "geometry": {"coordinates":[-122.577196,47.775739],"type":"Point"}
}