{
  "type": "Feature",
  "properties": {
    "addr:full":"707 W 3rd Ave Spokane WA 99201",
    "addr:housenumber":"707",
    "addr:postcode":"99201",
    "addr:street":"W 3Rd Ave",
    "iso:country":"US",
    "sg:address":"707 W 3rd Ave",
    "sg:city":"Spokane",
    "sg:classifiers":[
        {
            "category":"Restaurant",
            "type":"Food & Drink"
        }
    ],
    "sg:menulink":"http://www.allmenus.com/wa/spokane/160962-carls-jr/menu/",
    "sg:phone":"+1 509 455 9303",
    "sg:postcode":"99201",
    "sg:province":"WA",
    "sg:tags":[
        "burger",
        "american"
    ],
    "wof:name":"Carl's Jr.",
    "wof:placetype":"venue"
},
  "geometry": {"coordinates":[-117.422282,47.653382],"type":"Point"}
}