{
  "type": "Feature",
  "properties": {
    "addr:full":"4702 University Way NE Seattle WA 98105",
    "addr:housenumber":"4702",
    "addr:postcode":"98105",
    "addr:street":"University Way Ne",
    "iso:country":"US",
    "sg:address":"4702 University Way NE",
    "sg:city":"Seattle",
    "sg:classifiers":[
        {
            "category":"Shopping",
            "subcategory":"Computers & Home Electronics",
            "type":"Retail Goods"
        }
    ],
    "sg:phone":"+1 206 524 8100",
    "sg:postcode":"98105",
    "sg:province":"WA",
    "wof:name":"Apple Store University Village",
    "wof:placetype":"venue"
},
  "geometry": {"coordinates":[-122.313001,47.664886],"type":"Point"}
}