{
  "type": "Feature",
  "properties": {
    "addr:full":"15518 81st Ave NE Kenmore WA 98028",
    "addr:housenumber":"15518",
    "addr:postcode":"98028",
    "addr:street":"81St Ave Ne",
    "iso:country":"US",
    "sg:address":"15518 81st Ave NE",
    "sg:city":"Kenmore",
    "sg:classifiers":[
        {
            "category":"Wholesale",
            "subcategory":"Machinery & Supplies",
            "type":"Manufacturing & Wholesale Goods"
        }
    ],
    "sg:phone":"+1 425 488 1334",
    "sg:postcode":"98028",
    "sg:province":"WA",
    "sg:tags":[
        "equipment",
        "industrial"
    ],
    "wof:name":"Strategic Packaging",
    "wof:placetype":"venue"
},
  "geometry": {"coordinates":[-122.232719,47.741586],"type":"Point"}
}