{
  "type": "Feature",
  "properties": {
    "addr:full":"2514 East Cherry St Seattle WA 98122",
    "addr:housenumber":"2514",
    "addr:postcode":"98122",
    "addr:street":"East Cherry St",
    "iso:country":"US",
    "sg:address":"2514 East Cherry St",
    "sg:city":"Seattle",
    "sg:classifiers":[
        {
            "category":"Restaurant",
            "type":"Food & Drink"
        }
    ],
    "sg:phone":"+1 206 816 3403",
    "sg:postcode":"98122",
    "sg:province":"WA",
    "sg:tags":[
        "african"
    ],
    "sg:website":"www.riftvalleyrestaurant.com",
    "wof:name":"Rift Valley",
    "wof:placetype":"venue"
},
  "geometry": {"coordinates":[-122.299807,47.608002],"type":"Point"}
}