{
  "type": "Feature",
  "properties": {
    "iso:country":"US",
    "sg:address":"1416 N Rd 68",
    "sg:city":"Pasco",
    "sg:classifiers":[
        {
            "category":"Freight",
            "type":"Transportation"
        }
    ],
    "sg:phone":"+1 509 545 6785",
    "sg:postcode":"99301",
    "sg:province":"WA",
    "sg:tags":[
        "commercial",
        "storage"
    ],
    "wof:name":"Mor-Stor Mini Storages",
    "wof:placetype":"venue"
},
  "geometry": {"coordinates":[-119.189939,46.286944],"type":"Point"}
}