{
  "type": "Feature",
  "properties": {
    "addr:full":"24919 NE 98th Pl Battle Ground WA 98604",
    "addr:housenumber":"24919",
    "addr:postcode":"98604",
    "addr:street":"Ne 98Th Pl",
    "iso:country":"US",
    "sg:address":"24919 NE 98th Pl",
    "sg:city":"Battle Ground",
    "sg:classifiers":[
        {
            "category":"Building & Trades",
            "subcategory":"Landscaping Services",
            "type":"Services"
        }
    ],
    "sg:phone":"+1 360 600 3662",
    "sg:postcode":"98604",
    "sg:province":"WA",
    "sg:tags":[
        "landscape"
    ],
    "wof:name":"Top Notch",
    "wof:placetype":"venue"
},
  "geometry": {"coordinates":[-122.572382,45.803062],"type":"Point"}
}