{
  "type": "Feature",
  "properties": {
    "addr:full":"117 E Main St Auburn WA 98002",
    "addr:housenumber":"117",
    "addr:postcode":"98002",
    "addr:street":"E Main St",
    "iso:country":"US",
    "sg:address":"117 E Main St",
    "sg:city":"Auburn",
    "sg:classifiers":[
        {
            "category":"Restaurant",
            "type":"Food & Drink"
        }
    ],
    "sg:phone":"+1 253 735 3275",
    "sg:postcode":"98002",
    "sg:province":"WA",
    "sg:tags":[
        "eating"
    ],
    "wof:name":"Whiskers Cafe",
    "wof:placetype":"venue"
},
  "geometry": {"coordinates":[-122.22772000000001,47.30749],"type":"Point"}
}