{
  "type": "Feature",
  "properties": {
    "addr:full":"380 E Washington St Sequim WA 98382",
    "addr:housenumber":"380",
    "addr:postcode":"98382",
    "addr:street":"E Washington St",
    "iso:country":"US",
    "sg:address":"380 E Washington St",
    "sg:city":"Sequim",
    "sg:classifiers":[
        {
            "category":"Restaurant",
            "type":"Food & Drink"
        }
    ],
    "sg:phone":"+1 360 683 9999",
    "sg:postcode":"98382",
    "sg:province":"WA",
    "sg:tags":[
        "pizza",
        "italian"
    ],
    "wof:name":"Islander Pizza And Pasta Shack",
    "wof:placetype":"venue"
},
  "geometry": {"coordinates":[-123.097898,48.079632],"type":"Point"}
}