{
  "type": "Feature",
  "properties": {
    "addr:full":"556 E Columbia Dr Kennewick WA 99336",
    "addr:housenumber":"556",
    "addr:postcode":"99336",
    "addr:street":"E Columbia Dr",
    "iso:country":"US",
    "sg:address":"556 E Columbia Dr",
    "sg:city":"Kennewick",
    "sg:classifiers":[
        {
            "category":"Shopping",
            "subcategory":"Clothing, Apparel, & Fashions",
            "type":"Retail Goods"
        }
    ],
    "sg:phone":"+1 509 737 9292",
    "sg:postcode":"99336",
    "sg:province":"WA",
    "sg:tags":[
        "woman"
    ],
    "sg:website":"www.christopherandbanks.com",
    "wof:name":"Christopher & Banks",
    "wof:placetype":"venue"
},
  "geometry": {"coordinates":[-119.107311,46.21195],"type":"Point"}
}