{
  "type": "Feature",
  "properties": {
    "addr:full":"15461 139th Ave SE Renton WA 98058",
    "addr:housenumber":"15461",
    "addr:postcode":"98058",
    "addr:street":"139Th Ave Se",
    "iso:country":"US",
    "sg:address":"15461 139th Ave SE",
    "sg:city":"Renton",
    "sg:classifiers":[
        {
            "category":"Shopping",
            "subcategory":"Computers & Home Electronics",
            "type":"Retail Goods"
        }
    ],
    "sg:phone":"+1 425 226 3196",
    "sg:postcode":"98058",
    "sg:province":"WA",
    "wof:name":"Vertechs Computers",
    "wof:placetype":"venue"
},
  "geometry": {"coordinates":[-122.15338199999999,47.463692],"type":"Point"}
}