{
  "type": "Feature",
  "properties": {
    "addr:full":"228 219th Place SE Bothell WA 98021",
    "addr:housenumber":"228",
    "addr:postcode":"98021",
    "addr:street":"219Th Place Se",
    "iso:country":"US",
    "sg:address":"228 219th Place SE",
    "sg:city":"Bothell",
    "sg:classifiers":[
        {
            "category":"Professional",
            "subcategory":"Art Services",
            "type":"Services"
        }
    ],
    "sg:phone":"+1 206 634 2261",
    "sg:postcode":"98021",
    "sg:province":"WA",
    "sg:tags":[
        "photographer"
    ],
    "sg:website":"www.mbrownphoto.com",
    "wof:name":"Affordable Mike Brown Photography",
    "wof:placetype":"venue"
},
  "geometry": {"coordinates":[-122.22908700000001,47.798912],"type":"Point"}
}