{
  "type": "Feature",
  "properties": {
    "addr:full":"211 Lasiandra Ct Richland WA 99352",
    "addr:housenumber":"211",
    "addr:postcode":"99352",
    "addr:street":"Lasiandra Ct",
    "iso:country":"US",
    "sg:address":"211 Lasiandra Ct",
    "sg:city":"Richland",
    "sg:classifiers":[
        {
            "category":"Professional",
            "subcategory":"Engineering",
            "type":"Services"
        }
    ],
    "sg:phone":"+1 509 627 0629",
    "sg:postcode":"99352",
    "sg:province":"WA",
    "wof:name":"Montgomery Engineering Inc",
    "wof:placetype":"venue"
},
  "geometry": {"coordinates":[-119.261996,46.212438],"type":"Point"}
}