{
  "type": "Feature",
  "properties": {
    "addr:full":"1006 W Garland Ave Spokane WA 99205",
    "addr:housenumber":"1006",
    "addr:postcode":"99205",
    "addr:street":"W Garland Ave",
    "iso:country":"US",
    "sg:address":"1006 W Garland Ave",
    "sg:city":"Spokane",
    "sg:classifiers":[
        {
            "category":"Food & Beverages",
            "subcategory":"Groceries & Convenience Stores",
            "type":"Retail Goods"
        }
    ],
    "sg:phone":"+1 509 327 9192",
    "sg:postcode":"99205",
    "sg:province":"WA",
    "wof:name":"7-Eleven",
    "wof:placetype":"venue"
},
  "geometry": {"coordinates":[-117.42644799999999,47.693555],"type":"Point"}
}