{
  "type": "Feature",
  "properties": {
    "addr:full":"9421 N Davies Rd Lake Stevens WA 98258",
    "addr:housenumber":"9421",
    "addr:postcode":"98258",
    "addr:street":"N Davies Rd",
    "iso:country":"US",
    "sg:address":"9421 N Davies Rd",
    "sg:city":"Lake Stevens",
    "sg:classifiers":[
        {
            "category":"Health Services",
            "subcategory":"Doctor",
            "type":"Services"
        }
    ],
    "sg:phone":"+1 425 334 4001",
    "sg:postcode":"98258",
    "sg:province":"WA",
    "sg:tags":[
        "dentist"
    ],
    "wof:name":"Lake View Dental Clinic",
    "wof:placetype":"venue"
},
  "geometry": {"coordinates":[-122.104392,48.004803],"type":"Point"}
}