{
  "type": "Feature",
  "properties": {
    "addr:full":"8606 S Tacoma Way Lakewood WA 98499",
    "addr:housenumber":"8606",
    "addr:postcode":"98499",
    "addr:street":"S Tacoma Way",
    "iso:country":"US",
    "sg:address":"8606 S Tacoma Way",
    "sg:city":"Lakewood",
    "sg:classifiers":[
        {
            "category":"Shopping",
            "subcategory":"Books",
            "type":"Retail Goods"
        }
    ],
    "sg:phone":"+1 253 512 1102",
    "sg:postcode":"98499",
    "sg:province":"WA",
    "sg:tags":[
        "bookstore"
    ],
    "wof:name":"Sm Mart",
    "wof:placetype":"venue"
},
  "geometry": {"coordinates":[-122.48400100000001,47.1791],"type":"Point"}
}