{
  "type": "Feature",
  "properties": {
    "addr:full":"1450 Durant St Walla Walla WA 99362",
    "addr:housenumber":"1450",
    "addr:postcode":"99362",
    "addr:street":"Durant St",
    "iso:country":"US",
    "sg:address":"1450 Durant St",
    "sg:city":"Walla Walla",
    "sg:classifiers":[
        {
            "category":"Manufacturing",
            "subcategory":"Wood Products",
            "type":"Manufacturing & Wholesale Goods"
        }
    ],
    "sg:phone":"+1 509 529 3696",
    "sg:postcode":"99362",
    "sg:province":"WA",
    "sg:tags":[
        "mfg"
    ],
    "wof:name":"Bills Creative Wood",
    "wof:placetype":"venue"
},
  "geometry": {"coordinates":[-118.31356,46.053926],"type":"Point"}
}