{
  "type": "Feature",
  "properties": {
    "addr:full":"3033 NW 58th St Seattle WA 98107",
    "addr:housenumber":"3033",
    "addr:postcode":"98107",
    "addr:street":"Nw 58Th St",
    "iso:country":"US",
    "sg:address":"3033 NW 58th St",
    "sg:city":"Seattle",
    "sg:classifiers":[
        {
            "category":"Professional",
            "subcategory":"Management & Consulting",
            "type":"Services"
        }
    ],
    "sg:phone":"+1 206 784 7719",
    "sg:postcode":"98107",
    "sg:province":"WA",
    "sg:tags":[
        "consultant",
        "fishery"
    ],
    "wof:name":"Robert Kehoe",
    "wof:placetype":"venue"
},
  "geometry": {"coordinates":[-122.39803999999999,47.670852],"type":"Point"}
}