{
  "type": "Feature",
  "properties": {
    "addr:full":"14626 SE 244th St Kent WA 98042",
    "addr:postcode":"14626;98042",
    "addr:street":"Se 244Th St",
    "iso:country":"US",
    "sg:address":"14626 SE 244th St",
    "sg:city":"Kent",
    "sg:classifiers":[
        {
            "category":"Professional",
            "type":"Services"
        }
    ],
    "sg:phone":"+1 253 639 9983",
    "sg:postcode":"98042",
    "sg:province":"WA",
    "wof:name":"Hatfield Development Corp",
    "wof:placetype":"venue"
},
  "geometry": {"coordinates":[-122.146013,47.38311],"type":"Point"}
}