{
  "type": "Feature",
  "properties": {
    "addr:full":"2025 Freeman Rd Milton WA 98354",
    "addr:housenumber":"2025",
    "addr:postcode":"98354",
    "addr:street":"Freeman Rd",
    "iso:country":"US",
    "sg:address":"2025 Freeman Rd",
    "sg:city":"Milton",
    "sg:classifiers":[
        {
            "category":"Organizations",
            "subcategory":"Professional Association",
            "type":"Services"
        }
    ],
    "sg:phone":"+1 253 843 6868",
    "sg:postcode":"98354",
    "sg:province":"WA",
    "sg:tags":[
        "business",
        "trade"
    ],
    "wof:name":"Gomobile Commerce",
    "wof:placetype":"venue"
},
  "geometry": {"coordinates":[-122.327512,47.238809],"type":"Point"}
}