{
  "type": "Feature",
  "properties": {
    "addr:full":"7833 S Tacoma Way Tacoma WA 98409",
    "addr:housenumber":"7833",
    "addr:postcode":"98409",
    "addr:street":"S Tacoma Way",
    "iso:country":"US",
    "sg:address":"7833 S Tacoma Way",
    "sg:city":"Tacoma",
    "sg:classifiers":[
        {
            "category":"Autos & Motor Vehicles",
            "subcategory":"Automobile Sales",
            "type":"Retail Goods"
        }
    ],
    "sg:phone":"+1 253 471 8899",
    "sg:postcode":"98409",
    "sg:province":"WA",
    "sg:tags":[
        "used"
    ],
    "wof:name":"Cars Cost Less Inc",
    "wof:placetype":"venue"
},
  "geometry": {"coordinates":[-122.4836,47.186454],"type":"Point"}
}