{
  "type": "Feature",
  "properties": {
    "addr:full":"11510 E Riverside Dr Bothell WA 98011",
    "addr:housenumber":"11510",
    "addr:postcode":"98011",
    "addr:street":"E Riverside Dr",
    "iso:country":"US",
    "sg:address":"11510 E Riverside Dr",
    "sg:city":"Bothell",
    "sg:classifiers":[
        {
            "category":"Building & Trades",
            "subcategory":"Construction",
            "type":"Services"
        }
    ],
    "sg:phone":"+1 425 482 9136",
    "sg:postcode":"98011",
    "sg:province":"WA",
    "sg:tags":[
        "manufactured",
        "housing-communities"
    ],
    "wof:name":"Riverside Mobile Estates",
    "wof:placetype":"venue"
},
  "geometry": {"coordinates":[-122.187532,47.75394],"type":"Point"}
}