{
  "type": "Feature",
  "properties": {
    "iso:country":"US",
    "sg:address":"349 W Kinnear Pl",
    "sg:city":"Seattle",
    "sg:classifiers":[
        {
            "category":"Professional",
            "subcategory":"Computer Services",
            "type":"Services"
        }
    ],
    "sg:phone":"+1 206 352 7476",
    "sg:postcode":"98119",
    "sg:province":"WA",
    "sg:tags":[
        "prepackaged",
        "software"
    ],
    "wof:name":"Blue Horse Software Inc",
    "wof:placetype":"venue"
},
  "geometry": {"coordinates":[-122.36211900000001,47.627663],"type":"Point"}
}