{
  "type": "Feature",
  "properties": {
    "addr:full":"2616 S Jackson St Seattle WA 98144",
    "addr:housenumber":"2616",
    "addr:postcode":"98144",
    "addr:street":"S Jackson St",
    "iso:country":"US",
    "sg:address":"2616 S Jackson St",
    "sg:city":"Seattle",
    "sg:classifiers":[
        {
            "category":"Food & Beverages",
            "subcategory":"Specialty",
            "type":"Retail Goods"
        },
        {
            "category":"Food & Beverages",
            "subcategory":"Groceries & Convenience Stores",
            "type":"Retail Goods"
        }
    ],
    "sg:phone":"+1 206 328 2127",
    "sg:postcode":"98144",
    "sg:province":"WA",
    "sg:tags":[
        "grocers-specialty"
    ],
    "wof:name":"Quick Pack Food Mart",
    "wof:placetype":"venue"
},
  "geometry": {"coordinates":[-122.297997,47.599098],"type":"Point"}
}