{
  "type": "Feature",
  "properties": {
    "addr:full":"334 Wells Ave S Renton WA 98057",
    "addr:housenumber":"334",
    "addr:postcode":"98057",
    "addr:street":"Wells Ave S Renton",
    "iso:country":"US",
    "sg:address":"334 Wells Ave S",
    "sg:city":"Renton",
    "sg:classifiers":[
        {
            "category":"Retail",
            "subcategory":"Portrait Studio",
            "type":"Services"
        }
    ],
    "sg:phone":"+1 425 228 2702",
    "sg:postcode":"98057",
    "sg:province":"WA",
    "sg:tags":[
        "photo"
    ],
    "wof:name":"Jon Marie Studio",
    "wof:placetype":"venue"
},
  "geometry": {"coordinates":[-122.20545,47.479019],"type":"Point"}
}