{
  "type": "Feature",
  "properties": {
    "iso:country":"US",
    "sg:address":"1609 Central Ave S",
    "sg:city":"Kent",
    "sg:classifiers":[
        {
            "category":"Manufacturing",
            "subcategory":"Metals",
            "type":"Manufacturing & Wholesale Goods"
        }
    ],
    "sg:phone":"+1 253 859 4723",
    "sg:postcode":"98032",
    "sg:province":"WA",
    "sg:tags":[
        "sheet",
        "specialty",
        "mfg"
    ],
    "wof:name":"Smith Fabrication Inc",
    "wof:placetype":"venue"
},
  "geometry": {"coordinates":[-122.230231,47.371202],"type":"Point"}
}