{
  "type": "Feature",
  "properties": {
    "addr:full":"5101 E State Rte 106 Union WA 98592",
    "addr:housenumber":"5101",
    "addr:postcode":"98592",
    "addr:street":"E State Rte 106 Union",
    "iso:country":"US",
    "sg:address":"5101 E State Rte 106",
    "sg:city":"Union",
    "sg:classifiers":[
        {
            "category":"Recreation",
            "type":"Entertainment"
        }
    ],
    "sg:phone":"+1 360 898 5925",
    "sg:postcode":"98592",
    "sg:province":"WA",
    "sg:tags":[
        "charter",
        "boat"
    ],
    "wof:name":"Kayak Hood Canal",
    "wof:placetype":"venue"
},
  "geometry": {"coordinates":[-123.095046,47.356679],"type":"Point"}
}