{
  "type": "Feature",
  "properties": {
    "addr:full":"110 N 2nd St Yakima WA 98901",
    "addr:housenumber":"110",
    "addr:postcode":"98901",
    "addr:street":"N 2Nd St",
    "iso:country":"US",
    "sg:address":"110 N 2nd St",
    "sg:city":"Yakima",
    "sg:classifiers":[
        {
            "category":"Manufacturing",
            "subcategory":"Printing",
            "type":"Manufacturing & Wholesale Goods"
        }
    ],
    "sg:phone":"+1 509 457 6195",
    "sg:postcode":"98901",
    "sg:province":"WA",
    "sg:tags":[
        "offset"
    ],
    "wof:name":"Printing Plus",
    "wof:placetype":"venue"
},
  "geometry": {"coordinates":[-120.505807,46.604957],"type":"Point"}
}