{
  "type": "Feature",
  "properties": {
    "addr:full":"5449 Ballard Avenue NW Seattle WA 98107",
    "addr:housenumber":"5449",
    "addr:postcode":"98107",
    "addr:street":"Ballard Avenue Nw",
    "iso:country":"US",
    "sg:address":"5449 Ballard Avenue NW",
    "sg:city":"Seattle",
    "sg:classifiers":[
        {
            "category":"Bars & Pubs",
            "subcategory":"Lounge",
            "type":"Food & Drink"
        },
        {
            "category":"Restaurant",
            "type":"Food & Drink"
        }
    ],
    "sg:phone":"+1 206 297 0500",
    "sg:postcode":"98107",
    "sg:province":"WA",
    "sg:tags":[
        "new",
        "american"
    ],
    "sg:website":"www.thebalmar.com",
    "wof:name":"BalMar",
    "wof:placetype":"venue"
},
  "geometry": {"coordinates":[-122.38548400000001,47.668122],"type":"Point"}
}