{
  "type": "Feature",
  "properties": {
    "iso:country":"US",
    "sg:address":"33404 SE Redmond Fall City Rd",
    "sg:city":"Fall City",
    "sg:classifiers":[
        {
            "category":"Social Services",
            "subcategory":"Child Care",
            "type":"Services"
        }
    ],
    "sg:phone":"+1 425 222 7079",
    "sg:postcode":"98024",
    "sg:province":"WA",
    "sg:tags":[
        "kindergarten",
        "academic",
        "school"
    ],
    "wof:name":"Creative Kids",
    "wof:placetype":"venue"
},
  "geometry": {"coordinates":[-121.894406,47.569662],"type":"Point"}
}