{
  "type": "Feature",
  "properties": {
    "addr:full":"5206 S Toro Rd Kennewick WA 99338",
    "addr:housenumber":"5206",
    "addr:postcode":"99338",
    "addr:street":"S Toro Rd",
    "iso:country":"US",
    "sg:address":"5206 S Toro Rd",
    "sg:city":"Kennewick",
    "sg:classifiers":[
        {
            "category":"Health Services",
            "subcategory":"Chiropractor",
            "type":"Services"
        }
    ],
    "sg:phone":"+1 509 628 2371",
    "sg:postcode":"99338",
    "sg:province":"WA",
    "sg:tags":[
        "chiropractic"
    ],
    "wof:name":"M.C.C. Bampton",
    "wof:placetype":"venue"
},
  "geometry": {"coordinates":[-119.295587,46.204146],"type":"Point"}
}