{
  "type": "Feature",
  "properties": {
    "addr:full":"3919 Forest View Dr Washougal WA 98671",
    "addr:housenumber":"3919",
    "addr:postcode":"98671",
    "addr:street":"Forest View Dr",
    "iso:country":"US",
    "sg:address":"3919 Forest View Dr",
    "sg:city":"Washougal",
    "sg:classifiers":[
        {
            "category":"Banks & Credit Unions",
            "subcategory":"Investment Brokerage",
            "type":"Services"
        }
    ],
    "sg:phone":"+1 360 910 4978",
    "sg:postcode":"98671",
    "sg:province":"WA",
    "sg:tags":[
        "advisory"
    ],
    "wof:name":"Columbia Summit Investmen",
    "wof:placetype":"venue"
},
  "geometry": {"coordinates":[-122.326302,45.597439],"type":"Point"}
}