{
  "type": "Feature",
  "properties": {
    "addr:full":"26431 State Rte 20 Coupeville WA 98239",
    "addr:housenumber":"26431",
    "addr:postcode":"98239",
    "addr:street":"State Rte 20",
    "iso:country":"US",
    "sg:address":"26431 State Rte 20",
    "sg:city":"Coupeville",
    "sg:classifiers":[
        {
            "category":"Building & Trades",
            "subcategory":"Landscaping Services",
            "type":"Services"
        }
    ],
    "sg:phone":"+1 360 678 4223",
    "sg:postcode":"98239",
    "sg:province":"WA",
    "sg:tags":[
        "landscape"
    ],
    "wof:name":"Nelsons At Sandesbca",
    "wof:placetype":"venue"
},
  "geometry": {"coordinates":[-122.72147699999999,48.236498],"type":"Point"}
}