{
  "type": "Feature",
  "properties": {
    "addr:full":"1215 Tacoma Ave Sunnyside WA 98944",
    "addr:housenumber":"1215",
    "addr:postcode":"98944",
    "addr:street":"Tacoma Ave",
    "iso:country":"US",
    "sg:address":"1215 Tacoma Ave",
    "sg:city":"Sunnyside",
    "sg:classifiers":[
        {
            "category":"Professional",
            "subcategory":"Detective & Security Services",
            "type":"Services"
        }
    ],
    "sg:phone":"+1 509 839 2000",
    "sg:postcode":"98944",
    "sg:province":"WA",
    "sg:tags":[
        "guard"
    ],
    "wof:name":"Garza Security Service",
    "wof:placetype":"venue"
},
  "geometry": {"coordinates":[-120.00454999999999,46.320537],"type":"Point"}
}