{
  "type": "Feature",
  "properties": {
    "iso:country":"US",
    "sg:address":"3703 River Rd",
    "sg:city":"Yakima",
    "sg:classifiers":[
        {
            "category":"Personal",
            "type":"Services"
        }
    ],
    "sg:phone":"+1 509 307 4472",
    "sg:postcode":"98902",
    "sg:province":"WA",
    "sg:tags":[
        "therapist",
        "massage"
    ],
    "wof:name":"Heather's Massage",
    "wof:placetype":"venue"
},
  "geometry": {"coordinates":[-120.555661,46.618038],"type":"Point"}
}