{
  "type": "Feature",
  "properties": {
    "addr:full":"11811 N Morrill Dr Mead WA 99021",
    "addr:housenumber":"11811",
    "addr:postcode":"99021",
    "addr:street":"N Morrill Dr Mead",
    "iso:country":"US",
    "sg:address":"11811 N Morrill Dr",
    "sg:city":"Mead",
    "sg:classifiers":[
        {
            "category":"Manufacturing",
            "subcategory":"Motor Vehicles & Parts",
            "type":"Manufacturing & Wholesale Goods"
        }
    ],
    "sg:phone":"+1 509 467 8793",
    "sg:postcode":"99021",
    "sg:province":"WA",
    "sg:tags":[
        "mfg"
    ],
    "wof:name":"Precision Engine Rebuild",
    "wof:placetype":"venue"
},
  "geometry": {"coordinates":[-117.344032,47.76474],"type":"Point"}
}