{
  "type": "Feature",
  "properties": {
    "addr:full":"101 E 8th St Vancouver WA 98660",
    "addr:housenumber":"101",
    "addr:postcode":"98660",
    "addr:street":"E 8Th St",
    "iso:country":"US",
    "sg:address":"101 E 8th St",
    "sg:city":"Vancouver",
    "sg:classifiers":[
        {
            "category":"Professional",
            "subcategory":"Management & Consulting",
            "type":"Services"
        }
    ],
    "sg:phone":"+1 360 513 4816",
    "sg:postcode":"98660",
    "sg:province":"WA",
    "sg:tags":[
        "business"
    ],
    "wof:name":"Sunset Consulting",
    "wof:placetype":"venue"
},
  "geometry": {"coordinates":[-122.67056599999999,45.627202],"type":"Point"}
}