{
  "type": "Feature",
  "properties": {
    "addr:full":"3406 34th Ave S Seattle WA 98144",
    "addr:housenumber":"3406",
    "addr:postcode":"98144",
    "addr:street":"34Th Ave S",
    "iso:country":"US",
    "sg:address":"3406 34th Ave S",
    "sg:city":"Seattle",
    "sg:classifiers":[
        {
            "category":"Building & Trades",
            "subcategory":"Landscaping Services",
            "type":"Services"
        }
    ],
    "sg:phone":"+1 206 760 8529",
    "sg:postcode":"98144",
    "sg:province":"WA",
    "sg:tags":[
        "landscape"
    ],
    "wof:name":"Christopher White Inc",
    "wof:placetype":"venue"
},
  "geometry": {"coordinates":[-122.289849,47.571606],"type":"Point"}
}