{
  "type": "Feature",
  "properties": {
    "addr:full":"11300 Freund Canyon Rd Leavenworth WA 98826",
    "addr:housenumber":"11300",
    "addr:postcode":"98826",
    "addr:street":"Freund Canyon Rd",
    "iso:country":"US",
    "sg:address":"11300 Freund Canyon Rd",
    "sg:city":"Leavenworth",
    "sg:classifiers":[
        {
            "category":"Professional",
            "type":"Services"
        }
    ],
    "sg:phone":"+1 509 548 3327",
    "sg:postcode":"98826",
    "sg:province":"WA",
    "wof:name":"Blaine E Roberts",
    "wof:placetype":"venue"
},
  "geometry": {"coordinates":[-120.64770799999999,47.630182],"type":"Point"}
}