{
  "type": "Feature",
  "properties": {
    "addr:full":"7206 NE 37th Ave Vancouver WA 98665",
    "addr:housenumber":"7206",
    "addr:postcode":"98665",
    "addr:street":"Ne 37Th Ave",
    "iso:country":"US",
    "sg:address":"7206 NE 37th Ave",
    "sg:city":"Vancouver",
    "sg:classifiers":[
        {
            "category":"Retail",
            "subcategory":"Auto Repair",
            "type":"Services"
        }
    ],
    "sg:phone":"+1 360 735 7799",
    "sg:postcode":"98665",
    "sg:province":"WA",
    "sg:tags":[
        "general"
    ],
    "wof:name":"Ponchins Auto",
    "wof:placetype":"venue"
},
  "geometry": {"coordinates":[-122.63336099999999,45.674603],"type":"Point"}
}