{
  "type": "Feature",
  "properties": {
    "addr:full":"2009 E 70th St Tacoma WA 98404",
    "addr:housenumber":"2009",
    "addr:postcode":"98404",
    "addr:street":"E 70Th St",
    "iso:country":"US",
    "sg:address":"2009 E 70th St",
    "sg:city":"Tacoma",
    "sg:classifiers":[
        {
            "category":"Manufacturing",
            "subcategory":"Retail Goods",
            "type":"Manufacturing & Wholesale Goods"
        }
    ],
    "sg:phone":"+1 253 475 5471",
    "sg:postcode":"98404",
    "sg:province":"WA",
    "sg:tags":[
        "product",
        "mfg"
    ],
    "wof:name":"Robert F Wolf",
    "wof:placetype":"venue"
},
  "geometry": {"coordinates":[-122.40092199999999,47.193858],"type":"Point"}
}