{
  "type": "Feature",
  "properties": {
    "addr:full":"337 Proffitt Rd Centralia WA 98531",
    "addr:housenumber":"337",
    "addr:postcode":"98531",
    "addr:street":"Proffitt Rd",
    "iso:country":"US",
    "sg:address":"337 Proffitt Rd",
    "sg:city":"Centralia",
    "sg:classifiers":[
        {
            "category":"Personal",
            "subcategory":"Beauty Salon",
            "type":"Services"
        }
    ],
    "sg:phone":"+1 360 956 0555",
    "sg:postcode":"98531",
    "sg:province":"WA",
    "wof:name":"Capello-Hair Etc",
    "wof:placetype":"venue"
},
  "geometry": {"coordinates":[-122.89567,46.676803],"type":"Point"}
}