{
  "type": "Feature",
  "properties": {
    "iso:country":"US",
    "sg:address":"106 E State St",
    "sg:city":"Mossyrock",
    "sg:classifiers":[
        {
            "category":"Cinema",
            "subcategory":"Movie Theater",
            "type":"Entertainment"
        }
    ],
    "sg:phone":"+1 360 983 8487",
    "sg:postcode":"98564",
    "sg:province":"WA",
    "wof:name":"Mossyrock G Theater",
    "wof:placetype":"venue"
},
  "geometry": {"coordinates":[-122.485336,46.528879],"type":"Point"}
}