{
  "type": "Feature",
  "properties": {
    "addr:full":"14071 Avon Allen Rd Mount Vernon WA 98273",
    "addr:housenumber":"14071",
    "addr:postcode":"98273",
    "addr:street":"Avon Allen Rd",
    "iso:country":"US",
    "sg:address":"14071 Avon Allen Rd",
    "sg:city":"Mount Vernon",
    "sg:classifiers":[
        {
            "category":"Social Services",
            "subcategory":"Child Care",
            "type":"Services"
        }
    ],
    "sg:phone":"+1 360 848 1302",
    "sg:postcode":"98273",
    "sg:province":"WA",
    "sg:tags":[
        "day"
    ],
    "wof:name":"A B C Kidcare",
    "wof:placetype":"venue"
},
  "geometry": {"coordinates":[-122.37861100000001,48.44139],"type":"Point"}
}