{
  "type": "Feature",
  "properties": {
    "iso:country":"US",
    "sg:address":"2824 SE Bella Vista Rd",
    "sg:city":"Vancouver",
    "sg:classifiers":[
        {
            "category":"Professional",
            "subcategory":"Computer Services",
            "type":"Services"
        }
    ],
    "sg:phone":"+1 360 892 0423",
    "sg:postcode":"98683",
    "sg:province":"WA",
    "sg:tags":[
        "programing",
        "custom"
    ],
    "wof:name":"Metagear LLC",
    "wof:placetype":"venue"
},
  "geometry": {"coordinates":[-122.52653100000001,45.600758],"type":"Point"}
}