{
  "type": "Feature",
  "properties": {
    "addr:full":"12886 Interurban Ave S Seattle WA 98168",
    "addr:housenumber":"12886",
    "addr:postcode":"98168",
    "addr:street":"Interurban Ave S",
    "iso:country":"US",
    "sg:address":"12886 Interurban Ave S",
    "sg:city":"Seattle",
    "sg:classifiers":[
        {
            "category":"Banks & Credit Unions",
            "subcategory":"Investment Brokerage",
            "type":"Services"
        }
    ],
    "sg:phone":"+1 206 248 7300",
    "sg:postcode":"98168",
    "sg:province":"WA",
    "sg:tags":[
        "security",
        "real estate"
    ],
    "wof:name":"Kidder Mathews & Segner Inc",
    "wof:placetype":"venue"
},
  "geometry": {"coordinates":[-122.27640100000001,47.486892],"type":"Point"}
}