{
  "type": "Feature",
  "properties": {
    "addr:full":"326 Main St Edmonds WA 98020",
    "addr:housenumber":"326",
    "addr:postcode":"98020",
    "addr:street":"Main St",
    "iso:country":"US",
    "sg:address":"326 Main St",
    "sg:city":"Edmonds",
    "sg:classifiers":[
        {
            "category":"Home & Garden",
            "subcategory":"Furniture",
            "type":"Retail Goods"
        }
    ],
    "sg:phone":"+1 425 774 6222",
    "sg:postcode":"98020",
    "sg:province":"WA",
    "sg:tags":[
        "interior",
        "designer",
        "drapery",
        "carpet"
    ],
    "sg:website":"www.iofe.com",
    "wof:name":"Interiors Of Edmonds",
    "wof:placetype":"venue"
},
  "geometry": {"coordinates":[-122.378823,47.811041],"type":"Point"}
}