{
  "type": "Feature",
  "properties": {
    "iso:country":"US",
    "sg:address":"1725 River Rd",
    "sg:city":"Yakima",
    "sg:classifiers":[
        {
            "category":"Wholesale",
            "subcategory":"Stationery",
            "type":"Manufacturing & Wholesale Goods"
        }
    ],
    "sg:phone":"+1 509 452 4434",
    "sg:postcode":"98902",
    "sg:province":"WA",
    "sg:tags":[
        "box",
        "fiber"
    ],
    "wof:name":"Seattle/Tacoma Box",
    "wof:placetype":"venue"
},
  "geometry": {"coordinates":[-120.531696,46.618002],"type":"Point"}
}