{
  "type": "Feature",
  "properties": {
    "addr:full":"960 Guard St Friday Harbor WA 98250",
    "addr:housenumber":"960",
    "addr:postcode":"98250",
    "addr:street":"Guard St",
    "iso:country":"US",
    "sg:address":"960 Guard St",
    "sg:city":"Friday Harbor",
    "sg:classifiers":[
        {
            "category":"Manufacturing",
            "subcategory":"Tools & Machinery",
            "type":"Manufacturing & Wholesale Goods"
        }
    ],
    "sg:phone":"+1 360 378 9484",
    "sg:postcode":"98250",
    "sg:province":"WA",
    "sg:tags":[
        "machine",
        "shop"
    ],
    "wof:name":"Commins Manufacturing Inc",
    "wof:placetype":"venue"
},
  "geometry": {"coordinates":[-123.030091,48.536324],"type":"Point"}
}