{
  "type": "Feature",
  "properties": {
    "addr:full":"15670 Redmond Way Redmond WA 98052",
    "addr:housenumber":"15670",
    "addr:postcode":"98052",
    "addr:street":"Redmond Way",
    "iso:country":"US",
    "sg:address":"15670 Redmond Way",
    "sg:city":"Redmond",
    "sg:classifiers":[
        {
            "category":"Health Services",
            "subcategory":"Clinic",
            "type":"Services"
        }
    ],
    "sg:phone":"+1 425 702 8689",
    "sg:postcode":"98052",
    "sg:province":"WA",
    "sg:tags":[
        "medical"
    ],
    "sg:website":"www.swedish.org/body.cfm?id=3119",
    "wof:name":"Swedish Physicians Redmond",
    "wof:placetype":"venue"
},
  "geometry": {"coordinates":[-122.132797,47.67356],"type":"Point"}
}