{
  "type": "Feature",
  "properties": {
    "addr:full":"21756 123rd Ave SE Kent WA 98031",
    "addr:housenumber":"21756",
    "addr:postcode":"98031",
    "addr:street":"123Rd Ave Se",
    "iso:country":"US",
    "sg:address":"21756 123rd Ave SE",
    "sg:city":"Kent",
    "sg:classifiers":[
        {
            "category":"Building & Trades",
            "subcategory":"Plumbing",
            "type":"Services"
        }
    ],
    "sg:phone":"+1 253 639 0840",
    "sg:postcode":"98031",
    "sg:province":"WA",
    "sg:tags":[
        "plumbing",
        "contractor"
    ],
    "wof:name":"Another Plumber Inc",
    "wof:placetype":"venue"
},
  "geometry": {"coordinates":[-122.177098,47.406439],"type":"Point"}
}