{
  "type": "Feature",
  "properties": {
    "addr:full":"786 Frost Rd Winlock WA 98596",
    "addr:housenumber":"786",
    "addr:postcode":"98596",
    "addr:street":"Frost Rd",
    "iso:country":"US",
    "sg:address":"786 Frost Rd",
    "sg:city":"Winlock",
    "sg:classifiers":[
        {
            "category":"Social Services",
            "type":"Services"
        }
    ],
    "sg:phone":"+1 360 785 4494",
    "sg:postcode":"98596",
    "sg:province":"WA",
    "wof:name":"Over The Rainbow",
    "wof:placetype":"venue"
},
  "geometry": {"coordinates":[-122.875635,46.495874],"type":"Point"}
}