{
  "type": "Feature",
  "properties": {
    "iso:country":"US",
    "sg:address":"12822 133rd Pl NE",
    "sg:city":"Kirkland",
    "sg:classifiers":[
        {
            "category":"Building & Trades",
            "subcategory":"Construction",
            "type":"Services"
        }
    ],
    "sg:phone":"+1 425 820 0330",
    "sg:postcode":"98034",
    "sg:province":"WA",
    "sg:tags":[
        "contractor"
    ],
    "wof:name":"Image Contracting Inc",
    "wof:placetype":"venue"
},
  "geometry": {"coordinates":[-122.162109,47.715773],"type":"Point"}
}