{
  "type": "Feature",
  "properties": {
    "addr:full":"4732 US Hwy 12 Elma WA 98541",
    "addr:housenumber":"4732",
    "addr:postcode":"98541",
    "addr:street":"Us Hwy 12 Elma",
    "iso:country":"US",
    "sg:address":"4732 US Hwy 12",
    "sg:city":"Elma",
    "sg:classifiers":[
        {
            "category":"Manufacturing",
            "subcategory":"Lumber",
            "type":"Manufacturing & Wholesale Goods"
        }
    ],
    "sg:phone":"+1 360 482 5447",
    "sg:postcode":"98541",
    "sg:province":"WA",
    "sg:tags":[
        "company",
        "logging"
    ],
    "wof:name":"R L Smith Logging",
    "wof:placetype":"venue"
},
  "geometry": {"coordinates":[-123.383461,46.999166],"type":"Point"}
}