{
  "type": "Feature",
  "properties": {
    "addr:full":"7824 River Rd E Puyallup WA 98371",
    "addr:housenumber":"7824",
    "addr:postcode":"98371",
    "addr:street":"River Rd E",
    "iso:country":"US",
    "sg:address":"7824 River Rd E",
    "sg:city":"Puyallup",
    "sg:classifiers":[
        {
            "category":"Shopping",
            "subcategory":"Gifts & Souvenirs",
            "type":"Retail Goods"
        }
    ],
    "sg:phone":"+1 253 446 4595",
    "sg:postcode":"98371",
    "sg:province":"WA",
    "sg:tags":[
        "shop"
    ],
    "wof:name":"This That Other Treasures",
    "wof:placetype":"venue"
},
  "geometry": {"coordinates":[-122.32471700000001,47.207564],"type":"Point"}
}