{
  "type": "Feature",
  "properties": {
    "iso:country":"US",
    "sg:address":"20 SW 7th St",
    "sg:city":"Renton",
    "sg:classifiers":[
        {
            "category":"Restaurant",
            "type":"Food & Drink"
        }
    ],
    "sg:phone":"+1 425 271 9594",
    "sg:postcode":"98057",
    "sg:province":"WA",
    "sg:tags":[
        "eating"
    ],
    "wof:name":"Taco Del Mar",
    "wof:placetype":"venue"
},
  "geometry": {"coordinates":[-122.220089,47.473672],"type":"Point"}
}