{
  "type": "Feature",
  "properties": {
    "iso:country":"US",
    "sg:address":"701 W Columbia Dr",
    "sg:city":"Kennewick",
    "sg:classifiers":[
        {
            "category":"Cinema",
            "subcategory":"Movie Theater",
            "type":"Entertainment"
        }
    ],
    "sg:phone":"+1 509 783 5008",
    "sg:postcode":"99336",
    "sg:province":"WA",
    "wof:name":"Columbia Stadium 8",
    "wof:placetype":"venue"
},
  "geometry": {"coordinates":[-119.128773,46.216837],"type":"Point"}
}