{
  "type": "Feature",
  "properties": {
    "iso:country":"US",
    "sg:address":"4030 82nd Ave SE",
    "sg:city":"Mercer Island",
    "sg:classifiers":[
        {
            "category":"Wholesale",
            "subcategory":"Machinery & Supplies",
            "type":"Manufacturing & Wholesale Goods"
        }
    ],
    "sg:phone":"+1 206 232 0862",
    "sg:postcode":"98040",
    "sg:province":"WA",
    "sg:tags":[
        "equipment",
        "industrial"
    ],
    "wof:name":"Clean Air Systems",
    "wof:placetype":"venue"
},
  "geometry": {"coordinates":[-122.22958300000001,47.573667],"type":"Point"}
}