{
  "type": "Feature",
  "properties": {
    "addr:full":"11020 16th Ave SW Apt 201 Seattle WA 98146",
    "addr:housenumber":"11020;201",
    "addr:postcode":"98146",
    "addr:street":"16Th Ave Sw Apt",
    "iso:country":"US",
    "sg:address":"11020 16th Ave SW Apt 201",
    "sg:city":"Seattle",
    "sg:classifiers":[
        {
            "category":"Building & Trades",
            "subcategory":"Construction",
            "type":"Services"
        }
    ],
    "sg:phone":"+1 206 244 8942",
    "sg:postcode":"98146",
    "sg:province":"WA",
    "sg:tags":[
        "wallcoverings-installation",
        "wallpaper",
        "painting",
        "contractor"
    ],
    "wof:name":"Mr Lees Painting Co",
    "wof:placetype":"venue"
},
  "geometry": {"coordinates":[-122.355165,47.504494],"type":"Point"}
}