{
  "type": "Feature",
  "properties": {
    "iso:country":"US",
    "sg:address":"14668 NE 95th St",
    "sg:city":"Redmond",
    "sg:classifiers":[
        {
            "category":"Manufacturing",
            "subcategory":"Tools & Machinery",
            "type":"Manufacturing & Wholesale Goods"
        }
    ],
    "sg:phone":"+1 425 861 7372",
    "sg:postcode":"98052",
    "sg:province":"WA",
    "sg:tags":[
        "guidance",
        "laser",
        "system"
    ],
    "wof:name":"Laser Guidance Inc",
    "wof:placetype":"venue"
},
  "geometry": {"coordinates":[-122.14499600000001,47.685824],"type":"Point"}
}