{
  "type": "Feature",
  "properties": {
    "addr:full":"1122 3rd Ave Seattle WA 98101",
    "addr:housenumber":"1122",
    "addr:postcode":"98101",
    "addr:street":"3Rd Ave",
    "iso:country":"US",
    "sg:address":"1122 3rd Ave",
    "sg:city":"Seattle",
    "sg:classifiers":[
        {
            "category":"Professional",
            "subcategory":"Lawyer & Legal Services",
            "type":"Services"
        }
    ],
    "sg:phone":"+1 206 344 6800",
    "sg:postcode":"98101",
    "sg:province":"WA",
    "sg:tags":[
        "divorce",
        "law",
        "family"
    ],
    "wof:name":"Northwest Family Mediation",
    "wof:placetype":"venue"
},
  "geometry": {"coordinates":[-122.334999,47.606602],"type":"Point"}
}