{
  "type": "Feature",
  "properties": {
    "addr:full":"6110 64th St NE Marysville WA 98270",
    "addr:housenumber":"6110",
    "addr:postcode":"98270",
    "addr:street":"64Th St Ne",
    "iso:country":"US",
    "sg:address":"6110 64th St NE",
    "sg:city":"Marysville",
    "sg:classifiers":[
        {
            "category":"Professional",
            "subcategory":"Employment Agencies",
            "type":"Services"
        }
    ],
    "sg:phone":"+1 360 651 5995",
    "sg:postcode":"98270",
    "sg:province":"WA",
    "sg:tags":[
        "help",
        "supply"
    ],
    "wof:name":"Kim Smith",
    "wof:placetype":"venue"
},
  "geometry": {"coordinates":[-122.14344,48.053642],"type":"Point"}
}