{
  "type": "Feature",
  "properties": {
    "addr:full":"6736 Lake Washington Blvd NE Kirkland WA 98033",
    "addr:housenumber":"6736",
    "addr:postcode":"98033",
    "addr:street":"Lake Washington Blvd Ne",
    "iso:country":"US",
    "sg:address":"6736 Lake Washington Blvd NE",
    "sg:city":"Kirkland",
    "sg:classifiers":[
        {
            "category":"Real Estate",
            "subcategory":"Real Estate Agent",
            "type":"Services"
        }
    ],
    "sg:phone":"+1 425 828 1968",
    "sg:postcode":"98033",
    "sg:province":"WA",
    "wof:name":"Re/Max",
    "wof:placetype":"venue"
},
  "geometry": {"coordinates":[-122.206716,47.667332],"type":"Point"}
}