{
  "type": "Feature",
  "properties": {
    "addr:full":"116 Mandy Rd Toledo WA 98591",
    "addr:housenumber":"116",
    "addr:postcode":"98591",
    "addr:street":"Mandy Rd",
    "iso:country":"US",
    "sg:address":"116 Mandy Rd",
    "sg:city":"Toledo",
    "sg:classifiers":[
        {
            "category":"Farming",
            "subcategory":"Livestock Farm",
            "type":"Manufacturing & Wholesale Goods"
        }
    ],
    "sg:phone":"+1 360 864 6279",
    "sg:postcode":"98591",
    "sg:province":"WA",
    "wof:name":"Lyons Arland",
    "wof:placetype":"venue"
},
  "geometry": {"coordinates":[-122.881165,46.414998],"type":"Point"}
}