{
  "type": "Feature",
  "properties": {
    "addr:full":"7512 Bridgeport Way W Tacoma WA 98499",
    "addr:housenumber":"7512",
    "addr:postcode":"98499",
    "addr:street":"Bridgeport Way W",
    "iso:country":"US",
    "sg:address":"7512 Bridgeport Way W",
    "sg:city":"Tacoma",
    "sg:classifiers":[
        {
            "category":"Insurance",
            "subcategory":"Insurance Agent",
            "type":"Services"
        }
    ],
    "sg:phone":"+1 253 581 3937",
    "sg:postcode":"98499",
    "sg:province":"WA",
    "wof:name":"Allstate Insurance",
    "wof:placetype":"venue"
},
  "geometry": {"coordinates":[-122.518455,47.186543],"type":"Point"}
}