{
  "type": "Feature",
  "properties": {
    "addr:full":"13313 Westridge Pl NW Silverdale WA 98383",
    "addr:housenumber":"13313",
    "addr:postcode":"98383",
    "addr:street":"Westridge Pl Nw",
    "iso:country":"US",
    "sg:address":"13313 Westridge Pl NW",
    "sg:city":"Silverdale",
    "sg:classifiers":[
        {
            "category":"Building & Trades",
            "subcategory":"Landscaping Services",
            "type":"Services"
        }
    ],
    "sg:phone":"+1 360 697 4143",
    "sg:postcode":"98383",
    "sg:province":"WA",
    "sg:tags":[
        "landscape"
    ],
    "wof:name":"Landscape Co",
    "wof:placetype":"venue"
},
  "geometry": {"coordinates":[-122.679008,47.686063],"type":"Point"}
}