{
  "type": "Feature",
  "properties": {
    "addr:full":"1220 Main St Vancouver WA 98660",
    "addr:housenumber":"1220",
    "addr:postcode":"98660",
    "addr:street":"Main St",
    "iso:country":"US",
    "sg:address":"1220 Main St",
    "sg:city":"Vancouver",
    "sg:classifiers":[
        {
            "category":"Government",
            "subcategory":"Court House",
            "type":"Public Place"
        }
    ],
    "sg:phone":"+1 360 759 2150",
    "sg:postcode":"98660",
    "sg:province":"WA",
    "sg:tags":[
        "state",
        "counsel"
    ],
    "wof:name":"Attorney General",
    "wof:placetype":"venue"
},
  "geometry": {"coordinates":[-122.671645,45.6309],"type":"Point"}
}