{
  "type": "Feature",
  "properties": {
    "addr:full":"22458 Serenity Ln NE Poulsbo WA 98370",
    "addr:housenumber":"22458",
    "addr:postcode":"98370",
    "addr:street":"Serenity Ln Ne",
    "iso:country":"US",
    "sg:address":"22458 Serenity Ln NE",
    "sg:city":"Poulsbo",
    "sg:classifiers":[
        {
            "category":"Building & Trades",
            "subcategory":"Landscaping Services",
            "type":"Services"
        }
    ],
    "sg:phone":"+1 360 598 6071",
    "sg:postcode":"98370",
    "sg:province":"WA",
    "sg:tags":[
        "landscape"
    ],
    "wof:name":"B V S Services",
    "wof:placetype":"venue"
},
  "geometry": {"coordinates":[-122.614474,47.77104],"type":"Point"}
}