{
  "type": "Feature",
  "properties": {
    "addr:full":"94 Cook Ave Exd Port Townsend WA 98368",
    "addr:housenumber":"94",
    "addr:postcode":"98368",
    "addr:street":"Cook Ave Exd",
    "iso:country":"US",
    "sg:address":"94 Cook Ave Exd",
    "sg:city":"Port Townsend",
    "sg:classifiers":[
        {
            "category":"Retail",
            "subcategory":"Photofinishing",
            "type":"Services"
        }
    ],
    "sg:phone":"+1 360 379 3318",
    "sg:postcode":"98368",
    "sg:province":"WA",
    "sg:tags":[
        "laboratory",
        "portrait",
        "studio",
        "photo"
    ],
    "sg:website":"www.goldentimesphotography.com",
    "wof:name":"Golden Times Photography",
    "wof:placetype":"venue"
},
  "geometry": {"coordinates":[-122.81871099999999,48.121092],"type":"Point"}
}