{
  "type": "Feature",
  "properties": {
    "addr:full":"2127 Hammond Ave Dupont WA 98327",
    "addr:housenumber":"2127",
    "addr:postcode":"98327",
    "addr:street":"Hammond Ave Dupont",
    "iso:country":"US",
    "sg:address":"2127 Hammond Ave",
    "sg:city":"Dupont",
    "sg:classifiers":[
        {
            "category":"Professional",
            "subcategory":"Business Services",
            "type":"Services"
        }
    ],
    "sg:phone":"+1 253 588 0927",
    "sg:postcode":"98327",
    "sg:province":"WA",
    "sg:tags":[
        "consultant",
        "coach"
    ],
    "wof:name":"K Aldridge Consulting",
    "wof:placetype":"venue"
},
  "geometry": {"coordinates":[-122.640872,47.101738],"type":"Point"}
}