{
  "type": "Feature",
  "properties": {
    "addr:full":"15205 NE 16th Pl Bellevue WA 98007",
    "addr:housenumber":"15205",
    "addr:postcode":"98007",
    "addr:street":"Ne 16Th Pl",
    "iso:country":"US",
    "sg:address":"15205 NE 16th Pl",
    "sg:city":"Bellevue",
    "sg:classifiers":[
        {
            "category":"Banks & Credit Unions",
            "subcategory":"Bank",
            "type":"Services"
        }
    ],
    "sg:phone":"+1 425 442 0869",
    "sg:postcode":"98007",
    "sg:province":"WA",
    "sg:tags":[
        "food",
        "export"
    ],
    "wof:name":"Crossroads",
    "wof:placetype":"venue"
},
  "geometry": {"coordinates":[-122.13597,47.624452],"type":"Point"}
}