{
  "type": "Feature",
  "properties": {
    "addr:full":"11506 NE 3rd St Vancouver WA 98684",
    "addr:housenumber":"11506",
    "addr:postcode":"98684",
    "addr:street":"Ne 3Rd St",
    "iso:country":"US",
    "sg:address":"11506 NE 3rd St",
    "sg:city":"Vancouver",
    "sg:classifiers":[
        {
            "category":"Travel",
            "subcategory":"Hotels & Motels",
            "type":"Entertainment"
        }
    ],
    "sg:phone":"+1 360 254 4000",
    "sg:postcode":"98684",
    "sg:province":"WA",
    "sg:website":"http://book.bestwestern.com/bestwestern/priceAvail.do?propertyCode=48141&cm_mmc=IYP-_-YP-_-property-_-48141",
    "wof:name":"Best Western Inn of Vancouver",
    "wof:placetype":"venue"
},
  "geometry": {"coordinates":[-122.554001,45.6227],"type":"Point"}
}