{
  "type": "Feature",
  "properties": {
    "addr:full":"14623 35th Ave S Seattle WA 98168",
    "addr:housenumber":"14623",
    "addr:postcode":"98168",
    "addr:street":"35Th Ave S",
    "iso:country":"US",
    "sg:address":"14623 35th Ave S",
    "sg:city":"Seattle",
    "sg:classifiers":[
        {
            "category":"Social Services",
            "subcategory":"Child Care",
            "type":"Services"
        }
    ],
    "sg:phone":"+1 206 242 9811",
    "sg:postcode":"98168",
    "sg:province":"WA",
    "sg:tags":[
        "day"
    ],
    "wof:name":"Kid Kare Daykare Center of Tukwila",
    "wof:placetype":"venue"
},
  "geometry": {"coordinates":[-122.28800200000001,47.471901],"type":"Point"}
}