{
  "type": "Feature",
  "properties": {
    "addr:full":"5016 S Grove Rd Spokane WA 99224",
    "addr:housenumber":"5016",
    "addr:postcode":"99224",
    "addr:street":"S Grove Rd",
    "iso:country":"US",
    "sg:address":"5016 S Grove Rd",
    "sg:city":"Spokane",
    "sg:classifiers":[
        {
            "category":"Parking",
            "type":"Transportation"
        }
    ],
    "sg:phone":"+1 509 216 2990",
    "sg:postcode":"99224",
    "sg:province":"WA",
    "sg:tags":[
        "marina",
        "automobile",
        "operation"
    ],
    "wof:name":"K&R Storage",
    "wof:placetype":"venue"
},
  "geometry": {"coordinates":[-117.497113,47.605722],"type":"Point"}
}