{
  "type": "Feature",
  "properties": {
    "addr:full":"1249 Harrison Ave Centralia WA 98531",
    "addr:housenumber":"1249",
    "addr:postcode":"98531",
    "addr:street":"Harrison Ave",
    "iso:country":"US",
    "sg:address":"1249 Harrison Ave",
    "sg:city":"Centralia",
    "sg:classifiers":[
        {
            "category":"Government",
            "subcategory":"Office",
            "type":"Public Place"
        }
    ],
    "sg:phone":"+1 360 330 1471",
    "sg:postcode":"98531",
    "sg:province":"WA",
    "sg:tags":[
        "armed",
        "force",
        "recruiting"
    ],
    "wof:name":"US Navy Recruiting",
    "wof:placetype":"venue"
},
  "geometry": {"coordinates":[-122.983853,46.73002],"type":"Point"}
}