{
  "type": "Feature",
  "properties": {
    "addr:full":"1105 Hawley St E Wenatchee WA 98801",
    "addr:housenumber":"1105",
    "addr:postcode":"98801",
    "addr:street":"Hawley St",
    "iso:country":"US",
    "sg:address":"1105 Hawley St E",
    "sg:city":"Wenatchee",
    "sg:classifiers":[
        {
            "category":"Utilities",
            "subcategory":"Refuse",
            "type":"Services"
        }
    ],
    "sg:phone":"+1 509 663 6671",
    "sg:postcode":"98801",
    "sg:province":"WA",
    "sg:tags":[
        "system"
    ],
    "wof:name":"Central Washington Recycling",
    "wof:placetype":"venue"
},
  "geometry": {"coordinates":[-120.32468900000001,47.447897],"type":"Point"}
}