{
  "type": "Feature",
  "properties": {
    "addr:full":"4012 Wiggins Rd SE Olympia WA 98501",
    "addr:housenumber":"4012",
    "addr:postcode":"olympia;98501",
    "addr:street":"Wiggins Rd Se",
    "iso:country":"US",
    "sg:address":"4012 Wiggins Rd SE",
    "sg:city":"Olympia",
    "sg:classifiers":[
        {
            "category":"Professional",
            "subcategory":"Employment Agencies",
            "type":"Services"
        }
    ],
    "sg:phone":"+1 360 491 1036",
    "sg:postcode":"98501",
    "sg:province":"WA",
    "sg:tags":[
        "residential",
        "specialty",
        "outpatient"
    ],
    "wof:name":"Ashley House 3",
    "wof:placetype":"venue"
},
  "geometry": {"coordinates":[-122.844284,47.009617],"type":"Point"}
}