{
  "type": "Feature",
  "properties": {
    "addr:full":"1800 Pacific Ave N Long Beach WA 98631",
    "addr:housenumber":"1800",
    "addr:postcode":"98631",
    "addr:street":"Pacific Ave N",
    "iso:country":"US",
    "sg:address":"1800 Pacific Ave N",
    "sg:city":"Long Beach",
    "sg:classifiers":[
        {
            "category":"Insurance",
            "subcategory":"Insurance Agent",
            "type":"Services"
        }
    ],
    "sg:phone":"+1 360 642 4587",
    "sg:postcode":"98631",
    "sg:province":"WA",
    "wof:name":"State Farm Insurance",
    "wof:placetype":"venue"
},
  "geometry": {"coordinates":[-124.053766,46.366333],"type":"Point"}
}