{
  "type": "Feature",
  "properties": {
    "addr:full":"13016 133rd Pl NE Kirkland WA 98034",
    "addr:housenumber":"13016",
    "addr:postcode":"98034",
    "addr:street":"133Rd Pl Ne",
    "iso:country":"US",
    "sg:address":"13016 133rd Pl NE",
    "sg:city":"Kirkland",
    "sg:classifiers":[
        {
            "category":"Professional",
            "subcategory":"Printing & Photocopies",
            "type":"Services"
        }
    ],
    "sg:phone":"+1 425 444 6042",
    "sg:postcode":"98034",
    "sg:province":"WA",
    "sg:website":"www.b-seenapparel.com",
    "wof:name":"B-Seen Apparel",
    "wof:placetype":"venue"
},
  "geometry": {"coordinates":[-122.161823,47.717208],"type":"Point"}
}