{
  "type": "Feature",
  "properties": {
    "addr:full":"2206 Pacific St Bellingham WA 98229",
    "addr:housenumber":"2206",
    "addr:postcode":"98229",
    "addr:street":"Pacific St",
    "iso:country":"US",
    "sg:address":"2206 Pacific St",
    "sg:city":"Bellingham",
    "sg:classifiers":[
        {
            "category":"Autos & Motor Vehicles",
            "subcategory":"Auto Supplies",
            "type":"Retail Goods"
        },
        {
            "category":"Professional",
            "subcategory":"Advertising",
            "type":"Services"
        },
        {
            "category":"Manufacturing",
            "subcategory":"Signs",
            "type":"Manufacturing & Wholesale Goods"
        }
    ],
    "sg:phone":"+1 360 734 7617",
    "sg:postcode":"98229",
    "sg:province":"WA",
    "sg:tags":[
        "painting",
        "lettering",
        "truck",
        "specialty"
    ],
    "sg:website":"http://www.specialt.com",
    "wof:name":"Special-T Striping & Sign Co Inc",
    "wof:placetype":"venue"
},
  "geometry": {"coordinates":[-122.456208,48.75918],"type":"Point"}
}