{
  "type": "Feature",
  "properties": {
    "addr:full":"5520 Cedar Flats Rd SW Olympia WA 98512",
    "addr:housenumber":"5520",
    "addr:postcode":"98512",
    "addr:street":"Cedar Flats Rd Sw",
    "iso:country":"US",
    "sg:address":"5520 Cedar Flats Rd SW",
    "sg:city":"Olympia",
    "sg:classifiers":[
        {
            "category":"Manufacturing",
            "subcategory":"Printing",
            "type":"Manufacturing & Wholesale Goods"
        }
    ],
    "sg:phone":"+1 360 866 1089",
    "sg:postcode":"98512",
    "sg:province":"WA",
    "sg:tags":[
        "multimedia"
    ],
    "wof:name":"Icon Media Interactive",
    "wof:placetype":"venue"
},
  "geometry": {"coordinates":[-122.998372,47.028933],"type":"Point"}
}