{
  "type": "Feature",
  "properties": {
    "addr:full":"2300 Dallas St Richland WA 99352",
    "addr:housenumber":"2300",
    "addr:postcode":"99352",
    "addr:street":"Dallas St",
    "iso:country":"US",
    "sg:address":"2300 Dallas St",
    "sg:city":"Richland",
    "sg:classifiers":[
        {
            "category":"Building & Trades",
            "subcategory":"Construction",
            "type":"Services"
        }
    ],
    "sg:phone":"+1 509 539 0764",
    "sg:postcode":"99352",
    "sg:province":"WA",
    "sg:tags":[
        "fire",
        "restoration",
        "damage"
    ],
    "wof:name":"Blind Ambition",
    "wof:placetype":"venue"
},
  "geometry": {"coordinates":[-119.298321,46.26896],"type":"Point"}
}