{
  "type": "Feature",
  "properties": {
    "addr:full":"415 W Walnut St Yakima WA 98902",
    "addr:housenumber":"415",
    "addr:postcode":"98902",
    "addr:street":"W Walnut St",
    "iso:country":"US",
    "sg:address":"415 W Walnut St",
    "sg:city":"Yakima",
    "sg:classifiers":[
        {
            "category":"Deli",
            "type":"Food & Drink"
        },
        {
            "category":"Restaurant",
            "type":"Food & Drink"
        }
    ],
    "sg:phone":"+1 509 452 2332",
    "sg:postcode":"98902",
    "sg:province":"WA",
    "sg:tags":[
        "delicatessen"
    ],
    "wof:name":"5th Avenue Deli",
    "wof:placetype":"venue"
},
  "geometry": {"coordinates":[-120.513093,46.59782],"type":"Point"}
}