{
  "type": "Feature",
  "properties": {
    "iso:country":"US",
    "sg:address":"3224 Colby Ave",
    "sg:city":"Everett",
    "sg:classifiers":[
        {
            "category":"Health Services",
            "subcategory":"Doctor",
            "type":"Services"
        }
    ],
    "sg:phone":"+1 425 259 3505",
    "sg:postcode":"98201",
    "sg:province":"WA",
    "sg:tags":[
        "dentist"
    ],
    "wof:name":"Thomas E Benjamin DDS",
    "wof:placetype":"venue"
},
  "geometry": {"coordinates":[-122.208507,47.974207],"type":"Point"}
}