{
  "type": "Feature",
  "properties": {
    "addr:full":"815 121st St NW Gig Harbor WA 98332",
    "addr:housenumber":"815",
    "addr:postcode":"98332",
    "addr:street":"121St St Nw",
    "iso:country":"US",
    "sg:address":"815 121st St NW",
    "sg:city":"Gig Harbor",
    "sg:classifiers":[
        {
            "category":"Shopping",
            "subcategory":"Computers & Home Electronics",
            "type":"Retail Goods"
        }
    ],
    "sg:phone":"+1 253 858 6866",
    "sg:postcode":"98332",
    "sg:province":"WA",
    "sg:tags":[
        "high",
        "fidelity",
        "stereophonic"
    ],
    "wof:name":"Vision 21",
    "wof:placetype":"venue"
},
  "geometry": {"coordinates":[-122.55001900000001,47.368108],"type":"Point"}
}