{
  "type": "Feature",
  "properties": {
    "addr:full":"108 Trosper Rd SW Olympia WA 98501",
    "addr:housenumber":"108",
    "addr:postcode":"98501",
    "addr:street":"Trosper Rd Sw",
    "iso:country":"US",
    "sg:address":"108 Trosper Rd SW",
    "sg:city":"Olympia",
    "sg:classifiers":[
        {
            "category":"Education",
            "subcategory":"Special Training",
            "type":"Public Place"
        }
    ],
    "sg:phone":"+1 360 357 9896",
    "sg:postcode":"98501",
    "sg:province":"WA",
    "wof:name":"Ralphs Interpreting Serv",
    "wof:placetype":"venue"
},
  "geometry": {"coordinates":[-122.908826,47.000031],"type":"Point"}
}