{
  "type": "Feature",
  "properties": {
    "addr:full":"5293 Guemes Island Rd Anacortes WA 98221",
    "addr:housenumber":"5293",
    "addr:postcode":"98221",
    "addr:street":"Guemes Island Rd",
    "iso:country":"US",
    "sg:address":"5293 Guemes Island Rd",
    "sg:city":"Anacortes",
    "sg:classifiers":[
        {
            "category":"Organizations",
            "subcategory":"Professional Association",
            "type":"Services"
        }
    ],
    "sg:phone":"+1 360 293 8128",
    "sg:postcode":"98221",
    "sg:province":"WA",
    "sg:tags":[
        "religious"
    ],
    "wof:name":"Humanists of North Puget Sound",
    "wof:placetype":"venue"
},
  "geometry": {"coordinates":[-122.622379,48.56746],"type":"Point"}
}