{
  "type": "Feature",
  "properties": {
    "iso:country":"US",
    "sg:address":"34507 32nd Ct SW",
    "sg:city":"Federal Way",
    "sg:classifiers":[
        {
            "category":"Manufacturing",
            "subcategory":"Glass & Minerals",
            "type":"Manufacturing & Wholesale Goods"
        }
    ],
    "sg:phone":"+1 253 838 0323",
    "sg:postcode":"98023",
    "sg:province":"WA",
    "sg:tags":[
        "product",
        "mfg"
    ],
    "wof:name":"Beads of Fire",
    "wof:placetype":"venue"
},
  "geometry": {"coordinates":[-122.37469900000001,47.292909],"type":"Point"}
}