{
  "type": "Feature",
  "properties": {
    "addr:full":"1409 Franklin St Ste 201 Vancouver WA 98660",
    "addr:housenumber":"1409",
    "addr:postcode":"98660",
    "addr:street":"Franklin St Ste 201",
    "iso:country":"US",
    "sg:address":"1409 Franklin St Ste 201",
    "sg:city":"Vancouver",
    "sg:classifiers":[
        {
            "category":"Professional",
            "subcategory":"Research",
            "type":"Services"
        }
    ],
    "sg:phone":"+1 360 823 1700",
    "sg:postcode":"98660",
    "sg:province":"WA",
    "sg:tags":[
        "economic",
        "analysis"
    ],
    "wof:name":"Economic And Fincl Analysist",
    "wof:placetype":"venue"
},
  "geometry": {"coordinates":[-122.67707799999999,45.631912],"type":"Point"}
}