{
  "type": "Feature",
  "properties": {
    "addr:full":"600 NW 80th St Seattle WA 98117",
    "addr:housenumber":"600",
    "addr:postcode":"98117",
    "addr:street":"Nw 80Th St",
    "iso:country":"US",
    "sg:address":"600 NW 80th St",
    "sg:city":"Seattle",
    "sg:classifiers":[
        {
            "category":"Building & Trades",
            "subcategory":"Construction",
            "type":"Services"
        }
    ],
    "sg:phone":"+1 206 789 0950",
    "sg:postcode":"98117",
    "sg:province":"WA",
    "sg:tags":[
        "contractor"
    ],
    "wof:name":"Delta General Contractors LLC",
    "wof:placetype":"venue"
},
  "geometry": {"coordinates":[-122.366028,47.686935],"type":"Point"}
}