{
  "type": "Feature",
  "properties": {
    "addr:full":"1621 196th St SE Bothell WA 98012",
    "addr:housenumber":"1621",
    "addr:postcode":"98012",
    "addr:street":"196Th St Se",
    "iso:country":"US",
    "sg:address":"1621 196th St SE",
    "sg:city":"Bothell",
    "sg:classifiers":[
        {
            "category":"Freight",
            "type":"Transportation"
        }
    ],
    "sg:phone":"+1 425 481 8883",
    "sg:postcode":"98012",
    "sg:province":"WA",
    "sg:tags":[
        "special",
        "general"
    ],
    "wof:name":"Affordable Self Storage",
    "wof:placetype":"venue"
},
  "geometry": {"coordinates":[-122.21122,47.820309],"type":"Point"}
}