{
  "type": "Feature",
  "properties": {
    "iso:country":"US",
    "sg:address":"701 Grand Blvd",
    "sg:city":"Vancouver",
    "sg:classifiers":[
        {
            "category":"Organizations",
            "subcategory":"Membership Organization",
            "type":"Services"
        }
    ],
    "sg:phone":"+1 360 906 7119",
    "sg:postcode":"98661",
    "sg:province":"WA",
    "wof:name":"Lewis & Clark Bicentennial Van",
    "wof:placetype":"venue"
},
  "geometry": {"coordinates":[-122.640592,45.626781],"type":"Point"}
}