{
  "type": "Feature",
  "properties": {
    "addr:full":"2805 Saint Andrews Loop Pasco WA 99301",
    "addr:housenumber":"2805",
    "addr:postcode":"99301",
    "addr:street":"Saint Andrews Loop",
    "iso:country":"US",
    "sg:address":"2805 Saint Andrews Loop",
    "sg:city":"Pasco",
    "sg:classifiers":[
        {
            "category":"Real Estate",
            "subcategory":"Real Estate Services",
            "type":"Services"
        }
    ],
    "sg:phone":"+1 509 545 3355",
    "sg:postcode":"99301",
    "sg:province":"WA",
    "sg:tags":[
        "management",
        "rental"
    ],
    "wof:name":"Olympia Ltd Partnership",
    "wof:placetype":"venue"
},
  "geometry": {"coordinates":[-119.11483699999999,46.252798],"type":"Point"}
}