{
  "type": "Feature",
  "properties": {
    "addr:full":"1031 17th St NE Auburn WA 98002",
    "addr:housenumber":"1031",
    "addr:postcode":"98002",
    "addr:street":"17Th St Ne",
    "iso:country":"US",
    "sg:address":"1031 17th St NE",
    "sg:city":"Auburn",
    "sg:classifiers":[
        {
            "category":"Building & Trades",
            "subcategory":"Construction",
            "type":"Services"
        }
    ],
    "sg:phone":"+1 253 939 5674",
    "sg:postcode":"98002",
    "sg:province":"WA",
    "sg:tags":[
        "concrete",
        "contractor"
    ],
    "wof:name":"Liberty Cement Finishing",
    "wof:placetype":"venue"
},
  "geometry": {"coordinates":[-122.214043,47.322911],"type":"Point"}
}