{
  "type": "Feature",
  "properties": {
    "addr:full":"113 W Meeker Puyallup WA 98371",
    "addr:housenumber":"113",
    "addr:postcode":"98371",
    "addr:street":"W Meeker",
    "iso:country":"US",
    "sg:address":"113 W Meeker",
    "sg:city":"Puyallup",
    "sg:classifiers":[
        {
            "category":"Shopping",
            "subcategory":"Used Merchandise",
            "type":"Retail Goods"
        }
    ],
    "sg:phone":"+1 253 848 5637",
    "sg:postcode":"98371",
    "sg:province":"WA",
    "sg:tags":[
        "shop",
        "thrift"
    ],
    "wof:name":"St Vincent De Paul Thrift",
    "wof:placetype":"venue"
},
  "geometry": {"coordinates":[-122.29495799999999,47.191051],"type":"Point"}
}