{
  "type": "Feature",
  "properties": {
    "addr:full":"3403 W Princeton Ave Spokane WA 99205",
    "addr:housenumber":"3403",
    "addr:postcode":"99205",
    "addr:street":"W Princeton Ave",
    "iso:country":"US",
    "sg:address":"3403 W Princeton Ave",
    "sg:city":"Spokane",
    "sg:classifiers":[
        {
            "category":"Education",
            "subcategory":"Special Training",
            "type":"Public Place"
        }
    ],
    "sg:phone":"+1 509 325 7489",
    "sg:postcode":"99205",
    "sg:province":"WA",
    "sg:tags":[
        "personal",
        "development"
    ],
    "wof:name":"R & D Drafting & Modeling",
    "wof:placetype":"venue"
},
  "geometry": {"coordinates":[-117.460927,47.698959],"type":"Point"}
}