{
  "type": "Feature",
  "properties": {
    "addr:full":"122 Holiday Rd Vantage WA 98950",
    "addr:housenumber":"122",
    "addr:postcode":"98950",
    "addr:street":"Holiday Rd",
    "iso:country":"US",
    "sg:address":"122 Holiday Rd",
    "sg:city":"Vantage",
    "sg:classifiers":[
        {
            "category":"Utilities",
            "subcategory":"Water",
            "type":"Services"
        }
    ],
    "sg:phone":"+1 509 856 2041",
    "sg:postcode":"98950",
    "sg:province":"WA",
    "sg:tags":[
        "company",
        "sewage"
    ],
    "wof:name":"Kittitas County Water District",
    "wof:placetype":"venue"
},
  "geometry": {"coordinates":[-119.985867,46.942069],"type":"Point"}
}