{
  "type": "Feature",
  "properties": {
    "addr:full":"4621 Manastash Rd Ellensburg WA 98926",
    "addr:housenumber":"4621",
    "addr:postcode":"98926",
    "addr:street":"Manastash Rd",
    "iso:country":"US",
    "sg:address":"4621 Manastash Rd",
    "sg:city":"Ellensburg",
    "sg:classifiers":[
        {
            "category":"Professional",
            "subcategory":"Business Services",
            "type":"Services"
        }
    ],
    "sg:phone":"+1 509 962 4101",
    "sg:postcode":"98926",
    "sg:province":"WA",
    "wof:name":"Barn Burner Crafts Laserworks",
    "wof:placetype":"venue"
},
  "geometry": {"coordinates":[-120.630814,46.971224],"type":"Point"}
}