{
  "type": "Feature",
  "properties": {
    "addr:full":"649 Moji Ln NW Bainbridge Island WA 98110",
    "addr:housenumber":"649",
    "addr:postcode":"98110",
    "addr:street":"Moji Ln Nw",
    "iso:country":"US",
    "sg:address":"649 Moji Ln NW",
    "sg:city":"Bainbridge Island",
    "sg:classifiers":[
        {
            "category":"Building & Trades",
            "subcategory":"Construction",
            "type":"Services"
        }
    ],
    "sg:phone":"+1 206 780 2516",
    "sg:postcode":"98110",
    "sg:province":"WA",
    "sg:tags":[
        "contractor"
    ],
    "wof:name":"Toad Holler LLC",
    "wof:placetype":"venue"
},
  "geometry": {"coordinates":[-122.53165799999999,47.631678],"type":"Point"}
}