{
  "type": "Feature",
  "properties": {
    "addr:full":"5519 SW Campbell Pl Seattle WA 98116",
    "addr:housenumber":"5519",
    "addr:postcode":"98116",
    "addr:street":"Sw Campbell Pl",
    "iso:country":"US",
    "sg:address":"5519 SW Campbell Pl",
    "sg:city":"Seattle",
    "sg:classifiers":[
        {
            "category":"Professional",
            "type":"Services"
        }
    ],
    "sg:phone":"+1 206 938 9444",
    "sg:postcode":"98116",
    "sg:province":"WA",
    "wof:name":"Thomas C Fleming",
    "wof:placetype":"venue"
},
  "geometry": {"coordinates":[-122.404016,47.578002],"type":"Point"}
}