{
  "type": "Feature",
  "properties": {
    "addr:full":"25810 SE 30th St Sammamish WA 98075",
    "addr:postcode":"25810;98075",
    "addr:street":"Se 30Th St",
    "iso:country":"US",
    "sg:address":"25810 SE 30th St",
    "sg:city":"Sammamish",
    "sg:classifiers":[
        {
            "category":"Professional",
            "subcategory":"Business Services",
            "type":"Services"
        }
    ],
    "sg:phone":"+1 425 392 5039",
    "sg:postcode":"98075",
    "sg:province":"WA",
    "wof:name":"Ted H McIntyre",
    "wof:placetype":"venue"
},
  "geometry": {"coordinates":[-121.99417800000001,47.582414],"type":"Point"}
}