{
  "type": "Feature",
  "properties": {
    "addr:full":"11409 107th Pl NE Kirkland WA 98033",
    "addr:housenumber":"11409",
    "addr:postcode":"98033",
    "addr:street":"107Th Pl Ne",
    "iso:country":"US",
    "sg:address":"11409 107th Pl NE",
    "sg:city":"Kirkland",
    "sg:classifiers":[
        {
            "category":"Building & Trades",
            "subcategory":"Cleaning & Sanitation",
            "type":"Services"
        }
    ],
    "sg:phone":"+1 425 825 1128",
    "sg:postcode":"98033",
    "sg:province":"WA",
    "sg:tags":[
        "maintenance"
    ],
    "wof:name":"Clean & Tidy Service",
    "wof:placetype":"venue"
},
  "geometry": {"coordinates":[-122.1979,47.70264],"type":"Point"}
}