{
  "type": "Feature",
  "properties": {
    "addr:full":"15400 SE 155th Pl Unit 9 Renton WA 98058",
    "addr:housenumber":"unit 9",
    "addr:postcode":"15400;98058",
    "addr:street":"Se 155Th Pl",
    "iso:country":"US",
    "sg:address":"15400 SE 155th Pl Unit 9",
    "sg:city":"Renton",
    "sg:classifiers":[
        {
            "category":"Manufacturing",
            "subcategory":"Printing",
            "type":"Manufacturing & Wholesale Goods"
        }
    ],
    "sg:phone":"+1 425 204 1942",
    "sg:postcode":"98058",
    "sg:province":"WA",
    "sg:tags":[
        "supplies-wholesale",
        "copier",
        "manufacturer"
    ],
    "wof:name":"Infinity Business Solutions",
    "wof:placetype":"venue"
},
  "geometry": {"coordinates":[-122.135803,47.46339],"type":"Point"}
}