{
  "type": "Feature",
  "properties": {
    "addr:full":"31618 42nd Ave SW Federal Way WA 98023",
    "addr:housenumber":"31618",
    "addr:postcode":"98023",
    "addr:street":"42Nd Ave Sw Federal Way",
    "iso:country":"US",
    "sg:address":"31618 42nd Ave SW",
    "sg:city":"Federal Way",
    "sg:classifiers":[
        {
            "category":"Retail",
            "subcategory":"Repair Shop",
            "type":"Services"
        }
    ],
    "sg:phone":"+1 253 835 0058",
    "sg:postcode":"98023",
    "sg:province":"WA",
    "wof:name":"Hatfield Yacht Refinishing",
    "wof:placetype":"venue"
},
  "geometry": {"coordinates":[-122.385504,47.317105],"type":"Point"}
}