{
  "type": "Feature",
  "properties": {
    "addr:full":"4518 Roosevelt Way NE Seattle WA 98105",
    "addr:housenumber":"4518",
    "addr:postcode":"98105",
    "addr:street":"Roosevelt Way Ne",
    "iso:country":"US",
    "sg:address":"4518 Roosevelt Way NE",
    "sg:city":"Seattle",
    "sg:classifiers":[
        {
            "category":"Shopping",
            "subcategory":"Hobbies, Toys, & Games",
            "type":"Retail Goods"
        },
        {
            "category":"Retail",
            "subcategory":"Auto Repair",
            "type":"Services"
        }
    ],
    "sg:phone":"+1 206 547 3917",
    "sg:postcode":"98105",
    "sg:province":"WA",
    "sg:tags":[
        "shop",
        "body",
        "model",
        "hobby",
        "supply"
    ],
    "wof:name":"Onp Auto Hobbies Inc",
    "wof:placetype":"venue"
},
  "geometry": {"coordinates":[-122.317001,47.661301],"type":"Point"}
}