{
  "type": "Feature",
  "properties": {
    "addr:full":"7979 Provost Rd NW Silverdale WA 98383",
    "addr:housenumber":"7979",
    "addr:postcode":"98383",
    "addr:street":"Provost Rd Nw",
    "iso:country":"US",
    "sg:address":"7979 Provost Rd NW",
    "sg:city":"Silverdale",
    "sg:classifiers":[
        {
            "category":"Freight",
            "type":"Transportation"
        }
    ],
    "sg:phone":"+1 360 698 1253",
    "sg:postcode":"98383",
    "sg:province":"WA",
    "sg:tags":[
        "special"
    ],
    "wof:name":"Affordable Self Storage",
    "wof:placetype":"venue"
},
  "geometry": {"coordinates":[-122.710965,47.634609],"type":"Point"}
}