{
  "type": "Feature",
  "properties": {
    "addr:full":"54 S Dawson St Seattle WA 98134",
    "addr:housenumber":"54",
    "addr:postcode":"98134",
    "addr:street":"S Dawson St",
    "iso:country":"US",
    "sg:address":"54 S Dawson St",
    "sg:city":"Seattle",
    "sg:classifiers":[
        {
            "category":"Utilities",
            "subcategory":"Refuse",
            "type":"Services"
        }
    ],
    "sg:phone":"+1 206 332 7700",
    "sg:postcode":"98134",
    "sg:province":"WA",
    "sg:tags":[
        "collection",
        "garbage"
    ],
    "wof:name":"Site 175",
    "wof:placetype":"venue"
},
  "geometry": {"coordinates":[-122.33652600000001,47.555717],"type":"Point"}
}