{
  "type": "Feature",
  "properties": {
    "addr:full":"805 E Francis Ave Spokane WA 99208",
    "addr:housenumber":"805",
    "addr:postcode":"99208",
    "addr:street":"E Francis Ave",
    "iso:country":"US",
    "sg:address":"805 E Francis Ave",
    "sg:city":"Spokane",
    "sg:classifiers":[
        {
            "category":"Home & Garden",
            "subcategory":"Building Materials",
            "type":"Retail Goods"
        }
    ],
    "sg:phone":"+1 509 483 7001",
    "sg:postcode":"99208",
    "sg:province":"WA",
    "sg:tags":[
        "glass",
        "window",
        "plate"
    ],
    "wof:name":"Harmon Auto Glass",
    "wof:placetype":"venue"
},
  "geometry": {"coordinates":[-117.39537,47.715128],"type":"Point"}
}