{
  "type": "Feature",
  "properties": {
    "addr:full":"2220 Queen Anne Ave N Seattle WA 98109",
    "addr:housenumber":"2220",
    "addr:postcode":"98109",
    "addr:street":"Queen Anne Ave N",
    "iso:country":"US",
    "sg:address":"2220 Queen Anne Ave N",
    "sg:city":"Seattle",
    "sg:classifiers":[
        {
            "category":"Food & Beverages",
            "subcategory":"Specialty",
            "type":"Retail Goods"
        }
    ],
    "sg:phone":"+1 206 286 9988",
    "sg:postcode":"98109",
    "sg:province":"WA",
    "sg:tags":[
        "gourmet",
        "shop"
    ],
    "wof:name":"CHEFSHOP.COM",
    "wof:placetype":"venue"
},
  "geometry": {"coordinates":[-122.35684000000001,47.63947],"type":"Point"}
}