{
  "type": "Feature",
  "properties": {
    "addr:full":"2812 Pacific Ave SE Olympia WA 98501",
    "addr:housenumber":"2812",
    "addr:postcode":"98501",
    "addr:street":"Pacific Ave Se",
    "iso:country":"US",
    "sg:address":"2812 Pacific Ave SE",
    "sg:city":"Olympia",
    "sg:classifiers":[
        {
            "category":"Retail",
            "subcategory":"Auto Repair",
            "type":"Services"
        }
    ],
    "sg:phone":"+1 360 357 3907",
    "sg:postcode":"98501",
    "sg:province":"WA",
    "sg:tags":[
        "automotive",
        "general"
    ],
    "wof:name":"Customations NW",
    "wof:placetype":"venue"
},
  "geometry": {"coordinates":[-122.859996,47.04329],"type":"Point"}
}