{
  "type": "Feature",
  "properties": {
    "addr:full":"6520 201st Ave SW Centralia WA 98531",
    "addr:housenumber":"6520",
    "addr:postcode":"98531",
    "addr:street":"201St Ave Sw",
    "iso:country":"US",
    "sg:address":"6520 201st Ave SW",
    "sg:city":"Centralia",
    "sg:classifiers":[
        {
            "category":"Social Services",
            "subcategory":"Child Care",
            "type":"Services"
        }
    ],
    "sg:phone":"+1 360 273 3492",
    "sg:postcode":"98531",
    "sg:province":"WA",
    "sg:tags":[
        "day"
    ],
    "wof:name":"Wendys Wonderland",
    "wof:placetype":"venue"
},
  "geometry": {"coordinates":[-123.020726,46.797269],"type":"Point"}
}