{
  "type": "Feature",
  "properties": {
    "addr:full":"2950 McLeod Rd Bellingham WA 98225",
    "addr:housenumber":"2950",
    "addr:postcode":"98225",
    "addr:street":"Mcleod Rd",
    "iso:country":"US",
    "sg:address":"2950 McLeod Rd",
    "sg:city":"Bellingham",
    "sg:classifiers":[
        {
            "category":"Shopping",
            "subcategory":"Bicycles & Sporting Goods",
            "type":"Retail Goods"
        }
    ],
    "sg:phone":"+1 360 647 0351",
    "sg:postcode":"98225",
    "sg:province":"WA",
    "sg:tags":[
        "sport"
    ],
    "wof:name":"Aberdeen Golf Repair",
    "wof:placetype":"venue"
},
  "geometry": {"coordinates":[-122.51098500000001,48.782564],"type":"Point"}
}