{
  "type": "Feature",
  "properties": {
    "addr:full":"4325 123rd Ave SE Bellevue WA 98006",
    "addr:housenumber":"4325",
    "addr:postcode":"98006",
    "addr:street":"123Rd Ave Se",
    "iso:country":"US",
    "sg:address":"4325 123rd Ave SE",
    "sg:city":"Bellevue",
    "sg:classifiers":[
        {
            "category":"Professional",
            "subcategory":"Advertising",
            "type":"Services"
        }
    ],
    "sg:phone":"+1 206 499 7505",
    "sg:postcode":"98006",
    "sg:province":"WA",
    "sg:tags":[
        "motion",
        "production"
    ],
    "wof:name":"Craig Johnston Comm LLC",
    "wof:placetype":"venue"
},
  "geometry": {"coordinates":[-122.17552999999999,47.568031],"type":"Point"}
}