{
  "type": "Feature",
  "properties": {
    "addr:full":"8547 381st Pl SE Snoqualmie WA 98065",
    "addr:housenumber":"8547",
    "addr:postcode":"98065",
    "addr:street":"381St Pl Se",
    "iso:country":"US",
    "sg:address":"8547 381st Pl SE",
    "sg:city":"Snoqualmie",
    "sg:classifiers":[
        {
            "category":"Building & Trades",
            "subcategory":"Construction",
            "type":"Services"
        }
    ],
    "sg:phone":"+1 425 831 2027",
    "sg:postcode":"98065",
    "sg:province":"WA",
    "sg:tags":[
        "house"
    ],
    "wof:name":"AAA Remodeling",
    "wof:placetype":"venue"
},
  "geometry": {"coordinates":[-121.83231499999999,47.52338],"type":"Point"}
}