{
  "type": "Feature",
  "properties": {
    "addr:full":"3719 Smith Ave Everett WA 98201",
    "addr:housenumber":"3719",
    "addr:postcode":"98201",
    "addr:street":"Smith Ave",
    "iso:country":"US",
    "sg:address":"3719 Smith Ave",
    "sg:city":"Everett",
    "sg:classifiers":[
        {
            "category":"Personal",
            "type":"Services"
        }
    ],
    "sg:phone":"+1 425 953 2766",
    "sg:postcode":"98201",
    "sg:province":"WA",
    "sg:tags":[
        "mover"
    ],
    "sg:website":"http://www.tomtracker.com/redirect.cfm?bID=18703&hID=35764",
    "wof:name":"Evergreen Moving Systems, Inc.",
    "wof:placetype":"venue"
},
  "geometry": {"coordinates":[-122.196855,47.968125],"type":"Point"}
}