{
  "type": "Feature",
  "properties": {
    "addr:full":"1201 Wilson St Port Townsend WA 98368",
    "addr:housenumber":"1201",
    "addr:postcode":"98368",
    "addr:street":"Wilson St",
    "iso:country":"US",
    "sg:address":"1201 Wilson St",
    "sg:city":"Port Townsend",
    "sg:classifiers":[
        {
            "category":"Professional",
            "subcategory":"Accounting & Tax Preparation",
            "type":"Services"
        }
    ],
    "sg:phone":"+1 360 385 4347",
    "sg:postcode":"98368",
    "sg:province":"WA",
    "wof:name":"Lisa Diane Vizzini",
    "wof:placetype":"venue"
},
  "geometry": {"coordinates":[-122.78829899999999,48.10979],"type":"Point"}
}