{
  "type": "Feature",
  "properties": {
    "iso:country":"US",
    "sg:address":"3703 Norton Ave",
    "sg:city":"Everett",
    "sg:classifiers":[
        {
            "category":"Freight",
            "type":"Transportation"
        }
    ],
    "sg:phone":"+1 425 773 6683",
    "sg:postcode":"98201",
    "sg:province":"WA",
    "sg:tags":[
        "mover"
    ],
    "sg:website":"www.barnolimoving.com",
    "wof:name":"Barnoli Moving",
    "wof:placetype":"venue"
},
  "geometry": {"coordinates":[-122.213723,47.96849],"type":"Point"}
}