{
  "type": "Feature",
  "properties": {
    "addr:full":"18528 Firlands Way N Suite A Shoreline WA 98133",
    "addr:postcode":"18528;98133",
    "addr:street":"Firlands Way N Suite A",
    "iso:country":"US",
    "sg:address":"18528 Firlands Way N Suite A",
    "sg:city":"Shoreline",
    "sg:classifiers":[
        {
            "category":"Health Services",
            "subcategory":"Dentist",
            "type":"Services"
        }
    ],
    "sg:phone":"+1 206 542 3535",
    "sg:postcode":"98133",
    "sg:province":"WA",
    "wof:name":"Ganzkow Greg DDS",
    "wof:placetype":"venue"
},
  "geometry": {"coordinates":[-122.33917599999999,47.734119],"type":"Point"}
}