{
  "type": "Feature",
  "properties": {
    "addr:full":"3978 Weathers Ct SE Port Orchard WA 98366",
    "addr:housenumber":"3978",
    "addr:postcode":"98366",
    "addr:street":"Weathers Ct Se",
    "iso:country":"US",
    "sg:address":"3978 Weathers Ct SE",
    "sg:city":"Port Orchard",
    "sg:classifiers":[
        {
            "category":"Building & Trades",
            "subcategory":"Cleaning & Sanitation",
            "type":"Services"
        }
    ],
    "sg:phone":"+1 360 876 4876",
    "sg:postcode":"98366",
    "sg:province":"WA",
    "sg:tags":[
        "maintenance"
    ],
    "wof:name":"Quality Chimney Care",
    "wof:placetype":"venue"
},
  "geometry": {"coordinates":[-122.605935,47.513187],"type":"Point"}
}