{
  "type": "Feature",
  "properties": {
    "addr:full":"20818 Old Hwy 99 SW Centralia WA 98531",
    "addr:housenumber":"20818",
    "addr:postcode":"98531",
    "addr:street":"Old Hwy 99 Sw",
    "iso:country":"US",
    "sg:address":"20818 Old Hwy 99 SW",
    "sg:city":"Centralia",
    "sg:classifiers":[
        {
            "category":"Retail",
            "subcategory":"Animal Services",
            "type":"Services"
        }
    ],
    "sg:phone":"+1 360 273 6313",
    "sg:postcode":"98531",
    "sg:province":"WA",
    "wof:name":"Top-N-Tails",
    "wof:placetype":"venue"
},
  "geometry": {"coordinates":[-123.01141699999999,46.786616],"type":"Point"}
}