{
  "type": "Feature",
  "properties": {
    "addr:full":"291 Lupine Dr Sequim WA 98382",
    "addr:housenumber":"291",
    "addr:postcode":"98382",
    "addr:street":"Lupine Dr",
    "iso:country":"US",
    "sg:address":"291 Lupine Dr",
    "sg:city":"Sequim",
    "sg:classifiers":[
        {
            "category":"Manufacturing",
            "subcategory":"Jewelry",
            "type":"Manufacturing & Wholesale Goods"
        }
    ],
    "sg:phone":"+1 360 683 6369",
    "sg:postcode":"98382",
    "sg:province":"WA",
    "sg:tags":[
        "jewelers-wholesale",
        "manufacturer"
    ],
    "wof:name":"Raddew Designs",
    "wof:placetype":"venue"
},
  "geometry": {"coordinates":[-122.927335,48.093571],"type":"Point"}
}