{
  "type": "Feature",
  "properties": {
    "addr:full":"61 S Pomona Rd Yakima WA 98901",
    "addr:housenumber":"61",
    "addr:postcode":"98901",
    "addr:street":"S Pomona Rd",
    "iso:country":"US",
    "sg:address":"61 S Pomona Rd",
    "sg:city":"Yakima",
    "sg:classifiers":[
        {
            "category":"Farming",
            "subcategory":"Farm",
            "type":"Manufacturing & Wholesale Goods"
        }
    ],
    "sg:phone":"+1 509 575 5762",
    "sg:postcode":"98901",
    "sg:province":"WA",
    "sg:tags":[
        "crop",
        "general"
    ],
    "wof:name":"El Kay Farms",
    "wof:placetype":"venue"
},
  "geometry": {"coordinates":[-120.484251,46.676603],"type":"Point"}
}