{
  "type": "Feature",
  "properties": {
    "addr:full":"1640 NW Gilman Blvd Issaquah WA 98027",
    "addr:housenumber":"1640",
    "addr:postcode":"98027",
    "addr:street":"Nw Gilman Blvd",
    "iso:country":"US",
    "sg:address":"1640 NW Gilman Blvd",
    "sg:city":"Issaquah",
    "sg:classifiers":[
        {
            "category":"Real Estate",
            "subcategory":"Real Estate Services",
            "type":"Services"
        },
        {
            "category":"Real Estate",
            "subcategory":"Real Estate Agent",
            "type":"Services"
        }
    ],
    "sg:phone":"+1 425 837 3530",
    "sg:postcode":"98027",
    "sg:province":"WA",
    "sg:tags":[
        "management"
    ],
    "wof:name":"Realty Executives",
    "wof:placetype":"venue"
},
  "geometry": {"coordinates":[-122.061977,47.5457],"type":"Point"}
}