{
  "type": "Feature",
  "properties": {
    "addr:full":"7633 SE 41st St Mercer Island WA 98040",
    "addr:housenumber":"7633",
    "addr:postcode":"98040",
    "addr:street":"Se 41St St",
    "iso:country":"US",
    "sg:address":"7633 SE 41st St",
    "sg:city":"Mercer Island",
    "sg:classifiers":[
        {
            "category":"Building & Trades",
            "subcategory":"Construction",
            "type":"Services"
        }
    ],
    "sg:phone":"+1 206 232 8534",
    "sg:postcode":"98040",
    "sg:province":"WA",
    "sg:tags":[
        "contractor"
    ],
    "wof:name":"Scott Pierce Contracting Inc",
    "wof:placetype":"venue"
},
  "geometry": {"coordinates":[-122.235894,47.57366],"type":"Point"}
}