{
  "type": "Feature",
  "properties": {
    "addr:full":"2721 N Van Marter Rd Spokane Valley WA 99206",
    "addr:housenumber":"2721",
    "addr:postcode":"99206",
    "addr:street":"N Van Marter Rd",
    "iso:country":"US",
    "sg:address":"2721 N Van Marter Rd",
    "sg:city":"Spokane Valley",
    "sg:classifiers":[
        {
            "category":"Professional",
            "subcategory":"Engineering",
            "type":"Services"
        }
    ],
    "sg:phone":"+1 509 922 5629",
    "sg:postcode":"99206",
    "sg:province":"WA",
    "sg:tags":[
        "engineer",
        "r",
        "printed",
        "circuit",
        "mfg"
    ],
    "sg:website":"www.infinetix.com",
    "wof:name":"Infinetix Corp",
    "wof:placetype":"venue"
},
  "geometry": {"coordinates":[-117.25906500000001,47.681029],"type":"Point"}
}