{
  "type": "Feature",
  "properties": {
    "addr:full":"15631 Broadway Ave Snohomish WA 98296",
    "addr:housenumber":"15631",
    "addr:postcode":"98296",
    "addr:street":"Broadway Ave",
    "iso:country":"US",
    "sg:address":"15631 Broadway Ave",
    "sg:city":"Snohomish",
    "sg:classifiers":[
        {
            "category":"Professional",
            "subcategory":"Management & Consulting",
            "type":"Services"
        }
    ],
    "sg:phone":"+1 360 668 1094",
    "sg:postcode":"98296",
    "sg:province":"WA",
    "sg:tags":[
        "development",
        "consultant",
        "training"
    ],
    "wof:name":"Wiskerchen John",
    "wof:placetype":"venue"
},
  "geometry": {"coordinates":[-122.099093,47.855098],"type":"Point"}
}