{
  "type": "Feature",
  "properties": {
    "addr:full":"3951 SW Barton St. Seattle WA 98127",
    "addr:housenumber":"3951",
    "addr:postcode":"98127",
    "addr:street":"Sw Barton St.",
    "iso:country":"US",
    "sg:address":"3951 SW Barton St.",
    "sg:city":"Seattle",
    "sg:classifiers":[
        {
            "category":"Park",
            "type":"Public Place"
        }
    ],
    "sg:postcode":"98127",
    "sg:province":"WA",
    "sg:website":"www.seattle.gov/parks/parkspaces...",
    "wof:name":"Fauntleroy Park",
    "wof:placetype":"venue"
},
  "geometry": {"coordinates":[-122.382615,47.521105],"type":"Point"}
}