{
  "type": "Feature",
  "properties": {
    "addr:full":"5501 NE Foster Rd Bainbridge Island WA 98110",
    "addr:housenumber":"5501",
    "addr:postcode":"98110",
    "addr:street":"Ne Foster Rd",
    "iso:country":"US",
    "sg:address":"5501 NE Foster Rd",
    "sg:city":"Bainbridge Island",
    "sg:classifiers":[
        {
            "category":"Home & Garden",
            "subcategory":"Building Materials",
            "type":"Retail Goods"
        }
    ],
    "sg:phone":"+1 206 762 3411",
    "sg:postcode":"98110",
    "sg:province":"WA",
    "wof:name":"Talon Enterprises Inc",
    "wof:placetype":"venue"
},
  "geometry": {"coordinates":[-122.574043,47.641207],"type":"Point"}
}