{
  "type": "Feature",
  "properties": {
    "addr:full":"411 Washington Ave N Kent WA 98032",
    "addr:housenumber":"411",
    "addr:postcode":"98032",
    "addr:street":"Washington Ave N",
    "iso:country":"US",
    "sg:address":"411 Washington Ave N",
    "sg:city":"Kent",
    "sg:classifiers":[
        {
            "category":"Restaurant",
            "type":"Food & Drink"
        }
    ],
    "sg:phone":"+1 253 850 1500",
    "sg:postcode":"98032",
    "sg:province":"WA",
    "sg:tags":[
        "eating"
    ],
    "wof:name":"Stop By Cafe",
    "wof:placetype":"venue"
},
  "geometry": {"coordinates":[-122.24749,47.384222],"type":"Point"}
}