{
  "type": "Feature",
  "properties": {
    "addr:full":"7228 Sandy Point Rd NE Olympia WA 98516",
    "addr:housenumber":"7228",
    "addr:postcode":"98516",
    "addr:street":"Sandy Point Rd Ne",
    "iso:country":"US",
    "sg:address":"7228 Sandy Point Rd NE",
    "sg:city":"Olympia",
    "sg:classifiers":[
        {
            "category":"Professional",
            "type":"Services"
        }
    ],
    "sg:phone":"+1 360 459 2971",
    "sg:postcode":"98516",
    "sg:province":"WA",
    "sg:tags":[
        "merchandise"
    ],
    "wof:name":"Sandy Point Studio",
    "wof:placetype":"venue"
},
  "geometry": {"coordinates":[-122.777749,47.123684],"type":"Point"}
}