{
  "type": "Feature",
  "properties": {
    "addr:full":"5603 Bayview Rd Langley WA 98260",
    "addr:housenumber":"5603",
    "addr:postcode":"98260",
    "addr:street":"Bayview Rd",
    "iso:country":"US",
    "sg:address":"5603 Bayview Rd",
    "sg:city":"Langley",
    "sg:classifiers":[
        {
            "category":"Shopping",
            "type":"Retail Goods"
        }
    ],
    "sg:phone":"+1 360 321 8414",
    "sg:postcode":"98260",
    "sg:province":"WA",
    "sg:tags":[
        "material",
        "artist",
        "supply"
    ],
    "wof:name":"Bayview Arts",
    "wof:placetype":"venue"
},
  "geometry": {"coordinates":[-122.46094600000001,48.007596],"type":"Point"}
}