{
  "type": "Feature",
  "properties": {
    "addr:full":"1224 10th Ave NW Puyallup WA 98371",
    "addr:housenumber":"1224",
    "addr:postcode":"98371",
    "addr:street":"10Th Ave Nw",
    "iso:country":"US",
    "sg:address":"1224 10th Ave NW",
    "sg:city":"Puyallup",
    "sg:classifiers":[
        {
            "category":"Building & Trades",
            "subcategory":"Construction",
            "type":"Services"
        }
    ],
    "sg:phone":"+1 253 845 3679",
    "sg:postcode":"98371",
    "sg:province":"WA",
    "sg:tags":[
        "home",
        "general",
        "family",
        "contractor"
    ],
    "wof:name":"M & E Construction",
    "wof:placetype":"venue"
},
  "geometry": {"coordinates":[-122.309669,47.199827],"type":"Point"}
}