{
  "type": "Feature",
  "properties": {
    "addr:full":"6028 N Fleming St Spokane WA 99205",
    "addr:housenumber":"6028",
    "addr:postcode":"99205",
    "addr:street":"N Fleming St",
    "iso:country":"US",
    "sg:address":"6028 N Fleming St",
    "sg:city":"Spokane",
    "sg:classifiers":[
        {
            "category":"Professional",
            "type":"Services"
        }
    ],
    "sg:phone":"+1 509 325 5739",
    "sg:postcode":"99205",
    "sg:province":"WA",
    "wof:name":"Marlup Arts",
    "wof:placetype":"venue"
},
  "geometry": {"coordinates":[-117.467913,47.71414],"type":"Point"}
}