{
  "type": "Feature",
  "properties": {
    "addr:full":"203 SE Park Plaza Drive #220 Vancouver WA 98684",
    "addr:housenumber":"203",
    "addr:postcode":"98684",
    "addr:street":"Se Park Plaza Drive # 220",
    "iso:country":"US",
    "sg:address":"203 SE Park Plaza Drive #220",
    "sg:city":"Vancouver",
    "sg:classifiers":[
        {
            "category":"Professional",
            "subcategory":"Accounting & Tax Preparation",
            "type":"Services"
        },
        {
            "category":"Professional",
            "subcategory":"Lawyer & Legal Services",
            "type":"Services"
        },
        {
            "category":"Banks & Credit Unions",
            "subcategory":"Financial Services",
            "type":"Services"
        }
    ],
    "sg:phone":"+1 800 896 5536",
    "sg:postcode":"98684",
    "sg:province":"WA",
    "sg:tags":[
        "accountant",
        "advising"
    ],
    "sg:website":"www.JKHarris.com",
    "wof:name":"JK Harris & Company",
    "wof:placetype":"venue"
},
  "geometry": {"coordinates":[-122.53802,45.620954],"type":"Point"}
}