{
  "type": "Feature",
  "properties": {
    "addr:full":"1501 Pike Pl Seattle WA 98101",
    "addr:housenumber":"1501",
    "addr:postcode":"98101",
    "addr:street":"Pike Pl",
    "iso:country":"US",
    "sg:address":"1501 Pike Pl",
    "sg:city":"Seattle",
    "sg:classifiers":[
        {
            "category":"Shopping",
            "subcategory":"Used Merchandise",
            "type":"Retail Goods"
        }
    ],
    "sg:phone":"+1 206 623 2870",
    "sg:postcode":"98101",
    "sg:province":"WA",
    "wof:name":"Old Seattle Paper Works",
    "wof:placetype":"venue"
},
  "geometry": {"coordinates":[-122.34061699999999,47.608719],"type":"Point"}
}