{
  "type": "Feature",
  "properties": {
    "addr:full":"14430 52nd Pl W Edmonds WA 98026",
    "addr:housenumber":"14430",
    "addr:postcode":"98026",
    "addr:street":"52Nd Pl W",
    "iso:country":"US",
    "sg:address":"14430 52nd Pl W",
    "sg:city":"Edmonds",
    "sg:classifiers":[
        {
            "category":"Real Estate",
            "subcategory":"Real Estate Agent",
            "type":"Services"
        }
    ],
    "sg:phone":"+1 206 367 4947",
    "sg:postcode":"98026",
    "sg:province":"WA",
    "sg:tags":[
        "management"
    ],
    "wof:name":"Cornerstone Dev & Inv Co",
    "wof:placetype":"venue"
},
  "geometry": {"coordinates":[-122.304788,47.867328],"type":"Point"}
}