{
  "type": "Feature",
  "properties": {
    "addr:full":"413 N Tower Ave Centralia WA 98531",
    "addr:housenumber":"413",
    "addr:postcode":"98531",
    "addr:street":"N Tower Ave",
    "iso:country":"US",
    "sg:address":"413 N Tower Ave",
    "sg:city":"Centralia",
    "sg:classifiers":[
        {
            "category":"Organizations",
            "subcategory":"Religious Organization",
            "type":"Services"
        }
    ],
    "sg:phone":"+1 360 736 6443",
    "sg:postcode":"98531",
    "sg:province":"WA",
    "sg:tags":[
        "church"
    ],
    "sg:website":"www.destinycc.net",
    "wof:name":"Destiny Christian Ctr",
    "wof:placetype":"venue"
},
  "geometry": {"coordinates":[-122.952861,46.719833],"type":"Point"}
}