{
  "type": "Feature",
  "properties": {
    "addr:full":"1422 Millerdale Ave Wenatchee WA 98801",
    "addr:housenumber":"1422",
    "addr:postcode":"98801",
    "addr:street":"Millerdale Ave",
    "iso:country":"US",
    "sg:address":"1422 Millerdale Ave",
    "sg:city":"Wenatchee",
    "sg:classifiers":[
        {
            "category":"Professional",
            "subcategory":"Accounting & Tax Preparation",
            "type":"Services"
        }
    ],
    "sg:phone":"+1 509 665 9851",
    "sg:postcode":"98801",
    "sg:province":"WA",
    "sg:tags":[
        "billing"
    ],
    "wof:name":"Health Care Billing Specialist",
    "wof:placetype":"venue"
},
  "geometry": {"coordinates":[-120.33438200000001,47.411764],"type":"Point"}
}