{
  "type": "Feature",
  "properties": {
    "addr:full":"2310 Rudkin Rd Union Gap WA 98903",
    "addr:housenumber":"2310",
    "addr:postcode":"98903",
    "addr:street":"Rudkin Rd",
    "iso:country":"US",
    "sg:address":"2310 Rudkin Rd",
    "sg:city":"Union Gap",
    "sg:classifiers":[
        {
            "category":"Bars & Pubs",
            "type":"Food & Drink"
        }
    ],
    "sg:phone":"+1 509 574 4115",
    "sg:postcode":"98903",
    "sg:province":"WA",
    "sg:tags":[
        "drinking"
    ],
    "wof:name":"Jammer Sports Bar",
    "wof:placetype":"venue"
},
  "geometry": {"coordinates":[-120.47242199999999,46.573491],"type":"Point"}
}