{
  "type": "Feature",
  "properties": {
    "addr:full":"1404 Harrison Ave NW Olympia WA 98502",
    "addr:housenumber":"1404",
    "addr:postcode":"olympia wa 98502",
    "addr:street":"Harrison Ave Nw",
    "iso:country":"US",
    "sg:address":"1404 Harrison Ave NW",
    "sg:city":"Olympia",
    "sg:classifiers":[
        {
            "category":"Shopping",
            "subcategory":"Musical Instruments",
            "type":"Retail Goods"
        }
    ],
    "sg:phone":"+1 360 943 7500",
    "sg:postcode":"98502",
    "sg:province":"WA",
    "sg:tags":[
        "rental"
    ],
    "wof:name":"Yenney Music Company",
    "wof:placetype":"venue"
},
  "geometry": {"coordinates":[-122.92014399999999,47.046004],"type":"Point"}
}