{
  "type": "Feature",
  "properties": {
    "addr:full":"2737 78th Ave SE Mercer Island WA 98040",
    "addr:housenumber":"2737",
    "addr:postcode":"98040",
    "addr:street":"78Th Ave Se",
    "iso:country":"US",
    "sg:address":"2737 78th Ave SE",
    "sg:city":"Mercer Island",
    "sg:classifiers":[
        {
            "category":"Manufacturing",
            "subcategory":"Lumber",
            "type":"Manufacturing & Wholesale Goods"
        }
    ],
    "sg:phone":"+1 206 232 8390",
    "sg:postcode":"98040",
    "sg:province":"WA",
    "wof:name":"1st Western Financial LLC",
    "wof:placetype":"venue"
},
  "geometry": {"coordinates":[-122.233689,47.585941],"type":"Point"}
}