{
  "type": "Feature",
  "properties": {
    "addr:full":"3511 31st Ave W Seattle WA 98199",
    "addr:housenumber":"3511",
    "addr:postcode":"98199",
    "addr:street":"31St Ave W",
    "iso:country":"US",
    "sg:address":"3511 31st Ave W",
    "sg:city":"Seattle",
    "sg:classifiers":[
        {
            "category":"Sports & Exercise",
            "subcategory":"Gym",
            "type":"Entertainment"
        }
    ],
    "sg:phone":"+1 206 281 8004",
    "sg:postcode":"98199",
    "sg:province":"WA",
    "sg:tags":[
        "fitness",
        "physical",
        "facility"
    ],
    "wof:name":"Deborah Merriman Paulsen",
    "wof:placetype":"venue"
},
  "geometry": {"coordinates":[-122.39698,47.652161],"type":"Point"}
}