{
  "type": "Feature",
  "properties": {
    "addr:full":"2413 W 3rd Ave Spokane WA 99204",
    "addr:housenumber":"2413",
    "addr:postcode":"99204",
    "addr:street":"W 3Rd Ave",
    "iso:country":"US",
    "sg:address":"2413 W 3rd Ave",
    "sg:city":"Spokane",
    "sg:classifiers":[
        {
            "category":"Home & Garden",
            "subcategory":"Carpets & Floor Coverings",
            "type":"Retail Goods"
        }
    ],
    "sg:phone":"+1 509 456 5370",
    "sg:postcode":"99204",
    "sg:province":"WA",
    "wof:name":"JC Floor Covering",
    "wof:placetype":"venue"
},
  "geometry": {"coordinates":[-117.44850700000001,47.653566],"type":"Point"}
}