{
  "type": "Feature",
  "properties": {
    "addr:full":"415 W 13th Ave Spokane WA 99204",
    "addr:housenumber":"415",
    "addr:postcode":"99204",
    "addr:street":"W 13Th Ave",
    "iso:country":"US",
    "sg:address":"415 W 13th Ave",
    "sg:city":"Spokane",
    "sg:classifiers":[
        {
            "category":"Professional",
            "type":"Services"
        }
    ],
    "sg:phone":"+1 509 455 7191",
    "sg:postcode":"99204",
    "sg:province":"WA",
    "wof:name":"Carmen Gonzalez",
    "wof:placetype":"venue"
},
  "geometry": {"coordinates":[-117.417473,47.643779],"type":"Point"}
}