{
  "type": "Feature",
  "properties": {
    "addr:full":"13238 NE 20th St Bellevue WA 98005",
    "addr:housenumber":"13238",
    "addr:postcode":"98005",
    "addr:street":"Ne 20Th St",
    "iso:country":"US",
    "sg:address":"13238 NE 20th St",
    "sg:city":"Bellevue",
    "sg:classifiers":[
        {
            "category":"Wholesale",
            "subcategory":"Home Furnishings",
            "type":"Manufacturing & Wholesale Goods"
        }
    ],
    "sg:phone":"+1 425 649 9890",
    "sg:postcode":"98005",
    "sg:province":"WA",
    "sg:tags":[
        "blind",
        "shade"
    ],
    "sg:website":"www.3day.com",
    "wof:name":"3 Day Blinds",
    "wof:placetype":"venue"
},
  "geometry": {"coordinates":[-122.162504,47.628053],"type":"Point"}
}