{
  "type": "Feature",
  "properties": {
    "addr:full":"16430 29th Dr SE Bothell WA 98012",
    "addr:housenumber":"16430",
    "addr:postcode":"98012",
    "addr:street":"29Th Dr Se",
    "iso:country":"US",
    "sg:address":"16430 29th Dr SE",
    "sg:city":"Bothell",
    "sg:classifiers":[
        {
            "category":"Organizations",
            "subcategory":"Professional Association",
            "type":"Services"
        }
    ],
    "sg:phone":"+1 425 481 5579",
    "sg:postcode":"98012",
    "sg:province":"WA",
    "wof:name":"Richard C Wigre",
    "wof:placetype":"venue"
},
  "geometry": {"coordinates":[-122.19329999999999,47.848654],"type":"Point"}
}