{
  "type": "Feature",
  "properties": {
    "addr:full":"42 Chapman Loop Steilacoom WA 98388",
    "addr:housenumber":"42",
    "addr:postcode":"98388",
    "addr:street":"Chapman Loop",
    "iso:country":"US",
    "sg:address":"42 Chapman Loop",
    "sg:city":"Steilacoom",
    "sg:classifiers":[
        {
            "category":"Health Services",
            "subcategory":"Doctor",
            "type":"Services"
        }
    ],
    "sg:phone":"+1 253 588 0149",
    "sg:postcode":"98388",
    "sg:province":"WA",
    "sg:tags":[
        "medical"
    ],
    "wof:name":"Gregory H Cain MD PS",
    "wof:placetype":"venue"
},
  "geometry": {"coordinates":[-122.612137,47.158476],"type":"Point"}
}