{
  "type": "Feature",
  "properties": {
    "addr:full":"2358 10th Ave E #115 Seattle WA 98102",
    "addr:housenumber":"2358",
    "addr:postcode":"98102",
    "addr:street":"10Th Ave E # 115",
    "iso:country":"US",
    "sg:address":"2358 10th Ave E #115",
    "sg:city":"Seattle",
    "sg:classifiers":[
        {
            "category":"Personal",
            "subcategory":"Nail Salon",
            "type":"Services"
        }
    ],
    "sg:phone":"+1 206 838 8334",
    "sg:postcode":"98102",
    "sg:province":"WA",
    "wof:name":"Tenth Ave Spa & Nails",
    "wof:placetype":"venue"
},
  "geometry": {"coordinates":[-122.32006800000001,47.64074],"type":"Point"}
}