{
  "type": "Feature",
  "properties": {
    "addr:full":"864 S Fife St Tacoma WA 98405",
    "addr:housenumber":"864",
    "addr:postcode":"98405",
    "addr:street":"S Fife St",
    "iso:country":"US",
    "sg:address":"864 S Fife St",
    "sg:city":"Tacoma",
    "sg:classifiers":[
        {
            "category":"Shopping",
            "subcategory":"Stationery & Office Supplies",
            "type":"Retail Goods"
        }
    ],
    "sg:phone":"+1 253 565 6612",
    "sg:postcode":"98405",
    "sg:province":"WA",
    "sg:tags":[
        "album",
        "scrapbook"
    ],
    "wof:name":"Creative Memories",
    "wof:placetype":"venue"
},
  "geometry": {"coordinates":[-122.470367,47.251825],"type":"Point"}
}