{
  "type": "Feature",
  "properties": {
    "iso:country":"US",
    "sg:address":"6503 Evergreen Way",
    "sg:city":"Everett",
    "sg:classifiers":[
        {
            "category":"Food & Beverages",
            "subcategory":"Specialty",
            "type":"Retail Goods"
        }
    ],
    "sg:phone":"+1 425 347 2143",
    "sg:postcode":"98203",
    "sg:province":"WA",
    "sg:tags":[
        "tea",
        "coffee"
    ],
    "wof:name":"Bean Me Up Espresso",
    "wof:placetype":"venue"
},
  "geometry": {"coordinates":[-122.21895000000001,47.936224],"type":"Point"}
}