{
  "type": "Feature",
  "properties": {
    "addr:full":"705 4th Ave E Olympia WA 98506",
    "addr:housenumber":"705",
    "addr:postcode":"98506",
    "addr:street":"4Th Ave E",
    "iso:country":"US",
    "sg:address":"705 4th Ave E",
    "sg:city":"Olympia",
    "sg:classifiers":[
        {
            "category":"Professional",
            "subcategory":"Printing & Photocopies",
            "type":"Services"
        }
    ],
    "sg:phone":"+1 360 956 1020",
    "sg:postcode":"98506",
    "sg:province":"WA",
    "sg:tags":[
        "photocopying",
        "blueprinting",
        "digital"
    ],
    "wof:name":"Doopes Copy Tech",
    "wof:placetype":"venue"
},
  "geometry": {"coordinates":[-122.89344,47.04537],"type":"Point"}
}