{
  "type": "Feature",
  "properties": {
    "addr:full":"Southend Seattle WA 98108",
    "addr:postcode":"98108",
    "iso:country":"US",
    "sg:address":"Southend",
    "sg:city":"Seattle",
    "sg:classifiers":[
        {
            "category":"Building & Trades",
            "subcategory":"Plumbing",
            "type":"Services"
        }
    ],
    "sg:phone":"+1 206 248 9340",
    "sg:postcode":"98108",
    "sg:province":"WA",
    "wof:name":"Ed's Plumbing & Drain Cleaning",
    "wof:placetype":"venue"
},
  "geometry": {"coordinates":[-122.30300099999999,47.547798],"type":"Point"}
}