{
  "type": "Feature",
  "properties": {
    "addr:full":"422 W Riverside Ave Ste 830 Spokane WA 99201",
    "addr:housenumber":"422",
    "addr:postcode":"99201",
    "addr:street":"W Riverside Ave Ste 830",
    "iso:country":"US",
    "sg:address":"422 W Riverside Ave Ste 830",
    "sg:city":"Spokane",
    "sg:classifiers":[
        {
            "category":"Professional",
            "subcategory":"Management & Consulting",
            "type":"Services"
        },
        {
            "category":"Professional",
            "subcategory":"Lawyer & Legal Services",
            "type":"Services"
        },
        {
            "category":"Banks & Credit Unions",
            "subcategory":"Financial Services",
            "type":"Services"
        }
    ],
    "sg:phone":"+1 509 838 4175",
    "sg:postcode":"99201",
    "sg:province":"WA",
    "sg:tags":[
        "attorney",
        "estate",
        "consultant",
        "wills",
        "financing",
        "planning",
        "trust"
    ],
    "sg:website":"http://www.assetplanning.com",
    "wof:name":"Asset Planning & Management Inc",
    "wof:placetype":"venue"
},
  "geometry": {"coordinates":[-117.41837099999999,47.657955],"type":"Point"}
}