{
  "type": "Feature",
  "properties": {
    "addr:full":"16556 NE 74th St Redmond WA 98052",
    "addr:housenumber":"16556",
    "addr:postcode":"98052",
    "addr:street":"Ne 74Th St",
    "iso:country":"US",
    "sg:address":"16556 NE 74th St",
    "sg:city":"Redmond",
    "sg:classifiers":[
        {
            "category":"Restaurant",
            "type":"Food & Drink"
        }
    ],
    "sg:phone":"+1 425 861 4230",
    "sg:postcode":"98052",
    "sg:province":"WA",
    "sg:tags":[
        "grill",
        "bar"
    ],
    "wof:name":"Pasha Grill",
    "wof:placetype":"venue"
},
  "geometry": {"coordinates":[-122.119184,47.670099],"type":"Point"}
}