{
  "type": "Feature",
  "properties": {
    "addr:full":"19777 State Rte 20 Coupeville WA 98239",
    "addr:housenumber":"19777",
    "addr:postcode":"98239",
    "addr:street":"State Rte 20",
    "iso:country":"US",
    "sg:address":"19777 State Rte 20",
    "sg:city":"Coupeville",
    "sg:classifiers":[
        {
            "category":"Restaurant",
            "type":"Food & Drink"
        }
    ],
    "sg:phone":"+1 360 678 5610",
    "sg:postcode":"98239",
    "sg:province":"WA",
    "sg:tags":[
        "eating"
    ],
    "wof:name":"Countryside Inn",
    "wof:placetype":"venue"
},
  "geometry": {"coordinates":[-122.64445600000001,48.207909],"type":"Point"}
}