{
  "type": "Feature",
  "properties": {
    "addr:full":"5 North Rd N Tacoma WA 98406",
    "addr:housenumber":"5",
    "addr:postcode":"98406",
    "addr:street":"North Rd N",
    "iso:country":"US",
    "sg:address":"5 North Rd N",
    "sg:city":"Tacoma",
    "sg:classifiers":[
        {
            "category":"Education",
            "subcategory":"College",
            "type":"Public Place"
        }
    ],
    "sg:phone":"+1 253 752 2030",
    "sg:postcode":"98406",
    "sg:province":"WA",
    "wof:name":"Vancouver School of Theology",
    "wof:placetype":"venue"
},
  "geometry": {"coordinates":[-122.470596,47.272409],"type":"Point"}
}