{
  "type": "Feature",
  "properties": {
    "addr:full":"150 105th Ave NE Bellevue WA 98004",
    "addr:housenumber":"150",
    "addr:postcode":"98004",
    "addr:street":"105Th Ave Ne",
    "iso:country":"US",
    "sg:address":"150 105th Ave NE",
    "sg:city":"Bellevue",
    "sg:classifiers":[
        {
            "category":"Restaurant",
            "type":"Food & Drink"
        }
    ],
    "sg:phone":"+1 425 455 3226",
    "sg:postcode":"98004",
    "sg:province":"WA",
    "sg:tags":[
        "eating"
    ],
    "sg:website":"www.chantanee.com",
    "wof:name":"Chantanee Family Thai Rest",
    "wof:placetype":"venue"
},
  "geometry": {"coordinates":[-122.200075,47.611705],"type":"Point"}
}