{
  "type": "Feature",
  "properties": {
    "addr:full":"6109 N Royal Dr Spokane WA 99208",
    "addr:housenumber":"6109",
    "addr:postcode":"99208",
    "addr:street":"N Royal Dr",
    "iso:country":"US",
    "sg:address":"6109 N Royal Dr",
    "sg:city":"Spokane",
    "sg:classifiers":[
        {
            "category":"Building & Trades",
            "subcategory":"Landscaping Services",
            "type":"Services"
        }
    ],
    "sg:phone":"+1 509 326 9312",
    "sg:postcode":"99208",
    "sg:province":"WA",
    "wof:name":"Westgate Lawn & Yard Serv",
    "wof:placetype":"venue"
},
  "geometry": {"coordinates":[-117.482662,47.713285],"type":"Point"}
}