{
  "type": "Feature",
  "properties": {
    "iso:country":"US",
    "sg:address":"1512 Thornton Ave SW",
    "sg:city":"Puyallup",
    "sg:classifiers":[
        {
            "category":"Retail",
            "subcategory":"Auto Repair",
            "type":"Services"
        }
    ],
    "sg:phone":"+1 253 845 3320",
    "sg:postcode":"98390",
    "sg:province":"WA",
    "sg:tags":[
        "general"
    ],
    "wof:name":"Luis Truck Repair",
    "wof:placetype":"venue"
},
  "geometry": {"coordinates":[-122.253227,47.243327],"type":"Point"}
}