{
  "type": "Feature",
  "properties": {
    "iso:country":"US",
    "sg:address":"111 N Locust Rd",
    "sg:city":"Spokane Valley",
    "sg:classifiers":[
        {
            "category":"Real Estate",
            "subcategory":"Real Estate Operator",
            "type":"Services"
        }
    ],
    "sg:phone":"+1 509 891 5650",
    "sg:postcode":"99206",
    "sg:province":"WA",
    "sg:tags":[
        "building",
        "apartment"
    ],
    "wof:name":"Beringer Place Apartments",
    "wof:placetype":"venue"
},
  "geometry": {"coordinates":[-117.277542,47.657854],"type":"Point"}
}