{
  "type": "Feature",
  "properties": {
    "addr:full":"4517 Pennsylvania Pl Longview WA 98632",
    "addr:housenumber":"4517",
    "addr:postcode":"98632",
    "addr:street":"Pennsylvania Pl",
    "iso:country":"US",
    "sg:address":"4517 Pennsylvania Pl",
    "sg:city":"Longview",
    "sg:classifiers":[
        {
            "category":"Home & Garden",
            "subcategory":"Hardware",
            "type":"Retail Goods"
        },
        {
            "category":"Professional",
            "subcategory":"Business Services",
            "type":"Services"
        }
    ],
    "sg:phone":"+1 360 270 0881",
    "sg:postcode":"98632",
    "sg:province":"WA",
    "sg:tags":[
        "auctioneer"
    ],
    "wof:name":"Vic's Marketplace",
    "wof:placetype":"venue"
},
  "geometry": {"coordinates":[-122.993711,46.17656],"type":"Point"}
}