{
  "type": "Feature",
  "properties": {
    "addr:full":"459 15th Ave Kirkland WA 98033",
    "addr:housenumber":"459",
    "addr:postcode":"98033",
    "addr:street":"15Th Ave",
    "iso:country":"US",
    "sg:address":"459 15th Ave",
    "sg:city":"Kirkland",
    "sg:classifiers":[
        {
            "category":"Building & Trades",
            "subcategory":"Construction",
            "type":"Services"
        }
    ],
    "sg:phone":"+1 425 822 7997",
    "sg:postcode":"98033",
    "sg:province":"WA",
    "sg:tags":[
        "water",
        "contractor",
        "main",
        "road",
        "sewer"
    ],
    "wof:name":"Slick & Sons Bulldozing",
    "wof:placetype":"venue"
},
  "geometry": {"coordinates":[-122.20077000000001,47.687298],"type":"Point"}
}