{
  "type": "Feature",
  "properties": {
    "addr:full":"22007 NE 12th Pl Sammamish WA 98074",
    "addr:housenumber":"22007",
    "addr:postcode":"98074",
    "addr:street":"Ne 12Th Pl",
    "iso:country":"US",
    "sg:address":"22007 NE 12th Pl",
    "sg:city":"Sammamish",
    "sg:classifiers":[
        {
            "category":"Professional",
            "subcategory":"Lawyer & Legal Services",
            "type":"Services"
        }
    ],
    "sg:phone":"+1 425 802 7703",
    "sg:postcode":"98074",
    "sg:province":"WA",
    "sg:tags":[
        "plan"
    ],
    "wof:name":"The Law Office Of Dawn M Bettinger",
    "wof:placetype":"venue"
},
  "geometry": {"coordinates":[-122.045647,47.621478],"type":"Point"}
}