{
  "type": "Feature",
  "properties": {
    "addr:full":"311 B Occidental Avenue S. Ste. 200 Seattle WA 98104",
    "addr:housenumber":"311 b",
    "addr:postcode":"98104",
    "addr:street":"Occidental Avenue S. Ste. 200",
    "iso:country":"US",
    "sg:address":"311 B Occidental Avenue S. Ste. 200",
    "sg:city":"Seattle",
    "sg:classifiers":[
        {
            "category":"Professional",
            "type":"Services"
        },
        {
            "category":"Communications",
            "type":"Services"
        }
    ],
    "sg:phone":"+1 206 453 1120",
    "sg:postcode":"98104",
    "sg:province":"WA",
    "sg:tags":[
        "medium",
        "mass"
    ],
    "sg:website":"www.SpringCreekGroup.com",
    "wof:name":"Spring Creek Group",
    "wof:placetype":"venue"
},
  "geometry": {"coordinates":[-122.333443,47.529808],"type":"Point"}
}