{
  "type": "Feature",
  "properties": {
    "addr:full":"2401 E Union St Seattle WA 98122",
    "addr:housenumber":"2401",
    "addr:postcode":"98122",
    "addr:street":"E Union St",
    "iso:country":"US",
    "sg:address":"2401 E Union St",
    "sg:city":"Seattle",
    "sg:classifiers":[
        {
            "category":"Coffee & Tea",
            "type":"Food & Drink"
        },
        {
            "category":"Restaurant",
            "type":"Food & Drink"
        }
    ],
    "sg:phone":"+1 206 328 7068",
    "sg:postcode":"98122",
    "sg:province":"WA",
    "wof:name":"Fatima Cafe",
    "wof:placetype":"venue"
},
  "geometry": {"coordinates":[-122.301383,47.612936],"type":"Point"}
}