{
  "type": "Feature",
  "properties": {
    "iso:country":"US",
    "sg:address":"3609 W Vel View Dr",
    "sg:city":"Spokane",
    "sg:classifiers":[
        {
            "category":"Utilities",
            "subcategory":"Water",
            "type":"Services"
        }
    ],
    "sg:phone":"+1 509 466 4322",
    "sg:postcode":"99208",
    "sg:province":"WA",
    "sg:tags":[
        "supply"
    ],
    "wof:name":"Vel View Water Dist 13",
    "wof:placetype":"venue"
},
  "geometry": {"coordinates":[-117.461827,47.753295],"type":"Point"}
}