{
  "type": "Feature",
  "properties": {
    "addr:full":"1022 NE 92nd St Seattle WA 98115",
    "addr:housenumber":"1022",
    "addr:postcode":"98115",
    "addr:street":"Ne 92Nd St",
    "iso:country":"US",
    "sg:address":"1022 NE 92nd St",
    "sg:city":"Seattle",
    "sg:classifiers":[
        {
            "category":"Building & Trades",
            "subcategory":"Construction",
            "type":"Services"
        },
        {
            "category":"Manufacturing",
            "subcategory":"Building Materials",
            "type":"Manufacturing & Wholesale Goods"
        }
    ],
    "sg:phone":"+1 206 525 1727",
    "sg:postcode":"98115",
    "sg:province":"WA",
    "sg:tags":[
        "roofing",
        "industrial",
        "sheet",
        "work",
        "metal",
        "contractor",
        "siding",
        "contractors-commercial"
    ],
    "wof:name":"Youneeda Roofing Co",
    "wof:placetype":"venue"
},
  "geometry": {"coordinates":[-122.316998,47.69583],"type":"Point"}
}