{
  "type": "Feature",
  "properties": {
    "addr:full":"720 Olive Way #610 Seattle WA 98101",
    "addr:housenumber":"720",
    "addr:postcode":"98101",
    "addr:street":"Olive Way # 610",
    "iso:country":"US",
    "sg:address":"720 Olive Way #610",
    "sg:city":"Seattle",
    "sg:classifiers":[
        {
            "category":"Health Services",
            "subcategory":"Dentist",
            "type":"Services"
        }
    ],
    "sg:phone":"+1 206 625 9358",
    "sg:postcode":"98101",
    "sg:province":"WA",
    "sg:tags":[
        "dentists-cosmetic",
        "dental",
        "dentists-pediatric",
        "hygienist",
        "dentistry",
        "dentists-orthodontists"
    ],
    "sg:website":"http://www.perioinnovations.com",
    "wof:name":"Adrian P. Pawlowski, D.D.S. M.S.D.",
    "wof:placetype":"venue"
},
  "geometry": {"coordinates":[-122.334941,47.613675],"type":"Point"}
}