{
  "type": "Feature",
  "properties": {
    "addr:full":"2801 NE 101st Ct Vancouver WA 98662",
    "addr:housenumber":"2801",
    "addr:postcode":"98662",
    "addr:street":"Ne 101St Ct",
    "iso:country":"US",
    "sg:address":"2801 NE 101st Ct",
    "sg:city":"Vancouver",
    "sg:classifiers":[
        {
            "category":"Banks & Credit Unions",
            "subcategory":"Financial Services",
            "type":"Services"
        }
    ],
    "sg:phone":"+1 360 896 0885",
    "sg:postcode":"98662",
    "sg:province":"WA",
    "sg:tags":[
        "kitchen",
        "installation",
        "cabinet"
    ],
    "wof:name":"C R Enterprises",
    "wof:placetype":"venue"
},
  "geometry": {"coordinates":[-122.569237,45.643233],"type":"Point"}
}