{
  "type": "Feature",
  "properties": {
    "addr:full":"16409 Canyon Rd E Puyallup WA 98375",
    "addr:housenumber":"16409",
    "addr:postcode":"98375",
    "addr:street":"Canyon Rd E",
    "iso:country":"US",
    "sg:address":"16409 Canyon Rd E",
    "sg:city":"Puyallup",
    "sg:classifiers":[
        {
            "category":"Organizations",
            "subcategory":"Community Association",
            "type":"Services"
        },
        {
            "category":"Recreation",
            "type":"Entertainment"
        }
    ],
    "sg:phone":"+1 253 537 6151",
    "sg:postcode":"98375",
    "sg:province":"WA",
    "sg:tags":[
        "club",
        "membership",
        "sport",
        "center"
    ],
    "sg:website":"www.tacomasportsmensclub.com",
    "wof:name":"Tacoma Sportsmen's Club Inc",
    "wof:placetype":"venue"
},
  "geometry": {"coordinates":[-122.35758300000001,47.106496],"type":"Point"}
}