{
  "type": "Feature",
  "properties": {
    "iso:country":"US",
    "sg:address":"9531 Barnes Dr",
    "sg:city":"Castle Rock",
    "sg:classifiers":[
        {
            "category":"Professional",
            "subcategory":"Art Services",
            "type":"Services"
        }
    ],
    "sg:phone":"+1 360 431 8026",
    "sg:postcode":"98611",
    "sg:province":"WA",
    "sg:tags":[
        "commercial",
        "design"
    ],
    "wof:name":"Poouster Graphics",
    "wof:placetype":"venue"
},
  "geometry": {"coordinates":[-122.927306,46.340986],"type":"Point"}
}