{
  "type": "Feature",
  "properties": {
    "iso:country":"US",
    "sg:address":"6719 NE 219th St",
    "sg:city":"Battle Ground",
    "sg:classifiers":[
        {
            "category":"Shopping",
            "subcategory":"Bicycles & Sporting Goods",
            "type":"Retail Goods"
        }
    ],
    "sg:phone":"+1 360 687 3856",
    "sg:postcode":"98604",
    "sg:province":"WA",
    "sg:tags":[
        "mfg"
    ],
    "wof:name":"D & E Rods",
    "wof:placetype":"venue"
},
  "geometry": {"coordinates":[-122.604821,45.78],"type":"Point"}
}