{
  "type": "Feature",
  "properties": {
    "addr:full":"4318 Meridian Rd NE Lacey WA 98516",
    "addr:housenumber":"4318",
    "addr:postcode":"98516",
    "addr:street":"Meridian Rd Ne",
    "iso:country":"US",
    "sg:address":"4318 Meridian Rd NE",
    "sg:city":"Lacey",
    "sg:classifiers":[
        {
            "category":"Professional",
            "subcategory":"Accounting & Tax Preparation",
            "type":"Services"
        }
    ],
    "sg:phone":"+1 360 493 0780",
    "sg:postcode":"98516",
    "sg:province":"WA",
    "sg:tags":[
        "accountant",
        "return"
    ],
    "wof:name":"Lisa A Rivera CPA",
    "wof:placetype":"venue"
},
  "geometry": {"coordinates":[-122.738333,47.079863],"type":"Point"}
}