{
  "type": "Feature",
  "properties": {
    "iso:country":"US",
    "sg:address":"11315 157th Ave SE",
    "sg:city":"Snohomish",
    "sg:classifiers":[
        {
            "category":"Building & Trades",
            "subcategory":"Construction",
            "type":"Services"
        }
    ],
    "sg:phone":"+1 360 563 1180",
    "sg:postcode":"98290",
    "sg:province":"WA",
    "sg:tags":[
        "paving",
        "contractor"
    ],
    "wof:name":"Harms Paving Co",
    "wof:placetype":"venue"
},
  "geometry": {"coordinates":[-122.02089599999999,47.895112],"type":"Point"}
}