{
  "type": "Feature",
  "properties": {
    "addr:full":"18723 SE 384th St Auburn WA 98092",
    "addr:housenumber":"18723",
    "addr:postcode":"98092",
    "addr:street":"Se 384Th St",
    "iso:country":"US",
    "sg:address":"18723 SE 384th St",
    "sg:city":"Auburn",
    "sg:classifiers":[
        {
            "category":"Banks & Credit Unions",
            "subcategory":"Bank",
            "type":"Services"
        }
    ],
    "sg:phone":"+1 253 833 4944",
    "sg:postcode":"98092",
    "sg:province":"WA",
    "sg:tags":[
        "broker",
        "mortgage"
    ],
    "wof:name":"West Coast Mortgage Brokerage",
    "wof:placetype":"venue"
},
  "geometry": {"coordinates":[-122.095668,47.257211],"type":"Point"}
}