{
  "type": "Feature",
  "properties": {
    "addr:full":"3622 Oakes Ave Everett WA 98201",
    "addr:postcode":"3622;98201",
    "addr:street":"Oakes Ave",
    "iso:country":"US",
    "sg:address":"3622 Oakes Ave",
    "sg:city":"Everett",
    "sg:classifiers":[
        {
            "category":"Real Estate",
            "subcategory":"Real Estate Agent",
            "type":"Services"
        }
    ],
    "sg:phone":"+1 425 308 2808",
    "sg:postcode":"98201",
    "sg:province":"WA",
    "wof:name":"Michael Sorenson",
    "wof:placetype":"venue"
},
  "geometry": {"coordinates":[-122.204069,47.969003],"type":"Point"}
}