{
  "type": "Feature",
  "properties": {
    "iso:country":"US",
    "sg:address":"13600 NE 228th Ct",
    "sg:city":"Brush Prairie",
    "sg:classifiers":[
        {
            "category":"Farming",
            "subcategory":"Farm",
            "type":"Manufacturing & Wholesale Goods"
        }
    ],
    "sg:phone":"+1 360 254 4623",
    "sg:postcode":"98606",
    "sg:province":"WA",
    "sg:tags":[
        "crop",
        "general"
    ],
    "wof:name":"Sue Kaysinger",
    "wof:placetype":"venue"
},
  "geometry": {"coordinates":[-122.43690700000001,45.72079],"type":"Point"}
}