{
  "type": "Feature",
  "properties": {
    "addr:full":"1210 N 152nd St Shoreline WA 98133",
    "addr:housenumber":"1210",
    "addr:postcode":"98133",
    "addr:street":"N 152Nd St",
    "iso:country":"US",
    "sg:address":"1210 N 152nd St",
    "sg:city":"Shoreline",
    "sg:classifiers":[
        {
            "category":"Building & Trades",
            "subcategory":"Construction",
            "type":"Services"
        }
    ],
    "sg:phone":"+1 206 405 1620",
    "sg:postcode":"98133",
    "sg:province":"WA",
    "sg:tags":[
        "painter"
    ],
    "wof:name":"Advance Services",
    "wof:placetype":"venue"
},
  "geometry": {"coordinates":[-122.34352199999999,47.739028],"type":"Point"}
}