{
  "type": "Feature",
  "properties": {
    "addr:full":"9227 Killion Rd SE Yelm WA 98597",
    "addr:housenumber":"9227",
    "addr:postcode":"98597",
    "addr:street":"Killion Rd Se Yelm",
    "iso:country":"US",
    "sg:address":"9227 Killion Rd SE",
    "sg:city":"Yelm",
    "sg:classifiers":[
        {
            "category":"Building & Trades",
            "subcategory":"Plumbing",
            "type":"Services"
        }
    ],
    "sg:phone":"+1 360 458 6607",
    "sg:postcode":"98597",
    "sg:province":"WA",
    "sg:tags":[
        "plumbing",
        "contractor"
    ],
    "wof:name":"Out-House Plumbing",
    "wof:placetype":"venue"
},
  "geometry": {"coordinates":[-122.61697700000001,46.957025],"type":"Point"}
}