{
  "type": "Feature",
  "properties": {
    "addr:full":"1724 E Washington Ave Union Gap WA 98903",
    "addr:housenumber":"1724",
    "addr:postcode":"98903",
    "addr:street":"E Washington Ave",
    "iso:country":"US",
    "sg:address":"1724 E Washington Ave",
    "sg:city":"Union Gap",
    "sg:classifiers":[
        {
            "category":"Shopping",
            "subcategory":"Shoes",
            "type":"Retail Goods"
        }
    ],
    "sg:phone":"+1 509 469 9676",
    "sg:postcode":"98903",
    "sg:province":"WA",
    "sg:website":"www.famousfootwear.com",
    "wof:name":"Famous Footwear",
    "wof:placetype":"venue"
},
  "geometry": {"coordinates":[-120.481673,46.570468],"type":"Point"}
}