{
  "type": "Feature",
  "properties": {
    "addr:full":"117 A St SE Auburn WA 98002",
    "addr:housenumber":"117",
    "addr:postcode":"98002",
    "addr:street":"A St Se",
    "iso:country":"US",
    "sg:address":"117 A St SE",
    "sg:city":"Auburn",
    "sg:classifiers":[
        {
            "category":"Professional",
            "subcategory":"Management & Consulting",
            "type":"Services"
        }
    ],
    "sg:phone":"+1 253 939 9194",
    "sg:postcode":"98002",
    "sg:province":"WA",
    "wof:name":"First Northwest Estate Plg",
    "wof:placetype":"venue"
},
  "geometry": {"coordinates":[-122.22866500000001,47.305787],"type":"Point"}
}