{
  "type": "Feature",
  "properties": {
    "addr:full":"5819 136th St SE Everett WA 98208",
    "addr:housenumber":"5819",
    "addr:postcode":"98208",
    "addr:street":"136Th St Se",
    "iso:country":"US",
    "sg:address":"5819 136th St SE",
    "sg:city":"Everett",
    "sg:classifiers":[
        {
            "category":"Building & Trades",
            "subcategory":"Cleaning & Sanitation",
            "type":"Services"
        }
    ],
    "sg:phone":"+1 425 357 8693",
    "sg:postcode":"98208",
    "sg:province":"WA",
    "sg:tags":[
        "maintenance"
    ],
    "wof:name":"Anna S Dabkowska",
    "wof:placetype":"venue"
},
  "geometry": {"coordinates":[-122.154875,47.874746],"type":"Point"}
}