{
  "type": "Feature",
  "properties": {
    "addr:full":"181 Howards Ln Underwood WA 98651",
    "addr:housenumber":"181",
    "addr:postcode":"98651",
    "addr:street":"Howards Ln",
    "iso:country":"US",
    "sg:address":"181 Howards Ln",
    "sg:city":"Underwood",
    "sg:classifiers":[
        {
            "category":"Wholesale",
            "subcategory":"Auto Parts",
            "type":"Manufacturing & Wholesale Goods"
        }
    ],
    "sg:phone":"+1 509 493 2814",
    "sg:postcode":"98651",
    "sg:province":"WA",
    "sg:tags":[
        "automobile",
        "wrecking"
    ],
    "wof:name":"Howard's Wrecking Yard",
    "wof:placetype":"venue"
},
  "geometry": {"coordinates":[-121.54781800000001,45.756923],"type":"Point"}
}