{
  "type": "Feature",
  "properties": {
    "addr:full":"1422 Queen Anne Ave North Seattle WA 98119",
    "addr:housenumber":"1422",
    "addr:postcode":"98119",
    "addr:street":"Queen Anne Ave North",
    "iso:country":"US",
    "sg:address":"1422 Queen Anne Ave North",
    "sg:city":"Seattle",
    "sg:classifiers":[
        {
            "category":"Home & Garden",
            "subcategory":"Garden Supply",
            "type":"Retail Goods"
        }
    ],
    "sg:phone":"+1 206 274 5987",
    "sg:postcode":"98119",
    "sg:province":"WA",
    "sg:website":"www.kathleenmullaney.com",
    "wof:name":"Kathleen Mullaney",
    "wof:placetype":"venue"
},
  "geometry": {"coordinates":[-122.356585,47.631553],"type":"Point"}
}