{
  "type": "Feature",
  "properties": {
    "addr:full":"500 E 13th St Ofc Vancouver WA 98660",
    "addr:housenumber":"500",
    "addr:postcode":"98660",
    "addr:street":"E 13Th St",
    "iso:country":"US",
    "sg:address":"500 E 13th St Ofc",
    "sg:city":"Vancouver",
    "sg:classifiers":[
        {
            "category":"Real Estate",
            "subcategory":"Real Estate Operator",
            "type":"Services"
        }
    ],
    "sg:phone":"+1 360 694 3327",
    "sg:postcode":"98660",
    "sg:province":"WA",
    "sg:tags":[
        "apartment"
    ],
    "wof:name":"Fort Apartments",
    "wof:placetype":"venue"
},
  "geometry": {"coordinates":[-122.667,45.6311],"type":"Point"}
}