{
  "type": "Feature",
  "properties": {
    "iso:country":"US",
    "sg:address":"19200 44th Ave W",
    "sg:city":"Lynnwood",
    "sg:classifiers":[
        {
            "category":"Education",
            "subcategory":"Library",
            "type":"Public Place"
        }
    ],
    "sg:phone":"+1 425 778 2148",
    "sg:postcode":"98036",
    "sg:province":"WA",
    "sg:tags":[
        "executive"
    ],
    "wof:name":"Lynnwood Library",
    "wof:placetype":"venue"
},
  "geometry": {"coordinates":[-122.2924,47.822815],"type":"Point"}
}