{
  "type": "Feature",
  "properties": {
    "addr:full":"6300 9th Ave NE., Ste 300 Seattle WA 98115",
    "addr:housenumber":"6300",
    "addr:postcode":"98115",
    "addr:street":"9Th Ave Ne. Ste 300",
    "iso:country":"US",
    "sg:address":"6300 9th Ave NE., Ste 300",
    "sg:city":"Seattle",
    "sg:classifiers":[
        {
            "category":"Health Services",
            "subcategory":"Chiropractor",
            "type":"Services"
        }
    ],
    "sg:phone":"+1 206 363 5555",
    "sg:postcode":"98115",
    "sg:province":"WA",
    "sg:website":"www.oneskywellness.com",
    "wof:name":"Dr. Dan Buquicchio",
    "wof:placetype":"venue"
},
  "geometry": {"coordinates":[-122.318718,47.674259],"type":"Point"}
}