{
  "type": "Feature",
  "properties": {
    "iso:country":"US",
    "sg:address":"606 Lilly Rd NE",
    "sg:city":"Olympia",
    "sg:classifiers":[
        {
            "category":"Real Estate",
            "subcategory":"Real Estate Operator",
            "type":"Services"
        }
    ],
    "sg:phone":"+1 360 459 9686",
    "sg:postcode":"98506",
    "sg:province":"WA",
    "sg:tags":[
        "building",
        "apartment"
    ],
    "wof:name":"Arbor Square Apartments",
    "wof:placetype":"venue"
},
  "geometry": {"coordinates":[-122.84433300000001,47.055022],"type":"Point"}
}