{
  "type": "Feature",
  "properties": {
    "addr:full":"24307 E Kildea Ave Otis Orchards WA 99027",
    "addr:housenumber":"24307",
    "addr:postcode":"99027",
    "addr:street":"E Kildea Ave",
    "iso:country":"US",
    "sg:address":"24307 E Kildea Ave",
    "sg:city":"Otis Orchards",
    "sg:classifiers":[
        {
            "category":"Retail",
            "subcategory":"Auto Repair",
            "type":"Services"
        }
    ],
    "sg:phone":"+1 509 226 2670",
    "sg:postcode":"99027",
    "sg:province":"WA",
    "sg:tags":[
        "repairing",
        "automobile"
    ],
    "wof:name":"East Valley Auto Electric Inc",
    "wof:placetype":"venue"
},
  "geometry": {"coordinates":[-117.077012,47.700898],"type":"Point"}
}