{
  "type": "Feature",
  "properties": {
    "addr:full":"901 Shaw Rd Puyallup WA 98372",
    "addr:housenumber":"901",
    "addr:postcode":"98372",
    "addr:street":"Shaw Rd",
    "iso:country":"US",
    "sg:address":"901 Shaw Rd",
    "sg:city":"Puyallup",
    "sg:classifiers":[
        {
            "category":"Building & Trades",
            "subcategory":"Construction",
            "type":"Services"
        }
    ],
    "sg:phone":"+1 253 863 1171",
    "sg:postcode":"98372",
    "sg:province":"WA",
    "sg:tags":[
        "welder"
    ],
    "sg:website":"http://www.sanweld.com",
    "wof:name":"Sandvik Custom Welding & Fabrication",
    "wof:placetype":"venue"
},
  "geometry": {"coordinates":[-122.256197,47.183912],"type":"Point"}
}