{
  "type": "Feature",
  "properties": {
    "iso:country":"US",
    "sg:address":"16307 NE 83rd St",
    "sg:city":"Redmond",
    "sg:classifiers":[
        {
            "category":"Professional",
            "subcategory":"Engineering",
            "type":"Services"
        }
    ],
    "sg:phone":"+1 425 881 3635",
    "sg:postcode":"98052",
    "sg:province":"WA",
    "sg:tags":[
        "engineer"
    ],
    "wof:name":"GHKN Engineering LLC",
    "wof:placetype":"venue"
},
  "geometry": {"coordinates":[-122.12261700000001,47.676605],"type":"Point"}
}