{
  "type": "Feature",
  "properties": {
    "addr:full":"4024 E Wellesley Ave Spokane WA 99217",
    "addr:housenumber":"4024",
    "addr:postcode":"99217",
    "addr:street":"E Wellesley Ave",
    "iso:country":"US",
    "sg:address":"4024 E Wellesley Ave",
    "sg:city":"Spokane",
    "sg:classifiers":[
        {
            "category":"Home & Garden",
            "subcategory":"Building Materials",
            "type":"Retail Goods"
        },
        {
            "category":"Building & Trades",
            "subcategory":"Construction",
            "type":"Services"
        }
    ],
    "sg:phone":"+1 509 315 3865",
    "sg:postcode":"99217",
    "sg:province":"WA",
    "sg:tags":[
        "concrete",
        "industrial",
        "demolition",
        "contractors-commercial",
        "contractor"
    ],
    "wof:name":"Spokane Concrete Cutting Inc",
    "wof:placetype":"venue"
},
  "geometry": {"coordinates":[-117.35166099999999,47.700449],"type":"Point"}
}