{
  "type": "Feature",
  "properties": {
    "addr:full":"4309 52nd Ave NE Seattle WA 98105",
    "addr:housenumber":"4309",
    "addr:postcode":"98105",
    "addr:street":"52Nd Ave Ne",
    "iso:country":"US",
    "sg:address":"4309 52nd Ave NE",
    "sg:city":"Seattle",
    "sg:classifiers":[
        {
            "category":"Health Services",
            "subcategory":"Dentist",
            "type":"Services"
        }
    ],
    "sg:phone":"+1 206 523 7328",
    "sg:postcode":"98105",
    "sg:province":"WA",
    "wof:name":"Knutzen George P DDS",
    "wof:placetype":"venue"
},
  "geometry": {"coordinates":[-122.271923,47.659369],"type":"Point"}
}