{
  "type": "Feature",
  "properties": {
    "addr:full":"11312 NE 23rd St Vancouver WA 98684",
    "addr:housenumber":"11312",
    "addr:postcode":"98684",
    "addr:street":"Ne 23Rd St",
    "iso:country":"US",
    "sg:address":"11312 NE 23rd St",
    "sg:city":"Vancouver",
    "sg:classifiers":[
        {
            "category":"Home & Garden",
            "subcategory":"Household Appliances",
            "type":"Retail Goods"
        },
        {
            "category":"Retail",
            "subcategory":"Repair Shop",
            "type":"Services"
        }
    ],
    "sg:phone":"+1 360 892 2304",
    "sg:postcode":"98684",
    "sg:province":"WA",
    "sg:tags":[
        "machine",
        "small",
        "major",
        "dishwashing",
        "refinishing"
    ],
    "wof:name":"Needle-Tek",
    "wof:placetype":"venue"
},
  "geometry": {"coordinates":[-122.55688600000001,45.639211],"type":"Point"}
}