{
  "type": "Feature",
  "properties": {
    "addr:full":"2817 Wheaton Way Bremerton WA 98310",
    "addr:housenumber":"2817",
    "addr:postcode":"98310",
    "addr:street":"Wheaton Way",
    "iso:country":"US",
    "sg:address":"2817 Wheaton Way",
    "sg:city":"Bremerton",
    "sg:classifiers":[
        {
            "category":"Health Services",
            "subcategory":"Clinic",
            "type":"Services"
        },
        {
            "category":"Social Services",
            "type":"Services"
        }
    ],
    "sg:phone":"+1 360 373 6827",
    "sg:postcode":"98310",
    "sg:province":"WA",
    "sg:tags":[
        "information",
        "center",
        "family",
        "outpatient",
        "specialty",
        "planning"
    ],
    "wof:name":"Planned Parenthood",
    "wof:placetype":"venue"
},
  "geometry": {"coordinates":[-122.62799,47.587122],"type":"Point"}
}