{
  "type": "Feature",
  "properties": {
    "addr:full":"7844 SE 71st St Mercer Island WA 98040",
    "addr:housenumber":"7844",
    "addr:postcode":"98040",
    "addr:street":"Se 71St St",
    "iso:country":"US",
    "sg:address":"7844 SE 71st St",
    "sg:city":"Mercer Island",
    "sg:classifiers":[
        {
            "category":"Education",
            "subcategory":"Preschool",
            "type":"Public Place"
        },
        {
            "category":"Education",
            "subcategory":"School",
            "type":"Public Place"
        }
    ],
    "sg:phone":"+1 206 275 1738",
    "sg:postcode":"98040",
    "sg:province":"WA",
    "sg:tags":[
        "elementary"
    ],
    "sg:website":"www.mercerislandmontessori.com",
    "wof:name":"Mercer Island Montessori",
    "wof:placetype":"venue"
},
  "geometry": {"coordinates":[-122.233102,47.539584],"type":"Point"}
}