{
  "type": "Feature",
  "properties": {
    "iso:country":"US",
    "sg:address":"1901 S Union Ave",
    "sg:city":"Tacoma",
    "sg:classifiers":[
        {
            "category":"Real Estate",
            "subcategory":"Real Estate Operator",
            "type":"Services"
        }
    ],
    "sg:phone":"+1 253 383 2201",
    "sg:postcode":"98405",
    "sg:province":"WA",
    "sg:tags":[
        "building",
        "medical"
    ],
    "wof:name":"Allenmore Medical Center",
    "wof:placetype":"venue"
},
  "geometry": {"coordinates":[-122.48194599999999,47.239125],"type":"Point"}
}