{
  "type": "Feature",
  "properties": {
    "addr:full":"26015 104th Ave SE Kent WA 98030",
    "addr:housenumber":"26015",
    "addr:postcode":"98030",
    "addr:street":"104Th Ave Se",
    "iso:country":"US",
    "sg:address":"26015 104th Ave SE",
    "sg:city":"Kent",
    "sg:classifiers":[
        {
            "category":"Food & Beverages",
            "subcategory":"Groceries & Convenience Stores",
            "type":"Retail Goods"
        },
        {
            "category":"Bakery",
            "type":"Food & Drink"
        },
        {
            "category":"Shopping",
            "subcategory":"Pharmacy",
            "type":"Retail Goods"
        },
        {
            "category":"Shopping",
            "subcategory":"Florist",
            "type":"Retail Goods"
        }
    ],
    "sg:phone":"+1 206 439 5700",
    "sg:postcode":"98030",
    "sg:province":"WA",
    "sg:tags":[
        "cake",
        "pastry",
        "wedding"
    ],
    "sg:website":"http://www.top-foods.com",
    "wof:name":"Top Food & Drug",
    "wof:placetype":"venue"
},
  "geometry": {"coordinates":[-122.20230599999999,47.368791],"type":"Point"}
}