{
  "type": "Feature",
  "properties": {
    "addr:full":"653 NW 87th St Seattle WA 98117",
    "addr:housenumber":"653",
    "addr:postcode":"98117",
    "addr:street":"Nw 87Th St",
    "iso:country":"US",
    "sg:address":"653 NW 87th St",
    "sg:city":"Seattle",
    "sg:classifiers":[
        {
            "category":"Autos & Motor Vehicles",
            "subcategory":"Automobile Sales",
            "type":"Retail Goods"
        }
    ],
    "sg:phone":"+1 206 243 6001",
    "sg:postcode":"98117",
    "sg:province":"WA",
    "sg:tags":[
        "car",
        "dealer"
    ],
    "wof:name":"All Star Autos Inc",
    "wof:placetype":"venue"
},
  "geometry": {"coordinates":[-122.365531,47.692],"type":"Point"}
}