{
  "type": "Feature",
  "properties": {
    "addr:full":"5830 S Mullen St Tacoma WA 98409",
    "addr:housenumber":"5830",
    "addr:postcode":"98409",
    "addr:street":"S Mullen St",
    "iso:country":"US",
    "sg:address":"5830 S Mullen St",
    "sg:city":"Tacoma",
    "sg:classifiers":[
        {
            "category":"Professional",
            "type":"Services"
        }
    ],
    "sg:phone":"+1 253 475 5419",
    "sg:postcode":"98409",
    "sg:province":"WA",
    "wof:name":"Bawlamer Services",
    "wof:placetype":"venue"
},
  "geometry": {"coordinates":[-122.500895,47.202847],"type":"Point"}
}