{
  "type": "Feature",
  "properties": {
    "addr:full":"2902 Broadway Everett WA 98201",
    "addr:housenumber":"2902",
    "addr:postcode":"98201",
    "addr:street":"Broadway",
    "iso:country":"US",
    "sg:address":"2902 Broadway",
    "sg:city":"Everett",
    "sg:classifiers":[
        {
            "category":"Real Estate",
            "subcategory":"Real Estate Agent",
            "type":"Services"
        }
    ],
    "sg:phone":"+1 425 388 8200",
    "sg:postcode":"98201",
    "sg:province":"WA",
    "wof:name":"Prudential Preferred",
    "wof:placetype":"venue"
},
  "geometry": {"coordinates":[-122.201623,47.978794],"type":"Point"}
}