{
  "type": "Feature",
  "properties": {
    "addr:full":"23638 Coburg Pl NW Poulsbo WA 98370",
    "addr:postcode":"23638;98370",
    "addr:street":"Pl Nw",
    "iso:country":"US",
    "sg:address":"23638 Coburg Pl NW",
    "sg:city":"Poulsbo",
    "sg:classifiers":[
        {
            "category":"Professional",
            "type":"Services"
        }
    ],
    "sg:phone":"+1 360 598 3920",
    "sg:postcode":"98370",
    "sg:province":"WA",
    "wof:name":"Cooper Df Inc",
    "wof:placetype":"venue"
},
  "geometry": {"coordinates":[-122.661107,47.779765],"type":"Point"}
}