{
  "type": "Feature",
  "properties": {
    "addr:full":"507 B St South Bend WA 98586",
    "addr:housenumber":"507",
    "addr:postcode":"98586",
    "addr:street":"B St",
    "iso:country":"US",
    "sg:address":"507 B St",
    "sg:city":"South Bend",
    "sg:classifiers":[
        {
            "category":"Recreation",
            "subcategory":"Arcade",
            "type":"Entertainment"
        }
    ],
    "sg:phone":"+1 360 875 6370",
    "sg:postcode":"98586",
    "sg:province":"WA",
    "sg:tags":[
        "amusement",
        "devices"
    ],
    "wof:name":"Coastal Amusement Express",
    "wof:placetype":"venue"
},
  "geometry": {"coordinates":[-123.819807,46.668262],"type":"Point"}
}