{
  "type": "Feature",
  "properties": {
    "addr:full":"10172 Main St Peshastin WA 98847",
    "addr:housenumber":"10172",
    "addr:postcode":"98847",
    "addr:street":"Main St",
    "iso:country":"US",
    "sg:address":"10172 Main St",
    "sg:city":"Peshastin",
    "sg:classifiers":[
        {
            "category":"Personal",
            "subcategory":"Beauty Salon",
            "type":"Services"
        }
    ],
    "sg:phone":"+1 509 548 3075",
    "sg:postcode":"98847",
    "sg:province":"WA",
    "wof:name":"The Steel Magnolia",
    "wof:placetype":"venue"
},
  "geometry": {"coordinates":[-120.60601800000001,47.573448],"type":"Point"}
}