{
  "type": "Feature",
  "properties": {
    "addr:full":"157 Bowen Rd Mossyrock WA 98564",
    "addr:housenumber":"157",
    "addr:postcode":"98564",
    "addr:street":"Bowen Rd",
    "iso:country":"US",
    "sg:address":"157 Bowen Rd",
    "sg:city":"Mossyrock",
    "sg:classifiers":[
        {
            "category":"Professional",
            "type":"Services"
        }
    ],
    "sg:phone":"+1 360 983 3557",
    "sg:postcode":"98564",
    "sg:province":"WA",
    "wof:name":"Master Blaster",
    "wof:placetype":"venue"
},
  "geometry": {"coordinates":[-122.492707,46.517996],"type":"Point"}
}