{
  "type": "Feature",
  "properties": {
    "addr:full":"28855 Military Rd S Federal Way WA 98003",
    "addr:housenumber":"28855",
    "addr:postcode":"98003",
    "addr:street":"Military Rd S",
    "iso:country":"US",
    "sg:address":"28855 Military Rd S",
    "sg:city":"Federal Way",
    "sg:classifiers":[
        {
            "category":"Food & Beverages",
            "subcategory":"Groceries & Convenience Stores",
            "type":"Retail Goods"
        }
    ],
    "sg:phone":"+1 253 529 5894",
    "sg:postcode":"98003",
    "sg:province":"WA",
    "wof:name":"Ob Foods",
    "wof:placetype":"venue"
},
  "geometry": {"coordinates":[-122.301211,47.342761],"type":"Point"}
}