{
  "type": "Feature",
  "properties": {
    "iso:country":"US",
    "sg:address":"238 E Main St",
    "sg:city":"Dayton",
    "sg:classifiers":[
        {
            "category":"Banks & Credit Unions",
            "subcategory":"Financial Services",
            "type":"Services"
        }
    ],
    "sg:phone":"+1 509 382 2943",
    "sg:postcode":"99328",
    "sg:province":"WA",
    "sg:tags":[
        "trust",
        "management"
    ],
    "wof:name":"Project Timothy",
    "wof:placetype":"venue"
},
  "geometry": {"coordinates":[-117.979556,46.320047],"type":"Point"}
}