{
  "type": "Feature",
  "properties": {
    "addr:full":"202 S 62nd Ave Yakima WA 98908",
    "addr:housenumber":"202",
    "addr:postcode":"98908",
    "addr:street":"S 62Nd Ave",
    "iso:country":"US",
    "sg:address":"202 S 62nd Ave",
    "sg:city":"Yakima",
    "sg:classifiers":[
        {
            "category":"Restaurant",
            "type":"Food & Drink"
        }
    ],
    "sg:phone":"+1 509 966 7906",
    "sg:postcode":"98908",
    "sg:province":"WA",
    "sg:tags":[
        "eating"
    ],
    "wof:name":"Kuntz Irrigation",
    "wof:placetype":"venue"
},
  "geometry": {"coordinates":[-120.591247,46.594667],"type":"Point"}
}