{
  "type": "Feature",
  "properties": {
    "addr:full":"701 24th St SE Auburn WA 98002",
    "addr:housenumber":"701",
    "addr:postcode":"98002",
    "addr:street":"24Th St Se",
    "iso:country":"US",
    "sg:address":"701 24th St SE",
    "sg:city":"Auburn",
    "sg:classifiers":[
        {
            "category":"Building & Trades",
            "subcategory":"Construction",
            "type":"Services"
        }
    ],
    "sg:phone":"+1 253 939 2833",
    "sg:postcode":"98002",
    "sg:province":"WA",
    "sg:tags":[
        "house"
    ],
    "wof:name":"Clyde Construction",
    "wof:placetype":"venue"
},
  "geometry": {"coordinates":[-122.21996799999999,47.287228],"type":"Point"}
}