{
  "type": "Feature",
  "properties": {
    "addr:full":"700 Fairview Ave N Seattle WA 98109",
    "addr:housenumber":"700",
    "addr:postcode":"98109",
    "addr:street":"Fairview Ave N",
    "iso:country":"US",
    "sg:address":"700 Fairview Ave N",
    "sg:city":"Seattle",
    "sg:classifiers":[
        {
            "category":"Freight",
            "type":"Transportation"
        }
    ],
    "sg:phone":"+1 206 343 9181",
    "sg:postcode":"98109",
    "sg:province":"WA",
    "sg:tags":[
        "self",
        "storage",
        "rent",
        "unit"
    ],
    "wof:name":"Shurgard Storage Centers",
    "wof:placetype":"venue"
},
  "geometry": {"coordinates":[-122.334,47.626099],"type":"Point"}
}