{
  "type": "Feature",
  "properties": {
    "addr:full":"1411 Rush Rd Chehalis WA 98532",
    "addr:housenumber":"1411",
    "addr:postcode":"98532",
    "addr:street":"Rush Rd",
    "iso:country":"US",
    "sg:address":"1411 Rush Rd",
    "sg:city":"Chehalis",
    "sg:classifiers":[
        {
            "category":"Government",
            "subcategory":"Office",
            "type":"Public Place"
        }
    ],
    "sg:phone":"+1 360 748 2353",
    "sg:postcode":"98532",
    "sg:province":"WA",
    "sg:website":"www.wsdot.wa.gov",
    "wof:name":"Project Engineer",
    "wof:placetype":"venue"
},
  "geometry": {"coordinates":[-122.908253,46.611848],"type":"Point"}
}