{
  "type": "Feature",
  "properties": {
    "addr:full":"19920 SE 267th Pl Kent WA 98042",
    "addr:postcode":"19920;98042",
    "addr:street":"Se 267Th Pl",
    "iso:country":"US",
    "sg:address":"19920 SE 267th Pl",
    "sg:city":"Kent",
    "sg:classifiers":[
        {
            "category":"Banks & Credit Unions",
            "subcategory":"Bank",
            "type":"Services"
        }
    ],
    "sg:phone":"+1 206 412 0131",
    "sg:postcode":"98042",
    "sg:province":"WA",
    "sg:tags":[
        "mortgage"
    ],
    "wof:name":"Wendi Atencio",
    "wof:placetype":"venue"
},
  "geometry": {"coordinates":[-122.07439599999999,47.362096],"type":"Point"}
}