{
  "type": "Feature",
  "properties": {
    "addr:full":"520 Ferry St Sedro Woolley WA 98284",
    "addr:housenumber":"520",
    "addr:postcode":"98284",
    "addr:street":"Ferry St",
    "iso:country":"US",
    "sg:address":"520 Ferry St",
    "sg:city":"Sedro Woolley",
    "sg:classifiers":[
        {
            "category":"Professional",
            "subcategory":"Management & Consulting",
            "type":"Services"
        }
    ],
    "sg:phone":"+1 360 855 0315",
    "sg:postcode":"98284",
    "sg:province":"WA",
    "sg:tags":[
        "business"
    ],
    "wof:name":"Quiet Cove Consulting Services",
    "wof:placetype":"venue"
},
  "geometry": {"coordinates":[-122.233735,48.505406],"type":"Point"}
}