{
  "type": "Feature",
  "properties": {
    "addr:full":"28819 NE 112th Ave Battle Ground WA 98604",
    "addr:housenumber":"28819",
    "addr:postcode":"98604",
    "addr:street":"Ne 112Th Ave",
    "iso:country":"US",
    "sg:address":"28819 NE 112th Ave",
    "sg:city":"Battle Ground",
    "sg:classifiers":[
        {
            "category":"Shopping",
            "subcategory":"Discount & Variety Stores",
            "type":"Retail Goods"
        }
    ],
    "sg:phone":"+1 360 687 7781",
    "sg:postcode":"98604",
    "sg:province":"WA",
    "sg:tags":[
        "merchandise",
        "general"
    ],
    "wof:name":"Dollar Store The",
    "wof:placetype":"venue"
},
  "geometry": {"coordinates":[-122.5582,45.83328],"type":"Point"}
}