{
  "type": "Feature",
  "properties": {
    "addr:full":"215 E Main St Palouse WA 99161",
    "addr:housenumber":"215",
    "addr:postcode":"99161",
    "addr:street":"E Main St",
    "iso:country":"US",
    "sg:address":"215 E Main St",
    "sg:city":"Palouse",
    "sg:classifiers":[
        {
            "category":"Food & Beverages",
            "subcategory":"Groceries & Convenience Stores",
            "type":"Retail Goods"
        }
    ],
    "sg:phone":"+1 509 878 2012",
    "sg:postcode":"99161",
    "sg:province":"WA",
    "sg:tags":[
        "grocer"
    ],
    "wof:name":"Thurman's Palouse Market",
    "wof:placetype":"venue"
},
  "geometry": {"coordinates":[-117.07531,46.909742],"type":"Point"}
}