{
  "type": "Feature",
  "properties": {
    "addr:full":"397 S Bank Rd Elma WA 98541",
    "addr:housenumber":"397",
    "addr:postcode":"98541",
    "addr:street":"S Bank Rd",
    "iso:country":"US",
    "sg:address":"397 S Bank Rd",
    "sg:city":"Elma",
    "sg:classifiers":[
        {
            "category":"Wholesale",
            "subcategory":"Plants",
            "type":"Manufacturing & Wholesale Goods"
        }
    ],
    "sg:phone":"+1 360 482 6422",
    "sg:postcode":"98541",
    "sg:province":"WA",
    "sg:tags":[
        "supply"
    ],
    "wof:name":"Pacific Coast Evergreen",
    "wof:placetype":"venue"
},
  "geometry": {"coordinates":[-123.37123099999999,46.962835],"type":"Point"}
}