{
  "type": "Feature",
  "properties": {
    "addr:full":"3603 W Canal Dr Kennewick WA 99336",
    "addr:housenumber":"3603",
    "addr:postcode":"99336",
    "addr:street":"W Canal Dr",
    "iso:country":"US",
    "sg:address":"3603 W Canal Dr",
    "sg:city":"Kennewick",
    "sg:classifiers":[
        {
            "category":"Professional",
            "subcategory":"Computer Services",
            "type":"Services"
        }
    ],
    "sg:phone":"+1 509 521 1733",
    "sg:postcode":"99336",
    "sg:province":"WA",
    "wof:name":"All American Computer Repair",
    "wof:placetype":"venue"
},
  "geometry": {"coordinates":[-119.170086,46.220884],"type":"Point"}
}