{
  "type": "Feature",
  "properties": {
    "addr:full":"7504 35th Ave NE Seattle WA 98115",
    "addr:housenumber":"7504",
    "addr:postcode":"98115",
    "addr:street":"35Th Ave Ne",
    "iso:country":"US",
    "sg:address":"7504 35th Ave NE",
    "sg:city":"Seattle",
    "sg:classifiers":[
        {
            "category":"Education",
            "subcategory":"Preschool",
            "type":"Public Place"
        }
    ],
    "sg:phone":"+1 206 527 6902",
    "sg:postcode":"98115",
    "sg:province":"WA",
    "sg:website":"www.wedgwoodmorningpreschool.com",
    "wof:name":"Wedgwood Morning Preschool",
    "wof:placetype":"venue"
},
  "geometry": {"coordinates":[-122.29050100000001,47.684],"type":"Point"}
}