{
  "type": "Feature",
  "properties": {
    "addr:full":"519 E Woodin Ave Chelan WA 98816",
    "addr:housenumber":"519",
    "addr:postcode":"98816",
    "addr:street":"E Woodin Ave",
    "iso:country":"US",
    "sg:address":"519 E Woodin Ave",
    "sg:city":"Chelan",
    "sg:classifiers":[
        {
            "category":"Shopping",
            "subcategory":"Gifts & Souvenirs",
            "type":"Retail Goods"
        }
    ],
    "sg:phone":"+1 509 682 4103",
    "sg:postcode":"98816",
    "sg:province":"WA",
    "sg:tags":[
        "shop"
    ],
    "wof:name":"Hollyhocks & Poppycock",
    "wof:placetype":"venue"
},
  "geometry": {"coordinates":[-120.010497,47.839819],"type":"Point"}
}