{
  "type": "Feature",
  "properties": {
    "addr:full":"10915 157th Ct NE Redmond WA 98052",
    "addr:housenumber":"10915",
    "addr:postcode":"98052",
    "addr:street":"157Th Ct Ne",
    "iso:country":"US",
    "sg:address":"10915 157th Ct NE",
    "sg:city":"Redmond",
    "sg:classifiers":[
        {
            "category":"Retail",
            "subcategory":"Driving School",
            "type":"Services"
        }
    ],
    "sg:phone":"+1 425 885 5960",
    "sg:postcode":"98052",
    "sg:province":"WA",
    "sg:tags":[
        "proficiency",
        "test",
        "instruction",
        "traffic"
    ],
    "sg:website":"http://www.klhdrivingschool.com",
    "wof:name":"KLH Driving School",
    "wof:placetype":"venue"
},
  "geometry": {"coordinates":[-122.12957400000001,47.697457],"type":"Point"}
}