{
  "type": "Feature",
  "properties": {
    "addr:full":"1298 1st Ave S Okanogan WA 98840",
    "addr:housenumber":"1298",
    "addr:postcode":"98840",
    "addr:street":"1St Ave S Okanogan",
    "iso:country":"US",
    "sg:address":"1298 1st Ave S",
    "sg:city":"Okanogan",
    "sg:classifiers":[
        {
            "category":"Building & Trades",
            "subcategory":"Construction",
            "type":"Services"
        }
    ],
    "sg:phone":"+1 509 422 3198",
    "sg:postcode":"98840",
    "sg:province":"WA",
    "wof:name":"Wired Fencing",
    "wof:placetype":"venue"
},
  "geometry": {"coordinates":[-119.59432,48.354758],"type":"Point"}
}