{
  "type": "Feature",
  "properties": {
    "addr:full":"21436 Peter Grubb Rd SE Renton WA 98058",
    "addr:housenumber":"21436",
    "addr:postcode":"98058",
    "addr:street":"Peter Grubb Rd Se",
    "iso:country":"US",
    "sg:address":"21436 Peter Grubb Rd SE",
    "sg:city":"Renton",
    "sg:classifiers":[
        {
            "category":"Retail",
            "subcategory":"Repair Shop",
            "type":"Services"
        }
    ],
    "sg:phone":"+1 425 432 2827",
    "sg:postcode":"98058",
    "sg:province":"WA",
    "wof:name":"Midnight Sun Marine Services",
    "wof:placetype":"venue"
},
  "geometry": {"coordinates":[-122.10111499999999,47.409782],"type":"Point"}
}