{
  "type": "Feature",
  "properties": {
    "addr:full":"947 Powell Ave SW Ste 105 Renton WA 98057",
    "addr:housenumber":"947",
    "addr:postcode":"98057",
    "addr:street":"Powell Ave Sw Ste 105",
    "iso:country":"US",
    "sg:address":"947 Powell Ave SW Ste 105",
    "sg:city":"Renton",
    "sg:classifiers":[
        {
            "category":"Professional",
            "subcategory":"Lawyer & Legal Services",
            "type":"Services"
        }
    ],
    "sg:phone":"+1 425 227 4260",
    "sg:postcode":"98057",
    "sg:province":"WA",
    "sg:tags":[
        "personal",
        "injury"
    ],
    "wof:name":"Moen Leonard W & Associates",
    "wof:placetype":"venue"
},
  "geometry": {"coordinates":[-122.231459,47.470228],"type":"Point"}
}