{
  "type": "Feature",
  "properties": {
    "addr:full":"1520 NW 58th St Seattle WA 98107",
    "addr:housenumber":"1520",
    "addr:postcode":"98107",
    "addr:street":"Nw 58Th St",
    "iso:country":"US",
    "sg:address":"1520 NW 58th St",
    "sg:city":"Seattle",
    "sg:classifiers":[
        {
            "category":"Building & Trades",
            "subcategory":"Construction",
            "type":"Services"
        }
    ],
    "sg:phone":"+1 253 939 4007",
    "sg:postcode":"98107",
    "sg:province":"WA",
    "sg:tags":[
        "contractor"
    ],
    "wof:name":"Minhs Fence",
    "wof:placetype":"venue"
},
  "geometry": {"coordinates":[-122.378884,47.670902],"type":"Point"}
}