{
  "type": "Feature",
  "properties": {
    "addr:full":"1015 W Nickerson St Seattle WA 98119",
    "addr:housenumber":"1015",
    "addr:postcode":"98119",
    "addr:street":"W Nickerson St",
    "iso:country":"US",
    "sg:address":"1015 W Nickerson St",
    "sg:city":"Seattle",
    "sg:classifiers":[
        {
            "category":"Retail",
            "subcategory":"Auto Repair",
            "type":"Services"
        }
    ],
    "sg:phone":"+1 206 286 1227",
    "sg:postcode":"98119",
    "sg:province":"WA",
    "sg:tags":[
        "body"
    ],
    "wof:name":"Body Mind Beyond",
    "wof:placetype":"venue"
},
  "geometry": {"coordinates":[-122.371444,47.654534],"type":"Point"}
}