{
  "type": "Feature",
  "properties": {
    "iso:country":"US",
    "sg:address":"2524 S Hayford Rd",
    "sg:city":"Airway Heights",
    "sg:classifiers":[
        {
            "category":"Manufacturing",
            "subcategory":"Metals",
            "type":"Manufacturing & Wholesale Goods"
        }
    ],
    "sg:phone":"+1 509 244 2909",
    "sg:postcode":"99001",
    "sg:province":"WA",
    "sg:tags":[
        "steel"
    ],
    "sg:website":"www.metalsfab.com",
    "wof:name":"Metals Fabrication Co",
    "wof:placetype":"venue"
},
  "geometry": {"coordinates":[-117.560907,47.635612],"type":"Point"}
}