{
  "type": "Feature",
  "properties": {
    "addr:full":"2421 166th Pl SE Bothell WA 98012",
    "addr:housenumber":"2421",
    "addr:postcode":"98012",
    "addr:street":"166Th Pl Se",
    "iso:country":"US",
    "sg:address":"2421 166th Pl SE",
    "sg:city":"Bothell",
    "sg:classifiers":[
        {
            "category":"Retail",
            "subcategory":"Car Wash",
            "type":"Services"
        }
    ],
    "sg:phone":"+1 425 486 3459",
    "sg:postcode":"98012",
    "sg:province":"WA",
    "sg:tags":[
        "carwash"
    ],
    "wof:name":"Whites Mobile Detail Inc",
    "wof:placetype":"venue"
},
  "geometry": {"coordinates":[-122.198559,47.847248],"type":"Point"}
}