{
  "type": "Feature",
  "properties": {
    "addr:full":"13002 44th St NE Lake Stevens WA 98258",
    "addr:housenumber":"13002",
    "addr:postcode":"98258",
    "addr:street":"44Th St Ne",
    "iso:country":"US",
    "sg:address":"13002 44th St NE",
    "sg:city":"Lake Stevens",
    "sg:classifiers":[
        {
            "category":"Building & Trades",
            "subcategory":"Landscaping Services",
            "type":"Services"
        }
    ],
    "sg:phone":"+1 425 334 5790",
    "sg:postcode":"98258",
    "sg:province":"WA",
    "sg:tags":[
        "landscape",
        "contractor"
    ],
    "wof:name":"Wolfes Nursery and Landscape",
    "wof:placetype":"venue"
},
  "geometry": {"coordinates":[-122.055413,48.035956],"type":"Point"}
}