{
  "type": "Feature",
  "properties": {
    "addr:full":"10812 NE 26th St Vancouver WA 98684",
    "addr:housenumber":"10812",
    "addr:postcode":"98684",
    "addr:street":"Ne 26Th St",
    "iso:country":"US",
    "sg:address":"10812 NE 26th St",
    "sg:city":"Vancouver",
    "sg:classifiers":[
        {
            "category":"Professional",
            "subcategory":"Lawyer & Legal Services",
            "type":"Services"
        }
    ],
    "sg:phone":"+1 360 882 4809",
    "sg:postcode":"98684",
    "sg:province":"WA",
    "wof:name":"David W Gebbie",
    "wof:placetype":"venue"
},
  "geometry": {"coordinates":[-122.56097800000001,45.641281],"type":"Point"}
}