{
  "type": "Feature",
  "properties": {
    "iso:country":"US",
    "sg:address":"2050 Cloverdale Rd",
    "sg:city":"Kalama",
    "sg:classifiers":[
        {
            "category":"Manufacturing",
            "subcategory":"Food",
            "type":"Manufacturing & Wholesale Goods"
        }
    ],
    "sg:phone":"+1 360 673 3763",
    "sg:postcode":"98625",
    "sg:province":"WA",
    "sg:tags":[
        "smoking",
        "fish",
        "curing"
    ],
    "wof:name":"Green Mountain Smoked Salmon",
    "wof:placetype":"venue"
},
  "geometry": {"coordinates":[-122.800718,45.978426],"type":"Point"}
}