{
  "type": "Feature",
  "properties": {
    "addr:full":"9 Dunlap Rd Elma WA 98541",
    "addr:housenumber":"9",
    "addr:postcode":"98541",
    "addr:street":"Dunlap Rd",
    "iso:country":"US",
    "sg:address":"9 Dunlap Rd",
    "sg:city":"Elma",
    "sg:classifiers":[
        {
            "category":"Wholesale",
            "subcategory":"Chemicals & Plastics",
            "type":"Manufacturing & Wholesale Goods"
        }
    ],
    "sg:phone":"+1 360 482 4787",
    "sg:postcode":"98541",
    "sg:province":"WA",
    "sg:tags":[
        "product",
        "mfg"
    ],
    "wof:name":"Sunny Brook Gardens Ect",
    "wof:placetype":"venue"
},
  "geometry": {"coordinates":[-123.34773800000001,46.963724],"type":"Point"}
}