{
  "type": "Feature",
  "properties": {
    "addr:full":"3663 1st Ave S Seattle WA 98134",
    "addr:housenumber":"3663",
    "addr:postcode":"98134",
    "addr:street":"1St Ave S",
    "iso:country":"US",
    "sg:address":"3663 1st Ave S",
    "sg:city":"Seattle",
    "sg:classifiers":[
        {
            "category":"Food & Beverages",
            "subcategory":"Groceries & Convenience Stores",
            "type":"Retail Goods"
        }
    ],
    "sg:phone":"+1 206 622 9742",
    "sg:postcode":"98134",
    "sg:province":"WA",
    "wof:name":"Q F C",
    "wof:placetype":"venue"
},
  "geometry": {"coordinates":[-122.334283,47.569568],"type":"Point"}
}