{
  "type": "Feature",
  "properties": {
    "addr:full":"5010 W Clearwater Ave Kennewick WA 99336",
    "addr:housenumber":"5010",
    "addr:postcode":"99336",
    "addr:street":"W Clearwater Ave",
    "iso:country":"US",
    "sg:address":"5010 W Clearwater Ave",
    "sg:city":"Kennewick",
    "sg:classifiers":[
        {
            "category":"Freight",
            "type":"Transportation"
        }
    ],
    "sg:phone":"+1 509 783 9626",
    "sg:postcode":"99336",
    "sg:province":"WA",
    "sg:tags":[
        "marina",
        "good",
        "storage",
        "special",
        "op"
    ],
    "wof:name":"A Budget Mini Storage",
    "wof:placetype":"venue"
},
  "geometry": {"coordinates":[-119.18959099999999,46.212494],"type":"Point"}
}