{
  "type": "Feature",
  "properties": {
    "addr:full":"30 E Rainier Dr Allyn WA 98524",
    "addr:housenumber":"30",
    "addr:postcode":"98524",
    "addr:street":"E Rainier Dr",
    "iso:country":"US",
    "sg:address":"30 E Rainier Dr",
    "sg:city":"Allyn",
    "sg:classifiers":[
        {
            "category":"Manufacturing",
            "subcategory":"Buildings",
            "type":"Manufacturing & Wholesale Goods"
        },
        {
            "category":"Building & Trades",
            "subcategory":"Construction",
            "type":"Services"
        }
    ],
    "sg:phone":"+1 360 275 9679",
    "sg:postcode":"98524",
    "sg:province":"WA",
    "sg:tags":[
        "home",
        "builder",
        "contractor"
    ],
    "wof:name":"Brix Custom Homes",
    "wof:placetype":"venue"
},
  "geometry": {"coordinates":[-122.834782,47.386905],"type":"Point"}
}