{
  "type": "Feature",
  "properties": {
    "addr:full":"30002 N Newport Hwy Chattaroy WA 99003",
    "addr:housenumber":"30002",
    "addr:postcode":"99003",
    "addr:street":"N Newport Hwy Chattaroy",
    "iso:country":"US",
    "sg:address":"30002 N Newport Hwy",
    "sg:city":"Chattaroy",
    "sg:classifiers":[
        {
            "category":"Wholesale",
            "subcategory":"Painting Supplies",
            "type":"Manufacturing & Wholesale Goods"
        }
    ],
    "sg:phone":"+1 509 238 4176",
    "sg:postcode":"99003",
    "sg:province":"WA",
    "sg:tags":[
        "goods-wholesale",
        "art",
        "manufacturer"
    ],
    "wof:name":"Bear Country Carvings",
    "wof:placetype":"venue"
},
  "geometry": {"coordinates":[-117.351322,47.927487],"type":"Point"}
}