{
  "type": "Feature",
  "properties": {
    "addr:full":"915 15th Ave Seattle WA 98122",
    "addr:housenumber":"915",
    "addr:postcode":"98122",
    "addr:street":"15Th Ave",
    "iso:country":"US",
    "sg:address":"915 15th Ave",
    "sg:city":"Seattle",
    "sg:classifiers":[
        {
            "category":"Retail",
            "subcategory":"Portrait Studio",
            "type":"Services"
        }
    ],
    "sg:phone":"+1 206 322 9120",
    "sg:postcode":"98122",
    "sg:province":"WA",
    "sg:tags":[
        "photo"
    ],
    "wof:name":"Shana Goldman Photography",
    "wof:placetype":"venue"
},
  "geometry": {"coordinates":[-122.31288499999999,47.611464],"type":"Point"}
}