{
  "type": "Feature",
  "properties": {
    "iso:country":"US",
    "sg:address":"17234 NE 116th St",
    "sg:city":"Redmond",
    "sg:classifiers":[
        {
            "category":"Retail",
            "subcategory":"Auto Repair",
            "type":"Services"
        }
    ],
    "sg:phone":"+1 425 702 8761",
    "sg:postcode":"98052",
    "sg:province":"WA",
    "sg:tags":[
        "automotive"
    ],
    "wof:name":"Fender Towing",
    "wof:placetype":"venue"
},
  "geometry": {"coordinates":[-122.110401,47.703883],"type":"Point"}
}