{
  "type": "Feature",
  "properties": {
    "addr:full":"1812 Metzger Rd Carson WA 98610",
    "addr:housenumber":"1812",
    "addr:postcode":"98610",
    "addr:street":"Metzger Rd",
    "iso:country":"US",
    "sg:address":"1812 Metzger Rd",
    "sg:city":"Carson",
    "sg:classifiers":[
        {
            "category":"Manufacturing",
            "subcategory":"Wood Products",
            "type":"Manufacturing & Wholesale Goods"
        },
        {
            "category":"Home & Garden",
            "subcategory":"Furniture",
            "type":"Retail Goods"
        }
    ],
    "sg:phone":"+1 509 427 8979",
    "sg:postcode":"98610",
    "sg:province":"WA",
    "sg:tags":[
        "manufacturer",
        "cabinets-wholesale",
        "cabinet"
    ],
    "wof:name":"John Gittins",
    "wof:placetype":"venue"
},
  "geometry": {"coordinates":[-121.82552200000001,45.746049],"type":"Point"}
}