{
  "type": "Feature",
  "properties": {
    "addr:full":"24000 NE 419th St Amboy WA 98601",
    "addr:housenumber":"24000",
    "addr:postcode":"98601",
    "addr:street":"Ne 419Th St",
    "iso:country":"US",
    "sg:address":"24000 NE 419th St",
    "sg:city":"Amboy",
    "sg:classifiers":[
        {
            "category":"Freight",
            "type":"Transportation"
        }
    ],
    "sg:phone":"+1 360 247 5953",
    "sg:postcode":"98601",
    "sg:province":"WA",
    "sg:tags":[
        "hauling",
        "trucking"
    ],
    "wof:name":"Gene Gruber Trucking",
    "wof:placetype":"venue"
},
  "geometry": {"coordinates":[-122.425961,45.924412],"type":"Point"}
}