{
  "type": "Feature",
  "properties": {
    "addr:full":"7937 159th Pl NE Redmond WA 98052",
    "addr:housenumber":"7937",
    "addr:postcode":"98052",
    "addr:street":"159Th Pl Ne",
    "iso:country":"US",
    "sg:address":"7937 159th Pl NE",
    "sg:city":"Redmond",
    "sg:classifiers":[
        {
            "category":"Sports & Exercise",
            "subcategory":"Gym",
            "type":"Entertainment"
        },
        {
            "category":"Arena",
            "subcategory":"Sports Club",
            "type":"Entertainment"
        }
    ],
    "sg:phone":"+1 425 883 3387",
    "sg:postcode":"98052",
    "sg:province":"WA",
    "sg:tags":[
        "martial art"
    ],
    "wof:name":"Basic Training Center",
    "wof:placetype":"venue"
},
  "geometry": {"coordinates":[-122.129997,47.674],"type":"Point"}
}