{
  "type": "Feature",
  "properties": {
    "addr:full":"112 Northridge Dr Centralia WA 98531",
    "addr:housenumber":"112",
    "addr:postcode":"98531",
    "addr:street":"Northridge Dr",
    "iso:country":"US",
    "sg:address":"112 Northridge Dr",
    "sg:city":"Centralia",
    "sg:classifiers":[
        {
            "category":"Manufacturing",
            "subcategory":"Lumber",
            "type":"Manufacturing & Wholesale Goods"
        }
    ],
    "sg:phone":"+1 360 736 8923",
    "sg:postcode":"98531",
    "sg:province":"WA",
    "sg:tags":[
        "timberland",
        "forestry",
        "timber"
    ],
    "wof:name":"Christopherson, Rolin Price",
    "wof:placetype":"venue"
},
  "geometry": {"coordinates":[-122.94549499999999,46.757207],"type":"Point"}
}