{
  "type": "Feature",
  "properties": {
    "addr:full":"26310 NE 45th Ave Ridgefield WA 98642",
    "addr:housenumber":"26310",
    "addr:postcode":"98642",
    "addr:street":"Ne 45Th Ave",
    "iso:country":"US",
    "sg:address":"26310 NE 45th Ave",
    "sg:city":"Ridgefield",
    "sg:classifiers":[
        {
            "category":"Building & Trades",
            "subcategory":"Construction",
            "type":"Services"
        }
    ],
    "sg:phone":"+1 360 887 8522",
    "sg:postcode":"98642",
    "sg:province":"WA",
    "sg:tags":[
        "masonry",
        "contractor"
    ],
    "wof:name":"Farr Masonery",
    "wof:placetype":"venue"
},
  "geometry": {"coordinates":[-122.625641,45.812576],"type":"Point"}
}