{
  "type": "Feature",
  "properties": {
    "addr:full":"875 Bickleton Hwy Goldendale WA 98620",
    "addr:housenumber":"875",
    "addr:postcode":"98620",
    "addr:street":"Bickleton Hwy",
    "iso:country":"US",
    "sg:address":"875 Bickleton Hwy",
    "sg:city":"Goldendale",
    "sg:classifiers":[
        {
            "category":"Farming",
            "subcategory":"Livestock Farm",
            "type":"Manufacturing & Wholesale Goods"
        }
    ],
    "sg:phone":"+1 509 773 4195",
    "sg:postcode":"98620",
    "sg:province":"WA",
    "sg:tags":[
        "wheat",
        "beef",
        "crop",
        "field",
        "cattle",
        "feedlot"
    ],
    "wof:name":"Art Schuster Family Inc",
    "wof:placetype":"venue"
},
  "geometry": {"coordinates":[-120.64481600000001,45.840994],"type":"Point"}
}