{
  "type": "Feature",
  "properties": {
    "addr:full":"2212 Queen Anne Ave N Ste 817 Seattle WA 98109",
    "addr:housenumber":"2212",
    "addr:postcode":"98109",
    "addr:street":"Queen Anne Ave N Ste 817",
    "iso:country":"US",
    "sg:address":"2212 Queen Anne Ave N Ste 817",
    "sg:city":"Seattle",
    "sg:classifiers":[
        {
            "category":"Shopping",
            "subcategory":"Clothing, Apparel, & Fashions",
            "type":"Retail Goods"
        },
        {
            "category":"Personal",
            "type":"Services"
        }
    ],
    "sg:phone":"+1 206 324 4851",
    "sg:postcode":"98109",
    "sg:province":"WA",
    "sg:website":"lesegoistes.com",
    "wof:name":"les Egoistes, LLC",
    "wof:placetype":"venue"
},
  "geometry": {"coordinates":[-122.356882,47.638863],"type":"Point"}
}