{
  "type": "Feature",
  "properties": {
    "addr:full":"6131 Northwest Dr Ferndale WA 98248",
    "addr:housenumber":"6131",
    "addr:postcode":"98248",
    "addr:street":"Northwest Dr",
    "iso:country":"US",
    "sg:address":"6131 Northwest Dr",
    "sg:city":"Ferndale",
    "sg:classifiers":[
        {
            "category":"Professional",
            "subcategory":"Engineering",
            "type":"Services"
        },
        {
            "category":"Building & Trades",
            "subcategory":"Construction",
            "type":"Services"
        }
    ],
    "sg:phone":"+1 360 380 2019",
    "sg:postcode":"98248",
    "sg:province":"WA",
    "sg:tags":[
        "repair",
        "management",
        "energy",
        "systems-service",
        "equipment",
        "solar",
        "engineer"
    ],
    "wof:name":"The Lanai Solution Inc",
    "wof:placetype":"venue"
},
  "geometry": {"coordinates":[-122.540876,48.863538],"type":"Point"}
}