{
  "type": "Feature",
  "properties": {
    "addr:full":"1393 Rush Rd Chehalis WA 98532",
    "addr:housenumber":"1393",
    "addr:postcode":"98532",
    "addr:street":"Rush Rd",
    "iso:country":"US",
    "sg:address":"1393 Rush Rd",
    "sg:city":"Chehalis",
    "sg:classifiers":[
        {
            "category":"Autos & Motor Vehicles",
            "subcategory":"Automobile Sales",
            "type":"Retail Goods"
        }
    ],
    "sg:phone":"+1 360 748 4206",
    "sg:postcode":"98532",
    "sg:province":"WA",
    "sg:tags":[
        "sport",
        "trailer",
        "utility"
    ],
    "wof:name":"Carson Trailer Sales",
    "wof:placetype":"venue"
},
  "geometry": {"coordinates":[-122.908252,46.612262],"type":"Point"}
}