{
  "type": "Feature",
  "properties": {
    "addr:full":"16739 188th Pl NE Woodinville WA 98072",
    "addr:housenumber":"16739",
    "addr:postcode":"98072",
    "addr:street":"188Th Pl Ne",
    "iso:country":"US",
    "sg:address":"16739 188th Pl NE",
    "sg:city":"Woodinville",
    "sg:classifiers":[
        {
            "category":"Professional",
            "type":"Services"
        }
    ],
    "sg:phone":"+1 425 788 0919",
    "sg:postcode":"98072",
    "sg:province":"WA",
    "wof:name":"Exe-Lent Oxyfresh",
    "wof:placetype":"venue"
},
  "geometry": {"coordinates":[-122.087442,47.749654],"type":"Point"}
}