{
  "type": "Feature",
  "properties": {
    "iso:country":"US",
    "sg:address":"202 Williams Finney Rd",
    "sg:city":"Kelso",
    "sg:classifiers":[
        {
            "category":"Professional",
            "subcategory":"Accounting & Tax Preparation",
            "type":"Services"
        }
    ],
    "sg:phone":"+1 360 636 1117",
    "sg:postcode":"98626",
    "sg:province":"WA",
    "wof:name":"Paul Gearhart CPA",
    "wof:placetype":"venue"
},
  "geometry": {"coordinates":[-122.893466,46.159013],"type":"Point"}
}