{
  "type": "Feature",
  "properties": {
    "addr:full":"2523 Walnut Loop NW Olympia WA 98502",
    "addr:housenumber":"2523",
    "addr:postcode":"olympia wa 98502",
    "addr:street":"Walnut Loop Nw",
    "iso:country":"US",
    "sg:address":"2523 Walnut Loop NW",
    "sg:city":"Olympia",
    "sg:classifiers":[
        {
            "category":"Professional",
            "subcategory":"Management & Consulting",
            "type":"Services"
        }
    ],
    "sg:phone":"+1 360 357 4348",
    "sg:postcode":"98502",
    "sg:province":"WA",
    "sg:tags":[
        "business"
    ],
    "wof:name":"Cognasso Consulting",
    "wof:placetype":"venue"
},
  "geometry": {"coordinates":[-122.933779,47.056648],"type":"Point"}
}