{
  "type": "Feature",
  "properties": {
    "addr:full":"3705 S Edmunds St Seattle WA 98118",
    "addr:housenumber":"3705",
    "addr:postcode":"98118",
    "addr:street":"S Edmunds St",
    "iso:country":"US",
    "sg:address":"3705 S Edmunds St",
    "sg:city":"Seattle",
    "sg:classifiers":[
        {
            "category":"Personal",
            "subcategory":"Beauty Salon",
            "type":"Services"
        }
    ],
    "sg:phone":"+1 206 725 3841",
    "sg:postcode":"98118",
    "sg:province":"WA",
    "sg:tags":[
        "hair",
        "shop",
        "braiding"
    ],
    "sg:website":"http://www.salonadidez.com",
    "wof:name":"Salon Adidez",
    "wof:placetype":"venue"
},
  "geometry": {"coordinates":[-122.28614899999999,47.558651],"type":"Point"}
}