{
  "type": "Feature",
  "properties": {
    "addr:full":"1005 N 1st St Yakima WA 98901",
    "addr:housenumber":"1005",
    "addr:postcode":"98901",
    "addr:street":"N 1St St",
    "iso:country":"US",
    "sg:address":"1005 N 1st St",
    "sg:city":"Yakima",
    "sg:classifiers":[
        {
            "category":"Food & Beverages",
            "subcategory":"Groceries & Convenience Stores",
            "type":"Retail Goods"
        }
    ],
    "sg:phone":"+1 509 457 1113",
    "sg:postcode":"98901",
    "sg:province":"WA",
    "sg:tags":[
        "grocer"
    ],
    "wof:name":"Roadrunner Deli-Mart Inc",
    "wof:placetype":"venue"
},
  "geometry": {"coordinates":[-120.511865,46.614861],"type":"Point"}
}