{
  "type": "Feature",
  "properties": {
    "addr:full":"910 Lenora St Ste 152 Seattle WA 98121",
    "addr:housenumber":"910",
    "addr:postcode":"98121",
    "addr:street":"Lenora St Ste 152",
    "iso:country":"US",
    "sg:address":"910 Lenora St Ste 152",
    "sg:city":"Seattle",
    "sg:classifiers":[
        {
            "category":"Shopping",
            "subcategory":"Pharmacy",
            "type":"Retail Goods"
        }
    ],
    "sg:phone":"+1 206 405 3565",
    "sg:postcode":"98121",
    "sg:province":"WA",
    "sg:tags":[
        "drugstore"
    ],
    "wof:name":"Kelley-Ross Pharmacy",
    "wof:placetype":"venue"
},
  "geometry": {"coordinates":[-122.33709399999999,47.617349],"type":"Point"}
}