{
  "type": "Feature",
  "properties": {
    "addr:full":"7116 191st Pl SW Lynnwood WA 98036",
    "addr:housenumber":"7116",
    "addr:postcode":"98036",
    "addr:street":"191St Pl Sw",
    "iso:country":"US",
    "sg:address":"7116 191st Pl SW",
    "sg:city":"Lynnwood",
    "sg:classifiers":[
        {
            "category":"Home & Garden",
            "subcategory":"Building Materials",
            "type":"Retail Goods"
        }
    ],
    "sg:phone":"+1 425 774 8555",
    "sg:postcode":"98036",
    "sg:province":"WA",
    "sg:tags":[
        "glass",
        "window",
        "plate"
    ],
    "wof:name":"Economy Window & Glass",
    "wof:placetype":"venue"
},
  "geometry": {"coordinates":[-122.32972700000001,47.825371],"type":"Point"}
}