{
  "type": "Feature",
  "properties": {
    "addr:full":"29010 2nd Ave NW Arlington WA 98223",
    "addr:housenumber":"29010",
    "addr:postcode":"98223",
    "addr:street":"2Nd Ave Nw",
    "iso:country":"US",
    "sg:address":"29010 2nd Ave NW",
    "sg:city":"Arlington",
    "sg:classifiers":[
        {
            "category":"Manufacturing",
            "subcategory":"Lumber",
            "type":"Manufacturing & Wholesale Goods"
        }
    ],
    "sg:phone":"+1 360 629 9539",
    "sg:postcode":"98223",
    "sg:province":"WA",
    "sg:tags":[
        "logging"
    ],
    "wof:name":"Mf Logging",
    "wof:placetype":"venue"
},
  "geometry": {"coordinates":[-122.23427,48.25808],"type":"Point"}
}