{
  "type": "Feature",
  "properties": {
    "addr:full":"208 S Steen Rd Spokane Valley WA 99037",
    "addr:housenumber":"208",
    "addr:postcode":"99037",
    "addr:street":"S Steen Rd",
    "iso:country":"US",
    "sg:address":"208 S Steen Rd",
    "sg:city":"Spokane Valley",
    "sg:classifiers":[
        {
            "category":"Retail",
            "subcategory":"Veterinary Services",
            "type":"Services"
        }
    ],
    "sg:phone":"+1 509 924 4558",
    "sg:postcode":"99037",
    "sg:province":"WA",
    "sg:tags":[
        "veterinarian"
    ],
    "wof:name":"Heart Arrow Veterinary Svc",
    "wof:placetype":"venue"
},
  "geometry": {"coordinates":[-117.177835,47.653896],"type":"Point"}
}