{
  "type": "Feature",
  "properties": {
    "addr:full":"16330 NE 4th St Bellevue WA 98008",
    "addr:housenumber":"16330",
    "addr:postcode":"98008",
    "addr:street":"Ne 4Th St",
    "iso:country":"US",
    "sg:address":"16330 NE 4th St",
    "sg:city":"Bellevue",
    "sg:classifiers":[
        {
            "category":"Organizations",
            "subcategory":"Religious Organization",
            "type":"Services"
        }
    ],
    "sg:phone":"+1 425 747 5996",
    "sg:postcode":"98008",
    "sg:province":"WA",
    "sg:tags":[
        "book"
    ],
    "wof:name":"Unity Bookstore",
    "wof:placetype":"venue"
},
  "geometry": {"coordinates":[-122.123857,47.613446],"type":"Point"}
}