{
  "type": "Feature",
  "properties": {
    "addr:full":"4645 Universty Vlg Plz NE Seattle WA 98105",
    "addr:housenumber":"4645",
    "addr:postcode":"98105",
    "addr:street":"Universty Vlg Plz Ne",
    "iso:country":"US",
    "sg:address":"4645 Universty Vlg Plz NE",
    "sg:city":"Seattle",
    "sg:classifiers":[
        {
            "category":"Home & Garden",
            "subcategory":"Home Furnishings",
            "type":"Retail Goods"
        }
    ],
    "sg:phone":"+1 206 522 6860",
    "sg:postcode":"98105",
    "sg:province":"WA",
    "sg:tags":[
        "decor"
    ],
    "wof:name":"Pottery Barn",
    "wof:placetype":"venue"
},
  "geometry": {"coordinates":[-122.300003,47.661999],"type":"Point"}
}