{
  "type": "Feature",
  "properties": {
    "addr:full":"202 W 3rd Ave Moses Lake WA 98837",
    "addr:housenumber":"202",
    "addr:postcode":"98837",
    "addr:street":"W 3Rd Ave",
    "iso:country":"US",
    "sg:address":"202 W 3rd Ave",
    "sg:city":"Moses Lake",
    "sg:classifiers":[
        {
            "category":"Shopping",
            "subcategory":"Computers & Home Electronics",
            "type":"Retail Goods"
        }
    ],
    "sg:phone":"+1 509 762 9736",
    "sg:postcode":"98837",
    "sg:province":"WA",
    "wof:name":"Grant County Powernet",
    "wof:placetype":"venue"
},
  "geometry": {"coordinates":[-119.279358,47.129579],"type":"Point"}
}