{
  "type": "Feature",
  "properties": {
    "addr:full":"1310 Farragut Dr Coupeville WA 98239",
    "addr:housenumber":"1310",
    "addr:postcode":"98239",
    "addr:street":"Farragut Dr",
    "iso:country":"US",
    "sg:address":"1310 Farragut Dr",
    "sg:city":"Coupeville",
    "sg:classifiers":[
        {
            "category":"Building & Trades",
            "subcategory":"Landscaping Services",
            "type":"Services"
        },
        {
            "category":"Building & Trades",
            "subcategory":"Construction",
            "type":"Services"
        }
    ],
    "sg:phone":"+1 360 661 5332",
    "sg:postcode":"98239",
    "sg:province":"WA",
    "sg:tags":[
        "handyman",
        "painter"
    ],
    "wof:name":"DLK Construction",
    "wof:placetype":"venue"
},
  "geometry": {"coordinates":[-122.619664,48.162968],"type":"Point"}
}