{
  "type": "Feature",
  "properties": {
    "iso:country":"US",
    "sg:address":"3158 NW 85th St",
    "sg:city":"Seattle",
    "sg:classifiers":[
        {
            "category":"Building & Trades",
            "subcategory":"Construction",
            "type":"Services"
        }
    ],
    "sg:phone":"+1 206 782 1898",
    "sg:postcode":"98117",
    "sg:province":"WA",
    "sg:tags":[
        "repairing",
        "remodeling",
        "contractor"
    ],
    "wof:name":"Centennial Contracting Inc",
    "wof:placetype":"venue"
},
  "geometry": {"coordinates":[-122.39779,47.690643],"type":"Point"}
}