{
  "type": "Feature",
  "properties": {
    "addr:full":"2110 Coral Sea Ave Oak Harbor WA 98277",
    "addr:housenumber":"2110",
    "addr:postcode":"98277",
    "addr:street":"Coral Sea Ave",
    "iso:country":"US",
    "sg:address":"2110 Coral Sea Ave",
    "sg:city":"Oak Harbor",
    "sg:classifiers":[
        {
            "category":"Personal",
            "subcategory":"Barber",
            "type":"Services"
        }
    ],
    "sg:phone":"+1 360 257 0530",
    "sg:postcode":"98277",
    "sg:province":"WA",
    "sg:tags":[
        "shop"
    ],
    "wof:name":"Navy Barber Shop",
    "wof:placetype":"venue"
},
  "geometry": {"coordinates":[-122.628139,48.284151],"type":"Point"}
}