{
  "type": "Feature",
  "properties": {
    "addr:full":"10401 NE Fourth Plain Rd Vancouver WA 98662",
    "addr:housenumber":"10401",
    "addr:postcode":"98662",
    "addr:street":"Ne Fourth Plain Rd",
    "iso:country":"US",
    "sg:address":"10401 NE Fourth Plain Rd",
    "sg:city":"Vancouver",
    "sg:classifiers":[
        {
            "category":"Social Services",
            "subcategory":"Child Care",
            "type":"Services"
        }
    ],
    "sg:phone":"+1 360 213 0051",
    "sg:postcode":"98662",
    "sg:province":"WA",
    "sg:tags":[
        "day"
    ],
    "wof:name":"YMCA of Columbia-Willamette",
    "wof:placetype":"venue"
},
  "geometry": {"coordinates":[-122.566192,45.662727],"type":"Point"}
}