{
  "type": "Feature",
  "properties": {
    "addr:full":"119 NW 386th St Woodland WA 98674",
    "addr:housenumber":"119",
    "addr:postcode":"98674",
    "addr:street":"Nw 386Th St",
    "iso:country":"US",
    "sg:address":"119 NW 386th St",
    "sg:city":"Woodland",
    "sg:classifiers":[
        {
            "category":"Home & Garden",
            "subcategory":"Garden Supply",
            "type":"Retail Goods"
        }
    ],
    "sg:phone":"+1 360 263 3278",
    "sg:postcode":"98674",
    "sg:province":"WA",
    "sg:tags":[
        "embroidery"
    ],
    "wof:name":"Stitchery By Design",
    "wof:placetype":"venue"
},
  "geometry": {"coordinates":[-122.671916,45.9006],"type":"Point"}
}