{
  "type": "Feature",
  "properties": {
    "addr:full":"3915 E Nebraska Ave Spokane WA 99217",
    "addr:housenumber":"3915",
    "addr:postcode":"99217",
    "addr:street":"E Nebraska Ave",
    "iso:country":"US",
    "sg:address":"3915 E Nebraska Ave",
    "sg:city":"Spokane",
    "sg:classifiers":[
        {
            "category":"Building & Trades",
            "subcategory":"Construction",
            "type":"Services"
        }
    ],
    "sg:phone":"+1 509 468 4933",
    "sg:postcode":"99217",
    "sg:province":"WA",
    "sg:tags":[
        "industrial",
        "light",
        "speculative",
        "contractor",
        "real estate",
        "owner",
        "general",
        "builder",
        "developer"
    ],
    "sg:website":"www.burtonconstruction.net",
    "wof:name":"Burton Wolff Construction",
    "wof:placetype":"venue"
},
  "geometry": {"coordinates":[-117.35295499999999,47.70857],"type":"Point"}
}