{
  "type": "Feature",
  "properties": {
    "addr:full":"OnTheRoad Inc. 6800 132nd Pl SE, W-203 Newcastle WA 98059",
    "addr:housenumber":"6800",
    "addr:postcode":"98059",
    "addr:street":"132Nd Pl Se",
    "iso:country":"US",
    "sg:address":"OnTheRoad Inc. 6800 132nd Pl SE, W-203",
    "sg:city":"Newcastle",
    "sg:classifiers":[
        {
            "category":"Professional",
            "subcategory":"Computer Services",
            "type":"Services"
        }
    ],
    "sg:phone":"+1 425 614 5963",
    "sg:postcode":"98059",
    "sg:province":"WA",
    "sg:tags":[
        "travel",
        "travel-blog",
        "journal",
        "travelers",
        "travel-community",
        "photo",
        "iphone",
        "android",
        "facebook-connect",
        "tc50-demopit09"
    ],
    "sg:website":"http://www.ontheroad.to",
    "wof:name":"OnTheRoad",
    "wof:placetype":"venue"
},
  "geometry": {"coordinates":[-122.152835,47.484838],"type":"Point"}
}