{
  "type": "Feature",
  "properties": {
    "addr:full":"19511 64th Ave W Lynnwood WA 98036",
    "addr:housenumber":"19511",
    "addr:postcode":"98036",
    "addr:street":"64Th Ave W",
    "iso:country":"US",
    "sg:address":"19511 64th Ave W",
    "sg:city":"Lynnwood",
    "sg:classifiers":[
        {
            "category":"Manufacturing",
            "subcategory":"Toys & Sporting Goods",
            "type":"Manufacturing & Wholesale Goods"
        }
    ],
    "sg:phone":"+1 425 775 7959",
    "sg:postcode":"98036",
    "sg:province":"WA",
    "sg:tags":[
        "stationery",
        "mfg"
    ],
    "wof:name":"Creation Station The",
    "wof:placetype":"venue"
},
  "geometry": {"coordinates":[-122.319562,47.821324],"type":"Point"}
}