{
  "type": "Feature",
  "properties": {
    "addr:full":"20314 131st Ct NE Woodinville WA 98072",
    "addr:housenumber":"20314",
    "addr:postcode":"98072",
    "addr:street":"131St Ct Ne",
    "iso:country":"US",
    "sg:address":"20314 131st Ct NE",
    "sg:city":"Woodinville",
    "sg:classifiers":[
        {
            "category":"Autos & Motor Vehicles",
            "subcategory":"Motorcycle Sales",
            "type":"Retail Goods"
        }
    ],
    "sg:phone":"+1 425 486 1244",
    "sg:postcode":"98072",
    "sg:province":"WA",
    "wof:name":"E B C Brakes",
    "wof:placetype":"venue"
},
  "geometry": {"coordinates":[-122.16486,47.775614],"type":"Point"}
}