{
  "type": "Feature",
  "properties": {
    "addr:full":"707 S Seamount Dr Port Angeles WA 98363",
    "addr:housenumber":"707",
    "addr:postcode":"98363",
    "addr:street":"S Seamount Dr",
    "iso:country":"US",
    "sg:address":"707 S Seamount Dr",
    "sg:city":"Port Angeles",
    "sg:classifiers":[
        {
            "category":"Shopping",
            "subcategory":"Florist",
            "type":"Retail Goods"
        }
    ],
    "sg:phone":"+1 360 452 9605",
    "sg:postcode":"98363",
    "sg:province":"WA",
    "wof:name":"Otero Vogt Flowers M",
    "wof:placetype":"venue"
},
  "geometry": {"coordinates":[-123.478977,48.130375],"type":"Point"}
}