{
  "type": "Feature",
  "properties": {
    "addr:full":"407 N Perry St Spokane WA 99202",
    "addr:housenumber":"407",
    "addr:postcode":"99202",
    "addr:street":"N Perry St",
    "iso:country":"US",
    "sg:address":"407 N Perry St",
    "sg:city":"Spokane",
    "sg:classifiers":[
        {
            "category":"Freight",
            "type":"Transportation"
        }
    ],
    "sg:phone":"+1 509 535 7636",
    "sg:postcode":"99202",
    "sg:province":"WA",
    "sg:tags":[
        "cartage",
        "trucking"
    ],
    "sg:website":"www.spokanetransfer.com",
    "wof:name":"Spokane Transfer & Storage Co",
    "wof:placetype":"venue"
},
  "geometry": {"coordinates":[-117.389934,47.66135],"type":"Point"}
}