{
  "type": "Feature",
  "properties": {
    "iso:country":"US",
    "sg:address":"1400 N Highland Pkwy",
    "sg:city":"Tacoma",
    "sg:classifiers":[
        {
            "category":"Sports & Exercise",
            "subcategory":"Golf",
            "type":"Entertainment"
        }
    ],
    "sg:phone":"+1 253 759 3622",
    "sg:postcode":"98406",
    "sg:province":"WA",
    "sg:tags":[
        "course",
        "tennis",
        "court",
        "public"
    ],
    "wof:name":"Highlands Golf Course",
    "wof:placetype":"venue"
},
  "geometry": {"coordinates":[-122.523177,47.264169],"type":"Point"}
}