{
  "type": "Feature",
  "properties": {
    "addr:full":"17922 North Rd Bothell WA 98012",
    "addr:housenumber":"17922",
    "addr:postcode":"98012",
    "addr:street":"North Rd",
    "iso:country":"US",
    "sg:address":"17922 North Rd",
    "sg:city":"Bothell",
    "sg:classifiers":[
        {
            "category":"Professional",
            "type":"Services"
        }
    ],
    "sg:phone":"+1 425 787 0211",
    "sg:postcode":"98012",
    "sg:province":"WA",
    "wof:name":"Eastside Communications Inc",
    "wof:placetype":"venue"
},
  "geometry": {"coordinates":[-122.236716,47.834746],"type":"Point"}
}