{
  "type": "Feature",
  "properties": {
    "addr:full":"2430 Cornwall Ave Bellingham WA 98225",
    "addr:housenumber":"2430",
    "addr:postcode":"98225",
    "addr:street":"Cornwall Ave",
    "iso:country":"US",
    "sg:address":"2430 Cornwall Ave",
    "sg:city":"Bellingham",
    "sg:classifiers":[
        {
            "category":"Real Estate",
            "subcategory":"Real Estate Agent",
            "type":"Services"
        }
    ],
    "sg:phone":"+1 360 756 6500",
    "sg:postcode":"98225",
    "sg:province":"WA",
    "wof:name":"Property Management",
    "wof:placetype":"venue"
},
  "geometry": {"coordinates":[-122.47502299999999,48.761833],"type":"Point"}
}