{
  "type": "Feature",
  "properties": {
    "addr:full":"1903 N Western Ave Wenatchee WA 98801",
    "addr:housenumber":"1903",
    "addr:postcode":"98801",
    "addr:street":"N Western Ave",
    "iso:country":"US",
    "sg:address":"1903 N Western Ave",
    "sg:city":"Wenatchee",
    "sg:classifiers":[
        {
            "category":"Farming",
            "subcategory":"Orchard",
            "type":"Manufacturing & Wholesale Goods"
        }
    ],
    "sg:phone":"+1 509 662 6098",
    "sg:postcode":"98801",
    "sg:province":"WA",
    "sg:tags":[
        "fruit",
        "tree"
    ],
    "wof:name":"Dixie T Childress",
    "wof:placetype":"venue"
},
  "geometry": {"coordinates":[-120.346266,47.451389],"type":"Point"}
}