{
  "type": "Feature",
  "properties": {
    "addr:full":"2019 N Monroe St Spokane WA 99205",
    "addr:housenumber":"2019",
    "addr:postcode":"99205",
    "addr:street":"N Monroe St",
    "iso:country":"US",
    "sg:address":"2019 N Monroe St",
    "sg:city":"Spokane",
    "sg:classifiers":[
        {
            "category":"Autos & Motor Vehicles",
            "subcategory":"Auto Supplies",
            "type":"Retail Goods"
        }
    ],
    "sg:phone":"+1 509 217 1080",
    "sg:postcode":"99205",
    "sg:province":"WA",
    "wof:name":"Bullet Performance",
    "wof:placetype":"venue"
},
  "geometry": {"coordinates":[-117.426748,47.676122],"type":"Point"}
}