{
  "type": "Feature",
  "properties": {
    "iso:country":"US",
    "sg:address":"3878 Reflection Ln E",
    "sg:city":"Port Orchard",
    "sg:classifiers":[
        {
            "category":"Travel",
            "subcategory":"Hotels & Motels",
            "type":"Entertainment"
        }
    ],
    "sg:phone":"+1 360 871 5582",
    "sg:postcode":"98366",
    "sg:province":"WA",
    "sg:tags":[
        "breakfast",
        "operation",
        "bed",
        "accommodation"
    ],
    "wof:name":"Reflections Bed Breakfast Inn",
    "wof:placetype":"venue"
},
  "geometry": {"coordinates":[-122.583825,47.56905],"type":"Point"}
}