{
  "type": "Feature",
  "properties": {
    "iso:country":"US",
    "sg:address":"1117 Ellis St",
    "sg:city":"Bellingham",
    "sg:classifiers":[
        {
            "category":"Organizations",
            "subcategory":"Professional Association",
            "type":"Services"
        }
    ],
    "sg:phone":"+1 360 734 2935",
    "sg:postcode":"98225",
    "sg:province":"WA",
    "wof:name":"Daryl Stewart and Company",
    "wof:placetype":"venue"
},
  "geometry": {"coordinates":[-122.471908,48.741803],"type":"Point"}
}