{
  "type": "Feature",
  "properties": {
    "addr:full":"10505 Bridgeport Way SW Lakewood WA 98499",
    "addr:housenumber":"10505",
    "addr:postcode":"98499",
    "addr:street":"Bridgeport Way Sw",
    "iso:country":"US",
    "sg:address":"10505 Bridgeport Way SW",
    "sg:city":"Lakewood",
    "sg:classifiers":[
        {
            "category":"Shopping",
            "subcategory":"Hobbies, Toys, & Games",
            "type":"Retail Goods"
        },
        {
            "category":"Recreation",
            "subcategory":"Gun Range",
            "type":"Entertainment"
        }
    ],
    "sg:phone":"+1 253 584 8560",
    "sg:postcode":"98499",
    "sg:province":"WA",
    "sg:tags":[
        "safety",
        "instruction",
        "marksmanship",
        "gunsmith"
    ],
    "wof:name":"Rainier Guns",
    "wof:placetype":"venue"
},
  "geometry": {"coordinates":[-122.505256,47.161706],"type":"Point"}
}