{
  "type": "Feature",
  "properties": {
    "addr:full":"3139 W Government Way Seattle WA 98199",
    "addr:housenumber":"3139",
    "addr:postcode":"98199",
    "addr:street":"W Government Way",
    "iso:country":"US",
    "sg:address":"3139 W Government Way",
    "sg:city":"Seattle",
    "sg:classifiers":[
        {
            "category":"Shopping",
            "subcategory":"Hobbies, Toys, & Games",
            "type":"Retail Goods"
        }
    ],
    "sg:phone":"+1 206 859 8363",
    "sg:postcode":"98199",
    "sg:province":"WA",
    "sg:tags":[
        "shop",
        "hobby"
    ],
    "sg:website":"www.sparklingcitymagicshop.com",
    "wof:name":"Sparkling City Magic, Juggling, and Toys",
    "wof:placetype":"venue"
},
  "geometry": {"coordinates":[-122.397689,47.6612],"type":"Point"}
}