{
  "type": "Feature",
  "properties": {
    "addr:full":"6782 Salmon Beach Rd Anacortes WA 98221",
    "addr:housenumber":"6782",
    "addr:postcode":"98221",
    "addr:street":"Salmon Beach Rd",
    "iso:country":"US",
    "sg:address":"6782 Salmon Beach Rd",
    "sg:city":"Anacortes",
    "sg:classifiers":[
        {
            "category":"Professional",
            "subcategory":"Lawyer & Legal Services",
            "type":"Services"
        }
    ],
    "sg:phone":"+1 360 588 8031",
    "sg:postcode":"98221",
    "sg:province":"WA",
    "sg:tags":[
        "arbitration"
    ],
    "wof:name":"James M Paulson Professional Corporation",
    "wof:placetype":"venue"
},
  "geometry": {"coordinates":[-122.592007,48.425422],"type":"Point"}
}