{
  "type": "Feature",
  "properties": {
    "addr:full":"1103 Shaw Rd Puyallup WA 98372",
    "addr:housenumber":"1103",
    "addr:postcode":"98372",
    "addr:street":"Shaw Rd",
    "iso:country":"US",
    "sg:address":"1103 Shaw Rd",
    "sg:city":"Puyallup",
    "sg:classifiers":[
        {
            "category":"Professional",
            "subcategory":"Engineering",
            "type":"Services"
        }
    ],
    "sg:phone":"+1 253 848 6608",
    "sg:postcode":"98372",
    "sg:province":"WA",
    "sg:tags":[
        "engineer"
    ],
    "sg:website":"www.lseinc.com",
    "wof:name":"Leroy Surveyors & Engineers",
    "wof:placetype":"venue"
},
  "geometry": {"coordinates":[-122.256168,47.180774],"type":"Point"}
}