{
  "type": "Feature",
  "properties": {
    "addr:full":"4656 Monkey Hill Rd Oak Harbor WA 98277",
    "addr:housenumber":"4656",
    "addr:postcode":"98277",
    "addr:street":"Monkey Hill Rd",
    "iso:country":"US",
    "sg:address":"4656 Monkey Hill Rd",
    "sg:city":"Oak Harbor",
    "sg:classifiers":[
        {
            "category":"Building & Trades",
            "subcategory":"Construction",
            "type":"Services"
        }
    ],
    "sg:phone":"+1 360 679 3912",
    "sg:postcode":"98277",
    "sg:province":"WA",
    "sg:tags":[
        "builder",
        "operative"
    ],
    "wof:name":"Turpin Construction",
    "wof:placetype":"venue"
},
  "geometry": {"coordinates":[-122.636703,48.385105],"type":"Point"}
}