{
  "type": "Feature",
  "properties": {
    "addr:full":"8233 S Hosmer St Tacoma WA 98408",
    "addr:housenumber":"8233",
    "addr:postcode":"98408",
    "addr:street":"S Hosmer St",
    "iso:country":"US",
    "sg:address":"8233 S Hosmer St",
    "sg:city":"Tacoma",
    "sg:classifiers":[
        {
            "category":"Freight",
            "type":"Transportation"
        }
    ],
    "sg:phone":"+1 253 535 0305",
    "sg:postcode":"98408",
    "sg:province":"WA",
    "sg:tags":[
        "commercial",
        "storage"
    ],
    "wof:name":"A-1 Hosmer Self Storage",
    "wof:placetype":"venue"
},
  "geometry": {"coordinates":[-122.463138,47.181464],"type":"Point"}
}