{
  "type": "Feature",
  "properties": {
    "addr:full":"2227 Carriage Ave Richland WA 99354",
    "addr:housenumber":"2227",
    "addr:postcode":"99354",
    "addr:street":"Carriage Ave",
    "iso:country":"US",
    "sg:address":"2227 Carriage Ave",
    "sg:city":"Richland",
    "sg:classifiers":[
        {
            "category":"Education",
            "subcategory":"School",
            "type":"Public Place"
        }
    ],
    "sg:phone":"+1 509 375 4761",
    "sg:postcode":"99354",
    "sg:province":"WA",
    "wof:name":"Oasis School",
    "wof:placetype":"venue"
},
  "geometry": {"coordinates":[-119.275189,46.313335],"type":"Point"}
}