{
  "type": "Feature",
  "properties": {
    "addr:full":"8242 15th Ave NE Seattle WA 98115",
    "addr:housenumber":"8242",
    "addr:postcode":"98115",
    "addr:street":"15Th Ave Ne",
    "iso:country":"US",
    "sg:address":"8242 15th Ave NE",
    "sg:city":"Seattle",
    "sg:classifiers":[
        {
            "category":"Wholesale",
            "subcategory":"Durable Goods & Equipment",
            "type":"Manufacturing & Wholesale Goods"
        }
    ],
    "sg:phone":"+1 206 729 0416",
    "sg:postcode":"98115",
    "sg:province":"WA",
    "sg:tags":[
        "professional"
    ],
    "wof:name":"Prime Focus Inc",
    "wof:placetype":"venue"
},
  "geometry": {"coordinates":[-122.312153,47.690081],"type":"Point"}
}