{
  "type": "Feature",
  "properties": {
    "addr:full":"23501 112th Ave SE Kent WA 98031",
    "addr:housenumber":"23501",
    "addr:postcode":"98031",
    "addr:street":"112Th Ave Se",
    "iso:country":"US",
    "sg:address":"23501 112th Ave SE",
    "sg:city":"Kent",
    "sg:classifiers":[
        {
            "category":"Building & Trades",
            "subcategory":"Construction",
            "type":"Services"
        }
    ],
    "sg:phone":"+1 206 883 5746",
    "sg:postcode":"98031",
    "sg:province":"WA",
    "sg:tags":[
        "wallcoverings-installation",
        "wallpaper",
        "painting",
        "contractor"
    ],
    "wof:name":"Hands On Painting Co.",
    "wof:placetype":"venue"
},
  "geometry": {"coordinates":[-122.19193300000001,47.391609],"type":"Point"}
}