{
  "type": "Feature",
  "properties": {
    "addr:full":"2521 McCloud Creek Rd Newport WA 99156",
    "addr:housenumber":"2521",
    "addr:postcode":"99156",
    "addr:street":"Mccloud Creek Rd",
    "iso:country":"US",
    "sg:address":"2521 McCloud Creek Rd",
    "sg:city":"Newport",
    "sg:classifiers":[
        {
            "category":"Manufacturing",
            "subcategory":"Lumber",
            "type":"Manufacturing & Wholesale Goods"
        }
    ],
    "sg:phone":"+1 509 447 2095",
    "sg:postcode":"99156",
    "sg:province":"WA",
    "sg:tags":[
        "logging"
    ],
    "wof:name":"Swinging Ww Ranch Ba",
    "wof:placetype":"venue"
},
  "geometry": {"coordinates":[-117.176343,48.201291],"type":"Point"}
}