{
  "type": "Feature",
  "properties": {
    "addr:full":"8809 Waller Rd E Tacoma WA 98446",
    "addr:housenumber":"8809",
    "addr:postcode":"98446",
    "addr:street":"Waller Rd E",
    "iso:country":"US",
    "sg:address":"8809 Waller Rd E",
    "sg:city":"Tacoma",
    "sg:classifiers":[
        {
            "category":"Professional",
            "subcategory":"Accounting & Tax Preparation",
            "type":"Services"
        }
    ],
    "sg:phone":"+1 253 531 4488",
    "sg:postcode":"98446",
    "sg:province":"WA",
    "sg:tags":[
        "accountant"
    ],
    "wof:name":"Four Star Investments",
    "wof:placetype":"venue"
},
  "geometry": {"coordinates":[-122.389,47.175567],"type":"Point"}
}