{
  "type": "Feature",
  "properties": {
    "addr:full":"745 Main St Buckley WA 98321",
    "addr:housenumber":"745",
    "addr:postcode":"98321",
    "addr:street":"Main St",
    "iso:country":"US",
    "sg:address":"745 Main St",
    "sg:city":"Buckley",
    "sg:classifiers":[
        {
            "category":"Shopping",
            "subcategory":"Used Merchandise",
            "type":"Retail Goods"
        }
    ],
    "sg:phone":"+1 360 829 2267",
    "sg:postcode":"98321",
    "sg:province":"WA",
    "sg:tags":[
        "antique"
    ],
    "wof:name":"Purple Cow Antiques",
    "wof:placetype":"venue"
},
  "geometry": {"coordinates":[-122.02783100000001,47.162906],"type":"Point"}
}