{
  "type": "Feature",
  "properties": {
    "addr:full":"2222 NW Bucklin Hill Rd Silverdale WA 98383",
    "addr:housenumber":"2222",
    "addr:postcode":"98383",
    "addr:street":"Nw Bucklin Hill Rd",
    "iso:country":"US",
    "sg:address":"2222 NW Bucklin Hill Rd",
    "sg:city":"Silverdale",
    "sg:classifiers":[
        {
            "category":"Coffee & Tea",
            "type":"Food & Drink"
        }
    ],
    "sg:menulink":"http://www.allmenus.com/wa/bremerton/117708-starbucks-coffee/menu/",
    "sg:phone":"+1 360 692 8088",
    "sg:postcode":"98383",
    "sg:province":"WA",
    "sg:tags":[
        "american"
    ],
    "wof:name":"Starbucks Coffee",
    "wof:placetype":"venue"
},
  "geometry": {"coordinates":[-122.67952200000001,47.6516],"type":"Point"}
}