{
  "type": "Feature",
  "properties": {
    "addr:full":"501 Commercial Ave Anacortes WA 98221",
    "addr:housenumber":"501",
    "addr:postcode":"98221",
    "addr:street":"Commercial Ave",
    "iso:country":"US",
    "sg:address":"501 Commercial Ave",
    "sg:city":"Anacortes",
    "sg:classifiers":[
        {
            "category":"Home & Garden",
            "subcategory":"Furniture",
            "type":"Retail Goods"
        }
    ],
    "sg:phone":"+1 360 588 0226",
    "sg:postcode":"98221",
    "sg:province":"WA",
    "sg:tags":[
        "mattress"
    ],
    "wof:name":"A Better Night's Sleep",
    "wof:placetype":"venue"
},
  "geometry": {"coordinates":[-122.61250099999999,48.518285],"type":"Point"}
}