{
  "type": "Feature",
  "properties": {
    "addr:full":"13614 Cedar Ct E Sumner WA 98391",
    "addr:housenumber":"13614",
    "addr:postcode":"98391",
    "addr:street":"Cedar Ct E",
    "iso:country":"US",
    "sg:address":"13614 Cedar Ct E",
    "sg:city":"Sumner",
    "sg:classifiers":[
        {
            "category":"Building & Trades",
            "subcategory":"Construction",
            "type":"Services"
        }
    ],
    "sg:phone":"+1 360 897 1136",
    "sg:postcode":"98391",
    "sg:province":"WA",
    "sg:tags":[
        "house"
    ],
    "wof:name":"Lobo",
    "wof:placetype":"venue"
},
  "geometry": {"coordinates":[-122.13919300000001,47.134514],"type":"Point"}
}