{
  "type": "Feature",
  "properties": {
    "iso:country":"US",
    "sg:address":"5601 S Puget Sound Ave",
    "sg:city":"Tacoma",
    "sg:classifiers":[
        {
            "category":"Organizations",
            "subcategory":"Religious Organization",
            "type":"Services"
        }
    ],
    "sg:phone":"+1 253 472 4239",
    "sg:postcode":"98409",
    "sg:province":"WA",
    "wof:name":"Asbury United Methodist Church",
    "wof:placetype":"venue"
},
  "geometry": {"coordinates":[-122.482365,47.204336],"type":"Point"}
}