{
  "type": "Feature",
  "properties": {
    "addr:full":"8525 120th Ave NE, Suite 203 Kirkland WA 98033",
    "addr:housenumber":"8525",
    "addr:postcode":"98033",
    "addr:street":"120Th Ave Ne Suite 203",
    "iso:country":"US",
    "sg:address":"8525 120th Ave NE, Suite 203",
    "sg:city":"Kirkland",
    "sg:classifiers":[
        {
            "category":"Professional",
            "subcategory":"Computer Services",
            "type":"Services"
        }
    ],
    "sg:phone":"+1 425 827 6156",
    "sg:postcode":"98033",
    "sg:province":"WA",
    "sg:tags":[
        "contact-center-software",
        "call-recording-software",
        "workforce-optimization",
        "workforce-management",
        "speech-analytics"
    ],
    "sg:website":"http://www.telrex.com/",
    "wof:name":"Telrex",
    "wof:placetype":"venue"
},
  "geometry": {"coordinates":[-122.17885,47.661396],"type":"Point"}
}