{
  "type": "Feature",
  "properties": {
    "addr:full":"7000 NE 40th Ave Vancouver WA 98661",
    "addr:housenumber":"7000",
    "addr:postcode":"98661",
    "addr:street":"Ne 40Th Ave",
    "iso:country":"US",
    "sg:address":"7000 NE 40th Ave",
    "sg:city":"Vancouver",
    "sg:classifiers":[
        {
            "category":"Building & Trades",
            "subcategory":"Construction",
            "type":"Services"
        }
    ],
    "sg:phone":"+1 360 693 0703",
    "sg:postcode":"98661",
    "sg:province":"WA",
    "sg:tags":[
        "concrete",
        "restoration",
        "cleaning",
        "repair"
    ],
    "sg:website":"www.eaivalue.com",
    "wof:name":"Ea Services",
    "wof:placetype":"venue"
},
  "geometry": {"coordinates":[-122.63019,45.673406],"type":"Point"}
}