{
  "type": "Feature",
  "properties": {
    "addr:full":"1307 W 14th Ave Spokane WA 99204",
    "addr:housenumber":"1307",
    "addr:postcode":"99204",
    "addr:street":"W 14Th Ave",
    "iso:country":"US",
    "sg:address":"1307 W 14th Ave",
    "sg:city":"Spokane",
    "sg:classifiers":[
        {
            "category":"Retail",
            "subcategory":"Animal Services",
            "type":"Services"
        }
    ],
    "sg:phone":"+1 509 456 8237",
    "sg:postcode":"99204",
    "sg:province":"WA",
    "wof:name":"Dog House",
    "wof:placetype":"venue"
},
  "geometry": {"coordinates":[-117.43241999999999,47.642695],"type":"Point"}
}