{
  "type": "Feature",
  "properties": {
    "addr:full":"18465 Cascade View Dr Monroe WA 98272",
    "addr:housenumber":"18465",
    "addr:postcode":"98272",
    "addr:street":"Cascade View Dr",
    "iso:country":"US",
    "sg:address":"18465 Cascade View Dr",
    "sg:city":"Monroe",
    "sg:classifiers":[
        {
            "category":"Retail",
            "subcategory":"Veterinary Services",
            "type":"Services"
        }
    ],
    "sg:phone":"+1 360 794 1771",
    "sg:postcode":"98272",
    "sg:province":"WA",
    "sg:tags":[
        "veterinarian"
    ],
    "wof:name":"Maverick Veterinary Svc",
    "wof:placetype":"venue"
},
  "geometry": {"coordinates":[-121.984043,47.864641],"type":"Point"}
}