{
  "type": "Feature",
  "properties": {
    "addr:full":"7810 188th St SE Snohomish WA 98296",
    "addr:housenumber":"7810",
    "addr:postcode":"98296",
    "addr:street":"188Th St Se",
    "iso:country":"US",
    "sg:address":"7810 188th St SE",
    "sg:city":"Snohomish",
    "sg:classifiers":[
        {
            "category":"Shopping",
            "subcategory":"Gifts & Souvenirs",
            "type":"Retail Goods"
        },
        {
            "category":"Manufacturing",
            "subcategory":"Retail Goods",
            "type":"Manufacturing & Wholesale Goods"
        }
    ],
    "sg:phone":"+1 360 668 5887",
    "sg:postcode":"98296",
    "sg:province":"WA",
    "sg:tags":[
        "shop",
        "giftware's-wholesale",
        "manufacturer"
    ],
    "wof:name":"Cottonwood Creations",
    "wof:placetype":"venue"
},
  "geometry": {"coordinates":[-122.12766000000001,47.826645],"type":"Point"}
}