{
  "type": "Feature",
  "properties": {
    "addr:full":"2409 E Valley St Seattle WA 98112",
    "addr:housenumber":"2409",
    "addr:postcode":"98112",
    "addr:street":"E Valley St",
    "iso:country":"US",
    "sg:address":"2409 E Valley St",
    "sg:city":"Seattle",
    "sg:classifiers":[
        {
            "category":"Airline",
            "type":"Transportation"
        }
    ],
    "sg:phone":"+1 206 324 9476",
    "sg:postcode":"98112",
    "sg:province":"WA",
    "sg:tags":[
        "rental",
        "leasing",
        "aircraft-charter"
    ],
    "wof:name":"Wilbur F Vanpelt",
    "wof:placetype":"venue"
},
  "geometry": {"coordinates":[-122.300944,47.625929],"type":"Point"}
}