{
  "type": "Feature",
  "properties": {
    "addr:full":"1917 Cole St Enumclaw WA 98022",
    "addr:housenumber":"1917",
    "addr:postcode":"98022",
    "addr:street":"Cole St",
    "iso:country":"US",
    "sg:address":"1917 Cole St",
    "sg:city":"Enumclaw",
    "sg:classifiers":[
        {
            "category":"Retail",
            "subcategory":"Animal Services",
            "type":"Services"
        }
    ],
    "sg:phone":"+1 360 825 4044",
    "sg:postcode":"98022",
    "sg:province":"WA",
    "sg:tags":[
        "pet",
        "grooming",
        "washing"
    ],
    "wof:name":"April's Pet Salon",
    "wof:placetype":"venue"
},
  "geometry": {"coordinates":[-121.985832,47.207183],"type":"Point"}
}