{
  "type": "Feature",
  "properties": {
    "addr:full":"841 W 1st Ave Toppenish WA 98948",
    "addr:housenumber":"841",
    "addr:postcode":"98948",
    "addr:street":"W 1St Ave",
    "iso:country":"US",
    "sg:address":"841 W 1st Ave",
    "sg:city":"Toppenish",
    "sg:classifiers":[
        {
            "category":"Restaurant",
            "type":"Food & Drink"
        }
    ],
    "sg:phone":"+1 509 865 8700",
    "sg:postcode":"98948",
    "sg:province":"WA",
    "sg:tags":[
        "shop",
        "coffee"
    ],
    "wof:name":"Unique Drink Coffee Stop",
    "wof:placetype":"venue"
},
  "geometry": {"coordinates":[-120.323893,46.375132],"type":"Point"}
}