{
  "type": "Feature",
  "properties": {
    "addr:full":"2517 Blue Mountain Rd Port Angeles WA 98362",
    "addr:housenumber":"2517",
    "addr:postcode":"98362",
    "addr:street":"Blue Mountain Rd",
    "iso:country":"US",
    "sg:address":"2517 Blue Mountain Rd",
    "sg:city":"Port Angeles",
    "sg:classifiers":[
        {
            "category":"Real Estate",
            "subcategory":"Real Estate Agent",
            "type":"Services"
        }
    ],
    "sg:phone":"+1 360 683 5299",
    "sg:postcode":"98362",
    "sg:province":"WA",
    "wof:name":"John L Scott Real Estate",
    "wof:placetype":"venue"
},
  "geometry": {"coordinates":[-123.275057,48.051153],"type":"Point"}
}