{
  "type": "Feature",
  "properties": {
    "addr:full":"5020 Meridian Ave N Seattle WA 98103",
    "addr:housenumber":"5020",
    "addr:postcode":"98103",
    "addr:street":"Meridian Ave N",
    "iso:country":"US",
    "sg:address":"5020 Meridian Ave N",
    "sg:city":"Seattle",
    "sg:classifiers":[
        {
            "category":"Health Services",
            "subcategory":"Chiropractor",
            "type":"Services"
        }
    ],
    "sg:phone":"+1 206 632 5083",
    "sg:postcode":"98103",
    "sg:province":"WA",
    "wof:name":"W R Ewings DC",
    "wof:placetype":"venue"
},
  "geometry": {"coordinates":[-122.33364,47.665619],"type":"Point"}
}