{
  "type": "Feature",
  "properties": {
    "addr:full":"1280 Lewis River Rd Woodland WA 98674",
    "addr:housenumber":"1280",
    "addr:postcode":"98674",
    "addr:street":"Lewis River Rd",
    "iso:country":"US",
    "sg:address":"1280 Lewis River Rd",
    "sg:city":"Woodland",
    "sg:classifiers":[
        {
            "category":"Food & Beverages",
            "subcategory":"Groceries & Convenience Stores",
            "type":"Retail Goods"
        }
    ],
    "sg:phone":"+1 360 225 8619",
    "sg:postcode":"98674",
    "sg:province":"WA",
    "wof:name":"Quik Way Food Mart",
    "wof:placetype":"venue"
},
  "geometry": {"coordinates":[-122.740048,45.909173],"type":"Point"}
}