{
  "type": "Feature",
  "properties": {
    "addr:full":"190 Timberline Rd Port Townsend WA 98368",
    "addr:housenumber":"190",
    "addr:postcode":"98368",
    "addr:street":"Timberline Rd",
    "iso:country":"US",
    "sg:address":"190 Timberline Rd",
    "sg:city":"Port Townsend",
    "sg:classifiers":[
        {
            "category":"Professional",
            "type":"Services"
        }
    ],
    "sg:phone":"+1 360 385 3978",
    "sg:postcode":"98368",
    "sg:province":"WA",
    "wof:name":"Timberline Industs",
    "wof:placetype":"venue"
},
  "geometry": {"coordinates":[-122.831858,48.076502],"type":"Point"}
}