{
  "type": "Feature",
  "properties": {
    "addr:full":"13420 NE 16th St Bellevue WA 98005",
    "addr:housenumber":"13420",
    "addr:postcode":"98005",
    "addr:street":"Ne 16Th St",
    "iso:country":"US",
    "sg:address":"13420 NE 16th St",
    "sg:city":"Bellevue",
    "sg:classifiers":[
        {
            "category":"Personal",
            "type":"Services"
        },
        {
            "category":"Home & Garden",
            "subcategory":"Hardware",
            "type":"Retail Goods"
        },
        {
            "category":"Building & Trades",
            "subcategory":"Construction",
            "type":"Services"
        }
    ],
    "sg:phone":"+1 425 643 8411",
    "sg:postcode":"98005",
    "sg:province":"WA",
    "sg:tags":[
        "closet",
        "accessory",
        "designing",
        "contractor",
        "remodeling"
    ],
    "sg:website":"http://www.smartclosets.com",
    "wof:name":"Smart Closets Llc",
    "wof:placetype":"venue"
},
  "geometry": {"coordinates":[-122.161697,47.624518],"type":"Point"}
}