{
  "type": "Feature",
  "properties": {
    "addr:full":"735 N 35th St Seattle WA 98103",
    "addr:housenumber":"735",
    "addr:postcode":"98103",
    "addr:street":"N 35Th St",
    "iso:country":"US",
    "sg:address":"735 N 35th St",
    "sg:city":"Seattle",
    "sg:classifiers":[
        {
            "category":"Social Services",
            "type":"Services"
        }
    ],
    "sg:phone":"+1 206 547 5046",
    "sg:postcode":"98103",
    "sg:province":"WA",
    "sg:tags":[
        "individual",
        "family"
    ],
    "wof:name":"Barbara Johnstone Council",
    "wof:placetype":"venue"
},
  "geometry": {"coordinates":[-122.34768200000001,47.65014],"type":"Point"}
}