{
  "type": "Feature",
  "properties": {
    "addr:full":"500 108th Ave NE Bellevue WA 98004",
    "addr:housenumber":"500",
    "addr:postcode":"98004",
    "addr:street":"108Th Ave Ne",
    "iso:country":"US",
    "sg:address":"500 108th Ave NE",
    "sg:city":"Bellevue",
    "sg:classifiers":[
        {
            "category":"Banks & Credit Unions",
            "subcategory":"Bank",
            "type":"Services"
        }
    ],
    "sg:phone":"+1 425 646 6700",
    "sg:postcode":"98004",
    "sg:province":"WA",
    "sg:tags":[
        "national",
        "commercial"
    ],
    "wof:name":"Bank of America",
    "wof:placetype":"venue"
},
  "geometry": {"coordinates":[-122.196201,47.614636],"type":"Point"}
}