{
  "type": "Feature",
  "properties": {
    "addr:full":"715 Tacoma Ave S Tacoma WA 98402",
    "addr:housenumber":"715",
    "addr:postcode":"98402",
    "addr:street":"Tacoma Ave S",
    "iso:country":"US",
    "sg:address":"715 Tacoma Ave S",
    "sg:city":"Tacoma",
    "sg:classifiers":[
        {
            "category":"Professional",
            "subcategory":"Lawyer & Legal Services",
            "type":"Services"
        }
    ],
    "sg:phone":"+1 253 383 5388",
    "sg:postcode":"98402",
    "sg:province":"WA",
    "wof:name":"Dodge Harold T Jr",
    "wof:placetype":"venue"
},
  "geometry": {"coordinates":[-122.445373,47.256876],"type":"Point"}
}