{
  "type": "Feature",
  "properties": {
    "addr:full":"28703 N Cedar Rd Deer Park WA 99006",
    "addr:housenumber":"28703",
    "addr:postcode":"99006",
    "addr:street":"N Cedar Rd",
    "iso:country":"US",
    "sg:address":"28703 N Cedar Rd",
    "sg:city":"Deer Park",
    "sg:classifiers":[
        {
            "category":"Building & Trades",
            "subcategory":"Construction",
            "type":"Services"
        }
    ],
    "sg:phone":"+1 509 276 8628",
    "sg:postcode":"99006",
    "sg:province":"WA",
    "sg:tags":[
        "excavation",
        "excavating",
        "contractor"
    ],
    "wof:name":"7 C's Construction Inc",
    "wof:placetype":"venue"
},
  "geometry": {"coordinates":[-117.433312,47.922552],"type":"Point"}
}