{
  "type": "Feature",
  "properties": {
    "addr:full":"268 Burwell St Bremerton WA 98337",
    "addr:housenumber":"268",
    "addr:postcode":"98337",
    "addr:street":"Burwell St",
    "iso:country":"US",
    "sg:address":"268 Burwell St",
    "sg:city":"Bremerton",
    "sg:classifiers":[
        {
            "category":"Professional",
            "subcategory":"Computer Services",
            "type":"Services"
        }
    ],
    "sg:phone":"+1 360 362 1691",
    "sg:postcode":"98337",
    "sg:province":"WA",
    "sg:tags":[
        "isp",
        "provider",
        "internet"
    ],
    "wof:name":"Bremerton Satellite Internet",
    "wof:placetype":"venue"
},
  "geometry": {"coordinates":[-122.624617,47.564933],"type":"Point"}
}