{
  "type": "Feature",
  "properties": {
    "addr:full":"384 Mounts Rd Oak Harbor WA 98277",
    "addr:housenumber":"384",
    "addr:postcode":"98277",
    "addr:street":"Mounts Rd",
    "iso:country":"US",
    "sg:address":"384 Mounts Rd",
    "sg:city":"Oak Harbor",
    "sg:classifiers":[
        {
            "category":"Retail",
            "subcategory":"Repair Shop",
            "type":"Services"
        }
    ],
    "sg:phone":"+1 360 675 4421",
    "sg:postcode":"98277",
    "sg:province":"WA",
    "sg:tags":[
        "repairing",
        "piano",
        "refinishing"
    ],
    "wof:name":"Island Piano Svc",
    "wof:placetype":"venue"
},
  "geometry": {"coordinates":[-122.59551999999999,48.311542],"type":"Point"}
}