{
  "type": "Feature",
  "properties": {
    "addr:full":"102101 W Foisy Rd Prosser WA 99350",
    "addr:housenumber":"102101",
    "addr:postcode":"99350",
    "addr:street":"W Foisy Rd",
    "iso:country":"US",
    "sg:address":"102101 W Foisy Rd",
    "sg:city":"Prosser",
    "sg:classifiers":[
        {
            "category":"Education",
            "subcategory":"School",
            "type":"Public Place"
        }
    ],
    "sg:phone":"+1 509 973 2345",
    "sg:postcode":"99350",
    "sg:province":"WA",
    "sg:website":"www.prosserschools.org",
    "wof:name":"Whitstran Elementary School",
    "wof:placetype":"venue"
},
  "geometry": {"coordinates":[-119.71507699999999,46.235754],"type":"Point"}
}