{
  "type": "Feature",
  "properties": {
    "addr:full":"3201 S 192nd St Seattle WA 98188",
    "addr:housenumber":"3201",
    "addr:postcode":"98188",
    "addr:street":"S 192Nd St",
    "iso:country":"US",
    "sg:address":"3201 S 192nd St",
    "sg:city":"Seattle",
    "sg:classifiers":[
        {
            "category":"Building & Trades",
            "subcategory":"Cleaning & Sanitation",
            "type":"Services"
        }
    ],
    "sg:phone":"+1 206 890 0256",
    "sg:postcode":"98188",
    "sg:province":"WA",
    "sg:tags":[
        "maintenance"
    ],
    "wof:name":"Kulan Janitorial Services",
    "wof:placetype":"venue"
},
  "geometry": {"coordinates":[-122.29136099999999,47.4309],"type":"Point"}
}