{
  "type": "Feature",
  "properties": {
    "addr:full":"1315 N Monroe St Spokane WA 99201",
    "addr:housenumber":"1315",
    "addr:postcode":"99201",
    "addr:street":"N Monroe St",
    "iso:country":"US",
    "sg:address":"1315 N Monroe St",
    "sg:city":"Spokane",
    "sg:classifiers":[
        {
            "category":"Building & Trades",
            "subcategory":"Construction",
            "type":"Services"
        }
    ],
    "sg:phone":"+1 509 535 7170",
    "sg:postcode":"99201",
    "sg:province":"WA",
    "sg:tags":[
        "general",
        "contractor"
    ],
    "sg:website":"www.parashomes.com",
    "wof:name":"Paras General Contractors Inc",
    "wof:placetype":"venue"
},
  "geometry": {"coordinates":[-117.42676400000001,47.670071],"type":"Point"}
}