{
  "type": "Feature",
  "properties": {
    "addr:full":"507 Plymouth St SW Olympia WA 98502",
    "addr:housenumber":"507",
    "addr:postcode":"98502",
    "addr:street":"Plymouth St Sw",
    "iso:country":"US",
    "sg:address":"507 Plymouth St SW",
    "sg:city":"Olympia",
    "sg:classifiers":[
        {
            "category":"Professional",
            "subcategory":"Management & Consulting",
            "type":"Services"
        }
    ],
    "sg:phone":"+1 360 705 1044",
    "sg:postcode":"98502",
    "sg:province":"WA",
    "sg:tags":[
        "business"
    ],
    "wof:name":"Calkins Group L L C",
    "wof:placetype":"venue"
},
  "geometry": {"coordinates":[-122.919723,47.042662],"type":"Point"}
}