{
  "type": "Feature",
  "properties": {
    "addr:full":"203 W Kennewick Ave Kennewick WA 99336",
    "addr:housenumber":"203",
    "addr:postcode":"99336",
    "addr:street":"W Kennewick Ave",
    "iso:country":"US",
    "sg:address":"203 W Kennewick Ave",
    "sg:city":"Kennewick",
    "sg:classifiers":[
        {
            "category":"Shopping",
            "subcategory":"Stationery & Office Supplies",
            "type":"Retail Goods"
        },
        {
            "category":"Wholesale",
            "subcategory":"Office Equipment",
            "type":"Manufacturing & Wholesale Goods"
        },
        {
            "category":"Manufacturing",
            "subcategory":"Paper Products",
            "type":"Manufacturing & Wholesale Goods"
        }
    ],
    "sg:phone":"+1 509 586 8586",
    "sg:postcode":"99336",
    "sg:province":"WA",
    "sg:tags":[
        "register",
        "autographic",
        "stationery-wholesale",
        "store",
        "manufacturer"
    ],
    "wof:name":"T & L Office And Art Supply Inc",
    "wof:placetype":"venue"
},
  "geometry": {"coordinates":[-119.11998800000001,46.208679],"type":"Point"}
}