{
  "type": "Feature",
  "properties": {
    "iso:country":"US",
    "sg:address":"23425 62nd Ave S",
    "sg:city":"Kent",
    "sg:classifiers":[
        {
            "category":"Manufacturing",
            "subcategory":"Retail Goods",
            "type":"Manufacturing & Wholesale Goods"
        }
    ],
    "sg:phone":"+1 253 520 9496",
    "sg:postcode":"98032",
    "sg:province":"WA",
    "sg:tags":[
        "product",
        "mfg"
    ],
    "wof:name":"Candle Scents",
    "wof:placetype":"venue"
},
  "geometry": {"coordinates":[-122.257819,47.391406],"type":"Point"}
}