{
  "type": "Feature",
  "properties": {
    "addr:full":"4922 Bridgeport Way W Tacoma WA 98467",
    "addr:housenumber":"4922",
    "addr:postcode":"98467",
    "addr:street":"Bridgeport Way W",
    "iso:country":"US",
    "sg:address":"4922 Bridgeport Way W",
    "sg:city":"Tacoma",
    "sg:classifiers":[
        {
            "category":"Banks & Credit Unions",
            "subcategory":"Bank",
            "type":"Services"
        }
    ],
    "sg:phone":"+1 253 565 9737",
    "sg:postcode":"98467",
    "sg:province":"WA",
    "sg:tags":[
        "state"
    ],
    "sg:website":"www.westsidecommunitybank.com",
    "wof:name":"Westside Community Bank",
    "wof:placetype":"venue"
},
  "geometry": {"coordinates":[-122.53499100000001,47.210849],"type":"Point"}
}