{
  "type": "Feature",
  "properties": {
    "addr:full":"21608 NE 49th Cir Vancouver WA 98682",
    "addr:housenumber":"21608",
    "addr:postcode":"98682",
    "addr:street":"Ne 49Th Cir",
    "iso:country":"US",
    "sg:address":"21608 NE 49th Cir",
    "sg:city":"Vancouver",
    "sg:classifiers":[
        {
            "category":"Professional",
            "subcategory":"Engineering",
            "type":"Services"
        }
    ],
    "sg:phone":"+1 360 600 6084",
    "sg:postcode":"98682",
    "sg:province":"WA",
    "wof:name":"Anderson Structural Engrg",
    "wof:placetype":"venue"
},
  "geometry": {"coordinates":[-122.451222,45.658466],"type":"Point"}
}