{
  "type": "Feature",
  "properties": {
    "iso:country":"US",
    "sg:address":"14619 E Meridian Ave",
    "sg:city":"Puyallup",
    "sg:classifiers":[
        {
            "category":"Retail",
            "subcategory":"Auto Repair",
            "type":"Services"
        }
    ],
    "sg:phone":"+1 253 848 3600",
    "sg:postcode":"98375",
    "sg:province":"WA",
    "sg:tags":[
        "general"
    ],
    "wof:name":"Pro West Auto Select Inc",
    "wof:placetype":"venue"
},
  "geometry": {"coordinates":[-122.293053,47.123211],"type":"Point"}
}