{
  "type": "Feature",
  "properties": {
    "addr:full":"12623 44th Ave NE Marysville WA 98271",
    "addr:housenumber":"12623",
    "addr:postcode":"98271",
    "addr:street":"44Th Ave Ne",
    "iso:country":"US",
    "sg:address":"12623 44th Ave NE",
    "sg:city":"Marysville",
    "sg:classifiers":[
        {
            "category":"Manufacturing",
            "subcategory":"Textiles",
            "type":"Manufacturing & Wholesale Goods"
        }
    ],
    "sg:phone":"+1 360 651 1955",
    "sg:postcode":"98271",
    "sg:province":"WA",
    "sg:tags":[
        "mill",
        "knit",
        "fabric"
    ],
    "wof:name":"Net Services LLC",
    "wof:placetype":"venue"
},
  "geometry": {"coordinates":[-122.172173,48.110497],"type":"Point"}
}