{
  "type": "Feature",
  "properties": {
    "addr:full":"9330 Silverdale Way NW Silverdale WA 98383",
    "addr:housenumber":"9330",
    "addr:postcode":"98383",
    "addr:street":"Silverdale Way Nw",
    "iso:country":"US",
    "sg:address":"9330 Silverdale Way NW",
    "sg:city":"Silverdale",
    "sg:classifiers":[
        {
            "category":"Shopping",
            "subcategory":"Clothing, Apparel, & Fashions",
            "type":"Retail Goods"
        }
    ],
    "sg:phone":"+1 360 662 0272",
    "sg:postcode":"98383",
    "sg:province":"WA",
    "sg:tags":[
        "family"
    ],
    "wof:name":"Inner Winds",
    "wof:placetype":"venue"
},
  "geometry": {"coordinates":[-122.69404900000001,47.650406],"type":"Point"}
}