{
  "type": "Feature",
  "properties": {
    "addr:full":"18122 State Hwy 203 Monroe WA 98272",
    "addr:housenumber":"18122",
    "addr:postcode":"98272",
    "addr:street":"State Hwy 203",
    "iso:country":"US",
    "sg:address":"18122 State Hwy 203",
    "sg:city":"Monroe",
    "sg:classifiers":[
        {
            "category":"Farming",
            "subcategory":"Livestock Farm",
            "type":"Manufacturing & Wholesale Goods"
        }
    ],
    "sg:phone":"+1 360 805 9505",
    "sg:postcode":"98272",
    "sg:province":"WA",
    "sg:tags":[
        "equine"
    ],
    "wof:name":"Cascade Meadows",
    "wof:placetype":"venue"
},
  "geometry": {"coordinates":[-121.969573,47.833163],"type":"Point"}
}