{
  "type": "Feature",
  "properties": {
    "addr:full":"2465 S Kent Des Moines Rd Seattle WA 98198",
    "addr:housenumber":"2465",
    "addr:postcode":"98198",
    "addr:street":"S Kent Des Moines Rd",
    "iso:country":"US",
    "sg:address":"2465 S Kent Des Moines Rd",
    "sg:city":"Seattle",
    "sg:classifiers":[
        {
            "category":"Professional",
            "subcategory":"Business Services",
            "type":"Services"
        }
    ],
    "sg:phone":"+1 206 878 1363",
    "sg:postcode":"98198",
    "sg:province":"WA",
    "wof:name":"Aqua Capital Group",
    "wof:placetype":"venue"
},
  "geometry": {"coordinates":[-122.30336699999999,47.395063],"type":"Point"}
}