{
  "type": "Feature",
  "properties": {
    "addr:full":"9433 4th St SE Lake Stevens WA 98258",
    "addr:housenumber":"9433",
    "addr:postcode":"98258",
    "addr:street":"4Th St Se",
    "iso:country":"US",
    "sg:address":"9433 4th St SE",
    "sg:city":"Lake Stevens",
    "sg:classifiers":[
        {
            "category":"Building & Trades",
            "subcategory":"Construction",
            "type":"Services"
        }
    ],
    "sg:phone":"+1 425 334 5863",
    "sg:postcode":"98258",
    "sg:province":"WA",
    "sg:tags":[
        "contractor"
    ],
    "wof:name":"Glass By Lund Inc",
    "wof:placetype":"venue"
},
  "geometry": {"coordinates":[-122.10433399999999,47.992639],"type":"Point"}
}