{
  "type": "Feature",
  "properties": {
    "addr:full":"6396 NE Ralston Rd Bainbridge Isle WA 98110",
    "addr:housenumber":"6396",
    "addr:postcode":"98110",
    "addr:street":"Ne Ralston Rd;Isle",
    "iso:country":"US",
    "sg:address":"6396 NE Ralston Rd",
    "sg:city":"Bainbridge Isle",
    "sg:classifiers":[
        {
            "category":"Shopping",
            "subcategory":"Computers & Home Electronics",
            "type":"Retail Goods"
        }
    ],
    "sg:phone":"+1 206 842 2155",
    "sg:postcode":"98110",
    "sg:province":"WA",
    "sg:tags":[
        "software"
    ],
    "wof:name":"Educational Fontware Inc",
    "wof:placetype":"venue"
},
  "geometry": {"coordinates":[-122.563292,47.693777],"type":"Point"}
}