{
  "type": "Feature",
  "properties": {
    "addr:full":"130 SW Cedar St Pullman WA 99163",
    "addr:housenumber":"130",
    "addr:postcode":"99163",
    "addr:street":"Sw Cedar St",
    "iso:country":"US",
    "sg:address":"130 SW Cedar St",
    "sg:city":"Pullman",
    "sg:classifiers":[
        {
            "category":"Personal",
            "subcategory":"Beauty Salon",
            "type":"Services"
        }
    ],
    "sg:phone":"+1 509 334 2026",
    "sg:postcode":"99163",
    "sg:province":"WA",
    "sg:tags":[
        "shop"
    ],
    "wof:name":"Electrolysis By Joann",
    "wof:placetype":"venue"
},
  "geometry": {"coordinates":[-117.19091,46.730342],"type":"Point"}
}