{
  "type": "Feature",
  "properties": {
    "addr:full":"9522 1st Ave NE Seattle WA 98115",
    "addr:housenumber":"9522",
    "addr:postcode":"98115",
    "addr:street":"1St Ave Ne",
    "iso:country":"US",
    "sg:address":"9522 1st Ave NE",
    "sg:city":"Seattle",
    "sg:classifiers":[
        {
            "category":"Utilities",
            "subcategory":"Cable",
            "type":"Services"
        }
    ],
    "sg:phone":"+1 206 729 0388",
    "sg:postcode":"98115",
    "sg:province":"WA",
    "sg:tags":[
        "television"
    ],
    "wof:name":"Kristianna L Cable",
    "wof:placetype":"venue"
},
  "geometry": {"coordinates":[-122.328394,47.700053],"type":"Point"}
}