{
  "type": "Feature",
  "properties": {
    "addr:full":"104 S 325th Pl Federal Way WA 98003",
    "addr:housenumber":"104",
    "addr:postcode":"98003",
    "addr:street":"S 325Th Pl",
    "iso:country":"US",
    "sg:address":"104 S 325th Pl",
    "sg:city":"Federal Way",
    "sg:classifiers":[
        {
            "category":"Insurance",
            "subcategory":"Insurance Agent",
            "type":"Services"
        }
    ],
    "sg:phone":"+1 253 874 4282",
    "sg:postcode":"98003",
    "sg:province":"WA",
    "wof:name":"Darrigan R Lutcf Shelgren Fin",
    "wof:placetype":"venue"
},
  "geometry": {"coordinates":[-122.333724,47.310304],"type":"Point"}
}