{
  "type": "Feature",
  "properties": {
    "addr:full":"11105 SE 216th St Kent WA 98031",
    "addr:postcode":"11105;98031",
    "addr:street":"Se 216Th St",
    "iso:country":"US",
    "sg:address":"11105 SE 216th St",
    "sg:city":"Kent",
    "sg:classifiers":[
        {
            "category":"Building & Trades",
            "subcategory":"Construction",
            "type":"Services"
        }
    ],
    "sg:phone":"+1 253 854 6680",
    "sg:postcode":"98031",
    "sg:province":"WA",
    "sg:tags":[
        "hanging",
        "contractor"
    ],
    "wof:name":"Leung King Painting & Const",
    "wof:placetype":"venue"
},
  "geometry": {"coordinates":[-122.19282200000001,47.40888],"type":"Point"}
}