{
  "type": "Feature",
  "properties": {
    "addr:full":"3807 N 11th St Tacoma WA 98406",
    "addr:housenumber":"3807",
    "addr:postcode":"98406",
    "addr:street":"N 11Th St",
    "iso:country":"US",
    "sg:address":"3807 N 11th St",
    "sg:city":"Tacoma",
    "sg:classifiers":[
        {
            "category":"Wholesale",
            "subcategory":"Construction Materials",
            "type":"Manufacturing & Wholesale Goods"
        }
    ],
    "sg:phone":"+1 253 761 2983",
    "sg:postcode":"98406",
    "sg:province":"WA",
    "wof:name":"Sculpting In Stone",
    "wof:placetype":"venue"
},
  "geometry": {"coordinates":[-122.488775,47.260007],"type":"Point"}
}