{
  "type": "Feature",
  "properties": {
    "addr:full":"5400 Beach Dr SW Seattle WA 98136",
    "addr:housenumber":"5400",
    "addr:postcode":"98136",
    "addr:street":"Beach Dr Sw",
    "iso:country":"US",
    "sg:address":"5400 Beach Dr SW",
    "sg:city":"Seattle",
    "sg:classifiers":[
        {
            "category":"Personal",
            "subcategory":"Adult",
            "type":"Services"
        }
    ],
    "sg:phone":"+1 206 937 4633",
    "sg:postcode":"98136",
    "sg:province":"WA",
    "sg:tags":[
        "neckwear"
    ],
    "sg:website":"http://www.joycemcandrews.com",
    "wof:name":"Joyce Inc",
    "wof:placetype":"venue"
},
  "geometry": {"coordinates":[-122.399361,47.554161],"type":"Point"}
}