{
  "type": "Feature",
  "properties": {
    "addr:full":"113 1st Ave S Seattle WA 98104",
    "addr:housenumber":"113",
    "addr:postcode":"98104",
    "addr:street":"1St Ave S",
    "iso:country":"US",
    "sg:address":"113 1st Ave S",
    "sg:city":"Seattle",
    "sg:classifiers":[
        {
            "category":"Shopping",
            "type":"Retail Goods"
        },
        {
            "category":"Home & Garden",
            "subcategory":"Carpets & Floor Coverings",
            "type":"Retail Goods"
        }
    ],
    "sg:phone":"+1 206 624 7726",
    "sg:postcode":"98104",
    "sg:province":"WA",
    "sg:tags":[
        "distributor",
        "rug",
        "carpeting",
        "manufacturer"
    ],
    "sg:website":"www.turabiruggallery.com",
    "wof:name":"Turabi Rug Gallery",
    "wof:placetype":"venue"
},
  "geometry": {"coordinates":[-122.33426799999999,47.601191],"type":"Point"}
}