{
  "type": "Feature",
  "properties": {
    "addr:full":"311 Kel Lowry Rd Naches WA 98937",
    "addr:housenumber":"311",
    "addr:postcode":"98937",
    "addr:street":"Kel Lowry Rd",
    "iso:country":"US",
    "sg:address":"311 Kel Lowry Rd",
    "sg:city":"Naches",
    "sg:classifiers":[
        {
            "category":"Farming",
            "subcategory":"Orchard",
            "type":"Manufacturing & Wholesale Goods"
        }
    ],
    "sg:phone":"+1 509 653 2175",
    "sg:postcode":"98937",
    "sg:province":"WA",
    "sg:tags":[
        "fruit",
        "tree"
    ],
    "wof:name":"Hollis E Finney",
    "wof:placetype":"venue"
},
  "geometry": {"coordinates":[-120.689255,46.727902],"type":"Point"}
}