{
  "type": "Feature",
  "properties": {
    "iso:country":"US",
    "sg:address":"1317 Boren Ave",
    "sg:city":"Seattle",
    "sg:classifiers":[
        {
            "category":"Banks & Credit Unions",
            "subcategory":"Financial Services",
            "type":"Services"
        }
    ],
    "sg:phone":"+1 206 624 3070",
    "sg:postcode":"98101",
    "sg:province":"WA",
    "sg:tags":[
        "investor"
    ],
    "wof:name":"Globeeco Capital Corp",
    "wof:placetype":"venue"
},
  "geometry": {"coordinates":[-122.32797100000001,47.612269],"type":"Point"}
}