{
  "type": "Feature",
  "properties": {
    "addr:full":"40 Lake Bellevue Dr Bellevue WA 98005",
    "addr:housenumber":"40",
    "addr:postcode":"98005",
    "addr:street":"Lake Bellevue Dr",
    "iso:country":"US",
    "sg:address":"40 Lake Bellevue Dr",
    "sg:city":"Bellevue",
    "sg:classifiers":[
        {
            "category":"Professional",
            "subcategory":"Management & Consulting",
            "type":"Services"
        }
    ],
    "sg:phone":"+1 425 688 0077",
    "sg:postcode":"98005",
    "sg:province":"WA",
    "wof:name":"Teamswin Inc",
    "wof:placetype":"venue"
},
  "geometry": {"coordinates":[-122.179616,47.619728],"type":"Point"}
}