{
  "type": "Feature",
  "properties": {
    "addr:full":"1507 Pike Pl Seattle WA 98101",
    "addr:housenumber":"1507",
    "addr:postcode":"98101",
    "addr:street":"Pike Pl",
    "iso:country":"US",
    "sg:address":"1507 Pike Pl",
    "sg:city":"Seattle",
    "sg:classifiers":[
        {
            "category":"Restaurant",
            "type":"Food & Drink"
        }
    ],
    "sg:phone":"+1 206 624 2774",
    "sg:postcode":"98101",
    "sg:province":"WA",
    "sg:tags":[
        "eating",
        "market",
        "farmer"
    ],
    "wof:name":"Chicken Valley Farm Stores",
    "wof:placetype":"venue"
},
  "geometry": {"coordinates":[-122.340723,47.608788],"type":"Point"}
}