{
  "type": "Feature",
  "properties": {
    "addr:full":"5701.5 17th Ave NW Seattle WA 98107",
    "addr:housenumber":"5701.5",
    "addr:postcode":"98107",
    "addr:street":"17Th Ave Nw",
    "iso:country":"US",
    "sg:address":"5701.5 17th Ave NW",
    "sg:city":"Seattle",
    "sg:classifiers":[
        {
            "category":"Personal",
            "subcategory":"Hair Removal",
            "type":"Services"
        },
        {
            "category":"Personal",
            "subcategory":"Skin Care",
            "type":"Services"
        }
    ],
    "sg:phone":"+1 206 335 4453",
    "sg:postcode":"98107",
    "sg:province":"WA",
    "sg:website":"www.liberteliberte.com",
    "wof:name":"Liberte Skin Wellness",
    "wof:placetype":"venue"
},
  "geometry": {"coordinates":[-122.37911800000001,47.670403],"type":"Point"}
}