{
  "type": "Feature",
  "properties": {
    "addr:full":"16024 132nd Pl SE Renton WA 98058",
    "addr:housenumber":"16024",
    "addr:postcode":"98058",
    "addr:street":"132Nd Pl Se",
    "iso:country":"US",
    "sg:address":"16024 132nd Pl SE",
    "sg:city":"Renton",
    "sg:classifiers":[
        {
            "category":"Home & Garden",
            "subcategory":"Furniture",
            "type":"Retail Goods"
        }
    ],
    "sg:phone":"+1 253 872 7969",
    "sg:postcode":"98058",
    "sg:province":"WA",
    "sg:tags":[
        "cabinet"
    ],
    "sg:website":"www.highlandcabinets.com",
    "wof:name":"Highland Cabinets",
    "wof:placetype":"venue"
},
  "geometry": {"coordinates":[-122.163731,47.457618],"type":"Point"}
}