{
  "type": "Feature",
  "properties": {
    "addr:full":"3131 Smokey Point Dr Arlington WA 98223",
    "addr:housenumber":"3131",
    "addr:postcode":"98223",
    "addr:street":"Smokey Point Dr",
    "iso:country":"US",
    "sg:address":"3131 Smokey Point Dr",
    "sg:city":"Arlington",
    "sg:classifiers":[
        {
            "category":"Health Services",
            "subcategory":"Health Practitioner",
            "type":"Services"
        }
    ],
    "sg:phone":"+1 360 658 8400",
    "sg:postcode":"98223",
    "sg:province":"WA",
    "sg:tags":[
        "therapist",
        "physical"
    ],
    "wof:name":"Reaction Physical Therapy",
    "wof:placetype":"venue"
},
  "geometry": {"coordinates":[-122.184951,48.155172],"type":"Point"}
}