{
  "type": "Feature",
  "properties": {
    "addr:full":"1120 W Sylvester St Kennewick WA 99301",
    "addr:housenumber":"1120",
    "addr:postcode":"99301",
    "addr:street":"W Sylvester St",
    "iso:country":"US",
    "sg:address":"1120 W Sylvester St",
    "sg:city":"Kennewick",
    "sg:classifiers":[
        {
            "category":"Shopping",
            "subcategory":"Used Merchandise",
            "type":"Retail Goods"
        }
    ],
    "sg:phone":"+1 509 547 2341",
    "sg:postcode":"99301",
    "sg:province":"WA",
    "sg:tags":[
        "shop",
        "vintage",
        "consignment",
        "thrift"
    ],
    "wof:name":"St Vincent Depaul Store",
    "wof:placetype":"venue"
},
  "geometry": {"coordinates":[-119.104983,46.234086],"type":"Point"}
}