{
  "type": "Feature",
  "properties": {
    "addr:full":"2012 W 17th Ave Kennewick WA 99337",
    "addr:housenumber":"2012",
    "addr:postcode":"99337",
    "addr:street":"W 17Th Ave",
    "iso:country":"US",
    "sg:address":"2012 W 17th Ave",
    "sg:city":"Kennewick",
    "sg:classifiers":[
        {
            "category":"Professional",
            "subcategory":"Management & Consulting",
            "type":"Services"
        }
    ],
    "sg:phone":"+1 509 585 2804",
    "sg:postcode":"99337",
    "sg:province":"WA",
    "wof:name":"Sarah Hostick Lmp",
    "wof:placetype":"venue"
},
  "geometry": {"coordinates":[-119.14756800000001,46.192847],"type":"Point"}
}