{
  "type": "Feature",
  "properties": {
    "addr:full":"7004 180th Ave NE Redmond WA 98052",
    "addr:housenumber":"7004",
    "addr:postcode":"98052",
    "addr:street":"180Th Ave Ne",
    "iso:country":"US",
    "sg:address":"7004 180th Ave NE",
    "sg:city":"Redmond",
    "sg:phone":"+1 425 861 8891",
    "sg:postcode":"98052",
    "sg:province":"WA",
    "wof:name":"Mr Electric",
    "wof:placetype":"venue"
},
  "geometry": {"coordinates":[-122.10013499999999,47.66814],"type":"Point"}
}