{
  "type": "Feature",
  "properties": {
    "addr:full":"5216 170th Pl NE Arlington WA 98223",
    "addr:housenumber":"5216",
    "addr:postcode":"98223",
    "addr:street":"170Th Pl Ne",
    "iso:country":"US",
    "sg:address":"5216 170th Pl NE",
    "sg:city":"Arlington",
    "sg:classifiers":[
        {
            "category":"Social Services",
            "subcategory":"Child Care",
            "type":"Services"
        }
    ],
    "sg:phone":"+1 360 435 2302",
    "sg:postcode":"98223",
    "sg:province":"WA",
    "sg:tags":[
        "day"
    ],
    "wof:name":"Tammy Forbes",
    "wof:placetype":"venue"
},
  "geometry": {"coordinates":[-122.159981,48.150661],"type":"Point"}
}