{
  "type": "Feature",
  "properties": {
    "addr:full":"3815 S Othello St Seattle WA 98118",
    "addr:housenumber":"3815",
    "addr:postcode":"98118",
    "addr:street":"S Othello St",
    "iso:country":"US",
    "sg:address":"3815 S Othello St",
    "sg:city":"Seattle",
    "sg:classifiers":[
        {
            "category":"Building & Trades",
            "subcategory":"Locksmith",
            "type":"Services"
        }
    ],
    "sg:phone":"+1 425 207 3424",
    "sg:postcode":"98118",
    "sg:province":"WA",
    "sg:tags":[
        "key"
    ],
    "wof:name":"A Full Service Locksmith",
    "wof:placetype":"venue"
},
  "geometry": {"coordinates":[-122.284487,47.536816],"type":"Point"}
}