{
  "type": "Feature",
  "properties": {
    "addr:full":"3922 N Visscher St Tacoma WA 98407",
    "addr:housenumber":"3922",
    "addr:postcode":"98407",
    "addr:street":"N Visscher St",
    "iso:country":"US",
    "sg:address":"3922 N Visscher St",
    "sg:city":"Tacoma",
    "sg:classifiers":[
        {
            "category":"Personal",
            "type":"Services"
        }
    ],
    "sg:phone":"+1 800 285 5304",
    "sg:postcode":"98407",
    "sg:province":"WA",
    "wof:name":"Referrals Unlimited",
    "wof:placetype":"venue"
},
  "geometry": {"coordinates":[-122.516705,47.284307],"type":"Point"}
}