{
  "type": "Feature",
  "properties": {
    "addr:full":"112 N 36th St Seattle WA 98103",
    "addr:housenumber":"112",
    "addr:postcode":"98103",
    "addr:street":"N 36Th St",
    "iso:country":"US",
    "sg:address":"112 N 36th St",
    "sg:city":"Seattle",
    "sg:classifiers":[
        {
            "category":"Manufacturing",
            "subcategory":"Printing",
            "type":"Manufacturing & Wholesale Goods"
        }
    ],
    "sg:phone":"+1 206 547 7239",
    "sg:postcode":"98103",
    "sg:province":"WA",
    "sg:tags":[
        "lithographic",
        "commercial"
    ],
    "wof:name":"2nd Phase Printing",
    "wof:placetype":"venue"
},
  "geometry": {"coordinates":[-122.356663,47.652822],"type":"Point"}
}