{
  "type": "Feature",
  "properties": {
    "addr:full":"7916 4th Ct SE Lacey WA 98503",
    "addr:housenumber":"7916",
    "addr:postcode":"98503",
    "addr:street":"4Th Ct Se",
    "iso:country":"US",
    "sg:address":"7916 4th Ct SE",
    "sg:city":"Lacey",
    "sg:classifiers":[
        {
            "category":"Freight",
            "type":"Transportation"
        }
    ],
    "sg:phone":"+1 360 456 1292",
    "sg:postcode":"98503",
    "sg:province":"WA",
    "sg:tags":[
        "operator",
        "local",
        "trucking"
    ],
    "wof:name":"Lund Trucking Co Inc",
    "wof:placetype":"venue"
},
  "geometry": {"coordinates":[-122.770807,47.050215],"type":"Point"}
}