{
  "type": "Feature",
  "properties": {
    "addr:full":"3812 N 39th St Tacoma WA 98407",
    "addr:housenumber":"3812",
    "addr:postcode":"98407",
    "addr:street":"N 39Th St",
    "iso:country":"US",
    "sg:address":"3812 N 39th St",
    "sg:city":"Tacoma",
    "sg:classifiers":[
        {
            "category":"Professional",
            "subcategory":"Computer Services",
            "type":"Services"
        }
    ],
    "sg:phone":"+1 253 759 5123",
    "sg:postcode":"98407",
    "sg:province":"WA",
    "sg:tags":[
        "prepackaged",
        "software"
    ],
    "wof:name":"Osprey Sftwr Consulting Svcs",
    "wof:placetype":"venue"
},
  "geometry": {"coordinates":[-122.487983,47.283253],"type":"Point"}
}