{
  "type": "Feature",
  "properties": {
    "iso:country":"US",
    "sg:address":"1096 Ellie Ln",
    "sg:city":"Stanwood",
    "sg:classifiers":[
        {
            "category":"Building & Trades",
            "subcategory":"Cleaning & Sanitation",
            "type":"Services"
        }
    ],
    "sg:phone":"+1 360 387 1735",
    "sg:postcode":"98282",
    "sg:province":"WA",
    "sg:tags":[
        "maintenance"
    ],
    "wof:name":"Smiling Teris Housekeeping",
    "wof:placetype":"venue"
},
  "geometry": {"coordinates":[-122.519867,48.171279],"type":"Point"}
}