{
  "type": "Feature",
  "properties": {
    "addr:full":"13920 SE Eastgate Way Bellevue WA 98005",
    "addr:postcode":"13920;98005",
    "addr:street":"Se Eastgate Way",
    "iso:country":"US",
    "sg:address":"13920 SE Eastgate Way",
    "sg:city":"Bellevue",
    "sg:classifiers":[
        {
            "category":"Utilities",
            "subcategory":"Mobile Phone",
            "type":"Services"
        },
        {
            "category":"Utilities",
            "subcategory":"Telephone",
            "type":"Services"
        }
    ],
    "sg:phone":"+1 425 643 0471",
    "sg:postcode":"98005",
    "sg:province":"WA",
    "sg:tags":[
        "communication",
        "cellular"
    ],
    "sg:website":"http://www.t-mobile.com",
    "wof:name":"T-Mobile",
    "wof:placetype":"venue"
},
  "geometry": {"coordinates":[-122.154543,47.580062],"type":"Point"}
}