{
  "type": "Feature",
  "properties": {
    "addr:full":"620 Laurel St Yakima WA 98902",
    "addr:housenumber":"620",
    "addr:postcode":"98902",
    "addr:street":"Laurel St",
    "iso:country":"US",
    "sg:address":"620 Laurel St",
    "sg:city":"Yakima",
    "sg:classifiers":[
        {
            "category":"Building & Trades",
            "subcategory":"Construction",
            "type":"Services"
        }
    ],
    "sg:phone":"+1 509 452 9678",
    "sg:postcode":"98902",
    "sg:province":"WA",
    "sg:tags":[
        "excavation",
        "contractor"
    ],
    "wof:name":"Russ Johnson Excavating",
    "wof:placetype":"venue"
},
  "geometry": {"coordinates":[-120.52244,46.613332],"type":"Point"}
}