{
  "type": "Feature",
  "properties": {
    "addr:full":"3245 146th Pl SE Ste 110 Bellevue WA 98007",
    "addr:housenumber":"3245",
    "addr:postcode":"98007",
    "addr:street":"146Th Pl Se Ste 110",
    "iso:country":"US",
    "sg:address":"3245 146th Pl SE Ste 110",
    "sg:city":"Bellevue",
    "sg:classifiers":[
        {
            "category":"Communications",
            "subcategory":"Newspaper",
            "type":"Services"
        }
    ],
    "sg:phone":"+1 425 289 0060",
    "sg:postcode":"98007",
    "sg:province":"WA",
    "sg:tags":[
        "print",
        "medium"
    ],
    "sg:website":"www.paizopublishing.com",
    "wof:name":"Paizo Publishing Llc",
    "wof:placetype":"venue"
},
  "geometry": {"coordinates":[-122.144997,47.5909],"type":"Point"}
}