{
  "type": "Feature",
  "properties": {
    "addr:full":"925 E. Pike Street Seattle WA 98127",
    "addr:housenumber":"925",
    "addr:postcode":"98127",
    "addr:street":"E. Pike Street",
    "iso:country":"US",
    "sg:address":"925 E. Pike Street",
    "sg:city":"Seattle",
    "sg:classifiers":[
        {
            "category":"Arts & Performance",
            "subcategory":"Arts Center",
            "type":"Entertainment"
        },
        {
            "category":"Bars & Pubs",
            "subcategory":"Nightclub",
            "type":"Food & Drink"
        }
    ],
    "sg:postcode":"98127",
    "sg:province":"WA",
    "sg:tags":[
        "performing",
        "nightlife"
    ],
    "wof:name":"Noiselab",
    "wof:placetype":"venue"
},
  "geometry": {"coordinates":[-122.31999999999999,47.613998],"type":"Point"}
}