{
  "type": "Feature",
  "properties": {
    "addr:full":"456 W Wiser Lake Rd Ferndale WA 98248",
    "addr:housenumber":"456",
    "addr:postcode":"98248",
    "addr:street":"W Wiser Lake Rd",
    "iso:country":"US",
    "sg:address":"456 W Wiser Lake Rd",
    "sg:city":"Ferndale",
    "sg:classifiers":[
        {
            "category":"Personal",
            "subcategory":"Beauty Salon",
            "type":"Services"
        }
    ],
    "sg:phone":"+1 360 354 2905",
    "sg:postcode":"98248",
    "sg:province":"WA",
    "sg:tags":[
        "shop"
    ],
    "wof:name":"Jackies Styling Salon",
    "wof:placetype":"venue"
},
  "geometry": {"coordinates":[-122.510043,48.906171],"type":"Point"}
}