{
  "type": "Feature",
  "properties": {
    "addr:full":"224 W Galer St Seattle WA 98119",
    "addr:housenumber":"224",
    "addr:postcode":"98119",
    "addr:street":"W Galer St",
    "iso:country":"US",
    "sg:address":"224 W Galer St",
    "sg:city":"Seattle",
    "sg:classifiers":[
        {
            "category":"Coffee & Tea",
            "type":"Food & Drink"
        },
        {
            "category":"Restaurant",
            "type":"Food & Drink"
        },
        {
            "category":"Bakery",
            "type":"Food & Drink"
        }
    ],
    "sg:phone":"+1 206 282 1441",
    "sg:postcode":"98119",
    "sg:province":"WA",
    "sg:tags":[
        "shop",
        "health",
        "espresso"
    ],
    "sg:website":"www.caffefiore.com/",
    "wof:name":"Caffe Fiore",
    "wof:placetype":"venue"
},
  "geometry": {"coordinates":[-122.360022,47.632329],"type":"Point"}
}