{
  "type": "Feature",
  "properties": {
    "addr:full":"5505 108th St SW Lakewood WA 98499",
    "addr:housenumber":"5505",
    "addr:postcode":"98499",
    "addr:street":"108Th St Sw",
    "iso:country":"US",
    "sg:address":"5505 108th St SW",
    "sg:city":"Lakewood",
    "sg:classifiers":[
        {
            "category":"Organizations",
            "subcategory":"Religious Organization",
            "type":"Services"
        }
    ],
    "sg:phone":"+1 253 588 2142",
    "sg:postcode":"98499",
    "sg:province":"WA",
    "sg:tags":[
        "church"
    ],
    "wof:name":"St Frances Cabrini Church",
    "wof:placetype":"venue"
},
  "geometry": {"coordinates":[-122.510142,47.159597],"type":"Point"}
}