{
  "type": "Feature",
  "properties": {
    "addr:full":"6549 11th Ave NW Seattle WA 98117",
    "addr:housenumber":"6549",
    "addr:postcode":"98117",
    "addr:street":"11Th Ave Nw",
    "iso:country":"US",
    "sg:address":"6549 11th Ave NW",
    "sg:city":"Seattle",
    "sg:classifiers":[
        {
            "category":"Professional",
            "subcategory":"Art Services",
            "type":"Services"
        }
    ],
    "sg:phone":"+1 206 781 7933",
    "sg:postcode":"98117",
    "sg:province":"WA",
    "sg:tags":[
        "commercial",
        "design"
    ],
    "wof:name":"Dave Albers Illustration",
    "wof:placetype":"venue"
},
  "geometry": {"coordinates":[-122.370946,47.67734],"type":"Point"}
}