{
  "type": "Feature",
  "properties": {
    "addr:full":"230 128th St SW Everett WA 98204",
    "addr:housenumber":"230",
    "addr:postcode":"98204",
    "addr:street":"128Th St Sw",
    "iso:country":"US",
    "sg:address":"230 128th St SW",
    "sg:city":"Everett",
    "sg:classifiers":[
        {
            "category":"Restaurant",
            "type":"Food & Drink"
        },
        {
            "category":"Ice Cream",
            "type":"Food & Drink"
        }
    ],
    "sg:menulink":"http://www.allmenus.com/wa/everett/192637-dairy-queen/menu/",
    "sg:phone":"+1 425 355 3447",
    "sg:postcode":"98204",
    "sg:province":"WA",
    "sg:tags":[
        "burger",
        "american",
        "ice",
        "cream"
    ],
    "wof:name":"Dairy Queen",
    "wof:placetype":"venue"
},
  "geometry": {"coordinates":[-122.237599,47.881469],"type":"Point"}
}