{
  "type": "Feature",
  "properties": {
    "addr:full":"907 6th St Clarkston WA 99403",
    "addr:housenumber":"907",
    "addr:postcode":"99403",
    "addr:street":"6Th St",
    "iso:country":"US",
    "sg:address":"907 6th St",
    "sg:city":"Clarkston",
    "sg:classifiers":[
        {
            "category":"Restaurant",
            "type":"Food & Drink"
        }
    ],
    "sg:phone":"+1 509 295 6431",
    "sg:postcode":"99403",
    "sg:province":"WA",
    "sg:tags":[
        "chinese"
    ],
    "sg:website":"http://bamboomenu.com/",
    "wof:name":"Bamboo Gardens",
    "wof:placetype":"venue"
},
  "geometry": {"coordinates":[-117.04557,46.412673],"type":"Point"}
}