{
  "type": "Feature",
  "properties": {
    "addr:full":"1090 E Smith Rd Bellingham WA 98226",
    "addr:housenumber":"1090",
    "addr:postcode":"98226",
    "addr:street":"E Smith Rd",
    "iso:country":"US",
    "sg:address":"1090 E Smith Rd",
    "sg:city":"Bellingham",
    "sg:classifiers":[
        {
            "category":"Recreation",
            "type":"Entertainment"
        }
    ],
    "sg:phone":"+1 360 398 1255",
    "sg:postcode":"98226",
    "sg:province":"WA",
    "sg:tags":[
        "stable"
    ],
    "wof:name":"Papetti Lane Equestrian Ctr",
    "wof:placetype":"venue"
},
  "geometry": {"coordinates":[-122.43209400000001,48.833333],"type":"Point"}
}