{
  "type": "Feature",
  "properties": {
    "addr:full":"17801 Pacific Hwy S Seatac WA 98188",
    "addr:housenumber":"17801",
    "addr:postcode":"98188",
    "addr:street":"Pacific Hwy S Seatac",
    "iso:country":"US",
    "sg:address":"17801 Pacific Hwy S",
    "sg:city":"Seatac",
    "sg:classifiers":[
        {
            "category":"Wholesale",
            "subcategory":"Durable Goods & Equipment",
            "type":"Manufacturing & Wholesale Goods"
        }
    ],
    "sg:phone":"+1 206 433 5611",
    "sg:postcode":"98188",
    "sg:province":"WA",
    "sg:tags":[
        "importer"
    ],
    "sg:website":"www.hmshost.com",
    "wof:name":"HMS Host",
    "wof:placetype":"venue"
},
  "geometry": {"coordinates":[-122.296137,47.442236],"type":"Point"}
}