{
  "type": "Feature",
  "properties": {
    "addr:full":"619 N 36th St Seattle WA 98103",
    "addr:housenumber":"619",
    "addr:postcode":"98103",
    "addr:street":"N 36Th St",
    "iso:country":"US",
    "sg:address":"619 N 36th St",
    "sg:city":"Seattle",
    "sg:classifiers":[
        {
            "category":"Community Center",
            "subcategory":"Social",
            "type":"Public Place"
        }
    ],
    "sg:phone":"+1 206 632 7868",
    "sg:postcode":"98103",
    "sg:province":"WA",
    "sg:tags":[
        "club"
    ],
    "sg:website":"www.doric92.org",
    "wof:name":"Doric Masonic Lodge #92",
    "wof:placetype":"venue"
},
  "geometry": {"coordinates":[-122.35057399999999,47.651267],"type":"Point"}
}