{
  "type": "Feature",
  "properties": {
    "addr:full":"16202 Jordan Way Arlington WA 98223",
    "addr:housenumber":"16202",
    "addr:postcode":"98223",
    "addr:street":"Jordan Way",
    "iso:country":"US",
    "sg:address":"16202 Jordan Way",
    "sg:city":"Arlington",
    "sg:classifiers":[
        {
            "category":"Professional",
            "type":"Services"
        }
    ],
    "sg:phone":"+1 360 435 2910",
    "sg:postcode":"98223",
    "sg:province":"WA",
    "wof:name":"Larry J Melvin",
    "wof:placetype":"venue"
},
  "geometry": {"coordinates":[-122.04142,48.142664],"type":"Point"}
}