{
  "type": "Feature",
  "properties": {
    "iso:country":"US",
    "sg:address":"16590 NE 79th St",
    "sg:city":"Redmond",
    "sg:classifiers":[
        {
            "category":"Building & Trades",
            "subcategory":"Plumbing",
            "type":"Services"
        }
    ],
    "sg:phone":"+1 425 556 0933",
    "sg:postcode":"98052",
    "sg:province":"WA",
    "sg:tags":[
        "fire",
        "design",
        "installation",
        "sprinkler"
    ],
    "wof:name":"Nor Tech Fire Protection Inc",
    "wof:placetype":"venue"
},
  "geometry": {"coordinates":[-122.11958,47.673961],"type":"Point"}
}