{
  "type": "Feature",
  "properties": {
    "iso:country":"US",
    "sg:address":"13702 56th Ave NE",
    "sg:city":"Marysville",
    "sg:classifiers":[
        {
            "category":"Building & Trades",
            "subcategory":"Construction",
            "type":"Services"
        }
    ],
    "sg:phone":"+1 360 659 5893",
    "sg:postcode":"98271",
    "sg:province":"WA",
    "sg:tags":[
        "hanging",
        "painter",
        "contractor"
    ],
    "wof:name":"Rainier Painting Co",
    "wof:placetype":"venue"
},
  "geometry": {"coordinates":[-122.15616199999999,48.119683],"type":"Point"}
}