{
  "type": "Feature",
  "properties": {
    "addr:full":"200 Murdock St Sedro Woolley WA 98284",
    "addr:housenumber":"200",
    "addr:postcode":"98284",
    "addr:street":"Murdock St",
    "iso:country":"US",
    "sg:address":"200 Murdock St",
    "sg:city":"Sedro Woolley",
    "sg:classifiers":[
        {
            "category":"Retail",
            "subcategory":"Veterinary Services",
            "type":"Services"
        }
    ],
    "sg:phone":"+1 360 856 1809",
    "sg:postcode":"98284",
    "sg:province":"WA",
    "sg:tags":[
        "veterinarian"
    ],
    "sg:website":"www.northcascadevet.com",
    "wof:name":"North Cascade Vet Hospital",
    "wof:placetype":"venue"
},
  "geometry": {"coordinates":[-122.23699999999999,48.510502],"type":"Point"}
}