{
  "type": "Feature",
  "properties": {
    "addr:full":"1013 Bridge St Ste B Clarkston WA 99403",
    "addr:housenumber":"1013",
    "addr:postcode":"99403",
    "addr:street":"Bridge St Ste B",
    "iso:country":"US",
    "sg:address":"1013 Bridge St Ste B",
    "sg:city":"Clarkston",
    "sg:classifiers":[
        {
            "category":"Personal",
            "subcategory":"Nail Salon",
            "type":"Services"
        }
    ],
    "sg:phone":"+1 509 758 3034",
    "sg:postcode":"99403",
    "sg:province":"WA",
    "wof:name":"Nail L Art",
    "wof:placetype":"venue"
},
  "geometry": {"coordinates":[-117.050933,46.419922],"type":"Point"}
}