{
  "type": "Feature",
  "properties": {
    "addr:full":"517 S College Ave College Place WA 99324",
    "addr:housenumber":"517",
    "addr:postcode":"99324",
    "addr:street":"S College Ave",
    "iso:country":"US",
    "sg:address":"517 S College Ave",
    "sg:city":"College Place",
    "sg:classifiers":[
        {
            "category":"Professional",
            "subcategory":"Engineering",
            "type":"Services"
        }
    ],
    "sg:phone":"+1 509 526 0682",
    "sg:postcode":"99324",
    "sg:province":"WA",
    "sg:tags":[
        "engineer"
    ],
    "wof:name":"Alent Design Solutions",
    "wof:placetype":"venue"
},
  "geometry": {"coordinates":[-118.388462,46.04462],"type":"Point"}
}