{
  "type": "Feature",
  "properties": {
    "addr:full":"14313 Madison Ave NE Bainbridge Island WA 98110",
    "addr:housenumber":"14313",
    "addr:postcode":"98110",
    "addr:street":"Madison Ave Ne",
    "iso:country":"US",
    "sg:address":"14313 Madison Ave NE",
    "sg:city":"Bainbridge Island",
    "sg:classifiers":[
        {
            "category":"Retail",
            "subcategory":"Portrait Studio",
            "type":"Services"
        }
    ],
    "sg:phone":"+1 206 842 4480",
    "sg:postcode":"98110",
    "sg:province":"WA",
    "sg:tags":[
        "photo"
    ],
    "wof:name":"Charmelle Pool Fine Portraitur",
    "wof:placetype":"venue"
},
  "geometry": {"coordinates":[-122.522614,47.693704],"type":"Point"}
}