{
  "type": "Feature",
  "properties": {
    "addr:full":"2522 N Proctor St 454 Tacoma WA 98406",
    "addr:housenumber":"2522;454",
    "addr:postcode":"98406",
    "addr:street":"N Proctor St",
    "iso:country":"US",
    "sg:address":"2522 N Proctor St 454",
    "sg:city":"Tacoma",
    "sg:classifiers":[
        {
            "category":"Professional",
            "subcategory":"Computer Services",
            "type":"Services"
        }
    ],
    "sg:phone":"+1 253 566 9155",
    "sg:postcode":"98406",
    "sg:province":"WA",
    "sg:tags":[
        "consultant",
        "designer",
        "system"
    ],
    "wof:name":"My Network Company",
    "wof:placetype":"venue"
},
  "geometry": {"coordinates":[-122.488865,47.270339],"type":"Point"}
}