{
  "type": "Feature",
  "properties": {
    "addr:full":"5119 Brooklyn Ln Pasco WA 99301",
    "addr:housenumber":"5119",
    "addr:postcode":"99301",
    "addr:street":"Brooklyn Ln",
    "iso:country":"US",
    "sg:address":"5119 Brooklyn Ln",
    "sg:city":"Pasco",
    "sg:classifiers":[
        {
            "category":"Home & Garden",
            "subcategory":"Carpets & Floor Coverings",
            "type":"Retail Goods"
        }
    ],
    "sg:phone":"+1 509 539 2520",
    "sg:postcode":"99301",
    "sg:province":"WA",
    "wof:name":"Brandons Floor Covering",
    "wof:placetype":"venue"
},
  "geometry": {"coordinates":[-119.175753,46.274038],"type":"Point"}
}