{
  "type": "Feature",
  "properties": {
    "addr:full":"2017 23rd Ave W Seattle WA 98199",
    "addr:housenumber":"2017",
    "addr:postcode":"98199",
    "addr:street":"23Rd Ave W",
    "iso:country":"US",
    "sg:address":"2017 23rd Ave W",
    "sg:city":"Seattle",
    "sg:classifiers":[
        {
            "category":"Shopping",
            "subcategory":"Florist",
            "type":"Retail Goods"
        }
    ],
    "sg:phone":"+1 206 286 8466",
    "sg:postcode":"98199",
    "sg:province":"WA",
    "wof:name":"Glass Flowers",
    "wof:placetype":"venue"
},
  "geometry": {"coordinates":[-122.386375,47.637062],"type":"Point"}
}