{
  "type": "Feature",
  "properties": {
    "iso:country":"US",
    "sg:address":"17010 80th Street Kp S",
    "sg:city":"Longbranch",
    "sg:classifiers":[
        {
            "category":"Restaurant",
            "type":"Food & Drink"
        }
    ],
    "sg:phone":"+1 253 884 3534",
    "sg:postcode":"98351",
    "sg:province":"WA",
    "sg:tags":[
        "eating"
    ],
    "wof:name":"Purely Country",
    "wof:placetype":"venue"
},
  "geometry": {"coordinates":[-122.76827400000001,47.184419],"type":"Point"}
}