{
  "type": "Feature",
  "properties": {
    "addr:full":"8116 NE 69th St Vancouver WA 98662",
    "addr:housenumber":"8116",
    "addr:postcode":"98662",
    "addr:street":"Ne 69Th St",
    "iso:country":"US",
    "sg:address":"8116 NE 69th St",
    "sg:city":"Vancouver",
    "sg:classifiers":[
        {
            "category":"Professional",
            "subcategory":"Detective & Security Services",
            "type":"Services"
        }
    ],
    "sg:phone":"+1 360 254 0491",
    "sg:postcode":"98662",
    "sg:province":"WA",
    "sg:tags":[
        "private",
        "investigator"
    ],
    "wof:name":"James Reeds",
    "wof:placetype":"venue"
},
  "geometry": {"coordinates":[-122.58957100000001,45.671815],"type":"Point"}
}