{
  "type": "Feature",
  "properties": {
    "addr:full":"1011 Foster Ave Bridgeport WA 98813",
    "addr:housenumber":"1011",
    "addr:postcode":"98813",
    "addr:street":"Foster Ave",
    "iso:country":"US",
    "sg:address":"1011 Foster Ave",
    "sg:city":"Bridgeport",
    "sg:classifiers":[
        {
            "category":"Restaurant",
            "type":"Food & Drink"
        }
    ],
    "sg:phone":"+1 509 686 0408",
    "sg:postcode":"98813",
    "sg:province":"WA",
    "sg:tags":[
        "house",
        "steak"
    ],
    "wof:name":"El Petate Steakhouse",
    "wof:placetype":"venue"
},
  "geometry": {"coordinates":[-119.67735999999999,48.010281],"type":"Point"}
}