{
  "type": "Feature",
  "properties": {
    "addr:full":"2150 N 107th St Ste 345 Seattle WA 98133",
    "addr:housenumber":"2150",
    "addr:postcode":"98133",
    "addr:street":"N 107Th St Ste 345",
    "iso:country":"US",
    "sg:address":"2150 N 107th St Ste 345",
    "sg:city":"Seattle",
    "sg:classifiers":[
        {
            "category":"Health Services",
            "subcategory":"Clinic",
            "type":"Services"
        }
    ],
    "sg:phone":"+1 206 364 6565",
    "sg:postcode":"98133",
    "sg:province":"WA",
    "sg:tags":[
        "counseling",
        "mental"
    ],
    "wof:name":"Child Psychology Northwest",
    "wof:placetype":"venue"
},
  "geometry": {"coordinates":[-122.333,47.706799],"type":"Point"}
}