{
  "type": "Feature",
  "properties": {
    "addr:full":"805 Broadway St Vancouver WA 98660",
    "addr:housenumber":"805",
    "addr:postcode":"98660",
    "addr:street":"Broadway St",
    "iso:country":"US",
    "sg:address":"805 Broadway St",
    "sg:city":"Vancouver",
    "sg:classifiers":[
        {
            "category":"Professional",
            "subcategory":"Lawyer & Legal Services",
            "type":"Services"
        }
    ],
    "sg:phone":"+1 503 283 3393",
    "sg:postcode":"98660",
    "sg:province":"WA",
    "wof:name":"Landerholm Memovich Lansverk & Whitesides PS",
    "wof:placetype":"venue"
},
  "geometry": {"coordinates":[-122.66995199999999,45.6276],"type":"Point"}
}