{
  "type": "Feature",
  "properties": {
    "addr:full":"21907 64th Ave W Mountlake Ter WA 98043",
    "addr:housenumber":"21907",
    "addr:postcode":"98043",
    "addr:street":"64Th Ave W Mountlake Ter",
    "iso:country":"US",
    "sg:address":"21907 64th Ave W",
    "sg:city":"Mountlake Ter",
    "sg:classifiers":[
        {
            "category":"Insurance",
            "subcategory":"Insurance Agent",
            "type":"Services"
        }
    ],
    "sg:phone":"+1 425 775 2218",
    "sg:postcode":"98043",
    "sg:province":"WA",
    "wof:name":"Farmers Insurance Group",
    "wof:placetype":"venue"
},
  "geometry": {"coordinates":[-122.31922299999999,47.800269],"type":"Point"}
}