{
  "type": "Feature",
  "properties": {
    "addr:full":"1410 Ave D Snohomish WA 98290",
    "addr:postcode":"98290",
    "addr:street":"1410 Ave D",
    "iso:country":"US",
    "sg:address":"1410 Ave D",
    "sg:city":"Snohomish",
    "sg:classifiers":[
        {
            "category":"Retail",
            "subcategory":"Auto Repair",
            "type":"Services"
        }
    ],
    "sg:phone":"+1 360 568 8811",
    "sg:postcode":"98290",
    "sg:province":"WA",
    "sg:tags":[
        "body",
        "automobile",
        "painting",
        "repairing"
    ],
    "wof:name":"Precision Collision",
    "wof:placetype":"venue"
},
  "geometry": {"coordinates":[-122.09972399999999,47.929232],"type":"Point"}
}