{
  "type": "Feature",
  "properties": {
    "addr:full":"550 160th Ave SE Bellevue WA 98004",
    "addr:housenumber":"550",
    "addr:postcode":"98004",
    "addr:street":"160Th Ave Se",
    "iso:country":"US",
    "sg:address":"550 160th Ave SE",
    "sg:city":"Bellevue",
    "sg:classifiers":[
        {
            "category":"Building & Trades",
            "subcategory":"Locksmith",
            "type":"Services"
        }
    ],
    "sg:phone":"+1 425 605 5489",
    "sg:postcode":"98004",
    "sg:province":"WA",
    "sg:tags":[
        "key"
    ],
    "wof:name":"24 Hour Any Place Locksmith Assistance of Bellevue",
    "wof:placetype":"venue"
},
  "geometry": {"coordinates":[-122.12581400000001,47.604765],"type":"Point"}
}