{
  "type": "Feature",
  "properties": {
    "addr:full":"1124 Stevens Dr Richland WA 99354",
    "addr:housenumber":"1124",
    "addr:postcode":"99354",
    "addr:street":"Stevens Dr",
    "iso:country":"US",
    "sg:address":"1124 Stevens Dr",
    "sg:city":"Richland",
    "sg:classifiers":[
        {
            "category":"Social Services",
            "subcategory":"Child Care",
            "type":"Services"
        },
        {
            "category":"Education",
            "subcategory":"Preschool",
            "type":"Public Place"
        },
        {
            "category":"Education",
            "subcategory":"School",
            "type":"Public Place"
        }
    ],
    "sg:phone":"+1 509 943 1597",
    "sg:postcode":"99354",
    "sg:province":"WA",
    "sg:tags":[
        "k-",
        "kindergarten",
        "nursery",
        "private",
        "interest",
        "religious",
        "day"
    ],
    "wof:name":"Cupid Day Care",
    "wof:placetype":"venue"
},
  "geometry": {"coordinates":[-119.28442800000001,46.283246],"type":"Point"}
}