{
  "type": "Feature",
  "properties": {
    "addr:full":"5718 1st Ave S Seattle WA 98108",
    "addr:housenumber":"5718",
    "addr:postcode":"98108",
    "addr:street":"1St Ave S",
    "iso:country":"US",
    "sg:address":"5718 1st Ave S",
    "sg:city":"Seattle",
    "sg:classifiers":[
        {
            "category":"Autos & Motor Vehicles",
            "subcategory":"Automobile Sales",
            "type":"Retail Goods"
        },
        {
            "category":"Autos & Motor Vehicles",
            "subcategory":"Auto Supplies",
            "type":"Retail Goods"
        },
        {
            "category":"Wholesale",
            "subcategory":"Auto Parts",
            "type":"Manufacturing & Wholesale Goods"
        }
    ],
    "sg:phone":"+1 206 762 5111",
    "sg:postcode":"98108",
    "sg:province":"WA",
    "sg:tags":[
        "shop",
        "tire",
        "automotive",
        "body",
        "supply-wholesale",
        "equipment",
        "manufacturer"
    ],
    "sg:website":"http://nwsalesgroup.reachlocal.com/?scid=1876614",
    "wof:name":"Northwest Sales Group Inc",
    "wof:placetype":"venue"
},
  "geometry": {"coordinates":[-122.333778,47.551322],"type":"Point"}
}