{
  "type": "Feature",
  "properties": {
    "addr:full":"30120 SE Retreat Kanasket Rd Ravensdale WA 98051",
    "addr:postcode":"30120;98051",
    "addr:street":"Se Retreat Kanasket Rd",
    "iso:country":"US",
    "sg:address":"30120 SE Retreat Kanasket Rd",
    "sg:city":"Ravensdale",
    "sg:classifiers":[
        {
            "category":"Retail",
            "subcategory":"Auto Repair",
            "type":"Services"
        }
    ],
    "sg:phone":"+1 425 433 0712",
    "sg:postcode":"98051",
    "sg:province":"WA",
    "sg:tags":[
        "scooters-repairing",
        "motorcycle",
        "motor"
    ],
    "wof:name":"Custom Classic",
    "wof:placetype":"venue"
},
  "geometry": {"coordinates":[-121.94107099999999,47.339448],"type":"Point"}
}