{
  "type": "Feature",
  "properties": {
    "addr:full":"15802 Meridian E Puyallup WA 98375",
    "addr:housenumber":"15802",
    "addr:postcode":"98375",
    "addr:street":"Meridian E",
    "iso:country":"US",
    "sg:address":"15802 Meridian E",
    "sg:city":"Puyallup",
    "sg:classifiers":[
        {
            "category":"Restaurant",
            "type":"Food & Drink"
        }
    ],
    "sg:menulink":"http://www.allmenus.com/wa/graham-thrift/235521-taco-time/menu/",
    "sg:phone":"+1 253 841 2118",
    "sg:postcode":"98375",
    "sg:province":"WA",
    "sg:tags":[
        "american",
        "mexican",
        "tex-mex"
    ],
    "wof:name":"Taco Time",
    "wof:placetype":"venue"
},
  "geometry": {"coordinates":[-122.293903,47.11232],"type":"Point"}
}