{
  "type": "Feature",
  "properties": {
    "iso:country":"US",
    "sg:address":"255 State Rte 115",
    "sg:city":"Ocean Shores",
    "sg:classifiers":[
        {
            "category":"Recreation",
            "type":"Entertainment"
        }
    ],
    "sg:phone":"+1 360 289 0194",
    "sg:postcode":"98569",
    "sg:province":"WA",
    "sg:tags":[
        "stable"
    ],
    "wof:name":"Nan-Sea Stables Inc",
    "wof:placetype":"venue"
},
  "geometry": {"coordinates":[-124.156766,47.017153],"type":"Point"}
}