{
  "type": "Feature",
  "properties": {
    "addr:full":"33216 Pacific Hwy S Federal Way WA 98003",
    "addr:housenumber":"33216",
    "addr:postcode":"98003",
    "addr:street":"Pacific Hwy S Federal Way",
    "iso:country":"US",
    "sg:address":"33216 Pacific Hwy S",
    "sg:city":"Federal Way",
    "sg:classifiers":[
        {
            "category":"Autos & Motor Vehicles",
            "subcategory":"Automobile Sales",
            "type":"Retail Goods"
        }
    ],
    "sg:phone":"+1 253 838 5534",
    "sg:postcode":"98003",
    "sg:province":"WA",
    "sg:tags":[
        "car",
        "dealer"
    ],
    "wof:name":"Evergreen Sales & Leasing",
    "wof:placetype":"venue"
},
  "geometry": {"coordinates":[-122.313332,47.304705],"type":"Point"}
}