{
  "type": "Feature",
  "properties": {
    "addr:full":"4306 SW Edmunds St Seattle WA 98116",
    "addr:housenumber":"4306",
    "addr:postcode":"98116",
    "addr:street":"Sw Edmunds St",
    "iso:country":"US",
    "sg:address":"4306 SW Edmunds St",
    "sg:city":"Seattle",
    "sg:classifiers":[
        {
            "category":"Banks & Credit Unions",
            "subcategory":"Bank",
            "type":"Services"
        },
        {
            "category":"Banks & Credit Unions",
            "subcategory":"Financial Services",
            "type":"Services"
        }
    ],
    "sg:phone":"+1 206 461 3451",
    "sg:postcode":"98116",
    "sg:province":"WA",
    "sg:tags":[
        "saving",
        "loan",
        "commercial"
    ],
    "sg:website":"https://www.chase.com/",
    "wof:name":"CHASE Bank",
    "wof:placetype":"venue"
},
  "geometry": {"coordinates":[-122.38695300000001,47.559319],"type":"Point"}
}