{
  "type": "Feature",
  "properties": {
    "addr:full":"3311 Bethel Rd SE Port Orchard WA 98366",
    "addr:housenumber":"3311",
    "addr:postcode":"98366",
    "addr:street":"Bethel Rd Se",
    "iso:country":"US",
    "sg:address":"3311 Bethel Rd SE",
    "sg:city":"Port Orchard",
    "sg:classifiers":[
        {
            "category":"Autos & Motor Vehicles",
            "subcategory":"Auto Supplies",
            "type":"Retail Goods"
        }
    ],
    "sg:phone":"+1 360 874 0340",
    "sg:postcode":"98366",
    "sg:province":"WA",
    "sg:tags":[
        "parts"
    ],
    "wof:name":"Schucks Auto Supply 4375",
    "wof:placetype":"venue"
},
  "geometry": {"coordinates":[-122.631074,47.518243],"type":"Point"}
}