{
  "type": "Feature",
  "properties": {
    "addr:full":"40502 228th Way SE Enumclaw WA 98022",
    "addr:housenumber":"40502",
    "addr:postcode":"98022",
    "addr:street":"228Th Way Se",
    "iso:country":"US",
    "sg:address":"40502 228th Way SE",
    "sg:city":"Enumclaw",
    "sg:classifiers":[
        {
            "category":"Professional",
            "type":"Services"
        }
    ],
    "sg:phone":"+1 360 825 7501",
    "sg:postcode":"98022",
    "sg:province":"WA",
    "wof:name":"Howard J Pickering",
    "wof:placetype":"venue"
},
  "geometry": {"coordinates":[-122.040195,47.239295],"type":"Point"}
}