{
  "type": "Feature",
  "properties": {
    "addr:full":"601 W Chestnut St Bellingham WA 98225",
    "addr:housenumber":"601",
    "addr:postcode":"98225",
    "addr:street":"W Chestnut St",
    "iso:country":"US",
    "sg:address":"601 W Chestnut St",
    "sg:city":"Bellingham",
    "sg:classifiers":[
        {
            "category":"Manufacturing",
            "subcategory":"Apparel",
            "type":"Manufacturing & Wholesale Goods"
        }
    ],
    "sg:phone":"+1 360 676 4305",
    "sg:postcode":"98225",
    "sg:province":"WA",
    "sg:tags":[
        "canvas",
        "hat",
        "mfg"
    ],
    "wof:name":"Watership Trading Companie",
    "wof:placetype":"venue"
},
  "geometry": {"coordinates":[-122.48693900000001,48.752701],"type":"Point"}
}