{
  "type": "Feature",
  "properties": {
    "addr:full":"3716 Main St Union Gap WA 98903",
    "addr:housenumber":"3716",
    "addr:postcode":"98903",
    "addr:street":"Main St",
    "iso:country":"US",
    "sg:address":"3716 Main St",
    "sg:city":"Union Gap",
    "sg:classifiers":[
        {
            "category":"Bars & Pubs",
            "type":"Food & Drink"
        }
    ],
    "sg:phone":"+1 509 452 2864",
    "sg:postcode":"98903",
    "sg:province":"WA",
    "sg:tags":[
        "tavern"
    ],
    "wof:name":"Old Town Pump",
    "wof:placetype":"venue"
},
  "geometry": {"coordinates":[-120.47543,46.549981],"type":"Point"}
}