{
  "type": "Feature",
  "properties": {
    "addr:full":"1001 W 25th Ave Spokane WA 99203",
    "addr:housenumber":"1001",
    "addr:postcode":"99203",
    "addr:street":"W 25Th Ave",
    "iso:country":"US",
    "sg:address":"1001 W 25th Ave",
    "sg:city":"Spokane",
    "sg:classifiers":[
        {
            "category":"Personal",
            "subcategory":"Beauty Salon",
            "type":"Services"
        }
    ],
    "sg:phone":"+1 509 624 1412",
    "sg:postcode":"99203",
    "sg:province":"WA",
    "sg:tags":[
        "shop"
    ],
    "wof:name":"Alicia & Assoc Hair Studio",
    "wof:placetype":"venue"
},
  "geometry": {"coordinates":[-117.42799599999999,47.631769],"type":"Point"}
}