{
  "type": "Feature",
  "properties": {
    "iso:country":"US",
    "sg:address":"4112 University Way NE",
    "sg:city":"Seattle",
    "sg:classifiers":[
        {
            "category":"Restaurant",
            "type":"Food & Drink"
        }
    ],
    "sg:phone":"+1 206 632 6506",
    "sg:postcode":"98105",
    "sg:province":"WA",
    "sg:tags":[
        "eating"
    ],
    "wof:name":"Cafe Zoe",
    "wof:placetype":"venue"
},
  "geometry": {"coordinates":[-122.313137,47.65813],"type":"Point"}
}