{
  "type": "Feature",
  "properties": {
    "addr:full":"8012 South Tacoma Way Ste 27 Lakewood WA 98499",
    "addr:housenumber":"8012",
    "addr:postcode":"98499",
    "addr:street":"South Tacoma Way Ste 27",
    "iso:country":"US",
    "sg:address":"8012 South Tacoma Way Ste 27",
    "sg:city":"Lakewood",
    "sg:classifiers":[
        {
            "category":"Wholesale",
            "subcategory":"Computers",
            "type":"Manufacturing & Wholesale Goods"
        },
        {
            "category":"Professional",
            "subcategory":"Computer Services",
            "type":"Services"
        }
    ],
    "sg:phone":"+1 253 589 4995",
    "sg:postcode":"98499",
    "sg:province":"WA",
    "sg:tags":[
        "repair"
    ],
    "wof:name":"B & I Public Market Place",
    "wof:placetype":"venue"
},
  "geometry": {"coordinates":[-122.483969,47.18453],"type":"Point"}
}