{
  "type": "Feature",
  "properties": {
    "addr:full":"2007 NE Kresky Ave Chehalis WA 98532",
    "addr:housenumber":"2007",
    "addr:postcode":"98532",
    "addr:street":"Ne Kresky Ave",
    "iso:country":"US",
    "sg:address":"2007 NE Kresky Ave",
    "sg:city":"Chehalis",
    "sg:classifiers":[
        {
            "category":"Building & Trades",
            "subcategory":"Construction",
            "type":"Services"
        }
    ],
    "sg:phone":"+1 360 748 0238",
    "sg:postcode":"98532",
    "sg:province":"WA",
    "sg:tags":[
        "marking",
        "maintenance",
        "parking"
    ],
    "wof:name":"Chehalis City Public Works",
    "wof:placetype":"venue"
},
  "geometry": {"coordinates":[-122.955276,46.687483],"type":"Point"}
}