{
  "type": "Feature",
  "properties": {
    "addr:full":"700 NW Gilman Blvd #452 Issaquah WA 98027",
    "addr:housenumber":"700",
    "addr:postcode":"98027",
    "addr:street":"Nw Gilman Blvd # 452",
    "iso:country":"US",
    "sg:address":"700 NW Gilman Blvd #452",
    "sg:city":"Issaquah",
    "sg:classifiers":[
        {
            "category":"Building & Trades",
            "subcategory":"Construction",
            "type":"Services"
        },
        {
            "category":"Home & Garden",
            "subcategory":"Carpets & Floor Coverings",
            "type":"Retail Goods"
        }
    ],
    "sg:phone":"+1 888 386 0881",
    "sg:postcode":"98027",
    "sg:province":"WA",
    "sg:tags":[
        "refinishing",
        "flooring",
        "contractor",
        "tile-contractors",
        "sealing",
        "tile-cleaning"
    ],
    "sg:website":"http://local.ingenio.com/Listings/Details.aspx?NUM=a%3a10079939%3a13%3a4859924%3a14%3a0%3a7",
    "wof:name":"Semco Seattle Home Tech Design",
    "wof:placetype":"venue"
},
  "geometry": {"coordinates":[-122.046829,47.543179],"type":"Point"}
}