{
  "type": "Feature",
  "properties": {
    "addr:full":"14700 E Indiana Ave Spokane WA 99216",
    "addr:housenumber":"14700",
    "addr:postcode":"99216",
    "addr:street":"E Indiana Ave",
    "iso:country":"US",
    "sg:address":"14700 E Indiana Ave",
    "sg:city":"Spokane",
    "sg:classifiers":[
        {
            "category":"Restaurant",
            "type":"Food & Drink"
        }
    ],
    "sg:menulink":"http://www.allmenus.com/wa/spokane/195761-wendys/menu/",
    "sg:phone":"+1 509 893 1004",
    "sg:postcode":"99216",
    "sg:province":"WA",
    "sg:tags":[
        "burger",
        "american",
        "soup"
    ],
    "wof:name":"Wendy's",
    "wof:placetype":"venue"
},
  "geometry": {"coordinates":[-117.209653,47.676152],"type":"Point"}
}