{
  "type": "Feature",
  "properties": {
    "addr:full":"6012 26th Ave NE Seattle WA 98115",
    "addr:housenumber":"6012",
    "addr:postcode":"98115",
    "addr:street":"26Th Ave Ne",
    "iso:country":"US",
    "sg:address":"6012 26th Ave NE",
    "sg:city":"Seattle",
    "sg:classifiers":[
        {
            "category":"Professional",
            "subcategory":"Art Services",
            "type":"Services"
        }
    ],
    "sg:phone":"+1 206 524 5087",
    "sg:postcode":"98115",
    "sg:province":"WA",
    "sg:tags":[
        "commercial",
        "design"
    ],
    "wof:name":"Latent Image",
    "wof:placetype":"venue"
},
  "geometry": {"coordinates":[-122.299515,47.673854],"type":"Point"}
}