{
  "type": "Feature",
  "properties": {
    "addr:full":"4611 Tumwater Valley Dr SE Olympia WA 98501",
    "addr:housenumber":"4611",
    "addr:postcode":"98501",
    "addr:street":"Tumwater Valley Dr Se",
    "iso:country":"US",
    "sg:address":"4611 Tumwater Valley Dr SE",
    "sg:city":"Olympia",
    "sg:classifiers":[
        {
            "category":"Shopping",
            "subcategory":"Bicycles & Sporting Goods",
            "type":"Retail Goods"
        }
    ],
    "sg:phone":"+1 360 943 9500",
    "sg:postcode":"98501",
    "sg:province":"WA",
    "wof:name":"Tumwater Valley Golf Shop",
    "wof:placetype":"venue"
},
  "geometry": {"coordinates":[-122.904342,47.008581],"type":"Point"}
}