{
  "type": "Feature",
  "properties": {
    "addr:full":"24 N Stone St Ste D Spokane WA 99202",
    "addr:housenumber":"24",
    "addr:postcode":"99202",
    "addr:street":"N Stone St Ste D",
    "iso:country":"US",
    "sg:address":"24 N Stone St Ste D",
    "sg:city":"Spokane",
    "sg:classifiers":[
        {
            "category":"Manufacturing",
            "subcategory":"Buildings",
            "type":"Manufacturing & Wholesale Goods"
        },
        {
            "category":"Building & Trades",
            "subcategory":"Construction",
            "type":"Services"
        }
    ],
    "sg:phone":"+1 509 535 7574",
    "sg:postcode":"99202",
    "sg:province":"WA",
    "sg:tags":[
        "industrial",
        "consultant",
        "builder",
        "contractor",
        "contractors-commercial",
        "home"
    ],
    "wof:name":"Barnes Construction Services",
    "wof:placetype":"venue"
},
  "geometry": {"coordinates":[-117.37672000000001,47.657498],"type":"Point"}
}