{
  "type": "Feature",
  "properties": {
    "addr:full":"3104 36th St SE Puyallup WA 98374",
    "addr:housenumber":"3104",
    "addr:postcode":"98374",
    "addr:street":"36Th St Se",
    "iso:country":"US",
    "sg:address":"3104 36th St SE",
    "sg:city":"Puyallup",
    "sg:classifiers":[
        {
            "category":"Organizations",
            "subcategory":"Community Association",
            "type":"Services"
        }
    ],
    "sg:phone":"+1 253 840 1572",
    "sg:postcode":"98374",
    "sg:province":"WA",
    "wof:name":"Kiwanis Club Good Sam Puyal",
    "wof:placetype":"venue"
},
  "geometry": {"coordinates":[-122.246443,47.165189],"type":"Point"}
}