{
  "type": "Feature",
  "properties": {
    "addr:full":"510 14th St Benton City WA 99320",
    "addr:housenumber":"510",
    "addr:postcode":"99320",
    "addr:street":"14Th St",
    "iso:country":"US",
    "sg:address":"510 14th St",
    "sg:city":"Benton City",
    "sg:classifiers":[
        {
            "category":"Social Services",
            "subcategory":"Adult Care",
            "type":"Services"
        }
    ],
    "sg:phone":"+1 509 588 3094",
    "sg:postcode":"99320",
    "sg:province":"WA",
    "sg:tags":[
        "organization",
        "senior",
        "citizen"
    ],
    "wof:name":"Meals On Wheels",
    "wof:placetype":"venue"
},
  "geometry": {"coordinates":[-119.494647,46.261213],"type":"Point"}
}