{
  "type": "Feature",
  "properties": {
    "addr:full":"14733 NE 8th St Bellevue WA 98007",
    "addr:housenumber":"14733",
    "addr:postcode":"98007",
    "addr:street":"Ne 8Th St",
    "iso:country":"US",
    "sg:address":"14733 NE 8th St",
    "sg:city":"Bellevue",
    "sg:classifiers":[
        {
            "category":"Food & Beverages",
            "subcategory":"Specialty",
            "type":"Retail Goods"
        }
    ],
    "sg:phone":"+1 425 957 0787",
    "sg:postcode":"98007",
    "sg:province":"WA",
    "sg:tags":[
        "health",
        "market"
    ],
    "sg:website":"www.supersup.com",
    "wof:name":"Seattle Super Supplements",
    "wof:placetype":"venue"
},
  "geometry": {"coordinates":[-122.14408299999999,47.617068],"type":"Point"}
}