{
  "type": "Feature",
  "properties": {
    "addr:full":"1710 S Pacific Ave Kelso WA 98626",
    "addr:housenumber":"1710",
    "addr:postcode":"98626",
    "addr:street":"S Pacific Ave",
    "iso:country":"US",
    "sg:address":"1710 S Pacific Ave",
    "sg:city":"Kelso",
    "sg:classifiers":[
        {
            "category":"Home & Garden",
            "subcategory":"Household Appliances",
            "type":"Retail Goods"
        },
        {
            "category":"Building & Trades",
            "subcategory":"Construction",
            "type":"Services"
        },
        {
            "category":"Professional",
            "subcategory":"Engineering",
            "type":"Services"
        }
    ],
    "sg:phone":"+1 360 425 3320",
    "sg:postcode":"98626",
    "sg:province":"WA",
    "sg:tags":[
        "repair",
        "systems-repairing",
        "system",
        "specialty",
        "equipment",
        "pump",
        "heating",
        "contractor",
        "heat",
        "air conditioning"
    ],
    "sg:website":"http://www.twincityserviceco.com",
    "wof:name":"Twin City Service Co",
    "wof:placetype":"venue"
},
  "geometry": {"coordinates":[-122.913872,46.128728],"type":"Point"}
}