{
  "type": "Feature",
  "properties": {
    "addr:full":"32 Elma McCleary Rd Elma WA 98541",
    "addr:housenumber":"32",
    "addr:postcode":"98541",
    "addr:street":"Elma Mccleary Rd",
    "iso:country":"US",
    "sg:address":"32 Elma McCleary Rd",
    "sg:city":"Elma",
    "sg:classifiers":[
        {
            "category":"Professional",
            "subcategory":"Computer Services",
            "type":"Services"
        }
    ],
    "sg:phone":"+1 360 482 4166",
    "sg:postcode":"98541",
    "sg:province":"WA",
    "sg:tags":[
        "website",
        "design"
    ],
    "wof:name":"Grays Harbor Tourism",
    "wof:placetype":"venue"
},
  "geometry": {"coordinates":[-123.38205000000001,47.01225],"type":"Point"}
}