{
  "type": "Feature",
  "properties": {
    "addr:full":"13425 Hwy 99 Everett WA 98204",
    "addr:housenumber":"13425",
    "addr:postcode":"98204",
    "addr:street":"Hwy 99",
    "iso:country":"US",
    "sg:address":"13425 Hwy 99",
    "sg:city":"Everett",
    "sg:classifiers":[
        {
            "category":"Retail",
            "subcategory":"Auto Repair",
            "type":"Services"
        }
    ],
    "sg:phone":"+1 425 743 1503",
    "sg:postcode":"98204",
    "sg:province":"WA",
    "sg:tags":[
        "repairing",
        "automobile"
    ],
    "wof:name":"J & R Auto Repair",
    "wof:placetype":"venue"
},
  "geometry": {"coordinates":[-122.270132,47.87669],"type":"Point"}
}