{
  "type": "Feature",
  "properties": {
    "addr:full":"15511 N Howe Rd Mead WA 99021",
    "addr:housenumber":"15511",
    "addr:postcode":"99021",
    "addr:street":"N Howe Rd Mead",
    "iso:country":"US",
    "sg:address":"15511 N Howe Rd",
    "sg:city":"Mead",
    "sg:classifiers":[
        {
            "category":"Organizations",
            "subcategory":"Religious Organization",
            "type":"Services"
        }
    ],
    "sg:phone":"+1 509 468 4363",
    "sg:postcode":"99021",
    "sg:province":"WA",
    "sg:tags":[
        "church"
    ],
    "sg:website":"www.timberview.org",
    "wof:name":"Timberview Christian Fellowshp",
    "wof:placetype":"venue"
},
  "geometry": {"coordinates":[-117.328334,47.798002],"type":"Point"}
}