{
  "type": "Feature",
  "properties": {
    "addr:full":"7717 Greenwood Avenue N Seattle WA 98103",
    "addr:housenumber":"7717",
    "addr:postcode":"98103",
    "addr:street":"Greenwood Avenue N",
    "iso:country":"US",
    "sg:address":"7717 Greenwood Avenue N",
    "sg:city":"Seattle",
    "sg:classifiers":[
        {
            "category":"Restaurant",
            "type":"Food & Drink"
        }
    ],
    "sg:phone":"+1 206 784 5348",
    "sg:postcode":"98103",
    "sg:province":"WA",
    "sg:tags":[
        "breakfast",
        "brunch"
    ],
    "wof:name":"Pete's Egg Nest",
    "wof:placetype":"venue"
},
  "geometry": {"coordinates":[-122.35530900000001,47.684895],"type":"Point"}
}