{
  "type": "Feature",
  "properties": {
    "addr:full":"1703 Harvard Ave Seattle WA 98122",
    "addr:housenumber":"1703",
    "addr:postcode":"98122",
    "addr:street":"Harvard Ave",
    "iso:country":"US",
    "sg:address":"1703 Harvard Ave",
    "sg:city":"Seattle",
    "sg:classifiers":[
        {
            "category":"Communications",
            "subcategory":"Film & Video Production",
            "type":"Services"
        }
    ],
    "sg:phone":"+1 206 860 3919",
    "sg:postcode":"98122",
    "sg:province":"WA",
    "sg:tags":[
        "motion"
    ],
    "wof:name":"Negative Image Productions",
    "wof:placetype":"venue"
},
  "geometry": {"coordinates":[-122.322245,47.617535],"type":"Point"}
}