{
  "type": "Feature",
  "properties": {
    "addr:full":"9553 Old Pacific Hwy Woodland WA 98674",
    "addr:housenumber":"9553",
    "addr:postcode":"98674",
    "addr:street":"Old Pacific Hwy",
    "iso:country":"US",
    "sg:address":"9553 Old Pacific Hwy",
    "sg:city":"Woodland",
    "sg:classifiers":[
        {
            "category":"Wholesale",
            "subcategory":"Auto Parts",
            "type":"Manufacturing & Wholesale Goods"
        }
    ],
    "sg:phone":"+1 360 225 8813",
    "sg:postcode":"98674",
    "sg:province":"WA",
    "sg:tags":[
        "used"
    ],
    "wof:name":"Sargents 4x4 Bronco Shop Inc",
    "wof:placetype":"venue"
},
  "geometry": {"coordinates":[-122.74657999999999,45.920455],"type":"Point"}
}