{
  "type": "Feature",
  "properties": {
    "addr:full":"312 E Manitoba Ave Ellensburg WA 98926",
    "addr:housenumber":"312",
    "addr:postcode":"98926",
    "addr:street":"E Manitoba Ave",
    "iso:country":"US",
    "sg:address":"312 E Manitoba Ave",
    "sg:city":"Ellensburg",
    "sg:classifiers":[
        {
            "category":"Building & Trades",
            "subcategory":"Construction",
            "type":"Services"
        }
    ],
    "sg:phone":"+1 509 899 4340",
    "sg:postcode":"98926",
    "sg:province":"WA",
    "sg:tags":[
        "painter"
    ],
    "wof:name":"Ellensburg Wallworks",
    "wof:placetype":"venue"
},
  "geometry": {"coordinates":[-120.544438,46.988286],"type":"Point"}
}