{
  "type": "Feature",
  "properties": {
    "addr:full":"2110 N Pacific St Seattle WA 98103",
    "addr:housenumber":"2110",
    "addr:postcode":"98103",
    "addr:street":"N Pacific St",
    "iso:country":"US",
    "sg:address":"2110 N Pacific St",
    "sg:city":"Seattle",
    "sg:classifiers":[
        {
            "category":"Professional",
            "subcategory":"Business Services",
            "type":"Services"
        }
    ],
    "sg:phone":"+1 206 762 7414",
    "sg:postcode":"98103",
    "sg:province":"WA",
    "sg:tags":[
        "broker"
    ],
    "wof:name":"Fortune Oil Co",
    "wof:placetype":"venue"
},
  "geometry": {"coordinates":[-122.332638,47.648663],"type":"Point"}
}