{
  "type": "Feature",
  "properties": {
    "addr:full":"9215 58th Avenue Ct E Puyallup WA 98371",
    "addr:housenumber":"9215",
    "addr:postcode":"98371",
    "addr:street":"58Th Avenue Ct E",
    "iso:country":"US",
    "sg:address":"9215 58th Avenue Ct E",
    "sg:city":"Puyallup",
    "sg:classifiers":[
        {
            "category":"Food & Beverages",
            "subcategory":"Specialty",
            "type":"Retail Goods"
        }
    ],
    "sg:phone":"+1 253 848 8844",
    "sg:postcode":"98371",
    "sg:province":"WA",
    "sg:tags":[
        "herb"
    ],
    "wof:name":"Ingrid Kim",
    "wof:placetype":"venue"
},
  "geometry": {"coordinates":[-122.351089,47.175092],"type":"Point"}
}