{
  "type": "Feature",
  "properties": {
    "addr:full":"240 Winslow Way E Bainbridge Island WA 98110",
    "addr:housenumber":"240",
    "addr:postcode":"98110",
    "addr:street":"Winslow Way E",
    "iso:country":"US",
    "sg:address":"240 Winslow Way E",
    "sg:city":"Bainbridge Island",
    "sg:classifiers":[
        {
            "category":"Home & Garden",
            "subcategory":"Hardware",
            "type":"Retail Goods"
        }
    ],
    "sg:phone":"+1 206 842 3101",
    "sg:postcode":"98110",
    "sg:province":"WA",
    "wof:name":"Winslow Hardware",
    "wof:placetype":"venue"
},
  "geometry": {"coordinates":[-122.517112,47.624931],"type":"Point"}
}