{
  "type": "Feature",
  "properties": {
    "iso:country":"US",
    "sg:address":"2105 NW 199th St",
    "sg:city":"Seattle",
    "sg:classifiers":[
        {
            "category":"Wholesale",
            "subcategory":"Groceries",
            "type":"Manufacturing & Wholesale Goods"
        }
    ],
    "sg:phone":"+1 206 542 9391",
    "sg:postcode":"98177",
    "sg:province":"WA",
    "sg:tags":[
        "wholesaler"
    ],
    "wof:name":"Douglas Y Brindle & Associates",
    "wof:placetype":"venue"
},
  "geometry": {"coordinates":[-122.38808899999999,47.773744],"type":"Point"}
}