{
  "type": "Feature",
  "properties": {
    "addr:full":"225 E Henni Rd Oak Harbor WA 98277",
    "addr:housenumber":"225",
    "addr:postcode":"98277",
    "addr:street":"E Henni Rd",
    "iso:country":"US",
    "sg:address":"225 E Henni Rd",
    "sg:city":"Oak Harbor",
    "sg:classifiers":[
        {
            "category":"Building & Trades",
            "subcategory":"Construction",
            "type":"Services"
        }
    ],
    "sg:phone":"+1 360 675 1039",
    "sg:postcode":"98277",
    "sg:province":"WA",
    "sg:tags":[
        "house"
    ],
    "wof:name":"Brians Construction",
    "wof:placetype":"venue"
},
  "geometry": {"coordinates":[-122.605684,48.36186],"type":"Point"}
}