{
  "type": "Feature",
  "properties": {
    "addr:full":"916 SE 164th Ave Vancouver WA 98683",
    "addr:housenumber":"916",
    "addr:postcode":"98683",
    "addr:street":"Se 164Th Ave",
    "iso:country":"US",
    "sg:address":"916 SE 164th Ave",
    "sg:city":"Vancouver",
    "sg:classifiers":[
        {
            "category":"Restaurant",
            "type":"Food & Drink"
        }
    ],
    "sg:menulink":"http://www.allmenus.com/wa/vancouver/5829-ruby-tuesdays/menu/",
    "sg:phone":"+1 360 896 0277",
    "sg:postcode":"98683",
    "sg:province":"WA",
    "sg:tags":[
        "burger",
        "american"
    ],
    "wof:name":"Ruby Tuesdays",
    "wof:placetype":"venue"
},
  "geometry": {"coordinates":[-122.504381,45.614605],"type":"Point"}
}