{
  "type": "Feature",
  "properties": {
    "iso:country":"US",
    "sg:address":"926 87th Ave SE",
    "sg:city":"Everett",
    "sg:classifiers":[
        {
            "category":"Building & Trades",
            "subcategory":"Construction",
            "type":"Services"
        }
    ],
    "sg:phone":"+1 425 299 7285",
    "sg:postcode":"98205",
    "sg:province":"WA",
    "sg:tags":[
        "residential"
    ],
    "wof:name":"Llgs",
    "wof:placetype":"venue"
},
  "geometry": {"coordinates":[-122.114121,47.988425],"type":"Point"}
}