{
  "type": "Feature",
  "properties": {
    "addr:full":"18103 NE 159th Ave Brush Prairie WA 98606",
    "addr:housenumber":"18103",
    "addr:postcode":"98606",
    "addr:street":"Ne 159Th Ave",
    "iso:country":"US",
    "sg:address":"18103 NE 159th Ave",
    "sg:city":"Brush Prairie",
    "sg:classifiers":[
        {
            "category":"Health Services",
            "subcategory":"Doctor",
            "type":"Services"
        }
    ],
    "sg:phone":"+1 360 666 1313",
    "sg:postcode":"98606",
    "sg:province":"WA",
    "sg:tags":[
        "physician"
    ],
    "wof:name":"Steve Kohl",
    "wof:placetype":"venue"
},
  "geometry": {"coordinates":[-122.509068,45.753371],"type":"Point"}
}