{
  "type": "Feature",
  "properties": {
    "addr:full":"3670 N County Line Rd Grandview WA 98930",
    "addr:housenumber":"3670",
    "addr:postcode":"98930",
    "addr:street":"N County Line Rd",
    "iso:country":"US",
    "sg:address":"3670 N County Line Rd",
    "sg:city":"Grandview",
    "sg:classifiers":[
        {
            "category":"Farming",
            "subcategory":"Orchard",
            "type":"Manufacturing & Wholesale Goods"
        }
    ],
    "sg:phone":"+1 509 882 1750",
    "sg:postcode":"98930",
    "sg:province":"WA",
    "sg:tags":[
        "fruit",
        "tree"
    ],
    "wof:name":"White Orchards",
    "wof:placetype":"venue"
},
  "geometry": {"coordinates":[-119.87370199999999,46.308137],"type":"Point"}
}