{
  "type": "Feature",
  "properties": {
    "addr:full":"20101 163rd Ave NE Woodinville WA 98072",
    "addr:housenumber":"20101",
    "addr:postcode":"98072",
    "addr:street":"163Rd Ave Ne",
    "iso:country":"US",
    "sg:address":"20101 163rd Ave NE",
    "sg:city":"Woodinville",
    "sg:classifiers":[
        {
            "category":"Building & Trades",
            "subcategory":"Construction",
            "type":"Services"
        }
    ],
    "sg:phone":"+1 425 481 3144",
    "sg:postcode":"98072",
    "sg:province":"WA",
    "sg:tags":[
        "house"
    ],
    "wof:name":"Metcalfe Homes",
    "wof:placetype":"venue"
},
  "geometry": {"coordinates":[-122.12253800000001,47.774759],"type":"Point"}
}