{
  "type": "Feature",
  "properties": {
    "addr:full":"23904 111th Pl SE Kent WA 98031",
    "addr:housenumber":"23904",
    "addr:postcode":"98031",
    "addr:street":"111Th Pl Se",
    "iso:country":"US",
    "sg:address":"23904 111th Pl SE",
    "sg:city":"Kent",
    "sg:classifiers":[
        {
            "category":"Health Services",
            "subcategory":"Health Practitioner",
            "type":"Services"
        }
    ],
    "sg:phone":"+1 253 854 8856",
    "sg:postcode":"98031",
    "sg:province":"WA",
    "wof:name":"Sweets Health Care Servic",
    "wof:placetype":"venue"
},
  "geometry": {"coordinates":[-122.19345,47.387806],"type":"Point"}
}