{
  "type": "Feature",
  "properties": {
    "addr:full":"1120 W Ewing St Seattle WA 98119",
    "addr:housenumber":"1120",
    "addr:postcode":"98119",
    "addr:street":"W Ewing St",
    "iso:country":"US",
    "sg:address":"1120 W Ewing St",
    "sg:city":"Seattle",
    "sg:classifiers":[
        {
            "category":"Arts & Performance",
            "subcategory":"Theater",
            "type":"Entertainment"
        }
    ],
    "sg:phone":"+1 206 352 0300",
    "sg:postcode":"98119",
    "sg:province":"WA",
    "sg:tags":[
        "equipment",
        "supply",
        "lighting",
        "theatrical"
    ],
    "sg:website":"http://www.stagingtechniques.com",
    "wof:name":"Staging Techniques",
    "wof:placetype":"venue"
},
  "geometry": {"coordinates":[-122.371022,47.655947],"type":"Point"}
}