{
  "type": "Feature",
  "properties": {
    "addr:full":"24686 SE 9th Pl Sammamish WA 98074",
    "addr:housenumber":"24686",
    "addr:postcode":"98074",
    "addr:street":"Se 9Th Pl",
    "iso:country":"US",
    "sg:address":"24686 SE 9th Pl",
    "sg:city":"Sammamish",
    "sg:classifiers":[
        {
            "category":"Health Services",
            "subcategory":"Clinic",
            "type":"Services"
        }
    ],
    "sg:phone":"+1 425 837 1983",
    "sg:postcode":"98074",
    "sg:province":"WA",
    "wof:name":"Novartis Consumer Health",
    "wof:placetype":"venue"
},
  "geometry": {"coordinates":[-122.011191,47.600122],"type":"Point"}
}