{
  "type": "Feature",
  "properties": {
    "addr:full":"2025 112th Ave NE Bellevue WA 98004",
    "addr:housenumber":"2025",
    "addr:postcode":"98004",
    "addr:street":"112Th Ave Ne",
    "iso:country":"US",
    "sg:address":"2025 112th Ave NE",
    "sg:city":"Bellevue",
    "sg:classifiers":[
        {
            "category":"Health Services",
            "subcategory":"Doctor",
            "type":"Services"
        },
        {
            "category":"Health Services",
            "subcategory":"Clinic",
            "type":"Services"
        }
    ],
    "sg:phone":"+1 425 462 9511",
    "sg:postcode":"98004",
    "sg:province":"WA",
    "sg:tags":[
        "counseling",
        "mental",
        "psychiatrist"
    ],
    "sg:website":"www.interlakepsychiatry.com",
    "wof:name":"Blache Jeanne M MD",
    "wof:placetype":"venue"
},
  "geometry": {"coordinates":[-122.191002,47.628201],"type":"Point"}
}