{
  "type": "Feature",
  "properties": {
    "addr:full":"6301 NW Dogwood Dr Vancouver WA 98663",
    "addr:housenumber":"6301",
    "addr:postcode":"98663",
    "addr:street":"Nw Dogwood Dr",
    "iso:country":"US",
    "sg:address":"6301 NW Dogwood Dr",
    "sg:city":"Vancouver",
    "sg:classifiers":[
        {
            "category":"Professional",
            "type":"Services"
        }
    ],
    "sg:phone":"+1 360 693 4228",
    "sg:postcode":"98663",
    "sg:province":"WA",
    "sg:tags":[
        "establishment"
    ],
    "wof:name":"E M Gunderson",
    "wof:placetype":"venue"
},
  "geometry": {"coordinates":[-122.688191,45.668575],"type":"Point"}
}