{
  "type": "Feature",
  "properties": {
    "addr:full":"434 SW 127th St Seattle WA 98146",
    "addr:housenumber":"434",
    "addr:postcode":"98146",
    "addr:street":"Sw 127Th St",
    "iso:country":"US",
    "sg:address":"434 SW 127th St",
    "sg:city":"Seattle",
    "sg:classifiers":[
        {
            "category":"Professional",
            "subcategory":"Management & Consulting",
            "type":"Services"
        }
    ],
    "sg:phone":"+1 206 241 9346",
    "sg:postcode":"98146",
    "sg:province":"WA",
    "sg:tags":[
        "retail",
        "direct",
        "sales"
    ],
    "wof:name":"Hot Rod Espresso",
    "wof:placetype":"venue"
},
  "geometry": {"coordinates":[-122.341634,47.489452],"type":"Point"}
}