{
  "type": "Feature",
  "properties": {
    "addr:full":"5 Timmer Ln Goldendale WA 98620",
    "addr:housenumber":"5",
    "addr:postcode":"98620",
    "addr:street":"Timmer Ln",
    "iso:country":"US",
    "sg:address":"5 Timmer Ln",
    "sg:city":"Goldendale",
    "sg:classifiers":[
        {
            "category":"Organizations",
            "subcategory":"Religious Organization",
            "type":"Services"
        }
    ],
    "sg:phone":"+1 509 773 7141",
    "sg:postcode":"98620",
    "sg:province":"WA",
    "wof:name":"Greek Orthodox Holy Convent",
    "wof:placetype":"venue"
},
  "geometry": {"coordinates":[-120.67725,45.941264],"type":"Point"}
}