{
  "type": "Feature",
  "properties": {
    "iso:country":"US",
    "sg:address":"320 Dayton St",
    "sg:city":"Edmonds",
    "sg:classifiers":[
        {
            "category":"Education",
            "subcategory":"School",
            "type":"Public Place"
        }
    ],
    "sg:phone":"+1 425 776 4042",
    "sg:postcode":"98020",
    "sg:province":"WA",
    "sg:tags":[
        "academic",
        "special"
    ],
    "sg:website":"www.louisbraillecenter.org",
    "wof:name":"Louis Braille Ctr",
    "wof:placetype":"venue"
},
  "geometry": {"coordinates":[-122.37917400000001,47.809637],"type":"Point"}
}