{
  "type": "Feature",
  "properties": {
    "addr:full":"17928 SE 313th St Auburn WA 98092",
    "addr:housenumber":"17928",
    "addr:postcode":"98092",
    "addr:street":"Se 313Th St",
    "iso:country":"US",
    "sg:address":"17928 SE 313th St",
    "sg:city":"Auburn",
    "sg:classifiers":[
        {
            "category":"Banks & Credit Unions",
            "subcategory":"Bank",
            "type":"Services"
        }
    ],
    "sg:phone":"+1 253 631 6356",
    "sg:postcode":"98092",
    "sg:province":"WA",
    "sg:tags":[
        "personal",
        "institution"
    ],
    "wof:name":"Tr Business Services",
    "wof:placetype":"venue"
},
  "geometry": {"coordinates":[-122.09958,47.321116],"type":"Point"}
}