{
  "type": "Feature",
  "properties": {
    "addr:full":"201 Cottage Ave Ste 1 Cashmere WA 98815",
    "addr:housenumber":"201",
    "addr:postcode":"98815",
    "addr:street":"Cottage Ave Ste 1 Cashmere",
    "iso:country":"US",
    "sg:address":"201 Cottage Ave Ste 1",
    "sg:city":"Cashmere",
    "sg:classifiers":[
        {
            "category":"Retail",
            "subcategory":"Storage",
            "type":"Services"
        }
    ],
    "sg:phone":"+1 509 782 8113",
    "sg:postcode":"98815",
    "sg:province":"WA",
    "sg:tags":[
        "self",
        "commercial",
        "household"
    ],
    "wof:name":"Downtown Cashmere Mini Storage",
    "wof:placetype":"venue"
},
  "geometry": {"coordinates":[-120.467789,47.52187],"type":"Point"}
}