{
  "type": "Feature",
  "properties": {
    "addr:full":"1101 Andover Park W Seattle WA 98188",
    "addr:housenumber":"1101",
    "addr:postcode":"98188",
    "addr:street":"Andover Park W",
    "iso:country":"US",
    "sg:address":"1101 Andover Park W",
    "sg:city":"Seattle",
    "sg:classifiers":[
        {
            "category":"Social Services",
            "type":"Services"
        }
    ],
    "sg:phone":"+1 206 575 3917",
    "sg:postcode":"98188",
    "sg:province":"WA",
    "sg:tags":[
        "handicapped",
        "for"
    ],
    "wof:name":"Evergreen Cmnty Tenant Support",
    "wof:placetype":"venue"
},
  "geometry": {"coordinates":[-122.254503,47.445335],"type":"Point"}
}