{
  "type": "Feature",
  "properties": {
    "addr:full":"21225 80th Ave SE Woodinville WA 98072",
    "addr:housenumber":"21225",
    "addr:postcode":"98072",
    "addr:street":"80Th Ave Se",
    "iso:country":"US",
    "sg:address":"21225 80th Ave SE",
    "sg:city":"Woodinville",
    "sg:classifiers":[
        {
            "category":"Health Services",
            "subcategory":"Nursing And Care Facility",
            "type":"Services"
        }
    ],
    "sg:phone":"+1 360 668 9074",
    "sg:postcode":"98072",
    "sg:province":"WA",
    "sg:tags":[
        "home",
        "convalescent"
    ],
    "wof:name":"About Love AFH",
    "wof:placetype":"venue"
},
  "geometry": {"coordinates":[-122.125382,47.803019],"type":"Point"}
}