{
  "type": "Feature",
  "properties": {
    "addr:full":"1149 E Main St Othello WA 99344",
    "addr:housenumber":"1149",
    "addr:postcode":"99344",
    "addr:street":"E Main St",
    "iso:country":"US",
    "sg:address":"1149 E Main St",
    "sg:city":"Othello",
    "sg:classifiers":[
        {
            "category":"Restaurant",
            "type":"Food & Drink"
        }
    ],
    "sg:phone":"+1 509 488 0992",
    "sg:postcode":"99344",
    "sg:province":"WA",
    "sg:tags":[
        "eating"
    ],
    "wof:name":"Taquiera Guerrero",
    "wof:placetype":"venue"
},
  "geometry": {"coordinates":[-119.158348,46.826195],"type":"Point"}
}