{
  "type": "Feature",
  "properties": {
    "addr:full":"12912 SE Kent Kangley Rd Kent WA 98030",
    "addr:postcode":"12912;98030",
    "addr:street":"Se Kent Kangley Rd",
    "iso:country":"US",
    "sg:address":"12912 SE Kent Kangley Rd",
    "sg:city":"Kent",
    "sg:classifiers":[
        {
            "category":"Food & Beverages",
            "subcategory":"Ethnic Foods",
            "type":"Retail Goods"
        }
    ],
    "sg:phone":"+1 253 630 0284",
    "sg:postcode":"98030",
    "sg:province":"WA",
    "sg:tags":[
        "restaurant",
        "vietnamese"
    ],
    "wof:name":"Saigon Rose Vietnamese Rstrnt",
    "wof:placetype":"venue"
},
  "geometry": {"coordinates":[-122.1679,47.358452],"type":"Point"}
}