{
  "type": "Feature",
  "properties": {
    "addr:full":"1507 Belmont Ave Seattle WA 98122",
    "addr:housenumber":"1507",
    "addr:postcode":"98122",
    "addr:street":"Belmont Ave",
    "iso:country":"US",
    "sg:address":"1507 Belmont Ave",
    "sg:city":"Seattle",
    "sg:classifiers":[
        {
            "category":"Professional",
            "subcategory":"Printing & Photocopies",
            "type":"Services"
        }
    ],
    "sg:phone":"+1 206 328 2433",
    "sg:postcode":"98122",
    "sg:province":"WA",
    "sg:tags":[
        "photographers-commercial"
    ],
    "sg:website":"http://www.johngranen.com",
    "wof:name":"Granen Studio",
    "wof:placetype":"venue"
},
  "geometry": {"coordinates":[-122.324433,47.614159],"type":"Point"}
}