{
  "type": "Feature",
  "properties": {
    "addr:full":"10616 NE 132nd St Kirkland WA 98034",
    "addr:housenumber":"10616",
    "addr:postcode":"98034",
    "addr:street":"Ne 132Nd St",
    "iso:country":"US",
    "sg:address":"10616 NE 132nd St",
    "sg:city":"Kirkland",
    "sg:classifiers":[
        {
            "category":"Shopping",
            "subcategory":"Hobbies, Toys, & Games",
            "type":"Retail Goods"
        }
    ],
    "sg:phone":"+1 425 821 2492",
    "sg:postcode":"98034",
    "sg:province":"WA",
    "wof:name":"Rudelduit",
    "wof:placetype":"venue"
},
  "geometry": {"coordinates":[-122.198241,47.718559],"type":"Point"}
}