{
  "type": "Feature",
  "properties": {
    "addr:full":"4045 49th Ave SW Olympia WA 98512",
    "addr:housenumber":"4045",
    "addr:postcode":"98512",
    "addr:street":"49Th Ave Sw",
    "iso:country":"US",
    "sg:address":"4045 49th Ave SW",
    "sg:city":"Olympia",
    "sg:classifiers":[
        {
            "category":"Wholesale",
            "subcategory":"Non-durable Goods",
            "type":"Manufacturing & Wholesale Goods"
        }
    ],
    "sg:phone":"+1 360 570 1696",
    "sg:postcode":"98512",
    "sg:province":"WA",
    "wof:name":"B & C Distributing",
    "wof:placetype":"venue"
},
  "geometry": {"coordinates":[-122.968385,47.005188],"type":"Point"}
}