{
  "type": "Feature",
  "properties": {
    "addr:full":"321452 US Hwy 2 Newport WA 99156",
    "addr:housenumber":"321452",
    "addr:postcode":"99156",
    "addr:street":"Us Hwy 2",
    "iso:country":"US",
    "sg:address":"321452 US Hwy 2",
    "sg:city":"Newport",
    "sg:classifiers":[
        {
            "category":"Professional",
            "type":"Services"
        }
    ],
    "sg:phone":"+1 509 292 8400",
    "sg:postcode":"99156",
    "sg:province":"WA",
    "wof:name":"Marjorie Gannon",
    "wof:placetype":"venue"
},
  "geometry": {"coordinates":[-117.27527000000001,48.097408],"type":"Point"}
}