{
  "type": "Feature",
  "properties": {
    "addr:full":"11322 NE 124th St Kirkland WA 98034",
    "addr:housenumber":"11322",
    "addr:postcode":"98034",
    "addr:street":"Ne 124Th St",
    "iso:country":"US",
    "sg:address":"11322 NE 124th St",
    "sg:city":"Kirkland",
    "sg:classifiers":[
        {
            "category":"Restaurant",
            "type":"Food & Drink"
        }
    ],
    "sg:menulink":"http://www.allmenus.com/wa/east-seattle/144858-subway/menu/",
    "sg:phone":"+1 425 823 6576",
    "sg:postcode":"98034",
    "sg:province":"WA",
    "sg:tags":[
        "american",
        "sandwich"
    ],
    "wof:name":"Subway",
    "wof:placetype":"venue"
},
  "geometry": {"coordinates":[-122.190202,47.711189],"type":"Point"}
}