{
  "type": "Feature",
  "properties": {
    "addr:full":"317 E Queen Ave Spokane WA 99207",
    "addr:housenumber":"317",
    "addr:postcode":"99207",
    "addr:street":"E Queen Ave",
    "iso:country":"US",
    "sg:address":"317 E Queen Ave",
    "sg:city":"Spokane",
    "sg:classifiers":[
        {
            "category":"Social Services",
            "subcategory":"Child Care",
            "type":"Services"
        }
    ],
    "sg:phone":"+1 509 489 5509",
    "sg:postcode":"99207",
    "sg:province":"WA",
    "wof:name":"Little Guys Two",
    "wof:placetype":"venue"
},
  "geometry": {"coordinates":[-117.40339899999999,47.70399],"type":"Point"}
}