{
  "type": "Feature",
  "properties": {
    "addr:full":"1912 Olympic Hwy N Shelton WA 98584",
    "addr:housenumber":"1912",
    "addr:postcode":"98584",
    "addr:street":"Olympic Hwy N",
    "iso:country":"US",
    "sg:address":"1912 Olympic Hwy N",
    "sg:city":"Shelton",
    "sg:classifiers":[
        {
            "category":"Shopping",
            "type":"Retail Goods"
        }
    ],
    "sg:phone":"+1 360 462 0013",
    "sg:postcode":"98584",
    "sg:province":"WA",
    "sg:tags":[
        "merchandise"
    ],
    "wof:name":"Framing Group",
    "wof:placetype":"venue"
},
  "geometry": {"coordinates":[-123.12018,47.221893],"type":"Point"}
}