{
  "type": "Feature",
  "properties": {
    "addr:full":"3520 27th Pl W Seattle WA 98199",
    "addr:housenumber":"3520",
    "addr:postcode":"98199",
    "addr:street":"27Th Pl W",
    "iso:country":"US",
    "sg:address":"3520 27th Pl W",
    "sg:city":"Seattle",
    "sg:classifiers":[
        {
            "category":"Real Estate",
            "subcategory":"Real Estate Operator",
            "type":"Services"
        }
    ],
    "sg:phone":"+1 206 284 7040",
    "sg:postcode":"98199",
    "sg:province":"WA",
    "sg:tags":[
        "apartment"
    ],
    "sg:website":"www.weidner.com",
    "wof:name":"Overlook at Magnolia Apartments",
    "wof:placetype":"venue"
},
  "geometry": {"coordinates":[-122.390321,47.652774],"type":"Point"}
}