{
  "type": "Feature",
  "properties": {
    "addr:full":"20319 N Newport Hwy Colbert WA 99005",
    "addr:housenumber":"20319",
    "addr:postcode":"99005",
    "addr:street":"N Newport Hwy Colbert",
    "iso:country":"US",
    "sg:address":"20319 N Newport Hwy",
    "sg:city":"Colbert",
    "sg:classifiers":[
        {
            "category":"Building & Trades",
            "subcategory":"Construction",
            "type":"Services"
        }
    ],
    "sg:phone":"+1 509 238 4295",
    "sg:postcode":"99005",
    "sg:province":"WA",
    "sg:tags":[
        "house"
    ],
    "wof:name":"Vigil Tj Construction",
    "wof:placetype":"venue"
},
  "geometry": {"coordinates":[-117.35476800000001,47.845392],"type":"Point"}
}