{
  "type": "Feature",
  "properties": {
    "addr:full":"1668 Fort Nugent Rd Oak Harbor WA 98277",
    "addr:housenumber":"1668",
    "addr:postcode":"98277",
    "addr:street":"Fort Nugent Rd",
    "iso:country":"US",
    "sg:address":"1668 Fort Nugent Rd",
    "sg:city":"Oak Harbor",
    "sg:classifiers":[
        {
            "category":"Manufacturing",
            "subcategory":"Signs",
            "type":"Manufacturing & Wholesale Goods"
        }
    ],
    "sg:phone":"+1 360 675 3918",
    "sg:postcode":"98277",
    "sg:province":"WA",
    "wof:name":"A Custom Sign Svc",
    "wof:placetype":"venue"
},
  "geometry": {"coordinates":[-122.705786,48.282906],"type":"Point"}
}