{
  "type": "Feature",
  "properties": {
    "addr:full":"10424 Silverdale Way NW Silverdale WA 98383",
    "addr:housenumber":"10424",
    "addr:postcode":"98383",
    "addr:street":"Silverdale Way Nw",
    "iso:country":"US",
    "sg:address":"10424 Silverdale Way NW",
    "sg:city":"Silverdale",
    "sg:phone":"+1 360 613 4005",
    "sg:postcode":"98383",
    "sg:province":"WA",
    "wof:name":"Los Cabos Grill",
    "wof:placetype":"venue"
},
  "geometry": {"coordinates":[-122.687333,47.657159],"type":"Point"}
}