{
  "type": "Feature",
  "properties": {
    "addr:full":"201 Cascade Mall Dr Burlington WA 98233",
    "addr:housenumber":"201",
    "addr:postcode":"98233",
    "addr:street":"Cascade Mall Dr",
    "iso:country":"US",
    "sg:address":"201 Cascade Mall Dr",
    "sg:city":"Burlington",
    "sg:classifiers":[
        {
            "category":"Sports & Exercise",
            "subcategory":"Bicycle Rental",
            "type":"Entertainment"
        }
    ],
    "sg:phone":"+1 360 757 1930",
    "sg:postcode":"98233",
    "sg:province":"WA",
    "sg:tags":[
        "wear"
    ],
    "wof:name":"Pacific Sunwear",
    "wof:placetype":"venue"
},
  "geometry": {"coordinates":[-122.33699799999999,48.464298],"type":"Point"}
}