{
  "type": "Feature",
  "properties": {
    "addr:full":"3322 Rimrock Rd Colton WA 99113",
    "addr:housenumber":"3322",
    "addr:postcode":"99113",
    "addr:street":"Rimrock Rd",
    "iso:country":"US",
    "sg:address":"3322 Rimrock Rd",
    "sg:city":"Colton",
    "sg:phone":"+1 509 229 3397",
    "sg:postcode":"99113",
    "sg:province":"WA",
    "sg:tags":[
        "farm",
        "grain",
        "cash"
    ],
    "wof:name":"Dan Kramer",
    "wof:placetype":"venue"
},
  "geometry": {"coordinates":[-117.22473599999999,46.569502],"type":"Point"}
}