{
  "type": "Feature",
  "properties": {
    "addr:full":"1137 W Hwy 101 Port Angeles WA 98363",
    "addr:housenumber":"1137",
    "addr:postcode":"98363",
    "addr:street":"W Hwy 101",
    "iso:country":"US",
    "sg:address":"1137 W Hwy 101",
    "sg:city":"Port Angeles",
    "sg:classifiers":[
        {
            "category":"Restaurant",
            "type":"Food & Drink"
        }
    ],
    "sg:phone":"+1 360 928 9507",
    "sg:postcode":"98363",
    "sg:province":"WA",
    "sg:tags":[
        "eating"
    ],
    "wof:name":"Spotted Dog Cafe",
    "wof:placetype":"venue"
},
  "geometry": {"coordinates":[-123.469078,48.106188],"type":"Point"}
}