{
  "type": "Feature",
  "properties": {
    "addr:full":"11722 4th Ave W Everett WA 98204",
    "addr:housenumber":"11722",
    "addr:postcode":"98204",
    "addr:street":"4Th Ave W",
    "iso:country":"US",
    "sg:address":"11722 4th Ave W",
    "sg:city":"Everett",
    "sg:classifiers":[
        {
            "category":"Retail",
            "subcategory":"Repair Shop",
            "type":"Services"
        }
    ],
    "sg:phone":"+1 425 355 2034",
    "sg:postcode":"98204",
    "sg:province":"WA",
    "sg:tags":[
        "sell",
        "microscope"
    ],
    "wof:name":"Nafziger & Company Inc",
    "wof:placetype":"venue"
},
  "geometry": {"coordinates":[-122.238935,47.89093],"type":"Point"}
}