{
  "type": "Feature",
  "properties": {
    "addr:full":"7211 N Lake Cushman Rd Hoodsport WA 98548",
    "addr:housenumber":"7211",
    "addr:postcode":"98548",
    "addr:street":"N Lake Cushman Rd",
    "iso:country":"US",
    "sg:address":"7211 N Lake Cushman Rd",
    "sg:city":"Hoodsport",
    "sg:classifiers":[
        {
            "category":"Travel",
            "subcategory":"Campground",
            "type":"Entertainment"
        }
    ],
    "sg:phone":"+1 360 877 6770",
    "sg:postcode":"98548",
    "sg:province":"WA",
    "wof:name":"Camp Cushman",
    "wof:placetype":"venue"
},
  "geometry": {"coordinates":[-123.214631,47.459225],"type":"Point"}
}