{
  "type": "Feature",
  "properties": {
    "addr:full":"11419 19th Ave SE Everett WA 98208",
    "addr:housenumber":"11419",
    "addr:postcode":"98208",
    "addr:street":"19Th Ave Se",
    "iso:country":"US",
    "sg:address":"11419 19th Ave SE",
    "sg:city":"Everett",
    "sg:classifiers":[
        {
            "category":"Education",
            "subcategory":"Music School",
            "type":"Public Place"
        }
    ],
    "sg:phone":"+1 425 337 5328",
    "sg:postcode":"98208",
    "sg:province":"WA",
    "sg:tags":[
        "instruction-instrumental"
    ],
    "wof:name":"Arts & Music Center",
    "wof:placetype":"venue"
},
  "geometry": {"coordinates":[-122.202642,47.89541],"type":"Point"}
}