{
  "type": "Feature",
  "properties": {
    "addr:full":"1348 Lake Whatcom Blvd Bellingham WA 98229",
    "addr:housenumber":"1348",
    "addr:postcode":"98229",
    "addr:street":"Lake Whatcom Blvd",
    "iso:country":"US",
    "sg:address":"1348 Lake Whatcom Blvd",
    "sg:city":"Bellingham",
    "sg:classifiers":[
        {
            "category":"Real Estate",
            "subcategory":"Real Estate Agent",
            "type":"Services"
        }
    ],
    "sg:phone":"+1 360 647 5050",
    "sg:postcode":"98229",
    "sg:province":"WA",
    "wof:name":"Re/Max",
    "wof:placetype":"venue"
},
  "geometry": {"coordinates":[-122.396835,48.74755],"type":"Point"}
}