{
  "type": "Feature",
  "properties": {
    "addr:full":"118 Borovec Rd Chehalis WA 98532",
    "addr:housenumber":"118",
    "addr:postcode":"98532",
    "addr:street":"Borovec Rd",
    "iso:country":"US",
    "sg:address":"118 Borovec Rd",
    "sg:city":"Chehalis",
    "sg:classifiers":[
        {
            "category":"Professional",
            "subcategory":"Research",
            "type":"Services"
        }
    ],
    "sg:phone":"+1 360 748 9376",
    "sg:postcode":"98532",
    "sg:province":"WA",
    "sg:tags":[
        "development"
    ],
    "wof:name":"Webjoist",
    "wof:placetype":"venue"
},
  "geometry": {"coordinates":[-122.91852900000001,46.619243],"type":"Point"}
}