{
  "type": "Feature",
  "properties": {
    "addr:full":"14120 88th Pl NE Bothell WA 98011",
    "addr:housenumber":"14120",
    "addr:postcode":"98011",
    "addr:street":"88Th Pl Ne",
    "iso:country":"US",
    "sg:address":"14120 88th Pl NE",
    "sg:city":"Bothell",
    "sg:classifiers":[
        {
            "category":"Government",
            "subcategory":"Office",
            "type":"Public Place"
        }
    ],
    "sg:phone":"+1 425 820 9088",
    "sg:postcode":"98011",
    "sg:province":"WA",
    "sg:tags":[
        "agricultural",
        "regulation",
        "marketing"
    ],
    "wof:name":"Davlin Enterprises",
    "wof:placetype":"venue"
},
  "geometry": {"coordinates":[-122.223265,47.728155],"type":"Point"}
}