{
  "type": "Feature",
  "properties": {
    "iso:country":"US",
    "sg:address":"4817 Fern Ave NE",
    "sg:city":"Bremerton",
    "sg:classifiers":[
        {
            "category":"Professional",
            "type":"Services"
        }
    ],
    "sg:phone":"+1 360 373 2663",
    "sg:postcode":"98311",
    "sg:province":"WA",
    "sg:tags":[
        "consulting",
        "business"
    ],
    "wof:name":"Peacock Offshore Consulti",
    "wof:placetype":"venue"
},
  "geometry": {"coordinates":[-122.59998400000001,47.611244],"type":"Point"}
}