{
  "type": "Feature",
  "properties": {
    "addr:full":"3340 Crystal Springs Dr NE Bainbridge Island WA 98110",
    "addr:housenumber":"3340",
    "addr:postcode":"98110",
    "addr:street":"Crystal Springs Dr Ne",
    "iso:country":"US",
    "sg:address":"3340 Crystal Springs Dr NE",
    "sg:city":"Bainbridge Island",
    "sg:classifiers":[
        {
            "category":"Professional",
            "subcategory":"Engineering",
            "type":"Services"
        }
    ],
    "sg:phone":"+1 206 780 5504",
    "sg:postcode":"98110",
    "sg:province":"WA",
    "wof:name":"James W Kreuter Pe",
    "wof:placetype":"venue"
},
  "geometry": {"coordinates":[-122.57498,47.608259],"type":"Point"}
}