{
  "type": "Feature",
  "properties": {
    "addr:full":"6351 37th Ave SW Seattle WA 98126",
    "addr:housenumber":"6351",
    "addr:postcode":"98126",
    "addr:street":"37Th Ave Sw",
    "iso:country":"US",
    "sg:address":"6351 37th Ave SW",
    "sg:city":"Seattle",
    "sg:classifiers":[
        {
            "category":"Shopping",
            "subcategory":"Hobbies, Toys, & Games",
            "type":"Retail Goods"
        }
    ],
    "sg:phone":"+1 206 250 5244",
    "sg:postcode":"98126",
    "sg:province":"WA",
    "wof:name":"Mascot Toys LLC",
    "wof:placetype":"venue"
},
  "geometry": {"coordinates":[-122.379209,47.54519],"type":"Point"}
}