{
  "type": "Feature",
  "properties": {
    "addr:full":"2131 Riverbottom Rd Ellensburg WA 98926",
    "addr:housenumber":"2131",
    "addr:postcode":"98926",
    "addr:street":"Riverbottom Rd",
    "iso:country":"US",
    "sg:address":"2131 Riverbottom Rd",
    "sg:city":"Ellensburg",
    "sg:classifiers":[
        {
            "category":"Building & Trades",
            "subcategory":"Construction",
            "type":"Services"
        }
    ],
    "sg:phone":"+1 509 925 5457",
    "sg:postcode":"98926",
    "sg:province":"WA",
    "sg:tags":[
        "road",
        "contractor"
    ],
    "wof:name":"Thayer & Sons Excavating",
    "wof:placetype":"venue"
},
  "geometry": {"coordinates":[-120.551976,46.960028],"type":"Point"}
}