{
  "type": "Feature",
  "properties": {
    "addr:full":"7719 NE 88th St Vancouver WA 98662",
    "addr:housenumber":"7719",
    "addr:postcode":"98662",
    "addr:street":"Ne 88Th St",
    "iso:country":"US",
    "sg:address":"7719 NE 88th St",
    "sg:city":"Vancouver",
    "sg:classifiers":[
        {
            "category":"Manufacturing",
            "subcategory":"Signs",
            "type":"Manufacturing & Wholesale Goods"
        }
    ],
    "sg:phone":"+1 360 256 3370",
    "sg:postcode":"98662",
    "sg:province":"WA",
    "sg:tags":[
        "specialty",
        "mfg"
    ],
    "wof:name":"Done Right Signs",
    "wof:placetype":"venue"
},
  "geometry": {"coordinates":[-122.59897100000001,45.686452],"type":"Point"}
}