{
  "type": "Feature",
  "properties": {
    "addr:full":"145 Cascade Pl Ste 107 Burlington WA 98233",
    "addr:housenumber":"145",
    "addr:postcode":"98233",
    "addr:street":"Cascade Pl Ste 107",
    "iso:country":"US",
    "sg:address":"145 Cascade Pl Ste 107",
    "sg:city":"Burlington",
    "sg:classifiers":[
        {
            "category":"Personal",
            "subcategory":"Nail Salon",
            "type":"Services"
        }
    ],
    "sg:phone":"+1 360 707 2050",
    "sg:postcode":"98233",
    "sg:province":"WA",
    "wof:name":"Vip Nails",
    "wof:placetype":"venue"
},
  "geometry": {"coordinates":[-122.33341299999999,48.460418],"type":"Point"}
}