{
  "type": "Feature",
  "properties": {
    "addr:full":"14355 Corliss Ave N Seattle WA 98133",
    "addr:housenumber":"14355",
    "addr:postcode":"98133",
    "addr:street":"Corliss Ave N",
    "iso:country":"US",
    "sg:address":"14355 Corliss Ave N",
    "sg:city":"Seattle",
    "sg:classifiers":[
        {
            "category":"Manufacturing",
            "subcategory":"Textiles",
            "type":"Manufacturing & Wholesale Goods"
        }
    ],
    "sg:phone":"+1 206 362 5485",
    "sg:postcode":"98133",
    "sg:province":"WA",
    "sg:tags":[
        "mfg",
        "custom",
        "design",
        "interior",
        "curtain",
        "drapery"
    ],
    "sg:website":"www.beasleysworkroom.com",
    "wof:name":"Beasley's Work Room",
    "wof:placetype":"venue"
},
  "geometry": {"coordinates":[-122.33200100000001,47.733101],"type":"Point"}
}