{
  "type": "Feature",
  "properties": {
    "addr:full":"6426 Carleton Ave S Seattle WA 98108",
    "addr:housenumber":"6426",
    "addr:postcode":"98108",
    "addr:street":"Carleton Ave S",
    "iso:country":"US",
    "sg:address":"6426 Carleton Ave S",
    "sg:city":"Seattle",
    "sg:classifiers":[
        {
            "category":"Professional",
            "subcategory":"Computer Services",
            "type":"Services"
        }
    ],
    "sg:phone":"+1 206 763 6123",
    "sg:postcode":"98108",
    "sg:province":"WA",
    "sg:tags":[
        "graphic"
    ],
    "sg:website":"http://www.brightspectrum.net",
    "wof:name":"Bright Spectrum Web Solutions",
    "wof:placetype":"venue"
},
  "geometry": {"coordinates":[-122.32088899999999,47.545025],"type":"Point"}
}