{
  "type": "Feature",
  "properties": {
    "addr:full":"1021 204th Pl SW Lynnwood WA 98036",
    "addr:housenumber":"1021",
    "addr:postcode":"98036",
    "addr:street":"204Th Pl Sw",
    "iso:country":"US",
    "sg:address":"1021 204th Pl SW",
    "sg:city":"Lynnwood",
    "sg:classifiers":[
        {
            "category":"Building & Trades",
            "subcategory":"Cleaning & Sanitation",
            "type":"Services"
        }
    ],
    "sg:phone":"+1 425 608 2625",
    "sg:postcode":"98036",
    "sg:province":"WA",
    "sg:tags":[
        "house"
    ],
    "wof:name":"Say It Simply",
    "wof:placetype":"venue"
},
  "geometry": {"coordinates":[-122.24684600000001,47.812831],"type":"Point"}
}