{
  "type": "Feature",
  "properties": {
    "addr:full":"404 Basin St NW Ephrata WA 98823",
    "addr:housenumber":"404",
    "addr:postcode":"98823",
    "addr:street":"Basin St Nw",
    "iso:country":"US",
    "sg:address":"404 Basin St NW",
    "sg:city":"Ephrata",
    "sg:classifiers":[
        {
            "category":"Home & Garden",
            "subcategory":"Building Materials",
            "type":"Retail Goods"
        }
    ],
    "sg:phone":"+1 509 754 2331",
    "sg:postcode":"98823",
    "sg:province":"WA",
    "sg:tags":[
        "glass",
        "window",
        "plate"
    ],
    "wof:name":"Columbia Glass LLC",
    "wof:placetype":"venue"
},
  "geometry": {"coordinates":[-119.548092,47.325455],"type":"Point"}
}