{
  "type": "Feature",
  "properties": {
    "addr:full":"6843 E State Rte 106 Union WA 98592",
    "addr:housenumber":"6843",
    "addr:postcode":"98592",
    "addr:street":"E State Rte 106 Union",
    "iso:country":"US",
    "sg:address":"6843 E State Rte 106",
    "sg:city":"Union",
    "sg:classifiers":[
        {
            "category":"Shopping",
            "subcategory":"Clothing, Apparel, & Fashions",
            "type":"Retail Goods"
        }
    ],
    "sg:phone":"+1 360 898 3200",
    "sg:postcode":"98592",
    "sg:province":"WA",
    "sg:tags":[
        "item",
        "boutique"
    ],
    "wof:name":"Cameo Boutique",
    "wof:placetype":"venue"
},
  "geometry": {"coordinates":[-123.074927,47.352837],"type":"Point"}
}