{
  "type": "Feature",
  "properties": {
    "addr:full":"600 Stewart St Ste 1600 Seattle WA 98101",
    "addr:housenumber":"600",
    "addr:postcode":"98101",
    "addr:street":"Stewart St Ste 1600",
    "iso:country":"US",
    "sg:address":"600 Stewart St Ste 1600",
    "sg:city":"Seattle",
    "sg:classifiers":[
        {
            "category":"Professional",
            "subcategory":"Lawyer & Legal Services",
            "type":"Services"
        }
    ],
    "sg:phone":"+1 206 441 5444",
    "sg:postcode":"98101",
    "sg:province":"WA",
    "sg:tags":[
        "divorce",
        "law",
        "family"
    ],
    "wof:name":"Berry C Nelson III",
    "wof:placetype":"venue"
},
  "geometry": {"coordinates":[-122.33699799999999,47.613701],"type":"Point"}
}