{
  "type": "Feature",
  "properties": {
    "addr:full":"17410 Interurban Blvd Snohomish WA 98296",
    "addr:housenumber":"17410",
    "addr:postcode":"98296",
    "addr:street":"Interurban Blvd",
    "iso:country":"US",
    "sg:address":"17410 Interurban Blvd",
    "sg:city":"Snohomish",
    "sg:classifiers":[
        {
            "category":"Organizations",
            "subcategory":"Membership Organization",
            "type":"Services"
        }
    ],
    "sg:phone":"+1 360 668 1099",
    "sg:postcode":"98296",
    "sg:province":"WA",
    "wof:name":"Booriak Conservator",
    "wof:placetype":"venue"
},
  "geometry": {"coordinates":[-122.147767,47.838062],"type":"Point"}
}