{
  "type": "Feature",
  "properties": {
    "addr:full":"716 Jadwin Ave Richland WA 99352",
    "addr:housenumber":"716",
    "addr:postcode":"99352",
    "addr:street":"Jadwin Ave",
    "iso:country":"US",
    "sg:address":"716 Jadwin Ave",
    "sg:city":"Richland",
    "sg:classifiers":[
        {
            "category":"Professional",
            "subcategory":"Management & Consulting",
            "type":"Services"
        }
    ],
    "sg:phone":"+1 509 943 0358",
    "sg:postcode":"99352",
    "sg:province":"WA",
    "sg:tags":[
        "business"
    ],
    "wof:name":"Washington East Opera",
    "wof:placetype":"venue"
},
  "geometry": {"coordinates":[-119.27515,46.276339],"type":"Point"}
}