{
  "type": "Feature",
  "properties": {
    "addr:full":"270 Cascade Mall Dr Burlington WA 98233",
    "addr:housenumber":"270",
    "addr:postcode":"98233",
    "addr:street":"Cascade Mall Dr",
    "iso:country":"US",
    "sg:address":"270 Cascade Mall Dr",
    "sg:city":"Burlington",
    "sg:classifiers":[
        {
            "category":"Shopping",
            "subcategory":"Music",
            "type":"Retail Goods"
        }
    ],
    "sg:phone":"+1 360 757 1212",
    "sg:postcode":"98233",
    "sg:province":"WA",
    "sg:tags":[
        "product",
        "prerecorded",
        "tape",
        "blank",
        "small",
        "video",
        "audio"
    ],
    "wof:name":"Musicland 0684",
    "wof:placetype":"venue"
},
  "geometry": {"coordinates":[-122.336724,48.460117],"type":"Point"}
}