{
  "type": "Feature",
  "properties": {
    "addr:full":"7815 Coolidge Rd Yakima WA 98903",
    "addr:housenumber":"7815",
    "addr:postcode":"98903",
    "addr:street":"Coolidge Rd",
    "iso:country":"US",
    "sg:address":"7815 Coolidge Rd",
    "sg:city":"Yakima",
    "sg:classifiers":[
        {
            "category":"Organizations",
            "subcategory":"Membership Organization",
            "type":"Services"
        }
    ],
    "sg:phone":"+1 509 965 3868",
    "sg:postcode":"98903",
    "sg:province":"WA",
    "wof:name":"Great Amercn Classics Car CLB",
    "wof:placetype":"venue"
},
  "geometry": {"coordinates":[-120.614656,46.567628],"type":"Point"}
}