{
  "type": "Feature",
  "properties": {
    "addr:full":"2527 NE 135th St Seattle WA 98125",
    "addr:housenumber":"2527",
    "addr:postcode":"98125",
    "addr:street":"Ne 135Th St",
    "iso:country":"US",
    "sg:address":"2527 NE 135th St",
    "sg:city":"Seattle",
    "sg:classifiers":[
        {
            "category":"Wholesale",
            "subcategory":"Jewelry",
            "type":"Manufacturing & Wholesale Goods"
        }
    ],
    "sg:phone":"+1 206 367 0843",
    "sg:postcode":"98125",
    "sg:province":"WA",
    "sg:tags":[
        "stone"
    ],
    "wof:name":"Rain City Jewels",
    "wof:placetype":"venue"
},
  "geometry": {"coordinates":[-122.301655,47.72648],"type":"Point"}
}