{
  "type": "Feature",
  "properties": {
    "addr:full":"2400 W Kennewick Ave Kennewick WA 99336",
    "addr:housenumber":"2400",
    "addr:postcode":"99336",
    "addr:street":"W Kennewick Ave",
    "iso:country":"US",
    "sg:address":"2400 W Kennewick Ave",
    "sg:city":"Kennewick",
    "sg:classifiers":[
        {
            "category":"Restaurant",
            "type":"Food & Drink"
        }
    ],
    "sg:phone":"+1 509 374 8400",
    "sg:postcode":"99336",
    "sg:province":"WA",
    "sg:website":"www.papajohns.com",
    "wof:name":"Papa John's Pizza",
    "wof:placetype":"venue"
},
  "geometry": {"coordinates":[-119.15503,46.209452],"type":"Point"}
}