{
  "type": "Feature",
  "properties": {
    "addr:full":"18816 26th Ave NE Seattle WA 98155",
    "addr:housenumber":"18816",
    "addr:postcode":"98155",
    "addr:street":"26Th Ave Ne",
    "iso:country":"US",
    "sg:address":"18816 26th Ave NE",
    "sg:city":"Seattle",
    "sg:classifiers":[
        {
            "category":"Professional",
            "subcategory":"Computer Services",
            "type":"Services"
        }
    ],
    "sg:phone":"+1 206 365 2073",
    "sg:postcode":"98155",
    "sg:province":"WA",
    "sg:tags":[
        "programing",
        "custom"
    ],
    "wof:name":"Flowline Programming Serv",
    "wof:placetype":"venue"
},
  "geometry": {"coordinates":[-122.30128499999999,47.765755],"type":"Point"}
}