{
  "type": "Feature",
  "properties": {
    "addr:full":"2005 Squak Mountain Loop SW Issaquah WA 98027",
    "addr:housenumber":"2005",
    "addr:postcode":"98027",
    "addr:street":"Squak Mountain Loop Sw",
    "iso:country":"US",
    "sg:address":"2005 Squak Mountain Loop SW",
    "sg:city":"Issaquah",
    "sg:classifiers":[
        {
            "category":"Wholesale",
            "subcategory":"Beer",
            "type":"Manufacturing & Wholesale Goods"
        }
    ],
    "sg:phone":"+1 425 392 5078",
    "sg:postcode":"98027",
    "sg:province":"WA",
    "wof:name":"Microbeer Source",
    "wof:placetype":"venue"
},
  "geometry": {"coordinates":[-122.055301,47.518508],"type":"Point"}
}