{
  "type": "Feature",
  "properties": {
    "addr:full":"602 Auburn Way N Auburn WA 98002",
    "addr:housenumber":"602",
    "addr:postcode":"98002",
    "addr:street":"Auburn Way N",
    "iso:country":"US",
    "sg:address":"602 Auburn Way N",
    "sg:city":"Auburn",
    "sg:classifiers":[
        {
            "category":"Home & Garden",
            "subcategory":"Home Furnishings",
            "type":"Retail Goods"
        },
        {
            "category":"Sports & Exercise",
            "subcategory":"Gym",
            "type":"Entertainment"
        }
    ],
    "sg:phone":"+1 253 833 4246",
    "sg:postcode":"98002",
    "sg:province":"WA",
    "sg:tags":[
        "spa",
        "stove",
        "wood",
        "health",
        "burning"
    ],
    "wof:name":"Johnsons Stove & Patio Inc",
    "wof:placetype":"venue"
},
  "geometry": {"coordinates":[-122.22542900000001,47.312991],"type":"Point"}
}