{
  "type": "Feature",
  "properties": {
    "addr:full":"8018 NE 151st Ct Kenmore WA 98028",
    "addr:housenumber":"8018",
    "addr:postcode":"98028",
    "addr:street":"Ne 151St Ct",
    "iso:country":"US",
    "sg:address":"8018 NE 151st Ct",
    "sg:city":"Kenmore",
    "sg:classifiers":[
        {
            "category":"Professional",
            "subcategory":"Management & Consulting",
            "type":"Services"
        }
    ],
    "sg:phone":"+1 425 487 6150",
    "sg:postcode":"98028",
    "sg:province":"WA",
    "wof:name":"Phil Clifford & Associates",
    "wof:placetype":"venue"
},
  "geometry": {"coordinates":[-122.233853,47.737528],"type":"Point"}
}