{
  "type": "Feature",
  "properties": {
    "addr:full":"207 Allen St Kelso WA 98626",
    "addr:housenumber":"207",
    "addr:postcode":"98626",
    "addr:street":"Allen St",
    "iso:country":"US",
    "sg:address":"207 Allen St",
    "sg:city":"Kelso",
    "sg:classifiers":[
        {
            "category":"Food & Beverages",
            "subcategory":"Bakery",
            "type":"Retail Goods"
        }
    ],
    "sg:phone":"+1 360 423 8810",
    "sg:postcode":"98626",
    "sg:province":"WA",
    "sg:tags":[
        "baker"
    ],
    "wof:name":"Fraser's Bakery-Restaurant",
    "wof:placetype":"venue"
},
  "geometry": {"coordinates":[-122.910315,46.144869],"type":"Point"}
}