{
  "type": "Feature",
  "properties": {
    "addr:full":"6546 25th Ave NW Seattle WA 98117",
    "addr:housenumber":"6546",
    "addr:postcode":"98117",
    "addr:street":"25Th Ave Nw",
    "iso:country":"US",
    "sg:address":"6546 25th Ave NW",
    "sg:city":"Seattle",
    "sg:classifiers":[
        {
            "category":"Building & Trades",
            "subcategory":"Construction",
            "type":"Services"
        }
    ],
    "sg:phone":"+1 206 783 1381",
    "sg:postcode":"98117",
    "sg:province":"WA",
    "sg:tags":[
        "house"
    ],
    "wof:name":"Low Bid Construction",
    "wof:placetype":"venue"
},
  "geometry": {"coordinates":[-122.38857299999999,47.677275],"type":"Point"}
}