{
  "type": "Feature",
  "properties": {
    "addr:full":"2201 6th Ave Ste 215 Seattle WA 98121",
    "addr:housenumber":"2201",
    "addr:postcode":"98121",
    "addr:street":"6Th Ave Ste 215",
    "iso:country":"US",
    "sg:address":"2201 6th Ave Ste 215",
    "sg:city":"Seattle",
    "sg:classifiers":[
        {
            "category":"Government",
            "subcategory":"Office",
            "type":"Public Place"
        }
    ],
    "sg:phone":"+1 206 615 2547",
    "sg:postcode":"98121",
    "sg:province":"WA",
    "sg:tags":[
        "government-united",
        "state"
    ],
    "wof:name":"Region X",
    "wof:placetype":"venue"
},
  "geometry": {"coordinates":[-122.34092699999999,47.61591],"type":"Point"}
}