{
  "type": "Feature",
  "properties": {
    "addr:full":"2311 2nd Ave Seattle WA 98121",
    "addr:housenumber":"2311",
    "addr:postcode":"98121",
    "addr:street":"2Nd Ave",
    "iso:country":"US",
    "sg:address":"2311 2nd Ave",
    "sg:city":"Seattle",
    "sg:classifiers":[
        {
            "category":"Bakery",
            "type":"Food & Drink"
        }
    ],
    "sg:phone":"+1 206 441 5435",
    "sg:postcode":"98121",
    "sg:province":"WA",
    "wof:name":"Macrina Baking Co",
    "wof:placetype":"venue"
},
  "geometry": {"coordinates":[-122.34579100000001,47.614111],"type":"Point"}
}