{
  "type": "Feature",
  "properties": {
    "iso:country":"US",
    "sg:address":"1018 W Main St",
    "sg:city":"Centralia",
    "sg:classifiers":[
        {
            "category":"Home & Garden",
            "subcategory":"Household Appliances",
            "type":"Retail Goods"
        }
    ],
    "sg:phone":"+1 360 736 6997",
    "sg:postcode":"98531",
    "sg:province":"WA",
    "sg:tags":[
        "machine",
        "repair",
        "sewing",
        "vacuum"
    ],
    "wof:name":"Cen-Che Centralia",
    "wof:placetype":"venue"
},
  "geometry": {"coordinates":[-122.966548,46.718627],"type":"Point"}
}