{
  "type": "Feature",
  "properties": {
    "addr:full":"1501 Pike Pl Ste 325 Seattle WA 98101",
    "addr:housenumber":"1501",
    "addr:postcode":"98101",
    "addr:street":"Pike Pl Ste 325",
    "iso:country":"US",
    "sg:address":"1501 Pike Pl Ste 325",
    "sg:city":"Seattle",
    "sg:classifiers":[
        {
            "category":"Shopping",
            "subcategory":"Musical Instruments",
            "type":"Retail Goods"
        },
        {
            "category":"Shopping",
            "subcategory":"Music",
            "type":"Retail Goods"
        }
    ],
    "sg:phone":"+1 206 405 4200",
    "sg:postcode":"98101",
    "sg:province":"WA",
    "sg:tags":[
        "guitar",
        "amplifier",
        "dvd's",
        "store"
    ],
    "wof:name":"Holy Cow Records",
    "wof:placetype":"venue"
},
  "geometry": {"coordinates":[-122.341003,47.608799],"type":"Point"}
}