{
  "type": "Feature",
  "properties": {
    "addr:full":"7534 Holmes Island Rd SE Lacey WA 98503",
    "addr:housenumber":"7534",
    "addr:postcode":"98503",
    "addr:street":"Holmes Island Rd Se",
    "iso:country":"US",
    "sg:address":"7534 Holmes Island Rd SE",
    "sg:city":"Lacey",
    "sg:classifiers":[
        {
            "category":"Professional",
            "subcategory":"Management & Consulting",
            "type":"Services"
        }
    ],
    "sg:phone":"+1 360 923 5466",
    "sg:postcode":"98503",
    "sg:province":"WA",
    "sg:tags":[
        "public",
        "relations"
    ],
    "wof:name":"Public Affairs Assoc",
    "wof:placetype":"venue"
},
  "geometry": {"coordinates":[-122.78052099999999,47.024329],"type":"Point"}
}