{
  "type": "Feature",
  "properties": {
    "iso:country":"US",
    "sg:address":"202 Lands End Ln",
    "sg:city":"Sequim",
    "sg:classifiers":[
        {
            "category":"Professional",
            "subcategory":"Employment Agencies",
            "type":"Services"
        }
    ],
    "sg:phone":"+1 360 460 5936",
    "sg:postcode":"98382",
    "sg:province":"WA",
    "sg:tags":[
        "cargo",
        "pilot",
        "air"
    ],
    "wof:name":"Mountain High Aviation LLC",
    "wof:placetype":"venue"
},
  "geometry": {"coordinates":[-123.205791,48.13067],"type":"Point"}
}