{
  "type": "Feature",
  "properties": {
    "addr:full":"3709 S G St Tacoma WA 98418",
    "addr:housenumber":"3709",
    "addr:postcode":"98418",
    "addr:street":"S G St",
    "iso:country":"US",
    "sg:address":"3709 S G St",
    "sg:city":"Tacoma",
    "sg:classifiers":[
        {
            "category":"Restaurant",
            "type":"Food & Drink"
        }
    ],
    "sg:phone":"+1 253 475 1881",
    "sg:postcode":"98418",
    "sg:province":"WA",
    "sg:tags":[
        "soul"
    ],
    "wof:name":"Uncle Thurms Soul Food",
    "wof:placetype":"venue"
},
  "geometry": {"coordinates":[-122.440652,47.224553],"type":"Point"}
}