{
  "type": "Feature",
  "properties": {
    "addr:full":"14211 16th St E Sumner WA 98390",
    "addr:housenumber":"14211",
    "addr:postcode":"98390",
    "addr:street":"16Th St E",
    "iso:country":"US",
    "sg:address":"14211 16th St E",
    "sg:city":"Sumner",
    "sg:classifiers":[
        {
            "category":"Building & Trades",
            "subcategory":"Construction",
            "type":"Services"
        }
    ],
    "sg:phone":"+1 253 891 1311",
    "sg:postcode":"98390",
    "sg:province":"WA",
    "sg:tags":[
        "heavy"
    ],
    "wof:name":"Dmi",
    "wof:placetype":"venue"
},
  "geometry": {"coordinates":[-122.240296,47.242927],"type":"Point"}
}