{
  "type": "Feature",
  "properties": {
    "addr:full":"3318 18th Ave SE Olympia WA 98501",
    "addr:housenumber":"3318",
    "addr:postcode":"98501",
    "addr:street":"18Th Ave Se",
    "iso:country":"US",
    "sg:address":"3318 18th Ave SE",
    "sg:city":"Olympia",
    "sg:classifiers":[
        {
            "category":"Shopping",
            "subcategory":"Gifts & Souvenirs",
            "type":"Retail Goods"
        }
    ],
    "sg:phone":"+1 360 455 1128",
    "sg:postcode":"98501",
    "sg:province":"WA",
    "wof:name":"Armchair Crafts",
    "wof:placetype":"venue"
},
  "geometry": {"coordinates":[-122.849645,47.032566],"type":"Point"}
}