{
  "type": "Feature",
  "properties": {
    "addr:full":"1118 Finnegan Way Bellingham WA 98225",
    "addr:housenumber":"1118",
    "addr:postcode":"98225",
    "addr:street":"Finnegan Way",
    "iso:country":"US",
    "sg:address":"1118 Finnegan Way",
    "sg:city":"Bellingham",
    "sg:classifiers":[
        {
            "category":"Professional",
            "subcategory":"Lawyer & Legal Services",
            "type":"Services"
        }
    ],
    "sg:phone":"+1 360 671 2977",
    "sg:postcode":"98225",
    "sg:province":"WA",
    "sg:tags":[
        "attorney"
    ],
    "wof:name":"Denise C George",
    "wof:placetype":"venue"
},
  "geometry": {"coordinates":[-122.503147,48.722691],"type":"Point"}
}