{
  "type": "Feature",
  "properties": {
    "addr:full":"9530 Aurora Ave N Ste 200 Seattle WA 98103",
    "addr:housenumber":"9530",
    "addr:postcode":"98103",
    "addr:street":"Aurora Ave N Ste 200",
    "iso:country":"US",
    "sg:address":"9530 Aurora Ave N Ste 200",
    "sg:city":"Seattle",
    "sg:classifiers":[
        {
            "category":"Building & Trades",
            "subcategory":"Construction",
            "type":"Services"
        }
    ],
    "sg:phone":"+1 206 374 0222",
    "sg:postcode":"98103",
    "sg:province":"WA",
    "sg:tags":[
        "air",
        "heating",
        "conditioning/hvac"
    ],
    "wof:name":"Fm Hvac Sales Co",
    "wof:placetype":"venue"
},
  "geometry": {"coordinates":[-122.344589,47.698138],"type":"Point"}
}