{
  "type": "Feature",
  "properties": {
    "addr:full":"6014 238th St SE Woodinville WA 98072",
    "addr:housenumber":"6014",
    "addr:postcode":"98072",
    "addr:street":"238Th St Se",
    "iso:country":"US",
    "sg:address":"6014 238th St SE",
    "sg:city":"Woodinville",
    "sg:classifiers":[
        {
            "category":"Autos & Motor Vehicles",
            "subcategory":"Automobile Sales",
            "type":"Retail Goods"
        },
        {
            "category":"Utilities",
            "subcategory":"Recycling",
            "type":"Services"
        },
        {
            "category":"Wholesale",
            "subcategory":"Scrap",
            "type":"Manufacturing & Wholesale Goods"
        },
        {
            "category":"Shopping",
            "subcategory":"Discount & Variety Stores",
            "type":"Retail Goods"
        }
    ],
    "sg:phone":"+1 425 481 1828",
    "sg:postcode":"98072",
    "sg:province":"WA",
    "sg:tags":[
        "surplus",
        "wrecking",
        "metal",
        "truck",
        "metals-wholesale",
        "salvage",
        "merchandise"
    ],
    "sg:website":"http://www.arrowmetalscorp.com",
    "wof:name":"Arrow Metals Corp",
    "wof:placetype":"venue"
},
  "geometry": {"coordinates":[-122.153898,47.781646],"type":"Point"}
}