{
  "type": "Feature",
  "properties": {
    "addr:full":"151 Cunningham Rd Kelso WA 98626",
    "addr:housenumber":"151",
    "addr:postcode":"98626",
    "addr:street":"Cunningham Rd",
    "iso:country":"US",
    "sg:address":"151 Cunningham Rd",
    "sg:city":"Kelso",
    "sg:classifiers":[
        {
            "category":"Building & Trades",
            "subcategory":"Construction",
            "type":"Services"
        }
    ],
    "sg:phone":"+1 360 423 0418",
    "sg:postcode":"98626",
    "sg:province":"WA",
    "sg:tags":[
        "handyman"
    ],
    "wof:name":"B B's Repair Svc",
    "wof:placetype":"venue"
},
  "geometry": {"coordinates":[-122.82363700000001,46.091788],"type":"Point"}
}