{
  "type": "Feature",
  "properties": {
    "addr:full":"2712 Esther St Vancouver WA 98660",
    "addr:housenumber":"2712",
    "addr:postcode":"98660",
    "addr:street":"Esther St",
    "iso:country":"US",
    "sg:address":"2712 Esther St",
    "sg:city":"Vancouver",
    "sg:classifiers":[
        {
            "category":"Wholesale",
            "subcategory":"Music Publishers",
            "type":"Manufacturing & Wholesale Goods"
        }
    ],
    "sg:phone":"+1 360 693 7085",
    "sg:postcode":"98660",
    "sg:province":"WA",
    "sg:tags":[
        "distribution"
    ],
    "wof:name":"Factory West Studio",
    "wof:placetype":"venue"
},
  "geometry": {"coordinates":[-122.675569,45.641121],"type":"Point"}
}