{
  "type": "Feature",
  "properties": {
    "addr:full":"1737 NW 56th St Seattle WA 98107",
    "addr:housenumber":"1737",
    "addr:postcode":"98107",
    "addr:street":"Nw 56Th St",
    "iso:country":"US",
    "sg:address":"1737 NW 56th St",
    "sg:city":"Seattle",
    "sg:classifiers":[
        {
            "category":"Building & Trades",
            "subcategory":"Construction",
            "type":"Services"
        }
    ],
    "sg:phone":"+1 206 706 1123",
    "sg:postcode":"98107",
    "sg:province":"WA",
    "sg:tags":[
        "contractor"
    ],
    "sg:website":"www.fradkinfineconstruction.com",
    "wof:name":"Fradkin Mittendorf Fine Construction",
    "wof:placetype":"venue"
},
  "geometry": {"coordinates":[-122.38043999999999,47.669338],"type":"Point"}
}