{
  "type": "Feature",
  "properties": {
    "addr:full":"700 Sky Meadow Dr Centralia WA 98531",
    "addr:housenumber":"700",
    "addr:postcode":"98531",
    "addr:street":"Sky Meadow Dr",
    "iso:country":"US",
    "sg:address":"700 Sky Meadow Dr",
    "sg:city":"Centralia",
    "sg:classifiers":[
        {
            "category":"Professional",
            "subcategory":"Management & Consulting",
            "type":"Services"
        }
    ],
    "sg:phone":"+1 360 736 2332",
    "sg:postcode":"98531",
    "sg:province":"WA",
    "sg:tags":[
        "business"
    ],
    "wof:name":"Johnstone & Assoc",
    "wof:placetype":"venue"
},
  "geometry": {"coordinates":[-122.933813,46.722635],"type":"Point"}
}