{
  "type": "Feature",
  "properties": {
    "addr:full":"30803 22nd Ave SW Federal Way WA 98023",
    "addr:housenumber":"30803",
    "addr:postcode":"98023",
    "addr:street":"22Nd Ave Sw Federal Way",
    "iso:country":"US",
    "sg:address":"30803 22nd Ave SW",
    "sg:city":"Federal Way",
    "sg:classifiers":[
        {
            "category":"Manufacturing",
            "subcategory":"Signs",
            "type":"Manufacturing & Wholesale Goods"
        }
    ],
    "sg:phone":"+1 253 874 4749",
    "sg:postcode":"98023",
    "sg:province":"WA",
    "sg:tags":[
        "commercial",
        "specialty",
        "mfg"
    ],
    "wof:name":"Signs Systems Plus Inc",
    "wof:placetype":"venue"
},
  "geometry": {"coordinates":[-122.36246199999999,47.3261],"type":"Point"}
}