{
  "type": "Feature",
  "properties": {
    "iso:country":"US",
    "sg:address":"801 C St SW",
    "sg:city":"Auburn",
    "sg:classifiers":[
        {
            "category":"Retail",
            "subcategory":"Auto Repair",
            "type":"Services"
        }
    ],
    "sg:phone":"+1 253 887 9032",
    "sg:postcode":"98001",
    "sg:province":"WA",
    "sg:tags":[
        "automotive"
    ],
    "wof:name":"Outback Muffler & Brake",
    "wof:placetype":"venue"
},
  "geometry": {"coordinates":[-122.232344,47.300868],"type":"Point"}
}