{
  "type": "Feature",
  "properties": {
    "addr:full":"2159 Ivy St Port Townsend WA 98368",
    "addr:housenumber":"2159",
    "addr:postcode":"98368",
    "addr:street":"Ivy St",
    "iso:country":"US",
    "sg:address":"2159 Ivy St",
    "sg:city":"Port Townsend",
    "sg:classifiers":[
        {
            "category":"Personal",
            "type":"Services"
        }
    ],
    "sg:phone":"+1 360 379 5255",
    "sg:postcode":"98368",
    "sg:province":"WA",
    "sg:tags":[
        "therapist",
        "massage"
    ],
    "wof:name":"Sunlight Massage Therapies",
    "wof:placetype":"venue"
},
  "geometry": {"coordinates":[-122.813463,48.11615],"type":"Point"}
}