{
  "type": "Feature",
  "properties": {
    "addr:full":"16398 NE 85th St Ste 100 Redmond WA 98052",
    "addr:housenumber":"16398",
    "addr:postcode":"98052",
    "addr:street":"Ne 85Th St Ste 100",
    "iso:country":"US",
    "sg:address":"16398 NE 85th St Ste 100",
    "sg:city":"Redmond",
    "sg:classifiers":[
        {
            "category":"Insurance",
            "subcategory":"Insurance Agent",
            "type":"Services"
        },
        {
            "category":"Insurance",
            "subcategory":"Life Insurance",
            "type":"Services"
        },
        {
            "category":"Insurance",
            "subcategory":"Title Insurance",
            "type":"Services"
        }
    ],
    "sg:phone":"+1 425 242 4359",
    "sg:postcode":"98052",
    "sg:province":"WA",
    "sg:tags":[
        "auto",
        "homeowner"
    ],
    "sg:website":"http://www.silvermarkinsurance.com",
    "wof:name":"Silvermark Inc.",
    "wof:placetype":"venue"
},
  "geometry": {"coordinates":[-122.12159,47.67849],"type":"Point"}
}