{
  "type": "Feature",
  "properties": {
    "addr:full":"2343 Stevenson Ave Enumclaw WA 98022",
    "addr:housenumber":"2343",
    "addr:postcode":"98022",
    "addr:street":"Stevenson Ave",
    "iso:country":"US",
    "sg:address":"2343 Stevenson Ave",
    "sg:city":"Enumclaw",
    "sg:classifiers":[
        {
            "category":"Building & Trades",
            "subcategory":"Landscaping Services",
            "type":"Services"
        }
    ],
    "sg:phone":"+1 360 802 0941",
    "sg:postcode":"98022",
    "sg:province":"WA",
    "sg:tags":[
        "landscape"
    ],
    "wof:name":"Olympic Landscape",
    "wof:placetype":"venue"
},
  "geometry": {"coordinates":[-121.999689,47.20395],"type":"Point"}
}