{
  "type": "Feature",
  "properties": {
    "iso:country":"US",
    "sg:address":"7118 N Mahr Ct",
    "sg:city":"Spokane",
    "sg:classifiers":[
        {
            "category":"Building & Trades",
            "subcategory":"Construction",
            "type":"Services"
        }
    ],
    "sg:phone":"+1 509 464 3234",
    "sg:postcode":"99208",
    "sg:province":"WA",
    "sg:tags":[
        "house"
    ],
    "wof:name":"Flegel Building Contractors",
    "wof:placetype":"venue"
},
  "geometry": {"coordinates":[-117.428346,47.725645],"type":"Point"}
}