{
  "type": "Feature",
  "properties": {
    "addr:full":"1605 Pine View Dr NW Issaquah WA 98027",
    "addr:housenumber":"1605",
    "addr:postcode":"98027",
    "addr:street":"Pine View Dr Nw",
    "iso:country":"US",
    "sg:address":"1605 Pine View Dr NW",
    "sg:city":"Issaquah",
    "sg:classifiers":[
        {
            "category":"Professional",
            "subcategory":"Management & Consulting",
            "type":"Services"
        }
    ],
    "sg:phone":"+1 425 427 5118",
    "sg:postcode":"98027",
    "sg:province":"WA",
    "sg:tags":[
        "business"
    ],
    "wof:name":"Limerick Consulting",
    "wof:placetype":"venue"
},
  "geometry": {"coordinates":[-122.078276,47.550925],"type":"Point"}
}