{
  "type": "Feature",
  "properties": {
    "addr:full":"2334 4th Ave Seattle WA 98121",
    "addr:housenumber":"2334",
    "addr:postcode":"98121",
    "addr:street":"4Th Ave",
    "iso:country":"US",
    "sg:address":"2334 4th Ave",
    "sg:city":"Seattle",
    "sg:classifiers":[
        {
            "category":"Government",
            "subcategory":"Fire Station",
            "type":"Public Place"
        }
    ],
    "sg:phone":"+1 206 386 1400",
    "sg:postcode":"98121",
    "sg:province":"WA",
    "sg:tags":[
        "protection"
    ],
    "wof:name":"Fire Station 2",
    "wof:placetype":"venue"
},
  "geometry": {"coordinates":[-122.344848,47.615907],"type":"Point"}
}