{
  "type": "Feature",
  "properties": {
    "iso:country":"US",
    "sg:address":"8191 Delta Line Rd",
    "sg:city":"Custer",
    "sg:classifiers":[
        {
            "category":"Retail",
            "subcategory":"Repair Shop",
            "type":"Services"
        }
    ],
    "sg:phone":"+1 360 366 1018",
    "sg:postcode":"98240",
    "sg:province":"WA",
    "wof:name":"Wildlife Art Taxidermy",
    "wof:placetype":"venue"
},
  "geometry": {"coordinates":[-122.616248,48.941733],"type":"Point"}
}