{
  "type": "Feature",
  "properties": {
    "addr:full":"4204 Candlewood Ct SE Lacey WA 98503",
    "addr:housenumber":"4204",
    "addr:postcode":"98503",
    "addr:street":"Candlewood Ct Se",
    "iso:country":"US",
    "sg:address":"4204 Candlewood Ct SE",
    "sg:city":"Lacey",
    "sg:classifiers":[
        {
            "category":"Professional",
            "subcategory":"Business Services",
            "type":"Services"
        }
    ],
    "sg:phone":"+1 360 456 4981",
    "sg:postcode":"98503",
    "sg:province":"WA",
    "wof:name":"Olympia Ski Group",
    "wof:placetype":"venue"
},
  "geometry": {"coordinates":[-122.782628,47.008775],"type":"Point"}
}