{
  "type": "Feature",
  "properties": {
    "addr:full":"11555 SE 8th St Bellevue WA 98004",
    "addr:housenumber":"11555",
    "addr:postcode":"98004",
    "addr:street":"Se 8Th St",
    "iso:country":"US",
    "sg:address":"11555 SE 8th St",
    "sg:city":"Bellevue",
    "sg:classifiers":[
        {
            "category":"Professional",
            "type":"Services"
        },
        {
            "category":"Personal",
            "type":"Services"
        }
    ],
    "sg:phone":"+1 425 709 9610",
    "sg:postcode":"98004",
    "sg:province":"WA",
    "sg:tags":[
        "full",
        "material",
        "storage",
        "moving",
        "services-labor",
        "mover"
    ],
    "wof:name":"Project",
    "wof:placetype":"venue"
},
  "geometry": {"coordinates":[-122.186756,47.601853],"type":"Point"}
}