{
  "type": "Feature",
  "properties": {
    "addr:full":"2850 McKenzie Ave Bellingham WA 98225",
    "addr:housenumber":"2850",
    "addr:postcode":"98225",
    "addr:street":"Mckenzie Ave",
    "iso:country":"US",
    "sg:address":"2850 McKenzie Ave",
    "sg:city":"Bellingham",
    "sg:classifiers":[
        {
            "category":"Building & Trades",
            "subcategory":"Construction",
            "type":"Services"
        }
    ],
    "sg:phone":"+1 360 671 5003",
    "sg:postcode":"98225",
    "sg:province":"WA",
    "sg:tags":[
        "house"
    ],
    "wof:name":"Jewel Coast Construction",
    "wof:placetype":"venue"
},
  "geometry": {"coordinates":[-122.481105,48.719117],"type":"Point"}
}