{
  "type": "Feature",
  "properties": {
    "addr:full":"1819 S 116th St Seattle WA 98168",
    "addr:housenumber":"1819",
    "addr:postcode":"98168",
    "addr:street":"S 116Th St",
    "iso:country":"US",
    "sg:address":"1819 S 116th St",
    "sg:city":"Seattle",
    "sg:classifiers":[
        {
            "category":"Real Estate",
            "subcategory":"Real Estate Operator",
            "type":"Services"
        }
    ],
    "sg:phone":"+1 206 323 9642",
    "sg:postcode":"98168",
    "sg:province":"WA",
    "sg:tags":[
        "building",
        "apartment"
    ],
    "wof:name":"First Afrcan Mthdst Epscpalian",
    "wof:placetype":"venue"
},
  "geometry": {"coordinates":[-122.308087,47.499241],"type":"Point"}
}