{
  "type": "Feature",
  "properties": {
    "addr:full":"11 105th Ave SE Ste 9 Bellevue WA 98004",
    "addr:housenumber":"11",
    "addr:postcode":"98004",
    "addr:street":"105Th Ave Se Ste 9",
    "iso:country":"US",
    "sg:address":"11 105th Ave SE Ste 9",
    "sg:city":"Bellevue",
    "sg:classifiers":[
        {
            "category":"Banks & Credit Unions",
            "subcategory":"Financial Services",
            "type":"Services"
        }
    ],
    "sg:phone":"+1 425 688 8460",
    "sg:postcode":"98004",
    "sg:province":"WA",
    "sg:tags":[
        "broker",
        "mortgage"
    ],
    "wof:name":"Cornwall Real Estate Services Llc",
    "wof:placetype":"venue"
},
  "geometry": {"coordinates":[-122.199997,47.6101],"type":"Point"}
}