{
  "type": "Feature",
  "properties": {
    "addr:full":"12211 78th Ave E Puyallup WA 98373",
    "addr:housenumber":"12211",
    "addr:postcode":"98373",
    "addr:street":"78Th Ave E",
    "iso:country":"US",
    "sg:address":"12211 78th Ave E",
    "sg:city":"Puyallup",
    "sg:classifiers":[
        {
            "category":"Building & Trades",
            "subcategory":"Cleaning & Sanitation",
            "type":"Services"
        }
    ],
    "sg:phone":"+1 253 845 1201",
    "sg:postcode":"98373",
    "sg:province":"WA",
    "sg:tags":[
        "maintenance"
    ],
    "wof:name":"Windom Window Service",
    "wof:placetype":"venue"
},
  "geometry": {"coordinates":[-122.32540400000001,47.144019],"type":"Point"}
}