{
  "type": "Feature",
  "properties": {
    "addr:full":"449 Melva Ln Moses Lake WA 98837",
    "addr:housenumber":"449",
    "addr:postcode":"98837",
    "addr:street":"Melva Ln",
    "iso:country":"US",
    "sg:address":"449 Melva Ln",
    "sg:city":"Moses Lake",
    "sg:classifiers":[
        {
            "category":"Travel",
            "subcategory":"Hotels & Motels",
            "type":"Entertainment"
        }
    ],
    "sg:phone":"+1 509 765 8886",
    "sg:postcode":"98837",
    "sg:province":"WA",
    "wof:name":"Super 8 Motel",
    "wof:placetype":"venue"
},
  "geometry": {"coordinates":[-119.313157,47.102005],"type":"Point"}
}