{
  "type": "Feature",
  "properties": {
    "addr:full":"408 25th St SE Auburn WA 98002",
    "addr:housenumber":"408",
    "addr:postcode":"98002",
    "addr:street":"25Th St Se",
    "iso:country":"US",
    "sg:address":"408 25th St SE",
    "sg:city":"Auburn",
    "sg:classifiers":[
        {
            "category":"Building & Trades",
            "subcategory":"Construction",
            "type":"Services"
        }
    ],
    "sg:phone":"+1 253 351 6465",
    "sg:postcode":"98002",
    "sg:province":"WA",
    "sg:tags":[
        "floor",
        "laying",
        "contractor"
    ],
    "wof:name":"Jesus Carpet Installation",
    "wof:placetype":"venue"
},
  "geometry": {"coordinates":[-122.221423,47.286342],"type":"Point"}
}