{
  "type": "Feature",
  "properties": {
    "addr:full":"991 Carpenter Rd Granger WA 98932",
    "addr:housenumber":"991",
    "addr:postcode":"98932",
    "addr:street":"Carpenter Rd",
    "iso:country":"US",
    "sg:address":"991 Carpenter Rd",
    "sg:city":"Granger",
    "sg:classifiers":[
        {
            "category":"Farming",
            "subcategory":"Orchard",
            "type":"Manufacturing & Wholesale Goods"
        }
    ],
    "sg:phone":"+1 509 854 1090",
    "sg:postcode":"98932",
    "sg:province":"WA",
    "sg:tags":[
        "farm",
        "fruit",
        "tree",
        "berry",
        "crop"
    ],
    "wof:name":"Jean S Butler",
    "wof:placetype":"venue"
},
  "geometry": {"coordinates":[-120.174606,46.382964],"type":"Point"}
}