{
  "type": "Feature",
  "properties": {
    "addr:full":"2380 Grandview Rd Ferndale WA 98248",
    "addr:housenumber":"2380",
    "addr:postcode":"98248",
    "addr:street":"Grandview Rd",
    "iso:country":"US",
    "sg:address":"2380 Grandview Rd",
    "sg:city":"Ferndale",
    "sg:classifiers":[
        {
            "category":"Mining & Drilling",
            "type":"Manufacturing & Wholesale Goods"
        }
    ],
    "sg:phone":"+1 360 366 3303",
    "sg:postcode":"98248",
    "sg:province":"WA",
    "sg:tags":[
        "building",
        "field",
        "construction",
        "industrial"
    ],
    "wof:name":"Wrs Pacific Coverall",
    "wof:placetype":"venue"
},
  "geometry": {"coordinates":[-122.614867,48.891859],"type":"Point"}
}