{
  "type": "Feature",
  "properties": {
    "addr:full":"246 W Manson Hwy Chelan WA 98816",
    "addr:housenumber":"246",
    "addr:postcode":"98816",
    "addr:street":"W Manson Hwy",
    "iso:country":"US",
    "sg:address":"246 W Manson Hwy",
    "sg:city":"Chelan",
    "sg:classifiers":[
        {
            "category":"Fast Food",
            "type":"Food & Drink"
        },
        {
            "category":"Restaurant",
            "type":"Food & Drink"
        }
    ],
    "sg:phone":"+1 509 682 5633",
    "sg:postcode":"98816",
    "sg:province":"WA",
    "sg:tags":[
        "mexican",
        "take"
    ],
    "wof:name":"La Brisa",
    "wof:placetype":"venue"
},
  "geometry": {"coordinates":[-120.020973,47.841609],"type":"Point"}
}