{
  "type": "Feature",
  "properties": {
    "addr:full":"8490 S 190th St Kent WA 98031",
    "addr:housenumber":"8490",
    "addr:postcode":"98031",
    "addr:street":"S 190Th St",
    "iso:country":"US",
    "sg:address":"8490 S 190th St",
    "sg:city":"Kent",
    "sg:classifiers":[
        {
            "category":"Professional",
            "type":"Services"
        }
    ],
    "sg:phone":"+1 877 338 1351",
    "sg:postcode":"98031",
    "sg:province":"WA",
    "sg:tags":[
        "material",
        "moving",
        "services-labor"
    ],
    "sg:website":"http://local.ingenio.com/Listings/Details.aspx?NUM=a%3a10064461%3a13%3a4859924%3a14%3a0%3a7",
    "wof:name":"Lincoln Moving & Storage Company",
    "wof:placetype":"venue"
},
  "geometry": {"coordinates":[-122.225173,47.432163],"type":"Point"}
}