{
  "type": "Feature",
  "properties": {
    "addr:full":"6910 Roosevelt Way NE Ste 106 Seattle WA 98115",
    "addr:housenumber":"6910",
    "addr:postcode":"98115",
    "addr:street":"Roosevelt Way Ne Ste 106",
    "iso:country":"US",
    "sg:address":"6910 Roosevelt Way NE Ste 106",
    "sg:city":"Seattle",
    "sg:classifiers":[
        {
            "category":"Personal",
            "type":"Services"
        }
    ],
    "sg:phone":"+1 206 522 0600",
    "sg:postcode":"98115",
    "sg:province":"WA",
    "sg:tags":[
        "mover"
    ],
    "sg:website":"www.budgetmovingwa.com/",
    "wof:name":"Budget Moving Inc",
    "wof:placetype":"venue"
},
  "geometry": {"coordinates":[-122.317421,47.678835],"type":"Point"}
}