{
  "type": "Feature",
  "properties": {
    "addr:full":"1801 N Walnut St # 2 Ellensburg WA 98926",
    "addr:housenumber":"1801",
    "addr:postcode":"98926",
    "addr:street":"N Walnut St # 2",
    "iso:country":"US",
    "sg:address":"1801 N Walnut St # 2",
    "sg:city":"Ellensburg",
    "sg:phone":"+1 509 962 5400",
    "sg:postcode":"98926",
    "sg:province":"WA",
    "wof:name":"Wing Central",
    "wof:placetype":"venue"
},
  "geometry": {"coordinates":[-120.539703,47.010349],"type":"Point"}
}