{
  "type": "Feature",
  "properties": {
    "addr:full":"9024 15th Ave NW Seattle WA 98117",
    "addr:housenumber":"9024",
    "addr:postcode":"98117",
    "addr:street":"15Th Ave Nw",
    "iso:country":"US",
    "sg:address":"9024 15th Ave NW",
    "sg:city":"Seattle",
    "sg:classifiers":[
        {
            "category":"Manufacturing",
            "subcategory":"Printing",
            "type":"Manufacturing & Wholesale Goods"
        }
    ],
    "sg:phone":"+1 206 782 0757",
    "sg:postcode":"98117",
    "sg:province":"WA",
    "sg:tags":[
        "commercial",
        "business",
        "card"
    ],
    "wof:name":"Marcards",
    "wof:placetype":"venue"
},
  "geometry": {"coordinates":[-122.376801,47.69498],"type":"Point"}
}