{
  "type": "Feature",
  "properties": {
    "addr:full":"5420 104th St SW Lakewood WA 98499",
    "addr:housenumber":"5420",
    "addr:postcode":"98499",
    "addr:street":"104Th St Sw",
    "iso:country":"US",
    "sg:address":"5420 104th St SW",
    "sg:city":"Lakewood",
    "sg:classifiers":[
        {
            "category":"Place Of Worship",
            "subcategory":"Church",
            "type":"Public Place"
        },
        {
            "category":"Place Of Worship",
            "type":"Public Place"
        }
    ],
    "sg:phone":"+1 253 584 6246",
    "sg:postcode":"98499",
    "sg:province":"WA",
    "sg:tags":[
        "jesus",
        "churches-church",
        "christ",
        "saint",
        "latter-day"
    ],
    "wof:name":"Lakewood Washington Ward",
    "wof:placetype":"venue"
},
  "geometry": {"coordinates":[-122.508331,47.162699],"type":"Point"}
}