{
  "type": "Feature",
  "properties": {
    "addr:full":"7249 NE Vincent Rd Bainbridge Isle WA 98110",
    "addr:housenumber":"7249",
    "addr:postcode":"98110",
    "addr:street":"Ne Vincent Rd;Isle",
    "iso:country":"US",
    "sg:address":"7249 NE Vincent Rd",
    "sg:city":"Bainbridge Isle",
    "sg:classifiers":[
        {
            "category":"Building & Trades",
            "subcategory":"Landscaping Services",
            "type":"Services"
        }
    ],
    "sg:phone":"+1 206 842 0212",
    "sg:postcode":"98110",
    "sg:province":"WA",
    "sg:tags":[
        "lawn",
        "maintenance",
        "grounds"
    ],
    "wof:name":"All Seasons",
    "wof:placetype":"venue"
},
  "geometry": {"coordinates":[-122.552643,47.621286],"type":"Point"}
}