{
  "type": "Feature",
  "properties": {
    "addr:full":"6420 131st Ave SE Bellevue WA 98006",
    "addr:housenumber":"6420",
    "addr:postcode":"98006",
    "addr:street":"131St Ave Se",
    "iso:country":"US",
    "sg:address":"6420 131st Ave SE",
    "sg:city":"Bellevue",
    "sg:classifiers":[
        {
            "category":"Social Services",
            "type":"Services"
        }
    ],
    "sg:phone":"+1 425 562 3534",
    "sg:postcode":"98006",
    "sg:province":"WA",
    "wof:name":"Nite n Day Adult Family",
    "wof:placetype":"venue"
},
  "geometry": {"coordinates":[-122.16502800000001,47.543718],"type":"Point"}
}