{
  "type": "Feature",
  "properties": {
    "addr:full":"22630 Sofie Rd Monroe WA 98272",
    "addr:postcode":"22630;98272",
    "addr:street":"Sofie Rd",
    "iso:country":"US",
    "sg:address":"22630 Sofie Rd",
    "sg:city":"Monroe",
    "sg:classifiers":[
        {
            "category":"Farming",
            "subcategory":"Dairy Farm",
            "type":"Manufacturing & Wholesale Goods"
        }
    ],
    "sg:phone":"+1 360 794 8829",
    "sg:postcode":"98272",
    "sg:province":"WA",
    "wof:name":"Robert E Nash",
    "wof:placetype":"venue"
},
  "geometry": {"coordinates":[-121.907707,47.854199],"type":"Point"}
}