{
  "type": "Feature",
  "properties": {
    "addr:full":"16810 NE 79th St Redmond WA 98052",
    "addr:housenumber":"16810",
    "addr:postcode":"98052",
    "addr:street":"Ne 79Th St",
    "iso:country":"US",
    "sg:address":"16810 NE 79th St",
    "sg:city":"Redmond",
    "sg:classifiers":[
        {
            "category":"Health Services",
            "subcategory":"Health Practitioner",
            "type":"Services"
        }
    ],
    "sg:phone":"+1 425 497 9734",
    "sg:postcode":"98052",
    "sg:province":"WA",
    "wof:name":"Chao Yong Jiang Dr",
    "wof:placetype":"venue"
},
  "geometry": {"coordinates":[-122.115163,47.673523],"type":"Point"}
}