{
  "type": "Feature",
  "properties": {
    "addr:full":"34521 N Dunn Rd Chattaroy WA 99003",
    "addr:housenumber":"34521",
    "addr:postcode":"99003",
    "addr:street":"N Dunn Rd",
    "iso:country":"US",
    "sg:address":"34521 N Dunn Rd",
    "sg:city":"Chattaroy",
    "sg:classifiers":[
        {
            "category":"Building & Trades",
            "subcategory":"Construction",
            "type":"Services"
        }
    ],
    "sg:phone":"+1 509 292 2726",
    "sg:postcode":"99003",
    "sg:province":"WA",
    "sg:tags":[
        "house"
    ],
    "wof:name":"Steve Jorgensen Construction",
    "wof:placetype":"venue"
},
  "geometry": {"coordinates":[-117.278496,47.963629],"type":"Point"}
}