{
  "type": "Feature",
  "properties": {
    "addr:full":"2130 Harbor Ave SW Seattle WA 98126",
    "addr:housenumber":"2130",
    "addr:postcode":"98126",
    "addr:street":"Harbor Ave Sw",
    "iso:country":"US",
    "sg:address":"2130 Harbor Ave SW",
    "sg:city":"Seattle",
    "sg:classifiers":[
        {
            "category":"Wholesale",
            "subcategory":"Seafood",
            "type":"Manufacturing & Wholesale Goods"
        }
    ],
    "sg:phone":"+1 206 933 8433",
    "sg:postcode":"98126",
    "sg:province":"WA",
    "sg:website":"www.crabfresh.com",
    "wof:name":"Crab Fresh Inc",
    "wof:placetype":"venue"
},
  "geometry": {"coordinates":[-122.37599899999999,47.5849],"type":"Point"}
}