{
  "type": "Feature",
  "properties": {
    "addr:full":"2817 W McManamon Rd Othello WA 99344",
    "addr:housenumber":"2817",
    "addr:postcode":"99344",
    "addr:street":"W Mcmanamon Rd",
    "iso:country":"US",
    "sg:address":"2817 W McManamon Rd",
    "sg:city":"Othello",
    "sg:classifiers":[
        {
            "category":"Freight",
            "type":"Transportation"
        }
    ],
    "sg:phone":"+1 509 346 2530",
    "sg:postcode":"99344",
    "sg:province":"WA",
    "sg:tags":[
        "operator",
        "local",
        "trucking"
    ],
    "wof:name":"Larry Socorro Trucking",
    "wof:placetype":"venue"
},
  "geometry": {"coordinates":[-119.33277,46.912587],"type":"Point"}
}