{
  "type": "Feature",
  "properties": {
    "addr:full":"325 9th Ave Seattle WA 98104",
    "addr:housenumber":"325",
    "addr:postcode":"98104",
    "addr:street":"9Th Ave",
    "iso:country":"US",
    "sg:address":"325 9th Ave",
    "sg:city":"Seattle",
    "sg:classifiers":[
        {
            "category":"Health Services",
            "subcategory":"Doctor",
            "type":"Services"
        }
    ],
    "sg:phone":"+1 206 731 3111",
    "sg:postcode":"98104",
    "sg:province":"WA",
    "sg:tags":[
        "medical"
    ],
    "wof:name":"Chronic Fatigue Clinic",
    "wof:placetype":"venue"
},
  "geometry": {"coordinates":[-122.323251,47.603705],"type":"Point"}
}