{
  "type": "Feature",
  "properties": {
    "addr:full":"1508 Pike Pl Seattle WA 98101",
    "addr:housenumber":"1508",
    "addr:postcode":"98101",
    "addr:street":"Pike Pl",
    "iso:country":"US",
    "sg:address":"1508 Pike Pl",
    "sg:city":"Seattle",
    "sg:classifiers":[
        {
            "category":"Food & Beverages",
            "subcategory":"Dairy",
            "type":"Retail Goods"
        }
    ],
    "sg:phone":"+1 206 624 4029",
    "sg:postcode":"98101",
    "sg:province":"WA",
    "sg:tags":[
        "cheese",
        "grocery"
    ],
    "wof:name":"Pike Place Market",
    "wof:placetype":"venue"
},
  "geometry": {"coordinates":[-122.34062,47.608908],"type":"Point"}
}