{
  "type": "Feature",
  "properties": {
    "addr:full":"7616 139th Pl NE Redmond WA 98052",
    "addr:housenumber":"7616",
    "addr:postcode":"98052",
    "addr:street":"139Th Pl Ne",
    "iso:country":"US",
    "sg:address":"7616 139th Pl NE",
    "sg:city":"Redmond",
    "sg:classifiers":[
        {
            "category":"Arena",
            "subcategory":"Sports Club",
            "type":"Entertainment"
        },
        {
            "category":"Sports & Exercise",
            "subcategory":"Sports Center",
            "type":"Entertainment"
        },
        {
            "category":"Sports & Exercise",
            "subcategory":"Swimming Pool",
            "type":"Entertainment"
        }
    ],
    "sg:phone":"+1 425 885 6464",
    "sg:postcode":"98052",
    "sg:province":"WA",
    "sg:tags":[
        "pools-private"
    ],
    "wof:name":"Strattonwood Swim Club",
    "wof:placetype":"venue"
},
  "geometry": {"coordinates":[-122.15401900000001,47.672345],"type":"Point"}
}