{
  "type": "Feature",
  "properties": {
    "iso:country":"US",
    "sg:address":"1606 E 31st St",
    "sg:city":"Tacoma",
    "sg:classifiers":[
        {
            "category":"Social Services",
            "subcategory":"Adult Care",
            "type":"Services"
        },
        {
            "category":"Social Services",
            "type":"Services"
        }
    ],
    "sg:phone":"+1 253 572 7741",
    "sg:postcode":"98404",
    "sg:province":"WA",
    "sg:tags":[
        "foster",
        "related",
        "child"
    ],
    "sg:website":"www.rainbowyfstacwa.com",
    "wof:name":"Rainbow Youth & Family Svcs",
    "wof:placetype":"venue"
},
  "geometry": {"coordinates":[-122.40676499999999,47.235948],"type":"Point"}
}