{
  "type": "Feature",
  "properties": {
    "addr:full":"123 174th St SW Bothell WA 98012",
    "addr:housenumber":"123",
    "addr:postcode":"98012",
    "addr:street":"174Th St Sw",
    "iso:country":"US",
    "sg:address":"123 174th St SW",
    "sg:city":"Bothell",
    "sg:classifiers":[
        {
            "category":"Manufacturing",
            "subcategory":"Metals",
            "type":"Manufacturing & Wholesale Goods"
        }
    ],
    "sg:phone":"+1 425 742 9374",
    "sg:postcode":"98012",
    "sg:province":"WA",
    "sg:tags":[
        "blast",
        "furnace",
        "works"
    ],
    "wof:name":"Williams Maufacturing",
    "wof:placetype":"venue"
},
  "geometry": {"coordinates":[-122.234799,47.8407],"type":"Point"}
}