{
  "type": "Feature",
  "properties": {
    "addr:full":"5516 186th Pl SW Lynnwood WA 98037",
    "addr:housenumber":"5516",
    "addr:postcode":"98037",
    "addr:street":"186Th Pl Sw",
    "iso:country":"US",
    "sg:address":"5516 186th Pl SW",
    "sg:city":"Lynnwood",
    "sg:classifiers":[
        {
            "category":"Retail",
            "subcategory":"Auto Repair",
            "type":"Services"
        }
    ],
    "sg:phone":"+1 425 774 5504",
    "sg:postcode":"98037",
    "sg:province":"WA",
    "sg:tags":[
        "automotive",
        "carburetor"
    ],
    "wof:name":"Joe's Carburetors Inc",
    "wof:placetype":"venue"
},
  "geometry": {"coordinates":[-122.307744,47.830246],"type":"Point"}
}