{
  "type": "Feature",
  "properties": {
    "addr:full":"807 W Pine St Shelton WA 98584",
    "addr:housenumber":"807",
    "addr:postcode":"98584",
    "addr:street":"W Pine St",
    "iso:country":"US",
    "sg:address":"807 W Pine St",
    "sg:city":"Shelton",
    "sg:classifiers":[
        {
            "category":"Education",
            "subcategory":"School",
            "type":"Public Place"
        }
    ],
    "sg:phone":"+1 360 426 7664",
    "sg:postcode":"98584",
    "sg:province":"WA",
    "sg:website":"www.sheltonschools.org",
    "wof:name":"CHOICE High School",
    "wof:placetype":"venue"
},
  "geometry": {"coordinates":[-123.109196,47.215933],"type":"Point"}
}