{
  "type": "Feature",
  "properties": {
    "addr:full":"7509 86th St E Puyallup WA 98371",
    "addr:housenumber":"7509",
    "addr:postcode":"98371",
    "addr:street":"86Th St E",
    "iso:country":"US",
    "sg:address":"7509 86th St E",
    "sg:city":"Puyallup",
    "sg:classifiers":[
        {
            "category":"Manufacturing",
            "subcategory":"Printing",
            "type":"Manufacturing & Wholesale Goods"
        }
    ],
    "sg:phone":"+1 253 848 8031",
    "sg:postcode":"98371",
    "sg:province":"WA",
    "sg:tags":[
        "publisher",
        "software"
    ],
    "wof:name":"Old Goat Development",
    "wof:placetype":"venue"
},
  "geometry": {"coordinates":[-122.328142,47.178831],"type":"Point"}
}