{
  "type": "Feature",
  "properties": {
    "addr:full":"16915 W Charles Rd Nine Mile Falls WA 99026",
    "addr:housenumber":"16915",
    "addr:postcode":"99026",
    "addr:street":"W Charles Rd",
    "iso:country":"US",
    "sg:address":"16915 W Charles Rd",
    "sg:city":"Nine Mile Falls",
    "sg:classifiers":[
        {
            "category":"Personal",
            "type":"Services"
        }
    ],
    "sg:phone":"+1 509 466 4110",
    "sg:postcode":"99026",
    "sg:province":"WA",
    "wof:name":"Weight Room",
    "wof:placetype":"venue"
},
  "geometry": {"coordinates":[-117.643152,47.81155],"type":"Point"}
}