{
  "type": "Feature",
  "properties": {
    "addr:full":"6951 W Grandridge Blvd Kennewick WA 99336",
    "addr:housenumber":"6951",
    "addr:postcode":"99336",
    "addr:street":"W Grandridge Blvd",
    "iso:country":"US",
    "sg:address":"6951 W Grandridge Blvd",
    "sg:city":"Kennewick",
    "sg:classifiers":[
        {
            "category":"Building & Trades",
            "subcategory":"Equipment Rental",
            "type":"Services"
        }
    ],
    "sg:phone":"+1 509 735 2875",
    "sg:postcode":"99336",
    "sg:province":"WA",
    "sg:tags":[
        "aircraft",
        "instruction",
        "flight"
    ],
    "wof:name":"Kennewick Aircraft Svcs Inc",
    "wof:placetype":"venue"
},
  "geometry": {"coordinates":[-119.21392299999999,46.218741],"type":"Point"}
}