{
  "type": "Feature",
  "properties": {
    "addr:full":"12827 NE 135th St Kirkland WA 98034",
    "addr:housenumber":"12827",
    "addr:postcode":"98034",
    "addr:street":"Ne 135Th St",
    "iso:country":"US",
    "sg:address":"12827 NE 135th St",
    "sg:city":"Kirkland",
    "sg:classifiers":[
        {
            "category":"Building & Trades",
            "subcategory":"Landscaping Services",
            "type":"Services"
        }
    ],
    "sg:phone":"+1 425 753 6778",
    "sg:postcode":"98034",
    "sg:province":"WA",
    "wof:name":"LN's Gardening Service",
    "wof:placetype":"venue"
},
  "geometry": {"coordinates":[-122.168756,47.721369],"type":"Point"}
}