{
  "type": "Feature",
  "properties": {
    "addr:full":"12704 Pacific Hwy SW Lakewood WA 98499",
    "addr:housenumber":"12704",
    "addr:postcode":"98499",
    "addr:street":"Pacific Hwy Sw",
    "iso:country":"US",
    "sg:address":"12704 Pacific Hwy SW",
    "sg:city":"Lakewood",
    "sg:classifiers":[
        {
            "category":"Travel",
            "subcategory":"Hotels & Motels",
            "type":"Entertainment"
        }
    ],
    "sg:phone":"+1 253 581 5025",
    "sg:postcode":"98499",
    "sg:province":"WA",
    "sg:tags":[
        "operation"
    ],
    "wof:name":"Fort Clarke Motel",
    "wof:placetype":"venue"
},
  "geometry": {"coordinates":[-122.523477,47.138959],"type":"Point"}
}