{
  "type": "Feature",
  "properties": {
    "addr:full":"10900 NE 4th St Bellevue WA 98004",
    "addr:housenumber":"10900",
    "addr:postcode":"98004",
    "addr:street":"Ne 4Th St",
    "iso:country":"US",
    "sg:address":"10900 NE 4th St",
    "sg:city":"Bellevue",
    "sg:classifiers":[
        {
            "category":"Professional",
            "subcategory":"Lawyer & Legal Services",
            "type":"Services"
        }
    ],
    "sg:phone":"+1 425 467 4654",
    "sg:postcode":"98004",
    "sg:province":"WA",
    "sg:tags":[
        "plan"
    ],
    "wof:name":"Eaves Mathews Pllc",
    "wof:placetype":"venue"
},
  "geometry": {"coordinates":[-122.194883,47.613744],"type":"Point"}
}