{
  "type": "Feature",
  "properties": {
    "addr:full":"10522 Interlaaken Dr SW Lakewood WA 98498",
    "addr:housenumber":"10522",
    "addr:postcode":"98498",
    "addr:street":"Interlaaken Dr Sw",
    "iso:country":"US",
    "sg:address":"10522 Interlaaken Dr SW",
    "sg:city":"Lakewood",
    "sg:classifiers":[
        {
            "category":"Real Estate",
            "subcategory":"Architect",
            "type":"Services"
        }
    ],
    "sg:phone":"+1 253 581 4886",
    "sg:postcode":"98498",
    "sg:province":"WA",
    "sg:tags":[
        "architectural"
    ],
    "wof:name":"Dick A Hill Associates",
    "wof:placetype":"venue"
},
  "geometry": {"coordinates":[-122.541962,47.16125],"type":"Point"}
}