{
  "type": "Feature",
  "properties": {
    "addr:full":"7070 S 220th St Kent WA 98032",
    "addr:housenumber":"7070",
    "addr:postcode":"98032",
    "addr:street":"S 220Th St",
    "iso:country":"US",
    "sg:address":"7070 S 220th St",
    "sg:city":"Kent",
    "sg:classifiers":[
        {
            "category":"Freight",
            "type":"Transportation"
        }
    ],
    "sg:phone":"+1 253 872 7496",
    "sg:postcode":"98032",
    "sg:province":"WA",
    "sg:tags":[
        "operator",
        "local",
        "trucking"
    ],
    "wof:name":"Medical Delivery System Inc",
    "wof:placetype":"venue"
},
  "geometry": {"coordinates":[-122.24559600000001,47.404964],"type":"Point"}
}