{
  "type": "Feature",
  "properties": {
    "addr:full":"3409 W Laurelhurst Dr NE Seattle WA 98105",
    "addr:housenumber":"3409",
    "addr:postcode":"98105",
    "addr:street":"W Laurelhurst Dr Ne",
    "iso:country":"US",
    "sg:address":"3409 W Laurelhurst Dr NE",
    "sg:city":"Seattle",
    "sg:classifiers":[
        {
            "category":"Real Estate",
            "subcategory":"Real Estate Agent",
            "type":"Services"
        }
    ],
    "sg:phone":"+1 206 524 6370",
    "sg:postcode":"98105",
    "sg:province":"WA",
    "wof:name":"South Lander LLC",
    "wof:placetype":"venue"
},
  "geometry": {"coordinates":[-122.27949099999999,47.65401],"type":"Point"}
}