{
  "type": "Feature",
  "properties": {
    "addr:full":"2208 Frankfort St Richland WA 99352",
    "addr:housenumber":"2208",
    "addr:postcode":"99352",
    "addr:street":"Frankfort St",
    "iso:country":"US",
    "sg:address":"2208 Frankfort St",
    "sg:city":"Richland",
    "sg:classifiers":[
        {
            "category":"Professional",
            "subcategory":"Computer Services",
            "type":"Services"
        }
    ],
    "sg:phone":"+1 509 946 3988",
    "sg:postcode":"99352",
    "sg:province":"WA",
    "sg:tags":[
        "datum",
        "real estate"
    ],
    "wof:name":"Business Link",
    "wof:placetype":"venue"
},
  "geometry": {"coordinates":[-119.29724,46.272415],"type":"Point"}
}