{
  "type": "Feature",
  "properties": {
    "addr:full":"2130 NW 95th St Seattle WA 98117",
    "addr:housenumber":"2130",
    "addr:postcode":"98117",
    "addr:street":"Nw 95Th St",
    "iso:country":"US",
    "sg:address":"2130 NW 95th St",
    "sg:city":"Seattle",
    "sg:classifiers":[
        {
            "category":"Building & Trades",
            "subcategory":"Locksmith",
            "type":"Services"
        }
    ],
    "sg:phone":"+1 206 708 2379",
    "sg:postcode":"98117",
    "sg:province":"WA",
    "sg:tags":[
        "key"
    ],
    "wof:name":"Aarant Emergency Locksmith",
    "wof:placetype":"venue"
},
  "geometry": {"coordinates":[-122.38455999999999,47.698355],"type":"Point"}
}