{
  "type": "Feature",
  "properties": {
    "addr:full":"2010 15th Ave W Seattle WA 98119",
    "addr:housenumber":"2010",
    "addr:postcode":"98119",
    "addr:street":"15Th Ave W",
    "iso:country":"US",
    "sg:address":"2010 15th Ave W",
    "sg:city":"Seattle",
    "sg:classifiers":[
        {
            "category":"Government",
            "subcategory":"Post Office",
            "type":"Public Place"
        }
    ],
    "sg:postcode":"98119",
    "sg:province":"WA",
    "sg:website":"www.usps.com",
    "wof:name":"US Post Office - Interbay Annex",
    "wof:placetype":"venue"
},
  "geometry": {"coordinates":[-122.37555399999999,47.637131],"type":"Point"}
}