{
  "type": "Feature",
  "properties": {
    "addr:full":"2892 McNitt Rd Kettle Falls WA 99141",
    "addr:housenumber":"2892",
    "addr:postcode":"99141",
    "addr:street":"Mcnitt Rd",
    "iso:country":"US",
    "sg:address":"2892 McNitt Rd",
    "sg:city":"Kettle Falls",
    "sg:classifiers":[
        {
            "category":"Shopping",
            "subcategory":"Crafts & Fabrics",
            "type":"Retail Goods"
        }
    ],
    "sg:phone":"+1 509 738 6075",
    "sg:postcode":"99141",
    "sg:province":"WA",
    "sg:tags":[
        "sewing"
    ],
    "wof:name":"Girlie-Sue Collections",
    "wof:placetype":"venue"
},
  "geometry": {"coordinates":[-118.111082,48.80356],"type":"Point"}
}