{
  "type": "Feature",
  "properties": {
    "addr:full":"17347 Densmore Ave N Seattle WA 98133",
    "addr:housenumber":"17347",
    "addr:postcode":"98133",
    "addr:street":"Densmore Ave N",
    "iso:country":"US",
    "sg:address":"17347 Densmore Ave N",
    "sg:city":"Seattle",
    "sg:classifiers":[
        {
            "category":"Social Services",
            "type":"Services"
        }
    ],
    "sg:phone":"+1 206 546 9142",
    "sg:postcode":"98133",
    "sg:province":"WA",
    "wof:name":"A Little Piece of Heaven",
    "wof:placetype":"venue"
},
  "geometry": {"coordinates":[-122.338976,47.755444],"type":"Point"}
}