{
  "type": "Feature",
  "properties": {
    "addr:full":"1120 Cherry St Ste 300 Seattle WA 98104",
    "addr:housenumber":"1120",
    "addr:postcode":"98104",
    "addr:street":"Cherry St Ste 300",
    "iso:country":"US",
    "sg:address":"1120 Cherry St Ste 300",
    "sg:city":"Seattle",
    "sg:classifiers":[
        {
            "category":"Banks & Credit Unions",
            "subcategory":"Investment Brokerage",
            "type":"Services"
        }
    ],
    "sg:phone":"+1 206 215 2333",
    "sg:postcode":"98104",
    "sg:province":"WA",
    "sg:tags":[
        "sperm"
    ],
    "wof:name":"Seattle Sperm Bank",
    "wof:placetype":"venue"
},
  "geometry": {"coordinates":[-122.32296599999999,47.607279],"type":"Point"}
}