{
  "type": "Feature",
  "properties": {
    "addr:full":"351 Three Rivers Dr Kelso WA 98626",
    "addr:housenumber":"351",
    "addr:postcode":"98626",
    "addr:street":"Three Rivers Dr",
    "iso:country":"US",
    "sg:address":"351 Three Rivers Dr",
    "sg:city":"Kelso",
    "sg:classifiers":[
        {
            "category":"Shopping",
            "subcategory":"Beauty & Cosmetics",
            "type":"Retail Goods"
        },
        {
            "category":"Home & Garden",
            "subcategory":"Home Furnishings",
            "type":"Retail Goods"
        },
        {
            "category":"Personal",
            "subcategory":"Skin Care",
            "type":"Services"
        }
    ],
    "sg:phone":"+1 360 578 1708",
    "sg:postcode":"98626",
    "sg:province":"WA",
    "sg:tags":[
        "candle",
        "perfume"
    ],
    "sg:website":"http://www.bathandbodyworks.com",
    "wof:name":"Bath and Body Works",
    "wof:placetype":"venue"
},
  "geometry": {"coordinates":[-122.901535,46.140439],"type":"Point"}
}