{
  "type": "Feature",
  "properties": {
    "addr:full":"410 W 13th St Vancouver WA 98660",
    "addr:housenumber":"410",
    "addr:postcode":"98660",
    "addr:street":"W 13Th St",
    "iso:country":"US",
    "sg:address":"410 W 13th St",
    "sg:city":"Vancouver",
    "sg:classifiers":[
        {
            "category":"Social Services",
            "subcategory":"Adult Care",
            "type":"Services"
        }
    ],
    "sg:phone":"+1 360 750 4665",
    "sg:postcode":"98660",
    "sg:province":"WA",
    "sg:tags":[
        "home",
        "residential"
    ],
    "sg:website":"www.vanvistaalf.com",
    "wof:name":"Van Vista Assisted Living Comm",
    "wof:placetype":"venue"
},
  "geometry": {"coordinates":[-122.67590300000001,45.63115],"type":"Point"}
}