{
  "type": "Feature",
  "properties": {
    "addr:full":"105 S 152nd St Seattle WA 98148",
    "addr:housenumber":"105",
    "addr:postcode":"98148",
    "addr:street":"S 152Nd St",
    "iso:country":"US",
    "sg:address":"105 S 152nd St",
    "sg:city":"Seattle",
    "sg:classifiers":[
        {
            "category":"Manufacturing",
            "subcategory":"Printing",
            "type":"Manufacturing & Wholesale Goods"
        }
    ],
    "sg:phone":"+1 206 243 1170",
    "sg:postcode":"98148",
    "sg:province":"WA",
    "sg:tags":[
        "lithographic",
        "commercial"
    ],
    "wof:name":"Sudden Printing Inc",
    "wof:placetype":"venue"
},
  "geometry": {"coordinates":[-122.332367,47.46682],"type":"Point"}
}