{
  "type": "Feature",
  "properties": {
    "addr:full":"4519 1/2 University Way NE Seattle WA 98105",
    "addr:housenumber":"4519 1 / 2",
    "addr:postcode":"98105",
    "addr:street":"University Way Ne",
    "iso:country":"US",
    "sg:address":"4519 1/2 University Way NE",
    "sg:city":"Seattle",
    "sg:classifiers":[
        {
            "category":"Personal",
            "subcategory":"Massage",
            "type":"Services"
        }
    ],
    "sg:phone":"+1 206 632 5074",
    "sg:postcode":"98105",
    "sg:province":"WA",
    "wof:name":"Dennis La Master, lmp",
    "wof:placetype":"venue"
},
  "geometry": {"coordinates":[-122.313301,47.661732],"type":"Point"}
}