{
  "type": "Feature",
  "properties": {
    "iso:country":"US",
    "sg:address":"4417 S Farr Rd",
    "sg:city":"Spokane",
    "sg:classifiers":[
        {
            "category":"Retail",
            "subcategory":"Auto Repair",
            "type":"Services"
        }
    ],
    "sg:phone":"+1 509 922 3431",
    "sg:postcode":"99206",
    "sg:province":"WA",
    "sg:tags":[
        "body"
    ],
    "wof:name":"Packard Emporium",
    "wof:placetype":"venue"
},
  "geometry": {"coordinates":[-117.273371,47.613343],"type":"Point"}
}