{
  "type": "Feature",
  "properties": {
    "addr:full":"8518 S Tacoma Way Lakewood WA 98499",
    "addr:housenumber":"8518",
    "addr:postcode":"98499",
    "addr:street":"S Tacoma Way",
    "iso:country":"US",
    "sg:address":"8518 S Tacoma Way",
    "sg:city":"Lakewood",
    "sg:classifiers":[
        {
            "category":"Shopping",
            "subcategory":"Clothing, Apparel, & Fashions",
            "type":"Retail Goods"
        }
    ],
    "sg:phone":"+1 425 741 5575",
    "sg:postcode":"98499",
    "sg:province":"WA",
    "sg:tags":[
        "sewing",
        "alteration"
    ],
    "wof:name":"Seoul Alterations & Tailors",
    "wof:placetype":"venue"
},
  "geometry": {"coordinates":[-122.48400100000001,47.180099],"type":"Point"}
}