{
  "type": "Feature",
  "properties": {
    "addr:full":"2312 NE 344th Cir La Center WA 98629",
    "addr:housenumber":"2312",
    "addr:postcode":"98629",
    "addr:street":"Ne 344Th Cir",
    "iso:country":"US",
    "sg:address":"2312 NE 344th Cir",
    "sg:city":"La Center",
    "sg:classifiers":[
        {
            "category":"Professional",
            "type":"Services"
        }
    ],
    "sg:phone":"+1 360 263 6429",
    "sg:postcode":"98629",
    "sg:province":"WA",
    "wof:name":"Advanced Building Service",
    "wof:placetype":"venue"
},
  "geometry": {"coordinates":[-122.646959,45.869887],"type":"Point"}
}