{
  "type": "Feature",
  "properties": {
    "addr:full":"404 21st Ave E Seattle WA 98112",
    "addr:housenumber":"404",
    "addr:postcode":"98112",
    "addr:street":"21St Ave E",
    "iso:country":"US",
    "sg:address":"404 21st Ave E",
    "sg:city":"Seattle",
    "sg:classifiers":[
        {
            "category":"Real Estate",
            "subcategory":"Architect",
            "type":"Services"
        }
    ],
    "sg:phone":"+1 206 322 5391",
    "sg:postcode":"98112",
    "sg:province":"WA",
    "sg:tags":[
        "architectural"
    ],
    "wof:name":"Jack Baker Archtectural Design",
    "wof:placetype":"venue"
},
  "geometry": {"coordinates":[-122.304626,47.622248],"type":"Point"}
}