{
  "type": "Feature",
  "properties": {
    "addr:full":"2633 Parkmont Ln SW Olympia WA 98502",
    "addr:housenumber":"2633",
    "addr:postcode":"98502",
    "addr:street":"Parkmont Ln Sw",
    "iso:country":"US",
    "sg:address":"2633 Parkmont Ln SW",
    "sg:city":"Olympia",
    "sg:classifiers":[
        {
            "category":"Building & Trades",
            "subcategory":"Pest Control",
            "type":"Services"
        }
    ],
    "sg:phone":"+1 360 943 2270",
    "sg:postcode":"98502",
    "sg:province":"WA",
    "sg:website":"http://www.jacksonandprochnau.com",
    "wof:name":"Action Pest Control Inc",
    "wof:placetype":"venue"
},
  "geometry": {"coordinates":[-122.934883,47.035287],"type":"Point"}
}