{
  "type": "Feature",
  "properties": {
    "addr:full":"203 Mashell Ave N Eatonville WA 98328",
    "addr:housenumber":"203",
    "addr:postcode":"98328",
    "addr:street":"Mashell Ave N",
    "iso:country":"US",
    "sg:address":"203 Mashell Ave N",
    "sg:city":"Eatonville",
    "sg:classifiers":[
        {
            "category":"Autos & Motor Vehicles",
            "subcategory":"Automobile Sales",
            "type":"Retail Goods"
        }
    ],
    "sg:phone":"+1 360 832 3131",
    "sg:postcode":"98328",
    "sg:province":"WA",
    "sg:tags":[
        "car",
        "dealer"
    ],
    "wof:name":"Baydo Chevrolet",
    "wof:placetype":"venue"
},
  "geometry": {"coordinates":[-122.26665199999999,46.870369],"type":"Point"}
}