{
  "type": "Feature",
  "properties": {
    "addr:full":"21587 Oak Way Lynnwood WA 98036",
    "addr:housenumber":"21587",
    "addr:postcode":"98036",
    "addr:street":"Oak Way",
    "iso:country":"US",
    "sg:address":"21587 Oak Way",
    "sg:city":"Lynnwood",
    "sg:classifiers":[
        {
            "category":"Professional",
            "subcategory":"Art Services",
            "type":"Services"
        }
    ],
    "sg:phone":"+1 425 774 8435",
    "sg:postcode":"98036",
    "sg:province":"WA",
    "sg:tags":[
        "commercial",
        "design"
    ],
    "wof:name":"All Together Designs Inc",
    "wof:placetype":"venue"
},
  "geometry": {"coordinates":[-122.263912,47.802521],"type":"Point"}
}