{
  "type": "Feature",
  "properties": {
    "addr:full":"118 S 1st St Yakima WA 98901",
    "addr:housenumber":"118",
    "addr:postcode":"98901",
    "addr:street":"S 1St St",
    "iso:country":"US",
    "sg:address":"118 S 1st St",
    "sg:city":"Yakima",
    "sg:classifiers":[
        {
            "category":"Retail",
            "subcategory":"Repair Shop",
            "type":"Services"
        }
    ],
    "sg:phone":"+1 509 248 2723",
    "sg:postcode":"98901",
    "sg:province":"WA",
    "wof:name":"Triple A Upholstery",
    "wof:placetype":"venue"
},
  "geometry": {"coordinates":[-120.505025,46.599907],"type":"Point"}
}