{
  "type": "Feature",
  "properties": {
    "addr:full":"6320 Evergreen Way Everett WA 98203",
    "addr:housenumber":"6320",
    "addr:postcode":"98203",
    "addr:street":"Evergreen Way",
    "iso:country":"US",
    "sg:address":"6320 Evergreen Way",
    "sg:city":"Everett",
    "sg:classifiers":[
        {
            "category":"Professional",
            "subcategory":"Detective & Security Services",
            "type":"Services"
        }
    ],
    "sg:phone":"+1 425 374 3062",
    "sg:postcode":"98203",
    "sg:province":"WA",
    "sg:tags":[
        "bodyguard",
        "patrol",
        "consultant",
        "system",
        "equipment",
        "guard"
    ],
    "sg:website":"http://www.transcenddirect.com",
    "wof:name":"Transcend Consulting Firm",
    "wof:placetype":"venue"
},
  "geometry": {"coordinates":[-122.217815,47.940895],"type":"Point"}
}