{
  "type": "Feature",
  "properties": {
    "addr:full":"1105 NE 192nd Ave Vancouver WA 98684",
    "addr:housenumber":"1105",
    "addr:postcode":"98684",
    "addr:street":"Ne 192Nd Ave",
    "iso:country":"US",
    "sg:address":"1105 NE 192nd Ave",
    "sg:city":"Vancouver",
    "sg:classifiers":[
        {
            "category":"Building & Trades",
            "subcategory":"Construction",
            "type":"Services"
        }
    ],
    "sg:phone":"+1 360 256 0639",
    "sg:postcode":"98684",
    "sg:province":"WA",
    "sg:tags":[
        "contractor"
    ],
    "wof:name":"T J Roofing of Washington",
    "wof:placetype":"venue"
},
  "geometry": {"coordinates":[-122.475827,45.632182],"type":"Point"}
}