{
  "type": "Feature",
  "properties": {
    "iso:country":"US",
    "sg:address":"2029 Freeway Dr",
    "sg:city":"Mt Vernon",
    "sg:classifiers":[
        {
            "category":"Communications",
            "subcategory":"Radio Station",
            "type":"Services"
        }
    ],
    "sg:phone":"+1 360 424 7676",
    "sg:postcode":"98273",
    "sg:province":"WA",
    "sg:tags":[
        "company",
        "broadcasting"
    ],
    "sg:website":"www.kapsradio.com",
    "wof:name":"KAPS",
    "wof:placetype":"venue"
},
  "geometry": {"coordinates":[-122.343188,48.438722],"type":"Point"}
}