{
  "type": "Feature",
  "properties": {
    "addr:full":"2323 167th Ave NE Bellevue WA 98008",
    "addr:housenumber":"2323",
    "addr:postcode":"98008",
    "addr:street":"167Th Ave Ne",
    "iso:country":"US",
    "sg:address":"2323 167th Ave NE",
    "sg:city":"Bellevue",
    "sg:classifiers":[
        {
            "category":"Manufacturing",
            "subcategory":"Building Materials",
            "type":"Manufacturing & Wholesale Goods"
        }
    ],
    "sg:phone":"+1 425 672 4335",
    "sg:postcode":"98008",
    "sg:province":"WA",
    "sg:tags":[
        "mfg"
    ],
    "wof:name":"John M Havard",
    "wof:placetype":"venue"
},
  "geometry": {"coordinates":[-122.118111,47.630713],"type":"Point"}
}