{
  "type": "Feature",
  "properties": {
    "addr:full":"11 Crutcher Rd Port Townsend WA 98368",
    "addr:housenumber":"11",
    "addr:postcode":"98368",
    "addr:street":"Crutcher Rd",
    "iso:country":"US",
    "sg:address":"11 Crutcher Rd",
    "sg:city":"Port Townsend",
    "sg:classifiers":[
        {
            "category":"Manufacturing",
            "subcategory":"Metals",
            "type":"Manufacturing & Wholesale Goods"
        }
    ],
    "sg:phone":"+1 360 385 6425",
    "sg:postcode":"98368",
    "sg:province":"WA",
    "sg:tags":[
        "foundry",
        "nonferrous"
    ],
    "wof:name":"P T Foundry",
    "wof:placetype":"venue"
},
  "geometry": {"coordinates":[-122.84170899999999,48.094078],"type":"Point"}
}