{
  "type": "Feature",
  "properties": {
    "addr:full":"12620 20th Ave S Seattle WA 98168",
    "addr:housenumber":"12620",
    "addr:postcode":"98168",
    "addr:street":"20Th Ave S",
    "iso:country":"US",
    "sg:address":"12620 20th Ave S",
    "sg:city":"Seattle",
    "sg:classifiers":[
        {
            "category":"Social Services",
            "subcategory":"Child Care",
            "type":"Services"
        }
    ],
    "sg:phone":"+1 206 246 6279",
    "sg:postcode":"98168",
    "sg:province":"WA",
    "wof:name":"Debi's Daycare & Preschool",
    "wof:placetype":"venue"
},
  "geometry": {"coordinates":[-122.307368,47.489506],"type":"Point"}
}