{
  "type": "Feature",
  "properties": {
    "addr:full":"871 Wyatt Way NW Bainbridge Island WA 98110",
    "addr:housenumber":"871",
    "addr:postcode":"98110",
    "addr:street":"Wyatt Way Nw",
    "iso:country":"US",
    "sg:address":"871 Wyatt Way NW",
    "sg:city":"Bainbridge Island",
    "sg:classifiers":[
        {
            "category":"Arts & Performance",
            "subcategory":"Jazz & Blues",
            "type":"Entertainment"
        }
    ],
    "sg:phone":"+1 206 855 4108",
    "sg:postcode":"98110",
    "sg:province":"WA",
    "sg:website":"www.whozyamama.com",
    "wof:name":"Whozyamama Cajun and Zydeco Band",
    "wof:placetype":"venue"
},
  "geometry": {"coordinates":[-122.531091,47.628228],"type":"Point"}
}