{
  "type": "Feature",
  "properties": {
    "addr:full":"3808 W Court St Pasco WA 99301",
    "addr:housenumber":"3808",
    "addr:postcode":"99301",
    "addr:street":"W Court St",
    "iso:country":"US",
    "sg:address":"3808 W Court St",
    "sg:city":"Pasco",
    "sg:classifiers":[
        {
            "category":"Retail",
            "subcategory":"Auto Repair",
            "type":"Services"
        }
    ],
    "sg:phone":"+1 509 547 9098",
    "sg:postcode":"99301",
    "sg:province":"WA",
    "sg:tags":[
        "automobile",
        "lubrication"
    ],
    "wof:name":"Captain Phil's Auto Lube & Car",
    "wof:placetype":"venue"
},
  "geometry": {"coordinates":[-119.143456,46.241467],"type":"Point"}
}