{
  "type": "Feature",
  "properties": {
    "addr:full":"27019 N Sherman Rd Deer Park WA 99006",
    "addr:housenumber":"27019",
    "addr:postcode":"99006",
    "addr:street":"N Sherman Rd",
    "iso:country":"US",
    "sg:address":"27019 N Sherman Rd",
    "sg:city":"Deer Park",
    "sg:classifiers":[
        {
            "category":"Manufacturing",
            "subcategory":"Toys & Sporting Goods",
            "type":"Manufacturing & Wholesale Goods"
        }
    ],
    "sg:phone":"+1 509 276 6048",
    "sg:postcode":"99006",
    "sg:province":"WA",
    "sg:tags":[
        "mfg"
    ],
    "wof:name":"Jerrys Lures Designs Inc",
    "wof:placetype":"venue"
},
  "geometry": {"coordinates":[-117.454626,47.897067],"type":"Point"}
}