{
  "type": "Feature",
  "properties": {
    "addr:full":"7621 Rainier Ave S Seattle WA 98118",
    "addr:housenumber":"7621",
    "addr:postcode":"98118",
    "addr:street":"Rainier Ave S",
    "iso:country":"US",
    "sg:address":"7621 Rainier Ave S",
    "sg:city":"Seattle",
    "sg:classifiers":[
        {
            "category":"Structure",
            "subcategory":"Office Building",
            "type":"Public Place"
        }
    ],
    "sg:phone":"+1 206 725 5545",
    "sg:postcode":"98118",
    "sg:province":"WA",
    "sg:tags":[
        "park"
    ],
    "wof:name":"Dotcom Associates Iii",
    "wof:placetype":"venue"
},
  "geometry": {"coordinates":[-122.269981,47.534328],"type":"Point"}
}