{
  "type": "Feature",
  "properties": {
    "addr:full":"310 W Main St Harrington WA 99134",
    "addr:housenumber":"310",
    "addr:postcode":"99134",
    "addr:street":"W Main St",
    "iso:country":"US",
    "sg:address":"310 W Main St",
    "sg:city":"Harrington",
    "sg:classifiers":[
        {
            "category":"Professional",
            "subcategory":"Business Services",
            "type":"Services"
        },
        {
            "category":"Government",
            "subcategory":"Post Office",
            "type":"Public Place"
        }
    ],
    "sg:phone":"+1 509 253 4341",
    "sg:postcode":"99134",
    "sg:province":"WA",
    "sg:tags":[
        "mail",
        "shipping"
    ],
    "sg:website":"http://www.usps.gov",
    "wof:name":"USPS - United States Post Office",
    "wof:placetype":"venue"
},
  "geometry": {"coordinates":[-118.25551299999999,47.480794],"type":"Point"}
}