{
  "type": "Feature",
  "properties": {
    "addr:full":"322 Graham Rd Cusick WA 99119",
    "addr:housenumber":"322",
    "addr:postcode":"99119",
    "addr:street":"Graham Rd",
    "iso:country":"US",
    "sg:address":"322 Graham Rd",
    "sg:city":"Cusick",
    "sg:classifiers":[
        {
            "category":"Professional",
            "subcategory":"Business Services",
            "type":"Services"
        }
    ],
    "sg:phone":"+1 509 442 3126",
    "sg:postcode":"99119",
    "sg:province":"WA",
    "wof:name":"Mill Valley Homes",
    "wof:placetype":"venue"
},
  "geometry": {"coordinates":[-117.402815,48.699714],"type":"Point"}
}