{
  "type": "Feature",
  "properties": {
    "addr:full":"1735 S Pearl St Seattle WA 98108",
    "addr:housenumber":"1735",
    "addr:postcode":"98108",
    "addr:street":"S Pearl St",
    "iso:country":"US",
    "sg:address":"1735 S Pearl St",
    "sg:city":"Seattle",
    "sg:classifiers":[
        {
            "category":"Manufacturing",
            "subcategory":"Paper Products",
            "type":"Manufacturing & Wholesale Goods"
        }
    ],
    "sg:phone":"+1 206 764 9580",
    "sg:postcode":"98108",
    "sg:province":"WA",
    "sg:tags":[
        "mill",
        "pulp"
    ],
    "wof:name":"J&R Enterprises Unlimited",
    "wof:placetype":"venue"
},
  "geometry": {"coordinates":[-122.30879899999999,47.556635],"type":"Point"}
}