{
  "type": "Feature",
  "properties": {
    "iso:country":"US",
    "sg:address":"20260 N Wenas Rd",
    "sg:city":"Selah",
    "sg:classifiers":[
        {
            "category":"Freight",
            "type":"Transportation"
        }
    ],
    "sg:phone":"+1 509 698 3078",
    "sg:postcode":"98942",
    "sg:province":"WA",
    "sg:tags":[
        "operator",
        "local",
        "trucking"
    ],
    "wof:name":"Tough Truck Transportation",
    "wof:placetype":"venue"
},
  "geometry": {"coordinates":[-120.755803,46.861278],"type":"Point"}
}