{
  "type": "Feature",
  "properties": {
    "addr:full":"321 Price St Friday Harbor WA 98250",
    "addr:housenumber":"321",
    "addr:postcode":"98250",
    "addr:street":"Price St",
    "iso:country":"US",
    "sg:address":"321 Price St",
    "sg:city":"Friday Harbor",
    "sg:classifiers":[
        {
            "category":"Health Services",
            "subcategory":"Chiropractor",
            "type":"Services"
        }
    ],
    "sg:phone":"+1 360 378 3537",
    "sg:postcode":"98250",
    "sg:province":"WA",
    "wof:name":"Patricia Hansen DC",
    "wof:placetype":"venue"
},
  "geometry": {"coordinates":[-123.02439200000001,48.532821],"type":"Point"}
}