{
  "type": "Feature",
  "properties": {
    "addr:full":"11105 Homestead Rd Arlington WA 98223",
    "addr:housenumber":"11105",
    "addr:postcode":"98223",
    "addr:street":"Homestead Rd",
    "iso:country":"US",
    "sg:address":"11105 Homestead Rd",
    "sg:city":"Arlington",
    "sg:classifiers":[
        {
            "category":"Social Services",
            "subcategory":"Child Care",
            "type":"Services"
        }
    ],
    "sg:phone":"+1 360 435 8606",
    "sg:postcode":"98223",
    "sg:province":"WA",
    "sg:tags":[
        "day"
    ],
    "wof:name":"Pacific Learning Solutions",
    "wof:placetype":"venue"
},
  "geometry": {"coordinates":[-122.084174,48.196635],"type":"Point"}
}