{
  "type": "Feature",
  "properties": {
    "addr:full":"909 N Landing Way Renton WA 98057",
    "addr:housenumber":"909",
    "addr:postcode":"98057",
    "addr:street":"N Landing Way",
    "iso:country":"US",
    "sg:address":"909 N Landing Way",
    "sg:city":"Renton",
    "sg:classifiers":[
        {
            "category":"Shopping",
            "subcategory":"Department Store",
            "type":"Retail Goods"
        },
        {
            "category":"Shopping",
            "subcategory":"Clothing, Apparel, & Fashions",
            "type":"Retail Goods"
        },
        {
            "category":"Shopping",
            "subcategory":"Discount & Variety Stores",
            "type":"Retail Goods"
        }
    ],
    "sg:phone":"+1 425 687 4693",
    "sg:postcode":"98057",
    "sg:province":"WA",
    "sg:tags":[
        "clothing"
    ],
    "sg:website":"http://www.rossstores.com",
    "wof:name":"Ross Dress For Less",
    "wof:placetype":"venue"
},
  "geometry": {"coordinates":[-122.204224,47.496552],"type":"Point"}
}