{
  "type": "Feature",
  "properties": {
    "addr:full":"301 Minor Ave N Seattle WA 98109",
    "addr:housenumber":"301",
    "addr:postcode":"98109",
    "addr:street":"Minor Ave N",
    "iso:country":"US",
    "sg:address":"301 Minor Ave N",
    "sg:city":"Seattle",
    "sg:classifiers":[
        {
            "category":"Building & Trades",
            "subcategory":"Locksmith",
            "type":"Services"
        }
    ],
    "sg:phone":"+1 206 792 7739",
    "sg:postcode":"98109",
    "sg:province":"WA",
    "sg:tags":[
        "key"
    ],
    "wof:name":"Locksmith 1 0 1 Emergency",
    "wof:placetype":"venue"
},
  "geometry": {"coordinates":[-122.333203,47.620817],"type":"Point"}
}