{
  "type": "Feature",
  "properties": {
    "addr:full":"1701 SE Columbia River Dr Vancouver WA 98661",
    "addr:housenumber":"1701",
    "addr:postcode":"98661",
    "addr:street":"Se Columbia River Dr",
    "iso:country":"US",
    "sg:address":"1701 SE Columbia River Dr",
    "sg:city":"Vancouver",
    "sg:classifiers":[
        {
            "category":"Banks & Credit Unions",
            "subcategory":"Investment Brokerage",
            "type":"Services"
        }
    ],
    "sg:phone":"+1 360 696 0071",
    "sg:postcode":"98661",
    "sg:province":"WA",
    "sg:tags":[
        "security"
    ],
    "wof:name":"Dean Witter",
    "wof:placetype":"venue"
},
  "geometry": {"coordinates":[-122.654582,45.616186],"type":"Point"}
}