{
  "type": "Feature",
  "properties": {
    "addr:full":"4559 California Ave SW Seattle WA 98116",
    "addr:housenumber":"4559",
    "addr:postcode":"98116",
    "addr:street":"California Ave Sw",
    "iso:country":"US",
    "sg:address":"4559 California Ave SW",
    "sg:city":"Seattle",
    "sg:phone":"+1 206 938 3279",
    "sg:postcode":"98116",
    "sg:province":"WA",
    "sg:website":"http://www.easystreetrecords.com",
    "wof:name":"Easy Street Records & Cafe",
    "wof:placetype":"venue"
},
  "geometry": {"coordinates":[-122.386787,47.562398],"type":"Point"}
}