{
  "type": "Feature",
  "properties": {
    "addr:full":"8344 Pacific Ave SE Lacey WA 98513",
    "addr:housenumber":"8344",
    "addr:postcode":"98513",
    "addr:street":"Pacific Ave Se",
    "iso:country":"US",
    "sg:address":"8344 Pacific Ave SE",
    "sg:city":"Lacey",
    "sg:classifiers":[
        {
            "category":"Retail",
            "subcategory":"Animal Services",
            "type":"Services"
        }
    ],
    "sg:phone":"+1 360 491 9714",
    "sg:postcode":"98513",
    "sg:province":"WA",
    "sg:tags":[
        "pet",
        "grooming",
        "washing"
    ],
    "wof:name":"Happy Tails Grooming Shop",
    "wof:placetype":"venue"
},
  "geometry": {"coordinates":[-122.760722,47.038027],"type":"Point"}
}