{
  "type": "Feature",
  "properties": {
    "addr:full":"404 S 49th Ave Yakima WA 98908",
    "addr:housenumber":"404",
    "addr:postcode":"98908",
    "addr:street":"S 49Th Ave",
    "iso:country":"US",
    "sg:address":"404 S 49th Ave",
    "sg:city":"Yakima",
    "sg:classifiers":[
        {
            "category":"Professional",
            "type":"Services"
        },
        {
            "category":"Building & Trades",
            "subcategory":"Construction",
            "type":"Services"
        }
    ],
    "sg:phone":"+1 509 452 1551",
    "sg:postcode":"98908",
    "sg:province":"WA",
    "sg:tags":[
        "establishment",
        "contractor"
    ],
    "wof:name":"A J Fischer Inc",
    "wof:placetype":"venue"
},
  "geometry": {"coordinates":[-120.574455,46.593643],"type":"Point"}
}