{
  "type": "Feature",
  "properties": {
    "addr:full":"222 N 1st St Kalama WA 98625",
    "addr:housenumber":"222",
    "addr:postcode":"98625",
    "addr:street":"N 1St St",
    "iso:country":"US",
    "sg:address":"222 N 1st St",
    "sg:city":"Kalama",
    "sg:classifiers":[
        {
            "category":"Organizations",
            "subcategory":"Community Association",
            "type":"Services"
        }
    ],
    "sg:phone":"+1 360 673 2621",
    "sg:postcode":"98625",
    "sg:province":"WA",
    "sg:tags":[
        "club"
    ],
    "wof:name":"IOOF",
    "wof:placetype":"venue"
},
  "geometry": {"coordinates":[-122.845099,46.009447],"type":"Point"}
}