{
  "type": "Feature",
  "properties": {
    "addr:full":"5622 N Belt St Spokane WA 99205",
    "addr:housenumber":"5622",
    "addr:postcode":"99205",
    "addr:street":"N Belt St",
    "iso:country":"US",
    "sg:address":"5622 N Belt St",
    "sg:city":"Spokane",
    "sg:classifiers":[
        {
            "category":"Recreation",
            "type":"Entertainment"
        }
    ],
    "sg:phone":"+1 509 328 9981",
    "sg:postcode":"99205",
    "sg:province":"WA",
    "sg:tags":[
        "martial",
        "arts",
        "school"
    ],
    "wof:name":"Joan L Warme",
    "wof:placetype":"venue"
},
  "geometry": {"coordinates":[-117.443119,47.708772],"type":"Point"}
}