{
  "type": "Feature",
  "properties": {
    "addr:full":"2383 S 200th St Seatac WA 98198",
    "addr:housenumber":"2383",
    "addr:postcode":"98198",
    "addr:street":"S 200Th St",
    "iso:country":"US",
    "sg:address":"2383 S 200th St",
    "sg:city":"Seatac",
    "sg:classifiers":[
        {
            "category":"Food & Beverages",
            "subcategory":"Meat & Fish",
            "type":"Retail Goods"
        }
    ],
    "sg:phone":"+1 206 870 0233",
    "sg:postcode":"98198",
    "sg:province":"WA",
    "sg:tags":[
        "seafood-wholesale"
    ],
    "sg:website":"http://www.marinellishellfish.com",
    "wof:name":"Marinelli Shellfish",
    "wof:placetype":"venue"
},
  "geometry": {"coordinates":[-122.30111599999999,47.42271],"type":"Point"}
}