{
  "type": "Feature",
  "properties": {
    "addr:full":"1120 E Terrace St Ste 100 Seattle WA 98122",
    "addr:housenumber":"1120",
    "addr:postcode":"98122",
    "addr:street":"E Terrace St Ste 100",
    "iso:country":"US",
    "sg:address":"1120 E Terrace St Ste 100",
    "sg:city":"Seattle",
    "sg:classifiers":[
        {
            "category":"Real Estate",
            "subcategory":"Real Estate Services",
            "type":"Services"
        },
        {
            "category":"Real Estate",
            "subcategory":"Real Estate Agent",
            "type":"Services"
        }
    ],
    "sg:phone":"+1 206 325 0291",
    "sg:postcode":"98122",
    "sg:province":"WA",
    "sg:tags":[
        "buyer",
        "broker"
    ],
    "wof:name":"Western Pacific Investment Group",
    "wof:placetype":"venue"
},
  "geometry": {"coordinates":[-122.317829,47.605181],"type":"Point"}
}