{
  "type": "Feature",
  "properties": {
    "addr:full":"15833 Sunny Cove Dr SE Olalla WA 98359",
    "addr:housenumber":"15833",
    "addr:postcode":"98359",
    "addr:street":"Sunny Cove Dr Se",
    "iso:country":"US",
    "sg:address":"15833 Sunny Cove Dr SE",
    "sg:city":"Olalla",
    "sg:classifiers":[
        {
            "category":"Building & Trades",
            "subcategory":"Construction",
            "type":"Services"
        }
    ],
    "sg:phone":"+1 253 857 2433",
    "sg:postcode":"98359",
    "sg:province":"WA",
    "sg:tags":[
        "maker",
        "cabinet"
    ],
    "wof:name":"Colvos Cabinet Co",
    "wof:placetype":"venue"
},
  "geometry": {"coordinates":[-122.556769,47.40545],"type":"Point"}
}