{
  "type": "Feature",
  "properties": {
    "addr:full":"9905 NE 16th St Vancouver WA 98664",
    "addr:housenumber":"9905",
    "addr:postcode":"98664",
    "addr:street":"Ne 16Th St",
    "iso:country":"US",
    "sg:address":"9905 NE 16th St",
    "sg:city":"Vancouver",
    "sg:classifiers":[
        {
            "category":"Retail",
            "subcategory":"Repair Shop",
            "type":"Services"
        }
    ],
    "sg:phone":"+1 360 254 2884",
    "sg:postcode":"98664",
    "sg:province":"WA",
    "wof:name":"J&J Upholstry",
    "wof:placetype":"venue"
},
  "geometry": {"coordinates":[-122.571406,45.634057],"type":"Point"}
}