{
  "type": "Feature",
  "properties": {
    "addr:full":"437 Tillicum Ln Forks WA 98331",
    "addr:housenumber":"437",
    "addr:postcode":"98331",
    "addr:street":"Tillicum Ln",
    "iso:country":"US",
    "sg:address":"437 Tillicum Ln",
    "sg:city":"Forks",
    "sg:classifiers":[
        {
            "category":"Building & Trades",
            "subcategory":"Landscaping Services",
            "type":"Services"
        },
        {
            "category":"Government",
            "subcategory":"Office",
            "type":"Public Place"
        }
    ],
    "sg:phone":"+1 360 374 6522",
    "sg:postcode":"98331",
    "sg:province":"WA",
    "sg:tags":[
        "forester"
    ],
    "sg:website":"http://www.lbl.org",
    "wof:name":"Soleduck Ranger District",
    "wof:placetype":"venue"
},
  "geometry": {"coordinates":[-124.38534,47.954517],"type":"Point"}
}