{
  "type": "Feature",
  "properties": {
    "addr:full":"3017 21st Ave S Seattle WA 98144",
    "addr:housenumber":"3017",
    "addr:postcode":"98144",
    "addr:street":"21St Ave S",
    "iso:country":"US",
    "sg:address":"3017 21st Ave S",
    "sg:city":"Seattle",
    "sg:classifiers":[
        {
            "category":"Personal",
            "type":"Services"
        },
        {
            "category":"Professional",
            "subcategory":"Art Services",
            "type":"Services"
        }
    ],
    "sg:phone":"+1 206 965 0786",
    "sg:postcode":"98144",
    "sg:province":"WA",
    "sg:tags":[
        "photography",
        "videography",
        "wedding"
    ],
    "wof:name":"Matthew Mar Photography",
    "wof:placetype":"venue"
},
  "geometry": {"coordinates":[-122.30538,47.576619],"type":"Point"}
}