{
  "type": "Feature",
  "properties": {
    "addr:full":"7909 Delridge Way SW Seattle WA 98106",
    "addr:housenumber":"7909",
    "addr:postcode":"98106",
    "addr:street":"Delridge Way Sw",
    "iso:country":"US",
    "sg:address":"7909 Delridge Way SW",
    "sg:city":"Seattle",
    "sg:classifiers":[
        {
            "category":"Building & Trades",
            "subcategory":"Locksmith",
            "type":"Services"
        }
    ],
    "sg:phone":"+1 206 237 0243",
    "sg:postcode":"98106",
    "sg:province":"WA",
    "sg:tags":[
        "key"
    ],
    "wof:name":"Wa Emergency Locksmith",
    "wof:placetype":"venue"
},
  "geometry": {"coordinates":[-122.360608,47.530911],"type":"Point"}
}