{
  "type": "Feature",
  "properties": {
    "addr:full":"3611 N Union Ave Tacoma WA 98407",
    "addr:housenumber":"3611",
    "addr:postcode":"98407",
    "addr:street":"N Union Ave",
    "iso:country":"US",
    "sg:address":"3611 N Union Ave",
    "sg:city":"Tacoma",
    "sg:classifiers":[
        {
            "category":"Professional",
            "subcategory":"Computer Services",
            "type":"Services"
        }
    ],
    "sg:phone":"+1 253 759 9787",
    "sg:postcode":"98407",
    "sg:province":"WA",
    "sg:tags":[
        "consultant"
    ],
    "wof:name":"Morgan Griffin Inc",
    "wof:placetype":"venue"
},
  "geometry": {"coordinates":[-122.484768,47.283589],"type":"Point"}
}