{
  "type": "Feature",
  "properties": {
    "addr:full":"1415 S Wenatchee Ave Wenatchee WA 98801",
    "addr:housenumber":"1415",
    "addr:postcode":"98801",
    "addr:street":"S Wenatchee Ave",
    "iso:country":"US",
    "sg:address":"1415 S Wenatchee Ave",
    "sg:city":"Wenatchee",
    "sg:classifiers":[
        {
            "category":"Personal",
            "subcategory":"Beauty Salon",
            "type":"Services"
        }
    ],
    "sg:phone":"+1 509 662 6263",
    "sg:postcode":"98801",
    "sg:province":"WA",
    "sg:tags":[
        "shop"
    ],
    "wof:name":"Main Addition",
    "wof:placetype":"venue"
},
  "geometry": {"coordinates":[-120.299567,47.404263],"type":"Point"}
}