{
  "type": "Feature",
  "properties": {
    "addr:full":"21850 88th Pl S Kent WA 98031",
    "addr:housenumber":"21850",
    "addr:postcode":"98031",
    "addr:street":"88Th Pl S",
    "iso:country":"US",
    "sg:address":"21850 88th Pl S",
    "sg:city":"Kent",
    "sg:classifiers":[
        {
            "category":"Retail",
            "subcategory":"Repair Shop",
            "type":"Services"
        }
    ],
    "sg:phone":"+1 253 670 1763",
    "sg:postcode":"98031",
    "sg:province":"WA",
    "wof:name":"Jims Clipper & Small Engine R",
    "wof:placetype":"venue"
},
  "geometry": {"coordinates":[-122.222427,47.405523],"type":"Point"}
}