{
  "type": "Feature",
  "properties": {
    "addr:full":"1407 Krause Pl Mt Vernon WA 98274",
    "addr:housenumber":"1407",
    "addr:postcode":"98274",
    "addr:street":"Krause Pl",
    "iso:country":"US",
    "sg:address":"1407 Krause Pl",
    "sg:city":"Mt Vernon",
    "sg:classifiers":[
        {
            "category":"Social Services",
            "subcategory":"Child Care",
            "type":"Services"
        }
    ],
    "sg:phone":"+1 360 424 9309",
    "sg:postcode":"98274",
    "sg:province":"WA",
    "wof:name":"Little Mountain Daycare Home",
    "wof:placetype":"venue"
},
  "geometry": {"coordinates":[-122.30562500000001,48.412536],"type":"Point"}
}