{
  "type": "Feature",
  "properties": {
    "iso:country":"US",
    "sg:address":"2611 N Woodruff Rd",
    "sg:city":"Spokane",
    "sg:classifiers":[
        {
            "category":"Wholesale",
            "subcategory":"Drugs",
            "type":"Manufacturing & Wholesale Goods"
        }
    ],
    "sg:phone":"+1 509 922 3400",
    "sg:postcode":"99206",
    "sg:province":"WA",
    "wof:name":"McKesson Corporation",
    "wof:placetype":"venue"
},
  "geometry": {"coordinates":[-117.272087,47.681328],"type":"Point"}
}