{
  "type": "Feature",
  "properties": {
    "addr:full":"7683 SE 27th St Mercer Island WA 98040",
    "addr:housenumber":"7683",
    "addr:postcode":"98040",
    "addr:street":"Se 27Th St",
    "iso:country":"US",
    "sg:address":"7683 SE 27th St",
    "sg:city":"Mercer Island",
    "sg:classifiers":[
        {
            "category":"Health Services",
            "subcategory":"Health Practitioner",
            "type":"Services"
        }
    ],
    "sg:phone":"+1 206 232 9138",
    "sg:postcode":"98040",
    "sg:province":"WA",
    "sg:tags":[
        "nutritionist"
    ],
    "wof:name":"Kleiner Susan M PHD Rd",
    "wof:placetype":"venue"
},
  "geometry": {"coordinates":[-122.235001,47.5868],"type":"Point"}
}