{
  "type": "Feature",
  "properties": {
    "addr:full":"8419 Chambers Creek Rd W Tacoma WA 98467",
    "addr:housenumber":"8419",
    "addr:postcode":"98467",
    "addr:street":"Chambers Creek Rd W",
    "iso:country":"US",
    "sg:address":"8419 Chambers Creek Rd W",
    "sg:city":"Tacoma",
    "sg:classifiers":[
        {
            "category":"Building & Trades",
            "subcategory":"Construction",
            "type":"Services"
        }
    ],
    "sg:phone":"+1 253 565 0704",
    "sg:postcode":"98467",
    "sg:province":"WA",
    "sg:tags":[
        "resurfacing",
        "floor",
        "laying",
        "refinishing",
        "contractor"
    ],
    "wof:name":"Anderson's Hardwood Floors",
    "wof:placetype":"venue"
},
  "geometry": {"coordinates":[-122.549522,47.199055],"type":"Point"}
}