{
  "type": "Feature",
  "properties": {
    "addr:full":"6821 W Willamette Ave Kennewick WA 99336",
    "addr:housenumber":"6821",
    "addr:postcode":"99336",
    "addr:street":"W Willamette Ave",
    "iso:country":"US",
    "sg:address":"6821 W Willamette Ave",
    "sg:city":"Kennewick",
    "sg:phone":"+1 509 736 3646",
    "sg:postcode":"99336",
    "sg:province":"WA",
    "sg:tags":[
        "leather"
    ],
    "wof:name":"Jess Morgan",
    "wof:placetype":"venue"
},
  "geometry": {"coordinates":[-119.218126,46.22855],"type":"Point"}
}