{
  "type": "Feature",
  "properties": {
    "addr:full":"14730 NE 8th St Ste 105 Bellevue WA 98007",
    "addr:housenumber":"14730",
    "addr:postcode":"98007",
    "addr:street":"Ne 8Th St Ste 105",
    "iso:country":"US",
    "sg:address":"14730 NE 8th St Ste 105",
    "sg:city":"Bellevue",
    "sg:classifiers":[
        {
            "category":"Health Services",
            "subcategory":"Dentist",
            "type":"Services"
        }
    ],
    "sg:phone":"+1 425 649 0800",
    "sg:postcode":"98007",
    "sg:province":"WA",
    "sg:website":"www.pineviewdentistry.com",
    "wof:name":"Pineview Aesthetic and Family Dentistry",
    "wof:placetype":"venue"
},
  "geometry": {"coordinates":[-122.144109,47.617069],"type":"Point"}
}