{
  "type": "Feature",
  "properties": {
    "addr:full":"9338 Sportsman Club Rd NE Bainbridge Island WA 98110",
    "addr:housenumber":"9338",
    "addr:postcode":"98110",
    "addr:street":"Sportsman Club Rd Ne",
    "iso:country":"US",
    "sg:address":"9338 Sportsman Club Rd NE",
    "sg:city":"Bainbridge Island",
    "sg:classifiers":[
        {
            "category":"Arena",
            "subcategory":"Sports Club",
            "type":"Entertainment"
        }
    ],
    "sg:phone":"+1 206 842 8511",
    "sg:postcode":"98110",
    "sg:province":"WA",
    "sg:tags":[
        "martial art"
    ],
    "wof:name":"Island Aikido Art Center",
    "wof:placetype":"venue"
},
  "geometry": {"coordinates":[-122.52628,47.647433],"type":"Point"}
}