{
  "type": "Feature",
  "properties": {
    "addr:full":"8822 E Upriver Dr Spokane WA 99212",
    "addr:housenumber":"8822",
    "addr:postcode":"99212",
    "addr:street":"E Upriver Dr",
    "iso:country":"US",
    "sg:address":"8822 E Upriver Dr",
    "sg:city":"Spokane",
    "sg:classifiers":[
        {
            "category":"Place Of Worship",
            "subcategory":"Church",
            "type":"Public Place"
        },
        {
            "category":"Place Of Worship",
            "type":"Public Place"
        }
    ],
    "sg:phone":"+1 509 926 5858",
    "sg:postcode":"99212",
    "sg:province":"WA",
    "sg:tags":[
        "nazarene",
        "churches-church",
        "churches-nazarene"
    ],
    "wof:name":"Pasadena Park Church Of The Nazarene",
    "wof:placetype":"venue"
},
  "geometry": {"coordinates":[-117.286271,47.697038],"type":"Point"}
}