{
  "type": "Feature",
  "properties": {
    "addr:full":"12004 E 12th Ave Spokane WA 99206",
    "addr:housenumber":"12004",
    "addr:postcode":"99206",
    "addr:street":"E 12Th Ave",
    "iso:country":"US",
    "sg:address":"12004 E 12th Ave",
    "sg:city":"Spokane",
    "sg:classifiers":[
        {
            "category":"Wholesale",
            "subcategory":"Scrap",
            "type":"Manufacturing & Wholesale Goods"
        }
    ],
    "sg:phone":"+1 509 928 4600",
    "sg:postcode":"99206",
    "sg:province":"WA",
    "sg:tags":[
        "material"
    ],
    "wof:name":"Scrap For You",
    "wof:placetype":"venue"
},
  "geometry": {"coordinates":[-117.245868,47.646044],"type":"Point"}
}