{
  "type": "Feature",
  "properties": {
    "addr:full":"14500 141st Ave SE Snohomish WA 98290",
    "addr:housenumber":"14500",
    "addr:postcode":"98290",
    "addr:street":"141St Ave Se",
    "iso:country":"US",
    "sg:address":"14500 141st Ave SE",
    "sg:city":"Snohomish",
    "sg:classifiers":[
        {
            "category":"Wholesale",
            "subcategory":"Seafood",
            "type":"Manufacturing & Wholesale Goods"
        }
    ],
    "sg:phone":"+1 360 863 8003",
    "sg:postcode":"98290",
    "sg:province":"WA",
    "sg:tags":[
        "frozen",
        "canned",
        "fish"
    ],
    "wof:name":"Seatech Corporation",
    "wof:placetype":"venue"
},
  "geometry": {"coordinates":[-122.04353999999999,47.864326],"type":"Point"}
}