{
  "type": "Feature",
  "properties": {
    "addr:full":"507 131st St E Tacoma WA 98445",
    "addr:housenumber":"507",
    "addr:postcode":"98445",
    "addr:street":"131St St",
    "iso:country":"US",
    "sg:address":"507 131st St E",
    "sg:city":"Tacoma",
    "sg:classifiers":[
        {
            "category":"Real Estate",
            "subcategory":"Developer",
            "type":"Services"
        }
    ],
    "sg:phone":"+1 253 531 4455",
    "sg:postcode":"98445",
    "sg:province":"WA",
    "sg:tags":[
        "mobile",
        "home"
    ],
    "wof:name":"Parkland Mobile Village",
    "wof:placetype":"venue"
},
  "geometry": {"coordinates":[-122.42523,47.13836],"type":"Point"}
}