{
  "type": "Feature",
  "properties": {
    "addr:full":"1460 NW 73rd St Seattle WA 98117",
    "addr:housenumber":"1460",
    "addr:postcode":"98117",
    "addr:street":"Nw 73Rd St",
    "iso:country":"US",
    "sg:address":"1460 NW 73rd St",
    "sg:city":"Seattle",
    "sg:classifiers":[
        {
            "category":"Social Services",
            "type":"Services"
        }
    ],
    "sg:phone":"+1 206 789 1355",
    "sg:postcode":"98117",
    "sg:province":"WA",
    "wof:name":"Resurrection Life Ministries",
    "wof:placetype":"venue"
},
  "geometry": {"coordinates":[-122.375366,47.681498],"type":"Point"}
}