{
  "type": "Feature",
  "properties": {
    "addr:full":"44 Dwinell Rd Montesano WA 98563",
    "addr:housenumber":"44",
    "addr:postcode":"98563",
    "addr:street":"Dwinell Rd",
    "iso:country":"US",
    "sg:address":"44 Dwinell Rd",
    "sg:city":"Montesano",
    "sg:classifiers":[
        {
            "category":"Farming",
            "subcategory":"Farm",
            "type":"Manufacturing & Wholesale Goods"
        }
    ],
    "sg:phone":"+1 360 249 5602",
    "sg:postcode":"98563",
    "sg:province":"WA",
    "sg:tags":[
        "crop",
        "general"
    ],
    "wof:name":"Elmer Worman",
    "wof:placetype":"venue"
},
  "geometry": {"coordinates":[-123.49074400000001,46.995441],"type":"Point"}
}