{
  "type": "Feature",
  "properties": {
    "addr:full":"7 N 59th Ave Yakima WA 98908",
    "addr:housenumber":"7",
    "addr:postcode":"98908",
    "addr:street":"N 59Th Ave",
    "iso:country":"US",
    "sg:address":"7 N 59th Ave",
    "sg:city":"Yakima",
    "sg:classifiers":[
        {
            "category":"Personal",
            "type":"Services"
        }
    ],
    "sg:phone":"+1 509 949 6672",
    "sg:postcode":"98908",
    "sg:province":"WA",
    "wof:name":"Beautiful Beginnings",
    "wof:placetype":"venue"
},
  "geometry": {"coordinates":[-120.58709899999999,46.598112],"type":"Point"}
}