{
  "type": "Feature",
  "properties": {
    "addr:full":"17526 119th Pl NE Arlington WA 98223",
    "addr:housenumber":"17526",
    "addr:postcode":"98223",
    "addr:street":"119Th Pl Ne",
    "iso:country":"US",
    "sg:address":"17526 119th Pl NE",
    "sg:city":"Arlington",
    "sg:classifiers":[
        {
            "category":"Retail",
            "subcategory":"Portrait Studio",
            "type":"Services"
        }
    ],
    "sg:phone":"+1 425 501 5697",
    "sg:postcode":"98223",
    "sg:province":"WA",
    "sg:tags":[
        "photo"
    ],
    "wof:name":"Starry Night Photography",
    "wof:placetype":"venue"
},
  "geometry": {"coordinates":[-121.99474600000001,48.104478],"type":"Point"}
}