{
  "type": "Feature",
  "properties": {
    "addr:full":"3319 Lorne St SE Olympia WA 98501",
    "addr:housenumber":"3319",
    "addr:postcode":"98501",
    "addr:street":"Lorne St Se",
    "iso:country":"US",
    "sg:address":"3319 Lorne St SE",
    "sg:city":"Olympia",
    "sg:classifiers":[
        {
            "category":"Building & Trades",
            "subcategory":"Construction",
            "type":"Services"
        }
    ],
    "sg:phone":"+1 360 943 8422",
    "sg:postcode":"98501",
    "sg:province":"WA",
    "wof:name":"Rod Payne & Assoc",
    "wof:placetype":"venue"
},
  "geometry": {"coordinates":[-122.89272,47.017633],"type":"Point"}
}