{
  "type": "Feature",
  "properties": {
    "addr:full":"1400 Martin Luther King Jr Way S Seattle Seattle WA 98144",
    "addr:housenumber":"1400",
    "addr:postcode":"98144",
    "addr:street":"Martin Luther King Jr Way S",
    "iso:country":"US",
    "sg:address":"1400 Martin Luther King Jr Way S Seattle",
    "sg:city":"Seattle",
    "sg:classifiers":[
        {
            "category":"Shopping",
            "subcategory":"Pets & Pet Supplies",
            "type":"Retail Goods"
        }
    ],
    "sg:postcode":"98144",
    "sg:province":"WA",
    "sg:website":"www.seattle.gov/PARKS/offleash_d...",
    "wof:name":"Sam Smith Offleash Dog Park",
    "wof:placetype":"venue"
},
  "geometry": {"coordinates":[-122.297372,47.590643],"type":"Point"}
}