{
  "type": "Feature",
  "properties": {
    "addr:full":"4511 S Kenyon St Seattle WA 98118",
    "addr:housenumber":"4511",
    "addr:postcode":"98118",
    "addr:street":"S Kenyon St",
    "iso:country":"US",
    "sg:address":"4511 S Kenyon St",
    "sg:city":"Seattle",
    "sg:classifiers":[
        {
            "category":"Building & Trades",
            "subcategory":"Cleaning & Sanitation",
            "type":"Services"
        }
    ],
    "sg:phone":"+1 206 725 1197",
    "sg:postcode":"98118",
    "sg:province":"WA",
    "sg:tags":[
        "maintenance"
    ],
    "wof:name":"Celso Janitorial Service",
    "wof:placetype":"venue"
},
  "geometry": {"coordinates":[-122.27558399999999,47.531478],"type":"Point"}
}