{
  "type": "Feature",
  "properties": {
    "addr:full":"21818 4th Ave S Normandy Park WA 98198",
    "addr:housenumber":"21818",
    "addr:postcode":"98198",
    "addr:street":"4Th Ave S Normandy Park",
    "iso:country":"US",
    "sg:address":"21818 4th Ave S",
    "sg:city":"Normandy Park",
    "sg:classifiers":[
        {
            "category":"Professional",
            "type":"Services"
        },
        {
            "category":"Professional",
            "subcategory":"Business Services",
            "type":"Services"
        }
    ],
    "sg:phone":"+1 206 870 3274",
    "sg:postcode":"98198",
    "sg:province":"WA",
    "sg:tags":[
        "establishment"
    ],
    "wof:name":"Facility Group",
    "wof:placetype":"venue"
},
  "geometry": {"coordinates":[-122.330169,47.405947],"type":"Point"}
}