{
  "type": "Feature",
  "properties": {
    "addr:full":"427 E 20th Ave Spokane WA 99203",
    "addr:housenumber":"427",
    "addr:postcode":"99203",
    "addr:street":"E 20Th Ave",
    "iso:country":"US",
    "sg:address":"427 E 20th Ave",
    "sg:city":"Spokane",
    "sg:classifiers":[
        {
            "category":"Shopping",
            "subcategory":"Computers & Home Electronics",
            "type":"Retail Goods"
        }
    ],
    "sg:phone":"+1 509 951 7757",
    "sg:postcode":"99203",
    "sg:province":"WA",
    "wof:name":"Kowtko Cmpt Networking & SEC",
    "wof:placetype":"venue"
},
  "geometry": {"coordinates":[-117.40275099999999,47.636928],"type":"Point"}
}