{
  "type": "Feature",
  "properties": {
    "addr:full":"307 130th Ave SE Bellevue WA 98005",
    "addr:housenumber":"307",
    "addr:postcode":"98005",
    "addr:street":"130Th Ave Se",
    "iso:country":"US",
    "sg:address":"307 130th Ave SE",
    "sg:city":"Bellevue",
    "sg:classifiers":[
        {
            "category":"Shopping",
            "subcategory":"Books",
            "type":"Retail Goods"
        }
    ],
    "sg:phone":"+1 425 454 1663",
    "sg:postcode":"98005",
    "sg:province":"WA",
    "wof:name":"P T Mallahan Bookseller",
    "wof:placetype":"venue"
},
  "geometry": {"coordinates":[-122.167435,47.606779],"type":"Point"}
}