{
  "type": "Feature",
  "properties": {
    "addr:full":"3011 Webster Point Rd NE Seattle WA 98105",
    "addr:housenumber":"3011",
    "addr:postcode":"98105",
    "addr:street":"Webster Point Rd Ne",
    "iso:country":"US",
    "sg:address":"3011 Webster Point Rd NE",
    "sg:city":"Seattle",
    "sg:classifiers":[
        {
            "category":"Professional",
            "subcategory":"Management & Consulting",
            "type":"Services"
        }
    ],
    "sg:phone":"+1 206 524 9754",
    "sg:postcode":"98105",
    "sg:province":"WA",
    "wof:name":"Biotech Medical Regulation",
    "wof:placetype":"venue"
},
  "geometry": {"coordinates":[-122.27762199999999,47.649085],"type":"Point"}
}