{
  "type": "Feature",
  "properties": {
    "addr:full":"16325 NE 74th St Redmond WA 98052",
    "addr:housenumber":"16325",
    "addr:postcode":"98052",
    "addr:street":"Ne 74Th St",
    "iso:country":"US",
    "sg:address":"16325 NE 74th St",
    "sg:city":"Redmond",
    "sg:classifiers":[
        {
            "category":"Shopping",
            "subcategory":"Computers & Home Electronics",
            "type":"Retail Goods"
        }
    ],
    "sg:phone":"+1 425 881 7113",
    "sg:postcode":"98052",
    "sg:province":"WA",
    "sg:tags":[
        "television",
        "satellite",
        "system"
    ],
    "wof:name":"Premier Stllite Instlltion LLC",
    "wof:placetype":"venue"
},
  "geometry": {"coordinates":[-122.121696,47.670655],"type":"Point"}
}