{
  "type": "Feature",
  "properties": {
    "addr:full":"5039 S Washington St Tacoma WA 98409",
    "addr:housenumber":"5039",
    "addr:postcode":"98409",
    "addr:street":"S Washington St",
    "iso:country":"US",
    "sg:address":"5039 S Washington St",
    "sg:city":"Tacoma",
    "sg:classifiers":[
        {
            "category":"Home & Garden",
            "subcategory":"Garden Supply",
            "type":"Retail Goods"
        }
    ],
    "sg:phone":"+1 253 301 4343",
    "sg:postcode":"98409",
    "sg:province":"WA",
    "sg:tags":[
        "equipment",
        "hydroponics"
    ],
    "sg:website":"http://waterworkshydroponics.com",
    "wof:name":"Waterworks Hydroponics",
    "wof:placetype":"venue"
},
  "geometry": {"coordinates":[-122.485029,47.211233],"type":"Point"}
}