{
  "type": "Feature",
  "properties": {
    "addr:full":"27002 140th Ave SE Kent WA 98042",
    "addr:housenumber":"27002",
    "addr:postcode":"98042",
    "addr:street":"140Th Ave Se",
    "iso:country":"US",
    "sg:address":"27002 140th Ave SE",
    "sg:city":"Kent",
    "sg:classifiers":[
        {
            "category":"Manufacturing",
            "subcategory":"Retail Goods",
            "type":"Manufacturing & Wholesale Goods"
        }
    ],
    "sg:phone":"+1 253 334 7155",
    "sg:postcode":"98042",
    "sg:province":"WA",
    "sg:tags":[
        "product",
        "mfg"
    ],
    "wof:name":"Translucent Insomnia",
    "wof:placetype":"venue"
},
  "geometry": {"coordinates":[-122.156205,47.36085],"type":"Point"}
}