{
  "type": "Feature",
  "properties": {
    "addr:full":"1617 Interlaken Dr E Seattle WA 98112",
    "addr:postcode":"1617;98112",
    "addr:street":"Interlaken Dr E",
    "iso:country":"US",
    "sg:address":"1617 Interlaken Dr E",
    "sg:city":"Seattle",
    "sg:classifiers":[
        {
            "category":"Education",
            "subcategory":"Special Training",
            "type":"Public Place"
        },
        {
            "category":"Social Services",
            "subcategory":"Child Care",
            "type":"Services"
        },
        {
            "category":"Education",
            "subcategory":"Preschool",
            "type":"Public Place"
        },
        {
            "category":"Education",
            "subcategory":"School",
            "type":"Public Place"
        }
    ],
    "sg:phone":"+1 206 860 7519",
    "sg:postcode":"98112",
    "sg:province":"WA",
    "sg:tags":[
        "educational",
        "private",
        "high",
        "middle",
        "nursery",
        "k-",
        "elementary",
        "day"
    ],
    "sg:website":"http://www.seattlehebrewacademy.org",
    "wof:name":"Seattle Hebrew Academy Elementary",
    "wof:placetype":"venue"
},
  "geometry": {"coordinates":[-122.306999,47.632401],"type":"Point"}
}