{
  "type": "Feature",
  "properties": {
    "addr:full":"10610 NE 46th St Kirkland WA 98033",
    "addr:housenumber":"10610",
    "addr:postcode":"98033",
    "addr:street":"Ne 46Th St",
    "iso:country":"US",
    "sg:address":"10610 NE 46th St",
    "sg:city":"Kirkland",
    "sg:classifiers":[
        {
            "category":"Building & Trades",
            "subcategory":"Construction",
            "type":"Services"
        }
    ],
    "sg:phone":"+1 425 822 1002",
    "sg:postcode":"98033",
    "sg:province":"WA",
    "sg:tags":[
        "house"
    ],
    "wof:name":"Mid Pac Construction Inc",
    "wof:placetype":"venue"
},
  "geometry": {"coordinates":[-122.197451,47.651443],"type":"Point"}
}