{
  "type": "Feature",
  "properties": {
    "addr:full":"3502 E Mc Kinley Ave Tacoma WA 98404",
    "addr:housenumber":"3502",
    "addr:postcode":"98404",
    "addr:street":"E Mc Kinley Ave",
    "iso:country":"US",
    "sg:address":"3502 E Mc Kinley Ave",
    "sg:city":"Tacoma",
    "sg:classifiers":[
        {
            "category":"Real Estate",
            "subcategory":"Real Estate Operator",
            "type":"Services"
        }
    ],
    "sg:phone":"+1 253 627 6370",
    "sg:postcode":"98404",
    "sg:province":"WA",
    "sg:tags":[
        "building",
        "apartment"
    ],
    "wof:name":"Porter Apartments",
    "wof:placetype":"venue"
},
  "geometry": {"coordinates":[-122.420896,47.229747],"type":"Point"}
}