{
  "type": "Feature",
  "properties": {
    "addr:full":"3867 Pinecone Ct NE Bremerton WA 98310",
    "addr:housenumber":"3867",
    "addr:postcode":"98310",
    "addr:street":"Pinecone Ct Ne",
    "iso:country":"US",
    "sg:address":"3867 Pinecone Ct NE",
    "sg:city":"Bremerton",
    "sg:classifiers":[
        {
            "category":"Organizations",
            "subcategory":"Community Association",
            "type":"Services"
        }
    ],
    "sg:phone":"+1 360 373 9907",
    "sg:postcode":"98310",
    "sg:province":"WA",
    "wof:name":"Loyal D Campbell",
    "wof:placetype":"venue"
},
  "geometry": {"coordinates":[-122.644519,47.600221],"type":"Point"}
}