{
  "type": "Feature",
  "properties": {
    "addr:full":"7505 128th St NE Arlington WA 98223",
    "addr:housenumber":"7505",
    "addr:postcode":"98223",
    "addr:street":"128Th St Ne",
    "iso:country":"US",
    "sg:address":"7505 128th St NE",
    "sg:city":"Arlington",
    "sg:classifiers":[
        {
            "category":"Professional",
            "subcategory":"Business Services",
            "type":"Services"
        }
    ],
    "sg:phone":"+1 360 658 9781",
    "sg:postcode":"98223",
    "sg:province":"WA",
    "wof:name":"Michelle MB Clark Designs",
    "wof:placetype":"venue"
},
  "geometry": {"coordinates":[-122.133228,48.110345],"type":"Point"}
}