{
  "type": "Feature",
  "properties": {
    "addr:full":"318 Blanchard St Seattle WA 98121",
    "addr:housenumber":"318",
    "addr:postcode":"98121",
    "addr:street":"Blanchard St",
    "iso:country":"US",
    "sg:address":"318 Blanchard St",
    "sg:city":"Seattle",
    "sg:classifiers":[
        {
            "category":"Coffee & Tea",
            "type":"Food & Drink"
        },
        {
            "category":"Restaurant",
            "type":"Food & Drink"
        }
    ],
    "sg:phone":"+1 206 443 7666",
    "sg:postcode":"98121",
    "sg:province":"WA",
    "sg:tags":[
        "mediterranean"
    ],
    "sg:website":"www.delishez.com",
    "wof:name":"Deli Shez Caf?",
    "wof:placetype":"venue"
},
  "geometry": {"coordinates":[-122.34317,47.614207],"type":"Point"}
}