{
  "type": "Feature",
  "properties": {
    "addr:full":"15611 Manion Way NE Duvall WA 98019",
    "addr:housenumber":"15611",
    "addr:postcode":"98019",
    "addr:street":"Manion Way Ne",
    "iso:country":"US",
    "sg:address":"15611 Manion Way NE",
    "sg:city":"Duvall",
    "sg:classifiers":[
        {
            "category":"Retail",
            "subcategory":"Laundry & Dry Cleaning",
            "type":"Services"
        }
    ],
    "sg:phone":"+1 425 788 1348",
    "sg:postcode":"98019",
    "sg:province":"WA",
    "sg:tags":[
        "drycleaning",
        "plant"
    ],
    "wof:name":"Simon & Son",
    "wof:placetype":"venue"
},
  "geometry": {"coordinates":[-121.96572,47.741343],"type":"Point"}
}