{
  "type": "Feature",
  "properties": {
    "addr:full":"5413 NE 78th St Vancouver WA 98665",
    "addr:housenumber":"5413",
    "addr:postcode":"98665",
    "addr:street":"Ne 78Th St",
    "iso:country":"US",
    "sg:address":"5413 NE 78th St",
    "sg:city":"Vancouver",
    "sg:classifiers":[
        {
            "category":"Retail",
            "subcategory":"Repair Shop",
            "type":"Services"
        }
    ],
    "sg:phone":"+1 360 694 6052",
    "sg:postcode":"98665",
    "sg:province":"WA",
    "sg:tags":[
        "household",
        "electrical"
    ],
    "wof:name":"Norms Vacuum & Sew Mch Repr",
    "wof:placetype":"venue"
},
  "geometry": {"coordinates":[-122.61671699999999,45.678671],"type":"Point"}
}