{
  "type": "Feature",
  "properties": {
    "addr:full":"2210 Ilwaco Ave NE Renton WA 98059",
    "addr:housenumber":"2210",
    "addr:postcode":"98059",
    "addr:street":"Ilwaco Ave Ne",
    "iso:country":"US",
    "sg:address":"2210 Ilwaco Ave NE",
    "sg:city":"Renton",
    "sg:classifiers":[
        {
            "category":"Professional",
            "subcategory":"Management & Consulting",
            "type":"Services"
        }
    ],
    "sg:phone":"+1 425 235 1936",
    "sg:postcode":"98059",
    "sg:province":"WA",
    "wof:name":"Holder Consulting Group",
    "wof:placetype":"venue"
},
  "geometry": {"coordinates":[-122.14916700000001,47.511452],"type":"Point"}
}