{
  "type": "Feature",
  "properties": {
    "addr:full":"121 N 85th St Seattle WA 98103",
    "addr:housenumber":"121",
    "addr:postcode":"98103",
    "addr:street":"N 85Th St",
    "iso:country":"US",
    "sg:address":"121 N 85th St",
    "sg:city":"Seattle",
    "sg:classifiers":[
        {
            "category":"Personal",
            "subcategory":"Massage",
            "type":"Services"
        },
        {
            "category":"Health Services",
            "subcategory":"Health Practitioner",
            "type":"Services"
        }
    ],
    "sg:phone":"+1 206 805 0226",
    "sg:postcode":"98103",
    "sg:province":"WA",
    "sg:tags":[
        "acupuncture"
    ],
    "sg:website":"www.rheahealing.com",
    "wof:name":"Rhea Healing Essentials",
    "wof:placetype":"venue"
},
  "geometry": {"coordinates":[-122.35685599999999,47.690376],"type":"Point"}
}