{
  "type": "Feature",
  "properties": {
    "addr:full":"159 Western Ave W Ste 483 Seattle WA 98119",
    "addr:housenumber":"159",
    "addr:postcode":"98119",
    "addr:street":"Western Ave W Ste 483",
    "iso:country":"US",
    "sg:address":"159 Western Ave W Ste 483",
    "sg:city":"Seattle",
    "sg:classifiers":[
        {
            "category":"Professional",
            "subcategory":"Management & Consulting",
            "type":"Services"
        }
    ],
    "sg:phone":"+1 206 284 4200",
    "sg:postcode":"98119",
    "sg:province":"WA",
    "sg:tags":[
        "counselor",
        "relation",
        "public"
    ],
    "wof:name":"The Elliott Bay Group",
    "wof:placetype":"venue"
},
  "geometry": {"coordinates":[-122.358975,47.619551],"type":"Point"}
}