{
  "type": "Feature",
  "properties": {
    "addr:full":"1101 Harrison Ave Centralia WA 98531",
    "addr:housenumber":"1101",
    "addr:postcode":"98531",
    "addr:street":"Harrison Ave",
    "iso:country":"US",
    "sg:address":"1101 Harrison Ave",
    "sg:city":"Centralia",
    "sg:classifiers":[
        {
            "category":"Retail",
            "subcategory":"Laundry & Dry Cleaning",
            "type":"Services"
        }
    ],
    "sg:phone":"+1 360 736 8594",
    "sg:postcode":"98531",
    "sg:province":"WA",
    "sg:tags":[
        "drycleaning",
        "plant"
    ],
    "wof:name":"Youngs Cleaners",
    "wof:placetype":"venue"
},
  "geometry": {"coordinates":[-122.98069,46.728803],"type":"Point"}
}