{
  "type": "Feature",
  "properties": {
    "addr:full":"3032 N Shore Rd Bellingham WA 98226",
    "addr:housenumber":"3032",
    "addr:postcode":"98226",
    "addr:street":"N Shore Rd",
    "iso:country":"US",
    "sg:address":"3032 N Shore Rd",
    "sg:city":"Bellingham",
    "sg:classifiers":[
        {
            "category":"Social Services",
            "subcategory":"Job Training",
            "type":"Services"
        },
        {
            "category":"Education",
            "subcategory":"Vocational School",
            "type":"Public Place"
        }
    ],
    "sg:phone":"+1 360 738 9098",
    "sg:postcode":"98226",
    "sg:province":"WA",
    "sg:tags":[
        "consultant",
        "business"
    ],
    "sg:website":"http://www.novasim.com",
    "wof:name":"Novasim",
    "wof:placetype":"venue"
},
  "geometry": {"coordinates":[-122.32399700000001,48.739144],"type":"Point"}
}