{
  "type": "Feature",
  "properties": {
    "addr:full":"2717 E Roy St Seattle WA 98112",
    "addr:housenumber":"2717",
    "addr:postcode":"98112",
    "addr:street":"E Roy St",
    "iso:country":"US",
    "sg:address":"2717 E Roy St",
    "sg:city":"Seattle",
    "sg:classifiers":[
        {
            "category":"Professional",
            "subcategory":"Accounting & Tax Preparation",
            "type":"Services"
        }
    ],
    "sg:phone":"+1 206 522 1222",
    "sg:postcode":"98112",
    "sg:province":"WA",
    "sg:tags":[
        "medical",
        "billing"
    ],
    "wof:name":"A R Solutions",
    "wof:placetype":"venue"
},
  "geometry": {"coordinates":[-122.296654,47.625074],"type":"Point"}
}