{
  "type": "Feature",
  "properties": {
    "addr:full":"116 E Fir St Ste A Mount Vernon WA 98273",
    "addr:housenumber":"116",
    "addr:postcode":"98273",
    "addr:street":"E Fir St Ste A",
    "iso:country":"US",
    "sg:address":"116 E Fir St Ste A",
    "sg:city":"Mount Vernon",
    "sg:classifiers":[
        {
            "category":"Real Estate",
            "subcategory":"Architect",
            "type":"Services"
        }
    ],
    "sg:phone":"+1 360 424 0394",
    "sg:postcode":"98273",
    "sg:province":"WA",
    "sg:website":"www.carlettiarchitects.com",
    "wof:name":"Carletti Architects PS",
    "wof:placetype":"venue"
},
  "geometry": {"coordinates":[-122.334453,48.428243],"type":"Point"}
}