{
  "type": "Feature",
  "properties": {
    "addr:full":"5210 168th St SW Lynnwood WA 98037",
    "addr:housenumber":"5210",
    "addr:postcode":"98037",
    "addr:street":"168Th St Sw",
    "iso:country":"US",
    "sg:address":"5210 168th St SW",
    "sg:city":"Lynnwood",
    "sg:classifiers":[
        {
            "category":"Real Estate",
            "subcategory":"Real Estate Operator",
            "type":"Services"
        }
    ],
    "sg:phone":"+1 425 742 8903",
    "sg:postcode":"98037",
    "sg:province":"WA",
    "sg:tags":[
        "building",
        "apartment"
    ],
    "wof:name":"North Point Appartments",
    "wof:placetype":"venue"
},
  "geometry": {"coordinates":[-122.30444,47.84655],"type":"Point"}
}