{
  "type": "Feature",
  "properties": {
    "addr:full":"714 Ohio St Bellingham WA 98225",
    "addr:housenumber":"714",
    "addr:postcode":"98225",
    "addr:street":"Ohio St",
    "iso:country":"US",
    "sg:address":"714 Ohio St",
    "sg:city":"Bellingham",
    "sg:classifiers":[
        {
            "category":"Manufacturing",
            "subcategory":"Food",
            "type":"Manufacturing & Wholesale Goods"
        }
    ],
    "sg:phone":"+1 360 733 2344",
    "sg:postcode":"98225",
    "sg:province":"WA",
    "sg:tags":[
        "product",
        "retail",
        "bakery",
        "mfg"
    ],
    "wof:name":"Wonder/Hostess",
    "wof:placetype":"venue"
},
  "geometry": {"coordinates":[-122.465045,48.755044],"type":"Point"}
}