{
  "type": "Feature",
  "properties": {
    "addr:full":"9606 NE 302nd St Battle Ground WA 98604",
    "addr:housenumber":"9606",
    "addr:postcode":"98604",
    "addr:street":"Ne 302Nd St",
    "iso:country":"US",
    "sg:address":"9606 NE 302nd St",
    "sg:city":"Battle Ground",
    "sg:classifiers":[
        {
            "category":"Manufacturing",
            "subcategory":"Glass & Minerals",
            "type":"Manufacturing & Wholesale Goods"
        }
    ],
    "sg:phone":"+1 360 687 1663",
    "sg:postcode":"98604",
    "sg:province":"WA",
    "sg:tags":[
        "ornamental",
        "mfg",
        "precast",
        "concrete"
    ],
    "wof:name":"Custom Precast",
    "wof:placetype":"venue"
},
  "geometry": {"coordinates":[-122.574624,45.840725],"type":"Point"}
}