{
  "type": "Feature",
  "properties": {
    "addr:full":"4277 148th Ave NE Bellevue WA 98007",
    "addr:housenumber":"4277",
    "addr:postcode":"98007",
    "addr:street":"148Th Ave Ne",
    "iso:country":"US",
    "sg:address":"4277 148th Ave NE",
    "sg:city":"Bellevue",
    "sg:classifiers":[
        {
            "category":"Real Estate",
            "subcategory":"Real Estate Operator",
            "type":"Services"
        }
    ],
    "sg:phone":"+1 866 469 7492",
    "sg:postcode":"98007",
    "sg:province":"WA",
    "sg:tags":[
        "apartment"
    ],
    "sg:website":"www.equityapartments.com/market/...",
    "wof:name":"Bellevue Meadows",
    "wof:placetype":"venue"
},
  "geometry": {"coordinates":[-122.14317,47.648258],"type":"Point"}
}