{
  "type": "Feature",
  "properties": {
    "addr:full":"16340 NE 83rd St Redmond WA 98052",
    "addr:housenumber":"16340",
    "addr:postcode":"98052",
    "addr:street":"Ne 83Rd St",
    "iso:country":"US",
    "sg:address":"16340 NE 83rd St",
    "sg:city":"Redmond",
    "sg:classifiers":[
        {
            "category":"Professional",
            "subcategory":"Computer Services",
            "type":"Services"
        }
    ],
    "sg:phone":"+1 425 883 4690",
    "sg:postcode":"98052",
    "sg:province":"WA",
    "sg:tags":[
        "programing",
        "custom"
    ],
    "wof:name":"Ecommerce Vector Assoc",
    "wof:placetype":"venue"
},
  "geometry": {"coordinates":[-122.122371,47.676755],"type":"Point"}
}