{
  "type": "Feature",
  "properties": {
    "addr:full":"1112 W Spruce St Yakima WA 98902",
    "addr:housenumber":"1112",
    "addr:postcode":"98902",
    "addr:street":"W Spruce St",
    "iso:country":"US",
    "sg:address":"1112 W Spruce St",
    "sg:city":"Yakima",
    "sg:classifiers":[
        {
            "category":"Shopping",
            "subcategory":"Pharmacy",
            "type":"Retail Goods"
        }
    ],
    "sg:phone":"+1 509 453 4835",
    "sg:postcode":"98902",
    "sg:province":"WA",
    "wof:name":"Medicine Mart Stores",
    "wof:placetype":"venue"
},
  "geometry": {"coordinates":[-120.523206,46.594045],"type":"Point"}
}