{
  "type": "Feature",
  "properties": {
    "addr:full":"508 Coal Creek Rd Chehalis WA 98532",
    "addr:housenumber":"508",
    "addr:postcode":"98532",
    "addr:street":"Coal Creek Rd",
    "iso:country":"US",
    "sg:address":"508 Coal Creek Rd",
    "sg:city":"Chehalis",
    "sg:classifiers":[
        {
            "category":"Social Services",
            "type":"Services"
        }
    ],
    "sg:phone":"+1 360 748 1236",
    "sg:postcode":"98532",
    "sg:province":"WA",
    "sg:tags":[
        "shelter",
        "homeless"
    ],
    "wof:name":"Bethlehem Farm",
    "wof:placetype":"venue"
},
  "geometry": {"coordinates":[-122.93721600000001,46.66527],"type":"Point"}
}