{
  "type": "Feature",
  "properties": {
    "addr:full":"14500 Admiralty Way Lynnwood WA 98087",
    "addr:housenumber":"14500",
    "addr:postcode":"98087",
    "addr:street":"Admiralty Way",
    "iso:country":"US",
    "sg:address":"14500 Admiralty Way",
    "sg:city":"Lynnwood",
    "sg:classifiers":[
        {
            "category":"Real Estate",
            "subcategory":"Real Estate Operator",
            "type":"Services"
        }
    ],
    "sg:phone":"+1 425 742 3763",
    "sg:postcode":"98087",
    "sg:province":"WA",
    "sg:tags":[
        "apartment"
    ],
    "wof:name":"Tamaron Ranch",
    "wof:placetype":"venue"
},
  "geometry": {"coordinates":[-122.27209499999999,47.868304],"type":"Point"}
}