{
  "type": "Feature",
  "properties": {
    "addr:full":"420 W 8th St Vancouver WA 98660",
    "addr:housenumber":"420",
    "addr:postcode":"98660",
    "addr:street":"W 8Th St",
    "iso:country":"US",
    "sg:address":"420 W 8th St",
    "sg:city":"Vancouver",
    "sg:classifiers":[
        {
            "category":"Shopping",
            "subcategory":"Hobbies, Toys, & Games",
            "type":"Retail Goods"
        }
    ],
    "sg:phone":"+1 360 699 3050",
    "sg:postcode":"98660",
    "sg:province":"WA",
    "sg:tags":[
        "craft",
        "art",
        "supply"
    ],
    "wof:name":"Young Art",
    "wof:placetype":"venue"
},
  "geometry": {"coordinates":[-122.675135,45.627389],"type":"Point"}
}