{
  "type": "Feature",
  "properties": {
    "addr:full":"888 Hunter Ave Quincy WA 98848",
    "addr:housenumber":"888",
    "addr:postcode":"98848",
    "addr:street":"Hunter Ave",
    "iso:country":"US",
    "sg:address":"888 Hunter Ave",
    "sg:city":"Quincy",
    "sg:classifiers":[
        {
            "category":"Building & Trades",
            "subcategory":"Construction",
            "type":"Services"
        }
    ],
    "sg:phone":"+1 509 785 2003",
    "sg:postcode":"98848",
    "sg:province":"WA",
    "sg:tags":[
        "contractor"
    ],
    "wof:name":"Mountainside Construction",
    "wof:placetype":"venue"
},
  "geometry": {"coordinates":[-120.03108899999999,47.074368],"type":"Point"}
}