{
  "type": "Feature",
  "properties": {
    "addr:full":"1114 E Pike St Seattle WA 98122",
    "addr:housenumber":"1114",
    "addr:postcode":"98122",
    "addr:street":"E Pike St",
    "iso:country":"US",
    "sg:address":"1114 E Pike St",
    "sg:city":"Seattle",
    "sg:classifiers":[
        {
            "category":"Organizations",
            "subcategory":"Professional Association",
            "type":"Services"
        }
    ],
    "sg:phone":"+1 206 324 3359",
    "sg:postcode":"98122",
    "sg:province":"WA",
    "wof:name":"12th & Pike St Assocs",
    "wof:placetype":"venue"
},
  "geometry": {"coordinates":[-122.316964,47.614175],"type":"Point"}
}