{
  "type": "Feature",
  "properties": {
    "addr:full":"6600 NE 4th Plain Vancouver WA 98661",
    "addr:housenumber":"6600",
    "addr:postcode":"98661",
    "addr:street":"Ne 4Th Plain",
    "iso:country":"US",
    "sg:address":"6600 NE 4th Plain",
    "sg:city":"Vancouver",
    "sg:classifiers":[
        {
            "category":"Autos & Motor Vehicles",
            "subcategory":"Automobile Sales",
            "type":"Retail Goods"
        }
    ],
    "sg:phone":"+1 360 693 1481",
    "sg:postcode":"98661",
    "sg:province":"WA",
    "sg:tags":[
        "car"
    ],
    "sg:website":"www.carrauto.com/",
    "wof:name":"Carr Vancouver Cadillac GMC Pontiac Buick",
    "wof:placetype":"venue"
},
  "geometry": {"coordinates":[-122.604018,45.645026],"type":"Point"}
}