{
  "type": "Feature",
  "properties": {
    "addr:full":"4672 Birch Bay Lynden Rd Blaine WA 98230",
    "addr:housenumber":"4672",
    "addr:postcode":"98230",
    "addr:street":"Birch Bay Lynden Rd",
    "iso:country":"US",
    "sg:address":"4672 Birch Bay Lynden Rd",
    "sg:city":"Blaine",
    "sg:classifiers":[
        {
            "category":"Personal",
            "subcategory":"Beauty Salon",
            "type":"Services"
        }
    ],
    "sg:phone":"+1 360 371 3062",
    "sg:postcode":"98230",
    "sg:province":"WA",
    "wof:name":"Ann E & Randall W Heffner",
    "wof:placetype":"venue"
},
  "geometry": {"coordinates":[-122.735708,48.935855],"type":"Point"}
}