{
  "type": "Feature",
  "properties": {
    "addr:full":"8200 NE Highway 99 Ste 119 Vancouver WA 98665",
    "addr:housenumber":"8200",
    "addr:postcode":"98665",
    "addr:street":"Ne Highway 99 Ste 119",
    "iso:country":"US",
    "sg:address":"8200 NE Highway 99 Ste 119",
    "sg:city":"Vancouver",
    "sg:classifiers":[
        {
            "category":"Professional",
            "subcategory":"Management & Consulting",
            "type":"Services"
        },
        {
            "category":"Banks & Credit Unions",
            "subcategory":"Financial Services",
            "type":"Services"
        }
    ],
    "sg:phone":"+1 360 326 8726",
    "sg:postcode":"98665",
    "sg:province":"WA",
    "sg:tags":[
        "consultant",
        "financing",
        "planning"
    ],
    "wof:name":"Ccr & R",
    "wof:placetype":"venue"
},
  "geometry": {"coordinates":[-122.66165700000001,45.680857],"type":"Point"}
}