{
  "type": "Feature",
  "properties": {
    "addr:full":"13902 Hwy 99 Lynnwood WA 98087",
    "addr:housenumber":"13902",
    "addr:postcode":"98087",
    "addr:street":"Hwy 99",
    "iso:country":"US",
    "sg:address":"13902 Hwy 99",
    "sg:city":"Lynnwood",
    "sg:classifiers":[
        {
            "category":"Retail",
            "subcategory":"Laundry & Dry Cleaning",
            "type":"Services"
        }
    ],
    "sg:phone":"+1 206 282 2711",
    "sg:postcode":"98087",
    "sg:province":"WA",
    "sg:tags":[
        "cleaners"
    ],
    "wof:name":"Alpine Drapery & Carpet Clean",
    "wof:placetype":"venue"
},
  "geometry": {"coordinates":[-122.273904,47.87295],"type":"Point"}
}