{
  "type": "Feature",
  "properties": {
    "addr:full":"17009 Mink Rd NE Woodinville WA 98077",
    "addr:housenumber":"17009",
    "addr:postcode":"98077",
    "addr:street":"Mink Rd Ne",
    "iso:country":"US",
    "sg:address":"17009 Mink Rd NE",
    "sg:city":"Woodinville",
    "sg:classifiers":[
        {
            "category":"Wholesale",
            "subcategory":"Medical Equipment & Supplies",
            "type":"Manufacturing & Wholesale Goods"
        }
    ],
    "sg:phone":"+1 425 844 1189",
    "sg:postcode":"98077",
    "sg:province":"WA",
    "sg:tags":[
        "surgical",
        "laser"
    ],
    "wof:name":"Advanced Medical Inc",
    "wof:placetype":"venue"
},
  "geometry": {"coordinates":[-122.062004,47.752342],"type":"Point"}
}