{
  "type": "Feature",
  "properties": {
    "addr:full":"4100 Factoria Blvd SE Ste C Bellevue WA 98006",
    "addr:housenumber":"4100",
    "addr:postcode":"98006",
    "addr:street":"Factoria Blvd Se Ste C",
    "iso:country":"US",
    "sg:address":"4100 Factoria Blvd SE Ste C",
    "sg:city":"Bellevue",
    "sg:classifiers":[
        {
            "category":"Health Services",
            "subcategory":"Doctor",
            "type":"Services"
        }
    ],
    "sg:phone":"+1 425 747 7000",
    "sg:postcode":"98006",
    "sg:province":"WA",
    "sg:tags":[
        "surgeon",
        "oral"
    ],
    "wof:name":"Cooley Brandon E DDS",
    "wof:placetype":"venue"
},
  "geometry": {"coordinates":[-122.168999,47.5742],"type":"Point"}
}