{
  "type": "Feature",
  "properties": {
    "iso:country":"US",
    "sg:address":"17805 Frenchman Hills Rd",
    "sg:city":"Quincy",
    "sg:classifiers":[
        {
            "category":"Farming",
            "subcategory":"Orchard",
            "type":"Manufacturing & Wholesale Goods"
        }
    ],
    "sg:phone":"+1 509 785 2491",
    "sg:postcode":"98848",
    "sg:province":"WA",
    "sg:tags":[
        "fruit",
        "tree"
    ],
    "wof:name":"Northview Orchards",
    "wof:placetype":"venue"
},
  "geometry": {"coordinates":[-119.833544,47.000783],"type":"Point"}
}