{
  "type": "Feature",
  "properties": {
    "addr:full":"8930 W Payette Ave Kennewick WA 99336",
    "addr:housenumber":"8930",
    "addr:postcode":"99336",
    "addr:street":"W Payette Ave",
    "iso:country":"US",
    "sg:address":"8930 W Payette Ave",
    "sg:city":"Kennewick",
    "sg:classifiers":[
        {
            "category":"Building & Trades",
            "subcategory":"Construction",
            "type":"Services"
        }
    ],
    "sg:phone":"+1 509 735 8499",
    "sg:postcode":"99336",
    "sg:province":"WA",
    "sg:tags":[
        "foundation"
    ],
    "wof:name":"Concrete West Inc",
    "wof:placetype":"venue"
},
  "geometry": {"coordinates":[-119.242816,46.222304],"type":"Point"}
}