{
  "type": "Feature",
  "properties": {
    "addr:full":"12214 SE Mill Plain Blvd Vancouver WA 98684",
    "addr:postcode":"12214;98684",
    "addr:street":"Se Mill Plain Blvd",
    "iso:country":"US",
    "sg:address":"12214 SE Mill Plain Blvd",
    "sg:city":"Vancouver",
    "sg:classifiers":[
        {
            "category":"Health Services",
            "subcategory":"Chiropractor",
            "type":"Services"
        }
    ],
    "sg:phone":"+1 360 254 4040",
    "sg:postcode":"98684",
    "sg:province":"WA",
    "wof:name":"Homer Lucas Q DC",
    "wof:placetype":"venue"
},
  "geometry": {"coordinates":[-122.546997,45.6203],"type":"Point"}
}