{
  "type": "Feature",
  "properties": {
    "addr:full":"1531 Melrose Ave Ste C Seattle WA 98101",
    "addr:housenumber":"1531",
    "addr:postcode":"98101",
    "addr:street":"Melrose Ave Ste C",
    "iso:country":"US",
    "sg:address":"1531 Melrose Ave Ste C",
    "sg:city":"Seattle",
    "sg:classifiers":[
        {
            "category":"Food & Beverages",
            "subcategory":"Farmers Market",
            "type":"Retail Goods"
        },
        {
            "category":"Food & Beverages",
            "subcategory":"Meat & Fish",
            "type":"Retail Goods"
        },
        {
            "category":"Food & Beverages",
            "subcategory":"Groceries & Convenience Stores",
            "type":"Retail Goods"
        }
    ],
    "sg:phone":"+1 206 467 6328",
    "sg:postcode":"98101",
    "sg:province":"WA",
    "sg:tags":[
        "shop"
    ],
    "sg:website":"rainshadowmeats.com/",
    "wof:name":"Rain Shadow Meats",
    "wof:placetype":"venue"
},
  "geometry": {"coordinates":[-122.328211,47.614753],"type":"Point"}
}