{
  "type": "Feature",
  "properties": {
    "addr:full":"2602 3rd Avenue Seattle WA 98121",
    "addr:housenumber":"2602",
    "addr:postcode":"98121",
    "addr:street":"3Rd Avenue",
    "iso:country":"US",
    "sg:address":"2602 3rd Avenue",
    "sg:city":"Seattle",
    "sg:classifiers":[
        {
            "category":"Personal",
            "subcategory":"Beauty Salon",
            "type":"Services"
        }
    ],
    "sg:phone":"+1 206 890 6675",
    "sg:postcode":"98121",
    "sg:province":"WA",
    "sg:tags":[
        "hair"
    ],
    "wof:name":"Barney Rod R",
    "wof:placetype":"venue"
},
  "geometry": {"coordinates":[-122.348015,47.616633],"type":"Point"}
}