{
  "type": "Feature",
  "properties": {
    "addr:full":"19300 International Blvd Seatac WA 98188",
    "addr:housenumber":"19300",
    "addr:postcode":"98188",
    "addr:street":"International Blvd",
    "iso:country":"US",
    "sg:address":"19300 International Blvd",
    "sg:city":"Seatac",
    "sg:classifiers":[
        {
            "category":"Airline",
            "type":"Transportation"
        }
    ],
    "sg:phone":"+1 206 392 5040",
    "sg:postcode":"98188",
    "sg:province":"WA",
    "sg:tags":[
        "company"
    ],
    "sg:website":"www.alaskaair.com",
    "wof:name":"Alaska Air Group Inc",
    "wof:placetype":"venue"
},
  "geometry": {"coordinates":[-122.295419,47.429281],"type":"Point"}
}