{
  "type": "Feature",
  "properties": {
    "addr:full":"8926 178th Stct E Puyallup WA 98375",
    "addr:housenumber":"8926",
    "addr:postcode":"98375",
    "addr:street":"178Th Stct E",
    "iso:country":"US",
    "sg:address":"8926 178th Stct E",
    "sg:city":"Puyallup",
    "sg:classifiers":[
        {
            "category":"Shopping",
            "type":"Retail Goods"
        }
    ],
    "sg:phone":"+1 253 262 1218",
    "sg:postcode":"98375",
    "sg:province":"WA",
    "sg:tags":[
        "merchandise"
    ],
    "wof:name":"Naomis Perfect Wedding",
    "wof:placetype":"venue"
},
  "geometry": {"coordinates":[-122.30962,47.094534],"type":"Point"}
}