{
  "type": "Feature",
  "properties": {
    "addr:full":"16811 W Four Mound Rd Nine Mile Falls WA 99026",
    "addr:housenumber":"16811",
    "addr:postcode":"99026",
    "addr:street":"W Four Mound Rd",
    "iso:country":"US",
    "sg:address":"16811 W Four Mound Rd",
    "sg:city":"Nine Mile Falls",
    "sg:classifiers":[
        {
            "category":"Manufacturing",
            "subcategory":"Rubber & Plastics",
            "type":"Manufacturing & Wholesale Goods"
        }
    ],
    "sg:phone":"+1 509 466 1986",
    "sg:postcode":"99026",
    "sg:province":"WA",
    "wof:name":"Advanced Materials Fab & Rpr",
    "wof:placetype":"venue"
},
  "geometry": {"coordinates":[-117.641882,47.775486],"type":"Point"}
}