{
  "type": "Feature",
  "properties": {
    "addr:full":"901 Officers Row Vancouver WA 98661",
    "addr:housenumber":"901",
    "addr:postcode":"98661",
    "addr:street":"Officers Row",
    "iso:country":"US",
    "sg:address":"901 Officers Row",
    "sg:city":"Vancouver",
    "sg:classifiers":[
        {
            "category":"Health Services",
            "subcategory":"Doctor",
            "type":"Services"
        },
        {
            "category":"Health Services",
            "subcategory":"Clinic",
            "type":"Services"
        }
    ],
    "sg:phone":"+1 360 693 3715",
    "sg:postcode":"98661",
    "sg:province":"WA",
    "sg:tags":[
        "counseling",
        "mental"
    ],
    "wof:name":"Moore Lawrence H PHD",
    "wof:placetype":"venue"
},
  "geometry": {"coordinates":[-122.656998,45.6278],"type":"Point"}
}