{
  "type": "Feature",
  "properties": {
    "addr:full":"3359 Hollywood Ave Bellingham WA 98225",
    "addr:housenumber":"3359",
    "addr:postcode":"98225",
    "addr:street":"Hollywood Ave",
    "iso:country":"US",
    "sg:address":"3359 Hollywood Ave",
    "sg:city":"Bellingham",
    "sg:classifiers":[
        {
            "category":"Building & Trades",
            "subcategory":"Cleaning & Sanitation",
            "type":"Services"
        }
    ],
    "sg:phone":"+1 360 752 3228",
    "sg:postcode":"98225",
    "sg:province":"WA",
    "sg:tags":[
        "maintenance"
    ],
    "wof:name":"Emerald Shine",
    "wof:placetype":"venue"
},
  "geometry": {"coordinates":[-122.527716,48.777444],"type":"Point"}
}