{
  "type": "Feature",
  "properties": {
    "addr:full":"1155 Aberdeen Ave NE Renton WA 98056",
    "addr:housenumber":"1155",
    "addr:postcode":"98056",
    "addr:street":"Aberdeen Ave Ne",
    "iso:country":"US",
    "sg:address":"1155 Aberdeen Ave NE",
    "sg:city":"Renton",
    "sg:classifiers":[
        {
            "category":"Building & Trades",
            "subcategory":"Plumbing",
            "type":"Services"
        }
    ],
    "sg:phone":"+1 425 430 5410",
    "sg:postcode":"98056",
    "sg:province":"WA",
    "sg:tags":[
        "heating",
        "contractor"
    ],
    "wof:name":"Boilers Northwest",
    "wof:placetype":"venue"
},
  "geometry": {"coordinates":[-122.191146,47.501612],"type":"Point"}
}