{
  "type": "Feature",
  "properties": {
    "addr:full":"20205 107th Ave NE Bothell WA 98011",
    "addr:housenumber":"20205",
    "addr:postcode":"98011",
    "addr:street":"107Th Ave Ne",
    "iso:country":"US",
    "sg:address":"20205 107th Ave NE",
    "sg:city":"Bothell",
    "sg:classifiers":[
        {
            "category":"Health Services",
            "subcategory":"Nursing And Care Facility",
            "type":"Services"
        }
    ],
    "sg:phone":"+1 425 485 6213",
    "sg:postcode":"98011",
    "sg:province":"WA",
    "sg:tags":[
        "skilled"
    ],
    "wof:name":"Carlson Care Adult Family Home",
    "wof:placetype":"venue"
},
  "geometry": {"coordinates":[-122.197379,47.775123],"type":"Point"}
}