{
  "type": "Feature",
  "properties": {
    "addr:full":"2400 N 65th Street Seattle WA 98103",
    "addr:housenumber":"2400",
    "addr:postcode":"98103",
    "addr:street":"N 65Th Street",
    "iso:country":"US",
    "sg:address":"2400 N 65th Street",
    "sg:city":"Seattle",
    "sg:classifiers":[
        {
            "category":"Education",
            "subcategory":"School",
            "type":"Public Place"
        }
    ],
    "sg:phone":"+1 206 252 5320",
    "sg:postcode":"98103",
    "sg:province":"WA",
    "sg:website":"www.seattleschools.org",
    "wof:name":"Seattle Public Schools",
    "wof:placetype":"venue"
},
  "geometry": {"coordinates":[-122.32902300000001,47.675853],"type":"Point"}
}