{
  "type": "Feature",
  "properties": {
    "addr:full":"3901 N Market St Spokane WA 99207",
    "addr:housenumber":"3901",
    "addr:postcode":"99207",
    "addr:street":"N Market St",
    "iso:country":"US",
    "sg:address":"3901 N Market St",
    "sg:city":"Spokane",
    "sg:classifiers":[
        {
            "category":"Cinema",
            "subcategory":"Movie Rental",
            "type":"Entertainment"
        }
    ],
    "sg:phone":"+1 509 487 5709",
    "sg:postcode":"99207",
    "sg:province":"WA",
    "sg:tags":[
        "leasing",
        "video",
        "disc",
        "tape"
    ],
    "wof:name":"Blockbuster Video",
    "wof:placetype":"venue"
},
  "geometry": {"coordinates":[-117.365036,47.695122],"type":"Point"}
}