{
  "type": "Feature",
  "properties": {
    "addr:full":"18539 Westside Hwy SW Vashon WA 98070",
    "addr:housenumber":"18539",
    "addr:postcode":"98070",
    "addr:street":"Westside Hwy Sw",
    "iso:country":"US",
    "sg:address":"18539 Westside Hwy SW",
    "sg:city":"Vashon",
    "sg:classifiers":[
        {
            "category":"Professional",
            "subcategory":"Engineering",
            "type":"Services"
        }
    ],
    "sg:phone":"+1 206 463 2155",
    "sg:postcode":"98070",
    "sg:province":"WA",
    "sg:tags":[
        "consulting",
        "management"
    ],
    "wof:name":"John H Olsen Inc",
    "wof:placetype":"venue"
},
  "geometry": {"coordinates":[-122.50823800000001,47.438654],"type":"Point"}
}