{
  "type": "Feature",
  "properties": {
    "addr:full":"23106 118th St SE Monroe WA 98272",
    "addr:housenumber":"23106",
    "addr:postcode":"98272",
    "addr:street":"118Th St Se",
    "iso:country":"US",
    "sg:address":"23106 118th St SE",
    "sg:city":"Monroe",
    "sg:classifiers":[
        {
            "category":"Wholesale",
            "subcategory":"Non-durable Goods",
            "type":"Manufacturing & Wholesale Goods"
        }
    ],
    "sg:phone":"+1 360 794 0642",
    "sg:postcode":"98272",
    "sg:province":"WA",
    "wof:name":"Sachsen Imports",
    "wof:placetype":"venue"
},
  "geometry": {"coordinates":[-121.920306,47.891903],"type":"Point"}
}