{
  "type": "Feature",
  "properties": {
    "iso:country":"US",
    "sg:address":"14910 Pacific Ave S",
    "sg:city":"Tacoma",
    "sg:classifiers":[
        {
            "category":"Social Services",
            "subcategory":"Job Training",
            "type":"Services"
        }
    ],
    "sg:phone":"+1 253 537 6884",
    "sg:postcode":"98444",
    "sg:province":"WA",
    "sg:tags":[
        "employment"
    ],
    "wof:name":"Vocations Unlimited",
    "wof:placetype":"venue"
},
  "geometry": {"coordinates":[-122.43496,47.121794],"type":"Point"}
}