{
  "type": "Feature",
  "properties": {
    "addr:full":"2033 2nd Ave #1208 Seattle WA 98121",
    "addr:housenumber":"2033",
    "addr:postcode":"98121",
    "addr:street":"2Nd Ave # 1208",
    "iso:country":"US",
    "sg:address":"2033 2nd Ave #1208",
    "sg:city":"Seattle",
    "sg:classifiers":[
        {
            "category":"Professional",
            "subcategory":"Art Services",
            "type":"Services"
        }
    ],
    "sg:phone":"+1 206 226 7541",
    "sg:postcode":"98121",
    "sg:province":"WA",
    "sg:tags":[
        "interior",
        "designer",
        "decorator"
    ],
    "sg:website":"http://www.millerinteriordesign.com/",
    "wof:name":"Miller Interior Design, LLC",
    "wof:placetype":"venue"
},
  "geometry": {"coordinates":[-122.342167,47.611981],"type":"Point"}
}