{
  "type": "Feature",
  "properties": {
    "addr:full":"7201 S Oakes St Tacoma WA 98409",
    "addr:housenumber":"7201",
    "addr:postcode":"98409",
    "addr:street":"S Oakes St",
    "iso:country":"US",
    "sg:address":"7201 S Oakes St",
    "sg:city":"Tacoma",
    "sg:classifiers":[
        {
            "category":"Food & Beverages",
            "subcategory":"Groceries & Convenience Stores",
            "type":"Retail Goods"
        }
    ],
    "sg:phone":"+1 253 474 8731",
    "sg:postcode":"98409",
    "sg:province":"WA",
    "sg:tags":[
        "grocer"
    ],
    "wof:name":"Oak Street Market",
    "wof:placetype":"venue"
},
  "geometry": {"coordinates":[-122.47246699999999,47.190149],"type":"Point"}
}