{
  "type": "Feature",
  "properties": {
    "addr:full":"29616 41st Pl S Auburn WA 98001",
    "addr:housenumber":"29616",
    "addr:postcode":"98001",
    "addr:street":"41St Pl S",
    "iso:country":"US",
    "sg:address":"29616 41st Pl S",
    "sg:city":"Auburn",
    "sg:classifiers":[
        {
            "category":"Manufacturing",
            "subcategory":"Retail Goods",
            "type":"Manufacturing & Wholesale Goods"
        }
    ],
    "sg:phone":"+1 253 839 2492",
    "sg:postcode":"98001",
    "sg:province":"WA",
    "sg:tags":[
        "product",
        "mfg"
    ],
    "wof:name":"Beads Galore",
    "wof:placetype":"venue"
},
  "geometry": {"coordinates":[-122.28183199999999,47.336581],"type":"Point"}
}