{
  "type": "Feature",
  "properties": {
    "addr:full":"14400 Bel Red Rd Ste 205 Bellevue WA 98007",
    "addr:housenumber":"14400",
    "addr:postcode":"98007",
    "addr:street":"Bel Red Rd Ste 205",
    "iso:country":"US",
    "sg:address":"14400 Bel Red Rd Ste 205",
    "sg:city":"Bellevue",
    "sg:classifiers":[
        {
            "category":"Professional",
            "subcategory":"Research",
            "type":"Services"
        },
        {
            "category":"Education",
            "subcategory":"Library",
            "type":"Public Place"
        }
    ],
    "sg:phone":"+1 425 643 7780",
    "sg:postcode":"98007",
    "sg:province":"WA",
    "wof:name":"The Wayne Seminoff Company",
    "wof:placetype":"venue"
},
  "geometry": {"coordinates":[-122.149185,47.625278],"type":"Point"}
}