{
  "type": "Feature",
  "properties": {
    "addr:full":"18213 100th Street Kp N Vaughn WA 98329",
    "addr:housenumber":"18213",
    "addr:postcode":"98329",
    "addr:street":"100Th Street Kp N",
    "iso:country":"US",
    "sg:address":"18213 100th Street Kp N",
    "sg:city":"Vaughn",
    "sg:classifiers":[
        {
            "category":"Shopping",
            "subcategory":"Clothing, Apparel, & Fashions",
            "type":"Retail Goods"
        }
    ],
    "sg:phone":"+1 253 840 1018",
    "sg:postcode":"98329",
    "sg:province":"WA",
    "sg:tags":[
        "sportswear"
    ],
    "wof:name":"Sportswear Express",
    "wof:placetype":"venue"
},
  "geometry": {"coordinates":[-122.78215299999999,47.349218],"type":"Point"}
}