{
  "type": "Feature",
  "properties": {
    "addr:full":"1320 Lum Rd Centralia WA 98531",
    "addr:housenumber":"1320",
    "addr:postcode":"98531",
    "addr:street":"Lum Rd",
    "iso:country":"US",
    "sg:address":"1320 Lum Rd",
    "sg:city":"Centralia",
    "sg:classifiers":[
        {
            "category":"Home & Garden",
            "subcategory":"Home Furnishings",
            "type":"Retail Goods"
        }
    ],
    "sg:phone":"+1 360 736 6333",
    "sg:postcode":"98531",
    "sg:province":"WA",
    "sg:tags":[
        "ware",
        "kitchen"
    ],
    "wof:name":"Corning Revere Factory Store",
    "wof:placetype":"venue"
},
  "geometry": {"coordinates":[-122.97754399999999,46.730578],"type":"Point"}
}