{
  "type": "Feature",
  "properties": {
    "addr:full":"2501 9th Ave W Seattle WA 98119",
    "addr:housenumber":"2501",
    "addr:postcode":"98119",
    "addr:street":"9Th Ave W",
    "iso:country":"US",
    "sg:address":"2501 9th Ave W",
    "sg:city":"Seattle",
    "sg:classifiers":[
        {
            "category":"Shopping",
            "subcategory":"Crafts & Fabrics",
            "type":"Retail Goods"
        }
    ],
    "sg:phone":"+1 206 282 8018",
    "sg:postcode":"98119",
    "sg:province":"WA",
    "sg:tags":[
        "sewing"
    ],
    "wof:name":"Thimble Craft",
    "wof:placetype":"venue"
},
  "geometry": {"coordinates":[-122.368933,47.642013],"type":"Point"}
}