{
  "type": "Feature",
  "properties": {
    "addr:full":"1307 1st Ave Seattle WA 98101",
    "addr:housenumber":"1307",
    "addr:postcode":"98101",
    "addr:street":"1St Ave",
    "iso:country":"US",
    "sg:address":"1307 1st Ave",
    "sg:city":"Seattle",
    "sg:classifiers":[
        {
            "category":"Shopping",
            "subcategory":"Clothing, Apparel, & Fashions",
            "type":"Retail Goods"
        }
    ],
    "sg:phone":"+1 206 684 6886",
    "sg:postcode":"98101",
    "sg:province":"WA",
    "sg:tags":[
        "woman",
        "man"
    ],
    "wof:name":"Nuvo Moda",
    "wof:placetype":"venue"
},
  "geometry": {"coordinates":[-122.339133,47.607725],"type":"Point"}
}