{
  "type": "Feature",
  "properties": {
    "addr:full":"116 E Hemlock St Othello WA 99344",
    "addr:housenumber":"116",
    "addr:postcode":"99344",
    "addr:street":"E Hemlock St",
    "iso:country":"US",
    "sg:address":"116 E Hemlock St",
    "sg:city":"Othello",
    "sg:classifiers":[
        {
            "category":"Personal",
            "subcategory":"Beauty Salon",
            "type":"Services"
        }
    ],
    "sg:phone":"+1 509 488 6123",
    "sg:postcode":"99344",
    "sg:province":"WA",
    "sg:tags":[
        "shop"
    ],
    "wof:name":"Hair Designs",
    "wof:placetype":"venue"
},
  "geometry": {"coordinates":[-119.173759,46.825113],"type":"Point"}
}