{
  "type": "Feature",
  "properties": {
    "addr:full":"22942 State Highway 97 Orondo WA 98843",
    "addr:housenumber":"22942",
    "addr:postcode":"98843",
    "addr:street":"State Highway 97 Orondo",
    "iso:country":"US",
    "sg:address":"22942 State Highway 97",
    "sg:city":"Orondo",
    "sg:classifiers":[
        {
            "category":"Farming",
            "subcategory":"Orchard",
            "type":"Manufacturing & Wholesale Goods"
        }
    ],
    "sg:phone":"+1 509 682 5698",
    "sg:postcode":"98843",
    "sg:province":"WA",
    "wof:name":"E Davis Wesley & Sons Inc",
    "wof:placetype":"venue"
},
  "geometry": {"coordinates":[-120.046491,47.770981],"type":"Point"}
}