{
  "type": "Feature",
  "properties": {
    "addr:full":"17126 17th Ave SE Bothell WA 98012",
    "addr:housenumber":"17126",
    "addr:postcode":"98012",
    "addr:street":"17Th Ave Se",
    "iso:country":"US",
    "sg:address":"17126 17th Ave SE",
    "sg:city":"Bothell",
    "sg:classifiers":[
        {
            "category":"Professional",
            "subcategory":"Management & Consulting",
            "type":"Services"
        }
    ],
    "sg:phone":"+1 425 481 8988",
    "sg:postcode":"98012",
    "sg:province":"WA",
    "sg:tags":[
        "business"
    ],
    "wof:name":"Evans Communications",
    "wof:placetype":"venue"
},
  "geometry": {"coordinates":[-122.209653,47.842359],"type":"Point"}
}