{
  "type": "Feature",
  "properties": {
    "addr:full":"631 Young Grade Rd Yakima WA 98908",
    "addr:housenumber":"631",
    "addr:postcode":"98908",
    "addr:street":"Young Grade Rd",
    "iso:country":"US",
    "sg:address":"631 Young Grade Rd",
    "sg:city":"Yakima",
    "sg:classifiers":[
        {
            "category":"Professional",
            "subcategory":"Business Services",
            "type":"Services"
        }
    ],
    "sg:phone":"+1 509 966 0942",
    "sg:postcode":"98908",
    "sg:province":"WA",
    "sg:tags":[
        "estate"
    ],
    "wof:name":"Handwerkers",
    "wof:placetype":"venue"
},
  "geometry": {"coordinates":[-120.667794,46.665659],"type":"Point"}
}