{
  "type": "Feature",
  "properties": {
    "addr:full":"17 Hospital Way Brewster WA 98812",
    "addr:housenumber":"17",
    "addr:postcode":"98812",
    "addr:street":"Hospital Way",
    "iso:country":"US",
    "sg:address":"17 Hospital Way",
    "sg:city":"Brewster",
    "sg:classifiers":[
        {
            "category":"Organizations",
            "subcategory":"Religious Organization",
            "type":"Services"
        }
    ],
    "sg:phone":"+1 509 689 3537",
    "sg:postcode":"98812",
    "sg:province":"WA",
    "sg:tags":[
        "church"
    ],
    "wof:name":"Seventh-Day Adventist Church",
    "wof:placetype":"venue"
},
  "geometry": {"coordinates":[-119.77602899999999,48.10934],"type":"Point"}
}