{
  "type": "Feature",
  "properties": {
    "addr:full":"3456 37th Ave W Seattle WA 98199",
    "addr:housenumber":"3456",
    "addr:postcode":"98199",
    "addr:street":"37Th Ave W",
    "iso:country":"US",
    "sg:address":"3456 37th Ave W",
    "sg:city":"Seattle",
    "sg:classifiers":[
        {
            "category":"Manufacturing",
            "subcategory":"Retail Goods",
            "type":"Manufacturing & Wholesale Goods"
        }
    ],
    "sg:phone":"+1 206 283 7240",
    "sg:postcode":"98199",
    "sg:province":"WA",
    "sg:tags":[
        "product",
        "boat",
        "mfg"
    ],
    "wof:name":"Ship To Shore Inc",
    "wof:placetype":"venue"
},
  "geometry": {"coordinates":[-122.404599,47.651793],"type":"Point"}
}