{
  "type": "Feature",
  "properties": {
    "addr:full":"8276 Golden Valley Blvd Maple Falls WA 98266",
    "addr:housenumber":"8276",
    "addr:postcode":"98266",
    "addr:street":"Golden Valley Blvd",
    "iso:country":"US",
    "sg:address":"8276 Golden Valley Blvd",
    "sg:city":"Maple Falls",
    "sg:classifiers":[
        {
            "category":"Professional",
            "subcategory":"Business Services",
            "type":"Services"
        }
    ],
    "sg:phone":"+1 360 599 9181",
    "sg:postcode":"98266",
    "sg:province":"WA",
    "wof:name":"Charlie & Alix Hicks",
    "wof:placetype":"venue"
},
  "geometry": {"coordinates":[-122.149514,48.944275],"type":"Point"}
}