{
  "type": "Feature",
  "properties": {
    "addr:full":"3802 164th St SE Bothell WA 98012",
    "addr:housenumber":"3802",
    "addr:postcode":"98012",
    "addr:street":"164Th St Se",
    "iso:country":"US",
    "sg:address":"3802 164th St SE",
    "sg:city":"Bothell",
    "sg:classifiers":[
        {
            "category":"Manufacturing",
            "subcategory":"Metals",
            "type":"Manufacturing & Wholesale Goods"
        }
    ],
    "sg:phone":"+1 425 486 3187",
    "sg:postcode":"98012",
    "sg:province":"WA",
    "sg:tags":[
        "product",
        "wire",
        "fabricated",
        "mfg"
    ],
    "wof:name":"Avian Creations & More Inc",
    "wof:placetype":"venue"
},
  "geometry": {"coordinates":[-122.182457,47.848883],"type":"Point"}
}