{
  "type": "Feature",
  "properties": {
    "addr:full":"9716 NE 76th St Vancouver WA 98662",
    "addr:housenumber":"9716",
    "addr:postcode":"98662",
    "addr:street":"Ne 76Th St",
    "iso:country":"US",
    "sg:address":"9716 NE 76th St",
    "sg:city":"Vancouver",
    "sg:classifiers":[
        {
            "category":"Health Services",
            "subcategory":"Chiropractor",
            "type":"Services"
        },
        {
            "category":"Health Services",
            "subcategory":"Optometrist",
            "type":"Services"
        }
    ],
    "sg:phone":"+1 360 256 6970",
    "sg:postcode":"98662",
    "sg:province":"WA",
    "wof:name":"Whitmire Chiropractic Center",
    "wof:placetype":"venue"
},
  "geometry": {"coordinates":[-122.571427,45.677809],"type":"Point"}
}