{
  "type": "Feature",
  "properties": {
    "addr:full":"110 W 9th St Vancouver WA 98660",
    "addr:housenumber":"110",
    "addr:postcode":"98660",
    "addr:street":"W 9Th St",
    "iso:country":"US",
    "sg:address":"110 W 9th St",
    "sg:city":"Vancouver",
    "sg:classifiers":[
        {
            "category":"Shopping",
            "type":"Retail Goods"
        }
    ],
    "sg:phone":"+1 360 750 8660",
    "sg:postcode":"98660",
    "sg:province":"WA",
    "sg:tags":[
        "merchandise"
    ],
    "wof:name":"Vancouver Rare Coin",
    "wof:placetype":"venue"
},
  "geometry": {"coordinates":[-122.67173699999999,45.628011],"type":"Point"}
}