{
  "type": "Feature",
  "properties": {
    "addr:full":"315 2nd Ave S Seattle WA 98104",
    "addr:housenumber":"315",
    "addr:postcode":"98104",
    "addr:street":"2Nd Ave S",
    "iso:country":"US",
    "sg:address":"315 2nd Ave S",
    "sg:city":"Seattle",
    "sg:classifiers":[
        {
            "category":"Arts & Performance",
            "subcategory":"Music",
            "type":"Entertainment"
        },
        {
            "category":"Bars & Pubs",
            "subcategory":"Lounge",
            "type":"Food & Drink"
        },
        {
            "category":"Retail",
            "subcategory":"Event Space",
            "type":"Services"
        },
        {
            "category":"Restaurant",
            "type":"Food & Drink"
        },
        {
            "category":"Recreation",
            "type":"Entertainment"
        },
        {
            "category":"Bars & Pubs",
            "type":"Food & Drink"
        },
        {
            "category":"Personal",
            "type":"Services"
        },
        {
            "category":"Arts & Performance",
            "subcategory":"Comedy Club",
            "type":"Entertainment"
        },
        {
            "category":"Bars & Pubs",
            "subcategory":"Nightclub",
            "type":"Food & Drink"
        }
    ],
    "sg:phone":"+1 206 839 1300",
    "sg:postcode":"98104",
    "sg:province":"WA",
    "sg:tags":[
        "grill",
        "business",
        "musician",
        "orchestra",
        "band",
        "planning",
        "entertainers-family",
        "wedding",
        "party",
        "italian",
        "meeting",
        "karaoke",
        "night"
    ],
    "sg:website":"http://www.ilove88keys.com",
    "wof:name":"88 Keys Dueling Piano and Sport Bar",
    "wof:placetype":"venue"
},
  "geometry": {"coordinates":[-122.33158,47.59993],"type":"Point"}
}