{
  "type": "Feature",
  "properties": {
    "addr:full":"1800 7 Oaks Rd SE Lacey WA 98503",
    "addr:housenumber":"1800",
    "addr:postcode":"98503",
    "addr:street":"7 Oaks Rd Se",
    "iso:country":"US",
    "sg:address":"1800 7 Oaks Rd SE",
    "sg:city":"Lacey",
    "sg:classifiers":[
        {
            "category":"Education",
            "subcategory":"School",
            "type":"Public Place"
        }
    ],
    "sg:phone":"+1 360 412 4700",
    "sg:postcode":"98503",
    "sg:province":"WA",
    "sg:tags":[
        "elementary"
    ],
    "sg:website":"http://www.nthurston.k12.wa.us/education/components/scrapbook/default.php?sectionid=158",
    "wof:name":"Seven Oaks Elementary School",
    "wof:placetype":"venue"
},
  "geometry": {"coordinates":[-122.772758,47.02993],"type":"Point"}
}