{
  "type": "Feature",
  "properties": {
    "addr:full":"6710 108th Ave NE Kirkland WA 98033",
    "addr:housenumber":"6710",
    "addr:postcode":"98033",
    "addr:street":"108Th Ave Ne",
    "iso:country":"US",
    "sg:address":"6710 108th Ave NE",
    "sg:city":"Kirkland",
    "sg:classifiers":[
        {
            "category":"Professional",
            "subcategory":"Art Services",
            "type":"Services"
        },
        {
            "category":"Communications",
            "type":"Services"
        }
    ],
    "sg:phone":"+1 425 458 4580",
    "sg:postcode":"98033",
    "sg:province":"WA",
    "sg:tags":[
        "web",
        "graphic",
        "design"
    ],
    "sg:website":"www.clocktowermedia.com",
    "wof:name":"Clocktower Media",
    "wof:placetype":"venue"
},
  "geometry": {"coordinates":[-122.19529900000001,47.665869],"type":"Point"}
}