{
  "type": "Feature",
  "properties": {
    "addr:full":"602 Long Hollow Rd Colfax WA 99111",
    "addr:housenumber":"602",
    "addr:postcode":"99111",
    "addr:street":"Long Hollow Rd",
    "iso:country":"US",
    "sg:address":"602 Long Hollow Rd",
    "sg:city":"Colfax",
    "sg:classifiers":[
        {
            "category":"Structure",
            "subcategory":"Office Building",
            "type":"Public Place"
        }
    ],
    "sg:phone":"+1 509 397 4096",
    "sg:postcode":"99111",
    "sg:province":"WA",
    "sg:tags":[
        "park"
    ],
    "wof:name":"Camar Properties, Inc.",
    "wof:placetype":"venue"
},
  "geometry": {"coordinates":[-117.46233599999999,46.756828],"type":"Point"}
}