{
  "type": "Feature",
  "properties": {
    "addr:full":"916 Main St Vancouver WA 98660",
    "addr:housenumber":"916",
    "addr:postcode":"98660",
    "addr:street":"Main St",
    "iso:country":"US",
    "sg:address":"916 Main St",
    "sg:city":"Vancouver",
    "sg:classifiers":[
        {
            "category":"Insurance",
            "subcategory":"Insurance Agent",
            "type":"Services"
        },
        {
            "category":"Insurance",
            "subcategory":"Hazard Insurance",
            "type":"Services"
        }
    ],
    "sg:phone":"+1 360 695 3301",
    "sg:postcode":"98660",
    "sg:province":"WA",
    "sg:tags":[
        "auto",
        "recreational",
        "motorcycle",
        "vehicle",
        "marine",
        "boat"
    ],
    "sg:website":"http://www.biggsinsurance.com",
    "wof:name":"Biggs Insurance Services",
    "wof:placetype":"venue"
},
  "geometry": {"coordinates":[-122.671621,45.628136],"type":"Point"}
}