{
  "type": "Feature",
  "properties": {
    "addr:full":"111802 E Pine Hollow Pr SE Kennewick WA 99338",
    "addr:housenumber":"111802",
    "addr:postcode":"99338",
    "addr:street":"E Pine Hollow;Se",
    "iso:country":"US",
    "sg:address":"111802 E Pine Hollow Pr SE",
    "sg:city":"Kennewick",
    "sg:classifiers":[
        {
            "category":"Utilities",
            "subcategory":"Electric",
            "type":"Services"
        },
        {
            "category":"Building & Trades",
            "subcategory":"Electrical",
            "type":"Services"
        }
    ],
    "sg:phone":"+1 509 627 0400",
    "sg:postcode":"99338",
    "sg:province":"WA",
    "sg:tags":[
        "equipment-repair",
        "industrial",
        "electrician",
        "contractors-commercial"
    ],
    "sg:website":"http://raineselectricinc.com",
    "wof:name":"Raines Electric, inc.",
    "wof:placetype":"venue"
},
  "geometry": {"coordinates":[-119.26389500000001,46.179822],"type":"Point"}
}