{
  "type": "Feature",
  "properties": {
    "addr:full":"660 W Olympic Pl Apt 1 Seattle WA 98119",
    "addr:housenumber":"660;1",
    "addr:postcode":"98119",
    "addr:street":"W Olympic Pl Apt",
    "iso:country":"US",
    "sg:address":"660 W Olympic Pl Apt 1",
    "sg:city":"Seattle",
    "sg:classifiers":[
        {
            "category":"Shopping",
            "subcategory":"Clothing, Apparel, & Fashions",
            "type":"Retail Goods"
        }
    ],
    "sg:phone":"+1 206 281 1117",
    "sg:postcode":"98119",
    "sg:province":"WA",
    "sg:tags":[
        "clothing",
        "glove",
        "store"
    ],
    "wof:name":"Jacklyn Vhugen Design",
    "wof:placetype":"venue"
},
  "geometry": {"coordinates":[-122.36637500000001,47.627776],"type":"Point"}
}