{
  "type": "Feature",
  "properties": {
    "addr:full":"1730 N Madson St Liberty Lake WA 99019",
    "addr:housenumber":"1730",
    "addr:postcode":"99019",
    "addr:street":"N Madson St",
    "iso:country":"US",
    "sg:address":"1730 N Madson St",
    "sg:city":"Liberty Lake",
    "sg:classifiers":[
        {
            "category":"Manufacturing",
            "subcategory":"Tools & Machinery",
            "type":"Manufacturing & Wholesale Goods"
        }
    ],
    "sg:phone":"+1 509 624 6600",
    "sg:postcode":"99019",
    "sg:province":"WA",
    "sg:tags":[
        "computer",
        "electronic",
        "mfg"
    ],
    "wof:name":"Itronix Manufacturing  LLC",
    "wof:placetype":"venue"
},
  "geometry": {"coordinates":[-117.09460799999999,47.673622],"type":"Point"}
}