{
  "type": "Feature",
  "properties": {
    "addr:full":"1708 E Galer St Seattle WA 98112",
    "addr:housenumber":"1708",
    "addr:postcode":"98112",
    "addr:street":"E Galer St",
    "iso:country":"US",
    "sg:address":"1708 E Galer St",
    "sg:city":"Seattle",
    "sg:classifiers":[
        {
            "category":"Shopping",
            "subcategory":"Jewelry",
            "type":"Retail Goods"
        }
    ],
    "sg:phone":"+1 206 325 6620",
    "sg:postcode":"98112",
    "sg:province":"WA",
    "wof:name":"Professional Jewelry Serv",
    "wof:placetype":"venue"
},
  "geometry": {"coordinates":[-122.309285,47.632391],"type":"Point"}
}