{
  "type": "Feature",
  "properties": {
    "addr:full":"300 Thurston St Wenatchee WA 98801",
    "addr:housenumber":"300",
    "addr:postcode":"98801",
    "addr:street":"Thurston St",
    "iso:country":"US",
    "sg:address":"300 Thurston St",
    "sg:city":"Wenatchee",
    "sg:classifiers":[
        {
            "category":"Farming",
            "subcategory":"Orchard",
            "type":"Manufacturing & Wholesale Goods"
        }
    ],
    "sg:phone":"+1 509 667 1121",
    "sg:postcode":"98801",
    "sg:province":"WA",
    "sg:tags":[
        "fruit",
        "tree"
    ],
    "wof:name":"Cezanne Orchards LLC",
    "wof:placetype":"venue"
},
  "geometry": {"coordinates":[-120.304585,47.421302],"type":"Point"}
}