{
  "type": "Feature",
  "properties": {
    "addr:full":"2104 N Pines Rd Spokane Valley WA 99206",
    "addr:housenumber":"2104",
    "addr:postcode":"99206",
    "addr:street":"N Pines Rd",
    "iso:country":"US",
    "sg:address":"2104 N Pines Rd",
    "sg:city":"Spokane Valley",
    "sg:classifiers":[
        {
            "category":"Bars & Pubs",
            "type":"Food & Drink"
        }
    ],
    "sg:phone":"+1 509 893 9481",
    "sg:postcode":"99206",
    "sg:province":"WA",
    "wof:name":"Matthew's",
    "wof:placetype":"venue"
},
  "geometry": {"coordinates":[-117.239541,47.677367],"type":"Point"}
}