{
  "type": "Feature",
  "properties": {
    "addr:full":"10320 Kelly Rd NE Carnation WA 98014",
    "addr:housenumber":"10320",
    "addr:postcode":"98014",
    "addr:street":"Kelly Rd Ne",
    "iso:country":"US",
    "sg:address":"10320 Kelly Rd NE",
    "sg:city":"Carnation",
    "sg:classifiers":[
        {
            "category":"Autos & Motor Vehicles",
            "subcategory":"Fuel & Gas Station",
            "type":"Retail Goods"
        }
    ],
    "sg:phone":"+1 425 865 4850",
    "sg:postcode":"98014",
    "sg:province":"WA",
    "sg:tags":[
        "station",
        "gasoline"
    ],
    "wof:name":"Sally Shell",
    "wof:placetype":"venue"
},
  "geometry": {"coordinates":[-121.907523,47.688539],"type":"Point"}
}