{
  "type": "Feature",
  "properties": {
    "addr:full":"10357 Stone Ave N Seattle WA 98133",
    "addr:housenumber":"10357",
    "addr:postcode":"98133",
    "addr:street":"Stone Ave N",
    "iso:country":"US",
    "sg:address":"10357 Stone Ave N",
    "sg:city":"Seattle",
    "sg:classifiers":[
        {
            "category":"Community Center",
            "type":"Public Place"
        }
    ],
    "sg:phone":"+1 206 526 1970",
    "sg:postcode":"98133",
    "sg:province":"WA",
    "sg:tags":[
        "medical"
    ],
    "wof:name":"Northgate Blood Donor Center",
    "wof:placetype":"venue"
},
  "geometry": {"coordinates":[-122.34199,47.704234],"type":"Point"}
}