{
  "type": "Feature",
  "properties": {
    "addr:full":"1247 S Jackson St Seattle WA 98144",
    "addr:housenumber":"1247",
    "addr:postcode":"98144",
    "addr:street":"S Jackson St",
    "iso:country":"US",
    "sg:address":"1247 S Jackson St",
    "sg:city":"Seattle",
    "sg:classifiers":[
        {
            "category":"Wholesale",
            "subcategory":"Apparel",
            "type":"Manufacturing & Wholesale Goods"
        }
    ],
    "sg:phone":"+1 206 322 2427",
    "sg:postcode":"98144",
    "sg:province":"WA",
    "sg:tags":[
        "straight",
        "binding"
    ],
    "wof:name":"Bias & Novelty Stitching Co",
    "wof:placetype":"venue"
},
  "geometry": {"coordinates":[-122.314622,47.599128],"type":"Point"}
}