{
  "type": "Feature",
  "properties": {
    "addr:full":"5816 S Marshall Rd Spokane WA 99224",
    "addr:housenumber":"5816",
    "addr:postcode":"99224",
    "addr:street":"S Marshall Rd",
    "iso:country":"US",
    "sg:address":"5816 S Marshall Rd",
    "sg:city":"Spokane",
    "sg:classifiers":[
        {
            "category":"Retail",
            "subcategory":"Auto Repair",
            "type":"Services"
        }
    ],
    "sg:phone":"+1 509 487 6380",
    "sg:postcode":"99224",
    "sg:province":"WA",
    "sg:tags":[
        "general"
    ],
    "wof:name":"Ford Industries",
    "wof:placetype":"venue"
},
  "geometry": {"coordinates":[-117.44558600000001,47.597711],"type":"Point"}
}