{
  "type": "Feature",
  "properties": {
    "addr:full":"300 W Mill Plain Blvd Ste 400 Vancouver WA 98660",
    "addr:housenumber":"300",
    "addr:postcode":"98660",
    "addr:street":"W Mill Plain Blvd Ste 400",
    "iso:country":"US",
    "sg:address":"300 W Mill Plain Blvd Ste 400",
    "sg:city":"Vancouver",
    "sg:classifiers":[
        {
            "category":"Insurance",
            "subcategory":"Hazard Insurance",
            "type":"Services"
        },
        {
            "category":"Insurance",
            "subcategory":"Life Insurance",
            "type":"Services"
        }
    ],
    "sg:phone":"+1 360 750 5946",
    "sg:postcode":"98660",
    "sg:province":"WA",
    "wof:name":"New York Life",
    "wof:placetype":"venue"
},
  "geometry": {"coordinates":[-122.67382000000001,45.63184],"type":"Point"}
}