{
  "type": "Feature",
  "properties": {
    "addr:full":"201 116th Ave NE Bellevue WA 98004",
    "addr:housenumber":"201",
    "addr:postcode":"98004",
    "addr:street":"116Th Ave Ne",
    "iso:country":"US",
    "sg:address":"201 116th Ave NE",
    "sg:city":"Bellevue",
    "sg:classifiers":[
        {
            "category":"Autos & Motor Vehicles",
            "subcategory":"Automobile Sales",
            "type":"Retail Goods"
        }
    ],
    "sg:phone":"+1 425 454 2322",
    "sg:postcode":"98004",
    "sg:province":"WA",
    "sg:tags":[
        "car",
        "dealer"
    ],
    "wof:name":"Defintive Motors",
    "wof:placetype":"venue"
},
  "geometry": {"coordinates":[-122.185591,47.612939],"type":"Point"}
}