{
  "type": "Feature",
  "properties": {
    "addr:full":"1110 S Puget Sound Ave Tacoma WA 98405",
    "addr:housenumber":"1110",
    "addr:postcode":"98405",
    "addr:street":"S Puget Sound Ave",
    "iso:country":"US",
    "sg:address":"1110 S Puget Sound Ave",
    "sg:city":"Tacoma",
    "sg:classifiers":[
        {
            "category":"Social Services",
            "subcategory":"Child Care",
            "type":"Services"
        }
    ],
    "sg:phone":"+1 253 752 1661",
    "sg:postcode":"98405",
    "sg:province":"WA",
    "wof:name":"Joyful Noise Child Care",
    "wof:placetype":"venue"
},
  "geometry": {"coordinates":[-122.48225600000001,47.250109],"type":"Point"}
}