{
  "type": "Feature",
  "properties": {
    "addr:full":"15519 Peacock Hill Ave NW Gig Harbor WA 98332",
    "addr:housenumber":"15519",
    "addr:postcode":"98332",
    "addr:street":"Peacock Hill Ave Nw",
    "iso:country":"US",
    "sg:address":"15519 Peacock Hill Ave NW",
    "sg:city":"Gig Harbor",
    "sg:classifiers":[
        {
            "category":"Manufacturing",
            "subcategory":"Lumber",
            "type":"Manufacturing & Wholesale Goods"
        }
    ],
    "sg:phone":"+1 253 857 7840",
    "sg:postcode":"98332",
    "sg:province":"WA",
    "sg:tags":[
        "company",
        "logging"
    ],
    "wof:name":"Olympic Cascade Cnstr Svcs",
    "wof:placetype":"venue"
},
  "geometry": {"coordinates":[-122.588836,47.400055],"type":"Point"}
}