{
  "type": "Feature",
  "properties": {
    "addr:full":"1207 N 200th St Ste 210 Shoreline WA 98133",
    "addr:housenumber":"1207",
    "addr:postcode":"98133",
    "addr:street":"N 200Th St Ste 210",
    "iso:country":"US",
    "sg:address":"1207 N 200th St Ste 210",
    "sg:city":"Shoreline",
    "sg:classifiers":[
        {
            "category":"Insurance",
            "subcategory":"Insurance Agent",
            "type":"Services"
        },
        {
            "category":"Insurance",
            "subcategory":"Hazard Insurance",
            "type":"Services"
        },
        {
            "category":"Insurance",
            "subcategory":"Title Insurance",
            "type":"Services"
        },
        {
            "category":"Insurance",
            "subcategory":"Life Insurance",
            "type":"Services"
        }
    ],
    "sg:phone":"+1 206 533 2306",
    "sg:postcode":"98133",
    "sg:province":"WA",
    "sg:tags":[
        "auto",
        "homeowner",
        "boat",
        "property",
        "marine",
        "casualty"
    ],
    "wof:name":"Taylor, Eileen - Allstate Insurance Company",
    "wof:placetype":"venue"
},
  "geometry": {"coordinates":[-122.344684,47.774166],"type":"Point"}
}