{
  "type": "Feature",
  "properties": {
    "addr:full":"8414 5th Ave NE Seattle WA 98115",
    "addr:housenumber":"8414",
    "addr:postcode":"98115",
    "addr:street":"5Th Ave Ne",
    "iso:country":"US",
    "sg:address":"8414 5th Ave NE",
    "sg:city":"Seattle",
    "sg:classifiers":[
        {
            "category":"Arts & Performance",
            "subcategory":"Music",
            "type":"Entertainment"
        },
        {
            "category":"Manufacturing",
            "subcategory":"Musical Instruments",
            "type":"Manufacturing & Wholesale Goods"
        }
    ],
    "sg:phone":"+1 206 729 9299",
    "sg:postcode":"98115",
    "sg:province":"WA",
    "sg:tags":[
        "instruments-supplies",
        "accessory"
    ],
    "sg:website":"http://www.metropolitan-music.com",
    "wof:name":"Metropolitan Music",
    "wof:placetype":"venue"
},
  "geometry": {"coordinates":[-122.32298400000001,47.689772],"type":"Point"}
}