{
  "type": "Feature",
  "properties": {
    "addr:full":"2426 32nd Ave W Seattle WA 98199",
    "addr:housenumber":"2426",
    "addr:postcode":"98199",
    "addr:street":"32Nd Ave W",
    "iso:country":"US",
    "sg:address":"2426 32nd Ave W",
    "sg:city":"Seattle",
    "sg:classifiers":[
        {
            "category":"Shopping",
            "subcategory":"Gifts & Souvenirs",
            "type":"Retail Goods"
        },
        {
            "category":"Manufacturing",
            "subcategory":"Jewelry",
            "type":"Manufacturing & Wholesale Goods"
        }
    ],
    "sg:phone":"+1 206 284 5893",
    "sg:postcode":"98199",
    "sg:province":"WA",
    "sg:tags":[
        "shop",
        "novelty"
    ],
    "sg:website":"http://www.porcelaingalleryinc.com",
    "wof:name":"Porcelain Gallery",
    "wof:placetype":"venue"
},
  "geometry": {"coordinates":[-122.39836099999999,47.640483],"type":"Point"}
}