{
  "type": "Feature",
  "properties": {
    "addr:full":"2509 Cedarwood Ave Bellingham WA 98225",
    "addr:housenumber":"2509",
    "addr:postcode":"98225",
    "addr:street":"Cedarwood Ave",
    "iso:country":"US",
    "sg:address":"2509 Cedarwood Ave",
    "sg:city":"Bellingham",
    "sg:classifiers":[
        {
            "category":"Professional",
            "subcategory":"Accounting & Tax Preparation",
            "type":"Services"
        }
    ],
    "sg:phone":"+1 360 734 2172",
    "sg:postcode":"98225",
    "sg:province":"WA",
    "sg:tags":[
        "accountant"
    ],
    "wof:name":"Roy A Lentz Inc",
    "wof:placetype":"venue"
},
  "geometry": {"coordinates":[-122.50287899999999,48.771415],"type":"Point"}
}