{
  "type": "Feature",
  "properties": {
    "addr:full":"4213 W Indian Trail Rd Spokane WA 99208",
    "addr:housenumber":"4213",
    "addr:postcode":"99208",
    "addr:street":"W Indian Trail Rd",
    "iso:country":"US",
    "sg:address":"4213 W Indian Trail Rd",
    "sg:city":"Spokane",
    "sg:classifiers":[
        {
            "category":"Social Services",
            "subcategory":"Retirement Home",
            "type":"Services"
        },
        {
            "category":"Social Services",
            "subcategory":"Adult Care",
            "type":"Services"
        }
    ],
    "sg:phone":"+1 509 326 8617",
    "sg:postcode":"99208",
    "sg:province":"WA",
    "sg:tags":[
        "living",
        "nursing",
        "facility",
        "assisted",
        "convalescent",
        "centers-adult",
        "day"
    ],
    "wof:name":"Home Sweet Home Adult Family Home",
    "wof:placetype":"venue"
},
  "geometry": {"coordinates":[-117.47287300000001,47.727358],"type":"Point"}
}