{
  "type": "Feature",
  "properties": {
    "addr:full":"135 Pacific Ave Bremerton WA 98337",
    "addr:housenumber":"135",
    "addr:postcode":"98337",
    "addr:street":"Pacific Ave",
    "iso:country":"US",
    "sg:address":"135 Pacific Ave",
    "sg:city":"Bremerton",
    "sg:classifiers":[
        {
            "category":"Professional",
            "type":"Services"
        }
    ],
    "sg:phone":"+1 360 479 6169",
    "sg:postcode":"98337",
    "sg:province":"WA",
    "wof:name":"Zapata Melodie",
    "wof:placetype":"venue"
},
  "geometry": {"coordinates":[-122.62697799999999,47.563994],"type":"Point"}
}