{
  "type": "Feature",
  "properties": {
    "addr:full":"4208 Leary Way NW Seattle WA 98107",
    "addr:housenumber":"4208",
    "addr:postcode":"98107",
    "addr:street":"Leary Way Nw",
    "iso:country":"US",
    "sg:address":"4208 Leary Way NW",
    "sg:city":"Seattle",
    "sg:classifiers":[
        {
            "category":"Personal",
            "subcategory":"Hair Removal",
            "type":"Services"
        },
        {
            "category":"Personal",
            "subcategory":"Skin Care",
            "type":"Services"
        }
    ],
    "sg:phone":"+1 206 714 0136",
    "sg:postcode":"98107",
    "sg:province":"WA",
    "sg:website":"www.skincaresupreme.com",
    "wof:name":"Grace Skin Care",
    "wof:placetype":"venue"
},
  "geometry": {"coordinates":[-122.363559,47.658101],"type":"Point"}
}