{
  "type": "Feature",
  "properties": {
    "iso:country":"US",
    "sg:address":"902 Union Ave NE",
    "sg:city":"Renton",
    "sg:classifiers":[
        {
            "category":"Personal",
            "subcategory":"Beauty Salon",
            "type":"Services"
        }
    ],
    "sg:phone":"+1 425 228 6707",
    "sg:postcode":"98059",
    "sg:province":"WA",
    "sg:tags":[
        "shop"
    ],
    "wof:name":"Kari K Jennings",
    "wof:placetype":"venue"
},
  "geometry": {"coordinates":[-122.164394,47.497419],"type":"Point"}
}