{
  "type": "Feature",
  "properties": {
    "addr:full":"2253 N 56th St Seattle WA 98103",
    "addr:housenumber":"2253",
    "addr:postcode":"98103",
    "addr:street":"N 56Th St",
    "iso:country":"US",
    "sg:address":"2253 N 56th St",
    "sg:city":"Seattle",
    "sg:classifiers":[
        {
            "category":"Bars & Pubs",
            "type":"Food & Drink"
        },
        {
            "category":"Restaurant",
            "type":"Food & Drink"
        }
    ],
    "sg:phone":"+1 206 633 5828",
    "sg:postcode":"98103",
    "sg:province":"WA",
    "sg:website":"www.pourhouseseattle.com/",
    "wof:name":"Poor House",
    "wof:placetype":"venue"
},
  "geometry": {"coordinates":[-122.33142599999999,47.668912],"type":"Point"}
}