{
  "type": "Feature",
  "properties": {
    "addr:full":"4603 158th Ave SE Bellevue WA 98006",
    "addr:housenumber":"4603",
    "addr:postcode":"98006",
    "addr:street":"158Th Ave Se",
    "iso:country":"US",
    "sg:address":"4603 158th Ave SE",
    "sg:city":"Bellevue",
    "sg:classifiers":[
        {
            "category":"Real Estate",
            "subcategory":"Real Estate Services",
            "type":"Services"
        }
    ],
    "sg:phone":"+1 425 644 5924",
    "sg:postcode":"98006",
    "sg:province":"WA",
    "sg:tags":[
        "inspection"
    ],
    "wof:name":"Alex Home Inspection",
    "wof:placetype":"venue"
},
  "geometry": {"coordinates":[-122.130985,47.562078],"type":"Point"}
}