{
  "type": "Feature",
  "properties": {
    "addr:full":"632 NW 137th St Seattle WA 98177",
    "addr:housenumber":"632",
    "addr:postcode":"98177",
    "addr:street":"Nw 137Th St",
    "iso:country":"US",
    "sg:address":"632 NW 137th St",
    "sg:city":"Seattle",
    "sg:classifiers":[
        {
            "category":"Professional",
            "subcategory":"Business Services",
            "type":"Services"
        }
    ],
    "sg:phone":"+1 206 367 4527",
    "sg:postcode":"98177",
    "sg:province":"WA",
    "sg:tags":[
        "development",
        "product",
        "designers-industrial",
        "marketing",
        "commercial",
        "design"
    ],
    "wof:name":"Nw Design & Construction, Inc.",
    "wof:placetype":"venue"
},
  "geometry": {"coordinates":[-122.365606,47.72872],"type":"Point"}
}