{
  "type": "Feature",
  "properties": {
    "addr:full":"20300 Highway 99 Lynnwood WA 98036",
    "addr:housenumber":"20300",
    "addr:postcode":"98036",
    "addr:street":"Highway 99",
    "iso:country":"US",
    "sg:address":"20300 Highway 99",
    "sg:city":"Lynnwood",
    "sg:classifiers":[
        {
            "category":"Autos & Motor Vehicles",
            "subcategory":"Automobile Sales",
            "type":"Retail Goods"
        },
        {
            "category":"Banks & Credit Unions",
            "subcategory":"Financial Services",
            "type":"Services"
        }
    ],
    "sg:phone":"+1 425 774 7900",
    "sg:postcode":"98036",
    "sg:province":"WA",
    "sg:tags":[
        "financing",
        "used",
        "leasing",
        "car",
        "loan",
        "new"
    ],
    "sg:website":"http://www.lexusofseattle.com",
    "wof:name":"Lexus of Seattle",
    "wof:placetype":"venue"
},
  "geometry": {"coordinates":[-122.32064200000001,47.814762],"type":"Point"}
}