{
  "type": "Feature",
  "properties": {
    "addr:full":"19725 Orville Rd E Orting WA 98360",
    "addr:housenumber":"19725",
    "addr:postcode":"98360",
    "addr:street":"Orville Rd E",
    "iso:country":"US",
    "sg:address":"19725 Orville Rd E",
    "sg:city":"Orting",
    "sg:classifiers":[
        {
            "category":"Professional",
            "type":"Services"
        }
    ],
    "sg:phone":"+1 360 893 4172",
    "sg:postcode":"98360",
    "sg:province":"WA",
    "sg:tags":[
        "establishment"
    ],
    "wof:name":"Atkinson Guy F Co",
    "wof:placetype":"venue"
},
  "geometry": {"coordinates":[-122.18800299999999,47.077015],"type":"Point"}
}