{
  "type": "Feature",
  "properties": {
    "addr:full":"314 S Pines Rd Spokane Valley WA 99206",
    "addr:housenumber":"314",
    "addr:postcode":"99206",
    "addr:street":"S Pines Rd",
    "iso:country":"US",
    "sg:address":"314 S Pines Rd",
    "sg:city":"Spokane Valley",
    "sg:classifiers":[
        {
            "category":"Recreation",
            "type":"Entertainment"
        }
    ],
    "sg:phone":"+1 509 928 5298",
    "sg:postcode":"99206",
    "sg:province":"WA",
    "sg:tags":[
        "martial",
        "arts",
        "instruction"
    ],
    "wof:name":"Malinak Academy Of Martial Art",
    "wof:placetype":"venue"
},
  "geometry": {"coordinates":[-117.239898,47.653548],"type":"Point"}
}