{
  "type": "Feature",
  "properties": {
    "addr:full":"3216 W Lynn St Seattle WA 98199",
    "addr:housenumber":"3216",
    "addr:postcode":"98199",
    "addr:street":"W Lynn St",
    "iso:country":"US",
    "sg:address":"3216 W Lynn St",
    "sg:city":"Seattle",
    "sg:classifiers":[
        {
            "category":"Personal",
            "subcategory":"Beauty Salon",
            "type":"Services"
        }
    ],
    "sg:phone":"+1 206 285 5533",
    "sg:postcode":"98199",
    "sg:province":"WA",
    "sg:tags":[
        "shop"
    ],
    "wof:name":"Brennen Jenna",
    "wof:placetype":"venue"
},
  "geometry": {"coordinates":[-122.399365,47.639192],"type":"Point"}
}