{
  "type": "Feature",
  "properties": {
    "iso:country":"US",
    "sg:address":"7908 NW 9th Ave",
    "sg:city":"Vancouver",
    "sg:classifiers":[
        {
            "category":"Education",
            "subcategory":"Dance Studio",
            "type":"Public Place"
        }
    ],
    "sg:phone":"+1 360 574 0364",
    "sg:postcode":"98665",
    "sg:province":"WA",
    "wof:name":"William D & Marlen Schell",
    "wof:placetype":"venue"
},
  "geometry": {"coordinates":[-122.679744,45.681281],"type":"Point"}
}