{
  "type": "Feature",
  "properties": {
    "iso:country":"US",
    "sg:address":"29409 39th Ave S",
    "sg:city":"Roy",
    "sg:classifiers":[
        {
            "category":"Building & Trades",
            "subcategory":"Construction",
            "type":"Services"
        }
    ],
    "sg:phone":"+1 253 843 9355",
    "sg:postcode":"98580",
    "sg:province":"WA",
    "sg:tags":[
        "contract",
        "general"
    ],
    "wof:name":"Reich Construction Inc",
    "wof:placetype":"venue"
},
  "geometry": {"coordinates":[-122.482052,46.990545],"type":"Point"}
}