{
  "type": "Feature",
  "properties": {
    "addr:full":"16149 Redmond Way Ste 392 Redmond WA 98052",
    "addr:housenumber":"16149",
    "addr:postcode":"98052",
    "addr:street":"Redmond Way Ste 392",
    "iso:country":"US",
    "sg:address":"16149 Redmond Way Ste 392",
    "sg:city":"Redmond",
    "sg:classifiers":[
        {
            "category":"Professional",
            "type":"Services"
        }
    ],
    "sg:phone":"+1 425 869 9078",
    "sg:postcode":"98052",
    "sg:province":"WA",
    "sg:tags":[
        "caterer"
    ],
    "sg:website":"http://www.ordercatering.com",
    "wof:name":"Catering Company, The",
    "wof:placetype":"venue"
},
  "geometry": {"coordinates":[-122.124841,47.674729],"type":"Point"}
}