{
  "type": "Feature",
  "properties": {
    "addr:full":"5922 Rainier Ave S Seattle WA 98118",
    "addr:housenumber":"5922",
    "addr:postcode":"98118",
    "addr:street":"Rainier Ave S",
    "iso:country":"US",
    "sg:address":"5922 Rainier Ave S",
    "sg:city":"Seattle",
    "sg:classifiers":[
        {
            "category":"Place Of Worship",
            "subcategory":"Church",
            "type":"Public Place"
        },
        {
            "category":"Place Of Worship",
            "type":"Public Place"
        },
        {
            "category":"Organizations",
            "subcategory":"Religious Organization",
            "type":"Services"
        }
    ],
    "sg:phone":"+1 206 725 0827",
    "sg:postcode":"98118",
    "sg:province":"WA",
    "sg:tags":[
        "churches-baptist-general",
        "churches-baptist"
    ],
    "wof:name":"Star Bethel Missionary Baptist",
    "wof:placetype":"venue"
},
  "geometry": {"coordinates":[-122.277098,47.549362],"type":"Point"}
}