{
  "type": "Feature",
  "properties": {
    "addr:full":"1815 Hoyt Ave Everett WA 98201",
    "addr:housenumber":"1815",
    "addr:postcode":"98201",
    "addr:street":"Hoyt Ave",
    "iso:country":"US",
    "sg:address":"1815 Hoyt Ave",
    "sg:city":"Everett",
    "sg:classifiers":[
        {
            "category":"Retail",
            "subcategory":"Laundry & Dry Cleaning",
            "type":"Services"
        }
    ],
    "sg:phone":"+1 425 257 0691",
    "sg:postcode":"98201",
    "sg:province":"WA",
    "sg:tags":[
        "cleaners",
        "rug",
        "carpet"
    ],
    "wof:name":"Affordable Carpet Cleaners",
    "wof:placetype":"venue"
},
  "geometry": {"coordinates":[-122.20961,47.992677],"type":"Point"}
}