{
  "type": "Feature",
  "properties": {
    "addr:full":"530 Northgate Mall Seattle WA 98101",
    "addr:housenumber":"530",
    "addr:postcode":"98101",
    "addr:street":"Northgate Mall",
    "iso:country":"US",
    "sg:address":"530 Northgate Mall",
    "sg:city":"Seattle",
    "sg:classifiers":[
        {
            "category":"Health Services",
            "subcategory":"Optometrist",
            "type":"Services"
        }
    ],
    "sg:phone":"+1 206 364 2273",
    "sg:postcode":"98101",
    "sg:province":"WA",
    "wof:name":"Gander Robert Dr & Associates PC",
    "wof:placetype":"venue"
},
  "geometry": {"coordinates":[-122.32356,47.707385],"type":"Point"}
}