{
  "type": "Feature",
  "properties": {
    "addr:full":"7740 81st Pl SE Mercer Island WA 98040",
    "addr:housenumber":"7740",
    "addr:postcode":"98040",
    "addr:street":"81St Pl Se",
    "iso:country":"US",
    "sg:address":"7740 81st Pl SE",
    "sg:city":"Mercer Island",
    "sg:classifiers":[
        {
            "category":"Real Estate",
            "subcategory":"Real Estate Agent",
            "type":"Services"
        }
    ],
    "sg:phone":"+1 206 856 7576",
    "sg:postcode":"98040",
    "sg:province":"WA",
    "wof:name":"Brazose",
    "wof:placetype":"venue"
},
  "geometry": {"coordinates":[-122.230284,47.532872],"type":"Point"}
}