{
  "type": "Feature",
  "properties": {
    "addr:full":"820 4th St NW Puyallup WA 98371",
    "addr:housenumber":"820",
    "addr:postcode":"98371",
    "addr:street":"4Th St Nw",
    "iso:country":"US",
    "sg:address":"820 4th St NW",
    "sg:city":"Puyallup",
    "sg:classifiers":[
        {
            "category":"Freight",
            "type":"Transportation"
        }
    ],
    "sg:phone":"+1 253 845 8829",
    "sg:postcode":"98371",
    "sg:province":"WA",
    "sg:tags":[
        "mover",
        "interstate",
        "storage",
        "intrastate",
        "trucking"
    ],
    "sg:website":"www.boushmoving.com",
    "wof:name":"Boush Moving & Storage Inc",
    "wof:placetype":"venue"
},
  "geometry": {"coordinates":[-122.298474,47.199033],"type":"Point"}
}