{
  "type": "Feature",
  "properties": {
    "addr:full":"511 N Pine St Ellensburg WA 98926",
    "addr:housenumber":"511",
    "addr:postcode":"98926",
    "addr:street":"N Pine St",
    "iso:country":"US",
    "sg:address":"511 N Pine St",
    "sg:city":"Ellensburg",
    "sg:classifiers":[
        {
            "category":"Manufacturing",
            "subcategory":"Tools & Machinery",
            "type":"Manufacturing & Wholesale Goods"
        }
    ],
    "sg:phone":"+1 509 925 1000",
    "sg:postcode":"98926",
    "sg:province":"WA",
    "sg:tags":[
        "medical",
        "mfg",
        "ophthalmic"
    ],
    "wof:name":"Ellensburg Eye & Contact Lens",
    "wof:placetype":"venue"
},
  "geometry": {"coordinates":[-120.546038,46.997593],"type":"Point"}
}