{
  "type": "Feature",
  "properties": {
    "addr:full":"5315 15th Ave S Seattle WA 98108",
    "addr:housenumber":"5315",
    "addr:postcode":"98108",
    "addr:street":"15Th Ave S",
    "iso:country":"US",
    "sg:address":"5315 15th Ave S",
    "sg:city":"Seattle",
    "sg:classifiers":[
        {
            "category":"Home & Garden",
            "subcategory":"Building Materials",
            "type":"Retail Goods"
        }
    ],
    "sg:phone":"+1 206 767 9518",
    "sg:postcode":"98108",
    "sg:province":"WA",
    "sg:tags":[
        "glass",
        "window",
        "plate"
    ],
    "wof:name":"Glass Tech Windshield Repair",
    "wof:placetype":"venue"
},
  "geometry": {"coordinates":[-122.31355000000001,47.553534],"type":"Point"}
}