{
  "type": "Feature",
  "properties": {
    "addr:full":"787 Maynard Ave S Seattle WA 98104",
    "addr:housenumber":"787",
    "addr:postcode":"98104",
    "addr:street":"Maynard Ave S",
    "iso:country":"US",
    "sg:address":"787 Maynard Ave S",
    "sg:city":"Seattle",
    "sg:classifiers":[
        {
            "category":"Professional",
            "subcategory":"Lawyer & Legal Services",
            "type":"Services"
        }
    ],
    "sg:phone":"+1 206 625 4091",
    "sg:postcode":"98104",
    "sg:province":"WA",
    "sg:tags":[
        "attorney",
        "practice"
    ],
    "wof:name":"Tran, Timothy, Law Offices Of",
    "wof:placetype":"venue"
},
  "geometry": {"coordinates":[-122.32504299999999,47.595942],"type":"Point"}
}