{
  "type": "Feature",
  "properties": {
    "addr:full":"3705 Factoria Blvd SE Bellevue WA 98006",
    "addr:housenumber":"3705",
    "addr:postcode":"98006",
    "addr:street":"Factoria Blvd Se",
    "iso:country":"US",
    "sg:address":"3705 Factoria Blvd SE",
    "sg:city":"Bellevue",
    "sg:classifiers":[
        {
            "category":"Building & Trades",
            "subcategory":"Locksmith",
            "type":"Services"
        }
    ],
    "sg:phone":"+1 425 749 3378",
    "sg:postcode":"98006",
    "sg:province":"WA",
    "sg:tags":[
        "key"
    ],
    "wof:name":"24 Hour A Locksmith",
    "wof:placetype":"venue"
},
  "geometry": {"coordinates":[-122.16973,47.578037],"type":"Point"}
}