{
  "type": "Feature",
  "properties": {
    "addr:full":"14900 Interurban Ave S Ste 203 Tukwila WA 98168",
    "addr:housenumber":"14900",
    "addr:postcode":"98168",
    "addr:street":"Interurban Ave S Ste 203",
    "iso:country":"US",
    "sg:address":"14900 Interurban Ave S Ste 203",
    "sg:city":"Tukwila",
    "sg:classifiers":[
        {
            "category":"Professional",
            "subcategory":"Business Services",
            "type":"Services"
        }
    ],
    "sg:phone":"+1 206 443 1600",
    "sg:postcode":"98168",
    "sg:province":"WA",
    "sg:tags":[
        "import",
        "importer",
        "representative"
    ],
    "wof:name":"C T Takahashi & Co",
    "wof:placetype":"venue"
},
  "geometry": {"coordinates":[-122.252261,47.467785],"type":"Point"}
}