{
  "type": "Feature",
  "properties": {
    "addr:full":"427 Orondo Ave Wenatchee WA 98801",
    "addr:housenumber":"427",
    "addr:postcode":"98801",
    "addr:street":"Orondo Ave",
    "iso:country":"US",
    "sg:address":"427 Orondo Ave",
    "sg:city":"Wenatchee",
    "sg:classifiers":[
        {
            "category":"Banks & Credit Unions",
            "subcategory":"Investment Brokerage",
            "type":"Services"
        }
    ],
    "sg:phone":"+1 509 663 3552",
    "sg:postcode":"98801",
    "sg:province":"WA",
    "wof:name":"M-T Investments",
    "wof:placetype":"venue"
},
  "geometry": {"coordinates":[-120.315431,47.420603],"type":"Point"}
}