{
  "type": "Feature",
  "properties": {
    "addr:full":"4514 W 9th Ave Kennewick WA 99336",
    "addr:housenumber":"4514",
    "addr:postcode":"99336",
    "addr:street":"W 9Th Ave",
    "iso:country":"US",
    "sg:address":"4514 W 9th Ave",
    "sg:city":"Kennewick",
    "sg:classifiers":[
        {
            "category":"Building & Trades",
            "subcategory":"Construction",
            "type":"Services"
        }
    ],
    "sg:phone":"+1 509 544 0696",
    "sg:postcode":"99336",
    "sg:province":"WA",
    "sg:tags":[
        "house"
    ],
    "wof:name":"All Pro Contracting Inc",
    "wof:placetype":"venue"
},
  "geometry": {"coordinates":[-119.182731,46.200985],"type":"Point"}
}