{
  "type": "Feature",
  "properties": {
    "addr:full":"7601 S Tacoma Way Tacoma WA 98409",
    "addr:housenumber":"7601",
    "addr:postcode":"98409",
    "addr:street":"S Tacoma Way",
    "iso:country":"US",
    "sg:address":"7601 S Tacoma Way",
    "sg:city":"Tacoma",
    "sg:classifiers":[
        {
            "category":"Autos & Motor Vehicles",
            "subcategory":"Automobile Sales",
            "type":"Retail Goods"
        }
    ],
    "sg:phone":"+1 253 474 0621",
    "sg:postcode":"98409",
    "sg:province":"WA",
    "sg:tags":[
        "car",
        "dealer"
    ],
    "sg:website":"www.looklarson.com",
    "wof:name":"Robert Larson's Chrysler-Jeep",
    "wof:placetype":"venue"
},
  "geometry": {"coordinates":[-122.483599,47.189524],"type":"Point"}
}