{
  "type": "Feature",
  "properties": {
    "addr:full":"8216 E Baldwin Ave Spokane Valley WA 99212",
    "addr:housenumber":"8216",
    "addr:postcode":"99212",
    "addr:street":"E Baldwin Ave",
    "iso:country":"US",
    "sg:address":"8216 E Baldwin Ave",
    "sg:city":"Spokane Valley",
    "sg:classifiers":[
        {
            "category":"Manufacturing",
            "subcategory":"Furniture",
            "type":"Manufacturing & Wholesale Goods"
        },
        {
            "category":"Home & Garden",
            "subcategory":"Furniture",
            "type":"Retail Goods"
        }
    ],
    "sg:phone":"+1 509 928 1554",
    "sg:postcode":"99212",
    "sg:province":"WA",
    "sg:tags":[
        "mfg",
        "m",
        "cabinet",
        "member",
        "wood",
        "structural"
    ],
    "wof:name":"Gordie's Cabinets",
    "wof:placetype":"venue"
},
  "geometry": {"coordinates":[-117.293689,47.674],"type":"Point"}
}