{
  "type": "Feature",
  "properties": {
    "addr:full":"8221 NE Hazel Dell Ave # 104 Vancouver WA 98665",
    "addr:housenumber":"8221",
    "addr:postcode":"98665",
    "addr:street":"Ne Hazel Dell Ave # 104",
    "iso:country":"US",
    "sg:address":"8221 NE Hazel Dell Ave # 104",
    "sg:city":"Vancouver",
    "sg:classifiers":[
        {
            "category":"Health Services",
            "subcategory":"Chiropractor",
            "type":"Services"
        }
    ],
    "sg:phone":"+1 360 573 0729",
    "sg:postcode":"98665",
    "sg:province":"WA",
    "sg:tags":[
        "chiropractic"
    ],
    "wof:name":"Hagen Chiropractic Clinic",
    "wof:placetype":"venue"
},
  "geometry": {"coordinates":[-122.669245,45.681508],"type":"Point"}
}