{
  "type": "Feature",
  "properties": {
    "iso:country":"US",
    "sg:address":"1622 SW 140th St",
    "sg:city":"Seattle",
    "sg:classifiers":[
        {
            "category":"Building & Trades",
            "subcategory":"Construction",
            "type":"Services"
        }
    ],
    "sg:phone":"+1 206 431 1494",
    "sg:postcode":"98166",
    "sg:province":"WA",
    "sg:tags":[
        "contractor"
    ],
    "wof:name":"Keith Mooney Kitchen Rmdlg",
    "wof:placetype":"venue"
},
  "geometry": {"coordinates":[-122.355408,47.477232],"type":"Point"}
}