{
  "type": "Feature",
  "properties": {
    "addr:full":"11601 Willows Rd NE Redmond WA 98052",
    "addr:housenumber":"11601",
    "addr:postcode":"98052",
    "addr:street":"Willows Rd Ne",
    "iso:country":"US",
    "sg:address":"11601 Willows Rd NE",
    "sg:city":"Redmond",
    "sg:classifiers":[
        {
            "category":"Professional",
            "subcategory":"Computer Services",
            "type":"Services"
        }
    ],
    "sg:phone":"+1 425 882 8838",
    "sg:postcode":"98052",
    "sg:province":"WA",
    "sg:tags":[
        "marketing"
    ],
    "wof:name":"4greatbuyscom",
    "wof:placetype":"venue"
},
  "geometry": {"coordinates":[-122.153828,47.706886],"type":"Point"}
}