{
  "type": "Feature",
  "properties": {
    "addr:full":"615 W Pine St Apt 20 Newport WA 99156",
    "addr:housenumber":"615;20",
    "addr:postcode":"99156",
    "addr:street":"W Pine St Apt",
    "iso:country":"US",
    "sg:address":"615 W Pine St Apt 20",
    "sg:city":"Newport",
    "sg:classifiers":[
        {
            "category":"Real Estate",
            "subcategory":"Real Estate Services",
            "type":"Services"
        },
        {
            "category":"Real Estate",
            "subcategory":"Real Estate Operator",
            "type":"Services"
        }
    ],
    "sg:phone":"+1 509 447 3831",
    "sg:postcode":"99156",
    "sg:province":"WA",
    "sg:tags":[
        "vacancy",
        "apartment",
        "rental",
        "finder",
        "listing"
    ],
    "wof:name":"Silver Pines Apartments",
    "wof:placetype":"venue"
},
  "geometry": {"coordinates":[-117.047149,48.182093],"type":"Point"}
}