{
  "type": "Feature",
  "properties": {
    "addr:full":"1709 Stafford Dr Clarkston WA 99403",
    "addr:housenumber":"1709",
    "addr:postcode":"99403",
    "addr:street":"Stafford Dr",
    "iso:country":"US",
    "sg:address":"1709 Stafford Dr",
    "sg:city":"Clarkston",
    "sg:classifiers":[
        {
            "category":"Social Services",
            "type":"Services"
        }
    ],
    "sg:phone":"+1 509 758 9851",
    "sg:postcode":"99403",
    "sg:province":"WA",
    "wof:name":"Beverly Personal Care",
    "wof:placetype":"venue"
},
  "geometry": {"coordinates":[-117.070728,46.386593],"type":"Point"}
}