{
  "type": "Feature",
  "properties": {
    "addr:full":"4430 John Luhr Rd NE Olympia WA 98516",
    "addr:housenumber":"4430",
    "addr:postcode":"98516",
    "addr:street":"John Luhr Rd Ne",
    "iso:country":"US",
    "sg:address":"4430 John Luhr Rd NE",
    "sg:city":"Olympia",
    "sg:classifiers":[
        {
            "category":"Government",
            "subcategory":"Office",
            "type":"Public Place"
        }
    ],
    "sg:phone":"+1 360 491 6567",
    "sg:postcode":"98516",
    "sg:province":"WA",
    "sg:tags":[
        "growing",
        "consultant",
        "promotional",
        "agricultural",
        "research"
    ],
    "sg:website":"http://www.maurer-group.com",
    "wof:name":"Strawberry Commission",
    "wof:placetype":"venue"
},
  "geometry": {"coordinates":[-122.730925,47.095717],"type":"Point"}
}