{
  "type": "Feature",
  "properties": {
    "addr:full":"14421 Woodinville Redmond Rd NE Woodinville WA 98072",
    "addr:housenumber":"14421",
    "addr:postcode":"98072",
    "addr:street":"Woodinville Redmond Rd Ne",
    "iso:country":"US",
    "sg:address":"14421 Woodinville Redmond Rd NE",
    "sg:city":"Woodinville",
    "sg:classifiers":[
        {
            "category":"Health Services",
            "subcategory":"Doctor",
            "type":"Services"
        }
    ],
    "sg:phone":"+1 425 488 4999",
    "sg:postcode":"98072",
    "sg:province":"WA",
    "sg:tags":[
        "medical"
    ],
    "wof:name":"Richard J Pisani MD",
    "wof:placetype":"venue"
},
  "geometry": {"coordinates":[-122.140744,47.731328],"type":"Point"}
}