{
  "type": "Feature",
  "properties": {
    "addr:full":"3223 NE 125th Street Seattle WA 98125",
    "addr:housenumber":"3223",
    "addr:postcode":"98125",
    "addr:street":"Ne 125Th Street",
    "iso:country":"US",
    "sg:address":"3223 NE 125th Street",
    "sg:city":"Seattle",
    "sg:classifiers":[
        {
            "category":"Building & Trades",
            "subcategory":"Construction",
            "type":"Services"
        }
    ],
    "sg:phone":"+1 206 362 7227",
    "sg:postcode":"98125",
    "sg:province":"WA",
    "sg:tags":[
        "contractor"
    ],
    "wof:name":"Simmons Joseph S Construction",
    "wof:placetype":"venue"
},
  "geometry": {"coordinates":[-122.293271,47.719369],"type":"Point"}
}