{
  "type": "Feature",
  "properties": {
    "addr:full":"1360 N Louisiana St Kennewick WA 99336",
    "addr:housenumber":"1360",
    "addr:postcode":"99336",
    "addr:street":"N Louisiana St",
    "iso:country":"US",
    "sg:address":"1360 N Louisiana St",
    "sg:city":"Kennewick",
    "sg:classifiers":[
        {
            "category":"Restaurant",
            "type":"Food & Drink"
        }
    ],
    "sg:menulink":"http://www.allmenus.com/wa/richland-kennewick/6431-taco-del-mar/menu/",
    "sg:phone":"+1 509 783 8661",
    "sg:postcode":"99336",
    "sg:province":"WA",
    "sg:tags":[
        "mexican"
    ],
    "wof:name":"Taco Del Mar",
    "wof:placetype":"venue"
},
  "geometry": {"coordinates":[-119.233695,46.225281],"type":"Point"}
}