{
  "type": "Feature",
  "properties": {
    "addr:full":"18697 State Hwy 305 Poulsbo WA 98370",
    "addr:housenumber":"18697",
    "addr:postcode":"98370",
    "addr:street":"State Hwy 305",
    "iso:country":"US",
    "sg:address":"18697 State Hwy 305",
    "sg:city":"Poulsbo",
    "sg:classifiers":[
        {
            "category":"Building & Trades",
            "subcategory":"Plumbing",
            "type":"Services"
        }
    ],
    "sg:phone":"+1 360 779 2778",
    "sg:postcode":"98370",
    "sg:province":"WA",
    "sg:tags":[
        "plumbing",
        "contractor"
    ],
    "wof:name":"Swift Plumbing & Heating",
    "wof:placetype":"venue"
},
  "geometry": {"coordinates":[-122.637145,47.733152],"type":"Point"}
}