{
  "type": "Feature",
  "properties": {
    "addr:full":"140 Weel Rd Clallam Bay WA 98326",
    "addr:housenumber":"140",
    "addr:postcode":"98326",
    "addr:street":"Weel Rd",
    "iso:country":"US",
    "sg:address":"140 Weel Rd",
    "sg:city":"Clallam Bay",
    "sg:classifiers":[
        {
            "category":"Real Estate",
            "subcategory":"Real Estate Operator",
            "type":"Services"
        }
    ],
    "sg:phone":"+1 360 963 3131",
    "sg:postcode":"98326",
    "sg:province":"WA",
    "sg:tags":[
        "apartment"
    ],
    "wof:name":"Clallam Bay Apartments",
    "wof:placetype":"venue"
},
  "geometry": {"coordinates":[-124.254261,48.249247],"type":"Point"}
}