{
  "type": "Feature",
  "properties": {
    "addr:full":"9113 State Ave Marysville WA 98270",
    "addr:housenumber":"9113",
    "addr:postcode":"98270",
    "addr:street":"State Ave",
    "iso:country":"US",
    "sg:address":"9113 State Ave",
    "sg:city":"Marysville",
    "sg:classifiers":[
        {
            "category":"Retail",
            "subcategory":"Auto Repair",
            "type":"Services"
        }
    ],
    "sg:phone":"+1 360 657 1930",
    "sg:postcode":"98270",
    "sg:province":"WA",
    "sg:tags":[
        "brake"
    ],
    "wof:name":"Marysville Brake & Exhaust",
    "wof:placetype":"venue"
},
  "geometry": {"coordinates":[-122.175799,48.076378],"type":"Point"}
}