{
  "type": "Feature",
  "properties": {
    "addr:full":"3902 Richey Rd Yakima WA 98902",
    "addr:housenumber":"3902",
    "addr:postcode":"98902",
    "addr:street":"Richey Rd",
    "iso:country":"US",
    "sg:address":"3902 Richey Rd",
    "sg:city":"Yakima",
    "sg:classifiers":[
        {
            "category":"Professional",
            "subcategory":"Accounting & Tax Preparation",
            "type":"Services"
        }
    ],
    "sg:phone":"+1 509 453 0978",
    "sg:postcode":"98902",
    "sg:province":"WA",
    "wof:name":"Joann S Beaulaurier",
    "wof:placetype":"venue"
},
  "geometry": {"coordinates":[-120.562045,46.604618],"type":"Point"}
}