{
  "type": "Feature",
  "properties": {
    "addr:full":"5659 California Ave SW Seattle WA 98136",
    "addr:housenumber":"5659",
    "addr:postcode":"98136",
    "addr:street":"California Ave Sw",
    "iso:country":"US",
    "sg:address":"5659 California Ave SW",
    "sg:city":"Seattle",
    "sg:classifiers":[
        {
            "category":"Building & Trades",
            "subcategory":"Construction",
            "type":"Services"
        }
    ],
    "sg:phone":"+1 206 932 7363",
    "sg:postcode":"98136",
    "sg:province":"WA",
    "sg:tags":[
        "repair",
        "residential",
        "commercial",
        "installation",
        "auto"
    ],
    "wof:name":"Sattelite Auto Glass",
    "wof:placetype":"venue"
},
  "geometry": {"coordinates":[-122.38716100000001,47.550652],"type":"Point"}
}