{
  "type": "Feature",
  "properties": {
    "addr:full":"1011 SW Klickitat Way Seattle WA 98134",
    "addr:housenumber":"1011",
    "addr:postcode":"98134",
    "addr:street":"Sw Klickitat Way",
    "iso:country":"US",
    "sg:address":"1011 SW Klickitat Way",
    "sg:city":"Seattle",
    "sg:classifiers":[
        {
            "category":"Freight",
            "type":"Transportation"
        }
    ],
    "sg:phone":"+1 206 386 7722",
    "sg:postcode":"98134",
    "sg:province":"WA",
    "sg:tags":[
        "cargo",
        "handler",
        "marine"
    ],
    "wof:name":"General Stvodouring Operations",
    "wof:placetype":"venue"
},
  "geometry": {"coordinates":[-122.350182,47.570745],"type":"Point"}
}