{
  "type": "Feature",
  "properties": {
    "addr:full":"11751 19th Ave NE Seattle WA 98125",
    "addr:housenumber":"11751",
    "addr:postcode":"98125",
    "addr:street":"19Th Ave Ne",
    "iso:country":"US",
    "sg:address":"11751 19th Ave NE",
    "sg:city":"Seattle",
    "sg:classifiers":[
        {
            "category":"Professional",
            "type":"Services"
        }
    ],
    "sg:phone":"+1 206 364 4518",
    "sg:postcode":"98125",
    "sg:province":"WA",
    "wof:name":"Elsie A Smith",
    "wof:placetype":"venue"
},
  "geometry": {"coordinates":[-122.308594,47.715446],"type":"Point"}
}