{
  "type": "Feature",
  "properties": {
    "addr:full":"9047 Meridian Ave N Seattle WA 98103",
    "addr:housenumber":"9047",
    "addr:postcode":"98103",
    "addr:street":"Meridian Ave N",
    "iso:country":"US",
    "sg:address":"9047 Meridian Ave N",
    "sg:city":"Seattle",
    "sg:classifiers":[
        {
            "category":"Professional",
            "subcategory":"Management & Consulting",
            "type":"Services"
        }
    ],
    "sg:phone":"+1 206 528 8008",
    "sg:postcode":"98103",
    "sg:province":"WA",
    "wof:name":"Barbara Travers Marketing",
    "wof:placetype":"venue"
},
  "geometry": {"coordinates":[-122.333877,47.69552],"type":"Point"}
}