{
  "type": "Feature",
  "properties": {
    "addr:full":"1420 5th Ave Seattle WA 98101",
    "addr:housenumber":"1420",
    "addr:postcode":"98101",
    "addr:street":"5Th Ave",
    "iso:country":"US",
    "sg:address":"1420 5th Ave",
    "sg:city":"Seattle",
    "sg:classifiers":[
        {
            "category":"Professional",
            "subcategory":"Lawyer & Legal Services",
            "type":"Services"
        }
    ],
    "sg:phone":"+1 206 340 9634",
    "sg:postcode":"98101",
    "sg:province":"WA",
    "sg:tags":[
        "attorney"
    ],
    "wof:name":"Mark C Griffin",
    "wof:placetype":"venue"
},
  "geometry": {"coordinates":[-122.335387,47.610512],"type":"Point"}
}