{
  "type": "Feature",
  "properties": {
    "addr:full":"4 Crest Pl Longview WA 98632",
    "addr:housenumber":"4",
    "addr:postcode":"98632",
    "addr:street":"Crest Pl",
    "iso:country":"US",
    "sg:address":"4 Crest Pl",
    "sg:city":"Longview",
    "sg:classifiers":[
        {
            "category":"Professional",
            "subcategory":"Management & Consulting",
            "type":"Services"
        }
    ],
    "sg:phone":"+1 360 577 6031",
    "sg:postcode":"98632",
    "sg:province":"WA",
    "sg:tags":[
        "business"
    ],
    "wof:name":"J L Tossberg",
    "wof:placetype":"venue"
},
  "geometry": {"coordinates":[-122.940501,46.149427],"type":"Point"}
}