{
  "type": "Feature",
  "properties": {
    "addr:full":"3560 Breckenridge Rd Everson WA 98247",
    "addr:housenumber":"3560",
    "addr:postcode":"98247",
    "addr:street":"Breckenridge Rd",
    "iso:country":"US",
    "sg:address":"3560 Breckenridge Rd",
    "sg:city":"Everson",
    "sg:classifiers":[
        {
            "category":"Professional",
            "subcategory":"Business Services",
            "type":"Services"
        }
    ],
    "sg:phone":"+1 360 966 7414",
    "sg:postcode":"98247",
    "sg:province":"WA",
    "wof:name":"Eagle Enterprise",
    "wof:placetype":"venue"
},
  "geometry": {"coordinates":[-122.302364,48.928619],"type":"Point"}
}