{
  "type": "Feature",
  "properties": {
    "addr:full":"1001 4th Ave Seattle WA 98154",
    "addr:housenumber":"1001",
    "addr:postcode":"98154",
    "addr:street":"4Th Ave",
    "iso:country":"US",
    "sg:address":"1001 4th Ave",
    "sg:city":"Seattle",
    "sg:classifiers":[
        {
            "category":"Restaurant",
            "type":"Food & Drink"
        }
    ],
    "sg:menulink":"http://www.allmenus.com/wa/seattle/20572-blue-water-taco-grill/menu/",
    "sg:phone":"+1 206 264 8950",
    "sg:postcode":"98154",
    "sg:province":"WA",
    "sg:tags":[
        "seafood",
        "american"
    ],
    "wof:name":"Blue Water Taco Grill",
    "wof:placetype":"venue"
},
  "geometry": {"coordinates":[-122.33299700000001,47.606154],"type":"Point"}
}