{
  "type": "Feature",
  "properties": {
    "addr:full":"13218 NE Highway 99 Vancouver WA 98686",
    "addr:housenumber":"13218",
    "addr:postcode":"98686",
    "addr:street":"Ne Highway 99",
    "iso:country":"US",
    "sg:address":"13218 NE Highway 99",
    "sg:city":"Vancouver",
    "sg:classifiers":[
        {
            "category":"Tea Room",
            "subcategory":"None",
            "type":"Food & Drink"
        },
        {
            "category":"Coffee & Tea",
            "type":"Food & Drink"
        }
    ],
    "sg:phone":"+1 360 574 6621",
    "sg:postcode":"98686",
    "sg:province":"WA",
    "wof:name":"Greyhawk Coffee Corp",
    "wof:placetype":"venue"
},
  "geometry": {"coordinates":[-122.65215999999999,45.716633],"type":"Point"}
}