{
  "type": "Feature",
  "properties": {
    "addr:full":"1310 116th Ave NE Ste A Bellevue WA 98004",
    "addr:housenumber":"1310",
    "addr:postcode":"98004",
    "addr:street":"116Th Ave Ne Ste A",
    "iso:country":"US",
    "sg:address":"1310 116th Ave NE Ste A",
    "sg:city":"Bellevue",
    "sg:classifiers":[
        {
            "category":"Health Services",
            "subcategory":"Doctor",
            "type":"Services"
        }
    ],
    "sg:phone":"+1 425 451 8661",
    "sg:postcode":"98004",
    "sg:province":"WA",
    "wof:name":"Sanderson Aysel K MD",
    "wof:placetype":"venue"
},
  "geometry": {"coordinates":[-122.185997,47.623501],"type":"Point"}
}