{
  "type": "Feature",
  "properties": {
    "addr:full":"705 N Tower Ave Centralia WA 98531",
    "addr:housenumber":"705",
    "addr:postcode":"98531",
    "addr:street":"N Tower Ave",
    "iso:country":"US",
    "sg:address":"705 N Tower Ave",
    "sg:city":"Centralia",
    "sg:classifiers":[
        {
            "category":"Restaurant",
            "type":"Food & Drink"
        }
    ],
    "sg:phone":"+1 360 736 5979",
    "sg:postcode":"98531",
    "sg:province":"WA",
    "sg:tags":[
        "eating"
    ],
    "wof:name":"Carnitas Michoacan",
    "wof:placetype":"venue"
},
  "geometry": {"coordinates":[-122.952275,46.723858],"type":"Point"}
}