{
  "type": "Feature",
  "properties": {
    "addr:full":"17403 NE 88th Pl Redmond WA 98052",
    "addr:housenumber":"17403",
    "addr:postcode":"98052",
    "addr:street":"Ne 88Th Pl",
    "iso:country":"US",
    "sg:address":"17403 NE 88th Pl",
    "sg:city":"Redmond",
    "sg:classifiers":[
        {
            "category":"Wholesale",
            "subcategory":"Non-durable Goods",
            "type":"Manufacturing & Wholesale Goods"
        }
    ],
    "sg:phone":"+1 877 769 5328",
    "sg:postcode":"98052",
    "sg:province":"WA",
    "sg:tags":[
        "merchandise-wholesale"
    ],
    "wof:name":"Barjack Trading Company",
    "wof:placetype":"venue"
},
  "geometry": {"coordinates":[-122.10583699999999,47.681593],"type":"Point"}
}