{
  "type": "Feature",
  "properties": {
    "addr:full":"840 NW 10th Ave Camas WA 98607",
    "addr:housenumber":"840",
    "addr:postcode":"98607",
    "addr:street":"Nw 10Th Ave",
    "iso:country":"US",
    "sg:address":"840 NW 10th Ave",
    "sg:city":"Camas",
    "sg:classifiers":[
        {
            "category":"Arts & Performance",
            "subcategory":"Arts Center",
            "type":"Entertainment"
        }
    ],
    "sg:phone":"+1 360 834 4636",
    "sg:postcode":"98607",
    "sg:province":"WA",
    "sg:tags":[
        "performing"
    ],
    "wof:name":"Viruosity Perform Arts",
    "wof:placetype":"venue"
},
  "geometry": {"coordinates":[-122.418263,45.586937],"type":"Point"}
}