{
  "type": "Feature",
  "properties": {
    "addr:full":"14340 NE 21st St Bellevue WA 98007",
    "addr:housenumber":"14340",
    "addr:postcode":"98007",
    "addr:street":"Ne 21St St",
    "iso:country":"US",
    "sg:address":"14340 NE 21st St",
    "sg:city":"Bellevue",
    "sg:classifiers":[
        {
            "category":"Social Services",
            "subcategory":"Child Care",
            "type":"Services"
        },
        {
            "category":"Education",
            "subcategory":"Preschool",
            "type":"Public Place"
        },
        {
            "category":"Education",
            "subcategory":"School",
            "type":"Public Place"
        }
    ],
    "sg:phone":"+1 425 641 5437",
    "sg:postcode":"98007",
    "sg:province":"WA",
    "sg:tags":[
        "high",
        "middle",
        "day",
        "elementary"
    ],
    "sg:website":"www.americaschild.net",
    "wof:name":"Americas Child Montessori",
    "wof:placetype":"venue"
},
  "geometry": {"coordinates":[-122.150002,47.628601],"type":"Point"}
}