{
  "type": "Feature",
  "properties": {
    "addr:full":"230 SW 152nd St Burien WA 98166",
    "addr:housenumber":"230",
    "addr:postcode":"98166",
    "addr:street":"Sw 152Nd St",
    "iso:country":"US",
    "sg:address":"230 SW 152nd St",
    "sg:city":"Burien",
    "sg:classifiers":[
        {
            "category":"Banks & Credit Unions",
            "subcategory":"Bank",
            "type":"Services"
        }
    ],
    "sg:phone":"+1 206 358 2169",
    "sg:postcode":"98166",
    "sg:province":"WA",
    "sg:tags":[
        "national",
        "commercial"
    ],
    "wof:name":"Bank of America",
    "wof:placetype":"venue"
},
  "geometry": {"coordinates":[-122.335172,47.46696],"type":"Point"}
}