{
  "type": "Feature",
  "properties": {
    "addr:full":"2914 SW Avalon Way Ste B Seattle WA 98126",
    "addr:housenumber":"2914",
    "addr:postcode":"98126",
    "addr:street":"Sw Avalon Way Ste B",
    "iso:country":"US",
    "sg:address":"2914 SW Avalon Way Ste B",
    "sg:city":"Seattle",
    "sg:classifiers":[
        {
            "category":"Manufacturing",
            "subcategory":"Glass & Minerals",
            "type":"Manufacturing & Wholesale Goods"
        },
        {
            "category":"Manufacturing",
            "subcategory":"Building Materials",
            "type":"Manufacturing & Wholesale Goods"
        }
    ],
    "sg:phone":"+1 206 937 6369",
    "sg:postcode":"98126",
    "sg:province":"WA",
    "sg:tags":[
        "plate",
        "repair",
        "glazier",
        "glass-wholesale",
        "window",
        "replacement",
        "manufacturer"
    ],
    "wof:name":"Avalon Glass Works",
    "wof:placetype":"venue"
},
  "geometry": {"coordinates":[-122.370693,47.570752],"type":"Point"}
}