{
  "type": "Feature",
  "properties": {
    "addr:full":"5618 Marine View Dr Tacoma WA 98422",
    "addr:housenumber":"5618",
    "addr:postcode":"98422",
    "addr:street":"Marine View Dr",
    "iso:country":"US",
    "sg:address":"5618 Marine View Dr",
    "sg:city":"Tacoma",
    "sg:classifiers":[
        {
            "category":"Recreation",
            "subcategory":"Marina",
            "type":"Entertainment"
        }
    ],
    "sg:phone":"+1 253 383 5321",
    "sg:postcode":"98422",
    "sg:province":"WA",
    "wof:name":"Tyee Marina",
    "wof:placetype":"venue"
},
  "geometry": {"coordinates":[-122.416134,47.295923],"type":"Point"}
}