{
  "type": "Feature",
  "properties": {
    "addr:full":"9525 SE Cornell Rd Port Orchard WA 98366",
    "addr:housenumber":"9525",
    "addr:postcode":"98366",
    "addr:street":"Se Cornell Rd",
    "iso:country":"US",
    "sg:address":"9525 SE Cornell Rd",
    "sg:city":"Port Orchard",
    "sg:classifiers":[
        {
            "category":"Building & Trades",
            "subcategory":"Construction",
            "type":"Services"
        }
    ],
    "sg:phone":"+1 360 769 8216",
    "sg:postcode":"98366",
    "sg:province":"WA",
    "sg:tags":[
        "hanging",
        "contractor"
    ],
    "wof:name":"C H3 Painting",
    "wof:placetype":"venue"
},
  "geometry": {"coordinates":[-122.521877,47.523579],"type":"Point"}
}