{
  "type": "Feature",
  "properties": {
    "addr:full":"11815 Mukilteo Speedway Mukilteo WA 98275",
    "addr:housenumber":"11815",
    "addr:postcode":"98275",
    "addr:street":"Mukilteo Speedway",
    "iso:country":"US",
    "sg:address":"11815 Mukilteo Speedway",
    "sg:city":"Mukilteo",
    "sg:phone":"+1 425 347 0810",
    "sg:postcode":"98275",
    "sg:province":"WA",
    "sg:website":"http://mukilteoveterinaryhospital.vetsuite.com",
    "wof:name":"Mukilteo Veterinary Hospital - John Crockett DVM",
    "wof:placetype":"venue"
},
  "geometry": {"coordinates":[-122.28567200000001,47.891003],"type":"Point"}
}