{
  "type": "Feature",
  "properties": {
    "addr:full":"4900 Rainier Ave S Seattle WA 98118",
    "addr:housenumber":"4900",
    "addr:postcode":"98118",
    "addr:street":"Rainier Ave S",
    "iso:country":"US",
    "sg:address":"4900 Rainier Ave S",
    "sg:city":"Seattle",
    "sg:classifiers":[
        {
            "category":"Local Transit",
            "type":"Transportation"
        }
    ],
    "sg:phone":"+1 206 689 4994",
    "sg:postcode":"98118",
    "sg:province":"WA",
    "sg:tags":[
        "public"
    ],
    "wof:name":"Sound Transit",
    "wof:placetype":"venue"
},
  "geometry": {"coordinates":[-122.285022,47.557826],"type":"Point"}
}