{
  "type": "Feature",
  "properties": {
    "addr:full":"4002 S M St Tacoma WA 98418",
    "addr:housenumber":"4002",
    "addr:postcode":"98418",
    "addr:street":"S M St",
    "iso:country":"US",
    "sg:address":"4002 S M St",
    "sg:city":"Tacoma",
    "sg:classifiers":[
        {
            "category":"Health Services",
            "subcategory":"Doctor",
            "type":"Services"
        }
    ],
    "sg:phone":"+1 253 473 2166",
    "sg:postcode":"98418",
    "sg:province":"WA",
    "sg:tags":[
        "dentist"
    ],
    "wof:name":"Leonard E Estes DDS",
    "wof:placetype":"venue"
},
  "geometry": {"coordinates":[-122.450872,47.220036],"type":"Point"}
}