{
  "type": "Feature",
  "properties": {
    "addr:full":"502 N 70th St Seattle WA 98103",
    "addr:housenumber":"502",
    "addr:postcode":"98103",
    "addr:street":"N 70Th St",
    "iso:country":"US",
    "sg:address":"502 N 70th St",
    "sg:city":"Seattle",
    "sg:classifiers":[
        {
            "category":"Professional",
            "type":"Services"
        }
    ],
    "sg:phone":"+1 206 789 2500",
    "sg:postcode":"98103",
    "sg:province":"WA",
    "wof:name":"James Briggs",
    "wof:placetype":"venue"
},
  "geometry": {"coordinates":[-122.349897,47.679676],"type":"Point"}
}