{
  "type": "Feature",
  "properties": {
    "addr:full":"6604 S Cerda Rd Kennewick WA 99338",
    "addr:housenumber":"6604",
    "addr:postcode":"99338",
    "addr:street":"S Cerda Rd",
    "iso:country":"US",
    "sg:address":"6604 S Cerda Rd",
    "sg:city":"Kennewick",
    "sg:classifiers":[
        {
            "category":"Retail",
            "subcategory":"Animal Services",
            "type":"Services"
        }
    ],
    "sg:phone":"+1 509 627 1537",
    "sg:postcode":"99338",
    "sg:province":"WA",
    "wof:name":"Vinnecour Ardis",
    "wof:placetype":"venue"
},
  "geometry": {"coordinates":[-119.28428700000001,46.201733],"type":"Point"}
}