{
  "type": "Feature",
  "properties": {
    "addr:full":"22 Camp Creek Rd Montesano WA 98563",
    "addr:housenumber":"22",
    "addr:postcode":"98563",
    "addr:street":"Camp Creek Rd",
    "iso:country":"US",
    "sg:address":"22 Camp Creek Rd",
    "sg:city":"Montesano",
    "sg:classifiers":[
        {
            "category":"Professional",
            "subcategory":"Management & Consulting",
            "type":"Services"
        }
    ],
    "sg:phone":"+1 360 249 4402",
    "sg:postcode":"98563",
    "sg:province":"WA",
    "sg:tags":[
        "business"
    ],
    "wof:name":"Linda Caldwell",
    "wof:placetype":"venue"
},
  "geometry": {"coordinates":[-123.580483,46.987717],"type":"Point"}
}