{
  "type": "Feature",
  "properties": {
    "addr:full":"6920 Roosevelt Way NE Seattle WA 98115",
    "addr:housenumber":"6920",
    "addr:postcode":"98115",
    "addr:street":"Roosevelt Way Ne",
    "iso:country":"US",
    "sg:address":"6920 Roosevelt Way NE",
    "sg:city":"Seattle",
    "sg:classifiers":[
        {
            "category":"Building & Trades",
            "subcategory":"Cleaning & Sanitation",
            "type":"Services"
        }
    ],
    "sg:phone":"+1 206 527 1134",
    "sg:postcode":"98115",
    "sg:province":"WA",
    "sg:tags":[
        "window"
    ],
    "wof:name":"Aurora Window Cleaning Service",
    "wof:placetype":"venue"
},
  "geometry": {"coordinates":[-122.317427,47.678894],"type":"Point"}
}