{
  "type": "Feature",
  "properties": {
    "addr:full":"2230 8th Ave Seattle WA 98121",
    "addr:housenumber":"2230",
    "addr:postcode":"98121",
    "addr:street":"8Th Ave",
    "iso:country":"US",
    "sg:address":"2230 8th Ave",
    "sg:city":"Seattle",
    "sg:classifiers":[
        {
            "category":"Sports & Exercise",
            "subcategory":"Gym",
            "type":"Entertainment"
        }
    ],
    "sg:phone":"+1 206 682 2949",
    "sg:postcode":"98121",
    "sg:province":"WA",
    "sg:tags":[
        "trainer",
        "yoga"
    ],
    "sg:website":"www.breathehotyoga.com",
    "wof:name":"Breathe Hot Yoga",
    "wof:placetype":"venue"
},
  "geometry": {"coordinates":[-122.34003800000001,47.618118],"type":"Point"}
}