{
  "type": "Feature",
  "properties": {
    "addr:full":"29630 Green River Rd SE Auburn WA 98092",
    "addr:housenumber":"29630",
    "addr:postcode":"98092",
    "addr:street":"Green River Rd Se",
    "iso:country":"US",
    "sg:address":"29630 Green River Rd SE",
    "sg:city":"Auburn",
    "sg:classifiers":[
        {
            "category":"Sports & Exercise",
            "subcategory":"Golf",
            "type":"Entertainment"
        }
    ],
    "sg:phone":"+1 253 833 2350",
    "sg:postcode":"98092",
    "sg:province":"WA",
    "sg:tags":[
        "course",
        "executive",
        "public"
    ],
    "wof:name":"Auburn Golf Course",
    "wof:placetype":"venue"
},
  "geometry": {"coordinates":[-122.21086200000001,47.329934],"type":"Point"}
}