{
  "type": "Feature",
  "properties": {
    "addr:full":"533 N Islandcrest Dr Stanwood WA 98292",
    "addr:housenumber":"533",
    "addr:postcode":"98292",
    "addr:street":"N Islandcrest Dr",
    "iso:country":"US",
    "sg:address":"533 N Islandcrest Dr",
    "sg:city":"Stanwood",
    "sg:classifiers":[
        {
            "category":"Retail",
            "subcategory":"Auto Repair",
            "type":"Services"
        }
    ],
    "sg:phone":"+1 360 387 4206",
    "sg:postcode":"98292",
    "sg:province":"WA",
    "sg:tags":[
        "body"
    ],
    "wof:name":"D & R Upholstery",
    "wof:placetype":"venue"
},
  "geometry": {"coordinates":[-122.496844,48.230559],"type":"Point"}
}