{
  "type": "Feature",
  "properties": {
    "addr:full":"306 E Main St Dayton WA 99328",
    "addr:housenumber":"306",
    "addr:postcode":"99328",
    "addr:street":"E Main St",
    "iso:country":"US",
    "sg:address":"306 E Main St",
    "sg:city":"Dayton",
    "sg:classifiers":[
        {
            "category":"Banks & Credit Unions",
            "subcategory":"Bank",
            "type":"Services"
        }
    ],
    "sg:phone":"+1 509 382 4771",
    "sg:postcode":"99328",
    "sg:province":"WA",
    "sg:tags":[
        "national",
        "commercial"
    ],
    "wof:name":"Bank Of America",
    "wof:placetype":"venue"
},
  "geometry": {"coordinates":[-117.978612,46.320514],"type":"Point"}
}