{
  "type": "Feature",
  "properties": {
    "addr:full":"191 Suzanna Dr Selah WA 98942",
    "addr:housenumber":"191",
    "addr:postcode":"98942",
    "addr:street":"Suzanna Dr",
    "iso:country":"US",
    "sg:address":"191 Suzanna Dr",
    "sg:city":"Selah",
    "sg:classifiers":[
        {
            "category":"Retail",
            "subcategory":"Laundry & Dry Cleaning",
            "type":"Services"
        }
    ],
    "sg:phone":"+1 509 457 4585",
    "sg:postcode":"98942",
    "sg:province":"WA",
    "sg:tags":[
        "chimney"
    ],
    "wof:name":"North West Pressure Wash",
    "wof:placetype":"venue"
},
  "geometry": {"coordinates":[-120.668212,46.753838],"type":"Point"}
}