{
  "type": "Feature",
  "properties": {
    "addr:full":"204 4th St Cheney WA 99004",
    "addr:housenumber":"204",
    "addr:postcode":"99004",
    "addr:street":"4Th St",
    "iso:country":"US",
    "sg:address":"204 4th St",
    "sg:city":"Cheney",
    "sg:classifiers":[
        {
            "category":"Social Services",
            "subcategory":"Child Care",
            "type":"Services"
        }
    ],
    "sg:phone":"+1 509 235 2655",
    "sg:postcode":"99004",
    "sg:province":"WA",
    "sg:tags":[
        "kindergarten",
        "academic",
        "school"
    ],
    "wof:name":"University Preschool",
    "wof:placetype":"venue"
},
  "geometry": {"coordinates":[-117.579403,47.487673],"type":"Point"}
}