{
  "type": "Feature",
  "properties": {
    "addr:full":"2128 Queen Anne Ave N Seattle WA 98109",
    "addr:housenumber":"2128",
    "addr:postcode":"98109",
    "addr:street":"Queen Anne Ave N",
    "iso:country":"US",
    "sg:address":"2128 Queen Anne Ave N",
    "sg:city":"Seattle",
    "sg:classifiers":[
        {
            "category":"Coffee & Tea",
            "type":"Food & Drink"
        }
    ],
    "sg:phone":"+1 206 282 7422",
    "sg:postcode":"98109",
    "sg:province":"WA",
    "wof:name":"Tully's Coffee Corporation",
    "wof:placetype":"venue"
},
  "geometry": {"coordinates":[-122.35700199999999,47.637501],"type":"Point"}
}