{
  "type": "Feature",
  "properties": {
    "addr:full":"1819 Sumner Ave Aberdeen WA 98520",
    "addr:housenumber":"1819",
    "addr:postcode":"98520",
    "addr:street":"Sumner Ave",
    "iso:country":"US",
    "sg:address":"1819 Sumner Ave",
    "sg:city":"Aberdeen",
    "sg:classifiers":[
        {
            "category":"Health Services",
            "subcategory":"Doctor",
            "type":"Services"
        }
    ],
    "sg:phone":"+1 360 538 1463",
    "sg:postcode":"98520",
    "sg:province":"WA",
    "sg:tags":[
        "dentist"
    ],
    "wof:name":"Aberdeen Dental Clinic",
    "wof:placetype":"venue"
},
  "geometry": {"coordinates":[-123.837774,46.975947],"type":"Point"}
}