{
  "type": "Feature",
  "properties": {
    "addr:full":"133 Pontius Ave N Apt 308 Seattle WA 98109",
    "addr:housenumber":"133;308",
    "addr:postcode":"98109",
    "addr:street":"Pontius Ave N Apt",
    "iso:country":"US",
    "sg:address":"133 Pontius Ave N Apt 308",
    "sg:city":"Seattle",
    "sg:classifiers":[
        {
            "category":"Professional",
            "subcategory":"Computer Services",
            "type":"Services"
        }
    ],
    "sg:phone":"+1 206 467 3194",
    "sg:postcode":"98109",
    "sg:province":"WA",
    "sg:tags":[
        "graphic"
    ],
    "sg:website":"http://www.infobanc.net",
    "wof:name":"Infobanc.Net",
    "wof:placetype":"venue"
},
  "geometry": {"coordinates":[-122.332232,47.618889],"type":"Point"}
}