{
  "type": "Feature",
  "properties": {
    "addr:full":"31811 Pacific Hwy S Federal Way WA 98003",
    "addr:housenumber":"31811",
    "addr:postcode":"98003",
    "addr:street":"Pacific Hwy S Federal Way",
    "iso:country":"US",
    "sg:address":"31811 Pacific Hwy S",
    "sg:city":"Federal Way",
    "sg:classifiers":[
        {
            "category":"Shopping",
            "subcategory":"Stationery & Office Supplies",
            "type":"Retail Goods"
        }
    ],
    "sg:phone":"+1 253 839 4321",
    "sg:postcode":"98003",
    "sg:province":"WA",
    "wof:name":"OfficeMax",
    "wof:placetype":"venue"
},
  "geometry": {"coordinates":[-122.313456,47.317389],"type":"Point"}
}