{
  "type": "Feature",
  "properties": {
    "addr:full":"4043 145th Ave NE Bellevue WA 98007",
    "addr:housenumber":"4043",
    "addr:postcode":"98007",
    "addr:street":"145Th Ave Ne",
    "iso:country":"US",
    "sg:address":"4043 145th Ave NE",
    "sg:city":"Bellevue",
    "sg:classifiers":[
        {
            "category":"Professional",
            "type":"Services"
        }
    ],
    "sg:phone":"+1 425 885 1494",
    "sg:postcode":"98007",
    "sg:province":"WA",
    "wof:name":"Peter N Stadelman",
    "wof:placetype":"venue"
},
  "geometry": {"coordinates":[-122.14790499999999,47.647574],"type":"Point"}
}