{
  "type": "Feature",
  "properties": {
    "addr:full":"7000 Cleopatra Pl NW Seattle WA 98117",
    "addr:housenumber":"7000",
    "addr:postcode":"98117",
    "addr:street":"Cleopatra Pl Nw",
    "iso:country":"US",
    "sg:address":"7000 Cleopatra Pl NW",
    "sg:city":"Seattle",
    "sg:classifiers":[
        {
            "category":"Retail",
            "subcategory":"Portrait Studio",
            "type":"Services"
        }
    ],
    "sg:phone":"+1 206 706 1785",
    "sg:postcode":"98117",
    "sg:province":"WA",
    "sg:tags":[
        "photo"
    ],
    "wof:name":"Suna Gurol Photography",
    "wof:placetype":"venue"
},
  "geometry": {"coordinates":[-122.365488,47.68178],"type":"Point"}
}