{
  "type": "Feature",
  "properties": {
    "addr:full":"4541 Taylor Ave NE Bainbridge Island WA 98110",
    "addr:housenumber":"4541",
    "addr:postcode":"98110",
    "addr:street":"Taylor Ave Ne",
    "iso:country":"US",
    "sg:address":"4541 Taylor Ave NE",
    "sg:city":"Bainbridge Island",
    "sg:classifiers":[
        {
            "category":"Professional",
            "subcategory":"Advertising",
            "type":"Services"
        }
    ],
    "sg:phone":"+1 206 842 5308",
    "sg:postcode":"98110",
    "sg:province":"WA",
    "sg:tags":[
        "agency"
    ],
    "wof:name":"Van Slyke Graphics",
    "wof:placetype":"venue"
},
  "geometry": {"coordinates":[-122.51307199999999,47.605061],"type":"Point"}
}