{
  "type": "Feature",
  "properties": {
    "iso:country":"US",
    "sg:address":"7765 Nahahum Canyon Rd",
    "sg:city":"Cashmere",
    "sg:classifiers":[
        {
            "category":"Manufacturing",
            "subcategory":"Tools & Machinery",
            "type":"Manufacturing & Wholesale Goods"
        }
    ],
    "sg:phone":"+1 509 782 1539",
    "sg:postcode":"98815",
    "sg:province":"WA",
    "sg:tags":[
        "drilling",
        "drill",
        "mfg"
    ],
    "wof:name":"Pro Tech Upholstery & Design",
    "wof:placetype":"venue"
},
  "geometry": {"coordinates":[-120.433144,47.558729],"type":"Point"}
}