{
  "type": "Feature",
  "properties": {
    "addr:full":"1195 Hillandale Dr E Port Orchard WA 98366",
    "addr:housenumber":"1195",
    "addr:postcode":"98366",
    "addr:street":"Hillandale Dr E",
    "iso:country":"US",
    "sg:address":"1195 Hillandale Dr E",
    "sg:city":"Port Orchard",
    "sg:classifiers":[
        {
            "category":"Building & Trades",
            "subcategory":"Construction",
            "type":"Services"
        }
    ],
    "sg:phone":"+1 360 769 2584",
    "sg:postcode":"98366",
    "sg:province":"WA",
    "sg:tags":[
        "general",
        "contractor"
    ],
    "wof:name":"Puget Sound Home Services",
    "wof:placetype":"venue"
},
  "geometry": {"coordinates":[-122.582067,47.541899],"type":"Point"}
}