{
  "type": "Feature",
  "properties": {
    "addr:full":"145 Wheeler St Leavenworth WA 98826",
    "addr:housenumber":"145",
    "addr:postcode":"98826",
    "addr:street":"Wheeler St",
    "iso:country":"US",
    "sg:address":"145 Wheeler St",
    "sg:city":"Leavenworth",
    "sg:classifiers":[
        {
            "category":"Organizations",
            "subcategory":"Religious Organization",
            "type":"Services"
        }
    ],
    "sg:phone":"+1 509 548 5051",
    "sg:postcode":"98826",
    "sg:province":"WA",
    "sg:tags":[
        "church"
    ],
    "wof:name":"Our Lady Of The Snows Parish",
    "wof:placetype":"venue"
},
  "geometry": {"coordinates":[-120.670737,47.597922],"type":"Point"}
}