{
  "type": "Feature",
  "properties": {
    "addr:full":"17905 36th Ave W Lynnwood WA 98037",
    "addr:housenumber":"17905",
    "addr:postcode":"98037",
    "addr:street":"36Th Ave W",
    "iso:country":"US",
    "sg:address":"17905 36th Ave W",
    "sg:city":"Lynnwood",
    "sg:classifiers":[
        {
            "category":"Social Services",
            "subcategory":"Child Care",
            "type":"Services"
        }
    ],
    "sg:phone":"+1 425 787 9869",
    "sg:postcode":"98037",
    "sg:province":"WA",
    "sg:tags":[
        "day"
    ],
    "wof:name":"Play TA Learn",
    "wof:placetype":"venue"
},
  "geometry": {"coordinates":[-122.281831,47.835861],"type":"Point"}
}