{
  "type": "Feature",
  "properties": {
    "addr:full":"602 N 105th St Seattle WA 98133",
    "addr:housenumber":"602",
    "addr:postcode":"98133",
    "addr:street":"N 105Th St",
    "iso:country":"US",
    "sg:address":"602 N 105th St",
    "sg:city":"Seattle",
    "sg:classifiers":[
        {
            "category":"Bars & Pubs",
            "subcategory":"Dive Bar",
            "type":"Food & Drink"
        }
    ],
    "sg:phone":"+1 206 789 9005",
    "sg:postcode":"98133",
    "sg:province":"WA",
    "wof:name":"Van's 105 Tavern",
    "wof:placetype":"venue"
},
  "geometry": {"coordinates":[-122.350998,47.704899],"type":"Point"}
}