{
  "type": "Feature",
  "properties": {
    "addr:full":"9569 NE Torvanger Rd Bainbridge Island WA 98110",
    "addr:housenumber":"9569",
    "addr:postcode":"98110",
    "addr:street":"Ne Torvanger Rd",
    "iso:country":"US",
    "sg:address":"9569 NE Torvanger Rd",
    "sg:city":"Bainbridge Island",
    "sg:classifiers":[
        {
            "category":"Professional",
            "subcategory":"Art Services",
            "type":"Services"
        }
    ],
    "sg:phone":"+1 206 842 6499",
    "sg:postcode":"98110",
    "sg:province":"WA",
    "sg:tags":[
        "commercial",
        "design",
        "business"
    ],
    "wof:name":"CC Michel Design",
    "wof:placetype":"venue"
},
  "geometry": {"coordinates":[-122.513445,47.690061],"type":"Point"}
}