{
  "type": "Feature",
  "properties": {
    "addr:full":"Columbia Tower 701 5th Avenue, Suite 3440 Seattle WA 98104",
    "addr:housenumber":"701",
    "addr:postcode":"98104",
    "addr:street":"5Th Avenue Suite 3440",
    "iso:country":"US",
    "sg:address":"Columbia Tower 701 5th Avenue, Suite 3440",
    "sg:city":"Seattle",
    "sg:classifiers":[
        {
            "category":"Professional",
            "subcategory":"Business Services",
            "type":"Services"
        }
    ],
    "sg:phone":"+1 404 869 2500",
    "sg:postcode":"98104",
    "sg:province":"WA",
    "sg:tags":[
        "unified-communications",
        "hosted-unfied-communications",
        "unified-communications-as-a-service",
        "ucaas",
        "hosted-voip",
        "voip",
        "telecommunications",
        "telephony",
        "microsoft-ocs"
    ],
    "sg:website":"http://www.cypresscom.net",
    "wof:name":"Cypress Communications",
    "wof:placetype":"venue"
},
  "geometry": {"coordinates":[-122.328536,47.602982],"type":"Point"}
}