{
  "type": "Feature",
  "properties": {
    "addr:full":"18924 SE 116th Pl Issaquah WA 98027",
    "addr:postcode":"18924;98027",
    "addr:street":"Se 116Th Pl",
    "iso:country":"US",
    "sg:address":"18924 SE 116th Pl",
    "sg:city":"Issaquah",
    "sg:classifiers":[
        {
            "category":"Wholesale",
            "subcategory":"Home Furnishings",
            "type":"Manufacturing & Wholesale Goods"
        }
    ],
    "sg:phone":"+1 425 271 2258",
    "sg:postcode":"98027",
    "sg:province":"WA",
    "wof:name":"Vertech Inc",
    "wof:placetype":"venue"
},
  "geometry": {"coordinates":[-122.086037,47.497961],"type":"Point"}
}