{
  "type": "Feature",
  "properties": {
    "addr:full":"720 N Medcalf Ln Montesano WA 98563",
    "addr:housenumber":"720",
    "addr:postcode":"98563",
    "addr:street":"N Medcalf Ln",
    "iso:country":"US",
    "sg:address":"720 N Medcalf Ln",
    "sg:city":"Montesano",
    "sg:classifiers":[
        {
            "category":"Restaurant",
            "type":"Food & Drink"
        }
    ],
    "sg:phone":"+1 360 249 4980",
    "sg:postcode":"98563",
    "sg:province":"WA",
    "sg:tags":[
        "pizza"
    ],
    "wof:name":"Grabba Pizza & Sandwich Shop",
    "wof:placetype":"venue"
},
  "geometry": {"coordinates":[-123.58586,46.987164],"type":"Point"}
}