{
  "type": "Feature",
  "properties": {
    "addr:full":"811 E Wiser Lake Rd Lynden WA 98264",
    "addr:housenumber":"811",
    "addr:postcode":"98264",
    "addr:street":"E Wiser Lake Rd",
    "iso:country":"US",
    "sg:address":"811 E Wiser Lake Rd",
    "sg:city":"Lynden",
    "sg:classifiers":[
        {
            "category":"Personal",
            "subcategory":"Beauty Salon",
            "type":"Services"
        }
    ],
    "sg:phone":"+1 360 354 3528",
    "sg:postcode":"98264",
    "sg:province":"WA",
    "sg:tags":[
        "shop"
    ],
    "wof:name":"New Hairizon",
    "wof:placetype":"venue"
},
  "geometry": {"coordinates":[-122.445714,48.909891],"type":"Point"}
}