{
  "type": "Feature",
  "properties": {
    "addr:full":"853 SW 174th St Seattle WA 98166",
    "addr:housenumber":"853",
    "addr:postcode":"98166",
    "addr:street":"Sw 174Th St",
    "iso:country":"US",
    "sg:address":"853 SW 174th St",
    "sg:city":"Seattle",
    "sg:classifiers":[
        {
            "category":"Shopping",
            "subcategory":"Music",
            "type":"Retail Goods"
        }
    ],
    "sg:phone":"+1 206 433 6312",
    "sg:postcode":"98166",
    "sg:province":"WA",
    "wof:name":"Stubby Records",
    "wof:placetype":"venue"
},
  "geometry": {"coordinates":[-122.345078,47.446365],"type":"Point"}
}