{
  "type": "Feature",
  "properties": {
    "iso:country":"US",
    "sg:address":"221 S 63rd Ave",
    "sg:city":"Yakima",
    "sg:classifiers":[
        {
            "category":"Building & Trades",
            "subcategory":"Landscaping Services",
            "type":"Services"
        }
    ],
    "sg:phone":"+1 509 966 7524",
    "sg:postcode":"98908",
    "sg:province":"WA",
    "sg:tags":[
        "designer",
        "landscape"
    ],
    "wof:name":"JSM Landscape Architecture",
    "wof:placetype":"venue"
},
  "geometry": {"coordinates":[-120.59217,46.595032],"type":"Point"}
}