{
  "type": "Feature",
  "properties": {
    "iso:country":"US",
    "sg:address":"2401 S Meridian",
    "sg:city":"Puyallup",
    "sg:classifiers":[
        {
            "category":"Health Services",
            "subcategory":"Chiropractor",
            "type":"Services"
        }
    ],
    "sg:phone":"+1 253 841 6482",
    "sg:postcode":"98373",
    "sg:province":"WA",
    "wof:name":"Willows Chiropractic Clinic",
    "wof:placetype":"venue"
},
  "geometry": {"coordinates":[-122.293378,47.168778],"type":"Point"}
}