{
  "type": "Feature",
  "properties": {
    "addr:full":"13624 Ambaum Blvd SW Burien WA 98166",
    "addr:housenumber":"13624",
    "addr:postcode":"98166",
    "addr:street":"Ambaum Blvd Sw",
    "iso:country":"US",
    "sg:address":"13624 Ambaum Blvd SW",
    "sg:city":"Burien",
    "sg:classifiers":[
        {
            "category":"Retail",
            "subcategory":"Auto Repair",
            "type":"Services"
        }
    ],
    "sg:phone":"+1 206 242 0166",
    "sg:postcode":"98166",
    "sg:province":"WA",
    "sg:tags":[
        "repairing",
        "automobile",
        "part",
        "supply"
    ],
    "wof:name":"Burien Imports Ltd",
    "wof:placetype":"venue"
},
  "geometry": {"coordinates":[-122.348,47.480499],"type":"Point"}
}