{
  "type": "Feature",
  "properties": {
    "addr:full":"1302 C St Hoquiam WA 98550",
    "addr:housenumber":"1302",
    "addr:postcode":"98550",
    "addr:street":"C St",
    "iso:country":"US",
    "sg:address":"1302 C St",
    "sg:city":"Hoquiam",
    "sg:classifiers":[
        {
            "category":"Freight",
            "type":"Transportation"
        }
    ],
    "sg:phone":"+1 360 532 3204",
    "sg:postcode":"98550",
    "sg:province":"WA",
    "sg:tags":[
        "commercial",
        "storage"
    ],
    "wof:name":"Riverside Storage",
    "wof:placetype":"venue"
},
  "geometry": {"coordinates":[-123.883527,46.980588],"type":"Point"}
}