{
  "type": "Feature",
  "properties": {
    "addr:full":"25517 NE 42nd Pl Redmond WA 98053",
    "addr:housenumber":"25517",
    "addr:postcode":"98053",
    "addr:street":"Ne 42Nd Pl",
    "iso:country":"US",
    "sg:address":"25517 NE 42nd Pl",
    "sg:city":"Redmond",
    "sg:classifiers":[
        {
            "category":"Autos & Motor Vehicles",
            "subcategory":"Fuel & Gas Station",
            "type":"Retail Goods"
        }
    ],
    "sg:phone":"+1 425 868 2991",
    "sg:postcode":"98053",
    "sg:province":"WA",
    "sg:tags":[
        "station",
        "gasoline"
    ],
    "wof:name":"Shell",
    "wof:placetype":"venue"
},
  "geometry": {"coordinates":[-121.999336,47.646465],"type":"Point"}
}