{
  "type": "Feature",
  "properties": {
    "addr:full":"1039 Winslow Ave Richland WA 99354",
    "addr:housenumber":"1039",
    "addr:postcode":"99354",
    "addr:street":"Winslow Ave",
    "iso:country":"US",
    "sg:address":"1039 Winslow Ave",
    "sg:city":"Richland",
    "sg:classifiers":[
        {
            "category":"Personal",
            "subcategory":"Beauty Salon",
            "type":"Services"
        }
    ],
    "sg:phone":"+1 509 943 3142",
    "sg:postcode":"99354",
    "sg:province":"WA",
    "sg:tags":[
        "hair",
        "stylist"
    ],
    "wof:name":"A Wild Hair",
    "wof:placetype":"venue"
},
  "geometry": {"coordinates":[-119.29666899999999,46.281553],"type":"Point"}
}