{
  "type": "Feature",
  "properties": {
    "addr:full":"2202 State Rte 530 NE Arlington WA 98223",
    "addr:housenumber":"2202",
    "addr:postcode":"98223",
    "addr:street":"State Rte 530 Ne",
    "iso:country":"US",
    "sg:address":"2202 State Rte 530 NE",
    "sg:city":"Arlington",
    "sg:classifiers":[
        {
            "category":"Restaurant",
            "type":"Food & Drink"
        }
    ],
    "sg:phone":"+1 360 652 9444",
    "sg:postcode":"98223",
    "sg:province":"WA",
    "sg:tags":[
        "eating"
    ],
    "wof:name":"Dennys",
    "wof:placetype":"venue"
},
  "geometry": {"coordinates":[-122.197222,48.187976],"type":"Point"}
}