{
  "type": "Feature",
  "properties": {
    "addr:full":"1120 S 25th St Mount Vernon WA 98274",
    "addr:housenumber":"1120",
    "addr:postcode":"98274",
    "addr:street":"S 25Th St",
    "iso:country":"US",
    "sg:address":"1120 S 25th St",
    "sg:city":"Mount Vernon",
    "sg:classifiers":[
        {
            "category":"Social Services",
            "subcategory":"Child Care",
            "type":"Services"
        }
    ],
    "sg:phone":"+1 360 424 9509",
    "sg:postcode":"98274",
    "sg:province":"WA",
    "sg:tags":[
        "day"
    ],
    "wof:name":"Tinas Tiny Tots",
    "wof:placetype":"venue"
},
  "geometry": {"coordinates":[-122.308498,48.417677],"type":"Point"}
}