{
  "type": "Feature",
  "properties": {
    "addr:full":"11413 SE 266th St Kent WA 98030",
    "addr:postcode":"11413;98030",
    "addr:street":"Se 266Th St",
    "iso:country":"US",
    "sg:address":"11413 SE 266th St",
    "sg:city":"Kent",
    "sg:classifiers":[
        {
            "category":"Wholesale",
            "subcategory":"Construction Materials",
            "type":"Manufacturing & Wholesale Goods"
        }
    ],
    "sg:phone":"+1 253 813 8485",
    "sg:postcode":"98030",
    "sg:province":"WA",
    "sg:tags":[
        "interior",
        "wallboard"
    ],
    "wof:name":"Commercial Interior Systems",
    "wof:placetype":"venue"
},
  "geometry": {"coordinates":[-122.186716,47.363363],"type":"Point"}
}