{
  "type": "Feature",
  "properties": {
    "addr:full":"3700 W Armour Pl Seattle WA 98199",
    "addr:housenumber":"3700",
    "addr:postcode":"98199",
    "addr:street":"W Armour Pl",
    "iso:country":"US",
    "sg:address":"3700 W Armour Pl",
    "sg:city":"Seattle",
    "sg:classifiers":[
        {
            "category":"Farming",
            "subcategory":"Fish & Marine Products",
            "type":"Manufacturing & Wholesale Goods"
        }
    ],
    "sg:phone":"+1 206 282 2700",
    "sg:postcode":"98199",
    "sg:province":"WA",
    "sg:tags":[
        "commercial",
        "fisherman"
    ],
    "wof:name":"David Bakk",
    "wof:placetype":"venue"
},
  "geometry": {"coordinates":[-122.40588099999999,47.645579],"type":"Point"}
}