{
  "type": "Feature",
  "properties": {
    "addr:full":"318 5th Ave S Kent WA 98032",
    "addr:housenumber":"318",
    "addr:postcode":"98032",
    "addr:street":"5Th Ave S",
    "iso:country":"US",
    "sg:address":"318 5th Ave S",
    "sg:city":"Kent",
    "sg:classifiers":[
        {
            "category":"Education",
            "subcategory":"School",
            "type":"Public Place"
        }
    ],
    "sg:phone":"+1 253 852 5145",
    "sg:postcode":"98032",
    "sg:province":"WA",
    "sg:tags":[
        "elementary"
    ],
    "wof:name":"Kent View Christian School",
    "wof:placetype":"venue"
},
  "geometry": {"coordinates":[-122.238686,47.378732],"type":"Point"}
}