{
  "type": "Feature",
  "properties": {
    "addr:full":"1412 Bonnie Ln Toppenish WA 98948",
    "addr:housenumber":"1412",
    "addr:postcode":"98948",
    "addr:street":"Bonnie Ln",
    "iso:country":"US",
    "sg:address":"1412 Bonnie Ln",
    "sg:city":"Toppenish",
    "sg:classifiers":[
        {
            "category":"Professional",
            "type":"Services"
        }
    ],
    "sg:phone":"+1 509 865 5962",
    "sg:postcode":"98948",
    "sg:province":"WA",
    "sg:tags":[
        "fertilizing"
    ],
    "wof:name":"Gtb Ag Services L L C",
    "wof:placetype":"venue"
},
  "geometry": {"coordinates":[-120.328688,46.383821],"type":"Point"}
}