{
  "type": "Feature",
  "properties": {
    "addr:full":"909 N Nelson St Spokane WA 99202",
    "addr:housenumber":"909",
    "addr:postcode":"99202",
    "addr:street":"N Nelson St",
    "iso:country":"US",
    "sg:address":"909 N Nelson St",
    "sg:city":"Spokane",
    "sg:classifiers":[
        {
            "category":"Wholesale",
            "subcategory":"Construction Materials",
            "type":"Manufacturing & Wholesale Goods"
        },
        {
            "category":"Home & Garden",
            "subcategory":"Building Materials",
            "type":"Retail Goods"
        }
    ],
    "sg:phone":"+1 509 536 4311",
    "sg:postcode":"99202",
    "sg:province":"WA",
    "sg:tags":[
        "siding"
    ],
    "wof:name":"Alside Supply Center",
    "wof:placetype":"venue"
},
  "geometry": {"coordinates":[-117.369265,47.666488],"type":"Point"}
}