{
  "type": "Feature",
  "properties": {
    "addr:full":"1715 114th Ave SE Bellevue WA 98004",
    "addr:housenumber":"1715",
    "addr:postcode":"98004",
    "addr:street":"114Th Ave Se",
    "iso:country":"US",
    "sg:address":"1715 114th Ave SE",
    "sg:city":"Bellevue",
    "sg:classifiers":[
        {
            "category":"Wholesale",
            "subcategory":"Electrical",
            "type":"Manufacturing & Wholesale Goods"
        }
    ],
    "sg:phone":"+1 425 646 8750",
    "sg:postcode":"98004",
    "sg:province":"WA",
    "sg:tags":[
        "electronic",
        "component"
    ],
    "wof:name":"Bell Industries",
    "wof:placetype":"venue"
},
  "geometry": {"coordinates":[-122.189852,47.596669],"type":"Point"}
}