{
  "type": "Feature",
  "properties": {
    "addr:full":"1397 Olney Ave SE Port Orchard WA 98366",
    "addr:housenumber":"1397",
    "addr:postcode":"98366",
    "addr:street":"Olney Ave Se",
    "iso:country":"US",
    "sg:address":"1397 Olney Ave SE",
    "sg:city":"Port Orchard",
    "sg:classifiers":[
        {
            "category":"Personal",
            "subcategory":"Tanning Parlor",
            "type":"Services"
        }
    ],
    "sg:phone":"+1 360 876 6807",
    "sg:postcode":"98366",
    "sg:province":"WA",
    "sg:tags":[
        "salon"
    ],
    "wof:name":"Mango Bay Tanning Co",
    "wof:placetype":"venue"
},
  "geometry": {"coordinates":[-122.609548,47.535164],"type":"Point"}
}