{
  "type": "Feature",
  "properties": {
    "addr:full":"1826 E St Washougal WA 98671",
    "addr:housenumber":"1826",
    "addr:postcode":"98671",
    "addr:street":"E St",
    "iso:country":"US",
    "sg:address":"1826 E St",
    "sg:city":"Washougal",
    "sg:classifiers":[
        {
            "category":"Shopping",
            "subcategory":"Used Merchandise",
            "type":"Retail Goods"
        }
    ],
    "sg:phone":"+1 360 835 3062",
    "sg:postcode":"98671",
    "sg:province":"WA",
    "sg:tags":[
        "antique"
    ],
    "wof:name":"Collectible Corner Mall",
    "wof:placetype":"venue"
},
  "geometry": {"coordinates":[-122.352442,45.581092],"type":"Point"}
}