{
  "type": "Feature",
  "properties": {
    "addr:full":"18375 Olympic Ave S Seattle WA 98188",
    "addr:housenumber":"18375",
    "addr:postcode":"98188",
    "addr:street":"Olympic Ave S",
    "iso:country":"US",
    "sg:address":"18375 Olympic Ave S",
    "sg:city":"Seattle",
    "sg:classifiers":[
        {
            "category":"Wholesale",
            "subcategory":"Home Furnishings",
            "type":"Manufacturing & Wholesale Goods"
        }
    ],
    "sg:phone":"+1 206 575 1181",
    "sg:postcode":"98188",
    "sg:province":"WA",
    "sg:tags":[
        "floor",
        "covering"
    ],
    "wof:name":"Sound Floor Coverings Inc",
    "wof:placetype":"venue"
},
  "geometry": {"coordinates":[-122.251693,47.437222],"type":"Point"}
}