{
  "type": "Feature",
  "properties": {
    "addr:full":"7608 25th Ave E Tacoma WA 98404",
    "addr:housenumber":"7608",
    "addr:postcode":"98404",
    "addr:street":"25Th Ave E",
    "iso:country":"US",
    "sg:address":"7608 25th Ave E",
    "sg:city":"Tacoma",
    "sg:classifiers":[
        {
            "category":"Professional",
            "subcategory":"Computer Services",
            "type":"Services"
        }
    ],
    "sg:phone":"+1 253 539 1394",
    "sg:postcode":"98404",
    "sg:province":"WA",
    "sg:tags":[
        "datum",
        "commercial",
        "desi"
    ],
    "wof:name":"Jefron Graphics",
    "wof:placetype":"venue"
},
  "geometry": {"coordinates":[-122.396332,47.191717],"type":"Point"}
}