{
  "type": "Feature",
  "properties": {
    "addr:full":"2603 20th Ave NW Olympia WA 98502",
    "addr:housenumber":"2603",
    "addr:postcode":"olympia wa 98502",
    "addr:street":"20Th Ave Nw",
    "iso:country":"US",
    "sg:address":"2603 20th Ave NW",
    "sg:city":"Olympia",
    "sg:classifiers":[
        {
            "category":"Building & Trades",
            "subcategory":"Landscaping Services",
            "type":"Services"
        }
    ],
    "sg:phone":"+1 360 866 4429",
    "sg:postcode":"98502",
    "sg:province":"WA",
    "sg:tags":[
        "tree"
    ],
    "wof:name":"Wells Tree Farm",
    "wof:placetype":"venue"
},
  "geometry": {"coordinates":[-122.937648,47.06308],"type":"Point"}
}