{
  "type": "Feature",
  "properties": {
    "addr:full":"5401 Hinman Dr Cashmere WA 98815",
    "addr:housenumber":"5401",
    "addr:postcode":"98815",
    "addr:street":"Hinman Dr Cashmere",
    "iso:country":"US",
    "sg:address":"5401 Hinman Dr",
    "sg:city":"Cashmere",
    "sg:classifiers":[
        {
            "category":"Home & Garden",
            "subcategory":"Building Materials",
            "type":"Retail Goods"
        }
    ],
    "sg:phone":"+1 509 782 3173",
    "sg:postcode":"98815",
    "sg:province":"WA",
    "sg:tags":[
        "roofing"
    ],
    "wof:name":"Terry Brender's Superior Cedar",
    "wof:placetype":"venue"
},
  "geometry": {"coordinates":[-120.499197,47.514496],"type":"Point"}
}