{
  "type": "Feature",
  "properties": {
    "addr:full":"1000 Homann Dr SE Lacey WA 98503",
    "addr:housenumber":"1000",
    "addr:postcode":"98503",
    "addr:street":"Homann Dr Se",
    "iso:country":"US",
    "sg:address":"1000 Homann Dr SE",
    "sg:city":"Lacey",
    "sg:classifiers":[
        {
            "category":"Health Services",
            "subcategory":"Chiropractor",
            "type":"Services"
        }
    ],
    "sg:phone":"+1 360 491 6310",
    "sg:postcode":"98503",
    "sg:province":"WA",
    "wof:name":"Sandifer Chiropractic Clinic",
    "wof:placetype":"venue"
},
  "geometry": {"coordinates":[-122.805654,47.03516],"type":"Point"}
}