{
  "type": "Feature",
  "properties": {
    "addr:full":"1851 Bouslog Rd Burlington WA 98233",
    "addr:housenumber":"1851",
    "addr:postcode":"98233",
    "addr:street":"Bouslog Rd",
    "iso:country":"US",
    "sg:address":"1851 Bouslog Rd",
    "sg:city":"Burlington",
    "sg:classifiers":[
        {
            "category":"Restaurant",
            "type":"Food & Drink"
        }
    ],
    "sg:phone":"+1 360 757 7662",
    "sg:postcode":"98233",
    "sg:province":"WA",
    "wof:name":"EZ-Rider Cafe",
    "wof:placetype":"venue"
},
  "geometry": {"coordinates":[-122.345161,48.451681],"type":"Point"}
}