{
  "type": "Feature",
  "properties": {
    "addr:full":"11610 206th Pl SE Issaquah WA 98027",
    "addr:housenumber":"11610",
    "addr:postcode":"98027",
    "addr:street":"206Th Pl Se",
    "iso:country":"US",
    "sg:address":"11610 206th Pl SE",
    "sg:city":"Issaquah",
    "sg:classifiers":[
        {
            "category":"Building & Trades",
            "subcategory":"Construction",
            "type":"Services"
        }
    ],
    "sg:phone":"+1 425 430 9391",
    "sg:postcode":"98027",
    "sg:province":"WA",
    "sg:tags":[
        "house"
    ],
    "wof:name":"JM Construction Co",
    "wof:placetype":"venue"
},
  "geometry": {"coordinates":[-122.067151,47.497665],"type":"Point"}
}