{
  "type": "Feature",
  "properties": {
    "iso:country":"US",
    "sg:address":"19213 Bothell Everett Hwy",
    "sg:city":"Bothell",
    "sg:classifiers":[
        {
            "category":"Shopping",
            "subcategory":"Used Merchandise",
            "type":"Retail Goods"
        }
    ],
    "sg:phone":"+1 425 481 6682",
    "sg:postcode":"98012",
    "sg:province":"WA",
    "sg:tags":[
        "shop",
        "thrift"
    ],
    "wof:name":"Helping Hands Thrift Store",
    "wof:placetype":"venue"
},
  "geometry": {"coordinates":[-122.20737099999999,47.823754],"type":"Point"}
}