{
  "type": "Feature",
  "properties": {
    "addr:full":"3252 SE Nelson Rd Olalla WA 98359",
    "addr:housenumber":"3252",
    "addr:postcode":"98359",
    "addr:street":"Se Nelson Rd",
    "iso:country":"US",
    "sg:address":"3252 SE Nelson Rd",
    "sg:city":"Olalla",
    "sg:classifiers":[
        {
            "category":"Professional",
            "subcategory":"Printing & Photocopies",
            "type":"Services"
        },
        {
            "category":"Communications",
            "type":"Services"
        }
    ],
    "sg:phone":"+1 253 857 7635",
    "sg:postcode":"98359",
    "sg:province":"WA",
    "sg:tags":[
        "web",
        "design",
        "services-commercial"
    ],
    "sg:website":"http://www.northwoods-graphics.com",
    "wof:name":"North Woods Graphics",
    "wof:placetype":"venue"
},
  "geometry": {"coordinates":[-122.609364,47.417818],"type":"Point"}
}