{
  "type": "Feature",
  "properties": {
    "addr:full":"1024 3rd St Cosmopolis WA 98537",
    "addr:housenumber":"1024",
    "addr:postcode":"98537",
    "addr:street":"3Rd St",
    "iso:country":"US",
    "sg:address":"1024 3rd St",
    "sg:city":"Cosmopolis",
    "sg:classifiers":[
        {
            "category":"Organizations",
            "subcategory":"Religious Organization",
            "type":"Services"
        }
    ],
    "sg:phone":"+1 360 533 5847",
    "sg:postcode":"98537",
    "sg:province":"WA",
    "sg:tags":[
        "church"
    ],
    "wof:name":"Cosmopolis Gospel Church",
    "wof:placetype":"venue"
},
  "geometry": {"coordinates":[-123.774467,46.955927],"type":"Point"}
}