{
  "type": "Feature",
  "properties": {
    "iso:country":"US",
    "sg:address":"1517 E Rosewood Ave",
    "sg:city":"Spokane",
    "sg:classifiers":[
        {
            "category":"Retail",
            "subcategory":"Auto Repair",
            "type":"Services"
        }
    ],
    "sg:phone":"+1 509 926 7731",
    "sg:postcode":"99217",
    "sg:province":"WA",
    "sg:tags":[
        "exchanging",
        "engine"
    ],
    "wof:name":"Northwest Engine Exchange",
    "wof:placetype":"venue"
},
  "geometry": {"coordinates":[-117.38857299999999,47.715989],"type":"Point"}
}