{
  "type": "Feature",
  "properties": {
    "addr:full":"2001 2nd Ave Seattle WA 98121",
    "addr:housenumber":"2001",
    "addr:postcode":"98121",
    "addr:street":"2Nd Ave",
    "iso:country":"US",
    "sg:address":"2001 2nd Ave",
    "sg:city":"Seattle",
    "sg:classifiers":[
        {
            "category":"Parking",
            "type":"Transportation"
        }
    ],
    "sg:postcode":"98121",
    "sg:province":"WA",
    "sg:website":"www.rpnw.com",
    "wof:name":"Republic NW Parking Lot",
    "wof:placetype":"venue"
},
  "geometry": {"coordinates":[-122.34178900000001,47.611764],"type":"Point"}
}