{
  "type": "Feature",
  "properties": {
    "addr:full":"555 S Renton Village Pl # 600 Renton WA 98057",
    "addr:housenumber":"555;600",
    "addr:postcode":"98057",
    "addr:street":"S Renton Village Pl #",
    "iso:country":"US",
    "sg:address":"555 S Renton Village Pl # 600",
    "sg:city":"Renton",
    "sg:classifiers":[
        {
            "category":"Professional",
            "subcategory":"Business Services",
            "type":"Services"
        },
        {
            "category":"Government",
            "subcategory":"Post Office",
            "type":"Public Place"
        }
    ],
    "sg:phone":"+1 425 204 6300",
    "sg:postcode":"98057",
    "sg:province":"WA",
    "sg:tags":[
        "delivery",
        "labeling",
        "courier"
    ],
    "wof:name":"Horizon Lines",
    "wof:placetype":"venue"
},
  "geometry": {"coordinates":[-122.212441,47.469513],"type":"Point"}
}