{
  "type": "Feature",
  "properties": {
    "addr:full":"8918 161st Ave NE Redmond WA 98052",
    "addr:housenumber":"8918",
    "addr:postcode":"98052",
    "addr:street":"161St Ave Ne",
    "iso:country":"US",
    "sg:address":"8918 161st Ave NE",
    "sg:city":"Redmond",
    "sg:classifiers":[
        {
            "category":"Personal",
            "type":"Services"
        }
    ],
    "sg:phone":"+1 425 376 1122",
    "sg:postcode":"98052",
    "sg:province":"WA",
    "wof:name":"Midnight Sun III Inc",
    "wof:placetype":"venue"
},
  "geometry": {"coordinates":[-122.125449,47.680448],"type":"Point"}
}