{
  "type": "Feature",
  "properties": {
    "addr:full":"3005 30th Ave W Seattle WA 98199",
    "addr:housenumber":"3005",
    "addr:postcode":"98199",
    "addr:street":"30Th Ave W",
    "iso:country":"US",
    "sg:address":"3005 30th Ave W",
    "sg:city":"Seattle",
    "sg:classifiers":[
        {
            "category":"Food & Beverages",
            "subcategory":"Groceries & Convenience Stores",
            "type":"Retail Goods"
        }
    ],
    "sg:phone":"+1 206 352 5839",
    "sg:postcode":"98199",
    "sg:province":"WA",
    "wof:name":"Open Market Trading",
    "wof:placetype":"venue"
},
  "geometry": {"coordinates":[-122.39559199999999,47.646859],"type":"Point"}
}