{
  "type": "Feature",
  "properties": {
    "addr:full":"13430 314th Ave NE Duvall WA 98019",
    "addr:housenumber":"13430",
    "addr:postcode":"98019",
    "addr:street":"314Th Ave Ne",
    "iso:country":"US",
    "sg:address":"13430 314th Ave NE",
    "sg:city":"Duvall",
    "sg:classifiers":[
        {
            "category":"Professional",
            "subcategory":"Management & Consulting",
            "type":"Services"
        }
    ],
    "sg:phone":"+1 425 922 5900",
    "sg:postcode":"98019",
    "sg:province":"WA",
    "wof:name":"Cs3w Associates Inc",
    "wof:placetype":"venue"
},
  "geometry": {"coordinates":[-121.91965999999999,47.715678],"type":"Point"}
}