{
  "type": "Feature",
  "properties": {
    "addr:full":"2825 153rd Ave SE Snohomish WA 98290",
    "addr:housenumber":"2825",
    "addr:postcode":"98290",
    "addr:street":"153Rd Ave Se",
    "iso:country":"US",
    "sg:address":"2825 153rd Ave SE",
    "sg:city":"Snohomish",
    "sg:classifiers":[
        {
            "category":"Travel",
            "subcategory":"Travel Agent",
            "type":"Entertainment"
        }
    ],
    "sg:phone":"+1 425 335 1375",
    "sg:postcode":"98290",
    "sg:province":"WA",
    "sg:tags":[
        "operator",
        "tour"
    ],
    "wof:name":"Northwest Aero Tours",
    "wof:placetype":"venue"
},
  "geometry": {"coordinates":[-122.024745,47.969191],"type":"Point"}
}