{
  "type": "Feature",
  "properties": {
    "addr:full":"10006 S Tacoma Way Tacoma WA 98499",
    "addr:housenumber":"10006",
    "addr:postcode":"98499",
    "addr:street":"S Tacoma Way",
    "iso:country":"US",
    "sg:address":"10006 S Tacoma Way",
    "sg:city":"Tacoma",
    "sg:classifiers":[
        {
            "category":"Food & Beverages",
            "subcategory":"Groceries & Convenience Stores",
            "type":"Retail Goods"
        }
    ],
    "sg:phone":"+1 253 588 3103",
    "sg:postcode":"98499",
    "sg:province":"WA",
    "wof:name":"Lakewood Ampm",
    "wof:placetype":"venue"
},
  "geometry": {"coordinates":[-122.483683,47.166497],"type":"Point"}
}