{
  "type": "Feature",
  "properties": {
    "addr:full":"4209 S Lucile St Seattle WA 98118",
    "addr:housenumber":"4209",
    "addr:postcode":"98118",
    "addr:street":"S Lucile St",
    "iso:country":"US",
    "sg:address":"4209 S Lucile St",
    "sg:city":"Seattle",
    "sg:classifiers":[
        {
            "category":"Manufacturing",
            "subcategory":"Lumber",
            "type":"Manufacturing & Wholesale Goods"
        }
    ],
    "sg:phone":"+1 206 725 2018",
    "sg:postcode":"98118",
    "sg:province":"WA",
    "sg:tags":[
        "hardwood",
        "mill"
    ],
    "wof:name":"Finnel Floors Inc",
    "wof:placetype":"venue"
},
  "geometry": {"coordinates":[-122.27855099999999,47.552586],"type":"Point"}
}