{
  "type": "Feature",
  "properties": {
    "addr:full":"22227 NE 192nd St Woodinville WA 98077",
    "addr:housenumber":"22227",
    "addr:postcode":"98077",
    "addr:street":"Ne 192Nd St",
    "iso:country":"US",
    "sg:address":"22227 NE 192nd St",
    "sg:city":"Woodinville",
    "sg:classifiers":[
        {
            "category":"Sports & Exercise",
            "subcategory":"Gym",
            "type":"Entertainment"
        }
    ],
    "sg:phone":"+1 206 523 4569",
    "sg:postcode":"98077",
    "sg:province":"WA",
    "sg:tags":[
        "instruction",
        "yoga"
    ],
    "wof:name":"I Love Hot Yoga Inc",
    "wof:placetype":"venue"
},
  "geometry": {"coordinates":[-122.042473,47.766529],"type":"Point"}
}