{
  "type": "Feature",
  "properties": {
    "addr:full":"1202 Auburn Way N Auburn WA 98002",
    "addr:housenumber":"1202",
    "addr:postcode":"98002",
    "addr:street":"Auburn Way N",
    "iso:country":"US",
    "sg:address":"1202 Auburn Way N",
    "sg:city":"Auburn",
    "sg:classifiers":[
        {
            "category":"Restaurant",
            "type":"Food & Drink"
        }
    ],
    "sg:phone":"+1 253 887 1619",
    "sg:postcode":"98002",
    "sg:province":"WA",
    "sg:tags":[
        "seafood"
    ],
    "wof:name":"Skippers 141",
    "wof:placetype":"venue"
},
  "geometry": {"coordinates":[-122.221431,47.320193],"type":"Point"}
}