{
  "type": "Feature",
  "properties": {
    "addr:full":"365 118th Ave SE Ste 200 Bellevue WA 98005",
    "addr:housenumber":"365",
    "addr:postcode":"98005",
    "addr:street":"118Th Ave Se Ste 200",
    "iso:country":"US",
    "sg:address":"365 118th Ave SE Ste 200",
    "sg:city":"Bellevue",
    "sg:classifiers":[
        {
            "category":"Insurance",
            "subcategory":"Hazard Insurance",
            "type":"Services"
        }
    ],
    "sg:phone":"+1 425 488 4020",
    "sg:postcode":"98005",
    "sg:province":"WA",
    "wof:name":"Daniel Wong Insurance Agency",
    "wof:placetype":"venue"
},
  "geometry": {"coordinates":[-122.18369300000001,47.606615],"type":"Point"}
}