{
  "type": "Feature",
  "properties": {
    "addr:full":"180 Rock Island Rd East Wenatchee WA 98802",
    "addr:housenumber":"180",
    "addr:postcode":"98802",
    "addr:street":"Rock Island Rd",
    "iso:country":"US",
    "sg:address":"180 Rock Island Rd",
    "sg:city":"East Wenatchee",
    "sg:classifiers":[
        {
            "category":"Organizations",
            "subcategory":"Labor Organization",
            "type":"Services"
        }
    ],
    "sg:phone":"+1 509 884 6863",
    "sg:postcode":"98802",
    "sg:province":"WA",
    "wof:name":"Wenatchee Aluminum Trades Cncl",
    "wof:placetype":"venue"
},
  "geometry": {"coordinates":[-120.28835599999999,47.402426],"type":"Point"}
}