{
  "type": "Feature",
  "properties": {
    "addr:full":"360 Alder St SW Ephrata WA 98823",
    "addr:housenumber":"360",
    "addr:postcode":"98823",
    "addr:street":"Alder St Sw",
    "iso:country":"US",
    "sg:address":"360 Alder St SW",
    "sg:city":"Ephrata",
    "sg:classifiers":[
        {
            "category":"Building & Trades",
            "subcategory":"Construction",
            "type":"Services"
        }
    ],
    "sg:phone":"+1 509 754 4353",
    "sg:postcode":"98823",
    "sg:province":"WA",
    "sg:tags":[
        "general",
        "contractor"
    ],
    "wof:name":"Lakoduk Construction",
    "wof:placetype":"venue"
},
  "geometry": {"coordinates":[-119.55264200000001,47.316508],"type":"Point"}
}