{
  "type": "Feature",
  "properties": {
    "addr:full":"25905 N Jim Hill Rd Chattaroy WA 99003",
    "addr:housenumber":"25905",
    "addr:postcode":"99003",
    "addr:street":"N Jim Hill Rd",
    "iso:country":"US",
    "sg:address":"25905 N Jim Hill Rd",
    "sg:city":"Chattaroy",
    "sg:classifiers":[
        {
            "category":"Freight",
            "type":"Transportation"
        }
    ],
    "sg:phone":"+1 509 238 4491",
    "sg:postcode":"99003",
    "sg:province":"WA",
    "sg:tags":[
        "operator",
        "local",
        "trucking"
    ],
    "wof:name":"Gow Log Hauling",
    "wof:placetype":"venue"
},
  "geometry": {"coordinates":[-117.336731,47.89401],"type":"Point"}
}