{
  "type": "Feature",
  "properties": {
    "addr:full":"11011 Greenwood Ave N Seattle WA 98133",
    "addr:housenumber":"11011",
    "addr:postcode":"98133",
    "addr:street":"Greenwood Ave N",
    "iso:country":"US",
    "sg:address":"11011 Greenwood Ave N",
    "sg:city":"Seattle",
    "sg:classifiers":[
        {
            "category":"Professional",
            "subcategory":"Computer Services",
            "type":"Services"
        }
    ],
    "sg:phone":"+1 206 366 1909",
    "sg:postcode":"98133",
    "sg:province":"WA",
    "sg:tags":[
        "datum"
    ],
    "wof:name":"Water Dragon Web Design",
    "wof:placetype":"venue"
},
  "geometry": {"coordinates":[-122.355571,47.710436],"type":"Point"}
}