{
  "type": "Feature",
  "properties": {
    "iso:country":"US",
    "sg:address":"2114 N Pearl St",
    "sg:city":"Centralia",
    "sg:classifiers":[
        {
            "category":"Manufacturing",
            "subcategory":"Apparel",
            "type":"Manufacturing & Wholesale Goods"
        },
        {
            "category":"Home & Garden",
            "subcategory":"Home Furnishings",
            "type":"Retail Goods"
        }
    ],
    "sg:phone":"+1 360 736 1093",
    "sg:postcode":"98531",
    "sg:province":"WA",
    "sg:tags":[
        "blind",
        "made",
        "mfg",
        "rod",
        "custom",
        "window",
        "curtain",
        "drapery"
    ],
    "wof:name":"Woodring's Custom Draperies",
    "wof:placetype":"venue"
},
  "geometry": {"coordinates":[-122.95376,46.742264],"type":"Point"}
}