{
  "type": "Feature",
  "properties": {
    "addr:full":"1306 Dupont St Bellingham WA 98225",
    "addr:housenumber":"1306",
    "addr:postcode":"98225",
    "addr:street":"Dupont St",
    "iso:country":"US",
    "sg:address":"1306 Dupont St",
    "sg:city":"Bellingham",
    "sg:classifiers":[
        {
            "category":"Education",
            "subcategory":"School",
            "type":"Public Place"
        }
    ],
    "sg:phone":"+1 360 676 6400",
    "sg:postcode":"98225",
    "sg:province":"WA",
    "sg:website":"http://www.bham.wednet.edu",
    "wof:name":"Bellingham Public Schools",
    "wof:placetype":"venue"
},
  "geometry": {"coordinates":[-122.486896,48.758772],"type":"Point"}
}