{
  "type": "Feature",
  "properties": {
    "addr:full":"22020 72nd Ave S Kent WA 98032",
    "addr:housenumber":"22020",
    "addr:postcode":"98032",
    "addr:street":"72Nd Ave S",
    "iso:country":"US",
    "sg:address":"22020 72nd Ave S",
    "sg:city":"Kent",
    "sg:classifiers":[
        {
            "category":"Manufacturing",
            "subcategory":"Metals",
            "type":"Manufacturing & Wholesale Goods"
        }
    ],
    "sg:phone":"+1 253 872 2829",
    "sg:postcode":"98032",
    "sg:province":"WA",
    "sg:tags":[
        "hardware",
        "specializing",
        "mfg",
        "furniture"
    ],
    "wof:name":"Titus Tool Company Inc",
    "wof:placetype":"venue"
},
  "geometry": {"coordinates":[-122.24398600000001,47.405168],"type":"Point"}
}