{
  "type": "Feature",
  "properties": {
    "addr:full":"7848 Jenni St NE Olympia WA 98506",
    "addr:housenumber":"7848",
    "addr:postcode":"98506",
    "addr:street":"Jenni St Ne",
    "iso:country":"US",
    "sg:address":"7848 Jenni St NE",
    "sg:city":"Olympia",
    "sg:classifiers":[
        {
            "category":"Professional",
            "type":"Services"
        }
    ],
    "sg:phone":"+1 360 352 1177",
    "sg:postcode":"98506",
    "sg:province":"WA",
    "wof:name":"Prr Co",
    "wof:placetype":"venue"
},
  "geometry": {"coordinates":[-122.876548,47.14598],"type":"Point"}
}