{
  "type": "Feature",
  "properties": {
    "addr:full":"2980 Fir Rd Eltopia WA 99330",
    "addr:housenumber":"2980",
    "addr:postcode":"99330",
    "addr:street":"Fir Rd",
    "iso:country":"US",
    "sg:address":"2980 Fir Rd",
    "sg:city":"Eltopia",
    "sg:classifiers":[
        {
            "category":"Home & Garden",
            "subcategory":"Home Furnishings",
            "type":"Retail Goods"
        }
    ],
    "sg:phone":"+1 509 297 4445",
    "sg:postcode":"99330",
    "sg:province":"WA",
    "wof:name":"E JS Draperies",
    "wof:placetype":"venue"
},
  "geometry": {"coordinates":[-119.07756000000001,46.445422],"type":"Point"}
}