{
  "type": "Feature",
  "properties": {
    "addr:full":"3810 E Galer St Seattle WA 98112",
    "addr:housenumber":"3810",
    "addr:postcode":"98112",
    "addr:street":"E Galer St",
    "iso:country":"US",
    "sg:address":"3810 E Galer St",
    "sg:city":"Seattle",
    "sg:classifiers":[
        {
            "category":"Recreation",
            "type":"Entertainment"
        }
    ],
    "sg:phone":"+1 206 325 5569",
    "sg:postcode":"98112",
    "sg:province":"WA",
    "sg:tags":[
        "bike",
        "rental",
        "bicycles-renting"
    ],
    "wof:name":"Terrene Tours",
    "wof:placetype":"venue"
},
  "geometry": {"coordinates":[-122.283997,47.632099],"type":"Point"}
}