{
  "type": "Feature",
  "properties": {
    "addr:full":"7525 Orchard Ave Snohomish WA 98290",
    "addr:housenumber":"7525",
    "addr:postcode":"98290",
    "addr:street":"Orchard Ave",
    "iso:country":"US",
    "sg:address":"7525 Orchard Ave",
    "sg:city":"Snohomish",
    "sg:classifiers":[
        {
            "category":"Personal",
            "subcategory":"Beauty Salon",
            "type":"Services"
        }
    ],
    "sg:phone":"+1 360 568 4328",
    "sg:postcode":"98290",
    "sg:province":"WA",
    "sg:tags":[
        "shop"
    ],
    "wof:name":"Picket Fences",
    "wof:placetype":"venue"
},
  "geometry": {"coordinates":[-122.07754799999999,47.928154],"type":"Point"}
}