{
  "type": "Feature",
  "properties": {
    "addr:full":"4405 Rucker Ave Everett WA 98203",
    "addr:housenumber":"4405",
    "addr:postcode":"98203",
    "addr:street":"Rucker Ave",
    "iso:country":"US",
    "sg:address":"4405 Rucker Ave",
    "sg:city":"Everett",
    "sg:classifiers":[
        {
            "category":"Personal",
            "subcategory":"Beauty Salon",
            "type":"Services"
        }
    ],
    "sg:phone":"+1 425 339 1133",
    "sg:postcode":"98203",
    "sg:province":"WA",
    "sg:website":"www.3dsalons.com",
    "wof:name":"International Stylists Corp",
    "wof:placetype":"venue"
},
  "geometry": {"coordinates":[-122.210487,47.958087],"type":"Point"}
}