{
  "type": "Feature",
  "properties": {
    "addr:full":"210 W 4th St La Center WA 98629",
    "addr:housenumber":"210",
    "addr:postcode":"98629",
    "addr:street":"W 4Th St",
    "iso:country":"US",
    "sg:address":"210 W 4th St",
    "sg:city":"La Center",
    "sg:classifiers":[
        {
            "category":"Building & Trades",
            "subcategory":"Construction",
            "type":"Services"
        }
    ],
    "sg:phone":"+1 360 263 0002",
    "sg:postcode":"98629",
    "sg:province":"WA",
    "sg:tags":[
        "general"
    ],
    "wof:name":"J R Merit Inc",
    "wof:placetype":"venue"
},
  "geometry": {"coordinates":[-122.67205300000001,45.862078],"type":"Point"}
}