{
  "type": "Feature",
  "properties": {
    "iso:country":"US",
    "sg:address":"2880 Lee Rd",
    "sg:city":"Prosser",
    "sg:classifiers":[
        {
            "category":"Manufacturing",
            "subcategory":"Food",
            "type":"Manufacturing & Wholesale Goods"
        }
    ],
    "sg:phone":"+1 509 786 1100",
    "sg:postcode":"99350",
    "sg:province":"WA",
    "sg:tags":[
        "winery"
    ],
    "wof:name":"C R Sandidge Wines",
    "wof:placetype":"venue"
},
  "geometry": {"coordinates":[-119.744738,46.216777],"type":"Point"}
}