{
  "type": "Feature",
  "properties": {
    "addr:full":"160 NW Gilman Blvd Issaquah WA 98027",
    "addr:housenumber":"160",
    "addr:postcode":"98027",
    "addr:street":"Nw Gilman Blvd",
    "iso:country":"US",
    "sg:address":"160 NW Gilman Blvd",
    "sg:city":"Issaquah",
    "sg:classifiers":[
        {
            "category":"Insurance",
            "subcategory":"Hazard Insurance",
            "type":"Services"
        }
    ],
    "sg:phone":"+1 425 391 9714",
    "sg:postcode":"98027",
    "sg:province":"WA",
    "sg:tags":[
        "employee",
        "benefit",
        "compensation",
        "plan"
    ],
    "wof:name":"C B Solutions",
    "wof:placetype":"venue"
},
  "geometry": {"coordinates":[-122.040665,47.540524],"type":"Point"}
}