{
  "type": "Feature",
  "properties": {
    "addr:full":"313 N I St Tacoma WA 98403",
    "addr:housenumber":"313",
    "addr:postcode":"98403",
    "addr:street":"N I St",
    "iso:country":"US",
    "sg:address":"313 N I St",
    "sg:city":"Tacoma",
    "sg:classifiers":[
        {
            "category":"Bars & Pubs",
            "type":"Food & Drink"
        }
    ],
    "sg:phone":"+1 253 383 8748",
    "sg:postcode":"98403",
    "sg:province":"WA",
    "sg:tags":[
        "tavern"
    ],
    "wof:name":"Parkway Tavern",
    "wof:placetype":"venue"
},
  "geometry": {"coordinates":[-122.453334,47.262823],"type":"Point"}
}