{
  "type": "Feature",
  "properties": {
    "addr:full":"1314 Anderson Rd Mt Vernon WA 98274",
    "addr:housenumber":"1314",
    "addr:postcode":"98274",
    "addr:street":"Anderson Rd",
    "iso:country":"US",
    "sg:address":"1314 Anderson Rd",
    "sg:city":"Mt Vernon",
    "sg:classifiers":[
        {
            "category":"Shopping",
            "type":"Retail Goods"
        }
    ],
    "sg:phone":"+1 360 428 6833",
    "sg:postcode":"98274",
    "sg:province":"WA",
    "sg:tags":[
        "art",
        "gallery",
        "dealer"
    ],
    "wof:name":"Gallery Dei Gratia",
    "wof:placetype":"venue"
},
  "geometry": {"coordinates":[-122.328064,48.399365],"type":"Point"}
}