{
  "type": "Feature",
  "properties": {
    "iso:country":"US",
    "sg:address":"4401 N Freya St",
    "sg:city":"Spokane",
    "sg:classifiers":[
        {
            "category":"Government",
            "subcategory":"Post Office",
            "type":"Public Place"
        }
    ],
    "sg:phone":"+1 509 482 4581",
    "sg:postcode":"99217",
    "sg:province":"WA",
    "wof:name":"US Post Office",
    "wof:placetype":"venue"
},
  "geometry": {"coordinates":[-117.35740800000001,47.698305],"type":"Point"}
}