{
  "type": "Feature",
  "properties": {
    "addr:full":"20024 3rd Ave NW Seattle WA 98177",
    "addr:housenumber":"20024",
    "addr:postcode":"98177",
    "addr:street":"3Rd Ave Nw",
    "iso:country":"US",
    "sg:address":"20024 3rd Ave NW",
    "sg:city":"Seattle",
    "sg:classifiers":[
        {
            "category":"Social Services",
            "subcategory":"Adult Care",
            "type":"Services"
        }
    ],
    "sg:phone":"+1 206 542 3734",
    "sg:postcode":"98177",
    "sg:province":"WA",
    "sg:tags":[
        "residential"
    ],
    "wof:name":"Floral Hills Adult Family",
    "wof:placetype":"venue"
},
  "geometry": {"coordinates":[-122.361208,47.775172],"type":"Point"}
}