{
  "type": "Feature",
  "properties": {
    "addr:full":"9740 Greenwood Ave N Seattle WA 98103",
    "addr:housenumber":"9740",
    "addr:postcode":"98103",
    "addr:street":"Greenwood Ave N",
    "iso:country":"US",
    "sg:address":"9740 Greenwood Ave N",
    "sg:city":"Seattle",
    "sg:classifiers":[
        {
            "category":"Building & Trades",
            "subcategory":"Construction",
            "type":"Services"
        }
    ],
    "sg:phone":"+1 206 523 9007",
    "sg:postcode":"98103",
    "sg:province":"WA",
    "sg:tags":[
        "resurfacing",
        "laying",
        "refinishing",
        "floor"
    ],
    "wof:name":"Blackwood Hardwood",
    "wof:placetype":"venue"
},
  "geometry": {"coordinates":[-122.355339,47.701336],"type":"Point"}
}