{
  "type": "Feature",
  "properties": {
    "addr:full":"8825 Butte Ter SW Lakewood WA 98498",
    "addr:housenumber":"8825",
    "addr:postcode":"98498",
    "addr:street":"Butte Ter Sw",
    "iso:country":"US",
    "sg:address":"8825 Butte Ter SW",
    "sg:city":"Lakewood",
    "sg:classifiers":[
        {
            "category":"Professional",
            "type":"Services"
        }
    ],
    "sg:phone":"+1 253 588 4632",
    "sg:postcode":"98498",
    "sg:province":"WA",
    "wof:name":"Crowley Carliss",
    "wof:placetype":"venue"
},
  "geometry": {"coordinates":[-122.55715499999999,47.154498],"type":"Point"}
}