{
  "type": "Feature",
  "properties": {
    "addr:full":"3200 S 176th St Seattle WA 98188",
    "addr:housenumber":"3200",
    "addr:postcode":"98188",
    "addr:street":"S 176Th St",
    "iso:country":"US",
    "sg:address":"3200 S 176th St",
    "sg:city":"Seattle",
    "sg:classifiers":[
        {
            "category":"Professional",
            "subcategory":"Employment Agencies",
            "type":"Services"
        }
    ],
    "sg:phone":"+1 206 251 2800",
    "sg:postcode":"98188",
    "sg:province":"WA",
    "sg:tags":[
        "help",
        "supply"
    ],
    "wof:name":"Expert Care Staffing Service",
    "wof:placetype":"venue"
},
  "geometry": {"coordinates":[-122.291299,47.445243],"type":"Point"}
}