{
  "type": "Feature",
  "properties": {
    "addr:full":"1922 Wallula Ave Walla Walla WA 99362",
    "addr:housenumber":"1922",
    "addr:postcode":"99362",
    "addr:street":"Wallula Ave",
    "iso:country":"US",
    "sg:address":"1922 Wallula Ave",
    "sg:city":"Walla Walla",
    "sg:classifiers":[
        {
            "category":"Building & Trades",
            "subcategory":"Construction",
            "type":"Services"
        }
    ],
    "sg:phone":"+1 509 301 0425",
    "sg:postcode":"99362",
    "sg:province":"WA",
    "sg:tags":[
        "hanging",
        "contractor"
    ],
    "wof:name":"Hiebs Painting & Construction",
    "wof:placetype":"venue"
},
  "geometry": {"coordinates":[-118.426835,46.053403],"type":"Point"}
}