{
  "type": "Feature",
  "properties": {
    "addr:full":"903 Eagle Rd Othello WA 99344",
    "addr:housenumber":"903",
    "addr:postcode":"99344",
    "addr:street":"Eagle Rd",
    "iso:country":"US",
    "sg:address":"903 Eagle Rd",
    "sg:city":"Othello",
    "sg:classifiers":[
        {
            "category":"Travel",
            "subcategory":"Campground",
            "type":"Entertainment"
        },
        {
            "category":"Restaurant",
            "type":"Food & Drink"
        }
    ],
    "sg:phone":"+1 509 488 4484",
    "sg:postcode":"99344",
    "sg:province":"WA",
    "sg:tags":[
        "recreation",
        "sport",
        "camp"
    ],
    "sg:website":"www.eaglelakesranch.com",
    "wof:name":"Eagle Lakes Ranch Lodge",
    "wof:placetype":"venue"
},
  "geometry": {"coordinates":[-119.166389,46.709028],"type":"Point"}
}