{
  "type": "Feature",
  "properties": {
    "addr:full":"311 W Evergreen Blvd Vancouver WA 98660",
    "addr:housenumber":"311",
    "addr:postcode":"98660",
    "addr:street":"W Evergreen Blvd",
    "iso:country":"US",
    "sg:address":"311 W Evergreen Blvd",
    "sg:city":"Vancouver",
    "sg:classifiers":[
        {
            "category":"Health Services",
            "subcategory":"Clinic",
            "type":"Services"
        }
    ],
    "sg:phone":"+1 360 695 1590",
    "sg:postcode":"98660",
    "sg:province":"WA",
    "wof:name":"Alpha Plasma Center 413",
    "wof:placetype":"venue"
},
  "geometry": {"coordinates":[-122.67481100000001,45.628712],"type":"Point"}
}