{
  "type": "Feature",
  "properties": {
    "addr:full":"1303 K Ave Anacortes WA 98221",
    "addr:housenumber":"1303",
    "addr:postcode":"98221",
    "addr:street":"K Ave",
    "iso:country":"US",
    "sg:address":"1303 K Ave",
    "sg:city":"Anacortes",
    "sg:classifiers":[
        {
            "category":"Building & Trades",
            "subcategory":"Construction",
            "type":"Services"
        }
    ],
    "sg:phone":"+1 360 293 3562",
    "sg:postcode":"98221",
    "sg:province":"WA",
    "sg:tags":[
        "contractor"
    ],
    "wof:name":"Jims Drywall",
    "wof:placetype":"venue"
},
  "geometry": {"coordinates":[-122.62035899999999,48.511839],"type":"Point"}
}