{
  "type": "Feature",
  "properties": {
    "addr:full":"213 W California St Garfield WA 99130",
    "addr:housenumber":"213",
    "addr:postcode":"99130",
    "addr:street":"W California St",
    "iso:country":"US",
    "sg:address":"213 W California St",
    "sg:city":"Garfield",
    "sg:classifiers":[
        {
            "category":"Professional",
            "subcategory":"Lawyer & Legal Services",
            "type":"Services"
        }
    ],
    "sg:phone":"+1 509 635 1551",
    "sg:postcode":"99130",
    "sg:province":"WA",
    "sg:tags":[
        "attorney"
    ],
    "wof:name":"Bishop Law Offices",
    "wof:placetype":"venue"
},
  "geometry": {"coordinates":[-117.140062,47.007967],"type":"Point"}
}