{
  "type": "Feature",
  "properties": {
    "iso:country":"US",
    "sg:address":"94605 S Sagebrush Rd",
    "sg:city":"Kennewick",
    "sg:classifiers":[
        {
            "category":"Retail",
            "subcategory":"Auto Repair",
            "type":"Services"
        }
    ],
    "sg:phone":"+1 509 627 3257",
    "sg:postcode":"99338",
    "sg:province":"WA",
    "sg:tags":[
        "general"
    ],
    "wof:name":"Garage Door Specialists",
    "wof:placetype":"venue"
},
  "geometry": {"coordinates":[-119.292406,46.196158],"type":"Point"}
}