{
  "type": "Feature",
  "properties": {
    "addr:full":"4505 W Navaho Ave Spokane WA 99208",
    "addr:housenumber":"4505",
    "addr:postcode":"99208",
    "addr:street":"W Navaho Ave",
    "iso:country":"US",
    "sg:address":"4505 W Navaho Ave",
    "sg:city":"Spokane",
    "sg:classifiers":[
        {
            "category":"Professional",
            "subcategory":"Engineering",
            "type":"Services"
        }
    ],
    "sg:phone":"+1 509 467 7026",
    "sg:postcode":"99208",
    "sg:province":"WA",
    "sg:tags":[
        "engineer",
        "structural"
    ],
    "wof:name":"John Fulginiti Structural Engineering",
    "wof:placetype":"venue"
},
  "geometry": {"coordinates":[-117.47922699999999,47.750248],"type":"Point"}
}