{
  "type": "Feature",
  "properties": {
    "addr:full":"114 Alaskan Way S Seattle WA 98104",
    "addr:housenumber":"114",
    "addr:postcode":"98104",
    "addr:street":"Alaskan Way S",
    "iso:country":"US",
    "sg:address":"114 Alaskan Way S",
    "sg:city":"Seattle",
    "sg:classifiers":[
        {
            "category":"Professional",
            "subcategory":"Detective & Security Services",
            "type":"Services"
        }
    ],
    "sg:phone":"+1 888 888 2301",
    "sg:postcode":"98104",
    "sg:province":"WA",
    "sg:tags":[
        "information",
        "bureau"
    ],
    "wof:name":"Qwest 4 New Biz Service",
    "wof:placetype":"venue"
},
  "geometry": {"coordinates":[-122.33606399999999,47.601577],"type":"Point"}
}