{
  "type": "Feature",
  "properties": {
    "addr:full":"2521 Whitworth Ct S Renton WA 98055",
    "addr:housenumber":"2521",
    "addr:postcode":"98055",
    "addr:street":"Whitworth Ct S Renton",
    "iso:country":"US",
    "sg:address":"2521 Whitworth Ct S",
    "sg:city":"Renton",
    "sg:classifiers":[
        {
            "category":"Professional",
            "type":"Services"
        }
    ],
    "sg:phone":"+1 425 255 5853",
    "sg:postcode":"98055",
    "sg:province":"WA",
    "sg:tags":[
        "antique",
        "dealers-wholesale"
    ],
    "wof:name":"Glass Shelf",
    "wof:placetype":"venue"
},
  "geometry": {"coordinates":[-122.211163,47.45644],"type":"Point"}
}