{
  "type": "Feature",
  "properties": {
    "addr:full":"19540 104th Ave NE Bothell WA 98011",
    "addr:housenumber":"19540",
    "addr:postcode":"98011",
    "addr:street":"104Th Ave Ne",
    "iso:country":"US",
    "sg:address":"19540 104th Ave NE",
    "sg:city":"Bothell",
    "sg:classifiers":[
        {
            "category":"Organizations",
            "subcategory":"Religious Organization",
            "type":"Services"
        }
    ],
    "sg:phone":"+1 425 486 6388",
    "sg:postcode":"98011",
    "sg:province":"WA",
    "sg:website":"www.emmanuelpresbyterianchurch.com",
    "wof:name":"Emmanuel Presbyterian Church",
    "wof:placetype":"venue"
},
  "geometry": {"coordinates":[-122.20153500000001,47.770356],"type":"Point"}
}