{
  "type": "Feature",
  "properties": {
    "addr:full":"1511 S Gold St Centralia WA 98531",
    "addr:housenumber":"1511",
    "addr:postcode":"98531",
    "addr:street":"S Gold St",
    "iso:country":"US",
    "sg:address":"1511 S Gold St",
    "sg:city":"Centralia",
    "sg:classifiers":[
        {
            "category":"Shopping",
            "subcategory":"Antiques",
            "type":"Retail Goods"
        },
        {
            "category":"Home & Garden",
            "subcategory":"Furniture",
            "type":"Retail Goods"
        }
    ],
    "sg:phone":"+1 360 669 0005",
    "sg:postcode":"98531",
    "sg:province":"WA",
    "sg:tags":[
        "store"
    ],
    "sg:website":"http://www.lts2ndhand.com",
    "wof:name":"LT'S Second Hand Store",
    "wof:placetype":"venue"
},
  "geometry": {"coordinates":[-122.957489,46.698996],"type":"Point"}
}