{
  "type": "Feature",
  "properties": {
    "addr:full":"2332 E Madison St Seattle WA 98112",
    "addr:housenumber":"2332",
    "addr:postcode":"98112",
    "addr:street":"E Madison St",
    "iso:country":"US",
    "sg:address":"2332 E Madison St",
    "sg:city":"Seattle",
    "sg:classifiers":[
        {
            "category":"Food & Beverages",
            "subcategory":"Cheese",
            "type":"Retail Goods"
        }
    ],
    "sg:phone":"+1 206 323 1000",
    "sg:postcode":"98112",
    "sg:province":"WA",
    "sg:tags":[
        "cheesesteaks"
    ],
    "sg:website":"www.phillysteakshop.com/",
    "wof:name":"Phila Fevre Steak & Hoagie Shop",
    "wof:placetype":"venue"
},
  "geometry": {"coordinates":[-122.301439,47.620064],"type":"Point"}
}