{
  "type": "Feature",
  "properties": {
    "addr:full":"10 N Sullivan Rd Spokane Valley WA 99216",
    "addr:housenumber":"10",
    "addr:postcode":"99216",
    "addr:street":"N Sullivan Rd",
    "iso:country":"US",
    "sg:address":"10 N Sullivan Rd",
    "sg:city":"Spokane Valley",
    "sg:classifiers":[
        {
            "category":"Cinema",
            "subcategory":"Movie Rental",
            "type":"Entertainment"
        }
    ],
    "sg:phone":"+1 509 892 1556",
    "sg:postcode":"99216",
    "sg:province":"WA",
    "sg:tags":[
        "leasing",
        "video",
        "disc",
        "tape"
    ],
    "wof:name":"Hollywood Video",
    "wof:placetype":"venue"
},
  "geometry": {"coordinates":[-117.19651399999999,47.658735],"type":"Point"}
}