{
  "type": "Feature",
  "properties": {
    "addr:full":"80 Pond Rd Yakima WA 98901",
    "addr:housenumber":"80",
    "addr:postcode":"98901",
    "addr:street":"Pond Rd",
    "iso:country":"US",
    "sg:address":"80 Pond Rd",
    "sg:city":"Yakima",
    "sg:classifiers":[
        {
            "category":"Building & Trades",
            "subcategory":"Construction",
            "type":"Services"
        }
    ],
    "sg:phone":"+1 509 248 8376",
    "sg:postcode":"98901",
    "sg:province":"WA",
    "sg:tags":[
        "product",
        "asphalt"
    ],
    "wof:name":"Superior Asphlat & Concrete Co",
    "wof:placetype":"venue"
},
  "geometry": {"coordinates":[-120.497156,46.659134],"type":"Point"}
}