{
  "type": "Feature",
  "properties": {
    "addr:full":"7627 44th Ave NE Marysville WA 98270",
    "addr:housenumber":"7627",
    "addr:postcode":"98270",
    "addr:street":"44Th Ave Ne",
    "iso:country":"US",
    "sg:address":"7627 44th Ave NE",
    "sg:city":"Marysville",
    "sg:classifiers":[
        {
            "category":"Building & Trades",
            "subcategory":"Construction",
            "type":"Services"
        }
    ],
    "sg:phone":"+1 360 657 7000",
    "sg:postcode":"98270",
    "sg:province":"WA",
    "sg:tags":[
        "house",
        "general",
        "contractor"
    ],
    "wof:name":"K Four Construction",
    "wof:placetype":"venue"
},
  "geometry": {"coordinates":[-122.17170900000001,48.066977],"type":"Point"}
}