{
  "type": "Feature",
  "properties": {
    "addr:full":"1508 12th St Bremerton WA 98337",
    "addr:housenumber":"1508",
    "addr:postcode":"98337",
    "addr:street":"12Th St",
    "iso:country":"US",
    "sg:address":"1508 12th St",
    "sg:city":"Bremerton",
    "sg:classifiers":[
        {
            "category":"Organizations",
            "subcategory":"Religious Organization",
            "type":"Services"
        }
    ],
    "sg:phone":"+1 360 373 4332",
    "sg:postcode":"98337",
    "sg:province":"WA",
    "wof:name":"First Covenant Church",
    "wof:placetype":"venue"
},
  "geometry": {"coordinates":[-122.639775,47.571991],"type":"Point"}
}