{
  "type": "Feature",
  "properties": {
    "addr:full":"1435 Larch St Kettle Falls WA 99141",
    "addr:housenumber":"1435",
    "addr:postcode":"99141",
    "addr:street":"Larch St",
    "iso:country":"US",
    "sg:address":"1435 Larch St",
    "sg:city":"Kettle Falls",
    "sg:classifiers":[
        {
            "category":"Freight",
            "type":"Transportation"
        }
    ],
    "sg:phone":"+1 509 738 4813",
    "sg:postcode":"99141",
    "sg:province":"WA",
    "sg:tags":[
        "operator",
        "local",
        "trucking"
    ],
    "wof:name":"Skippy Trucking Corp",
    "wof:placetype":"venue"
},
  "geometry": {"coordinates":[-118.05741500000001,48.598262],"type":"Point"}
}