{
  "type": "Feature",
  "properties": {
    "iso:country":"US",
    "sg:address":"3008 161st Ave SE",
    "sg:city":"Bellevue",
    "sg:classifiers":[
        {
            "category":"Real Estate",
            "subcategory":"Architect",
            "type":"Services"
        }
    ],
    "sg:phone":"+1 425 747 2098",
    "sg:postcode":"98008",
    "sg:province":"WA",
    "sg:tags":[
        "architectural"
    ],
    "wof:name":"Arch Cnsltant/Space Efficiency",
    "wof:placetype":"venue"
},
  "geometry": {"coordinates":[-122.124422,47.584324],"type":"Point"}
}