{
  "type": "Feature",
  "properties": {
    "addr:full":"4910 35th St NE Tacoma WA 98422",
    "addr:housenumber":"4910",
    "addr:postcode":"98422",
    "addr:street":"35Th St Ne",
    "iso:country":"US",
    "sg:address":"4910 35th St NE",
    "sg:city":"Tacoma",
    "sg:classifiers":[
        {
            "category":"Manufacturing",
            "subcategory":"Wood Products",
            "type":"Manufacturing & Wholesale Goods"
        }
    ],
    "sg:phone":"+1 253 318 0334",
    "sg:postcode":"98422",
    "sg:province":"WA",
    "sg:tags":[
        "mfg"
    ],
    "wof:name":"C D N Continue",
    "wof:placetype":"venue"
},
  "geometry": {"coordinates":[-122.38066499999999,47.288559],"type":"Point"}
}