{
  "type": "Feature",
  "properties": {
    "addr:full":"1116 18th Ave Longview WA 98632",
    "addr:housenumber":"1116",
    "addr:postcode":"98632",
    "addr:street":"18Th Ave",
    "iso:country":"US",
    "sg:address":"1116 18th Ave",
    "sg:city":"Longview",
    "sg:classifiers":[
        {
            "category":"Building & Trades",
            "subcategory":"Landscaping Services",
            "type":"Services"
        }
    ],
    "sg:phone":"+1 360 636 3728",
    "sg:postcode":"98632",
    "sg:province":"WA",
    "sg:tags":[
        "landscape"
    ],
    "wof:name":"Basic Landscaping & Pruning",
    "wof:placetype":"venue"
},
  "geometry": {"coordinates":[-122.941543,46.136391],"type":"Point"}
}