{
  "type": "Feature",
  "properties": {
    "addr:full":"530 SE Derby St Pullman WA 99163",
    "addr:postcode":"530;99163",
    "addr:street":"Se Derby St",
    "iso:country":"US",
    "sg:address":"530 SE Derby St",
    "sg:city":"Pullman",
    "sg:classifiers":[
        {
            "category":"Professional",
            "type":"Services"
        }
    ],
    "sg:phone":"+1 509 334 3369",
    "sg:postcode":"99163",
    "sg:province":"WA",
    "wof:name":"Chris Watts",
    "wof:placetype":"venue"
},
  "geometry": {"coordinates":[-117.175617,46.723219],"type":"Point"}
}