{
  "type": "Feature",
  "properties": {
    "addr:full":"2116 NW 140th St Vancouver WA 98685",
    "addr:housenumber":"2116",
    "addr:postcode":"98685",
    "addr:street":"Nw 140Th St",
    "iso:country":"US",
    "sg:address":"2116 NW 140th St",
    "sg:city":"Vancouver",
    "sg:classifiers":[
        {
            "category":"Retail",
            "subcategory":"Repair Shop",
            "type":"Services"
        }
    ],
    "sg:phone":"+1 360 576 7141",
    "sg:postcode":"98685",
    "sg:province":"WA",
    "sg:tags":[
        "supplies-repair",
        "microwave",
        "equipment",
        "cellular",
        "tower",
        "electronic"
    ],
    "wof:name":"Sky-Comm Inc",
    "wof:placetype":"venue"
},
  "geometry": {"coordinates":[-122.693127,45.722549],"type":"Point"}
}