{
  "type": "Feature",
  "properties": {
    "addr:full":"558 Industrial Way Longview WA 98632",
    "addr:housenumber":"558",
    "addr:postcode":"98632",
    "addr:street":"Industrial Way",
    "iso:country":"US",
    "sg:address":"558 Industrial Way",
    "sg:city":"Longview",
    "sg:classifiers":[
        {
            "category":"Professional",
            "type":"Services"
        }
    ],
    "sg:phone":"+1 360 577 1226",
    "sg:postcode":"98632",
    "sg:province":"WA",
    "wof:name":"Jaz Performance Inc",
    "wof:placetype":"venue"
},
  "geometry": {"coordinates":[-122.935593,46.115908],"type":"Point"}
}