{
  "type": "Feature",
  "properties": {
    "addr:full":"7205 NE 117th Ave Vancouver WA 98662",
    "addr:housenumber":"7205",
    "addr:postcode":"98662",
    "addr:street":"Ne 117Th Ave",
    "iso:country":"US",
    "sg:address":"7205 NE 117th Ave",
    "sg:city":"Vancouver",
    "sg:classifiers":[
        {
            "category":"Fast Food",
            "type":"Food & Drink"
        },
        {
            "category":"Restaurant",
            "type":"Food & Drink"
        }
    ],
    "sg:phone":"+1 360 885 2450",
    "sg:postcode":"98662",
    "sg:province":"WA",
    "sg:tags":[
        "american",
        "hot",
        "hamburger",
        "dog"
    ],
    "sg:website":"http://www.jackinthebox.com",
    "wof:name":"Jack in the Box",
    "wof:placetype":"venue"
},
  "geometry": {"coordinates":[-122.552567,45.67461],"type":"Point"}
}