{
  "type": "Feature",
  "properties": {
    "addr:full":"210 SE 131st Ave Vancouver WA 98683",
    "addr:housenumber":"210",
    "addr:postcode":"98683",
    "addr:street":"Se 131St Ave",
    "iso:country":"US",
    "sg:address":"210 SE 131st Ave",
    "sg:city":"Vancouver",
    "sg:classifiers":[
        {
            "category":"Banks & Credit Unions",
            "subcategory":"Bank",
            "type":"Services"
        },
        {
            "category":"Banks & Credit Unions",
            "subcategory":"Financial Services",
            "type":"Services"
        }
    ],
    "sg:phone":"+1 360 891 4000",
    "sg:postcode":"98683",
    "sg:province":"WA",
    "sg:tags":[
        "broker",
        "mortgage"
    ],
    "sg:website":"www.columbiacu.org",
    "wof:name":"Columbia Credit Union",
    "wof:placetype":"venue"
},
  "geometry": {"coordinates":[-122.535004,45.619301],"type":"Point"}
}