{
  "type": "Feature",
  "properties": {
    "iso:country":"US",
    "sg:address":"3918 Rosedale St NW",
    "sg:city":"Gig Harbor",
    "sg:classifiers":[
        {
            "category":"Building & Trades",
            "subcategory":"Construction",
            "type":"Services"
        }
    ],
    "sg:phone":"+1 253 858 6291",
    "sg:postcode":"98335",
    "sg:province":"WA",
    "sg:tags":[
        "concrete",
        "work"
    ],
    "wof:name":"We R Concrete",
    "wof:placetype":"venue"
},
  "geometry": {"coordinates":[-122.59180600000001,47.330584],"type":"Point"}
}