{
  "type": "Feature",
  "properties": {
    "iso:country":"US",
    "sg:address":"23915 N Brooks Rd",
    "sg:city":"Orting",
    "sg:classifiers":[
        {
            "category":"Manufacturing",
            "subcategory":"Lumber",
            "type":"Manufacturing & Wholesale Goods"
        }
    ],
    "sg:phone":"+1 360 893 2196",
    "sg:postcode":"98360",
    "sg:province":"WA",
    "sg:tags":[
        "logging"
    ],
    "wof:name":"Carrigan Bros Inc",
    "wof:placetype":"venue"
},
  "geometry": {"coordinates":[-122.195728,47.037353],"type":"Point"}
}