{
  "type": "Feature",
  "properties": {
    "iso:country":"US",
    "sg:address":"7337 7th Ave SW",
    "sg:city":"Seattle",
    "sg:classifiers":[
        {
            "category":"Arts & Performance",
            "subcategory":"Theater",
            "type":"Entertainment"
        }
    ],
    "sg:phone":"+1 206 763 2841",
    "sg:postcode":"98106",
    "sg:province":"WA",
    "sg:tags":[
        "theatrical"
    ],
    "wof:name":"Valance Full Productions",
    "wof:placetype":"venue"
},
  "geometry": {"coordinates":[-122.34407899999999,47.534482],"type":"Point"}
}