{
  "type": "Feature",
  "properties": {
    "addr:full":"4425 S Orchard St Tacoma WA 98466",
    "addr:housenumber":"4425",
    "addr:postcode":"98466",
    "addr:street":"S Orchard St",
    "iso:country":"US",
    "sg:address":"4425 S Orchard St",
    "sg:city":"Tacoma",
    "sg:classifiers":[
        {
            "category":"Building & Trades",
            "subcategory":"Construction",
            "type":"Services"
        }
    ],
    "sg:phone":"+1 253 471 1428",
    "sg:postcode":"98466",
    "sg:province":"WA",
    "sg:tags":[
        "grading",
        "excavation",
        "contractor",
        "real estate",
        "developer"
    ],
    "wof:name":"Wagner Development Inc",
    "wof:placetype":"venue"
},
  "geometry": {"coordinates":[-122.505155,47.215518],"type":"Point"}
}