{
  "type": "Feature",
  "properties": {
    "iso:country":"US",
    "sg:address":"19501 144th Ave NE",
    "sg:city":"Woodinville",
    "sg:classifiers":[
        {
            "category":"Manufacturing",
            "subcategory":"Printing",
            "type":"Manufacturing & Wholesale Goods"
        }
    ],
    "sg:phone":"+1 425 483 1438",
    "sg:postcode":"98072",
    "sg:province":"WA",
    "sg:tags":[
        "print",
        "lithographic",
        "commercial",
        "typesetting"
    ],
    "wof:name":"C P S Printing Services",
    "wof:placetype":"venue"
},
  "geometry": {"coordinates":[-122.147837,47.768986],"type":"Point"}
}