{
  "type": "Feature",
  "properties": {
    "addr:full":"10214 SE 240th St Kent WA 98031",
    "addr:housenumber":"10214",
    "addr:postcode":"98031",
    "addr:street":"Se 240Th St",
    "iso:country":"US",
    "sg:address":"10214 SE 240th St",
    "sg:city":"Kent",
    "sg:classifiers":[
        {
            "category":"Retail",
            "subcategory":"Repair Shop",
            "type":"Services"
        }
    ],
    "sg:phone":"+1 253 859 6147",
    "sg:postcode":"98031",
    "sg:province":"WA",
    "wof:name":"Seatle Clock & Gift Co",
    "wof:placetype":"venue"
},
  "geometry": {"coordinates":[-122.204989,47.387031],"type":"Point"}
}