{
  "type": "Feature",
  "properties": {
    "addr:full":"4229 Sorrel Ln Clinton WA 98236",
    "addr:housenumber":"4229",
    "addr:postcode":"98236",
    "addr:street":"Sorrel Ln",
    "iso:country":"US",
    "sg:address":"4229 Sorrel Ln",
    "sg:city":"Clinton",
    "sg:classifiers":[
        {
            "category":"Personal",
            "type":"Services"
        },
        {
            "category":"Professional",
            "subcategory":"Art Services",
            "type":"Services"
        }
    ],
    "sg:phone":"+1 360 579 1913",
    "sg:postcode":"98236",
    "sg:province":"WA",
    "sg:tags":[
        "photography",
        "videography",
        "wedding"
    ],
    "wof:name":"The Enchanted Photo",
    "wof:placetype":"venue"
},
  "geometry": {"coordinates":[-122.389088,47.93701],"type":"Point"}
}