{
  "type": "Feature",
  "properties": {
    "addr:full":"909 52nd St SE Everett WA 98203",
    "addr:housenumber":"909",
    "addr:postcode":"98203",
    "addr:street":"52Nd St Se",
    "iso:country":"US",
    "sg:address":"909 52nd St SE",
    "sg:city":"Everett",
    "sg:classifiers":[
        {
            "category":"Shopping",
            "subcategory":"Computers & Home Electronics",
            "type":"Retail Goods"
        }
    ],
    "sg:phone":"+1 425 220 0758",
    "sg:postcode":"98203",
    "sg:province":"WA",
    "wof:name":"C & D Data",
    "wof:placetype":"venue"
},
  "geometry": {"coordinates":[-122.21840400000001,47.949517],"type":"Point"}
}