{
  "type": "Feature",
  "properties": {
    "addr:full":"1900 N 175th St Shoreline WA 98133",
    "addr:housenumber":"1900",
    "addr:postcode":"98133",
    "addr:street":"N 175Th St",
    "iso:country":"US",
    "sg:address":"1900 N 175th St",
    "sg:city":"Shoreline",
    "sg:classifiers":[
        {
            "category":"Place Of Worship",
            "subcategory":"Church",
            "type":"Public Place"
        },
        {
            "category":"Place Of Worship",
            "type":"Public Place"
        }
    ],
    "sg:phone":"+1 206 542 2111",
    "sg:postcode":"98133",
    "sg:province":"WA",
    "sg:tags":[
        "nazarene",
        "churches-church"
    ],
    "sg:website":"http://www.auroranazarene.org",
    "wof:name":"Aurora Church of the Nazarene",
    "wof:placetype":"venue"
},
  "geometry": {"coordinates":[-122.337593,47.756001],"type":"Point"}
}