{
  "type": "Feature",
  "properties": {
    "addr:full":"22618 87th Ave W Edmonds WA 98026",
    "addr:housenumber":"22618",
    "addr:postcode":"98026",
    "addr:street":"87Th Ave W",
    "iso:country":"US",
    "sg:address":"22618 87th Ave W",
    "sg:city":"Edmonds",
    "sg:classifiers":[
        {
            "category":"Banks & Credit Unions",
            "subcategory":"Financial Services",
            "type":"Services"
        }
    ],
    "sg:phone":"+1 425 775 7034",
    "sg:postcode":"98026",
    "sg:province":"WA",
    "sg:tags":[
        "investor"
    ],
    "wof:name":"Shoreline Womens Inv Group",
    "wof:placetype":"venue"
},
  "geometry": {"coordinates":[-122.349779,47.793701],"type":"Point"}
}