{
  "type": "Feature",
  "properties": {
    "iso:country":"US",
    "sg:address":"206 E Walnut St",
    "sg:city":"Winlock",
    "sg:classifiers":[
        {
            "category":"Food & Beverages",
            "subcategory":"Groceries & Convenience Stores",
            "type":"Retail Goods"
        }
    ],
    "sg:phone":"+1 360 785 4610",
    "sg:postcode":"98596",
    "sg:province":"WA",
    "sg:tags":[
        "grocer"
    ],
    "wof:name":"Cedar Village IGA",
    "wof:placetype":"venue"
},
  "geometry": {"coordinates":[-122.933851,46.491633],"type":"Point"}
}