{
  "type": "Feature",
  "properties": {
    "addr:full":"7012 44th Ave S Seattle WA 98118",
    "addr:housenumber":"7012",
    "addr:postcode":"98118",
    "addr:street":"44Th Ave S",
    "iso:country":"US",
    "sg:address":"7012 44th Ave S",
    "sg:city":"Seattle",
    "sg:classifiers":[
        {
            "category":"Building & Trades",
            "subcategory":"Construction",
            "type":"Services"
        }
    ],
    "sg:phone":"+1 206 762 3030",
    "sg:postcode":"98118",
    "sg:province":"WA",
    "sg:tags":[
        "resurfacing",
        "laying",
        "refinishing",
        "floor"
    ],
    "wof:name":"America Hardwood Floors",
    "wof:placetype":"venue"
},
  "geometry": {"coordinates":[-122.27799,47.539001],"type":"Point"}
}