{
  "type": "Feature",
  "properties": {
    "addr:full":"882 W Axton Rd Bellingham WA 98226",
    "addr:housenumber":"882",
    "addr:postcode":"98226",
    "addr:street":"W Axton Rd",
    "iso:country":"US",
    "sg:address":"882 W Axton Rd",
    "sg:city":"Bellingham",
    "sg:classifiers":[
        {
            "category":"Manufacturing",
            "subcategory":"Wood Products",
            "type":"Manufacturing & Wholesale Goods"
        }
    ],
    "sg:phone":"+1 360 303 4484",
    "sg:postcode":"98226",
    "sg:province":"WA",
    "sg:tags":[
        "mfg"
    ],
    "wof:name":"Pcworks",
    "wof:placetype":"venue"
},
  "geometry": {"coordinates":[-122.528819,48.848076],"type":"Point"}
}