{
  "type": "Feature",
  "properties": {
    "addr:full":"4905 NE 47th Ave Vancouver WA 98661",
    "addr:housenumber":"4905",
    "addr:postcode":"98661",
    "addr:street":"Ne 47Th Ave",
    "iso:country":"US",
    "sg:address":"4905 NE 47th Ave",
    "sg:city":"Vancouver",
    "sg:classifiers":[
        {
            "category":"Professional",
            "subcategory":"Lawyer & Legal Services",
            "type":"Services"
        }
    ],
    "sg:phone":"+1 360 699 5441",
    "sg:postcode":"98661",
    "sg:province":"WA",
    "sg:tags":[
        "mediation"
    ],
    "wof:name":"Deborah Nelson",
    "wof:placetype":"venue"
},
  "geometry": {"coordinates":[-122.62372499999999,45.65746],"type":"Point"}
}