{
  "type": "Feature",
  "properties": {
    "addr:full":"29229 18th Ave S Federal Way WA 98003",
    "addr:housenumber":"29229",
    "addr:postcode":"98003",
    "addr:street":"18Th Ave S Federal Way",
    "iso:country":"US",
    "sg:address":"29229 18th Ave S",
    "sg:city":"Federal Way",
    "sg:classifiers":[
        {
            "category":"Building & Trades",
            "subcategory":"Construction",
            "type":"Services"
        }
    ],
    "sg:phone":"+1 253 839 2058",
    "sg:postcode":"98003",
    "sg:province":"WA",
    "sg:tags":[
        "home",
        "speculative",
        "family",
        "contractor"
    ],
    "wof:name":"Hubner Bros",
    "wof:placetype":"venue"
},
  "geometry": {"coordinates":[-122.31070699999999,47.340799],"type":"Point"}
}