{
  "type": "Feature",
  "properties": {
    "addr:full":"28433 152nd Ave SE Kent WA 98042",
    "addr:housenumber":"28433",
    "addr:postcode":"98042",
    "addr:street":"152Nd Ave Se",
    "iso:country":"US",
    "sg:address":"28433 152nd Ave SE",
    "sg:city":"Kent",
    "sg:classifiers":[
        {
            "category":"Shopping",
            "subcategory":"Catalog Store",
            "type":"Retail Goods"
        }
    ],
    "sg:phone":"+1 253 631 2611",
    "sg:postcode":"98042",
    "sg:province":"WA",
    "sg:tags":[
        "mail",
        "house"
    ],
    "wof:name":"Granny Gooses Country Ho",
    "wof:placetype":"venue"
},
  "geometry": {"coordinates":[-122.13891599999999,47.346876],"type":"Point"}
}