{
  "type": "Feature",
  "properties": {
    "addr:full":"6405 NE 100th Ave Vancouver WA 98662",
    "addr:housenumber":"6405",
    "addr:postcode":"98662",
    "addr:street":"Ne 100Th Ave",
    "iso:country":"US",
    "sg:address":"6405 NE 100th Ave",
    "sg:city":"Vancouver",
    "sg:classifiers":[
        {
            "category":"Personal",
            "subcategory":"Beauty Salon",
            "type":"Services"
        }
    ],
    "sg:phone":"+1 360 883 1093",
    "sg:postcode":"98662",
    "sg:province":"WA",
    "sg:tags":[
        "shop"
    ],
    "wof:name":"Eastside Hair Design",
    "wof:placetype":"venue"
},
  "geometry": {"coordinates":[-122.570335,45.668071],"type":"Point"}
}