{
  "type": "Feature",
  "properties": {
    "iso:country":"US",
    "sg:address":"19903 Linden Ave N",
    "sg:city":"Seattle",
    "sg:classifiers":[
        {
            "category":"Home & Garden",
            "subcategory":"Garden Supply",
            "type":"Retail Goods"
        }
    ],
    "sg:phone":"+1 206 533 9454",
    "sg:postcode":"98133",
    "sg:province":"WA",
    "wof:name":"Anderson Gardens",
    "wof:placetype":"venue"
},
  "geometry": {"coordinates":[-122.34878,47.774125],"type":"Point"}
}