{
  "type": "Feature",
  "properties": {
    "addr:full":"61 Garden Ct Port Hadlock WA 98339",
    "addr:housenumber":"61",
    "addr:postcode":"98339",
    "addr:street":"Garden Ct;Hadlock",
    "iso:country":"US",
    "sg:address":"61 Garden Ct",
    "sg:city":"Port Hadlock",
    "sg:classifiers":[
        {
            "category":"Real Estate",
            "subcategory":"Real Estate Operator",
            "type":"Services"
        }
    ],
    "sg:phone":"+1 360 385 3968",
    "sg:postcode":"98339",
    "sg:province":"WA",
    "sg:tags":[
        "apartment"
    ],
    "wof:name":"Garden Court Apartments",
    "wof:placetype":"venue"
},
  "geometry": {"coordinates":[-122.762711,48.030955],"type":"Point"}
}