{
  "type": "Feature",
  "properties": {
    "addr:full":"12405 E Tallman Rd Chattaroy WA 99003",
    "addr:housenumber":"12405",
    "addr:postcode":"99003",
    "addr:street":"E Tallman Rd",
    "iso:country":"US",
    "sg:address":"12405 E Tallman Rd",
    "sg:city":"Chattaroy",
    "sg:classifiers":[
        {
            "category":"Professional",
            "subcategory":"Computer Services",
            "type":"Services"
        }
    ],
    "sg:phone":"+1 509 238 9519",
    "sg:postcode":"99003",
    "sg:province":"WA",
    "sg:tags":[
        "repair",
        "programing",
        "custom"
    ],
    "wof:name":"Computer Gurus",
    "wof:placetype":"venue"
},
  "geometry": {"coordinates":[-117.238927,47.909391],"type":"Point"}
}