{
  "type": "Feature",
  "properties": {
    "addr:full":"301 W Main St Auburn WA 98001",
    "addr:housenumber":"301",
    "addr:postcode":"98001",
    "addr:street":"W Main St",
    "iso:country":"US",
    "sg:address":"301 W Main St",
    "sg:city":"Auburn",
    "sg:classifiers":[
        {
            "category":"Home & Garden",
            "subcategory":"Furniture",
            "type":"Retail Goods"
        }
    ],
    "sg:phone":"+1 253 939 1949",
    "sg:postcode":"98001",
    "sg:province":"WA",
    "wof:name":"Total Office Furniture",
    "wof:placetype":"venue"
},
  "geometry": {"coordinates":[-122.234121,47.307569],"type":"Point"}
}