{
  "type": "Feature",
  "properties": {
    "addr:full":"1201 3rd Avenue Seattle WA 98101",
    "addr:housenumber":"1201",
    "addr:postcode":"98101",
    "addr:street":"3Rd Avenue",
    "iso:country":"US",
    "sg:address":"1201 3rd Avenue",
    "sg:city":"Seattle",
    "sg:classifiers":[
        {
            "category":"Professional",
            "subcategory":"Lawyer & Legal Services",
            "type":"Services"
        }
    ],
    "sg:phone":"+1 206 359 8364",
    "sg:postcode":"98101",
    "sg:province":"WA",
    "wof:name":"Eiting Brian J Atty",
    "wof:placetype":"venue"
},
  "geometry": {"coordinates":[-122.335381,47.607044],"type":"Point"}
}