{
  "type": "Feature",
  "properties": {
    "addr:full":"445 Pleasant Valley Rd Yakima WA 98908",
    "addr:housenumber":"445",
    "addr:postcode":"98908",
    "addr:street":"Pleasant Valley Rd",
    "iso:country":"US",
    "sg:address":"445 Pleasant Valley Rd",
    "sg:city":"Yakima",
    "sg:classifiers":[
        {
            "category":"Farming",
            "subcategory":"Farm & Veterinary Services",
            "type":"Manufacturing & Wholesale Goods"
        }
    ],
    "sg:phone":"+1 509 965 5900",
    "sg:postcode":"98908",
    "sg:province":"WA",
    "sg:tags":[
        "crop"
    ],
    "wof:name":"William R Garrigues",
    "wof:placetype":"venue"
},
  "geometry": {"coordinates":[-120.61513100000001,46.67578],"type":"Point"}
}