{
  "type": "Feature",
  "properties": {
    "addr:full":"208 Garfield St S Ste 101 Tacoma WA 98444",
    "addr:housenumber":"208",
    "addr:postcode":"98444",
    "addr:street":"Garfield St S Ste 101",
    "iso:country":"US",
    "sg:address":"208 Garfield St S Ste 101",
    "sg:city":"Tacoma",
    "sg:classifiers":[
        {
            "category":"Shopping",
            "subcategory":"Gifts & Souvenirs",
            "type":"Retail Goods"
        },
        {
            "category":"Shopping",
            "subcategory":"Books",
            "type":"Retail Goods"
        }
    ],
    "sg:phone":"+1 253 535 7665",
    "sg:postcode":"98444",
    "sg:province":"WA",
    "sg:tags":[
        "shop",
        "store"
    ],
    "sg:website":"http://www.garfieldbookcompany.com",
    "wof:name":"Garfield Book Co",
    "wof:placetype":"venue"
},
  "geometry": {"coordinates":[-122.43457600000001,47.146119],"type":"Point"}
}