{
  "type": "Feature",
  "properties": {
    "addr:full":"128 W 25th Ave Spokane WA 99203",
    "addr:housenumber":"128",
    "addr:postcode":"99203",
    "addr:street":"W 25Th Ave",
    "iso:country":"US",
    "sg:address":"128 W 25th Ave",
    "sg:city":"Spokane",
    "sg:classifiers":[
        {
            "category":"Building & Trades",
            "subcategory":"Construction",
            "type":"Services"
        }
    ],
    "sg:phone":"+1 509 624 4252",
    "sg:postcode":"99203",
    "sg:province":"WA",
    "sg:tags":[
        "residential"
    ],
    "wof:name":"Mandarino Construction",
    "wof:placetype":"venue"
},
  "geometry": {"coordinates":[-117.416555,47.631892],"type":"Point"}
}