{
  "type": "Feature",
  "properties": {
    "iso:country":"US",
    "sg:address":"24114 NE 132nd Ave",
    "sg:city":"Battle Ground",
    "sg:classifiers":[
        {
            "category":"Building & Trades",
            "subcategory":"Construction",
            "type":"Services"
        }
    ],
    "sg:phone":"+1 360 687 4766",
    "sg:postcode":"98604",
    "sg:province":"WA",
    "sg:tags":[
        "house",
        "nonresidential"
    ],
    "wof:name":"Deshirlias Construction",
    "wof:placetype":"venue"
},
  "geometry": {"coordinates":[-122.537159,45.795438],"type":"Point"}
}