{
  "type": "Feature",
  "properties": {
    "addr:full":"4537 Auburn Way N Auburn WA 98002",
    "addr:housenumber":"4537",
    "addr:postcode":"98002",
    "addr:street":"Auburn Way N",
    "iso:country":"US",
    "sg:address":"4537 Auburn Way N",
    "sg:city":"Auburn",
    "sg:classifiers":[
        {
            "category":"Wholesale",
            "subcategory":"Motor Vehicles",
            "type":"Manufacturing & Wholesale Goods"
        }
    ],
    "sg:phone":"+1 206 660 7998",
    "sg:postcode":"98002",
    "sg:province":"WA",
    "wof:name":"Dealers Suppliers",
    "wof:placetype":"venue"
},
  "geometry": {"coordinates":[-122.22539399999999,47.349493],"type":"Point"}
}