{
  "type": "Feature",
  "properties": {
    "addr:full":"14904 81st Ave NE Kenmore WA 98028",
    "addr:housenumber":"14904",
    "addr:postcode":"98028",
    "addr:street":"81St Ave Ne",
    "iso:country":"US",
    "sg:address":"14904 81st Ave NE",
    "sg:city":"Kenmore",
    "sg:classifiers":[
        {
            "category":"Professional",
            "type":"Services"
        }
    ],
    "sg:phone":"+1 425 273 6564",
    "sg:postcode":"98028",
    "sg:province":"WA",
    "wof:name":"KTI Services",
    "wof:placetype":"venue"
},
  "geometry": {"coordinates":[-122.23285199999999,47.736667],"type":"Point"}
}