{
  "type": "Feature",
  "properties": {
    "addr:full":"15440 NE 95th St Redmond WA 98052",
    "addr:housenumber":"15440",
    "addr:postcode":"98052",
    "addr:street":"Ne 95Th St",
    "iso:country":"US",
    "sg:address":"15440 NE 95th St",
    "sg:city":"Redmond",
    "sg:classifiers":[
        {
            "category":"Shopping",
            "subcategory":"Computers & Home Electronics",
            "type":"Retail Goods"
        }
    ],
    "sg:phone":"+1 425 885 9970",
    "sg:postcode":"98052",
    "sg:province":"WA",
    "sg:tags":[
        "software"
    ],
    "wof:name":"FAST Management Group Inc",
    "wof:placetype":"venue"
},
  "geometry": {"coordinates":[-122.13488599999999,47.685905],"type":"Point"}
}