{
  "type": "Feature",
  "properties": {
    "addr:full":"181 E Lakewood Ct Shelton WA 98584",
    "addr:housenumber":"181",
    "addr:postcode":"98584",
    "addr:street":"E Lakewood Ct",
    "iso:country":"US",
    "sg:address":"181 E Lakewood Ct",
    "sg:city":"Shelton",
    "sg:classifiers":[
        {
            "category":"Professional",
            "subcategory":"Business Services",
            "type":"Services"
        }
    ],
    "sg:phone":"+1 360 426 8771",
    "sg:postcode":"98584",
    "sg:province":"WA",
    "wof:name":"Shield Group",
    "wof:placetype":"venue"
},
  "geometry": {"coordinates":[-123.125764,47.245912],"type":"Point"}
}