{
  "type": "Feature",
  "properties": {
    "addr:full":"1736 N 21st Ave Pasco WA 99301",
    "addr:housenumber":"1736",
    "addr:postcode":"99301",
    "addr:street":"N 21St Ave",
    "iso:country":"US",
    "sg:address":"1736 N 21st Ave",
    "sg:city":"Pasco",
    "sg:classifiers":[
        {
            "category":"Manufacturing",
            "subcategory":"Printing",
            "type":"Manufacturing & Wholesale Goods"
        }
    ],
    "sg:phone":"+1 509 544 2155",
    "sg:postcode":"99301",
    "sg:province":"WA",
    "sg:tags":[
        "newspaper"
    ],
    "wof:name":"Cabin Fever Media",
    "wof:placetype":"venue"
},
  "geometry": {"coordinates":[-119.11862499999999,46.244177],"type":"Point"}
}