{
  "type": "Feature",
  "properties": {
    "addr:full":"3319 E 57th Ave Spokane WA 99223",
    "addr:housenumber":"3319",
    "addr:postcode":"99223",
    "addr:street":"E 57Th Ave",
    "iso:country":"US",
    "sg:address":"3319 E 57th Ave",
    "sg:city":"Spokane",
    "sg:classifiers":[
        {
            "category":"Personal",
            "subcategory":"Beauty Salon",
            "type":"Services"
        }
    ],
    "sg:phone":"+1 509 443 2141",
    "sg:postcode":"99223",
    "sg:province":"WA",
    "sg:tags":[
        "shop"
    ],
    "wof:name":"A Hair Affair",
    "wof:placetype":"venue"
},
  "geometry": {"coordinates":[-117.363688,47.602173],"type":"Point"}
}