{
  "type": "Feature",
  "properties": {
    "addr:full":"1960 SE Lund Ave Port Orchard WA 98366",
    "addr:housenumber":"1960",
    "addr:postcode":"98366",
    "addr:street":"Se Lund Ave",
    "iso:country":"US",
    "sg:address":"1960 SE Lund Ave",
    "sg:city":"Port Orchard",
    "sg:classifiers":[
        {
            "category":"Coffee & Tea",
            "type":"Food & Drink"
        }
    ],
    "sg:menulink":"http://www.allmenus.com/wa/port-orchard/117662-starbucks-coffee/menu/",
    "sg:phone":"+1 360 874 2360",
    "sg:postcode":"98366",
    "sg:province":"WA",
    "sg:tags":[
        "american"
    ],
    "wof:name":"Starbucks Coffee",
    "wof:placetype":"venue"
},
  "geometry": {"coordinates":[-122.62719,47.51919],"type":"Point"}
}