{
  "type": "Feature",
  "properties": {
    "addr:full":"6419 Martin Luther King Jr Way S Seattle WA 98118",
    "addr:housenumber":"6419",
    "addr:postcode":"98118",
    "addr:street":"Martin Luther King Jr Way S",
    "iso:country":"US",
    "sg:address":"6419 Martin Luther King Jr Way S",
    "sg:city":"Seattle",
    "sg:classifiers":[
        {
            "category":"Place Of Worship",
            "subcategory":"Church",
            "type":"Public Place"
        },
        {
            "category":"Place Of Worship",
            "type":"Public Place"
        },
        {
            "category":"Organizations",
            "subcategory":"Religious Organization",
            "type":"Services"
        }
    ],
    "sg:phone":"+1 206 723 6419",
    "sg:postcode":"98118",
    "sg:province":"WA",
    "sg:tags":[
        "god",
        "churches-church",
        "churches-pentecostal"
    ],
    "wof:name":"Greater Glory Church Of God",
    "wof:placetype":"venue"
},
  "geometry": {"coordinates":[-122.28511,47.54491],"type":"Point"}
}