{
  "type": "Feature",
  "properties": {
    "addr:full":"7109 114th Ave SE Newcastle WA 98056",
    "addr:housenumber":"7109",
    "addr:postcode":"98056",
    "addr:street":"114Th Ave Se",
    "iso:country":"US",
    "sg:address":"7109 114th Ave SE",
    "sg:city":"Newcastle",
    "sg:classifiers":[
        {
            "category":"Real Estate",
            "subcategory":"Real Estate Services",
            "type":"Services"
        },
        {
            "category":"Banks & Credit Unions",
            "subcategory":"Financial Services",
            "type":"Services"
        }
    ],
    "sg:phone":"+1 425 289 3600",
    "sg:postcode":"98056",
    "sg:province":"WA",
    "sg:tags":[
        "loan",
        "processing"
    ],
    "wof:name":"Precision Mortgage Inc",
    "wof:placetype":"venue"
},
  "geometry": {"coordinates":[-122.188219,47.539912],"type":"Point"}
}