{
  "type": "Feature",
  "properties": {
    "addr:full":"55 Limebelt Rd Okanogan WA 98840",
    "addr:housenumber":"55",
    "addr:postcode":"98840",
    "addr:street":"Limebelt Rd",
    "iso:country":"US",
    "sg:address":"55 Limebelt Rd",
    "sg:city":"Okanogan",
    "sg:classifiers":[
        {
            "category":"Farming",
            "subcategory":"Livestock Farm",
            "type":"Manufacturing & Wholesale Goods"
        }
    ],
    "sg:phone":"+1 509 826 6700",
    "sg:postcode":"98840",
    "sg:province":"WA",
    "sg:tags":[
        "animal",
        "general"
    ],
    "wof:name":"Haeberle Ranch Inc",
    "wof:placetype":"venue"
},
  "geometry": {"coordinates":[-119.62609399999999,48.50768],"type":"Point"}
}