{
  "type": "Feature",
  "properties": {
    "addr:full":"568 Ivarson Rd Camano Island WA 99323",
    "addr:housenumber":"568",
    "addr:postcode":"99323",
    "addr:street":"Ivarson Rd",
    "iso:country":"US",
    "sg:address":"568 Ivarson Rd",
    "sg:city":"Camano Island",
    "sg:classifiers":[
        {
            "category":"Communications",
            "subcategory":"Film & Video Production",
            "type":"Services"
        }
    ],
    "sg:phone":"+1 360 387 8222",
    "sg:postcode":"99323",
    "sg:province":"WA",
    "sg:tags":[
        "taping"
    ],
    "sg:website":"www.globalnetproductions.com",
    "wof:name":"Global Net Productions",
    "wof:placetype":"venue"
},
  "geometry": {"coordinates":[-118.93264600000001,46.163081],"type":"Point"}
}