{
  "type": "Feature",
  "properties": {
    "addr:full":"12728 Greenwood Ave N Seattle WA 98133",
    "addr:housenumber":"12728",
    "addr:postcode":"98133",
    "addr:street":"Greenwood Ave N",
    "iso:country":"US",
    "sg:address":"12728 Greenwood Ave N",
    "sg:city":"Seattle",
    "sg:classifiers":[
        {
            "category":"Health Services",
            "subcategory":"Health Practitioner",
            "type":"Services"
        }
    ],
    "sg:phone":"+1 206 669 1063",
    "sg:postcode":"98133",
    "sg:province":"WA",
    "wof:name":"Integrated Oriental Medicine",
    "wof:placetype":"venue"
},
  "geometry": {"coordinates":[-122.355473,47.723061],"type":"Point"}
}