{
  "type": "Feature",
  "properties": {
    "addr:full":"12300 Sidney Rd SW Port Orchard WA 98367",
    "addr:housenumber":"12300",
    "addr:postcode":"98367",
    "addr:street":"Sidney Rd Sw Port Orchard",
    "iso:country":"US",
    "sg:address":"12300 Sidney Rd SW",
    "sg:city":"Port Orchard",
    "sg:classifiers":[
        {
            "category":"Manufacturing",
            "subcategory":"Wood Products",
            "type":"Manufacturing & Wholesale Goods"
        }
    ],
    "sg:phone":"+1 360 340 0820",
    "sg:postcode":"98367",
    "sg:province":"WA",
    "sg:tags":[
        "mfg"
    ],
    "wof:name":"Visual Creations",
    "wof:placetype":"venue"
},
  "geometry": {"coordinates":[-122.661435,47.434925],"type":"Point"}
}