{
  "type": "Feature",
  "properties": {
    "iso:country":"US",
    "sg:address":"11818 55th Ave S",
    "sg:city":"Seattle",
    "sg:classifiers":[
        {
            "category":"Retail",
            "subcategory":"Portrait Studio",
            "type":"Services"
        }
    ],
    "sg:phone":"+1 206 799 1654",
    "sg:postcode":"98178",
    "sg:province":"WA",
    "sg:tags":[
        "photo"
    ],
    "wof:name":"Spx5 Photography",
    "wof:placetype":"venue"
},
  "geometry": {"coordinates":[-122.264258,47.49573],"type":"Point"}
}