{
  "type": "Feature",
  "properties": {
    "addr:full":"1102 Commerce St Tacoma WA 98402",
    "addr:housenumber":"1102",
    "addr:postcode":"98402",
    "addr:street":"Commerce St",
    "iso:country":"US",
    "sg:address":"1102 Commerce St",
    "sg:city":"Tacoma",
    "sg:classifiers":[
        {
            "category":"Real Estate",
            "subcategory":"Real Estate Agent",
            "type":"Services"
        }
    ],
    "sg:phone":"+1 253 926 6000",
    "sg:postcode":"98402",
    "sg:province":"WA",
    "sg:tags":[
        "investment"
    ],
    "sg:website":"www.colliers.com",
    "wof:name":"Colliers International",
    "wof:placetype":"venue"
},
  "geometry": {"coordinates":[-122.43899500000001,47.251247],"type":"Point"}
}