{
  "type": "Feature",
  "properties": {
    "addr:full":"7612 19th Ln SE Lacey WA 98503",
    "addr:housenumber":"7612",
    "addr:postcode":"98503",
    "addr:street":"19Th Ln Se",
    "iso:country":"US",
    "sg:address":"7612 19th Ln SE",
    "sg:city":"Lacey",
    "sg:classifiers":[
        {
            "category":"Real Estate",
            "subcategory":"Real Estate Operator",
            "type":"Services"
        }
    ],
    "sg:phone":"+1 360 455 0858",
    "sg:postcode":"98503",
    "sg:province":"WA",
    "sg:tags":[
        "building",
        "apartment"
    ],
    "wof:name":"Pacific Land Investment",
    "wof:placetype":"venue"
},
  "geometry": {"coordinates":[-122.776901,47.028954],"type":"Point"}
}