{
  "type": "Feature",
  "properties": {
    "addr:full":"2360 Oyster Creek Ln Bow WA 98232",
    "addr:housenumber":"2360",
    "addr:postcode":"98232",
    "addr:street":"Oyster Creek Ln",
    "iso:country":"US",
    "sg:address":"2360 Oyster Creek Ln",
    "sg:city":"Bow",
    "sg:classifiers":[
        {
            "category":"Professional",
            "subcategory":"Lawyer & Legal Services",
            "type":"Services"
        }
    ],
    "sg:phone":"+1 360 766 6666",
    "sg:postcode":"98232",
    "sg:province":"WA",
    "wof:name":"Michael C August",
    "wof:placetype":"venue"
},
  "geometry": {"coordinates":[-122.435401,48.623483],"type":"Point"}
}