{
  "type": "Feature",
  "properties": {
    "addr:full":"10500 NE 8th St Bellevue WA 98004",
    "addr:housenumber":"10500",
    "addr:postcode":"98004",
    "addr:street":"Ne 8Th St",
    "iso:country":"US",
    "sg:address":"10500 NE 8th St",
    "sg:city":"Bellevue",
    "sg:classifiers":[
        {
            "category":"Freight",
            "type":"Transportation"
        }
    ],
    "sg:phone":"+1 425 637 6833",
    "sg:postcode":"98004",
    "sg:province":"WA",
    "sg:tags":[
        "courier"
    ],
    "wof:name":"Fedex Freight East Inc",
    "wof:placetype":"venue"
},
  "geometry": {"coordinates":[-122.199912,47.617499],"type":"Point"}
}