{
  "type": "Feature",
  "properties": {
    "addr:full":"3037 127th Pl SE Bellevue WA 98005",
    "addr:housenumber":"3037",
    "addr:postcode":"98005",
    "addr:street":"127Th Pl Se",
    "iso:country":"US",
    "sg:address":"3037 127th Pl SE",
    "sg:city":"Bellevue",
    "sg:classifiers":[
        {
            "category":"Personal",
            "type":"Services"
        }
    ],
    "sg:phone":"+1 425 747 3157",
    "sg:postcode":"98005",
    "sg:province":"WA",
    "wof:name":"Affairs By Sher",
    "wof:placetype":"venue"
},
  "geometry": {"coordinates":[-122.170878,47.583378],"type":"Point"}
}