{
  "type": "Feature",
  "properties": {
    "addr:full":"2923 E 29th Ave Spokane WA 99223",
    "addr:housenumber":"2923",
    "addr:postcode":"99223",
    "addr:street":"E 29Th Ave",
    "iso:country":"US",
    "sg:address":"2923 E 29th Ave",
    "sg:city":"Spokane",
    "sg:classifiers":[
        {
            "category":"Retail",
            "subcategory":"Veterinary Services",
            "type":"Services"
        }
    ],
    "sg:phone":"+1 509 536 7387",
    "sg:postcode":"99223",
    "sg:province":"WA",
    "sg:tags":[
        "clinic",
        "hospital",
        "veterinarian",
        "specialty"
    ],
    "wof:name":"Regal Veterinary Clinic",
    "wof:placetype":"venue"
},
  "geometry": {"coordinates":[-117.36744,47.628208],"type":"Point"}
}