{
  "type": "Feature",
  "properties": {
    "addr:full":"1495 NW Gilman Blvd Issaquah WA 98027",
    "addr:housenumber":"1495",
    "addr:postcode":"98027",
    "addr:street":"Nw Gilman Blvd",
    "iso:country":"US",
    "sg:address":"1495 NW Gilman Blvd",
    "sg:city":"Issaquah",
    "sg:classifiers":[
        {
            "category":"Education",
            "subcategory":"Special Training",
            "type":"Public Place"
        }
    ],
    "sg:phone":"+1 425 392 2009",
    "sg:postcode":"98027",
    "sg:province":"WA",
    "sg:tags":[
        "educational"
    ],
    "wof:name":"E 2 Educational Svc",
    "wof:placetype":"venue"
},
  "geometry": {"coordinates":[-122.060641,47.54562],"type":"Point"}
}