{
  "type": "Feature",
  "properties": {
    "addr:full":"9409 Assink Rd Lynden WA 98264",
    "addr:postcode":"9409;98264",
    "addr:street":"Assink Rd",
    "iso:country":"US",
    "sg:address":"9409 Assink Rd",
    "sg:city":"Lynden",
    "sg:classifiers":[
        {
            "category":"Real Estate",
            "subcategory":"Real Estate Operator",
            "type":"Services"
        }
    ],
    "sg:phone":"+1 360 354 5559",
    "sg:postcode":"98264",
    "sg:province":"WA",
    "sg:tags":[
        "property",
        "lessor"
    ],
    "wof:name":"Dennis Assink Farm",
    "wof:placetype":"venue"
},
  "geometry": {"coordinates":[-122.42935799999999,48.979916],"type":"Point"}
}