{
  "type": "Feature",
  "properties": {
    "addr:full":"19709 Scriber Lake Rd Lynnwood WA 98036",
    "addr:housenumber":"19709",
    "addr:postcode":"98036",
    "addr:street":"Scriber Lake Rd",
    "iso:country":"US",
    "sg:address":"19709 Scriber Lake Rd",
    "sg:city":"Lynnwood",
    "sg:classifiers":[
        {
            "category":"Banks & Credit Unions",
            "subcategory":"Bank",
            "type":"Services"
        }
    ],
    "sg:phone":"+1 425 673 4859",
    "sg:postcode":"98036",
    "sg:province":"WA",
    "sg:tags":[
        "mortgage"
    ],
    "wof:name":"Perfect Solution",
    "wof:placetype":"venue"
},
  "geometry": {"coordinates":[-122.31166899999999,47.820294],"type":"Point"}
}