{
  "type": "Feature",
  "properties": {
    "addr:full":"3881 16th Ave SW Seattle WA 98106",
    "addr:housenumber":"3881",
    "addr:postcode":"98106",
    "addr:street":"16Th Ave Sw",
    "iso:country":"US",
    "sg:address":"3881 16th Ave SW",
    "sg:city":"Seattle",
    "sg:classifiers":[
        {
            "category":"Utilities",
            "subcategory":"Refuse",
            "type":"Services"
        }
    ],
    "sg:phone":"+1 206 935 4255",
    "sg:postcode":"98106",
    "sg:province":"WA",
    "sg:tags":[
        "recycling",
        "center"
    ],
    "wof:name":"West Seattle Recycling Inc",
    "wof:placetype":"venue"
},
  "geometry": {"coordinates":[-122.355418,47.568719],"type":"Point"}
}