{
  "type": "Feature",
  "properties": {
    "addr:full":"704 S 1st St Yakima WA 98901",
    "addr:housenumber":"704",
    "addr:postcode":"98901",
    "addr:street":"S 1St St",
    "iso:country":"US",
    "sg:address":"704 S 1st St",
    "sg:city":"Yakima",
    "sg:classifiers":[
        {
            "category":"Autos & Motor Vehicles",
            "subcategory":"Automobile Sales",
            "type":"Retail Goods"
        }
    ],
    "sg:phone":"+1 509 452 5922",
    "sg:postcode":"98901",
    "sg:province":"WA",
    "sg:tags":[
        "used"
    ],
    "wof:name":"Auto Mart",
    "wof:placetype":"venue"
},
  "geometry": {"coordinates":[-120.50137100000001,46.592471],"type":"Point"}
}