{
  "type": "Feature",
  "properties": {
    "addr:full":"4419 26th Ave SW Seattle WA 98106",
    "addr:housenumber":"4419",
    "addr:postcode":"98106",
    "addr:street":"26Th Ave Sw",
    "iso:country":"US",
    "sg:address":"4419 26th Ave SW",
    "sg:city":"Seattle",
    "sg:classifiers":[
        {
            "category":"Professional",
            "subcategory":"Business Services",
            "type":"Services"
        }
    ],
    "sg:phone":"+1 206 938 4664",
    "sg:postcode":"98106",
    "sg:province":"WA",
    "wof:name":"Vibrant Enterprise",
    "wof:placetype":"venue"
},
  "geometry": {"coordinates":[-122.365551,47.563147],"type":"Point"}
}