{
  "type": "Feature",
  "properties": {
    "addr:full":"811 112th St SW Everett WA 98204",
    "addr:housenumber":"811",
    "addr:postcode":"98204",
    "addr:street":"112Th St Sw",
    "iso:country":"US",
    "sg:address":"811 112th St SW",
    "sg:city":"Everett",
    "sg:classifiers":[
        {
            "category":"Real Estate",
            "subcategory":"Real Estate Operator",
            "type":"Services"
        }
    ],
    "sg:phone":"+1 425 745 7763",
    "sg:postcode":"98204",
    "sg:province":"WA",
    "sg:tags":[
        "building",
        "apartment"
    ],
    "wof:name":"Shadow Creek Apartments",
    "wof:placetype":"venue"
},
  "geometry": {"coordinates":[-122.246707,47.896524],"type":"Point"}
}