{
  "type": "Feature",
  "properties": {
    "addr:full":"275 Hahn Dr Kalama WA 98625",
    "addr:housenumber":"275",
    "addr:postcode":"98625",
    "addr:street":"Hahn Dr Kalama",
    "iso:country":"US",
    "sg:address":"275 Hahn Dr",
    "sg:city":"Kalama",
    "sg:classifiers":[
        {
            "category":"Building & Trades",
            "subcategory":"Electrical",
            "type":"Services"
        }
    ],
    "sg:phone":"+1 360 673 5173",
    "sg:postcode":"98625",
    "sg:province":"WA",
    "sg:tags":[
        "electrician"
    ],
    "wof:name":"Acme Electrical Svcs",
    "wof:placetype":"venue"
},
  "geometry": {"coordinates":[-122.809386,45.97537],"type":"Point"}
}