{
  "type": "Feature",
  "properties": {
    "addr:full":"17009 Orting Rd N Sumner WA 98391",
    "addr:postcode":"17009;98391",
    "addr:street":"Orting Rd N",
    "iso:country":"US",
    "sg:address":"17009 Orting Rd N",
    "sg:city":"Sumner",
    "sg:classifiers":[
        {
            "category":"Sports & Exercise",
            "subcategory":"Race Track",
            "type":"Entertainment"
        }
    ],
    "sg:phone":"+1 360 897 6239",
    "sg:postcode":"98391",
    "sg:province":"WA",
    "sg:tags":[
        "operation",
        "racing",
        "or"
    ],
    "wof:name":"Rnr Stables",
    "wof:placetype":"venue"
},
  "geometry": {"coordinates":[-122.183843,47.102003],"type":"Point"}
}