{
  "type": "Feature",
  "properties": {
    "addr:full":"1315 3rd St Wenatchee WA 98801",
    "addr:housenumber":"1315",
    "addr:postcode":"98801",
    "addr:street":"3Rd St",
    "iso:country":"US",
    "sg:address":"1315 3rd St",
    "sg:city":"Wenatchee",
    "sg:classifiers":[
        {
            "category":"Manufacturing",
            "subcategory":"Tools & Machinery",
            "type":"Manufacturing & Wholesale Goods"
        }
    ],
    "sg:phone":"+1 509 662 9637",
    "sg:postcode":"98801",
    "sg:province":"WA",
    "sg:tags":[
        "machine",
        "mfg"
    ],
    "wof:name":"Cnc Solutions Inc",
    "wof:placetype":"venue"
},
  "geometry": {"coordinates":[-120.33311999999999,47.427942],"type":"Point"}
}