{
  "type": "Feature",
  "properties": {
    "addr:full":"1808 SE 352nd Ave Washougal WA 98671",
    "addr:housenumber":"1808",
    "addr:postcode":"98671",
    "addr:street":"Se 352Nd Ave",
    "iso:country":"US",
    "sg:address":"1808 SE 352nd Ave",
    "sg:city":"Washougal",
    "sg:classifiers":[
        {
            "category":"Government",
            "subcategory":"Fire Station",
            "type":"Public Place"
        }
    ],
    "sg:phone":"+1 360 835 7731",
    "sg:postcode":"98671",
    "sg:province":"WA",
    "sg:tags":[
        "county",
        "protection"
    ],
    "wof:name":"Clark County Fire Dept",
    "wof:placetype":"venue"
},
  "geometry": {"coordinates":[-122.311379,45.608645],"type":"Point"}
}