{
  "type": "Feature",
  "properties": {
    "addr:full":"2190 Black Point Rd Brinnon WA 98320",
    "addr:housenumber":"2190",
    "addr:postcode":"98320",
    "addr:street":"Black Point Rd",
    "iso:country":"US",
    "sg:address":"2190 Black Point Rd",
    "sg:city":"Brinnon",
    "sg:classifiers":[
        {
            "category":"Farming",
            "subcategory":"Fish & Marine Products",
            "type":"Manufacturing & Wholesale Goods"
        }
    ],
    "sg:phone":"+1 360 796 4572",
    "sg:postcode":"98320",
    "sg:province":"WA",
    "sg:tags":[
        "fishing"
    ],
    "wof:name":"Fv Ocean Spirit",
    "wof:placetype":"venue"
},
  "geometry": {"coordinates":[-122.907563,47.656193],"type":"Point"}
}