{
  "type": "Feature",
  "properties": {
    "addr:full":"15517 Fair Oaks Dr S Spanaway WA 98387",
    "addr:housenumber":"15517",
    "addr:postcode":"98387",
    "addr:street":"Fair Oaks Dr S Spanaway",
    "iso:country":"US",
    "sg:address":"15517 Fair Oaks Dr S",
    "sg:city":"Spanaway",
    "sg:classifiers":[
        {
            "category":"Building & Trades",
            "subcategory":"Landscaping Services",
            "type":"Services"
        }
    ],
    "sg:phone":"+1 253 219 6682",
    "sg:postcode":"98387",
    "sg:province":"WA",
    "sg:website":"www.goodrowslandscaping.com",
    "wof:name":"Goodrows Landscaping",
    "wof:placetype":"venue"
},
  "geometry": {"coordinates":[-122.460793,47.115673],"type":"Point"}
}