{
  "type": "Feature",
  "properties": {
    "iso:country":"US",
    "sg:address":"2212 Queen Anne Ave N",
    "sg:city":"Seattle",
    "sg:classifiers":[
        {
            "category":"Professional",
            "subcategory":"Art Services",
            "type":"Services"
        }
    ],
    "sg:phone":"+1 206 216 0278",
    "sg:postcode":"98109",
    "sg:province":"WA",
    "sg:tags":[
        "graphic",
        "design"
    ],
    "wof:name":"Pixelube",
    "wof:placetype":"venue"
},
  "geometry": {"coordinates":[-122.35684000000001,47.639519],"type":"Point"}
}