{
  "type": "Feature",
  "properties": {
    "addr:full":"5025 N Road 68 Pasco WA 99301",
    "addr:housenumber":"5025",
    "addr:postcode":"99301",
    "addr:street":"N Road 68",
    "iso:country":"US",
    "sg:address":"5025 N Road 68",
    "sg:city":"Pasco",
    "sg:classifiers":[
        {
            "category":"Professional",
            "type":"Services"
        },
        {
            "category":"Professional",
            "subcategory":"Business Services",
            "type":"Services"
        },
        {
            "category":"Professional",
            "subcategory":"Printing & Photocopies",
            "type":"Services"
        },
        {
            "category":"Government",
            "subcategory":"Post Office",
            "type":"Public Place"
        },
        {
            "category":"Organizations",
            "subcategory":"Professional Association",
            "type":"Services"
        }
    ],
    "sg:phone":"+1 509 545 1807",
    "sg:postcode":"99301",
    "sg:province":"WA",
    "sg:tags":[
        "delivery",
        "coach",
        "courier",
        "corporation",
        "duplicating",
        "shipping",
        "mailbox-rental",
        "packaging",
        "copying",
        "consultant",
        "seals-notary",
        "mail",
        "receiving"
    ],
    "sg:website":"http://www.postnet.com/franchisee/index.asp?storenumber=WA129",
    "wof:name":"PostNet - Printing & Copy Services",
    "wof:placetype":"venue"
},
  "geometry": {"coordinates":[-119.185333,46.27469],"type":"Point"}
}