{
  "type": "Feature",
  "properties": {
    "addr:full":"8150 Rd 23 NE Soap Lake WA 98851",
    "addr:postcode":"8150;98851",
    "addr:street":"Rd 23 Ne Soap",
    "iso:country":"US",
    "sg:address":"8150 Rd 23 NE",
    "sg:city":"Soap Lake",
    "sg:classifiers":[
        {
            "category":"Freight",
            "type":"Transportation"
        }
    ],
    "sg:phone":"+1 509 345 2427",
    "sg:postcode":"98851",
    "sg:province":"WA",
    "sg:tags":[
        "warehouse",
        "self",
        "storage"
    ],
    "wof:name":"Kobata Sam Warehouse",
    "wof:placetype":"venue"
},
  "geometry": {"coordinates":[-119.30877,47.425032],"type":"Point"}
}