{
  "type": "Feature",
  "properties": {
    "addr:full":"6897 NE Silver Springs Ln Poulsbo WA 98370",
    "addr:housenumber":"6897",
    "addr:postcode":"98370",
    "addr:street":"Ne Silver Springs Ln",
    "iso:country":"US",
    "sg:address":"6897 NE Silver Springs Ln",
    "sg:city":"Poulsbo",
    "sg:classifiers":[
        {
            "category":"Professional",
            "subcategory":"Advertising",
            "type":"Services"
        }
    ],
    "sg:phone":"+1 360 779 9157",
    "sg:postcode":"98370",
    "sg:province":"WA",
    "wof:name":"Big Air Productions",
    "wof:placetype":"venue"
},
  "geometry": {"coordinates":[-122.563097,47.77577],"type":"Point"}
}