{
  "type": "Feature",
  "properties": {
    "addr:full":"12215 SE 1st St Vancouver WA 98684",
    "addr:housenumber":"12215",
    "addr:postcode":"98684",
    "addr:street":"Se 1St St",
    "iso:country":"US",
    "sg:address":"12215 SE 1st St",
    "sg:city":"Vancouver",
    "sg:classifiers":[
        {
            "category":"Shopping",
            "subcategory":"Bicycles & Sporting Goods",
            "type":"Retail Goods"
        }
    ],
    "sg:phone":"+1 360 883 3838",
    "sg:postcode":"98684",
    "sg:province":"WA",
    "wof:name":"Clark County Gun Repair",
    "wof:placetype":"venue"
},
  "geometry": {"coordinates":[-122.54608399999999,45.621163],"type":"Point"}
}