{
  "type": "Feature",
  "properties": {
    "addr:full":"5650 Rd 3 NE Moses Lake WA 98837",
    "addr:postcode":"5650;98837",
    "addr:street":"Rd 3 Ne",
    "iso:country":"US",
    "sg:address":"5650 Rd 3 NE",
    "sg:city":"Moses Lake",
    "sg:classifiers":[
        {
            "category":"Building & Trades",
            "subcategory":"Construction",
            "type":"Services"
        }
    ],
    "sg:phone":"+1 509 765 9418",
    "sg:postcode":"98837",
    "sg:province":"WA",
    "sg:tags":[
        "agricultural",
        "general",
        "storage",
        "contractor"
    ],
    "wof:name":"J Noyola Construction Inc",
    "wof:placetype":"venue"
},
  "geometry": {"coordinates":[-119.371475,47.13164],"type":"Point"}
}