{
  "type": "Feature",
  "properties": {
    "addr:full":"6301 Preston Fall City Rd SE Fall City WA 98024",
    "addr:housenumber":"6301",
    "addr:postcode":"98024",
    "addr:street":"Preston Fall City Rd Se",
    "iso:country":"US",
    "sg:address":"6301 Preston Fall City Rd SE",
    "sg:city":"Fall City",
    "sg:classifiers":[
        {
            "category":"Building & Trades",
            "subcategory":"Construction",
            "type":"Services"
        }
    ],
    "sg:phone":"+1 425 222 6280",
    "sg:postcode":"98024",
    "sg:province":"WA",
    "sg:tags":[
        "house",
        "speculative",
        "builder",
        "family"
    ],
    "wof:name":"Beckmann Homes Inc",
    "wof:placetype":"venue"
},
  "geometry": {"coordinates":[-121.903288,47.544948],"type":"Point"}
}