{
  "type": "Feature",
  "properties": {
    "addr:full":"1206 Palomino Dr SE Tumwater WA 98501",
    "addr:housenumber":"1206",
    "addr:postcode":"98501",
    "addr:street":"Palomino Dr Se",
    "iso:country":"US",
    "sg:address":"1206 Palomino Dr SE",
    "sg:city":"Tumwater",
    "sg:classifiers":[
        {
            "category":"Professional",
            "subcategory":"Lawyer & Legal Services",
            "type":"Services"
        }
    ],
    "sg:phone":"+1 360 867 9390",
    "sg:postcode":"98501",
    "sg:province":"WA",
    "sg:tags":[
        "attorney"
    ],
    "wof:name":"Craig W Hanson",
    "wof:placetype":"venue"
},
  "geometry": {"coordinates":[-122.884508,47.002215],"type":"Point"}
}