{
  "type": "Feature",
  "properties": {
    "addr:full":"3138 Overhulse Rd NW Olympia WA 98502",
    "addr:housenumber":"3138",
    "addr:postcode":"olympia wa 98502",
    "addr:street":"Overhulse Rd Nw",
    "iso:country":"US",
    "sg:address":"3138 Overhulse Rd NW",
    "sg:city":"Olympia",
    "sg:classifiers":[
        {
            "category":"Wholesale",
            "subcategory":"Stationery",
            "type":"Manufacturing & Wholesale Goods"
        }
    ],
    "sg:phone":"+1 360 866 8384",
    "sg:postcode":"98502",
    "sg:province":"WA",
    "sg:tags":[
        "supply"
    ],
    "wof:name":"Jr Hunters Forms",
    "wof:placetype":"venue"
},
  "geometry": {"coordinates":[-122.970446,47.077538],"type":"Point"}
}