{
  "type": "Feature",
  "properties": {
    "addr:full":"907 Lovell Ave NW Bainbridge Island WA 98110",
    "addr:housenumber":"907",
    "addr:postcode":"98110",
    "addr:street":"Lovell Ave Nw",
    "iso:country":"US",
    "sg:address":"907 Lovell Ave NW",
    "sg:city":"Bainbridge Island",
    "sg:classifiers":[
        {
            "category":"Health Services",
            "subcategory":"Doctor",
            "type":"Services"
        }
    ],
    "sg:phone":"+1 206 780 0677",
    "sg:postcode":"98110",
    "sg:province":"WA",
    "sg:tags":[
        "psychiatrist"
    ],
    "wof:name":"Walker F D MD",
    "wof:placetype":"venue"
},
  "geometry": {"coordinates":[-122.52600099999999,47.632599],"type":"Point"}
}