{
  "type": "Feature",
  "properties": {
    "iso:country":"US",
    "sg:address":"3620 N Nevada St",
    "sg:city":"Spokane",
    "sg:classifiers":[
        {
            "category":"Retail",
            "subcategory":"Auto Repair",
            "type":"Services"
        }
    ],
    "sg:phone":"+1 509 483 3200",
    "sg:postcode":"99207",
    "sg:province":"WA",
    "sg:tags":[
        "exchanging",
        "engine"
    ],
    "wof:name":"Import Auto Svc",
    "wof:placetype":"venue"
},
  "geometry": {"coordinates":[-117.39507,47.691023],"type":"Point"}
}