{
  "type": "Feature",
  "properties": {
    "addr:full":"505 SE 103rd Ave Vancouver WA 98664",
    "addr:housenumber":"505",
    "addr:postcode":"98664",
    "addr:street":"Se 103Rd Ave",
    "iso:country":"US",
    "sg:address":"505 SE 103rd Ave",
    "sg:city":"Vancouver",
    "sg:classifiers":[
        {
            "category":"Social Services",
            "subcategory":"Child Care",
            "type":"Services"
        }
    ],
    "sg:phone":"+1 360 254 0725",
    "sg:postcode":"98664",
    "sg:province":"WA",
    "sg:tags":[
        "day"
    ],
    "wof:name":"Peradise Daycare",
    "wof:placetype":"venue"
},
  "geometry": {"coordinates":[-122.566928,45.616056],"type":"Point"}
}