{
  "type": "Feature",
  "properties": {
    "addr:full":"1200 Franklin St Vancouver WA 98660",
    "addr:housenumber":"1200",
    "addr:postcode":"98660",
    "addr:street":"Franklin St",
    "iso:country":"US",
    "sg:address":"1200 Franklin St",
    "sg:city":"Vancouver",
    "sg:classifiers":[
        {
            "category":"Government",
            "subcategory":"Office",
            "type":"Public Place"
        }
    ],
    "sg:phone":"+1 360 397 2315",
    "sg:postcode":"98660",
    "sg:province":"WA",
    "wof:name":"Honorable Roger A Bennett",
    "wof:placetype":"venue"
},
  "geometry": {"coordinates":[-122.677064,45.631073],"type":"Point"}
}