{
  "type": "Feature",
  "properties": {
    "addr:full":"518 E Wheeler Rd Moses Lake WA 98837",
    "addr:housenumber":"518",
    "addr:postcode":"98837",
    "addr:street":"E Wheeler Rd",
    "iso:country":"US",
    "sg:address":"518 E Wheeler Rd",
    "sg:city":"Moses Lake",
    "sg:classifiers":[
        {
            "category":"Bars & Pubs",
            "type":"Food & Drink"
        }
    ],
    "sg:phone":"+1 509 765 3942",
    "sg:postcode":"98837",
    "sg:province":"WA",
    "sg:tags":[
        "drinking"
    ],
    "wof:name":"Rams",
    "wof:placetype":"venue"
},
  "geometry": {"coordinates":[-119.268998,47.131156],"type":"Point"}
}