{
  "type": "Feature",
  "properties": {
    "addr:full":"5415 Rainier Ave S Seattle WA 98118",
    "addr:housenumber":"5415",
    "addr:postcode":"98118",
    "addr:street":"Rainier Ave S",
    "iso:country":"US",
    "sg:address":"5415 Rainier Ave S",
    "sg:city":"Seattle",
    "sg:classifiers":[
        {
            "category":"Shopping",
            "subcategory":"Pharmacy",
            "type":"Retail Goods"
        }
    ],
    "sg:phone":"+1 206 722 2228",
    "sg:postcode":"98118",
    "sg:province":"WA",
    "sg:tags":[
        "drugstore"
    ],
    "wof:name":"Rainier Pharmacy Home Health Care - CLOSED",
    "wof:placetype":"venue"
},
  "geometry": {"coordinates":[-122.27800000000001,47.552799],"type":"Point"}
}