{
  "type": "Feature",
  "properties": {
    "addr:full":"2646 W Newton St Seattle WA 98199",
    "addr:housenumber":"2646",
    "addr:postcode":"98199",
    "addr:street":"W Newton St",
    "iso:country":"US",
    "sg:address":"2646 W Newton St",
    "sg:city":"Seattle",
    "sg:classifiers":[
        {
            "category":"Wholesale",
            "subcategory":"Construction Materials",
            "type":"Manufacturing & Wholesale Goods"
        }
    ],
    "sg:phone":"+1 206 691 3448",
    "sg:postcode":"98199",
    "sg:province":"WA",
    "wof:name":"Georgia-Pacific",
    "wof:placetype":"venue"
},
  "geometry": {"coordinates":[-122.39261999999999,47.637052],"type":"Point"}
}