{
  "type": "Feature",
  "properties": {
    "addr:full":"3711 Pacific Ave Tacoma WA 98418",
    "addr:housenumber":"3711",
    "addr:postcode":"98418",
    "addr:street":"Pacific Ave",
    "iso:country":"US",
    "sg:address":"3711 Pacific Ave",
    "sg:city":"Tacoma",
    "sg:classifiers":[
        {
            "category":"Health Services",
            "subcategory":"Health Practitioner",
            "type":"Services"
        }
    ],
    "sg:phone":"+1 253 475 4415",
    "sg:postcode":"98418",
    "sg:province":"WA",
    "sg:tags":[
        "therapist",
        "physical"
    ],
    "wof:name":"Soundview Physical Therapy Inc",
    "wof:placetype":"venue"
},
  "geometry": {"coordinates":[-122.433971,47.224027],"type":"Point"}
}