{
  "type": "Feature",
  "properties": {
    "addr:full":"14805 NE 39th St Vancouver WA 98682",
    "addr:housenumber":"14805",
    "addr:postcode":"98682",
    "addr:street":"Ne 39Th St",
    "iso:country":"US",
    "sg:address":"14805 NE 39th St",
    "sg:city":"Vancouver",
    "sg:classifiers":[
        {
            "category":"Shopping",
            "subcategory":"Antiques",
            "type":"Retail Goods"
        }
    ],
    "sg:phone":"+1 360 604 0080",
    "sg:postcode":"98682",
    "sg:province":"WA",
    "wof:name":"Far Star Website Design",
    "wof:placetype":"venue"
},
  "geometry": {"coordinates":[-122.519899,45.650142],"type":"Point"}
}