{
  "type": "Feature",
  "properties": {
    "addr:full":"6113 176th St E Puyallup WA 98375",
    "addr:housenumber":"6113",
    "addr:postcode":"98375",
    "addr:street":"176Th St E",
    "iso:country":"US",
    "sg:address":"6113 176th St E",
    "sg:city":"Puyallup",
    "sg:classifiers":[
        {
            "category":"Manufacturing",
            "subcategory":"Metals",
            "type":"Manufacturing & Wholesale Goods"
        }
    ],
    "sg:phone":"+1 253 847 3720",
    "sg:postcode":"98375",
    "sg:province":"WA",
    "sg:tags":[
        "steel"
    ],
    "wof:name":"Astro Steel",
    "wof:placetype":"venue"
},
  "geometry": {"coordinates":[-122.348528,47.096556],"type":"Point"}
}