{
  "type": "Feature",
  "properties": {
    "addr:full":"52 Engh Rd Omak WA 98841",
    "addr:housenumber":"52",
    "addr:postcode":"98841",
    "addr:street":"Engh Rd",
    "iso:country":"US",
    "sg:address":"52 Engh Rd",
    "sg:city":"Omak",
    "sg:classifiers":[
        {
            "category":"Food & Beverages",
            "subcategory":"Bakery",
            "type":"Retail Goods"
        }
    ],
    "sg:phone":"+1 509 826 2434",
    "sg:postcode":"98841",
    "sg:province":"WA",
    "wof:name":"Oomingmaks",
    "wof:placetype":"venue"
},
  "geometry": {"coordinates":[-119.496537,48.416616],"type":"Point"}
}