{
  "type": "Feature",
  "properties": {
    "addr:full":"5003 Mockingbird Ct Richland WA 99353",
    "addr:housenumber":"5003",
    "addr:postcode":"99353",
    "addr:street":"Mockingbird Ct",
    "iso:country":"US",
    "sg:address":"5003 Mockingbird Ct",
    "sg:city":"Richland",
    "sg:classifiers":[
        {
            "category":"Education",
            "subcategory":"Special Training",
            "type":"Public Place"
        }
    ],
    "sg:phone":"+1 509 967 3071",
    "sg:postcode":"99353",
    "sg:province":"WA",
    "wof:name":"Judy Lambert",
    "wof:placetype":"venue"
},
  "geometry": {"coordinates":[-119.35602900000001,46.276464],"type":"Point"}
}