{
  "type": "Feature",
  "properties": {
    "addr:full":"17800 Glade Rd Mabton WA 98935",
    "addr:housenumber":"17800",
    "addr:postcode":"98935",
    "addr:street":"Glade Rd",
    "iso:country":"US",
    "sg:address":"17800 Glade Rd",
    "sg:city":"Mabton",
    "sg:classifiers":[
        {
            "category":"Building & Trades",
            "subcategory":"Landscaping Services",
            "type":"Services"
        }
    ],
    "sg:phone":"+1 509 896 2474",
    "sg:postcode":"98935",
    "sg:province":"WA",
    "sg:tags":[
        "tree"
    ],
    "wof:name":"Quartz Creek Enhancement",
    "wof:placetype":"venue"
},
  "geometry": {"coordinates":[-120.20738900000001,46.0698],"type":"Point"}
}