{
  "type": "Feature",
  "properties": {
    "addr:full":"46319 244th Ave SE Enumclaw WA 98022",
    "addr:housenumber":"46319",
    "addr:postcode":"98022",
    "addr:street":"244Th Ave Se",
    "iso:country":"US",
    "sg:address":"46319 244th Ave SE",
    "sg:city":"Enumclaw",
    "sg:classifiers":[
        {
            "category":"Farming",
            "subcategory":"Livestock Farm",
            "type":"Manufacturing & Wholesale Goods"
        }
    ],
    "sg:phone":"+1 360 825 2082",
    "sg:postcode":"98022",
    "sg:province":"WA",
    "sg:tags":[
        "animal",
        "general"
    ],
    "wof:name":"Berens Ranch",
    "wof:placetype":"venue"
},
  "geometry": {"coordinates":[-122.01644400000001,47.185121],"type":"Point"}
}