{
  "type": "Feature",
  "properties": {
    "addr:full":"9504 Lowell Snohomish River Rd Snohomish WA 98296",
    "addr:housenumber":"9504",
    "addr:postcode":"98296",
    "addr:street":"Lowell Snohomish River Rd",
    "iso:country":"US",
    "sg:address":"9504 Lowell Snohomish River Rd",
    "sg:city":"Snohomish",
    "sg:classifiers":[
        {
            "category":"Building & Trades",
            "subcategory":"Construction",
            "type":"Services"
        }
    ],
    "sg:phone":"+1 360 568 8925",
    "sg:postcode":"98296",
    "sg:province":"WA",
    "sg:tags":[
        "hanging",
        "painter",
        "contractor"
    ],
    "wof:name":"Northwest Painting Service",
    "wof:placetype":"venue"
},
  "geometry": {"coordinates":[-122.103362,47.91068],"type":"Point"}
}