{
  "type": "Feature",
  "properties": {
    "addr:full":"3618 SW Alaska St Seattle WA 98126",
    "addr:housenumber":"3618",
    "addr:postcode":"98126",
    "addr:street":"Sw;St",
    "iso:country":"US",
    "sg:address":"3618 SW Alaska St",
    "sg:city":"Seattle",
    "sg:classifiers":[
        {
            "category":"Organizations",
            "subcategory":"Community Association",
            "type":"Services"
        }
    ],
    "sg:phone":"+1 206 932 9696",
    "sg:postcode":"98126",
    "sg:province":"WA",
    "sg:tags":[
        "military"
    ],
    "wof:name":"American Legion",
    "wof:placetype":"venue"
},
  "geometry": {"coordinates":[-122.378609,47.561152],"type":"Point"}
}