{
  "type": "Feature",
  "properties": {
    "addr:full":"6556 Palatine Ave N Seattle WA 98103",
    "addr:housenumber":"6556",
    "addr:postcode":"98103",
    "addr:street":"Palatine Ave N",
    "iso:country":"US",
    "sg:address":"6556 Palatine Ave N",
    "sg:city":"Seattle",
    "sg:classifiers":[
        {
            "category":"Organizations",
            "subcategory":"Community Association",
            "type":"Services"
        }
    ],
    "sg:phone":"+1 206 782 0505",
    "sg:postcode":"98103",
    "sg:province":"WA",
    "sg:tags":[
        "festival"
    ],
    "wof:name":"Seattle Folklore Society Inc",
    "wof:placetype":"venue"
},
  "geometry": {"coordinates":[-122.35633900000001,47.677277],"type":"Point"}
}