{
  "type": "Feature",
  "properties": {
    "addr:full":"4604 148th Ave NE Redmond WA 98052",
    "addr:housenumber":"4604",
    "addr:postcode":"98052",
    "addr:street":"148Th Ave Ne",
    "iso:country":"US",
    "sg:address":"4604 148th Ave NE",
    "sg:city":"Redmond",
    "sg:classifiers":[
        {
            "category":"Manufacturing",
            "subcategory":"Metals",
            "type":"Manufacturing & Wholesale Goods"
        }
    ],
    "sg:phone":"+1 425 861 9558",
    "sg:postcode":"98052",
    "sg:province":"WA",
    "sg:tags":[
        "steel",
        "detailers",
        "mfg",
        "architectural",
        "fabrication",
        "structural"
    ],
    "sg:website":"http://www.alliedsteelfab.com",
    "wof:name":"Allied Steel Fabricators Inc",
    "wof:placetype":"venue"
},
  "geometry": {"coordinates":[-122.14318900000001,47.652336],"type":"Point"}
}