{
  "type": "Feature",
  "properties": {
    "addr:full":"720 18th Ave E Seattle WA 98112",
    "addr:housenumber":"720",
    "addr:postcode":"98112",
    "addr:street":"18Th Ave E",
    "iso:country":"US",
    "sg:address":"720 18th Ave E",
    "sg:city":"Seattle",
    "sg:classifiers":[
        {
            "category":"Social Services",
            "subcategory":"Child Care",
            "type":"Services"
        },
        {
            "category":"Education",
            "subcategory":"Preschool",
            "type":"Public Place"
        },
        {
            "category":"Education",
            "subcategory":"School",
            "type":"Public Place"
        }
    ],
    "sg:phone":"+1 206 325 0497",
    "sg:postcode":"98112",
    "sg:province":"WA",
    "sg:tags":[
        "elementary",
        "private",
        "k-"
    ],
    "sg:website":"www.montessorischoolofseattle.com",
    "wof:name":"Montessori School of Seattle",
    "wof:placetype":"venue"
},
  "geometry": {"coordinates":[-122.307999,47.6255],"type":"Point"}
}