{
  "type": "Feature",
  "properties": {
    "addr:full":"23825 35th Ave W Brier WA 98036",
    "addr:housenumber":"23825",
    "addr:postcode":"98036",
    "addr:street":"35Th Ave W Brier",
    "iso:country":"US",
    "sg:address":"23825 35th Ave W",
    "sg:city":"Brier",
    "sg:classifiers":[
        {
            "category":"Building & Trades",
            "subcategory":"Landscaping Services",
            "type":"Services"
        }
    ],
    "sg:phone":"+1 425 489 3435",
    "sg:postcode":"98036",
    "sg:province":"WA",
    "sg:tags":[
        "landscape",
        "contractor"
    ],
    "wof:name":"Evergreen Landscape Mntnc",
    "wof:placetype":"venue"
},
  "geometry": {"coordinates":[-122.280467,47.782379],"type":"Point"}
}