{
  "type": "Feature",
  "properties": {
    "iso:country":"US",
    "sg:address":"1433 NW 64th St",
    "sg:city":"Seattle",
    "sg:classifiers":[
        {
            "category":"Wholesale",
            "subcategory":"Jewelry",
            "type":"Manufacturing & Wholesale Goods"
        }
    ],
    "sg:phone":"+1 206 783 9038",
    "sg:postcode":"98107",
    "sg:province":"WA",
    "sg:tags":[
        "stone"
    ],
    "wof:name":"Devine Designs",
    "wof:placetype":"venue"
},
  "geometry": {"coordinates":[-122.375754,47.675202],"type":"Point"}
}