{
  "type": "Feature",
  "properties": {
    "addr:full":"6812 140th Pl NE Redmond WA 98052",
    "addr:housenumber":"6812",
    "addr:postcode":"98052",
    "addr:street":"140Th Pl Ne",
    "iso:country":"US",
    "sg:address":"6812 140th Pl NE",
    "sg:city":"Redmond",
    "sg:classifiers":[
        {
            "category":"Professional",
            "subcategory":"Management & Consulting",
            "type":"Services"
        }
    ],
    "sg:phone":"+1 425 883 2955",
    "sg:postcode":"98052",
    "sg:province":"WA",
    "sg:tags":[
        "consultant",
        "safety"
    ],
    "wof:name":"Emerald Bay Consulting",
    "wof:placetype":"venue"
},
  "geometry": {"coordinates":[-122.152406,47.66523],"type":"Point"}
}