{
  "type": "Feature",
  "properties": {
    "addr:full":"2600 2nd Ave N Seattle WA 98109",
    "addr:housenumber":"2600",
    "addr:postcode":"98109",
    "addr:street":"2Nd Ave N",
    "iso:country":"US",
    "sg:address":"2600 2nd Ave N",
    "sg:city":"Seattle",
    "sg:classifiers":[
        {
            "category":"Building & Trades",
            "subcategory":"Locksmith",
            "type":"Services"
        }
    ],
    "sg:phone":"+1 206 494 9212",
    "sg:postcode":"98109",
    "sg:province":"WA",
    "sg:tags":[
        "key"
    ],
    "wof:name":"A Locksmith 24 Hr Emerg",
    "wof:placetype":"venue"
},
  "geometry": {"coordinates":[-122.353667,47.643225],"type":"Point"}
}