{
  "type": "Feature",
  "properties": {
    "addr:full":"200 SE 7th Cir Battle Ground WA 98604",
    "addr:housenumber":"200",
    "addr:postcode":"98604",
    "addr:street":"Se 7Th Cir",
    "iso:country":"US",
    "sg:address":"200 SE 7th Cir",
    "sg:city":"Battle Ground",
    "sg:classifiers":[
        {
            "category":"Building & Trades",
            "subcategory":"Plumbing",
            "type":"Services"
        }
    ],
    "sg:phone":"+1 360 904 8754",
    "sg:postcode":"98604",
    "sg:province":"WA",
    "sg:tags":[
        "plumbing",
        "heating",
        "air"
    ],
    "wof:name":"Watercourse Irrigation Inc",
    "wof:placetype":"venue"
},
  "geometry": {"coordinates":[-122.53512600000001,45.775199],"type":"Point"}
}