{
  "type": "Feature",
  "properties": {
    "addr:full":"11314 NE 50th Ave Vancouver WA 98686",
    "addr:housenumber":"11314",
    "addr:postcode":"98686",
    "addr:street":"Ne 50Th Ave",
    "iso:country":"US",
    "sg:address":"11314 NE 50th Ave",
    "sg:city":"Vancouver",
    "sg:classifiers":[
        {
            "category":"Manufacturing",
            "subcategory":"Tools & Machinery",
            "type":"Manufacturing & Wholesale Goods"
        }
    ],
    "sg:phone":"+1 360 574 5303",
    "sg:postcode":"98686",
    "sg:province":"WA",
    "sg:tags":[
        "machine",
        "shop"
    ],
    "wof:name":"Pleasant Valley Machine",
    "wof:placetype":"venue"
},
  "geometry": {"coordinates":[-122.620565,45.704039],"type":"Point"}
}