{
  "type": "Feature",
  "properties": {
    "addr:full":"1022 Industry Dr Tukwila WA 98188",
    "addr:housenumber":"1022",
    "addr:postcode":"98188",
    "addr:street":"Industry Dr",
    "iso:country":"US",
    "sg:address":"1022 Industry Dr",
    "sg:city":"Tukwila",
    "sg:classifiers":[
        {
            "category":"Wholesale",
            "subcategory":"Office Equipment",
            "type":"Manufacturing & Wholesale Goods"
        },
        {
            "category":"Professional",
            "subcategory":"Art Services",
            "type":"Services"
        },
        {
            "category":"Professional",
            "subcategory":"Printing & Photocopies",
            "type":"Services"
        },
        {
            "category":"Shopping",
            "subcategory":"Computers & Home Electronics",
            "type":"Retail Goods"
        }
    ],
    "sg:phone":"+1 206 575 4337",
    "sg:postcode":"98188",
    "sg:province":"WA",
    "sg:tags":[
        "scanning",
        "graphic",
        "supply",
        "services-commercial",
        "designer",
        "plotting",
        "printer"
    ],
    "wof:name":"Glacier Printing & Graphics",
    "wof:placetype":"venue"
},
  "geometry": {"coordinates":[-122.24844400000001,47.4485],"type":"Point"}
}