{
  "type": "Feature",
  "properties": {
    "addr:full":"112 Main St Vancouver WA 98663",
    "addr:housenumber":"112",
    "addr:postcode":"98663",
    "addr:street":"Main St",
    "iso:country":"US",
    "sg:address":"112 Main St",
    "sg:city":"Vancouver",
    "sg:classifiers":[
        {
            "category":"Manufacturing",
            "subcategory":"Food",
            "type":"Manufacturing & Wholesale Goods"
        },
        {
            "category":"Coffee & Tea",
            "type":"Food & Drink"
        },
        {
            "category":"Food & Beverages",
            "subcategory":"Specialty",
            "type":"Retail Goods"
        }
    ],
    "sg:phone":"+1 360 887 9018",
    "sg:postcode":"98663",
    "sg:province":"WA",
    "sg:tags":[
        "product",
        "health",
        "spices-wholesale",
        "diet",
        "manufacturer"
    ],
    "wof:name":"Myrtles Teahouse & Herbery",
    "wof:placetype":"venue"
},
  "geometry": {"coordinates":[-122.67025,45.642561],"type":"Point"}
}