{
  "type": "Feature",
  "properties": {
    "addr:full":"1615 SW Cambridge St Seattle WA 98106",
    "addr:housenumber":"1615",
    "addr:postcode":"98106",
    "addr:street":"Sw Cambridge St",
    "iso:country":"US",
    "sg:address":"1615 SW Cambridge St",
    "sg:city":"Seattle",
    "sg:classifiers":[
        {
            "category":"Professional",
            "subcategory":"Lawyer & Legal Services",
            "type":"Services"
        }
    ],
    "sg:phone":"+1 206 767 9814",
    "sg:postcode":"98106",
    "sg:province":"WA",
    "sg:tags":[
        "attorney"
    ],
    "wof:name":"Edward L Douglas",
    "wof:placetype":"venue"
},
  "geometry": {"coordinates":[-122.356362,47.51912],"type":"Point"}
}