{
  "type": "Feature",
  "properties": {
    "addr:full":"17414 156th Pl SE Renton WA 98058",
    "addr:housenumber":"17414",
    "addr:postcode":"98058",
    "addr:street":"156Th Pl Se",
    "iso:country":"US",
    "sg:address":"17414 156th Pl SE",
    "sg:city":"Renton",
    "sg:classifiers":[
        {
            "category":"Organizations",
            "subcategory":"Membership Organization",
            "type":"Services"
        }
    ],
    "sg:phone":"+1 425 687 8430",
    "sg:postcode":"98058",
    "sg:province":"WA",
    "wof:name":"Friends of Jamaica Seattl",
    "wof:placetype":"venue"
},
  "geometry": {"coordinates":[-122.13169499999999,47.446139],"type":"Point"}
}