{
  "type": "Feature",
  "properties": {
    "addr:full":"810 Winslow Ave Richland WA 99352",
    "addr:housenumber":"810",
    "addr:postcode":"99352",
    "addr:street":"Winslow Ave",
    "iso:country":"US",
    "sg:address":"810 Winslow Ave",
    "sg:city":"Richland",
    "sg:classifiers":[
        {
            "category":"Social Services",
            "subcategory":"Child Care",
            "type":"Services"
        }
    ],
    "sg:phone":"+1 509 946 5042",
    "sg:postcode":"99352",
    "sg:province":"WA",
    "sg:tags":[
        "day"
    ],
    "wof:name":"Scott Leola Louise",
    "wof:placetype":"venue"
},
  "geometry": {"coordinates":[-119.296606,46.27742],"type":"Point"}
}