{
  "type": "Feature",
  "properties": {
    "iso:country":"US",
    "sg:address":"7202 E Sprague Ave",
    "sg:city":"Spokane Valley",
    "sg:classifiers":[
        {
            "category":"Professional",
            "subcategory":"Lawyer & Legal Services",
            "type":"Services"
        }
    ],
    "sg:phone":"+1 509 924 2590",
    "sg:postcode":"99212",
    "sg:province":"WA",
    "sg:tags":[
        "attorney"
    ],
    "wof:name":"Sara L Tingley",
    "wof:placetype":"venue"
},
  "geometry": {"coordinates":[-117.30790500000001,47.656828],"type":"Point"}
}