{
  "type": "Feature",
  "properties": {
    "addr:full":"49 John Day Dam Rd Goldendale WA 98620",
    "addr:housenumber":"49",
    "addr:postcode":"98620",
    "addr:street":"John;Dam Rd",
    "iso:country":"US",
    "sg:address":"49 John Day Dam Rd",
    "sg:city":"Goldendale",
    "sg:classifiers":[
        {
            "category":"Professional",
            "subcategory":"Research",
            "type":"Services"
        }
    ],
    "sg:phone":"+1 509 773 2100",
    "sg:postcode":"98620",
    "sg:province":"WA",
    "sg:tags":[
        "laboratory"
    ],
    "wof:name":"Cascade Solutions",
    "wof:placetype":"venue"
},
  "geometry": {"coordinates":[-120.69439300000001,45.731637],"type":"Point"}
}