{
  "type": "Feature",
  "properties": {
    "addr:full":"7490 Naneum Rd Ellensburg WA 98926",
    "addr:housenumber":"7490",
    "addr:postcode":"98926",
    "addr:street":"Naneum Rd",
    "iso:country":"US",
    "sg:address":"7490 Naneum Rd",
    "sg:city":"Ellensburg",
    "sg:classifiers":[
        {
            "category":"Retail",
            "subcategory":"Animal Services",
            "type":"Services"
        }
    ],
    "sg:phone":"+1 509 925 9431",
    "sg:postcode":"98926",
    "sg:province":"WA",
    "wof:name":"Beards Rodeo Company LLC",
    "wof:placetype":"venue"
},
  "geometry": {"coordinates":[-120.46754199999999,47.066413],"type":"Point"}
}