{
  "type": "Feature",
  "properties": {
    "addr:full":"102 Military Rd S Spanaway WA 98387",
    "addr:housenumber":"102",
    "addr:postcode":"98387",
    "addr:street":"Military Rd",
    "iso:country":"US",
    "sg:address":"102 Military Rd S",
    "sg:city":"Spanaway",
    "sg:classifiers":[
        {
            "category":"Personal",
            "subcategory":"Beauty Salon",
            "type":"Services"
        }
    ],
    "sg:phone":"+1 253 548 2110",
    "sg:postcode":"98387",
    "sg:province":"WA",
    "wof:name":"TGF Haircutters",
    "wof:placetype":"venue"
},
  "geometry": {"coordinates":[-122.43214399999999,47.118964],"type":"Point"}
}