{
  "type": "Feature",
  "properties": {
    "iso:country":"US",
    "sg:address":"34217 Tanwax Ct E",
    "sg:city":"Eatonville",
    "sg:classifiers":[
        {
            "category":"Travel",
            "subcategory":"Hotels & Motels",
            "type":"Entertainment"
        }
    ],
    "sg:phone":"+1 360 879 5115",
    "sg:postcode":"98328",
    "sg:province":"WA",
    "sg:tags":[
        "resort"
    ],
    "wof:name":"Rainbow Resort",
    "wof:placetype":"venue"
},
  "geometry": {"coordinates":[-122.275288,46.946169],"type":"Point"}
}