{
  "type": "Feature",
  "properties": {
    "addr:full":"700 3rd Ave Seattle WA 98104",
    "addr:housenumber":"700",
    "addr:postcode":"98104",
    "addr:street":"3Rd Ave",
    "iso:country":"US",
    "sg:address":"700 3rd Ave",
    "sg:city":"Seattle",
    "sg:classifiers":[
        {
            "category":"Travel",
            "subcategory":"Hotels & Motels",
            "type":"Entertainment"
        }
    ],
    "sg:phone":"+1 206 340 0340",
    "sg:postcode":"98104",
    "sg:province":"WA",
    "sg:website":"www.arcticclubhotel.com",
    "wof:name":"Arctic Club Hotel",
    "wof:placetype":"venue"
},
  "geometry": {"coordinates":[-122.332125,47.603488],"type":"Point"}
}