{
  "type": "Feature",
  "properties": {
    "addr:full":"110 2nd St Wenatchee WA 98801",
    "addr:housenumber":"110",
    "addr:postcode":"98801",
    "addr:street":"2Nd St",
    "iso:country":"US",
    "sg:address":"110 2nd St",
    "sg:city":"Wenatchee",
    "sg:classifiers":[
        {
            "category":"Restaurant",
            "type":"Food & Drink"
        }
    ],
    "sg:phone":"+1 509 663 3954",
    "sg:postcode":"98801",
    "sg:province":"WA",
    "sg:tags":[
        "drinking",
        "eating"
    ],
    "sg:website":"http://www.bobsclassicautoglass.com",
    "wof:name":"Bob's Classic Brass & Brew",
    "wof:placetype":"venue"
},
  "geometry": {"coordinates":[-120.313631,47.427123],"type":"Point"}
}