{
  "type": "Feature",
  "properties": {
    "addr:full":"225 175th St E Spanaway WA 98387",
    "addr:housenumber":"225",
    "addr:postcode":"98387",
    "addr:street":"175Th St E",
    "iso:country":"US",
    "sg:address":"225 175th St E",
    "sg:city":"Spanaway",
    "sg:classifiers":[
        {
            "category":"Freight",
            "type":"Transportation"
        }
    ],
    "sg:phone":"+1 206 391 0942",
    "sg:postcode":"98387",
    "sg:province":"WA",
    "sg:tags":[
        "trucking"
    ],
    "wof:name":"Benny White Trucking",
    "wof:placetype":"venue"
},
  "geometry": {"coordinates":[-122.427255,47.098285],"type":"Point"}
}