{
  "type": "Feature",
  "properties": {
    "addr:full":"6060 Sands Way Anacortes WA 98221",
    "addr:housenumber":"6060",
    "addr:postcode":"98221",
    "addr:street":"Sands Way",
    "iso:country":"US",
    "sg:address":"6060 Sands Way",
    "sg:city":"Anacortes",
    "sg:classifiers":[
        {
            "category":"Real Estate",
            "subcategory":"Real Estate Agent",
            "type":"Services"
        }
    ],
    "sg:phone":"+1 360 293 6666",
    "sg:postcode":"98221",
    "sg:province":"WA",
    "wof:name":"Anacortes Realty",
    "wof:placetype":"venue"
},
  "geometry": {"coordinates":[-122.687076,48.49571],"type":"Point"}
}