{
  "type": "Feature",
  "properties": {
    "addr:full":"4412 Pacific Ave SE Lacey WA 98503",
    "addr:housenumber":"4412",
    "addr:postcode":"98503",
    "addr:street":"Pacific Ave Se",
    "iso:country":"US",
    "sg:address":"4412 Pacific Ave SE",
    "sg:city":"Lacey",
    "sg:classifiers":[
        {
            "category":"Health Services",
            "subcategory":"Podiatrist",
            "type":"Services"
        }
    ],
    "sg:phone":"+1 360 438 9092",
    "sg:postcode":"98503",
    "sg:province":"WA",
    "sg:tags":[
        "foot",
        "ankle",
        "clinic"
    ],
    "wof:name":"Cascade Foot & Ankle Clinic",
    "wof:placetype":"venue"
},
  "geometry": {"coordinates":[-122.825864,47.037809],"type":"Point"}
}