{
  "type": "Feature",
  "properties": {
    "addr:full":"18105 84th Ave E Puyallup WA 98375",
    "addr:housenumber":"18105",
    "addr:postcode":"98375",
    "addr:street":"84Th Ave E",
    "iso:country":"US",
    "sg:address":"18105 84th Ave E",
    "sg:city":"Puyallup",
    "sg:classifiers":[
        {
            "category":"Building & Trades",
            "subcategory":"Construction",
            "type":"Services"
        }
    ],
    "sg:phone":"+1 253 875 3467",
    "sg:postcode":"98375",
    "sg:province":"WA",
    "sg:tags":[
        "contractor"
    ],
    "wof:name":"Lynch Drywall Inc",
    "wof:placetype":"venue"
},
  "geometry": {"coordinates":[-122.317481,47.091899],"type":"Point"}
}