{
  "type": "Feature",
  "properties": {
    "addr:full":"1306 S 6th Ave Yakima WA 98902",
    "addr:housenumber":"1306",
    "addr:postcode":"98902",
    "addr:street":"S 6Th Ave",
    "iso:country":"US",
    "sg:address":"1306 S 6th Ave",
    "sg:city":"Yakima",
    "sg:classifiers":[
        {
            "category":"Shopping",
            "subcategory":"Clothing, Apparel, & Fashions",
            "type":"Retail Goods"
        }
    ],
    "sg:phone":"+1 509 457 9601",
    "sg:postcode":"98902",
    "sg:province":"WA",
    "sg:tags":[
        "wear"
    ],
    "wof:name":"Kidz Club",
    "wof:placetype":"venue"
},
  "geometry": {"coordinates":[-120.513507,46.579888],"type":"Point"}
}