{
  "type": "Feature",
  "properties": {
    "addr:full":"1430 34th Ave Seattle WA 98122",
    "addr:housenumber":"1430",
    "addr:postcode":"98122",
    "addr:street":"34Th Ave",
    "iso:country":"US",
    "sg:address":"1430 34th Ave",
    "sg:city":"Seattle",
    "sg:classifiers":[
        {
            "category":"Restaurant",
            "type":"Food & Drink"
        }
    ],
    "sg:menulink":"http://www.allmenus.com/wa/seattle/3606-dulces-latin-bistro/menu/",
    "sg:phone":"+1 206 322 5453",
    "sg:postcode":"98122",
    "sg:province":"WA",
    "sg:tags":[
        "german"
    ],
    "wof:name":"Dulces Latin Bistro",
    "wof:placetype":"venue"
},
  "geometry": {"coordinates":[-122.289286,47.613797],"type":"Point"}
}