{
  "type": "Feature",
  "properties": {
    "addr:full":"14210 50th Ave SE Everett WA 98208",
    "addr:housenumber":"14210",
    "addr:postcode":"98208",
    "addr:street":"50Th Ave Se",
    "iso:country":"US",
    "sg:address":"14210 50th Ave SE",
    "sg:city":"Everett",
    "sg:classifiers":[
        {
            "category":"Professional",
            "subcategory":"Computer Services",
            "type":"Services"
        }
    ],
    "sg:phone":"+1 425 385 3085",
    "sg:postcode":"98208",
    "sg:province":"WA",
    "sg:tags":[
        "datum",
        "commercial",
        "desi"
    ],
    "wof:name":"Herrmann Design",
    "wof:placetype":"venue"
},
  "geometry": {"coordinates":[-122.163586,47.868433],"type":"Point"}
}