{
  "type": "Feature",
  "properties": {
    "addr:full":"6538 4th Avenue S Seattle WA 98108",
    "addr:housenumber":"6538",
    "addr:postcode":"98108",
    "addr:street":"4Th Avenue S",
    "iso:country":"US",
    "sg:address":"6538 4th Avenue S",
    "sg:city":"Seattle",
    "sg:classifiers":[
        {
            "category":"Restaurant",
            "type":"Food & Drink"
        }
    ],
    "sg:phone":"+1 206 767 4583",
    "sg:postcode":"98108",
    "sg:province":"WA",
    "wof:name":"Red House",
    "wof:placetype":"venue"
},
  "geometry": {"coordinates":[-122.329657,47.545053],"type":"Point"}
}