{
  "type": "Feature",
  "properties": {
    "addr:full":"423 N Pines Rd Spokane Valley WA 99206",
    "addr:housenumber":"423",
    "addr:postcode":"99206",
    "addr:street":"N Pines Rd",
    "iso:country":"US",
    "sg:address":"423 N Pines Rd",
    "sg:city":"Spokane Valley",
    "sg:classifiers":[
        {
            "category":"Retail",
            "subcategory":"Car Wash",
            "type":"Services"
        }
    ],
    "sg:phone":"+1 509 928 7226",
    "sg:postcode":"99206",
    "sg:province":"WA",
    "sg:tags":[
        "polishing",
        "washing"
    ],
    "wof:name":"Mister Car Wash",
    "wof:placetype":"venue"
},
  "geometry": {"coordinates":[-117.23982599999999,47.661479],"type":"Point"}
}