{
  "type": "Feature",
  "properties": {
    "iso:country":"US",
    "sg:address":"1302 8th St",
    "sg:city":"Anacortes",
    "sg:classifiers":[
        {
            "category":"Health Services",
            "subcategory":"Doctor",
            "type":"Services"
        }
    ],
    "sg:phone":"+1 360 293 2000",
    "sg:postcode":"98221",
    "sg:province":"WA",
    "sg:tags":[
        "dentist"
    ],
    "wof:name":"Anacortes Dental Care Inc",
    "wof:placetype":"venue"
},
  "geometry": {"coordinates":[-122.618781,48.51597],"type":"Point"}
}