{
  "type": "Feature",
  "properties": {
    "addr:full":"4843 Kittitas Hwy Ellensburg WA 98926",
    "addr:housenumber":"4843",
    "addr:postcode":"98926",
    "addr:street":"Kittitas Hwy",
    "iso:country":"US",
    "sg:address":"4843 Kittitas Hwy",
    "sg:city":"Ellensburg",
    "sg:classifiers":[
        {
            "category":"Building & Trades",
            "subcategory":"Construction",
            "type":"Services"
        }
    ],
    "sg:phone":"+1 509 968 4611",
    "sg:postcode":"98926",
    "sg:province":"WA",
    "sg:tags":[
        "homes",
        "modular",
        "contractor",
        "special",
        "mfg"
    ],
    "wof:name":"Mainly Logs",
    "wof:placetype":"venue"
},
  "geometry": {"coordinates":[-120.459909,46.985611],"type":"Point"}
}