{
  "type": "Feature",
  "properties": {
    "addr:full":"4611 36th Ave SW Seattle WA 98126",
    "addr:housenumber":"4611",
    "addr:postcode":"98126",
    "addr:street":"36Th Ave Sw",
    "iso:country":"US",
    "sg:address":"4611 36th Ave SW",
    "sg:city":"Seattle",
    "sg:classifiers":[
        {
            "category":"Food & Beverages",
            "subcategory":"Bakery",
            "type":"Retail Goods"
        },
        {
            "category":"Bakery",
            "type":"Food & Drink"
        }
    ],
    "sg:phone":"+1 206 938 3960",
    "sg:postcode":"98126",
    "sg:province":"WA",
    "sg:tags":[
        "bakers-wholesale"
    ],
    "wof:name":"Little Rae's Bakery",
    "wof:placetype":"venue"
},
  "geometry": {"coordinates":[-122.377489,47.561929],"type":"Point"}
}