{
  "type": "Feature",
  "properties": {
    "addr:full":"2307 Lakewood Rd Arlington WA 98223",
    "addr:housenumber":"2307",
    "addr:postcode":"98223",
    "addr:street":"Lakewood Rd",
    "iso:country":"US",
    "sg:address":"2307 Lakewood Rd",
    "sg:city":"Arlington",
    "sg:classifiers":[
        {
            "category":"Retail",
            "subcategory":"Auto Repair",
            "type":"Services"
        }
    ],
    "sg:phone":"+1 360 654 9400",
    "sg:postcode":"98223",
    "sg:province":"WA",
    "sg:tags":[
        "wrecker"
    ],
    "wof:name":"Four Seasons Towing & Recovery",
    "wof:placetype":"venue"
},
  "geometry": {"coordinates":[-122.258781,48.155136],"type":"Point"}
}