{
  "type": "Feature",
  "properties": {
    "addr:full":"940 W Emerson St Apt A Seattle WA 98119",
    "addr:housenumber":"940",
    "addr:postcode":"98119",
    "addr:street":"W Emerson St Apt A",
    "iso:country":"US",
    "sg:address":"940 W Emerson St Apt A",
    "sg:city":"Seattle",
    "sg:classifiers":[
        {
            "category":"Shopping",
            "subcategory":"Books",
            "type":"Retail Goods"
        },
        {
            "category":"Wholesale",
            "subcategory":"Books, Periodicals, & Newspapers",
            "type":"Manufacturing & Wholesale Goods"
        }
    ],
    "sg:phone":"+1 206 283 2810",
    "sg:postcode":"98119",
    "sg:province":"WA",
    "sg:tags":[
        "books-wholesale",
        "store",
        "manufacturer"
    ],
    "wof:name":"Collins Lauris Enterprise",
    "wof:placetype":"venue"
},
  "geometry": {"coordinates":[-122.369331,47.65234],"type":"Point"}
}