{
  "type": "Feature",
  "properties": {
    "addr:full":"9117 NE 100th St Vancouver WA 98662",
    "addr:housenumber":"9117",
    "addr:postcode":"98662",
    "addr:street":"Ne 100Th St",
    "iso:country":"US",
    "sg:address":"9117 NE 100th St",
    "sg:city":"Vancouver",
    "sg:classifiers":[
        {
            "category":"Building & Trades",
            "subcategory":"Plumbing",
            "type":"Services"
        }
    ],
    "sg:phone":"+1 360 260 0476",
    "sg:postcode":"98662",
    "sg:province":"WA",
    "sg:tags":[
        "system",
        "contractor",
        "heating",
        "conditioning",
        "air",
        "remodeling"
    ],
    "wof:name":"B-Unique Designs Inc",
    "wof:placetype":"venue"
},
  "geometry": {"coordinates":[-122.579295,45.694098],"type":"Point"}
}