{
  "type": "Feature",
  "properties": {
    "addr:full":"555 N Market Blvd Chehalis WA 98532",
    "addr:housenumber":"555",
    "addr:postcode":"98532",
    "addr:street":"N Market Blvd",
    "iso:country":"US",
    "sg:address":"555 N Market Blvd",
    "sg:city":"Chehalis",
    "sg:classifiers":[
        {
            "category":"Bars & Pubs",
            "type":"Food & Drink"
        }
    ],
    "sg:phone":"+1 360 748 6171",
    "sg:postcode":"98532",
    "sg:province":"WA",
    "sg:tags":[
        "drinking"
    ],
    "wof:name":"Office Tavern",
    "wof:placetype":"venue"
},
  "geometry": {"coordinates":[-122.9708,46.665591],"type":"Point"}
}