{
  "type": "Feature",
  "properties": {
    "addr:full":"4720 NW Cherry St Vancouver WA 98663",
    "addr:housenumber":"4720",
    "addr:postcode":"98663",
    "addr:street":"Nw Cherry",
    "iso:country":"US",
    "sg:address":"4720 NW Cherry St",
    "sg:city":"Vancouver",
    "sg:classifiers":[
        {
            "category":"Retail",
            "subcategory":"Veterinary Services",
            "type":"Services"
        }
    ],
    "sg:phone":"+1 360 750 6633",
    "sg:postcode":"98663",
    "sg:province":"WA",
    "sg:tags":[
        "clinic",
        "hospital"
    ],
    "wof:name":"P C Evs",
    "wof:placetype":"venue"
},
  "geometry": {"coordinates":[-122.68640000000001,45.656954],"type":"Point"}
}