{
  "type": "Feature",
  "properties": {
    "addr:full":"1911 26th Avenue E Seattle WA 98112",
    "addr:housenumber":"1911",
    "addr:postcode":"98112",
    "addr:street":"26Th Avenue E",
    "iso:country":"US",
    "sg:address":"1911 26th Avenue E",
    "sg:city":"Seattle",
    "sg:classifiers":[
        {
            "category":"Insurance",
            "subcategory":"Health Insurance",
            "type":"Services"
        }
    ],
    "sg:phone":"+1 206 568 4485",
    "sg:postcode":"98112",
    "sg:province":"WA",
    "sg:tags":[
        "market"
    ],
    "wof:name":"Simbree",
    "wof:placetype":"venue"
},
  "geometry": {"coordinates":[-122.299663,47.636885],"type":"Point"}
}