{
  "type": "Feature",
  "properties": {
    "addr:full":"2301 Commerce St Aberdeen WA 98520",
    "addr:housenumber":"2301",
    "addr:postcode":"98520",
    "addr:street":"Commerce St",
    "iso:country":"US",
    "sg:address":"2301 Commerce St",
    "sg:city":"Aberdeen",
    "sg:classifiers":[
        {
            "category":"Wholesale",
            "subcategory":"Machinery & Supplies",
            "type":"Manufacturing & Wholesale Goods"
        }
    ],
    "sg:phone":"+1 360 532 3362",
    "sg:postcode":"98520",
    "sg:province":"WA",
    "sg:tags":[
        "equipment",
        "industrial"
    ],
    "wof:name":"L G Isaacson Co",
    "wof:placetype":"venue"
},
  "geometry": {"coordinates":[-123.84157999999999,46.966662],"type":"Point"}
}