{
  "type": "Feature",
  "properties": {
    "addr:full":"120 Glen Ave Snohomish WA 98290",
    "addr:housenumber":"120",
    "addr:postcode":"98290",
    "addr:street":"Glen Ave",
    "iso:country":"US",
    "sg:address":"120 Glen Ave",
    "sg:city":"Snohomish",
    "sg:classifiers":[
        {
            "category":"Restaurant",
            "type":"Food & Drink"
        }
    ],
    "sg:phone":"+1 360 568 1277",
    "sg:postcode":"98290",
    "sg:province":"WA",
    "sg:tags":[
        "personal",
        "drinking",
        "eating"
    ],
    "wof:name":"Collectors Choice Restaurant",
    "wof:placetype":"venue"
},
  "geometry": {"coordinates":[-122.091894,47.912828],"type":"Point"}
}