{
  "type": "Feature",
  "properties": {
    "addr:full":"3835 33rd Ave W Seattle WA 98199",
    "addr:housenumber":"3835",
    "addr:postcode":"98199",
    "addr:street":"33Rd Ave W",
    "iso:country":"US",
    "sg:address":"3835 33rd Ave W",
    "sg:city":"Seattle",
    "sg:classifiers":[
        {
            "category":"Real Estate",
            "subcategory":"Real Estate Agent",
            "type":"Services"
        }
    ],
    "sg:phone":"+1 206 283 2645",
    "sg:postcode":"98199",
    "sg:province":"WA",
    "wof:name":"SLK Real Estate LLC",
    "wof:placetype":"venue"
},
  "geometry": {"coordinates":[-122.399597,47.655557],"type":"Point"}
}