{
  "type": "Feature",
  "properties": {
    "iso:country":"US",
    "sg:address":"600 5th Ave W",
    "sg:city":"Seattle",
    "sg:classifiers":[
        {
            "category":"Shopping",
            "subcategory":"Beauty & Cosmetics",
            "type":"Retail Goods"
        }
    ],
    "sg:phone":"+1 206 223 1866",
    "sg:postcode":"98119",
    "sg:province":"WA",
    "sg:tags":[
        "merchandise"
    ],
    "wof:name":"Yurikos Cosmetics",
    "wof:placetype":"venue"
},
  "geometry": {"coordinates":[-122.36323299999999,47.625857],"type":"Point"}
}