{
  "type": "Feature",
  "properties": {
    "addr:full":"4806 88th Ave SE Mercer Island WA 98040",
    "addr:housenumber":"4806",
    "addr:postcode":"98040",
    "addr:street":"88Th Ave Se",
    "iso:country":"US",
    "sg:address":"4806 88th Ave SE",
    "sg:city":"Mercer Island",
    "sg:classifiers":[
        {
            "category":"Building & Trades",
            "subcategory":"Plumbing",
            "type":"Services"
        }
    ],
    "sg:phone":"+1 206 624 1726",
    "sg:postcode":"98040",
    "sg:province":"WA",
    "sg:tags":[
        "contractor"
    ],
    "wof:name":"Leong Plumbing Inc",
    "wof:placetype":"venue"
},
  "geometry": {"coordinates":[-122.221445,47.559259],"type":"Point"}
}