{
  "type": "Feature",
  "properties": {
    "addr:full":"280 Grant Rd East Wenatchee WA 98802",
    "addr:housenumber":"280",
    "addr:postcode":"98802",
    "addr:street":"Grant Rd",
    "iso:country":"US",
    "sg:address":"280 Grant Rd",
    "sg:city":"East Wenatchee",
    "sg:classifiers":[
        {
            "category":"Restaurant",
            "type":"Food & Drink"
        }
    ],
    "sg:phone":"+1 509 884 6219",
    "sg:postcode":"98802",
    "sg:province":"WA",
    "wof:name":"Buzz In Steak House & Lounge",
    "wof:placetype":"venue"
},
  "geometry": {"coordinates":[-120.284717,47.405916],"type":"Point"}
}