{
  "type": "Feature",
  "properties": {
    "addr:full":"3828 Cheasty Blvd S Seattle WA 98108",
    "addr:housenumber":"3828",
    "addr:postcode":"98108",
    "addr:street":"Cheasty Blvd S",
    "iso:country":"US",
    "sg:address":"3828 Cheasty Blvd S",
    "sg:city":"Seattle",
    "sg:classifiers":[
        {
            "category":"Personal",
            "type":"Services"
        }
    ],
    "sg:phone":"+1 206 722 2047",
    "sg:postcode":"98108",
    "sg:province":"WA",
    "wof:name":"Berdfiskman LLC",
    "wof:placetype":"venue"
},
  "geometry": {"coordinates":[-122.299139,47.572547],"type":"Point"}
}