{
  "type": "Feature",
  "properties": {
    "addr:full":"14313 NE 82nd Ave Vancouver WA 98662",
    "addr:housenumber":"14313",
    "addr:postcode":"98662",
    "addr:street":"Ne 82Nd Ave",
    "iso:country":"US",
    "sg:address":"14313 NE 82nd Ave",
    "sg:city":"Vancouver",
    "sg:classifiers":[
        {
            "category":"Building & Trades",
            "subcategory":"Construction",
            "type":"Services"
        }
    ],
    "sg:phone":"+1 360 573 0867",
    "sg:postcode":"98662",
    "sg:province":"WA",
    "sg:tags":[
        "general",
        "contractor"
    ],
    "sg:website":"www.clark-sonconstruction.com",
    "wof:name":"Clark & Son Construction Inc",
    "wof:placetype":"venue"
},
  "geometry": {"coordinates":[-122.58894600000001,45.724175],"type":"Point"}
}