{
  "type": "Feature",
  "properties": {
    "addr:full":"5008 121st Ave E Edgewood WA 98372",
    "addr:housenumber":"5008",
    "addr:postcode":"98372",
    "addr:street":"121St Ave E",
    "iso:country":"US",
    "sg:address":"5008 121st Ave E",
    "sg:city":"Edgewood",
    "sg:classifiers":[
        {
            "category":"Wholesale",
            "subcategory":"Medical Equipment & Supplies",
            "type":"Manufacturing & Wholesale Goods"
        },
        {
            "category":"Shopping",
            "subcategory":"Pharmacy",
            "type":"Retail Goods"
        }
    ],
    "sg:phone":"+1 253 863 3879",
    "sg:postcode":"98372",
    "sg:province":"WA",
    "sg:tags":[
        "home",
        "health",
        "care"
    ],
    "wof:name":"Walls Precision Instruments",
    "wof:placetype":"venue"
},
  "geometry": {"coordinates":[-122.26851499999999,47.212309],"type":"Point"}
}