{
  "type": "Feature",
  "properties": {
    "iso:country":"US",
    "sg:address":"5628 NE 70th St",
    "sg:city":"Seattle",
    "sg:classifiers":[
        {
            "category":"Shopping",
            "subcategory":"Shoes",
            "type":"Retail Goods"
        }
    ],
    "sg:phone":"+1 206 525 9642",
    "sg:postcode":"98115",
    "sg:province":"WA",
    "wof:name":"Itchy Feet Inc",
    "wof:placetype":"venue"
},
  "geometry": {"coordinates":[-122.26566800000001,47.679447],"type":"Point"}
}