{
  "type": "Feature",
  "properties": {
    "addr:full":"712 W Columbia Dr Kennewick WA 99336",
    "addr:housenumber":"712",
    "addr:postcode":"99336",
    "addr:street":"W Columbia Dr",
    "iso:country":"US",
    "sg:address":"712 W Columbia Dr",
    "sg:city":"Kennewick",
    "sg:classifiers":[
        {
            "category":"Retail",
            "subcategory":"Veterinary Services",
            "type":"Services"
        }
    ],
    "sg:phone":"+1 509 582 8008",
    "sg:postcode":"99336",
    "sg:province":"WA",
    "sg:tags":[
        "veterinarian"
    ],
    "wof:name":"Animal Hospital Of Kennewick",
    "wof:placetype":"venue"
},
  "geometry": {"coordinates":[-119.12866099999999,46.21691],"type":"Point"}
}