{
  "type": "Feature",
  "properties": {
    "addr:full":"300 SE Grant St Pullman WA 99163",
    "addr:housenumber":"300",
    "addr:postcode":"99163",
    "addr:street":"Se Grant St",
    "iso:country":"US",
    "sg:address":"300 SE Grant St",
    "sg:city":"Pullman",
    "sg:classifiers":[
        {
            "category":"Social Services",
            "type":"Services"
        }
    ],
    "sg:phone":"+1 509 332 2103",
    "sg:postcode":"99163",
    "sg:province":"WA",
    "wof:name":"Families Together NW Reg",
    "wof:placetype":"venue"
},
  "geometry": {"coordinates":[-117.17859,46.721399],"type":"Point"}
}