{
  "type": "Feature",
  "properties": {
    "addr:full":"2306 W 4th Pl Kennewick WA 99336",
    "addr:housenumber":"2306",
    "addr:postcode":"99336",
    "addr:street":"W 4Th Pl",
    "iso:country":"US",
    "sg:address":"2306 W 4th Pl",
    "sg:city":"Kennewick",
    "sg:classifiers":[
        {
            "category":"Building & Trades",
            "subcategory":"Construction",
            "type":"Services"
        }
    ],
    "sg:phone":"+1 509 582 4388",
    "sg:postcode":"99336",
    "sg:province":"WA",
    "sg:tags":[
        "general",
        "contractor"
    ],
    "wof:name":"Garretson Construction",
    "wof:placetype":"venue"
},
  "geometry": {"coordinates":[-119.151886,46.205001],"type":"Point"}
}