{
  "type": "Feature",
  "properties": {
    "addr:full":"32533 Cascade View Dr Sultan WA 98294",
    "addr:housenumber":"32533",
    "addr:postcode":"98294",
    "addr:street":"Cascade View Dr Sultan",
    "iso:country":"US",
    "sg:address":"32533 Cascade View Dr",
    "sg:city":"Sultan",
    "sg:classifiers":[
        {
            "category":"Manufacturing",
            "subcategory":"Food",
            "type":"Manufacturing & Wholesale Goods"
        },
        {
            "category":"Wholesale",
            "subcategory":"Groceries",
            "type":"Manufacturing & Wholesale Goods"
        },
        {
            "category":"Food & Beverages",
            "subcategory":"Supermarket",
            "type":"Retail Goods"
        }
    ],
    "sg:phone":"+1 360 793 2241",
    "sg:postcode":"98294",
    "sg:province":"WA",
    "sg:tags":[
        "grocers-wholesale",
        "processing",
        "super",
        "store"
    ],
    "sg:website":"http://www.purefoodsinc.com",
    "wof:name":"Sky River Brewing Inc",
    "wof:placetype":"venue"
},
  "geometry": {"coordinates":[-121.795154,47.864218],"type":"Point"}
}