{
  "type": "Feature",
  "properties": {
    "addr:full":"1701 Sturgus Ave S #2 Seattle WA 98144",
    "addr:housenumber":"1701",
    "addr:postcode":"98144",
    "addr:street":"Sturgus Ave S # 2",
    "iso:country":"US",
    "sg:address":"1701 Sturgus Ave S #2",
    "sg:city":"Seattle",
    "sg:classifiers":[
        {
            "category":"Professional",
            "subcategory":"Art Services",
            "type":"Services"
        }
    ],
    "sg:phone":"+1 206 323 6072",
    "sg:postcode":"98144",
    "sg:province":"WA",
    "sg:tags":[
        "photographer"
    ],
    "sg:website":"www.elliottbayphotography.com",
    "wof:name":"Elliott Bay Photography",
    "wof:placetype":"venue"
},
  "geometry": {"coordinates":[-122.311864,47.588307],"type":"Point"}
}