{
  "type": "Feature",
  "properties": {
    "addr:full":"113 12th Ave Seattle WA 98122",
    "addr:housenumber":"113",
    "addr:postcode":"98122",
    "addr:street":"12Th Ave",
    "iso:country":"US",
    "sg:address":"113 12th Ave",
    "sg:city":"Seattle",
    "sg:classifiers":[
        {
            "category":"Government",
            "subcategory":"Office",
            "type":"Public Place"
        }
    ],
    "sg:phone":"+1 206 839 0880",
    "sg:postcode":"98122",
    "sg:province":"WA",
    "sg:tags":[
        "s",
        "conservation"
    ],
    "wof:name":"Secluded Alley Works",
    "wof:placetype":"venue"
},
  "geometry": {"coordinates":[-122.316858,47.602436],"type":"Point"}
}