{
  "type": "Feature",
  "properties": {
    "addr:full":"528 2nd Ave S Kent WA 98032",
    "addr:housenumber":"528",
    "addr:postcode":"98032",
    "addr:street":"2Nd Ave S",
    "iso:country":"US",
    "sg:address":"528 2nd Ave S",
    "sg:city":"Kent",
    "sg:classifiers":[
        {
            "category":"Professional",
            "subcategory":"Lawyer & Legal Services",
            "type":"Services"
        }
    ],
    "sg:phone":"+1 425 251 0975",
    "sg:postcode":"98032",
    "sg:province":"WA",
    "wof:name":"Jump Law Group",
    "wof:placetype":"venue"
},
  "geometry": {"coordinates":[-122.234762,47.376925],"type":"Point"}
}