{
  "type": "Feature",
  "properties": {
    "addr:full":"15 W 5th St Cheney WA 99004",
    "addr:housenumber":"15",
    "addr:postcode":"99004",
    "addr:street":"W 5Th St",
    "iso:country":"US",
    "sg:address":"15 W 5th St",
    "sg:city":"Cheney",
    "sg:classifiers":[
        {
            "category":"Professional",
            "type":"Services"
        }
    ],
    "sg:phone":"+1 509 559 5591",
    "sg:postcode":"99004",
    "sg:province":"WA",
    "sg:tags":[
        "establishment"
    ],
    "wof:name":"Gray & Gray",
    "wof:placetype":"venue"
},
  "geometry": {"coordinates":[-117.582599,47.485791],"type":"Point"}
}