{
  "type": "Feature",
  "properties": {
    "addr:full":"2801 N Pittsburg St Spokane WA 99207",
    "addr:housenumber":"2801",
    "addr:postcode":"99207",
    "addr:street":"N Pittsburg St",
    "iso:country":"US",
    "sg:address":"2801 N Pittsburg St",
    "sg:city":"Spokane",
    "sg:classifiers":[
        {
            "category":"Personal",
            "type":"Services"
        }
    ],
    "sg:phone":"+1 509 484 4123",
    "sg:postcode":"99207",
    "sg:province":"WA",
    "sg:tags":[
        "towing"
    ],
    "wof:name":"Susan Cramer",
    "wof:placetype":"venue"
},
  "geometry": {"coordinates":[-117.384773,47.68346],"type":"Point"}
}