{
  "type": "Feature",
  "properties": {
    "iso:country":"US",
    "sg:address":"705 E Lincoln Ave",
    "sg:city":"Yakima",
    "sg:classifiers":[
        {
            "category":"Professional",
            "subcategory":"Management & Consulting",
            "type":"Services"
        }
    ],
    "sg:phone":"+1 509 225 3526",
    "sg:postcode":"98901",
    "sg:province":"WA",
    "sg:tags":[
        "business"
    ],
    "wof:name":"Eastern Sun Ecological Service",
    "wof:placetype":"venue"
},
  "geometry": {"coordinates":[-120.497326,46.60845],"type":"Point"}
}