{
  "type": "Feature",
  "properties": {
    "addr:full":"10409 Aurora Ave N Seattle WA 98133",
    "addr:housenumber":"10409",
    "addr:postcode":"98133",
    "addr:street":"Aurora Ave N",
    "iso:country":"US",
    "sg:address":"10409 Aurora Ave N",
    "sg:city":"Seattle",
    "sg:classifiers":[
        {
            "category":"Shopping",
            "subcategory":"Bicycles & Sporting Goods",
            "type":"Retail Goods"
        }
    ],
    "sg:phone":"+1 206 527 7770",
    "sg:postcode":"98133",
    "sg:province":"WA",
    "sg:tags":[
        "equipment",
        "golf"
    ],
    "wof:name":"Pro-Golf Discount",
    "wof:placetype":"venue"
},
  "geometry": {"coordinates":[-122.34477,47.704988],"type":"Point"}
}