{
  "type": "Feature",
  "properties": {
    "addr:full":"6113 NE Minder Rd Poulsbo WA 98370",
    "addr:housenumber":"6113",
    "addr:postcode":"98370",
    "addr:street":"Ne Minder Rd",
    "iso:country":"US",
    "sg:address":"6113 NE Minder Rd",
    "sg:city":"Poulsbo",
    "sg:classifiers":[
        {
            "category":"Manufacturing",
            "subcategory":"Tools & Machinery",
            "type":"Manufacturing & Wholesale Goods"
        }
    ],
    "sg:phone":"+1 360 297 3939",
    "sg:postcode":"98370",
    "sg:province":"WA",
    "sg:tags":[
        "machine",
        "shop"
    ],
    "sg:website":"www.pugetsoundprecision.com",
    "wof:name":"Puget Sound Precision",
    "wof:placetype":"venue"
},
  "geometry": {"coordinates":[-122.57364200000001,47.801823],"type":"Point"}
}