{
  "type": "Feature",
  "properties": {
    "addr:full":"1206 State Ave Marysville WA 98270",
    "addr:housenumber":"1206",
    "addr:postcode":"98270",
    "addr:street":"State Ave",
    "iso:country":"US",
    "sg:address":"1206 State Ave",
    "sg:city":"Marysville",
    "sg:classifiers":[
        {
            "category":"Restaurant",
            "type":"Food & Drink"
        }
    ],
    "sg:phone":"+1 360 658 0183",
    "sg:postcode":"98270",
    "sg:province":"WA",
    "wof:name":"Ichi Bento Teriyaki",
    "wof:placetype":"venue"
},
  "geometry": {"coordinates":[-122.17685299999999,48.062581],"type":"Point"}
}