{
  "type": "Feature",
  "properties": {
    "addr:full":"10515 St Helens Ave Vancouver WA 98664",
    "addr:housenumber":"10515",
    "addr:postcode":"98664",
    "addr:street":"St Helens Ave",
    "iso:country":"US",
    "sg:address":"10515 St Helens Ave",
    "sg:city":"Vancouver",
    "sg:classifiers":[
        {
            "category":"Retail",
            "subcategory":"Laundry & Dry Cleaning",
            "type":"Services"
        }
    ],
    "sg:phone":"+1 360 256 5435",
    "sg:postcode":"98664",
    "sg:province":"WA",
    "wof:name":"Nilco Carpet Cleaners",
    "wof:placetype":"venue"
},
  "geometry": {"coordinates":[-122.56387700000001,45.616028],"type":"Point"}
}