{
  "type": "Feature",
  "properties": {
    "addr:full":"1006 Main St Sumner WA 98390",
    "addr:housenumber":"1006",
    "addr:postcode":"98390",
    "addr:street":"Main St",
    "iso:country":"US",
    "sg:address":"1006 Main St",
    "sg:city":"Sumner",
    "sg:classifiers":[
        {
            "category":"Building & Trades",
            "subcategory":"Construction",
            "type":"Services"
        },
        {
            "category":"Military Area",
            "subcategory":"Armory",
            "type":"Public Place"
        }
    ],
    "sg:phone":"+1 253 863 6048",
    "sg:postcode":"98390",
    "sg:province":"WA",
    "sg:tags":[
        "repair",
        "fence-sales",
        "fence",
        "contractor"
    ],
    "wof:name":"A Picket Fence",
    "wof:placetype":"venue"
},
  "geometry": {"coordinates":[-122.241753,47.203309],"type":"Point"}
}