{
  "type": "Feature",
  "properties": {
    "addr:full":"17445 Lake Terrace Pl Mount Vernon WA 98274",
    "addr:housenumber":"17445",
    "addr:postcode":"98274",
    "addr:street":"Lake Terrace Pl",
    "iso:country":"US",
    "sg:address":"17445 Lake Terrace Pl",
    "sg:city":"Mount Vernon",
    "sg:classifiers":[
        {
            "category":"Professional",
            "subcategory":"Computer Services",
            "type":"Services"
        }
    ],
    "sg:phone":"+1 360 422 5924",
    "sg:postcode":"98274",
    "sg:province":"WA",
    "sg:tags":[
        "related"
    ],
    "wof:name":"Sunergos Business Solutions",
    "wof:placetype":"venue"
},
  "geometry": {"coordinates":[-122.250122,48.392811],"type":"Point"}
}