{
  "type": "Feature",
  "properties": {
    "addr:full":"200 W Jones St Yacolt WA 98675",
    "addr:housenumber":"200",
    "addr:postcode":"98675",
    "addr:street":"W Jones St",
    "iso:country":"US",
    "sg:address":"200 W Jones St",
    "sg:city":"Yacolt",
    "sg:classifiers":[
        {
            "category":"Organizations",
            "subcategory":"Religious Organization",
            "type":"Services"
        }
    ],
    "sg:phone":"+1 360 686 8088",
    "sg:postcode":"98675",
    "sg:province":"WA",
    "sg:tags":[
        "church"
    ],
    "wof:name":"St Joseph The Worker Church",
    "wof:placetype":"venue"
},
  "geometry": {"coordinates":[-122.409334,45.864967],"type":"Point"}
}