{
  "type": "Feature",
  "properties": {
    "addr:full":"1414 Morgan St Aberdeen WA 98520",
    "addr:housenumber":"1414",
    "addr:postcode":"98520",
    "addr:street":"Morgan St",
    "iso:country":"US",
    "sg:address":"1414 Morgan St",
    "sg:city":"Aberdeen",
    "sg:classifiers":[
        {
            "category":"Building & Trades",
            "subcategory":"Construction",
            "type":"Services"
        }
    ],
    "sg:phone":"+1 360 533 4785",
    "sg:postcode":"98520",
    "sg:province":"WA",
    "sg:tags":[
        "residential",
        "nonresidential"
    ],
    "wof:name":"Tetzlaff Construction",
    "wof:placetype":"venue"
},
  "geometry": {"coordinates":[-123.833592,46.970632],"type":"Point"}
}