{
  "type": "Feature",
  "properties": {
    "addr:full":"2414 SE Celebrity Ct Port Orchard WA 98367",
    "addr:housenumber":"2414",
    "addr:postcode":"98367",
    "addr:street":"Se Celebrity Ct",
    "iso:country":"US",
    "sg:address":"2414 SE Celebrity Ct",
    "sg:city":"Port Orchard",
    "sg:classifiers":[
        {
            "category":"Retail",
            "subcategory":"Repair Shop",
            "type":"Services"
        }
    ],
    "sg:phone":"+1 360 895 1450",
    "sg:postcode":"98367",
    "sg:province":"WA",
    "sg:tags":[
        "welding"
    ],
    "wof:name":"Just Bear Welding",
    "wof:placetype":"venue"
},
  "geometry": {"coordinates":[-122.618759,47.500494],"type":"Point"}
}