{
  "type": "Feature",
  "properties": {
    "addr:full":"600 Stewart St 1324 Seattle WA 98101",
    "addr:housenumber":"600",
    "addr:postcode":"1324;98101",
    "addr:street":"Stewart St",
    "iso:country":"US",
    "sg:address":"600 Stewart St 1324",
    "sg:city":"Seattle",
    "sg:classifiers":[
        {
            "category":"Insurance",
            "subcategory":"Insurance Agent",
            "type":"Services"
        },
        {
            "category":"Insurance",
            "subcategory":"Hazard Insurance",
            "type":"Services"
        },
        {
            "category":"Banks & Credit Unions",
            "subcategory":"Financial Services",
            "type":"Services"
        }
    ],
    "sg:phone":"+1 206 441 7399",
    "sg:postcode":"98101",
    "sg:province":"WA",
    "sg:tags":[
        "retirement",
        "profit",
        "annuity",
        "sharing",
        "planning",
        "plan",
        "consultant",
        "analyst",
        "pension"
    ],
    "wof:name":"Annuities Insurance Svcs",
    "wof:placetype":"venue"
},
  "geometry": {"coordinates":[-122.337013,47.613621],"type":"Point"}
}