{
  "type": "Feature",
  "properties": {
    "addr:full":"732 NE 2nd Ave Camas WA 98607",
    "addr:housenumber":"732",
    "addr:postcode":"98607",
    "addr:street":"Ne 2Nd Ave",
    "iso:country":"US",
    "sg:address":"732 NE 2nd Ave",
    "sg:city":"Camas",
    "sg:classifiers":[
        {
            "category":"Health Services",
            "subcategory":"Chiropractor",
            "type":"Services"
        }
    ],
    "sg:phone":"+1 360 834 3434",
    "sg:postcode":"98607",
    "sg:province":"WA",
    "sg:website":"www.DrGwilliam.com",
    "wof:name":"Gwilliam Evan DC",
    "wof:placetype":"venue"
},
  "geometry": {"coordinates":[-122.39994299999999,45.585996],"type":"Point"}
}