{
  "type": "Feature",
  "properties": {
    "addr:full":"1104 Main St Ste 550 Vancouver WA 98660",
    "addr:housenumber":"1104",
    "addr:postcode":"98660",
    "addr:street":"Main St Ste 550",
    "iso:country":"US",
    "sg:address":"1104 Main St Ste 550",
    "sg:city":"Vancouver",
    "sg:classifiers":[
        {
            "category":"Health Services",
            "subcategory":"Doctor",
            "type":"Services"
        },
        {
            "category":"Health Services",
            "subcategory":"Clinic",
            "type":"Services"
        }
    ],
    "sg:phone":"+1 360 699 0996",
    "sg:postcode":"98660",
    "sg:province":"WA",
    "sg:tags":[
        "psychiatry",
        "physician",
        "surgeon",
        "surgeons",
        "osteopathic"
    ],
    "wof:name":"Mecouch, George Do General Psychiatry",
    "wof:placetype":"venue"
},
  "geometry": {"coordinates":[-122.671541,45.629544],"type":"Point"}
}