{
  "type": "Feature",
  "properties": {
    "addr:full":"750 S Wenatchee Ave Wenatchee WA 98801",
    "addr:housenumber":"750",
    "addr:postcode":"98801",
    "addr:street":"S Wenatchee Ave",
    "iso:country":"US",
    "sg:address":"750 S Wenatchee Ave",
    "sg:city":"Wenatchee",
    "sg:classifiers":[
        {
            "category":"Autos & Motor Vehicles",
            "subcategory":"Automobile Sales",
            "type":"Retail Goods"
        }
    ],
    "sg:phone":"+1 509 662 9414",
    "sg:postcode":"98801",
    "sg:province":"WA",
    "sg:tags":[
        "car",
        "used",
        "dealer"
    ],
    "wof:name":"Days Dandies Used Cars",
    "wof:placetype":"venue"
},
  "geometry": {"coordinates":[-120.303253,47.414586],"type":"Point"}
}