{
  "type": "Feature",
  "properties": {
    "addr:full":"17606 7th Ave W Bothell WA 98012",
    "addr:housenumber":"17606",
    "addr:postcode":"98012",
    "addr:street":"7Th Ave W",
    "iso:country":"US",
    "sg:address":"17606 7th Ave W",
    "sg:city":"Bothell",
    "sg:classifiers":[
        {
            "category":"Real Estate",
            "subcategory":"Real Estate Services",
            "type":"Services"
        },
        {
            "category":"Real Estate",
            "subcategory":"Real Estate Agent",
            "type":"Services"
        }
    ],
    "sg:phone":"+1 425 741 8085",
    "sg:postcode":"98012",
    "sg:province":"WA",
    "sg:tags":[
        "management"
    ],
    "wof:name":"R S N Enterprises Inc",
    "wof:placetype":"venue"
},
  "geometry": {"coordinates":[-122.242924,47.838028],"type":"Point"}
}