{
  "type": "Feature",
  "properties": {
    "addr:full":"26713 72nd Ave NW Stanwood WA 98292",
    "addr:housenumber":"26713",
    "addr:postcode":"98292",
    "addr:street":"72Nd Ave Nw",
    "iso:country":"US",
    "sg:address":"26713 72nd Ave NW",
    "sg:city":"Stanwood",
    "sg:classifiers":[
        {
            "category":"Fast Food",
            "type":"Food & Drink"
        },
        {
            "category":"Restaurant",
            "type":"Food & Drink"
        }
    ],
    "sg:phone":"+1 360 629 9787",
    "sg:postcode":"98292",
    "sg:province":"WA",
    "sg:tags":[
        "hamburger",
        "hot",
        "dog",
        "american",
        "take",
        "chicken"
    ],
    "sg:website":"http://www.mcdonalds.com",
    "wof:name":"McDonald's",
    "wof:placetype":"venue"
},
  "geometry": {"coordinates":[-122.330235,48.238799],"type":"Point"}
}