{
  "type": "Feature",
  "properties": {
    "addr:full":"421 Park Ave Bremerton WA 98337",
    "addr:housenumber":"421",
    "addr:postcode":"98337",
    "addr:street":"Park Ave",
    "iso:country":"US",
    "sg:address":"421 Park Ave",
    "sg:city":"Bremerton",
    "sg:classifiers":[
        {
            "category":"Professional",
            "subcategory":"Employment Agencies",
            "type":"Services"
        }
    ],
    "sg:phone":"+1 360 782 0785",
    "sg:postcode":"98337",
    "sg:province":"WA",
    "sg:tags":[
        "opportunity"
    ],
    "wof:name":"Ameri Force Inc",
    "wof:placetype":"venue"
},
  "geometry": {"coordinates":[-122.630289,47.566411],"type":"Point"}
}