{
  "type": "Feature",
  "properties": {
    "addr:full":"14505 NE 91st St Redmond WA 98052",
    "addr:housenumber":"14505",
    "addr:postcode":"98052",
    "addr:street":"Ne 91St St",
    "iso:country":"US",
    "sg:address":"14505 NE 91st St",
    "sg:city":"Redmond",
    "sg:classifiers":[
        {
            "category":"Manufacturing",
            "subcategory":"Printing",
            "type":"Manufacturing & Wholesale Goods"
        }
    ],
    "sg:phone":"+1 425 883 1919",
    "sg:postcode":"98052",
    "sg:province":"WA",
    "sg:tags":[
        "typesetting",
        "periodical",
        "li"
    ],
    "wof:name":"Eagle Press",
    "wof:placetype":"venue"
},
  "geometry": {"coordinates":[-122.143939,47.683131],"type":"Point"}
}