{
  "type": "Feature",
  "properties": {
    "addr:full":"13014 E Sprague Ave Spokane Valley WA 99216",
    "addr:housenumber":"13014",
    "addr:postcode":"99216",
    "addr:street":"E Sprague Ave",
    "iso:country":"US",
    "sg:address":"13014 E Sprague Ave",
    "sg:city":"Spokane Valley",
    "sg:classifiers":[
        {
            "category":"Banks & Credit Unions",
            "subcategory":"Bank",
            "type":"Services"
        }
    ],
    "sg:phone":"+1 509 838 6171",
    "sg:postcode":"99216",
    "sg:province":"WA",
    "sg:tags":[
        "federal"
    ],
    "wof:name":"Global Federal Credit Union",
    "wof:placetype":"venue"
},
  "geometry": {"coordinates":[-117.233716,47.656986],"type":"Point"}
}