{
  "type": "Feature",
  "properties": {
    "addr:full":"1719 144th Pl SE Bothell WA 98012",
    "addr:housenumber":"1719",
    "addr:postcode":"98012",
    "addr:street":"144Th Pl Se",
    "iso:country":"US",
    "sg:address":"1719 144th Pl SE",
    "sg:city":"Bothell",
    "sg:classifiers":[
        {
            "category":"Insurance",
            "subcategory":"Insurance Agent",
            "type":"Services"
        }
    ],
    "sg:phone":"+1 425 337 0550",
    "sg:postcode":"98012",
    "sg:province":"WA",
    "wof:name":"R A Baggott Associates Inc",
    "wof:placetype":"venue"
},
  "geometry": {"coordinates":[-122.20921199999999,47.867778],"type":"Point"}
}