{
  "type": "Feature",
  "properties": {
    "addr:full":"12926 E Sanson Ave Spokane WA 99216",
    "addr:housenumber":"12926",
    "addr:postcode":"99216",
    "addr:street":"E Sanson Ave",
    "iso:country":"US",
    "sg:address":"12926 E Sanson Ave",
    "sg:city":"Spokane",
    "sg:classifiers":[
        {
            "category":"Retail",
            "subcategory":"Auto Repair",
            "type":"Services"
        }
    ],
    "sg:phone":"+1 509 928 5515",
    "sg:postcode":"99216",
    "sg:province":"WA",
    "sg:tags":[
        "small",
        "engine"
    ],
    "wof:name":"Rj Small Engine",
    "wof:placetype":"venue"
},
  "geometry": {"coordinates":[-117.23157,47.706415],"type":"Point"}
}