{
  "type": "Feature",
  "properties": {
    "addr:full":"5901 1st Ave NE Seattle WA 98105",
    "addr:housenumber":"5901",
    "addr:postcode":"98105",
    "addr:street":"1St Ave Ne",
    "iso:country":"US",
    "sg:address":"5901 1st Ave NE",
    "sg:city":"Seattle",
    "sg:classifiers":[
        {
            "category":"Building & Trades",
            "subcategory":"Cleaning & Sanitation",
            "type":"Services"
        }
    ],
    "sg:phone":"+1 206 522 3424",
    "sg:postcode":"98105",
    "sg:province":"WA",
    "sg:tags":[
        "maintenance"
    ],
    "wof:name":"Jaz Property Services",
    "wof:placetype":"venue"
},
  "geometry": {"coordinates":[-122.328214,47.67228],"type":"Point"}
}