{
  "type": "Feature",
  "properties": {
    "addr:full":"2727 W Howe St Seattle WA 98199",
    "addr:housenumber":"2727",
    "addr:postcode":"98199",
    "addr:street":"W Howe St",
    "iso:country":"US",
    "sg:address":"2727 W Howe St",
    "sg:city":"Seattle",
    "sg:classifiers":[
        {
            "category":"Sports & Exercise",
            "subcategory":"Swimming Pool",
            "type":"Entertainment"
        }
    ],
    "sg:phone":"+1 206 282 0340",
    "sg:postcode":"98199",
    "sg:province":"WA",
    "sg:tags":[
        "pond",
        "supply"
    ],
    "wof:name":"Patty S Pond Enterprises",
    "wof:placetype":"venue"
},
  "geometry": {"coordinates":[-122.3918,47.63591],"type":"Point"}
}