{
  "type": "Feature",
  "properties": {
    "addr:full":"2110 Westlake Ave N Seattle WA 98109",
    "addr:housenumber":"2110",
    "addr:postcode":"98109",
    "addr:street":"Westlake Ave N",
    "iso:country":"US",
    "sg:address":"2110 Westlake Ave N",
    "sg:city":"Seattle",
    "sg:classifiers":[
        {
            "category":"Building & Trades",
            "subcategory":"Construction",
            "type":"Services"
        }
    ],
    "sg:phone":"+1 206 284 6173",
    "sg:postcode":"98109",
    "sg:province":"WA",
    "sg:tags":[
        "contractor"
    ],
    "wof:name":"Lugo Construction",
    "wof:placetype":"venue"
},
  "geometry": {"coordinates":[-122.341003,47.637798],"type":"Point"}
}