{
  "type": "Feature",
  "properties": {
    "addr:full":"11 Green Ln Republic WA 99166",
    "addr:housenumber":"11",
    "addr:postcode":"99166",
    "addr:street":"Green Ln",
    "iso:country":"US",
    "sg:address":"11 Green Ln",
    "sg:city":"Republic",
    "sg:classifiers":[
        {
            "category":"Shopping",
            "subcategory":"Discount & Variety Stores",
            "type":"Retail Goods"
        }
    ],
    "sg:phone":"+1 509 775 2668",
    "sg:postcode":"99166",
    "sg:province":"WA",
    "sg:tags":[
        "merchandise",
        "general"
    ],
    "wof:name":"David A Orchard",
    "wof:placetype":"venue"
},
  "geometry": {"coordinates":[-118.711647,48.773227],"type":"Point"}
}