{
  "type": "Feature",
  "properties": {
    "addr:full":"13900 28th Dr SE Bothell WA 98012",
    "addr:housenumber":"13900",
    "addr:postcode":"98012",
    "addr:street":"28Th Dr Se",
    "iso:country":"US",
    "sg:address":"13900 28th Dr SE",
    "sg:city":"Bothell",
    "sg:classifiers":[
        {
            "category":"Professional",
            "subcategory":"Computer Services",
            "type":"Services"
        }
    ],
    "sg:phone":"+1 425 338 0945",
    "sg:postcode":"98012",
    "sg:province":"WA",
    "sg:tags":[
        "related"
    ],
    "wof:name":"Hennas Herbals",
    "wof:placetype":"venue"
},
  "geometry": {"coordinates":[-122.19248899999999,47.871041],"type":"Point"}
}