{
  "type": "Feature",
  "properties": {
    "addr:full":"3710 M Ave Anacortes WA 98221",
    "addr:housenumber":"3710",
    "addr:postcode":"98221",
    "addr:street":"M Ave",
    "iso:country":"US",
    "sg:address":"3710 M Ave",
    "sg:city":"Anacortes",
    "sg:classifiers":[
        {
            "category":"Shopping",
            "subcategory":"Computers & Home Electronics",
            "type":"Retail Goods"
        }
    ],
    "sg:phone":"+1 360 293 5386",
    "sg:postcode":"98221",
    "sg:province":"WA",
    "wof:name":"Carls Electronic Service",
    "wof:placetype":"venue"
},
  "geometry": {"coordinates":[-122.617655,48.492275],"type":"Point"}
}