{
  "type": "Feature",
  "properties": {
    "addr:full":"1011 W Mallon Ave Spokane WA 99201",
    "addr:housenumber":"1011",
    "addr:postcode":"99201",
    "addr:street":"W Mallon Ave",
    "iso:country":"US",
    "sg:address":"1011 W Mallon Ave",
    "sg:city":"Spokane",
    "sg:classifiers":[
        {
            "category":"Professional",
            "subcategory":"Lawyer & Legal Services",
            "type":"Services"
        }
    ],
    "sg:phone":"+1 509 326 1020",
    "sg:postcode":"99201",
    "sg:province":"WA",
    "sg:tags":[
        "attorney"
    ],
    "wof:name":"Tracy Scott Collins",
    "wof:placetype":"venue"
},
  "geometry": {"coordinates":[-117.427986,47.665209],"type":"Point"}
}