{
  "type": "Feature",
  "properties": {
    "addr:full":"9 Osterman Rd White Salmon WA 98672",
    "addr:housenumber":"9",
    "addr:postcode":"98672",
    "addr:street":"Osterman Rd",
    "iso:country":"US",
    "sg:address":"9 Osterman Rd",
    "sg:city":"White Salmon",
    "sg:classifiers":[
        {
            "category":"Building & Trades",
            "subcategory":"Construction",
            "type":"Services"
        }
    ],
    "sg:phone":"+1 509 493 1901",
    "sg:postcode":"98672",
    "sg:province":"WA",
    "sg:tags":[
        "excavation",
        "contractor"
    ],
    "wof:name":"Des Verley Contracting",
    "wof:placetype":"venue"
},
  "geometry": {"coordinates":[-121.52029400000001,45.779778],"type":"Point"}
}