{
  "type": "Feature",
  "properties": {
    "addr:full":"929 Pleasant Ave Bremerton WA 98337",
    "addr:housenumber":"929",
    "addr:postcode":"98337",
    "addr:street":"Pleasant Ave",
    "iso:country":"US",
    "sg:address":"929 Pleasant Ave",
    "sg:city":"Bremerton",
    "sg:classifiers":[
        {
            "category":"Shopping",
            "subcategory":"Used Merchandise",
            "type":"Retail Goods"
        }
    ],
    "sg:phone":"+1 360 377 7906",
    "sg:postcode":"98337",
    "sg:province":"WA",
    "wof:name":"Hans Alexander Supit",
    "wof:placetype":"venue"
},
  "geometry": {"coordinates":[-122.62590899999999,47.56753],"type":"Point"}
}