{
  "type": "Feature",
  "properties": {
    "addr:full":"17250 NE 67th Ct Redmond WA 98052",
    "addr:housenumber":"17250",
    "addr:postcode":"98052",
    "addr:street":"Ne 67Th Ct",
    "iso:country":"US",
    "sg:address":"17250 NE 67th Ct",
    "sg:city":"Redmond",
    "sg:classifiers":[
        {
            "category":"Wholesale",
            "subcategory":"Groceries",
            "type":"Manufacturing & Wholesale Goods"
        }
    ],
    "sg:phone":"+1 425 881 0132",
    "sg:postcode":"98052",
    "sg:province":"WA",
    "sg:tags":[
        "confectionery"
    ],
    "wof:name":"Frito-Lay",
    "wof:placetype":"venue"
},
  "geometry": {"coordinates":[-122.10598899999999,47.665306],"type":"Point"}
}