{
  "type": "Feature",
  "properties": {
    "addr:full":"3805 136th Pl SE Bellevue WA 98006",
    "addr:housenumber":"3805",
    "addr:postcode":"98006",
    "addr:street":"136Th Pl Se",
    "iso:country":"US",
    "sg:address":"3805 136th Pl SE",
    "sg:city":"Bellevue",
    "sg:classifiers":[
        {
            "category":"Building & Trades",
            "subcategory":"Landscaping Services",
            "type":"Services"
        }
    ],
    "sg:phone":"+1 425 614 1868",
    "sg:postcode":"98006",
    "sg:province":"WA",
    "sg:tags":[
        "landscape",
        "contractor"
    ],
    "wof:name":"Beautiful Landscapes Nw LLC",
    "wof:placetype":"venue"
},
  "geometry": {"coordinates":[-122.15850500000001,47.575752],"type":"Point"}
}