{
  "type": "Feature",
  "properties": {
    "addr:full":"3005 255th Ave SE Sammamish WA 98075",
    "addr:housenumber":"3005",
    "addr:postcode":"98075",
    "addr:street":"255Th Ave Se",
    "iso:country":"US",
    "sg:address":"3005 255th Ave SE",
    "sg:city":"Sammamish",
    "sg:classifiers":[
        {
            "category":"Building & Trades",
            "subcategory":"Locksmith",
            "type":"Services"
        }
    ],
    "sg:phone":"+1 425 507 0464",
    "sg:postcode":"98075",
    "sg:province":"WA",
    "sg:tags":[
        "key"
    ],
    "wof:name":"Locksmith All Day",
    "wof:placetype":"venue"
},
  "geometry": {"coordinates":[-121.999591,47.581563],"type":"Point"}
}