{
  "type": "Feature",
  "properties": {
    "addr:full":"10315 E Riverside Dr Bothell WA 98011",
    "addr:housenumber":"10315",
    "addr:postcode":"98011",
    "addr:street":"E Riverside Dr",
    "iso:country":"US",
    "sg:address":"10315 E Riverside Dr",
    "sg:city":"Bothell",
    "sg:classifiers":[
        {
            "category":"Health Services",
            "subcategory":"Nursing And Care Facility",
            "type":"Services"
        },
        {
            "category":"Social Services",
            "subcategory":"Retirement Home",
            "type":"Services"
        }
    ],
    "sg:phone":"+1 425 481 1976",
    "sg:postcode":"98011",
    "sg:province":"WA",
    "sg:tags":[
        "living",
        "assisted",
        "convalescent",
        "residential"
    ],
    "sg:website":"http://www.villageconcepts.com",
    "wof:name":"Riverside East",
    "wof:placetype":"venue"
},
  "geometry": {"coordinates":[-122.20228400000001,47.756364],"type":"Point"}
}