{
  "type": "Feature",
  "properties": {
    "addr:full":"17043 2nd Ave NW Seattle WA 98177",
    "addr:housenumber":"17043",
    "addr:postcode":"98177",
    "addr:street":"2Nd Ave Nw",
    "iso:country":"US",
    "sg:address":"17043 2nd Ave NW",
    "sg:city":"Seattle",
    "sg:classifiers":[
        {
            "category":"Organizations",
            "subcategory":"Membership Organization",
            "type":"Services"
        }
    ],
    "sg:phone":"+1 206 542 3056",
    "sg:postcode":"98177",
    "sg:province":"WA",
    "wof:name":"Gambia Help Health Education",
    "wof:placetype":"venue"
},
  "geometry": {"coordinates":[-122.36034100000001,47.753392],"type":"Point"}
}