{
  "type": "Feature",
  "properties": {
    "addr:full":"12014 NE 71st St Vancouver WA 98682",
    "addr:housenumber":"12014",
    "addr:postcode":"98682",
    "addr:street":"Ne 71St St",
    "iso:country":"US",
    "sg:address":"12014 NE 71st St",
    "sg:city":"Vancouver",
    "sg:classifiers":[
        {
            "category":"Professional",
            "type":"Services"
        }
    ],
    "sg:phone":"+1 360 909 4285",
    "sg:postcode":"98682",
    "sg:province":"WA",
    "wof:name":"Trimmers Edge",
    "wof:placetype":"venue"
},
  "geometry": {"coordinates":[-122.548998,45.674439],"type":"Point"}
}