{
  "type": "Feature",
  "properties": {
    "addr:full":"1206 King St Grandview WA 98930",
    "addr:housenumber":"1206",
    "addr:postcode":"98930",
    "addr:street":"King St",
    "iso:country":"US",
    "sg:address":"1206 King St",
    "sg:city":"Grandview",
    "sg:classifiers":[
        {
            "category":"Personal",
            "type":"Services"
        }
    ],
    "sg:phone":"+1 509 882 1622",
    "sg:postcode":"98930",
    "sg:province":"WA",
    "sg:tags":[
        "electrolysis"
    ],
    "wof:name":"Colleen's Electrolysis",
    "wof:placetype":"venue"
},
  "geometry": {"coordinates":[-119.917755,46.248391],"type":"Point"}
}