{
  "type": "Feature",
  "properties": {
    "addr:full":"10117 Edmonds Way Edmonds WA 98020",
    "addr:housenumber":"10117",
    "addr:postcode":"98020",
    "addr:street":"Edmonds Way",
    "iso:country":"US",
    "sg:address":"10117 Edmonds Way",
    "sg:city":"Edmonds",
    "sg:classifiers":[
        {
            "category":"Shopping",
            "type":"Retail Goods"
        }
    ],
    "sg:phone":"+1 425 776 6716",
    "sg:postcode":"98020",
    "sg:province":"WA",
    "sg:tags":[
        "merchandise"
    ],
    "wof:name":"Sunset Auctions",
    "wof:placetype":"venue"
},
  "geometry": {"coordinates":[-122.36903700000001,47.791566],"type":"Point"}
}