{
  "type": "Feature",
  "properties": {
    "addr:full":"9607 54th Ave NW Gig Harbor WA 98332",
    "addr:housenumber":"9607",
    "addr:postcode":"98332",
    "addr:street":"54Th Ave Nw",
    "iso:country":"US",
    "sg:address":"9607 54th Ave NW",
    "sg:city":"Gig Harbor",
    "sg:classifiers":[
        {
            "category":"Retail",
            "subcategory":"Auto Repair",
            "type":"Services"
        }
    ],
    "sg:phone":"+1 253 858 1200",
    "sg:postcode":"98332",
    "sg:province":"WA",
    "sg:tags":[
        "automotive",
        "general"
    ],
    "wof:name":"Phils Automotive",
    "wof:placetype":"venue"
},
  "geometry": {"coordinates":[-122.61027300000001,47.346584],"type":"Point"}
}