{
  "type": "Feature",
  "properties": {
    "addr:full":"114 4th Ave N Edmonds WA 98020",
    "addr:housenumber":"114",
    "addr:postcode":"98020",
    "addr:street":"4Th Ave N",
    "iso:country":"US",
    "sg:address":"114 4th Ave N",
    "sg:city":"Edmonds",
    "sg:classifiers":[
        {
            "category":"Manufacturing",
            "subcategory":"Signs",
            "type":"Manufacturing & Wholesale Goods"
        }
    ],
    "sg:phone":"+1 425 775 2442",
    "sg:postcode":"98020",
    "sg:province":"WA",
    "wof:name":"Forma",
    "wof:placetype":"venue"
},
  "geometry": {"coordinates":[-122.377684,47.811826],"type":"Point"}
}