{
  "type": "Feature",
  "properties": {
    "addr:full":"505 5th Ave S Seattle WA 98104",
    "addr:housenumber":"505",
    "addr:postcode":"98104",
    "addr:street":"5Th Ave S",
    "iso:country":"US",
    "sg:address":"505 5th Ave S",
    "sg:city":"Seattle",
    "sg:classifiers":[
        {
            "category":"Coffee & Tea",
            "type":"Food & Drink"
        },
        {
            "category":"Food & Beverages",
            "subcategory":"Bakery",
            "type":"Retail Goods"
        },
        {
            "category":"Bakery",
            "type":"Food & Drink"
        }
    ],
    "sg:phone":"+1 877 502 2837",
    "sg:postcode":"98104",
    "sg:province":"WA",
    "sg:tags":[
        "sandwich"
    ],
    "sg:website":"specialtysdirect.com",
    "wof:name":"Specialty's Cafe & Bakery",
    "wof:placetype":"venue"
},
  "geometry": {"coordinates":[-122.32767200000001,47.598235],"type":"Point"}
}