{
  "type": "Feature",
  "properties": {
    "addr:full":"780 6th Ave Fi Fox Island WA 98333",
    "addr:housenumber":"780",
    "addr:postcode":"98333",
    "addr:street":"6Th Ave Fi",
    "iso:country":"US",
    "sg:address":"780 6th Ave Fi",
    "sg:city":"Fox Island",
    "sg:classifiers":[
        {
            "category":"Building & Trades",
            "subcategory":"Cleaning & Sanitation",
            "type":"Services"
        }
    ],
    "sg:phone":"+1 253 549 2115",
    "sg:postcode":"98333",
    "sg:province":"WA",
    "sg:tags":[
        "house"
    ],
    "wof:name":"Maid Brigade Pacific Region",
    "wof:placetype":"venue"
},
  "geometry": {"coordinates":[-122.637219,47.251396],"type":"Point"}
}