{
  "type": "Feature",
  "properties": {
    "iso:country":"US",
    "sg:address":"5802 N 33rd St",
    "sg:city":"Tacoma",
    "sg:classifiers":[
        {
            "category":"Real Estate",
            "subcategory":"Real Estate Operator",
            "type":"Services"
        }
    ],
    "sg:phone":"+1 253 759 6827",
    "sg:postcode":"98407",
    "sg:province":"WA",
    "sg:tags":[
        "apartment"
    ],
    "wof:name":"Tacoma Gardens Apartment",
    "wof:placetype":"venue"
},
  "geometry": {"coordinates":[-122.514093,47.277821],"type":"Point"}
}