{
  "type": "Feature",
  "properties": {
    "addr:full":"105 Haywire Rd Napavine WA 98532",
    "addr:housenumber":"105",
    "addr:postcode":"98532",
    "addr:street":"Haywire Rd",
    "iso:country":"US",
    "sg:address":"105 Haywire Rd",
    "sg:city":"Napavine",
    "sg:classifiers":[
        {
            "category":"Real Estate",
            "subcategory":"Real Estate Operator",
            "type":"Services"
        }
    ],
    "sg:phone":"+1 360 262 3972",
    "sg:postcode":"98532",
    "sg:province":"WA",
    "sg:tags":[
        "apartment"
    ],
    "wof:name":"Park Place Apartments",
    "wof:placetype":"venue"
},
  "geometry": {"coordinates":[-122.912682,46.576231],"type":"Point"}
}