{
  "type": "Feature",
  "properties": {
    "addr:full":"6601 Ahtanum Rd Yakima WA 98903",
    "addr:housenumber":"6601",
    "addr:postcode":"98903",
    "addr:street":"Ahtanum Rd",
    "iso:country":"US",
    "sg:address":"6601 Ahtanum Rd",
    "sg:city":"Yakima",
    "sg:phone":"+1 509 966 2676",
    "sg:postcode":"98903",
    "sg:province":"WA",
    "sg:tags":[
        "farm",
        "field",
        "crop"
    ],
    "wof:name":"Larry Record",
    "wof:placetype":"venue"
},
  "geometry": {"coordinates":[-120.595826,46.5584],"type":"Point"}
}