{
  "type": "Feature",
  "properties": {
    "iso:country":"US",
    "sg:address":"228 S Main Ave",
    "sg:city":"Deer Park",
    "sg:classifiers":[
        {
            "category":"Wholesale",
            "subcategory":"Farm Supplies",
            "type":"Manufacturing & Wholesale Goods"
        }
    ],
    "sg:phone":"+1 509 276 2611",
    "sg:postcode":"99006",
    "sg:province":"WA",
    "sg:tags":[
        "fertilizer"
    ],
    "wof:name":"Inland Agronomy",
    "wof:placetype":"venue"
},
  "geometry": {"coordinates":[-117.476997,47.950879],"type":"Point"}
}