{
  "type": "Feature",
  "properties": {
    "addr:full":"16618 NE 26th St Bellevue WA 98008",
    "addr:housenumber":"16618",
    "addr:postcode":"98008",
    "addr:street":"Ne 26Th St",
    "iso:country":"US",
    "sg:address":"16618 NE 26th St",
    "sg:city":"Bellevue",
    "sg:classifiers":[
        {
            "category":"Retail",
            "subcategory":"Auto Repair",
            "type":"Services"
        }
    ],
    "sg:phone":"+1 425 885 7105",
    "sg:postcode":"98008",
    "sg:province":"WA",
    "sg:tags":[
        "body"
    ],
    "wof:name":"Fran Fender",
    "wof:placetype":"venue"
},
  "geometry": {"coordinates":[-122.11714600000001,47.633066],"type":"Point"}
}