{
  "type": "Feature",
  "properties": {
    "addr:full":"1706 Allen St Kelso WA 98626",
    "addr:housenumber":"1706",
    "addr:postcode":"98626",
    "addr:street":"Allen St",
    "iso:country":"US",
    "sg:address":"1706 Allen St",
    "sg:city":"Kelso",
    "sg:classifiers":[
        {
            "category":"Sports & Exercise",
            "subcategory":"Gym",
            "type":"Entertainment"
        }
    ],
    "sg:phone":"+1 360 425 8746",
    "sg:postcode":"98626",
    "sg:province":"WA",
    "sg:tags":[
        "fitness",
        "physical",
        "facility"
    ],
    "wof:name":"Curves For Women",
    "wof:placetype":"venue"
},
  "geometry": {"coordinates":[-122.893557,46.144966],"type":"Point"}
}