{
  "type": "Feature",
  "properties": {
    "addr:full":"16223 143rd Pl SE Renton WA 98058",
    "addr:housenumber":"16223",
    "addr:postcode":"98058",
    "addr:street":"143Rd Pl Se",
    "iso:country":"US",
    "sg:address":"16223 143rd Pl SE",
    "sg:city":"Renton",
    "sg:classifiers":[
        {
            "category":"Manufacturing",
            "subcategory":"Tools & Machinery",
            "type":"Manufacturing & Wholesale Goods"
        }
    ],
    "sg:phone":"+1 425 226 2525",
    "sg:postcode":"98058",
    "sg:province":"WA",
    "sg:tags":[
        "industrial",
        "mfg"
    ],
    "wof:name":"Pacific Precision Manufacturin",
    "wof:placetype":"venue"
},
  "geometry": {"coordinates":[-122.148295,47.456634],"type":"Point"}
}