{
  "type": "Feature",
  "properties": {
    "addr:full":"1905 Continental Pl Mount Vernon WA 98273",
    "addr:housenumber":"1905",
    "addr:postcode":"98273",
    "addr:street":"Continental Pl",
    "iso:country":"US",
    "sg:address":"1905 Continental Pl",
    "sg:city":"Mount Vernon",
    "sg:classifiers":[
        {
            "category":"Health Services",
            "subcategory":"Clinic",
            "type":"Services"
        }
    ],
    "sg:phone":"+1 360 428 7669",
    "sg:postcode":"98273",
    "sg:province":"WA",
    "sg:tags":[
        "specialty",
        "outpatient"
    ],
    "wof:name":"Detoxification Alcohol",
    "wof:placetype":"venue"
},
  "geometry": {"coordinates":[-122.32579,48.437856],"type":"Point"}
}