{
  "type": "Feature",
  "properties": {
    "addr:full":"4806 43rd Ave S Seattle WA 98118",
    "addr:housenumber":"4806",
    "addr:postcode":"98118",
    "addr:street":"43Rd Ave S",
    "iso:country":"US",
    "sg:address":"4806 43rd Ave S",
    "sg:city":"Seattle",
    "sg:classifiers":[
        {
            "category":"Building & Trades",
            "subcategory":"Construction",
            "type":"Services"
        }
    ],
    "sg:phone":"+1 206 359 0611",
    "sg:postcode":"98118",
    "sg:province":"WA",
    "sg:tags":[
        "contractor"
    ],
    "wof:name":"Columbia City Custom",
    "wof:placetype":"venue"
},
  "geometry": {"coordinates":[-122.279093,47.559069],"type":"Point"}
}