{
  "type": "Feature",
  "properties": {
    "addr:full":"4502 SW Brace Point Dr Seattle WA 98136",
    "addr:housenumber":"4502",
    "addr:postcode":"98136",
    "addr:street":"Sw Brace Point Dr",
    "iso:country":"US",
    "sg:address":"4502 SW Brace Point Dr",
    "sg:city":"Seattle",
    "sg:classifiers":[
        {
            "category":"Shopping",
            "subcategory":"Pets & Pet Supplies",
            "type":"Retail Goods"
        }
    ],
    "sg:phone":"+1 206 932 4446",
    "sg:postcode":"98136",
    "sg:province":"WA",
    "sg:tags":[
        "groomers"
    ],
    "sg:website":"www.caninecasa.net",
    "wof:name":"Canine Casa",
    "wof:placetype":"venue"
},
  "geometry": {"coordinates":[-122.390398,47.520216],"type":"Point"}
}