{
  "type": "Feature",
  "properties": {
    "iso:country":"US",
    "sg:address":"10604 SE 4th St",
    "sg:city":"Vancouver",
    "sg:classifiers":[
        {
            "category":"Professional",
            "subcategory":"Business Services",
            "type":"Services"
        }
    ],
    "sg:phone":"+1 360 944 6646",
    "sg:postcode":"98664",
    "sg:province":"WA",
    "wof:name":"C & S Water Features",
    "wof:placetype":"venue"
},
  "geometry": {"coordinates":[-122.56362300000001,45.618903],"type":"Point"}
}