{
  "type": "Feature",
  "properties": {
    "addr:full":"301 NE 191st St Shoreline WA 98155",
    "addr:housenumber":"301",
    "addr:postcode":"98155",
    "addr:street":"Ne 191St St",
    "iso:country":"US",
    "sg:address":"301 NE 191st St",
    "sg:city":"Shoreline",
    "sg:classifiers":[
        {
            "category":"Professional",
            "subcategory":"Business Services",
            "type":"Services"
        }
    ],
    "sg:phone":"+1 206 440 5889",
    "sg:postcode":"98155",
    "sg:province":"WA",
    "sg:tags":[
        "motion",
        "production"
    ],
    "sg:website":"http://www.mirrorsound.com",
    "wof:name":"Mirror Sound Studios",
    "wof:placetype":"venue"
},
  "geometry": {"coordinates":[-122.326927,47.767448],"type":"Point"}
}