{
  "type": "Feature",
  "properties": {
    "addr:full":"5913 NE 127th Ave Ste 100 Vancouver WA 98682",
    "addr:housenumber":"5913",
    "addr:postcode":"98682",
    "addr:street":"Ne 127Th Ave Ste 100",
    "iso:country":"US",
    "sg:address":"5913 NE 127th Ave Ste 100",
    "sg:city":"Vancouver",
    "sg:classifiers":[
        {
            "category":"Building & Trades",
            "subcategory":"Plumbing",
            "type":"Services"
        }
    ],
    "sg:phone":"+1 360 883 4876",
    "sg:postcode":"98682",
    "sg:province":"WA",
    "wof:name":"Fritz Teddy & Sunday",
    "wof:placetype":"venue"
},
  "geometry": {"coordinates":[-122.541354,45.665487],"type":"Point"}
}