{
  "type": "Feature",
  "properties": {
    "addr:full":"18219 96th Ave NE Bothell WA 98011",
    "addr:housenumber":"18219",
    "addr:postcode":"98011",
    "addr:street":"96Th Ave Ne",
    "iso:country":"US",
    "sg:address":"18219 96th Ave NE",
    "sg:city":"Bothell",
    "sg:classifiers":[
        {
            "category":"Professional",
            "subcategory":"Computer Services",
            "type":"Services"
        }
    ],
    "sg:phone":"+1 425 806 6965",
    "sg:postcode":"98011",
    "sg:province":"WA",
    "wof:name":"Automated Systems",
    "wof:placetype":"venue"
},
  "geometry": {"coordinates":[-122.212552,47.759097],"type":"Point"}
}