{
  "type": "Feature",
  "properties": {
    "addr:full":"3119 20th St Everett WA 98201",
    "addr:housenumber":"3119",
    "addr:postcode":"98201",
    "addr:street":"20Th St",
    "iso:country":"US",
    "sg:address":"3119 20th St",
    "sg:city":"Everett",
    "sg:classifiers":[
        {
            "category":"Building & Trades",
            "subcategory":"Cleaning & Sanitation",
            "type":"Services"
        }
    ],
    "sg:phone":"+1 425 252 1832",
    "sg:postcode":"98201",
    "sg:province":"WA",
    "sg:tags":[
        "maintenance"
    ],
    "wof:name":"Chadwicks Building Service",
    "wof:placetype":"venue"
},
  "geometry": {"coordinates":[-122.18812,47.991004],"type":"Point"}
}