{
  "type": "Feature",
  "properties": {
    "addr:full":"33758 Eglon Rd NE Kingston WA 98346",
    "addr:postcode":"33758;98346",
    "addr:street":"Eglon Rd Ne",
    "iso:country":"US",
    "sg:address":"33758 Eglon Rd NE",
    "sg:city":"Kingston",
    "sg:classifiers":[
        {
            "category":"Farming",
            "subcategory":"Fish & Marine Products",
            "type":"Manufacturing & Wholesale Goods"
        },
        {
            "category":"Recreation",
            "subcategory":"Fishing",
            "type":"Entertainment"
        }
    ],
    "sg:phone":"+1 360 638 1958",
    "sg:postcode":"98346",
    "sg:province":"WA",
    "sg:tags":[
        "pond",
        "pier",
        "lake"
    ],
    "wof:name":"D S R Inc",
    "wof:placetype":"venue"
},
  "geometry": {"coordinates":[-122.519212,47.86549],"type":"Point"}
}