{
  "type": "Feature",
  "properties": {
    "addr:full":"15212 NE 95th St Redmond WA 98052",
    "addr:housenumber":"15212",
    "addr:postcode":"98052",
    "addr:street":"Ne 95Th St",
    "iso:country":"US",
    "sg:address":"15212 NE 95th St",
    "sg:city":"Redmond",
    "sg:classifiers":[
        {
            "category":"Education",
            "subcategory":"School",
            "type":"Public Place"
        }
    ],
    "sg:phone":"+1 425 882 5100",
    "sg:postcode":"98052",
    "sg:province":"WA",
    "sg:tags":[
        "high"
    ],
    "sg:website":"http://www.lwsd.org",
    "wof:name":"Lake Washington School District No 414",
    "wof:placetype":"venue"
},
  "geometry": {"coordinates":[-122.137289,47.685842],"type":"Point"}
}