{
  "type": "Feature",
  "properties": {
    "addr:full":"502 2nd Ave SE Ephrata WA 98823",
    "addr:housenumber":"502",
    "addr:postcode":"98823",
    "addr:street":"2Nd Ave Se",
    "iso:country":"US",
    "sg:address":"502 2nd Ave SE",
    "sg:city":"Ephrata",
    "sg:classifiers":[
        {
            "category":"Shopping",
            "type":"Retail Goods"
        }
    ],
    "sg:phone":"+1 509 754 9453",
    "sg:postcode":"98823",
    "sg:province":"WA",
    "sg:tags":[
        "merchandise"
    ],
    "wof:name":"Western States Fire Equipment",
    "wof:placetype":"venue"
},
  "geometry": {"coordinates":[-119.544138,47.314354],"type":"Point"}
}