{
  "type": "Feature",
  "properties": {
    "addr:full":"1103 Boylston Ave Seattle WA 98101",
    "addr:housenumber":"1103",
    "addr:postcode":"98101",
    "addr:street":"Boylston Ave",
    "iso:country":"US",
    "sg:address":"1103 Boylston Ave",
    "sg:city":"Seattle",
    "sg:classifiers":[
        {
            "category":"Personal",
            "subcategory":"Beauty Salon",
            "type":"Services"
        }
    ],
    "sg:phone":"+1 206 324 7676",
    "sg:postcode":"98101",
    "sg:province":"WA",
    "sg:tags":[
        "shop"
    ],
    "wof:name":"Salon Sovaga",
    "wof:placetype":"venue"
},
  "geometry": {"coordinates":[-122.32317,47.612103],"type":"Point"}
}