{
  "type": "Feature",
  "properties": {
    "addr:full":"4708 Tree Ridge Ln NE Poulsbo WA 98370",
    "addr:housenumber":"4708",
    "addr:postcode":"98370",
    "addr:street":"Tree Ridge Ln Ne",
    "iso:country":"US",
    "sg:address":"4708 Tree Ridge Ln NE",
    "sg:city":"Poulsbo",
    "sg:classifiers":[
        {
            "category":"Wholesale",
            "subcategory":"Books, Periodicals, & Newspapers",
            "type":"Manufacturing & Wholesale Goods"
        }
    ],
    "sg:phone":"+1 360 697 2777",
    "sg:postcode":"98370",
    "sg:province":"WA",
    "sg:tags":[
        "dealers-wholesale",
        "news"
    ],
    "sg:website":"http://www.seventhraypress.com",
    "wof:name":"Seventh Ray Press",
    "wof:placetype":"venue"
},
  "geometry": {"coordinates":[-122.584729,47.762167],"type":"Point"}
}