{
  "type": "Feature",
  "properties": {
    "addr:full":"213 Yakima Valley Hwy Sunnyside WA 98944",
    "addr:housenumber":"213",
    "addr:postcode":"98944",
    "addr:street":"Yakima Valley Hwy",
    "iso:country":"US",
    "sg:address":"213 Yakima Valley Hwy",
    "sg:city":"Sunnyside",
    "sg:classifiers":[
        {
            "category":"Wholesale",
            "subcategory":"Furniture",
            "type":"Manufacturing & Wholesale Goods"
        },
        {
            "category":"Home & Garden",
            "subcategory":"Furniture",
            "type":"Retail Goods"
        }
    ],
    "sg:phone":"+1 509 836 2005",
    "sg:postcode":"98944",
    "sg:province":"WA",
    "sg:tags":[
        "store",
        "furniture-wholesale",
        "manufacturer"
    ],
    "wof:name":"El Real Furniture",
    "wof:placetype":"venue"
},
  "geometry": {"coordinates":[-120.01829600000001,46.33014],"type":"Point"}
}