{
  "type": "Feature",
  "properties": {
    "iso:country":"US",
    "sg:address":"714 N 179th St",
    "sg:city":"Seattle",
    "sg:classifiers":[
        {
            "category":"Professional",
            "subcategory":"Detective & Security Services",
            "type":"Services"
        }
    ],
    "sg:phone":"+1 206 546 1376",
    "sg:postcode":"98133",
    "sg:province":"WA",
    "sg:tags":[
        "car"
    ],
    "wof:name":"Pac Security Services",
    "wof:placetype":"venue"
},
  "geometry": {"coordinates":[-122.348535,47.758337],"type":"Point"}
}