{
  "type": "Feature",
  "properties": {
    "addr:full":"22637 96th Pl S Kent WA 98031",
    "addr:housenumber":"22637",
    "addr:postcode":"98031",
    "addr:street":"96Th Pl S",
    "iso:country":"US",
    "sg:address":"22637 96th Pl S",
    "sg:city":"Kent",
    "sg:classifiers":[
        {
            "category":"Professional",
            "subcategory":"Computer Services",
            "type":"Services"
        }
    ],
    "sg:phone":"+1 360 866 0655",
    "sg:postcode":"98031",
    "sg:province":"WA",
    "sg:tags":[
        "related"
    ],
    "wof:name":"Ceo Ltd",
    "wof:placetype":"venue"
},
  "geometry": {"coordinates":[-122.21156999999999,47.399659],"type":"Point"}
}