{
  "type": "Feature",
  "properties": {
    "addr:full":"9469 Silverdale Way NW Silverdale WA 98383",
    "addr:housenumber":"9469",
    "addr:postcode":"98383",
    "addr:street":"Silverdale Way Nw",
    "iso:country":"US",
    "sg:address":"9469 Silverdale Way NW",
    "sg:city":"Silverdale",
    "sg:classifiers":[
        {
            "category":"Restaurant",
            "type":"Food & Drink"
        }
    ],
    "sg:phone":"+1 360 692 5504",
    "sg:postcode":"98383",
    "sg:province":"WA",
    "sg:tags":[
        "mongolian"
    ],
    "wof:name":"Golden Grill Mongolian Barbeque",
    "wof:placetype":"venue"
},
  "geometry": {"coordinates":[-122.695432,47.649226],"type":"Point"}
}