{
  "type": "Feature",
  "properties": {
    "addr:full":"216 W Main Ave Ritzville WA 99169",
    "addr:housenumber":"216",
    "addr:postcode":"99169",
    "addr:street":"W Main Ave",
    "iso:country":"US",
    "sg:address":"216 W Main Ave",
    "sg:city":"Ritzville",
    "sg:classifiers":[
        {
            "category":"Personal",
            "subcategory":"Beauty Salon",
            "type":"Services"
        }
    ],
    "sg:phone":"+1 509 659 1562",
    "sg:postcode":"99169",
    "sg:province":"WA",
    "wof:name":"Hollie's Headlines",
    "wof:placetype":"venue"
},
  "geometry": {"coordinates":[-118.380892,47.126792],"type":"Point"}
}