{
  "type": "Feature",
  "properties": {
    "iso:country":"US",
    "sg:address":"8019 144th Dr SE",
    "sg:city":"Snohomish",
    "sg:classifiers":[
        {
            "category":"Restaurant",
            "type":"Food & Drink"
        }
    ],
    "sg:phone":"+1 360 568 9488",
    "sg:postcode":"98290",
    "sg:province":"WA",
    "sg:tags":[
        "eating"
    ],
    "wof:name":"Wendys",
    "wof:placetype":"venue"
},
  "geometry": {"coordinates":[-122.038354,47.923105],"type":"Point"}
}