{
  "type": "Feature",
  "properties": {
    "addr:full":"170 Winslow Way E Bainbridge Isle WA 98110",
    "addr:housenumber":"170",
    "addr:postcode":"98110",
    "addr:street":"Winslow Way E;Isle",
    "iso:country":"US",
    "sg:address":"170 Winslow Way E",
    "sg:city":"Bainbridge Isle",
    "sg:classifiers":[
        {
            "category":"Personal",
            "subcategory":"Barber",
            "type":"Services"
        }
    ],
    "sg:phone":"+1 206 842 2189",
    "sg:postcode":"98110",
    "sg:province":"WA",
    "sg:tags":[
        "shop"
    ],
    "wof:name":"Chuck's Barber Shop",
    "wof:placetype":"venue"
},
  "geometry": {"coordinates":[-122.520112,47.624947],"type":"Point"}
}