{
  "type": "Feature",
  "properties": {
    "addr:full":"2015 S Quincy Pl Kennewick WA 99337",
    "addr:housenumber":"2015",
    "addr:postcode":"99337",
    "addr:street":"S Quincy Pl",
    "iso:country":"US",
    "sg:address":"2015 S Quincy Pl",
    "sg:city":"Kennewick",
    "sg:classifiers":[
        {
            "category":"Building & Trades",
            "subcategory":"Construction",
            "type":"Services"
        },
        {
            "category":"Shopping",
            "subcategory":"Bicycles & Sporting Goods",
            "type":"Retail Goods"
        }
    ],
    "sg:phone":"+1 509 586 4441",
    "sg:postcode":"99337",
    "sg:province":"WA",
    "sg:tags":[
        "contractor"
    ],
    "wof:name":"Athletics Unlimited Corp",
    "wof:placetype":"venue"
},
  "geometry": {"coordinates":[-119.14124099999999,46.190711],"type":"Point"}
}