{
  "type": "Feature",
  "properties": {
    "iso:country":"US",
    "sg:address":"1717 Olympia Way",
    "sg:city":"Longview",
    "sg:classifiers":[
        {
            "category":"Health Services",
            "subcategory":"Health Practitioner",
            "type":"Services"
        }
    ],
    "sg:phone":"+1 360 577 8989",
    "sg:postcode":"98632",
    "sg:province":"WA",
    "sg:tags":[
        "acupuncture"
    ],
    "wof:name":"Sun & Moon Acupuncture Clinic",
    "wof:placetype":"venue"
},
  "geometry": {"coordinates":[-122.94020399999999,46.141037],"type":"Point"}
}