{
  "type": "Feature",
  "properties": {
    "addr:full":"1658 NE Sawdust Hill Rd Poulsbo WA 98370",
    "addr:housenumber":"1658",
    "addr:postcode":"98370",
    "addr:street":"Ne Sawdust Hill Rd",
    "iso:country":"US",
    "sg:address":"1658 NE Sawdust Hill Rd",
    "sg:city":"Poulsbo",
    "sg:classifiers":[
        {
            "category":"Travel",
            "subcategory":"Travel Agent",
            "type":"Entertainment"
        }
    ],
    "sg:phone":"+1 360 598 2200",
    "sg:postcode":"98370",
    "sg:province":"WA",
    "sg:tags":[
        "agency",
        "services-commercial"
    ],
    "wof:name":"Traveler's Life",
    "wof:placetype":"venue"
},
  "geometry": {"coordinates":[-122.628688,47.773664],"type":"Point"}
}