{
  "type": "Feature",
  "properties": {
    "iso:country":"US",
    "sg:address":"15430 Cottonwood Ln",
    "sg:city":"Mount Vernon",
    "sg:classifiers":[
        {
            "category":"Professional",
            "subcategory":"Management & Consulting",
            "type":"Services"
        }
    ],
    "sg:phone":"+1 360 424 9296",
    "sg:postcode":"98273",
    "sg:province":"WA",
    "sg:tags":[
        "business"
    ],
    "wof:name":"Dan Nelson Consulting",
    "wof:placetype":"venue"
},
  "geometry": {"coordinates":[-122.36279999999999,48.42228],"type":"Point"}
}