{
  "type": "Feature",
  "properties": {
    "addr:full":"2201 Shawnee Rd Pullman WA 99163",
    "addr:housenumber":"2201",
    "addr:postcode":"99163",
    "addr:street":"Shawnee Rd",
    "iso:country":"US",
    "sg:address":"2201 Shawnee Rd",
    "sg:city":"Pullman",
    "sg:classifiers":[
        {
            "category":"Professional",
            "subcategory":"Business Services",
            "type":"Services"
        },
        {
            "category":"Real Estate",
            "subcategory":"Developer",
            "type":"Services"
        }
    ],
    "sg:phone":"+1 509 397 3218",
    "sg:postcode":"99163",
    "sg:province":"WA",
    "sg:tags":[
        "land",
        "holding"
    ],
    "wof:name":"Cochran Land Corp",
    "wof:placetype":"venue"
},
  "geometry": {"coordinates":[-117.27716599999999,46.825622],"type":"Point"}
}