{
  "type": "Feature",
  "properties": {
    "addr:full":"3023 1st Avenue Seattle WA 98121",
    "addr:housenumber":"3023",
    "addr:postcode":"98121",
    "addr:street":"1St Avenue",
    "iso:country":"US",
    "sg:address":"3023 1st Avenue",
    "sg:city":"Seattle",
    "sg:classifiers":[
        {
            "category":"Real Estate",
            "subcategory":"Real Estate Operator",
            "type":"Services"
        }
    ],
    "sg:phone":"+1 206 448 0847",
    "sg:postcode":"98121",
    "sg:province":"WA",
    "sg:tags":[
        "apartment"
    ],
    "wof:name":"Eagle Bayt Apartments",
    "wof:placetype":"venue"
},
  "geometry": {"coordinates":[-122.35397399999999,47.617759],"type":"Point"}
}