{
  "type": "Feature",
  "properties": {
    "addr:full":"125 N Bend Blvd N North Bend WA 98045",
    "addr:housenumber":"125",
    "addr:postcode":"98045",
    "addr:street":"N Bend Blvd N",
    "iso:country":"US",
    "sg:address":"125 N Bend Blvd N",
    "sg:city":"North Bend",
    "sg:classifiers":[
        {
            "category":"Retail",
            "subcategory":"Self-service Laundry",
            "type":"Services"
        }
    ],
    "sg:phone":"+1 425 888 2501",
    "sg:postcode":"98045",
    "sg:province":"WA",
    "sg:tags":[
        "dry",
        "cleaner"
    ],
    "wof:name":"Snoqualmie Coin Laundry",
    "wof:placetype":"venue"
},
  "geometry": {"coordinates":[-121.78630099999999,47.496064],"type":"Point"}
}