{
  "type": "Feature",
  "properties": {
    "addr:full":"1704 Discovery Rd Port Townsend WA 98368",
    "addr:housenumber":"1704",
    "addr:postcode":"98368",
    "addr:street":"Discovery Rd",
    "iso:country":"US",
    "sg:address":"1704 Discovery Rd",
    "sg:city":"Port Townsend",
    "sg:classifiers":[
        {
            "category":"Organizations",
            "subcategory":"Religious Organization",
            "type":"Services"
        }
    ],
    "sg:phone":"+1 360 385 2545",
    "sg:postcode":"98368",
    "sg:province":"WA",
    "sg:tags":[
        "church"
    ],
    "sg:website":"www.sanjuanbaptist.org",
    "wof:name":"San Juan Baptist Church Inc",
    "wof:placetype":"venue"
},
  "geometry": {"coordinates":[-122.79382200000001,48.113099],"type":"Point"}
}