{
  "type": "Feature",
  "properties": {
    "addr:full":"2802 NW 7th St Battle Ground WA 98604",
    "addr:housenumber":"2802",
    "addr:postcode":"98604",
    "addr:street":"Nw 7Th St",
    "iso:country":"US",
    "sg:address":"2802 NW 7th St",
    "sg:city":"Battle Ground",
    "sg:classifiers":[
        {
            "category":"Food & Beverages",
            "subcategory":"Bakery",
            "type":"Retail Goods"
        }
    ],
    "sg:phone":"+1 360 666 1515",
    "sg:postcode":"98604",
    "sg:province":"WA",
    "wof:name":"Cakes By Sandra",
    "wof:placetype":"venue"
},
  "geometry": {"coordinates":[-122.566227,45.785962],"type":"Point"}
}