{
  "type": "Feature",
  "properties": {
    "addr:full":"22316 70th Ave W Mountlake Ter WA 98043",
    "addr:housenumber":"22316",
    "addr:postcode":"98043",
    "addr:street":"70Th Ave W Mountlake Ter",
    "iso:country":"US",
    "sg:address":"22316 70th Ave W",
    "sg:city":"Mountlake Ter",
    "sg:classifiers":[
        {
            "category":"Social Services",
            "subcategory":"Job Training",
            "type":"Services"
        },
        {
            "category":"Professional",
            "subcategory":"Employment Agencies",
            "type":"Services"
        }
    ],
    "sg:phone":"+1 425 774 3338",
    "sg:postcode":"98043",
    "sg:province":"WA",
    "sg:tags":[
        "opportunity"
    ],
    "sg:website":"www.wvs.org",
    "wof:name":"Washington Vocational Services",
    "wof:placetype":"venue"
},
  "geometry": {"coordinates":[-122.327691,47.796899],"type":"Point"}
}