{
  "type": "Feature",
  "properties": {
    "addr:full":"12701 Palatine Ave N Seattle WA 98133",
    "addr:housenumber":"12701",
    "addr:postcode":"98133",
    "addr:street":"Palatine Ave N",
    "iso:country":"US",
    "sg:address":"12701 Palatine Ave N",
    "sg:city":"Seattle",
    "sg:classifiers":[
        {
            "category":"Health Services",
            "subcategory":"Nursing And Care Facility",
            "type":"Services"
        }
    ],
    "sg:phone":"+1 206 363 2747",
    "sg:postcode":"98133",
    "sg:province":"WA",
    "sg:tags":[
        "skilled"
    ],
    "wof:name":"Terrace Care Family Homes Inc",
    "wof:placetype":"venue"
},
  "geometry": {"coordinates":[-122.356888,47.723239],"type":"Point"}
}