{
  "type": "Feature",
  "properties": {
    "addr:full":"19721 SE 264th Pl Covington WA 98042",
    "addr:postcode":"19721;98042",
    "addr:street":"Se 264Th Pl",
    "iso:country":"US",
    "sg:address":"19721 SE 264th Pl",
    "sg:city":"Covington",
    "sg:classifiers":[
        {
            "category":"Wholesale",
            "subcategory":"Medical Equipment & Supplies",
            "type":"Manufacturing & Wholesale Goods"
        }
    ],
    "sg:phone":"+1 253 630 5798",
    "sg:postcode":"98042",
    "sg:province":"WA",
    "sg:tags":[
        "alarm"
    ],
    "wof:name":"Companion Call Light",
    "wof:placetype":"venue"
},
  "geometry": {"coordinates":[-122.07872,47.364905],"type":"Point"}
}