{
  "type": "Feature",
  "properties": {
    "addr:full":"122 Madrone Ln N Bainbridge Island WA 98110",
    "addr:housenumber":"122",
    "addr:postcode":"98110",
    "addr:street":"Madrone Ln N",
    "iso:country":"US",
    "sg:address":"122 Madrone Ln N",
    "sg:city":"Bainbridge Island",
    "sg:classifiers":[
        {
            "category":"Professional",
            "type":"Services"
        }
    ],
    "sg:phone":"+1 206 366 0247",
    "sg:postcode":"98110",
    "sg:province":"WA",
    "wof:name":"John Edward Brotherton In",
    "wof:placetype":"venue"
},
  "geometry": {"coordinates":[-122.519535,47.625087],"type":"Point"}
}