{
  "type": "Feature",
  "properties": {
    "addr:full":"32 91st Ave SE Everett WA 98205",
    "addr:housenumber":"32",
    "addr:postcode":"98205",
    "addr:street":"91St Ave Se",
    "iso:country":"US",
    "sg:address":"32 91st Ave SE",
    "sg:city":"Everett",
    "sg:classifiers":[
        {
            "category":"Manufacturing",
            "subcategory":"Tools & Machinery",
            "type":"Manufacturing & Wholesale Goods"
        }
    ],
    "sg:phone":"+1 425 334 9860",
    "sg:postcode":"98205",
    "sg:province":"WA",
    "sg:tags":[
        "equipment",
        "coding",
        "check",
        "bank",
        "mfg"
    ],
    "wof:name":"Interntional Micr Encoding Inc",
    "wof:placetype":"venue"
},
  "geometry": {"coordinates":[-122.10861300000001,47.996471],"type":"Point"}
}