{
  "type": "Feature",
  "properties": {
    "addr:full":"1821 Plaza Way Walla Walla WA 99362",
    "addr:housenumber":"1821",
    "addr:postcode":"99362",
    "addr:street":"Plaza Way",
    "iso:country":"US",
    "sg:address":"1821 Plaza Way",
    "sg:city":"Walla Walla",
    "sg:classifiers":[
        {
            "category":"Real Estate",
            "subcategory":"Real Estate Operator",
            "type":"Services"
        }
    ],
    "sg:phone":"+1 509 526 7650",
    "sg:postcode":"99362",
    "sg:province":"WA",
    "sg:tags":[
        "building",
        "apartment"
    ],
    "wof:name":"Stonecreek Apartments",
    "wof:placetype":"venue"
},
  "geometry": {"coordinates":[-118.346023,46.046113],"type":"Point"}
}