{
  "type": "Feature",
  "properties": {
    "addr:full":"4455 7th Ave S Seattle WA 98108",
    "addr:housenumber":"4455",
    "addr:postcode":"98108",
    "addr:street":"7Th Ave S",
    "iso:country":"US",
    "sg:address":"4455 7th Ave S",
    "sg:city":"Seattle",
    "sg:classifiers":[
        {
            "category":"Freight",
            "type":"Transportation"
        }
    ],
    "sg:phone":"+1 206 621 6382",
    "sg:postcode":"98108",
    "sg:province":"WA",
    "sg:tags":[
        "courier"
    ],
    "wof:name":"UPS",
    "wof:placetype":"venue"
},
  "geometry": {"coordinates":[-122.32410299999999,47.563826],"type":"Point"}
}