{
  "type": "Feature",
  "properties": {
    "addr:full":"7108 39th Ave SW Seattle WA 98126",
    "addr:housenumber":"7108",
    "addr:postcode":"98126",
    "addr:street":"39Th Ave Sw",
    "iso:country":"US",
    "sg:address":"7108 39th Ave SW",
    "sg:city":"Seattle",
    "sg:classifiers":[
        {
            "category":"Building & Trades",
            "subcategory":"Construction",
            "type":"Services"
        }
    ],
    "sg:phone":"+1 206 228 2263",
    "sg:postcode":"98126",
    "sg:province":"WA",
    "sg:tags":[
        "contractor"
    ],
    "wof:name":"Velvet Hammer",
    "wof:placetype":"venue"
},
  "geometry": {"coordinates":[-122.381694,47.539375],"type":"Point"}
}