{
  "type": "Feature",
  "properties": {
    "addr:full":"9650 15th Ave SW Seattle WA 98106",
    "addr:housenumber":"9650",
    "addr:postcode":"98106",
    "addr:street":"15Th Ave Sw",
    "iso:country":"US",
    "sg:address":"9650 15th Ave SW",
    "sg:city":"Seattle",
    "sg:classifiers":[
        {
            "category":"Health Services",
            "subcategory":"Clinic",
            "type":"Services"
        }
    ],
    "sg:phone":"+1 206 341 7430",
    "sg:postcode":"98106",
    "sg:province":"WA",
    "sg:tags":[
        "medical"
    ],
    "sg:website":"fortress.wa.gov/dshs/f2ws03esaap...",
    "wof:name":"DSHS - White Center",
    "wof:placetype":"venue"
},
  "geometry": {"coordinates":[-122.353441,47.516236],"type":"Point"}
}