{
  "type": "Feature",
  "properties": {
    "addr:full":"3400 W 1st Pl Apt 4 Kennewick WA 99336",
    "addr:housenumber":"3400;4",
    "addr:postcode":"99336",
    "addr:street":"W 1St Pl Apt",
    "iso:country":"US",
    "sg:address":"3400 W 1st Pl Apt 4",
    "sg:city":"Kennewick",
    "sg:classifiers":[
        {
            "category":"Real Estate",
            "subcategory":"Real Estate Operator",
            "type":"Services"
        }
    ],
    "sg:phone":"+1 509 783 0404",
    "sg:postcode":"99336",
    "sg:province":"WA",
    "sg:tags":[
        "apartment"
    ],
    "wof:name":"Cedars Apartments",
    "wof:placetype":"venue"
},
  "geometry": {"coordinates":[-119.167574,46.208241],"type":"Point"}
}