{
  "type": "Feature",
  "properties": {
    "addr:full":"5225 W Canal Dr Kennewick WA 99336",
    "addr:housenumber":"5225",
    "addr:postcode":"99336",
    "addr:street":"W Canal Dr",
    "iso:country":"US",
    "sg:address":"5225 W Canal Dr",
    "sg:city":"Kennewick",
    "sg:classifiers":[
        {
            "category":"Retail",
            "subcategory":"Laundry & Dry Cleaning",
            "type":"Services"
        }
    ],
    "sg:phone":"+1 509 783 7835",
    "sg:postcode":"99336",
    "sg:province":"WA",
    "sg:tags":[
        "drycleaning",
        "plant"
    ],
    "wof:name":"Royal Cleaners",
    "wof:placetype":"venue"
},
  "geometry": {"coordinates":[-119.191659,46.223227],"type":"Point"}
}