{
  "type": "Feature",
  "properties": {
    "addr:full":"19125 N Dunn Rd Colbert WA 99005",
    "addr:housenumber":"19125",
    "addr:postcode":"99005",
    "addr:street":"N Dunn Rd Colbert",
    "iso:country":"US",
    "sg:address":"19125 N Dunn Rd",
    "sg:city":"Colbert",
    "sg:classifiers":[
        {
            "category":"Arts & Performance",
            "subcategory":"Art Gallery",
            "type":"Entertainment"
        }
    ],
    "sg:phone":"+1 509 238 9475",
    "sg:postcode":"99005",
    "sg:province":"WA",
    "sg:tags":[
        "fine",
        "artist"
    ],
    "wof:name":"Judy's Originals",
    "wof:placetype":"venue"
},
  "geometry": {"coordinates":[-117.28266499999999,47.831731],"type":"Point"}
}