{
  "type": "Feature",
  "properties": {
    "addr:full":"679 Union St Seattle WA 98101",
    "addr:housenumber":"679",
    "addr:postcode":"98101",
    "addr:street":"Union St",
    "iso:country":"US",
    "sg:address":"679 Union St",
    "sg:city":"Seattle",
    "sg:classifiers":[
        {
            "category":"Building & Trades",
            "subcategory":"Plumbing",
            "type":"Services"
        }
    ],
    "sg:phone":"+1 253 987 5473",
    "sg:postcode":"98101",
    "sg:province":"WA",
    "wof:name":"Plumbing and Drain Cleaning Seattle",
    "wof:placetype":"venue"
},
  "geometry": {"coordinates":[-122.332686,47.610509],"type":"Point"}
}