{
  "type": "Feature",
  "properties": {
    "addr:full":"500 SE Washington Ave Chehalis WA 98532",
    "addr:housenumber":"500",
    "addr:postcode":"98532",
    "addr:street":"Se Washington Ave",
    "iso:country":"US",
    "sg:address":"500 SE Washington Ave",
    "sg:city":"Chehalis",
    "sg:classifiers":[
        {
            "category":"Social Services",
            "type":"Services"
        }
    ],
    "sg:phone":"+1 360 740 8370",
    "sg:postcode":"98532",
    "sg:province":"WA",
    "sg:tags":[
        "senior",
        "citizen"
    ],
    "wof:name":"Lifeline Program",
    "wof:placetype":"venue"
},
  "geometry": {"coordinates":[-122.95964499999999,46.659721],"type":"Point"}
}