{
  "type": "Feature",
  "properties": {
    "addr:full":"16710 E Euclid Ave Spokane Valley WA 99216",
    "addr:housenumber":"16710",
    "addr:postcode":"99216",
    "addr:street":"E Euclid Ave",
    "iso:country":"US",
    "sg:address":"16710 E Euclid Ave",
    "sg:city":"Spokane Valley",
    "sg:classifiers":[
        {
            "category":"Building & Trades",
            "subcategory":"Construction",
            "type":"Services"
        }
    ],
    "sg:phone":"+1 509 921 7089",
    "sg:postcode":"99216",
    "sg:province":"WA",
    "sg:tags":[
        "product",
        "asphalt"
    ],
    "wof:name":"Koch Materials Co",
    "wof:placetype":"venue"
},
  "geometry": {"coordinates":[-117.182676,47.683856],"type":"Point"}
}