{
  "type": "Feature",
  "properties": {
    "addr:full":"34 S Colville St Walla Walla WA 99362",
    "addr:housenumber":"34",
    "addr:postcode":"99362",
    "addr:street":"S Colville St",
    "iso:country":"US",
    "sg:address":"34 S Colville St",
    "sg:city":"Walla Walla",
    "sg:classifiers":[
        {
            "category":"Personal",
            "subcategory":"Barber",
            "type":"Services"
        }
    ],
    "sg:phone":"+1 509 522 6393",
    "sg:postcode":"99362",
    "sg:province":"WA",
    "sg:tags":[
        "shop"
    ],
    "wof:name":"Sung's Barber Shop",
    "wof:placetype":"venue"
},
  "geometry": {"coordinates":[-118.336485,46.067441],"type":"Point"}
}