{
  "type": "Feature",
  "properties": {
    "addr:full":"19212 N Austin Rd Colbert WA 99005",
    "addr:housenumber":"19212",
    "addr:postcode":"99005",
    "addr:street":"N Austin Rd Colbert",
    "iso:country":"US",
    "sg:address":"19212 N Austin Rd",
    "sg:city":"Colbert",
    "sg:classifiers":[
        {
            "category":"Farming",
            "subcategory":"Livestock Farm",
            "type":"Manufacturing & Wholesale Goods"
        }
    ],
    "sg:phone":"+1 509 465 5079",
    "sg:postcode":"99005",
    "sg:province":"WA",
    "sg:tags":[
        "beef",
        "feedlot",
        "cattle"
    ],
    "wof:name":"Randall K Love",
    "wof:placetype":"venue"
},
  "geometry": {"coordinates":[-117.44325000000001,47.836442],"type":"Point"}
}