{
  "type": "Feature",
  "properties": {
    "addr:full":"4630 Village Ct NE Seattle WA 98105",
    "addr:housenumber":"4630",
    "addr:postcode":"98105",
    "addr:street":"Village Ct Ne",
    "iso:country":"US",
    "sg:address":"4630 Village Ct NE",
    "sg:city":"Seattle",
    "sg:classifiers":[
        {
            "category":"Arts & Performance",
            "subcategory":"Art Gallery",
            "type":"Entertainment"
        }
    ],
    "sg:phone":"+1 206 525 2400",
    "sg:postcode":"98105",
    "sg:province":"WA",
    "sg:website":"www.theartstudy.com/",
    "wof:name":"The Art Study",
    "wof:placetype":"venue"
},
  "geometry": {"coordinates":[-122.299165,47.663276],"type":"Point"}
}