{
  "type": "Feature",
  "properties": {
    "addr:full":"8400 55th Ave S Seattle WA 98118",
    "addr:housenumber":"8400",
    "addr:postcode":"98118",
    "addr:street":"55Th Ave S",
    "iso:country":"US",
    "sg:address":"8400 55th Ave S",
    "sg:city":"Seattle",
    "sg:classifiers":[
        {
            "category":"Recreation",
            "subcategory":"Water Park",
            "type":"Entertainment"
        }
    ],
    "sg:postcode":"98118",
    "sg:province":"WA",
    "sg:tags":[
        "beach"
    ],
    "sg:website":"www.seattle.gov/parks/park_detai...",
    "wof:name":"Pritchard Island Beach",
    "wof:placetype":"venue"
},
  "geometry": {"coordinates":[-122.263927,47.528547],"type":"Point"}
}