{
  "type": "Feature",
  "properties": {
    "addr:full":"3519 Arsenal Way Bremerton WA 98312",
    "addr:housenumber":"3519",
    "addr:postcode":"98312",
    "addr:street":"Arsenal Way",
    "iso:country":"US",
    "sg:address":"3519 Arsenal Way",
    "sg:city":"Bremerton",
    "sg:classifiers":[
        {
            "category":"Autos & Motor Vehicles",
            "subcategory":"Auto Supplies",
            "type":"Retail Goods"
        }
    ],
    "sg:phone":"+1 360 377 7383",
    "sg:postcode":"98312",
    "sg:province":"WA",
    "sg:tags":[
        "four",
        "wheel",
        "drive",
        "accessory"
    ],
    "sg:website":"www.bayview4x4.com",
    "wof:name":"Bayview 4X4 & Truck",
    "wof:placetype":"venue"
},
  "geometry": {"coordinates":[-122.663884,47.560394],"type":"Point"}
}