{
  "type": "Feature",
  "properties": {
    "addr:full":"117 E Louisa St Seattle WA 98102",
    "addr:housenumber":"117",
    "addr:postcode":"98102",
    "addr:street":"E Louisa St",
    "iso:country":"US",
    "sg:address":"117 E Louisa St",
    "sg:city":"Seattle",
    "sg:classifiers":[
        {
            "category":"Building & Trades",
            "subcategory":"Locksmith",
            "type":"Services"
        }
    ],
    "sg:phone":"+1 206 552 7292",
    "sg:postcode":"98102",
    "sg:province":"WA",
    "sg:tags":[
        "key"
    ],
    "wof:name":"One Twentyfour Hour Locksmith",
    "wof:placetype":"venue"
},
  "geometry": {"coordinates":[-122.326339,47.641905],"type":"Point"}
}