{
  "type": "Feature",
  "properties": {
    "addr:full":"18525 36th Ave S Seatac WA 98188",
    "addr:housenumber":"18525",
    "addr:postcode":"98188",
    "addr:street":"36Th Ave S Seatac",
    "iso:country":"US",
    "sg:address":"18525 36th Ave S",
    "sg:city":"Seatac",
    "sg:phone":"+1 206 901 9268",
    "sg:postcode":"98188",
    "sg:province":"WA",
    "wof:name":"Cedarbrook Lodge",
    "wof:placetype":"venue"
},
  "geometry": {"coordinates":[-122.287712,47.435861],"type":"Point"}
}