{
  "type": "Feature",
  "properties": {
    "addr:full":"1801 Fairview Ave E Seattle WA 98102",
    "addr:housenumber":"1801",
    "addr:postcode":"98102",
    "addr:street":"Fairview Ave E",
    "iso:country":"US",
    "sg:address":"1801 Fairview Ave E",
    "sg:city":"Seattle",
    "sg:classifiers":[
        {
            "category":"Organizations",
            "subcategory":"Professional Association",
            "type":"Services"
        }
    ],
    "sg:phone":"+1 206 553 8704",
    "sg:postcode":"98102",
    "sg:province":"WA",
    "wof:name":"Noah Health Services",
    "wof:placetype":"venue"
},
  "geometry": {"coordinates":[-122.32910099999999,47.63681],"type":"Point"}
}