{
  "type": "Feature",
  "properties": {
    "addr:full":"9223 11th Ave NW Seattle WA 98117",
    "addr:housenumber":"9223",
    "addr:postcode":"98117",
    "addr:street":"11Th Ave Nw",
    "iso:country":"US",
    "sg:address":"9223 11th Ave NW",
    "sg:city":"Seattle",
    "sg:classifiers":[
        {
            "category":"Shopping",
            "subcategory":"Florist",
            "type":"Retail Goods"
        }
    ],
    "sg:phone":"+1 206 234 1533",
    "sg:postcode":"98117",
    "sg:province":"WA",
    "sg:tags":[
        "landscape"
    ],
    "wof:name":"Down To Earth Gardener",
    "wof:placetype":"venue"
},
  "geometry": {"coordinates":[-122.37014000000001,47.697265],"type":"Point"}
}