{
  "type": "Feature",
  "properties": {
    "addr:full":"13930 SE 274th St Kent WA 98042",
    "addr:postcode":"13930;98042",
    "addr:street":"Se 274Th St",
    "iso:country":"US",
    "sg:address":"13930 SE 274th St",
    "sg:city":"Kent",
    "sg:classifiers":[
        {
            "category":"Manufacturing",
            "subcategory":"Buildings",
            "type":"Manufacturing & Wholesale Goods"
        },
        {
            "category":"Building & Trades",
            "subcategory":"Construction",
            "type":"Services"
        }
    ],
    "sg:phone":"+1 206 265 1399",
    "sg:postcode":"98042",
    "sg:province":"WA",
    "sg:tags":[
        "home",
        "builder",
        "contractor"
    ],
    "wof:name":"Lsri Construction Inc",
    "wof:placetype":"venue"
},
  "geometry": {"coordinates":[-122.15631399999999,47.35676],"type":"Point"}
}