{
  "type": "Feature",
  "properties": {
    "addr:full":"3411 C St NE Auburn WA 98002",
    "addr:housenumber":"3411",
    "addr:postcode":"98002",
    "addr:street":"C St Ne",
    "iso:country":"US",
    "sg:address":"3411 C St NE",
    "sg:city":"Auburn",
    "sg:classifiers":[
        {
            "category":"Restaurant",
            "type":"Food & Drink"
        }
    ],
    "sg:phone":"+1 253 939 7270",
    "sg:postcode":"98002",
    "sg:province":"WA",
    "sg:tags":[
        "eating"
    ],
    "wof:name":"C Street Cafe & Teriyaki",
    "wof:placetype":"venue"
},
  "geometry": {"coordinates":[-122.226619,47.336468],"type":"Point"}
}