{
  "type": "Feature",
  "properties": {
    "addr:full":"8308 142nd Avenue Ct E Puyallup WA 98372",
    "addr:housenumber":"8308",
    "addr:postcode":"98372",
    "addr:street":"142Nd Avenue Ct E",
    "iso:country":"US",
    "sg:address":"8308 142nd Avenue Ct E",
    "sg:city":"Puyallup",
    "sg:classifiers":[
        {
            "category":"Social Services",
            "subcategory":"Child Care",
            "type":"Services"
        }
    ],
    "sg:phone":"+1 253 840 2077",
    "sg:postcode":"98372",
    "sg:province":"WA",
    "sg:tags":[
        "day"
    ],
    "wof:name":"Circle Time Preschool",
    "wof:placetype":"venue"
},
  "geometry": {"coordinates":[-122.239189,47.181594],"type":"Point"}
}