{
  "type": "Feature",
  "properties": {
    "addr:full":"7005 Lillooet Loop Aberdeen WA 98520",
    "addr:housenumber":"7005",
    "addr:postcode":"98520",
    "addr:street":"Lillooet Loop",
    "iso:country":"US",
    "sg:address":"7005 Lillooet Loop",
    "sg:city":"Aberdeen",
    "sg:classifiers":[
        {
            "category":"Building & Trades",
            "subcategory":"Construction",
            "type":"Services"
        }
    ],
    "sg:phone":"+1 360 532 7377",
    "sg:postcode":"98520",
    "sg:province":"WA",
    "sg:tags":[
        "residential"
    ],
    "wof:name":"Gordon James Construction",
    "wof:placetype":"venue"
},
  "geometry": {"coordinates":[-123.684989,46.972817],"type":"Point"}
}