{
  "type": "Feature",
  "properties": {
    "addr:full":"516 N 1st St Yakima WA 98901",
    "addr:housenumber":"516",
    "addr:postcode":"98901",
    "addr:street":"N 1St St",
    "iso:country":"US",
    "sg:address":"516 N 1st St",
    "sg:city":"Yakima",
    "sg:classifiers":[
        {
            "category":"Social Services",
            "type":"Services"
        }
    ],
    "sg:phone":"+1 509 575 0757",
    "sg:postcode":"98901",
    "sg:province":"WA",
    "sg:tags":[
        "psychotherapist"
    ],
    "wof:name":"Gray & Gray",
    "wof:placetype":"venue"
},
  "geometry": {"coordinates":[-120.509747,46.609511],"type":"Point"}
}