{
  "type": "Feature",
  "properties": {
    "addr:full":"5706 Bethel Rd SE Port Orchard WA 98367",
    "addr:housenumber":"5706",
    "addr:postcode":"98367",
    "addr:street":"Bethel Rd Se",
    "iso:country":"US",
    "sg:address":"5706 Bethel Rd SE",
    "sg:city":"Port Orchard",
    "sg:classifiers":[
        {
            "category":"Utilities",
            "subcategory":"Telephone",
            "type":"Services"
        }
    ],
    "sg:phone":"+1 360 874 1924",
    "sg:postcode":"98367",
    "sg:province":"WA",
    "sg:tags":[
        "communications"
    ],
    "wof:name":"Netjamm Software Development",
    "wof:placetype":"venue"
},
  "geometry": {"coordinates":[-122.631753,47.496432],"type":"Point"}
}