{
  "type": "Feature",
  "properties": {
    "iso:country":"US",
    "sg:address":"46 Rd R SE",
    "sg:city":"Moses Lake",
    "sg:classifiers":[
        {
            "category":"Wholesale",
            "subcategory":"Farm Supplies",
            "type":"Manufacturing & Wholesale Goods"
        }
    ],
    "sg:phone":"+1 509 765 5663",
    "sg:postcode":"98837",
    "sg:province":"WA",
    "sg:tags":[
        "fertilizer"
    ],
    "sg:website":"www.simplot.com",
    "wof:name":"Simplot Soilbuilders",
    "wof:placetype":"venue"
},
  "geometry": {"coordinates":[-119.112422,47.08502],"type":"Point"}
}