{
  "type": "Feature",
  "properties": {
    "addr:full":"3304 Old Hartford Rd Lake Stevens WA 98258",
    "addr:housenumber":"3304",
    "addr:postcode":"98258",
    "addr:street":"Old Hartford Rd",
    "iso:country":"US",
    "sg:address":"3304 Old Hartford Rd",
    "sg:city":"Lake Stevens",
    "sg:classifiers":[
        {
            "category":"Building & Trades",
            "subcategory":"Construction",
            "type":"Services"
        }
    ],
    "sg:phone":"+1 425 377 9708",
    "sg:postcode":"98258",
    "sg:province":"WA",
    "sg:tags":[
        "general",
        "contractor"
    ],
    "wof:name":"Marshbank Construction",
    "wof:placetype":"venue"
},
  "geometry": {"coordinates":[-122.055913,48.025454],"type":"Point"}
}