{
  "type": "Feature",
  "properties": {
    "addr:full":"719 123rd Ave SE Lake Stevens WA 98258",
    "addr:housenumber":"719",
    "addr:postcode":"98258",
    "addr:street":"123Rd Ave Se",
    "iso:country":"US",
    "sg:address":"719 123rd Ave SE",
    "sg:city":"Lake Stevens",
    "sg:classifiers":[
        {
            "category":"Building & Trades",
            "subcategory":"Construction",
            "type":"Services"
        }
    ],
    "sg:phone":"+1 425 334 1689",
    "sg:postcode":"98258",
    "sg:province":"WA",
    "sg:tags":[
        "residential",
        "nonresidential"
    ],
    "wof:name":"Angell & Co",
    "wof:placetype":"venue"
},
  "geometry": {"coordinates":[-122.065646,47.990141],"type":"Point"}
}