{
  "type": "Feature",
  "properties": {
    "addr:full":"26184 State Rte 20 Coupeville WA 98239",
    "addr:housenumber":"26184",
    "addr:postcode":"98239",
    "addr:street":"State Rte 20",
    "iso:country":"US",
    "sg:address":"26184 State Rte 20",
    "sg:city":"Coupeville",
    "sg:classifiers":[
        {
            "category":"Home & Garden",
            "subcategory":"Home Furnishings",
            "type":"Retail Goods"
        }
    ],
    "sg:phone":"+1 360 678 6464",
    "sg:postcode":"98239",
    "sg:province":"WA",
    "sg:tags":[
        "merchandise",
        "gift"
    ],
    "wof:name":"Penn Cove Pottery",
    "wof:placetype":"venue"
},
  "geometry": {"coordinates":[-122.722013,48.235846],"type":"Point"}
}