{
  "type": "Feature",
  "properties": {
    "addr:full":"2920 Fairview Ave E Seattle WA 98102",
    "addr:housenumber":"2920",
    "addr:postcode":"98102",
    "addr:street":"Fairview Ave E",
    "iso:country":"US",
    "sg:address":"2920 Fairview Ave E",
    "sg:city":"Seattle",
    "sg:classifiers":[
        {
            "category":"Professional",
            "subcategory":"Management & Consulting",
            "type":"Services"
        }
    ],
    "sg:phone":"+1 206 324 3372",
    "sg:postcode":"98102",
    "sg:province":"WA",
    "sg:tags":[
        "public",
        "relations"
    ],
    "wof:name":"Payneless Promotions",
    "wof:placetype":"venue"
},
  "geometry": {"coordinates":[-122.32515100000001,47.647666],"type":"Point"}
}