{
  "type": "Feature",
  "properties": {
    "iso:country":"US",
    "sg:address":"1105 32nd St",
    "sg:city":"Anacortes",
    "sg:classifiers":[
        {
            "category":"Retail",
            "subcategory":"Funeral Services",
            "type":"Services"
        }
    ],
    "sg:phone":"+1 360 293 3311",
    "sg:postcode":"98221",
    "sg:province":"WA",
    "sg:tags":[
        "home"
    ],
    "wof:name":"Evans Funeral Chapel",
    "wof:placetype":"venue"
},
  "geometry": {"coordinates":[-122.61461300000001,48.496327],"type":"Point"}
}