{
  "type": "Feature",
  "properties": {
    "addr:full":"4041 Mountain View Dr Bremerton WA 98310",
    "addr:housenumber":"4041",
    "addr:postcode":"98310",
    "addr:street":"Mountain View Dr",
    "iso:country":"US",
    "sg:address":"4041 Mountain View Dr",
    "sg:city":"Bremerton",
    "sg:classifiers":[
        {
            "category":"Building & Trades",
            "subcategory":"Construction",
            "type":"Services"
        }
    ],
    "sg:phone":"+1 360 479 1596",
    "sg:postcode":"98310",
    "sg:province":"WA",
    "sg:tags":[
        "contractor"
    ],
    "wof:name":"Chapman Acoustical LLC",
    "wof:placetype":"venue"
},
  "geometry": {"coordinates":[-122.621115,47.576685],"type":"Point"}
}