{
  "type": "Feature",
  "properties": {
    "addr:full":"1201 S Clark Ave Republic WA 99166",
    "addr:housenumber":"1201",
    "addr:postcode":"99166",
    "addr:street":"S Clark Ave",
    "iso:country":"US",
    "sg:address":"1201 S Clark Ave",
    "sg:city":"Republic",
    "sg:classifiers":[
        {
            "category":"Professional",
            "subcategory":"Accounting & Tax Preparation",
            "type":"Services"
        }
    ],
    "sg:phone":"+1 509 775 2851",
    "sg:postcode":"99166",
    "sg:province":"WA",
    "sg:tags":[
        "accountant"
    ],
    "wof:name":"Log Cabin Accounting",
    "wof:placetype":"venue"
},
  "geometry": {"coordinates":[-118.733082,48.638777],"type":"Point"}
}