{
  "type": "Feature",
  "properties": {
    "addr:full":"700 6th St Clarkston WA 99403",
    "addr:housenumber":"700",
    "addr:postcode":"99403",
    "addr:street":"6Th St",
    "iso:country":"US",
    "sg:address":"700 6th St",
    "sg:city":"Clarkston",
    "sg:classifiers":[
        {
            "category":"Autos & Motor Vehicles",
            "subcategory":"Auto Supplies",
            "type":"Retail Goods"
        }
    ],
    "sg:phone":"+1 509 758 2596",
    "sg:postcode":"99403",
    "sg:province":"WA",
    "sg:tags":[
        "automobile",
        "part",
        "accessory"
    ],
    "sg:website":"http://www.napaautoparts.com",
    "wof:name":"Clarkston Auto and Truck Parts",
    "wof:placetype":"venue"
},
  "geometry": {"coordinates":[-117.045601,46.416279],"type":"Point"}
}