{
  "type": "Feature",
  "properties": {
    "addr:full":"5651 Mission Rd Bellingham WA 98226",
    "addr:housenumber":"5651",
    "addr:postcode":"98226",
    "addr:street":"Mission Rd",
    "iso:country":"US",
    "sg:address":"5651 Mission Rd",
    "sg:city":"Bellingham",
    "sg:classifiers":[
        {
            "category":"Building & Trades",
            "subcategory":"Construction",
            "type":"Services"
        }
    ],
    "sg:phone":"+1 360 966 2385",
    "sg:postcode":"98226",
    "sg:province":"WA",
    "sg:tags":[
        "general",
        "contractor"
    ],
    "sg:website":"www.garyreidhomes.com",
    "wof:name":"Gary Reid Homes Inc",
    "wof:placetype":"venue"
},
  "geometry": {"coordinates":[-122.354,48.845602],"type":"Point"}
}