{
  "type": "Feature",
  "properties": {
    "addr:full":"25119 SE 262nd St Ravensdale WA 98051",
    "addr:postcode":"25119;98051",
    "addr:street":"Se 262Nd St",
    "iso:country":"US",
    "sg:address":"25119 SE 262nd St",
    "sg:city":"Ravensdale",
    "sg:classifiers":[
        {
            "category":"Manufacturing",
            "subcategory":"Printing",
            "type":"Manufacturing & Wholesale Goods"
        }
    ],
    "sg:phone":"+1 425 432 3231",
    "sg:postcode":"98051",
    "sg:province":"WA",
    "sg:tags":[
        "publisher"
    ],
    "sg:website":"www.idyllarbor.com",
    "wof:name":"Idyll Arbor Inc",
    "wof:placetype":"venue"
},
  "geometry": {"coordinates":[-122.01136200000001,47.367117],"type":"Point"}
}