{
  "type": "Feature",
  "properties": {
    "addr:full":"1527 N Pines Rd Spokane Valley WA 99206",
    "addr:housenumber":"1527",
    "addr:postcode":"99206",
    "addr:street":"N Pines Rd",
    "iso:country":"US",
    "sg:address":"1527 N Pines Rd",
    "sg:city":"Spokane Valley",
    "sg:classifiers":[
        {
            "category":"Shopping",
            "subcategory":"Stationery & Office Supplies",
            "type":"Retail Goods"
        },
        {
            "category":"Professional",
            "subcategory":"Accounting & Tax Preparation",
            "type":"Services"
        }
    ],
    "sg:phone":"+1 509 892 1251",
    "sg:postcode":"99206",
    "sg:province":"WA",
    "sg:tags":[
        "album",
        "scrapbook"
    ],
    "wof:name":"Huckleberry's Paper Patch",
    "wof:placetype":"venue"
},
  "geometry": {"coordinates":[-117.23976,47.671351],"type":"Point"}
}