{
  "type": "Feature",
  "properties": {
    "addr:full":"2620 McKinley Pl SE Port Orchard WA 98366",
    "addr:housenumber":"2620",
    "addr:postcode":"98366",
    "addr:street":"Mckinley Pl Se",
    "iso:country":"US",
    "sg:address":"2620 McKinley Pl SE",
    "sg:city":"Port Orchard",
    "sg:classifiers":[
        {
            "category":"Retail",
            "subcategory":"Auto Repair",
            "type":"Services"
        }
    ],
    "sg:phone":"+1 360 876 1492",
    "sg:postcode":"98366",
    "sg:province":"WA",
    "sg:tags":[
        "general"
    ],
    "wof:name":"Schoonys Repair",
    "wof:placetype":"venue"
},
  "geometry": {"coordinates":[-122.62317,47.52334],"type":"Point"}
}