{
  "type": "Feature",
  "properties": {
    "addr:full":"21318 E Gilbert Ave Otis Orchards WA 99027",
    "addr:housenumber":"21318",
    "addr:postcode":"99027",
    "addr:street":"E Gilbert Ave",
    "iso:country":"US",
    "sg:address":"21318 E Gilbert Ave",
    "sg:city":"Otis Orchards",
    "sg:classifiers":[
        {
            "category":"Wholesale",
            "subcategory":"Electrical",
            "type":"Manufacturing & Wholesale Goods"
        }
    ],
    "sg:phone":"+1 509 926 1725",
    "sg:postcode":"99027",
    "sg:province":"WA",
    "sg:tags":[
        "transformer"
    ],
    "wof:name":"Valley Transformer Co",
    "wof:placetype":"venue"
},
  "geometry": {"coordinates":[-117.119562,47.706402],"type":"Point"}
}