{
  "type": "Feature",
  "properties": {
    "addr:full":"111 Stone Rd Yakima WA 98908",
    "addr:housenumber":"111",
    "addr:postcode":"98908",
    "addr:street":"Stone Rd",
    "iso:country":"US",
    "sg:address":"111 Stone Rd",
    "sg:city":"Yakima",
    "sg:classifiers":[
        {
            "category":"Shopping",
            "subcategory":"Gifts & Souvenirs",
            "type":"Retail Goods"
        },
        {
            "category":"Wholesale",
            "subcategory":"Durable Goods & Equipment",
            "type":"Manufacturing & Wholesale Goods"
        }
    ],
    "sg:phone":"+1 509 966 7572",
    "sg:postcode":"98908",
    "sg:province":"WA",
    "sg:tags":[
        "antique",
        "dealers-wholesale",
        "collectible"
    ],
    "sg:website":"http://www.widehollowcollectables.com",
    "wof:name":"Wide Hollow Collectables",
    "wof:placetype":"venue"
},
  "geometry": {"coordinates":[-120.709361,46.598604],"type":"Point"}
}