{
  "type": "Feature",
  "properties": {
    "iso:country":"US",
    "sg:address":"17403 139th Ave NE",
    "sg:city":"Woodinville",
    "sg:classifiers":[
        {
            "category":"Professional",
            "subcategory":"Business Services",
            "type":"Services"
        }
    ],
    "sg:phone":"+1 425 486 0677",
    "sg:postcode":"98072",
    "sg:province":"WA",
    "sg:tags":[
        "executive"
    ],
    "wof:name":"Woodinville Licensing Agency",
    "wof:placetype":"venue"
},
  "geometry": {"coordinates":[-122.15416,47.753612],"type":"Point"}
}