{
  "type": "Feature",
  "properties": {
    "addr:full":"2345 Eastlake Ave E Seattle WA 98102",
    "addr:housenumber":"2345",
    "addr:postcode":"98102",
    "addr:street":"Eastlake Ave E",
    "iso:country":"US",
    "sg:address":"2345 Eastlake Ave E",
    "sg:city":"Seattle",
    "sg:classifiers":[
        {
            "category":"Shopping",
            "subcategory":"Clothing, Apparel, & Fashions",
            "type":"Retail Goods"
        }
    ],
    "sg:phone":"+1 206 659 4421",
    "sg:postcode":"98102",
    "sg:province":"WA",
    "sg:tags":[
        "clothing",
        "women's"
    ],
    "sg:website":"jaxxboutique.com",
    "wof:name":"Jaxx Boutik",
    "wof:placetype":"venue"
},
  "geometry": {"coordinates":[-122.32625,47.641043],"type":"Point"}
}