{
  "type": "Feature",
  "properties": {
    "addr:full":"4018 NE 112th Ave Vancouver WA 98682",
    "addr:housenumber":"4018",
    "addr:postcode":"98682",
    "addr:street":"Ne 112Th Ave",
    "iso:country":"US",
    "sg:address":"4018 NE 112th Ave",
    "sg:city":"Vancouver",
    "sg:classifiers":[
        {
            "category":"Building & Trades",
            "subcategory":"Construction",
            "type":"Services"
        }
    ],
    "sg:phone":"+1 360 882 0800",
    "sg:postcode":"98682",
    "sg:province":"WA",
    "sg:tags":[
        "repair",
        "electrical"
    ],
    "wof:name":"Boc Group Inc A Delaware Corp",
    "wof:placetype":"venue"
},
  "geometry": {"coordinates":[-122.558076,45.651203],"type":"Point"}
}