{
  "type": "Feature",
  "properties": {
    "addr:full":"5514 N Moore St Spokane WA 99205",
    "addr:housenumber":"5514",
    "addr:postcode":"99205",
    "addr:street":"N Moore St",
    "iso:country":"US",
    "sg:address":"5514 N Moore St",
    "sg:city":"Spokane",
    "sg:classifiers":[
        {
            "category":"Building & Trades",
            "subcategory":"Construction",
            "type":"Services"
        }
    ],
    "sg:phone":"+1 509 324 8655",
    "sg:postcode":"99205",
    "sg:province":"WA",
    "sg:tags":[
        "general",
        "contractor"
    ],
    "wof:name":"Enswiler Construction",
    "wof:placetype":"venue"
},
  "geometry": {"coordinates":[-117.46317500000001,47.71116],"type":"Point"}
}