{
  "type": "Feature",
  "properties": {
    "iso:country":"US",
    "sg:address":"8500 Evergreen Way",
    "sg:city":"Everett",
    "sg:classifiers":[
        {
            "category":"Banks & Credit Unions",
            "subcategory":"Bank",
            "type":"Services"
        }
    ],
    "sg:phone":"+1 425 355 1177",
    "sg:postcode":"98203",
    "sg:province":"WA",
    "sg:tags":[
        "federal",
        "national",
        "commercial",
        "savings",
        "institution"
    ],
    "wof:name":"Bank Of America",
    "wof:placetype":"venue"
},
  "geometry": {"coordinates":[-122.231656,47.918171],"type":"Point"}
}