{
  "type": "Feature",
  "properties": {
    "addr:full":"1264 Eastlake Ave E Seattle WA 98102",
    "addr:housenumber":"1264",
    "addr:postcode":"98102",
    "addr:street":"Eastlake Ave E",
    "iso:country":"US",
    "sg:address":"1264 Eastlake Ave E",
    "sg:city":"Seattle",
    "sg:classifiers":[
        {
            "category":"Real Estate",
            "subcategory":"Real Estate Services",
            "type":"Services"
        }
    ],
    "sg:phone":"+1 206 323 3727",
    "sg:postcode":"98102",
    "sg:province":"WA",
    "sg:tags":[
        "management",
        "property"
    ],
    "wof:name":"Flatiron Properties",
    "wof:placetype":"venue"
},
  "geometry": {"coordinates":[-122.327003,47.630798],"type":"Point"}
}