{
  "type": "Feature",
  "properties": {
    "addr:full":"1710 N 34th St Seattle WA 98103",
    "addr:housenumber":"1710",
    "addr:postcode":"98103",
    "addr:street":"N 34Th St",
    "iso:country":"US",
    "sg:address":"1710 N 34th St",
    "sg:city":"Seattle",
    "sg:classifiers":[
        {
            "category":"Building & Trades",
            "subcategory":"Construction",
            "type":"Services"
        }
    ],
    "sg:phone":"+1 206 547 7562",
    "sg:postcode":"98103",
    "sg:province":"WA",
    "sg:tags":[
        "contractor"
    ],
    "wof:name":"Birdaco Enterprises",
    "wof:placetype":"venue"
},
  "geometry": {"coordinates":[-122.336433,47.648119],"type":"Point"}
}