{
  "type": "Feature",
  "properties": {
    "addr:full":"2304 E Nob Hill Blvd Yakima WA 98901",
    "addr:housenumber":"2304",
    "addr:postcode":"98901",
    "addr:street":"E Nob Hill Blvd",
    "iso:country":"US",
    "sg:address":"2304 E Nob Hill Blvd",
    "sg:city":"Yakima",
    "sg:classifiers":[
        {
            "category":"Shopping",
            "subcategory":"Department Store",
            "type":"Retail Goods"
        }
    ],
    "sg:phone":"+1 509 248 1990",
    "sg:postcode":"98901",
    "sg:province":"WA",
    "sg:website":"www.bluelight.com",
    "wof:name":"Kmart",
    "wof:placetype":"venue"
},
  "geometry": {"coordinates":[-120.46941700000001,46.584924],"type":"Point"}
}