{
  "type": "Feature",
  "properties": {
    "addr:full":"22411 SE 62nd St Issaquah WA 98027",
    "addr:postcode":"22411;98027",
    "addr:street":"Se 62Nd St",
    "iso:country":"US",
    "sg:address":"22411 SE 62nd St",
    "sg:city":"Issaquah",
    "sg:classifiers":[
        {
            "category":"Autos & Motor Vehicles",
            "subcategory":"Auto Supplies",
            "type":"Retail Goods"
        }
    ],
    "sg:phone":"+1 425 391 9307",
    "sg:postcode":"98027",
    "sg:province":"WA",
    "sg:tags":[
        "trailer",
        "hitch"
    ],
    "wof:name":"Hitch Co",
    "wof:placetype":"venue"
},
  "geometry": {"coordinates":[-122.039821,47.546525],"type":"Point"}
}