{
  "type": "Feature",
  "properties": {
    "addr:full":"1109 Elm St Kelso WA 98626",
    "addr:housenumber":"1109",
    "addr:postcode":"98626",
    "addr:street":"Elm St",
    "iso:country":"US",
    "sg:address":"1109 Elm St",
    "sg:city":"Kelso",
    "sg:classifiers":[
        {
            "category":"Restaurant",
            "type":"Food & Drink"
        }
    ],
    "sg:phone":"+1 360 577 2675",
    "sg:postcode":"98626",
    "sg:province":"WA",
    "sg:tags":[
        "eating"
    ],
    "wof:name":"Glenna Olson",
    "wof:placetype":"venue"
},
  "geometry": {"coordinates":[-122.904877,46.133524],"type":"Point"}
}