{
  "type": "Feature",
  "properties": {
    "addr:full":"8404 83rd Ave SW Ste H Lakewood WA 98498",
    "addr:housenumber":"8404",
    "addr:postcode":"98498",
    "addr:street":"83Rd Ave Sw Ste H",
    "iso:country":"US",
    "sg:address":"8404 83rd Ave SW Ste H",
    "sg:city":"Lakewood",
    "sg:classifiers":[
        {
            "category":"Building & Trades",
            "subcategory":"Construction",
            "type":"Services"
        }
    ],
    "sg:phone":"+1 253 584 5308",
    "sg:postcode":"98498",
    "sg:province":"WA",
    "sg:tags":[
        "contractor"
    ],
    "wof:name":"Lahfdany J General Contractor Inc",
    "wof:placetype":"venue"
},
  "geometry": {"coordinates":[-122.547997,47.181],"type":"Point"}
}