{
  "type": "Feature",
  "properties": {
    "addr:full":"3125 Conarty Rd Malaga WA 98828",
    "addr:housenumber":"3125",
    "addr:postcode":"98828",
    "addr:street":"Conarty Rd",
    "iso:country":"US",
    "sg:address":"3125 Conarty Rd",
    "sg:city":"Malaga",
    "sg:classifiers":[
        {
            "category":"Freight",
            "type":"Transportation"
        }
    ],
    "sg:phone":"+1 509 663 4134",
    "sg:postcode":"98828",
    "sg:province":"WA",
    "sg:tags":[
        "operator",
        "trucking"
    ],
    "wof:name":"Barry Hallock Trucking",
    "wof:placetype":"venue"
},
  "geometry": {"coordinates":[-120.219133,47.365562],"type":"Point"}
}