{
  "type": "Feature",
  "properties": {
    "addr:full":"808 115th Ave SE Lake Stevens WA 98258",
    "addr:housenumber":"808",
    "addr:postcode":"98258",
    "addr:street":"115Th Ave Se",
    "iso:country":"US",
    "sg:address":"808 115th Ave SE",
    "sg:city":"Lake Stevens",
    "sg:classifiers":[
        {
            "category":"Professional",
            "subcategory":"Business Services",
            "type":"Services"
        }
    ],
    "sg:phone":"+1 425 770 0873",
    "sg:postcode":"98258",
    "sg:province":"WA",
    "wof:name":"Double Up Espresso",
    "wof:placetype":"venue"
},
  "geometry": {"coordinates":[-122.07572,47.988633],"type":"Point"}
}