{
  "type": "Feature",
  "properties": {
    "addr:full":"8527 200th St SW Edmonds WA 98026",
    "addr:housenumber":"8527",
    "addr:postcode":"98026",
    "addr:street":"200Th St Sw",
    "iso:country":"US",
    "sg:address":"8527 200th St SW",
    "sg:city":"Edmonds",
    "sg:classifiers":[
        {
            "category":"Building & Trades",
            "subcategory":"Plumbing",
            "type":"Services"
        }
    ],
    "sg:phone":"+1 206 930 4205",
    "sg:postcode":"98026",
    "sg:province":"WA",
    "sg:tags":[
        "contractor"
    ],
    "wof:name":"Eagle Gas Mechanical Inc",
    "wof:placetype":"venue"
},
  "geometry": {"coordinates":[-122.349553,47.817868],"type":"Point"}
}