{
  "type": "Feature",
  "properties": {
    "addr:full":"1035 Andover Park W Seattle WA 98188",
    "addr:housenumber":"1035",
    "addr:postcode":"98188",
    "addr:street":"Andover Park W",
    "iso:country":"US",
    "sg:address":"1035 Andover Park W",
    "sg:city":"Seattle",
    "sg:classifiers":[
        {
            "category":"Professional",
            "subcategory":"Management & Consulting",
            "type":"Services"
        }
    ],
    "sg:phone":"+1 206 575 4610",
    "sg:postcode":"98188",
    "sg:province":"WA",
    "sg:tags":[
        "business"
    ],
    "wof:name":"Harris Bmdical Compliance Svcs",
    "wof:placetype":"venue"
},
  "geometry": {"coordinates":[-122.25452,47.448162],"type":"Point"}
}