{
  "type": "Feature",
  "properties": {
    "addr:full":"5717 156th Ave NE Redmond WA 98052",
    "addr:housenumber":"5717",
    "addr:postcode":"98052",
    "addr:street":"156Th Ave Ne",
    "iso:country":"US",
    "sg:address":"5717 156th Ave NE",
    "sg:city":"Redmond",
    "sg:classifiers":[
        {
            "category":"Retail",
            "subcategory":"Portrait Studio",
            "type":"Services"
        }
    ],
    "sg:phone":"+1 425 556 3996",
    "sg:postcode":"98052",
    "sg:province":"WA",
    "sg:tags":[
        "photo"
    ],
    "wof:name":"H Rober Classic Portrait",
    "wof:placetype":"venue"
},
  "geometry": {"coordinates":[-122.132637,47.658864],"type":"Point"}
}