{
  "type": "Feature",
  "properties": {
    "addr:full":"1809 7th Avenue Seattle WA 98101",
    "addr:housenumber":"1809",
    "addr:postcode":"98101",
    "addr:street":"7Th Avenue",
    "iso:country":"US",
    "sg:address":"1809 7th Avenue",
    "sg:city":"Seattle",
    "sg:classifiers":[
        {
            "category":"Professional",
            "subcategory":"Accounting & Tax Preparation",
            "type":"Services"
        }
    ],
    "sg:phone":"+1 206 682 6500",
    "sg:postcode":"98101",
    "sg:province":"WA",
    "sg:tags":[
        "accountant"
    ],
    "wof:name":"Rgl Gallagher",
    "wof:placetype":"venue"
},
  "geometry": {"coordinates":[-122.335256,47.613638],"type":"Point"}
}