{
  "type": "Feature",
  "properties": {
    "addr:full":"15819 Larch Way Lynnwood WA 98087",
    "addr:housenumber":"15819",
    "addr:postcode":"98087",
    "addr:street":"Larch Way",
    "iso:country":"US",
    "sg:address":"15819 Larch Way",
    "sg:city":"Lynnwood",
    "sg:classifiers":[
        {
            "category":"Communications",
            "subcategory":"Film & Video Production",
            "type":"Services"
        }
    ],
    "sg:phone":"+1 425 367 2149",
    "sg:postcode":"98087",
    "sg:province":"WA",
    "sg:tags":[
        "taping"
    ],
    "wof:name":"Tainter & Assoc",
    "wof:placetype":"venue"
},
  "geometry": {"coordinates":[-122.24707600000001,47.855079],"type":"Point"}
}