{
  "type": "Feature",
  "properties": {
    "iso:country":"US",
    "sg:address":"1222 Olympic Ave",
    "sg:city":"Shelton",
    "sg:classifiers":[
        {
            "category":"Personal",
            "type":"Services"
        }
    ],
    "sg:phone":"+1 360 280 3773",
    "sg:postcode":"98584",
    "sg:province":"WA",
    "wof:name":"See Bee Projects",
    "wof:placetype":"venue"
},
  "geometry": {"coordinates":[-123.11489899999999,47.210082],"type":"Point"}
}