{
  "type": "Feature",
  "properties": {
    "addr:full":"4429 26th Ave W Seattle WA 98199",
    "addr:housenumber":"4429",
    "addr:postcode":"98199",
    "addr:street":"26Th Ave W",
    "iso:country":"US",
    "sg:address":"4429 26th Ave W",
    "sg:city":"Seattle",
    "sg:classifiers":[
        {
            "category":"Building & Trades",
            "subcategory":"Landscaping Services",
            "type":"Services"
        }
    ],
    "sg:phone":"+1 206 284 5930",
    "sg:postcode":"98199",
    "sg:province":"WA",
    "wof:name":"Northwest Insured Tree Service",
    "wof:placetype":"venue"
},
  "geometry": {"coordinates":[-122.39001,47.661249],"type":"Point"}
}