{
  "type": "Feature",
  "properties": {
    "addr:full":"3523 S 261st St Kent WA 98032",
    "addr:housenumber":"3523",
    "addr:postcode":"98032",
    "addr:street":"S 261St St",
    "iso:country":"US",
    "sg:address":"3523 S 261st St",
    "sg:city":"Kent",
    "sg:classifiers":[
        {
            "category":"Shopping",
            "subcategory":"Computers & Home Electronics",
            "type":"Retail Goods"
        }
    ],
    "sg:phone":"+1 253 850 2033",
    "sg:postcode":"98032",
    "sg:province":"WA",
    "wof:name":"Kersh Software & Consulting",
    "wof:placetype":"venue"
},
  "geometry": {"coordinates":[-122.287631,47.367814],"type":"Point"}
}