{
  "type": "Feature",
  "properties": {
    "iso:country":"US",
    "sg:address":"538 S Spruce St",
    "sg:city":"Burlington",
    "sg:classifiers":[
        {
            "category":"Building & Trades",
            "subcategory":"Construction",
            "type":"Services"
        }
    ],
    "sg:phone":"+1 360 755 7314",
    "sg:postcode":"98233",
    "sg:province":"WA",
    "sg:tags":[
        "contractor"
    ],
    "wof:name":"Skagit Welding & Ornamental Ir",
    "wof:placetype":"venue"
},
  "geometry": {"coordinates":[-122.33072300000001,48.472171],"type":"Point"}
}