{
  "type": "Feature",
  "properties": {
    "addr:full":"1408 N 20th Ave Pasco WA 99301",
    "addr:housenumber":"1408",
    "addr:postcode":"99301",
    "addr:street":"N 20Th Ave",
    "iso:country":"US",
    "sg:address":"1408 N 20th Ave",
    "sg:city":"Pasco",
    "sg:classifiers":[
        {
            "category":"Professional",
            "subcategory":"Lawyer & Legal Services",
            "type":"Services"
        }
    ],
    "sg:phone":"+1 509 544 9080",
    "sg:postcode":"99301",
    "sg:province":"WA",
    "sg:tags":[
        "attorney"
    ],
    "wof:name":"Columbia Legal Svc",
    "wof:placetype":"venue"
},
  "geometry": {"coordinates":[-119.117458,46.241464],"type":"Point"}
}