{
  "type": "Feature",
  "properties": {
    "addr:full":"4728 N Elgin St Spokane WA 99205",
    "addr:housenumber":"4728",
    "addr:postcode":"99205",
    "addr:street":"N Elgin St",
    "iso:country":"US",
    "sg:address":"4728 N Elgin St",
    "sg:city":"Spokane",
    "sg:classifiers":[
        {
            "category":"Home & Garden",
            "subcategory":"Home Furnishings",
            "type":"Retail Goods"
        }
    ],
    "sg:phone":"+1 509 323 4863",
    "sg:postcode":"99205",
    "sg:province":"WA",
    "wof:name":"Blind Ambitions",
    "wof:placetype":"venue"
},
  "geometry": {"coordinates":[-117.441731,47.702167],"type":"Point"}
}