{
  "type": "Feature",
  "properties": {
    "addr:full":"150 Nickerson St Seattle WA 98109",
    "addr:housenumber":"150",
    "addr:postcode":"98109",
    "addr:street":"Nickerson St",
    "iso:country":"US",
    "sg:address":"150 Nickerson St",
    "sg:city":"Seattle",
    "sg:classifiers":[
        {
            "category":"Health Services",
            "subcategory":"Doctor",
            "type":"Services"
        }
    ],
    "sg:phone":"+1 206 282 2065",
    "sg:postcode":"98109",
    "sg:province":"WA",
    "sg:tags":[
        "medical"
    ],
    "wof:name":"David M White PHD Clinic",
    "wof:placetype":"venue"
},
  "geometry": {"coordinates":[-122.353325,47.647768],"type":"Point"}
}