{
  "type": "Feature",
  "properties": {
    "addr:full":"11408 Guthrie Rd Anderson Island WA 98303",
    "addr:housenumber":"11408",
    "addr:postcode":"98303",
    "addr:street":"Guthrie Rd",
    "iso:country":"US",
    "sg:address":"11408 Guthrie Rd",
    "sg:city":"Anderson Island",
    "sg:classifiers":[
        {
            "category":"Organizations",
            "subcategory":"Religious Organization",
            "type":"Services"
        }
    ],
    "sg:phone":"+1 253 884 4974",
    "sg:postcode":"98303",
    "sg:province":"WA",
    "sg:tags":[
        "church"
    ],
    "wof:name":"Faith Independent Lutheran Chr",
    "wof:placetype":"venue"
},
  "geometry": {"coordinates":[-122.690318,47.169804],"type":"Point"}
}