{
  "type": "Feature",
  "properties": {
    "iso:country":"US",
    "sg:address":"311 Erie Ave",
    "sg:city":"Seattle",
    "sg:classifiers":[
        {
            "category":"Professional",
            "subcategory":"Employment Agencies",
            "type":"Services"
        }
    ],
    "sg:phone":"+1 206 860 1869",
    "sg:postcode":"98122",
    "sg:province":"WA",
    "sg:tags":[
        "help",
        "supply"
    ],
    "wof:name":"Creative Health Care Solutions",
    "wof:placetype":"venue"
},
  "geometry": {"coordinates":[-122.284668,47.604928],"type":"Point"}
}