{
  "type": "Feature",
  "properties": {
    "addr:full":"29709 S McDowell Rd Cheney WA 99004",
    "addr:housenumber":"29709",
    "addr:postcode":"99004",
    "addr:street":"S Mcdowell Rd",
    "iso:country":"US",
    "sg:address":"29709 S McDowell Rd",
    "sg:city":"Cheney",
    "sg:classifiers":[
        {
            "category":"Real Estate",
            "subcategory":"Real Estate Operator",
            "type":"Services"
        }
    ],
    "sg:phone":"+1 509 245 3469",
    "sg:postcode":"99004",
    "sg:province":"WA",
    "sg:tags":[
        "property",
        "lessor"
    ],
    "wof:name":"Grogan Land Co LLC",
    "wof:placetype":"venue"
},
  "geometry": {"coordinates":[-117.477682,47.381993],"type":"Point"}
}