{
  "type": "Feature",
  "properties": {
    "addr:full":"346 Roosevelt Ave E Enumclaw WA 98022",
    "addr:housenumber":"346",
    "addr:postcode":"98022",
    "addr:street":"Roosevelt Ave E",
    "iso:country":"US",
    "sg:address":"346 Roosevelt Ave E",
    "sg:city":"Enumclaw",
    "sg:classifiers":[
        {
            "category":"Retail",
            "subcategory":"Repair Shop",
            "type":"Services"
        }
    ],
    "sg:phone":"+1 360 825 1221",
    "sg:postcode":"98022",
    "sg:province":"WA",
    "sg:tags":[
        "trade",
        "industrial",
        "machinery",
        "welding",
        "mfg"
    ],
    "wof:name":"Ron & Leos",
    "wof:placetype":"venue"
},
  "geometry": {"coordinates":[-121.969137,47.199231],"type":"Point"}
}