{
  "type": "Feature",
  "properties": {
    "addr:full":"2938 Iris Ln SW Olympia WA 98512",
    "addr:housenumber":"2938",
    "addr:postcode":"98512",
    "addr:street":"Iris Ln Sw",
    "iso:country":"US",
    "sg:address":"2938 Iris Ln SW",
    "sg:city":"Olympia",
    "sg:classifiers":[
        {
            "category":"Retail",
            "subcategory":"Car Wash",
            "type":"Services"
        }
    ],
    "sg:phone":"+1 360 786 1089",
    "sg:postcode":"98512",
    "sg:province":"WA",
    "sg:tags":[
        "carwash"
    ],
    "wof:name":"A Plus Detailing",
    "wof:placetype":"venue"
},
  "geometry": {"coordinates":[-122.919315,47.019281],"type":"Point"}
}