{
  "type": "Feature",
  "properties": {
    "addr:full":"20016 Cedar Valley Rd Lynnwood WA 98036",
    "addr:housenumber":"20016",
    "addr:postcode":"98036",
    "addr:street":"Cedar Valley Rd",
    "iso:country":"US",
    "sg:address":"20016 Cedar Valley Rd",
    "sg:city":"Lynnwood",
    "sg:classifiers":[
        {
            "category":"Health Services",
            "subcategory":"Health Practitioner",
            "type":"Services"
        }
    ],
    "sg:phone":"+1 425 672 8496",
    "sg:postcode":"98036",
    "sg:province":"WA",
    "wof:name":"John Thoburn PHD",
    "wof:placetype":"venue"
},
  "geometry": {"coordinates":[-122.303175,47.814599],"type":"Point"}
}