{
  "type": "Feature",
  "properties": {
    "addr:full":"10702 NE 36th Ave Vancouver WA 98686",
    "addr:housenumber":"10702",
    "addr:postcode":"98686",
    "addr:street":"Ne 36Th Ave",
    "iso:country":"US",
    "sg:address":"10702 NE 36th Ave",
    "sg:city":"Vancouver",
    "sg:classifiers":[
        {
            "category":"Health Services",
            "subcategory":"Clinic",
            "type":"Services"
        }
    ],
    "sg:phone":"+1 360 574 1718",
    "sg:postcode":"98686",
    "sg:province":"WA",
    "wof:name":"Advocare",
    "wof:placetype":"venue"
},
  "geometry": {"coordinates":[-122.63533700000001,45.698786],"type":"Point"}
}