{
  "type": "Feature",
  "properties": {
    "addr:full":"1511 1st Ave Seattle WA 98101",
    "addr:housenumber":"1511",
    "addr:postcode":"98101",
    "addr:street":"1St Ave",
    "iso:country":"US",
    "sg:address":"1511 1st Ave",
    "sg:city":"Seattle",
    "sg:classifiers":[
        {
            "category":"Shopping",
            "subcategory":"Hobbies, Toys, & Games",
            "type":"Retail Goods"
        }
    ],
    "sg:phone":"+1 206 623 8747",
    "sg:postcode":"98101",
    "sg:province":"WA",
    "sg:tags":[
        "shop",
        "hobby"
    ],
    "sg:website":"www.metskers.com",
    "wof:name":"Metsker Maps",
    "wof:placetype":"venue"
},
  "geometry": {"coordinates":[-122.339996,47.6087],"type":"Point"}
}