{
  "type": "Feature",
  "properties": {
    "iso:country":"US",
    "sg:address":"728 W Rees Ave",
    "sg:city":"Walla Walla",
    "sg:classifiers":[
        {
            "category":"Professional",
            "subcategory":"Business Services",
            "type":"Services"
        }
    ],
    "sg:phone":"+1 509 529 7770",
    "sg:postcode":"99362",
    "sg:province":"WA",
    "sg:tags":[
        "merchandise"
    ],
    "wof:name":"Macon Brothers Auctioneers",
    "wof:placetype":"venue"
},
  "geometry": {"coordinates":[-118.351642,46.075131],"type":"Point"}
}