{
  "type": "Feature",
  "properties": {
    "addr:full":"900 Winslow Way E Bainbridge Island WA 98110",
    "addr:housenumber":"900",
    "addr:postcode":"98110",
    "addr:street":"Winslow Way E",
    "iso:country":"US",
    "sg:address":"900 Winslow Way E",
    "sg:city":"Bainbridge Island",
    "sg:classifiers":[
        {
            "category":"Real Estate",
            "subcategory":"Architect",
            "type":"Services"
        }
    ],
    "sg:phone":"+1 206 842 3466",
    "sg:postcode":"98110",
    "sg:province":"WA",
    "wof:name":"Bios",
    "wof:placetype":"venue"
},
  "geometry": {"coordinates":[-122.509174,47.624896],"type":"Point"}
}