{
  "type": "Feature",
  "properties": {
    "addr:full":"13171 S Ahtanum Rd Yakima WA 98903",
    "addr:housenumber":"13171",
    "addr:postcode":"98903",
    "addr:street":"S Ahtanum Rd",
    "iso:country":"US",
    "sg:address":"13171 S Ahtanum Rd",
    "sg:city":"Yakima",
    "sg:classifiers":[
        {
            "category":"Farming",
            "subcategory":"Livestock Farm",
            "type":"Manufacturing & Wholesale Goods"
        }
    ],
    "sg:phone":"+1 509 965 4801",
    "sg:postcode":"98903",
    "sg:province":"WA",
    "sg:tags":[
        "beef",
        "feedlot",
        "cattle"
    ],
    "wof:name":"Brad A McGiure",
    "wof:placetype":"venue"
},
  "geometry": {"coordinates":[-120.676838,46.521026],"type":"Point"}
}