{
  "type": "Feature",
  "properties": {
    "addr:full":"13027 Bothell Everett Hwy Everett WA 98208",
    "addr:housenumber":"13027",
    "addr:postcode":"98208",
    "addr:street":"Bothell Everett Hwy",
    "iso:country":"US",
    "sg:address":"13027 Bothell Everett Hwy",
    "sg:city":"Everett",
    "sg:classifiers":[
        {
            "category":"Professional",
            "subcategory":"Accounting & Tax Preparation",
            "type":"Services"
        },
        {
            "category":"Banks & Credit Unions",
            "subcategory":"Financial Services",
            "type":"Services"
        }
    ],
    "sg:phone":"+1 425 337 9998",
    "sg:postcode":"98208",
    "sg:province":"WA",
    "sg:tags":[
        "return",
        "preparation-business",
        "taxes-consultants",
        "loan",
        "reporting",
        "representative",
        "alternative",
        "bookkeeping"
    ],
    "sg:website":"http://www.hrblock.com",
    "wof:name":"H&R Block",
    "wof:placetype":"venue"
},
  "geometry": {"coordinates":[-122.20681500000001,47.880035],"type":"Point"}
}