{
  "type": "Feature",
  "properties": {
    "addr:full":"12034 134th Ct NE Redmond WA 98052",
    "addr:housenumber":"12034",
    "addr:postcode":"98052",
    "addr:street":"134Th Ct Ne",
    "iso:country":"US",
    "sg:address":"12034 134th Ct NE",
    "sg:city":"Redmond",
    "sg:classifiers":[
        {
            "category":"Professional",
            "subcategory":"Engineering",
            "type":"Services"
        }
    ],
    "sg:phone":"+1 425 372 1600",
    "sg:postcode":"98052",
    "sg:province":"WA",
    "sg:tags":[
        "consulting",
        "business"
    ],
    "wof:name":"Secor",
    "wof:placetype":"venue"
},
  "geometry": {"coordinates":[-122.16171199999999,47.71048],"type":"Point"}
}