{
  "type": "Feature",
  "properties": {
    "addr:full":"14415 369th Ave SE Sultan WA 98294",
    "addr:housenumber":"14415",
    "addr:postcode":"98294",
    "addr:street":"369Th Ave Se Sultan",
    "iso:country":"US",
    "sg:address":"14415 369th Ave SE",
    "sg:city":"Sultan",
    "sg:classifiers":[
        {
            "category":"Organizations",
            "subcategory":"Religious Organization",
            "type":"Services"
        }
    ],
    "sg:phone":"+1 360 799 2460",
    "sg:postcode":"98294",
    "sg:province":"WA",
    "wof:name":"Sultan LDS Church",
    "wof:placetype":"venue"
},
  "geometry": {"coordinates":[-121.737053,47.867948],"type":"Point"}
}