{
  "type": "Feature",
  "properties": {
    "addr:full":"13400 NE 20th St Ste 31 Bellevue WA 98005",
    "addr:housenumber":"13400",
    "addr:postcode":"98005",
    "addr:street":"Ne 20Th St Ste 31",
    "iso:country":"US",
    "sg:address":"13400 NE 20th St Ste 31",
    "sg:city":"Bellevue",
    "sg:classifiers":[
        {
            "category":"Professional",
            "subcategory":"Computer Services",
            "type":"Services"
        }
    ],
    "sg:phone":"+1 425 644 0077",
    "sg:postcode":"98005",
    "sg:province":"WA",
    "sg:tags":[
        "repair"
    ],
    "sg:website":"www.hylink.com",
    "wof:name":"Hylink Technology Inc",
    "wof:placetype":"venue"
},
  "geometry": {"coordinates":[-122.160601,47.628149],"type":"Point"}
}