{
  "type": "Feature",
  "properties": {
    "addr:full":"1809 Sheridan St Port Townsend WA 98368",
    "addr:housenumber":"1809",
    "addr:postcode":"98368",
    "addr:street":"Sheridan St",
    "iso:country":"US",
    "sg:address":"1809 Sheridan St",
    "sg:city":"Port Townsend",
    "sg:classifiers":[
        {
            "category":"Social Services",
            "type":"Services"
        }
    ],
    "sg:phone":"+1 360 379 5109",
    "sg:postcode":"98368",
    "sg:province":"WA",
    "sg:tags":[
        "counselor",
        "marriage",
        "family"
    ],
    "wof:name":"Jumping Mouse Childrens Ctr",
    "wof:placetype":"venue"
},
  "geometry": {"coordinates":[-122.790502,48.113621],"type":"Point"}
}