{
  "type": "Feature",
  "properties": {
    "addr:full":"12530 128th Ln NE Kirkland WA 98034",
    "addr:housenumber":"12530",
    "addr:postcode":"98034",
    "addr:street":"128Th Ln Ne",
    "iso:country":"US",
    "sg:address":"12530 128th Ln NE",
    "sg:city":"Kirkland",
    "sg:classifiers":[
        {
            "category":"Manufacturing",
            "subcategory":"Metals",
            "type":"Manufacturing & Wholesale Goods"
        }
    ],
    "sg:phone":"+1 425 823 2112",
    "sg:postcode":"98034",
    "sg:province":"WA",
    "sg:tags":[
        "control",
        "industrial",
        "mfg",
        "process",
        "valve",
        "instrument"
    ],
    "wof:name":"Fisher Controls Intl LLC",
    "wof:placetype":"venue"
},
  "geometry": {"coordinates":[-122.169825,47.713356],"type":"Point"}
}