{
  "type": "Feature",
  "properties": {
    "addr:full":"25901 NE 10th St Camas WA 98607",
    "addr:housenumber":"25901",
    "addr:postcode":"98607",
    "addr:street":"Ne 10Th St",
    "iso:country":"US",
    "sg:address":"25901 NE 10th St",
    "sg:city":"Camas",
    "sg:classifiers":[
        {
            "category":"Organizations",
            "subcategory":"Non-profit Organization",
            "type":"Services"
        }
    ],
    "sg:phone":"+1 360 834 4549",
    "sg:postcode":"98607",
    "sg:province":"WA",
    "sg:tags":[
        "fund",
        "raising"
    ],
    "wof:name":"Custom Fundraising Solutions",
    "wof:placetype":"venue"
},
  "geometry": {"coordinates":[-122.405204,45.629755],"type":"Point"}
}