{
  "type": "Feature",
  "properties": {
    "addr:full":"6513 Siper Rd Everson WA 98247",
    "addr:housenumber":"6513",
    "addr:postcode":"98247",
    "addr:street":"Siper Rd",
    "iso:country":"US",
    "sg:address":"6513 Siper Rd",
    "sg:city":"Everson",
    "sg:classifiers":[
        {
            "category":"Wholesale",
            "subcategory":"Construction Materials",
            "type":"Manufacturing & Wholesale Goods"
        }
    ],
    "sg:phone":"+1 360 966 2826",
    "sg:postcode":"98247",
    "sg:province":"WA",
    "wof:name":"Concrete Norwest",
    "wof:placetype":"venue"
},
  "geometry": {"coordinates":[-122.293261,48.874459],"type":"Point"}
}