{
  "type": "Feature",
  "properties": {
    "addr:full":"1202 108th Ave E Puyallup WA 98372",
    "addr:housenumber":"1202",
    "addr:postcode":"98372",
    "addr:street":"108Th Ave E",
    "iso:country":"US",
    "sg:address":"1202 108th Ave E",
    "sg:city":"Puyallup",
    "sg:classifiers":[
        {
            "category":"Professional",
            "subcategory":"Computer Services",
            "type":"Services"
        }
    ],
    "sg:phone":"+1 253 927 6983",
    "sg:postcode":"98372",
    "sg:province":"WA",
    "sg:tags":[
        "consulting"
    ],
    "wof:name":"Watermark Consulting Ltd",
    "wof:placetype":"venue"
},
  "geometry": {"coordinates":[-122.28518099999999,47.247776],"type":"Point"}
}