{
  "type": "Feature",
  "properties": {
    "iso:country":"US",
    "sg:address":"6806 Foster Slough Rd",
    "sg:city":"Snohomish",
    "sg:classifiers":[
        {
            "category":"Professional",
            "subcategory":"Computer Services",
            "type":"Services"
        }
    ],
    "sg:phone":"+1 425 397 8210",
    "sg:postcode":"98290",
    "sg:province":"WA",
    "sg:tags":[
        "design",
        "system",
        "business"
    ],
    "wof:name":"Hunt Associate",
    "wof:placetype":"venue"
},
  "geometry": {"coordinates":[-122.135671,47.935111],"type":"Point"}
}