{
  "type": "Feature",
  "properties": {
    "addr:full":"258373 Hwy 101 Sequim WA 98382",
    "addr:housenumber":"258373",
    "addr:postcode":"98382",
    "addr:street":"Hwy 101",
    "iso:country":"US",
    "sg:address":"258373 Hwy 101",
    "sg:city":"Sequim",
    "sg:classifiers":[
        {
            "category":"Freight",
            "type":"Transportation"
        }
    ],
    "sg:phone":"+1 360 681 8708",
    "sg:postcode":"98382",
    "sg:province":"WA",
    "sg:tags":[
        "commercial",
        "storage"
    ],
    "wof:name":"A Cost Less Mini Storage",
    "wof:placetype":"venue"
},
  "geometry": {"coordinates":[-123.23319100000001,48.089062],"type":"Point"}
}