{
  "type": "Feature",
  "properties": {
    "addr:full":"7408 127th Ave NE Kirkland WA 98033",
    "addr:housenumber":"7408",
    "addr:postcode":"98033",
    "addr:street":"127Th Ave Ne",
    "iso:country":"US",
    "sg:address":"7408 127th Ave NE",
    "sg:city":"Kirkland",
    "sg:classifiers":[
        {
            "category":"Building & Trades",
            "subcategory":"Cleaning & Sanitation",
            "type":"Services"
        }
    ],
    "sg:phone":"+1 425 827 2761",
    "sg:postcode":"98033",
    "sg:province":"WA",
    "sg:tags":[
        "janitorial"
    ],
    "wof:name":"CM Cleaning",
    "wof:placetype":"venue"
},
  "geometry": {"coordinates":[-122.17055000000001,47.671654],"type":"Point"}
}