{
  "type": "Feature",
  "properties": {
    "addr:full":"1113 N Northgate Way Seattle WA 98133",
    "addr:housenumber":"1113",
    "addr:postcode":"98133",
    "addr:street":"N Northgate Way",
    "iso:country":"US",
    "sg:address":"1113 N Northgate Way",
    "sg:city":"Seattle",
    "sg:classifiers":[
        {
            "category":"Health Services",
            "subcategory":"Health Practitioner",
            "type":"Services"
        }
    ],
    "sg:phone":"+1 206 517 7870",
    "sg:postcode":"98133",
    "sg:province":"WA",
    "sg:tags":[
        "physician"
    ],
    "wof:name":"David Royce Anderson",
    "wof:placetype":"venue"
},
  "geometry": {"coordinates":[-122.343442,47.704973],"type":"Point"}
}