{
  "type": "Feature",
  "properties": {
    "addr:full":"5402 47th Avenue NE Seattle WA 98105",
    "addr:housenumber":"5402",
    "addr:postcode":"98105",
    "addr:street":"47Th Avenue Ne",
    "iso:country":"US",
    "sg:address":"5402 47th Avenue NE",
    "sg:city":"Seattle",
    "sg:classifiers":[
        {
            "category":"Health Services",
            "subcategory":"Doctor",
            "type":"Services"
        }
    ],
    "sg:phone":"+1 206 525 4090",
    "sg:postcode":"98105",
    "sg:province":"WA",
    "wof:name":"The Vasectomy Clinic",
    "wof:placetype":"venue"
},
  "geometry": {"coordinates":[-122.27719,47.668209],"type":"Point"}
}