{
  "type": "Feature",
  "properties": {
    "addr:full":"720 S Main St Colville WA 99114",
    "addr:housenumber":"720",
    "addr:postcode":"99114",
    "addr:street":"S Main St",
    "iso:country":"US",
    "sg:address":"720 S Main St",
    "sg:city":"Colville",
    "sg:classifiers":[
        {
            "category":"Home & Garden",
            "subcategory":"Home Furnishings",
            "type":"Retail Goods"
        }
    ],
    "sg:phone":"+1 509 684 3554",
    "sg:postcode":"99114",
    "sg:province":"WA",
    "sg:tags":[
        "blanket"
    ],
    "wof:name":"Q Is For Quilts",
    "wof:placetype":"venue"
},
  "geometry": {"coordinates":[-117.905756,48.537948],"type":"Point"}
}