{
  "type": "Feature",
  "properties": {
    "addr:full":"1601 5th Ave Seattle WA 98101",
    "addr:housenumber":"1601",
    "addr:postcode":"98101",
    "addr:street":"5Th Ave",
    "iso:country":"US",
    "sg:address":"1601 5th Ave",
    "sg:city":"Seattle",
    "sg:classifiers":[
        {
            "category":"Professional",
            "type":"Services"
        }
    ],
    "sg:phone":"+1 206 926 1116",
    "sg:postcode":"98101",
    "sg:province":"WA",
    "wof:name":"Starquest Expeditions LLC",
    "wof:placetype":"venue"
},
  "geometry": {"coordinates":[-122.33653,47.61172],"type":"Point"}
}