{
  "type": "Feature",
  "properties": {
    "addr:full":"109 Spruce Ave Prosser WA 99350",
    "addr:housenumber":"109",
    "addr:postcode":"99350",
    "addr:street":"Spruce Ave",
    "iso:country":"US",
    "sg:address":"109 Spruce Ave",
    "sg:city":"Prosser",
    "sg:classifiers":[
        {
            "category":"Building & Trades",
            "subcategory":"Plumbing",
            "type":"Services"
        }
    ],
    "sg:phone":"+1 509 786 4889",
    "sg:postcode":"99350",
    "sg:province":"WA",
    "sg:tags":[
        "contractor"
    ],
    "wof:name":"Plumlee Mechanical",
    "wof:placetype":"venue"
},
  "geometry": {"coordinates":[-119.790887,46.195144],"type":"Point"}
}