{
  "type": "Feature",
  "properties": {
    "addr:full":"2109 Walnut Rd NW Olympia WA 98502",
    "addr:housenumber":"2109",
    "addr:postcode":"olympia wa 98502",
    "addr:street":"Walnut Rd Nw",
    "iso:country":"US",
    "sg:address":"2109 Walnut Rd NW",
    "sg:city":"Olympia",
    "sg:classifiers":[
        {
            "category":"Education",
            "subcategory":"Dance Studio",
            "type":"Public Place"
        }
    ],
    "sg:phone":"+1 360 357 4137",
    "sg:postcode":"98502",
    "sg:province":"WA",
    "wof:name":"Dancing Dragons",
    "wof:placetype":"venue"
},
  "geometry": {"coordinates":[-122.92692099999999,47.056976],"type":"Point"}
}