{
  "type": "Feature",
  "properties": {
    "addr:full":"26 N Kirkpatrick Rd Omak WA 98841",
    "addr:housenumber":"26",
    "addr:postcode":"98841",
    "addr:street":"N Kirkpatrick Rd",
    "iso:country":"US",
    "sg:address":"26 N Kirkpatrick Rd",
    "sg:city":"Omak",
    "sg:classifiers":[
        {
            "category":"Farming",
            "subcategory":"Farm",
            "type":"Manufacturing & Wholesale Goods"
        }
    ],
    "sg:phone":"+1 509 826 4286",
    "sg:postcode":"98841",
    "sg:province":"WA",
    "sg:tags":[
        "orchard"
    ],
    "wof:name":"Nansen-Theis Orchards Inc",
    "wof:placetype":"venue"
},
  "geometry": {"coordinates":[-119.565478,48.419452],"type":"Point"}
}