{
  "type": "Feature",
  "properties": {
    "addr:full":"13301 SE 79th St Newcastle WA 98059",
    "addr:housenumber":"13301",
    "addr:postcode":"98059",
    "addr:street":"Se 79Th St",
    "iso:country":"US",
    "sg:address":"13301 SE 79th St",
    "sg:city":"Newcastle",
    "sg:classifiers":[
        {
            "category":"Wholesale",
            "subcategory":"Construction Materials",
            "type":"Manufacturing & Wholesale Goods"
        },
        {
            "category":"Home & Garden",
            "subcategory":"Building Materials",
            "type":"Retail Goods"
        }
    ],
    "sg:phone":"+1 425 577 0888",
    "sg:postcode":"98059",
    "sg:province":"WA",
    "sg:tags":[
        "other",
        "export",
        "lumber"
    ],
    "wof:name":"Butsurin America Inc",
    "wof:placetype":"venue"
},
  "geometry": {"coordinates":[-122.16283300000001,47.531732],"type":"Point"}
}