{
  "type": "Feature",
  "properties": {
    "addr:full":"9411 NE Hwy 99 Vancouver WA 98665",
    "addr:housenumber":"9411",
    "addr:postcode":"98665",
    "addr:street":"Ne Hwy 99",
    "iso:country":"US",
    "sg:address":"9411 NE Hwy 99",
    "sg:city":"Vancouver",
    "sg:classifiers":[
        {
            "category":"Shopping",
            "subcategory":"Music",
            "type":"Retail Goods"
        }
    ],
    "sg:phone":"+1 360 823 0451",
    "sg:postcode":"98665",
    "sg:province":"WA",
    "sg:tags":[
        "video",
        "disc",
        "tape",
        "cassette"
    ],
    "wof:name":"Video Business Opportunities",
    "wof:placetype":"venue"
},
  "geometry": {"coordinates":[-122.66009099999999,45.68643],"type":"Point"}
}