{
  "type": "Feature",
  "properties": {
    "addr:full":"1269 Private Dr Bellingham WA 98226",
    "addr:housenumber":"1269",
    "addr:postcode":"98226",
    "addr:street":"Private Dr",
    "iso:country":"US",
    "sg:address":"1269 Private Dr",
    "sg:city":"Bellingham",
    "sg:classifiers":[
        {
            "category":"Professional",
            "subcategory":"Computer Services",
            "type":"Services"
        }
    ],
    "sg:phone":"+1 360 961 6478",
    "sg:postcode":"98226",
    "sg:province":"WA",
    "sg:tags":[
        "related"
    ],
    "wof:name":"Kulshin Group",
    "wof:placetype":"venue"
},
  "geometry": {"coordinates":[-122.54853300000001,48.84031],"type":"Point"}
}