{
  "type": "Feature",
  "properties": {
    "addr:full":"3539 Rd 5 NW Ephrata WA 98823",
    "addr:postcode":"3539;98823",
    "addr:street":"Rd 5 Nw",
    "iso:country":"US",
    "sg:address":"3539 Rd 5 NW",
    "sg:city":"Ephrata",
    "sg:classifiers":[
        {
            "category":"Home & Garden",
            "subcategory":"Garden Supply",
            "type":"Retail Goods"
        }
    ],
    "sg:phone":"+1 509 787 1555",
    "sg:postcode":"98823",
    "sg:province":"WA",
    "sg:tags":[
        "nurseryman"
    ],
    "sg:website":"www.willowdrive.com",
    "wof:name":"Willow Drive Nursery",
    "wof:placetype":"venue"
},
  "geometry": {"coordinates":[-119.56734899999999,47.162561],"type":"Point"}
}