{
  "type": "Feature",
  "properties": {
    "iso:country":"US",
    "sg:address":"26436 Big Valley Rd NE",
    "sg:city":"Poulsbo",
    "sg:classifiers":[
        {
            "category":"Professional",
            "subcategory":"Accounting & Tax Preparation",
            "type":"Services"
        }
    ],
    "sg:phone":"+1 360 779 4494",
    "sg:postcode":"98370",
    "sg:province":"WA",
    "sg:tags":[
        "payroll"
    ],
    "wof:name":"Kitsap Payroll Svc",
    "wof:placetype":"venue"
},
  "geometry": {"coordinates":[-122.635094,47.807804],"type":"Point"}
}