{
  "type": "Feature",
  "properties": {
    "addr:full":"6511 136th Pl SW Edmonds WA 98026",
    "addr:housenumber":"6511",
    "addr:postcode":"98026",
    "addr:street":"136Th Pl Sw",
    "iso:country":"US",
    "sg:address":"6511 136th Pl SW",
    "sg:city":"Edmonds",
    "sg:classifiers":[
        {
            "category":"Real Estate",
            "subcategory":"Real Estate Agent",
            "type":"Services"
        }
    ],
    "sg:phone":"+1 425 743 6790",
    "sg:postcode":"98026",
    "sg:province":"WA",
    "wof:name":"Winston Property Management LL",
    "wof:placetype":"venue"
},
  "geometry": {"coordinates":[-122.321978,47.874765],"type":"Point"}
}