{
  "type": "Feature",
  "properties": {
    "addr:full":"17203 SE 260th St Kent WA 98042",
    "addr:housenumber":"17203",
    "addr:postcode":"98042",
    "addr:street":"Se 260Th St",
    "iso:country":"US",
    "sg:address":"17203 SE 260th St",
    "sg:city":"Kent",
    "sg:classifiers":[
        {
            "category":"Building & Trades",
            "subcategory":"Construction",
            "type":"Services"
        }
    ],
    "sg:phone":"+1 206 261 1009",
    "sg:postcode":"98042",
    "sg:province":"WA",
    "sg:tags":[
        "hanging",
        "contractor"
    ],
    "wof:name":"Miguel Antonio Painting",
    "wof:placetype":"venue"
},
  "geometry": {"coordinates":[-122.11033999999999,47.368481],"type":"Point"}
}