{
  "type": "Feature",
  "properties": {
    "addr:full":"8116 224th Ave E Buckley WA 98321",
    "addr:housenumber":"8116",
    "addr:postcode":"98321",
    "addr:street":"224Th Ave E",
    "iso:country":"US",
    "sg:address":"8116 224th Ave E",
    "sg:city":"Buckley",
    "sg:classifiers":[
        {
            "category":"Real Estate",
            "subcategory":"Real Estate Operator",
            "type":"Services"
        }
    ],
    "sg:phone":"+1 253 862 8900",
    "sg:postcode":"98321",
    "sg:province":"WA",
    "sg:tags":[
        "property",
        "lessor"
    ],
    "wof:name":"Hill Mounts Properties",
    "wof:placetype":"venue"
},
  "geometry": {"coordinates":[-122.130999,47.183548],"type":"Point"}
}