{
  "type": "Feature",
  "properties": {
    "addr:full":"7615 148th Ave E Sumner WA 98390",
    "addr:housenumber":"7615",
    "addr:postcode":"98390",
    "addr:street":"148Th Ave E",
    "iso:country":"US",
    "sg:address":"7615 148th Ave E",
    "sg:city":"Sumner",
    "sg:classifiers":[
        {
            "category":"Manufacturing",
            "subcategory":"Printing",
            "type":"Manufacturing & Wholesale Goods"
        }
    ],
    "sg:phone":"+1 253 891 1284",
    "sg:postcode":"98390",
    "sg:province":"WA",
    "sg:tags":[
        "commercial"
    ],
    "wof:name":"Superior Label Systems Inc",
    "wof:placetype":"venue"
},
  "geometry": {"coordinates":[-122.231994,47.186981],"type":"Point"}
}