{
  "type": "Feature",
  "properties": {
    "addr:full":"187 Llama Ln Port Hadlock WA 98368",
    "addr:housenumber":"187",
    "addr:postcode":"98368",
    "addr:street":"Llama Ln;Hadlock",
    "iso:country":"US",
    "sg:address":"187 Llama Ln",
    "sg:city":"Port Hadlock",
    "sg:classifiers":[
        {
            "category":"Retail",
            "subcategory":"Auto Repair",
            "type":"Services"
        }
    ],
    "sg:phone":"+1 360 379 4749",
    "sg:postcode":"98368",
    "sg:province":"WA",
    "sg:tags":[
        "body"
    ],
    "wof:name":"Need For Speed",
    "wof:placetype":"venue"
},
  "geometry": {"coordinates":[-122.79283700000001,48.045681],"type":"Point"}
}