{
  "type": "Feature",
  "properties": {
    "addr:full":"22 103rd Ave NE Bellevue WA 98004",
    "addr:housenumber":"22",
    "addr:postcode":"98004",
    "addr:street":"103Rd Ave Ne",
    "iso:country":"US",
    "sg:address":"22 103rd Ave NE",
    "sg:city":"Bellevue",
    "sg:classifiers":[
        {
            "category":"Manufacturing",
            "subcategory":"Leather Goods",
            "type":"Manufacturing & Wholesale Goods"
        },
        {
            "category":"Retail",
            "subcategory":"Repair Shop",
            "type":"Services"
        },
        {
            "category":"Home & Garden",
            "subcategory":"Kitchen Supply",
            "type":"Retail Goods"
        },
        {
            "category":"Shopping",
            "subcategory":"Antiques",
            "type":"Retail Goods"
        },
        {
            "category":"Home & Garden",
            "subcategory":"Furniture",
            "type":"Retail Goods"
        }
    ],
    "sg:phone":"+1 425 454 6227",
    "sg:postcode":"98004",
    "sg:province":"WA",
    "sg:tags":[
        "renting",
        "leasing",
        "utensil",
        "refinish",
        "cookware",
        "pad",
        "table",
        "store"
    ],
    "sg:website":"www.TimelessElegance.com",
    "wof:name":"Timeless Elegance",
    "wof:placetype":"venue"
},
  "geometry": {"coordinates":[-122.202825,47.610293],"type":"Point"}
}