{
  "type": "Feature",
  "properties": {
    "addr:full":"179 1st Ave SE Issaquah WA 98027",
    "addr:housenumber":"179",
    "addr:postcode":"98027",
    "addr:street":"1St Ave Se",
    "iso:country":"US",
    "sg:address":"179 1st Ave SE",
    "sg:city":"Issaquah",
    "sg:classifiers":[
        {
            "category":"Social Services",
            "type":"Services"
        }
    ],
    "sg:phone":"+1 425 392 5836",
    "sg:postcode":"98027",
    "sg:province":"WA",
    "sg:tags":[
        "organization",
        "welfare"
    ],
    "wof:name":"Issaquah Clothing Bank",
    "wof:placetype":"venue"
},
  "geometry": {"coordinates":[-122.034818,47.528626],"type":"Point"}
}