{
  "type": "Feature",
  "properties": {
    "addr:full":"9115 Bridgeport Way SW Lakewood WA 98499",
    "addr:housenumber":"9115",
    "addr:postcode":"98499",
    "addr:street":"Bridgeport Way Sw",
    "iso:country":"US",
    "sg:address":"9115 Bridgeport Way SW",
    "sg:city":"Lakewood",
    "sg:classifiers":[
        {
            "category":"Real Estate",
            "subcategory":"Real Estate Operator",
            "type":"Services"
        }
    ],
    "sg:phone":"+1 253 460 7392",
    "sg:postcode":"98499",
    "sg:province":"WA",
    "sg:tags":[
        "building",
        "nonresidential"
    ],
    "wof:name":"Lawson Properties LLC",
    "wof:placetype":"venue"
},
  "geometry": {"coordinates":[-122.518371,47.174545],"type":"Point"}
}