{
  "type": "Feature",
  "properties": {
    "addr:full":"3418 N Ferdinand St Tacoma WA 98407",
    "addr:housenumber":"3418",
    "addr:postcode":"98407",
    "addr:street":"N Ferdinand St",
    "iso:country":"US",
    "sg:address":"3418 N Ferdinand St",
    "sg:city":"Tacoma",
    "sg:classifiers":[
        {
            "category":"Professional",
            "subcategory":"Business Services",
            "type":"Services"
        }
    ],
    "sg:phone":"+1 253 759 7653",
    "sg:postcode":"98407",
    "sg:province":"WA",
    "sg:tags":[
        "translation",
        "sign",
        "interpreting",
        "language",
        "provides"
    ],
    "wof:name":"Asl Professionals",
    "wof:placetype":"venue"
},
  "geometry": {"coordinates":[-122.502591,47.278538],"type":"Point"}
}