{
  "type": "Feature",
  "properties": {
    "addr:full":"120 N 16th Ave Yakima WA 98902",
    "addr:housenumber":"120",
    "addr:postcode":"98902",
    "addr:street":"N 16Th Ave",
    "iso:country":"US",
    "sg:address":"120 N 16th Ave",
    "sg:city":"Yakima",
    "sg:classifiers":[
        {
            "category":"Education",
            "subcategory":"School",
            "type":"Public Place"
        }
    ],
    "sg:phone":"+1 509 573 1700",
    "sg:postcode":"98902",
    "sg:province":"WA",
    "wof:name":"Roosevelt Elementary School",
    "wof:placetype":"venue"
},
  "geometry": {"coordinates":[-120.530469,46.599266],"type":"Point"}
}