{
  "type": "Feature",
  "properties": {
    "addr:full":"1405 Harrison Ave NW Olympia WA 98502",
    "addr:housenumber":"1405",
    "addr:postcode":"olympia wa 98502",
    "addr:street":"Harrison Ave Nw",
    "iso:country":"US",
    "sg:address":"1405 Harrison Ave NW",
    "sg:city":"Olympia",
    "sg:classifiers":[
        {
            "category":"Social Services",
            "type":"Services"
        }
    ],
    "sg:phone":"+1 360 352 4165",
    "sg:postcode":"98502",
    "sg:province":"WA",
    "wof:name":"Jean P Jacob MA",
    "wof:placetype":"venue"
},
  "geometry": {"coordinates":[-122.920148,47.045854],"type":"Point"}
}