{
  "type": "Feature",
  "properties": {
    "addr:full":"1027 108th Ave SE Bellevue WA 98004",
    "addr:housenumber":"1027",
    "addr:postcode":"98004",
    "addr:street":"108Th Ave Se",
    "iso:country":"US",
    "sg:address":"1027 108th Ave SE",
    "sg:city":"Bellevue",
    "sg:classifiers":[
        {
            "category":"Wholesale",
            "subcategory":"Groceries",
            "type":"Manufacturing & Wholesale Goods"
        }
    ],
    "sg:phone":"+1 425 454 0455",
    "sg:postcode":"98004",
    "sg:province":"WA",
    "wof:name":"Millennium International LLC",
    "wof:placetype":"venue"
},
  "geometry": {"coordinates":[-122.196437,47.600577],"type":"Point"}
}