{
  "type": "Feature",
  "properties": {
    "addr:full":"17903 State Rte 9 SE Snohomish WA 98296",
    "addr:housenumber":"17903",
    "addr:postcode":"98296",
    "addr:street":"State Rte 9",
    "iso:country":"US",
    "sg:address":"17903 State Rte 9 SE",
    "sg:city":"Snohomish",
    "sg:classifiers":[
        {
            "category":"Freight",
            "type":"Transportation"
        }
    ],
    "sg:phone":"+1 360 668 5653",
    "sg:postcode":"98296",
    "sg:province":"WA",
    "sg:tags":[
        "operator",
        "local",
        "trucking"
    ],
    "wof:name":"Bumblebee Moving North Inc",
    "wof:placetype":"venue"
},
  "geometry": {"coordinates":[-122.125383,47.834714],"type":"Point"}
}