{
  "type": "Feature",
  "properties": {
    "addr:full":"706 Euclid St Grandview WA 98930",
    "addr:housenumber":"706",
    "addr:postcode":"98930",
    "addr:street":"Euclid St",
    "iso:country":"US",
    "sg:address":"706 Euclid St",
    "sg:city":"Grandview",
    "sg:classifiers":[
        {
            "category":"Building & Trades",
            "subcategory":"Construction",
            "type":"Services"
        }
    ],
    "sg:phone":"+1 509 882 3739",
    "sg:postcode":"98930",
    "sg:province":"WA",
    "sg:tags":[
        "house",
        "contractor"
    ],
    "wof:name":"Todorovich Construction Inc",
    "wof:placetype":"venue"
},
  "geometry": {"coordinates":[-119.91560800000001,46.248394],"type":"Point"}
}