{
  "type": "Feature",
  "properties": {
    "addr:full":"811 Yakima Ave S Seattle WA 98144",
    "addr:housenumber":"811",
    "addr:postcode":"98144",
    "addr:street":"Yakima Ave S",
    "iso:country":"US",
    "sg:address":"811 Yakima Ave S",
    "sg:city":"Seattle",
    "sg:classifiers":[
        {
            "category":"Recreation",
            "type":"Entertainment"
        }
    ],
    "sg:phone":"+1 206 328 1104",
    "sg:postcode":"98144",
    "sg:province":"WA",
    "sg:tags":[
        "instructor",
        "paragliding"
    ],
    "wof:name":"Paraglide Washington",
    "wof:placetype":"venue"
},
  "geometry": {"coordinates":[-122.29445,47.594596],"type":"Point"}
}