{
  "type": "Feature",
  "properties": {
    "addr:full":"131 Faulkner Rd Selah WA 98942",
    "addr:housenumber":"131",
    "addr:postcode":"98942",
    "addr:street":"Faulkner Rd",
    "iso:country":"US",
    "sg:address":"131 Faulkner Rd",
    "sg:city":"Selah",
    "sg:classifiers":[
        {
            "category":"Farming",
            "subcategory":"Vineyard",
            "type":"Manufacturing & Wholesale Goods"
        }
    ],
    "sg:phone":"+1 509 697 8299",
    "sg:postcode":"98942",
    "sg:province":"WA",
    "sg:tags":[
        "grape"
    ],
    "wof:name":"Cornerstone Vineyards",
    "wof:placetype":"venue"
},
  "geometry": {"coordinates":[-120.54115,46.673709],"type":"Point"}
}