{
  "type": "Feature",
  "properties": {
    "iso:country":"US",
    "sg:address":"4940 Hackett Rd",
    "sg:city":"Bellingham",
    "sg:classifiers":[
        {
            "category":"Professional",
            "type":"Services"
        }
    ],
    "sg:phone":"+1 360 398 2922",
    "sg:postcode":"98226",
    "sg:province":"WA",
    "wof:name":"Richard W Rohwer",
    "wof:placetype":"venue"
},
  "geometry": {"coordinates":[-122.47006,48.823911],"type":"Point"}
}