{
  "type": "Feature",
  "properties": {
    "addr:full":"11756 12th Ave NE Seattle WA 98125",
    "addr:housenumber":"11756",
    "addr:postcode":"98125",
    "addr:street":"12Th Ave Ne",
    "iso:country":"US",
    "sg:address":"11756 12th Ave NE",
    "sg:city":"Seattle",
    "sg:classifiers":[
        {
            "category":"Arts & Performance",
            "subcategory":"Theater",
            "type":"Entertainment"
        }
    ],
    "sg:phone":"+1 206 362 8331",
    "sg:postcode":"98125",
    "sg:province":"WA",
    "sg:tags":[
        "group"
    ],
    "wof:name":"Blues and Jazz By Eric Madis",
    "wof:placetype":"venue"
},
  "geometry": {"coordinates":[-122.315208,47.715467],"type":"Point"}
}