{
  "type": "Feature",
  "properties": {
    "addr:full":"4233 Meridian Ave N Seattle WA 98103",
    "addr:housenumber":"4233",
    "addr:postcode":"98103",
    "addr:street":"Meridian Ave N",
    "iso:country":"US",
    "sg:address":"4233 Meridian Ave N",
    "sg:city":"Seattle",
    "sg:classifiers":[
        {
            "category":"Banks & Credit Unions",
            "subcategory":"Financial Services",
            "type":"Services"
        }
    ],
    "sg:phone":"+1 206 548 1447",
    "sg:postcode":"98103",
    "sg:province":"WA",
    "sg:tags":[
        "ag",
        "nonphysical",
        "commercial",
        "research",
        "real estate",
        "investor"
    ],
    "wof:name":"R B I",
    "wof:placetype":"venue"
},
  "geometry": {"coordinates":[-122.33384700000001,47.658747],"type":"Point"}
}