{
  "type": "Feature",
  "properties": {
    "addr:full":"39151 SE Gamma St Snoqualmie WA 98065",
    "addr:postcode":"39151;98065",
    "addr:street":"Se Gamma St",
    "iso:country":"US",
    "sg:address":"39151 SE Gamma St",
    "sg:city":"Snoqualmie",
    "sg:classifiers":[
        {
            "category":"Professional",
            "subcategory":"Computer Services",
            "type":"Services"
        }
    ],
    "sg:phone":"+1 425 313 5766",
    "sg:postcode":"98065",
    "sg:province":"WA",
    "sg:tags":[
        "prepackaged",
        "software"
    ],
    "wof:name":"Quality Control Software Inc",
    "wof:placetype":"venue"
},
  "geometry": {"coordinates":[-121.82043299999999,47.523197],"type":"Point"}
}