{
  "type": "Feature",
  "properties": {
    "addr:full":"1271 N Liberty Rd Zillah WA 98932",
    "addr:housenumber":"1271",
    "addr:postcode":"98932",
    "addr:street":"N Liberty Rd",
    "iso:country":"US",
    "sg:address":"1271 N Liberty Rd",
    "sg:city":"Zillah",
    "sg:classifiers":[
        {
            "category":"Farming",
            "subcategory":"Dairy Farm",
            "type":"Manufacturing & Wholesale Goods"
        }
    ],
    "sg:phone":"+1 509 829 6252",
    "sg:postcode":"98932",
    "sg:province":"WA",
    "wof:name":"Hank Bosma Dairy",
    "wof:placetype":"venue"
},
  "geometry": {"coordinates":[-120.14635699999999,46.391006],"type":"Point"}
}