{
  "type": "Feature",
  "properties": {
    "addr:full":"13296 Lake Shore Dr NW Poulsbo WA 98370",
    "addr:housenumber":"13296",
    "addr:postcode":"98370",
    "addr:street":"Lake Shore Dr Nw",
    "iso:country":"US",
    "sg:address":"13296 Lake Shore Dr NW",
    "sg:city":"Poulsbo",
    "sg:classifiers":[
        {
            "category":"Professional",
            "subcategory":"Business Services",
            "type":"Services"
        }
    ],
    "sg:phone":"+1 360 779 0051",
    "sg:postcode":"98370",
    "sg:province":"WA",
    "wof:name":"Internet Retail Group",
    "wof:placetype":"venue"
},
  "geometry": {"coordinates":[-122.65685499999999,47.683571],"type":"Point"}
}