{
  "type": "Feature",
  "properties": {
    "addr:full":"1443 N Northlake Way Seattle WA 98103",
    "addr:housenumber":"1443",
    "addr:postcode":"98103",
    "addr:street":"N Northlake Way",
    "iso:country":"US",
    "sg:address":"1443 N Northlake Way",
    "sg:city":"Seattle",
    "sg:classifiers":[
        {
            "category":"Wholesale",
            "subcategory":"Auto Parts",
            "type":"Manufacturing & Wholesale Goods"
        }
    ],
    "sg:phone":"+1 206 632 9986",
    "sg:postcode":"98103",
    "sg:province":"WA",
    "sg:tags":[
        "body",
        "shop",
        "supply",
        "automobile",
        "equipment"
    ],
    "wof:name":"D Muth Corrosives",
    "wof:placetype":"venue"
},
  "geometry": {"coordinates":[-122.340377,47.647688],"type":"Point"}
}