{
  "type": "Feature",
  "properties": {
    "addr:full":"15308 S Murphy Rd Cheney WA 99004",
    "addr:housenumber":"15308",
    "addr:postcode":"99004",
    "addr:street":"S Murphy Rd",
    "iso:country":"US",
    "sg:address":"15308 S Murphy Rd",
    "sg:city":"Cheney",
    "sg:classifiers":[
        {
            "category":"Building & Trades",
            "subcategory":"Construction",
            "type":"Services"
        }
    ],
    "sg:phone":"+1 509 235 8254",
    "sg:postcode":"99004",
    "sg:province":"WA",
    "sg:tags":[
        "home",
        "improvement"
    ],
    "wof:name":"Dave's",
    "wof:placetype":"venue"
},
  "geometry": {"coordinates":[-117.574127,47.514609],"type":"Point"}
}