{
  "type": "Feature",
  "properties": {
    "addr:full":"6016 California Ave SW Seattle WA 98136",
    "addr:housenumber":"6016",
    "addr:postcode":"98136",
    "addr:street":"California Ave Sw",
    "iso:country":"US",
    "sg:address":"6016 California Ave SW",
    "sg:city":"Seattle",
    "sg:classifiers":[
        {
            "category":"Retail",
            "subcategory":"Repair Shop",
            "type":"Services"
        }
    ],
    "sg:phone":"+1 206 933 5677",
    "sg:postcode":"98136",
    "sg:province":"WA",
    "sg:tags":[
        "consumer",
        "electronic"
    ],
    "wof:name":"Express TV & Vacuum Repair",
    "wof:placetype":"venue"
},
  "geometry": {"coordinates":[-122.38712,47.546777],"type":"Point"}
}