{
  "type": "Feature",
  "properties": {
    "addr:full":"16404 126th Ave NE Woodinville WA 98072",
    "addr:housenumber":"16404",
    "addr:postcode":"98072",
    "addr:street":"126Th Ave Ne",
    "iso:country":"US",
    "sg:address":"16404 126th Ave NE",
    "sg:city":"Woodinville",
    "sg:classifiers":[
        {
            "category":"Retail",
            "subcategory":"Repair Shop",
            "type":"Services"
        }
    ],
    "sg:phone":"+1 206 947 5249",
    "sg:postcode":"98072",
    "sg:province":"WA",
    "wof:name":"Petes Custom Cycle",
    "wof:placetype":"venue"
},
  "geometry": {"coordinates":[-122.172892,47.742477],"type":"Point"}
}