{
  "type": "Feature",
  "properties": {
    "addr:full":"529 Liberty St Walla Walla WA 99362",
    "addr:housenumber":"529",
    "addr:postcode":"99362",
    "addr:street":"Liberty St",
    "iso:country":"US",
    "sg:address":"529 Liberty St",
    "sg:city":"Walla Walla",
    "sg:classifiers":[
        {
            "category":"Building & Trades",
            "subcategory":"Cleaning & Sanitation",
            "type":"Services"
        }
    ],
    "sg:phone":"+1 509 525 3267",
    "sg:postcode":"99362",
    "sg:province":"WA",
    "sg:tags":[
        "maintenance"
    ],
    "wof:name":"Mc Shanes General Mainte",
    "wof:placetype":"venue"
},
  "geometry": {"coordinates":[-118.32459299999999,46.055142],"type":"Point"}
}