{
  "type": "Feature",
  "properties": {
    "addr:full":"7522 28th St W University Place WA 98466",
    "addr:housenumber":"7522",
    "addr:postcode":"98466",
    "addr:street":"28Th St W;Place",
    "iso:country":"US",
    "sg:address":"7522 28th St W",
    "sg:city":"University Place",
    "sg:classifiers":[
        {
            "category":"Real Estate",
            "subcategory":"Real Estate Agent",
            "type":"Services"
        }
    ],
    "sg:phone":"+1 253 565 8107",
    "sg:postcode":"98466",
    "sg:province":"WA",
    "sg:tags":[
        "appraiser"
    ],
    "wof:name":"Richmond Co",
    "wof:placetype":"venue"
},
  "geometry": {"coordinates":[-122.53874,47.234445],"type":"Point"}
}