{
  "type": "Feature",
  "properties": {
    "addr:full":"700 5th Ave Ste 5800 Seattle WA 98104",
    "addr:housenumber":"700",
    "addr:postcode":"98104",
    "addr:street":"5Th Ave Ste 5800",
    "iso:country":"US",
    "sg:address":"700 5th Ave Ste 5800",
    "sg:city":"Seattle",
    "sg:classifiers":[
        {
            "category":"Professional",
            "subcategory":"Lawyer & Legal Services",
            "type":"Services"
        }
    ],
    "sg:phone":"+1 206 626 1811",
    "sg:postcode":"98104",
    "sg:province":"WA",
    "wof:name":"McCraw Nicky D Carney Badley Spellman Attys",
    "wof:placetype":"venue"
},
  "geometry": {"coordinates":[-122.33000199999999,47.604401],"type":"Point"}
}