{
  "type": "Feature",
  "properties": {
    "addr:full":"8021 Portland Ave E Tacoma WA 98404",
    "addr:housenumber":"8021",
    "addr:postcode":"98404",
    "addr:street":"Portland Ave E",
    "iso:country":"US",
    "sg:address":"8021 Portland Ave E",
    "sg:city":"Tacoma",
    "sg:classifiers":[
        {
            "category":"Organizations",
            "subcategory":"Religious Organization",
            "type":"Services"
        }
    ],
    "sg:phone":"+1 253 535 0120",
    "sg:postcode":"98404",
    "sg:province":"WA",
    "sg:tags":[
        "church"
    ],
    "wof:name":"Last Days Ministries Church",
    "wof:placetype":"venue"
},
  "geometry": {"coordinates":[-122.407636,47.182438],"type":"Point"}
}