{
  "type": "Feature",
  "properties": {
    "addr:full":"7604 Myers Rd Sumner WA 98391",
    "addr:housenumber":"7604",
    "addr:postcode":"98391",
    "addr:street":"Myers Rd",
    "iso:country":"US",
    "sg:address":"7604 Myers Rd",
    "sg:city":"Sumner",
    "sg:classifiers":[
        {
            "category":"Building & Trades",
            "subcategory":"Construction",
            "type":"Services"
        }
    ],
    "sg:phone":"+1 253 863 5627",
    "sg:postcode":"98391",
    "sg:province":"WA",
    "sg:tags":[
        "house"
    ],
    "wof:name":"Rmb Construction Inc",
    "wof:placetype":"venue"
},
  "geometry": {"coordinates":[-122.192272,47.186299],"type":"Point"}
}