{
  "type": "Feature",
  "properties": {
    "addr:full":"3212 Northwest Ave Ste A Bellingham WA 98225",
    "addr:housenumber":"3212",
    "addr:postcode":"98225",
    "addr:street":"Northwest Ave Ste A",
    "iso:country":"US",
    "sg:address":"3212 Northwest Ave Ste A",
    "sg:city":"Bellingham",
    "sg:phone":"+1 360 527 2333",
    "sg:postcode":"98225",
    "sg:province":"WA",
    "wof:name":"Hawaii Bbq & Noodle House",
    "wof:placetype":"venue"
},
  "geometry": {"coordinates":[-122.495975,48.774136],"type":"Point"}
}