{
  "type": "Feature",
  "properties": {
    "addr:full":"3835 Midvale Rd Clinton WA 98236",
    "addr:housenumber":"3835",
    "addr:postcode":"98236",
    "addr:street":"Midvale Rd",
    "iso:country":"US",
    "sg:address":"3835 Midvale Rd",
    "sg:city":"Clinton",
    "sg:classifiers":[
        {
            "category":"Building & Trades",
            "subcategory":"Construction",
            "type":"Services"
        }
    ],
    "sg:phone":"+1 360 341 2587",
    "sg:postcode":"98236",
    "sg:province":"WA",
    "sg:tags":[
        "nonresidential"
    ],
    "wof:name":"C Max Construction",
    "wof:placetype":"venue"
},
  "geometry": {"coordinates":[-122.40469899999999,47.995968],"type":"Point"}
}