{
  "type": "Feature",
  "properties": {
    "iso:country":"US",
    "sg:address":"2842 SW 170th St",
    "sg:city":"Seattle",
    "sg:classifiers":[
        {
            "category":"Professional",
            "subcategory":"Engineering",
            "type":"Services"
        }
    ],
    "sg:phone":"+1 206 242 4172",
    "sg:postcode":"98166",
    "sg:province":"WA",
    "wof:name":"McGregor Electronics",
    "wof:placetype":"venue"
},
  "geometry": {"coordinates":[-122.37149599999999,47.450962],"type":"Point"}
}