{
  "type": "Feature",
  "properties": {
    "addr:full":"1033 Old Blyn Hwy Sequim WA 98382",
    "addr:housenumber":"1033",
    "addr:postcode":"98382",
    "addr:street":"Old Blyn Hwy",
    "iso:country":"US",
    "sg:address":"1033 Old Blyn Hwy",
    "sg:city":"Sequim",
    "sg:classifiers":[
        {
            "category":"Recreation",
            "type":"Entertainment"
        }
    ],
    "sg:phone":"+1 360 683 1109",
    "sg:postcode":"98382",
    "sg:province":"WA",
    "sg:tags":[
        "commercial",
        "art",
        "gallery"
    ],
    "wof:name":"Northwest Native Expressions",
    "wof:placetype":"venue"
},
  "geometry": {"coordinates":[-122.999211,48.022815],"type":"Point"}
}