{
  "type": "Feature",
  "properties": {
    "addr:full":"5805 Kensington Pl N Seattle WA 98103",
    "addr:housenumber":"5805",
    "addr:postcode":"98103",
    "addr:street":"Kensington Pl N",
    "iso:country":"US",
    "sg:address":"5805 Kensington Pl N",
    "sg:city":"Seattle",
    "sg:classifiers":[
        {
            "category":"Professional",
            "type":"Services"
        }
    ],
    "sg:phone":"+1 206 523 2829",
    "sg:postcode":"98103",
    "sg:province":"WA",
    "wof:name":"Julia D Boyd",
    "wof:placetype":"venue"
},
  "geometry": {"coordinates":[-122.33202,47.671532],"type":"Point"}
}