{
  "type": "Feature",
  "properties": {
    "addr:full":"3502 254th Ave SE Issaquah WA 98029",
    "addr:housenumber":"3502",
    "addr:postcode":"98029",
    "addr:street":"254Th Ave Se",
    "iso:country":"US",
    "sg:address":"3502 254th Ave SE",
    "sg:city":"Issaquah",
    "sg:classifiers":[
        {
            "category":"Restaurant",
            "type":"Food & Drink"
        }
    ],
    "sg:phone":"+1 425 391 6474",
    "sg:postcode":"98029",
    "sg:province":"WA",
    "sg:tags":[
        "eating"
    ],
    "wof:name":"Sculptures In Ice",
    "wof:placetype":"venue"
},
  "geometry": {"coordinates":[-122.000027,47.576442],"type":"Point"}
}