{
  "type": "Feature",
  "properties": {
    "addr:full":"114 2nd Ave Burbank WA 99323",
    "addr:housenumber":"114",
    "addr:postcode":"99323",
    "addr:street":"2Nd Ave",
    "iso:country":"US",
    "sg:address":"114 2nd Ave",
    "sg:city":"Burbank",
    "sg:classifiers":[
        {
            "category":"Government",
            "subcategory":"Post Office",
            "type":"Public Place"
        }
    ],
    "sg:phone":"+1 509 000 1111",
    "sg:postcode":"99323",
    "sg:province":"WA",
    "wof:name":"US Post Office",
    "wof:placetype":"venue"
},
  "geometry": {"coordinates":[-119.01863299999999,46.2025],"type":"Point"}
}