{
  "type": "Feature",
  "properties": {
    "addr:full":"5391 US Hwy 12 Malone WA 98559",
    "addr:housenumber":"5391",
    "addr:postcode":"98559",
    "addr:street":"Us Hwy 12 Malone",
    "iso:country":"US",
    "sg:address":"5391 US Hwy 12",
    "sg:city":"Malone",
    "sg:classifiers":[
        {
            "category":"Government",
            "subcategory":"Post Office",
            "type":"Public Place"
        }
    ],
    "sg:phone":"+1 360 482 3320",
    "sg:postcode":"98559",
    "sg:province":"WA",
    "wof:name":"US Post Office",
    "wof:placetype":"venue"
},
  "geometry": {"coordinates":[-123.32923599999999,46.959833],"type":"Point"}
}