{
  "type": "Feature",
  "properties": {
    "addr:full":"18053 28th Ave NE Seattle WA 98155",
    "addr:housenumber":"18053",
    "addr:postcode":"98155",
    "addr:street":"28Th Ave Ne",
    "iso:country":"US",
    "sg:address":"18053 28th Ave NE",
    "sg:city":"Seattle",
    "sg:classifiers":[
        {
            "category":"Arts & Performance",
            "subcategory":"Theater",
            "type":"Entertainment"
        }
    ],
    "sg:phone":"+1 206 361 7171",
    "sg:postcode":"98155",
    "sg:province":"WA",
    "sg:tags":[
        "group"
    ],
    "wof:name":"Charles The Magician",
    "wof:placetype":"venue"
},
  "geometry": {"coordinates":[-122.302837,47.760092],"type":"Point"}
}