{
  "type": "Feature",
  "properties": {
    "iso:country":"US",
    "sg:address":"2561 152nd Ave NE",
    "sg:city":"Redmond",
    "sg:classifiers":[
        {
            "category":"Professional",
            "subcategory":"Engineering",
            "type":"Services"
        }
    ],
    "sg:phone":"+1 425 895 8484",
    "sg:postcode":"98052",
    "sg:province":"WA",
    "sg:tags":[
        "wholesale",
        "electrical",
        "equipment"
    ],
    "wof:name":"Pacific Machine Automation",
    "wof:placetype":"venue"
},
  "geometry": {"coordinates":[-122.137694,47.632247],"type":"Point"}
}