{
  "type": "Feature",
  "properties": {
    "addr:full":"3411 Fremont Ave N Seattle WA 98103",
    "addr:housenumber":"3411",
    "addr:postcode":"98103",
    "addr:street":"Fremont Ave N",
    "iso:country":"US",
    "sg:address":"3411 Fremont Ave N",
    "sg:city":"Seattle",
    "sg:classifiers":[
        {
            "category":"Restaurant",
            "type":"Food & Drink"
        }
    ],
    "sg:menulink":"http://www.allmenus.com/wa/seattle/275782-blue-c-sushi/menu/",
    "sg:phone":"+1 425 774 3719",
    "sg:postcode":"98103",
    "sg:province":"WA",
    "sg:tags":[
        "sushi",
        "japanese",
        "asian"
    ],
    "wof:name":"Blue C Sushi",
    "wof:placetype":"venue"
},
  "geometry": {"coordinates":[-122.349802,47.649666],"type":"Point"}
}