{
  "type": "Feature",
  "properties": {
    "addr:full":"10667 NE 2nd St Bellevue WA 98004",
    "addr:housenumber":"10667",
    "addr:postcode":"98004",
    "addr:street":"Ne 2Nd St",
    "iso:country":"US",
    "sg:address":"10667 NE 2nd St",
    "sg:city":"Bellevue",
    "sg:classifiers":[
        {
            "category":"Professional",
            "subcategory":"Business Services",
            "type":"Services"
        }
    ],
    "sg:phone":"+1 425 454 8318",
    "sg:postcode":"98004",
    "sg:province":"WA",
    "sg:tags":[
        "holding"
    ],
    "wof:name":"Vision Care Holdings",
    "wof:placetype":"venue"
},
  "geometry": {"coordinates":[-122.197914,47.611996],"type":"Point"}
}