{
  "type": "Feature",
  "properties": {
    "addr:full":"43 S Palouse St Walla Walla WA 99362",
    "addr:housenumber":"43",
    "addr:postcode":"99362",
    "addr:street":"S Palouse St",
    "iso:country":"US",
    "sg:address":"43 S Palouse St",
    "sg:city":"Walla Walla",
    "sg:classifiers":[
        {
            "category":"Shopping",
            "subcategory":"Books",
            "type":"Retail Goods"
        }
    ],
    "sg:phone":"+1 509 529 7658",
    "sg:postcode":"99362",
    "sg:province":"WA",
    "wof:name":"Lumen Christi Books Gifts & Ch",
    "wof:placetype":"venue"
},
  "geometry": {"coordinates":[-118.33462299999999,46.068939],"type":"Point"}
}