{
  "type": "Feature",
  "properties": {
    "addr:full":"516 S King St Seattle WA 98104",
    "addr:housenumber":"516",
    "addr:postcode":"98104",
    "addr:street":"S King St",
    "iso:country":"US",
    "sg:address":"516 S King St",
    "sg:city":"Seattle",
    "sg:classifiers":[
        {
            "category":"Professional",
            "subcategory":"Secretarial Services",
            "type":"Services"
        }
    ],
    "sg:phone":"+1 206 296 9173",
    "sg:postcode":"98104",
    "sg:province":"WA",
    "sg:tags":[
        "convention",
        "reporting",
        "reporters-court"
    ],
    "wof:name":"Diane C Stanley",
    "wof:placetype":"venue"
},
  "geometry": {"coordinates":[-122.32745,47.598387],"type":"Point"}
}