{
  "type": "Feature",
  "properties": {
    "addr:full":"27618 SE 15th St Camas WA 98607",
    "addr:postcode":"27618;98607",
    "addr:street":"Se 15Th St",
    "iso:country":"US",
    "sg:address":"27618 SE 15th St",
    "sg:city":"Camas",
    "sg:classifiers":[
        {
            "category":"Building & Trades",
            "subcategory":"Locksmith",
            "type":"Services"
        }
    ],
    "sg:phone":"+1 360 818 9102",
    "sg:postcode":"98607",
    "sg:province":"WA",
    "sg:tags":[
        "key"
    ],
    "wof:name":"15 Min Anytime Anywhere Locksmith",
    "wof:placetype":"venue"
},
  "geometry": {"coordinates":[-122.389349,45.610825],"type":"Point"}
}