{
  "type": "Feature",
  "properties": {
    "addr:full":"1923 1st Ave Ste 100 Seattle WA 98101",
    "addr:housenumber":"1923",
    "addr:postcode":"98101",
    "addr:street":"1St Ave Ste 100",
    "iso:country":"US",
    "sg:address":"1923 1st Ave Ste 100",
    "sg:city":"Seattle",
    "sg:classifiers":[
        {
            "category":"Personal",
            "subcategory":"Beauty Salon",
            "type":"Services"
        }
    ],
    "sg:phone":"+1 206 443 4646",
    "sg:postcode":"98101",
    "sg:province":"WA",
    "sg:tags":[
        "hair"
    ],
    "sg:website":"www.couperokei.com",
    "wof:name":"Coupe Rokei",
    "wof:placetype":"venue"
},
  "geometry": {"coordinates":[-122.34236199999999,47.610562],"type":"Point"}
}