{
  "type": "Feature",
  "properties": {
    "addr:full":"29805 8th Pl S Federal Way WA 98003",
    "addr:housenumber":"29805",
    "addr:postcode":"98003",
    "addr:street":"8Th Pl S Federal Way",
    "iso:country":"US",
    "sg:address":"29805 8th Pl S",
    "sg:city":"Federal Way",
    "sg:classifiers":[
        {
            "category":"Professional",
            "type":"Services"
        }
    ],
    "sg:phone":"+1 253 839 4329",
    "sg:postcode":"98003",
    "sg:province":"WA",
    "sg:tags":[
        "nuclear",
        "consultant"
    ],
    "wof:name":"Information Science Inc",
    "wof:placetype":"venue"
},
  "geometry": {"coordinates":[-122.322868,47.334131],"type":"Point"}
}