{
  "type": "Feature",
  "properties": {
    "addr:full":"1218 10th Ave Seattle WA 98122",
    "addr:housenumber":"1218",
    "addr:postcode":"98122",
    "addr:street":"10Th Ave",
    "iso:country":"US",
    "sg:address":"1218 10th Ave",
    "sg:city":"Seattle",
    "sg:classifiers":[
        {
            "category":"Retail",
            "subcategory":"Auto Repair",
            "type":"Services"
        }
    ],
    "sg:phone":"+1 206 322 6242",
    "sg:postcode":"98122",
    "sg:province":"WA",
    "sg:website":"www.frybrid.com",
    "wof:name":"Frybrid",
    "wof:placetype":"venue"
},
  "geometry": {"coordinates":[-122.319186,47.612176],"type":"Point"}
}