{
  "type": "Feature",
  "properties": {
    "iso:country":"US",
    "sg:address":"142 S Texas Ave",
    "sg:city":"East Wenatchee",
    "sg:classifiers":[
        {
            "category":"Farming",
            "subcategory":"Livestock Farm",
            "type":"Manufacturing & Wholesale Goods"
        }
    ],
    "sg:phone":"+1 509 884 8142",
    "sg:postcode":"98802",
    "sg:province":"WA",
    "sg:tags":[
        "specialty",
        "animal"
    ],
    "wof:name":"Ew Kramar",
    "wof:placetype":"venue"
},
  "geometry": {"coordinates":[-120.221537,47.402557],"type":"Point"}
}