{
  "type": "Feature",
  "properties": {
    "addr:full":"452 Meadow Ct Colville WA 99114",
    "addr:housenumber":"452",
    "addr:postcode":"99114",
    "addr:street":"Meadow Ct",
    "iso:country":"US",
    "sg:address":"452 Meadow Ct",
    "sg:city":"Colville",
    "sg:classifiers":[
        {
            "category":"Social Services",
            "subcategory":"Child Care",
            "type":"Services"
        }
    ],
    "sg:phone":"+1 509 685 0549",
    "sg:postcode":"99114",
    "sg:province":"WA",
    "sg:tags":[
        "day"
    ],
    "wof:name":"Country Homes Daycare",
    "wof:placetype":"venue"
},
  "geometry": {"coordinates":[-117.840673,48.524869],"type":"Point"}
}