{
  "type": "Feature",
  "properties": {
    "addr:full":"232 A St Friday Harbor WA 98250",
    "addr:housenumber":"232",
    "addr:postcode":"98250",
    "addr:street":"A St",
    "iso:country":"US",
    "sg:address":"232 A St",
    "sg:city":"Friday Harbor",
    "sg:classifiers":[
        {
            "category":"Shopping",
            "subcategory":"Gifts & Souvenirs",
            "type":"Retail Goods"
        }
    ],
    "sg:phone":"+1 360 378 9610",
    "sg:postcode":"98250",
    "sg:province":"WA",
    "wof:name":"Monkeys 2 Go",
    "wof:placetype":"venue"
},
  "geometry": {"coordinates":[-123.015117,48.533972],"type":"Point"}
}