{
  "type": "Feature",
  "properties": {
    "addr:full":"143 N Kelsey St Monroe WA 98272",
    "addr:housenumber":"143",
    "addr:postcode":"98272",
    "addr:street":"N Kelsey St",
    "iso:country":"US",
    "sg:address":"143 N Kelsey St",
    "sg:city":"Monroe",
    "sg:classifiers":[
        {
            "category":"Fast Food",
            "type":"Food & Drink"
        },
        {
            "category":"Restaurant",
            "type":"Food & Drink"
        }
    ],
    "sg:phone":"+1 360 794 5238",
    "sg:postcode":"98272",
    "sg:province":"WA",
    "sg:tags":[
        "hot",
        "hamburger",
        "dog"
    ],
    "wof:name":"Pop Fly Dogs",
    "wof:placetype":"venue"
},
  "geometry": {"coordinates":[-121.977188,47.855419],"type":"Point"}
}