{
  "type": "Feature",
  "properties": {
    "addr:full":"1508 39th Ave E Seattle WA 98112",
    "addr:housenumber":"1508",
    "addr:postcode":"98112",
    "addr:street":"39Th Ave E",
    "iso:country":"US",
    "sg:address":"1508 39th Ave E",
    "sg:city":"Seattle",
    "sg:classifiers":[
        {
            "category":"Professional",
            "subcategory":"Management & Consulting",
            "type":"Services"
        }
    ],
    "sg:phone":"+1 206 953 2521",
    "sg:postcode":"98112",
    "sg:province":"WA",
    "wof:name":"N Andrew Elliott & Assoc",
    "wof:placetype":"venue"
},
  "geometry": {"coordinates":[-122.282612,47.632543],"type":"Point"}
}