{
  "type": "Feature",
  "properties": {
    "addr:full":"17341 32nd Ave S Seatac WA 98188",
    "addr:housenumber":"17341",
    "addr:postcode":"98188",
    "addr:street":"32Nd Ave S Seatac",
    "iso:country":"US",
    "sg:address":"17341 32nd Ave S",
    "sg:city":"Seatac",
    "sg:classifiers":[
        {
            "category":"Freight",
            "type":"Transportation"
        }
    ],
    "sg:phone":"+1 206 243 2881",
    "sg:postcode":"98188",
    "sg:province":"WA",
    "wof:name":"Elegant Transportation",
    "wof:placetype":"venue"
},
  "geometry": {"coordinates":[-122.291934,47.446517],"type":"Point"}
}