{
  "type": "Feature",
  "properties": {
    "addr:full":"209 Iverson Rd Stanwood WA 98282",
    "addr:housenumber":"209",
    "addr:postcode":"98282",
    "addr:street":"Iverson Rd",
    "iso:country":"US",
    "sg:address":"209 Iverson Rd",
    "sg:city":"Stanwood",
    "sg:classifiers":[
        {
            "category":"Manufacturing",
            "subcategory":"Metals",
            "type":"Manufacturing & Wholesale Goods"
        }
    ],
    "sg:phone":"+1 360 387 6500",
    "sg:postcode":"98282",
    "sg:province":"WA",
    "sg:tags":[
        "blast",
        "furnace",
        "works"
    ],
    "wof:name":"Easy Launch Inc",
    "wof:placetype":"venue"
},
  "geometry": {"coordinates":[-122.447028,48.204006],"type":"Point"}
}