{
  "type": "Feature",
  "properties": {
    "addr:full":"72 SW Chehalis Ave Chehalis WA 98532",
    "addr:housenumber":"72",
    "addr:postcode":"98532",
    "addr:street":"Sw Chehalis Ave",
    "iso:country":"US",
    "sg:address":"72 SW Chehalis Ave",
    "sg:city":"Chehalis",
    "sg:classifiers":[
        {
            "category":"Social Services",
            "subcategory":"Child Care",
            "type":"Services"
        }
    ],
    "sg:phone":"+1 360 740 9211",
    "sg:postcode":"98532",
    "sg:province":"WA",
    "sg:tags":[
        "day"
    ],
    "wof:name":"Fun Time Afterschool",
    "wof:placetype":"venue"
},
  "geometry": {"coordinates":[-122.969528,46.659407],"type":"Point"}
}