{
  "type": "Feature",
  "properties": {
    "addr:full":"947 NE Boat St Seattle WA 98105",
    "addr:housenumber":"947",
    "addr:postcode":"98105",
    "addr:street":"Ne Boat St",
    "iso:country":"US",
    "sg:address":"947 NE Boat St",
    "sg:city":"Seattle",
    "sg:classifiers":[
        {
            "category":"Professional",
            "type":"Services"
        }
    ],
    "sg:phone":"+1 425 822 0614",
    "sg:postcode":"98105",
    "sg:province":"WA",
    "sg:tags":[
        "establishment"
    ],
    "wof:name":"Buck Enterprises",
    "wof:placetype":"venue"
},
  "geometry": {"coordinates":[-122.31779,47.65333],"type":"Point"}
}