{
  "type": "Feature",
  "properties": {
    "addr:full":"2405 50th Ave SW Olympia WA 98512",
    "addr:housenumber":"2405",
    "addr:postcode":"98512",
    "addr:street":"50Th Ave Sw",
    "iso:country":"US",
    "sg:address":"2405 50th Ave SW",
    "sg:city":"Olympia",
    "sg:classifiers":[
        {
            "category":"Manufacturing",
            "subcategory":"Tools & Machinery",
            "type":"Manufacturing & Wholesale Goods"
        }
    ],
    "sg:phone":"+1 360 754 3801",
    "sg:postcode":"98512",
    "sg:province":"WA",
    "sg:tags":[
        "paper",
        "die",
        "industrial",
        "maker",
        "mfg"
    ],
    "wof:name":"Pacific West Coast Dies Inc",
    "wof:placetype":"venue"
},
  "geometry": {"coordinates":[-122.936178,47.002957],"type":"Point"}
}