{
  "type": "Feature",
  "properties": {
    "addr:full":"1250 Sandstone Way Bellingham WA 98229",
    "addr:housenumber":"1250",
    "addr:postcode":"98229",
    "addr:street":"Sandstone Way",
    "iso:country":"US",
    "sg:address":"1250 Sandstone Way",
    "sg:city":"Bellingham",
    "sg:classifiers":[
        {
            "category":"Shopping",
            "type":"Retail Goods"
        }
    ],
    "sg:phone":"+1 360 734 8789",
    "sg:postcode":"98229",
    "sg:province":"WA",
    "sg:tags":[
        "merchandise"
    ],
    "wof:name":"Sweet Diehl Cookie Shoppe",
    "wof:placetype":"venue"
},
  "geometry": {"coordinates":[-122.42811399999999,48.704617],"type":"Point"}
}