{
  "type": "Feature",
  "properties": {
    "addr:full":"111 N 50th St Seattle WA 98103",
    "addr:housenumber":"111",
    "addr:postcode":"98103",
    "addr:street":"N 50Th St",
    "iso:country":"US",
    "sg:address":"111 N 50th St",
    "sg:city":"Seattle",
    "sg:classifiers":[
        {
            "category":"Professional",
            "subcategory":"Computer Services",
            "type":"Services"
        }
    ],
    "sg:phone":"+1 206 789 3695",
    "sg:postcode":"98103",
    "sg:province":"WA",
    "sg:tags":[
        "development",
        "software"
    ],
    "sg:website":"www.ironwoodsoftware.net",
    "wof:name":"Ironwood Software Inc",
    "wof:placetype":"venue"
},
  "geometry": {"coordinates":[-122.35547,47.664962],"type":"Point"}
}