{
  "type": "Feature",
  "properties": {
    "addr:full":"372 St Martins Springs Rd Carson WA 98610",
    "addr:housenumber":"372",
    "addr:postcode":"98610",
    "addr:street":"St Martins Springs Rd",
    "iso:country":"US",
    "sg:address":"372 St Martins Springs Rd",
    "sg:city":"Carson",
    "sg:classifiers":[
        {
            "category":"Restaurant",
            "type":"Food & Drink"
        }
    ],
    "sg:phone":"+1 509 427 7151",
    "sg:postcode":"98610",
    "sg:province":"WA",
    "wof:name":"Carson Mineral Hot Springs",
    "wof:placetype":"venue"
},
  "geometry": {"coordinates":[-121.79765399999999,45.727172],"type":"Point"}
}