{
  "type": "Feature",
  "properties": {
    "addr:full":"110 Union St Seattle WA 98101",
    "addr:housenumber":"110",
    "addr:postcode":"98101",
    "addr:street":"Union St",
    "iso:country":"US",
    "sg:address":"110 Union St",
    "sg:city":"Seattle",
    "sg:classifiers":[
        {
            "category":"Real Estate",
            "subcategory":"Real Estate Agent",
            "type":"Services"
        }
    ],
    "sg:phone":"+1 206 749 8171",
    "sg:postcode":"98101",
    "sg:province":"WA",
    "wof:name":"Ken Hutchen Real Estate",
    "wof:placetype":"venue"
},
  "geometry": {"coordinates":[-122.338469,47.60815],"type":"Point"}
}