{
  "type": "Feature",
  "properties": {
    "addr:full":"1101 N Columbia Center Blvd Kennewick WA 99336",
    "addr:housenumber":"1101",
    "addr:postcode":"99336",
    "addr:street":"N Columbia Center Blvd",
    "iso:country":"US",
    "sg:address":"1101 N Columbia Center Blvd",
    "sg:city":"Kennewick",
    "sg:classifiers":[
        {
            "category":"Travel",
            "subcategory":"Hotels & Motels",
            "type":"Entertainment"
        }
    ],
    "sg:phone":"+1 509 783 0611",
    "sg:postcode":"99336",
    "sg:province":"WA",
    "sg:website":"www.redlion.com",
    "wof:name":"Red Lion Columbia Ctr Kennewck",
    "wof:placetype":"venue"
},
  "geometry": {"coordinates":[-119.22375599999999,46.222929],"type":"Point"}
}