{
  "type": "Feature",
  "properties": {
    "addr:full":"1015 Lee Blvd Richland WA 99352",
    "addr:housenumber":"1015",
    "addr:postcode":"99352",
    "addr:street":"Lee Blvd",
    "iso:country":"US",
    "sg:address":"1015 Lee Blvd",
    "sg:city":"Richland",
    "sg:classifiers":[
        {
            "category":"Restaurant",
            "type":"Food & Drink"
        }
    ],
    "sg:phone":"+1 509 946 5465",
    "sg:postcode":"99352",
    "sg:province":"WA",
    "wof:name":"Atomic Ale Brewpub & Eatery",
    "wof:placetype":"venue"
},
  "geometry": {"coordinates":[-119.278414,46.274761],"type":"Point"}
}