{
  "type": "Feature",
  "properties": {
    "addr:full":"1200 N 14th Ave Pasco WA 99301",
    "addr:housenumber":"1200",
    "addr:postcode":"99301",
    "addr:street":"N 14Th Ave",
    "iso:country":"US",
    "sg:address":"1200 N 14th Ave",
    "sg:city":"Pasco",
    "sg:classifiers":[
        {
            "category":"Wholesale",
            "subcategory":"Medical Equipment & Supplies",
            "type":"Manufacturing & Wholesale Goods"
        },
        {
            "category":"Shopping",
            "subcategory":"Beauty & Cosmetics",
            "type":"Retail Goods"
        },
        {
            "category":"Food & Beverages",
            "subcategory":"Specialty",
            "type":"Retail Goods"
        },
        {
            "category":"Shopping",
            "subcategory":"Computers & Home Electronics",
            "type":"Retail Goods"
        },
        {
            "category":"Shopping",
            "subcategory":"Optical Goods",
            "type":"Retail Goods"
        },
        {
            "category":"Personal",
            "subcategory":"Skin Care",
            "type":"Services"
        },
        {
            "category":"Manufacturing",
            "subcategory":"Chemicals & Compounds",
            "type":"Manufacturing & Wholesale Goods"
        },
        {
            "category":"Retail",
            "subcategory":"Photofinishing",
            "type":"Services"
        },
        {
            "category":"Shopping",
            "subcategory":"Pharmacy",
            "type":"Retail Goods"
        },
        {
            "category":"Health Services",
            "subcategory":"Optometrist",
            "type":"Services"
        },
        {
            "category":"Food & Beverages",
            "subcategory":"Groceries & Convenience Stores",
            "type":"Retail Goods"
        }
    ],
    "sg:phone":"+1 509 547 1220",
    "sg:postcode":"99301",
    "sg:province":"WA",
    "sg:tags":[
        "pharmaceutical",
        "product",
        "photo",
        "wheelchair",
        "vitamin",
        "perfume",
        "lens",
        "supplement",
        "contact",
        "wellness",
        "finishing",
        "consumer"
    ],
    "sg:website":"http://www.walgreens.com/default.jsp?ec=iyp_yellowpages_trademark",
    "wof:name":"Walgreens Pharmacies",
    "wof:placetype":"venue"
},
  "geometry": {"coordinates":[-119.107269,46.237862],"type":"Point"}
}