{
  "type": "Feature",
  "properties": {
    "addr:full":"3724 E Front Ave Spokane WA 99202",
    "addr:housenumber":"3724",
    "addr:postcode":"99202",
    "addr:street":"E Front Ave",
    "iso:country":"US",
    "sg:address":"3724 E Front Ave",
    "sg:city":"Spokane",
    "sg:classifiers":[
        {
            "category":"Building & Trades",
            "subcategory":"Construction",
            "type":"Services"
        }
    ],
    "sg:phone":"+1 509 535 2978",
    "sg:postcode":"99202",
    "sg:province":"WA",
    "sg:tags":[
        "general",
        "contractor"
    ],
    "wof:name":"Haskins Co",
    "wof:placetype":"venue"
},
  "geometry": {"coordinates":[-117.354969,47.659919],"type":"Point"}
}