{
  "type": "Feature",
  "properties": {
    "addr:full":"1111 E Longfellow Ave Spokane WA 99207",
    "addr:housenumber":"1111",
    "addr:postcode":"99207",
    "addr:street":"E Longfellow Ave",
    "iso:country":"US",
    "sg:address":"1111 E Longfellow Ave",
    "sg:city":"Spokane",
    "sg:classifiers":[
        {
            "category":"Professional",
            "subcategory":"Business Services",
            "type":"Services"
        }
    ],
    "sg:phone":"+1 509 487 6315",
    "sg:postcode":"99207",
    "sg:province":"WA",
    "wof:name":"Draftech Planning & Design",
    "wof:placetype":"venue"
},
  "geometry": {"coordinates":[-117.39357800000001,47.69773],"type":"Point"}
}