{
  "type": "Feature",
  "properties": {
    "addr:full":"9657 Levin Rd NW Silverdale WA 98383",
    "addr:housenumber":"9657",
    "addr:postcode":"98383",
    "addr:street":"Levin Rd Nw",
    "iso:country":"US",
    "sg:address":"9657 Levin Rd NW",
    "sg:city":"Silverdale",
    "sg:classifiers":[
        {
            "category":"Professional",
            "subcategory":"Management & Consulting",
            "type":"Services"
        }
    ],
    "sg:phone":"+1 360 698 9930",
    "sg:postcode":"98383",
    "sg:province":"WA",
    "wof:name":"Merrill Lynch",
    "wof:placetype":"venue"
},
  "geometry": {"coordinates":[-122.684668,47.653572],"type":"Point"}
}