{
  "type": "Feature",
  "properties": {
    "iso:country":"US",
    "sg:address":"18719 NE 161st Pl",
    "sg:city":"Woodinville",
    "sg:classifiers":[
        {
            "category":"Professional",
            "subcategory":"Computer Services",
            "type":"Services"
        }
    ],
    "sg:phone":"+1 425 844 2500",
    "sg:postcode":"98072",
    "sg:province":"WA",
    "sg:tags":[
        "internet"
    ],
    "sg:website":"www.i-ocom.com",
    "wof:name":"I/O Com Inc",
    "wof:placetype":"venue"
},
  "geometry": {"coordinates":[-122.089035,47.743994],"type":"Point"}
}