{
  "type": "Feature",
  "properties": {
    "addr:full":"4870 55th Ln SE Lacey WA 98503",
    "addr:housenumber":"4870",
    "addr:postcode":"98503",
    "addr:street":"55Th Ln Se",
    "iso:country":"US",
    "sg:address":"4870 55th Ln SE",
    "sg:city":"Lacey",
    "sg:phone":"+1 360 456 7800",
    "sg:postcode":"98503",
    "sg:province":"WA",
    "wof:name":"College Glen Apartments",
    "wof:placetype":"venue"
},
  "geometry": {"coordinates":[-122.822256,46.998905],"type":"Point"}
}