{
  "type": "Feature",
  "properties": {
    "addr:full":"302 S 9th St Tacoma WA 98402",
    "addr:housenumber":"302",
    "addr:postcode":"98402",
    "addr:street":"S 9Th St",
    "iso:country":"US",
    "sg:address":"302 S 9th St",
    "sg:city":"Tacoma",
    "sg:classifiers":[
        {
            "category":"Professional",
            "subcategory":"Advertising",
            "type":"Services"
        }
    ],
    "sg:phone":"+1 253 572 1100",
    "sg:postcode":"98402",
    "sg:province":"WA",
    "wof:name":"Comcast Spotlight",
    "wof:placetype":"venue"
},
  "geometry": {"coordinates":[-122.44119000000001,47.255142],"type":"Point"}
}