{
  "type": "Feature",
  "properties": {
    "addr:full":"4916 Sunnyside Blvd Marysville WA 98270",
    "addr:housenumber":"4916",
    "addr:postcode":"98270",
    "addr:street":"Sunnyside Blvd",
    "iso:country":"US",
    "sg:address":"4916 Sunnyside Blvd",
    "sg:city":"Marysville",
    "sg:classifiers":[
        {
            "category":"Professional",
            "type":"Services"
        }
    ],
    "sg:phone":"+1 425 397 0166",
    "sg:postcode":"98270",
    "sg:province":"WA",
    "wof:name":"Bean Brain",
    "wof:placetype":"venue"
},
  "geometry": {"coordinates":[-122.14637500000001,48.041455],"type":"Point"}
}