{
  "type": "Feature",
  "properties": {
    "addr:full":"528 E Providence Ave Spokane WA 99207",
    "addr:housenumber":"528",
    "addr:postcode":"99207",
    "addr:street":"E Providence Ave",
    "iso:country":"US",
    "sg:address":"528 E Providence Ave",
    "sg:city":"Spokane",
    "sg:classifiers":[
        {
            "category":"Retail",
            "subcategory":"Portrait Studio",
            "type":"Services"
        }
    ],
    "sg:phone":"+1 509 484 3761",
    "sg:postcode":"99207",
    "sg:province":"WA",
    "sg:tags":[
        "photo"
    ],
    "wof:name":"Gary Wagner Photography",
    "wof:placetype":"venue"
},
  "geometry": {"coordinates":[-117.401276,47.692244],"type":"Point"}
}