{
  "type": "Feature",
  "properties": {
    "iso:country":"US",
    "sg:address":"805 SW 312th St",
    "sg:city":"Federal Way",
    "sg:classifiers":[
        {
            "category":"Retail",
            "subcategory":"Auto Rental",
            "type":"Services"
        }
    ],
    "sg:phone":"+1 253 839 6237",
    "sg:postcode":"98023",
    "sg:province":"WA",
    "sg:tags":[
        "truck",
        "trailer",
        "utility"
    ],
    "wof:name":"U-Haul",
    "wof:placetype":"venue"
},
  "geometry": {"coordinates":[-122.34538999999999,47.32234],"type":"Point"}
}