{
  "type": "Feature",
  "properties": {
    "addr:full":"18523 61st Pl W Lynnwood WA 98037",
    "addr:housenumber":"18523",
    "addr:postcode":"98037",
    "addr:street":"61St Pl W",
    "iso:country":"US",
    "sg:address":"18523 61st Pl W",
    "sg:city":"Lynnwood",
    "sg:classifiers":[
        {
            "category":"Building & Trades",
            "subcategory":"Cleaning & Sanitation",
            "type":"Services"
        }
    ],
    "sg:phone":"+1 206 390 1139",
    "sg:postcode":"98037",
    "sg:province":"WA",
    "sg:tags":[
        "maintenance"
    ],
    "wof:name":"Window Wizards Corp",
    "wof:placetype":"venue"
},
  "geometry": {"coordinates":[-122.316093,47.830934],"type":"Point"}
}