{
  "type": "Feature",
  "properties": {
    "addr:full":"913 W 25th Ave Kennewick WA 99337",
    "addr:housenumber":"913",
    "addr:postcode":"99337",
    "addr:street":"W 25Th Ave",
    "iso:country":"US",
    "sg:address":"913 W 25th Ave",
    "sg:city":"Kennewick",
    "sg:classifiers":[
        {
            "category":"Retail",
            "subcategory":"Photofinishing",
            "type":"Services"
        }
    ],
    "sg:phone":"+1 509 586 8107",
    "sg:postcode":"99337",
    "sg:province":"WA",
    "sg:tags":[
        "laboratory"
    ],
    "wof:name":"Creative Memories",
    "wof:placetype":"venue"
},
  "geometry": {"coordinates":[-119.130219,46.18546],"type":"Point"}
}