{
  "type": "Feature",
  "properties": {
    "iso:country":"US",
    "sg:address":"2204 SE 134th Ave",
    "sg:city":"Vancouver",
    "sg:classifiers":[
        {
            "category":"Local Transit",
            "type":"Transportation"
        }
    ],
    "sg:phone":"+1 360 882 8885",
    "sg:postcode":"98683",
    "sg:province":"WA",
    "wof:name":"Cascade Coach",
    "wof:placetype":"venue"
},
  "geometry": {"coordinates":[-122.53496699999999,45.605323],"type":"Point"}
}