{
  "type": "Feature",
  "properties": {
    "addr:full":"7035 S 125th St Seattle WA 98178",
    "addr:housenumber":"7035",
    "addr:postcode":"98178",
    "addr:street":"S 125Th St",
    "iso:country":"US",
    "sg:address":"7035 S 125th St",
    "sg:city":"Seattle",
    "sg:classifiers":[
        {
            "category":"Professional",
            "type":"Services"
        }
    ],
    "sg:phone":"+1 206 772 6102",
    "sg:postcode":"98178",
    "sg:province":"WA",
    "sg:tags":[
        "establishment"
    ],
    "wof:name":"Finishing Touch Team",
    "wof:placetype":"venue"
},
  "geometry": {"coordinates":[-122.242705,47.49154],"type":"Point"}
}