{
  "type": "Feature",
  "properties": {
    "addr:full":"1160 23rd Avenue Seattle WA 98122",
    "addr:housenumber":"1160",
    "addr:postcode":"98122",
    "addr:street":"23Rd Avenue",
    "iso:country":"US",
    "sg:address":"1160 23rd Avenue",
    "sg:city":"Seattle",
    "sg:classifiers":[
        {
            "category":"Shopping",
            "subcategory":"Beauty & Cosmetics",
            "type":"Retail Goods"
        }
    ],
    "sg:phone":"+1 206 726 0455",
    "sg:postcode":"98122",
    "sg:province":"WA",
    "sg:tags":[
        "supply"
    ],
    "wof:name":"Mana Beauty Supply",
    "wof:placetype":"venue"
},
  "geometry": {"coordinates":[-122.30257899999999,47.611502],"type":"Point"}
}