{
  "type": "Feature",
  "properties": {
    "addr:full":"2912 W Lynn St Seattle WA 98199",
    "addr:housenumber":"2912",
    "addr:postcode":"98199",
    "addr:street":"W Lynn St",
    "iso:country":"US",
    "sg:address":"2912 W Lynn St",
    "sg:city":"Seattle",
    "sg:classifiers":[
        {
            "category":"Professional",
            "type":"Services"
        }
    ],
    "sg:phone":"+1 206 281 1222",
    "sg:postcode":"98199",
    "sg:province":"WA",
    "wof:name":"Cricket Events",
    "wof:placetype":"venue"
},
  "geometry": {"coordinates":[-122.395561,47.638898],"type":"Point"}
}