{
  "type": "Feature",
  "properties": {
    "addr:full":"423 Jackson St Port Townsend WA 98368",
    "addr:housenumber":"423",
    "addr:postcode":"98368",
    "addr:street":"Jackson St",
    "iso:country":"US",
    "sg:address":"423 Jackson St",
    "sg:city":"Port Townsend",
    "sg:classifiers":[
        {
            "category":"Retail",
            "subcategory":"Repair Shop",
            "type":"Services"
        }
    ],
    "sg:phone":"+1 360 379 6566",
    "sg:postcode":"98368",
    "sg:province":"WA",
    "wof:name":"TLC Marine Services",
    "wof:placetype":"venue"
},
  "geometry": {"coordinates":[-122.753282,48.118401],"type":"Point"}
}