{
  "type": "Feature",
  "properties": {
    "addr:full":"104 Green Gables Dr Centralia WA 98531",
    "addr:housenumber":"104",
    "addr:postcode":"98531",
    "addr:street":"Green Gables Dr",
    "iso:country":"US",
    "sg:address":"104 Green Gables Dr",
    "sg:city":"Centralia",
    "sg:classifiers":[
        {
            "category":"Professional",
            "subcategory":"Lawyer & Legal Services",
            "type":"Services"
        }
    ],
    "sg:phone":"+1 360 330 5297",
    "sg:postcode":"98531",
    "sg:province":"WA",
    "sg:tags":[
        "attorney"
    ],
    "wof:name":"Stephen R Geringer",
    "wof:placetype":"venue"
},
  "geometry": {"coordinates":[-122.894473,46.715847],"type":"Point"}
}