{
  "type": "Feature",
  "properties": {
    "addr:full":"18318 N Division Rd Colbert WA 99005",
    "addr:housenumber":"18318",
    "addr:postcode":"99005",
    "addr:street":"N Division Rd Colbert",
    "iso:country":"US",
    "sg:address":"18318 N Division Rd",
    "sg:city":"Colbert",
    "sg:classifiers":[
        {
            "category":"Freight",
            "type":"Transportation"
        }
    ],
    "sg:phone":"+1 509 466 7849",
    "sg:postcode":"99005",
    "sg:province":"WA",
    "wof:name":"T&N Freight LLC",
    "wof:placetype":"venue"
},
  "geometry": {"coordinates":[-117.410471,47.819373],"type":"Point"}
}