{
  "type": "Feature",
  "properties": {
    "addr:full":"1315 W 4th Ave Kennewick WA 99336",
    "addr:housenumber":"1315",
    "addr:postcode":"99336",
    "addr:street":"W 4Th Ave",
    "iso:country":"US",
    "sg:address":"1315 W 4th Ave",
    "sg:city":"Kennewick",
    "sg:classifiers":[
        {
            "category":"Government",
            "subcategory":"Office",
            "type":"Public Place"
        }
    ],
    "sg:phone":"+1 509 735 7581",
    "sg:postcode":"99336",
    "sg:province":"WA",
    "sg:tags":[
        "management",
        "resource",
        "solid",
        "air",
        "waste",
        "pollution"
    ],
    "wof:name":"Washington Ecology Department",
    "wof:placetype":"venue"
},
  "geometry": {"coordinates":[-119.13767799999999,46.205688],"type":"Point"}
}