{
  "type": "Feature",
  "properties": {
    "addr:full":"3015 Country Club Rd NW Olympia WA 98502",
    "addr:housenumber":"3015",
    "addr:postcode":"olympia wa 98502",
    "addr:street":"Country Club Rd Nw",
    "iso:country":"US",
    "sg:address":"3015 Country Club Rd NW",
    "sg:city":"Olympia",
    "sg:classifiers":[
        {
            "category":"Banks & Credit Unions",
            "subcategory":"Financial Services",
            "type":"Services"
        }
    ],
    "sg:phone":"+1 360 866 4125",
    "sg:postcode":"98502",
    "sg:province":"WA",
    "sg:tags":[
        "trust",
        "management"
    ],
    "wof:name":"Marvin Foundation Inc",
    "wof:placetype":"venue"
},
  "geometry": {"coordinates":[-122.945235,47.087215],"type":"Point"}
}