{
  "type": "Feature",
  "properties": {
    "addr:full":"238 E Alder St Walla Walla WA 99362",
    "addr:housenumber":"238",
    "addr:postcode":"99362",
    "addr:street":"E Alder St",
    "iso:country":"US",
    "sg:address":"238 E Alder St",
    "sg:city":"Walla Walla",
    "sg:classifiers":[
        {
            "category":"Education",
            "subcategory":"Library",
            "type":"Public Place"
        }
    ],
    "sg:phone":"+1 509 527 4388",
    "sg:postcode":"99362",
    "sg:province":"WA",
    "sg:tags":[
        "executive"
    ],
    "wof:name":"Walla Walla Public Library",
    "wof:placetype":"venue"
},
  "geometry": {"coordinates":[-118.335348,46.067012],"type":"Point"}
}