{
  "type": "Feature",
  "properties": {
    "addr:full":"331 NE McWilliams Ct Bremerton WA 98311",
    "addr:housenumber":"331",
    "addr:postcode":"98311",
    "addr:street":"Ne Mcwilliams Ct",
    "iso:country":"US",
    "sg:address":"331 NE McWilliams Ct",
    "sg:city":"Bremerton",
    "sg:classifiers":[
        {
            "category":"Professional",
            "subcategory":"Management & Consulting",
            "type":"Services"
        }
    ],
    "sg:phone":"+1 360 792 1550",
    "sg:postcode":"98311",
    "sg:province":"WA",
    "sg:tags":[
        "international",
        "consultant"
    ],
    "wof:name":"Fitzgerald Limited",
    "wof:placetype":"venue"
},
  "geometry": {"coordinates":[-122.647261,47.617819],"type":"Point"}
}