{
  "type": "Feature",
  "properties": {
    "addr:full":"26009 11th Ave E Spanaway WA 98387",
    "addr:housenumber":"26009",
    "addr:postcode":"98387",
    "addr:street":"11Th Ave E",
    "iso:country":"US",
    "sg:address":"26009 11th Ave E",
    "sg:city":"Spanaway",
    "sg:classifiers":[
        {
            "category":"Travel",
            "subcategory":"Hotels & Motels",
            "type":"Entertainment"
        }
    ],
    "sg:phone":"+1 253 875 4598",
    "sg:postcode":"98387",
    "sg:province":"WA",
    "wof:name":"11th Ave Gate",
    "wof:placetype":"venue"
},
  "geometry": {"coordinates":[-122.417284,47.018512],"type":"Point"}
}