{
  "type": "Feature",
  "properties": {
    "addr:full":"25019 N Madison Rd Chattaroy WA 99003",
    "addr:housenumber":"25019",
    "addr:postcode":"99003",
    "addr:street":"N Madison Rd",
    "iso:country":"US",
    "sg:address":"25019 N Madison Rd",
    "sg:city":"Chattaroy",
    "sg:classifiers":[
        {
            "category":"Building & Trades",
            "subcategory":"Construction",
            "type":"Services"
        }
    ],
    "sg:phone":"+1 509 238 4630",
    "sg:postcode":"99003",
    "sg:province":"WA",
    "sg:tags":[
        "house"
    ],
    "wof:name":"Highland Builders",
    "wof:placetype":"venue"
},
  "geometry": {"coordinates":[-117.239195,47.878381],"type":"Point"}
}