{
  "type": "Feature",
  "properties": {
    "addr:full":"140 Alta Lake Rd Pateros WA 98846",
    "addr:housenumber":"140",
    "addr:postcode":"98846",
    "addr:street":"Alta Lake Rd",
    "iso:country":"US",
    "sg:address":"140 Alta Lake Rd",
    "sg:city":"Pateros",
    "sg:classifiers":[
        {
            "category":"Sports & Exercise",
            "subcategory":"Golf",
            "type":"Entertainment"
        }
    ],
    "sg:phone":"+1 509 923 2359",
    "sg:postcode":"98846",
    "sg:province":"WA",
    "sg:tags":[
        "course"
    ],
    "wof:name":"Alta Lake Golf Resort",
    "wof:placetype":"venue"
},
  "geometry": {"coordinates":[-119.940816,48.023274],"type":"Point"}
}