{
  "type": "Feature",
  "properties": {
    "addr:full":"20437 SE 272nd St Covington WA 98042",
    "addr:postcode":"20437;98042",
    "addr:street":"Se 272Nd St",
    "iso:country":"US",
    "sg:address":"20437 SE 272nd St",
    "sg:city":"Covington",
    "sg:classifiers":[
        {
            "category":"Building & Trades",
            "subcategory":"Landscaping Services",
            "type":"Services"
        }
    ],
    "sg:phone":"+1 253 639 2896",
    "sg:postcode":"98042",
    "sg:province":"WA",
    "sg:tags":[
        "landscape",
        "contractor"
    ],
    "wof:name":"Holten Landscape & Rockeries",
    "wof:placetype":"venue"
},
  "geometry": {"coordinates":[-122.06918400000001,47.35797],"type":"Point"}
}