{
  "type": "Feature",
  "properties": {
    "addr:full":"1632 116th Ave NE Suite C Bellevue WA 98004",
    "addr:housenumber":"1632",
    "addr:postcode":"98004",
    "addr:street":"116Th Ave Ne Suite C",
    "iso:country":"US",
    "sg:address":"1632 116th Ave NE Suite C",
    "sg:city":"Bellevue",
    "sg:classifiers":[
        {
            "category":"Personal",
            "subcategory":"Massage",
            "type":"Services"
        },
        {
            "category":"Health Services",
            "subcategory":"Clinic",
            "type":"Services"
        },
        {
            "category":"Health Services",
            "subcategory":"Doctor",
            "type":"Services"
        },
        {
            "category":"Health Services",
            "subcategory":"Chiropractor",
            "type":"Services"
        }
    ],
    "sg:phone":"+1 425 285 9304",
    "sg:postcode":"98004",
    "sg:province":"WA",
    "sg:tags":[
        "medical",
        "welfare"
    ],
    "sg:website":"back2healthbellevue.com/",
    "wof:name":"Back 2 Health Bellevue",
    "wof:placetype":"venue"
},
  "geometry": {"coordinates":[-122.185564,47.625264],"type":"Point"}
}