{
  "type": "Feature",
  "properties": {
    "addr:full":"220 NW Sunrise Dr Pullman WA 99163",
    "addr:housenumber":"220",
    "addr:postcode":"99163",
    "addr:street":"Nw Sunrise Dr",
    "iso:country":"US",
    "sg:address":"220 NW Sunrise Dr",
    "sg:city":"Pullman",
    "sg:classifiers":[
        {
            "category":"Utilities",
            "subcategory":"Telephone",
            "type":"Services"
        }
    ],
    "sg:phone":"+1 509 332 2790",
    "sg:postcode":"99163",
    "sg:province":"WA",
    "sg:tags":[
        "communications"
    ],
    "wof:name":"Galexis Technologies",
    "wof:placetype":"venue"
},
  "geometry": {"coordinates":[-117.20128800000001,46.73114],"type":"Point"}
}