{
  "type": "Feature",
  "properties": {
    "addr:full":"1703 Canyon Rd Ellensburg WA 98926",
    "addr:housenumber":"1703",
    "addr:postcode":"98926",
    "addr:street":"Canyon Rd",
    "iso:country":"US",
    "sg:address":"1703 Canyon Rd",
    "sg:city":"Ellensburg",
    "sg:classifiers":[
        {
            "category":"Food & Beverages",
            "subcategory":"Groceries & Convenience Stores",
            "type":"Retail Goods"
        }
    ],
    "sg:phone":"+1 509 962 9527",
    "sg:postcode":"98926",
    "sg:province":"WA",
    "wof:name":"Toad's Express Mart & Deli",
    "wof:placetype":"venue"
},
  "geometry": {"coordinates":[-120.539282,46.971506],"type":"Point"}
}