{
  "type": "Feature",
  "properties": {
    "addr:full":"5913 152nd St E Puyallup WA 98375",
    "addr:housenumber":"5913",
    "addr:postcode":"98375",
    "addr:street":"152Nd St E",
    "iso:country":"US",
    "sg:address":"5913 152nd St E",
    "sg:city":"Puyallup",
    "sg:classifiers":[
        {
            "category":"Travel",
            "subcategory":"Travel Agent",
            "type":"Entertainment"
        }
    ],
    "sg:phone":"+1 253 538 2416",
    "sg:postcode":"98375",
    "sg:province":"WA",
    "sg:tags":[
        "tours",
        "promoter"
    ],
    "wof:name":"Adventures Northwest Tours",
    "wof:placetype":"venue"
},
  "geometry": {"coordinates":[-122.347706,47.118292],"type":"Point"}
}