{
  "type": "Feature",
  "properties": {
    "addr:full":"10024 Valmay Ave NW Seattle WA 98177",
    "addr:housenumber":"10024",
    "addr:postcode":"98177",
    "addr:street":"Valmay Ave Nw",
    "iso:country":"US",
    "sg:address":"10024 Valmay Ave NW",
    "sg:city":"Seattle",
    "sg:classifiers":[
        {
            "category":"Building & Trades",
            "subcategory":"Landscaping Services",
            "type":"Services"
        }
    ],
    "sg:phone":"+1 206 783 9188",
    "sg:postcode":"98177",
    "sg:province":"WA",
    "wof:name":"Pauls Gardening",
    "wof:placetype":"venue"
},
  "geometry": {"coordinates":[-122.378801,47.702439],"type":"Point"}
}