{
  "type": "Feature",
  "properties": {
    "addr:full":"27 Shafer Ave Naches WA 98937",
    "addr:housenumber":"27",
    "addr:postcode":"98937",
    "addr:street":"Shafer Ave",
    "iso:country":"US",
    "sg:address":"27 Shafer Ave",
    "sg:city":"Naches",
    "sg:classifiers":[
        {
            "category":"Retail",
            "subcategory":"Auto Repair",
            "type":"Services"
        }
    ],
    "sg:phone":"+1 509 453 2434",
    "sg:postcode":"98937",
    "sg:province":"WA",
    "sg:tags":[
        "general"
    ],
    "wof:name":"Bus Garage",
    "wof:placetype":"venue"
},
  "geometry": {"coordinates":[-120.694739,46.728958],"type":"Point"}
}