{
  "type": "Feature",
  "properties": {
    "addr:full":"625 C St Cheney WA 99004",
    "addr:housenumber":"625",
    "addr:postcode":"99004",
    "addr:street":"C St",
    "iso:country":"US",
    "sg:address":"625 C St",
    "sg:city":"Cheney",
    "sg:classifiers":[
        {
            "category":"Organizations",
            "subcategory":"Religious Organization",
            "type":"Services"
        }
    ],
    "sg:phone":"+1 509 235 6150",
    "sg:postcode":"99004",
    "sg:province":"WA",
    "sg:tags":[
        "place",
        "worship",
        "church"
    ],
    "wof:name":"Saint Paul's Episcopal Church",
    "wof:placetype":"venue"
},
  "geometry": {"coordinates":[-117.57811100000001,47.491425],"type":"Point"}
}