{
  "type": "Feature",
  "properties": {
    "iso:country":"US",
    "sg:address":"1131 Columbia St",
    "sg:city":"Port Angeles",
    "sg:classifiers":[
        {
            "category":"Building & Trades",
            "subcategory":"Construction",
            "type":"Services"
        }
    ],
    "sg:phone":"+1 360 565 1061",
    "sg:postcode":"98362",
    "sg:province":"WA",
    "sg:tags":[
        "contracting",
        "general"
    ],
    "wof:name":"Shadow Mountain Contg LLC",
    "wof:placetype":"venue"
},
  "geometry": {"coordinates":[-123.410707,48.114559],"type":"Point"}
}