{
  "type": "Feature",
  "properties": {
    "addr:full":"1011 W 1st Ave Spokane WA 99201",
    "addr:housenumber":"1011",
    "addr:postcode":"99201",
    "addr:street":"W 1St Ave",
    "iso:country":"US",
    "sg:address":"1011 W 1st Ave",
    "sg:city":"Spokane",
    "sg:classifiers":[
        {
            "category":"Restaurant",
            "type":"Food & Drink"
        }
    ],
    "sg:phone":"+1 509 235 2800",
    "sg:postcode":"99201",
    "sg:province":"WA",
    "sg:tags":[
        "eating"
    ],
    "wof:name":"Gattos Pizza Restaurant",
    "wof:placetype":"venue"
},
  "geometry": {"coordinates":[-117.427954,47.656464],"type":"Point"}
}