{
  "type": "Feature",
  "properties": {
    "iso:country":"US",
    "sg:address":"802 NW 104th St",
    "sg:city":"Vancouver",
    "sg:classifiers":[
        {
            "category":"Manufacturing",
            "subcategory":"Lumber",
            "type":"Manufacturing & Wholesale Goods"
        }
    ],
    "sg:phone":"+1 360 574 7013",
    "sg:postcode":"98685",
    "sg:province":"WA",
    "sg:tags":[
        "logging",
        "contractor"
    ],
    "wof:name":"Staples Logging Inc",
    "wof:placetype":"venue"
},
  "geometry": {"coordinates":[-122.678528,45.696963],"type":"Point"}
}