{
  "type": "Feature",
  "properties": {
    "addr:full":"600 1st Ave Seattle WA 98104",
    "addr:housenumber":"600",
    "addr:postcode":"98104",
    "addr:street":"1St Ave",
    "iso:country":"US",
    "sg:address":"600 1st Ave",
    "sg:city":"Seattle",
    "sg:classifiers":[
        {
            "category":"Fast Food",
            "type":"Food & Drink"
        },
        {
            "category":"Restaurant",
            "type":"Food & Drink"
        }
    ],
    "sg:phone":"+1 206 352 1600",
    "sg:postcode":"98104",
    "sg:province":"WA",
    "sg:tags":[
        "hamburger",
        "hot",
        "dog",
        "american",
        "take",
        "chicken"
    ],
    "sg:website":"http://www.mcdonalds.com",
    "wof:name":"McDonald's",
    "wof:placetype":"venue"
},
  "geometry": {"coordinates":[-122.334221,47.601761],"type":"Point"}
}