{
  "type": "Feature",
  "properties": {
    "addr:full":"11336 120th Ave NE Ste 125 Kirkland WA 98033",
    "addr:housenumber":"11336",
    "addr:postcode":"98033",
    "addr:street":"120Th Ave Ne Ste 125",
    "iso:country":"US",
    "sg:address":"11336 120th Ave NE Ste 125",
    "sg:city":"Kirkland",
    "sg:classifiers":[
        {
            "category":"Manufacturing",
            "subcategory":"Wood Products",
            "type":"Manufacturing & Wholesale Goods"
        },
        {
            "category":"Home & Garden",
            "subcategory":"Furniture",
            "type":"Retail Goods"
        },
        {
            "category":"Home & Garden",
            "subcategory":"Home Furnishings",
            "type":"Retail Goods"
        },
        {
            "category":"Building & Trades",
            "subcategory":"Construction",
            "type":"Services"
        },
        {
            "category":"Wholesale",
            "subcategory":"Home Furnishings",
            "type":"Manufacturing & Wholesale Goods"
        }
    ],
    "sg:phone":"+1 425 827 7050",
    "sg:postcode":"98033",
    "sg:province":"WA",
    "sg:tags":[
        "cabinets-wholesale",
        "equipment-wholesale",
        "kitchen",
        "cabinet",
        "refacing",
        "resurfacing",
        "equipment-household",
        "maker",
        "cabinets-refinishing",
        "manufacturer"
    ],
    "wof:name":"Walkers Custom Cabinets",
    "wof:placetype":"venue"
},
  "geometry": {"coordinates":[-122.18113700000001,47.701608],"type":"Point"}
}