{
  "type": "Feature",
  "properties": {
    "addr:full":"460 Dennis Blvd Port Townsend WA 98368",
    "addr:housenumber":"460",
    "addr:postcode":"98368",
    "addr:street":"Dennis Blvd",
    "iso:country":"US",
    "sg:address":"460 Dennis Blvd",
    "sg:city":"Port Townsend",
    "sg:classifiers":[
        {
            "category":"Manufacturing",
            "subcategory":"Printing",
            "type":"Manufacturing & Wholesale Goods"
        }
    ],
    "sg:phone":"+1 360 379 4080",
    "sg:postcode":"98368",
    "sg:province":"WA",
    "sg:tags":[
        "newspaper"
    ],
    "wof:name":"Inside Golf",
    "wof:placetype":"venue"
},
  "geometry": {"coordinates":[-122.87584,48.091924],"type":"Point"}
}