{
  "type": "Feature",
  "properties": {
    "addr:full":"15 W Yakima Ave Yakima WA 98902",
    "addr:housenumber":"15",
    "addr:postcode":"98902",
    "addr:street":"W Yakima Ave",
    "iso:country":"US",
    "sg:address":"15 W Yakima Ave",
    "sg:city":"Yakima",
    "sg:classifiers":[
        {
            "category":"Government",
            "subcategory":"Office",
            "type":"Public Place"
        }
    ],
    "sg:phone":"+1 509 225 2643",
    "sg:postcode":"98902",
    "sg:province":"WA",
    "sg:tags":[
        "agricultural",
        "regulation",
        "marketing"
    ],
    "wof:name":"Laboratory Services",
    "wof:placetype":"venue"
},
  "geometry": {"coordinates":[-120.50806799999999,46.601841],"type":"Point"}
}