{
  "type": "Feature",
  "properties": {
    "addr:full":"1016 Riesling Pl Prosser WA 99350",
    "addr:housenumber":"1016",
    "addr:postcode":"99350",
    "addr:street":"Riesling Pl",
    "iso:country":"US",
    "sg:address":"1016 Riesling Pl",
    "sg:city":"Prosser",
    "sg:classifiers":[
        {
            "category":"Building & Trades",
            "subcategory":"Construction",
            "type":"Services"
        }
    ],
    "sg:phone":"+1 509 786 5393",
    "sg:postcode":"99350",
    "sg:province":"WA",
    "sg:tags":[
        "house"
    ],
    "wof:name":"His Touch Construction",
    "wof:placetype":"venue"
},
  "geometry": {"coordinates":[-119.772453,46.193948],"type":"Point"}
}