{
  "type": "Feature",
  "properties": {
    "addr:full":"6818 Miner Dr SW Tumwater WA 98512",
    "addr:housenumber":"6818",
    "addr:postcode":"98512",
    "addr:street":"Miner Dr Sw",
    "iso:country":"US",
    "sg:address":"6818 Miner Dr SW",
    "sg:city":"Tumwater",
    "sg:classifiers":[
        {
            "category":"Real Estate",
            "subcategory":"Real Estate Services",
            "type":"Services"
        }
    ],
    "sg:phone":"+1 360 956 6818",
    "sg:postcode":"98512",
    "sg:province":"WA",
    "sg:tags":[
        "inspection"
    ],
    "wof:name":"Bryson Group",
    "wof:placetype":"venue"
},
  "geometry": {"coordinates":[-122.93332700000001,46.986777],"type":"Point"}
}