{
  "type": "Feature",
  "properties": {
    "addr:full":"1033 Sunset Blvd NE Renton WA 98056",
    "addr:housenumber":"1033",
    "addr:postcode":"98056",
    "addr:street":"Sunset Blvd Ne",
    "iso:country":"US",
    "sg:address":"1033 Sunset Blvd NE",
    "sg:city":"Renton",
    "sg:classifiers":[
        {
            "category":"Real Estate",
            "subcategory":"Real Estate Agent",
            "type":"Services"
        }
    ],
    "sg:phone":"+1 425 228 4857",
    "sg:postcode":"98056",
    "sg:province":"WA",
    "wof:name":"Cypress Pines Apartments",
    "wof:placetype":"venue"
},
  "geometry": {"coordinates":[-122.190168,47.499436],"type":"Point"}
}