{
  "type": "Feature",
  "properties": {
    "addr:full":"3509 Fremont Pl N Seattle WA 98103",
    "addr:housenumber":"3509",
    "addr:postcode":"98103",
    "addr:street":"Fremont Pl N",
    "iso:country":"US",
    "sg:address":"3509 Fremont Pl N",
    "sg:city":"Seattle",
    "sg:classifiers":[
        {
            "category":"Building & Trades",
            "subcategory":"Landscaping Services",
            "type":"Services"
        }
    ],
    "sg:phone":"+1 206 547 2002",
    "sg:postcode":"98103",
    "sg:province":"WA",
    "sg:tags":[
        "designer",
        "landscape"
    ],
    "wof:name":"Gaynor Landscape Arch/Dsgnrs",
    "wof:placetype":"venue"
},
  "geometry": {"coordinates":[-122.350837,47.650854],"type":"Point"}
}