{
  "type": "Feature",
  "properties": {
    "addr:full":"3210 S 176th St Apt 326 Seatac WA 98188",
    "addr:housenumber":"3210;326",
    "addr:postcode":"98188",
    "addr:street":"S 176Th St Apt",
    "iso:country":"US",
    "sg:address":"3210 S 176th St Apt 326",
    "sg:city":"Seatac",
    "sg:classifiers":[
        {
            "category":"Building & Trades",
            "subcategory":"Landscaping Services",
            "type":"Services"
        }
    ],
    "sg:phone":"+1 206 246 4370",
    "sg:postcode":"98188",
    "sg:province":"WA",
    "sg:tags":[
        "landscape",
        "contractor"
    ],
    "wof:name":"Ameri Landscaping & Gardening",
    "wof:placetype":"venue"
},
  "geometry": {"coordinates":[-122.291757,47.44527],"type":"Point"}
}