{
  "type": "Feature",
  "properties": {
    "addr:full":"19523 61st Ave NE Kenmore WA 98028",
    "addr:housenumber":"19523",
    "addr:postcode":"98028",
    "addr:street":"61St Ave Ne",
    "iso:country":"US",
    "sg:address":"19523 61st Ave NE",
    "sg:city":"Kenmore",
    "sg:classifiers":[
        {
            "category":"Autos & Motor Vehicles",
            "subcategory":"Auto Supplies",
            "type":"Retail Goods"
        }
    ],
    "sg:phone":"+1 206 459 9551",
    "sg:postcode":"98028",
    "sg:province":"WA",
    "wof:name":"Adrenaline Parts",
    "wof:placetype":"venue"
},
  "geometry": {"coordinates":[-122.264054,47.770239],"type":"Point"}
}