{
  "type": "Feature",
  "properties": {
    "iso:country":"US",
    "sg:address":"4515 177th Ave SE",
    "sg:city":"Bellevue",
    "sg:classifiers":[
        {
            "category":"Travel",
            "subcategory":"Travel Agent",
            "type":"Entertainment"
        }
    ],
    "sg:phone":"+1 425 378 1720",
    "sg:postcode":"98006",
    "sg:province":"WA",
    "sg:tags":[
        "operator",
        "tour"
    ],
    "wof:name":"Ride The Ducks of Seattle Inc",
    "wof:placetype":"venue"
},
  "geometry": {"coordinates":[-122.10632,47.564799],"type":"Point"}
}