{
  "type": "Feature",
  "properties": {
    "addr:full":"529 Rock Island Rd East Wenatchee WA 98802",
    "addr:housenumber":"529",
    "addr:postcode":"98802",
    "addr:street":"Rock Island Rd",
    "iso:country":"US",
    "sg:address":"529 Rock Island Rd",
    "sg:city":"East Wenatchee",
    "sg:classifiers":[
        {
            "category":"Personal",
            "subcategory":"Beauty Salon",
            "type":"Services"
        }
    ],
    "sg:phone":"+1 509 884 7018",
    "sg:postcode":"98802",
    "sg:province":"WA",
    "sg:tags":[
        "shop"
    ],
    "wof:name":"Karen Cortez",
    "wof:placetype":"venue"
},
  "geometry": {"coordinates":[-120.28006000000001,47.39547],"type":"Point"}
}