{
  "type": "Feature",
  "properties": {
    "addr:full":"160 NW Gilman Blvd Suite 2 Issaquah WA 98027",
    "addr:housenumber":"160",
    "addr:postcode":"98027",
    "addr:street":"Nw Gilman Blvd Suite 2",
    "iso:country":"US",
    "sg:address":"160 NW Gilman Blvd Suite 2",
    "sg:city":"Issaquah",
    "sg:classifiers":[
        {
            "category":"Shopping",
            "subcategory":"Jewelry",
            "type":"Retail Goods"
        },
        {
            "category":"Shopping",
            "subcategory":"Antiques",
            "type":"Retail Goods"
        },
        {
            "category":"Professional",
            "subcategory":"Business Services",
            "type":"Services"
        },
        {
            "category":"Personal",
            "type":"Services"
        },
        {
            "category":"Shopping",
            "subcategory":"Discount & Variety Stores",
            "type":"Retail Goods"
        }
    ],
    "sg:phone":"+1 425 440 0513",
    "sg:postcode":"98027",
    "sg:province":"WA",
    "sg:tags":[
        "liquidation",
        "liquidator",
        "auction",
        "estates-sales",
        "jeweler",
        "appraisal"
    ],
    "sg:website":"http://www.kbaileyantiques.com",
    "wof:name":"Antique Appraisal And Estate Sale Service-Kathleen Bailey",
    "wof:placetype":"venue"
},
  "geometry": {"coordinates":[-122.03834500000001,47.5393],"type":"Point"}
}