{
  "type": "Feature",
  "properties": {
    "addr:full":"924 176th St E Spanaway WA 98387",
    "addr:housenumber":"924",
    "addr:postcode":"98387",
    "addr:street":"176Th St E",
    "iso:country":"US",
    "sg:address":"924 176th St E",
    "sg:city":"Spanaway",
    "sg:classifiers":[
        {
            "category":"Real Estate",
            "subcategory":"Developer",
            "type":"Services"
        },
        {
            "category":"Retail",
            "subcategory":"Funeral Services",
            "type":"Services"
        }
    ],
    "sg:phone":"+1 253 531 6600",
    "sg:postcode":"98387",
    "sg:province":"WA",
    "sg:tags":[
        "director",
        "home",
        "cemetery"
    ],
    "sg:website":"www.firlane.com",
    "wof:name":"Fir Lane Funeral Home & Mem Pk",
    "wof:placetype":"venue"
},
  "geometry": {"coordinates":[-122.418198,47.096997],"type":"Point"}
}