{
  "type": "Feature",
  "properties": {
    "addr:full":"305 State Rte 4 Cathlamet WA 98612",
    "addr:housenumber":"305",
    "addr:postcode":"98612",
    "addr:street":"State Rte 4",
    "iso:country":"US",
    "sg:address":"305 State Rte 4",
    "sg:city":"Cathlamet",
    "sg:classifiers":[
        {
            "category":"Autos & Motor Vehicles",
            "subcategory":"Auto Supplies",
            "type":"Retail Goods"
        }
    ],
    "sg:phone":"+1 360 795 3269",
    "sg:postcode":"98612",
    "sg:province":"WA",
    "sg:tags":[
        "automobile",
        "parts"
    ],
    "wof:name":"Larry's Auto Parts",
    "wof:placetype":"venue"
},
  "geometry": {"coordinates":[-123.36593999999999,46.197021],"type":"Point"}
}