{
  "type": "Feature",
  "properties": {
    "addr:full":"1014 116th Ave NE Ste A - C Bellevue WA 98004",
    "addr:housenumber":"1014",
    "addr:postcode":"98004",
    "addr:street":"116Th Ave Ne Ste A",
    "iso:country":"US",
    "sg:address":"1014 116th Ave NE Ste A - C",
    "sg:city":"Bellevue",
    "sg:classifiers":[
        {
            "category":"Personal",
            "type":"Services"
        },
        {
            "category":"Home & Garden",
            "subcategory":"Hardware",
            "type":"Retail Goods"
        }
    ],
    "sg:phone":"+1 800 814 1729",
    "sg:postcode":"98004",
    "sg:province":"WA",
    "sg:tags":[
        "designing",
        "remodeling",
        "closet",
        "accessory"
    ],
    "sg:website":"http://www.californiaclosetsseattle.com",
    "wof:name":"California Closets",
    "wof:placetype":"venue"
},
  "geometry": {"coordinates":[-122.185669,47.619411],"type":"Point"}
}