{
  "type": "Feature",
  "properties": {
    "addr:full":"1520 S Oakes St Tacoma WA 98405",
    "addr:housenumber":"1520",
    "addr:postcode":"98405",
    "addr:street":"S Oakes St",
    "iso:country":"US",
    "sg:address":"1520 S Oakes St",
    "sg:city":"Tacoma",
    "sg:classifiers":[
        {
            "category":"Professional",
            "type":"Services"
        },
        {
            "category":"Professional",
            "subcategory":"Management & Consulting",
            "type":"Services"
        }
    ],
    "sg:phone":"+1 253 572 5203",
    "sg:postcode":"98405",
    "sg:province":"WA",
    "sg:tags":[
        "consultant",
        "energy",
        "conservation"
    ],
    "wof:name":"Autism Society of Washing",
    "wof:placetype":"venue"
},
  "geometry": {"coordinates":[-122.47190399999999,47.244944],"type":"Point"}
}