{
  "type": "Feature",
  "properties": {
    "addr:full":"1118 E Maple St Bellingham WA 98225",
    "addr:housenumber":"1118",
    "addr:postcode":"98225",
    "addr:street":"E Maple St",
    "iso:country":"US",
    "sg:address":"1118 E Maple St",
    "sg:city":"Bellingham",
    "sg:classifiers":[
        {
            "category":"Restaurant",
            "type":"Food & Drink"
        }
    ],
    "sg:menulink":"http://www.allmenus.com/wa/bellingham/237665-bostons-gourmet-pizza/menu/",
    "sg:phone":"+1 360 647 3600",
    "sg:postcode":"98225",
    "sg:province":"WA",
    "sg:tags":[
        "american",
        "pizza"
    ],
    "wof:name":"Boston's Gourmet Pizza",
    "wof:placetype":"venue"
},
  "geometry": {"coordinates":[-122.47160100000001,48.740821],"type":"Point"}
}