{
  "type": "Feature",
  "properties": {
    "addr:full":"1008 3rd St Sedro Woolley WA 98284",
    "addr:housenumber":"1008",
    "addr:postcode":"98284",
    "addr:street":"3Rd St",
    "iso:country":"US",
    "sg:address":"1008 3rd St",
    "sg:city":"Sedro Woolley",
    "sg:classifiers":[
        {
            "category":"Retail",
            "subcategory":"Funeral Services",
            "type":"Services"
        }
    ],
    "sg:phone":"+1 360 855 1288",
    "sg:postcode":"98284",
    "sg:province":"WA",
    "sg:tags":[
        "cemetery",
        "mortuary"
    ],
    "sg:website":"www.lemleychapel.com",
    "wof:name":"Lemley Funeral Chapel",
    "wof:placetype":"venue"
},
  "geometry": {"coordinates":[-122.237999,48.502102],"type":"Point"}
}