{
  "type": "Feature",
  "properties": {
    "iso:country":"US",
    "sg:address":"600 128th St SE",
    "sg:city":"Everett",
    "sg:classifiers":[
        {
            "category":"Education",
            "subcategory":"Special Training",
            "type":"Public Place"
        }
    ],
    "sg:phone":"+1 425 338 2400",
    "sg:postcode":"98208",
    "sg:province":"WA",
    "sg:tags":[
        "executive"
    ],
    "wof:name":"Snohomish Cooperative EXT",
    "wof:placetype":"venue"
},
  "geometry": {"coordinates":[-122.223276,47.881976],"type":"Point"}
}