{
  "type": "Feature",
  "properties": {
    "addr:full":"3004 Douglas Rd Ferndale WA 98248",
    "addr:housenumber":"3004",
    "addr:postcode":"98248",
    "addr:street":"Douglas Rd",
    "iso:country":"US",
    "sg:address":"3004 Douglas Rd",
    "sg:city":"Ferndale",
    "sg:classifiers":[
        {
            "category":"Manufacturing",
            "subcategory":"Food",
            "type":"Manufacturing & Wholesale Goods"
        }
    ],
    "sg:phone":"+1 360 380 1931",
    "sg:postcode":"98248",
    "sg:province":"WA",
    "sg:tags":[
        "ice",
        "mfg"
    ],
    "wof:name":"Ctmcc",
    "wof:placetype":"venue"
},
  "geometry": {"coordinates":[-122.645258,48.841175],"type":"Point"}
}