{
  "type": "Feature",
  "properties": {
    "addr:full":"4303 Meridian Ave N Seattle WA 98103",
    "addr:housenumber":"4303",
    "addr:postcode":"98103",
    "addr:street":"Meridian Ave N",
    "iso:country":"US",
    "sg:address":"4303 Meridian Ave N",
    "sg:city":"Seattle",
    "sg:classifiers":[
        {
            "category":"Home & Garden",
            "subcategory":"Furniture",
            "type":"Retail Goods"
        }
    ],
    "sg:phone":"+1 206 633 3702",
    "sg:postcode":"98103",
    "sg:province":"WA",
    "sg:tags":[
        "store"
    ],
    "wof:name":"Gellert Collection",
    "wof:placetype":"venue"
},
  "geometry": {"coordinates":[-122.333763,47.659154],"type":"Point"}
}