{
  "type": "Feature",
  "properties": {
    "addr:full":"6020 Airport Way S Seattle WA 98108",
    "addr:housenumber":"6020",
    "addr:postcode":"98108",
    "addr:street":"Airport Way S",
    "iso:country":"US",
    "sg:address":"6020 Airport Way S",
    "sg:city":"Seattle",
    "sg:classifiers":[
        {
            "category":"Coffee & Tea",
            "type":"Food & Drink"
        }
    ],
    "sg:phone":"+1 206 762 5300",
    "sg:postcode":"98108",
    "sg:province":"WA",
    "wof:name":"Caffe Umbria Inc",
    "wof:placetype":"venue"
},
  "geometry": {"coordinates":[-122.317001,47.5495],"type":"Point"}
}