{
  "type": "Feature",
  "properties": {
    "addr:full":"10025 E Montgomery Dr Spokane WA 99206",
    "addr:housenumber":"10025",
    "addr:postcode":"99206",
    "addr:street":"E Montgomery Dr",
    "iso:country":"US",
    "sg:address":"10025 E Montgomery Dr",
    "sg:city":"Spokane",
    "sg:classifiers":[
        {
            "category":"Manufacturing",
            "subcategory":"Tools & Machinery",
            "type":"Manufacturing & Wholesale Goods"
        }
    ],
    "sg:phone":"+1 509 928 9441",
    "sg:postcode":"99206",
    "sg:province":"WA",
    "sg:tags":[
        "machine",
        "shop"
    ],
    "wof:name":"Wilson Tool & Manufacturing Co",
    "wof:placetype":"venue"
},
  "geometry": {"coordinates":[-117.26916199999999,47.67974],"type":"Point"}
}