{
  "type": "Feature",
  "properties": {
    "addr:full":"50 Grey Rd Grandview WA 98930",
    "addr:housenumber":"50",
    "addr:postcode":"98930",
    "addr:street":"Grey Rd",
    "iso:country":"US",
    "sg:address":"50 Grey Rd",
    "sg:city":"Grandview",
    "sg:classifiers":[
        {
            "category":"Social Services",
            "subcategory":"Child Care",
            "type":"Services"
        }
    ],
    "sg:phone":"+1 509 882 4070",
    "sg:postcode":"98930",
    "sg:province":"WA",
    "sg:tags":[
        "day"
    ],
    "wof:name":"Teddy Bear Corner Day Care",
    "wof:placetype":"venue"
},
  "geometry": {"coordinates":[-119.978815,46.25038],"type":"Point"}
}