{
  "type": "Feature",
  "properties": {
    "addr:full":"304 Cullum Ave Richland WA 99352",
    "addr:housenumber":"304",
    "addr:postcode":"99352",
    "addr:street":"Cullum Ave",
    "iso:country":"US",
    "sg:address":"304 Cullum Ave",
    "sg:city":"Richland",
    "sg:classifiers":[
        {
            "category":"Professional",
            "subcategory":"Management & Consulting",
            "type":"Services"
        }
    ],
    "sg:phone":"+1 509 943 9340",
    "sg:postcode":"99352",
    "sg:province":"WA",
    "sg:tags":[
        "support",
        "facility"
    ],
    "wof:name":"Compasionate Friends Inc",
    "wof:placetype":"venue"
},
  "geometry": {"coordinates":[-119.27954099999999,46.268965],"type":"Point"}
}