{
  "type": "Feature",
  "properties": {
    "addr:full":"1308 144th St NW Gig Harbor WA 98332",
    "addr:housenumber":"1308",
    "addr:postcode":"98332",
    "addr:street":"144Th St Nw",
    "iso:country":"US",
    "sg:address":"1308 144th St NW",
    "sg:city":"Gig Harbor",
    "sg:classifiers":[
        {
            "category":"Building & Trades",
            "subcategory":"Construction",
            "type":"Services"
        }
    ],
    "sg:phone":"+1 253 312 1296",
    "sg:postcode":"98332",
    "sg:province":"WA",
    "sg:tags":[
        "house"
    ],
    "wof:name":"Baldwins Better Builders",
    "wof:placetype":"venue"
},
  "geometry": {"coordinates":[-122.55547799999999,47.388766],"type":"Point"}
}