{
  "type": "Feature",
  "properties": {
    "addr:full":"800 15th Ave SW Puyallup WA 98371",
    "addr:housenumber":"800",
    "addr:postcode":"98371",
    "addr:street":"15Th Ave Sw",
    "iso:country":"US",
    "sg:address":"800 15th Ave SW",
    "sg:city":"Puyallup",
    "sg:classifiers":[
        {
            "category":"Shopping",
            "subcategory":"Computers & Home Electronics",
            "type":"Retail Goods"
        }
    ],
    "sg:phone":"+1 253 770 4823",
    "sg:postcode":"98371",
    "sg:province":"WA",
    "sg:tags":[
        "programing",
        "custom"
    ],
    "wof:name":"Advanced Toolware LLC",
    "wof:placetype":"venue"
},
  "geometry": {"coordinates":[-122.302735,47.177296],"type":"Point"}
}