{
  "type": "Feature",
  "properties": {
    "addr:full":"1500 NE 87th Way Vancouver WA 98665",
    "addr:housenumber":"1500",
    "addr:postcode":"98665",
    "addr:street":"Ne 87Th Way",
    "iso:country":"US",
    "sg:address":"1500 NE 87th Way",
    "sg:city":"Vancouver",
    "sg:classifiers":[
        {
            "category":"Professional",
            "subcategory":"Art Services",
            "type":"Services"
        }
    ],
    "sg:phone":"+1 360 909 7813",
    "sg:postcode":"98665",
    "sg:province":"WA",
    "sg:tags":[
        "designer",
        "display",
        "producer"
    ],
    "wof:name":"Moxieme Designs",
    "wof:placetype":"venue"
},
  "geometry": {"coordinates":[-122.656677,45.685539],"type":"Point"}
}