{
  "type": "Feature",
  "properties": {
    "addr:full":"2021 130th Ave NE Ste A Bellevue WA 98005",
    "addr:housenumber":"2021",
    "addr:postcode":"98005",
    "addr:street":"130Th Ave Ne Ste A",
    "iso:country":"US",
    "sg:address":"2021 130th Ave NE Ste A",
    "sg:city":"Bellevue",
    "sg:classifiers":[
        {
            "category":"Building & Trades",
            "subcategory":"Cleaning & Sanitation",
            "type":"Services"
        },
        {
            "category":"Wholesale",
            "subcategory":"Construction Materials",
            "type":"Manufacturing & Wholesale Goods"
        },
        {
            "category":"Building & Trades",
            "subcategory":"Construction",
            "type":"Services"
        }
    ],
    "sg:phone":"+1 425 702 1200",
    "sg:postcode":"98005",
    "sg:province":"WA",
    "sg:tags":[
        "elevator-consultants",
        "elevators-repairing",
        "elevator",
        "cars-refinishing",
        "inspector"
    ],
    "sg:website":"http://www.thyssenkruppelevator.com",
    "wof:name":"ThyssenKrupp Elevator",
    "wof:placetype":"venue"
},
  "geometry": {"coordinates":[-122.167057,47.628076],"type":"Point"}
}