{
  "type": "Feature",
  "properties": {
    "addr:full":"1040 S Jackson St Seattle WA 98104",
    "addr:housenumber":"1040",
    "addr:postcode":"98104",
    "addr:street":"S Jackson St",
    "iso:country":"US",
    "sg:address":"1040 S Jackson St",
    "sg:city":"Seattle",
    "sg:classifiers":[
        {
            "category":"Food & Beverages",
            "subcategory":"Meat & Fish",
            "type":"Retail Goods"
        }
    ],
    "sg:phone":"+1 206 325 3483",
    "sg:postcode":"98104",
    "sg:province":"WA",
    "sg:tags":[
        "shop"
    ],
    "wof:name":"Minh Tam's Market Bbq & Deli",
    "wof:placetype":"venue"
},
  "geometry": {"coordinates":[-122.31912699999999,47.599341],"type":"Point"}
}