{
  "type": "Feature",
  "properties": {
    "addr:full":"500 S Auburn St Kennewick WA 99336",
    "addr:housenumber":"500",
    "addr:postcode":"99336",
    "addr:street":"S Auburn St",
    "iso:country":"US",
    "sg:address":"500 S Auburn St",
    "sg:city":"Kennewick",
    "sg:classifiers":[
        {
            "category":"Social Services",
            "type":"Services"
        }
    ],
    "sg:phone":"+1 509 585 4303",
    "sg:postcode":"99336",
    "sg:province":"WA",
    "sg:tags":[
        "senior",
        "citizen"
    ],
    "sg:website":"www.ci.kennewick.wa.us",
    "wof:name":"Kennewick Senior Citizen Ctr",
    "wof:placetype":"venue"
},
  "geometry": {"coordinates":[-119.118481,46.202631],"type":"Point"}
}