{
  "type": "Feature",
  "properties": {
    "addr:full":"323 N 85th St Seattle WA 98103",
    "addr:housenumber":"323",
    "addr:postcode":"98103",
    "addr:street":"N 85Th St",
    "iso:country":"US",
    "sg:address":"323 N 85th St",
    "sg:city":"Seattle",
    "sg:classifiers":[
        {
            "category":"Shopping",
            "subcategory":"Pharmacy",
            "type":"Retail Goods"
        }
    ],
    "sg:phone":"+1 206 789 0800",
    "sg:postcode":"98103",
    "sg:province":"WA",
    "sg:tags":[
        "food",
        "product",
        "health",
        "market",
        "diet"
    ],
    "wof:name":"Medicine Man Pharmacy",
    "wof:placetype":"venue"
},
  "geometry": {"coordinates":[-122.354158,47.690556],"type":"Point"}
}