{
  "type": "Feature",
  "properties": {
    "addr:full":"151 105th Ave Bellevue WA 98004",
    "addr:housenumber":"151",
    "addr:postcode":"98004",
    "addr:street":"105Th Ave",
    "iso:country":"US",
    "sg:address":"151 105th Ave",
    "sg:city":"Bellevue",
    "sg:classifiers":[
        {
            "category":"Shopping",
            "subcategory":"Florist",
            "type":"Retail Goods"
        }
    ],
    "sg:phone":"+1 425 454 7598",
    "sg:postcode":"98004",
    "sg:province":"WA",
    "wof:name":"Magnolia Flowers of Bellevue",
    "wof:placetype":"venue"
},
  "geometry": {"coordinates":[-122.200142,47.608525],"type":"Point"}
}