{
  "type": "Feature",
  "properties": {
    "addr:full":"4385 11th Ave NW Seattle WA 98107",
    "addr:housenumber":"4385",
    "addr:postcode":"98107",
    "addr:street":"11Th Ave Nw",
    "iso:country":"US",
    "sg:address":"4385 11th Ave NW",
    "sg:city":"Seattle",
    "sg:classifiers":[
        {
            "category":"Retail",
            "subcategory":"Repair Shop",
            "type":"Services"
        }
    ],
    "sg:phone":"+1 206 297 6223",
    "sg:postcode":"98107",
    "sg:province":"WA",
    "wof:name":"Northwest Marine Fiberglass",
    "wof:placetype":"venue"
},
  "geometry": {"coordinates":[-122.37085,47.660804],"type":"Point"}
}