{
  "type": "Feature",
  "properties": {
    "iso:country":"US",
    "sg:address":"6059 Northwest Rd",
    "sg:city":"Ferndale",
    "sg:classifiers":[
        {
            "category":"Retail",
            "subcategory":"Repair Shop",
            "type":"Services"
        }
    ],
    "sg:phone":"+1 360 384 8877",
    "sg:postcode":"98248",
    "sg:province":"WA",
    "wof:name":"Shines For You Cleaning",
    "wof:placetype":"venue"
},
  "geometry": {"coordinates":[-122.540994,48.86139],"type":"Point"}
}