{
  "type": "Feature",
  "properties": {
    "addr:full":"701 5th Ave Ste 6710 Seattle WA 98104",
    "addr:housenumber":"701",
    "addr:postcode":"98104",
    "addr:street":"5Th Ave Ste 6710",
    "iso:country":"US",
    "sg:address":"701 5th Ave Ste 6710",
    "sg:city":"Seattle",
    "sg:classifiers":[
        {
            "category":"Banks & Credit Unions",
            "subcategory":"Investment Brokerage",
            "type":"Services"
        },
        {
            "category":"Banks & Credit Unions",
            "subcategory":"Bank",
            "type":"Services"
        },
        {
            "category":"Banks & Credit Unions",
            "subcategory":"Financial Services",
            "type":"Services"
        }
    ],
    "sg:phone":"+1 206 389 8000",
    "sg:postcode":"98104",
    "sg:province":"WA",
    "sg:tags":[
        "advisory",
        "management",
        "transfer",
        "broker",
        "agent",
        "bond",
        "stock"
    ],
    "sg:website":"http://www.seacapinvests.com",
    "wof:name":"C Cap Investment Advisors",
    "wof:placetype":"venue"
},
  "geometry": {"coordinates":[-122.329826,47.604431],"type":"Point"}
}