{
  "type": "Feature",
  "properties": {
    "addr:full":"10035 16th Ave SW Seattle WA 98146",
    "addr:housenumber":"10035",
    "addr:postcode":"98146",
    "addr:street":"16Th Ave Sw",
    "iso:country":"US",
    "sg:address":"10035 16th Ave SW",
    "sg:city":"Seattle",
    "sg:classifiers":[
        {
            "category":"Arts & Performance",
            "subcategory":"Theater",
            "type":"Entertainment"
        }
    ],
    "sg:phone":"+1 206 763 0395",
    "sg:postcode":"98146",
    "sg:province":"WA",
    "sg:tags":[
        "bureau"
    ],
    "wof:name":"Community Entertainment Ctr",
    "wof:placetype":"venue"
},
  "geometry": {"coordinates":[-122.355187,47.51218],"type":"Point"}
}