{
  "type": "Feature",
  "properties": {
    "addr:full":"5421 196th St SW Lynnwood WA 98036",
    "addr:housenumber":"5421",
    "addr:postcode":"98036",
    "addr:street":"196Th St Sw",
    "iso:country":"US",
    "sg:address":"5421 196th St SW",
    "sg:city":"Lynnwood",
    "sg:classifiers":[
        {
            "category":"Building & Trades",
            "subcategory":"Cleaning & Sanitation",
            "type":"Services"
        }
    ],
    "sg:phone":"+1 425 771 6889",
    "sg:postcode":"98036",
    "sg:province":"WA",
    "sg:tags":[
        "house"
    ],
    "wof:name":"Western Construction Svc",
    "wof:placetype":"venue"
},
  "geometry": {"coordinates":[-122.30768399999999,47.82149],"type":"Point"}
}