{
  "type": "Feature",
  "properties": {
    "addr:full":"400 S 43rd St Renton WA 98055",
    "addr:housenumber":"400",
    "addr:postcode":"98055",
    "addr:street":"S 43Rd St",
    "iso:country":"US",
    "sg:address":"400 S 43rd St",
    "sg:city":"Renton",
    "sg:classifiers":[
        {
            "category":"Health Services",
            "subcategory":"Hospital",
            "type":"Services"
        }
    ],
    "sg:phone":"+1 425 228 3450",
    "sg:postcode":"98055",
    "sg:province":"WA",
    "sg:website":"http://www.valleymed.org",
    "wof:name":"Valley Medical Center",
    "wof:placetype":"venue"
},
  "geometry": {"coordinates":[-122.214401,47.441132],"type":"Point"}
}