{
  "type": "Feature",
  "properties": {
    "addr:full":"8107 Central Valley Rd NW Bremerton WA 98311",
    "addr:housenumber":"8107",
    "addr:postcode":"98311",
    "addr:street":"Central Valley Rd Nw",
    "iso:country":"US",
    "sg:address":"8107 Central Valley Rd NW",
    "sg:city":"Bremerton",
    "sg:classifiers":[
        {
            "category":"Education",
            "subcategory":"School",
            "type":"Public Place"
        }
    ],
    "sg:phone":"+1 360 662 2600",
    "sg:postcode":"98311",
    "sg:province":"WA",
    "wof:name":"Fairview Junior High School",
    "wof:placetype":"venue"
},
  "geometry": {"coordinates":[-122.650375,47.636335],"type":"Point"}
}