{
  "type": "Feature",
  "properties": {
    "addr:full":"1540 E J St Tacoma WA 98421",
    "addr:housenumber":"1540",
    "addr:postcode":"98421",
    "addr:street":"E J St",
    "iso:country":"US",
    "sg:address":"1540 E J St",
    "sg:city":"Tacoma",
    "sg:classifiers":[
        {
            "category":"Manufacturing",
            "subcategory":"Tools & Machinery",
            "type":"Manufacturing & Wholesale Goods"
        }
    ],
    "sg:phone":"+1 253 572 7636",
    "sg:postcode":"98421",
    "sg:province":"WA",
    "wof:name":"HEMCO",
    "wof:placetype":"venue"
},
  "geometry": {"coordinates":[-122.42267200000001,47.249478],"type":"Point"}
}