{
  "type": "Feature",
  "properties": {
    "addr:full":"1433 8th St NE Auburn WA 98002",
    "addr:housenumber":"1433",
    "addr:postcode":"98002",
    "addr:street":"8Th St Ne",
    "iso:country":"US",
    "sg:address":"1433 8th St NE",
    "sg:city":"Auburn",
    "sg:classifiers":[
        {
            "category":"Real Estate",
            "subcategory":"Real Estate Operator",
            "type":"Services"
        }
    ],
    "sg:phone":"+1 253 939 4846",
    "sg:postcode":"98002",
    "sg:province":"WA",
    "sg:tags":[
        "building",
        "apartment"
    ],
    "wof:name":"Brittany Lane Apartments",
    "wof:placetype":"venue"
},
  "geometry": {"coordinates":[-122.210024,47.315461],"type":"Point"}
}