{
  "type": "Feature",
  "properties": {
    "addr:full":"4703 116th St E Tacoma WA 98446",
    "addr:housenumber":"4703",
    "addr:postcode":"98446",
    "addr:street":"116Th St",
    "iso:country":"US",
    "sg:address":"4703 116th St E",
    "sg:city":"Tacoma",
    "sg:classifiers":[
        {
            "category":"Professional",
            "subcategory":"Engineering",
            "type":"Services"
        },
        {
            "category":"Home & Garden",
            "subcategory":"Building Materials",
            "type":"Retail Goods"
        },
        {
            "category":"Building & Trades",
            "subcategory":"Construction",
            "type":"Services"
        }
    ],
    "sg:phone":"+1 253 537 0655",
    "sg:postcode":"98446",
    "sg:province":"WA",
    "sg:tags":[
        "repair",
        "system",
        "specialty",
        "heating",
        "equipment",
        "contractor",
        "air conditioning"
    ],
    "sg:website":"http://find.trane.com/tcs-dealer-410760?utm_source=YP&utm_medium=banner&utm_campaign=TL",
    "wof:name":"Kliemann Brothers Heating",
    "wof:placetype":"venue"
},
  "geometry": {"coordinates":[-122.366209,47.150935],"type":"Point"}
}