{
  "type": "Feature",
  "properties": {
    "addr:full":"6022 Chennault Beach Dr Mukilteo WA 98275",
    "addr:housenumber":"6022",
    "addr:postcode":"98275",
    "addr:street":"Chennault Beach Dr",
    "iso:country":"US",
    "sg:address":"6022 Chennault Beach Dr",
    "sg:city":"Mukilteo",
    "sg:classifiers":[
        {
            "category":"Real Estate",
            "subcategory":"Real Estate Agent",
            "type":"Services"
        }
    ],
    "sg:phone":"+1 425 347 5499",
    "sg:postcode":"98275",
    "sg:province":"WA",
    "sg:website":"www.huntingtonappraisal.com",
    "wof:name":"Huntington Appraisal",
    "wof:placetype":"venue"
},
  "geometry": {"coordinates":[-122.31638100000001,47.901329],"type":"Point"}
}