{
  "type": "Feature",
  "properties": {
    "addr:full":"3007 E 57th Ave Spokane WA 99223",
    "addr:housenumber":"3007",
    "addr:postcode":"99223",
    "addr:street":"E 57Th Ave",
    "iso:country":"US",
    "sg:address":"3007 E 57th Ave",
    "sg:city":"Spokane",
    "sg:classifiers":[
        {
            "category":"Coffee & Tea",
            "type":"Food & Drink"
        }
    ],
    "sg:menulink":"http://www.allmenus.com/wa/spokane/117759-starbucks-coffee/menu/",
    "sg:phone":"+1 509 443 9270",
    "sg:postcode":"99223",
    "sg:province":"WA",
    "sg:tags":[
        "american"
    ],
    "wof:name":"Starbucks Coffee",
    "wof:placetype":"venue"
},
  "geometry": {"coordinates":[-117.365137,47.60218],"type":"Point"}
}