{
  "type": "Feature",
  "properties": {
    "addr:full":"1802 23rd Ave Seattle WA 98122",
    "addr:housenumber":"1802",
    "addr:postcode":"98122",
    "addr:street":"23Rd Ave",
    "iso:country":"US",
    "sg:address":"1802 23rd Ave",
    "sg:city":"Seattle",
    "sg:classifiers":[
        {
            "category":"Arts & Performance",
            "subcategory":"Theater",
            "type":"Entertainment"
        }
    ],
    "sg:phone":"+1 206 271 1669",
    "sg:postcode":"98122",
    "sg:province":"WA",
    "sg:tags":[
        "group"
    ],
    "wof:name":"Mks Sound",
    "wof:placetype":"venue"
},
  "geometry": {"coordinates":[-122.302492,47.618161],"type":"Point"}
}