{
  "type": "Feature",
  "properties": {
    "addr:full":"10 McLo Ln Sequim WA 98382",
    "addr:housenumber":"10",
    "addr:postcode":"98382",
    "addr:street":"Mclo Ln",
    "iso:country":"US",
    "sg:address":"10 McLo Ln",
    "sg:city":"Sequim",
    "sg:classifiers":[
        {
            "category":"Autos & Motor Vehicles",
            "subcategory":"Recreational Vehicle Sales",
            "type":"Retail Goods"
        },
        {
            "category":"Retail",
            "subcategory":"Auto Repair",
            "type":"Services"
        }
    ],
    "sg:phone":"+1 360 582 9934",
    "sg:postcode":"98382",
    "sg:province":"WA",
    "wof:name":"Anywhere R V Repair",
    "wof:placetype":"venue"
},
  "geometry": {"coordinates":[-123.180733,48.085353],"type":"Point"}
}