{
  "type": "Feature",
  "properties": {
    "addr:full":"PO Box 33990 Seattle WA 98133",
    "addr:housenumber":"po box",
    "addr:postcode":"33990;98133",
    "iso:country":"US",
    "sg:address":"PO Box 33990",
    "sg:city":"Seattle",
    "sg:classifiers":[
        {
            "category":"Professional",
            "subcategory":"Lawyer & Legal Services",
            "type":"Services"
        }
    ],
    "sg:phone":"+1 206 622 1107",
    "sg:postcode":"98133",
    "sg:province":"WA",
    "wof:name":"Albo Joseph Atty",
    "wof:placetype":"venue"
},
  "geometry": {"coordinates":[-122.33917599999999,47.734119],"type":"Point"}
}