{
  "type": "Feature",
  "properties": {
    "addr:full":"120 E Birch St Walla Walla WA 99362",
    "addr:housenumber":"120",
    "addr:postcode":"99362",
    "addr:street":"E Birch St",
    "iso:country":"US",
    "sg:address":"120 E Birch St",
    "sg:city":"Walla Walla",
    "sg:classifiers":[
        {
            "category":"Social Services",
            "subcategory":"Adult Care",
            "type":"Services"
        },
        {
            "category":"Social Services",
            "type":"Services"
        }
    ],
    "sg:phone":"+1 509 522 0400",
    "sg:postcode":"99362",
    "sg:province":"WA",
    "sg:tags":[
        "residential",
        "jo",
        "organization",
        "welfare"
    ],
    "sg:website":"www.valleyresidential.org",
    "wof:name":"Valley Residential Services",
    "wof:placetype":"venue"
},
  "geometry": {"coordinates":[-118.33488800000001,46.064975],"type":"Point"}
}