{
  "type": "Feature",
  "properties": {
    "addr:full":"600 S 96th St Seattle WA 98108",
    "addr:housenumber":"600",
    "addr:postcode":"98108",
    "addr:street":"S 96Th St",
    "iso:country":"US",
    "sg:address":"600 S 96th St",
    "sg:city":"Seattle",
    "sg:classifiers":[
        {
            "category":"Transit Center",
            "subcategory":"Freight",
            "type":"Transportation"
        }
    ],
    "sg:phone":"+1 206 764 5120",
    "sg:postcode":"98108",
    "sg:province":"WA",
    "sg:tags":[
        "container"
    ],
    "wof:name":"Old Dominion Freight Line",
    "wof:placetype":"venue"
},
  "geometry": {"coordinates":[-122.32577499999999,47.51721],"type":"Point"}
}