{
  "type": "Feature",
  "properties": {
    "addr:full":"12473 NE North Shore Rd Belfair WA 98528",
    "addr:housenumber":"12473",
    "addr:postcode":"98528",
    "addr:street":"Ne North Shore Rd",
    "iso:country":"US",
    "sg:address":"12473 NE North Shore Rd",
    "sg:city":"Belfair",
    "sg:classifiers":[
        {
            "category":"Building & Trades",
            "subcategory":"Construction",
            "type":"Services"
        }
    ],
    "sg:phone":"+1 360 801 6354",
    "sg:postcode":"98528",
    "sg:province":"WA",
    "sg:tags":[
        "wallcoverings-installation",
        "wallpaper",
        "painting",
        "contractor"
    ],
    "wof:name":"Skyblu Painting",
    "wof:placetype":"venue"
},
  "geometry": {"coordinates":[-123.030439,47.360234],"type":"Point"}
}