{
  "type": "Feature",
  "properties": {
    "addr:full":"8987 Graham St NE Moses Lake WA 98837",
    "addr:housenumber":"8987",
    "addr:postcode":"98837",
    "addr:street":"Graham St Ne",
    "iso:country":"US",
    "sg:address":"8987 Graham St NE",
    "sg:city":"Moses Lake",
    "sg:classifiers":[
        {
            "category":"Manufacturing",
            "subcategory":"Tools & Machinery",
            "type":"Manufacturing & Wholesale Goods"
        }
    ],
    "sg:phone":"+1 509 762 2096",
    "sg:postcode":"98837",
    "sg:province":"WA",
    "sg:tags":[
        "industry",
        "aerospace"
    ],
    "wof:name":"Boeing Co",
    "wof:placetype":"venue"
},
  "geometry": {"coordinates":[-119.30109,47.191262],"type":"Point"}
}