{
  "type": "Feature",
  "properties": {
    "addr:full":"1107 S 56th St Tacoma WA 98408",
    "addr:housenumber":"1107",
    "addr:postcode":"98408",
    "addr:street":"S 56Th St",
    "iso:country":"US",
    "sg:address":"1107 S 56th St",
    "sg:city":"Tacoma",
    "sg:classifiers":[
        {
            "category":"Wholesale",
            "subcategory":"Durable Goods & Equipment",
            "type":"Manufacturing & Wholesale Goods"
        }
    ],
    "sg:phone":"+1 253 473 2650",
    "sg:postcode":"98408",
    "sg:province":"WA",
    "wof:name":"Wood Bee Stuff",
    "wof:placetype":"venue"
},
  "geometry": {"coordinates":[-122.449697,47.206511],"type":"Point"}
}