{
  "type": "Feature",
  "properties": {
    "addr:full":"3034 Marine Dr Bremerton WA 98312",
    "addr:housenumber":"3034",
    "addr:postcode":"98312",
    "addr:street":"Marine Dr",
    "iso:country":"US",
    "sg:address":"3034 Marine Dr",
    "sg:city":"Bremerton",
    "sg:classifiers":[
        {
            "category":"Shopping",
            "subcategory":"Gifts & Souvenirs",
            "type":"Retail Goods"
        }
    ],
    "sg:phone":"+1 360 698 8120",
    "sg:postcode":"98312",
    "sg:province":"WA",
    "wof:name":"Lasting Impressions",
    "wof:placetype":"venue"
},
  "geometry": {"coordinates":[-122.676089,47.593567],"type":"Point"}
}