{
  "type": "Feature",
  "properties": {
    "addr:full":"15109 NE 369th St La Center WA 98629",
    "addr:housenumber":"15109",
    "addr:postcode":"98629",
    "addr:street":"Ne 369Th St",
    "iso:country":"US",
    "sg:address":"15109 NE 369th St",
    "sg:city":"La Center",
    "sg:classifiers":[
        {
            "category":"Organizations",
            "subcategory":"Membership Organization",
            "type":"Services"
        },
        {
            "category":"Professional",
            "type":"Services"
        }
    ],
    "sg:phone":"+1 360 263 6447",
    "sg:postcode":"98629",
    "sg:province":"WA",
    "sg:tags":[
        "athletic"
    ],
    "wof:name":"Equine Athletic Center",
    "wof:placetype":"venue"
},
  "geometry": {"coordinates":[-122.516435,45.888188],"type":"Point"}
}