{
  "type": "Feature",
  "properties": {
    "addr:full":"214 W Lee St Seattle WA 98119",
    "addr:housenumber":"214",
    "addr:postcode":"98119",
    "addr:street":"W Lee St",
    "iso:country":"US",
    "sg:address":"214 W Lee St",
    "sg:city":"Seattle",
    "sg:classifiers":[
        {
            "category":"Professional",
            "subcategory":"Computer Services",
            "type":"Services"
        }
    ],
    "sg:phone":"+1 206 282 1384",
    "sg:postcode":"98119",
    "sg:province":"WA",
    "sg:tags":[
        "datum"
    ],
    "wof:name":"Wonderhorsecom",
    "wof:placetype":"venue"
},
  "geometry": {"coordinates":[-122.36038499999999,47.631396],"type":"Point"}
}