{
  "type": "Feature",
  "properties": {
    "addr:full":"18046 Dunbar Rd Mount Vernon WA 98273",
    "addr:housenumber":"18046",
    "addr:postcode":"98273",
    "addr:street":"Dunbar Rd",
    "iso:country":"US",
    "sg:address":"18046 Dunbar Rd",
    "sg:city":"Mount Vernon",
    "sg:classifiers":[
        {
            "category":"Building & Trades",
            "subcategory":"Construction",
            "type":"Services"
        }
    ],
    "sg:phone":"+1 360 416 0469",
    "sg:postcode":"98273",
    "sg:province":"WA",
    "sg:tags":[
        "residential"
    ],
    "wof:name":"Washington Alaska LLC",
    "wof:placetype":"venue"
},
  "geometry": {"coordinates":[-122.357044,48.428868],"type":"Point"}
}