{
  "type": "Feature",
  "properties": {
    "addr:full":"1503 E St Bellingham WA 98225",
    "addr:housenumber":"1503",
    "addr:postcode":"98225",
    "addr:street":"E St",
    "iso:country":"US",
    "sg:address":"1503 E St",
    "sg:city":"Bellingham",
    "sg:classifiers":[
        {
            "category":"Professional",
            "subcategory":"Lawyer & Legal Services",
            "type":"Services"
        }
    ],
    "sg:phone":"+1 360 647 5278",
    "sg:postcode":"98225",
    "sg:province":"WA",
    "wof:name":"Thomas H Flattery",
    "wof:placetype":"venue"
},
  "geometry": {"coordinates":[-122.484583,48.756274],"type":"Point"}
}