{
  "type": "Feature",
  "properties": {
    "iso:country":"US",
    "sg:address":"1701 Lincoln Ave",
    "sg:city":"Vancouver",
    "sg:classifiers":[
        {
            "category":"Building & Trades",
            "subcategory":"Construction",
            "type":"Services"
        }
    ],
    "sg:phone":"+1 360 254 2900",
    "sg:postcode":"98660",
    "sg:province":"WA",
    "sg:tags":[
        "repairing",
        "remodeling",
        "contractor"
    ],
    "wof:name":"Sequoia Construction Co",
    "wof:placetype":"venue"
},
  "geometry": {"coordinates":[-122.683306,45.634758],"type":"Point"}
}