{
  "type": "Feature",
  "properties": {
    "addr:full":"19307 E Cataldo Ave Spokane Valley WA 99016",
    "addr:housenumber":"19307",
    "addr:postcode":"99016",
    "addr:street":"E Cataldo Ave",
    "iso:country":"US",
    "sg:address":"19307 E Cataldo Ave",
    "sg:city":"Spokane Valley",
    "sg:classifiers":[
        {
            "category":"Education",
            "subcategory":"School",
            "type":"Public Place"
        }
    ],
    "sg:phone":"+1 509 922 6733",
    "sg:postcode":"99016",
    "sg:province":"WA",
    "wof:name":"Special Education Co-Op Prgrm",
    "wof:placetype":"venue"
},
  "geometry": {"coordinates":[-117.145078,47.666013],"type":"Point"}
}