{
  "type": "Feature",
  "properties": {
    "addr:full":"18250 68th Ave S Kent WA 98032",
    "addr:housenumber":"18250",
    "addr:postcode":"98032",
    "addr:street":"68Th Ave S",
    "iso:country":"US",
    "sg:address":"18250 68th Ave S",
    "sg:city":"Kent",
    "sg:classifiers":[
        {
            "category":"Wholesale",
            "subcategory":"Sporting Goods",
            "type":"Manufacturing & Wholesale Goods"
        }
    ],
    "sg:phone":"+1 253 872 7256",
    "sg:postcode":"98032",
    "sg:province":"WA",
    "sg:tags":[
        "equipment",
        "pool",
        "swimming"
    ],
    "wof:name":"Coates Heater Co",
    "wof:placetype":"venue"
},
  "geometry": {"coordinates":[-122.246032,47.438467],"type":"Point"}
}