{
  "type": "Feature",
  "properties": {
    "addr:full":"19303 88th Ave W Edmonds WA 98026",
    "addr:housenumber":"19303",
    "addr:postcode":"98026",
    "addr:street":"88Th Ave W",
    "iso:country":"US",
    "sg:address":"19303 88th Ave W",
    "sg:city":"Edmonds",
    "sg:classifiers":[
        {
            "category":"Shopping",
            "subcategory":"Gifts & Souvenirs",
            "type":"Retail Goods"
        }
    ],
    "sg:phone":"+1 425 673 6471",
    "sg:postcode":"98026",
    "sg:province":"WA",
    "wof:name":"Roosters Housecom",
    "wof:placetype":"venue"
},
  "geometry": {"coordinates":[-122.352171,47.823809],"type":"Point"}
}