{
  "type": "Feature",
  "properties": {
    "addr:full":"921 S 2nd Ave Walla Walla WA 99362",
    "addr:housenumber":"921",
    "addr:postcode":"99362",
    "addr:street":"S 2Nd Ave",
    "iso:country":"US",
    "sg:address":"921 S 2nd Ave",
    "sg:city":"Walla Walla",
    "sg:classifiers":[
        {
            "category":"Personal",
            "subcategory":"Beauty Salon",
            "type":"Services"
        }
    ],
    "sg:phone":"+1 509 529 0903",
    "sg:postcode":"99362",
    "sg:province":"WA",
    "sg:tags":[
        "shop"
    ],
    "wof:name":"Special F X",
    "wof:placetype":"venue"
},
  "geometry": {"coordinates":[-118.33246699999999,46.055582],"type":"Point"}
}