{
  "type": "Feature",
  "properties": {
    "addr:full":"804 N State St Tacoma WA 98403",
    "addr:housenumber":"804",
    "addr:postcode":"98403",
    "addr:street":"N State St",
    "iso:country":"US",
    "sg:address":"804 N State St",
    "sg:city":"Tacoma",
    "sg:classifiers":[
        {
            "category":"Organizations",
            "subcategory":"Religious Organization",
            "type":"Services"
        }
    ],
    "sg:phone":"+1 253 627 5090",
    "sg:postcode":"98403",
    "sg:province":"WA",
    "sg:tags":[
        "place",
        "worship",
        "church"
    ],
    "sg:website":"http://www.watchtower.org",
    "wof:name":"Jehovah's Witnesses",
    "wof:placetype":"venue"
},
  "geometry": {"coordinates":[-122.466044,47.258004],"type":"Point"}
}