{
  "type": "Feature",
  "properties": {
    "addr:full":"3301 N Argonne Rd Spokane WA 99212",
    "addr:housenumber":"3301",
    "addr:postcode":"99212",
    "addr:street":"N Argonne Rd",
    "iso:country":"US",
    "sg:address":"3301 N Argonne Rd",
    "sg:city":"Spokane",
    "sg:classifiers":[
        {
            "category":"Shopping",
            "subcategory":"Books",
            "type":"Retail Goods"
        }
    ],
    "sg:phone":"+1 509 921 9253",
    "sg:postcode":"99212",
    "sg:province":"WA",
    "sg:tags":[
        "eating"
    ],
    "wof:name":"Corner Door Fountain & Books",
    "wof:placetype":"venue"
},
  "geometry": {"coordinates":[-117.28268199999999,47.68776],"type":"Point"}
}