{
  "type": "Feature",
  "properties": {
    "addr:full":"604 Oakesdale Ave SW 101 Renton WA 98057",
    "addr:housenumber":"604;101",
    "addr:postcode":"98057",
    "addr:street":"Oakesdale Ave Sw",
    "iso:country":"US",
    "sg:address":"604 Oakesdale Ave SW 101",
    "sg:city":"Renton",
    "sg:classifiers":[
        {
            "category":"Communications",
            "subcategory":"Radio Station",
            "type":"Services"
        },
        {
            "category":"Professional",
            "subcategory":"Business Services",
            "type":"Services"
        }
    ],
    "sg:phone":"+1 425 272 1500",
    "sg:postcode":"98057",
    "sg:province":"WA",
    "sg:tags":[
        "medium",
        "publicity",
        "broker"
    ],
    "wof:name":"Millennium Digital Media Systems",
    "wof:placetype":"venue"
},
  "geometry": {"coordinates":[-122.242256,47.473959],"type":"Point"}
}