{
  "type": "Feature",
  "properties": {
    "addr:full":"23613 112th Ave SE Kent WA 98031",
    "addr:housenumber":"23613",
    "addr:postcode":"98031",
    "addr:street":"112Th Ave Se",
    "iso:country":"US",
    "sg:address":"23613 112th Ave SE",
    "sg:city":"Kent",
    "sg:classifiers":[
        {
            "category":"Health Services",
            "subcategory":"Clinic",
            "type":"Services"
        }
    ],
    "sg:phone":"+1 253 854 4089",
    "sg:postcode":"98031",
    "sg:province":"WA",
    "sg:tags":[
        "specialty",
        "outpatient"
    ],
    "wof:name":"Kiley Eva Marie D",
    "wof:placetype":"venue"
},
  "geometry": {"coordinates":[-122.19202,47.389978],"type":"Point"}
}