{
  "type": "Feature",
  "properties": {
    "addr:full":"16715 NE 79th St Redmond WA 98052",
    "addr:housenumber":"16715",
    "addr:postcode":"98052",
    "addr:street":"Ne 79Th St",
    "iso:country":"US",
    "sg:address":"16715 NE 79th St",
    "sg:city":"Redmond",
    "sg:classifiers":[
        {
            "category":"Organizations",
            "subcategory":"Membership Organization",
            "type":"Services"
        }
    ],
    "sg:phone":"+1 425 881 2264",
    "sg:postcode":"98052",
    "sg:province":"WA",
    "wof:name":"Unitus Inc",
    "wof:placetype":"venue"
},
  "geometry": {"coordinates":[-122.11784,47.673793],"type":"Point"}
}