{
  "type": "Feature",
  "properties": {
    "iso:country":"US",
    "sg:address":"9811 St Helens Ave",
    "sg:city":"Vancouver",
    "sg:classifiers":[
        {
            "category":"Building & Trades",
            "subcategory":"Construction",
            "type":"Services"
        }
    ],
    "sg:phone":"+1 360 892 5437",
    "sg:postcode":"98664",
    "sg:province":"WA",
    "sg:tags":[
        "device",
        "house",
        "opera",
        "amusement"
    ],
    "wof:name":"Pierce & Pierce Construction",
    "wof:placetype":"venue"
},
  "geometry": {"coordinates":[-122.57131,45.615976],"type":"Point"}
}