{
  "type": "Feature",
  "properties": {
    "addr:full":"312 N 104th St Seattle WA 98133",
    "addr:housenumber":"312",
    "addr:postcode":"98133",
    "addr:street":"N 104Th St",
    "iso:country":"US",
    "sg:address":"312 N 104th St",
    "sg:city":"Seattle",
    "sg:classifiers":[
        {
            "category":"Wholesale",
            "subcategory":"Electrical",
            "type":"Manufacturing & Wholesale Goods"
        },
        {
            "category":"Manufacturing",
            "subcategory":"Tools & Machinery",
            "type":"Manufacturing & Wholesale Goods"
        }
    ],
    "sg:phone":"+1 206 789 7525",
    "sg:postcode":"98133",
    "sg:province":"WA",
    "sg:tags":[
        "connector",
        "electronic",
        "component"
    ],
    "sg:website":"www.connectorworldsupply.com",
    "wof:name":"Connector World Supply Inc",
    "wof:placetype":"venue"
},
  "geometry": {"coordinates":[-122.35286600000001,47.704424],"type":"Point"}
}