{
  "type": "Feature",
  "properties": {
    "addr:full":"3225 44th Ave SW Seattle WA 98116",
    "addr:housenumber":"3225",
    "addr:postcode":"98116",
    "addr:street":"44Th Ave Sw",
    "iso:country":"US",
    "sg:address":"3225 44th Ave SW",
    "sg:city":"Seattle",
    "sg:classifiers":[
        {
            "category":"Building & Trades",
            "subcategory":"Construction",
            "type":"Services"
        }
    ],
    "sg:phone":"+1 206 937 1810",
    "sg:postcode":"98116",
    "sg:province":"WA",
    "sg:tags":[
        "house"
    ],
    "wof:name":"Duke Construction",
    "wof:placetype":"venue"
},
  "geometry": {"coordinates":[-122.388136,47.574051],"type":"Point"}
}