{
  "type": "Feature",
  "properties": {
    "addr:full":"560 Industry Dr Bldg 4 Tukwila WA 98188",
    "addr:housenumber":"560",
    "addr:postcode":"98188",
    "addr:street":"Industry Dr Bldg 4",
    "iso:country":"US",
    "sg:address":"560 Industry Dr Bldg 4",
    "sg:city":"Tukwila",
    "sg:classifiers":[
        {
            "category":"Banks & Credit Unions",
            "subcategory":"Financial Services",
            "type":"Services"
        },
        {
            "category":"Professional",
            "subcategory":"Credit Reporting & Collection",
            "type":"Services"
        }
    ],
    "sg:phone":"+1 206 575 3222",
    "sg:postcode":"98188",
    "sg:province":"WA",
    "sg:tags":[
        "agency",
        "adjuster",
        "debt"
    ],
    "sg:website":"http://www.corprecoveries.com",
    "wof:name":"Recoveries Inc Corporate",
    "wof:placetype":"venue"
},
  "geometry": {"coordinates":[-122.247519,47.453147],"type":"Point"}
}