{
  "type": "Feature",
  "properties": {
    "addr:full":"1902 120th Pl SE Everett WA 98208",
    "addr:housenumber":"1902",
    "addr:postcode":"98208",
    "addr:street":"120Th Pl Se",
    "iso:country":"US",
    "sg:address":"1902 120th Pl SE",
    "sg:city":"Everett",
    "sg:classifiers":[
        {
            "category":"Professional",
            "subcategory":"Lawyer & Legal Services",
            "type":"Services"
        }
    ],
    "sg:phone":"+1 425 379 7213",
    "sg:postcode":"98208",
    "sg:province":"WA",
    "wof:name":"E Todd Stephan",
    "wof:placetype":"venue"
},
  "geometry": {"coordinates":[-122.201443,47.888575],"type":"Point"}
}