{
  "type": "Feature",
  "properties": {
    "addr:full":"6457 NE 154th St Kenmore WA 98028",
    "addr:housenumber":"6457",
    "addr:postcode":"98028",
    "addr:street":"Ne 154Th St",
    "iso:country":"US",
    "sg:address":"6457 NE 154th St",
    "sg:city":"Kenmore",
    "sg:classifiers":[
        {
            "category":"Shopping",
            "subcategory":"Used Merchandise",
            "type":"Retail Goods"
        }
    ],
    "sg:phone":"+1 425 488 7046",
    "sg:postcode":"98028",
    "sg:province":"WA",
    "wof:name":"Lady Esther Antiques & Co",
    "wof:placetype":"venue"
},
  "geometry": {"coordinates":[-122.254785,47.740052],"type":"Point"}
}