{
  "type": "Feature",
  "properties": {
    "addr:full":"725 W Main Brewster WA 98812",
    "addr:housenumber":"725",
    "addr:postcode":"98812",
    "addr:street":"W Main Brewster",
    "iso:country":"US",
    "sg:address":"725 W Main",
    "sg:city":"Brewster",
    "sg:classifiers":[
        {
            "category":"Building & Trades",
            "subcategory":"Electrical",
            "type":"Services"
        }
    ],
    "sg:phone":"+1 509 689 9277",
    "sg:postcode":"98812",
    "sg:province":"WA",
    "sg:tags":[
        "electric",
        "contractor"
    ],
    "wof:name":"Erickson Electric",
    "wof:placetype":"venue"
},
  "geometry": {"coordinates":[-119.78531700000001,48.099188],"type":"Point"}
}