{
  "type": "Feature",
  "properties": {
    "addr:full":"1543 NW 62nd St Seattle WA 98107",
    "addr:housenumber":"1543",
    "addr:postcode":"98107",
    "addr:street":"Nw 62Nd St",
    "iso:country":"US",
    "sg:address":"1543 NW 62nd St",
    "sg:city":"Seattle",
    "sg:classifiers":[
        {
            "category":"Professional",
            "subcategory":"Management & Consulting",
            "type":"Services"
        }
    ],
    "sg:phone":"+1 206 782 8392",
    "sg:postcode":"98107",
    "sg:province":"WA",
    "sg:tags":[
        "business"
    ],
    "wof:name":"Davidya Kasperzyk",
    "wof:placetype":"venue"
},
  "geometry": {"coordinates":[-122.378502,47.673744],"type":"Point"}
}