{
  "type": "Feature",
  "properties": {
    "addr:full":"6405 Chapel Hill Blvd Apt. #N101 Pasco WA 99301",
    "addr:housenumber":"6405",
    "addr:postcode":"99301",
    "addr:street":"Chapel Hill Blvd Apt. # N101",
    "iso:country":"US",
    "sg:address":"6405 Chapel Hill Blvd Apt. #N101",
    "sg:city":"Pasco",
    "sg:classifiers":[
        {
            "category":"Building & Trades",
            "subcategory":"Landscaping Services",
            "type":"Services"
        },
        {
            "category":"Wholesale",
            "subcategory":"Construction Materials",
            "type":"Manufacturing & Wholesale Goods"
        }
    ],
    "sg:phone":"+1 509 551 1814",
    "sg:postcode":"99301",
    "sg:province":"WA",
    "sg:tags":[
        "control",
        "lawn",
        "tree",
        "contractor",
        "weed",
        "erosion",
        "landscape"
    ],
    "sg:website":"http://www.Myspace.com/Carrillo_LawnCare",
    "wof:name":"Carrillo Lawn Care",
    "wof:placetype":"venue"
},
  "geometry": {"coordinates":[-119.172911,46.261131],"type":"Point"}
}