{
  "type": "Feature",
  "properties": {
    "addr:full":"10545 41st Pl NE Seattle WA 98125",
    "addr:housenumber":"10545",
    "addr:postcode":"98125",
    "addr:street":"41St Pl Ne",
    "iso:country":"US",
    "sg:address":"10545 41st Pl NE",
    "sg:city":"Seattle",
    "sg:classifiers":[
        {
            "category":"Professional",
            "subcategory":"Business Services",
            "type":"Services"
        }
    ],
    "sg:phone":"+1 206 367 2888",
    "sg:postcode":"98125",
    "sg:province":"WA",
    "sg:tags":[
        "translating",
        "interpreting"
    ],
    "wof:name":"Lincom International Corp",
    "wof:placetype":"venue"
},
  "geometry": {"coordinates":[-122.283517,47.705187],"type":"Point"}
}