{
  "type": "Feature",
  "properties": {
    "iso:country":"US",
    "sg:address":"170 Madera Dr",
    "sg:city":"Sequim",
    "sg:classifiers":[
        {
            "category":"Retail",
            "subcategory":"Portrait Studio",
            "type":"Services"
        }
    ],
    "sg:phone":"+1 360 681 6913",
    "sg:postcode":"98382",
    "sg:province":"WA",
    "sg:tags":[
        "photo",
        "mfg"
    ],
    "wof:name":"Apple Cheeks",
    "wof:placetype":"venue"
},
  "geometry": {"coordinates":[-123.229513,48.092691],"type":"Point"}
}