{
  "type": "Feature",
  "properties": {
    "addr:full":"1178 Central Rd Everson WA 98247",
    "addr:housenumber":"1178",
    "addr:postcode":"98247",
    "addr:street":"Central Rd",
    "iso:country":"US",
    "sg:address":"1178 Central Rd",
    "sg:city":"Everson",
    "sg:classifiers":[
        {
            "category":"Building & Trades",
            "subcategory":"Plumbing",
            "type":"Services"
        }
    ],
    "sg:phone":"+1 360 398 7708",
    "sg:postcode":"98247",
    "sg:province":"WA",
    "sg:tags":[
        "contractor"
    ],
    "wof:name":"Cruleys Plumbing",
    "wof:placetype":"venue"
},
  "geometry": {"coordinates":[-122.427454,48.877251],"type":"Point"}
}