{
  "type": "Feature",
  "properties": {
    "addr:full":"1100 NW 27th Ave Battle Ground WA 98604",
    "addr:housenumber":"1100",
    "addr:postcode":"98604",
    "addr:street":"Nw 27Th Ave",
    "iso:country":"US",
    "sg:address":"1100 NW 27th Ave",
    "sg:city":"Battle Ground",
    "sg:classifiers":[
        {
            "category":"Professional",
            "subcategory":"Computer Services",
            "type":"Services"
        }
    ],
    "sg:phone":"+1 360 687 1248",
    "sg:postcode":"98604",
    "sg:province":"WA",
    "sg:tags":[
        "related"
    ],
    "wof:name":"Bl Computer Consulting & Svcs",
    "wof:placetype":"venue"
},
  "geometry": {"coordinates":[-122.565676,45.789241],"type":"Point"}
}