{
  "type": "Feature",
  "properties": {
    "addr:full":"11304 SE 10th St Vancouver WA 98664",
    "addr:housenumber":"11304",
    "addr:postcode":"98664",
    "addr:street":"Se 10Th St",
    "iso:country":"US",
    "sg:address":"11304 SE 10th St",
    "sg:city":"Vancouver",
    "sg:classifiers":[
        {
            "category":"Professional",
            "subcategory":"Accounting & Tax Preparation",
            "type":"Services"
        }
    ],
    "sg:phone":"+1 360 260 4824",
    "sg:postcode":"98664",
    "sg:province":"WA",
    "wof:name":"Computaxes & Bkping",
    "wof:placetype":"venue"
},
  "geometry": {"coordinates":[-122.55467400000001,45.614548],"type":"Point"}
}