{
  "type": "Feature",
  "properties": {
    "addr:full":"7115 132nd Pl SE Newcastle WA 98059",
    "addr:housenumber":"7115",
    "addr:postcode":"98059",
    "addr:street":"132Nd Pl Se",
    "iso:country":"US",
    "sg:address":"7115 132nd Pl SE",
    "sg:city":"Newcastle",
    "sg:classifiers":[
        {
            "category":"Personal",
            "type":"Services"
        }
    ],
    "sg:phone":"+1 425 235 7200",
    "sg:postcode":"98059",
    "sg:province":"WA",
    "sg:tags":[
        "mover"
    ],
    "wof:name":"Rainier Overseas Movers",
    "wof:placetype":"venue"
},
  "geometry": {"coordinates":[-122.16300200000001,47.538502],"type":"Point"}
}