{
  "type": "Feature",
  "properties": {
    "addr:full":"5619 Countryside Beach Dr NW Olympia WA 98502",
    "addr:housenumber":"5619",
    "addr:postcode":"olympia wa 98502",
    "addr:street":"Countryside Beach Dr Nw",
    "iso:country":"US",
    "sg:address":"5619 Countryside Beach Dr NW",
    "sg:city":"Olympia",
    "sg:classifiers":[
        {
            "category":"Professional",
            "subcategory":"Business Services",
            "type":"Services"
        }
    ],
    "sg:phone":"+1 360 866 2178",
    "sg:postcode":"98502",
    "sg:province":"WA",
    "wof:name":"Lewis Ruth Stubbs",
    "wof:placetype":"venue"
},
  "geometry": {"coordinates":[-122.935923,47.114239],"type":"Point"}
}