{
  "type": "Feature",
  "properties": {
    "addr:full":"500 108th Ave NE Ste 1H3 Bellevue WA 98004",
    "addr:housenumber":"500",
    "addr:postcode":"98004",
    "addr:street":"108Th Ave Ne Ste 1H3",
    "iso:country":"US",
    "sg:address":"500 108th Ave NE Ste 1H3",
    "sg:city":"Bellevue",
    "sg:classifiers":[
        {
            "category":"Banks & Credit Unions",
            "subcategory":"Bank",
            "type":"Services"
        }
    ],
    "sg:phone":"+1 425 688 8328",
    "sg:postcode":"98004",
    "sg:province":"WA",
    "sg:website":"www.chinatrustbankusa.com",
    "wof:name":"Chinatrust Bank USA",
    "wof:placetype":"venue"
},
  "geometry": {"coordinates":[-122.195999,47.6147],"type":"Point"}
}