{
  "type": "Feature",
  "properties": {
    "addr:full":"3720 Gravelly Beach Loop NW Olympia WA 98502",
    "addr:housenumber":"3720",
    "addr:postcode":"olympia wa 98502",
    "addr:street":"Gravelly Beach Loop Nw",
    "iso:country":"US",
    "sg:address":"3720 Gravelly Beach Loop NW",
    "sg:city":"Olympia",
    "sg:classifiers":[
        {
            "category":"Shopping",
            "subcategory":"Computers & Home Electronics",
            "type":"Retail Goods"
        }
    ],
    "sg:phone":"+1 360 867 1798",
    "sg:postcode":"98502",
    "sg:province":"WA",
    "sg:tags":[
        "stereo",
        "high",
        "stereophonic",
        "video",
        "equipment-dealers",
        "fidelity",
        "audio"
    ],
    "sg:website":"http://www.bayviewproaudio.com",
    "wof:name":"Cascade Microphones",
    "wof:placetype":"venue"
},
  "geometry": {"coordinates":[-122.961478,47.10553],"type":"Point"}
}