{
  "type": "Feature",
  "properties": {
    "addr:full":"903 E Main St Ste 105 Auburn WA 98002",
    "addr:housenumber":"903",
    "addr:postcode":"98002",
    "addr:street":"E Main St Ste 105",
    "iso:country":"US",
    "sg:address":"903 E Main St Ste 105",
    "sg:city":"Auburn",
    "sg:classifiers":[
        {
            "category":"Banks & Credit Unions",
            "subcategory":"Investment Brokerage",
            "type":"Services"
        },
        {
            "category":"Insurance",
            "subcategory":"Hazard Insurance",
            "type":"Services"
        }
    ],
    "sg:phone":"+1 253 952 7852",
    "sg:postcode":"98002",
    "sg:province":"WA",
    "sg:tags":[
        "commercial",
        "agent",
        "business",
        "resume"
    ],
    "sg:website":"http://www.farmers.com",
    "wof:name":"Flannigan Agency",
    "wof:placetype":"venue"
},
  "geometry": {"coordinates":[-122.217888,47.307859],"type":"Point"}
}