{
  "type": "Feature",
  "properties": {
    "addr:full":"266 SW 153rd St Burien WA 98166",
    "addr:housenumber":"266",
    "addr:postcode":"98166",
    "addr:street":"Sw 153Rd St",
    "iso:country":"US",
    "sg:address":"266 SW 153rd St",
    "sg:city":"Burien",
    "sg:classifiers":[
        {
            "category":"Autos & Motor Vehicles",
            "subcategory":"Auto Supplies",
            "type":"Retail Goods"
        }
    ],
    "sg:phone":"+1 206 246 4464",
    "sg:postcode":"98166",
    "sg:province":"WA",
    "sg:tags":[
        "automotive",
        "tune",
        "tire"
    ],
    "sg:website":"http://www.bigotires.com",
    "wof:name":"Big O Tires",
    "wof:placetype":"venue"
},
  "geometry": {"coordinates":[-122.33831600000001,47.465949],"type":"Point"}
}