{
  "type": "Feature",
  "properties": {
    "addr:full":"1718 S 84th St Tacoma WA 98444",
    "addr:housenumber":"1718",
    "addr:postcode":"98444",
    "addr:street":"S 84Th St",
    "iso:country":"US",
    "sg:address":"1718 S 84th St",
    "sg:city":"Tacoma",
    "sg:classifiers":[
        {
            "category":"Real Estate",
            "subcategory":"Real Estate Operator",
            "type":"Services"
        }
    ],
    "sg:phone":"+1 253 537 6914",
    "sg:postcode":"98444",
    "sg:province":"WA",
    "sg:tags":[
        "apartment"
    ],
    "wof:name":"Waterfall Apartments",
    "wof:placetype":"venue"
},
  "geometry": {"coordinates":[-122.46288699999999,47.18097],"type":"Point"}
}