{
  "type": "Feature",
  "properties": {
    "addr:full":"234 W Columbia Dr Kennewick WA 99336",
    "addr:housenumber":"234",
    "addr:postcode":"99336",
    "addr:street":"W Columbia Dr",
    "iso:country":"US",
    "sg:address":"234 W Columbia Dr",
    "sg:city":"Kennewick",
    "sg:classifiers":[
        {
            "category":"Shopping",
            "subcategory":"Clothing, Apparel, & Fashions",
            "type":"Retail Goods"
        }
    ],
    "sg:phone":"+1 509 783 4199",
    "sg:postcode":"99336",
    "sg:province":"WA",
    "wof:name":"Swim In",
    "wof:placetype":"venue"
},
  "geometry": {"coordinates":[-119.120786,46.212906],"type":"Point"}
}