{
  "type": "Feature",
  "properties": {
    "addr:full":"10310 E Bridges Rd Elk WA 99009",
    "addr:housenumber":"10310",
    "addr:postcode":"99009",
    "addr:street":"E Bridges Rd",
    "iso:country":"US",
    "sg:address":"10310 E Bridges Rd",
    "sg:city":"Elk",
    "sg:classifiers":[
        {
            "category":"Manufacturing",
            "subcategory":"Lumber",
            "type":"Manufacturing & Wholesale Goods"
        }
    ],
    "sg:phone":"+1 509 292 8656",
    "sg:postcode":"99009",
    "sg:province":"WA",
    "sg:tags":[
        "company",
        "logging"
    ],
    "wof:name":"Mc Namee & Sons Logging",
    "wof:placetype":"venue"
},
  "geometry": {"coordinates":[-117.27370500000001,48.019268],"type":"Point"}
}