{
  "type": "Feature",
  "properties": {
    "addr:full":"801 Main St Sultan WA 98294",
    "addr:housenumber":"801",
    "addr:postcode":"98294",
    "addr:street":"Main St",
    "iso:country":"US",
    "sg:address":"801 Main St",
    "sg:city":"Sultan",
    "sg:classifiers":[
        {
            "category":"Insurance",
            "subcategory":"Insurance Agent",
            "type":"Services"
        }
    ],
    "sg:phone":"+1 360 793 1111",
    "sg:postcode":"98294",
    "sg:province":"WA",
    "sg:website":"www.sultaninsurance.com",
    "wof:name":"Sultan Insurance",
    "wof:placetype":"venue"
},
  "geometry": {"coordinates":[-121.80808500000001,47.862518],"type":"Point"}
}