{
  "type": "Feature",
  "properties": {
    "addr:full":"19920 N US Hwy 101 Skokomish Nation WA 98584",
    "addr:housenumber":"19920",
    "addr:postcode":"98584",
    "addr:street":"N Us Hwy 101",
    "iso:country":"US",
    "sg:address":"19920 N US Hwy 101",
    "sg:city":"Skokomish Nation",
    "sg:classifiers":[
        {
            "category":"Utilities",
            "subcategory":"Fuel Oil & Lpg",
            "type":"Services"
        }
    ],
    "sg:phone":"+1 360 877 5311",
    "sg:postcode":"98584",
    "sg:province":"WA",
    "sg:tags":[
        "propane",
        "gas"
    ],
    "wof:name":"Ferrellgas",
    "wof:placetype":"venue"
},
  "geometry": {"coordinates":[-123.161165,47.344762],"type":"Point"}
}