{
  "type": "Feature",
  "properties": {
    "addr:full":"16174 State Highway 305 NE Poulsbo WA 98370",
    "addr:housenumber":"16174",
    "addr:postcode":"98370",
    "addr:street":"State Highway 305 Ne",
    "iso:country":"US",
    "sg:address":"16174 State Highway 305 NE",
    "sg:city":"Poulsbo",
    "sg:classifiers":[
        {
            "category":"Coffee & Tea",
            "type":"Food & Drink"
        },
        {
            "category":"Restaurant",
            "type":"Food & Drink"
        }
    ],
    "sg:phone":"+1 360 394 1800",
    "sg:postcode":"98370",
    "sg:province":"WA",
    "sg:tags":[
        "shop",
        "espresso"
    ],
    "wof:name":"Coyote Coffee",
    "wof:placetype":"venue"
},
  "geometry": {"coordinates":[-122.58908599999999,47.706131],"type":"Point"}
}