{
  "type": "Feature",
  "properties": {
    "addr:full":"2000 Lakeridge Dr SW Olympia WA 98502",
    "addr:housenumber":"2000",
    "addr:postcode":"98502",
    "addr:street":"Lakeridge Dr Sw",
    "iso:country":"US",
    "sg:address":"2000 Lakeridge Dr SW",
    "sg:city":"Olympia",
    "sg:classifiers":[
        {
            "category":"Government",
            "subcategory":"Office",
            "type":"Public Place"
        }
    ],
    "sg:phone":"+1 360 786 5217",
    "sg:postcode":"98502",
    "sg:province":"WA",
    "wof:name":"Honorable Gary R Tabor",
    "wof:placetype":"venue"
},
  "geometry": {"coordinates":[-122.913601,47.029042],"type":"Point"}
}