{
  "type": "Feature",
  "properties": {
    "addr:full":"1220 Lawrence St Port Townsend WA 98368",
    "addr:housenumber":"1220",
    "addr:postcode":"98368",
    "addr:street":"Lawrence St",
    "iso:country":"US",
    "sg:address":"1220 Lawrence St",
    "sg:city":"Port Townsend",
    "sg:classifiers":[
        {
            "category":"Education",
            "subcategory":"Library",
            "type":"Public Place"
        }
    ],
    "sg:phone":"+1 360 385 3181",
    "sg:postcode":"98368",
    "sg:province":"WA",
    "wof:name":"Port Townsend Public Library",
    "wof:placetype":"venue"
},
  "geometry": {"coordinates":[-122.762899,48.116507],"type":"Point"}
}