{
  "type": "Feature",
  "properties": {
    "addr:full":"3206 Orleans St Bellingham WA 98226",
    "addr:housenumber":"3206",
    "addr:postcode":"98226",
    "addr:street":"Orleans St",
    "iso:country":"US",
    "sg:address":"3206 Orleans St",
    "sg:city":"Bellingham",
    "sg:classifiers":[
        {
            "category":"Retail",
            "subcategory":"Repair Shop",
            "type":"Services"
        }
    ],
    "sg:phone":"+1 360 715 9023",
    "sg:postcode":"98226",
    "sg:province":"WA",
    "wof:name":"Tech One Electronics",
    "wof:placetype":"venue"
},
  "geometry": {"coordinates":[-122.457576,48.774945],"type":"Point"}
}