{
  "type": "Feature",
  "properties": {
    "addr:full":"5512 NE 109 Ct Ste A1 Vancouver WA 98662",
    "addr:housenumber":"5512",
    "addr:postcode":"98662",
    "addr:street":"Ne 109 Ct Ste A1",
    "iso:country":"US",
    "sg:address":"5512 NE 109 Ct Ste A1",
    "sg:city":"Vancouver",
    "sg:classifiers":[
        {
            "category":"Real Estate",
            "subcategory":"Real Estate Services",
            "type":"Services"
        },
        {
            "category":"Real Estate",
            "subcategory":"Surveying",
            "type":"Services"
        },
        {
            "category":"Real Estate",
            "subcategory":"Real Estate Agent",
            "type":"Services"
        },
        {
            "category":"Professional",
            "type":"Services"
        }
    ],
    "sg:phone":"+1 360 772 0036",
    "sg:postcode":"98662",
    "sg:province":"WA",
    "sg:tags":[
        "commercial",
        "industrial",
        "appraisers-commercial",
        "appraiser",
        "relocation"
    ],
    "sg:website":"www.vancouverwarealtors.com",
    "wof:name":"Jensen White Real Estate",
    "wof:placetype":"venue"
},
  "geometry": {"coordinates":[-122.56107299999999,45.662272],"type":"Point"}
}