{
  "type": "Feature",
  "properties": {
    "addr:full":"21221 Shell Valley Rd Edmonds WA 98026",
    "addr:housenumber":"21221",
    "addr:postcode":"98026",
    "addr:street":"Shell Valley Rd",
    "iso:country":"US",
    "sg:address":"21221 Shell Valley Rd",
    "sg:city":"Edmonds",
    "sg:classifiers":[
        {
            "category":"Manufacturing",
            "subcategory":"Jewelry",
            "type":"Manufacturing & Wholesale Goods"
        }
    ],
    "sg:phone":"+1 425 778 3693",
    "sg:postcode":"98026",
    "sg:province":"WA",
    "sg:tags":[
        "costume",
        "mfg"
    ],
    "wof:name":"My Mothers Buttons",
    "wof:placetype":"venue"
},
  "geometry": {"coordinates":[-122.353375,47.806743],"type":"Point"}
}