{
  "type": "Feature",
  "properties": {
    "addr:full":"21819 SE 13th Pl Sammamish WA 98075",
    "addr:postcode":"21819;98075",
    "addr:street":"Se 13Th Pl",
    "iso:country":"US",
    "sg:address":"21819 SE 13th Pl",
    "sg:city":"Sammamish",
    "sg:classifiers":[
        {
            "category":"Shopping",
            "subcategory":"Discount & Variety Stores",
            "type":"Retail Goods"
        }
    ],
    "sg:phone":"+1 425 391 1127",
    "sg:postcode":"98075",
    "sg:province":"WA",
    "sg:tags":[
        "merchandise",
        "general"
    ],
    "wof:name":"HK At Home Inc",
    "wof:placetype":"venue"
},
  "geometry": {"coordinates":[-122.049137,47.598365],"type":"Point"}
}