{
  "type": "Feature",
  "properties": {
    "addr:full":"19110 Bothell Way NE Bothell WA 98011",
    "addr:housenumber":"19110",
    "addr:postcode":"98011",
    "addr:street":"Bothell Way Ne",
    "iso:country":"US",
    "sg:address":"19110 Bothell Way NE",
    "sg:city":"Bothell",
    "sg:classifiers":[
        {
            "category":"Health Services",
            "subcategory":"Health Practitioner",
            "type":"Services"
        },
        {
            "category":"Organizations",
            "subcategory":"Professional Association",
            "type":"Services"
        }
    ],
    "sg:phone":"+1 425 424 3588",
    "sg:postcode":"98011",
    "sg:province":"WA",
    "sg:tags":[
        "acupuncture"
    ],
    "wof:name":"Eastwind Acupuncture & Hlstc",
    "wof:placetype":"venue"
},
  "geometry": {"coordinates":[-122.210086,47.766275],"type":"Point"}
}