{
  "type": "Feature",
  "properties": {
    "addr:full":"2724 6th Pl S Seattle WA 98134",
    "addr:housenumber":"2724",
    "addr:postcode":"98134",
    "addr:street":"6Th Pl S",
    "iso:country":"US",
    "sg:address":"2724 6th Pl S",
    "sg:city":"Seattle",
    "sg:classifiers":[
        {
            "category":"Shopping",
            "subcategory":"Clothing, Apparel, & Fashions",
            "type":"Retail Goods"
        }
    ],
    "sg:phone":"+1 206 623 7688",
    "sg:postcode":"98134",
    "sg:province":"WA",
    "sg:tags":[
        "pattern",
        "maker"
    ],
    "wof:name":"Continuous Casting Co",
    "wof:placetype":"venue"
},
  "geometry": {"coordinates":[-122.32521800000001,47.579291],"type":"Point"}
}