{
  "type": "Feature",
  "properties": {
    "addr:full":"801 Manila St Walla Walla WA 99362",
    "addr:housenumber":"801",
    "addr:postcode":"99362",
    "addr:street":"Manila St",
    "iso:country":"US",
    "sg:address":"801 Manila St",
    "sg:city":"Walla Walla",
    "sg:classifiers":[
        {
            "category":"Organizations",
            "subcategory":"Professional Association",
            "type":"Services"
        }
    ],
    "sg:phone":"+1 509 522 9439",
    "sg:postcode":"99362",
    "sg:province":"WA",
    "wof:name":"Zonta International",
    "wof:placetype":"venue"
},
  "geometry": {"coordinates":[-118.305543,46.060562],"type":"Point"}
}