{
  "type": "Feature",
  "properties": {
    "addr:full":"8312 5th Ave NE Seattle WA 98115",
    "addr:housenumber":"8312",
    "addr:postcode":"98115",
    "addr:street":"5Th Ave Ne",
    "iso:country":"US",
    "sg:address":"8312 5th Ave NE",
    "sg:city":"Seattle",
    "sg:classifiers":[
        {
            "category":"Professional",
            "subcategory":"Business Services",
            "type":"Services"
        }
    ],
    "sg:phone":"+1 206 526 9821",
    "sg:postcode":"98115",
    "sg:province":"WA",
    "sg:tags":[
        "decorating",
        "contractor"
    ],
    "wof:name":"Balloonist/Renaissance Balloon",
    "wof:placetype":"venue"
},
  "geometry": {"coordinates":[-122.32291600000001,47.689588],"type":"Point"}
}