{
  "type": "Feature",
  "properties": {
    "addr:full":"3503 SW Morgan St Seattle WA 98126",
    "addr:housenumber":"3503",
    "addr:postcode":"98126",
    "addr:street":"Sw Morgan St",
    "iso:country":"US",
    "sg:address":"3503 SW Morgan St",
    "sg:city":"Seattle",
    "sg:classifiers":[
        {
            "category":"Retail",
            "subcategory":"Laundry & Dry Cleaning",
            "type":"Services"
        }
    ],
    "sg:phone":"+1 206 938 2185",
    "sg:postcode":"98126",
    "sg:province":"WA",
    "wof:name":"Checkmate Dry Cleaners",
    "wof:placetype":"venue"
},
  "geometry": {"coordinates":[-122.37599899999999,47.544601],"type":"Point"}
}