{
  "type": "Feature",
  "properties": {
    "addr:full":"11624 E Sprague Ave Spokane WA 99206",
    "addr:housenumber":"11624",
    "addr:postcode":"99206",
    "addr:street":"E Sprague Ave",
    "iso:country":"US",
    "sg:address":"11624 E Sprague Ave",
    "sg:city":"Spokane",
    "sg:classifiers":[
        {
            "category":"Retail",
            "subcategory":"Auto Repair",
            "type":"Services"
        }
    ],
    "sg:phone":"+1 509 928 4793",
    "sg:postcode":"99206",
    "sg:province":"WA",
    "sg:tags":[
        "general"
    ],
    "wof:name":"Abbeys Auto",
    "wof:placetype":"venue"
},
  "geometry": {"coordinates":[-117.247951,47.65698],"type":"Point"}
}