{
  "type": "Feature",
  "properties": {
    "addr:full":"4084 156th Ave SE Bellevue WA 98006",
    "addr:housenumber":"4084",
    "addr:postcode":"98006",
    "addr:street":"156Th Ave Se",
    "iso:country":"US",
    "sg:address":"4084 156th Ave SE",
    "sg:city":"Bellevue",
    "sg:classifiers":[
        {
            "category":"Building & Trades",
            "subcategory":"Construction",
            "type":"Services"
        }
    ],
    "sg:phone":"+1 425 643 3654",
    "sg:postcode":"98006",
    "sg:province":"WA",
    "sg:tags":[
        "roofing",
        "contractor"
    ],
    "wof:name":"West Seattle Roofing Inc",
    "wof:placetype":"venue"
},
  "geometry": {"coordinates":[-122.132723,47.572158],"type":"Point"}
}