{
  "type": "Feature",
  "properties": {
    "addr:full":"20373 Viking Ave NW Poulsbo WA 98370",
    "addr:housenumber":"20373",
    "addr:postcode":"98370",
    "addr:street":"Viking Ave Nw",
    "iso:country":"US",
    "sg:address":"20373 Viking Ave NW",
    "sg:city":"Poulsbo",
    "sg:classifiers":[
        {
            "category":"Retail",
            "subcategory":"Repair Shop",
            "type":"Services"
        }
    ],
    "sg:phone":"+1 360 779 5736",
    "sg:postcode":"98370",
    "sg:province":"WA",
    "sg:tags":[
        "appliance"
    ],
    "wof:name":"Bill's City Appliance Repair",
    "wof:placetype":"venue"
},
  "geometry": {"coordinates":[-122.65460299999999,47.748734],"type":"Point"}
}