{
  "type": "Feature",
  "properties": {
    "addr:full":"13014 97th Ave E Puyallup WA 98373",
    "addr:housenumber":"13014",
    "addr:postcode":"98373",
    "addr:street":"97Th Ave E",
    "iso:country":"US",
    "sg:address":"13014 97th Ave E",
    "sg:city":"Puyallup",
    "sg:classifiers":[
        {
            "category":"Wholesale",
            "subcategory":"Computers",
            "type":"Manufacturing & Wholesale Goods"
        }
    ],
    "sg:phone":"+1 253 445 1597",
    "sg:postcode":"98373",
    "sg:province":"WA",
    "wof:name":"Pcice",
    "wof:placetype":"venue"
},
  "geometry": {"coordinates":[-122.30047500000001,47.141306],"type":"Point"}
}