{
  "type": "Feature",
  "properties": {
    "addr:full":"3026 109th Ave SE Bellevue WA 98004",
    "addr:housenumber":"3026",
    "addr:postcode":"98004",
    "addr:street":"109Th Ave Se",
    "iso:country":"US",
    "sg:address":"3026 109th Ave SE",
    "sg:city":"Bellevue",
    "sg:classifiers":[
        {
            "category":"Recreation",
            "subcategory":"Boat Charter",
            "type":"Entertainment"
        },
        {
            "category":"Shopping",
            "subcategory":"Bicycles & Sporting Goods",
            "type":"Retail Goods"
        },
        {
            "category":"Travel",
            "subcategory":"Travel Agent",
            "type":"Entertainment"
        },
        {
            "category":"Marine",
            "type":"Transportation"
        }
    ],
    "sg:phone":"+1 425 455 5769",
    "sg:postcode":"98004",
    "sg:province":"WA",
    "sg:tags":[
        "watercraft-personal-renting",
        "boat-rental",
        "agency"
    ],
    "wof:name":"A Champagne Cruise",
    "wof:placetype":"venue"
},
  "geometry": {"coordinates":[-122.19520799999999,47.583639],"type":"Point"}
}