{
  "type": "Feature",
  "properties": {
    "addr:full":"24028 Brier Way Brier WA 98036",
    "addr:postcode":"24028;98036",
    "addr:street":"Brier Way",
    "iso:country":"US",
    "sg:address":"24028 Brier Way",
    "sg:city":"Brier",
    "sg:classifiers":[
        {
            "category":"Personal",
            "subcategory":"Beauty Salon",
            "type":"Services"
        }
    ],
    "sg:phone":"+1 425 486 2271",
    "sg:postcode":"98036",
    "sg:province":"WA",
    "wof:name":"Sigi's Family Hairstyling",
    "wof:placetype":"venue"
},
  "geometry": {"coordinates":[-122.274098,47.780432],"type":"Point"}
}