{
  "type": "Feature",
  "properties": {
    "addr:full":"1902 SW 170th St Seattle WA 98166",
    "addr:housenumber":"1902",
    "addr:postcode":"98166",
    "addr:street":"Sw 170Th St",
    "iso:country":"US",
    "sg:address":"1902 SW 170th St",
    "sg:city":"Seattle",
    "sg:classifiers":[
        {
            "category":"Professional",
            "subcategory":"Computer Services",
            "type":"Services"
        }
    ],
    "sg:phone":"+1 206 624 5385",
    "sg:postcode":"98166",
    "sg:province":"WA",
    "sg:tags":[
        "related"
    ],
    "wof:name":"Soccerbuddies LLC",
    "wof:placetype":"venue"
},
  "geometry": {"coordinates":[-122.358638,47.450708],"type":"Point"}
}