{
  "type": "Feature",
  "properties": {
    "addr:full":"1103 5th St Wenatchee WA 98801",
    "addr:housenumber":"1103",
    "addr:postcode":"98801",
    "addr:street":"5Th St",
    "iso:country":"US",
    "sg:address":"1103 5th St",
    "sg:city":"Wenatchee",
    "sg:classifiers":[
        {
            "category":"Social Services",
            "subcategory":"Child Care",
            "type":"Services"
        }
    ],
    "sg:phone":"+1 509 662 9453",
    "sg:postcode":"98801",
    "sg:province":"WA",
    "sg:tags":[
        "kindergarten",
        "academic",
        "school"
    ],
    "wof:name":"Greater Wenatchee Preschool",
    "wof:placetype":"venue"
},
  "geometry": {"coordinates":[-120.327195,47.429736],"type":"Point"}
}