{
  "type": "Feature",
  "properties": {
    "addr:full":"2312 Magnolia Blvd W Seattle WA 98199",
    "addr:housenumber":"2312",
    "addr:postcode":"98199",
    "addr:street":"Magnolia Blvd W",
    "iso:country":"US",
    "sg:address":"2312 Magnolia Blvd W",
    "sg:city":"Seattle",
    "sg:classifiers":[
        {
            "category":"Real Estate",
            "subcategory":"Architect",
            "type":"Services"
        }
    ],
    "sg:phone":"+1 206 283 1715",
    "sg:postcode":"98199",
    "sg:province":"WA",
    "sg:tags":[
        "residential",
        "designer"
    ],
    "sg:website":"http://melissakinteriordesign.com",
    "wof:name":"mkID",
    "wof:placetype":"venue"
},
  "geometry": {"coordinates":[-122.407996,47.637797],"type":"Point"}
}