{
  "type": "Feature",
  "properties": {
    "addr:full":"3221 NE Sunset Blvd Renton WA 98056",
    "addr:housenumber":"3221",
    "addr:postcode":"98056",
    "addr:street":"Ne Sunset Blvd",
    "iso:country":"US",
    "sg:address":"3221 NE Sunset Blvd",
    "sg:city":"Renton",
    "sg:classifiers":[
        {
            "category":"Bars & Pubs",
            "subcategory":"Lounge",
            "type":"Food & Drink"
        },
        {
            "category":"Restaurant",
            "type":"Food & Drink"
        }
    ],
    "sg:phone":"+1 425 228 7757",
    "sg:postcode":"98056",
    "sg:province":"WA",
    "sg:tags":[
        "american",
        "mexican",
        "cocktail"
    ],
    "wof:name":"La Fuente",
    "wof:placetype":"venue"
},
  "geometry": {"coordinates":[-122.17600299999999,47.504799],"type":"Point"}
}