{
  "type": "Feature",
  "properties": {
    "addr:full":"1114 S 11th St Tacoma WA 98405",
    "addr:housenumber":"1114",
    "addr:postcode":"98405",
    "addr:street":"S 11Th St",
    "iso:country":"US",
    "sg:address":"1114 S 11th St",
    "sg:city":"Tacoma",
    "sg:classifiers":[
        {
            "category":"Real Estate",
            "subcategory":"Real Estate Operator",
            "type":"Services"
        }
    ],
    "sg:phone":"+1 253 779 0299",
    "sg:postcode":"98405",
    "sg:province":"WA",
    "sg:tags":[
        "building",
        "apartment"
    ],
    "wof:name":"Mlk New Look Apts",
    "wof:placetype":"venue"
},
  "geometry": {"coordinates":[-122.453,47.2518],"type":"Point"}
}