{
  "type": "Feature",
  "properties": {
    "addr:full":"13324 Waller Rd E Tacoma WA 98446",
    "addr:housenumber":"13324",
    "addr:postcode":"98446",
    "addr:street":"Waller Rd E",
    "iso:country":"US",
    "sg:address":"13324 Waller Rd E",
    "sg:city":"Tacoma",
    "sg:classifiers":[
        {
            "category":"Building & Trades",
            "subcategory":"Construction",
            "type":"Services"
        }
    ],
    "sg:phone":"+1 253 537 7309",
    "sg:postcode":"98446",
    "sg:province":"WA",
    "sg:tags":[
        "excavating",
        "contractor"
    ],
    "wof:name":"Gary Reed's Excavating",
    "wof:placetype":"venue"
},
  "geometry": {"coordinates":[-122.392955,47.135484],"type":"Point"}
}