{
  "type": "Feature",
  "properties": {
    "addr:full":"10613 225th Ave E Buckley WA 98321",
    "addr:housenumber":"10613",
    "addr:postcode":"98321",
    "addr:street":"225Th Ave E",
    "iso:country":"US",
    "sg:address":"10613 225th Ave E",
    "sg:city":"Buckley",
    "sg:classifiers":[
        {
            "category":"Professional",
            "subcategory":"Business Services",
            "type":"Services"
        }
    ],
    "sg:phone":"+1 253 227 1466",
    "sg:postcode":"98321",
    "sg:province":"WA",
    "wof:name":"K & S Home Creations",
    "wof:placetype":"venue"
},
  "geometry": {"coordinates":[-122.128745,47.159745],"type":"Point"}
}