{
  "type": "Feature",
  "properties": {
    "addr:full":"4901 NE Minnehaha St Vancouver WA 98661",
    "addr:housenumber":"4901",
    "addr:postcode":"98661",
    "addr:street":"Ne Minnehaha St",
    "iso:country":"US",
    "sg:address":"4901 NE Minnehaha St",
    "sg:city":"Vancouver",
    "sg:classifiers":[
        {
            "category":"Retail",
            "subcategory":"Storage",
            "type":"Services"
        }
    ],
    "sg:phone":"+1 360 699 6226",
    "sg:postcode":"98661",
    "sg:province":"WA",
    "sg:tags":[
        "self"
    ],
    "sg:website":"www.additionalselfstorage.com",
    "wof:name":"Additional Self Storage",
    "wof:placetype":"venue"
},
  "geometry": {"coordinates":[-122.621002,45.667999],"type":"Point"}
}