{
  "type": "Feature",
  "properties": {
    "addr:full":"825 116th Ave NE Bellevue WA 98004",
    "addr:housenumber":"825",
    "addr:postcode":"98004",
    "addr:street":"116Th Ave Ne",
    "iso:country":"US",
    "sg:address":"825 116th Ave NE",
    "sg:city":"Bellevue",
    "sg:classifiers":[
        {
            "category":"Restaurant",
            "type":"Food & Drink"
        }
    ],
    "sg:phone":"+1 425 455 0222",
    "sg:postcode":"98004",
    "sg:province":"WA",
    "sg:tags":[
        "japanese"
    ],
    "wof:name":"Taste of Tokyo",
    "wof:placetype":"venue"
},
  "geometry": {"coordinates":[-122.185669,47.617512],"type":"Point"}
}