{
  "type": "Feature",
  "properties": {
    "addr:full":"7631 212th St SW Ste 111 Edmonds WA 98026",
    "addr:housenumber":"7631",
    "addr:postcode":"98026",
    "addr:street":"212Th St Sw Ste 111",
    "iso:country":"US",
    "sg:address":"7631 212th St SW Ste 111",
    "sg:city":"Edmonds",
    "sg:classifiers":[
        {
            "category":"Health Services",
            "subcategory":"Clinic",
            "type":"Services"
        },
        {
            "category":"Health Services",
            "subcategory":"Health Practitioner",
            "type":"Services"
        },
        {
            "category":"Community Center",
            "type":"Public Place"
        }
    ],
    "sg:phone":"+1 425 712 3119",
    "sg:postcode":"98026",
    "sg:province":"WA",
    "sg:tags":[
        "acupuncture",
        "medicine",
        "medical",
        "alternative"
    ],
    "wof:name":"Silver Needle Acupuncture",
    "wof:placetype":"venue"
},
  "geometry": {"coordinates":[-122.33627300000001,47.806931],"type":"Point"}
}