{
  "type": "Feature",
  "properties": {
    "addr:full":"320 N Tower Ave Centralia WA 98531",
    "addr:housenumber":"320",
    "addr:postcode":"98531",
    "addr:street":"N Tower Ave",
    "iso:country":"US",
    "sg:address":"320 N Tower Ave",
    "sg:city":"Centralia",
    "sg:classifiers":[
        {
            "category":"Wholesale",
            "subcategory":"Non-durable Goods",
            "type":"Manufacturing & Wholesale Goods"
        },
        {
            "category":"Personal",
            "subcategory":"Barber",
            "type":"Services"
        }
    ],
    "sg:phone":"+1 360 736 2562",
    "sg:postcode":"98531",
    "sg:province":"WA",
    "sg:tags":[
        "beauty",
        "supply",
        "equipment",
        "salons-equipment",
        "supplies-wholesale",
        "manufacturer"
    ],
    "wof:name":"Jim Stilner",
    "wof:placetype":"venue"
},
  "geometry": {"coordinates":[-122.953463,46.718333],"type":"Point"}
}