{
  "type": "Feature",
  "properties": {
    "addr:full":"822 Pleasant Valley Rd Yakima WA 98908",
    "addr:housenumber":"822",
    "addr:postcode":"98908",
    "addr:street":"Pleasant Valley Rd",
    "iso:country":"US",
    "sg:address":"822 Pleasant Valley Rd",
    "sg:city":"Yakima",
    "sg:classifiers":[
        {
            "category":"Professional",
            "subcategory":"Management & Consulting",
            "type":"Services"
        }
    ],
    "sg:phone":"+1 509 965 7712",
    "sg:postcode":"98908",
    "sg:province":"WA",
    "sg:tags":[
        "business"
    ],
    "wof:name":"AG Forensics",
    "wof:placetype":"venue"
},
  "geometry": {"coordinates":[-120.61528199999999,46.680067],"type":"Point"}
}