{
  "type": "Feature",
  "properties": {
    "addr:full":"2859 Chaussee Victoria Ct East Wenatchee WA 98802",
    "addr:housenumber":"2859",
    "addr:postcode":"98802",
    "addr:street":"Chaussee Victoria Ct",
    "iso:country":"US",
    "sg:address":"2859 Chaussee Victoria Ct",
    "sg:city":"East Wenatchee",
    "sg:classifiers":[
        {
            "category":"Manufacturing",
            "subcategory":"Printing",
            "type":"Manufacturing & Wholesale Goods"
        }
    ],
    "sg:phone":"+1 509 884 0812",
    "sg:postcode":"98802",
    "sg:province":"WA",
    "sg:tags":[
        "lithographic",
        "commercial"
    ],
    "wof:name":"Wall To Wall Publications",
    "wof:placetype":"venue"
},
  "geometry": {"coordinates":[-120.304188,47.452854],"type":"Point"}
}