{
  "type": "Feature",
  "properties": {
    "addr:full":"3608 88th St NE Marysville WA 98270",
    "addr:housenumber":"3608",
    "addr:postcode":"98270",
    "addr:street":"88Th St Ne",
    "iso:country":"US",
    "sg:address":"3608 88th St NE",
    "sg:city":"Marysville",
    "sg:classifiers":[
        {
            "category":"Autos & Motor Vehicles",
            "subcategory":"Fuel & Gas Station",
            "type":"Retail Goods"
        }
    ],
    "sg:phone":"+1 360 658 3318",
    "sg:postcode":"98270",
    "sg:province":"WA",
    "sg:tags":[
        "station",
        "gasoline"
    ],
    "wof:name":"Chevron",
    "wof:placetype":"venue"
},
  "geometry": {"coordinates":[-122.182169,48.075637],"type":"Point"}
}