{
  "type": "Feature",
  "properties": {
    "addr:full":"113 E Main St Auburn WA 98002",
    "addr:housenumber":"113",
    "addr:postcode":"98002",
    "addr:street":"E Main St",
    "iso:country":"US",
    "sg:address":"113 E Main St",
    "sg:city":"Auburn",
    "sg:classifiers":[
        {
            "category":"Personal",
            "subcategory":"Beauty Salon",
            "type":"Services"
        }
    ],
    "sg:phone":"+1 253 737 4248",
    "sg:postcode":"98002",
    "sg:province":"WA",
    "wof:name":"Family Affair",
    "wof:placetype":"venue"
},
  "geometry": {"coordinates":[-122.228106,47.307428],"type":"Point"}
}