{
  "type": "Feature",
  "properties": {
    "addr:full":"115 W Main St Monroe WA 98272",
    "addr:housenumber":"115",
    "addr:postcode":"98272",
    "addr:street":"W Main St",
    "iso:country":"US",
    "sg:address":"115 W Main St",
    "sg:city":"Monroe",
    "sg:classifiers":[
        {
            "category":"Wholesale",
            "subcategory":"Electrical",
            "type":"Manufacturing & Wholesale Goods"
        }
    ],
    "sg:phone":"+1 360 794 0579",
    "sg:postcode":"98272",
    "sg:province":"WA",
    "sg:tags":[
        "equipment"
    ],
    "wof:name":"Yard Moods",
    "wof:placetype":"venue"
},
  "geometry": {"coordinates":[-121.97099900000001,47.855756],"type":"Point"}
}