{
  "type": "Feature",
  "properties": {
    "addr:full":"10 N 10th Ave Yakima WA 98902",
    "addr:housenumber":"10",
    "addr:postcode":"98902",
    "addr:street":"N 10Th Ave",
    "iso:country":"US",
    "sg:address":"10 N 10th Ave",
    "sg:city":"Yakima",
    "sg:classifiers":[
        {
            "category":"Social Services",
            "type":"Services"
        }
    ],
    "sg:phone":"+1 509 453 4795",
    "sg:postcode":"98902",
    "sg:province":"WA",
    "sg:tags":[
        "youth",
        "organization",
        "center"
    ],
    "sg:website":"www.grandcolumbiabsa.org",
    "wof:name":"Boy Scouts Of America",
    "wof:placetype":"venue"
},
  "geometry": {"coordinates":[-120.523538,46.599515],"type":"Point"}
}