{
  "type": "Feature",
  "properties": {
    "addr:full":"20140 Grand Mound Way SW Rochester WA 98531",
    "addr:housenumber":"20140",
    "addr:postcode":"98531",
    "addr:street":"Grand Mound Way Sw",
    "iso:country":"US",
    "sg:address":"20140 Grand Mound Way SW",
    "sg:city":"Rochester",
    "sg:classifiers":[
        {
            "category":"Organizations",
            "subcategory":"Religious Organization",
            "type":"Services"
        }
    ],
    "sg:phone":"+1 360 273 0994",
    "sg:postcode":"98531",
    "sg:province":"WA",
    "sg:tags":[
        "church"
    ],
    "wof:name":"Grand Mound Church",
    "wof:placetype":"venue"
},
  "geometry": {"coordinates":[-123.03119599999999,46.796244],"type":"Point"}
}