{
  "type": "Feature",
  "properties": {
    "addr:full":"32901 138th St SE Sultan WA 98294",
    "addr:housenumber":"32901",
    "addr:postcode":"98294",
    "addr:street":"138Th St Se Sultan",
    "iso:country":"US",
    "sg:address":"32901 138th St SE",
    "sg:city":"Sultan",
    "sg:classifiers":[
        {
            "category":"Building & Trades",
            "subcategory":"Landscaping Services",
            "type":"Services"
        }
    ],
    "sg:phone":"+1 360 793 9789",
    "sg:postcode":"98294",
    "sg:province":"WA",
    "sg:tags":[
        "landscape",
        "contractor"
    ],
    "wof:name":"Sharpes Jake Construction",
    "wof:placetype":"venue"
},
  "geometry": {"coordinates":[-121.79472699999999,47.873092],"type":"Point"}
}