{
  "type": "Feature",
  "properties": {
    "addr:full":"2709 W Boone Ave Spokane WA 99201",
    "addr:housenumber":"2709",
    "addr:postcode":"99201",
    "addr:street":"W Boone Ave",
    "iso:country":"US",
    "sg:address":"2709 W Boone Ave",
    "sg:city":"Spokane",
    "sg:classifiers":[
        {
            "category":"Organizations",
            "subcategory":"Religious Organization",
            "type":"Services"
        }
    ],
    "sg:phone":"+1 509 325 0393",
    "sg:postcode":"99201",
    "sg:province":"WA",
    "sg:tags":[
        "medical"
    ],
    "wof:name":"Christ Clinic",
    "wof:placetype":"venue"
},
  "geometry": {"coordinates":[-117.453746,47.667906],"type":"Point"}
}