{
  "type": "Feature",
  "properties": {
    "addr:full":"6820 52nd Ave NE Seattle WA 98115",
    "addr:housenumber":"6820",
    "addr:postcode":"98115",
    "addr:street":"52Nd Ave Ne",
    "iso:country":"US",
    "sg:address":"6820 52nd Ave NE",
    "sg:city":"Seattle",
    "sg:classifiers":[
        {
            "category":"Building & Trades",
            "subcategory":"Electrical",
            "type":"Services"
        }
    ],
    "sg:phone":"+1 206 527 5099",
    "sg:postcode":"98115",
    "sg:province":"WA",
    "sg:tags":[
        "electrical",
        "contractor"
    ],
    "wof:name":"Fountain Light Electric",
    "wof:placetype":"venue"
},
  "geometry": {"coordinates":[-122.271553,47.679211],"type":"Point"}
}