{
  "type": "Feature",
  "properties": {
    "iso:country":"US",
    "sg:address":"30 Lake St S",
    "sg:city":"Kirkland",
    "sg:classifiers":[
        {
            "category":"Personal",
            "type":"Services"
        }
    ],
    "sg:phone":"+1 425 827 3173",
    "sg:postcode":"98033",
    "sg:province":"WA",
    "wof:name":"Kirkland Skin Care",
    "wof:placetype":"venue"
},
  "geometry": {"coordinates":[-122.206793,47.676159],"type":"Point"}
}