{
  "type": "Feature",
  "properties": {
    "addr:full":"7302 Corregidor Rd Vancouver WA 98664",
    "addr:housenumber":"7302",
    "addr:postcode":"98664",
    "addr:street":"Corregidor Rd",
    "iso:country":"US",
    "sg:address":"7302 Corregidor Rd",
    "sg:city":"Vancouver",
    "sg:classifiers":[
        {
            "category":"Building & Trades",
            "subcategory":"Construction",
            "type":"Services"
        }
    ],
    "sg:phone":"+1 360 699 7117",
    "sg:postcode":"98664",
    "sg:province":"WA",
    "sg:tags":[
        "repairing",
        "remodeling",
        "contractor"
    ],
    "wof:name":"Sundown Development Constr",
    "wof:placetype":"venue"
},
  "geometry": {"coordinates":[-122.597358,45.616304],"type":"Point"}
}