{
  "type": "Feature",
  "properties": {
    "addr:full":"2119 15th Ave S Seattle WA 98144",
    "addr:housenumber":"2119",
    "addr:postcode":"98144",
    "addr:street":"15Th Ave S",
    "iso:country":"US",
    "sg:address":"2119 15th Ave S",
    "sg:city":"Seattle",
    "sg:classifiers":[
        {
            "category":"Autos & Motor Vehicles",
            "subcategory":"Automobile Sales",
            "type":"Retail Goods"
        }
    ],
    "sg:phone":"+1 206 709 9718",
    "sg:postcode":"98144",
    "sg:province":"WA",
    "sg:tags":[
        "merchandising",
        "internet"
    ],
    "wof:name":"Eamo Enterprises",
    "wof:placetype":"venue"
},
  "geometry": {"coordinates":[-122.313463,47.58385],"type":"Point"}
}