{
  "type": "Feature",
  "properties": {
    "addr:full":"13401 Bel Red Rd Ste B1 Bellevue WA 98005",
    "addr:housenumber":"13401",
    "addr:postcode":"98005",
    "addr:street":"Bel Red Rd Ste B1",
    "iso:country":"US",
    "sg:address":"13401 Bel Red Rd Ste B1",
    "sg:city":"Bellevue",
    "sg:classifiers":[
        {
            "category":"Health Services",
            "subcategory":"Health Practitioner",
            "type":"Services"
        }
    ],
    "sg:phone":"+1 425 746 3315",
    "sg:postcode":"98005",
    "sg:province":"WA",
    "sg:tags":[
        "therapy",
        "physical"
    ],
    "wof:name":"Therapeutic Message Clinic",
    "wof:placetype":"venue"
},
  "geometry": {"coordinates":[-122.160972,47.622326],"type":"Point"}
}