{
  "type": "Feature",
  "properties": {
    "addr:full":"20021 120th Ave NE # 102 Bothell WA 98011",
    "addr:housenumber":"20021",
    "addr:postcode":"98011",
    "addr:street":"120Th Ave Ne # 102",
    "iso:country":"US",
    "sg:address":"20021 120th Ave NE # 102",
    "sg:city":"Bothell",
    "sg:classifiers":[
        {
            "category":"Wholesale",
            "subcategory":"Computers",
            "type":"Manufacturing & Wholesale Goods"
        },
        {
            "category":"Internet Cafe",
            "subcategory":"None",
            "type":"Food & Drink"
        },
        {
            "category":"Professional",
            "subcategory":"Computer Services",
            "type":"Services"
        }
    ],
    "sg:phone":"+1 425 483 4700",
    "sg:postcode":"98011",
    "sg:province":"WA",
    "sg:tags":[
        "product",
        "designer",
        "network",
        "consultant",
        "isp",
        "system",
        "equipment",
        "design",
        "provider",
        "software"
    ],
    "sg:website":"http://www.mediapro.com",
    "wof:name":"Media Pro",
    "wof:placetype":"venue"
},
  "geometry": {"coordinates":[-122.18017500000001,47.771642],"type":"Point"}
}