{
  "type": "Feature",
  "properties": {
    "addr:full":"6703 55th Dr NE Marysville WA 98270",
    "addr:housenumber":"6703",
    "addr:postcode":"98270",
    "addr:street":"55Th Dr Ne",
    "iso:country":"US",
    "sg:address":"6703 55th Dr NE",
    "sg:city":"Marysville",
    "sg:classifiers":[
        {
            "category":"Professional",
            "subcategory":"Accounting & Tax Preparation",
            "type":"Services"
        }
    ],
    "sg:phone":"+1 360 651 0560",
    "sg:postcode":"98270",
    "sg:province":"WA",
    "sg:tags":[
        "return",
        "filing"
    ],
    "wof:name":"H & B Svc",
    "wof:placetype":"venue"
},
  "geometry": {"coordinates":[-122.15628100000001,48.057997],"type":"Point"}
}