{
  "type": "Feature",
  "properties": {
    "addr:full":"1417 3rd Ave Seattle WA 98101",
    "addr:housenumber":"1417",
    "addr:postcode":"98101",
    "addr:street":"3Rd Ave",
    "iso:country":"US",
    "sg:address":"1417 3rd Ave",
    "sg:city":"Seattle",
    "sg:classifiers":[
        {
            "category":"Building & Trades",
            "subcategory":"Locksmith",
            "type":"Services"
        }
    ],
    "sg:phone":"+1 206 905 6130",
    "sg:postcode":"98101",
    "sg:province":"WA",
    "sg:tags":[
        "key"
    ],
    "wof:name":"Locksmith",
    "wof:placetype":"venue"
},
  "geometry": {"coordinates":[-122.337191,47.608842],"type":"Point"}
}