{
  "type": "Feature",
  "properties": {
    "addr:full":"569 Division St Port Orchard WA 98366",
    "addr:housenumber":"569",
    "addr:postcode":"98366",
    "addr:street":"Division St",
    "iso:country":"US",
    "sg:address":"569 Division St",
    "sg:city":"Port Orchard",
    "sg:classifiers":[
        {
            "category":"Government",
            "subcategory":"Police Station",
            "type":"Public Place"
        }
    ],
    "sg:phone":"+1 360 874 1410",
    "sg:postcode":"98366",
    "sg:province":"WA",
    "sg:tags":[
        "protection"
    ],
    "wof:name":"Smed Wagner Investments",
    "wof:placetype":"venue"
},
  "geometry": {"coordinates":[-122.640141,47.538067],"type":"Point"}
}