{
  "type": "Feature",
  "properties": {
    "addr:full":"700 Broadway Ave E Seattle WA 98102",
    "addr:housenumber":"700",
    "addr:postcode":"98102",
    "addr:street":"Broadway Ave E",
    "iso:country":"US",
    "sg:address":"700 Broadway Ave E",
    "sg:city":"Seattle",
    "sg:classifiers":[
        {
            "category":"Coffee & Tea",
            "type":"Food & Drink"
        }
    ],
    "sg:phone":"+1 206 325 2211",
    "sg:postcode":"98102",
    "sg:province":"WA",
    "sg:website":"www.roystreetcoffee.com",
    "wof:name":"Roy Street Coffee & Tea",
    "wof:placetype":"venue"
},
  "geometry": {"coordinates":[-122.321084,47.625137],"type":"Point"}
}