{
  "type": "Feature",
  "properties": {
    "addr:full":"24510 64th Ave S Kent WA 98032",
    "addr:housenumber":"24510",
    "addr:postcode":"98032",
    "addr:street":"64Th Ave S",
    "iso:country":"US",
    "sg:address":"24510 64th Ave S",
    "sg:city":"Kent",
    "sg:classifiers":[
        {
            "category":"Health Services",
            "subcategory":"Clinic",
            "type":"Services"
        }
    ],
    "sg:phone":"+1 253 850 6415",
    "sg:postcode":"98032",
    "sg:province":"WA",
    "sg:tags":[
        "home"
    ],
    "sg:website":"www.armstronghomecare.com",
    "wof:name":"Armstrong Uniserve Inc",
    "wof:placetype":"venue"
},
  "geometry": {"coordinates":[-122.25362800000001,47.381396],"type":"Point"}
}