{
  "type": "Feature",
  "properties": {
    "iso:country":"US",
    "sg:address":"13790 Vantage Hwy",
    "sg:city":"Ellensburg",
    "sg:classifiers":[
        {
            "category":"Farming",
            "subcategory":"Livestock Farm",
            "type":"Manufacturing & Wholesale Goods"
        }
    ],
    "sg:phone":"+1 509 968 3681",
    "sg:postcode":"98926",
    "sg:province":"WA",
    "sg:tags":[
        "beef",
        "feedlot",
        "cattle"
    ],
    "wof:name":"Joe Laub",
    "wof:placetype":"venue"
},
  "geometry": {"coordinates":[-120.348074,47.001094],"type":"Point"}
}