{
  "type": "Feature",
  "properties": {
    "addr:full":"14703 State Hwy 203 Duvall WA 98019",
    "addr:housenumber":"14703",
    "addr:postcode":"98019",
    "addr:street":"State Hwy 203",
    "iso:country":"US",
    "sg:address":"14703 State Hwy 203",
    "sg:city":"Duvall",
    "sg:classifiers":[
        {
            "category":"Health Services",
            "subcategory":"Doctor",
            "type":"Services"
        }
    ],
    "sg:phone":"+1 425 788 2626",
    "sg:postcode":"98019",
    "sg:province":"WA",
    "wof:name":"Duvall Dental Clinic",
    "wof:placetype":"venue"
},
  "geometry": {"coordinates":[-121.987398,47.734196],"type":"Point"}
}