{
  "type": "Feature",
  "properties": {
    "addr:full":"4442 Ridgewood Ct NW Olympia WA 98502",
    "addr:housenumber":"4442",
    "addr:postcode":"olympia wa 98502",
    "addr:street":"Ridgewood Ct Nw",
    "iso:country":"US",
    "sg:address":"4442 Ridgewood Ct NW",
    "sg:city":"Olympia",
    "sg:classifiers":[
        {
            "category":"Building & Trades",
            "subcategory":"Landscaping Services",
            "type":"Services"
        }
    ],
    "sg:phone":"+1 360 866 5298",
    "sg:postcode":"98502",
    "sg:province":"WA",
    "wof:name":"Silverback Services",
    "wof:placetype":"venue"
},
  "geometry": {"coordinates":[-122.936391,47.095259],"type":"Point"}
}