{
  "type": "Feature",
  "properties": {
    "addr:full":"1222 13th St SW Puyallup WA 98371",
    "addr:housenumber":"1222",
    "addr:postcode":"98371",
    "addr:street":"13Th St Sw",
    "iso:country":"US",
    "sg:address":"1222 13th St SW",
    "sg:city":"Puyallup",
    "sg:classifiers":[
        {
            "category":"Building & Trades",
            "subcategory":"Construction",
            "type":"Services"
        }
    ],
    "sg:phone":"+1 253 840 1222",
    "sg:postcode":"98371",
    "sg:province":"WA",
    "sg:tags":[
        "consultant"
    ],
    "wof:name":"Flansburg Investments",
    "wof:placetype":"venue"
},
  "geometry": {"coordinates":[-122.311357,47.180812],"type":"Point"}
}