{
  "type": "Feature",
  "properties": {
    "addr:full":"23004 Bothell Everett Hwy Bothell WA 98021",
    "addr:housenumber":"23004",
    "addr:postcode":"98021",
    "addr:street":"Bothell Everett Hwy",
    "iso:country":"US",
    "sg:address":"23004 Bothell Everett Hwy",
    "sg:city":"Bothell",
    "sg:classifiers":[
        {
            "category":"Building & Trades",
            "subcategory":"Electrical",
            "type":"Services"
        }
    ],
    "sg:phone":"+1 425 482 6278",
    "sg:postcode":"98021",
    "sg:province":"WA",
    "sg:tags":[
        "electrical",
        "contractor"
    ],
    "wof:name":"Lantz Electric",
    "wof:placetype":"venue"
},
  "geometry": {"coordinates":[-122.218856,47.789245],"type":"Point"}
}