{
  "type": "Feature",
  "properties": {
    "iso:country":"US",
    "sg:address":"14789 River Bend Rd",
    "sg:city":"Mount Vernon",
    "sg:classifiers":[
        {
            "category":"Wholesale",
            "subcategory":"Farm Supplies",
            "type":"Manufacturing & Wholesale Goods"
        }
    ],
    "sg:phone":"+1 360 424 6073",
    "sg:postcode":"98273",
    "sg:province":"WA",
    "sg:tags":[
        "straw",
        "hay"
    ],
    "wof:name":"Northwest Hay Sales",
    "wof:placetype":"venue"
},
  "geometry": {"coordinates":[-122.354403,48.430903],"type":"Point"}
}