{
  "type": "Feature",
  "properties": {
    "addr:full":"1053 SW Fleet St Oak Harbor WA 98277",
    "addr:housenumber":"1053",
    "addr:postcode":"98277",
    "addr:street":"Sw Fleet St",
    "iso:country":"US",
    "sg:address":"1053 SW Fleet St",
    "sg:city":"Oak Harbor",
    "sg:classifiers":[
        {
            "category":"Real Estate",
            "subcategory":"Real Estate Operator",
            "type":"Services"
        }
    ],
    "sg:phone":"+1 360 675 4560",
    "sg:postcode":"98277",
    "sg:province":"WA",
    "wof:name":"Harbour Shores",
    "wof:placetype":"venue"
},
  "geometry": {"coordinates":[-122.66529800000001,48.290525],"type":"Point"}
}