{
  "type": "Feature",
  "properties": {
    "addr:full":"4321 University Way NE Seattle WA 98105",
    "addr:housenumber":"4321",
    "addr:postcode":"98105",
    "addr:street":"University Way Ne",
    "iso:country":"US",
    "sg:address":"4321 University Way NE",
    "sg:city":"Seattle",
    "sg:classifiers":[
        {
            "category":"Animal Shelter",
            "type":"Public Place"
        },
        {
            "category":"Shopping",
            "subcategory":"Books",
            "type":"Retail Goods"
        },
        {
            "category":"Retail",
            "subcategory":"Pet Boarding",
            "type":"Services"
        }
    ],
    "sg:phone":"+1 206 632 0774",
    "sg:postcode":"98105",
    "sg:province":"WA",
    "sg:tags":[
        "bookstore",
        "kennel"
    ],
    "sg:website":"www.bookkennel.com",
    "wof:name":"Book Kennel",
    "wof:placetype":"venue"
},
  "geometry": {"coordinates":[-122.313138,47.659963],"type":"Point"}
}