{
  "type": "Feature",
  "properties": {
    "addr:full":"1420 Commercial Ave Anacortes WA 98221",
    "addr:housenumber":"1420",
    "addr:postcode":"98221",
    "addr:street":"Commercial Ave",
    "iso:country":"US",
    "sg:address":"1420 Commercial Ave",
    "sg:city":"Anacortes",
    "sg:classifiers":[
        {
            "category":"Shopping",
            "subcategory":"Florist",
            "type":"Retail Goods"
        }
    ],
    "sg:phone":"+1 360 293 5145",
    "sg:postcode":"98221",
    "sg:province":"WA",
    "sg:tags":[
        "shop",
        "gift"
    ],
    "sg:website":"http://www.sheelysfloral.com",
    "wof:name":"Sheely's Floral & Gifts",
    "wof:placetype":"venue"
},
  "geometry": {"coordinates":[-122.612622,48.510765],"type":"Point"}
}