{
  "type": "Feature",
  "properties": {
    "addr:full":"215 15th St Snohomish WA 98290",
    "addr:housenumber":"215",
    "addr:postcode":"98290",
    "addr:street":"15Th St",
    "iso:country":"US",
    "sg:address":"215 15th St",
    "sg:city":"Snohomish",
    "sg:classifiers":[
        {
            "category":"Professional",
            "subcategory":"Management & Consulting",
            "type":"Services"
        }
    ],
    "sg:phone":"+1 360 568 2646",
    "sg:postcode":"98290",
    "sg:province":"WA",
    "sg:tags":[
        "business"
    ],
    "wof:name":"Hughes Micro Corporation",
    "wof:placetype":"venue"
},
  "geometry": {"coordinates":[-122.082466,47.929989],"type":"Point"}
}