{
  "type": "Feature",
  "properties": {
    "addr:full":"1124 Columbia St Seattle WA 98104",
    "addr:housenumber":"1124",
    "addr:postcode":"98104",
    "addr:street":"Columbia St",
    "iso:country":"US",
    "sg:address":"1124 Columbia St",
    "sg:city":"Seattle",
    "sg:classifiers":[
        {
            "category":"Professional",
            "type":"Services"
        }
    ],
    "sg:phone":"+1 206 667 5628",
    "sg:postcode":"98104",
    "sg:province":"WA",
    "sg:tags":[
        "establishment"
    ],
    "wof:name":"Gen Quest",
    "wof:placetype":"venue"
},
  "geometry": {"coordinates":[-122.32294899999999,47.608323],"type":"Point"}
}