{
  "type": "Feature",
  "properties": {
    "addr:full":"315 S Union St Kennewick WA 99336",
    "addr:housenumber":"315",
    "addr:postcode":"99336",
    "addr:street":"S Union St",
    "iso:country":"US",
    "sg:address":"315 S Union St",
    "sg:city":"Kennewick",
    "sg:classifiers":[
        {
            "category":"Shopping",
            "subcategory":"Computers & Home Electronics",
            "type":"Retail Goods"
        }
    ],
    "sg:phone":"+1 509 586 0652",
    "sg:postcode":"99336",
    "sg:province":"WA",
    "wof:name":"Two Way Shop",
    "wof:placetype":"venue"
},
  "geometry": {"coordinates":[-119.17999,46.207534],"type":"Point"}
}