{
  "type": "Feature",
  "properties": {
    "addr:full":"4225 7th Ave NE Seattle WA 98105",
    "addr:housenumber":"4225",
    "addr:postcode":"98105",
    "addr:street":"7Th Ave Ne",
    "iso:country":"US",
    "sg:address":"4225 7th Ave NE",
    "sg:city":"Seattle",
    "sg:classifiers":[
        {
            "category":"Banks & Credit Unions",
            "subcategory":"Investment Brokerage",
            "type":"Services"
        }
    ],
    "sg:phone":"+1 206 632 2196",
    "sg:postcode":"98105",
    "sg:province":"WA",
    "wof:name":"A & T Investments",
    "wof:placetype":"venue"
},
  "geometry": {"coordinates":[-122.320915,47.658985],"type":"Point"}
}