{
  "type": "Feature",
  "properties": {
    "iso:country":"US",
    "sg:address":"1125 S 3rd St",
    "sg:city":"Mt Vernon",
    "sg:classifiers":[
        {
            "category":"Personal",
            "type":"Services"
        }
    ],
    "sg:phone":"+1 360 336 9574",
    "sg:postcode":"98273",
    "sg:province":"WA",
    "sg:tags":[
        "therapist",
        "massage"
    ],
    "wof:name":"Stephanie Tate",
    "wof:placetype":"venue"
},
  "geometry": {"coordinates":[-122.336737,48.414575],"type":"Point"}
}