{
  "type": "Feature",
  "properties": {
    "addr:full":"1213 NE 192nd Ave Vancouver WA 98684",
    "addr:housenumber":"1213",
    "addr:postcode":"98684",
    "addr:street":"Ne 192Nd Ave",
    "iso:country":"US",
    "sg:address":"1213 NE 192nd Ave",
    "sg:city":"Vancouver",
    "sg:classifiers":[
        {
            "category":"Building & Trades",
            "subcategory":"Landscaping Services",
            "type":"Services"
        }
    ],
    "sg:phone":"+1 360 253 8960",
    "sg:postcode":"98684",
    "sg:province":"WA",
    "wof:name":"A Better Cut",
    "wof:placetype":"venue"
},
  "geometry": {"coordinates":[-122.475846,45.63087],"type":"Point"}
}